{
  "type": "Feature",
  "properties": {
    "iso:country":"US",
    "sg:address":"5608 Wildflower Ct",
    "sg:city":"Charlotte",
    "sg:classifiers":[
        {
            "category":"Professional",
            "subcategory":"Art Services",
            "type":"Services"
        },
        {
            "category":"Professional",
            "subcategory":"Advertising",
            "type":"Services"
        }
    ],
    "sg:phone":"+1 704 573 1555",
    "sg:postcode":"28227",
    "sg:province":"NC",
    "sg:tags":[
        "graphic",
        "agency",
        "designer"
    ],
    "wof:name":"Miller Design",
    "wof:placetype":"venue"
},
  "geometry": {"coordinates":[-80.69340800000001,35.168959],"type":"Point"}
}