{
  "type": "Feature",
  "properties": {
    "addr:full":"981 Old Graham Rd Pittsboro NC 27312",
    "addr:housenumber":"981",
    "addr:postcode":"27312",
    "addr:street":"Old Graham Rd",
    "iso:country":"US",
    "sg:address":"981 Old Graham Rd",
    "sg:city":"Pittsboro",
    "sg:classifiers":[
        {
            "category":"Wholesale",
            "subcategory":"Construction Materials",
            "type":"Manufacturing & Wholesale Goods"
        }
    ],
    "sg:phone":"+1 919 542 3686",
    "sg:postcode":"27312",
    "sg:province":"NC",
    "sg:tags":[
        "timberland",
        "company",
        "timber"
    ],
    "wof:name":"Chatham Land & Timber Mgmt",
    "wof:placetype":"venue"
},
  "geometry": {"coordinates":[-79.186891,35.734163],"type":"Point"}
}