{
  "type": "Feature",
  "properties": {
    "iso:country":"US",
    "sg:address":"301 East Blvd",
    "sg:city":"Charlotte",
    "sg:classifiers":[
        {
            "category":"Professional",
            "subcategory":"Accounting & Tax Preparation",
            "type":"Services"
        }
    ],
    "sg:phone":"+1   ",
    "sg:postcode":"28203",
    "sg:province":"NC",
    "wof:name":"TDS Assoc LLC",
    "wof:placetype":"venue"
},
  "geometry": {"coordinates":[-80.85540399999999,35.210015],"type":"Point"}
}