{
  "type": "Feature",
  "properties": {
    "iso:country":"US",
    "sg:address":"422 Chesham Dr",
    "sg:city":"Kernersville",
    "sg:classifiers":[
        {
            "category":"Recreation",
            "type":"Entertainment"
        }
    ],
    "sg:phone":"+1   ",
    "sg:postcode":"27284",
    "sg:province":"NC",
    "wof:name":"Dreams In Motion Inc",
    "wof:placetype":"venue"
},
  "geometry": {"coordinates":[-80.119675,36.121395],"type":"Point"}
}