{
  "type": "Feature",
  "properties": {
    "iso:country":"US",
    "sg:address":"8416 Old Dowd Rd",
    "sg:city":"Charlotte",
    "sg:classifiers":[
        {
            "category":"Retail",
            "subcategory":"Auto Repair",
            "type":"Services"
        }
    ],
    "sg:phone":"+1   ",
    "sg:postcode":"28214",
    "sg:province":"NC",
    "sg:tags":[
        "general"
    ],
    "wof:name":"Allen Massey Garage",
    "wof:placetype":"venue"
},
  "geometry": {"coordinates":[-80.974054,35.228568],"type":"Point"}
}