{
  "type": "Feature",
  "properties": {
    "addr:full":"7709 Pineville-Matthews Rd Charlotte NC 28226",
    "addr:housenumber":"7709",
    "addr:postcode":"28226",
    "addr:street":"Pineville-Matthews Rd",
    "iso:country":"US",
    "sg:address":"7709 Pineville-Matthews Rd",
    "sg:city":"Charlotte",
    "sg:classifiers":[
        {
            "category":"Personal",
            "subcategory":"Beauty Salon",
            "type":"Services"
        }
    ],
    "sg:phone":"+1 704 369 7007",
    "sg:postcode":"28226",
    "sg:province":"NC",
    "wof:name":"Haircolorexperts-Carmel Cmmns",
    "wof:placetype":"venue"
},
  "geometry": {"coordinates":[-80.850683,35.087609],"type":"Point"}
}