{
  "type": "Feature",
  "properties": {
    "addr:full":"605 Creekside Dr Raleigh NC 27609",
    "addr:housenumber":"605",
    "addr:postcode":"27609",
    "addr:street":"Creekside Dr",
    "iso:country":"US",
    "sg:address":"605 Creekside Dr",
    "sg:city":"Raleigh",
    "sg:classifiers":[
        {
            "category":"Home & Garden",
            "subcategory":"Furniture",
            "type":"Retail Goods"
        }
    ],
    "sg:phone":"+1 919 834 6500",
    "sg:postcode":"27609",
    "sg:province":"NC",
    "wof:name":"Old Camp",
    "wof:placetype":"venue"
},
  "geometry": {"coordinates":[-78.622529,35.816259],"type":"Point"}
}