{
  "type": "Feature",
  "properties": {
    "iso:country":"US",
    "sg:address":"230 Cherry St S",
    "sg:city":"Winston Salem",
    "sg:classifiers":[
        {
            "category":"Social Services",
            "type":"Services"
        }
    ],
    "sg:phone":"+1 336 725 1750",
    "sg:postcode":"27101",
    "sg:province":"NC",
    "sg:tags":[
        "youth",
        "organization",
        "center"
    ],
    "wof:name":"Young Life-Winston Salem",
    "wof:placetype":"venue"
},
  "geometry": {"coordinates":[-80.245845,36.091094],"type":"Point"}
}