{
  "type": "Feature",
  "properties": {
    "addr:full":"110 Tot Dellinger Rd Cherryville NC 28021",
    "addr:housenumber":"110",
    "addr:postcode":"28021",
    "addr:street":"Tot Dellinger Rd",
    "iso:country":"US",
    "sg:address":"110 Tot Dellinger Rd",
    "sg:city":"Cherryville",
    "sg:classifiers":[
        {
            "category":"Home & Garden",
            "subcategory":"Furniture",
            "type":"Retail Goods"
        }
    ],
    "sg:phone":"+1 704 445 0289",
    "sg:postcode":"28021",
    "sg:province":"NC",
    "sg:tags":[
        "cabinet"
    ],
    "wof:name":"EGS Cabintry & Millwork",
    "wof:placetype":"venue"
},
  "geometry": {"coordinates":[-81.366941,35.391962],"type":"Point"}
}