{
  "type": "Feature",
  "properties": {
    "addr:full":"364 Windermere Dr Fayetteville NC 28314",
    "addr:housenumber":"364",
    "addr:postcode":"28314",
    "addr:street":"Windermere Dr",
    "iso:country":"US",
    "sg:address":"364 Windermere Dr",
    "sg:city":"Fayetteville",
    "sg:classifiers":[
        {
            "category":"Travel",
            "subcategory":"Campground",
            "type":"Entertainment"
        },
        {
            "category":"Retail",
            "subcategory":"Auto Repair",
            "type":"Services"
        }
    ],
    "sg:phone":"+1 910 867 1226",
    "sg:postcode":"28314",
    "sg:province":"NC",
    "sg:tags":[
        "automotive"
    ],
    "wof:name":"Art's Rv Sites",
    "wof:placetype":"venue"
},
  "geometry": {"coordinates":[-78.97443699999999,35.064119],"type":"Point"}
}