{
  "type": "Feature",
  "properties": {
    "iso:country":"US",
    "sg:address":"4 S Ridge Dr",
    "sg:city":"Pisgah Forest",
    "sg:classifiers":[
        {
            "category":"Restaurant",
            "type":"Food & Drink"
        }
    ],
    "sg:phone":"+1 828 884 7476",
    "sg:postcode":"28777",
    "sg:province":"NC",
    "wof:name":"Win's Smokehouse Svc LTD",
    "wof:placetype":"venue"
},
  "geometry": {"coordinates":[-82.05474,35.892474],"type":"Point"}
}