{
  "type": "Feature",
  "properties": {
    "iso:country":"US",
    "sg:address":"109 N Gill St",
    "sg:city":"Laurinburg",
    "sg:classifiers":[
        {
            "category":"Government",
            "subcategory":"Post Office",
            "type":"Public Place"
        }
    ],
    "sg:phone":"+1 910 276 0911",
    "sg:postcode":"28352",
    "sg:province":"NC",
    "sg:tags":[
        "postal",
        "us"
    ],
    "wof:name":"Laurinburg Main Office",
    "wof:placetype":"venue"
},
  "geometry": {"coordinates":[-79.462739,34.778115],"type":"Point"}
}