{
  "type": "Feature",
  "properties": {
    "addr:full":"601 N Polk St Pineville NC 28134",
    "addr:housenumber":"601",
    "addr:postcode":"28134",
    "addr:street":"N Polk St",
    "iso:country":"US",
    "sg:address":"601 N Polk St",
    "sg:city":"Pineville",
    "sg:classifiers":[
        {
            "category":"Professional",
            "subcategory":"Business Services",
            "type":"Services"
        }
    ],
    "sg:phone":"+1 704 889 3325",
    "sg:postcode":"28134",
    "sg:province":"NC",
    "sg:tags":[
        "merchandise",
        "liquidator"
    ],
    "wof:name":"Purple Picket Furn Sample Mall",
    "wof:placetype":"venue"
},
  "geometry": {"coordinates":[-80.88515,35.091674],"type":"Point"}
}