{
  "type": "Feature",
  "properties": {
    "iso:country":"US",
    "sg:address":"181 W Iredell Cir",
    "sg:city":"Statesville",
    "sg:classifiers":[
        {
            "category":"Professional",
            "subcategory":"Art Services",
            "type":"Services"
        }
    ],
    "sg:phone":"+1   ",
    "sg:postcode":"28625",
    "sg:province":"NC",
    "sg:tags":[
        "commercial",
        "design"
    ],
    "wof:name":"Carolina Screen Prtg Design",
    "wof:placetype":"venue"
},
  "geometry": {"coordinates":[-81.028257,35.800557],"type":"Point"}
}