{
  "type": "Feature",
  "properties": {
    "addr:full":"4425 Randolph Rd Charlotte NC 28211",
    "addr:housenumber":"4425",
    "addr:postcode":"28211",
    "addr:street":"Randolph Rd",
    "iso:country":"US",
    "sg:address":"4425 Randolph Rd",
    "sg:city":"Charlotte",
    "sg:classifiers":[
        {
            "category":"Professional",
            "type":"Services"
        }
    ],
    "sg:phone":"+1 704 364 6553",
    "sg:postcode":"28211",
    "sg:province":"NC",
    "sg:tags":[
        "establishment"
    ],
    "wof:name":"Silver Family LLC",
    "wof:placetype":"venue"
},
  "geometry": {"coordinates":[-80.7987,35.176589],"type":"Point"}
}