{
  "type": "Feature",
  "properties": {
    "iso:country":"US",
    "sg:address":"7212 Cornwallis Rd",
    "sg:city":"Garner",
    "sg:classifiers":[
        {
            "category":"Professional",
            "subcategory":"Management & Consulting",
            "type":"Services"
        }
    ],
    "sg:phone":"+1   ",
    "sg:postcode":"27529",
    "sg:province":"NC",
    "wof:name":"American Grounds Management",
    "wof:placetype":"venue"
},
  "geometry": {"coordinates":[-78.53778,35.639824],"type":"Point"}
}