{
  "type": "Feature",
  "properties": {
    "addr:full":"51 Smith Rd Leasburg NC 27291",
    "addr:housenumber":"51",
    "addr:postcode":"27291",
    "addr:street":"Smith Rd",
    "iso:country":"US",
    "sg:address":"51 Smith Rd",
    "sg:city":"Leasburg",
    "sg:classifiers":[
        {
            "category":"Freight",
            "type":"Transportation"
        }
    ],
    "sg:phone":"+1 336 694 6416",
    "sg:postcode":"27291",
    "sg:province":"NC",
    "sg:tags":[
        "operator",
        "local",
        "trucking"
    ],
    "wof:name":"McDuffie Trucking",
    "wof:placetype":"venue"
},
  "geometry": {"coordinates":[-79.23541299999999,36.344601],"type":"Point"}
}