{
  "type": "Feature",
  "properties": {
    "iso:country":"US",
    "sg:address":"1017 Hidden Hills Dr",
    "sg:city":"Wake Forest",
    "sg:classifiers":[
        {
            "category":"Building & Trades",
            "subcategory":"Construction",
            "type":"Services"
        }
    ],
    "sg:phone":"+1 919 528 9189",
    "sg:postcode":"27587",
    "sg:province":"NC",
    "sg:tags":[
        "builder",
        "operative"
    ],
    "wof:name":"New Light Custom Builders",
    "wof:placetype":"venue"
},
  "geometry": {"coordinates":[-78.637173,36.03923],"type":"Point"}
}