{
  "type": "Feature",
  "properties": {
    "iso:country":"US",
    "sg:address":"2711 Park Ave",
    "sg:city":"Wilmington",
    "sg:classifiers":[
        {
            "category":"Banks & Credit Unions",
            "subcategory":"Financial Services",
            "type":"Services"
        }
    ],
    "sg:phone":"+1 910 762 7898",
    "sg:postcode":"28403",
    "sg:province":"NC",
    "sg:tags":[
        "trust",
        "investment",
        "real estate"
    ],
    "wof:name":"J H W Williams LLC",
    "wof:placetype":"venue"
},
  "geometry": {"coordinates":[-77.909706,34.222293],"type":"Point"}
}