{
  "type": "Feature",
  "properties": {
    "iso:country":"US",
    "sg:address":"1201 Hawthorne Ln",
    "sg:city":"Charlotte",
    "sg:classifiers":[
        {
            "category":"Organizations",
            "subcategory":"Community Association",
            "type":"Services"
        }
    ],
    "sg:phone":"+1 704 376 3838",
    "sg:postcode":"28205",
    "sg:province":"NC",
    "sg:tags":[
        "fraternal"
    ],
    "wof:name":"Fraternal Order Of Police",
    "wof:placetype":"venue"
},
  "geometry": {"coordinates":[-80.813326,35.227259],"type":"Point"}
}