{
  "type": "Feature",
  "properties": {
    "addr:full":"19420 Jetton Rd Cornelius NC 28031",
    "addr:housenumber":"19420",
    "addr:postcode":"28031",
    "addr:street":"Jetton Rd",
    "iso:country":"US",
    "sg:address":"19420 Jetton Rd",
    "sg:city":"Cornelius",
    "sg:classifiers":[
        {
            "category":"Personal",
            "subcategory":"Beauty Salon",
            "type":"Services"
        }
    ],
    "sg:phone":"+1 704 895 5890",
    "sg:postcode":"28031",
    "sg:province":"NC",
    "wof:name":"Salon Blue",
    "wof:placetype":"venue"
},
  "geometry": {"coordinates":[-80.891823,35.476703],"type":"Point"}
}