{
  "type": "Feature",
  "properties": {
    "iso:country":"US",
    "sg:address":"162 N Cherry St",
    "sg:city":"Asheboro",
    "sg:classifiers":[
        {
            "category":"Manufacturing",
            "subcategory":"Rubber & Plastics",
            "type":"Manufacturing & Wholesale Goods"
        }
    ],
    "sg:phone":"+1 336 626 0975",
    "sg:postcode":"27203",
    "sg:province":"NC",
    "sg:tags":[
        "product"
    ],
    "sg:website":"www.dartcontainer.com",
    "wof:name":"Dart Container",
    "wof:placetype":"venue"
},
  "geometry": {"coordinates":[-79.8248,35.708318],"type":"Point"}
}