{
  "type": "Feature",
  "properties": {
    "iso:country":"US",
    "sg:address":"16716 Spinnaker Ln",
    "sg:city":"Cornelius",
    "sg:classifiers":[
        {
            "category":"Manufacturing",
            "subcategory":"Paper Products",
            "type":"Manufacturing & Wholesale Goods"
        }
    ],
    "sg:phone":"+1 704 894 0647",
    "sg:postcode":"28031",
    "sg:province":"NC",
    "sg:tags":[
        "bag"
    ],
    "wof:name":"Poly Plastics Product",
    "wof:placetype":"venue"
},
  "geometry": {"coordinates":[-80.894812,35.445573],"type":"Point"}
}