{
  "type": "Feature",
  "properties": {
    "addr:full":"5922 Weddington Monroe Rd Matthews NC 28104",
    "addr:housenumber":"5922",
    "addr:postcode":"28104",
    "addr:street":"Weddington Monroe Rd",
    "iso:country":"US",
    "sg:address":"5922 Weddington Monroe Rd",
    "sg:city":"Matthews",
    "sg:classifiers":[
        {
            "category":"Restaurant",
            "type":"Food & Drink"
        }
    ],
    "sg:menulink":"http://www.allmenus.com/nc/sandy-ridge/272902-la-strada-pizza--pasta/menu/",
    "sg:phone":"+1 704 843 2420",
    "sg:postcode":"28104",
    "sg:province":"NC",
    "sg:tags":[
        "salad",
        "burger",
        "american",
        "pasta",
        "pizza",
        "wing",
        "italian"
    ],
    "wof:name":"La Strada Pizza & Pasta",
    "wof:placetype":"venue"
},
  "geometry": {"coordinates":[-80.69816899999999,35.00119],"type":"Point"}
}