{
  "type": "Feature",
  "properties": {
    "iso:country":"US",
    "sg:address":"1205 Huntsdale Rd",
    "sg:city":"Reidsville",
    "sg:classifiers":[
        {
            "category":"Professional",
            "subcategory":"Business Services",
            "type":"Services"
        }
    ],
    "sg:phone":"+1   ",
    "sg:postcode":"27320",
    "sg:province":"NC",
    "wof:name":"Zht Enterprises LLC",
    "wof:placetype":"venue"
},
  "geometry": {"coordinates":[-79.67069100000001,36.34303],"type":"Point"}
}