{
  "type": "Feature",
  "properties": {
    "iso:country":"US",
    "sg:address":"2456 Milburnie Rd",
    "sg:city":"Raleigh",
    "sg:classifiers":[
        {
            "category":"Professional",
            "subcategory":"Business Services",
            "type":"Services"
        },
        {
            "category":"Personal",
            "type":"Services"
        }
    ],
    "sg:phone":"+1 919 369 6953",
    "sg:postcode":"27610",
    "sg:province":"NC",
    "sg:tags":[
        "credit",
        "debt",
        "counseling"
    ],
    "wof:name":"Debt Freedom Group LLC",
    "wof:placetype":"venue"
},
  "geometry": {"coordinates":[-78.600189,35.788429],"type":"Point"}
}