{
  "type": "Feature",
  "properties": {
    "addr:full":"840 2nd St NE Hickory NC 28601",
    "addr:housenumber":"840",
    "addr:postcode":"28601",
    "addr:street":"2Nd St Ne",
    "iso:country":"US",
    "sg:address":"840 2nd St NE",
    "sg:city":"Hickory",
    "sg:classifiers":[
        {
            "category":"Real Estate",
            "subcategory":"Real Estate Agent",
            "type":"Services"
        }
    ],
    "sg:phone":"+1 800 968 8985",
    "sg:postcode":"28601",
    "sg:province":"NC",
    "wof:name":"Century 21",
    "wof:placetype":"venue"
},
  "geometry": {"coordinates":[-81.335154,35.744612],"type":"Point"}
}