{
  "type": "Feature",
  "properties": {
    "iso:country":"US",
    "sg:address":"720 Hunt Rd",
    "sg:city":"Lexington",
    "sg:classifiers":[
        {
            "category":"Retail",
            "subcategory":"Auto Repair",
            "type":"Services"
        }
    ],
    "sg:phone":"+1 336 242 1493",
    "sg:postcode":"27292",
    "sg:province":"NC",
    "sg:tags":[
        "repairing",
        "automobile"
    ],
    "wof:name":"Merican Auto Repair & Muffler",
    "wof:placetype":"venue"
},
  "geometry": {"coordinates":[-80.256865,35.718777],"type":"Point"}
}