{
  "type": "Feature",
  "properties": {
    "iso:country":"US",
    "sg:address":"3307 Cross Winds Rd",
    "sg:city":"Charlotte",
    "sg:classifiers":[
        {
            "category":"Professional",
            "subcategory":"Business Services",
            "type":"Services"
        }
    ],
    "sg:phone":"+1 704 532 0341",
    "sg:postcode":"28227",
    "sg:province":"NC",
    "sg:tags":[
        "consultant",
        "coach"
    ],
    "wof:name":"Blake Speech Therapy",
    "wof:placetype":"venue"
},
  "geometry": {"coordinates":[-80.720485,35.177574],"type":"Point"}
}