{
  "type": "Feature",
  "properties": {
    "iso:country":"US",
    "sg:address":"4505 Emperor Blvd Suite 320",
    "sg:city":"Durham",
    "sg:classifiers":[
        {
            "category":"Professional",
            "subcategory":"Computer Services",
            "type":"Services"
        }
    ],
    "sg:phone":"+1 919 765 5000",
    "sg:postcode":"27703",
    "sg:province":"NC",
    "sg:tags":[
        "saas",
        "software-as-a-service",
        "small-business",
        "cloud-computing"
    ],
    "sg:website":"http://www.smartonline.com",
    "wof:name":"Smart Online",
    "wof:placetype":"venue"
},
  "geometry": {"coordinates":[-78.841545,35.873799],"type":"Point"}
}