{
  "type": "Feature",
  "properties": {
    "iso:country":"US",
    "sg:address":"3022 Tyson St",
    "sg:city":"Stokes",
    "sg:classifiers":[
        {
            "category":"Insurance",
            "subcategory":"Insurance Agent",
            "type":"Services"
        }
    ],
    "sg:phone":"+1 252 752 6447",
    "sg:postcode":"27884",
    "sg:province":"NC",
    "wof:name":"Tyson-Congleton Inc",
    "wof:placetype":"venue"
},
  "geometry": {"coordinates":[-77.26473799999999,35.71654],"type":"Point"}
}