{
  "type": "Feature",
  "properties": {
    "addr:full":"40 Cisco Rd Asheville NC 28805",
    "addr:housenumber":"40",
    "addr:postcode":"28805",
    "addr:street":"Cisco Rd",
    "iso:country":"US",
    "sg:address":"40 Cisco Rd",
    "sg:city":"Asheville",
    "sg:classifiers":[
        {
            "category":"Building & Trades",
            "subcategory":"Construction",
            "type":"Services"
        }
    ],
    "sg:phone":"+1 828 298 8939",
    "sg:postcode":"28805",
    "sg:province":"NC",
    "sg:tags":[
        "excavation",
        "contractor"
    ],
    "wof:name":"Eds Skd-Steer Lder Bckhoe Svc",
    "wof:placetype":"venue"
},
  "geometry": {"coordinates":[-82.511713,35.596195],"type":"Point"}
}