{
  "type": "Feature",
  "properties": {
    "addr:full":"118 Bonkin Lake Rd Mocksville NC 27028",
    "addr:housenumber":"118",
    "addr:postcode":"27028",
    "addr:street":"Bonkin Lake Rd",
    "iso:country":"US",
    "sg:address":"118 Bonkin Lake Rd",
    "sg:city":"Mocksville",
    "sg:classifiers":[
        {
            "category":"Personal",
            "subcategory":"Beauty Salon",
            "type":"Services"
        }
    ],
    "sg:phone":"+1   ",
    "sg:postcode":"27028",
    "sg:province":"NC",
    "sg:tags":[
        "shop"
    ],
    "wof:name":"Country Charm Beauty Shop",
    "wof:placetype":"venue"
},
  "geometry": {"coordinates":[-80.58946299999999,36.033806],"type":"Point"}
}