{
  "type": "Feature",
  "properties": {
    "addr:full":"1919 S 16th St Wilmington NC 28401",
    "addr:housenumber":"1919",
    "addr:postcode":"28401",
    "addr:street":"S 16Th St",
    "iso:country":"US",
    "sg:address":"1919 S 16th St",
    "sg:city":"Wilmington",
    "sg:classifiers":[
        {
            "category":"Health Services",
            "subcategory":"Podiatrist",
            "type":"Services"
        }
    ],
    "sg:phone":"+1 910 395 1202",
    "sg:postcode":"28401",
    "sg:province":"NC",
    "wof:name":"Young Christopher C DPM",
    "wof:placetype":"venue"
},
  "geometry": {"coordinates":[-77.92603699999999,34.213265],"type":"Point"}
}