{
  "type": "Feature",
  "properties": {
    "addr:full":"19 Mears Ave Canton NC 28716",
    "addr:housenumber":"19",
    "addr:postcode":"28716",
    "addr:street":"Mears Ave",
    "iso:country":"US",
    "sg:address":"19 Mears Ave",
    "sg:city":"Canton",
    "sg:classifiers":[
        {
            "category":"Shopping",
            "subcategory":"Musical Instruments",
            "type":"Retail Goods"
        }
    ],
    "sg:phone":"+1 828 648 5830",
    "sg:postcode":"28716",
    "sg:province":"NC",
    "wof:name":"Larry Watson Guitar & Banjo In",
    "wof:placetype":"venue"
},
  "geometry": {"coordinates":[-82.839007,35.531169],"type":"Point"}
}