{
  "type": "Feature",
  "properties": {
    "addr:full":"2720 Discovery Dr Raleigh NC 27616",
    "addr:housenumber":"2720",
    "addr:postcode":"27616",
    "addr:street":"Discovery Dr",
    "iso:country":"US",
    "sg:address":"2720 Discovery Dr",
    "sg:city":"Raleigh",
    "sg:classifiers":[
        {
            "category":"Wholesale",
            "subcategory":"Medical Equipment & Supplies",
            "type":"Manufacturing & Wholesale Goods"
        }
    ],
    "sg:phone":"+1 919 790 3839",
    "sg:postcode":"27616",
    "sg:province":"NC",
    "sg:tags":[
        "dental"
    ],
    "wof:name":"Thompson Dental Co",
    "wof:placetype":"venue"
},
  "geometry": {"coordinates":[-78.59464,35.862108],"type":"Point"}
}