{
  "type": "Feature",
  "properties": {
    "addr:full":"3722 Market St Wilmington NC 28403",
    "addr:housenumber":"3722",
    "addr:postcode":"28403",
    "addr:street":"Market St",
    "iso:country":"US",
    "sg:address":"3722 Market St",
    "sg:city":"Wilmington",
    "sg:classifiers":[
        {
            "category":"Home & Garden",
            "subcategory":"Furniture",
            "type":"Retail Goods"
        }
    ],
    "sg:phone":"+1 910 763 1009",
    "sg:postcode":"28403",
    "sg:province":"NC",
    "wof:name":"Furniture Outlet Of Wilmington",
    "wof:placetype":"venue"
},
  "geometry": {"coordinates":[-77.90069099999999,34.240783],"type":"Point"}
}