{
  "type": "Feature",
  "properties": {
    "addr:full":"216 Crestview Dr Raleigh NC 27609",
    "addr:housenumber":"216",
    "addr:postcode":"27609",
    "addr:street":"Crestview Dr",
    "iso:country":"US",
    "sg:address":"216 Crestview Dr",
    "sg:city":"Raleigh",
    "sg:classifiers":[
        {
            "category":"Real Estate",
            "subcategory":"Architect",
            "type":"Services"
        }
    ],
    "sg:phone":"+1   ",
    "sg:postcode":"27609",
    "sg:province":"NC",
    "sg:tags":[
        "architectural"
    ],
    "wof:name":"Built Environment Ken Smith",
    "wof:placetype":"venue"
},
  "geometry": {"coordinates":[-78.63673199999999,35.852256],"type":"Point"}
}