{
  "type": "Feature",
  "properties": {
    "addr:full":"1806 Goldsboro St SW Wilson NC 27893",
    "addr:housenumber":"1806",
    "addr:postcode":"27893",
    "addr:street":"Goldsboro St Sw",
    "iso:country":"US",
    "sg:address":"1806 Goldsboro St SW",
    "sg:city":"Wilson",
    "sg:classifiers":[
        {
            "category":"Government",
            "subcategory":"Office",
            "type":"Public Place"
        }
    ],
    "sg:phone":"+1 252 237 2711",
    "sg:postcode":"27893",
    "sg:province":"NC",
    "sg:tags":[
        "federal"
    ],
    "wof:name":"Natural Resources Conservation",
    "wof:placetype":"venue"
},
  "geometry": {"coordinates":[-77.926357,35.707574],"type":"Point"}
}