{
  "type": "Feature",
  "properties": {
    "iso:country":"US",
    "sg:address":"1872 N Clodfelter Rd",
    "sg:city":"High Point",
    "sg:classifiers":[
        {
            "category":"Shopping",
            "subcategory":"Clothing, Apparel, & Fashions",
            "type":"Retail Goods"
        }
    ],
    "sg:phone":"+1 336 869 3730",
    "sg:postcode":"27265",
    "sg:province":"NC",
    "sg:tags":[
        "salvage",
        "surplus",
        "merchandise"
    ],
    "wof:name":"J & S Pyne Enterprises Inc",
    "wof:placetype":"venue"
},
  "geometry": {"coordinates":[-80.109042,35.992],"type":"Point"}
}