{
  "type": "Feature",
  "properties": {
    "iso:country":"US",
    "sg:address":"1001 Waterview Pl",
    "sg:city":"Carolina Beach",
    "sg:classifiers":[
        {
            "category":"Building & Trades",
            "subcategory":"Construction",
            "type":"Services"
        }
    ],
    "sg:phone":"+1 910 458 6981",
    "sg:postcode":"28428",
    "sg:province":"NC",
    "sg:tags":[
        "house"
    ],
    "wof:name":"Wills Construction",
    "wof:placetype":"venue"
},
  "geometry": {"coordinates":[-77.89258599999999,34.043048],"type":"Point"}
}