{
  "type": "Feature",
  "properties": {
    "iso:country":"US",
    "sg:address":"11 Gingerwood Ln",
    "sg:city":"Durham",
    "sg:classifiers":[
        {
            "category":"Restaurant",
            "type":"Food & Drink"
        }
    ],
    "sg:phone":"+1 919 673 9900",
    "sg:postcode":"27713",
    "sg:province":"NC",
    "sg:tags":[
        "eating"
    ],
    "wof:name":"Gamefrog",
    "wof:placetype":"venue"
},
  "geometry": {"coordinates":[-78.90247100000001,35.87946],"type":"Point"}
}