{
  "type": "Feature",
  "properties": {
    "addr:full":"100 Colburn Pt Chapel Hill NC 27516",
    "addr:housenumber":"100",
    "addr:postcode":"27516",
    "addr:street":"Colburn Pt",
    "iso:country":"US",
    "sg:address":"100 Colburn Pt",
    "sg:city":"Chapel Hill",
    "sg:classifiers":[
        {
            "category":"Professional",
            "subcategory":"Business Services",
            "type":"Services"
        }
    ],
    "sg:phone":"+1   ",
    "sg:postcode":"27516",
    "sg:province":"NC",
    "wof:name":"Mark Rhodes Consulting Group",
    "wof:placetype":"venue"
},
  "geometry": {"coordinates":[-79.06861499999999,35.894217],"type":"Point"}
}