{
  "type": "Feature",
  "properties": {
    "addr:full":"4361 Federal Dr Greensboro NC 27410",
    "addr:housenumber":"4361",
    "addr:postcode":"27410",
    "addr:street":"Federal Dr",
    "iso:country":"US",
    "sg:address":"4361 Federal Dr",
    "sg:city":"Greensboro",
    "sg:classifiers":[
        {
            "category":"Manufacturing",
            "subcategory":"Tools & Machinery",
            "type":"Manufacturing & Wholesale Goods"
        }
    ],
    "sg:phone":"+1 336 297 1913",
    "sg:postcode":"27410",
    "sg:province":"NC",
    "sg:tags":[
        "x",
        "mfg"
    ],
    "wof:name":"Blue Ridge X Ray Company",
    "wof:placetype":"venue"
},
  "geometry": {"coordinates":[-79.949252,36.063691],"type":"Point"}
}