{
  "type": "Feature",
  "properties": {
    "addr:full":"2604 Phoenix Dr Greensboro NC 27406",
    "addr:housenumber":"2604",
    "addr:postcode":"27406",
    "addr:street":"Phoenix Dr",
    "iso:country":"US",
    "sg:address":"2604 Phoenix Dr",
    "sg:city":"Greensboro",
    "sg:classifiers":[
        {
            "category":"Wholesale",
            "subcategory":"Apparel",
            "type":"Manufacturing & Wholesale Goods"
        }
    ],
    "sg:phone":"+1 336 854 9909",
    "sg:postcode":"27406",
    "sg:province":"NC",
    "sg:tags":[
        "clothing"
    ],
    "wof:name":"Gold Medal Hoisery",
    "wof:placetype":"venue"
},
  "geometry": {"coordinates":[-79.833929,36.01089],"type":"Point"}
}