{
  "type": "Feature",
  "properties": {
    "addr:full":"805 Sunnybrook Rd Raleigh NC 27610",
    "addr:housenumber":"805",
    "addr:postcode":"27610",
    "addr:street":"Sunnybrook Rd",
    "iso:country":"US",
    "sg:address":"805 Sunnybrook Rd",
    "sg:city":"Raleigh",
    "sg:classifiers":[
        {
            "category":"Building & Trades",
            "subcategory":"Plumbing",
            "type":"Services"
        }
    ],
    "sg:phone":"+1 919 231 1388",
    "sg:postcode":"27610",
    "sg:province":"NC",
    "sg:tags":[
        "contractor"
    ],
    "wof:name":"Lane Plumbing",
    "wof:placetype":"venue"
},
  "geometry": {"coordinates":[-78.582233,35.765562],"type":"Point"}
}