{
  "type": "Feature",
  "properties": {
    "addr:full":"1412 W Haven Blvd Rocky Mount NC 27803",
    "addr:housenumber":"1412",
    "addr:postcode":"27803",
    "addr:street":"W Haven Blvd",
    "iso:country":"US",
    "sg:address":"1412 W Haven Blvd",
    "sg:city":"Rocky Mount",
    "sg:classifiers":[
        {
            "category":"Shopping",
            "type":"Retail Goods"
        }
    ],
    "sg:phone":"+1 252 446 6926",
    "sg:postcode":"27803",
    "sg:province":"NC",
    "sg:tags":[
        "cosmetic",
        "perfume"
    ],
    "wof:name":"Mary Kay Cosmetics",
    "wof:placetype":"venue"
},
  "geometry": {"coordinates":[-77.817712,35.944446],"type":"Point"}
}