{
  "type": "Feature",
  "properties": {
    "iso:country":"US",
    "sg:address":"702 E Franklin Blvd",
    "sg:city":"Gastonia",
    "sg:classifiers":[
        {
            "category":"Personal",
            "type":"Services"
        }
    ],
    "sg:phone":"+1   ",
    "sg:postcode":"28054",
    "sg:province":"NC",
    "wof:name":"Skin Art By Randy",
    "wof:placetype":"venue"
},
  "geometry": {"coordinates":[-81.170239,35.262418],"type":"Point"}
}