{
  "type": "Feature",
  "properties": {
    "iso:country":"US",
    "sg:address":"1037 Mountain Ct",
    "sg:city":"East Bend",
    "sg:classifiers":[
        {
            "category":"Shopping",
            "subcategory":"Clothing, Apparel, & Fashions",
            "type":"Retail Goods"
        }
    ],
    "sg:phone":"+1 336 699 2957",
    "sg:postcode":"27018",
    "sg:province":"NC",
    "sg:tags":[
        "uniform"
    ],
    "wof:name":"Bills Uniforms",
    "wof:placetype":"venue"
},
  "geometry": {"coordinates":[-80.465936,36.211725],"type":"Point"}
}