{
  "type": "Feature",
  "properties": {
    "iso:country":"US",
    "sg:address":"1009 Clarence Dr",
    "sg:city":"Chapel Hill",
    "sg:classifiers":[
        {
            "category":"Building & Trades",
            "subcategory":"Construction",
            "type":"Services"
        }
    ],
    "sg:phone":"+1 919 967 3327",
    "sg:postcode":"27516",
    "sg:province":"NC",
    "sg:tags":[
        "hanging",
        "contractor"
    ],
    "wof:name":"Morgan Paint",
    "wof:placetype":"venue"
},
  "geometry": {"coordinates":[-79.084915,35.873784],"type":"Point"}
}