{
  "type": "Feature",
  "properties": {
    "addr:full":"2889 Gray Fox Rd Monroe NC 28110",
    "addr:housenumber":"2889",
    "addr:postcode":"28110",
    "addr:street":"Gray Fox Rd",
    "iso:country":"US",
    "sg:address":"2889 Gray Fox Rd",
    "sg:city":"Monroe",
    "sg:classifiers":[
        {
            "category":"Building & Trades",
            "subcategory":"Construction",
            "type":"Services"
        }
    ],
    "sg:phone":"+1 704 238 1659",
    "sg:postcode":"28110",
    "sg:province":"NC",
    "sg:tags":[
        "contractor"
    ],
    "wof:name":"Silestone",
    "wof:placetype":"venue"
},
  "geometry": {"coordinates":[-80.623508,35.057033],"type":"Point"}
}