{
  "type": "Feature",
  "properties": {
    "addr:full":"377 Faith Dr SW Concord NC 28027",
    "addr:housenumber":"377",
    "addr:postcode":"28027",
    "addr:street":"Faith Dr Sw",
    "iso:country":"US",
    "sg:address":"377 Faith Dr SW",
    "sg:city":"Concord",
    "sg:classifiers":[
        {
            "category":"Building & Trades",
            "subcategory":"Construction",
            "type":"Services"
        }
    ],
    "sg:phone":"+1 704 782 3638",
    "sg:postcode":"28027",
    "sg:province":"NC",
    "sg:tags":[
        "home",
        "improvement"
    ],
    "wof:name":"Wallcoverings Unlimited",
    "wof:placetype":"venue"
},
  "geometry": {"coordinates":[-80.597343,35.381775],"type":"Point"}
}