{
  "type": "Feature",
  "properties": {
    "addr:full":"210 Turner St Beaufort NC 28516",
    "addr:housenumber":"210",
    "addr:postcode":"28516",
    "addr:street":"Turner St",
    "iso:country":"US",
    "sg:address":"210 Turner St",
    "sg:city":"Beaufort",
    "sg:classifiers":[
        {
            "category":"Education",
            "subcategory":"Library",
            "type":"Public Place"
        }
    ],
    "sg:phone":"+1 252 728 2050",
    "sg:postcode":"28516",
    "sg:province":"NC",
    "sg:website":"www.cpclib.org",
    "wof:name":"Carteret County Public Library",
    "wof:placetype":"venue"
},
  "geometry": {"coordinates":[-76.66387400000001,34.719434],"type":"Point"}
}