{
  "type": "Feature",
  "properties": {
    "iso:country":"US",
    "sg:address":"1819 Charlotte Dr",
    "sg:city":"Charlotte",
    "sg:classifiers":[
        {
            "category":"Education",
            "subcategory":"Special Training",
            "type":"Public Place"
        }
    ],
    "sg:phone":"+1 704 377 9299",
    "sg:postcode":"28203",
    "sg:province":"NC",
    "sg:tags":[
        "h",
        "real estate"
    ],
    "wof:name":"Stone Rentals",
    "wof:placetype":"venue"
},
  "geometry": {"coordinates":[-80.84583499999999,35.201697],"type":"Point"}
}