{
  "type": "Feature",
  "properties": {
    "addr:full":"1001 Worth St Mount Airy NC 27030",
    "addr:housenumber":"1001",
    "addr:postcode":"27030",
    "addr:street":"Worth St",
    "iso:country":"US",
    "sg:address":"1001 Worth St",
    "sg:city":"Mount Airy",
    "sg:classifiers":[
        {
            "category":"Insurance",
            "subcategory":"Insurance Agent",
            "type":"Services"
        }
    ],
    "sg:phone":"+1 336 789 5091",
    "sg:postcode":"27030",
    "sg:province":"NC",
    "wof:name":"Farm Bureau Insur Mt Airy Off",
    "wof:placetype":"venue"
},
  "geometry": {"coordinates":[-80.614696,36.489544],"type":"Point"}
}