{
  "type": "Feature",
  "properties": {
    "addr:full":"2029 S 17th St Wilmington NC 28401",
    "addr:housenumber":"2029",
    "addr:postcode":"28401",
    "addr:street":"S 17Th St",
    "iso:country":"US",
    "sg:address":"2029 S 17th St",
    "sg:city":"Wilmington",
    "sg:classifiers":[
        {
            "category":"Government",
            "subcategory":"Office",
            "type":"Public Place"
        }
    ],
    "sg:phone":"+1 910 343 6500",
    "sg:postcode":"28401",
    "sg:province":"NC",
    "sg:tags":[
        "county",
        "program",
        "health"
    ],
    "wof:name":"New Hanover County Health Dept",
    "wof:placetype":"venue"
},
  "geometry": {"coordinates":[-77.924481,34.207451],"type":"Point"}
}