{
  "type": "Feature",
  "properties": {
    "addr:full":"166 Nelson St Clyde NC 28721",
    "addr:housenumber":"166",
    "addr:postcode":"28721",
    "addr:street":"Nelson St",
    "iso:country":"US",
    "sg:address":"166 Nelson St",
    "sg:city":"Clyde",
    "sg:classifiers":[
        {
            "category":"Organizations",
            "subcategory":"Labor Organization",
            "type":"Services"
        }
    ],
    "sg:phone":"+1 828 627 2200",
    "sg:postcode":"28721",
    "sg:province":"NC",
    "wof:name":"Clyde Dental Laboratory",
    "wof:placetype":"venue"
},
  "geometry": {"coordinates":[-82.918668,35.52923],"type":"Point"}
}