{
  "type": "Feature",
  "properties": {
    "iso:country":"US",
    "sg:address":"5998 Reidsville Rd",
    "sg:city":"Belews Creek",
    "sg:classifiers":[
        {
            "category":"Professional",
            "subcategory":"Business Services",
            "type":"Services"
        }
    ],
    "sg:phone":"+1   ",
    "sg:postcode":"27009",
    "sg:province":"NC",
    "wof:name":"Coleman Enterprises",
    "wof:placetype":"venue"
},
  "geometry": {"coordinates":[-80.093149,36.194493],"type":"Point"}
}