{
  "type": "Feature",
  "properties": {
    "iso:country":"US",
    "sg:address":"1300 S Graham St",
    "sg:city":"Charlotte",
    "sg:classifiers":[
        {
            "category":"Manufacturing",
            "subcategory":"Printing",
            "type":"Manufacturing & Wholesale Goods"
        }
    ],
    "sg:phone":"+1 704 358 0459",
    "sg:postcode":"28203",
    "sg:province":"NC",
    "sg:tags":[
        "printer"
    ],
    "wof:name":"C Harrison Conroy Co",
    "wof:placetype":"venue"
},
  "geometry": {"coordinates":[-80.85915799999999,35.221353],"type":"Point"}
}