{
  "type": "Feature",
  "properties": {
    "addr:full":"2797 State Hwy 55 Apex NC 27502",
    "addr:housenumber":"2797",
    "addr:postcode":"27502",
    "addr:street":"State Hwy 55",
    "iso:country":"US",
    "sg:address":"2797 State Hwy 55",
    "sg:city":"Apex",
    "sg:classifiers":[
        {
            "category":"Shopping",
            "subcategory":"Pharmacy",
            "type":"Retail Goods"
        }
    ],
    "sg:phone":"+1 919 362 0632",
    "sg:postcode":"27502",
    "sg:province":"NC",
    "wof:name":"CVS Pharmacy",
    "wof:placetype":"venue"
},
  "geometry": {"coordinates":[-78.871251,35.785007],"type":"Point"}
}