{
  "type": "Feature",
  "properties": {
    "addr:full":"116 W Academy St Randleman NC 27317",
    "addr:housenumber":"116",
    "addr:postcode":"27317",
    "addr:street":"W Academy St",
    "iso:country":"US",
    "sg:address":"116 W Academy St",
    "sg:city":"Randleman",
    "sg:classifiers":[
        {
            "category":"Restaurant",
            "type":"Food & Drink"
        }
    ],
    "sg:phone":"+1 336 498 7755",
    "sg:postcode":"27317",
    "sg:province":"NC",
    "sg:tags":[
        "eating"
    ],
    "wof:name":"Randelman Restaurant",
    "wof:placetype":"venue"
},
  "geometry": {"coordinates":[-79.803209,35.817917],"type":"Point"}
}