{
  "type": "Feature",
  "properties": {
    "iso:country":"US",
    "sg:address":"248 Barkley Rd",
    "sg:city":"Statesville",
    "sg:classifiers":[
        {
            "category":"Freight",
            "type":"Transportation"
        }
    ],
    "sg:phone":"+1 704 872 9918",
    "sg:postcode":"28677",
    "sg:province":"NC",
    "sg:tags":[
        "trucking"
    ],
    "wof:name":"Parker Trucking Inc",
    "wof:placetype":"venue"
},
  "geometry": {"coordinates":[-80.843631,35.762655],"type":"Point"}
}