{
  "type": "Feature",
  "properties": {
    "iso:country":"US",
    "sg:address":"158 Glen Cannon Dr Exd",
    "sg:city":"Pisgah Forest",
    "sg:classifiers":[
        {
            "category":"Real Estate",
            "subcategory":"Real Estate Agent",
            "type":"Services"
        }
    ],
    "sg:phone":"+1 828 885 7202",
    "sg:postcode":"28768",
    "sg:province":"NC",
    "wof:name":"Eckert Realty",
    "wof:placetype":"venue"
},
  "geometry": {"coordinates":[-82.686797,35.234432],"type":"Point"}
}