{
  "type": "Feature",
  "properties": {
    "addr:full":"245 Highlands Rd Franklin NC 28734",
    "addr:housenumber":"245",
    "addr:postcode":"nc 28734",
    "addr:street":"Highlands Rd",
    "iso:country":"US",
    "sg:address":"245 Highlands Rd",
    "sg:city":"Franklin",
    "sg:classifiers":[
        {
            "category":"Personal",
            "subcategory":"Tanning Parlor",
            "type":"Services"
        },
        {
            "category":"Personal",
            "subcategory":"Beauty Salon",
            "type":"Services"
        },
        {
            "category":"Personal",
            "subcategory":"Nail Salon",
            "type":"Services"
        }
    ],
    "sg:phone":"+1 828 524 5008",
    "sg:postcode":"28734",
    "sg:province":"NC",
    "wof:name":"A Touch Of Class",
    "wof:placetype":"venue"
},
  "geometry": {"coordinates":[-83.357986,35.174961],"type":"Point"}
}