{
  "type": "Feature",
  "properties": {
    "addr:full":"3708 John Fleming Rd Stokes NC 27884",
    "addr:housenumber":"3708",
    "addr:postcode":"27884",
    "addr:street":"John Fleming Rd",
    "iso:country":"US",
    "sg:address":"3708 John Fleming Rd",
    "sg:city":"Stokes",
    "sg:classifiers":[
        {
            "category":"Farming",
            "subcategory":"Farm",
            "type":"Manufacturing & Wholesale Goods"
        }
    ],
    "sg:phone":"+1 252 752 3710",
    "sg:postcode":"27884",
    "sg:province":"NC",
    "wof:name":"Taylor Barnhill Farms",
    "wof:placetype":"venue"
},
  "geometry": {"coordinates":[-77.284041,35.735227],"type":"Point"}
}