{
  "type": "Feature",
  "properties": {
    "iso:country":"US",
    "sg:address":"53 Carolina Lakes Rd",
    "sg:city":"Sanford",
    "sg:classifiers":[
        {
            "category":"Sports & Exercise",
            "subcategory":"Golf",
            "type":"Entertainment"
        }
    ],
    "sg:phone":"+1 919 499 5421",
    "sg:postcode":"27332",
    "sg:province":"NC",
    "sg:tags":[
        "course"
    ],
    "sg:website":"www.carolinalakes.com",
    "wof:name":"Carolina Lakes Golf Course",
    "wof:placetype":"venue"
},
  "geometry": {"coordinates":[-79.05833699999999,35.287604],"type":"Point"}
}