{
  "type": "Feature",
  "properties": {
    "iso:country":"US",
    "sg:address":"1033 Burke St NW",
    "sg:city":"Winston Salem",
    "sg:classifiers":[
        {
            "category":"Home & Garden",
            "subcategory":"Furniture",
            "type":"Retail Goods"
        }
    ],
    "sg:phone":"+1 336 724 1754",
    "sg:postcode":"27101",
    "sg:province":"NC",
    "sg:tags":[
        "cabinet"
    ],
    "sg:website":"www.cabinetstudio.com",
    "wof:name":"Cabinet Studio",
    "wof:placetype":"venue"
},
  "geometry": {"coordinates":[-80.258138,36.094589],"type":"Point"}
}