{
  "type": "Feature",
  "properties": {
    "iso:country":"US",
    "sg:address":"3728 S Holden Rd",
    "sg:city":"Greensboro",
    "sg:classifiers":[
        {
            "category":"Food & Beverages",
            "subcategory":"Specialty",
            "type":"Retail Goods"
        }
    ],
    "sg:phone":"+1 336 632 4452",
    "sg:postcode":"27406",
    "sg:province":"NC",
    "wof:name":"GNC",
    "wof:placetype":"venue"
},
  "geometry": {"coordinates":[-79.84248599999999,36.014431],"type":"Point"}
}