{
  "type": "Feature",
  "properties": {
    "iso:country":"US",
    "sg:address":"5202 Carolina Beach Rd",
    "sg:city":"Wilmington",
    "sg:classifiers":[
        {
            "category":"Insurance",
            "subcategory":"Insurance Agent",
            "type":"Services"
        }
    ],
    "sg:phone":"+1 910 790 5501",
    "sg:postcode":"28412",
    "sg:province":"NC",
    "wof:name":"Hibiske Insurance Group",
    "wof:placetype":"venue"
},
  "geometry": {"coordinates":[-77.897015,34.143417],"type":"Point"}
}