{
  "type": "Feature",
  "properties": {
    "addr:full":"201 W Arrowood Rd Charlotte NC 28217",
    "addr:housenumber":"201",
    "addr:postcode":"28217",
    "addr:street":"W Arrowood Rd",
    "iso:country":"US",
    "sg:address":"201 W Arrowood Rd",
    "sg:city":"Charlotte",
    "sg:phone":"+1 704 529 1015",
    "sg:postcode":"28217",
    "sg:province":"NC",
    "sg:website":"http://www.foodlion.com/",
    "wof:name":"Food Lion",
    "wof:placetype":"venue"
},
  "geometry": {"coordinates":[-80.89496800000001,35.13495],"type":"Point"}
}