{
  "type": "Feature",
  "properties": {
    "addr:full":"6413 Amsterdam Way Wilmington NC 28405",
    "addr:housenumber":"6413",
    "addr:postcode":"28405",
    "addr:street":"Amsterdam Way",
    "iso:country":"US",
    "sg:address":"6413 Amsterdam Way",
    "sg:city":"Wilmington",
    "sg:classifiers":[
        {
            "category":"Shopping",
            "subcategory":"Computers & Home Electronics",
            "type":"Retail Goods"
        }
    ],
    "sg:phone":"+1 910 762 0294",
    "sg:postcode":"28405",
    "sg:province":"NC",
    "sg:tags":[
        "installation",
        "marine",
        "sales"
    ],
    "sg:website":"www.battlecat.com",
    "wof:name":"Battlecat Marine",
    "wof:placetype":"venue"
},
  "geometry": {"coordinates":[-77.84744999999999,34.260162],"type":"Point"}
}