{
  "type": "Feature",
  "properties": {
    "addr:full":"1016 Lincoln St Greensboro NC 27401",
    "addr:housenumber":"1016",
    "addr:postcode":"27401",
    "addr:street":"Lincoln St",
    "iso:country":"US",
    "sg:address":"1016 Lincoln St",
    "sg:city":"Greensboro",
    "sg:classifiers":[
        {
            "category":"Education",
            "subcategory":"School",
            "type":"Public Place"
        }
    ],
    "sg:phone":"+1 336 370 8250",
    "sg:postcode":"27401",
    "sg:province":"NC",
    "wof:name":"Harriston Middle School",
    "wof:placetype":"venue"
},
  "geometry": {"coordinates":[-79.76532899999999,36.060931],"type":"Point"}
}