{
  "type": "Feature",
  "properties": {
    "addr:full":"1610 E Salisbury St Asheboro NC 27203",
    "addr:housenumber":"1610",
    "addr:postcode":"27203",
    "addr:street":"E Salisbury St",
    "iso:country":"US",
    "sg:address":"1610 E Salisbury St",
    "sg:city":"Asheboro",
    "sg:classifiers":[
        {
            "category":"Manufacturing",
            "subcategory":"Metals",
            "type":"Manufacturing & Wholesale Goods"
        }
    ],
    "sg:phone":"+1 336 625 6348",
    "sg:postcode":"27203",
    "sg:province":"NC",
    "sg:tags":[
        "hardware",
        "mfg"
    ],
    "wof:name":"Fire Equipment Placement",
    "wof:placetype":"venue"
},
  "geometry": {"coordinates":[-79.78712899999999,35.704016],"type":"Point"}
}