{
  "type": "Feature",
  "properties": {
    "iso:country":"US",
    "sg:address":"8037 Fairview Rd",
    "sg:city":"Charlotte",
    "sg:classifiers":[
        {
            "category":"Real Estate",
            "subcategory":"Developer",
            "type":"Services"
        }
    ],
    "sg:phone":"+1 704 545 6648",
    "sg:postcode":"28227",
    "sg:province":"NC",
    "wof:name":"Carlyle Winston and Co",
    "wof:placetype":"venue"
},
  "geometry": {"coordinates":[-80.64424699999999,35.179129],"type":"Point"}
}