{
  "type": "Feature",
  "properties": {
    "addr:full":"136 Dockside Dr Jacksonville NC 28546",
    "addr:housenumber":"136",
    "addr:postcode":"28546",
    "addr:street":"Dockside Dr",
    "iso:country":"US",
    "sg:address":"136 Dockside Dr",
    "sg:city":"Jacksonville",
    "sg:classifiers":[
        {
            "category":"Professional",
            "type":"Services"
        }
    ],
    "sg:phone":"+1 910 353 7126",
    "sg:postcode":"28546",
    "sg:province":"NC",
    "wof:name":"ICN Inc",
    "wof:placetype":"venue"
},
  "geometry": {"coordinates":[-77.34920099999999,34.747025],"type":"Point"}
}