{
  "type": "Feature",
  "properties": {
    "iso:country":"US",
    "sg:address":"2163 Ranch Rd",
    "sg:city":"Clayton",
    "sg:classifiers":[
        {
            "category":"Organizations",
            "subcategory":"Religious Organization",
            "type":"Services"
        }
    ],
    "sg:phone":"+1   ",
    "sg:postcode":"27520",
    "sg:province":"NC",
    "wof:name":"Baptist Center Church",
    "wof:placetype":"venue"
},
  "geometry": {"coordinates":[-78.475229,35.597693],"type":"Point"}
}