{
  "type": "Feature",
  "properties": {
    "addr:full":"3220 High Point Rd Greensboro NC 27407",
    "addr:housenumber":"3220",
    "addr:postcode":"27407",
    "addr:street":"High Point Rd",
    "iso:country":"US",
    "sg:address":"3220 High Point Rd",
    "sg:city":"Greensboro",
    "sg:classifiers":[
        {
            "category":"Travel",
            "subcategory":"Hotels & Motels",
            "type":"Entertainment"
        }
    ],
    "sg:phone":"+1 336 856 9696",
    "sg:postcode":"27407",
    "sg:province":"NC",
    "sg:tags":[
        "operation"
    ],
    "wof:name":"Drury Inn & Suites",
    "wof:placetype":"venue"
},
  "geometry": {"coordinates":[-79.844943,36.041179],"type":"Point"}
}