{
  "type": "Feature",
  "properties": {
    "addr:full":"7103 Raeford Rd Fayetteville NC 28304",
    "addr:housenumber":"7103",
    "addr:postcode":"28304",
    "addr:street":"Raeford Rd",
    "iso:country":"US",
    "sg:address":"7103 Raeford Rd",
    "sg:city":"Fayetteville",
    "sg:classifiers":[
        {
            "category":"Retail",
            "subcategory":"Veterinary Services",
            "type":"Services"
        },
        {
            "category":"Retail",
            "subcategory":"Animal Services",
            "type":"Services"
        }
    ],
    "sg:phone":"+1 910 487 5070",
    "sg:postcode":"28304",
    "sg:province":"NC",
    "sg:tags":[
        "veterinarian"
    ],
    "wof:name":"Seventy First Animal Hosp P C",
    "wof:placetype":"venue"
},
  "geometry": {"coordinates":[-79.019672,35.035042],"type":"Point"}
}