{
  "type": "Feature",
  "properties": {
    "addr:full":"254 Highland Pl Roaring River NC 28669",
    "addr:housenumber":"254",
    "addr:postcode":"28669",
    "addr:street":"Highland Pl",
    "iso:country":"US",
    "sg:address":"254 Highland Pl",
    "sg:city":"Roaring River",
    "sg:classifiers":[
        {
            "category":"Utilities",
            "subcategory":"Refuse",
            "type":"Services"
        }
    ],
    "sg:phone":"+1 336 957 5628",
    "sg:postcode":"28669",
    "sg:province":"NC",
    "sg:tags":[
        "system"
    ],
    "wof:name":"K4 Inc",
    "wof:placetype":"venue"
},
  "geometry": {"coordinates":[-80.968718,36.266318],"type":"Point"}
}