{
  "type": "Feature",
  "properties": {
    "iso:country":"US",
    "sg:address":"3218 Leicester Dr",
    "sg:city":"Matthews",
    "sg:classifiers":[
        {
            "category":"Communications",
            "subcategory":"Film & Video Production",
            "type":"Services"
        }
    ],
    "sg:phone":"+1 704 882 5228",
    "sg:postcode":"28104",
    "sg:province":"NC",
    "sg:tags":[
        "taping"
    ],
    "wof:name":"Ryder Productions",
    "wof:placetype":"venue"
},
  "geometry": {"coordinates":[-80.604871,35.133354],"type":"Point"}
}