{
  "type": "Feature",
  "properties": {
    "iso:country":"US",
    "sg:address":"1200 Mason Farm Rd",
    "sg:city":"Chapel Hill",
    "sg:classifiers":[
        {
            "category":"Social Services",
            "subcategory":"Child Care",
            "type":"Services"
        }
    ],
    "sg:phone":"+1 919 942 9060",
    "sg:postcode":"27514",
    "sg:province":"NC",
    "sg:tags":[
        "kindergarten",
        "academic",
        "school"
    ],
    "sg:website":"www.languagecenternc.org",
    "wof:name":"Language Center",
    "wof:placetype":"venue"
},
  "geometry": {"coordinates":[-79.05032799999999,35.899153],"type":"Point"}
}