{
  "type": "Feature",
  "properties": {
    "iso:country":"US",
    "sg:address":"1202 S Madison St",
    "sg:city":"Whiteville",
    "sg:classifiers":[
        {
            "category":"Autos & Motor Vehicles",
            "subcategory":"Auto Supplies",
            "type":"Retail Goods"
        }
    ],
    "sg:phone":"+1 910 641 0012",
    "sg:postcode":"28472",
    "sg:province":"NC",
    "sg:tags":[
        "automobile",
        "parts"
    ],
    "wof:name":"Autozone",
    "wof:placetype":"venue"
},
  "geometry": {"coordinates":[-78.707554,34.314981],"type":"Point"}
}