{
  "type": "Feature",
  "properties": {
    "addr:full":"2511 Wake Forest Rd Raleigh NC 27609",
    "addr:housenumber":"2511",
    "addr:postcode":"27609",
    "addr:street":"Wake Forest Rd",
    "iso:country":"US",
    "sg:address":"2511 Wake Forest Rd",
    "sg:city":"Raleigh",
    "sg:phone":"+1 919 839 7392",
    "sg:postcode":"27609",
    "sg:province":"NC",
    "sg:website":"http://www.nissanofraleigh.net/",
    "wof:name":"Southern States Nissan",
    "wof:placetype":"venue"
},
  "geometry": {"coordinates":[-78.625654,35.816383],"type":"Point"}
}