{
  "type": "Feature",
  "properties": {
    "iso:country":"US",
    "sg:address":"1401 W Innes St",
    "sg:city":"Salisbury",
    "sg:classifiers":[
        {
            "category":"Banks & Credit Unions",
            "subcategory":"Bank",
            "type":"Services"
        }
    ],
    "sg:phone":"+1 704 647 3150",
    "sg:postcode":"28144",
    "sg:province":"NC",
    "sg:tags":[
        "loan",
        "real estate"
    ],
    "wof:name":"Central Carolina Bank",
    "wof:placetype":"venue"
},
  "geometry": {"coordinates":[-80.481982,35.681825],"type":"Point"}
}