{
  "type": "Feature",
  "properties": {
    "addr:full":"2312 Randleman Rd Greensboro NC 27406",
    "addr:postcode":"2312;27406",
    "addr:street":"Randleman Rd",
    "iso:country":"US",
    "sg:address":"2312 Randleman Rd",
    "sg:city":"Greensboro",
    "sg:classifiers":[
        {
            "category":"Restaurant",
            "type":"Food & Drink"
        }
    ],
    "sg:phone":"+1 336 271 2155",
    "sg:postcode":"27406",
    "sg:province":"NC",
    "sg:tags":[
        "eating"
    ],
    "wof:name":"Soul Food By Regina",
    "wof:placetype":"venue"
},
  "geometry": {"coordinates":[-79.800991,36.04369],"type":"Point"}
}