{
  "type": "Feature",
  "properties": {
    "iso:country":"US",
    "sg:address":"4516 State Hwy 49",
    "sg:city":"Burlington",
    "sg:classifiers":[
        {
            "category":"Health Services",
            "subcategory":"Nursing And Care Facility",
            "type":"Services"
        }
    ],
    "sg:phone":"+1   ",
    "sg:postcode":"27217",
    "sg:province":"NC",
    "wof:name":"Pleasant Grove Retirement Home",
    "wof:placetype":"venue"
},
  "geometry": {"coordinates":[-79.32047799999999,36.191127],"type":"Point"}
}