{
  "type": "Feature",
  "properties": {
    "iso:country":"US",
    "sg:address":"9414 Penshurst Trce",
    "sg:city":"Charlotte",
    "sg:classifiers":[
        {
            "category":"Manufacturing",
            "subcategory":"Electronics",
            "type":"Manufacturing & Wholesale Goods"
        }
    ],
    "sg:phone":"+1 704 341 0373",
    "sg:postcode":"28210",
    "sg:province":"NC",
    "sg:tags":[
        "printed",
        "circuit",
        "etched"
    ],
    "wof:name":"Elec & Eltek",
    "wof:placetype":"venue"
},
  "geometry": {"coordinates":[-80.860596,35.102417],"type":"Point"}
}