{
  "type": "Feature",
  "properties": {
    "iso:country":"US",
    "sg:address":"4909 Waters Edge Dr",
    "sg:city":"Raleigh",
    "sg:classifiers":[
        {
            "category":"Freight",
            "type":"Transportation"
        }
    ],
    "sg:phone":"+1 919 233 5815",
    "sg:postcode":"27606",
    "sg:province":"NC",
    "wof:name":"Lewis Transportation LLC",
    "wof:placetype":"venue"
},
  "geometry": {"coordinates":[-78.722104,35.773439],"type":"Point"}
}