{
  "type": "Feature",
  "properties": {
    "addr:full":"529 N Trade St Winston Salem NC 27101",
    "addr:housenumber":"529",
    "addr:postcode":"27101",
    "addr:street":"N Trade St",
    "iso:country":"US",
    "sg:address":"529 N Trade St",
    "sg:city":"Winston Salem",
    "sg:classifiers":[
        {
            "category":"Restaurant",
            "type":"Food & Drink"
        }
    ],
    "sg:menulink":"http://www.allmenus.com/nc/winston/270736-sweet-potatoes/menu/",
    "sg:phone":"+1 336 727 4844",
    "sg:postcode":"27101",
    "sg:province":"NC",
    "sg:tags":[
        "food",
        "american",
        "soul"
    ],
    "wof:name":"Sweet Potatoes",
    "wof:placetype":"venue"
},
  "geometry": {"coordinates":[-80.245901,36.100671],"type":"Point"}
}