{
  "type": "Feature",
  "properties": {
    "addr:full":"439 Acacia Cir Fayetteville NC 28314",
    "addr:housenumber":"439",
    "addr:postcode":"28314",
    "addr:street":"Acacia Cir",
    "iso:country":"US",
    "sg:address":"439 Acacia Cir",
    "sg:city":"Fayetteville",
    "sg:classifiers":[
        {
            "category":"Professional",
            "subcategory":"Computer Services",
            "type":"Services"
        }
    ],
    "sg:phone":"+1   ",
    "sg:postcode":"28314",
    "sg:province":"NC",
    "sg:tags":[
        "datum"
    ],
    "wof:name":"1nesolution",
    "wof:placetype":"venue"
},
  "geometry": {"coordinates":[-78.97625600000001,35.058809],"type":"Point"}
}