{
  "type": "Feature",
  "properties": {
    "addr:full":"144 S Steele St Sanford NC 27330",
    "addr:housenumber":"144",
    "addr:postcode":"27330",
    "addr:street":"S Steele St",
    "iso:country":"US",
    "sg:address":"144 S Steele St",
    "sg:city":"Sanford",
    "sg:classifiers":[
        {
            "category":"Real Estate",
            "subcategory":"Real Estate Agent",
            "type":"Services"
        }
    ],
    "sg:phone":"+1 919 776 4351",
    "sg:postcode":"27330",
    "sg:province":"NC",
    "wof:name":"Ak & K Corp",
    "wof:placetype":"venue"
},
  "geometry": {"coordinates":[-79.178786,35.480126],"type":"Point"}
}