{
  "type": "Feature",
  "properties": {
    "iso:country":"US",
    "sg:address":"855 Old US Hwy 421",
    "sg:city":"Lillington",
    "sg:classifiers":[
        {
            "category":"Education",
            "subcategory":"School",
            "type":"Public Place"
        }
    ],
    "sg:phone":"+1 910 893 3483",
    "sg:postcode":"27546",
    "sg:province":"NC",
    "wof:name":"Lillington Elementary School",
    "wof:placetype":"venue"
},
  "geometry": {"coordinates":[-78.83832200000001,35.394437],"type":"Point"}
}