{
  "type": "Feature",
  "properties": {
    "addr:full":"1204 Corbett Rd Clayton NC 27520",
    "addr:housenumber":"1204",
    "addr:postcode":"27520",
    "addr:street":"Corbett Rd",
    "iso:country":"US",
    "sg:address":"1204 Corbett Rd",
    "sg:city":"Clayton",
    "sg:classifiers":[
        {
            "category":"Manufacturing",
            "subcategory":"Apparel",
            "type":"Manufacturing & Wholesale Goods"
        }
    ],
    "sg:phone":"+1 919 553 3328",
    "sg:postcode":"27520",
    "sg:province":"NC",
    "sg:tags":[
        "custom",
        "embroidery",
        "monogramming"
    ],
    "wof:name":"Monogram Creations",
    "wof:placetype":"venue"
},
  "geometry": {"coordinates":[-78.499976,35.609751],"type":"Point"}
}