{
  "type": "Feature",
  "properties": {
    "iso:country":"US",
    "sg:address":"618 W Morehead St",
    "sg:city":"Charlotte",
    "sg:classifiers":[
        {
            "category":"Retail",
            "subcategory":"Repair Shop",
            "type":"Services"
        }
    ],
    "sg:phone":"+1 704 332 7477",
    "sg:postcode":"28208",
    "sg:province":"NC",
    "sg:tags":[
        "instrument",
        "musical"
    ],
    "wof:name":"Mohawk Audio",
    "wof:placetype":"venue"
},
  "geometry": {"coordinates":[-80.85572000000001,35.225726],"type":"Point"}
}