{
  "type": "Feature",
  "properties": {
    "addr:full":"14855 US Hwy 158 Summerfield NC 27358",
    "addr:housenumber":"14855",
    "addr:postcode":"27358",
    "addr:street":"Us Hwy 158",
    "iso:country":"US",
    "sg:address":"14855 US Hwy 158",
    "sg:city":"Summerfield",
    "sg:classifiers":[
        {
            "category":"Organizations",
            "subcategory":"Religious Organization",
            "type":"Services"
        }
    ],
    "sg:phone":"+1   ",
    "sg:postcode":"27358",
    "sg:province":"NC",
    "wof:name":"Trinity Chapel",
    "wof:placetype":"venue"
},
  "geometry": {"coordinates":[-79.875258,36.258115],"type":"Point"}
}