{
  "type": "Feature",
  "properties": {
    "addr:full":"8514 University City Blvd Charlotte NC 28213",
    "addr:housenumber":"8514",
    "addr:postcode":"28213",
    "addr:street":"University City Blvd",
    "iso:country":"US",
    "sg:address":"8514 University City Blvd",
    "sg:city":"Charlotte",
    "sg:classifiers":[
        {
            "category":"Personal",
            "type":"Services"
        },
        {
            "category":"Sports & Exercise",
            "subcategory":"Gym",
            "type":"Entertainment"
        },
        {
            "category":"Arena",
            "subcategory":"Sports Club",
            "type":"Entertainment"
        }
    ],
    "sg:phone":"+1 704 510 4988",
    "sg:postcode":"28213",
    "sg:province":"NC",
    "sg:tags":[
        "trainer",
        "yoga",
        "consultant",
        "instruction",
        "gymnasium",
        "equipment",
        "program",
        "health",
        "fitness",
        "pilate",
        "physical"
    ],
    "sg:website":"http://www.lff.com",
    "wof:name":"Lifestyle Family Fitness",
    "wof:placetype":"venue"
},
  "geometry": {"coordinates":[-80.74112700000001,35.296698],"type":"Point"}
}