{
  "type": "Feature",
  "properties": {
    "addr:full":"6613 Swallowtail Ln Raleigh NC 27613",
    "addr:housenumber":"6613",
    "addr:postcode":"27613",
    "addr:street":"Swallowtail Ln",
    "iso:country":"US",
    "sg:address":"6613 Swallowtail Ln",
    "sg:city":"Raleigh",
    "sg:classifiers":[
        {
            "category":"Autos & Motor Vehicles",
            "subcategory":"Motorcycle Sales",
            "type":"Retail Goods"
        }
    ],
    "sg:phone":"+1 919 848 9676",
    "sg:postcode":"27613",
    "sg:province":"NC",
    "wof:name":"Brunos Classic Cycles",
    "wof:placetype":"venue"
},
  "geometry": {"coordinates":[-78.711536,35.960698],"type":"Point"}
}