{
  "type": "Feature",
  "properties": {
    "addr:full":"63 Elmwood Way Waynesville NC 28786",
    "addr:housenumber":"63",
    "addr:postcode":"28786",
    "addr:street":"Elmwood Way",
    "iso:country":"US",
    "sg:address":"63 Elmwood Way",
    "sg:city":"Waynesville",
    "sg:classifiers":[
        {
            "category":"Home & Garden",
            "subcategory":"Carpets & Floor Coverings",
            "type":"Retail Goods"
        }
    ],
    "sg:phone":"+1 828 456 8435",
    "sg:postcode":"28786",
    "sg:province":"NC",
    "sg:tags":[
        "cabinet"
    ],
    "wof:name":"Bargains",
    "wof:placetype":"venue"
},
  "geometry": {"coordinates":[-82.988213,35.517838],"type":"Point"}
}