{
  "type": "Feature",
  "properties": {
    "addr:full":"1037 3rd St SE Hickory NC 28602",
    "addr:housenumber":"1037",
    "addr:postcode":"28602",
    "addr:street":"3Rd St Se",
    "iso:country":"US",
    "sg:address":"1037 3rd St SE",
    "sg:city":"Hickory",
    "sg:classifiers":[
        {
            "category":"Building & Trades",
            "subcategory":"Construction",
            "type":"Services"
        }
    ],
    "sg:phone":"+1 828 308 0821",
    "sg:postcode":"28602",
    "sg:province":"NC",
    "sg:tags":[
        "home",
        "improvement"
    ],
    "wof:name":"Do All Repair & Remodeling",
    "wof:placetype":"venue"
},
  "geometry": {"coordinates":[-81.33309,35.720298],"type":"Point"}
}