{
  "type": "Feature",
  "properties": {
    "addr:full":"450 US Hwy 64 Bus Hayesville NC 28904",
    "addr:housenumber":"450",
    "addr:postcode":"28904",
    "addr:street":"Us Hwy 64 Bus",
    "iso:country":"US",
    "sg:address":"450 US Hwy 64 Bus",
    "sg:city":"Hayesville",
    "sg:classifiers":[
        {
            "category":"Shopping",
            "subcategory":"Used Merchandise",
            "type":"Retail Goods"
        }
    ],
    "sg:phone":"+1 828 389 4443",
    "sg:postcode":"28904",
    "sg:province":"NC",
    "sg:tags":[
        "clothing"
    ],
    "wof:name":"Ala Tan Boutique",
    "wof:placetype":"venue"
},
  "geometry": {"coordinates":[-83.81779899999999,35.039458],"type":"Point"}
}