{
  "type": "Feature",
  "properties": {
    "iso:country":"US",
    "sg:address":"1030 Industrial Dr",
    "sg:city":"Matthews",
    "sg:classifiers":[
        {
            "category":"Retail",
            "subcategory":"Driving School",
            "type":"Services"
        },
        {
            "category":"Autos & Motor Vehicles",
            "subcategory":"Motorcycle Sales",
            "type":"Retail Goods"
        },
        {
            "category":"Retail",
            "subcategory":"Auto Repair",
            "type":"Services"
        }
    ],
    "sg:phone":"+1 704 708 5828",
    "sg:postcode":"28105",
    "sg:province":"NC",
    "sg:tags":[
        "scooters-repairing",
        "instruction"
    ],
    "sg:website":"http://www.thecyclexchange.com",
    "wof:name":"Cycle Xchange",
    "wof:placetype":"venue"
},
  "geometry": {"coordinates":[-80.726826,35.126453],"type":"Point"}
}