{
  "type": "Feature",
  "properties": {
    "iso:country":"US",
    "sg:address":"3716 Clinton Rd",
    "sg:city":"Fayetteville",
    "sg:classifiers":[
        {
            "category":"Organizations",
            "subcategory":"Religious Organization",
            "type":"Services"
        }
    ],
    "sg:phone":"+1 910 484 9541",
    "sg:postcode":"28312",
    "sg:province":"NC",
    "wof:name":"Free Commission Church",
    "wof:placetype":"venue"
},
  "geometry": {"coordinates":[-78.789976,35.031891],"type":"Point"}
}