{
  "type": "Feature",
  "properties": {
    "addr:full":"4260 Bennett Memorial Rd Durham NC 27705",
    "addr:housenumber":"4260",
    "addr:postcode":"27705",
    "addr:street":"Bennett Memorial Rd",
    "iso:country":"US",
    "sg:address":"4260 Bennett Memorial Rd",
    "sg:city":"Durham",
    "sg:classifiers":[
        {
            "category":"Retail",
            "subcategory":"Repair Shop",
            "type":"Services"
        }
    ],
    "sg:phone":"+1 919 382 8624",
    "sg:postcode":"27705",
    "sg:province":"NC",
    "wof:name":"Boat Repairs & More",
    "wof:placetype":"venue"
},
  "geometry": {"coordinates":[-78.96618700000001,36.030383],"type":"Point"}
}