{
  "type": "Feature",
  "properties": {
    "iso:country":"US",
    "sg:address":"2091 Skibo Rd",
    "sg:city":"Fayetteville",
    "sg:classifiers":[
        {
            "category":"Shopping",
            "subcategory":"Hobbies, Toys, & Games",
            "type":"Retail Goods"
        }
    ],
    "sg:phone":"+1 910 860 2653",
    "sg:postcode":"28314",
    "sg:province":"NC",
    "sg:tags":[
        "craft",
        "supply"
    ],
    "wof:name":"Michaels Arts & Crafts Store",
    "wof:placetype":"venue"
},
  "geometry": {"coordinates":[-78.97289000000001,35.054641],"type":"Point"}
}