{
  "type": "Feature",
  "properties": {
    "iso:country":"US",
    "sg:address":"201 Rainbow Dr",
    "sg:city":"Carrboro",
    "sg:classifiers":[
        {
            "category":"Arts & Performance",
            "subcategory":"Theater",
            "type":"Entertainment"
        }
    ],
    "sg:phone":"+1   ",
    "sg:postcode":"27510",
    "sg:province":"NC",
    "sg:tags":[
        "theatrical"
    ],
    "wof:name":"Tg2 Artist Representation",
    "wof:placetype":"venue"
},
  "geometry": {"coordinates":[-79.09236799999999,35.923756],"type":"Point"}
}