{
  "type": "Feature",
  "properties": {
    "addr:full":"2300 W Roosevelt Blvd Monroe NC 28110",
    "addr:housenumber":"2300",
    "addr:postcode":"28110",
    "addr:street":"W Roosevelt Blvd",
    "iso:country":"US",
    "sg:address":"2300 W Roosevelt Blvd",
    "sg:city":"Monroe",
    "sg:classifiers":[
        {
            "category":"Restaurant",
            "type":"Food & Drink"
        }
    ],
    "sg:phone":"+1 704 225 1957",
    "sg:postcode":"28110",
    "sg:province":"NC",
    "sg:tags":[
        "parlor",
        "eating",
        "ice",
        "cream"
    ],
    "sg:website":"www.dairyqueen.com",
    "wof:name":"Dairy Queen",
    "wof:placetype":"venue"
},
  "geometry": {"coordinates":[-80.562273,35.00913],"type":"Point"}
}