{
  "type": "Feature",
  "properties": {
    "iso:country":"US",
    "sg:address":"2300 E 7th St",
    "sg:city":"Charlotte",
    "sg:classifiers":[
        {
            "category":"Professional",
            "subcategory":"Lawyer & Legal Services",
            "type":"Services"
        }
    ],
    "sg:phone":"+1 704 333 7800",
    "sg:postcode":"28204",
    "sg:province":"NC",
    "sg:tags":[
        "corporation",
        "attorney",
        "partnership",
        "law"
    ],
    "wof:name":"Hockfield, Steven A",
    "wof:placetype":"venue"
},
  "geometry": {"coordinates":[-80.814453,35.209839],"type":"Point"}
}