{
  "type": "Feature",
  "properties": {
    "addr:full":"325 W Horne St Clayton NC 27520",
    "addr:housenumber":"325",
    "addr:postcode":"27520",
    "addr:street":"W Horne St",
    "iso:country":"US",
    "sg:address":"325 W Horne St",
    "sg:city":"Clayton",
    "sg:classifiers":[
        {
            "category":"Government",
            "subcategory":"Fire Station",
            "type":"Public Place"
        }
    ],
    "sg:phone":"+1 919 553 1755",
    "sg:postcode":"27520",
    "sg:province":"NC",
    "sg:tags":[
        "department"
    ],
    "wof:name":"Clayton Fire Chief",
    "wof:placetype":"venue"
},
  "geometry": {"coordinates":[-78.464167,35.654153],"type":"Point"}
}