{
  "type": "Feature",
  "properties": {
    "addr:full":"5530 State Hwy 42 W Garner NC 27529",
    "addr:housenumber":"5530",
    "addr:postcode":"27529",
    "addr:street":"State Hwy 42 W",
    "iso:country":"US",
    "sg:address":"5530 State Hwy 42 W",
    "sg:city":"Garner",
    "sg:classifiers":[
        {
            "category":"Restaurant",
            "type":"Food & Drink"
        }
    ],
    "sg:phone":"+1 919 773 2440",
    "sg:postcode":"27529",
    "sg:province":"NC",
    "sg:tags":[
        "eating"
    ],
    "sg:website":"www.kfc.com",
    "wof:name":"KFC",
    "wof:placetype":"venue"
},
  "geometry": {"coordinates":[-78.567718,35.60504],"type":"Point"}
}