{
  "type": "Feature",
  "properties": {
    "iso:country":"US",
    "sg:address":"901 Chalk Level Rd",
    "sg:city":"Durham",
    "sg:classifiers":[
        {
            "category":"Professional",
            "type":"Services"
        }
    ],
    "sg:phone":"+1 919 620 0574",
    "sg:postcode":"27704",
    "sg:province":"NC",
    "sg:tags":[
        "arranger",
        "music",
        "composer"
    ],
    "wof:name":"Barak Musicwrite",
    "wof:placetype":"venue"
},
  "geometry": {"coordinates":[-78.910859,36.051147],"type":"Point"}
}