{
  "type": "Feature",
  "properties": {
    "addr:full":"256 Fairview Acres Rd Lexington NC 27295",
    "addr:housenumber":"256",
    "addr:postcode":"27295",
    "addr:street":"Fairview Acres Rd",
    "iso:country":"US",
    "sg:address":"256 Fairview Acres Rd",
    "sg:city":"Lexington",
    "sg:classifiers":[
        {
            "category":"Building & Trades",
            "subcategory":"Landscaping Services",
            "type":"Services"
        }
    ],
    "sg:phone":"+1 336 249 8120",
    "sg:postcode":"27295",
    "sg:province":"NC",
    "sg:tags":[
        "lawn",
        "maintenance",
        "grounds"
    ],
    "wof:name":"Canady's Light Grading",
    "wof:placetype":"venue"
},
  "geometry": {"coordinates":[-80.315521,35.87946],"type":"Point"}
}