{
  "type": "Feature",
  "properties": {
    "iso:country":"US",
    "sg:address":"4910 Sylva Rd",
    "sg:city":"Franklin",
    "sg:classifiers":[
        {
            "category":"Autos & Motor Vehicles",
            "subcategory":"Automobile Sales",
            "type":"Retail Goods"
        }
    ],
    "sg:phone":"+1 828 524 2156",
    "sg:postcode":"28734",
    "sg:province":"NC",
    "sg:tags":[
        "car",
        "dealer"
    ],
    "wof:name":"Franklin Ford Inc",
    "wof:placetype":"venue"
},
  "geometry": {"coordinates":[-83.35641800000001,35.222089],"type":"Point"}
}