{
  "type": "Feature",
  "properties": {
    "addr:full":"14460 New Falls of Neuse Rd Raleigh NC 27614",
    "addr:housenumber":"14460",
    "addr:postcode":"27614",
    "addr:street":"New Falls;Neuse Rd",
    "iso:country":"US",
    "sg:address":"14460 New Falls of Neuse Rd",
    "sg:city":"Raleigh",
    "sg:classifiers":[
        {
            "category":"Restaurant",
            "type":"Food & Drink"
        }
    ],
    "sg:phone":"+1 919 488 0262",
    "sg:postcode":"27614",
    "sg:province":"NC",
    "sg:tags":[
        "sandwich"
    ],
    "wof:name":"Jersey Mike's Subs",
    "wof:placetype":"venue"
},
  "geometry": {"coordinates":[-78.541692,35.945846],"type":"Point"}
}