{
  "type": "Feature",
  "properties": {
    "addr:full":"6540 Glenwood Ave Raleigh NC 27612",
    "addr:housenumber":"6540",
    "addr:postcode":"27612",
    "addr:street":"Glenwood Ave",
    "iso:country":"US",
    "sg:address":"6540 Glenwood Ave",
    "sg:city":"Raleigh",
    "sg:classifiers":[
        {
            "category":"Shopping",
            "subcategory":"Department Store",
            "type":"Retail Goods"
        }
    ],
    "sg:phone":"+1 919 420 0321",
    "sg:postcode":"27612",
    "sg:province":"NC",
    "sg:website":"www.biglots.com",
    "wof:name":"Big Lots",
    "wof:placetype":"venue"
},
  "geometry": {"coordinates":[-78.70707299999999,35.859571],"type":"Point"}
}