{
  "type": "Feature",
  "properties": {
    "iso:country":"US",
    "sg:address":"356 N South St",
    "sg:city":"Mount Airy",
    "sg:classifiers":[
        {
            "category":"Banks & Credit Unions",
            "subcategory":"Bank",
            "type":"Services"
        }
    ],
    "sg:phone":"+1 336 789 6264",
    "sg:postcode":"27030",
    "sg:province":"NC",
    "sg:tags":[
        "personal",
        "mortgage"
    ],
    "wof:name":"Wells Fargo",
    "wof:placetype":"venue"
},
  "geometry": {"coordinates":[-80.61461300000001,36.501113],"type":"Point"}
}