{
  "type": "Feature",
  "properties": {
    "iso:country":"US",
    "sg:address":"12413 Village Gate Way",
    "sg:city":"Raleigh",
    "sg:classifiers":[
        {
            "category":"Wholesale",
            "subcategory":"Machinery & Supplies",
            "type":"Manufacturing & Wholesale Goods"
        }
    ],
    "sg:phone":"+1 919 671 4210",
    "sg:postcode":"27614",
    "sg:province":"NC",
    "sg:tags":[
        "industrial",
        "equipment",
        "used",
        "machinery-new",
        "supplies-wholesale"
    ],
    "wof:name":"Orbi Automation",
    "wof:placetype":"venue"
},
  "geometry": {"coordinates":[-78.560204,35.947322],"type":"Point"}
}