{
  "type": "Feature",
  "properties": {
    "iso:country":"US",
    "sg:address":"152 Christys Way",
    "sg:city":"Roxboro",
    "sg:classifiers":[
        {
            "category":"Building & Trades",
            "subcategory":"Cleaning & Sanitation",
            "type":"Services"
        }
    ],
    "sg:phone":"+1   ",
    "sg:postcode":"27574",
    "sg:province":"NC",
    "sg:tags":[
        "maintenance"
    ],
    "wof:name":"Anas Cleaning Services",
    "wof:placetype":"venue"
},
  "geometry": {"coordinates":[-78.89766299999999,36.365728],"type":"Point"}
}