{
  "type": "Feature",
  "properties": {
    "iso:country":"US",
    "sg:address":"65 Red Fox Run",
    "sg:city":"Pinehurst",
    "sg:classifiers":[
        {
            "category":"Insurance",
            "subcategory":"Insurance Agent",
            "type":"Services"
        }
    ],
    "sg:phone":"+1 910 215 9955",
    "sg:postcode":"28374",
    "sg:province":"NC",
    "wof:name":"Liberty Mutual",
    "wof:placetype":"venue"
},
  "geometry": {"coordinates":[-79.49182,35.189494],"type":"Point"}
}