{
  "type": "Feature",
  "properties": {
    "addr:full":"2086 Jamestown Rd Morganton NC 28655",
    "addr:housenumber":"2086",
    "addr:postcode":"28655",
    "addr:street":"Jamestown Rd",
    "iso:country":"US",
    "sg:address":"2086 Jamestown Rd",
    "sg:city":"Morganton",
    "sg:classifiers":[
        {
            "category":"Freight",
            "type":"Transportation"
        }
    ],
    "sg:phone":"+1 828 584 4441",
    "sg:postcode":"28655",
    "sg:province":"NC",
    "sg:tags":[
        "arrangement"
    ],
    "wof:name":"Detter Enterprises Inc",
    "wof:placetype":"venue"
},
  "geometry": {"coordinates":[-81.786412,35.70377],"type":"Point"}
}