{
  "type": "Feature",
  "properties": {
    "addr:full":"141 Reems Creek Rd Weaverville NC 28787",
    "addr:housenumber":"141",
    "addr:postcode":"28787",
    "addr:street":"Reems Creek Rd",
    "iso:country":"US",
    "sg:address":"141 Reems Creek Rd",
    "sg:city":"Weaverville",
    "sg:classifiers":[
        {
            "category":"Professional",
            "type":"Services"
        }
    ],
    "sg:phone":"+1 828 645 7500",
    "sg:postcode":"28787",
    "sg:province":"NC",
    "sg:tags":[
        "establishment"
    ],
    "wof:name":"Peggy Reid & Assoc-Realtors",
    "wof:placetype":"venue"
},
  "geometry": {"coordinates":[-82.560463,35.688957],"type":"Point"}
}