{
  "type": "Feature",
  "properties": {
    "addr:full":"2605 E 3rd St Greenville NC 27858",
    "addr:housenumber":"2605",
    "addr:postcode":"27858",
    "addr:street":"E 3Rd St",
    "iso:country":"US",
    "sg:address":"2605 E 3rd St",
    "sg:city":"Greenville",
    "sg:classifiers":[
        {
            "category":"Manufacturing",
            "subcategory":"Retail Goods",
            "type":"Manufacturing & Wholesale Goods"
        }
    ],
    "sg:phone":"+1 252 752 0055",
    "sg:postcode":"27858",
    "sg:province":"NC",
    "sg:tags":[
        "shell"
    ],
    "wof:name":"Our Fathers Hse-Born 2 Win",
    "wof:placetype":"venue"
},
  "geometry": {"coordinates":[-77.343689,35.608455],"type":"Point"}
}