{
  "type": "Feature",
  "properties": {
    "addr:full":"517 W Sothel St Kill Devil Hills NC 27948",
    "addr:housenumber":"517",
    "addr:postcode":"27948",
    "addr:street":"W Sothel St",
    "iso:country":"US",
    "sg:address":"517 W Sothel St",
    "sg:city":"Kill Devil Hills",
    "sg:classifiers":[
        {
            "category":"Manufacturing",
            "subcategory":"Printing",
            "type":"Manufacturing & Wholesale Goods"
        }
    ],
    "sg:phone":"+1 252 480 0246",
    "sg:postcode":"27948",
    "sg:province":"NC",
    "sg:tags":[
        "newspaper"
    ],
    "wof:name":"Classified Plus",
    "wof:placetype":"venue"
},
  "geometry": {"coordinates":[-75.684995,36.045918],"type":"Point"}
}