{
  "type": "Feature",
  "properties": {
    "iso:country":"US",
    "sg:address":"617 Greystone Rd",
    "sg:city":"Charlotte",
    "sg:classifiers":[
        {
            "category":"Restaurant",
            "type":"Food & Drink"
        }
    ],
    "sg:phone":"+1 704 561 0082",
    "sg:postcode":"28209",
    "sg:province":"NC",
    "sg:tags":[
        "eating"
    ],
    "wof:name":"Hollywood Grill",
    "wof:placetype":"venue"
},
  "geometry": {"coordinates":[-80.86312599999999,35.192296],"type":"Point"}
}