{
  "type": "Feature",
  "properties": {
    "addr:full":"315 Valley River Ave Murphy NC 28906",
    "addr:housenumber":"315",
    "addr:postcode":"28906",
    "addr:street":"Valley River Ave",
    "iso:country":"US",
    "sg:address":"315 Valley River Ave",
    "sg:city":"Murphy",
    "sg:classifiers":[
        {
            "category":"Education",
            "subcategory":"School",
            "type":"Public Place"
        }
    ],
    "sg:phone":"+1 828 835 3224",
    "sg:postcode":"28906",
    "sg:province":"NC",
    "wof:name":"Valley River Learning Ctr",
    "wof:placetype":"venue"
},
  "geometry": {"coordinates":[-84.03086,35.088105],"type":"Point"}
}