{
  "type": "Feature",
  "properties": {
    "iso:country":"US",
    "sg:address":"1007 Porters Neck Rd",
    "sg:city":"Wilmington",
    "sg:classifiers":[
        {
            "category":"Social Services",
            "subcategory":"Adult Care",
            "type":"Services"
        }
    ],
    "sg:phone":"+1 910 686 6462",
    "sg:postcode":"28411",
    "sg:province":"NC",
    "sg:tags":[
        "home",
        "residential"
    ],
    "sg:website":"www.championsassistedliving.com",
    "wof:name":"Champions Assisted Living",
    "wof:placetype":"venue"
},
  "geometry": {"coordinates":[-77.775908,34.293225],"type":"Point"}
}