{
  "type": "Feature",
  "properties": {
    "addr:full":"1810 Lazy Ln High Point NC 27265",
    "addr:housenumber":"1810",
    "addr:postcode":"27265",
    "addr:street":"Lazy Ln",
    "iso:country":"US",
    "sg:address":"1810 Lazy Ln",
    "sg:city":"High Point",
    "sg:classifiers":[
        {
            "category":"Building & Trades",
            "subcategory":"Construction",
            "type":"Services"
        }
    ],
    "sg:phone":"+1 336 869 7594",
    "sg:postcode":"27265",
    "sg:province":"NC",
    "sg:tags":[
        "house"
    ],
    "wof:name":"Lcg Construction LLC",
    "wof:placetype":"venue"
},
  "geometry": {"coordinates":[-79.984695,36.005646],"type":"Point"}
}