{
  "type": "Feature",
  "properties": {
    "addr:full":"112 E Industry Dr Oxford NC 27565",
    "addr:housenumber":"112",
    "addr:postcode":"27565",
    "addr:street":"E Industry Dr",
    "iso:country":"US",
    "sg:address":"112 E Industry Dr",
    "sg:city":"Oxford",
    "sg:classifiers":[
        {
            "category":"Shopping",
            "subcategory":"Discount & Variety Stores",
            "type":"Retail Goods"
        }
    ],
    "sg:phone":"+1 919 693 4861",
    "sg:postcode":"27565",
    "sg:province":"NC",
    "wof:name":"Super 10",
    "wof:placetype":"venue"
},
  "geometry": {"coordinates":[-78.60082800000001,36.294771],"type":"Point"}
}