{
  "type": "Feature",
  "properties": {
    "addr:full":"744 Circle Dr Greenville NC 27858",
    "addr:housenumber":"744",
    "addr:postcode":"27858",
    "addr:street":"Circle Dr",
    "iso:country":"US",
    "sg:address":"744 Circle Dr",
    "sg:city":"Greenville",
    "sg:classifiers":[
        {
            "category":"Education",
            "subcategory":"Special Training",
            "type":"Public Place"
        }
    ],
    "sg:phone":"+1 252 752 3630",
    "sg:postcode":"27858",
    "sg:province":"NC",
    "sg:tags":[
        "tutoring"
    ],
    "wof:name":"Danielique's Tutoring Svc",
    "wof:placetype":"venue"
},
  "geometry": {"coordinates":[-77.29427800000001,35.576961],"type":"Point"}
}