{
  "type": "Feature",
  "properties": {
    "addr:full":"2750 State Hwy 55 Cary NC 27519",
    "addr:housenumber":"2750",
    "addr:postcode":"27519",
    "addr:street":"State Hwy 55",
    "iso:country":"US",
    "sg:address":"2750 State Hwy 55",
    "sg:city":"Cary",
    "sg:classifiers":[
        {
            "category":"Restaurant",
            "type":"Food & Drink"
        }
    ],
    "sg:phone":"+1 919 363 0483",
    "sg:postcode":"27519",
    "sg:province":"NC",
    "sg:tags":[
        "shop",
        "coffee"
    ],
    "wof:name":"Starbucks",
    "wof:placetype":"venue"
},
  "geometry": {"coordinates":[-78.87085999999999,35.786713],"type":"Point"}
}