{
  "type": "Feature",
  "properties": {
    "iso:country":"US",
    "sg:address":"288 Montford Ave",
    "sg:city":"Asheville",
    "sg:classifiers":[
        {
            "category":"Travel",
            "subcategory":"Hotels & Motels",
            "type":"Entertainment"
        }
    ],
    "sg:phone":"+1 828 254 3878",
    "sg:postcode":"28801",
    "sg:province":"NC",
    "sg:tags":[
        "breakfast",
        "accommodation",
        "bed"
    ],
    "sg:website":"www.blackwalnut.com",
    "wof:name":"Black Walnut Bed & Breakfast",
    "wof:placetype":"venue"
},
  "geometry": {"coordinates":[-82.567058,35.605583],"type":"Point"}
}