{
  "type": "Feature",
  "properties": {
    "iso:country":"US",
    "sg:address":"34 2nd St NW",
    "sg:city":"Hickory",
    "sg:classifiers":[
        {
            "category":"Building & Trades",
            "subcategory":"Electrical",
            "type":"Services"
        }
    ],
    "sg:phone":"+1 828 327 0504",
    "sg:postcode":"28601",
    "sg:province":"NC",
    "sg:tags":[
        "telecommunication",
        "contractor"
    ],
    "wof:name":"Kevin E Wall & Assocs",
    "wof:placetype":"venue"
},
  "geometry": {"coordinates":[-81.339573,35.732288],"type":"Point"}
}