{
  "type": "Feature",
  "properties": {
    "iso:country":"US",
    "sg:address":"3325 Washburn Ave",
    "sg:city":"Charlotte",
    "sg:classifiers":[
        {
            "category":"Retail",
            "subcategory":"Laundry & Dry Cleaning",
            "type":"Services"
        }
    ],
    "sg:phone":"+1 704 335 7273",
    "sg:postcode":"28205",
    "sg:province":"NC",
    "sg:tags":[
        "cleaner",
        "drapery",
        "curtain"
    ],
    "wof:name":"Carolina Carpet & Drapery",
    "wof:placetype":"venue"
},
  "geometry": {"coordinates":[-80.80037299999999,35.20344],"type":"Point"}
}