{
  "type": "Feature",
  "properties": {
    "iso:country":"US",
    "sg:address":"740 Sullivan Rd",
    "sg:city":"Statesville",
    "sg:classifiers":[
        {
            "category":"Travel",
            "subcategory":"Hotels & Motels",
            "type":"Entertainment"
        }
    ],
    "sg:phone":"+1 704 872 2385",
    "sg:postcode":"28677",
    "sg:province":"NC",
    "wof:name":"Shaner Hotel Group",
    "wof:placetype":"venue"
},
  "geometry": {"coordinates":[-80.87620699999999,35.805365],"type":"Point"}
}