{
  "type": "Feature",
  "properties": {
    "iso:country":"US",
    "sg:address":"326 Tuckers Grove Rd",
    "sg:city":"Statesville",
    "sg:phone":"+1 704 876 1531",
    "sg:postcode":"28625",
    "sg:province":"NC",
    "sg:tags":[
        "farm",
        "corn"
    ],
    "wof:name":"Grover Johnson Jr",
    "wof:placetype":"venue"
},
  "geometry": {"coordinates":[-80.947619,35.952825],"type":"Point"}
}