{
  "type": "Feature",
  "properties": {
    "iso:country":"US",
    "sg:address":"204 Curtis Dr",
    "sg:city":"Erwin",
    "sg:classifiers":[
        {
            "category":"Manufacturing",
            "subcategory":"Building Materials",
            "type":"Manufacturing & Wholesale Goods"
        }
    ],
    "sg:phone":"+1 910 897 6522",
    "sg:postcode":"28339",
    "sg:province":"NC",
    "sg:tags":[
        "mfg",
        "wood",
        "kitchen",
        "cabinet"
    ],
    "wof:name":"Pryors Cabinets Inc",
    "wof:placetype":"venue"
},
  "geometry": {"coordinates":[-78.712391,35.363079],"type":"Point"}
}