{
  "type": "Feature",
  "properties": {
    "iso:country":"US",
    "sg:address":"43 Vermont Ct",
    "sg:city":"Asheville",
    "sg:classifiers":[
        {
            "category":"Manufacturing",
            "subcategory":"Building Materials",
            "type":"Manufacturing & Wholesale Goods"
        }
    ],
    "sg:phone":"+1 828 281 1077",
    "sg:postcode":"28806",
    "sg:province":"NC",
    "sg:tags":[
        "mfg",
        "wood",
        "kitchen",
        "cabinet"
    ],
    "wof:name":"James Frerotte Cabinetmaker",
    "wof:placetype":"venue"
},
  "geometry": {"coordinates":[-82.599524,35.573767],"type":"Point"}
}