{
  "type": "Feature",
  "properties": {
    "addr:full":"399 Joan Dr Lexington NC 27292",
    "addr:housenumber":"399",
    "addr:postcode":"27292",
    "addr:street":"Joan Dr",
    "iso:country":"US",
    "sg:address":"399 Joan Dr",
    "sg:city":"Lexington",
    "sg:classifiers":[
        {
            "category":"Organizations",
            "subcategory":"Religious Organization",
            "type":"Services"
        }
    ],
    "sg:phone":"+1 336 746 5453",
    "sg:postcode":"27292",
    "sg:province":"NC",
    "sg:tags":[
        "clergy"
    ],
    "wof:name":"Maranatha Bapist",
    "wof:placetype":"venue"
},
  "geometry": {"coordinates":[-80.209672,35.742752],"type":"Point"}
}