{
  "type": "Feature",
  "properties": {
    "addr:full":"4000 Old Lexington Rd Winston Salem NC 27107",
    "addr:housenumber":"4000",
    "addr:postcode":"27107",
    "addr:street":"Old Lexington Rd",
    "iso:country":"US",
    "sg:address":"4000 Old Lexington Rd",
    "sg:city":"Winston Salem",
    "sg:classifiers":[
        {
            "category":"Banks & Credit Unions",
            "subcategory":"Bank",
            "type":"Services"
        }
    ],
    "sg:phone":"+1 336 788 0082",
    "sg:postcode":"27107",
    "sg:province":"NC",
    "sg:tags":[
        "mortgage",
        "loan",
        "broker",
        "real estate"
    ],
    "wof:name":"Seaboard Mortgage Corporation",
    "wof:placetype":"venue"
},
  "geometry": {"coordinates":[-80.21750400000001,36.038024],"type":"Point"}
}