{
  "type": "Feature",
  "properties": {
    "addr:full":"500 Winchester Ave Monroe NC 28110",
    "addr:housenumber":"500",
    "addr:postcode":"28110",
    "addr:street":"Winchester Ave",
    "iso:country":"US",
    "sg:address":"500 Winchester Ave",
    "sg:city":"Monroe",
    "sg:classifiers":[
        {
            "category":"Personal",
            "subcategory":"Barber",
            "type":"Services"
        }
    ],
    "sg:phone":"+1   ",
    "sg:postcode":"28110",
    "sg:province":"NC",
    "sg:tags":[
        "shop"
    ],
    "wof:name":"Esquire Barber Shop",
    "wof:placetype":"venue"
},
  "geometry": {"coordinates":[-80.54434500000001,34.984817],"type":"Point"}
}