{
  "type": "Feature",
  "properties": {
    "iso:country":"US",
    "sg:address":"1012 Starita Ct",
    "sg:city":"Apex",
    "sg:classifiers":[
        {
            "category":"Professional",
            "type":"Services"
        }
    ],
    "sg:phone":"+1   ",
    "sg:postcode":"27502",
    "sg:province":"NC",
    "sg:tags":[
        "communication"
    ],
    "wof:name":"Netphone Services Inc",
    "wof:placetype":"venue"
},
  "geometry": {"coordinates":[-78.90767200000001,35.731363],"type":"Point"}
}