{
  "type": "Feature",
  "properties": {
    "addr:full":"5051 Saint Stephens Church Rd Gold Hill NC 28071",
    "addr:housenumber":"5051",
    "addr:postcode":"28071",
    "addr:street":"Saint;Church Rd",
    "iso:country":"US",
    "sg:address":"5051 Saint Stephens Church Rd",
    "sg:city":"Gold Hill",
    "sg:classifiers":[
        {
            "category":"Building & Trades",
            "subcategory":"Construction",
            "type":"Services"
        },
        {
            "category":"Mining & Drilling",
            "type":"Manufacturing & Wholesale Goods"
        }
    ],
    "sg:phone":"+1 704 279 5309",
    "sg:postcode":"28071",
    "sg:province":"NC",
    "sg:tags":[
        "industrial",
        "grading",
        "trucking",
        "sand",
        "operator",
        "contractor",
        "local"
    ],
    "wof:name":"Hammill Construction Inc",
    "wof:placetype":"venue"
},
  "geometry": {"coordinates":[-80.36728100000001,35.480971],"type":"Point"}
}