{
  "type": "Feature",
  "properties": {
    "addr:full":"3638 State Hwy 16 Maiden NC 28658",
    "addr:housenumber":"3638",
    "addr:postcode":"28658",
    "addr:street":"State Hwy 16",
    "iso:country":"US",
    "sg:address":"3638 State Hwy 16",
    "sg:city":"Maiden",
    "sg:classifiers":[
        {
            "category":"Health Services",
            "subcategory":"Doctor",
            "type":"Services"
        }
    ],
    "sg:phone":"+1 704 483 6136",
    "sg:postcode":"28658",
    "sg:province":"NC",
    "sg:tags":[
        "physician",
        "surgeon"
    ],
    "wof:name":"Carolina Eye Care",
    "wof:placetype":"venue"
},
  "geometry": {"coordinates":[-81.12966900000001,35.616841],"type":"Point"}
}