{
  "type": "Feature",
  "properties": {
    "iso:country":"US",
    "sg:address":"3109 US Hwy 15",
    "sg:city":"Stem",
    "sg:classifiers":[
        {
            "category":"Farming",
            "subcategory":"Livestock Farm",
            "type":"Manufacturing & Wholesale Goods"
        }
    ],
    "sg:phone":"+1 919 528 3004",
    "sg:postcode":"27581",
    "sg:province":"NC",
    "sg:tags":[
        "merchandise",
        "general"
    ],
    "wof:name":"Hester Farm & Equipment Co",
    "wof:placetype":"venue"
},
  "geometry": {"coordinates":[-78.665988,36.181643],"type":"Point"}
}