{
  "type": "Feature",
  "properties": {
    "iso:country":"US",
    "sg:address":"101 E Front St",
    "sg:city":"Lillington",
    "sg:classifiers":[
        {
            "category":"Professional",
            "subcategory":"Lawyer & Legal Services",
            "type":"Services"
        }
    ],
    "sg:phone":"+1 910 893 5131",
    "sg:postcode":"27546",
    "sg:province":"NC",
    "sg:tags":[
        "attorney"
    ],
    "wof:name":"Morgan Reeves & Gilchrist",
    "wof:placetype":"venue"
},
  "geometry": {"coordinates":[-78.814892,35.398389],"type":"Point"}
}