{
  "type": "Feature",
  "properties": {
    "iso:country":"US",
    "sg:address":"70 Weaverville Hwy",
    "sg:city":"Asheville",
    "sg:classifiers":[
        {
            "category":"Personal",
            "subcategory":"Barber",
            "type":"Services"
        }
    ],
    "sg:phone":"+1   ",
    "sg:postcode":"28804",
    "sg:province":"NC",
    "sg:tags":[
        "shop"
    ],
    "wof:name":"North Buncombe Electrolysis",
    "wof:placetype":"venue"
},
  "geometry": {"coordinates":[-82.57859999999999,35.639987],"type":"Point"}
}