{
  "type": "Feature",
  "properties": {
    "addr:full":"109 Union Grove Church Rd Dunn NC 28334",
    "addr:housenumber":"109",
    "addr:postcode":"28334",
    "addr:street":"Union Grove Church Rd",
    "iso:country":"US",
    "sg:address":"109 Union Grove Church Rd",
    "sg:city":"Dunn",
    "sg:classifiers":[
        {
            "category":"Retail",
            "subcategory":"Repair Shop",
            "type":"Services"
        }
    ],
    "sg:phone":"+1   ",
    "sg:postcode":"28334",
    "sg:province":"NC",
    "sg:tags":[
        "welding"
    ],
    "wof:name":"Williams Welding",
    "wof:placetype":"venue"
},
  "geometry": {"coordinates":[-78.553229,35.222131],"type":"Point"}
}