{
  "type": "Feature",
  "properties": {
    "addr:full":"6330 Linda Dr Lewisville NC 27023",
    "addr:housenumber":"6330",
    "addr:postcode":"27023",
    "addr:street":"Linda Dr",
    "iso:country":"US",
    "sg:address":"6330 Linda Dr",
    "sg:city":"Lewisville",
    "sg:classifiers":[
        {
            "category":"Personal",
            "type":"Services"
        }
    ],
    "sg:phone":"+1   ",
    "sg:postcode":"27023",
    "sg:province":"NC",
    "wof:name":"Hawaiian Tanning",
    "wof:placetype":"venue"
},
  "geometry": {"coordinates":[-80.416252,36.10082],"type":"Point"}
}