{
  "type": "Feature",
  "properties": {
    "iso:country":"US",
    "sg:address":"2505 Battery Pl",
    "sg:city":"Wilmington",
    "sg:classifiers":[
        {
            "category":"Organizations",
            "subcategory":"Religious Organization",
            "type":"Services"
        }
    ],
    "sg:phone":"+1   ",
    "sg:postcode":"28403",
    "sg:province":"NC",
    "wof:name":"Way of Cross Deliverance Ctr",
    "wof:placetype":"venue"
},
  "geometry": {"coordinates":[-77.914851,34.228714],"type":"Point"}
}