{
  "type": "Feature",
  "properties": {
    "iso:country":"US",
    "sg:address":"309 Robert St",
    "sg:city":"Cary",
    "sg:classifiers":[
        {
            "category":"Personal",
            "subcategory":"Beauty Salon",
            "type":"Services"
        }
    ],
    "sg:phone":"+1   ",
    "sg:postcode":"27511",
    "sg:province":"NC",
    "sg:tags":[
        "shop"
    ],
    "wof:name":"Natty Affair LLC",
    "wof:placetype":"venue"
},
  "geometry": {"coordinates":[-78.785989,35.782284],"type":"Point"}
}