{
  "type": "Feature",
  "properties": {
    "addr:full":"3003 Buckingham Way Apex NC 27502",
    "addr:housenumber":"3003",
    "addr:postcode":"27502",
    "addr:street":"Buckingham Way",
    "iso:country":"US",
    "sg:address":"3003 Buckingham Way",
    "sg:city":"Apex",
    "sg:classifiers":[
        {
            "category":"Real Estate",
            "subcategory":"Real Estate Agent",
            "type":"Services"
        }
    ],
    "sg:phone":"+1 919 362 0458",
    "sg:postcode":"27502",
    "sg:province":"NC",
    "wof:name":"Carl Banks Realty",
    "wof:placetype":"venue"
},
  "geometry": {"coordinates":[-78.826375,35.734135],"type":"Point"}
}