{
  "type": "Feature",
  "properties": {
    "iso:country":"US",
    "sg:address":"306 Bradsher Rd Ste 806",
    "sg:city":"Hillsborough",
    "sg:classifiers":[
        {
            "category":"Real Estate",
            "subcategory":"Real Estate Agent",
            "type":"Services"
        }
    ],
    "sg:phone":"+1 919 732 3242",
    "sg:postcode":"27278",
    "sg:province":"NC",
    "wof:name":"Stray Dog Farm Inc",
    "wof:placetype":"venue"
},
  "geometry": {"coordinates":[-79.125558,36.168621],"type":"Point"}
}