{
  "type": "Feature",
  "properties": {
    "iso:country":"US",
    "sg:address":"234 Orange Grove St",
    "sg:city":"Hillsborough",
    "sg:classifiers":[
        {
            "category":"Health Services",
            "subcategory":"Hospital",
            "type":"Services"
        }
    ],
    "sg:phone":"+1 919 732 5167",
    "sg:postcode":"27278",
    "sg:province":"NC",
    "sg:tags":[
        "mental"
    ],
    "wof:name":"TASCOPC Mental Health",
    "wof:placetype":"venue"
},
  "geometry": {"coordinates":[-79.099765,36.065492],"type":"Point"}
}