{
  "type": "Feature",
  "properties": {
    "addr:full":"1 Weaverville Rd Asheville NC 28804",
    "addr:housenumber":"1",
    "addr:postcode":"28804",
    "addr:street":"Weaverville Rd",
    "iso:country":"US",
    "sg:address":"1 Weaverville Rd",
    "sg:city":"Asheville",
    "sg:classifiers":[
        {
            "category":"Manufacturing",
            "subcategory":"Motor Vehicles & Parts",
            "type":"Manufacturing & Wholesale Goods"
        }
    ],
    "sg:phone":"+1 828 645 9553",
    "sg:postcode":"28804",
    "sg:province":"NC",
    "sg:tags":[
        "automobile",
        "supply"
    ],
    "wof:name":"Cannon Racks & Axles",
    "wof:placetype":"venue"
},
  "geometry": {"coordinates":[-82.576616,35.638922],"type":"Point"}
}