{
  "type": "Feature",
  "properties": {
    "addr:full":"3525 Matthews Mint Hill Rd Matthews NC 28105",
    "addr:housenumber":"3525",
    "addr:postcode":"28105",
    "addr:street":"Matthews Mint Hill Rd",
    "iso:country":"US",
    "sg:address":"3525 Matthews Mint Hill Rd",
    "sg:city":"Matthews",
    "sg:classifiers":[
        {
            "category":"Health Services",
            "subcategory":"Health Practitioner",
            "type":"Services"
        },
        {
            "category":"Health Services",
            "subcategory":"Chiropractor",
            "type":"Services"
        }
    ],
    "sg:phone":"+1 704 847 3335",
    "sg:postcode":"28105",
    "sg:province":"NC",
    "sg:tags":[
        "acupuncture",
        "medicine",
        "alternative",
        "chiropractic"
    ],
    "wof:name":"Idlewild Chiropractic",
    "wof:placetype":"venue"
},
  "geometry": {"coordinates":[-80.683266,35.137521],"type":"Point"}
}