{
  "type": "Feature",
  "properties": {
    "iso:country":"US",
    "sg:address":"109 S Market St",
    "sg:city":"Madison",
    "sg:classifiers":[
        {
            "category":"Shopping",
            "subcategory":"Clothing, Apparel, & Fashions",
            "type":"Retail Goods"
        }
    ],
    "sg:phone":"+1 336 427 2934",
    "sg:postcode":"27025",
    "sg:province":"NC",
    "wof:name":"Kay's Boutique",
    "wof:placetype":"venue"
},
  "geometry": {"coordinates":[-79.959551,36.387442],"type":"Point"}
}