{
  "type": "Feature",
  "properties": {
    "addr:full":"424 Petersburg Rd Richlands NC 28574",
    "addr:housenumber":"424",
    "addr:postcode":"28574",
    "addr:street":"Petersburg Rd",
    "iso:country":"US",
    "sg:address":"424 Petersburg Rd",
    "sg:city":"Richlands",
    "sg:classifiers":[
        {
            "category":"Manufacturing",
            "subcategory":"Tools & Machinery",
            "type":"Manufacturing & Wholesale Goods"
        }
    ],
    "sg:phone":"+1 910 324 4100",
    "sg:postcode":"28574",
    "sg:province":"NC",
    "sg:tags":[
        "industry",
        "mfg"
    ],
    "wof:name":"Automotive Craftsman Inc",
    "wof:placetype":"venue"
},
  "geometry": {"coordinates":[-77.527417,34.926381],"type":"Point"}
}