{
  "type": "Feature",
  "properties": {
    "iso:country":"US",
    "sg:address":"1400 Buffaloe St",
    "sg:city":"Roanoke Rapids",
    "sg:classifiers":[
        {
            "category":"Autos & Motor Vehicles",
            "subcategory":"Automobile Sales",
            "type":"Retail Goods"
        }
    ],
    "sg:phone":"+1 252 537 3729",
    "sg:postcode":"27870",
    "sg:province":"NC",
    "sg:tags":[
        "repair",
        "truck"
    ],
    "wof:name":"Shortys Truck Repair Inc",
    "wof:placetype":"venue"
},
  "geometry": {"coordinates":[-77.646637,36.439606],"type":"Point"}
}