{
  "type": "Feature",
  "properties": {
    "iso:country":"US",
    "sg:address":"2313 S Memorial Dr",
    "sg:city":"Greenville",
    "sg:classifiers":[
        {
            "category":"Professional",
            "type":"Services"
        }
    ],
    "sg:phone":"+1 252 355 9199",
    "sg:postcode":"27834",
    "sg:province":"NC",
    "wof:name":"Demo House",
    "wof:placetype":"venue"
},
  "geometry": {"coordinates":[-77.39530999999999,35.596945],"type":"Point"}
}