{
  "type": "Feature",
  "properties": {
    "addr:full":"2150 Country Club Rd Winston Salem NC 27104",
    "addr:housenumber":"2150",
    "addr:postcode":"27104",
    "addr:street":"Country Club Rd",
    "iso:country":"US",
    "sg:address":"2150 Country Club Rd",
    "sg:city":"Winston Salem",
    "sg:classifiers":[
        {
            "category":"Banks & Credit Unions",
            "subcategory":"Investment Brokerage",
            "type":"Services"
        }
    ],
    "sg:phone":"+1 336 631 5617",
    "sg:postcode":"27104",
    "sg:province":"NC",
    "sg:tags":[
        "stock",
        "bond"
    ],
    "wof:name":"Rbc Dain Rauscher",
    "wof:placetype":"venue"
},
  "geometry": {"coordinates":[-80.27768500000001,36.097129],"type":"Point"}
}