{
  "type": "Feature",
  "properties": {
    "iso:country":"US",
    "sg:address":"5960 Concord Pkwy S",
    "sg:city":"Harrisburg",
    "sg:classifiers":[
        {
            "category":"Building & Trades",
            "subcategory":"Construction",
            "type":"Services"
        }
    ],
    "sg:phone":"+1 704 454 7294",
    "sg:postcode":"28027",
    "sg:province":"NC",
    "sg:tags":[
        "contractor"
    ],
    "wof:name":"Sealand Contractors",
    "wof:placetype":"venue"
},
  "geometry": {"coordinates":[-80.692694,35.347707],"type":"Point"}
}