{
  "type": "Feature",
  "properties": {
    "addr:full":"215 W Walnut St Goldsboro NC 27530",
    "addr:housenumber":"215",
    "addr:postcode":"27530",
    "addr:street":"W Walnut St",
    "iso:country":"US",
    "sg:address":"215 W Walnut St",
    "sg:city":"Goldsboro",
    "sg:classifiers":[
        {
            "category":"Shopping",
            "subcategory":"Clothing, Apparel, & Fashions",
            "type":"Retail Goods"
        }
    ],
    "sg:phone":"+1 919 735 5522",
    "sg:postcode":"27530",
    "sg:province":"NC",
    "sg:tags":[
        "shop",
        "tuxedo",
        "wear",
        "bridal",
        "rental",
        "formal"
    ],
    "wof:name":"Aries Formal Wear",
    "wof:placetype":"venue"
},
  "geometry": {"coordinates":[-78.000005,35.383973],"type":"Point"}
}