{
  "type": "Feature",
  "properties": {
    "iso:country":"US",
    "sg:address":"3351 Godwin Lake Rd",
    "sg:city":"Benson",
    "sg:classifiers":[
        {
            "category":"Farming",
            "subcategory":"Farm",
            "type":"Manufacturing & Wholesale Goods"
        }
    ],
    "sg:phone":"+1 919 894 3335",
    "sg:postcode":"27504",
    "sg:province":"NC",
    "sg:tags":[
        "general"
    ],
    "wof:name":"Max Lee Farms",
    "wof:placetype":"venue"
},
  "geometry": {"coordinates":[-78.450115,35.305578],"type":"Point"}
}