{
  "type": "Feature",
  "properties": {
    "addr:full":"2608 S Ridge Ave Concord NC 28025",
    "addr:housenumber":"2608",
    "addr:postcode":"28025",
    "addr:street":"S Ridge Ave",
    "iso:country":"US",
    "sg:address":"2608 S Ridge Ave",
    "sg:city":"Concord",
    "sg:classifiers":[
        {
            "category":"Freight",
            "type":"Transportation"
        }
    ],
    "sg:phone":"+1 704 786 5140",
    "sg:postcode":"28025",
    "sg:province":"NC",
    "sg:tags":[
        "packing",
        "crating"
    ],
    "wof:name":"Movers Support Svc Inc",
    "wof:placetype":"venue"
},
  "geometry": {"coordinates":[-80.61771299999999,35.459414],"type":"Point"}
}