{
  "type": "Feature",
  "properties": {
    "addr:full":"3521 Stancliff Rd Clemmons NC 27012",
    "addr:housenumber":"3521",
    "addr:postcode":"27012",
    "addr:street":"Stancliff Rd",
    "iso:country":"US",
    "sg:address":"3521 Stancliff Rd",
    "sg:city":"Clemmons",
    "sg:classifiers":[
        {
            "category":"Communications",
            "subcategory":"Film & Video Production",
            "type":"Services"
        }
    ],
    "sg:phone":"+1   ",
    "sg:postcode":"27012",
    "sg:province":"NC",
    "sg:tags":[
        "motion"
    ],
    "wof:name":"Last Chance Productions",
    "wof:placetype":"venue"
},
  "geometry": {"coordinates":[-80.390957,36.001393],"type":"Point"}
}