{
  "type": "Feature",
  "properties": {
    "iso:country":"US",
    "sg:address":"106 Courthouse Dr",
    "sg:city":"Elizabethtown",
    "sg:classifiers":[
        {
            "category":"Government",
            "subcategory":"Court House",
            "type":"Public Place"
        }
    ],
    "sg:phone":"+1 910 862 4911",
    "sg:postcode":"28337",
    "sg:province":"NC",
    "sg:tags":[
        "county"
    ],
    "wof:name":"District Court Clerk's Ofc",
    "wof:placetype":"venue"
},
  "geometry": {"coordinates":[-78.605611,34.627466],"type":"Point"}
}