{
  "type": "Feature",
  "properties": {
    "iso:country":"US",
    "sg:address":"914 Davis Ave",
    "sg:city":"Gastonia",
    "sg:classifiers":[
        {
            "category":"Real Estate",
            "subcategory":"Real Estate Operator",
            "type":"Services"
        }
    ],
    "sg:phone":"+1 704 867 4399",
    "sg:postcode":"28054",
    "sg:province":"NC",
    "sg:tags":[
        "sub",
        "lessor"
    ],
    "wof:name":"Gaston Community Development",
    "wof:placetype":"venue"
},
  "geometry": {"coordinates":[-81.16515200000001,35.263954],"type":"Point"}
}