{
  "type": "Feature",
  "properties": {
    "addr:full":"1570 Pell Rd Westfield NC 27053",
    "addr:housenumber":"1570",
    "addr:postcode":"27053",
    "addr:street":"Pell Rd",
    "iso:country":"US",
    "sg:address":"1570 Pell Rd",
    "sg:city":"Westfield",
    "sg:classifiers":[
        {
            "category":"Building & Trades",
            "subcategory":"Construction",
            "type":"Services"
        }
    ],
    "sg:phone":"+1 336 351 4108",
    "sg:postcode":"27053",
    "sg:province":"NC",
    "sg:tags":[
        "contractor"
    ],
    "wof:name":"Samco Construction Inc",
    "wof:placetype":"venue"
},
  "geometry": {"coordinates":[-80.422276,36.4583],"type":"Point"}
}