{
  "type": "Feature",
  "properties": {
    "iso:country":"US",
    "sg:address":"2441 Norwood St SW",
    "sg:city":"Lenoir",
    "sg:classifiers":[
        {
            "category":"Restaurant",
            "type":"Food & Drink"
        }
    ],
    "sg:phone":"+1 828 726 0026",
    "sg:postcode":"28645",
    "sg:province":"NC",
    "wof:name":"Mama Nance",
    "wof:placetype":"venue"
},
  "geometry": {"coordinates":[-81.51117000000001,35.870452],"type":"Point"}
}