{
  "type": "Feature",
  "properties": {
    "iso:country":"US",
    "sg:address":"10700 Sikes Pl",
    "sg:city":"Charlotte",
    "sg:classifiers":[
        {
            "category":"Building & Trades",
            "subcategory":"Construction",
            "type":"Services"
        }
    ],
    "sg:phone":"+1 704 321 3392",
    "sg:postcode":"28277",
    "sg:province":"NC",
    "sg:tags":[
        "contractor"
    ],
    "wof:name":"Merrcal Builders LLC",
    "wof:placetype":"venue"
},
  "geometry": {"coordinates":[-80.76847600000001,35.062022],"type":"Point"}
}