{
  "type": "Feature",
  "properties": {
    "addr:full":"4203 Ella St Charlotte NC 28206",
    "addr:housenumber":"4203",
    "addr:postcode":"28206",
    "addr:street":"Ella St",
    "iso:country":"US",
    "sg:address":"4203 Ella St",
    "sg:city":"Charlotte",
    "sg:classifiers":[
        {
            "category":"Building & Trades",
            "subcategory":"Plumbing",
            "type":"Services"
        }
    ],
    "sg:phone":"+1 704 598 2900",
    "sg:postcode":"28206",
    "sg:province":"NC",
    "sg:tags":[
        "plumbing",
        "contractor"
    ],
    "sg:website":"www.rapidrooternc.com",
    "wof:name":"Rapid Rooter",
    "wof:placetype":"venue"
},
  "geometry": {"coordinates":[-80.81537400000001,35.275394],"type":"Point"}
}