{
  "type": "Feature",
  "properties": {
    "iso:country":"US",
    "sg:address":"110 Loves Creek Church Rd",
    "sg:city":"Siler City",
    "sg:classifiers":[
        {
            "category":"Retail",
            "subcategory":"Car Wash",
            "type":"Services"
        }
    ],
    "sg:phone":"+1 919 742 2619",
    "sg:postcode":"27344",
    "sg:province":"NC",
    "sg:tags":[
        "truck",
        "cleaning"
    ],
    "wof:name":"Wet Spot",
    "wof:placetype":"venue"
},
  "geometry": {"coordinates":[-79.433852,35.735438],"type":"Point"}
}