{
  "type": "Feature",
  "properties": {
    "iso:country":"US",
    "sg:address":"106 Willis Rd",
    "sg:city":"Canton",
    "sg:classifiers":[
        {
            "category":"Freight",
            "type":"Transportation"
        }
    ],
    "sg:phone":"+1 828 400 1715",
    "sg:postcode":"28716",
    "sg:province":"NC",
    "sg:tags":[
        "commercial",
        "storage"
    ],
    "wof:name":"J & R Storage Rentals",
    "wof:placetype":"venue"
},
  "geometry": {"coordinates":[-82.848567,35.557889],"type":"Point"}
}