{
  "type": "Feature",
  "properties": {
    "iso:country":"US",
    "sg:address":"1309 Annapolis Dr",
    "sg:city":"Raleigh",
    "sg:classifiers":[
        {
            "category":"Government",
            "subcategory":"Office",
            "type":"Public Place"
        }
    ],
    "sg:phone":"+1 919 856 4064",
    "sg:postcode":"27608",
    "sg:province":"NC",
    "sg:tags":[
        "federal",
        "human"
    ],
    "wof:name":"US Equal Employment Opportunty",
    "wof:placetype":"venue"
},
  "geometry": {"coordinates":[-78.65817800000001,35.799217],"type":"Point"}
}