{
  "type": "Feature",
  "properties": {
    "iso:country":"US",
    "sg:address":"215 Sand Ridge Rd",
    "sg:city":"Hubert",
    "sg:classifiers":[
        {
            "category":"Building & Trades",
            "subcategory":"Construction",
            "type":"Services"
        }
    ],
    "sg:phone":"+1 910 326 5566",
    "sg:postcode":"28539",
    "sg:province":"NC",
    "sg:tags":[
        "industrial"
    ],
    "wof:name":"Rust Construction",
    "wof:placetype":"venue"
},
  "geometry": {"coordinates":[-77.22669500000001,34.702604],"type":"Point"}
}