{
  "type": "Feature",
  "properties": {
    "iso:country":"US",
    "sg:address":"2611 Lavista Dr",
    "sg:city":"Burlington",
    "sg:classifiers":[
        {
            "category":"Professional",
            "type":"Services"
        }
    ],
    "sg:phone":"+1 336 228 6251",
    "sg:postcode":"27215",
    "sg:province":"NC",
    "wof:name":"Impact Fulfilment Svc Inc",
    "wof:placetype":"venue"
},
  "geometry": {"coordinates":[-79.423461,36.063894],"type":"Point"}
}