{
  "type": "Feature",
  "properties": {
    "addr:full":"1480 Harbour Dr Wilmington NC 28401",
    "addr:housenumber":"1480",
    "addr:postcode":"28401",
    "addr:street":"Harbour Dr",
    "iso:country":"US",
    "sg:address":"1480 Harbour Dr",
    "sg:city":"Wilmington",
    "sg:classifiers":[
        {
            "category":"Government",
            "subcategory":"Office",
            "type":"Public Place"
        }
    ],
    "sg:phone":"+1 910 395 4553",
    "sg:postcode":"28401",
    "sg:province":"NC",
    "wof:name":"Capefear Counsel Govenments",
    "wof:placetype":"venue"
},
  "geometry": {"coordinates":[-77.92227800000001,34.196845],"type":"Point"}
}