{
  "type": "Feature",
  "properties": {
    "iso:country":"US",
    "sg:address":"2106 Neuse Blvd",
    "sg:city":"New Bern",
    "sg:classifiers":[
        {
            "category":"Government",
            "subcategory":"Office",
            "type":"Public Place"
        }
    ],
    "sg:phone":"+1 252 514 4734",
    "sg:postcode":"28560",
    "sg:province":"NC",
    "sg:tags":[
        "state",
        "program"
    ],
    "wof:name":"Drivers License Ofc",
    "wof:placetype":"venue"
},
  "geometry": {"coordinates":[-77.07013499999999,35.114024],"type":"Point"}
}