{
  "type": "Feature",
  "properties": {
    "addr:full":"125 Doral Dr Pinehurst NC 28374",
    "addr:housenumber":"125",
    "addr:postcode":"28374",
    "addr:street":"Doral Dr",
    "iso:country":"US",
    "sg:address":"125 Doral Dr",
    "sg:city":"Pinehurst",
    "sg:classifiers":[
        {
            "category":"Real Estate",
            "subcategory":"Real Estate Agent",
            "type":"Services"
        }
    ],
    "sg:phone":"+1 910 673 1724",
    "sg:postcode":"28374",
    "sg:province":"NC",
    "wof:name":"Century 21",
    "wof:placetype":"venue"
},
  "geometry": {"coordinates":[-79.46202,35.180229],"type":"Point"}
}