{
  "type": "Feature",
  "properties": {
    "addr:full":"5042 Morrowick Rd Charlotte NC 28226",
    "addr:housenumber":"5042",
    "addr:postcode":"28226",
    "addr:street":"Morrowick Rd",
    "iso:country":"US",
    "sg:address":"5042 Morrowick Rd",
    "sg:city":"Charlotte",
    "sg:classifiers":[
        {
            "category":"Professional",
            "subcategory":"Management & Consulting",
            "type":"Services"
        }
    ],
    "sg:phone":"+1   ",
    "sg:postcode":"28226",
    "sg:province":"NC",
    "wof:name":"Healthcare Prfmce Solutions",
    "wof:placetype":"venue"
},
  "geometry": {"coordinates":[-80.81039199999999,35.114126],"type":"Point"}
}