{
  "type": "Feature",
  "properties": {
    "iso:country":"US",
    "sg:address":"3801 Rose Lake Dr",
    "sg:city":"Charlotte",
    "sg:classifiers":[
        {
            "category":"Wholesale",
            "subcategory":"Computers",
            "type":"Manufacturing & Wholesale Goods"
        }
    ],
    "sg:phone":"+1 704 329 8096",
    "sg:postcode":"28217",
    "sg:province":"NC",
    "sg:website":"www.fsiinc.com",
    "wof:name":"Fortress Systems International",
    "wof:placetype":"venue"
},
  "geometry": {"coordinates":[-80.925675,35.177483],"type":"Point"}
}