{
  "type": "Feature",
  "properties": {
    "addr:full":"2100 Gateway Centre Blvd. Suite 150 Morrisville NC 27560",
    "addr:housenumber":"2100",
    "addr:postcode":"27560",
    "addr:street":"Gateway Centre Blvd. Suite 150",
    "iso:country":"US",
    "sg:address":"2100 Gateway Centre Blvd. Suite 150",
    "sg:city":"Morrisville",
    "sg:classifiers":[
        {
            "category":"Professional",
            "subcategory":"Computer Services",
            "type":"Services"
        }
    ],
    "sg:phone":"+1 919 228 2100",
    "sg:postcode":"27560",
    "sg:province":"NC",
    "sg:website":"http://www.radarfind.com",
    "wof:name":"RadarFind",
    "wof:placetype":"venue"
},
  "geometry": {"coordinates":[-78.801221,35.845632],"type":"Point"}
}