{
  "type": "Feature",
  "properties": {
    "iso:country":"US",
    "sg:address":"2235 Bear Wallow Rd",
    "sg:city":"Lansing",
    "sg:classifiers":[
        {
            "category":"Building & Trades",
            "subcategory":"Construction",
            "type":"Services"
        }
    ],
    "sg:phone":"+1 336 384 1000",
    "sg:postcode":"28643",
    "sg:province":"NC",
    "sg:tags":[
        "masonry",
        "contractor"
    ],
    "wof:name":"Cherokee Masonry Inc",
    "wof:placetype":"venue"
},
  "geometry": {"coordinates":[-81.54186799999999,36.58096],"type":"Point"}
}