{
  "type": "Feature",
  "properties": {
    "iso:country":"US",
    "sg:address":"3588 W Thollie Green Rd",
    "sg:city":"Stem",
    "sg:classifiers":[
        {
            "category":"Arena",
            "subcategory":"Sports Club",
            "type":"Entertainment"
        }
    ],
    "sg:phone":"+1 919 528 4927",
    "sg:postcode":"27581",
    "sg:province":"NC",
    "sg:tags":[
        "martial art"
    ],
    "wof:name":"Hansley Perry & Pam",
    "wof:placetype":"venue"
},
  "geometry": {"coordinates":[-78.68589799999999,36.202301],"type":"Point"}
}