{
  "type": "Feature",
  "properties": {
    "addr:full":"44188 Dennis Rd Albemarle NC 28001",
    "addr:housenumber":"44188",
    "addr:postcode":"28001",
    "addr:street":"Dennis Rd",
    "iso:country":"US",
    "sg:address":"44188 Dennis Rd",
    "sg:city":"Albemarle",
    "sg:classifiers":[
        {
            "category":"Farming",
            "subcategory":"Dairy Farm",
            "type":"Manufacturing & Wholesale Goods"
        }
    ],
    "sg:phone":"+1 704 982 9887",
    "sg:postcode":"28001",
    "sg:province":"NC",
    "wof:name":"Dennis Farm Inc",
    "wof:placetype":"venue"
},
  "geometry": {"coordinates":[-80.12777,35.280315],"type":"Point"}
}