{
  "type": "Feature",
  "properties": {
    "addr:full":"189 Broadway St Rockingham NC 28379",
    "addr:housenumber":"189",
    "addr:postcode":"28379",
    "addr:street":"Broadway St",
    "iso:country":"US",
    "sg:address":"189 Broadway St",
    "sg:city":"Rockingham",
    "sg:classifiers":[
        {
            "category":"Building & Trades",
            "subcategory":"Electrical",
            "type":"Services"
        }
    ],
    "sg:phone":"+1 910 206 9899",
    "sg:postcode":"28379",
    "sg:province":"NC",
    "sg:tags":[
        "contracting",
        "electrical"
    ],
    "wof:name":"Claude Dailey Electric",
    "wof:placetype":"venue"
},
  "geometry": {"coordinates":[-79.776222,34.919878],"type":"Point"}
}