{
  "type": "Feature",
  "properties": {
    "iso:country":"US",
    "sg:address":"1717 Glengate Cir",
    "sg:city":"Morrisville",
    "sg:classifiers":[
        {
            "category":"Professional",
            "subcategory":"Accounting & Tax Preparation",
            "type":"Services"
        }
    ],
    "sg:phone":"+1 919 678 8080",
    "sg:postcode":"27560",
    "sg:province":"NC",
    "sg:tags":[
        "billing"
    ],
    "wof:name":"Lakeside Medical Billing",
    "wof:placetype":"venue"
},
  "geometry": {"coordinates":[-78.81978100000001,35.817061],"type":"Point"}
}