{
  "type": "Feature",
  "properties": {
    "addr:full":"5830 Casar Rd Casar NC 28020",
    "addr:housenumber":"5830",
    "addr:postcode":"28020",
    "addr:street":"Casar Rd",
    "iso:country":"US",
    "sg:address":"5830 Casar Rd",
    "sg:city":"Casar",
    "sg:classifiers":[
        {
            "category":"Personal",
            "subcategory":"Tanning Parlor",
            "type":"Services"
        }
    ],
    "sg:phone":"+1 704 538 9400",
    "sg:postcode":"28020",
    "sg:province":"NC",
    "sg:tags":[
        "salon"
    ],
    "wof:name":"Suntouch Tanning & Accessories",
    "wof:placetype":"venue"
},
  "geometry": {"coordinates":[-81.61320600000001,35.516715],"type":"Point"}
}