{
  "type": "Feature",
  "properties": {
    "iso:country":"US",
    "sg:address":"2307 Burnett Blvd",
    "sg:city":"Wilmington",
    "sg:classifiers":[
        {
            "category":"Travel",
            "subcategory":"Travel Agent",
            "type":"Entertainment"
        }
    ],
    "sg:phone":"+1 910 763 8493",
    "sg:postcode":"28401",
    "sg:province":"NC",
    "sg:tags":[
        "agency",
        "steamship"
    ],
    "wof:name":"Waterfront Services Inc",
    "wof:placetype":"venue"
},
  "geometry": {"coordinates":[-77.947537,34.193014],"type":"Point"}
}