{
  "type": "Feature",
  "properties": {
    "addr:full":"3133 Cedar Park Rd Greensboro NC 27405",
    "addr:housenumber":"3133",
    "addr:postcode":"27405",
    "addr:street":"Cedar Park Rd",
    "iso:country":"US",
    "sg:address":"3133 Cedar Park Rd",
    "sg:city":"Greensboro",
    "sg:classifiers":[
        {
            "category":"Building & Trades",
            "subcategory":"Equipment Rental",
            "type":"Services"
        }
    ],
    "sg:phone":"+1 336 697 9200",
    "sg:postcode":"27405",
    "sg:province":"NC",
    "sg:tags":[
        "heavy",
        "construction",
        "r",
        "yard"
    ],
    "sg:website":"www.ur.com",
    "wof:name":"United Rentals",
    "wof:placetype":"venue"
},
  "geometry": {"coordinates":[-79.733445,36.052667],"type":"Point"}
}