{
  "type": "Feature",
  "properties": {
    "iso:country":"US",
    "sg:address":"4109 Trelawney Ct",
    "sg:city":"Hope Mills",
    "sg:classifiers":[
        {
            "category":"Professional",
            "subcategory":"Management & Consulting",
            "type":"Services"
        }
    ],
    "sg:phone":"+1   ",
    "sg:postcode":"28348",
    "sg:province":"NC",
    "sg:tags":[
        "translation"
    ],
    "wof:name":"Foreign Language Services",
    "wof:placetype":"venue"
},
  "geometry": {"coordinates":[-78.973389,34.958754],"type":"Point"}
}