{
  "type": "Feature",
  "properties": {
    "iso:country":"US",
    "sg:address":"129 S Main St",
    "sg:city":"Broadway",
    "sg:classifiers":[
        {
            "category":"Retail",
            "subcategory":"Auto Repair",
            "type":"Services"
        }
    ],
    "sg:phone":"+1 919 258 6621",
    "sg:postcode":"27505",
    "sg:province":"NC",
    "sg:tags":[
        "body",
        "automobile",
        "painting"
    ],
    "wof:name":"Claude's Paint & Body Shop",
    "wof:placetype":"venue"
},
  "geometry": {"coordinates":[-79.052447,35.455878],"type":"Point"}
}