{
  "type": "Feature",
  "properties": {
    "iso:country":"US",
    "sg:address":"1480 US Hwy 29 N",
    "sg:city":"Concord",
    "sg:classifiers":[
        {
            "category":"Shopping",
            "subcategory":"Jewelry",
            "type":"Retail Goods"
        }
    ],
    "sg:phone":"+1 704 723 6927",
    "sg:postcode":"28025",
    "sg:province":"NC",
    "wof:name":"Piercing Pagoda",
    "wof:placetype":"venue"
},
  "geometry": {"coordinates":[-80.60532499999999,35.438503],"type":"Point"}
}