{
  "type": "Feature",
  "properties": {
    "iso:country":"US",
    "sg:address":"2111 Cedar Creek Rd",
    "sg:city":"Fayetteville",
    "sg:classifiers":[
        {
            "category":"Restaurant",
            "type":"Food & Drink"
        }
    ],
    "sg:phone":"+1 910 485 0038",
    "sg:postcode":"28312",
    "sg:province":"NC",
    "wof:name":"Steves Sports Bar & Grill",
    "wof:placetype":"venue"
},
  "geometry": {"coordinates":[-78.817785,35.007004],"type":"Point"}
}