{
  "type": "Feature",
  "properties": {
    "addr:full":"317 US Hwy 70 E Garner NC 27529",
    "addr:housenumber":"317",
    "addr:postcode":"27529",
    "addr:street":"Us Hwy 70 E",
    "iso:country":"US",
    "sg:address":"317 US Hwy 70 E",
    "sg:city":"Garner",
    "sg:classifiers":[
        {
            "category":"Restaurant",
            "type":"Food & Drink"
        }
    ],
    "sg:phone":"+1 919 773 1222",
    "sg:postcode":"27529",
    "sg:province":"NC",
    "sg:tags":[
        "eating"
    ],
    "wof:name":"Pure Gold",
    "wof:placetype":"venue"
},
  "geometry": {"coordinates":[-78.59882399999999,35.701225],"type":"Point"}
}