{
  "type": "Feature",
  "properties": {
    "iso:country":"US",
    "sg:address":"40 Odell School Rd",
    "sg:city":"Concord",
    "sg:classifiers":[
        {
            "category":"Professional",
            "subcategory":"Engineering",
            "type":"Services"
        }
    ],
    "sg:phone":"+1 704 784 2025",
    "sg:postcode":"28027",
    "sg:province":"NC",
    "sg:tags":[
        "engineer"
    ],
    "wof:name":"Apex Engineering PC",
    "wof:placetype":"venue"
},
  "geometry": {"coordinates":[-80.709614,35.41319],"type":"Point"}
}