{
  "type": "Feature",
  "properties": {
    "iso:country":"US",
    "sg:address":"1501 N Chester St",
    "sg:city":"Gastonia",
    "sg:classifiers":[
        {
            "category":"Home & Garden",
            "subcategory":"Building Materials",
            "type":"Retail Goods"
        }
    ],
    "sg:phone":"+1 704 869 6299",
    "sg:postcode":"28052",
    "sg:province":"NC",
    "sg:tags":[
        "glass",
        "window",
        "plate"
    ],
    "wof:name":"Eastern Glass Co",
    "wof:placetype":"venue"
},
  "geometry": {"coordinates":[-81.187855,35.281462],"type":"Point"}
}