{
  "type": "Feature",
  "properties": {
    "iso:country":"US",
    "sg:address":"4309 Burlington Rd",
    "sg:city":"Greensboro",
    "sg:classifiers":[
        {
            "category":"Building & Trades",
            "subcategory":"Construction",
            "type":"Services"
        }
    ],
    "sg:phone":"+1 336 621 1020",
    "sg:postcode":"27405",
    "sg:province":"NC",
    "sg:tags":[
        "contractor"
    ],
    "wof:name":"C A I Stair Shop",
    "wof:placetype":"venue"
},
  "geometry": {"coordinates":[-79.705646,36.088094],"type":"Point"}
}