{
  "type": "Feature",
  "properties": {
    "addr:full":"4406 High Meadow Ln Wilson NC 27896",
    "addr:housenumber":"4406",
    "addr:postcode":"27896",
    "addr:street":"High Meadow Ln",
    "iso:country":"US",
    "sg:address":"4406 High Meadow Ln",
    "sg:city":"Wilson",
    "sg:classifiers":[
        {
            "category":"Professional",
            "type":"Services"
        }
    ],
    "sg:phone":"+1 252 291 2473",
    "sg:postcode":"27896",
    "sg:province":"NC",
    "wof:name":"David Hobgood",
    "wof:placetype":"venue"
},
  "geometry": {"coordinates":[-77.93207700000001,35.781323],"type":"Point"}
}