{
  "type": "Feature",
  "properties": {
    "addr:full":"5720 General Industrial Dr Charlotte NC 28213",
    "addr:housenumber":"5720",
    "addr:postcode":"28213",
    "addr:street":"General Industrial Dr",
    "iso:country":"US",
    "sg:address":"5720 General Industrial Dr",
    "sg:city":"Charlotte",
    "sg:classifiers":[
        {
            "category":"Building & Trades",
            "subcategory":"Landscaping Services",
            "type":"Services"
        }
    ],
    "sg:phone":"+1 704 599 2500",
    "sg:postcode":"28213",
    "sg:province":"NC",
    "sg:tags":[
        "consultant",
        "designer",
        "landscape",
        "contractor"
    ],
    "sg:website":"http://www.realpagessites.com/gwloobylandscaping",
    "wof:name":"Looby Landscaping Inc",
    "wof:placetype":"venue"
},
  "geometry": {"coordinates":[-80.76708600000001,35.258666],"type":"Point"}
}