{
  "type": "Feature",
  "properties": {
    "iso:country":"US",
    "sg:address":"471 Brandermill Rd",
    "sg:city":"Fayetteville",
    "sg:classifiers":[
        {
            "category":"Building & Trades",
            "subcategory":"Electrical",
            "type":"Services"
        }
    ],
    "sg:phone":"+1 910 483 5935",
    "sg:postcode":"28314",
    "sg:province":"NC",
    "sg:tags":[
        "electric",
        "contractor"
    ],
    "wof:name":"Al Russell Electric Svc",
    "wof:placetype":"venue"
},
  "geometry": {"coordinates":[-78.98415,35.058563],"type":"Point"}
}