{
  "type": "Feature",
  "properties": {
    "addr:full":"5513 Bridgeview Dr Greensboro NC 27406",
    "addr:housenumber":"5513",
    "addr:postcode":"27406",
    "addr:street":"Bridgeview Dr",
    "iso:country":"US",
    "sg:address":"5513 Bridgeview Dr",
    "sg:city":"Greensboro",
    "sg:classifiers":[
        {
            "category":"Shopping",
            "subcategory":"Computers & Home Electronics",
            "type":"Retail Goods"
        }
    ],
    "sg:phone":"+1 336 549 4588",
    "sg:postcode":"27406",
    "sg:province":"NC",
    "sg:tags":[
        "equipment",
        "dealer"
    ],
    "wof:name":"CBM Computer Finance",
    "wof:placetype":"venue"
},
  "geometry": {"coordinates":[-79.799504,35.976464],"type":"Point"}
}