{
  "type": "Feature",
  "properties": {
    "addr:full":"2316 Danbury Rd Greensboro NC 27408",
    "addr:housenumber":"2316",
    "addr:postcode":"27408",
    "addr:street":"Danbury Rd",
    "iso:country":"US",
    "sg:address":"2316 Danbury Rd",
    "sg:city":"Greensboro",
    "sg:classifiers":[
        {
            "category":"Insurance",
            "subcategory":"Insurance Agent",
            "type":"Services"
        }
    ],
    "sg:phone":"+1 336 272 2988",
    "sg:postcode":"27408",
    "sg:province":"NC",
    "wof:name":"Louis P Godwin Insurance",
    "wof:placetype":"venue"
},
  "geometry": {"coordinates":[-79.791256,36.107628],"type":"Point"}
}