{
  "type": "Feature",
  "properties": {
    "addr:full":"6100 E Independence Blvd Charlotte NC 28212",
    "addr:housenumber":"6100",
    "addr:postcode":"28212",
    "addr:street":"E Independence Blvd",
    "iso:country":"US",
    "sg:address":"6100 E Independence Blvd",
    "sg:city":"Charlotte",
    "sg:classifiers":[
        {
            "category":"Shopping",
            "subcategory":"Hobbies, Toys, & Games",
            "type":"Retail Goods"
        }
    ],
    "sg:phone":"+1 704 568 4914",
    "sg:postcode":"28212",
    "sg:province":"NC",
    "sg:website":"http://www.toysrus.com",
    "wof:name":"Toys R Us",
    "wof:placetype":"venue"
},
  "geometry": {"coordinates":[-80.75122399999999,35.17774],"type":"Point"}
}