{
  "type": "Feature",
  "properties": {
    "addr:full":"4217 Six Forks Rd Raleigh NC 27609",
    "addr:housenumber":"4217",
    "addr:postcode":"27609",
    "addr:street":"Six Forks Rd",
    "iso:country":"US",
    "sg:address":"4217 Six Forks Rd",
    "sg:city":"Raleigh",
    "sg:phone":"+1 919 787 1155",
    "sg:postcode":"27609",
    "sg:province":"NC",
    "sg:website":"http://www.kerrdrug.com",
    "wof:name":"Kerr Drug",
    "wof:placetype":"venue"
},
  "geometry": {"coordinates":[-78.640728,35.836999],"type":"Point"}
}