{
  "type": "Feature",
  "properties": {
    "iso:country":"US",
    "sg:address":"1461 Joe Layne Mill Rd",
    "sg:city":"Elkin",
    "sg:classifiers":[
        {
            "category":"Wholesale",
            "subcategory":"Farm Supplies",
            "type":"Manufacturing & Wholesale Goods"
        }
    ],
    "sg:phone":"+1 336 366 2409",
    "sg:postcode":"28621",
    "sg:province":"NC",
    "wof:name":"Windy Hill Trading Post",
    "wof:placetype":"venue"
},
  "geometry": {"coordinates":[-80.78703,36.305772],"type":"Point"}
}