{
  "type": "Feature",
  "properties": {
    "addr:full":"414 S Main St Salisbury NC 28144",
    "addr:housenumber":"414",
    "addr:postcode":"28144",
    "addr:street":"S Main St",
    "iso:country":"US",
    "sg:address":"414 S Main St",
    "sg:city":"Salisbury",
    "sg:classifiers":[
        {
            "category":"Personal",
            "subcategory":"Beauty Salon",
            "type":"Services"
        }
    ],
    "sg:phone":"+1   ",
    "sg:postcode":"28144",
    "sg:province":"NC",
    "sg:tags":[
        "shop"
    ],
    "wof:name":"Hair Flair",
    "wof:placetype":"venue"
},
  "geometry": {"coordinates":[-80.474237,35.664123],"type":"Point"}
}