{
  "type": "Feature",
  "properties": {
    "addr:full":"37 Loop Rd Arden NC 28715",
    "addr:housenumber":"37",
    "addr:postcode":"28715",
    "addr:street":"Loop Rd",
    "iso:country":"US",
    "sg:address":"37 Loop Rd",
    "sg:city":"Arden",
    "sg:classifiers":[
        {
            "category":"Professional",
            "type":"Services"
        }
    ],
    "sg:phone":"+1 828 681 0712",
    "sg:postcode":"28715",
    "sg:province":"NC",
    "wof:name":"Victors Granted & Marble",
    "wof:placetype":"venue"
},
  "geometry": {"coordinates":[-82.74645099999999,35.549529],"type":"Point"}
}