{
  "type": "Feature",
  "properties": {
    "addr:full":"497 E Queen St Grifton NC 28530",
    "addr:housenumber":"497",
    "addr:postcode":"28530",
    "addr:street":"E Queen St",
    "iso:country":"US",
    "sg:address":"497 E Queen St",
    "sg:city":"Grifton",
    "sg:classifiers":[
        {
            "category":"Personal",
            "subcategory":"Beauty Salon",
            "type":"Services"
        }
    ],
    "sg:phone":"+1 252 524 5033",
    "sg:postcode":"28530",
    "sg:province":"NC",
    "sg:tags":[
        "shop"
    ],
    "wof:name":"Styles By Christy",
    "wof:placetype":"venue"
},
  "geometry": {"coordinates":[-77.426157,35.370476],"type":"Point"}
}