{
  "type": "Feature",
  "properties": {
    "iso:country":"US",
    "sg:address":"480 Fayetteville Hwy",
    "sg:city":"Dunn",
    "sg:classifiers":[
        {
            "category":"Wholesale",
            "subcategory":"Farm Supplies",
            "type":"Manufacturing & Wholesale Goods"
        }
    ],
    "sg:phone":"+1 910 567 2917",
    "sg:postcode":"28334",
    "sg:province":"NC",
    "sg:tags":[
        "livestock"
    ],
    "wof:name":"L L Parks Livestock Inc",
    "wof:placetype":"venue"
},
  "geometry": {"coordinates":[-78.49527500000001,35.193818],"type":"Point"}
}