{
  "type": "Feature",
  "properties": {
    "addr:full":"2469 Old US Hwy 421 N Siler City NC 27344",
    "addr:housenumber":"2469",
    "addr:postcode":"27344",
    "addr:street":"Old Us Hwy 421 N",
    "iso:country":"US",
    "sg:address":"2469 Old US Hwy 421 N",
    "sg:city":"Siler City",
    "sg:classifiers":[
        {
            "category":"Wholesale",
            "subcategory":"Office Equipment",
            "type":"Manufacturing & Wholesale Goods"
        }
    ],
    "sg:phone":"+1 919 742 3132",
    "sg:postcode":"27344",
    "sg:province":"NC",
    "sg:tags":[
        "vault",
        "safe"
    ],
    "wof:name":"International Precast Inc",
    "wof:placetype":"venue"
},
  "geometry": {"coordinates":[-79.47895200000001,35.750855],"type":"Point"}
}