{
  "type": "Feature",
  "properties": {
    "addr:full":"2610 Arendell St Morehead City NC 28557",
    "addr:postcode":"2610;28557",
    "addr:street":"Arendell St",
    "iso:country":"US",
    "sg:address":"2610 Arendell St",
    "sg:city":"Morehead City",
    "sg:classifiers":[
        {
            "category":"Food & Beverages",
            "subcategory":"Groceries & Convenience Stores",
            "type":"Retail Goods"
        }
    ],
    "sg:phone":"+1 252 726 5020",
    "sg:postcode":"28557",
    "sg:province":"NC",
    "wof:name":"Snak N Pak",
    "wof:placetype":"venue"
},
  "geometry": {"coordinates":[-76.73957,34.723605],"type":"Point"}
}