{
  "type": "Feature",
  "properties": {
    "iso:country":"US",
    "sg:address":"241 Silkwood Dr",
    "sg:city":"Ramseur",
    "sg:classifiers":[
        {
            "category":"Social Services",
            "subcategory":"Child Care",
            "type":"Services"
        }
    ],
    "sg:phone":"+1 336 824 1823",
    "sg:postcode":"27316",
    "sg:province":"NC",
    "wof:name":"Laura's Best Of Care",
    "wof:placetype":"venue"
},
  "geometry": {"coordinates":[-79.64501799999999,35.745439],"type":"Point"}
}