{
  "type": "Feature",
  "properties": {
    "iso:country":"US",
    "sg:address":"2480 Mill Creek Rd",
    "sg:city":"Newport",
    "sg:classifiers":[
        {
            "category":"Building & Trades",
            "subcategory":"Construction",
            "type":"Services"
        }
    ],
    "sg:phone":"+1 252 342 4750",
    "sg:postcode":"28570",
    "sg:province":"NC",
    "sg:tags":[
        "house"
    ],
    "wof:name":"Bornmans Carpentry",
    "wof:placetype":"venue"
},
  "geometry": {"coordinates":[-76.749134,34.775163],"type":"Point"}
}