{
  "type": "Feature",
  "properties": {
    "iso:country":"US",
    "sg:address":"3706 Old River Rd",
    "sg:city":"Greenville",
    "sg:classifiers":[
        {
            "category":"Building & Trades",
            "subcategory":"Construction",
            "type":"Services"
        }
    ],
    "sg:phone":"+1 252 830 4874",
    "sg:postcode":"27834",
    "sg:province":"NC",
    "sg:tags":[
        "nonresidential"
    ],
    "wof:name":"Nolan Construction",
    "wof:placetype":"venue"
},
  "geometry": {"coordinates":[-77.45874999999999,35.683116],"type":"Point"}
}