{
  "type": "Feature",
  "properties": {
    "iso:country":"US",
    "sg:address":"5200 Spring Farm Rd",
    "sg:city":"Raleigh",
    "sg:classifiers":[
        {
            "category":"Farming",
            "subcategory":"Farm",
            "type":"Manufacturing & Wholesale Goods"
        }
    ],
    "sg:phone":"+1 919 661 6809",
    "sg:postcode":"27603",
    "sg:province":"NC",
    "sg:tags":[
        "crop",
        "general"
    ],
    "wof:name":"Equiterra Farms LLC",
    "wof:placetype":"venue"
},
  "geometry": {"coordinates":[-78.70392699999999,35.637658],"type":"Point"}
}