{
  "type": "Feature",
  "properties": {
    "iso:country":"US",
    "sg:address":"7213 Ogden Business Ln",
    "sg:city":"Wilmington",
    "sg:classifiers":[
        {
            "category":"Building & Trades",
            "subcategory":"Construction",
            "type":"Services"
        }
    ],
    "sg:phone":"+1 910 686 3067",
    "sg:postcode":"28411",
    "sg:province":"NC",
    "sg:tags":[
        "painter"
    ],
    "wof:name":"Colour Solutions",
    "wof:placetype":"venue"
},
  "geometry": {"coordinates":[-77.821108,34.272901],"type":"Point"}
}