{
  "type": "Feature",
  "properties": {
    "addr:full":"5218 Rehobeth Rd Waxhaw NC 28173",
    "addr:housenumber":"5218",
    "addr:postcode":"28173",
    "addr:street":"Rehobeth Rd",
    "iso:country":"US",
    "sg:address":"5218 Rehobeth Rd",
    "sg:city":"Waxhaw",
    "sg:classifiers":[
        {
            "category":"Building & Trades",
            "subcategory":"Landscaping Services",
            "type":"Services"
        }
    ],
    "sg:phone":"+1 704 560 0052",
    "sg:postcode":"28173",
    "sg:province":"NC",
    "wof:name":"Action Lawn Care",
    "wof:placetype":"venue"
},
  "geometry": {"coordinates":[-80.759945,34.906996],"type":"Point"}
}