{
  "type": "Feature",
  "properties": {
    "iso:country":"US",
    "sg:address":"5020 Randall Pkwy",
    "sg:city":"Wilmington",
    "sg:classifiers":[
        {
            "category":"Organizations",
            "subcategory":"Labor Organization",
            "type":"Services"
        }
    ],
    "sg:phone":"+1 910 799 6220",
    "sg:postcode":"28403",
    "sg:province":"NC",
    "wof:name":"Local 548 Intrntnl Assn Fire",
    "wof:placetype":"venue"
},
  "geometry": {"coordinates":[-77.877456,34.230817],"type":"Point"}
}