{
  "type": "Feature",
  "properties": {
    "addr:full":"909 Overman Rd Goldsboro NC 27530",
    "addr:housenumber":"909",
    "addr:postcode":"27530",
    "addr:street":"Overman Rd",
    "iso:country":"US",
    "sg:address":"909 Overman Rd",
    "sg:city":"Goldsboro",
    "sg:classifiers":[
        {
            "category":"Farming",
            "subcategory":"Livestock Farm",
            "type":"Manufacturing & Wholesale Goods"
        }
    ],
    "sg:phone":"+1 919 689 9977",
    "sg:postcode":"27530",
    "sg:province":"NC",
    "sg:tags":[
        "hog",
        "or",
        "feedlot"
    ],
    "wof:name":"Goldsboro Hog Farms Inc",
    "wof:placetype":"venue"
},
  "geometry": {"coordinates":[-78.11371200000001,35.329521],"type":"Point"}
}