{
  "type": "Feature",
  "properties": {
    "addr:full":"1511 Union Cross Rd Kernersville NC 27284",
    "addr:housenumber":"1511",
    "addr:postcode":"27284",
    "addr:street":"Union Cross Rd",
    "iso:country":"US",
    "sg:address":"1511 Union Cross Rd",
    "sg:city":"Kernersville",
    "sg:classifiers":[
        {
            "category":"Wholesale",
            "subcategory":"Medical Equipment & Supplies",
            "type":"Manufacturing & Wholesale Goods"
        }
    ],
    "sg:phone":"+1 336 993 5005",
    "sg:postcode":"27284",
    "sg:province":"NC",
    "sg:tags":[
        "durable",
        "retail"
    ],
    "wof:name":"Wheelchair Company Inc",
    "wof:placetype":"venue"
},
  "geometry": {"coordinates":[-80.10775599999999,36.078507],"type":"Point"}
}