{
  "type": "Feature",
  "properties": {
    "iso:country":"US",
    "sg:address":"1428 Orchard Lake Dr",
    "sg:city":"Charlotte",
    "sg:classifiers":[
        {
            "category":"Arena",
            "subcategory":"Sports Club",
            "type":"Entertainment"
        }
    ],
    "sg:phone":"+1   ",
    "sg:postcode":"28270",
    "sg:province":"NC",
    "sg:tags":[
        "marketing",
        "sporting",
        "event",
        "special",
        "promotional"
    ],
    "wof:name":"IMI Box Co",
    "wof:placetype":"venue"
},
  "geometry": {"coordinates":[-80.742924,35.141542],"type":"Point"}
}