{
  "type": "Feature",
  "properties": {
    "addr:full":"6100 Fairview Rd Charlotte NC 28210",
    "addr:housenumber":"6100",
    "addr:postcode":"28210",
    "addr:street":"Fairview Rd",
    "iso:country":"US",
    "sg:address":"6100 Fairview Rd",
    "sg:city":"Charlotte",
    "sg:classifiers":[
        {
            "category":"Banks & Credit Unions",
            "subcategory":"Bank",
            "type":"Services"
        }
    ],
    "sg:phone":"+1 704 553 6700",
    "sg:postcode":"28210",
    "sg:province":"NC",
    "sg:tags":[
        "financing"
    ],
    "sg:website":"www.fleetcapital.com",
    "wof:name":"Bank Of America Business",
    "wof:placetype":"venue"
},
  "geometry": {"coordinates":[-80.837103,35.150807],"type":"Point"}
}