{
  "type": "Feature",
  "properties": {
    "iso:country":"US",
    "sg:address":"908 Madame Moores Ln",
    "sg:city":"New Bern",
    "sg:classifiers":[
        {
            "category":"Organizations",
            "subcategory":"Religious Organization",
            "type":"Services"
        }
    ],
    "sg:phone":"+1   ",
    "sg:postcode":"28562",
    "sg:province":"NC",
    "wof:name":"Village Chapel Presbyterian",
    "wof:placetype":"venue"
},
  "geometry": {"coordinates":[-77.053162,35.078497],"type":"Point"}
}