{
  "type": "Feature",
  "properties": {
    "addr:full":"2334 Hendersonville Rd Arden NC 28704",
    "addr:housenumber":"2334",
    "addr:postcode":"28704",
    "addr:street":"Hendersonville Rd",
    "iso:country":"US",
    "sg:address":"2334 Hendersonville Rd",
    "sg:city":"Arden",
    "sg:classifiers":[
        {
            "category":"Retail",
            "subcategory":"Auto Repair",
            "type":"Services"
        }
    ],
    "sg:phone":"+1 828 684 4842",
    "sg:postcode":"28704",
    "sg:province":"NC",
    "sg:tags":[
        "repairing",
        "automobile"
    ],
    "wof:name":"Carland Body Shop",
    "wof:placetype":"venue"
},
  "geometry": {"coordinates":[-82.517596,35.467827],"type":"Point"}
}