{
  "type": "Feature",
  "properties": {
    "addr:full":"1167 1st Ave SW Hickory NC 28602",
    "addr:housenumber":"1167",
    "addr:postcode":"28602",
    "addr:street":"1St Ave Sw",
    "iso:country":"US",
    "sg:address":"1167 1st Ave SW",
    "sg:city":"Hickory",
    "sg:classifiers":[
        {
            "category":"Manufacturing",
            "subcategory":"Motor Vehicles & Parts",
            "type":"Manufacturing & Wholesale Goods"
        }
    ],
    "sg:phone":"+1 828 327 6002",
    "sg:postcode":"28602",
    "sg:province":"NC",
    "sg:tags":[
        "equipment",
        "transportation",
        "mfg"
    ],
    "wof:name":"Karts Unlimited",
    "wof:placetype":"venue"
},
  "geometry": {"coordinates":[-81.35932200000001,35.730127],"type":"Point"}
}