{
  "type": "Feature",
  "properties": {
    "addr:full":"7215 Pineville-Matthews Rd Charlotte NC 28226",
    "addr:housenumber":"7215",
    "addr:postcode":"28226",
    "addr:street":"Pineville-Matthews Rd",
    "iso:country":"US",
    "sg:address":"7215 Pineville-Matthews Rd",
    "sg:city":"Charlotte",
    "sg:classifiers":[
        {
            "category":"Personal",
            "type":"Services"
        }
    ],
    "sg:phone":"+1 704 541 7353",
    "sg:postcode":"28226",
    "sg:province":"NC",
    "sg:tags":[
        "therapist",
        "massage"
    ],
    "wof:name":"Sanctuary Healing Ctr",
    "wof:placetype":"venue"
},
  "geometry": {"coordinates":[-80.839748,35.087133],"type":"Point"}
}