{
  "type": "Feature",
  "properties": {
    "iso:country":"US",
    "sg:address":"157 Montgomery Xing",
    "sg:city":"Biscoe",
    "sg:classifiers":[
        {
            "category":"Utilities",
            "subcategory":"Telephone",
            "type":"Services"
        }
    ],
    "sg:phone":"+1 910 428 2600",
    "sg:postcode":"27209",
    "sg:province":"NC",
    "sg:tags":[
        "telecommunication"
    ],
    "wof:name":"Liberty Tax Svc",
    "wof:placetype":"venue"
},
  "geometry": {"coordinates":[-79.798642,35.358242],"type":"Point"}
}