{
  "type": "Feature",
  "properties": {
    "addr:full":"2381 Madison Green Dr Gastonia NC 28054",
    "addr:housenumber":"2381",
    "addr:postcode":"28054",
    "addr:street":"Madison Green Dr",
    "iso:country":"US",
    "sg:address":"2381 Madison Green Dr",
    "sg:city":"Gastonia",
    "sg:classifiers":[
        {
            "category":"Organizations",
            "subcategory":"Professional Association",
            "type":"Services"
        }
    ],
    "sg:phone":"+1 704 867 9321",
    "sg:postcode":"28054",
    "sg:province":"NC",
    "wof:name":"Homeowners Association",
    "wof:placetype":"venue"
},
  "geometry": {"coordinates":[-81.17935,35.231243],"type":"Point"}
}