{
  "type": "Feature",
  "properties": {
    "addr:full":"45 Tunnel Rd Asheville NC 28805",
    "addr:housenumber":"45",
    "addr:postcode":"28805",
    "addr:street":"Tunnel Rd",
    "iso:country":"US",
    "sg:address":"45 Tunnel Rd",
    "sg:city":"Asheville",
    "sg:classifiers":[
        {
            "category":"Restaurant",
            "type":"Food & Drink"
        }
    ],
    "sg:menulink":"http://www.allmenus.com/nc/asheville/131319-mikado/menu/",
    "sg:phone":"+1 828 258 9696",
    "sg:postcode":"28805",
    "sg:province":"NC",
    "sg:tags":[
        "japanese",
        "asian"
    ],
    "wof:name":"Mikado",
    "wof:placetype":"venue"
},
  "geometry": {"coordinates":[-82.53435500000001,35.596664],"type":"Point"}
}