{
  "type": "Feature",
  "properties": {
    "addr:full":"830 Silver Fox Dr Concord NC 28025",
    "addr:housenumber":"830",
    "addr:postcode":"28025",
    "addr:street":"Silver Fox Dr",
    "iso:country":"US",
    "sg:address":"830 Silver Fox Dr",
    "sg:city":"Concord",
    "sg:classifiers":[
        {
            "category":"Wholesale",
            "subcategory":"Construction Materials",
            "type":"Manufacturing & Wholesale Goods"
        }
    ],
    "sg:phone":"+1 704 788 7674",
    "sg:postcode":"28025",
    "sg:province":"NC",
    "sg:tags":[
        "marble"
    ],
    "wof:name":"Greg Dixion Marble Inc",
    "wof:placetype":"venue"
},
  "geometry": {"coordinates":[-80.59253200000001,35.329813],"type":"Point"}
}