{
  "type": "Feature",
  "properties": {
    "addr:full":"110 Deerfield Ct Swansboro NC 28584",
    "addr:housenumber":"110",
    "addr:postcode":"28584",
    "addr:street":"Deerfield Ct",
    "iso:country":"US",
    "sg:address":"110 Deerfield Ct",
    "sg:city":"Swansboro",
    "sg:classifiers":[
        {
            "category":"Real Estate",
            "subcategory":"Real Estate Agent",
            "type":"Services"
        }
    ],
    "sg:phone":"+1 252 393 7271",
    "sg:postcode":"28584",
    "sg:province":"NC",
    "wof:name":"Howard Real Estate",
    "wof:placetype":"venue"
},
  "geometry": {"coordinates":[-77.074714,34.68261],"type":"Point"}
}