{
  "type": "Feature",
  "properties": {
    "iso:country":"US",
    "sg:address":"158 Courthouse Rd",
    "sg:city":"Currituck",
    "sg:classifiers":[
        {
            "category":"Personal",
            "subcategory":"Beauty Salon",
            "type":"Services"
        }
    ],
    "sg:phone":"+1 252 232 3700",
    "sg:postcode":"27929",
    "sg:province":"NC",
    "wof:name":"Cherie & Co Hair Designs",
    "wof:placetype":"venue"
},
  "geometry": {"coordinates":[-76.014312,36.449488],"type":"Point"}
}