{
  "type": "Feature",
  "properties": {
    "addr:full":"6022 Unionville-Brief Rd Monroe NC 28110",
    "addr:housenumber":"6022",
    "addr:postcode":"28110",
    "addr:street":"Unionville-Brief Rd",
    "iso:country":"US",
    "sg:address":"6022 Unionville-Brief Rd",
    "sg:city":"Monroe",
    "sg:classifiers":[
        {
            "category":"Wholesale",
            "subcategory":"Machinery & Supplies",
            "type":"Manufacturing & Wholesale Goods"
        }
    ],
    "sg:phone":"+1 704 753 4726",
    "sg:postcode":"28110",
    "sg:province":"NC",
    "sg:tags":[
        "poultry",
        "equipment"
    ],
    "wof:name":"Griffin Farm Machine Co Inc",
    "wof:placetype":"venue"
},
  "geometry": {"coordinates":[-80.51114,35.115756],"type":"Point"}
}