{
  "type": "Feature",
  "properties": {
    "addr:full":"5413 Fayetteville Rd Durham NC 27713",
    "addr:housenumber":"5413",
    "addr:postcode":"27713",
    "addr:street":"Fayetteville Rd",
    "iso:country":"US",
    "sg:address":"5413 Fayetteville Rd",
    "sg:city":"Durham",
    "sg:classifiers":[
        {
            "category":"Building & Trades",
            "subcategory":"Construction",
            "type":"Services"
        }
    ],
    "sg:phone":"+1 919 361 3378",
    "sg:postcode":"27713",
    "sg:province":"NC",
    "sg:tags":[
        "builder",
        "operative"
    ],
    "wof:name":"U F R Model Home",
    "wof:placetype":"venue"
},
  "geometry": {"coordinates":[-78.924012,35.925849],"type":"Point"}
}