{
  "type": "Feature",
  "properties": {
    "iso:country":"US",
    "sg:address":"4309 Burlington Rd",
    "sg:city":"Greensboro",
    "sg:classifiers":[
        {
            "category":"Shopping",
            "subcategory":"Crafts & Fabrics",
            "type":"Retail Goods"
        }
    ],
    "sg:phone":"+1 336 458 0051",
    "sg:postcode":"27405",
    "sg:province":"NC",
    "sg:tags":[
        "shop"
    ],
    "wof:name":"Black Pearl Fabric Outlet",
    "wof:placetype":"venue"
},
  "geometry": {"coordinates":[-79.705646,36.088094],"type":"Point"}
}