{
  "type": "Feature",
  "properties": {
    "iso:country":"US",
    "sg:address":"637 Nuway Cir NE",
    "sg:city":"Lenoir",
    "sg:classifiers":[
        {
            "category":"Professional",
            "type":"Services"
        }
    ],
    "sg:phone":"+1 828 754 6069",
    "sg:postcode":"28645",
    "sg:province":"NC",
    "sg:tags":[
        "establishment"
    ],
    "wof:name":"Irrimax",
    "wof:placetype":"venue"
},
  "geometry": {"coordinates":[-81.529262,35.944982],"type":"Point"}
}