{
  "type": "Feature",
  "properties": {
    "iso:country":"US",
    "sg:address":"159 Bethlehem Church Rd",
    "sg:city":"Youngsville",
    "sg:classifiers":[
        {
            "category":"Building & Trades",
            "subcategory":"Landscaping Services",
            "type":"Services"
        }
    ],
    "sg:phone":"+1 919 496 7297",
    "sg:postcode":"27596",
    "sg:province":"NC",
    "wof:name":"Watkins Landscape Maintenance",
    "wof:placetype":"venue"
},
  "geometry": {"coordinates":[-78.35699099999999,35.969763],"type":"Point"}
}