{
  "type": "Feature",
  "properties": {
    "iso:country":"US",
    "sg:address":"106 Open Ct",
    "sg:city":"Morrisville",
    "sg:classifiers":[
        {
            "category":"Professional",
            "subcategory":"Management & Consulting",
            "type":"Services"
        }
    ],
    "sg:phone":"+1   ",
    "sg:postcode":"27560",
    "sg:province":"NC",
    "wof:name":"Van F Mainer",
    "wof:placetype":"venue"
},
  "geometry": {"coordinates":[-78.81806,35.801826],"type":"Point"}
}