{
  "type": "Feature",
  "properties": {
    "addr:full":"160 Big Jack Rd Thomasville NC 27360",
    "addr:housenumber":"160",
    "addr:postcode":"27360",
    "addr:street":"Big Jack Rd",
    "iso:country":"US",
    "sg:address":"160 Big Jack Rd",
    "sg:city":"Thomasville",
    "sg:classifiers":[
        {
            "category":"Shopping",
            "type":"Retail Goods"
        }
    ],
    "sg:phone":"+1 336 472 6258",
    "sg:postcode":"27360",
    "sg:province":"NC",
    "sg:tags":[
        "wood",
        "carving"
    ],
    "wof:name":"Myers Carving & Sanding Co",
    "wof:placetype":"venue"
},
  "geometry": {"coordinates":[-80.119907,35.830707],"type":"Point"}
}