{
  "type": "Feature",
  "properties": {
    "iso:country":"US",
    "sg:address":"210 Eagle Rd",
    "sg:city":"Morehead City",
    "sg:classifiers":[
        {
            "category":"Building & Trades",
            "subcategory":"Plumbing",
            "type":"Services"
        }
    ],
    "sg:phone":"+1 252 726 4610",
    "sg:postcode":"28570",
    "sg:province":"NC",
    "sg:tags":[
        "plumbing",
        "contractor"
    ],
    "wof:name":"Robinson's Plumbing & Pump Rpr",
    "wof:placetype":"venue"
},
  "geometry": {"coordinates":[-76.888209,34.742184],"type":"Point"}
}