{
  "type": "Feature",
  "properties": {
    "addr:full":"3598 Ruddy Duck Ln Bolivia NC 28461",
    "addr:housenumber":"3598",
    "addr:postcode":"28461",
    "addr:street":"Ruddy Duck Ln",
    "iso:country":"US",
    "sg:address":"3598 Ruddy Duck Ln",
    "sg:city":"Bolivia",
    "sg:classifiers":[
        {
            "category":"Building & Trades",
            "subcategory":"Construction",
            "type":"Services"
        }
    ],
    "sg:phone":"+1 910 253 7190",
    "sg:postcode":"28461",
    "sg:province":"NC",
    "sg:tags":[
        "plant",
        "treatment",
        "sewage",
        "contractor"
    ],
    "wof:name":"Treatment Plant",
    "wof:placetype":"venue"
},
  "geometry": {"coordinates":[-78.09374800000001,33.941482],"type":"Point"}
}