{
  "type": "Feature",
  "properties": {
    "addr:full":"115 N 3rd St Wilmington NC 28401",
    "addr:housenumber":"115",
    "addr:postcode":"28401",
    "addr:street":"N 3Rd St",
    "iso:country":"US",
    "sg:address":"115 N 3rd St",
    "sg:city":"Wilmington",
    "sg:classifiers":[
        {
            "category":"Manufacturing",
            "subcategory":"Chemicals & Compounds",
            "type":"Manufacturing & Wholesale Goods"
        }
    ],
    "sg:phone":"+1 910 362 0021",
    "sg:postcode":"28401",
    "sg:province":"NC",
    "sg:tags":[
        "miller",
        "drug"
    ],
    "wof:name":"Lek Pharmaceuticals Inc",
    "wof:placetype":"venue"
},
  "geometry": {"coordinates":[-77.94636300000001,34.237595],"type":"Point"}
}