{
  "type": "Feature",
  "properties": {
    "iso:country":"US",
    "sg:address":"133 Watson Ln",
    "sg:city":"Clayton",
    "sg:classifiers":[
        {
            "category":"Building & Trades",
            "subcategory":"Construction",
            "type":"Services"
        }
    ],
    "sg:phone":"+1 919 553 9002",
    "sg:postcode":"27983",
    "sg:province":"NC",
    "sg:tags":[
        "tile",
        "dealer"
    ],
    "wof:name":"Concepts In Resinous Flooring",
    "wof:placetype":"venue"
},
  "geometry": {"coordinates":[-77.052173,36.077261],"type":"Point"}
}