{
  "type": "Feature",
  "properties": {
    "iso:country":"US",
    "sg:address":"118 S Monk St",
    "sg:city":"Magnolia",
    "sg:classifiers":[
        {
            "category":"Retail",
            "subcategory":"Auto Repair",
            "type":"Services"
        }
    ],
    "sg:phone":"+1 910 289 2162",
    "sg:postcode":"28453",
    "sg:province":"NC",
    "sg:tags":[
        "repairing",
        "automobile"
    ],
    "wof:name":"Register's Trucking & Garage",
    "wof:placetype":"venue"
},
  "geometry": {"coordinates":[-78.053839,34.895253],"type":"Point"}
}