{
  "type": "Feature",
  "properties": {
    "addr:full":"14312 Arbor Ridge Dr Charlotte NC 28273",
    "addr:housenumber":"14312",
    "addr:postcode":"28273",
    "addr:street":"Arbor Ridge Dr",
    "iso:country":"US",
    "sg:address":"14312 Arbor Ridge Dr",
    "sg:city":"Charlotte",
    "sg:classifiers":[
        {
            "category":"Building & Trades",
            "subcategory":"Construction",
            "type":"Services"
        }
    ],
    "sg:phone":"+1 704 504 1722",
    "sg:postcode":"28273",
    "sg:province":"NC",
    "sg:tags":[
        "carpenter"
    ],
    "wof:name":"Interior Wood",
    "wof:placetype":"venue"
},
  "geometry": {"coordinates":[-80.98044400000001,35.120524],"type":"Point"}
}