{
  "type": "Feature",
  "properties": {
    "addr:full":"51 Cassidy Ct Clayton NC 27520",
    "addr:housenumber":"51",
    "addr:postcode":"27520",
    "addr:street":"Cassidy Ct",
    "iso:country":"US",
    "sg:address":"51 Cassidy Ct",
    "sg:city":"Clayton",
    "sg:classifiers":[
        {
            "category":"Professional",
            "subcategory":"Management & Consulting",
            "type":"Services"
        }
    ],
    "sg:phone":"+1   ",
    "sg:postcode":"27520",
    "sg:province":"NC",
    "wof:name":"Revpro Dental Inc",
    "wof:placetype":"venue"
},
  "geometry": {"coordinates":[-78.52641199999999,35.625075],"type":"Point"}
}