{
  "type": "Feature",
  "properties": {
    "addr:full":"422 Washington St Williamston NC 27892",
    "addr:housenumber":"422",
    "addr:postcode":"27892",
    "addr:street":"Washington St",
    "iso:country":"US",
    "sg:address":"422 Washington St",
    "sg:city":"Williamston",
    "sg:classifiers":[
        {
            "category":"Real Estate",
            "subcategory":"Surveying",
            "type":"Services"
        }
    ],
    "sg:phone":"+1 252 792 2276",
    "sg:postcode":"27892",
    "sg:province":"NC",
    "sg:tags":[
        "surveyor"
    ],
    "wof:name":"Roanoke Land Surveying",
    "wof:placetype":"venue"
},
  "geometry": {"coordinates":[-77.05723399999999,35.848552],"type":"Point"}
}