{
  "type": "Feature",
  "properties": {
    "addr:full":"1005 W Ehringhaus St Elizabeth City NC 27909",
    "addr:housenumber":"1005",
    "addr:postcode":"27909",
    "addr:street":"W Ehringhaus St",
    "iso:country":"US",
    "sg:address":"1005 W Ehringhaus St",
    "sg:city":"Elizabeth City",
    "sg:classifiers":[
        {
            "category":"Autos & Motor Vehicles",
            "subcategory":"Automobile Sales",
            "type":"Retail Goods"
        }
    ],
    "sg:phone":"+1 252 338 9100",
    "sg:postcode":"27909",
    "sg:province":"NC",
    "sg:tags":[
        "car",
        "dealer"
    ],
    "sg:website":"www.perryautogroup.com",
    "wof:name":"Performance Chevrolet",
    "wof:placetype":"venue"
},
  "geometry": {"coordinates":[-76.234559,36.295342],"type":"Point"}
}