{
  "type": "Feature",
  "properties": {
    "addr:full":"5920 Mcchesney Dr Charlotte NC 28269",
    "addr:housenumber":"5920",
    "addr:postcode":"28269",
    "addr:street":"Mcchesney Dr",
    "iso:country":"US",
    "sg:address":"5920 Mcchesney Dr",
    "sg:city":"Charlotte",
    "sg:classifiers":[
        {
            "category":"Social Services",
            "subcategory":"Adult Care",
            "type":"Services"
        }
    ],
    "sg:phone":"+1 704 992 1560",
    "sg:postcode":"28269",
    "sg:province":"NC",
    "sg:tags":[
        "alzheimer's"
    ],
    "wof:name":"The Haven In Highland Creek",
    "wof:placetype":"venue"
},
  "geometry": {"coordinates":[-80.757496,35.388995],"type":"Point"}
}