{
  "type": "Feature",
  "properties": {
    "addr:full":"9618 Monroe Rd Charlotte NC 28270",
    "addr:housenumber":"9618",
    "addr:postcode":"28270",
    "addr:street":"Monroe Rd",
    "iso:country":"US",
    "sg:address":"9618 Monroe Rd",
    "sg:city":"Charlotte",
    "sg:classifiers":[
        {
            "category":"Food & Beverages",
            "subcategory":"Groceries & Convenience Stores",
            "type":"Retail Goods"
        }
    ],
    "sg:phone":"+1 704 849 2299",
    "sg:postcode":"28270",
    "sg:province":"NC",
    "sg:tags":[
        "market"
    ],
    "wof:name":"Perspolis Market",
    "wof:placetype":"venue"
},
  "geometry": {"coordinates":[-80.739954,35.140876],"type":"Point"}
}