{
  "type": "Feature",
  "properties": {
    "iso:country":"US",
    "sg:address":"3108 Old State Hwy 109",
    "sg:city":"Lexington",
    "sg:classifiers":[
        {
            "category":"Retail",
            "subcategory":"Repair Shop",
            "type":"Services"
        }
    ],
    "sg:phone":"+1 336 859 1978",
    "sg:postcode":"27292",
    "sg:province":"NC",
    "sg:tags":[
        "taxidermist"
    ],
    "wof:name":"Affordable Taxidermy",
    "wof:placetype":"venue"
},
  "geometry": {"coordinates":[-80.10753699999999,35.722806],"type":"Point"}
}