{
  "type": "Feature",
  "properties": {
    "iso:country":"US",
    "sg:address":"1401 Forrest St",
    "sg:city":"High Point",
    "sg:classifiers":[
        {
            "category":"Professional",
            "subcategory":"Business Services",
            "type":"Services"
        }
    ],
    "sg:phone":"+1 336 883 9637",
    "sg:postcode":"27262",
    "sg:province":"NC",
    "sg:tags":[
        "interior",
        "consultant",
        "design",
        "decorator"
    ],
    "wof:name":"Portfolio Interiors",
    "wof:placetype":"venue"
},
  "geometry": {"coordinates":[-80.00437100000001,35.980158],"type":"Point"}
}