{
  "type": "Feature",
  "properties": {
    "addr:full":"209 Brookfield Dr Wilmington NC 28405",
    "addr:housenumber":"209",
    "addr:postcode":"28405",
    "addr:street":"Brookfield Dr",
    "iso:country":"US",
    "sg:address":"209 Brookfield Dr",
    "sg:city":"Wilmington",
    "sg:classifiers":[
        {
            "category":"Retail",
            "subcategory":"Portrait Studio",
            "type":"Services"
        }
    ],
    "sg:phone":"+1   ",
    "sg:postcode":"28405",
    "sg:province":"NC",
    "sg:tags":[
        "photo"
    ],
    "wof:name":"Carmack Photography LLC",
    "wof:placetype":"venue"
},
  "geometry": {"coordinates":[-77.879533,34.276137],"type":"Point"}
}