{
  "type": "Feature",
  "properties": {
    "addr:full":"1894 Riverside Dr Lexington NC 27292",
    "addr:housenumber":"1894",
    "addr:postcode":"27292",
    "addr:street":"Riverside Dr",
    "iso:country":"US",
    "sg:address":"1894 Riverside Dr",
    "sg:city":"Lexington",
    "sg:classifiers":[
        {
            "category":"Building & Trades",
            "subcategory":"Construction",
            "type":"Services"
        }
    ],
    "sg:phone":"+1 336 236 6023",
    "sg:postcode":"27292",
    "sg:province":"NC",
    "sg:tags":[
        "general",
        "contractor"
    ],
    "wof:name":"Leonard Roofing & Construction",
    "wof:placetype":"venue"
},
  "geometry": {"coordinates":[-80.31438199999999,35.68508],"type":"Point"}
}