{
  "type": "Feature",
  "properties": {
    "addr:full":"170 Claremont Dr Elkin NC 28621",
    "addr:housenumber":"170",
    "addr:postcode":"28621",
    "addr:street":"Claremont Dr",
    "iso:country":"US",
    "sg:address":"170 Claremont Dr",
    "sg:city":"Elkin",
    "sg:classifiers":[
        {
            "category":"Building & Trades",
            "subcategory":"Construction",
            "type":"Services"
        }
    ],
    "sg:phone":"+1 336 835 4886",
    "sg:postcode":"28621",
    "sg:province":"NC",
    "sg:tags":[
        "residential",
        "home"
    ],
    "wof:name":"Heritage Construction Co",
    "wof:placetype":"venue"
},
  "geometry": {"coordinates":[-80.842161,36.267862],"type":"Point"}
}