{
  "type": "Feature",
  "properties": {
    "iso:country":"US",
    "sg:address":"332 Liveoak Dr",
    "sg:city":"Cape Carteret",
    "sg:classifiers":[
        {
            "category":"Travel",
            "subcategory":"Hotels & Motels",
            "type":"Entertainment"
        }
    ],
    "sg:phone":"+1 252 393 6868",
    "sg:postcode":"28584",
    "sg:province":"NC",
    "sg:tags":[
        "breakfast",
        "operation",
        "bed",
        "accommodation"
    ],
    "wof:name":"Harbor Light Guest House",
    "wof:placetype":"venue"
},
  "geometry": {"coordinates":[-77.04770000000001,34.687785],"type":"Point"}
}