{
  "type": "Feature",
  "properties": {
    "iso:country":"US",
    "sg:address":"545 Snuggs St",
    "sg:city":"Albemarle",
    "sg:classifiers":[
        {
            "category":"Retail",
            "subcategory":"Auto Repair",
            "type":"Services"
        }
    ],
    "sg:phone":"+1 704 982 3684",
    "sg:postcode":"28001",
    "sg:province":"NC",
    "sg:tags":[
        "repairing",
        "automobile"
    ],
    "wof:name":"Doug's Garage",
    "wof:placetype":"venue"
},
  "geometry": {"coordinates":[-80.205991,35.370436],"type":"Point"}
}