{
  "type": "Feature",
  "properties": {
    "iso:country":"US",
    "sg:address":"201 S. Estes Drive",
    "sg:city":"Chapel Hill",
    "sg:classifiers":[
        {
            "category":"Personal",
            "subcategory":"Nail Salon",
            "type":"Services"
        }
    ],
    "sg:phone":"+1 919 932 7424",
    "sg:postcode":"27514",
    "sg:province":"NC",
    "sg:website":"www.lessanctuarynail.com",
    "wof:name":"Le's Sanctuary Nail Spa",
    "wof:placetype":"venue"
},
  "geometry": {"coordinates":[-79.02807,35.926512],"type":"Point"}
}