{
  "type": "Feature",
  "properties": {
    "iso:country":"US",
    "sg:address":"215 Pineholt Ln",
    "sg:city":"Flat Rock",
    "sg:classifiers":[
        {
            "category":"Professional",
            "subcategory":"Management & Consulting",
            "type":"Services"
        }
    ],
    "sg:phone":"+1   ",
    "sg:postcode":"28731",
    "sg:province":"NC",
    "wof:name":"Ddi",
    "wof:placetype":"venue"
},
  "geometry": {"coordinates":[-82.440786,35.252439],"type":"Point"}
}