{
  "type": "Feature",
  "properties": {
    "addr:full":"681 W King St Boone NC 28607",
    "addr:housenumber":"681",
    "addr:postcode":"28607",
    "addr:street":"W King St",
    "iso:country":"US",
    "sg:address":"681 W King St",
    "sg:city":"Boone",
    "sg:classifiers":[
        {
            "category":"Shopping",
            "subcategory":"Books",
            "type":"Retail Goods"
        }
    ],
    "sg:phone":"+1 828 265 4263",
    "sg:postcode":"28607",
    "sg:province":"NC",
    "sg:tags":[
        "comic"
    ],
    "wof:name":"Dragon's Den Comic Books",
    "wof:placetype":"venue"
},
  "geometry": {"coordinates":[-81.684344,36.218824],"type":"Point"}
}