{
  "type": "Feature",
  "properties": {
    "iso:country":"US",
    "sg:address":"402 Airport Rd",
    "sg:city":"New Bern",
    "sg:classifiers":[
        {
            "category":"Shopping",
            "type":"Retail Goods"
        }
    ],
    "sg:phone":"+1 252 636 1135",
    "sg:postcode":"28560",
    "sg:province":"NC",
    "sg:tags":[
        "plastic"
    ],
    "wof:name":"Southtech Plastics",
    "wof:placetype":"venue"
},
  "geometry": {"coordinates":[-77.02549399999999,35.074864],"type":"Point"}
}