{
  "type": "Feature",
  "properties": {
    "iso:country":"US",
    "sg:address":"1915 Conley Rd",
    "sg:city":"Morganton",
    "sg:classifiers":[
        {
            "category":"Shopping",
            "subcategory":"Discount & Variety Stores",
            "type":"Retail Goods"
        },
        {
            "category":"Home & Garden",
            "subcategory":"Hardware",
            "type":"Retail Goods"
        }
    ],
    "sg:phone":"+1 828 584 2835",
    "sg:postcode":"28655",
    "sg:province":"NC",
    "sg:tags":[
        "station",
        "gasoline",
        "merchandise",
        "general"
    ],
    "wof:name":"B & J's General Store Inc",
    "wof:placetype":"venue"
},
  "geometry": {"coordinates":[-81.769266,35.679377],"type":"Point"}
}