{
  "type": "Feature",
  "properties": {
    "addr:full":"320 Plymouth St Washington NC 27889",
    "addr:housenumber":"320",
    "addr:postcode":"27889",
    "addr:street":"Plymouth St",
    "iso:country":"US",
    "sg:address":"320 Plymouth St",
    "sg:city":"Washington",
    "sg:classifiers":[
        {
            "category":"Professional",
            "subcategory":"Accounting & Tax Preparation",
            "type":"Services"
        }
    ],
    "sg:phone":"+1 252 946 0231",
    "sg:postcode":"27889",
    "sg:province":"NC",
    "sg:tags":[
        "accountant"
    ],
    "wof:name":"Mobiletax Bookkeeping Svc",
    "wof:placetype":"venue"
},
  "geometry": {"coordinates":[-77.069452,35.555188],"type":"Point"}
}