{
  "type": "Feature",
  "properties": {
    "addr:full":"224 Roy Bell Rd Kings Mountain NC 28086",
    "addr:housenumber":"224",
    "addr:postcode":"28086",
    "addr:street":"Roy Bell Rd",
    "iso:country":"US",
    "sg:address":"224 Roy Bell Rd",
    "sg:city":"Kings Mountain",
    "sg:classifiers":[
        {
            "category":"Building & Trades",
            "subcategory":"Landscaping Services",
            "type":"Services"
        }
    ],
    "sg:phone":"+1 704 937 3232",
    "sg:postcode":"28086",
    "sg:province":"NC",
    "wof:name":"Thomas Lawn Care",
    "wof:placetype":"venue"
},
  "geometry": {"coordinates":[-81.423484,35.187793],"type":"Point"}
}