{
  "type": "Feature",
  "properties": {
    "addr:full":"5928 South Blvd Charlotte NC 28217",
    "addr:housenumber":"5928",
    "addr:postcode":"28217",
    "addr:street":"South Blvd",
    "iso:country":"US",
    "sg:address":"5928 South Blvd",
    "sg:city":"Charlotte",
    "sg:classifiers":[
        {
            "category":"Personal",
            "subcategory":"Beauty Salon",
            "type":"Services"
        }
    ],
    "sg:phone":"+1 704 554 8456",
    "sg:postcode":"28217",
    "sg:province":"NC",
    "wof:name":"Yolanda's Beauty Salon",
    "wof:placetype":"venue"
},
  "geometry": {"coordinates":[-80.876368,35.154452],"type":"Point"}
}