{
  "type": "Feature",
  "properties": {
    "iso:country":"US",
    "sg:address":"2900 Spring Forest Rd",
    "sg:city":"Raleigh",
    "sg:classifiers":[
        {
            "category":"Insurance",
            "subcategory":"Insurance Agent",
            "type":"Services"
        },
        {
            "category":"Insurance",
            "subcategory":"Hazard Insurance",
            "type":"Services"
        },
        {
            "category":"Insurance",
            "subcategory":"Title Insurance",
            "type":"Services"
        },
        {
            "category":"Insurance",
            "subcategory":"Life Insurance",
            "type":"Services"
        }
    ],
    "sg:phone":"+1 919 872 4593",
    "sg:postcode":"27616",
    "sg:province":"NC",
    "sg:tags":[
        "business",
        "auto",
        "commercial",
        "homeowner",
        "motorcycle",
        "renter"
    ],
    "wof:name":"Allstate Insurance Company - Tony Sheets",
    "wof:placetype":"venue"
},
  "geometry": {"coordinates":[-78.591713,35.855549],"type":"Point"}
}