{
  "type": "Feature",
  "properties": {
    "addr:full":"138 1st Ave SW Taylorsville NC 28681",
    "addr:housenumber":"138",
    "addr:postcode":"28681",
    "addr:street":"1St Ave Sw",
    "iso:country":"US",
    "sg:address":"138 1st Ave SW",
    "sg:city":"Taylorsville",
    "sg:classifiers":[
        {
            "category":"Building & Trades",
            "subcategory":"Construction",
            "type":"Services"
        }
    ],
    "sg:phone":"+1 828 635 1717",
    "sg:postcode":"28681",
    "sg:province":"NC",
    "sg:tags":[
        "contractor"
    ],
    "wof:name":"Turn Key Contractors Inc",
    "wof:placetype":"venue"
},
  "geometry": {"coordinates":[-81.176074,35.920956],"type":"Point"}
}