{
  "type": "Feature",
  "properties": {
    "iso:country":"US",
    "sg:address":"103 Canterbury Rd NW",
    "sg:city":"Wilson",
    "sg:classifiers":[
        {
            "category":"Education",
            "subcategory":"Library",
            "type":"Public Place"
        }
    ],
    "sg:phone":"+1   ",
    "sg:postcode":"27896",
    "sg:province":"NC",
    "wof:name":"Black Creek Library",
    "wof:placetype":"venue"
},
  "geometry": {"coordinates":[-77.93122700000001,35.753529],"type":"Point"}
}