{
  "type": "Feature",
  "properties": {
    "iso:country":"US",
    "sg:address":"2626 S York Rd",
    "sg:city":"Gastonia",
    "sg:classifiers":[
        {
            "category":"Home & Garden",
            "subcategory":"Mobile Homes",
            "type":"Retail Goods"
        }
    ],
    "sg:phone":"+1 704 867 4124",
    "sg:postcode":"28052",
    "sg:province":"NC",
    "wof:name":"Dynasty Homes Of Gastonia",
    "wof:placetype":"venue"
},
  "geometry": {"coordinates":[-81.198063,35.228278],"type":"Point"}
}