{
  "type": "Feature",
  "properties": {
    "addr:full":"1528 S Evans St Greenville NC 27834",
    "addr:housenumber":"1528",
    "addr:postcode":"27834",
    "addr:street":"S Evans St",
    "iso:country":"US",
    "sg:address":"1528 S Evans St",
    "sg:city":"Greenville",
    "sg:classifiers":[
        {
            "category":"Professional",
            "type":"Services"
        }
    ],
    "sg:phone":"+1 252 756 1166",
    "sg:postcode":"27834",
    "sg:province":"NC",
    "wof:name":"Intelligent Environments",
    "wof:placetype":"venue"
},
  "geometry": {"coordinates":[-77.375997,35.599908],"type":"Point"}
}