{
  "type": "Feature",
  "properties": {
    "iso:country":"US",
    "sg:address":"3528 Hawkins Ave",
    "sg:city":"Sanford",
    "sg:classifiers":[
        {
            "category":"Manufacturing",
            "subcategory":"Tools & Machinery",
            "type":"Manufacturing & Wholesale Goods"
        }
    ],
    "sg:phone":"+1 919 775 3707",
    "sg:postcode":"27330",
    "sg:province":"NC",
    "sg:tags":[
        "industrial",
        "mfg"
    ],
    "wof:name":"Geo Chip Machine",
    "wof:placetype":"venue"
},
  "geometry": {"coordinates":[-79.188182,35.538346],"type":"Point"}
}