{
  "type": "Feature",
  "properties": {
    "addr:full":"1393 White Level Rd Louisburg NC 27549",
    "addr:housenumber":"1393",
    "addr:postcode":"27549",
    "addr:street":"White Level Rd",
    "iso:country":"US",
    "sg:address":"1393 White Level Rd",
    "sg:city":"Louisburg",
    "sg:classifiers":[
        {
            "category":"Food & Beverages",
            "subcategory":"Groceries & Convenience Stores",
            "type":"Retail Goods"
        }
    ],
    "sg:phone":"+1 919 853 2415",
    "sg:postcode":"27549",
    "sg:province":"NC",
    "sg:tags":[
        "grocer"
    ],
    "wof:name":"Champion Grocery",
    "wof:placetype":"venue"
},
  "geometry": {"coordinates":[-78.173818,36.115512],"type":"Point"}
}