{
  "type": "Feature",
  "properties": {
    "iso:country":"US",
    "sg:address":"606 Belmont Mount Holly Rd",
    "sg:city":"Belmont",
    "sg:classifiers":[
        {
            "category":"Home & Garden",
            "subcategory":"Household Appliances",
            "type":"Retail Goods"
        }
    ],
    "sg:phone":"+1 704 827 5856",
    "sg:postcode":"28012",
    "sg:province":"NC",
    "wof:name":"Berckman Custom Carts",
    "wof:placetype":"venue"
},
  "geometry": {"coordinates":[-81.032031,35.272043],"type":"Point"}
}