{
  "type": "Feature",
  "properties": {
    "iso:country":"US",
    "sg:address":"4621 Wilkinson Blvd",
    "sg:city":"Charlotte",
    "sg:classifiers":[
        {
            "category":"Professional",
            "type":"Services"
        }
    ],
    "sg:phone":"+1 704 399 4946",
    "sg:postcode":"28208",
    "sg:province":"NC",
    "sg:tags":[
        "establishment"
    ],
    "wof:name":"Coyote Joe's",
    "wof:placetype":"venue"
},
  "geometry": {"coordinates":[-80.916005,35.228747],"type":"Point"}
}