{
  "type": "Feature",
  "properties": {
    "iso:country":"US",
    "sg:address":"8439 Davis Lake Pkwy",
    "sg:city":"Charlotte",
    "sg:classifiers":[
        {
            "category":"Coffee & Tea",
            "type":"Food & Drink"
        }
    ],
    "sg:menulink":"http://www.allmenus.com/nc/charlotte/124987-starbucks-coffee/menu/",
    "sg:phone":"+1 704 921 4515",
    "sg:postcode":"28269",
    "sg:province":"NC",
    "sg:tags":[
        "american"
    ],
    "wof:name":"Starbucks Coffee",
    "wof:placetype":"venue"
},
  "geometry": {"coordinates":[-80.81129900000001,35.334003],"type":"Point"}
}