{
  "type": "Feature",
  "properties": {
    "addr:full":"3552 W Stage Coach Trl Shelby NC 28150",
    "addr:housenumber":"3552",
    "addr:postcode":"28150",
    "addr:street":"W Stage Coach Trl",
    "iso:country":"US",
    "sg:address":"3552 W Stage Coach Trl",
    "sg:city":"Shelby",
    "sg:classifiers":[
        {
            "category":"Professional",
            "type":"Services"
        }
    ],
    "sg:phone":"+1 704 538 8030",
    "sg:postcode":"28150",
    "sg:province":"NC",
    "wof:name":"Jeffrey A Spivey",
    "wof:placetype":"venue"
},
  "geometry": {"coordinates":[-81.67980799999999,35.399997],"type":"Point"}
}