{
  "type": "Feature",
  "properties": {
    "addr:full":"44 Stroup Rd Spruce Pine NC 28777",
    "addr:housenumber":"44",
    "addr:postcode":"28777",
    "addr:street":"Stroup Rd",
    "iso:country":"US",
    "sg:address":"44 Stroup Rd",
    "sg:city":"Spruce Pine",
    "sg:classifiers":[
        {
            "category":"Shopping",
            "subcategory":"Hobbies, Toys, & Games",
            "type":"Retail Goods"
        }
    ],
    "sg:phone":"+1 828 765 2765",
    "sg:postcode":"28777",
    "sg:province":"NC",
    "sg:tags":[
        "model",
        "supply"
    ],
    "wof:name":"Stroup Hobby Shop",
    "wof:placetype":"venue"
},
  "geometry": {"coordinates":[-82.078159,35.918104],"type":"Point"}
}