{
  "type": "Feature",
  "properties": {
    "addr:full":"120 Campbell Dr Pisgah Forest NC 28768",
    "addr:housenumber":"120",
    "addr:postcode":"28768",
    "addr:street":"Campbell Dr Pisgah",
    "iso:country":"US",
    "sg:address":"120 Campbell Dr",
    "sg:city":"Pisgah Forest",
    "sg:classifiers":[
        {
            "category":"Building & Trades",
            "subcategory":"Construction",
            "type":"Services"
        }
    ],
    "sg:phone":"+1 828 862 6973",
    "sg:postcode":"28768",
    "sg:province":"NC",
    "sg:tags":[
        "concrete",
        "contractor"
    ],
    "wof:name":"Roger Dodger Inc",
    "wof:placetype":"venue"
},
  "geometry": {"coordinates":[-82.684811,35.233723],"type":"Point"}
}