{
  "type": "Feature",
  "properties": {
    "addr:full":"2417 23rd St Ct NE Hickory NC 28601",
    "addr:housenumber":"2417",
    "addr:postcode":"28601",
    "addr:street":"23Rd St Ct Ne",
    "iso:country":"US",
    "sg:address":"2417 23rd St Ct NE",
    "sg:city":"Hickory",
    "sg:classifiers":[
        {
            "category":"Real Estate",
            "subcategory":"Real Estate Agent",
            "type":"Services"
        }
    ],
    "sg:phone":"+1 828 431 2323",
    "sg:postcode":"28601",
    "sg:province":"NC",
    "wof:name":"Hometown Builders Realty Co",
    "wof:placetype":"venue"
},
  "geometry": {"coordinates":[-81.28824299999999,35.762879],"type":"Point"}
}