{
  "type": "Feature",
  "properties": {
    "addr:full":"2500 Erwin Rd Durham NC 27705",
    "addr:housenumber":"2500",
    "addr:postcode":"27705",
    "addr:street":"Erwin Rd",
    "iso:country":"US",
    "sg:address":"2500 Erwin Rd",
    "sg:city":"Durham",
    "sg:classifiers":[
        {
            "category":"Retail",
            "subcategory":"Auto Repair",
            "type":"Services"
        }
    ],
    "sg:phone":"+1 919 286 3396",
    "sg:postcode":"27705",
    "sg:province":"NC",
    "sg:tags":[
        "repairing",
        "automobile"
    ],
    "wof:name":"Exxon University Svc Ctr",
    "wof:placetype":"venue"
},
  "geometry": {"coordinates":[-78.94409400000001,36.008719],"type":"Point"}
}