{
  "type": "Feature",
  "properties": {
    "iso:country":"US",
    "sg:address":"3005 Shulls Mill Rd",
    "sg:city":"Boone",
    "sg:classifiers":[
        {
            "category":"Restaurant",
            "type":"Food & Drink"
        }
    ],
    "sg:menulink":"http://www.allmenus.com/nc/watauga/137809-gamekeeper/menu/",
    "sg:phone":"+1 828 963 7400",
    "sg:postcode":"28607",
    "sg:province":"NC",
    "sg:tags":[
        "american",
        "southern"
    ],
    "wof:name":"Gamekeeper",
    "wof:placetype":"venue"
},
  "geometry": {"coordinates":[-81.718187,36.171908],"type":"Point"}
}