{
  "type": "Feature",
  "properties": {
    "addr:full":"1050 Flat River Church Rd Roxboro NC 27574",
    "addr:housenumber":"1050",
    "addr:postcode":"27574",
    "addr:street":"Flat River Church Rd",
    "iso:country":"US",
    "sg:address":"1050 Flat River Church Rd",
    "sg:city":"Roxboro",
    "sg:phone":"+1 336 599 5796",
    "sg:postcode":"27574",
    "sg:province":"NC",
    "sg:tags":[
        "farm",
        "tobacco"
    ],
    "wof:name":"Moore Farm",
    "wof:placetype":"venue"
},
  "geometry": {"coordinates":[-78.991086,36.337063],"type":"Point"}
}