{
  "type": "Feature",
  "properties": {
    "addr:full":"512 E Franklin Blvd Gastonia NC 28054",
    "addr:housenumber":"512",
    "addr:postcode":"28054",
    "addr:street":"E Franklin Blvd",
    "iso:country":"US",
    "sg:address":"512 E Franklin Blvd",
    "sg:city":"Gastonia",
    "sg:classifiers":[
        {
            "category":"Autos & Motor Vehicles",
            "subcategory":"Automobile Sales",
            "type":"Retail Goods"
        }
    ],
    "sg:phone":"+1 704 866 4143",
    "sg:postcode":"28054",
    "sg:province":"NC",
    "sg:tags":[
        "car",
        "dealer"
    ],
    "wof:name":"J & J Reliable Auto Sales Inc",
    "wof:placetype":"venue"
},
  "geometry": {"coordinates":[-81.17357,35.26237],"type":"Point"}
}