{
  "type": "Feature",
  "properties": {
    "iso:country":"US",
    "sg:address":"4625 Dwight Evans Rd",
    "sg:city":"Charlotte",
    "sg:classifiers":[
        {
            "category":"Manufacturing",
            "subcategory":"Paper Products",
            "type":"Manufacturing & Wholesale Goods"
        }
    ],
    "sg:phone":"+1 704 523 1300",
    "sg:postcode":"28217",
    "sg:province":"NC",
    "sg:tags":[
        "printing",
        "work",
        "commercial",
        "mill"
    ],
    "wof:name":"Universal Concepts Inc",
    "wof:placetype":"venue"
},
  "geometry": {"coordinates":[-80.90102899999999,35.189612],"type":"Point"}
}