{
  "type": "Feature",
  "properties": {
    "addr:full":"910 W 15th St Washington NC 27889",
    "addr:housenumber":"910",
    "addr:postcode":"27889",
    "addr:street":"W 15Th St",
    "iso:country":"US",
    "sg:address":"910 W 15th St",
    "sg:city":"Washington",
    "sg:classifiers":[
        {
            "category":"Health Services",
            "subcategory":"Doctor",
            "type":"Services"
        }
    ],
    "sg:phone":"+1 252 946 1181",
    "sg:postcode":"27889",
    "sg:province":"NC",
    "sg:tags":[
        "physician",
        "surgeon"
    ],
    "wof:name":"Roberson Foot Care Pa",
    "wof:placetype":"venue"
},
  "geometry": {"coordinates":[-77.057282,35.560517],"type":"Point"}
}