{
  "type": "Feature",
  "properties": {
    "addr:full":"824 N Topsail Dr Holly Ridge NC 28445",
    "addr:housenumber":"824",
    "addr:postcode":"28445",
    "addr:street":"N Topsail Dr",
    "iso:country":"US",
    "sg:address":"824 N Topsail Dr",
    "sg:city":"Holly Ridge",
    "sg:classifiers":[
        {
            "category":"Professional",
            "subcategory":"Business Services",
            "type":"Services"
        }
    ],
    "sg:phone":"+1   ",
    "sg:postcode":"28445",
    "sg:province":"NC",
    "wof:name":"Disa Sales LLC",
    "wof:placetype":"venue"
},
  "geometry": {"coordinates":[-77.53231100000001,34.43357],"type":"Point"}
}