{
  "type": "Feature",
  "properties": {
    "iso:country":"US",
    "sg:address":"600 Raintree Dr",
    "sg:city":"Matthews",
    "sg:classifiers":[
        {
            "category":"Professional",
            "type":"Services"
        }
    ],
    "sg:phone":"+1 704 821 9198",
    "sg:postcode":"28104",
    "sg:province":"NC",
    "wof:name":"Edward R Squires",
    "wof:placetype":"venue"
},
  "geometry": {"coordinates":[-80.70666,35.055891],"type":"Point"}
}