{
  "type": "Feature",
  "properties": {
    "addr:full":"4404 Shipyard Blvd Wilmington NC 28403",
    "addr:housenumber":"4404",
    "addr:postcode":"28403",
    "addr:street":"Shipyard Blvd",
    "iso:country":"US",
    "sg:address":"4404 Shipyard Blvd",
    "sg:city":"Wilmington",
    "sg:classifiers":[
        {
            "category":"Personal",
            "subcategory":"Shoe Repair & Shine",
            "type":"Services"
        }
    ],
    "sg:phone":"+1   ",
    "sg:postcode":"28403",
    "sg:province":"NC",
    "sg:tags":[
        "parlor"
    ],
    "wof:name":"Longleaf Shoe Repair",
    "wof:placetype":"venue"
},
  "geometry": {"coordinates":[-77.889623,34.199959],"type":"Point"}
}