{
  "type": "Feature",
  "properties": {
    "addr:full":"200 N Church St Rocky Mount NC 27804",
    "addr:housenumber":"200",
    "addr:postcode":"27804",
    "addr:street":"N Church St",
    "iso:country":"US",
    "sg:address":"200 N Church St",
    "sg:city":"Rocky Mount",
    "sg:classifiers":[
        {
            "category":"Banks & Credit Unions",
            "subcategory":"Bank",
            "type":"Services"
        }
    ],
    "sg:phone":"+1 252 977 9788",
    "sg:postcode":"27804",
    "sg:province":"NC",
    "wof:name":"B B & T",
    "wof:placetype":"venue"
},
  "geometry": {"coordinates":[-77.795664,35.945909],"type":"Point"}
}