{
  "type": "Feature",
  "properties": {
    "addr:full":"116 N Main St Rich Square NC 27869",
    "addr:housenumber":"116",
    "addr:postcode":"27869",
    "addr:street":"N Main St Rich",
    "iso:country":"US",
    "sg:address":"116 N Main St",
    "sg:city":"Rich Square",
    "sg:classifiers":[
        {
            "category":"Home & Garden",
            "subcategory":"Hardware",
            "type":"Retail Goods"
        }
    ],
    "sg:phone":"+1 252 539 2114",
    "sg:postcode":"27869",
    "sg:province":"NC",
    "wof:name":"Rich Sq Trustworthy Hardware",
    "wof:placetype":"venue"
},
  "geometry": {"coordinates":[-77.28169200000001,36.276542],"type":"Point"}
}