{
  "type": "Feature",
  "properties": {
    "addr:full":"146 Dogwood Trl Manteo NC 27954",
    "addr:housenumber":"146",
    "addr:postcode":"27954",
    "addr:street":"Dogwood Trl",
    "iso:country":"US",
    "sg:address":"146 Dogwood Trl",
    "sg:city":"Manteo",
    "sg:classifiers":[
        {
            "category":"Real Estate",
            "subcategory":"Real Estate Agent",
            "type":"Services"
        }
    ],
    "sg:phone":"+1 252 473 1276",
    "sg:postcode":"27954",
    "sg:province":"NC",
    "wof:name":"Connie Sadler Inc",
    "wof:placetype":"venue"
},
  "geometry": {"coordinates":[-75.70281,35.931373],"type":"Point"}
}