{
  "type": "Feature",
  "properties": {
    "addr:full":"1925 N Roberts Ave Lumberton NC 28358",
    "addr:housenumber":"1925",
    "addr:postcode":"28358",
    "addr:street":"N Roberts Ave",
    "iso:country":"US",
    "sg:address":"1925 N Roberts Ave",
    "sg:city":"Lumberton",
    "sg:classifiers":[
        {
            "category":"Restaurant",
            "type":"Food & Drink"
        }
    ],
    "sg:phone":"+1 910 735 0352",
    "sg:postcode":"28358",
    "sg:province":"NC",
    "sg:tags":[
        "eating"
    ],
    "wof:name":"Zeno's Italian Restaurant",
    "wof:placetype":"venue"
},
  "geometry": {"coordinates":[-78.993487,34.633158],"type":"Point"}
}