{
  "type": "Feature",
  "properties": {
    "addr:full":"7000 Six Forks Rd Raleigh NC 27615",
    "addr:housenumber":"7000",
    "addr:postcode":"27615",
    "addr:street":"Six Forks Rd",
    "iso:country":"US",
    "sg:address":"7000 Six Forks Rd",
    "sg:city":"Raleigh",
    "sg:classifiers":[
        {
            "category":"Real Estate",
            "subcategory":"Developer",
            "type":"Services"
        }
    ],
    "sg:phone":"+1 919 855 0024",
    "sg:postcode":"27615",
    "sg:province":"NC",
    "sg:tags":[
        "land",
        "subdivider"
    ],
    "wof:name":"Barton Development Group",
    "wof:placetype":"venue"
},
  "geometry": {"coordinates":[-78.643722,35.873929],"type":"Point"}
}