{
  "type": "Feature",
  "properties": {
    "addr:full":"14418 Arbor Ridge Dr Charlotte NC 28273",
    "addr:housenumber":"14418",
    "addr:postcode":"28273",
    "addr:street":"Arbor Ridge Dr",
    "iso:country":"US",
    "sg:address":"14418 Arbor Ridge Dr",
    "sg:city":"Charlotte",
    "sg:classifiers":[
        {
            "category":"Professional",
            "subcategory":"Business Services",
            "type":"Services"
        }
    ],
    "sg:phone":"+1   ",
    "sg:postcode":"28273",
    "sg:province":"NC",
    "wof:name":"Trejos Enterprises Inc",
    "wof:placetype":"venue"
},
  "geometry": {"coordinates":[-80.977908,35.119908],"type":"Point"}
}