{
  "type": "Feature",
  "properties": {
    "addr:full":"400 Caldwell Ext Chapel Hill NC 27516",
    "addr:housenumber":"400",
    "addr:postcode":"27516",
    "addr:street":"Caldwell Ext",
    "iso:country":"US",
    "sg:address":"400 Caldwell Ext",
    "sg:city":"Chapel Hill",
    "sg:classifiers":[
        {
            "category":"Social Services",
            "subcategory":"Child Care",
            "type":"Services"
        }
    ],
    "sg:phone":"+1 919 929 1543",
    "sg:postcode":"27516",
    "sg:province":"NC",
    "sg:tags":[
        "day"
    ],
    "sg:website":"www.cspu6.org",
    "wof:name":"Community School For People Under Six",
    "wof:placetype":"venue"
},
  "geometry": {"coordinates":[-79.063103,35.916901],"type":"Point"}
}