{
  "type": "Feature",
  "properties": {
    "addr:full":"2561 US Hwy 158 Yanceyville NC 27379",
    "addr:housenumber":"2561",
    "addr:postcode":"27379",
    "addr:street":"Us Hwy 158",
    "iso:country":"US",
    "sg:address":"2561 US Hwy 158",
    "sg:city":"Yanceyville",
    "sg:classifiers":[
        {
            "category":"Professional",
            "subcategory":"Management & Consulting",
            "type":"Services"
        }
    ],
    "sg:phone":"+1   ",
    "sg:postcode":"27379",
    "sg:province":"NC",
    "wof:name":"B & B Red & White",
    "wof:placetype":"venue"
},
  "geometry": {"coordinates":[-79.23209199999999,36.405058],"type":"Point"}
}