{
  "type": "Feature",
  "properties": {
    "addr:full":"101 E Main St Williamston NC 27892",
    "addr:housenumber":"101",
    "addr:postcode":"27892",
    "addr:street":"E Main St",
    "iso:country":"US",
    "sg:address":"101 E Main St",
    "sg:city":"Williamston",
    "sg:classifiers":[
        {
            "category":"Wholesale",
            "subcategory":"Medical Equipment & Supplies",
            "type":"Manufacturing & Wholesale Goods"
        }
    ],
    "sg:phone":"+1 252 792 7144",
    "sg:postcode":"27892",
    "sg:province":"NC",
    "sg:tags":[
        "physician",
        "surgeon"
    ],
    "wof:name":"Angelic Medical Supply",
    "wof:placetype":"venue"
},
  "geometry": {"coordinates":[-77.05365999999999,35.855841],"type":"Point"}
}