{
  "type": "Feature",
  "properties": {
    "addr:full":"342 N Eastern Blvd Fayetteville NC 28301",
    "addr:housenumber":"342",
    "addr:postcode":"28301",
    "addr:street":"N Eastern Blvd",
    "iso:country":"US",
    "sg:address":"342 N Eastern Blvd",
    "sg:city":"Fayetteville",
    "sg:classifiers":[
        {
            "category":"Wholesale",
            "subcategory":"Machinery & Supplies",
            "type":"Manufacturing & Wholesale Goods"
        }
    ],
    "sg:phone":"+1 910 223 0777",
    "sg:postcode":"28301",
    "sg:province":"NC",
    "sg:tags":[
        "salon",
        "beauty"
    ],
    "wof:name":"Young's Beauty Supply",
    "wof:placetype":"venue"
},
  "geometry": {"coordinates":[-78.864518,35.051047],"type":"Point"}
}