{
  "type": "Feature",
  "properties": {
    "addr:full":"120 W Worthington Ave Charlotte NC 28203",
    "addr:housenumber":"120",
    "addr:postcode":"28203",
    "addr:street":"W Worthington Ave",
    "iso:country":"US",
    "sg:address":"120 W Worthington Ave",
    "sg:city":"Charlotte",
    "sg:classifiers":[
        {
            "category":"Professional",
            "subcategory":"Business Services",
            "type":"Services"
        }
    ],
    "sg:phone":"+1 704 377 9088",
    "sg:postcode":"28203",
    "sg:province":"NC",
    "sg:tags":[
        "interior",
        "consultant",
        "design",
        "decorator"
    ],
    "wof:name":"Cathy W Jones Interiors Allied",
    "wof:placetype":"venue"
},
  "geometry": {"coordinates":[-80.86062699999999,35.212121],"type":"Point"}
}