{
  "type": "Feature",
  "properties": {
    "iso:country":"US",
    "sg:address":"107 Brevard Rd",
    "sg:city":"Asheville",
    "sg:classifiers":[
        {
            "category":"Health Services",
            "subcategory":"Health Practitioner",
            "type":"Services"
        }
    ],
    "sg:phone":"+1 828 253 6666",
    "sg:postcode":"28806",
    "sg:province":"NC",
    "sg:tags":[
        "psychotherapist"
    ],
    "wof:name":"Care Link",
    "wof:placetype":"venue"
},
  "geometry": {"coordinates":[-82.59356099999999,35.572667],"type":"Point"}
}