{
  "type": "Feature",
  "properties": {
    "addr:full":"2200 W Vernon Ave Kinston NC 28504",
    "addr:housenumber":"2200",
    "addr:postcode":"28504",
    "addr:street":"W Vernon Ave",
    "iso:country":"US",
    "sg:address":"2200 W Vernon Ave",
    "sg:city":"Kinston",
    "sg:classifiers":[
        {
            "category":"Shopping",
            "subcategory":"Computers & Home Electronics",
            "type":"Retail Goods"
        }
    ],
    "sg:phone":"+1 252 523 8933",
    "sg:postcode":"28504",
    "sg:province":"NC",
    "sg:tags":[
        "appliance",
        "consumer"
    ],
    "wof:name":"Highland TV Inc",
    "wof:placetype":"venue"
},
  "geometry": {"coordinates":[-77.615848,35.269087],"type":"Point"}
}