{
  "type": "Feature",
  "properties": {
    "iso:country":"US",
    "sg:address":"2301 Pickard Mountain Rd",
    "sg:city":"Hillsborough",
    "sg:classifiers":[
        {
            "category":"Building & Trades",
            "subcategory":"Construction",
            "type":"Services"
        }
    ],
    "sg:phone":"+1 919 933 3559",
    "sg:postcode":"27278",
    "sg:province":"NC",
    "sg:tags":[
        "residential"
    ],
    "wof:name":"Out of The Woods Builders Inc",
    "wof:placetype":"venue"
},
  "geometry": {"coordinates":[-79.16389100000001,35.963142],"type":"Point"}
}