{
  "type": "Feature",
  "properties": {
    "addr:full":"300 N Steele St Sanford NC 27330",
    "addr:housenumber":"300",
    "addr:postcode":"27330",
    "addr:street":"N Steele St",
    "iso:country":"US",
    "sg:address":"300 N Steele St",
    "sg:city":"Sanford",
    "sg:classifiers":[
        {
            "category":"Retail",
            "subcategory":"Auto Repair",
            "type":"Services"
        }
    ],
    "sg:phone":"+1 919 775 2432",
    "sg:postcode":"27330",
    "sg:province":"NC",
    "sg:tags":[
        "repairing",
        "automobile",
        "general"
    ],
    "wof:name":"Sloan Motor Co",
    "wof:placetype":"venue"
},
  "geometry": {"coordinates":[-79.182113,35.484218],"type":"Point"}
}