{
  "type": "Feature",
  "properties": {
    "iso:country":"US",
    "sg:address":"8701 State Hwy 11",
    "sg:city":"Willard",
    "sg:classifiers":[
        {
            "category":"Retail",
            "subcategory":"Repair Shop",
            "type":"Services"
        }
    ],
    "sg:phone":"+1   ",
    "sg:postcode":"28478",
    "sg:province":"NC",
    "wof:name":"Currie Hornes Marine Repair L",
    "wof:placetype":"venue"
},
  "geometry": {"coordinates":[-77.974553,34.692811],"type":"Point"}
}