{
  "type": "Feature",
  "properties": {
    "iso:country":"US",
    "sg:address":"1501 Old Mill Rd",
    "sg:city":"Rocky Mount",
    "sg:classifiers":[
        {
            "category":"Organizations",
            "subcategory":"Religious Organization",
            "type":"Services"
        }
    ],
    "sg:phone":"+1   ",
    "sg:postcode":"27803",
    "sg:province":"NC",
    "wof:name":"Gospel Singers",
    "wof:placetype":"venue"
},
  "geometry": {"coordinates":[-77.843734,35.935459],"type":"Point"}
}