{
  "type": "Feature",
  "properties": {
    "addr:full":"350 Toulon Dr Wilmington NC 28405",
    "addr:housenumber":"350",
    "addr:postcode":"28405",
    "addr:street":"Toulon Dr",
    "iso:country":"US",
    "sg:address":"350 Toulon Dr",
    "sg:city":"Wilmington",
    "sg:classifiers":[
        {
            "category":"Retail",
            "subcategory":"Animal Services",
            "type":"Services"
        }
    ],
    "sg:phone":"+1 910 790 9123",
    "sg:postcode":"28405",
    "sg:province":"NC",
    "wof:name":"Good As Gold Companion Care",
    "wof:placetype":"venue"
},
  "geometry": {"coordinates":[-77.839828,34.250816],"type":"Point"}
}