{
  "type": "Feature",
  "properties": {
    "addr:full":"1935 E Woodlawn Rd Charlotte NC 28209",
    "addr:housenumber":"1935",
    "addr:postcode":"28209",
    "addr:street":"E Woodlawn Rd",
    "iso:country":"US",
    "sg:address":"1935 E Woodlawn Rd",
    "sg:city":"Charlotte",
    "sg:classifiers":[
        {
            "category":"Manufacturing",
            "subcategory":"Printing",
            "type":"Manufacturing & Wholesale Goods"
        }
    ],
    "sg:phone":"+1 704 523 7111",
    "sg:postcode":"28209",
    "sg:province":"NC",
    "sg:tags":[
        "publisher",
        "software"
    ],
    "wof:name":"Kirkwood Technologies",
    "wof:placetype":"venue"
},
  "geometry": {"coordinates":[-80.843626,35.171188],"type":"Point"}
}