{
  "type": "Feature",
  "properties": {
    "iso:country":"US",
    "sg:address":"10100 Moores Chapel Rd",
    "sg:city":"Charlotte",
    "sg:classifiers":[
        {
            "category":"Food & Beverages",
            "subcategory":"Groceries & Convenience Stores",
            "type":"Retail Goods"
        }
    ],
    "sg:phone":"+1 704 399 9557",
    "sg:postcode":"28214",
    "sg:province":"NC",
    "sg:tags":[
        "station",
        "gasoline"
    ],
    "wof:name":"Snappys",
    "wof:placetype":"venue"
},
  "geometry": {"coordinates":[-80.969872,35.274879],"type":"Point"}
}