{
  "type": "Feature",
  "properties": {
    "addr:full":"3341 Courtney Church Rd Yadkinville NC 27055",
    "addr:housenumber":"3341",
    "addr:postcode":"27055",
    "addr:street":"Courtney Church Rd",
    "iso:country":"US",
    "sg:address":"3341 Courtney Church Rd",
    "sg:city":"Yadkinville",
    "sg:classifiers":[
        {
            "category":"Organizations",
            "subcategory":"Religious Organization",
            "type":"Services"
        }
    ],
    "sg:phone":"+1 336 463 2681",
    "sg:postcode":"27055",
    "sg:province":"NC",
    "wof:name":"Courtney Baptist Church",
    "wof:placetype":"venue"
},
  "geometry": {"coordinates":[-80.620272,36.059816],"type":"Point"}
}