{
  "type": "Feature",
  "properties": {
    "addr:full":"10035 N State Hwy 16 Millers Creek NC 28651",
    "addr:housenumber":"10035",
    "addr:postcode":"28651",
    "addr:street":"N State Hwy 16 Millers",
    "iso:country":"US",
    "sg:address":"10035 N State Hwy 16",
    "sg:city":"Millers Creek",
    "sg:classifiers":[
        {
            "category":"Government",
            "subcategory":"Fire Station",
            "type":"Public Place"
        }
    ],
    "sg:phone":"+1 336 667 2842",
    "sg:postcode":"28651",
    "sg:province":"NC",
    "sg:tags":[
        "protection"
    ],
    "wof:name":"Wilbur Volunteer Fire Dept",
    "wof:placetype":"venue"
},
  "geometry": {"coordinates":[-81.307385,36.255172],"type":"Point"}
}