{
  "type": "Feature",
  "properties": {
    "iso:country":"US",
    "sg:address":"108 N Blue Ridge Rd",
    "sg:city":"Black Mountain",
    "sg:classifiers":[
        {
            "category":"Real Estate",
            "subcategory":"Real Estate Operator",
            "type":"Services"
        }
    ],
    "sg:phone":"+1 828 669 5948",
    "sg:postcode":"28711",
    "sg:province":"NC",
    "sg:tags":[
        "apartment"
    ],
    "wof:name":"Blue Ridge Apartments Senior",
    "wof:placetype":"venue"
},
  "geometry": {"coordinates":[-82.341595,35.612097],"type":"Point"}
}