{
  "type": "Feature",
  "properties": {
    "addr:full":"4442 Westridge Dr Charlotte NC 28208",
    "addr:housenumber":"4442",
    "addr:postcode":"28208",
    "addr:street":"Westridge Dr",
    "iso:country":"US",
    "sg:address":"4442 Westridge Dr",
    "sg:city":"Charlotte",
    "sg:classifiers":[
        {
            "category":"Personal",
            "subcategory":"Beauty Salon",
            "type":"Services"
        }
    ],
    "sg:phone":"+1 704 333 9572",
    "sg:postcode":"28208",
    "sg:province":"NC",
    "sg:tags":[
        "manicuring"
    ],
    "wof:name":"Zoe Nail Salon",
    "wof:placetype":"venue"
},
  "geometry": {"coordinates":[-80.905928,35.261543],"type":"Point"}
}