{
  "type": "Feature",
  "properties": {
    "addr:full":"1023 N Main St Roxboro NC 27573",
    "addr:housenumber":"1023",
    "addr:postcode":"27573",
    "addr:street":"N Main St",
    "iso:country":"US",
    "sg:address":"1023 N Main St",
    "sg:city":"Roxboro",
    "sg:classifiers":[
        {
            "category":"Wholesale",
            "subcategory":"Hardware",
            "type":"Manufacturing & Wholesale Goods"
        }
    ],
    "sg:phone":"+1 336 597 2256",
    "sg:postcode":"27573",
    "sg:province":"NC",
    "sg:tags":[
        "machine",
        "making",
        "ice",
        "equipment"
    ],
    "wof:name":"Roxboro Refrigeration",
    "wof:placetype":"venue"
},
  "geometry": {"coordinates":[-78.97244999999999,36.409667],"type":"Point"}
}