{
  "type": "Feature",
  "properties": {
    "addr:full":"203 Amberglow Pl Cary NC 27513",
    "addr:housenumber":"203",
    "addr:postcode":"27513",
    "addr:street":"Amberglow Pl",
    "iso:country":"US",
    "sg:address":"203 Amberglow Pl",
    "sg:city":"Cary",
    "sg:classifiers":[
        {
            "category":"Utilities",
            "subcategory":"Telephone",
            "type":"Services"
        }
    ],
    "sg:phone":"+1 919 463 9669",
    "sg:postcode":"27513",
    "sg:province":"NC",
    "sg:tags":[
        "communications"
    ],
    "wof:name":"McLainhomecom",
    "wof:placetype":"venue"
},
  "geometry": {"coordinates":[-78.820652,35.767742],"type":"Point"}
}