{
  "type": "Feature",
  "properties": {
    "iso:country":"US",
    "sg:address":"50 Merrimon Ave",
    "sg:city":"Asheville",
    "sg:classifiers":[
        {
            "category":"Professional",
            "subcategory":"Lawyer & Legal Services",
            "type":"Services"
        }
    ],
    "sg:phone":"+1 828 251 9310",
    "sg:postcode":"28801",
    "sg:province":"NC",
    "sg:tags":[
        "attorney"
    ],
    "wof:name":"Kelly & Rowe",
    "wof:placetype":"venue"
},
  "geometry": {"coordinates":[-82.553541,35.601382],"type":"Point"}
}