{
  "type": "Feature",
  "properties": {
    "iso:country":"US",
    "sg:address":"1493 Mecklenburg Hwy",
    "sg:city":"Mooresville",
    "sg:classifiers":[
        {
            "category":"Retail",
            "subcategory":"Animal Services",
            "type":"Services"
        }
    ],
    "sg:phone":"+1 704 892 9970",
    "sg:postcode":"28115",
    "sg:province":"NC",
    "sg:tags":[
        "pet",
        "grooming"
    ],
    "wof:name":"Darlene's Pampered Pets",
    "wof:placetype":"venue"
},
  "geometry": {"coordinates":[-80.84715799999999,35.543311],"type":"Point"}
}