{
  "type": "Feature",
  "properties": {
    "addr:full":"3603 Calvert St Greensboro NC 27405",
    "addr:housenumber":"3603",
    "addr:postcode":"27405",
    "addr:street":"Calvert St",
    "iso:country":"US",
    "sg:address":"3603 Calvert St",
    "sg:city":"Greensboro",
    "sg:classifiers":[
        {
            "category":"Social Services",
            "subcategory":"Child Care",
            "type":"Services"
        }
    ],
    "sg:phone":"+1 336 288 9265",
    "sg:postcode":"27405",
    "sg:province":"NC",
    "wof:name":"All Gods Children Daycare",
    "wof:placetype":"venue"
},
  "geometry": {"coordinates":[-79.791978,36.124743],"type":"Point"}
}