{
  "type": "Feature",
  "properties": {
    "addr:full":"622 Kanuga Rd Hendersonville NC 28739",
    "addr:housenumber":"622",
    "addr:postcode":"28739",
    "addr:street":"Kanuga Rd",
    "iso:country":"US",
    "sg:address":"622 Kanuga Rd",
    "sg:city":"Hendersonville",
    "sg:classifiers":[
        {
            "category":"Health Services",
            "subcategory":"Clinic",
            "type":"Services"
        }
    ],
    "sg:phone":"+1 828 696 0946",
    "sg:postcode":"28739",
    "sg:province":"NC",
    "sg:tags":[
        "home"
    ],
    "wof:name":"Compassionate Home Care Inc",
    "wof:placetype":"venue"
},
  "geometry": {"coordinates":[-82.462609,35.307466],"type":"Point"}
}