{
  "type": "Feature",
  "properties": {
    "addr:full":"1820 Amethyst Ridge Rd Raleigh NC 27604",
    "addr:housenumber":"1820",
    "addr:postcode":"27604",
    "addr:street":"Amethyst Ridge Rd",
    "iso:country":"US",
    "sg:address":"1820 Amethyst Ridge Rd",
    "sg:city":"Raleigh",
    "sg:classifiers":[
        {
            "category":"Professional",
            "subcategory":"Business Services",
            "type":"Services"
        }
    ],
    "sg:phone":"+1   ",
    "sg:postcode":"27604",
    "sg:province":"NC",
    "wof:name":"M Walker Builders",
    "wof:placetype":"venue"
},
  "geometry": {"coordinates":[-78.496064,35.826188],"type":"Point"}
}