{
  "type": "Feature",
  "properties": {
    "addr:full":"37 38th Ave NW Hickory NC 28601",
    "addr:housenumber":"37",
    "addr:postcode":"28601",
    "addr:street":"38Th Ave Nw",
    "iso:country":"US",
    "sg:address":"37 38th Ave NW",
    "sg:city":"Hickory",
    "sg:classifiers":[
        {
            "category":"Professional",
            "type":"Services"
        }
    ],
    "sg:phone":"+1 828 327 9999",
    "sg:postcode":"28601",
    "sg:province":"NC",
    "wof:name":"Millsaps",
    "wof:placetype":"venue"
},
  "geometry": {"coordinates":[-81.32305100000001,35.781644],"type":"Point"}
}