{
  "type": "Feature",
  "properties": {
    "iso:country":"US",
    "sg:address":"3041 Control Tower Rd",
    "sg:city":"Fayetteville",
    "sg:classifiers":[
        {
            "category":"Government",
            "subcategory":"Office",
            "type":"Public Place"
        }
    ],
    "sg:phone":"+1 910 484 6723",
    "sg:postcode":"28306",
    "sg:province":"NC",
    "sg:tags":[
        "transportation"
    ],
    "wof:name":"Airport Traffic Control Tower",
    "wof:placetype":"venue"
},
  "geometry": {"coordinates":[-78.88608499999999,34.990677],"type":"Point"}
}