{
  "type": "Feature",
  "properties": {
    "iso:country":"US",
    "sg:address":"311 N East St",
    "sg:city":"Kinston",
    "sg:classifiers":[
        {
            "category":"Organizations",
            "subcategory":"Religious Organization",
            "type":"Services"
        }
    ],
    "sg:phone":"+1 252 523 3333",
    "sg:postcode":"28501",
    "sg:province":"NC",
    "sg:tags":[
        "church"
    ],
    "wof:name":"Greater Mt Zion Baptist Church",
    "wof:placetype":"venue"
},
  "geometry": {"coordinates":[-77.575851,35.263639],"type":"Point"}
}