{
  "type": "Feature",
  "properties": {
    "iso:country":"US",
    "sg:address":"118 N Churton St",
    "sg:city":"Hillsborough",
    "sg:classifiers":[
        {
            "category":"Education",
            "subcategory":"Special Training",
            "type":"Public Place"
        }
    ],
    "sg:phone":"+1 919 732 0868",
    "sg:postcode":"27278",
    "sg:province":"NC",
    "sg:tags":[
        "tutoring"
    ],
    "wof:name":"Orange County Literacy Council",
    "wof:placetype":"venue"
},
  "geometry": {"coordinates":[-79.099394,36.076745],"type":"Point"}
}