{
  "type": "Feature",
  "properties": {
    "addr:full":"130 Dove Meadows Dr Archdale NC 27263",
    "addr:housenumber":"130",
    "addr:postcode":"27263",
    "addr:street":"Dove Meadows Dr",
    "iso:country":"US",
    "sg:address":"130 Dove Meadows Dr",
    "sg:city":"Archdale",
    "sg:classifiers":[
        {
            "category":"Organizations",
            "subcategory":"Religious Organization",
            "type":"Services"
        }
    ],
    "sg:phone":"+1 336 885 7926",
    "sg:postcode":"27263",
    "sg:province":"NC",
    "sg:tags":[
        "church"
    ],
    "wof:name":"Full Gospel Revival Ctr",
    "wof:placetype":"venue"
},
  "geometry": {"coordinates":[-79.94370499999999,35.905306],"type":"Point"}
}