{
  "type": "Feature",
  "properties": {
    "addr:full":"2207 Front St Beaufort NC 28516",
    "addr:housenumber":"2207",
    "addr:postcode":"28516",
    "addr:street":"Front St",
    "iso:country":"US",
    "sg:address":"2207 Front St",
    "sg:city":"Beaufort",
    "sg:classifiers":[
        {
            "category":"Organizations",
            "subcategory":"Community Association",
            "type":"Services"
        }
    ],
    "sg:phone":"+1   ",
    "sg:postcode":"28516",
    "sg:province":"NC",
    "wof:name":"Independent Order of Odd",
    "wof:placetype":"venue"
},
  "geometry": {"coordinates":[-76.63735200000001,34.711134],"type":"Point"}
}