{
  "type": "Feature",
  "properties": {
    "iso:country":"US",
    "sg:address":"7200 Ridge Lane Rd",
    "sg:city":"Charlotte",
    "sg:classifiers":[
        {
            "category":"Wholesale",
            "subcategory":"Hardware",
            "type":"Manufacturing & Wholesale Goods"
        },
        {
            "category":"Wholesale",
            "subcategory":"Durable Goods & Equipment",
            "type":"Manufacturing & Wholesale Goods"
        }
    ],
    "sg:phone":"+1 704 597 1700",
    "sg:postcode":"28262",
    "sg:province":"NC",
    "sg:tags":[
        "plumbing",
        "manufacturer",
        "heating",
        "representative",
        "supply"
    ],
    "wof:name":"Stover Sales Co Inc",
    "wof:placetype":"venue"
},
  "geometry": {"coordinates":[-80.779473,35.30373],"type":"Point"}
}