{
  "type": "Feature",
  "properties": {
    "addr:full":"3515 S Holden Rd Greensboro NC 27407",
    "addr:housenumber":"3515",
    "addr:postcode":"27407",
    "addr:street":"S Holden Rd",
    "iso:country":"US",
    "sg:address":"3515 S Holden Rd",
    "sg:city":"Greensboro",
    "sg:classifiers":[
        {
            "category":"Home & Garden",
            "subcategory":"Building Materials",
            "type":"Retail Goods"
        }
    ],
    "sg:phone":"+1 336 292 8700",
    "sg:postcode":"27407",
    "sg:province":"NC",
    "wof:name":"Fleetwood Home Center",
    "wof:placetype":"venue"
},
  "geometry": {"coordinates":[-79.844179,36.017443],"type":"Point"}
}