{
  "type": "Feature",
  "properties": {
    "iso:country":"US",
    "sg:address":"1379 Tellowee Rd",
    "sg:city":"Eden",
    "sg:classifiers":[
        {
            "category":"Utilities",
            "subcategory":"Refuse",
            "type":"Services"
        }
    ],
    "sg:phone":"+1 336 623 8384",
    "sg:postcode":"27288",
    "sg:province":"NC",
    "sg:tags":[
        "waste",
        "management"
    ],
    "wof:name":"Republic Services Inc",
    "wof:placetype":"venue"
},
  "geometry": {"coordinates":[-79.730587,36.458985],"type":"Point"}
}