{
  "type": "Feature",
  "properties": {
    "iso:country":"US",
    "sg:address":"3709 W Hedrick Dr",
    "sg:city":"Morehead City",
    "sg:classifiers":[
        {
            "category":"Building & Trades",
            "subcategory":"Construction",
            "type":"Services"
        }
    ],
    "sg:phone":"+1 252 726 7566",
    "sg:postcode":"28557",
    "sg:province":"NC",
    "sg:tags":[
        "track",
        "running",
        "tennis",
        "court",
        "contractor"
    ],
    "wof:name":"Advantage Sports Surfaces Inc",
    "wof:placetype":"venue"
},
  "geometry": {"coordinates":[-76.765197,34.740375],"type":"Point"}
}