{
  "type": "Feature",
  "properties": {
    "iso:country":"US",
    "sg:address":"8712 Tamarron Dr",
    "sg:city":"Charlotte",
    "sg:classifiers":[
        {
            "category":"Autos & Motor Vehicles",
            "subcategory":"Auto Supplies",
            "type":"Retail Goods"
        }
    ],
    "sg:phone":"+1 704 542 0248",
    "sg:postcode":"28277",
    "sg:province":"NC",
    "sg:tags":[
        "equipment",
        "racing",
        "car",
        "automobile"
    ],
    "wof:name":"Unjustified Motorsports",
    "wof:placetype":"venue"
},
  "geometry": {"coordinates":[-80.81586299999999,35.030552],"type":"Point"}
}