{
  "type": "Feature",
  "properties": {
    "iso:country":"US",
    "sg:address":"1517 S Brightleaf Blvd",
    "sg:city":"Smithfield",
    "sg:classifiers":[
        {
            "category":"Wholesale",
            "subcategory":"Durable Goods & Equipment",
            "type":"Manufacturing & Wholesale Goods"
        }
    ],
    "sg:phone":"+1 919 934 7904",
    "sg:postcode":"27577",
    "sg:province":"NC",
    "sg:tags":[
        "importer"
    ],
    "wof:name":"JWM",
    "wof:placetype":"venue"
},
  "geometry": {"coordinates":[-78.35788700000001,35.492185],"type":"Point"}
}