{
  "type": "Feature",
  "properties": {
    "addr:full":"112 Village Rd NE Leland NC 28451",
    "addr:housenumber":"112",
    "addr:postcode":"28451",
    "addr:street":"Village Rd Ne",
    "iso:country":"US",
    "sg:address":"112 Village Rd NE",
    "sg:city":"Leland",
    "sg:classifiers":[
        {
            "category":"Food & Beverages",
            "subcategory":"Groceries & Convenience Stores",
            "type":"Retail Goods"
        }
    ],
    "sg:phone":"+1 910 371 2696",
    "sg:postcode":"28451",
    "sg:province":"NC",
    "sg:tags":[
        "grocer"
    ],
    "sg:website":"www.pigglywiggly.com",
    "wof:name":"Piggly Wiggly",
    "wof:placetype":"venue"
},
  "geometry": {"coordinates":[-78.00906999999999,34.239603],"type":"Point"}
}