{
  "type": "Feature",
  "properties": {
    "addr:full":"610 W Ritchie Rd Salisbury NC 28147",
    "addr:housenumber":"610",
    "addr:postcode":"28147",
    "addr:street":"W Ritchie Rd",
    "iso:country":"US",
    "sg:address":"610 W Ritchie Rd",
    "sg:city":"Salisbury",
    "sg:phone":"+1 704 637 1680",
    "sg:postcode":"28147",
    "sg:province":"NC",
    "wof:name":"Extreme Motorcycles",
    "wof:placetype":"venue"
},
  "geometry": {"coordinates":[-80.494871,35.631271],"type":"Point"}
}