{
  "type": "Feature",
  "properties": {
    "addr:full":"4333 Triple Crown Dr SW Concord NC 28027",
    "addr:housenumber":"4333",
    "addr:postcode":"28027",
    "addr:street":"Triple Crown Dr Sw",
    "iso:country":"US",
    "sg:address":"4333 Triple Crown Dr SW",
    "sg:city":"Concord",
    "sg:classifiers":[
        {
            "category":"Freight",
            "type":"Transportation"
        }
    ],
    "sg:phone":"+1 704 707 2424",
    "sg:postcode":"28027",
    "sg:province":"NC",
    "sg:tags":[
        "broker",
        "trucking"
    ],
    "wof:name":"Dimension Trucking",
    "wof:placetype":"venue"
},
  "geometry": {"coordinates":[-80.621197,35.353341],"type":"Point"}
}