{
  "type": "Feature",
  "properties": {
    "iso:country":"US",
    "sg:address":"916 Richard Switch Rd",
    "sg:city":"Currie",
    "sg:classifiers":[
        {
            "category":"Professional",
            "type":"Services"
        }
    ],
    "sg:phone":"+1 910 259 8680",
    "sg:postcode":"28435",
    "sg:province":"NC",
    "wof:name":"Litwiler Loggin Co",
    "wof:placetype":"venue"
},
  "geometry": {"coordinates":[-78.06507499999999,34.431893],"type":"Point"}
}