{
  "type": "Feature",
  "properties": {
    "iso:country":"US",
    "sg:address":"915 Hay St",
    "sg:city":"Fayetteville",
    "sg:classifiers":[
        {
            "category":"Shopping",
            "subcategory":"Pharmacy",
            "type":"Retail Goods"
        }
    ],
    "sg:phone":"+1 910 485 2167",
    "sg:postcode":"28305",
    "sg:province":"NC",
    "sg:website":"www.rxfixer.com",
    "wof:name":"Prescription Center",
    "wof:placetype":"venue"
},
  "geometry": {"coordinates":[-78.896137,35.056105],"type":"Point"}
}