{
  "type": "Feature",
  "properties": {
    "addr:full":"713 N Fayetteville St Asheboro NC 27203",
    "addr:housenumber":"713",
    "addr:postcode":"27203",
    "addr:street":"N;St",
    "iso:country":"US",
    "sg:address":"713 N Fayetteville St",
    "sg:city":"Asheboro",
    "sg:classifiers":[
        {
            "category":"Health Services",
            "subcategory":"Hospital",
            "type":"Services"
        }
    ],
    "sg:phone":"+1 336 626 0033",
    "sg:postcode":"27203",
    "sg:province":"NC",
    "sg:tags":[
        "general"
    ],
    "wof:name":"Randolph Cancer Center",
    "wof:placetype":"venue"
},
  "geometry": {"coordinates":[-79.81084,35.716937],"type":"Point"}
}