{
  "type": "Feature",
  "properties": {
    "iso:country":"US",
    "sg:address":"3424 Neuma Dr",
    "sg:city":"Zebulon",
    "sg:classifiers":[
        {
            "category":"Personal",
            "type":"Services"
        }
    ],
    "sg:phone":"+1 919 269 9355",
    "sg:postcode":"27597",
    "sg:province":"NC",
    "sg:tags":[
        "therapist",
        "massage"
    ],
    "wof:name":"Womens Wellness Massage",
    "wof:placetype":"venue"
},
  "geometry": {"coordinates":[-78.33068900000001,35.880039],"type":"Point"}
}