{
  "type": "Feature",
  "properties": {
    "iso:country":"US",
    "sg:address":"1143 Executive Cir",
    "sg:city":"Cary",
    "sg:classifiers":[
        {
            "category":"Real Estate",
            "subcategory":"Surveying",
            "type":"Services"
        }
    ],
    "sg:phone":"+1 919 469 4738",
    "sg:postcode":"27511",
    "sg:province":"NC",
    "sg:tags":[
        "surveyor"
    ],
    "wof:name":"Sullivan Surveying Co",
    "wof:placetype":"venue"
},
  "geometry": {"coordinates":[-78.781835,35.767416],"type":"Point"}
}