{
  "type": "Feature",
  "properties": {
    "addr:full":"10020 John Russell Rd Charlotte NC 28213",
    "addr:housenumber":"10020",
    "addr:postcode":"28213",
    "addr:street":"John Russell Rd",
    "iso:country":"US",
    "sg:address":"10020 John Russell Rd",
    "sg:city":"Charlotte",
    "sg:classifiers":[
        {
            "category":"Wholesale",
            "subcategory":"Plants",
            "type":"Manufacturing & Wholesale Goods"
        }
    ],
    "sg:phone":"+1 704 596 3220",
    "sg:postcode":"28213",
    "sg:province":"NC",
    "sg:tags":[
        "nursery",
        "tree"
    ],
    "wof:name":"Baucom's Nursery Co",
    "wof:placetype":"venue"
},
  "geometry": {"coordinates":[-80.71247200000001,35.280338],"type":"Point"}
}