{
  "type": "Feature",
  "properties": {
    "addr:full":"1300 Sterling Green Dr Morrisville NC 27560",
    "addr:housenumber":"1300",
    "addr:postcode":"27560",
    "addr:street":"Sterling Green Dr",
    "iso:country":"US",
    "sg:address":"1300 Sterling Green Dr",
    "sg:city":"Morrisville",
    "sg:classifiers":[
        {
            "category":"Real Estate",
            "subcategory":"Real Estate Operator",
            "type":"Services"
        }
    ],
    "sg:phone":"+1 919 468 1668",
    "sg:postcode":"27560",
    "sg:province":"NC",
    "sg:tags":[
        "apartment"
    ],
    "wof:name":"Sterling Green At Preston Apartments",
    "wof:placetype":"venue"
},
  "geometry": {"coordinates":[-78.82669799999999,35.812199],"type":"Point"}
}