{
  "type": "Feature",
  "properties": {
    "iso:country":"US",
    "sg:address":"633 Foxfire Cir",
    "sg:city":"Jacksonville",
    "sg:classifiers":[
        {
            "category":"Utilities",
            "subcategory":"Cable",
            "type":"Services"
        }
    ],
    "sg:phone":"+1 910 455 6362",
    "sg:postcode":"28546",
    "sg:province":"NC",
    "sg:tags":[
        "television"
    ],
    "wof:name":"J L Cable Comaiori Josep",
    "wof:placetype":"venue"
},
  "geometry": {"coordinates":[-77.442702,34.81076],"type":"Point"}
}