{
  "type": "Feature",
  "properties": {
    "addr:full":"826 Elm St Eden NC 27288",
    "addr:housenumber":"826",
    "addr:postcode":"27288",
    "addr:street":"Elm St",
    "iso:country":"US",
    "sg:address":"826 Elm St",
    "sg:city":"Eden",
    "sg:classifiers":[
        {
            "category":"Insurance",
            "subcategory":"Insurance Agent",
            "type":"Services"
        }
    ],
    "sg:phone":"+1 336 623 1600",
    "sg:postcode":"27288",
    "sg:province":"NC",
    "wof:name":"Berrier Insurance Agency",
    "wof:placetype":"venue"
},
  "geometry": {"coordinates":[-79.77818600000001,36.485282],"type":"Point"}
}