{
  "type": "Feature",
  "properties": {
    "iso:country":"US",
    "sg:address":"1950 4th St SW",
    "sg:city":"Hickory",
    "sg:classifiers":[
        {
            "category":"Government",
            "subcategory":"Office",
            "type":"Public Place"
        }
    ],
    "sg:phone":"+1 828 322 2509",
    "sg:postcode":"28602",
    "sg:province":"NC",
    "sg:tags":[
        "village"
    ],
    "wof:name":"Brookford Maintenance",
    "wof:placetype":"venue"
},
  "geometry": {"coordinates":[-81.35028,35.703773],"type":"Point"}
}