{
  "type": "Feature",
  "properties": {
    "addr:full":"770 Singletary Mill Pond Rd Bladenboro NC 28320",
    "addr:housenumber":"770",
    "addr:postcode":"28320",
    "addr:street":"Singletary Mill Pond Rd",
    "iso:country":"US",
    "sg:address":"770 Singletary Mill Pond Rd",
    "sg:city":"Bladenboro",
    "sg:classifiers":[
        {
            "category":"Building & Trades",
            "subcategory":"Construction",
            "type":"Services"
        }
    ],
    "sg:phone":"+1 910 648 4925",
    "sg:postcode":"28320",
    "sg:province":"NC",
    "sg:tags":[
        "paving",
        "contractor"
    ],
    "wof:name":"Smith Brothers Paving Inc",
    "wof:placetype":"venue"
},
  "geometry": {"coordinates":[-78.77343500000001,34.60572],"type":"Point"}
}