{
  "type": "Feature",
  "properties": {
    "addr:full":"5701 Northlake Dr Greensboro NC 27410",
    "addr:housenumber":"5701",
    "addr:postcode":"27410",
    "addr:street":"Northlake Dr",
    "iso:country":"US",
    "sg:address":"5701 Northlake Dr",
    "sg:city":"Greensboro",
    "sg:classifiers":[
        {
            "category":"Retail",
            "subcategory":"Repair Shop",
            "type":"Services"
        }
    ],
    "sg:phone":"+1   ",
    "sg:postcode":"27410",
    "sg:province":"NC",
    "sg:tags":[
        "electrical"
    ],
    "wof:name":"Two Feathers Service Co",
    "wof:placetype":"venue"
},
  "geometry": {"coordinates":[-79.891915,36.110102],"type":"Point"}
}