{
  "type": "Feature",
  "properties": {
    "iso:country":"US",
    "sg:address":"822 Mocksville Hwy",
    "sg:city":"Statesville",
    "sg:classifiers":[
        {
            "category":"Retail",
            "subcategory":"Auto Rental",
            "type":"Services"
        }
    ],
    "sg:phone":"+1 704 876 1257",
    "sg:postcode":"28625",
    "sg:province":"NC",
    "sg:tags":[
        "truck",
        "lease"
    ],
    "wof:name":"John W Douglas Jr Inc",
    "wof:placetype":"venue"
},
  "geometry": {"coordinates":[-80.79225,35.806931],"type":"Point"}
}