{
  "type": "Feature",
  "properties": {
    "addr:full":"1110 Buck Jones Rd Raleigh NC 27606",
    "addr:housenumber":"1110",
    "addr:postcode":"27606",
    "addr:street":"Buck Jones Rd",
    "iso:country":"US",
    "sg:address":"1110 Buck Jones Rd",
    "sg:city":"Raleigh",
    "sg:classifiers":[
        {
            "category":"Education",
            "subcategory":"School",
            "type":"Public Place"
        }
    ],
    "sg:phone":"+1 919 388 8437",
    "sg:postcode":"27606",
    "sg:province":"NC",
    "wof:name":"Insurance Educational Systems",
    "wof:placetype":"venue"
},
  "geometry": {"coordinates":[-78.74099699999999,35.768299],"type":"Point"}
}