{
  "type": "Feature",
  "properties": {
    "iso:country":"US",
    "sg:address":"2590 Farrington Rd",
    "sg:city":"Apex",
    "sg:classifiers":[
        {
            "category":"Professional",
            "type":"Services"
        },
        {
            "category":"Retail",
            "subcategory":"Repair Shop",
            "type":"Services"
        }
    ],
    "sg:phone":"+1 919 926 8756",
    "sg:postcode":"27523",
    "sg:province":"NC",
    "sg:tags":[
        "antique",
        "refinishing",
        "furniture"
    ],
    "sg:website":"http://www.heritagestripandfinish.com",
    "wof:name":"Heritage Strip & Finish",
    "wof:placetype":"venue"
},
  "geometry": {"coordinates":[-79.00272,35.770827],"type":"Point"}
}