{
  "type": "Feature",
  "properties": {
    "addr:full":"810 S Reilly Rd Fayetteville NC 28314",
    "addr:housenumber":"810",
    "addr:postcode":"28314",
    "addr:street":"S Reilly Rd",
    "iso:country":"US",
    "sg:address":"810 S Reilly Rd",
    "sg:city":"Fayetteville",
    "sg:classifiers":[
        {
            "category":"Restaurant",
            "type":"Food & Drink"
        }
    ],
    "sg:menulink":"http://www.allmenus.com/nc/seventy-first/211765-mcdonalds/menu/",
    "sg:phone":"+1 910 864 9631",
    "sg:postcode":"28314",
    "sg:province":"NC",
    "sg:tags":[
        "burger",
        "american"
    ],
    "wof:name":"McDonald's",
    "wof:placetype":"venue"
},
  "geometry": {"coordinates":[-79.016124,35.061281],"type":"Point"}
}