{
  "type": "Feature",
  "properties": {
    "addr:full":"304 Sawmill Rd Raleigh NC 27615",
    "addr:housenumber":"304",
    "addr:postcode":"27615",
    "addr:street":"Sawmill Rd",
    "iso:country":"US",
    "sg:address":"304 Sawmill Rd",
    "sg:city":"Raleigh",
    "sg:classifiers":[
        {
            "category":"Freight",
            "type":"Transportation"
        }
    ],
    "sg:phone":"+1 919 847 8946",
    "sg:postcode":"27615",
    "sg:province":"NC",
    "sg:tags":[
        "busing",
        "trucking"
    ],
    "wof:name":"D Smith Trucking Inc",
    "wof:placetype":"venue"
},
  "geometry": {"coordinates":[-78.64992100000001,35.882028],"type":"Point"}
}