{
  "type": "Feature",
  "properties": {
    "iso:country":"US",
    "sg:address":"5 Commerce St",
    "sg:city":"Thomasville",
    "sg:classifiers":[
        {
            "category":"Retail",
            "subcategory":"Animal Services",
            "type":"Services"
        }
    ],
    "sg:phone":"+1 336 472 5593",
    "sg:postcode":"27360",
    "sg:province":"NC",
    "sg:tags":[
        "pet",
        "grooming",
        "washing"
    ],
    "wof:name":"Pretty Paws Pet Grooming",
    "wof:placetype":"venue"
},
  "geometry": {"coordinates":[-80.08035099999999,35.883803],"type":"Point"}
}