{
  "type": "Feature",
  "properties": {
    "addr:full":"4602 Walnut Grove Church Rd Hillsborough NC 27278",
    "addr:housenumber":"4602",
    "addr:postcode":"27278",
    "addr:street":"Walnut Grove Church Rd",
    "iso:country":"US",
    "sg:address":"4602 Walnut Grove Church Rd",
    "sg:city":"Hillsborough",
    "sg:classifiers":[
        {
            "category":"Building & Trades",
            "subcategory":"Plumbing",
            "type":"Services"
        }
    ],
    "sg:phone":"+1 919 644 3232",
    "sg:postcode":"27278",
    "sg:province":"NC",
    "sg:tags":[
        "heating",
        "contractor",
        "air",
        "system",
        "conditioning"
    ],
    "wof:name":"Raleigh Durham Heating & Air",
    "wof:placetype":"venue"
},
  "geometry": {"coordinates":[-79.11025100000001,36.15811],"type":"Point"}
}