{
  "type": "Feature",
  "properties": {
    "iso:country":"US",
    "sg:address":"1266 N Scales St",
    "sg:city":"Reidsville",
    "sg:classifiers":[
        {
            "category":"Banks & Credit Unions",
            "subcategory":"Bank",
            "type":"Services"
        }
    ],
    "sg:phone":"+1 336 349 9754",
    "sg:postcode":"27320",
    "sg:province":"NC",
    "sg:tags":[
        "loan",
        "real estate"
    ],
    "wof:name":"First Mortgage-North Carolina",
    "wof:placetype":"venue"
},
  "geometry": {"coordinates":[-79.668556,36.381039],"type":"Point"}
}