{
  "type": "Feature",
  "properties": {
    "iso:country":"US",
    "sg:address":"3001 Holloway St",
    "sg:city":"Durham",
    "sg:classifiers":[
        {
            "category":"Restaurant",
            "type":"Food & Drink"
        }
    ],
    "sg:menulink":"http://www.allmenus.com/nc/oak-grove/85357-dominos-pizza/menu/",
    "sg:phone":"+1 919 598 1111",
    "sg:postcode":"27703",
    "sg:province":"NC",
    "sg:tags":[
        "american",
        "wing",
        "pizza"
    ],
    "wof:name":"Domino's Pizza",
    "wof:placetype":"venue"
},
  "geometry": {"coordinates":[-78.843509,35.987054],"type":"Point"}
}