{
  "type": "Feature",
  "properties": {
    "addr:full":"3401 Green Level Rd W Cary NC 27519",
    "addr:housenumber":"3401",
    "addr:postcode":"27519",
    "addr:street":"Green Level Rd W",
    "iso:country":"US",
    "sg:address":"3401 Green Level Rd W",
    "sg:city":"Cary",
    "sg:classifiers":[
        {
            "category":"Building & Trades",
            "subcategory":"Plumbing",
            "type":"Services"
        }
    ],
    "sg:phone":"+1 919 367 0020",
    "sg:postcode":"27519",
    "sg:province":"NC",
    "sg:tags":[
        "plumbing",
        "contractor"
    ],
    "wof:name":"B J Plumbing Inc",
    "wof:placetype":"venue"
},
  "geometry": {"coordinates":[-78.897462,35.781146],"type":"Point"}
}