{
  "type": "Feature",
  "properties": {
    "addr:full":"525 Gillespie St Fayetteville NC 28301",
    "addr:housenumber":"525",
    "addr:postcode":"28301",
    "addr:street":"Gillespie St",
    "iso:country":"US",
    "sg:address":"525 Gillespie St",
    "sg:city":"Fayetteville",
    "sg:classifiers":[
        {
            "category":"Manufacturing",
            "subcategory":"Printing",
            "type":"Manufacturing & Wholesale Goods"
        }
    ],
    "sg:phone":"+1 910 221 0968",
    "sg:postcode":"28301",
    "sg:province":"NC",
    "sg:tags":[
        "screen"
    ],
    "wof:name":"B & B Screen Printing",
    "wof:placetype":"venue"
},
  "geometry": {"coordinates":[-78.881438,35.04336],"type":"Point"}
}