{
  "type": "Feature",
  "properties": {
    "iso:country":"US",
    "sg:address":"107 Gaston Pointe Dr",
    "sg:city":"Littleton",
    "sg:classifiers":[
        {
            "category":"Real Estate",
            "subcategory":"Real Estate Agent",
            "type":"Services"
        }
    ],
    "sg:phone":"+1 252 586 3700",
    "sg:postcode":"27850",
    "sg:province":"NC",
    "wof:name":"D&M Land Co LLC",
    "wof:placetype":"venue"
},
  "geometry": {"coordinates":[-77.95190100000001,36.48915],"type":"Point"}
}