{
  "type": "Feature",
  "properties": {
    "iso:country":"US",
    "sg:address":"341 N Caswell Rd",
    "sg:city":"Charlotte",
    "sg:classifiers":[
        {
            "category":"Professional",
            "subcategory":"Management & Consulting",
            "type":"Services"
        },
        {
            "category":"Professional",
            "subcategory":"Lawyer & Legal Services",
            "type":"Services"
        },
        {
            "category":"Banks & Credit Unions",
            "subcategory":"Financial Services",
            "type":"Services"
        },
        {
            "category":"Social Services",
            "subcategory":"Adult Care",
            "type":"Services"
        },
        {
            "category":"Health Services",
            "subcategory":"Nursing And Care Facility",
            "type":"Services"
        }
    ],
    "sg:phone":"+1 704 372 5520",
    "sg:postcode":"28204",
    "sg:province":"NC",
    "sg:tags":[
        "living",
        "financing",
        "retirement",
        "estate",
        "consultant",
        "assisted",
        "attorney",
        "rest",
        "elder",
        "planning",
        "home",
        "trust",
        "wills"
    ],
    "wof:name":"Retirement Estate Planning Services",
    "wof:placetype":"venue"
},
  "geometry": {"coordinates":[-80.81988,35.21188],"type":"Point"}
}