{
  "type": "Feature",
  "properties": {
    "addr:full":"3104 Philippine Dr Fayetteville NC 28306",
    "addr:housenumber":"3104",
    "addr:postcode":"28306",
    "addr:street":"Philippine Dr",
    "iso:country":"US",
    "sg:address":"3104 Philippine Dr",
    "sg:city":"Fayetteville",
    "sg:classifiers":[
        {
            "category":"Building & Trades",
            "subcategory":"Construction",
            "type":"Services"
        }
    ],
    "sg:phone":"+1 910 425 2169",
    "sg:postcode":"28306",
    "sg:province":"NC",
    "sg:tags":[
        "contractor"
    ],
    "wof:name":"Jj Roofing Inc",
    "wof:placetype":"venue"
},
  "geometry": {"coordinates":[-78.954548,34.985253],"type":"Point"}
}