{
  "type": "Feature",
  "properties": {
    "iso:country":"US",
    "sg:address":"161 State Hwy 42",
    "sg:city":"Clayton",
    "sg:classifiers":[
        {
            "category":"Personal",
            "subcategory":"Beauty Salon",
            "type":"Services"
        }
    ],
    "sg:phone":"+1 919 550 1633",
    "sg:postcode":"27967",
    "sg:province":"NC",
    "sg:tags":[
        "manicuring"
    ],
    "wof:name":"Day Dreams Nail Salon",
    "wof:placetype":"venue"
},
  "geometry": {"coordinates":[-76.93674300000001,36.227253],"type":"Point"}
}