{
  "type": "Feature",
  "properties": {
    "addr:full":"2321 Burnett Blvd Wilmington NC 28401",
    "addr:housenumber":"2321",
    "addr:postcode":"28401",
    "addr:street":"Burnett Blvd",
    "iso:country":"US",
    "sg:address":"2321 Burnett Blvd",
    "sg:city":"Wilmington",
    "sg:classifiers":[
        {
            "category":"Professional",
            "subcategory":"Testing Lab",
            "type":"Services"
        }
    ],
    "sg:phone":"+1 910 763 8444",
    "sg:postcode":"28401",
    "sg:province":"NC",
    "sg:tags":[
        "laboratory"
    ],
    "wof:name":"Saybolt Inc",
    "wof:placetype":"venue"
},
  "geometry": {"coordinates":[-77.94757799999999,34.19314],"type":"Point"}
}