{
  "type": "Feature",
  "properties": {
    "addr:full":"921 Eastchester Dr High Point NC 27262",
    "addr:housenumber":"921",
    "addr:postcode":"27262",
    "addr:street":"Eastchester Dr",
    "iso:country":"US",
    "sg:address":"921 Eastchester Dr",
    "sg:city":"High Point",
    "sg:classifiers":[
        {
            "category":"Personal",
            "type":"Services"
        }
    ],
    "sg:phone":"+1 336 883 9747",
    "sg:postcode":"27262",
    "sg:province":"NC",
    "sg:tags":[
        "ear",
        "piercing"
    ],
    "wof:name":"Piercing Pagoda",
    "wof:placetype":"venue"
},
  "geometry": {"coordinates":[-80.003158,35.988201],"type":"Point"}
}