{
  "type": "Feature",
  "properties": {
    "addr:full":"4824 Parkway Plaza Blvd Charlotte NC 28217",
    "addr:housenumber":"4824",
    "addr:postcode":"28217",
    "addr:street":"Parkway Plaza Blvd",
    "iso:country":"US",
    "sg:address":"4824 Parkway Plaza Blvd",
    "sg:city":"Charlotte",
    "sg:classifiers":[
        {
            "category":"Banks & Credit Unions",
            "subcategory":"Investment Brokerage",
            "type":"Services"
        }
    ],
    "sg:phone":"+1 704 357 0005",
    "sg:postcode":"28217",
    "sg:province":"NC",
    "sg:tags":[
        "consultant",
        "planning",
        "financial"
    ],
    "wof:name":"BMH Investment Group Inc",
    "wof:placetype":"venue"
},
  "geometry": {"coordinates":[-80.902879,35.183394],"type":"Point"}
}