{
  "type": "Feature",
  "properties": {
    "addr:full":"8282 Scarlet Oak Ct Harrisburg NC 28075",
    "addr:housenumber":"8282",
    "addr:postcode":"28075",
    "addr:street":"Scarlet Oak Ct",
    "iso:country":"US",
    "sg:address":"8282 Scarlet Oak Ct",
    "sg:city":"Harrisburg",
    "sg:classifiers":[
        {
            "category":"Professional",
            "type":"Services"
        }
    ],
    "sg:phone":"+1 704 455 9229",
    "sg:postcode":"28075",
    "sg:province":"NC",
    "wof:name":"Richard Farr",
    "wof:placetype":"venue"
},
  "geometry": {"coordinates":[-80.623014,35.302532],"type":"Point"}
}