{
  "type": "Feature",
  "properties": {
    "addr:full":"3821 Rockford Rd Boonville NC 27011",
    "addr:housenumber":"3821",
    "addr:postcode":"27011",
    "addr:street":"Rockford Rd",
    "iso:country":"US",
    "sg:address":"3821 Rockford Rd",
    "sg:city":"Boonville",
    "sg:classifiers":[
        {
            "category":"Home & Garden",
            "subcategory":"Garden Supply",
            "type":"Retail Goods"
        }
    ],
    "sg:phone":"+1 336 367 7604",
    "sg:postcode":"27011",
    "sg:province":"NC",
    "wof:name":"Crissman Tree Service",
    "wof:placetype":"venue"
},
  "geometry": {"coordinates":[-80.65589300000001,36.23223],"type":"Point"}
}