{
  "type": "Feature",
  "properties": {
    "iso:country":"US",
    "sg:address":"1307 Arendell St",
    "sg:city":"Morehead City",
    "sg:classifiers":[
        {
            "category":"Autos & Motor Vehicles",
            "subcategory":"Automobile Sales",
            "type":"Retail Goods"
        }
    ],
    "sg:phone":"+1 252 726 9988",
    "sg:postcode":"28557",
    "sg:province":"NC",
    "sg:tags":[
        "used"
    ],
    "wof:name":"Pay Les Auto Sales Inc",
    "wof:placetype":"venue"
},
  "geometry": {"coordinates":[-76.720843,34.721776],"type":"Point"}
}