{
  "type": "Feature",
  "properties": {
    "addr:full":"206 E Main St Elizabeth City NC 27909",
    "addr:housenumber":"206",
    "addr:postcode":"27909",
    "addr:street":"E Main St",
    "iso:country":"US",
    "sg:address":"206 E Main St",
    "sg:city":"Elizabeth City",
    "sg:classifiers":[
        {
            "category":"Government",
            "subcategory":"Court House",
            "type":"Public Place"
        }
    ],
    "sg:phone":"+1 252 335 0569",
    "sg:postcode":"27909",
    "sg:province":"NC",
    "sg:tags":[
        "county",
        "counsel"
    ],
    "wof:name":"Pasquotank County Attorney",
    "wof:placetype":"venue"
},
  "geometry": {"coordinates":[-76.222882,36.300233],"type":"Point"}
}