{
  "type": "Feature",
  "properties": {
    "iso:country":"US",
    "sg:address":"794 Sand Hill Rd",
    "sg:city":"Asheville",
    "sg:classifiers":[
        {
            "category":"Personal",
            "subcategory":"Beauty Salon",
            "type":"Services"
        }
    ],
    "sg:phone":"+1 828 665 1025",
    "sg:postcode":"28806",
    "sg:province":"NC",
    "sg:tags":[
        "hair"
    ],
    "wof:name":"Dot's Beauty Salon",
    "wof:placetype":"venue"
},
  "geometry": {"coordinates":[-82.62130000000001,35.554798],"type":"Point"}
}