{
  "type": "Feature",
  "properties": {
    "addr:full":"5490 Ocean Hwy E Winnabow NC 28479",
    "addr:housenumber":"5490",
    "addr:postcode":"28479",
    "addr:street":"Ocean Hwy E Winnabow",
    "iso:country":"US",
    "sg:address":"5490 Ocean Hwy E",
    "sg:city":"Winnabow",
    "sg:classifiers":[
        {
            "category":"Professional",
            "subcategory":"Accounting & Tax Preparation",
            "type":"Services"
        }
    ],
    "sg:phone":"+1 910 253 5525",
    "sg:postcode":"28479",
    "sg:province":"NC",
    "sg:tags":[
        "accountant"
    ],
    "wof:name":"Walton Accounting Svc",
    "wof:placetype":"venue"
},
  "geometry": {"coordinates":[-78.114054,34.111542],"type":"Point"}
}