{
  "type": "Feature",
  "properties": {
    "iso:country":"US",
    "sg:address":"301 S Queen St",
    "sg:city":"Kinston",
    "sg:classifiers":[
        {
            "category":"Autos & Motor Vehicles",
            "subcategory":"Auto Supplies",
            "type":"Retail Goods"
        }
    ],
    "sg:phone":"+1 252 523 4666",
    "sg:postcode":"28501",
    "sg:province":"NC",
    "wof:name":"Real Deal Tires",
    "wof:placetype":"venue"
},
  "geometry": {"coordinates":[-77.58122899999999,35.257448],"type":"Point"}
}