{
  "type": "Feature",
  "properties": {
    "addr:full":"731 N Caldwell Ave Newton NC 28658",
    "addr:housenumber":"731",
    "addr:postcode":"28658",
    "addr:street":"N Caldwell Ave",
    "iso:country":"US",
    "sg:address":"731 N Caldwell Ave",
    "sg:city":"Newton",
    "sg:classifiers":[
        {
            "category":"Organizations",
            "subcategory":"Religious Organization",
            "type":"Services"
        }
    ],
    "sg:phone":"+1   ",
    "sg:postcode":"28658",
    "sg:province":"NC",
    "sg:tags":[
        "pentecostal",
        "church"
    ],
    "wof:name":"Pentecostal Church Living God",
    "wof:placetype":"venue"
},
  "geometry": {"coordinates":[-81.218164,35.668108],"type":"Point"}
}