{
  "type": "Feature",
  "properties": {
    "addr:full":"2022 E 7th St Charlotte NC 28204",
    "addr:housenumber":"2022",
    "addr:postcode":"28204",
    "addr:street":"E 7Th St",
    "iso:country":"US",
    "sg:address":"2022 E 7th St",
    "sg:city":"Charlotte",
    "sg:classifiers":[
        {
            "category":"Food & Beverages",
            "subcategory":"Groceries & Convenience Stores",
            "type":"Retail Goods"
        }
    ],
    "sg:phone":"+1 704 373 2983",
    "sg:postcode":"28204",
    "sg:province":"NC",
    "wof:name":"Friendly Mart Inc",
    "wof:placetype":"venue"
},
  "geometry": {"coordinates":[-80.81698799999999,35.21154],"type":"Point"}
}