{
  "type": "Feature",
  "properties": {
    "iso:country":"US",
    "sg:address":"1914 S Miami Blvd",
    "sg:city":"Durham",
    "sg:classifiers":[
        {
            "category":"Organizations",
            "subcategory":"Religious Organization",
            "type":"Services"
        }
    ],
    "sg:phone":"+1 919 596 2158",
    "sg:postcode":"27703",
    "sg:province":"NC",
    "sg:tags":[
        "church"
    ],
    "wof:name":"Bethesda Baptist Church Inc",
    "wof:placetype":"venue"
},
  "geometry": {"coordinates":[-78.838576,35.942654],"type":"Point"}
}