{
  "type": "Feature",
  "properties": {
    "iso:country":"US",
    "sg:address":"733 Brigham Rd",
    "sg:city":"Greensboro",
    "sg:classifiers":[
        {
            "category":"Home & Garden",
            "subcategory":"Building Materials",
            "type":"Retail Goods"
        }
    ],
    "sg:phone":"+1 336 668 2221",
    "sg:postcode":"27409",
    "sg:province":"NC",
    "sg:tags":[
        "door"
    ],
    "wof:name":"Full Circle Garage Door Co",
    "wof:placetype":"venue"
},
  "geometry": {"coordinates":[-79.967716,36.114433],"type":"Point"}
}