{
  "type": "Feature",
  "properties": {
    "iso:country":"US",
    "sg:address":"906 Devonshire Trl",
    "sg:city":"Aberdeen",
    "sg:classifiers":[
        {
            "category":"Personal",
            "type":"Services"
        }
    ],
    "sg:phone":"+1   ",
    "sg:postcode":"28315",
    "sg:province":"NC",
    "wof:name":"Casper Rolf Home Improvement",
    "wof:placetype":"venue"
},
  "geometry": {"coordinates":[-79.410296,35.134259],"type":"Point"}
}