{
  "type": "Feature",
  "properties": {
    "iso:country":"US",
    "sg:address":"184 Gilbert Barnes Rd",
    "sg:city":"Boone",
    "sg:classifiers":[
        {
            "category":"Professional",
            "subcategory":"Computer Services",
            "type":"Services"
        }
    ],
    "sg:phone":"+1   ",
    "sg:postcode":"28607",
    "sg:province":"NC",
    "sg:tags":[
        "related"
    ],
    "wof:name":"Dougnet",
    "wof:placetype":"venue"
},
  "geometry": {"coordinates":[-81.714681,36.227818],"type":"Point"}
}