{
  "type": "Feature",
  "properties": {
    "iso:country":"US",
    "sg:address":"2114 Summit Ridge Loop",
    "sg:city":"Morrisville",
    "sg:classifiers":[
        {
            "category":"Real Estate",
            "subcategory":"Real Estate Agent",
            "type":"Services"
        }
    ],
    "sg:phone":"+1 919 460 0101",
    "sg:postcode":"27560",
    "sg:province":"NC",
    "wof:name":"Camden Summit Partnership",
    "wof:placetype":"venue"
},
  "geometry": {"coordinates":[-78.82029199999999,35.812593],"type":"Point"}
}