{
  "type": "Feature",
  "properties": {
    "iso:country":"US",
    "sg:address":"3684 Henderson Dr",
    "sg:city":"Jacksonville",
    "sg:classifiers":[
        {
            "category":"Professional",
            "subcategory":"Lawyer & Legal Services",
            "type":"Services"
        }
    ],
    "sg:phone":"+1 910 938 1122",
    "sg:postcode":"28546",
    "sg:province":"NC",
    "sg:tags":[
        "attorney"
    ],
    "wof:name":"Jones Garland & Peterman",
    "wof:placetype":"venue"
},
  "geometry": {"coordinates":[-77.41568700000001,34.793125],"type":"Point"}
}