{
  "type": "Feature",
  "properties": {
    "addr:full":"1027 Highway # 70 Raleigh NC 27695",
    "addr:housenumber":"1027;70",
    "addr:postcode":"27695",
    "addr:street":"Highway #",
    "iso:country":"US",
    "sg:address":"1027 Highway # 70",
    "sg:city":"Raleigh",
    "sg:classifiers":[
        {
            "category":"Banks & Credit Unions",
            "subcategory":"Atm",
            "type":"Services"
        }
    ],
    "sg:phone":"+1 919 779 7775",
    "sg:postcode":"27695",
    "sg:province":"NC",
    "sg:tags":[
        "bankruptcy"
    ],
    "wof:name":"Hopkins Levette H",
    "wof:placetype":"venue"
},
  "geometry": {"coordinates":[-78.72260300000001,35.813801],"type":"Point"}
}