{
  "type": "Feature",
  "properties": {
    "addr:full":"1707 Medical Park Dr Wilson NC 27893",
    "addr:housenumber":"1707",
    "addr:postcode":"27893",
    "addr:street":"Medical Park Dr",
    "iso:country":"US",
    "sg:address":"1707 Medical Park Dr",
    "sg:city":"Wilson",
    "sg:classifiers":[
        {
            "category":"Shopping",
            "subcategory":"Optical Goods",
            "type":"Retail Goods"
        }
    ],
    "sg:phone":"+1 252 237 9141",
    "sg:postcode":"27893",
    "sg:province":"NC",
    "wof:name":"Wilson Optical Ctr Inc",
    "wof:placetype":"venue"
},
  "geometry": {"coordinates":[-77.94219699999999,35.723129],"type":"Point"}
}