{
  "type": "Feature",
  "properties": {
    "iso:country":"US",
    "sg:address":"2007 John Small Ave",
    "sg:city":"Washington",
    "sg:classifiers":[
        {
            "category":"Autos & Motor Vehicles",
            "subcategory":"Fuel & Gas Station",
            "type":"Retail Goods"
        }
    ],
    "sg:phone":"+1 252 946 5696",
    "sg:postcode":"27889",
    "sg:province":"NC",
    "sg:tags":[
        "oil"
    ],
    "wof:name":"Washington Gas House",
    "wof:placetype":"venue"
},
  "geometry": {"coordinates":[-77.008691,35.542291],"type":"Point"}
}