{
  "type": "Feature",
  "properties": {
    "iso:country":"US",
    "sg:address":"2048 Carmel Rd",
    "sg:city":"Charlotte",
    "sg:classifiers":[
        {
            "category":"Organizations",
            "subcategory":"Religious Organization",
            "type":"Services"
        }
    ],
    "sg:phone":"+1 704 366 5114",
    "sg:postcode":"28226",
    "sg:province":"NC",
    "sg:tags":[
        "church"
    ],
    "sg:website":"www.carmelpresbyterian.org",
    "wof:name":"Carmel Presbyterian Church",
    "wof:placetype":"venue"
},
  "geometry": {"coordinates":[-80.80206699999999,35.140352],"type":"Point"}
}