{
  "type": "Feature",
  "properties": {
    "addr:full":"8413 Thompson Mill Rd Wake Forest NC 27587",
    "addr:housenumber":"8413",
    "addr:postcode":"27587",
    "addr:street":"Thompson Mill Rd",
    "iso:country":"US",
    "sg:address":"8413 Thompson Mill Rd",
    "sg:city":"Wake Forest",
    "sg:classifiers":[
        {
            "category":"Government",
            "subcategory":"Office",
            "type":"Public Place"
        }
    ],
    "sg:phone":"+1 919 556 6416",
    "sg:postcode":"27587",
    "sg:province":"NC",
    "sg:tags":[
        "advertising",
        "specialty"
    ],
    "wof:name":"National Assn State Foresters",
    "wof:placetype":"venue"
},
  "geometry": {"coordinates":[-78.553021,36.007417],"type":"Point"}
}