{
  "type": "Feature",
  "properties": {
    "iso:country":"US",
    "sg:address":"4404 W Wendover Ave",
    "sg:city":"Greensboro",
    "sg:classifiers":[
        {
            "category":"Restaurant",
            "type":"Food & Drink"
        }
    ],
    "sg:menulink":"http://www.allmenus.com/nc/greensboro/182463-wendys/menu/",
    "sg:phone":"+1 336 632 1650",
    "sg:postcode":"27407",
    "sg:province":"NC",
    "sg:tags":[
        "burger",
        "american",
        "soup"
    ],
    "wof:name":"Wendy's",
    "wof:placetype":"venue"
},
  "geometry": {"coordinates":[-79.896828,36.056387],"type":"Point"}
}