{
  "type": "Feature",
  "properties": {
    "iso:country":"US",
    "sg:address":"24599 US Hwy 264 E",
    "sg:city":"Pantego",
    "sg:classifiers":[
        {
            "category":"Organizations",
            "subcategory":"Religious Organization",
            "type":"Services"
        }
    ],
    "sg:phone":"+1 252 943 2002",
    "sg:postcode":"27860",
    "sg:province":"NC",
    "sg:tags":[
        "church"
    ],
    "wof:name":"Convenant United Reformed Chur",
    "wof:placetype":"venue"
},
  "geometry": {"coordinates":[-76.674057,35.57919],"type":"Point"}
}