{
  "type": "Feature",
  "properties": {
    "iso:country":"US",
    "sg:address":"314 Main St",
    "sg:city":"Newton Grove",
    "sg:classifiers":[
        {
            "category":"Sports & Exercise",
            "subcategory":"Gym",
            "type":"Entertainment"
        }
    ],
    "sg:phone":"+1 910 594 1000",
    "sg:postcode":"28366",
    "sg:province":"NC",
    "sg:tags":[
        "club",
        "health",
        "studio",
        "gymnasium"
    ],
    "wof:name":"Curves",
    "wof:placetype":"venue"
},
  "geometry": {"coordinates":[-78.355572,35.248962],"type":"Point"}
}