{
  "type": "Feature",
  "properties": {
    "iso:country":"US",
    "sg:address":"4276 Deacon Ct SW",
    "sg:city":"Concord",
    "sg:classifiers":[
        {
            "category":"Professional",
            "subcategory":"Business Services",
            "type":"Services"
        }
    ],
    "sg:phone":"+1   ",
    "sg:postcode":"28025",
    "sg:province":"NC",
    "wof:name":"Carino Inc",
    "wof:placetype":"venue"
},
  "geometry": {"coordinates":[-80.58465099999999,35.349447],"type":"Point"}
}