{
  "type": "Feature",
  "properties": {
    "iso:country":"US",
    "sg:address":"1955 New Elam Church Rd",
    "sg:city":"New Hill",
    "sg:classifiers":[
        {
            "category":"Real Estate",
            "subcategory":"Real Estate Agent",
            "type":"Services"
        }
    ],
    "sg:phone":"+1 919 387 0961",
    "sg:postcode":"27562",
    "sg:province":"NC",
    "wof:name":"Realty World Anchor Prof",
    "wof:placetype":"venue"
},
  "geometry": {"coordinates":[-79.03248499999999,35.656826],"type":"Point"}
}