{
  "type": "Feature",
  "properties": {
    "iso:country":"US",
    "sg:address":"156 Jess Ln",
    "sg:city":"Stokesdale",
    "sg:classifiers":[
        {
            "category":"Organizations",
            "subcategory":"Religious Organization",
            "type":"Services"
        }
    ],
    "sg:phone":"+1   ",
    "sg:postcode":"27357",
    "sg:province":"NC",
    "wof:name":"Choice Ministries Inc",
    "wof:placetype":"venue"
},
  "geometry": {"coordinates":[-79.954943,36.290611],"type":"Point"}
}