{
  "type": "Feature",
  "properties": {
    "addr:full":"1900 N Sandhills Blvd Aberdeen NC 28315",
    "addr:housenumber":"1900",
    "addr:postcode":"28315",
    "addr:street":"N Sandhills Blvd",
    "iso:country":"US",
    "sg:address":"1900 N Sandhills Blvd",
    "sg:city":"Aberdeen",
    "sg:classifiers":[
        {
            "category":"Restaurant",
            "type":"Food & Drink"
        }
    ],
    "sg:phone":"+1 910 692 6686",
    "sg:postcode":"28315",
    "sg:province":"NC",
    "sg:tags":[
        "a",
        "fast"
    ],
    "wof:name":"Burger King",
    "wof:placetype":"venue"
},
  "geometry": {"coordinates":[-79.414316,35.155459],"type":"Point"}
}