{
  "type": "Feature",
  "properties": {
    "iso:country":"US",
    "sg:address":"249 Roanoke Ave",
    "sg:city":"Roanoke Rapids",
    "sg:classifiers":[
        {
            "category":"Professional",
            "subcategory":"Advertising",
            "type":"Services"
        }
    ],
    "sg:phone":"+1 252 410 0100",
    "sg:postcode":"27870",
    "sg:province":"NC",
    "sg:tags":[
        "distribution"
    ],
    "wof:name":"Pure Distributor",
    "wof:placetype":"venue"
},
  "geometry": {"coordinates":[-77.650818,36.468732],"type":"Point"}
}