{
  "type": "Feature",
  "properties": {
    "iso:country":"US",
    "sg:address":"3027 Hillsborough St",
    "sg:city":"Raleigh",
    "sg:classifiers":[
        {
            "category":"Shopping",
            "subcategory":"Books",
            "type":"Retail Goods"
        }
    ],
    "sg:phone":"+1 919 832 4600",
    "sg:postcode":"27607",
    "sg:province":"NC",
    "wof:name":"Capitol Comics",
    "wof:placetype":"venue"
},
  "geometry": {"coordinates":[-78.67787,35.789936],"type":"Point"}
}