{
  "type": "Feature",
  "properties": {
    "addr:full":"4000 Pond Valley Ct Mc Leansville NC 27301",
    "addr:housenumber":"4000",
    "addr:postcode":"27301",
    "addr:street":"Pond Valley Ct Mc Leansville",
    "iso:country":"US",
    "sg:address":"4000 Pond Valley Ct",
    "sg:city":"Mc Leansville",
    "sg:classifiers":[
        {
            "category":"Building & Trades",
            "subcategory":"Construction",
            "type":"Services"
        }
    ],
    "sg:phone":"+1 336 375 8550",
    "sg:postcode":"27301",
    "sg:province":"NC",
    "sg:tags":[
        "house"
    ],
    "wof:name":"A D Shelton Builders Inc",
    "wof:placetype":"venue"
},
  "geometry": {"coordinates":[-79.694237,36.136306],"type":"Point"}
}