{
  "type": "Feature",
  "properties": {
    "addr:full":"5099 Westgate Dr Fayetteville NC 28304",
    "addr:housenumber":"5099",
    "addr:postcode":"28304",
    "addr:street":"Westgate Dr",
    "iso:country":"US",
    "sg:address":"5099 Westgate Dr",
    "sg:city":"Fayetteville",
    "sg:classifiers":[
        {
            "category":"Real Estate",
            "subcategory":"Real Estate Operator",
            "type":"Services"
        }
    ],
    "sg:phone":"+1 910 424 6555",
    "sg:postcode":"28304",
    "sg:province":"NC",
    "sg:tags":[
        "mobile",
        "home",
        "community"
    ],
    "wof:name":"Westgate Mobile Home Village",
    "wof:placetype":"venue"
},
  "geometry": {"coordinates":[-78.968744,35.01129],"type":"Point"}
}