{
  "type": "Feature",
  "properties": {
    "addr:full":"127 Crawford Rd Ellerbe NC 28338",
    "addr:housenumber":"127",
    "addr:postcode":"28338",
    "addr:street":"Crawford Rd",
    "iso:country":"US",
    "sg:address":"127 Crawford Rd",
    "sg:city":"Ellerbe",
    "sg:classifiers":[
        {
            "category":"Government",
            "subcategory":"Office",
            "type":"Public Place"
        }
    ],
    "sg:phone":"+1 910 652 6599",
    "sg:postcode":"28338",
    "sg:province":"NC",
    "sg:tags":[
        "village"
    ],
    "wof:name":"Ellerbe Maintenance Shop",
    "wof:placetype":"venue"
},
  "geometry": {"coordinates":[-79.758077,35.075103],"type":"Point"}
}