{
  "type": "Feature",
  "properties": {
    "iso:country":"US",
    "sg:address":"7934 US Hwy 701 S",
    "sg:city":"Newton Grove",
    "sg:classifiers":[
        {
            "category":"Shopping",
            "subcategory":"Clothing, Apparel, & Fashions",
            "type":"Retail Goods"
        }
    ],
    "sg:phone":"+1 919 963 3750",
    "sg:postcode":"28366",
    "sg:province":"NC",
    "wof:name":"Pats Hats & Accessories",
    "wof:placetype":"venue"
},
  "geometry": {"coordinates":[-78.36228199999999,35.324582],"type":"Point"}
}