{
  "type": "Feature",
  "properties": {
    "iso:country":"US",
    "sg:address":"1425 Jake Alexander Blvd S",
    "sg:city":"Salisbury",
    "sg:classifiers":[
        {
            "category":"Personal",
            "subcategory":"Beauty Salon",
            "type":"Services"
        }
    ],
    "sg:phone":"+1 704 636 7495",
    "sg:postcode":"28146",
    "sg:province":"NC",
    "wof:name":"Styles At Payton Place",
    "wof:placetype":"venue"
},
  "geometry": {"coordinates":[-80.475201,35.641365],"type":"Point"}
}