{
  "type": "Feature",
  "properties": {
    "addr:full":"1802 Glenside Dr Greensboro NC 27405",
    "addr:housenumber":"1802",
    "addr:postcode":"27405",
    "addr:street":"Glenside Dr",
    "iso:country":"US",
    "sg:address":"1802 Glenside Dr",
    "sg:city":"Greensboro",
    "sg:classifiers":[
        {
            "category":"Restaurant",
            "type":"Food & Drink"
        }
    ],
    "sg:phone":"+1 336 375 8983",
    "sg:postcode":"27405",
    "sg:province":"NC",
    "sg:tags":[
        "caterer"
    ],
    "wof:name":"P & B Catering",
    "wof:placetype":"venue"
},
  "geometry": {"coordinates":[-79.76720899999999,36.133869],"type":"Point"}
}