{
  "type": "Feature",
  "properties": {
    "iso:country":"US",
    "sg:address":"8610 Camfield St # G",
    "sg:city":"Charlotte",
    "sg:classifiers":[
        {
            "category":"Building & Trades",
            "subcategory":"Landscaping Services",
            "type":"Services"
        },
        {
            "category":"Home & Garden",
            "subcategory":"Building Materials",
            "type":"Retail Goods"
        },
        {
            "category":"Building & Trades",
            "subcategory":"Construction",
            "type":"Services"
        }
    ],
    "sg:phone":"+1 704 408 3379",
    "sg:postcode":"28277",
    "sg:province":"NC",
    "sg:tags":[
        "designer",
        "consultant",
        "contractor",
        "concrete",
        "driveway",
        "gazebo",
        "landscape"
    ],
    "sg:website":"http://www.infinitylandscapedev.com",
    "wof:name":"a 1 infinity landscape patios and outdoor kitchen designers and installers",
    "wof:placetype":"venue"
},
  "geometry": {"coordinates":[-80.8146,35.052367],"type":"Point"}
}