{
  "type": "Feature",
  "properties": {
    "iso:country":"US",
    "sg:address":"1251 NW Maynard Rd",
    "sg:city":"Cary",
    "sg:classifiers":[
        {
            "category":"Home & Garden",
            "subcategory":"Carpets & Floor Coverings",
            "type":"Retail Goods"
        }
    ],
    "sg:phone":"+1 919 481 1968",
    "sg:postcode":"27513",
    "sg:province":"NC",
    "wof:name":"Floor Coverings International",
    "wof:placetype":"venue"
},
  "geometry": {"coordinates":[-78.810013,35.784813],"type":"Point"}
}