{
  "type": "Feature",
  "properties": {
    "iso:country":"US",
    "sg:address":"2497 W 5th St",
    "sg:city":"Washington",
    "sg:classifiers":[
        {
            "category":"Food & Beverages",
            "subcategory":"Groceries & Convenience Stores",
            "type":"Retail Goods"
        }
    ],
    "sg:phone":"+1 252 946 0886",
    "sg:postcode":"27889",
    "sg:province":"NC",
    "wof:name":"Travel Store",
    "wof:placetype":"venue"
},
  "geometry": {"coordinates":[-77.091835,35.581741],"type":"Point"}
}