{
  "type": "Feature",
  "properties": {
    "iso:country":"US",
    "sg:address":"1114 Colehurst Cres",
    "sg:city":"Apex",
    "sg:classifiers":[
        {
            "category":"Shopping",
            "subcategory":"Computers & Home Electronics",
            "type":"Retail Goods"
        }
    ],
    "sg:phone":"+1 919 303 3114",
    "sg:postcode":"27502",
    "sg:province":"NC",
    "sg:tags":[
        "software"
    ],
    "wof:name":"Infoplus",
    "wof:placetype":"venue"
},
  "geometry": {"coordinates":[-78.86596,35.744013],"type":"Point"}
}