{
  "type": "Feature",
  "properties": {
    "iso:country":"US",
    "sg:address":"242 State Hwy 42",
    "sg:city":"Ahoskie",
    "sg:classifiers":[
        {
            "category":"Government",
            "subcategory":"Police Station",
            "type":"Public Place"
        }
    ],
    "sg:phone":"+1 252 332 6800",
    "sg:postcode":"27910",
    "sg:province":"NC",
    "sg:tags":[
        "state"
    ],
    "wof:name":"Highway Patrol",
    "wof:placetype":"venue"
},
  "geometry": {"coordinates":[-76.988316,36.281],"type":"Point"}
}