{
  "type": "Feature",
  "properties": {
    "iso:country":"US",
    "sg:address":"1158 Superior St",
    "sg:city":"Conover",
    "sg:classifiers":[
        {
            "category":"Manufacturing",
            "subcategory":"Metals",
            "type":"Manufacturing & Wholesale Goods"
        }
    ],
    "sg:phone":"+1 828 256 7564",
    "sg:postcode":"28613",
    "sg:province":"NC",
    "sg:tags":[
        "tool",
        "mfg"
    ],
    "wof:name":"Jem Cutting Tools",
    "wof:placetype":"venue"
},
  "geometry": {"coordinates":[-81.22553000000001,35.785768],"type":"Point"}
}