{
  "type": "Feature",
  "properties": {
    "iso:country":"US",
    "sg:address":"10190 Foreman Ranch Rd",
    "sg:city":"Oakboro",
    "sg:classifiers":[
        {
            "category":"Recreation",
            "type":"Entertainment"
        }
    ],
    "sg:phone":"+1   ",
    "sg:postcode":"28129",
    "sg:province":"NC",
    "wof:name":"River Ridge Riding Academy",
    "wof:placetype":"venue"
},
  "geometry": {"coordinates":[-80.26414,35.21142],"type":"Point"}
}