{
  "type": "Feature",
  "properties": {
    "iso:country":"US",
    "sg:address":"1524 Oakdale Green Dr",
    "sg:city":"Charlotte",
    "sg:classifiers":[
        {
            "category":"Bus Charters",
            "type":"Transportation"
        }
    ],
    "sg:phone":"+1 704 507 9046",
    "sg:postcode":"28216",
    "sg:province":"NC",
    "sg:tags":[
        "buses-charter",
        "rental"
    ],
    "wof:name":"Student",
    "wof:placetype":"venue"
},
  "geometry": {"coordinates":[-80.90545,35.300466],"type":"Point"}
}