{
  "type": "Feature",
  "properties": {
    "addr:full":"2050 N Main St Marion NC 28752",
    "addr:housenumber":"2050",
    "addr:postcode":"28752",
    "addr:street":"N Main St",
    "iso:country":"US",
    "sg:address":"2050 N Main St",
    "sg:city":"Marion",
    "sg:classifiers":[
        {
            "category":"Insurance",
            "subcategory":"Insurance Agent",
            "type":"Services"
        }
    ],
    "sg:phone":"+1 828 652 6567",
    "sg:postcode":"28752",
    "sg:province":"NC",
    "wof:name":"Mc Daniel Insurance",
    "wof:placetype":"venue"
},
  "geometry": {"coordinates":[-82.03192,35.70594],"type":"Point"}
}