{
  "type": "Feature",
  "properties": {
    "iso:country":"US",
    "sg:address":"7124 Davis Rd",
    "sg:city":"Waxhaw",
    "sg:classifiers":[
        {
            "category":"Arts & Performance",
            "subcategory":"Theater",
            "type":"Entertainment"
        }
    ],
    "sg:phone":"+1   ",
    "sg:postcode":"28173",
    "sg:province":"NC",
    "sg:tags":[
        "group"
    ],
    "wof:name":"Susans Mobile Barnyard",
    "wof:placetype":"venue"
},
  "geometry": {"coordinates":[-80.741686,34.848994],"type":"Point"}
}