{
  "type": "Feature",
  "properties": {
    "addr:full":"11115 Rushmore Drive Charlotte NC 28277",
    "addr:housenumber":"11115",
    "addr:postcode":"28277",
    "addr:street":"Rushmore Drive",
    "iso:country":"US",
    "sg:address":"11115 Rushmore Drive",
    "sg:city":"Charlotte",
    "sg:classifiers":[
        {
            "category":"Professional",
            "subcategory":"Computer Services",
            "type":"Services"
        }
    ],
    "sg:phone":"+1 704 943 8175",
    "sg:postcode":"28277",
    "sg:province":"NC",
    "sg:tags":[
        "real-estate",
        "realestate",
        "homes-for-sale",
        "realtor",
        "realtors",
        "real-estate-agents",
        "real-estate-agent",
        "home-listings",
        "mls",
        "find-a-realtor",
        "new-homes",
        "home",
        "homes",
        "condo",
        "condos",
        "for-sale",
        "buy",
        "sell",
        "buying",
        "selling",
        "multiple-listing-service",
        "mortgage",
        "rates"
    ],
    "sg:website":"http://www.realestate.com",
    "wof:name":"RealEstate.com",
    "wof:placetype":"venue"
},
  "geometry": {"coordinates":[-80.85807,35.061515],"type":"Point"}
}