{
  "type": "Feature",
  "properties": {
    "addr:full":"741 Rutherford Rd Marion NC 28752",
    "addr:housenumber":"741",
    "addr:postcode":"28752",
    "addr:street":"Rutherford Rd",
    "iso:country":"US",
    "sg:address":"741 Rutherford Rd",
    "sg:city":"Marion",
    "sg:classifiers":[
        {
            "category":"Shopping",
            "subcategory":"Used Merchandise",
            "type":"Retail Goods"
        }
    ],
    "sg:phone":"+1 828 659 5521",
    "sg:postcode":"28752",
    "sg:province":"NC",
    "sg:tags":[
        "pawnbroker"
    ],
    "wof:name":"Silver Dollar Pawn",
    "wof:placetype":"venue"
},
  "geometry": {"coordinates":[-82.00065499999999,35.678089],"type":"Point"}
}