{
  "type": "Feature",
  "properties": {
    "addr:full":"725 E US Hwy 74 Bus Ellenboro NC 28040",
    "addr:housenumber":"725",
    "addr:postcode":"28040",
    "addr:street":"E Us Hwy 74 Bus",
    "iso:country":"US",
    "sg:address":"725 E US Hwy 74 Bus",
    "sg:city":"Ellenboro",
    "sg:classifiers":[
        {
            "category":"Shopping",
            "subcategory":"Jewelry",
            "type":"Retail Goods"
        }
    ],
    "sg:phone":"+1 828 453 7575",
    "sg:postcode":"28040",
    "sg:province":"NC",
    "wof:name":"All Things Unique Jwly & Gifts",
    "wof:placetype":"venue"
},
  "geometry": {"coordinates":[-81.73666900000001,35.311832],"type":"Point"}
}