{
  "type": "Feature",
  "properties": {
    "iso:country":"US",
    "sg:address":"4947 Quartz Ridge Rd",
    "sg:city":"Maiden",
    "sg:classifiers":[
        {
            "category":"Organizations",
            "subcategory":"Religious Organization",
            "type":"Services"
        }
    ],
    "sg:phone":"+1   ",
    "sg:postcode":"28650",
    "sg:province":"NC",
    "wof:name":"Cross Timbers Ministries",
    "wof:placetype":"venue"
},
  "geometry": {"coordinates":[-81.100914,35.554765],"type":"Point"}
}