{
  "type": "Feature",
  "properties": {
    "iso:country":"US",
    "sg:address":"4546 Fairport Rd",
    "sg:city":"Oxford",
    "sg:classifiers":[
        {
            "category":"Professional",
            "subcategory":"Business Services",
            "type":"Services"
        }
    ],
    "sg:phone":"+1 919 939 3279",
    "sg:postcode":"27565",
    "sg:province":"NC",
    "sg:tags":[
        "consultant",
        "coach"
    ],
    "wof:name":"A L D Consulting",
    "wof:placetype":"venue"
},
  "geometry": {"coordinates":[-78.542862,36.246658],"type":"Point"}
}