{
  "type": "Feature",
  "properties": {
    "iso:country":"US",
    "sg:address":"6313 Lake Wheeler Rd",
    "sg:city":"Raleigh",
    "sg:classifiers":[
        {
            "category":"Home & Garden",
            "subcategory":"Carpets & Floor Coverings",
            "type":"Retail Goods"
        }
    ],
    "sg:phone":"+1 919 773 2225",
    "sg:postcode":"27603",
    "sg:province":"NC",
    "wof:name":"Maggiemae Flooring & Design",
    "wof:placetype":"venue"
},
  "geometry": {"coordinates":[-78.69281700000001,35.696207],"type":"Point"}
}