{
  "type": "Feature",
  "properties": {
    "addr:full":"2504 Cork St Greensboro NC 27401",
    "addr:housenumber":"2504",
    "addr:postcode":"27401",
    "addr:street":"Cork St",
    "iso:country":"US",
    "sg:address":"2504 Cork St",
    "sg:city":"Greensboro",
    "sg:classifiers":[
        {
            "category":"Professional",
            "subcategory":"Employment Agencies",
            "type":"Services"
        }
    ],
    "sg:phone":"+1   ",
    "sg:postcode":"27401",
    "sg:province":"NC",
    "sg:tags":[
        "building",
        "help",
        "maintenance",
        "supply"
    ],
    "wof:name":"Give US This Day Cleaning Svc",
    "wof:placetype":"venue"
},
  "geometry": {"coordinates":[-79.75033500000001,36.058582],"type":"Point"}
}