{
  "type": "Feature",
  "properties": {
    "iso:country":"US",
    "sg:address":"506 N Ellis Ave",
    "sg:city":"Dunn",
    "sg:classifiers":[
        {
            "category":"Autos & Motor Vehicles",
            "subcategory":"Fuel & Gas Station",
            "type":"Retail Goods"
        }
    ],
    "sg:phone":"+1 910 892 7493",
    "sg:postcode":"28334",
    "sg:province":"NC",
    "sg:tags":[
        "oil"
    ],
    "wof:name":"Wayne Lee's Exxon Svc Station",
    "wof:placetype":"venue"
},
  "geometry": {"coordinates":[-78.611929,35.315246],"type":"Point"}
}