{
  "type": "Feature",
  "properties": {
    "addr:full":"5 Moss Cir Granite Falls NC 28630",
    "addr:housenumber":"5",
    "addr:postcode":"28630",
    "addr:street":"Moss Cir",
    "iso:country":"US",
    "sg:address":"5 Moss Cir",
    "sg:city":"Granite Falls",
    "sg:classifiers":[
        {
            "category":"Retail",
            "subcategory":"Repair Shop",
            "type":"Services"
        }
    ],
    "sg:phone":"+1   ",
    "sg:postcode":"28630",
    "sg:province":"NC",
    "wof:name":"Repair Shack",
    "wof:placetype":"venue"
},
  "geometry": {"coordinates":[-81.42772100000001,35.782073],"type":"Point"}
}