{
  "type": "Feature",
  "properties": {
    "addr:full":"2109 E Ash St Goldsboro NC 27530",
    "addr:housenumber":"2109",
    "addr:postcode":"27530",
    "addr:street":"E Ash St",
    "iso:country":"US",
    "sg:address":"2109 E Ash St",
    "sg:city":"Goldsboro",
    "sg:classifiers":[
        {
            "category":"Autos & Motor Vehicles",
            "subcategory":"Auto Supplies",
            "type":"Retail Goods"
        }
    ],
    "sg:phone":"+1 919 734 9227",
    "sg:postcode":"27530",
    "sg:province":"NC",
    "sg:tags":[
        "automobile",
        "parts"
    ],
    "sg:website":"www.autozone.com",
    "wof:name":"Autozone",
    "wof:placetype":"venue"
},
  "geometry": {"coordinates":[-77.962535,35.376291],"type":"Point"}
}