{
  "type": "Feature",
  "properties": {
    "iso:country":"US",
    "sg:address":"436 1st Ave SW",
    "sg:city":"Hickory",
    "sg:classifiers":[
        {
            "category":"Retail",
            "subcategory":"Auto Repair",
            "type":"Services"
        }
    ],
    "sg:phone":"+1   ",
    "sg:postcode":"28602",
    "sg:province":"NC",
    "sg:tags":[
        "general"
    ],
    "wof:name":"Reliable Auto",
    "wof:placetype":"venue"
},
  "geometry": {"coordinates":[-81.345641,35.730891],"type":"Point"}
}