{
  "type": "Feature",
  "properties": {
    "iso:country":"US",
    "sg:address":"3010 Faith Rd",
    "sg:city":"Salisbury",
    "sg:classifiers":[
        {
            "category":"Wholesale",
            "subcategory":"Machinery & Supplies",
            "type":"Manufacturing & Wholesale Goods"
        }
    ],
    "sg:phone":"+1 704 279 7009",
    "sg:postcode":"28146",
    "sg:province":"NC",
    "sg:tags":[
        "farm",
        "equipment"
    ],
    "wof:name":"Faith Farm & Equipment Sales",
    "wof:placetype":"venue"
},
  "geometry": {"coordinates":[-80.465067,35.605271],"type":"Point"}
}