{
  "type": "Feature",
  "properties": {
    "addr:full":"3614 Green Park Cir Charlotte NC 28217",
    "addr:housenumber":"3614",
    "addr:postcode":"28217",
    "addr:street":"Green Park Cir",
    "iso:country":"US",
    "sg:address":"3614 Green Park Cir",
    "sg:city":"Charlotte",
    "sg:classifiers":[
        {
            "category":"Restaurant",
            "type":"Food & Drink"
        }
    ],
    "sg:phone":"+1 704 423 8300",
    "sg:postcode":"28217",
    "sg:province":"NC",
    "sg:tags":[
        "caterer"
    ],
    "wof:name":"Chef Charles Catering",
    "wof:placetype":"venue"
},
  "geometry": {"coordinates":[-80.933207,35.171929],"type":"Point"}
}