{
  "type": "Feature",
  "properties": {
    "addr:full":"512 East Blvd Charlotte NC 28203",
    "addr:housenumber":"512",
    "addr:postcode":"28203",
    "addr:street":"East Blvd",
    "iso:country":"US",
    "sg:address":"512 East Blvd",
    "sg:city":"Charlotte",
    "sg:classifiers":[
        {
            "category":"Arts & Performance",
            "subcategory":"Theater",
            "type":"Entertainment"
        }
    ],
    "sg:phone":"+1 704 339 0100",
    "sg:postcode":"28203",
    "sg:province":"NC",
    "sg:tags":[
        "bureau"
    ],
    "wof:name":"East Coast Entertainment",
    "wof:placetype":"venue"
},
  "geometry": {"coordinates":[-80.853291,35.208363],"type":"Point"}
}