{
  "type": "Feature",
  "properties": {
    "iso:country":"US",
    "sg:address":"209 S Main St",
    "sg:city":"Laurinburg",
    "sg:classifiers":[
        {
            "category":"Shopping",
            "subcategory":"Gifts & Souvenirs",
            "type":"Retail Goods"
        }
    ],
    "sg:phone":"+1 910 276 1955",
    "sg:postcode":"28352",
    "sg:province":"NC",
    "sg:tags":[
        "florist"
    ],
    "wof:name":"Countrywood Crafts",
    "wof:placetype":"venue"
},
  "geometry": {"coordinates":[-79.461868,34.776017],"type":"Point"}
}