{
  "type": "Feature",
  "properties": {
    "addr:full":"206 N Fisher St Burlington NC 27215",
    "addr:housenumber":"206",
    "addr:postcode":"27215",
    "addr:street":"N Fisher St",
    "iso:country":"US",
    "sg:address":"206 N Fisher St",
    "sg:city":"Burlington",
    "sg:classifiers":[
        {
            "category":"Professional",
            "subcategory":"Business Services",
            "type":"Services"
        }
    ],
    "sg:phone":"+1   ",
    "sg:postcode":"27215",
    "sg:province":"NC",
    "wof:name":"Allied Churches",
    "wof:placetype":"venue"
},
  "geometry": {"coordinates":[-79.43591499999999,36.099605],"type":"Point"}
}