{
  "type": "Feature",
  "properties": {
    "iso:country":"US",
    "sg:address":"2100 Dickinson Ave",
    "sg:city":"Greenville",
    "sg:classifiers":[
        {
            "category":"Mining & Drilling",
            "type":"Manufacturing & Wholesale Goods"
        }
    ],
    "sg:phone":"+1 252 756 4470",
    "sg:postcode":"27834",
    "sg:province":"NC",
    "sg:tags":[
        "oil",
        "gas",
        "producer"
    ],
    "wof:name":"Carawan Oil Co Inc",
    "wof:placetype":"venue"
},
  "geometry": {"coordinates":[-77.392413,35.600616],"type":"Point"}
}