{
  "type": "Feature",
  "properties": {
    "addr:full":"222 E Main St Clayton NC 27520",
    "addr:housenumber":"222",
    "addr:postcode":"27520",
    "addr:street":"E Main St",
    "iso:country":"US",
    "sg:address":"222 E Main St",
    "sg:city":"Clayton",
    "sg:classifiers":[
        {
            "category":"Real Estate",
            "subcategory":"Real Estate Agent",
            "type":"Services"
        }
    ],
    "sg:phone":"+1 919 553 7725",
    "sg:postcode":"27520",
    "sg:province":"NC",
    "wof:name":"Spencer Realty Co & Insurance",
    "wof:placetype":"venue"
},
  "geometry": {"coordinates":[-78.458505,35.652166],"type":"Point"}
}