{
  "type": "Feature",
  "properties": {
    "addr:full":"6 Miller Rd Fairview NC 28730",
    "addr:housenumber":"6",
    "addr:postcode":"28730",
    "addr:street":"Miller Rd",
    "iso:country":"US",
    "sg:address":"6 Miller Rd",
    "sg:city":"Fairview",
    "sg:classifiers":[
        {
            "category":"Professional",
            "subcategory":"Business Services",
            "type":"Services"
        }
    ],
    "sg:phone":"+1   ",
    "sg:postcode":"28730",
    "sg:province":"NC",
    "sg:tags":[
        "interpreting"
    ],
    "wof:name":"Olga Earwood",
    "wof:placetype":"venue"
},
  "geometry": {"coordinates":[-82.405976,35.523588],"type":"Point"}
}