{
  "type": "Feature",
  "properties": {
    "addr:full":"7118 Martin Lake Rd Summerfield NC 27358",
    "addr:housenumber":"7118",
    "addr:postcode":"27358",
    "addr:street":"Martin Lake Rd",
    "iso:country":"US",
    "sg:address":"7118 Martin Lake Rd",
    "sg:city":"Summerfield",
    "sg:classifiers":[
        {
            "category":"Building & Trades",
            "subcategory":"Electrical",
            "type":"Services"
        }
    ],
    "sg:phone":"+1 336 643 5981",
    "sg:postcode":"27358",
    "sg:province":"NC",
    "sg:tags":[
        "electric",
        "contractor"
    ],
    "wof:name":"Summerfield Electric Svc",
    "wof:placetype":"venue"
},
  "geometry": {"coordinates":[-79.889359,36.194343],"type":"Point"}
}