{
  "type": "Feature",
  "properties": {
    "addr:full":"5081 State Hwy 150 Lexington NC 27295",
    "addr:housenumber":"5081",
    "addr:postcode":"27295",
    "addr:street":"State Hwy 150",
    "iso:country":"US",
    "sg:address":"5081 State Hwy 150",
    "sg:city":"Lexington",
    "sg:classifiers":[
        {
            "category":"Building & Trades",
            "subcategory":"Construction",
            "type":"Services"
        }
    ],
    "sg:phone":"+1 336 853 6698",
    "sg:postcode":"27295",
    "sg:province":"NC",
    "sg:tags":[
        "hanging",
        "contractor"
    ],
    "wof:name":"Myers Painting",
    "wof:placetype":"venue"
},
  "geometry": {"coordinates":[-80.384942,35.802384],"type":"Point"}
}