{
  "type": "Feature",
  "properties": {
    "iso:country":"US",
    "sg:address":"200 Persimmon Rd SW",
    "sg:city":"Calabash",
    "sg:classifiers":[
        {
            "category":"Government",
            "subcategory":"Office",
            "type":"Public Place"
        }
    ],
    "sg:phone":"+1 910 575 4877",
    "sg:postcode":"28467",
    "sg:province":"NC",
    "sg:tags":[
        "village"
    ],
    "wof:name":"Carolina Shores Town Office",
    "wof:placetype":"venue"
},
  "geometry": {"coordinates":[-78.577358,33.91072],"type":"Point"}
}