{
  "type": "Feature",
  "properties": {
    "iso:country":"US",
    "sg:address":"10814 Sherrill Ave",
    "sg:city":"Cornelius",
    "sg:classifiers":[
        {
            "category":"Manufacturing",
            "subcategory":"Tools & Machinery",
            "type":"Manufacturing & Wholesale Goods"
        }
    ],
    "sg:phone":"+1 704 641 7301",
    "sg:postcode":"28031",
    "sg:province":"NC",
    "sg:tags":[
        "industry",
        "mfg"
    ],
    "wof:name":"Motoscan",
    "wof:placetype":"venue"
},
  "geometry": {"coordinates":[-80.85655,35.473104],"type":"Point"}
}