{
  "type": "Feature",
  "properties": {
    "addr:full":"4401 Susan Dr Raleigh NC 27603",
    "addr:housenumber":"4401",
    "addr:postcode":"27603",
    "addr:street":"Susan Dr",
    "iso:country":"US",
    "sg:address":"4401 Susan Dr",
    "sg:city":"Raleigh",
    "sg:classifiers":[
        {
            "category":"Building & Trades",
            "subcategory":"Construction",
            "type":"Services"
        }
    ],
    "sg:phone":"+1 919 661 2646",
    "sg:postcode":"27603",
    "sg:province":"NC",
    "sg:tags":[
        "contractor"
    ],
    "wof:name":"Young John Tile & Stone",
    "wof:placetype":"venue"
},
  "geometry": {"coordinates":[-78.64078000000001,35.71672],"type":"Point"}
}