{
  "type": "Feature",
  "properties": {
    "iso:country":"US",
    "sg:address":"1131 Amble Dr",
    "sg:city":"Charlotte",
    "sg:classifiers":[
        {
            "category":"Building & Trades",
            "subcategory":"Construction",
            "type":"Services"
        }
    ],
    "sg:phone":"+1 704 598 7508",
    "sg:postcode":"28206",
    "sg:province":"NC",
    "sg:tags":[
        "communication",
        "line",
        "contractor"
    ],
    "wof:name":"Ansco & Associates LLC",
    "wof:placetype":"venue"
},
  "geometry": {"coordinates":[-80.808515,35.270542],"type":"Point"}
}