{
  "type": "Feature",
  "properties": {
    "addr:full":"131 Matthews Station St Matthews NC 28105",
    "addr:housenumber":"131",
    "addr:postcode":"28105",
    "addr:street":"Matthews Station",
    "iso:country":"US",
    "sg:address":"131 Matthews Station St",
    "sg:city":"Matthews",
    "sg:classifiers":[
        {
            "category":"Restaurant",
            "type":"Food & Drink"
        }
    ],
    "sg:menulink":"http://www.allmenus.com/nc/morning-star/43351-thai-taste/menu/",
    "sg:phone":"+1 704 841 4455",
    "sg:postcode":"28105",
    "sg:province":"NC",
    "sg:tags":[
        "thai",
        "asian"
    ],
    "wof:name":"Thai Taste",
    "wof:placetype":"venue"
},
  "geometry": {"coordinates":[-80.720343,35.117262],"type":"Point"}
}