{
  "type": "Feature",
  "properties": {
    "iso:country":"US",
    "sg:address":"2893 Richlands Hwy",
    "sg:city":"Jacksonville",
    "sg:classifiers":[
        {
            "category":"Home & Garden",
            "subcategory":"Mobile Homes",
            "type":"Retail Goods"
        }
    ],
    "sg:phone":"+1 910 346 2512",
    "sg:postcode":"28540",
    "sg:province":"NC",
    "wof:name":"Leader Home Sales",
    "wof:placetype":"venue"
},
  "geometry": {"coordinates":[-77.46685100000001,34.755364],"type":"Point"}
}