{
  "type": "Feature",
  "properties": {
    "iso:country":"US",
    "sg:address":"2251 Bella Bridge Rd",
    "sg:city":"Broadway",
    "sg:phone":"+1 919 499 6955",
    "sg:postcode":"27505",
    "sg:province":"NC",
    "sg:tags":[
        "farm",
        "tobacco"
    ],
    "wof:name":"Tmg Farms",
    "wof:placetype":"venue"
},
  "geometry": {"coordinates":[-79.040131,35.348388],"type":"Point"}
}