{
  "type": "Feature",
  "properties": {
    "addr:full":"2606 Phoenix Dr Greensboro NC 27406",
    "addr:housenumber":"2606",
    "addr:postcode":"27406",
    "addr:street":"Phoenix Dr",
    "iso:country":"US",
    "sg:address":"2606 Phoenix Dr",
    "sg:city":"Greensboro",
    "sg:classifiers":[
        {
            "category":"Retail",
            "subcategory":"Repair Shop",
            "type":"Services"
        }
    ],
    "sg:phone":"+1 336 294 1420",
    "sg:postcode":"27406",
    "sg:province":"NC",
    "sg:tags":[
        "equipment",
        "conditioning",
        "air"
    ],
    "wof:name":"Piedmont Air Conditioning",
    "wof:placetype":"venue"
},
  "geometry": {"coordinates":[-79.833428,36.010905],"type":"Point"}
}