{
  "type": "Feature",
  "properties": {
    "iso:country":"US",
    "sg:address":"929 Ashley Glen Ln",
    "sg:city":"Winston Salem",
    "sg:classifiers":[
        {
            "category":"Wholesale",
            "subcategory":"Stationery",
            "type":"Manufacturing & Wholesale Goods"
        }
    ],
    "sg:phone":"+1 336 659 3323",
    "sg:postcode":"27104",
    "sg:province":"NC",
    "sg:tags":[
        "supply"
    ],
    "sg:website":"www.niches.com",
    "wof:name":"Niche Computer Supply Inc",
    "wof:placetype":"venue"
},
  "geometry": {"coordinates":[-80.325062,36.111092],"type":"Point"}
}