{
  "type": "Feature",
  "properties": {
    "iso:country":"US",
    "sg:address":"232 N Main St",
    "sg:city":"Salisbury",
    "sg:classifiers":[
        {
            "category":"Government",
            "subcategory":"Police Station",
            "type":"Public Place"
        }
    ],
    "sg:phone":"+1 704 638 3052",
    "sg:postcode":"28144",
    "sg:province":"NC",
    "sg:tags":[
        "sheriff"
    ],
    "wof:name":"Sheriff's Office-Civil Process",
    "wof:placetype":"venue"
},
  "geometry": {"coordinates":[-80.46803300000001,35.668905],"type":"Point"}
}