{
  "type": "Feature",
  "properties": {
    "addr:full":"323 Arnold Watson Rd Deep Gap NC 28618",
    "addr:housenumber":"323",
    "addr:postcode":"28618",
    "addr:street":"Arnold Watson Rd",
    "iso:country":"US",
    "sg:address":"323 Arnold Watson Rd",
    "sg:city":"Deep Gap",
    "sg:classifiers":[
        {
            "category":"Autos & Motor Vehicles",
            "subcategory":"Auto Supplies",
            "type":"Retail Goods"
        }
    ],
    "sg:phone":"+1 828 264 3386",
    "sg:postcode":"28618",
    "sg:province":"NC",
    "sg:tags":[
        "tire"
    ],
    "wof:name":"AAA Tire Auto Ctr Inc",
    "wof:placetype":"venue"
},
  "geometry": {"coordinates":[-81.52381200000001,36.218896],"type":"Point"}
}