{
  "type": "Feature",
  "properties": {
    "addr:full":"1915 12th Ave NE Hickory NC 28601",
    "addr:housenumber":"1915",
    "addr:postcode":"28601",
    "addr:street":"12Th Ave Ne",
    "iso:country":"US",
    "sg:address":"1915 12th Ave NE",
    "sg:city":"Hickory",
    "sg:classifiers":[
        {
            "category":"Personal",
            "subcategory":"Barber",
            "type":"Services"
        }
    ],
    "sg:phone":"+1   ",
    "sg:postcode":"28601",
    "sg:province":"NC",
    "sg:tags":[
        "shop"
    ],
    "wof:name":"Buelin Haircutters",
    "wof:placetype":"venue"
},
  "geometry": {"coordinates":[-81.300906,35.742943],"type":"Point"}
}