{
  "type": "Feature",
  "properties": {
    "addr:full":"800 Spartanburg Hwy Hendersonville NC 28792",
    "addr:housenumber":"800",
    "addr:postcode":"28792",
    "addr:street":"Spartanburg Hwy",
    "iso:country":"US",
    "sg:address":"800 Spartanburg Hwy",
    "sg:city":"Hendersonville",
    "sg:classifiers":[
        {
            "category":"Restaurant",
            "type":"Food & Drink"
        }
    ],
    "sg:phone":"+1 828 697 5158",
    "sg:postcode":"28792",
    "sg:province":"NC",
    "sg:tags":[
        "eating"
    ],
    "wof:name":"Pizza Inn",
    "wof:placetype":"venue"
},
  "geometry": {"coordinates":[-82.452607,35.306503],"type":"Point"}
}