{
  "type": "Feature",
  "properties": {
    "iso:country":"US",
    "sg:address":"123 Wicklow Ln",
    "sg:city":"Durham",
    "sg:classifiers":[
        {
            "category":"Professional",
            "subcategory":"Lawyer & Legal Services",
            "type":"Services"
        }
    ],
    "sg:phone":"+1   ",
    "sg:postcode":"27713",
    "sg:province":"NC",
    "wof:name":"Castle L R Pllc",
    "wof:placetype":"venue"
},
  "geometry": {"coordinates":[-78.91498300000001,35.889037],"type":"Point"}
}