{
  "type": "Feature",
  "properties": {
    "addr:full":"114 Old St Fayetteville NC 28301",
    "addr:housenumber":"114",
    "addr:postcode":"28301",
    "addr:street":"Old St",
    "iso:country":"US",
    "sg:address":"114 Old St",
    "sg:city":"Fayetteville",
    "sg:classifiers":[
        {
            "category":"Manufacturing",
            "subcategory":"Jewelry",
            "type":"Manufacturing & Wholesale Goods"
        }
    ],
    "sg:phone":"+1 910 323 9662",
    "sg:postcode":"28301",
    "sg:province":"NC",
    "sg:tags":[
        "ware",
        "mfg"
    ],
    "wof:name":"Carolina Specialties of NC",
    "wof:placetype":"venue"
},
  "geometry": {"coordinates":[-78.87931500000001,35.053922],"type":"Point"}
}