{
  "type": "Feature",
  "properties": {
    "addr:full":"4901 Old Pineville Rd Charlotte NC 28217",
    "addr:housenumber":"4901",
    "addr:postcode":"28217",
    "addr:street":"Old Pineville Rd",
    "iso:country":"US",
    "sg:address":"4901 Old Pineville Rd",
    "sg:city":"Charlotte",
    "sg:classifiers":[
        {
            "category":"Restaurant",
            "type":"Food & Drink"
        }
    ],
    "sg:phone":"+1 704 527 8811",
    "sg:postcode":"28217",
    "sg:province":"NC",
    "sg:tags":[
        "eating"
    ],
    "wof:name":"Chucky TS Beer & Bbq",
    "wof:placetype":"venue"
},
  "geometry": {"coordinates":[-80.87842999999999,35.172284],"type":"Point"}
}