{
  "type": "Feature",
  "properties": {
    "iso:country":"US",
    "sg:address":"306 New Bridge St",
    "sg:city":"Jacksonville",
    "sg:classifiers":[
        {
            "category":"Real Estate",
            "subcategory":"Surveying",
            "type":"Services"
        }
    ],
    "sg:phone":"+1 910 455 2414",
    "sg:postcode":"28540",
    "sg:province":"NC",
    "sg:tags":[
        "surveyor"
    ],
    "wof:name":"Parker & Assoc Surveyors",
    "wof:placetype":"venue"
},
  "geometry": {"coordinates":[-77.427881,34.750399],"type":"Point"}
}