{
  "type": "Feature",
  "properties": {
    "iso:country":"US",
    "sg:address":"1690 Pacolet Ct",
    "sg:city":"Gastonia",
    "sg:classifiers":[
        {
            "category":"Building & Trades",
            "subcategory":"Construction",
            "type":"Services"
        }
    ],
    "sg:phone":"+1 704 861 0080",
    "sg:postcode":"28052",
    "sg:province":"NC",
    "sg:tags":[
        "pavement",
        "marking"
    ],
    "wof:name":"Ledbetter Pavement Marking",
    "wof:placetype":"venue"
},
  "geometry": {"coordinates":[-81.224042,35.28742],"type":"Point"}
}