{
  "type": "Feature",
  "properties": {
    "addr:full":"6765 Jordan Rd Elm City NC 27822",
    "addr:housenumber":"6765",
    "addr:postcode":"27822",
    "addr:street":"Jordan Rd",
    "iso:country":"US",
    "sg:address":"6765 Jordan Rd",
    "sg:city":"Elm City",
    "sg:classifiers":[
        {
            "category":"Real Estate",
            "subcategory":"Developer",
            "type":"Services"
        }
    ],
    "sg:phone":"+1 252 442 3624",
    "sg:postcode":"27822",
    "sg:province":"NC",
    "wof:name":"Williams Farm Subdivision",
    "wof:placetype":"venue"
},
  "geometry": {"coordinates":[-77.874054,35.861672],"type":"Point"}
}