{
  "type": "Feature",
  "properties": {
    "iso:country":"US",
    "sg:address":"4021 Churchill Rd",
    "sg:city":"Charlotte",
    "sg:classifiers":[
        {
            "category":"Building & Trades",
            "subcategory":"Construction",
            "type":"Services"
        }
    ],
    "sg:phone":"+1 704 634 7582",
    "sg:postcode":"28211",
    "sg:province":"NC",
    "sg:tags":[
        "residential",
        "house"
    ],
    "wof:name":"Banister Homes Inc",
    "wof:placetype":"venue"
},
  "geometry": {"coordinates":[-80.801895,35.187712],"type":"Point"}
}