{
  "type": "Feature",
  "properties": {
    "iso:country":"US",
    "sg:address":"222 N Main St",
    "sg:city":"Norwood",
    "sg:classifiers":[
        {
            "category":"Autos & Motor Vehicles",
            "subcategory":"Fuel & Gas Station",
            "type":"Retail Goods"
        }
    ],
    "sg:phone":"+1 704 474 4041",
    "sg:postcode":"28128",
    "sg:province":"NC",
    "sg:tags":[
        "station",
        "gasoline"
    ],
    "wof:name":"Servco",
    "wof:placetype":"venue"
},
  "geometry": {"coordinates":[-80.123082,35.226606],"type":"Point"}
}