{
  "type": "Feature",
  "properties": {
    "addr:full":"4315 New Bern Hwy Jacksonville NC 28546",
    "addr:housenumber":"4315",
    "addr:postcode":"28546",
    "addr:street":"New Bern Hwy",
    "iso:country":"US",
    "sg:address":"4315 New Bern Hwy",
    "sg:city":"Jacksonville",
    "sg:classifiers":[
        {
            "category":"Travel",
            "subcategory":"Hotels & Motels",
            "type":"Entertainment"
        }
    ],
    "sg:phone":"+1 910 347 1948",
    "sg:postcode":"28546",
    "sg:province":"NC",
    "wof:name":"Travelers Inn",
    "wof:placetype":"venue"
},
  "geometry": {"coordinates":[-77.33485899999999,34.813977],"type":"Point"}
}