{
  "type": "Feature",
  "properties": {
    "addr:full":"107 Laurel Branch Dr Cary NC 27513",
    "addr:housenumber":"107",
    "addr:postcode":"27513",
    "addr:street":"Laurel Branch Dr",
    "iso:country":"US",
    "sg:address":"107 Laurel Branch Dr",
    "sg:city":"Cary",
    "sg:classifiers":[
        {
            "category":"Professional",
            "subcategory":"Computer Services",
            "type":"Services"
        }
    ],
    "sg:phone":"+1   ",
    "sg:postcode":"27513",
    "sg:province":"NC",
    "sg:tags":[
        "datum"
    ],
    "wof:name":"Josh Hames",
    "wof:placetype":"venue"
},
  "geometry": {"coordinates":[-78.823527,35.76923],"type":"Point"}
}