{
  "type": "Feature",
  "properties": {
    "iso:country":"US",
    "sg:address":"9800 S Tryon St",
    "sg:city":"Charlotte",
    "sg:classifiers":[
        {
            "category":"Autos & Motor Vehicles",
            "subcategory":"Auto Supplies",
            "type":"Retail Goods"
        }
    ],
    "sg:phone":"+1 704 583 2800",
    "sg:postcode":"28273",
    "sg:province":"NC",
    "sg:tags":[
        "tire"
    ],
    "wof:name":"Steele Creek Tire & Svc Ctr",
    "wof:placetype":"venue"
},
  "geometry": {"coordinates":[-80.94353099999999,35.125781],"type":"Point"}
}