{
  "type": "Feature",
  "properties": {
    "iso:country":"US",
    "sg:address":"901 E F St",
    "sg:city":"Butner",
    "sg:classifiers":[
        {
            "category":"Organizations",
            "subcategory":"Religious Organization",
            "type":"Services"
        }
    ],
    "sg:phone":"+1 919 575 6154",
    "sg:postcode":"27509",
    "sg:province":"NC",
    "sg:tags":[
        "church"
    ],
    "wof:name":"Union Chapel Baptist Church",
    "wof:placetype":"venue"
},
  "geometry": {"coordinates":[-78.750309,36.149543],"type":"Point"}
}