{
  "type": "Feature",
  "properties": {
    "iso:country":"US",
    "sg:address":"940 Corriher Springs Rd",
    "sg:city":"China Grove",
    "sg:classifiers":[
        {
            "category":"Farming",
            "subcategory":"Dairy Farm",
            "type":"Manufacturing & Wholesale Goods"
        }
    ],
    "sg:phone":"+1 704 857 9669",
    "sg:postcode":"28023",
    "sg:province":"NC",
    "wof:name":"Corriher Brothers",
    "wof:placetype":"venue"
},
  "geometry": {"coordinates":[-80.668176,35.585699],"type":"Point"}
}