{
  "type": "Feature",
  "properties": {
    "iso:country":"US",
    "sg:address":"125 Albert Morris Rd",
    "sg:city":"Vanceboro",
    "sg:classifiers":[
        {
            "category":"Utilities",
            "subcategory":"Telephone",
            "type":"Services"
        }
    ],
    "sg:phone":"+1 252 244 0682",
    "sg:postcode":"28586",
    "sg:province":"NC",
    "sg:tags":[
        "communications"
    ],
    "wof:name":"A D Morris",
    "wof:placetype":"venue"
},
  "geometry": {"coordinates":[-77.174403,35.311254],"type":"Point"}
}