{
  "type": "Feature",
  "properties": {
    "addr:full":"153 Hickory Tree Ln Angier NC 27501",
    "addr:housenumber":"153",
    "addr:postcode":"27501",
    "addr:street":"Hickory Tree Ln",
    "iso:country":"US",
    "sg:address":"153 Hickory Tree Ln",
    "sg:city":"Angier",
    "sg:classifiers":[
        {
            "category":"Retail",
            "subcategory":"Repair Shop",
            "type":"Services"
        }
    ],
    "sg:phone":"+1 919 854 9122",
    "sg:postcode":"27501",
    "sg:province":"NC",
    "sg:tags":[
        "repairing",
        "lawn",
        "mower"
    ],
    "wof:name":"Precision Outdoor Power Equip",
    "wof:placetype":"venue"
},
  "geometry": {"coordinates":[-78.684955,35.456359],"type":"Point"}
}