{
  "type": "Feature",
  "properties": {
    "iso:country":"US",
    "sg:address":"205 Lee St",
    "sg:city":"Shelby",
    "sg:classifiers":[
        {
            "category":"Health Services",
            "subcategory":"Health Practitioner",
            "type":"Services"
        }
    ],
    "sg:phone":"+1 704 471 0030",
    "sg:postcode":"28150",
    "sg:province":"NC",
    "sg:tags":[
        "pathologist",
        "speech"
    ],
    "wof:name":"Speech Language Pathology Svc",
    "wof:placetype":"venue"
},
  "geometry": {"coordinates":[-81.54431599999999,35.300865],"type":"Point"}
}