{
  "type": "Feature",
  "properties": {
    "iso:country":"US",
    "sg:address":"1201 W Lee St",
    "sg:city":"Greensboro",
    "sg:classifiers":[
        {
            "category":"Autos & Motor Vehicles",
            "subcategory":"Automobile Sales",
            "type":"Retail Goods"
        }
    ],
    "sg:phone":"+1 336 275 5448",
    "sg:postcode":"27403",
    "sg:province":"NC",
    "sg:tags":[
        "car",
        "dealer"
    ],
    "wof:name":"Monroe's Used Cars Inc",
    "wof:placetype":"venue"
},
  "geometry": {"coordinates":[-79.811859,36.062844],"type":"Point"}
}