{
  "type": "Feature",
  "properties": {
    "iso:country":"US",
    "sg:address":"101 Neville St",
    "sg:city":"Princeville",
    "sg:classifiers":[
        {
            "category":"Professional",
            "subcategory":"Advertising",
            "type":"Services"
        }
    ],
    "sg:phone":"+1 252 823 7175",
    "sg:postcode":"27886",
    "sg:province":"NC",
    "wof:name":"T.COM",
    "wof:placetype":"venue"
},
  "geometry": {"coordinates":[-77.523178,35.890817],"type":"Point"}
}