{
  "type": "Feature",
  "properties": {
    "iso:country":"US",
    "sg:address":"103 Muirs Chapel Rd",
    "sg:city":"Greensboro",
    "sg:classifiers":[
        {
            "category":"Restaurant",
            "type":"Food & Drink"
        }
    ],
    "sg:phone":"+1 336 808 0202",
    "sg:postcode":"27410",
    "sg:province":"NC",
    "sg:tags":[
        "eating"
    ],
    "wof:name":"Bohogs",
    "wof:placetype":"venue"
},
  "geometry": {"coordinates":[-79.86923899999999,36.070591],"type":"Point"}
}