{
  "type": "Feature",
  "properties": {
    "iso:country":"US",
    "sg:address":"230 W High Ave",
    "sg:city":"High Point",
    "sg:classifiers":[
        {
            "category":"Retail",
            "subcategory":"Auto Repair",
            "type":"Services"
        }
    ],
    "sg:phone":"+1 336 889 6211",
    "sg:postcode":"27260",
    "sg:province":"NC",
    "sg:tags":[
        "repairing",
        "automobile"
    ],
    "wof:name":"Robert's Auto Repair",
    "wof:placetype":"venue"
},
  "geometry": {"coordinates":[-80.010141,35.955042],"type":"Point"}
}