{
  "type": "Feature",
  "properties": {
    "addr:full":"1006 Norwalk St Greensboro NC 27407",
    "addr:housenumber":"1006",
    "addr:postcode":"27407",
    "addr:street":"Norwalk St",
    "iso:country":"US",
    "sg:address":"1006 Norwalk St",
    "sg:city":"Greensboro",
    "sg:classifiers":[
        {
            "category":"Manufacturing",
            "subcategory":"Paper Products",
            "type":"Manufacturing & Wholesale Goods"
        }
    ],
    "sg:phone":"+1 336 316 5080",
    "sg:postcode":"27407",
    "sg:province":"NC",
    "sg:tags":[
        "box",
        "mfg",
        "lithographic",
        "p",
        "converted",
        "mill"
    ],
    "wof:name":"Smurfit Stone Container Corp",
    "wof:placetype":"venue"
},
  "geometry": {"coordinates":[-79.872512,36.053463],"type":"Point"}
}