{
  "type": "Feature",
  "properties": {
    "iso:country":"US",
    "sg:address":"1639 US Hwy 74A Byp",
    "sg:city":"Spindale",
    "sg:classifiers":[
        {
            "category":"Restaurant",
            "type":"Food & Drink"
        }
    ],
    "sg:phone":"+1 828 287 5707",
    "sg:postcode":"28160",
    "sg:province":"NC",
    "wof:name":"Dragon Palace",
    "wof:placetype":"venue"
},
  "geometry": {"coordinates":[-81.90777300000001,35.340213],"type":"Point"}
}