{
  "type": "Feature",
  "properties": {
    "addr:full":"1501 Godwin Ave Lumberton NC 28358",
    "addr:housenumber":"1501",
    "addr:postcode":"28358",
    "addr:street":"Godwin Ave",
    "iso:country":"US",
    "sg:address":"1501 Godwin Ave",
    "sg:city":"Lumberton",
    "sg:classifiers":[
        {
            "category":"Utilities",
            "subcategory":"Telephone",
            "type":"Services"
        }
    ],
    "sg:phone":"+1 910 739 9091",
    "sg:postcode":"28358",
    "sg:province":"NC",
    "sg:tags":[
        "communications"
    ],
    "wof:name":"BellSouth",
    "wof:placetype":"venue"
},
  "geometry": {"coordinates":[-78.99636099999999,34.628015],"type":"Point"}
}