{
  "type": "Feature",
  "properties": {
    "addr:full":"508 E Main St Elizabeth City NC 27909",
    "addr:housenumber":"508",
    "addr:postcode":"27909",
    "addr:street":"E Main St",
    "iso:country":"US",
    "sg:address":"508 E Main St",
    "sg:city":"Elizabeth City",
    "sg:classifiers":[
        {
            "category":"Professional",
            "subcategory":"Business Services",
            "type":"Services"
        }
    ],
    "sg:phone":"+1 252 384 1048",
    "sg:postcode":"27909",
    "sg:province":"NC",
    "sg:tags":[
        "broker"
    ],
    "wof:name":"Sunbelt Business Brokers",
    "wof:placetype":"venue"
},
  "geometry": {"coordinates":[-76.220405,36.299915],"type":"Point"}
}