{
  "type": "Feature",
  "properties": {
    "addr:full":"117 W 3rd Ave Gastonia NC 28052",
    "addr:housenumber":"117",
    "addr:postcode":"28052",
    "addr:street":"W 3Rd Ave",
    "iso:country":"US",
    "sg:address":"117 W 3rd Ave",
    "sg:city":"Gastonia",
    "sg:classifiers":[
        {
            "category":"Professional",
            "subcategory":"Lawyer & Legal Services",
            "type":"Services"
        }
    ],
    "sg:phone":"+1   ",
    "sg:postcode":"28052",
    "sg:province":"NC",
    "wof:name":"Bob W Lawing",
    "wof:placetype":"venue"
},
  "geometry": {"coordinates":[-81.183544,35.259048],"type":"Point"}
}