{
  "type": "Feature",
  "properties": {
    "addr:full":"490 Vail Dr Greenville NC 27834",
    "addr:housenumber":"490",
    "addr:postcode":"27834",
    "addr:street":"Vail Dr",
    "iso:country":"US",
    "sg:address":"490 Vail Dr",
    "sg:city":"Greenville",
    "sg:classifiers":[
        {
            "category":"Personal",
            "subcategory":"Beauty Salon",
            "type":"Services"
        }
    ],
    "sg:phone":"+1 252 758 4306",
    "sg:postcode":"27834",
    "sg:province":"NC",
    "wof:name":"Crown & Glory Beauty Salon",
    "wof:placetype":"venue"
},
  "geometry": {"coordinates":[-77.313806,35.613921],"type":"Point"}
}