{
  "type": "Feature",
  "properties": {
    "iso:country":"US",
    "sg:address":"266 Northfield Rd",
    "sg:city":"Lumberton",
    "sg:classifiers":[
        {
            "category":"Professional",
            "type":"Services"
        }
    ],
    "sg:phone":"+1 910 738 8784",
    "sg:postcode":"28360",
    "sg:province":"NC",
    "wof:name":"Kenneth Locklear Rev",
    "wof:placetype":"venue"
},
  "geometry": {"coordinates":[-79.05154,34.648379],"type":"Point"}
}