{
  "type": "Feature",
  "properties": {
    "addr:full":"1318 Shelby Rd Kings Mountain NC 28086",
    "addr:housenumber":"1318",
    "addr:postcode":"28086",
    "addr:street":"Shelby Rd",
    "iso:country":"US",
    "sg:address":"1318 Shelby Rd",
    "sg:city":"Kings Mountain",
    "sg:classifiers":[
        {
            "category":"Shopping",
            "subcategory":"Discount & Variety Stores",
            "type":"Retail Goods"
        },
        {
            "category":"Shopping",
            "subcategory":"Department Store",
            "type":"Retail Goods"
        }
    ],
    "sg:phone":"+1 704 730 1210",
    "sg:postcode":"28086",
    "sg:province":"NC",
    "wof:name":"Family Dollar Stores",
    "wof:placetype":"venue"
},
  "geometry": {"coordinates":[-81.372105,35.239761],"type":"Point"}
}