{
  "type": "Feature",
  "properties": {
    "addr:full":"115 Union St S Concord NC 28025",
    "addr:housenumber":"115",
    "addr:postcode":"28025",
    "addr:street":"Union St S",
    "iso:country":"US",
    "sg:address":"115 Union St S",
    "sg:city":"Concord",
    "sg:classifiers":[
        {
            "category":"Manufacturing",
            "subcategory":"Printing",
            "type":"Manufacturing & Wholesale Goods"
        }
    ],
    "sg:phone":"+1 704 784 8337",
    "sg:postcode":"28025",
    "sg:province":"NC",
    "sg:tags":[
        "commercial"
    ],
    "wof:name":"TN Tees",
    "wof:placetype":"venue"
},
  "geometry": {"coordinates":[-80.578729,35.408414],"type":"Point"}
}