{
  "type": "Feature",
  "properties": {
    "iso:country":"US",
    "sg:address":"7600 Dunsmuir Ct",
    "sg:city":"Cornelius",
    "sg:classifiers":[
        {
            "category":"Arena",
            "subcategory":"Sports Club",
            "type":"Entertainment"
        }
    ],
    "sg:phone":"+1   ",
    "sg:postcode":"28031",
    "sg:province":"NC",
    "wof:name":"Hanson Enterprises",
    "wof:placetype":"venue"
},
  "geometry": {"coordinates":[-80.897914,35.443619],"type":"Point"}
}