{
  "type": "Feature",
  "properties": {
    "addr:full":"5725 Concord Pkwy S Concord NC 28027",
    "addr:housenumber":"5725",
    "addr:postcode":"28027",
    "addr:street":"Concord Pkwy S",
    "iso:country":"US",
    "sg:address":"5725 Concord Pkwy S",
    "sg:city":"Concord",
    "sg:classifiers":[
        {
            "category":"Real Estate",
            "subcategory":"Real Estate Agent",
            "type":"Services"
        }
    ],
    "sg:phone":"+1 704 455 3235",
    "sg:postcode":"28027",
    "sg:province":"NC",
    "wof:name":"SMI Properties",
    "wof:placetype":"venue"
},
  "geometry": {"coordinates":[-80.690161,35.349977],"type":"Point"}
}