{
  "type": "Feature",
  "properties": {
    "iso:country":"US",
    "sg:address":"3735 W Dixon Blvd",
    "sg:city":"Shelby",
    "sg:classifiers":[
        {
            "category":"Shopping",
            "subcategory":"Discount & Variety Stores",
            "type":"Retail Goods"
        }
    ],
    "sg:phone":"+1 704 434 8848",
    "sg:postcode":"28152",
    "sg:province":"NC",
    "wof:name":"Juniors Variety",
    "wof:placetype":"venue"
},
  "geometry": {"coordinates":[-81.63567,35.291038],"type":"Point"}
}