{
  "type": "Feature",
  "properties": {
    "iso:country":"US",
    "sg:address":"2689 Greensboro St Exd",
    "sg:city":"Lexington",
    "sg:classifiers":[
        {
            "category":"Real Estate",
            "subcategory":"Surveying",
            "type":"Services"
        }
    ],
    "sg:phone":"+1 336 242 1331",
    "sg:postcode":"27295",
    "sg:province":"NC",
    "sg:tags":[
        "surveyor"
    ],
    "wof:name":"Allan Mize Surveying",
    "wof:placetype":"venue"
},
  "geometry": {"coordinates":[-80.201685,35.853522],"type":"Point"}
}