{
  "type": "Feature",
  "properties": {
    "addr:full":"214 Andrew Sink Rd Lexington NC 27295",
    "addr:housenumber":"214",
    "addr:postcode":"27295",
    "addr:street":"Andrew Sink Rd",
    "iso:country":"US",
    "sg:address":"214 Andrew Sink Rd",
    "sg:city":"Lexington",
    "sg:classifiers":[
        {
            "category":"Organizations",
            "subcategory":"Religious Organization",
            "type":"Services"
        }
    ],
    "sg:phone":"+1   ",
    "sg:postcode":"27295",
    "sg:province":"NC",
    "wof:name":"Madison Heights Freewill",
    "wof:placetype":"venue"
},
  "geometry": {"coordinates":[-80.343125,35.839328],"type":"Point"}
}