{
  "type": "Feature",
  "properties": {
    "iso:country":"US",
    "sg:address":"212 Bell Arthur Dr",
    "sg:city":"Cary",
    "sg:classifiers":[
        {
            "category":"Professional",
            "subcategory":"Computer Services",
            "type":"Services"
        }
    ],
    "sg:phone":"+1   ",
    "sg:postcode":"27519",
    "sg:province":"NC",
    "sg:tags":[
        "related"
    ],
    "wof:name":"Business Resource Management",
    "wof:placetype":"venue"
},
  "geometry": {"coordinates":[-78.849099,35.771535],"type":"Point"}
}