{
  "type": "Feature",
  "properties": {
    "addr:full":"1691 Staton Mill Rd Greenville NC 27834",
    "addr:housenumber":"1691",
    "addr:postcode":"27834",
    "addr:street":"Staton Mill Rd",
    "iso:country":"US",
    "sg:address":"1691 Staton Mill Rd",
    "sg:city":"Greenville",
    "sg:classifiers":[
        {
            "category":"Organizations",
            "subcategory":"Religious Organization",
            "type":"Services"
        }
    ],
    "sg:phone":"+1 252 758 2151",
    "sg:postcode":"27834",
    "sg:province":"NC",
    "sg:tags":[
        "church"
    ],
    "wof:name":"St Mary Baptist Church",
    "wof:placetype":"venue"
},
  "geometry": {"coordinates":[-77.36130900000001,35.683254],"type":"Point"}
}