{
  "type": "Feature",
  "properties": {
    "iso:country":"US",
    "sg:address":"8108 Glamorgan Ln",
    "sg:city":"Matthews",
    "sg:classifiers":[
        {
            "category":"Shopping",
            "subcategory":"Gifts & Souvenirs",
            "type":"Retail Goods"
        }
    ],
    "sg:phone":"+1 704 882 0934",
    "sg:postcode":"28104",
    "sg:province":"NC",
    "wof:name":"Carolina Impressions",
    "wof:placetype":"venue"
},
  "geometry": {"coordinates":[-80.634086,35.13502],"type":"Point"}
}