{
  "type": "Feature",
  "properties": {
    "iso:country":"US",
    "sg:address":"731 E Mountain St",
    "sg:city":"Kernersville",
    "sg:classifiers":[
        {
            "category":"Autos & Motor Vehicles",
            "subcategory":"Auto Supplies",
            "type":"Retail Goods"
        }
    ],
    "sg:phone":"+1 336 996 2033",
    "sg:postcode":"27284",
    "sg:province":"NC",
    "sg:tags":[
        "tire"
    ],
    "wof:name":"Beroth Tire & Automotive Inc",
    "wof:placetype":"venue"
},
  "geometry": {"coordinates":[-80.058511,36.113236],"type":"Point"}
}