{
  "type": "Feature",
  "properties": {
    "iso:country":"US",
    "sg:address":"4381 Apex Hwy",
    "sg:city":"Durham",
    "sg:classifiers":[
        {
            "category":"Restaurant",
            "type":"Food & Drink"
        }
    ],
    "sg:phone":"+1 919 544 7887",
    "sg:postcode":"27713",
    "sg:province":"NC",
    "sg:tags":[
        "eating"
    ],
    "wof:name":"Bojangles",
    "wof:placetype":"venue"
},
  "geometry": {"coordinates":[-78.89262100000001,35.911042],"type":"Point"}
}