{
  "type": "Feature",
  "properties": {
    "iso:country":"US",
    "sg:address":"7097 Mendenhall Rd",
    "sg:city":"Archdale",
    "sg:classifiers":[
        {
            "category":"Wholesale",
            "subcategory":"Apparel",
            "type":"Manufacturing & Wholesale Goods"
        }
    ],
    "sg:phone":"+1 336 883 9171",
    "sg:postcode":"27263",
    "sg:province":"NC",
    "sg:tags":[
        "fabric"
    ],
    "sg:website":"www.goldingfabrics.com",
    "wof:name":"Golding Fabrics Inc",
    "wof:placetype":"venue"
},
  "geometry": {"coordinates":[-80.02879900000001,35.909342],"type":"Point"}
}