{
  "type": "Feature",
  "properties": {
    "iso:country":"US",
    "sg:address":"10332 James B White Hwy S",
    "sg:city":"Whiteville",
    "sg:classifiers":[
        {
            "category":"Professional",
            "type":"Services"
        }
    ],
    "sg:phone":"+1 910 653 2839",
    "sg:postcode":"28472",
    "sg:province":"NC",
    "wof:name":"James Elton Long",
    "wof:placetype":"venue"
},
  "geometry": {"coordinates":[-78.762547,34.204896],"type":"Point"}
}