{
  "type": "Feature",
  "properties": {
    "addr:full":"139 N Center St Statesville NC 28677",
    "addr:housenumber":"139",
    "addr:postcode":"28677",
    "addr:street":"N Center St",
    "iso:country":"US",
    "sg:address":"139 N Center St",
    "sg:city":"Statesville",
    "sg:classifiers":[
        {
            "category":"Insurance",
            "subcategory":"Insurance Agent",
            "type":"Services"
        }
    ],
    "sg:phone":"+1 704 872 3600",
    "sg:postcode":"28677",
    "sg:province":"NC",
    "wof:name":"Pegram & Bost",
    "wof:placetype":"venue"
},
  "geometry": {"coordinates":[-80.889296,35.786277],"type":"Point"}
}