{
  "type": "Feature",
  "properties": {
    "iso:country":"US",
    "sg:address":"1521 N Wesleyan Blvd",
    "sg:city":"Rocky Mount",
    "sg:classifiers":[
        {
            "category":"Home & Garden",
            "subcategory":"Mobile Homes",
            "type":"Retail Goods"
        }
    ],
    "sg:phone":"+1 252 977 9727",
    "sg:postcode":"27804",
    "sg:province":"NC",
    "wof:name":"Clayton Homes Inc",
    "wof:placetype":"venue"
},
  "geometry": {"coordinates":[-77.788625,35.980158],"type":"Point"}
}