{
  "type": "Feature",
  "properties": {
    "iso:country":"US",
    "sg:address":"2815 Voa Rd",
    "sg:city":"Washington",
    "sg:classifiers":[
        {
            "category":"Professional",
            "type":"Services"
        }
    ],
    "sg:phone":"+1 252 975 3217",
    "sg:postcode":"27889",
    "sg:province":"NC",
    "wof:name":"William V Alligood",
    "wof:placetype":"venue"
},
  "geometry": {"coordinates":[-77.09484999999999,35.654341],"type":"Point"}
}