{
  "type": "Feature",
  "properties": {
    "addr:full":"720 S Summit Ave Charlotte NC 28208",
    "addr:housenumber":"720",
    "addr:postcode":"28208",
    "addr:street":"S Summit Ave",
    "iso:country":"US",
    "sg:address":"720 S Summit Ave",
    "sg:city":"Charlotte",
    "sg:classifiers":[
        {
            "category":"Organizations",
            "subcategory":"Community Association",
            "type":"Services"
        }
    ],
    "sg:phone":"+1 704 370 1918",
    "sg:postcode":"28208",
    "sg:province":"NC",
    "sg:tags":[
        "club"
    ],
    "wof:name":"Foundations Club",
    "wof:placetype":"venue"
},
  "geometry": {"coordinates":[-80.862435,35.231258],"type":"Point"}
}