{
  "type": "Feature",
  "properties": {
    "iso:country":"US",
    "sg:address":"4404 Bridgeport Dr",
    "sg:city":"Wilmington",
    "sg:classifiers":[
        {
            "category":"Shopping",
            "subcategory":"Computers & Home Electronics",
            "type":"Retail Goods"
        }
    ],
    "sg:phone":"+1 910 452 2039",
    "sg:postcode":"28405",
    "sg:province":"NC",
    "sg:tags":[
        "software"
    ],
    "wof:name":"Allware Solutions",
    "wof:placetype":"venue"
},
  "geometry": {"coordinates":[-77.878511,34.305988],"type":"Point"}
}