{
  "type": "Feature",
  "properties": {
    "iso:country":"US",
    "sg:address":"5 Woodland Ave",
    "sg:city":"Asheville",
    "sg:classifiers":[
        {
            "category":"Social Services",
            "subcategory":"Child Care",
            "type":"Services"
        }
    ],
    "sg:phone":"+1 828 225 6555",
    "sg:postcode":"28806",
    "sg:province":"NC",
    "wof:name":"Hearts & Hands Child Care Ctr",
    "wof:placetype":"venue"
},
  "geometry": {"coordinates":[-82.622277,35.570995],"type":"Point"}
}