{
  "type": "Feature",
  "properties": {
    "addr:full":"2445 Reliance Ave Apex NC 27539",
    "addr:housenumber":"2445",
    "addr:postcode":"27539",
    "addr:street":"Reliance Ave",
    "iso:country":"US",
    "sg:address":"2445 Reliance Ave",
    "sg:city":"Apex",
    "sg:classifiers":[
        {
            "category":"Home & Garden",
            "subcategory":"Building Materials",
            "type":"Retail Goods"
        }
    ],
    "sg:phone":"+1 919 363 7637",
    "sg:postcode":"27539",
    "sg:province":"NC",
    "sg:tags":[
        "downspouts",
        "gutter"
    ],
    "sg:website":"http://www.triangleinstall.com",
    "wof:name":"Triangle Installation Service",
    "wof:placetype":"venue"
},
  "geometry": {"coordinates":[-78.820921,35.717183],"type":"Point"}
}