{
  "type": "Feature",
  "properties": {
    "iso:country":"US",
    "sg:address":"1725 Cotton Grove Rd",
    "sg:city":"Lexington",
    "sg:classifiers":[
        {
            "category":"Building & Trades",
            "subcategory":"Construction",
            "type":"Services"
        }
    ],
    "sg:phone":"+1 336 357 5555",
    "sg:postcode":"27292",
    "sg:province":"NC",
    "sg:tags":[
        "tile",
        "dealer"
    ],
    "wof:name":"E E Wilson Floor Covering Inc",
    "wof:placetype":"venue"
},
  "geometry": {"coordinates":[-80.259586,35.775707],"type":"Point"}
}