{
  "type": "Feature",
  "properties": {
    "iso:country":"US",
    "sg:address":"212 Hillcrest Cir",
    "sg:city":"Chapel Hill",
    "sg:classifiers":[
        {
            "category":"Building & Trades",
            "subcategory":"Construction",
            "type":"Services"
        }
    ],
    "sg:phone":"+1 919 929 1866",
    "sg:postcode":"27514",
    "sg:province":"NC",
    "sg:tags":[
        "general",
        "commercial",
        "contractor"
    ],
    "wof:name":"Msl Enterprises Inc",
    "wof:placetype":"venue"
},
  "geometry": {"coordinates":[-79.03517600000001,35.921215],"type":"Point"}
}