{
  "type": "Feature",
  "properties": {
    "iso:country":"US",
    "sg:address":"3515 Stoney Creek Church Rd",
    "sg:city":"Elon College",
    "sg:classifiers":[
        {
            "category":"Manufacturing",
            "subcategory":"Food",
            "type":"Manufacturing & Wholesale Goods"
        }
    ],
    "sg:phone":"+1 336 584 4117",
    "sg:postcode":"27244",
    "sg:province":"NC",
    "sg:tags":[
        "winery"
    ],
    "wof:name":"Creek Side Winery",
    "wof:placetype":"venue"
},
  "geometry": {"coordinates":[-79.491741,36.22423],"type":"Point"}
}