{
  "type": "Feature",
  "properties": {
    "addr:full":"2160 Joelene Dr Rocky Mount NC 27803",
    "addr:housenumber":"2160",
    "addr:postcode":"27803",
    "addr:street":"Joelene Dr",
    "iso:country":"US",
    "sg:address":"2160 Joelene Dr",
    "sg:city":"Rocky Mount",
    "sg:phone":"+1 252 827 4875",
    "sg:postcode":"27803",
    "sg:province":"NC",
    "sg:tags":[
        "farm",
        "tobacco"
    ],
    "wof:name":"Marshall Dunn",
    "wof:placetype":"venue"
},
  "geometry": {"coordinates":[-77.8562,35.941629],"type":"Point"}
}