{
  "type": "Feature",
  "properties": {
    "addr:full":"115 Nash St E Wilson NC 27893",
    "addr:housenumber":"115",
    "addr:postcode":"27893",
    "addr:street":"Nash St E",
    "iso:country":"US",
    "sg:address":"115 Nash St E",
    "sg:city":"Wilson",
    "sg:classifiers":[
        {
            "category":"Government",
            "subcategory":"Office",
            "type":"Public Place"
        }
    ],
    "sg:phone":"+1 252 291 1063",
    "sg:postcode":"27893",
    "sg:province":"NC",
    "wof:name":"Victim-Witness Coordinator",
    "wof:placetype":"venue"
},
  "geometry": {"coordinates":[-77.91091900000001,35.72573],"type":"Point"}
}