{
  "type": "Feature",
  "properties": {
    "addr:full":"8207 Market St Ste C Wilmington NC 28411",
    "addr:housenumber":"8207",
    "addr:postcode":"28411",
    "addr:street":"Market St Ste C",
    "iso:country":"US",
    "sg:address":"8207 Market St Ste C",
    "sg:city":"Wilmington",
    "sg:classifiers":[
        {
            "category":"Restaurant",
            "type":"Food & Drink"
        }
    ],
    "sg:phone":"+1 910 686 4849",
    "sg:postcode":"28411",
    "sg:province":"NC",
    "wof:name":"Jersey Mike's Giant Subs",
    "wof:placetype":"venue"
},
  "geometry": {"coordinates":[-77.810097,34.282501],"type":"Point"}
}