{
  "type": "Feature",
  "properties": {
    "addr:full":"35 Fountain Manor Dr Greensboro NC 27405",
    "addr:housenumber":"35",
    "addr:postcode":"27405",
    "addr:street":"Fountain Manor Dr",
    "iso:country":"US",
    "sg:address":"35 Fountain Manor Dr",
    "sg:city":"Greensboro",
    "sg:classifiers":[
        {
            "category":"Banks & Credit Unions",
            "subcategory":"Financial Services",
            "type":"Services"
        }
    ],
    "sg:phone":"+1 336 272 5530",
    "sg:postcode":"27405",
    "sg:province":"NC",
    "sg:tags":[
        "trust",
        "management"
    ],
    "wof:name":"Ben Cone Family Partnership",
    "wof:placetype":"venue"
},
  "geometry": {"coordinates":[-79.78549,36.104841],"type":"Point"}
}