{
  "type": "Feature",
  "properties": {
    "iso:country":"US",
    "sg:address":"7151 Meeting St",
    "sg:city":"Charlotte",
    "sg:classifiers":[
        {
            "category":"Personal",
            "subcategory":"Beauty Salon",
            "type":"Services"
        }
    ],
    "sg:phone":"+1   ",
    "sg:postcode":"28210",
    "sg:province":"NC",
    "sg:tags":[
        "shop"
    ],
    "wof:name":"Km & Company Inc",
    "wof:placetype":"venue"
},
  "geometry": {"coordinates":[-80.85688500000001,35.122497],"type":"Point"}
}