{
  "type": "Feature",
  "properties": {
    "iso:country":"US",
    "sg:address":"210 Brentwood Cir",
    "sg:city":"Newton",
    "sg:classifiers":[
        {
            "category":"Manufacturing",
            "subcategory":"Building Materials",
            "type":"Manufacturing & Wholesale Goods"
        }
    ],
    "sg:phone":"+1 828 464 0187",
    "sg:postcode":"28658",
    "sg:province":"NC",
    "sg:tags":[
        "hardwood",
        "mfg"
    ],
    "wof:name":"Oliver Wood Products Co",
    "wof:placetype":"venue"
},
  "geometry": {"coordinates":[-81.227862,35.64101],"type":"Point"}
}