{
  "type": "Feature",
  "properties": {
    "addr:full":"1603 E Dixon Blvd Shelby NC 28152",
    "addr:housenumber":"1603",
    "addr:postcode":"28152",
    "addr:street":"E Dixon Blvd",
    "iso:country":"US",
    "sg:address":"1603 E Dixon Blvd",
    "sg:city":"Shelby",
    "sg:classifiers":[
        {
            "category":"Shopping",
            "subcategory":"Used Merchandise",
            "type":"Retail Goods"
        }
    ],
    "sg:phone":"+1 704 471 0052",
    "sg:postcode":"28152",
    "sg:province":"NC",
    "sg:tags":[
        "pawnbroker"
    ],
    "wof:name":"74 Pawn & Arcade",
    "wof:placetype":"venue"
},
  "geometry": {"coordinates":[-81.514579,35.273372],"type":"Point"}
}