{
  "type": "Feature",
  "properties": {
    "addr:full":"307 N Sterling St Morganton NC 28655",
    "addr:housenumber":"307",
    "addr:postcode":"28655",
    "addr:street":"N Sterling St",
    "iso:country":"US",
    "sg:address":"307 N Sterling St",
    "sg:city":"Morganton",
    "sg:classifiers":[
        {
            "category":"Professional",
            "type":"Services"
        }
    ],
    "sg:phone":"+1 828 437 3606",
    "sg:postcode":"28655",
    "sg:province":"NC",
    "sg:tags":[
        "establishment"
    ],
    "wof:name":"Community Grounds",
    "wof:placetype":"venue"
},
  "geometry": {"coordinates":[-81.689595,35.746653],"type":"Point"}
}