{
  "type": "Feature",
  "properties": {
    "iso:country":"US",
    "sg:address":"3337 Monroe Rd",
    "sg:city":"Charlotte",
    "sg:classifiers":[
        {
            "category":"Real Estate",
            "subcategory":"Real Estate Agent",
            "type":"Services"
        }
    ],
    "sg:phone":"+1 704 342 5800",
    "sg:postcode":"28205",
    "sg:province":"NC",
    "sg:tags":[
        "management"
    ],
    "wof:name":"Harpe Realty",
    "wof:placetype":"venue"
},
  "geometry": {"coordinates":[-80.799217,35.202399],"type":"Point"}
}