{
  "type": "Feature",
  "properties": {
    "iso:country":"US",
    "sg:address":"17668 Efird Rd",
    "sg:city":"Albemarle",
    "sg:classifiers":[
        {
            "category":"Building & Trades",
            "subcategory":"Construction",
            "type":"Services"
        }
    ],
    "sg:phone":"+1 704 983 1384",
    "sg:postcode":"28001",
    "sg:province":"NC",
    "sg:tags":[
        "contractor"
    ],
    "wof:name":"Donnie L Furr Inc",
    "wof:placetype":"venue"
},
  "geometry": {"coordinates":[-80.277242,35.275581],"type":"Point"}
}