{
  "type": "Feature",
  "properties": {
    "iso:country":"US",
    "sg:address":"9 Lakeside Ave",
    "sg:city":"Granite Falls",
    "sg:classifiers":[
        {
            "category":"Organizations",
            "subcategory":"Religious Organization",
            "type":"Services"
        }
    ],
    "sg:phone":"+1 828 396 1011",
    "sg:postcode":"28630",
    "sg:province":"NC",
    "sg:tags":[
        "church"
    ],
    "wof:name":"First United Methodist Church",
    "wof:placetype":"venue"
},
  "geometry": {"coordinates":[-81.43452600000001,35.798912],"type":"Point"}
}