{
  "type": "Feature",
  "properties": {
    "addr:full":"4858 Steel Bridge Rd Sanford NC 27330",
    "addr:housenumber":"4858",
    "addr:postcode":"27330",
    "addr:street":"Steel Bridge Rd",
    "iso:country":"US",
    "sg:address":"4858 Steel Bridge Rd",
    "sg:city":"Sanford",
    "sg:classifiers":[
        {
            "category":"Building & Trades",
            "subcategory":"Construction",
            "type":"Services"
        }
    ],
    "sg:phone":"+1 919 776 5748",
    "sg:postcode":"27330",
    "sg:province":"NC",
    "sg:tags":[
        "house"
    ],
    "wof:name":"BJ Construction",
    "wof:placetype":"venue"
},
  "geometry": {"coordinates":[-79.302875,35.458596],"type":"Point"}
}