{
  "type": "Feature",
  "properties": {
    "iso:country":"US",
    "sg:address":"1515 Penny Ln",
    "sg:city":"Lenoir",
    "sg:classifiers":[
        {
            "category":"Shopping",
            "subcategory":"Musical Instruments",
            "type":"Retail Goods"
        }
    ],
    "sg:phone":"+1 828 754 7156",
    "sg:postcode":"28645",
    "sg:province":"NC",
    "wof:name":"Amm Mini Storage",
    "wof:placetype":"venue"
},
  "geometry": {"coordinates":[-81.605058,35.918202],"type":"Point"}
}