{
  "type": "Feature",
  "properties": {
    "iso:country":"US",
    "sg:address":"1385 Crews Farm Rd",
    "sg:city":"Kernersville",
    "sg:classifiers":[
        {
            "category":"Organizations",
            "subcategory":"Religious Organization",
            "type":"Services"
        }
    ],
    "sg:phone":"+1   ",
    "sg:postcode":"27284",
    "sg:province":"NC",
    "wof:name":"Reorgan Church of Jesus Christ",
    "wof:placetype":"venue"
},
  "geometry": {"coordinates":[-80.06442199999999,36.080097],"type":"Point"}
}