{
  "type": "Feature",
  "properties": {
    "iso:country":"US",
    "sg:address":"328 Laurel Creek Rd",
    "sg:city":"Todd",
    "sg:classifiers":[
        {
            "category":"Real Estate",
            "subcategory":"Real Estate Services",
            "type":"Services"
        },
        {
            "category":"Real Estate",
            "subcategory":"Real Estate Agent",
            "type":"Services"
        }
    ],
    "sg:phone":"+1 336 977 0249",
    "sg:postcode":"28684",
    "sg:province":"NC",
    "sg:tags":[
        "buyer",
        "broker"
    ],
    "wof:name":"North Peak Real Estate",
    "wof:placetype":"venue"
},
  "geometry": {"coordinates":[-81.553498,36.339253],"type":"Point"}
}