{
  "type": "Feature",
  "properties": {
    "addr:full":"106 Mackwood Rd Mooresville NC 28115",
    "addr:housenumber":"106",
    "addr:postcode":"28115",
    "addr:street":"Mackwood Rd",
    "iso:country":"US",
    "sg:address":"106 Mackwood Rd",
    "sg:city":"Mooresville",
    "sg:classifiers":[
        {
            "category":"Retail",
            "subcategory":"Auto Repair",
            "type":"Services"
        }
    ],
    "sg:phone":"+1 704 660 7912",
    "sg:postcode":"28115",
    "sg:province":"NC",
    "sg:tags":[
        "repairing",
        "automobile"
    ],
    "wof:name":"Hickman Automotive Honda-Acura",
    "wof:placetype":"venue"
},
  "geometry": {"coordinates":[-80.835092,35.558706],"type":"Point"}
}