{
  "type": "Feature",
  "properties": {
    "iso:country":"US",
    "sg:address":"80 Peachtree Rd",
    "sg:city":"Asheville",
    "sg:classifiers":[
        {
            "category":"Professional",
            "type":"Services"
        }
    ],
    "sg:phone":"+1 828 274 7775",
    "sg:postcode":"28803",
    "sg:province":"NC",
    "sg:tags":[
        "establishment"
    ],
    "wof:name":"Cornerstone Group",
    "wof:placetype":"venue"
},
  "geometry": {"coordinates":[-82.52563499999999,35.51437],"type":"Point"}
}