{
  "type": "Feature",
  "properties": {
    "iso:country":"US",
    "sg:address":"3189 US Hwy 158",
    "sg:city":"Mocksville",
    "sg:classifiers":[
        {
            "category":"Shopping",
            "type":"Retail Goods"
        }
    ],
    "sg:phone":"+1 336 998 2790",
    "sg:postcode":"27028",
    "sg:province":"NC",
    "sg:tags":[
        "product",
        "wood"
    ],
    "wof:name":"L A Wood Inc",
    "wof:placetype":"venue"
},
  "geometry": {"coordinates":[-80.511866,35.95773],"type":"Point"}
}