{
  "type": "Feature",
  "properties": {
    "iso:country":"US",
    "sg:address":"80 West Blvd",
    "sg:city":"Franklin",
    "sg:classifiers":[
        {
            "category":"Shopping",
            "subcategory":"Computers & Home Electronics",
            "type":"Retail Goods"
        },
        {
            "category":"Cinema",
            "subcategory":"Movie Rental",
            "type":"Entertainment"
        }
    ],
    "sg:phone":"+1 828 349 2893",
    "sg:postcode":"28734",
    "sg:province":"NC",
    "sg:tags":[
        "tape",
        "video",
        "system"
    ],
    "wof:name":"About Audio Video Inc",
    "wof:placetype":"venue"
},
  "geometry": {"coordinates":[-83.390169,35.181159],"type":"Point"}
}