{
  "type": "Feature",
  "properties": {
    "addr:full":"114 N Steele St Sanford NC 27330",
    "addr:housenumber":"114",
    "addr:postcode":"27330",
    "addr:street":"N Steele St",
    "iso:country":"US",
    "sg:address":"114 N Steele St",
    "sg:city":"Sanford",
    "sg:classifiers":[
        {
            "category":"Education",
            "subcategory":"Dance Studio",
            "type":"Public Place"
        }
    ],
    "sg:phone":"+1 919 774 6917",
    "sg:postcode":"27330",
    "sg:province":"NC",
    "sg:tags":[
        "instruction",
        "dancing"
    ],
    "wof:name":"Kelly's School Of Dance",
    "wof:placetype":"venue"
},
  "geometry": {"coordinates":[-79.179333,35.480926],"type":"Point"}
}