{
  "type": "Feature",
  "properties": {
    "iso:country":"US",
    "sg:address":"7000 Winding Cedar Trl",
    "sg:city":"Charlotte",
    "sg:classifiers":[
        {
            "category":"Building & Trades",
            "subcategory":"Construction",
            "type":"Services"
        }
    ],
    "sg:phone":"+1 704 752 8538",
    "sg:postcode":"28212",
    "sg:province":"NC",
    "sg:tags":[
        "maintenance",
        "contractor"
    ],
    "wof:name":"Quality Maintenance",
    "wof:placetype":"venue"
},
  "geometry": {"coordinates":[-80.728015,35.206422],"type":"Point"}
}