{
  "type": "Feature",
  "properties": {
    "iso:country":"US",
    "sg:address":"330 W High Ave",
    "sg:city":"High Point",
    "sg:classifiers":[
        {
            "category":"Professional",
            "type":"Services"
        }
    ],
    "sg:phone":"+1 336 882 2633",
    "sg:postcode":"27260",
    "sg:province":"NC",
    "sg:tags":[
        "establishment"
    ],
    "wof:name":"Amy Howard Collection",
    "wof:placetype":"venue"
},
  "geometry": {"coordinates":[-80.008702,35.955936],"type":"Point"}
}