{
  "type": "Feature",
  "properties": {
    "addr:full":"8111 Fairview Rd Charlotte NC 28227",
    "addr:housenumber":"8111",
    "addr:postcode":"28227",
    "addr:street":"Fairview Rd",
    "iso:country":"US",
    "sg:address":"8111 Fairview Rd",
    "sg:city":"Charlotte",
    "sg:classifiers":[
        {
            "category":"Bars & Pubs",
            "type":"Food & Drink"
        }
    ],
    "sg:phone":"+1 704 545 1070",
    "sg:postcode":"28227",
    "sg:province":"NC",
    "sg:tags":[
        "club",
        "sport",
        "bar"
    ],
    "wof:name":"ONeils",
    "wof:placetype":"venue"
},
  "geometry": {"coordinates":[-80.644779,35.179193],"type":"Point"}
}