{
  "type": "Feature",
  "properties": {
    "iso:country":"US",
    "sg:address":"1622 Kirkpatrick Rd",
    "sg:city":"Burlington",
    "sg:classifiers":[
        {
            "category":"Organizations",
            "subcategory":"Religious Organization",
            "type":"Services"
        }
    ],
    "sg:phone":"+1 336 226 5205",
    "sg:postcode":"27215",
    "sg:province":"NC",
    "sg:tags":[
        "church"
    ],
    "sg:website":"www.beaconbaptist.com",
    "wof:name":"Beacon Baptist Church",
    "wof:placetype":"venue"
},
  "geometry": {"coordinates":[-79.489814,36.044102],"type":"Point"}
}