{
  "type": "Feature",
  "properties": {
    "addr:full":"404 E Main St Jamestown NC 27282",
    "addr:housenumber":"404",
    "addr:postcode":"27282",
    "addr:street":"E Main St",
    "iso:country":"US",
    "sg:address":"404 E Main St",
    "sg:city":"Jamestown",
    "sg:classifiers":[
        {
            "category":"Farming",
            "subcategory":"Farm",
            "type":"Manufacturing & Wholesale Goods"
        }
    ],
    "sg:phone":"+1 336 454 1986",
    "sg:postcode":"27282",
    "sg:province":"NC",
    "wof:name":"Magnolia Farms Riding Academy",
    "wof:placetype":"venue"
},
  "geometry": {"coordinates":[-79.93357899999999,35.997097],"type":"Point"}
}