{
  "type": "Feature",
  "properties": {
    "addr:full":"3626 Holloway St Durham NC 27703",
    "addr:housenumber":"3626",
    "addr:postcode":"27703",
    "addr:street":"Holloway St",
    "iso:country":"US",
    "sg:address":"3626 Holloway St",
    "sg:city":"Durham",
    "sg:classifiers":[
        {
            "category":"Autos & Motor Vehicles",
            "subcategory":"Automobile Sales",
            "type":"Retail Goods"
        }
    ],
    "sg:phone":"+1 919 598 0966",
    "sg:postcode":"27703",
    "sg:province":"NC",
    "sg:tags":[
        "used"
    ],
    "wof:name":"Car Care Express",
    "wof:placetype":"venue"
},
  "geometry": {"coordinates":[-78.821113,35.981374],"type":"Point"}
}