{
  "type": "Feature",
  "properties": {
    "addr:full":"1100 Bragg Blvd Fayetteville NC 28301",
    "addr:housenumber":"1100",
    "addr:postcode":"28301",
    "addr:street":"Bragg Blvd",
    "iso:country":"US",
    "sg:address":"1100 Bragg Blvd",
    "sg:city":"Fayetteville",
    "sg:classifiers":[
        {
            "category":"Travel",
            "subcategory":"Hotels & Motels",
            "type":"Entertainment"
        }
    ],
    "sg:phone":"+1 910 436 6700",
    "sg:postcode":"28301",
    "sg:province":"NC",
    "wof:name":"Sleep Inn",
    "wof:placetype":"venue"
},
  "geometry": {"coordinates":[-78.90034300000001,35.066662],"type":"Point"}
}