{
  "type": "Feature",
  "properties": {
    "iso:country":"US",
    "sg:address":"829 Shoreland Rd",
    "sg:city":"Winston Salem",
    "sg:classifiers":[
        {
            "category":"Social Services",
            "type":"Services"
        }
    ],
    "sg:phone":"+1 336 768 1595",
    "sg:postcode":"27106",
    "sg:province":"NC",
    "sg:tags":[
        "counseling"
    ],
    "wof:name":"Insight Psychotherapy & Human",
    "wof:placetype":"venue"
},
  "geometry": {"coordinates":[-80.299684,36.111918],"type":"Point"}
}