{
  "type": "Feature",
  "properties": {
    "iso:country":"US",
    "sg:address":"506 Radar Rd",
    "sg:city":"Greensboro",
    "sg:classifiers":[
        {
            "category":"Building & Trades",
            "subcategory":"Equipment Rental",
            "type":"Services"
        }
    ],
    "sg:phone":"+1 336 851 1351",
    "sg:postcode":"27410",
    "sg:province":"NC",
    "sg:tags":[
        "furniture"
    ],
    "wof:name":"Executive Furniture Leasing",
    "wof:placetype":"venue"
},
  "geometry": {"coordinates":[-79.92205,36.095981],"type":"Point"}
}