{
  "type": "Feature",
  "properties": {
    "iso:country":"US",
    "sg:address":"2007 Walnut St",
    "sg:city":"Cary",
    "sg:classifiers":[
        {
            "category":"Bars & Pubs",
            "type":"Food & Drink"
        }
    ],
    "sg:phone":"+1 919 852 4040",
    "sg:postcode":"27518",
    "sg:province":"NC",
    "wof:name":"Cary Crossroads Tavern LLC",
    "wof:placetype":"venue"
},
  "geometry": {"coordinates":[-78.743414,35.760189],"type":"Point"}
}