{
  "type": "Feature",
  "properties": {
    "iso:country":"US",
    "sg:address":"355 Wildlife Rd",
    "sg:city":"Lillington",
    "sg:classifiers":[
        {
            "category":"Farming",
            "subcategory":"Farm",
            "type":"Manufacturing & Wholesale Goods"
        }
    ],
    "sg:phone":"+1 910 893 5532",
    "sg:postcode":"27546",
    "sg:province":"NC",
    "sg:tags":[
        "crop",
        "general"
    ],
    "wof:name":"Shroats Farms LLC",
    "wof:placetype":"venue"
},
  "geometry": {"coordinates":[-78.773831,35.397422],"type":"Point"}
}