{
  "type": "Feature",
  "properties": {
    "addr:full":"8811 Blakeney Dr Charlotte NC 28277",
    "addr:housenumber":"8811",
    "addr:postcode":"28277",
    "addr:street":"Blakeney Dr",
    "iso:country":"US",
    "sg:address":"8811 Blakeney Dr",
    "sg:city":"Charlotte",
    "sg:classifiers":[
        {
            "category":"Health Services",
            "subcategory":"Optometrist",
            "type":"Services"
        }
    ],
    "sg:phone":"+1 704 926 3937",
    "sg:postcode":"28277",
    "sg:province":"NC",
    "wof:name":"Piedmont Eyecare Assoc",
    "wof:placetype":"venue"
},
  "geometry": {"coordinates":[-80.81558800000001,35.037743],"type":"Point"}
}