{
  "type": "Feature",
  "properties": {
    "addr:full":"208 Valley Creek Dr Maggie Valley NC 28751",
    "addr:housenumber":"208",
    "addr:postcode":"28751",
    "addr:street":"Valley Creek Dr Maggie",
    "iso:country":"US",
    "sg:address":"208 Valley Creek Dr",
    "sg:city":"Maggie Valley",
    "sg:classifiers":[
        {
            "category":"Retail",
            "subcategory":"Repair Shop",
            "type":"Services"
        }
    ],
    "sg:phone":"+1   ",
    "sg:postcode":"28751",
    "sg:province":"NC",
    "wof:name":"Paul M Wilson",
    "wof:placetype":"venue"
},
  "geometry": {"coordinates":[-83.103058,35.521625],"type":"Point"}
}