{
  "type": "Feature",
  "properties": {
    "iso:country":"US",
    "sg:address":"103 Sleepy Dr",
    "sg:city":"Spring Lake",
    "sg:classifiers":[
        {
            "category":"Food & Beverages",
            "subcategory":"Groceries & Convenience Stores",
            "type":"Retail Goods"
        }
    ],
    "sg:phone":"+1 910 496 1247",
    "sg:postcode":"28390",
    "sg:province":"NC",
    "sg:tags":[
        "grocer"
    ],
    "wof:name":"Care Shop",
    "wof:placetype":"venue"
},
  "geometry": {"coordinates":[-78.983265,35.177811],"type":"Point"}
}