{
  "type": "Feature",
  "properties": {
    "iso:country":"US",
    "sg:address":"305 Ashville Ave Ste H",
    "sg:city":"Cary",
    "sg:classifiers":[
        {
            "category":"Arts & Performance",
            "subcategory":"Arts Center",
            "type":"Entertainment"
        }
    ],
    "sg:phone":"+1 919 851 2570",
    "sg:postcode":"27511",
    "sg:province":"NC",
    "sg:tags":[
        "performing"
    ],
    "sg:website":"www.premierschoolofdance.com",
    "wof:name":"Premier School of Dance",
    "wof:placetype":"venue"
},
  "geometry": {"coordinates":[-78.785202,35.739399],"type":"Point"}
}