{
  "type": "Feature",
  "properties": {
    "iso:country":"US",
    "sg:address":"221 S Cool Spring St",
    "sg:city":"Fayetteville",
    "sg:classifiers":[
        {
            "category":"Retail",
            "subcategory":"Auto Repair",
            "type":"Services"
        }
    ],
    "sg:phone":"+1 910 323 2444",
    "sg:postcode":"28301",
    "sg:province":"NC",
    "sg:tags":[
        "repairing",
        "automobile"
    ],
    "wof:name":"Prestige Automotive Svc",
    "wof:placetype":"venue"
},
  "geometry": {"coordinates":[-78.87549,35.049027],"type":"Point"}
}