{
  "type": "Feature",
  "properties": {
    "addr:full":"1025 W Mount Dr Rocky Mount NC 27803",
    "addr:housenumber":"1025",
    "addr:postcode":"27803",
    "addr:street":"W Mount Dr",
    "iso:country":"US",
    "sg:address":"1025 W Mount Dr",
    "sg:city":"Rocky Mount",
    "sg:classifiers":[
        {
            "category":"Retail",
            "subcategory":"Auto Repair",
            "type":"Services"
        }
    ],
    "sg:phone":"+1 252 443 5700",
    "sg:postcode":"27803",
    "sg:province":"NC",
    "sg:tags":[
        "engine",
        "transmission",
        "shop",
        "general"
    ],
    "wof:name":"Wester Auto Service",
    "wof:placetype":"venue"
},
  "geometry": {"coordinates":[-77.832076,35.934121],"type":"Point"}
}