{
  "type": "Feature",
  "properties": {
    "addr:full":"1319 Atkinson St Laurinburg NC 28352",
    "addr:housenumber":"1319",
    "addr:postcode":"28352",
    "addr:street":"Atkinson St",
    "iso:country":"US",
    "sg:address":"1319 Atkinson St",
    "sg:city":"Laurinburg",
    "sg:classifiers":[
        {
            "category":"Utilities",
            "subcategory":"Water",
            "type":"Services"
        }
    ],
    "sg:phone":"+1 910 276 2811",
    "sg:postcode":"28352",
    "sg:province":"NC",
    "sg:tags":[
        "supply"
    ],
    "wof:name":"Laurinburg and Southern RR",
    "wof:placetype":"venue"
},
  "geometry": {"coordinates":[-79.47111700000001,34.760649],"type":"Point"}
}