{
  "type": "Feature",
  "properties": {
    "iso:country":"US",
    "sg:address":"1833 Camden Ave",
    "sg:city":"Durham",
    "sg:classifiers":[
        {
            "category":"Government",
            "subcategory":"Office",
            "type":"Public Place"
        }
    ],
    "sg:phone":"+1 919 560 4185",
    "sg:postcode":"27704",
    "sg:province":"NC",
    "sg:tags":[
        "city",
        "program"
    ],
    "sg:website":"www.durhamnc.gov",
    "wof:name":"Durham Dept Solid Waste Mgmt",
    "wof:placetype":"venue"
},
  "geometry": {"coordinates":[-78.86147099999999,36.023885],"type":"Point"}
}