{
  "type": "Feature",
  "properties": {
    "iso:country":"US",
    "sg:address":"804 Fedelon Trl",
    "sg:city":"Goldsboro",
    "sg:classifiers":[
        {
            "category":"Shopping",
            "type":"Retail Goods"
        }
    ],
    "sg:phone":"+1 919 736 2888",
    "sg:postcode":"27530",
    "sg:province":"NC",
    "sg:tags":[
        "equipment",
        "telephone",
        "supply"
    ],
    "wof:name":"Tel-COM USA Inc",
    "wof:placetype":"venue"
},
  "geometry": {"coordinates":[-77.98868299999999,35.414349],"type":"Point"}
}