{
  "type": "Feature",
  "properties": {
    "iso:country":"US",
    "sg:address":"79 Cortez Morrison Rd",
    "sg:city":"Lillington",
    "sg:classifiers":[
        {
            "category":"Home & Garden",
            "subcategory":"Mobile Homes",
            "type":"Retail Goods"
        }
    ],
    "sg:phone":"+1 910 814 2600",
    "sg:postcode":"27546",
    "sg:province":"NC",
    "wof:name":"J & R Mobile Home Sales",
    "wof:placetype":"venue"
},
  "geometry": {"coordinates":[-78.95678100000001,35.424966],"type":"Point"}
}