{
  "type": "Feature",
  "properties": {
    "addr:full":"206 Cooper St Statesville NC 28677",
    "addr:housenumber":"206",
    "addr:postcode":"28677",
    "addr:street":"Cooper St",
    "iso:country":"US",
    "sg:address":"206 Cooper St",
    "sg:city":"Statesville",
    "sg:classifiers":[
        {
            "category":"Health Services",
            "subcategory":"Health Practitioner",
            "type":"Services"
        }
    ],
    "sg:phone":"+1   ",
    "sg:postcode":"28677",
    "sg:province":"NC",
    "wof:name":"A Balanced Life LLC",
    "wof:placetype":"venue"
},
  "geometry": {"coordinates":[-80.88709,35.784296],"type":"Point"}
}