{
  "type": "Feature",
  "properties": {
    "iso:country":"US",
    "sg:address":"1721 E Broad St",
    "sg:city":"Statesville",
    "sg:classifiers":[
        {
            "category":"Banks & Credit Unions",
            "subcategory":"Bank",
            "type":"Services"
        }
    ],
    "sg:phone":"+1 704 878 9544",
    "sg:postcode":"28625",
    "sg:province":"NC",
    "sg:tags":[
        "personal",
        "financing",
        "institution"
    ],
    "wof:name":"Security Financial Services",
    "wof:placetype":"venue"
},
  "geometry": {"coordinates":[-80.86154399999999,35.791189],"type":"Point"}
}