{
  "type": "Feature",
  "properties": {
    "iso:country":"US",
    "sg:address":"7701 Six Forks Rd",
    "sg:city":"Raleigh",
    "sg:classifiers":[
        {
            "category":"Health Services",
            "subcategory":"Doctor",
            "type":"Services"
        }
    ],
    "sg:phone":"+1 919 870 6892",
    "sg:postcode":"27615",
    "sg:province":"NC",
    "sg:tags":[
        "dentist"
    ],
    "sg:website":"www.drdengler.com",
    "wof:name":"Theodore J Dengler Jr DDS",
    "wof:placetype":"venue"
},
  "geometry": {"coordinates":[-78.64679599999999,35.886711],"type":"Point"}
}