{
  "type": "Feature",
  "properties": {
    "addr:full":"2103 Peters Creek Pkwy Winston Salem NC 27127",
    "addr:housenumber":"2103",
    "addr:postcode":"27127",
    "addr:street":"Peters Creek Pkwy",
    "iso:country":"US",
    "sg:address":"2103 Peters Creek Pkwy",
    "sg:city":"Winston Salem",
    "sg:classifiers":[
        {
            "category":"Autos & Motor Vehicles",
            "subcategory":"Auto Supplies",
            "type":"Retail Goods"
        }
    ],
    "sg:phone":"+1 336 464 0073",
    "sg:postcode":"27127",
    "sg:province":"NC",
    "sg:tags":[
        "automobile",
        "parts"
    ],
    "wof:name":"NAPA Auto Parts",
    "wof:placetype":"venue"
},
  "geometry": {"coordinates":[-80.257887,36.067616],"type":"Point"}
}