{
  "type": "Feature",
  "properties": {
    "iso:country":"US",
    "sg:address":"115 S Canterbury Rd",
    "sg:city":"Charlotte",
    "sg:classifiers":[
        {
            "category":"Autos & Motor Vehicles",
            "subcategory":"Motorcycle Sales",
            "type":"Retail Goods"
        }
    ],
    "sg:phone":"+1 704 366 8672",
    "sg:postcode":"28211",
    "sg:province":"NC",
    "wof:name":"Big City Thunder Inc",
    "wof:placetype":"venue"
},
  "geometry": {"coordinates":[-80.810227,35.180634],"type":"Point"}
}