{
  "type": "Feature",
  "properties": {
    "addr:full":"6221 Round Hill Rd Charlotte NC 28211",
    "addr:housenumber":"6221",
    "addr:postcode":"28211",
    "addr:street":"Round Hill Rd",
    "iso:country":"US",
    "sg:address":"6221 Round Hill Rd",
    "sg:city":"Charlotte",
    "sg:classifiers":[
        {
            "category":"Shopping",
            "subcategory":"Jewelry",
            "type":"Retail Goods"
        }
    ],
    "sg:phone":"+1 704 364 4985",
    "sg:postcode":"28211",
    "sg:province":"NC",
    "wof:name":"Jewels B Come U",
    "wof:placetype":"venue"
},
  "geometry": {"coordinates":[-80.752387,35.150503],"type":"Point"}
}