{
  "type": "Feature",
  "properties": {
    "addr:full":"8549 Mill Branch Rd Rocky Mount NC 27803",
    "addr:housenumber":"8549",
    "addr:postcode":"27803",
    "addr:street":"Mill Branch Rd",
    "iso:country":"US",
    "sg:address":"8549 Mill Branch Rd",
    "sg:city":"Rocky Mount",
    "sg:phone":"+1 252 442 4595",
    "sg:postcode":"27803",
    "sg:province":"NC",
    "sg:tags":[
        "farm",
        "tobacco"
    ],
    "wof:name":"Pridgen Farm Inc",
    "wof:placetype":"venue"
},
  "geometry": {"coordinates":[-77.845668,35.884003],"type":"Point"}
}