{
  "type": "Feature",
  "properties": {
    "iso:country":"US",
    "sg:address":"2713 Cedar Creek Dr",
    "sg:city":"Durham",
    "sg:classifiers":[
        {
            "category":"Professional",
            "subcategory":"Business Services",
            "type":"Services"
        }
    ],
    "sg:phone":"+1   ",
    "sg:postcode":"27705",
    "sg:province":"NC",
    "wof:name":"Thompson Design Technolog",
    "wof:placetype":"venue"
},
  "geometry": {"coordinates":[-78.985243,36.040056],"type":"Point"}
}