{
  "type": "Feature",
  "properties": {
    "addr:full":"177 Queens Cove Rd Mooresville NC 28117",
    "addr:housenumber":"177",
    "addr:postcode":"28117",
    "addr:street":"Queens Cove Rd",
    "iso:country":"US",
    "sg:address":"177 Queens Cove Rd",
    "sg:city":"Mooresville",
    "sg:classifiers":[
        {
            "category":"Professional",
            "subcategory":"Computer Services",
            "type":"Services"
        }
    ],
    "sg:phone":"+1   ",
    "sg:postcode":"28117",
    "sg:province":"NC",
    "sg:tags":[
        "related"
    ],
    "wof:name":"Renich Consulting",
    "wof:placetype":"venue"
},
  "geometry": {"coordinates":[-80.875096,35.541672],"type":"Point"}
}