{
  "type": "Feature",
  "properties": {
    "addr:full":"6915 Lakeside Dr Charlotte NC 28215",
    "addr:housenumber":"6915",
    "addr:postcode":"28215",
    "addr:street":"Lakeside Dr",
    "iso:country":"US",
    "sg:address":"6915 Lakeside Dr",
    "sg:city":"Charlotte",
    "sg:classifiers":[
        {
            "category":"Home & Garden",
            "subcategory":"Building Materials",
            "type":"Retail Goods"
        }
    ],
    "sg:phone":"+1 704 568 2334",
    "sg:postcode":"28215",
    "sg:province":"NC",
    "sg:tags":[
        "glass",
        "window",
        "plate"
    ],
    "wof:name":"Auto Glass Svc",
    "wof:placetype":"venue"
},
  "geometry": {"coordinates":[-80.72600300000001,35.236767],"type":"Point"}
}