{
  "type": "Feature",
  "properties": {
    "iso:country":"US",
    "sg:address":"1285 Progressive Church Rd",
    "sg:city":"Princeton",
    "sg:classifiers":[
        {
            "category":"Organizations",
            "subcategory":"Religious Organization",
            "type":"Services"
        }
    ],
    "sg:phone":"+1 919 936 4781",
    "sg:postcode":"27569",
    "sg:province":"NC",
    "sg:tags":[
        "church"
    ],
    "wof:name":"Holt's Pond Ch-God Prophecy",
    "wof:placetype":"venue"
},
  "geometry": {"coordinates":[-78.186487,35.46119],"type":"Point"}
}