{
  "type": "Feature",
  "properties": {
    "addr:full":"7740 Virginia Dare Trl Nags Head NC 27959",
    "addr:housenumber":"7740",
    "addr:postcode":"27959",
    "addr:street":"Virginia Dare Trl",
    "iso:country":"US",
    "sg:address":"7740 Virginia Dare Trl",
    "sg:city":"Nags Head",
    "sg:classifiers":[
        {
            "category":"Travel",
            "subcategory":"Hotels & Motels",
            "type":"Entertainment"
        }
    ],
    "sg:phone":"+1 252 441 5353",
    "sg:postcode":"27959",
    "sg:province":"NC",
    "sg:website":"www.finnfeather.com",
    "wof:name":"Orson Hill Inc",
    "wof:placetype":"venue"
},
  "geometry": {"coordinates":[-75.617113,35.897799],"type":"Point"}
}