{
  "type": "Feature",
  "properties": {
    "addr:full":"5112 US Hwy 1 Vass NC 28394",
    "addr:housenumber":"5112",
    "addr:postcode":"28394",
    "addr:street":"Us Hwy 1",
    "iso:country":"US",
    "sg:address":"5112 US Hwy 1",
    "sg:city":"Vass",
    "sg:classifiers":[
        {
            "category":"Organizations",
            "subcategory":"Religious Organization",
            "type":"Services"
        }
    ],
    "sg:phone":"+1 910 692 9071",
    "sg:postcode":"28394",
    "sg:province":"NC",
    "sg:tags":[
        "church"
    ],
    "wof:name":"Covenant Christian Church",
    "wof:placetype":"venue"
},
  "geometry": {"coordinates":[-79.322058,35.22479],"type":"Point"}
}