{
  "type": "Feature",
  "properties": {
    "iso:country":"US",
    "sg:address":"3772 W Dixon Blvd",
    "sg:city":"Shelby",
    "sg:classifiers":[
        {
            "category":"Shopping",
            "subcategory":"Tobacco",
            "type":"Retail Goods"
        }
    ],
    "sg:phone":"+1 704 434 8653",
    "sg:postcode":"28152",
    "sg:province":"NC",
    "sg:tags":[
        "tobacconist"
    ],
    "wof:name":"Smokers Edge",
    "wof:placetype":"venue"
},
  "geometry": {"coordinates":[-81.63996400000001,35.291823],"type":"Point"}
}