{
  "type": "Feature",
  "properties": {
    "addr:full":"800 Salem Woods Dr Raleigh NC 27615",
    "addr:housenumber":"800",
    "addr:postcode":"27615",
    "addr:street":"Salem Woods Dr",
    "iso:country":"US",
    "sg:address":"800 Salem Woods Dr",
    "sg:city":"Raleigh",
    "sg:classifiers":[
        {
            "category":"Real Estate",
            "subcategory":"Real Estate Agent",
            "type":"Services"
        },
        {
            "category":"Professional",
            "subcategory":"Business Services",
            "type":"Services"
        }
    ],
    "sg:phone":"+1 919 571 2511",
    "sg:postcode":"27615",
    "sg:province":"NC",
    "sg:tags":[
        "inspection"
    ],
    "wof:name":"Home Check Systems",
    "wof:placetype":"venue"
},
  "geometry": {"coordinates":[-78.62407899999999,35.889365],"type":"Point"}
}