{
  "type": "Feature",
  "properties": {
    "addr:full":"1959 New Hope Rd Hertford NC 27944",
    "addr:housenumber":"1959",
    "addr:postcode":"27944",
    "addr:street":"New Hope Rd",
    "iso:country":"US",
    "sg:address":"1959 New Hope Rd",
    "sg:city":"Hertford",
    "sg:classifiers":[
        {
            "category":"Professional",
            "subcategory":"Business Services",
            "type":"Services"
        }
    ],
    "sg:phone":"+1 252 264 4220",
    "sg:postcode":"27944",
    "sg:province":"NC",
    "sg:tags":[
        "interior",
        "consultant",
        "design",
        "decorator"
    ],
    "wof:name":"Customs Interior & Exterior",
    "wof:placetype":"venue"
},
  "geometry": {"coordinates":[-76.32684999999999,36.16139],"type":"Point"}
}