{
  "type": "Feature",
  "properties": {
    "addr:full":"750 E Chatham St Cary NC 27511",
    "addr:housenumber":"750",
    "addr:postcode":"27511",
    "addr:street":"E Chatham St",
    "iso:country":"US",
    "sg:address":"750 E Chatham St",
    "sg:city":"Cary",
    "sg:classifiers":[
        {
            "category":"Shopping",
            "subcategory":"Clothing, Apparel, & Fashions",
            "type":"Retail Goods"
        }
    ],
    "sg:phone":"+1 919 460 0220",
    "sg:postcode":"27511",
    "sg:province":"NC",
    "sg:tags":[
        "accessory",
        "clothing",
        "women's"
    ],
    "wof:name":"Suwan Womens Clothing and Alteration",
    "wof:placetype":"venue"
},
  "geometry": {"coordinates":[-78.76509900000001,35.791801],"type":"Point"}
}