{
  "type": "Feature",
  "properties": {
    "addr:full":"557 Old Cheraw Hwy Rockingham NC 28379",
    "addr:housenumber":"557",
    "addr:postcode":"28379",
    "addr:street":"Old Cheraw Hwy",
    "iso:country":"US",
    "sg:address":"557 Old Cheraw Hwy",
    "sg:city":"Rockingham",
    "sg:classifiers":[
        {
            "category":"Personal",
            "subcategory":"Tanning Parlor",
            "type":"Services"
        }
    ],
    "sg:phone":"+1 910 895 7206",
    "sg:postcode":"28379",
    "sg:province":"NC",
    "sg:tags":[
        "salon"
    ],
    "wof:name":"Meadowood Tanning & Treats",
    "wof:placetype":"venue"
},
  "geometry": {"coordinates":[-79.796449,34.91387],"type":"Point"}
}