{
  "type": "Feature",
  "properties": {
    "addr:full":"2076 Thad Carey Rd Oxford NC 27565",
    "addr:housenumber":"2076",
    "addr:postcode":"27565",
    "addr:street":"Thad Carey Rd",
    "iso:country":"US",
    "sg:address":"2076 Thad Carey Rd",
    "sg:city":"Oxford",
    "sg:classifiers":[
        {
            "category":"Building & Trades",
            "subcategory":"Construction",
            "type":"Services"
        }
    ],
    "sg:phone":"+1 919 690 8845",
    "sg:postcode":"27565",
    "sg:province":"NC",
    "sg:tags":[
        "hanging",
        "contractor"
    ],
    "wof:name":"David L Harris",
    "wof:placetype":"venue"
},
  "geometry": {"coordinates":[-78.68231900000001,36.239332],"type":"Point"}
}