{
  "type": "Feature",
  "properties": {
    "addr:full":"5079 Fayetteville Rd Lumberton NC 28358",
    "addr:housenumber":"5079",
    "addr:postcode":"28358",
    "addr:street":"Fayetteville Rd",
    "iso:country":"US",
    "sg:address":"5079 Fayetteville Rd",
    "sg:city":"Lumberton",
    "sg:classifiers":[
        {
            "category":"Shopping",
            "subcategory":"Computers & Home Electronics",
            "type":"Retail Goods"
        }
    ],
    "sg:phone":"+1 910 739 3013",
    "sg:postcode":"28358",
    "sg:province":"NC",
    "sg:tags":[
        "equipment",
        "electronic",
        "supply"
    ],
    "wof:name":"Radio Shack",
    "wof:placetype":"venue"
},
  "geometry": {"coordinates":[-79.00095899999999,34.664986],"type":"Point"}
}