{
  "type": "Feature",
  "properties": {
    "addr:full":"410 Old US Hwy 70 Swannanoa NC 28778",
    "addr:housenumber":"410",
    "addr:postcode":"28778",
    "addr:street":"Old Us Hwy 70",
    "iso:country":"US",
    "sg:address":"410 Old US Hwy 70",
    "sg:city":"Swannanoa",
    "sg:classifiers":[
        {
            "category":"Personal",
            "subcategory":"Barber",
            "type":"Services"
        }
    ],
    "sg:phone":"+1 828 686 7002",
    "sg:postcode":"28778",
    "sg:province":"NC",
    "wof:name":"Village Barber & Style Shop",
    "wof:placetype":"venue"
},
  "geometry": {"coordinates":[-82.39528199999999,35.603674],"type":"Point"}
}