{
  "type": "Feature",
  "properties": {
    "iso:country":"US",
    "sg:address":"5266 Cokesbury Rd",
    "sg:city":"Fuquay Varina",
    "sg:classifiers":[
        {
            "category":"Retail",
            "subcategory":"Auto Repair",
            "type":"Services"
        }
    ],
    "sg:phone":"+1   ",
    "sg:postcode":"27526",
    "sg:province":"NC",
    "sg:tags":[
        "automotive"
    ],
    "wof:name":"Jacks Repair Service",
    "wof:placetype":"venue"
},
  "geometry": {"coordinates":[-78.893989,35.54532],"type":"Point"}
}