{
  "type": "Feature",
  "properties": {
    "iso:country":"US",
    "sg:address":"324 Pine St",
    "sg:city":"Forest City",
    "sg:classifiers":[
        {
            "category":"Wholesale",
            "subcategory":"Metals & Minerals",
            "type":"Manufacturing & Wholesale Goods"
        }
    ],
    "sg:phone":"+1 828 245 5717",
    "sg:postcode":"28043",
    "sg:province":"NC",
    "sg:tags":[
        "center"
    ],
    "wof:name":"Atlantic Pipe & Steel Inc",
    "wof:placetype":"venue"
},
  "geometry": {"coordinates":[-81.85256099999999,35.313113],"type":"Point"}
}