{
  "type": "Feature",
  "properties": {
    "iso:country":"US",
    "sg:address":"2450 Coltrane Mill Rd",
    "sg:city":"Archdale",
    "sg:classifiers":[
        {
            "category":"Manufacturing",
            "subcategory":"Furniture",
            "type":"Manufacturing & Wholesale Goods"
        }
    ],
    "sg:phone":"+1 336 861 0363",
    "sg:postcode":"27263",
    "sg:province":"NC",
    "wof:name":"B-Safe Co",
    "wof:placetype":"venue"
},
  "geometry": {"coordinates":[-79.875742,35.90468],"type":"Point"}
}