{
  "type": "Feature",
  "properties": {
    "addr:full":"2817 Tobermary Ln Raleigh NC 27606",
    "addr:housenumber":"2817",
    "addr:postcode":"27606",
    "addr:street":"Tobermary Ln",
    "iso:country":"US",
    "sg:address":"2817 Tobermary Ln",
    "sg:city":"Raleigh",
    "sg:classifiers":[
        {
            "category":"Professional",
            "subcategory":"Detective & Security Services",
            "type":"Services"
        }
    ],
    "sg:phone":"+1   ",
    "sg:postcode":"27606",
    "sg:province":"NC",
    "sg:tags":[
        "car"
    ],
    "wof:name":"Fords Protective Services Inc",
    "wof:placetype":"venue"
},
  "geometry": {"coordinates":[-78.73888100000001,35.726185],"type":"Point"}
}