{
  "type": "Feature",
  "properties": {
    "iso:country":"US",
    "sg:address":"1007 College St",
    "sg:city":"Oxford",
    "sg:classifiers":[
        {
            "category":"Retail",
            "subcategory":"Laundry & Dry Cleaning",
            "type":"Services"
        }
    ],
    "sg:phone":"+1   ",
    "sg:postcode":"27565",
    "sg:province":"NC",
    "sg:tags":[
        "drycleaning",
        "plant"
    ],
    "wof:name":"Oxford Dry Cleaners & Laundry",
    "wof:placetype":"venue"
},
  "geometry": {"coordinates":[-78.595106,36.324738],"type":"Point"}
}