{
  "type": "Feature",
  "properties": {
    "addr:full":"214 E Mountain St Kernersville NC 27284",
    "addr:housenumber":"214",
    "addr:postcode":"27284",
    "addr:street":"E Mountain St",
    "iso:country":"US",
    "sg:address":"214 E Mountain St",
    "sg:city":"Kernersville",
    "sg:classifiers":[
        {
            "category":"Professional",
            "type":"Services"
        }
    ],
    "sg:phone":"+1 336 993 2281",
    "sg:postcode":"27284",
    "sg:province":"NC",
    "wof:name":"Coates Field Svc Inc",
    "wof:placetype":"venue"
},
  "geometry": {"coordinates":[-80.071259,36.119031],"type":"Point"}
}