{
  "type": "Feature",
  "properties": {
    "addr:full":"114 Kilmer Ln Reidsville NC 27320",
    "addr:housenumber":"114",
    "addr:postcode":"27320",
    "addr:street":"Kilmer Ln",
    "iso:country":"US",
    "sg:address":"114 Kilmer Ln",
    "sg:city":"Reidsville",
    "sg:classifiers":[
        {
            "category":"Professional",
            "type":"Services"
        }
    ],
    "sg:phone":"+1 336 342 6171",
    "sg:postcode":"27320",
    "sg:province":"NC",
    "wof:name":"C Bert Jones Ltd",
    "wof:placetype":"venue"
},
  "geometry": {"coordinates":[-79.704505,36.400817],"type":"Point"}
}