{
  "type": "Feature",
  "properties": {
    "iso:country":"US",
    "sg:address":"201 N Breazeale Ave",
    "sg:city":"Mount Olive",
    "sg:classifiers":[
        {
            "category":"Health Services",
            "subcategory":"Doctor",
            "type":"Services"
        }
    ],
    "sg:phone":"+1 919 658 4954",
    "sg:postcode":"28365",
    "sg:province":"NC",
    "sg:tags":[
        "medical"
    ],
    "wof:name":"Mt Olive Family Medicine Ctr",
    "wof:placetype":"venue"
},
  "geometry": {"coordinates":[-78.067956,35.199004],"type":"Point"}
}