{
  "type": "Feature",
  "properties": {
    "iso:country":"US",
    "sg:address":"2126 Portertown Rd",
    "sg:city":"Greenville",
    "sg:classifiers":[
        {
            "category":"Health Services",
            "subcategory":"Clinic",
            "type":"Services"
        }
    ],
    "sg:phone":"+1 252 355 1491",
    "sg:postcode":"27858",
    "sg:province":"NC",
    "sg:tags":[
        "specialty",
        "outpatient"
    ],
    "wof:name":"Rocking Horse Ranch Thera",
    "wof:placetype":"venue"
},
  "geometry": {"coordinates":[-77.32869100000001,35.57334],"type":"Point"}
}