{
  "type": "Feature",
  "properties": {
    "addr:full":"1724 Blandford Dr Charlotte NC 28262",
    "addr:housenumber":"1724",
    "addr:postcode":"28262",
    "addr:street":"Blandford Dr",
    "iso:country":"US",
    "sg:address":"1724 Blandford Dr",
    "sg:city":"Charlotte",
    "sg:classifiers":[
        {
            "category":"Restaurant",
            "type":"Food & Drink"
        }
    ],
    "sg:phone":"+1 704 596 6961",
    "sg:postcode":"28262",
    "sg:province":"NC",
    "wof:name":"Jimmy's Southern Cooking",
    "wof:placetype":"venue"
},
  "geometry": {"coordinates":[-80.79224499999999,35.287837],"type":"Point"}
}