{
  "type": "Feature",
  "properties": {
    "addr:full":"200 W Ash St Goldsboro NC 27530",
    "addr:housenumber":"200",
    "addr:postcode":"27530",
    "addr:street":"W Ash St",
    "iso:country":"US",
    "sg:address":"200 W Ash St",
    "sg:city":"Goldsboro",
    "sg:classifiers":[
        {
            "category":"Professional",
            "subcategory":"Advertising",
            "type":"Services"
        }
    ],
    "sg:phone":"+1 919 736 2326",
    "sg:postcode":"27530",
    "sg:province":"NC",
    "wof:name":"Jones Advertising Specialties",
    "wof:placetype":"venue"
},
  "geometry": {"coordinates":[-77.999088,35.386601],"type":"Point"}
}