{
  "type": "Feature",
  "properties": {
    "iso:country":"US",
    "sg:address":"303 Boltstone Ct",
    "sg:city":"Cary",
    "sg:classifiers":[
        {
            "category":"Professional",
            "subcategory":"Business Services",
            "type":"Services"
        }
    ],
    "sg:phone":"+1   ",
    "sg:postcode":"27513",
    "sg:province":"NC",
    "wof:name":"Riverhouse Interiors",
    "wof:placetype":"venue"
},
  "geometry": {"coordinates":[-78.846929,35.808937],"type":"Point"}
}