{
  "type": "Feature",
  "properties": {
    "iso:country":"US",
    "sg:address":"3232 Cheswick Dr",
    "sg:city":"Greensboro",
    "sg:classifiers":[
        {
            "category":"Insurance",
            "subcategory":"Insurance Agent",
            "type":"Services"
        }
    ],
    "sg:phone":"+1 336 931 1335",
    "sg:postcode":"27410",
    "sg:province":"NC",
    "wof:name":"Humana Health Insurance Agent",
    "wof:placetype":"venue"
},
  "geometry": {"coordinates":[-79.920616,36.125569],"type":"Point"}
}