{
  "type": "Feature",
  "properties": {
    "addr:full":"280 Fire Ln Clayton NC 27582",
    "addr:housenumber":"280",
    "addr:postcode":"27582",
    "addr:street":"Fire Ln",
    "iso:country":"US",
    "sg:address":"280 Fire Ln",
    "sg:city":"Clayton",
    "sg:classifiers":[
        {
            "category":"Professional",
            "subcategory":"Employment Agencies",
            "type":"Services"
        }
    ],
    "sg:phone":"+1 919 359 3080",
    "sg:postcode":"27582",
    "sg:province":"NC",
    "sg:tags":[
        "modeling"
    ],
    "wof:name":"Dream Fashion Model Agency",
    "wof:placetype":"venue"
},
  "geometry": {"coordinates":[-78.570973,36.443859],"type":"Point"}
}