{
  "type": "Feature",
  "properties": {
    "iso:country":"US",
    "sg:address":"1624 Meadow Ln",
    "sg:city":"Chapel Hill",
    "sg:classifiers":[
        {
            "category":"Professional",
            "type":"Services"
        }
    ],
    "sg:phone":"+1 919 960 6793",
    "sg:postcode":"27516",
    "sg:province":"NC",
    "sg:tags":[
        "establishment"
    ],
    "wof:name":"Padgett Station LLC",
    "wof:placetype":"venue"
},
  "geometry": {"coordinates":[-79.136486,35.944354],"type":"Point"}
}