{
  "type": "Feature",
  "properties": {
    "addr:full":"972 E Franklin Blvd Gastonia NC 28054",
    "addr:housenumber":"972",
    "addr:postcode":"28054",
    "addr:street":"E Franklin Blvd",
    "iso:country":"US",
    "sg:address":"972 E Franklin Blvd",
    "sg:city":"Gastonia",
    "sg:classifiers":[
        {
            "category":"Restaurant",
            "type":"Food & Drink"
        }
    ],
    "sg:menulink":"http://www.allmenus.com/nc/gastonia/84184-papa-johns-pizza/menu/",
    "sg:phone":"+1 704 853 0006",
    "sg:postcode":"28054",
    "sg:province":"NC",
    "sg:tags":[
        "american",
        "pizza"
    ],
    "wof:name":"Papa John's Pizza",
    "wof:placetype":"venue"
},
  "geometry": {"coordinates":[-81.167266,35.262384],"type":"Point"}
}