{
  "type": "Feature",
  "properties": {
    "iso:country":"US",
    "sg:address":"1702 E Arlington Blvd",
    "sg:city":"Greenville",
    "sg:classifiers":[
        {
            "category":"Real Estate",
            "subcategory":"Real Estate Agent",
            "type":"Services"
        }
    ],
    "sg:phone":"+1 252 321 9914",
    "sg:postcode":"27858",
    "sg:province":"NC",
    "wof:name":"Rhonda B Adams",
    "wof:placetype":"venue"
},
  "geometry": {"coordinates":[-77.356925,35.56866],"type":"Point"}
}