{
  "type": "Feature",
  "properties": {
    "iso:country":"US",
    "sg:address":"215 N Salisbury Gq Ave",
    "sg:city":"Granite Quarry",
    "sg:classifiers":[
        {
            "category":"Restaurant",
            "type":"Food & Drink"
        }
    ],
    "sg:phone":"+1 704 279 2510",
    "sg:postcode":"28072",
    "sg:province":"NC",
    "sg:tags":[
        "eating"
    ],
    "wof:name":"Jabes Deli Inc",
    "wof:placetype":"venue"
},
  "geometry": {"coordinates":[-80.447222,35.614605],"type":"Point"}
}