{
  "type": "Feature",
  "properties": {
    "addr:full":"210 E N St Newton NC 28658",
    "addr:housenumber":"210",
    "addr:postcode":"28658",
    "addr:street":"E N St",
    "iso:country":"US",
    "sg:address":"210 E N St",
    "sg:city":"Newton",
    "sg:classifiers":[
        {
            "category":"Retail",
            "subcategory":"Funeral Services",
            "type":"Services"
        }
    ],
    "sg:phone":"+1 828 464 7576",
    "sg:postcode":"28658",
    "sg:province":"NC",
    "sg:tags":[
        "director"
    ],
    "wof:name":"Clemons Funeral Home",
    "wof:placetype":"venue"
},
  "geometry": {"coordinates":[-81.21933199999999,35.646135],"type":"Point"}
}