{
  "type": "Feature",
  "properties": {
    "iso:country":"US",
    "sg:address":"3090 High Meadows Dr",
    "sg:city":"South Brunswick",
    "sg:classifiers":[
        {
            "category":"Organizations",
            "subcategory":"Religious Organization",
            "type":"Services"
        }
    ],
    "sg:phone":"+1 910 755 7171",
    "sg:postcode":"28470",
    "sg:province":"NC",
    "wof:name":"Rock Hispanic Ministries",
    "wof:placetype":"venue"
},
  "geometry": {"coordinates":[-78.35205499999999,33.947109],"type":"Point"}
}