{
  "type": "Feature",
  "properties": {
    "iso:country":"US",
    "sg:address":"8837 Stage Ford Rd",
    "sg:city":"Raleigh",
    "sg:classifiers":[
        {
            "category":"Real Estate",
            "subcategory":"Developer",
            "type":"Services"
        }
    ],
    "sg:phone":"+1 919 847 0733",
    "sg:postcode":"27615",
    "sg:province":"NC",
    "wof:name":"Haywood Co Of The Triangle",
    "wof:placetype":"venue"
},
  "geometry": {"coordinates":[-78.680014,35.91142],"type":"Point"}
}