{
  "type": "Feature",
  "properties": {
    "iso:country":"US",
    "sg:address":"2145 Foxfire Rd",
    "sg:city":"Jackson Springs",
    "sg:classifiers":[
        {
            "category":"Real Estate",
            "subcategory":"Real Estate Agent",
            "type":"Services"
        },
        {
            "category":"Professional",
            "subcategory":"Business Services",
            "type":"Services"
        }
    ],
    "sg:phone":"+1 910 295 0440",
    "sg:postcode":"27281",
    "sg:province":"NC",
    "wof:name":"Real Eastate Solutions",
    "wof:placetype":"venue"
},
  "geometry": {"coordinates":[-79.57079299999999,35.180705],"type":"Point"}
}