{
  "type": "Feature",
  "properties": {
    "iso:country":"US",
    "sg:address":"2 Weybridge Pl",
    "sg:city":"Chapel Hill",
    "sg:classifiers":[
        {
            "category":"Real Estate",
            "subcategory":"Real Estate Services",
            "type":"Services"
        }
    ],
    "sg:phone":"+1 919 489 7389",
    "sg:postcode":"27517",
    "sg:province":"NC",
    "wof:name":"Biddle Susan Rl Est",
    "wof:placetype":"venue"
},
  "geometry": {"coordinates":[-78.98840300000001,35.9086],"type":"Point"}
}