{
  "type": "Feature",
  "properties": {
    "iso:country":"US",
    "sg:address":"115 Weeping Willow Way",
    "sg:city":"Gastonia",
    "sg:classifiers":[
        {
            "category":"Manufacturing",
            "subcategory":"Aerospace",
            "type":"Manufacturing & Wholesale Goods"
        }
    ],
    "sg:phone":"+1 704 869 0752",
    "sg:postcode":"28052",
    "sg:province":"NC",
    "sg:tags":[
        "repair",
        "aircraft"
    ],
    "wof:name":"Brothers Aviation Maint Svc",
    "wof:placetype":"venue"
},
  "geometry": {"coordinates":[-81.23718,35.200555],"type":"Point"}
}