{
  "type": "Feature",
  "properties": {
    "addr:full":"1603 Frances Pl SW Lenoir NC 28645",
    "addr:housenumber":"1603",
    "addr:postcode":"28645",
    "addr:street":"Frances Pl Sw",
    "iso:country":"US",
    "sg:address":"1603 Frances Pl SW",
    "sg:city":"Lenoir",
    "sg:classifiers":[
        {
            "category":"Shopping",
            "type":"Retail Goods"
        }
    ],
    "sg:phone":"+1 828 728 9163",
    "sg:postcode":"28645",
    "sg:province":"NC",
    "sg:tags":[
        "monument"
    ],
    "wof:name":"Clark's Monument Svc",
    "wof:placetype":"venue"
},
  "geometry": {"coordinates":[-81.521739,35.887058],"type":"Point"}
}