{
  "type": "Feature",
  "properties": {
    "iso:country":"US",
    "sg:address":"2487 Charlotte Hwy",
    "sg:city":"Mooresville",
    "sg:classifiers":[
        {
            "category":"Organizations",
            "subcategory":"Religious Organization",
            "type":"Services"
        }
    ],
    "sg:phone":"+1 704 664 3540",
    "sg:postcode":"28117",
    "sg:province":"NC",
    "sg:tags":[
        "church"
    ],
    "sg:website":"www.247online.org",
    "wof:name":"River Life Fellowship",
    "wof:placetype":"venue"
},
  "geometry": {"coordinates":[-80.838604,35.598572],"type":"Point"}
}