{
  "type": "Feature",
  "properties": {
    "addr:full":"1133 Sweeten Creek Rd Asheville NC 28803",
    "addr:housenumber":"1133",
    "addr:postcode":"28803",
    "addr:street":"Sweeten Creek Rd",
    "iso:country":"US",
    "sg:address":"1133 Sweeten Creek Rd",
    "sg:city":"Asheville",
    "sg:classifiers":[
        {
            "category":"Home & Garden",
            "subcategory":"Building Materials",
            "type":"Retail Goods"
        }
    ],
    "sg:phone":"+1 828 274 6790",
    "sg:postcode":"28803",
    "sg:province":"NC",
    "sg:tags":[
        "glass",
        "window",
        "plate"
    ],
    "wof:name":"Triumph Auto Glass",
    "wof:placetype":"venue"
},
  "geometry": {"coordinates":[-82.520775,35.541151],"type":"Point"}
}