{
  "type": "Feature",
  "properties": {
    "iso:country":"US",
    "sg:address":"809 E Arrowood Rd",
    "sg:city":"Charlotte",
    "sg:classifiers":[
        {
            "category":"Personal",
            "subcategory":"Beauty Salon",
            "type":"Services"
        },
        {
            "category":"Personal",
            "subcategory":"Barber",
            "type":"Services"
        }
    ],
    "sg:phone":"+1 704 527 4557",
    "sg:postcode":"28217",
    "sg:province":"NC",
    "sg:tags":[
        "shop"
    ],
    "wof:name":"Farrer's Barber & Styling",
    "wof:placetype":"venue"
},
  "geometry": {"coordinates":[-80.878119,35.13777],"type":"Point"}
}