{
  "type": "Feature",
  "properties": {
    "iso:country":"US",
    "sg:address":"5566 Jose Rd",
    "sg:city":"Bennett",
    "sg:classifiers":[
        {
            "category":"Building & Trades",
            "subcategory":"Construction",
            "type":"Services"
        }
    ],
    "sg:phone":"+1 336 879 2035",
    "sg:postcode":"27208",
    "sg:province":"NC",
    "sg:tags":[
        "water",
        "well",
        "drilling"
    ],
    "wof:name":"Brown Billy Joe and Farrell",
    "wof:placetype":"venue"
},
  "geometry": {"coordinates":[-79.557029,35.59347],"type":"Point"}
}