{
  "type": "Feature",
  "properties": {
    "iso:country":"US",
    "sg:address":"101 Main St W",
    "sg:city":"Valdese",
    "sg:classifiers":[
        {
            "category":"Real Estate",
            "subcategory":"Real Estate Agent",
            "type":"Services"
        }
    ],
    "sg:phone":"+1 828 874 0837",
    "sg:postcode":"28690",
    "sg:province":"NC",
    "wof:name":"Hatley Realty",
    "wof:placetype":"venue"
},
  "geometry": {"coordinates":[-81.564065,35.743794],"type":"Point"}
}