{
  "type": "Feature",
  "properties": {
    "iso:country":"US",
    "sg:address":"18409 State Hwy 210",
    "sg:city":"Angier",
    "sg:phone":"+1 919 639 2700",
    "sg:postcode":"27501",
    "sg:province":"NC",
    "sg:tags":[
        "farm",
        "tobacco",
        "beef",
        "feedlot",
        "cattle"
    ],
    "wof:name":"Ronnie Fish Farm & Cnstr",
    "wof:placetype":"venue"
},
  "geometry": {"coordinates":[-78.66853500000001,35.518817],"type":"Point"}
}