{
  "type": "Feature",
  "properties": {
    "addr:full":"297 Oak Ave Spruce Pine NC 28777",
    "addr:housenumber":"297",
    "addr:postcode":"28777",
    "addr:street":"Oak Ave",
    "iso:country":"US",
    "sg:address":"297 Oak Ave",
    "sg:city":"Spruce Pine",
    "sg:classifiers":[
        {
            "category":"Shopping",
            "subcategory":"Gifts & Souvenirs",
            "type":"Retail Goods"
        }
    ],
    "sg:phone":"+1 828 766 7667",
    "sg:postcode":"28777",
    "sg:province":"NC",
    "wof:name":"Granny Marts Gifts",
    "wof:placetype":"venue"
},
  "geometry": {"coordinates":[-82.068129,35.915901],"type":"Point"}
}