{
  "type": "Feature",
  "properties": {
    "iso:country":"US",
    "sg:address":"4350 Lassiter At North Hills Ave",
    "sg:city":"Raleigh",
    "sg:classifiers":[
        {
            "category":"Restaurant",
            "type":"Food & Drink"
        }
    ],
    "sg:menulink":"http://www.allmenus.com/nc/raleigh/89625-moes-southwest-grill/menu/",
    "sg:phone":"+1 919 781 3446",
    "sg:postcode":"27609",
    "sg:province":"NC",
    "sg:tags":[
        "mexican"
    ],
    "wof:name":"Moe's Southwest Grill",
    "wof:placetype":"venue"
},
  "geometry": {"coordinates":[-78.64108299999999,35.839854],"type":"Point"}
}