{
  "type": "Feature",
  "properties": {
    "iso:country":"US",
    "sg:address":"4809 Hillsborough Rd",
    "sg:city":"Durham",
    "sg:classifiers":[
        {
            "category":"Manufacturing",
            "subcategory":"Chemicals & Compounds",
            "type":"Manufacturing & Wholesale Goods"
        },
        {
            "category":"Manufacturing",
            "subcategory":"Rubber & Plastics",
            "type":"Manufacturing & Wholesale Goods"
        }
    ],
    "sg:phone":"+1 919 383 7439",
    "sg:postcode":"27705",
    "sg:province":"NC",
    "sg:tags":[
        "pa",
        "polyethylene",
        "material",
        "prod",
        "mfg"
    ],
    "wof:name":"Southern Tape & Poly Inc",
    "wof:placetype":"venue"
},
  "geometry": {"coordinates":[-78.986155,36.032274],"type":"Point"}
}