{
  "type": "Feature",
  "properties": {
    "addr:full":"7168 Pharr Mill Rd Harrisburg NC 28075",
    "addr:housenumber":"7168",
    "addr:postcode":"28075",
    "addr:street":"Pharr Mill Rd",
    "iso:country":"US",
    "sg:address":"7168 Pharr Mill Rd",
    "sg:city":"Harrisburg",
    "sg:classifiers":[
        {
            "category":"Professional",
            "type":"Services"
        }
    ],
    "sg:phone":"+1 704 454 5029",
    "sg:postcode":"28075",
    "sg:province":"NC",
    "sg:tags":[
        "establishment"
    ],
    "wof:name":"Code Advantage Inc",
    "wof:placetype":"venue"
},
  "geometry": {"coordinates":[-80.61215199999999,35.317825],"type":"Point"}
}