{
  "type": "Feature",
  "properties": {
    "iso:country":"US",
    "sg:address":"6439 Clinton Rd",
    "sg:city":"Stedman",
    "sg:classifiers":[
        {
            "category":"Professional",
            "subcategory":"Accounting & Tax Preparation",
            "type":"Services"
        }
    ],
    "sg:phone":"+1 910 483 5696",
    "sg:postcode":"28391",
    "sg:province":"NC",
    "sg:tags":[
        "accountant"
    ],
    "wof:name":"Adam R Hall CPA",
    "wof:placetype":"venue"
},
  "geometry": {"coordinates":[-78.68779499999999,35.010984],"type":"Point"}
}