{
  "type": "Feature",
  "properties": {
    "iso:country":"US",
    "sg:address":"13812 Independence Blvd",
    "sg:city":"Indian Trail",
    "sg:classifiers":[
        {
            "category":"Restaurant",
            "type":"Food & Drink"
        }
    ],
    "sg:menulink":"http://www.allmenus.com/nc/vance/153254-bojangles/menu/",
    "sg:phone":"+1 704 346 3012",
    "sg:postcode":"28079",
    "sg:province":"NC",
    "sg:tags":[
        "chicken",
        "sandwich",
        "american"
    ],
    "wof:name":"Bojangle's",
    "wof:placetype":"venue"
},
  "geometry": {"coordinates":[-80.66034999999999,35.083516],"type":"Point"}
}