{
  "type": "Feature",
  "properties": {
    "addr:full":"112 W Lambert Dr Benson NC 27504",
    "addr:housenumber":"112",
    "addr:postcode":"27504",
    "addr:street":"W Lambert Dr",
    "iso:country":"US",
    "sg:address":"112 W Lambert Dr",
    "sg:city":"Benson",
    "sg:classifiers":[
        {
            "category":"Wholesale",
            "subcategory":"Electrical",
            "type":"Manufacturing & Wholesale Goods"
        }
    ],
    "sg:phone":"+1 919 894 8711",
    "sg:postcode":"27504",
    "sg:province":"NC",
    "sg:tags":[
        "electric",
        "motor"
    ],
    "wof:name":"Lambert's Motor Repairs",
    "wof:placetype":"venue"
},
  "geometry": {"coordinates":[-78.54868399999999,35.382334],"type":"Point"}
}