{
  "type": "Feature",
  "properties": {
    "iso:country":"US",
    "sg:address":"136 Mine Lake Ct",
    "sg:city":"Raleigh",
    "sg:classifiers":[
        {
            "category":"Wholesale",
            "subcategory":"Groceries",
            "type":"Manufacturing & Wholesale Goods"
        }
    ],
    "sg:phone":"+1 919 847 1311",
    "sg:postcode":"27615",
    "sg:province":"NC",
    "sg:tags":[
        "food",
        "chemical",
        "broker",
        "candy"
    ],
    "wof:name":"Dunn Marketing Inc",
    "wof:placetype":"venue"
},
  "geometry": {"coordinates":[-78.64393099999999,35.87598],"type":"Point"}
}