{
  "type": "Feature",
  "properties": {
    "addr:full":"1804 Sea Swept St Kill Devil Hills NC 27948",
    "addr:housenumber":"1804",
    "addr:postcode":"27948",
    "addr:street":"Sea Swept St",
    "iso:country":"US",
    "sg:address":"1804 Sea Swept St",
    "sg:city":"Kill Devil Hills",
    "sg:classifiers":[
        {
            "category":"Professional",
            "subcategory":"Business Services",
            "type":"Services"
        }
    ],
    "sg:phone":"+1   ",
    "sg:postcode":"27948",
    "sg:province":"NC",
    "wof:name":"Sign Man",
    "wof:placetype":"venue"
},
  "geometry": {"coordinates":[-75.681404,36.030914],"type":"Point"}
}