{
  "type": "Feature",
  "properties": {
    "addr:full":"263 Howard Blvd Newport NC 28570",
    "addr:housenumber":"263",
    "addr:postcode":"28570",
    "addr:street":"Howard Blvd",
    "iso:country":"US",
    "sg:address":"263 Howard Blvd",
    "sg:city":"Newport",
    "sg:classifiers":[
        {
            "category":"Shopping",
            "subcategory":"Florist",
            "type":"Retail Goods"
        }
    ],
    "sg:phone":"+1 252 223 5911",
    "sg:postcode":"28570",
    "sg:province":"NC",
    "wof:name":"Newport Florist",
    "wof:placetype":"venue"
},
  "geometry": {"coordinates":[-76.867088,34.788023],"type":"Point"}
}