{
  "type": "Feature",
  "properties": {
    "addr:full":"4737 Sunrise Beach Rd Catawba NC 28609",
    "addr:housenumber":"4737",
    "addr:postcode":"28609",
    "addr:street":"Sunrise Beach Rd",
    "iso:country":"US",
    "sg:address":"4737 Sunrise Beach Rd",
    "sg:city":"Catawba",
    "sg:classifiers":[
        {
            "category":"Manufacturing",
            "subcategory":"Textiles",
            "type":"Manufacturing & Wholesale Goods"
        }
    ],
    "sg:phone":"+1 828 241 3647",
    "sg:postcode":"28609",
    "sg:province":"NC",
    "sg:tags":[
        "mfg"
    ],
    "wof:name":"Quilting Designs Inc",
    "wof:placetype":"venue"
},
  "geometry": {"coordinates":[-81.095332,35.761246],"type":"Point"}
}