{
  "type": "Feature",
  "properties": {
    "addr:full":"2367 Collinstown Rd Westfield NC 27053",
    "addr:housenumber":"2367",
    "addr:postcode":"27053",
    "addr:street":"Collinstown Rd",
    "iso:country":"US",
    "sg:address":"2367 Collinstown Rd",
    "sg:city":"Westfield",
    "sg:classifiers":[
        {
            "category":"Retail",
            "subcategory":"Auto Repair",
            "type":"Services"
        }
    ],
    "sg:phone":"+1   ",
    "sg:postcode":"27053",
    "sg:province":"NC",
    "sg:tags":[
        "general"
    ],
    "wof:name":"Beasley Garage",
    "wof:placetype":"venue"
},
  "geometry": {"coordinates":[-80.350652,36.537662],"type":"Point"}
}