{
  "type": "Feature",
  "properties": {
    "addr:full":"4105 Southall Rd Raleigh NC 27604",
    "addr:housenumber":"4105",
    "addr:postcode":"27604",
    "addr:street":"Southall Rd",
    "iso:country":"US",
    "sg:address":"4105 Southall Rd",
    "sg:city":"Raleigh",
    "sg:classifiers":[
        {
            "category":"Professional",
            "type":"Services"
        }
    ],
    "sg:phone":"+1 919 876 7786",
    "sg:postcode":"27604",
    "sg:province":"NC",
    "wof:name":"Charlie McGee",
    "wof:placetype":"venue"
},
  "geometry": {"coordinates":[-78.555561,35.828889],"type":"Point"}
}