{
  "type": "Feature",
  "properties": {
    "iso:country":"US",
    "sg:address":"1485 Rymco Dr",
    "sg:city":"Winston Salem",
    "sg:classifiers":[
        {
            "category":"Professional",
            "subcategory":"Accounting & Tax Preparation",
            "type":"Services"
        }
    ],
    "sg:phone":"+1 336 774 1400",
    "sg:postcode":"27103",
    "sg:province":"NC",
    "sg:tags":[
        "accountant"
    ],
    "wof:name":"Justice Thore & Co",
    "wof:placetype":"venue"
},
  "geometry": {"coordinates":[-80.31316700000001,36.073994],"type":"Point"}
}