{
  "type": "Feature",
  "properties": {
    "addr:full":"9639 Center Rd Bladenboro NC 28320",
    "addr:housenumber":"9639",
    "addr:postcode":"28320",
    "addr:street":"Center Rd",
    "iso:country":"US",
    "sg:address":"9639 Center Rd",
    "sg:city":"Bladenboro",
    "sg:classifiers":[
        {
            "category":"Retail",
            "subcategory":"Auto Repair",
            "type":"Services"
        }
    ],
    "sg:phone":"+1   ",
    "sg:postcode":"28320",
    "sg:province":"NC",
    "sg:tags":[
        "automotive"
    ],
    "wof:name":"R & R Body Shop & Wrecker Svc",
    "wof:placetype":"venue"
},
  "geometry": {"coordinates":[-78.819586,34.5742],"type":"Point"}
}