{
  "type": "Feature",
  "properties": {
    "addr:full":"233 W 5th St Winston Salem NC 27101",
    "addr:housenumber":"233",
    "addr:postcode":"27101",
    "addr:street":"W 5Th St",
    "iso:country":"US",
    "sg:address":"233 W 5th St",
    "sg:city":"Winston Salem",
    "sg:classifiers":[
        {
            "category":"Shopping",
            "subcategory":"Clothing, Apparel, & Fashions",
            "type":"Retail Goods"
        }
    ],
    "sg:phone":"+1 336 722 3962",
    "sg:postcode":"27101",
    "sg:province":"NC",
    "wof:name":"Lefkowitz Tailor Shop",
    "wof:placetype":"venue"
},
  "geometry": {"coordinates":[-80.246956,36.099794],"type":"Point"}
}