{
  "type": "Feature",
  "properties": {
    "iso:country":"US",
    "sg:address":"3115 Wrightsville Ave",
    "sg:city":"Wilmington",
    "sg:classifiers":[
        {
            "category":"Professional",
            "subcategory":"Advertising",
            "type":"Services"
        }
    ],
    "sg:phone":"+1 910 763 2263",
    "sg:postcode":"28403",
    "sg:province":"NC",
    "sg:tags":[
        "counselor"
    ],
    "wof:name":"Atlantic Advertising & Product",
    "wof:placetype":"venue"
},
  "geometry": {"coordinates":[-77.903942,34.22482],"type":"Point"}
}