{
  "type": "Feature",
  "properties": {
    "addr:full":"1559 Olive Branch Rd Roxboro NC 27574",
    "addr:housenumber":"1559",
    "addr:postcode":"27574",
    "addr:street":"Olive Branch Rd",
    "iso:country":"US",
    "sg:address":"1559 Olive Branch Rd",
    "sg:city":"Roxboro",
    "sg:classifiers":[
        {
            "category":"Organizations",
            "subcategory":"Religious Organization",
            "type":"Services"
        }
    ],
    "sg:phone":"+1   ",
    "sg:postcode":"27574",
    "sg:province":"NC",
    "wof:name":"New Hope Praise Center",
    "wof:placetype":"venue"
},
  "geometry": {"coordinates":[-78.90094499999999,36.493943],"type":"Point"}
}