{
  "type": "Feature",
  "properties": {
    "iso:country":"US",
    "sg:address":"1152 Executive Cir",
    "sg:city":"Cary",
    "sg:classifiers":[
        {
            "category":"Professional",
            "subcategory":"Engineering",
            "type":"Services"
        }
    ],
    "sg:phone":"+1 919 463 5488",
    "sg:postcode":"27511",
    "sg:province":"NC",
    "sg:tags":[
        "engineer"
    ],
    "sg:website":"www.buckengineering.com",
    "wof:name":"Buck Engineering",
    "wof:placetype":"venue"
},
  "geometry": {"coordinates":[-78.781459,35.765378],"type":"Point"}
}