{
  "type": "Feature",
  "properties": {
    "addr:full":"801 Moton Dr Greensboro NC 27401",
    "addr:housenumber":"801",
    "addr:postcode":"27401",
    "addr:street":"Moton Dr",
    "iso:country":"US",
    "sg:address":"801 Moton Dr",
    "sg:city":"Greensboro",
    "sg:classifiers":[
        {
            "category":"Real Estate",
            "subcategory":"Real Estate Agent",
            "type":"Services"
        }
    ],
    "sg:phone":"+1 336 370 9067",
    "sg:postcode":"27401",
    "sg:province":"NC",
    "sg:tags":[
        "authorities",
        "housing"
    ],
    "wof:name":"Greensboro Housing Auth",
    "wof:placetype":"venue"
},
  "geometry": {"coordinates":[-79.76399000000001,36.066529],"type":"Point"}
}