{
  "type": "Feature",
  "properties": {
    "iso:country":"US",
    "sg:address":"4080 N Center St",
    "sg:city":"Hickory",
    "sg:classifiers":[
        {
            "category":"Organizations",
            "subcategory":"Religious Organization",
            "type":"Services"
        }
    ],
    "sg:phone":"+1 828 324 8085",
    "sg:postcode":"28601",
    "sg:province":"NC",
    "sg:website":"www.lakeviewbaptistchurch.net",
    "wof:name":"Lakeview Baptist Church",
    "wof:placetype":"venue"
},
  "geometry": {"coordinates":[-81.31725900000001,35.786654],"type":"Point"}
}