{
  "type": "Feature",
  "properties": {
    "addr:full":"4392 Wallburg-High Point Rd High Point NC 27265",
    "addr:housenumber":"4392",
    "addr:postcode":"27265",
    "addr:street":"Wallburg-High Point Rd",
    "iso:country":"US",
    "sg:address":"4392 Wallburg-High Point Rd",
    "sg:city":"High Point",
    "sg:classifiers":[
        {
            "category":"Building & Trades",
            "subcategory":"Electrical",
            "type":"Services"
        }
    ],
    "sg:phone":"+1 336 869 3714",
    "sg:postcode":"27265",
    "sg:province":"NC",
    "sg:tags":[
        "electrical",
        "contractor"
    ],
    "wof:name":"McDaniel Electric Co Inc",
    "wof:placetype":"venue"
},
  "geometry": {"coordinates":[-80.066226,35.9847],"type":"Point"}
}