{
  "type": "Feature",
  "properties": {
    "iso:country":"US",
    "sg:address":"1918 Wake Forest Rd",
    "sg:city":"Raleigh",
    "sg:classifiers":[
        {
            "category":"Utilities",
            "subcategory":"Telephone",
            "type":"Services"
        }
    ],
    "sg:phone":"+1 919 341 2200",
    "sg:postcode":"27608",
    "sg:province":"NC",
    "sg:tags":[
        "company"
    ],
    "sg:website":"www.telcove.com",
    "wof:name":"Tel Cove",
    "wof:placetype":"venue"
},
  "geometry": {"coordinates":[-78.62493000000001,35.805054],"type":"Point"}
}