{
  "type": "Feature",
  "properties": {
    "iso:country":"US",
    "sg:address":"5821 Fairview Rd",
    "sg:city":"Charlotte",
    "sg:classifiers":[
        {
            "category":"Insurance",
            "subcategory":"Insurance Agent",
            "type":"Services"
        }
    ],
    "sg:phone":"+1 704 554 7750",
    "sg:postcode":"28209",
    "sg:province":"NC",
    "wof:name":"Living Benefits Corp",
    "wof:placetype":"venue"
},
  "geometry": {"coordinates":[-80.841959,35.151747],"type":"Point"}
}