{
  "type": "Feature",
  "properties": {
    "addr:full":"503 Martin Luther King Jr Dr Thomasville NC 27360",
    "addr:housenumber":"503",
    "addr:postcode":"27360",
    "addr:street":"Martin Luther King Jr Dr",
    "iso:country":"US",
    "sg:address":"503 Martin Luther King Jr Dr",
    "sg:city":"Thomasville",
    "sg:classifiers":[
        {
            "category":"Shopping",
            "subcategory":"Clothing, Apparel, & Fashions",
            "type":"Retail Goods"
        }
    ],
    "sg:phone":"+1 336 472 1487",
    "sg:postcode":"27360",
    "sg:province":"NC",
    "wof:name":"Sonya's Boutique & Salon",
    "wof:placetype":"venue"
},
  "geometry": {"coordinates":[-80.100122,35.88545],"type":"Point"}
}