{
  "type": "Feature",
  "properties": {
    "iso:country":"US",
    "sg:address":"1100 S Clinton Ave",
    "sg:city":"Dunn",
    "sg:classifiers":[
        {
            "category":"Health Services",
            "subcategory":"Clinic",
            "type":"Services"
        }
    ],
    "sg:phone":"+1 910 897 4794",
    "sg:postcode":"28334",
    "sg:province":"NC",
    "sg:tags":[
        "home"
    ],
    "wof:name":"Basic Home Health Care",
    "wof:placetype":"venue"
},
  "geometry": {"coordinates":[-78.61519199999999,35.299092],"type":"Point"}
}