{
  "type": "Feature",
  "properties": {
    "iso:country":"US",
    "sg:address":"520 Log Barn Acres",
    "sg:city":"Pittsboro",
    "sg:classifiers":[
        {
            "category":"Building & Trades",
            "subcategory":"Construction",
            "type":"Services"
        }
    ],
    "sg:phone":"+1 919 545 9117",
    "sg:postcode":"27312",
    "sg:province":"NC",
    "sg:tags":[
        "house"
    ],
    "wof:name":"Prometheus Construction LLC",
    "wof:placetype":"venue"
},
  "geometry": {"coordinates":[-79.18919,35.699016],"type":"Point"}
}