{
  "type": "Feature",
  "properties": {
    "addr:full":"261 Griffith St Davidson NC 28036",
    "addr:housenumber":"261",
    "addr:postcode":"28036",
    "addr:street":"Griffith St",
    "iso:country":"US",
    "sg:address":"261 Griffith St",
    "sg:city":"Davidson",
    "sg:classifiers":[
        {
            "category":"Food & Beverages",
            "subcategory":"Groceries & Convenience Stores",
            "type":"Retail Goods"
        }
    ],
    "sg:phone":"+1 704 892 6191",
    "sg:postcode":"28036",
    "sg:province":"NC",
    "sg:tags":[
        "grocer"
    ],
    "sg:website":"www.homeeconomistmarket.com",
    "wof:name":"Home Economist Market",
    "wof:placetype":"venue"
},
  "geometry": {"coordinates":[-80.84964100000001,35.502472],"type":"Point"}
}