{
  "type": "Feature",
  "properties": {
    "iso:country":"US",
    "sg:address":"1209 Cape Ct",
    "sg:city":"Fayetteville",
    "sg:classifiers":[
        {
            "category":"Health Services",
            "subcategory":"Doctor",
            "type":"Services"
        }
    ],
    "sg:phone":"+1 910 485 7003",
    "sg:postcode":"28304",
    "sg:province":"NC",
    "sg:tags":[
        "medical"
    ],
    "wof:name":"Trinity Hematology & Oncology",
    "wof:placetype":"venue"
},
  "geometry": {"coordinates":[-78.935862,35.037276],"type":"Point"}
}