{
  "type": "Feature",
  "properties": {
    "iso:country":"US",
    "sg:address":"218 Wesley Heights Way",
    "sg:city":"Charlotte",
    "sg:classifiers":[
        {
            "category":"Retail",
            "subcategory":"Funeral Services",
            "type":"Services"
        }
    ],
    "sg:phone":"+1 704 910 2600",
    "sg:postcode":"28208",
    "sg:province":"NC",
    "sg:tags":[
        "director"
    ],
    "wof:name":"Wesley Heights Mortuary Service",
    "wof:placetype":"venue"
},
  "geometry": {"coordinates":[-80.860421,35.236988],"type":"Point"}
}