{
  "type": "Feature",
  "properties": {
    "iso:country":"US",
    "sg:address":"6 Maybury Ct",
    "sg:city":"Arden",
    "sg:classifiers":[
        {
            "category":"Retail",
            "subcategory":"Animal Services",
            "type":"Services"
        }
    ],
    "sg:phone":"+1 828 684 3620",
    "sg:postcode":"28704",
    "sg:province":"NC",
    "sg:tags":[
        "pet",
        "boarding",
        "sitting"
    ],
    "wof:name":"Pets' Best Friend",
    "wof:placetype":"venue"
},
  "geometry": {"coordinates":[-82.500401,35.478236],"type":"Point"}
}