{
  "type": "Feature",
  "properties": {
    "addr:full":"2143 Asheville Rd Waynesville NC 28786",
    "addr:housenumber":"2143",
    "addr:postcode":"28786",
    "addr:street":"Asheville Rd",
    "iso:country":"US",
    "sg:address":"2143 Asheville Rd",
    "sg:city":"Waynesville",
    "sg:classifiers":[
        {
            "category":"Social Services",
            "type":"Services"
        }
    ],
    "sg:phone":"+1 828 452 2005",
    "sg:postcode":"28786",
    "sg:province":"NC",
    "sg:tags":[
        "organization",
        "welfare"
    ],
    "wof:name":"United Way",
    "wof:placetype":"venue"
},
  "geometry": {"coordinates":[-82.965034,35.506113],"type":"Point"}
}