{
  "type": "Feature",
  "properties": {
    "iso:country":"US",
    "sg:address":"7310 US Hwy 158",
    "sg:city":"Leasburg",
    "sg:classifiers":[
        {
            "category":"Food & Beverages",
            "subcategory":"Groceries & Convenience Stores",
            "type":"Retail Goods"
        }
    ],
    "sg:phone":"+1 336 599 3031",
    "sg:postcode":"27291",
    "sg:province":"NC",
    "sg:tags":[
        "grocer"
    ],
    "wof:name":"Leasburg Grocery",
    "wof:placetype":"venue"
},
  "geometry": {"coordinates":[-79.116097,36.386284],"type":"Point"}
}