{
  "type": "Feature",
  "properties": {
    "addr:full":"233 S Churton St Hillsborough NC 27278",
    "addr:housenumber":"233",
    "addr:postcode":"27278",
    "addr:street":"S Churton St",
    "iso:country":"US",
    "sg:address":"233 S Churton St",
    "sg:city":"Hillsborough",
    "sg:classifiers":[
        {
            "category":"Autos & Motor Vehicles",
            "subcategory":"Automobile Sales",
            "type":"Retail Goods"
        }
    ],
    "sg:phone":"+1 919 732 5200",
    "sg:postcode":"27278",
    "sg:province":"NC",
    "sg:tags":[
        "car",
        "dealer"
    ],
    "wof:name":"CBS Quality Cars",
    "wof:placetype":"venue"
},
  "geometry": {"coordinates":[-79.099391,36.070177],"type":"Point"}
}