{
  "type": "Feature",
  "properties": {
    "addr:full":"33 Old Sweetwater Rd Robbinsville NC 28771",
    "addr:housenumber":"33",
    "addr:postcode":"28771",
    "addr:street":"Old Sweetwater Rd",
    "iso:country":"US",
    "sg:address":"33 Old Sweetwater Rd",
    "sg:city":"Robbinsville",
    "sg:classifiers":[
        {
            "category":"Autos & Motor Vehicles",
            "subcategory":"Auto Supplies",
            "type":"Retail Goods"
        }
    ],
    "sg:phone":"+1 828 479 8494",
    "sg:postcode":"28771",
    "sg:province":"NC",
    "sg:tags":[
        "automobile",
        "parts"
    ],
    "wof:name":"Fords Auto Parts",
    "wof:placetype":"venue"
},
  "geometry": {"coordinates":[-83.79100099999999,35.32327],"type":"Point"}
}