{
  "type": "Feature",
  "properties": {
    "addr:full":"300 Saint Marys St Raleigh NC 27605",
    "addr:housenumber":"300",
    "addr:postcode":"27605",
    "addr:street":"Saint Marys St",
    "iso:country":"US",
    "sg:address":"300 Saint Marys St",
    "sg:city":"Raleigh",
    "sg:classifiers":[
        {
            "category":"Retail",
            "subcategory":"Funeral Services",
            "type":"Services"
        }
    ],
    "sg:phone":"+1 919 828 4311",
    "sg:postcode":"27605",
    "sg:province":"NC",
    "sg:tags":[
        "director",
        "plans-pre-arranged"
    ],
    "sg:website":"http://www.dignitymemorial.com",
    "wof:name":"Brown-Wynne Funeral Home",
    "wof:placetype":"venue"
},
  "geometry": {"coordinates":[-78.65070299999999,35.784294],"type":"Point"}
}