{
  "type": "Feature",
  "properties": {
    "iso:country":"US",
    "sg:address":"127 Sweetwater Dr",
    "sg:city":"Canton",
    "sg:classifiers":[
        {
            "category":"Building & Trades",
            "subcategory":"Landscaping Services",
            "type":"Services"
        }
    ],
    "sg:phone":"+1 828 648 3112",
    "sg:postcode":"28789",
    "sg:province":"NC",
    "sg:tags":[
        "lawn",
        "maintenance",
        "grounds"
    ],
    "wof:name":"Lawn Doctor Of Asheville",
    "wof:placetype":"venue"
},
  "geometry": {"coordinates":[-83.320313,35.380869],"type":"Point"}
}