{
  "type": "Feature",
  "properties": {
    "addr:full":"652 Browns Mill Rd Robbins NC 27325",
    "addr:housenumber":"652",
    "addr:postcode":"27325",
    "addr:street":"Browns Mill Rd",
    "iso:country":"US",
    "sg:address":"652 Browns Mill Rd",
    "sg:city":"Robbins",
    "sg:phone":"+1 910 464 3191",
    "sg:postcode":"27325",
    "sg:province":"NC",
    "sg:tags":[
        "farm"
    ],
    "wof:name":"Larry Robbins",
    "wof:placetype":"venue"
},
  "geometry": {"coordinates":[-79.643452,35.456267],"type":"Point"}
}