{
  "type": "Feature",
  "properties": {
    "addr:full":"347 Palamino Trl Jacksonville NC 28546",
    "addr:housenumber":"347",
    "addr:postcode":"28546",
    "addr:street":"Palamino Trl",
    "iso:country":"US",
    "sg:address":"347 Palamino Trl",
    "sg:city":"Jacksonville",
    "sg:classifiers":[
        {
            "category":"Building & Trades",
            "subcategory":"Construction",
            "type":"Services"
        }
    ],
    "sg:phone":"+1 910 353 1509",
    "sg:postcode":"28546",
    "sg:province":"NC",
    "sg:tags":[
        "hanging",
        "contractor"
    ],
    "wof:name":"New Way Painting",
    "wof:placetype":"venue"
},
  "geometry": {"coordinates":[-77.300867,34.759928],"type":"Point"}
}