{
  "type": "Feature",
  "properties": {
    "iso:country":"US",
    "sg:address":"4014 Shipyard Blvd",
    "sg:city":"Wilmington",
    "sg:classifiers":[
        {
            "category":"Social Services",
            "type":"Services"
        }
    ],
    "sg:phone":"+1 910 791 8510",
    "sg:postcode":"28403",
    "sg:province":"NC",
    "sg:tags":[
        "organization",
        "welfare"
    ],
    "wof:name":"Big Buddy A Program Of Family",
    "wof:placetype":"venue"
},
  "geometry": {"coordinates":[-77.89529,34.197959],"type":"Point"}
}