{
  "type": "Feature",
  "properties": {
    "iso:country":"US",
    "sg:address":"7700 Boeing Dr",
    "sg:city":"Greensboro",
    "sg:classifiers":[
        {
            "category":"Bars & Pubs",
            "type":"Food & Drink"
        }
    ],
    "sg:phone":"+1 336 662 0086",
    "sg:postcode":"27409",
    "sg:province":"NC",
    "sg:tags":[
        "club",
        "night"
    ],
    "wof:name":"Music City Event Ctr",
    "wof:placetype":"venue"
},
  "geometry": {"coordinates":[-79.94605199999999,36.082756],"type":"Point"}
}