{
  "type": "Feature",
  "properties": {
    "iso:country":"US",
    "sg:address":"4731 Dwight Evans Rd",
    "sg:city":"Charlotte",
    "sg:classifiers":[
        {
            "category":"Wholesale",
            "subcategory":"Apparel",
            "type":"Manufacturing & Wholesale Goods"
        }
    ],
    "sg:phone":"+1 704 529 6973",
    "sg:postcode":"28217",
    "sg:province":"NC",
    "sg:tags":[
        "flag",
        "pole",
        "pennant",
        "wholesaler",
        "retail",
        "banner"
    ],
    "wof:name":"All Star Flags of Carolinas",
    "wof:placetype":"venue"
},
  "geometry": {"coordinates":[-80.899169,35.190179],"type":"Point"}
}