{
  "type": "Feature",
  "properties": {
    "iso:country":"US",
    "sg:address":"5519 Grapevine Ct",
    "sg:city":"Greensboro",
    "sg:classifiers":[
        {
            "category":"Building & Trades",
            "subcategory":"Construction",
            "type":"Services"
        }
    ],
    "sg:phone":"+1 336 375 0605",
    "sg:postcode":"27405",
    "sg:province":"NC",
    "sg:tags":[
        "hanging",
        "contractor"
    ],
    "wof:name":"Mr Wright Himself Paint Co",
    "wof:placetype":"venue"
},
  "geometry": {"coordinates":[-79.714342,36.155135],"type":"Point"}
}