{
  "type": "Feature",
  "properties": {
    "addr:full":"11427 Olde Turnbury Ct Charlotte NC 28277",
    "addr:housenumber":"11427",
    "addr:postcode":"28277",
    "addr:street":"Olde Turnbury Ct",
    "iso:country":"US",
    "sg:address":"11427 Olde Turnbury Ct",
    "sg:city":"Charlotte",
    "sg:classifiers":[
        {
            "category":"Organizations",
            "subcategory":"Religious Organization",
            "type":"Services"
        }
    ],
    "sg:phone":"+1 704 542 0951",
    "sg:postcode":"28277",
    "sg:province":"NC",
    "sg:tags":[
        "monastery",
        "convent"
    ],
    "wof:name":"Sisters Of Mercy Of NC",
    "wof:placetype":"venue"
},
  "geometry": {"coordinates":[-80.81684799999999,35.055691],"type":"Point"}
}