{
  "type": "Feature",
  "properties": {
    "addr:full":"608 S Cumberland St Wallace NC 28466",
    "addr:housenumber":"608",
    "addr:postcode":"28466",
    "addr:street":"S Cumberland St",
    "iso:country":"US",
    "sg:address":"608 S Cumberland St",
    "sg:city":"Wallace",
    "sg:classifiers":[
        {
            "category":"Farming",
            "subcategory":"Livestock Farm",
            "type":"Manufacturing & Wholesale Goods"
        }
    ],
    "sg:phone":"+1 910 285 5565",
    "sg:postcode":"28466",
    "sg:province":"NC",
    "sg:tags":[
        "hog",
        "or",
        "feedlot"
    ],
    "wof:name":"Karen Knoll",
    "wof:placetype":"venue"
},
  "geometry": {"coordinates":[-77.997339,34.728537],"type":"Point"}
}