{
  "type": "Feature",
  "properties": {
    "addr:full":"7104 Sandy Pines Dr Youngsville NC 27596",
    "addr:housenumber":"7104",
    "addr:postcode":"27596",
    "addr:street":"Sandy Pines Dr",
    "iso:country":"US",
    "sg:address":"7104 Sandy Pines Dr",
    "sg:city":"Youngsville",
    "sg:classifiers":[
        {
            "category":"Government",
            "subcategory":"Office",
            "type":"Public Place"
        }
    ],
    "sg:phone":"+1 919 524 2005",
    "sg:postcode":"27596",
    "sg:province":"NC",
    "sg:tags":[
        "remediation",
        "response",
        "spill"
    ],
    "wof:name":"Protect Environmental Svcs LLC",
    "wof:placetype":"venue"
},
  "geometry": {"coordinates":[-78.440181,35.983699],"type":"Point"}
}