{
  "type": "Feature",
  "properties": {
    "addr:full":"1016 Earl Rd Shelby NC 28152",
    "addr:housenumber":"1016",
    "addr:postcode":"28152",
    "addr:street":"Earl Rd",
    "iso:country":"US",
    "sg:address":"1016 Earl Rd",
    "sg:city":"Shelby",
    "sg:classifiers":[
        {
            "category":"Autos & Motor Vehicles",
            "subcategory":"Auto Supplies",
            "type":"Retail Goods"
        }
    ],
    "sg:phone":"+1 704 480 0363",
    "sg:postcode":"28152",
    "sg:province":"NC",
    "sg:tags":[
        "trailer",
        "hitch"
    ],
    "wof:name":"Smith Trailer Sales",
    "wof:placetype":"venue"
},
  "geometry": {"coordinates":[-81.522835,35.269267],"type":"Point"}
}