{
  "type": "Feature",
  "properties": {
    "iso:country":"US",
    "sg:address":"2214D Wrightsville Ave",
    "sg:city":"Wilmington",
    "sg:classifiers":[
        {
            "category":"Insurance",
            "subcategory":"Hazard Insurance",
            "type":"Services"
        },
        {
            "category":"Insurance",
            "subcategory":"Insurance Agent",
            "type":"Services"
        },
        {
            "category":"Insurance",
            "subcategory":"Life Insurance",
            "type":"Services"
        },
        {
            "category":"Insurance",
            "subcategory":"Title Insurance",
            "type":"Services"
        }
    ],
    "sg:phone":"+1 910 763 1311",
    "sg:postcode":"28403",
    "sg:province":"NC",
    "sg:tags":[
        "auto",
        "homeowner"
    ],
    "sg:website":"http://www.nationwide.com/agent/Wilmington-NORTH-CAROLINA-insurance-agent/david-prince/office.html",
    "wof:name":"David C Prince - Nationwide Insurance",
    "wof:placetype":"venue"
},
  "geometry": {"coordinates":[-77.91905300000001,34.227391],"type":"Point"}
}