{
  "type": "Feature",
  "properties": {
    "iso:country":"US",
    "sg:address":"2332 N Meadows Loop",
    "sg:city":"Randleman",
    "sg:classifiers":[
        {
            "category":"Shopping",
            "subcategory":"Gifts & Souvenirs",
            "type":"Retail Goods"
        }
    ],
    "sg:phone":"+1 336 683 1309",
    "sg:postcode":"27317",
    "sg:province":"NC",
    "wof:name":"Kresges Gift Korner",
    "wof:placetype":"venue"
},
  "geometry": {"coordinates":[-79.79212099999999,35.766807],"type":"Point"}
}