{
  "type": "Feature",
  "properties": {
    "iso:country":"US",
    "sg:address":"218 N Heritage St",
    "sg:city":"Kinston",
    "sg:classifiers":[
        {
            "category":"Shopping",
            "subcategory":"Clothing, Apparel, & Fashions",
            "type":"Retail Goods"
        }
    ],
    "sg:phone":"+1 252 522 1907",
    "sg:postcode":"28501",
    "sg:province":"NC",
    "wof:name":"Blythe House",
    "wof:placetype":"venue"
},
  "geometry": {"coordinates":[-77.58289499999999,35.262285],"type":"Point"}
}