{
  "type": "Feature",
  "properties": {
    "addr:full":"5850 Potomac Dr NW Concord NC 28027",
    "addr:housenumber":"5850",
    "addr:postcode":"28027",
    "addr:street":"Potomac Dr Nw",
    "iso:country":"US",
    "sg:address":"5850 Potomac Dr NW",
    "sg:city":"Concord",
    "sg:classifiers":[
        {
            "category":"Manufacturing",
            "subcategory":"Electronics",
            "type":"Manufacturing & Wholesale Goods"
        }
    ],
    "sg:phone":"+1 704 720 9396",
    "sg:postcode":"28027",
    "sg:province":"NC",
    "sg:tags":[
        "apparatus",
        "mfg"
    ],
    "wof:name":"Alcatel Dunkermotoren",
    "wof:placetype":"venue"
},
  "geometry": {"coordinates":[-80.680792,35.395176],"type":"Point"}
}