{
  "type": "Feature",
  "properties": {
    "addr:full":"914 E Franklin Blvd Gastonia NC 28054",
    "addr:housenumber":"914",
    "addr:postcode":"28054",
    "addr:street":"E Franklin Blvd",
    "iso:country":"US",
    "sg:address":"914 E Franklin Blvd",
    "sg:city":"Gastonia",
    "sg:classifiers":[
        {
            "category":"Wholesale",
            "subcategory":"Auto Parts",
            "type":"Manufacturing & Wholesale Goods"
        }
    ],
    "sg:phone":"+1 704 867 9370",
    "sg:postcode":"28054",
    "sg:province":"NC",
    "sg:website":"www.carolinapaint.com",
    "wof:name":"Carolina Paint Inc",
    "wof:placetype":"venue"
},
  "geometry": {"coordinates":[-81.167333,35.262455],"type":"Point"}
}