{
  "type": "Feature",
  "properties": {
    "iso:country":"US",
    "sg:address":"4707 Pony Run Dr",
    "sg:city":"Fayetteville",
    "sg:classifiers":[
        {
            "category":"Health Services",
            "subcategory":"Clinic",
            "type":"Services"
        }
    ],
    "sg:phone":"+1 910 424 0500",
    "sg:postcode":"28304",
    "sg:province":"NC",
    "sg:tags":[
        "home"
    ],
    "wof:name":"JBS Health Svc",
    "wof:placetype":"venue"
},
  "geometry": {"coordinates":[-78.959125,35.012928],"type":"Point"}
}