{
  "type": "Feature",
  "properties": {
    "addr:full":"1901 Charden Rd Davidson NC 28036",
    "addr:housenumber":"1901",
    "addr:postcode":"28036",
    "addr:street":"Charden Rd",
    "iso:country":"US",
    "sg:address":"1901 Charden Rd",
    "sg:city":"Davidson",
    "sg:classifiers":[
        {
            "category":"Building & Trades",
            "subcategory":"Construction",
            "type":"Services"
        }
    ],
    "sg:phone":"+1 704 892 8663",
    "sg:postcode":"28036",
    "sg:province":"NC",
    "sg:tags":[
        "residential",
        "commercial",
        "framing",
        "contractor"
    ],
    "wof:name":"Precision Framing Inc",
    "wof:placetype":"venue"
},
  "geometry": {"coordinates":[-80.81481599999999,35.498926],"type":"Point"}
}