{
  "type": "Feature",
  "properties": {
    "addr:full":"55 Vilcom Circle Boyd Hall, Suite 110 Chapel Hill NC 27514",
    "addr:housenumber":"55",
    "addr:postcode":"27514",
    "addr:street":"Vilcom Circle Boyd Hall Suite 110",
    "iso:country":"US",
    "sg:address":"55 Vilcom Circle Boyd Hall, Suite 110",
    "sg:city":"Chapel Hill",
    "sg:classifiers":[
        {
            "category":"Health Services",
            "subcategory":"Health Practitioner",
            "type":"Services"
        },
        {
            "category":"Community Center",
            "type":"Public Place"
        }
    ],
    "sg:phone":"+1 919 929 7990",
    "sg:postcode":"27514",
    "sg:province":"NC",
    "sg:tags":[
        "acupuncture",
        "medical"
    ],
    "sg:website":"www.chapelhilldoctors.com",
    "wof:name":"Integrative Health Center of Chapel Hill",
    "wof:placetype":"venue"
},
  "geometry": {"coordinates":[-79.048081,35.964442],"type":"Point"}
}