{
  "type": "Feature",
  "properties": {
    "addr:full":"212 E Rosemary St Chapel Hill NC 27514",
    "addr:housenumber":"212",
    "addr:postcode":"27514",
    "addr:street":"E Rosemary St",
    "iso:country":"US",
    "sg:address":"212 E Rosemary St",
    "sg:city":"Chapel Hill",
    "sg:classifiers":[
        {
            "category":"Professional",
            "subcategory":"Accounting & Tax Preparation",
            "type":"Services"
        }
    ],
    "sg:phone":"+1 919 929 8444",
    "sg:postcode":"27514",
    "sg:province":"NC",
    "sg:tags":[
        "payroll"
    ],
    "wof:name":"ATA Payroll & Business Svc",
    "wof:placetype":"venue"
},
  "geometry": {"coordinates":[-79.051788,35.915704],"type":"Point"}
}