{
  "type": "Feature",
  "properties": {
    "iso:country":"US",
    "sg:address":"7565 Friendship Church Rd",
    "sg:city":"Browns Summit",
    "sg:classifiers":[
        {
            "category":"Retail",
            "subcategory":"Repair Shop",
            "type":"Services"
        }
    ],
    "sg:phone":"+1   ",
    "sg:postcode":"27214",
    "sg:province":"NC",
    "wof:name":"Worsham Castle Cycle Leather",
    "wof:placetype":"venue"
},
  "geometry": {"coordinates":[-79.65215999999999,36.219161],"type":"Point"}
}