{
  "type": "Feature",
  "properties": {
    "iso:country":"US",
    "sg:address":"2400 Old Salisbury-Concord Rd",
    "sg:city":"Concord",
    "sg:classifiers":[
        {
            "category":"Organizations",
            "subcategory":"Religious Organization",
            "type":"Services"
        }
    ],
    "sg:phone":"+1   ",
    "sg:postcode":"28025",
    "sg:province":"NC",
    "wof:name":"New Glead Reformed Untd Church",
    "wof:placetype":"venue"
},
  "geometry": {"coordinates":[-80.546977,35.44759],"type":"Point"}
}