{
  "type": "Feature",
  "properties": {
    "addr:full":"2691 Owen Dr Fayetteville NC 28306",
    "addr:housenumber":"2691",
    "addr:postcode":"28306",
    "addr:street":"Owen Dr",
    "iso:country":"US",
    "sg:address":"2691 Owen Dr",
    "sg:city":"Fayetteville",
    "sg:classifiers":[
        {
            "category":"Autos & Motor Vehicles",
            "subcategory":"Auto Supplies",
            "type":"Retail Goods"
        }
    ],
    "sg:phone":"+1 910 323 4144",
    "sg:postcode":"28306",
    "sg:province":"NC",
    "sg:tags":[
        "automotive",
        "towing",
        "tire",
        "repair"
    ],
    "wof:name":"Ernies Tire Sales and Service",
    "wof:placetype":"venue"
},
  "geometry": {"coordinates":[-78.907324,35.018131],"type":"Point"}
}