{
  "type": "Feature",
  "properties": {
    "iso:country":"US",
    "sg:address":"4090 Wendell Blvd",
    "sg:city":"Wendell",
    "sg:classifiers":[
        {
            "category":"Social Services",
            "subcategory":"Child Care",
            "type":"Services"
        }
    ],
    "sg:phone":"+1 919 365 7055",
    "sg:postcode":"27591",
    "sg:province":"NC",
    "wof:name":"Parham's Country Day School",
    "wof:placetype":"venue"
},
  "geometry": {"coordinates":[-78.362115,35.783474],"type":"Point"}
}