{
  "type": "Feature",
  "properties": {
    "addr:full":"201 Forest Hills Rd NW Wilson NC 27896",
    "addr:housenumber":"201",
    "addr:postcode":"27896",
    "addr:street":"Forest Hills Rd Nw",
    "iso:country":"US",
    "sg:address":"201 Forest Hills Rd NW",
    "sg:city":"Wilson",
    "sg:classifiers":[
        {
            "category":"Travel",
            "subcategory":"Travel Agent",
            "type":"Entertainment"
        }
    ],
    "sg:phone":"+1 252 291 7616",
    "sg:postcode":"27896",
    "sg:province":"NC",
    "sg:tags":[
        "agency",
        "bureau"
    ],
    "wof:name":"Travel Shoppe",
    "wof:placetype":"venue"
},
  "geometry": {"coordinates":[-77.93411999999999,35.750951],"type":"Point"}
}