{
  "type": "Feature",
  "properties": {
    "addr:full":"2204 Lionel Ln Raleigh NC 27607",
    "addr:housenumber":"2204",
    "addr:postcode":"27607",
    "addr:street":"Lionel Ln",
    "iso:country":"US",
    "sg:address":"2204 Lionel Ln",
    "sg:city":"Raleigh",
    "sg:classifiers":[
        {
            "category":"Wholesale",
            "subcategory":"Medical Equipment & Supplies",
            "type":"Manufacturing & Wholesale Goods"
        },
        {
            "category":"Shopping",
            "subcategory":"Pharmacy",
            "type":"Retail Goods"
        }
    ],
    "sg:phone":"+1 919 789 4439",
    "sg:postcode":"27607",
    "sg:province":"NC",
    "sg:tags":[
        "home",
        "health",
        "care"
    ],
    "wof:name":"Ics Beta 650061",
    "wof:placetype":"venue"
},
  "geometry": {"coordinates":[-78.696761,35.812298],"type":"Point"}
}