{
  "type": "Feature",
  "properties": {
    "iso:country":"US",
    "sg:address":"836 Santa Maria Ave",
    "sg:city":"Wilmington",
    "sg:classifiers":[
        {
            "category":"Professional",
            "subcategory":"Management & Consulting",
            "type":"Services"
        }
    ],
    "sg:phone":"+1   ",
    "sg:postcode":"28411",
    "sg:province":"NC",
    "wof:name":"Muck Roberson & Associates",
    "wof:placetype":"venue"
},
  "geometry": {"coordinates":[-77.77064900000001,34.275359],"type":"Point"}
}