{
  "type": "Feature",
  "properties": {
    "addr:full":"4791 S Depot St Claremont NC 28610",
    "addr:housenumber":"4791",
    "addr:postcode":"28610",
    "addr:street":"S Depot St",
    "iso:country":"US",
    "sg:address":"4791 S Depot St",
    "sg:city":"Claremont",
    "sg:classifiers":[
        {
            "category":"Organizations",
            "subcategory":"Religious Organization",
            "type":"Services"
        }
    ],
    "sg:phone":"+1 828 459 7110",
    "sg:postcode":"28610",
    "sg:province":"NC",
    "sg:tags":[
        "church"
    ],
    "wof:name":"First Baptist Church",
    "wof:placetype":"venue"
},
  "geometry": {"coordinates":[-81.146475,35.7119],"type":"Point"}
}