{
  "type": "Feature",
  "properties": {
    "iso:country":"US",
    "sg:address":"829 Stadium Dr",
    "sg:city":"Wake Forest",
    "sg:classifiers":[
        {
            "category":"Building & Trades",
            "subcategory":"Construction",
            "type":"Services"
        }
    ],
    "sg:phone":"+1 919 562 7090",
    "sg:postcode":"27587",
    "sg:province":"NC",
    "sg:tags":[
        "house"
    ],
    "wof:name":"Just Decks",
    "wof:placetype":"venue"
},
  "geometry": {"coordinates":[-78.52387899999999,35.988313],"type":"Point"}
}