{
  "type": "Feature",
  "properties": {
    "iso:country":"US",
    "sg:address":"406 Village Crossing Dr",
    "sg:city":"Chapel Hill",
    "sg:classifiers":[
        {
            "category":"Professional",
            "type":"Services"
        }
    ],
    "sg:phone":"+1 919 960 0450",
    "sg:postcode":"27517",
    "sg:province":"NC",
    "wof:name":"Douglas Meyer",
    "wof:placetype":"venue"
},
  "geometry": {"coordinates":[-79.007159,35.904851],"type":"Point"}
}