{
  "type": "Feature",
  "properties": {
    "addr:full":"1 Court Square Dr Lincolnton NC 28092",
    "addr:housenumber":"1",
    "addr:postcode":"28092",
    "addr:street":"Court Square Dr",
    "iso:country":"US",
    "sg:address":"1 Court Square Dr",
    "sg:city":"Lincolnton",
    "sg:classifiers":[
        {
            "category":"Government",
            "subcategory":"Office",
            "type":"Public Place"
        }
    ],
    "sg:phone":"+1 704 736 8530",
    "sg:postcode":"28092",
    "sg:province":"NC",
    "sg:website":"www.lincolncounty.org",
    "wof:name":"Register Of Deeds",
    "wof:placetype":"venue"
},
  "geometry": {"coordinates":[-80.602999,35.399039],"type":"Point"}
}