{
  "type": "Feature",
  "properties": {
    "iso:country":"US",
    "sg:address":"424 Hilo Dr",
    "sg:city":"Charlotte",
    "sg:classifiers":[
        {
            "category":"Insurance",
            "subcategory":"Insurance Agent",
            "type":"Services"
        }
    ],
    "sg:phone":"+1 704 840 6103",
    "sg:postcode":"28206",
    "sg:province":"NC",
    "sg:tags":[
        "processing"
    ],
    "wof:name":"Camc Medical Billing",
    "wof:placetype":"venue"
},
  "geometry": {"coordinates":[-80.805132,35.257666],"type":"Point"}
}