{
  "type": "Feature",
  "properties": {
    "addr:full":"139 Parker Dr West Jefferson NC 28694",
    "addr:housenumber":"139",
    "addr:postcode":"28694",
    "addr:street":"Parker Dr",
    "iso:country":"US",
    "sg:address":"139 Parker Dr",
    "sg:city":"West Jefferson",
    "sg:classifiers":[
        {
            "category":"Personal",
            "subcategory":"Hair Removal",
            "type":"Services"
        }
    ],
    "sg:phone":"+1   ",
    "sg:postcode":"28694",
    "sg:province":"NC",
    "wof:name":"Wholebrain Learning Center",
    "wof:placetype":"venue"
},
  "geometry": {"coordinates":[-81.49348000000001,36.380061],"type":"Point"}
}