{
  "type": "Feature",
  "properties": {
    "addr:full":"317 Sanford Dr Morganton NC 28655",
    "addr:housenumber":"317",
    "addr:postcode":"28655",
    "addr:street":"Sanford Dr",
    "iso:country":"US",
    "sg:address":"317 Sanford Dr",
    "sg:city":"Morganton",
    "sg:classifiers":[
        {
            "category":"Health Services",
            "subcategory":"Chiropractor",
            "type":"Services"
        }
    ],
    "sg:phone":"+1 828 433 7611",
    "sg:postcode":"28655",
    "sg:province":"NC",
    "wof:name":"Suber Chiropractic Center",
    "wof:placetype":"venue"
},
  "geometry": {"coordinates":[-81.704385,35.748033],"type":"Point"}
}