{
  "type": "Feature",
  "properties": {
    "iso:country":"US",
    "sg:address":"11 N Market St",
    "sg:city":"Asheville",
    "sg:classifiers":[
        {
            "category":"Professional",
            "subcategory":"Lawyer & Legal Services",
            "type":"Services"
        }
    ],
    "sg:phone":"+1   ",
    "sg:postcode":"28801",
    "sg:province":"NC",
    "wof:name":"Adam L Shealy",
    "wof:placetype":"venue"
},
  "geometry": {"coordinates":[-82.551181,35.596835],"type":"Point"}
}