{
  "type": "Feature",
  "properties": {
    "addr:full":"89 Peachtree Rd Asheville NC 28803",
    "addr:housenumber":"89",
    "addr:postcode":"28803",
    "addr:street":"Peachtree Rd",
    "iso:country":"US",
    "sg:address":"89 Peachtree Rd",
    "sg:city":"Asheville",
    "sg:classifiers":[
        {
            "category":"Professional",
            "subcategory":"Advertising",
            "type":"Services"
        },
        {
            "category":"Manufacturing",
            "subcategory":"Printing",
            "type":"Manufacturing & Wholesale Goods"
        }
    ],
    "sg:phone":"+1 828 255 0100",
    "sg:postcode":"28803",
    "sg:province":"NC",
    "sg:tags":[
        "agency",
        "multimedia",
        "representative"
    ],
    "sg:website":"www.chartermedia.com",
    "wof:name":"Charter Media",
    "wof:placetype":"venue"
},
  "geometry": {"coordinates":[-82.526302,35.514133],"type":"Point"}
}