{
  "type": "Feature",
  "properties": {
    "addr:full":"2153 Southfork Dr Morganton NC 28655",
    "addr:housenumber":"2153",
    "addr:postcode":"28655",
    "addr:street":"Southfork Dr",
    "iso:country":"US",
    "sg:address":"2153 Southfork Dr",
    "sg:city":"Morganton",
    "sg:classifiers":[
        {
            "category":"Real Estate",
            "subcategory":"Real Estate Agent",
            "type":"Services"
        }
    ],
    "sg:phone":"+1 828 437 5466",
    "sg:postcode":"28655",
    "sg:province":"NC",
    "wof:name":"Foster Rentals",
    "wof:placetype":"venue"
},
  "geometry": {"coordinates":[-81.737132,35.679551],"type":"Point"}
}