{
  "type": "Feature",
  "properties": {
    "addr:full":"6502 Lundin Links Ln Charlotte NC 28277",
    "addr:housenumber":"6502",
    "addr:postcode":"28277",
    "addr:street":"Lundin Links Ln",
    "iso:country":"US",
    "sg:address":"6502 Lundin Links Ln",
    "sg:city":"Charlotte",
    "sg:classifiers":[
        {
            "category":"Home & Garden",
            "subcategory":"Building Materials",
            "type":"Retail Goods"
        },
        {
            "category":"Professional",
            "subcategory":"Management & Consulting",
            "type":"Services"
        }
    ],
    "sg:phone":"+1 704 527 2111",
    "sg:postcode":"28277",
    "sg:province":"NC",
    "sg:tags":[
        "windows"
    ],
    "wof:name":"First Choice Windows & Siding",
    "wof:placetype":"venue"
},
  "geometry": {"coordinates":[-80.78516500000001,35.045708],"type":"Point"}
}