{
  "type": "Feature",
  "properties": {
    "iso:country":"US",
    "sg:address":"298 R and R Ln",
    "sg:city":"Taylorsville",
    "sg:classifiers":[
        {
            "category":"Farming",
            "subcategory":"Farm",
            "type":"Manufacturing & Wholesale Goods"
        }
    ],
    "sg:phone":"+1 828 635 7112",
    "sg:postcode":"28681",
    "sg:province":"NC",
    "wof:name":"Grand C Farm",
    "wof:placetype":"venue"
},
  "geometry": {"coordinates":[-81.138898,35.850942],"type":"Point"}
}