{
  "type": "Feature",
  "properties": {
    "addr:full":"229 Engleman Ave Burlington NC 27215",
    "addr:housenumber":"229",
    "addr:postcode":"27215",
    "addr:street":"Engleman Ave",
    "iso:country":"US",
    "sg:address":"229 Engleman Ave",
    "sg:city":"Burlington",
    "sg:classifiers":[
        {
            "category":"Professional",
            "subcategory":"Management & Consulting",
            "type":"Services"
        }
    ],
    "sg:phone":"+1   ",
    "sg:postcode":"27215",
    "sg:province":"NC",
    "sg:tags":[
        "business"
    ],
    "wof:name":"AMS Consulting Inc",
    "wof:placetype":"venue"
},
  "geometry": {"coordinates":[-79.469303,36.085045],"type":"Point"}
}