{
  "type": "Feature",
  "properties": {
    "iso:country":"US",
    "sg:address":"244 Dobson Ave",
    "sg:city":"Statesville",
    "sg:classifiers":[
        {
            "category":"Social Services",
            "type":"Services"
        }
    ],
    "sg:phone":"+1   ",
    "sg:postcode":"28677",
    "sg:province":"NC",
    "wof:name":"Statesville Housing Authority",
    "wof:placetype":"venue"
},
  "geometry": {"coordinates":[-80.88131199999999,35.768817],"type":"Point"}
}