{
  "type": "Feature",
  "properties": {
    "addr:full":"3019 Shamrock Dr Charlotte NC 28215",
    "addr:housenumber":"3019",
    "addr:postcode":"28215",
    "addr:street":"Shamrock Dr",
    "iso:country":"US",
    "sg:address":"3019 Shamrock Dr",
    "sg:city":"Charlotte",
    "sg:classifiers":[
        {
            "category":"Restaurant",
            "type":"Food & Drink"
        }
    ],
    "sg:menulink":"http://www.allmenus.com/nc/charlotte/38030-lang-van/menu/",
    "sg:phone":"+1 704 531 9525",
    "sg:postcode":"28215",
    "sg:province":"NC",
    "sg:tags":[
        "asian",
        "vietnamese"
    ],
    "wof:name":"Lang Van",
    "wof:placetype":"venue"
},
  "geometry": {"coordinates":[-80.774804,35.23639],"type":"Point"}
}