{
  "type": "Feature",
  "properties": {
    "iso:country":"US",
    "sg:address":"301 S 2nd St",
    "sg:city":"Smithfield",
    "sg:classifiers":[
        {
            "category":"Professional",
            "subcategory":"Accounting & Tax Preparation",
            "type":"Services"
        }
    ],
    "sg:phone":"+1 919 934 4607",
    "sg:postcode":"27577",
    "sg:province":"NC",
    "sg:tags":[
        "accountant"
    ],
    "wof:name":"Claud L Dunn Jr CPA",
    "wof:placetype":"venue"
},
  "geometry": {"coordinates":[-78.348947,35.509447],"type":"Point"}
}