{
  "type": "Feature",
  "properties": {
    "iso:country":"US",
    "sg:address":"3225 Jefferson Davis Hwy",
    "sg:city":"Sanford",
    "sg:classifiers":[
        {
            "category":"Building & Trades",
            "subcategory":"Construction",
            "type":"Services"
        }
    ],
    "sg:phone":"+1 919 774 6811",
    "sg:postcode":"27332",
    "sg:province":"NC",
    "sg:tags":[
        "general",
        "contractor"
    ],
    "wof:name":"Cole Construction Co-Sanford",
    "wof:placetype":"venue"
},
  "geometry": {"coordinates":[-79.23143,35.40653],"type":"Point"}
}