{
  "type": "Feature",
  "properties": {
    "addr:full":"758 Radio Dr Lexington NC 27292",
    "addr:housenumber":"758",
    "addr:postcode":"27292",
    "addr:street":"Radio Dr",
    "iso:country":"US",
    "sg:address":"758 Radio Dr",
    "sg:city":"Lexington",
    "sg:classifiers":[
        {
            "category":"Retail",
            "subcategory":"Animal Services",
            "type":"Services"
        }
    ],
    "sg:phone":"+1 336 249 7618",
    "sg:postcode":"27292",
    "sg:province":"NC",
    "sg:tags":[
        "pet",
        "grooming",
        "washing"
    ],
    "wof:name":"Creative K-9 Cuts",
    "wof:placetype":"venue"
},
  "geometry": {"coordinates":[-80.225224,35.838437],"type":"Point"}
}