{
  "type": "Feature",
  "properties": {
    "addr:full":"2580 Court Dr Gastonia NC 28054",
    "addr:housenumber":"2580",
    "addr:postcode":"28054",
    "addr:street":"Court Dr",
    "iso:country":"US",
    "sg:address":"2580 Court Dr",
    "sg:city":"Gastonia",
    "sg:classifiers":[
        {
            "category":"Shopping",
            "subcategory":"Pharmacy",
            "type":"Retail Goods"
        }
    ],
    "sg:phone":"+1 704 810 3681",
    "sg:postcode":"28054",
    "sg:province":"NC",
    "sg:website":"www.cvs.com",
    "wof:name":"CVS Pharmacy",
    "wof:placetype":"venue"
},
  "geometry": {"coordinates":[-81.136309,35.273092],"type":"Point"}
}