{
  "type": "Feature",
  "properties": {
    "iso:country":"US",
    "sg:address":"2101 New Hope Rd",
    "sg:city":"Hertford",
    "sg:classifiers":[
        {
            "category":"Food & Beverages",
            "subcategory":"Groceries & Convenience Stores",
            "type":"Retail Goods"
        }
    ],
    "sg:phone":"+1 252 264 3117",
    "sg:postcode":"27944",
    "sg:province":"NC",
    "sg:tags":[
        "grocer"
    ],
    "wof:name":"New Hope Country Store Inc",
    "wof:placetype":"venue"
},
  "geometry": {"coordinates":[-76.31674099999999,36.155803],"type":"Point"}
}