{
  "type": "Feature",
  "properties": {
    "iso:country":"US",
    "sg:address":"505 Baity St",
    "sg:city":"Winston Salem",
    "sg:classifiers":[
        {
            "category":"Home & Garden",
            "subcategory":"Building Materials",
            "type":"Retail Goods"
        }
    ],
    "sg:phone":"+1 336 722 0089",
    "sg:postcode":"27105",
    "sg:province":"NC",
    "sg:tags":[
        "stone"
    ],
    "wof:name":"Yadkin Valley Stone",
    "wof:placetype":"venue"
},
  "geometry": {"coordinates":[-80.260283,36.129779],"type":"Point"}
}