{
  "type": "Feature",
  "properties": {
    "iso:country":"US",
    "sg:address":"2914 Selwyn Ave",
    "sg:city":"Charlotte",
    "sg:classifiers":[
        {
            "category":"Manufacturing",
            "subcategory":"Building Materials",
            "type":"Manufacturing & Wholesale Goods"
        },
        {
            "category":"Home & Garden",
            "subcategory":"Furniture",
            "type":"Retail Goods"
        }
    ],
    "sg:phone":"+1 704 339 0222",
    "sg:postcode":"28209",
    "sg:province":"NC",
    "sg:tags":[
        "equipment",
        "cabinet",
        "wood",
        "kitchen",
        "mfg"
    ],
    "wof:name":"Cabinets By Design LLC",
    "wof:placetype":"venue"
},
  "geometry": {"coordinates":[-80.840311,35.17387],"type":"Point"}
}