{
  "type": "Feature",
  "properties": {
    "iso:country":"US",
    "sg:address":"4131 Old Course Dr",
    "sg:city":"Charlotte",
    "sg:classifiers":[
        {
            "category":"Wholesale",
            "subcategory":"Machinery & Supplies",
            "type":"Manufacturing & Wholesale Goods"
        }
    ],
    "sg:phone":"+1 704 849 2863",
    "sg:postcode":"28277",
    "sg:province":"NC",
    "sg:tags":[
        "equipment",
        "industrial"
    ],
    "wof:name":"Salesman Forhydromat",
    "wof:placetype":"venue"
},
  "geometry": {"coordinates":[-80.812926,35.06665],"type":"Point"}
}