{
  "type": "Feature",
  "properties": {
    "addr:full":"3548 Summerfield Ln Winston Salem NC 27106",
    "addr:housenumber":"3548",
    "addr:postcode":"27106",
    "addr:street":"Summerfield Ln",
    "iso:country":"US",
    "sg:address":"3548 Summerfield Ln",
    "sg:city":"Winston Salem",
    "sg:classifiers":[
        {
            "category":"Professional",
            "subcategory":"Lawyer & Legal Services",
            "type":"Services"
        }
    ],
    "sg:phone":"+1   ",
    "sg:postcode":"27106",
    "sg:province":"NC",
    "wof:name":"Hodges Warren C Atty At Law",
    "wof:placetype":"venue"
},
  "geometry": {"coordinates":[-80.34785599999999,36.131278],"type":"Point"}
}