{
  "type": "Feature",
  "properties": {
    "iso:country":"US",
    "sg:address":"600 Kingsdale Blvd",
    "sg:city":"Lumberton",
    "sg:classifiers":[
        {
            "category":"Recreation",
            "type":"Entertainment"
        }
    ],
    "sg:phone":"+1 910 608 0164",
    "sg:postcode":"28358",
    "sg:province":"NC",
    "sg:tags":[
        "parks"
    ],
    "wof:name":"River Way",
    "wof:placetype":"venue"
},
  "geometry": {"coordinates":[-79.00195600000001,34.610015],"type":"Point"}
}