{
  "type": "Feature",
  "properties": {
    "iso:country":"US",
    "sg:address":"2431 US Hwy 21",
    "sg:city":"State Road",
    "sg:classifiers":[
        {
            "category":"Personal",
            "subcategory":"Beauty Salon",
            "type":"Services"
        }
    ],
    "sg:phone":"+1 336 874 2927",
    "sg:postcode":"28676",
    "sg:province":"NC",
    "wof:name":"Lavons Beauty Shop",
    "wof:placetype":"venue"
},
  "geometry": {"coordinates":[-80.896396,36.347699],"type":"Point"}
}