{
  "type": "Feature",
  "properties": {
    "addr:full":"560 39th Avenue Dr NW Hickory NC 28601",
    "addr:housenumber":"560",
    "addr:postcode":"28601",
    "addr:street":"39Th Avenue Dr Nw",
    "iso:country":"US",
    "sg:address":"560 39th Avenue Dr NW",
    "sg:city":"Hickory",
    "sg:classifiers":[
        {
            "category":"Professional",
            "subcategory":"Business Services",
            "type":"Services"
        }
    ],
    "sg:phone":"+1   ",
    "sg:postcode":"28601",
    "sg:province":"NC",
    "wof:name":"Lenoir Atrium LLC",
    "wof:placetype":"venue"
},
  "geometry": {"coordinates":[-81.331985,35.786755],"type":"Point"}
}