{
  "type": "Feature",
  "properties": {
    "addr:full":"1909 Baytree Dr Greensboro NC 27455",
    "addr:housenumber":"1909",
    "addr:postcode":"27455",
    "addr:street":"Baytree Dr",
    "iso:country":"US",
    "sg:address":"1909 Baytree Dr",
    "sg:city":"Greensboro",
    "sg:classifiers":[
        {
            "category":"Professional",
            "subcategory":"Management & Consulting",
            "type":"Services"
        }
    ],
    "sg:phone":"+1   ",
    "sg:postcode":"27455",
    "sg:province":"NC",
    "sg:tags":[
        "training"
    ],
    "wof:name":"Agility Cnsulting Training LLC",
    "wof:placetype":"venue"
},
  "geometry": {"coordinates":[-79.81932399999999,36.151655],"type":"Point"}
}