{
  "type": "Feature",
  "properties": {
    "addr:full":"227 W Martin St Raleigh NC 27601",
    "addr:housenumber":"227",
    "addr:postcode":"27601",
    "addr:street":"W Martin St",
    "iso:country":"US",
    "sg:address":"227 W Martin St",
    "sg:city":"Raleigh",
    "sg:classifiers":[
        {
            "category":"Professional",
            "subcategory":"Lawyer & Legal Services",
            "type":"Services"
        }
    ],
    "sg:phone":"+1 919 832 3915",
    "sg:postcode":"27601",
    "sg:province":"NC",
    "sg:tags":[
        "attorney"
    ],
    "wof:name":"Boxley Bolton & Garber",
    "wof:placetype":"venue"
},
  "geometry": {"coordinates":[-78.643111,35.776974],"type":"Point"}
}