{
  "type": "Feature",
  "properties": {
    "addr:full":"231 Main St NW Lenoir NC 28645",
    "addr:housenumber":"231",
    "addr:postcode":"28645",
    "addr:street":"Main St Nw",
    "iso:country":"US",
    "sg:address":"231 Main St NW",
    "sg:city":"Lenoir",
    "sg:classifiers":[
        {
            "category":"Professional",
            "subcategory":"Business Services",
            "type":"Services"
        }
    ],
    "sg:phone":"+1   ",
    "sg:postcode":"28645",
    "sg:province":"NC",
    "wof:name":"Nelson Bail Bonding",
    "wof:placetype":"venue"
},
  "geometry": {"coordinates":[-81.539298,35.913923],"type":"Point"}
}