{
  "type": "Feature",
  "properties": {
    "addr:full":"5727 Pineway Ln Graham NC 27253",
    "addr:housenumber":"5727",
    "addr:postcode":"27253",
    "addr:street":"Pineway Ln",
    "iso:country":"US",
    "sg:address":"5727 Pineway Ln",
    "sg:city":"Graham",
    "sg:classifiers":[
        {
            "category":"Retail",
            "subcategory":"Car Wash",
            "type":"Services"
        }
    ],
    "sg:phone":"+1   ",
    "sg:postcode":"27253",
    "sg:province":"NC",
    "sg:tags":[
        "carwash"
    ],
    "wof:name":"S & K Automotive",
    "wof:placetype":"venue"
},
  "geometry": {"coordinates":[-79.346385,35.937844],"type":"Point"}
}