{
  "type": "Feature",
  "properties": {
    "iso:country":"US",
    "sg:address":"606 Clark Dr",
    "sg:city":"Tarboro",
    "sg:classifiers":[
        {
            "category":"Personal",
            "type":"Services"
        }
    ],
    "sg:phone":"+1   ",
    "sg:postcode":"27886",
    "sg:province":"NC",
    "wof:name":"Eastern Carolina Regional",
    "wof:placetype":"venue"
},
  "geometry": {"coordinates":[-77.531584,35.910182],"type":"Point"}
}