{
  "type": "Feature",
  "properties": {
    "addr:full":"4031 Wake Forest Rd Raleigh NC 27609",
    "addr:housenumber":"4031",
    "addr:postcode":"27609",
    "addr:street":"Wake Forest Rd",
    "iso:country":"US",
    "sg:address":"4031 Wake Forest Rd",
    "sg:city":"Raleigh",
    "sg:classifiers":[
        {
            "category":"Shopping",
            "subcategory":"Books",
            "type":"Retail Goods"
        }
    ],
    "sg:phone":"+1 919 790 8784",
    "sg:postcode":"27609",
    "sg:province":"NC",
    "sg:tags":[
        "bookstore"
    ],
    "wof:name":"Books-A-Million",
    "wof:placetype":"venue"
},
  "geometry": {"coordinates":[-78.614206,35.836107],"type":"Point"}
}