{
  "type": "Feature",
  "properties": {
    "iso:country":"US",
    "sg:address":"206 Tournament Dr SW",
    "sg:city":"Concord",
    "sg:classifiers":[
        {
            "category":"Banks & Credit Unions",
            "subcategory":"Financial Services",
            "type":"Services"
        }
    ],
    "sg:phone":"+1 704 785 8743",
    "sg:postcode":"28025",
    "sg:province":"NC",
    "sg:tags":[
        "investor"
    ],
    "wof:name":"Nai Nigerian Assn of Investors",
    "wof:placetype":"venue"
},
  "geometry": {"coordinates":[-80.578194,35.402952],"type":"Point"}
}