{
  "type": "Feature",
  "properties": {
    "addr:full":"1266 N Wesleyan Blvd Rocky Mount NC 27804",
    "addr:housenumber":"1266",
    "addr:postcode":"27804",
    "addr:street":"N Wesleyan Blvd",
    "iso:country":"US",
    "sg:address":"1266 N Wesleyan Blvd",
    "sg:city":"Rocky Mount",
    "sg:classifiers":[
        {
            "category":"Restaurant",
            "type":"Food & Drink"
        }
    ],
    "sg:phone":"+1 252 446 4241",
    "sg:postcode":"27804",
    "sg:province":"NC",
    "sg:website":"www.kwcafeterias.com",
    "wof:name":"K & W Cafeterias",
    "wof:placetype":"venue"
},
  "geometry": {"coordinates":[-77.79901599999999,35.975168],"type":"Point"}
}