{
  "type": "Feature",
  "properties": {
    "addr:full":"612 S Main St Landis NC 28088",
    "addr:housenumber":"612",
    "addr:postcode":"28088",
    "addr:street":"S Main St",
    "iso:country":"US",
    "sg:address":"612 S Main St",
    "sg:city":"Landis",
    "sg:classifiers":[
        {
            "category":"Manufacturing",
            "subcategory":"Apparel",
            "type":"Manufacturing & Wholesale Goods"
        }
    ],
    "sg:phone":"+1 704 857 4080",
    "sg:postcode":"28088",
    "sg:province":"NC",
    "wof:name":"Signworx",
    "wof:placetype":"venue"
},
  "geometry": {"coordinates":[-80.616004,35.542357],"type":"Point"}
}