{
  "type": "Feature",
  "properties": {
    "iso:country":"US",
    "sg:address":"2435 Plantation Center Dr # 110",
    "sg:city":"Matthews",
    "sg:classifiers":[
        {
            "category":"Health Services",
            "subcategory":"Doctor",
            "type":"Services"
        }
    ],
    "sg:phone":"+1 704 846 1911",
    "sg:postcode":"28105",
    "sg:province":"NC",
    "sg:tags":[
        "medicine",
        "physician",
        "practice",
        "surgeons",
        "family"
    ],
    "wof:name":"Choice Care Family Medical Center Pc",
    "wof:placetype":"venue"
},
  "geometry": {"coordinates":[-80.73215999999999,35.085815],"type":"Point"}
}