{
  "type": "Feature",
  "properties": {
    "iso:country":"US",
    "sg:address":"504 1st Ave SW",
    "sg:city":"Hickory",
    "sg:classifiers":[
        {
            "category":"Professional",
            "subcategory":"Lawyer & Legal Services",
            "type":"Services"
        }
    ],
    "sg:phone":"+1 828 322 1688",
    "sg:postcode":"28602",
    "sg:province":"NC",
    "sg:tags":[
        "attorney"
    ],
    "wof:name":"Matthews Law Firm",
    "wof:placetype":"venue"
},
  "geometry": {"coordinates":[-81.346076,35.730824],"type":"Point"}
}