{
  "type": "Feature",
  "properties": {
    "addr:full":"166 E Ward St Asheboro NC 27203",
    "addr:housenumber":"166",
    "addr:postcode":"27203",
    "addr:street":"E Ward St",
    "iso:country":"US",
    "sg:address":"166 E Ward St",
    "sg:city":"Asheboro",
    "sg:classifiers":[
        {
            "category":"Insurance",
            "subcategory":"Insurance Agent",
            "type":"Services"
        }
    ],
    "sg:phone":"+1 336 626 8216",
    "sg:postcode":"27203",
    "sg:province":"NC",
    "wof:name":"Pegram & Crisp Insurance",
    "wof:placetype":"venue"
},
  "geometry": {"coordinates":[-79.81204700000001,35.709038],"type":"Point"}
}