{
  "type": "Feature",
  "properties": {
    "addr:full":"455 Queens Creek Rd Hubert NC 28539",
    "addr:housenumber":"455",
    "addr:postcode":"28539",
    "addr:street":"Queens Creek Rd",
    "iso:country":"US",
    "sg:address":"455 Queens Creek Rd",
    "sg:city":"Hubert",
    "sg:classifiers":[
        {
            "category":"Shopping",
            "subcategory":"Used Merchandise",
            "type":"Retail Goods"
        }
    ],
    "sg:phone":"+1 910 326 3131",
    "sg:postcode":"28539",
    "sg:province":"NC",
    "sg:tags":[
        "shop",
        "thrift"
    ],
    "wof:name":"Creekside Bargain Shop",
    "wof:placetype":"venue"
},
  "geometry": {"coordinates":[-77.170936,34.684691],"type":"Point"}
}