{
  "type": "Feature",
  "properties": {
    "iso:country":"US",
    "sg:address":"4457 Arendell St",
    "sg:city":"Morehead City",
    "sg:classifiers":[
        {
            "category":"Shopping",
            "subcategory":"Books",
            "type":"Retail Goods"
        }
    ],
    "sg:phone":"+1 252 240 1118",
    "sg:postcode":"28557",
    "sg:province":"NC",
    "sg:tags":[
        "dealer"
    ],
    "wof:name":"Graceway Christian Stores",
    "wof:placetype":"venue"
},
  "geometry": {"coordinates":[-76.778482,34.730371],"type":"Point"}
}