{
  "type": "Feature",
  "properties": {
    "iso:country":"US",
    "sg:address":"3755 Benson Dr",
    "sg:city":"Raleigh",
    "sg:classifiers":[
        {
            "category":"Professional",
            "subcategory":"Engineering",
            "type":"Services"
        }
    ],
    "sg:phone":"+1 919 790 5303",
    "sg:postcode":"27609",
    "sg:province":"NC",
    "sg:tags":[
        "engineer"
    ],
    "wof:name":"Mc Evoy Engineering Svc Inc",
    "wof:placetype":"venue"
},
  "geometry": {"coordinates":[-78.619277,35.834288],"type":"Point"}
}