{
  "type": "Feature",
  "properties": {
    "addr:full":"1033 Randolph St Thomasville NC 27360",
    "addr:housenumber":"1033",
    "addr:postcode":"27360",
    "addr:street":"Randolph St",
    "iso:country":"US",
    "sg:address":"1033 Randolph St",
    "sg:city":"Thomasville",
    "sg:classifiers":[
        {
            "category":"Utilities",
            "subcategory":"Mobile Phone",
            "type":"Services"
        }
    ],
    "sg:phone":"+1 336 476 0261",
    "sg:postcode":"27360",
    "sg:province":"NC",
    "sg:tags":[
        "telephone",
        "cellular"
    ],
    "wof:name":"Alltel Communications Retail",
    "wof:placetype":"venue"
},
  "geometry": {"coordinates":[-80.07288200000001,35.867779],"type":"Point"}
}