{
  "type": "Feature",
  "properties": {
    "iso:country":"US",
    "sg:address":"2707 Creek Run Ct",
    "sg:city":"Chapel Hill",
    "sg:classifiers":[
        {
            "category":"Building & Trades",
            "subcategory":"Construction",
            "type":"Services"
        }
    ],
    "sg:phone":"+1 919 942 2848",
    "sg:postcode":"27514",
    "sg:province":"NC",
    "sg:tags":[
        "general",
        "contractor"
    ],
    "wof:name":"J T Lewis Builders",
    "wof:placetype":"venue"
},
  "geometry": {"coordinates":[-79.053037,35.975822],"type":"Point"}
}