{
  "type": "Feature",
  "properties": {
    "addr:full":"4100 Wendell Blvd Wendell NC 27591",
    "addr:housenumber":"4100",
    "addr:postcode":"27591",
    "addr:street":"Wendell Blvd",
    "iso:country":"US",
    "sg:address":"4100 Wendell Blvd",
    "sg:city":"Wendell",
    "sg:classifiers":[
        {
            "category":"Autos & Motor Vehicles",
            "subcategory":"Auto Supplies",
            "type":"Retail Goods"
        }
    ],
    "sg:phone":"+1 919 365 7145",
    "sg:postcode":"27591",
    "sg:province":"NC",
    "sg:tags":[
        "automobile",
        "parts"
    ],
    "wof:name":"Western Auto",
    "wof:placetype":"venue"
},
  "geometry": {"coordinates":[-78.35934899999999,35.784677],"type":"Point"}
}