{
  "type": "Feature",
  "properties": {
    "iso:country":"US",
    "sg:address":"510 Greer Cir SW",
    "sg:city":"Lenoir",
    "sg:classifiers":[
        {
            "category":"Government",
            "subcategory":"Office",
            "type":"Public Place"
        }
    ],
    "sg:phone":"+1 828 757 2174",
    "sg:postcode":"28645",
    "sg:province":"NC",
    "sg:tags":[
        "village"
    ],
    "wof:name":"Streets Dept",
    "wof:placetype":"venue"
},
  "geometry": {"coordinates":[-81.553297,35.901748],"type":"Point"}
}