{
  "type": "Feature",
  "properties": {
    "addr:full":"1300 Westwood Ln Wilkesboro NC 28697",
    "addr:housenumber":"1300",
    "addr:postcode":"28697",
    "addr:street":"Westwood Ln",
    "iso:country":"US",
    "sg:address":"1300 Westwood Ln",
    "sg:city":"Wilkesboro",
    "sg:classifiers":[
        {
            "category":"Shopping",
            "subcategory":"Pharmacy",
            "type":"Retail Goods"
        }
    ],
    "sg:phone":"+1 336 667 9347",
    "sg:postcode":"28697",
    "sg:province":"NC",
    "wof:name":"Wilkes Family Pharmacy",
    "wof:placetype":"venue"
},
  "geometry": {"coordinates":[-81.166961,36.131986],"type":"Point"}
}