{
  "type": "Feature",
  "properties": {
    "addr:full":"2915 Heathmoor Ln Charlotte NC 28211",
    "addr:housenumber":"2915",
    "addr:postcode":"28211",
    "addr:street":"Heathmoor Ln",
    "iso:country":"US",
    "sg:address":"2915 Heathmoor Ln",
    "sg:city":"Charlotte",
    "sg:classifiers":[
        {
            "category":"Professional",
            "subcategory":"Business Services",
            "type":"Services"
        }
    ],
    "sg:phone":"+1   ",
    "sg:postcode":"28211",
    "sg:province":"NC",
    "wof:name":"Weg Group Inc",
    "wof:placetype":"venue"
},
  "geometry": {"coordinates":[-80.80954300000001,35.167784],"type":"Point"}
}