{
  "type": "Feature",
  "properties": {
    "addr:full":"7315 Mount Hermon Rock Creek Rd Snow Camp NC 27349",
    "addr:housenumber":"7315",
    "addr:postcode":"27349",
    "addr:street":"Mount Hermon Rock Creek Rd",
    "iso:country":"US",
    "sg:address":"7315 Mount Hermon Rock Creek Rd",
    "sg:city":"Snow Camp",
    "sg:classifiers":[
        {
            "category":"Organizations",
            "subcategory":"Religious Organization",
            "type":"Services"
        }
    ],
    "sg:phone":"+1 336 376 3515",
    "sg:postcode":"27349",
    "sg:province":"NC",
    "sg:tags":[
        "church"
    ],
    "wof:name":"Rock Creek United Mthdst Chr",
    "wof:placetype":"venue"
},
  "geometry": {"coordinates":[-79.476054,35.919715],"type":"Point"}
}