{
  "type": "Feature",
  "properties": {
    "iso:country":"US",
    "sg:address":"6717 Porterfield Rd",
    "sg:city":"Charlotte",
    "sg:classifiers":[
        {
            "category":"Government",
            "subcategory":"Office",
            "type":"Public Place"
        }
    ],
    "sg:phone":"+1 704 341 7497",
    "sg:postcode":"28226",
    "sg:province":"NC",
    "sg:tags":[
        "development"
    ],
    "wof:name":"Rcl Stuccocampos Lozano R",
    "wof:placetype":"venue"
},
  "geometry": {"coordinates":[-80.842534,35.079806],"type":"Point"}
}