{
  "type": "Feature",
  "properties": {
    "addr:full":"7455 Six Forks Rd Raleigh NC 27615",
    "addr:housenumber":"7455",
    "addr:postcode":"27615",
    "addr:street":"Six Forks Rd",
    "iso:country":"US",
    "sg:address":"7455 Six Forks Rd",
    "sg:city":"Raleigh",
    "sg:classifiers":[
        {
            "category":"Shopping",
            "subcategory":"Jewelry",
            "type":"Retail Goods"
        }
    ],
    "sg:phone":"+1 919 676 0401",
    "sg:postcode":"27615",
    "sg:province":"NC",
    "sg:tags":[
        "jeweler"
    ],
    "wof:name":"Godfrey's North Raleigh Jwlrs",
    "wof:placetype":"venue"
},
  "geometry": {"coordinates":[-78.645841,35.879707],"type":"Point"}
}