{
  "type": "Feature",
  "properties": {
    "addr:full":"4412 Central Ave Charlotte NC 28205",
    "addr:housenumber":"4412",
    "addr:postcode":"28205",
    "addr:street":"Central Ave",
    "iso:country":"US",
    "sg:address":"4412 Central Ave",
    "sg:city":"Charlotte",
    "sg:classifiers":[
        {
            "category":"Wholesale",
            "subcategory":"Meat",
            "type":"Manufacturing & Wholesale Goods"
        }
    ],
    "sg:phone":"+1 704 568 4810",
    "sg:postcode":"28205",
    "sg:province":"NC",
    "sg:tags":[
        "plant",
        "packing"
    ],
    "wof:name":"Carniceria La Mexicana Nbr 2 M",
    "wof:placetype":"venue"
},
  "geometry": {"coordinates":[-80.77066600000001,35.213782],"type":"Point"}
}