{
  "type": "Feature",
  "properties": {
    "iso:country":"US",
    "sg:address":"703 Martin Luther King Jr Dr",
    "sg:city":"Maxton",
    "sg:classifiers":[
        {
            "category":"Food & Beverages",
            "subcategory":"Liquor & Beverages",
            "type":"Retail Goods"
        }
    ],
    "sg:phone":"+1 910 844 3517",
    "sg:postcode":"28364",
    "sg:province":"NC",
    "sg:tags":[
        "alcoholic"
    ],
    "wof:name":"ABC Store of Maxton",
    "wof:placetype":"venue"
},
  "geometry": {"coordinates":[-79.33703300000001,34.731376],"type":"Point"}
}