{
  "type": "Feature",
  "properties": {
    "addr:full":"53 Rex Ave Gastonia NC 28054",
    "addr:housenumber":"53",
    "addr:postcode":"28054",
    "addr:street":"Rex Ave",
    "iso:country":"US",
    "sg:address":"53 Rex Ave",
    "sg:city":"Gastonia",
    "sg:classifiers":[
        {
            "category":"Home & Garden",
            "subcategory":"Hardware",
            "type":"Retail Goods"
        }
    ],
    "sg:phone":"+1 704 853 3037",
    "sg:postcode":"28054",
    "sg:province":"NC",
    "wof:name":"Mailbox Designs",
    "wof:placetype":"venue"
},
  "geometry": {"coordinates":[-81.131321,35.288773],"type":"Point"}
}