{
  "type": "Feature",
  "properties": {
    "addr:full":"6280 Ramada Dr Clemmons NC 27012",
    "addr:housenumber":"6280",
    "addr:postcode":"27012",
    "addr:street":"Ramada Dr",
    "iso:country":"US",
    "sg:address":"6280 Ramada Dr",
    "sg:city":"Clemmons",
    "sg:classifiers":[
        {
            "category":"Autos & Motor Vehicles",
            "subcategory":"Auto Supplies",
            "type":"Retail Goods"
        },
        {
            "category":"Manufacturing",
            "subcategory":"Motor Vehicles & Parts",
            "type":"Manufacturing & Wholesale Goods"
        },
        {
            "category":"Retail",
            "subcategory":"Auto Repair",
            "type":"Services"
        }
    ],
    "sg:phone":"+1 336 766 1116",
    "sg:postcode":"27012",
    "sg:province":"NC",
    "sg:tags":[
        "body",
        "repairing",
        "buses-distributors",
        "automobile",
        "buses-parts",
        "truck",
        "painting",
        "manufacturer"
    ],
    "wof:name":"Dings & Dents Inc",
    "wof:placetype":"venue"
},
  "geometry": {"coordinates":[-80.37617,36.03929],"type":"Point"}
}