{
  "type": "Feature",
  "properties": {
    "iso:country":"US",
    "sg:address":"2704 Alamance Rd",
    "sg:city":"Burlington",
    "sg:classifiers":[
        {
            "category":"Shopping",
            "subcategory":"Tobacco",
            "type":"Retail Goods"
        }
    ],
    "sg:phone":"+1 336 221 0961",
    "sg:postcode":"27215",
    "sg:province":"NC",
    "sg:tags":[
        "cigarette",
        "cigar",
        "dealer"
    ],
    "wof:name":"J R Cigars",
    "wof:placetype":"venue"
},
  "geometry": {"coordinates":[-79.46924,36.064396],"type":"Point"}
}