{
  "type": "Feature",
  "properties": {
    "iso:country":"US",
    "sg:address":"4109 Wake Forest Rd",
    "sg:city":"Raleigh",
    "sg:classifiers":[
        {
            "category":"Organizations",
            "subcategory":"Professional Association",
            "type":"Services"
        }
    ],
    "sg:phone":"+1 919 876 5545",
    "sg:postcode":"27609",
    "sg:province":"NC",
    "wof:name":"Small Business Bureau Assn",
    "wof:placetype":"venue"
},
  "geometry": {"coordinates":[-78.61367199999999,35.83659],"type":"Point"}
}