{
  "type": "Feature",
  "properties": {
    "addr:full":"411 Graves Mill Rd Kernersville NC 27284",
    "addr:housenumber":"411",
    "addr:postcode":"27284",
    "addr:street":"Graves Mill Rd",
    "iso:country":"US",
    "sg:address":"411 Graves Mill Rd",
    "sg:city":"Kernersville",
    "sg:classifiers":[
        {
            "category":"Building & Trades",
            "subcategory":"Plumbing",
            "type":"Services"
        }
    ],
    "sg:phone":"+1 336 996 7444",
    "sg:postcode":"27284",
    "sg:province":"NC",
    "sg:tags":[
        "plumbing",
        "contractor"
    ],
    "wof:name":"Mr Plumber",
    "wof:placetype":"venue"
},
  "geometry": {"coordinates":[-80.05985,36.122923],"type":"Point"}
}