{
  "type": "Feature",
  "properties": {
    "addr:full":"1033 Gaston Ave Gastonia NC 28052",
    "addr:housenumber":"1033",
    "addr:postcode":"28052",
    "addr:street":"Gaston Ave",
    "iso:country":"US",
    "sg:address":"1033 Gaston Ave",
    "sg:city":"Gastonia",
    "sg:classifiers":[
        {
            "category":"Retail",
            "subcategory":"Repair Shop",
            "type":"Services"
        }
    ],
    "sg:phone":"+1 704 868 8538",
    "sg:postcode":"28052",
    "sg:province":"NC",
    "sg:tags":[
        "refinishing",
        "furniture"
    ],
    "wof:name":"Finishing Touch",
    "wof:placetype":"venue"
},
  "geometry": {"coordinates":[-81.200209,35.264337],"type":"Point"}
}