{
  "type": "Feature",
  "properties": {
    "iso:country":"US",
    "sg:address":"1412 Pine Cove Rd",
    "sg:city":"Old Fort",
    "sg:classifiers":[
        {
            "category":"Building & Trades",
            "subcategory":"Construction",
            "type":"Services"
        },
        {
            "category":"Manufacturing",
            "subcategory":"Tools & Machinery",
            "type":"Manufacturing & Wholesale Goods"
        }
    ],
    "sg:phone":"+1 828 668 9177",
    "sg:postcode":"28762",
    "sg:province":"NC",
    "sg:tags":[
        "shop",
        "contractor",
        "machine",
        "industrial",
        "mfg"
    ],
    "wof:name":"W N C Welding & Machine",
    "wof:placetype":"venue"
},
  "geometry": {"coordinates":[-82.187262,35.585326],"type":"Point"}
}