{
  "type": "Feature",
  "properties": {
    "addr:full":"250 Joyceton Church St Lenoir NC 28645",
    "addr:housenumber":"250",
    "addr:postcode":"28645",
    "addr:street":"Joyceton Church St",
    "iso:country":"US",
    "sg:address":"250 Joyceton Church St",
    "sg:city":"Lenoir",
    "sg:classifiers":[
        {
            "category":"Retail",
            "subcategory":"Auto Repair",
            "type":"Services"
        }
    ],
    "sg:phone":"+1 828 728 9949",
    "sg:postcode":"28645",
    "sg:province":"NC",
    "sg:tags":[
        "wrecker"
    ],
    "wof:name":"Tucker's Towing & Auto Repair",
    "wof:placetype":"venue"
},
  "geometry": {"coordinates":[-81.505571,35.871258],"type":"Point"}
}