{
  "type": "Feature",
  "properties": {
    "iso:country":"US",
    "sg:address":"19 Tallent St",
    "sg:city":"Franklin",
    "sg:classifiers":[
        {
            "category":"Shopping",
            "subcategory":"Used Merchandise",
            "type":"Retail Goods"
        }
    ],
    "sg:phone":"+1 828 524 5944",
    "sg:postcode":"28734",
    "sg:province":"NC",
    "wof:name":"Crisps Used Cars-Parts & Salv",
    "wof:placetype":"venue"
},
  "geometry": {"coordinates":[-83.392647,35.173644],"type":"Point"}
}