{
  "type": "Feature",
  "properties": {
    "addr:full":"204 Augusta Ct Havelock NC 28532",
    "addr:housenumber":"204",
    "addr:postcode":"28532",
    "addr:street":"Augusta Ct",
    "iso:country":"US",
    "sg:address":"204 Augusta Ct",
    "sg:city":"Havelock",
    "sg:classifiers":[
        {
            "category":"Manufacturing",
            "subcategory":"Metals",
            "type":"Manufacturing & Wholesale Goods"
        }
    ],
    "sg:phone":"+1 252 444 2492",
    "sg:postcode":"28532",
    "sg:province":"NC",
    "sg:tags":[
        "stampings",
        "mfg"
    ],
    "wof:name":"Creation En Faience",
    "wof:placetype":"venue"
},
  "geometry": {"coordinates":[-76.76128199999999,34.875876],"type":"Point"}
}