{
  "type": "Feature",
  "properties": {
    "addr:full":"6123 Delham Dr Charlotte NC 28215",
    "addr:housenumber":"6123",
    "addr:postcode":"28215",
    "addr:street":"Delham Dr",
    "iso:country":"US",
    "sg:address":"6123 Delham Dr",
    "sg:city":"Charlotte",
    "sg:classifiers":[
        {
            "category":"Real Estate",
            "subcategory":"Real Estate Agent",
            "type":"Services"
        }
    ],
    "sg:phone":"+1 704 536 8422",
    "sg:postcode":"28215",
    "sg:province":"NC",
    "sg:tags":[
        "manager"
    ],
    "wof:name":"Dolly Realty Co",
    "wof:placetype":"venue"
},
  "geometry": {"coordinates":[-80.73896999999999,35.263425],"type":"Point"}
}