{
  "type": "Feature",
  "properties": {
    "addr:full":"973 N Harrison Ave Cary NC 27513",
    "addr:housenumber":"973",
    "addr:postcode":"27513",
    "addr:street":"N Harrison Ave",
    "iso:country":"US",
    "sg:address":"973 N Harrison Ave",
    "sg:city":"Cary",
    "sg:classifiers":[
        {
            "category":"Deli",
            "type":"Food & Drink"
        }
    ],
    "sg:phone":"+1 919 380 8596",
    "sg:postcode":"27513",
    "sg:province":"NC",
    "sg:website":"www.foodlion.com",
    "wof:name":"Food Lion Inc",
    "wof:placetype":"venue"
},
  "geometry": {"coordinates":[-78.783096,35.802502],"type":"Point"}
}