{
  "type": "Feature",
  "properties": {
    "addr:full":"4010 Oleander Dr Wilmington NC 28403",
    "addr:housenumber":"4010",
    "addr:postcode":"28403",
    "addr:street":"Oleander Dr",
    "iso:country":"US",
    "sg:address":"4010 Oleander Dr",
    "sg:city":"Wilmington",
    "sg:classifiers":[
        {
            "category":"Professional",
            "subcategory":"Detective & Security Services",
            "type":"Services"
        }
    ],
    "sg:phone":"+1   ",
    "sg:postcode":"28403",
    "sg:province":"NC",
    "sg:tags":[
        "car",
        "armored"
    ],
    "wof:name":"Loomis Fargo Co",
    "wof:placetype":"venue"
},
  "geometry": {"coordinates":[-77.89667900000001,34.212442],"type":"Point"}
}