{
  "type": "Feature",
  "properties": {
    "iso:country":"US",
    "sg:address":"170 Marble Rd",
    "sg:city":"Statesville",
    "sg:classifiers":[
        {
            "category":"Manufacturing",
            "subcategory":"Retail Goods",
            "type":"Manufacturing & Wholesale Goods"
        }
    ],
    "sg:phone":"+1 704 881 0175",
    "sg:postcode":"28625",
    "sg:province":"NC",
    "sg:tags":[
        "manufacturer"
    ],
    "wof:name":"Labelcraft Industries",
    "wof:placetype":"venue"
},
  "geometry": {"coordinates":[-80.949499,35.800556],"type":"Point"}
}