{
  "type": "Feature",
  "properties": {
    "addr:full":"2704 E Ash St Goldsboro NC 27534",
    "addr:housenumber":"2704",
    "addr:postcode":"27534",
    "addr:street":"E Ash St",
    "iso:country":"US",
    "sg:address":"2704 E Ash St",
    "sg:city":"Goldsboro",
    "sg:classifiers":[
        {
            "category":"Shopping",
            "subcategory":"Used Merchandise",
            "type":"Retail Goods"
        }
    ],
    "sg:phone":"+1 919 778 0104",
    "sg:postcode":"27534",
    "sg:province":"NC",
    "wof:name":"Gasperson Music and Pawn",
    "wof:placetype":"venue"
},
  "geometry": {"coordinates":[-77.95109600000001,35.369865],"type":"Point"}
}