{
  "type": "Feature",
  "properties": {
    "addr:full":"250 Eades Rd Mount Airy NC 27030",
    "addr:housenumber":"250",
    "addr:postcode":"27030",
    "addr:street":"Eades Rd",
    "iso:country":"US",
    "sg:address":"250 Eades Rd",
    "sg:city":"Mount Airy",
    "sg:classifiers":[
        {
            "category":"Building & Trades",
            "subcategory":"Cleaning & Sanitation",
            "type":"Services"
        }
    ],
    "sg:phone":"+1   ",
    "sg:postcode":"27030",
    "sg:province":"NC",
    "sg:tags":[
        "maintenance"
    ],
    "wof:name":"M & J Cleaning Service",
    "wof:placetype":"venue"
},
  "geometry": {"coordinates":[-80.664207,36.534039],"type":"Point"}
}