{
  "type": "Feature",
  "properties": {
    "addr:full":"2621 Springwood Dr Greensboro NC 27403",
    "addr:housenumber":"2621",
    "addr:postcode":"27403",
    "addr:street":"Springwood Dr",
    "iso:country":"US",
    "sg:address":"2621 Springwood Dr",
    "sg:city":"Greensboro",
    "sg:classifiers":[
        {
            "category":"Building & Trades",
            "subcategory":"Construction",
            "type":"Services"
        }
    ],
    "sg:phone":"+1 336 851 0102",
    "sg:postcode":"27403",
    "sg:province":"NC",
    "sg:tags":[
        "house"
    ],
    "wof:name":"CNF Builders Inc",
    "wof:placetype":"venue"
},
  "geometry": {"coordinates":[-79.837897,36.066594],"type":"Point"}
}