{
  "type": "Feature",
  "properties": {
    "iso:country":"US",
    "sg:address":"15217 Bexley Pl",
    "sg:city":"Charlotte",
    "sg:classifiers":[
        {
            "category":"Building & Trades",
            "subcategory":"Plumbing",
            "type":"Services"
        }
    ],
    "sg:phone":"+1 704 545 9117",
    "sg:postcode":"28227",
    "sg:province":"NC",
    "sg:tags":[
        "contractor"
    ],
    "wof:name":"Design Air",
    "wof:placetype":"venue"
},
  "geometry": {"coordinates":[-80.65100700000001,35.144756],"type":"Point"}
}