{
  "type": "Feature",
  "properties": {
    "addr:full":"2800 Friedland Church Rd Winston Salem NC 27107",
    "addr:postcode":"2800;27107",
    "addr:street":"Friedland Church Rd",
    "iso:country":"US",
    "sg:address":"2800 Friedland Church Rd",
    "sg:city":"Winston Salem",
    "sg:classifiers":[
        {
            "category":"Building & Trades",
            "subcategory":"Construction",
            "type":"Services"
        }
    ],
    "sg:phone":"+1 336 749 1180",
    "sg:postcode":"27107",
    "sg:province":"NC",
    "sg:tags":[
        "carpentry",
        "contractor"
    ],
    "wof:name":"Triad Trim Carpentry Inc",
    "wof:placetype":"venue"
},
  "geometry": {"coordinates":[-80.163697,36.063015],"type":"Point"}
}