{
  "type": "Feature",
  "properties": {
    "addr:full":"4625 Creekstone Dr Durham NC 27703",
    "addr:housenumber":"4625",
    "addr:postcode":"27703",
    "addr:street":"Creekstone Dr",
    "iso:country":"US",
    "sg:address":"4625 Creekstone Dr",
    "sg:city":"Durham",
    "sg:classifiers":[
        {
            "category":"Professional",
            "subcategory":"Employment Agencies",
            "type":"Services"
        }
    ],
    "sg:phone":"+1 919 941 1571",
    "sg:postcode":"27703",
    "sg:province":"NC",
    "sg:tags":[
        "temporary"
    ],
    "wof:name":"Manpower",
    "wof:placetype":"venue"
},
  "geometry": {"coordinates":[-78.84702900000001,35.88219],"type":"Point"}
}