{
  "type": "Feature",
  "properties": {
    "addr:full":"2319 Dover Fort Barnwell Rd Dover NC 28526",
    "addr:housenumber":"2319",
    "addr:postcode":"28526",
    "addr:street":"Dover Fort Barnwell Rd",
    "iso:country":"US",
    "sg:address":"2319 Dover Fort Barnwell Rd",
    "sg:city":"Dover",
    "sg:classifiers":[
        {
            "category":"Building & Trades",
            "subcategory":"Landscaping Services",
            "type":"Services"
        }
    ],
    "sg:phone":"+1 252 527 2880",
    "sg:postcode":"28526",
    "sg:province":"NC",
    "sg:tags":[
        "lawn",
        "sod",
        "sodding"
    ],
    "wof:name":"Tarheel Turfgrass Co",
    "wof:placetype":"venue"
},
  "geometry": {"coordinates":[-77.39408,35.276817],"type":"Point"}
}