{
  "type": "Feature",
  "properties": {
    "addr:full":"163 Bumgarner Hollow Dr Taylorsville NC 28681",
    "addr:housenumber":"163",
    "addr:postcode":"28681",
    "addr:street":"Bumgarner Hollow Dr",
    "iso:country":"US",
    "sg:address":"163 Bumgarner Hollow Dr",
    "sg:city":"Taylorsville",
    "sg:classifiers":[
        {
            "category":"Building & Trades",
            "subcategory":"Construction",
            "type":"Services"
        }
    ],
    "sg:phone":"+1 828 632 9367",
    "sg:postcode":"28681",
    "sg:province":"NC",
    "sg:tags":[
        "house"
    ],
    "wof:name":"Davis Constuction Co",
    "wof:placetype":"venue"
},
  "geometry": {"coordinates":[-81.252762,35.973093],"type":"Point"}
}