{
  "type": "Feature",
  "properties": {
    "addr:full":"4076 Grover Smith Rd Grimesland NC 27837",
    "addr:housenumber":"4076",
    "addr:postcode":"27837",
    "addr:street":"Grover Smith Rd",
    "iso:country":"US",
    "sg:address":"4076 Grover Smith Rd",
    "sg:city":"Grimesland",
    "sg:classifiers":[
        {
            "category":"Autos & Motor Vehicles",
            "subcategory":"Fuel & Gas Station",
            "type":"Retail Goods"
        }
    ],
    "sg:phone":"+1 252 746 2656",
    "sg:postcode":"27837",
    "sg:province":"NC",
    "sg:tags":[
        "oil"
    ],
    "wof:name":"Scott's Service Ctr",
    "wof:placetype":"venue"
},
  "geometry": {"coordinates":[-77.253596,35.426718],"type":"Point"}
}