{
  "type": "Feature",
  "properties": {
    "addr:full":"4112 Pleasant Valley Rd Raleigh NC 27612",
    "addr:housenumber":"4112",
    "addr:postcode":"27612",
    "addr:street":"Pleasant Valley Rd",
    "iso:country":"US",
    "sg:address":"4112 Pleasant Valley Rd",
    "sg:city":"Raleigh",
    "sg:classifiers":[
        {
            "category":"Shopping",
            "subcategory":"Mobile Phones",
            "type":"Retail Goods"
        }
    ],
    "sg:phone":"+1 800 274 2538",
    "sg:postcode":"27612",
    "sg:province":"NC",
    "wof:name":"Cricket",
    "wof:placetype":"venue"
},
  "geometry": {"coordinates":[-78.704133,35.860197],"type":"Point"}
}