{
  "type": "Feature",
  "properties": {
    "addr:full":"9513 Jefferson Valley Dr Rural Hall NC 27045",
    "addr:housenumber":"9513",
    "addr:postcode":"27045",
    "addr:street":"Jefferson Valley Dr",
    "iso:country":"US",
    "sg:address":"9513 Jefferson Valley Dr",
    "sg:city":"Rural Hall",
    "sg:classifiers":[
        {
            "category":"Professional",
            "subcategory":"Business Services",
            "type":"Services"
        }
    ],
    "sg:phone":"+1 336 969 0444",
    "sg:postcode":"27045",
    "sg:province":"NC",
    "sg:tags":[
        "embroidery"
    ],
    "wof:name":"Logowear",
    "wof:placetype":"venue"
},
  "geometry": {"coordinates":[-80.332404,36.254045],"type":"Point"}
}