{
  "type": "Feature",
  "properties": {
    "addr:full":"2419 Jefferson Ave Gastonia NC 28056",
    "addr:housenumber":"2419",
    "addr:postcode":"28056",
    "addr:street":"Jefferson Ave",
    "iso:country":"US",
    "sg:address":"2419 Jefferson Ave",
    "sg:city":"Gastonia",
    "sg:classifiers":[
        {
            "category":"Banks & Credit Unions",
            "subcategory":"Financial Services",
            "type":"Services"
        }
    ],
    "sg:phone":"+1 704 865 9007",
    "sg:postcode":"28056",
    "sg:province":"NC",
    "sg:tags":[
        "investor"
    ],
    "wof:name":"MBA Investments LLC",
    "wof:placetype":"venue"
},
  "geometry": {"coordinates":[-81.107074,35.24619],"type":"Point"}
}