{
  "type": "Feature",
  "properties": {
    "addr:full":"135 Duke Marine Lab Rd Beaufort NC 28516",
    "addr:housenumber":"135",
    "addr:postcode":"28516",
    "addr:street":"Duke;Lab Rd",
    "iso:country":"US",
    "sg:address":"135 Duke Marine Lab Rd",
    "sg:city":"Beaufort",
    "sg:classifiers":[
        {
            "category":"Education",
            "subcategory":"Library",
            "type":"Public Place"
        }
    ],
    "sg:phone":"+1 252 504 7510",
    "sg:postcode":"28516",
    "sg:province":"NC",
    "wof:name":"Pearse Memorial Library",
    "wof:placetype":"venue"
},
  "geometry": {"coordinates":[-76.67200099999999,34.715923],"type":"Point"}
}