{
  "type": "Feature",
  "properties": {
    "iso:country":"US",
    "sg:address":"207 Heathridge Ln",
    "sg:city":"Cary",
    "sg:classifiers":[
        {
            "category":"Real Estate",
            "subcategory":"Real Estate Agent",
            "type":"Services"
        }
    ],
    "sg:phone":"+1 919 319 3693",
    "sg:postcode":"27513",
    "sg:province":"NC",
    "wof:name":"John I Harris Remax United",
    "wof:placetype":"venue"
},
  "geometry": {"coordinates":[-78.834806,35.770547],"type":"Point"}
}