{
  "type": "Feature",
  "properties": {
    "iso:country":"US",
    "sg:address":"1200 N Lake Park Blvd",
    "sg:city":"Carolina Beach",
    "sg:classifiers":[
        {
            "category":"Retail",
            "subcategory":"Car Wash",
            "type":"Services"
        }
    ],
    "sg:phone":"+1 910 458 3395",
    "sg:postcode":"28428",
    "sg:province":"NC",
    "wof:name":"Coastal Carolina Car Wash",
    "wof:placetype":"venue"
},
  "geometry": {"coordinates":[-77.89919999999999,34.046902],"type":"Point"}
}