{
  "type": "Feature",
  "properties": {
    "addr:full":"4345 Fescue Pl SW Concord NC 28027",
    "addr:housenumber":"4345",
    "addr:postcode":"28027",
    "addr:street":"Fescue Pl Sw",
    "iso:country":"US",
    "sg:address":"4345 Fescue Pl SW",
    "sg:city":"Concord",
    "sg:classifiers":[
        {
            "category":"Home & Garden",
            "subcategory":"Home Furnishings",
            "type":"Retail Goods"
        }
    ],
    "sg:phone":"+1 704 723 6712",
    "sg:postcode":"28027",
    "sg:province":"NC",
    "sg:tags":[
        "venetian",
        "blind"
    ],
    "wof:name":"Blind & Shutter Depot",
    "wof:placetype":"venue"
},
  "geometry": {"coordinates":[-80.641791,35.347315],"type":"Point"}
}