{
  "type": "Feature",
  "properties": {
    "iso:country":"US",
    "sg:address":"1600 N Main St",
    "sg:city":"High Point",
    "sg:classifiers":[
        {
            "category":"Shopping",
            "subcategory":"Crafts & Fabrics",
            "type":"Retail Goods"
        }
    ],
    "sg:phone":"+1 336 887 6668",
    "sg:postcode":"27262",
    "sg:province":"NC",
    "sg:tags":[
        "sewing"
    ],
    "wof:name":"Fabric & Trim On Main",
    "wof:placetype":"venue"
},
  "geometry": {"coordinates":[-80.01952799999999,35.976684],"type":"Point"}
}