{
  "type": "Feature",
  "properties": {
    "iso:country":"US",
    "sg:address":"916 Roanoke Ave",
    "sg:city":"Roanoke Rapids",
    "sg:classifiers":[
        {
            "category":"Manufacturing",
            "subcategory":"Printing",
            "type":"Manufacturing & Wholesale Goods"
        }
    ],
    "sg:phone":"+1 252 537 2505",
    "sg:postcode":"27870",
    "sg:province":"NC",
    "sg:tags":[
        "newspaper"
    ],
    "wof:name":"Herald",
    "wof:placetype":"venue"
},
  "geometry": {"coordinates":[-77.65648899999999,36.457514],"type":"Point"}
}