{
  "type": "Feature",
  "properties": {
    "iso:country":"US",
    "sg:address":"4209 Arcadia Dr SW",
    "sg:city":"Shallotte",
    "sg:classifiers":[
        {
            "category":"Organizations",
            "subcategory":"Religious Organization",
            "type":"Services"
        }
    ],
    "sg:phone":"+1 910 443 7856",
    "sg:postcode":"28470",
    "sg:province":"NC",
    "sg:tags":[
        "house"
    ],
    "wof:name":"Covenant Construction",
    "wof:placetype":"venue"
},
  "geometry": {"coordinates":[-78.38816799999999,33.936378],"type":"Point"}
}