{
  "type": "Feature",
  "properties": {
    "iso:country":"US",
    "sg:address":"114 Ivy Brook Ln",
    "sg:city":"Chapel Hill",
    "sg:classifiers":[
        {
            "category":"Professional",
            "type":"Services"
        }
    ],
    "sg:phone":"+1 919 968 0491",
    "sg:postcode":"27516",
    "sg:province":"NC",
    "wof:name":"Alfonse Lopez",
    "wof:placetype":"venue"
},
  "geometry": {"coordinates":[-79.07265599999999,35.890868],"type":"Point"}
}