{
  "type": "Feature",
  "properties": {
    "iso:country":"US",
    "sg:address":"214 N Academy St",
    "sg:city":"Mooresville",
    "sg:classifiers":[
        {
            "category":"Social Services",
            "type":"Services"
        }
    ],
    "sg:phone":"+1 704 664 4915",
    "sg:postcode":"28115",
    "sg:province":"NC",
    "sg:tags":[
        "senior",
        "citizen"
    ],
    "wof:name":"Iredell Co Council On Aging",
    "wof:placetype":"venue"
},
  "geometry": {"coordinates":[-80.811696,35.585995],"type":"Point"}
}