{
  "type": "Feature",
  "properties": {
    "iso:country":"US",
    "sg:address":"20 W A St",
    "sg:city":"Newton",
    "sg:classifiers":[
        {
            "category":"Personal",
            "subcategory":"Beauty Salon",
            "type":"Services"
        }
    ],
    "sg:phone":"+1 828 464 2563",
    "sg:postcode":"28658",
    "sg:province":"NC",
    "wof:name":"Eva's Beauty Salon",
    "wof:placetype":"venue"
},
  "geometry": {"coordinates":[-81.223366,35.663103],"type":"Point"}
}