{
  "type": "Feature",
  "properties": {
    "addr:full":"2982 Trailwood Dr SE Southport NC 28461",
    "addr:housenumber":"2982",
    "addr:postcode":"28461",
    "addr:street":"Trailwood Dr Se",
    "iso:country":"US",
    "sg:address":"2982 Trailwood Dr SE",
    "sg:city":"Southport",
    "sg:classifiers":[
        {
            "category":"Professional",
            "subcategory":"Management & Consulting",
            "type":"Services"
        }
    ],
    "sg:phone":"+1   ",
    "sg:postcode":"28461",
    "sg:province":"NC",
    "wof:name":"Buhay Management Inc",
    "wof:placetype":"venue"
},
  "geometry": {"coordinates":[-78.113398,33.932272],"type":"Point"}
}