{
  "type": "Feature",
  "properties": {
    "addr:full":"400 Weeks St Clinton NC 28328",
    "addr:housenumber":"400",
    "addr:postcode":"28328",
    "addr:street":"Weeks St",
    "iso:country":"US",
    "sg:address":"400 Weeks St",
    "sg:city":"Clinton",
    "sg:classifiers":[
        {
            "category":"Social Services",
            "subcategory":"Child Care",
            "type":"Services"
        }
    ],
    "sg:phone":"+1   ",
    "sg:postcode":"28328",
    "sg:province":"NC",
    "sg:tags":[
        "day"
    ],
    "wof:name":"Annies Daycare",
    "wof:placetype":"venue"
},
  "geometry": {"coordinates":[-78.310028,34.990629],"type":"Point"}
}