{
  "type": "Feature",
  "properties": {
    "iso:country":"US",
    "sg:address":"2537 S Saunders St",
    "sg:city":"Raleigh",
    "sg:classifiers":[
        {
            "category":"Utilities",
            "subcategory":"Mobile Phone",
            "type":"Services"
        }
    ],
    "sg:phone":"+1 919 546 9658",
    "sg:postcode":"27603",
    "sg:province":"NC",
    "sg:tags":[
        "telephone",
        "cellular"
    ],
    "wof:name":"Sc Kiosk Inc",
    "wof:placetype":"venue"
},
  "geometry": {"coordinates":[-78.64900299999999,35.7507],"type":"Point"}
}