{
  "type": "Feature",
  "properties": {
    "iso:country":"US",
    "sg:address":"5301 N Sharon Amity Rd",
    "sg:city":"Charlotte",
    "sg:classifiers":[
        {
            "category":"Freight",
            "type":"Transportation"
        }
    ],
    "sg:phone":"+1 704 535 6789",
    "sg:postcode":"28215",
    "sg:province":"NC",
    "sg:tags":[
        "commercial",
        "storage"
    ],
    "wof:name":"Shur Gard Self Storage",
    "wof:placetype":"venue"
},
  "geometry": {"coordinates":[-80.74078299999999,35.231134],"type":"Point"}
}