{
  "type": "Feature",
  "properties": {
    "iso:country":"US",
    "sg:address":"409 Wildwood Dr",
    "sg:city":"Durham",
    "sg:classifiers":[
        {
            "category":"Professional",
            "subcategory":"Advertising",
            "type":"Services"
        }
    ],
    "sg:phone":"+1   ",
    "sg:postcode":"27712",
    "sg:province":"NC",
    "sg:tags":[
        "agency"
    ],
    "wof:name":"Raineys Marketing",
    "wof:placetype":"venue"
},
  "geometry": {"coordinates":[-78.919588,36.072754],"type":"Point"}
}