{
  "type": "Feature",
  "properties": {
    "addr:full":"146 Ruffin School Rd Ruffin NC 27326",
    "addr:housenumber":"146",
    "addr:postcode":"27326",
    "addr:street":"Ruffin School Rd",
    "iso:country":"US",
    "sg:address":"146 Ruffin School Rd",
    "sg:city":"Ruffin",
    "sg:classifiers":[
        {
            "category":"Building & Trades",
            "subcategory":"Construction",
            "type":"Services"
        }
    ],
    "sg:phone":"+1 336 939 7684",
    "sg:postcode":"27326",
    "sg:province":"NC",
    "sg:tags":[
        "asbestos",
        "removal"
    ],
    "wof:name":"Webster Environmental Inc",
    "wof:placetype":"venue"
},
  "geometry": {"coordinates":[-79.536503,36.45047],"type":"Point"}
}