{
  "type": "Feature",
  "properties": {
    "addr:full":"5241 Sunset Walk Ln Holly Springs NC 27540",
    "addr:housenumber":"5241",
    "addr:postcode":"27540",
    "addr:street":"Sunset Walk Ln",
    "iso:country":"US",
    "sg:address":"5241 Sunset Walk Ln",
    "sg:city":"Holly Springs",
    "sg:classifiers":[
        {
            "category":"Shopping",
            "subcategory":"Musical Instruments",
            "type":"Retail Goods"
        }
    ],
    "sg:phone":"+1 919 303 5556",
    "sg:postcode":"27540",
    "sg:province":"NC",
    "sg:tags":[
        "music",
        "dealer"
    ],
    "wof:name":"Music Academy",
    "wof:placetype":"venue"
},
  "geometry": {"coordinates":[-78.81627899999999,35.649479],"type":"Point"}
}