{
  "type": "Feature",
  "properties": {
    "iso:country":"US",
    "sg:address":"196 Bethany Woods Dr",
    "sg:city":"Summerfield",
    "sg:classifiers":[
        {
            "category":"Home & Garden",
            "subcategory":"Building Materials",
            "type":"Retail Goods"
        }
    ],
    "sg:phone":"+1 336 951 2064",
    "sg:postcode":"27358",
    "sg:province":"NC",
    "wof:name":"Sherwin-Williams",
    "wof:placetype":"venue"
},
  "geometry": {"coordinates":[-79.83469599999999,36.290883],"type":"Point"}
}