{
  "type": "Feature",
  "properties": {
    "iso:country":"US",
    "sg:address":"2101 S New Hope Rd",
    "sg:city":"Gastonia",
    "sg:classifiers":[
        {
            "category":"Health Services",
            "subcategory":"Doctor",
            "type":"Services"
        }
    ],
    "sg:phone":"+1 704 865 3145",
    "sg:postcode":"28054",
    "sg:province":"NC",
    "sg:tags":[
        "dentist"
    ],
    "wof:name":"John T Walsh & Assoc",
    "wof:placetype":"venue"
},
  "geometry": {"coordinates":[-81.12720299999999,35.242304],"type":"Point"}
}