{
  "type": "Feature",
  "properties": {
    "addr:full":"5808 Falstaff Dr Charlotte NC 28227",
    "addr:housenumber":"5808",
    "addr:postcode":"28227",
    "addr:street":"Falstaff Dr",
    "iso:country":"US",
    "sg:address":"5808 Falstaff Dr",
    "sg:city":"Charlotte",
    "sg:classifiers":[
        {
            "category":"Freight",
            "type":"Transportation"
        }
    ],
    "sg:phone":"+1 704 568 2911",
    "sg:postcode":"28227",
    "sg:province":"NC",
    "sg:tags":[
        "operator",
        "local",
        "trucking"
    ],
    "wof:name":"Falstaff Trucking Inc",
    "wof:placetype":"venue"
},
  "geometry": {"coordinates":[-80.703603,35.22008],"type":"Point"}
}