{
  "type": "Feature",
  "properties": {
    "iso:country":"US",
    "sg:address":"102 Seth Thomas Ln",
    "sg:city":"Swansboro",
    "sg:classifiers":[
        {
            "category":"Professional",
            "type":"Services"
        }
    ],
    "sg:phone":"+1 910 326 1344",
    "sg:postcode":"28584",
    "sg:province":"NC",
    "sg:tags":[
        "establishment"
    ],
    "wof:name":"Serv Pro Of Carteret E Onslow",
    "wof:placetype":"venue"
},
  "geometry": {"coordinates":[-77.159183,34.706884],"type":"Point"}
}