{
  "type": "Feature",
  "properties": {
    "addr:full":"327 E Sunset Blvd Cove City NC 28523",
    "addr:housenumber":"327",
    "addr:postcode":"28523",
    "addr:street":"E Sunset Blvd Cove",
    "iso:country":"US",
    "sg:address":"327 E Sunset Blvd",
    "sg:city":"Cove City",
    "sg:classifiers":[
        {
            "category":"Building & Trades",
            "subcategory":"Plumbing",
            "type":"Services"
        }
    ],
    "sg:phone":"+1 252 637 6344",
    "sg:postcode":"28523",
    "sg:province":"NC",
    "sg:tags":[
        "septic"
    ],
    "wof:name":"C & B Septic Tank Pumping",
    "wof:placetype":"venue"
},
  "geometry": {"coordinates":[-77.313523,35.185113],"type":"Point"}
}