{
  "type": "Feature",
  "properties": {
    "addr:full":"16225 Leeward Ln Huntersville NC 28078",
    "addr:housenumber":"16225",
    "addr:postcode":"28078",
    "addr:street":"Leeward Ln",
    "iso:country":"US",
    "sg:address":"16225 Leeward Ln",
    "sg:city":"Huntersville",
    "sg:classifiers":[
        {
            "category":"Professional",
            "subcategory":"Business Services",
            "type":"Services"
        }
    ],
    "sg:phone":"+1   ",
    "sg:postcode":"28078",
    "sg:province":"NC",
    "wof:name":"Schrader Design Inc",
    "wof:placetype":"venue"
},
  "geometry": {"coordinates":[-80.911871,35.435325],"type":"Point"}
}