{
  "type": "Feature",
  "properties": {
    "addr:full":"431 Vance St NW Lenoir NC 28645",
    "addr:housenumber":"431",
    "addr:postcode":"28645",
    "addr:street":"Vance St Nw",
    "iso:country":"US",
    "sg:address":"431 Vance St NW",
    "sg:city":"Lenoir",
    "sg:classifiers":[
        {
            "category":"Real Estate",
            "subcategory":"Real Estate Agent",
            "type":"Services"
        }
    ],
    "sg:phone":"+1 828 758 5536",
    "sg:postcode":"28645",
    "sg:province":"NC",
    "sg:tags":[
        "authorities",
        "housing"
    ],
    "wof:name":"Lenoir Housing Authority",
    "wof:placetype":"venue"
},
  "geometry": {"coordinates":[-81.543468,35.9174],"type":"Point"}
}