{
  "type": "Feature",
  "properties": {
    "iso:country":"US",
    "sg:address":"1104 Stonebridge Dr",
    "sg:city":"Durham",
    "sg:classifiers":[
        {
            "category":"Wholesale",
            "subcategory":"Durable Goods & Equipment",
            "type":"Manufacturing & Wholesale Goods"
        }
    ],
    "sg:phone":"+1 919 620 0444",
    "sg:postcode":"27712",
    "sg:province":"NC",
    "wof:name":"Riverbend Antiques",
    "wof:placetype":"venue"
},
  "geometry": {"coordinates":[-78.862094,36.125166],"type":"Point"}
}