{
  "type": "Feature",
  "properties": {
    "iso:country":"US",
    "sg:address":"2 Regent Park Blvd",
    "sg:city":"Asheville",
    "sg:classifiers":[
        {
            "category":"Restaurant",
            "type":"Food & Drink"
        }
    ],
    "sg:menulink":"http://www.allmenus.com/nc/asheville/116973-green-tea/menu/",
    "sg:phone":"+1 828 252 8300",
    "sg:postcode":"28806",
    "sg:province":"NC",
    "sg:tags":[
        "japanese",
        "asian"
    ],
    "wof:name":"Green Tea",
    "wof:placetype":"venue"
},
  "geometry": {"coordinates":[-82.58196700000001,35.588789],"type":"Point"}
}