{
  "type": "Feature",
  "properties": {
    "iso:country":"US",
    "sg:address":"922 Highland Ave NE",
    "sg:city":"Hickory",
    "sg:classifiers":[
        {
            "category":"Autos & Motor Vehicles",
            "subcategory":"Automobile Sales",
            "type":"Retail Goods"
        }
    ],
    "sg:phone":"+1 828 310 4770",
    "sg:postcode":"28601",
    "sg:province":"NC",
    "sg:tags":[
        "used"
    ],
    "wof:name":"Buy Right Auto Inc",
    "wof:placetype":"venue"
},
  "geometry": {"coordinates":[-81.317639,35.73973],"type":"Point"}
}