{
  "type": "Feature",
  "properties": {
    "addr:full":"483 River Rd Wallace NC 28466",
    "addr:housenumber":"483",
    "addr:postcode":"28466",
    "addr:street":"River Rd",
    "iso:country":"US",
    "sg:address":"483 River Rd",
    "sg:city":"Wallace",
    "sg:classifiers":[
        {
            "category":"Building & Trades",
            "subcategory":"Pest Control",
            "type":"Services"
        }
    ],
    "sg:phone":"+1 910 285 5980",
    "sg:postcode":"28466",
    "sg:province":"NC",
    "sg:tags":[
        "exterminating"
    ],
    "wof:name":"Murry Exterminating Company",
    "wof:placetype":"venue"
},
  "geometry": {"coordinates":[-77.95279499999999,34.732582],"type":"Point"}
}