{
  "type": "Feature",
  "properties": {
    "addr:full":"8111 Creedmoor Rd Raleigh NC 27613",
    "addr:housenumber":"8111",
    "addr:postcode":"27613",
    "addr:street":"Creedmoor Rd",
    "iso:country":"US",
    "sg:address":"8111 Creedmoor Rd",
    "sg:city":"Raleigh",
    "sg:classifiers":[
        {
            "category":"Restaurant",
            "type":"Food & Drink"
        }
    ],
    "sg:menulink":"http://www.allmenus.com/nc/leesville/73365-pizza-hut/menu/",
    "sg:phone":"+1 919 848 9890",
    "sg:postcode":"27613",
    "sg:province":"NC",
    "sg:tags":[
        "american",
        "pizza"
    ],
    "wof:name":"Pizza Hut",
    "wof:placetype":"venue"
},
  "geometry": {"coordinates":[-78.68247599999999,35.898475],"type":"Point"}
}