{
  "type": "Feature",
  "properties": {
    "iso:country":"US",
    "sg:address":"50 Formosa Dr",
    "sg:city":"Marshall",
    "sg:classifiers":[
        {
            "category":"Farming",
            "subcategory":"Farm",
            "type":"Manufacturing & Wholesale Goods"
        }
    ],
    "sg:phone":"+1 828 649 3211",
    "sg:postcode":"28752",
    "sg:province":"NC",
    "sg:tags":[
        "crop",
        "animal",
        "general"
    ],
    "wof:name":"Z Herbert Ponder",
    "wof:placetype":"venue"
},
  "geometry": {"coordinates":[-82.075233,35.544682],"type":"Point"}
}