{
  "type": "Feature",
  "properties": {
    "iso:country":"US",
    "sg:address":"1512 Zoo Pkwy",
    "sg:city":"Asheboro",
    "sg:classifiers":[
        {
            "category":"Shopping",
            "subcategory":"Clothing, Apparel, & Fashions",
            "type":"Retail Goods"
        }
    ],
    "sg:phone":"+1 336 625 4663",
    "sg:postcode":"27205",
    "sg:province":"NC",
    "wof:name":"Top2 Bottom Fashion",
    "wof:placetype":"venue"
},
  "geometry": {"coordinates":[-79.80958099999999,35.686994],"type":"Point"}
}