{
  "type": "Feature",
  "properties": {
    "addr:full":"110 Matthews Station St Matthews NC 28105",
    "addr:housenumber":"110",
    "addr:postcode":"28105",
    "addr:street":"Matthews Station",
    "iso:country":"US",
    "sg:address":"110 Matthews Station St",
    "sg:city":"Matthews",
    "sg:classifiers":[
        {
            "category":"Banks & Credit Unions",
            "subcategory":"Bank",
            "type":"Services"
        }
    ],
    "sg:phone":"+1 704 686 1770",
    "sg:postcode":"28105",
    "sg:province":"NC",
    "sg:website":"www.centura.com",
    "wof:name":"RBC Centura Bank",
    "wof:placetype":"venue"
},
  "geometry": {"coordinates":[-80.720448,35.117242],"type":"Point"}
}