{
  "type": "Feature",
  "properties": {
    "iso:country":"US",
    "sg:address":"4414 Lake Boone Trl Ste 210",
    "sg:city":"Raleigh",
    "sg:classifiers":[
        {
            "category":"Health Services",
            "subcategory":"Doctor",
            "type":"Services"
        }
    ],
    "sg:phone":"+1 919 571 1040",
    "sg:postcode":"27607",
    "sg:province":"NC",
    "sg:tags":[
        "obstetrician",
        "gynecologist"
    ],
    "sg:website":"www.wilkersonobgyn.com",
    "wof:name":"Wilkerson Obstetrics & Gynecology PA",
    "wof:placetype":"venue"
},
  "geometry": {"coordinates":[-78.701291,35.817361],"type":"Point"}
}