{
  "type": "Feature",
  "properties": {
    "addr:full":"103 Cascade Rd Mooresville NC 28115",
    "addr:housenumber":"103",
    "addr:postcode":"28115",
    "addr:street":"Cascade Rd",
    "iso:country":"US",
    "sg:address":"103 Cascade Rd",
    "sg:city":"Mooresville",
    "sg:classifiers":[
        {
            "category":"Organizations",
            "subcategory":"Religious Organization",
            "type":"Services"
        }
    ],
    "sg:phone":"+1 704 663 3974",
    "sg:postcode":"28115",
    "sg:province":"NC",
    "sg:tags":[
        "church"
    ],
    "wof:name":"Watkins Chapel AME Zion Chr",
    "wof:placetype":"venue"
},
  "geometry": {"coordinates":[-80.812242,35.60164],"type":"Point"}
}