{
  "type": "Feature",
  "properties": {
    "addr:full":"611 Woodland Dr Rockwell NC 28138",
    "addr:housenumber":"611",
    "addr:postcode":"28138",
    "addr:street":"Woodland Dr",
    "iso:country":"US",
    "sg:address":"611 Woodland Dr",
    "sg:city":"Rockwell",
    "sg:classifiers":[
        {
            "category":"Freight",
            "type":"Transportation"
        }
    ],
    "sg:phone":"+1 704 279 8683",
    "sg:postcode":"28138",
    "sg:province":"NC",
    "sg:tags":[
        "operator",
        "local",
        "trucking"
    ],
    "wof:name":"Del Ron Trucking Inc",
    "wof:placetype":"venue"
},
  "geometry": {"coordinates":[-80.413274,35.545642],"type":"Point"}
}