{
  "type": "Feature",
  "properties": {
    "iso:country":"US",
    "sg:address":"1525 Lisbon Ln",
    "sg:city":"Charlotte",
    "sg:classifiers":[
        {
            "category":"Restaurant",
            "type":"Food & Drink"
        }
    ],
    "sg:phone":"+1 704 598 6252",
    "sg:postcode":"28269",
    "sg:province":"NC",
    "sg:tags":[
        "eating",
        "product",
        "dairy"
    ],
    "wof:name":"Carmens Ice Cream Parlor",
    "wof:placetype":"venue"
},
  "geometry": {"coordinates":[-80.795063,35.284161],"type":"Point"}
}