{
  "type": "Feature",
  "properties": {
    "iso:country":"US",
    "sg:address":"209 Lost Tree Ln",
    "sg:city":"Cary",
    "sg:classifiers":[
        {
            "category":"Banks & Credit Unions",
            "subcategory":"Financial Services",
            "type":"Services"
        }
    ],
    "sg:phone":"+1 919 469 2596",
    "sg:postcode":"27513",
    "sg:province":"NC",
    "sg:tags":[
        "trust",
        "management"
    ],
    "wof:name":"Folsom Family Trust",
    "wof:placetype":"venue"
},
  "geometry": {"coordinates":[-78.829594,35.762311],"type":"Point"}
}