{
  "type": "Feature",
  "properties": {
    "iso:country":"US",
    "sg:address":"4371 State Hwy 49",
    "sg:city":"Burlington",
    "sg:classifiers":[
        {
            "category":"Retail",
            "subcategory":"Laundry & Dry Cleaning",
            "type":"Services"
        }
    ],
    "sg:phone":"+1   ",
    "sg:postcode":"27217",
    "sg:province":"NC",
    "wof:name":"Basons Superior Carpet Clg",
    "wof:placetype":"venue"
},
  "geometry": {"coordinates":[-79.322678,36.191382],"type":"Point"}
}