{
  "type": "Feature",
  "properties": {
    "addr:full":"2128 Burnett Blvd Wilmington NC 28401",
    "addr:housenumber":"2128",
    "addr:postcode":"28401",
    "addr:street":"Burnett Blvd",
    "iso:country":"US",
    "sg:address":"2128 Burnett Blvd",
    "sg:city":"Wilmington",
    "sg:classifiers":[
        {
            "category":"Freight",
            "type":"Transportation"
        }
    ],
    "sg:phone":"+1 910 342 0407",
    "sg:postcode":"28401",
    "sg:province":"NC",
    "sg:tags":[
        "broker",
        "customs"
    ],
    "sg:website":"www.utcoverseas.com",
    "wof:name":"UTC",
    "wof:placetype":"venue"
},
  "geometry": {"coordinates":[-77.94942,34.199296],"type":"Point"}
}