{
  "type": "Feature",
  "properties": {
    "iso:country":"US",
    "sg:address":"2800 Pine Lake Dr",
    "sg:city":"Greensboro",
    "sg:classifiers":[
        {
            "category":"Building & Trades",
            "subcategory":"Construction",
            "type":"Services"
        }
    ],
    "sg:phone":"+1 336 294 7113",
    "sg:postcode":"27407",
    "sg:province":"NC",
    "sg:tags":[
        "residential"
    ],
    "wof:name":"AKR Builders",
    "wof:placetype":"venue"
},
  "geometry": {"coordinates":[-79.842775,36.020773],"type":"Point"}
}