{
  "type": "Feature",
  "properties": {
    "iso:country":"US",
    "sg:address":"437 S Center St",
    "sg:city":"Statesville",
    "sg:classifiers":[
        {
            "category":"Personal",
            "subcategory":"Beauty Salon",
            "type":"Services"
        }
    ],
    "sg:phone":"+1 704 871 9330",
    "sg:postcode":"28677",
    "sg:province":"NC",
    "wof:name":"Salon Tee-Jewel",
    "wof:placetype":"venue"
},
  "geometry": {"coordinates":[-80.886357,35.780932],"type":"Point"}
}