{
  "type": "Feature",
  "properties": {
    "iso:country":"US",
    "sg:address":"4820 Copperfield Dr",
    "sg:city":"Gastonia",
    "sg:classifiers":[
        {
            "category":"Professional",
            "subcategory":"Management & Consulting",
            "type":"Services"
        }
    ],
    "sg:phone":"+1   ",
    "sg:postcode":"28056",
    "sg:province":"NC",
    "sg:tags":[
        "business"
    ],
    "wof:name":"Lezlie Hill",
    "wof:placetype":"venue"
},
  "geometry": {"coordinates":[-81.145169,35.171104],"type":"Point"}
}