{
  "type": "Feature",
  "properties": {
    "addr:full":"1066 Bethany Church Rd Winston Salem NC 27107",
    "addr:housenumber":"1066",
    "addr:postcode":"27107",
    "addr:street":"Bethany Church Rd",
    "iso:country":"US",
    "sg:address":"1066 Bethany Church Rd",
    "sg:city":"Winston Salem",
    "sg:classifiers":[
        {
            "category":"Organizations",
            "subcategory":"Religious Organization",
            "type":"Services"
        }
    ],
    "sg:phone":"+1 336 769 2943",
    "sg:postcode":"27107",
    "sg:province":"NC",
    "sg:tags":[
        "church"
    ],
    "wof:name":"Bethany United Church Christ",
    "wof:placetype":"venue"
},
  "geometry": {"coordinates":[-80.164715,35.957568],"type":"Point"}
}