{
  "type": "Feature",
  "properties": {
    "iso:country":"US",
    "sg:address":"225 Gay St",
    "sg:city":"Kannapolis",
    "sg:classifiers":[
        {
            "category":"Recreation",
            "type":"Entertainment"
        }
    ],
    "sg:phone":"+1 704 933 0123",
    "sg:postcode":"28081",
    "sg:province":"NC",
    "sg:tags":[
        "martial",
        "arts",
        "instruction"
    ],
    "wof:name":"Mussington's Karate",
    "wof:placetype":"venue"
},
  "geometry": {"coordinates":[-80.630292,35.488891],"type":"Point"}
}