{
  "type": "Feature",
  "properties": {
    "addr:full":"1212 Turrentine St Burlington NC 27215",
    "addr:housenumber":"1212",
    "addr:postcode":"27215",
    "addr:street":"Turrentine St",
    "iso:country":"US",
    "sg:address":"1212 Turrentine St",
    "sg:city":"Burlington",
    "sg:classifiers":[
        {
            "category":"Social Services",
            "type":"Services"
        }
    ],
    "sg:phone":"+1 336 513 4335",
    "sg:postcode":"27215",
    "sg:province":"NC",
    "wof:name":"Adau",
    "wof:placetype":"venue"
},
  "geometry": {"coordinates":[-79.43262,36.076069],"type":"Point"}
}