{
  "type": "Feature",
  "properties": {
    "addr:full":"272 Dot Dr Asheboro NC 27205",
    "addr:housenumber":"272",
    "addr:postcode":"27205",
    "addr:street":"Dot Dr",
    "iso:country":"US",
    "sg:address":"272 Dot Dr",
    "sg:city":"Asheboro",
    "sg:classifiers":[
        {
            "category":"Government",
            "subcategory":"Office",
            "type":"Public Place"
        }
    ],
    "sg:phone":"+1 336 625 1309",
    "sg:postcode":"27205",
    "sg:province":"NC",
    "wof:name":"Transportation-Resident Engr",
    "wof:placetype":"venue"
},
  "geometry": {"coordinates":[-79.824237,35.667693],"type":"Point"}
}