{
  "type": "Feature",
  "properties": {
    "addr:full":"953 Freedom Way Hubert NC 28539",
    "addr:housenumber":"953",
    "addr:postcode":"28539",
    "addr:street":"Freedom Way",
    "iso:country":"US",
    "sg:address":"953 Freedom Way",
    "sg:city":"Hubert",
    "sg:classifiers":[
        {
            "category":"Retail",
            "subcategory":"Auto Repair",
            "type":"Services"
        }
    ],
    "sg:phone":"+1   ",
    "sg:postcode":"28539",
    "sg:province":"NC",
    "sg:tags":[
        "general"
    ],
    "wof:name":"AGW Automotive",
    "wof:placetype":"venue"
},
  "geometry": {"coordinates":[-77.29279699999999,34.709681],"type":"Point"}
}