{
  "type": "Feature",
  "properties": {
    "addr:full":"1420 E Arlington Blvd Greenville NC 27858",
    "addr:housenumber":"1420",
    "addr:postcode":"27858",
    "addr:street":"E Arlington Blvd",
    "iso:country":"US",
    "sg:address":"1420 E Arlington Blvd",
    "sg:city":"Greenville",
    "sg:classifiers":[
        {
            "category":"Professional",
            "subcategory":"Research",
            "type":"Services"
        }
    ],
    "sg:phone":"+1 252 752 0200",
    "sg:postcode":"27858",
    "sg:province":"NC",
    "sg:tags":[
        "environmental",
        "ecological"
    ],
    "wof:name":"CBM Environmental Svc",
    "wof:placetype":"venue"
},
  "geometry": {"coordinates":[-77.36051999999999,35.573746],"type":"Point"}
}