{
  "type": "Feature",
  "properties": {
    "iso:country":"US",
    "sg:address":"712 S Salisbury Ave",
    "sg:city":"Spencer",
    "sg:classifiers":[
        {
            "category":"Autos & Motor Vehicles",
            "subcategory":"Fuel & Gas Station",
            "type":"Retail Goods"
        }
    ],
    "sg:phone":"+1 704 637 1415",
    "sg:postcode":"28159",
    "sg:province":"NC",
    "sg:tags":[
        "oil"
    ],
    "wof:name":"Bobby's Mobil Svc",
    "wof:placetype":"venue"
},
  "geometry": {"coordinates":[-80.437883,35.686578],"type":"Point"}
}