{
  "type": "Feature",
  "properties": {
    "addr:full":"117 Edinburgh Dr Cary NC 27511",
    "addr:housenumber":"117",
    "addr:postcode":"27511",
    "addr:street":"Edinburgh Dr",
    "iso:country":"US",
    "sg:address":"117 Edinburgh Dr",
    "sg:city":"Cary",
    "sg:classifiers":[
        {
            "category":"Health Services",
            "subcategory":"Clinic",
            "type":"Services"
        },
        {
            "category":"Professional",
            "subcategory":"Employment Agencies",
            "type":"Services"
        }
    ],
    "sg:phone":"+1   ",
    "sg:postcode":"27511",
    "sg:province":"NC",
    "sg:tags":[
        "help",
        "staffing",
        "supply"
    ],
    "wof:name":"Kelly Services",
    "wof:placetype":"venue"
},
  "geometry": {"coordinates":[-78.798258,35.741756],"type":"Point"}
}