{
  "type": "Feature",
  "properties": {
    "addr:full":"6655 University Pkwy Rural Hall NC 27045",
    "addr:housenumber":"6655",
    "addr:postcode":"27045",
    "addr:street":"University Pkwy Rural Hall",
    "iso:country":"US",
    "sg:address":"6655 University Pkwy",
    "sg:city":"Rural Hall",
    "sg:classifiers":[
        {
            "category":"Retail",
            "subcategory":"Repair Shop",
            "type":"Services"
        }
    ],
    "sg:phone":"+1   ",
    "sg:postcode":"27045",
    "sg:province":"NC",
    "wof:name":"Electronic Service of Wilkes",
    "wof:placetype":"venue"
},
  "geometry": {"coordinates":[-80.283664,36.213231],"type":"Point"}
}