{
  "type": "Feature",
  "properties": {
    "addr:full":"3 Church Rd Taylorsville NC 28681",
    "addr:housenumber":"3",
    "addr:postcode":"28681",
    "addr:street":"Church Rd",
    "iso:country":"US",
    "sg:address":"3 Church Rd",
    "sg:city":"Taylorsville",
    "sg:classifiers":[
        {
            "category":"Wholesale",
            "subcategory":"Machinery & Supplies",
            "type":"Manufacturing & Wholesale Goods"
        }
    ],
    "sg:phone":"+1 828 635 0100",
    "sg:postcode":"28681",
    "sg:province":"NC",
    "sg:tags":[
        "industrial"
    ],
    "wof:name":"Omega Motion LLC",
    "wof:placetype":"venue"
},
  "geometry": {"coordinates":[-81.25264199999999,35.918724],"type":"Point"}
}