{
  "type": "Feature",
  "properties": {
    "addr:full":"871 College Ave Shelby NC 28152",
    "addr:housenumber":"871",
    "addr:postcode":"28152",
    "addr:street":"College Ave",
    "iso:country":"US",
    "sg:address":"871 College Ave",
    "sg:city":"Shelby",
    "sg:classifiers":[
        {
            "category":"Organizations",
            "subcategory":"Religious Organization",
            "type":"Services"
        }
    ],
    "sg:phone":"+1 704 484 3109",
    "sg:postcode":"28152",
    "sg:province":"NC",
    "sg:tags":[
        "methodist",
        "church"
    ],
    "wof:name":"Sharon United Methodist Church",
    "wof:placetype":"venue"
},
  "geometry": {"coordinates":[-81.601466,35.250599],"type":"Point"}
}