{
  "type": "Feature",
  "properties": {
    "addr:full":"3905 Reedy Creek Rd Raleigh NC 27607",
    "addr:housenumber":"3905",
    "addr:postcode":"27607",
    "addr:street":"Reedy Creek Rd",
    "iso:country":"US",
    "sg:address":"3905 Reedy Creek Rd",
    "sg:city":"Raleigh",
    "sg:classifiers":[
        {
            "category":"Education",
            "subcategory":"Special Training",
            "type":"Public Place"
        }
    ],
    "sg:phone":"+1 919 715 5379",
    "sg:postcode":"27607",
    "sg:province":"NC",
    "wof:name":"Textbook Services",
    "wof:placetype":"venue"
},
  "geometry": {"coordinates":[-78.711676,35.813255],"type":"Point"}
}