{
  "type": "Feature",
  "properties": {
    "iso:country":"US",
    "sg:address":"202 Centerport Dr",
    "sg:city":"Greensboro",
    "sg:classifiers":[
        {
            "category":"Organizations",
            "subcategory":"Non-profit Organization",
            "type":"Services"
        },
        {
            "category":"Organizations",
            "subcategory":"Professional Association",
            "type":"Services"
        }
    ],
    "sg:phone":"+1 336 668 0167",
    "sg:postcode":"27409",
    "sg:province":"NC",
    "sg:tags":[
        "social"
    ],
    "sg:website":"www.americanheart.org",
    "wof:name":"American Heart Association",
    "wof:placetype":"venue"
},
  "geometry": {"coordinates":[-79.96314,36.085784],"type":"Point"}
}