{
  "type": "Feature",
  "properties": {
    "addr:full":"499 E King St Boone NC 28607",
    "addr:housenumber":"499",
    "addr:postcode":"28607",
    "addr:street":"E King St",
    "iso:country":"US",
    "sg:address":"499 E King St",
    "sg:city":"Boone",
    "sg:classifiers":[
        {
            "category":"Shopping",
            "subcategory":"Used Merchandise",
            "type":"Retail Goods"
        }
    ],
    "sg:phone":"+1 828 265 3121",
    "sg:postcode":"28607",
    "sg:province":"NC",
    "sg:tags":[
        "pawnbroker"
    ],
    "wof:name":"Gold & Closeout Connection",
    "wof:placetype":"venue"
},
  "geometry": {"coordinates":[-81.669011,36.216442],"type":"Point"}
}