{
  "type": "Feature",
  "properties": {
    "iso:country":"US",
    "sg:address":"511 Lakewood Dr",
    "sg:city":"Wilkesboro",
    "sg:classifiers":[
        {
            "category":"Education",
            "subcategory":"Special Training",
            "type":"Public Place"
        }
    ],
    "sg:phone":"+1   ",
    "sg:postcode":"28697",
    "sg:province":"NC",
    "wof:name":"Skill Driving For America Inc",
    "wof:placetype":"venue"
},
  "geometry": {"coordinates":[-81.25676900000001,36.116819],"type":"Point"}
}