{
  "type": "Feature",
  "properties": {
    "addr:full":"1022 Martin Branch Rd Garner NC 27529",
    "addr:housenumber":"1022",
    "addr:postcode":"27529",
    "addr:street":"Martin Branch Rd",
    "iso:country":"US",
    "sg:address":"1022 Martin Branch Rd",
    "sg:city":"Garner",
    "sg:classifiers":[
        {
            "category":"Shopping",
            "subcategory":"Florist",
            "type":"Retail Goods"
        },
        {
            "category":"Farming",
            "subcategory":"Nursery",
            "type":"Manufacturing & Wholesale Goods"
        }
    ],
    "sg:phone":"+1 919 772 1983",
    "sg:postcode":"27529",
    "sg:province":"NC",
    "sg:tags":[
        "greenhouse",
        "supply"
    ],
    "wof:name":"Bynum's Greenhouses",
    "wof:placetype":"venue"
},
  "geometry": {"coordinates":[-78.586894,35.720583],"type":"Point"}
}