{
  "type": "Feature",
  "properties": {
    "iso:country":"US",
    "sg:address":"46 Clearwater Dr",
    "sg:city":"Waynesville",
    "sg:classifiers":[
        {
            "category":"Building & Trades",
            "subcategory":"Construction",
            "type":"Services"
        }
    ],
    "sg:phone":"+1 828 452 7405",
    "sg:postcode":"28785",
    "sg:province":"NC",
    "sg:tags":[
        "house"
    ],
    "wof:name":"Simpson Aluminum Co",
    "wof:placetype":"venue"
},
  "geometry": {"coordinates":[-83.02869699999999,35.536705],"type":"Point"}
}