{
  "type": "Feature",
  "properties": {
    "iso:country":"US",
    "sg:address":"1168 US Hwy 17",
    "sg:city":"Elizabeth City",
    "sg:classifiers":[
        {
            "category":"Autos & Motor Vehicles",
            "subcategory":"Automobile Sales",
            "type":"Retail Goods"
        }
    ],
    "sg:phone":"+1 252 338 4007",
    "sg:postcode":"27909",
    "sg:province":"NC",
    "sg:tags":[
        "car",
        "dealer"
    ],
    "wof:name":"T & G Auto Sales",
    "wof:placetype":"venue"
},
  "geometry": {"coordinates":[-76.21983,36.321268],"type":"Point"}
}