{
  "type": "Feature",
  "properties": {
    "iso:country":"US",
    "sg:address":"5701 Yadkin Rd",
    "sg:city":"Fayetteville",
    "sg:classifiers":[
        {
            "category":"Personal",
            "subcategory":"Beauty Salon",
            "type":"Services"
        }
    ],
    "sg:phone":"+1 910 864 7757",
    "sg:postcode":"28303",
    "sg:province":"NC",
    "sg:tags":[
        "shop"
    ],
    "wof:name":"Natural Classy",
    "wof:placetype":"venue"
},
  "geometry": {"coordinates":[-78.984156,35.091657],"type":"Point"}
}