{
  "type": "Feature",
  "properties": {
    "addr:full":"4828 High Point Rd Greensboro NC 27407",
    "addr:housenumber":"4828",
    "addr:postcode":"27407",
    "addr:street":"High Point Rd",
    "iso:country":"US",
    "sg:address":"4828 High Point Rd",
    "sg:city":"Greensboro",
    "sg:classifiers":[
        {
            "category":"Wholesale",
            "subcategory":"Auto Parts",
            "type":"Manufacturing & Wholesale Goods"
        }
    ],
    "sg:phone":"+1 336 299 4691",
    "sg:postcode":"27407",
    "sg:province":"NC",
    "sg:tags":[
        "automobile",
        "supply"
    ],
    "wof:name":"Atlantic Mobile Home & Rv Supl",
    "wof:placetype":"venue"
},
  "geometry": {"coordinates":[-79.87548700000001,36.025311],"type":"Point"}
}