{
  "type": "Feature",
  "properties": {
    "iso:country":"US",
    "sg:address":"5720 Old Valley School Rd",
    "sg:city":"Kernersville",
    "sg:classifiers":[
        {
            "category":"Health Services",
            "subcategory":"Health Practitioner",
            "type":"Services"
        }
    ],
    "sg:phone":"+1 336 993 2238",
    "sg:postcode":"27284",
    "sg:province":"NC",
    "sg:tags":[
        "psychologist"
    ],
    "wof:name":"Pieter Vaniderstine",
    "wof:placetype":"venue"
},
  "geometry": {"coordinates":[-80.121369,36.157509],"type":"Point"}
}