{
  "type": "Feature",
  "properties": {
    "iso:country":"US",
    "sg:address":"26 S Mitchell Ave",
    "sg:city":"Bakersville",
    "sg:classifiers":[
        {
            "category":"Government",
            "subcategory":"Office",
            "type":"Public Place"
        }
    ],
    "sg:phone":"+1 828 688 2113",
    "sg:postcode":"28705",
    "sg:province":"NC",
    "sg:tags":[
        "village"
    ],
    "wof:name":"Bakersville Town Office",
    "wof:placetype":"venue"
},
  "geometry": {"coordinates":[-82.158569,36.014942],"type":"Point"}
}