{
  "type": "Feature",
  "properties": {
    "addr:full":"626 Harper Ave NW Lenoir NC 28645",
    "addr:housenumber":"626",
    "addr:postcode":"28645",
    "addr:street":"Harper Ave Nw",
    "iso:country":"US",
    "sg:address":"626 Harper Ave NW",
    "sg:city":"Lenoir",
    "sg:classifiers":[
        {
            "category":"Home & Garden",
            "subcategory":"Furniture",
            "type":"Retail Goods"
        }
    ],
    "sg:phone":"+1 828 758 2253",
    "sg:postcode":"28645",
    "sg:province":"NC",
    "wof:name":"Shaw WE Furniture Co Inc",
    "wof:placetype":"venue"
},
  "geometry": {"coordinates":[-81.537306,35.914738],"type":"Point"}
}