{
  "type": "Feature",
  "properties": {
    "addr:full":"127 Buck Seaford Rd Mocksville NC 27028",
    "addr:housenumber":"127",
    "addr:postcode":"27028",
    "addr:street":"Buck Seaford Rd",
    "iso:country":"US",
    "sg:address":"127 Buck Seaford Rd",
    "sg:city":"Mocksville",
    "sg:classifiers":[
        {
            "category":"Wholesale",
            "subcategory":"Construction Materials",
            "type":"Manufacturing & Wholesale Goods"
        },
        {
            "category":"Manufacturing",
            "subcategory":"Lumber",
            "type":"Manufacturing & Wholesale Goods"
        }
    ],
    "sg:phone":"+1 336 634 5148",
    "sg:postcode":"27028",
    "sg:province":"NC",
    "sg:tags":[
        "manufacture",
        "pressure",
        "rough",
        "treat"
    ],
    "wof:name":"Seaford Lumber Company",
    "wof:placetype":"venue"
},
  "geometry": {"coordinates":[-80.587164,35.865431],"type":"Point"}
}