{
  "type": "Feature",
  "properties": {
    "iso:country":"US",
    "sg:address":"64 Blue Spruce Dr",
    "sg:city":"Candler",
    "sg:classifiers":[
        {
            "category":"Professional",
            "subcategory":"Business Services",
            "type":"Services"
        }
    ],
    "sg:phone":"+1   ",
    "sg:postcode":"28715",
    "sg:province":"NC",
    "wof:name":"Shannon M Merren",
    "wof:placetype":"venue"
},
  "geometry": {"coordinates":[-82.75815,35.55685],"type":"Point"}
}