{
  "type": "Feature",
  "properties": {
    "addr:full":"1509 Atkinson St Laurinburg NC 28352",
    "addr:housenumber":"1509",
    "addr:postcode":"28352",
    "addr:street":"Atkinson St",
    "iso:country":"US",
    "sg:address":"1509 Atkinson St",
    "sg:city":"Laurinburg",
    "sg:classifiers":[
        {
            "category":"Sports & Exercise",
            "subcategory":"Bowling",
            "type":"Entertainment"
        }
    ],
    "sg:phone":"+1 910 277 0449",
    "sg:postcode":"28352",
    "sg:province":"NC",
    "sg:tags":[
        "center"
    ],
    "wof:name":"Martin Bowling Ctr",
    "wof:placetype":"venue"
},
  "geometry": {"coordinates":[-79.472398,34.758447],"type":"Point"}
}