{
  "type": "Feature",
  "properties": {
    "iso:country":"US",
    "sg:address":"1030 Amble Dr",
    "sg:city":"Charlotte",
    "sg:classifiers":[
        {
            "category":"Freight",
            "type":"Transportation"
        }
    ],
    "sg:phone":"+1 704 597 0447",
    "sg:postcode":"28206",
    "sg:province":"NC",
    "sg:tags":[
        "operator",
        "local",
        "trucking"
    ],
    "sg:website":"www.gptruck.com",
    "wof:name":"G & P Trucking Co Inc",
    "wof:placetype":"venue"
},
  "geometry": {"coordinates":[-80.80667699999999,35.269433],"type":"Point"}
}