{
  "type": "Feature",
  "properties": {
    "iso:country":"US",
    "sg:address":"153 E Bellevue Dr",
    "sg:city":"High Point",
    "sg:classifiers":[
        {
            "category":"Social Services",
            "subcategory":"Job Training",
            "type":"Services"
        }
    ],
    "sg:phone":"+1 336 883 0650",
    "sg:postcode":"27265",
    "sg:province":"NC",
    "sg:tags":[
        "retardation",
        "disabled",
        "mental",
        "dev"
    ],
    "sg:website":"www.arc-of-hp.com",
    "wof:name":"Arc Of Highpoint",
    "wof:placetype":"venue"
},
  "geometry": {"coordinates":[-80.03353799999999,35.999444],"type":"Point"}
}