{
  "type": "Feature",
  "properties": {
    "iso:country":"US",
    "sg:address":"308 White Jenkins Rd",
    "sg:city":"Bessemer City",
    "sg:classifiers":[
        {
            "category":"Shopping",
            "subcategory":"Bicycles & Sporting Goods",
            "type":"Retail Goods"
        }
    ],
    "sg:phone":"+1 704 629 2138",
    "sg:postcode":"28016",
    "sg:province":"NC",
    "wof:name":"Golfmates LLC",
    "wof:placetype":"venue"
},
  "geometry": {"coordinates":[-81.23992699999999,35.292089],"type":"Point"}
}