{
  "type": "Feature",
  "properties": {
    "addr:full":"3182 Peters Creek Pkwy Winston Salem NC 27127",
    "addr:housenumber":"3182",
    "addr:postcode":"27127",
    "addr:street":"Peters Creek Pkwy",
    "iso:country":"US",
    "sg:address":"3182 Peters Creek Pkwy",
    "sg:city":"Winston Salem",
    "sg:classifiers":[
        {
            "category":"Restaurant",
            "type":"Food & Drink"
        }
    ],
    "sg:phone":"+1 336 771 0120",
    "sg:postcode":"27127",
    "sg:province":"NC",
    "wof:name":"Wendy's",
    "wof:placetype":"venue"
},
  "geometry": {"coordinates":[-80.259913,36.045443],"type":"Point"}
}