{
  "type": "Feature",
  "properties": {
    "iso:country":"US",
    "sg:address":"101 Lake Circle Dr",
    "sg:city":"Kannapolis",
    "sg:classifiers":[
        {
            "category":"Professional",
            "type":"Services"
        }
    ],
    "sg:phone":"+1 704 938 9420",
    "sg:postcode":"28081",
    "sg:province":"NC",
    "sg:tags":[
        "establishment"
    ],
    "wof:name":"LCA",
    "wof:placetype":"venue"
},
  "geometry": {"coordinates":[-80.62246399999999,35.50022],"type":"Point"}
}