{
  "type": "Feature",
  "properties": {
    "iso:country":"US",
    "sg:address":"5119 Raeford Rd",
    "sg:city":"Fayetteville",
    "sg:classifiers":[
        {
            "category":"Home & Garden",
            "subcategory":"Carpets & Floor Coverings",
            "type":"Retail Goods"
        }
    ],
    "sg:phone":"+1 910 309 4281",
    "sg:postcode":"28304",
    "sg:province":"NC",
    "sg:tags":[
        "store"
    ],
    "wof:name":"All About Floors LLC",
    "wof:placetype":"venue"
},
  "geometry": {"coordinates":[-78.96402500000001,35.042568],"type":"Point"}
}