{
  "type": "Feature",
  "properties": {
    "addr:full":"3511 16th St NE Hickory NC 28601",
    "addr:housenumber":"3511",
    "addr:postcode":"28601",
    "addr:street":"16Th St Ne",
    "iso:country":"US",
    "sg:address":"3511 16th St NE",
    "sg:city":"Hickory",
    "sg:classifiers":[
        {
            "category":"Organizations",
            "subcategory":"Religious Organization",
            "type":"Services"
        }
    ],
    "sg:phone":"+1   ",
    "sg:postcode":"28601",
    "sg:province":"NC",
    "wof:name":"Church Ronnie",
    "wof:placetype":"venue"
},
  "geometry": {"coordinates":[-81.295541,35.776897],"type":"Point"}
}