{
  "type": "Feature",
  "properties": {
    "addr:full":"1302 Fleming Rd Greensboro NC 27410",
    "addr:housenumber":"1302",
    "addr:postcode":"27410",
    "addr:street":"Fleming Rd",
    "iso:country":"US",
    "sg:address":"1302 Fleming Rd",
    "sg:city":"Greensboro",
    "sg:classifiers":[
        {
            "category":"Social Services",
            "subcategory":"Child Care",
            "type":"Services"
        }
    ],
    "sg:phone":"+1 336 834 9080",
    "sg:postcode":"27410",
    "sg:province":"NC",
    "sg:tags":[
        "day"
    ],
    "wof:name":"Childrens Friend 35",
    "wof:placetype":"venue"
},
  "geometry": {"coordinates":[-79.891813,36.099866],"type":"Point"}
}