{
  "type": "Feature",
  "properties": {
    "addr:full":"2700 Matlyn Ct Raleigh NC 27613",
    "addr:postcode":"2700;27613",
    "addr:street":"Matlyn Ct",
    "iso:country":"US",
    "sg:address":"2700 Matlyn Ct",
    "sg:city":"Raleigh",
    "sg:classifiers":[
        {
            "category":"Real Estate",
            "subcategory":"Real Estate Agent",
            "type":"Services"
        }
    ],
    "sg:phone":"+1 919 878 3155",
    "sg:postcode":"27613",
    "sg:province":"NC",
    "wof:name":"Realty",
    "wof:placetype":"venue"
},
  "geometry": {"coordinates":[-78.68653999999999,35.931464],"type":"Point"}
}