{
  "type": "Feature",
  "properties": {
    "iso:country":"US",
    "sg:address":"5605 Carnegie Blvd # 125",
    "sg:city":"Charlotte",
    "sg:classifiers":[
        {
            "category":"Utilities",
            "subcategory":"Telephone",
            "type":"Services"
        }
    ],
    "sg:phone":"+1 704 556 2820",
    "sg:postcode":"28209",
    "sg:province":"NC",
    "sg:tags":[
        "communication"
    ],
    "wof:name":"Windstream Nuvox, Inc.",
    "wof:placetype":"venue"
},
  "geometry": {"coordinates":[-80.837526,35.153728],"type":"Point"}
}