{
  "type": "Feature",
  "properties": {
    "iso:country":"US",
    "sg:address":"2212 Smokey Park Hwy",
    "sg:city":"Candler",
    "sg:classifiers":[
        {
            "category":"Recreation",
            "type":"Entertainment"
        }
    ],
    "sg:phone":"+1   ",
    "sg:postcode":"28715",
    "sg:province":"NC",
    "wof:name":"Candler Tae Kwon Do Academy",
    "wof:placetype":"venue"
},
  "geometry": {"coordinates":[-82.73339199999999,35.543577],"type":"Point"}
}