{
  "type": "Feature",
  "properties": {
    "addr:full":"1358 Dunlap Rd Madison NC 27025",
    "addr:housenumber":"1358",
    "addr:postcode":"27025",
    "addr:street":"Dunlap Rd",
    "iso:country":"US",
    "sg:address":"1358 Dunlap Rd",
    "sg:city":"Madison",
    "sg:classifiers":[
        {
            "category":"Farming",
            "subcategory":"Farm",
            "type":"Manufacturing & Wholesale Goods"
        }
    ],
    "sg:phone":"+1 336 548 2085",
    "sg:postcode":"27025",
    "sg:province":"NC",
    "sg:tags":[
        "crop",
        "general"
    ],
    "wof:name":"Robert J Mudd",
    "wof:placetype":"venue"
},
  "geometry": {"coordinates":[-80.049443,36.416567],"type":"Point"}
}