{
  "type": "Feature",
  "properties": {
    "iso:country":"US",
    "sg:address":"518 Church St N",
    "sg:city":"Concord",
    "sg:classifiers":[
        {
            "category":"Shopping",
            "subcategory":"Florist",
            "type":"Retail Goods"
        }
    ],
    "sg:phone":"+1 704 788 3310",
    "sg:postcode":"28025",
    "sg:province":"NC",
    "wof:name":"Pots Of Luck Florist",
    "wof:placetype":"venue"
},
  "geometry": {"coordinates":[-80.592462,35.423707],"type":"Point"}
}