{
  "type": "Feature",
  "properties": {
    "addr:full":"1372 Eufola Rd Statesville NC 28677",
    "addr:housenumber":"1372",
    "addr:postcode":"28677",
    "addr:street":"Eufola Rd",
    "iso:country":"US",
    "sg:address":"1372 Eufola Rd",
    "sg:city":"Statesville",
    "sg:classifiers":[
        {
            "category":"Health Services",
            "subcategory":"Nursing And Care Facility",
            "type":"Services"
        }
    ],
    "sg:phone":"+1 704 528 4568",
    "sg:postcode":"28677",
    "sg:province":"NC",
    "sg:tags":[
        "home",
        "rest"
    ],
    "wof:name":"Heritage Place Adult Living",
    "wof:placetype":"venue"
},
  "geometry": {"coordinates":[-80.96521300000001,35.719825],"type":"Point"}
}