{
  "type": "Feature",
  "properties": {
    "iso:country":"US",
    "sg:address":"416 Saint Marys St",
    "sg:city":"Raleigh",
    "sg:classifiers":[
        {
            "category":"Personal",
            "type":"Services"
        },
        {
            "category":"Personal",
            "subcategory":"Beauty Salon",
            "type":"Services"
        }
    ],
    "sg:phone":"+1 919 832 5387",
    "sg:postcode":"27605",
    "sg:province":"NC",
    "sg:tags":[
        "shop",
        "electrolysis"
    ],
    "wof:name":"Ogburn and Smith Electrolysis",
    "wof:placetype":"venue"
},
  "geometry": {"coordinates":[-78.65070299999999,35.786228],"type":"Point"}
}