{
  "type": "Feature",
  "properties": {
    "iso:country":"US",
    "sg:address":"2814 Superior Dr",
    "sg:city":"Wake Forest",
    "sg:classifiers":[
        {
            "category":"Building & Trades",
            "subcategory":"Construction",
            "type":"Services"
        }
    ],
    "sg:phone":"+1 919 570 0804",
    "sg:postcode":"27587",
    "sg:province":"NC",
    "sg:tags":[
        "boring",
        "drilling",
        "contractor"
    ],
    "wof:name":"East Coast Drilling & Blasting",
    "wof:placetype":"venue"
},
  "geometry": {"coordinates":[-78.534649,35.925619],"type":"Point"}
}