{
  "type": "Feature",
  "properties": {
    "addr:full":"11201 Pine Valley Club Dr Charlotte NC 28277",
    "addr:housenumber":"11201",
    "addr:postcode":"28277",
    "addr:street":"Pine Valley Club Dr",
    "iso:country":"US",
    "sg:address":"11201 Pine Valley Club Dr",
    "sg:city":"Charlotte",
    "sg:classifiers":[
        {
            "category":"Professional",
            "subcategory":"Business Services",
            "type":"Services"
        }
    ],
    "sg:phone":"+1   ",
    "sg:postcode":"28277",
    "sg:province":"NC",
    "wof:name":"EDG Sales",
    "wof:placetype":"venue"
},
  "geometry": {"coordinates":[-80.783185,35.045792],"type":"Point"}
}