{
  "type": "Feature",
  "properties": {
    "addr:full":"4610 Pigott Rd SW Shallotte NC 28470",
    "addr:postcode":"4610;28470",
    "addr:street":"Pigott Rd Sw",
    "iso:country":"US",
    "sg:address":"4610 Pigott Rd SW",
    "sg:city":"Shallotte",
    "sg:classifiers":[
        {
            "category":"Sports & Exercise",
            "subcategory":"Golf",
            "type":"Entertainment"
        }
    ],
    "sg:phone":"+1 910 754 4948",
    "sg:postcode":"28470",
    "sg:province":"NC",
    "sg:tags":[
        "course",
        "drinking",
        "eating",
        "public"
    ],
    "wof:name":"Goose Bay Bar",
    "wof:placetype":"venue"
},
  "geometry": {"coordinates":[-78.396474,33.926459],"type":"Point"}
}