{
  "type": "Feature",
  "properties": {
    "iso:country":"US",
    "sg:address":"2 Abbey Ct",
    "sg:city":"Greensboro",
    "sg:classifiers":[
        {
            "category":"Real Estate",
            "subcategory":"Real Estate Agent",
            "type":"Services"
        }
    ],
    "sg:phone":"+1 336 851 0442",
    "sg:postcode":"27410",
    "sg:province":"NC",
    "wof:name":"Underwood Investments Inc",
    "wof:placetype":"venue"
},
  "geometry": {"coordinates":[-79.868663,36.104973],"type":"Point"}
}