{
  "type": "Feature",
  "properties": {
    "addr:full":"3 Brickyard Rd Etowah NC 28729",
    "addr:housenumber":"3",
    "addr:postcode":"28729",
    "addr:street":"Brickyard Rd",
    "iso:country":"US",
    "sg:address":"3 Brickyard Rd",
    "sg:city":"Etowah",
    "sg:classifiers":[
        {
            "category":"Recreation",
            "type":"Entertainment"
        }
    ],
    "sg:phone":"+1 828 891 5916",
    "sg:postcode":"28729",
    "sg:province":"NC",
    "sg:tags":[
        "course",
        "golf"
    ],
    "wof:name":"Etowah Valley Ladies Golf Assn",
    "wof:placetype":"venue"
},
  "geometry": {"coordinates":[-82.595204,35.318263],"type":"Point"}
}