{
  "type": "Feature",
  "properties": {
    "addr:full":"514 Brook Forest Dr Belmont NC 28012",
    "addr:housenumber":"514",
    "addr:postcode":"28012",
    "addr:street":"Brook Forest Dr",
    "iso:country":"US",
    "sg:address":"514 Brook Forest Dr",
    "sg:city":"Belmont",
    "sg:classifiers":[
        {
            "category":"Building & Trades",
            "subcategory":"Landscaping Services",
            "type":"Services"
        }
    ],
    "sg:phone":"+1 704 829 5447",
    "sg:postcode":"28012",
    "sg:province":"NC",
    "sg:tags":[
        "landscape"
    ],
    "wof:name":"Southeastern Landscape Co",
    "wof:placetype":"venue"
},
  "geometry": {"coordinates":[-81.029799,35.20163],"type":"Point"}
}