{
  "type": "Feature",
  "properties": {
    "iso:country":"US",
    "sg:address":"2325 Concord Church Rd",
    "sg:city":"Greensboro",
    "sg:classifiers":[
        {
            "category":"Organizations",
            "subcategory":"Community Association",
            "type":"Services"
        }
    ],
    "sg:phone":"+1 336 855 5036",
    "sg:postcode":"27406",
    "sg:province":"NC",
    "wof:name":"Sumner Civitan Club",
    "wof:placetype":"venue"
},
  "geometry": {"coordinates":[-79.840694,35.984901],"type":"Point"}
}