{
  "type": "Feature",
  "properties": {
    "iso:country":"US",
    "sg:address":"1143 Airport Rd",
    "sg:city":"Shelby",
    "sg:classifiers":[
        {
            "category":"Retail",
            "subcategory":"Repair Shop",
            "type":"Services"
        }
    ],
    "sg:phone":"+1 704 482 9979",
    "sg:postcode":"28150",
    "sg:province":"NC",
    "sg:tags":[
        "armature",
        "rep",
        "electrical",
        "rewinding"
    ],
    "wof:name":"Electric Motor Svc Of Shelby",
    "wof:placetype":"venue"
},
  "geometry": {"coordinates":[-81.506083,35.31279],"type":"Point"}
}