{
  "type": "Feature",
  "properties": {
    "addr:full":"225 Richey Rd Taylorsville NC 28681",
    "addr:housenumber":"225",
    "addr:postcode":"28681",
    "addr:street":"Richey Rd",
    "iso:country":"US",
    "sg:address":"225 Richey Rd",
    "sg:city":"Taylorsville",
    "sg:classifiers":[
        {
            "category":"Retail",
            "subcategory":"Auto Repair",
            "type":"Services"
        }
    ],
    "sg:phone":"+1 828 495 8183",
    "sg:postcode":"28681",
    "sg:province":"NC",
    "sg:tags":[
        "body",
        "automobile",
        "top",
        "upholstery"
    ],
    "wof:name":"Glenn's Auto Trim Shop",
    "wof:placetype":"venue"
},
  "geometry": {"coordinates":[-81.314812,35.844347],"type":"Point"}
}