{
  "type": "Feature",
  "properties": {
    "addr:full":"3720 Mechanicsville Run Raleigh NC 27610",
    "addr:postcode":"3720;27610",
    "addr:street":"Mechanicsville Run",
    "iso:country":"US",
    "sg:address":"3720 Mechanicsville Run",
    "sg:city":"Raleigh",
    "sg:classifiers":[
        {
            "category":"Professional",
            "subcategory":"Business Services",
            "type":"Services"
        }
    ],
    "sg:phone":"+1   ",
    "sg:postcode":"27610",
    "sg:province":"NC",
    "wof:name":"A1 Commercial Services",
    "wof:placetype":"venue"
},
  "geometry": {"coordinates":[-78.52991299999999,35.728405],"type":"Point"}
}