{
  "type": "Feature",
  "properties": {
    "addr:full":"420 N Main St Kernersville NC 27284",
    "addr:housenumber":"420",
    "addr:postcode":"27284",
    "addr:street":"N Main St",
    "iso:country":"US",
    "sg:address":"420 N Main St",
    "sg:city":"Kernersville",
    "sg:classifiers":[
        {
            "category":"Manufacturing",
            "subcategory":"Tools & Machinery",
            "type":"Manufacturing & Wholesale Goods"
        }
    ],
    "sg:phone":"+1 336 992 2929",
    "sg:postcode":"27284",
    "sg:province":"NC",
    "sg:tags":[
        "equipment",
        "industrial",
        "liquid"
    ],
    "wof:name":"Pump Systems Inc",
    "wof:placetype":"venue"
},
  "geometry": {"coordinates":[-80.067677,36.126232],"type":"Point"}
}