{
  "type": "Feature",
  "properties": {
    "addr:full":"4009 Anderson Mountain Rd Maiden NC 28650",
    "addr:housenumber":"4009",
    "addr:postcode":"28650",
    "addr:street":"Anderson Mountain Rd",
    "iso:country":"US",
    "sg:address":"4009 Anderson Mountain Rd",
    "sg:city":"Maiden",
    "sg:classifiers":[
        {
            "category":"Arts & Performance",
            "subcategory":"Theater",
            "type":"Entertainment"
        }
    ],
    "sg:phone":"+1   ",
    "sg:postcode":"28650",
    "sg:province":"NC",
    "sg:tags":[
        "group"
    ],
    "wof:name":"Magic Show",
    "wof:placetype":"venue"
},
  "geometry": {"coordinates":[-81.095865,35.580644],"type":"Point"}
}