{
  "type": "Feature",
  "properties": {
    "addr:full":"3801 W Dixon Blvd Shelby NC 28152",
    "addr:housenumber":"3801",
    "addr:postcode":"28152",
    "addr:street":"W Dixon Blvd",
    "iso:country":"US",
    "sg:address":"3801 W Dixon Blvd",
    "sg:city":"Shelby",
    "sg:classifiers":[
        {
            "category":"Retail",
            "subcategory":"Auto Repair",
            "type":"Services"
        }
    ],
    "sg:phone":"+1   ",
    "sg:postcode":"28152",
    "sg:province":"NC",
    "sg:tags":[
        "body"
    ],
    "wof:name":"Bowen Body Shop & Used Cars",
    "wof:placetype":"venue"
},
  "geometry": {"coordinates":[-81.642422,35.291989],"type":"Point"}
}