{
  "type": "Feature",
  "properties": {
    "iso:country":"US",
    "sg:address":"1634 Binkley Farm Rd",
    "sg:city":"Clemmons",
    "sg:classifiers":[
        {
            "category":"Building & Trades",
            "subcategory":"Construction",
            "type":"Services"
        }
    ],
    "sg:phone":"+1 336 766 9720",
    "sg:postcode":"27012",
    "sg:province":"NC",
    "sg:tags":[
        "home",
        "remodeling"
    ],
    "wof:name":"Tim N Reynolds Construction Co",
    "wof:placetype":"venue"
},
  "geometry": {"coordinates":[-80.412745,36.06914],"type":"Point"}
}