{
  "type": "Feature",
  "properties": {
    "iso:country":"US",
    "sg:address":"206 Vatersay Dr",
    "sg:city":"Apex",
    "sg:classifiers":[
        {
            "category":"Retail",
            "subcategory":"Car Wash",
            "type":"Services"
        }
    ],
    "sg:phone":"+1   ",
    "sg:postcode":"27502",
    "sg:province":"NC",
    "sg:tags":[
        "carwash"
    ],
    "wof:name":"Prestige Auto Spa LLC",
    "wof:placetype":"venue"
},
  "geometry": {"coordinates":[-78.871146,35.729895],"type":"Point"}
}