{
  "type": "Feature",
  "properties": {
    "iso:country":"US",
    "sg:address":"505 Hedgewood Pl",
    "sg:city":"Winston Salem",
    "sg:classifiers":[
        {
            "category":"Real Estate",
            "subcategory":"Real Estate Agent",
            "type":"Services"
        }
    ],
    "sg:phone":"+1 336 760 2054",
    "sg:postcode":"27104",
    "sg:province":"NC",
    "wof:name":"Buyers Real Estate Svc",
    "wof:placetype":"venue"
},
  "geometry": {"coordinates":[-80.33403300000001,36.095147],"type":"Point"}
}