{
  "type": "Feature",
  "properties": {
    "addr:full":"3928 Mills Rd Greenville NC 27858",
    "addr:housenumber":"3928",
    "addr:postcode":"27858",
    "addr:street":"Mills Rd",
    "iso:country":"US",
    "sg:address":"3928 Mills Rd",
    "sg:city":"Greenville",
    "sg:classifiers":[
        {
            "category":"Food & Beverages",
            "subcategory":"Groceries & Convenience Stores",
            "type":"Retail Goods"
        }
    ],
    "sg:phone":"+1 252 757 3813",
    "sg:postcode":"27858",
    "sg:province":"NC",
    "wof:name":"Country Store",
    "wof:placetype":"venue"
},
  "geometry": {"coordinates":[-77.24899499999999,35.504375],"type":"Point"}
}