{
  "type": "Feature",
  "properties": {
    "addr:full":"4257 Jim Beard Rd Maiden NC 28650",
    "addr:housenumber":"4257",
    "addr:postcode":"28650",
    "addr:street":"Jim Beard Rd",
    "iso:country":"US",
    "sg:address":"4257 Jim Beard Rd",
    "sg:city":"Maiden",
    "sg:classifiers":[
        {
            "category":"Professional",
            "type":"Services"
        }
    ],
    "sg:phone":"+1 828 428 5623",
    "sg:postcode":"28650",
    "sg:province":"NC",
    "wof:name":"Double S Co Inc",
    "wof:placetype":"venue"
},
  "geometry": {"coordinates":[-81.17038700000001,35.573887],"type":"Point"}
}