{
  "type": "Feature",
  "properties": {
    "addr:full":"2111 New Hope Church Rd Raleigh NC 27604",
    "addr:housenumber":"2111",
    "addr:postcode":"27604",
    "addr:street":"New Hope Church Rd",
    "iso:country":"US",
    "sg:address":"2111 New Hope Church Rd",
    "sg:city":"Raleigh",
    "sg:classifiers":[
        {
            "category":"Professional",
            "type":"Services"
        }
    ],
    "sg:phone":"+1 919 790 1053",
    "sg:postcode":"27604",
    "sg:province":"NC",
    "sg:tags":[
        "establishment"
    ],
    "wof:name":"Acsi-Wwi",
    "wof:placetype":"venue"
},
  "geometry": {"coordinates":[-78.60279300000001,35.834639],"type":"Point"}
}