{
  "type": "Feature",
  "properties": {
    "iso:country":"US",
    "sg:address":"1 Cardinal Run",
    "sg:city":"Pinehurst",
    "sg:classifiers":[
        {
            "category":"Shopping",
            "subcategory":"News",
            "type":"Retail Goods"
        }
    ],
    "sg:phone":"+1 910 715 0307",
    "sg:postcode":"28374",
    "sg:province":"NC",
    "sg:tags":[
        "dealer"
    ],
    "wof:name":"Arlington Heights Daily Herald",
    "wof:placetype":"venue"
},
  "geometry": {"coordinates":[-79.495087,35.189985],"type":"Point"}
}