{
  "type": "Feature",
  "properties": {
    "iso:country":"US",
    "sg:address":"116 Parham Rd",
    "sg:city":"Henderson",
    "sg:classifiers":[
        {
            "category":"Restaurant",
            "type":"Food & Drink"
        }
    ],
    "sg:phone":"+1 252 438 5707",
    "sg:postcode":"27536",
    "sg:province":"NC",
    "sg:tags":[
        "eating"
    ],
    "wof:name":"Waffle House",
    "wof:placetype":"venue"
},
  "geometry": {"coordinates":[-78.39123499999999,36.346864],"type":"Point"}
}