{
  "type": "Feature",
  "properties": {
    "iso:country":"US",
    "sg:address":"706 E 17th St",
    "sg:city":"Lumberton",
    "sg:classifiers":[
        {
            "category":"Retail",
            "subcategory":"Auto Repair",
            "type":"Services"
        }
    ],
    "sg:phone":"+1   ",
    "sg:postcode":"28358",
    "sg:province":"NC",
    "sg:tags":[
        "body"
    ],
    "wof:name":"KNOX Body Shop",
    "wof:placetype":"venue"
},
  "geometry": {"coordinates":[-78.99806,34.628716],"type":"Point"}
}