{
  "type": "Feature",
  "properties": {
    "addr:full":"149 Houston Rd Troutman NC 28166",
    "addr:housenumber":"149",
    "addr:postcode":"28166",
    "addr:street":"Houston Rd",
    "iso:country":"US",
    "sg:address":"149 Houston Rd",
    "sg:city":"Troutman",
    "sg:classifiers":[
        {
            "category":"Building & Trades",
            "subcategory":"Cleaning & Sanitation",
            "type":"Services"
        }
    ],
    "sg:phone":"+1 704 528 8055",
    "sg:postcode":"28166",
    "sg:province":"NC",
    "sg:tags":[
        "janitorial"
    ],
    "sg:website":"http://www.realpagessites.com/southpark",
    "wof:name":"Southpark Services Of NC Inc",
    "wof:placetype":"venue"
},
  "geometry": {"coordinates":[-80.855672,35.68055],"type":"Point"}
}