{
  "type": "Feature",
  "properties": {
    "addr:full":"101 S Cooper Dr Henderson NC 27536",
    "addr:housenumber":"101",
    "addr:postcode":"27536",
    "addr:street":"S Cooper Dr",
    "iso:country":"US",
    "sg:address":"101 S Cooper Dr",
    "sg:city":"Henderson",
    "sg:classifiers":[
        {
            "category":"Banks & Credit Unions",
            "subcategory":"Bank",
            "type":"Services"
        }
    ],
    "sg:phone":"+1 252 438 2621",
    "sg:postcode":"27536",
    "sg:province":"NC",
    "sg:tags":[
        "cashing",
        "check"
    ],
    "wof:name":"Friendly Check",
    "wof:placetype":"venue"
},
  "geometry": {"coordinates":[-78.437333,36.331862],"type":"Point"}
}