{
  "type": "Feature",
  "properties": {
    "addr:full":"305 E Mulberry St Goldsboro NC 27530",
    "addr:housenumber":"305",
    "addr:postcode":"27530",
    "addr:street":"E Mulberry St",
    "iso:country":"US",
    "sg:address":"305 E Mulberry St",
    "sg:city":"Goldsboro",
    "sg:classifiers":[
        {
            "category":"Personal",
            "subcategory":"Beauty Salon",
            "type":"Services"
        }
    ],
    "sg:phone":"+1 919 705 1102",
    "sg:postcode":"27530",
    "sg:province":"NC",
    "wof:name":"It's All Hair",
    "wof:placetype":"venue"
},
  "geometry": {"coordinates":[-77.991873,35.383272],"type":"Point"}
}