{
  "type": "Feature",
  "properties": {
    "addr:full":"5884 Kellys Landing Rd Fayetteville NC 28306",
    "addr:housenumber":"5884",
    "addr:postcode":"28306",
    "addr:street":"Kellys Landing Rd",
    "iso:country":"US",
    "sg:address":"5884 Kellys Landing Rd",
    "sg:city":"Fayetteville",
    "sg:classifiers":[
        {
            "category":"Building & Trades",
            "subcategory":"Construction",
            "type":"Services"
        }
    ],
    "sg:phone":"+1 910 424 5038",
    "sg:postcode":"28306",
    "sg:province":"NC",
    "sg:tags":[
        "hanging",
        "contractor"
    ],
    "wof:name":"Barnhill Painting Co Tony",
    "wof:placetype":"venue"
},
  "geometry": {"coordinates":[-78.814763,34.96486],"type":"Point"}
}