{
  "type": "Feature",
  "properties": {
    "addr:full":"325 N Broad St Edenton NC 27932",
    "addr:housenumber":"325",
    "addr:postcode":"27932",
    "addr:street":"N Broad St",
    "iso:country":"US",
    "sg:address":"325 N Broad St",
    "sg:city":"Edenton",
    "sg:phone":"+1 252 482 2694",
    "sg:postcode":"27932",
    "sg:province":"NC",
    "sg:tags":[
        "farm",
        "corn",
        "soybean"
    ],
    "wof:name":"Frankie Edmundson",
    "wof:placetype":"venue"
},
  "geometry": {"coordinates":[-76.60704699999999,36.065005],"type":"Point"}
}