{
  "type": "Feature",
  "properties": {
    "addr:full":"4217 Wayne Rd Greensboro NC 27407",
    "addr:housenumber":"4217",
    "addr:postcode":"27407",
    "addr:street":"Wayne Rd",
    "iso:country":"US",
    "sg:address":"4217 Wayne Rd",
    "sg:city":"Greensboro",
    "sg:classifiers":[
        {
            "category":"Travel",
            "subcategory":"Travel Agent",
            "type":"Entertainment"
        }
    ],
    "sg:phone":"+1 336 854 2241",
    "sg:postcode":"27407",
    "sg:province":"NC",
    "sg:tags":[
        "agency"
    ],
    "wof:name":"Wills Travel Inc",
    "wof:placetype":"venue"
},
  "geometry": {"coordinates":[-79.86646399999999,36.015378],"type":"Point"}
}