{
  "type": "Feature",
  "properties": {
    "iso:country":"US",
    "sg:address":"13777 Ballantyne Corporate Pl",
    "sg:city":"Charlotte",
    "sg:classifiers":[
        {
            "category":"Banks & Credit Unions",
            "subcategory":"Bank",
            "type":"Services"
        }
    ],
    "sg:phone":"+1 704 544 9998",
    "sg:postcode":"28277",
    "sg:province":"NC",
    "sg:tags":[
        "loan",
        "real estate"
    ],
    "wof:name":"Charter One Mortgage",
    "wof:placetype":"venue"
},
  "geometry": {"coordinates":[-80.852464,35.061783],"type":"Point"}
}