{
  "type": "Feature",
  "properties": {
    "iso:country":"US",
    "sg:address":"3060 Dartmouth Dr",
    "sg:city":"Greenville",
    "sg:classifiers":[
        {
            "category":"Real Estate",
            "subcategory":"Real Estate Operator",
            "type":"Services"
        }
    ],
    "sg:phone":"+1 252 321 2440",
    "sg:postcode":"27858",
    "sg:province":"NC",
    "sg:tags":[
        "property",
        "lessor"
    ],
    "wof:name":"Harvell Properties",
    "wof:placetype":"venue"
},
  "geometry": {"coordinates":[-77.37354999999999,35.58054],"type":"Point"}
}