{
  "type": "Feature",
  "properties": {
    "addr:full":"2903 Gibsonville Ossipee Rd Elon College NC 27244",
    "addr:housenumber":"2903",
    "addr:postcode":"27244",
    "addr:street":"Gibsonville Ossipee Rd Elon",
    "iso:country":"US",
    "sg:address":"2903 Gibsonville Ossipee Rd",
    "sg:city":"Elon College",
    "sg:classifiers":[
        {
            "category":"Manufacturing",
            "subcategory":"Tools & Machinery",
            "type":"Manufacturing & Wholesale Goods"
        }
    ],
    "sg:phone":"+1 336 584 1311",
    "sg:postcode":"27244",
    "sg:province":"NC",
    "sg:tags":[
        "machine",
        "shop"
    ],
    "sg:website":"www.mabryind.com",
    "wof:name":"MABRY Industries",
    "wof:placetype":"venue"
},
  "geometry": {"coordinates":[-79.516485,36.168386],"type":"Point"}
}