{
  "type": "Feature",
  "properties": {
    "iso:country":"US",
    "sg:address":"129 N Main St",
    "sg:city":"Mocksville",
    "sg:classifiers":[
        {
            "category":"Shopping",
            "subcategory":"Musical Instruments",
            "type":"Retail Goods"
        }
    ],
    "sg:phone":"+1 336 751 1934",
    "sg:postcode":"27028",
    "sg:province":"NC",
    "wof:name":"Daves Musical Instruments",
    "wof:placetype":"venue"
},
  "geometry": {"coordinates":[-80.561818,35.8946],"type":"Point"}
}