{
  "type": "Feature",
  "properties": {
    "iso:country":"US",
    "sg:address":"115 S Center St",
    "sg:city":"Statesville",
    "sg:classifiers":[
        {
            "category":"Personal",
            "subcategory":"Tanning Parlor",
            "type":"Services"
        }
    ],
    "sg:phone":"+1 704 838 1393",
    "sg:postcode":"28677",
    "sg:province":"NC",
    "sg:tags":[
        "salon"
    ],
    "wof:name":"Body Elements",
    "wof:placetype":"venue"
},
  "geometry": {"coordinates":[-80.88817899999999,35.784521],"type":"Point"}
}