{
  "type": "Feature",
  "properties": {
    "addr:full":"6511 Union Grove Church Rd Hillsborough NC 27278",
    "addr:housenumber":"6511",
    "addr:postcode":"27278",
    "addr:street":"Union Grove Church Rd",
    "iso:country":"US",
    "sg:address":"6511 Union Grove Church Rd",
    "sg:city":"Hillsborough",
    "sg:classifiers":[
        {
            "category":"Building & Trades",
            "subcategory":"Cleaning & Sanitation",
            "type":"Services"
        }
    ],
    "sg:phone":"+1   ",
    "sg:postcode":"27278",
    "sg:province":"NC",
    "sg:tags":[
        "maintenance"
    ],
    "wof:name":"Oliver Janitorial Services",
    "wof:placetype":"venue"
},
  "geometry": {"coordinates":[-79.12307800000001,35.984546],"type":"Point"}
}