{
  "type": "Feature",
  "properties": {
    "addr:full":"38 Arlington St Asheville NC 28801",
    "addr:housenumber":"38",
    "addr:postcode":"28801",
    "addr:street":"Arlington St",
    "iso:country":"US",
    "sg:address":"38 Arlington St",
    "sg:city":"Asheville",
    "sg:classifiers":[
        {
            "category":"Professional",
            "subcategory":"Lawyer & Legal Services",
            "type":"Services"
        }
    ],
    "sg:phone":"+1   ",
    "sg:postcode":"28801",
    "sg:province":"NC",
    "wof:name":"Arrowood Mary E Atty At Law",
    "wof:placetype":"venue"
},
  "geometry": {"coordinates":[-82.545788,35.60131],"type":"Point"}
}