{
  "type": "Feature",
  "properties": {
    "addr:full":"2115 Georgia Ave Winston Salem NC 27104",
    "addr:housenumber":"2115",
    "addr:postcode":"27104",
    "addr:street":"Georgia Ave",
    "iso:country":"US",
    "sg:address":"2115 Georgia Ave",
    "sg:city":"Winston Salem",
    "sg:classifiers":[
        {
            "category":"Health Services",
            "subcategory":"Doctor",
            "type":"Services"
        }
    ],
    "sg:phone":"+1   ",
    "sg:postcode":"27104",
    "sg:province":"NC",
    "sg:tags":[
        "medical"
    ],
    "wof:name":"George Podgorny MD",
    "wof:placetype":"venue"
},
  "geometry": {"coordinates":[-80.2779,36.100615],"type":"Point"}
}