{
  "type": "Feature",
  "properties": {
    "addr:full":"2875 Knoll Trl Graham NC 27253",
    "addr:housenumber":"2875",
    "addr:postcode":"27253",
    "addr:street":"Knoll Trl",
    "iso:country":"US",
    "sg:address":"2875 Knoll Trl",
    "sg:city":"Graham",
    "sg:classifiers":[
        {
            "category":"Autos & Motor Vehicles",
            "subcategory":"Auto Supplies",
            "type":"Retail Goods"
        }
    ],
    "sg:phone":"+1 336 570 2886",
    "sg:postcode":"27253",
    "sg:province":"NC",
    "sg:tags":[
        "tire"
    ],
    "wof:name":"Edwards Tire & Auto Ctr",
    "wof:placetype":"venue"
},
  "geometry": {"coordinates":[-79.375665,36.011902],"type":"Point"}
}