{
  "type": "Feature",
  "properties": {
    "iso:country":"US",
    "sg:address":"466 Dillard Rd",
    "sg:city":"Highlands",
    "sg:classifiers":[
        {
            "category":"Professional",
            "subcategory":"Business Services",
            "type":"Services"
        }
    ],
    "sg:phone":"+1 828 526 3966",
    "sg:postcode":"28741",
    "sg:province":"NC",
    "sg:tags":[
        "interior",
        "consultant",
        "design",
        "decorator"
    ],
    "wof:name":"Great Things Design Studios",
    "wof:placetype":"venue"
},
  "geometry": {"coordinates":[-83.207515,35.05027],"type":"Point"}
}