{
  "type": "Feature",
  "properties": {
    "iso:country":"US",
    "sg:address":"225 4th St NW",
    "sg:city":"Hickory",
    "sg:classifiers":[
        {
            "category":"Professional",
            "subcategory":"Management & Consulting",
            "type":"Services"
        }
    ],
    "sg:phone":"+1 828 326 7222",
    "sg:postcode":"28601",
    "sg:province":"NC",
    "sg:tags":[
        "banking",
        "finance",
        "consultant"
    ],
    "sg:website":"www.capitalbank-nc.com",
    "wof:name":"Capital Bank",
    "wof:placetype":"venue"
},
  "geometry": {"coordinates":[-81.344527,35.735362],"type":"Point"}
}