{
  "type": "Feature",
  "properties": {
    "addr:full":"404 Esclip Rd Elizabeth City NC 27909",
    "addr:housenumber":"404",
    "addr:postcode":"27909",
    "addr:street":"Esclip Rd",
    "iso:country":"US",
    "sg:address":"404 Esclip Rd",
    "sg:city":"Elizabeth City",
    "sg:classifiers":[
        {
            "category":"Organizations",
            "subcategory":"Religious Organization",
            "type":"Services"
        }
    ],
    "sg:phone":"+1 252 330 4725",
    "sg:postcode":"27909",
    "sg:province":"NC",
    "sg:tags":[
        "church"
    ],
    "wof:name":"Galilee Missionary Baptist",
    "wof:placetype":"venue"
},
  "geometry": {"coordinates":[-76.162629,36.168845],"type":"Point"}
}