{
  "type": "Feature",
  "properties": {
    "addr:full":"4436 N Center St Hickory NC 28601",
    "addr:housenumber":"4436",
    "addr:postcode":"28601",
    "addr:street":"N Center St",
    "iso:country":"US",
    "sg:address":"4436 N Center St",
    "sg:city":"Hickory",
    "sg:classifiers":[
        {
            "category":"Professional",
            "subcategory":"Business Services",
            "type":"Services"
        }
    ],
    "sg:phone":"+1   ",
    "sg:postcode":"28601",
    "sg:province":"NC",
    "wof:name":"Compton Enterprises of NC Inc",
    "wof:placetype":"venue"
},
  "geometry": {"coordinates":[-81.30988000000001,35.791358],"type":"Point"}
}