{
  "type": "Feature",
  "properties": {
    "addr:full":"388 S West St Wilkesboro NC 28697",
    "addr:housenumber":"388",
    "addr:postcode":"28697",
    "addr:street":"S;St",
    "iso:country":"US",
    "sg:address":"388 S West St",
    "sg:city":"Wilkesboro",
    "sg:classifiers":[
        {
            "category":"Building & Trades",
            "subcategory":"Electrical",
            "type":"Services"
        }
    ],
    "sg:phone":"+1 336 667 5349",
    "sg:postcode":"28697",
    "sg:province":"NC",
    "sg:tags":[
        "electrical",
        "electric",
        "contractor"
    ],
    "wof:name":"Randie's Electric",
    "wof:placetype":"venue"
},
  "geometry": {"coordinates":[-81.15204,36.146299],"type":"Point"}
}