{
  "type": "Feature",
  "properties": {
    "addr:full":"13400 York Rd Charlotte NC 28278",
    "addr:housenumber":"13400",
    "addr:postcode":"28278",
    "addr:street":"York Rd",
    "iso:country":"US",
    "sg:address":"13400 York Rd",
    "sg:city":"Charlotte",
    "sg:classifiers":[
        {
            "category":"Building & Trades",
            "subcategory":"Construction",
            "type":"Services"
        }
    ],
    "sg:phone":"+1 704 588 1106",
    "sg:postcode":"28278",
    "sg:province":"NC",
    "sg:tags":[
        "general",
        "contractor"
    ],
    "wof:name":"Compton Contracting Co",
    "wof:placetype":"venue"
},
  "geometry": {"coordinates":[-80.99369299999999,35.099904],"type":"Point"}
}