{
  "type": "Feature",
  "properties": {
    "iso:country":"US",
    "sg:address":"300 Waterfront Dr",
    "sg:city":"Wilkesboro",
    "sg:phone":"+1 336 921 3166",
    "sg:postcode":"28697",
    "sg:province":"NC",
    "sg:tags":[
        "farm",
        "corn"
    ],
    "wof:name":"David Shepherd",
    "wof:placetype":"venue"
},
  "geometry": {"coordinates":[-81.253263,36.120218],"type":"Point"}
}