{
  "type": "Feature",
  "properties": {
    "iso:country":"US",
    "sg:address":"15410 US Hwy 17",
    "sg:city":"Hampstead",
    "sg:classifiers":[
        {
            "category":"Personal",
            "subcategory":"Beauty Salon",
            "type":"Services"
        }
    ],
    "sg:phone":"+1 910 270 1980",
    "sg:postcode":"28443",
    "sg:province":"NC",
    "wof:name":"Boomers Hair Salon",
    "wof:placetype":"venue"
},
  "geometry": {"coordinates":[-77.70097699999999,34.376123],"type":"Point"}
}