{
  "type": "Feature",
  "properties": {
    "iso:country":"US",
    "sg:address":"4220 Province Dr",
    "sg:city":"Wilmington",
    "sg:classifiers":[
        {
            "category":"Organizations",
            "subcategory":"Religious Organization",
            "type":"Services"
        }
    ],
    "sg:phone":"+1   ",
    "sg:postcode":"28405",
    "sg:province":"NC",
    "wof:name":"Devane Jr Rev George M",
    "wof:placetype":"venue"
},
  "geometry": {"coordinates":[-77.884683,34.30251],"type":"Point"}
}