{
  "type": "Feature",
  "properties": {
    "addr:full":"2205 E Courtyard Cir Goldsboro NC 27530",
    "addr:housenumber":"2205",
    "addr:postcode":"27530",
    "addr:street":"E Courtyard Cir",
    "iso:country":"US",
    "sg:address":"2205 E Courtyard Cir",
    "sg:city":"Goldsboro",
    "sg:classifiers":[
        {
            "category":"Utilities",
            "subcategory":"Natural Gas",
            "type":"Services"
        }
    ],
    "sg:phone":"+1 919 583 8651",
    "sg:postcode":"27530",
    "sg:province":"NC",
    "sg:tags":[
        "company"
    ],
    "wof:name":"Piedmont Natual Gas",
    "wof:placetype":"venue"
},
  "geometry": {"coordinates":[-77.985998,35.356272],"type":"Point"}
}