{
  "type": "Feature",
  "properties": {
    "iso:country":"US",
    "sg:address":"7324 Lawyers Station Dr",
    "sg:city":"Charlotte",
    "sg:classifiers":[
        {
            "category":"Building & Trades",
            "subcategory":"Construction",
            "type":"Services"
        }
    ],
    "sg:phone":"+1 704 442 0715",
    "sg:postcode":"28227",
    "sg:province":"NC",
    "sg:tags":[
        "home",
        "contractor",
        "family",
        "paint"
    ],
    "wof:name":"C R Walls Inc",
    "wof:placetype":"venue"
},
  "geometry": {"coordinates":[-80.67242,35.181225],"type":"Point"}
}