{
  "type": "Feature",
  "properties": {
    "iso:country":"US",
    "sg:address":"3305 Magnolia Hill Dr",
    "sg:city":"Charlotte",
    "sg:classifiers":[
        {
            "category":"Professional",
            "subcategory":"Business Services",
            "type":"Services"
        }
    ],
    "sg:phone":"+1   ",
    "sg:postcode":"28205",
    "sg:province":"NC",
    "wof:name":"Nieves Translation Svcs Inc",
    "wof:placetype":"venue"
},
  "geometry": {"coordinates":[-80.773881,35.229182],"type":"Point"}
}