{
  "type": "Feature",
  "properties": {
    "addr:full":"212 Henry St Rocky Mount NC 27803",
    "addr:housenumber":"212",
    "addr:postcode":"27803",
    "addr:street":"Henry St",
    "iso:country":"US",
    "sg:address":"212 Henry St",
    "sg:city":"Rocky Mount",
    "sg:classifiers":[
        {
            "category":"Organizations",
            "subcategory":"Religious Organization",
            "type":"Services"
        }
    ],
    "sg:phone":"+1 252 212 1769",
    "sg:postcode":"27803",
    "sg:province":"NC",
    "wof:name":"Shekinah Temple Hcod",
    "wof:placetype":"venue"
},
  "geometry": {"coordinates":[-77.80318200000001,35.930672],"type":"Point"}
}