{
  "type": "Feature",
  "properties": {
    "addr:full":"2943 Industrial Dr Sanford NC 27332",
    "addr:housenumber":"2943",
    "addr:postcode":"27332",
    "addr:street":"Industrial Dr",
    "iso:country":"US",
    "sg:address":"2943 Industrial Dr",
    "sg:city":"Sanford",
    "sg:classifiers":[
        {
            "category":"Food & Beverages",
            "subcategory":"Groceries & Convenience Stores",
            "type":"Retail Goods"
        }
    ],
    "sg:phone":"+1 919 777 0554",
    "sg:postcode":"27332",
    "sg:province":"NC",
    "sg:tags":[
        "grocer"
    ],
    "wof:name":"Mundo Latino",
    "wof:placetype":"venue"
},
  "geometry": {"coordinates":[-79.146548,35.448141],"type":"Point"}
}