{
  "type": "Feature",
  "properties": {
    "iso:country":"US",
    "sg:address":"138 Mooreland Rd",
    "sg:city":"Mooresville",
    "sg:classifiers":[
        {
            "category":"Banks & Credit Unions",
            "subcategory":"Financial Services",
            "type":"Services"
        }
    ],
    "sg:phone":"+1 704 660 5066",
    "sg:postcode":"28117",
    "sg:province":"NC",
    "sg:tags":[
        "management",
        "open",
        "investment"
    ],
    "wof:name":"Money Consulting & Management",
    "wof:placetype":"venue"
},
  "geometry": {"coordinates":[-80.87159699999999,35.571135],"type":"Point"}
}