{
  "type": "Feature",
  "properties": {
    "iso:country":"US",
    "sg:address":"3628 Volunteer Rd",
    "sg:city":"Elm City",
    "sg:classifiers":[
        {
            "category":"Government",
            "subcategory":"Fire Station",
            "type":"Public Place"
        }
    ],
    "sg:phone":"+1 252 443 2252",
    "sg:postcode":"27822",
    "sg:province":"NC",
    "sg:tags":[
        "protection"
    ],
    "wof:name":"Coopers Vol Fire Dept & Rescue",
    "wof:placetype":"venue"
},
  "geometry": {"coordinates":[-77.950278,35.878754],"type":"Point"}
}