{
  "type": "Feature",
  "properties": {
    "addr:full":"1583 Liberty Dr Thomasville NC 27360",
    "addr:housenumber":"1583",
    "addr:postcode":"27360",
    "addr:street":"Liberty Dr",
    "iso:country":"US",
    "sg:address":"1583 Liberty Dr",
    "sg:city":"Thomasville",
    "sg:classifiers":[
        {
            "category":"Professional",
            "type":"Services"
        }
    ],
    "sg:phone":"+1 336 476 0060",
    "sg:postcode":"27360",
    "sg:province":"NC",
    "sg:tags":[
        "establishment"
    ],
    "wof:name":"Murphy USA Inc",
    "wof:placetype":"venue"
},
  "geometry": {"coordinates":[-80.067961,35.856748],"type":"Point"}
}