{
  "type": "Feature",
  "properties": {
    "addr:full":"2006 Riverview Ln Morehead City NC 28557",
    "addr:housenumber":"2006",
    "addr:postcode":"28557",
    "addr:street":"Riverview Ln",
    "iso:country":"US",
    "sg:address":"2006 Riverview Ln",
    "sg:city":"Morehead City",
    "sg:classifiers":[
        {
            "category":"Freight",
            "type":"Transportation"
        }
    ],
    "sg:phone":"+1 252 247 5147",
    "sg:postcode":"28557",
    "sg:province":"NC",
    "sg:tags":[
        "operator",
        "local",
        "trucking"
    ],
    "wof:name":"Ernie Boyd Trucking Inc",
    "wof:placetype":"venue"
},
  "geometry": {"coordinates":[-76.716752,34.752647],"type":"Point"}
}