{
  "type": "Feature",
  "properties": {
    "addr:full":"454 Bayles Rd Lillington NC 27546",
    "addr:housenumber":"454",
    "addr:postcode":"27546",
    "addr:street":"Bayles Rd",
    "iso:country":"US",
    "sg:address":"454 Bayles Rd",
    "sg:city":"Lillington",
    "sg:classifiers":[
        {
            "category":"Retail",
            "subcategory":"Auto Repair",
            "type":"Services"
        }
    ],
    "sg:phone":"+1 910 814 0844",
    "sg:postcode":"27546",
    "sg:province":"NC",
    "sg:tags":[
        "recreational",
        "vehicle"
    ],
    "wof:name":"T & J Rv REPAIR Svc",
    "wof:placetype":"venue"
},
  "geometry": {"coordinates":[-78.91212,35.428231],"type":"Point"}
}