{
  "type": "Feature",
  "properties": {
    "addr:full":"18 Union St N Concord NC 28025",
    "addr:housenumber":"18",
    "addr:postcode":"28025",
    "addr:street":"Union St N",
    "iso:country":"US",
    "sg:address":"18 Union St N",
    "sg:city":"Concord",
    "sg:classifiers":[
        {
            "category":"Professional",
            "subcategory":"Business Services",
            "type":"Services"
        }
    ],
    "sg:phone":"+1 704 788 1311",
    "sg:postcode":"28025",
    "sg:province":"NC",
    "sg:tags":[
        "interior",
        "consultant",
        "design",
        "decorator"
    ],
    "wof:name":"Rinehardt's Interiors",
    "wof:placetype":"venue"
},
  "geometry": {"coordinates":[-80.581971,35.411097],"type":"Point"}
}