{
  "type": "Feature",
  "properties": {
    "iso:country":"US",
    "sg:address":"5708 Windlestraw Dr",
    "sg:city":"Durham",
    "sg:classifiers":[
        {
            "category":"Building & Trades",
            "subcategory":"Construction",
            "type":"Services"
        }
    ],
    "sg:phone":"+1 919 544 5486",
    "sg:postcode":"27713",
    "sg:province":"NC",
    "sg:tags":[
        "hanging",
        "contractor"
    ],
    "wof:name":"Tilley William Painting & Dctg",
    "wof:placetype":"venue"
},
  "geometry": {"coordinates":[-78.92695399999999,35.920005],"type":"Point"}
}