{
  "type": "Feature",
  "properties": {
    "iso:country":"US",
    "sg:address":"201 E Atlantic Blvd",
    "sg:city":"Atlantic Beach",
    "sg:classifiers":[
        {
            "category":"Bars & Pubs",
            "type":"Food & Drink"
        }
    ],
    "sg:menulink":"http://www.allmenus.com/nc/morehead/140871-the-crabs-claw-restaurant-and-oyster-bar/menu/",
    "sg:phone":"+1 252 726 8222",
    "sg:postcode":"28512",
    "sg:province":"NC",
    "sg:tags":[
        "seafood",
        "american"
    ],
    "wof:name":"The Crab's Claw Restaurant And Oyster Bar",
    "wof:placetype":"venue"
},
  "geometry": {"coordinates":[-76.740066,34.698516],"type":"Point"}
}