{
  "type": "Feature",
  "properties": {
    "iso:country":"US",
    "sg:address":"713 E Dixon Blvd",
    "sg:city":"Shelby",
    "sg:classifiers":[
        {
            "category":"Personal",
            "subcategory":"Beauty Salon",
            "type":"Services"
        }
    ],
    "sg:phone":"+1 704 487 0390",
    "sg:postcode":"28152",
    "sg:province":"NC",
    "sg:tags":[
        "manicuring"
    ],
    "wof:name":"Today's Nail",
    "wof:placetype":"venue"
},
  "geometry": {"coordinates":[-81.527919,35.274254],"type":"Point"}
}