{
  "type": "Feature",
  "properties": {
    "addr:full":"650 Angell Rd Madison NC 27025",
    "addr:housenumber":"650",
    "addr:postcode":"27025",
    "addr:street":"Angell Rd",
    "iso:country":"US",
    "sg:address":"650 Angell Rd",
    "sg:city":"Madison",
    "sg:classifiers":[
        {
            "category":"Real Estate",
            "subcategory":"Real Estate Agent",
            "type":"Services"
        }
    ],
    "sg:phone":"+1 336 427 4798",
    "sg:postcode":"27025",
    "sg:province":"NC",
    "wof:name":"Pjs Properties Inc",
    "wof:placetype":"venue"
},
  "geometry": {"coordinates":[-79.89160699999999,36.294724],"type":"Point"}
}