{
  "type": "Feature",
  "properties": {
    "iso:country":"US",
    "sg:address":"7426 Broken Oak Ln",
    "sg:city":"Charlotte",
    "sg:classifiers":[
        {
            "category":"Professional",
            "type":"Services"
        }
    ],
    "sg:phone":"+1 704 544 9744",
    "sg:postcode":"28226",
    "sg:province":"NC",
    "wof:name":"Blanton Ark",
    "wof:placetype":"venue"
},
  "geometry": {"coordinates":[-80.852529,35.071122],"type":"Point"}
}