{
  "type": "Feature",
  "properties": {
    "iso:country":"US",
    "sg:address":"130 River Trl",
    "sg:city":"Winton",
    "sg:classifiers":[
        {
            "category":"Manufacturing",
            "subcategory":"Buildings",
            "type":"Manufacturing & Wholesale Goods"
        },
        {
            "category":"Building & Trades",
            "subcategory":"Construction",
            "type":"Services"
        }
    ],
    "sg:phone":"+1 252 358 1632",
    "sg:postcode":"27986",
    "sg:province":"NC",
    "sg:tags":[
        "home",
        "builder",
        "contractor"
    ],
    "wof:name":"Thomas Lee Bazemore Jr",
    "wof:placetype":"venue"
},
  "geometry": {"coordinates":[-76.94138700000001,36.394022],"type":"Point"}
}