{
  "type": "Feature",
  "properties": {
    "addr:full":"902 Fayetteville St Durham NC 27701",
    "addr:housenumber":"902",
    "addr:postcode":"27701",
    "addr:street":"Fayetteville St",
    "iso:country":"US",
    "sg:address":"902 Fayetteville St",
    "sg:city":"Durham",
    "sg:classifiers":[
        {
            "category":"Personal",
            "subcategory":"Nail Salon",
            "type":"Services"
        }
    ],
    "sg:phone":"+1 919 667 9880",
    "sg:postcode":"27701",
    "sg:province":"NC",
    "wof:name":"The Nail Trix",
    "wof:placetype":"venue"
},
  "geometry": {"coordinates":[-78.89904300000001,35.984761],"type":"Point"}
}