{
  "type": "Feature",
  "properties": {
    "iso:country":"US",
    "sg:address":"8426 Medical Plaza Dr",
    "sg:city":"Charlotte",
    "sg:classifiers":[
        {
            "category":"Manufacturing",
            "subcategory":"Tools & Machinery",
            "type":"Manufacturing & Wholesale Goods"
        },
        {
            "category":"Health Services",
            "subcategory":"Doctor",
            "type":"Services"
        }
    ],
    "sg:phone":"+1 704 510 9292",
    "sg:postcode":"28262",
    "sg:province":"NC",
    "sg:tags":[
        "medical",
        "eyes",
        "artificial"
    ],
    "wof:name":"Southeastern Ocularists Inc",
    "wof:placetype":"venue"
},
  "geometry": {"coordinates":[-80.77570299999999,35.319401],"type":"Point"}
}