{
  "type": "Feature",
  "properties": {
    "iso:country":"US",
    "sg:address":"2260 N College Ave",
    "sg:city":"Newton",
    "sg:classifiers":[
        {
            "category":"Retail",
            "subcategory":"Auto Repair",
            "type":"Services"
        }
    ],
    "sg:phone":"+1 828 695 1238",
    "sg:postcode":"28658",
    "sg:province":"NC",
    "sg:tags":[
        "transmission",
        "tractor",
        "general"
    ],
    "wof:name":"Highway Star Truck & Trlr Repr",
    "wof:placetype":"venue"
},
  "geometry": {"coordinates":[-81.216615,35.687906],"type":"Point"}
}