{
  "type": "Feature",
  "properties": {
    "addr:full":"853 S 17th St Wilmington NC 28401",
    "addr:housenumber":"853",
    "addr:postcode":"28401",
    "addr:street":"S 17Th St",
    "iso:country":"US",
    "sg:address":"853 S 17th St",
    "sg:city":"Wilmington",
    "sg:classifiers":[
        {
            "category":"Restaurant",
            "type":"Food & Drink"
        }
    ],
    "sg:phone":"+1 910 343 9902",
    "sg:postcode":"28401",
    "sg:province":"NC",
    "sg:tags":[
        "caterer"
    ],
    "wof:name":"Angie's Of Chris's Restaurant",
    "wof:placetype":"venue"
},
  "geometry": {"coordinates":[-77.926266,34.226394],"type":"Point"}
}