{
  "type": "Feature",
  "properties": {
    "iso:country":"US",
    "sg:address":"2641 Russell McPherson Rd",
    "sg:city":"Burlington",
    "sg:classifiers":[
        {
            "category":"Building & Trades",
            "subcategory":"Construction",
            "type":"Services"
        }
    ],
    "sg:phone":"+1 336 227 9231",
    "sg:postcode":"27215",
    "sg:province":"NC",
    "sg:tags":[
        "grading",
        "contractor"
    ],
    "wof:name":"McPherson Rssell Clring Grding",
    "wof:placetype":"venue"
},
  "geometry": {"coordinates":[-79.459086,35.956238],"type":"Point"}
}