{
  "type": "Feature",
  "properties": {
    "iso:country":"US",
    "sg:address":"8333 Fountain Park Dr",
    "sg:city":"Raleigh",
    "sg:classifiers":[
        {
            "category":"Professional",
            "subcategory":"Employment Agencies",
            "type":"Services"
        }
    ],
    "sg:phone":"+1 919 841 4488",
    "sg:postcode":"27613",
    "sg:province":"NC",
    "sg:tags":[
        "opportunity"
    ],
    "wof:name":"Corporate Resource Assoc",
    "wof:placetype":"venue"
},
  "geometry": {"coordinates":[-78.731409,35.897182],"type":"Point"}
}