{
  "type": "Feature",
  "properties": {
    "iso:country":"US",
    "sg:address":"1268 E Harden St",
    "sg:city":"Graham",
    "sg:phone":"+1 336 227 1117",
    "sg:postcode":"27253",
    "sg:province":"NC",
    "sg:tags":[
        "gas"
    ],
    "wof:name":"Conklin Oil & Propane Co",
    "wof:placetype":"venue"
},
  "geometry": {"coordinates":[-79.372168,36.053479],"type":"Point"}
}