{
  "type": "Feature",
  "properties": {
    "addr:full":"1700 Fort Bragg Rd Fayetteville NC 28303",
    "addr:housenumber":"1700",
    "addr:postcode":"28303",
    "addr:street":"Fort Bragg Rd",
    "iso:country":"US",
    "sg:address":"1700 Fort Bragg Rd",
    "sg:city":"Fayetteville",
    "sg:classifiers":[
        {
            "category":"Building & Trades",
            "subcategory":"Construction",
            "type":"Services"
        }
    ],
    "sg:phone":"+1 910 484 2689",
    "sg:postcode":"28303",
    "sg:province":"NC",
    "sg:tags":[
        "contractor"
    ],
    "wof:name":"Ellis Walker Builders Inc",
    "wof:placetype":"venue"
},
  "geometry": {"coordinates":[-78.909391,35.062549],"type":"Point"}
}