{
  "type": "Feature",
  "properties": {
    "iso:country":"US",
    "sg:address":"3365 Mount Pleasant Rd",
    "sg:city":"Willow Spring",
    "sg:classifiers":[
        {
            "category":"Personal",
            "subcategory":"Beauty Salon",
            "type":"Services"
        }
    ],
    "sg:phone":"+1 919 639 0600",
    "sg:postcode":"27592",
    "sg:province":"NC",
    "wof:name":"Kenneth Stancil",
    "wof:placetype":"venue"
},
  "geometry": {"coordinates":[-78.643922,35.560124],"type":"Point"}
}