{
  "type": "Feature",
  "properties": {
    "iso:country":"US",
    "sg:address":"1709 Morven Rd",
    "sg:city":"Wadesboro",
    "sg:classifiers":[
        {
            "category":"Food & Beverages",
            "subcategory":"Groceries & Convenience Stores",
            "type":"Retail Goods"
        }
    ],
    "sg:phone":"+1 704 694 6787",
    "sg:postcode":"28170",
    "sg:province":"NC",
    "sg:tags":[
        "be",
        "station",
        "gasoline",
        "alcoholic"
    ],
    "wof:name":"Chapels Bill Food Center",
    "wof:placetype":"venue"
},
  "geometry": {"coordinates":[-80.06519,34.950958],"type":"Point"}
}