{
  "type": "Feature",
  "properties": {
    "addr:full":"2990 Rogers Mill Rd Magnolia NC 28453",
    "addr:housenumber":"2990",
    "addr:postcode":"28453",
    "addr:street":"Rogers Mill Rd",
    "iso:country":"US",
    "sg:address":"2990 Rogers Mill Rd",
    "sg:city":"Magnolia",
    "sg:classifiers":[
        {
            "category":"Farming",
            "subcategory":"Farm",
            "type":"Manufacturing & Wholesale Goods"
        }
    ],
    "sg:phone":"+1 910 532 4585",
    "sg:postcode":"28453",
    "sg:province":"NC",
    "wof:name":"Johnson Breeders-Chestnutt Frm",
    "wof:placetype":"venue"
},
  "geometry": {"coordinates":[-78.194247,34.813188],"type":"Point"}
}