{
  "type": "Feature",
  "properties": {
    "iso:country":"US",
    "sg:address":"184 Piver Rd",
    "sg:city":"Beaufort",
    "sg:classifiers":[
        {
            "category":"Building & Trades",
            "subcategory":"Cleaning & Sanitation",
            "type":"Services"
        }
    ],
    "sg:phone":"+1   ",
    "sg:postcode":"28516",
    "sg:province":"NC",
    "sg:tags":[
        "maintenance"
    ],
    "wof:name":"Holt Enterprises",
    "wof:placetype":"venue"
},
  "geometry": {"coordinates":[-76.630132,34.742836],"type":"Point"}
}