{
  "type": "Feature",
  "properties": {
    "iso:country":"US",
    "sg:address":"82 Grist Rd",
    "sg:city":"Chadbourn",
    "sg:classifiers":[
        {
            "category":"Wholesale",
            "subcategory":"Motor Vehicles",
            "type":"Manufacturing & Wholesale Goods"
        }
    ],
    "sg:phone":"+1 910 654 3507",
    "sg:postcode":"28431",
    "sg:province":"NC",
    "sg:tags":[
        "automobile",
        "dealer"
    ],
    "wof:name":"Big Will's Auto Sales",
    "wof:placetype":"venue"
},
  "geometry": {"coordinates":[-78.859882,34.333016],"type":"Point"}
}