{
  "type": "Feature",
  "properties": {
    "iso:country":"US",
    "sg:address":"6645 Pine Hall Rd",
    "sg:city":"Belews Creek",
    "sg:classifiers":[
        {
            "category":"Building & Trades",
            "subcategory":"Electrical",
            "type":"Services"
        }
    ],
    "sg:phone":"+1 336 595 4803",
    "sg:postcode":"27009",
    "sg:province":"NC",
    "sg:tags":[
        "electrical",
        "work",
        "wiring",
        "electric",
        "contractor"
    ],
    "wof:name":"Carter Electric Co Inc",
    "wof:placetype":"venue"
},
  "geometry": {"coordinates":[-80.111165,36.230062],"type":"Point"}
}