{
  "type": "Feature",
  "properties": {
    "iso:country":"US",
    "sg:address":"1471 Runabout Rd",
    "sg:city":"Pfafftown",
    "sg:classifiers":[
        {
            "category":"Building & Trades",
            "subcategory":"Landscaping Services",
            "type":"Services"
        }
    ],
    "sg:phone":"+1 336 945 2981",
    "sg:postcode":"27023",
    "sg:province":"NC",
    "wof:name":"Warlicks Tree Service",
    "wof:placetype":"venue"
},
  "geometry": {"coordinates":[-80.41600099999999,36.122184],"type":"Point"}
}