{
  "type": "Feature",
  "properties": {
    "iso:country":"US",
    "sg:address":"4710 Waldorf Dr",
    "sg:city":"Greensboro",
    "sg:classifiers":[
        {
            "category":"Banks & Credit Unions",
            "subcategory":"Financial Services",
            "type":"Services"
        }
    ],
    "sg:phone":"+1 336 288 0832",
    "sg:postcode":"27455",
    "sg:province":"NC",
    "sg:tags":[
        "investor"
    ],
    "wof:name":"Uplink Investment Club LLC",
    "wof:placetype":"venue"
},
  "geometry": {"coordinates":[-79.795,36.146776],"type":"Point"}
}