{
  "type": "Feature",
  "properties": {
    "addr:full":"116 Roper St Belmont NC 28012",
    "addr:housenumber":"116",
    "addr:postcode":"28012",
    "addr:street":"Roper St",
    "iso:country":"US",
    "sg:address":"116 Roper St",
    "sg:city":"Belmont",
    "sg:classifiers":[
        {
            "category":"Building & Trades",
            "subcategory":"Equipment Rental",
            "type":"Services"
        }
    ],
    "sg:phone":"+1   ",
    "sg:postcode":"28012",
    "sg:province":"NC",
    "wof:name":"AB Leasing Co Inc",
    "wof:placetype":"venue"
},
  "geometry": {"coordinates":[-81.049009,35.271407],"type":"Point"}
}