{
  "type": "Feature",
  "properties": {
    "addr:full":"217 E Sugar Creek Rd Charlotte NC 28213",
    "addr:housenumber":"217",
    "addr:postcode":"28213",
    "addr:street":"E Sugar Creek Rd",
    "iso:country":"US",
    "sg:address":"217 E Sugar Creek Rd",
    "sg:city":"Charlotte",
    "sg:classifiers":[
        {
            "category":"Restaurant",
            "type":"Food & Drink"
        }
    ],
    "sg:phone":"+1 704 509 4611",
    "sg:postcode":"28213",
    "sg:province":"NC",
    "wof:name":"Breeze Cafe & Lounge",
    "wof:placetype":"venue"
},
  "geometry": {"coordinates":[-80.793127,35.254902],"type":"Point"}
}