{
  "type": "Feature",
  "properties": {
    "addr:full":"2525 Fort St Charlotte NC 28205",
    "addr:housenumber":"2525",
    "addr:postcode":"28205",
    "addr:street":"Fort St",
    "iso:country":"US",
    "sg:address":"2525 Fort St",
    "sg:city":"Charlotte",
    "sg:classifiers":[
        {
            "category":"Building & Trades",
            "subcategory":"Construction",
            "type":"Services"
        }
    ],
    "sg:phone":"+1 704 890 4748",
    "sg:postcode":"28205",
    "sg:province":"NC",
    "sg:tags":[
        "home",
        "improvement"
    ],
    "wof:name":"J P Group Construction Inc",
    "wof:placetype":"venue"
},
  "geometry": {"coordinates":[-80.799228,35.232543],"type":"Point"}
}