{
  "type": "Feature",
  "properties": {
    "iso:country":"US",
    "sg:address":"2075 Centennial Rd",
    "sg:city":"Union Mills",
    "sg:classifiers":[
        {
            "category":"Manufacturing",
            "subcategory":"Paper Products",
            "type":"Manufacturing & Wholesale Goods"
        }
    ],
    "sg:phone":"+1 828 287 8003",
    "sg:postcode":"28167",
    "sg:province":"NC",
    "sg:tags":[
        "mill",
        "pulp"
    ],
    "wof:name":"Broad River Forest Products",
    "wof:placetype":"venue"
},
  "geometry": {"coordinates":[-81.920558,35.468306],"type":"Point"}
}