{
  "type": "Feature",
  "properties": {
    "iso:country":"US",
    "sg:address":"1028 S Madison St",
    "sg:city":"Whiteville",
    "sg:phone":"+1 910 642 4137",
    "sg:postcode":"28472",
    "sg:province":"NC",
    "sg:tags":[
        "gas"
    ],
    "wof:name":"Diversified Energy",
    "wof:placetype":"venue"
},
  "geometry": {"coordinates":[-78.705202,34.318745],"type":"Point"}
}