{
  "type": "Feature",
  "properties": {
    "iso:country":"US",
    "sg:address":"818 Tyvola Rd",
    "sg:city":"Charlotte",
    "sg:classifiers":[
        {
            "category":"Professional",
            "subcategory":"Management & Consulting",
            "type":"Services"
        }
    ],
    "sg:phone":"+1 704 679 9990",
    "sg:postcode":"28217",
    "sg:province":"NC",
    "sg:tags":[
        "marketing",
        "consultant"
    ],
    "wof:name":"L D Bennett & Assoc",
    "wof:placetype":"venue"
},
  "geometry": {"coordinates":[-80.882682,35.164798],"type":"Point"}
}