{
  "type": "Feature",
  "properties": {
    "iso:country":"US",
    "sg:address":"262 W Center St",
    "sg:city":"Welcome",
    "sg:classifiers":[
        {
            "category":"Wholesale",
            "subcategory":"Stationery",
            "type":"Manufacturing & Wholesale Goods"
        }
    ],
    "sg:phone":"+1 336 731 7787",
    "sg:postcode":"27302",
    "sg:province":"NC",
    "sg:tags":[
        "product",
        "paper"
    ],
    "wof:name":"Summer Industries",
    "wof:placetype":"venue"
},
  "geometry": {"coordinates":[-79.270184,36.096866],"type":"Point"}
}