{
  "type": "Feature",
  "properties": {
    "iso:country":"US",
    "sg:address":"1411 Aversboro Rd",
    "sg:city":"Garner",
    "sg:classifiers":[
        {
            "category":"Personal",
            "subcategory":"Beauty Salon",
            "type":"Services"
        }
    ],
    "sg:phone":"+1 919 772 5002",
    "sg:postcode":"27529",
    "sg:province":"NC",
    "wof:name":"Shear Glory Salon",
    "wof:placetype":"venue"
},
  "geometry": {"coordinates":[-78.61655,35.695048],"type":"Point"}
}