{
  "type": "Feature",
  "properties": {
    "addr:full":"321 Clegg St Statesville NC 28677",
    "addr:housenumber":"321",
    "addr:postcode":"28677",
    "addr:street":"Clegg St",
    "iso:country":"US",
    "sg:address":"321 Clegg St",
    "sg:city":"Statesville",
    "sg:classifiers":[
        {
            "category":"Education",
            "subcategory":"School",
            "type":"Public Place"
        }
    ],
    "sg:phone":"+1 704 872 2135",
    "sg:postcode":"28677",
    "sg:province":"NC",
    "sg:website":"www.iss.k12.nc.us",
    "wof:name":"Statesville Middle School",
    "wof:placetype":"venue"
},
  "geometry": {"coordinates":[-80.872418,35.787235],"type":"Point"}
}