{
  "type": "Feature",
  "properties": {
    "iso:country":"US",
    "sg:address":"101 Professional Ct",
    "sg:city":"Garner",
    "sg:classifiers":[
        {
            "category":"Sports & Exercise",
            "subcategory":"Gym",
            "type":"Entertainment"
        }
    ],
    "sg:phone":"+1 919 772 9900",
    "sg:postcode":"27529",
    "sg:province":"NC",
    "sg:tags":[
        "fitness",
        "physical",
        "facility"
    ],
    "sg:website":"www.fflhealthclub.com",
    "wof:name":"Fit For Life Health Club",
    "wof:placetype":"venue"
},
  "geometry": {"coordinates":[-78.569695,35.608133],"type":"Point"}
}