{
  "type": "Feature",
  "properties": {
    "addr:full":"427 Hollis Rd Charlotte NC 28209",
    "addr:housenumber":"427",
    "addr:postcode":"28209",
    "addr:street":"Hollis Rd",
    "iso:country":"US",
    "sg:address":"427 Hollis Rd",
    "sg:city":"Charlotte",
    "sg:classifiers":[
        {
            "category":"Building & Trades",
            "subcategory":"Cleaning & Sanitation",
            "type":"Services"
        }
    ],
    "sg:phone":"+1   ",
    "sg:postcode":"28209",
    "sg:province":"NC",
    "sg:tags":[
        "maintenance"
    ],
    "wof:name":"Clean Castles",
    "wof:placetype":"venue"
},
  "geometry": {"coordinates":[-80.86786600000001,35.190103],"type":"Point"}
}