{
  "type": "Feature",
  "properties": {
    "addr:full":"62 Haywood St Asheville NC 28801",
    "addr:housenumber":"62",
    "addr:postcode":"28801",
    "addr:street":"Haywood St",
    "iso:country":"US",
    "sg:address":"62 Haywood St",
    "sg:city":"Asheville",
    "sg:classifiers":[
        {
            "category":"Shopping",
            "subcategory":"Stationery & Office Supplies",
            "type":"Retail Goods"
        },
        {
            "category":"Shopping",
            "type":"Retail Goods"
        }
    ],
    "sg:phone":"+1 828 236 9815",
    "sg:postcode":"28801",
    "sg:province":"NC",
    "sg:tags":[
        "map",
        "chart"
    ],
    "wof:name":"Map & Globe Store LLC",
    "wof:placetype":"venue"
},
  "geometry": {"coordinates":[-82.55535999999999,35.596457],"type":"Point"}
}