{
  "type": "Feature",
  "properties": {
    "addr:full":"345 Pugh Rd Clinton NC 28328",
    "addr:housenumber":"345",
    "addr:postcode":"28328",
    "addr:street":"Pugh Rd",
    "iso:country":"US",
    "sg:address":"345 Pugh Rd",
    "sg:city":"Clinton",
    "sg:classifiers":[
        {
            "category":"Wholesale",
            "subcategory":"Farm Supplies",
            "type":"Manufacturing & Wholesale Goods"
        }
    ],
    "sg:phone":"+1 910 592 8078",
    "sg:postcode":"28328",
    "sg:province":"NC",
    "sg:tags":[
        "fertilizer"
    ],
    "wof:name":"Royster-Clark Inc",
    "wof:placetype":"venue"
},
  "geometry": {"coordinates":[-78.307855,35.002869],"type":"Point"}
}