{
  "type": "Feature",
  "properties": {
    "iso:country":"US",
    "sg:address":"107 Greenmeadows Ct",
    "sg:city":"Gastonia",
    "sg:classifiers":[
        {
            "category":"Building & Trades",
            "subcategory":"Construction",
            "type":"Services"
        }
    ],
    "sg:phone":"+1 704 868 2550",
    "sg:postcode":"28056",
    "sg:province":"NC",
    "sg:tags":[
        "contractor"
    ],
    "wof:name":"Duquettte Siding",
    "wof:placetype":"venue"
},
  "geometry": {"coordinates":[-81.136625,35.1637],"type":"Point"}
}