{
  "type": "Feature",
  "properties": {
    "addr:full":"1001 Blythe Blvd Charlotte NC 28203",
    "addr:housenumber":"1001",
    "addr:postcode":"28203",
    "addr:street":"Blythe Blvd",
    "iso:country":"US",
    "sg:address":"1001 Blythe Blvd",
    "sg:city":"Charlotte",
    "sg:classifiers":[
        {
            "category":"Professional",
            "subcategory":"Research",
            "type":"Services"
        }
    ],
    "sg:phone":"+1 704 374 0505",
    "sg:postcode":"28203",
    "sg:province":"NC",
    "sg:tags":[
        "development",
        "human",
        "factor"
    ],
    "wof:name":"Heineman Medical Research Ctr",
    "wof:placetype":"venue"
},
  "geometry": {"coordinates":[-80.83843,35.204725],"type":"Point"}
}