{
  "type": "Feature",
  "properties": {
    "addr:full":"795 Roberts Rd Newport NC 28570",
    "addr:housenumber":"795",
    "addr:postcode":"28570",
    "addr:street":"Roberts Rd",
    "iso:country":"US",
    "sg:address":"795 Roberts Rd",
    "sg:city":"Newport",
    "sg:classifiers":[
        {
            "category":"Building & Trades",
            "subcategory":"Construction",
            "type":"Services"
        }
    ],
    "sg:phone":"+1 252 223 3909",
    "sg:postcode":"28570",
    "sg:province":"NC",
    "sg:tags":[
        "contractor"
    ],
    "wof:name":"Johnston & Johnston Builders",
    "wof:placetype":"venue"
},
  "geometry": {"coordinates":[-76.88803299999999,34.778944],"type":"Point"}
}