{
  "type": "Feature",
  "properties": {
    "iso:country":"US",
    "sg:address":"540 Ellynn Dr",
    "sg:city":"Cary",
    "sg:classifiers":[
        {
            "category":"Professional",
            "subcategory":"Engineering",
            "type":"Services"
        }
    ],
    "sg:phone":"+1   ",
    "sg:postcode":"27511",
    "sg:province":"NC",
    "wof:name":"Megaplexx Corp",
    "wof:placetype":"venue"
},
  "geometry": {"coordinates":[-78.77246,35.774495],"type":"Point"}
}