{
  "type": "Feature",
  "properties": {
    "iso:country":"US",
    "sg:address":"7713 Glencannon Dr",
    "sg:city":"Charlotte",
    "sg:classifiers":[
        {
            "category":"Wholesale",
            "subcategory":"Metals & Minerals",
            "type":"Manufacturing & Wholesale Goods"
        }
    ],
    "sg:phone":"+1 704 536 2497",
    "sg:postcode":"28227",
    "sg:province":"NC",
    "sg:tags":[
        "center"
    ],
    "wof:name":"J&J Prewire Construction Co",
    "wof:placetype":"venue"
},
  "geometry": {"coordinates":[-80.71475,35.212312],"type":"Point"}
}