{
  "type": "Feature",
  "properties": {
    "iso:country":"US",
    "sg:address":"222 Hawthorn Dr",
    "sg:city":"Hendersonville",
    "sg:classifiers":[
        {
            "category":"Professional",
            "subcategory":"Computer Services",
            "type":"Services"
        }
    ],
    "sg:phone":"+1 828 890 1111",
    "sg:postcode":"28791",
    "sg:province":"NC",
    "sg:tags":[
        "programing",
        "custom"
    ],
    "sg:website":"www.access-ct.com",
    "wof:name":"Access Computer Technology",
    "wof:placetype":"venue"
},
  "geometry": {"coordinates":[-82.508678,35.333335],"type":"Point"}
}