{
  "type": "Feature",
  "properties": {
    "addr:full":"6589 Murrayville Rd Wilmington NC 28411",
    "addr:housenumber":"6589",
    "addr:postcode":"28411",
    "addr:street":"Murrayville Rd",
    "iso:country":"US",
    "sg:address":"6589 Murrayville Rd",
    "sg:city":"Wilmington",
    "sg:classifiers":[
        {
            "category":"Building & Trades",
            "subcategory":"Construction",
            "type":"Services"
        }
    ],
    "sg:phone":"+1 910 799 2055",
    "sg:postcode":"28411",
    "sg:province":"NC",
    "sg:tags":[
        "house"
    ],
    "wof:name":"Albert Joseph Builder Valade",
    "wof:placetype":"venue"
},
  "geometry": {"coordinates":[-77.847103,34.295683],"type":"Point"}
}