{
  "type": "Feature",
  "properties": {
    "addr:full":"1225 Holland Rd Apex NC 27526",
    "addr:housenumber":"1225",
    "addr:postcode":"27526",
    "addr:street":"Holland Rd",
    "iso:country":"US",
    "sg:address":"1225 Holland Rd",
    "sg:city":"Apex",
    "sg:classifiers":[
        {
            "category":"Real Estate",
            "subcategory":"Real Estate Agent",
            "type":"Services"
        }
    ],
    "sg:phone":"+1 919 303 3666",
    "sg:postcode":"27526",
    "sg:province":"NC",
    "wof:name":"Landcore Commercial RE",
    "wof:placetype":"venue"
},
  "geometry": {"coordinates":[-78.773268,35.57117],"type":"Point"}
}