{
  "type": "Feature",
  "properties": {
    "iso:country":"US",
    "sg:address":"161 3rd St NE",
    "sg:city":"Hildebran",
    "sg:classifiers":[
        {
            "category":"Building & Trades",
            "subcategory":"Landscaping Services",
            "type":"Services"
        }
    ],
    "sg:phone":"+1 828 397 5953",
    "sg:postcode":"28637",
    "sg:province":"NC",
    "sg:tags":[
        "landscape"
    ],
    "wof:name":"J & N Landscaping",
    "wof:placetype":"venue"
},
  "geometry": {"coordinates":[-81.421725,35.720962],"type":"Point"}
}