{
  "type": "Feature",
  "properties": {
    "addr:full":"3443 Gray Moss Rd Charlotte NC 28270",
    "addr:housenumber":"3443",
    "addr:postcode":"28270",
    "addr:street":"Gray Moss Rd",
    "iso:country":"US",
    "sg:address":"3443 Gray Moss Rd",
    "sg:city":"Charlotte",
    "sg:classifiers":[
        {
            "category":"Professional",
            "subcategory":"Advertising",
            "type":"Services"
        }
    ],
    "sg:phone":"+1 704 814 7157",
    "sg:postcode":"28270",
    "sg:province":"NC",
    "sg:tags":[
        "agency",
        "specialty"
    ],
    "sg:website":"http://www.griffin-media.com",
    "wof:name":"Griffin Media, Inc",
    "wof:placetype":"venue"
},
  "geometry": {"coordinates":[-80.747137,35.076999],"type":"Point"}
}