{
  "type": "Feature",
  "properties": {
    "iso:country":"US",
    "sg:address":"9339 Four Mile Creek Rd",
    "sg:city":"Charlotte",
    "sg:classifiers":[
        {
            "category":"Professional",
            "subcategory":"Employment Agencies",
            "type":"Services"
        }
    ],
    "sg:phone":"+1 704 957 2152",
    "sg:postcode":"28277",
    "sg:province":"NC",
    "sg:tags":[
        "consultant",
        "search",
        "executive"
    ],
    "wof:name":"Creative Search Solutions",
    "wof:placetype":"venue"
},
  "geometry": {"coordinates":[-80.78102800000001,35.083462],"type":"Point"}
}