{
  "type": "Feature",
  "properties": {
    "iso:country":"US",
    "sg:address":"4100 Carmel Rd",
    "sg:city":"Charlotte",
    "sg:classifiers":[
        {
            "category":"Retail",
            "subcategory":"Repair Shop",
            "type":"Services"
        }
    ],
    "sg:phone":"+1   ",
    "sg:postcode":"28226",
    "sg:province":"NC",
    "wof:name":"Faux Finished Furniture",
    "wof:placetype":"venue"
},
  "geometry": {"coordinates":[-80.822429,35.11777],"type":"Point"}
}