{
  "type": "Feature",
  "properties": {
    "iso:country":"US",
    "sg:address":"2721 Charleston Oaks Dr",
    "sg:city":"Raleigh",
    "sg:classifiers":[
        {
            "category":"Professional",
            "subcategory":"Management & Consulting",
            "type":"Services"
        }
    ],
    "sg:phone":"+1   ",
    "sg:postcode":"27614",
    "sg:province":"NC",
    "wof:name":"Acudata Marketing Service",
    "wof:placetype":"venue"
},
  "geometry": {"coordinates":[-78.55394699999999,35.957537],"type":"Point"}
}