{
  "type": "Feature",
  "properties": {
    "iso:country":"US",
    "sg:address":"425 Fenton Pl",
    "sg:city":"Charlotte",
    "sg:classifiers":[
        {
            "category":"Real Estate",
            "subcategory":"Real Estate Services",
            "type":"Services"
        }
    ],
    "sg:phone":"+1 704 377 4599",
    "sg:postcode":"28207",
    "sg:province":"NC",
    "sg:tags":[
        "management",
        "condominium"
    ],
    "wof:name":"Fentonplace Condominium Owners Association",
    "wof:placetype":"venue"
},
  "geometry": {"coordinates":[-80.82220700000001,35.201346],"type":"Point"}
}