{
  "type": "Feature",
  "properties": {
    "iso:country":"US",
    "sg:address":"9420 Guernsey Ct",
    "sg:city":"Charlotte",
    "sg:classifiers":[
        {
            "category":"Building & Trades",
            "subcategory":"Construction",
            "type":"Services"
        }
    ],
    "sg:phone":"+1 704 522 7923",
    "sg:postcode":"28213",
    "sg:province":"NC",
    "sg:tags":[
        "hanging",
        "painter",
        "contractor"
    ],
    "wof:name":"Pearson's Painting",
    "wof:placetype":"venue"
},
  "geometry": {"coordinates":[-80.712964,35.295003],"type":"Point"}
}