{
  "type": "Feature",
  "properties": {
    "addr:full":"1497 Concord Pkwy N Concord NC 28025",
    "addr:housenumber":"1497",
    "addr:postcode":"28025",
    "addr:street":"Concord Pkwy N",
    "iso:country":"US",
    "sg:address":"1497 Concord Pkwy N",
    "sg:city":"Concord",
    "sg:classifiers":[
        {
            "category":"Restaurant",
            "type":"Food & Drink"
        }
    ],
    "sg:menulink":"http://www.allmenus.com/nc/concord/51208-hokkaido-japanese-express/menu/",
    "sg:phone":"+1 704 788 2882",
    "sg:postcode":"28025",
    "sg:province":"NC",
    "sg:tags":[
        "japanese",
        "asian"
    ],
    "wof:name":"Hokkaido Japanese Express",
    "wof:placetype":"venue"
},
  "geometry": {"coordinates":[-80.606298,35.439324],"type":"Point"}
}