{
  "type": "Feature",
  "properties": {
    "addr:full":"244 5th Ave W Hendersonville NC 28739",
    "addr:housenumber":"244",
    "addr:postcode":"28739",
    "addr:street":"5Th Ave W",
    "iso:country":"US",
    "sg:address":"244 5th Ave W",
    "sg:city":"Hendersonville",
    "sg:classifiers":[
        {
            "category":"Banks & Credit Unions",
            "subcategory":"Bank",
            "type":"Services"
        }
    ],
    "sg:phone":"+1 828 698 1105",
    "sg:postcode":"28739",
    "sg:province":"NC",
    "sg:tags":[
        "loan",
        "real estate"
    ],
    "wof:name":"Southern Mortgage Source Inc",
    "wof:placetype":"venue"
},
  "geometry": {"coordinates":[-82.46214500000001,35.317423],"type":"Point"}
}