{
  "type": "Feature",
  "properties": {
    "addr:full":"810 Oregon Ave Kannapolis NC 28083",
    "addr:housenumber":"810",
    "addr:postcode":"28083",
    "addr:street":"Oregon Ave",
    "iso:country":"US",
    "sg:address":"810 Oregon Ave",
    "sg:city":"Kannapolis",
    "sg:classifiers":[
        {
            "category":"Personal",
            "type":"Services"
        },
        {
            "category":"Retail",
            "subcategory":"Storage",
            "type":"Services"
        }
    ],
    "sg:phone":"+1 877 258 8230",
    "sg:postcode":"28083",
    "sg:province":"NC",
    "sg:tags":[
        "self",
        "full",
        "commercial",
        "mover",
        "household"
    ],
    "sg:website":"http://www.publicstorage.com/?pid=ypcomCPCingenio",
    "wof:name":"Public Storage",
    "wof:placetype":"venue"
},
  "geometry": {"coordinates":[-80.60829699999999,35.454772],"type":"Point"}
}