{
  "type": "Feature",
  "properties": {
    "addr:full":"13735 Steele Creek Rd Charlotte NC 28273",
    "addr:housenumber":"13735",
    "addr:postcode":"28273",
    "addr:street":"Steele Creek Rd",
    "iso:country":"US",
    "sg:address":"13735 Steele Creek Rd",
    "sg:city":"Charlotte",
    "sg:classifiers":[
        {
            "category":"Shopping",
            "type":"Retail Goods"
        }
    ],
    "sg:phone":"+1 704 587 9350",
    "sg:postcode":"28273",
    "sg:province":"NC",
    "sg:tags":[
        "fine",
        "art",
        "gallery",
        "artist"
    ],
    "wof:name":"Winget Art",
    "wof:placetype":"venue"
},
  "geometry": {"coordinates":[-80.98843599999999,35.106878],"type":"Point"}
}