{
  "type": "Feature",
  "properties": {
    "addr:full":"285 Eagle Rd Newport NC 28570",
    "addr:housenumber":"285",
    "addr:postcode":"28570",
    "addr:street":"Eagle Rd",
    "iso:country":"US",
    "sg:address":"285 Eagle Rd",
    "sg:city":"Newport",
    "sg:classifiers":[
        {
            "category":"Building & Trades",
            "subcategory":"Construction",
            "type":"Services"
        }
    ],
    "sg:phone":"+1 252 726 7746",
    "sg:postcode":"28570",
    "sg:province":"NC",
    "sg:tags":[
        "contractor"
    ],
    "wof:name":"Atlantic Siding Inc",
    "wof:placetype":"venue"
},
  "geometry": {"coordinates":[-76.890399,34.74418],"type":"Point"}
}