{
  "type": "Feature",
  "properties": {
    "iso:country":"US",
    "sg:address":"243 Sycamore Dr",
    "sg:city":"Arden",
    "sg:classifiers":[
        {
            "category":"Retail",
            "subcategory":"Auto Repair",
            "type":"Services"
        }
    ],
    "sg:phone":"+1 828 684 1125",
    "sg:postcode":"28704",
    "sg:province":"NC",
    "sg:tags":[
        "wrecker"
    ],
    "wof:name":"Roberts Towing & Transport",
    "wof:placetype":"venue"
},
  "geometry": {"coordinates":[-82.514433,35.474028],"type":"Point"}
}