{
  "type": "Feature",
  "properties": {
    "iso:country":"US",
    "sg:address":"4433 Long Beach Rd SE",
    "sg:city":"Southport",
    "sg:classifiers":[
        {
            "category":"Banks & Credit Unions",
            "subcategory":"Bank",
            "type":"Services"
        }
    ],
    "sg:phone":"+1 910 454 0024",
    "sg:postcode":"28461",
    "sg:province":"NC",
    "sg:tags":[
        "loan"
    ],
    "wof:name":"Coastal Finance Co",
    "wof:placetype":"venue"
},
  "geometry": {"coordinates":[-78.06068999999999,33.939779],"type":"Point"}
}