{
  "type": "Feature",
  "properties": {
    "iso:country":"US",
    "sg:address":"9221 Bracken Ln",
    "sg:city":"Chapel Hill",
    "sg:classifiers":[
        {
            "category":"Professional",
            "subcategory":"Management & Consulting",
            "type":"Services"
        }
    ],
    "sg:phone":"+1   ",
    "sg:postcode":"27510",
    "sg:province":"NC",
    "sg:tags":[
        "business"
    ],
    "wof:name":"Saw Dog Woodworks",
    "wof:placetype":"venue"
},
  "geometry": {"coordinates":[-79.19197699999999,35.934473],"type":"Point"}
}