{
  "type": "Feature",
  "properties": {
    "iso:country":"US",
    "sg:address":"8330 Pineville-Matthews Rd",
    "sg:city":"Charlotte",
    "sg:classifiers":[
        {
            "category":"Shopping",
            "subcategory":"Discount & Variety Stores",
            "type":"Retail Goods"
        }
    ],
    "sg:phone":"+1 704 540 7121",
    "sg:postcode":"28226",
    "sg:province":"NC",
    "wof:name":"Dollar Tree",
    "wof:placetype":"venue"
},
  "geometry": {"coordinates":[-80.861513,35.08762],"type":"Point"}
}