{
  "type": "Feature",
  "properties": {
    "iso:country":"US",
    "sg:address":"98 Fair Hollow Ln",
    "sg:city":"Hendersonville",
    "sg:classifiers":[
        {
            "category":"Autos & Motor Vehicles",
            "subcategory":"Automobile Sales",
            "type":"Retail Goods"
        }
    ],
    "sg:phone":"+1 828 685 0355",
    "sg:postcode":"28792",
    "sg:province":"NC",
    "sg:tags":[
        "performance",
        "race",
        "dealer"
    ],
    "sg:website":"www.teammms.com",
    "wof:name":"Mountain Machine Svc",
    "wof:placetype":"venue"
},
  "geometry": {"coordinates":[-82.41239899999999,35.403359],"type":"Point"}
}