{
  "type": "Feature",
  "properties": {
    "addr:full":"3760 N Liberty St Winston Salem NC 27105",
    "addr:housenumber":"3760",
    "addr:postcode":"27105",
    "addr:street":"N Liberty St",
    "iso:country":"US",
    "sg:address":"3760 N Liberty St",
    "sg:city":"Winston Salem",
    "sg:classifiers":[
        {
            "category":"Wholesale",
            "subcategory":"Machinery & Supplies",
            "type":"Manufacturing & Wholesale Goods"
        }
    ],
    "sg:phone":"+1 336 767 6900",
    "sg:postcode":"27105",
    "sg:province":"NC",
    "sg:tags":[
        "contractor"
    ],
    "sg:website":"www.jwburress.com",
    "wof:name":"J W Burress Inc",
    "wof:placetype":"venue"
},
  "geometry": {"coordinates":[-80.229839,36.138168],"type":"Point"}
}