{
  "type": "Feature",
  "properties": {
    "iso:country":"US",
    "sg:address":"129 Colington Creek Rd",
    "sg:city":"Kill Devil Hills",
    "sg:classifiers":[
        {
            "category":"Building & Trades",
            "subcategory":"Cleaning & Sanitation",
            "type":"Services"
        }
    ],
    "sg:phone":"+1   ",
    "sg:postcode":"27948",
    "sg:province":"NC",
    "sg:tags":[
        "maintenance"
    ],
    "wof:name":"Consider It Clean",
    "wof:placetype":"venue"
},
  "geometry": {"coordinates":[-75.680235,36.007722],"type":"Point"}
}