{
  "type": "Feature",
  "properties": {
    "iso:country":"US",
    "sg:address":"5201 Duckdown Ct",
    "sg:city":"Raleigh",
    "sg:classifiers":[
        {
            "category":"Real Estate",
            "subcategory":"Real Estate Agent",
            "type":"Services"
        }
    ],
    "sg:phone":"+1 919 212 1622",
    "sg:postcode":"27604",
    "sg:province":"NC",
    "sg:tags":[
        "agency"
    ],
    "wof:name":"Westmnster Hmes Pinehall Plntn",
    "wof:placetype":"venue"
},
  "geometry": {"coordinates":[-78.551704,35.820052],"type":"Point"}
}