{
  "type": "Feature",
  "properties": {
    "iso:country":"US",
    "sg:address":"945 State Hwy 152 W",
    "sg:city":"China Grove",
    "sg:classifiers":[
        {
            "category":"Wholesale",
            "subcategory":"Computers",
            "type":"Manufacturing & Wholesale Goods"
        }
    ],
    "sg:phone":"+1 704 857 8744",
    "sg:postcode":"28023",
    "sg:province":"NC",
    "sg:tags":[
        "related",
        "software"
    ],
    "wof:name":"Bai",
    "wof:placetype":"venue"
},
  "geometry": {"coordinates":[-80.596394,35.579281],"type":"Point"}
}