{
  "type": "Feature",
  "properties": {
    "iso:country":"US",
    "sg:address":"3131 Brookforest Dr",
    "sg:city":"Greensboro",
    "sg:phone":"+1 336 379 1736",
    "sg:postcode":"27406",
    "sg:province":"NC",
    "sg:tags":[
        "equipment",
        "commercial"
    ],
    "wof:name":"Carroll Equipment Inc",
    "wof:placetype":"venue"
},
  "geometry": {"coordinates":[-79.72626099999999,36.007329],"type":"Point"}
}