{
  "type": "Feature",
  "properties": {
    "addr:full":"105 E Trollinger Ave Elon College NC 27244",
    "addr:housenumber":"105",
    "addr:postcode":"27244",
    "addr:street":"E Trollinger Ave Elon",
    "iso:country":"US",
    "sg:address":"105 E Trollinger Ave",
    "sg:city":"Elon College",
    "sg:classifiers":[
        {
            "category":"Shopping",
            "subcategory":"Used Merchandise",
            "type":"Retail Goods"
        }
    ],
    "sg:phone":"+1 336 524 0077",
    "sg:postcode":"27244",
    "sg:province":"NC",
    "sg:tags":[
        "antique"
    ],
    "wof:name":"Annie Pearls Consignment Gllry",
    "wof:placetype":"venue"
},
  "geometry": {"coordinates":[-79.505268,36.100308],"type":"Point"}
}