{
  "type": "Feature",
  "properties": {
    "addr:full":"2750 Rowan Rd Clinton NC 28328",
    "addr:housenumber":"2750",
    "addr:postcode":"28328",
    "addr:street":"Rowan Rd",
    "iso:country":"US",
    "sg:address":"2750 Rowan Rd",
    "sg:city":"Clinton",
    "sg:classifiers":[
        {
            "category":"Manufacturing",
            "subcategory":"Food",
            "type":"Manufacturing & Wholesale Goods"
        }
    ],
    "sg:phone":"+1 910 592 5934",
    "sg:postcode":"28328",
    "sg:province":"NC",
    "sg:tags":[
        "baker",
        "mfg",
        "product",
        "supply"
    ],
    "wof:name":"Noel's E-Z Bake Inc",
    "wof:placetype":"venue"
},
  "geometry": {"coordinates":[-78.25828799999999,34.974373],"type":"Point"}
}