{
  "type": "Feature",
  "properties": {
    "iso:country":"US",
    "sg:address":"144 Coxe Ave",
    "sg:city":"Asheville",
    "sg:classifiers":[
        {
            "category":"Professional",
            "subcategory":"Art Services",
            "type":"Services"
        }
    ],
    "sg:phone":"+1 828 253 1634",
    "sg:postcode":"28801",
    "sg:province":"NC",
    "sg:tags":[
        "photographer"
    ],
    "sg:website":"www.rbaimaging.com",
    "wof:name":"Richard Brown & Assoc Inc",
    "wof:placetype":"venue"
},
  "geometry": {"coordinates":[-82.554973,35.590977],"type":"Point"}
}