{
  "type": "Feature",
  "properties": {
    "addr:full":"1108 Canal Dr Carolina Beach NC 28428",
    "addr:housenumber":"1108",
    "addr:postcode":"28428",
    "addr:street":"Canal Dr",
    "iso:country":"US",
    "sg:address":"1108 Canal Dr",
    "sg:city":"Carolina Beach",
    "sg:classifiers":[
        {
            "category":"Shopping",
            "subcategory":"Optical Goods",
            "type":"Retail Goods"
        }
    ],
    "sg:phone":"+1 910 458 3625",
    "sg:postcode":"28428",
    "sg:province":"NC",
    "wof:name":"Donnie R Kennedy Opt",
    "wof:placetype":"venue"
},
  "geometry": {"coordinates":[-77.88686800000001,34.048862],"type":"Point"}
}