{
  "type": "Feature",
  "properties": {
    "iso:country":"US",
    "sg:address":"301 Roberts Hill Rd",
    "sg:city":"Marshall",
    "sg:classifiers":[
        {
            "category":"Professional",
            "type":"Services"
        }
    ],
    "sg:phone":"+1 828 649 9289",
    "sg:postcode":"28753",
    "sg:province":"NC",
    "wof:name":"Madison Friends Program",
    "wof:placetype":"venue"
},
  "geometry": {"coordinates":[-82.69567000000001,35.8069],"type":"Point"}
}