{
  "type": "Feature",
  "properties": {
    "iso:country":"US",
    "sg:address":"5834 Bur-Mill Club Rd",
    "sg:city":"Greensboro",
    "sg:classifiers":[
        {
            "category":"Recreation",
            "type":"Entertainment"
        }
    ],
    "sg:phone":"+1 336 510 4653",
    "sg:postcode":"27410",
    "sg:province":"NC",
    "sg:tags":[
        "tennis",
        "instruction"
    ],
    "wof:name":"Robert Linville's Prcsion Golf",
    "wof:placetype":"venue"
},
  "geometry": {"coordinates":[-79.87064700000001,36.161914],"type":"Point"}
}