{
  "type": "Feature",
  "properties": {
    "iso:country":"US",
    "sg:address":"6404 Old Plank Rd",
    "sg:city":"Charlotte",
    "sg:classifiers":[
        {
            "category":"Real Estate",
            "subcategory":"Real Estate Operator",
            "type":"Services"
        }
    ],
    "sg:phone":"+1 704 399 5179",
    "sg:postcode":"28216",
    "sg:province":"NC",
    "sg:tags":[
        "mobile",
        "home",
        "site",
        "community"
    ],
    "wof:name":"Sunset Grove Mobile Homes Park",
    "wof:placetype":"venue"
},
  "geometry": {"coordinates":[-80.90719199999999,35.293346],"type":"Point"}
}