{
  "type": "Feature",
  "properties": {
    "iso:country":"US",
    "sg:address":"8300 Meadow Ridge Ct",
    "sg:city":"Raleigh",
    "sg:classifiers":[
        {
            "category":"Building & Trades",
            "subcategory":"Electrical",
            "type":"Services"
        }
    ],
    "sg:phone":"+1 919 848 8719",
    "sg:postcode":"27615",
    "sg:province":"NC",
    "sg:tags":[
        "electrical",
        "contractor"
    ],
    "wof:name":"Atlantic Coast Controls",
    "wof:placetype":"venue"
},
  "geometry": {"coordinates":[-78.643489,35.893657],"type":"Point"}
}