{
  "type": "Feature",
  "properties": {
    "addr:full":"2759 Interstate St Charlotte NC 28208",
    "addr:housenumber":"2759",
    "addr:postcode":"28208",
    "addr:street":"Interstate St",
    "iso:country":"US",
    "sg:address":"2759 Interstate St",
    "sg:city":"Charlotte",
    "sg:classifiers":[
        {
            "category":"Building & Trades",
            "subcategory":"Construction",
            "type":"Services"
        }
    ],
    "sg:phone":"+1 704 932 0809",
    "sg:postcode":"28208",
    "sg:province":"NC",
    "sg:tags":[
        "fire",
        "restoration",
        "damage"
    ],
    "wof:name":"Disaster One",
    "wof:placetype":"venue"
},
  "geometry": {"coordinates":[-80.909778,35.238145],"type":"Point"}
}