{
  "type": "Feature",
  "properties": {
    "addr:full":"21420 Townwood Dr Cornelius NC 28031",
    "addr:postcode":"21420;28031",
    "addr:street":"Townwood Dr",
    "iso:country":"US",
    "sg:address":"21420 Townwood Dr",
    "sg:city":"Cornelius",
    "sg:classifiers":[
        {
            "category":"Shopping",
            "type":"Retail Goods"
        }
    ],
    "sg:phone":"+1 704 892 7799",
    "sg:postcode":"28031",
    "sg:province":"NC",
    "sg:tags":[
        "merchandise"
    ],
    "wof:name":"One Stop Car Shop At Lake Norm",
    "wof:placetype":"venue"
},
  "geometry": {"coordinates":[-80.857804,35.477176],"type":"Point"}
}