{
  "type": "Feature",
  "properties": {
    "addr:full":"76 Church St Murphy NC 28904",
    "addr:housenumber":"76",
    "addr:postcode":"28904",
    "addr:street":"Church St",
    "iso:country":"US",
    "sg:address":"76 Church St",
    "sg:city":"Murphy",
    "sg:classifiers":[
        {
            "category":"Home & Garden",
            "subcategory":"Furniture",
            "type":"Retail Goods"
        }
    ],
    "sg:phone":"+1 828 835 8686",
    "sg:postcode":"28904",
    "sg:province":"NC",
    "sg:tags":[
        "bedding"
    ],
    "wof:name":"Direct Mattress Sales",
    "wof:placetype":"venue"
},
  "geometry": {"coordinates":[-83.81841799999999,35.046573],"type":"Point"}
}