{
  "type": "Feature",
  "properties": {
    "iso:country":"US",
    "sg:address":"3919 Chub Lake Rd",
    "sg:city":"Roxboro",
    "sg:classifiers":[
        {
            "category":"Organizations",
            "subcategory":"Religious Organization",
            "type":"Services"
        }
    ],
    "sg:phone":"+1   ",
    "sg:postcode":"27574",
    "sg:province":"NC",
    "sg:website":"www.theresabaptistchurch.org",
    "wof:name":"Theresa Baptist Church",
    "wof:placetype":"venue"
},
  "geometry": {"coordinates":[-78.992901,36.441366],"type":"Point"}
}