{
  "type": "Feature",
  "properties": {
    "iso:country":"US",
    "sg:address":"706 Scotts Store Rd",
    "sg:city":"Mount Olive",
    "sg:classifiers":[
        {
            "category":"Government",
            "subcategory":"Office",
            "type":"Public Place"
        }
    ],
    "sg:phone":"+1 919 658 5790",
    "sg:postcode":"28365",
    "sg:province":"NC",
    "sg:tags":[
        "management"
    ],
    "wof:name":"Crystal Clear Monitoring Svc",
    "wof:placetype":"venue"
},
  "geometry": {"coordinates":[-77.87612,35.113933],"type":"Point"}
}