{
  "type": "Feature",
  "properties": {
    "addr:full":"809 Kavkaz St Raleigh NC 27610",
    "addr:housenumber":"809",
    "addr:postcode":"27610",
    "addr:street":"Kavkaz St",
    "iso:country":"US",
    "sg:address":"809 Kavkaz St",
    "sg:city":"Raleigh",
    "sg:classifiers":[
        {
            "category":"Communications",
            "type":"Services"
        },
        {
            "category":"Shopping",
            "subcategory":"Computers & Home Electronics",
            "type":"Retail Goods"
        }
    ],
    "sg:phone":"+1 646 251 5298",
    "sg:postcode":"27610",
    "sg:province":"NC",
    "sg:tags":[
        "sound",
        "television",
        "system",
        "equipment",
        "radio",
        "store"
    ],
    "wof:name":"Ram Memory",
    "wof:placetype":"venue"
},
  "geometry": {"coordinates":[-78.547539,35.765664],"type":"Point"}
}