{
  "type": "Feature",
  "properties": {
    "iso:country":"US",
    "sg:address":"201 Mill St",
    "sg:city":"Elizabeth City",
    "sg:classifiers":[
        {
            "category":"Building & Trades",
            "subcategory":"Construction",
            "type":"Services"
        }
    ],
    "sg:phone":"+1 252 384 0336",
    "sg:postcode":"27909",
    "sg:province":"NC",
    "sg:tags":[
        "contractor",
        "general"
    ],
    "wof:name":"Metal Building Maintenance",
    "wof:placetype":"venue"
},
  "geometry": {"coordinates":[-76.237771,36.304261],"type":"Point"}
}