{
  "type": "Feature",
  "properties": {
    "iso:country":"US",
    "sg:address":"2714 N Center St",
    "sg:city":"Hickory",
    "sg:classifiers":[
        {
            "category":"Education",
            "subcategory":"Special Training",
            "type":"Public Place"
        }
    ],
    "sg:phone":"+1 828 324 2140",
    "sg:postcode":"28601",
    "sg:province":"NC",
    "sg:tags":[
        "tutoring"
    ],
    "wof:name":"Knowledge Points",
    "wof:placetype":"venue"
},
  "geometry": {"coordinates":[-81.331756,35.767004],"type":"Point"}
}