{
  "type": "Feature",
  "properties": {
    "iso:country":"US",
    "sg:address":"135 Shuffler Rd",
    "sg:city":"Morganton",
    "sg:classifiers":[
        {
            "category":"Social Services",
            "subcategory":"Child Care",
            "type":"Services"
        }
    ],
    "sg:phone":"+1 828 437 5318",
    "sg:postcode":"28655",
    "sg:province":"NC",
    "wof:name":"Wee Wisdom Daycare & Preschool",
    "wof:placetype":"venue"
},
  "geometry": {"coordinates":[-81.715402,35.777047],"type":"Point"}
}