{
  "type": "Feature",
  "properties": {
    "addr:full":"302 Charlotte St Hamlet NC 28345",
    "addr:housenumber":"302",
    "addr:postcode":"28345",
    "addr:street":"Charlotte St",
    "iso:country":"US",
    "sg:address":"302 Charlotte St",
    "sg:city":"Hamlet",
    "sg:classifiers":[
        {
            "category":"Banks & Credit Unions",
            "subcategory":"Bank",
            "type":"Services"
        }
    ],
    "sg:phone":"+1 910 582 1227",
    "sg:postcode":"28345",
    "sg:province":"NC",
    "wof:name":"Hamlet Federal Credit Union",
    "wof:placetype":"venue"
},
  "geometry": {"coordinates":[-79.70006100000001,34.888465],"type":"Point"}
}