{
  "type": "Feature",
  "properties": {
    "addr:full":"901 Ward Blvd Wilson NC 27893",
    "addr:housenumber":"901",
    "addr:postcode":"27893",
    "addr:street":"Ward Blvd",
    "iso:country":"US",
    "sg:address":"901 Ward Blvd",
    "sg:city":"Wilson",
    "sg:classifiers":[
        {
            "category":"Bars & Pubs",
            "type":"Food & Drink"
        }
    ],
    "sg:phone":"+1 252 243 4255",
    "sg:postcode":"27893",
    "sg:province":"NC",
    "sg:tags":[
        "drinking"
    ],
    "wof:name":"Sports Bar",
    "wof:placetype":"venue"
},
  "geometry": {"coordinates":[-77.934004,35.717698],"type":"Point"}
}