{
  "type": "Feature",
  "properties": {
    "addr:full":"478 Richardson Rd Zebulon NC 27597",
    "addr:housenumber":"478",
    "addr:postcode":"27597",
    "addr:street":"Richardson Rd",
    "iso:country":"US",
    "sg:address":"478 Richardson Rd",
    "sg:city":"Zebulon",
    "sg:classifiers":[
        {
            "category":"Organizations",
            "subcategory":"Religious Organization",
            "type":"Services"
        }
    ],
    "sg:phone":"+1 919 269 8933",
    "sg:postcode":"27597",
    "sg:province":"NC",
    "sg:tags":[
        "church"
    ],
    "wof:name":"O'Neal Revival Tabernacle",
    "wof:placetype":"venue"
},
  "geometry": {"coordinates":[-78.279528,35.746226],"type":"Point"}
}