{
  "type": "Feature",
  "properties": {
    "addr:full":"6539 Sugar Hill Rd Marion NC 28752",
    "addr:housenumber":"6539",
    "addr:postcode":"28752",
    "addr:street":"Sugar Hill Rd",
    "iso:country":"US",
    "sg:address":"6539 Sugar Hill Rd",
    "sg:city":"Marion",
    "sg:classifiers":[
        {
            "category":"Professional",
            "subcategory":"Business Services",
            "type":"Services"
        }
    ],
    "sg:phone":"+1   ",
    "sg:postcode":"28752",
    "sg:province":"NC",
    "wof:name":"Steve Lewing Auction Service",
    "wof:placetype":"venue"
},
  "geometry": {"coordinates":[-82.046024,35.609901],"type":"Point"}
}