{
  "type": "Feature",
  "properties": {
    "addr:full":"601 Hibriten Dr SW Lenoir NC 28645",
    "addr:housenumber":"601",
    "addr:postcode":"28645",
    "addr:street":"Hibriten Dr Sw",
    "iso:country":"US",
    "sg:address":"601 Hibriten Dr SW",
    "sg:city":"Lenoir",
    "sg:classifiers":[
        {
            "category":"Manufacturing",
            "subcategory":"Rubber & Plastics",
            "type":"Manufacturing & Wholesale Goods"
        }
    ],
    "sg:phone":"+1 828 754 8441",
    "sg:postcode":"28645",
    "sg:province":"NC",
    "wof:name":"Meridian Automotive Systems",
    "wof:placetype":"venue"
},
  "geometry": {"coordinates":[-81.52552,35.886078],"type":"Point"}
}