{
  "type": "Feature",
  "properties": {
    "addr:full":"5900 Grassy Creek Blvd Winston Salem NC 27105",
    "addr:housenumber":"5900",
    "addr:postcode":"27105",
    "addr:street":"Grassy Creek Blvd",
    "iso:country":"US",
    "sg:address":"5900 Grassy Creek Blvd",
    "sg:city":"Winston Salem",
    "sg:classifiers":[
        {
            "category":"Freight",
            "type":"Transportation"
        }
    ],
    "sg:phone":"+1 336 767 9230",
    "sg:postcode":"27105",
    "sg:province":"NC",
    "sg:tags":[
        "operator",
        "truck",
        "trucking",
        "local",
        "general"
    ],
    "wof:name":"Lentz GATX",
    "wof:placetype":"venue"
},
  "geometry": {"coordinates":[-80.288021,36.178658],"type":"Point"}
}