{
  "type": "Feature",
  "properties": {
    "addr:full":"219 Craven St New Bern NC 28560",
    "addr:housenumber":"219",
    "addr:postcode":"28560",
    "addr:street":"Craven St",
    "iso:country":"US",
    "sg:address":"219 Craven St",
    "sg:city":"New Bern",
    "sg:classifiers":[
        {
            "category":"Shopping",
            "subcategory":"Crafts & Fabrics",
            "type":"Retail Goods"
        }
    ],
    "sg:phone":"+1 252 638 2500",
    "sg:postcode":"28560",
    "sg:province":"NC",
    "sg:tags":[
        "sewing"
    ],
    "wof:name":"Strictly Stitching",
    "wof:placetype":"venue"
},
  "geometry": {"coordinates":[-77.038364,35.106329],"type":"Point"}
}