{
  "type": "Feature",
  "properties": {
    "addr:full":"227 Barrington Pl Winston Salem NC 27104",
    "addr:housenumber":"227",
    "addr:postcode":"27104",
    "addr:street":"Barrington Pl",
    "iso:country":"US",
    "sg:address":"227 Barrington Pl",
    "sg:city":"Winston Salem",
    "sg:classifiers":[
        {
            "category":"Travel",
            "subcategory":"Travel Agent",
            "type":"Entertainment"
        }
    ],
    "sg:phone":"+1 336 765 4010",
    "sg:postcode":"27104",
    "sg:province":"NC",
    "sg:tags":[
        "agency"
    ],
    "wof:name":"Peters Travel Services",
    "wof:placetype":"venue"
},
  "geometry": {"coordinates":[-80.35506599999999,36.077672],"type":"Point"}
}