{
  "type": "Feature",
  "properties": {
    "addr:full":"6408 Honegger Dr Charlotte NC 28211",
    "addr:postcode":"6408;28211",
    "addr:street":"Honegger Dr",
    "iso:country":"US",
    "sg:address":"6408 Honegger Dr",
    "sg:city":"Charlotte",
    "sg:classifiers":[
        {
            "category":"Professional",
            "subcategory":"Employment Agencies",
            "type":"Services"
        }
    ],
    "sg:phone":"+1   ",
    "sg:postcode":"28211",
    "sg:province":"NC",
    "sg:tags":[
        "executive",
        "placement"
    ],
    "wof:name":"Linden Group Inc",
    "wof:placetype":"venue"
},
  "geometry": {"coordinates":[-80.766103,35.163072],"type":"Point"}
}