{
  "type": "Feature",
  "properties": {
    "addr:full":"4822 Albemarle Rd Charlotte NC 28205",
    "addr:housenumber":"4822",
    "addr:postcode":"28205",
    "addr:street":"Albemarle Rd",
    "iso:country":"US",
    "sg:address":"4822 Albemarle Rd",
    "sg:city":"Charlotte",
    "sg:classifiers":[
        {
            "category":"Professional",
            "subcategory":"Business Services",
            "type":"Services"
        },
        {
            "category":"Social Services",
            "type":"Services"
        }
    ],
    "sg:phone":"+1 704 563 9908",
    "sg:postcode":"28205",
    "sg:province":"NC",
    "sg:tags":[
        "arbitration"
    ],
    "wof:name":"Christian Focus Counseling Svc",
    "wof:placetype":"venue"
},
  "geometry": {"coordinates":[-80.76860600000001,35.19885],"type":"Point"}
}