{
  "type": "Feature",
  "properties": {
    "iso:country":"US",
    "sg:address":"6301 Head Rd",
    "sg:city":"Wilmington",
    "sg:classifiers":[
        {
            "category":"Building & Trades",
            "subcategory":"Construction",
            "type":"Services"
        }
    ],
    "sg:phone":"+1 910 791 7953",
    "sg:postcode":"28409",
    "sg:province":"NC",
    "sg:tags":[
        "house"
    ],
    "wof:name":"Walt Lackey Const Co",
    "wof:placetype":"venue"
},
  "geometry": {"coordinates":[-77.845472,34.191614],"type":"Point"}
}