{
  "type": "Feature",
  "properties": {
    "iso:country":"US",
    "sg:address":"1020 Brookstown Ave NW",
    "sg:city":"Winston Salem",
    "sg:classifiers":[
        {
            "category":"Building & Trades",
            "subcategory":"Cleaning & Sanitation",
            "type":"Services"
        },
        {
            "category":"Professional",
            "type":"Services"
        }
    ],
    "sg:phone":"+1 336 724 4708",
    "sg:postcode":"27101",
    "sg:province":"NC",
    "sg:tags":[
        "house",
        "establishment"
    ],
    "wof:name":"Damage' LTD",
    "wof:placetype":"venue"
},
  "geometry": {"coordinates":[-80.25704,36.096828],"type":"Point"}
}