{
  "type": "Feature",
  "properties": {
    "iso:country":"US",
    "sg:address":"516 Mammoth Oaks Dr",
    "sg:city":"Charlotte",
    "sg:classifiers":[
        {
            "category":"Shopping",
            "subcategory":"Jewelry",
            "type":"Retail Goods"
        }
    ],
    "sg:phone":"+1 704 364 9501",
    "sg:postcode":"28270",
    "sg:province":"NC",
    "wof:name":"D P Hurdle Manufactioring Co",
    "wof:placetype":"venue"
},
  "geometry": {"coordinates":[-80.791848,35.154347],"type":"Point"}
}