{
  "type": "Feature",
  "properties": {
    "addr:full":"101 E Main St Forest City NC 28043",
    "addr:housenumber":"101",
    "addr:postcode":"28043",
    "addr:street":"E Main St",
    "iso:country":"US",
    "sg:address":"101 E Main St",
    "sg:city":"Forest City",
    "sg:classifiers":[
        {
            "category":"Shopping",
            "subcategory":"Used Merchandise",
            "type":"Retail Goods"
        }
    ],
    "sg:phone":"+1 828 245 9859",
    "sg:postcode":"28043",
    "sg:province":"NC",
    "sg:tags":[
        "shop",
        "pawnbroker",
        "jewelry",
        "pawn"
    ],
    "wof:name":"Butler's Jewelry & Loan",
    "wof:placetype":"venue"
},
  "geometry": {"coordinates":[-81.864615,35.333676],"type":"Point"}
}