{
  "type": "Feature",
  "properties": {
    "addr:full":"119 Caldis St Whiteville NC 28472",
    "addr:housenumber":"119",
    "addr:postcode":"28472",
    "addr:street":"Caldis St",
    "iso:country":"US",
    "sg:address":"119 Caldis St",
    "sg:city":"Whiteville",
    "sg:classifiers":[
        {
            "category":"Retail",
            "subcategory":"Repair Shop",
            "type":"Services"
        }
    ],
    "sg:phone":"+1 910 642 7376",
    "sg:postcode":"28472",
    "sg:province":"NC",
    "sg:tags":[
        "upholsterer"
    ],
    "wof:name":"Upholstery Shop",
    "wof:placetype":"venue"
},
  "geometry": {"coordinates":[-78.703943,34.319581],"type":"Point"}
}