{
  "type": "Feature",
  "properties": {
    "addr:full":"10920 Tavernay Pkwy Charlotte NC 28262",
    "addr:housenumber":"10920",
    "addr:postcode":"28262",
    "addr:street":"Tavernay Pkwy",
    "iso:country":"US",
    "sg:address":"10920 Tavernay Pkwy",
    "sg:city":"Charlotte",
    "sg:classifiers":[
        {
            "category":"Professional",
            "subcategory":"Business Services",
            "type":"Services"
        }
    ],
    "sg:phone":"+1 704 608 2662",
    "sg:postcode":"28262",
    "sg:province":"NC",
    "wof:name":"PSA LTD",
    "wof:placetype":"venue"
},
  "geometry": {"coordinates":[-80.753787,35.345865],"type":"Point"}
}