{
  "type": "Feature",
  "properties": {
    "addr:full":"13945 Statesville Blvd Cleveland NC 27013",
    "addr:housenumber":"13945",
    "addr:postcode":"27013",
    "addr:street":"Statesville Blvd",
    "iso:country":"US",
    "sg:address":"13945 Statesville Blvd",
    "sg:city":"Cleveland",
    "sg:classifiers":[
        {
            "category":"Home & Garden",
            "subcategory":"Mobile Homes",
            "type":"Retail Goods"
        }
    ],
    "sg:phone":"+1 704 278 9205",
    "sg:postcode":"27013",
    "sg:province":"NC",
    "sg:tags":[
        "operator",
        "site"
    ],
    "wof:name":"Cedar Glen Mobile Home Park",
    "wof:placetype":"venue"
},
  "geometry": {"coordinates":[-80.73530599999999,35.748291],"type":"Point"}
}