{
  "type": "Feature",
  "properties": {
    "addr:full":"801 E Market St Greensboro NC 27401",
    "addr:housenumber":"801",
    "addr:postcode":"27401",
    "addr:street":"E Market St",
    "iso:country":"US",
    "sg:address":"801 E Market St",
    "sg:city":"Greensboro",
    "sg:classifiers":[
        {
            "category":"Banks & Credit Unions",
            "subcategory":"Bank",
            "type":"Services"
        }
    ],
    "sg:phone":"+1 336 273 1845",
    "sg:postcode":"27401",
    "sg:province":"NC",
    "sg:tags":[
        "machine",
        "teller",
        "automated"
    ],
    "wof:name":"Adkins ATM",
    "wof:placetype":"venue"
},
  "geometry": {"coordinates":[-79.783283,36.072033],"type":"Point"}
}