{
  "type": "Feature",
  "properties": {
    "iso:country":"US",
    "sg:address":"5815 Hillsborough St",
    "sg:city":"Raleigh",
    "sg:classifiers":[
        {
            "category":"Manufacturing",
            "subcategory":"Metals",
            "type":"Manufacturing & Wholesale Goods"
        }
    ],
    "sg:phone":"+1 919 851 2590",
    "sg:postcode":"27606",
    "sg:province":"NC",
    "wof:name":"Brass & Copper Polishing Works",
    "wof:placetype":"venue"
},
  "geometry": {"coordinates":[-78.730468,35.78657],"type":"Point"}
}