{
  "type": "Feature",
  "properties": {
    "addr:full":"162 Morningside Dr Asheville NC 28806",
    "addr:housenumber":"162",
    "addr:postcode":"28806",
    "addr:street":"Morningside Dr",
    "iso:country":"US",
    "sg:address":"162 Morningside Dr",
    "sg:city":"Asheville",
    "sg:classifiers":[
        {
            "category":"Restaurant",
            "type":"Food & Drink"
        }
    ],
    "sg:phone":"+1 828 281 3667",
    "sg:postcode":"28806",
    "sg:province":"NC",
    "sg:tags":[
        "drinking",
        "eating"
    ],
    "wof:name":"Westville Pub",
    "wof:placetype":"venue"
},
  "geometry": {"coordinates":[-82.596704,35.566231],"type":"Point"}
}