{
  "type": "Feature",
  "properties": {
    "iso:country":"US",
    "sg:address":"824 N Oakum St",
    "sg:city":"Edenton",
    "sg:classifiers":[
        {
            "category":"Recreation",
            "type":"Entertainment"
        }
    ],
    "sg:phone":"+1 252 482 7082",
    "sg:postcode":"27932",
    "sg:province":"NC",
    "sg:tags":[
        "center"
    ],
    "wof:name":"Boys & Girls Club Of South Va",
    "wof:placetype":"venue"
},
  "geometry": {"coordinates":[-76.601646,36.068796],"type":"Point"}
}