{
  "type": "Feature",
  "properties": {
    "addr:full":"8 S Oak Forest Dr Asheville NC 28803",
    "addr:housenumber":"8",
    "addr:postcode":"28803",
    "addr:street":"S Oak Forest Dr",
    "iso:country":"US",
    "sg:address":"8 S Oak Forest Dr",
    "sg:city":"Asheville",
    "sg:classifiers":[
        {
            "category":"Restaurant",
            "type":"Food & Drink"
        }
    ],
    "sg:phone":"+1 828 654 0852",
    "sg:postcode":"28803",
    "sg:province":"NC",
    "wof:name":"Shang Lin",
    "wof:placetype":"venue"
},
  "geometry": {"coordinates":[-82.524929,35.490293],"type":"Point"}
}