{
  "type": "Feature",
  "properties": {
    "addr:full":"89 Milliken Rd Pittsboro NC 27312",
    "addr:housenumber":"89",
    "addr:postcode":"27312",
    "addr:street":"Milliken Rd",
    "iso:country":"US",
    "sg:address":"89 Milliken Rd",
    "sg:city":"Pittsboro",
    "sg:classifiers":[
        {
            "category":"Organizations",
            "subcategory":"Religious Organization",
            "type":"Services"
        }
    ],
    "sg:phone":"+1 919 542 4279",
    "sg:postcode":"27312",
    "sg:province":"NC",
    "sg:tags":[
        "church"
    ],
    "wof:name":"Pittsboro Church Of God",
    "wof:placetype":"venue"
},
  "geometry": {"coordinates":[-79.201381,35.761059],"type":"Point"}
}