{
  "type": "Feature",
  "properties": {
    "iso:country":"US",
    "sg:address":"6240 Hackberry Creek Trl",
    "sg:city":"Charlotte",
    "sg:classifiers":[
        {
            "category":"Professional",
            "subcategory":"Management & Consulting",
            "type":"Services"
        }
    ],
    "sg:phone":"+1   ",
    "sg:postcode":"28269",
    "sg:province":"NC",
    "sg:tags":[
        "promotion",
        "sales"
    ],
    "wof:name":"Cgs Inc",
    "wof:placetype":"venue"
},
  "geometry": {"coordinates":[-80.806084,35.333125],"type":"Point"}
}