{
  "type": "Feature",
  "properties": {
    "iso:country":"US",
    "sg:address":"44 George White Ln",
    "sg:city":"Newland",
    "sg:classifiers":[
        {
            "category":"Organizations",
            "subcategory":"Religious Organization",
            "type":"Services"
        }
    ],
    "sg:phone":"+1 828 733 4592",
    "sg:postcode":"28657",
    "sg:province":"NC",
    "sg:tags":[
        "church"
    ],
    "wof:name":"Stameytown Baptist Church",
    "wof:placetype":"venue"
},
  "geometry": {"coordinates":[-81.938333,35.983171],"type":"Point"}
}