{
  "type": "Feature",
  "properties": {
    "addr:full":"1576 Staleys Farm Rd Asheboro NC 27205",
    "addr:housenumber":"1576",
    "addr:postcode":"27205",
    "addr:street":"Staleys Farm Rd",
    "iso:country":"US",
    "sg:address":"1576 Staleys Farm Rd",
    "sg:city":"Asheboro",
    "sg:classifiers":[
        {
            "category":"Building & Trades",
            "subcategory":"Construction",
            "type":"Services"
        }
    ],
    "sg:phone":"+1 336 629 9404",
    "sg:postcode":"27205",
    "sg:province":"NC",
    "sg:tags":[
        "general",
        "contractor"
    ],
    "wof:name":"Garner Carpentry",
    "wof:placetype":"venue"
},
  "geometry": {"coordinates":[-79.79612299999999,35.652961],"type":"Point"}
}