{
  "type": "Feature",
  "properties": {
    "iso:country":"US",
    "sg:address":"5170 State Hwy 105",
    "sg:city":"Banner Elk",
    "sg:classifiers":[
        {
            "category":"Health Services",
            "subcategory":"Chiropractor",
            "type":"Services"
        }
    ],
    "sg:phone":"+1   ",
    "sg:postcode":"28604",
    "sg:province":"NC",
    "wof:name":"Northwest Chiro Clnc",
    "wof:placetype":"venue"
},
  "geometry": {"coordinates":[-81.818168,36.132935],"type":"Point"}
}