{
  "type": "Feature",
  "properties": {
    "iso:country":"US",
    "sg:address":"5613 Davis Rd",
    "sg:city":"Walkertown",
    "sg:classifiers":[
        {
            "category":"Building & Trades",
            "subcategory":"Construction",
            "type":"Services"
        }
    ],
    "sg:phone":"+1 336 744 8002",
    "sg:postcode":"27051",
    "sg:province":"NC",
    "sg:tags":[
        "roofing",
        "contractor"
    ],
    "wof:name":"Vortec Exteriors",
    "wof:placetype":"venue"
},
  "geometry": {"coordinates":[-80.199252,36.189402],"type":"Point"}
}