{
  "type": "Feature",
  "properties": {
    "iso:country":"US",
    "sg:address":"709 Greenbriar Dr",
    "sg:city":"Matthews",
    "sg:classifiers":[
        {
            "category":"Manufacturing",
            "subcategory":"Tools & Machinery",
            "type":"Manufacturing & Wholesale Goods"
        }
    ],
    "sg:phone":"+1 704 821 1848",
    "sg:postcode":"28104",
    "sg:province":"NC",
    "sg:tags":[
        "engine",
        "internal",
        "combustion",
        "mfg"
    ],
    "wof:name":"Mikro Systems",
    "wof:placetype":"venue"
},
  "geometry": {"coordinates":[-80.683701,35.094261],"type":"Point"}
}