{
  "type": "Feature",
  "properties": {
    "addr:full":"1087 Leonard Rd Lexington NC 27295",
    "addr:housenumber":"1087",
    "addr:postcode":"27295",
    "addr:street":"Leonard Rd",
    "iso:country":"US",
    "sg:address":"1087 Leonard Rd",
    "sg:city":"Lexington",
    "sg:classifiers":[
        {
            "category":"Organizations",
            "subcategory":"Religious Organization",
            "type":"Services"
        }
    ],
    "sg:phone":"+1 336 249 1410",
    "sg:postcode":"27295",
    "sg:province":"NC",
    "sg:tags":[
        "church"
    ],
    "wof:name":"Ebenezer Methodist Church",
    "wof:placetype":"venue"
},
  "geometry": {"coordinates":[-80.251397,35.868401],"type":"Point"}
}