{
  "type": "Feature",
  "properties": {
    "addr:full":"271 Dawkins St Aberdeen NC 28315",
    "addr:housenumber":"271",
    "addr:postcode":"28315",
    "addr:street":"Dawkins St",
    "iso:country":"US",
    "sg:address":"271 Dawkins St",
    "sg:city":"Aberdeen",
    "sg:classifiers":[
        {
            "category":"Utilities",
            "subcategory":"Refuse",
            "type":"Services"
        }
    ],
    "sg:phone":"+1 910 295 0720",
    "sg:postcode":"28315",
    "sg:province":"NC",
    "sg:tags":[
        "landfill"
    ],
    "wof:name":"S & N Debris Landfill",
    "wof:placetype":"venue"
},
  "geometry": {"coordinates":[-79.477159,35.165084],"type":"Point"}
}