{
  "type": "Feature",
  "properties": {
    "iso:country":"US",
    "sg:address":"5622 W Hanes Mill Rd",
    "sg:city":"Winston Salem",
    "sg:classifiers":[
        {
            "category":"Food & Beverages",
            "subcategory":"Groceries & Convenience Stores",
            "type":"Retail Goods"
        }
    ],
    "sg:phone":"+1 336 000 1111",
    "sg:postcode":"27105",
    "sg:province":"NC",
    "sg:tags":[
        "grocer"
    ],
    "wof:name":"Aldi",
    "wof:placetype":"venue"
},
  "geometry": {"coordinates":[-80.278891,36.175997],"type":"Point"}
}