{
  "type": "Feature",
  "properties": {
    "iso:country":"US",
    "sg:address":"1320 Harvey Point Rd",
    "sg:city":"Hertford",
    "sg:classifiers":[
        {
            "category":"Retail",
            "subcategory":"Auto Repair",
            "type":"Services"
        }
    ],
    "sg:phone":"+1 252 426 7901",
    "sg:postcode":"27944",
    "sg:province":"NC",
    "sg:tags":[
        "repairing",
        "automobile",
        "general"
    ],
    "wof:name":"Overton's Service",
    "wof:placetype":"venue"
},
  "geometry": {"coordinates":[-76.442543,36.16103],"type":"Point"}
}