{
  "type": "Feature",
  "properties": {
    "addr:full":"6136 Carolina Beach Rd Wilmington NC 28412",
    "addr:housenumber":"6136",
    "addr:postcode":"28412",
    "addr:street":"Carolina Beach Rd",
    "iso:country":"US",
    "sg:address":"6136 Carolina Beach Rd",
    "sg:city":"Wilmington",
    "sg:classifiers":[
        {
            "category":"Building & Trades",
            "subcategory":"Landscaping Services",
            "type":"Services"
        }
    ],
    "sg:phone":"+1 910 798 6247",
    "sg:postcode":"28412",
    "sg:province":"NC",
    "sg:tags":[
        "landscape",
        "contractor"
    ],
    "wof:name":"Riptide Landscaping Inc",
    "wof:placetype":"venue"
},
  "geometry": {"coordinates":[-77.90085000000001,34.115709],"type":"Point"}
}