{
  "type": "Feature",
  "properties": {
    "addr:full":"9330 Whispering Wind Dr Charlotte NC 28277",
    "addr:housenumber":"9330",
    "addr:postcode":"28277",
    "addr:street":"Whispering Wind Dr",
    "iso:country":"US",
    "sg:address":"9330 Whispering Wind Dr",
    "sg:city":"Charlotte",
    "sg:classifiers":[
        {
            "category":"Museum",
            "type":"Entertainment"
        }
    ],
    "sg:phone":"+1   ",
    "sg:postcode":"28277",
    "sg:province":"NC",
    "sg:tags":[
        "gallery"
    ],
    "wof:name":"Emerging Art",
    "wof:placetype":"venue"
},
  "geometry": {"coordinates":[-80.83026599999999,35.053382],"type":"Point"}
}