{
  "type": "Feature",
  "properties": {
    "iso:country":"US",
    "sg:address":"280 Huffmantown Rd",
    "sg:city":"Richlands",
    "sg:classifiers":[
        {
            "category":"Retail",
            "subcategory":"Portrait Studio",
            "type":"Services"
        }
    ],
    "sg:phone":"+1 910 324 7427",
    "sg:postcode":"28574",
    "sg:province":"NC",
    "sg:tags":[
        "photographer"
    ],
    "wof:name":"State Of An Art Photorphy",
    "wof:placetype":"venue"
},
  "geometry": {"coordinates":[-77.563385,34.914064],"type":"Point"}
}