{
  "type": "Feature",
  "properties": {
    "iso:country":"US",
    "sg:address":"1843 Manor Mill Rd",
    "sg:city":"Charlotte",
    "sg:classifiers":[
        {
            "category":"Retail",
            "subcategory":"Repair Shop",
            "type":"Services"
        }
    ],
    "sg:phone":"+1   ",
    "sg:postcode":"28226",
    "sg:province":"NC",
    "wof:name":"Coblenz Enterprises Inc",
    "wof:placetype":"venue"
},
  "geometry": {"coordinates":[-80.805493,35.141879],"type":"Point"}
}