{
  "type": "Feature",
  "properties": {
    "addr:full":"3008 Hemby Commons Pkwy Indian Trail NC 28079",
    "addr:housenumber":"3008",
    "addr:postcode":"28079",
    "addr:street":"Hemby Commons Pkwy;Trail",
    "iso:country":"US",
    "sg:address":"3008 Hemby Commons Pkwy",
    "sg:city":"Indian Trail",
    "sg:classifiers":[
        {
            "category":"Shopping",
            "subcategory":"Music",
            "type":"Retail Goods"
        }
    ],
    "sg:phone":"+1 704 451 5304",
    "sg:postcode":"28079",
    "sg:province":"NC",
    "wof:name":"M & K Record Researchers",
    "wof:placetype":"venue"
},
  "geometry": {"coordinates":[-80.622192,35.106832],"type":"Point"}
}