{
  "type": "Feature",
  "properties": {
    "iso:country":"US",
    "sg:address":"13201 Willow Breeze Ln",
    "sg:city":"Huntersville",
    "sg:classifiers":[
        {
            "category":"Real Estate",
            "subcategory":"Real Estate Operator",
            "type":"Services"
        }
    ],
    "sg:phone":"+1 704 896 0643",
    "sg:postcode":"28078",
    "sg:province":"NC",
    "sg:tags":[
        "property",
        "lessor"
    ],
    "wof:name":"Brian Adams",
    "wof:placetype":"venue"
},
  "geometry": {"coordinates":[-80.82015199999999,35.445119],"type":"Point"}
}