{
  "type": "Feature",
  "properties": {
    "iso:country":"US",
    "sg:address":"5214 Aria Ct",
    "sg:city":"Charlotte",
    "sg:phone":"+1 704 536 6674",
    "sg:postcode":"28215",
    "sg:province":"NC",
    "sg:website":"http://www.nbmoving.com",
    "wof:name":"New Beginnings Movin",
    "wof:placetype":"venue"
},
  "geometry": {"coordinates":[-80.656407,35.239152],"type":"Point"}
}