{
  "type": "Feature",
  "properties": {
    "iso:country":"US",
    "sg:address":"4724 Murphy Rd",
    "sg:city":"Franklin",
    "sg:classifiers":[
        {
            "category":"Travel",
            "subcategory":"Campground",
            "type":"Entertainment"
        }
    ],
    "sg:phone":"+1   ",
    "sg:postcode":"28734",
    "sg:province":"NC",
    "sg:tags":[
        "trailer"
    ],
    "wof:name":"Pines Rv Park & Cabins",
    "wof:placetype":"venue"
},
  "geometry": {"coordinates":[-83.45572799999999,35.158219],"type":"Point"}
}