{
  "type": "Feature",
  "properties": {
    "addr:full":"3304 Wrightsville Ave Wilmington NC 28403",
    "addr:housenumber":"3304",
    "addr:postcode":"28403",
    "addr:street":"Wrightsville Ave",
    "iso:country":"US",
    "sg:address":"3304 Wrightsville Ave",
    "sg:city":"Wilmington",
    "sg:classifiers":[
        {
            "category":"Professional",
            "subcategory":"Business Services",
            "type":"Services"
        }
    ],
    "sg:phone":"+1 910 392 1975",
    "sg:postcode":"28403",
    "sg:province":"NC",
    "sg:tags":[
        "interior",
        "consultant",
        "design",
        "decorator"
    ],
    "wof:name":"Melaine Bowe Interiors",
    "wof:placetype":"venue"
},
  "geometry": {"coordinates":[-77.900361,34.221886],"type":"Point"}
}