{
  "type": "Feature",
  "properties": {
    "iso:country":"US",
    "sg:address":"2509 Houston Branch Rd",
    "sg:city":"Charlotte",
    "sg:classifiers":[
        {
            "category":"Professional",
            "subcategory":"Research",
            "type":"Services"
        }
    ],
    "sg:phone":"+1 704 849 2955",
    "sg:postcode":"28270",
    "sg:province":"NC",
    "sg:tags":[
        "development",
        "marketing",
        "product"
    ],
    "wof:name":"Arrk Creative Network",
    "wof:placetype":"venue"
},
  "geometry": {"coordinates":[-80.745772,35.088019],"type":"Point"}
}