{
  "type": "Feature",
  "properties": {
    "addr:full":"420 E Highland Ave Rocky Mount NC 27801",
    "addr:housenumber":"420",
    "addr:postcode":"27801",
    "addr:street":"E Highland Ave",
    "iso:country":"US",
    "sg:address":"420 E Highland Ave",
    "sg:city":"Rocky Mount",
    "sg:classifiers":[
        {
            "category":"Food & Beverages",
            "subcategory":"Groceries & Convenience Stores",
            "type":"Retail Goods"
        }
    ],
    "sg:phone":"+1 252 454 0712",
    "sg:postcode":"27801",
    "sg:province":"NC",
    "wof:name":"Flea Market Vendor",
    "wof:placetype":"venue"
},
  "geometry": {"coordinates":[-77.78853100000001,35.94813],"type":"Point"}
}