{
  "type": "Feature",
  "properties": {
    "addr:full":"3032 N Center St Hickory NC 28601",
    "addr:housenumber":"3032",
    "addr:postcode":"28601",
    "addr:street":"N Center St",
    "iso:country":"US",
    "sg:address":"3032 N Center St",
    "sg:city":"Hickory",
    "sg:classifiers":[
        {
            "category":"Restaurant",
            "type":"Food & Drink"
        }
    ],
    "sg:phone":"+1 828 267 0911",
    "sg:postcode":"28601",
    "sg:province":"NC",
    "wof:name":"Mama Fu's",
    "wof:placetype":"venue"
},
  "geometry": {"coordinates":[-81.32916,35.772997],"type":"Point"}
}