{
  "type": "Feature",
  "properties": {
    "addr:full":"13250 New Light Rd Of Neuse Raleigh NC 27614",
    "addr:housenumber":"13250",
    "addr:postcode":"27614",
    "addr:street":"New Light Rd",
    "iso:country":"US",
    "sg:address":"13250 New Light Rd Of Neuse",
    "sg:city":"Raleigh",
    "sg:classifiers":[
        {
            "category":"Manufacturing",
            "subcategory":"Petroleum Products",
            "type":"Manufacturing & Wholesale Goods"
        },
        {
            "category":"Wholesale",
            "subcategory":"Petroleum",
            "type":"Manufacturing & Wholesale Goods"
        },
        {
            "category":"Utilities",
            "subcategory":"Natural Gas",
            "type":"Services"
        }
    ],
    "sg:phone":"+1 919 554 3165",
    "sg:postcode":"27614",
    "sg:province":"NC",
    "sg:tags":[
        "manufacturer",
        "products-wholesale",
        "oils-petroleum"
    ],
    "wof:name":"Holmes Oil Company",
    "wof:placetype":"venue"
},
  "geometry": {"coordinates":[-78.658682,35.985173],"type":"Point"}
}