{
  "type": "Feature",
  "properties": {
    "addr:full":"92 N Main St Canton NC 28716",
    "addr:housenumber":"92",
    "addr:postcode":"28716",
    "addr:street":"N Main St",
    "iso:country":"US",
    "sg:address":"92 N Main St",
    "sg:city":"Canton",
    "sg:classifiers":[
        {
            "category":"Building & Trades",
            "subcategory":"Plumbing",
            "type":"Services"
        }
    ],
    "sg:phone":"+1 828 648 8400",
    "sg:postcode":"28716",
    "sg:province":"NC",
    "sg:tags":[
        "contractor"
    ],
    "wof:name":"GLC Services",
    "wof:placetype":"venue"
},
  "geometry": {"coordinates":[-82.832053,35.541146],"type":"Point"}
}