{
  "type": "Feature",
  "properties": {
    "iso:country":"US",
    "sg:address":"1120 Fairway Dr",
    "sg:city":"Yadkinville",
    "sg:classifiers":[
        {
            "category":"Building & Trades",
            "subcategory":"Construction",
            "type":"Services"
        }
    ],
    "sg:phone":"+1 336 679 8089",
    "sg:postcode":"27055",
    "sg:province":"NC",
    "sg:tags":[
        "house"
    ],
    "wof:name":"Brendle Construction Inc",
    "wof:placetype":"venue"
},
  "geometry": {"coordinates":[-80.669651,36.173585],"type":"Point"}
}