{
  "type": "Feature",
  "properties": {
    "iso:country":"US",
    "sg:address":"626 Veachs Mill Rd",
    "sg:city":"Warsaw",
    "sg:classifiers":[
        {
            "category":"Farming",
            "subcategory":"Farm",
            "type":"Manufacturing & Wholesale Goods"
        }
    ],
    "sg:phone":"+1 910 293 7865",
    "sg:postcode":"28398",
    "sg:province":"NC",
    "wof:name":"Bowles & Son Farms",
    "wof:placetype":"venue"
},
  "geometry": {"coordinates":[-77.99216800000001,35.054447],"type":"Point"}
}