{
  "type": "Feature",
  "properties": {
    "addr:full":"131 Daniel Boone St Hillsborough NC 27278",
    "addr:housenumber":"131",
    "addr:postcode":"27278",
    "addr:street":"Daniel Boone St",
    "iso:country":"US",
    "sg:address":"131 Daniel Boone St",
    "sg:city":"Hillsborough",
    "sg:classifiers":[
        {
            "category":"Health Services",
            "subcategory":"Optometrist",
            "type":"Services"
        }
    ],
    "sg:phone":"+1 919 732 2020",
    "sg:postcode":"27278",
    "sg:province":"NC",
    "wof:name":"Hillsborough Eye Clinic",
    "wof:placetype":"venue"
},
  "geometry": {"coordinates":[-79.100807,36.057812],"type":"Point"}
}