{
  "type": "Feature",
  "properties": {
    "iso:country":"US",
    "sg:address":"9242 Covey Hollow Ct",
    "sg:city":"Charlotte",
    "sg:classifiers":[
        {
            "category":"Banks & Credit Unions",
            "subcategory":"Bank",
            "type":"Services"
        }
    ],
    "sg:phone":"+1 704 553 7860",
    "sg:postcode":"28210",
    "sg:province":"NC",
    "sg:tags":[
        "federal",
        "agency"
    ],
    "wof:name":"McLauki & Hunter LLC",
    "wof:placetype":"venue"
},
  "geometry": {"coordinates":[-80.848584,35.103246],"type":"Point"}
}