{
  "type": "Feature",
  "properties": {
    "addr:full":"200 Medical Park Dr NE Concord NC 28025",
    "addr:housenumber":"200",
    "addr:postcode":"28025",
    "addr:street":"Medical Park Dr Ne",
    "iso:country":"US",
    "sg:address":"200 Medical Park Dr NE",
    "sg:city":"Concord",
    "sg:classifiers":[
        {
            "category":"Real Estate",
            "subcategory":"Real Estate Agent",
            "type":"Services"
        },
        {
            "category":"Building & Trades",
            "subcategory":"Equipment Rental",
            "type":"Services"
        }
    ],
    "sg:phone":"+1 704 793 1493",
    "sg:postcode":"28025",
    "sg:province":"NC",
    "sg:tags":[
        "medical",
        "management"
    ],
    "wof:name":"Cogdell   Spencer Advisors Inc",
    "wof:placetype":"venue"
},
  "geometry": {"coordinates":[-80.604028,35.438064],"type":"Point"}
}