{
  "type": "Feature",
  "properties": {
    "addr:full":"210 Gwynn St Salisbury NC 28147",
    "addr:housenumber":"210",
    "addr:postcode":"28147",
    "addr:street":"Gwynn St",
    "iso:country":"US",
    "sg:address":"210 Gwynn St",
    "sg:city":"Salisbury",
    "sg:classifiers":[
        {
            "category":"Professional",
            "subcategory":"Management & Consulting",
            "type":"Services"
        }
    ],
    "sg:phone":"+1   ",
    "sg:postcode":"28147",
    "sg:province":"NC",
    "sg:tags":[
        "business"
    ],
    "wof:name":"Dehart Gean Edward",
    "wof:placetype":"venue"
},
  "geometry": {"coordinates":[-80.54231900000001,35.706163],"type":"Point"}
}