{
  "type": "Feature",
  "properties": {
    "iso:country":"US",
    "sg:address":"2444 Mamie May Rd",
    "sg:city":"Franklinville",
    "sg:classifiers":[
        {
            "category":"Retail",
            "subcategory":"Repair Shop",
            "type":"Services"
        },
        {
            "category":"Taxi",
            "type":"Transportation"
        }
    ],
    "sg:phone":"+1 336 495 3354",
    "sg:postcode":"27248",
    "sg:province":"NC",
    "sg:tags":[
        "taxicab"
    ],
    "wof:name":"Jim's Taxidermy & Repair",
    "wof:placetype":"venue"
},
  "geometry": {"coordinates":[-79.74417800000001,35.8381],"type":"Point"}
}