{
  "type": "Feature",
  "properties": {
    "iso:country":"US",
    "sg:address":"207 McBrayer St",
    "sg:city":"Shelby",
    "sg:classifiers":[
        {
            "category":"Taxi",
            "type":"Transportation"
        }
    ],
    "sg:phone":"+1 704 471 0333",
    "sg:postcode":"28150",
    "sg:province":"NC",
    "sg:tags":[
        "taxicab"
    ],
    "wof:name":"A A L & B Taxi Service",
    "wof:placetype":"venue"
},
  "geometry": {"coordinates":[-81.544387,35.290956],"type":"Point"}
}