{
  "type": "Feature",
  "properties": {
    "iso:country":"US",
    "sg:address":"7024 Smith Corners Blvd",
    "sg:city":"Charlotte",
    "sg:classifiers":[
        {
            "category":"Home & Garden",
            "subcategory":"Household Appliances",
            "type":"Retail Goods"
        },
        {
            "category":"Wholesale",
            "subcategory":"Electrical",
            "type":"Manufacturing & Wholesale Goods"
        },
        {
            "category":"Shopping",
            "subcategory":"Computers & Home Electronics",
            "type":"Retail Goods"
        }
    ],
    "sg:phone":"+1 704 599 4196",
    "sg:postcode":"28269",
    "sg:province":"NC",
    "sg:tags":[
        "major",
        "dishwashing",
        "electric",
        "supply",
        "appliances-small",
        "machine",
        "equipment",
        "consumer"
    ],
    "sg:website":"http://www.hhgregg.com",
    "wof:name":"Hhgregg, Inc.",
    "wof:placetype":"venue"
},
  "geometry": {"coordinates":[-80.843506,35.348702],"type":"Point"}
}