{
  "type": "Feature",
  "properties": {
    "iso:country":"US",
    "sg:address":"3614 Green Park Cir",
    "sg:city":"Charlotte",
    "sg:classifiers":[
        {
            "category":"Manufacturing",
            "subcategory":"Food",
            "type":"Manufacturing & Wholesale Goods"
        }
    ],
    "sg:phone":"+1 704 357 1736",
    "sg:postcode":"28217",
    "sg:province":"NC",
    "sg:tags":[
        "product",
        "mfg"
    ],
    "wof:name":"Bellinis LLC",
    "wof:placetype":"venue"
},
  "geometry": {"coordinates":[-80.933207,35.171929],"type":"Point"}
}