{
  "type": "Feature",
  "properties": {
    "addr:full":"517 E 18th St Lumberton NC 28358",
    "addr:housenumber":"517",
    "addr:postcode":"28358",
    "addr:street":"E 18Th St",
    "iso:country":"US",
    "sg:address":"517 E 18th St",
    "sg:city":"Lumberton",
    "sg:classifiers":[
        {
            "category":"Social Services",
            "subcategory":"Child Care",
            "type":"Services"
        }
    ],
    "sg:phone":"+1   ",
    "sg:postcode":"28358",
    "sg:province":"NC",
    "sg:tags":[
        "day"
    ],
    "wof:name":"Michelles Lullaby",
    "wof:placetype":"venue"
},
  "geometry": {"coordinates":[-79.00293000000001,34.62973],"type":"Point"}
}