{
  "type": "Feature",
  "properties": {
    "addr:full":"5520 Yadkin Rd Fayetteville NC 28303",
    "addr:housenumber":"5520",
    "addr:postcode":"28303",
    "addr:street":"Yadkin Rd",
    "iso:country":"US",
    "sg:address":"5520 Yadkin Rd",
    "sg:city":"Fayetteville",
    "sg:classifiers":[
        {
            "category":"Retail",
            "subcategory":"Auto Repair",
            "type":"Services"
        }
    ],
    "sg:phone":"+1 910 826 1005",
    "sg:postcode":"28303",
    "sg:province":"NC",
    "sg:tags":[
        "automotive"
    ],
    "wof:name":"Sanford Quick Lube",
    "wof:placetype":"venue"
},
  "geometry": {"coordinates":[-78.98152399999999,35.088797],"type":"Point"}
}