{
  "type": "Feature",
  "properties": {
    "iso:country":"US",
    "sg:address":"101 Essie Mae Ct",
    "sg:city":"Tabor City",
    "sg:classifiers":[
        {
            "category":"Professional",
            "subcategory":"Management & Consulting",
            "type":"Services"
        }
    ],
    "sg:phone":"+1   ",
    "sg:postcode":"28463",
    "sg:province":"NC",
    "wof:name":"Pendergraph Management",
    "wof:placetype":"venue"
},
  "geometry": {"coordinates":[-78.870121,34.135391],"type":"Point"}
}