{
  "type": "Feature",
  "properties": {
    "iso:country":"US",
    "sg:address":"563 Pleasant Hill Church Rd",
    "sg:city":"Rutherfordton",
    "sg:classifiers":[
        {
            "category":"Organizations",
            "subcategory":"Religious Organization",
            "type":"Services"
        }
    ],
    "sg:phone":"+1 828 286 9218",
    "sg:postcode":"28139",
    "sg:province":"NC",
    "sg:tags":[
        "church"
    ],
    "wof:name":"Pleasant Hill Baptist Church",
    "wof:placetype":"venue"
},
  "geometry": {"coordinates":[-82.023042,35.362035],"type":"Point"}
}