{
  "type": "Feature",
  "properties": {
    "addr:full":"2570 Wilmington Hwy Jacksonville NC 28540",
    "addr:housenumber":"2570",
    "addr:postcode":"28540",
    "addr:street":"Wilmington Hwy",
    "iso:country":"US",
    "sg:address":"2570 Wilmington Hwy",
    "sg:city":"Jacksonville",
    "sg:classifiers":[
        {
            "category":"Building & Trades",
            "subcategory":"Plumbing",
            "type":"Services"
        }
    ],
    "sg:phone":"+1 910 347 6607",
    "sg:postcode":"28540",
    "sg:province":"NC",
    "sg:tags":[
        "plumbing",
        "contractor",
        "retail",
        "supply"
    ],
    "wof:name":"Buceks Plumbing Company",
    "wof:placetype":"venue"
},
  "geometry": {"coordinates":[-77.47974000000001,34.703443],"type":"Point"}
}