{
  "type": "Feature",
  "properties": {
    "addr:full":"4300 Freedom Dr Charlotte NC 28208",
    "addr:housenumber":"4300",
    "addr:postcode":"28208",
    "addr:street":"Freedom Dr",
    "iso:country":"US",
    "sg:address":"4300 Freedom Dr",
    "sg:city":"Charlotte",
    "sg:classifiers":[
        {
            "category":"Social Services",
            "subcategory":"Child Care",
            "type":"Services"
        }
    ],
    "sg:phone":"+1 704 392 8850",
    "sg:postcode":"28208",
    "sg:province":"NC",
    "wof:name":"Kidz Are Fun Child Devmnt Ctr",
    "wof:placetype":"venue"
},
  "geometry": {"coordinates":[-80.908953,35.256471],"type":"Point"}
}