{
  "type": "Feature",
  "properties": {
    "iso:country":"US",
    "sg:address":"3006 Crosby Ct",
    "sg:city":"Summerfield",
    "sg:classifiers":[
        {
            "category":"Manufacturing",
            "subcategory":"Printing",
            "type":"Manufacturing & Wholesale Goods"
        }
    ],
    "sg:phone":"+1 336 644 7544",
    "sg:postcode":"27358",
    "sg:province":"NC",
    "sg:tags":[
        "multimedia"
    ],
    "wof:name":"Deja View Media Inc",
    "wof:placetype":"venue"
},
  "geometry": {"coordinates":[-79.853064,36.192155],"type":"Point"}
}