{
  "type": "Feature",
  "properties": {
    "iso:country":"US",
    "sg:address":"2434 Woodfield Ct",
    "sg:city":"Sophia",
    "sg:classifiers":[
        {
            "category":"Retail",
            "subcategory":"Repair Shop",
            "type":"Services"
        }
    ],
    "sg:phone":"+1   ",
    "sg:postcode":"27350",
    "sg:province":"NC",
    "wof:name":"Full Throttle Motor Sports",
    "wof:placetype":"venue"
},
  "geometry": {"coordinates":[-79.873699,35.771588],"type":"Point"}
}