{
  "type": "Feature",
  "properties": {
    "addr:full":"701 S Main St Robersonville NC 27871",
    "addr:housenumber":"701",
    "addr:postcode":"27871",
    "addr:street":"S Main St",
    "iso:country":"US",
    "sg:address":"701 S Main St",
    "sg:city":"Robersonville",
    "sg:classifiers":[
        {
            "category":"Retail",
            "subcategory":"Funeral Services",
            "type":"Services"
        }
    ],
    "sg:phone":"+1 252 795 4301",
    "sg:postcode":"27871",
    "sg:province":"NC",
    "sg:tags":[
        "director"
    ],
    "wof:name":"Biggs Funeral Home",
    "wof:placetype":"venue"
},
  "geometry": {"coordinates":[-77.25099,35.814578],"type":"Point"}
}