{
  "type": "Feature",
  "properties": {
    "addr:full":"1003 Carmel Dr Gastonia NC 28056",
    "addr:housenumber":"1003",
    "addr:postcode":"28056",
    "addr:street":"Carmel Dr",
    "iso:country":"US",
    "sg:address":"1003 Carmel Dr",
    "sg:city":"Gastonia",
    "sg:classifiers":[
        {
            "category":"Professional",
            "subcategory":"Computer Services",
            "type":"Services"
        }
    ],
    "sg:phone":"+1   ",
    "sg:postcode":"28056",
    "sg:province":"NC",
    "wof:name":"Tbc Computers",
    "wof:placetype":"venue"
},
  "geometry": {"coordinates":[-81.146258,35.188033],"type":"Point"}
}