{
  "type": "Feature",
  "properties": {
    "addr:full":"3637 Fairview Rd Andrews NC 28901",
    "addr:housenumber":"3637",
    "addr:postcode":"28901",
    "addr:street":"Fairview Rd",
    "iso:country":"US",
    "sg:address":"3637 Fairview Rd",
    "sg:city":"Andrews",
    "sg:classifiers":[
        {
            "category":"Retail",
            "subcategory":"Auto Repair",
            "type":"Services"
        }
    ],
    "sg:phone":"+1   ",
    "sg:postcode":"28901",
    "sg:province":"NC",
    "sg:tags":[
        "automotive"
    ],
    "wof:name":"Luther Auto Electric",
    "wof:placetype":"venue"
},
  "geometry": {"coordinates":[-83.88262899999999,35.180153],"type":"Point"}
}