{
  "type": "Feature",
  "properties": {
    "iso:country":"US",
    "sg:address":"2908 Oak Ridge Rd",
    "sg:city":"Oak Ridge",
    "sg:classifiers":[
        {
            "category":"Organizations",
            "subcategory":"Membership Organization",
            "type":"Services"
        }
    ],
    "sg:phone":"+1 336 643 0233",
    "sg:postcode":"27310",
    "sg:province":"NC",
    "sg:tags":[
        "society",
        "humane"
    ],
    "sg:website":"www.greyhoundfriends.com",
    "wof:name":"Greyhound Friends Of Nc",
    "wof:placetype":"venue"
},
  "geometry": {"coordinates":[-79.958332,36.195776],"type":"Point"}
}