{
  "type": "Feature",
  "properties": {
    "addr:full":"876 Faison Hwy Clinton NC 28328",
    "addr:housenumber":"876",
    "addr:postcode":"28328",
    "addr:street":"Faison Hwy",
    "iso:country":"US",
    "sg:address":"876 Faison Hwy",
    "sg:city":"Clinton",
    "sg:classifiers":[
        {
            "category":"Home & Garden",
            "subcategory":"Carpets & Floor Coverings",
            "type":"Retail Goods"
        }
    ],
    "sg:phone":"+1 910 596 4440",
    "sg:postcode":"28328",
    "sg:province":"NC",
    "sg:tags":[
        "dealer",
        "rug"
    ],
    "wof:name":"Edwards Carpet Sales",
    "wof:placetype":"venue"
},
  "geometry": {"coordinates":[-78.29723199999999,35.011063],"type":"Point"}
}