{
  "type": "Feature",
  "properties": {
    "addr:full":"402 Gower Cir Knightdale NC 27545",
    "addr:housenumber":"402",
    "addr:postcode":"27545",
    "addr:street":"Gower Cir",
    "iso:country":"US",
    "sg:address":"402 Gower Cir",
    "sg:city":"Knightdale",
    "sg:classifiers":[
        {
            "category":"Building & Trades",
            "subcategory":"Construction",
            "type":"Services"
        }
    ],
    "sg:phone":"+1 919 266 9169",
    "sg:postcode":"27545",
    "sg:province":"NC",
    "sg:tags":[
        "house"
    ],
    "wof:name":"Jerri Builders Inc",
    "wof:placetype":"venue"
},
  "geometry": {"coordinates":[-78.509607,35.773439],"type":"Point"}
}