{
  "type": "Feature",
  "properties": {
    "addr:full":"435 Cathay Rd Wilmington NC 28412",
    "addr:housenumber":"435",
    "addr:postcode":"28412",
    "addr:street":"Cathay Rd",
    "iso:country":"US",
    "sg:address":"435 Cathay Rd",
    "sg:city":"Wilmington",
    "sg:classifiers":[
        {
            "category":"Shopping",
            "subcategory":"Crafts & Fabrics",
            "type":"Retail Goods"
        }
    ],
    "sg:phone":"+1 910 392 0516",
    "sg:postcode":"28412",
    "sg:province":"NC",
    "sg:tags":[
        "art"
    ],
    "wof:name":"Creative Craftsman",
    "wof:placetype":"venue"
},
  "geometry": {"coordinates":[-77.91300200000001,34.109699],"type":"Point"}
}