{
  "type": "Feature",
  "properties": {
    "addr:full":"3120 Zebulon Rd Rocky Mount NC 27804",
    "addr:housenumber":"3120",
    "addr:postcode":"27804",
    "addr:street":"Zebulon Rd",
    "iso:country":"US",
    "sg:address":"3120 Zebulon Rd",
    "sg:city":"Rocky Mount",
    "sg:classifiers":[
        {
            "category":"Social Services",
            "type":"Services"
        }
    ],
    "sg:phone":"+1 252 446 4730",
    "sg:postcode":"27804",
    "sg:province":"NC",
    "sg:tags":[
        "organization",
        "welfare"
    ],
    "wof:name":"Friends Helping Friends Family",
    "wof:placetype":"venue"
},
  "geometry": {"coordinates":[-77.83902500000001,35.965927],"type":"Point"}
}