{
  "type": "Feature",
  "properties": {
    "iso:country":"US",
    "sg:address":"309 E State Hwy 24",
    "sg:city":"Roseboro",
    "sg:classifiers":[
        {
            "category":"Personal",
            "subcategory":"Beauty Salon",
            "type":"Services"
        }
    ],
    "sg:phone":"+1 910 525 3312",
    "sg:postcode":"28382",
    "sg:province":"NC",
    "sg:tags":[
        "manicuring"
    ],
    "wof:name":"Perfect Nails",
    "wof:placetype":"venue"
},
  "geometry": {"coordinates":[-78.508872,34.955831],"type":"Point"}
}