{
  "type": "Feature",
  "properties": {
    "addr:full":"5 Elmore St Asheville NC 28804",
    "addr:housenumber":"5",
    "addr:postcode":"28804",
    "addr:street":"Elmore St",
    "iso:country":"US",
    "sg:address":"5 Elmore St",
    "sg:city":"Asheville",
    "sg:classifiers":[
        {
            "category":"Building & Trades",
            "subcategory":"Construction",
            "type":"Services"
        }
    ],
    "sg:phone":"+1 828 236 1241",
    "sg:postcode":"28804",
    "sg:province":"NC",
    "sg:tags":[
        "house"
    ],
    "wof:name":"Garden Construction Inc",
    "wof:placetype":"venue"
},
  "geometry": {"coordinates":[-82.561753,35.617759],"type":"Point"}
}