{
  "type": "Feature",
  "properties": {
    "addr:full":"3819 Ellenwood Pl Charlotte NC 28217",
    "addr:housenumber":"3819",
    "addr:postcode":"28217",
    "addr:street":"Ellenwood Pl",
    "iso:country":"US",
    "sg:address":"3819 Ellenwood Pl",
    "sg:city":"Charlotte",
    "sg:classifiers":[
        {
            "category":"Professional",
            "subcategory":"Business Services",
            "type":"Services"
        }
    ],
    "sg:phone":"+1   ",
    "sg:postcode":"28217",
    "sg:province":"NC",
    "wof:name":"Moffetts Bailbonding",
    "wof:placetype":"venue"
},
  "geometry": {"coordinates":[-80.878491,35.190924],"type":"Point"}
}