{
  "type": "Feature",
  "properties": {
    "iso:country":"US",
    "sg:address":"100 Capitola Dr",
    "sg:city":"Durham",
    "sg:classifiers":[
        {
            "category":"Professional",
            "type":"Services"
        }
    ],
    "sg:phone":"+1 919 544 3717",
    "sg:postcode":"27713",
    "sg:province":"NC",
    "wof:name":"Nickel Producers Envmtl Res",
    "wof:placetype":"venue"
},
  "geometry": {"coordinates":[-78.89128599999999,35.889011],"type":"Point"}
}