{
  "type": "Feature",
  "properties": {
    "iso:country":"US",
    "sg:address":"370 Taylor Town Rd",
    "sg:city":"Faison",
    "sg:classifiers":[
        {
            "category":"Freight",
            "type":"Transportation"
        }
    ],
    "sg:phone":"+1 910 293 4650",
    "sg:postcode":"28341",
    "sg:province":"NC",
    "sg:tags":[
        "operator",
        "local",
        "trucking"
    ],
    "wof:name":"Joe Taylor Trucking",
    "wof:placetype":"venue"
},
  "geometry": {"coordinates":[-78.07717100000001,35.076246],"type":"Point"}
}