{
  "type": "Feature",
  "properties": {
    "addr:full":"4480 Richlands Hwy Jacksonville NC 28540",
    "addr:postcode":"4480;28540",
    "addr:street":"Richlands Hwy",
    "iso:country":"US",
    "sg:address":"4480 Richlands Hwy",
    "sg:city":"Jacksonville",
    "sg:classifiers":[
        {
            "category":"Organizations",
            "subcategory":"Religious Organization",
            "type":"Services"
        }
    ],
    "sg:phone":"+1 910 324 3574",
    "sg:postcode":"28540",
    "sg:province":"NC",
    "sg:tags":[
        "church"
    ],
    "wof:name":"Faith Tab In Denom Ch Inc",
    "wof:placetype":"venue"
},
  "geometry": {"coordinates":[-77.501115,34.795994],"type":"Point"}
}