{
  "type": "Feature",
  "properties": {
    "iso:country":"US",
    "sg:address":"7826 Caswell Rd",
    "sg:city":"Stanley",
    "sg:classifiers":[
        {
            "category":"Building & Trades",
            "subcategory":"Construction",
            "type":"Services"
        }
    ],
    "sg:phone":"+1 704 827 3793",
    "sg:postcode":"28164",
    "sg:province":"NC",
    "sg:tags":[
        "excavation",
        "contractor"
    ],
    "wof:name":"CJ Mayer Construction Co",
    "wof:placetype":"venue"
},
  "geometry": {"coordinates":[-80.96911299999999,35.42698],"type":"Point"}
}