{
  "type": "Feature",
  "properties": {
    "iso:country":"US",
    "sg:address":"1815 Main St",
    "sg:city":"Charlotte",
    "sg:classifiers":[
        {
            "category":"Personal",
            "subcategory":"Barber",
            "type":"Services"
        }
    ],
    "sg:phone":"+1   ",
    "sg:postcode":"28204",
    "sg:province":"NC",
    "sg:tags":[
        "shop"
    ],
    "wof:name":"Big Johns",
    "wof:placetype":"venue"
},
  "geometry": {"coordinates":[-80.830489,35.20748],"type":"Point"}
}