{
  "type": "Feature",
  "properties": {
    "addr:full":"231 Englewood Dr Wilmington NC 28409",
    "addr:housenumber":"231",
    "addr:postcode":"28409",
    "addr:street":"Englewood Dr",
    "iso:country":"US",
    "sg:address":"231 Englewood Dr",
    "sg:city":"Wilmington",
    "sg:classifiers":[
        {
            "category":"Organizations",
            "subcategory":"Religious Organization",
            "type":"Services"
        }
    ],
    "sg:phone":"+1 910 799 6645",
    "sg:postcode":"28409",
    "sg:province":"NC",
    "sg:tags":[
        "church"
    ],
    "wof:name":"Wilmington Korean Presbyterian",
    "wof:placetype":"venue"
},
  "geometry": {"coordinates":[-77.860608,34.20807],"type":"Point"}
}