{
  "type": "Feature",
  "properties": {
    "iso:country":"US",
    "sg:address":"1145 Wade Smith Rd",
    "sg:city":"Garland",
    "sg:classifiers":[
        {
            "category":"Manufacturing",
            "subcategory":"Lumber",
            "type":"Manufacturing & Wholesale Goods"
        }
    ],
    "sg:phone":"+1 910 588 4174",
    "sg:postcode":"28441",
    "sg:province":"NC",
    "sg:tags":[
        "logging",
        "contractor"
    ],
    "wof:name":"Smith Logging Co",
    "wof:placetype":"venue"
},
  "geometry": {"coordinates":[-78.461853,34.720825],"type":"Point"}
}