{
  "type": "Feature",
  "properties": {
    "iso:country":"US",
    "sg:address":"3610 Barnett Rd",
    "sg:city":"Mebane",
    "sg:classifiers":[
        {
            "category":"Professional",
            "type":"Services"
        }
    ],
    "sg:phone":"+1 336 578 0117",
    "sg:postcode":"27302",
    "sg:province":"NC",
    "wof:name":"Dewey Rainey",
    "wof:placetype":"venue"
},
  "geometry": {"coordinates":[-79.294864,36.173967],"type":"Point"}
}