{
  "type": "Feature",
  "properties": {
    "addr:full":"1055 Jabara Ave Goldsboro NC 27534",
    "addr:housenumber":"1055",
    "addr:postcode":"27534",
    "addr:street":"Jabara Ave",
    "iso:country":"US",
    "sg:address":"1055 Jabara Ave",
    "sg:city":"Goldsboro",
    "sg:classifiers":[
        {
            "category":"Health Services",
            "subcategory":"Doctor",
            "type":"Services"
        }
    ],
    "sg:phone":"+1   ",
    "sg:postcode":"27534",
    "sg:province":"NC",
    "wof:name":"Sjafb 4th Medical Dntl Surgeon",
    "wof:placetype":"venue"
},
  "geometry": {"coordinates":[-77.96210000000001,35.360748],"type":"Point"}
}