{
  "type": "Feature",
  "properties": {
    "addr:full":"602 S 5th St Wilmington NC 28401",
    "addr:housenumber":"602",
    "addr:postcode":"28401",
    "addr:street":"S 5Th St",
    "iso:country":"US",
    "sg:address":"602 S 5th St",
    "sg:city":"Wilmington",
    "sg:classifiers":[
        {
            "category":"Organizations",
            "subcategory":"Non-profit Organization",
            "type":"Services"
        }
    ],
    "sg:phone":"+1 910 762 4255",
    "sg:postcode":"28401",
    "sg:province":"NC",
    "sg:tags":[
        "human"
    ],
    "wof:name":"Southeastern Alliance-Change",
    "wof:placetype":"venue"
},
  "geometry": {"coordinates":[-77.942477,34.227474],"type":"Point"}
}