{
  "type": "Feature",
  "properties": {
    "iso:country":"US",
    "sg:address":"237 Washington St",
    "sg:city":"Williamston",
    "sg:classifiers":[
        {
            "category":"Personal",
            "subcategory":"Beauty Salon",
            "type":"Services"
        }
    ],
    "sg:phone":"+1 252 792 1388",
    "sg:postcode":"27892",
    "sg:province":"NC",
    "sg:tags":[
        "shop"
    ],
    "wof:name":"All American Beauty Shoppe",
    "wof:placetype":"venue"
},
  "geometry": {"coordinates":[-77.056095,35.851277],"type":"Point"}
}