{
  "type": "Feature",
  "properties": {
    "addr:full":"1020 W Hudson Blvd Gastonia NC 28052",
    "addr:housenumber":"1020",
    "addr:postcode":"28052",
    "addr:street":"W Hudson Blvd",
    "iso:country":"US",
    "sg:address":"1020 W Hudson Blvd",
    "sg:city":"Gastonia",
    "sg:classifiers":[
        {
            "category":"Restaurant",
            "type":"Food & Drink"
        }
    ],
    "sg:menulink":"http://www.allmenus.com/nc/gastonia/137305-subway/menu/",
    "sg:phone":"+1 704 853 2626",
    "sg:postcode":"28052",
    "sg:province":"NC",
    "sg:tags":[
        "american",
        "sandwich"
    ],
    "wof:name":"Subway",
    "wof:placetype":"venue"
},
  "geometry": {"coordinates":[-81.204114,35.235076],"type":"Point"}
}