{
  "type": "Feature",
  "properties": {
    "iso:country":"US",
    "sg:address":"342 Causeway Dr",
    "sg:city":"Wrightsville Beach",
    "sg:classifiers":[
        {
            "category":"Personal",
            "subcategory":"Beauty Salon",
            "type":"Services"
        }
    ],
    "sg:phone":"+1   ",
    "sg:postcode":"28480",
    "sg:province":"NC",
    "sg:tags":[
        "shop"
    ],
    "wof:name":"Miracles Hair Salon",
    "wof:placetype":"venue"
},
  "geometry": {"coordinates":[-77.80223599999999,34.211762],"type":"Point"}
}