{
  "type": "Feature",
  "properties": {
    "iso:country":"US",
    "sg:address":"3948 Browning Pl",
    "sg:city":"Raleigh",
    "sg:classifiers":[
        {
            "category":"Organizations",
            "subcategory":"Professional Association",
            "type":"Services"
        }
    ],
    "sg:phone":"+1 919 781 4335",
    "sg:postcode":"27609",
    "sg:province":"NC",
    "wof:name":"Alpha Association Management",
    "wof:placetype":"venue"
},
  "geometry": {"coordinates":[-78.63087299999999,35.831229],"type":"Point"}
}