{
  "type": "Feature",
  "properties": {
    "addr:full":"254 Dodson Rd Elkin NC 28621",
    "addr:housenumber":"254",
    "addr:postcode":"28621",
    "addr:street":"Dodson Rd",
    "iso:country":"US",
    "sg:address":"254 Dodson Rd",
    "sg:city":"Elkin",
    "sg:classifiers":[
        {
            "category":"Organizations",
            "subcategory":"Religious Organization",
            "type":"Services"
        }
    ],
    "sg:phone":"+1   ",
    "sg:postcode":"28621",
    "sg:province":"NC",
    "wof:name":"Zephyr Baptist Church",
    "wof:placetype":"venue"
},
  "geometry": {"coordinates":[-80.784009,36.319614],"type":"Point"}
}