{
  "type": "Feature",
  "properties": {
    "iso:country":"US",
    "sg:address":"288 Howell Mill Rd",
    "sg:city":"Waynesville",
    "sg:classifiers":[
        {
            "category":"Manufacturing",
            "subcategory":"Rubber & Plastics",
            "type":"Manufacturing & Wholesale Goods"
        }
    ],
    "sg:phone":"+1 828 452 4774",
    "sg:postcode":"28786",
    "sg:province":"NC",
    "sg:website":"www.aptechnologies.com",
    "wof:name":"Associated Packaging Tchnlgs",
    "wof:placetype":"venue"
},
  "geometry": {"coordinates":[-82.983812,35.50384],"type":"Point"}
}