{
  "type": "Feature",
  "properties": {
    "addr:full":"600 Rawls Dr Raleigh NC 27610",
    "addr:housenumber":"600",
    "addr:postcode":"27610",
    "addr:street":"Rawls Dr",
    "iso:country":"US",
    "sg:address":"600 Rawls Dr",
    "sg:city":"Raleigh",
    "sg:classifiers":[
        {
            "category":"Shopping",
            "subcategory":"Clothing, Apparel, & Fashions",
            "type":"Retail Goods"
        }
    ],
    "sg:phone":"+1 919 231 7609",
    "sg:postcode":"27610",
    "sg:province":"NC",
    "wof:name":"Shav S Wigs",
    "wof:placetype":"venue"
},
  "geometry": {"coordinates":[-78.587261,35.774642],"type":"Point"}
}