{
  "type": "Feature",
  "properties": {
    "addr:full":"1129 Big Island Rd Rutherfordton NC 28139",
    "addr:housenumber":"1129",
    "addr:postcode":"28139",
    "addr:street":"Big Island Rd",
    "iso:country":"US",
    "sg:address":"1129 Big Island Rd",
    "sg:city":"Rutherfordton",
    "sg:classifiers":[
        {
            "category":"Retail",
            "subcategory":"Auto Repair",
            "type":"Services"
        }
    ],
    "sg:phone":"+1   ",
    "sg:postcode":"28139",
    "sg:province":"NC",
    "sg:tags":[
        "automotive"
    ],
    "wof:name":"Shiloh Motors",
    "wof:placetype":"venue"
},
  "geometry": {"coordinates":[-81.932283,35.272803],"type":"Point"}
}