{
  "type": "Feature",
  "properties": {
    "addr:full":"1818 Martin Luther King, Jr. Blvd Suite 137 Chapel Hill NC 27514",
    "addr:housenumber":"1818",
    "addr:postcode":"27514",
    "addr:street":"Martin Luther King Jr. Blvd Suite 137",
    "iso:country":"US",
    "sg:address":"1818 Martin Luther King, Jr. Blvd Suite 137",
    "sg:city":"Chapel Hill",
    "sg:classifiers":[
        {
            "category":"Social Services",
            "subcategory":"Retirement Home",
            "type":"Services"
        }
    ],
    "sg:phone":"+1 919 357 1440",
    "sg:postcode":"27514",
    "sg:province":"NC",
    "sg:website":"www.alwaysbestcare.com",
    "wof:name":"Always Best Care Senior Services",
    "wof:placetype":"venue"
},
  "geometry": {"coordinates":[-79.058561,35.967986],"type":"Point"}
}