{
  "type": "Feature",
  "properties": {
    "iso:country":"US",
    "sg:address":"6202 Tri-Port Ct",
    "sg:city":"Greensboro",
    "sg:classifiers":[
        {
            "category":"Freight",
            "type":"Transportation"
        }
    ],
    "sg:phone":"+1 336 854 4339",
    "sg:postcode":"27409",
    "sg:province":"NC",
    "sg:tags":[
        "domestic",
        "courier",
        "sea",
        "air"
    ],
    "wof:name":"Custom Global Logistics",
    "wof:placetype":"venue"
},
  "geometry": {"coordinates":[-79.910053,36.074137],"type":"Point"}
}