{
  "type": "Feature",
  "properties": {
    "iso:country":"US",
    "sg:address":"18 Causeway Dr",
    "sg:city":"Ocean Isle Beach",
    "sg:classifiers":[
        {
            "category":"Professional",
            "type":"Services"
        }
    ],
    "sg:phone":"+1 910 579 7227",
    "sg:postcode":"28469",
    "sg:province":"NC",
    "sg:tags":[
        "establishment"
    ],
    "wof:name":"Dunes B4",
    "wof:placetype":"venue"
},
  "geometry": {"coordinates":[-78.437631,33.890315],"type":"Point"}
}