{
  "type": "Feature",
  "properties": {
    "addr:full":"537 W Old Glencoe Rd Burlington NC 27217",
    "addr:housenumber":"537",
    "addr:postcode":"27217",
    "addr:street":"W Old Glencoe Rd",
    "iso:country":"US",
    "sg:address":"537 W Old Glencoe Rd",
    "sg:city":"Burlington",
    "sg:phone":"+1 336 226 5655",
    "sg:postcode":"27217",
    "sg:province":"NC",
    "sg:tags":[
        "farm",
        "soybean",
        "tobacco"
    ],
    "wof:name":"Mike Davis",
    "wof:placetype":"venue"
},
  "geometry": {"coordinates":[-79.437952,36.131081],"type":"Point"}
}