{
  "type": "Feature",
  "properties": {
    "iso:country":"US",
    "sg:address":"3880 Cherry Grove Dr",
    "sg:city":"Hickory",
    "sg:classifiers":[
        {
            "category":"Building & Trades",
            "subcategory":"Construction",
            "type":"Services"
        }
    ],
    "sg:phone":"+1 828 294 0023",
    "sg:postcode":"28602",
    "sg:province":"NC",
    "sg:tags":[
        "resurfacing",
        "laying",
        "refinishing",
        "floor"
    ],
    "wof:name":"Atlas Hardwood Flooring Svc",
    "wof:placetype":"venue"
},
  "geometry": {"coordinates":[-81.31864400000001,35.643934],"type":"Point"}
}