{
  "type": "Feature",
  "properties": {
    "iso:country":"US",
    "sg:address":"5342 Prosperity Church Rd",
    "sg:city":"Charlotte",
    "sg:classifiers":[
        {
            "category":"Personal",
            "subcategory":"Shoe Repair & Shine",
            "type":"Services"
        }
    ],
    "sg:phone":"+1   ",
    "sg:postcode":"28269",
    "sg:province":"NC",
    "sg:tags":[
        "parlor"
    ],
    "wof:name":"Sung Tae & Son Shoe Repair",
    "wof:placetype":"venue"
},
  "geometry": {"coordinates":[-80.78604900000001,35.368947],"type":"Point"}
}