{
  "type": "Feature",
  "properties": {
    "addr:full":"18637 Northline Dr Cornelius NC 28031",
    "addr:housenumber":"18637",
    "addr:postcode":"28031",
    "addr:street":"Northline Dr",
    "iso:country":"US",
    "sg:address":"18637 Northline Dr",
    "sg:city":"Cornelius",
    "sg:classifiers":[
        {
            "category":"Home & Garden",
            "subcategory":"Home Furnishings",
            "type":"Retail Goods"
        }
    ],
    "sg:phone":"+1 704 987 8157",
    "sg:postcode":"28031",
    "sg:province":"NC",
    "sg:tags":[
        "window",
        "covering"
    ],
    "wof:name":"Window Fashion Direct",
    "wof:placetype":"venue"
},
  "geometry": {"coordinates":[-80.854327,35.459283],"type":"Point"}
}