{
  "type": "Feature",
  "properties": {
    "iso:country":"US",
    "sg:address":"138 Bridle Trl",
    "sg:city":"Youngsville",
    "sg:classifiers":[
        {
            "category":"Shopping",
            "subcategory":"Hobbies, Toys, & Games",
            "type":"Retail Goods"
        }
    ],
    "sg:phone":"+1 919 562 0509",
    "sg:postcode":"27596",
    "sg:province":"NC",
    "sg:tags":[
        "wholesale"
    ],
    "wof:name":"Phatboy Video",
    "wof:placetype":"venue"
},
  "geometry": {"coordinates":[-78.394943,35.95485],"type":"Point"}
}