{
  "type": "Feature",
  "properties": {
    "addr:full":"3634 Litchfield Rd Charlotte NC 28211",
    "addr:housenumber":"3634",
    "addr:postcode":"28211",
    "addr:street":"Litchfield Rd",
    "iso:country":"US",
    "sg:address":"3634 Litchfield Rd",
    "sg:city":"Charlotte",
    "sg:classifiers":[
        {
            "category":"Restaurant",
            "type":"Food & Drink"
        }
    ],
    "sg:phone":"+1 704 533 2343",
    "sg:postcode":"28211",
    "sg:province":"NC",
    "sg:tags":[
        "caterer"
    ],
    "wof:name":"Gardners Eden",
    "wof:placetype":"venue"
},
  "geometry": {"coordinates":[-80.78911600000001,35.187855],"type":"Point"}
}