{
  "type": "Feature",
  "properties": {
    "addr:full":"200 Temple Gate Dr Cary NC 27518",
    "addr:housenumber":"200",
    "addr:postcode":"27518",
    "addr:street":"Temple Gate Dr",
    "iso:country":"US",
    "sg:address":"200 Temple Gate Dr",
    "sg:city":"Cary",
    "sg:classifiers":[
        {
            "category":"Building & Trades",
            "subcategory":"Construction",
            "type":"Services"
        }
    ],
    "sg:phone":"+1 919 362 4534",
    "sg:postcode":"27518",
    "sg:province":"NC",
    "sg:tags":[
        "hanging",
        "contractor"
    ],
    "wof:name":"An Inside Job",
    "wof:placetype":"venue"
},
  "geometry": {"coordinates":[-78.803144,35.708068],"type":"Point"}
}