{
  "type": "Feature",
  "properties": {
    "addr:full":"1141 Broad Creek Rd New Bern NC 28560",
    "addr:housenumber":"1141",
    "addr:postcode":"28560",
    "addr:street":"Broad Creek Rd",
    "iso:country":"US",
    "sg:address":"1141 Broad Creek Rd",
    "sg:city":"New Bern",
    "sg:classifiers":[
        {
            "category":"Real Estate",
            "subcategory":"Real Estate Agent",
            "type":"Services"
        },
        {
            "category":"Travel",
            "subcategory":"Hotels & Motels",
            "type":"Entertainment"
        }
    ],
    "sg:phone":"+1 252 633 1151",
    "sg:postcode":"28560",
    "sg:province":"NC",
    "sg:tags":[
        "resort"
    ],
    "wof:name":"Vacation Resorts International",
    "wof:placetype":"venue"
},
  "geometry": {"coordinates":[-76.967753,35.115567],"type":"Point"}
}