{
  "type": "Feature",
  "properties": {
    "iso:country":"US",
    "sg:address":"105 S Buffalo St",
    "sg:city":"Wendell",
    "sg:classifiers":[
        {
            "category":"Real Estate",
            "subcategory":"Real Estate Services",
            "type":"Services"
        }
    ],
    "sg:phone":"+1 919 366 2247",
    "sg:postcode":"27591",
    "sg:province":"NC",
    "sg:tags":[
        "company",
        "title"
    ],
    "wof:name":"Olde World Title & Marble",
    "wof:placetype":"venue"
},
  "geometry": {"coordinates":[-78.375862,35.779253],"type":"Point"}
}