{
  "type": "Feature",
  "properties": {
    "iso:country":"US",
    "sg:address":"1508 Lula Long Rd",
    "sg:city":"Elizabethtown",
    "sg:classifiers":[
        {
            "category":"Farming",
            "subcategory":"Farm",
            "type":"Manufacturing & Wholesale Goods"
        }
    ],
    "sg:phone":"+1 910 588 4895",
    "sg:postcode":"28337",
    "sg:province":"NC",
    "wof:name":"Prestage Farm",
    "wof:placetype":"venue"
},
  "geometry": {"coordinates":[-78.601164,34.739505],"type":"Point"}
}