{
  "type": "Feature",
  "properties": {
    "addr:full":"4800 University Dr Durham NC 27707",
    "addr:housenumber":"4800",
    "addr:postcode":"27707",
    "addr:street":"University Dr",
    "iso:country":"US",
    "sg:address":"4800 University Dr",
    "sg:city":"Durham",
    "sg:classifiers":[
        {
            "category":"Professional",
            "subcategory":"Computer Services",
            "type":"Services"
        }
    ],
    "sg:phone":"+1   ",
    "sg:postcode":"27707",
    "sg:province":"NC",
    "sg:tags":[
        "hardware",
        "upgrade"
    ],
    "wof:name":"Computeq Industries",
    "wof:placetype":"venue"
},
  "geometry": {"coordinates":[-78.96624199999999,35.953633],"type":"Point"}
}