{
  "type": "Feature",
  "properties": {
    "addr:full":"5701 Executive Center Dr Charlotte NC 28212",
    "addr:housenumber":"5701",
    "addr:postcode":"28212",
    "addr:street":"Executive Center Dr",
    "iso:country":"US",
    "sg:address":"5701 Executive Center Dr",
    "sg:city":"Charlotte",
    "sg:classifiers":[
        {
            "category":"Social Services",
            "type":"Services"
        }
    ],
    "sg:phone":"+1 704 563 4125",
    "sg:postcode":"28212",
    "sg:province":"NC",
    "sg:tags":[
        "probation"
    ],
    "wof:name":"Probation & Parole Dept Adult",
    "wof:placetype":"venue"
},
  "geometry": {"coordinates":[-80.744089,35.201901],"type":"Point"}
}