{
  "type": "Feature",
  "properties": {
    "addr:full":"936 W 4th St Winston Salem NC 27101",
    "addr:housenumber":"936",
    "addr:postcode":"27101",
    "addr:street":"W 4Th St",
    "iso:country":"US",
    "sg:address":"936 W 4th St",
    "sg:city":"Winston Salem",
    "sg:classifiers":[
        {
            "category":"Building & Trades",
            "subcategory":"Construction",
            "type":"Services"
        }
    ],
    "sg:phone":"+1 336 723 6624",
    "sg:postcode":"27101",
    "sg:province":"NC",
    "sg:tags":[
        "specializing",
        "f",
        "work",
        "contractor",
        "restoration",
        "resulting"
    ],
    "sg:website":"www.disastermaster.net",
    "wof:name":"MHC Construction",
    "wof:placetype":"venue"
},
  "geometry": {"coordinates":[-80.257921,36.096347],"type":"Point"}
}