{
  "type": "Feature",
  "properties": {
    "addr:full":"120 Lake Concord Rd NE Concord NC 28025",
    "addr:housenumber":"120",
    "addr:postcode":"28025",
    "addr:street":"Lake Concord Rd Ne",
    "iso:country":"US",
    "sg:address":"120 Lake Concord Rd NE",
    "sg:city":"Concord",
    "sg:classifiers":[
        {
            "category":"Health Services",
            "subcategory":"Doctor",
            "type":"Services"
        }
    ],
    "sg:phone":"+1 704 262 4650",
    "sg:postcode":"28025",
    "sg:province":"NC",
    "sg:tags":[
        "clinic"
    ],
    "wof:name":"Northeast Medical Ctr",
    "wof:placetype":"venue"
},
  "geometry": {"coordinates":[-80.599266,35.437778],"type":"Point"}
}