{
  "type": "Feature",
  "properties": {
    "iso:country":"US",
    "sg:address":"4979 Harvest Rd",
    "sg:city":"Mc Leansville",
    "sg:classifiers":[
        {
            "category":"Building & Trades",
            "subcategory":"Construction",
            "type":"Services"
        }
    ],
    "sg:phone":"+1 336 621 2182",
    "sg:postcode":"27301",
    "sg:province":"NC",
    "sg:tags":[
        "house"
    ],
    "wof:name":"Chris Gann Construction LLC",
    "wof:placetype":"venue"
},
  "geometry": {"coordinates":[-79.682232,36.109172],"type":"Point"}
}