{
  "type": "Feature",
  "properties": {
    "iso:country":"US",
    "sg:address":"102 Montreat Rd",
    "sg:city":"Black Mountain",
    "sg:classifiers":[
        {
            "category":"Government",
            "subcategory":"Office",
            "type":"Public Place"
        }
    ],
    "sg:phone":"+1 828 669 8732",
    "sg:postcode":"28711",
    "sg:province":"NC",
    "sg:tags":[
        "executive",
        "business",
        "association"
    ],
    "wof:name":"Black Mountain Golf Course",
    "wof:placetype":"venue"
},
  "geometry": {"coordinates":[-82.320804,35.617696],"type":"Point"}
}