{
  "type": "Feature",
  "properties": {
    "iso:country":"US",
    "sg:address":"1284 Leasburg Rd",
    "sg:city":"Roxboro",
    "sg:classifiers":[
        {
            "category":"Health Services",
            "subcategory":"Nursing And Care Facility",
            "type":"Services"
        }
    ],
    "sg:phone":"+1 336 330 0108",
    "sg:postcode":"27574",
    "sg:province":"NC",
    "sg:tags":[
        "home",
        "rest"
    ],
    "wof:name":"Cantebury House",
    "wof:placetype":"venue"
},
  "geometry": {"coordinates":[-79.007698,36.389323],"type":"Point"}
}