{
  "type": "Feature",
  "properties": {
    "addr:full":"3040 Hunter Hill Rd Rocky Mount NC 27804",
    "addr:housenumber":"3040",
    "addr:postcode":"27804",
    "addr:street":"Hunter Hill Rd",
    "iso:country":"US",
    "sg:address":"3040 Hunter Hill Rd",
    "sg:city":"Rocky Mount",
    "sg:classifiers":[
        {
            "category":"Retail",
            "subcategory":"Repair Shop",
            "type":"Services"
        }
    ],
    "sg:phone":"+1   ",
    "sg:postcode":"27804",
    "sg:province":"NC",
    "wof:name":"Loren Beeman",
    "wof:placetype":"venue"
},
  "geometry": {"coordinates":[-77.911869,36.010412],"type":"Point"}
}