{
  "type": "Feature",
  "properties": {
    "iso:country":"US",
    "sg:address":"2210 N Elm St",
    "sg:city":"Greensboro",
    "sg:classifiers":[
        {
            "category":"Organizations",
            "subcategory":"Religious Organization",
            "type":"Services"
        }
    ],
    "sg:phone":"+1 336 272 4681",
    "sg:postcode":"27408",
    "sg:province":"NC",
    "sg:tags":[
        "church"
    ],
    "sg:website":"www.members.aol.com/piusxfaith",
    "wof:name":"St Pius The Tenth Catholic Chr",
    "wof:placetype":"venue"
},
  "geometry": {"coordinates":[-79.78787199999999,36.103385],"type":"Point"}
}