{
  "type": "Feature",
  "properties": {
    "addr:full":"2009 McLean Chapel Church Rd Bunnlevel NC 28323",
    "addr:housenumber":"2009",
    "addr:postcode":"28323",
    "addr:street":"Mclean;Church Rd",
    "iso:country":"US",
    "sg:address":"2009 McLean Chapel Church Rd",
    "sg:city":"Bunnlevel",
    "sg:classifiers":[
        {
            "category":"Organizations",
            "subcategory":"Religious Organization",
            "type":"Services"
        }
    ],
    "sg:phone":"+1 910 893 9521",
    "sg:postcode":"28323",
    "sg:province":"NC",
    "sg:tags":[
        "church"
    ],
    "wof:name":"Andrews Chapel AME-Zion Chr",
    "wof:placetype":"venue"
},
  "geometry": {"coordinates":[-78.815725,35.309182],"type":"Point"}
}