{
  "type": "Feature",
  "properties": {
    "addr:full":"3125 Nevada Blvd Charlotte NC 28273",
    "addr:housenumber":"3125",
    "addr:postcode":"28273",
    "addr:street":"Nevada Blvd",
    "iso:country":"US",
    "sg:address":"3125 Nevada Blvd",
    "sg:city":"Charlotte",
    "sg:classifiers":[
        {
            "category":"Building & Trades",
            "subcategory":"Equipment Rental",
            "type":"Services"
        }
    ],
    "sg:phone":"+1 704 588 1119",
    "sg:postcode":"28273",
    "sg:province":"NC",
    "sg:tags":[
        "heavy",
        "repair",
        "construction",
        "who"
    ],
    "wof:name":"Morrow Equipment Co",
    "wof:placetype":"venue"
},
  "geometry": {"coordinates":[-80.94314900000001,35.120276],"type":"Point"}
}