{
  "type": "Feature",
  "properties": {
    "addr:full":"6801 Holly Springs Rd Raleigh NC 27606",
    "addr:housenumber":"6801",
    "addr:postcode":"27606",
    "addr:street":"Holly Springs Rd",
    "iso:country":"US",
    "sg:address":"6801 Holly Springs Rd",
    "sg:city":"Raleigh",
    "sg:classifiers":[
        {
            "category":"Building & Trades",
            "subcategory":"Construction",
            "type":"Services"
        }
    ],
    "sg:phone":"+1 919 851 7529",
    "sg:postcode":"27606",
    "sg:province":"NC",
    "sg:tags":[
        "contractor",
        "grading"
    ],
    "wof:name":"Neal Bob G Grading Service",
    "wof:placetype":"venue"
},
  "geometry": {"coordinates":[-78.745369,35.734268],"type":"Point"}
}