{
  "type": "Feature",
  "properties": {
    "iso:country":"US",
    "sg:address":"10125 Fayetteville Rd",
    "sg:city":"Fuquay Varina",
    "sg:classifiers":[
        {
            "category":"Recreation",
            "type":"Entertainment"
        }
    ],
    "sg:phone":"+1   ",
    "sg:postcode":"27526",
    "sg:province":"NC",
    "wof:name":"Lucky Seven Bingo",
    "wof:placetype":"venue"
},
  "geometry": {"coordinates":[-78.71895600000001,35.627808],"type":"Point"}
}