{
  "type": "Feature",
  "properties": {
    "iso:country":"US",
    "sg:address":"303 Carrituck Ct",
    "sg:city":"Lenoir",
    "sg:classifiers":[
        {
            "category":"Professional",
            "subcategory":"Business Services",
            "type":"Services"
        }
    ],
    "sg:phone":"+1   ",
    "sg:postcode":"28645",
    "sg:province":"NC",
    "wof:name":"Parkway Group LLC",
    "wof:placetype":"venue"
},
  "geometry": {"coordinates":[-81.523538,35.931127],"type":"Point"}
}