{
  "type": "Feature",
  "properties": {
    "addr:full":"1338 Hundred Oaks Dr Charlotte NC 28217",
    "addr:housenumber":"1338",
    "addr:postcode":"28217",
    "addr:street":"Hundred Oaks Dr",
    "iso:country":"US",
    "sg:address":"1338 Hundred Oaks Dr",
    "sg:city":"Charlotte",
    "sg:classifiers":[
        {
            "category":"Wholesale",
            "subcategory":"Groceries",
            "type":"Manufacturing & Wholesale Goods"
        }
    ],
    "sg:phone":"+1 704 565 5500",
    "sg:postcode":"28217",
    "sg:province":"NC",
    "sg:tags":[
        "grocer"
    ],
    "wof:name":"Kraft Foods",
    "wof:placetype":"venue"
},
  "geometry": {"coordinates":[-80.905738,35.143733],"type":"Point"}
}