{
  "type": "Feature",
  "properties": {
    "addr:full":"1423 N Church St Burlington NC 27217",
    "addr:housenumber":"1423",
    "addr:postcode":"27217",
    "addr:street":"N Church St",
    "iso:country":"US",
    "sg:address":"1423 N Church St",
    "sg:city":"Burlington",
    "sg:classifiers":[
        {
            "category":"Professional",
            "subcategory":"Management & Consulting",
            "type":"Services"
        }
    ],
    "sg:phone":"+1   ",
    "sg:postcode":"27217",
    "sg:province":"NC",
    "sg:tags":[
        "business"
    ],
    "wof:name":"Bahrani Hooman",
    "wof:placetype":"venue"
},
  "geometry": {"coordinates":[-79.41295,36.096723],"type":"Point"}
}