{
  "type": "Feature",
  "properties": {
    "addr:full":"2582 State Hwy 49 N Ramseur NC 27316",
    "addr:housenumber":"2582",
    "addr:postcode":"27316",
    "addr:street":"State Hwy 49 N",
    "iso:country":"US",
    "sg:address":"2582 State Hwy 49 N",
    "sg:city":"Ramseur",
    "sg:classifiers":[
        {
            "category":"Building & Trades",
            "subcategory":"Construction",
            "type":"Services"
        }
    ],
    "sg:phone":"+1 336 824 5841",
    "sg:postcode":"27316",
    "sg:province":"NC",
    "wof:name":"H & R Storage",
    "wof:placetype":"venue"
},
  "geometry": {"coordinates":[-79.611087,35.776487],"type":"Point"}
}