{
  "type": "Feature",
  "properties": {
    "addr:full":"245 Donna Ave Winston Salem NC 27101",
    "addr:housenumber":"245",
    "addr:postcode":"27101",
    "addr:street":"Donna Ave",
    "iso:country":"US",
    "sg:address":"245 Donna Ave",
    "sg:city":"Winston Salem",
    "sg:classifiers":[
        {
            "category":"Banks & Credit Unions",
            "subcategory":"Investment Brokerage",
            "type":"Services"
        }
    ],
    "sg:phone":"+1 336 748 1005",
    "sg:postcode":"27101",
    "sg:province":"NC",
    "sg:tags":[
        "stock",
        "bond"
    ],
    "wof:name":"Sterling Investments Inc",
    "wof:placetype":"venue"
},
  "geometry": {"coordinates":[-80.177485,36.121465],"type":"Point"}
}