{
  "type": "Feature",
  "properties": {
    "addr:full":"8208 Smith Rd Apex NC 27539",
    "addr:housenumber":"8208",
    "addr:postcode":"27539",
    "addr:street":"Smith Rd",
    "iso:country":"US",
    "sg:address":"8208 Smith Rd",
    "sg:city":"Apex",
    "sg:classifiers":[
        {
            "category":"Building & Trades",
            "subcategory":"Cleaning & Sanitation",
            "type":"Services"
        }
    ],
    "sg:phone":"+1   ",
    "sg:postcode":"27539",
    "sg:province":"NC",
    "sg:tags":[
        "maintenance"
    ],
    "wof:name":"Horton Commercial System Inc",
    "wof:placetype":"venue"
},
  "geometry": {"coordinates":[-78.80468,35.704827],"type":"Point"}
}