{
  "type": "Feature",
  "properties": {
    "iso:country":"US",
    "sg:address":"801 Hub Morris Rd",
    "sg:city":"Randleman",
    "sg:classifiers":[
        {
            "category":"Real Estate",
            "subcategory":"Real Estate Operator",
            "type":"Services"
        }
    ],
    "sg:phone":"+1 336 672 6200",
    "sg:postcode":"27317",
    "sg:province":"NC",
    "sg:tags":[
        "mobile",
        "home",
        "community"
    ],
    "wof:name":"North Meadows Manufactured",
    "wof:placetype":"venue"
},
  "geometry": {"coordinates":[-79.794535,35.765798],"type":"Point"}
}