{
  "type": "Feature",
  "properties": {
    "addr:full":"2940 Golden Oak Ct Raleigh NC 27603",
    "addr:housenumber":"2940",
    "addr:postcode":"27603",
    "addr:street":"Golden Oak Ct",
    "iso:country":"US",
    "sg:address":"2940 Golden Oak Ct",
    "sg:city":"Raleigh",
    "sg:classifiers":[
        {
            "category":"Professional",
            "subcategory":"Computer Services",
            "type":"Services"
        }
    ],
    "sg:phone":"+1   ",
    "sg:postcode":"27603",
    "sg:province":"NC",
    "sg:tags":[
        "prepackaged",
        "software"
    ],
    "wof:name":"Centuro Software",
    "wof:placetype":"venue"
},
  "geometry": {"coordinates":[-78.68829599999999,35.750327],"type":"Point"}
}