{
  "type": "Feature",
  "properties": {
    "iso:country":"US",
    "sg:address":"102 E High Ave",
    "sg:city":"High Point",
    "sg:classifiers":[
        {
            "category":"Autos & Motor Vehicles",
            "subcategory":"Fuel & Gas Station",
            "type":"Retail Goods"
        }
    ],
    "sg:phone":"+1 336 841 3305",
    "sg:postcode":"27260",
    "sg:province":"NC",
    "sg:tags":[
        "station",
        "gasoline"
    ],
    "wof:name":"Auto Oil Co",
    "wof:placetype":"venue"
},
  "geometry": {"coordinates":[-80.00468499999999,35.957724],"type":"Point"}
}