{
  "type": "Feature",
  "properties": {
    "addr:full":"2504 Creech Rd Raleigh NC 27610",
    "addr:housenumber":"2504",
    "addr:postcode":"27610",
    "addr:street":"Creech Rd",
    "iso:country":"US",
    "sg:address":"2504 Creech Rd",
    "sg:city":"Raleigh",
    "sg:classifiers":[
        {
            "category":"Organizations",
            "subcategory":"Religious Organization",
            "type":"Services"
        }
    ],
    "sg:phone":"+1   ",
    "sg:postcode":"27610",
    "sg:province":"NC",
    "wof:name":"Progrssive Mssnary Bptst Chrch",
    "wof:placetype":"venue"
},
  "geometry": {"coordinates":[-78.607231,35.743742],"type":"Point"}
}