{
  "type": "Feature",
  "properties": {
    "addr:full":"1501 Burton St Rocky Mount NC 27803",
    "addr:housenumber":"1501",
    "addr:postcode":"27803",
    "addr:street":"Burton St",
    "iso:country":"US",
    "sg:address":"1501 Burton St",
    "sg:city":"Rocky Mount",
    "sg:classifiers":[
        {
            "category":"Social Services",
            "subcategory":"Child Care",
            "type":"Services"
        }
    ],
    "sg:phone":"+1 252 446 5529",
    "sg:postcode":"27803",
    "sg:province":"NC",
    "wof:name":"Kids Place",
    "wof:placetype":"venue"
},
  "geometry": {"coordinates":[-77.820677,35.929832],"type":"Point"}
}