{
  "type": "Feature",
  "properties": {
    "iso:country":"US",
    "sg:address":"516 S Van Buren Rd",
    "sg:city":"Eden",
    "sg:classifiers":[
        {
            "category":"Health Services",
            "subcategory":"Doctor",
            "type":"Services"
        }
    ],
    "sg:phone":"+1   ",
    "sg:postcode":"27288",
    "sg:province":"NC",
    "sg:tags":[
        "osteopathic"
    ],
    "wof:name":"Stephen D Guthrie MD",
    "wof:placetype":"venue"
},
  "geometry": {"coordinates":[-79.74169500000001,36.496978],"type":"Point"}
}