{
  "type": "Feature",
  "properties": {
    "addr:full":"415 Vick Ave Raleigh NC 27612",
    "addr:housenumber":"415",
    "addr:postcode":"27612",
    "addr:street":"Vick Ave",
    "iso:country":"US",
    "sg:address":"415 Vick Ave",
    "sg:city":"Raleigh",
    "sg:classifiers":[
        {
            "category":"Health Services",
            "subcategory":"Doctor",
            "type":"Services"
        }
    ],
    "sg:phone":"+1 919 787 0355",
    "sg:postcode":"27612",
    "sg:province":"NC",
    "sg:tags":[
        "dentist"
    ],
    "wof:name":"Bettie R Mc Kaig DDS",
    "wof:placetype":"venue"
},
  "geometry": {"coordinates":[-78.667266,35.82429],"type":"Point"}
}