{
  "type": "Feature",
  "properties": {
    "addr:full":"1802 N Walnut St Lumberton NC 28358",
    "addr:housenumber":"1802",
    "addr:postcode":"28358",
    "addr:street":"N Walnut St",
    "iso:country":"US",
    "sg:address":"1802 N Walnut St",
    "sg:city":"Lumberton",
    "sg:classifiers":[
        {
            "category":"Organizations",
            "subcategory":"Membership Organization",
            "type":"Services"
        }
    ],
    "sg:phone":"+1   ",
    "sg:postcode":"28358",
    "sg:province":"NC",
    "wof:name":"Friends of Recreation & P",
    "wof:placetype":"venue"
},
  "geometry": {"coordinates":[-79.005646,34.630454],"type":"Point"}
}