{
  "type": "Feature",
  "properties": {
    "iso:country":"US",
    "sg:address":"4265 Brownsboro Rd",
    "sg:city":"Winston Salem",
    "sg:classifiers":[
        {
            "category":"Banks & Credit Unions",
            "subcategory":"Financial Services",
            "type":"Services"
        }
    ],
    "sg:phone":"+1 336 896 0999",
    "sg:postcode":"27106",
    "sg:province":"NC",
    "sg:tags":[
        "investor"
    ],
    "wof:name":"Slade Investments",
    "wof:placetype":"venue"
},
  "geometry": {"coordinates":[-80.27202800000001,36.148203],"type":"Point"}
}