{
  "type": "Feature",
  "properties": {
    "iso:country":"US",
    "sg:address":"6604 Ivystone Dr",
    "sg:city":"Jamestown",
    "sg:classifiers":[
        {
            "category":"Freight",
            "type":"Transportation"
        }
    ],
    "sg:phone":"+1 336 456 4680",
    "sg:postcode":"27282",
    "sg:province":"NC",
    "sg:tags":[
        "operator",
        "trucking"
    ],
    "wof:name":"American Delivery",
    "wof:placetype":"venue"
},
  "geometry": {"coordinates":[-79.93465,36.031782],"type":"Point"}
}