{
  "type": "Feature",
  "properties": {
    "addr:full":"7032 Orchard Trce Wilmington NC 28409",
    "addr:housenumber":"7032",
    "addr:postcode":"28409",
    "addr:street":"Orchard Trce",
    "iso:country":"US",
    "sg:address":"7032 Orchard Trce",
    "sg:city":"Wilmington",
    "sg:classifiers":[
        {
            "category":"Professional",
            "type":"Services"
        }
    ],
    "sg:phone":"+1 910 799 8576",
    "sg:postcode":"28409",
    "sg:province":"NC",
    "wof:name":"Garland Simons Concreate Inc",
    "wof:placetype":"venue"
},
  "geometry": {"coordinates":[-77.857648,34.181418],"type":"Point"}
}