{
  "type": "Feature",
  "properties": {
    "addr:full":"2997 US Hwy 258 Kinston NC 28504",
    "addr:housenumber":"2997",
    "addr:postcode":"28504",
    "addr:street":"Us Hwy 258",
    "iso:country":"US",
    "sg:address":"2997 US Hwy 258",
    "sg:city":"Kinston",
    "sg:classifiers":[
        {
            "category":"Shopping",
            "subcategory":"Computers & Home Electronics",
            "type":"Retail Goods"
        }
    ],
    "sg:phone":"+1 252 527 0700",
    "sg:postcode":"28504",
    "sg:province":"NC",
    "sg:tags":[
        "equipment",
        "dealer"
    ],
    "wof:name":"East Carolina Computers",
    "wof:placetype":"venue"
},
  "geometry": {"coordinates":[-77.656037,35.316881],"type":"Point"}
}