{
  "type": "Feature",
  "properties": {
    "addr:full":"4057 US Hwy 70 Bus W Clayton NC 27520",
    "addr:housenumber":"4057",
    "addr:postcode":"27520",
    "addr:street":"Us Hwy 70 Bus W",
    "iso:country":"US",
    "sg:address":"4057 US Hwy 70 Bus W",
    "sg:city":"Clayton",
    "sg:classifiers":[
        {
            "category":"Organizations",
            "subcategory":"Religious Organization",
            "type":"Services"
        }
    ],
    "sg:phone":"+1 919 934 2084",
    "sg:postcode":"27520",
    "sg:province":"NC",
    "sg:tags":[
        "church"
    ],
    "wof:name":"St Ann's Catholic Church",
    "wof:placetype":"venue"
},
  "geometry": {"coordinates":[-78.394944,35.571752],"type":"Point"}
}