{
  "type": "Feature",
  "properties": {
    "iso:country":"US",
    "sg:address":"601 Clay St",
    "sg:city":"Gastonia",
    "sg:classifiers":[
        {
            "category":"Education",
            "subcategory":"School",
            "type":"Public Place"
        }
    ],
    "sg:phone":"+1 704 866 6297",
    "sg:postcode":"28052",
    "sg:province":"NC",
    "sg:tags":[
        "middle"
    ],
    "sg:website":"www.gaston.k12.nc.us",
    "wof:name":"York Chester Middle School",
    "wof:placetype":"venue"
},
  "geometry": {"coordinates":[-81.19204499999999,35.254815],"type":"Point"}
}