{
  "type": "Feature",
  "properties": {
    "iso:country":"US",
    "sg:address":"3905 Country Oaks Dr",
    "sg:city":"Waxhaw",
    "sg:classifiers":[
        {
            "category":"Professional",
            "subcategory":"Management & Consulting",
            "type":"Services"
        }
    ],
    "sg:phone":"+1   ",
    "sg:postcode":"28173",
    "sg:province":"NC",
    "sg:tags":[
        "business"
    ],
    "wof:name":"Nutritionmatters Consulting",
    "wof:placetype":"venue"
},
  "geometry": {"coordinates":[-80.756559,34.936342],"type":"Point"}
}