{
  "type": "Feature",
  "properties": {
    "iso:country":"US",
    "sg:address":"1338 N Brightleaf Blvd",
    "sg:city":"Smithfield",
    "sg:classifiers":[
        {
            "category":"Wholesale",
            "subcategory":"Hardware",
            "type":"Manufacturing & Wholesale Goods"
        }
    ],
    "sg:phone":"+1 919 938 2095",
    "sg:postcode":"27577",
    "sg:province":"NC",
    "sg:tags":[
        "fastener"
    ],
    "sg:website":"www.fastenal.com",
    "wof:name":"Fastenal Co",
    "wof:placetype":"venue"
},
  "geometry": {"coordinates":[-78.305942,35.521562],"type":"Point"}
}