{
  "type": "Feature",
  "properties": {
    "iso:country":"US",
    "sg:address":"10437 US Hwy 17",
    "sg:city":"Williamston",
    "sg:phone":"+1 252 946 4564",
    "sg:postcode":"27892",
    "sg:province":"NC",
    "sg:tags":[
        "farm",
        "corn"
    ],
    "wof:name":"Ralph Lee",
    "wof:placetype":"venue"
},
  "geometry": {"coordinates":[-77.07943400000001,35.691325],"type":"Point"}
}