{
  "type": "Feature",
  "properties": {
    "addr:full":"8701 Goose Pond Cove Waxhaw NC 28173",
    "addr:housenumber":"8701",
    "addr:postcode":"28173",
    "addr:street":"Goose Pond Cove",
    "iso:country":"US",
    "sg:address":"8701 Goose Pond Cove",
    "sg:city":"Waxhaw",
    "sg:classifiers":[
        {
            "category":"Banks & Credit Unions",
            "subcategory":"Bank",
            "type":"Services"
        }
    ],
    "sg:phone":"+1 704 243 0555",
    "sg:postcode":"28173",
    "sg:province":"NC",
    "sg:tags":[
        "loan",
        "real estate"
    ],
    "wof:name":"Union Mortgage Group",
    "wof:placetype":"venue"
},
  "geometry": {"coordinates":[-80.78342000000001,34.981964],"type":"Point"}
}