{
  "type": "Feature",
  "properties": {
    "addr:full":"825 W Morgan St Raleigh NC 27603",
    "addr:housenumber":"825",
    "addr:postcode":"27603",
    "addr:street":"W Morgan St",
    "iso:country":"US",
    "sg:address":"825 W Morgan St",
    "sg:city":"Raleigh",
    "sg:classifiers":[
        {
            "category":"Food & Beverages",
            "subcategory":"Specialty",
            "type":"Retail Goods"
        },
        {
            "category":"Food & Beverages",
            "subcategory":"Groceries & Convenience Stores",
            "type":"Retail Goods"
        }
    ],
    "sg:phone":"+1 919 834 0098",
    "sg:postcode":"27603",
    "sg:province":"NC",
    "sg:tags":[
        "grocers-specialty"
    ],
    "wof:name":"Pick Mart Food Mart",
    "wof:placetype":"venue"
},
  "geometry": {"coordinates":[-78.653526,35.779889],"type":"Point"}
}