{
  "type": "Feature",
  "properties": {
    "iso:country":"US",
    "sg:address":"6100 Hope Farm Ln",
    "sg:city":"Wake Forest",
    "sg:classifiers":[
        {
            "category":"Building & Trades",
            "subcategory":"Landscaping Services",
            "type":"Services"
        }
    ],
    "sg:phone":"+1 919 562 1167",
    "sg:postcode":"27587",
    "sg:province":"NC",
    "sg:tags":[
        "landscape"
    ],
    "wof:name":"Marc Kreuzs Earthly Endvr",
    "wof:placetype":"venue"
},
  "geometry": {"coordinates":[-78.440248,35.953661],"type":"Point"}
}