{
  "type": "Feature",
  "properties": {
    "iso:country":"US",
    "sg:address":"1800 State Hwy 5",
    "sg:city":"Aberdeen",
    "sg:classifiers":[
        {
            "category":"Shopping",
            "subcategory":"Department Store",
            "type":"Retail Goods"
        }
    ],
    "sg:phone":"+1 910 295 4164",
    "sg:postcode":"28315",
    "sg:province":"NC",
    "wof:name":"Dollar General",
    "wof:placetype":"venue"
},
  "geometry": {"coordinates":[-79.47159000000001,35.161372],"type":"Point"}
}