{
  "type": "Feature",
  "properties": {
    "iso:country":"US",
    "sg:address":"1206 Elliot Farm Rd",
    "sg:city":"Fayetteville",
    "sg:classifiers":[
        {
            "category":"Manufacturing",
            "subcategory":"Lumber",
            "type":"Manufacturing & Wholesale Goods"
        },
        {
            "category":"Home & Garden",
            "subcategory":"Garden Supply",
            "type":"Retail Goods"
        }
    ],
    "sg:phone":"+1 910 482 4404",
    "sg:postcode":"28311",
    "sg:province":"NC",
    "sg:tags":[
        "operation",
        "timber",
        "tree",
        "christmas",
        "tract"
    ],
    "wof:name":"B & D Christmas Tree Farm",
    "wof:placetype":"venue"
},
  "geometry": {"coordinates":[-78.89103299999999,35.207047],"type":"Point"}
}