{
  "type": "Feature",
  "properties": {
    "iso:country":"US",
    "sg:address":"608 W 30th St",
    "sg:city":"Lumberton",
    "sg:classifiers":[
        {
            "category":"Education",
            "subcategory":"Library",
            "type":"Public Place"
        }
    ],
    "sg:phone":"+1   ",
    "sg:postcode":"28358",
    "sg:province":"NC",
    "wof:name":"Anderson Creek Inc",
    "wof:placetype":"venue"
},
  "geometry": {"coordinates":[-79.016149,34.638882],"type":"Point"}
}