{
  "type": "Feature",
  "properties": {
    "addr:full":"4809 Hathaway Rd Wilson NC 27893",
    "addr:housenumber":"4809",
    "addr:postcode":"27893",
    "addr:street":"Hathaway Rd",
    "iso:country":"US",
    "sg:address":"4809 Hathaway Rd",
    "sg:city":"Wilson",
    "sg:classifiers":[
        {
            "category":"Building & Trades",
            "subcategory":"Construction",
            "type":"Services"
        }
    ],
    "sg:phone":"+1 252 243 4494",
    "sg:postcode":"27893",
    "sg:province":"NC",
    "sg:tags":[
        "hanging",
        "wallpaper",
        "contractor"
    ],
    "wof:name":"Robert Warrick Paint & Paper",
    "wof:placetype":"venue"
},
  "geometry": {"coordinates":[-77.91145299999999,35.660868],"type":"Point"}
}