{
  "type": "Feature",
  "properties": {
    "addr:full":"409 E Garrison Blvd Gastonia NC 28054",
    "addr:housenumber":"409",
    "addr:postcode":"28054",
    "addr:street":"E Garrison Blvd",
    "iso:country":"US",
    "sg:address":"409 E Garrison Blvd",
    "sg:city":"Gastonia",
    "sg:classifiers":[
        {
            "category":"Food & Beverages",
            "subcategory":"Groceries & Convenience Stores",
            "type":"Retail Goods"
        }
    ],
    "sg:phone":"+1 704 864 0077",
    "sg:postcode":"28054",
    "sg:province":"NC",
    "wof:name":"Daves Express",
    "wof:placetype":"venue"
},
  "geometry": {"coordinates":[-81.175736,35.25338],"type":"Point"}
}