{
  "type": "Feature",
  "properties": {
    "iso:country":"US",
    "sg:address":"7476 State Hwy 705",
    "sg:city":"Eagle Springs",
    "sg:classifiers":[
        {
            "category":"Freight",
            "type":"Transportation"
        }
    ],
    "sg:phone":"+1 910 948 9909",
    "sg:postcode":"27242",
    "sg:province":"NC",
    "sg:tags":[
        "hauling",
        "trucking"
    ],
    "wof:name":"Rouse Brothers Hauling Excavtg",
    "wof:placetype":"venue"
},
  "geometry": {"coordinates":[-79.580398,35.393928],"type":"Point"}
}