{
  "type": "Feature",
  "properties": {
    "iso:country":"US",
    "sg:address":"2599 Mount Gilead Church Rd",
    "sg:city":"Pittsboro",
    "sg:classifiers":[
        {
            "category":"Organizations",
            "subcategory":"Religious Organization",
            "type":"Services"
        }
    ],
    "sg:phone":"+1 919 542 2431",
    "sg:postcode":"27312",
    "sg:province":"NC",
    "sg:tags":[
        "church"
    ],
    "wof:name":"Mt Gilead Baptist Church",
    "wof:placetype":"venue"
},
  "geometry": {"coordinates":[-79.09376,35.771945],"type":"Point"}
}