{
  "type": "Feature",
  "properties": {
    "addr:full":"538 Hollis Rd Charlotte NC 28209",
    "addr:housenumber":"538",
    "addr:postcode":"28209",
    "addr:street":"Hollis Rd",
    "iso:country":"US",
    "sg:address":"538 Hollis Rd",
    "sg:city":"Charlotte",
    "sg:classifiers":[
        {
            "category":"Social Services",
            "type":"Services"
        }
    ],
    "sg:phone":"+1 704 679 9991",
    "sg:postcode":"28209",
    "sg:province":"NC",
    "sg:tags":[
        "youth",
        "organization",
        "center"
    ],
    "wof:name":"Hope Youth Svc",
    "wof:placetype":"venue"
},
  "geometry": {"coordinates":[-80.86664500000001,35.18926],"type":"Point"}
}