{
  "type": "Feature",
  "properties": {
    "addr:full":"150 Dickens Ct Mooresville NC 28115",
    "addr:housenumber":"150",
    "addr:postcode":"28115",
    "addr:street":"Dickens Ct",
    "iso:country":"US",
    "sg:address":"150 Dickens Ct",
    "sg:city":"Mooresville",
    "sg:classifiers":[
        {
            "category":"Manufacturing",
            "subcategory":"Metals",
            "type":"Manufacturing & Wholesale Goods"
        }
    ],
    "sg:phone":"+1 704 662 8878",
    "sg:postcode":"28115",
    "sg:province":"NC",
    "sg:tags":[
        "tool",
        "mfg"
    ],
    "wof:name":"Snap-On Tools",
    "wof:placetype":"venue"
},
  "geometry": {"coordinates":[-80.819475,35.601257],"type":"Point"}
}