{
  "type": "Feature",
  "properties": {
    "iso:country":"US",
    "sg:address":"11801 US Hwy 70 W",
    "sg:city":"Clayton",
    "sg:classifiers":[
        {
            "category":"Professional",
            "subcategory":"Computer Services",
            "type":"Services"
        }
    ],
    "sg:phone":"+1 919 550 0373",
    "sg:postcode":"27520",
    "sg:province":"NC",
    "sg:tags":[
        "internet"
    ],
    "wof:name":"Clearview Of Nc",
    "wof:placetype":"venue"
},
  "geometry": {"coordinates":[-78.47728600000001,35.656068],"type":"Point"}
}