{
  "type": "Feature",
  "properties": {
    "iso:country":"US",
    "sg:address":"3110 S Evans St",
    "sg:city":"Greenville",
    "sg:classifiers":[
        {
            "category":"Home & Garden",
            "subcategory":"Home Furnishings",
            "type":"Retail Goods"
        }
    ],
    "sg:phone":"+1 252 756 8483",
    "sg:postcode":"27834",
    "sg:province":"NC",
    "sg:tags":[
        "curtain",
        "bedding",
        "window",
        "linen"
    ],
    "wof:name":"Affordable HM Fashions Blinds",
    "wof:placetype":"venue"
},
  "geometry": {"coordinates":[-77.381868,35.576974],"type":"Point"}
}