{
  "type": "Feature",
  "properties": {
    "iso:country":"US",
    "sg:address":"1000 Park Forty Plz",
    "sg:city":"Durham",
    "sg:classifiers":[
        {
            "category":"Professional",
            "type":"Services"
        }
    ],
    "sg:phone":"+1 919 544 8073",
    "sg:postcode":"27713",
    "sg:province":"NC",
    "sg:tags":[
        "establishment"
    ],
    "wof:name":"Hanover Co",
    "wof:placetype":"venue"
},
  "geometry": {"coordinates":[-78.893484,35.905067],"type":"Point"}
}