{
  "type": "Feature",
  "properties": {
    "iso:country":"US",
    "sg:address":"5021 Fayetteville Rd",
    "sg:city":"Lumberton",
    "sg:classifiers":[
        {
            "category":"Food & Beverages",
            "subcategory":"Groceries & Convenience Stores",
            "type":"Retail Goods"
        }
    ],
    "sg:phone":"+1 910 738 9051",
    "sg:postcode":"28358",
    "sg:province":"NC",
    "sg:tags":[
        "station",
        "gasoline"
    ],
    "wof:name":"Minuteman Food Mart",
    "wof:placetype":"venue"
},
  "geometry": {"coordinates":[-79.00208000000001,34.666093],"type":"Point"}
}