{
  "type": "Feature",
  "properties": {
    "addr:full":"6940 Hidden Forest Dr Charlotte NC 28213",
    "addr:housenumber":"6940",
    "addr:postcode":"28213",
    "addr:street":"Hidden Forest Dr",
    "iso:country":"US",
    "sg:address":"6940 Hidden Forest Dr",
    "sg:city":"Charlotte",
    "sg:classifiers":[
        {
            "category":"Real Estate",
            "subcategory":"Real Estate Operator",
            "type":"Services"
        }
    ],
    "sg:phone":"+1 704 921 2922",
    "sg:postcode":"28213",
    "sg:province":"NC",
    "sg:tags":[
        "building",
        "apartment"
    ],
    "wof:name":"Crossroads At Village Park",
    "wof:placetype":"venue"
},
  "geometry": {"coordinates":[-80.77891099999999,35.282291],"type":"Point"}
}