{
  "type": "Feature",
  "properties": {
    "iso:country":"US",
    "sg:address":"910 Greenbriar Ln",
    "sg:city":"Wilkesboro",
    "sg:classifiers":[
        {
            "category":"Professional",
            "subcategory":"Management & Consulting",
            "type":"Services"
        }
    ],
    "sg:phone":"+1   ",
    "sg:postcode":"28697",
    "sg:province":"NC",
    "wof:name":"Greenbriar LLP",
    "wof:placetype":"venue"
},
  "geometry": {"coordinates":[-81.167288,36.148249],"type":"Point"}
}