{
  "type": "Feature",
  "properties": {
    "iso:country":"US",
    "sg:address":"3670 Union Chapel Rd",
    "sg:city":"Pembroke",
    "sg:classifiers":[
        {
            "category":"Building & Trades",
            "subcategory":"Electrical",
            "type":"Services"
        }
    ],
    "sg:phone":"+1 910 521 9590",
    "sg:postcode":"28372",
    "sg:province":"NC",
    "sg:tags":[
        "electrical",
        "electric",
        "contractor"
    ],
    "wof:name":"East Coast Electrical Construc",
    "wof:placetype":"venue"
},
  "geometry": {"coordinates":[-79.136549,34.709459],"type":"Point"}
}