{
  "type": "Feature",
  "properties": {
    "iso:country":"US",
    "sg:address":"102 N Main St",
    "sg:city":"Kenansville",
    "sg:classifiers":[
        {
            "category":"Health Services",
            "subcategory":"Clinic",
            "type":"Services"
        }
    ],
    "sg:phone":"+1 910 296 1102",
    "sg:postcode":"28349",
    "sg:province":"NC",
    "sg:tags":[
        "information",
        "program",
        "referral"
    ],
    "wof:name":"Preparing For The Drug Free",
    "wof:placetype":"venue"
},
  "geometry": {"coordinates":[-77.961544,34.961759],"type":"Point"}
}