{
  "type": "Feature",
  "properties": {
    "addr:full":"4275 Old Tar Rd Winterville NC 28590",
    "addr:housenumber":"4275",
    "addr:postcode":"28590",
    "addr:street":"Old Tar Rd",
    "iso:country":"US",
    "sg:address":"4275 Old Tar Rd",
    "sg:city":"Winterville",
    "sg:classifiers":[
        {
            "category":"Retail",
            "subcategory":"Laundry & Dry Cleaning",
            "type":"Services"
        }
    ],
    "sg:phone":"+1 252 321 4717",
    "sg:postcode":"28590",
    "sg:province":"NC",
    "sg:tags":[
        "cleaners"
    ],
    "wof:name":"Rabo Cleaners",
    "wof:placetype":"venue"
},
  "geometry": {"coordinates":[-77.384445,35.542223],"type":"Point"}
}