{
  "type": "Feature",
  "properties": {
    "addr:full":"104 S Main St Walstonburg NC 27888",
    "addr:housenumber":"104",
    "addr:postcode":"27888",
    "addr:street":"S Main St",
    "iso:country":"US",
    "sg:address":"104 S Main St",
    "sg:city":"Walstonburg",
    "sg:classifiers":[
        {
            "category":"Wholesale",
            "subcategory":"Home Furnishings",
            "type":"Manufacturing & Wholesale Goods"
        }
    ],
    "sg:phone":"+1 252 753 3790",
    "sg:postcode":"27888",
    "sg:province":"NC",
    "sg:tags":[
        "picture",
        "frame"
    ],
    "wof:name":"Three 23 Moulding",
    "wof:placetype":"venue"
},
  "geometry": {"coordinates":[-77.697405,35.593926],"type":"Point"}
}