{
  "type": "Feature",
  "properties": {
    "addr:full":"105 W Main St Durham NC 27701",
    "addr:housenumber":"105",
    "addr:postcode":"27701",
    "addr:street":"W Main St",
    "iso:country":"US",
    "sg:address":"105 W Main St",
    "sg:city":"Durham",
    "sg:classifiers":[
        {
            "category":"Real Estate",
            "subcategory":"Real Estate Agent",
            "type":"Services"
        }
    ],
    "sg:phone":"+1 919 682 0501",
    "sg:postcode":"27701",
    "sg:province":"NC",
    "wof:name":"Maverick Partners",
    "wof:placetype":"venue"
},
  "geometry": {"coordinates":[-78.901871,35.995616],"type":"Point"}
}