{
  "type": "Feature",
  "properties": {
    "addr:full":"1839 Washington St Wilmington NC 28401",
    "addr:housenumber":"1839",
    "addr:postcode":"28401",
    "addr:street":"Washington St",
    "iso:country":"US",
    "sg:address":"1839 Washington St",
    "sg:city":"Wilmington",
    "sg:classifiers":[
        {
            "category":"Retail",
            "subcategory":"Auto Repair",
            "type":"Services"
        }
    ],
    "sg:phone":"+1 910 762 6511",
    "sg:postcode":"28401",
    "sg:province":"NC",
    "sg:tags":[
        "repairing",
        "automobile"
    ],
    "wof:name":"Clyde's Auto Svc",
    "wof:placetype":"venue"
},
  "geometry": {"coordinates":[-77.945194,34.208205],"type":"Point"}
}