{
  "type": "Feature",
  "properties": {
    "iso:country":"US",
    "sg:address":"173 N Winstead Ave",
    "sg:city":"Rocky Mount",
    "sg:classifiers":[
        {
            "category":"Health Services",
            "subcategory":"Clinic",
            "type":"Services"
        }
    ],
    "sg:phone":"+1 252 972 4040",
    "sg:postcode":"27804",
    "sg:province":"NC",
    "sg:website":"www.americanhealthcare.com",
    "wof:name":"American Health LLC",
    "wof:placetype":"venue"
},
  "geometry": {"coordinates":[-77.849434,35.964485],"type":"Point"}
}