{
  "type": "Feature",
  "properties": {
    "addr:full":"6841 Market St Ste C Wilmington NC 28405",
    "addr:housenumber":"6841",
    "addr:postcode":"28405",
    "addr:street":"Market St Ste C",
    "iso:country":"US",
    "sg:address":"6841 Market St Ste C",
    "sg:city":"Wilmington",
    "sg:classifiers":[
        {
            "category":"Insurance",
            "subcategory":"Hazard Insurance",
            "type":"Services"
        },
        {
            "category":"Insurance",
            "subcategory":"Insurance Agent",
            "type":"Services"
        },
        {
            "category":"Insurance",
            "subcategory":"Life Insurance",
            "type":"Services"
        },
        {
            "category":"Insurance",
            "subcategory":"Title Insurance",
            "type":"Services"
        }
    ],
    "sg:phone":"+1 910 799 6161",
    "sg:postcode":"28405",
    "sg:province":"NC",
    "sg:tags":[
        "auto",
        "homeowner"
    ],
    "sg:website":"http://www.nationwide.com/agent/Wilmington-NORTH-CAROLINA-insurance-agent/greg-hibiske/office.html",
    "wof:name":"Hibiske Insurance Group - Nationwide Insurance",
    "wof:placetype":"venue"
},
  "geometry": {"coordinates":[-77.831087,34.260504],"type":"Point"}
}