{
  "type": "Feature",
  "properties": {
    "iso:country":"US",
    "sg:address":"541 Pace St",
    "sg:city":"Raleigh",
    "sg:classifiers":[
        {
            "category":"Real Estate",
            "subcategory":"Real Estate Services",
            "type":"Services"
        },
        {
            "category":"Real Estate",
            "subcategory":"Real Estate Agent",
            "type":"Services"
        }
    ],
    "sg:phone":"+1 919 834 3932",
    "sg:postcode":"27604",
    "sg:province":"NC",
    "sg:tags":[
        "buyer",
        "broker"
    ],
    "wof:name":"Chuck Ellstrom Realty",
    "wof:placetype":"venue"
},
  "geometry": {"coordinates":[-78.63107599999999,35.789081],"type":"Point"}
}