{
  "type": "Feature",
  "properties": {
    "addr:full":"3907 N Elm St Greensboro NC 27455",
    "addr:housenumber":"3907",
    "addr:postcode":"27455",
    "addr:street":"N Elm St",
    "iso:country":"US",
    "sg:address":"3907 N Elm St",
    "sg:city":"Greensboro",
    "sg:classifiers":[
        {
            "category":"Real Estate",
            "subcategory":"Real Estate Agent",
            "type":"Services"
        }
    ],
    "sg:phone":"+1 336 282 5979",
    "sg:postcode":"27455",
    "sg:province":"NC",
    "wof:name":"Jeanette Lake Realty",
    "wof:placetype":"venue"
},
  "geometry": {"coordinates":[-79.800071,36.143951],"type":"Point"}
}