{
  "type": "Feature",
  "properties": {
    "iso:country":"US",
    "sg:address":"841 State Hwy 24",
    "sg:city":"Albemarle",
    "sg:classifiers":[
        {
            "category":"Home & Garden",
            "subcategory":"Furniture",
            "type":"Retail Goods"
        }
    ],
    "sg:phone":"+1 704 982 4102",
    "sg:postcode":"28001",
    "sg:province":"NC",
    "wof:name":"Baddock & More Furniture Co",
    "wof:placetype":"venue"
},
  "geometry": {"coordinates":[-80.20485499999999,35.338546],"type":"Point"}
}