{
  "type": "Feature",
  "properties": {
    "iso:country":"US",
    "sg:address":"124 W Broad St",
    "sg:city":"Statesville",
    "sg:classifiers":[
        {
            "category":"Recreation",
            "type":"Entertainment"
        }
    ],
    "sg:phone":"+1 704 872 0731",
    "sg:postcode":"28677",
    "sg:province":"NC",
    "sg:tags":[
        "martial",
        "arts",
        "instruction"
    ],
    "wof:name":"Champion Muay Thai & Fitness",
    "wof:placetype":"venue"
},
  "geometry": {"coordinates":[-80.888632,35.78458],"type":"Point"}
}