{
  "type": "Feature",
  "properties": {
    "addr:full":"3179 Sam Usry Rd Oxford NC 27565",
    "addr:housenumber":"3179",
    "addr:postcode":"27565",
    "addr:street":"Sam Usry Rd",
    "iso:country":"US",
    "sg:address":"3179 Sam Usry Rd",
    "sg:city":"Oxford",
    "sg:classifiers":[
        {
            "category":"Organizations",
            "subcategory":"Religious Organization",
            "type":"Services"
        }
    ],
    "sg:phone":"+1 919 693 1636",
    "sg:postcode":"27565",
    "sg:province":"NC",
    "sg:tags":[
        "church"
    ],
    "wof:name":"Dexter Baptist Church",
    "wof:placetype":"venue"
},
  "geometry": {"coordinates":[-78.60301699999999,36.22027],"type":"Point"}
}