{
  "type": "Feature",
  "properties": {
    "addr:full":"901 Southwood Dr Kings Mountain NC 28086",
    "addr:housenumber":"901",
    "addr:postcode":"28086",
    "addr:street":"Southwood Dr",
    "iso:country":"US",
    "sg:address":"901 Southwood Dr",
    "sg:city":"Kings Mountain",
    "sg:classifiers":[
        {
            "category":"Building & Trades",
            "subcategory":"Landscaping Services",
            "type":"Services"
        }
    ],
    "sg:phone":"+1 704 739 4527",
    "sg:postcode":"28086",
    "sg:province":"NC",
    "wof:name":"Patterson Lawn & Lnd",
    "wof:placetype":"venue"
},
  "geometry": {"coordinates":[-81.36751700000001,35.224942],"type":"Point"}
}