{
  "type": "Feature",
  "properties": {
    "iso:country":"US",
    "sg:address":"3965 Mount Hope Church Rd",
    "sg:city":"Salisbury",
    "sg:classifiers":[
        {
            "category":"Retail",
            "subcategory":"Auto Repair",
            "type":"Services"
        }
    ],
    "sg:phone":"+1   ",
    "sg:postcode":"28146",
    "sg:province":"NC",
    "sg:tags":[
        "body"
    ],
    "wof:name":"Ray Leazer",
    "wof:placetype":"venue"
},
  "geometry": {"coordinates":[-80.494964,35.565514],"type":"Point"}
}