{
  "type": "Feature",
  "properties": {
    "addr:full":"1590 Farmington Rd Mocksville NC 27028",
    "addr:housenumber":"1590",
    "addr:postcode":"27028",
    "addr:street":"Farmington Rd",
    "iso:country":"US",
    "sg:address":"1590 Farmington Rd",
    "sg:city":"Mocksville",
    "sg:classifiers":[
        {
            "category":"Health Services",
            "subcategory":"Clinic",
            "type":"Services"
        }
    ],
    "sg:phone":"+1   ",
    "sg:postcode":"27028",
    "sg:province":"NC",
    "wof:name":"Piedmont Medical Management",
    "wof:placetype":"venue"
},
  "geometry": {"coordinates":[-80.530091,36.003065],"type":"Point"}
}