{
  "type": "Feature",
  "properties": {
    "iso:country":"US",
    "sg:address":"805 S Walker St",
    "sg:city":"Burgaw",
    "sg:classifiers":[
        {
            "category":"Government",
            "subcategory":"Office",
            "type":"Public Place"
        }
    ],
    "sg:phone":"+1 910 259 1536",
    "sg:postcode":"28425",
    "sg:province":"NC",
    "sg:tags":[
        "county",
        "program",
        "adm"
    ],
    "wof:name":"Pender County Tourism",
    "wof:placetype":"venue"
},
  "geometry": {"coordinates":[-77.91281600000001,34.543108],"type":"Point"}
}