{
  "type": "Feature",
  "properties": {
    "iso:country":"US",
    "sg:address":"316 Oak Knoll",
    "sg:city":"Hildebran",
    "sg:classifiers":[
        {
            "category":"Building & Trades",
            "subcategory":"Construction",
            "type":"Services"
        }
    ],
    "sg:phone":"+1 828 397 6596",
    "sg:postcode":"28637",
    "sg:province":"NC",
    "sg:tags":[
        "house"
    ],
    "wof:name":"Metcalf Homebuilders LLC",
    "wof:placetype":"venue"
},
  "geometry": {"coordinates":[-81.418025,35.711135],"type":"Point"}
}