{
  "type": "Feature",
  "properties": {
    "iso:country":"US",
    "sg:address":"1766 Prince Edward Dr",
    "sg:city":"Elon College",
    "sg:classifiers":[
        {
            "category":"Professional",
            "subcategory":"Business Services",
            "type":"Services"
        }
    ],
    "sg:phone":"+1 336 584 7079",
    "sg:postcode":"27244",
    "sg:province":"NC",
    "sg:tags":[
        "auctioneer"
    ],
    "wof:name":"Creekside Auction Svc",
    "wof:placetype":"venue"
},
  "geometry": {"coordinates":[-79.48362299999999,36.115472],"type":"Point"}
}