{
  "type": "Feature",
  "properties": {
    "iso:country":"US",
    "sg:address":"3400 Highland Farm Rd",
    "sg:city":"Hillsborough",
    "sg:classifiers":[
        {
            "category":"Building & Trades",
            "subcategory":"Electrical",
            "type":"Services"
        }
    ],
    "sg:phone":"+1 919 732 6092",
    "sg:postcode":"27278",
    "sg:province":"NC",
    "sg:tags":[
        "electrical",
        "contractor"
    ],
    "wof:name":"Thompson Power & Phone Inc",
    "wof:placetype":"venue"
},
  "geometry": {"coordinates":[-79.146811,36.130183],"type":"Point"}
}