{
  "type": "Feature",
  "properties": {
    "addr:full":"1578 Trailwood Dr Rocky Mount NC 27804",
    "addr:housenumber":"1578",
    "addr:postcode":"27804",
    "addr:street":"Trailwood Dr",
    "iso:country":"US",
    "sg:address":"1578 Trailwood Dr",
    "sg:city":"Rocky Mount",
    "sg:classifiers":[
        {
            "category":"Building & Trades",
            "subcategory":"Construction",
            "type":"Services"
        }
    ],
    "sg:phone":"+1 252 443 5425",
    "sg:postcode":"27804",
    "sg:province":"NC",
    "sg:tags":[
        "house"
    ],
    "wof:name":"Ezzell Construction Inc",
    "wof:placetype":"venue"
},
  "geometry": {"coordinates":[-77.897344,35.991746],"type":"Point"}
}