{
  "type": "Feature",
  "properties": {
    "addr:full":"5852 Farringdon Pl Raleigh NC 27609",
    "addr:housenumber":"5852",
    "addr:postcode":"27609",
    "addr:street":"Farringdon Pl",
    "iso:country":"US",
    "sg:address":"5852 Farringdon Pl",
    "sg:city":"Raleigh",
    "sg:classifiers":[
        {
            "category":"Social Services",
            "type":"Services"
        }
    ],
    "sg:phone":"+1 919 872 2666",
    "sg:postcode":"27609",
    "sg:province":"NC",
    "sg:tags":[
        "organization",
        "welfare"
    ],
    "sg:website":"www.madd.org",
    "wof:name":"Mothers Against Drunk Driving",
    "wof:placetype":"venue"
},
  "geometry": {"coordinates":[-78.621718,35.861596],"type":"Point"}
}