{
  "type": "Feature",
  "properties": {
    "addr:full":"3209 State Hwy 87 Sanford NC 27330",
    "addr:housenumber":"3209",
    "addr:postcode":"27330",
    "addr:street":"State Hwy 87",
    "iso:country":"US",
    "sg:address":"3209 State Hwy 87",
    "sg:city":"Sanford",
    "sg:classifiers":[
        {
            "category":"Autos & Motor Vehicles",
            "subcategory":"Automobile Sales",
            "type":"Retail Goods"
        }
    ],
    "sg:phone":"+1 919 708 5622",
    "sg:postcode":"27330",
    "sg:province":"NC",
    "sg:tags":[
        "car",
        "dealer"
    ],
    "wof:name":"CARSOUTH.NET",
    "wof:placetype":"venue"
},
  "geometry": {"coordinates":[-79.186463,35.531007],"type":"Point"}
}