{
  "type": "Feature",
  "properties": {
    "addr:full":"16590 State Hwy 71 N Shannon NC 28386",
    "addr:housenumber":"16590",
    "addr:postcode":"28386",
    "addr:street":"State Hwy 71 N",
    "iso:country":"US",
    "sg:address":"16590 State Hwy 71 N",
    "sg:city":"Shannon",
    "sg:classifiers":[
        {
            "category":"Retail",
            "subcategory":"Auto Repair",
            "type":"Services"
        }
    ],
    "sg:phone":"+1 910 843 5480",
    "sg:postcode":"28386",
    "sg:province":"NC",
    "sg:tags":[
        "repairing",
        "automobile"
    ],
    "wof:name":"Burns Automotive",
    "wof:placetype":"venue"
},
  "geometry": {"coordinates":[-79.10906199999999,34.858469],"type":"Point"}
}