{
  "type": "Feature",
  "properties": {
    "addr:full":"135 S Bickett Blvd Louisburg NC 27549",
    "addr:housenumber":"135",
    "addr:postcode":"27549",
    "addr:street":"S Bickett Blvd",
    "iso:country":"US",
    "sg:address":"135 S Bickett Blvd",
    "sg:city":"Louisburg",
    "sg:classifiers":[
        {
            "category":"Professional",
            "type":"Services"
        }
    ],
    "sg:phone":"+1 919 496 2535",
    "sg:postcode":"27549",
    "sg:province":"NC",
    "sg:tags":[
        "establishment"
    ],
    "wof:name":"Mga Incorported Dist Manager",
    "wof:placetype":"venue"
},
  "geometry": {"coordinates":[-78.296566,36.095873],"type":"Point"}
}