{
  "type": "Feature",
  "properties": {
    "iso:country":"US",
    "sg:address":"2001 Mount Harmony Church Rd",
    "sg:city":"Matthews",
    "sg:classifiers":[
        {
            "category":"Travel",
            "subcategory":"Hotels & Motels",
            "type":"Entertainment"
        }
    ],
    "sg:phone":"+1 704 849 7227",
    "sg:postcode":"28104",
    "sg:province":"NC",
    "sg:tags":[
        "operation"
    ],
    "wof:name":"Country Suites By Carlson",
    "wof:placetype":"venue"
},
  "geometry": {"coordinates":[-80.68059,35.10482],"type":"Point"}
}