{
  "type": "Feature",
  "properties": {
    "addr:full":"3301 Roberta Rd Concord NC 28027",
    "addr:housenumber":"3301",
    "addr:postcode":"28027",
    "addr:street":"Roberta Rd",
    "iso:country":"US",
    "sg:address":"3301 Roberta Rd",
    "sg:city":"Concord",
    "sg:classifiers":[
        {
            "category":"Organizations",
            "subcategory":"Religious Organization",
            "type":"Services"
        }
    ],
    "sg:phone":"+1   ",
    "sg:postcode":"28027",
    "sg:province":"NC",
    "wof:name":"Roberta Baptist Church",
    "wof:placetype":"venue"
},
  "geometry": {"coordinates":[-80.631787,35.364751],"type":"Point"}
}