{
  "type": "Feature",
  "properties": {
    "addr:full":"2489 Rock Pillar Rd Clayton NC 27520",
    "addr:housenumber":"2489",
    "addr:postcode":"27520",
    "addr:street":"Rock Pillar Rd",
    "iso:country":"US",
    "sg:address":"2489 Rock Pillar Rd",
    "sg:city":"Clayton",
    "sg:classifiers":[
        {
            "category":"Professional",
            "subcategory":"Employment Agencies",
            "type":"Services"
        }
    ],
    "sg:phone":"+1   ",
    "sg:postcode":"27520",
    "sg:province":"NC",
    "sg:tags":[
        "help",
        "supply"
    ],
    "wof:name":"Barbour J Paul Trucking",
    "wof:placetype":"venue"
},
  "geometry": {"coordinates":[-78.413293,35.571228],"type":"Point"}
}