{
  "type": "Feature",
  "properties": {
    "addr:full":"713 W Peace St Raleigh NC 27605",
    "addr:housenumber":"713",
    "addr:postcode":"27605",
    "addr:street":"W Peace St",
    "iso:country":"US",
    "sg:address":"713 W Peace St",
    "sg:city":"Raleigh",
    "sg:classifiers":[
        {
            "category":"Wholesale",
            "subcategory":"Painting Supplies",
            "type":"Manufacturing & Wholesale Goods"
        },
        {
            "category":"Manufacturing",
            "subcategory":"Tools & Machinery",
            "type":"Manufacturing & Wholesale Goods"
        },
        {
            "category":"Building & Trades",
            "subcategory":"Construction",
            "type":"Services"
        },
        {
            "category":"Home & Garden",
            "subcategory":"Building Materials",
            "type":"Retail Goods"
        },
        {
            "category":"Manufacturing",
            "subcategory":"Chemicals & Compounds",
            "type":"Manufacturing & Wholesale Goods"
        },
        {
            "category":"Autos & Motor Vehicles",
            "subcategory":"Auto Supplies",
            "type":"Retail Goods"
        },
        {
            "category":"Building & Trades",
            "subcategory":"Equipment Rental",
            "type":"Services"
        },
        {
            "category":"Manufacturing",
            "subcategory":"Building Materials",
            "type":"Manufacturing & Wholesale Goods"
        }
    ],
    "sg:phone":"+1 919 829 8005",
    "sg:postcode":"27605",
    "sg:province":"NC",
    "sg:tags":[
        "shop",
        "body",
        "spraying",
        "wall",
        "automobile",
        "wallpaper",
        "coating",
        "improvement",
        "paint-wholesale",
        "paint",
        "wallcoverings-installation",
        "wallcoverings",
        "contractor",
        "equipment-renting",
        "painter",
        "manufacturer"
    ],
    "sg:website":"http://raleigh.citysearch.com/profile/external/44047824/raleigh_nc/sherwin_williams.html?publisher=yellowpages&reference_id=1&placement=ypwebsitemip",
    "wof:name":"Sherwin-Williams",
    "wof:placetype":"venue"
},
  "geometry": {"coordinates":[-78.648895,35.788632],"type":"Point"}
}