{
  "type": "Feature",
  "properties": {
    "iso:country":"US",
    "sg:address":"1611 Jones Franklin Rd",
    "sg:city":"Raleigh",
    "sg:classifiers":[
        {
            "category":"Health Services",
            "subcategory":"Health Practitioner",
            "type":"Services"
        }
    ],
    "sg:phone":"+1 919 852 0702",
    "sg:postcode":"27606",
    "sg:province":"NC",
    "sg:tags":[
        "pathologist",
        "speech"
    ],
    "wof:name":"Let's Talk Speech & Language",
    "wof:placetype":"venue"
},
  "geometry": {"coordinates":[-78.728887,35.758078],"type":"Point"}
}