{
  "type": "Feature",
  "properties": {
    "iso:country":"US",
    "sg:address":"208 Jameson Rd",
    "sg:city":"Newland",
    "sg:classifiers":[
        {
            "category":"Wholesale",
            "subcategory":"Durable Goods & Equipment",
            "type":"Manufacturing & Wholesale Goods"
        }
    ],
    "sg:phone":"+1 828 737 0961",
    "sg:postcode":"28657",
    "sg:province":"NC",
    "wof:name":"Mountain Central Vacuums Distr",
    "wof:placetype":"venue"
},
  "geometry": {"coordinates":[-81.91793199999999,36.060553],"type":"Point"}
}