{
  "type": "Feature",
  "properties": {
    "addr:full":"4912 Birkenhead Ct Apex NC 27539",
    "addr:housenumber":"4912",
    "addr:postcode":"27539",
    "addr:street":"Birkenhead Ct",
    "iso:country":"US",
    "sg:address":"4912 Birkenhead Ct",
    "sg:city":"Apex",
    "sg:classifiers":[
        {
            "category":"Professional",
            "type":"Services"
        }
    ],
    "sg:phone":"+1 919 773 2371",
    "sg:postcode":"27539",
    "sg:province":"NC",
    "wof:name":"Pella Window &",
    "wof:placetype":"venue"
},
  "geometry": {"coordinates":[-78.73739500000001,35.643072],"type":"Point"}
}