{
  "type": "Feature",
  "properties": {
    "addr:full":"2767 W 5th St Lumberton NC 28360",
    "addr:housenumber":"2767",
    "addr:postcode":"28360",
    "addr:street":"W 5Th St",
    "iso:country":"US",
    "sg:address":"2767 W 5th St",
    "sg:city":"Lumberton",
    "sg:classifiers":[
        {
            "category":"Personal",
            "subcategory":"Beauty Salon",
            "type":"Services"
        }
    ],
    "sg:phone":"+1   ",
    "sg:postcode":"28360",
    "sg:province":"NC",
    "sg:tags":[
        "shop"
    ],
    "wof:name":"Top Nails",
    "wof:placetype":"venue"
},
  "geometry": {"coordinates":[-79.046609,34.623188],"type":"Point"}
}