{
  "type": "Feature",
  "properties": {
    "addr:full":"4833 Old Charlotte Hwy Monroe NC 28110",
    "addr:housenumber":"4833",
    "addr:postcode":"28110",
    "addr:street":"Old Charlotte Hwy",
    "iso:country":"US",
    "sg:address":"4833 Old Charlotte Hwy",
    "sg:city":"Monroe",
    "sg:classifiers":[
        {
            "category":"Professional",
            "subcategory":"Employment Agencies",
            "type":"Services"
        }
    ],
    "sg:phone":"+1 704 283 6250",
    "sg:postcode":"28110",
    "sg:province":"NC",
    "sg:tags":[
        "opportunity"
    ],
    "wof:name":"Adecco",
    "wof:placetype":"venue"
},
  "geometry": {"coordinates":[-80.637281,35.042566],"type":"Point"}
}