{
  "type": "Feature",
  "properties": {
    "iso:country":"US",
    "sg:address":"148 W College St",
    "sg:city":"Stanley",
    "sg:classifiers":[
        {
            "category":"Freight",
            "type":"Transportation"
        }
    ],
    "sg:phone":"+1 704 263 1334",
    "sg:postcode":"28164",
    "sg:province":"NC",
    "sg:tags":[
        "mover"
    ],
    "wof:name":"All Star Moving & Storage",
    "wof:placetype":"venue"
},
  "geometry": {"coordinates":[-81.098506,35.359758],"type":"Point"}
}