{
  "type": "Feature",
  "properties": {
    "iso:country":"US",
    "sg:address":"1012 Charles Blvd",
    "sg:city":"Greenville",
    "sg:classifiers":[
        {
            "category":"Health Services",
            "subcategory":"Doctor",
            "type":"Services"
        }
    ],
    "sg:phone":"+1 252 752 4812",
    "sg:postcode":"27858",
    "sg:province":"NC",
    "sg:tags":[
        "dentist"
    ],
    "wof:name":"Thomas F Webb DDS",
    "wof:placetype":"venue"
},
  "geometry": {"coordinates":[-77.372328,35.605533],"type":"Point"}
}