{
  "type": "Feature",
  "properties": {
    "iso:country":"US",
    "sg:address":"425 Church Rd",
    "sg:city":"New Bern",
    "sg:classifiers":[
        {
            "category":"Wholesale",
            "subcategory":"Scrap",
            "type":"Manufacturing & Wholesale Goods"
        }
    ],
    "sg:phone":"+1 252 633 9072",
    "sg:postcode":"28560",
    "sg:province":"NC",
    "sg:tags":[
        "metal",
        "iron"
    ],
    "wof:name":"Mitchell Metals",
    "wof:placetype":"venue"
},
  "geometry": {"coordinates":[-77.02077800000001,35.068825],"type":"Point"}
}