{
  "type": "Feature",
  "properties": {
    "iso:country":"US",
    "sg:address":"1496 Garner Station Blvd",
    "sg:city":"Raleigh",
    "sg:classifiers":[
        {
            "category":"Shopping",
            "subcategory":"Gifts & Souvenirs",
            "type":"Retail Goods"
        }
    ],
    "sg:phone":"+1 919 662 1493",
    "sg:postcode":"27603",
    "sg:province":"NC",
    "sg:tags":[
        "shop",
        "card"
    ],
    "wof:name":"Carolyn's Hallmark",
    "wof:placetype":"venue"
},
  "geometry": {"coordinates":[-78.656896,35.724915],"type":"Point"}
}