{
  "type": "Feature",
  "properties": {
    "iso:country":"US",
    "sg:address":"111 Cloister Ct",
    "sg:city":"Chapel Hill",
    "sg:classifiers":[
        {
            "category":"Real Estate",
            "subcategory":"Developer",
            "type":"Services"
        },
        {
            "category":"Building & Trades",
            "subcategory":"Construction",
            "type":"Services"
        }
    ],
    "sg:phone":"+1 919 489 9192",
    "sg:postcode":"27514",
    "sg:province":"NC",
    "sg:tags":[
        "development"
    ],
    "wof:name":"Spang Development",
    "wof:placetype":"venue"
},
  "geometry": {"coordinates":[-79.00505800000001,35.95333],"type":"Point"}
}