{
  "type": "Feature",
  "properties": {
    "addr:full":"6612 Sadie Dr Wendell NC 27591",
    "addr:housenumber":"6612",
    "addr:postcode":"27591",
    "addr:street":"Sadie Dr",
    "iso:country":"US",
    "sg:address":"6612 Sadie Dr",
    "sg:city":"Wendell",
    "sg:classifiers":[
        {
            "category":"Building & Trades",
            "subcategory":"Construction",
            "type":"Services"
        }
    ],
    "sg:phone":"+1 919 365 5045",
    "sg:postcode":"27591",
    "sg:province":"NC",
    "sg:tags":[
        "drywall",
        "contractor"
    ],
    "wof:name":"Curtis Drywall",
    "wof:placetype":"venue"
},
  "geometry": {"coordinates":[-78.405829,35.840871],"type":"Point"}
}