{
  "type": "Feature",
  "properties": {
    "iso:country":"US",
    "sg:address":"345 Cranberry Springs Rd",
    "sg:city":"Fleetwood",
    "sg:classifiers":[
        {
            "category":"Manufacturing",
            "subcategory":"Glass & Minerals",
            "type":"Manufacturing & Wholesale Goods"
        }
    ],
    "sg:phone":"+1 336 877 9090",
    "sg:postcode":"28626",
    "sg:province":"NC",
    "sg:tags":[
        "stone",
        "cut",
        "product"
    ],
    "wof:name":"Appalachian Manufactured Stone",
    "wof:placetype":"venue"
},
  "geometry": {"coordinates":[-81.500362,36.260835],"type":"Point"}
}