{
  "type": "Feature",
  "properties": {
    "iso:country":"US",
    "sg:address":"1236 Suffolk Ct",
    "sg:city":"Cary",
    "sg:classifiers":[
        {
            "category":"Building & Trades",
            "subcategory":"Cleaning & Sanitation",
            "type":"Services"
        },
        {
            "category":"Professional",
            "subcategory":"Business Services",
            "type":"Services"
        }
    ],
    "sg:phone":"+1 919 363 7585",
    "sg:postcode":"27511",
    "sg:province":"NC",
    "wof:name":"Advanced Hood and Duct Svcs",
    "wof:placetype":"venue"
},
  "geometry": {"coordinates":[-78.74886600000001,35.775011],"type":"Point"}
}