{
  "type": "Feature",
  "properties": {
    "addr:full":"2202 Burnett Blvd Wilmington NC 28401",
    "addr:housenumber":"2202",
    "addr:postcode":"28401",
    "addr:street":"Burnett Blvd",
    "iso:country":"US",
    "sg:address":"2202 Burnett Blvd",
    "sg:city":"Wilmington",
    "sg:classifiers":[
        {
            "category":"Building & Trades",
            "subcategory":"Construction",
            "type":"Services"
        }
    ],
    "sg:phone":"+1 910 762 3232",
    "sg:postcode":"28401",
    "sg:province":"NC",
    "sg:tags":[
        "general",
        "contractor"
    ],
    "wof:name":"Taylor Brothers Mrne Constr",
    "wof:placetype":"venue"
},
  "geometry": {"coordinates":[-77.94789,34.196297],"type":"Point"}
}