{
  "type": "Feature",
  "properties": {
    "iso:country":"US",
    "sg:address":"500 Piney Creek School Rd",
    "sg:city":"Piney Creek",
    "sg:classifiers":[
        {
            "category":"Government",
            "subcategory":"Office",
            "type":"Public Place"
        }
    ],
    "sg:phone":"+1 336 359 2538",
    "sg:postcode":"28663",
    "sg:province":"NC",
    "sg:tags":[
        "county"
    ],
    "wof:name":"Alleghany County",
    "wof:placetype":"venue"
},
  "geometry": {"coordinates":[-81.303011,36.548852],"type":"Point"}
}