{
  "type": "Feature",
  "properties": {
    "iso:country":"US",
    "sg:address":"225 B St",
    "sg:city":"Fayetteville",
    "sg:classifiers":[
        {
            "category":"Education",
            "subcategory":"School",
            "type":"Public Place"
        }
    ],
    "sg:phone":"+1 910 483 5434",
    "sg:postcode":"28301",
    "sg:province":"NC",
    "wof:name":"Pauline Jones Elementary Schl",
    "wof:placetype":"venue"
},
  "geometry": {"coordinates":[-78.86812500000001,35.052099],"type":"Point"}
}