{
  "type": "Feature",
  "properties": {
    "iso:country":"US",
    "sg:address":"1925 Rosemont St",
    "sg:city":"Salisbury",
    "sg:classifiers":[
        {
            "category":"Professional",
            "subcategory":"Business Services",
            "type":"Services"
        }
    ],
    "sg:phone":"+1   ",
    "sg:postcode":"28144",
    "sg:province":"NC",
    "wof:name":"Unity Force Three Inc",
    "wof:placetype":"venue"
},
  "geometry": {"coordinates":[-80.49852,35.657178],"type":"Point"}
}