{
  "type": "Feature",
  "properties": {
    "iso:country":"US",
    "sg:address":"401 Farris Ave E",
    "sg:city":"High Point",
    "sg:classifiers":[
        {
            "category":"Building & Trades",
            "subcategory":"Construction",
            "type":"Services"
        }
    ],
    "sg:phone":"+1 336 885 9213",
    "sg:postcode":"27262",
    "sg:province":"NC",
    "sg:tags":[
        "house",
        "remodeling"
    ],
    "wof:name":"Ned R Eldridge Inc",
    "wof:placetype":"venue"
},
  "geometry": {"coordinates":[-80.010385,35.971902],"type":"Point"}
}