{
  "type": "Feature",
  "properties": {
    "addr:full":"571 S Sycamore St Rose Hill NC 28458",
    "addr:housenumber":"571",
    "addr:postcode":"28458",
    "addr:street":"S Sycamore St",
    "iso:country":"US",
    "sg:address":"571 S Sycamore St",
    "sg:city":"Rose Hill",
    "sg:classifiers":[
        {
            "category":"Health Services",
            "subcategory":"Nursing And Care Facility",
            "type":"Services"
        }
    ],
    "sg:phone":"+1 910 289 2435",
    "sg:postcode":"28458",
    "sg:province":"NC",
    "sg:tags":[
        "home",
        "rest"
    ],
    "wof:name":"Rosemary Rest Home",
    "wof:placetype":"venue"
},
  "geometry": {"coordinates":[-78.02048600000001,34.821501],"type":"Point"}
}