{
  "type": "Feature",
  "properties": {
    "addr:full":"111 Homestead Ave Boiling Springs NC 28081",
    "addr:housenumber":"111",
    "addr:postcode":"28081",
    "addr:street":"Homestead Ave",
    "iso:country":"US",
    "sg:address":"111 Homestead Ave",
    "sg:city":"Boiling Springs",
    "sg:classifiers":[
        {
            "category":"Retail",
            "subcategory":"Veterinary Services",
            "type":"Services"
        }
    ],
    "sg:phone":"+1 704 434 6815",
    "sg:postcode":"28081",
    "sg:province":"NC",
    "sg:tags":[
        "veterinarian"
    ],
    "wof:name":"Boiling Springs Animal Clinic",
    "wof:placetype":"venue"
},
  "geometry": {"coordinates":[-80.653966,35.513608],"type":"Point"}
}