{
  "type": "Feature",
  "properties": {
    "addr:full":"110 Charles Ridge Rd Asheville NC 28805",
    "addr:housenumber":"110",
    "addr:postcode":"28805",
    "addr:street":"Charles Ridge Rd",
    "iso:country":"US",
    "sg:address":"110 Charles Ridge Rd",
    "sg:city":"Asheville",
    "sg:classifiers":[
        {
            "category":"Wholesale",
            "subcategory":"Groceries",
            "type":"Manufacturing & Wholesale Goods"
        }
    ],
    "sg:phone":"+1 828 299 4849",
    "sg:postcode":"28805",
    "sg:province":"NC",
    "sg:tags":[
        "general"
    ],
    "wof:name":"VMD Enterprises Inc",
    "wof:placetype":"venue"
},
  "geometry": {"coordinates":[-82.48159,35.609331],"type":"Point"}
}