{
  "type": "Feature",
  "properties": {
    "iso:country":"US",
    "sg:address":"727 W Hargett St",
    "sg:city":"Raleigh",
    "sg:classifiers":[
        {
            "category":"Banks & Credit Unions",
            "subcategory":"Bank",
            "type":"Services"
        }
    ],
    "sg:phone":"+1 919 834 3334",
    "sg:postcode":"27603",
    "sg:province":"NC",
    "sg:tags":[
        "loan",
        "real estate"
    ],
    "wof:name":"Hearthside Lending Corp",
    "wof:placetype":"venue"
},
  "geometry": {"coordinates":[-78.65046599999999,35.778663],"type":"Point"}
}