{
  "type": "Feature",
  "properties": {
    "iso:country":"US",
    "sg:address":"1001 US Hwy 17",
    "sg:city":"Elizabeth City",
    "sg:classifiers":[
        {
            "category":"Restaurant",
            "type":"Food & Drink"
        }
    ],
    "sg:phone":"+1 252 331 1702",
    "sg:postcode":"27909",
    "sg:province":"NC",
    "sg:website":"www.hardees.com",
    "wof:name":"Hardee's",
    "wof:placetype":"venue"
},
  "geometry": {"coordinates":[-76.218593,36.313618],"type":"Point"}
}