{
  "type": "Feature",
  "properties": {
    "iso:country":"US",
    "sg:address":"6341 S Point Dr",
    "sg:city":"Charlotte",
    "sg:classifiers":[
        {
            "category":"Building & Trades",
            "subcategory":"Construction",
            "type":"Services"
        }
    ],
    "sg:phone":"+1 704 752 1800",
    "sg:postcode":"28277",
    "sg:province":"NC",
    "sg:tags":[
        "builder",
        "deck"
    ],
    "wof:name":"Wood Re New",
    "wof:placetype":"venue"
},
  "geometry": {"coordinates":[-80.826821,35.076544],"type":"Point"}
}