{
  "type": "Feature",
  "properties": {
    "iso:country":"US",
    "sg:address":"1229 Burkemont Ave",
    "sg:city":"Morganton",
    "sg:classifiers":[
        {
            "category":"Shopping",
            "subcategory":"Books",
            "type":"Retail Goods"
        }
    ],
    "sg:phone":"+1 828 437 1885",
    "sg:postcode":"28655",
    "sg:province":"NC",
    "wof:name":"Living Water",
    "wof:placetype":"venue"
},
  "geometry": {"coordinates":[-81.69528800000001,35.716873],"type":"Point"}
}