{
  "type": "Feature",
  "properties": {
    "iso:country":"US",
    "sg:address":"814 N Main St",
    "sg:city":"Mount Airy",
    "sg:classifiers":[
        {
            "category":"Home & Garden",
            "subcategory":"Carpets & Floor Coverings",
            "type":"Retail Goods"
        }
    ],
    "sg:phone":"+1 336 789 4231",
    "sg:postcode":"27030",
    "sg:province":"NC",
    "wof:name":"Stephens Agency Inc",
    "wof:placetype":"venue"
},
  "geometry": {"coordinates":[-80.609702,36.508959],"type":"Point"}
}