{
  "type": "Feature",
  "properties": {
    "iso:country":"US",
    "sg:address":"6331 South Blvd",
    "sg:city":"Charlotte",
    "sg:classifiers":[
        {
            "category":"Retail",
            "subcategory":"Auto Repair",
            "type":"Services"
        }
    ],
    "sg:phone":"+1   ",
    "sg:postcode":"28217",
    "sg:province":"NC",
    "sg:tags":[
        "muffler",
        "brake",
        "installation",
        "sales"
    ],
    "wof:name":"Midas Muffler",
    "wof:placetype":"venue"
},
  "geometry": {"coordinates":[-80.876328,35.148276],"type":"Point"}
}