{
  "type": "Feature",
  "properties": {
    "iso:country":"US",
    "sg:address":"151 Patton Ave",
    "sg:city":"Asheville",
    "sg:classifiers":[
        {
            "category":"Government",
            "subcategory":"Office",
            "type":"Public Place"
        }
    ],
    "sg:phone":"+1 828 271 4764",
    "sg:postcode":"28801",
    "sg:province":"NC",
    "sg:tags":[
        "federal",
        "taxation"
    ],
    "wof:name":"US Internal Revenue Svc",
    "wof:placetype":"venue"
},
  "geometry": {"coordinates":[-82.55691400000001,35.594012],"type":"Point"}
}