{
  "type": "Feature",
  "properties": {
    "iso:country":"US",
    "sg:address":"420 Fairview Dr SW",
    "sg:city":"Lenoir",
    "sg:classifiers":[
        {
            "category":"Government",
            "subcategory":"Fire Station",
            "type":"Public Place"
        }
    ],
    "sg:phone":"+1 828 754 7117",
    "sg:postcode":"28645",
    "sg:province":"NC",
    "sg:tags":[
        "department"
    ],
    "wof:name":"Lenoir Rescue Squad",
    "wof:placetype":"venue"
},
  "geometry": {"coordinates":[-81.561487,35.899742],"type":"Point"}
}