{
  "type": "Feature",
  "properties": {
    "addr:full":"6505 Liberty Rd Julian NC 27283",
    "addr:housenumber":"6505",
    "addr:postcode":"27283",
    "addr:street":"Liberty Rd",
    "iso:country":"US",
    "sg:address":"6505 Liberty Rd",
    "sg:city":"Julian",
    "sg:classifiers":[
        {
            "category":"Food & Beverages",
            "subcategory":"Groceries & Convenience Stores",
            "type":"Retail Goods"
        }
    ],
    "sg:phone":"+1 336 685 9739",
    "sg:postcode":"27283",
    "sg:province":"NC",
    "wof:name":"Murphy's",
    "wof:placetype":"venue"
},
  "geometry": {"coordinates":[-79.662068,35.911629],"type":"Point"}
}