{
  "type": "Feature",
  "properties": {
    "addr:full":"3383 Hickory Blvd Hudson NC 28638",
    "addr:housenumber":"3383",
    "addr:postcode":"28638",
    "addr:street":"Hickory Blvd",
    "iso:country":"US",
    "sg:address":"3383 Hickory Blvd",
    "sg:city":"Hudson",
    "sg:classifiers":[
        {
            "category":"Home & Garden",
            "subcategory":"Furniture",
            "type":"Retail Goods"
        }
    ],
    "sg:phone":"+1 828 313 1096",
    "sg:postcode":"28638",
    "sg:province":"NC",
    "wof:name":"Furniture For Less",
    "wof:placetype":"venue"
},
  "geometry": {"coordinates":[-81.45851500000001,35.833633],"type":"Point"}
}