{
  "type": "Feature",
  "properties": {
    "iso:country":"US",
    "sg:address":"108 Girard Ave",
    "sg:city":"Fayetteville",
    "sg:classifiers":[
        {
            "category":"Professional",
            "type":"Services"
        }
    ],
    "sg:phone":"+1 910 822 4060",
    "sg:postcode":"28311",
    "sg:province":"NC",
    "sg:tags":[
        "establishment"
    ],
    "wof:name":"Homeplace At Fayetteville",
    "wof:placetype":"venue"
},
  "geometry": {"coordinates":[-78.872873,35.143564],"type":"Point"}
}