{
  "type": "Feature",
  "properties": {
    "iso:country":"US",
    "sg:address":"44 Buck Shoals Rd",
    "sg:city":"Arden",
    "sg:classifiers":[
        {
            "category":"Manufacturing",
            "subcategory":"Tools & Machinery",
            "type":"Manufacturing & Wholesale Goods"
        }
    ],
    "sg:phone":"+1 828 687 3686",
    "sg:postcode":"28704",
    "sg:province":"NC",
    "sg:tags":[
        "precision",
        "related",
        "mfg"
    ],
    "wof:name":"S T and F Precision Tech & Tls",
    "wof:placetype":"venue"
},
  "geometry": {"coordinates":[-82.516149,35.4605],"type":"Point"}
}