{
  "type": "Feature",
  "properties": {
    "iso:country":"US",
    "sg:address":"105 N 10th St",
    "sg:city":"Morehead City",
    "sg:classifiers":[
        {
            "category":"Arts & Performance",
            "subcategory":"Theater",
            "type":"Entertainment"
        }
    ],
    "sg:phone":"+1   ",
    "sg:postcode":"28557",
    "sg:province":"NC",
    "sg:tags":[
        "group"
    ],
    "wof:name":"9 Muses Entertainment",
    "wof:placetype":"venue"
},
  "geometry": {"coordinates":[-76.715408,34.722445],"type":"Point"}
}