{
  "type": "Feature",
  "properties": {
    "iso:country":"US",
    "sg:address":"12628 Sabal Park Dr",
    "sg:city":"Pineville",
    "sg:classifiers":[
        {
            "category":"Education",
            "subcategory":"Dance Studio",
            "type":"Public Place"
        }
    ],
    "sg:phone":"+1   ",
    "sg:postcode":"28134",
    "sg:province":"NC",
    "wof:name":"Howland Dance Productions Inc",
    "wof:placetype":"venue"
},
  "geometry": {"coordinates":[-80.882938,35.074999],"type":"Point"}
}