{
  "type": "Feature",
  "properties": {
    "iso:country":"US",
    "sg:address":"6511 S Rocky River Rd",
    "sg:city":"Monroe",
    "sg:classifiers":[
        {
            "category":"Building & Trades",
            "subcategory":"Construction",
            "type":"Services"
        }
    ],
    "sg:phone":"+1 704 764 8333",
    "sg:postcode":"28112",
    "sg:province":"NC",
    "sg:tags":[
        "general",
        "industrial",
        "commercial",
        "contractor"
    ],
    "wof:name":"AMS Contractors",
    "wof:placetype":"venue"
},
  "geometry": {"coordinates":[-80.62186199999999,34.847759],"type":"Point"}
}