{
  "type": "Feature",
  "properties": {
    "iso:country":"US",
    "sg:address":"227 Barnes Ct",
    "sg:city":"Nashville",
    "sg:classifiers":[
        {
            "category":"Government",
            "subcategory":"Jail",
            "type":"Public Place"
        }
    ],
    "sg:phone":"+1 252 459 4554",
    "sg:postcode":"27856",
    "sg:province":"NC",
    "sg:tags":[
        "corrections",
        "community"
    ],
    "wof:name":"Community Corrections",
    "wof:placetype":"venue"
},
  "geometry": {"coordinates":[-77.931938,35.957148],"type":"Point"}
}