{
  "type": "Feature",
  "properties": {
    "addr:full":"645 Park St Belmont NC 28012",
    "addr:housenumber":"645",
    "addr:postcode":"28012",
    "addr:street":"Park St",
    "iso:country":"US",
    "sg:address":"645 Park St",
    "sg:city":"Belmont",
    "sg:classifiers":[
        {
            "category":"Banks & Credit Unions",
            "subcategory":"Bank",
            "type":"Services"
        }
    ],
    "sg:phone":"+1 704 825 4591",
    "sg:postcode":"28012",
    "sg:province":"NC",
    "sg:tags":[
        "national",
        "commercial"
    ],
    "wof:name":"Bank Of America",
    "wof:placetype":"venue"
},
  "geometry": {"coordinates":[-81.027822,35.252903],"type":"Point"}
}