{
  "type": "Feature",
  "properties": {
    "addr:full":"262 Gibbs Rd Mooresville NC 28117",
    "addr:housenumber":"262",
    "addr:postcode":"28117",
    "addr:street":"Gibbs Rd",
    "iso:country":"US",
    "sg:address":"262 Gibbs Rd",
    "sg:city":"Mooresville",
    "sg:classifiers":[
        {
            "category":"Manufacturing",
            "subcategory":"Rubber & Plastics",
            "type":"Manufacturing & Wholesale Goods"
        }
    ],
    "sg:phone":"+1 704 664 3005",
    "sg:postcode":"28117",
    "sg:province":"NC",
    "sg:tags":[
        "foam",
        "mfg"
    ],
    "wof:name":"Bsci Inc",
    "wof:placetype":"venue"
},
  "geometry": {"coordinates":[-80.858283,35.571215],"type":"Point"}
}