{
  "type": "Feature",
  "properties": {
    "iso:country":"US",
    "sg:address":"224 Edwards Rd",
    "sg:city":"Thomasville",
    "sg:classifiers":[
        {
            "category":"Building & Trades",
            "subcategory":"Construction",
            "type":"Services"
        }
    ],
    "sg:phone":"+1 336 476 7313",
    "sg:postcode":"27360",
    "sg:province":"NC",
    "sg:tags":[
        "heavy"
    ],
    "wof:name":"Fansler Grading Inc",
    "wof:placetype":"venue"
},
  "geometry": {"coordinates":[-80.143117,35.839092],"type":"Point"}
}