{
  "type": "Feature",
  "properties": {
    "iso:country":"US",
    "sg:address":"2160 Hollerin Rd",
    "sg:city":"Dunn",
    "sg:classifiers":[
        {
            "category":"Farming",
            "subcategory":"Poultry Farm",
            "type":"Manufacturing & Wholesale Goods"
        }
    ],
    "sg:phone":"+1 910 567 6280",
    "sg:postcode":"28334",
    "sg:province":"NC",
    "sg:tags":[
        "egg"
    ],
    "wof:name":"B & L Farms Inc",
    "wof:placetype":"venue"
},
  "geometry": {"coordinates":[-78.513761,35.183899],"type":"Point"}
}