{
  "type": "Feature",
  "properties": {
    "addr:full":"1102 Saint Patrick St Tarboro NC 27886",
    "addr:housenumber":"1102",
    "addr:postcode":"27886",
    "addr:street":"Saint Patrick St",
    "iso:country":"US",
    "sg:address":"1102 Saint Patrick St",
    "sg:city":"Tarboro",
    "sg:classifiers":[
        {
            "category":"Health Services",
            "subcategory":"Doctor",
            "type":"Services"
        }
    ],
    "sg:phone":"+1   ",
    "sg:postcode":"27886",
    "sg:province":"NC",
    "sg:tags":[
        "medical"
    ],
    "wof:name":"Anesthesia Relief Service P C",
    "wof:placetype":"venue"
},
  "geometry": {"coordinates":[-77.53705600000001,35.905566],"type":"Point"}
}