{
  "type": "Feature",
  "properties": {
    "iso:country":"US",
    "sg:address":"4300 S Miami Blvd",
    "sg:city":"Durham",
    "sg:classifiers":[
        {
            "category":"Education",
            "subcategory":"Library",
            "type":"Public Place"
        }
    ],
    "sg:phone":"+1 919 549 4227",
    "sg:postcode":"27703",
    "sg:province":"NC",
    "wof:name":"Us Army Research Ofc Tech Libr",
    "wof:placetype":"venue"
},
  "geometry": {"coordinates":[-78.85113200000001,35.901531],"type":"Point"}
}