{
  "type": "Feature",
  "properties": {
    "iso:country":"US",
    "sg:address":"5 Dundas Cir",
    "sg:city":"Greensboro",
    "sg:classifiers":[
        {
            "category":"Building & Trades",
            "subcategory":"Cleaning & Sanitation",
            "type":"Services"
        },
        {
            "category":"Retail",
            "subcategory":"Laundry & Dry Cleaning",
            "type":"Services"
        }
    ],
    "sg:phone":"+1 336 379 8187",
    "sg:postcode":"27407",
    "sg:province":"NC",
    "sg:tags":[
        "janitor"
    ],
    "wof:name":"Eagle Carpet Care",
    "wof:placetype":"venue"
},
  "geometry": {"coordinates":[-79.864116,36.068057],"type":"Point"}
}