{
  "type": "Feature",
  "properties": {
    "addr:full":"3209 Boone Trl Fayetteville NC 28306",
    "addr:housenumber":"3209",
    "addr:postcode":"28306",
    "addr:street":"Boone Trl",
    "iso:country":"US",
    "sg:address":"3209 Boone Trl",
    "sg:city":"Fayetteville",
    "sg:classifiers":[
        {
            "category":"Manufacturing",
            "subcategory":"Metals",
            "type":"Manufacturing & Wholesale Goods"
        }
    ],
    "sg:phone":"+1 910 425 1769",
    "sg:postcode":"28306",
    "sg:province":"NC",
    "sg:tags":[
        "fence"
    ],
    "wof:name":"Smelcer Fence Contractors",
    "wof:placetype":"venue"
},
  "geometry": {"coordinates":[-78.929332,35.026681],"type":"Point"}
}