{
  "type": "Feature",
  "properties": {
    "iso:country":"US",
    "sg:address":"282 Berkeley Rd",
    "sg:city":"Hendersonville",
    "sg:classifiers":[
        {
            "category":"Building & Trades",
            "subcategory":"Construction",
            "type":"Services"
        }
    ],
    "sg:phone":"+1 828 698 9363",
    "sg:postcode":"28792",
    "sg:province":"NC",
    "sg:tags":[
        "contractor"
    ],
    "wof:name":"TNT Roofing",
    "wof:placetype":"venue"
},
  "geometry": {"coordinates":[-82.464156,35.342195],"type":"Point"}
}