{
  "type": "Feature",
  "properties": {
    "addr:full":"3 Trexler Ave Thomasville NC 27360",
    "addr:housenumber":"3",
    "addr:postcode":"27360",
    "addr:street":"Trexler Ave",
    "iso:country":"US",
    "sg:address":"3 Trexler Ave",
    "sg:city":"Thomasville",
    "sg:classifiers":[
        {
            "category":"Retail",
            "subcategory":"Auto Repair",
            "type":"Services"
        }
    ],
    "sg:phone":"+1 336 476 2068",
    "sg:postcode":"27360",
    "sg:province":"NC",
    "sg:tags":[
        "body",
        "automobile",
        "painting",
        "general"
    ],
    "wof:name":"Beck's Automotive",
    "wof:placetype":"venue"
},
  "geometry": {"coordinates":[-80.09179399999999,35.859919],"type":"Point"}
}