{
  "type": "Feature",
  "properties": {
    "addr:full":"224 Chapel St Spruce Pine NC 28777",
    "addr:housenumber":"224",
    "addr:postcode":"28777",
    "addr:street":"Chapel St",
    "iso:country":"US",
    "sg:address":"224 Chapel St",
    "sg:city":"Spruce Pine",
    "sg:classifiers":[
        {
            "category":"Organizations",
            "subcategory":"Religious Organization",
            "type":"Services"
        }
    ],
    "sg:phone":"+1 828 765 6590",
    "sg:postcode":"28777",
    "sg:province":"NC",
    "wof:name":"Berry Chapel Baptist Church",
    "wof:placetype":"venue"
},
  "geometry": {"coordinates":[-82.063568,35.907699],"type":"Point"}
}