{
  "type": "Feature",
  "properties": {
    "addr:full":"1826 E Ozark Ave Gastonia NC 28054",
    "addr:housenumber":"1826",
    "addr:postcode":"28054",
    "addr:street":"E Ozark Ave",
    "iso:country":"US",
    "sg:address":"1826 E Ozark Ave",
    "sg:city":"Gastonia",
    "sg:classifiers":[
        {
            "category":"Retail",
            "subcategory":"Auto Rental",
            "type":"Services"
        }
    ],
    "sg:phone":"+1 704 867 0668",
    "sg:postcode":"28054",
    "sg:province":"NC",
    "sg:tags":[
        "renting",
        "truck",
        "leasing"
    ],
    "wof:name":"U-Haul Co",
    "wof:placetype":"venue"
},
  "geometry": {"coordinates":[-81.15391700000001,35.27748],"type":"Point"}
}