{
  "type": "Feature",
  "properties": {
    "addr:full":"201 W Market St Greensboro NC 27401",
    "addr:housenumber":"201",
    "addr:postcode":"27401",
    "addr:street":"W Market St",
    "iso:country":"US",
    "sg:address":"201 W Market St",
    "sg:city":"Greensboro",
    "sg:classifiers":[
        {
            "category":"Banks & Credit Unions",
            "subcategory":"Bank",
            "type":"Services"
        },
        {
            "category":"Banks & Credit Unions",
            "subcategory":"Financial Services",
            "type":"Services"
        }
    ],
    "sg:phone":"+1 336 433 4001",
    "sg:postcode":"27401",
    "sg:province":"NC",
    "sg:tags":[
        "commercial",
        "financing",
        "saving",
        "loan"
    ],
    "sg:website":"http://www.bbt.com",
    "wof:name":"BB & T",
    "wof:placetype":"venue"
},
  "geometry": {"coordinates":[-79.791489,36.072552],"type":"Point"}
}