{
  "type": "Feature",
  "properties": {
    "iso:country":"US",
    "sg:address":"74 Riverwood Rd",
    "sg:city":"Swannanoa",
    "sg:classifiers":[
        {
            "category":"Education",
            "subcategory":"School",
            "type":"Public Place"
        }
    ],
    "sg:phone":"+1 828 581 2200",
    "sg:postcode":"28778",
    "sg:province":"NC",
    "sg:website":"www.acacademy.org",
    "wof:name":"Asheville Christian Academy",
    "wof:placetype":"venue"
},
  "geometry": {"coordinates":[-82.407916,35.603795],"type":"Point"}
}