{
  "type": "Feature",
  "properties": {
    "iso:country":"US",
    "sg:address":"1111 Beatties Ford Rd",
    "sg:city":"Charlotte",
    "sg:classifiers":[
        {
            "category":"Organizations",
            "subcategory":"Religious Organization",
            "type":"Services"
        }
    ],
    "sg:phone":"+1 704 331 0908",
    "sg:postcode":"28216",
    "sg:province":"NC",
    "sg:tags":[
        "mosque"
    ],
    "wof:name":"Musalla & Musalla",
    "wof:placetype":"venue"
},
  "geometry": {"coordinates":[-80.85612500000001,35.253441],"type":"Point"}
}