{
  "type": "Feature",
  "properties": {
    "iso:country":"US",
    "sg:address":"4400 Morris Park Dr",
    "sg:city":"Charlotte",
    "sg:classifiers":[
        {
            "category":"Real Estate",
            "subcategory":"Real Estate Agent",
            "type":"Services"
        }
    ],
    "sg:phone":"+1 704 573 3863",
    "sg:postcode":"28227",
    "sg:province":"NC",
    "sg:website":"www.jackbryan.com",
    "wof:name":"Performance Marketing Group",
    "wof:placetype":"venue"
},
  "geometry": {"coordinates":[-80.680626,35.152251],"type":"Point"}
}