{
  "type": "Feature",
  "properties": {
    "addr:full":"110 Brynn Marr Rd Jacksonville NC 28546",
    "addr:housenumber":"110",
    "addr:postcode":"28546",
    "addr:street":"Brynn Marr Rd",
    "iso:country":"US",
    "sg:address":"110 Brynn Marr Rd",
    "sg:city":"Jacksonville",
    "sg:classifiers":[
        {
            "category":"Wholesale",
            "subcategory":"Hardware",
            "type":"Manufacturing & Wholesale Goods"
        }
    ],
    "sg:phone":"+1 910 989 0800",
    "sg:postcode":"28546",
    "sg:province":"NC",
    "sg:tags":[
        "heater",
        "make",
        "air"
    ],
    "sg:website":"www.johnstonesupply.com",
    "wof:name":"Johnstone Supply",
    "wof:placetype":"venue"
},
  "geometry": {"coordinates":[-77.382706,34.748755],"type":"Point"}
}