{
  "type": "Feature",
  "properties": {
    "iso:country":"US",
    "sg:address":"15720 John J Delaney Dr",
    "sg:city":"Charlotte",
    "sg:classifiers":[
        {
            "category":"Professional",
            "type":"Services"
        }
    ],
    "sg:phone":"+1 704 944 3205",
    "sg:postcode":"28277",
    "sg:province":"NC",
    "sg:tags":[
        "establishment"
    ],
    "wof:name":"Boston Scientific",
    "wof:placetype":"venue"
},
  "geometry": {"coordinates":[-80.85111999999999,35.058378],"type":"Point"}
}