{
  "type": "Feature",
  "properties": {
    "iso:country":"US",
    "sg:address":"114 Court St",
    "sg:city":"Statesville",
    "sg:classifiers":[
        {
            "category":"Insurance",
            "subcategory":"Insurance Agent",
            "type":"Services"
        }
    ],
    "sg:phone":"+1 704 873 1824",
    "sg:postcode":"28677",
    "sg:province":"NC",
    "wof:name":"Myers Insurance",
    "wof:placetype":"venue"
},
  "geometry": {"coordinates":[-80.888141,35.783868],"type":"Point"}
}