{
  "type": "Feature",
  "properties": {
    "iso:country":"US",
    "sg:address":"3140 McDaniels St",
    "sg:city":"Newton",
    "sg:classifiers":[
        {
            "category":"Retail",
            "subcategory":"Auto Repair",
            "type":"Services"
        }
    ],
    "sg:phone":"+1 828 324 1967",
    "sg:postcode":"28658",
    "sg:province":"NC",
    "sg:tags":[
        "body",
        "automobile",
        "painting"
    ],
    "wof:name":"Renpro Auto Collision",
    "wof:placetype":"venue"
},
  "geometry": {"coordinates":[-81.294594,35.678286],"type":"Point"}
}