{
  "type": "Feature",
  "properties": {
    "addr:full":"508 Regency Park Dr Clayton NC 27520",
    "addr:housenumber":"508",
    "addr:postcode":"27520",
    "addr:street":"Regency Park Dr",
    "iso:country":"US",
    "sg:address":"508 Regency Park Dr",
    "sg:city":"Clayton",
    "sg:classifiers":[
        {
            "category":"Shopping",
            "subcategory":"Used Merchandise",
            "type":"Retail Goods"
        }
    ],
    "sg:phone":"+1 919 359 0492",
    "sg:postcode":"27520",
    "sg:province":"NC",
    "sg:tags":[
        "shop",
        "thrift"
    ],
    "sg:website":"www.goodwillenc.org",
    "wof:name":"Goodwill Industries",
    "wof:placetype":"venue"
},
  "geometry": {"coordinates":[-78.46069,35.644387],"type":"Point"}
}