{
  "type": "Feature",
  "properties": {
    "addr:full":"2911 Breezewood Ave Fayetteville NC 28303",
    "addr:housenumber":"2911",
    "addr:postcode":"28303",
    "addr:street":"Breezewood Ave",
    "iso:country":"US",
    "sg:address":"2911 Breezewood Ave",
    "sg:city":"Fayetteville",
    "sg:classifiers":[
        {
            "category":"Professional",
            "subcategory":"Employment Agencies",
            "type":"Services"
        }
    ],
    "sg:phone":"+1 910 484 2249",
    "sg:postcode":"28303",
    "sg:province":"NC",
    "sg:tags":[
        "opportunity"
    ],
    "wof:name":"Adecco",
    "wof:placetype":"venue"
},
  "geometry": {"coordinates":[-78.92841900000001,35.043792],"type":"Point"}
}