{
  "type": "Feature",
  "properties": {
    "iso:country":"US",
    "sg:address":"9520 State Hwy 88 W",
    "sg:city":"Warrensville",
    "sg:classifiers":[
        {
            "category":"Real Estate",
            "subcategory":"Real Estate Agent",
            "type":"Services"
        }
    ],
    "sg:phone":"+1 336 385 6112",
    "sg:postcode":"28693",
    "sg:province":"NC",
    "wof:name":"Cox Realty and Auction Co",
    "wof:placetype":"venue"
},
  "geometry": {"coordinates":[-81.573346,36.44925],"type":"Point"}
}