{
  "type": "Feature",
  "properties": {
    "iso:country":"US",
    "sg:address":"116 Cottage Grove Ln",
    "sg:city":"Mooresville",
    "sg:classifiers":[
        {
            "category":"Airport",
            "type":"Transportation"
        }
    ],
    "sg:phone":"+1 704 975 2012",
    "sg:postcode":"28117",
    "sg:province":"NC",
    "wof:name":"Wefas Inc",
    "wof:placetype":"venue"
},
  "geometry": {"coordinates":[-80.945168,35.511441],"type":"Point"}
}