{
  "type": "Feature",
  "properties": {
    "iso:country":"US",
    "sg:address":"4744 US Hwy 21",
    "sg:city":"Hamptonville",
    "sg:classifiers":[
        {
            "category":"Home & Garden",
            "subcategory":"Building Materials",
            "type":"Retail Goods"
        }
    ],
    "sg:phone":"+1 336 468 2757",
    "sg:postcode":"27020",
    "sg:province":"NC",
    "sg:tags":[
        "lumber"
    ],
    "wof:name":"Casstevens Lumber Company",
    "wof:placetype":"venue"
},
  "geometry": {"coordinates":[-80.759767,36.033903],"type":"Point"}
}