{
  "type": "Feature",
  "properties": {
    "iso:country":"US",
    "sg:address":"3439 Alamance Rd",
    "sg:city":"Burlington",
    "sg:classifiers":[
        {
            "category":"Wholesale",
            "subcategory":"Construction Materials",
            "type":"Manufacturing & Wholesale Goods"
        },
        {
            "category":"Freight",
            "type":"Transportation"
        }
    ],
    "sg:phone":"+1 336 263 5115",
    "sg:postcode":"27215",
    "sg:province":"NC",
    "sg:tags":[
        "trucking"
    ],
    "wof:name":"J V Blackwell & Sons Trucking",
    "wof:placetype":"venue"
},
  "geometry": {"coordinates":[-79.480369,36.04963],"type":"Point"}
}