{
  "type": "Feature",
  "properties": {
    "addr:full":"4139 US Hwy 311 Randleman NC 27317",
    "addr:housenumber":"4139",
    "addr:postcode":"27317",
    "addr:street":"Us Hwy 311",
    "iso:country":"US",
    "sg:address":"4139 US Hwy 311",
    "sg:city":"Randleman",
    "sg:classifiers":[
        {
            "category":"Manufacturing",
            "subcategory":"Paper Products",
            "type":"Manufacturing & Wholesale Goods"
        }
    ],
    "sg:phone":"+1 336 498 2631",
    "sg:postcode":"27317",
    "sg:province":"NC",
    "sg:tags":[
        "box"
    ],
    "wof:name":"Caraustar Custom Packaging",
    "wof:placetype":"venue"
},
  "geometry": {"coordinates":[-79.827392,35.804632],"type":"Point"}
}