{
  "type": "Feature",
  "properties": {
    "iso:country":"US",
    "sg:address":"410 Swannanoa River Rd",
    "sg:city":"Asheville",
    "sg:classifiers":[
        {
            "category":"Social Services",
            "type":"Services"
        }
    ],
    "sg:phone":"+1 828 299 7277",
    "sg:postcode":"28805",
    "sg:province":"NC",
    "sg:tags":[
        "youth",
        "organization",
        "center"
    ],
    "wof:name":"Abysa Youth Soccer",
    "wof:placetype":"venue"
},
  "geometry": {"coordinates":[-82.51877,35.578717],"type":"Point"}
}