{
  "type": "Feature",
  "properties": {
    "iso:country":"US",
    "sg:address":"1713 Nantuckett Ln Apt 201",
    "sg:city":"Charlotte",
    "sg:classifiers":[
        {
            "category":"Building & Trades",
            "subcategory":"Construction",
            "type":"Services"
        }
    ],
    "sg:phone":"+1 704 246 8175",
    "sg:postcode":"28270",
    "sg:province":"NC",
    "sg:tags":[
        "system",
        "contractor",
        "air conditioning"
    ],
    "wof:name":"Arce Heating And Ac",
    "wof:placetype":"venue"
},
  "geometry": {"coordinates":[-80.76672600000001,35.109952],"type":"Point"}
}