{
  "type": "Feature",
  "properties": {
    "iso:country":"US",
    "sg:address":"303 Honeywood Ct",
    "sg:city":"Apex",
    "sg:classifiers":[
        {
            "category":"Health Services",
            "subcategory":"Clinic",
            "type":"Services"
        }
    ],
    "sg:phone":"+1   ",
    "sg:postcode":"27518",
    "sg:province":"NC",
    "wof:name":"Durham Drug & Alcohol Services",
    "wof:placetype":"venue"
},
  "geometry": {"coordinates":[-78.791927,35.692462],"type":"Point"}
}