{
  "type": "Feature",
  "properties": {
    "iso:country":"US",
    "sg:address":"1043 Bragg Blvd",
    "sg:city":"Fayetteville",
    "sg:classifiers":[
        {
            "category":"Personal",
            "subcategory":"Beauty Salon",
            "type":"Services"
        }
    ],
    "sg:phone":"+1   ",
    "sg:postcode":"28301",
    "sg:province":"NC",
    "sg:tags":[
        "shop"
    ],
    "wof:name":"First Class Styling",
    "wof:placetype":"venue"
},
  "geometry": {"coordinates":[-78.89710700000001,35.065046],"type":"Point"}
}