{
  "type": "Feature",
  "properties": {
    "iso:country":"US",
    "sg:address":"2013 Marguerite Ave",
    "sg:city":"Charlotte",
    "sg:classifiers":[
        {
            "category":"Professional",
            "subcategory":"Computer Services",
            "type":"Services"
        }
    ],
    "sg:phone":"+1 704 335 9829",
    "sg:postcode":"28205",
    "sg:province":"NC",
    "sg:tags":[
        "website",
        "design"
    ],
    "wof:name":"Uttley Communications Inc",
    "wof:placetype":"venue"
},
  "geometry": {"coordinates":[-80.80193,35.232876],"type":"Point"}
}