{
  "type": "Feature",
  "properties": {
    "addr:full":"1504 Brightwater Ct Raleigh NC 27614",
    "addr:housenumber":"1504",
    "addr:postcode":"27614",
    "addr:street":"Brightwater Ct",
    "iso:country":"US",
    "sg:address":"1504 Brightwater Ct",
    "sg:city":"Raleigh",
    "sg:classifiers":[
        {
            "category":"Real Estate",
            "subcategory":"Developer",
            "type":"Services"
        }
    ],
    "sg:phone":"+1 919 676 7566",
    "sg:postcode":"27614",
    "sg:province":"NC",
    "wof:name":"Deli Developer",
    "wof:placetype":"venue"
},
  "geometry": {"coordinates":[-78.61279999999999,35.945963],"type":"Point"}
}