{
  "type": "Feature",
  "properties": {
    "iso:country":"US",
    "sg:address":"3611 University Dr",
    "sg:city":"Durham",
    "sg:classifiers":[
        {
            "category":"Professional",
            "subcategory":"Employment Agencies",
            "type":"Services"
        }
    ],
    "sg:phone":"+1   ",
    "sg:postcode":"27707",
    "sg:province":"NC",
    "sg:tags":[
        "help",
        "supply"
    ],
    "wof:name":"TAC Nation Wide Co",
    "wof:placetype":"venue"
},
  "geometry": {"coordinates":[-78.949257,35.967028],"type":"Point"}
}