{
  "type": "Feature",
  "properties": {
    "addr:full":"282 Bowen Ln Ayden NC 28513",
    "addr:housenumber":"282",
    "addr:postcode":"28513",
    "addr:street":"Bowen Ln",
    "iso:country":"US",
    "sg:address":"282 Bowen Ln",
    "sg:city":"Ayden",
    "sg:classifiers":[
        {
            "category":"Professional",
            "type":"Services"
        }
    ],
    "sg:phone":"+1 252 746 9355",
    "sg:postcode":"28513",
    "sg:province":"NC",
    "wof:name":"Richardson Central LLC",
    "wof:placetype":"venue"
},
  "geometry": {"coordinates":[-77.534069,35.495798],"type":"Point"}
}