{
  "type": "Feature",
  "properties": {
    "addr:full":"2514 University Dr Durham NC 27707",
    "addr:housenumber":"2514",
    "addr:postcode":"27707",
    "addr:street":"University Dr",
    "iso:country":"US",
    "sg:address":"2514 University Dr",
    "sg:city":"Durham",
    "sg:classifiers":[
        {
            "category":"Restaurant",
            "type":"Food & Drink"
        }
    ],
    "sg:phone":"+1 919 622 0023",
    "sg:postcode":"27707",
    "sg:province":"NC",
    "sg:tags":[
        "eating"
    ],
    "wof:name":"Durham Catering Company",
    "wof:placetype":"venue"
},
  "geometry": {"coordinates":[-78.924722,35.973994],"type":"Point"}
}