{
  "type": "Feature",
  "properties": {
    "iso:country":"US",
    "sg:address":"220 Ballard Creek Rd",
    "sg:city":"Fairview",
    "sg:classifiers":[
        {
            "category":"Wholesale",
            "subcategory":"Auto Parts",
            "type":"Manufacturing & Wholesale Goods"
        }
    ],
    "sg:phone":"+1 828 628 1123",
    "sg:postcode":"28730",
    "sg:province":"NC",
    "sg:tags":[
        "truck",
        "refrigeration",
        "equipment"
    ],
    "wof:name":"Ron's Refrigeration Svc",
    "wof:placetype":"venue"
},
  "geometry": {"coordinates":[-82.41907399999999,35.550616],"type":"Point"}
}