{
  "type": "Feature",
  "properties": {
    "addr:full":"220 New Leicester Hwy Asheville NC 28806",
    "addr:housenumber":"220",
    "addr:postcode":"28806",
    "addr:street":"New Leicester Hwy",
    "iso:country":"US",
    "sg:address":"220 New Leicester Hwy",
    "sg:city":"Asheville",
    "sg:classifiers":[
        {
            "category":"Manufacturing",
            "subcategory":"Metals",
            "type":"Manufacturing & Wholesale Goods"
        },
        {
            "category":"Home & Garden",
            "subcategory":"Building Materials",
            "type":"Retail Goods"
        },
        {
            "category":"Building & Trades",
            "subcategory":"Construction",
            "type":"Services"
        },
        {
            "category":"Manufacturing",
            "subcategory":"Building Materials",
            "type":"Manufacturing & Wholesale Goods"
        }
    ],
    "sg:phone":"+1 828 255 8870",
    "sg:postcode":"28806",
    "sg:province":"NC",
    "sg:tags":[
        "roofing",
        "sheet",
        "work",
        "contractor",
        "fabricator",
        "improvement"
    ],
    "sg:website":"http://www.stroupinc.com",
    "wof:name":"Stroup Sheet Metal Works Inc",
    "wof:placetype":"venue"
},
  "geometry": {"coordinates":[-82.615028,35.592709],"type":"Point"}
}