{
  "type": "Feature",
  "properties": {
    "addr:full":"8909 Jw Clay Blvd Charlotte NC 28262",
    "addr:postcode":"8909;28262",
    "addr:street":"Jw Clay Blvd",
    "iso:country":"US",
    "sg:address":"8909 Jw Clay Blvd",
    "sg:city":"Charlotte",
    "sg:phone":"+1 704 593 0227",
    "sg:postcode":"28262",
    "sg:province":"NC",
    "sg:website":"http://www.samsclub.com",
    "wof:name":"Sam's Club",
    "wof:placetype":"venue"
},
  "geometry": {"coordinates":[-80.752655,35.313281],"type":"Point"}
}