{
  "type": "Feature",
  "properties": {
    "addr:full":"150 Bluefield Rd Mooresville NC 28117",
    "addr:housenumber":"150",
    "addr:postcode":"28117",
    "addr:street":"Bluefield Rd",
    "iso:country":"US",
    "sg:address":"150 Bluefield Rd",
    "sg:city":"Mooresville",
    "sg:classifiers":[
        {
            "category":"Shopping",
            "subcategory":"Department Store",
            "type":"Retail Goods"
        },
        {
            "category":"Shopping",
            "subcategory":"Discount & Variety Stores",
            "type":"Retail Goods"
        }
    ],
    "sg:phone":"+1 704 799 3757",
    "sg:postcode":"28117",
    "sg:province":"NC",
    "sg:website":"http://www.tjx.com",
    "wof:name":"T.J. Maxx",
    "wof:placetype":"venue"
},
  "geometry": {"coordinates":[-80.860928,35.623794],"type":"Point"}
}