{
  "type": "Feature",
  "properties": {
    "iso:country":"US",
    "sg:address":"3437 Hillsborough Rd",
    "sg:city":"Durham",
    "sg:classifiers":[
        {
            "category":"Professional",
            "subcategory":"Computer Services",
            "type":"Services"
        }
    ],
    "sg:phone":"+1 919 309 2629",
    "sg:postcode":"27705",
    "sg:province":"NC",
    "sg:tags":[
        "repair"
    ],
    "wof:name":"Carolina Computer Ctr",
    "wof:placetype":"venue"
},
  "geometry": {"coordinates":[-78.944934,36.018632],"type":"Point"}
}