{
  "type": "Feature",
  "properties": {
    "iso:country":"US",
    "sg:address":"787 Marsh Rose Path NW",
    "sg:city":"Calabash",
    "sg:classifiers":[
        {
            "category":"Professional",
            "subcategory":"Management & Consulting",
            "type":"Services"
        }
    ],
    "sg:phone":"+1   ",
    "sg:postcode":"28467",
    "sg:province":"NC",
    "sg:tags":[
        "business"
    ],
    "wof:name":"Sn Consulting Company LLC",
    "wof:placetype":"venue"
},
  "geometry": {"coordinates":[-78.607879,33.928151],"type":"Point"}
}