{
  "type": "Feature",
  "properties": {
    "iso:country":"US",
    "sg:address":"9067 State Hwy 99 N",
    "sg:city":"Pantego",
    "sg:classifiers":[
        {
            "category":"Manufacturing",
            "subcategory":"Lumber",
            "type":"Manufacturing & Wholesale Goods"
        }
    ],
    "sg:phone":"+1 252 935 5571",
    "sg:postcode":"27860",
    "sg:province":"NC",
    "sg:tags":[
        "company",
        "logging"
    ],
    "wof:name":"G & S Logging",
    "wof:placetype":"venue"
},
  "geometry": {"coordinates":[-76.63027099999999,35.687071],"type":"Point"}
}