{
  "type": "Feature",
  "properties": {
    "iso:country":"US",
    "sg:address":"8101 Tifton Rd",
    "sg:city":"Charlotte",
    "sg:classifiers":[
        {
            "category":"Professional",
            "type":"Services"
        }
    ],
    "sg:phone":"+1 704 543 6715",
    "sg:postcode":"28226",
    "sg:province":"NC",
    "wof:name":"Larry D Good",
    "wof:placetype":"venue"
},
  "geometry": {"coordinates":[-80.85633,35.08298],"type":"Point"}
}