{
  "type": "Feature",
  "properties": {
    "iso:country":"US",
    "sg:address":"712 Mountain Rd",
    "sg:city":"Asheboro",
    "sg:classifiers":[
        {
            "category":"Real Estate",
            "subcategory":"Real Estate Operator",
            "type":"Services"
        }
    ],
    "sg:phone":"+1 336 672 1700",
    "sg:postcode":"27205",
    "sg:province":"NC",
    "sg:tags":[
        "building",
        "apartment"
    ],
    "wof:name":"Ranco Investors Inc",
    "wof:placetype":"venue"
},
  "geometry": {"coordinates":[-79.83200100000001,35.716444],"type":"Point"}
}