{
  "type": "Feature",
  "properties": {
    "addr:full":"5227 Millstream Rd Mc Leansville NC 27301",
    "addr:housenumber":"5227",
    "addr:postcode":"27301",
    "addr:street":"Millstream Rd",
    "iso:country":"US",
    "sg:address":"5227 Millstream Rd",
    "sg:city":"Mc Leansville",
    "sg:classifiers":[
        {
            "category":"Professional",
            "subcategory":"Computer Services",
            "type":"Services"
        }
    ],
    "sg:phone":"+1 252 443 2789",
    "sg:postcode":"27301",
    "sg:province":"NC",
    "wof:name":"Jim Jones Computer Svc",
    "wof:placetype":"venue"
},
  "geometry": {"coordinates":[-79.665209,36.045254],"type":"Point"}
}