{
  "type": "Feature",
  "properties": {
    "iso:country":"US",
    "sg:address":"2199 State Hwy 705",
    "sg:city":"Seagrove",
    "sg:classifiers":[
        {
            "category":"Home & Garden",
            "subcategory":"Home Furnishings",
            "type":"Retail Goods"
        }
    ],
    "sg:phone":"+1 910 464 2261",
    "sg:postcode":"27341",
    "sg:province":"NC",
    "sg:website":"www.benowenpottery.com",
    "wof:name":"Ben Owen Pottery",
    "wof:placetype":"venue"
},
  "geometry": {"coordinates":[-79.73846,35.517923],"type":"Point"}
}