{
  "type": "Feature",
  "properties": {
    "iso:country":"US",
    "sg:address":"927 Hamilton St",
    "sg:city":"Roanoke Rapids",
    "sg:classifiers":[
        {
            "category":"Professional",
            "subcategory":"Business Services",
            "type":"Services"
        },
        {
            "category":"Health Services",
            "subcategory":"Clinic",
            "type":"Services"
        }
    ],
    "sg:phone":"+1 252 519 0811",
    "sg:postcode":"27870",
    "sg:province":"NC",
    "sg:tags":[
        "home"
    ],
    "wof:name":"Home Life Care Inc",
    "wof:placetype":"venue"
},
  "geometry": {"coordinates":[-77.65539699999999,36.456963],"type":"Point"}
}