{
  "type": "Feature",
  "properties": {
    "iso:country":"US",
    "sg:address":"5650 Lakeside Dr",
    "sg:city":"Pfafftown",
    "sg:classifiers":[
        {
            "category":"Shopping",
            "subcategory":"Computers & Home Electronics",
            "type":"Retail Goods"
        }
    ],
    "sg:phone":"+1 336 922 2025",
    "sg:postcode":"27040",
    "sg:province":"NC",
    "sg:tags":[
        "software"
    ],
    "wof:name":"Dogwood Micro Design",
    "wof:placetype":"venue"
},
  "geometry": {"coordinates":[-80.343159,36.189822],"type":"Point"}
}