{
  "type": "Feature",
  "properties": {
    "iso:country":"US",
    "sg:address":"639 Greens Cross Rd",
    "sg:city":"Windsor",
    "sg:phone":"+1 252 794 3501",
    "sg:postcode":"27983",
    "sg:province":"NC",
    "sg:tags":[
        "farm",
        "field",
        "crop",
        "cotton"
    ],
    "wof:name":"Stanley Thompson Farms",
    "wof:placetype":"venue"
},
  "geometry": {"coordinates":[-76.92079699999999,36.015727],"type":"Point"}
}