{
  "type": "Feature",
  "properties": {
    "addr:full":"4020 Capital Blvd Raleigh NC 27604",
    "addr:postcode":"4020;27604",
    "addr:street":"Capital Blvd",
    "iso:country":"US",
    "sg:address":"4020 Capital Blvd",
    "sg:city":"Raleigh",
    "sg:classifiers":[
        {
            "category":"Restaurant",
            "type":"Food & Drink"
        }
    ],
    "sg:phone":"+1 919 790 2230",
    "sg:postcode":"27604",
    "sg:province":"NC",
    "sg:tags":[
        "eating"
    ],
    "wof:name":"Little Caesars",
    "wof:placetype":"venue"
},
  "geometry": {"coordinates":[-78.58081300000001,35.837852],"type":"Point"}
}