{
  "type": "Feature",
  "properties": {
    "iso:country":"US",
    "sg:address":"3643 Roxboro Rd",
    "sg:city":"Durham",
    "sg:classifiers":[
        {
            "category":"Health Services",
            "subcategory":"Hospital",
            "type":"Services"
        }
    ],
    "sg:phone":"+1 919 470 5345",
    "sg:postcode":"27704",
    "sg:province":"NC",
    "wof:name":"Durham Emergency Room",
    "wof:placetype":"venue"
},
  "geometry": {"coordinates":[-78.897677,36.037775],"type":"Point"}
}