{
  "type": "Feature",
  "properties": {
    "addr:full":"150 Government Cir Jefferson NC 28640",
    "addr:housenumber":"150",
    "addr:postcode":"28640",
    "addr:street":"Government Cir",
    "iso:country":"US",
    "sg:address":"150 Government Cir",
    "sg:city":"Jefferson",
    "sg:classifiers":[
        {
            "category":"Government",
            "subcategory":"Office",
            "type":"Public Place"
        }
    ],
    "sg:phone":"+1 336 219 2570",
    "sg:postcode":"28640",
    "sg:province":"NC",
    "wof:name":"Ashe County Board Of Elections",
    "wof:placetype":"venue"
},
  "geometry": {"coordinates":[-81.459211,36.419802],"type":"Point"}
}