{
  "type": "Feature",
  "properties": {
    "iso:country":"US",
    "sg:address":"6621 State Hwy 89 W",
    "sg:city":"Westfield",
    "sg:phone":"+1 336 351 4142",
    "sg:postcode":"27053",
    "sg:province":"NC",
    "sg:tags":[
        "farm",
        "tobacco"
    ],
    "wof:name":"Stephen Jessup Farm",
    "wof:placetype":"venue"
},
  "geometry": {"coordinates":[-80.33229300000001,36.506601],"type":"Point"}
}