{
  "type": "Feature",
  "properties": {
    "addr:full":"2169 Cheatham Ford Rd Hiddenite NC 28636",
    "addr:housenumber":"2169",
    "addr:postcode":"28636",
    "addr:street":"Cheatham Ford Rd",
    "iso:country":"US",
    "sg:address":"2169 Cheatham Ford Rd",
    "sg:city":"Hiddenite",
    "sg:classifiers":[
        {
            "category":"Food & Beverages",
            "subcategory":"Specialty",
            "type":"Retail Goods"
        }
    ],
    "sg:phone":"+1 828 632 7754",
    "sg:postcode":"28636",
    "sg:province":"NC",
    "wof:name":"Woodwards Farm",
    "wof:placetype":"venue"
},
  "geometry": {"coordinates":[-81.052043,35.907991],"type":"Point"}
}