{
  "type": "Feature",
  "properties": {
    "iso:country":"US",
    "sg:address":"112 Conway Dr",
    "sg:city":"Durham",
    "sg:classifiers":[
        {
            "category":"Building & Trades",
            "subcategory":"Cleaning & Sanitation",
            "type":"Services"
        }
    ],
    "sg:phone":"+1   ",
    "sg:postcode":"27713",
    "sg:province":"NC",
    "sg:tags":[
        "maintenance"
    ],
    "wof:name":"Cornigan Cleaning Service",
    "wof:placetype":"venue"
},
  "geometry": {"coordinates":[-78.885256,35.939852],"type":"Point"}
}