{
  "type": "Feature",
  "properties": {
    "iso:country":"US",
    "sg:address":"100 Red Iron Rd",
    "sg:city":"Rocky Mount",
    "sg:classifiers":[
        {
            "category":"Building & Trades",
            "subcategory":"Construction",
            "type":"Services"
        }
    ],
    "sg:phone":"+1 252 977 2131",
    "sg:postcode":"27804",
    "sg:province":"NC",
    "wof:name":"Ceco Building Systems",
    "wof:placetype":"venue"
},
  "geometry": {"coordinates":[-77.761966,36.025373],"type":"Point"}
}