{
  "type": "Feature",
  "properties": {
    "iso:country":"US",
    "sg:address":"183 Woodrow McCoy Rd",
    "sg:city":"Cove City",
    "sg:classifiers":[
        {
            "category":"Recreation",
            "type":"Entertainment"
        }
    ],
    "sg:phone":"+1 252 514 9494",
    "sg:postcode":"28523",
    "sg:province":"NC",
    "sg:tags":[
        "attraction",
        "tourist"
    ],
    "wof:name":"A Day At The Farm",
    "wof:placetype":"venue"
},
  "geometry": {"coordinates":[-77.31853700000001,35.168253],"type":"Point"}
}