{
  "type": "Feature",
  "properties": {
    "addr:full":"302 Easy St La Grange NC 28551",
    "addr:housenumber":"302",
    "addr:postcode":"28551",
    "addr:street":"Easy St",
    "iso:country":"US",
    "sg:address":"302 Easy St",
    "sg:city":"La Grange",
    "sg:classifiers":[
        {
            "category":"Shopping",
            "subcategory":"Gifts & Souvenirs",
            "type":"Retail Goods"
        }
    ],
    "sg:phone":"+1 252 566 4302",
    "sg:postcode":"28551",
    "sg:province":"NC",
    "sg:tags":[
        "persona"
    ],
    "wof:name":"Janes Gifts & Things",
    "wof:placetype":"venue"
},
  "geometry": {"coordinates":[-77.802684,35.316939],"type":"Point"}
}