{
  "type": "Feature",
  "properties": {
    "addr:full":"1800 E 10th St Roanoke Rapids NC 27870",
    "addr:housenumber":"1800",
    "addr:postcode":"27870",
    "addr:street":"E 10Th St",
    "iso:country":"US",
    "sg:address":"1800 E 10th St",
    "sg:city":"Roanoke Rapids",
    "sg:classifiers":[
        {
            "category":"Autos & Motor Vehicles",
            "subcategory":"Fuel & Gas Station",
            "type":"Retail Goods"
        }
    ],
    "sg:phone":"+1 252 537 0034",
    "sg:postcode":"27870",
    "sg:province":"NC",
    "sg:tags":[
        "station",
        "beverage",
        "gasoline",
        "alcoholic"
    ],
    "wof:name":"Oakland Mini Mart",
    "wof:placetype":"venue"
},
  "geometry": {"coordinates":[-77.644227,36.437757],"type":"Point"}
}