{
  "type": "Feature",
  "properties": {
    "addr:full":"171 Great Oak Dr Canton NC 28716",
    "addr:housenumber":"171",
    "addr:postcode":"28716",
    "addr:street":"Great Oak Dr",
    "iso:country":"US",
    "sg:address":"171 Great Oak Dr",
    "sg:city":"Canton",
    "sg:classifiers":[
        {
            "category":"Manufacturing",
            "subcategory":"Metals",
            "type":"Manufacturing & Wholesale Goods"
        }
    ],
    "sg:phone":"+1 828 648 7027",
    "sg:postcode":"28716",
    "sg:province":"NC",
    "sg:tags":[
        "steel",
        "foundry"
    ],
    "wof:name":"Consolidated Metco",
    "wof:placetype":"venue"
},
  "geometry": {"coordinates":[-82.839429,35.567362],"type":"Point"}
}