{
  "type": "Feature",
  "properties": {
    "iso:country":"US",
    "sg:address":"2079 Orchard Rd",
    "sg:city":"Dana",
    "sg:classifiers":[
        {
            "category":"Wholesale",
            "subcategory":"Scrap",
            "type":"Manufacturing & Wholesale Goods"
        }
    ],
    "sg:phone":"+1 828 685 8831",
    "sg:postcode":"28731",
    "sg:province":"NC",
    "sg:tags":[
        "metal",
        "iron"
    ],
    "wof:name":"Charlie's Used Parts & Scrap",
    "wof:placetype":"venue"
},
  "geometry": {"coordinates":[-82.377937,35.325215],"type":"Point"}
}