{
  "type": "Feature",
  "properties": {
    "iso:country":"US",
    "sg:address":"2318 Mason St",
    "sg:city":"Shelby",
    "sg:classifiers":[
        {
            "category":"Retail",
            "subcategory":"Auto Repair",
            "type":"Services"
        }
    ],
    "sg:phone":"+1 704 482 5698",
    "sg:postcode":"28150",
    "sg:province":"NC",
    "sg:tags":[
        "body",
        "automobile",
        "painting"
    ],
    "wof:name":"Homer Harper Body Shop",
    "wof:placetype":"venue"
},
  "geometry": {"coordinates":[-81.473055,35.293002],"type":"Point"}
}