{
  "type": "Feature",
  "properties": {
    "addr:full":"1033 Wade Ave Ste 208 Raleigh NC 27605",
    "addr:housenumber":"1033",
    "addr:postcode":"27605",
    "addr:street":"Wade Ave Ste 208",
    "iso:country":"US",
    "sg:address":"1033 Wade Ave Ste 208",
    "sg:city":"Raleigh",
    "sg:classifiers":[
        {
            "category":"Personal",
            "subcategory":"Massage",
            "type":"Services"
        },
        {
            "category":"Health Services",
            "subcategory":"Hospital",
            "type":"Services"
        },
        {
            "category":"Health Services",
            "subcategory":"Clinic",
            "type":"Services"
        },
        {
            "category":"Health Services",
            "subcategory":"Health Practitioner",
            "type":"Services"
        },
        {
            "category":"Arena",
            "subcategory":"Sports Club",
            "type":"Entertainment"
        }
    ],
    "sg:phone":"+1 919 828 4525",
    "sg:postcode":"27605",
    "sg:province":"NC",
    "sg:tags":[
        "therapist",
        "therapy",
        "treatment",
        "sleep",
        "disorders-information",
        "physical"
    ],
    "sg:website":"http://www.bodybalancetherapy.com",
    "wof:name":"Body Balance Movement Therapy Inc",
    "wof:placetype":"venue"
},
  "geometry": {"coordinates":[-78.658446,35.799208],"type":"Point"}
}