{
  "type": "Feature",
  "properties": {
    "addr:full":"1218 Beatties Ford Rd Charlotte NC 28216",
    "addr:housenumber":"1218",
    "addr:postcode":"28216",
    "addr:street":"Beatties Ford Rd",
    "iso:country":"US",
    "sg:address":"1218 Beatties Ford Rd",
    "sg:city":"Charlotte",
    "sg:phone":"+1 704 532 7400",
    "sg:postcode":"28216",
    "sg:province":"NC",
    "wof:name":"She's International",
    "wof:placetype":"venue"
},
  "geometry": {"coordinates":[-80.85596,35.254157],"type":"Point"}
}