{
  "type": "Feature",
  "properties": {
    "addr:full":"3512 Trent Rd Havelock NC 28562",
    "addr:housenumber":"3512",
    "addr:postcode":"28562",
    "addr:street":"Trent Rd",
    "iso:country":"US",
    "sg:address":"3512 Trent Rd",
    "sg:city":"Havelock",
    "sg:classifiers":[
        {
            "category":"Wholesale",
            "subcategory":"Hardware",
            "type":"Manufacturing & Wholesale Goods"
        }
    ],
    "sg:phone":"+1 252 447 6121",
    "sg:postcode":"28562",
    "sg:province":"NC",
    "sg:tags":[
        "plumbing",
        "heating",
        "supply"
    ],
    "wof:name":"Ferguson 167",
    "wof:placetype":"venue"
},
  "geometry": {"coordinates":[-77.095322,35.093205],"type":"Point"}
}