{
  "type": "Feature",
  "properties": {
    "addr:full":"2119 W Main St Albemarle NC 28001",
    "addr:housenumber":"2119",
    "addr:postcode":"28001",
    "addr:street":"W Main St",
    "iso:country":"US",
    "sg:address":"2119 W Main St",
    "sg:city":"Albemarle",
    "sg:classifiers":[
        {
            "category":"Autos & Motor Vehicles",
            "subcategory":"Auto Supplies",
            "type":"Retail Goods"
        }
    ],
    "sg:phone":"+1 704 982 3724",
    "sg:postcode":"28001",
    "sg:province":"NC",
    "wof:name":"Jspeed",
    "wof:placetype":"venue"
},
  "geometry": {"coordinates":[-80.220811,35.34022],"type":"Point"}
}