{
  "type": "Feature",
  "properties": {
    "iso:country":"US",
    "sg:address":"1313 Military Cutoff Rd",
    "sg:city":"Wilmington",
    "sg:classifiers":[
        {
            "category":"Professional",
            "subcategory":"Lawyer & Legal Services",
            "type":"Services"
        }
    ],
    "sg:phone":"+1 910 256 0221",
    "sg:postcode":"28405",
    "sg:province":"NC",
    "wof:name":"Wachovia",
    "wof:placetype":"venue"
},
  "geometry": {"coordinates":[-77.82933800000001,34.230167],"type":"Point"}
}