{
  "type": "Feature",
  "properties": {
    "iso:country":"US",
    "sg:address":"127 Highlands Rd",
    "sg:city":"Franklin",
    "sg:classifiers":[
        {
            "category":"Food & Beverages",
            "subcategory":"Groceries & Convenience Stores",
            "type":"Retail Goods"
        }
    ],
    "sg:phone":"+1 828 369 5656",
    "sg:postcode":"28734",
    "sg:province":"NC",
    "wof:name":"Olveras Mexican Store",
    "wof:placetype":"venue"
},
  "geometry": {"coordinates":[-83.370243,35.186037],"type":"Point"}
}