{
  "type": "Feature",
  "properties": {
    "iso:country":"US",
    "sg:address":"1206 Ascot Ct",
    "sg:city":"High Point",
    "sg:classifiers":[
        {
            "category":"Wholesale",
            "subcategory":"Hardware",
            "type":"Manufacturing & Wholesale Goods"
        }
    ],
    "sg:phone":"+1 336 882 7756",
    "sg:postcode":"27262",
    "sg:province":"NC",
    "wof:name":"Bosch Hardware Supply Corp",
    "wof:placetype":"venue"
},
  "geometry": {"coordinates":[-80.04141,35.97688],"type":"Point"}
}