{
  "type": "Feature",
  "properties": {
    "addr:full":"203 Julia Ct Jacksonville NC 28540",
    "addr:housenumber":"203",
    "addr:postcode":"28540",
    "addr:street":"Julia Ct",
    "iso:country":"US",
    "sg:address":"203 Julia Ct",
    "sg:city":"Jacksonville",
    "sg:classifiers":[
        {
            "category":"Professional",
            "subcategory":"Computer Services",
            "type":"Services"
        }
    ],
    "sg:phone":"+1   ",
    "sg:postcode":"28540",
    "sg:province":"NC",
    "sg:tags":[
        "related"
    ],
    "wof:name":"Stevi Enterprises",
    "wof:placetype":"venue"
},
  "geometry": {"coordinates":[-77.419918,34.774155],"type":"Point"}
}