{
  "type": "Feature",
  "properties": {
    "iso:country":"US",
    "sg:address":"5986 Old Pineville Rd",
    "sg:city":"Charlotte",
    "sg:classifiers":[
        {
            "category":"Professional",
            "subcategory":"Business Services",
            "type":"Services"
        }
    ],
    "sg:phone":"+1 704 556 7609",
    "sg:postcode":"28217",
    "sg:province":"NC",
    "wof:name":"Professional Auto Recovery",
    "wof:placetype":"venue"
},
  "geometry": {"coordinates":[-80.877781,35.158749],"type":"Point"}
}