{
  "type": "Feature",
  "properties": {
    "iso:country":"US",
    "sg:address":"1244 Campground Rd",
    "sg:city":"Elizabeth City",
    "sg:classifiers":[
        {
            "category":"Food & Beverages",
            "subcategory":"Groceries & Convenience Stores",
            "type":"Retail Goods"
        }
    ],
    "sg:phone":"+1 252 771 5688",
    "sg:postcode":"27909",
    "sg:province":"NC",
    "sg:tags":[
        "grocer"
    ],
    "wof:name":"Eastern Organics LTD",
    "wof:placetype":"venue"
},
  "geometry": {"coordinates":[-76.426469,36.401518],"type":"Point"}
}