{
  "type": "Feature",
  "properties": {
    "addr:full":"2076 Highlands Rd Franklin NC 28734",
    "addr:housenumber":"2076",
    "addr:postcode":"nc 28734",
    "addr:street":"Highlands Rd",
    "iso:country":"US",
    "sg:address":"2076 Highlands Rd",
    "sg:city":"Franklin",
    "sg:classifiers":[
        {
            "category":"Utilities",
            "subcategory":"Refuse",
            "type":"Services"
        }
    ],
    "sg:phone":"+1 828 369 2727",
    "sg:postcode":"28734",
    "sg:province":"NC",
    "wof:name":"J & B Disposal Inc",
    "wof:placetype":"venue"
},
  "geometry": {"coordinates":[-83.354553,35.176039],"type":"Point"}
}