{
  "type": "Feature",
  "properties": {
    "addr:full":"26661 US Hwy 264 E Pantego NC 27860",
    "addr:postcode":"26661;27860",
    "addr:street":"Us Hwy 264 E",
    "iso:country":"US",
    "sg:address":"26661 US Hwy 264 E",
    "sg:city":"Pantego",
    "sg:classifiers":[
        {
            "category":"Building & Trades",
            "subcategory":"Plumbing",
            "type":"Services"
        }
    ],
    "sg:phone":"+1 252 943 3696",
    "sg:postcode":"27860",
    "sg:province":"NC",
    "sg:tags":[
        "conditioning",
        "air",
        "system",
        "contractor"
    ],
    "wof:name":"Mike Polovitch Air Cond & Htg",
    "wof:placetype":"venue"
},
  "geometry": {"coordinates":[-76.646411,35.58032],"type":"Point"}
}