{
  "type": "Feature",
  "properties": {
    "addr:full":"204 Roxie Ln Belmont NC 28012",
    "addr:housenumber":"204",
    "addr:postcode":"28012",
    "addr:street":"Roxie Ln",
    "iso:country":"US",
    "sg:address":"204 Roxie Ln",
    "sg:city":"Belmont",
    "sg:classifiers":[
        {
            "category":"Shopping",
            "subcategory":"Computers & Home Electronics",
            "type":"Retail Goods"
        }
    ],
    "sg:phone":"+1 704 426 7053",
    "sg:postcode":"28012",
    "sg:province":"NC",
    "sg:tags":[
        "television",
        "radio",
        "store"
    ],
    "wof:name":"Wired On Demand",
    "wof:placetype":"venue"
},
  "geometry": {"coordinates":[-81.063025,35.193624],"type":"Point"}
}