{
  "type": "Feature",
  "properties": {
    "iso:country":"US",
    "sg:address":"5044 Yadkin Rd",
    "sg:city":"Fayetteville",
    "sg:classifiers":[
        {
            "category":"Restaurant",
            "type":"Food & Drink"
        }
    ],
    "sg:phone":"+1 910 867 8879",
    "sg:postcode":"28303",
    "sg:province":"NC",
    "sg:tags":[
        "shop",
        "coffee"
    ],
    "wof:name":"Jerr's",
    "wof:placetype":"venue"
},
  "geometry": {"coordinates":[-78.972965,35.084105],"type":"Point"}
}