{
  "type": "Feature",
  "properties": {
    "iso:country":"US",
    "sg:address":"300 N Salisbury St",
    "sg:city":"Raleigh",
    "sg:classifiers":[
        {
            "category":"Government",
            "subcategory":"Office",
            "type":"Public Place"
        }
    ],
    "sg:phone":"+1 919 733 3924",
    "sg:postcode":"27603",
    "sg:province":"NC",
    "sg:tags":[
        "state",
        "inspection"
    ],
    "wof:name":"Securities Division",
    "wof:placetype":"venue"
},
  "geometry": {"coordinates":[-78.639802,35.785894],"type":"Point"}
}