{
  "type": "Feature",
  "properties": {
    "addr:full":"1807 Oglesby Rd Morehead City NC 28557",
    "addr:housenumber":"1807",
    "addr:postcode":"28557",
    "addr:street":"Oglesby Rd",
    "iso:country":"US",
    "sg:address":"1807 Oglesby Rd",
    "sg:city":"Morehead City",
    "sg:classifiers":[
        {
            "category":"Professional",
            "type":"Services"
        }
    ],
    "sg:phone":"+1 252 726 8060",
    "sg:postcode":"28557",
    "sg:province":"NC",
    "wof:name":"Jack A Roberts",
    "wof:placetype":"venue"
},
  "geometry": {"coordinates":[-76.727953,34.733014],"type":"Point"}
}