{
  "type": "Feature",
  "properties": {
    "addr:full":"18 Northwood Rd Asheville NC 28804",
    "addr:housenumber":"18",
    "addr:postcode":"28804",
    "addr:street":"Northwood Rd",
    "iso:country":"US",
    "sg:address":"18 Northwood Rd",
    "sg:city":"Asheville",
    "sg:classifiers":[
        {
            "category":"Professional",
            "subcategory":"Management & Consulting",
            "type":"Services"
        }
    ],
    "sg:phone":"+1   ",
    "sg:postcode":"28804",
    "sg:province":"NC",
    "wof:name":"Thordec Inc",
    "wof:placetype":"venue"
},
  "geometry": {"coordinates":[-82.542512,35.626324],"type":"Point"}
}