{
  "type": "Feature",
  "properties": {
    "addr:full":"526 N Greenbriar Rd Statesville NC 28625",
    "addr:housenumber":"526",
    "addr:postcode":"28625",
    "addr:street":"N Greenbriar Rd",
    "iso:country":"US",
    "sg:address":"526 N Greenbriar Rd",
    "sg:city":"Statesville",
    "sg:classifiers":[
        {
            "category":"Freight",
            "type":"Transportation"
        }
    ],
    "sg:phone":"+1 704 872 9054",
    "sg:postcode":"28625",
    "sg:province":"NC",
    "sg:tags":[
        "forwarder"
    ],
    "wof:name":"Apparell Connection",
    "wof:placetype":"venue"
},
  "geometry": {"coordinates":[-80.827613,35.809134],"type":"Point"}
}