{
  "type": "Feature",
  "properties": {
    "iso:country":"US",
    "sg:address":"4740 Dwight Evans Rd",
    "sg:city":"Charlotte",
    "sg:classifiers":[
        {
            "category":"Freight",
            "type":"Transportation"
        }
    ],
    "sg:phone":"+1 704 525 6116",
    "sg:postcode":"28217",
    "sg:province":"NC",
    "sg:tags":[
        "courier"
    ],
    "wof:name":"Sonicair Couriers",
    "wof:placetype":"venue"
},
  "geometry": {"coordinates":[-80.89895799999999,35.190078],"type":"Point"}
}