{
  "type": "Feature",
  "properties": {
    "iso:country":"US",
    "sg:address":"125 S Church St",
    "sg:city":"Hendersonville",
    "sg:classifiers":[
        {
            "category":"Retail",
            "subcategory":"Funeral Services",
            "type":"Services"
        }
    ],
    "sg:phone":"+1 828 693 3435",
    "sg:postcode":"28792",
    "sg:province":"NC",
    "sg:tags":[
        "director"
    ],
    "sg:website":"www.thosshepherd.com",
    "wof:name":"Thomas Shepherd & Sons Funeral",
    "wof:placetype":"venue"
},
  "geometry": {"coordinates":[-82.460965,35.313896],"type":"Point"}
}