{
  "type": "Feature",
  "properties": {
    "addr:full":"151 W Rosemary St Chapel Hill NC 27516",
    "addr:housenumber":"151",
    "addr:postcode":"27516",
    "addr:street":"W Rosemary St",
    "iso:country":"US",
    "sg:address":"151 W Rosemary St",
    "sg:city":"Chapel Hill",
    "sg:classifiers":[
        {
            "category":"Travel",
            "subcategory":"Travel Agent",
            "type":"Entertainment"
        }
    ],
    "sg:phone":"+1 919 932 4605",
    "sg:postcode":"27516",
    "sg:province":"NC",
    "sg:tags":[
        "agency"
    ],
    "wof:name":"Arts Europe",
    "wof:placetype":"venue"
},
  "geometry": {"coordinates":[-79.056709,35.914069],"type":"Point"}
}