{
  "type": "Feature",
  "properties": {
    "iso:country":"US",
    "sg:address":"360 Faison Hwy",
    "sg:city":"Clinton",
    "sg:classifiers":[
        {
            "category":"Home & Garden",
            "subcategory":"Household Appliances",
            "type":"Retail Goods"
        }
    ],
    "sg:phone":"+1 910 592 8071",
    "sg:postcode":"28328",
    "sg:province":"NC",
    "sg:tags":[
        "machine",
        "sewing"
    ],
    "wof:name":"Anne's Sew N Vac",
    "wof:placetype":"venue"
},
  "geometry": {"coordinates":[-78.30570899999999,35.008201],"type":"Point"}
}