{
  "type": "Feature",
  "properties": {
    "iso:country":"US",
    "sg:address":"175 Alvin Hough Rd",
    "sg:city":"Midland",
    "sg:classifiers":[
        {
            "category":"Building & Trades",
            "subcategory":"Construction",
            "type":"Services"
        }
    ],
    "sg:phone":"+1 704 888 5654",
    "sg:postcode":"28107",
    "sg:province":"NC",
    "sg:tags":[
        "contractor"
    ],
    "wof:name":"C N Furr Masonry Co",
    "wof:placetype":"venue"
},
  "geometry": {"coordinates":[-80.57499199999999,35.225964],"type":"Point"}
}