{
  "type": "Feature",
  "properties": {
    "addr:full":"1217 Julian R Allsbrook Hwy Roanoke Rapids NC 27870",
    "addr:housenumber":"1217",
    "addr:postcode":"27870",
    "addr:street":"Julian R Allsbrook Hwy",
    "iso:country":"US",
    "sg:address":"1217 Julian R Allsbrook Hwy",
    "sg:city":"Roanoke Rapids",
    "sg:classifiers":[
        {
            "category":"Shopping",
            "type":"Retail Goods"
        },
        {
            "category":"Shopping",
            "subcategory":"Clothing, Apparel, & Fashions",
            "type":"Retail Goods"
        }
    ],
    "sg:phone":"+1 252 535 1374",
    "sg:postcode":"27870",
    "sg:province":"NC",
    "sg:tags":[
        "merchandise"
    ],
    "wof:name":"Max Ways Stores",
    "wof:placetype":"venue"
},
  "geometry": {"coordinates":[-77.641593,36.434904],"type":"Point"}
}