{
  "type": "Feature",
  "properties": {
    "iso:country":"US",
    "sg:address":"910 Tarboro St W",
    "sg:city":"Wilson",
    "sg:classifiers":[
        {
            "category":"Organizations",
            "subcategory":"Religious Organization",
            "type":"Services"
        }
    ],
    "sg:phone":"+1   ",
    "sg:postcode":"27893",
    "sg:province":"NC",
    "sg:website":"www.tbconline.org",
    "wof:name":"Tabernacle Baptist Church",
    "wof:placetype":"venue"
},
  "geometry": {"coordinates":[-77.92919500000001,35.721721],"type":"Point"}
}