{
  "type": "Feature",
  "properties": {
    "iso:country":"US",
    "sg:address":"1419 Pebble Dr",
    "sg:city":"Graham",
    "sg:classifiers":[
        {
            "category":"Professional",
            "type":"Services"
        }
    ],
    "sg:phone":"+1 336 578 0087",
    "sg:postcode":"27253",
    "sg:province":"NC",
    "wof:name":"Greg Staton",
    "wof:placetype":"venue"
},
  "geometry": {"coordinates":[-79.354861,36.030196],"type":"Point"}
}