{
  "type": "Feature",
  "properties": {
    "iso:country":"US",
    "sg:address":"5348 Vickrey Chapel Rd",
    "sg:city":"Greensboro",
    "sg:classifiers":[
        {
            "category":"Organizations",
            "subcategory":"Religious Organization",
            "type":"Services"
        }
    ],
    "sg:phone":"+1   ",
    "sg:postcode":"27407",
    "sg:province":"NC",
    "wof:name":"Vickery United Methdst Church",
    "wof:placetype":"venue"
},
  "geometry": {"coordinates":[-79.89804100000001,35.966527],"type":"Point"}
}