{
  "type": "Feature",
  "properties": {
    "iso:country":"US",
    "sg:address":"315 W High Ave",
    "sg:city":"High Point",
    "sg:classifiers":[
        {
            "category":"Banks & Credit Unions",
            "subcategory":"Bank",
            "type":"Services"
        }
    ],
    "sg:phone":"+1 336 882 3926",
    "sg:postcode":"27260",
    "sg:province":"NC",
    "wof:name":"Triad Postal Credit Union",
    "wof:placetype":"venue"
},
  "geometry": {"coordinates":[-80.008927,35.955677],"type":"Point"}
}