{
  "type": "Feature",
  "properties": {
    "addr:full":"2109 Durham St Exd Burlington NC 27217",
    "addr:housenumber":"2109",
    "addr:postcode":"27217",
    "addr:street":"Durham St Exd",
    "iso:country":"US",
    "sg:address":"2109 Durham St Exd",
    "sg:city":"Burlington",
    "sg:classifiers":[
        {
            "category":"Food & Beverages",
            "subcategory":"Groceries & Convenience Stores",
            "type":"Retail Goods"
        }
    ],
    "sg:phone":"+1 336 570 0877",
    "sg:postcode":"27217",
    "sg:province":"NC",
    "sg:tags":[
        "grocer"
    ],
    "wof:name":"Eagle Food Mart",
    "wof:placetype":"venue"
},
  "geometry": {"coordinates":[-79.464551,36.119867],"type":"Point"}
}