{
  "type": "Feature",
  "properties": {
    "iso:country":"US",
    "sg:address":"6015 Fayetteville Rd",
    "sg:city":"Durham",
    "sg:classifiers":[
        {
            "category":"Organizations",
            "subcategory":"Religious Organization",
            "type":"Services"
        }
    ],
    "sg:phone":"+1 919 484 8473",
    "sg:postcode":"27713",
    "sg:province":"NC",
    "sg:tags":[
        "church"
    ],
    "wof:name":"World Overcomers Christian Chr",
    "wof:placetype":"venue"
},
  "geometry": {"coordinates":[-78.932243,35.915336],"type":"Point"}
}