{
  "type": "Feature",
  "properties": {
    "addr:full":"5810 Yadkin Rd Fayetteville NC 28303",
    "addr:housenumber":"5810",
    "addr:postcode":"28303",
    "addr:street":"Yadkin Rd",
    "iso:country":"US",
    "sg:address":"5810 Yadkin Rd",
    "sg:city":"Fayetteville",
    "sg:classifiers":[
        {
            "category":"Wholesale",
            "subcategory":"Sporting Goods",
            "type":"Manufacturing & Wholesale Goods"
        },
        {
            "category":"Recreation",
            "type":"Entertainment"
        }
    ],
    "sg:phone":"+1 910 860 4469",
    "sg:postcode":"28303",
    "sg:province":"NC",
    "sg:tags":[
        "paint",
        "ball",
        "sport"
    ],
    "sg:website":"www.forceofnature.com",
    "wof:name":"Freedom Paintball U S A",
    "wof:placetype":"venue"
},
  "geometry": {"coordinates":[-78.986091,35.093873],"type":"Point"}
}