{
  "type": "Feature",
  "properties": {
    "addr:full":"1100 Corporation Pkwy Raleigh NC 27610",
    "addr:housenumber":"1100",
    "addr:postcode":"27610",
    "addr:street":"Corporation Pkwy",
    "iso:country":"US",
    "sg:address":"1100 Corporation Pkwy",
    "sg:city":"Raleigh",
    "sg:classifiers":[
        {
            "category":"Wholesale",
            "subcategory":"Chemicals & Plastics",
            "type":"Manufacturing & Wholesale Goods"
        }
    ],
    "sg:phone":"+1 919 231 3800",
    "sg:postcode":"27610",
    "sg:province":"NC",
    "sg:tags":[
        "adhesive",
        "glue"
    ],
    "wof:name":"R S Hughes Co",
    "wof:placetype":"venue"
},
  "geometry": {"coordinates":[-78.56898,35.793009],"type":"Point"}
}