{
  "type": "Feature",
  "properties": {
    "addr:full":"3301 Womens Club Dr Raleigh NC 27612",
    "addr:housenumber":"3301",
    "addr:postcode":"27612",
    "addr:street":"Womens Club Dr",
    "iso:country":"US",
    "sg:address":"3301 Womens Club Dr",
    "sg:city":"Raleigh",
    "sg:classifiers":[
        {
            "category":"Health Services",
            "subcategory":"Clinic",
            "type":"Services"
        }
    ],
    "sg:phone":"+1 919 783 4070",
    "sg:postcode":"27612",
    "sg:province":"NC",
    "wof:name":"Healthcare Negligence Control",
    "wof:placetype":"venue"
},
  "geometry": {"coordinates":[-78.665905,35.829913],"type":"Point"}
}