{
  "type": "Feature",
  "properties": {
    "iso:country":"US",
    "sg:address":"18 Garren Ln",
    "sg:city":"Fairview",
    "sg:classifiers":[
        {
            "category":"Professional",
            "type":"Services"
        }
    ],
    "sg:phone":"+1 828 779 1569",
    "sg:postcode":"28730",
    "sg:province":"NC",
    "sg:tags":[
        "arts",
        "artist"
    ],
    "wof:name":"Cherry Orchard Studio",
    "wof:placetype":"venue"
},
  "geometry": {"coordinates":[-82.376814,35.523291],"type":"Point"}
}