{
  "type": "Feature",
  "properties": {
    "iso:country":"US",
    "sg:address":"5801 Branchwood Dr",
    "sg:city":"Raleigh",
    "sg:classifiers":[
        {
            "category":"Education",
            "subcategory":"Special Training",
            "type":"Public Place"
        }
    ],
    "sg:phone":"+1   ",
    "sg:postcode":"27609",
    "sg:province":"NC",
    "wof:name":"Edvance Inc",
    "wof:placetype":"venue"
},
  "geometry": {"coordinates":[-78.6271,35.85975],"type":"Point"}
}