{
  "type": "Feature",
  "properties": {
    "iso:country":"US",
    "sg:address":"3704 Carolina Beach Rd",
    "sg:city":"Wilmington",
    "sg:classifiers":[
        {
            "category":"Professional",
            "type":"Services"
        }
    ],
    "sg:phone":"+1 910 397 0721",
    "sg:postcode":"28412",
    "sg:province":"NC",
    "wof:name":"Estetica Familiar",
    "wof:placetype":"venue"
},
  "geometry": {"coordinates":[-77.926416,34.177811],"type":"Point"}
}