{
  "type": "Feature",
  "properties": {
    "addr:full":"4950 Cameron Rd Hope Mills NC 28348",
    "addr:housenumber":"4950",
    "addr:postcode":"28348",
    "addr:street":"Cameron Rd",
    "iso:country":"US",
    "sg:address":"4950 Cameron Rd",
    "sg:city":"Hope Mills",
    "sg:classifiers":[
        {
            "category":"Health Services",
            "subcategory":"Doctor",
            "type":"Services"
        }
    ],
    "sg:phone":"+1 910 424 1918",
    "sg:postcode":"28348",
    "sg:province":"NC",
    "sg:tags":[
        "dentist"
    ],
    "wof:name":"Hope Mills Family Dentistry",
    "wof:placetype":"venue"
},
  "geometry": {"coordinates":[-78.938183,34.966503],"type":"Point"}
}