{
  "type": "Feature",
  "properties": {
    "addr:full":"419 Country Club Dr Waynesville NC 28786",
    "addr:housenumber":"419",
    "addr:postcode":"28786",
    "addr:street":"Country Club Dr",
    "iso:country":"US",
    "sg:address":"419 Country Club Dr",
    "sg:city":"Waynesville",
    "sg:classifiers":[
        {
            "category":"Professional",
            "subcategory":"Engineering",
            "type":"Services"
        }
    ],
    "sg:phone":"+1   ",
    "sg:postcode":"28786",
    "sg:province":"NC",
    "wof:name":"Global Catalyst & Prcss Tchnlg",
    "wof:placetype":"venue"
},
  "geometry": {"coordinates":[-82.99381,35.470809],"type":"Point"}
}