{
  "type": "Feature",
  "properties": {
    "addr:full":"5417 Bevington Pl Charlotte NC 28277",
    "addr:housenumber":"5417",
    "addr:postcode":"28277",
    "addr:street":"Bevington Pl",
    "iso:country":"US",
    "sg:address":"5417 Bevington Pl",
    "sg:city":"Charlotte",
    "sg:classifiers":[
        {
            "category":"Building & Trades",
            "subcategory":"Cleaning & Sanitation",
            "type":"Services"
        }
    ],
    "sg:phone":"+1   ",
    "sg:postcode":"28277",
    "sg:province":"NC",
    "sg:tags":[
        "maintenance"
    ],
    "wof:name":"Asepsis LLC",
    "wof:placetype":"venue"
},
  "geometry": {"coordinates":[-80.81209200000001,35.078824],"type":"Point"}
}