{
  "type": "Feature",
  "properties": {
    "addr:full":"495 Chicora Club Dr Dunn NC 28334",
    "addr:housenumber":"495",
    "addr:postcode":"28334",
    "addr:street":"Chicora Club Dr",
    "iso:country":"US",
    "sg:address":"495 Chicora Club Dr",
    "sg:city":"Dunn",
    "sg:classifiers":[
        {
            "category":"Recreation",
            "type":"Entertainment"
        }
    ],
    "sg:phone":"+1 910 897 7366",
    "sg:postcode":"28334",
    "sg:province":"NC",
    "sg:tags":[
        "course",
        "golf"
    ],
    "wof:name":"Pine Hill South",
    "wof:placetype":"venue"
},
  "geometry": {"coordinates":[-78.682433,35.300802],"type":"Point"}
}