{
  "type": "Feature",
  "properties": {
    "iso:country":"US",
    "sg:address":"1620 Norwood Pl",
    "sg:city":"Hendersonville",
    "sg:classifiers":[
        {
            "category":"Professional",
            "type":"Services"
        }
    ],
    "sg:phone":"+1 828 692 1694",
    "sg:postcode":"28791",
    "sg:province":"NC",
    "sg:tags":[
        "establishment"
    ],
    "wof:name":"Institute For Servant Ldrshp",
    "wof:placetype":"venue"
},
  "geometry": {"coordinates":[-82.469965,35.330661],"type":"Point"}
}