{
  "type": "Feature",
  "properties": {
    "addr:full":"329 N Harrison Ave Cary NC 27513",
    "addr:housenumber":"329",
    "addr:postcode":"27513",
    "addr:street":"N Harrison Ave",
    "iso:country":"US",
    "sg:address":"329 N Harrison Ave",
    "sg:city":"Cary",
    "sg:classifiers":[
        {
            "category":"Bars & Pubs",
            "subcategory":"Sports Bar",
            "type":"Food & Drink"
        }
    ],
    "sg:phone":"+1 919 460 9977",
    "sg:postcode":"27513",
    "sg:province":"NC",
    "wof:name":"Upper Deck Sports Pub",
    "wof:placetype":"venue"
},
  "geometry": {"coordinates":[-78.783401,35.789398],"type":"Point"}
}