{
  "type": "Feature",
  "properties": {
    "addr:full":"1726 Fountain Dr Raleigh NC 27610",
    "addr:housenumber":"1726",
    "addr:postcode":"27610",
    "addr:street":"Fountain Dr",
    "iso:country":"US",
    "sg:address":"1726 Fountain Dr",
    "sg:city":"Raleigh",
    "sg:classifiers":[
        {
            "category":"Building & Trades",
            "subcategory":"Landscaping Services",
            "type":"Services"
        }
    ],
    "sg:phone":"+1 919 832 2903",
    "sg:postcode":"27610",
    "sg:province":"NC",
    "sg:tags":[
        "landscape"
    ],
    "wof:name":"Prices Tree & Landscape",
    "wof:placetype":"venue"
},
  "geometry": {"coordinates":[-78.609234,35.753592],"type":"Point"}
}