{
  "type": "Feature",
  "properties": {
    "addr:full":"720 Matthews Township Pkwy Matthews NC 28105",
    "addr:housenumber":"720",
    "addr:postcode":"28105",
    "addr:street":"Matthews Township Pkwy",
    "iso:country":"US",
    "sg:address":"720 Matthews Township Pkwy",
    "sg:city":"Matthews",
    "sg:classifiers":[
        {
            "category":"Professional",
            "subcategory":"Business Services",
            "type":"Services"
        },
        {
            "category":"Home & Garden",
            "subcategory":"Home Furnishings",
            "type":"Retail Goods"
        }
    ],
    "sg:phone":"+1 704 708 9368",
    "sg:postcode":"28105",
    "sg:province":"NC",
    "sg:tags":[
        "curtain",
        "made",
        "drapery"
    ],
    "wof:name":"Kim's Curtains & Interiors",
    "wof:placetype":"venue"
},
  "geometry": {"coordinates":[-80.728416,35.122244],"type":"Point"}
}