{
  "type": "Feature",
  "properties": {
    "addr:full":"108 Saint Germain Ave SW Valdese NC 28690",
    "addr:housenumber":"108",
    "addr:postcode":"28690",
    "addr:street":"Saint Germain Ave Sw",
    "iso:country":"US",
    "sg:address":"108 Saint Germain Ave SW",
    "sg:city":"Valdese",
    "sg:classifiers":[
        {
            "category":"Organizations",
            "subcategory":"Religious Organization",
            "type":"Services"
        }
    ],
    "sg:phone":"+1 828 893 0956",
    "sg:postcode":"28690",
    "sg:province":"NC",
    "sg:tags":[
        "church"
    ],
    "wof:name":"Waldensian Presbyterian Chr",
    "wof:placetype":"venue"
},
  "geometry": {"coordinates":[-81.564295,35.742517],"type":"Point"}
}