{
  "type": "Feature",
  "properties": {
    "iso:country":"US",
    "sg:address":"1002 Old Lumberton Rd",
    "sg:city":"Whiteville",
    "sg:classifiers":[
        {
            "category":"Building & Trades",
            "subcategory":"Plumbing",
            "type":"Services"
        }
    ],
    "sg:phone":"+1 910 642 7431",
    "sg:postcode":"28472",
    "sg:province":"NC",
    "sg:tags":[
        "repair",
        "contractor"
    ],
    "wof:name":"Inman Rudolph Septic Tank Co",
    "wof:placetype":"venue"
},
  "geometry": {"coordinates":[-78.73151799999999,34.387688],"type":"Point"}
}