{
  "type": "Feature",
  "properties": {
    "iso:country":"US",
    "sg:address":"8111 Concord Mills Blvd",
    "sg:city":"Concord",
    "sg:classifiers":[
        {
            "category":"Coffee & Tea",
            "type":"Food & Drink"
        }
    ],
    "sg:menulink":"http://www.allmenus.com/nc/poplar-tent/125010-starbucks-coffee/menu/",
    "sg:phone":"+1 704 979 1555",
    "sg:postcode":"28027",
    "sg:province":"NC",
    "sg:tags":[
        "american"
    ],
    "wof:name":"Starbucks Coffee",
    "wof:placetype":"venue"
},
  "geometry": {"coordinates":[-80.719639,35.371876],"type":"Point"}
}