{
  "type": "Feature",
  "properties": {
    "addr:full":"2101 US Hwy 258 S Tarboro NC 27886",
    "addr:housenumber":"2101",
    "addr:postcode":"27886",
    "addr:street":"Us Hwy 258 S",
    "iso:country":"US",
    "sg:address":"2101 US Hwy 258 S",
    "sg:city":"Tarboro",
    "sg:classifiers":[
        {
            "category":"Personal",
            "subcategory":"Beauty Salon",
            "type":"Services"
        }
    ],
    "sg:phone":"+1 252 823 5519",
    "sg:postcode":"27886",
    "sg:province":"NC",
    "sg:tags":[
        "shop"
    ],
    "wof:name":"Becky's Beauty Shop",
    "wof:placetype":"venue"
},
  "geometry": {"coordinates":[-77.55335100000001,35.875166],"type":"Point"}
}