{
  "type": "Feature",
  "properties": {
    "addr:full":"2114 Atlantic Ave Raleigh NC 27604",
    "addr:housenumber":"2114",
    "addr:postcode":"27604",
    "addr:street":"Atlantic Ave",
    "iso:country":"US",
    "sg:address":"2114 Atlantic Ave",
    "sg:city":"Raleigh",
    "sg:classifiers":[
        {
            "category":"Freight",
            "type":"Transportation"
        }
    ],
    "sg:phone":"+1 919 667 9766",
    "sg:postcode":"27604",
    "sg:province":"NC",
    "sg:tags":[
        "operator",
        "local",
        "trucking"
    ],
    "wof:name":"Mayflower Transit",
    "wof:placetype":"venue"
},
  "geometry": {"coordinates":[-78.620144,35.808827],"type":"Point"}
}