{
  "type": "Feature",
  "properties": {
    "addr:full":"45 Community Rd Pinehurst NC 28374",
    "addr:housenumber":"45",
    "addr:postcode":"28374",
    "addr:street":"Community Rd",
    "iso:country":"US",
    "sg:address":"45 Community Rd",
    "sg:city":"Pinehurst",
    "sg:classifiers":[
        {
            "category":"Government",
            "subcategory":"Fire Station",
            "type":"Public Place"
        }
    ],
    "sg:phone":"+1 910 295 5575",
    "sg:postcode":"28374",
    "sg:province":"NC",
    "sg:tags":[
        "department"
    ],
    "sg:website":"www.villageofpinehurst.org",
    "wof:name":"Pinehurst Fire Dept",
    "wof:placetype":"venue"
},
  "geometry": {"coordinates":[-79.470067,35.19711],"type":"Point"}
}