{
  "type": "Feature",
  "properties": {
    "iso:country":"US",
    "sg:address":"183 Wind Chime Ct",
    "sg:city":"Raleigh",
    "sg:classifiers":[
        {
            "category":"Organizations",
            "subcategory":"Non-profit Organization",
            "type":"Services"
        }
    ],
    "sg:phone":"+1 919 870 8881",
    "sg:postcode":"27615",
    "sg:province":"NC",
    "sg:tags":[
        "human"
    ],
    "wof:name":"N C Coalition Against Sexual",
    "wof:placetype":"venue"
},
  "geometry": {"coordinates":[-78.643377,35.874058],"type":"Point"}
}