{
  "type": "Feature",
  "properties": {
    "addr:full":"1060 Northwoods Dr Greenville NC 27834",
    "addr:housenumber":"1060",
    "addr:postcode":"27834",
    "addr:street":"Northwoods Dr",
    "iso:country":"US",
    "sg:address":"1060 Northwoods Dr",
    "sg:city":"Greenville",
    "sg:classifiers":[
        {
            "category":"Organizations",
            "subcategory":"Community Association",
            "type":"Services"
        }
    ],
    "sg:phone":"+1   ",
    "sg:postcode":"27834",
    "sg:province":"NC",
    "wof:name":"Civitan International",
    "wof:placetype":"venue"
},
  "geometry": {"coordinates":[-77.32453599999999,35.64107],"type":"Point"}
}