{
  "type": "Feature",
  "properties": {
    "addr:full":"2521 N Wesleyan Blvd Rocky Mount NC 27804",
    "addr:housenumber":"2521",
    "addr:postcode":"27804",
    "addr:street":"N Wesleyan Blvd",
    "iso:country":"US",
    "sg:address":"2521 N Wesleyan Blvd",
    "sg:city":"Rocky Mount",
    "sg:classifiers":[
        {
            "category":"Manufacturing",
            "subcategory":"Petroleum Products",
            "type":"Manufacturing & Wholesale Goods"
        },
        {
            "category":"Home & Garden",
            "subcategory":"Building Materials",
            "type":"Retail Goods"
        }
    ],
    "sg:phone":"+1 252 972 1864",
    "sg:postcode":"27804",
    "sg:province":"NC",
    "sg:tags":[
        "siding",
        "asphalt",
        "mfg"
    ],
    "wof:name":"Eastern Aluminum Supply Co",
    "wof:placetype":"venue"
},
  "geometry": {"coordinates":[-77.77643399999999,35.998981],"type":"Point"}
}