{
  "type": "Feature",
  "properties": {
    "iso:country":"US",
    "sg:address":"9013 Perimeter Woods Dr",
    "sg:city":"Charlotte",
    "sg:classifiers":[
        {
            "category":"Manufacturing",
            "subcategory":"Printing",
            "type":"Manufacturing & Wholesale Goods"
        }
    ],
    "sg:phone":"+1 704 921 5501",
    "sg:postcode":"28216",
    "sg:province":"NC",
    "sg:tags":[
        "process",
        "commercial",
        "datum",
        "mfg"
    ],
    "wof:name":"Customer Service",
    "wof:placetype":"venue"
},
  "geometry": {"coordinates":[-80.850399,35.343098],"type":"Point"}
}