{
  "type": "Feature",
  "properties": {
    "addr:full":"443 John Garner Rd Sanford NC 27332",
    "addr:housenumber":"443",
    "addr:postcode":"27332",
    "addr:street":"John Garner Rd",
    "iso:country":"US",
    "sg:address":"443 John Garner Rd",
    "sg:city":"Sanford",
    "sg:classifiers":[
        {
            "category":"Travel",
            "subcategory":"Campground",
            "type":"Entertainment"
        }
    ],
    "sg:phone":"+1   ",
    "sg:postcode":"27332",
    "sg:province":"NC",
    "sg:tags":[
        "trailer"
    ],
    "wof:name":"L & L Mobile Home Services",
    "wof:placetype":"venue"
},
  "geometry": {"coordinates":[-79.14145499999999,35.381812],"type":"Point"}
}