{
  "type": "Feature",
  "properties": {
    "iso:country":"US",
    "sg:address":"118 Hamby Rd",
    "sg:city":"Dobson",
    "sg:classifiers":[
        {
            "category":"Government",
            "subcategory":"Office",
            "type":"Public Place"
        }
    ],
    "sg:phone":"+1 336 401 8250",
    "sg:postcode":"27017",
    "sg:province":"NC",
    "sg:tags":[
        "executive"
    ],
    "wof:name":"Surry County Nutrition Center",
    "wof:placetype":"venue"
},
  "geometry": {"coordinates":[-80.708744,36.393243],"type":"Point"}
}