{
  "type": "Feature",
  "properties": {
    "addr:full":"103 W Lashley St Pinetops NC 27864",
    "addr:housenumber":"103",
    "addr:postcode":"27864",
    "addr:street":"W Lashley St",
    "iso:country":"US",
    "sg:address":"103 W Lashley St",
    "sg:city":"Pinetops",
    "sg:classifiers":[
        {
            "category":"Real Estate",
            "subcategory":"Developer",
            "type":"Services"
        }
    ],
    "sg:phone":"+1 252 827 4349",
    "sg:postcode":"27864",
    "sg:province":"NC",
    "wof:name":"Matt S Cobb Developments",
    "wof:placetype":"venue"
},
  "geometry": {"coordinates":[-77.63991799999999,35.789751],"type":"Point"}
}