{
  "type": "Feature",
  "properties": {
    "iso:country":"US",
    "sg:address":"4484 Amelia Ct",
    "sg:city":"Wilmington",
    "sg:classifiers":[
        {
            "category":"Professional",
            "subcategory":"Business Services",
            "type":"Services"
        }
    ],
    "sg:phone":"+1   ",
    "sg:postcode":"28405",
    "sg:province":"NC",
    "sg:tags":[
        "automobile",
        "towing",
        "recovery"
    ],
    "wof:name":"Carders Recovery Service",
    "wof:placetype":"venue"
},
  "geometry": {"coordinates":[-77.88094,34.261212],"type":"Point"}
}