{
  "type": "Feature",
  "properties": {
    "addr:full":"210 Blackwell St Durham NC 27701",
    "addr:housenumber":"210",
    "addr:postcode":"27701",
    "addr:street":"Blackwell St",
    "iso:country":"US",
    "sg:address":"210 Blackwell St",
    "sg:city":"Durham",
    "sg:classifiers":[
        {
            "category":"Wholesale",
            "subcategory":"Tobacco Products",
            "type":"Manufacturing & Wholesale Goods"
        }
    ],
    "sg:phone":"+1 919 682 2834",
    "sg:postcode":"27701",
    "sg:province":"NC",
    "sg:tags":[
        "cigarette",
        "cigar",
        "dealer"
    ],
    "wof:name":"Bryant Durham Electric Tobacco",
    "wof:placetype":"venue"
},
  "geometry": {"coordinates":[-78.902784,35.99474],"type":"Point"}
}