{
  "type": "Feature",
  "properties": {
    "addr:full":"4293 State Hwy 27 Midland NC 28107",
    "addr:housenumber":"4293",
    "addr:postcode":"28107",
    "addr:street":"State Hwy 27",
    "iso:country":"US",
    "sg:address":"4293 State Hwy 27",
    "sg:city":"Midland",
    "sg:classifiers":[
        {
            "category":"Utilities",
            "subcategory":"Mobile Phone",
            "type":"Services"
        }
    ],
    "sg:phone":"+1 704 888 6788",
    "sg:postcode":"28107",
    "sg:province":"NC",
    "sg:tags":[
        "telephone",
        "cellular"
    ],
    "wof:name":"Cellular Connections",
    "wof:placetype":"venue"
},
  "geometry": {"coordinates":[-80.51114099999999,35.250075],"type":"Point"}
}