{
  "type": "Feature",
  "properties": {
    "addr:full":"1055 19th Avenue Pl NW Hickory NC 28601",
    "addr:housenumber":"1055",
    "addr:postcode":"28601",
    "addr:street":"19Th Avenue Pl Nw",
    "iso:country":"US",
    "sg:address":"1055 19th Avenue Pl NW",
    "sg:city":"Hickory",
    "sg:classifiers":[
        {
            "category":"Manufacturing",
            "subcategory":"Metals",
            "type":"Manufacturing & Wholesale Goods"
        }
    ],
    "sg:phone":"+1 828 328 4553",
    "sg:postcode":"28601",
    "sg:province":"NC",
    "sg:tags":[
        "product",
        "wire",
        "fabricated",
        "mfg"
    ],
    "wof:name":"Leggett & Platt Incorporated",
    "wof:placetype":"venue"
},
  "geometry": {"coordinates":[-81.361982,35.761339],"type":"Point"}
}