{
  "type": "Feature",
  "properties": {
    "iso:country":"US",
    "sg:address":"5632 Alanhurst Pl",
    "sg:city":"Charlotte",
    "sg:classifiers":[
        {
            "category":"Building & Trades",
            "subcategory":"Plumbing",
            "type":"Services"
        }
    ],
    "sg:phone":"+1 704 527 7285",
    "sg:postcode":"28217",
    "sg:province":"NC",
    "sg:tags":[
        "heating",
        "contractor"
    ],
    "wof:name":"Southland Heating & Air Cond",
    "wof:placetype":"venue"
},
  "geometry": {"coordinates":[-80.887134,35.1545],"type":"Point"}
}