{
  "type": "Feature",
  "properties": {
    "iso:country":"US",
    "sg:address":"523 Bethany Church Rd",
    "sg:city":"Winston Salem",
    "sg:classifiers":[
        {
            "category":"Building & Trades",
            "subcategory":"Electrical",
            "type":"Services"
        }
    ],
    "sg:phone":"+1 336 769 1209",
    "sg:postcode":"27107",
    "sg:province":"NC",
    "sg:tags":[
        "electrical",
        "contractor"
    ],
    "wof:name":"Hillco Electric Co",
    "wof:placetype":"venue"
},
  "geometry": {"coordinates":[-80.171154,35.952172],"type":"Point"}
}