{
  "type": "Feature",
  "properties": {
    "addr:full":"3206 Hampton Rd Raleigh NC 27607",
    "addr:housenumber":"3206",
    "addr:postcode":"27607",
    "addr:street":"Hampton Rd",
    "iso:country":"US",
    "sg:address":"3206 Hampton Rd",
    "sg:city":"Raleigh",
    "sg:classifiers":[
        {
            "category":"Real Estate",
            "subcategory":"Real Estate Agent",
            "type":"Services"
        }
    ],
    "sg:phone":"+1 919 782 6440",
    "sg:postcode":"27607",
    "sg:province":"NC",
    "wof:name":"Carter Real Estate Inc",
    "wof:placetype":"venue"
},
  "geometry": {"coordinates":[-78.681901,35.818961],"type":"Point"}
}