{
  "type": "Feature",
  "properties": {
    "iso:country":"US",
    "sg:address":"120 Crowsnest Rd",
    "sg:city":"Littleton",
    "sg:classifiers":[
        {
            "category":"Professional",
            "type":"Services"
        }
    ],
    "sg:phone":"+1   ",
    "sg:postcode":"27850",
    "sg:province":"NC",
    "wof:name":"Waddell Services",
    "wof:placetype":"venue"
},
  "geometry": {"coordinates":[-77.934409,36.5247],"type":"Point"}
}