{
  "type": "Feature",
  "properties": {
    "iso:country":"US",
    "sg:address":"127 Goose Creek Loop Rd",
    "sg:city":"Newport",
    "sg:classifiers":[
        {
            "category":"Manufacturing",
            "subcategory":"Signs",
            "type":"Manufacturing & Wholesale Goods"
        }
    ],
    "sg:phone":"+1 252 393 8572",
    "sg:postcode":"28570",
    "sg:province":"NC",
    "sg:tags":[
        "mfg"
    ],
    "wof:name":"Quickie Signs & Graphics",
    "wof:placetype":"venue"
},
  "geometry": {"coordinates":[-77.014748,34.702186],"type":"Point"}
}