{
  "type": "Feature",
  "properties": {
    "iso:country":"US",
    "sg:address":"301 10th St NW",
    "sg:city":"Conover",
    "sg:classifiers":[
        {
            "category":"Retail",
            "subcategory":"Repair Shop",
            "type":"Services"
        }
    ],
    "sg:phone":"+1 828 465 2808",
    "sg:postcode":"28613",
    "sg:province":"NC",
    "sg:tags":[
        "upholsterer"
    ],
    "wof:name":"Axis Technical Fabrics",
    "wof:placetype":"venue"
},
  "geometry": {"coordinates":[-81.223305,35.718925],"type":"Point"}
}