{
  "type": "Feature",
  "properties": {
    "iso:country":"US",
    "sg:address":"796 Luby Smith Rd",
    "sg:city":"Princeton",
    "sg:classifiers":[
        {
            "category":"Shopping",
            "subcategory":"Beauty & Cosmetics",
            "type":"Retail Goods"
        }
    ],
    "sg:phone":"+1 919 736 1162",
    "sg:postcode":"27569",
    "sg:province":"NC",
    "sg:tags":[
        "merchandise"
    ],
    "wof:name":"Beauticontrol Cosmetics",
    "wof:placetype":"venue"
},
  "geometry": {"coordinates":[-78.135671,35.430606],"type":"Point"}
}