{
  "type": "Feature",
  "properties": {
    "addr:full":"4936 Cumberland Rd Fayetteville NC 28306",
    "addr:housenumber":"4936",
    "addr:postcode":"28306",
    "addr:street":"Cumberland Rd",
    "iso:country":"US",
    "sg:address":"4936 Cumberland Rd",
    "sg:city":"Fayetteville",
    "sg:classifiers":[
        {
            "category":"Retail",
            "subcategory":"Repair Shop",
            "type":"Services"
        }
    ],
    "sg:phone":"+1   ",
    "sg:postcode":"28306",
    "sg:province":"NC",
    "wof:name":"Stephanies Cleaning",
    "wof:placetype":"venue"
},
  "geometry": {"coordinates":[-78.97162,35.002596],"type":"Point"}
}