{
  "type": "Feature",
  "properties": {
    "addr:full":"3517 Ralph Rd Boonville NC 27011",
    "addr:housenumber":"3517",
    "addr:postcode":"27011",
    "addr:street":"Ralph Rd",
    "iso:country":"US",
    "sg:address":"3517 Ralph Rd",
    "sg:city":"Boonville",
    "sg:classifiers":[
        {
            "category":"Building & Trades",
            "subcategory":"Construction",
            "type":"Services"
        }
    ],
    "sg:phone":"+1 336 468 8920",
    "sg:postcode":"27011",
    "sg:province":"NC",
    "sg:tags":[
        "stone",
        "setting",
        "contractor"
    ],
    "wof:name":"E S Matthews Masonary",
    "wof:placetype":"venue"
},
  "geometry": {"coordinates":[-80.76837500000001,36.148612],"type":"Point"}
}