{
  "type": "Feature",
  "properties": {
    "addr:full":"1681 Little Creek Cir Winston Salem NC 27103",
    "addr:housenumber":"1681",
    "addr:postcode":"27103",
    "addr:street":"Little Creek Cir",
    "iso:country":"US",
    "sg:address":"1681 Little Creek Cir",
    "sg:city":"Winston Salem",
    "sg:classifiers":[
        {
            "category":"Building & Trades",
            "subcategory":"Construction",
            "type":"Services"
        }
    ],
    "sg:phone":"+1 336 765 0928",
    "sg:postcode":"27103",
    "sg:province":"NC",
    "sg:tags":[
        "house"
    ],
    "wof:name":"Montage Construction Inc",
    "wof:placetype":"venue"
},
  "geometry": {"coordinates":[-80.341988,36.041012],"type":"Point"}
}