{
  "type": "Feature",
  "properties": {
    "addr:full":"301 Dogwood Dr Mebane NC 27302",
    "addr:housenumber":"301",
    "addr:postcode":"27302",
    "addr:street":"Dogwood Dr",
    "iso:country":"US",
    "sg:address":"301 Dogwood Dr",
    "sg:city":"Mebane",
    "sg:classifiers":[
        {
            "category":"Real Estate",
            "subcategory":"Real Estate Operator",
            "type":"Services"
        }
    ],
    "sg:phone":"+1 919 304 4411",
    "sg:postcode":"27302",
    "sg:province":"NC",
    "sg:tags":[
        "apartment"
    ],
    "wof:name":"Mebane Mill Apartments",
    "wof:placetype":"venue"
},
  "geometry": {"coordinates":[-79.28165,36.07426],"type":"Point"}
}