{
  "type": "Feature",
  "properties": {
    "addr:full":"3910 Ellison St Hope Mills NC 28348",
    "addr:housenumber":"3910",
    "addr:postcode":"28348",
    "addr:street":"Ellison St",
    "iso:country":"US",
    "sg:address":"3910 Ellison St",
    "sg:city":"Hope Mills",
    "sg:classifiers":[
        {
            "category":"Retail",
            "subcategory":"Auto Rental",
            "type":"Services"
        }
    ],
    "sg:phone":"+1 910 425 4424",
    "sg:postcode":"28348",
    "sg:province":"NC",
    "sg:tags":[
        "renting",
        "truck",
        "leasing"
    ],
    "wof:name":"U-Haul Co",
    "wof:placetype":"venue"
},
  "geometry": {"coordinates":[-78.947141,34.969494],"type":"Point"}
}