{
  "type": "Feature",
  "properties": {
    "iso:country":"US",
    "sg:address":"7909 Falls of Neuse Rd",
    "sg:city":"Raleigh",
    "sg:classifiers":[
        {
            "category":"Restaurant",
            "type":"Food & Drink"
        }
    ],
    "sg:phone":"+1 919 846 6666",
    "sg:postcode":"27615",
    "sg:province":"NC",
    "wof:name":"Los Tres Magueyes III",
    "wof:placetype":"venue"
},
  "geometry": {"coordinates":[-78.625516,35.893211],"type":"Point"}
}