{
  "type": "Feature",
  "properties": {
    "iso:country":"US",
    "sg:address":"3339 Pineville-Matthews Rd",
    "sg:city":"Charlotte",
    "sg:classifiers":[
        {
            "category":"Personal",
            "subcategory":"Beauty Salon",
            "type":"Services"
        }
    ],
    "sg:phone":"+1 704 542 4255",
    "sg:postcode":"28226",
    "sg:province":"NC",
    "sg:tags":[
        "treatment",
        "skin"
    ],
    "sg:website":"www.bathandbodyworks.com",
    "wof:name":"Bath & Body Works Arboretum",
    "wof:placetype":"venue"
},
  "geometry": {"coordinates":[-80.78607,35.097068],"type":"Point"}
}