{
  "type": "Feature",
  "properties": {
    "addr:full":"1565 New Hope Rd Hertford NC 27944",
    "addr:housenumber":"1565",
    "addr:postcode":"27944",
    "addr:street":"New Hope Rd",
    "iso:country":"US",
    "sg:address":"1565 New Hope Rd",
    "sg:city":"Hertford",
    "sg:classifiers":[
        {
            "category":"Farming",
            "subcategory":"Nursery",
            "type":"Manufacturing & Wholesale Goods"
        },
        {
            "category":"Home & Garden",
            "subcategory":"Garden Supply",
            "type":"Retail Goods"
        }
    ],
    "sg:phone":"+1 252 264 3326",
    "sg:postcode":"27944",
    "sg:province":"NC",
    "sg:tags":[
        "bulb",
        "seed",
        "ornamental"
    ],
    "wof:name":"Eure Seed Farms Inc",
    "wof:placetype":"venue"
},
  "geometry": {"coordinates":[-76.354973,36.175019],"type":"Point"}
}