{
  "type": "Feature",
  "properties": {
    "iso:country":"US",
    "sg:address":"133 US Hwy 158",
    "sg:city":"Camden",
    "sg:classifiers":[
        {
            "category":"Shopping",
            "subcategory":"Florist",
            "type":"Retail Goods"
        }
    ],
    "sg:phone":"+1 252 338 5588",
    "sg:postcode":"27921",
    "sg:province":"NC",
    "wof:name":"Rose Petal",
    "wof:placetype":"venue"
},
  "geometry": {"coordinates":[-76.174729,36.323957],"type":"Point"}
}