{
  "type": "Feature",
  "properties": {
    "iso:country":"US",
    "sg:address":"708 Sunset Dr",
    "sg:city":"High Point",
    "sg:classifiers":[
        {
            "category":"Manufacturing",
            "subcategory":"Printing",
            "type":"Manufacturing & Wholesale Goods"
        }
    ],
    "sg:phone":"+1 336 883 1056",
    "sg:postcode":"27262",
    "sg:province":"NC",
    "sg:tags":[
        "publisher"
    ],
    "wof:name":"Temasmith Inc",
    "wof:placetype":"venue"
},
  "geometry": {"coordinates":[-80.02163899999999,35.965478],"type":"Point"}
}