{
  "type": "Feature",
  "properties": {
    "iso:country":"US",
    "sg:address":"2981 Oak Ridge Cir",
    "sg:city":"Lincolnton",
    "sg:classifiers":[
        {
            "category":"Professional",
            "subcategory":"Management & Consulting",
            "type":"Services"
        }
    ],
    "sg:phone":"+1   ",
    "sg:postcode":"28092",
    "sg:province":"NC",
    "wof:name":"Robbins Nest Consultants",
    "wof:placetype":"venue"
},
  "geometry": {"coordinates":[-81.119951,35.52613],"type":"Point"}
}