{
  "type": "Feature",
  "properties": {
    "iso:country":"US",
    "sg:address":"1814 Chandellay Dr",
    "sg:city":"Durham",
    "sg:classifiers":[
        {
            "category":"Building & Trades",
            "subcategory":"Cleaning & Sanitation",
            "type":"Services"
        }
    ],
    "sg:phone":"+1   ",
    "sg:postcode":"27705",
    "sg:province":"NC",
    "sg:tags":[
        "maintenance"
    ],
    "wof:name":"Tjs Contract Cleaning",
    "wof:placetype":"venue"
},
  "geometry": {"coordinates":[-78.927629,36.049209],"type":"Point"}
}