{
  "type": "Feature",
  "properties": {
    "iso:country":"US",
    "sg:address":"4897 Fayetteville Rd",
    "sg:city":"Lumberton",
    "sg:classifiers":[
        {
            "category":"Health Services",
            "subcategory":"Doctor",
            "type":"Services"
        }
    ],
    "sg:phone":"+1 910 739 6911",
    "sg:postcode":"28358",
    "sg:province":"NC",
    "sg:tags":[
        "physician",
        "surgeon"
    ],
    "wof:name":"Physicians Practices",
    "wof:placetype":"venue"
},
  "geometry": {"coordinates":[-79.000186,34.66235],"type":"Point"}
}