{
  "type": "Feature",
  "properties": {
    "iso:country":"US",
    "sg:address":"110 Capcom Ave",
    "sg:city":"Wake Forest",
    "sg:classifiers":[
        {
            "category":"Health Services",
            "subcategory":"Optometrist",
            "type":"Services"
        }
    ],
    "sg:phone":"+1 919 556 1909",
    "sg:postcode":"27587",
    "sg:province":"NC",
    "sg:website":"www.wakeforestfamilyeye.com",
    "wof:name":"Wake Forest Family Eye Care",
    "wof:placetype":"venue"
},
  "geometry": {"coordinates":[-78.529404,35.950689],"type":"Point"}
}