{
  "type": "Feature",
  "properties": {
    "addr:full":"5011 State Hwy 90 Hiddenite NC 28636",
    "addr:housenumber":"5011",
    "addr:postcode":"28636",
    "addr:street":"State Hwy 90",
    "iso:country":"US",
    "sg:address":"5011 State Hwy 90",
    "sg:city":"Hiddenite",
    "sg:classifiers":[
        {
            "category":"Building & Trades",
            "subcategory":"Pest Control",
            "type":"Services"
        }
    ],
    "sg:phone":"+1 828 632 7240",
    "sg:postcode":"28636",
    "sg:province":"NC",
    "wof:name":"Northstate Pest Control Inc",
    "wof:placetype":"venue"
},
  "geometry": {"coordinates":[-81.092602,35.901876],"type":"Point"}
}