{
  "type": "Feature",
  "properties": {
    "addr:full":"201 W High Ave High Point NC 27260",
    "addr:housenumber":"201",
    "addr:postcode":"27260",
    "addr:street":"W High Ave",
    "iso:country":"US",
    "sg:address":"201 W High Ave",
    "sg:city":"High Point",
    "sg:classifiers":[
        {
            "category":"Manufacturing",
            "subcategory":"Retail Goods",
            "type":"Manufacturing & Wholesale Goods"
        }
    ],
    "sg:phone":"+1 336 886 5452",
    "sg:postcode":"27260",
    "sg:province":"NC",
    "sg:tags":[
        "manufacturer"
    ],
    "wof:name":"Beach Mfg Inc",
    "wof:placetype":"venue"
},
  "geometry": {"coordinates":[-80.01042700000001,35.954718],"type":"Point"}
}