{
  "type": "Feature",
  "properties": {
    "addr:full":"6512 Yateswood Dr Charlotte NC 28212",
    "addr:housenumber":"6512",
    "addr:postcode":"28212",
    "addr:street":"Yateswood Dr",
    "iso:country":"US",
    "sg:address":"6512 Yateswood Dr",
    "sg:city":"Charlotte",
    "sg:classifiers":[
        {
            "category":"Banks & Credit Unions",
            "subcategory":"Bank",
            "type":"Services"
        }
    ],
    "sg:phone":"+1 704 388 8037",
    "sg:postcode":"28212",
    "sg:province":"NC",
    "sg:tags":[
        "national",
        "commercial"
    ],
    "wof:name":"Bank of America",
    "wof:placetype":"venue"
},
  "geometry": {"coordinates":[-80.733602,35.200538],"type":"Point"}
}