{
  "type": "Feature",
  "properties": {
    "addr:full":"5815 Bayleaf Ln Greensboro NC 27455",
    "addr:housenumber":"5815",
    "addr:postcode":"27455",
    "addr:street":"Bayleaf Ln",
    "iso:country":"US",
    "sg:address":"5815 Bayleaf Ln",
    "sg:city":"Greensboro",
    "sg:classifiers":[
        {
            "category":"Professional",
            "type":"Services"
        }
    ],
    "sg:phone":"+1   ",
    "sg:postcode":"27455",
    "sg:province":"NC",
    "wof:name":"Wescare",
    "wof:placetype":"venue"
},
  "geometry": {"coordinates":[-79.826815,36.158086],"type":"Point"}
}