{
  "type": "Feature",
  "properties": {
    "iso:country":"US",
    "sg:address":"317 Trindale Rd",
    "sg:city":"Archdale",
    "sg:classifiers":[
        {
            "category":"Freight",
            "type":"Transportation"
        }
    ],
    "sg:phone":"+1 336 431 0535",
    "sg:postcode":"27263",
    "sg:province":"NC",
    "sg:tags":[
        "commercial",
        "storage"
    ],
    "wof:name":"Trindale Self Storage",
    "wof:placetype":"venue"
},
  "geometry": {"coordinates":[-79.977774,35.91272],"type":"Point"}
}