{
  "type": "Feature",
  "properties": {
    "addr:full":"1250 Western Blvd Jacksonville NC 28546",
    "addr:housenumber":"1250",
    "addr:postcode":"28546",
    "addr:street":"Western Blvd",
    "iso:country":"US",
    "sg:address":"1250 Western Blvd",
    "sg:city":"Jacksonville",
    "sg:classifiers":[
        {
            "category":"Food & Beverages",
            "subcategory":"Specialty",
            "type":"Retail Goods"
        }
    ],
    "sg:phone":"+1 910 478 0500",
    "sg:postcode":"28546",
    "sg:province":"NC",
    "sg:tags":[
        "health",
        "diet"
    ],
    "wof:name":"GNC",
    "wof:placetype":"venue"
},
  "geometry": {"coordinates":[-77.393096,34.777818],"type":"Point"}
}