{
  "type": "Feature",
  "properties": {
    "addr:full":"1312 Annapolis Dr Raleigh NC 27608",
    "addr:housenumber":"1312",
    "addr:postcode":"27608",
    "addr:street":"Annapolis Dr",
    "iso:country":"US",
    "sg:address":"1312 Annapolis Dr",
    "sg:city":"Raleigh",
    "sg:classifiers":[
        {
            "category":"Professional",
            "subcategory":"Lawyer & Legal Services",
            "type":"Services"
        }
    ],
    "sg:phone":"+1 919 828 7333",
    "sg:postcode":"27608",
    "sg:province":"NC",
    "sg:tags":[
        "attorney"
    ],
    "wof:name":"Scudder & Hedrick",
    "wof:placetype":"venue"
},
  "geometry": {"coordinates":[-78.658023,35.799305],"type":"Point"}
}