{
  "type": "Feature",
  "properties": {
    "addr:full":"4980 Taylorsville Hwy Stony Point NC 28678",
    "addr:housenumber":"4980",
    "addr:postcode":"28678",
    "addr:street":"Taylorsville Hwy",
    "iso:country":"US",
    "sg:address":"4980 Taylorsville Hwy",
    "sg:city":"Stony Point",
    "sg:classifiers":[
        {
            "category":"Retail",
            "subcategory":"Portrait Studio",
            "type":"Services"
        }
    ],
    "sg:phone":"+1 704 585 2845",
    "sg:postcode":"28678",
    "sg:province":"NC",
    "sg:tags":[
        "photographer",
        "photo"
    ],
    "wof:name":"Pride & Joy Photgraphy Inc",
    "wof:placetype":"venue"
},
  "geometry": {"coordinates":[-81.027205,35.854917],"type":"Point"}
}