{
  "type": "Feature",
  "properties": {
    "addr:full":"2908 New Sharon Church Rd Hillsborough NC 27278",
    "addr:housenumber":"2908",
    "addr:postcode":"27278",
    "addr:street":"New Sharon Church Rd",
    "iso:country":"US",
    "sg:address":"2908 New Sharon Church Rd",
    "sg:city":"Hillsborough",
    "sg:classifiers":[
        {
            "category":"Building & Trades",
            "subcategory":"Plumbing",
            "type":"Services"
        }
    ],
    "sg:phone":"+1 919 732 7457",
    "sg:postcode":"27278",
    "sg:province":"NC",
    "sg:tags":[
        "plumbing",
        "contractor"
    ],
    "wof:name":"Cole's Plumbing Co",
    "wof:placetype":"venue"
},
  "geometry": {"coordinates":[-79.022301,36.133439],"type":"Point"}
}