{
  "type": "Feature",
  "properties": {
    "iso:country":"US",
    "sg:address":"1620 E 4th St",
    "sg:city":"Charlotte",
    "sg:classifiers":[
        {
            "category":"Shopping",
            "subcategory":"Gifts & Souvenirs",
            "type":"Retail Goods"
        }
    ],
    "sg:phone":"+1 704 374 0388",
    "sg:postcode":"28204",
    "sg:province":"NC",
    "wof:name":"Gifts For Less",
    "wof:placetype":"venue"
},
  "geometry": {"coordinates":[-80.827743,35.212965],"type":"Point"}
}