{
  "type": "Feature",
  "properties": {
    "addr:full":"130 Lee St Kenansville NC 28349",
    "addr:housenumber":"130",
    "addr:postcode":"28349",
    "addr:street":"Lee St",
    "iso:country":"US",
    "sg:address":"130 Lee St",
    "sg:city":"Kenansville",
    "sg:classifiers":[
        {
            "category":"Health Services",
            "subcategory":"Health Practitioner",
            "type":"Services"
        }
    ],
    "sg:phone":"+1 910 296 0544",
    "sg:postcode":"28349",
    "sg:province":"NC",
    "sg:tags":[
        "nutritionist"
    ],
    "wof:name":"Pittman's Nutrition Wic Store",
    "wof:placetype":"venue"
},
  "geometry": {"coordinates":[-77.957661,34.960999],"type":"Point"}
}