{
  "type": "Feature",
  "properties": {
    "addr:full":"231 Memorial Dr Jacksonville NC 28546",
    "addr:housenumber":"231",
    "addr:postcode":"28546",
    "addr:street":"Memorial Dr",
    "iso:country":"US",
    "sg:address":"231 Memorial Dr",
    "sg:city":"Jacksonville",
    "sg:classifiers":[
        {
            "category":"Health Services",
            "subcategory":"Doctor",
            "type":"Services"
        }
    ],
    "sg:phone":"+1 910 353 2800",
    "sg:postcode":"28546",
    "sg:province":"NC",
    "sg:tags":[
        "physician",
        "surgeon"
    ],
    "wof:name":"Jacksonville General Practice",
    "wof:placetype":"venue"
},
  "geometry": {"coordinates":[-77.38465100000001,34.766641],"type":"Point"}
}