{
  "type": "Feature",
  "properties": {
    "addr:full":"103 South Ave Swannanoa NC 28778",
    "addr:housenumber":"103",
    "addr:postcode":"28778",
    "addr:street":"South Ave",
    "iso:country":"US",
    "sg:address":"103 South Ave",
    "sg:city":"Swannanoa",
    "sg:classifiers":[
        {
            "category":"Government",
            "subcategory":"Fire Station",
            "type":"Public Place"
        }
    ],
    "sg:phone":"+1 828 686 3335",
    "sg:postcode":"28778",
    "sg:province":"NC",
    "sg:tags":[
        "department"
    ],
    "sg:website":"www.svfd.net",
    "wof:name":"Swannanoa Fire Dept",
    "wof:placetype":"venue"
},
  "geometry": {"coordinates":[-82.39655,35.598914],"type":"Point"}
}