{
  "type": "Feature",
  "properties": {
    "iso:country":"US",
    "sg:address":"1493 Concord Pkwy N",
    "sg:city":"Concord",
    "sg:classifiers":[
        {
            "category":"Restaurant",
            "type":"Food & Drink"
        }
    ],
    "sg:phone":"+1 704 784 5577",
    "sg:postcode":"28025",
    "sg:province":"NC",
    "sg:website":"www.mayflowerseafood.com",
    "wof:name":"Mayflower Seafood Restaurant",
    "wof:placetype":"venue"
},
  "geometry": {"coordinates":[-80.605272,35.43794],"type":"Point"}
}