{
  "type": "Feature",
  "properties": {
    "addr:full":"24453 US Hwy 52 Albemarle NC 28001",
    "addr:housenumber":"24453",
    "addr:postcode":"28001",
    "addr:street":"Us Hwy 52",
    "iso:country":"US",
    "sg:address":"24453 US Hwy 52",
    "sg:city":"Albemarle",
    "sg:classifiers":[
        {
            "category":"Organizations",
            "subcategory":"Community Association",
            "type":"Services"
        }
    ],
    "sg:phone":"+1   ",
    "sg:postcode":"28001",
    "sg:province":"NC",
    "wof:name":"Howard Moose",
    "wof:placetype":"venue"
},
  "geometry": {"coordinates":[-80.18336499999999,35.330628],"type":"Point"}
}