{
  "type": "Feature",
  "properties": {
    "addr:full":"294 E Davis St Burlington NC 27215",
    "addr:housenumber":"294",
    "addr:postcode":"27215",
    "addr:street":"E Davis St",
    "iso:country":"US",
    "sg:address":"294 E Davis St",
    "sg:city":"Burlington",
    "sg:classifiers":[
        {
            "category":"Health Services",
            "subcategory":"Doctor",
            "type":"Services"
        }
    ],
    "sg:phone":"+1 336 226 6300",
    "sg:postcode":"27215",
    "sg:province":"NC",
    "wof:name":"Dr Ricks Robert",
    "wof:placetype":"venue"
},
  "geometry": {"coordinates":[-79.43687799999999,36.092627],"type":"Point"}
}