{
  "type": "Feature",
  "properties": {
    "addr:full":"1985 Eastwood Rd Wilmington NC 28403",
    "addr:housenumber":"1985",
    "addr:postcode":"28403",
    "addr:street":"Eastwood Rd",
    "iso:country":"US",
    "sg:address":"1985 Eastwood Rd",
    "sg:city":"Wilmington",
    "sg:classifiers":[
        {
            "category":"Professional",
            "subcategory":"Accounting & Tax Preparation",
            "type":"Services"
        }
    ],
    "sg:phone":"+1 910 509 3800",
    "sg:postcode":"28403",
    "sg:province":"NC",
    "sg:tags":[
        "accountant",
        "public",
        "certified"
    ],
    "wof:name":"Fisher & Company Cpas",
    "wof:placetype":"venue"
},
  "geometry": {"coordinates":[-77.820193,34.222422],"type":"Point"}
}