{
  "type": "Feature",
  "properties": {
    "iso:country":"US",
    "sg:address":"238 Skylark St",
    "sg:city":"Franklin",
    "sg:classifiers":[
        {
            "category":"Building & Trades",
            "subcategory":"Construction",
            "type":"Services"
        }
    ],
    "sg:phone":"+1 828 369 5716",
    "sg:postcode":"28734",
    "sg:province":"NC",
    "sg:tags":[
        "floor",
        "laying",
        "contractor"
    ],
    "wof:name":"Michaels Flooring Installation",
    "wof:placetype":"venue"
},
  "geometry": {"coordinates":[-83.376525,35.192259],"type":"Point"}
}