{
  "type": "Feature",
  "properties": {
    "iso:country":"US",
    "sg:address":"2930 W Main St",
    "sg:city":"Durham",
    "sg:classifiers":[
        {
            "category":"Food & Beverages",
            "subcategory":"Groceries & Convenience Stores",
            "type":"Retail Goods"
        }
    ],
    "sg:phone":"+1 919 286 0400",
    "sg:postcode":"27705",
    "sg:province":"NC",
    "sg:tags":[
        "grocer"
    ],
    "sg:website":"www.foodlion.com",
    "wof:name":"Food Lion",
    "wof:placetype":"venue"
},
  "geometry": {"coordinates":[-78.934855,36.014395],"type":"Point"}
}