{
  "type": "Feature",
  "properties": {
    "iso:country":"US",
    "sg:address":"125 Murray Hill Rd",
    "sg:city":"Southern Pines",
    "sg:classifiers":[
        {
            "category":"Freight",
            "type":"Transportation"
        }
    ],
    "sg:phone":"+1 910 693 8070",
    "sg:postcode":"28387",
    "sg:province":"NC",
    "sg:tags":[
        "general"
    ],
    "wof:name":"Atrium Storage Facility",
    "wof:placetype":"venue"
},
  "geometry": {"coordinates":[-79.413005,35.163926],"type":"Point"}
}