{
  "type": "Feature",
  "properties": {
    "addr:full":"7713 Lead Mine Rd Raleigh NC 27615",
    "addr:housenumber":"7713",
    "addr:postcode":"27615",
    "addr:street":"Lead Mine Rd",
    "iso:country":"US",
    "sg:address":"7713 Lead Mine Rd",
    "sg:city":"Raleigh",
    "sg:classifiers":[
        {
            "category":"Building & Trades",
            "subcategory":"Pest Control",
            "type":"Services"
        }
    ],
    "sg:phone":"+1 919 676 7778",
    "sg:postcode":"27615",
    "sg:province":"NC",
    "sg:tags":[
        "termite"
    ],
    "wof:name":"Frye Exterminating Co Inc",
    "wof:placetype":"venue"
},
  "geometry": {"coordinates":[-78.659308,35.88648],"type":"Point"}
}