{
  "type": "Feature",
  "properties": {
    "iso:country":"US",
    "sg:address":"1612 Edgewater Dr",
    "sg:city":"Charlotte",
    "sg:classifiers":[
        {
            "category":"Freight",
            "type":"Transportation"
        }
    ],
    "sg:phone":"+1 704 553 1887",
    "sg:postcode":"28210",
    "sg:province":"NC",
    "sg:tags":[
        "operator",
        "trucking"
    ],
    "wof:name":"William C Gilbert Trucking",
    "wof:placetype":"venue"
},
  "geometry": {"coordinates":[-80.87055599999999,35.142846],"type":"Point"}
}