{
  "type": "Feature",
  "properties": {
    "addr:full":"2520 W Roosevelt Blvd Monroe NC 28110",
    "addr:housenumber":"2520",
    "addr:postcode":"28110",
    "addr:street":"W Roosevelt Blvd",
    "iso:country":"US",
    "sg:address":"2520 W Roosevelt Blvd",
    "sg:city":"Monroe",
    "sg:classifiers":[
        {
            "category":"Food & Beverages",
            "subcategory":"Groceries & Convenience Stores",
            "type":"Retail Goods"
        }
    ],
    "sg:phone":"+1 704 238 0260",
    "sg:postcode":"28110",
    "sg:province":"NC",
    "sg:tags":[
        "grocer"
    ],
    "wof:name":"El Soplon Deportivo",
    "wof:placetype":"venue"
},
  "geometry": {"coordinates":[-80.569016,35.013934],"type":"Point"}
}