{
  "type": "Feature",
  "properties": {
    "iso:country":"US",
    "sg:address":"102 N 4th St",
    "sg:city":"Wilmington",
    "sg:classifiers":[
        {
            "category":"Professional",
            "subcategory":"Testing Lab",
            "type":"Services"
        }
    ],
    "sg:phone":"+1 910 341 7999",
    "sg:postcode":"28401",
    "sg:province":"NC",
    "sg:tags":[
        "laboratory"
    ],
    "wof:name":"ITS Caleb Brett",
    "wof:placetype":"venue"
},
  "geometry": {"coordinates":[-77.94488200000001,34.237849],"type":"Point"}
}