{
  "type": "Feature",
  "properties": {
    "addr:full":"290 Edwardia Dr Greensboro NC 27409",
    "addr:housenumber":"290",
    "addr:postcode":"27409",
    "addr:street":"Edwardia Dr",
    "iso:country":"US",
    "sg:address":"290 Edwardia Dr",
    "sg:city":"Greensboro",
    "sg:classifiers":[
        {
            "category":"Recreation",
            "type":"Entertainment"
        }
    ],
    "sg:phone":"+1 336 294 3116",
    "sg:postcode":"27409",
    "sg:province":"NC",
    "sg:tags":[
        "club",
        "membership"
    ],
    "wof:name":"West Market Street Yacht Club",
    "wof:placetype":"venue"
},
  "geometry": {"coordinates":[-79.882743,36.070757],"type":"Point"}
}