{
  "type": "Feature",
  "properties": {
    "iso:country":"US",
    "sg:address":"311 Center Pointe Dr",
    "sg:city":"Cary",
    "sg:classifiers":[
        {
            "category":"Professional",
            "subcategory":"Research",
            "type":"Services"
        }
    ],
    "sg:phone":"+1   ",
    "sg:postcode":"27513",
    "sg:province":"NC",
    "sg:tags":[
        "organization",
        "noncommercial"
    ],
    "wof:name":"Rubicon Foundation Inc",
    "wof:placetype":"venue"
},
  "geometry": {"coordinates":[-78.825301,35.764144],"type":"Point"}
}