{
  "type": "Feature",
  "properties": {
    "iso:country":"US",
    "sg:address":"1111 N 5th St",
    "sg:city":"Wilmington",
    "sg:classifiers":[
        {
            "category":"Organizations",
            "subcategory":"Religious Organization",
            "type":"Services"
        }
    ],
    "sg:phone":"+1   ",
    "sg:postcode":"28401",
    "sg:province":"NC",
    "wof:name":"Mount Zion AME Church",
    "wof:placetype":"venue"
},
  "geometry": {"coordinates":[-77.94507400000001,34.249063],"type":"Point"}
}