{
  "type": "Feature",
  "properties": {
    "iso:country":"US",
    "sg:address":"3327 Archdale Dr",
    "sg:city":"Charlotte",
    "sg:classifiers":[
        {
            "category":"Organizations",
            "subcategory":"Religious Organization",
            "type":"Services"
        }
    ],
    "sg:phone":"+1   ",
    "sg:postcode":"28210",
    "sg:province":"NC",
    "wof:name":"Exciting Word Ministries",
    "wof:placetype":"venue"
},
  "geometry": {"coordinates":[-80.847497,35.144913],"type":"Point"}
}