{
  "type": "Feature",
  "properties": {
    "iso:country":"US",
    "sg:address":"3530 Dockside Ln",
    "sg:city":"Sherrills Ford",
    "sg:classifiers":[
        {
            "category":"Building & Trades",
            "subcategory":"Construction",
            "type":"Services"
        }
    ],
    "sg:phone":"+1 828 478 3514",
    "sg:postcode":"28673",
    "sg:province":"NC",
    "sg:tags":[
        "grading",
        "contractor"
    ],
    "wof:name":"Beatty Grading",
    "wof:placetype":"venue"
},
  "geometry": {"coordinates":[-81.008287,35.594879],"type":"Point"}
}