{
  "type": "Feature",
  "properties": {
    "addr:full":"195 Fairground Ave Hendersonville NC 28792",
    "addr:housenumber":"195",
    "addr:postcode":"28792",
    "addr:street":"Fairground Ave",
    "iso:country":"US",
    "sg:address":"195 Fairground Ave",
    "sg:city":"Hendersonville",
    "sg:classifiers":[
        {
            "category":"Sports & Exercise",
            "subcategory":"Gym",
            "type":"Entertainment"
        }
    ],
    "sg:phone":"+1   ",
    "sg:postcode":"28792",
    "sg:province":"NC",
    "sg:tags":[
        "fitness",
        "physical",
        "facility"
    ],
    "wof:name":"Professional Fitness Center",
    "wof:placetype":"venue"
},
  "geometry": {"coordinates":[-82.425639,35.298975],"type":"Point"}
}