{
  "type": "Feature",
  "properties": {
    "iso:country":"US",
    "sg:address":"5959 Dean Ave",
    "sg:city":"Raleigh",
    "sg:classifiers":[
        {
            "category":"Shopping",
            "subcategory":"Clothing, Apparel, & Fashions",
            "type":"Retail Goods"
        }
    ],
    "sg:phone":"+1 919 792 2180",
    "sg:postcode":"27616",
    "sg:province":"NC",
    "sg:tags":[
        "wear"
    ],
    "wof:name":"Childrens Place The",
    "wof:placetype":"venue"
},
  "geometry": {"coordinates":[-78.562377,35.861437],"type":"Point"}
}