{
  "type": "Feature",
  "properties": {
    "iso:country":"US",
    "sg:address":"5544 US Hwy 64 E",
    "sg:city":"Ramseur",
    "sg:classifiers":[
        {
            "category":"Arts & Performance",
            "subcategory":"Theater",
            "type":"Entertainment"
        },
        {
            "category":"Cinema",
            "subcategory":"Movie Theater",
            "type":"Entertainment"
        }
    ],
    "sg:phone":"+1 336 824 4800",
    "sg:postcode":"27316",
    "sg:province":"NC",
    "sg:tags":[
        "motion",
        "picture"
    ],
    "wof:name":"Rand Ol' Opry",
    "wof:placetype":"venue"
},
  "geometry": {"coordinates":[-79.683277,35.728874],"type":"Point"}
}