{
  "type": "Feature",
  "properties": {
    "addr:full":"3942 Rockford Rd Boonville NC 27011",
    "addr:housenumber":"3942",
    "addr:postcode":"27011",
    "addr:street":"Rockford Rd",
    "iso:country":"US",
    "sg:address":"3942 Rockford Rd",
    "sg:city":"Boonville",
    "sg:classifiers":[
        {
            "category":"Freight",
            "type":"Transportation"
        }
    ],
    "sg:phone":"+1 336 367 7336",
    "sg:postcode":"27011",
    "sg:province":"NC",
    "sg:tags":[
        "commercial",
        "storage",
        "special"
    ],
    "wof:name":"Boonville Self Storage",
    "wof:placetype":"venue"
},
  "geometry": {"coordinates":[-80.654915,36.243713],"type":"Point"}
}