{
  "type": "Feature",
  "properties": {
    "iso:country":"US",
    "sg:address":"139 Apex Ln",
    "sg:city":"Mt Airy",
    "sg:classifiers":[
        {
            "category":"Social Services",
            "subcategory":"Adult Care",
            "type":"Services"
        }
    ],
    "sg:phone":"+1 336 320 2185",
    "sg:postcode":"27030",
    "sg:province":"NC",
    "sg:tags":[
        "home",
        "residential"
    ],
    "wof:name":"Central Care Inc",
    "wof:placetype":"venue"
},
  "geometry": {"coordinates":[-80.648996,36.452894],"type":"Point"}
}