{
  "type": "Feature",
  "properties": {
    "iso:country":"US",
    "sg:address":"245 Liberty Park Rd",
    "sg:city":"Jacksonville",
    "sg:classifiers":[
        {
            "category":"Organizations",
            "subcategory":"Religious Organization",
            "type":"Services"
        }
    ],
    "sg:phone":"+1 910 455 8099",
    "sg:postcode":"28540",
    "sg:province":"NC",
    "sg:tags":[
        "church"
    ],
    "wof:name":"St Mary's Church-Christ",
    "wof:placetype":"venue"
},
  "geometry": {"coordinates":[-77.506242,34.79717],"type":"Point"}
}