{
  "type": "Feature",
  "properties": {
    "addr:full":"106 Armory Rd North Wilkesboro NC 28659",
    "addr:housenumber":"106",
    "addr:postcode":"28659",
    "addr:street":"Armory Rd",
    "iso:country":"US",
    "sg:address":"106 Armory Rd",
    "sg:city":"North Wilkesboro",
    "sg:classifiers":[
        {
            "category":"Wholesale",
            "subcategory":"Farm Supplies",
            "type":"Manufacturing & Wholesale Goods"
        }
    ],
    "sg:phone":"+1 336 838 3442",
    "sg:postcode":"28659",
    "sg:province":"NC",
    "sg:tags":[
        "auction",
        "livestock",
        "market"
    ],
    "wof:name":"Kilby's Livestock Market Inc",
    "wof:placetype":"venue"
},
  "geometry": {"coordinates":[-81.12667399999999,36.164594],"type":"Point"}
}