{
  "type": "Feature",
  "properties": {
    "iso:country":"US",
    "sg:address":"502 N Broad St",
    "sg:city":"Winston Salem",
    "sg:classifiers":[
        {
            "category":"Organizations",
            "subcategory":"Religious Organization",
            "type":"Services"
        }
    ],
    "sg:phone":"+1 336 723 0625",
    "sg:postcode":"27101",
    "sg:province":"NC",
    "sg:tags":[
        "church"
    ],
    "wof:name":"Christian Fountain Church Inc",
    "wof:placetype":"venue"
},
  "geometry": {"coordinates":[-80.254283,36.100142],"type":"Point"}
}