{
  "type": "Feature",
  "properties": {
    "addr:full":"1250 Massengill Pond Rd Angier NC 27501",
    "addr:housenumber":"1250",
    "addr:postcode":"27501",
    "addr:street":"Massengill Pond Rd",
    "iso:country":"US",
    "sg:address":"1250 Massengill Pond Rd",
    "sg:city":"Angier",
    "sg:classifiers":[
        {
            "category":"Autos & Motor Vehicles",
            "subcategory":"Auto Supplies",
            "type":"Retail Goods"
        }
    ],
    "sg:phone":"+1 919 639 3076",
    "sg:postcode":"27501",
    "sg:province":"NC",
    "sg:tags":[
        "tire"
    ],
    "wof:name":"Countryside Tire",
    "wof:placetype":"venue"
},
  "geometry": {"coordinates":[-78.635177,35.49483],"type":"Point"}
}