{
  "type": "Feature",
  "properties": {
    "addr:full":"4208 Arendell St Morehead City NC 28557",
    "addr:postcode":"4208;28557",
    "addr:street":"Arendell St",
    "iso:country":"US",
    "sg:address":"4208 Arendell St",
    "sg:city":"Morehead City",
    "sg:classifiers":[
        {
            "category":"Real Estate",
            "subcategory":"Real Estate Operator",
            "type":"Services"
        }
    ],
    "sg:phone":"+1 252 726 6330",
    "sg:postcode":"28557",
    "sg:province":"NC",
    "sg:tags":[
        "building",
        "nonresidential"
    ],
    "wof:name":"Jim Johnson",
    "wof:placetype":"venue"
},
  "geometry": {"coordinates":[-76.77213999999999,34.728069],"type":"Point"}
}