{
  "type": "Feature",
  "properties": {
    "addr:full":"5704 Bibar Rd Fayetteville NC 28304",
    "addr:housenumber":"5704",
    "addr:postcode":"28304",
    "addr:street":"Bibar Rd",
    "iso:country":"US",
    "sg:address":"5704 Bibar Rd",
    "sg:city":"Fayetteville",
    "sg:classifiers":[
        {
            "category":"Personal",
            "subcategory":"Beauty Salon",
            "type":"Services"
        }
    ],
    "sg:phone":"+1   ",
    "sg:postcode":"28304",
    "sg:province":"NC",
    "sg:tags":[
        "shop"
    ],
    "wof:name":"Ethels Beauty Shop",
    "wof:placetype":"venue"
},
  "geometry": {"coordinates":[-78.98095499999999,35.017461],"type":"Point"}
}