{
  "type": "Feature",
  "properties": {
    "addr:full":"800 Beaty St Davidson NC 28036",
    "addr:housenumber":"800",
    "addr:postcode":"28036",
    "addr:street":"Beaty St",
    "iso:country":"US",
    "sg:address":"800 Beaty St",
    "sg:city":"Davidson",
    "sg:classifiers":[
        {
            "category":"Wholesale",
            "subcategory":"Machinery & Supplies",
            "type":"Manufacturing & Wholesale Goods"
        }
    ],
    "sg:phone":"+1 704 896 4000",
    "sg:postcode":"28036",
    "sg:province":"NC",
    "sg:tags":[
        "compressor",
        "gas"
    ],
    "sg:website":"www.irco.com",
    "wof:name":"Ingersoll-Rand Air Solutions",
    "wof:placetype":"venue"
},
  "geometry": {"coordinates":[-80.84200199999999,35.508652],"type":"Point"}
}