{
  "type": "Feature",
  "properties": {
    "addr:full":"3155 Dunlavin Way Charlotte NC 28205",
    "addr:housenumber":"3155",
    "addr:postcode":"28205",
    "addr:street":"Dunlavin Way",
    "iso:country":"US",
    "sg:address":"3155 Dunlavin Way",
    "sg:city":"Charlotte",
    "sg:classifiers":[
        {
            "category":"Retail",
            "subcategory":"Portrait Studio",
            "type":"Services"
        }
    ],
    "sg:phone":"+1   ",
    "sg:postcode":"28205",
    "sg:province":"NC",
    "sg:tags":[
        "photo"
    ],
    "wof:name":"David Brenizer Photography",
    "wof:placetype":"venue"
},
  "geometry": {"coordinates":[-80.77514600000001,35.23237],"type":"Point"}
}