{
  "type": "Feature",
  "properties": {
    "addr:full":"8301 University Executive Park Dr Charlotte NC 28262",
    "addr:housenumber":"8301",
    "addr:postcode":"28262",
    "addr:street":"University Executive Park Dr",
    "iso:country":"US",
    "sg:address":"8301 University Executive Park Dr",
    "sg:city":"Charlotte",
    "sg:classifiers":[
        {
            "category":"Education",
            "subcategory":"Special Training",
            "type":"Public Place"
        }
    ],
    "sg:phone":"+1 704 548 3910",
    "sg:postcode":"28262",
    "sg:province":"NC",
    "sg:tags":[
        "center"
    ],
    "sg:website":"www.educate.com",
    "wof:name":"Innovated Learning Concepts",
    "wof:placetype":"venue"
},
  "geometry": {"coordinates":[-80.754806,35.301016],"type":"Point"}
}