{
  "type": "Feature",
  "properties": {
    "iso:country":"US",
    "sg:address":"2900 Spring Forest Rd",
    "sg:city":"Raleigh",
    "sg:classifiers":[
        {
            "category":"Personal",
            "subcategory":"Beauty Salon",
            "type":"Services"
        }
    ],
    "sg:phone":"+1 919 876 8003",
    "sg:postcode":"27616",
    "sg:province":"NC",
    "wof:name":"Cathy Smith Hair Stylist",
    "wof:placetype":"venue"
},
  "geometry": {"coordinates":[-78.59250900000001,35.855956],"type":"Point"}
}