{
  "type": "Feature",
  "properties": {
    "iso:country":"US",
    "sg:address":"7900 Matthews-Mint Hill Rd",
    "sg:city":"Charlotte",
    "sg:classifiers":[
        {
            "category":"Building & Trades",
            "subcategory":"Plumbing",
            "type":"Services"
        }
    ],
    "sg:phone":"+1 704 545 8889",
    "sg:postcode":"28227",
    "sg:province":"NC",
    "sg:tags":[
        "conditioning",
        "air",
        "system",
        "contractor"
    ],
    "wof:name":"Air Comfort Svc Inc",
    "wof:placetype":"venue"
},
  "geometry": {"coordinates":[-80.648258,35.179522],"type":"Point"}
}