{
  "type": "Feature",
  "properties": {
    "addr:full":"176 N Main St Mooresville NC 28115",
    "addr:housenumber":"176",
    "addr:postcode":"28115",
    "addr:street":"N Main St",
    "iso:country":"US",
    "sg:address":"176 N Main St",
    "sg:city":"Mooresville",
    "sg:classifiers":[
        {
            "category":"Wholesale",
            "subcategory":"Durable Goods & Equipment",
            "type":"Manufacturing & Wholesale Goods"
        }
    ],
    "sg:phone":"+1 704 664 9684",
    "sg:postcode":"28115",
    "sg:province":"NC",
    "sg:tags":[
        "importer"
    ],
    "wof:name":"Simply Musik",
    "wof:placetype":"venue"
},
  "geometry": {"coordinates":[-80.81072,35.584032],"type":"Point"}
}