{
  "type": "Feature",
  "properties": {
    "addr:full":"914 Rowan Ave Salisbury NC 28146",
    "addr:housenumber":"914",
    "addr:postcode":"28146",
    "addr:street":"Rowan Ave",
    "iso:country":"US",
    "sg:address":"914 Rowan Ave",
    "sg:city":"Salisbury",
    "sg:classifiers":[
        {
            "category":"Retail",
            "subcategory":"Auto Repair",
            "type":"Services"
        }
    ],
    "sg:phone":"+1 704 637 1642",
    "sg:postcode":"28146",
    "sg:province":"NC",
    "sg:tags":[
        "repairing",
        "automobile"
    ],
    "wof:name":"Pepper's Garage",
    "wof:placetype":"venue"
},
  "geometry": {"coordinates":[-80.471969,35.648489],"type":"Point"}
}