{
  "type": "Feature",
  "properties": {
    "addr:full":"2118 Carolina Mill Rd Burlington NC 27217",
    "addr:housenumber":"2118",
    "addr:postcode":"27217",
    "addr:street":"Carolina Mill Rd",
    "iso:country":"US",
    "sg:address":"2118 Carolina Mill Rd",
    "sg:city":"Burlington",
    "sg:classifiers":[
        {
            "category":"Building & Trades",
            "subcategory":"Construction",
            "type":"Services"
        }
    ],
    "sg:phone":"+1 336 229 0908",
    "sg:postcode":"27217",
    "sg:province":"NC",
    "sg:tags":[
        "hanging",
        "contractor"
    ],
    "wof:name":"Carpenter Paint Co",
    "wof:placetype":"venue"
},
  "geometry": {"coordinates":[-79.410151,36.127274],"type":"Point"}
}