{
  "type": "Feature",
  "properties": {
    "iso:country":"US",
    "sg:address":"6420 Amsterdam Way",
    "sg:city":"Wilmington",
    "sg:classifiers":[
        {
            "category":"Professional",
            "subcategory":"Business Services",
            "type":"Services"
        }
    ],
    "sg:phone":"+1 910 763 4553",
    "sg:postcode":"28405",
    "sg:province":"NC",
    "sg:tags":[
        "water",
        "treatment"
    ],
    "sg:website":"www.ecowater.com",
    "wof:name":"Hydra Solutions Inc",
    "wof:placetype":"venue"
},
  "geometry": {"coordinates":[-77.847589,34.259929],"type":"Point"}
}