{
  "type": "Feature",
  "properties": {
    "iso:country":"US",
    "sg:address":"1011 Mountain Creek Rd",
    "sg:city":"Chapel Hill",
    "sg:classifiers":[
        {
            "category":"Education",
            "subcategory":"Dance Studio",
            "type":"Public Place"
        }
    ],
    "sg:phone":"+1   ",
    "sg:postcode":"27516",
    "sg:province":"NC",
    "wof:name":"Hillsborough School of Dance",
    "wof:placetype":"venue"
},
  "geometry": {"coordinates":[-79.083265,35.997967],"type":"Point"}
}