{
  "type": "Feature",
  "properties": {
    "addr:full":"106 E Love Mill Rd Whiteville NC 28472",
    "addr:housenumber":"106",
    "addr:postcode":"28472",
    "addr:street":"E Love Mill Rd",
    "iso:country":"US",
    "sg:address":"106 E Love Mill Rd",
    "sg:city":"Whiteville",
    "sg:classifiers":[
        {
            "category":"Wholesale",
            "subcategory":"Groceries",
            "type":"Manufacturing & Wholesale Goods"
        }
    ],
    "sg:phone":"+1 910 642 4404",
    "sg:postcode":"28472",
    "sg:province":"NC",
    "sg:tags":[
        "baker"
    ],
    "wof:name":"Merita Bread",
    "wof:placetype":"venue"
},
  "geometry": {"coordinates":[-78.717921,34.303173],"type":"Point"}
}