{
  "type": "Feature",
  "properties": {
    "addr:full":"1433 Major Hill Rd Snow Camp NC 27349",
    "addr:housenumber":"1433",
    "addr:postcode":"27349",
    "addr:street":"Major Hill Rd",
    "iso:country":"US",
    "sg:address":"1433 Major Hill Rd",
    "sg:city":"Snow Camp",
    "sg:classifiers":[
        {
            "category":"Professional",
            "subcategory":"Art Services",
            "type":"Services"
        }
    ],
    "sg:phone":"+1   ",
    "sg:postcode":"27349",
    "sg:province":"NC",
    "sg:tags":[
        "commercial",
        "design"
    ],
    "wof:name":"Kd Graphics & Design Inc",
    "wof:placetype":"venue"
},
  "geometry": {"coordinates":[-79.37974,35.879275],"type":"Point"}
}