{
  "type": "Feature",
  "properties": {
    "iso:country":"US",
    "sg:address":"3626 Latrobe Dr",
    "sg:city":"Charlotte",
    "sg:classifiers":[
        {
            "category":"Health Services",
            "subcategory":"Doctor",
            "type":"Services"
        }
    ],
    "sg:phone":"+1 704 377 3791",
    "sg:postcode":"28211",
    "sg:province":"NC",
    "sg:tags":[
        "medical"
    ],
    "wof:name":"Amir H Farahany MD",
    "wof:placetype":"venue"
},
  "geometry": {"coordinates":[-80.79817199999999,35.196437],"type":"Point"}
}