{
  "type": "Feature",
  "properties": {
    "addr:full":"117 N Adams St Durham NC 27703",
    "addr:housenumber":"117",
    "addr:postcode":"27703",
    "addr:street":"N Adams St",
    "iso:country":"US",
    "sg:address":"117 N Adams St",
    "sg:city":"Durham",
    "sg:classifiers":[
        {
            "category":"Building & Trades",
            "subcategory":"Landscaping Services",
            "type":"Services"
        }
    ],
    "sg:phone":"+1 919 596 2458",
    "sg:postcode":"27703",
    "sg:province":"NC",
    "wof:name":"Walters Landscaping",
    "wof:placetype":"venue"
},
  "geometry": {"coordinates":[-78.852059,35.990374],"type":"Point"}
}