{
  "type": "Feature",
  "properties": {
    "addr:full":"537 Hazel Mill Rd Asheville NC 28806",
    "addr:housenumber":"537",
    "addr:postcode":"28806",
    "addr:street":"Hazel Mill Rd",
    "iso:country":"US",
    "sg:address":"537 Hazel Mill Rd",
    "sg:city":"Asheville",
    "sg:classifiers":[
        {
            "category":"Building & Trades",
            "subcategory":"Electrical",
            "type":"Services"
        }
    ],
    "sg:phone":"+1 828 251 4288",
    "sg:postcode":"28806",
    "sg:province":"NC",
    "sg:tags":[
        "electric",
        "contractor"
    ],
    "wof:name":"Scope Service",
    "wof:placetype":"venue"
},
  "geometry": {"coordinates":[-82.60094700000001,35.595226],"type":"Point"}
}