{
  "type": "Feature",
  "properties": {
    "addr:full":"276 W 1st St Denton NC 27239",
    "addr:housenumber":"276",
    "addr:postcode":"27239",
    "addr:street":"W 1St St",
    "iso:country":"US",
    "sg:address":"276 W 1st St",
    "sg:city":"Denton",
    "sg:classifiers":[
        {
            "category":"Organizations",
            "subcategory":"Religious Organization",
            "type":"Services"
        }
    ],
    "sg:phone":"+1 336 859 3502",
    "sg:postcode":"27239",
    "sg:province":"NC",
    "sg:tags":[
        "church"
    ],
    "wof:name":"Central United Methodist Chr",
    "wof:placetype":"venue"
},
  "geometry": {"coordinates":[-80.118363,35.634877],"type":"Point"}
}