{
  "type": "Feature",
  "properties": {
    "iso:country":"US",
    "sg:address":"11235 Wildlife Rd",
    "sg:city":"Charlotte",
    "sg:classifiers":[
        {
            "category":"Organizations",
            "subcategory":"Community Association",
            "type":"Services"
        }
    ],
    "sg:phone":"+1 704 544 0201",
    "sg:postcode":"28278",
    "sg:province":"NC",
    "sg:tags":[
        "club"
    ],
    "wof:name":"Ballantyne Country Club",
    "wof:placetype":"venue"
},
  "geometry": {"coordinates":[-81.012157,35.136623],"type":"Point"}
}