{
  "type": "Feature",
  "properties": {
    "addr:full":"1289 Mills Rd Mt Olive NC 28365",
    "addr:housenumber":"1289",
    "addr:postcode":"28365",
    "addr:street":"Mills Rd",
    "iso:country":"US",
    "sg:address":"1289 Mills Rd",
    "sg:city":"Mt Olive",
    "sg:classifiers":[
        {
            "category":"Organizations",
            "subcategory":"Religious Organization",
            "type":"Services"
        }
    ],
    "sg:phone":"+1 919 689 2651",
    "sg:postcode":"28365",
    "sg:province":"NC",
    "sg:tags":[
        "church"
    ],
    "wof:name":"Rhodes Friends Meeting",
    "wof:placetype":"venue"
},
  "geometry": {"coordinates":[-78.12600999999999,35.263628],"type":"Point"}
}