{
  "type": "Feature",
  "properties": {
    "iso:country":"US",
    "sg:address":"3424 Belmont Blvd",
    "sg:city":"New Bern",
    "sg:classifiers":[
        {
            "category":"Organizations",
            "subcategory":"Religious Organization",
            "type":"Services"
        }
    ],
    "sg:phone":"+1 252 633 5880",
    "sg:postcode":"28562",
    "sg:province":"NC",
    "sg:tags":[
        "church"
    ],
    "wof:name":"True Vine Full Gospel",
    "wof:placetype":"venue"
},
  "geometry": {"coordinates":[-77.102093,35.126853],"type":"Point"}
}