{
  "type": "Feature",
  "properties": {
    "iso:country":"US",
    "sg:address":"118 E Main St",
    "sg:city":"Carrboro",
    "sg:classifiers":[
        {
            "category":"Professional",
            "type":"Services"
        }
    ],
    "sg:phone":"+1 919 969 8601",
    "sg:postcode":"27510",
    "sg:province":"NC",
    "sg:tags":[
        "establishment"
    ],
    "wof:name":"Nested Co",
    "wof:placetype":"venue"
},
  "geometry": {"coordinates":[-79.07046800000001,35.910577],"type":"Point"}
}