{
  "type": "Feature",
  "properties": {
    "iso:country":"US",
    "sg:address":"1916 Skibo Rd",
    "sg:city":"Fayetteville",
    "sg:classifiers":[
        {
            "category":"Personal",
            "subcategory":"Beauty Salon",
            "type":"Services"
        },
        {
            "category":"Personal",
            "subcategory":"Barber",
            "type":"Services"
        }
    ],
    "sg:phone":"+1 910 583 4635",
    "sg:postcode":"28314",
    "sg:province":"NC",
    "sg:tags":[
        "hair",
        "stylist"
    ],
    "wof:name":"On The Go Kutz LLC",
    "wof:placetype":"venue"
},
  "geometry": {"coordinates":[-78.96650699999999,35.068187],"type":"Point"}
}