{
  "type": "Feature",
  "properties": {
    "iso:country":"US",
    "sg:address":"1269 Light Rd",
    "sg:city":"Thomasville",
    "sg:classifiers":[
        {
            "category":"Retail",
            "subcategory":"Auto Repair",
            "type":"Services"
        }
    ],
    "sg:phone":"+1 336 476 3147",
    "sg:postcode":"27360",
    "sg:province":"NC",
    "sg:tags":[
        "repairing",
        "automobile"
    ],
    "wof:name":"L & L Automotive",
    "wof:placetype":"venue"
},
  "geometry": {"coordinates":[-80.107568,35.807967],"type":"Point"}
}