{
  "type": "Feature",
  "properties": {
    "addr:full":"550 Tate Rd Rural Hall NC 27045",
    "addr:housenumber":"550",
    "addr:postcode":"27045",
    "addr:street":"Tate Rd",
    "iso:country":"US",
    "sg:address":"550 Tate Rd",
    "sg:city":"Rural Hall",
    "sg:classifiers":[
        {
            "category":"Building & Trades",
            "subcategory":"Construction",
            "type":"Services"
        }
    ],
    "sg:phone":"+1 336 969 2544",
    "sg:postcode":"27045",
    "sg:province":"NC",
    "sg:tags":[
        "paint",
        "contractor"
    ],
    "wof:name":"Ron-Jon Paint & Wallpaper Inc",
    "wof:placetype":"venue"
},
  "geometry": {"coordinates":[-80.296536,36.255951],"type":"Point"}
}