{
  "type": "Feature",
  "properties": {
    "iso:country":"US",
    "sg:address":"4509 Creedmoor Rd",
    "sg:city":"Raleigh",
    "sg:classifiers":[
        {
            "category":"Organizations",
            "subcategory":"Political Organization",
            "type":"Services"
        }
    ],
    "sg:phone":"+1 919 881 9660",
    "sg:postcode":"27612",
    "sg:province":"NC",
    "wof:name":"Judge Beecher Gray Campaign",
    "wof:placetype":"venue"
},
  "geometry": {"coordinates":[-78.685536,35.840704],"type":"Point"}
}