{
  "type": "Feature",
  "properties": {
    "addr:full":"200 E Umstead St Durham NC 27707",
    "addr:housenumber":"200",
    "addr:postcode":"27707",
    "addr:street":"E Umstead St",
    "iso:country":"US",
    "sg:address":"200 E Umstead St",
    "sg:city":"Durham",
    "sg:classifiers":[
        {
            "category":"Government",
            "subcategory":"Office",
            "type":"Public Place"
        }
    ],
    "sg:phone":"+1 919 530 8508",
    "sg:postcode":"27707",
    "sg:province":"NC",
    "sg:tags":[
        "school",
        "program",
        "prevention"
    ],
    "wof:name":"New Horizons",
    "wof:placetype":"venue"
},
  "geometry": {"coordinates":[-78.901719,35.982748],"type":"Point"}
}