{
  "type": "Feature",
  "properties": {
    "addr:full":"400 Washington Dr Fayetteville NC 28301",
    "addr:housenumber":"400",
    "addr:postcode":"28301",
    "addr:street":"Washington Dr",
    "iso:country":"US",
    "sg:address":"400 Washington Dr",
    "sg:city":"Fayetteville",
    "sg:classifiers":[
        {
            "category":"Personal",
            "subcategory":"Beauty Salon",
            "type":"Services"
        }
    ],
    "sg:phone":"+1 910 485 8055",
    "sg:postcode":"28301",
    "sg:province":"NC",
    "wof:name":"Alpha & Omega Creations",
    "wof:placetype":"venue"
},
  "geometry": {"coordinates":[-78.88864100000001,35.061676],"type":"Point"}
}