{
  "type": "Feature",
  "properties": {
    "iso:country":"US",
    "sg:address":"5522 Chedworth Dr",
    "sg:city":"Charlotte",
    "sg:classifiers":[
        {
            "category":"Shopping",
            "subcategory":"Computers & Home Electronics",
            "type":"Retail Goods"
        }
    ],
    "sg:phone":"+1 704 529 5522",
    "sg:postcode":"28210",
    "sg:province":"NC",
    "wof:name":"Stereo Showcase",
    "wof:placetype":"venue"
},
  "geometry": {"coordinates":[-80.865585,35.155275],"type":"Point"}
}