{
  "type": "Feature",
  "properties": {
    "addr:full":"610 Sandy Bottom Rd Marshall NC 28753",
    "addr:housenumber":"610",
    "addr:postcode":"28753",
    "addr:street":"Sandy Bottom Rd",
    "iso:country":"US",
    "sg:address":"610 Sandy Bottom Rd",
    "sg:city":"Marshall",
    "sg:classifiers":[
        {
            "category":"Retail",
            "subcategory":"Auto Repair",
            "type":"Services"
        }
    ],
    "sg:phone":"+1   ",
    "sg:postcode":"28753",
    "sg:province":"NC",
    "sg:tags":[
        "towing"
    ],
    "wof:name":"David Marler",
    "wof:placetype":"venue"
},
  "geometry": {"coordinates":[-82.74315,35.855247],"type":"Point"}
}