{
  "type": "Feature",
  "properties": {
    "addr:full":"120 Century Place Blvd Kernersville NC 27284",
    "addr:housenumber":"120",
    "addr:postcode":"27284",
    "addr:street":"Century Place Blvd",
    "iso:country":"US",
    "sg:address":"120 Century Place Blvd",
    "sg:city":"Kernersville",
    "sg:classifiers":[
        {
            "category":"Restaurant",
            "type":"Food & Drink"
        }
    ],
    "sg:menulink":"http://www.allmenus.com/nc/kernersville/115800-quiznos-sub/menu/",
    "sg:phone":"+1 336 996 2227",
    "sg:postcode":"27284",
    "sg:province":"NC",
    "sg:tags":[
        "wrap",
        "american",
        "sandwich"
    ],
    "wof:name":"Quiznos Sub",
    "wof:placetype":"venue"
},
  "geometry": {"coordinates":[-80.095781,36.107712],"type":"Point"}
}