{
  "type": "Feature",
  "properties": {
    "addr:full":"11532 Shopton Rd W Charlotte NC 28278",
    "addr:postcode":"11532;28278",
    "addr:street":"Shopton Rd W",
    "iso:country":"US",
    "sg:address":"11532 Shopton Rd W",
    "sg:city":"Charlotte",
    "sg:classifiers":[
        {
            "category":"Retail",
            "subcategory":"Repair Shop",
            "type":"Services"
        }
    ],
    "sg:phone":"+1   ",
    "sg:postcode":"28278",
    "sg:province":"NC",
    "wof:name":"Western Iron Works",
    "wof:placetype":"venue"
},
  "geometry": {"coordinates":[-80.995244,35.148552],"type":"Point"}
}