{
  "type": "Feature",
  "properties": {
    "iso:country":"US",
    "sg:address":"4208 Six Forks Rd",
    "sg:city":"Raleigh",
    "sg:classifiers":[
        {
            "category":"Professional",
            "subcategory":"Accounting & Tax Preparation",
            "type":"Services"
        }
    ],
    "sg:phone":"+1 919 571 1345",
    "sg:postcode":"27609",
    "sg:province":"NC",
    "sg:tags":[
        "bookkeeping",
        "general"
    ],
    "wof:name":"M Ibrahim Accounting & Tax Ofc",
    "wof:placetype":"venue"
},
  "geometry": {"coordinates":[-78.641488,35.838096],"type":"Point"}
}