{
  "type": "Feature",
  "properties": {
    "iso:country":"US",
    "sg:address":"208 N College Ave",
    "sg:city":"Newton",
    "sg:classifiers":[
        {
            "category":"Banks & Credit Unions",
            "subcategory":"Bank",
            "type":"Services"
        }
    ],
    "sg:phone":"+1 828 464 0770",
    "sg:postcode":"28658",
    "sg:province":"NC",
    "sg:tags":[
        "loan",
        "real estate"
    ],
    "wof:name":"Charlie's Mortgage Co",
    "wof:placetype":"venue"
},
  "geometry": {"coordinates":[-81.220848,35.664918],"type":"Point"}
}