{
  "type": "Feature",
  "properties": {
    "addr:full":"7202 Wilkinson Blvd Belmont NC 28012",
    "addr:housenumber":"7202",
    "addr:postcode":"28012",
    "addr:street":"Wilkinson Blvd",
    "iso:country":"US",
    "sg:address":"7202 Wilkinson Blvd",
    "sg:city":"Belmont",
    "sg:classifiers":[
        {
            "category":"Professional",
            "subcategory":"Business Services",
            "type":"Services"
        }
    ],
    "sg:phone":"+1   ",
    "sg:postcode":"28012",
    "sg:province":"NC",
    "wof:name":"National Truck Sales & Leasing",
    "wof:placetype":"venue"
},
  "geometry": {"coordinates":[-81.019015,35.247823],"type":"Point"}
}