{
  "type": "Feature",
  "properties": {
    "iso:country":"US",
    "sg:address":"616 E Marion St",
    "sg:city":"Shelby",
    "sg:classifiers":[
        {
            "category":"Health Services",
            "subcategory":"Hospital",
            "type":"Services"
        }
    ],
    "sg:phone":"+1 704 484 2450",
    "sg:postcode":"28150",
    "sg:province":"NC",
    "sg:tags":[
        "mental"
    ],
    "wof:name":"Tanyi's Respite & Habilitation",
    "wof:placetype":"venue"
},
  "geometry": {"coordinates":[-81.528493,35.293741],"type":"Point"}
}