{
  "type": "Feature",
  "properties": {
    "iso:country":"US",
    "sg:address":"204 E Academy St",
    "sg:city":"Asheboro",
    "sg:classifiers":[
        {
            "category":"Government",
            "subcategory":"Office",
            "type":"Public Place"
        }
    ],
    "sg:phone":"+1 336 633 7205",
    "sg:postcode":"27203",
    "sg:province":"NC",
    "sg:tags":[
        "administrative",
        "program",
        "health"
    ],
    "wof:name":"Reimbursements",
    "wof:placetype":"venue"
},
  "geometry": {"coordinates":[-79.812208,35.703176],"type":"Point"}
}