{
  "type": "Feature",
  "properties": {
    "addr:full":"2213 Distribution Center Dr Charlotte NC 28269",
    "addr:housenumber":"2213",
    "addr:postcode":"28269",
    "addr:street":"Distribution Center Dr",
    "iso:country":"US",
    "sg:address":"2213 Distribution Center Dr",
    "sg:city":"Charlotte",
    "sg:classifiers":[
        {
            "category":"Retail",
            "subcategory":"Auto Rental",
            "type":"Services"
        }
    ],
    "sg:phone":"+1 704 494 0867",
    "sg:postcode":"28269",
    "sg:province":"NC",
    "sg:tags":[
        "renting",
        "truck",
        "leasing"
    ],
    "wof:name":"Ryder",
    "wof:placetype":"venue"
},
  "geometry": {"coordinates":[-80.835596,35.276522],"type":"Point"}
}