{
  "type": "Feature",
  "properties": {
    "iso:country":"US",
    "sg:address":"150 Hamby Rd",
    "sg:city":"Wilkesboro",
    "sg:classifiers":[
        {
            "category":"Building & Trades",
            "subcategory":"Landscaping Services",
            "type":"Services"
        }
    ],
    "sg:phone":"+1 336 667 1734",
    "sg:postcode":"28697",
    "sg:province":"NC",
    "wof:name":"H&H Lawn Svc",
    "wof:placetype":"venue"
},
  "geometry": {"coordinates":[-81.17084800000001,36.12441],"type":"Point"}
}