{
  "type": "Feature",
  "properties": {
    "addr:full":"503 Lowdermilk St Greensboro NC 27401",
    "addr:housenumber":"503",
    "addr:postcode":"27401",
    "addr:street":"Lowdermilk St",
    "iso:country":"US",
    "sg:address":"503 Lowdermilk St",
    "sg:city":"Greensboro",
    "sg:classifiers":[
        {
            "category":"Health Services",
            "subcategory":"Nursing And Care Facility",
            "type":"Services"
        },
        {
            "category":"Real Estate",
            "subcategory":"Real Estate Agent",
            "type":"Services"
        }
    ],
    "sg:phone":"+1 336 271 6543",
    "sg:postcode":"27401",
    "sg:province":"NC",
    "sg:tags":[
        "home"
    ],
    "wof:name":"Eli's Home",
    "wof:placetype":"venue"
},
  "geometry": {"coordinates":[-79.74579799999999,36.077322],"type":"Point"}
}