{
  "type": "Feature",
  "properties": {
    "iso:country":"US",
    "sg:address":"5337 Sandy Trail Dr",
    "sg:city":"Knightdale",
    "sg:classifiers":[
        {
            "category":"Professional",
            "subcategory":"Research",
            "type":"Services"
        }
    ],
    "sg:phone":"+1   ",
    "sg:postcode":"27545",
    "sg:province":"NC",
    "sg:tags":[
        "commercial",
        "physical"
    ],
    "wof:name":"Teletracting Technologies",
    "wof:placetype":"venue"
},
  "geometry": {"coordinates":[-78.461231,35.777678],"type":"Point"}
}