{
  "type": "Feature",
  "properties": {
    "iso:country":"US",
    "sg:address":"495 Beddard Farm Rd",
    "sg:city":"Snow Hill",
    "sg:phone":"+1 252 747 3957",
    "sg:postcode":"28580",
    "sg:province":"NC",
    "sg:tags":[
        "farm",
        "corn",
        "soybean",
        "cotton"
    ],
    "wof:name":"Stewart Beddard",
    "wof:placetype":"venue"
},
  "geometry": {"coordinates":[-77.597055,35.471541],"type":"Point"}
}