{
  "type": "Feature",
  "properties": {
    "addr:full":"1654 Faucette Rd Burlington NC 27215",
    "addr:housenumber":"1654",
    "addr:postcode":"27215",
    "addr:street":"Faucette Rd",
    "iso:country":"US",
    "sg:address":"1654 Faucette Rd",
    "sg:city":"Burlington",
    "sg:classifiers":[
        {
            "category":"Organizations",
            "subcategory":"Membership Organization",
            "type":"Services"
        }
    ],
    "sg:phone":"+1   ",
    "sg:postcode":"27215",
    "sg:province":"NC",
    "wof:name":"North Crolina Draft Hrse Mules",
    "wof:placetype":"venue"
},
  "geometry": {"coordinates":[-79.44851199999999,36.053987],"type":"Point"}
}