{
  "type": "Feature",
  "properties": {
    "iso:country":"US",
    "sg:address":"141 Haley Ln",
    "sg:city":"Thomasville",
    "sg:classifiers":[
        {
            "category":"Health Services",
            "subcategory":"Health Practitioner",
            "type":"Services"
        }
    ],
    "sg:phone":"+1   ",
    "sg:postcode":"27360",
    "sg:province":"NC",
    "wof:name":"Prn Inc PC",
    "wof:placetype":"venue"
},
  "geometry": {"coordinates":[-80.087856,35.818671],"type":"Point"}
}