{
  "type": "Feature",
  "properties": {
    "addr:full":"3114 Tripoli Dr Durham NC 27713",
    "addr:housenumber":"3114",
    "addr:postcode":"27713",
    "addr:street":"Tripoli Dr",
    "iso:country":"US",
    "sg:address":"3114 Tripoli Dr",
    "sg:city":"Durham",
    "sg:classifiers":[
        {
            "category":"Taxi",
            "type":"Transportation"
        }
    ],
    "sg:phone":"+1 919 605 2734",
    "sg:postcode":"27713",
    "sg:province":"NC",
    "sg:tags":[
        "taxicab"
    ],
    "wof:name":"Grays Taxi",
    "wof:placetype":"venue"
},
  "geometry": {"coordinates":[-78.910488,35.951794],"type":"Point"}
}