{
  "type": "Feature",
  "properties": {
    "addr:full":"136 E Holly Trl Kitty Hawk NC 27949",
    "addr:housenumber":"136",
    "addr:postcode":"27949",
    "addr:street":"E Holly Trl",
    "iso:country":"US",
    "sg:address":"136 E Holly Trl",
    "sg:city":"Kitty Hawk",
    "sg:classifiers":[
        {
            "category":"Banks & Credit Unions",
            "subcategory":"Financial Services",
            "type":"Services"
        }
    ],
    "sg:phone":"+1 252 261 8847",
    "sg:postcode":"27949",
    "sg:province":"NC",
    "sg:tags":[
        "investor"
    ],
    "wof:name":"Creative Investors",
    "wof:placetype":"venue"
},
  "geometry": {"coordinates":[-75.737751,36.121209],"type":"Point"}
}