{
  "type": "Feature",
  "properties": {
    "iso:country":"US",
    "sg:address":"22 W 2nd St",
    "sg:city":"Lexington",
    "sg:classifiers":[
        {
            "category":"Home & Garden",
            "subcategory":"Furniture",
            "type":"Retail Goods"
        }
    ],
    "sg:phone":"+1 336 224 1776",
    "sg:postcode":"27292",
    "sg:province":"NC",
    "wof:name":"Scumble Goosie",
    "wof:placetype":"venue"
},
  "geometry": {"coordinates":[-80.25308699999999,35.826082],"type":"Point"}
}