{
  "type": "Feature",
  "properties": {
    "iso:country":"US",
    "sg:address":"632 Abington Dr NE",
    "sg:city":"Concord",
    "sg:classifiers":[
        {
            "category":"Real Estate",
            "subcategory":"Real Estate Agent",
            "type":"Services"
        }
    ],
    "sg:phone":"+1 704 785 8204",
    "sg:postcode":"28025",
    "sg:province":"NC",
    "wof:name":"T David Propst Realty",
    "wof:placetype":"venue"
},
  "geometry": {"coordinates":[-80.57996199999999,35.4412],"type":"Point"}
}