{
  "type": "Feature",
  "properties": {
    "iso:country":"US",
    "sg:address":"522 Odum Dr",
    "sg:city":"Hubert",
    "sg:classifiers":[
        {
            "category":"Organizations",
            "subcategory":"Membership Organization",
            "type":"Services"
        }
    ],
    "sg:phone":"+1   ",
    "sg:postcode":"28539",
    "sg:province":"NC",
    "wof:name":"Carolina Animal Protection Soc",
    "wof:placetype":"venue"
},
  "geometry": {"coordinates":[-77.17152299999999,34.682955],"type":"Point"}
}