{
  "type": "Feature",
  "properties": {
    "addr:full":"115 Harbor Dr Cary NC 27551",
    "addr:housenumber":"115",
    "addr:postcode":"27551",
    "addr:street":"Harbor Dr",
    "iso:country":"US",
    "sg:address":"115 Harbor Dr",
    "sg:city":"Cary",
    "sg:classifiers":[
        {
            "category":"Communications",
            "subcategory":"Film & Video Production",
            "type":"Services"
        }
    ],
    "sg:phone":"+1 919 363 9558",
    "sg:postcode":"27551",
    "sg:province":"NC",
    "sg:tags":[
        "motion",
        "taping"
    ],
    "wof:name":"Moments In Motion Inc",
    "wof:placetype":"venue"
},
  "geometry": {"coordinates":[-78.02675499999999,36.525628],"type":"Point"}
}