{
  "type": "Feature",
  "properties": {
    "iso:country":"US",
    "sg:address":"209 Crowatan Rd",
    "sg:city":"Castle Hayne",
    "sg:classifiers":[
        {
            "category":"Manufacturing",
            "subcategory":"Building Materials",
            "type":"Manufacturing & Wholesale Goods"
        },
        {
            "category":"Building & Trades",
            "subcategory":"Construction",
            "type":"Services"
        }
    ],
    "sg:phone":"+1 910 675 3442",
    "sg:postcode":"28429",
    "sg:province":"NC",
    "sg:tags":[
        "cabinet",
        "wood",
        "maker",
        "kitchen",
        "mfg"
    ],
    "wof:name":"Bron Cabinet Shop",
    "wof:placetype":"venue"
},
  "geometry": {"coordinates":[-77.907876,34.328296],"type":"Point"}
}