{
  "type": "Feature",
  "properties": {
    "iso:country":"US",
    "sg:address":"504 Sign Pine Rd",
    "sg:city":"Tyner",
    "sg:classifiers":[
        {
            "category":"Retail",
            "subcategory":"Portrait Studio",
            "type":"Services"
        }
    ],
    "sg:phone":"+1 252 221 8019",
    "sg:postcode":"27980",
    "sg:province":"NC",
    "sg:tags":[
        "photographer",
        "photo"
    ],
    "wof:name":"Precious Moments Photography",
    "wof:placetype":"venue"
},
  "geometry": {"coordinates":[-76.62434500000001,36.30896],"type":"Point"}
}