{
  "type": "Feature",
  "properties": {
    "iso:country":"US",
    "sg:address":"1089 Ammons Branch Rd",
    "sg:city":"Marshall",
    "sg:classifiers":[
        {
            "category":"Building & Trades",
            "subcategory":"Construction",
            "type":"Services"
        }
    ],
    "sg:phone":"+1 828 649 0077",
    "sg:postcode":"28753",
    "sg:province":"NC",
    "sg:tags":[
        "paving",
        "contractor"
    ],
    "wof:name":"French Broad Paving Inc",
    "wof:placetype":"venue"
},
  "geometry": {"coordinates":[-82.650375,35.835298],"type":"Point"}
}