{
  "type": "Feature",
  "properties": {
    "addr:full":"141 Burslem Ln Cameron NC 28326",
    "addr:housenumber":"141",
    "addr:postcode":"28326",
    "addr:street":"Burslem Ln",
    "iso:country":"US",
    "sg:address":"141 Burslem Ln",
    "sg:city":"Cameron",
    "sg:classifiers":[
        {
            "category":"Freight",
            "type":"Transportation"
        }
    ],
    "sg:phone":"+1 919 499 6518",
    "sg:postcode":"28326",
    "sg:province":"NC",
    "sg:tags":[
        "truck",
        "hauling",
        "dump"
    ],
    "wof:name":"Roberts Grading",
    "wof:placetype":"venue"
},
  "geometry": {"coordinates":[-79.08007000000001,35.287213],"type":"Point"}
}