{
  "type": "Feature",
  "properties": {
    "iso:country":"US",
    "sg:address":"730 Blackwell St",
    "sg:city":"Fayetteville",
    "sg:classifiers":[
        {
            "category":"Organizations",
            "subcategory":"Religious Organization",
            "type":"Services"
        }
    ],
    "sg:phone":"+1 910 483 8918",
    "sg:postcode":"28312",
    "sg:province":"NC",
    "sg:tags":[
        "church"
    ],
    "wof:name":"Culbreth Mem United Mthdst Ch",
    "wof:placetype":"venue"
},
  "geometry": {"coordinates":[-78.844697,35.036702],"type":"Point"}
}