{
  "type": "Feature",
  "properties": {
    "addr:full":"2408 Maple Ave Burlington NC 27215",
    "addr:housenumber":"2408",
    "addr:postcode":"27215",
    "addr:street":"Maple Ave",
    "iso:country":"US",
    "sg:address":"2408 Maple Ave",
    "sg:city":"Burlington",
    "sg:classifiers":[
        {
            "category":"Home & Garden",
            "subcategory":"Carpets & Floor Coverings",
            "type":"Retail Goods"
        }
    ],
    "sg:phone":"+1 336 222 8161",
    "sg:postcode":"27215",
    "sg:province":"NC",
    "wof:name":"Floor Designs Unlimited",
    "wof:placetype":"venue"
},
  "geometry": {"coordinates":[-79.429975,36.065625],"type":"Point"}
}