{
  "type": "Feature",
  "properties": {
    "iso:country":"US",
    "sg:address":"4625 Yadkinville Rd",
    "sg:city":"Pfafftown",
    "sg:classifiers":[
        {
            "category":"Restaurant",
            "type":"Food & Drink"
        }
    ],
    "sg:phone":"+1 336 924 6553",
    "sg:postcode":"27040",
    "sg:province":"NC",
    "sg:tags":[
        "eating"
    ],
    "wof:name":"El Maguey Restaurant Inc",
    "wof:placetype":"venue"
},
  "geometry": {"coordinates":[-80.36152,36.152873],"type":"Point"}
}