{
  "type": "Feature",
  "properties": {
    "iso:country":"US",
    "sg:address":"325 N Marietta St",
    "sg:city":"Gastonia",
    "sg:classifiers":[
        {
            "category":"Government",
            "subcategory":"Office",
            "type":"Public Place"
        }
    ],
    "sg:phone":"+1 704 852 3128",
    "sg:postcode":"28052",
    "sg:province":"NC",
    "wof:name":"Court Reporters",
    "wof:placetype":"venue"
},
  "geometry": {"coordinates":[-81.181909,35.266678],"type":"Point"}
}