{
  "type": "Feature",
  "properties": {
    "iso:country":"US",
    "sg:address":"3521 Buena Vista Rd",
    "sg:city":"Winston Salem",
    "sg:classifiers":[
        {
            "category":"Farming",
            "subcategory":"Fish & Marine Products",
            "type":"Manufacturing & Wholesale Goods"
        }
    ],
    "sg:phone":"+1 336 722 7564",
    "sg:postcode":"27106",
    "sg:province":"NC",
    "sg:tags":[
        "management"
    ],
    "wof:name":"Teachers At Play LLC",
    "wof:placetype":"venue"
},
  "geometry": {"coordinates":[-80.29446900000001,36.11671],"type":"Point"}
}