{
  "type": "Feature",
  "properties": {
    "iso:country":"US",
    "sg:address":"1469 Chicken Bridge Rd",
    "sg:city":"Pittsboro",
    "sg:classifiers":[
        {
            "category":"Restaurant",
            "type":"Food & Drink"
        }
    ],
    "sg:phone":"+1 919 545 2077",
    "sg:postcode":"27312",
    "sg:province":"NC",
    "sg:tags":[
        "eating"
    ],
    "wof:name":"Chicken Bridge Pottery",
    "wof:placetype":"venue"
},
  "geometry": {"coordinates":[-79.21916,35.83216],"type":"Point"}
}