{
  "type": "Feature",
  "properties": {
    "addr:full":"3004 Wonderland Trl Conover NC 28613",
    "addr:housenumber":"3004",
    "addr:postcode":"28613",
    "addr:street":"Wonderland Trl",
    "iso:country":"US",
    "sg:address":"3004 Wonderland Trl",
    "sg:city":"Conover",
    "sg:classifiers":[
        {
            "category":"Restaurant",
            "type":"Food & Drink"
        }
    ],
    "sg:phone":"+1 828 465 1297",
    "sg:postcode":"28613",
    "sg:province":"NC",
    "sg:tags":[
        "eating"
    ],
    "wof:name":"Thai Lanna 2 Restaurant LLC",
    "wof:placetype":"venue"
},
  "geometry": {"coordinates":[-81.15486799999999,35.690707],"type":"Point"}
}