{
  "type": "Feature",
  "properties": {
    "iso:country":"US",
    "sg:address":"1401 Moonstone Dr",
    "sg:city":"Matthews",
    "sg:classifiers":[
        {
            "category":"Professional",
            "type":"Services"
        }
    ],
    "sg:phone":"+1   ",
    "sg:postcode":"28105",
    "sg:province":"NC",
    "wof:name":"Transcription Network Services",
    "wof:placetype":"venue"
},
  "geometry": {"coordinates":[-80.728459,35.098658],"type":"Point"}
}