{
  "type": "Feature",
  "properties": {
    "iso:country":"US",
    "sg:address":"2400 Old Lexington Rd",
    "sg:city":"Winston Salem",
    "sg:classifiers":[
        {
            "category":"Wholesale",
            "subcategory":"Groceries",
            "type":"Manufacturing & Wholesale Goods"
        }
    ],
    "sg:phone":"+1 336 784 9676",
    "sg:postcode":"27107",
    "sg:province":"NC",
    "sg:tags":[
        "baker"
    ],
    "wof:name":"B & G Pies",
    "wof:placetype":"venue"
},
  "geometry": {"coordinates":[-80.226872,36.066632],"type":"Point"}
}