{
  "type": "Feature",
  "properties": {
    "addr:full":"680 Greenville Hwy Brevard NC 28712",
    "addr:housenumber":"680",
    "addr:postcode":"28712",
    "addr:street":"Greenville Hwy",
    "iso:country":"US",
    "sg:address":"680 Greenville Hwy",
    "sg:city":"Brevard",
    "sg:classifiers":[
        {
            "category":"Professional",
            "subcategory":"Management & Consulting",
            "type":"Services"
        }
    ],
    "sg:phone":"+1   ",
    "sg:postcode":"28712",
    "sg:province":"NC",
    "sg:tags":[
        "business"
    ],
    "wof:name":"Bevuk Co",
    "wof:placetype":"venue"
},
  "geometry": {"coordinates":[-82.720378,35.2208],"type":"Point"}
}