{
  "type": "Feature",
  "properties": {
    "addr:full":"16116 Sunninghill Park Rd Charlotte NC 28277",
    "addr:housenumber":"16116",
    "addr:postcode":"28277",
    "addr:street":"Sunninghill Park Rd",
    "iso:country":"US",
    "sg:address":"16116 Sunninghill Park Rd",
    "sg:city":"Charlotte",
    "sg:classifiers":[
        {
            "category":"Wholesale",
            "subcategory":"Machinery & Supplies",
            "type":"Manufacturing & Wholesale Goods"
        }
    ],
    "sg:phone":"+1 704 522 7433",
    "sg:postcode":"28277",
    "sg:province":"NC",
    "sg:tags":[
        "equipment",
        "industrial"
    ],
    "wof:name":"Igus Bearings Inc",
    "wof:placetype":"venue"
},
  "geometry": {"coordinates":[-80.851838,35.033822],"type":"Point"}
}