{
  "type": "Feature",
  "properties": {
    "iso:country":"US",
    "sg:address":"2822 Glendale Rd",
    "sg:city":"Charlotte",
    "sg:classifiers":[
        {
            "category":"Wholesale",
            "subcategory":"Machinery & Supplies",
            "type":"Manufacturing & Wholesale Goods"
        }
    ],
    "sg:phone":"+1 704 372 5574",
    "sg:postcode":"28209",
    "sg:province":"NC",
    "sg:tags":[
        "fastener"
    ],
    "wof:name":"Illinois Tool Works Inc",
    "wof:placetype":"venue"
},
  "geometry": {"coordinates":[-80.839257,35.173147],"type":"Point"}
}