{
  "type": "Feature",
  "properties": {
    "iso:country":"US",
    "sg:address":"1894 US Hwy 220",
    "sg:city":"Ellerbe",
    "sg:classifiers":[
        {
            "category":"Autos & Motor Vehicles",
            "subcategory":"Automobile Sales",
            "type":"Retail Goods"
        }
    ],
    "sg:phone":"+1 910 652 3124",
    "sg:postcode":"28338",
    "sg:province":"NC",
    "sg:tags":[
        "car",
        "used",
        "dealer"
    ],
    "wof:name":"Clay's Cars",
    "wof:placetype":"venue"
},
  "geometry": {"coordinates":[-79.76853,35.056219],"type":"Point"}
}