{
  "type": "Feature",
  "properties": {
    "addr:full":"7328 Market St Wilmington NC 28411",
    "addr:housenumber":"7328",
    "addr:postcode":"28411",
    "addr:street":"Market St",
    "iso:country":"US",
    "sg:address":"7328 Market St",
    "sg:city":"Wilmington",
    "sg:classifiers":[
        {
            "category":"Retail",
            "subcategory":"Car Wash",
            "type":"Services"
        }
    ],
    "sg:phone":"+1 910 686 1615",
    "sg:postcode":"28411",
    "sg:province":"NC",
    "sg:tags":[
        "polishing",
        "washing"
    ],
    "wof:name":"Intracoastal Detailing",
    "wof:placetype":"venue"
},
  "geometry": {"coordinates":[-77.814646,34.276832],"type":"Point"}
}