{
  "type": "Feature",
  "properties": {
    "addr:full":"44 Boundary St Waynesville NC 28786",
    "addr:housenumber":"44",
    "addr:postcode":"28786",
    "addr:street":"Boundary St",
    "iso:country":"US",
    "sg:address":"44 Boundary St",
    "sg:city":"Waynesville",
    "sg:classifiers":[
        {
            "category":"Recreation",
            "type":"Entertainment"
        }
    ],
    "sg:phone":"+1   ",
    "sg:postcode":"28786",
    "sg:province":"NC",
    "wof:name":"Recreation Center",
    "wof:placetype":"venue"
},
  "geometry": {"coordinates":[-82.98886,35.494492],"type":"Point"}
}