{
  "type": "Feature",
  "properties": {
    "iso:country":"US",
    "sg:address":"261 Legion Hut Rd",
    "sg:city":"Carthage",
    "sg:classifiers":[
        {
            "category":"Building & Trades",
            "subcategory":"Pest Control",
            "type":"Services"
        }
    ],
    "sg:phone":"+1   ",
    "sg:postcode":"28327",
    "sg:province":"NC",
    "wof:name":"Moore County Exterminating Co",
    "wof:placetype":"venue"
},
  "geometry": {"coordinates":[-79.417534,35.312694],"type":"Point"}
}