{
  "type": "Feature",
  "properties": {
    "iso:country":"US",
    "sg:address":"416 E North Main St",
    "sg:city":"Waxhaw",
    "sg:classifiers":[
        {
            "category":"Place Of Worship",
            "subcategory":"Church",
            "type":"Public Place"
        },
        {
            "category":"Place Of Worship",
            "type":"Public Place"
        }
    ],
    "sg:phone":"+1 704 843 7411",
    "sg:postcode":"28173",
    "sg:province":"NC",
    "sg:tags":[
        "lutheran",
        "america",
        "churches-lutheran",
        "churches-lutheran-evangelical"
    ],
    "wof:name":"Amazing Grace Lutheran Church",
    "wof:placetype":"venue"
},
  "geometry": {"coordinates":[-80.739295,34.925305],"type":"Point"}
}