{
  "type": "Feature",
  "properties": {
    "addr:full":"848 W Craighead Rd Charlotte NC 28206",
    "addr:housenumber":"848",
    "addr:postcode":"28206",
    "addr:street":"W Craighead Rd",
    "iso:country":"US",
    "sg:address":"848 W Craighead Rd",
    "sg:city":"Charlotte",
    "sg:classifiers":[
        {
            "category":"Bus Charters",
            "type":"Transportation"
        }
    ],
    "sg:phone":"+1 704 598 2204",
    "sg:postcode":"28206",
    "sg:province":"NC",
    "sg:tags":[
        "rental"
    ],
    "wof:name":"Charlotte Party Charters",
    "wof:placetype":"venue"
},
  "geometry": {"coordinates":[-80.81375199999999,35.270318],"type":"Point"}
}