{
  "type": "Feature",
  "properties": {
    "addr:full":"294 Bennet Rd Goldsboro NC 27530",
    "addr:housenumber":"294",
    "addr:postcode":"27530",
    "addr:street":"Bennet Rd",
    "iso:country":"US",
    "sg:address":"294 Bennet Rd",
    "sg:city":"Goldsboro",
    "sg:classifiers":[
        {
            "category":"Utilities",
            "subcategory":"Refuse",
            "type":"Services"
        }
    ],
    "sg:phone":"+1 919 689 9999",
    "sg:postcode":"27530",
    "sg:province":"NC",
    "sg:tags":[
        "waste",
        "container"
    ],
    "wof:name":"Wayne County Waste",
    "wof:placetype":"venue"
},
  "geometry": {"coordinates":[-78.174311,35.305791],"type":"Point"}
}