{
  "type": "Feature",
  "properties": {
    "addr:full":"78 Woody Ct SW Concord NC 28025",
    "addr:housenumber":"78",
    "addr:postcode":"28025",
    "addr:street":"Woody Ct Sw",
    "iso:country":"US",
    "sg:address":"78 Woody Ct SW",
    "sg:city":"Concord",
    "sg:classifiers":[
        {
            "category":"Wholesale",
            "subcategory":"Construction Materials",
            "type":"Manufacturing & Wholesale Goods"
        }
    ],
    "sg:phone":"+1 704 795 0598",
    "sg:postcode":"28025",
    "sg:province":"NC",
    "sg:tags":[
        "marble"
    ],
    "wof:name":"Leonardos Marble & Granite",
    "wof:placetype":"venue"
},
  "geometry": {"coordinates":[-80.577718,35.401592],"type":"Point"}
}