{
  "type": "Feature",
  "properties": {
    "iso:country":"US",
    "sg:address":"4401 E Independence Blvd",
    "sg:city":"Charlotte",
    "sg:classifiers":[
        {
            "category":"Insurance",
            "subcategory":"Insurance Agent",
            "type":"Services"
        }
    ],
    "sg:phone":"+1 704 567 6500",
    "sg:postcode":"28205",
    "sg:province":"NC",
    "wof:name":"Allstate Insurance Co",
    "wof:placetype":"venue"
},
  "geometry": {"coordinates":[-80.76975299999999,35.198588],"type":"Point"}
}