{
  "type": "Feature",
  "properties": {
    "addr:full":"210 Westwood Dr Greenville NC 27834",
    "addr:housenumber":"210",
    "addr:postcode":"27834",
    "addr:street":"Westwood Dr",
    "iso:country":"US",
    "sg:address":"210 Westwood Dr",
    "sg:city":"Greenville",
    "sg:classifiers":[
        {
            "category":"Social Services",
            "subcategory":"Child Care",
            "type":"Services"
        }
    ],
    "sg:phone":"+1 252 758 3021",
    "sg:postcode":"27834",
    "sg:province":"NC",
    "sg:tags":[
        "center"
    ],
    "wof:name":"A Splash Of Learning Childcare",
    "wof:placetype":"venue"
},
  "geometry": {"coordinates":[-77.403127,35.598121],"type":"Point"}
}