{
  "type": "Feature",
  "properties": {
    "iso:country":"US",
    "sg:address":"1979 Hoods Creek Rd",
    "sg:city":"New Bern",
    "sg:classifiers":[
        {
            "category":"Home & Garden",
            "subcategory":"Building Materials",
            "type":"Retail Goods"
        }
    ],
    "sg:phone":"+1 252 636 0602",
    "sg:postcode":"28562",
    "sg:province":"NC",
    "sg:tags":[
        "glass",
        "window",
        "plate"
    ],
    "wof:name":"Glass Roots",
    "wof:placetype":"venue"
},
  "geometry": {"coordinates":[-77.081405,35.065809],"type":"Point"}
}