{
  "type": "Feature",
  "properties": {
    "addr:full":"170 Spring Meadows Rd Vanceboro NC 28586",
    "addr:housenumber":"170",
    "addr:postcode":"28586",
    "addr:street":"Spring Meadows Rd",
    "iso:country":"US",
    "sg:address":"170 Spring Meadows Rd",
    "sg:city":"Vanceboro",
    "sg:classifiers":[
        {
            "category":"Professional",
            "type":"Services"
        }
    ],
    "sg:phone":"+1 252 244 2482",
    "sg:postcode":"28586",
    "sg:province":"NC",
    "wof:name":"Earthsong Elementals",
    "wof:placetype":"venue"
},
  "geometry": {"coordinates":[-77.145988,35.251988],"type":"Point"}
}