{
  "type": "Feature",
  "properties": {
    "iso:country":"US",
    "sg:address":"1511 Dogwood Ln",
    "sg:city":"Kill Devil Hills",
    "sg:classifiers":[
        {
            "category":"Professional",
            "subcategory":"Business Services",
            "type":"Services"
        }
    ],
    "sg:phone":"+1   ",
    "sg:postcode":"27948",
    "sg:province":"NC",
    "wof:name":"All Star Pool & Spa Clg Svcs",
    "wof:placetype":"venue"
},
  "geometry": {"coordinates":[-75.679081,36.023627],"type":"Point"}
}