{
  "type": "Feature",
  "properties": {
    "addr:full":"1175 Main St Fair Bluff NC 28439",
    "addr:housenumber":"1175",
    "addr:postcode":"28439",
    "addr:street":"Main St",
    "iso:country":"US",
    "sg:address":"1175 Main St",
    "sg:city":"Fair Bluff",
    "sg:classifiers":[
        {
            "category":"Government",
            "subcategory":"Police Station",
            "type":"Public Place"
        }
    ],
    "sg:phone":"+1 910 649 7323",
    "sg:postcode":"28439",
    "sg:province":"NC",
    "sg:tags":[
        "department"
    ],
    "wof:name":"Fair Bluff Police Dept",
    "wof:placetype":"venue"
},
  "geometry": {"coordinates":[-79.036844,34.313427],"type":"Point"}
}