{
  "type": "Feature",
  "properties": {
    "iso:country":"US",
    "sg:address":"35 Ayugidv Ct",
    "sg:city":"Brevard",
    "sg:classifiers":[
        {
            "category":"Health Services",
            "subcategory":"Doctor",
            "type":"Services"
        }
    ],
    "sg:phone":"+1   ",
    "sg:postcode":"28712",
    "sg:province":"SC",
    "sg:tags":[
        "medical"
    ],
    "wof:name":"Harriet Marquis PHD Lcsw",
    "wof:placetype":"venue"
},
  "geometry": {"coordinates":[-82.768793,35.149],"type":"Point"}
}