{
  "type": "Feature",
  "properties": {
    "iso:country":"US",
    "sg:address":"32 Pine Hill Rd",
    "sg:city":"Fairview",
    "sg:classifiers":[
        {
            "category":"Building & Trades",
            "subcategory":"Plumbing",
            "type":"Services"
        }
    ],
    "sg:phone":"+1 828 628 4652",
    "sg:postcode":"28730",
    "sg:province":"NC",
    "sg:tags":[
        "air",
        "heating",
        "contractor",
        "system",
        "conditioning"
    ],
    "wof:name":"Stickels Service Company Inc",
    "wof:placetype":"venue"
},
  "geometry": {"coordinates":[-82.30027,35.523896],"type":"Point"}
}