{
  "type": "Feature",
  "properties": {
    "addr:full":"203 Muirs Chapel Rd Greensboro NC 27410",
    "addr:housenumber":"203",
    "addr:postcode":"27410",
    "addr:street":"Muirs Chapel Rd",
    "iso:country":"US",
    "sg:address":"203 Muirs Chapel Rd",
    "sg:city":"Greensboro",
    "sg:classifiers":[
        {
            "category":"Personal",
            "subcategory":"Beauty Salon",
            "type":"Services"
        }
    ],
    "sg:phone":"+1   ",
    "sg:postcode":"27410",
    "sg:province":"NC",
    "sg:tags":[
        "shop"
    ],
    "wof:name":"Aljills",
    "wof:placetype":"venue"
},
  "geometry": {"coordinates":[-79.86979100000001,36.071822],"type":"Point"}
}