{
  "type": "Feature",
  "properties": {
    "addr:full":"4539 Busbee Rd Seagrove NC 27341",
    "addr:housenumber":"4539",
    "addr:postcode":"27341",
    "addr:street":"Busbee Rd",
    "iso:country":"US",
    "sg:address":"4539 Busbee Rd",
    "sg:city":"Seagrove",
    "sg:classifiers":[
        {
            "category":"Home & Garden",
            "subcategory":"Home Furnishings",
            "type":"Retail Goods"
        }
    ],
    "sg:phone":"+1 910 464 3166",
    "sg:postcode":"27341",
    "sg:province":"NC",
    "sg:tags":[
        "pottery"
    ],
    "wof:name":"Hickory Hill Pottery Inc",
    "wof:placetype":"venue"
},
  "geometry": {"coordinates":[-79.673823,35.493107],"type":"Point"}
}