{
  "type": "Feature",
  "properties": {
    "iso:country":"US",
    "sg:address":"234 Market St",
    "sg:city":"Waynesville",
    "sg:classifiers":[
        {
            "category":"Building & Trades",
            "subcategory":"Construction",
            "type":"Services"
        }
    ],
    "sg:phone":"+1 828 648 0928",
    "sg:postcode":"28786",
    "sg:province":"NC",
    "sg:tags":[
        "house"
    ],
    "wof:name":"Medford Const Co",
    "wof:placetype":"venue"
},
  "geometry": {"coordinates":[-82.892314,35.473287],"type":"Point"}
}