{
  "type": "Feature",
  "properties": {
    "iso:country":"US",
    "sg:address":"4412 S Main St",
    "sg:city":"Winston Salem",
    "sg:classifiers":[
        {
            "category":"Freight",
            "type":"Transportation"
        }
    ],
    "sg:phone":"+1 336 784 0843",
    "sg:postcode":"27127",
    "sg:province":"NC",
    "sg:tags":[
        "mobile",
        "home"
    ],
    "wof:name":"Moore's Mobile Home Trnsprtng",
    "wof:placetype":"venue"
},
  "geometry": {"coordinates":[-80.24382300000001,36.028802],"type":"Point"}
}