{
  "type": "Feature",
  "properties": {
    "addr:full":"178 Soco Rd Maggie Valley NC 28751",
    "addr:housenumber":"178",
    "addr:postcode":"28751",
    "addr:street":"Soco Rd",
    "iso:country":"US",
    "sg:address":"178 Soco Rd",
    "sg:city":"Maggie Valley",
    "sg:classifiers":[
        {
            "category":"Travel",
            "subcategory":"Hotels & Motels",
            "type":"Entertainment"
        }
    ],
    "sg:phone":"+1   ",
    "sg:postcode":"28751",
    "sg:province":"NC",
    "sg:tags":[
        "operation"
    ],
    "sg:website":"www.scottishinn.com",
    "wof:name":"Scottish Inn",
    "wof:placetype":"venue"
},
  "geometry": {"coordinates":[-83.031299,35.52169],"type":"Point"}
}