{
  "type": "Feature",
  "properties": {
    "addr:full":"127 Holly Dr Grandy NC 27909",
    "addr:housenumber":"127",
    "addr:postcode":"27909",
    "addr:street":"Holly Dr",
    "iso:country":"US",
    "sg:address":"127 Holly Dr",
    "sg:city":"Grandy",
    "sg:classifiers":[
        {
            "category":"Building & Trades",
            "subcategory":"Construction",
            "type":"Services"
        }
    ],
    "sg:phone":"+1 252 453 6452",
    "sg:postcode":"27909",
    "sg:province":"NC",
    "sg:tags":[
        "contractor"
    ],
    "wof:name":"Outer Banks Roofing",
    "wof:placetype":"venue"
},
  "geometry": {"coordinates":[-76.22545700000001,36.33566],"type":"Point"}
}