{
  "type": "Feature",
  "properties": {
    "addr:full":"112 NC-102 W Ayden NC 28513",
    "addr:housenumber":"112",
    "addr:postcode":"28513",
    "addr:street":"Nc-102 W",
    "iso:country":"US",
    "sg:address":"112 NC-102 W",
    "sg:city":"Ayden",
    "sg:classifiers":[
        {
            "category":"Restaurant",
            "type":"Food & Drink"
        }
    ],
    "sg:menulink":"http://www.allmenus.com/nc/ayden/153158-bojangles/menu/",
    "sg:phone":"+1 252 746 1225",
    "sg:postcode":"28513",
    "sg:province":"NC",
    "sg:tags":[
        "chicken",
        "sandwich",
        "american"
    ],
    "wof:name":"Bojangle's",
    "wof:placetype":"venue"
},
  "geometry": {"coordinates":[-77.417469,35.471107],"type":"Point"}
}