{
  "type": "Feature",
  "properties": {
    "iso:country":"US",
    "sg:address":"3317 Cheswick Dr",
    "sg:city":"Raleigh",
    "sg:classifiers":[
        {
            "category":"Communications",
            "type":"Services"
        }
    ],
    "sg:phone":"+1 919 782 3200",
    "sg:postcode":"27609",
    "sg:province":"NC",
    "wof:name":"Toxicology Communications Inc",
    "wof:placetype":"venue"
},
  "geometry": {"coordinates":[-78.63073300000001,35.825948],"type":"Point"}
}