{
  "type": "Feature",
  "properties": {
    "addr:full":"109 Wellspring Dr Holly Springs NC 27540",
    "addr:housenumber":"109",
    "addr:postcode":"27540",
    "addr:street":"Wellspring Dr",
    "iso:country":"US",
    "sg:address":"109 Wellspring Dr",
    "sg:city":"Holly Springs",
    "sg:classifiers":[
        {
            "category":"Manufacturing",
            "subcategory":"Printing",
            "type":"Manufacturing & Wholesale Goods"
        }
    ],
    "sg:phone":"+1 919 363 9814",
    "sg:postcode":"27540",
    "sg:province":"NC",
    "sg:tags":[
        "multimedia"
    ],
    "wof:name":"Cyber Media Corp",
    "wof:placetype":"venue"
},
  "geometry": {"coordinates":[-78.82897199999999,35.672324],"type":"Point"}
}