{
  "type": "Feature",
  "properties": {
    "addr:full":"6105 Waxhaw Ct Raleigh NC 27616",
    "addr:postcode":"6105;27616",
    "addr:street":"Waxhaw Ct",
    "iso:country":"US",
    "sg:address":"6105 Waxhaw Ct",
    "sg:city":"Raleigh",
    "sg:classifiers":[
        {
            "category":"Home & Garden",
            "subcategory":"Building Materials",
            "type":"Retail Goods"
        }
    ],
    "sg:phone":"+1 919 790 9690",
    "sg:postcode":"27616",
    "sg:province":"NC",
    "sg:tags":[
        "modular"
    ],
    "wof:name":"Linda Miller Builder Sales",
    "wof:placetype":"venue"
},
  "geometry": {"coordinates":[-78.555014,35.862256],"type":"Point"}
}