{
  "type": "Feature",
  "properties": {
    "addr:full":"426 S Lee St Whiteville NC 28472",
    "addr:housenumber":"426",
    "addr:postcode":"28472",
    "addr:street":"S Lee St",
    "iso:country":"US",
    "sg:address":"426 S Lee St",
    "sg:city":"Whiteville",
    "sg:classifiers":[
        {
            "category":"Education",
            "subcategory":"School",
            "type":"Public Place"
        }
    ],
    "sg:phone":"+1 910 640 0855",
    "sg:postcode":"28472",
    "sg:province":"NC",
    "wof:name":"Philadelphia SDA Christian",
    "wof:placetype":"venue"
},
  "geometry": {"coordinates":[-78.70517100000001,34.325135],"type":"Point"}
}