{
  "type": "Feature",
  "properties": {
    "iso:country":"US",
    "sg:address":"3717 Elveden Rd",
    "sg:city":"New Bern",
    "sg:classifiers":[
        {
            "category":"Building & Trades",
            "subcategory":"Construction",
            "type":"Services"
        }
    ],
    "sg:phone":"+1 252 638 6653",
    "sg:postcode":"28562",
    "sg:province":"NC",
    "sg:tags":[
        "siding",
        "contractor"
    ],
    "wof:name":"Master Builders",
    "wof:placetype":"venue"
},
  "geometry": {"coordinates":[-77.104358,35.099906],"type":"Point"}
}