{
  "type": "Feature",
  "properties": {
    "addr:full":"819 Lakeview St Kannapolis NC 28083",
    "addr:housenumber":"819",
    "addr:postcode":"28083",
    "addr:street":"Lakeview St",
    "iso:country":"US",
    "sg:address":"819 Lakeview St",
    "sg:city":"Kannapolis",
    "sg:classifiers":[
        {
            "category":"Freight",
            "type":"Transportation"
        },
        {
            "category":"Personal",
            "type":"Services"
        }
    ],
    "sg:phone":"+1 704 938 8060",
    "sg:postcode":"28083",
    "sg:province":"NC",
    "sg:tags":[
        "commercial",
        "storage"
    ],
    "wof:name":"Harrington's Mini Storage",
    "wof:placetype":"venue"
},
  "geometry": {"coordinates":[-80.610231,35.491552],"type":"Point"}
}