{
  "type": "Feature",
  "properties": {
    "iso:country":"US",
    "sg:address":"136 Stutts Rd",
    "sg:city":"Mooresville",
    "sg:classifiers":[
        {
            "category":"Retail",
            "subcategory":"Animal Services",
            "type":"Services"
        }
    ],
    "sg:phone":"+1 704 663 3889",
    "sg:postcode":"28117",
    "sg:province":"NC",
    "sg:tags":[
        "pet",
        "grooming",
        "washing"
    ],
    "wof:name":"Four Paws Pet Salon",
    "wof:placetype":"venue"
},
  "geometry": {"coordinates":[-80.894462,35.543504],"type":"Point"}
}