{
  "type": "Feature",
  "properties": {
    "iso:country":"US",
    "sg:address":"645 Pressley Rd",
    "sg:city":"Charlotte",
    "sg:classifiers":[
        {
            "category":"Professional",
            "subcategory":"Business Services",
            "type":"Services"
        }
    ],
    "sg:phone":"+1 704 523 7713",
    "sg:postcode":"28217",
    "sg:province":"NC",
    "sg:tags":[
        "recording",
        "studio"
    ],
    "wof:name":"Wireknot Productions LTD",
    "wof:placetype":"venue"
},
  "geometry": {"coordinates":[-80.89256399999999,35.188807],"type":"Point"}
}