{
  "type": "Feature",
  "properties": {
    "iso:country":"US",
    "sg:address":"200 N Leslie St",
    "sg:city":"Goldsboro",
    "sg:classifiers":[
        {
            "category":"Health Services",
            "subcategory":"Doctor",
            "type":"Services"
        }
    ],
    "sg:phone":"+1 919 735 0124",
    "sg:postcode":"27530",
    "sg:province":"NC",
    "sg:tags":[
        "dentist"
    ],
    "wof:name":"Joseph A Marchese Jr Pa",
    "wof:placetype":"venue"
},
  "geometry": {"coordinates":[-77.98617299999999,35.38294],"type":"Point"}
}