{
  "type": "Feature",
  "properties": {
    "iso:country":"US",
    "sg:address":"839 State Hwy 105 Byp",
    "sg:city":"Boone",
    "sg:classifiers":[
        {
            "category":"Retail",
            "subcategory":"Auto Repair",
            "type":"Services"
        }
    ],
    "sg:phone":"+1 828 297 6211",
    "sg:postcode":"28607",
    "sg:province":"NC",
    "sg:tags":[
        "automotive",
        "general",
        "sup"
    ],
    "wof:name":"Alternator and Starter",
    "wof:placetype":"venue"
},
  "geometry": {"coordinates":[-81.71763900000001,36.220386],"type":"Point"}
}