{
  "type": "Feature",
  "properties": {
    "iso:country":"US",
    "sg:address":"108 S Gaston St",
    "sg:city":"Kings Mountain",
    "sg:classifiers":[
        {
            "category":"Education",
            "subcategory":"Special Training",
            "type":"Public Place"
        }
    ],
    "sg:phone":"+1   ",
    "sg:postcode":"28086",
    "sg:province":"NC",
    "wof:name":"Km Driving School Inc",
    "wof:placetype":"venue"
},
  "geometry": {"coordinates":[-81.340429,35.240734],"type":"Point"}
}