{
  "type": "Feature",
  "properties": {
    "iso:country":"US",
    "sg:address":"6780 Market St",
    "sg:city":"Wilmington",
    "sg:classifiers":[
        {
            "category":"Recreation",
            "type":"Entertainment"
        }
    ],
    "sg:phone":"+1   ",
    "sg:postcode":"28405",
    "sg:province":"NC",
    "wof:name":"Exchange Club of Lower Cape",
    "wof:placetype":"venue"
},
  "geometry": {"coordinates":[-77.836969,34.258022],"type":"Point"}
}