{
  "type": "Feature",
  "properties": {
    "iso:country":"US",
    "sg:address":"183 W Main St",
    "sg:city":"Washington",
    "sg:classifiers":[
        {
            "category":"Shopping",
            "subcategory":"Jewelry",
            "type":"Retail Goods"
        }
    ],
    "sg:phone":"+1 252 946 6489",
    "sg:postcode":"27889",
    "sg:province":"NC",
    "wof:name":"Washington Jewelers",
    "wof:placetype":"venue"
},
  "geometry": {"coordinates":[-77.056883,35.542813],"type":"Point"}
}