{
  "type": "Feature",
  "properties": {
    "addr:full":"206 Colonades Way Cary NC 27518",
    "addr:housenumber":"206",
    "addr:postcode":"27518",
    "addr:street":"Colonades Way",
    "iso:country":"US",
    "sg:address":"206 Colonades Way",
    "sg:city":"Cary",
    "sg:classifiers":[
        {
            "category":"Shopping",
            "subcategory":"Used Merchandise",
            "type":"Retail Goods"
        }
    ],
    "sg:phone":"+1 919 851 5300",
    "sg:postcode":"27518",
    "sg:province":"NC",
    "sg:tags":[
        "antique"
    ],
    "wof:name":"Treillage Antiques & Interiors",
    "wof:placetype":"venue"
},
  "geometry": {"coordinates":[-78.778925,35.738869],"type":"Point"}
}