{
  "type": "Feature",
  "properties": {
    "iso:country":"US",
    "sg:address":"1415 29th Avenue Dr NE",
    "sg:city":"Hickory",
    "sg:classifiers":[
        {
            "category":"Personal",
            "type":"Services"
        }
    ],
    "sg:phone":"+1   ",
    "sg:postcode":"28601",
    "sg:province":"NC",
    "wof:name":"Caribbean Tan",
    "wof:placetype":"venue"
},
  "geometry": {"coordinates":[-81.306539,35.76632],"type":"Point"}
}