{
  "type": "Feature",
  "properties": {
    "iso:country":"US",
    "sg:address":"325 Hasty School Rd",
    "sg:city":"Thomasville",
    "sg:classifiers":[
        {
            "category":"Education",
            "subcategory":"School",
            "type":"Public Place"
        }
    ],
    "sg:phone":"+1 336 475 1924",
    "sg:postcode":"27360",
    "sg:province":"NC",
    "sg:tags":[
        "elementary"
    ],
    "sg:website":"www.davidson.k12.nc.us",
    "wof:name":"Hasty Elementary School",
    "wof:placetype":"venue"
},
  "geometry": {"coordinates":[-80.08332,35.921319],"type":"Point"}
}