{
  "type": "Feature",
  "properties": {
    "addr:full":"243 Broad St Milton NC 27305",
    "addr:housenumber":"243",
    "addr:postcode":"27305",
    "addr:street":"Broad St",
    "iso:country":"US",
    "sg:address":"243 Broad St",
    "sg:city":"Milton",
    "sg:classifiers":[
        {
            "category":"Shopping",
            "subcategory":"Used Merchandise",
            "type":"Retail Goods"
        }
    ],
    "sg:phone":"+1 336 234 0102",
    "sg:postcode":"27305",
    "sg:province":"NC",
    "sg:tags":[
        "antique"
    ],
    "wof:name":"Milton Antiques",
    "wof:placetype":"venue"
},
  "geometry": {"coordinates":[-79.20419800000001,36.53856],"type":"Point"}
}