{
  "type": "Feature",
  "properties": {
    "iso:country":"US",
    "sg:address":"95 Salola St",
    "sg:city":"Asheville",
    "sg:classifiers":[
        {
            "category":"Building & Trades",
            "subcategory":"Electrical",
            "type":"Services"
        }
    ],
    "sg:phone":"+1 828 251 1514",
    "sg:postcode":"28806",
    "sg:province":"NC",
    "sg:tags":[
        "electric",
        "contractor"
    ],
    "wof:name":"4th Generation Electric",
    "wof:placetype":"venue"
},
  "geometry": {"coordinates":[-82.607658,35.572281],"type":"Point"}
}