{
  "type": "Feature",
  "properties": {
    "iso:country":"US",
    "sg:address":"2900 Allred Rd",
    "sg:city":"Lexington",
    "sg:classifiers":[
        {
            "category":"Organizations",
            "subcategory":"Religious Organization",
            "type":"Services"
        }
    ],
    "sg:phone":"+1 336 746 4324",
    "sg:postcode":"27292",
    "sg:province":"NC",
    "sg:tags":[
        "clergy"
    ],
    "wof:name":"Donald M Leonard",
    "wof:placetype":"venue"
},
  "geometry": {"coordinates":[-80.187291,35.761117],"type":"Point"}
}