{
  "type": "Feature",
  "properties": {
    "addr:full":"523 N Main St Fuquay Varina NC 27526",
    "addr:housenumber":"523",
    "addr:postcode":"27526",
    "addr:street":"N Main St",
    "iso:country":"US",
    "sg:address":"523 N Main St",
    "sg:city":"Fuquay Varina",
    "sg:classifiers":[
        {
            "category":"Social Services",
            "subcategory":"Child Care",
            "type":"Services"
        }
    ],
    "sg:phone":"+1 919 552 8915",
    "sg:postcode":"27526",
    "sg:province":"NC",
    "wof:name":"For Young Minds Child Devmnt",
    "wof:placetype":"venue"
},
  "geometry": {"coordinates":[-78.799059,35.589542],"type":"Point"}
}