{
  "type": "Feature",
  "properties": {
    "addr:full":"5124 Locust Ct Kitty Hawk NC 27949",
    "addr:housenumber":"5124",
    "addr:postcode":"27949",
    "addr:street":"Locust Ct",
    "iso:country":"US",
    "sg:address":"5124 Locust Ct",
    "sg:city":"Kitty Hawk",
    "sg:classifiers":[
        {
            "category":"Retail",
            "subcategory":"Auto Repair",
            "type":"Services"
        }
    ],
    "sg:phone":"+1 252 261 5089",
    "sg:postcode":"27949",
    "sg:province":"NC",
    "sg:tags":[
        "repairing",
        "automobile"
    ],
    "wof:name":"Mobile Services Mobile Auto",
    "wof:placetype":"venue"
},
  "geometry": {"coordinates":[-75.724924,36.093338],"type":"Point"}
}