{
  "type": "Feature",
  "properties": {
    "iso:country":"US",
    "sg:address":"215 Blowing Rock Blvd",
    "sg:city":"Lenoir",
    "sg:classifiers":[
        {
            "category":"Food & Beverages",
            "subcategory":"Groceries & Convenience Stores",
            "type":"Retail Goods"
        }
    ],
    "sg:phone":"+1 828 754 6863",
    "sg:postcode":"28645",
    "sg:province":"NC",
    "wof:name":"Fastop Food Mart 301",
    "wof:placetype":"venue"
},
  "geometry": {"coordinates":[-81.525002,35.914833],"type":"Point"}
}