{
  "type": "Feature",
  "properties": {
    "addr:full":"2230 Cloister Dr Charlotte NC 28211",
    "addr:housenumber":"2230",
    "addr:postcode":"28211",
    "addr:street":"Cloister Dr",
    "iso:country":"US",
    "sg:address":"2230 Cloister Dr",
    "sg:city":"Charlotte",
    "sg:classifiers":[
        {
            "category":"Professional",
            "type":"Services"
        }
    ],
    "sg:phone":"+1 704 366 8774",
    "sg:postcode":"28211",
    "sg:province":"NC",
    "wof:name":"Colleen Gentry Inc",
    "wof:placetype":"venue"
},
  "geometry": {"coordinates":[-80.80689,35.157365],"type":"Point"}
}