{
  "type": "Feature",
  "properties": {
    "iso:country":"US",
    "sg:address":"17111 Kenton Dr",
    "sg:city":"Cornelius",
    "sg:classifiers":[
        {
            "category":"Real Estate",
            "subcategory":"Developer",
            "type":"Services"
        }
    ],
    "sg:phone":"+1 704 987 3391",
    "sg:postcode":"28031",
    "sg:province":"NC",
    "wof:name":"North State Partners",
    "wof:placetype":"venue"
},
  "geometry": {"coordinates":[-80.889589,35.449339],"type":"Point"}
}