{
  "type": "Feature",
  "properties": {
    "addr:full":"409 Tynemouth Dr Cary NC 27513",
    "addr:housenumber":"409",
    "addr:postcode":"27513",
    "addr:street":"Tynemouth Dr",
    "iso:country":"US",
    "sg:address":"409 Tynemouth Dr",
    "sg:city":"Cary",
    "sg:classifiers":[
        {
            "category":"Professional",
            "type":"Services"
        }
    ],
    "sg:phone":"+1 919 677 7875",
    "sg:postcode":"27513",
    "sg:province":"NC",
    "wof:name":"ATI Technologies",
    "wof:placetype":"venue"
},
  "geometry": {"coordinates":[-78.784255,35.828464],"type":"Point"}
}