{
  "type": "Feature",
  "properties": {
    "addr:full":"5471 Central Ave Charlotte NC 28212",
    "addr:housenumber":"5471",
    "addr:postcode":"28212",
    "addr:street":"Central Ave",
    "iso:country":"US",
    "sg:address":"5471 Central Ave",
    "sg:city":"Charlotte",
    "sg:classifiers":[
        {
            "category":"Restaurant",
            "type":"Food & Drink"
        }
    ],
    "sg:phone":"+1 704 531 4900",
    "sg:postcode":"28212",
    "sg:province":"NC",
    "sg:tags":[
        "shop",
        "coffee",
        "eating"
    ],
    "wof:name":"Le Cafe & Juice",
    "wof:placetype":"venue"
},
  "geometry": {"coordinates":[-80.753671,35.207914],"type":"Point"}
}