{
  "type": "Feature",
  "properties": {
    "addr:full":"2454 Remus Rd Charlotte NC 28203",
    "addr:housenumber":"2454",
    "addr:postcode":"28203",
    "addr:street":"Remus Rd",
    "iso:country":"US",
    "sg:address":"2454 Remus Rd",
    "sg:city":"Charlotte",
    "sg:classifiers":[
        {
            "category":"Organizations",
            "subcategory":"Religious Organization",
            "type":"Services"
        }
    ],
    "sg:phone":"+1 704 333 4818",
    "sg:postcode":"28203",
    "sg:province":"NC",
    "sg:tags":[
        "church"
    ],
    "wof:name":"South Tryon Community Church",
    "wof:placetype":"venue"
},
  "geometry": {"coordinates":[-80.869559,35.20864],"type":"Point"}
}