{
  "type": "Feature",
  "properties": {
    "iso:country":"US",
    "sg:address":"1806 Robinwood Village Dr",
    "sg:city":"Gastonia",
    "sg:classifiers":[
        {
            "category":"Building & Trades",
            "subcategory":"Construction",
            "type":"Services"
        }
    ],
    "sg:phone":"+1 704 867 5274",
    "sg:postcode":"28054",
    "sg:province":"NC",
    "sg:tags":[
        "windows",
        "siding"
    ],
    "wof:name":"Bobby Lunsfords Siding Windows",
    "wof:placetype":"venue"
},
  "geometry": {"coordinates":[-81.14794000000001,35.241569],"type":"Point"}
}