{
  "type": "Feature",
  "properties": {
    "iso:country":"US",
    "sg:address":"1555 Cain Rd",
    "sg:city":"Fayetteville",
    "sg:classifiers":[
        {
            "category":"Insurance",
            "subcategory":"Insurance Agent",
            "type":"Services"
        }
    ],
    "sg:phone":"+1 910 822 6676",
    "sg:postcode":"28303",
    "sg:province":"NC",
    "wof:name":"State Farm Insurance",
    "wof:placetype":"venue"
},
  "geometry": {"coordinates":[-78.926665,35.088318],"type":"Point"}
}