{
  "type": "Feature",
  "properties": {
    "iso:country":"US",
    "sg:address":"5807 Pointer Dr",
    "sg:city":"Raleigh",
    "sg:classifiers":[
        {
            "category":"Building & Trades",
            "subcategory":"Cleaning & Sanitation",
            "type":"Services"
        }
    ],
    "sg:phone":"+1   ",
    "sg:postcode":"27609",
    "sg:province":"NC",
    "sg:tags":[
        "maintenance"
    ],
    "wof:name":"Ansel Janitorial Services",
    "wof:placetype":"venue"
},
  "geometry": {"coordinates":[-78.60786299999999,35.853243],"type":"Point"}
}