{
  "type": "Feature",
  "properties": {
    "addr:full":"2000 Perimeter Park Dr Morrisville NC 27560",
    "addr:housenumber":"2000",
    "addr:postcode":"27560",
    "addr:street":"Perimeter Park Dr",
    "iso:country":"US",
    "sg:address":"2000 Perimeter Park Dr",
    "sg:city":"Morrisville",
    "sg:classifiers":[
        {
            "category":"Professional",
            "subcategory":"Computer Services",
            "type":"Services"
        }
    ],
    "sg:phone":"+1 919 376 1339",
    "sg:postcode":"27560",
    "sg:province":"NC",
    "sg:tags":[
        "consultant",
        "technology"
    ],
    "wof:name":"Collegis Inc",
    "wof:placetype":"venue"
},
  "geometry": {"coordinates":[-78.82974,35.851713],"type":"Point"}
}