{
  "type": "Feature",
  "properties": {
    "iso:country":"US",
    "sg:address":"55 Old Hwy 64 W",
    "sg:city":"Hayesville",
    "sg:classifiers":[
        {
            "category":"Wholesale",
            "subcategory":"Machinery & Supplies",
            "type":"Manufacturing & Wholesale Goods"
        }
    ],
    "sg:phone":"+1 828 389 8868",
    "sg:postcode":"28904",
    "sg:province":"NC",
    "sg:tags":[
        "crane",
        "derrick"
    ],
    "wof:name":"Kenneth Swanson Builder",
    "wof:placetype":"venue"
},
  "geometry": {"coordinates":[-83.833765,35.034523],"type":"Point"}
}