{
  "type": "Feature",
  "properties": {
    "iso:country":"US",
    "sg:address":"3200 N Davidson St",
    "sg:city":"Charlotte",
    "sg:classifiers":[
        {
            "category":"Shopping",
            "type":"Retail Goods"
        }
    ],
    "sg:phone":"+1 704 358 8882",
    "sg:postcode":"28205",
    "sg:province":"NC",
    "sg:tags":[
        "picture",
        "frame",
        "merchandise"
    ],
    "wof:name":"Art Preserve The",
    "wof:placetype":"venue"
},
  "geometry": {"coordinates":[-80.804559,35.247688],"type":"Point"}
}