{
  "type": "Feature",
  "properties": {
    "addr:full":"4702 Arendell St Morehead City NC 28557",
    "addr:housenumber":"4702",
    "addr:postcode":"28557",
    "addr:street":"Arendell St",
    "iso:country":"US",
    "sg:address":"4702 Arendell St",
    "sg:city":"Morehead City",
    "sg:classifiers":[
        {
            "category":"Shopping",
            "subcategory":"Florist",
            "type":"Retail Goods"
        }
    ],
    "sg:phone":"+1 252 247 3323",
    "sg:postcode":"28557",
    "sg:province":"NC",
    "wof:name":"Sandy's Flower Shoppe",
    "wof:placetype":"venue"
},
  "geometry": {"coordinates":[-76.784494,34.732623],"type":"Point"}
}