{
  "type": "Feature",
  "properties": {
    "iso:country":"US",
    "sg:address":"8513 Powis Cir",
    "sg:city":"Raleigh",
    "sg:classifiers":[
        {
            "category":"Professional",
            "subcategory":"Management & Consulting",
            "type":"Services"
        }
    ],
    "sg:phone":"+1   ",
    "sg:postcode":"27615",
    "sg:province":"NC",
    "sg:tags":[
        "educational",
        "technology"
    ],
    "wof:name":"Clarity Solutions Inc",
    "wof:placetype":"venue"
},
  "geometry": {"coordinates":[-78.588189,35.895629],"type":"Point"}
}