{
  "type": "Feature",
  "properties": {
    "iso:country":"US",
    "sg:address":"5807 Horseshoe Dr",
    "sg:city":"Raleigh",
    "sg:classifiers":[
        {
            "category":"Real Estate",
            "subcategory":"Real Estate Operator",
            "type":"Services"
        }
    ],
    "sg:phone":"+1 919 772 1643",
    "sg:postcode":"27603",
    "sg:province":"NC",
    "sg:tags":[
        "mobile",
        "home",
        "site",
        "community"
    ],
    "wof:name":"Horseshoe Mobile Home Comm",
    "wof:placetype":"venue"
},
  "geometry": {"coordinates":[-78.68517799999999,35.700319],"type":"Point"}
}