{
  "type": "Feature",
  "properties": {
    "iso:country":"US",
    "sg:address":"174 Marshburn Rd",
    "sg:city":"Teachey",
    "sg:phone":"+1 910 289 3544",
    "sg:postcode":"28464",
    "sg:province":"NC",
    "sg:tags":[
        "farm",
        "tobacco"
    ],
    "wof:name":"Brown Farms",
    "wof:placetype":"venue"
},
  "geometry": {"coordinates":[-78.053372,34.790212],"type":"Point"}
}