{
  "type": "Feature",
  "properties": {
    "iso:country":"US",
    "sg:address":"430 Haled St",
    "sg:city":"Winston Salem",
    "sg:classifiers":[
        {
            "category":"Home & Garden",
            "subcategory":"Garden Supply",
            "type":"Retail Goods"
        }
    ],
    "sg:phone":"+1 336 722 9333",
    "sg:postcode":"27127",
    "sg:province":"NC",
    "sg:tags":[
        "farm"
    ],
    "wof:name":"Bills Lawn & Garden Center",
    "wof:placetype":"venue"
},
  "geometry": {"coordinates":[-80.22938000000001,36.071338],"type":"Point"}
}