{
  "type": "Feature",
  "properties": {
    "iso:country":"US",
    "sg:address":"120 Jackson Store Rd",
    "sg:city":"Beulaville",
    "sg:classifiers":[
        {
            "category":"Freight",
            "type":"Transportation"
        }
    ],
    "sg:phone":"+1 910 298 4172",
    "sg:postcode":"28518",
    "sg:province":"NC",
    "sg:tags":[
        "operator",
        "local",
        "trucking"
    ],
    "wof:name":"Wj Jones Trucking",
    "wof:placetype":"venue"
},
  "geometry": {"coordinates":[-77.83198299999999,34.906174],"type":"Point"}
}