{
  "type": "Feature",
  "properties": {
    "addr:full":"909 E 5th St Tabor City NC 28463",
    "addr:housenumber":"909",
    "addr:postcode":"28463",
    "addr:street":"E 5Th St",
    "iso:country":"US",
    "sg:address":"909 E 5th St",
    "sg:city":"Tabor City",
    "sg:classifiers":[
        {
            "category":"Autos & Motor Vehicles",
            "subcategory":"Automobile Sales",
            "type":"Retail Goods"
        }
    ],
    "sg:phone":"+1 910 653 2143",
    "sg:postcode":"28463",
    "sg:province":"NC",
    "sg:tags":[
        "car",
        "dealer"
    ],
    "wof:name":"Twin State Motor Sales",
    "wof:placetype":"venue"
},
  "geometry": {"coordinates":[-78.864525,34.154346],"type":"Point"}
}