{
  "type": "Feature",
  "properties": {
    "addr:full":"1141 Greenville Hwy Hendersonville NC 28792",
    "addr:housenumber":"1141",
    "addr:postcode":"28792",
    "addr:street":"Greenville Hwy",
    "iso:country":"US",
    "sg:address":"1141 Greenville Hwy",
    "sg:city":"Hendersonville",
    "sg:classifiers":[
        {
            "category":"Professional",
            "subcategory":"Accounting & Tax Preparation",
            "type":"Services"
        }
    ],
    "sg:phone":"+1 828 692 2150",
    "sg:postcode":"28792",
    "sg:province":"NC",
    "sg:tags":[
        "accountant"
    ],
    "wof:name":"Workman Tax & Accounting Svc",
    "wof:placetype":"venue"
},
  "geometry": {"coordinates":[-82.45279499999999,35.298254],"type":"Point"}
}