{
  "type": "Feature",
  "properties": {
    "iso:country":"US",
    "sg:address":"8829 E W T Harris Blvd",
    "sg:city":"Charlotte",
    "sg:classifiers":[
        {
            "category":"Retail",
            "subcategory":"Laundry & Dry Cleaning",
            "type":"Services"
        }
    ],
    "sg:phone":"+1   ",
    "sg:postcode":"28227",
    "sg:province":"NC",
    "sg:tags":[
        "drycleaning",
        "plant",
        "coin"
    ],
    "wof:name":"Cinderella Cleaners",
    "wof:placetype":"venue"
},
  "geometry": {"coordinates":[-80.72592299999999,35.201403],"type":"Point"}
}