{
  "type": "Feature",
  "properties": {
    "iso:country":"US",
    "sg:address":"1158 C P Stewart Rd",
    "sg:city":"Lillington",
    "sg:phone":"+1 910 893 5446",
    "sg:postcode":"27546",
    "sg:province":"NC",
    "sg:tags":[
        "farm",
        "tobacco"
    ],
    "wof:name":"Curtis Salmon",
    "wof:placetype":"venue"
},
  "geometry": {"coordinates":[-78.919079,35.394307],"type":"Point"}
}