{
  "type": "Feature",
  "properties": {
    "addr:full":"928 S Madison St Whiteville NC 28472",
    "addr:housenumber":"928",
    "addr:postcode":"28472",
    "addr:street":"S Madison St",
    "iso:country":"US",
    "sg:address":"928 S Madison St",
    "sg:city":"Whiteville",
    "sg:classifiers":[
        {
            "category":"Building & Trades",
            "subcategory":"Plumbing",
            "type":"Services"
        }
    ],
    "sg:phone":"+1 910 641 0068",
    "sg:postcode":"28472",
    "sg:province":"NC",
    "sg:tags":[
        "contractor"
    ],
    "wof:name":"Macs Plumbing",
    "wof:placetype":"venue"
},
  "geometry": {"coordinates":[-78.704576,34.319755],"type":"Point"}
}