{
  "type": "Feature",
  "properties": {
    "addr:full":"2180 Dawson Cabin Rd Jacksonville NC 28540",
    "addr:housenumber":"2180",
    "addr:postcode":"28540",
    "addr:street":"Dawson Cabin Rd",
    "iso:country":"US",
    "sg:address":"2180 Dawson Cabin Rd",
    "sg:city":"Jacksonville",
    "sg:classifiers":[
        {
            "category":"Building & Trades",
            "subcategory":"Equipment Rental",
            "type":"Services"
        }
    ],
    "sg:phone":"+1 910 938 0085",
    "sg:postcode":"28540",
    "sg:province":"NC",
    "sg:tags":[
        "yard"
    ],
    "wof:name":"Priced Right Rentals",
    "wof:placetype":"venue"
},
  "geometry": {"coordinates":[-77.49283800000001,34.69225],"type":"Point"}
}