{
  "type": "Feature",
  "properties": {
    "iso:country":"US",
    "sg:address":"1000 11th St",
    "sg:city":"Goldsboro",
    "sg:classifiers":[
        {
            "category":"Organizations",
            "subcategory":"Religious Organization",
            "type":"Services"
        }
    ],
    "sg:phone":"+1 919 735 0633",
    "sg:postcode":"27534",
    "sg:province":"NC",
    "sg:tags":[
        "church"
    ],
    "wof:name":"Church Of Jesus Christ Of Lds",
    "wof:placetype":"venue"
},
  "geometry": {"coordinates":[-77.969348,35.40011],"type":"Point"}
}