{
  "type": "Feature",
  "properties": {
    "iso:country":"US",
    "sg:address":"4037 Commonwealth Ave",
    "sg:city":"Charlotte",
    "sg:classifiers":[
        {
            "category":"Organizations",
            "subcategory":"Religious Organization",
            "type":"Services"
        }
    ],
    "sg:phone":"+1 704 537 6011",
    "sg:postcode":"28205",
    "sg:province":"NC",
    "sg:tags":[
        "church"
    ],
    "wof:name":"Spanish Congregation",
    "wof:placetype":"venue"
},
  "geometry": {"coordinates":[-80.78525500000001,35.199461],"type":"Point"}
}