{
  "type": "Feature",
  "properties": {
    "iso:country":"US",
    "sg:address":"6701 Morrison Blvd",
    "sg:city":"Charlotte",
    "sg:classifiers":[
        {
            "category":"Coffee & Tea",
            "type":"Food & Drink"
        }
    ],
    "sg:menulink":"http://www.allmenus.com/nc/charlotte/124991-starbucks-coffee/menu/",
    "sg:phone":"+1 704 365 5194",
    "sg:postcode":"28211",
    "sg:province":"NC",
    "sg:tags":[
        "american"
    ],
    "wof:name":"Starbucks Coffee",
    "wof:placetype":"venue"
},
  "geometry": {"coordinates":[-80.825796,35.152698],"type":"Point"}
}