{
  "type": "Feature",
  "properties": {
    "iso:country":"US",
    "sg:address":"208 E Washington St",
    "sg:city":"Bethel",
    "sg:classifiers":[
        {
            "category":"Autos & Motor Vehicles",
            "subcategory":"Fuel & Gas Station",
            "type":"Retail Goods"
        }
    ],
    "sg:phone":"+1 252 825 1588",
    "sg:postcode":"27812",
    "sg:province":"NC",
    "sg:tags":[
        "oil"
    ],
    "wof:name":"Whitaker's 66 Svc Station",
    "wof:placetype":"venue"
},
  "geometry": {"coordinates":[-77.371948,35.806719],"type":"Point"}
}