{
  "type": "Feature",
  "properties": {
    "addr:full":"1321 N Road St Elizabeth City NC 27909",
    "addr:housenumber":"1321",
    "addr:postcode":"27909",
    "addr:street":"N Road St",
    "iso:country":"US",
    "sg:address":"1321 N Road St",
    "sg:city":"Elizabeth City",
    "sg:classifiers":[
        {
            "category":"Restaurant",
            "type":"Food & Drink"
        }
    ],
    "sg:phone":"+1 252 335 7122",
    "sg:postcode":"27909",
    "sg:province":"NC",
    "wof:name":"Mc Donald's",
    "wof:placetype":"venue"
},
  "geometry": {"coordinates":[-76.227001,36.331242],"type":"Point"}
}