{
  "type": "Feature",
  "properties": {
    "iso:country":"US",
    "sg:address":"1701 N Main St",
    "sg:city":"High Point",
    "sg:classifiers":[
        {
            "category":"Shopping",
            "subcategory":"Gifts & Souvenirs",
            "type":"Retail Goods"
        }
    ],
    "sg:phone":"+1 336 884 7368",
    "sg:postcode":"27262",
    "sg:province":"NC",
    "sg:tags":[
        "party",
        "supply"
    ],
    "wof:name":"Party Rental Source",
    "wof:placetype":"venue"
},
  "geometry": {"coordinates":[-80.02040100000001,35.978238],"type":"Point"}
}