{
  "type": "Feature",
  "properties": {
    "iso:country":"US",
    "sg:address":"131 4th Ave W",
    "sg:city":"Hendersonville",
    "sg:classifiers":[
        {
            "category":"Social Services",
            "type":"Services"
        }
    ],
    "sg:phone":"+1 828 329 0431",
    "sg:postcode":"28792",
    "sg:province":"NC",
    "sg:tags":[
        "counselor",
        "marriage",
        "family"
    ],
    "wof:name":"Roberta Moore",
    "wof:placetype":"venue"
},
  "geometry": {"coordinates":[-82.46095099999999,35.316758],"type":"Point"}
}