{
  "type": "Feature",
  "properties": {
    "addr:full":"1520 Lawnside Pl Kannapolis NC 28083",
    "addr:housenumber":"1520",
    "addr:postcode":"28083",
    "addr:street":"Lawnside Pl",
    "iso:country":"US",
    "sg:address":"1520 Lawnside Pl",
    "sg:city":"Kannapolis",
    "sg:classifiers":[
        {
            "category":"Organizations",
            "subcategory":"Membership Organization",
            "type":"Services"
        }
    ],
    "sg:phone":"+1 704 213 5050",
    "sg:postcode":"28083",
    "sg:province":"NC",
    "wof:name":"M A D D Rowan County C A T",
    "wof:placetype":"venue"
},
  "geometry": {"coordinates":[-80.602726,35.507878],"type":"Point"}
}