{
  "type": "Feature",
  "properties": {
    "addr:full":"5040 Flagstone Ct Harrisburg NC 28075",
    "addr:housenumber":"5040",
    "addr:postcode":"28075",
    "addr:street":"Flagstone Ct",
    "iso:country":"US",
    "sg:address":"5040 Flagstone Ct",
    "sg:city":"Harrisburg",
    "sg:classifiers":[
        {
            "category":"Real Estate",
            "subcategory":"Real Estate Agent",
            "type":"Services"
        }
    ],
    "sg:phone":"+1 704 455 5068",
    "sg:postcode":"28075",
    "sg:province":"NC",
    "wof:name":"Foley L-Cornerstone Realty",
    "wof:placetype":"venue"
},
  "geometry": {"coordinates":[-80.661123,35.310619],"type":"Point"}
}