{
  "type": "Feature",
  "properties": {
    "iso:country":"US",
    "sg:address":"256 McGill Ave NW",
    "sg:city":"Concord",
    "sg:classifiers":[
        {
            "category":"Travel",
            "subcategory":"Travel Agent",
            "type":"Entertainment"
        }
    ],
    "sg:phone":"+1 704 795 3974",
    "sg:postcode":"28025",
    "sg:province":"NC",
    "sg:tags":[
        "agency"
    ],
    "wof:name":"Avenduras Travel",
    "wof:placetype":"venue"
},
  "geometry": {"coordinates":[-80.600595,35.416407],"type":"Point"}
}