{
  "type": "Feature",
  "properties": {
    "addr:full":"318 S Dyer St Elizabeth City NC 27909",
    "addr:housenumber":"318",
    "addr:postcode":"27909",
    "addr:street":"S Dyer St",
    "iso:country":"US",
    "sg:address":"318 S Dyer St",
    "sg:city":"Elizabeth City",
    "sg:classifiers":[
        {
            "category":"Restaurant",
            "type":"Food & Drink"
        }
    ],
    "sg:phone":"+1 252 335 4155",
    "sg:postcode":"27909",
    "sg:province":"NC",
    "sg:tags":[
        "eating"
    ],
    "wof:name":"Linda Bennett",
    "wof:placetype":"venue"
},
  "geometry": {"coordinates":[-76.225385,36.298784],"type":"Point"}
}