{
  "type": "Feature",
  "properties": {
    "iso:country":"US",
    "sg:address":"723 White Oak Ln",
    "sg:city":"Matthews",
    "sg:classifiers":[
        {
            "category":"Communications",
            "subcategory":"Film & Video Production",
            "type":"Services"
        }
    ],
    "sg:phone":"+1   ",
    "sg:postcode":"28104",
    "sg:province":"NC",
    "sg:tags":[
        "motion"
    ],
    "wof:name":"Visual Reality",
    "wof:placetype":"venue"
},
  "geometry": {"coordinates":[-80.66162799999999,35.095644],"type":"Point"}
}