{
  "type": "Feature",
  "properties": {
    "addr:full":"7191 Stag Park Rd Burgaw NC 28425",
    "addr:housenumber":"7191",
    "addr:postcode":"28425",
    "addr:street":"Stag Park Rd",
    "iso:country":"US",
    "sg:address":"7191 Stag Park Rd",
    "sg:city":"Burgaw",
    "sg:classifiers":[
        {
            "category":"Organizations",
            "subcategory":"Religious Organization",
            "type":"Services"
        }
    ],
    "sg:phone":"+1 910 259 3530",
    "sg:postcode":"28425",
    "sg:province":"NC",
    "sg:tags":[
        "church"
    ],
    "wof:name":"Full Gospel Temple-Deliverance",
    "wof:placetype":"venue"
},
  "geometry": {"coordinates":[-77.847545,34.506692],"type":"Point"}
}