{
  "type": "Feature",
  "properties": {
    "addr:full":"7713 Kingsberry Ct Raleigh NC 27615",
    "addr:housenumber":"7713",
    "addr:postcode":"27615",
    "addr:street":"Kingsberry Ct",
    "iso:country":"US",
    "sg:address":"7713 Kingsberry Ct",
    "sg:city":"Raleigh",
    "sg:classifiers":[
        {
            "category":"Professional",
            "subcategory":"Business Services",
            "type":"Services"
        }
    ],
    "sg:phone":"+1 919 845 9827",
    "sg:postcode":"27615",
    "sg:province":"NC",
    "wof:name":"Welch Enterprises",
    "wof:placetype":"venue"
},
  "geometry": {"coordinates":[-78.645105,35.886521],"type":"Point"}
}