{
  "type": "Feature",
  "properties": {
    "addr:full":"1319 Headquarters Dr Greensboro NC 27405",
    "addr:housenumber":"1319",
    "addr:postcode":"27405",
    "addr:street":"Headquarters Dr",
    "iso:country":"US",
    "sg:address":"1319 Headquarters Dr",
    "sg:city":"Greensboro",
    "sg:classifiers":[
        {
            "category":"Building & Trades",
            "subcategory":"Plumbing",
            "type":"Services"
        }
    ],
    "sg:phone":"+1 336 375 8824",
    "sg:postcode":"27405",
    "sg:province":"NC",
    "sg:tags":[
        "mechanical",
        "contractor"
    ],
    "wof:name":"Benic Mechanical Inc",
    "wof:placetype":"venue"
},
  "geometry": {"coordinates":[-79.767381,36.084154],"type":"Point"}
}