{
  "type": "Feature",
  "properties": {
    "addr:full":"3909 Edwards Mill Rd Raleigh NC 27612",
    "addr:housenumber":"3909",
    "addr:postcode":"27612",
    "addr:street":"Edwards Mill Rd",
    "iso:country":"US",
    "sg:address":"3909 Edwards Mill Rd",
    "sg:city":"Raleigh",
    "sg:classifiers":[
        {
            "category":"Building & Trades",
            "subcategory":"Construction",
            "type":"Services"
        }
    ],
    "sg:phone":"+1 919 781 3191",
    "sg:postcode":"27612",
    "sg:province":"NC",
    "sg:tags":[
        "home",
        "builder"
    ],
    "wof:name":"Drees Homes Inc At Avallon",
    "wof:placetype":"venue"
},
  "geometry": {"coordinates":[-78.69758,35.833821],"type":"Point"}
}