{
  "type": "Feature",
  "properties": {
    "iso:country":"US",
    "sg:address":"110 Academy St",
    "sg:city":"Vass",
    "sg:classifiers":[
        {
            "category":"Wholesale",
            "subcategory":"Machinery & Supplies",
            "type":"Manufacturing & Wholesale Goods"
        }
    ],
    "sg:phone":"+1 910 245 2912",
    "sg:postcode":"28394",
    "sg:province":"NC",
    "sg:tags":[
        "equipment",
        "railroad"
    ],
    "wof:name":"R I Locomotive Works",
    "wof:placetype":"venue"
},
  "geometry": {"coordinates":[-79.28241800000001,35.257706],"type":"Point"}
}