{
  "type": "Feature",
  "properties": {
    "iso:country":"US",
    "sg:address":"1067 Brompton Ln",
    "sg:city":"Greenville",
    "sg:classifiers":[
        {
            "category":"Wholesale",
            "subcategory":"Machinery & Supplies",
            "type":"Manufacturing & Wholesale Goods"
        },
        {
            "category":"Home & Garden",
            "subcategory":"Furniture",
            "type":"Retail Goods"
        }
    ],
    "sg:phone":"+1 252 493 7163",
    "sg:postcode":"27834",
    "sg:province":"NC",
    "sg:tags":[
        "equipment",
        "top",
        "industrial",
        "material",
        "counter"
    ],
    "wof:name":"Aspen Tops East Inc",
    "wof:placetype":"venue"
},
  "geometry": {"coordinates":[-77.445347,35.574242],"type":"Point"}
}