{
  "type": "Feature",
  "properties": {
    "iso:country":"US",
    "sg:address":"3200 Temple School Rd",
    "sg:city":"Winston Salem",
    "sg:classifiers":[
        {
            "category":"Building & Trades",
            "subcategory":"Construction",
            "type":"Services"
        }
    ],
    "sg:phone":"+1 336 769 2747",
    "sg:postcode":"27107",
    "sg:province":"NC",
    "sg:tags":[
        "general",
        "contractor"
    ],
    "wof:name":"Ace Avant Construction",
    "wof:placetype":"venue"
},
  "geometry": {"coordinates":[-80.124861,36.05792],"type":"Point"}
}