{
  "type": "Feature",
  "properties": {
    "addr:full":"6302 Fairview Rd Ste 100 Charlotte NC 28210",
    "addr:housenumber":"6302",
    "addr:postcode":"28210",
    "addr:street":"Fairview Rd Ste 100",
    "iso:country":"US",
    "sg:address":"6302 Fairview Rd Ste 100",
    "sg:city":"Charlotte",
    "sg:classifiers":[
        {
            "category":"Wholesale",
            "subcategory":"Computers",
            "type":"Manufacturing & Wholesale Goods"
        }
    ],
    "sg:phone":"+1 704 362 7799",
    "sg:postcode":"28210",
    "sg:province":"NC",
    "sg:tags":[
        "equipment",
        "computer-wholesale",
        "manufacturer"
    ],
    "sg:website":"http://www.peaktech.com",
    "wof:name":"Mesa Div",
    "wof:placetype":"venue"
},
  "geometry": {"coordinates":[-80.83557,35.150182],"type":"Point"}
}