{
  "type": "Feature",
  "properties": {
    "iso:country":"US",
    "sg:address":"126 E Hargett St",
    "sg:city":"Raleigh",
    "sg:classifiers":[
        {
            "category":"Shopping",
            "subcategory":"Pharmacy",
            "type":"Retail Goods"
        }
    ],
    "sg:phone":"+1 919 828 2391",
    "sg:postcode":"27601",
    "sg:province":"NC",
    "wof:name":"Hamlin Drug Co",
    "wof:placetype":"venue"
},
  "geometry": {"coordinates":[-78.63791000000001,35.778211],"type":"Point"}
}