{
  "type": "Feature",
  "properties": {
    "iso:country":"US",
    "sg:address":"208 Turtle Creek Dr",
    "sg:city":"Asheville",
    "sg:classifiers":[
        {
            "category":"Shopping",
            "subcategory":"Musical Instruments",
            "type":"Retail Goods"
        }
    ],
    "sg:phone":"+1 828 274 1729",
    "sg:postcode":"28803",
    "sg:province":"NC",
    "sg:tags":[
        "piano"
    ],
    "wof:name":"Alpha Piano & Keyboard",
    "wof:placetype":"venue"
},
  "geometry": {"coordinates":[-82.520194,35.508746],"type":"Point"}
}