{
  "type": "Feature",
  "properties": {
    "iso:country":"US",
    "sg:address":"2611 Fern Gully Dr",
    "sg:city":"Claremont",
    "sg:classifiers":[
        {
            "category":"Home & Garden",
            "subcategory":"Furniture",
            "type":"Retail Goods"
        }
    ],
    "sg:phone":"+1 828 459 7189",
    "sg:postcode":"28610",
    "sg:province":"NC",
    "wof:name":"Legacy Furniture Group",
    "wof:placetype":"venue"
},
  "geometry": {"coordinates":[-81.120643,35.708763],"type":"Point"}
}