{
  "type": "Feature",
  "properties": {
    "addr:full":"46 Williams Pond Rd Pittsboro NC 27312",
    "addr:housenumber":"46",
    "addr:postcode":"27312",
    "addr:street":"Williams Pond Rd",
    "iso:country":"US",
    "sg:address":"46 Williams Pond Rd",
    "sg:city":"Pittsboro",
    "sg:classifiers":[
        {
            "category":"Retail",
            "subcategory":"Repair Shop",
            "type":"Services"
        },
        {
            "category":"Retail",
            "subcategory":"Laundry & Dry Cleaning",
            "type":"Services"
        }
    ],
    "sg:phone":"+1 919 545 2322",
    "sg:postcode":"27312",
    "sg:province":"NC",
    "sg:tags":[
        "cleaners",
        "rug",
        "carpet"
    ],
    "wof:name":"Precision Steaming Cleaning",
    "wof:placetype":"venue"
},
  "geometry": {"coordinates":[-79.13609,35.775078],"type":"Point"}
}