{
  "type": "Feature",
  "properties": {
    "iso:country":"US",
    "sg:address":"2980 E Sprague St",
    "sg:city":"Winston Salem",
    "sg:classifiers":[
        {
            "category":"Freight",
            "type":"Transportation"
        }
    ],
    "sg:phone":"+1 336 784 0786",
    "sg:postcode":"27107",
    "sg:province":"NC",
    "sg:tags":[
        "general"
    ],
    "wof:name":"Todds Easy Move",
    "wof:placetype":"venue"
},
  "geometry": {"coordinates":[-80.18123799999999,36.076297],"type":"Point"}
}