{
  "type": "Feature",
  "properties": {
    "addr:full":"2056 Carolina Beach Rd Wilmington NC 28401",
    "addr:housenumber":"2056",
    "addr:postcode":"28401",
    "addr:street":"Carolina Beach Rd",
    "iso:country":"US",
    "sg:address":"2056 Carolina Beach Rd",
    "sg:city":"Wilmington",
    "sg:classifiers":[
        {
            "category":"Insurance",
            "subcategory":"Insurance Agent",
            "type":"Services"
        },
        {
            "category":"Insurance",
            "subcategory":"Hazard Insurance",
            "type":"Services"
        },
        {
            "category":"Insurance",
            "subcategory":"Title Insurance",
            "type":"Services"
        }
    ],
    "sg:phone":"+1 910 251 8334",
    "sg:postcode":"28401",
    "sg:province":"NC",
    "sg:tags":[
        "auto",
        "homeowner"
    ],
    "wof:name":"American Insurance Center Inc",
    "wof:placetype":"venue"
},
  "geometry": {"coordinates":[-77.94144799999999,34.203859],"type":"Point"}
}