{
  "type": "Feature",
  "properties": {
    "iso:country":"US",
    "sg:address":"817 S Meadow Rd",
    "sg:city":"Raleigh",
    "sg:phone":"+1 919 779 5623",
    "sg:postcode":"27603",
    "sg:province":"NC",
    "sg:tags":[
        "communications",
        "telegraph"
    ],
    "wof:name":"Written Word Transcription Svc",
    "wof:placetype":"venue"
},
  "geometry": {"coordinates":[-78.639031,35.623905],"type":"Point"}
}