{
  "type": "Feature",
  "properties": {
    "addr:full":"3138 Shillington Pl Charlotte NC 28210",
    "addr:housenumber":"3138",
    "addr:postcode":"28210",
    "addr:street":"Shillington Pl",
    "iso:country":"US",
    "sg:address":"3138 Shillington Pl",
    "sg:city":"Charlotte",
    "sg:classifiers":[
        {
            "category":"Professional",
            "subcategory":"Management & Consulting",
            "type":"Services"
        }
    ],
    "sg:phone":"+1 704 552 5861",
    "sg:postcode":"28210",
    "sg:province":"NC",
    "sg:tags":[
        "farm"
    ],
    "wof:name":"Davis Gebhart",
    "wof:placetype":"venue"
},
  "geometry": {"coordinates":[-80.85356899999999,35.118774],"type":"Point"}
}