{
  "type": "Feature",
  "properties": {
    "iso:country":"US",
    "sg:address":"288 Hawkins Ln",
    "sg:city":"Moravian Falls",
    "sg:classifiers":[
        {
            "category":"Shopping",
            "subcategory":"Musical Instruments",
            "type":"Retail Goods"
        }
    ],
    "sg:phone":"+1 336 667 9628",
    "sg:postcode":"28654",
    "sg:province":"NC",
    "wof:name":"Guitar Spec B Gee",
    "wof:placetype":"venue"
},
  "geometry": {"coordinates":[-81.177335,36.100188],"type":"Point"}
}