{
  "type": "Feature",
  "properties": {
    "addr:full":"1020 High Point St Randleman NC 27317",
    "addr:housenumber":"1020",
    "addr:postcode":"27317",
    "addr:street":"High Point St",
    "iso:country":"US",
    "sg:address":"1020 High Point St",
    "sg:city":"Randleman",
    "sg:classifiers":[
        {
            "category":"Food & Beverages",
            "subcategory":"Groceries & Convenience Stores",
            "type":"Retail Goods"
        }
    ],
    "sg:phone":"+1 336 498 1109",
    "sg:postcode":"27317",
    "sg:province":"NC",
    "wof:name":"Tank & Tummy Store 11",
    "wof:placetype":"venue"
},
  "geometry": {"coordinates":[-79.822963,35.822504],"type":"Point"}
}