{
  "type": "Feature",
  "properties": {
    "iso:country":"US",
    "sg:address":"240 Midlothian Dr",
    "sg:city":"Southern Pines",
    "sg:classifiers":[
        {
            "category":"Building & Trades",
            "subcategory":"Landscaping Services",
            "type":"Services"
        }
    ],
    "sg:phone":"+1 910 246 2300",
    "sg:postcode":"28387",
    "sg:province":"NC",
    "sg:tags":[
        "tree"
    ],
    "wof:name":"Heartwood Tree Svc",
    "wof:placetype":"venue"
},
  "geometry": {"coordinates":[-79.37741,35.184202],"type":"Point"}
}