{
  "type": "Feature",
  "properties": {
    "addr:full":"162 Ellerbe Grove Church Rd Rockingham NC 28379",
    "addr:housenumber":"162",
    "addr:postcode":"28379",
    "addr:street":"Ellerbe Grove Church Rd",
    "iso:country":"US",
    "sg:address":"162 Ellerbe Grove Church Rd",
    "sg:city":"Rockingham",
    "sg:classifiers":[
        {
            "category":"Organizations",
            "subcategory":"Religious Organization",
            "type":"Services"
        }
    ],
    "sg:phone":"+1 910 582 5902",
    "sg:postcode":"28379",
    "sg:province":"NC",
    "sg:tags":[
        "church"
    ],
    "wof:name":"Ellerbe Grove Baptist Church",
    "wof:placetype":"venue"
},
  "geometry": {"coordinates":[-79.779939,34.861119],"type":"Point"}
}