{
  "type": "Feature",
  "properties": {
    "iso:country":"US",
    "sg:address":"1787 Weeksville Rd",
    "sg:city":"Elizabeth City",
    "sg:classifiers":[
        {
            "category":"Utilities",
            "subcategory":"Mobile Phone",
            "type":"Services"
        }
    ],
    "sg:phone":"+1 252 335 9719",
    "sg:postcode":"27909",
    "sg:province":"NC",
    "sg:tags":[
        "telephone",
        "cellular"
    ],
    "wof:name":"Elizabeth City Cell",
    "wof:placetype":"venue"
},
  "geometry": {"coordinates":[-76.207256,36.271069],"type":"Point"}
}