{
  "type": "Feature",
  "properties": {
    "addr:full":"3417 Ashmill Ct Apex NC 27539",
    "addr:housenumber":"3417",
    "addr:postcode":"27539",
    "addr:street":"Ashmill Ct",
    "iso:country":"US",
    "sg:address":"3417 Ashmill Ct",
    "sg:city":"Apex",
    "sg:classifiers":[
        {
            "category":"Building & Trades",
            "subcategory":"Construction",
            "type":"Services"
        }
    ],
    "sg:phone":"+1 919 303 9000",
    "sg:postcode":"27539",
    "sg:province":"NC",
    "sg:tags":[
        "contractor"
    ],
    "wof:name":"Ark Roofing Co",
    "wof:placetype":"venue"
},
  "geometry": {"coordinates":[-78.790846,35.677965],"type":"Point"}
}