{
  "type": "Feature",
  "properties": {
    "addr:full":"603 Highland Ave SE Hickory NC 28602",
    "addr:housenumber":"603",
    "addr:postcode":"28602",
    "addr:street":"Highland Ave Se",
    "iso:country":"US",
    "sg:address":"603 Highland Ave SE",
    "sg:city":"Hickory",
    "sg:classifiers":[
        {
            "category":"Retail",
            "subcategory":"Veterinary Services",
            "type":"Services"
        }
    ],
    "sg:phone":"+1 828 322 1135",
    "sg:postcode":"28602",
    "sg:province":"NC",
    "sg:tags":[
        "veterinarian"
    ],
    "wof:name":"Animal Hospital",
    "wof:placetype":"venue"
},
  "geometry": {"coordinates":[-81.328436,35.733509],"type":"Point"}
}