{
  "type": "Feature",
  "properties": {
    "iso:country":"US",
    "sg:address":"228 Grace St",
    "sg:city":"Mount Airy",
    "sg:classifiers":[
        {
            "category":"Wholesale",
            "subcategory":"Toys & Hobbies",
            "type":"Manufacturing & Wholesale Goods"
        }
    ],
    "sg:phone":"+1 336 789 5767",
    "sg:postcode":"27030",
    "sg:province":"NC",
    "wof:name":"Main Street Pottery",
    "wof:placetype":"venue"
},
  "geometry": {"coordinates":[-80.609363,36.516243],"type":"Point"}
}