{
  "type": "Feature",
  "properties": {
    "addr:full":"410 Oakwood Creek Ln Charlotte NC 28262",
    "addr:housenumber":"410",
    "addr:postcode":"28262",
    "addr:street":"Oakwood Creek Ln",
    "iso:country":"US",
    "sg:address":"410 Oakwood Creek Ln",
    "sg:city":"Charlotte",
    "sg:classifiers":[
        {
            "category":"Professional",
            "type":"Services"
        }
    ],
    "sg:phone":"+1 704 971 7419",
    "sg:postcode":"28262",
    "sg:province":"NC",
    "wof:name":"Valerie Lamey",
    "wof:placetype":"venue"
},
  "geometry": {"coordinates":[-80.734172,35.325066],"type":"Point"}
}