{
  "type": "Feature",
  "properties": {
    "iso:country":"US",
    "sg:address":"1272 Campground Rd",
    "sg:city":"Elizabeth City",
    "sg:phone":"+1 252 771 2793",
    "sg:postcode":"27909",
    "sg:province":"NC",
    "sg:tags":[
        "farm",
        "corn",
        "wheat",
        "soybean"
    ],
    "wof:name":"William Sharber",
    "wof:placetype":"venue"
},
  "geometry": {"coordinates":[-76.428195,36.399387],"type":"Point"}
}