{
  "type": "Feature",
  "properties": {
    "addr:full":"508 Fulton St Durham NC 27705",
    "addr:housenumber":"508",
    "addr:postcode":"27705",
    "addr:street":"Fulton St",
    "iso:country":"US",
    "sg:address":"508 Fulton St",
    "sg:city":"Durham",
    "sg:classifiers":[
        {
            "category":"Shopping",
            "subcategory":"Optical Goods",
            "type":"Retail Goods"
        }
    ],
    "sg:phone":"+1 919 286 1113",
    "sg:postcode":"27705",
    "sg:province":"NC",
    "wof:name":"Safelite Optical",
    "wof:placetype":"venue"
},
  "geometry": {"coordinates":[-78.937349,36.009046],"type":"Point"}
}