{
  "type": "Feature",
  "properties": {
    "iso:country":"US",
    "sg:address":"217 Southside Dr",
    "sg:city":"Charlotte",
    "sg:classifiers":[
        {
            "category":"Wholesale",
            "subcategory":"Machinery & Supplies",
            "type":"Manufacturing & Wholesale Goods"
        },
        {
            "category":"Building & Trades",
            "subcategory":"Construction",
            "type":"Services"
        }
    ],
    "sg:phone":"+1 704 676 9788",
    "sg:postcode":"28217",
    "sg:province":"NC",
    "sg:tags":[
        "control",
        "horticultural",
        "erosion"
    ],
    "wof:name":"Protech Environmental Supply",
    "wof:placetype":"venue"
},
  "geometry": {"coordinates":[-80.879988,35.185463],"type":"Point"}
}