{
  "type": "Feature",
  "properties": {
    "addr:full":"3737 Lucky Dr Apex NC 27539",
    "addr:housenumber":"3737",
    "addr:postcode":"27539",
    "addr:street":"Lucky Dr",
    "iso:country":"US",
    "sg:address":"3737 Lucky Dr",
    "sg:city":"Apex",
    "sg:classifiers":[
        {
            "category":"Utilities",
            "subcategory":"Cable",
            "type":"Services"
        }
    ],
    "sg:phone":"+1 919 771 1505",
    "sg:postcode":"27539",
    "sg:province":"NC",
    "sg:tags":[
        "television"
    ],
    "wof:name":"High Tech Cable Communications",
    "wof:placetype":"venue"
},
  "geometry": {"coordinates":[-78.76689,35.688055],"type":"Point"}
}