{
  "type": "Feature",
  "properties": {
    "iso:country":"US",
    "sg:address":"13325 S Point Blvd",
    "sg:city":"Charlotte",
    "sg:classifiers":[
        {
            "category":"Professional",
            "subcategory":"Employment Agencies",
            "type":"Services"
        }
    ],
    "sg:phone":"+1 704 588 4872",
    "sg:postcode":"28273",
    "sg:province":"NC",
    "sg:tags":[
        "consultant",
        "search",
        "executive"
    ],
    "wof:name":"Bank Resources",
    "wof:placetype":"venue"
},
  "geometry": {"coordinates":[-80.95746699999999,35.108069],"type":"Point"}
}