{
  "type": "Feature",
  "properties": {
    "iso:country":"US",
    "sg:address":"5612 Oak Bluff Ln",
    "sg:city":"Wilmington",
    "sg:classifiers":[
        {
            "category":"Professional",
            "subcategory":"Business Services",
            "type":"Services"
        }
    ],
    "sg:phone":"+1   ",
    "sg:postcode":"28409",
    "sg:province":"NC",
    "wof:name":"Timeless Designs",
    "wof:placetype":"venue"
},
  "geometry": {"coordinates":[-77.849011,34.202022],"type":"Point"}
}