{
  "type": "Feature",
  "properties": {
    "addr:full":"1118 Franklin St SW Winston Salem NC 27101",
    "addr:housenumber":"1118",
    "addr:postcode":"27101",
    "addr:street":"Franklin St Sw",
    "iso:country":"US",
    "sg:address":"1118 Franklin St SW",
    "sg:city":"Winston Salem",
    "sg:classifiers":[
        {
            "category":"Health Services",
            "subcategory":"Nursing And Care Facility",
            "type":"Services"
        },
        {
            "category":"Social Services",
            "subcategory":"Adult Care",
            "type":"Services"
        }
    ],
    "sg:phone":"+1 336 748 0974",
    "sg:postcode":"27101",
    "sg:province":"NC",
    "sg:tags":[
        "foster"
    ],
    "wof:name":"Arrington's Care Home Inc",
    "wof:placetype":"venue"
},
  "geometry": {"coordinates":[-80.255583,36.086474],"type":"Point"}
}