{
  "type": "Feature",
  "properties": {
    "addr:full":"3603 S Tryon St Charlotte NC 28217",
    "addr:housenumber":"3603",
    "addr:postcode":"28217",
    "addr:street":"S Tryon St",
    "iso:country":"US",
    "sg:address":"3603 S Tryon St",
    "sg:city":"Charlotte",
    "sg:classifiers":[
        {
            "category":"Shopping",
            "subcategory":"Bicycles & Sporting Goods",
            "type":"Retail Goods"
        }
    ],
    "sg:phone":"+1 704 522 9007",
    "sg:postcode":"28217",
    "sg:province":"NC",
    "wof:name":"Shooters",
    "wof:placetype":"venue"
},
  "geometry": {"coordinates":[-80.87923499999999,35.193153],"type":"Point"}
}