{
  "type": "Feature",
  "properties": {
    "addr:full":"6201 Fairview Rd Charlotte NC 28210",
    "addr:housenumber":"6201",
    "addr:postcode":"28210",
    "addr:street":"Fairview Rd",
    "iso:country":"US",
    "sg:address":"6201 Fairview Rd",
    "sg:city":"Charlotte",
    "sg:classifiers":[
        {
            "category":"Professional",
            "subcategory":"Lawyer & Legal Services",
            "type":"Services"
        }
    ],
    "sg:phone":"+1 704 529 0646",
    "sg:postcode":"28210",
    "sg:province":"NC",
    "sg:tags":[
        "attorney"
    ],
    "wof:name":"Booth Harrington & Johns LLP",
    "wof:placetype":"venue"
},
  "geometry": {"coordinates":[-80.83444799999999,35.149787],"type":"Point"}
}