{
  "type": "Feature",
  "properties": {
    "iso:country":"US",
    "sg:address":"2001 N William St",
    "sg:city":"Goldsboro",
    "sg:classifiers":[
        {
            "category":"Building & Trades",
            "subcategory":"Construction",
            "type":"Services"
        }
    ],
    "sg:phone":"+1 919 581 0279",
    "sg:postcode":"27530",
    "sg:province":"NC",
    "sg:tags":[
        "television",
        "telephone",
        "cable",
        "contractor"
    ],
    "wof:name":"Prince Cable",
    "wof:placetype":"venue"
},
  "geometry": {"coordinates":[-77.98293099999999,35.407455],"type":"Point"}
}