{
  "type": "Feature",
  "properties": {
    "addr:full":"4515 Cedar Ave Wilmington NC 28403",
    "addr:housenumber":"4515",
    "addr:postcode":"28403",
    "addr:street":"Cedar Ave",
    "iso:country":"US",
    "sg:address":"4515 Cedar Ave",
    "sg:city":"Wilmington",
    "sg:classifiers":[
        {
            "category":"Building & Trades",
            "subcategory":"Construction",
            "type":"Services"
        }
    ],
    "sg:phone":"+1 910 798 1749",
    "sg:postcode":"28403",
    "sg:province":"NC",
    "sg:tags":[
        "concrete",
        "contractor"
    ],
    "wof:name":"Kore Kut Inc",
    "wof:placetype":"venue"
},
  "geometry": {"coordinates":[-77.88572000000001,34.217166],"type":"Point"}
}