{
  "type": "Feature",
  "properties": {
    "iso:country":"US",
    "sg:address":"5177 Hwy 58 N",
    "sg:city":"Stantonsburg",
    "sg:classifiers":[
        {
            "category":"Building & Trades",
            "subcategory":"Landscaping Services",
            "type":"Services"
        }
    ],
    "sg:phone":"+1 252 238 3951",
    "sg:postcode":"27883",
    "sg:province":"NC",
    "sg:tags":[
        "landscape",
        "contractor"
    ],
    "wof:name":"Harper Landscaping",
    "wof:placetype":"venue"
},
  "geometry": {"coordinates":[-77.75636,35.512222],"type":"Point"}
}