{
  "type": "Feature",
  "properties": {
    "iso:country":"US",
    "sg:address":"811 Purser Dr",
    "sg:city":"Raleigh",
    "sg:classifiers":[
        {
            "category":"Autos & Motor Vehicles",
            "subcategory":"Auto Supplies",
            "type":"Retail Goods"
        }
    ],
    "sg:phone":"+1 919 779 8798",
    "sg:postcode":"27603",
    "sg:province":"NC",
    "sg:tags":[
        "tire"
    ],
    "wof:name":"Universal Tire Svc Inc",
    "wof:placetype":"venue"
},
  "geometry": {"coordinates":[-78.664197,35.716926],"type":"Point"}
}