{
  "type": "Feature",
  "properties": {
    "iso:country":"US",
    "sg:address":"1318 E 10th St",
    "sg:city":"Greenville",
    "sg:classifiers":[
        {
            "category":"Shopping",
            "subcategory":"Florist",
            "type":"Retail Goods"
        }
    ],
    "sg:phone":"+1 252 757 1892",
    "sg:postcode":"27858",
    "sg:province":"NC",
    "wof:name":"Cynthia's Flowers Inc",
    "wof:placetype":"venue"
},
  "geometry": {"coordinates":[-77.35286499999999,35.60253],"type":"Point"}
}