{
  "type": "Feature",
  "properties": {
    "addr:full":"207 E Salisbury St Asheboro NC 27203",
    "addr:housenumber":"207",
    "addr:postcode":"27203",
    "addr:street":"E Salisbury St",
    "iso:country":"US",
    "sg:address":"207 E Salisbury St",
    "sg:city":"Asheboro",
    "sg:classifiers":[
        {
            "category":"Professional",
            "type":"Services"
        }
    ],
    "sg:phone":"+1 336 626 3937",
    "sg:postcode":"27203",
    "sg:province":"NC",
    "sg:tags":[
        "establishment"
    ],
    "wof:name":"Visualeyes",
    "wof:placetype":"venue"
},
  "geometry": {"coordinates":[-79.811413,35.707576],"type":"Point"}
}