{
  "type": "Feature",
  "properties": {
    "addr:full":"345 N Main St Troutman NC 28166",
    "addr:housenumber":"345",
    "addr:postcode":"28166",
    "addr:street":"N Main St",
    "iso:country":"US",
    "sg:address":"345 N Main St",
    "sg:city":"Troutman",
    "sg:classifiers":[
        {
            "category":"Retail",
            "subcategory":"Funeral Services",
            "type":"Services"
        }
    ],
    "sg:phone":"+1 704 528 4106",
    "sg:postcode":"28166",
    "sg:province":"NC",
    "sg:tags":[
        "director"
    ],
    "wof:name":"Troutman Funeral Home Inc",
    "wof:placetype":"venue"
},
  "geometry": {"coordinates":[-80.89462899999999,35.709959],"type":"Point"}
}