{
  "type": "Feature",
  "properties": {
    "addr:full":"301 E Wendover Ave Greensboro NC 27405",
    "addr:housenumber":"301",
    "addr:postcode":"27405",
    "addr:street":"E Wendover Ave",
    "iso:country":"US",
    "sg:address":"301 E Wendover Ave",
    "sg:city":"Greensboro",
    "sg:classifiers":[
        {
            "category":"Health Services",
            "subcategory":"Doctor",
            "type":"Services"
        }
    ],
    "sg:phone":"+1 336 379 8377",
    "sg:postcode":"27405",
    "sg:province":"NC",
    "sg:tags":[
        "dentist"
    ],
    "sg:website":"www.mlkdds.com",
    "wof:name":"Mackler Lutins & KNOX",
    "wof:placetype":"venue"
},
  "geometry": {"coordinates":[-79.787373,36.088068],"type":"Point"}
}