{
  "type": "Feature",
  "properties": {
    "iso:country":"US",
    "sg:address":"618 Saint Andrews Rd",
    "sg:city":"Statesville",
    "sg:classifiers":[
        {
            "category":"Building & Trades",
            "subcategory":"Landscaping Services",
            "type":"Services"
        }
    ],
    "sg:phone":"+1 704 902 3046",
    "sg:postcode":"28625",
    "sg:province":"NC",
    "sg:tags":[
        "designer",
        "landscape"
    ],
    "wof:name":"Bio-Landscaping & Design LLC",
    "wof:placetype":"venue"
},
  "geometry": {"coordinates":[-80.813041,35.79223],"type":"Point"}
}