{
  "type": "Feature",
  "properties": {
    "iso:country":"US",
    "sg:address":"28272 Austin Rd",
    "sg:city":"Albemarle",
    "sg:classifiers":[
        {
            "category":"Building & Trades",
            "subcategory":"Electrical",
            "type":"Services"
        }
    ],
    "sg:phone":"+1 704 982 6320",
    "sg:postcode":"28001",
    "sg:province":"NC",
    "sg:tags":[
        "electrical",
        "contractor"
    ],
    "wof:name":"Rd Faulkner Electric Inc",
    "wof:placetype":"venue"
},
  "geometry": {"coordinates":[-80.26526,35.387661],"type":"Point"}
}