{
  "type": "Feature",
  "properties": {
    "iso:country":"US",
    "sg:address":"5978 Springs Rd",
    "sg:city":"Conover",
    "sg:classifiers":[
        {
            "category":"Retail",
            "subcategory":"Auto Repair",
            "type":"Services"
        }
    ],
    "sg:phone":"+1 828 256 0065",
    "sg:postcode":"28613",
    "sg:province":"NC",
    "sg:tags":[
        "repairing",
        "automobile"
    ],
    "wof:name":"66 Auto Svc",
    "wof:placetype":"venue"
},
  "geometry": {"coordinates":[-81.185711,35.794451],"type":"Point"}
}