{
  "type": "Feature",
  "properties": {
    "addr:full":"1913 E Main St Lincolnton NC 28092",
    "addr:housenumber":"1913",
    "addr:postcode":"28092",
    "addr:street":"E Main St",
    "iso:country":"US",
    "sg:address":"1913 E Main St",
    "sg:city":"Lincolnton",
    "sg:classifiers":[
        {
            "category":"Professional",
            "type":"Services"
        }
    ],
    "sg:phone":"+1 704 732 8620",
    "sg:postcode":"28092",
    "sg:province":"NC",
    "sg:tags":[
        "establishment"
    ],
    "wof:name":"NASG",
    "wof:placetype":"venue"
},
  "geometry": {"coordinates":[-81.23105200000001,35.477964],"type":"Point"}
}