{
  "type": "Feature",
  "properties": {
    "addr:full":"308 W Raleigh St Siler City NC 27344",
    "addr:housenumber":"308",
    "addr:postcode":"27344",
    "addr:street":"W Raleigh St",
    "iso:country":"US",
    "sg:address":"308 W Raleigh St",
    "sg:city":"Siler City",
    "sg:classifiers":[
        {
            "category":"Personal",
            "type":"Services"
        }
    ],
    "sg:phone":"+1 919 663 2213",
    "sg:postcode":"27344",
    "sg:province":"NC",
    "sg:tags":[
        "fitness",
        "physical",
        "facility"
    ],
    "wof:name":"Easy Tan & Jewelry",
    "wof:placetype":"venue"
},
  "geometry": {"coordinates":[-79.465889,35.721899],"type":"Point"}
}