{
  "type": "Feature",
  "properties": {
    "addr:full":"417 W Main St Albemarle NC 28001",
    "addr:housenumber":"417",
    "addr:postcode":"28001",
    "addr:street":"W Main St",
    "iso:country":"US",
    "sg:address":"417 W Main St",
    "sg:city":"Albemarle",
    "sg:classifiers":[
        {
            "category":"Food & Beverages",
            "subcategory":"Groceries & Convenience Stores",
            "type":"Retail Goods"
        }
    ],
    "sg:phone":"+1 704 982 0813",
    "sg:postcode":"28001",
    "sg:province":"NC",
    "wof:name":"Convenient Corner Inc",
    "wof:placetype":"venue"
},
  "geometry": {"coordinates":[-80.20174900000001,35.35037],"type":"Point"}
}