{
  "type": "Feature",
  "properties": {
    "addr:full":"6505 Birkdale Ct Fuquay Varina NC 27526",
    "addr:housenumber":"6505",
    "addr:postcode":"27526",
    "addr:street":"Birkdale Ct",
    "iso:country":"US",
    "sg:address":"6505 Birkdale Ct",
    "sg:city":"Fuquay Varina",
    "sg:classifiers":[
        {
            "category":"Shopping",
            "subcategory":"Computers & Home Electronics",
            "type":"Retail Goods"
        }
    ],
    "sg:phone":"+1 919 567 9222",
    "sg:postcode":"27526",
    "sg:province":"NC",
    "sg:tags":[
        "equipment",
        "electronic",
        "supply"
    ],
    "wof:name":"Southern Marketing Assoc Inc",
    "wof:placetype":"venue"
},
  "geometry": {"coordinates":[-78.764342,35.629481],"type":"Point"}
}