{
  "type": "Feature",
  "properties": {
    "addr:full":"1344 Us Highway 258 S Kinston NC 28504",
    "addr:housenumber":"1344",
    "addr:postcode":"28504",
    "addr:street":"Us Highway 258 S",
    "iso:country":"US",
    "sg:address":"1344 Us Highway 258 S",
    "sg:city":"Kinston",
    "sg:classifiers":[
        {
            "category":"Restaurant",
            "type":"Food & Drink"
        }
    ],
    "sg:menulink":"http://www.allmenus.com/nc/neuse/156256-hardees/menu/",
    "sg:phone":"+1 252 527 7925",
    "sg:postcode":"28504",
    "sg:province":"NC",
    "sg:tags":[
        "burger",
        "american"
    ],
    "wof:name":"Hardee's",
    "wof:placetype":"venue"
},
  "geometry": {"coordinates":[-77.66557299999999,35.195756],"type":"Point"}
}