{
  "type": "Feature",
  "properties": {
    "iso:country":"US",
    "sg:address":"20 Hamby Dr",
    "sg:city":"Asheville",
    "sg:classifiers":[
        {
            "category":"Health Services",
            "subcategory":"Clinic",
            "type":"Services"
        }
    ],
    "sg:phone":"+1   ",
    "sg:postcode":"28803",
    "sg:province":"NC",
    "wof:name":"Strategic Consulting Inc",
    "wof:placetype":"venue"
},
  "geometry": {"coordinates":[-82.48252599999999,35.562478],"type":"Point"}
}