{
  "type": "Feature",
  "properties": {
    "addr:full":"10240 Blackwell Rd SE Leland NC 28451",
    "addr:housenumber":"10240",
    "addr:postcode":"28451",
    "addr:street":"Blackwell Rd Se",
    "iso:country":"US",
    "sg:address":"10240 Blackwell Rd SE",
    "sg:city":"Leland",
    "sg:classifiers":[
        {
            "category":"Professional",
            "type":"Services"
        }
    ],
    "sg:phone":"+1 910 371 3489",
    "sg:postcode":"28451",
    "sg:province":"NC",
    "sg:tags":[
        "establishment"
    ],
    "wof:name":"Williams HC Jr Truck Co Inc",
    "wof:placetype":"venue"
},
  "geometry": {"coordinates":[-77.99896200000001,34.227729],"type":"Point"}
}