{
  "type": "Feature",
  "properties": {
    "addr:full":"801 Clanton Rd Suite C112 Charlotte NC 28217",
    "addr:housenumber":"801",
    "addr:postcode":"28217",
    "addr:street":"Clanton Rd Suite C112",
    "iso:country":"US",
    "sg:address":"801 Clanton Rd Suite C112",
    "sg:city":"Charlotte",
    "sg:classifiers":[
        {
            "category":"Professional",
            "subcategory":"Business Services",
            "type":"Services"
        },
        {
            "category":"Manufacturing",
            "subcategory":"Paper Products",
            "type":"Manufacturing & Wholesale Goods"
        },
        {
            "category":"Real Estate",
            "subcategory":"Architect",
            "type":"Services"
        }
    ],
    "sg:phone":"+1 704 749 2921",
    "sg:postcode":"28217",
    "sg:province":"NC",
    "sg:tags":[
        "machine",
        "shredding-paper",
        "record",
        "shredding",
        "document",
        "destruction"
    ],
    "sg:website":"http://proshred.com/about.aspx?franchise_id=18&id=578",
    "wof:name":"PROSHRED",
    "wof:placetype":"venue"
},
  "geometry": {"coordinates":[-80.884452,35.198459],"type":"Point"}
}