{
  "type": "Feature",
  "properties": {
    "iso:country":"US",
    "sg:address":"114 Pond Creek Rd",
    "sg:city":"Banner Elk",
    "sg:classifiers":[
        {
            "category":"Home & Garden",
            "subcategory":"Garden Supply",
            "type":"Retail Goods"
        }
    ],
    "sg:phone":"+1 828 387 2730",
    "sg:postcode":"28604",
    "sg:province":"NC",
    "wof:name":"Robert & Connie Maher",
    "wof:placetype":"venue"
},
  "geometry": {"coordinates":[-81.866327,36.202513],"type":"Point"}
}