{
  "type": "Feature",
  "properties": {
    "iso:country":"US",
    "sg:address":"2003 Bismark Ct",
    "sg:city":"Fayetteville",
    "sg:classifiers":[
        {
            "category":"Building & Trades",
            "subcategory":"Construction",
            "type":"Services"
        }
    ],
    "sg:phone":"+1 910 483 3500",
    "sg:postcode":"28304",
    "sg:province":"NC",
    "sg:tags":[
        "general",
        "contractor"
    ],
    "wof:name":"Crown Builders-The Carolina's",
    "wof:placetype":"venue"
},
  "geometry": {"coordinates":[-78.91864,35.03471],"type":"Point"}
}