{
  "type": "Feature",
  "properties": {
    "addr:full":"7216 Country View Ct Charlotte NC 28211",
    "addr:housenumber":"7216",
    "addr:postcode":"28211",
    "addr:street":"Country View Ct",
    "iso:country":"US",
    "sg:address":"7216 Country View Ct",
    "sg:city":"Charlotte",
    "sg:classifiers":[
        {
            "category":"Professional",
            "type":"Services"
        }
    ],
    "sg:phone":"+1 704 907 5186",
    "sg:postcode":"28211",
    "sg:province":"NC",
    "wof:name":"Peck Systems LLC",
    "wof:placetype":"venue"
},
  "geometry": {"coordinates":[-80.82039,35.147325],"type":"Point"}
}