{
  "type": "Feature",
  "properties": {
    "addr:full":"215 Cemetery St Mocksville NC 27028",
    "addr:housenumber":"215",
    "addr:postcode":"27028",
    "addr:street":"Cemetery St",
    "iso:country":"US",
    "sg:address":"215 Cemetery St",
    "sg:city":"Mocksville",
    "sg:classifiers":[
        {
            "category":"Social Services",
            "type":"Services"
        }
    ],
    "sg:phone":"+1 336 751 9622",
    "sg:postcode":"27028",
    "sg:province":"NC",
    "sg:tags":[
        "organization",
        "welfare"
    ],
    "wof:name":"YMCA",
    "wof:placetype":"venue"
},
  "geometry": {"coordinates":[-80.554593,35.903744],"type":"Point"}
}