{
  "type": "Feature",
  "properties": {
    "iso:country":"US",
    "sg:address":"6254 Valwood Rd",
    "sg:city":"Conover",
    "sg:classifiers":[
        {
            "category":"Building & Trades",
            "subcategory":"Construction",
            "type":"Services"
        }
    ],
    "sg:phone":"+1 828 256 9789",
    "sg:postcode":"28613",
    "sg:province":"NC",
    "sg:tags":[
        "contractor"
    ],
    "wof:name":"Carroll E Yoder Masonry",
    "wof:placetype":"venue"
},
  "geometry": {"coordinates":[-81.206643,35.806721],"type":"Point"}
}