{
  "type": "Feature",
  "properties": {
    "iso:country":"US",
    "sg:address":"1500 Tunnel Rd",
    "sg:city":"Asheville",
    "sg:classifiers":[
        {
            "category":"Travel",
            "subcategory":"Hotels & Motels",
            "type":"Entertainment"
        }
    ],
    "sg:phone":"+1 828 298 5140",
    "sg:postcode":"28805",
    "sg:province":"NC",
    "sg:tags":[
        "operation"
    ],
    "wof:name":"Travelodge",
    "wof:placetype":"venue"
},
  "geometry": {"coordinates":[-82.461051,35.584759],"type":"Point"}
}