{
  "type": "Feature",
  "properties": {
    "iso:country":"US",
    "sg:address":"4920 E W T Harris Blvd",
    "sg:city":"Charlotte",
    "sg:classifiers":[
        {
            "category":"Organizations",
            "subcategory":"Religious Organization",
            "type":"Services"
        }
    ],
    "sg:phone":"+1 704 535 3383",
    "sg:postcode":"28215",
    "sg:province":"NC",
    "sg:website":"www.tlcooljc.org",
    "wof:name":"Living Church Of Our Lord",
    "wof:placetype":"venue"
},
  "geometry": {"coordinates":[-80.737337,35.248291],"type":"Point"}
}