{
  "type": "Feature",
  "properties": {
    "iso:country":"US",
    "sg:address":"44 Buck Shoals Rd",
    "sg:city":"Arden",
    "sg:classifiers":[
        {
            "category":"Building & Trades",
            "subcategory":"Construction",
            "type":"Services"
        }
    ],
    "sg:phone":"+1 828 687 9363",
    "sg:postcode":"28704",
    "sg:province":"NC",
    "sg:tags":[
        "contractor"
    ],
    "wof:name":"Hammersmith Builders LLC",
    "wof:placetype":"venue"
},
  "geometry": {"coordinates":[-82.516149,35.4605],"type":"Point"}
}