{
  "type": "Feature",
  "properties": {
    "addr:full":"2925 Nc 69 Hayesville NC 28904",
    "addr:housenumber":"2925",
    "addr:postcode":"28904",
    "addr:street":"Nc 69",
    "iso:country":"US",
    "sg:address":"2925 Nc 69",
    "sg:city":"Hayesville",
    "sg:classifiers":[
        {
            "category":"Retail",
            "subcategory":"Auto Repair",
            "type":"Services"
        }
    ],
    "sg:phone":"+1 828 389 0808",
    "sg:postcode":"28904",
    "sg:province":"NC",
    "sg:tags":[
        "transmission"
    ],
    "wof:name":"AJC Carolina Transmission",
    "wof:placetype":"venue"
},
  "geometry": {"coordinates":[-83.82523500000001,35.001199],"type":"Point"}
}