{
  "type": "Feature",
  "properties": {
    "addr:full":"314 Bashford Rd Raleigh NC 27606",
    "addr:housenumber":"314",
    "addr:postcode":"27606",
    "addr:street":"Bashford Rd",
    "iso:country":"US",
    "sg:address":"314 Bashford Rd",
    "sg:city":"Raleigh",
    "sg:classifiers":[
        {
            "category":"Organizations",
            "subcategory":"Religious Organization",
            "type":"Services"
        }
    ],
    "sg:phone":"+1   ",
    "sg:postcode":"27606",
    "sg:province":"NC",
    "wof:name":"Cary Christian Assembly",
    "wof:placetype":"venue"
},
  "geometry": {"coordinates":[-78.736958,35.781321],"type":"Point"}
}