{
  "type": "Feature",
  "properties": {
    "iso:country":"US",
    "sg:address":"202 E Woodlawn Rd",
    "sg:city":"Charlotte",
    "sg:classifiers":[
        {
            "category":"Wholesale",
            "subcategory":"Medical Equipment & Supplies",
            "type":"Manufacturing & Wholesale Goods"
        },
        {
            "category":"Shopping",
            "type":"Retail Goods"
        }
    ],
    "sg:phone":"+1 704 521 2882",
    "sg:postcode":"28217",
    "sg:province":"NC",
    "sg:tags":[
        "physician",
        "surgeon",
        "diabetic",
        "order",
        "mail"
    ],
    "wof:name":"National Direct Diabetic Sup",
    "wof:placetype":"venue"
},
  "geometry": {"coordinates":[-80.882442,35.178752],"type":"Point"}
}