{
  "type": "Feature",
  "properties": {
    "iso:country":"US",
    "sg:address":"1215 Planters St",
    "sg:city":"Rocky Mount",
    "sg:classifiers":[
        {
            "category":"Social Services",
            "subcategory":"Child Care",
            "type":"Services"
        }
    ],
    "sg:phone":"+1   ",
    "sg:postcode":"27801",
    "sg:province":"NC",
    "sg:tags":[
        "day"
    ],
    "wof:name":"Sally S Loving Home Child",
    "wof:placetype":"venue"
},
  "geometry": {"coordinates":[-77.781346,35.928181],"type":"Point"}
}