{
  "type": "Feature",
  "properties": {
    "addr:full":"2301 Grace Ave New Bern NC 28562",
    "addr:housenumber":"2301",
    "addr:postcode":"28562",
    "addr:street":"Grace Ave",
    "iso:country":"US",
    "sg:address":"2301 Grace Ave",
    "sg:city":"New Bern",
    "sg:classifiers":[
        {
            "category":"Health Services",
            "subcategory":"Doctor",
            "type":"Services"
        }
    ],
    "sg:phone":"+1   ",
    "sg:postcode":"28562",
    "sg:province":"NC",
    "wof:name":"Gentle Dental Care",
    "wof:placetype":"venue"
},
  "geometry": {"coordinates":[-77.076415,35.107327],"type":"Point"}
}