{
  "type": "Feature",
  "properties": {
    "addr:full":"1084 Orange St Newport NC 28570",
    "addr:housenumber":"1084",
    "addr:postcode":"28570",
    "addr:street":"Orange St",
    "iso:country":"US",
    "sg:address":"1084 Orange St",
    "sg:city":"Newport",
    "sg:classifiers":[
        {
            "category":"Government",
            "subcategory":"Jail",
            "type":"Public Place"
        }
    ],
    "sg:phone":"+1 252 223 5100",
    "sg:postcode":"28570",
    "sg:province":"NC",
    "sg:tags":[
        "govt",
        "state",
        "institution"
    ],
    "wof:name":"Cateret Correctional Ctr",
    "wof:placetype":"venue"
},
  "geometry": {"coordinates":[-76.84655600000001,34.780594],"type":"Point"}
}