{
  "type": "Feature",
  "properties": {
    "iso:country":"US",
    "sg:address":"8015 W Kenton Cir",
    "sg:city":"Huntersville",
    "sg:classifiers":[
        {
            "category":"Insurance",
            "subcategory":"Insurance Agent",
            "type":"Services"
        },
        {
            "category":"Insurance",
            "subcategory":"Hazard Insurance",
            "type":"Services"
        },
        {
            "category":"Insurance",
            "subcategory":"Title Insurance",
            "type":"Services"
        },
        {
            "category":"Insurance",
            "subcategory":"Life Insurance",
            "type":"Services"
        }
    ],
    "sg:phone":"+1 704 896 4950",
    "sg:postcode":"28078",
    "sg:province":"NC",
    "sg:tags":[
        "business",
        "auto",
        "commercial",
        "homeowner",
        "motorcycle",
        "renter"
    ],
    "wof:name":"Allstate Insurance Company - Marty Rasnake",
    "wof:placetype":"venue"
},
  "geometry": {"coordinates":[-80.890714,35.444908],"type":"Point"}
}