{
  "type": "Feature",
  "properties": {
    "iso:country":"US",
    "sg:address":"139 N Beaumont Ave",
    "sg:city":"Burlington",
    "sg:classifiers":[
        {
            "category":"Organizations",
            "subcategory":"Religious Organization",
            "type":"Services"
        }
    ],
    "sg:phone":"+1 336 570 3230",
    "sg:postcode":"27217",
    "sg:province":"NC",
    "sg:tags":[
        "church"
    ],
    "wof:name":"Grace & Peace Ministries",
    "wof:placetype":"venue"
},
  "geometry": {"coordinates":[-79.414069,36.097877],"type":"Point"}
}