{
  "type": "Feature",
  "properties": {
    "iso:country":"US",
    "sg:address":"117 Professional Dr",
    "sg:city":"Roanoke Rapids",
    "sg:classifiers":[
        {
            "category":"Health Services",
            "subcategory":"Doctor",
            "type":"Services"
        }
    ],
    "sg:phone":"+1 252 308 6889",
    "sg:postcode":"27870",
    "sg:province":"NC",
    "sg:tags":[
        "physician",
        "surgeon"
    ],
    "wof:name":"Sai Urology Ctr",
    "wof:placetype":"venue"
},
  "geometry": {"coordinates":[-77.639708,36.442432],"type":"Point"}
}