{
  "type": "Feature",
  "properties": {
    "addr:full":"1405 S 39th St Wilmington NC 28403",
    "addr:housenumber":"1405",
    "addr:postcode":"28403",
    "addr:street":"S 39Th St",
    "iso:country":"US",
    "sg:address":"1405 S 39th St",
    "sg:city":"Wilmington",
    "sg:classifiers":[
        {
            "category":"Real Estate",
            "subcategory":"Real Estate Agent",
            "type":"Services"
        }
    ],
    "sg:phone":"+1 910 799 0554",
    "sg:postcode":"28403",
    "sg:province":"NC",
    "wof:name":"Wilmington Realty",
    "wof:placetype":"venue"
},
  "geometry": {"coordinates":[-77.898945,34.214518],"type":"Point"}
}