{
  "type": "Feature",
  "properties": {
    "iso:country":"US",
    "sg:address":"109 Everette St",
    "sg:city":"Princeton",
    "sg:classifiers":[
        {
            "category":"Building & Trades",
            "subcategory":"Construction",
            "type":"Services"
        }
    ],
    "sg:phone":"+1 919 936 9992",
    "sg:postcode":"27569",
    "sg:province":"NC",
    "sg:tags":[
        "utility",
        "contractor"
    ],
    "wof:name":"Portland Utilities Constr Co",
    "wof:placetype":"venue"
},
  "geometry": {"coordinates":[-78.166584,35.468207],"type":"Point"}
}