{
  "type": "Feature",
  "properties": {
    "iso:country":"US",
    "sg:address":"201 E Water St",
    "sg:city":"Statesville",
    "sg:classifiers":[
        {
            "category":"Government",
            "subcategory":"Office",
            "type":"Public Place"
        }
    ],
    "sg:phone":"+1 704 878 5353",
    "sg:postcode":"28677",
    "sg:province":"NC",
    "sg:tags":[
        "county",
        "safety",
        "order"
    ],
    "wof:name":"Iredell County Emergency Mgmt",
    "wof:placetype":"venue"
},
  "geometry": {"coordinates":[-80.88597900000001,35.787102],"type":"Point"}
}