{
  "type": "Feature",
  "properties": {
    "addr:full":"115 Clark St Gaston NC 27832",
    "addr:housenumber":"115",
    "addr:postcode":"27832",
    "addr:street":"Clark St",
    "iso:country":"US",
    "sg:address":"115 Clark St",
    "sg:city":"Gaston",
    "sg:classifiers":[
        {
            "category":"Organizations",
            "subcategory":"Religious Organization",
            "type":"Services"
        }
    ],
    "sg:phone":"+1   ",
    "sg:postcode":"27832",
    "sg:province":"NC",
    "wof:name":"Evangelical Methodist Chu",
    "wof:placetype":"venue"
},
  "geometry": {"coordinates":[-77.637117,36.502577],"type":"Point"}
}