{
  "type": "Feature",
  "properties": {
    "addr:full":"470 US Hwy 29 S China Grove NC 28023",
    "addr:housenumber":"470",
    "addr:postcode":"28023",
    "addr:street":"Us Hwy 29 S China Grove",
    "iso:country":"US",
    "sg:address":"470 US Hwy 29 S",
    "sg:city":"China Grove",
    "sg:classifiers":[
        {
            "category":"Autos & Motor Vehicles",
            "subcategory":"Automobile Sales",
            "type":"Retail Goods"
        }
    ],
    "sg:phone":"+1 704 855 5573",
    "sg:postcode":"28023",
    "sg:province":"NC",
    "sg:tags":[
        "car",
        "dealer"
    ],
    "wof:name":"Road Runner Auto Sales",
    "wof:placetype":"venue"
},
  "geometry": {"coordinates":[-80.578456,35.563181],"type":"Point"}
}