{
  "type": "Feature",
  "properties": {
    "addr:full":"128 Overhill Dr Mooresville NC 28117",
    "addr:housenumber":"128",
    "addr:postcode":"28117",
    "addr:street":"Overhill Dr",
    "iso:country":"US",
    "sg:address":"128 Overhill Dr",
    "sg:city":"Mooresville",
    "sg:classifiers":[
        {
            "category":"Real Estate",
            "subcategory":"Surveying",
            "type":"Services"
        }
    ],
    "sg:phone":"+1 704 662 0100",
    "sg:postcode":"28117",
    "sg:province":"NC",
    "sg:tags":[
        "engineering"
    ],
    "wof:name":"Patterson Brewer & Assoc PA",
    "wof:placetype":"venue"
},
  "geometry": {"coordinates":[-80.849402,35.599404],"type":"Point"}
}