{
  "type": "Feature",
  "properties": {
    "iso:country":"US",
    "sg:address":"166 Skyview Cir",
    "sg:city":"Asheville",
    "sg:classifiers":[
        {
            "category":"Professional",
            "type":"Services"
        },
        {
            "category":"Wholesale",
            "subcategory":"Durable Goods & Equipment",
            "type":"Manufacturing & Wholesale Goods"
        }
    ],
    "sg:phone":"+1 828 259 9988",
    "sg:postcode":"28804",
    "sg:province":"NC",
    "sg:tags":[
        "representative",
        "manufacturer"
    ],
    "wof:name":"William A Walker LLC",
    "wof:placetype":"venue"
},
  "geometry": {"coordinates":[-82.534969,35.638307],"type":"Point"}
}