{
  "type": "Feature",
  "properties": {
    "addr:full":"4077 Sunrise Dr Kannapolis NC 28083",
    "addr:housenumber":"4077",
    "addr:postcode":"28083",
    "addr:street":"Sunrise Dr",
    "iso:country":"US",
    "sg:address":"4077 Sunrise Dr",
    "sg:city":"Kannapolis",
    "sg:classifiers":[
        {
            "category":"Professional",
            "subcategory":"Computer Services",
            "type":"Services"
        }
    ],
    "sg:phone":"+1   ",
    "sg:postcode":"28083",
    "sg:province":"NC",
    "sg:tags":[
        "programing",
        "custom"
    ],
    "wof:name":"Twisted Circle Tech",
    "wof:placetype":"venue"
},
  "geometry": {"coordinates":[-80.57342,35.469989],"type":"Point"}
}