{
  "type": "Feature",
  "properties": {
    "iso:country":"US",
    "sg:address":"2424 Hillsborough St",
    "sg:city":"Raleigh",
    "sg:classifiers":[
        {
            "category":"Restaurant",
            "type":"Food & Drink"
        }
    ],
    "sg:phone":"+1 919 828 8813",
    "sg:postcode":"27607",
    "sg:province":"NC",
    "sg:tags":[
        "eating"
    ],
    "wof:name":"College Grill",
    "wof:placetype":"venue"
},
  "geometry": {"coordinates":[-78.66793800000001,35.787794],"type":"Point"}
}