{
  "type": "Feature",
  "properties": {
    "addr:full":"847 Brantleytown Rd Zebulon NC 27597",
    "addr:housenumber":"847",
    "addr:postcode":"27597",
    "addr:street":"Brantleytown Rd",
    "iso:country":"US",
    "sg:address":"847 Brantleytown Rd",
    "sg:city":"Zebulon",
    "sg:classifiers":[
        {
            "category":"Building & Trades",
            "subcategory":"Construction",
            "type":"Services"
        }
    ],
    "sg:phone":"+1 919 496 5883",
    "sg:postcode":"27597",
    "sg:province":"NC",
    "sg:tags":[
        "house"
    ],
    "wof:name":"Bakers Mfg Home Service",
    "wof:placetype":"venue"
},
  "geometry": {"coordinates":[-78.288431,35.93795],"type":"Point"}
}