{
  "type": "Feature",
  "properties": {
    "iso:country":"US",
    "sg:address":"643 Tamco Rd",
    "sg:city":"Reidsville",
    "sg:classifiers":[
        {
            "category":"Wholesale",
            "subcategory":"Metals & Minerals",
            "type":"Manufacturing & Wholesale Goods"
        }
    ],
    "sg:phone":"+1 336 349 6057",
    "sg:postcode":"27320",
    "sg:province":"NC",
    "sg:tags":[
        "steel",
        "warehouse"
    ],
    "wof:name":"Tri-State Steel Products Inc",
    "wof:placetype":"venue"
},
  "geometry": {"coordinates":[-79.630301,36.325074],"type":"Point"}
}