{
  "type": "Feature",
  "properties": {
    "iso:country":"US",
    "sg:address":"130 Wooded Acres Dr",
    "sg:city":"Newport",
    "sg:classifiers":[
        {
            "category":"Arts & Performance",
            "subcategory":"Theater",
            "type":"Entertainment"
        }
    ],
    "sg:phone":"+1 252 726 8365",
    "sg:postcode":"28570",
    "sg:province":"NC",
    "sg:tags":[
        "live",
        "music"
    ],
    "wof:name":"Party Tyme Music",
    "wof:placetype":"venue"
},
  "geometry": {"coordinates":[-76.861831,34.745736],"type":"Point"}
}