{
  "type": "Feature",
  "properties": {
    "iso:country":"US",
    "sg:address":"190 Cape Cod Way",
    "sg:city":"Mooresville",
    "sg:classifiers":[
        {
            "category":"Building & Trades",
            "subcategory":"Construction",
            "type":"Services"
        }
    ],
    "sg:phone":"+1 704 799 1688",
    "sg:postcode":"28117",
    "sg:province":"NC",
    "sg:tags":[
        "contractor"
    ],
    "wof:name":"David Dibble Custom Homes",
    "wof:placetype":"venue"
},
  "geometry": {"coordinates":[-80.92965599999999,35.518499],"type":"Point"}
}