{
  "type": "Feature",
  "properties": {
    "addr:full":"1500 Old Washington Rd Vanceboro NC 28586",
    "addr:housenumber":"1500",
    "addr:postcode":"28586",
    "addr:street":"Old Washington Rd",
    "iso:country":"US",
    "sg:address":"1500 Old Washington Rd",
    "sg:city":"Vanceboro",
    "sg:classifiers":[
        {
            "category":"Farming",
            "subcategory":"Farm",
            "type":"Manufacturing & Wholesale Goods"
        }
    ],
    "sg:phone":"+1 252 244 1629",
    "sg:postcode":"28586",
    "sg:province":"NC",
    "wof:name":"Palmetto Nursery",
    "wof:placetype":"venue"
},
  "geometry": {"coordinates":[-77.14551299999999,35.35311],"type":"Point"}
}