{
  "type": "Feature",
  "properties": {
    "iso:country":"US",
    "sg:address":"212 South St",
    "sg:city":"Belmont",
    "sg:classifiers":[
        {
            "category":"Organizations",
            "subcategory":"Religious Organization",
            "type":"Services"
        }
    ],
    "sg:phone":"+1   ",
    "sg:postcode":"28012",
    "sg:province":"NC",
    "wof:name":"Mt Pleasant Baptist Church",
    "wof:placetype":"venue"
},
  "geometry": {"coordinates":[-81.035269,35.231277],"type":"Point"}
}