{
  "type": "Feature",
  "properties": {
    "iso:country":"US",
    "sg:address":"1210 Pressley Rd",
    "sg:city":"Charlotte",
    "sg:classifiers":[
        {
            "category":"Professional",
            "type":"Services"
        }
    ],
    "sg:phone":"+1 704 521 2890",
    "sg:postcode":"28217",
    "sg:province":"NC",
    "wof:name":"Gegregorio",
    "wof:placetype":"venue"
},
  "geometry": {"coordinates":[-80.895034,35.192853],"type":"Point"}
}