{
  "type": "Feature",
  "properties": {
    "iso:country":"US",
    "sg:address":"1125 US Hwy 17",
    "sg:city":"Elizabeth City",
    "sg:phone":"+1 252 331 1191",
    "sg:postcode":"27909",
    "sg:province":"NC",
    "sg:tags":[
        "equipment",
        "station"
    ],
    "wof:name":"Northeastern Oil Co",
    "wof:placetype":"venue"
},
  "geometry": {"coordinates":[-76.219264,36.320229],"type":"Point"}
}