{
  "type": "Feature",
  "properties": {
    "iso:country":"US",
    "sg:address":"1185 Salem Lake Rd",
    "sg:city":"Winston Salem",
    "sg:classifiers":[
        {
            "category":"Social Services",
            "subcategory":"Child Care",
            "type":"Services"
        }
    ],
    "sg:phone":"+1 336 788 1902",
    "sg:postcode":"27107",
    "sg:province":"NC",
    "sg:tags":[
        "day"
    ],
    "wof:name":"Granny's Childcare",
    "wof:placetype":"venue"
},
  "geometry": {"coordinates":[-80.191085,36.086856],"type":"Point"}
}