{
  "type": "Feature",
  "properties": {
    "iso:country":"US",
    "sg:address":"801 Forest Hill Dr",
    "sg:city":"Greensboro",
    "sg:classifiers":[
        {
            "category":"Building & Trades",
            "subcategory":"Construction",
            "type":"Services"
        }
    ],
    "sg:phone":"+1 336 294 4875",
    "sg:postcode":"27410",
    "sg:province":"NC",
    "sg:tags":[
        "house",
        "builder",
        "operative"
    ],
    "wof:name":"Fraley B Company LLC",
    "wof:placetype":"venue"
},
  "geometry": {"coordinates":[-79.849323,36.091013],"type":"Point"}
}