{
  "type": "Feature",
  "properties": {
    "addr:full":"5121 Everette Ct Wilmington NC 28412",
    "addr:housenumber":"5121",
    "addr:postcode":"28412",
    "addr:street":"Everette Ct",
    "iso:country":"US",
    "sg:address":"5121 Everette Ct",
    "sg:city":"Wilmington",
    "sg:classifiers":[
        {
            "category":"Professional",
            "type":"Services"
        }
    ],
    "sg:phone":"+1   ",
    "sg:postcode":"28412",
    "sg:province":"NC",
    "wof:name":"Roger Marshall Services",
    "wof:placetype":"venue"
},
  "geometry": {"coordinates":[-77.898901,34.152221],"type":"Point"}
}