{
  "type": "Feature",
  "properties": {
    "addr:full":"2116 Wilkinson Blvd Charlotte NC 28208",
    "addr:housenumber":"2116",
    "addr:postcode":"28208",
    "addr:street":"Wilkinson Blvd",
    "iso:country":"US",
    "sg:address":"2116 Wilkinson Blvd",
    "sg:city":"Charlotte",
    "sg:classifiers":[
        {
            "category":"Shopping",
            "subcategory":"Stationery & Office Supplies",
            "type":"Retail Goods"
        },
        {
            "category":"Organizations",
            "subcategory":"Professional Association",
            "type":"Services"
        }
    ],
    "sg:phone":"+1 704 377 1740",
    "sg:postcode":"28208",
    "sg:province":"NC",
    "sg:tags":[
        "teacher",
        "store"
    ],
    "wof:name":"Classroom Central Inc",
    "wof:placetype":"venue"
},
  "geometry": {"coordinates":[-80.87642,35.2237],"type":"Point"}
}