{
  "type": "Feature",
  "properties": {
    "addr:full":"8406 W Nc 10 Hwy Vale NC 28168",
    "addr:housenumber":"8406",
    "addr:postcode":"28168",
    "addr:street":"W Nc 10 Hwy",
    "iso:country":"US",
    "sg:address":"8406 W Nc 10 Hwy",
    "sg:city":"Vale",
    "sg:classifiers":[
        {
            "category":"Home & Garden",
            "subcategory":"Building Materials",
            "type":"Retail Goods"
        }
    ],
    "sg:phone":"+1 704 462 0767",
    "sg:postcode":"28168",
    "sg:province":"NC",
    "wof:name":"MD Deviney Lumber Company",
    "wof:placetype":"venue"
},
  "geometry": {"coordinates":[-81.454156,35.577018],"type":"Point"}
}