{
  "type": "Feature",
  "properties": {
    "addr:full":"8324 Statesville Rd Charlotte NC 28269",
    "addr:housenumber":"8324",
    "addr:postcode":"28269",
    "addr:street":"Statesville Rd",
    "iso:country":"US",
    "sg:address":"8324 Statesville Rd",
    "sg:city":"Charlotte",
    "sg:classifiers":[
        {
            "category":"Recreation",
            "type":"Entertainment"
        }
    ],
    "sg:phone":"+1   ",
    "sg:postcode":"28269",
    "sg:province":"NC",
    "wof:name":"Kellys",
    "wof:placetype":"venue"
},
  "geometry": {"coordinates":[-80.842602,35.335413],"type":"Point"}
}