{
  "type": "Feature",
  "properties": {
    "iso:country":"US",
    "sg:address":"3402 Mandy Ln",
    "sg:city":"Morehead City",
    "sg:classifiers":[
        {
            "category":"Health Services",
            "subcategory":"Health Practitioner",
            "type":"Services"
        }
    ],
    "sg:phone":"+1   ",
    "sg:postcode":"28557",
    "sg:province":"NC",
    "wof:name":"Lauve James E Ccsw Bcd",
    "wof:placetype":"venue"
},
  "geometry": {"coordinates":[-76.752701,34.736244],"type":"Point"}
}