{
  "type": "Feature",
  "properties": {
    "iso:country":"US",
    "sg:address":"6929 US Hwy 70",
    "sg:city":"Newport",
    "sg:classifiers":[
        {
            "category":"Real Estate",
            "subcategory":"Real Estate Agent",
            "type":"Services"
        }
    ],
    "sg:phone":"+1 252 223 3333",
    "sg:postcode":"28570",
    "sg:province":"NC",
    "wof:name":"First Realty",
    "wof:placetype":"venue"
},
  "geometry": {"coordinates":[-76.875918,34.787968],"type":"Point"}
}