{
  "type": "Feature",
  "properties": {
    "addr:full":"8601 Monroe Rd Charlotte NC 28212",
    "addr:housenumber":"8601",
    "addr:postcode":"28212",
    "addr:street":"Monroe Rd",
    "iso:country":"US",
    "sg:address":"8601 Monroe Rd",
    "sg:city":"Charlotte",
    "sg:classifiers":[
        {
            "category":"Manufacturing",
            "subcategory":"Building Materials",
            "type":"Manufacturing & Wholesale Goods"
        },
        {
            "category":"Building & Trades",
            "subcategory":"Construction",
            "type":"Services"
        }
    ],
    "sg:phone":"+1 704 569 9941",
    "sg:postcode":"28212",
    "sg:province":"NC",
    "sg:tags":[
        "planning",
        "mfg",
        "cabinet",
        "wood",
        "remodeling",
        "kitchen"
    ],
    "wof:name":"Howdens Millwork Inc",
    "wof:placetype":"venue"
},
  "geometry": {"coordinates":[-80.746583,35.153357],"type":"Point"}
}