{
  "type": "Feature",
  "properties": {
    "addr:full":"1036 W Northwest Blvd Winston Salem NC 27101",
    "addr:housenumber":"1036",
    "addr:postcode":"27101",
    "addr:street":"W Northwest Blvd",
    "iso:country":"US",
    "sg:address":"1036 W Northwest Blvd",
    "sg:city":"Winston Salem",
    "sg:classifiers":[
        {
            "category":"Professional",
            "subcategory":"Art Services",
            "type":"Services"
        }
    ],
    "sg:phone":"+1 336 725 2223",
    "sg:postcode":"27101",
    "sg:province":"NC",
    "sg:tags":[
        "artist"
    ],
    "wof:name":"Eclectible Shop",
    "wof:placetype":"venue"
},
  "geometry": {"coordinates":[-80.26076999999999,36.103564],"type":"Point"}
}