{
  "type": "Feature",
  "properties": {
    "iso:country":"US",
    "sg:address":"611 E Franklin Blvd",
    "sg:city":"Gastonia",
    "sg:classifiers":[
        {
            "category":"Recreation",
            "type":"Entertainment"
        },
        {
            "category":"Bars & Pubs",
            "type":"Food & Drink"
        }
    ],
    "sg:phone":"+1 704 869 6340",
    "sg:postcode":"28054",
    "sg:province":"NC",
    "wof:name":"Screwball's Bar & Billiards",
    "wof:placetype":"venue"
},
  "geometry": {"coordinates":[-81.171998,35.262242],"type":"Point"}
}