{
  "type": "Feature",
  "properties": {
    "addr:full":"212 Ashville Ave Cary NC 27518",
    "addr:housenumber":"212",
    "addr:postcode":"27518",
    "addr:street":"Ashville Ave",
    "iso:country":"US",
    "sg:address":"212 Ashville Ave",
    "sg:city":"Cary",
    "sg:classifiers":[
        {
            "category":"Health Services",
            "subcategory":"Doctor",
            "type":"Services"
        }
    ],
    "sg:phone":"+1 919 233 6000",
    "sg:postcode":"27518",
    "sg:province":"NC",
    "sg:tags":[
        "physician",
        "surgeon"
    ],
    "sg:website":"www.caryhealthcareassociates.com",
    "wof:name":"Cary Health Care Assoc",
    "wof:placetype":"venue"
},
  "geometry": {"coordinates":[-78.786338,35.738542],"type":"Point"}
}