{
  "type": "Feature",
  "properties": {
    "addr:full":"2461 Arty Ave Charlotte NC 28208",
    "addr:housenumber":"2461",
    "addr:postcode":"28208",
    "addr:street":"Arty Ave",
    "iso:country":"US",
    "sg:address":"2461 Arty Ave",
    "sg:city":"Charlotte",
    "sg:classifiers":[
        {
            "category":"Organizations",
            "subcategory":"Religious Organization",
            "type":"Services"
        }
    ],
    "sg:phone":"+1 704 392 2116",
    "sg:postcode":"28208",
    "sg:province":"NC",
    "sg:tags":[
        "churches-presbyterian-usa",
        "church"
    ],
    "sg:website":"http://www.pcwoodbury.com",
    "wof:name":"Christ Presbyterian Church",
    "wof:placetype":"venue"
},
  "geometry": {"coordinates":[-80.88094,35.224902],"type":"Point"}
}