{
  "type": "Feature",
  "properties": {
    "addr:full":"5301 The Dyke Dr Raleigh NC 27606",
    "addr:housenumber":"5301",
    "addr:postcode":"27606",
    "addr:street":"The Dyke Dr",
    "iso:country":"US",
    "sg:address":"5301 The Dyke Dr",
    "sg:city":"Raleigh",
    "sg:classifiers":[
        {
            "category":"Building & Trades",
            "subcategory":"Construction",
            "type":"Services"
        }
    ],
    "sg:phone":"+1 919 696 9550",
    "sg:postcode":"27606",
    "sg:province":"NC",
    "sg:tags":[
        "contractor"
    ],
    "wof:name":"Perfect Spaces",
    "wof:placetype":"venue"
},
  "geometry": {"coordinates":[-78.779222,35.710463],"type":"Point"}
}