{
  "type": "Feature",
  "properties": {
    "iso:country":"US",
    "sg:address":"211 Providence Rd",
    "sg:city":"Chapel Hill",
    "sg:classifiers":[
        {
            "category":"Health Services",
            "subcategory":"Health Practitioner",
            "type":"Services"
        }
    ],
    "sg:phone":"+1 919 493 6183",
    "sg:postcode":"27514",
    "sg:province":"NC",
    "sg:tags":[
        "counseling",
        "mental"
    ],
    "wof:name":"Wilner Margaret E Lcsw",
    "wof:placetype":"venue"
},
  "geometry": {"coordinates":[-79.00720200000001,35.952599],"type":"Point"}
}