{
  "type": "Feature",
  "properties": {
    "addr:full":"351 N Front St Wilmington NC 28401",
    "addr:housenumber":"351",
    "addr:postcode":"28401",
    "addr:street":"N Front St",
    "iso:country":"US",
    "sg:address":"351 N Front St",
    "sg:city":"Wilmington",
    "sg:classifiers":[
        {
            "category":"Professional",
            "subcategory":"Business Services",
            "type":"Services"
        }
    ],
    "sg:phone":"+1 910 762 6093",
    "sg:postcode":"28401",
    "sg:province":"NC",
    "sg:tags":[
        "interior",
        "consultant",
        "design",
        "decorator"
    ],
    "wof:name":"Keen Interiors",
    "wof:placetype":"venue"
},
  "geometry": {"coordinates":[-77.949296,34.239335],"type":"Point"}
}