{
  "type": "Feature",
  "properties": {
    "iso:country":"US",
    "sg:address":"813 Churchill Dr",
    "sg:city":"Chapel Hill",
    "sg:classifiers":[
        {
            "category":"Manufacturing",
            "subcategory":"Printing",
            "type":"Manufacturing & Wholesale Goods"
        }
    ],
    "sg:phone":"+1 919 933 1867",
    "sg:postcode":"27517",
    "sg:province":"NC",
    "sg:tags":[
        "periodical"
    ],
    "wof:name":"Science Publishing Inc",
    "wof:placetype":"venue"
},
  "geometry": {"coordinates":[-79.01273,35.924806],"type":"Point"}
}