{
  "type": "Feature",
  "properties": {
    "iso:country":"US",
    "sg:address":"1010 N Main St",
    "sg:city":"High Point",
    "sg:classifiers":[
        {
            "category":"Food & Beverages",
            "subcategory":"Groceries & Convenience Stores",
            "type":"Retail Goods"
        }
    ],
    "sg:phone":"+1 336 887 2567",
    "sg:postcode":"27262",
    "sg:province":"NC",
    "wof:name":"Fairway One Stop 19",
    "wof:placetype":"venue"
},
  "geometry": {"coordinates":[-80.01455799999999,35.968139],"type":"Point"}
}