{
  "type": "Feature",
  "properties": {
    "addr:full":"3852 Bill Holden Rd SW South Brunswick NC 28470",
    "addr:housenumber":"3852",
    "addr:postcode":"28470",
    "addr:street":"Bill Holden Rd Sw",
    "iso:country":"US",
    "sg:address":"3852 Bill Holden Rd SW",
    "sg:city":"South Brunswick",
    "sg:classifiers":[
        {
            "category":"Restaurant",
            "type":"Food & Drink"
        }
    ],
    "sg:phone":"+1 910 579 6373",
    "sg:postcode":"28470",
    "sg:province":"NC",
    "sg:tags":[
        "eating"
    ],
    "sg:website":"www.twinlakesseafood.com",
    "wof:name":"Twin Lakes Seafood Restaurant",
    "wof:placetype":"venue"
},
  "geometry": {"coordinates":[-78.369518,33.931574],"type":"Point"}
}