{
  "type": "Feature",
  "properties": {
    "addr:full":"4744 Lakeview Acres Rd Valdese NC 28690",
    "addr:housenumber":"4744",
    "addr:postcode":"28690",
    "addr:street":"Lakeview Acres Rd",
    "iso:country":"US",
    "sg:address":"4744 Lakeview Acres Rd",
    "sg:city":"Valdese",
    "sg:classifiers":[
        {
            "category":"Organizations",
            "subcategory":"Religious Organization",
            "type":"Services"
        }
    ],
    "sg:phone":"+1 828 874 0717",
    "sg:postcode":"28690",
    "sg:province":"NC",
    "sg:tags":[
        "church"
    ],
    "wof:name":"Lakeview Baptist Church",
    "wof:placetype":"venue"
},
  "geometry": {"coordinates":[-81.57149,35.769592],"type":"Point"}
}