{
  "type": "Feature",
  "properties": {
    "iso:country":"US",
    "sg:address":"2635 Buck Mountain Trl",
    "sg:city":"Sophia",
    "sg:classifiers":[
        {
            "category":"Retail",
            "subcategory":"Repair Shop",
            "type":"Services"
        },
        {
            "category":"Retail",
            "subcategory":"Laundry & Dry Cleaning",
            "type":"Services"
        }
    ],
    "sg:phone":"+1 336 625 9093",
    "sg:postcode":"27350",
    "sg:province":"NC",
    "sg:tags":[
        "cleaners",
        "rug",
        "carpet"
    ],
    "wof:name":"Buck's Deep Steam Carpet Clng",
    "wof:placetype":"venue"
},
  "geometry": {"coordinates":[-79.89191599999999,35.759527],"type":"Point"}
}