{
  "type": "Feature",
  "properties": {
    "addr:full":"10716 Carmel Commons Blvd Charlotte NC 28226",
    "addr:housenumber":"10716",
    "addr:postcode":"28226",
    "addr:street":"Carmel Commons Blvd",
    "iso:country":"US",
    "sg:address":"10716 Carmel Commons Blvd",
    "sg:city":"Charlotte",
    "sg:classifiers":[
        {
            "category":"Insurance",
            "subcategory":"Insurance Agent",
            "type":"Services"
        }
    ],
    "sg:phone":"+1 704 542 5012",
    "sg:postcode":"28226",
    "sg:province":"NC",
    "wof:name":"Mary Klenz Agency",
    "wof:placetype":"venue"
},
  "geometry": {"coordinates":[-80.850938,35.087409],"type":"Point"}
}