{
  "type": "Feature",
  "properties": {
    "iso:country":"US",
    "sg:address":"4491 Wayne Memorial Dr",
    "sg:city":"Goldsboro",
    "sg:classifiers":[
        {
            "category":"Organizations",
            "subcategory":"Labor Organization",
            "type":"Services"
        }
    ],
    "sg:phone":"+1   ",
    "sg:postcode":"27534",
    "sg:province":"NC",
    "wof:name":"Lc Hill Construction",
    "wof:placetype":"venue"
},
  "geometry": {"coordinates":[-77.91933899999999,35.424998],"type":"Point"}
}