{
  "type": "Feature",
  "properties": {
    "addr:full":"2643 N Old Greensboro Rd High Point NC 27265",
    "addr:housenumber":"2643",
    "addr:postcode":"27265",
    "addr:street":"N Old Greensboro Rd",
    "iso:country":"US",
    "sg:address":"2643 N Old Greensboro Rd",
    "sg:city":"High Point",
    "sg:classifiers":[
        {
            "category":"Manufacturing",
            "subcategory":"Rubber & Plastics",
            "type":"Manufacturing & Wholesale Goods"
        }
    ],
    "sg:phone":"+1 336 889 2001",
    "sg:postcode":"27265",
    "sg:province":"NC",
    "sg:tags":[
        "product",
        "mfg"
    ],
    "wof:name":"Concept Plastics Inc",
    "wof:placetype":"venue"
},
  "geometry": {"coordinates":[-80.074088,35.976766],"type":"Point"}
}