{
  "type": "Feature",
  "properties": {
    "addr:full":"400 E Main St Burnsville NC 28714",
    "addr:housenumber":"400",
    "addr:postcode":"28714",
    "addr:street":"E Main St",
    "iso:country":"US",
    "sg:address":"400 E Main St",
    "sg:city":"Burnsville",
    "sg:classifiers":[
        {
            "category":"Building & Trades",
            "subcategory":"Construction",
            "type":"Services"
        }
    ],
    "sg:phone":"+1 828 682 7421",
    "sg:postcode":"28714",
    "sg:province":"NC",
    "sg:tags":[
        "residential"
    ],
    "wof:name":"Mayfair Properties LLC",
    "wof:placetype":"venue"
},
  "geometry": {"coordinates":[-82.290869,35.916478],"type":"Point"}
}