{
  "type": "Feature",
  "properties": {
    "iso:country":"US",
    "sg:address":"165 Gentian Way",
    "sg:city":"Waynesville",
    "sg:classifiers":[
        {
            "category":"Building & Trades",
            "subcategory":"Construction",
            "type":"Services"
        }
    ],
    "sg:phone":"+1 828 926 6150",
    "sg:postcode":"28785",
    "sg:province":"NC",
    "sg:tags":[
        "grading",
        "contractor"
    ],
    "wof:name":"Caroline-A-Contracting",
    "wof:placetype":"venue"
},
  "geometry": {"coordinates":[-83.023636,35.524944],"type":"Point"}
}