{
  "type": "Feature",
  "properties": {
    "iso:country":"US",
    "sg:address":"607 N Hill St",
    "sg:city":"Dallas",
    "sg:classifiers":[
        {
            "category":"Building & Trades",
            "subcategory":"Construction",
            "type":"Services"
        }
    ],
    "sg:phone":"+1 704 913 4416",
    "sg:postcode":"28034",
    "sg:province":"NC",
    "sg:tags":[
        "roofing",
        "contractor"
    ],
    "wof:name":"Kirksey's Roofing",
    "wof:placetype":"venue"
},
  "geometry": {"coordinates":[-81.172956,35.319276],"type":"Point"}
}