{
  "type": "Feature",
  "properties": {
    "iso:country":"US",
    "sg:address":"4702 Market St",
    "sg:city":"Wilmington",
    "sg:classifiers":[
        {
            "category":"Bars & Pubs",
            "type":"Food & Drink"
        }
    ],
    "sg:phone":"+1 910 350 1707",
    "sg:postcode":"28405",
    "sg:province":"NC",
    "sg:tags":[
        "lounge",
        "cocktail"
    ],
    "wof:name":"Fat Boy's",
    "wof:placetype":"venue"
},
  "geometry": {"coordinates":[-77.886403,34.243263],"type":"Point"}
}