{
  "type": "Feature",
  "properties": {
    "iso:country":"US",
    "sg:address":"307 Simpson St",
    "sg:city":"Conover",
    "sg:classifiers":[
        {
            "category":"Building & Trades",
            "subcategory":"Construction",
            "type":"Services"
        }
    ],
    "sg:phone":"+1 828 324 9310",
    "sg:postcode":"28613",
    "sg:province":"NC",
    "sg:tags":[
        "woodworker"
    ],
    "wof:name":"Oyama Woodworking",
    "wof:placetype":"venue"
},
  "geometry": {"coordinates":[-81.24670399999999,35.711184],"type":"Point"}
}