{
  "type": "Feature",
  "properties": {
    "iso:country":"US",
    "sg:address":"2543 Centergrove Rd",
    "sg:city":"Kannapolis",
    "sg:classifiers":[
        {
            "category":"Organizations",
            "subcategory":"Religious Organization",
            "type":"Services"
        }
    ],
    "sg:phone":"+1   ",
    "sg:postcode":"28083",
    "sg:province":"NC",
    "wof:name":"Concord Lake Baptist Church",
    "wof:placetype":"venue"
},
  "geometry": {"coordinates":[-80.580534,35.481729],"type":"Point"}
}