{
  "type": "Feature",
  "properties": {
    "addr:full":"111 E Main St Lincolnton NC 28092",
    "addr:housenumber":"111",
    "addr:postcode":"28092",
    "addr:street":"E Main St",
    "iso:country":"US",
    "sg:address":"111 E Main St",
    "sg:city":"Lincolnton",
    "sg:classifiers":[
        {
            "category":"Shopping",
            "subcategory":"Bicycles & Sporting Goods",
            "type":"Retail Goods"
        }
    ],
    "sg:phone":"+1 704 732 3403",
    "sg:postcode":"28092",
    "sg:province":"NC",
    "sg:tags":[
        "screen",
        "printing"
    ],
    "wof:name":"Lincoln Athletic Company",
    "wof:placetype":"venue"
},
  "geometry": {"coordinates":[-81.255606,35.471877],"type":"Point"}
}