{
  "type": "Feature",
  "properties": {
    "addr:full":"7580 Benwicke Ct Pfafftown NC 27040",
    "addr:housenumber":"7580",
    "addr:postcode":"27040",
    "addr:street":"Benwicke Ct",
    "iso:country":"US",
    "sg:address":"7580 Benwicke Ct",
    "sg:city":"Pfafftown",
    "sg:classifiers":[
        {
            "category":"Home & Garden",
            "subcategory":"Home Furnishings",
            "type":"Retail Goods"
        }
    ],
    "sg:phone":"+1 336 946 0551",
    "sg:postcode":"27040",
    "sg:province":"NC",
    "sg:tags":[
        "product",
        "cutlery",
        "sales"
    ],
    "wof:name":"Epocketknivescom",
    "wof:placetype":"venue"
},
  "geometry": {"coordinates":[-80.431572,36.128504],"type":"Point"}
}