{
  "type": "Feature",
  "properties": {
    "iso:country":"US",
    "sg:address":"202 Commerce Blvd",
    "sg:city":"Kings Mountain",
    "sg:classifiers":[
        {
            "category":"Wholesale",
            "subcategory":"Medical Equipment & Supplies",
            "type":"Manufacturing & Wholesale Goods"
        }
    ],
    "sg:phone":"+1 704 730 8117",
    "sg:postcode":"28086",
    "sg:province":"NC",
    "sg:tags":[
        "surgical"
    ],
    "wof:name":"Owens & Minor Inc",
    "wof:placetype":"venue"
},
  "geometry": {"coordinates":[-81.40341100000001,35.241266],"type":"Point"}
}