{
  "type": "Feature",
  "properties": {
    "addr:full":"306 Spring Branch Rd Dunn NC 28334",
    "addr:housenumber":"306",
    "addr:postcode":"28334",
    "addr:street":"Spring Branch Rd",
    "iso:country":"US",
    "sg:address":"306 Spring Branch Rd",
    "sg:city":"Dunn",
    "sg:classifiers":[
        {
            "category":"Retail",
            "subcategory":"Auto Repair",
            "type":"Services"
        }
    ],
    "sg:phone":"+1 910 892 7353",
    "sg:postcode":"28334",
    "sg:province":"NC",
    "sg:tags":[
        "repairing",
        "automobile"
    ],
    "wof:name":"Automobile Service Ctr",
    "wof:placetype":"venue"
},
  "geometry": {"coordinates":[-78.606137,35.297885],"type":"Point"}
}