{
  "type": "Feature",
  "properties": {
    "iso:country":"US",
    "sg:address":"1 Medical Center Blvd",
    "sg:city":"Winston Salem",
    "sg:classifiers":[
        {
            "category":"Health Services",
            "subcategory":"Doctor",
            "type":"Services"
        }
    ],
    "sg:phone":"+1 336 716 2588",
    "sg:postcode":"27157",
    "sg:province":"NC",
    "sg:tags":[
        "physician",
        "surgeon"
    ],
    "wof:name":"Wake Forest Univ Physicians",
    "wof:placetype":"venue"
},
  "geometry": {"coordinates":[-80.271501,36.090261],"type":"Point"}
}