{
  "type": "Feature",
  "properties": {
    "iso:country":"US",
    "sg:address":"125 North Ln",
    "sg:city":"Swannanoa",
    "sg:classifiers":[
        {
            "category":"Arena",
            "subcategory":"Sports Club",
            "type":"Entertainment"
        }
    ],
    "sg:phone":"+1   ",
    "sg:postcode":"28778",
    "sg:province":"NC",
    "wof:name":"Innovative Sports Solutions",
    "wof:placetype":"venue"
},
  "geometry": {"coordinates":[-82.440515,35.61571],"type":"Point"}
}