{
  "type": "Feature",
  "properties": {
    "iso:country":"US",
    "sg:address":"4933 Lailwood Cir",
    "sg:city":"Charlotte",
    "sg:classifiers":[
        {
            "category":"Wholesale",
            "subcategory":"Furniture",
            "type":"Manufacturing & Wholesale Goods"
        }
    ],
    "sg:phone":"+1 704 568 2811",
    "sg:postcode":"28227",
    "sg:province":"NC",
    "wof:name":"Connect Systems Inc",
    "wof:placetype":"venue"
},
  "geometry": {"coordinates":[-80.71289400000001,35.17698],"type":"Point"}
}