{
  "type": "Feature",
  "properties": {
    "addr:full":"1108 Shetland Ct Raleigh NC 27609",
    "addr:housenumber":"1108",
    "addr:postcode":"27609",
    "addr:street":"Shetland Ct",
    "iso:country":"US",
    "sg:address":"1108 Shetland Ct",
    "sg:city":"Raleigh",
    "sg:classifiers":[
        {
            "category":"Professional",
            "subcategory":"Lawyer & Legal Services",
            "type":"Services"
        }
    ],
    "sg:phone":"+1   ",
    "sg:postcode":"27609",
    "sg:province":"NC",
    "sg:tags":[
        "attorney"
    ],
    "wof:name":"David Henry Rogers",
    "wof:placetype":"venue"
},
  "geometry": {"coordinates":[-78.655597,35.866146],"type":"Point"}
}