{
  "type": "Feature",
  "properties": {
    "addr:full":"1473 New Hendersonville Hwy Pisgah Forest NC 28768",
    "addr:housenumber":"1473",
    "addr:postcode":"28768",
    "addr:street":"New Hendersonville Hwy",
    "iso:country":"US",
    "sg:address":"1473 New Hendersonville Hwy",
    "sg:city":"Pisgah Forest",
    "sg:classifiers":[
        {
            "category":"Manufacturing",
            "subcategory":"Printing",
            "type":"Manufacturing & Wholesale Goods"
        }
    ],
    "sg:phone":"+1 828 877 3904",
    "sg:postcode":"28768",
    "sg:province":"NC",
    "sg:tags":[
        "publisher"
    ],
    "wof:name":"Transylvania County Buyers Gui",
    "wof:placetype":"venue"
},
  "geometry": {"coordinates":[-82.684164,35.270173],"type":"Point"}
}