{
  "type": "Feature",
  "properties": {
    "addr:full":"603 S Wall St Benson NC 27504",
    "addr:housenumber":"603",
    "addr:postcode":"27504",
    "addr:street":"S Wall St",
    "iso:country":"US",
    "sg:address":"603 S Wall St",
    "sg:city":"Benson",
    "sg:classifiers":[
        {
            "category":"Home & Garden",
            "subcategory":"Furniture",
            "type":"Retail Goods"
        }
    ],
    "sg:phone":"+1 919 894 4241",
    "sg:postcode":"27504",
    "sg:province":"NC",
    "wof:name":"Holland Furniture Co",
    "wof:placetype":"venue"
},
  "geometry": {"coordinates":[-78.552423,35.377825],"type":"Point"}
}