{
  "type": "Feature",
  "properties": {
    "addr:full":"13501 S Old Statesville Rd Huntersville NC 28078",
    "addr:housenumber":"13501",
    "addr:postcode":"28078",
    "addr:street":"S Old Statesville Rd",
    "iso:country":"US",
    "sg:address":"13501 S Old Statesville Rd",
    "sg:city":"Huntersville",
    "sg:classifiers":[
        {
            "category":"Manufacturing",
            "subcategory":"Paper Products",
            "type":"Manufacturing & Wholesale Goods"
        }
    ],
    "sg:phone":"+1 704 875 8234",
    "sg:postcode":"28078",
    "sg:province":"NC",
    "sg:tags":[
        "bamboo"
    ],
    "sg:website":"http://www.dearnessgardens.com",
    "wof:name":"Dearness Gardens",
    "wof:placetype":"venue"
},
  "geometry": {"coordinates":[-80.839249,35.401741],"type":"Point"}
}