{
  "type": "Feature",
  "properties": {
    "addr:full":"203 Ward Blvd Wilson NC 27893",
    "addr:housenumber":"203",
    "addr:postcode":"27893",
    "addr:street":"Ward Blvd",
    "iso:country":"US",
    "sg:address":"203 Ward Blvd",
    "sg:city":"Wilson",
    "sg:classifiers":[
        {
            "category":"Restaurant",
            "type":"Food & Drink"
        }
    ],
    "sg:menulink":"http://www.allmenus.com/nc/wilson/137712-subway/menu/",
    "sg:phone":"+1 252 291 3536",
    "sg:postcode":"27893",
    "sg:province":"NC",
    "sg:tags":[
        "american",
        "sandwich"
    ],
    "wof:name":"Subway",
    "wof:placetype":"venue"
},
  "geometry": {"coordinates":[-77.934917,35.734735],"type":"Point"}
}