{
  "type": "Feature",
  "properties": {
    "iso:country":"US",
    "sg:address":"5631 Racine Ave",
    "sg:city":"Charlotte",
    "sg:classifiers":[
        {
            "category":"Shopping",
            "subcategory":"Gifts & Souvenirs",
            "type":"Retail Goods"
        }
    ],
    "sg:phone":"+1 704 598 2225",
    "sg:postcode":"28269",
    "sg:province":"NC",
    "wof:name":"Americas Baseball Cards",
    "wof:placetype":"venue"
},
  "geometry": {"coordinates":[-80.799623,35.289252],"type":"Point"}
}