{
  "type": "Feature",
  "properties": {
    "iso:country":"US",
    "sg:address":"1501 Carrier Dr",
    "sg:city":"Charlotte",
    "sg:classifiers":[
        {
            "category":"Communications",
            "subcategory":"Radio Station",
            "type":"Services"
        }
    ],
    "sg:phone":"+1 704 393 1540",
    "sg:postcode":"28216",
    "sg:province":"NC",
    "sg:tags":[
        "broadcast"
    ],
    "wof:name":"Wgtb",
    "wof:placetype":"venue"
},
  "geometry": {"coordinates":[-80.859241,35.270982],"type":"Point"}
}