{
  "type": "Feature",
  "properties": {
    "addr:full":"906 N Horner Blvd Sanford NC 27330",
    "addr:housenumber":"906",
    "addr:postcode":"27330",
    "addr:street":"N Horner Blvd",
    "iso:country":"US",
    "sg:address":"906 N Horner Blvd",
    "sg:city":"Sanford",
    "sg:classifiers":[
        {
            "category":"Shopping",
            "subcategory":"Clothing, Apparel, & Fashions",
            "type":"Retail Goods"
        }
    ],
    "sg:phone":"+1 919 776 6667",
    "sg:postcode":"27330",
    "sg:province":"NC",
    "wof:name":"K Beauty Supplies",
    "wof:placetype":"venue"
},
  "geometry": {"coordinates":[-79.190129,35.491434],"type":"Point"}
}