{
  "type": "Feature",
  "properties": {
    "iso:country":"US",
    "sg:address":"122 E 1st St",
    "sg:city":"Kinston",
    "sg:classifiers":[
        {
            "category":"Government",
            "subcategory":"Office",
            "type":"Public Place"
        }
    ],
    "sg:phone":"+1 252 526 4415",
    "sg:postcode":"28504",
    "sg:province":"NC",
    "sg:tags":[
        "state",
        "program"
    ],
    "wof:name":"Transportation Equipment Grg",
    "wof:placetype":"venue"
},
  "geometry": {"coordinates":[-77.59508599999999,35.238971],"type":"Point"}
}