{
  "type": "Feature",
  "properties": {
    "addr:full":"419 Pine Valley Rd Jacksonville NC 28546",
    "addr:housenumber":"419",
    "addr:postcode":"28546",
    "addr:street":"Pine Valley Rd",
    "iso:country":"US",
    "sg:address":"419 Pine Valley Rd",
    "sg:city":"Jacksonville",
    "sg:classifiers":[
        {
            "category":"Personal",
            "subcategory":"Adult",
            "type":"Services"
        }
    ],
    "sg:phone":"+1 910 937 6969",
    "sg:postcode":"28546",
    "sg:province":"NC",
    "sg:tags":[
        "escort"
    ],
    "wof:name":"A Sexy Babes",
    "wof:placetype":"venue"
},
  "geometry": {"coordinates":[-77.368914,34.750406],"type":"Point"}
}