{
  "type": "Feature",
  "properties": {
    "addr:full":"2059 Suitts Store Rd Franklinton NC 27525",
    "addr:housenumber":"2059",
    "addr:postcode":"27525",
    "addr:street":"Suitts Store Rd",
    "iso:country":"US",
    "sg:address":"2059 Suitts Store Rd",
    "sg:city":"Franklinton",
    "sg:classifiers":[
        {
            "category":"Building & Trades",
            "subcategory":"Construction",
            "type":"Services"
        }
    ],
    "sg:phone":"+1 919 528 0675",
    "sg:postcode":"27525",
    "sg:province":"NC",
    "sg:tags":[
        "house"
    ],
    "wof:name":"Newlin Construction",
    "wof:placetype":"venue"
},
  "geometry": {"coordinates":[-78.54509899999999,36.119062],"type":"Point"}
}