{
  "type": "Feature",
  "properties": {
    "iso:country":"US",
    "sg:address":"149 E Holding Ave",
    "sg:city":"Wake Forest",
    "sg:classifiers":[
        {
            "category":"Organizations",
            "subcategory":"Religious Organization",
            "type":"Services"
        }
    ],
    "sg:phone":"+1 919 556 7144",
    "sg:postcode":"27587",
    "sg:province":"NC",
    "wof:name":"Tri-Area Ministry",
    "wof:placetype":"venue"
},
  "geometry": {"coordinates":[-78.51411400000001,35.972196],"type":"Point"}
}