{
  "type": "Feature",
  "properties": {
    "iso:country":"US",
    "sg:address":"124 State Hwy 901",
    "sg:city":"Harmony",
    "sg:classifiers":[
        {
            "category":"Wholesale",
            "subcategory":"Machinery & Supplies",
            "type":"Manufacturing & Wholesale Goods"
        }
    ],
    "sg:phone":"+1 336 492 5734",
    "sg:postcode":"28634",
    "sg:province":"NC",
    "sg:tags":[
        "farm",
        "equipment"
    ],
    "wof:name":"Blackwelder's Trading Post",
    "wof:placetype":"venue"
},
  "geometry": {"coordinates":[-80.69235,35.903533],"type":"Point"}
}