{
  "type": "Feature",
  "properties": {
    "iso:country":"US",
    "sg:address":"3500 Westgate Dr",
    "sg:city":"Durham",
    "sg:classifiers":[
        {
            "category":"Insurance",
            "subcategory":"Insurance Agent",
            "type":"Services"
        }
    ],
    "sg:phone":"+1 919 402 2801",
    "sg:postcode":"27707",
    "sg:province":"NC",
    "wof:name":"Integon Corporation",
    "wof:placetype":"venue"
},
  "geometry": {"coordinates":[-78.961094,35.96649],"type":"Point"}
}