{
  "type": "Feature",
  "properties": {
    "addr:full":"5706 Dallas Cherryville Hwy Bessemer City NC 28016",
    "addr:housenumber":"5706",
    "addr:postcode":"28016",
    "addr:street":"Dallas Cherryville Hwy",
    "iso:country":"US",
    "sg:address":"5706 Dallas Cherryville Hwy",
    "sg:city":"Bessemer City",
    "sg:classifiers":[
        {
            "category":"Freight",
            "type":"Transportation"
        }
    ],
    "sg:phone":"+1 704 435 6464",
    "sg:postcode":"28016",
    "sg:province":"NC",
    "sg:tags":[
        "general"
    ],
    "wof:name":"Pack N Stack Mini Storage",
    "wof:placetype":"venue"
},
  "geometry": {"coordinates":[-81.29863400000001,35.359878],"type":"Point"}
}