{
  "type": "Feature",
  "properties": {
    "iso:country":"US",
    "sg:address":"1534 E 14th St",
    "sg:city":"Greenville",
    "sg:classifiers":[
        {
            "category":"Restaurant",
            "type":"Food & Drink"
        }
    ],
    "sg:phone":"+1 252 758 8880",
    "sg:postcode":"27858",
    "sg:province":"NC",
    "sg:tags":[
        "eating"
    ],
    "wof:name":"Boss Hogs Backyard Barbeque",
    "wof:placetype":"venue"
},
  "geometry": {"coordinates":[-77.347065,35.591625],"type":"Point"}
}