{
  "type": "Feature",
  "properties": {
    "iso:country":"US",
    "sg:address":"335 Deaverview Rd",
    "sg:city":"Asheville",
    "sg:classifiers":[
        {
            "category":"Shopping",
            "subcategory":"Discount & Variety Stores",
            "type":"Retail Goods"
        }
    ],
    "sg:phone":"+1 828 258 1643",
    "sg:postcode":"28806",
    "sg:province":"NC",
    "sg:tags":[
        "merchandise",
        "general"
    ],
    "wof:name":"Amway",
    "wof:placetype":"venue"
},
  "geometry": {"coordinates":[-82.621729,35.580505],"type":"Point"}
}