{
  "type": "Feature",
  "properties": {
    "iso:country":"US",
    "sg:address":"111 Walters Dr",
    "sg:city":"Goldsboro",
    "sg:classifiers":[
        {
            "category":"Wholesale",
            "subcategory":"Durable Goods & Equipment",
            "type":"Manufacturing & Wholesale Goods"
        }
    ],
    "sg:phone":"+1 919 735 5337",
    "sg:postcode":"27534",
    "sg:province":"NC",
    "sg:tags":[
        "fire",
        "extinguisher"
    ],
    "wof:name":"Quality Fire Extinguisher Sale",
    "wof:placetype":"venue"
},
  "geometry": {"coordinates":[-77.9328,35.428095],"type":"Point"}
}