{
  "type": "Feature",
  "properties": {
    "iso:country":"US",
    "sg:address":"561 Emmett Jackson Rd",
    "sg:city":"Faison",
    "sg:phone":"+1 910 267 1151",
    "sg:postcode":"28341",
    "sg:province":"NC",
    "sg:tags":[
        "farm",
        "soybean"
    ],
    "wof:name":"Davis John",
    "wof:placetype":"venue"
},
  "geometry": {"coordinates":[-78.14572699999999,35.160505],"type":"Point"}
}