{
  "type": "Feature",
  "properties": {
    "addr:full":"127 W Main St Forest City NC 28043",
    "addr:housenumber":"127",
    "addr:postcode":"28043",
    "addr:street":"W Main St",
    "iso:country":"US",
    "sg:address":"127 W Main St",
    "sg:city":"Forest City",
    "sg:classifiers":[
        {
            "category":"Real Estate",
            "subcategory":"Real Estate Agent",
            "type":"Services"
        }
    ],
    "sg:phone":"+1 828 245 7400",
    "sg:postcode":"28043",
    "sg:province":"NC",
    "sg:tags":[
        "management"
    ],
    "wof:name":"Rentals Unlimited",
    "wof:placetype":"venue"
},
  "geometry": {"coordinates":[-81.864892,35.333718],"type":"Point"}
}