{
  "type": "Feature",
  "properties": {
    "iso:country":"US",
    "sg:address":"853 Greensboro St Exd",
    "sg:city":"Lexington",
    "sg:classifiers":[
        {
            "category":"Retail",
            "subcategory":"Repair Shop",
            "type":"Services"
        }
    ],
    "sg:phone":"+1 336 248 5550",
    "sg:postcode":"27295",
    "sg:province":"NC",
    "sg:tags":[
        "welding"
    ],
    "wof:name":"Earl Everhart Welding Shop",
    "wof:placetype":"venue"
},
  "geometry": {"coordinates":[-80.23825600000001,35.836406],"type":"Point"}
}