{
  "type": "Feature",
  "properties": {
    "iso:country":"US",
    "sg:address":"2104 Fayetteville Rd",
    "sg:city":"Rockingham",
    "sg:classifiers":[
        {
            "category":"Shopping",
            "subcategory":"Discount & Variety Stores",
            "type":"Retail Goods"
        }
    ],
    "sg:phone":"+1 910 410 0600",
    "sg:postcode":"28379",
    "sg:province":"NC",
    "wof:name":"Dollar General",
    "wof:placetype":"venue"
},
  "geometry": {"coordinates":[-79.742159,34.951073],"type":"Point"}
}