{
  "type": "Feature",
  "properties": {
    "iso:country":"US",
    "sg:address":"1017 N Wendover Rd",
    "sg:city":"Charlotte",
    "sg:classifiers":[
        {
            "category":"Food & Beverages",
            "subcategory":"Liquor & Beverages",
            "type":"Retail Goods"
        }
    ],
    "sg:phone":"+1 704 365 2495",
    "sg:postcode":"28211",
    "sg:province":"NC",
    "sg:tags":[
        "store"
    ],
    "sg:website":"http://www.meckabc.com",
    "wof:name":"Mecklenburg County Abc Store",
    "wof:placetype":"venue"
},
  "geometry": {"coordinates":[-80.796037,35.191767],"type":"Point"}
}