{
  "type": "Feature",
  "properties": {
    "addr:full":"4220 Ebert Rd Winston Salem NC 27127",
    "addr:postcode":"4220;27127",
    "addr:street":"Ebert Rd",
    "iso:country":"US",
    "sg:address":"4220 Ebert Rd",
    "sg:city":"Winston Salem",
    "sg:classifiers":[
        {
            "category":"Shopping",
            "type":"Retail Goods"
        }
    ],
    "sg:phone":"+1 336 788 6005",
    "sg:postcode":"27127",
    "sg:province":"NC",
    "sg:tags":[
        "spa",
        "hot",
        "tub"
    ],
    "wof:name":"Diversified Spa Products",
    "wof:placetype":"venue"
},
  "geometry": {"coordinates":[-80.293859,36.026531],"type":"Point"}
}