{
  "type": "Feature",
  "properties": {
    "addr:full":"816 N Old Stage Rd St Pauls NC 28384",
    "addr:housenumber":"816",
    "addr:postcode":"28384",
    "addr:street":"N Old Stage Rd St",
    "iso:country":"US",
    "sg:address":"816 N Old Stage Rd",
    "sg:city":"St Pauls",
    "sg:classifiers":[
        {
            "category":"Travel",
            "subcategory":"Travel Agent",
            "type":"Entertainment"
        }
    ],
    "sg:phone":"+1 910 865 2332",
    "sg:postcode":"28384",
    "sg:province":"NC",
    "sg:tags":[
        "agency",
        "bureau"
    ],
    "wof:name":"Debbie's Destinations",
    "wof:placetype":"venue"
},
  "geometry": {"coordinates":[-78.97749,34.817557],"type":"Point"}
}