{
  "type": "Feature",
  "properties": {
    "addr:full":"1440 York Pl Burlington NC 27215",
    "addr:housenumber":"1440",
    "addr:postcode":"27215",
    "addr:street":"York Pl",
    "iso:country":"US",
    "sg:address":"1440 York Pl",
    "sg:city":"Burlington",
    "sg:classifiers":[
        {
            "category":"Health Services",
            "subcategory":"Medical Lab",
            "type":"Services"
        }
    ],
    "sg:phone":"+1 800 222 7566",
    "sg:postcode":"27215",
    "sg:province":"NC",
    "sg:tags":[
        "testing",
        "paternity"
    ],
    "wof:name":"Laboratory Corporation America",
    "wof:placetype":"venue"
},
  "geometry": {"coordinates":[-79.47997599999999,36.102292],"type":"Point"}
}