{
  "type": "Feature",
  "properties": {
    "addr:full":"615 N Sharon Amity Rd Charlotte NC 28211",
    "addr:housenumber":"615",
    "addr:postcode":"28211",
    "addr:street":"N Sharon Amity Rd",
    "iso:country":"US",
    "sg:address":"615 N Sharon Amity Rd",
    "sg:city":"Charlotte",
    "sg:classifiers":[
        {
            "category":"Personal",
            "subcategory":"Beauty Salon",
            "type":"Services"
        }
    ],
    "sg:phone":"+1 704 365 9640",
    "sg:postcode":"28211",
    "sg:province":"NC",
    "wof:name":"Special Touch Salon",
    "wof:placetype":"venue"
},
  "geometry": {"coordinates":[-80.78899699999999,35.179273],"type":"Point"}
}