{
  "type": "Feature",
  "properties": {
    "iso:country":"US",
    "sg:address":"7411 Crowflock Ct",
    "sg:city":"Charlotte",
    "sg:classifiers":[
        {
            "category":"Wholesale",
            "subcategory":"Apparel",
            "type":"Manufacturing & Wholesale Goods"
        }
    ],
    "sg:phone":"+1 704 554 0160",
    "sg:postcode":"28226",
    "sg:province":"NC",
    "sg:tags":[
        "fabric"
    ],
    "wof:name":"Alfred Associates Inc",
    "wof:placetype":"venue"
},
  "geometry": {"coordinates":[-80.782079,35.111161],"type":"Point"}
}