{
  "type": "Feature",
  "properties": {
    "addr:full":"635 Coliseum Dr NW Winston Salem NC 27106",
    "addr:housenumber":"635",
    "addr:postcode":"27106",
    "addr:street":"Coliseum Dr Nw",
    "iso:country":"US",
    "sg:address":"635 Coliseum Dr NW",
    "sg:city":"Winston Salem",
    "sg:classifiers":[
        {
            "category":"Banks & Credit Unions",
            "subcategory":"Bank",
            "type":"Services"
        }
    ],
    "sg:phone":"+1 336 721 4001",
    "sg:postcode":"27106",
    "sg:province":"NC",
    "sg:tags":[
        "national",
        "commercial"
    ],
    "wof:name":"Bank of America",
    "wof:placetype":"venue"
},
  "geometry": {"coordinates":[-80.261909,36.124277],"type":"Point"}
}