{
  "type": "Feature",
  "properties": {
    "iso:country":"US",
    "sg:address":"1602 Phillips Ave",
    "sg:city":"Greensboro",
    "sg:classifiers":[
        {
            "category":"Restaurant",
            "type":"Food & Drink"
        }
    ],
    "sg:phone":"+1 336 370 1400",
    "sg:postcode":"27405",
    "sg:province":"NC",
    "sg:tags":[
        "eating"
    ],
    "wof:name":"T V Grill",
    "wof:placetype":"venue"
},
  "geometry": {"coordinates":[-79.761768,36.098998],"type":"Point"}
}