{
  "type": "Feature",
  "properties": {
    "iso:country":"US",
    "sg:address":"2321 N Davidson St",
    "sg:city":"Charlotte",
    "sg:classifiers":[
        {
            "category":"Manufacturing",
            "subcategory":"Rubber & Plastics",
            "type":"Manufacturing & Wholesale Goods"
        }
    ],
    "sg:phone":"+1 704 376 3582",
    "sg:postcode":"28205",
    "sg:province":"NC",
    "sg:tags":[
        "compounding",
        "resin",
        "custom"
    ],
    "wof:name":"Textile Rubber & Chemical Co",
    "wof:placetype":"venue"
},
  "geometry": {"coordinates":[-80.813492,35.240933],"type":"Point"}
}