{
  "type": "Feature",
  "properties": {
    "addr:full":"510 Commerce St Clinton NC 28328",
    "addr:housenumber":"510",
    "addr:postcode":"28328",
    "addr:street":"Commerce St",
    "iso:country":"US",
    "sg:address":"510 Commerce St",
    "sg:city":"Clinton",
    "sg:classifiers":[
        {
            "category":"Utilities",
            "subcategory":"Telephone",
            "type":"Services"
        }
    ],
    "sg:phone":"+1 910 299 5200",
    "sg:postcode":"28328",
    "sg:province":"NC",
    "sg:tags":[
        "company"
    ],
    "wof:name":"Sanmina SCI Inc",
    "wof:placetype":"venue"
},
  "geometry": {"coordinates":[-78.30489300000001,34.989145],"type":"Point"}
}