{
  "type": "Feature",
  "properties": {
    "iso:country":"US",
    "sg:address":"6311 High View Rd",
    "sg:city":"Greensboro",
    "sg:classifiers":[
        {
            "category":"Building & Trades",
            "subcategory":"Construction",
            "type":"Services"
        }
    ],
    "sg:phone":"+1 336 668 3097",
    "sg:postcode":"27410",
    "sg:province":"NC",
    "sg:tags":[
        "contractor"
    ],
    "wof:name":"Thompsons Pressure Washing",
    "wof:placetype":"venue"
},
  "geometry": {"coordinates":[-79.91916500000001,36.124964],"type":"Point"}
}