{
  "type": "Feature",
  "properties": {
    "iso:country":"US",
    "sg:address":"1724 Barber Rd",
    "sg:city":"Jamesville",
    "sg:phone":"+1 252 792 1220",
    "sg:postcode":"27846",
    "sg:province":"NC",
    "sg:tags":[
        "farm",
        "tobacco"
    ],
    "wof:name":"Howard Gardner",
    "wof:placetype":"venue"
},
  "geometry": {"coordinates":[-76.91155999999999,35.758687],"type":"Point"}
}