{
  "type": "Feature",
  "properties": {
    "addr:full":"570 Brevard Rd Ste 15 Asheville NC 28806",
    "addr:housenumber":"570;15",
    "addr:postcode":"28806",
    "addr:street":"Brevard Rd Ste",
    "iso:country":"US",
    "sg:address":"570 Brevard Rd Ste 15",
    "sg:city":"Asheville",
    "sg:classifiers":[
        {
            "category":"Wholesale",
            "subcategory":"Fruits & Vegetables",
            "type":"Manufacturing & Wholesale Goods"
        }
    ],
    "sg:phone":"+1 828 252 4851",
    "sg:postcode":"28806",
    "sg:province":"NC",
    "sg:tags":[
        "veggie"
    ],
    "wof:name":"Whitt's Produce",
    "wof:placetype":"venue"
},
  "geometry": {"coordinates":[-82.59989899999999,35.553902],"type":"Point"}
}