{
  "type": "Feature",
  "properties": {
    "addr:full":"8717 Body Shop Dr NE Leland NC 28451",
    "addr:housenumber":"8717",
    "addr:postcode":"28451",
    "addr:street":"Dr Ne",
    "iso:country":"US",
    "sg:address":"8717 Body Shop Dr NE",
    "sg:city":"Leland",
    "sg:classifiers":[
        {
            "category":"Retail",
            "subcategory":"Auto Repair",
            "type":"Services"
        }
    ],
    "sg:phone":"+1 910 371 2962",
    "sg:postcode":"28451",
    "sg:province":"NC",
    "sg:tags":[
        "body",
        "automobile",
        "painting"
    ],
    "wof:name":"Moore's Paint & Body Shop",
    "wof:placetype":"venue"
},
  "geometry": {"coordinates":[-78.056359,34.227908],"type":"Point"}
}