{
  "type": "Feature",
  "properties": {
    "iso:country":"US",
    "sg:address":"82 Westhaven Dr",
    "sg:city":"Asheville",
    "sg:classifiers":[
        {
            "category":"Real Estate",
            "subcategory":"Real Estate Agent",
            "type":"Services"
        }
    ],
    "sg:phone":"+1 828 254 2547",
    "sg:postcode":"28804",
    "sg:province":"NC",
    "wof:name":"Jim Reid Real Estate",
    "wof:placetype":"venue"
},
  "geometry": {"coordinates":[-82.533603,35.620668],"type":"Point"}
}