{
  "type": "Feature",
  "properties": {
    "addr:full":"1526 Dale Earnhardt Blvd Kannapolis NC 28083",
    "addr:housenumber":"1526",
    "addr:postcode":"28083",
    "addr:street":"Dale Earnhardt Blvd",
    "iso:country":"US",
    "sg:address":"1526 Dale Earnhardt Blvd",
    "sg:city":"Kannapolis",
    "sg:classifiers":[
        {
            "category":"Manufacturing",
            "subcategory":"Printing",
            "type":"Manufacturing & Wholesale Goods"
        }
    ],
    "sg:phone":"+1 704 932 0755",
    "sg:postcode":"28083",
    "sg:province":"NC",
    "sg:tags":[
        "commercial"
    ],
    "wof:name":"Carter Printing Co",
    "wof:placetype":"venue"
},
  "geometry": {"coordinates":[-80.61289499999999,35.477088],"type":"Point"}
}