{
  "type": "Feature",
  "properties": {
    "addr:full":"497 Ben Eller Ln Taylorsville NC 28681",
    "addr:housenumber":"497",
    "addr:postcode":"28681",
    "addr:street":"Ben Eller Ln",
    "iso:country":"US",
    "sg:address":"497 Ben Eller Ln",
    "sg:city":"Taylorsville",
    "sg:classifiers":[
        {
            "category":"Restaurant",
            "type":"Food & Drink"
        }
    ],
    "sg:phone":"+1 828 632 3434",
    "sg:postcode":"28681",
    "sg:province":"NC",
    "sg:tags":[
        "eating"
    ],
    "wof:name":"Smoke House Bar-B-Q",
    "wof:placetype":"venue"
},
  "geometry": {"coordinates":[-81.206221,35.826988],"type":"Point"}
}