{
  "type": "Feature",
  "properties": {
    "addr:full":"4310 Long Beach Rd SE Southport NC 28461",
    "addr:housenumber":"4310",
    "addr:postcode":"28461",
    "addr:street":"Long Beach Rd Se",
    "iso:country":"US",
    "sg:address":"4310 Long Beach Rd SE",
    "sg:city":"Southport",
    "sg:classifiers":[
        {
            "category":"Shopping",
            "subcategory":"Gifts & Souvenirs",
            "type":"Retail Goods"
        }
    ],
    "sg:phone":"+1 910 454 8888",
    "sg:postcode":"28461",
    "sg:province":"NC",
    "wof:name":"Blue Crab Blue",
    "wof:placetype":"venue"
},
  "geometry": {"coordinates":[-78.064263,33.936444],"type":"Point"}
}