{
  "type": "Feature",
  "properties": {
    "addr:full":"754 Upper Spencer Mountain Rd Stanley NC 28164",
    "addr:housenumber":"754",
    "addr:postcode":"28164",
    "addr:street":"Upper Spencer Mountain Rd",
    "iso:country":"US",
    "sg:address":"754 Upper Spencer Mountain Rd",
    "sg:city":"Stanley",
    "sg:classifiers":[
        {
            "category":"Retail",
            "subcategory":"Auto Repair",
            "type":"Services"
        }
    ],
    "sg:phone":"+1   ",
    "sg:postcode":"28164",
    "sg:province":"NC",
    "sg:tags":[
        "automotive",
        "exhaust"
    ],
    "wof:name":"Costners Muffler & Brake Shop",
    "wof:placetype":"venue"
},
  "geometry": {"coordinates":[-81.127861,35.354336],"type":"Point"}
}