{
  "type": "Feature",
  "properties": {
    "iso:country":"US",
    "sg:address":"8018 W Nc 10 Hwy",
    "sg:city":"Vale",
    "sg:classifiers":[
        {
            "category":"Shopping",
            "subcategory":"Music",
            "type":"Retail Goods"
        },
        {
            "category":"Cinema",
            "subcategory":"Movie Rental",
            "type":"Entertainment"
        }
    ],
    "sg:phone":"+1 704 462 0980",
    "sg:postcode":"28168",
    "sg:province":"NC",
    "sg:tags":[
        "leasing",
        "video",
        "disc",
        "tape",
        "cassette"
    ],
    "wof:name":"Video Quest",
    "wof:placetype":"venue"
},
  "geometry": {"coordinates":[-81.452417,35.578126],"type":"Point"}
}