{
  "type": "Feature",
  "properties": {
    "addr:full":"138 W Broad St Elizabethtown NC 28337",
    "addr:housenumber":"138",
    "addr:postcode":"28337",
    "addr:street":"W Broad St",
    "iso:country":"US",
    "sg:address":"138 W Broad St",
    "sg:city":"Elizabethtown",
    "sg:classifiers":[
        {
            "category":"Retail",
            "subcategory":"Photofinishing",
            "type":"Services"
        }
    ],
    "sg:phone":"+1 910 872 5007",
    "sg:postcode":"28337",
    "sg:province":"NC",
    "sg:tags":[
        "photo",
        "finishing"
    ],
    "wof:name":"E Town Photo",
    "wof:placetype":"venue"
},
  "geometry": {"coordinates":[-78.606764,34.629255],"type":"Point"}
}