{
  "type": "Feature",
  "properties": {
    "addr:full":"207 Wilson St Chapel Hill NC 27525",
    "addr:housenumber":"207",
    "addr:postcode":"27525",
    "addr:street":"Wilson St",
    "iso:country":"US",
    "sg:address":"207 Wilson St",
    "sg:city":"Chapel Hill",
    "sg:classifiers":[
        {
            "category":"Social Services",
            "subcategory":"Child Care",
            "type":"Services"
        }
    ],
    "sg:phone":"+1 919 962 8888",
    "sg:postcode":"27525",
    "sg:province":"NC",
    "sg:tags":[
        "day"
    ],
    "wof:name":"Learn North Carolina",
    "wof:placetype":"venue"
},
  "geometry": {"coordinates":[-78.450351,36.101126],"type":"Point"}
}