{
  "type": "Feature",
  "properties": {
    "iso:country":"US",
    "sg:address":"68 Court Sq",
    "sg:city":"Mocksville",
    "sg:classifiers":[
        {
            "category":"Personal",
            "subcategory":"Barber",
            "type":"Services"
        }
    ],
    "sg:phone":"+1 336 751 3864",
    "sg:postcode":"27028",
    "sg:province":"NC",
    "wof:name":"House Of Styles",
    "wof:placetype":"venue"
},
  "geometry": {"coordinates":[-80.56147799999999,35.894304],"type":"Point"}
}