{
  "type": "Feature",
  "properties": {
    "iso:country":"US",
    "sg:address":"235 Southgate Dr",
    "sg:city":"Garner",
    "sg:classifiers":[
        {
            "category":"Food & Beverages",
            "subcategory":"Groceries & Convenience Stores",
            "type":"Retail Goods"
        }
    ],
    "sg:phone":"+1 919 779 0031",
    "sg:postcode":"27529",
    "sg:province":"NC",
    "wof:name":"Dean's Gas & Grocery",
    "wof:placetype":"venue"
},
  "geometry": {"coordinates":[-78.558083,35.576801],"type":"Point"}
}