{
  "type": "Feature",
  "properties": {
    "addr:full":"2326 Fox Ridge Manor Rd Raleigh NC 27610",
    "addr:housenumber":"2326",
    "addr:postcode":"27610",
    "addr:street":"Fox Ridge Manor Rd",
    "iso:country":"US",
    "sg:address":"2326 Fox Ridge Manor Rd",
    "sg:city":"Raleigh",
    "sg:classifiers":[
        {
            "category":"Social Services",
            "subcategory":"Child Care",
            "type":"Services"
        }
    ],
    "sg:phone":"+1   ",
    "sg:postcode":"27610",
    "sg:province":"NC",
    "sg:tags":[
        "day"
    ],
    "wof:name":"Beckeys Child Care",
    "wof:placetype":"venue"
},
  "geometry": {"coordinates":[-78.609166,35.748462],"type":"Point"}
}