{
  "type": "Feature",
  "properties": {
    "iso:country":"US",
    "sg:address":"3302 Puetts Chapel Rd",
    "sg:city":"Dallas",
    "sg:classifiers":[
        {
            "category":"Manufacturing",
            "subcategory":"Tools & Machinery",
            "type":"Manufacturing & Wholesale Goods"
        }
    ],
    "sg:phone":"+1 704 922 7914",
    "sg:postcode":"28034",
    "sg:province":"NC",
    "sg:tags":[
        "machine",
        "shop"
    ],
    "wof:name":"Kevin-Gray Machine Co",
    "wof:placetype":"venue"
},
  "geometry": {"coordinates":[-81.24199299999999,35.356402],"type":"Point"}
}