{
  "type": "Feature",
  "properties": {
    "addr:full":"2017 Smoky Park Hwy Candler NC 28715",
    "addr:housenumber":"2017",
    "addr:postcode":"28715",
    "addr:street":"Smoky Park Hwy",
    "iso:country":"US",
    "sg:address":"2017 Smoky Park Hwy",
    "sg:city":"Candler",
    "sg:classifiers":[
        {
            "category":"Autos & Motor Vehicles",
            "subcategory":"Automobile Sales",
            "type":"Retail Goods"
        },
        {
            "category":"Airline",
            "type":"Transportation"
        }
    ],
    "sg:phone":"+1 828 665 2055",
    "sg:postcode":"28715",
    "sg:province":"NC",
    "sg:tags":[
        "shuttle",
        "airport",
        "limo"
    ],
    "wof:name":"Carolina Limousine",
    "wof:placetype":"venue"
},
  "geometry": {"coordinates":[-82.717579,35.54424],"type":"Point"}
}