{
  "type": "Feature",
  "properties": {
    "iso:country":"US",
    "sg:address":"1209 Industrial Park Dr",
    "sg:city":"Smithfield",
    "sg:classifiers":[
        {
            "category":"Home & Garden",
            "subcategory":"Home Furnishings",
            "type":"Retail Goods"
        }
    ],
    "sg:phone":"+1 919 934 8049",
    "sg:postcode":"27577",
    "sg:province":"NC",
    "sg:tags":[
        "kitchen",
        "accessory"
    ],
    "sg:website":"www.legourmetchef.com",
    "wof:name":"Le Gourmet Chef",
    "wof:placetype":"venue"
},
  "geometry": {"coordinates":[-78.30694800000001,35.511628],"type":"Point"}
}