{
  "type": "Feature",
  "properties": {
    "iso:country":"US",
    "sg:address":"1169 State Rd 150",
    "sg:city":"Lincolnton",
    "sg:classifiers":[
        {
            "category":"Building & Trades",
            "subcategory":"Plumbing",
            "type":"Services"
        }
    ],
    "sg:phone":"+1 704 732 0886",
    "sg:postcode":"28092",
    "sg:province":"NC",
    "sg:tags":[
        "heating",
        "contractor"
    ],
    "wof:name":"Putnam Heating & Air Cond Inc",
    "wof:placetype":"venue"
},
  "geometry": {"coordinates":[-81.275767,35.439702],"type":"Point"}
}