{
  "type": "Feature",
  "properties": {
    "addr:full":"301 E King St Kinston NC 28501",
    "addr:housenumber":"301",
    "addr:postcode":"28501",
    "addr:street":"E King St",
    "iso:country":"US",
    "sg:address":"301 E King St",
    "sg:city":"Kinston",
    "sg:classifiers":[
        {
            "category":"Government",
            "subcategory":"Office",
            "type":"Public Place"
        }
    ],
    "sg:phone":"+1 252 939 3168",
    "sg:postcode":"28501",
    "sg:province":"NC",
    "sg:tags":[
        "village"
    ],
    "sg:website":"www.kinstonpd.org",
    "wof:name":"Kinston Support Svc Div",
    "wof:placetype":"venue"
},
  "geometry": {"coordinates":[-77.57663599999999,35.258734],"type":"Point"}
}