{
  "type": "Feature",
  "properties": {
    "addr:full":"100 Abby Way Kings Mountain NC 28086",
    "addr:housenumber":"100",
    "addr:postcode":"28086",
    "addr:street":"Abby Way",
    "iso:country":"US",
    "sg:address":"100 Abby Way",
    "sg:city":"Kings Mountain",
    "sg:classifiers":[
        {
            "category":"Manufacturing",
            "subcategory":"Apparel",
            "type":"Manufacturing & Wholesale Goods"
        }
    ],
    "sg:phone":"+1 704 739 4800",
    "sg:postcode":"28086",
    "sg:province":"NC",
    "wof:name":"Classic Stitching",
    "wof:placetype":"venue"
},
  "geometry": {"coordinates":[-81.44205599999999,35.248484],"type":"Point"}
}