{
  "type": "Feature",
  "properties": {
    "iso:country":"US",
    "sg:address":"716 Barksdale Cir",
    "sg:city":"Charlotte",
    "sg:classifiers":[
        {
            "category":"Professional",
            "subcategory":"Computer Services",
            "type":"Services"
        }
    ],
    "sg:phone":"+1   ",
    "sg:postcode":"28270",
    "sg:province":"NC",
    "sg:tags":[
        "prepackaged",
        "custom",
        "programing",
        "software"
    ],
    "wof:name":"Stonehaven Software Solution",
    "wof:placetype":"venue"
},
  "geometry": {"coordinates":[-80.75215300000001,35.141675],"type":"Point"}
}