{
  "type": "Feature",
  "properties": {
    "addr:full":"119 Jack St Hendersonville NC 28792",
    "addr:housenumber":"119",
    "addr:postcode":"28792",
    "addr:street":"Jack St",
    "iso:country":"US",
    "sg:address":"119 Jack St",
    "sg:city":"Hendersonville",
    "sg:classifiers":[
        {
            "category":"Shopping",
            "subcategory":"Used Merchandise",
            "type":"Retail Goods"
        }
    ],
    "sg:phone":"+1 828 693 0855",
    "sg:postcode":"28792",
    "sg:province":"NC",
    "wof:name":"Squirrels Nest",
    "wof:placetype":"venue"
},
  "geometry": {"coordinates":[-82.442953,35.336631],"type":"Point"}
}