{
  "type": "Feature",
  "properties": {
    "iso:country":"US",
    "sg:address":"9023 Providence Rd S",
    "sg:city":"Waxhaw",
    "sg:classifiers":[
        {
            "category":"Home & Garden",
            "subcategory":"Building Materials",
            "type":"Retail Goods"
        }
    ],
    "sg:phone":"+1 704 843 5051",
    "sg:postcode":"28173",
    "sg:province":"NC",
    "sg:tags":[
        "glass",
        "window",
        "plate"
    ],
    "wof:name":"Glass Menagerie",
    "wof:placetype":"venue"
},
  "geometry": {"coordinates":[-80.69886200000001,34.83301],"type":"Point"}
}