{
  "type": "Feature",
  "properties": {
    "iso:country":"US",
    "sg:address":"1209 Osborne Rd",
    "sg:city":"Rockingham",
    "sg:classifiers":[
        {
            "category":"Home & Garden",
            "subcategory":"Building Materials",
            "type":"Retail Goods"
        }
    ],
    "sg:phone":"+1 910 582 1147",
    "sg:postcode":"28379",
    "sg:province":"NC",
    "wof:name":"Walts Wallcovering",
    "wof:placetype":"venue"
},
  "geometry": {"coordinates":[-79.779512,34.821751],"type":"Point"}
}