{
  "type": "Feature",
  "properties": {
    "iso:country":"US",
    "sg:address":"4912 Albemarle Rd",
    "sg:city":"Charlotte",
    "sg:classifiers":[
        {
            "category":"Autos & Motor Vehicles",
            "subcategory":"Auto Supplies",
            "type":"Retail Goods"
        },
        {
            "category":"Professional",
            "subcategory":"Art Services",
            "type":"Services"
        },
        {
            "category":"Professional",
            "subcategory":"Printing & Photocopies",
            "type":"Services"
        },
        {
            "category":"Professional",
            "subcategory":"Advertising",
            "type":"Services"
        },
        {
            "category":"Manufacturing",
            "subcategory":"Signs",
            "type":"Manufacturing & Wholesale Goods"
        }
    ],
    "sg:phone":"+1 866 254 2657",
    "sg:postcode":"28205",
    "sg:province":"NC",
    "sg:tags":[
        "lettering",
        "product",
        "designer",
        "advertising-promotional",
        "producer",
        "specialty",
        "flag",
        "truck",
        "pennant",
        "banners",
        "painting",
        "display"
    ],
    "sg:website":"http://ad.doubleclick.net/clk;226205760;50079909;i?http://fastsigns.com/67",
    "wof:name":"FASTSIGNS",
    "wof:placetype":"venue"
},
  "geometry": {"coordinates":[-80.764777,35.20019],"type":"Point"}
}