{
  "type": "Feature",
  "properties": {
    "iso:country":"US",
    "sg:address":"521 Yaupon Dr",
    "sg:city":"Oak Island",
    "sg:classifiers":[
        {
            "category":"Home & Garden",
            "subcategory":"Home Furnishings",
            "type":"Retail Goods"
        }
    ],
    "sg:phone":"+1 910 278 5991",
    "sg:postcode":"28465",
    "sg:province":"NC",
    "sg:tags":[
        "pottery"
    ],
    "wof:name":"Pottery By Bob Furr",
    "wof:placetype":"venue"
},
  "geometry": {"coordinates":[-78.07966999999999,33.908703],"type":"Point"}
}