{
  "type": "Feature",
  "properties": {
    "iso:country":"US",
    "sg:address":"738 Tallulah Rd",
    "sg:city":"Robbinsville",
    "sg:classifiers":[
        {
            "category":"Personal",
            "subcategory":"Beauty Salon",
            "type":"Services"
        }
    ],
    "sg:phone":"+1 828 479 4996",
    "sg:postcode":"28771",
    "sg:province":"NC",
    "wof:name":"Shear Elegance",
    "wof:placetype":"venue"
},
  "geometry": {"coordinates":[-83.79635500000001,35.311965],"type":"Point"}
}