{
  "type": "Feature",
  "properties": {
    "iso:country":"US",
    "sg:address":"11102 Colonial Country Ln",
    "sg:city":"Charlotte",
    "sg:classifiers":[
        {
            "category":"Real Estate",
            "subcategory":"Developer",
            "type":"Services"
        }
    ],
    "sg:phone":"+1 704 846 3400",
    "sg:postcode":"28277",
    "sg:province":"NC",
    "sg:tags":[
        "building"
    ],
    "wof:name":"Business Interiors",
    "wof:placetype":"venue"
},
  "geometry": {"coordinates":[-80.787127,35.045555],"type":"Point"}
}