{
  "type": "Feature",
  "properties": {
    "addr:full":"2306 S Church St Burlington NC 27215",
    "addr:housenumber":"2306",
    "addr:postcode":"27215",
    "addr:street":"S Church St",
    "iso:country":"US",
    "sg:address":"2306 S Church St",
    "sg:city":"Burlington",
    "sg:classifiers":[
        {
            "category":"Shopping",
            "subcategory":"Jewelry",
            "type":"Retail Goods"
        }
    ],
    "sg:phone":"+1 336 228 7242",
    "sg:postcode":"27215",
    "sg:province":"NC",
    "sg:tags":[
        "jeweler"
    ],
    "wof:name":"S Burke Jewelers & Brdl Rgstry",
    "wof:placetype":"venue"
},
  "geometry": {"coordinates":[-79.473934,36.081363],"type":"Point"}
}