{
  "type": "Feature",
  "properties": {
    "addr:full":"2730 Peverell Ln Charlotte NC 28270",
    "addr:postcode":"2730;28270",
    "addr:street":"Peverell Ln",
    "iso:country":"US",
    "sg:address":"2730 Peverell Ln",
    "sg:city":"Charlotte",
    "sg:classifiers":[
        {
            "category":"Building & Trades",
            "subcategory":"Construction",
            "type":"Services"
        }
    ],
    "sg:phone":"+1 704 363 3117",
    "sg:postcode":"28270",
    "sg:province":"NC",
    "sg:tags":[
        "contractor"
    ],
    "wof:name":"Hunt Plaster and Stucco",
    "wof:placetype":"venue"
},
  "geometry": {"coordinates":[-80.756748,35.093807],"type":"Point"}
}