{
  "type": "Feature",
  "properties": {
    "addr:full":"2002 US Hwy 64 Morganton NC 28655",
    "addr:housenumber":"2002",
    "addr:postcode":"28655",
    "addr:street":"Us Hwy 64",
    "iso:country":"US",
    "sg:address":"2002 US Hwy 64",
    "sg:city":"Morganton",
    "sg:classifiers":[
        {
            "category":"Autos & Motor Vehicles",
            "subcategory":"Automobile Sales",
            "type":"Retail Goods"
        }
    ],
    "sg:phone":"+1 828 433 8715",
    "sg:postcode":"28655",
    "sg:province":"NC",
    "sg:tags":[
        "car",
        "dealer"
    ],
    "wof:name":"Country Corner Auto Sales",
    "wof:placetype":"venue"
},
  "geometry": {"coordinates":[-81.70987,35.705556],"type":"Point"}
}