{
  "type": "Feature",
  "properties": {
    "addr:full":"160 Romans Dr Stoneville NC 27048",
    "addr:housenumber":"160",
    "addr:postcode":"27048",
    "addr:street":"Romans Dr",
    "iso:country":"US",
    "sg:address":"160 Romans Dr",
    "sg:city":"Stoneville",
    "sg:classifiers":[
        {
            "category":"Organizations",
            "subcategory":"Religious Organization",
            "type":"Services"
        }
    ],
    "sg:phone":"+1   ",
    "sg:postcode":"27048",
    "sg:province":"NC",
    "wof:name":"Tri City Baptist Church Inc",
    "wof:placetype":"venue"
},
  "geometry": {"coordinates":[-79.82708700000001,36.465153],"type":"Point"}
}