{
  "type": "Feature",
  "properties": {
    "iso:country":"US",
    "sg:address":"413 Brooks St",
    "sg:city":"Wake Forest",
    "sg:classifiers":[
        {
            "category":"Personal",
            "subcategory":"Beauty Salon",
            "type":"Services"
        }
    ],
    "sg:phone":"+1   ",
    "sg:postcode":"27587",
    "sg:province":"NC",
    "sg:tags":[
        "shop"
    ],
    "wof:name":"In Flight International Salon",
    "wof:placetype":"venue"
},
  "geometry": {"coordinates":[-78.509446,35.975007],"type":"Point"}
}