{
  "type": "Feature",
  "properties": {
    "iso:country":"US",
    "sg:address":"46 Haywood St",
    "sg:city":"Asheville",
    "sg:classifiers":[
        {
            "category":"Shopping",
            "subcategory":"Jewelry",
            "type":"Retail Goods"
        }
    ],
    "sg:phone":"+1 828 257 2033",
    "sg:postcode":"28801",
    "sg:province":"NC",
    "sg:tags":[
        "jeweler"
    ],
    "wof:name":"Beatuiful Jewelry",
    "wof:placetype":"venue"
},
  "geometry": {"coordinates":[-82.55458299999999,35.595362],"type":"Point"}
}