{
  "type": "Feature",
  "properties": {
    "addr:full":"5755 Crenshaw Dr Hope Mills NC 28348",
    "addr:housenumber":"5755",
    "addr:postcode":"28348",
    "addr:street":"Crenshaw Dr",
    "iso:country":"US",
    "sg:address":"5755 Crenshaw Dr",
    "sg:city":"Hope Mills",
    "sg:classifiers":[
        {
            "category":"Building & Trades",
            "subcategory":"Electrical",
            "type":"Services"
        }
    ],
    "sg:phone":"+1 910 425 4915",
    "sg:postcode":"28348",
    "sg:province":"NC",
    "sg:tags":[
        "electric",
        "contractor"
    ],
    "wof:name":"Priority One Electrical Svc",
    "wof:placetype":"venue"
},
  "geometry": {"coordinates":[-78.96131,34.969378],"type":"Point"}
}