{
  "type": "Feature",
  "properties": {
    "addr:full":"5505 Adams Farm Ln Greensboro NC 27407",
    "addr:housenumber":"5505",
    "addr:postcode":"27407",
    "addr:street":"Adams Farm Ln",
    "iso:country":"US",
    "sg:address":"5505 Adams Farm Ln",
    "sg:city":"Greensboro",
    "sg:classifiers":[
        {
            "category":"Health Services",
            "subcategory":"Doctor",
            "type":"Services"
        }
    ],
    "sg:phone":"+1 336 292 6265",
    "sg:postcode":"27407",
    "sg:province":"NC",
    "sg:tags":[
        "dentist"
    ],
    "wof:name":"Steven L Davis DDS PA",
    "wof:placetype":"venue"
},
  "geometry": {"coordinates":[-79.90489700000001,36.01895],"type":"Point"}
}