{
  "type": "Feature",
  "properties": {
    "iso:country":"US",
    "sg:address":"102 Goforth Rd",
    "sg:city":"Kings Mountain",
    "sg:classifiers":[
        {
            "category":"Autos & Motor Vehicles",
            "subcategory":"Fuel & Gas Station",
            "type":"Retail Goods"
        }
    ],
    "sg:phone":"+1 704 739 2800",
    "sg:postcode":"28086",
    "sg:province":"NC",
    "sg:tags":[
        "grocery",
        "station",
        "gasoline"
    ],
    "wof:name":"Village Servicenter Store Inc",
    "wof:placetype":"venue"
},
  "geometry": {"coordinates":[-81.355132,35.279519],"type":"Point"}
}