{
  "type": "Feature",
  "properties": {
    "iso:country":"US",
    "sg:address":"201 Commonwealth Ct",
    "sg:city":"Cary",
    "sg:classifiers":[
        {
            "category":"Real Estate",
            "subcategory":"Architect",
            "type":"Services"
        }
    ],
    "sg:phone":"+1 919 468 1717",
    "sg:postcode":"27511",
    "sg:province":"NC",
    "sg:tags":[
        "architectural"
    ],
    "wof:name":"Gurel Architecture Inc",
    "wof:placetype":"venue"
},
  "geometry": {"coordinates":[-78.784756,35.766721],"type":"Point"}
}