{
  "type": "Feature",
  "properties": {
    "iso:country":"US",
    "sg:address":"1216 Bridford Pkwy",
    "sg:city":"Greensboro",
    "sg:classifiers":[
        {
            "category":"Professional",
            "subcategory":"Employment Agencies",
            "type":"Services"
        }
    ],
    "sg:phone":"+1 336 852 0500",
    "sg:postcode":"27407",
    "sg:province":"NC",
    "sg:tags":[
        "provides",
        "staffing"
    ],
    "wof:name":"Olsten",
    "wof:placetype":"venue"
},
  "geometry": {"coordinates":[-79.903305,36.058636],"type":"Point"}
}