{
  "type": "Feature",
  "properties": {
    "iso:country":"US",
    "sg:address":"507 Silversmith Ln",
    "sg:city":"Charlotte",
    "sg:classifiers":[
        {
            "category":"Retail",
            "subcategory":"Repair Shop",
            "type":"Services"
        }
    ],
    "sg:phone":"+1   ",
    "sg:postcode":"28270",
    "sg:province":"NC",
    "sg:tags":[
        "electrical"
    ],
    "wof:name":"Metrolina Appliance Services",
    "wof:placetype":"venue"
},
  "geometry": {"coordinates":[-80.747387,35.115395],"type":"Point"}
}