{
  "type": "Feature",
  "properties": {
    "iso:country":"US",
    "sg:address":"1019 Union St",
    "sg:city":"Greensboro",
    "sg:classifiers":[
        {
            "category":"Retail",
            "subcategory":"Portrait Studio",
            "type":"Services"
        }
    ],
    "sg:phone":"+1   ",
    "sg:postcode":"27403",
    "sg:province":"NC",
    "sg:tags":[
        "photo"
    ],
    "wof:name":"David B Alford Photography",
    "wof:placetype":"venue"
},
  "geometry": {"coordinates":[-79.808941,36.062355],"type":"Point"}
}