{
  "type": "Feature",
  "properties": {
    "iso:country":"US",
    "sg:address":"1631 Pactolus Hwy",
    "sg:city":"Greenville",
    "sg:classifiers":[
        {
            "category":"Bars & Pubs",
            "type":"Food & Drink"
        },
        {
            "category":"Organizations",
            "subcategory":"Community Association",
            "type":"Services"
        }
    ],
    "sg:phone":"+1 252 758 6856",
    "sg:postcode":"27834",
    "sg:province":"NC",
    "sg:tags":[
        "club",
        "drinking"
    ],
    "wof:name":"Player's Retreat",
    "wof:placetype":"venue"
},
  "geometry": {"coordinates":[-77.348648,35.629409],"type":"Point"}
}