{
  "type": "Feature",
  "properties": {
    "iso:country":"US",
    "sg:address":"11400 Common Oaks Dr",
    "sg:city":"Raleigh",
    "sg:classifiers":[
        {
            "category":"Professional",
            "subcategory":"Management & Consulting",
            "type":"Services"
        }
    ],
    "sg:phone":"+1   ",
    "sg:postcode":"27614",
    "sg:province":"NC",
    "sg:tags":[
        "motel"
    ],
    "wof:name":"Holiday Inn",
    "wof:placetype":"venue"
},
  "geometry": {"coordinates":[-78.54292599999999,35.952795],"type":"Point"}
}