{
  "type": "Feature",
  "properties": {
    "addr:full":"462 Masontown Rd Newport NC 28570",
    "addr:housenumber":"462",
    "addr:postcode":"28570",
    "addr:street":"Masontown Rd",
    "iso:country":"US",
    "sg:address":"462 Masontown Rd",
    "sg:city":"Newport",
    "sg:classifiers":[
        {
            "category":"Professional",
            "type":"Services"
        }
    ],
    "sg:phone":"+1 252 223 3578",
    "sg:postcode":"28570",
    "sg:province":"NC",
    "sg:tags":[
        "establishment"
    ],
    "wof:name":"Jerry Ballard & Assoc LLC",
    "wof:placetype":"venue"
},
  "geometry": {"coordinates":[-76.883933,34.805131],"type":"Point"}
}