{
  "type": "Feature",
  "properties": {
    "iso:country":"US",
    "sg:address":"7204 Pear Tree Rd",
    "sg:city":"Charlotte",
    "sg:classifiers":[
        {
            "category":"Building & Trades",
            "subcategory":"Construction",
            "type":"Services"
        }
    ],
    "sg:phone":"+1 704 398 1301",
    "sg:postcode":"28216",
    "sg:province":"NC",
    "sg:tags":[
        "steel",
        "erection",
        "structural"
    ],
    "wof:name":"Rubright Construction Co",
    "wof:placetype":"venue"
},
  "geometry": {"coordinates":[-80.908889,35.346996],"type":"Point"}
}