{
  "type": "Feature",
  "properties": {
    "addr:full":"707 E Parker Rd Morganton NC 28655",
    "addr:housenumber":"707",
    "addr:postcode":"28655",
    "addr:street":"E Parker Rd",
    "iso:country":"US",
    "sg:address":"707 E Parker Rd",
    "sg:city":"Morganton",
    "sg:classifiers":[
        {
            "category":"Organizations",
            "subcategory":"Religious Organization",
            "type":"Services"
        }
    ],
    "sg:phone":"+1 828 433 6198",
    "sg:postcode":"28655",
    "sg:province":"NC",
    "sg:tags":[
        "church"
    ],
    "wof:name":"Heritage Baptist Church",
    "wof:placetype":"venue"
},
  "geometry": {"coordinates":[-81.646415,35.725882],"type":"Point"}
}