{
  "type": "Feature",
  "properties": {
    "iso:country":"US",
    "sg:address":"420 Old Vanceboro Rd",
    "sg:city":"New Bern",
    "sg:classifiers":[
        {
            "category":"Freight",
            "type":"Transportation"
        }
    ],
    "sg:phone":"+1 252 633 4774",
    "sg:postcode":"28560",
    "sg:province":"NC",
    "sg:tags":[
        "operator",
        "local",
        "trucking"
    ],
    "wof:name":"Arthur JD Trucking",
    "wof:placetype":"venue"
},
  "geometry": {"coordinates":[-77.026481,35.145886],"type":"Point"}
}