{
  "type": "Feature",
  "properties": {
    "addr:full":"601 N Van Buren Rd Eden NC 27288",
    "addr:housenumber":"601",
    "addr:postcode":"27288",
    "addr:street":"N Van Buren Rd",
    "iso:country":"US",
    "sg:address":"601 N Van Buren Rd",
    "sg:city":"Eden",
    "sg:classifiers":[
        {
            "category":"Home & Garden",
            "subcategory":"Household Appliances",
            "type":"Retail Goods"
        },
        {
            "category":"Retail",
            "subcategory":"Repair Shop",
            "type":"Services"
        }
    ],
    "sg:phone":"+1 336 627 5383",
    "sg:postcode":"27288",
    "sg:province":"NC",
    "wof:name":"Sensible TV & Appliances",
    "wof:placetype":"venue"
},
  "geometry": {"coordinates":[-79.75014400000001,36.517342],"type":"Point"}
}