{
  "type": "Feature",
  "properties": {
    "iso:country":"US",
    "sg:address":"3875 Blackjack-Simpson Rd",
    "sg:city":"Greenville",
    "sg:phone":"+1 252 746 6826",
    "sg:postcode":"27858",
    "sg:province":"NC",
    "sg:tags":[
        "farm",
        "tobacco",
        "cotton"
    ],
    "wof:name":"Rufus White",
    "wof:placetype":"venue"
},
  "geometry": {"coordinates":[-77.249495,35.470372],"type":"Point"}
}