{
  "type": "Feature",
  "properties": {
    "addr:full":"509 W High Ave High Point NC 27260",
    "addr:housenumber":"509",
    "addr:postcode":"27260",
    "addr:street":"W High Ave",
    "iso:country":"US",
    "sg:address":"509 W High Ave",
    "sg:city":"High Point",
    "sg:classifiers":[
        {
            "category":"Autos & Motor Vehicles",
            "subcategory":"Motorcycle Sales",
            "type":"Retail Goods"
        }
    ],
    "sg:phone":"+1 336 869 4900",
    "sg:postcode":"27260",
    "sg:province":"NC",
    "sg:tags":[
        "all",
        "terrain"
    ],
    "wof:name":"Legacy ATV",
    "wof:placetype":"venue"
},
  "geometry": {"coordinates":[-80.012682,35.953129],"type":"Point"}
}