{
  "type": "Feature",
  "properties": {
    "addr:full":"195 Dogwood Ln Black Mountain NC 28711",
    "addr:housenumber":"195",
    "addr:postcode":"28711",
    "addr:street":"Dogwood Ln",
    "iso:country":"US",
    "sg:address":"195 Dogwood Ln",
    "sg:city":"Black Mountain",
    "sg:classifiers":[
        {
            "category":"Recreation",
            "type":"Entertainment"
        }
    ],
    "sg:phone":"+1   ",
    "sg:postcode":"28711",
    "sg:province":"NC",
    "sg:tags":[
        "club",
        "membership"
    ],
    "wof:name":"Cheshire Racquet Club",
    "wof:placetype":"venue"
},
  "geometry": {"coordinates":[-82.32080499999999,35.602881],"type":"Point"}
}