{
  "type": "Feature",
  "properties": {
    "iso:country":"US",
    "sg:address":"223 W Matthews St",
    "sg:city":"Matthews",
    "sg:classifiers":[
        {
            "category":"Professional",
            "subcategory":"Business Services",
            "type":"Services"
        }
    ],
    "sg:phone":"+1 704 821 5301",
    "sg:postcode":"28105",
    "sg:province":"NC",
    "sg:tags":[
        "paging",
        "answering"
    ],
    "wof:name":"A & A Communications Inc",
    "wof:placetype":"venue"
},
  "geometry": {"coordinates":[-80.72178700000001,35.119227],"type":"Point"}
}