{
  "type": "Feature",
  "properties": {
    "addr:full":"255 Callahan Koon Rd Spindale NC 28160",
    "addr:housenumber":"255",
    "addr:postcode":"28160",
    "addr:street":"Callahan Koon Rd",
    "iso:country":"US",
    "sg:address":"255 Callahan Koon Rd",
    "sg:city":"Spindale",
    "sg:classifiers":[
        {
            "category":"Education",
            "subcategory":"Library",
            "type":"Public Place"
        }
    ],
    "sg:phone":"+1 828 287 6115",
    "sg:postcode":"28160",
    "sg:province":"NC",
    "wof:name":"Rutherford County Library",
    "wof:placetype":"venue"
},
  "geometry": {"coordinates":[-81.91064799999999,35.347875],"type":"Point"}
}