{
  "type": "Feature",
  "properties": {
    "iso:country":"US",
    "sg:address":"5901 W Market St",
    "sg:city":"Greensboro",
    "sg:classifiers":[
        {
            "category":"Home & Garden",
            "subcategory":"Building Materials",
            "type":"Retail Goods"
        }
    ],
    "sg:phone":"+1 336 665 1900",
    "sg:postcode":"27409",
    "sg:province":"NC",
    "wof:name":"Quality Door Service",
    "wof:placetype":"venue"
},
  "geometry": {"coordinates":[-79.89922,36.076586],"type":"Point"}
}