{
  "type": "Feature",
  "properties": {
    "iso:country":"US",
    "sg:address":"1839 Newkirk Rd",
    "sg:city":"Wilmington",
    "sg:classifiers":[
        {
            "category":"Organizations",
            "subcategory":"Community Association",
            "type":"Services"
        }
    ],
    "sg:phone":"+1 910 392 1793",
    "sg:postcode":"28409",
    "sg:province":"NC",
    "wof:name":"Timberbrook Homeowners Assn",
    "wof:placetype":"venue"
},
  "geometry": {"coordinates":[-77.876926,34.127939],"type":"Point"}
}