{
  "type": "Feature",
  "properties": {
    "addr:full":"5623 Durham Chapl Hl Blvd Durham NC 27707",
    "addr:housenumber":"5623",
    "addr:postcode":"27707",
    "addr:street":"Durham Chapl Hl Blvd",
    "iso:country":"US",
    "sg:address":"5623 Durham Chapl Hl Blvd",
    "sg:city":"Durham",
    "sg:classifiers":[
        {
            "category":"Travel",
            "subcategory":"Hotels & Motels",
            "type":"Entertainment"
        }
    ],
    "sg:phone":"+1 919 489 9421",
    "sg:postcode":"27707",
    "sg:province":"NC",
    "wof:name":"Red Roof Inn",
    "wof:placetype":"venue"
},
  "geometry": {"coordinates":[-78.99520099999999,35.9524],"type":"Point"}
}