{
  "type": "Feature",
  "properties": {
    "iso:country":"US",
    "sg:address":"103 Keowee Cir",
    "sg:city":"Indian Trail",
    "sg:classifiers":[
        {
            "category":"Professional",
            "subcategory":"Business Services",
            "type":"Services"
        }
    ],
    "sg:phone":"+1   ",
    "sg:postcode":"28079",
    "sg:province":"NC",
    "wof:name":"Universal Marketing Allia",
    "wof:placetype":"venue"
},
  "geometry": {"coordinates":[-80.67952099999999,35.070347],"type":"Point"}
}