{
  "type": "Feature",
  "properties": {
    "iso:country":"US",
    "sg:address":"1532 Main St",
    "sg:city":"Ramseur",
    "sg:classifiers":[
        {
            "category":"Home & Garden",
            "subcategory":"Building Materials",
            "type":"Retail Goods"
        }
    ],
    "sg:phone":"+1 336 824 6485",
    "sg:postcode":"27316",
    "sg:province":"NC",
    "sg:tags":[
        "glass",
        "leaded"
    ],
    "wof:name":"Country Depot",
    "wof:placetype":"venue"
},
  "geometry": {"coordinates":[-79.654068,35.731493],"type":"Point"}
}