{
  "type": "Feature",
  "properties": {
    "addr:full":"105 Winding Ridge Dr Cary NC 27518",
    "addr:housenumber":"105",
    "addr:postcode":"27518",
    "addr:street":"Winding Ridge Dr",
    "iso:country":"US",
    "sg:address":"105 Winding Ridge Dr",
    "sg:city":"Cary",
    "sg:classifiers":[
        {
            "category":"Building & Trades",
            "subcategory":"Construction",
            "type":"Services"
        }
    ],
    "sg:phone":"+1 919 402 0577",
    "sg:postcode":"27518",
    "sg:province":"NC",
    "sg:tags":[
        "general",
        "contractor"
    ],
    "wof:name":"Canstruct LLC",
    "wof:placetype":"venue"
},
  "geometry": {"coordinates":[-78.779572,35.716671],"type":"Point"}
}