{
  "type": "Feature",
  "properties": {
    "iso:country":"US",
    "sg:address":"419 Elmore Rd",
    "sg:city":"Mocksville",
    "sg:classifiers":[
        {
            "category":"Real Estate",
            "subcategory":"Real Estate Agent",
            "type":"Services"
        }
    ],
    "sg:phone":"+1 336 492 2708",
    "sg:postcode":"27028",
    "sg:province":"NC",
    "wof:name":"Denise Hendrix",
    "wof:placetype":"venue"
},
  "geometry": {"coordinates":[-80.63010800000001,35.996169],"type":"Point"}
}