{
  "type": "Feature",
  "properties": {
    "iso:country":"US",
    "sg:address":"200 Grey Squirrel Dr",
    "sg:city":"Waynesville",
    "sg:classifiers":[
        {
            "category":"Retail",
            "subcategory":"Auto Repair",
            "type":"Services"
        }
    ],
    "sg:phone":"+1 828 926 3700",
    "sg:postcode":"28785",
    "sg:province":"NC",
    "sg:tags":[
        "body",
        "automobile",
        "painting"
    ],
    "wof:name":"J-Creek Body Shop",
    "wof:placetype":"venue"
},
  "geometry": {"coordinates":[-83.019925,35.559005],"type":"Point"}
}