{
  "type": "Feature",
  "properties": {
    "iso:country":"US",
    "sg:address":"1647 State Rd 98",
    "sg:city":"Louisburg",
    "sg:classifiers":[
        {
            "category":"Autos & Motor Vehicles",
            "subcategory":"Automobile Sales",
            "type":"Retail Goods"
        }
    ],
    "sg:phone":"+1 919 497 4066",
    "sg:postcode":"27549",
    "sg:province":"NC",
    "sg:tags":[
        "car",
        "dealer"
    ],
    "wof:name":"Medlins' Auto Sales",
    "wof:placetype":"venue"
},
  "geometry": {"coordinates":[-78.30157199999999,35.963094],"type":"Point"}
}