{
  "type": "Feature",
  "properties": {
    "iso:country":"US",
    "sg:address":"99 Merrimon Ave",
    "sg:city":"Asheville",
    "sg:classifiers":[
        {
            "category":"Restaurant",
            "type":"Food & Drink"
        }
    ],
    "sg:menulink":"http://www.allmenus.com/nc/asheville/153154-bojangles/menu/",
    "sg:phone":"+1 828 252 2777",
    "sg:postcode":"28801",
    "sg:province":"NC",
    "sg:tags":[
        "chicken",
        "sandwich",
        "american"
    ],
    "wof:name":"Bojangle's",
    "wof:placetype":"venue"
},
  "geometry": {"coordinates":[-82.55319799999999,35.602527],"type":"Point"}
}