{
  "type": "Feature",
  "properties": {
    "addr:full":"10620 Park Rd Charlotte NC 28210",
    "addr:housenumber":"10620",
    "addr:postcode":"28210",
    "addr:street":"Park Rd",
    "iso:country":"US",
    "sg:address":"10620 Park Rd",
    "sg:city":"Charlotte",
    "sg:classifiers":[
        {
            "category":"Health Services",
            "subcategory":"Doctor",
            "type":"Services"
        }
    ],
    "sg:phone":"+1 704 541 7654",
    "sg:postcode":"28210",
    "sg:province":"NC",
    "sg:tags":[
        "physician",
        "surgeon",
        "medical"
    ],
    "sg:website":"www.drbednar.com",
    "wof:name":"Metrolina Plastic Surgery P A",
    "wof:placetype":"venue"
},
  "geometry": {"coordinates":[-80.869733,35.0911],"type":"Point"}
}