{
  "type": "Feature",
  "properties": {
    "iso:country":"US",
    "sg:address":"8000 Regency Pkwy",
    "sg:city":"Cary",
    "sg:classifiers":[
        {
            "category":"Professional",
            "type":"Services"
        }
    ],
    "sg:phone":"+1 919 469 1266",
    "sg:postcode":"27518",
    "sg:province":"NC",
    "sg:tags":[
        "establishment"
    ],
    "wof:name":"Seer Technologies",
    "wof:placetype":"venue"
},
  "geometry": {"coordinates":[-78.792176,35.728237],"type":"Point"}
}