{
  "type": "Feature",
  "properties": {
    "addr:full":"242 Kitty Fork Rd Saint Pauls NC 28384",
    "addr:housenumber":"242",
    "addr:postcode":"28384",
    "addr:street":"Kitty Fork Rd",
    "iso:country":"US",
    "sg:address":"242 Kitty Fork Rd",
    "sg:city":"Saint Pauls",
    "sg:classifiers":[
        {
            "category":"Building & Trades",
            "subcategory":"Construction",
            "type":"Services"
        }
    ],
    "sg:phone":"+1 910 865 1422",
    "sg:postcode":"28384",
    "sg:province":"NC",
    "sg:tags":[
        "house"
    ],
    "wof:name":"Kinlaw Home Imprv St Paul",
    "wof:placetype":"venue"
},
  "geometry": {"coordinates":[-78.87059000000001,34.765072],"type":"Point"}
}