{
  "type": "Feature",
  "properties": {
    "iso:country":"US",
    "sg:address":"2903 Davie Dr",
    "sg:city":"Durham",
    "sg:classifiers":[
        {
            "category":"Building & Trades",
            "subcategory":"Construction",
            "type":"Services"
        }
    ],
    "sg:phone":"+1 919 682 8357",
    "sg:postcode":"27704",
    "sg:province":"NC",
    "sg:tags":[
        "contractor"
    ],
    "wof:name":"Parra Santiago A Roofing Co",
    "wof:placetype":"venue"
},
  "geometry": {"coordinates":[-78.845214,36.047484],"type":"Point"}
}