{
  "type": "Feature",
  "properties": {
    "iso:country":"US",
    "sg:address":"120 Chadwick Ave",
    "sg:city":"Hendersonville",
    "sg:classifiers":[
        {
            "category":"Professional",
            "subcategory":"Business Services",
            "type":"Services"
        }
    ],
    "sg:phone":"+1   ",
    "sg:postcode":"28792",
    "sg:province":"NC",
    "wof:name":"First Southern Business Brks",
    "wof:placetype":"venue"
},
  "geometry": {"coordinates":[-82.45542,35.303431],"type":"Point"}
}