{
  "type": "Feature",
  "properties": {
    "iso:country":"US",
    "sg:address":"313 Chapanoke Rd",
    "sg:city":"Raleigh",
    "sg:classifiers":[
        {
            "category":"Government",
            "subcategory":"Office",
            "type":"Public Place"
        }
    ],
    "sg:phone":"+1 919 661 4872",
    "sg:postcode":"27603",
    "sg:province":"NC",
    "sg:tags":[
        "conservation"
    ],
    "wof:name":"North Carolina Wildlifr Comm",
    "wof:placetype":"venue"
},
  "geometry": {"coordinates":[-78.649501,35.735571],"type":"Point"}
}