{
  "type": "Feature",
  "properties": {
    "addr:full":"2903 Hillman Rd Kinston NC 28504",
    "addr:housenumber":"2903",
    "addr:postcode":"28504",
    "addr:street":"Hillman Rd",
    "iso:country":"US",
    "sg:address":"2903 Hillman Rd",
    "sg:city":"Kinston",
    "sg:classifiers":[
        {
            "category":"Building & Trades",
            "subcategory":"Cleaning & Sanitation",
            "type":"Services"
        }
    ],
    "sg:phone":"+1   ",
    "sg:postcode":"28504",
    "sg:province":"NC",
    "sg:tags":[
        "maintenance"
    ],
    "wof:name":"Smiths Powerwash",
    "wof:placetype":"venue"
},
  "geometry": {"coordinates":[-77.602828,35.298199],"type":"Point"}
}