{
  "type": "Feature",
  "properties": {
    "iso:country":"US",
    "sg:address":"400 S Summit Ave",
    "sg:city":"Charlotte",
    "sg:classifiers":[
        {
            "category":"Personal",
            "type":"Services"
        },
        {
            "category":"Restaurant",
            "type":"Food & Drink"
        }
    ],
    "sg:phone":"+1 704 332 3050",
    "sg:postcode":"28208",
    "sg:province":"NC",
    "sg:tags":[
        "planning",
        "meeting",
        "banquet",
        "rooms"
    ],
    "wof:name":"Wadesworth House",
    "wof:placetype":"venue"
},
  "geometry": {"coordinates":[-80.861282,35.232338],"type":"Point"}
}