{
  "type": "Feature",
  "properties": {
    "iso:country":"US",
    "sg:address":"4407 Helms Rd",
    "sg:city":"Waxhaw",
    "sg:classifiers":[
        {
            "category":"Real Estate",
            "subcategory":"Real Estate Agent",
            "type":"Services"
        }
    ],
    "sg:phone":"+1 704 843 5990",
    "sg:postcode":"28173",
    "sg:province":"NC",
    "wof:name":"LJK Properties",
    "wof:placetype":"venue"
},
  "geometry": {"coordinates":[-80.761109,34.926224],"type":"Point"}
}