{
  "type": "Feature",
  "properties": {
    "addr:full":"5 Westwood Rd Asheville NC 28803",
    "addr:housenumber":"5",
    "addr:postcode":"28803",
    "addr:street":"Westwood Rd",
    "iso:country":"US",
    "sg:address":"5 Westwood Rd",
    "sg:city":"Asheville",
    "sg:classifiers":[
        {
            "category":"Professional",
            "subcategory":"Management & Consulting",
            "type":"Services"
        }
    ],
    "sg:phone":"+1   ",
    "sg:postcode":"28803",
    "sg:province":"NC",
    "sg:tags":[
        "business"
    ],
    "wof:name":"Lockwood Kilbert",
    "wof:placetype":"venue"
},
  "geometry": {"coordinates":[-82.53867700000001,35.524326],"type":"Point"}
}