{
  "type": "Feature",
  "properties": {
    "addr:full":"139 W College St Oxford NC 27565",
    "addr:housenumber":"139",
    "addr:postcode":"27565",
    "addr:street":"W College St",
    "iso:country":"US",
    "sg:address":"139 W College St",
    "sg:city":"Oxford",
    "sg:classifiers":[
        {
            "category":"Social Services",
            "type":"Services"
        }
    ],
    "sg:phone":"+1 919 693 8201",
    "sg:postcode":"27565",
    "sg:province":"NC",
    "sg:tags":[
        "worker"
    ],
    "wof:name":"Stephanie Beck",
    "wof:placetype":"venue"
},
  "geometry": {"coordinates":[-78.598677,36.322283],"type":"Point"}
}