{
  "type": "Feature",
  "properties": {
    "iso:country":"US",
    "sg:address":"3758 Tulip Dr",
    "sg:city":"Winston Salem",
    "sg:classifiers":[
        {
            "category":"Building & Trades",
            "subcategory":"Construction",
            "type":"Services"
        }
    ],
    "sg:phone":"+1 336 723 0686",
    "sg:postcode":"27105",
    "sg:province":"NC",
    "sg:tags":[
        "house"
    ],
    "wof:name":"Jls Mobile Home Repair",
    "wof:placetype":"venue"
},
  "geometry": {"coordinates":[-80.187359,36.136423],"type":"Point"}
}