{
  "type": "Feature",
  "properties": {
    "addr:full":"91 Catawba St Belmont NC 28012",
    "addr:housenumber":"91",
    "addr:postcode":"28012",
    "addr:street":"Catawba St",
    "iso:country":"US",
    "sg:address":"91 Catawba St",
    "sg:city":"Belmont",
    "sg:classifiers":[
        {
            "category":"Health Services",
            "subcategory":"Health Practitioner",
            "type":"Services"
        }
    ],
    "sg:phone":"+1 704 829 0078",
    "sg:postcode":"28012",
    "sg:province":"NC",
    "sg:tags":[
        "nurse",
        "registry"
    ],
    "wof:name":"Bellmont Parish Nurse",
    "wof:placetype":"venue"
},
  "geometry": {"coordinates":[-81.033934,35.243662],"type":"Point"}
}