{
  "type": "Feature",
  "properties": {
    "addr:full":"3280 US Hwy 64 Taylorsville NC 28681",
    "addr:housenumber":"3280",
    "addr:postcode":"28681",
    "addr:street":"Us Hwy 64",
    "iso:country":"US",
    "sg:address":"3280 US Hwy 64",
    "sg:city":"Taylorsville",
    "sg:classifiers":[
        {
            "category":"Organizations",
            "subcategory":"Religious Organization",
            "type":"Services"
        }
    ],
    "sg:phone":"+1 828 632 6659",
    "sg:postcode":"28681",
    "sg:province":"NC",
    "sg:tags":[
        "church"
    ],
    "wof:name":"Mount Herman Baptist Church",
    "wof:placetype":"venue"
},
  "geometry": {"coordinates":[-81.23827,35.92048],"type":"Point"}
}