{
  "type": "Feature",
  "properties": {
    "iso:country":"US",
    "sg:address":"6633 Old US Hwy 52",
    "sg:city":"Lexington",
    "sg:classifiers":[
        {
            "category":"Home & Garden",
            "subcategory":"Carpets & Floor Coverings",
            "type":"Retail Goods"
        }
    ],
    "sg:phone":"+1 336 731 2146",
    "sg:postcode":"27295",
    "sg:province":"NC",
    "sg:tags":[
        "dealer",
        "rug"
    ],
    "sg:website":"www.nelsonsfloorfashions.com",
    "wof:name":"Nelson's Floor Fashions Inc",
    "wof:placetype":"venue"
},
  "geometry": {"coordinates":[-80.25012700000001,35.915631],"type":"Point"}
}