{
  "type": "Feature",
  "properties": {
    "iso:country":"US",
    "sg:address":"4241 Louisburg Rd",
    "sg:city":"Raleigh",
    "sg:classifiers":[
        {
            "category":"Food & Beverages",
            "subcategory":"Groceries & Convenience Stores",
            "type":"Retail Goods"
        }
    ],
    "sg:phone":"+1 919 000 1111",
    "sg:postcode":"27604",
    "sg:province":"NC",
    "sg:tags":[
        "grocer"
    ],
    "wof:name":"Aldi",
    "wof:placetype":"venue"
},
  "geometry": {"coordinates":[-78.578498,35.840856],"type":"Point"}
}