{
  "type": "Feature",
  "properties": {
    "iso:country":"US",
    "sg:address":"119 N 2nd Ave",
    "sg:city":"Siler City",
    "sg:classifiers":[
        {
            "category":"Retail",
            "subcategory":"Auto Repair",
            "type":"Services"
        }
    ],
    "sg:phone":"+1   ",
    "sg:postcode":"27344",
    "sg:province":"NC",
    "sg:tags":[
        "general"
    ],
    "wof:name":"S & W Speed Shop",
    "wof:placetype":"venue"
},
  "geometry": {"coordinates":[-79.462755,35.724074],"type":"Point"}
}