{
  "type": "Feature",
  "properties": {
    "addr:full":"1639 Nc Highway 50 Creedmoor NC 27522",
    "addr:housenumber":"1639",
    "addr:postcode":"27522",
    "addr:street":"Nc Highway 50",
    "iso:country":"US",
    "sg:address":"1639 Nc Highway 50",
    "sg:city":"Creedmoor",
    "sg:classifiers":[
        {
            "category":"Organizations",
            "subcategory":"Non-profit Organization",
            "type":"Services"
        }
    ],
    "sg:phone":"+1 919 529 1325",
    "sg:postcode":"27522",
    "sg:province":"NC",
    "sg:tags":[
        "service/non-profit",
        "community"
    ],
    "wof:name":"Concerned Biker Association",
    "wof:placetype":"venue"
},
  "geometry": {"coordinates":[-78.69029999999999,36.096401],"type":"Point"}
}