{
  "type": "Feature",
  "properties": {
    "addr:full":"775 4th St SW Hickory NC 28602",
    "addr:housenumber":"775",
    "addr:postcode":"28602",
    "addr:street":"4Th St Sw",
    "iso:country":"US",
    "sg:address":"775 4th St SW",
    "sg:city":"Hickory",
    "sg:classifiers":[
        {
            "category":"Insurance",
            "subcategory":"Insurance Agent",
            "type":"Services"
        }
    ],
    "sg:phone":"+1 828 322 7216",
    "sg:postcode":"28602",
    "sg:province":"NC",
    "wof:name":"Jefferson-Pilot Life Ins Co",
    "wof:placetype":"venue"
},
  "geometry": {"coordinates":[-81.34538499999999,35.72251],"type":"Point"}
}