{
  "type": "Feature",
  "properties": {
    "addr:full":"6525 Ocean Hwy E Winnabow NC 28479",
    "addr:housenumber":"6525",
    "addr:postcode":"28479",
    "addr:street":"Ocean Hwy E Winnabow",
    "iso:country":"US",
    "sg:address":"6525 Ocean Hwy E",
    "sg:city":"Winnabow",
    "sg:classifiers":[
        {
            "category":"Shopping",
            "subcategory":"Used Merchandise",
            "type":"Retail Goods"
        }
    ],
    "sg:phone":"+1 910 253 0045",
    "sg:postcode":"28479",
    "sg:province":"NC",
    "sg:tags":[
        "appliance"
    ],
    "wof:name":"K & R Appliance",
    "wof:placetype":"venue"
},
  "geometry": {"coordinates":[-78.093836,34.150165],"type":"Point"}
}