{
  "type": "Feature",
  "properties": {
    "addr:full":"206 Carolina St Morganton NC 28655",
    "addr:housenumber":"206",
    "addr:postcode":"28655",
    "addr:street":"Carolina St",
    "iso:country":"US",
    "sg:address":"206 Carolina St",
    "sg:city":"Morganton",
    "sg:classifiers":[
        {
            "category":"Social Services",
            "type":"Services"
        }
    ],
    "sg:phone":"+1 828 439 8893",
    "sg:postcode":"28655",
    "sg:province":"NC",
    "sg:tags":[
        "organization",
        "welfare"
    ],
    "wof:name":"Olive Hill Community Economic",
    "wof:placetype":"venue"
},
  "geometry": {"coordinates":[-81.674795,35.75334],"type":"Point"}
}