{
  "type": "Feature",
  "properties": {
    "iso:country":"US",
    "sg:address":"9100 Perimeter Woods Dr",
    "sg:city":"Charlotte",
    "sg:classifiers":[
        {
            "category":"Manufacturing",
            "subcategory":"Tools & Machinery",
            "type":"Manufacturing & Wholesale Goods"
        }
    ],
    "sg:phone":"+1 704 598 5660",
    "sg:postcode":"28216",
    "sg:province":"NC",
    "sg:tags":[
        "control"
    ],
    "wof:name":"Emerson Process Management",
    "wof:placetype":"venue"
},
  "geometry": {"coordinates":[-80.85117200000001,35.343956],"type":"Point"}
}