{
  "type": "Feature",
  "properties": {
    "addr:full":"3356 Frog Level Rd Greenville NC 27834",
    "addr:housenumber":"3356",
    "addr:postcode":"27834",
    "addr:street":"Frog Level Rd",
    "iso:country":"US",
    "sg:address":"3356 Frog Level Rd",
    "sg:city":"Greenville",
    "sg:classifiers":[
        {
            "category":"Building & Trades",
            "subcategory":"Construction",
            "type":"Services"
        }
    ],
    "sg:phone":"+1 252 355 8310",
    "sg:postcode":"27834",
    "sg:province":"NC",
    "sg:tags":[
        "restoration",
        "cleaning",
        "patio",
        "deck"
    ],
    "wof:name":"J J's Pressure Washing",
    "wof:placetype":"venue"
},
  "geometry": {"coordinates":[-77.44548899999999,35.567657],"type":"Point"}
}