{
  "type": "Feature",
  "properties": {
    "iso:country":"US",
    "sg:address":"100 Beatties Ford Rd",
    "sg:city":"Charlotte",
    "sg:classifiers":[
        {
            "category":"Personal",
            "type":"Services"
        },
        {
            "category":"Arena",
            "subcategory":"Sports Club",
            "type":"Entertainment"
        }
    ],
    "sg:phone":"+1 704 522 6500",
    "sg:postcode":"28216",
    "sg:province":"NC",
    "sg:tags":[
        "trainer",
        "consultant",
        "physical",
        "health",
        "fitness"
    ],
    "wof:name":"Brayboy Gymnasium Johnson C Smith U",
    "wof:placetype":"venue"
},
  "geometry": {"coordinates":[-80.858688,35.241711],"type":"Point"}
}