{
  "type": "Feature",
  "properties": {
    "addr:full":"3005 Broadbay Dr Winston Salem NC 27107",
    "addr:housenumber":"3005",
    "addr:postcode":"27107",
    "addr:street":"Broadbay Dr",
    "iso:country":"US",
    "sg:address":"3005 Broadbay Dr",
    "sg:city":"Winston Salem",
    "sg:classifiers":[
        {
            "category":"Professional",
            "type":"Services"
        }
    ],
    "sg:phone":"+1 336 788 7174",
    "sg:postcode":"27107",
    "sg:province":"NC",
    "wof:name":"Gloria M Moore",
    "wof:placetype":"venue"
},
  "geometry": {"coordinates":[-80.178206,36.076621],"type":"Point"}
}