{
  "type": "Feature",
  "properties": {
    "addr:full":"1315 Elder Way Burlington NC 27215",
    "addr:housenumber":"1315",
    "addr:postcode":"27215",
    "addr:street":"Elder Way",
    "iso:country":"US",
    "sg:address":"1315 Elder Way",
    "sg:city":"Burlington",
    "sg:classifiers":[
        {
            "category":"Wholesale",
            "subcategory":"Durable Goods & Equipment",
            "type":"Manufacturing & Wholesale Goods"
        }
    ],
    "sg:phone":"+1 336 227 2964",
    "sg:postcode":"27215",
    "sg:province":"NC",
    "sg:tags":[
        "fire",
        "extinguisher"
    ],
    "wof:name":"Catoe's Safety Equipment",
    "wof:placetype":"venue"
},
  "geometry": {"coordinates":[-79.44087500000001,36.07507],"type":"Point"}
}