{
  "type": "Feature",
  "properties": {
    "iso:country":"US",
    "sg:address":"109 Village Walk W",
    "sg:city":"Lumberton",
    "sg:classifiers":[
        {
            "category":"Retail",
            "subcategory":"Self-service Laundry",
            "type":"Services"
        }
    ],
    "sg:phone":"+1   ",
    "sg:postcode":"28358",
    "sg:province":"NC",
    "sg:tags":[
        "coin"
    ],
    "wof:name":"Jts Laundry Center Inc",
    "wof:placetype":"venue"
},
  "geometry": {"coordinates":[-78.996831,34.662185],"type":"Point"}
}