{
  "type": "Feature",
  "properties": {
    "iso:country":"US",
    "sg:address":"100 Euclid St",
    "sg:city":"Stedman",
    "sg:classifiers":[
        {
            "category":"Farming",
            "subcategory":"Farm",
            "type":"Manufacturing & Wholesale Goods"
        }
    ],
    "sg:phone":"+1 910 437 5114",
    "sg:postcode":"28391",
    "sg:province":"NC",
    "sg:tags":[
        "crop",
        "general"
    ],
    "wof:name":"Hornes Farms",
    "wof:placetype":"venue"
},
  "geometry": {"coordinates":[-78.693708,35.013549],"type":"Point"}
}