{
  "type": "Feature",
  "properties": {
    "iso:country":"US",
    "sg:address":"114 Walnut Dr",
    "sg:city":"Swansboro",
    "sg:classifiers":[
        {
            "category":"Wholesale",
            "subcategory":"Durable Goods & Equipment",
            "type":"Manufacturing & Wholesale Goods"
        }
    ],
    "sg:phone":"+1 910 326 4977",
    "sg:postcode":"28584",
    "sg:province":"NC",
    "sg:tags":[
        "fire",
        "extinguisher"
    ],
    "wof:name":"A-1 Alert Fire Equipment",
    "wof:placetype":"venue"
},
  "geometry": {"coordinates":[-77.144076,34.715826],"type":"Point"}
}