{
  "type": "Feature",
  "properties": {
    "iso:country":"US",
    "sg:address":"130 E Blanche St",
    "sg:city":"Clayton",
    "sg:classifiers":[
        {
            "category":"Professional",
            "subcategory":"Management & Consulting",
            "type":"Services"
        }
    ],
    "sg:phone":"+1   ",
    "sg:postcode":"27520",
    "sg:province":"NC",
    "sg:tags":[
        "personal",
        "house"
    ],
    "wof:name":"Barnes Home Management",
    "wof:placetype":"venue"
},
  "geometry": {"coordinates":[-78.461951,35.650351],"type":"Point"}
}