{
  "type": "Feature",
  "properties": {
    "addr:full":"1100 W Craighead Rd Charlotte NC 28206",
    "addr:housenumber":"1100",
    "addr:postcode":"28206",
    "addr:street":"W Craighead Rd",
    "iso:country":"US",
    "sg:address":"1100 W Craighead Rd",
    "sg:city":"Charlotte",
    "sg:classifiers":[
        {
            "category":"Freight",
            "type":"Transportation"
        }
    ],
    "sg:phone":"+1 704 597 7500",
    "sg:postcode":"28206",
    "sg:province":"NC",
    "sg:tags":[
        "operator",
        "trucking"
    ],
    "wof:name":"Rothrock Trucking",
    "wof:placetype":"venue"
},
  "geometry": {"coordinates":[-80.81291400000001,35.269788],"type":"Point"}
}