{
  "type": "Feature",
  "properties": {
    "iso:country":"US",
    "sg:address":"2660 Old Vashti Rd",
    "sg:city":"Taylorsville",
    "sg:classifiers":[
        {
            "category":"Wholesale",
            "subcategory":"Petroleum",
            "type":"Manufacturing & Wholesale Goods"
        }
    ],
    "sg:phone":"+1 828 632 2872",
    "sg:postcode":"28681",
    "sg:province":"NC",
    "sg:tags":[
        "fuel",
        "home",
        "delivery",
        "oil"
    ],
    "wof:name":"Farmers Oil Co of Alexander Co",
    "wof:placetype":"venue"
},
  "geometry": {"coordinates":[-81.112256,35.986593],"type":"Point"}
}