{
  "type": "Feature",
  "properties": {
    "iso:country":"US",
    "sg:address":"645 Pressley Rd",
    "sg:city":"Charlotte",
    "sg:classifiers":[
        {
            "category":"Communications",
            "subcategory":"Film & Video Production",
            "type":"Services"
        }
    ],
    "sg:phone":"+1 704 525 1773",
    "sg:postcode":"28217",
    "sg:province":"NC",
    "sg:tags":[
        "dvd",
        "cassette",
        "services-commercial",
        "duplicating",
        "cd"
    ],
    "wof:name":"Dragonfly Film & Video Production",
    "wof:placetype":"venue"
},
  "geometry": {"coordinates":[-80.89142200000001,35.186891],"type":"Point"}
}