{
  "type": "Feature",
  "properties": {
    "iso:country":"US",
    "sg:address":"4107 Romaine St",
    "sg:city":"Greensboro",
    "sg:classifiers":[
        {
            "category":"Recreation",
            "type":"Entertainment"
        }
    ],
    "sg:phone":"+1   ",
    "sg:postcode":"27407",
    "sg:province":"NC",
    "sg:tags":[
        "karate",
        "school",
        "instruction"
    ],
    "wof:name":"Yu Young Tae Kwon Do Assn",
    "wof:placetype":"venue"
},
  "geometry": {"coordinates":[-79.867311,36.036733],"type":"Point"}
}