{
  "type": "Feature",
  "properties": {
    "iso:country":"US",
    "sg:address":"405 N Clinton Ave",
    "sg:city":"Dunn",
    "sg:classifiers":[
        {
            "category":"Retail",
            "subcategory":"Auto Rental",
            "type":"Services"
        }
    ],
    "sg:phone":"+1 910 892 6890",
    "sg:postcode":"28334",
    "sg:province":"NC",
    "sg:tags":[
        "renting",
        "automobile"
    ],
    "wof:name":"Mobile Auto Svc & Rental",
    "wof:placetype":"venue"
},
  "geometry": {"coordinates":[-78.605542,35.310434],"type":"Point"}
}