{
  "type": "Feature",
  "properties": {
    "iso:country":"US",
    "sg:address":"1510 Kay St",
    "sg:city":"Charlotte",
    "sg:classifiers":[
        {
            "category":"Food & Beverages",
            "subcategory":"Groceries & Convenience Stores",
            "type":"Retail Goods"
        }
    ],
    "sg:phone":"+1 704 376 8114",
    "sg:postcode":"28216",
    "sg:province":"NC",
    "wof:name":"Mmseas Two Way LLC",
    "wof:placetype":"venue"
},
  "geometry": {"coordinates":[-80.844939,35.255756],"type":"Point"}
}