{
  "type": "Feature",
  "properties": {
    "addr:full":"201 Town Creek Dr Cary NC 27519",
    "addr:housenumber":"201",
    "addr:postcode":"27519",
    "addr:street":"Town Creek Dr",
    "iso:country":"US",
    "sg:address":"201 Town Creek Dr",
    "sg:city":"Cary",
    "sg:classifiers":[
        {
            "category":"Professional",
            "subcategory":"Computer Services",
            "type":"Services"
        }
    ],
    "sg:phone":"+1   ",
    "sg:postcode":"27519",
    "sg:province":"NC",
    "sg:tags":[
        "prepackaged",
        "software"
    ],
    "wof:name":"Emu Software",
    "wof:placetype":"venue"
},
  "geometry": {"coordinates":[-78.858936,35.773227],"type":"Point"}
}