{
  "type": "Feature",
  "properties": {
    "iso:country":"US",
    "sg:address":"1 Many Ln",
    "sg:city":"Black Mountain",
    "sg:classifiers":[
        {
            "category":"Manufacturing",
            "subcategory":"Retail Goods",
            "type":"Manufacturing & Wholesale Goods"
        }
    ],
    "sg:phone":"+1 828 296 1181",
    "sg:postcode":"28711",
    "sg:province":"NC",
    "sg:tags":[
        "product",
        "mfg"
    ],
    "wof:name":"Factory Direct Industries LLC",
    "wof:placetype":"venue"
},
  "geometry": {"coordinates":[-82.33928899999999,35.597284],"type":"Point"}
}