{
  "type": "Feature",
  "properties": {
    "addr:full":"51 Mercury Ln Sanford NC 27332",
    "addr:housenumber":"51",
    "addr:postcode":"27332",
    "addr:street":"Mercury Ln",
    "iso:country":"US",
    "sg:address":"51 Mercury Ln",
    "sg:city":"Sanford",
    "sg:classifiers":[
        {
            "category":"Shopping",
            "subcategory":"Used Merchandise",
            "type":"Retail Goods"
        }
    ],
    "sg:phone":"+1 919 774 6437",
    "sg:postcode":"27332",
    "sg:province":"NC",
    "wof:name":"William Beal",
    "wof:placetype":"venue"
},
  "geometry": {"coordinates":[-79.20559799999999,35.423573],"type":"Point"}
}