{
  "type": "Feature",
  "properties": {
    "addr:full":"604 Texas Trl Dallas NC 28034",
    "addr:housenumber":"604",
    "addr:postcode":"28034",
    "addr:street":"Texas Trl",
    "iso:country":"US",
    "sg:address":"604 Texas Trl",
    "sg:city":"Dallas",
    "sg:classifiers":[
        {
            "category":"Manufacturing",
            "subcategory":"Tools & Machinery",
            "type":"Manufacturing & Wholesale Goods"
        }
    ],
    "sg:phone":"+1 704 922 9621",
    "sg:postcode":"28034",
    "sg:province":"NC",
    "sg:tags":[
        "industrial",
        "mfg"
    ],
    "wof:name":"Carriage House Tool Labs",
    "wof:placetype":"venue"
},
  "geometry": {"coordinates":[-81.231623,35.387822],"type":"Point"}
}