{
  "type": "Feature",
  "properties": {
    "iso:country":"US",
    "sg:address":"535 Dimmocks Mill Rd",
    "sg:city":"Hillsborough",
    "sg:classifiers":[
        {
            "category":"Manufacturing",
            "subcategory":"Tools & Machinery",
            "type":"Manufacturing & Wholesale Goods"
        }
    ],
    "sg:phone":"+1 919 732 6444",
    "sg:postcode":"27278",
    "sg:province":"NC",
    "sg:tags":[
        "orthopedic"
    ],
    "sg:website":"www.kayeproducts.com",
    "wof:name":"Kaye Products Inc",
    "wof:placetype":"venue"
},
  "geometry": {"coordinates":[-79.118088,36.06969],"type":"Point"}
}