{
  "type": "Feature",
  "properties": {
    "addr:full":"5301 E Independence Blvd Charlotte NC 28212",
    "addr:housenumber":"5301",
    "addr:postcode":"28212",
    "addr:street":"E Independence Blvd",
    "iso:country":"US",
    "sg:address":"5301 E Independence Blvd",
    "sg:city":"Charlotte",
    "sg:classifiers":[
        {
            "category":"Restaurant",
            "type":"Food & Drink"
        }
    ],
    "sg:menulink":"http://www.allmenus.com/nc/charlotte/39247-fulin/menu/",
    "sg:phone":"+1 704 568 8877",
    "sg:postcode":"28212",
    "sg:province":"NC",
    "sg:tags":[
        "asian",
        "chinese"
    ],
    "wof:name":"Fulin",
    "wof:placetype":"venue"
},
  "geometry": {"coordinates":[-80.75919,35.186933],"type":"Point"}
}