{
  "type": "Feature",
  "properties": {
    "iso:country":"US",
    "sg:address":"501 Seminole Trl",
    "sg:city":"Jacksonville",
    "sg:classifiers":[
        {
            "category":"Personal",
            "subcategory":"Beauty Salon",
            "type":"Services"
        }
    ],
    "sg:phone":"+1 910 346 9355",
    "sg:postcode":"28540",
    "sg:province":"NC",
    "sg:tags":[
        "shop"
    ],
    "wof:name":"Allure Beauty Shop Salon",
    "wof:placetype":"venue"
},
  "geometry": {"coordinates":[-77.434544,34.771596],"type":"Point"}
}