{
  "type": "Feature",
  "properties": {
    "iso:country":"US",
    "sg:address":"824 Anderson St",
    "sg:city":"Durham",
    "sg:classifiers":[
        {
            "category":"Professional",
            "subcategory":"Management & Consulting",
            "type":"Services"
        }
    ],
    "sg:phone":"+1   ",
    "sg:postcode":"27705",
    "sg:province":"NC",
    "sg:tags":[
        "business"
    ],
    "wof:name":"Donald Serafin",
    "wof:placetype":"venue"
},
  "geometry": {"coordinates":[-78.930307,35.99839],"type":"Point"}
}