{
  "type": "Feature",
  "properties": {
    "iso:country":"US",
    "sg:address":"6135 Lakeview Rd",
    "sg:city":"Charlotte",
    "sg:classifiers":[
        {
            "category":"Wholesale",
            "subcategory":"Furniture",
            "type":"Manufacturing & Wholesale Goods"
        }
    ],
    "sg:phone":"+1 704 494 4866",
    "sg:postcode":"28269",
    "sg:province":"NC",
    "sg:tags":[
        "furniture-wholesale",
        "manufacturer"
    ],
    "wof:name":"Global Industries",
    "wof:placetype":"venue"
},
  "geometry": {"coordinates":[-80.836327,35.338342],"type":"Point"}
}