{
  "type": "Feature",
  "properties": {
    "addr:full":"1 N Keller Ln Grandy NC 27939",
    "addr:housenumber":"1",
    "addr:postcode":"27939",
    "addr:street":"N Keller Ln",
    "iso:country":"US",
    "sg:address":"1 N Keller Ln",
    "sg:city":"Grandy",
    "sg:classifiers":[
        {
            "category":"Building & Trades",
            "subcategory":"Construction",
            "type":"Services"
        }
    ],
    "sg:phone":"+1 252 453 6836",
    "sg:postcode":"27939",
    "sg:province":"NC",
    "sg:tags":[
        "water",
        "restoration",
        "damage"
    ],
    "wof:name":"Brittco Carpet Care",
    "wof:placetype":"venue"
},
  "geometry": {"coordinates":[-75.871172,36.243354],"type":"Point"}
}