{
  "type": "Feature",
  "properties": {
    "addr:full":"1317 Kirkland Rd Raleigh NC 27603",
    "addr:housenumber":"1317",
    "addr:postcode":"27603",
    "addr:street":"Kirkland Rd",
    "iso:country":"US",
    "sg:address":"1317 Kirkland Rd",
    "sg:city":"Raleigh",
    "sg:classifiers":[
        {
            "category":"Freight",
            "type":"Transportation"
        }
    ],
    "sg:phone":"+1 919 856 1971",
    "sg:postcode":"27603",
    "sg:province":"NC",
    "sg:tags":[
        "delivery"
    ],
    "wof:name":"Td Services",
    "wof:placetype":"venue"
},
  "geometry": {"coordinates":[-78.660684,35.753378],"type":"Point"}
}