{
  "type": "Feature",
  "properties": {
    "iso:country":"US",
    "sg:address":"2726 Buckhorn Rd",
    "sg:city":"Sanford",
    "sg:classifiers":[
        {
            "category":"Retail",
            "subcategory":"Auto Repair",
            "type":"Services"
        }
    ],
    "sg:phone":"+1   ",
    "sg:postcode":"27330",
    "sg:province":"NC",
    "sg:tags":[
        "general"
    ],
    "wof:name":"Acme Auto Care & Maint Exch",
    "wof:placetype":"venue"
},
  "geometry": {"coordinates":[-78.993612,35.50532],"type":"Point"}
}