{
  "type": "Feature",
  "properties": {
    "addr:full":"2602 Hendersonville Rd Arden NC 28704",
    "addr:housenumber":"2602",
    "addr:postcode":"28704",
    "addr:street":"Hendersonville Rd",
    "iso:country":"US",
    "sg:address":"2602 Hendersonville Rd",
    "sg:city":"Arden",
    "sg:classifiers":[
        {
            "category":"Real Estate",
            "subcategory":"Real Estate Agent",
            "type":"Services"
        }
    ],
    "sg:phone":"+1 828 650 6890",
    "sg:postcode":"28704",
    "sg:province":"NC",
    "sg:tags":[
        "agency",
        "rental"
    ],
    "wof:name":"Rental Management",
    "wof:placetype":"venue"
},
  "geometry": {"coordinates":[-82.508582,35.448913],"type":"Point"}
}