{
  "type": "Feature",
  "properties": {
    "iso:country":"US",
    "sg:address":"1155 Salisbury Rd",
    "sg:city":"Statesville",
    "sg:classifiers":[
        {
            "category":"Autos & Motor Vehicles",
            "subcategory":"Fuel & Gas Station",
            "type":"Retail Goods"
        }
    ],
    "sg:phone":"+1 704 872 1276",
    "sg:postcode":"28625",
    "sg:province":"NC",
    "sg:tags":[
        "convenient",
        "station",
        "gasoline",
        "store"
    ],
    "wof:name":"Maydhr Corporation",
    "wof:placetype":"venue"
},
  "geometry": {"coordinates":[-80.86248399999999,35.774704],"type":"Point"}
}