{
  "type": "Feature",
  "properties": {
    "iso:country":"US",
    "sg:address":"2005 Rowan Rd",
    "sg:city":"Clinton",
    "sg:classifiers":[
        {
            "category":"Freight",
            "type":"Transportation"
        }
    ],
    "sg:phone":"+1 910 592 2354",
    "sg:postcode":"28328",
    "sg:province":"NC",
    "sg:tags":[
        "operator",
        "trucking"
    ],
    "wof:name":"Curtis Smith",
    "wof:placetype":"venue"
},
  "geometry": {"coordinates":[-78.269357,34.975187],"type":"Point"}
}