{
  "type": "Feature",
  "properties": {
    "iso:country":"US",
    "sg:address":"4540 Main St",
    "sg:city":"Shallotte",
    "sg:classifiers":[
        {
            "category":"Shopping",
            "subcategory":"Optical Goods",
            "type":"Retail Goods"
        }
    ],
    "sg:phone":"+1 910 754 3263",
    "sg:postcode":"28470",
    "sg:province":"NC",
    "wof:name":"National Vision",
    "wof:placetype":"venue"
},
  "geometry": {"coordinates":[-78.37344,33.981466],"type":"Point"}
}