{
  "type": "Feature",
  "properties": {
    "addr:full":"108 Walden Woods Dr La Grange NC 28551",
    "addr:housenumber":"108",
    "addr:postcode":"28551",
    "addr:street":"Walden Woods Dr",
    "iso:country":"US",
    "sg:address":"108 Walden Woods Dr",
    "sg:city":"La Grange",
    "sg:classifiers":[
        {
            "category":"Building & Trades",
            "subcategory":"Construction",
            "type":"Services"
        }
    ],
    "sg:phone":"+1 919 751 2668",
    "sg:postcode":"28551",
    "sg:province":"NC",
    "sg:tags":[
        "house"
    ],
    "wof:name":"Govan Construction",
    "wof:placetype":"venue"
},
  "geometry": {"coordinates":[-77.834299,35.398859],"type":"Point"}
}