{
  "type": "Feature",
  "properties": {
    "iso:country":"US",
    "sg:address":"308 Settlers Ln",
    "sg:city":"Kure Beach",
    "sg:classifiers":[
        {
            "category":"Building & Trades",
            "subcategory":"Construction",
            "type":"Services"
        }
    ],
    "sg:phone":"+1 910 458 0080",
    "sg:postcode":"28449",
    "sg:province":"NC",
    "sg:tags":[
        "residential",
        "designer"
    ],
    "wof:name":"Moore's Drafting Svc",
    "wof:placetype":"venue"
},
  "geometry": {"coordinates":[-77.90925900000001,34.002778],"type":"Point"}
}