{
  "type": "Feature",
  "properties": {
    "addr:full":"7205 Shoe Rd Burlington NC 27215",
    "addr:housenumber":"7205",
    "addr:postcode":"27215",
    "addr:street":"Shoe Rd",
    "iso:country":"US",
    "sg:address":"7205 Shoe Rd",
    "sg:city":"Burlington",
    "sg:classifiers":[
        {
            "category":"Retail",
            "subcategory":"Repair Shop",
            "type":"Services"
        }
    ],
    "sg:phone":"+1 336 449 9800",
    "sg:postcode":"27215",
    "sg:province":"NC",
    "sg:tags":[
        "bathtub",
        "sink",
        "refinishing"
    ],
    "wof:name":"Bath Brite",
    "wof:placetype":"venue"
},
  "geometry": {"coordinates":[-79.56037600000001,36.017949],"type":"Point"}
}