{
  "type": "Feature",
  "properties": {
    "addr:full":"241 W 5th St Winston Salem NC 27101",
    "addr:housenumber":"241",
    "addr:postcode":"27101",
    "addr:street":"W 5Th St",
    "iso:country":"US",
    "sg:address":"241 W 5th St",
    "sg:city":"Winston Salem",
    "sg:classifiers":[
        {
            "category":"Restaurant",
            "type":"Food & Drink"
        }
    ],
    "sg:phone":"+1 336 724 2691",
    "sg:postcode":"27101",
    "sg:province":"NC",
    "wof:name":"Kopper Kitchen",
    "wof:placetype":"venue"
},
  "geometry": {"coordinates":[-80.246871,36.099807],"type":"Point"}
}