{
  "type": "Feature",
  "properties": {
    "iso:country":"US",
    "sg:address":"166 Heath Dr",
    "sg:city":"Waynesville",
    "sg:classifiers":[
        {
            "category":"Building & Trades",
            "subcategory":"Construction",
            "type":"Services"
        }
    ],
    "sg:phone":"+1 828 648 6662",
    "sg:postcode":"28786",
    "sg:province":"NC",
    "sg:tags":[
        "maker",
        "cabinet"
    ],
    "wof:name":"Janney's Woodworking Shop",
    "wof:placetype":"venue"
},
  "geometry": {"coordinates":[-83.02728399999999,35.476077],"type":"Point"}
}