{
  "type": "Feature",
  "properties": {
    "addr:full":"505 Stanley Ave Charlotte NC 28205",
    "addr:housenumber":"505",
    "addr:postcode":"28205",
    "addr:street":"Stanley Ave",
    "iso:country":"US",
    "sg:address":"505 Stanley Ave",
    "sg:city":"Charlotte",
    "sg:classifiers":[
        {
            "category":"Restaurant",
            "type":"Food & Drink"
        }
    ],
    "sg:phone":"+1 704 334 2628",
    "sg:postcode":"28205",
    "sg:province":"NC",
    "wof:name":"Jalapeno To Go",
    "wof:placetype":"venue"
},
  "geometry": {"coordinates":[-80.79387199999999,35.197793],"type":"Point"}
}