{
  "type": "Feature",
  "properties": {
    "addr:full":"504 Oakwood Ave Durham NC 27701",
    "addr:housenumber":"504",
    "addr:postcode":"27701",
    "addr:street":"Oakwood Ave",
    "iso:country":"US",
    "sg:address":"504 Oakwood Ave",
    "sg:city":"Durham",
    "sg:classifiers":[
        {
            "category":"Building & Trades",
            "subcategory":"Landscaping Services",
            "type":"Services"
        }
    ],
    "sg:phone":"+1 919 688 8126",
    "sg:postcode":"27701",
    "sg:province":"NC",
    "sg:tags":[
        "tree"
    ],
    "wof:name":"Perry's Tree Svc",
    "wof:placetype":"venue"
},
  "geometry": {"coordinates":[-78.893406,35.996906],"type":"Point"}
}