{
  "type": "Feature",
  "properties": {
    "iso:country":"US",
    "sg:address":"113 Arendell St",
    "sg:city":"Morehead City",
    "sg:classifiers":[
        {
            "category":"Building & Trades",
            "subcategory":"Construction",
            "type":"Services"
        }
    ],
    "sg:phone":"+1 252 726 9229",
    "sg:postcode":"28557",
    "sg:province":"NC",
    "sg:tags":[
        "designer",
        "marine",
        "contractor"
    ],
    "wof:name":"Compass Marine Inc",
    "wof:placetype":"venue"
},
  "geometry": {"coordinates":[-76.69963199999999,34.720769],"type":"Point"}
}