{
  "type": "Feature",
  "properties": {
    "addr:full":"1436 Cotton Grove Rd Lexington NC 27292",
    "addr:housenumber":"1436",
    "addr:postcode":"27292",
    "addr:street":"Cotton Grove Rd",
    "iso:country":"US",
    "sg:address":"1436 Cotton Grove Rd",
    "sg:city":"Lexington",
    "sg:classifiers":[
        {
            "category":"Organizations",
            "subcategory":"Religious Organization",
            "type":"Services"
        }
    ],
    "sg:phone":"+1   ",
    "sg:postcode":"27292",
    "sg:province":"NC",
    "wof:name":"Fairmont Presbyterian Church",
    "wof:placetype":"venue"
},
  "geometry": {"coordinates":[-80.260222,35.783525],"type":"Point"}
}