{
  "type": "Feature",
  "properties": {
    "iso:country":"US",
    "sg:address":"3676 Guess Rd",
    "sg:city":"Durham",
    "sg:classifiers":[
        {
            "category":"Health Services",
            "subcategory":"Health Practitioner",
            "type":"Services"
        }
    ],
    "sg:phone":"+1 919 471 4288",
    "sg:postcode":"27705",
    "sg:province":"NC",
    "sg:tags":[
        "therapist"
    ],
    "wof:name":"Right Direction Inc",
    "wof:placetype":"venue"
},
  "geometry": {"coordinates":[-78.929356,36.045868],"type":"Point"}
}