{
  "type": "Feature",
  "properties": {
    "addr:full":"7416 Valleybrook Rd Charlotte NC 28270",
    "addr:housenumber":"7416",
    "addr:postcode":"28270",
    "addr:street":"Valleybrook Rd",
    "iso:country":"US",
    "sg:address":"7416 Valleybrook Rd",
    "sg:city":"Charlotte",
    "sg:classifiers":[
        {
            "category":"Banks & Credit Unions",
            "subcategory":"Financial Services",
            "type":"Services"
        }
    ],
    "sg:phone":"+1 704 364 1601",
    "sg:postcode":"28270",
    "sg:province":"NC",
    "sg:tags":[
        "trust",
        "management"
    ],
    "wof:name":"Patten Ventures Inc",
    "wof:placetype":"venue"
},
  "geometry": {"coordinates":[-80.774106,35.136619],"type":"Point"}
}