{
  "type": "Feature",
  "properties": {
    "iso:country":"US",
    "sg:address":"225 Jim Moore Rd",
    "sg:city":"Timberlake",
    "sg:classifiers":[
        {
            "category":"Real Estate",
            "subcategory":"Real Estate Agent",
            "type":"Services"
        }
    ],
    "sg:phone":"+1 336 364 4386",
    "sg:postcode":"27583",
    "sg:province":"NC",
    "wof:name":"Perry Realty Dev",
    "wof:placetype":"venue"
},
  "geometry": {"coordinates":[-78.927252,36.281149],"type":"Point"}
}