{
  "type": "Feature",
  "properties": {
    "addr:full":"259 W Fleming Dr Morganton NC 28655",
    "addr:housenumber":"259",
    "addr:postcode":"28655",
    "addr:street":"W Fleming Dr",
    "iso:country":"US",
    "sg:address":"259 W Fleming Dr",
    "sg:city":"Morganton",
    "sg:classifiers":[
        {
            "category":"Personal",
            "subcategory":"Beauty Salon",
            "type":"Services"
        }
    ],
    "sg:phone":"+1 828 437 0911",
    "sg:postcode":"28655",
    "sg:province":"NC",
    "wof:name":"X Ceptional Hair Salon",
    "wof:placetype":"venue"
},
  "geometry": {"coordinates":[-81.683646,35.734774],"type":"Point"}
}