{
  "type": "Feature",
  "properties": {
    "addr:full":"667 Hyde Park Dr NE Concord NC 28025",
    "addr:housenumber":"667",
    "addr:postcode":"28025",
    "addr:street":"Hyde Park Dr Ne",
    "iso:country":"US",
    "sg:address":"667 Hyde Park Dr NE",
    "sg:city":"Concord",
    "sg:classifiers":[
        {
            "category":"Organizations",
            "subcategory":"Religious Organization",
            "type":"Services"
        }
    ],
    "sg:phone":"+1 704 782 5156",
    "sg:postcode":"28025",
    "sg:province":"NC",
    "sg:tags":[
        "clergy"
    ],
    "wof:name":"David W Brown",
    "wof:placetype":"venue"
},
  "geometry": {"coordinates":[-80.593643,35.430203],"type":"Point"}
}