{
  "type": "Feature",
  "properties": {
    "addr:full":"2749 Cherokee Ln Winston Salem NC 27103",
    "addr:housenumber":"2749",
    "addr:postcode":"27103",
    "addr:street":"Cherokee Ln",
    "iso:country":"US",
    "sg:address":"2749 Cherokee Ln",
    "sg:city":"Winston Salem",
    "sg:classifiers":[
        {
            "category":"Insurance",
            "subcategory":"Insurance Agent",
            "type":"Services"
        }
    ],
    "sg:phone":"+1 336 768 6509",
    "sg:postcode":"27103",
    "sg:province":"NC",
    "wof:name":"Woodmen of World Lf Insur Soc",
    "wof:placetype":"venue"
},
  "geometry": {"coordinates":[-80.288141,36.07309],"type":"Point"}
}