{
  "type": "Feature",
  "properties": {
    "addr:full":"719 N Main St Marion NC 28752",
    "addr:housenumber":"719",
    "addr:postcode":"28752",
    "addr:street":"N Main St",
    "iso:country":"US",
    "sg:address":"719 N Main St",
    "sg:city":"Marion",
    "sg:classifiers":[
        {
            "category":"Retail",
            "subcategory":"Auto Repair",
            "type":"Services"
        }
    ],
    "sg:phone":"+1   ",
    "sg:postcode":"28752",
    "sg:province":"NC",
    "sg:tags":[
        "transmission"
    ],
    "wof:name":"Millers Transmission Service",
    "wof:placetype":"venue"
},
  "geometry": {"coordinates":[-82.01854299999999,35.690165],"type":"Point"}
}