{
  "type": "Feature",
  "properties": {
    "addr:full":"2515 Smoky Park Hwy Candler NC 28715",
    "addr:housenumber":"2515",
    "addr:postcode":"28715",
    "addr:street":"Smoky Park Hwy",
    "iso:country":"US",
    "sg:address":"2515 Smoky Park Hwy",
    "sg:city":"Candler",
    "sg:classifiers":[
        {
            "category":"Food & Beverages",
            "subcategory":"Groceries & Convenience Stores",
            "type":"Retail Goods"
        }
    ],
    "sg:phone":"+1 828 670 9272",
    "sg:postcode":"28715",
    "sg:province":"NC",
    "wof:name":"Time Out Market #15",
    "wof:placetype":"venue"
},
  "geometry": {"coordinates":[-82.753508,35.541008],"type":"Point"}
}