{
  "type": "Feature",
  "properties": {
    "addr:full":"653 E Webb Ave Burlington NC 27217",
    "addr:housenumber":"653",
    "addr:postcode":"27217",
    "addr:street":"E Webb Ave",
    "iso:country":"US",
    "sg:address":"653 E Webb Ave",
    "sg:city":"Burlington",
    "sg:classifiers":[
        {
            "category":"Banks & Credit Unions",
            "subcategory":"Bank",
            "type":"Services"
        }
    ],
    "sg:phone":"+1 336 229 6100",
    "sg:postcode":"27217",
    "sg:province":"NC",
    "sg:tags":[
        "cashing",
        "check"
    ],
    "wof:name":"Friendly Check Cashing",
    "wof:placetype":"venue"
},
  "geometry": {"coordinates":[-79.430164,36.088426],"type":"Point"}
}