{
  "type": "Feature",
  "properties": {
    "addr:full":"412 W Fleming Dr Morganton NC 28655",
    "addr:housenumber":"412",
    "addr:postcode":"28655",
    "addr:street":"W Fleming Dr",
    "iso:country":"US",
    "sg:address":"412 W Fleming Dr",
    "sg:city":"Morganton",
    "sg:classifiers":[
        {
            "category":"Shopping",
            "subcategory":"Used Merchandise",
            "type":"Retail Goods"
        },
        {
            "category":"Social Services",
            "type":"Services"
        }
    ],
    "sg:phone":"+1 828 439 8080",
    "sg:postcode":"28655",
    "sg:province":"NC",
    "sg:tags":[
        "organization",
        "welfare"
    ],
    "wof:name":"Salvation Army Thrift Store",
    "wof:placetype":"venue"
},
  "geometry": {"coordinates":[-81.684657,35.734562],"type":"Point"}
}