{
  "type": "Feature",
  "properties": {
    "iso:country":"US",
    "sg:address":"340 Merrimon Ave",
    "sg:city":"Asheville",
    "sg:classifiers":[
        {
            "category":"Shopping",
            "subcategory":"Clothing, Apparel, & Fashions",
            "type":"Retail Goods"
        }
    ],
    "sg:phone":"+1 828 251 5651",
    "sg:postcode":"28801",
    "sg:province":"NC",
    "sg:tags":[
        "apparel",
        "women's"
    ],
    "wof:name":"Clothes Encounters",
    "wof:placetype":"venue"
},
  "geometry": {"coordinates":[-82.554754,35.610373],"type":"Point"}
}