{
  "type": "Feature",
  "properties": {
    "iso:country":"US",
    "sg:address":"4191 State Hwy 87 S",
    "sg:city":"Moncure",
    "sg:classifiers":[
        {
            "category":"Building & Trades",
            "subcategory":"Construction",
            "type":"Services"
        }
    ],
    "sg:phone":"+1 919 642 0140",
    "sg:postcode":"27559",
    "sg:province":"NC",
    "sg:tags":[
        "nonresidential"
    ],
    "wof:name":"J A Jones of The Carolinas",
    "wof:placetype":"venue"
},
  "geometry": {"coordinates":[-79.176794,35.660476],"type":"Point"}
}