{
  "type": "Feature",
  "properties": {
    "iso:country":"US",
    "sg:address":"510 N Green St",
    "sg:city":"Morganton",
    "sg:classifiers":[
        {
            "category":"Home & Garden",
            "subcategory":"Garden Supply",
            "type":"Retail Goods"
        }
    ],
    "sg:phone":"+1 828 433 4428",
    "sg:postcode":"28655",
    "sg:province":"NC",
    "sg:tags":[
        "lawn",
        "mower"
    ],
    "wof:name":"North Green Small Engine",
    "wof:placetype":"venue"
},
  "geometry": {"coordinates":[-81.695798,35.748404],"type":"Point"}
}