{
  "type": "Feature",
  "properties": {
    "iso:country":"US",
    "sg:address":"9870 Leesville Rd",
    "sg:city":"Raleigh",
    "sg:classifiers":[
        {
            "category":"Restaurant",
            "type":"Food & Drink"
        }
    ],
    "sg:phone":"+1 919 847 0453",
    "sg:postcode":"27617",
    "sg:province":"NC",
    "wof:name":"Goodberry's Frozen Custard",
    "wof:placetype":"venue"
},
  "geometry": {"coordinates":[-78.727296,35.907437],"type":"Point"}
}