{
  "type": "Feature",
  "properties": {
    "addr:full":"101 Zebulon Ct Rocky Mount NC 27804",
    "addr:housenumber":"101",
    "addr:postcode":"27804",
    "addr:street":"Zebulon Ct",
    "iso:country":"US",
    "sg:address":"101 Zebulon Ct",
    "sg:city":"Rocky Mount",
    "sg:classifiers":[
        {
            "category":"Professional",
            "subcategory":"Accounting & Tax Preparation",
            "type":"Services"
        }
    ],
    "sg:phone":"+1 252 451 1900",
    "sg:postcode":"27804",
    "sg:province":"NC",
    "sg:tags":[
        "accountant"
    ],
    "wof:name":"Oettinger & Norwood",
    "wof:placetype":"venue"
},
  "geometry": {"coordinates":[-77.837981,35.964259],"type":"Point"}
}