{
  "type": "Feature",
  "properties": {
    "iso:country":"US",
    "sg:address":"2946 Ivy Ave",
    "sg:city":"Winston Salem",
    "sg:classifiers":[
        {
            "category":"Organizations",
            "subcategory":"Religious Organization",
            "type":"Services"
        }
    ],
    "sg:phone":"+1   ",
    "sg:postcode":"27105",
    "sg:province":"NC",
    "wof:name":"New Unity Mssnary Bptst Church",
    "wof:placetype":"venue"
},
  "geometry": {"coordinates":[-80.239498,36.125793],"type":"Point"}
}