{
  "type": "Feature",
  "properties": {
    "iso:country":"US",
    "sg:address":"2406 M L King Jr Blvd",
    "sg:city":"New Bern",
    "sg:classifiers":[
        {
            "category":"Shopping",
            "subcategory":"Jewelry",
            "type":"Retail Goods"
        }
    ],
    "sg:phone":"+1 252 637 7999",
    "sg:postcode":"28562",
    "sg:province":"NC",
    "sg:tags":[
        "jeweler"
    ],
    "wof:name":"J & W Jewelry & Loan",
    "wof:placetype":"venue"
},
  "geometry": {"coordinates":[-77.078774,35.106246],"type":"Point"}
}