{
  "type": "Feature",
  "properties": {
    "addr:full":"215 E Broad St St Pauls NC 28384",
    "addr:housenumber":"215",
    "addr:postcode":"28384",
    "addr:street":"E Broad St",
    "iso:country":"US",
    "sg:address":"215 E Broad St",
    "sg:city":"St Pauls",
    "sg:classifiers":[
        {
            "category":"Freight",
            "type":"Transportation"
        }
    ],
    "sg:phone":"+1 910 865 4421",
    "sg:postcode":"28384",
    "sg:province":"NC",
    "sg:tags":[
        "mover"
    ],
    "wof:name":"All American Mobile Hm Movers",
    "wof:placetype":"venue"
},
  "geometry": {"coordinates":[-78.96953999999999,34.806474],"type":"Point"}
}