{
  "type": "Feature",
  "properties": {
    "iso:country":"US",
    "sg:address":"6517 Hilburn Dr",
    "sg:city":"Raleigh",
    "sg:classifiers":[
        {
            "category":"Building & Trades",
            "subcategory":"Electrical",
            "type":"Services"
        }
    ],
    "sg:phone":"+1 919 781 4651",
    "sg:postcode":"27613",
    "sg:province":"NC",
    "sg:tags":[
        "electrician"
    ],
    "wof:name":"Watson Electrical Construction Co Llc",
    "wof:placetype":"venue"
},
  "geometry": {"coordinates":[-78.71550000000001,35.869701],"type":"Point"}
}