{
  "type": "Feature",
  "properties": {
    "addr:full":"1414 E Franklin Blvd Gastonia NC 28054",
    "addr:housenumber":"1414",
    "addr:postcode":"28054",
    "addr:street":"E Franklin Blvd",
    "iso:country":"US",
    "sg:address":"1414 E Franklin Blvd",
    "sg:city":"Gastonia",
    "sg:classifiers":[
        {
            "category":"Restaurant",
            "type":"Food & Drink"
        }
    ],
    "sg:phone":"+1 704 868 2010",
    "sg:postcode":"28054",
    "sg:province":"NC",
    "sg:tags":[
        "eating"
    ],
    "wof:name":"Arbys",
    "wof:placetype":"venue"
},
  "geometry": {"coordinates":[-81.15438899999999,35.26229],"type":"Point"}
}