{
  "type": "Feature",
  "properties": {
    "iso:country":"US",
    "sg:address":"103 Worth St",
    "sg:city":"Asheboro",
    "sg:classifiers":[
        {
            "category":"Professional",
            "subcategory":"Lawyer & Legal Services",
            "type":"Services"
        }
    ],
    "sg:phone":"+1   ",
    "sg:postcode":"27203",
    "sg:province":"NC",
    "wof:name":"Law Offices of James Young",
    "wof:placetype":"venue"
},
  "geometry": {"coordinates":[-79.81404000000001,35.706127],"type":"Point"}
}