{
  "type": "Feature",
  "properties": {
    "addr:full":"2805 Haven Rd Raleigh NC 27610",
    "addr:housenumber":"2805",
    "addr:postcode":"27610",
    "addr:street":"Haven Rd",
    "iso:country":"US",
    "sg:address":"2805 Haven Rd",
    "sg:city":"Raleigh",
    "sg:classifiers":[
        {
            "category":"Building & Trades",
            "subcategory":"Construction",
            "type":"Services"
        }
    ],
    "sg:phone":"+1 919 250 0942",
    "sg:postcode":"27610",
    "sg:province":"NC",
    "sg:tags":[
        "carpentry",
        "contractor"
    ],
    "wof:name":"Morales Construction",
    "wof:placetype":"venue"
},
  "geometry": {"coordinates":[-78.58747700000001,35.776582],"type":"Point"}
}