{
  "type": "Feature",
  "properties": {
    "addr:full":"2100 N Davidson St Charlotte NC 28205",
    "addr:housenumber":"2100",
    "addr:postcode":"28205",
    "addr:street":"N Davidson St",
    "iso:country":"US",
    "sg:address":"2100 N Davidson St",
    "sg:city":"Charlotte",
    "sg:classifiers":[
        {
            "category":"Manufacturing",
            "subcategory":"Signs",
            "type":"Manufacturing & Wholesale Goods"
        }
    ],
    "sg:phone":"+1 704 358 1099",
    "sg:postcode":"28205",
    "sg:province":"NC",
    "wof:name":"Sensational Signs",
    "wof:placetype":"venue"
},
  "geometry": {"coordinates":[-80.81542399999999,35.239382],"type":"Point"}
}