{
  "type": "Feature",
  "properties": {
    "iso:country":"US",
    "sg:address":"741 E Webb Ave",
    "sg:city":"Burlington",
    "sg:classifiers":[
        {
            "category":"Manufacturing",
            "subcategory":"Textiles",
            "type":"Manufacturing & Wholesale Goods"
        }
    ],
    "sg:phone":"+1 336 227 2716",
    "sg:postcode":"27217",
    "sg:province":"NC",
    "sg:tags":[
        "hosiery"
    ],
    "sg:website":"www.picketthosiery.com",
    "wof:name":"Pickett Hosiery Mills Inc",
    "wof:placetype":"venue"
},
  "geometry": {"coordinates":[-79.42868300000001,36.086884],"type":"Point"}
}