{
  "type": "Feature",
  "properties": {
    "addr:full":"101 Majestic Ct Chapel Hill NC 27517",
    "addr:housenumber":"101",
    "addr:postcode":"27517",
    "addr:street":"Majestic Ct",
    "iso:country":"US",
    "sg:address":"101 Majestic Ct",
    "sg:city":"Chapel Hill",
    "sg:classifiers":[
        {
            "category":"Social Services",
            "type":"Services"
        }
    ],
    "sg:phone":"+1   ",
    "sg:postcode":"27517",
    "sg:province":"NC",
    "sg:tags":[
        "consulting",
        "family"
    ],
    "wof:name":"Gary L Bowen",
    "wof:placetype":"venue"
},
  "geometry": {"coordinates":[-79.034504,35.885804],"type":"Point"}
}