{
  "type": "Feature",
  "properties": {
    "addr:full":"1023 W Morehead St Charlotte NC 28208",
    "addr:housenumber":"1023",
    "addr:postcode":"28208",
    "addr:street":"W Morehead St",
    "iso:country":"US",
    "sg:address":"1023 W Morehead St",
    "sg:city":"Charlotte",
    "sg:classifiers":[
        {
            "category":"Real Estate",
            "subcategory":"Real Estate Agent",
            "type":"Services"
        }
    ],
    "sg:phone":"+1 704 335 5455",
    "sg:postcode":"28208",
    "sg:province":"NC",
    "wof:name":"Shopping Center Group",
    "wof:placetype":"venue"
},
  "geometry": {"coordinates":[-80.859506,35.228566],"type":"Point"}
}