{
  "type": "Feature",
  "properties": {
    "addr:full":"3687 Chimney Rock Rd Hendersonville NC 28792",
    "addr:housenumber":"3687",
    "addr:postcode":"28792",
    "addr:street":"Chimney Rock Rd",
    "iso:country":"US",
    "sg:address":"3687 Chimney Rock Rd",
    "sg:city":"Hendersonville",
    "sg:classifiers":[
        {
            "category":"Retail",
            "subcategory":"Animal Services",
            "type":"Services"
        }
    ],
    "sg:phone":"+1 828 685 1669",
    "sg:postcode":"28792",
    "sg:province":"NC",
    "wof:name":"Ox Bow Saddle Shop",
    "wof:placetype":"venue"
},
  "geometry": {"coordinates":[-82.357647,35.383889],"type":"Point"}
}