{
  "type": "Feature",
  "properties": {
    "addr:full":"307 Gilead Rd Huntersville NC 28078",
    "addr:housenumber":"307",
    "addr:postcode":"28078",
    "addr:street":"Gilead Rd",
    "iso:country":"US",
    "sg:address":"307 Gilead Rd",
    "sg:city":"Huntersville",
    "sg:classifiers":[
        {
            "category":"Insurance",
            "subcategory":"Insurance Agent",
            "type":"Services"
        }
    ],
    "sg:phone":"+1 704 875 1696",
    "sg:postcode":"28078",
    "sg:province":"NC",
    "sg:tags":[
        "brokerage"
    ],
    "wof:name":"First Charter",
    "wof:placetype":"venue"
},
  "geometry": {"coordinates":[-80.849791,35.410541],"type":"Point"}
}