{
  "type": "Feature",
  "properties": {
    "addr:full":"1015 Owen Blvd Charlotte NC 28213",
    "addr:housenumber":"1015",
    "addr:postcode":"28213",
    "addr:street":"Owen Blvd",
    "iso:country":"US",
    "sg:address":"1015 Owen Blvd",
    "sg:city":"Charlotte",
    "sg:classifiers":[
        {
            "category":"Building & Trades",
            "subcategory":"Construction",
            "type":"Services"
        }
    ],
    "sg:phone":"+1 704 408 2437",
    "sg:postcode":"28213",
    "sg:province":"NC",
    "sg:tags":[
        "floor",
        "laying",
        "contractor"
    ],
    "wof:name":"Jamie Barbosa",
    "wof:placetype":"venue"
},
  "geometry": {"coordinates":[-80.753635,35.279741],"type":"Point"}
}