{
  "type": "Feature",
  "properties": {
    "iso:country":"US",
    "sg:address":"3672 Polkville Rd",
    "sg:city":"Shelby",
    "sg:classifiers":[
        {
            "category":"Shopping",
            "subcategory":"Used Merchandise",
            "type":"Retail Goods"
        }
    ],
    "sg:phone":"+1 704 482 8542",
    "sg:postcode":"28150",
    "sg:province":"NC",
    "wof:name":"Antique Outlet",
    "wof:placetype":"venue"
},
  "geometry": {"coordinates":[-81.611969,35.379608],"type":"Point"}
}