{
  "type": "Feature",
  "properties": {
    "addr:full":"3328 Guess Rd Durham NC 27705",
    "addr:housenumber":"3328",
    "addr:postcode":"27705",
    "addr:street":"Guess Rd",
    "iso:country":"US",
    "sg:address":"3328 Guess Rd",
    "sg:city":"Durham",
    "sg:classifiers":[
        {
            "category":"Professional",
            "subcategory":"Accounting & Tax Preparation",
            "type":"Services"
        }
    ],
    "sg:phone":"+1 919 620 5700",
    "sg:postcode":"27705",
    "sg:province":"NC",
    "sg:tags":[
        "billing"
    ],
    "wof:name":"Summit Physicians Svc Inc",
    "wof:placetype":"venue"
},
  "geometry": {"coordinates":[-78.929519,36.039186],"type":"Point"}
}