{
  "type": "Feature",
  "properties": {
    "addr:full":"3606 Wyatt St Fayetteville NC 28304",
    "addr:housenumber":"3606",
    "addr:postcode":"28304",
    "addr:street":"Wyatt St",
    "iso:country":"US",
    "sg:address":"3606 Wyatt St",
    "sg:city":"Fayetteville",
    "sg:classifiers":[
        {
            "category":"Building & Trades",
            "subcategory":"Construction",
            "type":"Services"
        }
    ],
    "sg:phone":"+1 910 429 3001",
    "sg:postcode":"28304",
    "sg:province":"NC",
    "sg:tags":[
        "house"
    ],
    "wof:name":"Kwik Fix Inc",
    "wof:placetype":"venue"
},
  "geometry": {"coordinates":[-78.938017,35.024596],"type":"Point"}
}