{
  "type": "Feature",
  "properties": {
    "iso:country":"US",
    "sg:address":"720 Mc Rae St",
    "sg:city":"Wilmington",
    "sg:classifiers":[
        {
            "category":"Organizations",
            "subcategory":"Religious Organization",
            "type":"Services"
        }
    ],
    "sg:phone":"+1   ",
    "sg:postcode":"28401",
    "sg:province":"NC",
    "wof:name":"Temple Rock Tabernacle Church",
    "wof:placetype":"venue"
},
  "geometry": {"coordinates":[-77.93947300000001,34.244803],"type":"Point"}
}