{
  "type": "Feature",
  "properties": {
    "addr:full":"2525 Branch Rd Raleigh NC 27610",
    "addr:housenumber":"2525",
    "addr:postcode":"27610",
    "addr:street":"Branch Rd",
    "iso:country":"US",
    "sg:address":"2525 Branch Rd",
    "sg:city":"Raleigh",
    "sg:classifiers":[
        {
            "category":"Shopping",
            "subcategory":"Computers & Home Electronics",
            "type":"Retail Goods"
        }
    ],
    "sg:phone":"+1 919 779 4831",
    "sg:postcode":"27610",
    "sg:province":"NC",
    "sg:tags":[
        "software"
    ],
    "wof:name":"1 Vision Technologies",
    "wof:placetype":"venue"
},
  "geometry": {"coordinates":[-78.51893,35.704928],"type":"Point"}
}