{
  "type": "Feature",
  "properties": {
    "addr:full":"1001 Mason Rd Durham NC 27712",
    "addr:housenumber":"1001",
    "addr:postcode":"27712",
    "addr:street":"Mason Rd",
    "iso:country":"US",
    "sg:address":"1001 Mason Rd",
    "sg:city":"Durham",
    "sg:classifiers":[
        {
            "category":"Organizations",
            "subcategory":"Religious Organization",
            "type":"Services"
        }
    ],
    "sg:phone":"+1 919 479 1001",
    "sg:postcode":"27712",
    "sg:province":"NC",
    "sg:tags":[
        "church"
    ],
    "sg:website":"www.stmatthewcc.org",
    "wof:name":"St Matthew Catholic Church",
    "wof:placetype":"venue"
},
  "geometry": {"coordinates":[-78.92272199999999,36.126464],"type":"Point"}
}