{
  "type": "Feature",
  "properties": {
    "iso:country":"US",
    "sg:address":"216 Dalewood Ave",
    "sg:city":"Kannapolis",
    "sg:classifiers":[
        {
            "category":"Professional",
            "type":"Services"
        }
    ],
    "sg:phone":"+1   ",
    "sg:postcode":"28083",
    "sg:province":"NC",
    "wof:name":"Errands Unlimited",
    "wof:placetype":"venue"
},
  "geometry": {"coordinates":[-80.589467,35.492551],"type":"Point"}
}