{
  "type": "Feature",
  "properties": {
    "addr:full":"6641 Tealbriar Dr Raleigh NC 27615",
    "addr:housenumber":"6641",
    "addr:postcode":"27615",
    "addr:street":"Tealbriar Dr",
    "iso:country":"US",
    "sg:address":"6641 Tealbriar Dr",
    "sg:city":"Raleigh",
    "sg:classifiers":[
        {
            "category":"Professional",
            "subcategory":"Research",
            "type":"Services"
        }
    ],
    "sg:phone":"+1   ",
    "sg:postcode":"27615",
    "sg:province":"NC",
    "sg:tags":[
        "commercial",
        "physical"
    ],
    "wof:name":"Ausam Biotechnologies",
    "wof:placetype":"venue"
},
  "geometry": {"coordinates":[-78.61033,35.870133],"type":"Point"}
}