{
  "type": "Feature",
  "properties": {
    "addr:full":"630 East St Pittsboro NC 27312",
    "addr:housenumber":"630",
    "addr:postcode":"27312",
    "addr:street":"East St",
    "iso:country":"US",
    "sg:address":"630 East St",
    "sg:city":"Pittsboro",
    "sg:classifiers":[
        {
            "category":"Professional",
            "subcategory":"Accounting & Tax Preparation",
            "type":"Services"
        }
    ],
    "sg:phone":"+1 919 542 5025",
    "sg:postcode":"27312",
    "sg:province":"NC",
    "sg:tags":[
        "return",
        "filing"
    ],
    "wof:name":"Jackson Hewitt Tax Svc",
    "wof:placetype":"venue"
},
  "geometry": {"coordinates":[-79.166828,35.719912],"type":"Point"}
}