{
  "type": "Feature",
  "properties": {
    "iso:country":"US",
    "sg:address":"223 Jenkins St",
    "sg:city":"Sanford",
    "sg:classifiers":[
        {
            "category":"Retail",
            "subcategory":"Repair Shop",
            "type":"Services"
        }
    ],
    "sg:phone":"+1 919 776 3888",
    "sg:postcode":"27330",
    "sg:province":"NC",
    "sg:tags":[
        "armature",
        "rewinding",
        "merchandise"
    ],
    "wof:name":"Central Electric Motor Repair",
    "wof:placetype":"venue"
},
  "geometry": {"coordinates":[-79.174746,35.479972],"type":"Point"}
}