{
  "type": "Feature",
  "properties": {
    "iso:country":"US",
    "sg:address":"512 River Rd",
    "sg:city":"Washington",
    "sg:classifiers":[
        {
            "category":"Shopping",
            "subcategory":"Gifts & Souvenirs",
            "type":"Retail Goods"
        }
    ],
    "sg:phone":"+1 252 946 9484",
    "sg:postcode":"27889",
    "sg:province":"NC",
    "sg:tags":[
        "shop"
    ],
    "wof:name":"House Next Door",
    "wof:placetype":"venue"
},
  "geometry": {"coordinates":[-77.027422,35.534404],"type":"Point"}
}