{
  "type": "Feature",
  "properties": {
    "addr:full":"3650 Patterson Ave Winston Salem NC 27105",
    "addr:housenumber":"3650",
    "addr:postcode":"27105",
    "addr:street":"Patterson Ave",
    "iso:country":"US",
    "sg:address":"3650 Patterson Ave",
    "sg:city":"Winston Salem",
    "sg:classifiers":[
        {
            "category":"Wholesale",
            "subcategory":"Machinery & Supplies",
            "type":"Manufacturing & Wholesale Goods"
        }
    ],
    "sg:phone":"+1 336 767 9355",
    "sg:postcode":"27105",
    "sg:province":"NC",
    "sg:tags":[
        "tool"
    ],
    "sg:website":"www.fastenal.com",
    "wof:name":"Fastenal Co",
    "wof:placetype":"venue"
},
  "geometry": {"coordinates":[-80.243956,36.14137],"type":"Point"}
}