{
  "type": "Feature",
  "properties": {
    "iso:country":"US",
    "sg:address":"11925 Sam Roper Dr",
    "sg:city":"Charlotte",
    "sg:classifiers":[
        {
            "category":"Professional",
            "subcategory":"Management & Consulting",
            "type":"Services"
        }
    ],
    "sg:phone":"+1 704 947 4945",
    "sg:postcode":"28269",
    "sg:province":"NC",
    "sg:tags":[
        "marketing",
        "consultant"
    ],
    "wof:name":"Box Seat Inc",
    "wof:placetype":"venue"
},
  "geometry": {"coordinates":[-80.834957,35.369513],"type":"Point"}
}