{
  "type": "Feature",
  "properties": {
    "addr:full":"20 W 2nd St Newton NC 28658",
    "addr:housenumber":"20",
    "addr:postcode":"28658",
    "addr:street":"W 2Nd St",
    "iso:country":"US",
    "sg:address":"20 W 2nd St",
    "sg:city":"Newton",
    "sg:classifiers":[
        {
            "category":"Insurance",
            "subcategory":"Insurance Agent",
            "type":"Services"
        }
    ],
    "sg:phone":"+1 828 464 2743",
    "sg:postcode":"28658",
    "sg:province":"NC",
    "wof:name":"Hunsucker-Cooke Insurance",
    "wof:placetype":"venue"
},
  "geometry": {"coordinates":[-81.222782,35.664666],"type":"Point"}
}