{
  "type": "Feature",
  "properties": {
    "addr:full":"913 S Main St Burlington NC 27215",
    "addr:housenumber":"913",
    "addr:postcode":"27215",
    "addr:street":"S Main St",
    "iso:country":"US",
    "sg:address":"913 S Main St",
    "sg:city":"Burlington",
    "sg:classifiers":[
        {
            "category":"Wholesale",
            "subcategory":"Computers",
            "type":"Manufacturing & Wholesale Goods"
        }
    ],
    "sg:phone":"+1 336 228 0486",
    "sg:postcode":"27215",
    "sg:province":"NC",
    "sg:tags":[
        "equipment",
        "processing",
        "datum"
    ],
    "wof:name":"IBM Corp",
    "wof:placetype":"venue"
},
  "geometry": {"coordinates":[-79.44391299999999,36.089446],"type":"Point"}
}