{
  "type": "Feature",
  "properties": {
    "addr:full":"300 Liberty Hill Rd Vilas NC 28692",
    "addr:housenumber":"300",
    "addr:postcode":"28692",
    "addr:street":"Liberty Hill Rd",
    "iso:country":"US",
    "sg:address":"300 Liberty Hill Rd",
    "sg:city":"Vilas",
    "sg:classifiers":[
        {
            "category":"Building & Trades",
            "subcategory":"Construction",
            "type":"Services"
        }
    ],
    "sg:phone":"+1 828 963 7231",
    "sg:postcode":"28692",
    "sg:province":"NC",
    "sg:tags":[
        "excavating",
        "contractor"
    ],
    "wof:name":"G & G Excavating & Contracting",
    "wof:placetype":"venue"
},
  "geometry": {"coordinates":[-81.73049899999999,36.209516],"type":"Point"}
}