{
  "type": "Feature",
  "properties": {
    "addr:full":"210 W Nc Highway 54 Durham NC 27713",
    "addr:housenumber":"210",
    "addr:postcode":"27713",
    "addr:street":"W Nc Highway 54",
    "iso:country":"US",
    "sg:address":"210 W Nc Highway 54",
    "sg:city":"Durham",
    "sg:classifiers":[
        {
            "category":"Restaurant",
            "type":"Food & Drink"
        }
    ],
    "sg:menulink":"http://www.allmenus.com/nc/triangle/103761-ruby-tuesdays/menu/",
    "sg:phone":"+1 919 405 4118",
    "sg:postcode":"27713",
    "sg:province":"NC",
    "sg:tags":[
        "burger",
        "american"
    ],
    "wof:name":"Ruby Tuesdays",
    "wof:placetype":"venue"
},
  "geometry": {"coordinates":[-78.938282,35.911027],"type":"Point"}
}