{
  "type": "Feature",
  "properties": {
    "iso:country":"US",
    "sg:address":"2490 Wendell Blvd",
    "sg:city":"Wendell",
    "sg:classifiers":[
        {
            "category":"Freight",
            "type":"Transportation"
        }
    ],
    "sg:phone":"+1 919 365 3799",
    "sg:postcode":"27591",
    "sg:province":"NC",
    "sg:tags":[
        "arrangement"
    ],
    "wof:name":"Fast Track Expedite",
    "wof:placetype":"venue"
},
  "geometry": {"coordinates":[-78.38949,35.799873],"type":"Point"}
}