{
  "type": "Feature",
  "properties": {
    "addr:full":"2208 Baywater Dr Fayetteville NC 28304",
    "addr:housenumber":"2208",
    "addr:postcode":"28304",
    "addr:street":"Baywater Dr",
    "iso:country":"US",
    "sg:address":"2208 Baywater Dr",
    "sg:city":"Fayetteville",
    "sg:classifiers":[
        {
            "category":"Professional",
            "type":"Services"
        },
        {
            "category":"Building & Trades",
            "subcategory":"Construction",
            "type":"Services"
        }
    ],
    "sg:phone":"+1 910 423 6500",
    "sg:postcode":"28304",
    "sg:province":"NC",
    "sg:tags":[
        "handyman"
    ],
    "wof:name":"Lankford's All Around Svc",
    "wof:placetype":"venue"
},
  "geometry": {"coordinates":[-78.999872,35.008085],"type":"Point"}
}