{
  "type": "Feature",
  "properties": {
    "iso:country":"US",
    "sg:address":"4591 Faith Ln",
    "sg:city":"Hudson",
    "sg:classifiers":[
        {
            "category":"Education",
            "subcategory":"Dance Studio",
            "type":"Public Place"
        }
    ],
    "sg:phone":"+1 828 728 3210",
    "sg:postcode":"28638",
    "sg:province":"NC",
    "sg:tags":[
        "instruction",
        "dancing"
    ],
    "wof:name":"Sherry's Dance Studio",
    "wof:placetype":"venue"
},
  "geometry": {"coordinates":[-81.515176,35.814467],"type":"Point"}
}