{
  "type": "Feature",
  "properties": {
    "iso:country":"US",
    "sg:address":"834 Hardee Rd",
    "sg:city":"Kinston",
    "sg:classifiers":[
        {
            "category":"Shopping",
            "subcategory":"Department Store",
            "type":"Retail Goods"
        }
    ],
    "sg:phone":"+1 252 527 7181",
    "sg:postcode":"28504",
    "sg:province":"NC",
    "wof:name":"Belk",
    "wof:placetype":"venue"
},
  "geometry": {"coordinates":[-77.60684500000001,35.272471],"type":"Point"}
}