{
  "type": "Feature",
  "properties": {
    "iso:country":"US",
    "sg:address":"8340 Bandford Way Ste #107",
    "sg:city":"Raleigh",
    "sg:classifiers":[
        {
            "category":"Shopping",
            "subcategory":"Beauty & Cosmetics",
            "type":"Retail Goods"
        },
        {
            "category":"Personal",
            "subcategory":"Hair Removal",
            "type":"Services"
        },
        {
            "category":"Personal",
            "subcategory":"Day Spa",
            "type":"Services"
        },
        {
            "category":"Personal",
            "subcategory":"Tanning Parlor",
            "type":"Services"
        },
        {
            "category":"Personal",
            "subcategory":"Skin Care",
            "type":"Services"
        },
        {
            "category":"Personal",
            "subcategory":"Beauty Salon",
            "type":"Services"
        }
    ],
    "sg:phone":"+1 919 518 9396",
    "sg:postcode":"27615",
    "sg:province":"NC",
    "sg:tags":[
        "perfume"
    ],
    "sg:website":"http://raleigh.citysearch.com/profile/external/41635471/raleigh_nc/skin_essence_a_day_spa.html?publisher=yellowpages&reference_id=1&placement=ypwebsitemip",
    "wof:name":"Skin Essence A Day Spa",
    "wof:placetype":"venue"
},
  "geometry": {"coordinates":[-78.678887,35.900829],"type":"Point"}
}