{
  "type": "Feature",
  "properties": {
    "addr:full":"5045 Hendersonville Rd Fletcher NC 28732",
    "addr:housenumber":"5045",
    "addr:postcode":"fletcher;28732",
    "addr:street":"Hendersonville Rd",
    "iso:country":"US",
    "sg:address":"5045 Hendersonville Rd",
    "sg:city":"Fletcher",
    "sg:classifiers":[
        {
            "category":"Professional",
            "type":"Services"
        }
    ],
    "sg:phone":"+1 828 687 7966",
    "sg:postcode":"28732",
    "sg:province":"NC",
    "wof:name":"Superior Walls North Carolina",
    "wof:placetype":"venue"
},
  "geometry": {"coordinates":[-82.509064,35.413419],"type":"Point"}
}