{
  "type": "Feature",
  "properties": {
    "addr:full":"2876 State Hwy 53 Burgaw NC 28425",
    "addr:housenumber":"2876",
    "addr:postcode":"28425",
    "addr:street":"State Hwy 53",
    "iso:country":"US",
    "sg:address":"2876 State Hwy 53",
    "sg:city":"Burgaw",
    "sg:phone":"+1 910 259 4683",
    "sg:postcode":"28425",
    "sg:province":"NC",
    "sg:tags":[
        "farm"
    ],
    "wof:name":"Thomas Produce Farm",
    "wof:placetype":"venue"
},
  "geometry": {"coordinates":[-77.969584,34.539209],"type":"Point"}
}