{
  "type": "Feature",
  "properties": {
    "iso:country":"US",
    "sg:address":"306 W High Ave",
    "sg:city":"High Point",
    "sg:classifiers":[
        {
            "category":"Wholesale",
            "subcategory":"Hardware",
            "type":"Manufacturing & Wholesale Goods"
        }
    ],
    "sg:phone":"+1 336 841 3109",
    "sg:postcode":"27260",
    "sg:province":"NC",
    "sg:tags":[
        "equipment",
        "refrigeration",
        "conditioning",
        "air"
    ],
    "wof:name":"C C Dickson Co",
    "wof:placetype":"venue"
},
  "geometry": {"coordinates":[-80.009109,35.955724],"type":"Point"}
}