{
  "type": "Feature",
  "properties": {
    "iso:country":"US",
    "sg:address":"1645 E Arlington Blvd",
    "sg:city":"Greenville",
    "sg:classifiers":[
        {
            "category":"Banks & Credit Unions",
            "subcategory":"Financial Services",
            "type":"Services"
        }
    ],
    "sg:phone":"+1 252 353 5730",
    "sg:postcode":"27858",
    "sg:province":"NC",
    "sg:tags":[
        "trust",
        "management"
    ],
    "wof:name":"Select Bank & Trust Proposed",
    "wof:placetype":"venue"
},
  "geometry": {"coordinates":[-77.358467,35.571105],"type":"Point"}
}