{
  "type": "Feature",
  "properties": {
    "addr:full":"10647 US Hwy 17 Vanceboro NC 28586",
    "addr:housenumber":"10647",
    "addr:postcode":"28586",
    "addr:street":"Us Hwy 17",
    "iso:country":"US",
    "sg:address":"10647 US Hwy 17",
    "sg:city":"Vanceboro",
    "sg:classifiers":[
        {
            "category":"Manufacturing",
            "subcategory":"Tools & Machinery",
            "type":"Manufacturing & Wholesale Goods"
        }
    ],
    "sg:phone":"+1 252 974 0900",
    "sg:postcode":"28586",
    "sg:province":"NC",
    "sg:tags":[
        "industrial",
        "electrical",
        "apparatus",
        "mfg"
    ],
    "wof:name":"ISA of North Carolina",
    "wof:placetype":"venue"
},
  "geometry": {"coordinates":[-77.15043,35.363252],"type":"Point"}
}