{
  "type": "Feature",
  "properties": {
    "iso:country":"US",
    "sg:address":"225 Pickler Rd",
    "sg:city":"Salisbury",
    "sg:classifiers":[
        {
            "category":"Professional",
            "subcategory":"Business Services",
            "type":"Services"
        }
    ],
    "sg:phone":"+1 704 638 9335",
    "sg:postcode":"28144",
    "sg:province":"NC",
    "sg:tags":[
        "pipeline",
        "testing",
        "related"
    ],
    "wof:name":"Jan X-Ray Services Inc",
    "wof:placetype":"venue"
},
  "geometry": {"coordinates":[-80.473084,35.751513],"type":"Point"}
}