{
  "type": "Feature",
  "properties": {
    "iso:country":"US",
    "sg:address":"1609 S Horner Blvd",
    "sg:city":"Sanford",
    "sg:classifiers":[
        {
            "category":"Organizations",
            "subcategory":"Community Association",
            "type":"Services"
        }
    ],
    "sg:phone":"+1 919 777 0522",
    "sg:postcode":"27330",
    "sg:province":"NC",
    "sg:tags":[
        "club"
    ],
    "wof:name":"Sparks Mexican Cantina",
    "wof:placetype":"venue"
},
  "geometry": {"coordinates":[-79.161024,35.467174],"type":"Point"}
}