{
  "type": "Feature",
  "properties": {
    "addr:full":"52 Biltmore Ave Asheville NC 28801",
    "addr:housenumber":"52",
    "addr:postcode":"28801",
    "addr:street":"Biltmore Ave",
    "iso:country":"US",
    "sg:address":"52 Biltmore Ave",
    "sg:city":"Asheville",
    "sg:classifiers":[
        {
            "category":"Building & Trades",
            "subcategory":"Construction",
            "type":"Services"
        }
    ],
    "sg:phone":"+1 828 257 2236",
    "sg:postcode":"28801",
    "sg:province":"NC",
    "sg:tags":[
        "general",
        "contractor"
    ],
    "wof:name":"KBC Construction",
    "wof:placetype":"venue"
},
  "geometry": {"coordinates":[-82.551345,35.593756],"type":"Point"}
}