{
  "type": "Feature",
  "properties": {
    "addr:full":"2019 Downing St Greensboro NC 27410",
    "addr:housenumber":"2019",
    "addr:postcode":"27410",
    "addr:street":"Downing St",
    "iso:country":"US",
    "sg:address":"2019 Downing St",
    "sg:city":"Greensboro",
    "sg:classifiers":[
        {
            "category":"Shopping",
            "type":"Retail Goods"
        }
    ],
    "sg:phone":"+1 336 286 7049",
    "sg:postcode":"27410",
    "sg:province":"NC",
    "sg:tags":[
        "merchandise"
    ],
    "wof:name":"Commhawk Services",
    "wof:placetype":"venue"
},
  "geometry": {"coordinates":[-79.850346,36.124752],"type":"Point"}
}