{
  "type": "Feature",
  "properties": {
    "addr:full":"369 Wafford Cir Lexington NC 27292",
    "addr:housenumber":"369",
    "addr:postcode":"27292",
    "addr:street":"Wafford Cir",
    "iso:country":"US",
    "sg:address":"369 Wafford Cir",
    "sg:city":"Lexington",
    "sg:classifiers":[
        {
            "category":"Wholesale",
            "subcategory":"Vending Machines",
            "type":"Manufacturing & Wholesale Goods"
        }
    ],
    "sg:phone":"+1 336 798 2400",
    "sg:postcode":"27292",
    "sg:province":"NC",
    "sg:tags":[
        "food",
        "broker"
    ],
    "wof:name":"Quality Plus Vending Inc",
    "wof:placetype":"venue"
},
  "geometry": {"coordinates":[-80.26298800000001,35.687025],"type":"Point"}
}