{
  "type": "Feature",
  "properties": {
    "iso:country":"US",
    "sg:address":"802 W Center St",
    "sg:city":"Lexington",
    "sg:classifiers":[
        {
            "category":"Manufacturing",
            "subcategory":"Furniture",
            "type":"Manufacturing & Wholesale Goods"
        }
    ],
    "sg:phone":"+1 336 248 5961",
    "sg:postcode":"27292",
    "sg:province":"NC",
    "sg:website":"www.stanleyfurniture.com",
    "wof:name":"Stanley Furniture Co",
    "wof:placetype":"venue"
},
  "geometry": {"coordinates":[-80.26509299999999,35.831696],"type":"Point"}
}