{
  "type": "Feature",
  "properties": {
    "addr:full":"605 German St Fayetteville NC 28301",
    "addr:housenumber":"605",
    "addr:postcode":"28301",
    "addr:street":"German St",
    "iso:country":"US",
    "sg:address":"605 German St",
    "sg:city":"Fayetteville",
    "sg:classifiers":[
        {
            "category":"Building & Trades",
            "subcategory":"Construction",
            "type":"Services"
        }
    ],
    "sg:phone":"+1 910 323 5000",
    "sg:postcode":"28301",
    "sg:province":"NC",
    "sg:tags":[
        "home",
        "builder"
    ],
    "wof:name":"Carolina Model Home Corp",
    "wof:placetype":"venue"
},
  "geometry": {"coordinates":[-78.88920400000001,35.0529],"type":"Point"}
}