{
  "type": "Feature",
  "properties": {
    "addr:full":"1809 Gum Branch Rd Charlotte NC 28214",
    "addr:housenumber":"1809",
    "addr:postcode":"28214",
    "addr:street":"Gum Branch Rd",
    "iso:country":"US",
    "sg:address":"1809 Gum Branch Rd",
    "sg:city":"Charlotte",
    "sg:classifiers":[
        {
            "category":"Building & Trades",
            "subcategory":"Cleaning & Sanitation",
            "type":"Services"
        }
    ],
    "sg:phone":"+1   ",
    "sg:postcode":"28214",
    "sg:province":"NC",
    "sg:tags":[
        "maintenance"
    ],
    "wof:name":"Morningside Cleaning Services",
    "wof:placetype":"venue"
},
  "geometry": {"coordinates":[-80.957989,35.291662],"type":"Point"}
}