{
  "type": "Feature",
  "properties": {
    "addr:full":"308 E Worthington Ave Charlotte NC 28203",
    "addr:housenumber":"308",
    "addr:postcode":"28203",
    "addr:street":"E Worthington Ave",
    "iso:country":"US",
    "sg:address":"308 E Worthington Ave",
    "sg:city":"Charlotte",
    "sg:classifiers":[
        {
            "category":"Wholesale",
            "subcategory":"Durable Goods & Equipment",
            "type":"Manufacturing & Wholesale Goods"
        }
    ],
    "sg:phone":"+1 704 376 7387",
    "sg:postcode":"28203",
    "sg:province":"NC",
    "wof:name":"W L Brass Restoration",
    "wof:placetype":"venue"
},
  "geometry": {"coordinates":[-80.85660799999999,35.20906],"type":"Point"}
}