{
  "type": "Feature",
  "properties": {
    "iso:country":"US",
    "sg:address":"4523 Hope Valley Rd",
    "sg:city":"Durham",
    "sg:classifiers":[
        {
            "category":"Real Estate",
            "subcategory":"Real Estate Agent",
            "type":"Services"
        }
    ],
    "sg:phone":"+1 919 403 0055",
    "sg:postcode":"27707",
    "sg:province":"NC",
    "sg:tags":[
        "management"
    ],
    "sg:website":"www.springarborliving.com",
    "wof:name":"Spring Arbor Of Durham",
    "wof:placetype":"venue"
},
  "geometry": {"coordinates":[-78.95415,35.926367],"type":"Point"}
}