{
  "type": "Feature",
  "properties": {
    "addr:full":"3601 Dr Pickett Rd Burlington NC 27215",
    "addr:housenumber":"3601",
    "addr:postcode":"27215",
    "addr:street":"Dr Pickett Rd",
    "iso:country":"US",
    "sg:address":"3601 Dr Pickett Rd",
    "sg:city":"Burlington",
    "sg:classifiers":[
        {
            "category":"Real Estate",
            "subcategory":"Real Estate Agent",
            "type":"Services"
        }
    ],
    "sg:phone":"+1 336 436 0030",
    "sg:postcode":"27215",
    "sg:province":"NC",
    "wof:name":"Piedmont Center Properties",
    "wof:placetype":"venue"
},
  "geometry": {"coordinates":[-79.463032,36.011786],"type":"Point"}
}