{
  "type": "Feature",
  "properties": {
    "addr:full":"4816 Worth Pl Charlotte NC 28216",
    "addr:housenumber":"4816",
    "addr:postcode":"28216",
    "addr:street":"Worth Pl",
    "iso:country":"US",
    "sg:address":"4816 Worth Pl",
    "sg:city":"Charlotte",
    "sg:classifiers":[
        {
            "category":"Retail",
            "subcategory":"Repair Shop",
            "type":"Services"
        }
    ],
    "sg:phone":"+1 704 399 0446",
    "sg:postcode":"28216",
    "sg:province":"NC",
    "wof:name":"Ingersoll-Dresser Pump Company",
    "wof:placetype":"venue"
},
  "geometry": {"coordinates":[-80.882013,35.275252],"type":"Point"}
}