{
  "type": "Feature",
  "properties": {
    "iso:country":"US",
    "sg:address":"3006 New Bern Ave",
    "sg:city":"Raleigh",
    "sg:classifiers":[
        {
            "category":"Wholesale",
            "subcategory":"Medical Equipment & Supplies",
            "type":"Manufacturing & Wholesale Goods"
        },
        {
            "category":"Social Services",
            "type":"Services"
        },
        {
            "category":"Shopping",
            "subcategory":"Pharmacy",
            "type":"Retail Goods"
        }
    ],
    "sg:phone":"+1 919 231 8315",
    "sg:postcode":"27610",
    "sg:province":"NC",
    "sg:tags":[
        "product",
        "developmentally",
        "disabled",
        "health",
        "need",
        "home",
        "special",
        "care"
    ],
    "sg:website":"http://www.hilltophome.org",
    "wof:name":"Hilltop Home",
    "wof:placetype":"venue"
},
  "geometry": {"coordinates":[-78.588702,35.786496],"type":"Point"}
}