{
  "type": "Feature",
  "properties": {
    "addr:full":"923 Ramsey St Fayetteville NC 28301",
    "addr:housenumber":"923",
    "addr:postcode":"28301",
    "addr:street":"Ramsey St",
    "iso:country":"US",
    "sg:address":"923 Ramsey St",
    "sg:city":"Fayetteville",
    "sg:classifiers":[
        {
            "category":"Building & Trades",
            "subcategory":"Plumbing",
            "type":"Services"
        }
    ],
    "sg:phone":"+1 910 323 0095",
    "sg:postcode":"28301",
    "sg:province":"NC",
    "sg:tags":[
        "contractor"
    ],
    "wof:name":"Grooms Heating & AC Inc",
    "wof:placetype":"venue"
},
  "geometry": {"coordinates":[-78.879372,35.068527],"type":"Point"}
}