{
  "type": "Feature",
  "properties": {
    "iso:country":"US",
    "sg:address":"17 Moore St",
    "sg:city":"Andrews",
    "sg:classifiers":[
        {
            "category":"Health Services",
            "subcategory":"Nursing And Care Facility",
            "type":"Services"
        },
        {
            "category":"Social Services",
            "type":"Services"
        }
    ],
    "sg:phone":"+1 828 321 1317",
    "sg:postcode":"28901",
    "sg:province":"NC",
    "sg:tags":[
        "adult"
    ],
    "wof:name":"Oak Park Guest Home Inc",
    "wof:placetype":"venue"
},
  "geometry": {"coordinates":[-83.827814,35.196623],"type":"Point"}
}