{
  "type": "Feature",
  "properties": {
    "iso:country":"US",
    "sg:address":"454 Goodwin Mill Rd",
    "sg:city":"Hertford",
    "sg:classifiers":[
        {
            "category":"Freight",
            "type":"Transportation"
        }
    ],
    "sg:phone":"+1 252 297 2165",
    "sg:postcode":"27944",
    "sg:province":"NC",
    "sg:tags":[
        "operator",
        "local",
        "trucking"
    ],
    "wof:name":"B&L Hauling Inc",
    "wof:placetype":"venue"
},
  "geometry": {"coordinates":[-76.549187,36.256842],"type":"Point"}
}