{
  "type": "Feature",
  "properties": {
    "iso:country":"US",
    "sg:address":"5705 Carnegie Blvd",
    "sg:city":"Charlotte",
    "sg:classifiers":[
        {
            "category":"Professional",
            "type":"Services"
        }
    ],
    "sg:phone":"+1 704 553 1331",
    "sg:postcode":"28209",
    "sg:province":"NC",
    "sg:tags":[
        "establishment"
    ],
    "wof:name":"Shelco",
    "wof:placetype":"venue"
},
  "geometry": {"coordinates":[-80.83905900000001,35.153635],"type":"Point"}
}