{
  "type": "Feature",
  "properties": {
    "addr:full":"706 7th Ave E Hendersonville NC 28792",
    "addr:housenumber":"706",
    "addr:postcode":"28792",
    "addr:street":"7Th Ave E",
    "iso:country":"US",
    "sg:address":"706 7th Ave E",
    "sg:city":"Hendersonville",
    "sg:classifiers":[
        {
            "category":"Autos & Motor Vehicles",
            "subcategory":"Auto Supplies",
            "type":"Retail Goods"
        }
    ],
    "sg:phone":"+1 828 692 8244",
    "sg:postcode":"28792",
    "sg:province":"NC",
    "sg:tags":[
        "tire"
    ],
    "sg:website":"www.citytireservice.com",
    "wof:name":"City Tire Svc",
    "wof:placetype":"venue"
},
  "geometry": {"coordinates":[-82.454598,35.323376],"type":"Point"}
}