{
  "type": "Feature",
  "properties": {
    "addr:full":"405 Jones Ferry Rd Carrboro NC 27510",
    "addr:housenumber":"405",
    "addr:postcode":"27510",
    "addr:street":"Jones Ferry Rd",
    "iso:country":"US",
    "sg:address":"405 Jones Ferry Rd",
    "sg:city":"Carrboro",
    "sg:classifiers":[
        {
            "category":"Building & Trades",
            "subcategory":"Construction",
            "type":"Services"
        }
    ],
    "sg:phone":"+1 919 967 2241",
    "sg:postcode":"27510",
    "sg:province":"NC",
    "sg:tags":[
        "contractor",
        "paving",
        "grading"
    ],
    "sg:website":"http://www.realpagessites.com/mellottcontractors",
    "wof:name":"Mellott Contractors & Supply",
    "wof:placetype":"venue"
},
  "geometry": {"coordinates":[-79.08005300000001,35.908048],"type":"Point"}
}