{
  "type": "Feature",
  "properties": {
    "iso:country":"US",
    "sg:address":"1751 Main St NW",
    "sg:city":"Lenoir",
    "sg:classifiers":[
        {
            "category":"Manufacturing",
            "subcategory":"Tools & Machinery",
            "type":"Manufacturing & Wholesale Goods"
        }
    ],
    "sg:phone":"+1 828 754 4184",
    "sg:postcode":"28645",
    "sg:province":"NC",
    "sg:tags":[
        "machine",
        "shop",
        "industrial",
        "mfg"
    ],
    "wof:name":"Annas Machine Shop Inc",
    "wof:placetype":"venue"
},
  "geometry": {"coordinates":[-81.54311300000001,35.93427],"type":"Point"}
}