{
  "type": "Feature",
  "properties": {
    "iso:country":"US",
    "sg:address":"212 Toms Dr",
    "sg:city":"Hendersonville",
    "sg:classifiers":[
        {
            "category":"Manufacturing",
            "subcategory":"Metals",
            "type":"Manufacturing & Wholesale Goods"
        }
    ],
    "sg:phone":"+1 828 696 9077",
    "sg:postcode":"28739",
    "sg:province":"NC",
    "sg:tags":[
        "steel",
        "processing"
    ],
    "wof:name":"Delta Steel",
    "wof:placetype":"venue"
},
  "geometry": {"coordinates":[-82.512294,35.31788],"type":"Point"}
}