{
  "type": "Feature",
  "properties": {
    "iso:country":"US",
    "sg:address":"342 Church St N",
    "sg:city":"Concord",
    "sg:classifiers":[
        {
            "category":"Personal",
            "subcategory":"Tattoo Parlor",
            "type":"Services"
        }
    ],
    "sg:phone":"+1 704 788 4612",
    "sg:postcode":"28025",
    "sg:province":"NC",
    "sg:tags":[
        "tattooing"
    ],
    "wof:name":"Make-Up Enhancements By Marcia",
    "wof:placetype":"venue"
},
  "geometry": {"coordinates":[-80.589839,35.420051],"type":"Point"}
}