{
  "type": "Feature",
  "properties": {
    "addr:full":"954 N Davidson St Charlotte NC 28206",
    "addr:housenumber":"954",
    "addr:postcode":"28206",
    "addr:street":"N Davidson St",
    "iso:country":"US",
    "sg:address":"954 N Davidson St",
    "sg:city":"Charlotte",
    "sg:classifiers":[
        {
            "category":"Building & Trades",
            "subcategory":"Construction",
            "type":"Services"
        }
    ],
    "sg:phone":"+1 704 334 1691",
    "sg:postcode":"28206",
    "sg:province":"NC",
    "sg:tags":[
        "roofing",
        "industrial",
        "contractors-commercial",
        "contractor"
    ],
    "wof:name":"Rike Roofing And Manufacturing Co",
    "wof:placetype":"venue"
},
  "geometry": {"coordinates":[-80.82762099999999,35.230301],"type":"Point"}
}