{
  "type": "Feature",
  "properties": {
    "iso:country":"US",
    "sg:address":"9418 Hathwyck Ct",
    "sg:city":"Matthews",
    "sg:classifiers":[
        {
            "category":"Health Services",
            "subcategory":"Doctor",
            "type":"Services"
        }
    ],
    "sg:phone":"+1   ",
    "sg:postcode":"28105",
    "sg:province":"NC",
    "wof:name":"Harry W Moczek DDS",
    "wof:placetype":"venue"
},
  "geometry": {"coordinates":[-80.743848,35.122284],"type":"Point"}
}