{
  "type": "Feature",
  "properties": {
    "addr:full":"114 SW Railroad St Enfield NC 27823",
    "addr:housenumber":"114",
    "addr:postcode":"27823",
    "addr:street":"Sw Railroad St",
    "iso:country":"US",
    "sg:address":"114 SW Railroad St",
    "sg:city":"Enfield",
    "sg:classifiers":[
        {
            "category":"Insurance",
            "subcategory":"Insurance Agent",
            "type":"Services"
        }
    ],
    "sg:phone":"+1 252 445 5101",
    "sg:postcode":"27823",
    "sg:province":"NC",
    "wof:name":"Halifax Mutual Insurance Co",
    "wof:placetype":"venue"
},
  "geometry": {"coordinates":[-77.66703800000001,36.180349],"type":"Point"}
}