{
  "type": "Feature",
  "properties": {
    "iso:country":"US",
    "sg:address":"1871 Catherine Lake Rd",
    "sg:city":"Richlands",
    "sg:classifiers":[
        {
            "category":"Home & Garden",
            "subcategory":"Garden Supply",
            "type":"Retail Goods"
        }
    ],
    "sg:phone":"+1 910 324 8444",
    "sg:postcode":"28574",
    "sg:province":"NC",
    "sg:tags":[
        "nurseryman"
    ],
    "wof:name":"Onslow Nursery",
    "wof:placetype":"venue"
},
  "geometry": {"coordinates":[-77.54765500000001,34.819214],"type":"Point"}
}