{
  "type": "Feature",
  "properties": {
    "addr:full":"1500 Ramsey St Fayetteville NC 28301",
    "addr:housenumber":"1500",
    "addr:postcode":"28301",
    "addr:street":"Ramsey St",
    "iso:country":"US",
    "sg:address":"1500 Ramsey St",
    "sg:city":"Fayetteville",
    "sg:classifiers":[
        {
            "category":"Wholesale",
            "subcategory":"Electrical",
            "type":"Manufacturing & Wholesale Goods"
        }
    ],
    "sg:phone":"+1 910 483 0493",
    "sg:postcode":"28301",
    "sg:province":"NC",
    "sg:tags":[
        "equipment",
        "electric",
        "supply"
    ],
    "wof:name":"Butler's Electric Supply",
    "wof:placetype":"venue"
},
  "geometry": {"coordinates":[-78.881332,35.077241],"type":"Point"}
}