{
  "type": "Feature",
  "properties": {
    "iso:country":"US",
    "sg:address":"214 N Center St",
    "sg:city":"Statesville",
    "sg:classifiers":[
        {
            "category":"Home & Garden",
            "subcategory":"Carpets & Floor Coverings",
            "type":"Retail Goods"
        }
    ],
    "sg:phone":"+1 704 873 4329",
    "sg:postcode":"28677",
    "sg:province":"NC",
    "sg:tags":[
        "dealer",
        "rug"
    ],
    "sg:website":"www.gordonsfurniturestores.com",
    "wof:name":"Gordon's Rugs & Carpeting",
    "wof:placetype":"venue"
},
  "geometry": {"coordinates":[-80.89099,35.789721],"type":"Point"}
}