{
  "type": "Feature",
  "properties": {
    "iso:country":"US",
    "sg:address":"5185 Mercer Mill Rd",
    "sg:city":"Clarkton",
    "sg:classifiers":[
        {
            "category":"Professional",
            "type":"Services"
        }
    ],
    "sg:phone":"+1 910 645 4856",
    "sg:postcode":"28433",
    "sg:province":"NC",
    "sg:tags":[
        "establishment"
    ],
    "wof:name":"For The Cause Of The Christ",
    "wof:placetype":"venue"
},
  "geometry": {"coordinates":[-78.60134499999999,34.562802],"type":"Point"}
}