{
  "type": "Feature",
  "properties": {
    "iso:country":"US",
    "sg:address":"235 N Edgeworth St",
    "sg:city":"Greensboro",
    "sg:classifiers":[
        {
            "category":"Social Services",
            "type":"Services"
        }
    ],
    "sg:phone":"+1   ",
    "sg:postcode":"27401",
    "sg:province":"NC",
    "sg:tags":[
        "legal"
    ],
    "wof:name":"Chatham Counseling & Cons",
    "wof:placetype":"venue"
},
  "geometry": {"coordinates":[-79.79599899999999,36.075066],"type":"Point"}
}