{
  "type": "Feature",
  "properties": {
    "addr:full":"220 Barden St Princeton NC 27569",
    "addr:housenumber":"220",
    "addr:postcode":"27569",
    "addr:street":"Barden St",
    "iso:country":"US",
    "sg:address":"220 Barden St",
    "sg:city":"Princeton",
    "sg:classifiers":[
        {
            "category":"Organizations",
            "subcategory":"Religious Organization",
            "type":"Services"
        }
    ],
    "sg:phone":"+1 919 936 3241",
    "sg:postcode":"27569",
    "sg:province":"NC",
    "sg:tags":[
        "church"
    ],
    "wof:name":"Grace Baptist Church",
    "wof:placetype":"venue"
},
  "geometry": {"coordinates":[-78.162094,35.471557],"type":"Point"}
}