{
  "type": "Feature",
  "properties": {
    "addr:full":"136 Weatherbend Pittsboro NC 27312",
    "addr:housenumber":"136",
    "addr:postcode":"27312",
    "addr:street":"Weatherbend",
    "iso:country":"US",
    "sg:address":"136 Weatherbend",
    "sg:city":"Pittsboro",
    "sg:classifiers":[
        {
            "category":"Sports & Exercise",
            "subcategory":"Gym",
            "type":"Entertainment"
        }
    ],
    "sg:phone":"+1   ",
    "sg:postcode":"27312",
    "sg:province":"NC",
    "sg:tags":[
        "fitness",
        "physical",
        "facility"
    ],
    "wof:name":"Aerobics & Fitness",
    "wof:placetype":"venue"
},
  "geometry": {"coordinates":[-79.08442100000001,35.803757],"type":"Point"}
}