{
  "type": "Feature",
  "properties": {
    "iso:country":"US",
    "sg:address":"5618 Rehobeth Rd",
    "sg:city":"Waxhaw",
    "sg:classifiers":[
        {
            "category":"Building & Trades",
            "subcategory":"Cleaning & Sanitation",
            "type":"Services"
        }
    ],
    "sg:phone":"+1   ",
    "sg:postcode":"28173",
    "sg:province":"NC",
    "sg:tags":[
        "maintenance"
    ],
    "wof:name":"J M H Cleaning Services",
    "wof:placetype":"venue"
},
  "geometry": {"coordinates":[-80.761735,34.897908],"type":"Point"}
}