{
  "type": "Feature",
  "properties": {
    "iso:country":"US",
    "sg:address":"6920 Howey Bottoms Rd",
    "sg:city":"Indian Trail",
    "sg:classifiers":[
        {
            "category":"Sports & Exercise",
            "subcategory":"Golf",
            "type":"Entertainment"
        }
    ],
    "sg:phone":"+1 704 882 8282",
    "sg:postcode":"28079",
    "sg:province":"NC",
    "sg:tags":[
        "course"
    ],
    "wof:name":"Charlotte National Golf Club",
    "wof:placetype":"venue"
},
  "geometry": {"coordinates":[-80.58275,35.127231],"type":"Point"}
}