{
  "type": "Feature",
  "properties": {
    "addr:full":"1704 Pineview St Newton NC 28613",
    "addr:housenumber":"1704",
    "addr:postcode":"28613",
    "addr:street":"Pineview St",
    "iso:country":"US",
    "sg:address":"1704 Pineview St",
    "sg:city":"Newton",
    "sg:classifiers":[
        {
            "category":"Retail",
            "subcategory":"Auto Repair",
            "type":"Services"
        }
    ],
    "sg:phone":"+1   ",
    "sg:postcode":"28613",
    "sg:province":"NC",
    "sg:tags":[
        "automotive"
    ],
    "wof:name":"Precision Towing & Auto",
    "wof:placetype":"venue"
},
  "geometry": {"coordinates":[-81.192145,35.70083],"type":"Point"}
}