{
  "type": "Feature",
  "properties": {
    "addr:full":"220 Chandler Rd Durham NC 27703",
    "addr:housenumber":"220",
    "addr:postcode":"27703",
    "addr:street":"Chandler Rd",
    "iso:country":"US",
    "sg:address":"220 Chandler Rd",
    "sg:city":"Durham",
    "sg:classifiers":[
        {
            "category":"Organizations",
            "subcategory":"Community Association",
            "type":"Services"
        }
    ],
    "sg:phone":"+1 919 957 9517",
    "sg:postcode":"27703",
    "sg:province":"NC",
    "sg:tags":[
        "member",
        "only",
        "bar",
        "for"
    ],
    "wof:name":"Club 2000 Inc",
    "wof:placetype":"venue"
},
  "geometry": {"coordinates":[-78.83819200000001,35.991824],"type":"Point"}
}