{
  "type": "Feature",
  "properties": {
    "addr:full":"2196 US Hwy 401 Raeford NC 28376",
    "addr:housenumber":"2196",
    "addr:postcode":"28376",
    "addr:street":"Us Hwy 401",
    "iso:country":"US",
    "sg:address":"2196 US Hwy 401",
    "sg:city":"Raeford",
    "sg:classifiers":[
        {
            "category":"Food & Beverages",
            "subcategory":"Groceries & Convenience Stores",
            "type":"Retail Goods"
        }
    ],
    "sg:phone":"+1 910 904 1034",
    "sg:postcode":"28376",
    "sg:province":"NC",
    "sg:tags":[
        "grocer"
    ],
    "wof:name":"Short Stop Food Mart",
    "wof:placetype":"venue"
},
  "geometry": {"coordinates":[-79.22531600000001,34.996721],"type":"Point"}
}