{
  "type": "Feature",
  "properties": {
    "addr:full":"1104 N Main St Laurinburg NC 28352",
    "addr:housenumber":"1104",
    "addr:postcode":"28352",
    "addr:street":"N Main St",
    "iso:country":"US",
    "sg:address":"1104 N Main St",
    "sg:city":"Laurinburg",
    "sg:classifiers":[
        {
            "category":"Autos & Motor Vehicles",
            "subcategory":"Automobile Sales",
            "type":"Retail Goods"
        }
    ],
    "sg:phone":"+1 910 276 7250",
    "sg:postcode":"28352",
    "sg:province":"NC",
    "sg:tags":[
        "car",
        "dealer"
    ],
    "wof:name":"Scotland Motors Inc",
    "wof:placetype":"venue"
},
  "geometry": {"coordinates":[-79.45081,34.789551],"type":"Point"}
}