{
  "type": "Feature",
  "properties": {
    "addr:full":"1309 Micol Ln Kernersville NC 27284",
    "addr:housenumber":"1309",
    "addr:postcode":"27284",
    "addr:street":"Micol Ln",
    "iso:country":"US",
    "sg:address":"1309 Micol Ln",
    "sg:city":"Kernersville",
    "sg:classifiers":[
        {
            "category":"Building & Trades",
            "subcategory":"Construction",
            "type":"Services"
        }
    ],
    "sg:phone":"+1 336 993 7833",
    "sg:postcode":"27284",
    "sg:province":"NC",
    "sg:tags":[
        "residential"
    ],
    "wof:name":"Clubb Building Co LLC",
    "wof:placetype":"venue"
},
  "geometry": {"coordinates":[-80.086608,36.094357],"type":"Point"}
}