{
  "type": "Feature",
  "properties": {
    "addr:full":"43 Dixie Way Canton NC 28716",
    "addr:housenumber":"43",
    "addr:postcode":"28716",
    "addr:street":"Dixie Way",
    "iso:country":"US",
    "sg:address":"43 Dixie Way",
    "sg:city":"Canton",
    "sg:classifiers":[
        {
            "category":"Communications",
            "subcategory":"Film & Video Production",
            "type":"Services"
        },
        {
            "category":"Professional",
            "subcategory":"Business Services",
            "type":"Services"
        }
    ],
    "sg:phone":"+1 828 235 1817",
    "sg:postcode":"28716",
    "sg:province":"NC",
    "sg:tags":[
        "motion",
        "recording",
        "studio"
    ],
    "wof:name":"Chris-Mar Studios",
    "wof:placetype":"venue"
},
  "geometry": {"coordinates":[-82.85435,35.538728],"type":"Point"}
}