{
  "type": "Feature",
  "properties": {
    "addr:full":"1360 Fisher Ferry Rd Thomasville NC 27360",
    "addr:housenumber":"1360",
    "addr:postcode":"27360",
    "addr:street":"Fisher Ferry Rd",
    "iso:country":"US",
    "sg:address":"1360 Fisher Ferry Rd",
    "sg:city":"Thomasville",
    "sg:classifiers":[
        {
            "category":"Organizations",
            "subcategory":"Religious Organization",
            "type":"Services"
        }
    ],
    "sg:phone":"+1 336 475 7380",
    "sg:postcode":"27360",
    "sg:province":"NC",
    "sg:tags":[
        "church"
    ],
    "wof:name":"East Davidson Baptist Church",
    "wof:placetype":"venue"
},
  "geometry": {"coordinates":[-80.08928,35.853933],"type":"Point"}
}