{
  "type": "Feature",
  "properties": {
    "addr:full":"11216 Arthur Auten Rd Huntersville NC 28078",
    "addr:housenumber":"11216",
    "addr:postcode":"28078",
    "addr:street":"Arthur Auten Rd",
    "iso:country":"US",
    "sg:address":"11216 Arthur Auten Rd",
    "sg:city":"Huntersville",
    "sg:classifiers":[
        {
            "category":"Manufacturing",
            "subcategory":"Tools & Machinery",
            "type":"Manufacturing & Wholesale Goods"
        }
    ],
    "sg:phone":"+1 704 875 8424",
    "sg:postcode":"28078",
    "sg:province":"NC",
    "sg:tags":[
        "machine",
        "folding"
    ],
    "wof:name":"Brewer Co Inc",
    "wof:placetype":"venue"
},
  "geometry": {"coordinates":[-80.938076,35.368299],"type":"Point"}
}