{
  "type": "Feature",
  "properties": {
    "iso:country":"US",
    "sg:address":"709 Halls Creek Rd",
    "sg:city":"Elizabeth City",
    "sg:classifiers":[
        {
            "category":"Building & Trades",
            "subcategory":"Construction",
            "type":"Services"
        }
    ],
    "sg:phone":"+1 252 264 2478",
    "sg:postcode":"27909",
    "sg:province":"NC",
    "wof:name":"Dg Ferrell Electrical Con",
    "wof:placetype":"venue"
},
  "geometry": {"coordinates":[-76.305976,36.237606],"type":"Point"}
}