{
  "type": "Feature",
  "properties": {
    "iso:country":"US",
    "sg:address":"302 E Pettigrew St",
    "sg:city":"Durham",
    "sg:classifiers":[
        {
            "category":"Insurance",
            "subcategory":"Insurance Agent",
            "type":"Services"
        }
    ],
    "sg:phone":"+1 919 530 8589",
    "sg:postcode":"27701",
    "sg:province":"NC",
    "wof:name":"Ronald Desrochers Insurance",
    "wof:placetype":"venue"
},
  "geometry": {"coordinates":[-78.899091,35.992895],"type":"Point"}
}