{
  "type": "Feature",
  "properties": {
    "addr:full":"15 Lack Ln Clyde NC 28721",
    "addr:housenumber":"15",
    "addr:postcode":"28721",
    "addr:street":"Lack Ln",
    "iso:country":"US",
    "sg:address":"15 Lack Ln",
    "sg:city":"Clyde",
    "sg:classifiers":[
        {
            "category":"Building & Trades",
            "subcategory":"Construction",
            "type":"Services"
        }
    ],
    "sg:phone":"+1 828 627 9991",
    "sg:postcode":"28721",
    "sg:province":"NC",
    "sg:tags":[
        "hanging",
        "contractor"
    ],
    "wof:name":"Vargos Painting",
    "wof:placetype":"venue"
},
  "geometry": {"coordinates":[-82.92873400000001,35.530807],"type":"Point"}
}