{
  "type": "Feature",
  "properties": {
    "iso:country":"US",
    "sg:address":"1717 W Mountain St",
    "sg:city":"Kernersville",
    "sg:classifiers":[
        {
            "category":"Autos & Motor Vehicles",
            "subcategory":"Auto Supplies",
            "type":"Retail Goods"
        }
    ],
    "sg:phone":"+1 336 993 3747",
    "sg:postcode":"27284",
    "sg:province":"NC",
    "sg:tags":[
        "tire"
    ],
    "wof:name":"Wilson Tire Shop Inc",
    "wof:placetype":"venue"
},
  "geometry": {"coordinates":[-80.11009799999999,36.136194],"type":"Point"}
}