{
  "type": "Feature",
  "properties": {
    "addr:full":"1301 Tobacco Barn Rd Fuquay Varina NC 27526",
    "addr:housenumber":"1301",
    "addr:postcode":"27526",
    "addr:street":"Barn Rd",
    "iso:country":"US",
    "sg:address":"1301 Tobacco Barn Rd",
    "sg:city":"Fuquay Varina",
    "sg:classifiers":[
        {
            "category":"Building & Trades",
            "subcategory":"Plumbing",
            "type":"Services"
        }
    ],
    "sg:phone":"+1 919 557 1584",
    "sg:postcode":"27526",
    "sg:province":"NC",
    "sg:tags":[
        "contractor"
    ],
    "wof:name":"Camden Plumbing Inc",
    "wof:placetype":"venue"
},
  "geometry": {"coordinates":[-78.81809699999999,35.562472],"type":"Point"}
}