{
  "type": "Feature",
  "properties": {
    "iso:country":"US",
    "sg:address":"1630 Ed Rickard Rd",
    "sg:city":"Lexington",
    "sg:classifiers":[
        {
            "category":"Building & Trades",
            "subcategory":"Construction",
            "type":"Services"
        }
    ],
    "sg:phone":"+1 336 853 2065",
    "sg:postcode":"27295",
    "sg:province":"NC",
    "sg:tags":[
        "roofing",
        "contractor"
    ],
    "wof:name":"Andrews Roofing",
    "wof:placetype":"venue"
},
  "geometry": {"coordinates":[-80.40368100000001,35.798135],"type":"Point"}
}