{
  "type": "Feature",
  "properties": {
    "addr:full":"535 Nash St E Wilson NC 27893",
    "addr:housenumber":"535",
    "addr:postcode":"27893",
    "addr:street":"Nash St E",
    "iso:country":"US",
    "sg:address":"535 Nash St E",
    "sg:city":"Wilson",
    "sg:classifiers":[
        {
            "category":"Personal",
            "subcategory":"Beauty Salon",
            "type":"Services"
        }
    ],
    "sg:phone":"+1 252 246 9798",
    "sg:postcode":"27893",
    "sg:province":"NC",
    "wof:name":"After Effects Hair Salon",
    "wof:placetype":"venue"
},
  "geometry": {"coordinates":[-77.90688299999999,35.721639],"type":"Point"}
}