{
  "type": "Feature",
  "properties": {
    "addr:full":"5616 Old Pineville Rd Charlotte NC 28217",
    "addr:housenumber":"5616",
    "addr:postcode":"28217",
    "addr:street":"Old Pineville Rd",
    "iso:country":"US",
    "sg:address":"5616 Old Pineville Rd",
    "sg:city":"Charlotte",
    "sg:classifiers":[
        {
            "category":"Building & Trades",
            "subcategory":"Construction",
            "type":"Services"
        }
    ],
    "sg:phone":"+1 704 525 3143",
    "sg:postcode":"28217",
    "sg:province":"NC",
    "sg:tags":[
        "roofing",
        "contractor"
    ],
    "wof:name":"Interstate Roofing Co",
    "wof:placetype":"venue"
},
  "geometry": {"coordinates":[-80.87773300000001,35.164436],"type":"Point"}
}