{
  "type": "Feature",
  "properties": {
    "addr:full":"504 W James St La Grange NC 28551",
    "addr:housenumber":"504",
    "addr:postcode":"28551",
    "addr:street":"W James St",
    "iso:country":"US",
    "sg:address":"504 W James St",
    "sg:city":"La Grange",
    "sg:classifiers":[
        {
            "category":"Food & Beverages",
            "subcategory":"Groceries & Convenience Stores",
            "type":"Retail Goods"
        }
    ],
    "sg:phone":"+1 252 566 4707",
    "sg:postcode":"28551",
    "sg:province":"NC",
    "sg:tags":[
        "grocer"
    ],
    "wof:name":"Smith's Grocery",
    "wof:placetype":"venue"
},
  "geometry": {"coordinates":[-77.79648299999999,35.311817],"type":"Point"}
}