{
  "type": "Feature",
  "properties": {
    "addr:full":"11613 N Main St Archdale NC 27263",
    "addr:housenumber":"11613",
    "addr:postcode":"27263",
    "addr:street":"N Main St",
    "iso:country":"US",
    "sg:address":"11613 N Main St",
    "sg:city":"Archdale",
    "sg:classifiers":[
        {
            "category":"Banks & Credit Unions",
            "subcategory":"Bank",
            "type":"Services"
        }
    ],
    "sg:phone":"+1 336 883 3730",
    "sg:postcode":"27263",
    "sg:province":"NC",
    "wof:name":"First-Citizens Bank & Trust Co",
    "wof:placetype":"venue"
},
  "geometry": {"coordinates":[-79.974326,35.916916],"type":"Point"}
}