{
  "type": "Feature",
  "properties": {
    "iso:country":"US",
    "sg:address":"5805 Graburn's Ford Dr",
    "sg:city":"Charlotte",
    "sg:classifiers":[
        {
            "category":"Building & Trades",
            "subcategory":"Construction",
            "type":"Services"
        }
    ],
    "sg:phone":"+1 704 309 3196",
    "sg:postcode":"28269",
    "sg:province":"NC",
    "sg:tags":[
        "house"
    ],
    "wof:name":"Quad City Homes LLC",
    "wof:placetype":"venue"
},
  "geometry": {"coordinates":[-80.754153,35.382028],"type":"Point"}
}