{
  "type": "Feature",
  "properties": {
    "iso:country":"US",
    "sg:address":"484 Oldham Rd",
    "sg:city":"Robbins",
    "sg:classifiers":[
        {
            "category":"Building & Trades",
            "subcategory":"Construction",
            "type":"Services"
        }
    ],
    "sg:phone":"+1 336 581 3581",
    "sg:postcode":"27376",
    "sg:province":"NC",
    "sg:tags":[
        "house"
    ],
    "wof:name":"Larry D Scott",
    "wof:placetype":"venue"
},
  "geometry": {"coordinates":[-79.48790099999999,35.238494],"type":"Point"}
}