{
  "type": "Feature",
  "properties": {
    "iso:country":"US",
    "sg:address":"3494 Kings Crossroads Rd",
    "sg:city":"Greenville",
    "sg:classifiers":[
        {
            "category":"Shopping",
            "type":"Retail Goods"
        },
        {
            "category":"Shopping",
            "subcategory":"Computers & Home Electronics",
            "type":"Retail Goods"
        }
    ],
    "sg:phone":"+1 252 353 9924",
    "sg:postcode":"27834",
    "sg:province":"NC",
    "sg:tags":[
        "equipment",
        "dealer",
        "merchandise"
    ],
    "wof:name":"Pos Solutions Inc",
    "wof:placetype":"venue"
},
  "geometry": {"coordinates":[-77.510666,35.69182],"type":"Point"}
}