{
  "type": "Feature",
  "properties": {
    "iso:country":"US",
    "sg:address":"226 6th Ave E",
    "sg:city":"Hendersonville",
    "sg:classifiers":[
        {
            "category":"Banks & Credit Unions",
            "subcategory":"Investment Brokerage",
            "type":"Services"
        }
    ],
    "sg:phone":"+1 828 697 9961",
    "sg:postcode":"28792",
    "sg:province":"NC",
    "sg:tags":[
        "firm",
        "brokerage",
        "security"
    ],
    "wof:name":"Merrill Lynch",
    "wof:placetype":"venue"
},
  "geometry": {"coordinates":[-82.458539,35.318916],"type":"Point"}
}