{
  "type": "Feature",
  "properties": {
    "iso:country":"US",
    "sg:address":"3900 Hahns Ln",
    "sg:city":"Greensboro",
    "sg:classifiers":[
        {
            "category":"Real Estate",
            "subcategory":"Real Estate Operator",
            "type":"Services"
        }
    ],
    "sg:phone":"+1 336 272 7270",
    "sg:postcode":"27401",
    "sg:province":"NC",
    "sg:tags":[
        "apartment"
    ],
    "wof:name":"Ashton Woods",
    "wof:placetype":"venue"
},
  "geometry": {"coordinates":[-79.734673,36.076792],"type":"Point"}
}