{
  "type": "Feature",
  "properties": {
    "iso:country":"US",
    "sg:address":"4435 Highsmith Rd",
    "sg:city":"Burgaw",
    "sg:classifiers":[
        {
            "category":"Autos & Motor Vehicles",
            "subcategory":"Automobile Sales",
            "type":"Retail Goods"
        }
    ],
    "sg:phone":"+1 910 259 6286",
    "sg:postcode":"28425",
    "sg:province":"NC",
    "sg:tags":[
        "used"
    ],
    "wof:name":"Carolina Cachworks Restoration",
    "wof:placetype":"venue"
},
  "geometry": {"coordinates":[-77.963887,34.499556],"type":"Point"}
}