{
  "type": "Feature",
  "properties": {
    "addr:full":"830 H B Lewis Rd Clinton NC 28328",
    "addr:housenumber":"830 h b",
    "addr:postcode":"28328",
    "addr:street":"Lewis Rd",
    "iso:country":"US",
    "sg:address":"830 H B Lewis Rd",
    "sg:city":"Clinton",
    "sg:classifiers":[
        {
            "category":"Communications",
            "type":"Services"
        }
    ],
    "sg:phone":"+1 910 590 3129",
    "sg:postcode":"28328",
    "sg:province":"NC",
    "wof:name":"Communications Structure",
    "wof:placetype":"venue"
},
  "geometry": {"coordinates":[-78.30451499999999,35.024428],"type":"Point"}
}