{
  "type": "Feature",
  "properties": {
    "addr:full":"139 Big Bend Dr Moyock NC 27958",
    "addr:housenumber":"139",
    "addr:postcode":"27958",
    "addr:street":"Big Bend Dr",
    "iso:country":"US",
    "sg:address":"139 Big Bend Dr",
    "sg:city":"Moyock",
    "sg:classifiers":[
        {
            "category":"Building & Trades",
            "subcategory":"Construction",
            "type":"Services"
        }
    ],
    "sg:phone":"+1 252 232 3864",
    "sg:postcode":"27958",
    "sg:province":"NC",
    "sg:tags":[
        "carpentry",
        "contractor"
    ],
    "wof:name":"Twilight Construction",
    "wof:placetype":"venue"
},
  "geometry": {"coordinates":[-76.093047,36.500384],"type":"Point"}
}