{
  "type": "Feature",
  "properties": {
    "iso:country":"US",
    "sg:address":"3321 Guess Rd",
    "sg:city":"Durham",
    "sg:classifiers":[
        {
            "category":"Building & Trades",
            "subcategory":"Cleaning & Sanitation",
            "type":"Services"
        }
    ],
    "sg:phone":"+1 919 471 1449",
    "sg:postcode":"27705",
    "sg:province":"NC",
    "sg:tags":[
        "janitorial"
    ],
    "wof:name":"ServiceMaster",
    "wof:placetype":"venue"
},
  "geometry": {"coordinates":[-78.92966699999999,36.039348],"type":"Point"}
}