{
  "type": "Feature",
  "properties": {
    "iso:country":"US",
    "sg:address":"102 N Forbes St",
    "sg:city":"La Grange",
    "sg:classifiers":[
        {
            "category":"Home & Garden",
            "subcategory":"Building Materials",
            "type":"Retail Goods"
        }
    ],
    "sg:phone":"+1 252 566 3121",
    "sg:postcode":"28551",
    "sg:province":"NC",
    "wof:name":"Sasser Lumber Co",
    "wof:placetype":"venue"
},
  "geometry": {"coordinates":[-77.798086,35.31241],"type":"Point"}
}