{
  "type": "Feature",
  "properties": {
    "iso:country":"US",
    "sg:address":"138 Magnolia Dr",
    "sg:city":"Smithfield",
    "sg:classifiers":[
        {
            "category":"Health Services",
            "subcategory":"Health Practitioner",
            "type":"Services"
        }
    ],
    "sg:phone":"+1 919 989 6594",
    "sg:postcode":"27573",
    "sg:province":"NC",
    "sg:tags":[
        "therapist",
        "physical"
    ],
    "wof:name":"Quality Therapy Svc Inc",
    "wof:placetype":"venue"
},
  "geometry": {"coordinates":[-78.986873,36.354412],"type":"Point"}
}