{
  "type": "Feature",
  "properties": {
    "iso:country":"US",
    "sg:address":"39 Laughter Country Ln",
    "sg:city":"Hendersonville",
    "sg:classifiers":[
        {
            "category":"Wholesale",
            "subcategory":"Dairy",
            "type":"Manufacturing & Wholesale Goods"
        }
    ],
    "sg:phone":"+1 828 685 2650",
    "sg:postcode":"28792",
    "sg:province":"NC",
    "sg:tags":[
        "frozen",
        "dessert",
        "ice",
        "cream"
    ],
    "wof:name":"Hershey Creamy Co",
    "wof:placetype":"venue"
},
  "geometry": {"coordinates":[-82.37723,35.358298],"type":"Point"}
}