{
  "type": "Feature",
  "properties": {
    "iso:country":"US",
    "sg:address":"2000 W 1st St",
    "sg:city":"Winston Salem",
    "sg:classifiers":[
        {
            "category":"Government",
            "subcategory":"Office",
            "type":"Public Place"
        }
    ],
    "sg:phone":"+1 336 722 1139",
    "sg:postcode":"27104",
    "sg:province":"NC",
    "wof:name":"US Bankruptcy Chapter 13",
    "wof:placetype":"venue"
},
  "geometry": {"coordinates":[-80.27291099999999,36.096404],"type":"Point"}
}