{
  "type": "Feature",
  "properties": {
    "iso:country":"US",
    "sg:address":"1350 S Main St",
    "sg:city":"China Grove",
    "sg:classifiers":[
        {
            "category":"Real Estate",
            "subcategory":"Developer",
            "type":"Services"
        }
    ],
    "sg:phone":"+1 704 857 9414",
    "sg:postcode":"28023",
    "sg:province":"NC",
    "sg:tags":[
        "cemetery"
    ],
    "wof:name":"West Lawn Memorial Park Inc",
    "wof:placetype":"venue"
},
  "geometry": {"coordinates":[-80.587683,35.559779],"type":"Point"}
}