{
  "type": "Feature",
  "properties": {
    "addr:full":"175 Tarheel Dr Gastonia NC 28056",
    "addr:housenumber":"175",
    "addr:postcode":"28056",
    "addr:street":"Tarheel Dr",
    "iso:country":"US",
    "sg:address":"175 Tarheel Dr",
    "sg:city":"Gastonia",
    "sg:classifiers":[
        {
            "category":"Manufacturing",
            "subcategory":"Tools & Machinery",
            "type":"Manufacturing & Wholesale Goods"
        }
    ],
    "sg:phone":"+1 704 865 1050",
    "sg:postcode":"28056",
    "sg:province":"NC",
    "sg:tags":[
        "pattern",
        "industrial",
        "mfg"
    ],
    "wof:name":"Humphrey Pattern Works",
    "wof:placetype":"venue"
},
  "geometry": {"coordinates":[-81.194734,35.176971],"type":"Point"}
}