{
  "type": "Feature",
  "properties": {
    "addr:full":"7437 US Hwy 220 S Asheboro NC 27205",
    "addr:housenumber":"7437",
    "addr:postcode":"27205",
    "addr:street":"Us Hwy 220 S",
    "iso:country":"US",
    "sg:address":"7437 US Hwy 220 S",
    "sg:city":"Asheboro",
    "sg:classifiers":[
        {
            "category":"Home & Garden",
            "subcategory":"Home Furnishings",
            "type":"Retail Goods"
        }
    ],
    "sg:phone":"+1 336 873 8764",
    "sg:postcode":"27205",
    "sg:province":"NC",
    "sg:tags":[
        "pottery"
    ],
    "wof:name":"Lufkin Pottery",
    "wof:placetype":"venue"
},
  "geometry": {"coordinates":[-79.78697,35.560411],"type":"Point"}
}