{
  "type": "Feature",
  "properties": {
    "iso:country":"US",
    "sg:address":"35 Peggy Loop",
    "sg:city":"Old Fort",
    "sg:classifiers":[
        {
            "category":"Travel",
            "subcategory":"Campground",
            "type":"Entertainment"
        }
    ],
    "sg:phone":"+1 828 668 4831",
    "sg:postcode":"28762",
    "sg:province":"NC",
    "wof:name":"Catawba Falls Campground",
    "wof:placetype":"venue"
},
  "geometry": {"coordinates":[-82.223275,35.613566],"type":"Point"}
}