{
  "type": "Feature",
  "properties": {
    "iso:country":"US",
    "sg:address":"909 King Ave",
    "sg:city":"Kannapolis",
    "sg:classifiers":[
        {
            "category":"Building & Trades",
            "subcategory":"Construction",
            "type":"Services"
        }
    ],
    "sg:phone":"+1 704 938 6263",
    "sg:postcode":"28081",
    "sg:province":"NC",
    "sg:tags":[
        "contractor"
    ],
    "wof:name":"Lackey Gutters",
    "wof:placetype":"venue"
},
  "geometry": {"coordinates":[-80.63394099999999,35.50735],"type":"Point"}
}