{
  "type": "Feature",
  "properties": {
    "iso:country":"US",
    "sg:address":"175 Jane Sowers Rd",
    "sg:city":"Statesville",
    "sg:classifiers":[
        {
            "category":"Professional",
            "subcategory":"Business Services",
            "type":"Services"
        }
    ],
    "sg:phone":"+1   ",
    "sg:postcode":"28625",
    "sg:province":"NC",
    "sg:tags":[
        "training",
        "consultation",
        "promoting"
    ],
    "wof:name":"Just Imagine",
    "wof:placetype":"venue"
},
  "geometry": {"coordinates":[-80.869536,35.834246],"type":"Point"}
}