{
  "type": "Feature",
  "properties": {
    "addr:full":"791 US Hwy 13 S Goldsboro NC 27530",
    "addr:housenumber":"791",
    "addr:postcode":"27530",
    "addr:street":"Us Hwy 13 S",
    "iso:country":"US",
    "sg:address":"791 US Hwy 13 S",
    "sg:city":"Goldsboro",
    "sg:classifiers":[
        {
            "category":"Organizations",
            "subcategory":"Religious Organization",
            "type":"Services"
        }
    ],
    "sg:phone":"+1 919 583 0208",
    "sg:postcode":"27530",
    "sg:province":"NC",
    "sg:tags":[
        "church"
    ],
    "wof:name":"Victory Faith Ctr",
    "wof:placetype":"venue"
},
  "geometry": {"coordinates":[-78.06062900000001,35.319894],"type":"Point"}
}