{
  "type": "Feature",
  "properties": {
    "addr:full":"8483 Colliers Chapel Church Rd Linden NC 28356",
    "addr:postcode":"8483;28356",
    "addr:street":"Church Rd",
    "iso:country":"US",
    "sg:address":"8483 Colliers Chapel Church Rd",
    "sg:city":"Linden",
    "sg:classifiers":[
        {
            "category":"Retail",
            "subcategory":"Repair Shop",
            "type":"Services"
        }
    ],
    "sg:phone":"+1 910 980 0662",
    "sg:postcode":"28356",
    "sg:province":"NC",
    "sg:tags":[
        "repairing",
        "lawn",
        "mower"
    ],
    "wof:name":"Morgan Saw & Mower",
    "wof:placetype":"venue"
},
  "geometry": {"coordinates":[-78.71972599999999,35.232373],"type":"Point"}
}