{
  "type": "Feature",
  "properties": {
    "iso:country":"US",
    "sg:address":"308 E Bodenhamer St",
    "sg:city":"Kernersville",
    "sg:classifiers":[
        {
            "category":"Autos & Motor Vehicles",
            "subcategory":"Automobile Sales",
            "type":"Retail Goods"
        }
    ],
    "sg:phone":"+1 336 993 0400",
    "sg:postcode":"27284",
    "sg:province":"NC",
    "sg:tags":[
        "car",
        "dealer"
    ],
    "wof:name":"Ryan's Auto Sales",
    "wof:placetype":"venue"
},
  "geometry": {"coordinates":[-80.06761299999999,36.118751],"type":"Point"}
}