{
  "type": "Feature",
  "properties": {
    "addr:full":"224 N Clinton Ave Dunn NC 28334",
    "addr:housenumber":"224",
    "addr:postcode":"28334",
    "addr:street":"N Clinton Ave",
    "iso:country":"US",
    "sg:address":"224 N Clinton Ave",
    "sg:city":"Dunn",
    "sg:classifiers":[
        {
            "category":"Shopping",
            "subcategory":"Bicycles & Sporting Goods",
            "type":"Retail Goods"
        }
    ],
    "sg:phone":"+1 910 891 1250",
    "sg:postcode":"28334",
    "sg:province":"NC",
    "sg:tags":[
        "equipment",
        "archery",
        "hunting",
        "supply"
    ],
    "wof:name":"Bowsmithe Inc",
    "wof:placetype":"venue"
},
  "geometry": {"coordinates":[-78.606964,35.308524],"type":"Point"}
}