{
  "type": "Feature",
  "properties": {
    "iso:country":"US",
    "sg:address":"50 Bethel Road",
    "sg:city":"Black Mountain",
    "sg:classifiers":[
        {
            "category":"Professional",
            "subcategory":"Computer Services",
            "type":"Services"
        }
    ],
    "sg:phone":"+1 828 778 0901",
    "sg:postcode":"28711",
    "sg:province":"NC",
    "sg:website":"http://www.roomtag.com/",
    "wof:name":"Roomtag",
    "wof:placetype":"venue"
},
  "geometry": {"coordinates":[-82.338686,35.630627],"type":"Point"}
}