{
  "type": "Feature",
  "properties": {
    "iso:country":"US",
    "sg:address":"70 College St",
    "sg:city":"Asheville",
    "sg:classifiers":[
        {
            "category":"Shopping",
            "type":"Retail Goods"
        }
    ],
    "sg:phone":"+1 828 254 5444",
    "sg:postcode":"28801",
    "sg:province":"NC",
    "sg:tags":[
        "art",
        "gallery",
        "dealer"
    ],
    "wof:name":"Golden Gate Gallery & Custom",
    "wof:placetype":"venue"
},
  "geometry": {"coordinates":[-82.552144,35.595551],"type":"Point"}
}