{
  "type": "Feature",
  "properties": {
    "addr:full":"826 Plantation Dr Burlington NC 27215",
    "addr:housenumber":"826",
    "addr:postcode":"27215",
    "addr:street":"Plantation Dr",
    "iso:country":"US",
    "sg:address":"826 Plantation Dr",
    "sg:city":"Burlington",
    "sg:classifiers":[
        {
            "category":"Wholesale",
            "subcategory":"Dairy",
            "type":"Manufacturing & Wholesale Goods"
        }
    ],
    "sg:phone":"+1 336 226 4252",
    "sg:postcode":"27215",
    "sg:province":"NC",
    "sg:tags":[
        "product"
    ],
    "wof:name":"Pet Dairy",
    "wof:placetype":"venue"
},
  "geometry": {"coordinates":[-79.44029500000001,36.065375],"type":"Point"}
}