{
  "type": "Feature",
  "properties": {
    "addr:full":"210 S College St Boiling Springs NC 28034",
    "addr:housenumber":"210",
    "addr:postcode":"28034",
    "addr:street":"S College St",
    "iso:country":"US",
    "sg:address":"210 S College St",
    "sg:city":"Boiling Springs",
    "sg:classifiers":[
        {
            "category":"Travel",
            "subcategory":"Hotels & Motels",
            "type":"Entertainment"
        }
    ],
    "sg:phone":"+1 704 434 9589",
    "sg:postcode":"28034",
    "sg:province":"NC",
    "sg:tags":[
        "breakfast",
        "accommodation",
        "bed"
    ],
    "wof:name":"Hamrick Goode House",
    "wof:placetype":"venue"
},
  "geometry": {"coordinates":[-81.174556,35.31409],"type":"Point"}
}