{
  "type": "Feature",
  "properties": {
    "iso:country":"US",
    "sg:address":"1290 E Arlington Blvd",
    "sg:city":"Greenville",
    "sg:classifiers":[
        {
            "category":"Banks & Credit Unions",
            "subcategory":"Bank",
            "type":"Services"
        }
    ],
    "sg:phone":"+1 252 439 1888",
    "sg:postcode":"27858",
    "sg:province":"NC",
    "sg:tags":[
        "financing"
    ],
    "wof:name":"Kiely Financial Svc Inc",
    "wof:placetype":"venue"
},
  "geometry": {"coordinates":[-77.36215900000001,35.576273],"type":"Point"}
}