{
  "type": "Feature",
  "properties": {
    "addr:full":"500 Oak Tree Dr Selma NC 27576",
    "addr:housenumber":"500",
    "addr:postcode":"27576",
    "addr:street":"Oak Tree Dr",
    "iso:country":"US",
    "sg:address":"500 Oak Tree Dr",
    "sg:city":"Selma",
    "sg:classifiers":[
        {
            "category":"Manufacturing",
            "subcategory":"Metals",
            "type":"Manufacturing & Wholesale Goods"
        },
        {
            "category":"Manufacturing",
            "subcategory":"Tools & Machinery",
            "type":"Manufacturing & Wholesale Goods"
        }
    ],
    "sg:phone":"+1 919 965 5555",
    "sg:postcode":"27576",
    "sg:province":"NC",
    "sg:tags":[
        "machine",
        "mfg",
        "forging"
    ],
    "sg:website":"www.buddcompany.com",
    "wof:name":"Thyssen Krupp Precision Forge",
    "wof:placetype":"venue"
},
  "geometry": {"coordinates":[-78.29679299999999,35.539774],"type":"Point"}
}