{
  "type": "Feature",
  "properties": {
    "iso:country":"US",
    "sg:address":"1737 Williams Rd",
    "sg:city":"Monroe",
    "sg:classifiers":[
        {
            "category":"Government",
            "subcategory":"Office",
            "type":"Public Place"
        }
    ],
    "sg:phone":"+1 704 282 4716",
    "sg:postcode":"28110",
    "sg:province":"NC",
    "sg:tags":[
        "civil",
        "defense",
        "agency"
    ],
    "wof:name":"Monroe Fire Dept",
    "wof:placetype":"venue"
},
  "geometry": {"coordinates":[-80.5684,35.008113],"type":"Point"}
}