{
  "type": "Feature",
  "properties": {
    "iso:country":"US",
    "sg:address":"3219 Ferncliff Rd",
    "sg:city":"Charlotte",
    "sg:classifiers":[
        {
            "category":"Professional",
            "subcategory":"Employment Agencies",
            "type":"Services"
        }
    ],
    "sg:phone":"+1 704 442 2567",
    "sg:postcode":"28211",
    "sg:province":"NC",
    "sg:tags":[
        "consultant",
        "search",
        "executive"
    ],
    "wof:name":"Hayes Group Intl",
    "wof:placetype":"venue"
},
  "geometry": {"coordinates":[-80.83466199999999,35.164188],"type":"Point"}
}