{
  "type": "Feature",
  "properties": {
    "iso:country":"US",
    "sg:address":"305 Crystal Springs Dr",
    "sg:city":"Timberlake",
    "sg:classifiers":[
        {
            "category":"Social Services",
            "subcategory":"Child Care",
            "type":"Services"
        }
    ],
    "sg:phone":"+1   ",
    "sg:postcode":"27583",
    "sg:province":"NC",
    "sg:tags":[
        "day"
    ],
    "wof:name":"Kidz Etc",
    "wof:placetype":"venue"
},
  "geometry": {"coordinates":[-78.935215,36.323465],"type":"Point"}
}