{
  "type": "Feature",
  "properties": {
    "iso:country":"US",
    "sg:address":"3124 Old Highway 64 W",
    "sg:city":"Hayesville",
    "sg:classifiers":[
        {
            "category":"Home & Garden",
            "subcategory":"Home Furnishings",
            "type":"Retail Goods"
        },
        {
            "category":"Building & Trades",
            "subcategory":"Construction",
            "type":"Services"
        },
        {
            "category":"Manufacturing",
            "subcategory":"Building Materials",
            "type":"Manufacturing & Wholesale Goods"
        },
        {
            "category":"Home & Garden",
            "subcategory":"Furniture",
            "type":"Retail Goods"
        }
    ],
    "sg:phone":"+1 828 389 3863",
    "sg:postcode":"28904",
    "sg:province":"NC",
    "sg:tags":[
        "industrial",
        "cabinetmakers-commercial",
        "cabinet",
        "refacing",
        "resurfacing",
        "maker",
        "cabinets-refinishing",
        "kitchen"
    ],
    "wof:name":"L & L Cabinets",
    "wof:placetype":"venue"
},
  "geometry": {"coordinates":[-83.87280800000001,35.0066],"type":"Point"}
}