{
  "type": "Feature",
  "properties": {
    "addr:full":"7202 Quail Meadow Ln Charlotte NC 28210",
    "addr:housenumber":"7202",
    "addr:postcode":"28210",
    "addr:street":"Quail Meadow Ln",
    "iso:country":"US",
    "sg:address":"7202 Quail Meadow Ln",
    "sg:city":"Charlotte",
    "sg:classifiers":[
        {
            "category":"Professional",
            "type":"Services"
        }
    ],
    "sg:phone":"+1 704 643 4089",
    "sg:postcode":"28210",
    "sg:province":"NC",
    "wof:name":"Sara Bowers Designer",
    "wof:placetype":"venue"
},
  "geometry": {"coordinates":[-80.862801,35.119279],"type":"Point"}
}