{
  "type": "Feature",
  "properties": {
    "iso:country":"US",
    "sg:address":"1035 Edwards Rd",
    "sg:city":"Princeton",
    "sg:classifiers":[
        {
            "category":"Autos & Motor Vehicles",
            "subcategory":"Automobile Sales",
            "type":"Retail Goods"
        }
    ],
    "sg:phone":"+1 919 936 2142",
    "sg:postcode":"27569",
    "sg:province":"NC",
    "sg:tags":[
        "car",
        "used",
        "dealer"
    ],
    "wof:name":"Logan's Used Cars",
    "wof:placetype":"venue"
},
  "geometry": {"coordinates":[-78.14742099999999,35.466128],"type":"Point"}
}