{
  "type": "Feature",
  "properties": {
    "iso:country":"US",
    "sg:address":"4607 Franklin Ave",
    "sg:city":"Wilmington",
    "sg:classifiers":[
        {
            "category":"Professional",
            "type":"Services"
        }
    ],
    "sg:phone":"+1 910 392 2331",
    "sg:postcode":"28403",
    "sg:province":"NC",
    "sg:tags":[
        "establishment"
    ],
    "wof:name":"Bye Bye Bottles",
    "wof:placetype":"venue"
},
  "geometry": {"coordinates":[-77.886833,34.238751],"type":"Point"}
}