{
  "type": "Feature",
  "properties": {
    "addr:full":"236 S Torrence St Charlotte NC 28204",
    "addr:housenumber":"236",
    "addr:postcode":"28204",
    "addr:street":"S Torrence St",
    "iso:country":"US",
    "sg:address":"236 S Torrence St",
    "sg:city":"Charlotte",
    "sg:classifiers":[
        {
            "category":"Organizations",
            "subcategory":"Religious Organization",
            "type":"Services"
        }
    ],
    "sg:phone":"+1   ",
    "sg:postcode":"28204",
    "sg:province":"NC",
    "wof:name":"Missionaries of Charity",
    "wof:placetype":"venue"
},
  "geometry": {"coordinates":[-80.82987199999999,35.212942],"type":"Point"}
}