{
  "type": "Feature",
  "properties": {
    "addr:full":"112 E North St Albemarle NC 28001",
    "addr:housenumber":"112",
    "addr:postcode":"28001",
    "addr:street":"E North St",
    "iso:country":"US",
    "sg:address":"112 E North St",
    "sg:city":"Albemarle",
    "sg:classifiers":[
        {
            "category":"Professional",
            "subcategory":"Lawyer & Legal Services",
            "type":"Services"
        }
    ],
    "sg:phone":"+1 704 983 4209",
    "sg:postcode":"28001",
    "sg:province":"NC",
    "sg:tags":[
        "attorney"
    ],
    "wof:name":"Michael W Taylor",
    "wof:placetype":"venue"
},
  "geometry": {"coordinates":[-80.197846,35.352182],"type":"Point"}
}