{
  "type": "Feature",
  "properties": {
    "addr:full":"506 Merrimon Ave Asheville NC 28804",
    "addr:housenumber":"506",
    "addr:postcode":"28804",
    "addr:street":"Merrimon Ave",
    "iso:country":"US",
    "sg:address":"506 Merrimon Ave",
    "sg:city":"Asheville",
    "sg:classifiers":[
        {
            "category":"Personal",
            "type":"Services"
        }
    ],
    "sg:phone":"+1 828 225 7969",
    "sg:postcode":"28804",
    "sg:province":"NC",
    "wof:name":"Ace Of Spades Tattoo",
    "wof:placetype":"venue"
},
  "geometry": {"coordinates":[-82.554637,35.616368],"type":"Point"}
}