{
  "type": "Feature",
  "properties": {
    "iso:country":"US",
    "sg:address":"338 Hankins Rd",
    "sg:city":"Marion",
    "sg:classifiers":[
        {
            "category":"Building & Trades",
            "subcategory":"Construction",
            "type":"Services"
        }
    ],
    "sg:phone":"+1 828 659 8193",
    "sg:postcode":"28752",
    "sg:province":"NC",
    "sg:tags":[
        "roofing",
        "contractor"
    ],
    "wof:name":"Johnson Roofing Concepts Inc",
    "wof:placetype":"venue"
},
  "geometry": {"coordinates":[-82.035062,35.716609],"type":"Point"}
}