{
  "type": "Feature",
  "properties": {
    "addr:full":"421 W Peace St Raleigh NC 27603",
    "addr:housenumber":"421",
    "addr:postcode":"27603",
    "addr:street":"W Peace St",
    "iso:country":"US",
    "sg:address":"421 W Peace St",
    "sg:city":"Raleigh",
    "sg:phone":"+1 919 836 2222",
    "sg:postcode":"27603",
    "sg:province":"NC",
    "sg:website":"http://www.peacecamera.com",
    "wof:name":"Peace Camera",
    "wof:placetype":"venue"
},
  "geometry": {"coordinates":[-78.64374100000001,35.788574],"type":"Point"}
}