{
  "type": "Feature",
  "properties": {
    "iso:country":"US",
    "sg:address":"5920 Glenwood Ave",
    "sg:city":"Raleigh",
    "sg:classifiers":[
        {
            "category":"Home & Garden",
            "subcategory":"Furniture",
            "type":"Retail Goods"
        }
    ],
    "sg:phone":"+1 919 785 9572",
    "sg:postcode":"27612",
    "sg:province":"NC",
    "sg:website":"www.rhodesfurniture.com",
    "wof:name":"Rhodes Furniture",
    "wof:placetype":"venue"
},
  "geometry": {"coordinates":[-78.699527,35.854042],"type":"Point"}
}