{
  "type": "Feature",
  "properties": {
    "iso:country":"US",
    "sg:address":"11908 Tanton Ln",
    "sg:city":"Charlotte",
    "sg:classifiers":[
        {
            "category":"Professional",
            "type":"Services"
        }
    ],
    "sg:phone":"+1 704 588 4948",
    "sg:postcode":"28273",
    "sg:province":"NC",
    "wof:name":"Janice R Crook",
    "wof:placetype":"venue"
},
  "geometry": {"coordinates":[-80.967528,35.105512],"type":"Point"}
}