{
  "type": "Feature",
  "properties": {
    "addr:full":"8105 Old Concord Rd Newell NC 28146",
    "addr:housenumber":"8105",
    "addr:postcode":"28146",
    "addr:street":"Old Concord Rd",
    "iso:country":"US",
    "sg:address":"8105 Old Concord Rd",
    "sg:city":"Newell",
    "sg:classifiers":[
        {
            "category":"Government",
            "subcategory":"Post Office",
            "type":"Public Place"
        }
    ],
    "sg:phone":"+1 704 596 1651",
    "sg:postcode":"28146",
    "sg:province":"NC",
    "wof:name":"US Post Office",
    "wof:placetype":"venue"
},
  "geometry": {"coordinates":[-80.51541,35.561463],"type":"Point"}
}