{
  "type": "Feature",
  "properties": {
    "iso:country":"US",
    "sg:address":"4301 Atlantic Ave",
    "sg:city":"Raleigh",
    "sg:classifiers":[
        {
            "category":"Airline",
            "type":"Transportation"
        }
    ],
    "sg:phone":"+1 919 877 3000",
    "sg:postcode":"27604",
    "sg:province":"NC",
    "sg:tags":[
        "air",
        "courier",
        "ground"
    ],
    "wof:name":"Fedex",
    "wof:placetype":"venue"
},
  "geometry": {"coordinates":[-78.60130599999999,35.839912],"type":"Point"}
}