{
  "type": "Feature",
  "properties": {
    "iso:country":"US",
    "sg:address":"202 E Lake View Dr",
    "sg:city":"Hayesville",
    "sg:classifiers":[
        {
            "category":"Utilities",
            "subcategory":"Refuse",
            "type":"Services"
        }
    ],
    "sg:phone":"+1 828 389 3447",
    "sg:postcode":"28904",
    "sg:province":"NC",
    "sg:tags":[
        "system"
    ],
    "wof:name":"Trash Be Gone",
    "wof:placetype":"venue"
},
  "geometry": {"coordinates":[-83.768125,35.035409],"type":"Point"}
}