{
  "type": "Feature",
  "properties": {
    "addr:full":"1212 Woodys Store Rd Roxboro NC 27574",
    "addr:housenumber":"1212",
    "addr:postcode":"27574",
    "addr:street":"Woodys Store Rd",
    "iso:country":"US",
    "sg:address":"1212 Woodys Store Rd",
    "sg:city":"Roxboro",
    "sg:classifiers":[
        {
            "category":"Farming",
            "subcategory":"Farm",
            "type":"Manufacturing & Wholesale Goods"
        }
    ],
    "sg:phone":"+1 336 599 8445",
    "sg:postcode":"27574",
    "sg:province":"NC",
    "wof:name":"Andrew Walker",
    "wof:placetype":"venue"
},
  "geometry": {"coordinates":[-78.92379699999999,36.520565],"type":"Point"}
}