{
  "type": "Feature",
  "properties": {
    "addr:full":"320 Cook St Kannapolis NC 28083",
    "addr:housenumber":"320",
    "addr:postcode":"28083",
    "addr:street":"Cook St",
    "iso:country":"US",
    "sg:address":"320 Cook St",
    "sg:city":"Kannapolis",
    "sg:classifiers":[
        {
            "category":"Social Services",
            "subcategory":"Child Care",
            "type":"Services"
        }
    ],
    "sg:phone":"+1 704 933 6400",
    "sg:postcode":"28083",
    "sg:province":"NC",
    "sg:tags":[
        "day"
    ],
    "wof:name":"Kiddie Kollege",
    "wof:placetype":"venue"
},
  "geometry": {"coordinates":[-80.618184,35.48036],"type":"Point"}
}