{
  "type": "Feature",
  "properties": {
    "iso:country":"US",
    "sg:address":"139 E. College St.",
    "sg:city":"Boiling Springs",
    "sg:classifiers":[
        {
            "category":"Restaurant",
            "type":"Food & Drink"
        }
    ],
    "sg:menulink":"http://www.allmenus.com/nc/boiling-springs/88883-papas-pizza-to-go/menu/",
    "sg:phone":"+1 704 434 5004",
    "sg:postcode":"28017",
    "sg:province":"NC",
    "sg:tags":[
        "american",
        "pizza"
    ],
    "wof:name":"Papas Pizza To Go",
    "wof:placetype":"venue"
},
  "geometry": {"coordinates":[-81.66327200000001,35.250793],"type":"Point"}
}