{
  "type": "Feature",
  "properties": {
    "iso:country":"US",
    "sg:address":"2513 Lakeshore Dr",
    "sg:city":"Greensboro",
    "sg:classifiers":[
        {
            "category":"Building & Trades",
            "subcategory":"Landscaping Services",
            "type":"Services"
        }
    ],
    "sg:phone":"+1 336 852 1439",
    "sg:postcode":"27407",
    "sg:province":"NC",
    "sg:tags":[
        "lawn",
        "maintenance",
        "grounds"
    ],
    "wof:name":"Roberts Lawn Care & Lndscpng",
    "wof:placetype":"venue"
},
  "geometry": {"coordinates":[-79.89631,36.0349],"type":"Point"}
}