{
  "type": "Feature",
  "properties": {
    "addr:full":"1240 Waterloo Dr Rocky Mount NC 27804",
    "addr:housenumber":"1240",
    "addr:postcode":"27804",
    "addr:street":"Waterloo Dr",
    "iso:country":"US",
    "sg:address":"1240 Waterloo Dr",
    "sg:city":"Rocky Mount",
    "sg:classifiers":[
        {
            "category":"Restaurant",
            "type":"Food & Drink"
        }
    ],
    "sg:phone":"+1 252 972 2944",
    "sg:postcode":"27804",
    "sg:province":"NC",
    "sg:tags":[
        "eating"
    ],
    "wof:name":"Wings East Carolina LLC",
    "wof:placetype":"venue"
},
  "geometry": {"coordinates":[-77.803226,35.993138],"type":"Point"}
}