{
  "type": "Feature",
  "properties": {
    "iso:country":"US",
    "sg:address":"3107 S Evans St",
    "sg:city":"Greenville",
    "sg:classifiers":[
        {
            "category":"Manufacturing",
            "subcategory":"Printing",
            "type":"Manufacturing & Wholesale Goods"
        }
    ],
    "sg:phone":"+1 252 931 0678",
    "sg:postcode":"27834",
    "sg:province":"NC",
    "sg:tags":[
        "newspaper"
    ],
    "wof:name":"Daily Drum",
    "wof:placetype":"venue"
},
  "geometry": {"coordinates":[-77.381697,35.577074],"type":"Point"}
}