{
  "type": "Feature",
  "properties": {
    "addr:full":"3700 Smith Farm Rd Matthews NC 28104",
    "addr:housenumber":"3700",
    "addr:postcode":"28104",
    "addr:street":"Smith Farm Rd",
    "iso:country":"US",
    "sg:address":"3700 Smith Farm Rd",
    "sg:city":"Matthews",
    "sg:classifiers":[
        {
            "category":"Wholesale",
            "subcategory":"Construction Materials",
            "type":"Manufacturing & Wholesale Goods"
        }
    ],
    "sg:phone":"+1 704 821 6071",
    "sg:postcode":"28104",
    "sg:province":"NC",
    "sg:tags":[
        "lumber"
    ],
    "sg:website":"www.midamericacedar.com",
    "wof:name":"Mid-America Cedar",
    "wof:placetype":"venue"
},
  "geometry": {"coordinates":[-80.676635,35.085921],"type":"Point"}
}