{
  "type": "Feature",
  "properties": {
    "iso:country":"US",
    "sg:address":"921 Ridge Rd",
    "sg:city":"Roxboro",
    "sg:classifiers":[
        {
            "category":"Health Services",
            "subcategory":"Doctor",
            "type":"Services"
        }
    ],
    "sg:phone":"+1 336 599 5353",
    "sg:postcode":"27573",
    "sg:province":"NC",
    "sg:tags":[
        "physician",
        "surgeon"
    ],
    "wof:name":"Sudha Amatya MD",
    "wof:placetype":"venue"
},
  "geometry": {"coordinates":[-78.976371,36.414674],"type":"Point"}
}