{
  "type": "Feature",
  "properties": {
    "iso:country":"US",
    "sg:address":"412 Raleigh St",
    "sg:city":"Fayetteville",
    "sg:classifiers":[
        {
            "category":"Retail",
            "subcategory":"Repair Shop",
            "type":"Services"
        }
    ],
    "sg:phone":"+1 910 323 1359",
    "sg:postcode":"28301",
    "sg:province":"NC",
    "sg:tags":[
        "television",
        "radio"
    ],
    "wof:name":"Pioneer TV Svc",
    "wof:placetype":"venue"
},
  "geometry": {"coordinates":[-78.885362,35.060657],"type":"Point"}
}