{
  "type": "Feature",
  "properties": {
    "addr:full":"201 N Main St Tabor City NC 28463",
    "addr:housenumber":"201",
    "addr:postcode":"28463",
    "addr:street":"N Main St",
    "iso:country":"US",
    "sg:address":"201 N Main St",
    "sg:city":"Tabor City",
    "sg:phone":"+1 910 653 2327",
    "sg:postcode":"28463",
    "sg:province":"NC",
    "sg:tags":[
        "gas"
    ],
    "wof:name":"Tabor City Oil Co Inc",
    "wof:placetype":"venue"
},
  "geometry": {"coordinates":[-78.876876,34.151126],"type":"Point"}
}