{
  "type": "Feature",
  "properties": {
    "addr:full":"655 Brookside Camp Rd Hendersonville NC 28792",
    "addr:housenumber":"655",
    "addr:postcode":"28792",
    "addr:street":"Brookside Camp Rd",
    "iso:country":"US",
    "sg:address":"655 Brookside Camp Rd",
    "sg:city":"Hendersonville",
    "sg:classifiers":[
        {
            "category":"Autos & Motor Vehicles",
            "subcategory":"Automobile Sales",
            "type":"Retail Goods"
        }
    ],
    "sg:phone":"+1 828 696 4841",
    "sg:postcode":"28792",
    "sg:province":"NC",
    "sg:tags":[
        "car",
        "dealer"
    ],
    "wof:name":"Noel Auto Sales",
    "wof:placetype":"venue"
},
  "geometry": {"coordinates":[-82.472611,35.379648],"type":"Point"}
}