{
  "type": "Feature",
  "properties": {
    "iso:country":"US",
    "sg:address":"1901 Blue Clay Rd Ste I",
    "sg:city":"Wilmington",
    "sg:classifiers":[
        {
            "category":"Retail",
            "subcategory":"Auto Repair",
            "type":"Services"
        }
    ],
    "sg:phone":"+1 910 452 0411",
    "sg:postcode":"28405",
    "sg:province":"NC",
    "wof:name":"J T's Automotive Repair Inc",
    "wof:placetype":"venue"
},
  "geometry": {"coordinates":[-77.92237799999999,34.272069],"type":"Point"}
}