{
  "type": "Feature",
  "properties": {
    "iso:country":"US",
    "sg:address":"2120 Laura Ln",
    "sg:city":"High Point",
    "sg:classifiers":[
        {
            "category":"Real Estate",
            "subcategory":"Real Estate Agent",
            "type":"Services"
        }
    ],
    "sg:phone":"+1 336 883 0122",
    "sg:postcode":"27262",
    "sg:province":"NC",
    "wof:name":"Howard Realty",
    "wof:placetype":"venue"
},
  "geometry": {"coordinates":[-80.06510900000001,35.955766],"type":"Point"}
}