{
  "type": "Feature",
  "properties": {
    "iso:country":"US",
    "sg:address":"706 Hadrian Dr",
    "sg:city":"Garner",
    "sg:classifiers":[
        {
            "category":"Professional",
            "type":"Services"
        }
    ],
    "sg:phone":"+1 919 661 4071",
    "sg:postcode":"27529",
    "sg:province":"NC",
    "wof:name":"Norann Systems Inc",
    "wof:placetype":"venue"
},
  "geometry": {"coordinates":[-78.617136,35.678542],"type":"Point"}
}