{
  "type": "Feature",
  "properties": {
    "iso:country":"US",
    "sg:address":"1904 Rockglen Ln",
    "sg:city":"Greensboro",
    "sg:classifiers":[
        {
            "category":"Real Estate",
            "subcategory":"Real Estate Operator",
            "type":"Services"
        }
    ],
    "sg:phone":"+1 336 282 9526",
    "sg:postcode":"27410",
    "sg:province":"NC",
    "sg:tags":[
        "building",
        "nonresidential"
    ],
    "wof:name":"Keating Family Proeprties LLC",
    "wof:placetype":"venue"
},
  "geometry": {"coordinates":[-79.860669,36.122226],"type":"Point"}
}