{
  "type": "Feature",
  "properties": {
    "addr:full":"501 E Lane St Raleigh NC 27601",
    "addr:housenumber":"501",
    "addr:postcode":"27601",
    "addr:street":"E Lane",
    "iso:country":"US",
    "sg:address":"501 E Lane St",
    "sg:city":"Raleigh",
    "sg:classifiers":[
        {
            "category":"Organizations",
            "subcategory":"Religious Organization",
            "type":"Services"
        }
    ],
    "sg:phone":"+1   ",
    "sg:postcode":"27601",
    "sg:province":"NC",
    "wof:name":"Praise Temple Church",
    "wof:placetype":"venue"
},
  "geometry": {"coordinates":[-78.63044600000001,35.78357],"type":"Point"}
}