{
  "type": "Feature",
  "properties": {
    "addr:full":"205 Shamrock Rd Belmont NC 28056",
    "addr:housenumber":"205",
    "addr:postcode":"28056",
    "addr:street":"Shamrock Rd",
    "iso:country":"US",
    "sg:address":"205 Shamrock Rd",
    "sg:city":"Belmont",
    "sg:classifiers":[
        {
            "category":"Manufacturing",
            "subcategory":"Metals",
            "type":"Manufacturing & Wholesale Goods"
        }
    ],
    "sg:phone":"+1 704 827 1303",
    "sg:postcode":"28056",
    "sg:province":"NC",
    "sg:tags":[
        "fabrication",
        "structural"
    ],
    "wof:name":"Ham Brothers Inc",
    "wof:placetype":"venue"
},
  "geometry": {"coordinates":[-81.06626799999999,35.292779],"type":"Point"}
}