{
  "type": "Feature",
  "properties": {
    "iso:country":"US",
    "sg:address":"3324 Robinhood Rd",
    "sg:city":"Winston Salem",
    "sg:classifiers":[
        {
            "category":"Restaurant",
            "type":"Food & Drink"
        }
    ],
    "sg:menulink":"http://www.allmenus.com/nc/winston/271071-riverbirch-lodge--restaurants/menu/",
    "sg:phone":"+1 336 768 1111",
    "sg:postcode":"27106",
    "sg:province":"NC",
    "sg:tags":[
        "american"
    ],
    "wof:name":"Riverbirch Lodge & Restaurants",
    "wof:placetype":"venue"
},
  "geometry": {"coordinates":[-80.31169199999999,36.115174],"type":"Point"}
}