{
  "type": "Feature",
  "properties": {
    "addr:full":"516 Tyvola Rd Charlotte NC 28217",
    "addr:housenumber":"516",
    "addr:postcode":"28217",
    "addr:street":"Tyvola Rd",
    "iso:country":"US",
    "sg:address":"516 Tyvola Rd",
    "sg:city":"Charlotte",
    "sg:phone":"+1 704 525 3889",
    "sg:postcode":"28217",
    "sg:province":"NC",
    "wof:name":"Loyal Buffet",
    "wof:placetype":"venue"
},
  "geometry": {"coordinates":[-80.88728999999999,35.163041],"type":"Point"}
}