{
  "type": "Feature",
  "properties": {
    "addr:full":"3695 US Hwy 301 N Dunn NC 28334",
    "addr:housenumber":"3695",
    "addr:postcode":"28334",
    "addr:street":"Us Hwy 301 N",
    "iso:country":"US",
    "sg:address":"3695 US Hwy 301 N",
    "sg:city":"Dunn",
    "sg:classifiers":[
        {
            "category":"Food & Beverages",
            "subcategory":"Groceries & Convenience Stores",
            "type":"Retail Goods"
        }
    ],
    "sg:phone":"+1 910 892 4124",
    "sg:postcode":"28334",
    "sg:province":"NC",
    "wof:name":"Carlie CS IGA Inc",
    "wof:placetype":"venue"
},
  "geometry": {"coordinates":[-78.582155,35.343354],"type":"Point"}
}