{
  "type": "Feature",
  "properties": {
    "addr:full":"6005 N Hills Dr Raleigh NC 27609",
    "addr:housenumber":"6005",
    "addr:postcode":"27609",
    "addr:street":"N Hills Dr",
    "iso:country":"US",
    "sg:address":"6005 N Hills Dr",
    "sg:city":"Raleigh",
    "sg:classifiers":[
        {
            "category":"Insurance",
            "subcategory":"Insurance Agent",
            "type":"Services"
        }
    ],
    "sg:phone":"+1 919 787 1239",
    "sg:postcode":"27609",
    "sg:province":"NC",
    "wof:name":"Insurance Planning Assoc",
    "wof:placetype":"venue"
},
  "geometry": {"coordinates":[-78.65406299999999,35.863892],"type":"Point"}
}