{
  "type": "Feature",
  "properties": {
    "addr:full":"8666 Lasater Rd Clemmons NC 27012",
    "addr:housenumber":"8666",
    "addr:postcode":"27012",
    "addr:street":"Lasater Rd",
    "iso:country":"US",
    "sg:address":"8666 Lasater Rd",
    "sg:city":"Clemmons",
    "sg:classifiers":[
        {
            "category":"Manufacturing",
            "subcategory":"Tools & Machinery",
            "type":"Manufacturing & Wholesale Goods"
        }
    ],
    "sg:phone":"+1 336 766 6609",
    "sg:postcode":"27012",
    "sg:province":"NC",
    "sg:tags":[
        "machine",
        "shop"
    ],
    "wof:name":"Etchison Machine Works Inc",
    "wof:placetype":"venue"
},
  "geometry": {"coordinates":[-80.418997,36.045295],"type":"Point"}
}