{
  "type": "Feature",
  "properties": {
    "addr:full":"25 New Covenant Dr Weaverville NC 28787",
    "addr:housenumber":"25",
    "addr:postcode":"28787",
    "addr:street":"New Covenant Dr",
    "iso:country":"US",
    "sg:address":"25 New Covenant Dr",
    "sg:city":"Weaverville",
    "sg:classifiers":[
        {
            "category":"Building & Trades",
            "subcategory":"Construction",
            "type":"Services"
        }
    ],
    "sg:phone":"+1 828 658 3187",
    "sg:postcode":"28787",
    "sg:province":"NC",
    "sg:tags":[
        "contractor"
    ],
    "wof:name":"Storm Roofing",
    "wof:placetype":"venue"
},
  "geometry": {"coordinates":[-82.56551899999999,35.724188],"type":"Point"}
}