{
  "type": "Feature",
  "properties": {
    "iso:country":"US",
    "sg:address":"54 College Dr",
    "sg:city":"Marion",
    "sg:classifiers":[
        {
            "category":"Education",
            "subcategory":"Junior College",
            "type":"Public Place"
        }
    ],
    "sg:phone":"+1 828 652 6021",
    "sg:postcode":"28752",
    "sg:province":"NC",
    "sg:tags":[
        "technical"
    ],
    "wof:name":"McDowell Tchncal Cmnty College",
    "wof:placetype":"venue"
},
  "geometry": {"coordinates":[-81.960888,35.656096],"type":"Point"}
}