{
  "type": "Feature",
  "properties": {
    "addr:full":"3491 Martin Dr New Bern NC 28562",
    "addr:housenumber":"3491",
    "addr:postcode":"28562",
    "addr:street":"Martin Dr",
    "iso:country":"US",
    "sg:address":"3491 Martin Dr",
    "sg:city":"New Bern",
    "sg:classifiers":[
        {
            "category":"Retail",
            "subcategory":"Auto Repair",
            "type":"Services"
        }
    ],
    "sg:phone":"+1 252 633 5677",
    "sg:postcode":"28562",
    "sg:province":"NC",
    "sg:tags":[
        "repairing",
        "automobile"
    ],
    "wof:name":"Martin Auto Svc",
    "wof:placetype":"venue"
},
  "geometry": {"coordinates":[-77.099463,35.103188],"type":"Point"}
}