{
  "type": "Feature",
  "properties": {
    "iso:country":"US",
    "sg:address":"5847 McHines Pl",
    "sg:city":"Raleigh",
    "sg:classifiers":[
        {
            "category":"Professional",
            "subcategory":"Computer Services",
            "type":"Services"
        }
    ],
    "sg:phone":"+1 919 878 3274",
    "sg:postcode":"27616",
    "sg:province":"NC",
    "sg:tags":[
        "hardware",
        "provider",
        "internet",
        "software"
    ],
    "sg:website":"www.dashsystems.com",
    "wof:name":"DASH Systems Inc",
    "wof:placetype":"venue"
},
  "geometry": {"coordinates":[-78.59505299999999,35.859134],"type":"Point"}
}