{
  "type": "Feature",
  "properties": {
    "addr:full":"1970 Marthas Chapel Rd Apex NC 27523",
    "addr:postcode":"1970;27523",
    "addr:street":"Marthas Chapel Rd",
    "iso:country":"US",
    "sg:address":"1970 Marthas Chapel Rd",
    "sg:city":"Apex",
    "sg:classifiers":[
        {
            "category":"Professional",
            "type":"Services"
        }
    ],
    "sg:phone":"+1 919 481 1311",
    "sg:postcode":"27523",
    "sg:province":"NC",
    "wof:name":"Ratosh Inc",
    "wof:placetype":"venue"
},
  "geometry": {"coordinates":[-78.96596099999999,35.790393],"type":"Point"}
}