{
  "type": "Feature",
  "properties": {
    "addr:full":"4657 Arendell St Morehead City NC 28557",
    "addr:housenumber":"4657",
    "addr:postcode":"28557",
    "addr:street":"Arendell St",
    "iso:country":"US",
    "sg:address":"4657 Arendell St",
    "sg:city":"Morehead City",
    "sg:classifiers":[
        {
            "category":"Insurance",
            "subcategory":"Insurance Agent",
            "type":"Services"
        }
    ],
    "sg:phone":"+1 252 726 7844",
    "sg:postcode":"28557",
    "sg:province":"NC",
    "wof:name":"Willis Of North Carolina Inc",
    "wof:placetype":"venue"
},
  "geometry": {"coordinates":[-76.783412,34.732052],"type":"Point"}
}