{
  "type": "Feature",
  "properties": {
    "iso:country":"US",
    "sg:address":"70 Crayton Rd",
    "sg:city":"Asheville",
    "sg:classifiers":[
        {
            "category":"Freight",
            "type":"Transportation"
        }
    ],
    "sg:phone":"+1 828 274 5917",
    "sg:postcode":"28803",
    "sg:province":"NC",
    "sg:tags":[
        "special"
    ],
    "wof:name":"Iron Mountain",
    "wof:placetype":"venue"
},
  "geometry": {"coordinates":[-82.519436,35.557566],"type":"Point"}
}