{
  "type": "Feature",
  "properties": {
    "addr:full":"106 Toynbee Pl Chapel Hill NC 27514",
    "addr:housenumber":"106",
    "addr:postcode":"27514",
    "addr:street":"Toynbee Pl",
    "iso:country":"US",
    "sg:address":"106 Toynbee Pl",
    "sg:city":"Chapel Hill",
    "sg:classifiers":[
        {
            "category":"Professional",
            "subcategory":"Management & Consulting",
            "type":"Services"
        }
    ],
    "sg:phone":"+1   ",
    "sg:postcode":"27514",
    "sg:province":"NC",
    "sg:tags":[
        "reviewer"
    ],
    "wof:name":"Timothy A J Haystead",
    "wof:placetype":"venue"
},
  "geometry": {"coordinates":[-79.026628,35.964832],"type":"Point"}
}