{
  "type": "Feature",
  "properties": {
    "addr:full":"3036 Holloway St Durham NC 27703",
    "addr:housenumber":"3036",
    "addr:postcode":"27703",
    "addr:street":"Holloway St",
    "iso:country":"US",
    "sg:address":"3036 Holloway St",
    "sg:city":"Durham",
    "sg:classifiers":[
        {
            "category":"Recreation",
            "subcategory":"Amusement Park",
            "type":"Entertainment"
        }
    ],
    "sg:phone":"+1 919 596 9661",
    "sg:postcode":"27703",
    "sg:province":"NC",
    "wof:name":"M & M Amusements Inc",
    "wof:placetype":"venue"
},
  "geometry": {"coordinates":[-78.83949200000001,35.985779],"type":"Point"}
}