{
  "type": "Feature",
  "properties": {
    "addr:full":"4415 State Hwy 109 N Troy NC 27371",
    "addr:housenumber":"4415",
    "addr:postcode":"27371",
    "addr:street":"State Hwy 109 N",
    "iso:country":"US",
    "sg:address":"4415 State Hwy 109 N",
    "sg:city":"Troy",
    "sg:classifiers":[
        {
            "category":"Organizations",
            "subcategory":"Political Organization",
            "type":"Services"
        }
    ],
    "sg:phone":"+1 910 572 1265",
    "sg:postcode":"27371",
    "sg:province":"NC",
    "wof:name":"Montgomery County Board",
    "wof:placetype":"venue"
},
  "geometry": {"coordinates":[-80.028474,35.466856],"type":"Point"}
}