{
  "type": "Feature",
  "properties": {
    "addr:full":"203 Lee St Kinston NC 28501",
    "addr:housenumber":"203",
    "addr:postcode":"28501",
    "addr:street":"Lee St",
    "iso:country":"US",
    "sg:address":"203 Lee St",
    "sg:city":"Kinston",
    "sg:classifiers":[
        {
            "category":"Organizations",
            "subcategory":"Religious Organization",
            "type":"Services"
        }
    ],
    "sg:phone":"+1   ",
    "sg:postcode":"28501",
    "sg:province":"NC",
    "wof:name":"Trinity Drama Ministries Inc",
    "wof:placetype":"venue"
},
  "geometry": {"coordinates":[-77.57904499999999,35.283475],"type":"Point"}
}