{
  "type": "Feature",
  "properties": {
    "addr:full":"730 W Firetower Rd Winterville NC 28590",
    "addr:housenumber":"730",
    "addr:postcode":"28590",
    "addr:street":"W Firetower Rd",
    "iso:country":"US",
    "sg:address":"730 W Firetower Rd",
    "sg:city":"Winterville",
    "sg:classifiers":[
        {
            "category":"Retail",
            "subcategory":"Auto Repair",
            "type":"Services"
        }
    ],
    "sg:phone":"+1 252 752 4700",
    "sg:postcode":"28590",
    "sg:province":"NC",
    "sg:tags":[
        "repairing",
        "automobile"
    ],
    "wof:name":"Meineke Car Care Ctr",
    "wof:placetype":"venue"
},
  "geometry": {"coordinates":[-77.401714,35.548149],"type":"Point"}
}