{
  "type": "Feature",
  "properties": {
    "iso:country":"US",
    "sg:address":"1124 Harper Rd",
    "sg:city":"Raleigh",
    "sg:classifiers":[
        {
            "category":"Professional",
            "type":"Services"
        }
    ],
    "sg:phone":"+1 919 859 3027",
    "sg:postcode":"27603",
    "sg:province":"NC",
    "wof:name":"Custom Network Wiring Inc",
    "wof:placetype":"venue"
},
  "geometry": {"coordinates":[-78.66187600000001,35.744816],"type":"Point"}
}