{
  "type": "Feature",
  "properties": {
    "iso:country":"US",
    "sg:address":"506 Pineview Rd",
    "sg:city":"Clinton",
    "sg:classifiers":[
        {
            "category":"Farming",
            "subcategory":"Livestock Farm",
            "type":"Manufacturing & Wholesale Goods"
        }
    ],
    "sg:phone":"+1 910 592 4356",
    "sg:postcode":"28328",
    "sg:province":"NC",
    "sg:tags":[
        "hog",
        "or",
        "feedlot"
    ],
    "wof:name":"James Pope",
    "wof:placetype":"venue"
},
  "geometry": {"coordinates":[-78.31205199999999,35.019033],"type":"Point"}
}