{
  "type": "Feature",
  "properties": {
    "iso:country":"US",
    "sg:address":"309 E Market St",
    "sg:city":"Smithfield",
    "sg:classifiers":[
        {
            "category":"Government",
            "subcategory":"Office",
            "type":"Public Place"
        }
    ],
    "sg:phone":"+1 919 989 5609",
    "sg:postcode":"27577",
    "sg:province":"NC",
    "sg:tags":[
        "county"
    ],
    "wof:name":"Johnston County Government 24",
    "wof:placetype":"venue"
},
  "geometry": {"coordinates":[-78.345877,35.511226],"type":"Point"}
}