{
  "type": "Feature",
  "properties": {
    "addr:full":"5111 W Market St Greensboro NC 27409",
    "addr:housenumber":"5111",
    "addr:postcode":"27409",
    "addr:street":"W Market St",
    "iso:country":"US",
    "sg:address":"5111 W Market St",
    "sg:city":"Greensboro",
    "sg:classifiers":[
        {
            "category":"Professional",
            "type":"Services"
        }
    ],
    "sg:phone":"+1 336 292 9771",
    "sg:postcode":"27409",
    "sg:province":"NC",
    "wof:name":"Rca Svc Co Div Rca",
    "wof:placetype":"venue"
},
  "geometry": {"coordinates":[-79.879294,36.069154],"type":"Point"}
}