{
  "type": "Feature",
  "properties": {
    "addr:full":"1055 E Lindsay St Greensboro NC 27405",
    "addr:housenumber":"1055",
    "addr:postcode":"27405",
    "addr:street":"E Lindsay St",
    "iso:country":"US",
    "sg:address":"1055 E Lindsay St",
    "sg:city":"Greensboro",
    "sg:classifiers":[
        {
            "category":"Retail",
            "subcategory":"Repair Shop",
            "type":"Services"
        }
    ],
    "sg:phone":"+1   ",
    "sg:postcode":"27405",
    "sg:province":"NC",
    "wof:name":"McClain Enterprises",
    "wof:placetype":"venue"
},
  "geometry": {"coordinates":[-79.769312,36.087689],"type":"Point"}
}