{
  "type": "Feature",
  "properties": {
    "iso:country":"US",
    "sg:address":"3500 Old Wire Rd",
    "sg:city":"Red Springs",
    "sg:classifiers":[
        {
            "category":"Social Services",
            "subcategory":"Child Care",
            "type":"Services"
        }
    ],
    "sg:phone":"+1 910 843 3482",
    "sg:postcode":"28377",
    "sg:province":"NC",
    "sg:tags":[
        "kindergarten",
        "academic",
        "school"
    ],
    "wof:name":"Laurinburg District Christian",
    "wof:placetype":"venue"
},
  "geometry": {"coordinates":[-79.26480599999999,34.862598],"type":"Point"}
}