{
  "type": "Feature",
  "properties": {
    "iso:country":"US",
    "sg:address":"4701 Beryl Rd",
    "sg:city":"Raleigh",
    "sg:classifiers":[
        {
            "category":"Wholesale",
            "subcategory":"Stationery",
            "type":"Manufacturing & Wholesale Goods"
        }
    ],
    "sg:phone":"+1 919 829 1116",
    "sg:postcode":"27606",
    "sg:province":"NC",
    "sg:tags":[
        "cup"
    ],
    "sg:website":"www.pfssales.com",
    "wof:name":"Pfs Sales Co",
    "wof:placetype":"venue"
},
  "geometry": {"coordinates":[-78.704317,35.794358],"type":"Point"}
}