{
  "type": "Feature",
  "properties": {
    "addr:full":"310 New Bern Ave Raleigh NC 27601",
    "addr:housenumber":"310",
    "addr:postcode":"27601",
    "addr:street":"New Bern Ave",
    "iso:country":"US",
    "sg:address":"310 New Bern Ave",
    "sg:city":"Raleigh",
    "sg:classifiers":[
        {
            "category":"Professional",
            "type":"Services"
        }
    ],
    "sg:phone":"+1 919 839 1236",
    "sg:postcode":"27601",
    "sg:province":"NC",
    "sg:tags":[
        "establishment"
    ],
    "wof:name":"Triangle Associates",
    "wof:placetype":"venue"
},
  "geometry": {"coordinates":[-78.633318,35.78012],"type":"Point"}
}