{
  "type": "Feature",
  "properties": {
    "iso:country":"US",
    "sg:address":"3229 State Hwy 49",
    "sg:city":"Burlington",
    "sg:classifiers":[
        {
            "category":"Farming",
            "subcategory":"Farm",
            "type":"Manufacturing & Wholesale Goods"
        }
    ],
    "sg:phone":"+1 336 578 3395",
    "sg:postcode":"27217",
    "sg:province":"NC",
    "sg:tags":[
        "crop",
        "general"
    ],
    "wof:name":"Warren Bros",
    "wof:placetype":"venue"
},
  "geometry": {"coordinates":[-79.33162799999999,36.170083],"type":"Point"}
}