{
  "type": "Feature",
  "properties": {
    "iso:country":"US",
    "sg:address":"3002 Buckingham Way",
    "sg:city":"Apex",
    "sg:classifiers":[
        {
            "category":"Food & Beverages",
            "subcategory":"Bakery",
            "type":"Retail Goods"
        }
    ],
    "sg:phone":"+1 919 362 4722",
    "sg:postcode":"27502",
    "sg:province":"NC",
    "sg:tags":[
        "baker"
    ],
    "wof:name":"Cakes By Greta Inc",
    "wof:placetype":"venue"
},
  "geometry": {"coordinates":[-78.82651199999999,35.734075],"type":"Point"}
}