{
  "type": "Feature",
  "properties": {
    "addr:full":"134 Elk St Lexington NC 27292",
    "addr:housenumber":"134",
    "addr:postcode":"27292",
    "addr:street":"Elk St",
    "iso:country":"US",
    "sg:address":"134 Elk St",
    "sg:city":"Lexington",
    "sg:classifiers":[
        {
            "category":"Professional",
            "subcategory":"Business Services",
            "type":"Services"
        }
    ],
    "sg:phone":"+1 336 248 5604",
    "sg:postcode":"27292",
    "sg:province":"NC",
    "sg:tags":[
        "embroidery"
    ],
    "wof:name":"Stitchery Inc",
    "wof:placetype":"venue"
},
  "geometry": {"coordinates":[-80.252456,35.819946],"type":"Point"}
}