{
  "type": "Feature",
  "properties": {
    "addr:full":"476 Rosewood Rd Goldsboro NC 27530",
    "addr:housenumber":"476",
    "addr:postcode":"27530",
    "addr:street":"Rosewood Rd",
    "iso:country":"US",
    "sg:address":"476 Rosewood Rd",
    "sg:city":"Goldsboro",
    "sg:classifiers":[
        {
            "category":"Real Estate",
            "subcategory":"Real Estate Operator",
            "type":"Services"
        }
    ],
    "sg:phone":"+1 919 735 7033",
    "sg:postcode":"27530",
    "sg:province":"NC",
    "sg:tags":[
        "property",
        "lessor"
    ],
    "wof:name":"Larry Grady",
    "wof:placetype":"venue"
},
  "geometry": {"coordinates":[-78.059603,35.412445],"type":"Point"}
}