{
  "type": "Feature",
  "properties": {
    "addr:full":"3006 Grassy Creek Virgilina Rd Bullock NC 27507",
    "addr:housenumber":"3006",
    "addr:postcode":"27507",
    "addr:street":"Grassy Creek Virgilina Rd",
    "iso:country":"US",
    "sg:address":"3006 Grassy Creek Virgilina Rd",
    "sg:city":"Bullock",
    "sg:classifiers":[
        {
            "category":"Building & Trades",
            "subcategory":"Plumbing",
            "type":"Services"
        }
    ],
    "sg:phone":"+1 919 693 8924",
    "sg:postcode":"27507",
    "sg:province":"NC",
    "sg:tags":[
        "conditioning",
        "air",
        "system",
        "contractor"
    ],
    "wof:name":"Noblin Heating & Air Cond",
    "wof:placetype":"venue"
},
  "geometry": {"coordinates":[-78.629839,36.516567],"type":"Point"}
}