{
  "type": "Feature",
  "properties": {
    "iso:country":"US",
    "sg:address":"602 Hickory Ridge Dr",
    "sg:city":"Greensboro",
    "sg:classifiers":[
        {
            "category":"Banks & Credit Unions",
            "subcategory":"Bank",
            "type":"Services"
        }
    ],
    "sg:phone":"+1 336 841 6850",
    "sg:postcode":"27409",
    "sg:province":"NC",
    "sg:tags":[
        "financing"
    ],
    "wof:name":"Norwest Financial NC Inc",
    "wof:placetype":"venue"
},
  "geometry": {"coordinates":[-79.956941,36.072384],"type":"Point"}
}