{
  "type": "Feature",
  "properties": {
    "iso:country":"US",
    "sg:address":"1200 Wynnewood Ave",
    "sg:city":"High Point",
    "sg:classifiers":[
        {
            "category":"Wholesale",
            "subcategory":"Vending Machines",
            "type":"Manufacturing & Wholesale Goods"
        }
    ],
    "sg:phone":"+1 336 883 6452",
    "sg:postcode":"27262",
    "sg:province":"NC",
    "wof:name":"Turnkey Showroom Svc",
    "wof:placetype":"venue"
},
  "geometry": {"coordinates":[-80.030541,35.969377],"type":"Point"}
}