{
  "type": "Feature",
  "properties": {
    "iso:country":"US",
    "sg:address":"2700 High Point Rd",
    "sg:city":"Greensboro",
    "sg:classifiers":[
        {
            "category":"Restaurant",
            "type":"Food & Drink"
        }
    ],
    "sg:menulink":"http://www.allmenus.com/nc/greensboro/136117-carolinas-diner/menu/",
    "sg:phone":"+1 336 297 9363",
    "sg:postcode":"27403",
    "sg:province":"NC",
    "sg:tags":[
        "american"
    ],
    "wof:name":"Carolina's Diner",
    "wof:placetype":"venue"
},
  "geometry": {"coordinates":[-79.833606,36.052519],"type":"Point"}
}