{
  "type": "Feature",
  "properties": {
    "addr:full":"331 Walnut St Waynesville NC 28786",
    "addr:housenumber":"331",
    "addr:postcode":"28786",
    "addr:street":"Walnut St",
    "iso:country":"US",
    "sg:address":"331 Walnut St",
    "sg:city":"Waynesville",
    "sg:classifiers":[
        {
            "category":"Shopping",
            "subcategory":"Bicycles & Sporting Goods",
            "type":"Retail Goods"
        }
    ],
    "sg:phone":"+1 828 452 0961",
    "sg:postcode":"28786",
    "sg:province":"NC",
    "wof:name":"Sports Zone Wnc",
    "wof:placetype":"venue"
},
  "geometry": {"coordinates":[-82.985097,35.497256],"type":"Point"}
}