{
  "type": "Feature",
  "properties": {
    "iso:country":"US",
    "sg:address":"815 Lewis St",
    "sg:city":"Gastonia",
    "sg:classifiers":[
        {
            "category":"Building & Trades",
            "subcategory":"Construction",
            "type":"Services"
        }
    ],
    "sg:phone":"+1 704 866 8110",
    "sg:postcode":"28054",
    "sg:province":"NC",
    "sg:tags":[
        "siding",
        "contractor"
    ],
    "sg:website":"www.gastoniasiding.com",
    "wof:name":"Gastonia Siding & Windows",
    "wof:placetype":"venue"
},
  "geometry": {"coordinates":[-81.164669,35.274496],"type":"Point"}
}