{
  "type": "Feature",
  "properties": {
    "addr:full":"2733 Hodge Rd Knightdale NC 27545",
    "addr:housenumber":"2733",
    "addr:postcode":"27545",
    "addr:street":"Hodge Rd",
    "iso:country":"US",
    "sg:address":"2733 Hodge Rd",
    "sg:city":"Knightdale",
    "sg:classifiers":[
        {
            "category":"Professional",
            "type":"Services"
        }
    ],
    "sg:phone":"+1 919 217 9077",
    "sg:postcode":"27545",
    "sg:province":"NC",
    "wof:name":"Billy J Myrick",
    "wof:placetype":"venue"
},
  "geometry": {"coordinates":[-78.51691099999999,35.754343],"type":"Point"}
}