{
  "type": "Feature",
  "properties": {
    "addr:full":"700 Wilkesboro St Mocksville NC 27028",
    "addr:housenumber":"700",
    "addr:postcode":"27028",
    "addr:street":"Wilkesboro St",
    "iso:country":"US",
    "sg:address":"700 Wilkesboro St",
    "sg:city":"Mocksville",
    "sg:classifiers":[
        {
            "category":"Home & Garden",
            "subcategory":"Mobile Homes",
            "type":"Retail Goods"
        }
    ],
    "sg:phone":"+1 336 751 5959",
    "sg:postcode":"27028",
    "sg:province":"NC",
    "wof:name":"Bonanza Mobile Homes Inc",
    "wof:placetype":"venue"
},
  "geometry": {"coordinates":[-80.57276299999999,35.901949],"type":"Point"}
}