{
  "type": "Feature",
  "properties": {
    "iso:country":"US",
    "sg:address":"21212 Senlac Ln",
    "sg:city":"Cornelius",
    "sg:classifiers":[
        {
            "category":"Real Estate",
            "subcategory":"Real Estate Agent",
            "type":"Services"
        }
    ],
    "sg:phone":"+1 704 896 8000",
    "sg:postcode":"28031",
    "sg:province":"NC",
    "wof:name":"Derek Risley",
    "wof:placetype":"venue"
},
  "geometry": {"coordinates":[-80.89487,35.503362],"type":"Point"}
}