{
  "type": "Feature",
  "properties": {
    "addr:full":"630 Davis Dr Morrisville NC 27560",
    "addr:housenumber":"630",
    "addr:postcode":"27560",
    "addr:street":"Davis Dr",
    "iso:country":"US",
    "sg:address":"630 Davis Dr",
    "sg:city":"Morrisville",
    "sg:classifiers":[
        {
            "category":"Professional",
            "subcategory":"Employment Agencies",
            "type":"Services"
        }
    ],
    "sg:phone":"+1 919 474 0771",
    "sg:postcode":"27560",
    "sg:province":"NC",
    "sg:tags":[
        "consultant",
        "search",
        "executive"
    ],
    "sg:website":"www.ccesearch.com",
    "wof:name":"Carlyle & Conlan",
    "wof:placetype":"venue"
},
  "geometry": {"coordinates":[-78.864127,35.871453],"type":"Point"}
}