{
  "type": "Feature",
  "properties": {
    "addr:full":"195 Starpoint Dr Fayetteville NC 28303",
    "addr:housenumber":"195",
    "addr:postcode":"28303",
    "addr:street":"Starpoint Dr",
    "iso:country":"US",
    "sg:address":"195 Starpoint Dr",
    "sg:city":"Fayetteville",
    "sg:classifiers":[
        {
            "category":"Insurance",
            "subcategory":"Insurance Agent",
            "type":"Services"
        }
    ],
    "sg:phone":"+1 910 826 7111",
    "sg:postcode":"28303",
    "sg:province":"NC",
    "wof:name":"All In 1 Insurance",
    "wof:placetype":"venue"
},
  "geometry": {"coordinates":[-79.00942499999999,35.086881],"type":"Point"}
}