{
  "type": "Feature",
  "properties": {
    "iso:country":"US",
    "sg:address":"1132 Arden Dr",
    "sg:city":"Salisbury",
    "sg:classifiers":[
        {
            "category":"Shopping",
            "subcategory":"Clothing, Apparel, & Fashions",
            "type":"Retail Goods"
        }
    ],
    "sg:phone":"+1 704 637 2932",
    "sg:postcode":"28144",
    "sg:province":"NC",
    "sg:tags":[
        "alteration"
    ],
    "wof:name":"Professional Alterations",
    "wof:placetype":"venue"
},
  "geometry": {"coordinates":[-80.49490299999999,35.693082],"type":"Point"}
}