{
  "type": "Feature",
  "properties": {
    "addr:full":"337 Buie Rd Broadway NC 27505",
    "addr:housenumber":"337",
    "addr:postcode":"27505",
    "addr:street":"Buie Rd",
    "iso:country":"US",
    "sg:address":"337 Buie Rd",
    "sg:city":"Broadway",
    "sg:classifiers":[
        {
            "category":"Retail",
            "subcategory":"Auto Rental",
            "type":"Services"
        }
    ],
    "sg:phone":"+1   ",
    "sg:postcode":"27505",
    "sg:province":"NC",
    "sg:tags":[
        "mobile",
        "house",
        "home"
    ],
    "wof:name":"Lasater Rentals",
    "wof:placetype":"venue"
},
  "geometry": {"coordinates":[-79.00579500000001,35.354107],"type":"Point"}
}