{
  "type": "Feature",
  "properties": {
    "iso:country":"US",
    "sg:address":"5513 Surreydowns Ct",
    "sg:city":"Wilmington",
    "sg:classifiers":[
        {
            "category":"Professional",
            "subcategory":"Management & Consulting",
            "type":"Services"
        }
    ],
    "sg:phone":"+1   ",
    "sg:postcode":"28403",
    "sg:province":"NC",
    "sg:tags":[
        "large",
        "program"
    ],
    "wof:name":"Intracoastial Consulting Copr",
    "wof:placetype":"venue"
},
  "geometry": {"coordinates":[-77.849795,34.216728],"type":"Point"}
}