{
  "type": "Feature",
  "properties": {
    "addr:full":"696 N Morgan Branch Rd Candler NC 28715",
    "addr:housenumber":"696",
    "addr:postcode":"28715",
    "addr:street":"N Morgan Branch Rd",
    "iso:country":"US",
    "sg:address":"696 N Morgan Branch Rd",
    "sg:city":"Candler",
    "sg:classifiers":[
        {
            "category":"Retail",
            "subcategory":"Auto Repair",
            "type":"Services"
        }
    ],
    "sg:phone":"+1   ",
    "sg:postcode":"28715",
    "sg:province":"NC",
    "sg:tags":[
        "general"
    ],
    "wof:name":"Tolers Auto",
    "wof:placetype":"venue"
},
  "geometry": {"coordinates":[-82.730704,35.543635],"type":"Point"}
}