{
  "type": "Feature",
  "properties": {
    "iso:country":"US",
    "sg:address":"1600 S Miami Blvd",
    "sg:city":"Durham",
    "sg:classifiers":[
        {
            "category":"Home & Garden",
            "subcategory":"Building Materials",
            "type":"Retail Goods"
        }
    ],
    "sg:phone":"+1 919 968 0100",
    "sg:postcode":"27703",
    "sg:province":"NC",
    "sg:tags":[
        "glass",
        "window",
        "plate"
    ],
    "wof:name":"Glass Master",
    "wof:placetype":"venue"
},
  "geometry": {"coordinates":[-78.838138,35.950043],"type":"Point"}
}