{
  "type": "Feature",
  "properties": {
    "iso:country":"US",
    "sg:address":"218 Mangum Rd",
    "sg:city":"Angier",
    "sg:classifiers":[
        {
            "category":"Building & Trades",
            "subcategory":"Construction",
            "type":"Services"
        }
    ],
    "sg:phone":"+1 919 639 4456",
    "sg:postcode":"27501",
    "sg:province":"NC",
    "sg:tags":[
        "general",
        "contractor"
    ],
    "wof:name":"Austin Construction & Dev",
    "wof:placetype":"venue"
},
  "geometry": {"coordinates":[-78.768748,35.463563],"type":"Point"}
}