{
  "type": "Feature",
  "properties": {
    "iso:country":"US",
    "sg:address":"111 Commercial Park Dr SW",
    "sg:city":"Concord",
    "sg:classifiers":[
        {
            "category":"Retail",
            "subcategory":"Animal Services",
            "type":"Services"
        }
    ],
    "sg:phone":"+1 704 786 7275",
    "sg:postcode":"28027",
    "sg:province":"NC",
    "sg:tags":[
        "pet",
        "grooming",
        "washing"
    ],
    "wof:name":"Dog Park LLC",
    "wof:placetype":"venue"
},
  "geometry": {"coordinates":[-80.623918,35.39077],"type":"Point"}
}