{
  "type": "Feature",
  "properties": {
    "iso:country":"US",
    "sg:address":"2466 SW Cary Pkwy",
    "sg:city":"Cary",
    "sg:classifiers":[
        {
            "category":"Insurance",
            "subcategory":"Hazard Insurance",
            "type":"Services"
        }
    ],
    "sg:phone":"+1 919 481 9357",
    "sg:postcode":"27513",
    "sg:province":"NC",
    "sg:tags":[
        "life",
        "casualty"
    ],
    "wof:name":"Liberty Mutual",
    "wof:placetype":"venue"
},
  "geometry": {"coordinates":[-78.822425,35.763479],"type":"Point"}
}