{
  "type": "Feature",
  "properties": {
    "addr:full":"315 N Berkeley Blvd Goldsboro NC 27534",
    "addr:housenumber":"315",
    "addr:postcode":"27534",
    "addr:street":"N Berkeley Blvd",
    "iso:country":"US",
    "sg:address":"315 N Berkeley Blvd",
    "sg:city":"Goldsboro",
    "sg:classifiers":[
        {
            "category":"Professional",
            "type":"Services"
        },
        {
            "category":"Restaurant",
            "type":"Food & Drink"
        }
    ],
    "sg:phone":"+1 919 778 4625",
    "sg:postcode":"27534",
    "sg:province":"NC",
    "sg:tags":[
        "shop",
        "coffee"
    ],
    "wof:name":"Theo's Espresso",
    "wof:placetype":"venue"
},
  "geometry": {"coordinates":[-77.945885,35.374381],"type":"Point"}
}