{
  "type": "Feature",
  "properties": {
    "iso:country":"US",
    "sg:address":"3706 High Point Rd",
    "sg:city":"Greensboro",
    "sg:classifiers":[
        {
            "category":"Restaurant",
            "type":"Food & Drink"
        }
    ],
    "sg:phone":"+1 336 315 2131",
    "sg:postcode":"27407",
    "sg:province":"NC",
    "sg:tags":[
        "eating"
    ],
    "wof:name":"Mamma Maria Italian Pasta & Gr",
    "wof:placetype":"venue"
},
  "geometry": {"coordinates":[-79.85019,36.039801],"type":"Point"}
}