{
  "type": "Feature",
  "properties": {
    "addr:full":"5600 Glenkirk Rd Charlotte NC 28210",
    "addr:housenumber":"5600",
    "addr:postcode":"28210",
    "addr:street":"Glenkirk Rd",
    "iso:country":"US",
    "sg:address":"5600 Glenkirk Rd",
    "sg:city":"Charlotte",
    "sg:classifiers":[
        {
            "category":"Professional",
            "subcategory":"Business Services",
            "type":"Services"
        }
    ],
    "sg:phone":"+1   ",
    "sg:postcode":"28210",
    "sg:province":"NC",
    "sg:tags":[
        "interior",
        "item",
        "decorating",
        "retail"
    ],
    "wof:name":"Thistledown Designs",
    "wof:placetype":"venue"
},
  "geometry": {"coordinates":[-80.84658899999999,35.150615],"type":"Point"}
}