{
  "type": "Feature",
  "properties": {
    "addr:full":"101 S Tryon St Charlotte NC 28202",
    "addr:housenumber":"101",
    "addr:postcode":"28202",
    "addr:street":"S Tryon St",
    "iso:country":"US",
    "sg:address":"101 S Tryon St",
    "sg:city":"Charlotte",
    "sg:classifiers":[
        {
            "category":"Professional",
            "subcategory":"Employment Agencies",
            "type":"Services"
        }
    ],
    "sg:phone":"+1 704 644 7000",
    "sg:postcode":"28202",
    "sg:province":"NC",
    "sg:tags":[
        "opportunity"
    ],
    "wof:name":"Talent Bridge",
    "wof:placetype":"venue"
},
  "geometry": {"coordinates":[-80.844207,35.226414],"type":"Point"}
}