{
  "type": "Feature",
  "properties": {
    "addr:full":"115 Snowridge Rd Banner Elk NC 28604",
    "addr:housenumber":"115",
    "addr:postcode":"28604",
    "addr:street":"Snowridge Rd",
    "iso:country":"US",
    "sg:address":"115 Snowridge Rd",
    "sg:city":"Banner Elk",
    "sg:classifiers":[
        {
            "category":"Food & Beverages",
            "subcategory":"Specialty",
            "type":"Retail Goods"
        }
    ],
    "sg:phone":"+1 828 898 7642",
    "sg:postcode":"28604",
    "sg:province":"NC",
    "sg:tags":[
        "herb"
    ],
    "wof:name":"Strategic Botanicals Div",
    "wof:placetype":"venue"
},
  "geometry": {"coordinates":[-81.831503,36.172719],"type":"Point"}
}