{
  "type": "Feature",
  "properties": {
    "iso:country":"US",
    "sg:address":"300 Our Rd",
    "sg:city":"Beaufort",
    "sg:classifiers":[
        {
            "category":"Marine",
            "type":"Transportation"
        }
    ],
    "sg:phone":"+1 252 728 2931",
    "sg:postcode":"28516",
    "sg:province":"NC",
    "sg:tags":[
        "surveyor"
    ],
    "wof:name":"Four Winds Marine Surveying",
    "wof:placetype":"venue"
},
  "geometry": {"coordinates":[-76.664592,34.807546],"type":"Point"}
}