{
  "type": "Feature",
  "properties": {
    "iso:country":"US",
    "sg:address":"9760 Harkers Ct",
    "sg:city":"Huntersville",
    "sg:classifiers":[
        {
            "category":"Building & Trades",
            "subcategory":"Construction",
            "type":"Services"
        }
    ],
    "sg:phone":"+1 704 875 9542",
    "sg:postcode":"28078",
    "sg:province":"NC",
    "sg:tags":[
        "house"
    ],
    "wof:name":"Welch Roofing",
    "wof:placetype":"venue"
},
  "geometry": {"coordinates":[-80.87282,35.3841],"type":"Point"}
}