{
  "type": "Feature",
  "properties": {
    "iso:country":"US",
    "sg:address":"318 New Rand Rd",
    "sg:city":"Garner",
    "sg:classifiers":[
        {
            "category":"Education",
            "subcategory":"Special Training",
            "type":"Public Place"
        }
    ],
    "sg:phone":"+1 919 779 8820",
    "sg:postcode":"27529",
    "sg:province":"NC",
    "sg:tags":[
        "instruction",
        "music"
    ],
    "wof:name":"R J Graves Productions",
    "wof:placetype":"venue"
},
  "geometry": {"coordinates":[-78.602699,35.698473],"type":"Point"}
}