{
  "type": "Feature",
  "properties": {
    "addr:full":"12212 Raven Ridge Rd Raleigh NC 27614",
    "addr:housenumber":"12212",
    "addr:postcode":"27614",
    "addr:street":"Raven Ridge Rd",
    "iso:country":"US",
    "sg:address":"12212 Raven Ridge Rd",
    "sg:city":"Raleigh",
    "sg:classifiers":[
        {
            "category":"Building & Trades",
            "subcategory":"Construction",
            "type":"Services"
        }
    ],
    "sg:phone":"+1 919 847 7556",
    "sg:postcode":"27614",
    "sg:province":"NC",
    "sg:tags":[
        "home",
        "builder",
        "custom"
    ],
    "sg:website":"www.randallshirleybuilders.com",
    "wof:name":"Randall Shirley Builders Inc",
    "wof:placetype":"venue"
},
  "geometry": {"coordinates":[-78.61065000000001,35.939242],"type":"Point"}
}