{
  "type": "Feature",
  "properties": {
    "iso:country":"US",
    "sg:address":"1303 N Collegiate Dr",
    "sg:city":"Wilkesboro",
    "sg:classifiers":[
        {
            "category":"Professional",
            "subcategory":"Accounting & Tax Preparation",
            "type":"Services"
        }
    ],
    "sg:phone":"+1 336 667 4901",
    "sg:postcode":"28697",
    "sg:province":"NC",
    "sg:tags":[
        "return"
    ],
    "wof:name":"H & R Block",
    "wof:placetype":"venue"
},
  "geometry": {"coordinates":[-81.178134,36.142981],"type":"Point"}
}