{
  "type": "Feature",
  "properties": {
    "addr:full":"10653 Montford Cove Rd Marion NC 28752",
    "addr:housenumber":"10653",
    "addr:postcode":"28752",
    "addr:street":"Montford Cove Rd",
    "iso:country":"US",
    "sg:address":"10653 Montford Cove Rd",
    "sg:city":"Marion",
    "sg:classifiers":[
        {
            "category":"Communications",
            "subcategory":"Film & Video Production",
            "type":"Services"
        }
    ],
    "sg:phone":"+1   ",
    "sg:postcode":"28752",
    "sg:province":"NC",
    "sg:tags":[
        "motion"
    ],
    "wof:name":"Littleleadhead Productions",
    "wof:placetype":"venue"
},
  "geometry": {"coordinates":[-82.059561,35.564477],"type":"Point"}
}