{
  "type": "Feature",
  "properties": {
    "addr:full":"206 Ether Rd Star NC 27356",
    "addr:housenumber":"206",
    "addr:postcode":"27356",
    "addr:street":"Ether Rd",
    "iso:country":"US",
    "sg:address":"206 Ether Rd",
    "sg:city":"Star",
    "sg:classifiers":[
        {
            "category":"Manufacturing",
            "subcategory":"Textiles",
            "type":"Manufacturing & Wholesale Goods"
        }
    ],
    "sg:phone":"+1 910 428 2147",
    "sg:postcode":"27356",
    "sg:province":"NC",
    "sg:tags":[
        "hosiery"
    ],
    "wof:name":"Pine Hosiery Mill",
    "wof:placetype":"venue"
},
  "geometry": {"coordinates":[-79.787959,35.442758],"type":"Point"}
}