{
  "type": "Feature",
  "properties": {
    "iso:country":"US",
    "sg:address":"475 Hein Dr",
    "sg:city":"Garner",
    "sg:classifiers":[
        {
            "category":"Wholesale",
            "subcategory":"Electrical",
            "type":"Manufacturing & Wholesale Goods"
        }
    ],
    "sg:phone":"+1 919 779 8777",
    "sg:postcode":"27529",
    "sg:province":"NC",
    "sg:tags":[
        "supply"
    ],
    "wof:name":"Voss Lighting",
    "wof:placetype":"venue"
},
  "geometry": {"coordinates":[-78.55509600000001,35.675909],"type":"Point"}
}