{
  "type": "Feature",
  "properties": {
    "addr:full":"1101 W Main St Yadkinville NC 27055",
    "addr:housenumber":"1101",
    "addr:postcode":"27055",
    "addr:street":"W Main St",
    "iso:country":"US",
    "sg:address":"1101 W Main St",
    "sg:city":"Yadkinville",
    "sg:classifiers":[
        {
            "category":"Personal",
            "subcategory":"Barber",
            "type":"Services"
        }
    ],
    "sg:phone":"+1 336 677 3805",
    "sg:postcode":"27055",
    "sg:province":"NC",
    "sg:tags":[
        "shop"
    ],
    "wof:name":"West Main Street Barber Shop",
    "wof:placetype":"venue"
},
  "geometry": {"coordinates":[-80.678331,36.13565],"type":"Point"}
}