{
  "type": "Feature",
  "properties": {
    "addr:full":"110 Oak St Morganton NC 28655",
    "addr:housenumber":"110",
    "addr:postcode":"28655",
    "addr:street":"Oak St",
    "iso:country":"US",
    "sg:address":"110 Oak St",
    "sg:city":"Morganton",
    "sg:classifiers":[
        {
            "category":"Personal",
            "subcategory":"Beauty Salon",
            "type":"Services"
        }
    ],
    "sg:phone":"+1   ",
    "sg:postcode":"28655",
    "sg:province":"NC",
    "sg:tags":[
        "shop"
    ],
    "wof:name":"Clean Cuts Marvin Clark",
    "wof:placetype":"venue"
},
  "geometry": {"coordinates":[-81.684978,35.758084],"type":"Point"}
}