{
  "type": "Feature",
  "properties": {
    "iso:country":"US",
    "sg:address":"99 Village Dr",
    "sg:city":"Jacksonville",
    "sg:classifiers":[
        {
            "category":"Real Estate",
            "subcategory":"Real Estate Agent",
            "type":"Services"
        }
    ],
    "sg:phone":"+1 910 353 0223",
    "sg:postcode":"28546",
    "sg:province":"NC",
    "wof:name":"J & J Realty Inc",
    "wof:placetype":"venue"
},
  "geometry": {"coordinates":[-77.379586,34.747187],"type":"Point"}
}