{
  "type": "Feature",
  "properties": {
    "iso:country":"US",
    "sg:address":"1862 Caratoke Hwy",
    "sg:city":"Moyock",
    "sg:classifiers":[
        {
            "category":"Freight",
            "type":"Transportation"
        }
    ],
    "sg:phone":"+1 252 232 6626",
    "sg:postcode":"27958",
    "sg:province":"NC",
    "sg:tags":[
        "commercial",
        "storage"
    ],
    "wof:name":"Sound Side Self Storage Inc",
    "wof:placetype":"venue"
},
  "geometry": {"coordinates":[-76.09969599999999,36.459768],"type":"Point"}
}