{
  "type": "Feature",
  "properties": {
    "addr:full":"366 Windy Acres Ridge Rd Fleetwood NC 28626",
    "addr:housenumber":"366",
    "addr:postcode":"28626",
    "addr:street":"Windy Acres Ridge Rd",
    "iso:country":"US",
    "sg:address":"366 Windy Acres Ridge Rd",
    "sg:city":"Fleetwood",
    "sg:classifiers":[
        {
            "category":"Building & Trades",
            "subcategory":"Construction",
            "type":"Services"
        }
    ],
    "sg:phone":"+1 336 877 5639",
    "sg:postcode":"28626",
    "sg:province":"NC",
    "sg:tags":[
        "home",
        "improvement"
    ],
    "wof:name":"Wall-To-Wall Construction",
    "wof:placetype":"venue"
},
  "geometry": {"coordinates":[-81.50023400000001,36.309596],"type":"Point"}
}