{
  "type": "Feature",
  "properties": {
    "iso:country":"US",
    "sg:address":"110 S Queen St",
    "sg:city":"Kinston",
    "sg:classifiers":[
        {
            "category":"Professional",
            "subcategory":"Lawyer & Legal Services",
            "type":"Services"
        }
    ],
    "sg:phone":"+1 252 527 7777",
    "sg:postcode":"28501",
    "sg:province":"NC",
    "sg:tags":[
        "attorney"
    ],
    "sg:website":"www.rduke.com",
    "wof:name":"Duke Rod Law Office",
    "wof:placetype":"venue"
},
  "geometry": {"coordinates":[-77.581091,35.260117],"type":"Point"}
}