{
  "type": "Feature",
  "properties": {
    "addr:full":"2904 Buckthorne Ct Raleigh NC 27610",
    "addr:housenumber":"2904",
    "addr:postcode":"27610",
    "addr:street":"Buckthorne Ct",
    "iso:country":"US",
    "sg:address":"2904 Buckthorne Ct",
    "sg:city":"Raleigh",
    "sg:classifiers":[
        {
            "category":"Building & Trades",
            "subcategory":"Construction",
            "type":"Services"
        }
    ],
    "sg:phone":"+1 919 828 2598",
    "sg:postcode":"27610",
    "sg:province":"NC",
    "sg:tags":[
        "carpentry",
        "contractor"
    ],
    "wof:name":"Johnny Knight",
    "wof:placetype":"venue"
},
  "geometry": {"coordinates":[-78.60539,35.741805],"type":"Point"}
}