{
  "type": "Feature",
  "properties": {
    "addr:full":"219 N Graham St Charlotte NC 28202",
    "addr:housenumber":"219",
    "addr:postcode":"28202",
    "addr:street":"N Graham St",
    "iso:country":"US",
    "sg:address":"219 N Graham St",
    "sg:city":"Charlotte",
    "sg:classifiers":[
        {
            "category":"Banks & Credit Unions",
            "subcategory":"Bank",
            "type":"Services"
        }
    ],
    "sg:phone":"+1 704 376 8438",
    "sg:postcode":"28202",
    "sg:province":"NC",
    "sg:tags":[
        "loan",
        "real estate"
    ],
    "wof:name":"Graham Investment Co",
    "wof:placetype":"venue"
},
  "geometry": {"coordinates":[-80.84551999999999,35.231675],"type":"Point"}
}