{
  "type": "Feature",
  "properties": {
    "addr:full":"561 Queens Creek Rd Hubert NC 28539",
    "addr:housenumber":"561",
    "addr:postcode":"28539",
    "addr:street":"Queens Creek Rd",
    "iso:country":"US",
    "sg:address":"561 Queens Creek Rd",
    "sg:city":"Hubert",
    "sg:classifiers":[
        {
            "category":"Social Services",
            "type":"Services"
        }
    ],
    "sg:phone":"+1 910 326 2290",
    "sg:postcode":"28539",
    "sg:province":"NC",
    "sg:tags":[
        "organization",
        "welfare"
    ],
    "wof:name":"Carobell Inc",
    "wof:placetype":"venue"
},
  "geometry": {"coordinates":[-77.17321,34.682703],"type":"Point"}
}