{
  "type": "Feature",
  "properties": {
    "addr:full":"168 Dyson Rd Mocksville NC 27028",
    "addr:housenumber":"168",
    "addr:postcode":"27028",
    "addr:street":"Dyson Rd",
    "iso:country":"US",
    "sg:address":"168 Dyson Rd",
    "sg:city":"Mocksville",
    "sg:classifiers":[
        {
            "category":"Building & Trades",
            "subcategory":"Electrical",
            "type":"Services"
        }
    ],
    "sg:phone":"+1 336 492 2475",
    "sg:postcode":"27028",
    "sg:province":"NC",
    "sg:tags":[
        "electrical",
        "contractor"
    ],
    "wof:name":"Carlton B Dyson",
    "wof:placetype":"venue"
},
  "geometry": {"coordinates":[-80.67998799999999,35.970436],"type":"Point"}
}