{
  "type": "Feature",
  "properties": {
    "addr:full":"103 N Center St Goldsboro NC 27530",
    "addr:housenumber":"103",
    "addr:postcode":"27530",
    "addr:street":"N Center St",
    "iso:country":"US",
    "sg:address":"103 N Center St",
    "sg:city":"Goldsboro",
    "sg:classifiers":[
        {
            "category":"Restaurant",
            "type":"Food & Drink"
        }
    ],
    "sg:phone":"+1 919 735 7979",
    "sg:postcode":"27530",
    "sg:province":"NC",
    "sg:tags":[
        "eating"
    ],
    "wof:name":"Central Lunch Restaurant",
    "wof:placetype":"venue"
},
  "geometry": {"coordinates":[-77.996726,35.384404],"type":"Point"}
}