{
  "type": "Feature",
  "properties": {
    "iso:country":"US",
    "sg:address":"608 Wilder Ave",
    "sg:city":"Aberdeen",
    "sg:classifiers":[
        {
            "category":"Organizations",
            "subcategory":"Religious Organization",
            "type":"Services"
        }
    ],
    "sg:phone":"+1 910 944 1595",
    "sg:postcode":"28315",
    "sg:province":"NC",
    "sg:tags":[
        "church"
    ],
    "wof:name":"Page Memorial United Methodist",
    "wof:placetype":"venue"
},
  "geometry": {"coordinates":[-79.437911,35.130709],"type":"Point"}
}