{
  "type": "Feature",
  "properties": {
    "iso:country":"US",
    "sg:address":"5435 Seventy-Seven Center Dr",
    "sg:city":"Charlotte",
    "sg:classifiers":[
        {
            "category":"Building & Trades",
            "subcategory":"Construction",
            "type":"Services"
        }
    ],
    "sg:phone":"+1 704 527 6420",
    "sg:postcode":"28217",
    "sg:province":"NC",
    "sg:tags":[
        "home",
        "builder"
    ],
    "wof:name":"Fortis Westminster Homes",
    "wof:placetype":"venue"
},
  "geometry": {"coordinates":[-80.886608,35.168613],"type":"Point"}
}