{
  "type": "Feature",
  "properties": {
    "iso:country":"US",
    "sg:address":"109 W 2nd St",
    "sg:city":"Robersonville",
    "sg:classifiers":[
        {
            "category":"Social Services",
            "type":"Services"
        }
    ],
    "sg:phone":"+1 252 795 4230",
    "sg:postcode":"27871",
    "sg:province":"NC",
    "sg:tags":[
        "counseling"
    ],
    "wof:name":"Haven Counseling Svc",
    "wof:placetype":"venue"
},
  "geometry": {"coordinates":[-77.253153,35.822527],"type":"Point"}
}