{
  "type": "Feature",
  "properties": {
    "addr:full":"5917 Myrtle Grove Rd Wilmington NC 28409",
    "addr:housenumber":"5917",
    "addr:postcode":"28409",
    "addr:street":"Myrtle Grove Rd",
    "iso:country":"US",
    "sg:address":"5917 Myrtle Grove Rd",
    "sg:city":"Wilmington",
    "sg:classifiers":[
        {
            "category":"Autos & Motor Vehicles",
            "subcategory":"Automobile Sales",
            "type":"Retail Goods"
        }
    ],
    "sg:phone":"+1 910 395 1200",
    "sg:postcode":"28409",
    "sg:province":"NC",
    "sg:tags":[
        "car"
    ],
    "wof:name":"Port City Auto Sales",
    "wof:placetype":"venue"
},
  "geometry": {"coordinates":[-77.886703,34.101299],"type":"Point"}
}