{
  "type": "Feature",
  "properties": {
    "addr:full":"575 Becktown Rd Mocksville NC 27028",
    "addr:housenumber":"575",
    "addr:postcode":"27028",
    "addr:street":"Becktown Rd",
    "iso:country":"US",
    "sg:address":"575 Becktown Rd",
    "sg:city":"Mocksville",
    "sg:classifiers":[
        {
            "category":"Farming",
            "subcategory":"Farm",
            "type":"Manufacturing & Wholesale Goods"
        }
    ],
    "sg:phone":"+1 336 998 4683",
    "sg:postcode":"27028",
    "sg:province":"NC",
    "sg:tags":[
        "crop",
        "general"
    ],
    "wof:name":"Larry Stephens",
    "wof:placetype":"venue"
},
  "geometry": {"coordinates":[-80.49814000000001,35.822981],"type":"Point"}
}