{
  "type": "Feature",
  "properties": {
    "addr:full":"226 Carbon City Rd Morganton NC 28655",
    "addr:housenumber":"226",
    "addr:postcode":"28655",
    "addr:street":"Carbon City Rd",
    "iso:country":"US",
    "sg:address":"226 Carbon City Rd",
    "sg:city":"Morganton",
    "sg:classifiers":[
        {
            "category":"Autos & Motor Vehicles",
            "subcategory":"Auto Supplies",
            "type":"Retail Goods"
        }
    ],
    "sg:phone":"+1 828 433 6021",
    "sg:postcode":"28655",
    "sg:province":"NC",
    "wof:name":"Alray Tire Center",
    "wof:placetype":"venue"
},
  "geometry": {"coordinates":[-81.712152,35.735887],"type":"Point"}
}