{
  "type": "Feature",
  "properties": {
    "iso:country":"US",
    "sg:address":"131 Pisgah Dr",
    "sg:city":"Canton",
    "sg:classifiers":[
        {
            "category":"Personal",
            "subcategory":"Beauty Salon",
            "type":"Services"
        }
    ],
    "sg:phone":"+1 828 648 6127",
    "sg:postcode":"28716",
    "sg:province":"NC",
    "sg:tags":[
        "shop"
    ],
    "wof:name":"Enchanting Hair Fashions",
    "wof:placetype":"venue"
},
  "geometry": {"coordinates":[-82.83690199999999,35.525213],"type":"Point"}
}