{
  "type": "Feature",
  "properties": {
    "addr:full":"7330 US Hwy 158 Leasburg NC 27291",
    "addr:housenumber":"7330",
    "addr:postcode":"27291",
    "addr:street":"Us Hwy 158",
    "iso:country":"US",
    "sg:address":"7330 US Hwy 158",
    "sg:city":"Leasburg",
    "sg:classifiers":[
        {
            "category":"Government",
            "subcategory":"Post Office",
            "type":"Public Place"
        }
    ],
    "sg:phone":"+1 336 599 8520",
    "sg:postcode":"27291",
    "sg:province":"NC",
    "wof:name":"US Post Office",
    "wof:placetype":"venue"
},
  "geometry": {"coordinates":[-79.11398199999999,36.386221],"type":"Point"}
}