{
  "type": "Feature",
  "properties": {
    "addr:full":"1625 Maurice Trull Rd Wingate NC 28174",
    "addr:housenumber":"1625",
    "addr:postcode":"28174",
    "addr:street":"Maurice Trull Rd",
    "iso:country":"US",
    "sg:address":"1625 Maurice Trull Rd",
    "sg:city":"Wingate",
    "sg:classifiers":[
        {
            "category":"Retail",
            "subcategory":"Repair Shop",
            "type":"Services"
        }
    ],
    "sg:phone":"+1   ",
    "sg:postcode":"28174",
    "sg:province":"NC",
    "wof:name":"Union Small Engine Sales & Svc",
    "wof:placetype":"venue"
},
  "geometry": {"coordinates":[-80.43463800000001,35.025949],"type":"Point"}
}