{
  "type": "Feature",
  "properties": {
    "iso:country":"US",
    "sg:address":"300 E Spring St",
    "sg:city":"Seven Springs",
    "sg:classifiers":[
        {
            "category":"Restaurant",
            "type":"Food & Drink"
        }
    ],
    "sg:phone":"+1 910 293 2218",
    "sg:postcode":"28578",
    "sg:province":"NC",
    "sg:tags":[
        "eating"
    ],
    "wof:name":"Bills Chicken & Bbq",
    "wof:placetype":"venue"
},
  "geometry": {"coordinates":[-77.84207499999999,35.226372],"type":"Point"}
}