{
  "type": "Feature",
  "properties": {
    "addr:full":"832 E 4th St Charlotte NC 28202",
    "addr:housenumber":"832",
    "addr:postcode":"28202",
    "addr:street":"E 4Th St",
    "iso:country":"US",
    "sg:address":"832 E 4th St",
    "sg:city":"Charlotte",
    "sg:classifiers":[
        {
            "category":"Building & Trades",
            "subcategory":"Electrical",
            "type":"Services"
        }
    ],
    "sg:phone":"+1 704 332 3331",
    "sg:postcode":"28202",
    "sg:province":"NC",
    "sg:tags":[
        "electrical",
        "contractor"
    ],
    "wof:name":"Griffin Electric",
    "wof:placetype":"venue"
},
  "geometry": {"coordinates":[-80.837611,35.220662],"type":"Point"}
}