{
  "type": "Feature",
  "properties": {
    "iso:country":"US",
    "sg:address":"2372 Zephyr Rd",
    "sg:city":"Dobson",
    "sg:classifiers":[
        {
            "category":"Food & Beverages",
            "subcategory":"Groceries & Convenience Stores",
            "type":"Retail Goods"
        }
    ],
    "sg:phone":"+1 336 366 4099",
    "sg:postcode":"27017",
    "sg:province":"NC",
    "wof:name":"On The Way Food Store",
    "wof:placetype":"venue"
},
  "geometry": {"coordinates":[-80.784768,36.395061],"type":"Point"}
}