{
  "type": "Feature",
  "properties": {
    "iso:country":"US",
    "sg:address":"3119 Shannon Rd",
    "sg:city":"Durham",
    "sg:classifiers":[
        {
            "category":"Restaurant",
            "type":"Food & Drink"
        }
    ],
    "sg:phone":"+1 919 403 7765",
    "sg:postcode":"27707",
    "sg:province":"NC",
    "sg:tags":[
        "eating"
    ],
    "wof:name":"KFC",
    "wof:placetype":"venue"
},
  "geometry": {"coordinates":[-78.955005,35.966925],"type":"Point"}
}