{
  "type": "Feature",
  "properties": {
    "addr:full":"3112 Henslowe Dr Raleigh NC 27603",
    "addr:housenumber":"3112",
    "addr:postcode":"27603",
    "addr:street":"Henslowe Dr",
    "iso:country":"US",
    "sg:address":"3112 Henslowe Dr",
    "sg:city":"Raleigh",
    "sg:classifiers":[
        {
            "category":"Professional",
            "type":"Services"
        }
    ],
    "sg:phone":"+1 919 833 3444",
    "sg:postcode":"27603",
    "sg:province":"NC",
    "wof:name":"Meditech",
    "wof:placetype":"venue"
},
  "geometry": {"coordinates":[-78.676204,35.750787],"type":"Point"}
}