{
  "type": "Feature",
  "properties": {
    "addr:full":"705 Windmill St Walnut Cove NC 27052",
    "addr:housenumber":"705",
    "addr:postcode":"27052",
    "addr:street":"Windmill St",
    "iso:country":"US",
    "sg:address":"705 Windmill St",
    "sg:city":"Walnut Cove",
    "sg:classifiers":[
        {
            "category":"Building & Trades",
            "subcategory":"Construction",
            "type":"Services"
        }
    ],
    "sg:phone":"+1 336 474 4504",
    "sg:postcode":"27052",
    "sg:province":"NC",
    "sg:tags":[
        "industrial",
        "painting"
    ],
    "wof:name":"Canon Painting Inc",
    "wof:placetype":"venue"
},
  "geometry": {"coordinates":[-80.143269,36.300741],"type":"Point"}
}