{
  "type": "Feature",
  "properties": {
    "iso:country":"US",
    "sg:address":"7731 Alcorn Rd",
    "sg:city":"Greensboro",
    "sg:classifiers":[
        {
            "category":"Building & Trades",
            "subcategory":"Landscaping Services",
            "type":"Services"
        }
    ],
    "sg:phone":"+1 336 340 3772",
    "sg:postcode":"27409",
    "sg:province":"NC",
    "sg:tags":[
        "lawn",
        "maintenance",
        "grounds"
    ],
    "wof:name":"Patriot Lawn Svc",
    "wof:placetype":"venue"
},
  "geometry": {"coordinates":[-79.959193,36.152053],"type":"Point"}
}