{
  "type": "Feature",
  "properties": {
    "iso:country":"US",
    "sg:address":"414 E Main St",
    "sg:city":"Sanford",
    "sg:classifiers":[
        {
            "category":"Autos & Motor Vehicles",
            "subcategory":"Auto Supplies",
            "type":"Retail Goods"
        }
    ],
    "sg:phone":"+1 919 777 9499",
    "sg:postcode":"27332",
    "sg:province":"NC",
    "sg:tags":[
        "tire"
    ],
    "wof:name":"Perry Brothers Tire Svc",
    "wof:placetype":"venue"
},
  "geometry": {"coordinates":[-79.147796,35.458718],"type":"Point"}
}