{
  "type": "Feature",
  "properties": {
    "iso:country":"US",
    "sg:address":"1857 Winkler Mill Rd",
    "sg:city":"Wilkesboro",
    "sg:classifiers":[
        {
            "category":"Retail",
            "subcategory":"Repair Shop",
            "type":"Services"
        },
        {
            "category":"Building & Trades",
            "subcategory":"Construction",
            "type":"Services"
        }
    ],
    "sg:phone":"+1 336 667 5058",
    "sg:postcode":"28697",
    "sg:province":"NC",
    "sg:tags":[
        "vinyl",
        "contractor"
    ],
    "wof:name":"Dead Head Vinyl Siding & Replc",
    "wof:placetype":"venue"
},
  "geometry": {"coordinates":[-81.212408,36.16332],"type":"Point"}
}