{
  "type": "Feature",
  "properties": {
    "iso:country":"US",
    "sg:address":"40461 Mount Zion Church Rd",
    "sg:city":"Norwood",
    "sg:classifiers":[
        {
            "category":"Wholesale",
            "subcategory":"Non-durable Goods",
            "type":"Manufacturing & Wholesale Goods"
        }
    ],
    "sg:phone":"+1 704 474 3467",
    "sg:postcode":"28128",
    "sg:province":"NC",
    "wof:name":"Rats Trading Post",
    "wof:placetype":"venue"
},
  "geometry": {"coordinates":[-80.158438,35.190318],"type":"Point"}
}