{
  "type": "Feature",
  "properties": {
    "iso:country":"US",
    "sg:address":"5302 Goldmine Rd",
    "sg:city":"Monroe",
    "sg:phone":"+1 704 821 1932",
    "sg:postcode":"28110",
    "sg:province":"NC",
    "sg:tags":[
        "irrigation",
        "company"
    ],
    "wof:name":"Southern Rain",
    "wof:placetype":"venue"
},
  "geometry": {"coordinates":[-80.659041,35.019074],"type":"Point"}
}