{
  "type": "Feature",
  "properties": {
    "iso:country":"US",
    "sg:address":"224 SW Market St",
    "sg:city":"Reidsville",
    "sg:classifiers":[
        {
            "category":"Shopping",
            "subcategory":"Used Merchandise",
            "type":"Retail Goods"
        }
    ],
    "sg:phone":"+1 336 349 4413",
    "sg:postcode":"27320",
    "sg:province":"NC",
    "wof:name":"Uptown Antiques",
    "wof:placetype":"venue"
},
  "geometry": {"coordinates":[-79.663183,36.359864],"type":"Point"}
}