{
  "type": "Feature",
  "properties": {
    "iso:country":"US",
    "sg:address":"255 Rutledge Rd",
    "sg:city":"Fletcher",
    "sg:classifiers":[
        {
            "category":"Wholesale",
            "subcategory":"Beer",
            "type":"Manufacturing & Wholesale Goods"
        }
    ],
    "sg:phone":"+1 828 651 0353",
    "sg:postcode":"28732",
    "sg:province":"NC",
    "sg:tags":[
        "ale"
    ],
    "wof:name":"Budweiser Of Asheville",
    "wof:placetype":"venue"
},
  "geometry": {"coordinates":[-82.526754,35.444438],"type":"Point"}
}