{
  "type": "Feature",
  "properties": {
    "addr:full":"18720 Maplecroft Lake Ln Davidson NC 28036",
    "addr:housenumber":"18720",
    "addr:postcode":"28036",
    "addr:street":"Maplecroft Lake Ln",
    "iso:country":"US",
    "sg:address":"18720 Maplecroft Lake Ln",
    "sg:city":"Davidson",
    "sg:classifiers":[
        {
            "category":"Education",
            "subcategory":"Special Training",
            "type":"Public Place"
        }
    ],
    "sg:phone":"+1   ",
    "sg:postcode":"28036",
    "sg:province":"NC",
    "wof:name":"Jeanne T Stimson",
    "wof:placetype":"venue"
},
  "geometry": {"coordinates":[-80.80141999999999,35.460494],"type":"Point"}
}