{
  "type": "Feature",
  "properties": {
    "iso:country":"US",
    "sg:address":"701 N Howe St",
    "sg:city":"Southport",
    "sg:classifiers":[
        {
            "category":"Banks & Credit Unions",
            "subcategory":"Bank",
            "type":"Services"
        }
    ],
    "sg:phone":"+1 910 457 6999",
    "sg:postcode":"28461",
    "sg:province":"NC",
    "sg:website":"www.waccamawbank.com",
    "wof:name":"Waccamaw Bank",
    "wof:placetype":"venue"
},
  "geometry": {"coordinates":[-78.021587,33.926703],"type":"Point"}
}