{
  "type": "Feature",
  "properties": {
    "addr:full":"5033 US Hwy 117 Wallace NC 28466",
    "addr:housenumber":"5033",
    "addr:postcode":"28466",
    "addr:street":"Us Hwy 117",
    "iso:country":"US",
    "sg:address":"5033 US Hwy 117",
    "sg:city":"Wallace",
    "sg:classifiers":[
        {
            "category":"Farming",
            "subcategory":"Farm",
            "type":"Manufacturing & Wholesale Goods"
        }
    ],
    "sg:phone":"+1 910 285 2014",
    "sg:postcode":"28466",
    "sg:province":"NC",
    "sg:tags":[
        "crop",
        "general"
    ],
    "wof:name":"Jdt Farming LLC",
    "wof:placetype":"venue"
},
  "geometry": {"coordinates":[-78.00184900000001,34.764061],"type":"Point"}
}