{
  "type": "Feature",
  "properties": {
    "addr:full":"595 Warren St NE Concord NC 28025",
    "addr:housenumber":"595",
    "addr:postcode":"28025",
    "addr:street":"Warren St Ne",
    "iso:country":"US",
    "sg:address":"595 Warren St NE",
    "sg:city":"Concord",
    "sg:classifiers":[
        {
            "category":"Food & Beverages",
            "subcategory":"Groceries & Convenience Stores",
            "type":"Retail Goods"
        }
    ],
    "sg:phone":"+1 704 793 1331",
    "sg:postcode":"28025",
    "sg:province":"NC",
    "sg:tags":[
        "grocer"
    ],
    "sg:website":"www.bi-lo.com",
    "wof:name":"Bi-Lo",
    "wof:placetype":"venue"
},
  "geometry": {"coordinates":[-80.59478300000001,35.430572],"type":"Point"}
}