{
  "type": "Feature",
  "properties": {
    "addr:full":"3801 Bach Cir Greenville NC 27858",
    "addr:housenumber":"3801",
    "addr:postcode":"27858",
    "addr:street":"Bach Cir",
    "iso:country":"US",
    "sg:address":"3801 Bach Cir",
    "sg:city":"Greenville",
    "sg:classifiers":[
        {
            "category":"Professional",
            "subcategory":"Lawyer & Legal Services",
            "type":"Services"
        }
    ],
    "sg:phone":"+1   ",
    "sg:postcode":"27858",
    "sg:province":"NC",
    "wof:name":"Stanley Law Firm",
    "wof:placetype":"venue"
},
  "geometry": {"coordinates":[-77.34759099999999,35.577951],"type":"Point"}
}