{
  "type": "Feature",
  "properties": {
    "iso:country":"US",
    "sg:address":"214 E Arlington Blvd",
    "sg:city":"Greenville",
    "sg:classifiers":[
        {
            "category":"Personal",
            "type":"Services"
        },
        {
            "category":"Sports & Exercise",
            "subcategory":"Gym",
            "type":"Entertainment"
        }
    ],
    "sg:phone":"+1 252 353 6348",
    "sg:postcode":"27858",
    "sg:province":"NC",
    "sg:tags":[
        "club",
        "gymnasium",
        "program",
        "health",
        "fitness",
        "studio",
        "physical"
    ],
    "wof:name":"Max Fitness Personal Training",
    "wof:placetype":"venue"
},
  "geometry": {"coordinates":[-77.37456899999999,35.588445],"type":"Point"}
}