{
  "type": "Feature",
  "properties": {
    "addr:full":"5345 Market St Wilmington NC 28405",
    "addr:housenumber":"5345",
    "addr:postcode":"28405",
    "addr:street":"Market St",
    "iso:country":"US",
    "sg:address":"5345 Market St",
    "sg:city":"Wilmington",
    "sg:classifiers":[
        {
            "category":"Travel",
            "subcategory":"Hotels & Motels",
            "type":"Entertainment"
        }
    ],
    "sg:phone":"+1 910 799 4292",
    "sg:postcode":"28405",
    "sg:province":"NC",
    "sg:website":"www.innkeeperhotel.com",
    "wof:name":"Innkeeper Of Wilmington",
    "wof:placetype":"venue"
},
  "geometry": {"coordinates":[-77.87148000000001,34.245978],"type":"Point"}
}