{
  "type": "Feature",
  "properties": {
    "iso:country":"US",
    "sg:address":"8900 Autumn Winds Dr",
    "sg:city":"Raleigh",
    "sg:classifiers":[
        {
            "category":"Building & Trades",
            "subcategory":"Cleaning & Sanitation",
            "type":"Services"
        }
    ],
    "sg:phone":"+1 919 862 0700",
    "sg:postcode":"27615",
    "sg:province":"NC",
    "sg:tags":[
        "house"
    ],
    "sg:website":"www.mollymaid.com",
    "wof:name":"Molly Maids",
    "wof:placetype":"venue"
},
  "geometry": {"coordinates":[-78.659848,35.904657],"type":"Point"}
}