{
  "type": "Feature",
  "properties": {
    "iso:country":"US",
    "sg:address":"601 S Wall St",
    "sg:city":"Benson",
    "sg:classifiers":[
        {
            "category":"Building & Trades",
            "subcategory":"Construction",
            "type":"Services"
        }
    ],
    "sg:phone":"+1 919 868 5918",
    "sg:postcode":"27504",
    "sg:province":"NC",
    "sg:tags":[
        "carpentry",
        "contractor"
    ],
    "wof:name":"Cabinets By Andy",
    "wof:placetype":"venue"
},
  "geometry": {"coordinates":[-78.55247300000001,35.377885],"type":"Point"}
}