{
  "type": "Feature",
  "properties": {
    "iso:country":"US",
    "sg:address":"993 Perry Rd",
    "sg:city":"Zebulon",
    "sg:classifiers":[
        {
            "category":"Organizations",
            "subcategory":"Religious Organization",
            "type":"Services"
        }
    ],
    "sg:phone":"+1 919 404 1902",
    "sg:postcode":"27597",
    "sg:province":"NC",
    "sg:tags":[
        "church"
    ],
    "wof:name":"Little Mt Olive Deliverance Te",
    "wof:placetype":"venue"
},
  "geometry": {"coordinates":[-78.31023,35.919706],"type":"Point"}
}