{
  "type": "Feature",
  "properties": {
    "iso:country":"US",
    "sg:address":"408 Church St",
    "sg:city":"Morganton",
    "sg:classifiers":[
        {
            "category":"Organizations",
            "subcategory":"Religious Organization",
            "type":"Services"
        }
    ],
    "sg:phone":"+1   ",
    "sg:postcode":"28655",
    "sg:province":"NC",
    "wof:name":"Friendship Baptist Church",
    "wof:placetype":"venue"
},
  "geometry": {"coordinates":[-81.67930699999999,35.746],"type":"Point"}
}