{
  "type": "Feature",
  "properties": {
    "iso:country":"US",
    "sg:address":"1301 Airport Rd",
    "sg:city":"Pikeville",
    "sg:phone":"+1 919 734 5763",
    "sg:postcode":"27863",
    "sg:province":"NC",
    "sg:tags":[
        "farm",
        "corn",
        "soybean",
        "tobacco"
    ],
    "wof:name":"Mack Lancaster",
    "wof:placetype":"venue"
},
  "geometry": {"coordinates":[-77.951015,35.49675],"type":"Point"}
}