{
  "type": "Feature",
  "properties": {
    "addr:full":"1949 Park Rd Charlotte NC 28203",
    "addr:housenumber":"1949",
    "addr:postcode":"28203",
    "addr:street":"Park Rd",
    "iso:country":"US",
    "sg:address":"1949 Park Rd",
    "sg:city":"Charlotte",
    "sg:classifiers":[
        {
            "category":"Professional",
            "subcategory":"Management & Consulting",
            "type":"Services"
        }
    ],
    "sg:phone":"+1 704 375 6262",
    "sg:postcode":"28203",
    "sg:province":"NC",
    "sg:tags":[
        "consultant"
    ],
    "wof:name":"Openline",
    "wof:placetype":"venue"
},
  "geometry": {"coordinates":[-80.851625,35.203981],"type":"Point"}
}