{
  "type": "Feature",
  "properties": {
    "iso:country":"US",
    "sg:address":"2333 James B White Hwy N",
    "sg:city":"Whiteville",
    "sg:classifiers":[
        {
            "category":"Organizations",
            "subcategory":"Community Association",
            "type":"Services"
        }
    ],
    "sg:phone":"+1 910 642 3623",
    "sg:postcode":"28472",
    "sg:province":"NC",
    "sg:tags":[
        "club"
    ],
    "wof:name":"Whiteville Country Club",
    "wof:placetype":"venue"
},
  "geometry": {"coordinates":[-78.716009,34.370293],"type":"Point"}
}