{
  "type": "Feature",
  "properties": {
    "iso:country":"US",
    "sg:address":"5845 Yadkin Rd",
    "sg:city":"Fayetteville",
    "sg:classifiers":[
        {
            "category":"Personal",
            "subcategory":"Barber",
            "type":"Services"
        }
    ],
    "sg:phone":"+1 910 860 7976",
    "sg:postcode":"28303",
    "sg:province":"NC",
    "wof:name":"Young's Barber Shop",
    "wof:placetype":"venue"
},
  "geometry": {"coordinates":[-78.98565600000001,35.093047],"type":"Point"}
}