{
  "type": "Feature",
  "properties": {
    "iso:country":"US",
    "sg:address":"113 S Main St",
    "sg:city":"Louisburg",
    "sg:classifiers":[
        {
            "category":"Government",
            "subcategory":"Office",
            "type":"Public Place"
        }
    ],
    "sg:phone":"+1 919 496 6304",
    "sg:postcode":"27549",
    "sg:province":"NC",
    "sg:website":"www.djjdp.org",
    "wof:name":"Franklin Juvenile Ct Counselor",
    "wof:placetype":"venue"
},
  "geometry": {"coordinates":[-78.30100899999999,36.099066],"type":"Point"}
}