{
  "type": "Feature",
  "properties": {
    "iso:country":"US",
    "sg:address":"3947 Ebert Rd",
    "sg:city":"Winston Salem",
    "sg:classifiers":[
        {
            "category":"Building & Trades",
            "subcategory":"Construction",
            "type":"Services"
        }
    ],
    "sg:phone":"+1 336 785 7785",
    "sg:postcode":"27127",
    "sg:province":"NC",
    "sg:tags":[
        "painter"
    ],
    "wof:name":"S & S Painting Co",
    "wof:placetype":"venue"
},
  "geometry": {"coordinates":[-80.29246999999999,36.035983],"type":"Point"}
}