{
  "type": "Feature",
  "properties": {
    "addr:full":"302 Greenville Blvd SE Greenville NC 27858",
    "addr:housenumber":"302",
    "addr:postcode":"27858",
    "addr:street":"Greenville Blvd Se",
    "iso:country":"US",
    "sg:address":"302 Greenville Blvd SE",
    "sg:city":"Greenville",
    "sg:classifiers":[
        {
            "category":"Retail",
            "subcategory":"Laundry & Dry Cleaning",
            "type":"Services"
        },
        {
            "category":"Shopping",
            "subcategory":"Clothing, Apparel, & Fashions",
            "type":"Retail Goods"
        }
    ],
    "sg:phone":"+1 252 321 0111",
    "sg:postcode":"27858",
    "sg:province":"NC",
    "sg:tags":[
        "tailor"
    ],
    "wof:name":"B P's Alteration",
    "wof:placetype":"venue"
},
  "geometry": {"coordinates":[-77.37944,35.578664],"type":"Point"}
}