{
  "type": "Feature",
  "properties": {
    "addr:full":"2400 Queen City Dr Charlotte NC 28208",
    "addr:housenumber":"2400",
    "addr:postcode":"28208",
    "addr:street":"Queen City Dr",
    "iso:country":"US",
    "sg:address":"2400 Queen City Dr",
    "sg:city":"Charlotte",
    "sg:classifiers":[
        {
            "category":"Building & Trades",
            "subcategory":"Construction",
            "type":"Services"
        }
    ],
    "sg:phone":"+1 704 399 8317",
    "sg:postcode":"28208",
    "sg:province":"NC",
    "sg:tags":[
        "home",
        "builder"
    ],
    "sg:website":"www.jimwalterhomes.com",
    "wof:name":"Jim Walter Homes Inc",
    "wof:placetype":"venue"
},
  "geometry": {"coordinates":[-80.91043999999999,35.239611],"type":"Point"}
}