{
  "type": "Feature",
  "properties": {
    "iso:country":"US",
    "sg:address":"5606 E Independence Blvd",
    "sg:city":"Charlotte",
    "sg:classifiers":[
        {
            "category":"Personal",
            "subcategory":"Beauty Salon",
            "type":"Services"
        }
    ],
    "sg:phone":"+1 704 537 8482",
    "sg:postcode":"28212",
    "sg:province":"NC",
    "sg:tags":[
        "shop",
        "manicuring"
    ],
    "wof:name":"Roses Nails",
    "wof:placetype":"venue"
},
  "geometry": {"coordinates":[-80.754283,35.181219],"type":"Point"}
}