{
  "type": "Feature",
  "properties": {
    "iso:country":"US",
    "sg:address":"134 Medical Park Rd Ste 102",
    "sg:city":"Mooresville",
    "sg:classifiers":[
        {
            "category":"Health Services",
            "subcategory":"Clinic",
            "type":"Services"
        },
        {
            "category":"Health Services",
            "subcategory":"Medical Lab",
            "type":"Services"
        }
    ],
    "sg:phone":"+1 866 946 0261",
    "sg:postcode":"28117",
    "sg:province":"NC",
    "sg:tags":[
        "information",
        "aid",
        "welfare"
    ],
    "sg:website":"http://national.citysearch.com/profile/external/603803002/mooresville_nc/std_test_express_mooresville.html?publisher=yellowpages&reference_id=1&placement=ypwebsitemip",
    "wof:name":"STD Test Express Mooresville",
    "wof:placetype":"venue"
},
  "geometry": {"coordinates":[-80.85276,35.550702],"type":"Point"}
}