{
  "type": "Feature",
  "properties": {
    "iso:country":"US",
    "sg:address":"3806 S Church St",
    "sg:city":"Burlington",
    "sg:classifiers":[
        {
            "category":"Social Services",
            "subcategory":"Job Training",
            "type":"Services"
        }
    ],
    "sg:phone":"+1 336 278 8700",
    "sg:postcode":"27215",
    "sg:province":"NC",
    "sg:tags":[
        "rehabilitation"
    ],
    "wof:name":"Alamance Regional Medical Ctr",
    "wof:placetype":"venue"
},
  "geometry": {"coordinates":[-79.52866400000001,36.08054],"type":"Point"}
}