{
  "type": "Feature",
  "properties": {
    "iso:country":"US",
    "sg:address":"2812 Golden St",
    "sg:city":"Raleigh",
    "sg:classifiers":[
        {
            "category":"Retail",
            "subcategory":"Repair Shop",
            "type":"Services"
        }
    ],
    "sg:phone":"+1   ",
    "sg:postcode":"27610",
    "sg:province":"NC",
    "sg:tags":[
        "electrical"
    ],
    "wof:name":"Dobbin Appliance Repair Svc",
    "wof:placetype":"venue"
},
  "geometry": {"coordinates":[-78.621976,35.740488],"type":"Point"}
}