{
  "type": "Feature",
  "properties": {
    "iso:country":"US",
    "sg:address":"1 Edgewood Rd S",
    "sg:city":"Asheville",
    "sg:classifiers":[
        {
            "category":"Education",
            "subcategory":"Special Training",
            "type":"Public Place"
        }
    ],
    "sg:phone":"+1 828 274 5577",
    "sg:postcode":"28803",
    "sg:province":"NC",
    "wof:name":"Arden Reading Clinic",
    "wof:placetype":"venue"
},
  "geometry": {"coordinates":[-82.520939,35.538],"type":"Point"}
}