{
  "type": "Feature",
  "properties": {
    "iso:country":"US",
    "sg:address":"125 Nova Dr",
    "sg:city":"Morrisville",
    "sg:classifiers":[
        {
            "category":"Professional",
            "subcategory":"Detective & Security Services",
            "type":"Services"
        }
    ],
    "sg:phone":"+1 919 469 5992",
    "sg:postcode":"27560",
    "sg:province":"NC",
    "sg:tags":[
        "car",
        "armored"
    ],
    "wof:name":"Loomis Fargo & Co",
    "wof:placetype":"venue"
},
  "geometry": {"coordinates":[-78.813968,35.841935],"type":"Point"}
}