{
  "type": "Feature",
  "properties": {
    "iso:country":"US",
    "sg:address":"208 S Railroad St",
    "sg:city":"Magnolia",
    "sg:classifiers":[
        {
            "category":"Government",
            "subcategory":"Office",
            "type":"Public Place"
        }
    ],
    "sg:phone":"+1 910 289 2502",
    "sg:postcode":"28453",
    "sg:province":"NC",
    "sg:tags":[
        "village"
    ],
    "wof:name":"Magnolia EMS",
    "wof:placetype":"venue"
},
  "geometry": {"coordinates":[-78.054824,34.893531],"type":"Point"}
}