{
  "type": "Feature",
  "properties": {
    "addr:full":"7245 McTeal Pl Charlotte NC 28262",
    "addr:housenumber":"7245",
    "addr:postcode":"28262",
    "addr:street":"Mcteal Pl",
    "iso:country":"US",
    "sg:address":"7245 McTeal Pl",
    "sg:city":"Charlotte",
    "sg:classifiers":[
        {
            "category":"Building & Trades",
            "subcategory":"Landscaping Services",
            "type":"Services"
        }
    ],
    "sg:phone":"+1 704 599 1529",
    "sg:postcode":"28262",
    "sg:province":"NC",
    "wof:name":"Parris Lawn Maint",
    "wof:placetype":"venue"
},
  "geometry": {"coordinates":[-80.784279,35.294608],"type":"Point"}
}