{
  "type": "Feature",
  "properties": {
    "addr:full":"203 E Whitaker Mill Rd Raleigh NC 27608",
    "addr:housenumber":"203",
    "addr:postcode":"27608",
    "addr:street":"E Whitaker Mill Rd",
    "iso:country":"US",
    "sg:address":"203 E Whitaker Mill Rd",
    "sg:city":"Raleigh",
    "sg:classifiers":[
        {
            "category":"Personal",
            "subcategory":"Beauty Salon",
            "type":"Services"
        }
    ],
    "sg:phone":"+1 919 828 1008",
    "sg:postcode":"27608",
    "sg:province":"NC",
    "sg:tags":[
        "manicuring"
    ],
    "wof:name":"Barton Hayes Nails",
    "wof:placetype":"venue"
},
  "geometry": {"coordinates":[-78.63821799999999,35.80696],"type":"Point"}
}