{
  "type": "Feature",
  "properties": {
    "addr:full":"105 S Main St Robersonville NC 27871",
    "addr:housenumber":"105",
    "addr:postcode":"27871",
    "addr:street":"S Main St",
    "iso:country":"US",
    "sg:address":"105 S Main St",
    "sg:city":"Robersonville",
    "sg:classifiers":[
        {
            "category":"Personal",
            "subcategory":"Beauty Salon",
            "type":"Services"
        }
    ],
    "sg:phone":"+1 252 795 3992",
    "sg:postcode":"27871",
    "sg:province":"NC",
    "wof:name":"Clip & Curl Beauty Salon",
    "wof:placetype":"venue"
},
  "geometry": {"coordinates":[-77.25353800000001,35.824184],"type":"Point"}
}