{
  "type": "Feature",
  "properties": {
    "iso:country":"US",
    "sg:address":"635 Old Farm Rd",
    "sg:city":"Garysburg",
    "sg:classifiers":[
        {
            "category":"Airport",
            "type":"Transportation"
        }
    ],
    "sg:phone":"+1 252 535 4884",
    "sg:postcode":"27801",
    "sg:province":"NC",
    "wof:name":"Gaston Airport",
    "wof:placetype":"venue"
},
  "geometry": {"coordinates":[-77.723451,35.91323],"type":"Point"}
}