{
  "type": "Feature",
  "properties": {
    "addr:full":"2704 L D Parker Dr Charlotte NC 28206",
    "addr:housenumber":"2704 l d",
    "addr:postcode":"28206",
    "addr:street":"Parker Dr",
    "iso:country":"US",
    "sg:address":"2704 L D Parker Dr",
    "sg:city":"Charlotte",
    "sg:classifiers":[
        {
            "category":"Professional",
            "type":"Services"
        }
    ],
    "sg:phone":"+1 704 338 1796",
    "sg:postcode":"28206",
    "sg:province":"NC",
    "sg:tags":[
        "establishment"
    ],
    "wof:name":"D G Intl",
    "wof:placetype":"venue"
},
  "geometry": {"coordinates":[-80.835995,35.257542],"type":"Point"}
}