{
  "type": "Feature",
  "properties": {
    "iso:country":"US",
    "sg:address":"2365 Hickory Forest Dr",
    "sg:city":"Asheboro",
    "sg:classifiers":[
        {
            "category":"Professional",
            "subcategory":"Accounting & Tax Preparation",
            "type":"Services"
        }
    ],
    "sg:phone":"+1   ",
    "sg:postcode":"27203",
    "sg:province":"NC",
    "wof:name":"Williamson Bookkeeping Tax Svc",
    "wof:placetype":"venue"
},
  "geometry": {"coordinates":[-79.80256300000001,35.768374],"type":"Point"}
}