{
  "type": "Feature",
  "properties": {
    "iso:country":"US",
    "sg:address":"4649 Highlake Dr",
    "sg:city":"Charlotte",
    "sg:classifiers":[
        {
            "category":"Personal",
            "type":"Services"
        }
    ],
    "sg:phone":"+1 704 713 1969",
    "sg:postcode":"28215",
    "sg:province":"NC",
    "sg:tags":[
        "butlers'",
        "maids'"
    ],
    "wof:name":"Macon Magic Maid",
    "wof:placetype":"venue"
},
  "geometry": {"coordinates":[-80.771103,35.254232],"type":"Point"}
}