{
  "type": "Feature",
  "properties": {
    "iso:country":"US",
    "sg:address":"6028 Fairhaven Dr",
    "sg:city":"Charlotte",
    "sg:classifiers":[
        {
            "category":"Professional",
            "type":"Services"
        }
    ],
    "sg:phone":"+1 704 597 8654",
    "sg:postcode":"28213",
    "sg:province":"NC",
    "sg:tags":[
        "establishment"
    ],
    "wof:name":"Fairhaven Hickory Grove",
    "wof:placetype":"venue"
},
  "geometry": {"coordinates":[-80.753169,35.268316],"type":"Point"}
}