{
  "type": "Feature",
  "properties": {
    "addr:full":"707 W Barbee St Exd Zebulon NC 27597",
    "addr:housenumber":"707",
    "addr:postcode":"27597",
    "addr:street":"W Barbee St Exd",
    "iso:country":"US",
    "sg:address":"707 W Barbee St Exd",
    "sg:city":"Zebulon",
    "sg:classifiers":[
        {
            "category":"Retail",
            "subcategory":"Laundry & Dry Cleaning",
            "type":"Services"
        }
    ],
    "sg:phone":"+1 919 404 2388",
    "sg:postcode":"27597",
    "sg:province":"NC",
    "sg:tags":[
        "cleaners",
        "rug",
        "carpet"
    ],
    "wof:name":"Adams Carpet & Upholstery",
    "wof:placetype":"venue"
},
  "geometry": {"coordinates":[-78.3254,35.811989],"type":"Point"}
}