{
  "type": "Feature",
  "properties": {
    "iso:country":"US",
    "sg:address":"171 Kings Rd",
    "sg:city":"Kings Mountain",
    "sg:classifiers":[
        {
            "category":"Professional",
            "type":"Services"
        }
    ],
    "sg:phone":"+1 704 730 9100",
    "sg:postcode":"28086",
    "sg:province":"NC",
    "sg:tags":[
        "establishment"
    ],
    "wof:name":"Control Tek Inc",
    "wof:placetype":"venue"
},
  "geometry": {"coordinates":[-81.32753099999999,35.268462],"type":"Point"}
}