{
  "type": "Feature",
  "properties": {
    "iso:country":"US",
    "sg:address":"18726 Nautical Dr",
    "sg:city":"Cornelius",
    "sg:classifiers":[
        {
            "category":"Professional",
            "subcategory":"Business Services",
            "type":"Services"
        }
    ],
    "sg:phone":"+1   ",
    "sg:postcode":"28031",
    "sg:province":"NC",
    "wof:name":"Kyle Lb Assoc Intl",
    "wof:placetype":"venue"
},
  "geometry": {"coordinates":[-80.893148,35.461183],"type":"Point"}
}