{
  "type": "Feature",
  "properties": {
    "iso:country":"US",
    "sg:address":"301 Smokey Park Hwy",
    "sg:city":"Asheville",
    "sg:classifiers":[
        {
            "category":"Restaurant",
            "type":"Food & Drink"
        }
    ],
    "sg:phone":"+1 828 667 2257",
    "sg:postcode":"28806",
    "sg:province":"NC",
    "wof:name":"Sub Station II",
    "wof:placetype":"venue"
},
  "geometry": {"coordinates":[-82.635807,35.560593],"type":"Point"}
}