{
  "type": "Feature",
  "properties": {
    "iso:country":"US",
    "sg:address":"240 Shadowline Dr",
    "sg:city":"Boone",
    "sg:classifiers":[
        {
            "category":"Restaurant",
            "type":"Food & Drink"
        }
    ],
    "sg:phone":"+1 828 262 1250",
    "sg:postcode":"28607",
    "sg:province":"NC",
    "sg:website":"www.peppers-restaurant.com",
    "wof:name":"Pepper's",
    "wof:placetype":"venue"
},
  "geometry": {"coordinates":[-81.658506,36.204003],"type":"Point"}
}