{
  "type": "Feature",
  "properties": {
    "addr:full":"204 E Fairview Dr Oxford NC 27565",
    "addr:housenumber":"204",
    "addr:postcode":"27565",
    "addr:street":"E Fairview Dr",
    "iso:country":"US",
    "sg:address":"204 E Fairview Dr",
    "sg:city":"Oxford",
    "sg:classifiers":[
        {
            "category":"Real Estate",
            "subcategory":"Surveying",
            "type":"Services"
        }
    ],
    "sg:phone":"+1 919 690 0172",
    "sg:postcode":"27565",
    "sg:province":"NC",
    "sg:tags":[
        "surveyor"
    ],
    "wof:name":"Ben Gentry Land Surveyor",
    "wof:placetype":"venue"
},
  "geometry": {"coordinates":[-78.59961699999999,36.308792],"type":"Point"}
}