{
  "type": "Feature",
  "properties": {
    "addr:full":"4121 New Bern Ave Raleigh NC 27610",
    "addr:housenumber":"4121",
    "addr:postcode":"27610",
    "addr:street":"New Bern Ave",
    "iso:country":"US",
    "sg:address":"4121 New Bern Ave",
    "sg:city":"Raleigh",
    "sg:classifiers":[
        {
            "category":"Restaurant",
            "type":"Food & Drink"
        }
    ],
    "sg:menulink":"http://www.allmenus.com/nc/st-matthews/228804-jersey-mikes/menu/",
    "sg:phone":"+1 919 231 0070",
    "sg:postcode":"27610",
    "sg:province":"NC",
    "sg:tags":[
        "american",
        "sandwich"
    ],
    "wof:name":"Jersey Mike's",
    "wof:placetype":"venue"
},
  "geometry": {"coordinates":[-78.567121,35.799149],"type":"Point"}
}