{
  "type": "Feature",
  "properties": {
    "iso:country":"US",
    "sg:address":"1802 Old Firetower Rd",
    "sg:city":"Greenville",
    "sg:classifiers":[
        {
            "category":"Recreation",
            "type":"Entertainment"
        }
    ],
    "sg:phone":"+1 252 321 7264",
    "sg:postcode":"27858",
    "sg:province":"NC",
    "sg:tags":[
        "instruction",
        "gymnastic"
    ],
    "sg:website":"www.rosesgymnastics.com",
    "wof:name":"Roses Gymnastics Training Ctr",
    "wof:placetype":"venue"
},
  "geometry": {"coordinates":[-77.356983,35.562891],"type":"Point"}
}