{
  "type": "Feature",
  "properties": {
    "addr:full":"101 Reddick Rd Asheville NC 28805",
    "addr:housenumber":"101",
    "addr:postcode":"28805",
    "addr:street":"Reddick Rd",
    "iso:country":"US",
    "sg:address":"101 Reddick Rd",
    "sg:city":"Asheville",
    "sg:classifiers":[
        {
            "category":"Professional",
            "subcategory":"Computer Services",
            "type":"Services"
        }
    ],
    "sg:phone":"+1 828 299 7950",
    "sg:postcode":"28805",
    "sg:province":"NC",
    "wof:name":"EMS Inc",
    "wof:placetype":"venue"
},
  "geometry": {"coordinates":[-82.473924,35.583903],"type":"Point"}
}