{
  "type": "Feature",
  "properties": {
    "iso:country":"US",
    "sg:address":"623 Washington St",
    "sg:city":"Washington",
    "sg:classifiers":[
        {
            "category":"Shopping",
            "subcategory":"Beauty & Cosmetics",
            "type":"Retail Goods"
        }
    ],
    "sg:phone":"+1 252 946 2235",
    "sg:postcode":"27889",
    "sg:province":"NC",
    "sg:tags":[
        "merchandise"
    ],
    "wof:name":"Merle Norma Cosmetics",
    "wof:placetype":"venue"
},
  "geometry": {"coordinates":[-77.05878300000001,35.552598],"type":"Point"}
}