{
  "type": "Feature",
  "properties": {
    "addr:full":"78 Burgin St Marion NC 28752",
    "addr:housenumber":"78",
    "addr:postcode":"28752",
    "addr:street":"Burgin St",
    "iso:country":"US",
    "sg:address":"78 Burgin St",
    "sg:city":"Marion",
    "sg:classifiers":[
        {
            "category":"Autos & Motor Vehicles",
            "subcategory":"Fuel & Gas Station",
            "type":"Retail Goods"
        }
    ],
    "sg:phone":"+1 828 659 9928",
    "sg:postcode":"28752",
    "sg:province":"NC",
    "sg:tags":[
        "station",
        "gasoline"
    ],
    "wof:name":"Sugarhill Rest & Trck Stop",
    "wof:placetype":"venue"
},
  "geometry": {"coordinates":[-82.011838,35.681805],"type":"Point"}
}