{
  "type": "Feature",
  "properties": {
    "iso:country":"US",
    "sg:address":"1003 Sutton Rd",
    "sg:city":"Greensboro",
    "sg:classifiers":[
        {
            "category":"Building & Trades",
            "subcategory":"Construction",
            "type":"Services"
        }
    ],
    "sg:phone":"+1 336 674 7379",
    "sg:postcode":"27406",
    "sg:province":"NC",
    "sg:tags":[
        "house"
    ],
    "wof:name":"Keen Enterprises",
    "wof:placetype":"venue"
},
  "geometry": {"coordinates":[-79.813023,35.966344],"type":"Point"}
}