{
  "type": "Feature",
  "properties": {
    "iso:country":"US",
    "sg:address":"128 Steeplechase Way",
    "sg:city":"Southern Pines",
    "sg:classifiers":[
        {
            "category":"Professional",
            "subcategory":"Management & Consulting",
            "type":"Services"
        }
    ],
    "sg:phone":"+1   ",
    "sg:postcode":"28387",
    "sg:province":"NC",
    "wof:name":"Keen Asset Management Inc",
    "wof:placetype":"venue"
},
  "geometry": {"coordinates":[-79.42160199999999,35.213032],"type":"Point"}
}