{
  "type": "Feature",
  "properties": {
    "addr:full":"289 W Palmer St Franklin NC 28734",
    "addr:housenumber":"289",
    "addr:postcode":"nc 28734",
    "addr:street":"W Palmer St",
    "iso:country":"US",
    "sg:address":"289 W Palmer St",
    "sg:city":"Franklin",
    "sg:classifiers":[
        {
            "category":"Autos & Motor Vehicles",
            "subcategory":"Automobile Sales",
            "type":"Retail Goods"
        }
    ],
    "sg:phone":"+1 828 369 1107",
    "sg:postcode":"28734",
    "sg:province":"NC",
    "sg:tags":[
        "car",
        "dealer"
    ],
    "wof:name":"D S Eprformance Inc",
    "wof:placetype":"venue"
},
  "geometry": {"coordinates":[-83.390708,35.178757],"type":"Point"}
}