{
  "type": "Feature",
  "properties": {
    "iso:country":"US",
    "sg:address":"2406 Blue Ridge Rd",
    "sg:city":"Raleigh",
    "sg:classifiers":[
        {
            "category":"Health Services",
            "subcategory":"Doctor",
            "type":"Services"
        }
    ],
    "sg:phone":"+1 919 789 4322",
    "sg:postcode":"27607",
    "sg:province":"NC",
    "sg:tags":[
        "physician",
        "surgeon"
    ],
    "wof:name":"After Hours Pediatrics",
    "wof:placetype":"venue"
},
  "geometry": {"coordinates":[-78.70534499999999,35.814324],"type":"Point"}
}