{
  "type": "Feature",
  "properties": {
    "iso:country":"US",
    "sg:address":"517 Coke Ave",
    "sg:city":"Edenton",
    "sg:classifiers":[
        {
            "category":"Personal",
            "type":"Services"
        }
    ],
    "sg:phone":"+1 252 482 1978",
    "sg:postcode":"27932",
    "sg:province":"NC",
    "sg:tags":[
        "therapist",
        "massage"
    ],
    "wof:name":"Life's Balance Massage Therapy",
    "wof:placetype":"venue"
},
  "geometry": {"coordinates":[-76.59760900000001,36.068774],"type":"Point"}
}