{
  "type": "Feature",
  "properties": {
    "iso:country":"US",
    "sg:address":"1210 Gordon St",
    "sg:city":"Charlotte",
    "sg:classifiers":[
        {
            "category":"Taxi",
            "type":"Transportation"
        }
    ],
    "sg:phone":"+1 704 596 1221",
    "sg:postcode":"28205",
    "sg:province":"NC",
    "sg:tags":[
        "taxicab"
    ],
    "wof:name":"Mexicar Cab Service",
    "wof:placetype":"venue"
},
  "geometry": {"coordinates":[-80.813436,35.219934],"type":"Point"}
}