{
  "type": "Feature",
  "properties": {
    "iso:country":"US",
    "sg:address":"10102 S Main St",
    "sg:city":"Archdale",
    "sg:classifiers":[
        {
            "category":"Sports & Exercise",
            "subcategory":"Gym",
            "type":"Entertainment"
        }
    ],
    "sg:phone":"+1 336 434 2625",
    "sg:postcode":"27263",
    "sg:province":"NC",
    "sg:tags":[
        "club",
        "health",
        "studio",
        "gymnasium"
    ],
    "wof:name":"Curves For Women",
    "wof:placetype":"venue"
},
  "geometry": {"coordinates":[-79.94913699999999,35.90144],"type":"Point"}
}