{
  "type": "Feature",
  "properties": {
    "iso:country":"US",
    "sg:address":"3948 Biggerstaff Rd",
    "sg:city":"Maiden",
    "sg:classifiers":[
        {
            "category":"Retail",
            "subcategory":"Animal Services",
            "type":"Services"
        }
    ],
    "sg:phone":"+1 828 428 3195",
    "sg:postcode":"28650",
    "sg:province":"NC",
    "sg:tags":[
        "boarding"
    ],
    "wof:name":"Ronald E Austin",
    "wof:placetype":"venue"
},
  "geometry": {"coordinates":[-81.25725199999999,35.554179],"type":"Point"}
}