{
  "type": "Feature",
  "properties": {
    "iso:country":"US",
    "sg:address":"5111 Cheviot Rd",
    "sg:city":"Charlotte",
    "sg:classifiers":[
        {
            "category":"Organizations",
            "subcategory":"Religious Organization",
            "type":"Services"
        }
    ],
    "sg:phone":"+1   ",
    "sg:postcode":"28269",
    "sg:province":"NC",
    "wof:name":"Bethel Korean Church",
    "wof:placetype":"venue"
},
  "geometry": {"coordinates":[-80.814792,35.289482],"type":"Point"}
}