{
  "type": "Feature",
  "properties": {
    "addr:full":"2100 Whitley Rd Middlesex NC 27557",
    "addr:housenumber":"2100",
    "addr:postcode":"27557",
    "addr:street":"Whitley Rd",
    "iso:country":"US",
    "sg:address":"2100 Whitley Rd",
    "sg:city":"Middlesex",
    "sg:classifiers":[
        {
            "category":"Food & Beverages",
            "subcategory":"Groceries & Convenience Stores",
            "type":"Retail Goods"
        }
    ],
    "sg:phone":"+1 919 284 9077",
    "sg:postcode":"27557",
    "sg:province":"NC",
    "wof:name":"Shot Shell Inc",
    "wof:placetype":"venue"
},
  "geometry": {"coordinates":[-78.220769,35.723238],"type":"Point"}
}