{
  "type": "Feature",
  "properties": {
    "addr:full":"1726 Davie Ave Statesville NC 28677",
    "addr:housenumber":"1726",
    "addr:postcode":"28677",
    "addr:street":"Davie Ave",
    "iso:country":"US",
    "sg:address":"1726 Davie Ave",
    "sg:city":"Statesville",
    "sg:classifiers":[
        {
            "category":"Health Services",
            "subcategory":"Doctor",
            "type":"Services"
        }
    ],
    "sg:phone":"+1   ",
    "sg:postcode":"28677",
    "sg:province":"NC",
    "sg:tags":[
        "medical"
    ],
    "wof:name":"Cochran W Gerald MD Facs",
    "wof:placetype":"venue"
},
  "geometry": {"coordinates":[-80.862317,35.801503],"type":"Point"}
}