{
  "type": "Feature",
  "properties": {
    "iso:country":"US",
    "sg:address":"6430 W Sugar Creek Rd",
    "sg:city":"Charlotte",
    "sg:classifiers":[
        {
            "category":"Shopping",
            "subcategory":"Florist",
            "type":"Retail Goods"
        }
    ],
    "sg:phone":"+1 704 509 0289",
    "sg:postcode":"28269",
    "sg:province":"NC",
    "wof:name":"Flowers & Plants Express",
    "wof:placetype":"venue"
},
  "geometry": {"coordinates":[-80.79781699999999,35.335266],"type":"Point"}
}