{
  "type": "Feature",
  "properties": {
    "iso:country":"US",
    "sg:address":"4317 Dinglewood Ave",
    "sg:city":"Charlotte",
    "sg:classifiers":[
        {
            "category":"Building & Trades",
            "subcategory":"Electrical",
            "type":"Services"
        }
    ],
    "sg:phone":"+1 704 333 8513",
    "sg:postcode":"28205",
    "sg:province":"NC",
    "sg:tags":[
        "electrical",
        "electric",
        "contractor"
    ],
    "wof:name":"Willie Morris Electric Company",
    "wof:placetype":"venue"
},
  "geometry": {"coordinates":[-80.783418,35.249864],"type":"Point"}
}