{
  "type": "Feature",
  "properties": {
    "iso:country":"US",
    "sg:address":"302 S 10th St",
    "sg:city":"Wilmington",
    "sg:classifiers":[
        {
            "category":"Government",
            "subcategory":"Office",
            "type":"Public Place"
        }
    ],
    "sg:phone":"+1 910 341 7872",
    "sg:postcode":"28401",
    "sg:province":"NC",
    "sg:tags":[
        "village"
    ],
    "wof:name":"Wilmington Boxing Ctr",
    "wof:placetype":"venue"
},
  "geometry": {"coordinates":[-77.935936,34.228779],"type":"Point"}
}