{
  "type": "Feature",
  "properties": {
    "addr:full":"16356 Highway 17 N Rocky Point NC 28457",
    "addr:housenumber":"16356",
    "addr:postcode":"28457",
    "addr:street":"Highway 17 N",
    "iso:country":"US",
    "sg:address":"16356 Highway 17 N",
    "sg:city":"Rocky Point",
    "sg:classifiers":[
        {
            "category":"Retail",
            "subcategory":"Pet Boarding",
            "type":"Services"
        }
    ],
    "sg:phone":"+1 910 270 4970",
    "sg:postcode":"28457",
    "sg:province":"NC",
    "sg:tags":[
        "boarding/pet",
        "sitting"
    ],
    "wof:name":"Four Paws and Claws",
    "wof:placetype":"venue"
},
  "geometry": {"coordinates":[-77.89569899999999,34.430401],"type":"Point"}
}