{
  "type": "Feature",
  "properties": {
    "addr:full":"1314 Raeford Rd Fayetteville NC 28305",
    "addr:housenumber":"1314",
    "addr:postcode":"28305",
    "addr:street":"Raeford Rd",
    "iso:country":"US",
    "sg:address":"1314 Raeford Rd",
    "sg:city":"Fayetteville",
    "sg:classifiers":[
        {
            "category":"Professional",
            "type":"Services"
        }
    ],
    "sg:phone":"+1 910 223 7874",
    "sg:postcode":"28305",
    "sg:province":"NC",
    "sg:tags":[
        "writer"
    ],
    "wof:name":"A Hinek",
    "wof:placetype":"venue"
},
  "geometry": {"coordinates":[-78.901337,35.055211],"type":"Point"}
}