{
  "type": "Feature",
  "properties": {
    "iso:country":"US",
    "sg:address":"129 Williamson Rd",
    "sg:city":"Mooresville",
    "sg:classifiers":[
        {
            "category":"Personal",
            "subcategory":"Hair Removal",
            "type":"Services"
        }
    ],
    "sg:phone":"+1 704 799 2843",
    "sg:postcode":"28117",
    "sg:province":"NC",
    "sg:tags":[
        "removing"
    ],
    "wof:name":"New Image Hair Removal",
    "wof:placetype":"venue"
},
  "geometry": {"coordinates":[-80.86965600000001,35.593516],"type":"Point"}
}