{
  "type": "Feature",
  "properties": {
    "iso:country":"US",
    "sg:address":"2362 Garnett St",
    "sg:city":"Henderson",
    "sg:classifiers":[
        {
            "category":"Restaurant",
            "type":"Food & Drink"
        }
    ],
    "sg:phone":"+1 252 438 5228",
    "sg:postcode":"27537",
    "sg:province":"NC",
    "wof:name":"Forsyth's Bar-B-Q",
    "wof:placetype":"venue"
},
  "geometry": {"coordinates":[-78.37978099999999,36.350146],"type":"Point"}
}