{
  "type": "Feature",
  "properties": {
    "addr:full":"6322 Halifax Rd Conover NC 28613",
    "addr:housenumber":"6322",
    "addr:postcode":"28613",
    "addr:street":"Halifax Rd",
    "iso:country":"US",
    "sg:address":"6322 Halifax Rd",
    "sg:city":"Conover",
    "sg:classifiers":[
        {
            "category":"Banks & Credit Unions",
            "subcategory":"Financial Services",
            "type":"Services"
        }
    ],
    "sg:phone":"+1 828 256 5455",
    "sg:postcode":"28613",
    "sg:province":"NC",
    "sg:tags":[
        "investor"
    ],
    "wof:name":"Generation IV",
    "wof:placetype":"venue"
},
  "geometry": {"coordinates":[-81.226578,35.806817],"type":"Point"}
}