{
  "type": "Feature",
  "properties": {
    "iso:country":"US",
    "sg:address":"529 S New Hope Rd",
    "sg:city":"Gastonia",
    "sg:classifiers":[
        {
            "category":"Banks & Credit Unions",
            "subcategory":"Bank",
            "type":"Services"
        }
    ],
    "sg:phone":"+1 704 865 1233",
    "sg:postcode":"28054",
    "sg:province":"NC",
    "sg:tags":[
        "national",
        "commercial"
    ],
    "wof:name":"First National Bank",
    "wof:placetype":"venue"
},
  "geometry": {"coordinates":[-81.14985299999999,35.257559],"type":"Point"}
}