{
  "type": "Feature",
  "properties": {
    "iso:country":"US",
    "sg:address":"13222 Ferguson Forest Dr",
    "sg:city":"Charlotte",
    "sg:classifiers":[
        {
            "category":"Community Center",
            "subcategory":"Youth",
            "type":"Public Place"
        }
    ],
    "sg:phone":"+1 704 688 9532",
    "sg:postcode":"28273",
    "sg:province":"NC",
    "wof:name":"Big Girls Venture",
    "wof:placetype":"venue"
},
  "geometry": {"coordinates":[-80.985039,35.113602],"type":"Point"}
}