{
  "type": "Feature",
  "properties": {
    "addr:full":"3993 York Hwy Gastonia NC 28052",
    "addr:housenumber":"3993",
    "addr:postcode":"28052",
    "addr:street":"York Hwy",
    "iso:country":"US",
    "sg:address":"3993 York Hwy",
    "sg:city":"Gastonia",
    "sg:classifiers":[
        {
            "category":"Home & Garden",
            "subcategory":"Furniture",
            "type":"Retail Goods"
        }
    ],
    "sg:phone":"+1 704 852 9478",
    "sg:postcode":"28052",
    "sg:province":"NC",
    "wof:name":"All Good Furniture",
    "wof:placetype":"venue"
},
  "geometry": {"coordinates":[-81.20356099999999,35.209411],"type":"Point"}
}