{
  "type": "Feature",
  "properties": {
    "addr:full":"103 W Main St Elkin NC 28621",
    "addr:housenumber":"103",
    "addr:postcode":"28621",
    "addr:street":"W Main St",
    "iso:country":"US",
    "sg:address":"103 W Main St",
    "sg:city":"Elkin",
    "sg:classifiers":[
        {
            "category":"Organizations",
            "subcategory":"Membership Organization",
            "type":"Services"
        }
    ],
    "sg:phone":"+1 336 835 7909",
    "sg:postcode":"28621",
    "sg:province":"NC",
    "wof:name":"Hospital Auxiliary Thrift Shop",
    "wof:placetype":"venue"
},
  "geometry": {"coordinates":[-80.85074400000001,36.24397],"type":"Point"}
}