{
  "type": "Feature",
  "properties": {
    "addr:full":"3704 Clinton Rd Fayetteville NC 28312",
    "addr:housenumber":"3704",
    "addr:postcode":"28312",
    "addr:street":"Clinton Rd",
    "iso:country":"US",
    "sg:address":"3704 Clinton Rd",
    "sg:city":"Fayetteville",
    "sg:classifiers":[
        {
            "category":"Wholesale",
            "subcategory":"Hardware",
            "type":"Manufacturing & Wholesale Goods"
        }
    ],
    "sg:phone":"+1 910 484 5990",
    "sg:postcode":"28312",
    "sg:province":"NC",
    "sg:tags":[
        "plumbing",
        "fixture",
        "supply"
    ],
    "wof:name":"Hughes Supply Inc",
    "wof:placetype":"venue"
},
  "geometry": {"coordinates":[-78.790218,35.031819],"type":"Point"}
}