{
  "type": "Feature",
  "properties": {
    "iso:country":"US",
    "sg:address":"3071 Cutrite",
    "sg:city":"Claremont",
    "sg:classifiers":[
        {
            "category":"Wholesale",
            "subcategory":"Furniture",
            "type":"Manufacturing & Wholesale Goods"
        }
    ],
    "sg:phone":"+1 828 459 9510",
    "sg:postcode":"28610",
    "sg:province":"NC",
    "wof:name":"Clairmont Furniture",
    "wof:placetype":"venue"
},
  "geometry": {"coordinates":[-81.15213,35.711594],"type":"Point"}
}