{
  "type": "Feature",
  "properties": {
    "addr:full":"505 Rudy Dr Clayton NC 27520",
    "addr:housenumber":"505",
    "addr:postcode":"27520",
    "addr:street":"Rudy Dr",
    "iso:country":"US",
    "sg:address":"505 Rudy Dr",
    "sg:city":"Clayton",
    "sg:classifiers":[
        {
            "category":"Shopping",
            "subcategory":"Gifts & Souvenirs",
            "type":"Retail Goods"
        }
    ],
    "sg:phone":"+1 919 209 5277",
    "sg:postcode":"27520",
    "sg:province":"NC",
    "wof:name":"Marcelletta S Creati",
    "wof:placetype":"venue"
},
  "geometry": {"coordinates":[-78.54455299999999,35.559085],"type":"Point"}
}