{
  "type": "Feature",
  "properties": {
    "addr:full":"7912 Oneal Rd Raleigh NC 27613",
    "addr:housenumber":"7912",
    "addr:postcode":"27613",
    "addr:street":"Oneal Rd",
    "iso:country":"US",
    "sg:address":"7912 Oneal Rd",
    "sg:city":"Raleigh",
    "sg:classifiers":[
        {
            "category":"Professional",
            "subcategory":"Computer Services",
            "type":"Services"
        }
    ],
    "sg:phone":"+1   ",
    "sg:postcode":"27613",
    "sg:province":"NC",
    "sg:tags":[
        "related"
    ],
    "wof:name":"Trak 5 Inc",
    "wof:placetype":"venue"
},
  "geometry": {"coordinates":[-78.725573,35.891401],"type":"Point"}
}