{
  "type": "Feature",
  "properties": {
    "iso:country":"US",
    "sg:address":"177 Sparrow Ln",
    "sg:city":"Statesville",
    "sg:classifiers":[
        {
            "category":"Professional",
            "type":"Services"
        }
    ],
    "sg:phone":"+1 704 873 4828",
    "sg:postcode":"28625",
    "sg:province":"NC",
    "sg:tags":[
        "establishment"
    ],
    "wof:name":"Aunt Nanny's Livermush",
    "wof:placetype":"venue"
},
  "geometry": {"coordinates":[-80.808183,35.820484],"type":"Point"}
}