{
  "type": "Feature",
  "properties": {
    "iso:country":"US",
    "sg:address":"103 S Green St",
    "sg:city":"Morganton",
    "sg:classifiers":[
        {
            "category":"Restaurant",
            "type":"Food & Drink"
        }
    ],
    "sg:phone":"+1 828 438 2284",
    "sg:postcode":"28655",
    "sg:province":"NC",
    "wof:name":"Piccolo's",
    "wof:placetype":"venue"
},
  "geometry": {"coordinates":[-81.687372,35.746246],"type":"Point"}
}