{
  "type": "Feature",
  "properties": {
    "addr:full":"871 Harp St Raleigh NC 27604",
    "addr:housenumber":"871",
    "addr:postcode":"27604",
    "addr:street":"Harp St",
    "iso:country":"US",
    "sg:address":"871 Harp St",
    "sg:city":"Raleigh",
    "sg:classifiers":[
        {
            "category":"Education",
            "subcategory":"Special Training",
            "type":"Public Place"
        }
    ],
    "sg:phone":"+1 919 834 5663",
    "sg:postcode":"27604",
    "sg:province":"NC",
    "sg:tags":[
        "center"
    ],
    "wof:name":"Communities In Schools",
    "wof:placetype":"venue"
},
  "geometry": {"coordinates":[-78.636833,35.790418],"type":"Point"}
}