{
  "type": "Feature",
  "properties": {
    "addr:full":"2203 Cothran Rd Rougemont NC 27572",
    "addr:housenumber":"2203",
    "addr:postcode":"27572",
    "addr:street":"Cothran Rd",
    "iso:country":"US",
    "sg:address":"2203 Cothran Rd",
    "sg:city":"Rougemont",
    "sg:classifiers":[
        {
            "category":"Building & Trades",
            "subcategory":"Construction",
            "type":"Services"
        }
    ],
    "sg:phone":"+1 919 477 9812",
    "sg:postcode":"27572",
    "sg:province":"NC",
    "wof:name":"JB Denby Grading Inc",
    "wof:placetype":"venue"
},
  "geometry": {"coordinates":[-78.943403,36.206278],"type":"Point"}
}