{
  "type": "Feature",
  "properties": {
    "iso:country":"US",
    "sg:address":"611 Biesecker Rd",
    "sg:city":"Lexington",
    "sg:classifiers":[
        {
            "category":"Personal",
            "subcategory":"Beauty Salon",
            "type":"Services"
        }
    ],
    "sg:phone":"+1 336 248 4793",
    "sg:postcode":"27295",
    "sg:province":"NC",
    "wof:name":"Charm Beauty Salon",
    "wof:placetype":"venue"
},
  "geometry": {"coordinates":[-80.276042,35.845092],"type":"Point"}
}