{
  "type": "Feature",
  "properties": {
    "iso:country":"US",
    "sg:address":"1421 Forest Acres Dr",
    "sg:city":"Greenville",
    "sg:classifiers":[
        {
            "category":"Professional",
            "subcategory":"Computer Services",
            "type":"Services"
        }
    ],
    "sg:phone":"+1   ",
    "sg:postcode":"27834",
    "sg:province":"NC",
    "sg:tags":[
        "related"
    ],
    "wof:name":"Image Ination Co",
    "wof:placetype":"venue"
},
  "geometry": {"coordinates":[-77.448471,35.611221],"type":"Point"}
}