{
  "type": "Feature",
  "properties": {
    "iso:country":"US",
    "sg:address":"2000 W 1st St",
    "sg:city":"Winston Salem",
    "sg:classifiers":[
        {
            "category":"Social Services",
            "subcategory":"Job Training",
            "type":"Services"
        }
    ],
    "sg:phone":"+1 336 748 0809",
    "sg:postcode":"27104",
    "sg:province":"NC",
    "sg:tags":[
        "career",
        "counseling",
        "vocational"
    ],
    "wof:name":"Dana Ann Hiatt",
    "wof:placetype":"venue"
},
  "geometry": {"coordinates":[-80.27291099999999,36.096404],"type":"Point"}
}