{
  "type": "Feature",
  "properties": {
    "iso:country":"US",
    "sg:address":"6112 Hardwood Ln",
    "sg:city":"Concord",
    "sg:classifiers":[
        {
            "category":"Building & Trades",
            "subcategory":"Construction",
            "type":"Services"
        }
    ],
    "sg:phone":"+1 704 721 6797",
    "sg:postcode":"28027",
    "sg:province":"NC",
    "sg:tags":[
        "contractor"
    ],
    "wof:name":"C & C Tile",
    "wof:placetype":"venue"
},
  "geometry": {"coordinates":[-80.679993,35.449463],"type":"Point"}
}