{
  "type": "Feature",
  "properties": {
    "addr:full":"3901 Pine Grove Cir Charlotte NC 28206",
    "addr:housenumber":"3901",
    "addr:postcode":"28206",
    "addr:street":"Pine Grove Cir",
    "iso:country":"US",
    "sg:address":"3901 Pine Grove Cir",
    "sg:city":"Charlotte",
    "sg:classifiers":[
        {
            "category":"Manufacturing",
            "subcategory":"Metals",
            "type":"Manufacturing & Wholesale Goods"
        },
        {
            "category":"Manufacturing",
            "subcategory":"Wood Products",
            "type":"Manufacturing & Wholesale Goods"
        }
    ],
    "sg:phone":"+1 704 597 1502",
    "sg:postcode":"28206",
    "sg:province":"NC",
    "sg:tags":[
        "spar",
        "sailboat",
        "mast",
        "mfg"
    ],
    "sg:website":"www.charlestonspar.com",
    "wof:name":"Charleston's Spar",
    "wof:placetype":"venue"
},
  "geometry": {"coordinates":[-80.808223,35.268515],"type":"Point"}
}