{
  "type": "Feature",
  "properties": {
    "addr:full":"601 N 8th St Smithfield NC 27577",
    "addr:housenumber":"601",
    "addr:postcode":"27577",
    "addr:street":"N 8Th St",
    "iso:country":"US",
    "sg:address":"601 N 8th St",
    "sg:city":"Smithfield",
    "sg:classifiers":[
        {
            "category":"Shopping",
            "subcategory":"Pharmacy",
            "type":"Retail Goods"
        }
    ],
    "sg:phone":"+1 919 934 2111",
    "sg:postcode":"27577",
    "sg:province":"NC",
    "wof:name":"Realo Discount Drugs",
    "wof:placetype":"venue"
},
  "geometry": {"coordinates":[-78.334419,35.51607],"type":"Point"}
}