{
  "type": "Feature",
  "properties": {
    "addr:full":"1001 Orangewood St Kannapolis NC 28081",
    "addr:housenumber":"1001",
    "addr:postcode":"28081",
    "addr:street":"Orangewood St",
    "iso:country":"US",
    "sg:address":"1001 Orangewood St",
    "sg:city":"Kannapolis",
    "sg:classifiers":[
        {
            "category":"Farming",
            "subcategory":"Livestock Farm",
            "type":"Manufacturing & Wholesale Goods"
        }
    ],
    "sg:phone":"+1 704 932 4619",
    "sg:postcode":"28081",
    "sg:province":"NC",
    "sg:tags":[
        "animal",
        "general"
    ],
    "wof:name":"Walter E Overcash",
    "wof:placetype":"venue"
},
  "geometry": {"coordinates":[-80.63924799999999,35.50387],"type":"Point"}
}