{
  "type": "Feature",
  "properties": {
    "iso:country":"US",
    "sg:address":"2079 Bella Bridge Rd",
    "sg:city":"Broadway",
    "sg:classifiers":[
        {
            "category":"Social Services",
            "subcategory":"Child Care",
            "type":"Services"
        },
        {
            "category":"Health Services",
            "subcategory":"Clinic",
            "type":"Services"
        }
    ],
    "sg:phone":"+1 919 498 0484",
    "sg:postcode":"27505",
    "sg:province":"NC",
    "sg:tags":[
        "home"
    ],
    "wof:name":"Shirley's Home Care Provider",
    "wof:placetype":"venue"
},
  "geometry": {"coordinates":[-79.040375,35.351059],"type":"Point"}
}