{
  "type": "Feature",
  "properties": {
    "iso:country":"US",
    "sg:address":"1117 Heron Pond Dr",
    "sg:city":"Chapel Hill",
    "sg:classifiers":[
        {
            "category":"Manufacturing",
            "subcategory":"Building Materials",
            "type":"Manufacturing & Wholesale Goods"
        }
    ],
    "sg:phone":"+1 919 967 8932",
    "sg:postcode":"27516",
    "sg:province":"NC",
    "sg:tags":[
        "mfg"
    ],
    "wof:name":"Michael Joerling",
    "wof:placetype":"venue"
},
  "geometry": {"coordinates":[-79.18124400000001,35.889206],"type":"Point"}
}