{
  "type": "Feature",
  "properties": {
    "iso:country":"US",
    "sg:address":"7 Park Ave",
    "sg:city":"Brevard",
    "sg:classifiers":[
        {
            "category":"Health Services",
            "subcategory":"Health Practitioner",
            "type":"Services"
        }
    ],
    "sg:phone":"+1 828 884 7750",
    "sg:postcode":"28712",
    "sg:province":"SC",
    "sg:tags":[
        "psychologist"
    ],
    "wof:name":"Lanier Psychological Assoc",
    "wof:placetype":"venue"
},
  "geometry": {"coordinates":[-82.727834,35.229459],"type":"Point"}
}