{
  "type": "Feature",
  "properties": {
    "addr:full":"121 Peacock Ave Lexington NC 27292",
    "addr:housenumber":"121",
    "addr:postcode":"27292",
    "addr:street":"Peacock Ave",
    "iso:country":"US",
    "sg:address":"121 Peacock Ave",
    "sg:city":"Lexington",
    "sg:classifiers":[
        {
            "category":"Building & Trades",
            "subcategory":"Plumbing",
            "type":"Services"
        }
    ],
    "sg:phone":"+1 336 859 3585",
    "sg:postcode":"27292",
    "sg:province":"NC",
    "sg:tags":[
        "heating",
        "contractor"
    ],
    "wof:name":"Wagoner Services Inc",
    "wof:placetype":"venue"
},
  "geometry": {"coordinates":[-80.275632,35.809313],"type":"Point"}
}