{
  "type": "Feature",
  "properties": {
    "addr:full":"5701 Turtle Cove Raleigh NC 27609",
    "addr:housenumber":"5701",
    "addr:postcode":"27609",
    "addr:street":"Turtle Cove",
    "iso:country":"US",
    "sg:address":"5701 Turtle Cove",
    "sg:city":"Raleigh",
    "sg:classifiers":[
        {
            "category":"Real Estate",
            "subcategory":"Real Estate Operator",
            "type":"Services"
        }
    ],
    "sg:phone":"+1 919 790 0290",
    "sg:postcode":"27609",
    "sg:province":"NC",
    "sg:tags":[
        "apartment"
    ],
    "wof:name":"Bridge Crossing",
    "wof:placetype":"venue"
},
  "geometry": {"coordinates":[-78.601833,35.857671],"type":"Point"}
}