{
  "type": "Feature",
  "properties": {
    "addr:full":"4279 Old US Hwy 29 Thomasville NC 27360",
    "addr:housenumber":"4279",
    "addr:postcode":"27360",
    "addr:street":"Old Us Hwy 29",
    "iso:country":"US",
    "sg:address":"4279 Old US Hwy 29",
    "sg:city":"Thomasville",
    "sg:classifiers":[
        {
            "category":"Food & Beverages",
            "subcategory":"Groceries & Convenience Stores",
            "type":"Retail Goods"
        }
    ],
    "sg:phone":"+1 336 475 4703",
    "sg:postcode":"27360",
    "sg:province":"NC",
    "wof:name":"Pilot",
    "wof:placetype":"venue"
},
  "geometry": {"coordinates":[-80.13547699999999,35.879173],"type":"Point"}
}