{
  "type": "Feature",
  "properties": {
    "addr:full":"730 Oak St Charlotte NC 28214",
    "addr:housenumber":"730",
    "addr:postcode":"28214",
    "addr:street":"Oak St",
    "iso:country":"US",
    "sg:address":"730 Oak St",
    "sg:city":"Charlotte",
    "sg:classifiers":[
        {
            "category":"Home & Garden",
            "subcategory":"Furniture",
            "type":"Retail Goods"
        }
    ],
    "sg:phone":"+1 704 399 1305",
    "sg:postcode":"28214",
    "sg:province":"NC",
    "sg:tags":[
        "wood",
        "cabinetry",
        "custom"
    ],
    "wof:name":"T H Custom Woods",
    "wof:placetype":"venue"
},
  "geometry": {"coordinates":[-80.920474,35.289587],"type":"Point"}
}