{
  "type": "Feature",
  "properties": {
    "iso:country":"US",
    "sg:address":"1041 Strickland Bridge Rd",
    "sg:city":"Fayetteville",
    "sg:classifiers":[
        {
            "category":"Professional",
            "subcategory":"Management & Consulting",
            "type":"Services"
        }
    ],
    "sg:phone":"+1 910 867 0080",
    "sg:postcode":"28304",
    "sg:province":"NC",
    "sg:tags":[
        "consultant",
        "training"
    ],
    "wof:name":"IDY Development Group",
    "wof:placetype":"venue"
},
  "geometry": {"coordinates":[-78.997287,35.039262],"type":"Point"}
}