{
  "type": "Feature",
  "properties": {
    "addr:full":"1468 W Corbett Ave Swansboro NC 28584",
    "addr:housenumber":"1468",
    "addr:postcode":"28584",
    "addr:street":"W Corbett Ave",
    "iso:country":"US",
    "sg:address":"1468 W Corbett Ave",
    "sg:city":"Swansboro",
    "sg:classifiers":[
        {
            "category":"Retail",
            "subcategory":"Veterinary Services",
            "type":"Services"
        }
    ],
    "sg:phone":"+1 910 326 8387",
    "sg:postcode":"28584",
    "sg:province":"NC",
    "sg:tags":[
        "veterinarian"
    ],
    "wof:name":"Swansboro Pet Care",
    "wof:placetype":"venue"
},
  "geometry": {"coordinates":[-77.160989,34.707145],"type":"Point"}
}