{
  "type": "Feature",
  "properties": {
    "iso:country":"US",
    "sg:address":"207 Orange St",
    "sg:city":"Henderson",
    "sg:classifiers":[
        {
            "category":"Organizations",
            "subcategory":"Community Association",
            "type":"Services"
        }
    ],
    "sg:phone":"+1   ",
    "sg:postcode":"27536",
    "sg:province":"NC",
    "wof:name":"Pines Carolina Girl S Council",
    "wof:placetype":"venue"
},
  "geometry": {"coordinates":[-78.40727099999999,36.326969],"type":"Point"}
}