{
  "type": "Feature",
  "properties": {
    "addr:full":"800 Eastway Dr Charlotte NC 28205",
    "addr:housenumber":"800",
    "addr:postcode":"28205",
    "addr:street":"Eastway Dr",
    "iso:country":"US",
    "sg:address":"800 Eastway Dr",
    "sg:city":"Charlotte",
    "sg:classifiers":[
        {
            "category":"Insurance",
            "subcategory":"Insurance Agent",
            "type":"Services"
        }
    ],
    "sg:phone":"+1 704 373 2929",
    "sg:postcode":"28205",
    "sg:province":"NC",
    "wof:name":"A Plus Insurance Agency",
    "wof:placetype":"venue"
},
  "geometry": {"coordinates":[-80.78100000000001,35.245765],"type":"Point"}
}