{
  "type": "Feature",
  "properties": {
    "addr:full":"251 Clarkann Dr Thomasville NC 27360",
    "addr:housenumber":"251",
    "addr:postcode":"27360",
    "addr:street":"Clarkann Dr",
    "iso:country":"US",
    "sg:address":"251 Clarkann Dr",
    "sg:city":"Thomasville",
    "sg:classifiers":[
        {
            "category":"Building & Trades",
            "subcategory":"Construction",
            "type":"Services"
        }
    ],
    "sg:phone":"+1 336 688 0677",
    "sg:postcode":"27360",
    "sg:province":"NC",
    "sg:tags":[
        "house"
    ],
    "wof:name":"Eagle USA Industries",
    "wof:placetype":"venue"
},
  "geometry": {"coordinates":[-80.175937,35.872275],"type":"Point"}
}