{
  "type": "Feature",
  "properties": {
    "addr:full":"152 Weaver Dairy Rd Chapel Hill NC 27514",
    "addr:housenumber":"152",
    "addr:postcode":"27514",
    "addr:street":"Weaver Dairy Rd",
    "iso:country":"US",
    "sg:address":"152 Weaver Dairy Rd",
    "sg:city":"Chapel Hill",
    "sg:classifiers":[
        {
            "category":"Building & Trades",
            "subcategory":"Construction",
            "type":"Services"
        }
    ],
    "sg:phone":"+1 919 929 3545",
    "sg:postcode":"27514",
    "sg:province":"NC",
    "sg:tags":[
        "repair",
        "contractor"
    ],
    "wof:name":"Birtchett Welding & Mch Svc",
    "wof:placetype":"venue"
},
  "geometry": {"coordinates":[-79.021547,35.954833],"type":"Point"}
}