{
  "type": "Feature",
  "properties": {
    "iso:country":"US",
    "sg:address":"5300 Apex Peakway",
    "sg:city":"Apex",
    "sg:classifiers":[
        {
            "category":"Building & Trades",
            "subcategory":"Construction",
            "type":"Services"
        }
    ],
    "sg:phone":"+1 919 303 5677",
    "sg:postcode":"27502",
    "sg:province":"NC",
    "sg:tags":[
        "general",
        "contractor"
    ],
    "wof:name":"Centurion Construction Co",
    "wof:placetype":"venue"
},
  "geometry": {"coordinates":[-78.86709999999999,35.737795],"type":"Point"}
}