{
  "type": "Feature",
  "properties": {
    "iso:country":"US",
    "sg:address":"119 Banks Bridge Rd",
    "sg:city":"Richlands",
    "sg:classifiers":[
        {
            "category":"Building & Trades",
            "subcategory":"Construction",
            "type":"Services"
        }
    ],
    "sg:phone":"+1 910 324 1748",
    "sg:postcode":"28574",
    "sg:province":"NC",
    "sg:tags":[
        "concrete",
        "contractor"
    ],
    "wof:name":"B & E Concrete",
    "wof:placetype":"venue"
},
  "geometry": {"coordinates":[-77.58424100000001,34.902289],"type":"Point"}
}