{
  "type": "Feature",
  "properties": {
    "iso:country":"US",
    "sg:address":"2612 Camden Rd",
    "sg:city":"Fayetteville",
    "sg:classifiers":[
        {
            "category":"Autos & Motor Vehicles",
            "subcategory":"Automobile Sales",
            "type":"Retail Goods"
        }
    ],
    "sg:phone":"+1 910 484 5123",
    "sg:postcode":"28306",
    "sg:province":"NC",
    "sg:tags":[
        "used"
    ],
    "wof:name":"Able Auto Sales",
    "wof:placetype":"venue"
},
  "geometry": {"coordinates":[-78.90779999999999,35.016904],"type":"Point"}
}