{
  "type": "Feature",
  "properties": {
    "addr:full":"2903 J Herbert Rd Fayetteville NC 28312",
    "addr:housenumber":"2903 j",
    "addr:postcode":"28312",
    "addr:street":"Herbert Rd",
    "iso:country":"US",
    "sg:address":"2903 J Herbert Rd",
    "sg:city":"Fayetteville",
    "sg:classifiers":[
        {
            "category":"Wholesale",
            "subcategory":"Electrical",
            "type":"Manufacturing & Wholesale Goods"
        }
    ],
    "sg:phone":"+1 910 483 7930",
    "sg:postcode":"28312",
    "sg:province":"NC",
    "sg:tags":[
        "appliance"
    ],
    "wof:name":"Elliott's Service",
    "wof:placetype":"venue"
},
  "geometry": {"coordinates":[-78.749398,35.09531],"type":"Point"}
}