{
  "type": "Feature",
  "properties": {
    "iso:country":"US",
    "sg:address":"5504 Farrell Rd",
    "sg:city":"Sanford",
    "sg:classifiers":[
        {
            "category":"Professional",
            "subcategory":"Art Services",
            "type":"Services"
        }
    ],
    "sg:phone":"+1   ",
    "sg:postcode":"27330",
    "sg:province":"NC",
    "sg:tags":[
        "sign",
        "graphics"
    ],
    "wof:name":"Trackside Graphics",
    "wof:placetype":"venue"
},
  "geometry": {"coordinates":[-79.132779,35.601825],"type":"Point"}
}