{
  "type": "Feature",
  "properties": {
    "iso:country":"US",
    "sg:address":"317 Quail Dr",
    "sg:city":"Raleigh",
    "sg:classifiers":[
        {
            "category":"Utilities",
            "subcategory":"Telephone",
            "type":"Services"
        }
    ],
    "sg:phone":"+1 919 821 1322",
    "sg:postcode":"27604",
    "sg:province":"NC",
    "sg:tags":[
        "communications"
    ],
    "wof:name":"William E Glaub",
    "wof:placetype":"venue"
},
  "geometry": {"coordinates":[-78.615172,35.802518],"type":"Point"}
}