{
  "type": "Feature",
  "properties": {
    "iso:country":"US",
    "sg:address":"3565 Gables Dr",
    "sg:city":"Fayetteville",
    "sg:classifiers":[
        {
            "category":"Professional",
            "subcategory":"Management & Consulting",
            "type":"Services"
        }
    ],
    "sg:phone":"+1   ",
    "sg:postcode":"28311",
    "sg:province":"NC",
    "sg:tags":[
        "medical"
    ],
    "wof:name":"Tcb Medical Consultants",
    "wof:placetype":"venue"
},
  "geometry": {"coordinates":[-78.884109,35.108793],"type":"Point"}
}