{
  "type": "Feature",
  "properties": {
    "iso:country":"US",
    "sg:address":"3126 Blue Ridge Rd",
    "sg:city":"Raleigh",
    "sg:classifiers":[
        {
            "category":"Health Services",
            "subcategory":"Doctor",
            "type":"Services"
        }
    ],
    "sg:phone":"+1 919 787 0486",
    "sg:postcode":"27612",
    "sg:province":"NC",
    "sg:tags":[
        "practice",
        "family"
    ],
    "sg:website":"www.cpgmd.com",
    "wof:name":"Capital Physicians Group PA",
    "wof:placetype":"venue"
},
  "geometry": {"coordinates":[-78.702698,35.821899],"type":"Point"}
}