{
  "type": "Feature",
  "properties": {
    "addr:full":"1822 Pickrell Rd Reidsville NC 27320",
    "addr:housenumber":"1822",
    "addr:postcode":"27320",
    "addr:street":"Pickrell Rd",
    "iso:country":"US",
    "sg:address":"1822 Pickrell Rd",
    "sg:city":"Reidsville",
    "sg:classifiers":[
        {
            "category":"Building & Trades",
            "subcategory":"Landscaping Services",
            "type":"Services"
        }
    ],
    "sg:phone":"+1 336 342 1643",
    "sg:postcode":"27320",
    "sg:province":"NC",
    "sg:tags":[
        "lawn",
        "maintenance",
        "grounds"
    ],
    "wof:name":"Deaton's Landscaping & Lawn",
    "wof:placetype":"venue"
},
  "geometry": {"coordinates":[-79.63266400000001,36.335081],"type":"Point"}
}