{
  "type": "Feature",
  "properties": {
    "iso:country":"US",
    "sg:address":"158 Leslie Ln",
    "sg:city":"Swansboro",
    "sg:classifiers":[
        {
            "category":"Real Estate",
            "subcategory":"Real Estate Agent",
            "type":"Services"
        }
    ],
    "sg:phone":"+1 910 326 5174",
    "sg:postcode":"28584",
    "sg:province":"NC",
    "sg:tags":[
        "appraiser"
    ],
    "wof:name":"Behan & Benedict Appraisers",
    "wof:placetype":"venue"
},
  "geometry": {"coordinates":[-77.15409699999999,34.706878],"type":"Point"}
}