{
  "type": "Feature",
  "properties": {
    "iso:country":"US",
    "sg:address":"5324 Sandstone Dr",
    "sg:city":"Fayetteville",
    "sg:classifiers":[
        {
            "category":"Building & Trades",
            "subcategory":"Landscaping Services",
            "type":"Services"
        }
    ],
    "sg:phone":"+1 910 488 6732",
    "sg:postcode":"28311",
    "sg:province":"NC",
    "wof:name":"Williams Pro Lawn Care",
    "wof:placetype":"venue"
},
  "geometry": {"coordinates":[-78.90089,35.138033],"type":"Point"}
}