{
  "type": "Feature",
  "properties": {
    "iso:country":"US",
    "sg:address":"662 N Cannon Blvd",
    "sg:city":"Kannapolis",
    "sg:classifiers":[
        {
            "category":"Food & Beverages",
            "subcategory":"Groceries & Convenience Stores",
            "type":"Retail Goods"
        }
    ],
    "sg:phone":"+1 704 933 6543",
    "sg:postcode":"28083",
    "sg:province":"NC",
    "wof:name":"Vientaine Oriental",
    "wof:placetype":"venue"
},
  "geometry": {"coordinates":[-80.609026,35.503311],"type":"Point"}
}