{
  "type": "Feature",
  "properties": {
    "iso:country":"US",
    "sg:address":"285 Potato House Rd",
    "sg:city":"Clinton",
    "sg:classifiers":[
        {
            "category":"Utilities",
            "subcategory":"Refuse",
            "type":"Services"
        }
    ],
    "sg:phone":"+1 910 564 6048",
    "sg:postcode":"28328",
    "sg:province":"NC",
    "sg:tags":[
        "disposal",
        "waste"
    ],
    "wof:name":"Waste Industries",
    "wof:placetype":"venue"
},
  "geometry": {"coordinates":[-78.330134,35.106886],"type":"Point"}
}