{
  "type": "Feature",
  "properties": {
    "addr:full":"1579 Highlands Rd Franklin NC 28734",
    "addr:housenumber":"1579",
    "addr:postcode":"nc 28734",
    "addr:street":"Highlands Rd",
    "iso:country":"US",
    "sg:address":"1579 Highlands Rd",
    "sg:city":"Franklin",
    "sg:classifiers":[
        {
            "category":"Professional",
            "subcategory":"Accounting & Tax Preparation",
            "type":"Services"
        }
    ],
    "sg:phone":"+1 828 524 1140",
    "sg:postcode":"28734",
    "sg:province":"NC",
    "sg:tags":[
        "return",
        "filing"
    ],
    "wof:name":"Jackson Hewitt Tax Service",
    "wof:placetype":"venue"
},
  "geometry": {"coordinates":[-83.355403,35.175434],"type":"Point"}
}