{
  "type": "Feature",
  "properties": {
    "addr:full":"248 E Broad St Statesville NC 28677",
    "addr:housenumber":"248",
    "addr:postcode":"28677",
    "addr:street":"E Broad St",
    "iso:country":"US",
    "sg:address":"248 E Broad St",
    "sg:city":"Statesville",
    "sg:classifiers":[
        {
            "category":"Organizations",
            "subcategory":"Non-profit Organization",
            "type":"Services"
        }
    ],
    "sg:phone":"+1   ",
    "sg:postcode":"28677",
    "sg:province":"NC",
    "sg:tags":[
        "legal",
        "social"
    ],
    "wof:name":"Appropriate Punishment Options",
    "wof:placetype":"venue"
},
  "geometry": {"coordinates":[-80.884477,35.785698],"type":"Point"}
}