{
  "type": "Feature",
  "properties": {
    "iso:country":"US",
    "sg:address":"803 Ramseur St",
    "sg:city":"Durham",
    "sg:classifiers":[
        {
            "category":"Manufacturing",
            "subcategory":"Printing",
            "type":"Manufacturing & Wholesale Goods"
        }
    ],
    "sg:phone":"+1 919 682 2869",
    "sg:postcode":"27701",
    "sg:province":"NC",
    "sg:tags":[
        "commercial"
    ],
    "wof:name":"Real Truth Printing Group",
    "wof:placetype":"venue"
},
  "geometry": {"coordinates":[-78.893974,35.987468],"type":"Point"}
}