{
  "type": "Feature",
  "properties": {
    "addr:full":"205 Locust St Spruce Pine NC 28777",
    "addr:housenumber":"205",
    "addr:postcode":"28777",
    "addr:street":"Locust St",
    "iso:country":"US",
    "sg:address":"205 Locust St",
    "sg:city":"Spruce Pine",
    "sg:classifiers":[
        {
            "category":"Banks & Credit Unions",
            "subcategory":"Investment Brokerage",
            "type":"Services"
        }
    ],
    "sg:phone":"+1 828 766 9064",
    "sg:postcode":"28777",
    "sg:province":"NC",
    "sg:tags":[
        "security"
    ],
    "wof:name":"AIG American General",
    "wof:placetype":"venue"
},
  "geometry": {"coordinates":[-82.069294,35.9157],"type":"Point"}
}