{
  "type": "Feature",
  "properties": {
    "iso:country":"US",
    "sg:address":"1404 Troy Rd",
    "sg:city":"Monroe",
    "sg:classifiers":[
        {
            "category":"Retail",
            "subcategory":"Photofinishing",
            "type":"Services"
        }
    ],
    "sg:phone":"+1 704 283 5643",
    "sg:postcode":"28150",
    "sg:province":"NC",
    "sg:tags":[
        "photo",
        "finishing"
    ],
    "wof:name":"Photo Pro & More",
    "wof:placetype":"venue"
},
  "geometry": {"coordinates":[-81.48862099999999,35.314437],"type":"Point"}
}