{
  "type": "Feature",
  "properties": {
    "iso:country":"US",
    "sg:address":"130 Cardinal Dr",
    "sg:city":"Roanoke Rapids",
    "sg:classifiers":[
        {
            "category":"Health Services",
            "subcategory":"Doctor",
            "type":"Services"
        }
    ],
    "sg:phone":"+1 252 535 3091",
    "sg:postcode":"27870",
    "sg:province":"NC",
    "sg:tags":[
        "physician",
        "surgeon"
    ],
    "wof:name":"Halifax Orthopedic & Hand",
    "wof:placetype":"venue"
},
  "geometry": {"coordinates":[-77.642433,36.435058],"type":"Point"}
}