{
  "type": "Feature",
  "properties": {
    "iso:country":"US",
    "sg:address":"635 Sand Pit Rd",
    "sg:city":"Aberdeen",
    "sg:classifiers":[
        {
            "category":"Building & Trades",
            "subcategory":"Landscaping Services",
            "type":"Services"
        }
    ],
    "sg:phone":"+1 910 215 4826",
    "sg:postcode":"28315",
    "sg:province":"NC",
    "wof:name":"Nucci Ron Haul Grd LNDscp&",
    "wof:placetype":"venue"
},
  "geometry": {"coordinates":[-79.473175,35.133641],"type":"Point"}
}