{
  "type": "Feature",
  "properties": {
    "addr:full":"123 Mozelle Rd Cherryville NC 28021",
    "addr:housenumber":"123",
    "addr:postcode":"28021",
    "addr:street":"Mozelle Rd",
    "iso:country":"US",
    "sg:address":"123 Mozelle Rd",
    "sg:city":"Cherryville",
    "sg:classifiers":[
        {
            "category":"Building & Trades",
            "subcategory":"Construction",
            "type":"Services"
        }
    ],
    "sg:phone":"+1 704 435 6561",
    "sg:postcode":"28021",
    "sg:province":"NC",
    "sg:tags":[
        "house"
    ],
    "wof:name":"Wt Const Co",
    "wof:placetype":"venue"
},
  "geometry": {"coordinates":[-81.379947,35.346847],"type":"Point"}
}