{
  "type": "Feature",
  "properties": {
    "addr:full":"651 Gilbert Rd SE Bolivia NC 28422",
    "addr:housenumber":"651",
    "addr:postcode":"28422",
    "addr:street":"Gilbert Rd Se",
    "iso:country":"US",
    "sg:address":"651 Gilbert Rd SE",
    "sg:city":"Bolivia",
    "sg:classifiers":[
        {
            "category":"Recreation",
            "type":"Entertainment"
        }
    ],
    "sg:phone":"+1 910 253 4020",
    "sg:postcode":"28422",
    "sg:province":"NC",
    "sg:tags":[
        "stable"
    ],
    "wof:name":"Laura-Daye Stables",
    "wof:placetype":"venue"
},
  "geometry": {"coordinates":[-78.20578500000001,34.025315],"type":"Point"}
}