{
  "type": "Feature",
  "properties": {
    "iso:country":"US",
    "sg:address":"339 N Caldwell St",
    "sg:city":"Brevard",
    "sg:classifiers":[
        {
            "category":"Personal",
            "subcategory":"Beauty Salon",
            "type":"Services"
        }
    ],
    "sg:phone":"+1   ",
    "sg:postcode":"28712",
    "sg:province":"SC",
    "sg:tags":[
        "shop"
    ],
    "wof:name":"Mixed Company",
    "wof:placetype":"venue"
},
  "geometry": {"coordinates":[-82.73310499999999,35.236508],"type":"Point"}
}