{
  "type": "Feature",
  "properties": {
    "addr:full":"2608 New Walkertown Rd NE Winston Salem NC 27101",
    "addr:housenumber":"2608",
    "addr:postcode":"27101",
    "addr:street":"New Walkertown Rd Ne",
    "iso:country":"US",
    "sg:address":"2608 New Walkertown Rd NE",
    "sg:city":"Winston Salem",
    "sg:classifiers":[
        {
            "category":"Health Services",
            "subcategory":"Doctor",
            "type":"Services"
        }
    ],
    "sg:phone":"+1 336 724 2112",
    "sg:postcode":"27101",
    "sg:province":"NC",
    "sg:tags":[
        "dentist"
    ],
    "wof:name":"H M Holt DDS",
    "wof:placetype":"venue"
},
  "geometry": {"coordinates":[-80.212461,36.111301],"type":"Point"}
}