{
  "type": "Feature",
  "properties": {
    "iso:country":"US",
    "sg:address":"740 Bell Fork Rd",
    "sg:city":"Jacksonville",
    "sg:classifiers":[
        {
            "category":"Retail",
            "subcategory":"Auto Repair",
            "type":"Services"
        }
    ],
    "sg:phone":"+1 910 353 3160",
    "sg:postcode":"28540",
    "sg:province":"NC",
    "sg:tags":[
        "muffler",
        "exhaust",
        "system"
    ],
    "wof:name":"30 Minute Muffler & Brake Ctr",
    "wof:placetype":"venue"
},
  "geometry": {"coordinates":[-77.390171,34.752969],"type":"Point"}
}