{
  "type": "Feature",
  "properties": {
    "iso:country":"US",
    "sg:address":"175 Biltmore Ave",
    "sg:city":"Asheville",
    "sg:classifiers":[
        {
            "category":"Wholesale",
            "subcategory":"Apparel",
            "type":"Manufacturing & Wholesale Goods"
        }
    ],
    "sg:phone":"+1 828 254 4585",
    "sg:postcode":"28801",
    "sg:province":"NC",
    "sg:tags":[
        "r",
        "piece",
        "foam",
        "retail"
    ],
    "wof:name":"Bestbuy Foam & Fabrics",
    "wof:placetype":"venue"
},
  "geometry": {"coordinates":[-82.551627,35.589388],"type":"Point"}
}