{
  "type": "Feature",
  "properties": {
    "addr:full":"5192 James B White Hwy S Whiteville NC 28472",
    "addr:housenumber":"5192",
    "addr:postcode":"28472",
    "addr:street":"James B White Hwy S",
    "iso:country":"US",
    "sg:address":"5192 James B White Hwy S",
    "sg:city":"Whiteville",
    "sg:classifiers":[
        {
            "category":"Wholesale",
            "subcategory":"Scrap",
            "type":"Manufacturing & Wholesale Goods"
        }
    ],
    "sg:phone":"+1 910 640 2008",
    "sg:postcode":"28472",
    "sg:province":"NC",
    "sg:tags":[
        "recycling",
        "center"
    ],
    "wof:name":"Carolina Recycling",
    "wof:placetype":"venue"
},
  "geometry": {"coordinates":[-78.742503,34.275232],"type":"Point"}
}