{
  "type": "Feature",
  "properties": {
    "iso:country":"US",
    "sg:address":"116 State Hwy 210",
    "sg:city":"Smithfield",
    "sg:classifiers":[
        {
            "category":"Health Services",
            "subcategory":"Nursing And Care Facility",
            "type":"Services"
        }
    ],
    "sg:phone":"+1   ",
    "sg:postcode":"27577",
    "sg:province":"NC",
    "sg:tags":[
        "intermediate"
    ],
    "wof:name":"Windsor Place Apartments",
    "wof:placetype":"venue"
},
  "geometry": {"coordinates":[-78.36214,35.517632],"type":"Point"}
}