{
  "type": "Feature",
  "properties": {
    "addr:full":"950 E Firetower Rd Winterville NC 28590",
    "addr:housenumber":"950",
    "addr:postcode":"28590",
    "addr:street":"E Firetower Rd",
    "iso:country":"US",
    "sg:address":"950 E Firetower Rd",
    "sg:city":"Winterville",
    "sg:classifiers":[
        {
            "category":"Real Estate",
            "subcategory":"Real Estate Operator",
            "type":"Services"
        }
    ],
    "sg:phone":"+1 252 355 2340",
    "sg:postcode":"28590",
    "sg:province":"NC",
    "sg:tags":[
        "mobile",
        "home",
        "site"
    ],
    "wof:name":"Evans Mobile Home Park Inc",
    "wof:placetype":"venue"
},
  "geometry": {"coordinates":[-77.36851299999999,35.557316],"type":"Point"}
}