{
  "type": "Feature",
  "properties": {
    "iso:country":"US",
    "sg:address":"4915 Monroe Rd",
    "sg:city":"Charlotte",
    "sg:classifiers":[
        {
            "category":"Real Estate",
            "subcategory":"Real Estate Agent",
            "type":"Services"
        }
    ],
    "sg:phone":"+1 704 537 3900",
    "sg:postcode":"28205",
    "sg:province":"NC",
    "wof:name":"Stikeleather Realty",
    "wof:placetype":"venue"
},
  "geometry": {"coordinates":[-80.77897400000001,35.192258],"type":"Point"}
}