{
  "type": "Feature",
  "properties": {
    "addr:full":"411 National Hwy Thomasville NC 27360",
    "addr:housenumber":"411",
    "addr:postcode":"27360",
    "addr:street":"National Hwy",
    "iso:country":"US",
    "sg:address":"411 National Hwy",
    "sg:city":"Thomasville",
    "sg:classifiers":[
        {
            "category":"Insurance",
            "subcategory":"Insurance Agent",
            "type":"Services"
        }
    ],
    "sg:phone":"+1 336 475 1948",
    "sg:postcode":"27360",
    "sg:province":"NC",
    "wof:name":"All-Risk Insurance Ctr Inc",
    "wof:placetype":"venue"
},
  "geometry": {"coordinates":[-80.070983,35.894882],"type":"Point"}
}