{
  "type": "Feature",
  "properties": {
    "addr:full":"2940 E Franklin Blvd Gastonia NC 28056",
    "addr:housenumber":"2940",
    "addr:postcode":"28056",
    "addr:street":"E Franklin Blvd",
    "iso:country":"US",
    "sg:address":"2940 E Franklin Blvd",
    "sg:city":"Gastonia",
    "sg:classifiers":[
        {
            "category":"Home & Garden",
            "subcategory":"Furniture",
            "type":"Retail Goods"
        }
    ],
    "sg:phone":"+1 704 869 8999",
    "sg:postcode":"28056",
    "sg:province":"NC",
    "sg:tags":[
        "mattress"
    ],
    "sg:website":"www.originalmattress.com",
    "wof:name":"Original Mattress Company",
    "wof:placetype":"venue"
},
  "geometry": {"coordinates":[-81.124893,35.259103],"type":"Point"}
}