{
  "type": "Feature",
  "properties": {
    "addr:full":"12993 US Hwy 70 W Clayton NC 27520",
    "addr:housenumber":"12993",
    "addr:postcode":"27520",
    "addr:street":"Us Hwy 70 W",
    "iso:country":"US",
    "sg:address":"12993 US Hwy 70 W",
    "sg:city":"Clayton",
    "sg:classifiers":[
        {
            "category":"Shopping",
            "subcategory":"Department Store",
            "type":"Retail Goods"
        }
    ],
    "sg:phone":"+1 919 359 1688",
    "sg:postcode":"27520",
    "sg:province":"NC",
    "sg:tags":[
        "shop"
    ],
    "wof:name":"Dollar Tree",
    "wof:placetype":"venue"
},
  "geometry": {"coordinates":[-78.49819100000001,35.665626],"type":"Point"}
}