{
  "type": "Feature",
  "properties": {
    "addr:full":"10436 Connell Rd Charlotte NC 28227",
    "addr:housenumber":"10436",
    "addr:postcode":"28227",
    "addr:street":"Connell Rd",
    "iso:country":"US",
    "sg:address":"10436 Connell Rd",
    "sg:city":"Charlotte",
    "sg:classifiers":[
        {
            "category":"Building & Trades",
            "subcategory":"Electrical",
            "type":"Services"
        }
    ],
    "sg:phone":"+1 704 573 0007",
    "sg:postcode":"28227",
    "sg:province":"NC",
    "sg:tags":[
        "house",
        "electrical",
        "contractor"
    ],
    "wof:name":"BEC Inc",
    "wof:placetype":"venue"
},
  "geometry": {"coordinates":[-80.627928,35.213526],"type":"Point"}
}