{
  "type": "Feature",
  "properties": {
    "iso:country":"US",
    "sg:address":"207 Dale Adams Rd",
    "sg:city":"Sugar Grove",
    "sg:classifiers":[
        {
            "category":"Retail",
            "subcategory":"Repair Shop",
            "type":"Services"
        }
    ],
    "sg:phone":"+1 828 297 4757",
    "sg:postcode":"28679",
    "sg:province":"NC",
    "sg:tags":[
        "ironwork"
    ],
    "wof:name":"Carolina Iron Furniture",
    "wof:placetype":"venue"
},
  "geometry": {"coordinates":[-81.784217,36.264036],"type":"Point"}
}