{
  "type": "Feature",
  "properties": {
    "iso:country":"US",
    "sg:address":"3606 N Elm St",
    "sg:city":"Greensboro",
    "sg:classifiers":[
        {
            "category":"Food & Beverages",
            "subcategory":"Dairy",
            "type":"Retail Goods"
        }
    ],
    "sg:phone":"+1 336 540 0190",
    "sg:postcode":"27455",
    "sg:province":"NC",
    "sg:tags":[
        "product"
    ],
    "wof:name":"Cool Beans Coffee & Ice Cream",
    "wof:placetype":"venue"
},
  "geometry": {"coordinates":[-79.797584,36.135642],"type":"Point"}
}