{
  "type": "Feature",
  "properties": {
    "iso:country":"US",
    "sg:address":"2828 Croasdaile Dr",
    "sg:city":"Durham",
    "sg:classifiers":[
        {
            "category":"Professional",
            "subcategory":"Accounting & Tax Preparation",
            "type":"Services"
        }
    ],
    "sg:phone":"+1 919 383 2683",
    "sg:postcode":"27705",
    "sg:province":"NC",
    "sg:tags":[
        "management"
    ],
    "wof:name":"Scott Medical Group LLC",
    "wof:placetype":"venue"
},
  "geometry": {"coordinates":[-78.93899399999999,36.028058],"type":"Point"}
}