{
  "type": "Feature",
  "properties": {
    "addr:full":"527 Revell Rd Selma NC 27576",
    "addr:housenumber":"527",
    "addr:postcode":"27576",
    "addr:street":"Revell Rd",
    "iso:country":"US",
    "sg:address":"527 Revell Rd",
    "sg:city":"Selma",
    "sg:classifiers":[
        {
            "category":"Organizations",
            "subcategory":"Religious Organization",
            "type":"Services"
        }
    ],
    "sg:phone":"+1   ",
    "sg:postcode":"27576",
    "sg:province":"NC",
    "wof:name":"United Love Holiness Church",
    "wof:placetype":"venue"
},
  "geometry": {"coordinates":[-78.275158,35.589358],"type":"Point"}
}