{
  "type": "Feature",
  "properties": {
    "iso:country":"US",
    "sg:address":"1000 Wesley Pines Rd",
    "sg:city":"Lumberton",
    "sg:classifiers":[
        {
            "category":"Health Services",
            "subcategory":"Nursing And Care Facility",
            "type":"Services"
        }
    ],
    "sg:phone":"+1 910 738 9691",
    "sg:postcode":"28358",
    "sg:province":"NC",
    "sg:tags":[
        "home",
        "retirement",
        "community"
    ],
    "sg:website":"www.umrh.org",
    "wof:name":"Wesley Pines Retirement Ctr",
    "wof:placetype":"venue"
},
  "geometry": {"coordinates":[-78.99459899999999,34.657195],"type":"Point"}
}