{
  "type": "Feature",
  "properties": {
    "addr:full":"20 Dearmin Ter Franklin NC 28734",
    "addr:housenumber":"20",
    "addr:postcode":"nc 28734",
    "addr:street":"Dearmin Ter",
    "iso:country":"US",
    "sg:address":"20 Dearmin Ter",
    "sg:city":"Franklin",
    "sg:classifiers":[
        {
            "category":"Professional",
            "subcategory":"Accounting & Tax Preparation",
            "type":"Services"
        }
    ],
    "sg:phone":"+1 828 369 6101",
    "sg:postcode":"28734",
    "sg:province":"NC",
    "sg:tags":[
        "billing"
    ],
    "wof:name":"Doctors Administrators",
    "wof:placetype":"venue"
},
  "geometry": {"coordinates":[-83.374127,35.182218],"type":"Point"}
}