{
  "type": "Feature",
  "properties": {
    "addr:full":"401 Oberlin Rd Suite 115 Raleigh NC 27605",
    "addr:housenumber":"401",
    "addr:postcode":"27605",
    "addr:street":"Oberlin Rd Suite 115",
    "iso:country":"US",
    "sg:address":"401 Oberlin Rd Suite 115",
    "sg:city":"Raleigh",
    "sg:classifiers":[
        {
            "category":"Social Services",
            "type":"Services"
        }
    ],
    "sg:phone":"+1 919 835 3636",
    "sg:postcode":"27605",
    "sg:province":"NC",
    "sg:tags":[
        "disability"
    ],
    "wof:name":"Nc Statewide Independent Living Council",
    "wof:placetype":"venue"
},
  "geometry": {"coordinates":[-78.663017,35.789349],"type":"Point"}
}