{
  "type": "Feature",
  "properties": {
    "addr:full":"303 Traphill Rd Hays NC 28635",
    "addr:housenumber":"303",
    "addr:postcode":"28635",
    "addr:street":"Traphill Rd",
    "iso:country":"US",
    "sg:address":"303 Traphill Rd",
    "sg:city":"Hays",
    "sg:classifiers":[
        {
            "category":"Food & Beverages",
            "subcategory":"Groceries & Convenience Stores",
            "type":"Retail Goods"
        }
    ],
    "sg:phone":"+1 336 696 4166",
    "sg:postcode":"28635",
    "sg:province":"NC",
    "wof:name":"Grocery Bag",
    "wof:placetype":"venue"
},
  "geometry": {"coordinates":[-81.11759499999999,36.251915],"type":"Point"}
}