{
  "type": "Feature",
  "properties": {
    "iso:country":"US",
    "sg:address":"9620 University City Blvd",
    "sg:city":"Charlotte",
    "sg:classifiers":[
        {
            "category":"Education",
            "subcategory":"Special Training",
            "type":"Public Place"
        }
    ],
    "sg:phone":"+1 704 548 1483",
    "sg:postcode":"28213",
    "sg:province":"NC",
    "sg:tags":[
        "center"
    ],
    "wof:name":"Kumon Of Charlotte UNC",
    "wof:placetype":"venue"
},
  "geometry": {"coordinates":[-80.721897,35.307335],"type":"Point"}
}