{
  "type": "Feature",
  "properties": {
    "iso:country":"US",
    "sg:address":"235 Dunns Mountain Church Rd",
    "sg:city":"Salisbury",
    "sg:classifiers":[
        {
            "category":"Shopping",
            "subcategory":"Florist",
            "type":"Retail Goods"
        }
    ],
    "sg:phone":"+1 704 279 0661",
    "sg:postcode":"28146",
    "sg:province":"NC",
    "sg:tags":[
        "catering"
    ],
    "wof:name":"Rainbow Florist & Catering",
    "wof:placetype":"venue"
},
  "geometry": {"coordinates":[-80.44514700000001,35.628417],"type":"Point"}
}