{
  "type": "Feature",
  "properties": {
    "addr:full":"6605 Marshville Blvd Marshville NC 28103",
    "addr:housenumber":"6605",
    "addr:postcode":"28103",
    "addr:street":"Marshville Blvd",
    "iso:country":"US",
    "sg:address":"6605 Marshville Blvd",
    "sg:city":"Marshville",
    "sg:classifiers":[
        {
            "category":"Utilities",
            "subcategory":"Mobile Phone",
            "type":"Services"
        }
    ],
    "sg:phone":"+1 704 624 1977",
    "sg:postcode":"28103",
    "sg:province":"NC",
    "sg:tags":[
        "telephone",
        "cellular"
    ],
    "wof:name":"Cellstar Communications",
    "wof:placetype":"venue"
},
  "geometry": {"coordinates":[-80.357828,34.9868],"type":"Point"}
}