{
  "type": "Feature",
  "properties": {
    "iso:country":"US",
    "sg:address":"834 Hardee Rd",
    "sg:city":"Kinston",
    "sg:classifiers":[
        {
            "category":"Personal",
            "subcategory":"Barber",
            "type":"Services"
        }
    ],
    "sg:phone":"+1 252 527 0888",
    "sg:postcode":"28504",
    "sg:province":"NC",
    "wof:name":"Upper Cut",
    "wof:placetype":"venue"
},
  "geometry": {"coordinates":[-77.60684500000001,35.272471],"type":"Point"}
}