{
  "type": "Feature",
  "properties": {
    "addr:full":"5335 Oleander Dr Wilmington NC 28403",
    "addr:housenumber":"5335",
    "addr:postcode":"28403",
    "addr:street":"Oleander Dr",
    "iso:country":"US",
    "sg:address":"5335 Oleander Dr",
    "sg:city":"Wilmington",
    "sg:classifiers":[
        {
            "category":"Cinema",
            "subcategory":"Movie Theater",
            "type":"Entertainment"
        }
    ],
    "sg:phone":"+1 910 799 1066",
    "sg:postcode":"28403",
    "sg:province":"NC",
    "wof:name":"Carmike Cinemas",
    "wof:placetype":"venue"
},
  "geometry": {"coordinates":[-77.862826,34.208094],"type":"Point"}
}