{
  "type": "Feature",
  "properties": {
    "iso:country":"US",
    "sg:address":"3704 Fernwood Dr",
    "sg:city":"Raleigh",
    "sg:classifiers":[
        {
            "category":"Real Estate",
            "subcategory":"Real Estate Operator",
            "type":"Services"
        }
    ],
    "sg:phone":"+1 919 781 0644",
    "sg:postcode":"27612",
    "sg:province":"NC",
    "sg:tags":[
        "property",
        "lessor"
    ],
    "wof:name":"Lipkin Properties Inc",
    "wof:placetype":"venue"
},
  "geometry": {"coordinates":[-78.696528,35.854477],"type":"Point"}
}