{
  "type": "Feature",
  "properties": {
    "iso:country":"US",
    "sg:address":"3509 Misty River Dr",
    "sg:city":"Raleigh",
    "sg:classifiers":[
        {
            "category":"Professional",
            "type":"Services"
        }
    ],
    "sg:phone":"+1 919 217 8595",
    "sg:postcode":"27610",
    "sg:province":"NC",
    "wof:name":"Jacobs Ladder Transitiona",
    "wof:placetype":"venue"
},
  "geometry": {"coordinates":[-78.525547,35.755204],"type":"Point"}
}