{
  "type": "Feature",
  "properties": {
    "addr:full":"2543 Broadstone Rd Banner Elk NC 28604",
    "addr:housenumber":"2543",
    "addr:postcode":"28604",
    "addr:street":"Broadstone Rd",
    "iso:country":"US",
    "sg:address":"2543 Broadstone Rd",
    "sg:city":"Banner Elk",
    "sg:classifiers":[
        {
            "category":"Travel",
            "subcategory":"Hotels & Motels",
            "type":"Entertainment"
        }
    ],
    "sg:phone":"+1 828 963 5857",
    "sg:postcode":"28604",
    "sg:province":"NC",
    "sg:tags":[
        "country",
        "inn"
    ],
    "sg:website":"www.mastfarminn.com",
    "wof:name":"Mast Farm Inn",
    "wof:placetype":"venue"
},
  "geometry": {"coordinates":[-81.769217,36.205907],"type":"Point"}
}