{
  "type": "Feature",
  "properties": {
    "iso:country":"US",
    "sg:address":"1500 Sunday Dr",
    "sg:city":"Raleigh",
    "sg:classifiers":[
        {
            "category":"Building & Trades",
            "subcategory":"Construction",
            "type":"Services"
        }
    ],
    "sg:phone":"+1 919 828 1106",
    "sg:postcode":"27607",
    "sg:province":"NC",
    "sg:tags":[
        "contractor"
    ],
    "wof:name":"M I Homes Raleigh Division",
    "wof:placetype":"venue"
},
  "geometry": {"coordinates":[-78.730598,35.7994],"type":"Point"}
}