{
  "type": "Feature",
  "properties": {
    "addr:full":"704 S Lee St Whiteville NC 28472",
    "addr:housenumber":"704",
    "addr:postcode":"28472",
    "addr:street":"S Lee St",
    "iso:country":"US",
    "sg:address":"704 S Lee St",
    "sg:city":"Whiteville",
    "sg:classifiers":[
        {
            "category":"Shopping",
            "subcategory":"Clothing, Apparel, & Fashions",
            "type":"Retail Goods"
        }
    ],
    "sg:phone":"+1 910 640 1209",
    "sg:postcode":"28472",
    "sg:province":"NC",
    "sg:tags":[
        "alteration"
    ],
    "wof:name":"Ruby's Alterations & Sewing",
    "wof:placetype":"venue"
},
  "geometry": {"coordinates":[-78.704925,34.322258],"type":"Point"}
}