{
  "type": "Feature",
  "properties": {
    "iso:country":"US",
    "sg:address":"1608 Pinecrest Rd",
    "sg:city":"Rocky Mount",
    "sg:classifiers":[
        {
            "category":"Shopping",
            "subcategory":"Pharmacy",
            "type":"Retail Goods"
        }
    ],
    "sg:phone":"+1 252 977 0062",
    "sg:postcode":"27803",
    "sg:province":"NC",
    "sg:tags":[
        "drug",
        "store"
    ],
    "wof:name":"Raper Drugs Inc 1",
    "wof:placetype":"venue"
},
  "geometry": {"coordinates":[-77.82046699999999,35.941208],"type":"Point"}
}