{
  "type": "Feature",
  "properties": {
    "iso:country":"US",
    "sg:address":"3303 US Hwy 70",
    "sg:city":"Durham",
    "sg:classifiers":[
        {
            "category":"Building & Trades",
            "subcategory":"Equipment Rental",
            "type":"Services"
        }
    ],
    "sg:phone":"+1 919 596 3913",
    "sg:postcode":"27703",
    "sg:province":"NC",
    "sg:tags":[
        "leasing"
    ],
    "sg:website":"www.logisticleasing.com",
    "wof:name":"Logistic Leasing LLC",
    "wof:placetype":"venue"
},
  "geometry": {"coordinates":[-78.810292,35.932927],"type":"Point"}
}