{
  "type": "Feature",
  "properties": {
    "addr:full":"234 W Front St Burlington NC 27215",
    "addr:housenumber":"234",
    "addr:postcode":"27215",
    "addr:street":"W Front St",
    "iso:country":"US",
    "sg:address":"234 W Front St",
    "sg:city":"Burlington",
    "sg:classifiers":[
        {
            "category":"Organizations",
            "subcategory":"Religious Organization",
            "type":"Services"
        }
    ],
    "sg:phone":"+1 336 227 8114",
    "sg:postcode":"27215",
    "sg:province":"NC",
    "wof:name":"Back To Basics Ministries",
    "wof:placetype":"venue"
},
  "geometry": {"coordinates":[-79.43795900000001,36.094963],"type":"Point"}
}