{
  "type": "Feature",
  "properties": {
    "addr:full":"803 Confederate Ave Salisbury NC 28144",
    "addr:housenumber":"803",
    "addr:postcode":"28144",
    "addr:street":"Confederate Ave",
    "iso:country":"US",
    "sg:address":"803 Confederate Ave",
    "sg:city":"Salisbury",
    "sg:classifiers":[
        {
            "category":"Building & Trades",
            "subcategory":"Construction",
            "type":"Services"
        }
    ],
    "sg:phone":"+1 704 633 1113",
    "sg:postcode":"28144",
    "sg:province":"NC",
    "sg:tags":[
        "tile",
        "dealer"
    ],
    "wof:name":"Delta Tile",
    "wof:placetype":"venue"
},
  "geometry": {"coordinates":[-80.46014099999999,35.685131],"type":"Point"}
}