{
  "type": "Feature",
  "properties": {
    "addr:full":"270 Pleasant Spring Rd Pittsboro NC 27312",
    "addr:housenumber":"270",
    "addr:postcode":"27312",
    "addr:street":"Pleasant Spring Rd",
    "iso:country":"US",
    "sg:address":"270 Pleasant Spring Rd",
    "sg:city":"Pittsboro",
    "sg:classifiers":[
        {
            "category":"Building & Trades",
            "subcategory":"Electrical",
            "type":"Services"
        }
    ],
    "sg:phone":"+1 919 542 1260",
    "sg:postcode":"27312",
    "sg:province":"NC",
    "sg:tags":[
        "electrical",
        "contractor"
    ],
    "wof:name":"Barnes Js Electric",
    "wof:placetype":"venue"
},
  "geometry": {"coordinates":[-79.14533400000001,35.795705],"type":"Point"}
}