{
  "type": "Feature",
  "properties": {
    "iso:country":"US",
    "sg:address":"1093 13th St SE",
    "sg:city":"Hickory",
    "sg:classifiers":[
        {
            "category":"Health Services",
            "subcategory":"Chiropractor",
            "type":"Services"
        }
    ],
    "sg:phone":"+1 828 238 2952",
    "sg:postcode":"28602",
    "sg:province":"NC",
    "wof:name":"Back To Health Chiropractic",
    "wof:placetype":"venue"
},
  "geometry": {"coordinates":[-81.313073,35.718513],"type":"Point"}
}