{
  "type": "Feature",
  "properties": {
    "iso:country":"US",
    "sg:address":"720 Gastonia Hwy",
    "sg:city":"Bessemer City",
    "sg:classifiers":[
        {
            "category":"Health Services",
            "subcategory":"Doctor",
            "type":"Services"
        }
    ],
    "sg:phone":"+1   ",
    "sg:postcode":"28016",
    "sg:province":"NC",
    "sg:tags":[
        "medical"
    ],
    "wof:name":"Henry L Kiser Jr MD",
    "wof:placetype":"venue"
},
  "geometry": {"coordinates":[-81.268502,35.285898],"type":"Point"}
}