{
  "type": "Feature",
  "properties": {
    "iso:country":"US",
    "sg:address":"3625 Litchfield Dr",
    "sg:city":"Rocky Mount",
    "sg:classifiers":[
        {
            "category":"Organizations",
            "subcategory":"Religious Organization",
            "type":"Services"
        }
    ],
    "sg:phone":"+1 252 937 2450",
    "sg:postcode":"27803",
    "sg:province":"NC",
    "sg:tags":[
        "church"
    ],
    "wof:name":"Faith & Victory Christian",
    "wof:placetype":"venue"
},
  "geometry": {"coordinates":[-77.862953,35.955328],"type":"Point"}
}