{
  "type": "Feature",
  "properties": {
    "addr:full":"222 E Hargett St Raleigh NC 27601",
    "addr:housenumber":"222",
    "addr:postcode":"27601",
    "addr:street":"E Hargett St",
    "iso:country":"US",
    "sg:address":"222 E Hargett St",
    "sg:city":"Raleigh",
    "sg:classifiers":[
        {
            "category":"Government",
            "subcategory":"Office",
            "type":"Public Place"
        }
    ],
    "sg:phone":"+1 919 832 7238",
    "sg:postcode":"27601",
    "sg:province":"NC",
    "sg:tags":[
        "village"
    ],
    "sg:website":"www.rhdc.org",
    "wof:name":"Raleigh Historic Districts",
    "wof:placetype":"venue"
},
  "geometry": {"coordinates":[-78.635289,35.778045],"type":"Point"}
}