{
  "type": "Feature",
  "properties": {
    "addr:full":"36 Bethlehem Mfg Ln Hickory NC 28601",
    "addr:housenumber":"36",
    "addr:postcode":"28601",
    "addr:street":"Bethlehem Mfg Ln",
    "iso:country":"US",
    "sg:address":"36 Bethlehem Mfg Ln",
    "sg:city":"Hickory",
    "sg:classifiers":[
        {
            "category":"Retail",
            "subcategory":"Repair Shop",
            "type":"Services"
        }
    ],
    "sg:phone":"+1   ",
    "sg:postcode":"28601",
    "sg:province":"NC",
    "sg:tags":[
        "welding"
    ],
    "wof:name":"Moretz of NC LLC",
    "wof:placetype":"venue"
},
  "geometry": {"coordinates":[-81.318741,35.8058],"type":"Point"}
}