{
  "type": "Feature",
  "properties": {
    "addr:full":"14901 Hickory View Ln Charlotte NC 28278",
    "addr:housenumber":"14901",
    "addr:postcode":"28278",
    "addr:street":"Hickory View Ln",
    "iso:country":"US",
    "sg:address":"14901 Hickory View Ln",
    "sg:city":"Charlotte",
    "sg:classifiers":[
        {
            "category":"Building & Trades",
            "subcategory":"Equipment Rental",
            "type":"Services"
        }
    ],
    "sg:phone":"+1 704 583 0196",
    "sg:postcode":"28278",
    "sg:province":"NC",
    "sg:tags":[
        "leasing"
    ],
    "wof:name":"Rex Equipment Leasing Inc",
    "wof:placetype":"venue"
},
  "geometry": {"coordinates":[-81.016019,35.086367],"type":"Point"}
}