{
  "type": "Feature",
  "properties": {
    "iso:country":"US",
    "sg:address":"12640 Old US Hwy 52",
    "sg:city":"Winston Salem",
    "sg:classifiers":[
        {
            "category":"Building & Trades",
            "subcategory":"Construction",
            "type":"Services"
        }
    ],
    "sg:phone":"+1 336 788 3182",
    "sg:postcode":"27107",
    "sg:province":"NC",
    "sg:tags":[
        "home",
        "improvement"
    ],
    "sg:website":"www.kguardnc.com",
    "wof:name":"Bassett Seamless Guttering",
    "wof:placetype":"venue"
},
  "geometry": {"coordinates":[-80.229381,35.989539],"type":"Point"}
}