{
  "type": "Feature",
  "properties": {
    "addr:full":"156 River Rd Fuquay Varina NC 27526",
    "addr:housenumber":"156",
    "addr:postcode":"27526",
    "addr:street":"River Rd",
    "iso:country":"US",
    "sg:address":"156 River Rd",
    "sg:city":"Fuquay Varina",
    "sg:classifiers":[
        {
            "category":"Retail",
            "subcategory":"Repair Shop",
            "type":"Services"
        }
    ],
    "sg:phone":"+1   ",
    "sg:postcode":"27526",
    "sg:province":"NC",
    "wof:name":"R W Blanchard",
    "wof:placetype":"venue"
},
  "geometry": {"coordinates":[-78.883865,35.48619],"type":"Point"}
}