{
  "type": "Feature",
  "properties": {
    "addr:full":"119 Sunrise Cir Shelby NC 28150",
    "addr:housenumber":"119",
    "addr:postcode":"28150",
    "addr:street":"Sunrise Cir",
    "iso:country":"US",
    "sg:address":"119 Sunrise Cir",
    "sg:city":"Shelby",
    "sg:classifiers":[
        {
            "category":"Organizations",
            "subcategory":"Religious Organization",
            "type":"Services"
        }
    ],
    "sg:phone":"+1   ",
    "sg:postcode":"28150",
    "sg:province":"NC",
    "wof:name":"Rev Harold E Fite Minister",
    "wof:placetype":"venue"
},
  "geometry": {"coordinates":[-81.51125399999999,35.298105],"type":"Point"}
}