{
  "type": "Feature",
  "properties": {
    "iso:country":"US",
    "sg:address":"800 Little Kelly Rd",
    "sg:city":"Rocky Point",
    "sg:classifiers":[
        {
            "category":"Farming",
            "subcategory":"Livestock Farm",
            "type":"Manufacturing & Wholesale Goods"
        }
    ],
    "sg:phone":"+1 910 259 4088",
    "sg:postcode":"28457",
    "sg:province":"NC",
    "sg:tags":[
        "hog",
        "tobacco",
        "beef",
        "cattle",
        "or",
        "feedlot"
    ],
    "wof:name":"Fennell Brothers Farms",
    "wof:placetype":"venue"
},
  "geometry": {"coordinates":[-77.961544,34.487408],"type":"Point"}
}