{
  "type": "Feature",
  "properties": {
    "iso:country":"US",
    "sg:address":"645 Washington St",
    "sg:city":"Eden",
    "sg:classifiers":[
        {
            "category":"Retail",
            "subcategory":"Repair Shop",
            "type":"Services"
        },
        {
            "category":"Shopping",
            "subcategory":"Bicycles & Sporting Goods",
            "type":"Retail Goods"
        }
    ],
    "sg:phone":"+1 336 623 7888",
    "sg:postcode":"27288",
    "sg:province":"NC",
    "sg:tags":[
        "equipment",
        "golf",
        "supply"
    ],
    "wof:name":"Wayne's Golf Shop & Repair",
    "wof:placetype":"venue"
},
  "geometry": {"coordinates":[-79.763712,36.490698],"type":"Point"}
}