{
  "type": "Feature",
  "properties": {
    "iso:country":"US",
    "sg:address":"927 S Lafayette St",
    "sg:city":"Shelby",
    "sg:classifiers":[
        {
            "category":"Social Services",
            "type":"Services"
        }
    ],
    "sg:phone":"+1 704 481 8626",
    "sg:postcode":"28152",
    "sg:province":"NC",
    "sg:tags":[
        "counselor",
        "marriage",
        "family"
    ],
    "wof:name":"Cleveland Counseling Pa",
    "wof:placetype":"venue"
},
  "geometry": {"coordinates":[-81.54300499999999,35.278394],"type":"Point"}
}