{
  "type": "Feature",
  "properties": {
    "iso:country":"US",
    "sg:address":"101 Sea Tern Dr E",
    "sg:city":"Kitty Hawk",
    "sg:classifiers":[
        {
            "category":"Building & Trades",
            "subcategory":"Construction",
            "type":"Services"
        }
    ],
    "sg:phone":"+1 252 261 2637",
    "sg:postcode":"27949",
    "sg:province":"NC",
    "sg:tags":[
        "contractor"
    ],
    "wof:name":"Hometown Builders",
    "wof:placetype":"venue"
},
  "geometry": {"coordinates":[-75.75973399999999,36.200908],"type":"Point"}
}