{
  "type": "Feature",
  "properties": {
    "iso:country":"US",
    "sg:address":"288 Battlefield Rd",
    "sg:city":"Four Oaks",
    "sg:phone":"+1 919 934 4099",
    "sg:postcode":"27524",
    "sg:province":"NC",
    "sg:tags":[
        "farm",
        "corn",
        "tobacco",
        "soybean"
    ],
    "wof:name":"Timothy Westbrook",
    "wof:placetype":"venue"
},
  "geometry": {"coordinates":[-78.307891,35.311575],"type":"Point"}
}