{
  "type": "Feature",
  "properties": {
    "addr:full":"290 Yates Ave Ridgecrest NC 28711",
    "addr:housenumber":"290",
    "addr:postcode":"28711",
    "addr:street":"Yates Ave",
    "iso:country":"US",
    "sg:address":"290 Yates Ave",
    "sg:city":"Ridgecrest",
    "sg:classifiers":[
        {
            "category":"Travel",
            "subcategory":"Campground",
            "type":"Entertainment"
        }
    ],
    "sg:phone":"+1 828 669 8051",
    "sg:postcode":"28711",
    "sg:province":"NC",
    "sg:tags":[
        "camp"
    ],
    "wof:name":"Ridgecrest Summer Camps",
    "wof:placetype":"venue"
},
  "geometry": {"coordinates":[-82.284971,35.617668],"type":"Point"}
}