{
  "type": "Feature",
  "properties": {
    "iso:country":"US",
    "sg:address":"2000 Donald Ross Rd",
    "sg:city":"Charlotte",
    "sg:classifiers":[
        {
            "category":"Manufacturing",
            "subcategory":"Tools & Machinery",
            "type":"Manufacturing & Wholesale Goods"
        }
    ],
    "sg:phone":"+1 704 392 4156",
    "sg:postcode":"28208",
    "sg:province":"NC",
    "sg:tags":[
        "furnace",
        "mfg",
        "textile",
        "works",
        "fab",
        "blast"
    ],
    "wof:name":"Mount Hope Machinery Co",
    "wof:placetype":"venue"
},
  "geometry": {"coordinates":[-80.89529899999999,35.219833],"type":"Point"}
}