{
  "type": "Feature",
  "properties": {
    "iso:country":"US",
    "sg:address":"855 Caler Rd",
    "sg:city":"Brasstown",
    "sg:classifiers":[
        {
            "category":"Professional",
            "subcategory":"Employment Agencies",
            "type":"Services"
        }
    ],
    "sg:phone":"+1 828 835 8464",
    "sg:postcode":"28902",
    "sg:province":"NC",
    "sg:tags":[
        "opportunity"
    ],
    "wof:name":"Pro Tech Inc",
    "wof:placetype":"venue"
},
  "geometry": {"coordinates":[-83.968244,35.002774],"type":"Point"}
}