{
  "type": "Feature",
  "properties": {
    "iso:country":"US",
    "sg:address":"1017 Cook Rd",
    "sg:city":"Durham",
    "sg:classifiers":[
        {
            "category":"Real Estate",
            "subcategory":"Real Estate Operator",
            "type":"Services"
        }
    ],
    "sg:phone":"+1 919 688 0843",
    "sg:postcode":"27713",
    "sg:province":"NC",
    "sg:tags":[
        "apartment"
    ],
    "wof:name":"Handicapped Housing",
    "wof:placetype":"venue"
},
  "geometry": {"coordinates":[-78.92073499999999,35.946987],"type":"Point"}
}