{
  "type": "Feature",
  "properties": {
    "iso:country":"US",
    "sg:address":"1777 N Fordham Blvd",
    "sg:city":"Chapel Hill",
    "sg:classifiers":[
        {
            "category":"Professional",
            "subcategory":"Lawyer & Legal Services",
            "type":"Services"
        }
    ],
    "sg:phone":"+1 919 932 1030",
    "sg:postcode":"27514",
    "sg:province":"NC",
    "sg:tags":[
        "attorney"
    ],
    "wof:name":"Jay Reeves",
    "wof:placetype":"venue"
},
  "geometry": {"coordinates":[-79.02627,35.91297],"type":"Point"}
}