{
  "type": "Feature",
  "properties": {
    "addr:full":"6171 Deans St Bailey NC 27807",
    "addr:housenumber":"6171",
    "addr:postcode":"27807",
    "addr:street":"Deans St",
    "iso:country":"US",
    "sg:address":"6171 Deans St",
    "sg:city":"Bailey",
    "sg:classifiers":[
        {
            "category":"Government",
            "subcategory":"Post Office",
            "type":"Public Place"
        }
    ],
    "sg:phone":"+1 252 235 3565",
    "sg:postcode":"27807",
    "sg:province":"NC",
    "sg:tags":[
        "postal",
        "us"
    ],
    "wof:name":"US Post Office",
    "wof:placetype":"venue"
},
  "geometry": {"coordinates":[-78.11224,35.779776],"type":"Point"}
}