{
  "type": "Feature",
  "properties": {
    "addr:full":"935 Rollover Creek Rd New Bern NC 28562",
    "addr:housenumber":"935",
    "addr:postcode":"28562",
    "addr:street":"Rollover Creek Rd",
    "iso:country":"US",
    "sg:address":"935 Rollover Creek Rd",
    "sg:city":"New Bern",
    "sg:classifiers":[
        {
            "category":"Travel",
            "subcategory":"Hotels & Motels",
            "type":"Entertainment"
        }
    ],
    "sg:phone":"+1 252 635 6697",
    "sg:postcode":"28562",
    "sg:province":"NC",
    "sg:tags":[
        "breakfast",
        "accommodation",
        "bed"
    ],
    "wof:name":"Foxbern Manor Bed & Breakfast",
    "wof:placetype":"venue"
},
  "geometry": {"coordinates":[-77.237617,35.153686],"type":"Point"}
}