{
  "type": "Feature",
  "properties": {
    "iso:country":"US",
    "sg:address":"826 E Morehead St",
    "sg:city":"Charlotte",
    "sg:classifiers":[
        {
            "category":"Shopping",
            "subcategory":"Bicycles & Sporting Goods",
            "type":"Retail Goods"
        }
    ],
    "sg:phone":"+1 704 377 5999",
    "sg:postcode":"28202",
    "sg:province":"NC",
    "sg:tags":[
        "equipment",
        "tennis",
        "supply"
    ],
    "wof:name":"Don's Tennis & Accessories",
    "wof:placetype":"venue"
},
  "geometry": {"coordinates":[-80.84513200000001,35.214251],"type":"Point"}
}