{
  "type": "Feature",
  "properties": {
    "addr:full":"511 N Spence Ave Goldsboro NC 27534",
    "addr:housenumber":"511",
    "addr:postcode":"27534",
    "addr:street":"N Spence Ave",
    "iso:country":"US",
    "sg:address":"511 N Spence Ave",
    "sg:city":"Goldsboro",
    "sg:classifiers":[
        {
            "category":"Insurance",
            "subcategory":"Insurance Agent",
            "type":"Services"
        }
    ],
    "sg:phone":"+1 919 751 5433",
    "sg:postcode":"27534",
    "sg:province":"NC",
    "wof:name":"Benefit Consultants Group",
    "wof:placetype":"venue"
},
  "geometry": {"coordinates":[-77.94707099999999,35.378291],"type":"Point"}
}