{
  "type": "Feature",
  "properties": {
    "addr:full":"1 College St Asheville NC 28801",
    "addr:housenumber":"1",
    "addr:postcode":"28801",
    "addr:street":"College St",
    "iso:country":"US",
    "sg:address":"1 College St",
    "sg:city":"Asheville",
    "sg:classifiers":[
        {
            "category":"Banks & Credit Unions",
            "subcategory":"Bank",
            "type":"Services"
        }
    ],
    "sg:phone":"+1 828 250 0712",
    "sg:postcode":"28801",
    "sg:province":"NC",
    "sg:tags":[
        "mortgage"
    ],
    "wof:name":"Charter One",
    "wof:placetype":"venue"
},
  "geometry": {"coordinates":[-82.55426199999999,35.595022],"type":"Point"}
}