{
  "type": "Feature",
  "properties": {
    "addr:full":"3400 Hampshire Dr Wilmington NC 28409",
    "addr:housenumber":"3400",
    "addr:postcode":"28409",
    "addr:street":"Hampshire Dr",
    "iso:country":"US",
    "sg:address":"3400 Hampshire Dr",
    "sg:city":"Wilmington",
    "sg:classifiers":[
        {
            "category":"Professional",
            "subcategory":"Management & Consulting",
            "type":"Services"
        }
    ],
    "sg:phone":"+1   ",
    "sg:postcode":"28409",
    "sg:province":"NC",
    "wof:name":"Salient Point Marketing",
    "wof:placetype":"venue"
},
  "geometry": {"coordinates":[-77.877228,34.18708],"type":"Point"}
}