{
  "type": "Feature",
  "properties": {
    "iso:country":"US",
    "sg:address":"11127 Fountaingrove Dr",
    "sg:city":"Charlotte",
    "sg:classifiers":[
        {
            "category":"Travel",
            "subcategory":"Hotels & Motels",
            "type":"Entertainment"
        }
    ],
    "sg:phone":"+1 704 510 2251",
    "sg:postcode":"28262",
    "sg:province":"NC",
    "wof:name":"Sun Hotels Of Rdu Nc Inc",
    "wof:placetype":"venue"
},
  "geometry": {"coordinates":[-80.752949,35.343928],"type":"Point"}
}