{
  "type": "Feature",
  "properties": {
    "addr:full":"212 Spring House Ct Winston Salem NC 27107",
    "addr:housenumber":"212",
    "addr:postcode":"27107",
    "addr:street":"Spring House Ct",
    "iso:country":"US",
    "sg:address":"212 Spring House Ct",
    "sg:city":"Winston Salem",
    "sg:classifiers":[
        {
            "category":"Social Services",
            "type":"Services"
        }
    ],
    "sg:phone":"+1 336 784 1818",
    "sg:postcode":"27107",
    "sg:province":"NC",
    "wof:name":"Mad Science",
    "wof:placetype":"venue"
},
  "geometry": {"coordinates":[-80.201666,36.025245],"type":"Point"}
}