{
  "type": "Feature",
  "properties": {
    "iso:country":"US",
    "sg:address":"1100 Nutmeg Dr",
    "sg:city":"Browns Summit",
    "sg:classifiers":[
        {
            "category":"Building & Trades",
            "subcategory":"Landscaping Services",
            "type":"Services"
        }
    ],
    "sg:phone":"+1 336 375 0004",
    "sg:postcode":"27214",
    "sg:province":"NC",
    "sg:tags":[
        "designer",
        "landscape"
    ],
    "wof:name":"Greensboro Landscaping",
    "wof:placetype":"venue"
},
  "geometry": {"coordinates":[-79.771176,36.189318],"type":"Point"}
}