{
  "type": "Feature",
  "properties": {
    "addr:full":"820 Tanner Rd Richfield NC 28071",
    "addr:housenumber":"820",
    "addr:postcode":"28071",
    "addr:street":"Tanner Rd",
    "iso:country":"US",
    "sg:address":"820 Tanner Rd",
    "sg:city":"Richfield",
    "sg:classifiers":[
        {
            "category":"Building & Trades",
            "subcategory":"Construction",
            "type":"Services"
        }
    ],
    "sg:phone":"+1 704 638 0387",
    "sg:postcode":"28071",
    "sg:province":"NC",
    "sg:tags":[
        "hanging",
        "contractor"
    ],
    "wof:name":"Chavis Painting",
    "wof:placetype":"venue"
},
  "geometry": {"coordinates":[-80.263971,35.55607],"type":"Point"}
}