{
  "type": "Feature",
  "properties": {
    "addr:full":"210 Jersey Church Rd Lexington NC 27292",
    "addr:housenumber":"210",
    "addr:postcode":"27292",
    "addr:street":"Jersey Church Rd",
    "iso:country":"US",
    "sg:address":"210 Jersey Church Rd",
    "sg:city":"Lexington",
    "sg:classifiers":[
        {
            "category":"Retail",
            "subcategory":"Auto Repair",
            "type":"Services"
        }
    ],
    "sg:phone":"+1 336 357 5577",
    "sg:postcode":"27292",
    "sg:province":"NC",
    "sg:tags":[
        "automobile",
        "lubrication"
    ],
    "wof:name":"D T Co Inc",
    "wof:placetype":"venue"
},
  "geometry": {"coordinates":[-80.265413,35.736506],"type":"Point"}
}