{
  "type": "Feature",
  "properties": {
    "addr:full":"407 Broad St Oxford NC 27565",
    "addr:housenumber":"407",
    "addr:postcode":"27565",
    "addr:street":"Broad St",
    "iso:country":"US",
    "sg:address":"407 Broad St",
    "sg:city":"Oxford",
    "sg:classifiers":[
        {
            "category":"Organizations",
            "subcategory":"Religious Organization",
            "type":"Services"
        }
    ],
    "sg:phone":"+1   ",
    "sg:postcode":"27565",
    "sg:province":"NC",
    "wof:name":"Grace Baptist Church",
    "wof:placetype":"venue"
},
  "geometry": {"coordinates":[-78.596127,36.317581],"type":"Point"}
}