{
  "type": "Feature",
  "properties": {
    "iso:country":"US",
    "sg:address":"21310 Harken Dr",
    "sg:city":"Cornelius",
    "sg:classifiers":[
        {
            "category":"Professional",
            "type":"Services"
        }
    ],
    "sg:phone":"+1 704 895 0937",
    "sg:postcode":"28031",
    "sg:province":"NC",
    "sg:tags":[
        "establishment"
    ],
    "wof:name":"Bluestone Harbor Homeowners",
    "wof:placetype":"venue"
},
  "geometry": {"coordinates":[-80.882768,35.487393],"type":"Point"}
}