{
  "type": "Feature",
  "properties": {
    "iso:country":"US",
    "sg:address":"1026 Hanes Mall Blvd",
    "sg:city":"Winston Salem",
    "sg:classifiers":[
        {
            "category":"Shopping",
            "subcategory":"Department Store",
            "type":"Retail Goods"
        }
    ],
    "sg:phone":"+1 336 760 9200",
    "sg:postcode":"27103",
    "sg:province":"NC",
    "sg:tags":[
        "shop"
    ],
    "wof:name":"Pier 1 Imports",
    "wof:placetype":"venue"
},
  "geometry": {"coordinates":[-80.31758600000001,36.066853],"type":"Point"}
}