{
  "type": "Feature",
  "properties": {
    "iso:country":"US",
    "sg:address":"1830 Eastchester Dr",
    "sg:city":"High Point",
    "sg:classifiers":[
        {
            "category":"Health Services",
            "subcategory":"Clinic",
            "type":"Services"
        }
    ],
    "sg:phone":"+1 336 885 1830",
    "sg:postcode":"27265",
    "sg:province":"NC",
    "sg:tags":[
        "home",
        "care"
    ],
    "wof:name":"Genesis Family Healthcare Inc",
    "wof:placetype":"venue"
},
  "geometry": {"coordinates":[-79.98597100000001,36.008492],"type":"Point"}
}