{
  "type": "Feature",
  "properties": {
    "addr:full":"2127 Flint Hill Church Rd Shelby NC 28152",
    "addr:housenumber":"2127",
    "addr:postcode":"28152",
    "addr:street":"Flint Hill Church Rd",
    "iso:country":"US",
    "sg:address":"2127 Flint Hill Church Rd",
    "sg:city":"Shelby",
    "sg:classifiers":[
        {
            "category":"Building & Trades",
            "subcategory":"Construction",
            "type":"Services"
        }
    ],
    "sg:phone":"+1 704 434 5273",
    "sg:postcode":"28152",
    "sg:province":"NC",
    "sg:tags":[
        "general",
        "contractor"
    ],
    "wof:name":"Denis Thurman Construction Co",
    "wof:placetype":"venue"
},
  "geometry": {"coordinates":[-81.645144,35.223495],"type":"Point"}
}