{
  "type": "Feature",
  "properties": {
    "addr:full":"1066 Reedy Creek Rd Lexington NC 27295",
    "addr:housenumber":"1066",
    "addr:postcode":"27295",
    "addr:street":"Reedy Creek Rd",
    "iso:country":"US",
    "sg:address":"1066 Reedy Creek Rd",
    "sg:city":"Lexington",
    "sg:classifiers":[
        {
            "category":"Building & Trades",
            "subcategory":"Construction",
            "type":"Services"
        }
    ],
    "sg:phone":"+1 336 731 3085",
    "sg:postcode":"27295",
    "sg:province":"NC",
    "sg:tags":[
        "contractor"
    ],
    "wof:name":"Rsp Custom Welding",
    "wof:placetype":"venue"
},
  "geometry": {"coordinates":[-80.318883,35.920023],"type":"Point"}
}