{
  "type": "Feature",
  "properties": {
    "addr:full":"2312 S Post Rd Shelby NC 28152",
    "addr:housenumber":"2312",
    "addr:postcode":"28152",
    "addr:street":"S Post Rd",
    "iso:country":"US",
    "sg:address":"2312 S Post Rd",
    "sg:city":"Shelby",
    "sg:classifiers":[
        {
            "category":"Restaurant",
            "type":"Food & Drink"
        }
    ],
    "sg:phone":"+1 704 482 7686",
    "sg:postcode":"28152",
    "sg:province":"NC",
    "sg:tags":[
        "eating"
    ],
    "wof:name":"Jacks Fast Food Inc",
    "wof:placetype":"venue"
},
  "geometry": {"coordinates":[-81.52874799999999,35.224481],"type":"Point"}
}