{
  "type": "Feature",
  "properties": {
    "addr:full":"700 N Lincoln St Benson NC 27504",
    "addr:housenumber":"700",
    "addr:postcode":"27504",
    "addr:street":"N Lincoln St",
    "iso:country":"US",
    "sg:address":"700 N Lincoln St",
    "sg:city":"Benson",
    "sg:classifiers":[
        {
            "category":"Wholesale",
            "subcategory":"Construction Materials",
            "type":"Manufacturing & Wholesale Goods"
        }
    ],
    "sg:phone":"+1 919 894 8867",
    "sg:postcode":"27504",
    "sg:province":"NC",
    "sg:tags":[
        "fence"
    ],
    "wof:name":"Medlin Electric Fencer Repair",
    "wof:placetype":"venue"
},
  "geometry": {"coordinates":[-78.55449299999999,35.391259],"type":"Point"}
}