{
  "type": "Feature",
  "properties": {
    "iso:country":"US",
    "sg:address":"585 Brick Mill Rd",
    "sg:city":"Coats",
    "sg:classifiers":[
        {
            "category":"Education",
            "subcategory":"School",
            "type":"Public Place"
        }
    ],
    "sg:phone":"+1 910 897 8353",
    "sg:postcode":"27521",
    "sg:province":"NC",
    "wof:name":"Coats Elementary School",
    "wof:placetype":"venue"
},
  "geometry": {"coordinates":[-78.683719,35.398605],"type":"Point"}
}