{
  "type": "Feature",
  "properties": {
    "addr:full":"4571 Gilmore Dr Liberty NC 27298",
    "addr:housenumber":"4571",
    "addr:postcode":"27298",
    "addr:street":"Gilmore Dr",
    "iso:country":"US",
    "sg:address":"4571 Gilmore Dr",
    "sg:city":"Liberty",
    "sg:classifiers":[
        {
            "category":"Retail",
            "subcategory":"Repair Shop",
            "type":"Services"
        }
    ],
    "sg:phone":"+1   ",
    "sg:postcode":"27298",
    "sg:province":"NC",
    "wof:name":"Mechanical Maintenance Inc",
    "wof:placetype":"venue"
},
  "geometry": {"coordinates":[-79.644274,35.870903],"type":"Point"}
}