{
  "type": "Feature",
  "properties": {
    "addr:full":"6260 Glenwood Ave Raleigh NC 27612",
    "addr:housenumber":"6260",
    "addr:postcode":"27612",
    "addr:street":"Glenwood Ave",
    "iso:country":"US",
    "sg:address":"6260 Glenwood Ave",
    "sg:city":"Raleigh",
    "sg:classifiers":[
        {
            "category":"Banks & Credit Unions",
            "subcategory":"Bank",
            "type":"Services"
        }
    ],
    "sg:phone":"+1 919 782 3510",
    "sg:postcode":"27612",
    "sg:province":"NC",
    "sg:tags":[
        "national"
    ],
    "wof:name":"Wells Fargo",
    "wof:placetype":"venue"
},
  "geometry": {"coordinates":[-78.700692,35.855028],"type":"Point"}
}