{
  "type": "Feature",
  "properties": {
    "iso:country":"US",
    "sg:address":"400 Crown Creek Dr",
    "sg:city":"Cherryville",
    "sg:classifiers":[
        {
            "category":"Building & Trades",
            "subcategory":"Construction",
            "type":"Services"
        }
    ],
    "sg:phone":"+1 704 435 8086",
    "sg:postcode":"28021",
    "sg:province":"NC",
    "sg:tags":[
        "contractor"
    ],
    "wof:name":"Randy Heffner",
    "wof:placetype":"venue"
},
  "geometry": {"coordinates":[-81.393272,35.36322],"type":"Point"}
}