{
  "type": "Feature",
  "properties": {
    "iso:country":"US",
    "sg:address":"414 W Atkins St",
    "sg:city":"Dobson",
    "sg:classifiers":[
        {
            "category":"Social Services",
            "subcategory":"Child Care",
            "type":"Services"
        },
        {
            "category":"Education",
            "subcategory":"School",
            "type":"Public Place"
        }
    ],
    "sg:phone":"+1 336 386 8913",
    "sg:postcode":"27017",
    "sg:province":"NC",
    "sg:tags":[
        "day"
    ],
    "wof:name":"Dobson Elementary School Child",
    "wof:placetype":"venue"
},
  "geometry": {"coordinates":[-80.72650899999999,36.394311],"type":"Point"}
}