{
  "type": "Feature",
  "properties": {
    "addr:full":"3381 Treyburn Dr Midland NC 28107",
    "addr:housenumber":"3381",
    "addr:postcode":"28107",
    "addr:street":"Treyburn Dr",
    "iso:country":"US",
    "sg:address":"3381 Treyburn Dr",
    "sg:city":"Midland",
    "sg:classifiers":[
        {
            "category":"Building & Trades",
            "subcategory":"Construction",
            "type":"Services"
        }
    ],
    "sg:phone":"+1 704 792 1642",
    "sg:postcode":"28107",
    "sg:province":"NC",
    "sg:tags":[
        "house"
    ],
    "wof:name":"Peoples Construction Comp",
    "wof:placetype":"venue"
},
  "geometry": {"coordinates":[-80.518964,35.271332],"type":"Point"}
}