{
  "type": "Feature",
  "properties": {
    "iso:country":"US",
    "sg:address":"211 Clubhouse Rd",
    "sg:city":"Sunset Beach",
    "sg:classifiers":[
        {
            "category":"Real Estate",
            "subcategory":"Developer",
            "type":"Services"
        }
    ],
    "sg:phone":"+1 910 287 1100",
    "sg:postcode":"28468",
    "sg:province":"NC",
    "sg:tags":[
        "public",
        "g"
    ],
    "wof:name":"Sea Trail Realty",
    "wof:placetype":"venue"
},
  "geometry": {"coordinates":[-78.513312,33.887731],"type":"Point"}
}