{
  "type": "Feature",
  "properties": {
    "iso:country":"US",
    "sg:address":"1006 N Elm St",
    "sg:city":"Greensboro",
    "sg:classifiers":[
        {
            "category":"Professional",
            "type":"Services"
        }
    ],
    "sg:phone":"+1 336 379 0960",
    "sg:postcode":"27401",
    "sg:province":"NC",
    "wof:name":"Margaret Bell",
    "wof:placetype":"venue"
},
  "geometry": {"coordinates":[-79.78904300000001,36.087899],"type":"Point"}
}