{
  "type": "Feature",
  "properties": {
    "iso:country":"US",
    "sg:address":"5605 Oleander Dr",
    "sg:city":"Wilmington",
    "sg:classifiers":[
        {
            "category":"Personal",
            "subcategory":"Beauty Salon",
            "type":"Services"
        }
    ],
    "sg:phone":"+1 910 392 2609",
    "sg:postcode":"28403",
    "sg:province":"NC",
    "wof:name":"Eloise's Innovative Hair Salon",
    "wof:placetype":"venue"
},
  "geometry": {"coordinates":[-77.85122800000001,34.20894],"type":"Point"}
}