{
  "type": "Feature",
  "properties": {
    "addr:full":"291 Pilot-Riley Rd Zebulon NC 27597",
    "addr:housenumber":"291",
    "addr:postcode":"27597",
    "addr:street":"Pilot-Riley Rd",
    "iso:country":"US",
    "sg:address":"291 Pilot-Riley Rd",
    "sg:city":"Zebulon",
    "sg:classifiers":[
        {
            "category":"Restaurant",
            "type":"Food & Drink"
        }
    ],
    "sg:phone":"+1 919 404 0590",
    "sg:postcode":"27597",
    "sg:province":"NC",
    "sg:tags":[
        "eating"
    ],
    "wof:name":"Personal Chefs Network",
    "wof:placetype":"venue"
},
  "geometry": {"coordinates":[-78.276385,35.89459],"type":"Point"}
}