{
  "type": "Feature",
  "properties": {
    "addr:full":"1806 Martin Farm Rd Madison NC 27025",
    "addr:housenumber":"1806",
    "addr:postcode":"27025",
    "addr:street":"Martin Farm Rd",
    "iso:country":"US",
    "sg:address":"1806 Martin Farm Rd",
    "sg:city":"Madison",
    "sg:classifiers":[
        {
            "category":"Building & Trades",
            "subcategory":"Electrical",
            "type":"Services"
        }
    ],
    "sg:phone":"+1 336 548 1015",
    "sg:postcode":"27025",
    "sg:province":"NC",
    "sg:tags":[
        "electrical",
        "electric",
        "contractor"
    ],
    "wof:name":"Bruce Shaw Electric Service",
    "wof:placetype":"venue"
},
  "geometry": {"coordinates":[-80.05897400000001,36.43486],"type":"Point"}
}