{
  "type": "Feature",
  "properties": {
    "iso:country":"US",
    "sg:address":"1103 Massey Farm Rd",
    "sg:city":"Knightdale",
    "sg:classifiers":[
        {
            "category":"Professional",
            "subcategory":"Business Services",
            "type":"Services"
        }
    ],
    "sg:phone":"+1   ",
    "sg:postcode":"27545",
    "sg:province":"NC",
    "wof:name":"V Lynne & Co",
    "wof:placetype":"venue"
},
  "geometry": {"coordinates":[-78.46530199999999,35.79745],"type":"Point"}
}