{
  "type": "Feature",
  "properties": {
    "addr:full":"6325 Falls Of Neuse Rd Ste 19 Raleigh NC 27615",
    "addr:housenumber":"6325;19",
    "addr:postcode":"27615",
    "addr:street":"Falls Of Neuse Rd Ste",
    "iso:country":"US",
    "sg:address":"6325 Falls Of Neuse Rd Ste 19",
    "sg:city":"Raleigh",
    "sg:phone":"+1 919 872 7161",
    "sg:postcode":"27615",
    "sg:province":"NC",
    "wof:name":"Taza Grill",
    "wof:placetype":"venue"
},
  "geometry": {"coordinates":[-78.62087699999999,35.868486],"type":"Point"}
}