{
  "type": "Feature",
  "properties": {
    "iso:country":"US",
    "sg:address":"402 Green Valley Rd",
    "sg:city":"Leicester",
    "sg:classifiers":[
        {
            "category":"Shopping",
            "type":"Retail Goods"
        }
    ],
    "sg:phone":"+1 828 683 3486",
    "sg:postcode":"28748",
    "sg:province":"NC",
    "sg:tags":[
        "merchandise"
    ],
    "wof:name":"Brevard Trophy",
    "wof:placetype":"venue"
},
  "geometry": {"coordinates":[-82.72571600000001,35.631427],"type":"Point"}
}