{
  "type": "Feature",
  "properties": {
    "addr:full":"633 State Hwy 150 W Greensboro NC 27455",
    "addr:housenumber":"633",
    "addr:postcode":"27455",
    "addr:street":"State Hwy 150 W",
    "iso:country":"US",
    "sg:address":"633 State Hwy 150 W",
    "sg:city":"Greensboro",
    "sg:classifiers":[
        {
            "category":"Organizations",
            "subcategory":"Religious Organization",
            "type":"Services"
        }
    ],
    "sg:phone":"+1 336 643 6228",
    "sg:postcode":"27455",
    "sg:province":"NC",
    "sg:tags":[
        "church"
    ],
    "wof:name":"St Thomas Chapel Pentecostal",
    "wof:placetype":"venue"
},
  "geometry": {"coordinates":[-79.819326,36.212807],"type":"Point"}
}