{
  "type": "Feature",
  "properties": {
    "addr:full":"1629 Stan Hope St Fayetteville NC 28304",
    "addr:housenumber":"1629",
    "addr:postcode":"28304",
    "addr:street":"Stan Hope St",
    "iso:country":"US",
    "sg:address":"1629 Stan Hope St",
    "sg:city":"Fayetteville",
    "sg:classifiers":[
        {
            "category":"Retail",
            "subcategory":"Animal Services",
            "type":"Services"
        }
    ],
    "sg:phone":"+1 910 423 0303",
    "sg:postcode":"28304",
    "sg:province":"NC",
    "wof:name":"Loving Care Dog Grooming",
    "wof:placetype":"venue"
},
  "geometry": {"coordinates":[-79.00538400000001,35.025224],"type":"Point"}
}