{
  "type": "Feature",
  "properties": {
    "iso:country":"US",
    "sg:address":"4518 S Miami Blvd",
    "sg:city":"Durham",
    "sg:classifiers":[
        {
            "category":"Professional",
            "type":"Services"
        }
    ],
    "sg:phone":"+1 919 474 3015",
    "sg:postcode":"27703",
    "sg:province":"NC",
    "sg:tags":[
        "establishment"
    ],
    "wof:name":"Epic International Inc",
    "wof:placetype":"venue"
},
  "geometry": {"coordinates":[-78.84922,35.897014],"type":"Point"}
}