{
  "type": "Feature",
  "properties": {
    "addr:full":"401 Park Ridge Rd Albemarle NC 28001",
    "addr:housenumber":"401",
    "addr:postcode":"28001",
    "addr:street":"Park Ridge Rd",
    "iso:country":"US",
    "sg:address":"401 Park Ridge Rd",
    "sg:city":"Albemarle",
    "sg:classifiers":[
        {
            "category":"Organizations",
            "subcategory":"Religious Organization",
            "type":"Services"
        }
    ],
    "sg:phone":"+1 704 983 3146",
    "sg:postcode":"28001",
    "sg:province":"NC",
    "sg:tags":[
        "church"
    ],
    "sg:website":"www.northabc.net",
    "wof:name":"North Albemarle Baptist Church",
    "wof:placetype":"venue"
},
  "geometry": {"coordinates":[-80.189418,35.370961],"type":"Point"}
}