{
  "type": "Feature",
  "properties": {
    "iso:country":"US",
    "sg:address":"1804 Joy Dr",
    "sg:city":"Denver",
    "sg:classifiers":[
        {
            "category":"Building & Trades",
            "subcategory":"Electrical",
            "type":"Services"
        }
    ],
    "sg:phone":"+1 704 489 0378",
    "sg:postcode":"28037",
    "sg:province":"NC",
    "sg:tags":[
        "electrical",
        "contractor"
    ],
    "wof:name":"P M B Electric Co",
    "wof:placetype":"venue"
},
  "geometry": {"coordinates":[-80.97841200000001,35.475248],"type":"Point"}
}