{
  "type": "Feature",
  "properties": {
    "addr:full":"4715 Hoots Hollow Rd Liberty NC 27298",
    "addr:postcode":"4715;27298",
    "addr:street":"Hoots Hollow Rd",
    "iso:country":"US",
    "sg:address":"4715 Hoots Hollow Rd",
    "sg:city":"Liberty",
    "sg:classifiers":[
        {
            "category":"Sports & Exercise",
            "subcategory":"Gym",
            "type":"Entertainment"
        }
    ],
    "sg:phone":"+1 336 622 3886",
    "sg:postcode":"27298",
    "sg:province":"NC",
    "sg:tags":[
        "gymnasium"
    ],
    "wof:name":"King's Gym Inc",
    "wof:placetype":"venue"
},
  "geometry": {"coordinates":[-79.62352,35.87867],"type":"Point"}
}