{
  "type": "Feature",
  "properties": {
    "iso:country":"US",
    "sg:address":"1163 Grassy Knob Rd",
    "sg:city":"Pilot Mountain",
    "sg:classifiers":[
        {
            "category":"Building & Trades",
            "subcategory":"Landscaping Services",
            "type":"Services"
        }
    ],
    "sg:phone":"+1 336 368 4934",
    "sg:postcode":"27041",
    "sg:province":"NC",
    "sg:tags":[
        "landscape"
    ],
    "wof:name":"Grassy Knob Beautification",
    "wof:placetype":"venue"
},
  "geometry": {"coordinates":[-80.44492,36.384396],"type":"Point"}
}