{
  "type": "Feature",
  "properties": {
    "iso:country":"US",
    "sg:address":"2100 Stantonsburg Rd",
    "sg:city":"Greenville",
    "sg:classifiers":[
        {
            "category":"Health Services",
            "subcategory":"Hospital",
            "type":"Services"
        }
    ],
    "sg:phone":"+1 252 816 4100",
    "sg:postcode":"27834",
    "sg:province":"NC",
    "sg:tags":[
        "medical",
        "surgical",
        "general"
    ],
    "wof:name":"Pitt County Memorial Hospital",
    "wof:placetype":"venue"
},
  "geometry": {"coordinates":[-77.400835,35.605844],"type":"Point"}
}