{
  "type": "Feature",
  "properties": {
    "iso:country":"US",
    "sg:address":"601 E Sugar Creek Rd",
    "sg:city":"Charlotte",
    "sg:classifiers":[
        {
            "category":"Retail",
            "subcategory":"Auto Repair",
            "type":"Services"
        }
    ],
    "sg:phone":"+1 704 509 0619",
    "sg:postcode":"28213",
    "sg:province":"NC",
    "sg:tags":[
        "brake"
    ],
    "wof:name":"Page Brake Co",
    "wof:placetype":"venue"
},
  "geometry": {"coordinates":[-80.791124,35.251456],"type":"Point"}
}