{
  "type": "Feature",
  "properties": {
    "iso:country":"US",
    "sg:address":"304 Barbee Rd",
    "sg:city":"Richlands",
    "sg:classifiers":[
        {
            "category":"Organizations",
            "subcategory":"Religious Organization",
            "type":"Services"
        }
    ],
    "sg:phone":"+1 910 324 5013",
    "sg:postcode":"28574",
    "sg:province":"NC",
    "sg:tags":[
        "church"
    ],
    "wof:name":"Richlands First Free Will Chr",
    "wof:placetype":"venue"
},
  "geometry": {"coordinates":[-77.572672,34.951216],"type":"Point"}
}