{
  "type": "Feature",
  "properties": {
    "iso:country":"US",
    "sg:address":"131 Bethany Church Rd",
    "sg:city":"Forest City",
    "sg:classifiers":[
        {
            "category":"Restaurant",
            "type":"Food & Drink"
        }
    ],
    "sg:menulink":"http://www.allmenus.com/nc/cool-spring/183340-kfc---kentucky-fried-chicken/menu/",
    "sg:phone":"+1 828 245 5716",
    "sg:postcode":"28043",
    "sg:province":"NC",
    "sg:tags":[
        "american",
        "chicken"
    ],
    "wof:name":"KFC - Kentucky Fried Chicken",
    "wof:placetype":"venue"
},
  "geometry": {"coordinates":[-81.881462,35.317732],"type":"Point"}
}