{
  "type": "Feature",
  "properties": {
    "iso:country":"US",
    "sg:address":"5709 Tomahawk Trl",
    "sg:city":"Durham",
    "sg:classifiers":[
        {
            "category":"Building & Trades",
            "subcategory":"Plumbing",
            "type":"Services"
        }
    ],
    "sg:phone":"+1 919 479 6636",
    "sg:postcode":"27712",
    "sg:province":"NC",
    "sg:tags":[
        "contractor"
    ],
    "wof:name":"Horizon Heating & AC SC",
    "wof:placetype":"venue"
},
  "geometry": {"coordinates":[-78.901899,36.101708],"type":"Point"}
}