{
  "type": "Feature",
  "properties": {
    "addr:full":"121 Swain St Fayetteville NC 28303",
    "addr:housenumber":"121",
    "addr:postcode":"28303",
    "addr:street":"Swain St",
    "iso:country":"US",
    "sg:address":"121 Swain St",
    "sg:city":"Fayetteville",
    "sg:classifiers":[
        {
            "category":"Autos & Motor Vehicles",
            "subcategory":"Automobile Sales",
            "type":"Retail Goods"
        }
    ],
    "sg:phone":"+1 910 868 6180",
    "sg:postcode":"28303",
    "sg:province":"NC",
    "sg:tags":[
        "used"
    ],
    "wof:name":"Tonys Used Cars & Salvage",
    "wof:placetype":"venue"
},
  "geometry": {"coordinates":[-78.95280700000001,35.086086],"type":"Point"}
}