{
  "type": "Feature",
  "properties": {
    "iso:country":"US",
    "sg:address":"703 Margrace Rd",
    "sg:city":"Kings Mountain",
    "sg:classifiers":[
        {
            "category":"Organizations",
            "subcategory":"Religious Organization",
            "type":"Services"
        }
    ],
    "sg:phone":"+1 704 739 6711",
    "sg:postcode":"28086",
    "sg:province":"NC",
    "sg:tags":[
        "church"
    ],
    "wof:name":"Midview Baptist Church",
    "wof:placetype":"venue"
},
  "geometry": {"coordinates":[-81.383467,35.212185],"type":"Point"}
}