{
  "type": "Feature",
  "properties": {
    "addr:full":"1400 Medford Dr Charlotte NC 28205",
    "addr:housenumber":"1400",
    "addr:postcode":"28205",
    "addr:street":"Medford Dr",
    "iso:country":"US",
    "sg:address":"1400 Medford Dr",
    "sg:city":"Charlotte",
    "sg:classifiers":[
        {
            "category":"Banks & Credit Unions",
            "subcategory":"Financial Services",
            "type":"Services"
        }
    ],
    "sg:phone":"+1 704 537 0537",
    "sg:postcode":"28205",
    "sg:province":"NC",
    "sg:tags":[
        "company",
        "investment"
    ],
    "wof:name":"Morris Investment Company",
    "wof:placetype":"venue"
},
  "geometry": {"coordinates":[-80.779836,35.213046],"type":"Point"}
}