{
  "type": "Feature",
  "properties": {
    "addr:full":"503 Cox Ave Thomasville NC 27360",
    "addr:housenumber":"503",
    "addr:postcode":"27360",
    "addr:street":"Cox Ave",
    "iso:country":"US",
    "sg:address":"503 Cox Ave",
    "sg:city":"Thomasville",
    "sg:classifiers":[
        {
            "category":"Building & Trades",
            "subcategory":"Construction",
            "type":"Services"
        }
    ],
    "sg:phone":"+1 336 475 6200",
    "sg:postcode":"27360",
    "sg:province":"NC",
    "sg:tags":[
        "contractor"
    ],
    "wof:name":"Steve WEBB Construction",
    "wof:placetype":"venue"
},
  "geometry": {"coordinates":[-80.076519,35.891897],"type":"Point"}
}