{
  "type": "Feature",
  "properties": {
    "addr:full":"3030 Burke Mill Rd Winston Salem NC 27103",
    "addr:housenumber":"3030",
    "addr:postcode":"27103",
    "addr:street":"Burke Mill Rd",
    "iso:country":"US",
    "sg:address":"3030 Burke Mill Rd",
    "sg:city":"Winston Salem",
    "sg:classifiers":[
        {
            "category":"Organizations",
            "subcategory":"Religious Organization",
            "type":"Services"
        }
    ],
    "sg:phone":"+1   ",
    "sg:postcode":"27103",
    "sg:province":"NC",
    "wof:name":"Grace Free Presbyterian Church",
    "wof:placetype":"venue"
},
  "geometry": {"coordinates":[-80.302452,36.056121],"type":"Point"}
}