{
  "type": "Feature",
  "properties": {
    "addr:full":"131 Wades Way Mooresville NC 28117",
    "addr:housenumber":"131",
    "addr:postcode":"28117",
    "addr:street":"Wades Way",
    "iso:country":"US",
    "sg:address":"131 Wades Way",
    "sg:city":"Mooresville",
    "sg:classifiers":[
        {
            "category":"Wholesale",
            "subcategory":"Electrical",
            "type":"Manufacturing & Wholesale Goods"
        }
    ],
    "sg:phone":"+1 704 895 0041",
    "sg:postcode":"28117",
    "sg:province":"NC",
    "sg:tags":[
        "alarm",
        "burglar",
        "system"
    ],
    "wof:name":"Pro-Tech Security",
    "wof:placetype":"venue"
},
  "geometry": {"coordinates":[-80.862666,35.534296],"type":"Point"}
}