{
  "type": "Feature",
  "properties": {
    "iso:country":"US",
    "sg:address":"475 Buck Swamp Rd",
    "sg:city":"Goldsboro",
    "sg:classifiers":[
        {
            "category":"Personal",
            "subcategory":"Beauty Salon",
            "type":"Services"
        }
    ],
    "sg:phone":"+1 919 581 0190",
    "sg:postcode":"27530",
    "sg:province":"NC",
    "sg:tags":[
        "shop"
    ],
    "sg:website":"www.headdresssalon.com",
    "wof:name":"Headdress Salon & Spa",
    "wof:placetype":"venue"
},
  "geometry": {"coordinates":[-78.008816,35.44426],"type":"Point"}
}