{
  "type": "Feature",
  "properties": {
    "addr:full":"1668 Jones Rd King NC 27021",
    "addr:housenumber":"1668",
    "addr:postcode":"27021",
    "addr:street":"Jones Rd",
    "iso:country":"US",
    "sg:address":"1668 Jones Rd",
    "sg:city":"King",
    "sg:phone":"+1 336 983 4471",
    "sg:postcode":"27021",
    "sg:province":"NC",
    "sg:tags":[
        "wheat",
        "tobacco",
        "farm",
        "corn",
        "crop",
        "field"
    ],
    "wof:name":"Carlton Jones",
    "wof:placetype":"venue"
},
  "geometry": {"coordinates":[-80.310266,36.328672],"type":"Point"}
}