{
  "type": "Feature",
  "properties": {
    "addr:full":"1001 Wendell Rd Wendell NC 27591",
    "addr:housenumber":"1001",
    "addr:postcode":"27591",
    "addr:street":"Wendell Rd",
    "iso:country":"US",
    "sg:address":"1001 Wendell Rd",
    "sg:city":"Wendell",
    "sg:classifiers":[
        {
            "category":"Professional",
            "type":"Services"
        },
        {
            "category":"Autos & Motor Vehicles",
            "subcategory":"Fuel & Gas Station",
            "type":"Retail Goods"
        }
    ],
    "sg:phone":"+1 919 365 4837",
    "sg:postcode":"27591",
    "sg:province":"NC",
    "sg:tags":[
        "establishment",
        "station",
        "gasoline"
    ],
    "wof:name":"Measurements Group Lift Statio",
    "wof:placetype":"venue"
},
  "geometry": {"coordinates":[-78.366827,35.705578],"type":"Point"}
}