{
  "type": "Feature",
  "properties": {
    "iso:country":"US",
    "sg:address":"612 S Front St",
    "sg:city":"Wilmington",
    "sg:classifiers":[
        {
            "category":"Wholesale",
            "subcategory":"Construction Materials",
            "type":"Manufacturing & Wholesale Goods"
        }
    ],
    "sg:phone":"+1 910 763 4960",
    "sg:postcode":"28401",
    "sg:province":"NC",
    "sg:tags":[
        "fence"
    ],
    "wof:name":"Mc Call's Hurricane Fence Co",
    "wof:placetype":"venue"
},
  "geometry": {"coordinates":[-77.947762,34.226664],"type":"Point"}
}