{
  "type": "Feature",
  "properties": {
    "addr:full":"32481 Charlie Rd Albemarle NC 28001",
    "addr:housenumber":"32481",
    "addr:postcode":"28001",
    "addr:street":"Charlie Rd",
    "iso:country":"US",
    "sg:address":"32481 Charlie Rd",
    "sg:city":"Albemarle",
    "sg:classifiers":[
        {
            "category":"Building & Trades",
            "subcategory":"Cleaning & Sanitation",
            "type":"Services"
        }
    ],
    "sg:phone":"+1   ",
    "sg:postcode":"28001",
    "sg:province":"NC",
    "sg:tags":[
        "maintenance"
    ],
    "wof:name":"Inspirational Cleaning & Jntrl",
    "wof:placetype":"venue"
},
  "geometry": {"coordinates":[-80.224318,35.372792],"type":"Point"}
}