{
  "type": "Feature",
  "properties": {
    "iso:country":"US",
    "sg:address":"1076 State Hwy 58",
    "sg:city":"Cape Carteret",
    "sg:classifiers":[
        {
            "category":"Organizations",
            "subcategory":"Religious Organization",
            "type":"Services"
        }
    ],
    "sg:phone":"+1 252 393 6424",
    "sg:postcode":"28584",
    "sg:province":"NC",
    "sg:tags":[
        "church"
    ],
    "wof:name":"Swansboro Bible Church Inc",
    "wof:placetype":"venue"
},
  "geometry": {"coordinates":[-77.067938,34.714255],"type":"Point"}
}