{
  "type": "Feature",
  "properties": {
    "iso:country":"US",
    "sg:address":"6 Bentwood Pl",
    "sg:city":"Durham",
    "sg:classifiers":[
        {
            "category":"Real Estate",
            "subcategory":"Real Estate Operator",
            "type":"Services"
        }
    ],
    "sg:phone":"+1 919 321 0379",
    "sg:postcode":"27703",
    "sg:province":"NC",
    "sg:tags":[
        "building",
        "nonresidential"
    ],
    "wof:name":"Alkan Properties",
    "wof:placetype":"venue"
},
  "geometry": {"coordinates":[-78.82665799999999,35.992779],"type":"Point"}
}