{
  "type": "Feature",
  "properties": {
    "iso:country":"US",
    "sg:address":"137 Brookgreen Ln",
    "sg:city":"Hendersonville",
    "sg:classifiers":[
        {
            "category":"Professional",
            "subcategory":"Advertising",
            "type":"Services"
        }
    ],
    "sg:phone":"+1 828 692 7200",
    "sg:postcode":"28739",
    "sg:province":"NC",
    "wof:name":"Molton Advertising LLC",
    "wof:placetype":"venue"
},
  "geometry": {"coordinates":[-82.508101,35.301581],"type":"Point"}
}