{
  "type": "Feature",
  "properties": {
    "iso:country":"US",
    "sg:address":"3703 Gillespie St",
    "sg:city":"Fayetteville",
    "sg:classifiers":[
        {
            "category":"Retail",
            "subcategory":"Auto Rental",
            "type":"Services"
        }
    ],
    "sg:phone":"+1 910 483 3635",
    "sg:postcode":"28306",
    "sg:province":"NC",
    "sg:tags":[
        "renting",
        "leasing",
        "trailer"
    ],
    "wof:name":"Mobile Storage Group Inc",
    "wof:placetype":"venue"
},
  "geometry": {"coordinates":[-78.907156,34.980858],"type":"Point"}
}