{
  "type": "Feature",
  "properties": {
    "addr:full":"3639 Joel Turner Dr Charlotte NC 28216",
    "addr:housenumber":"3639",
    "addr:postcode":"28216",
    "addr:street":"Joel Turner Dr",
    "iso:country":"US",
    "sg:address":"3639 Joel Turner Dr",
    "sg:city":"Charlotte",
    "sg:classifiers":[
        {
            "category":"Building & Trades",
            "subcategory":"Construction",
            "type":"Services"
        }
    ],
    "sg:phone":"+1 704 393 5383",
    "sg:postcode":"28216",
    "sg:province":"NC",
    "sg:tags":[
        "home",
        "builder"
    ],
    "wof:name":"Brookwood Home Builders",
    "wof:placetype":"venue"
},
  "geometry": {"coordinates":[-80.892888,35.318759],"type":"Point"}
}