{
  "type": "Feature",
  "properties": {
    "iso:country":"US",
    "sg:address":"1423 Mordecai Dr",
    "sg:city":"Raleigh",
    "sg:classifiers":[
        {
            "category":"Manufacturing",
            "subcategory":"Jewelry",
            "type":"Manufacturing & Wholesale Goods"
        }
    ],
    "sg:phone":"+1 919 829 8074",
    "sg:postcode":"27604",
    "sg:province":"NC",
    "sg:tags":[
        "costume",
        "mfg"
    ],
    "wof:name":"Pendergast Designs",
    "wof:placetype":"venue"
},
  "geometry": {"coordinates":[-78.627729,35.799574],"type":"Point"}
}