{
  "type": "Feature",
  "properties": {
    "addr:full":"8705 Golf Ridge Dr Charlotte NC 28277",
    "addr:housenumber":"8705",
    "addr:postcode":"28277",
    "addr:street":"Golf Ridge Dr",
    "iso:country":"US",
    "sg:address":"8705 Golf Ridge Dr",
    "sg:city":"Charlotte",
    "sg:classifiers":[
        {
            "category":"Freight",
            "type":"Transportation"
        }
    ],
    "sg:phone":"+1 704 846 0666",
    "sg:postcode":"28277",
    "sg:province":"NC",
    "sg:tags":[
        "forwarding",
        "arrangement"
    ],
    "wof:name":"Federated Transport Systems Inc",
    "wof:placetype":"venue"
},
  "geometry": {"coordinates":[-80.79635399999999,35.073716],"type":"Point"}
}