{
  "type": "Feature",
  "properties": {
    "iso:country":"US",
    "sg:address":"2210 W Morehead St",
    "sg:city":"Charlotte",
    "sg:classifiers":[
        {
            "category":"Food & Beverages",
            "subcategory":"Groceries & Convenience Stores",
            "type":"Retail Goods"
        }
    ],
    "sg:phone":"+1 704 342 0540",
    "sg:postcode":"28208",
    "sg:province":"NC",
    "wof:name":"N&R Grocery Inc",
    "wof:placetype":"venue"
},
  "geometry": {"coordinates":[-80.87671899999999,35.225706],"type":"Point"}
}