{
  "type": "Feature",
  "properties": {
    "addr:full":"104 College Dr Flat Rock NC 28731",
    "addr:housenumber":"104",
    "addr:postcode":"28731",
    "addr:street":"College Dr",
    "iso:country":"US",
    "sg:address":"104 College Dr",
    "sg:city":"Flat Rock",
    "sg:classifiers":[
        {
            "category":"Personal",
            "subcategory":"Beauty Salon",
            "type":"Services"
        }
    ],
    "sg:phone":"+1 828 693 7697",
    "sg:postcode":"28731",
    "sg:province":"NC",
    "wof:name":"Pardee Care Ctr Beauty Shop",
    "wof:placetype":"venue"
},
  "geometry": {"coordinates":[-82.41867999999999,35.303843],"type":"Point"}
}