{
  "type": "Feature",
  "properties": {
    "iso:country":"US",
    "sg:address":"1219 Forest Bluff Dr",
    "sg:city":"Midland",
    "sg:classifiers":[
        {
            "category":"Building & Trades",
            "subcategory":"Plumbing",
            "type":"Services"
        }
    ],
    "sg:phone":"+1 704 888 8535",
    "sg:postcode":"28107",
    "sg:province":"NC",
    "sg:tags":[
        "contractor"
    ],
    "wof:name":"Fred Little Heating & Air Inc",
    "wof:placetype":"venue"
},
  "geometry": {"coordinates":[-80.550614,35.21846],"type":"Point"}
}