{
  "type": "Feature",
  "properties": {
    "iso:country":"US",
    "sg:address":"1928 South Blvd Ste 200",
    "sg:city":"Charlotte",
    "sg:classifiers":[
        {
            "category":"Restaurant",
            "type":"Food & Drink"
        }
    ],
    "sg:phone":"+1 704 893 8476",
    "sg:postcode":"28203",
    "sg:province":"NC",
    "sg:tags":[
        "house",
        "seafood",
        "steak",
        "american"
    ],
    "sg:website":"http://charlotte.citysearch.com/profile/external/6270699/charlotte_nc/sullivan_s_steakhouse_charlotte.html?publisher=yellowpages&reference_id=15&placement=ypwebsitemip",
    "wof:name":"Sullivan's Steakhouse - Charlotte",
    "wof:placetype":"venue"
},
  "geometry": {"coordinates":[-80.859521,35.210082],"type":"Point"}
}