{
  "type": "Feature",
  "properties": {
    "iso:country":"US",
    "sg:address":"2412 Concord Hwy",
    "sg:city":"Monroe",
    "sg:classifiers":[
        {
            "category":"Food & Beverages",
            "subcategory":"Groceries & Convenience Stores",
            "type":"Retail Goods"
        }
    ],
    "sg:phone":"+1 704 289 8630",
    "sg:postcode":"28110",
    "sg:province":"NC",
    "sg:tags":[
        "station",
        "gasoline"
    ],
    "wof:name":"601 Food Mart",
    "wof:placetype":"venue"
},
  "geometry": {"coordinates":[-80.541731,35.019213],"type":"Point"}
}