{
  "type": "Feature",
  "properties": {
    "iso:country":"US",
    "sg:address":"307 Long Cir",
    "sg:city":"Roanoke Rapids",
    "sg:classifiers":[
        {
            "category":"Real Estate",
            "subcategory":"Real Estate Agent",
            "type":"Services"
        }
    ],
    "sg:phone":"+1 252 537 9873",
    "sg:postcode":"27870",
    "sg:province":"NC",
    "wof:name":"Heaton Real Estate",
    "wof:placetype":"venue"
},
  "geometry": {"coordinates":[-77.64190600000001,36.445652],"type":"Point"}
}