{
  "type": "Feature",
  "properties": {
    "iso:country":"US",
    "sg:address":"628 N Main St",
    "sg:city":"Salisbury",
    "sg:classifiers":[
        {
            "category":"Health Services",
            "subcategory":"Clinic",
            "type":"Services"
        },
        {
            "category":"Health Services",
            "subcategory":"Health Practitioner",
            "type":"Services"
        }
    ],
    "sg:phone":"+1 704 637 0053",
    "sg:postcode":"28144",
    "sg:province":"NC",
    "sg:tags":[
        "nutritionist"
    ],
    "wof:name":"Nutrition For Brighter Beginin",
    "wof:placetype":"venue"
},
  "geometry": {"coordinates":[-80.463465,35.672454],"type":"Point"}
}