{
  "type": "Feature",
  "properties": {
    "addr:full":"5545 Racine Ave Charlotte NC 28269",
    "addr:housenumber":"5545",
    "addr:postcode":"28269",
    "addr:street":"Racine Ave",
    "iso:country":"US",
    "sg:address":"5545 Racine Ave",
    "sg:city":"Charlotte",
    "sg:classifiers":[
        {
            "category":"Manufacturing",
            "subcategory":"Buildings",
            "type":"Manufacturing & Wholesale Goods"
        },
        {
            "category":"Retail",
            "subcategory":"Auto Rental",
            "type":"Services"
        },
        {
            "category":"Professional",
            "subcategory":"Business Services",
            "type":"Services"
        }
    ],
    "sg:phone":"+1 879 585 0645",
    "sg:postcode":"28269",
    "sg:province":"NC",
    "sg:tags":[
        "renting",
        "leasing",
        "modular",
        "mobile",
        "commercial",
        "trailers-offices",
        "prefabricated",
        "unit",
        "buildings-pre-cut",
        "modulars",
        "trailer"
    ],
    "sg:website":"http://www.pacvan.com/?utm_source=yellowpages&utm_medium=dir&utm_term=trailer_renting_leasing&utm_campaign=TRL",
    "wof:name":"Pac Van",
    "wof:placetype":"venue"
},
  "geometry": {"coordinates":[-80.799927,35.28828],"type":"Point"}
}