{
  "type": "Feature",
  "properties": {
    "iso:country":"US",
    "sg:address":"4474 Posterity Ct",
    "sg:city":"Gastonia",
    "sg:classifiers":[
        {
            "category":"Farming",
            "subcategory":"Nursery",
            "type":"Manufacturing & Wholesale Goods"
        }
    ],
    "sg:phone":"+1 704 824 8351",
    "sg:postcode":"28056",
    "sg:province":"NC",
    "sg:tags":[
        "turf"
    ],
    "wof:name":"Carolina Turf Equipment",
    "wof:placetype":"venue"
},
  "geometry": {"coordinates":[-81.113598,35.223309],"type":"Point"}
}