{
  "type": "Feature",
  "properties": {
    "iso:country":"US",
    "sg:address":"329 Huntsmoor Dr",
    "sg:city":"Charlotte",
    "sg:classifiers":[
        {
            "category":"Retail",
            "subcategory":"Repair Shop",
            "type":"Services"
        }
    ],
    "sg:phone":"+1   ",
    "sg:postcode":"28217",
    "sg:province":"NC",
    "wof:name":"H & A Team Cleaning Concept",
    "wof:placetype":"venue"
},
  "geometry": {"coordinates":[-80.89582900000001,35.136793],"type":"Point"}
}