{
  "type": "Feature",
  "properties": {
    "addr:full":"3206 Tommie Wooten Rd Chadbourn NC 28431",
    "addr:housenumber":"3206",
    "addr:postcode":"28431",
    "addr:street":"Tommie Wooten Rd",
    "iso:country":"US",
    "sg:address":"3206 Tommie Wooten Rd",
    "sg:city":"Chadbourn",
    "sg:classifiers":[
        {
            "category":"Manufacturing",
            "subcategory":"Printing",
            "type":"Manufacturing & Wholesale Goods"
        }
    ],
    "sg:phone":"+1 910 654 6317",
    "sg:postcode":"28431",
    "sg:province":"NC",
    "sg:tags":[
        "lithographic",
        "commercial"
    ],
    "wof:name":"Business Cards Galore",
    "wof:placetype":"venue"
},
  "geometry": {"coordinates":[-78.808432,34.366276],"type":"Point"}
}