{
  "type": "Feature",
  "properties": {
    "iso:country":"US",
    "sg:address":"6650 Brynwood Dr",
    "sg:city":"Charlotte",
    "sg:classifiers":[
        {
            "category":"Building & Trades",
            "subcategory":"Construction",
            "type":"Services"
        }
    ],
    "sg:phone":"+1 704 542 9123",
    "sg:postcode":"28226",
    "sg:province":"NC",
    "sg:tags":[
        "new",
        "residential"
    ],
    "wof:name":"Ethos Providence Lane LLC",
    "wof:placetype":"venue"
},
  "geometry": {"coordinates":[-80.80353599999999,35.112644],"type":"Point"}
}