{
  "type": "Feature",
  "properties": {
    "iso:country":"US",
    "sg:address":"3542 US Hwy 70 E",
    "sg:city":"Marion",
    "sg:classifiers":[
        {
            "category":"Personal",
            "subcategory":"Beauty Salon",
            "type":"Services"
        }
    ],
    "sg:phone":"+1 828 724 4470",
    "sg:postcode":"28752",
    "sg:province":"NC",
    "wof:name":"Shear Image",
    "wof:placetype":"venue"
},
  "geometry": {"coordinates":[-81.962374,35.702484],"type":"Point"}
}