{
  "type": "Feature",
  "properties": {
    "addr:full":"944 Central Dr NW Concord NC 28027",
    "addr:housenumber":"944",
    "addr:postcode":"28027",
    "addr:street":"Central Dr Nw",
    "iso:country":"US",
    "sg:address":"944 Central Dr NW",
    "sg:city":"Concord",
    "sg:classifiers":[
        {
            "category":"Retail",
            "subcategory":"Auto Repair",
            "type":"Services"
        }
    ],
    "sg:phone":"+1   ",
    "sg:postcode":"28027",
    "sg:province":"NC",
    "sg:tags":[
        "body"
    ],
    "wof:name":"Hall of Flame",
    "wof:placetype":"venue"
},
  "geometry": {"coordinates":[-80.614974,35.427929],"type":"Point"}
}