{
  "type": "Feature",
  "properties": {
    "iso:country":"US",
    "sg:address":"3800 Martin Luther King Jr Dr",
    "sg:city":"Lumberton",
    "sg:classifiers":[
        {
            "category":"Professional",
            "subcategory":"Computer Services",
            "type":"Services"
        }
    ],
    "sg:phone":"+1 910 272 8159",
    "sg:postcode":"28358",
    "sg:province":"NC",
    "sg:tags":[
        "internet"
    ],
    "wof:name":"Servusa Internet Svc",
    "wof:placetype":"venue"
},
  "geometry": {"coordinates":[-79.03767999999999,34.59611],"type":"Point"}
}