{
  "type": "Feature",
  "properties": {
    "addr:full":"2531 Buffaloe Rd Garner NC 27529",
    "addr:housenumber":"2531",
    "addr:postcode":"27529",
    "addr:street":"Buffaloe Rd",
    "iso:country":"US",
    "sg:address":"2531 Buffaloe Rd",
    "sg:city":"Garner",
    "sg:classifiers":[
        {
            "category":"Real Estate",
            "subcategory":"Real Estate Agent",
            "type":"Services"
        }
    ],
    "sg:phone":"+1 919 772 0321",
    "sg:postcode":"27529",
    "sg:province":"NC",
    "sg:tags":[
        "agency"
    ],
    "wof:name":"Byrd Realty Co Inc",
    "wof:placetype":"venue"
},
  "geometry": {"coordinates":[-78.617752,35.6707],"type":"Point"}
}