{
  "type": "Feature",
  "properties": {
    "iso:country":"US",
    "sg:address":"15109 Hubbard Rd",
    "sg:city":"Huntersville",
    "sg:classifiers":[
        {
            "category":"Banks & Credit Unions",
            "subcategory":"Financial Services",
            "type":"Services"
        }
    ],
    "sg:phone":"+1 704 875 7972",
    "sg:postcode":"28078",
    "sg:province":"NC",
    "sg:tags":[
        "investment",
        "closed"
    ],
    "wof:name":"Can AM Investments LLC",
    "wof:placetype":"venue"
},
  "geometry": {"coordinates":[-80.92984,35.425292],"type":"Point"}
}