{
  "type": "Feature",
  "properties": {
    "addr:full":"5250 Flowes Store Rd Concord NC 28025",
    "addr:housenumber":"5250",
    "addr:postcode":"28025",
    "addr:street":"Flowes Store Rd",
    "iso:country":"US",
    "sg:address":"5250 Flowes Store Rd",
    "sg:city":"Concord",
    "sg:classifiers":[
        {
            "category":"Building & Trades",
            "subcategory":"Construction",
            "type":"Services"
        }
    ],
    "sg:phone":"+1 704 786 4694",
    "sg:postcode":"28025",
    "sg:province":"NC",
    "sg:tags":[
        "grading",
        "contractor"
    ],
    "wof:name":"Page's Landscaping",
    "wof:placetype":"venue"
},
  "geometry": {"coordinates":[-80.55256,35.344605],"type":"Point"}
}