{
  "type": "Feature",
  "properties": {
    "iso:country":"US",
    "sg:address":"249 E 3rd St",
    "sg:city":"Ayden",
    "sg:classifiers":[
        {
            "category":"Food & Beverages",
            "subcategory":"Groceries & Convenience Stores",
            "type":"Retail Goods"
        }
    ],
    "sg:phone":"+1 252 746 4041",
    "sg:postcode":"28513",
    "sg:province":"NC",
    "sg:tags":[
        "grocer"
    ],
    "sg:website":"www.pigglywiggly.com",
    "wof:name":"Piggly Wiggly",
    "wof:placetype":"venue"
},
  "geometry": {"coordinates":[-77.41591699999999,35.470954],"type":"Point"}
}