{
  "type": "Feature",
  "properties": {
    "addr:full":"600 Hillsborough St Raleigh NC 27603",
    "addr:housenumber":"600",
    "addr:postcode":"27603",
    "addr:street":"Hillsborough St",
    "iso:country":"US",
    "sg:address":"600 Hillsborough St",
    "sg:city":"Raleigh",
    "sg:classifiers":[
        {
            "category":"Restaurant",
            "type":"Food & Drink"
        }
    ],
    "sg:phone":"+1 919 839 2176",
    "sg:postcode":"27603",
    "sg:province":"NC",
    "wof:name":"Snoopy's Hot Dogs",
    "wof:placetype":"venue"
},
  "geometry": {"coordinates":[-78.649181,35.780812],"type":"Point"}
}