{
  "type": "Feature",
  "properties": {
    "iso:country":"US",
    "sg:address":"306 W Water St",
    "sg:city":"Plymouth",
    "sg:classifiers":[
        {
            "category":"Organizations",
            "subcategory":"Political Organization",
            "type":"Services"
        }
    ],
    "sg:phone":"+1 252 793 2769",
    "sg:postcode":"27962",
    "sg:province":"NC",
    "wof:name":"Washington County Board",
    "wof:placetype":"venue"
},
  "geometry": {"coordinates":[-76.753882,35.865862],"type":"Point"}
}