{
  "type": "Feature",
  "properties": {
    "addr:full":"5640 Shattalon Dr Winston Salem NC 27105",
    "addr:housenumber":"5640",
    "addr:postcode":"27105",
    "addr:street":"Shattalon Dr",
    "iso:country":"US",
    "sg:address":"5640 Shattalon Dr",
    "sg:city":"Winston Salem",
    "sg:classifiers":[
        {
            "category":"Retail",
            "subcategory":"Auto Repair",
            "type":"Services"
        }
    ],
    "sg:phone":"+1 336 776 1555",
    "sg:postcode":"27105",
    "sg:province":"NC",
    "sg:tags":[
        "repairing",
        "automobile"
    ],
    "wof:name":"J Medic Car Care Ctr",
    "wof:placetype":"venue"
},
  "geometry": {"coordinates":[-80.28612699999999,36.168852],"type":"Point"}
}