{
  "type": "Feature",
  "properties": {
    "iso:country":"US",
    "sg:address":"2003 Hydes Corner",
    "sg:city":"New Bern",
    "sg:classifiers":[
        {
            "category":"Building & Trades",
            "subcategory":"Construction",
            "type":"Services"
        }
    ],
    "sg:phone":"+1 252 633 5337",
    "sg:postcode":"28562",
    "sg:province":"NC",
    "sg:tags":[
        "residential"
    ],
    "wof:name":"Huffman Enterprises of Ne",
    "wof:placetype":"venue"
},
  "geometry": {"coordinates":[-77.09195699999999,35.089243],"type":"Point"}
}