{
  "type": "Feature",
  "properties": {
    "iso:country":"US",
    "sg:address":"10 Stockton Rd",
    "sg:city":"Weaverville",
    "sg:classifiers":[
        {
            "category":"Autos & Motor Vehicles",
            "subcategory":"Fuel & Gas Station",
            "type":"Retail Goods"
        }
    ],
    "sg:phone":"+1 828 626 2525",
    "sg:postcode":"28787",
    "sg:province":"NC",
    "sg:tags":[
        "oil"
    ],
    "wof:name":"Bp Station",
    "wof:placetype":"venue"
},
  "geometry": {"coordinates":[-82.538944,35.791215],"type":"Point"}
}