{
  "type": "Feature",
  "properties": {
    "addr:full":"10500 Park Rd Charlotte NC 28210",
    "addr:housenumber":"10500",
    "addr:postcode":"28210",
    "addr:street":"Park Rd",
    "iso:country":"US",
    "sg:address":"10500 Park Rd",
    "sg:city":"Charlotte",
    "sg:classifiers":[
        {
            "category":"Cemetery",
            "type":"Public Place"
        },
        {
            "category":"Retail",
            "subcategory":"Funeral Services",
            "type":"Services"
        }
    ],
    "sg:phone":"+1 704 544 1412",
    "sg:postcode":"28210",
    "sg:province":"NC",
    "sg:tags":[
        "director",
        "crematory",
        "plans-pre-arranged",
        "supply"
    ],
    "wof:name":"Mc Ewen Funeral Home",
    "wof:placetype":"venue"
},
  "geometry": {"coordinates":[-80.868172,35.09362],"type":"Point"}
}