{
  "type": "Feature",
  "properties": {
    "iso:country":"US",
    "sg:address":"3200 Olive Chapel Rd",
    "sg:city":"Apex",
    "sg:classifiers":[
        {
            "category":"Organizations",
            "subcategory":"Religious Organization",
            "type":"Services"
        }
    ],
    "sg:phone":"+1 919 362 0648",
    "sg:postcode":"27502",
    "sg:province":"NC",
    "sg:tags":[
        "church"
    ],
    "wof:name":"Collins Grove Baptist Church",
    "wof:placetype":"venue"
},
  "geometry": {"coordinates":[-78.937354,35.730593],"type":"Point"}
}