{
  "type": "Feature",
  "properties": {
    "iso:country":"US",
    "sg:address":"3519 Maple Ave",
    "sg:city":"Burlington",
    "sg:classifiers":[
        {
            "category":"Organizations",
            "subcategory":"Religious Organization",
            "type":"Services"
        }
    ],
    "sg:phone":"+1   ",
    "sg:postcode":"27215",
    "sg:province":"NC",
    "wof:name":"Shamrock Evang Methdst Church",
    "wof:placetype":"venue"
},
  "geometry": {"coordinates":[-79.437789,36.035483],"type":"Point"}
}