{
  "type": "Feature",
  "properties": {
    "addr:full":"12834 English Walnut Ln Charlotte NC 28215",
    "addr:housenumber":"12834",
    "addr:postcode":"28215",
    "addr:street":"English Walnut Ln",
    "iso:country":"US",
    "sg:address":"12834 English Walnut Ln",
    "sg:city":"Charlotte",
    "sg:classifiers":[
        {
            "category":"Building & Trades",
            "subcategory":"Construction",
            "type":"Services"
        }
    ],
    "sg:phone":"+1 704 573 2602",
    "sg:postcode":"28215",
    "sg:province":"NC",
    "sg:tags":[
        "restoration",
        "cleaning",
        "patio",
        "deck"
    ],
    "wof:name":"Industrial Pressure Works",
    "wof:placetype":"venue"
},
  "geometry": {"coordinates":[-80.641867,35.247844],"type":"Point"}
}