{
  "type": "Feature",
  "properties": {
    "iso:country":"US",
    "sg:address":"2700 New Bern Ave",
    "sg:city":"New Bern",
    "sg:classifiers":[
        {
            "category":"Building & Trades",
            "subcategory":"Cleaning & Sanitation",
            "type":"Services"
        }
    ],
    "sg:phone":"+1 252 638 5367",
    "sg:postcode":"28562",
    "sg:province":"NC",
    "wof:name":"Busy Bee Cleaning Service",
    "wof:placetype":"venue"
},
  "geometry": {"coordinates":[-77.073013,35.095901],"type":"Point"}
}