{
  "type": "Feature",
  "properties": {
    "iso:country":"US",
    "sg:address":"3808 Guess Rd",
    "sg:city":"Durham",
    "sg:classifiers":[
        {
            "category":"Personal",
            "subcategory":"Beauty Salon",
            "type":"Services"
        }
    ],
    "sg:phone":"+1 919 477 5611",
    "sg:postcode":"27705",
    "sg:province":"NC",
    "sg:tags":[
        "shop",
        "manicuring"
    ],
    "wof:name":"Unique Nail",
    "wof:placetype":"venue"
},
  "geometry": {"coordinates":[-78.928917,36.05928],"type":"Point"}
}