{
  "type": "Feature",
  "properties": {
    "iso:country":"US",
    "sg:address":"2301 Old Stantonsburg Rd",
    "sg:city":"Wilson",
    "sg:classifiers":[
        {
            "category":"Building & Trades",
            "subcategory":"Plumbing",
            "type":"Services"
        }
    ],
    "sg:phone":"+1 252 291 4460",
    "sg:postcode":"27893",
    "sg:province":"NC",
    "sg:tags":[
        "heating",
        "contractor"
    ],
    "wof:name":"Baker Mechanical Inc",
    "wof:placetype":"venue"
},
  "geometry": {"coordinates":[-77.89281200000001,35.69906],"type":"Point"}
}