{
  "type": "Feature",
  "properties": {
    "addr:full":"105 N Raiford St Selma NC 27576",
    "addr:housenumber":"105",
    "addr:postcode":"27576",
    "addr:street":"N Raiford St",
    "iso:country":"US",
    "sg:address":"105 N Raiford St",
    "sg:city":"Selma",
    "sg:classifiers":[
        {
            "category":"Organizations",
            "subcategory":"Religious Organization",
            "type":"Services"
        }
    ],
    "sg:phone":"+1   ",
    "sg:postcode":"27576",
    "sg:province":"NC",
    "wof:name":"Holy Church Of Christ",
    "wof:placetype":"venue"
},
  "geometry": {"coordinates":[-78.282878,35.536622],"type":"Point"}
}