{
  "type": "Feature",
  "properties": {
    "addr:full":"5275 Hilltop Rd Jamestown NC 27282",
    "addr:housenumber":"5275",
    "addr:postcode":"27282",
    "addr:street":"Hilltop Rd",
    "iso:country":"US",
    "sg:address":"5275 Hilltop Rd",
    "sg:city":"Jamestown",
    "sg:classifiers":[
        {
            "category":"Sports & Exercise",
            "subcategory":"Golf",
            "type":"Entertainment"
        }
    ],
    "sg:phone":"+1 336 855 5278",
    "sg:postcode":"27282",
    "sg:province":"NC",
    "sg:tags":[
        "course",
        "beverage",
        "public",
        "alcoholic"
    ],
    "wof:name":"Cork & Bottle Shop",
    "wof:placetype":"venue"
},
  "geometry": {"coordinates":[-79.90843099999999,36.03865],"type":"Point"}
}