{
  "type": "Feature",
  "properties": {
    "iso:country":"US",
    "sg:address":"436 State St",
    "sg:city":"Marion",
    "sg:classifiers":[
        {
            "category":"Social Services",
            "type":"Services"
        }
    ],
    "sg:phone":"+1 828 652 4333",
    "sg:postcode":"28752",
    "sg:province":"NC",
    "sg:tags":[
        "counseling"
    ],
    "wof:name":"Peaceful Personal Grwth Prgrm",
    "wof:placetype":"venue"
},
  "geometry": {"coordinates":[-82.00170900000001,35.684712],"type":"Point"}
}