{
  "type": "Feature",
  "properties": {
    "iso:country":"US",
    "sg:address":"165 Johnson Dairy Rd",
    "sg:city":"Rockwell",
    "sg:classifiers":[
        {
            "category":"Utilities",
            "subcategory":"Refuse",
            "type":"Services"
        }
    ],
    "sg:phone":"+1 704 209 3068",
    "sg:postcode":"28138",
    "sg:province":"NC",
    "sg:tags":[
        "disposal",
        "waste"
    ],
    "wof:name":"Lowery's Waste Svc",
    "wof:placetype":"venue"
},
  "geometry": {"coordinates":[-80.380646,35.538246],"type":"Point"}
}