{
  "type": "Feature",
  "properties": {
    "iso:country":"US",
    "sg:address":"4801 Leigh Dr",
    "sg:city":"Raleigh",
    "sg:classifiers":[
        {
            "category":"Bars & Pubs",
            "type":"Food & Drink"
        }
    ],
    "sg:phone":"+1 919 872 6818",
    "sg:postcode":"27616",
    "sg:province":"NC",
    "sg:tags":[
        "club",
        "drinking",
        "night"
    ],
    "wof:name":"Back Door",
    "wof:placetype":"venue"
},
  "geometry": {"coordinates":[-78.584734,35.851661],"type":"Point"}
}