{
  "type": "Feature",
  "properties": {
    "iso:country":"US",
    "sg:address":"2008 Pearces Rd",
    "sg:city":"Zebulon",
    "sg:classifiers":[
        {
            "category":"Building & Trades",
            "subcategory":"Construction",
            "type":"Services"
        }
    ],
    "sg:phone":"+1 919 404 0076",
    "sg:postcode":"27597",
    "sg:province":"NC",
    "sg:tags":[
        "paving",
        "contractor"
    ],
    "wof:name":"Precise Paving and Seal Coatin",
    "wof:placetype":"venue"
},
  "geometry": {"coordinates":[-78.31695000000001,35.870362],"type":"Point"}
}