{
  "type": "Feature",
  "properties": {
    "iso:country":"US",
    "sg:address":"1812 Crafton Rd",
    "sg:city":"Hickory",
    "sg:classifiers":[
        {
            "category":"Building & Trades",
            "subcategory":"Landscaping Services",
            "type":"Services"
        }
    ],
    "sg:phone":"+1 828 294 1321",
    "sg:postcode":"28602",
    "sg:province":"NC",
    "wof:name":"Stump Busters",
    "wof:placetype":"venue"
},
  "geometry": {"coordinates":[-81.387353,35.682805],"type":"Point"}
}