{
  "type": "Feature",
  "properties": {
    "addr:full":"402 Main St W Valdese NC 28690",
    "addr:housenumber":"402",
    "addr:postcode":"28690",
    "addr:street":"Main St W",
    "iso:country":"US",
    "sg:address":"402 Main St W",
    "sg:city":"Valdese",
    "sg:classifiers":[
        {
            "category":"Wholesale",
            "subcategory":"Groceries",
            "type":"Manufacturing & Wholesale Goods"
        }
    ],
    "sg:phone":"+1 828 874 0235",
    "sg:postcode":"28690",
    "sg:province":"NC",
    "sg:tags":[
        "food",
        "broker"
    ],
    "wof:name":"Advantage Sales & Marketing",
    "wof:placetype":"venue"
},
  "geometry": {"coordinates":[-81.567189,35.744196],"type":"Point"}
}