{
  "type": "Feature",
  "properties": {
    "iso:country":"US",
    "sg:address":"1207 Fairview St",
    "sg:city":"Greensboro",
    "sg:classifiers":[
        {
            "category":"Personal",
            "subcategory":"Beauty Salon",
            "type":"Services"
        }
    ],
    "sg:phone":"+1   ",
    "sg:postcode":"27405",
    "sg:province":"NC",
    "sg:tags":[
        "shop"
    ],
    "wof:name":"Total Connections",
    "wof:placetype":"venue"
},
  "geometry": {"coordinates":[-79.77361999999999,36.09311],"type":"Point"}
}