{
  "type": "Feature",
  "properties": {
    "iso:country":"US",
    "sg:address":"2500 Little Rock Rd",
    "sg:city":"Charlotte",
    "sg:classifiers":[
        {
            "category":"Wholesale",
            "subcategory":"Auto Parts",
            "type":"Manufacturing & Wholesale Goods"
        }
    ],
    "sg:phone":"+1 704 391 8473",
    "sg:postcode":"28214",
    "sg:province":"NC",
    "sg:tags":[
        "supply"
    ],
    "wof:name":"Gerrard Tire Company Inc",
    "wof:placetype":"venue"
},
  "geometry": {"coordinates":[-80.93744599999999,35.244237],"type":"Point"}
}