{
  "type": "Feature",
  "properties": {
    "iso:country":"US",
    "sg:address":"111 Eastbrook Dr",
    "sg:city":"Greenville",
    "sg:classifiers":[
        {
            "category":"Social Services",
            "subcategory":"Child Care",
            "type":"Services"
        }
    ],
    "sg:phone":"+1 252 758 8885",
    "sg:postcode":"27858",
    "sg:province":"NC",
    "sg:website":"www.mppfc.org",
    "wof:name":"Childlinks",
    "wof:placetype":"venue"
},
  "geometry": {"coordinates":[-77.33735299999999,35.596991],"type":"Point"}
}