{
  "type": "Feature",
  "properties": {
    "iso:country":"US",
    "sg:address":"7642 Turnberry Ln",
    "sg:city":"Stanley",
    "sg:classifiers":[
        {
            "category":"Building & Trades",
            "subcategory":"Landscaping Services",
            "type":"Services"
        }
    ],
    "sg:phone":"+1 704 822 6620",
    "sg:postcode":"28164",
    "sg:province":"NC",
    "sg:tags":[
        "lawn",
        "maintenance",
        "grounds"
    ],
    "wof:name":"Weed Man Of Lake Norman",
    "wof:placetype":"venue"
},
  "geometry": {"coordinates":[-80.97363300000001,35.440948],"type":"Point"}
}