{
  "type": "Feature",
  "properties": {
    "iso:country":"US",
    "sg:address":"700 Walnut Forest Rd",
    "sg:city":"Winston Salem",
    "sg:classifiers":[
        {
            "category":"Real Estate",
            "subcategory":"Real Estate Agent",
            "type":"Services"
        }
    ],
    "sg:phone":"+1 336 760 1916",
    "sg:postcode":"27103",
    "sg:province":"NC",
    "wof:name":"Highland Oaks",
    "wof:placetype":"venue"
},
  "geometry": {"coordinates":[-80.29868399999999,36.060603],"type":"Point"}
}