{
  "type": "Feature",
  "properties": {
    "iso:country":"US",
    "sg:address":"192 N Main St",
    "sg:city":"Lowell",
    "sg:classifiers":[
        {
            "category":"Organizations",
            "subcategory":"Religious Organization",
            "type":"Services"
        }
    ],
    "sg:phone":"+1 704 824 2740",
    "sg:postcode":"28098",
    "sg:province":"NC",
    "sg:tags":[
        "church"
    ],
    "wof:name":"Mc Adenville Baptist Church",
    "wof:placetype":"venue"
},
  "geometry": {"coordinates":[-81.10096299999999,35.266622],"type":"Point"}
}