{
  "type": "Feature",
  "properties": {
    "addr:full":"41934 State Hwy 12 Buxton NC 27920",
    "addr:housenumber":"41934",
    "addr:postcode":"27920",
    "addr:street":"State Hwy 12",
    "iso:country":"US",
    "sg:address":"41934 State Hwy 12",
    "sg:city":"Buxton",
    "sg:classifiers":[
        {
            "category":"Food & Beverages",
            "subcategory":"Candy",
            "type":"Retail Goods"
        }
    ],
    "sg:phone":"+1 252 995 0012",
    "sg:postcode":"27920",
    "sg:province":"NC",
    "sg:tags":[
        "confectionery"
    ],
    "wof:name":"Sweet & Simple Pleasures Inc",
    "wof:placetype":"venue"
},
  "geometry": {"coordinates":[-75.539843,35.26873],"type":"Point"}
}