{
  "type": "Feature",
  "properties": {
    "addr:full":"3605 Glenwood Ave Raleigh NC 27612",
    "addr:housenumber":"3605",
    "addr:postcode":"27612",
    "addr:street":"Glenwood Ave",
    "iso:country":"US",
    "sg:address":"3605 Glenwood Ave",
    "sg:city":"Raleigh",
    "sg:classifiers":[
        {
            "category":"Professional",
            "subcategory":"Accounting & Tax Preparation",
            "type":"Services"
        }
    ],
    "sg:phone":"+1 919 782 8410",
    "sg:postcode":"27612",
    "sg:province":"NC",
    "sg:tags":[
        "accountant"
    ],
    "sg:website":"www.lhcpa.com",
    "wof:name":"Lynch & Howard",
    "wof:placetype":"venue"
},
  "geometry": {"coordinates":[-78.666511,35.827831],"type":"Point"}
}