{
  "type": "Feature",
  "properties": {
    "addr:full":"1749 Carriage Cove Ln Winston Salem NC 27127",
    "addr:housenumber":"1749",
    "addr:postcode":"27127",
    "addr:street":"Carriage Cove Ln",
    "iso:country":"US",
    "sg:address":"1749 Carriage Cove Ln",
    "sg:city":"Winston Salem",
    "sg:classifiers":[
        {
            "category":"Professional",
            "subcategory":"Management & Consulting",
            "type":"Services"
        }
    ],
    "sg:phone":"+1   ",
    "sg:postcode":"27127",
    "sg:province":"NC",
    "wof:name":"Elite Athletic Sports Inc",
    "wof:placetype":"venue"
},
  "geometry": {"coordinates":[-80.275356,36.036256],"type":"Point"}
}