{
  "type": "Feature",
  "properties": {
    "addr:full":"9000 Corbin Rd Wendell NC 27591",
    "addr:housenumber":"9000",
    "addr:postcode":"27591",
    "addr:street":"Corbin Rd",
    "iso:country":"US",
    "sg:address":"9000 Corbin Rd",
    "sg:city":"Wendell",
    "sg:phone":"+1 919 365 7498",
    "sg:postcode":"27591",
    "sg:province":"NC",
    "sg:tags":[
        "farm",
        "wheat"
    ],
    "wof:name":"Victor M Pace",
    "wof:placetype":"venue"
},
  "geometry": {"coordinates":[-78.33008100000001,35.779421],"type":"Point"}
}