{
  "type": "Feature",
  "properties": {
    "addr:full":"107 Windel Dr Raleigh NC 27609",
    "addr:housenumber":"107",
    "addr:postcode":"27609",
    "addr:street":"Windel Dr",
    "iso:country":"US",
    "sg:address":"107 Windel Dr",
    "sg:city":"Raleigh",
    "sg:classifiers":[
        {
            "category":"Personal",
            "type":"Services"
        }
    ],
    "sg:phone":"+1 919 785 0849",
    "sg:postcode":"27609",
    "sg:province":"NC",
    "sg:tags":[
        "electrolysis"
    ],
    "wof:name":"Clinical Electrolysis",
    "wof:placetype":"venue"
},
  "geometry": {"coordinates":[-78.637181,35.852883],"type":"Point"}
}