{
  "type": "Feature",
  "properties": {
    "addr:full":"638 N Patterson St Maxton NC 28364",
    "addr:housenumber":"638",
    "addr:postcode":"28364",
    "addr:street":"N Patterson St",
    "iso:country":"US",
    "sg:address":"638 N Patterson St",
    "sg:city":"Maxton",
    "sg:classifiers":[
        {
            "category":"Food & Beverages",
            "subcategory":"Groceries & Convenience Stores",
            "type":"Retail Goods"
        }
    ],
    "sg:phone":"+1 910 844 9878",
    "sg:postcode":"28364",
    "sg:province":"NC",
    "sg:tags":[
        "grocer"
    ],
    "wof:name":"Food Lion",
    "wof:placetype":"venue"
},
  "geometry": {"coordinates":[-79.34536300000001,34.744265],"type":"Point"}
}