{
  "type": "Feature",
  "properties": {
    "iso:country":"US",
    "sg:address":"402 N Pine St",
    "sg:city":"Lumberton",
    "sg:classifiers":[
        {
            "category":"Health Services",
            "subcategory":"Doctor",
            "type":"Services"
        }
    ],
    "sg:phone":"+1   ",
    "sg:postcode":"28358",
    "sg:province":"NC",
    "sg:tags":[
        "medical"
    ],
    "wof:name":"Southern Allergy & Asthma",
    "wof:placetype":"venue"
},
  "geometry": {"coordinates":[-79.00438800000001,34.620027],"type":"Point"}
}