{
  "type": "Feature",
  "properties": {
    "iso:country":"US",
    "sg:address":"6970 Terrence Knoll Rd",
    "sg:city":"Belews Creek",
    "sg:classifiers":[
        {
            "category":"Retail",
            "subcategory":"Repair Shop",
            "type":"Services"
        }
    ],
    "sg:phone":"+1   ",
    "sg:postcode":"27009",
    "sg:province":"NC",
    "wof:name":"Hudson Repair",
    "wof:placetype":"venue"
},
  "geometry": {"coordinates":[-80.114082,36.191391],"type":"Point"}
}