{
  "type": "Feature",
  "properties": {
    "iso:country":"US",
    "sg:address":"2290 Griffith Rd",
    "sg:city":"Winston Salem",
    "sg:classifiers":[
        {
            "category":"Wholesale",
            "subcategory":"Motor Vehicles",
            "type":"Manufacturing & Wholesale Goods"
        }
    ],
    "sg:phone":"+1 336 768 3003",
    "sg:postcode":"27103",
    "sg:province":"NC",
    "sg:tags":[
        "supply"
    ],
    "wof:name":"Trans Tech South Inc",
    "wof:placetype":"venue"
},
  "geometry": {"coordinates":[-80.309496,36.056297],"type":"Point"}
}