{
  "type": "Feature",
  "properties": {
    "addr:full":"810 Troy St Ahoskie NC 27910",
    "addr:housenumber":"810",
    "addr:postcode":"27910",
    "addr:street":"Troy St",
    "iso:country":"US",
    "sg:address":"810 Troy St",
    "sg:city":"Ahoskie",
    "sg:classifiers":[
        {
            "category":"Professional",
            "type":"Services"
        }
    ],
    "sg:phone":"+1 252 332 8271",
    "sg:postcode":"27910",
    "sg:province":"NC",
    "wof:name":"Melvin Artis",
    "wof:placetype":"venue"
},
  "geometry": {"coordinates":[-76.97515,36.289115],"type":"Point"}
}