{
  "type": "Feature",
  "properties": {
    "addr:full":"3849 Woodfern Rd Asheboro NC 27205",
    "addr:housenumber":"3849",
    "addr:postcode":"27205",
    "addr:street":"Woodfern Rd",
    "iso:country":"US",
    "sg:address":"3849 Woodfern Rd",
    "sg:city":"Asheboro",
    "sg:classifiers":[
        {
            "category":"Building & Trades",
            "subcategory":"Construction",
            "type":"Services"
        }
    ],
    "sg:phone":"+1 336 879 3355",
    "sg:postcode":"27205",
    "sg:province":"NC",
    "sg:tags":[
        "heavy"
    ],
    "wof:name":"Gann Grading & Hauling",
    "wof:placetype":"venue"
},
  "geometry": {"coordinates":[-79.711608,35.618512],"type":"Point"}
}