{
  "type": "Feature",
  "properties": {
    "addr:full":"102 Rosewood Ln Locust NC 28073",
    "addr:housenumber":"102",
    "addr:postcode":"28073",
    "addr:street":"Rosewood Ln",
    "iso:country":"US",
    "sg:address":"102 Rosewood Ln",
    "sg:city":"Locust",
    "sg:classifiers":[
        {
            "category":"Building & Trades",
            "subcategory":"Construction",
            "type":"Services"
        }
    ],
    "sg:phone":"+1 704 888 4625",
    "sg:postcode":"28073",
    "sg:province":"NC",
    "sg:tags":[
        "general",
        "contractor"
    ],
    "wof:name":"Clifton Cnstr & Renovation Co",
    "wof:placetype":"venue"
},
  "geometry": {"coordinates":[-81.50059899999999,35.188422],"type":"Point"}
}