{
  "type": "Feature",
  "properties": {
    "iso:country":"US",
    "sg:address":"503 Pawley Dr",
    "sg:city":"Charlotte",
    "sg:classifiers":[
        {
            "category":"Real Estate",
            "subcategory":"Developer",
            "type":"Services"
        }
    ],
    "sg:phone":"+1 704 822 6282",
    "sg:postcode":"28214",
    "sg:province":"NC",
    "wof:name":"Stagecoach Ventures",
    "wof:placetype":"venue"
},
  "geometry": {"coordinates":[-80.982949,35.304345],"type":"Point"}
}