{
  "type": "Feature",
  "properties": {
    "iso:country":"US",
    "sg:address":"100 Old Tom St",
    "sg:city":"Manteo",
    "sg:classifiers":[
        {
            "category":"Building & Trades",
            "subcategory":"Plumbing",
            "type":"Services"
        }
    ],
    "sg:phone":"+1 252 473 1106",
    "sg:postcode":"27954",
    "sg:province":"NC",
    "sg:tags":[
        "plumbing",
        "contractor"
    ],
    "wof:name":"Mc Gee & Sons Plumbing Co",
    "wof:placetype":"venue"
},
  "geometry": {"coordinates":[-75.67007099999999,35.908904],"type":"Point"}
}