{
  "type": "Feature",
  "properties": {
    "iso:country":"US",
    "sg:address":"2015 N Bridge St",
    "sg:city":"Elkin",
    "sg:classifiers":[
        {
            "category":"Autos & Motor Vehicles",
            "subcategory":"Auto Supplies",
            "type":"Retail Goods"
        }
    ],
    "sg:phone":"+1 336 526 4764",
    "sg:postcode":"28621",
    "sg:province":"NC",
    "sg:tags":[
        "equipment",
        "parts",
        "electrical",
        "automobile"
    ],
    "sg:website":"www.advancedautoparts.com",
    "wof:name":"Advance Auto Parts Inc",
    "wof:placetype":"venue"
},
  "geometry": {"coordinates":[-80.852735,36.286591],"type":"Point"}
}