{
  "type": "Feature",
  "properties": {
    "addr:full":"1136 Old Linwood Rd Lexington NC 27292",
    "addr:housenumber":"1136",
    "addr:postcode":"27292",
    "addr:street":"Old Linwood Rd",
    "iso:country":"US",
    "sg:address":"1136 Old Linwood Rd",
    "sg:city":"Lexington",
    "sg:classifiers":[
        {
            "category":"Organizations",
            "subcategory":"Religious Organization",
            "type":"Services"
        }
    ],
    "sg:phone":"+1 336 357 7866",
    "sg:postcode":"27292",
    "sg:province":"NC",
    "sg:tags":[
        "church"
    ],
    "wof:name":"Calvary Family Worship Ctr",
    "wof:placetype":"venue"
},
  "geometry": {"coordinates":[-80.273219,35.785951],"type":"Point"}
}