{
  "type": "Feature",
  "properties": {
    "iso:country":"US",
    "sg:address":"226 Watlington Industrial Dr",
    "sg:city":"Reidsville",
    "sg:classifiers":[
        {
            "category":"Manufacturing",
            "subcategory":"Rubber & Plastics",
            "type":"Manufacturing & Wholesale Goods"
        },
        {
            "category":"Manufacturing",
            "subcategory":"Motor Vehicles & Parts",
            "type":"Manufacturing & Wholesale Goods"
        }
    ],
    "sg:phone":"+1 336 342 9300",
    "sg:postcode":"27320",
    "sg:province":"NC",
    "sg:tags":[
        "automobile",
        "supply",
        "seal",
        "for",
        "mfg"
    ],
    "sg:website":"www.metzeler-profiles.com",
    "wof:name":"Metzeler Automotive Profile",
    "wof:placetype":"venue"
},
  "geometry": {"coordinates":[-79.64751099999999,36.327696],"type":"Point"}
}