{
  "type": "Feature",
  "properties": {
    "addr:full":"529 Harrison Rd Nashville NC 27856",
    "addr:housenumber":"529",
    "addr:postcode":"27856",
    "addr:street":"Harrison Rd",
    "iso:country":"US",
    "sg:address":"529 Harrison Rd",
    "sg:city":"Nashville",
    "sg:classifiers":[
        {
            "category":"Manufacturing",
            "subcategory":"Printing",
            "type":"Manufacturing & Wholesale Goods"
        }
    ],
    "sg:phone":"+1 252 937 5721",
    "sg:postcode":"27856",
    "sg:province":"NC",
    "sg:tags":[
        "lithographic",
        "commercial"
    ],
    "wof:name":"Saunders Printing Co",
    "wof:placetype":"venue"
},
  "geometry": {"coordinates":[-77.96092,36.160229],"type":"Point"}
}