{
  "type": "Feature",
  "properties": {
    "addr:full":"4799 Old Greensboro Rd Randleman NC 27317",
    "addr:housenumber":"4799",
    "addr:postcode":"27317",
    "addr:street":"Old Greensboro Rd",
    "iso:country":"US",
    "sg:address":"4799 Old Greensboro Rd",
    "sg:city":"Randleman",
    "sg:classifiers":[
        {
            "category":"Retail",
            "subcategory":"Repair Shop",
            "type":"Services"
        }
    ],
    "sg:phone":"+1   ",
    "sg:postcode":"27317",
    "sg:province":"NC",
    "sg:tags":[
        "electrical"
    ],
    "wof:name":"Electronic Repair Service Ashe",
    "wof:placetype":"venue"
},
  "geometry": {"coordinates":[-79.78677999999999,35.846977],"type":"Point"}
}