{
  "type": "Feature",
  "properties": {
    "iso:country":"US",
    "sg:address":"15 Holly Ln",
    "sg:city":"Glade Valley",
    "sg:classifiers":[
        {
            "category":"Building & Trades",
            "subcategory":"Construction",
            "type":"Services"
        }
    ],
    "sg:phone":"+1 336 363 3611",
    "sg:postcode":"28627",
    "sg:province":"NC",
    "sg:tags":[
        "concrete",
        "contractor"
    ],
    "wof:name":"Church S Concrete",
    "wof:placetype":"venue"
},
  "geometry": {"coordinates":[-81.000066,36.414432],"type":"Point"}
}