{
  "type": "Feature",
  "properties": {
    "addr:full":"154 Dogwood Rd Stoneville NC 27048",
    "addr:housenumber":"154",
    "addr:postcode":"27048",
    "addr:street":"Dogwood Rd",
    "iso:country":"US",
    "sg:address":"154 Dogwood Rd",
    "sg:city":"Stoneville",
    "sg:classifiers":[
        {
            "category":"Manufacturing",
            "subcategory":"Food",
            "type":"Manufacturing & Wholesale Goods"
        }
    ],
    "sg:phone":"+1 336 573 9313",
    "sg:postcode":"27048",
    "sg:province":"NC",
    "sg:tags":[
        "canned",
        "mfg"
    ],
    "wof:name":"Papa Lonnies Inc",
    "wof:placetype":"venue"
},
  "geometry": {"coordinates":[-79.856994,36.435062],"type":"Point"}
}