{
  "type": "Feature",
  "properties": {
    "iso:country":"US",
    "sg:address":"750 W Williams St",
    "sg:city":"Apex",
    "sg:classifiers":[
        {
            "category":"Shopping",
            "subcategory":"Pharmacy",
            "type":"Retail Goods"
        },
        {
            "category":"Food & Beverages",
            "subcategory":"Groceries & Convenience Stores",
            "type":"Retail Goods"
        }
    ],
    "sg:phone":"+1 919 362 3782",
    "sg:postcode":"27502",
    "sg:province":"NC",
    "sg:tags":[
        "drugstore"
    ],
    "sg:website":"www.harristeeter.com",
    "wof:name":"Harris Teeter Inc",
    "wof:placetype":"venue"
},
  "geometry": {"coordinates":[-78.865951,35.739438],"type":"Point"}
}