{
  "type": "Feature",
  "properties": {
    "addr:full":"4749 Edgar Rd Sophia NC 27350",
    "addr:housenumber":"4749",
    "addr:postcode":"27350",
    "addr:street":"Edgar Rd",
    "iso:country":"US",
    "sg:address":"4749 Edgar Rd",
    "sg:city":"Sophia",
    "sg:classifiers":[
        {
            "category":"Building & Trades",
            "subcategory":"Construction",
            "type":"Services"
        }
    ],
    "sg:phone":"+1 336 861 1018",
    "sg:postcode":"27350",
    "sg:province":"NC",
    "sg:tags":[
        "water",
        "well",
        "drilling"
    ],
    "wof:name":"Billy Stewart Well Drilling",
    "wof:placetype":"venue"
},
  "geometry": {"coordinates":[-79.900459,35.84421],"type":"Point"}
}