{
  "type": "Feature",
  "properties": {
    "addr:full":"6204 Rowsley St Wilmington NC 28409",
    "addr:postcode":"6204;28409",
    "addr:street":"Rowsley St",
    "iso:country":"US",
    "sg:address":"6204 Rowsley St",
    "sg:city":"Wilmington",
    "sg:classifiers":[
        {
            "category":"Building & Trades",
            "subcategory":"Construction",
            "type":"Services"
        }
    ],
    "sg:phone":"+1 910 313 1808",
    "sg:postcode":"28409",
    "sg:province":"NC",
    "sg:tags":[
        "house"
    ],
    "wof:name":"Island Repairs Unlimited",
    "wof:placetype":"venue"
},
  "geometry": {"coordinates":[-77.88618200000001,34.124828],"type":"Point"}
}