{
  "type": "Feature",
  "properties": {
    "addr:full":"600 E Cumberland St Dunn NC 28334",
    "addr:housenumber":"600",
    "addr:postcode":"28334",
    "addr:street":"E Cumberland St",
    "iso:country":"US",
    "sg:address":"600 E Cumberland St",
    "sg:city":"Dunn",
    "sg:classifiers":[
        {
            "category":"Local Transit",
            "type":"Transportation"
        }
    ],
    "sg:phone":"+1 910 892 5805",
    "sg:postcode":"28334",
    "sg:province":"NC",
    "sg:tags":[
        "bus",
        "line"
    ],
    "wof:name":"Greyhound Bus Lines",
    "wof:placetype":"venue"
},
  "geometry": {"coordinates":[-78.605997,35.304536],"type":"Point"}
}