{
  "type": "Feature",
  "properties": {
    "iso:country":"US",
    "sg:address":"230 Neel Rd",
    "sg:city":"Salisbury",
    "sg:classifiers":[
        {
            "category":"Building & Trades",
            "subcategory":"Construction",
            "type":"Services"
        }
    ],
    "sg:phone":"+1 704 637 1748",
    "sg:postcode":"28147",
    "sg:province":"NC",
    "sg:tags":[
        "repair",
        "co",
        "addition",
        "general",
        "siding",
        "home",
        "remodeling"
    ],
    "wof:name":"Yates Construction Company",
    "wof:placetype":"venue"
},
  "geometry": {"coordinates":[-80.557749,35.6621],"type":"Point"}
}