{
  "type": "Feature",
  "properties": {
    "addr:full":"5864 Laurel Ridge Dr Snow Camp NC 27349",
    "addr:housenumber":"5864",
    "addr:postcode":"27349",
    "addr:street":"Laurel Ridge Dr Snow Camp",
    "iso:country":"US",
    "sg:address":"5864 Laurel Ridge Dr",
    "sg:city":"Snow Camp",
    "sg:classifiers":[
        {
            "category":"Banks & Credit Unions",
            "subcategory":"Bank",
            "type":"Services"
        }
    ],
    "sg:phone":"+1 336 376 8889",
    "sg:postcode":"27349",
    "sg:province":"NC",
    "sg:tags":[
        "mortgage"
    ],
    "wof:name":"Cendant Mortgage",
    "wof:placetype":"venue"
},
  "geometry": {"coordinates":[-79.443867,35.954035],"type":"Point"}
}