{
  "type": "Feature",
  "properties": {
    "iso:country":"US",
    "sg:address":"1081 S Wesleyan Blvd",
    "sg:city":"Rocky Mount",
    "sg:classifiers":[
        {
            "category":"Shopping",
            "subcategory":"Used Merchandise",
            "type":"Retail Goods"
        }
    ],
    "sg:phone":"+1 252 442 5225",
    "sg:postcode":"27803",
    "sg:province":"NC",
    "sg:tags":[
        "flea",
        "market"
    ],
    "wof:name":"301 Craft & Flea Mall",
    "wof:placetype":"venue"
},
  "geometry": {"coordinates":[-77.831203,35.922894],"type":"Point"}
}