{
  "type": "Feature",
  "properties": {
    "addr:full":"605 Church St N Concord NC 28025",
    "addr:housenumber":"605",
    "addr:postcode":"28025",
    "addr:street":"Church St N",
    "iso:country":"US",
    "sg:address":"605 Church St N",
    "sg:city":"Concord",
    "sg:classifiers":[
        {
            "category":"Banks & Credit Unions",
            "subcategory":"Bank",
            "type":"Services"
        }
    ],
    "sg:phone":"+1 704 786 8713",
    "sg:postcode":"28025",
    "sg:province":"NC",
    "sg:tags":[
        "lender",
        "loan"
    ],
    "wof:name":"National Finance Co Inc",
    "wof:placetype":"venue"
},
  "geometry": {"coordinates":[-80.59607099999999,35.426087],"type":"Point"}
}