{
  "type": "Feature",
  "properties": {
    "addr:full":"20 Ravenscroft Dr Asheville NC 28801",
    "addr:housenumber":"20",
    "addr:postcode":"28801",
    "addr:street":"Ravenscroft Dr",
    "iso:country":"US",
    "sg:address":"20 Ravenscroft Dr",
    "sg:city":"Asheville",
    "sg:classifiers":[
        {
            "category":"Health Services",
            "subcategory":"Health Practitioner",
            "type":"Services"
        }
    ],
    "sg:phone":"+1   ",
    "sg:postcode":"28801",
    "sg:province":"NC",
    "wof:name":"Beverly D Brooks PHD",
    "wof:placetype":"venue"
},
  "geometry": {"coordinates":[-82.553605,35.591709],"type":"Point"}
}