{
  "type": "Feature",
  "properties": {
    "iso:country":"US",
    "sg:address":"1353 N Graham Hopedale Rd",
    "sg:city":"Burlington",
    "sg:classifiers":[
        {
            "category":"Freight",
            "type":"Transportation"
        }
    ],
    "sg:phone":"+1 336 227 5238",
    "sg:postcode":"27217",
    "sg:province":"NC",
    "sg:tags":[
        "operator",
        "local",
        "trucking"
    ],
    "wof:name":"Waste Industries LLC",
    "wof:placetype":"venue"
},
  "geometry": {"coordinates":[-79.40576,36.117219],"type":"Point"}
}