{
  "type": "Feature",
  "properties": {
    "addr:full":"2021 Rockford St Mount Airy NC 27030",
    "addr:housenumber":"2021",
    "addr:postcode":"27030",
    "addr:street":"Rockford St",
    "iso:country":"US",
    "sg:address":"2021 Rockford St",
    "sg:city":"Mount Airy",
    "sg:classifiers":[
        {
            "category":"Restaurant",
            "type":"Food & Drink"
        }
    ],
    "sg:phone":"+1 336 789 9969",
    "sg:postcode":"27030",
    "sg:province":"NC",
    "sg:tags":[
        "eating"
    ],
    "wof:name":"China King Buffet",
    "wof:placetype":"venue"
},
  "geometry": {"coordinates":[-80.615341,36.480519],"type":"Point"}
}