{
  "type": "Feature",
  "properties": {
    "addr:full":"135 E Main St Murfreesboro NC 27855",
    "addr:housenumber":"135",
    "addr:postcode":"27855",
    "addr:street":"E Main St",
    "iso:country":"US",
    "sg:address":"135 E Main St",
    "sg:city":"Murfreesboro",
    "sg:classifiers":[
        {
            "category":"Shopping",
            "subcategory":"Used Merchandise",
            "type":"Retail Goods"
        }
    ],
    "sg:phone":"+1 252 398 8198",
    "sg:postcode":"27855",
    "sg:province":"NC",
    "sg:tags":[
        "flea",
        "market"
    ],
    "wof:name":"Inside Outside Flea Market",
    "wof:placetype":"venue"
},
  "geometry": {"coordinates":[-77.100903,36.442338],"type":"Point"}
}