{
  "type": "Feature",
  "properties": {
    "addr:full":"5435 Prosperity Church Rd Charlotte NC 28269",
    "addr:housenumber":"5435",
    "addr:postcode":"28269",
    "addr:street":"Prosperity Church Rd",
    "iso:country":"US",
    "sg:address":"5435 Prosperity Church Rd",
    "sg:city":"Charlotte",
    "sg:classifiers":[
        {
            "category":"Health Services",
            "subcategory":"Doctor",
            "type":"Services"
        }
    ],
    "sg:phone":"+1 704 717 2000",
    "sg:postcode":"28269",
    "sg:province":"NC",
    "sg:tags":[
        "physician",
        "pediatrics-emergency",
        "pediatrics",
        "surgeons",
        "medicine",
        "surgeon"
    ],
    "wof:name":"Freeman, Kevin, Md - University Pediatrics",
    "wof:placetype":"venue"
},
  "geometry": {"coordinates":[-80.78696600000001,35.367643],"type":"Point"}
}