{
  "type": "Feature",
  "properties": {
    "addr:full":"1206 Anora Dr Apex NC 27502",
    "addr:housenumber":"1206",
    "addr:postcode":"27502",
    "addr:street":"Anora Dr",
    "iso:country":"US",
    "sg:address":"1206 Anora Dr",
    "sg:city":"Apex",
    "sg:classifiers":[
        {
            "category":"Building & Trades",
            "subcategory":"Construction",
            "type":"Services"
        }
    ],
    "sg:phone":"+1 919 363 8497",
    "sg:postcode":"27502",
    "sg:province":"NC",
    "sg:tags":[
        "house"
    ],
    "wof:name":"Macgregor Homes Inc",
    "wof:placetype":"venue"
},
  "geometry": {"coordinates":[-78.869208,35.746884],"type":"Point"}
}