{
  "type": "Feature",
  "properties": {
    "iso:country":"US",
    "sg:address":"1292 Piney Creek Rd",
    "sg:city":"Lansing",
    "sg:classifiers":[
        {
            "category":"Building & Trades",
            "subcategory":"Construction",
            "type":"Services"
        }
    ],
    "sg:phone":"+1 336 384 3534",
    "sg:postcode":"28643",
    "sg:province":"NC",
    "sg:tags":[
        "excavating",
        "contractor"
    ],
    "wof:name":"Brooks Larry Dozer Service",
    "wof:placetype":"venue"
},
  "geometry": {"coordinates":[-81.492642,36.499445],"type":"Point"}
}