{
  "type": "Feature",
  "properties": {
    "iso:country":"US",
    "sg:address":"1617 National Ave",
    "sg:city":"New Bern",
    "sg:classifiers":[
        {
            "category":"Home & Garden",
            "subcategory":"Hardware",
            "type":"Retail Goods"
        }
    ],
    "sg:phone":"+1 252 637 6308",
    "sg:postcode":"28560",
    "sg:province":"NC",
    "wof:name":"Riverside Hardware Co",
    "wof:placetype":"venue"
},
  "geometry": {"coordinates":[-77.051213,35.123126],"type":"Point"}
}