{
  "type": "Feature",
  "properties": {
    "addr:full":"2331 Vineyard Ln Charlotte NC 28210",
    "addr:housenumber":"2331",
    "addr:postcode":"28210",
    "addr:street":"Vineyard Ln",
    "iso:country":"US",
    "sg:address":"2331 Vineyard Ln",
    "sg:city":"Charlotte",
    "sg:classifiers":[
        {
            "category":"Real Estate",
            "subcategory":"Real Estate Operator",
            "type":"Services"
        }
    ],
    "sg:phone":"+1 704 553 2173",
    "sg:postcode":"28210",
    "sg:province":"NC",
    "sg:tags":[
        "building",
        "nonresidential"
    ],
    "wof:name":"Godbold Properties Inc",
    "wof:placetype":"venue"
},
  "geometry": {"coordinates":[-80.86144299999999,35.133855],"type":"Point"}
}