{
  "type": "Feature",
  "properties": {
    "iso:country":"US",
    "sg:address":"912 Copperfield Blvd NE",
    "sg:city":"Concord",
    "sg:classifiers":[
        {
            "category":"Professional",
            "subcategory":"Management & Consulting",
            "type":"Services"
        }
    ],
    "sg:phone":"+1 704 784 5327",
    "sg:postcode":"28025",
    "sg:province":"NC",
    "sg:tags":[
        "association"
    ],
    "wof:name":"Llams Inc-Copperfield Commons",
    "wof:placetype":"venue"
},
  "geometry": {"coordinates":[-80.586558,35.458341],"type":"Point"}
}