{
  "type": "Feature",
  "properties": {
    "addr:full":"1409 Skyway Dr Monroe NC 28110",
    "addr:housenumber":"1409",
    "addr:postcode":"28110",
    "addr:street":"Skyway Dr",
    "iso:country":"US",
    "sg:address":"1409 Skyway Dr",
    "sg:city":"Monroe",
    "sg:classifiers":[
        {
            "category":"Banks & Credit Unions",
            "subcategory":"Bank",
            "type":"Services"
        }
    ],
    "sg:phone":"+1 704 283 8111",
    "sg:postcode":"28110",
    "sg:province":"NC",
    "sg:tags":[
        "financing"
    ],
    "wof:name":"American General Finance Inc",
    "wof:placetype":"venue"
},
  "geometry": {"coordinates":[-80.549015,34.996092],"type":"Point"}
}