{
  "type": "Feature",
  "properties": {
    "addr:full":"995 S Shore Dr Southport NC 28461",
    "addr:housenumber":"995",
    "addr:postcode":"28461",
    "addr:street":"S Shore Dr",
    "iso:country":"US",
    "sg:address":"995 S Shore Dr",
    "sg:city":"Southport",
    "sg:classifiers":[
        {
            "category":"Building & Trades",
            "subcategory":"Landscaping Services",
            "type":"Services"
        }
    ],
    "sg:phone":"+1 910 845 3158",
    "sg:postcode":"28461",
    "sg:province":"NC",
    "sg:tags":[
        "landscape",
        "contractor"
    ],
    "wof:name":"Lawnscapes Limited LLC",
    "wof:placetype":"venue"
},
  "geometry": {"coordinates":[-78.044636,34.038771],"type":"Point"}
}