{
  "type": "Feature",
  "properties": {
    "iso:country":"US",
    "sg:address":"452 Eastway Dr",
    "sg:city":"Charlotte",
    "sg:classifiers":[
        {
            "category":"Personal",
            "subcategory":"Beauty Salon",
            "type":"Services"
        }
    ],
    "sg:phone":"+1   ",
    "sg:postcode":"28205",
    "sg:province":"NC",
    "sg:tags":[
        "shop"
    ],
    "wof:name":"Rise Above Hair & Nail Design",
    "wof:placetype":"venue"
},
  "geometry": {"coordinates":[-80.78061599999999,35.251317],"type":"Point"}
}