{
  "type": "Feature",
  "properties": {
    "iso:country":"US",
    "sg:address":"2202 Lynnwood Dr",
    "sg:city":"Wilmington",
    "sg:classifiers":[
        {
            "category":"Organizations",
            "subcategory":"Religious Organization",
            "type":"Services"
        }
    ],
    "sg:phone":"+1   ",
    "sg:postcode":"28403",
    "sg:province":"NC",
    "wof:name":"Product Realization Service",
    "wof:placetype":"venue"
},
  "geometry": {"coordinates":[-77.91569,34.201059],"type":"Point"}
}