{
  "type": "Feature",
  "properties": {
    "addr:full":"5900 Oleander Dr Wilmington NC 28403",
    "addr:housenumber":"5900",
    "addr:postcode":"28403",
    "addr:street":"Oleander Dr",
    "iso:country":"US",
    "sg:address":"5900 Oleander Dr",
    "sg:city":"Wilmington",
    "sg:classifiers":[
        {
            "category":"Education",
            "subcategory":"School",
            "type":"Public Place"
        },
        {
            "category":"Education",
            "subcategory":"Special Training",
            "type":"Public Place"
        }
    ],
    "sg:phone":"+1 910 313 2636",
    "sg:postcode":"28403",
    "sg:province":"NC",
    "sg:tags":[
        "academic"
    ],
    "sg:website":"www.huntingtonlearning.com",
    "wof:name":"Huntington Learning Center",
    "wof:placetype":"venue"
},
  "geometry": {"coordinates":[-77.842338,34.209506],"type":"Point"}
}