{
  "type": "Feature",
  "properties": {
    "iso:country":"US",
    "sg:address":"16 Cherokee Cir",
    "sg:city":"Whittier",
    "sg:classifiers":[
        {
            "category":"Shopping",
            "type":"Retail Goods"
        }
    ],
    "sg:phone":"+1 828 497 2262",
    "sg:postcode":"28747",
    "sg:province":"NC",
    "sg:tags":[
        "telephone",
        "cellular"
    ],
    "sg:website":"www.ramcell.com",
    "wof:name":"Ramcell Of North Carolina",
    "wof:placetype":"venue"
},
  "geometry": {"coordinates":[-82.934264,35.157581],"type":"Point"}
}