{
  "type": "Feature",
  "properties": {
    "iso:country":"US",
    "sg:address":"120 Sky View Ln",
    "sg:city":"Hendersonville",
    "sg:classifiers":[
        {
            "category":"Building & Trades",
            "subcategory":"Plumbing",
            "type":"Services"
        }
    ],
    "sg:phone":"+1 828 694 0305",
    "sg:postcode":"28739",
    "sg:province":"NC",
    "sg:tags":[
        "contractor"
    ],
    "wof:name":"Trice Plumbing Inc",
    "wof:placetype":"venue"
},
  "geometry": {"coordinates":[-82.505212,35.30109],"type":"Point"}
}