{
  "type": "Feature",
  "properties": {
    "iso:country":"US",
    "sg:address":"6010 McCrimmon Pkwy",
    "sg:city":"Morrisville",
    "sg:classifiers":[
        {
            "category":"Education",
            "subcategory":"Preschool",
            "type":"Public Place"
        }
    ],
    "sg:phone":"+1 919 460 1500",
    "sg:postcode":"27560",
    "sg:province":"NC",
    "sg:website":"kidsrkidsmorrisville.com",
    "wof:name":"Kids R Kids of Morrisville",
    "wof:placetype":"venue"
},
  "geometry": {"coordinates":[-78.851525,35.836379],"type":"Point"}
}