{
  "type": "Feature",
  "properties": {
    "iso:country":"US",
    "sg:address":"8112 Idlewild Rd",
    "sg:city":"Charlotte",
    "sg:classifiers":[
        {
            "category":"Restaurant",
            "type":"Food & Drink"
        }
    ],
    "sg:phone":"+1 704 531 6535",
    "sg:postcode":"28227",
    "sg:province":"NC",
    "wof:name":"Wing Stop Idlewild",
    "wof:placetype":"venue"
},
  "geometry": {"coordinates":[-80.72721799999999,35.182887],"type":"Point"}
}