{
  "type": "Feature",
  "properties": {
    "iso:country":"US",
    "sg:address":"5959 Triangle Town Blvd",
    "sg:city":"Raleigh",
    "sg:classifiers":[
        {
            "category":"Restaurant",
            "type":"Food & Drink"
        }
    ],
    "sg:menulink":"http://www.allmenus.com/nc/neuse/83045-villa-pizza/menu/",
    "sg:phone":"+1 919 792 2181",
    "sg:postcode":"27616",
    "sg:province":"NC",
    "sg:tags":[
        "american",
        "italian",
        "pizza"
    ],
    "wof:name":"Villa Pizza",
    "wof:placetype":"venue"
},
  "geometry": {"coordinates":[-78.571493,35.864931],"type":"Point"}
}