{
  "type": "Feature",
  "properties": {
    "addr:full":"2500 Wilkinson Blvd Charlotte NC 28208",
    "addr:housenumber":"2500",
    "addr:postcode":"28208",
    "addr:street":"Wilkinson Blvd",
    "iso:country":"US",
    "sg:address":"2500 Wilkinson Blvd",
    "sg:city":"Charlotte",
    "sg:classifiers":[
        {
            "category":"Wholesale",
            "subcategory":"Electrical",
            "type":"Manufacturing & Wholesale Goods"
        }
    ],
    "sg:phone":"+1 704 375 9831",
    "sg:postcode":"28208",
    "sg:province":"NC",
    "sg:tags":[
        "equipment",
        "electric",
        "supply"
    ],
    "wof:name":"Graybar Electric Co",
    "wof:placetype":"venue"
},
  "geometry": {"coordinates":[-80.884514,35.224067],"type":"Point"}
}