{
  "type": "Feature",
  "properties": {
    "addr:full":"4 W Main St Brevard NC 28712",
    "addr:housenumber":"4",
    "addr:postcode":"28712",
    "addr:street":"W Main St",
    "iso:country":"US",
    "sg:address":"4 W Main St",
    "sg:city":"Brevard",
    "sg:classifiers":[
        {
            "category":"Wholesale",
            "subcategory":"Furniture",
            "type":"Manufacturing & Wholesale Goods"
        }
    ],
    "sg:phone":"+1 828 885 7112",
    "sg:postcode":"28712",
    "sg:province":"NC",
    "wof:name":"Life Plan Systems",
    "wof:placetype":"venue"
},
  "geometry": {"coordinates":[-82.734854,35.234073],"type":"Point"}
}