{
  "type": "Feature",
  "properties": {
    "iso:country":"US",
    "sg:address":"3725 Williamsborough Cir",
    "sg:city":"Raleigh",
    "sg:classifiers":[
        {
            "category":"Insurance",
            "subcategory":"Hazard Insurance",
            "type":"Services"
        }
    ],
    "sg:phone":"+1 919 787 7739",
    "sg:postcode":"27609",
    "sg:province":"NC",
    "sg:tags":[
        "profit",
        "sharing",
        "pension",
        "plan"
    ],
    "wof:name":"Qualified Plan Svc Inc",
    "wof:placetype":"venue"
},
  "geometry": {"coordinates":[-78.6497,35.830915],"type":"Point"}
}