{
  "type": "Feature",
  "properties": {
    "addr:full":"103 Lewey Brook Dr Cary NC 27519",
    "addr:housenumber":"103",
    "addr:postcode":"27519",
    "addr:street":"Lewey Brook Dr",
    "iso:country":"US",
    "sg:address":"103 Lewey Brook Dr",
    "sg:city":"Cary",
    "sg:classifiers":[
        {
            "category":"Professional",
            "subcategory":"Management & Consulting",
            "type":"Services"
        }
    ],
    "sg:phone":"+1   ",
    "sg:postcode":"27519",
    "sg:province":"NC",
    "sg:tags":[
        "public",
        "relations"
    ],
    "wof:name":"Wwj Products Inc",
    "wof:placetype":"venue"
},
  "geometry": {"coordinates":[-78.86251,35.77589],"type":"Point"}
}