{
  "type": "Feature",
  "properties": {
    "addr:full":"598 Airport Blvd Morrisville NC 27560",
    "addr:housenumber":"598",
    "addr:postcode":"27560",
    "addr:street":"Airport Blvd",
    "iso:country":"US",
    "sg:address":"598 Airport Blvd",
    "sg:city":"Morrisville",
    "sg:classifiers":[
        {
            "category":"Professional",
            "type":"Services"
        }
    ],
    "sg:phone":"+1 919 380 9120",
    "sg:postcode":"27560",
    "sg:province":"NC",
    "sg:tags":[
        "establishment"
    ],
    "wof:name":"Pitney Bowes",
    "wof:placetype":"venue"
},
  "geometry": {"coordinates":[-78.827011,35.847116],"type":"Point"}
}