{
  "type": "Feature",
  "properties": {
    "addr:full":"1209 N Lake Park Blvd Carolina Beach NC 28428",
    "addr:housenumber":"1209",
    "addr:postcode":"28428",
    "addr:street":"N Lake Park Blvd",
    "iso:country":"US",
    "sg:address":"1209 N Lake Park Blvd",
    "sg:city":"Carolina Beach",
    "sg:classifiers":[
        {
            "category":"Organizations",
            "subcategory":"Religious Organization",
            "type":"Services"
        }
    ],
    "sg:phone":"+1 910 458 5417",
    "sg:postcode":"28428",
    "sg:province":"NC",
    "wof:name":"Carolina Beach Presbyterian Church",
    "wof:placetype":"venue"
},
  "geometry": {"coordinates":[-77.899399,34.046799],"type":"Point"}
}