{
  "type": "Feature",
  "properties": {
    "iso:country":"US",
    "sg:address":"1616 Tramway Rd",
    "sg:city":"Sanford",
    "sg:classifiers":[
        {
            "category":"Autos & Motor Vehicles",
            "subcategory":"Automobile Sales",
            "type":"Retail Goods"
        }
    ],
    "sg:phone":"+1 919 776 3715",
    "sg:postcode":"27332",
    "sg:province":"NC",
    "sg:tags":[
        "car",
        "dealer"
    ],
    "wof:name":"Nick's Auto Sales",
    "wof:placetype":"venue"
},
  "geometry": {"coordinates":[-79.171582,35.44582],"type":"Point"}
}