{
  "type": "Feature",
  "properties": {
    "iso:country":"US",
    "sg:address":"920 Ray Ave",
    "sg:city":"Sanford",
    "sg:classifiers":[
        {
            "category":"Professional",
            "type":"Services"
        }
    ],
    "sg:phone":"+1 919 777 9234",
    "sg:postcode":"27330",
    "sg:province":"NC",
    "sg:tags":[
        "establishment"
    ],
    "wof:name":"Static Control",
    "wof:placetype":"venue"
},
  "geometry": {"coordinates":[-79.164039,35.476042],"type":"Point"}
}