{
  "type": "Feature",
  "properties": {
    "addr:full":"3012 Morningside Dr Raleigh NC 27607",
    "addr:housenumber":"3012",
    "addr:postcode":"27607",
    "addr:street":"Morningside Dr",
    "iso:country":"US",
    "sg:address":"3012 Morningside Dr",
    "sg:city":"Raleigh",
    "sg:classifiers":[
        {
            "category":"Building & Trades",
            "subcategory":"Construction",
            "type":"Services"
        }
    ],
    "sg:phone":"+1 919 786 9020",
    "sg:postcode":"27607",
    "sg:province":"NC",
    "sg:tags":[
        "contractor"
    ],
    "wof:name":"Bradshaw Builders Inc",
    "wof:placetype":"venue"
},
  "geometry": {"coordinates":[-78.691233,35.826541],"type":"Point"}
}