{
  "type": "Feature",
  "properties": {
    "iso:country":"US",
    "sg:address":"121 E Phifer St",
    "sg:city":"Monroe",
    "sg:classifiers":[
        {
            "category":"Real Estate",
            "subcategory":"Surveying",
            "type":"Services"
        }
    ],
    "sg:phone":"+1 704 238 0471",
    "sg:postcode":"28110",
    "sg:province":"NC",
    "sg:tags":[
        "surveyor"
    ],
    "wof:name":"Huneycutt Surveying Co",
    "wof:placetype":"venue"
},
  "geometry": {"coordinates":[-80.547189,34.993139],"type":"Point"}
}