{
  "type": "Feature",
  "properties": {
    "iso:country":"US",
    "sg:address":"429 N 4th St",
    "sg:city":"Highlands",
    "sg:classifiers":[
        {
            "category":"Shopping",
            "subcategory":"Gifts & Souvenirs",
            "type":"Retail Goods"
        }
    ],
    "sg:phone":"+1 828 526 2221",
    "sg:postcode":"28741",
    "sg:province":"NC",
    "sg:tags":[
        "shop"
    ],
    "wof:name":"Interior Exchange",
    "wof:placetype":"venue"
},
  "geometry": {"coordinates":[-83.196477,35.054512],"type":"Point"}
}