{
  "type": "Feature",
  "properties": {
    "addr:full":"4115 Old Wilson Rd Rocky Mount NC 27801",
    "addr:housenumber":"4115",
    "addr:postcode":"27801",
    "addr:street":"Old Wilson Rd",
    "iso:country":"US",
    "sg:address":"4115 Old Wilson Rd",
    "sg:city":"Rocky Mount",
    "sg:classifiers":[
        {
            "category":"Home & Garden",
            "subcategory":"Home Furnishings",
            "type":"Retail Goods"
        }
    ],
    "sg:phone":"+1 252 467 0800",
    "sg:postcode":"27801",
    "sg:province":"NC",
    "sg:tags":[
        "venetian",
        "blind"
    ],
    "wof:name":"Budget Blinds",
    "wof:placetype":"venue"
},
  "geometry": {"coordinates":[-77.80423,35.879922],"type":"Point"}
}