{
  "type": "Feature",
  "properties": {
    "addr:full":"1824 N Sandhills Blvd Aberdeen NC 28315",
    "addr:housenumber":"1824",
    "addr:postcode":"28315",
    "addr:street":"N Sandhills Blvd",
    "iso:country":"US",
    "sg:address":"1824 N Sandhills Blvd",
    "sg:city":"Aberdeen",
    "sg:classifiers":[
        {
            "category":"Building & Trades",
            "subcategory":"Equipment Rental",
            "type":"Services"
        }
    ],
    "sg:phone":"+1 910 692 1999",
    "sg:postcode":"28315",
    "sg:province":"NC",
    "sg:tags":[
        "appliance"
    ],
    "sg:website":"www.rentway.com",
    "wof:name":"Rent Way",
    "wof:placetype":"venue"
},
  "geometry": {"coordinates":[-79.41500600000001,35.15459],"type":"Point"}
}