{
  "type": "Feature",
  "properties": {
    "addr:full":"6855 Belt Rd Concord NC 28027",
    "addr:housenumber":"6855",
    "addr:postcode":"28027",
    "addr:street":"Belt Rd",
    "iso:country":"US",
    "sg:address":"6855 Belt Rd",
    "sg:city":"Concord",
    "sg:classifiers":[
        {
            "category":"Wholesale",
            "subcategory":"Durable Goods & Equipment",
            "type":"Manufacturing & Wholesale Goods"
        }
    ],
    "sg:phone":"+1 704 869 9323",
    "sg:postcode":"28027",
    "sg:province":"NC",
    "sg:tags":[
        "engineering",
        "supply"
    ],
    "wof:name":"Everest VIT",
    "wof:placetype":"venue"
},
  "geometry": {"coordinates":[-80.69585600000001,35.381243],"type":"Point"}
}