{
  "type": "Feature",
  "properties": {
    "addr:full":"1090 Virginia St Eden NC 27288",
    "addr:housenumber":"1090",
    "addr:postcode":"27288",
    "addr:street":"Virginia St",
    "iso:country":"US",
    "sg:address":"1090 Virginia St",
    "sg:city":"Eden",
    "sg:classifiers":[
        {
            "category":"Building & Trades",
            "subcategory":"Construction",
            "type":"Services"
        }
    ],
    "sg:phone":"+1 336 623 7898",
    "sg:postcode":"27288",
    "sg:province":"NC",
    "sg:tags":[
        "paving",
        "contractor"
    ],
    "wof:name":"Bray's Asphalt Seal Coating Co",
    "wof:placetype":"venue"
},
  "geometry": {"coordinates":[-79.746039,36.531205],"type":"Point"}
}