{
  "type": "Feature",
  "properties": {
    "iso:country":"US",
    "sg:address":"428 Chatham View Rd",
    "sg:city":"Ramseur",
    "sg:classifiers":[
        {
            "category":"Farming",
            "subcategory":"Livestock Farm",
            "type":"Manufacturing & Wholesale Goods"
        }
    ],
    "sg:phone":"+1 919 663 3040",
    "sg:postcode":"27316",
    "sg:province":"NC",
    "sg:tags":[
        "equine"
    ],
    "wof:name":"Oak Trace Farm",
    "wof:placetype":"venue"
},
  "geometry": {"coordinates":[-79.554794,35.736826],"type":"Point"}
}