{
  "type": "Feature",
  "properties": {
    "iso:country":"US",
    "sg:address":"2301 Lake Dr",
    "sg:city":"Raleigh",
    "sg:classifiers":[
        {
            "category":"Real Estate",
            "subcategory":"Real Estate Agent",
            "type":"Services"
        }
    ],
    "sg:phone":"+1 919 781 6010",
    "sg:postcode":"27609",
    "sg:province":"NC",
    "wof:name":"Lawrence & Assoc Realtors",
    "wof:placetype":"venue"
},
  "geometry": {"coordinates":[-78.649868,35.814892],"type":"Point"}
}