{
  "type": "Feature",
  "properties": {
    "addr:full":"1108 Hill Road Cir Ayden NC 28513",
    "addr:housenumber":"1108",
    "addr:postcode":"28513",
    "addr:street":"Hill Road Cir",
    "iso:country":"US",
    "sg:address":"1108 Hill Road Cir",
    "sg:city":"Ayden",
    "sg:classifiers":[
        {
            "category":"Building & Trades",
            "subcategory":"Construction",
            "type":"Services"
        }
    ],
    "sg:phone":"+1 252 746 2067",
    "sg:postcode":"28513",
    "sg:province":"NC",
    "sg:tags":[
        "hanging",
        "contractor"
    ],
    "wof:name":"Lt Painters",
    "wof:placetype":"venue"
},
  "geometry": {"coordinates":[-77.407555,35.477064],"type":"Point"}
}