{
  "type": "Feature",
  "properties": {
    "iso:country":"US",
    "sg:address":"803 Dawson St",
    "sg:city":"Wilmington",
    "sg:classifiers":[
        {
            "category":"Health Services",
            "subcategory":"Hospital",
            "type":"Services"
        }
    ],
    "sg:phone":"+1 910 815 3008",
    "sg:postcode":"28401",
    "sg:province":"NC",
    "sg:tags":[
        "psychiatric"
    ],
    "wof:name":"Direct Support Professionals",
    "wof:placetype":"venue"
},
  "geometry": {"coordinates":[-77.937652,34.224856],"type":"Point"}
}