{
  "type": "Feature",
  "properties": {
    "addr:full":"6698 Dam Cove Rd Conover NC 28613",
    "addr:housenumber":"6698",
    "addr:postcode":"28613",
    "addr:street":"Dam Cove Rd",
    "iso:country":"US",
    "sg:address":"6698 Dam Cove Rd",
    "sg:city":"Conover",
    "sg:classifiers":[
        {
            "category":"Home & Garden",
            "subcategory":"Building Materials",
            "type":"Retail Goods"
        }
    ],
    "sg:phone":"+1 828 325 0531",
    "sg:postcode":"28613",
    "sg:province":"NC",
    "sg:tags":[
        "concrete",
        "patching",
        "compound"
    ],
    "wof:name":"Complete Concrete Coat & Dsgn",
    "wof:placetype":"venue"
},
  "geometry": {"coordinates":[-81.200766,35.815656],"type":"Point"}
}