{
  "type": "Feature",
  "properties": {
    "addr:full":"11220 Elm Ln Charlotte NC 28277",
    "addr:housenumber":"11220",
    "addr:postcode":"28277",
    "addr:street":"Elm Ln",
    "iso:country":"US",
    "sg:address":"11220 Elm Ln",
    "sg:city":"Charlotte",
    "sg:classifiers":[
        {
            "category":"Insurance",
            "subcategory":"Insurance Agent",
            "type":"Services"
        }
    ],
    "sg:phone":"+1 704 541 5166",
    "sg:postcode":"28277",
    "sg:province":"NC",
    "sg:website":"www.storickgroup.com",
    "wof:name":"Scott Storick & Assoc",
    "wof:placetype":"venue"
},
  "geometry": {"coordinates":[-80.81738799999999,35.058831],"type":"Point"}
}