{
  "type": "Feature",
  "properties": {
    "addr:full":"3940 Beacon Dr NW Winston Salem NC 27106",
    "addr:housenumber":"3940",
    "addr:postcode":"27106",
    "addr:street":"Beacon Dr Nw",
    "iso:country":"US",
    "sg:address":"3940 Beacon Dr NW",
    "sg:city":"Winston Salem",
    "sg:classifiers":[
        {
            "category":"Building & Trades",
            "subcategory":"Construction",
            "type":"Services"
        }
    ],
    "sg:phone":"+1 336 924 8877",
    "sg:postcode":"27106",
    "sg:province":"NC",
    "sg:tags":[
        "contractor"
    ],
    "wof:name":"C & S Contract Svc Inc",
    "wof:placetype":"venue"
},
  "geometry": {"coordinates":[-80.31513,36.159775],"type":"Point"}
}