{
  "type": "Feature",
  "properties": {
    "addr:full":"6444 Osceola Ossipee Rd Gibsonville NC 27249",
    "addr:housenumber":"6444",
    "addr:postcode":"27249",
    "addr:street":"Osceola Ossipee Rd",
    "iso:country":"US",
    "sg:address":"6444 Osceola Ossipee Rd",
    "sg:city":"Gibsonville",
    "sg:classifiers":[
        {
            "category":"Farming",
            "subcategory":"Farm",
            "type":"Manufacturing & Wholesale Goods"
        }
    ],
    "sg:phone":"+1 336 584 9136",
    "sg:postcode":"27249",
    "sg:province":"NC",
    "sg:tags":[
        "crop",
        "general"
    ],
    "wof:name":"Albert Brown",
    "wof:placetype":"venue"
},
  "geometry": {"coordinates":[-79.551378,36.20318],"type":"Point"}
}