{
  "type": "Feature",
  "properties": {
    "addr:full":"401 N Elm St Greensboro NC 27401",
    "addr:housenumber":"401",
    "addr:postcode":"27401",
    "addr:street":"N Elm St",
    "iso:country":"US",
    "sg:address":"401 N Elm St",
    "sg:city":"Greensboro",
    "sg:classifiers":[
        {
            "category":"Autos & Motor Vehicles",
            "subcategory":"Auto Supplies",
            "type":"Retail Goods"
        }
    ],
    "sg:phone":"+1 336 273 5547",
    "sg:postcode":"27401",
    "sg:province":"NC",
    "sg:tags":[
        "tire"
    ],
    "wof:name":"Elm Street Tire",
    "wof:placetype":"venue"
},
  "geometry": {"coordinates":[-79.789895,36.078252],"type":"Point"}
}