{
  "type": "Feature",
  "properties": {
    "iso:country":"US",
    "sg:address":"215 Queens Rd",
    "sg:city":"Charlotte",
    "sg:classifiers":[
        {
            "category":"Professional",
            "type":"Services"
        }
    ],
    "sg:phone":"+1 704 372 2142",
    "sg:postcode":"28204",
    "sg:province":"NC",
    "sg:tags":[
        "establishment"
    ],
    "wof:name":"Providence Center",
    "wof:placetype":"venue"
},
  "geometry": {"coordinates":[-80.82774499999999,35.210267],"type":"Point"}
}