{
  "type": "Feature",
  "properties": {
    "addr:full":"1751 Country Club W High Point NC 27262",
    "addr:housenumber":"1751",
    "addr:postcode":"27262",
    "addr:street":"Country Club W",
    "iso:country":"US",
    "sg:address":"1751 Country Club W",
    "sg:city":"High Point",
    "sg:classifiers":[
        {
            "category":"Retail",
            "subcategory":"Car Wash",
            "type":"Services"
        }
    ],
    "sg:phone":"+1 336 887 0188",
    "sg:postcode":"27262",
    "sg:province":"NC",
    "sg:tags":[
        "carwash",
        "equipment",
        "industrial"
    ],
    "wof:name":"Home Care Systems",
    "wof:placetype":"venue"
},
  "geometry": {"coordinates":[-80.04762100000001,35.960028],"type":"Point"}
}