{
  "type": "Feature",
  "properties": {
    "iso:country":"US",
    "sg:address":"260 S Churton St",
    "sg:city":"Hillsborough",
    "sg:classifiers":[
        {
            "category":"Banks & Credit Unions",
            "subcategory":"Bank",
            "type":"Services"
        }
    ],
    "sg:phone":"+1 919 732 2143",
    "sg:postcode":"27278",
    "sg:province":"NC",
    "sg:website":"www.ccbonline.com",
    "wof:name":"Central Carolina Bank",
    "wof:placetype":"venue"
},
  "geometry": {"coordinates":[-79.10102500000001,36.064389],"type":"Point"}
}