{
  "type": "Feature",
  "properties": {
    "iso:country":"US",
    "sg:address":"1301 King Cross Ct",
    "sg:city":"Raleigh",
    "sg:classifiers":[
        {
            "category":"Professional",
            "subcategory":"Business Services",
            "type":"Services"
        }
    ],
    "sg:phone":"+1 919 846 9191",
    "sg:postcode":"27614",
    "sg:province":"NC",
    "sg:website":"www.solutionsys.com",
    "wof:name":"Solution Systems",
    "wof:placetype":"venue"
},
  "geometry": {"coordinates":[-78.60861800000001,35.92023],"type":"Point"}
}