{
  "type": "Feature",
  "properties": {
    "iso:country":"US",
    "sg:address":"309 S Elm St",
    "sg:city":"Creedmoor",
    "sg:classifiers":[
        {
            "category":"Retail",
            "subcategory":"Auto Repair",
            "type":"Services"
        }
    ],
    "sg:phone":"+1 919 528 2033",
    "sg:postcode":"27522",
    "sg:province":"NC",
    "wof:name":"David's Auto Repair",
    "wof:placetype":"venue"
},
  "geometry": {"coordinates":[-78.689003,36.117699],"type":"Point"}
}