{
  "type": "Feature",
  "properties": {
    "addr:full":"3723 Dairy Pond Pl Durham NC 27705",
    "addr:housenumber":"3723",
    "addr:postcode":"27705",
    "addr:street":"Dairy Pond Pl",
    "iso:country":"US",
    "sg:address":"3723 Dairy Pond Pl",
    "sg:city":"Durham",
    "sg:classifiers":[
        {
            "category":"Food & Beverages",
            "subcategory":"Groceries & Convenience Stores",
            "type":"Retail Goods"
        }
    ],
    "sg:phone":"+1 919 382 9236",
    "sg:postcode":"27705",
    "sg:province":"NC",
    "wof:name":"Food Passion Inc",
    "wof:placetype":"venue"
},
  "geometry": {"coordinates":[-78.95089,36.042558],"type":"Point"}
}