{
  "type": "Feature",
  "properties": {
    "iso:country":"US",
    "sg:address":"410 Four Seasons Town Center",
    "sg:city":"Greensboro",
    "sg:classifiers":[
        {
            "category":"Professional",
            "type":"Services"
        }
    ],
    "sg:phone":"+1 336 854 3092",
    "sg:postcode":"27407",
    "sg:province":"NC",
    "wof:name":"Lotion In Motion",
    "wof:placetype":"venue"
},
  "geometry": {"coordinates":[-79.840209,36.039469],"type":"Point"}
}