{
  "type": "Feature",
  "properties": {
    "iso:country":"US",
    "sg:address":"2125 Ten Ten Rd",
    "sg:city":"Apex",
    "sg:classifiers":[
        {
            "category":"Deli",
            "type":"Food & Drink"
        },
        {
            "category":"Food & Beverages",
            "subcategory":"Bakery",
            "type":"Retail Goods"
        }
    ],
    "sg:phone":"+1 919 387 8331",
    "sg:postcode":"27539",
    "sg:province":"NC",
    "sg:tags":[
        "sandwich"
    ],
    "wof:name":"Giovanni's Sandwich Shop",
    "wof:placetype":"venue"
},
  "geometry": {"coordinates":[-78.81884700000001,35.720664],"type":"Point"}
}