{
  "type": "Feature",
  "properties": {
    "iso:country":"US",
    "sg:address":"985 Concord Pkwy S",
    "sg:city":"Concord",
    "sg:classifiers":[
        {
            "category":"Restaurant",
            "type":"Food & Drink"
        }
    ],
    "sg:menulink":"http://www.allmenus.com/nc/central-cabarrus/178907-chick-fil-a/menu/",
    "sg:phone":"+1 704 720 9115",
    "sg:postcode":"28027",
    "sg:province":"NC",
    "sg:tags":[
        "wrap",
        "soup",
        "american",
        "sandwich",
        "salad"
    ],
    "wof:name":"Chick-fil-A",
    "wof:placetype":"venue"
},
  "geometry": {"coordinates":[-80.623913,35.391961],"type":"Point"}
}