{
  "type": "Feature",
  "properties": {
    "iso:country":"US",
    "sg:address":"1459 Billy Hicks Rd",
    "sg:city":"Roxboro",
    "sg:classifiers":[
        {
            "category":"Home & Garden",
            "subcategory":"Carpets & Floor Coverings",
            "type":"Retail Goods"
        }
    ],
    "sg:phone":"+1 336 599 6203",
    "sg:postcode":"27574",
    "sg:province":"NC",
    "wof:name":"Carpet Corner",
    "wof:placetype":"venue"
},
  "geometry": {"coordinates":[-78.953255,36.358568],"type":"Point"}
}