{
  "type": "Feature",
  "properties": {
    "addr:full":"102 Wendy Ct Cary NC 27511",
    "addr:housenumber":"102",
    "addr:postcode":"27511",
    "addr:street":"Wendy Ct",
    "iso:country":"US",
    "sg:address":"102 Wendy Ct",
    "sg:city":"Cary",
    "sg:classifiers":[
        {
            "category":"Professional",
            "subcategory":"Computer Services",
            "type":"Services"
        }
    ],
    "sg:phone":"+1   ",
    "sg:postcode":"27511",
    "sg:province":"NC",
    "sg:tags":[
        "related"
    ],
    "wof:name":"Intersolutions Inc",
    "wof:placetype":"venue"
},
  "geometry": {"coordinates":[-78.79153100000001,35.768215],"type":"Point"}
}