{
  "type": "Feature",
  "properties": {
    "addr:full":"4403 Stough Rd Concord NC 28027",
    "addr:housenumber":"4403",
    "addr:postcode":"28027",
    "addr:street":"Stough Rd",
    "iso:country":"US",
    "sg:address":"4403 Stough Rd",
    "sg:city":"Concord",
    "sg:classifiers":[
        {
            "category":"Autos & Motor Vehicles",
            "subcategory":"Automobile Sales",
            "type":"Retail Goods"
        }
    ],
    "sg:phone":"+1 704 788 8315",
    "sg:postcode":"28027",
    "sg:province":"NC",
    "sg:tags":[
        "performance",
        "race",
        "dealer"
    ],
    "sg:website":"www.schraderracing.com",
    "wof:name":"Ken Schrader Racing Inc",
    "wof:placetype":"venue"
},
  "geometry": {"coordinates":[-80.616218,35.354232],"type":"Point"}
}