{
  "type": "Feature",
  "properties": {
    "addr:full":"3113 Marlboro Church Rd Sophia NC 27350",
    "addr:housenumber":"3113",
    "addr:postcode":"27350",
    "addr:street":"Marlboro Church Rd",
    "iso:country":"US",
    "sg:address":"3113 Marlboro Church Rd",
    "sg:city":"Sophia",
    "sg:classifiers":[
        {
            "category":"Farming",
            "subcategory":"Dairy Farm",
            "type":"Manufacturing & Wholesale Goods"
        }
    ],
    "sg:phone":"+1 336 498 3973",
    "sg:postcode":"27350",
    "sg:province":"NC",
    "wof:name":"Judy D Baker",
    "wof:placetype":"venue"
},
  "geometry": {"coordinates":[-79.896435,35.836567],"type":"Point"}
}