{
  "type": "Feature",
  "properties": {
    "addr:full":"5657 Bragg Blvd Fayetteville NC 28303",
    "addr:housenumber":"5657",
    "addr:postcode":"28303",
    "addr:street":"Bragg Blvd",
    "iso:country":"US",
    "sg:address":"5657 Bragg Blvd",
    "sg:city":"Fayetteville",
    "sg:classifiers":[
        {
            "category":"Insurance",
            "subcategory":"Insurance Agent",
            "type":"Services"
        }
    ],
    "sg:phone":"+1 910 867 0811",
    "sg:postcode":"28303",
    "sg:province":"NC",
    "wof:name":"Debbie's Insurance",
    "wof:placetype":"venue"
},
  "geometry": {"coordinates":[-78.958443,35.101522],"type":"Point"}
}