{
  "type": "Feature",
  "properties": {
    "iso:country":"US",
    "sg:address":"1628 Doctors Cir",
    "sg:city":"Wilmington",
    "sg:classifiers":[
        {
            "category":"Health Services",
            "subcategory":"Doctor",
            "type":"Services"
        }
    ],
    "sg:phone":"+1 910 763 2476",
    "sg:postcode":"28401",
    "sg:province":"NC",
    "sg:tags":[
        "medical"
    ],
    "wof:name":"Forehand Lamond & Carter",
    "wof:placetype":"venue"
},
  "geometry": {"coordinates":[-77.92551400000001,34.206914],"type":"Point"}
}