{
  "type": "Feature",
  "properties": {
    "iso:country":"US",
    "sg:address":"2407 Forest Hills Rd W",
    "sg:city":"Wilson",
    "sg:classifiers":[
        {
            "category":"Restaurant",
            "type":"Food & Drink"
        }
    ],
    "sg:menulink":"http://www.allmenus.com/nc/wilson/178987-chick-fil-a/menu/",
    "sg:phone":"+1 252 206 9862",
    "sg:postcode":"27893",
    "sg:province":"NC",
    "sg:tags":[
        "wrap",
        "soup",
        "american",
        "sandwich",
        "salad"
    ],
    "wof:name":"Chick-fil-A",
    "wof:placetype":"venue"
},
  "geometry": {"coordinates":[-77.952162,35.733062],"type":"Point"}
}