{
  "type": "Feature",
  "properties": {
    "addr:full":"398 Pleasant Garden Rd Bladenboro NC 28320",
    "addr:housenumber":"398",
    "addr:postcode":"28320",
    "addr:street":"Pleasant Garden Rd",
    "iso:country":"US",
    "sg:address":"398 Pleasant Garden Rd",
    "sg:city":"Bladenboro",
    "sg:classifiers":[
        {
            "category":"Travel",
            "subcategory":"Travel Agent",
            "type":"Entertainment"
        }
    ],
    "sg:phone":"+1 910 648 5871",
    "sg:postcode":"28320",
    "sg:province":"NC",
    "sg:tags":[
        "tours",
        "promoter"
    ],
    "wof:name":"Interstate Tours USA",
    "wof:placetype":"venue"
},
  "geometry": {"coordinates":[-78.81747,34.484434],"type":"Point"}
}