{
  "type": "Feature",
  "properties": {
    "addr:full":"101 Hannah Ln Rocky Mount NC 27803",
    "addr:housenumber":"101",
    "addr:postcode":"27803",
    "addr:street":"Hannah Ln",
    "iso:country":"US",
    "sg:address":"101 Hannah Ln",
    "sg:city":"Rocky Mount",
    "sg:classifiers":[
        {
            "category":"Real Estate",
            "subcategory":"Real Estate Operator",
            "type":"Services"
        }
    ],
    "sg:phone":"+1 252 446 2441",
    "sg:postcode":"27803",
    "sg:province":"NC",
    "sg:tags":[
        "apartment"
    ],
    "wof:name":"Hannah Lane Apartments",
    "wof:placetype":"venue"
},
  "geometry": {"coordinates":[-77.81711799999999,35.917747],"type":"Point"}
}