{
  "type": "Feature",
  "properties": {
    "addr:full":"2010 S Main St Wake Forest NC 27587",
    "addr:housenumber":"2010",
    "addr:postcode":"27587",
    "addr:street":"S Main St",
    "iso:country":"US",
    "sg:address":"2010 S Main St",
    "sg:city":"Wake Forest",
    "sg:classifiers":[
        {
            "category":"Restaurant",
            "type":"Food & Drink"
        }
    ],
    "sg:phone":"+1 919 562 0660",
    "sg:postcode":"27587",
    "sg:province":"NC",
    "wof:name":"Full Moon Italian Cafe",
    "wof:placetype":"venue"
},
  "geometry": {"coordinates":[-78.531308,35.949696],"type":"Point"}
}