{
  "type": "Feature",
  "properties": {
    "iso:country":"US",
    "sg:address":"1520 Burnetts Chapel Rd",
    "sg:city":"Greensboro",
    "sg:classifiers":[
        {
            "category":"Real Estate",
            "subcategory":"Real Estate Operator",
            "type":"Services"
        }
    ],
    "sg:phone":"+1 336 230 1919",
    "sg:postcode":"27407",
    "sg:province":"NC",
    "sg:tags":[
        "auto",
        "parts"
    ],
    "wof:name":"Greensboro Antiques",
    "wof:placetype":"venue"
},
  "geometry": {"coordinates":[-79.850741,35.954875],"type":"Point"}
}