{
  "type": "Feature",
  "properties": {
    "iso:country":"US",
    "sg:address":"1915 Onslow Dr",
    "sg:city":"Jacksonville",
    "sg:classifiers":[
        {
            "category":"Health Services",
            "subcategory":"Doctor",
            "type":"Services"
        }
    ],
    "sg:phone":"+1   ",
    "sg:postcode":"28540",
    "sg:province":"NC",
    "sg:tags":[
        "medical"
    ],
    "wof:name":"Department of Social Service",
    "wof:placetype":"venue"
},
  "geometry": {"coordinates":[-77.40728900000001,34.753237],"type":"Point"}
}