{
  "type": "Feature",
  "properties": {
    "addr:full":"814 7th Ave E Hendersonville NC 28792",
    "addr:housenumber":"814",
    "addr:postcode":"28792",
    "addr:street":"7Th Ave E",
    "iso:country":"US",
    "sg:address":"814 7th Ave E",
    "sg:city":"Hendersonville",
    "sg:classifiers":[
        {
            "category":"Banks & Credit Unions",
            "subcategory":"Investment Brokerage",
            "type":"Services"
        }
    ],
    "sg:phone":"+1 828 693 7334",
    "sg:postcode":"28792",
    "sg:province":"NC",
    "sg:tags":[
        "consultant",
        "planning",
        "financial"
    ],
    "wof:name":"Roger Lowe Insurance",
    "wof:placetype":"venue"
},
  "geometry": {"coordinates":[-82.453295,35.323881],"type":"Point"}
}