{
  "type": "Feature",
  "properties": {
    "addr:full":"127 US Hwy 70 W Garner NC 27529",
    "addr:housenumber":"127",
    "addr:postcode":"27529",
    "addr:street":"Us Hwy 70 W",
    "iso:country":"US",
    "sg:address":"127 US Hwy 70 W",
    "sg:city":"Garner",
    "sg:classifiers":[
        {
            "category":"Shopping",
            "subcategory":"Pharmacy",
            "type":"Retail Goods"
        }
    ],
    "sg:phone":"+1 919 329 6744",
    "sg:postcode":"27529",
    "sg:province":"NC",
    "wof:name":"Eckerd",
    "wof:placetype":"venue"
},
  "geometry": {"coordinates":[-78.61534399999999,35.706979],"type":"Point"}
}