{
  "type": "Feature",
  "properties": {
    "addr:full":"1605 Lord Finwick Pl Greensboro NC 27405",
    "addr:housenumber":"1605",
    "addr:postcode":"27405",
    "addr:street":"Lord Finwick Pl",
    "iso:country":"US",
    "sg:address":"1605 Lord Finwick Pl",
    "sg:city":"Greensboro",
    "sg:classifiers":[
        {
            "category":"Building & Trades",
            "subcategory":"Landscaping Services",
            "type":"Services"
        }
    ],
    "sg:phone":"+1 336 423 7511",
    "sg:postcode":"27405",
    "sg:province":"NC",
    "sg:tags":[
        "lawn",
        "maintenance",
        "grounds"
    ],
    "wof:name":"Bobby's Lawn Svc",
    "wof:placetype":"venue"
},
  "geometry": {"coordinates":[-79.738452,36.099612],"type":"Point"}
}