{
  "type": "Feature",
  "properties": {
    "iso:country":"US",
    "sg:address":"405 Battleground Ave",
    "sg:city":"Greensboro",
    "sg:classifiers":[
        {
            "category":"Insurance",
            "subcategory":"Insurance Agent",
            "type":"Services"
        }
    ],
    "sg:phone":"+1 336 273 7084",
    "sg:postcode":"27410",
    "sg:province":"NC",
    "sg:tags":[
        "consultant"
    ],
    "wof:name":"Coface North America Insurance",
    "wof:placetype":"venue"
},
  "geometry": {"coordinates":[-79.79331999999999,36.078186],"type":"Point"}
}