{
  "type": "Feature",
  "properties": {
    "addr:full":"8960 Valley Blvd Blowing Rock NC 28605",
    "addr:housenumber":"8960",
    "addr:postcode":"28605",
    "addr:street":"Valley Blvd",
    "iso:country":"US",
    "sg:address":"8960 Valley Blvd",
    "sg:city":"Blowing Rock",
    "sg:classifiers":[
        {
            "category":"Restaurant",
            "type":"Food & Drink"
        }
    ],
    "sg:menulink":"http://www.allmenus.com/nc/globe/136264-canyons-restaurant/menu/",
    "sg:phone":"+1 828 295 7661",
    "sg:postcode":"28605",
    "sg:province":"NC",
    "sg:tags":[
        "american"
    ],
    "wof:name":"Canyons Restaurant",
    "wof:placetype":"venue"
},
  "geometry": {"coordinates":[-81.664209,36.120003],"type":"Point"}
}