{
  "type": "Feature",
  "properties": {
    "iso:country":"US",
    "sg:address":"132 N Main St",
    "sg:city":"Norwood",
    "sg:classifiers":[
        {
            "category":"Autos & Motor Vehicles",
            "subcategory":"Auto Supplies",
            "type":"Retail Goods"
        }
    ],
    "sg:phone":"+1 704 474 3718",
    "sg:postcode":"28128",
    "sg:province":"NC",
    "sg:tags":[
        "automobile",
        "parts"
    ],
    "wof:name":"Western Auto",
    "wof:placetype":"venue"
},
  "geometry": {"coordinates":[-80.11984200000001,35.224963],"type":"Point"}
}