{
  "type": "Feature",
  "properties": {
    "iso:country":"US",
    "sg:address":"115 W Tryon St",
    "sg:city":"Hillsborough",
    "sg:classifiers":[
        {
            "category":"Health Services",
            "subcategory":"Doctor",
            "type":"Services"
        }
    ],
    "sg:phone":"+1   ",
    "sg:postcode":"27278",
    "sg:province":"NC",
    "wof:name":"Ray Margaret Walker DDS",
    "wof:placetype":"venue"
},
  "geometry": {"coordinates":[-79.099834,36.076971],"type":"Point"}
}