{
  "type": "Feature",
  "properties": {
    "iso:country":"US",
    "sg:address":"354 E Main St",
    "sg:city":"Franklin",
    "sg:classifiers":[
        {
            "category":"Retail",
            "subcategory":"Auto Repair",
            "type":"Services"
        }
    ],
    "sg:phone":"+1   ",
    "sg:postcode":"28734",
    "sg:province":"NC",
    "sg:tags":[
        "automotive",
        "general"
    ],
    "wof:name":"Ambassador Automotive",
    "wof:placetype":"venue"
},
  "geometry": {"coordinates":[-83.375263,35.183593],"type":"Point"}
}