{
  "type": "Feature",
  "properties": {
    "addr:full":"3704 Doc Bennett Rd Fayetteville NC 28306",
    "addr:housenumber":"3704",
    "addr:postcode":"28306",
    "addr:street":"Doc Bennett Rd",
    "iso:country":"US",
    "sg:address":"3704 Doc Bennett Rd",
    "sg:city":"Fayetteville",
    "sg:classifiers":[
        {
            "category":"Sports & Exercise",
            "subcategory":"Race Track",
            "type":"Entertainment"
        }
    ],
    "sg:phone":"+1 910 484 3677",
    "sg:postcode":"28306",
    "sg:province":"NC",
    "wof:name":"Fayetteville Motorsports Park",
    "wof:placetype":"venue"
},
  "geometry": {"coordinates":[-78.877517,34.978168],"type":"Point"}
}