{
  "type": "Feature",
  "properties": {
    "iso:country":"US",
    "sg:address":"734 W 2nd St",
    "sg:city":"Washington",
    "sg:classifiers":[
        {
            "category":"Banks & Credit Unions",
            "subcategory":"Bank",
            "type":"Services"
        }
    ],
    "sg:phone":"+1 252 946 1972",
    "sg:postcode":"27889",
    "sg:province":"NC",
    "sg:tags":[
        "loan",
        "real estate"
    ],
    "wof:name":"Columbia National Inc",
    "wof:placetype":"venue"
},
  "geometry": {"coordinates":[-77.063582,35.547509],"type":"Point"}
}