{
  "type": "Feature",
  "properties": {
    "iso:country":"US",
    "sg:address":"158 Everett St",
    "sg:city":"Bryson City",
    "sg:classifiers":[
        {
            "category":"Manufacturing",
            "subcategory":"Signs",
            "type":"Manufacturing & Wholesale Goods"
        }
    ],
    "sg:phone":"+1 828 488 1715",
    "sg:postcode":"28713",
    "sg:province":"NC",
    "sg:tags":[
        "specialty",
        "mfg"
    ],
    "wof:name":"Sticky Sams Signs",
    "wof:placetype":"venue"
},
  "geometry": {"coordinates":[-83.446304,35.429116],"type":"Point"}
}