{
  "type": "Feature",
  "properties": {
    "iso:country":"US",
    "sg:address":"7544 Fulghum Rd",
    "sg:city":"Kenly",
    "sg:classifiers":[
        {
            "category":"Building & Trades",
            "subcategory":"Construction",
            "type":"Services"
        }
    ],
    "sg:phone":"+1 252 291 8198",
    "sg:postcode":"27542",
    "sg:province":"NC",
    "sg:tags":[
        "house"
    ],
    "wof:name":"Jerry W Coleman Cnstr Co",
    "wof:placetype":"venue"
},
  "geometry": {"coordinates":[-78.10662499999999,35.711697],"type":"Point"}
}