{
  "type": "Feature",
  "properties": {
    "addr:full":"2902 S Church St Rocky Mount NC 27803",
    "addr:housenumber":"2902",
    "addr:postcode":"27803",
    "addr:street":"S Church St",
    "iso:country":"US",
    "sg:address":"2902 S Church St",
    "sg:city":"Rocky Mount",
    "sg:classifiers":[
        {
            "category":"Shopping",
            "subcategory":"Used Merchandise",
            "type":"Retail Goods"
        }
    ],
    "sg:phone":"+1 252 442 0050",
    "sg:postcode":"27803",
    "sg:province":"NC",
    "sg:tags":[
        "furniture"
    ],
    "wof:name":"C & J's Treasure Chest",
    "wof:placetype":"venue"
},
  "geometry": {"coordinates":[-77.810058,35.911488],"type":"Point"}
}