{
  "type": "Feature",
  "properties": {
    "addr:full":"8711 Six Forks Rd Raleigh NC 27615",
    "addr:housenumber":"8711",
    "addr:postcode":"27615",
    "addr:street":"Six Forks Rd",
    "iso:country":"US",
    "sg:address":"8711 Six Forks Rd",
    "sg:city":"Raleigh",
    "sg:classifiers":[
        {
            "category":"Professional",
            "subcategory":"Computer Services",
            "type":"Services"
        }
    ],
    "sg:phone":"+1 919 848 3259",
    "sg:postcode":"27615",
    "sg:province":"NC",
    "sg:tags":[
        "repair"
    ],
    "wof:name":"Call The PC Guy",
    "wof:placetype":"venue"
},
  "geometry": {"coordinates":[-78.651471,35.899405],"type":"Point"}
}