{
  "type": "Feature",
  "properties": {
    "iso:country":"US",
    "sg:address":"8109 Olde Hill Ct",
    "sg:city":"Raleigh",
    "sg:classifiers":[
        {
            "category":"Wholesale",
            "subcategory":"Machinery & Supplies",
            "type":"Manufacturing & Wholesale Goods"
        }
    ],
    "sg:phone":"+1 919 803 4544",
    "sg:postcode":"27615",
    "sg:province":"NC",
    "sg:tags":[
        "equipment",
        "irrigation",
        "system"
    ],
    "wof:name":"Spray Smart Irrigation",
    "wof:placetype":"venue"
},
  "geometry": {"coordinates":[-78.64230999999999,35.889421],"type":"Point"}
}