{
  "type": "Feature",
  "properties": {
    "addr:full":"5959 Dean Ave Raleigh NC 27616",
    "addr:housenumber":"5959",
    "addr:postcode":"27616",
    "addr:street":"Dean Ave",
    "iso:country":"US",
    "sg:address":"5959 Dean Ave",
    "sg:city":"Raleigh",
    "sg:classifiers":[
        {
            "category":"Shopping",
            "subcategory":"Gifts & Souvenirs",
            "type":"Retail Goods"
        }
    ],
    "sg:phone":"+1 919 792 2303",
    "sg:postcode":"27616",
    "sg:province":"NC",
    "sg:tags":[
        "shop"
    ],
    "wof:name":"Charlotte's Inc",
    "wof:placetype":"venue"
},
  "geometry": {"coordinates":[-78.562377,35.861437],"type":"Point"}
}