{
  "type": "Feature",
  "properties": {
    "addr:full":"1188 US Hwy 158 Oxford NC 27565",
    "addr:housenumber":"1188",
    "addr:postcode":"27565",
    "addr:street":"Us Hwy 158",
    "iso:country":"US",
    "sg:address":"1188 US Hwy 158",
    "sg:city":"Oxford",
    "sg:phone":"+1 919 693 4792",
    "sg:postcode":"27565",
    "sg:province":"NC",
    "sg:tags":[
        "farm",
        "tobacco"
    ],
    "wof:name":"Denny Farm",
    "wof:placetype":"venue"
},
  "geometry": {"coordinates":[-78.74055799999999,36.317919],"type":"Point"}
}