{
  "type": "Feature",
  "properties": {
    "addr:full":"722 Washington St Eden NC 27288",
    "addr:housenumber":"722",
    "addr:postcode":"27288",
    "addr:street":"Washington St",
    "iso:country":"US",
    "sg:address":"722 Washington St",
    "sg:city":"Eden",
    "sg:classifiers":[
        {
            "category":"Banks & Credit Unions",
            "subcategory":"Bank",
            "type":"Services"
        }
    ],
    "sg:phone":"+1 336 623 9787",
    "sg:postcode":"27288",
    "sg:province":"NC",
    "wof:name":"Home Savings Bank",
    "wof:placetype":"venue"
},
  "geometry": {"coordinates":[-79.764793,36.48987],"type":"Point"}
}