{
  "type": "Feature",
  "properties": {
    "iso:country":"US",
    "sg:address":"5946 Millbury Ct",
    "sg:city":"Charlotte",
    "sg:classifiers":[
        {
            "category":"Building & Trades",
            "subcategory":"Construction",
            "type":"Services"
        }
    ],
    "sg:phone":"+1 704 362 3144",
    "sg:postcode":"28211",
    "sg:province":"NC",
    "sg:tags":[
        "architectural",
        "contractor"
    ],
    "sg:website":"www.pooldesignconsultants.com",
    "wof:name":"Pool Design Consultants Inc",
    "wof:placetype":"venue"
},
  "geometry": {"coordinates":[-80.777716,35.162085],"type":"Point"}
}