{
  "type": "Feature",
  "properties": {
    "iso:country":"US",
    "sg:address":"717 S Main St",
    "sg:city":"Laurinburg",
    "sg:classifiers":[
        {
            "category":"Real Estate",
            "subcategory":"Real Estate Agent",
            "type":"Services"
        }
    ],
    "sg:phone":"+1 910 276 1200",
    "sg:postcode":"28352",
    "sg:province":"NC",
    "wof:name":"Associated Realty Of Scotland",
    "wof:placetype":"venue"
},
  "geometry": {"coordinates":[-79.46509,34.769824],"type":"Point"}
}