{
  "type": "Feature",
  "properties": {
    "iso:country":"US",
    "sg:address":"950 US Hwy 64 W",
    "sg:city":"Apex",
    "sg:classifiers":[
        {
            "category":"Personal",
            "subcategory":"Beauty Salon",
            "type":"Services"
        }
    ],
    "sg:phone":"+1 919 468 5050",
    "sg:postcode":"27523",
    "sg:province":"NC",
    "sg:website":"www.greatclips.com",
    "wof:name":"Great Clips",
    "wof:placetype":"venue"
},
  "geometry": {"coordinates":[-78.82561200000001,35.744716],"type":"Point"}
}