{
  "type": "Feature",
  "properties": {
    "addr:full":"174 Valley Ct Hickory NC 28602",
    "addr:housenumber":"174",
    "addr:postcode":"28602",
    "addr:street":"Valley Ct",
    "iso:country":"US",
    "sg:address":"174 Valley Ct",
    "sg:city":"Hickory",
    "sg:classifiers":[
        {
            "category":"Shopping",
            "subcategory":"Tobacco",
            "type":"Retail Goods"
        }
    ],
    "sg:phone":"+1 828 328 8002",
    "sg:postcode":"28602",
    "sg:province":"NC",
    "sg:tags":[
        "product"
    ],
    "wof:name":"Pipes Ltd",
    "wof:placetype":"venue"
},
  "geometry": {"coordinates":[-81.37487,35.662143],"type":"Point"}
}