{
  "type": "Feature",
  "properties": {
    "addr:full":"3320 Executive Dr Raleigh NC 27609",
    "addr:housenumber":"3320",
    "addr:postcode":"27609",
    "addr:street":"Executive Dr",
    "iso:country":"US",
    "sg:address":"3320 Executive Dr",
    "sg:city":"Raleigh",
    "sg:classifiers":[
        {
            "category":"Health Services",
            "subcategory":"Doctor",
            "type":"Services"
        }
    ],
    "sg:phone":"+1 919 878 8596",
    "sg:postcode":"27609",
    "sg:province":"NC",
    "sg:tags":[
        "physician",
        "surgeon",
        "medical"
    ],
    "wof:name":"Capital Family Medicine",
    "wof:placetype":"venue"
},
  "geometry": {"coordinates":[-78.617266,35.829533],"type":"Point"}
}