{
  "type": "Feature",
  "properties": {
    "addr:full":"830 Dolly St NW Concord NC 28027",
    "addr:housenumber":"830",
    "addr:postcode":"28027",
    "addr:street":"Dolly St Nw",
    "iso:country":"US",
    "sg:address":"830 Dolly St NW",
    "sg:city":"Concord",
    "sg:classifiers":[
        {
            "category":"Building & Trades",
            "subcategory":"Construction",
            "type":"Services"
        }
    ],
    "sg:phone":"+1 704 786 4181",
    "sg:postcode":"28027",
    "sg:province":"NC",
    "sg:tags":[
        "general",
        "contractor"
    ],
    "wof:name":"Graham Construction Co",
    "wof:placetype":"venue"
},
  "geometry": {"coordinates":[-80.609679,35.427277],"type":"Point"}
}