{
  "type": "Feature",
  "properties": {
    "addr:full":"1421 E Cone Blvd Greensboro NC 27405",
    "addr:housenumber":"1421",
    "addr:postcode":"27405",
    "addr:street":"E Cone Blvd",
    "iso:country":"US",
    "sg:address":"1421 E Cone Blvd",
    "sg:city":"Greensboro",
    "sg:classifiers":[
        {
            "category":"Food & Beverages",
            "subcategory":"Groceries & Convenience Stores",
            "type":"Retail Goods"
        }
    ],
    "sg:phone":"+1 336 375 8845",
    "sg:postcode":"27405",
    "sg:province":"NC",
    "sg:website":"www.winndixie.com",
    "wof:name":"Winn-Dixie",
    "wof:placetype":"venue"
},
  "geometry": {"coordinates":[-79.768326,36.113613],"type":"Point"}
}