{
  "type": "Feature",
  "properties": {
    "addr:full":"9009 J M Keynes Dr Charlotte NC 28262",
    "addr:housenumber":"9009",
    "addr:postcode":"28262",
    "addr:street":"J M Keynes Dr",
    "iso:country":"US",
    "sg:address":"9009 J M Keynes Dr",
    "sg:city":"Charlotte",
    "sg:classifiers":[
        {
            "category":"Personal",
            "subcategory":"Beauty Salon",
            "type":"Services"
        }
    ],
    "sg:phone":"+1 704 547 9435",
    "sg:postcode":"28262",
    "sg:province":"NC",
    "sg:tags":[
        "barber"
    ],
    "sg:website":"http://www.haircuttery.com/",
    "wof:name":"Hair Cuttery",
    "wof:placetype":"venue"
},
  "geometry": {"coordinates":[-80.747979,35.310847],"type":"Point"}
}