{
  "type": "Feature",
  "properties": {
    "iso:country":"US",
    "sg:address":"606 Glenwood Ave",
    "sg:city":"Raleigh",
    "sg:classifiers":[
        {
            "category":"Manufacturing",
            "subcategory":"Printing",
            "type":"Manufacturing & Wholesale Goods"
        }
    ],
    "sg:phone":"+1 919 833 5934",
    "sg:postcode":"27603",
    "sg:province":"NC",
    "sg:tags":[
        "lithographic",
        "commercial",
        "typesetting"
    ],
    "wof:name":"Hill Printing Co Inc",
    "wof:placetype":"venue"
},
  "geometry": {"coordinates":[-78.64707300000001,35.788553],"type":"Point"}
}