{
  "type": "Feature",
  "properties": {
    "iso:country":"US",
    "sg:address":"2676 Henson Creek Rd",
    "sg:city":"Newland",
    "sg:classifiers":[
        {
            "category":"Retail",
            "subcategory":"Auto Repair",
            "type":"Services"
        }
    ],
    "sg:phone":"+1 828 765 4373",
    "sg:postcode":"28657",
    "sg:province":"NC",
    "sg:tags":[
        "body",
        "automobile",
        "painting"
    ],
    "wof:name":"Tim's Body Shop & Wrecker Svc",
    "wof:placetype":"venue"
},
  "geometry": {"coordinates":[-82.05057600000001,36.041813],"type":"Point"}
}