{
  "type": "Feature",
  "properties": {
    "iso:country":"US",
    "sg:address":"1913 S Wesleyan Blvd",
    "sg:city":"Rocky Mount",
    "sg:classifiers":[
        {
            "category":"Autos & Motor Vehicles",
            "subcategory":"Automobile Sales",
            "type":"Retail Goods"
        }
    ],
    "sg:phone":"+1 252 977 9791",
    "sg:postcode":"27803",
    "sg:province":"NC",
    "sg:tags":[
        "car",
        "dealer"
    ],
    "wof:name":"Curt Van Inc",
    "wof:placetype":"venue"
},
  "geometry": {"coordinates":[-77.826054,35.900153],"type":"Point"}
}