{
  "type": "Feature",
  "properties": {
    "addr:full":"143 Perrin Pl Charlotte NC 28207",
    "addr:housenumber":"143",
    "addr:postcode":"28207",
    "addr:street":"Perrin Pl",
    "iso:country":"US",
    "sg:address":"143 Perrin Pl",
    "sg:city":"Charlotte",
    "sg:classifiers":[
        {
            "category":"Wholesale",
            "subcategory":"Machinery & Supplies",
            "type":"Manufacturing & Wholesale Goods"
        }
    ],
    "sg:phone":"+1 704 376 5911",
    "sg:postcode":"28207",
    "sg:province":"NC",
    "sg:tags":[
        "equipment",
        "industrial"
    ],
    "wof:name":"Jkdk",
    "wof:placetype":"venue"
},
  "geometry": {"coordinates":[-80.825687,35.197048],"type":"Point"}
}