{
  "type": "Feature",
  "properties": {
    "iso:country":"US",
    "sg:address":"47 Spring St NW",
    "sg:city":"Concord",
    "sg:classifiers":[
        {
            "category":"Professional",
            "subcategory":"Management & Consulting",
            "type":"Services"
        },
        {
            "category":"Arts & Performance",
            "subcategory":"Theater",
            "type":"Entertainment"
        }
    ],
    "sg:phone":"+1 704 784 3337",
    "sg:postcode":"28025",
    "sg:province":"NC",
    "sg:tags":[
        "movie"
    ],
    "wof:name":"Bee Creative Co",
    "wof:placetype":"venue"
},
  "geometry": {"coordinates":[-80.583742,35.410356],"type":"Point"}
}