{
  "type": "Feature",
  "properties": {
    "iso:country":"US",
    "sg:address":"230 N Bennett St",
    "sg:city":"Southern Pines",
    "sg:classifiers":[
        {
            "category":"Real Estate",
            "subcategory":"Architect",
            "type":"Services"
        }
    ],
    "sg:phone":"+1 910 695 1441",
    "sg:postcode":"28387",
    "sg:province":"NC",
    "wof:name":"Heckethorn Architecture",
    "wof:placetype":"venue"
},
  "geometry": {"coordinates":[-79.39084800000001,35.176424],"type":"Point"}
}