{
  "type": "Feature",
  "properties": {
    "iso:country":"US",
    "sg:address":"205 3rd Ave NW",
    "sg:city":"Conover",
    "sg:classifiers":[
        {
            "category":"Manufacturing",
            "subcategory":"Tools & Machinery",
            "type":"Manufacturing & Wholesale Goods"
        }
    ],
    "sg:phone":"+1 828 465 0118",
    "sg:postcode":"28613",
    "sg:province":"NC",
    "sg:tags":[
        "die",
        "cutting"
    ],
    "wof:name":"Otto Inc",
    "wof:placetype":"venue"
},
  "geometry": {"coordinates":[-81.22028400000001,35.709105],"type":"Point"}
}