{
  "type": "Feature",
  "properties": {
    "iso:country":"US",
    "sg:address":"179 Valleyview Rd",
    "sg:city":"Mooresville",
    "sg:classifiers":[
        {
            "category":"Building & Trades",
            "subcategory":"Cleaning & Sanitation",
            "type":"Services"
        }
    ],
    "sg:phone":"+1 704 663 2191",
    "sg:postcode":"28117",
    "sg:province":"NC",
    "sg:tags":[
        "janitor"
    ],
    "wof:name":"Checkered Flag Cleaning",
    "wof:placetype":"venue"
},
  "geometry": {"coordinates":[-80.840841,35.606504],"type":"Point"}
}