{
  "type": "Feature",
  "properties": {
    "addr:full":"1698 Island Rd Harkers Island NC 28531",
    "addr:housenumber":"1698",
    "addr:postcode":"28531",
    "addr:street":"Island Rd",
    "iso:country":"US",
    "sg:address":"1698 Island Rd",
    "sg:city":"Harkers Island",
    "sg:classifiers":[
        {
            "category":"Travel",
            "subcategory":"Hotels & Motels",
            "type":"Entertainment"
        }
    ],
    "sg:phone":"+1 252 728 3575",
    "sg:postcode":"28531",
    "sg:province":"NC",
    "sg:website":"www.capelookoutferry.com",
    "wof:name":"Calico Jacks Inn & Marina",
    "wof:placetype":"venue"
},
  "geometry": {"coordinates":[-76.531156,34.686428],"type":"Point"}
}