{
  "type": "Feature",
  "properties": {
    "addr:full":"112 Willow Peak Rd Hendersonville NC 28739",
    "addr:housenumber":"112",
    "addr:postcode":"28739",
    "addr:street":"Willow Peak Rd",
    "iso:country":"US",
    "sg:address":"112 Willow Peak Rd",
    "sg:city":"Hendersonville",
    "sg:classifiers":[
        {
            "category":"Building & Trades",
            "subcategory":"Construction",
            "type":"Services"
        }
    ],
    "sg:phone":"+1 828 696 2516",
    "sg:postcode":"28739",
    "sg:province":"NC",
    "sg:tags":[
        "carpentry",
        "contractor"
    ],
    "wof:name":"Keith Morris Custom Cabinets",
    "wof:placetype":"venue"
},
  "geometry": {"coordinates":[-82.541893,35.285433],"type":"Point"}
}