{
  "type": "Feature",
  "properties": {
    "iso:country":"US",
    "sg:address":"5101 Monroe Rd",
    "sg:city":"Charlotte",
    "sg:classifiers":[
        {
            "category":"Professional",
            "subcategory":"Secretarial Services",
            "type":"Services"
        }
    ],
    "sg:phone":"+1 704 531 7100",
    "sg:postcode":"28205",
    "sg:province":"NC",
    "sg:tags":[
        "reporting",
        "court"
    ],
    "wof:name":"Charlotte Corporate Svc",
    "wof:placetype":"venue"
},
  "geometry": {"coordinates":[-80.775374,35.190796],"type":"Point"}
}