{
  "type": "Feature",
  "properties": {
    "iso:country":"US",
    "sg:address":"109 Millbrae Ln",
    "sg:city":"Chapel Hill",
    "sg:classifiers":[
        {
            "category":"Professional",
            "subcategory":"Lawyer & Legal Services",
            "type":"Services"
        }
    ],
    "sg:phone":"+1   ",
    "sg:postcode":"27514",
    "sg:province":"NC",
    "sg:tags":[
        "consulting",
        "trust"
    ],
    "wof:name":"Frank A Sloan",
    "wof:placetype":"venue"
},
  "geometry": {"coordinates":[-79.025492,35.956923],"type":"Point"}
}