{
  "type": "Feature",
  "properties": {
    "addr:full":"103 W Masonic St Creedmoor NC 27522",
    "addr:housenumber":"103",
    "addr:postcode":"27522",
    "addr:street":"W Masonic St",
    "iso:country":"US",
    "sg:address":"103 W Masonic St",
    "sg:city":"Creedmoor",
    "sg:classifiers":[
        {
            "category":"Retail",
            "subcategory":"Pet Boarding",
            "type":"Services"
        }
    ],
    "sg:phone":"+1 919 529 1111",
    "sg:postcode":"27522",
    "sg:province":"NC",
    "sg:tags":[
        "boarding/pet",
        "sitting"
    ],
    "wof:name":"Purple Poodle",
    "wof:placetype":"venue"
},
  "geometry": {"coordinates":[-78.672203,36.120499],"type":"Point"}
}