{
  "type": "Feature",
  "properties": {
    "iso:country":"US",
    "sg:address":"303 Old Spring Hill Ln",
    "sg:city":"Fuquay Varina",
    "sg:classifiers":[
        {
            "category":"Professional",
            "subcategory":"Business Services",
            "type":"Services"
        }
    ],
    "sg:phone":"+1   ",
    "sg:postcode":"27526",
    "sg:province":"NC",
    "wof:name":"David A Jones",
    "wof:placetype":"venue"
},
  "geometry": {"coordinates":[-78.802324,35.575643],"type":"Point"}
}