{
  "type": "Feature",
  "properties": {
    "addr:full":"315 W Main St Clayton NC 27520",
    "addr:housenumber":"315",
    "addr:postcode":"27520",
    "addr:street":"W Main St",
    "iso:country":"US",
    "sg:address":"315 W Main St",
    "sg:city":"Clayton",
    "sg:classifiers":[
        {
            "category":"Manufacturing",
            "subcategory":"Signs",
            "type":"Manufacturing & Wholesale Goods"
        }
    ],
    "sg:phone":"+1 919 553 2273",
    "sg:postcode":"27520",
    "sg:province":"NC",
    "sg:tags":[
        "customer",
        "maker"
    ],
    "wof:name":"Signage Of The Carolinas",
    "wof:placetype":"venue"
},
  "geometry": {"coordinates":[-78.462923,35.65551],"type":"Point"}
}