{
  "type": "Feature",
  "properties": {
    "iso:country":"US",
    "sg:address":"105 E Franklin St",
    "sg:city":"Chapel Hill",
    "sg:classifiers":[
        {
            "category":"Shopping",
            "subcategory":"Beauty & Cosmetics",
            "type":"Retail Goods"
        }
    ],
    "sg:phone":"+1 919 968 7800",
    "sg:postcode":"27514",
    "sg:province":"NC",
    "sg:tags":[
        "personal",
        "product",
        "care"
    ],
    "wof:name":"Bath & Body Works",
    "wof:placetype":"venue"
},
  "geometry": {"coordinates":[-79.05462300000001,35.913669],"type":"Point"}
}