{
  "type": "Feature",
  "properties": {
    "iso:country":"US",
    "sg:address":"212 W Main St",
    "sg:city":"Sanford",
    "sg:classifiers":[
        {
            "category":"Health Services",
            "subcategory":"Doctor",
            "type":"Services"
        }
    ],
    "sg:phone":"+1 919 776 0004",
    "sg:postcode":"27332",
    "sg:province":"NC",
    "sg:tags":[
        "physician",
        "surgeon"
    ],
    "wof:name":"Carolina Medicine",
    "wof:placetype":"venue"
},
  "geometry": {"coordinates":[-79.153063,35.456356],"type":"Point"}
}