{
  "type": "Feature",
  "properties": {
    "addr:full":"209 Eastside Dr Statesville NC 28625",
    "addr:housenumber":"209",
    "addr:postcode":"28625",
    "addr:street":"Eastside Dr",
    "iso:country":"US",
    "sg:address":"209 Eastside Dr",
    "sg:city":"Statesville",
    "sg:classifiers":[
        {
            "category":"Banks & Credit Unions",
            "subcategory":"Bank",
            "type":"Services"
        }
    ],
    "sg:phone":"+1 704 873 2803",
    "sg:postcode":"28625",
    "sg:province":"NC",
    "sg:tags":[
        "institution",
        "business"
    ],
    "wof:name":"Allied Financial Services Inc",
    "wof:placetype":"venue"
},
  "geometry": {"coordinates":[-80.857071,35.790578],"type":"Point"}
}