{
  "type": "Feature",
  "properties": {
    "addr:full":"10822 Pineville Rd Pineville NC 28134",
    "addr:housenumber":"10822",
    "addr:postcode":"28134",
    "addr:street":"Pineville Rd",
    "iso:country":"US",
    "sg:address":"10822 Pineville Rd",
    "sg:city":"Pineville",
    "sg:classifiers":[
        {
            "category":"Autos & Motor Vehicles",
            "subcategory":"Auto Supplies",
            "type":"Retail Goods"
        }
    ],
    "sg:phone":"+1 704 553 0199",
    "sg:postcode":"28134",
    "sg:province":"NC",
    "sg:tags":[
        "automobile",
        "parts"
    ],
    "wof:name":"Hubcap Masters",
    "wof:placetype":"venue"
},
  "geometry": {"coordinates":[-80.88397500000001,35.094294],"type":"Point"}
}