{
  "type": "Feature",
  "properties": {
    "iso:country":"US",
    "sg:address":"149 N Cherry St",
    "sg:city":"Kernersville",
    "sg:classifiers":[
        {
            "category":"Health Services",
            "subcategory":"Doctor",
            "type":"Services"
        }
    ],
    "sg:phone":"+1   ",
    "sg:postcode":"27284",
    "sg:province":"NC",
    "sg:tags":[
        "medical"
    ],
    "wof:name":"Curling O Del Jr MD",
    "wof:placetype":"venue"
},
  "geometry": {"coordinates":[-80.073052,36.122222],"type":"Point"}
}