{
  "type": "Feature",
  "properties": {
    "iso:country":"US",
    "sg:address":"208 Radford Rd",
    "sg:city":"Ellenboro",
    "sg:classifiers":[
        {
            "category":"Building & Trades",
            "subcategory":"Construction",
            "type":"Services"
        }
    ],
    "sg:phone":"+1 828 657 4430",
    "sg:postcode":"28019",
    "sg:province":"NC",
    "sg:tags":[
        "contractor"
    ],
    "wof:name":"Pannell & Dobbins Inc",
    "wof:placetype":"venue"
},
  "geometry": {"coordinates":[-81.783717,35.28175],"type":"Point"}
}