{
  "type": "Feature",
  "properties": {
    "iso:country":"US",
    "sg:address":"3617 Market St",
    "sg:city":"Wilmington",
    "sg:classifiers":[
        {
            "category":"Restaurant",
            "type":"Food & Drink"
        }
    ],
    "sg:phone":"+1 910 772 9000",
    "sg:postcode":"28403",
    "sg:province":"NC",
    "wof:name":"LA Costa Mexican Restaurant",
    "wof:placetype":"venue"
},
  "geometry": {"coordinates":[-77.89972299999999,34.241134],"type":"Point"}
}