{
  "type": "Feature",
  "properties": {
    "addr:full":"3070 Adams Creek Rd Havelock NC 28532",
    "addr:housenumber":"3070",
    "addr:postcode":"28532",
    "addr:street":"Adams Creek Rd",
    "iso:country":"US",
    "sg:address":"3070 Adams Creek Rd",
    "sg:city":"Havelock",
    "sg:classifiers":[
        {
            "category":"Organizations",
            "subcategory":"Religious Organization",
            "type":"Services"
        }
    ],
    "sg:phone":"+1 252 447 4391",
    "sg:postcode":"28532",
    "sg:province":"NC",
    "sg:tags":[
        "church"
    ],
    "wof:name":"Oak Grove United Methodist Chr",
    "wof:placetype":"venue"
},
  "geometry": {"coordinates":[-76.728207,34.907696],"type":"Point"}
}