{
  "type": "Feature",
  "properties": {
    "iso:country":"US",
    "sg:address":"3605 Governors Rd",
    "sg:city":"Kelford",
    "sg:classifiers":[
        {
            "category":"Restaurant",
            "type":"Food & Drink"
        }
    ],
    "sg:phone":"+1 252 348 2280",
    "sg:postcode":"27847",
    "sg:province":"NC",
    "wof:name":"Bazemore Country Kitchen",
    "wof:placetype":"venue"
},
  "geometry": {"coordinates":[-77.21132299999999,36.145004],"type":"Point"}
}