{
  "type": "Feature",
  "properties": {
    "iso:country":"US",
    "sg:address":"1428 W Pine St",
    "sg:city":"Mount Airy",
    "sg:classifiers":[
        {
            "category":"Insurance",
            "subcategory":"Insurance Agent",
            "type":"Services"
        }
    ],
    "sg:phone":"+1 336 786 1532",
    "sg:postcode":"27030",
    "sg:province":"NC",
    "wof:name":"David S Brintle Insurance Agcy",
    "wof:placetype":"venue"
},
  "geometry": {"coordinates":[-80.638002,36.501099],"type":"Point"}
}