{
  "type": "Feature",
  "properties": {
    "addr:full":"706 W 2nd Ave Lexington NC 27292",
    "addr:housenumber":"706",
    "addr:postcode":"27292",
    "addr:street":"W 2Nd Ave",
    "iso:country":"US",
    "sg:address":"706 W 2nd Ave",
    "sg:city":"Lexington",
    "sg:classifiers":[
        {
            "category":"Personal",
            "subcategory":"Beauty Salon",
            "type":"Services"
        }
    ],
    "sg:phone":"+1 336 248 5275",
    "sg:postcode":"27292",
    "sg:province":"NC",
    "wof:name":"Hair Studio 21",
    "wof:placetype":"venue"
},
  "geometry": {"coordinates":[-80.262029,35.829304],"type":"Point"}
}