{
  "type": "Feature",
  "properties": {
    "addr:full":"700 N Roberts Ave Lumberton NC 28358",
    "addr:housenumber":"700",
    "addr:postcode":"28358",
    "addr:street":"N Roberts Ave",
    "iso:country":"US",
    "sg:address":"700 N Roberts Ave",
    "sg:city":"Lumberton",
    "sg:classifiers":[
        {
            "category":"Food & Beverages",
            "subcategory":"Groceries & Convenience Stores",
            "type":"Retail Goods"
        }
    ],
    "sg:phone":"+1 910 739 8315",
    "sg:postcode":"28358",
    "sg:province":"NC",
    "sg:tags":[
        "product"
    ],
    "wof:name":"Scottish Foods Systems Distrct",
    "wof:placetype":"venue"
},
  "geometry": {"coordinates":[-78.98189499999999,34.622208],"type":"Point"}
}