{
  "type": "Feature",
  "properties": {
    "iso:country":"US",
    "sg:address":"101 Reliance Rd",
    "sg:city":"Kings Mountain",
    "sg:classifiers":[
        {
            "category":"Building & Trades",
            "subcategory":"Electrical",
            "type":"Services"
        }
    ],
    "sg:phone":"+1 704 734 2500",
    "sg:postcode":"28086",
    "sg:province":"NC",
    "sg:tags":[
        "electric",
        "contractor"
    ],
    "wof:name":"Reliance Electric Engineered",
    "wof:placetype":"venue"
},
  "geometry": {"coordinates":[-81.41073299999999,35.249477],"type":"Point"}
}