{
  "type": "Feature",
  "properties": {
    "addr:full":"2317 Old Liberty Rd Randleman NC 27317",
    "addr:housenumber":"2317",
    "addr:postcode":"27317",
    "addr:street":"Old Liberty Rd",
    "iso:country":"US",
    "sg:address":"2317 Old Liberty Rd",
    "sg:city":"Randleman",
    "sg:classifiers":[
        {
            "category":"Building & Trades",
            "subcategory":"Construction",
            "type":"Services"
        },
        {
            "category":"Building & Trades",
            "subcategory":"Plumbing",
            "type":"Services"
        }
    ],
    "sg:phone":"+1 336 302 4499",
    "sg:postcode":"27317",
    "sg:province":"NC",
    "sg:tags":[
        "home",
        "contractor",
        "improvement"
    ],
    "wof:name":"John & Sons Friendly Plumbing",
    "wof:placetype":"venue"
},
  "geometry": {"coordinates":[-79.765479,35.770106],"type":"Point"}
}