{
  "type": "Feature",
  "properties": {
    "addr:full":"104 W Trade St Forest City NC 28043",
    "addr:housenumber":"104",
    "addr:postcode":"28043",
    "addr:street":"W Trade St",
    "iso:country":"US",
    "sg:address":"104 W Trade St",
    "sg:city":"Forest City",
    "sg:classifiers":[
        {
            "category":"Personal",
            "subcategory":"Beauty Salon",
            "type":"Services"
        }
    ],
    "sg:phone":"+1   ",
    "sg:postcode":"28043",
    "sg:province":"NC",
    "sg:tags":[
        "shop"
    ],
    "wof:name":"Hair Heaven Beauty Salon",
    "wof:placetype":"venue"
},
  "geometry": {"coordinates":[-81.865505,35.335331],"type":"Point"}
}