{
  "type": "Feature",
  "properties": {
    "iso:country":"US",
    "sg:address":"5058 State Hwy 49 S",
    "sg:city":"Harrisburg",
    "sg:classifiers":[
        {
            "category":"Professional",
            "subcategory":"Accounting & Tax Preparation",
            "type":"Services"
        }
    ],
    "sg:phone":"+1 704 455 7844",
    "sg:postcode":"28075",
    "sg:province":"NC",
    "sg:tags":[
        "consultant"
    ],
    "wof:name":"Us Tax Pro Inc",
    "wof:placetype":"venue"
},
  "geometry": {"coordinates":[-80.659803,35.321356],"type":"Point"}
}