{
  "type": "Feature",
  "properties": {
    "iso:country":"US",
    "sg:address":"3741 Cokey Rd",
    "sg:city":"Rocky Mount",
    "sg:classifiers":[
        {
            "category":"Organizations",
            "subcategory":"Religious Organization",
            "type":"Services"
        }
    ],
    "sg:phone":"+1 252 442 7041",
    "sg:postcode":"27801",
    "sg:province":"NC",
    "wof:name":"West Edgecombe Baptist Church",
    "wof:placetype":"venue"
},
  "geometry": {"coordinates":[-77.742583,35.90675],"type":"Point"}
}