{
  "type": "Feature",
  "properties": {
    "iso:country":"US",
    "sg:address":"6725 Brachnell View Dr",
    "sg:city":"Charlotte",
    "sg:classifiers":[
        {
            "category":"Building & Trades",
            "subcategory":"Construction",
            "type":"Services"
        }
    ],
    "sg:phone":"+1 704 509 6870",
    "sg:postcode":"28269",
    "sg:province":"NC",
    "sg:tags":[
        "house"
    ],
    "wof:name":"Pennies From Heaven Remodeling",
    "wof:placetype":"venue"
},
  "geometry": {"coordinates":[-80.799226,35.308201],"type":"Point"}
}