{
  "type": "Feature",
  "properties": {
    "addr:full":"4315 Lead Mine Rd Raleigh NC 27612",
    "addr:housenumber":"4315",
    "addr:postcode":"27612",
    "addr:street":"Lead Mine Rd",
    "iso:country":"US",
    "sg:address":"4315 Lead Mine Rd",
    "sg:city":"Raleigh",
    "sg:classifiers":[
        {
            "category":"Real Estate",
            "subcategory":"Real Estate Services",
            "type":"Services"
        }
    ],
    "sg:phone":"+1 888 809 2166",
    "sg:postcode":"27612",
    "sg:province":"NC",
    "sg:tags":[
        "apartment",
        "management",
        "rental",
        "finder"
    ],
    "wof:name":"Northampton/Richmond Hills",
    "wof:placetype":"venue"
},
  "geometry": {"coordinates":[-78.673716,35.838978],"type":"Point"}
}