{
  "type": "Feature",
  "properties": {
    "iso:country":"US",
    "sg:address":"212 S Grove St",
    "sg:city":"Hendersonville",
    "sg:classifiers":[
        {
            "category":"Shopping",
            "type":"Retail Goods"
        }
    ],
    "sg:phone":"+1 828 692 0580",
    "sg:postcode":"28792",
    "sg:province":"NC",
    "sg:tags":[
        "hearing",
        "equipment",
        "supply",
        "impaired"
    ],
    "wof:name":"Beltone Hearing Aid Ctr",
    "wof:placetype":"venue"
},
  "geometry": {"coordinates":[-82.457043,35.313622],"type":"Point"}
}