{
  "type": "Feature",
  "properties": {
    "addr:full":"2502 Hillsborough St Raleigh NC 27607",
    "addr:housenumber":"2502",
    "addr:postcode":"27607",
    "addr:street":"Hillsborough St",
    "iso:country":"US",
    "sg:address":"2502 Hillsborough St",
    "sg:city":"Raleigh",
    "sg:classifiers":[
        {
            "category":"Restaurant",
            "type":"Food & Drink"
        }
    ],
    "sg:phone":"+1 919 754 9797",
    "sg:postcode":"27607",
    "sg:province":"NC",
    "sg:tags":[
        "eating"
    ],
    "wof:name":"Shanghai Express",
    "wof:placetype":"venue"
},
  "geometry": {"coordinates":[-78.669629,35.788203],"type":"Point"}
}