{
  "type": "Feature",
  "properties": {
    "addr:full":"4014 Oleander Dr Wilmington NC 28403",
    "addr:housenumber":"4014",
    "addr:postcode":"28403",
    "addr:street":"Oleander Dr",
    "iso:country":"US",
    "sg:address":"4014 Oleander Dr",
    "sg:city":"Wilmington",
    "sg:classifiers":[
        {
            "category":"Health Services",
            "subcategory":"Health Practitioner",
            "type":"Services"
        }
    ],
    "sg:phone":"+1 910 790 9500",
    "sg:postcode":"28403",
    "sg:province":"NC",
    "sg:tags":[
        "psychologist",
        "specialty",
        "outpatient"
    ],
    "wof:name":"Chrysalis Ctr For Counseling",
    "wof:placetype":"venue"
},
  "geometry": {"coordinates":[-77.897006,34.212629],"type":"Point"}
}