{
  "type": "Feature",
  "properties": {
    "iso:country":"US",
    "sg:address":"157 Jackson Ave",
    "sg:city":"Hot Springs",
    "sg:classifiers":[
        {
            "category":"Social Services",
            "type":"Services"
        }
    ],
    "sg:phone":"+1 828 622 7205",
    "sg:postcode":"28743",
    "sg:province":"NC",
    "sg:tags":[
        "organization",
        "welfare"
    ],
    "wof:name":"Salvation Army Quarters",
    "wof:placetype":"venue"
},
  "geometry": {"coordinates":[-82.832763,35.89293],"type":"Point"}
}