{
  "type": "Feature",
  "properties": {
    "iso:country":"US",
    "sg:address":"1006 E E St",
    "sg:city":"Butner",
    "sg:classifiers":[
        {
            "category":"Social Services",
            "subcategory":"Child Care",
            "type":"Services"
        }
    ],
    "sg:phone":"+1   ",
    "sg:postcode":"27509",
    "sg:province":"NC",
    "sg:tags":[
        "day"
    ],
    "wof:name":"Heavens Delight Day Care Home",
    "wof:placetype":"venue"
},
  "geometry": {"coordinates":[-78.751121,36.145804],"type":"Point"}
}