{
  "type": "Feature",
  "properties": {
    "addr:full":"109 NE 1st St Pinetops NC 27864",
    "addr:housenumber":"109",
    "addr:postcode":"27864",
    "addr:street":"Ne 1St St",
    "iso:country":"US",
    "sg:address":"109 NE 1st St",
    "sg:city":"Pinetops",
    "sg:classifiers":[
        {
            "category":"Professional",
            "subcategory":"Advertising",
            "type":"Services"
        }
    ],
    "sg:phone":"+1 252 827 2150",
    "sg:postcode":"27864",
    "sg:province":"NC",
    "sg:tags":[
        "counselor"
    ],
    "wof:name":"Media Mix Marketing",
    "wof:placetype":"venue"
},
  "geometry": {"coordinates":[-77.636893,35.791912],"type":"Point"}
}