{
  "type": "Feature",
  "properties": {
    "addr:full":"701 Hill St Greensboro NC 27408",
    "addr:housenumber":"701",
    "addr:postcode":"27408",
    "addr:street":"Hill St",
    "iso:country":"US",
    "sg:address":"701 Hill St",
    "sg:city":"Greensboro",
    "sg:classifiers":[
        {
            "category":"Wholesale",
            "subcategory":"Durable Goods & Equipment",
            "type":"Manufacturing & Wholesale Goods"
        }
    ],
    "sg:phone":"+1 336 273 2424",
    "sg:postcode":"27408",
    "sg:province":"NC",
    "sg:tags":[
        "importer"
    ],
    "wof:name":"Wind Rose",
    "wof:placetype":"venue"
},
  "geometry": {"coordinates":[-79.800856,36.080172],"type":"Point"}
}