{
  "type": "Feature",
  "properties": {
    "iso:country":"US",
    "sg:address":"2633 Pinewood Rd",
    "sg:city":"Gastonia",
    "sg:classifiers":[
        {
            "category":"Professional",
            "subcategory":"Business Services",
            "type":"Services"
        }
    ],
    "sg:phone":"+1   ",
    "sg:postcode":"28054",
    "sg:province":"NC",
    "wof:name":"Sparkles LLC",
    "wof:placetype":"venue"
},
  "geometry": {"coordinates":[-81.13611899999999,35.251191],"type":"Point"}
}