{
  "type": "Feature",
  "properties": {
    "addr:full":"125 High Sail Ct Mooresville NC 28117",
    "addr:housenumber":"125",
    "addr:postcode":"28117",
    "addr:street":"High Sail Ct",
    "iso:country":"US",
    "sg:address":"125 High Sail Ct",
    "sg:city":"Mooresville",
    "sg:classifiers":[
        {
            "category":"Manufacturing",
            "subcategory":"Printing",
            "type":"Manufacturing & Wholesale Goods"
        }
    ],
    "sg:phone":"+1 704 662 6404",
    "sg:postcode":"28117",
    "sg:province":"NC",
    "sg:tags":[
        "publisher",
        "software"
    ],
    "wof:name":"CRV Inc",
    "wof:placetype":"venue"
},
  "geometry": {"coordinates":[-80.907498,35.549904],"type":"Point"}
}