{
  "type": "Feature",
  "properties": {
    "addr:full":"2200 Westchester Dr High Point NC 27262",
    "addr:housenumber":"2200",
    "addr:postcode":"27262",
    "addr:street":"Westchester Dr",
    "iso:country":"US",
    "sg:address":"2200 Westchester Dr",
    "sg:city":"High Point",
    "sg:classifiers":[
        {
            "category":"Food & Beverages",
            "subcategory":"Groceries & Convenience Stores",
            "type":"Retail Goods"
        }
    ],
    "sg:phone":"+1 336 885 5896",
    "sg:postcode":"27262",
    "sg:province":"NC",
    "sg:tags":[
        "grocer"
    ],
    "sg:website":"www.foodlion.com",
    "wof:name":"Food Lion",
    "wof:placetype":"venue"
},
  "geometry": {"coordinates":[-80.034386,35.939849],"type":"Point"}
}