{
  "type": "Feature",
  "properties": {
    "addr:full":"5591 Hendersonville Rd Fletcher NC 28732",
    "addr:postcode":"5591;28732",
    "addr:street":"Hendersonville Rd",
    "iso:country":"US",
    "sg:address":"5591 Hendersonville Rd",
    "sg:city":"Fletcher",
    "sg:classifiers":[
        {
            "category":"Personal",
            "subcategory":"Beauty Salon",
            "type":"Services"
        }
    ],
    "sg:phone":"+1 828 651 9905",
    "sg:postcode":"28732",
    "sg:province":"NC",
    "wof:name":"Cutting Edge Salon",
    "wof:placetype":"venue"
},
  "geometry": {"coordinates":[-82.5138,35.40693],"type":"Point"}
}