{
  "type": "Feature",
  "properties": {
    "addr:full":"1340 SE Maynard Rd Cary NC 27511",
    "addr:housenumber":"1340",
    "addr:postcode":"27511",
    "addr:street":"Se Maynard Rd",
    "iso:country":"US",
    "sg:address":"1340 SE Maynard Rd",
    "sg:city":"Cary",
    "sg:classifiers":[
        {
            "category":"Professional",
            "type":"Services"
        }
    ],
    "sg:phone":"+1 919 463 0997",
    "sg:postcode":"27511",
    "sg:province":"NC",
    "sg:tags":[
        "establishment"
    ],
    "wof:name":"Payment Processing Inc",
    "wof:placetype":"venue"
},
  "geometry": {"coordinates":[-78.76400099999999,35.787539],"type":"Point"}
}