{
  "type": "Feature",
  "properties": {
    "iso:country":"US",
    "sg:address":"5135 Country Club Rd",
    "sg:city":"Winston Salem",
    "sg:classifiers":[
        {
            "category":"Autos & Motor Vehicles",
            "subcategory":"Automobile Sales",
            "type":"Retail Goods"
        }
    ],
    "sg:phone":"+1 336 774 2057",
    "sg:postcode":"27104",
    "sg:province":"NC",
    "sg:tags":[
        "car",
        "dealer"
    ],
    "wof:name":"Club Haven Auto Sales",
    "wof:placetype":"venue"
},
  "geometry": {"coordinates":[-80.351203,36.084824],"type":"Point"}
}