{
  "type": "Feature",
  "properties": {
    "addr:full":"2936 Beech Glen Rd Mars Hill NC 28754",
    "addr:housenumber":"2936",
    "addr:postcode":"28754",
    "addr:street":"Beech Glen Rd Mars Hill",
    "iso:country":"US",
    "sg:address":"2936 Beech Glen Rd",
    "sg:city":"Mars Hill",
    "sg:classifiers":[
        {
            "category":"Recreation",
            "type":"Entertainment"
        }
    ],
    "sg:phone":"+1 828 680 9525",
    "sg:postcode":"28754",
    "sg:province":"NC",
    "sg:tags":[
        "hall",
        "auditorium"
    ],
    "wof:name":"Beach Glen Community Ctr",
    "wof:placetype":"venue"
},
  "geometry": {"coordinates":[-82.50551,35.8186],"type":"Point"}
}