{
  "type": "Feature",
  "properties": {
    "iso:country":"US",
    "sg:address":"2005 Corporate Dr",
    "sg:city":"Wilmington",
    "sg:classifiers":[
        {
            "category":"Building & Trades",
            "subcategory":"Construction",
            "type":"Services"
        }
    ],
    "sg:phone":"+1 910 452 2993",
    "sg:postcode":"28405",
    "sg:province":"NC",
    "sg:tags":[
        "painter"
    ],
    "wof:name":"Ludlum Glenn Painting Inc",
    "wof:placetype":"venue"
},
  "geometry": {"coordinates":[-77.869338,34.299291],"type":"Point"}
}