{
  "type": "Feature",
  "properties": {
    "iso:country":"US",
    "sg:address":"190 Luffman Farm Rd",
    "sg:city":"Ronda",
    "sg:classifiers":[
        {
            "category":"Real Estate",
            "subcategory":"Real Estate Operator",
            "type":"Services"
        }
    ],
    "sg:phone":"+1 336 957 4271",
    "sg:postcode":"28670",
    "sg:province":"NC",
    "sg:tags":[
        "building",
        "apartment"
    ],
    "wof:name":"Jacob Manor Apartments",
    "wof:placetype":"venue"
},
  "geometry": {"coordinates":[-80.909108,36.26707],"type":"Point"}
}