{
  "type": "Feature",
  "properties": {
    "iso:country":"US",
    "sg:address":"4300 McKee Rd",
    "sg:city":"Charlotte",
    "sg:classifiers":[
        {
            "category":"Organizations",
            "subcategory":"Religious Organization",
            "type":"Services"
        }
    ],
    "sg:phone":"+1 704 847 5600",
    "sg:postcode":"28270",
    "sg:province":"NC",
    "sg:tags":[
        "church"
    ],
    "wof:name":"Southern Evangelical Seminary",
    "wof:placetype":"venue"
},
  "geometry": {"coordinates":[-80.75760699999999,35.067942],"type":"Point"}
}