{
  "type": "Feature",
  "properties": {
    "iso:country":"US",
    "sg:address":"2333 Mount Vernon Church Rd",
    "sg:city":"Raleigh",
    "sg:classifiers":[
        {
            "category":"Professional",
            "type":"Services"
        }
    ],
    "sg:phone":"+1 919 676 4235",
    "sg:postcode":"27614",
    "sg:province":"NC",
    "sg:tags":[
        "establishment"
    ],
    "wof:name":"Itron",
    "wof:placetype":"venue"
},
  "geometry": {"coordinates":[-78.678934,35.960629],"type":"Point"}
}