{
  "type": "Feature",
  "properties": {
    "addr:full":"219 Bell Fork Rd Jacksonville NC 28540",
    "addr:housenumber":"219",
    "addr:postcode":"28540",
    "addr:street":"Bell Fork Rd",
    "iso:country":"US",
    "sg:address":"219 Bell Fork Rd",
    "sg:city":"Jacksonville",
    "sg:classifiers":[
        {
            "category":"Retail",
            "subcategory":"Auto Repair",
            "type":"Services"
        }
    ],
    "sg:phone":"+1 910 346 9625",
    "sg:postcode":"28540",
    "sg:province":"NC",
    "sg:tags":[
        "muffler",
        "exhaust",
        "system"
    ],
    "wof:name":"Ronnie's Muffler Shop",
    "wof:placetype":"venue"
},
  "geometry": {"coordinates":[-77.40196899999999,34.763675],"type":"Point"}
}