{
  "type": "Feature",
  "properties": {
    "iso:country":"US",
    "sg:address":"1305 W Roosevelt Blvd",
    "sg:city":"Monroe",
    "sg:classifiers":[
        {
            "category":"Home & Garden",
            "subcategory":"Household Appliances",
            "type":"Retail Goods"
        }
    ],
    "sg:phone":"+1 704 289 9551",
    "sg:postcode":"28110",
    "sg:province":"NC",
    "wof:name":"Queen City Appliances & TV",
    "wof:placetype":"venue"
},
  "geometry": {"coordinates":[-80.544977,34.996305],"type":"Point"}
}