{
  "type": "Feature",
  "properties": {
    "iso:country":"US",
    "sg:address":"327 W Main St",
    "sg:city":"Havelock",
    "sg:classifiers":[
        {
            "category":"Shopping",
            "type":"Retail Goods"
        },
        {
            "category":"Shopping",
            "subcategory":"Gifts & Souvenirs",
            "type":"Retail Goods"
        }
    ],
    "sg:phone":"+1 252 444 4505",
    "sg:postcode":"28532",
    "sg:province":"NC",
    "sg:tags":[
        "cards",
        "sport",
        "baseball",
        "memorabilia"
    ],
    "sg:website":"www.hall-of-fame-sports.com",
    "wof:name":"Hall of Fame Sports",
    "wof:placetype":"venue"
},
  "geometry": {"coordinates":[-76.917337,34.887263],"type":"Point"}
}