{
  "type": "Feature",
  "properties": {
    "iso:country":"US",
    "sg:address":"4715 E Independence Blvd",
    "sg:city":"Charlotte",
    "sg:classifiers":[
        {
            "category":"Bars & Pubs",
            "type":"Food & Drink"
        }
    ],
    "sg:menulink":"http://www.allmenus.com/nc/charlotte/57894-macarenas-bar--grill/menu/",
    "sg:phone":"+1 704 536 6848",
    "sg:postcode":"28212",
    "sg:province":"NC",
    "sg:tags":[
        "spanish"
    ],
    "wof:name":"Macarena's Bar & Grill",
    "wof:placetype":"venue"
},
  "geometry": {"coordinates":[-80.76483899999999,35.193206],"type":"Point"}
}