{
  "type": "Feature",
  "properties": {
    "iso:country":"US",
    "sg:address":"17008 State Hwy 150",
    "sg:city":"Mooresville",
    "sg:classifiers":[
        {
            "category":"Professional",
            "subcategory":"Business Services",
            "type":"Services"
        }
    ],
    "sg:phone":"+1 704 664 7484",
    "sg:postcode":"28115",
    "sg:province":"NC",
    "sg:tags":[
        "tank",
        "testing",
        "inspection"
    ],
    "sg:website":"www.ndei.net",
    "wof:name":"Non Destructive Evaluation",
    "wof:placetype":"venue"
},
  "geometry": {"coordinates":[-80.735488,35.617996],"type":"Point"}
}