{
  "type": "Feature",
  "properties": {
    "addr:full":"107 Doe Ln Ahoskie NC 27983",
    "addr:housenumber":"107",
    "addr:postcode":"27983",
    "addr:street":"Doe Ln",
    "iso:country":"US",
    "sg:address":"107 Doe Ln",
    "sg:city":"Ahoskie",
    "sg:phone":"+1 252 332 3439",
    "sg:postcode":"27983",
    "sg:province":"NC",
    "sg:tags":[
        "farm",
        "field",
        "tobacco",
        "crop"
    ],
    "wof:name":"Pierce Farm",
    "wof:placetype":"venue"
},
  "geometry": {"coordinates":[-76.928347,35.928379],"type":"Point"}
}