{
  "type": "Feature",
  "properties": {
    "addr:full":"660 Merrimon Ave Asheville NC 28804",
    "addr:housenumber":"660",
    "addr:postcode":"28804",
    "addr:street":"Merrimon Ave",
    "iso:country":"US",
    "sg:address":"660 Merrimon Ave",
    "sg:city":"Asheville",
    "sg:classifiers":[
        {
            "category":"Shopping",
            "subcategory":"Pharmacy",
            "type":"Retail Goods"
        }
    ],
    "sg:phone":"+1 828 252 7626",
    "sg:postcode":"28804",
    "sg:province":"NC",
    "wof:name":"Lord's Drug Store",
    "wof:placetype":"venue"
},
  "geometry": {"coordinates":[-82.554682,35.622595],"type":"Point"}
}