{
  "type": "Feature",
  "properties": {
    "iso:country":"US",
    "sg:address":"731 Providence Rd",
    "sg:city":"Charlotte",
    "sg:phone":"+1 704 334 2288",
    "sg:postcode":"28207",
    "sg:province":"NC",
    "wof:name":"Taipei Express",
    "wof:placetype":"venue"
},
  "geometry": {"coordinates":[-80.825653,35.199711],"type":"Point"}
}