{
  "type": "Feature",
  "properties": {
    "addr:full":"8217 Old Waxhaw Monroe Rd Waxhaw NC 28173",
    "addr:housenumber":"8217",
    "addr:postcode":"28173",
    "addr:street":"Old Waxhaw Monroe Rd",
    "iso:country":"US",
    "sg:address":"8217 Old Waxhaw Monroe Rd",
    "sg:city":"Waxhaw",
    "sg:classifiers":[
        {
            "category":"Manufacturing",
            "subcategory":"Tools & Machinery",
            "type":"Manufacturing & Wholesale Goods"
        }
    ],
    "sg:phone":"+1 704 843 2870",
    "sg:postcode":"28173",
    "sg:province":"NC",
    "sg:tags":[
        "c",
        "mfg",
        "industry",
        "hanging"
    ],
    "wof:name":"American Pressure Wshg & Pntg",
    "wof:placetype":"venue"
},
  "geometry": {"coordinates":[-80.72895800000001,34.905909],"type":"Point"}
}