{
  "type": "Feature",
  "properties": {
    "iso:country":"US",
    "sg:address":"10401 Durant Rd",
    "sg:city":"Raleigh",
    "sg:classifiers":[
        {
            "category":"Education",
            "subcategory":"School",
            "type":"Public Place"
        }
    ],
    "sg:phone":"+1 919 870 4098",
    "sg:postcode":"27614",
    "sg:province":"NC",
    "sg:tags":[
        "middle"
    ],
    "wof:name":"Durant Road Middle School",
    "wof:placetype":"venue"
},
  "geometry": {"coordinates":[-78.588122,35.904443],"type":"Point"}
}