{
  "type": "Feature",
  "properties": {
    "addr:full":"1200 Southern Grace Ln Raleigh NC 27603",
    "addr:housenumber":"1200",
    "addr:postcode":"27603",
    "addr:street":"Southern Grace Ln",
    "iso:country":"US",
    "sg:address":"1200 Southern Grace Ln",
    "sg:city":"Raleigh",
    "sg:classifiers":[
        {
            "category":"Personal",
            "type":"Services"
        }
    ],
    "sg:phone":"+1   ",
    "sg:postcode":"27603",
    "sg:province":"NC",
    "wof:name":"Southern Grace Wedding Chapel",
    "wof:placetype":"venue"
},
  "geometry": {"coordinates":[-78.638362,35.58303],"type":"Point"}
}