{
  "type": "Feature",
  "properties": {
    "iso:country":"US",
    "sg:address":"2940 US Hwy 64 W",
    "sg:city":"Plymouth",
    "sg:classifiers":[
        {
            "category":"Building & Trades",
            "subcategory":"Construction",
            "type":"Services"
        }
    ],
    "sg:phone":"+1 252 793 1026",
    "sg:postcode":"27962",
    "sg:province":"NC",
    "sg:tags":[
        "contractor"
    ],
    "wof:name":"Phelps Pressure Washing",
    "wof:placetype":"venue"
},
  "geometry": {"coordinates":[-76.780366,35.829803],"type":"Point"}
}