{
  "type": "Feature",
  "properties": {
    "iso:country":"US",
    "sg:address":"5205 Deergrass Ct",
    "sg:city":"Raleigh",
    "sg:classifiers":[
        {
            "category":"Real Estate",
            "subcategory":"Real Estate Agent",
            "type":"Services"
        }
    ],
    "sg:phone":"+1 919 272 3316",
    "sg:postcode":"27613",
    "sg:province":"NC",
    "wof:name":"D K K Developers LLC",
    "wof:placetype":"venue"
},
  "geometry": {"coordinates":[-78.69572700000001,35.928796],"type":"Point"}
}