{
  "type": "Feature",
  "properties": {
    "addr:full":"281 Bricks Ln Whitakers NC 27891",
    "addr:housenumber":"281",
    "addr:postcode":"27891",
    "addr:street":"Bricks Ln",
    "iso:country":"US",
    "sg:address":"281 Bricks Ln",
    "sg:city":"Whitakers",
    "sg:classifiers":[
        {
            "category":"Professional",
            "subcategory":"Business Services",
            "type":"Services"
        }
    ],
    "sg:phone":"+1 252 437 1824",
    "sg:postcode":"27891",
    "sg:province":"NC",
    "sg:tags":[
        "conference",
        "center"
    ],
    "wof:name":"Franklinton Center At Bricks",
    "wof:placetype":"venue"
},
  "geometry": {"coordinates":[-77.69814700000001,36.145221],"type":"Point"}
}