{
  "type": "Feature",
  "properties": {
    "addr:full":"7335 Sunset Lake Rd Fuquay Varina NC 27526",
    "addr:housenumber":"7335",
    "addr:postcode":"27526",
    "addr:street":"Sunset Lake Rd",
    "iso:country":"US",
    "sg:address":"7335 Sunset Lake Rd",
    "sg:city":"Fuquay Varina",
    "sg:phone":"+1 919 552 5274",
    "sg:postcode":"27526",
    "sg:province":"NC",
    "sg:tags":[
        "farm",
        "tobacco"
    ],
    "wof:name":"Willie Wilkes",
    "wof:placetype":"venue"
},
  "geometry": {"coordinates":[-78.774416,35.596141],"type":"Point"}
}