{
  "type": "Feature",
  "properties": {
    "iso:country":"US",
    "sg:address":"239 Mount Herman Rd",
    "sg:city":"Hudson",
    "sg:classifiers":[
        {
            "category":"Organizations",
            "subcategory":"Religious Organization",
            "type":"Services"
        }
    ],
    "sg:phone":"+1 828 728 2459",
    "sg:postcode":"28638",
    "sg:province":"NC",
    "sg:tags":[
        "church"
    ],
    "wof:name":"Ambassador Baptist Church",
    "wof:placetype":"venue"
},
  "geometry": {"coordinates":[-81.48871800000001,35.85624],"type":"Point"}
}