{
  "type": "Feature",
  "properties": {
    "iso:country":"US",
    "sg:address":"809 W Minneola St",
    "sg:city":"Gibsonville",
    "sg:classifiers":[
        {
            "category":"Social Services",
            "subcategory":"Child Care",
            "type":"Services"
        }
    ],
    "sg:phone":"+1   ",
    "sg:postcode":"27249",
    "sg:province":"NC",
    "sg:tags":[
        "day"
    ],
    "wof:name":"Pulliam Family Care Home",
    "wof:placetype":"venue"
},
  "geometry": {"coordinates":[-79.554647,36.109834],"type":"Point"}
}