{
  "type": "Feature",
  "properties": {
    "iso:country":"US",
    "sg:address":"1905 Smith Farm Rd",
    "sg:city":"Lincolnton",
    "sg:classifiers":[
        {
            "category":"Manufacturing",
            "subcategory":"Tools & Machinery",
            "type":"Manufacturing & Wholesale Goods"
        }
    ],
    "sg:phone":"+1 704 735 2025",
    "sg:postcode":"28092",
    "sg:province":"NC",
    "sg:tags":[
        "industrial",
        "mfg"
    ],
    "wof:name":"Ronald Downs Machine Shop",
    "wof:placetype":"venue"
},
  "geometry": {"coordinates":[-81.21409,35.440952],"type":"Point"}
}