{
  "type": "Feature",
  "properties": {
    "iso:country":"US",
    "sg:address":"5003 Edinborough Rd",
    "sg:city":"Greensboro",
    "sg:classifiers":[
        {
            "category":"Banks & Credit Unions",
            "subcategory":"Financial Services",
            "type":"Services"
        }
    ],
    "sg:phone":"+1 336 674 8939",
    "sg:postcode":"27406",
    "sg:province":"NC",
    "sg:tags":[
        "company",
        "holding"
    ],
    "wof:name":"Sand Hill Investment LLC",
    "wof:placetype":"venue"
},
  "geometry": {"coordinates":[-79.71402999999999,35.981658],"type":"Point"}
}