{
  "type": "Feature",
  "properties": {
    "iso:country":"US",
    "sg:address":"482 E Connecticut Ave",
    "sg:city":"Southern Pines",
    "sg:classifiers":[
        {
            "category":"Social Services",
            "type":"Services"
        }
    ],
    "sg:phone":"+1 910 695 7252",
    "sg:postcode":"28387",
    "sg:province":"NC",
    "wof:name":"Occoneechee Boy Scouts America",
    "wof:placetype":"venue"
},
  "geometry": {"coordinates":[-79.385369,35.170917],"type":"Point"}
}