{
  "type": "Feature",
  "properties": {
    "addr:full":"387 Alf Hoover Rd Lincolnton NC 28092",
    "addr:housenumber":"387",
    "addr:postcode":"28092",
    "addr:street":"Alf Hoover Rd",
    "iso:country":"US",
    "sg:address":"387 Alf Hoover Rd",
    "sg:city":"Lincolnton",
    "sg:classifiers":[
        {
            "category":"Building & Trades",
            "subcategory":"Electrical",
            "type":"Services"
        }
    ],
    "sg:phone":"+1 704 735 9272",
    "sg:postcode":"28092",
    "sg:province":"NC",
    "sg:tags":[
        "electrical",
        "contractor"
    ],
    "wof:name":"Aero Electrical Serv",
    "wof:placetype":"venue"
},
  "geometry": {"coordinates":[-81.337565,35.47946],"type":"Point"}
}