{
  "type": "Feature",
  "properties": {
    "addr:full":"1765 Mount Hope Church Rd Mc Leansville NC 27301",
    "addr:housenumber":"1765",
    "addr:postcode":"27301",
    "addr:street":"Mount Hope Church Rd",
    "iso:country":"US",
    "sg:address":"1765 Mount Hope Church Rd",
    "sg:city":"Mc Leansville",
    "sg:classifiers":[
        {
            "category":"Autos & Motor Vehicles",
            "subcategory":"Fuel & Gas Station",
            "type":"Retail Goods"
        }
    ],
    "sg:phone":"+1 336 697 9495",
    "sg:postcode":"27301",
    "sg:province":"NC",
    "sg:tags":[
        "oil"
    ],
    "wof:name":"Texaco",
    "wof:placetype":"venue"
},
  "geometry": {"coordinates":[-79.665706,36.061881],"type":"Point"}
}