{
  "type": "Feature",
  "properties": {
    "iso:country":"US",
    "sg:address":"466 Harper St",
    "sg:city":"Winston Salem",
    "sg:classifiers":[
        {
            "category":"Building & Trades",
            "subcategory":"Construction",
            "type":"Services"
        }
    ],
    "sg:phone":"+1 336 774 8768",
    "sg:postcode":"27104",
    "sg:province":"NC",
    "sg:tags":[
        "home",
        "improvement"
    ],
    "wof:name":"Richard Hancock Contracting",
    "wof:placetype":"venue"
},
  "geometry": {"coordinates":[-80.31016200000001,36.083817],"type":"Point"}
}