{
  "type": "Feature",
  "properties": {
    "addr:full":"2547 Manchester Dr Creedmoor NC 27525",
    "addr:housenumber":"2547",
    "addr:postcode":"27525",
    "addr:street":"Manchester Dr",
    "iso:country":"US",
    "sg:address":"2547 Manchester Dr",
    "sg:city":"Creedmoor",
    "sg:classifiers":[
        {
            "category":"Wholesale",
            "subcategory":"Electrical",
            "type":"Manufacturing & Wholesale Goods"
        }
    ],
    "sg:phone":"+1 919 528 2574",
    "sg:postcode":"27525",
    "sg:province":"NC",
    "sg:tags":[
        "generator"
    ],
    "wof:name":"E & W Electrical Contracting",
    "wof:placetype":"venue"
},
  "geometry": {"coordinates":[-78.566478,36.148451],"type":"Point"}
}