{
  "type": "Feature",
  "properties": {
    "addr:full":"3500 Lownwood Way Raleigh NC 27616",
    "addr:postcode":"3500;27616",
    "addr:street":"Lownwood Way",
    "iso:country":"US",
    "sg:address":"3500 Lownwood Way",
    "sg:city":"Raleigh",
    "sg:classifiers":[
        {
            "category":"Social Services",
            "type":"Services"
        }
    ],
    "sg:phone":"+1 919 266 5551",
    "sg:postcode":"27616",
    "sg:province":"NC",
    "sg:tags":[
        "worker"
    ],
    "wof:name":"Wesley Taylor Lcsw",
    "wof:placetype":"venue"
},
  "geometry": {"coordinates":[-78.512091,35.877266],"type":"Point"}
}