{
  "type": "Feature",
  "properties": {
    "addr:full":"722 Salem St Thomasville NC 27360",
    "addr:housenumber":"722",
    "addr:postcode":"27360",
    "addr:street":"Salem St",
    "iso:country":"US",
    "sg:address":"722 Salem St",
    "sg:city":"Thomasville",
    "sg:classifiers":[
        {
            "category":"Real Estate",
            "subcategory":"Real Estate Operator",
            "type":"Services"
        }
    ],
    "sg:phone":"+1 336 883 7035",
    "sg:postcode":"27360",
    "sg:province":"NC",
    "sg:tags":[
        "apartment"
    ],
    "wof:name":"Peter's Crossing Apartments",
    "wof:placetype":"venue"
},
  "geometry": {"coordinates":[-80.089423,35.893543],"type":"Point"}
}