{
  "type": "Feature",
  "properties": {
    "addr:full":"630 East St Pittsboro NC 27312",
    "addr:housenumber":"630",
    "addr:postcode":"27312",
    "addr:street":"East St",
    "iso:country":"US",
    "sg:address":"630 East St",
    "sg:city":"Pittsboro",
    "sg:classifiers":[
        {
            "category":"Banks & Credit Unions",
            "subcategory":"Investment Brokerage",
            "type":"Services"
        }
    ],
    "sg:phone":"+1 919 545 5669",
    "sg:postcode":"27312",
    "sg:province":"NC",
    "sg:tags":[
        "security"
    ],
    "wof:name":"Edward Jones Investments",
    "wof:placetype":"venue"
},
  "geometry": {"coordinates":[-79.166828,35.719912],"type":"Point"}
}