{
  "type": "Feature",
  "properties": {
    "addr:full":"602 Eagles Nest Rd Grimesland NC 27837",
    "addr:housenumber":"602",
    "addr:postcode":"27837",
    "addr:street":"Eagles Nest Rd",
    "iso:country":"US",
    "sg:address":"602 Eagles Nest Rd",
    "sg:city":"Grimesland",
    "sg:classifiers":[
        {
            "category":"Health Services",
            "subcategory":"Clinic",
            "type":"Services"
        }
    ],
    "sg:phone":"+1 252 752 2562",
    "sg:postcode":"27837",
    "sg:province":"NC",
    "sg:tags":[
        "specialty",
        "outpatient"
    ],
    "wof:name":"Carolina Rehab Services",
    "wof:placetype":"venue"
},
  "geometry": {"coordinates":[-77.24710899999999,35.586547],"type":"Point"}
}