{
  "type": "Feature",
  "properties": {
    "addr:full":"100 N Tryon St Charlotte NC 28202",
    "addr:housenumber":"100",
    "addr:postcode":"28202",
    "addr:street":"N Tryon St",
    "iso:country":"US",
    "sg:address":"100 N Tryon St",
    "sg:city":"Charlotte",
    "sg:classifiers":[
        {
            "category":"Banks & Credit Unions",
            "subcategory":"Financial Services",
            "type":"Services"
        }
    ],
    "sg:phone":"+1 704 386 5681",
    "sg:postcode":"28202",
    "sg:province":"NC",
    "sg:tags":[
        "company",
        "holding"
    ],
    "sg:website":"www.bankofamerica.com",
    "wof:name":"Bank Of America Corp",
    "wof:placetype":"venue"
},
  "geometry": {"coordinates":[-80.841945,35.227995],"type":"Point"}
}