{
  "type": "Feature",
  "properties": {
    "iso:country":"US",
    "sg:address":"2209 Park Rd",
    "sg:city":"Charlotte",
    "sg:classifiers":[
        {
            "category":"Professional",
            "subcategory":"Art Services",
            "type":"Services"
        }
    ],
    "sg:phone":"+1   ",
    "sg:postcode":"28203",
    "sg:province":"NC",
    "sg:tags":[
        "graphic",
        "designer"
    ],
    "wof:name":"Peter McRae Design LLC",
    "wof:placetype":"venue"
},
  "geometry": {"coordinates":[-80.851911,35.199094],"type":"Point"}
}