{
  "type": "Feature",
  "properties": {
    "addr:full":"748 E Chatham St Cary NC 27511",
    "addr:housenumber":"748",
    "addr:postcode":"27511",
    "addr:street":"E Chatham St",
    "iso:country":"US",
    "sg:address":"748 E Chatham St",
    "sg:city":"Cary",
    "sg:classifiers":[
        {
            "category":"Restaurant",
            "type":"Food & Drink"
        }
    ],
    "sg:menulink":"http://www.allmenus.com/nc/cary/158075-suchi-indian-cuisine/menu/",
    "sg:phone":"+1 919 466 7273",
    "sg:postcode":"27511",
    "sg:province":"NC",
    "sg:tags":[
        "indian",
        "asian"
    ],
    "wof:name":"Suchi Indian Cuisine",
    "wof:placetype":"venue"
},
  "geometry": {"coordinates":[-78.760244,35.791555],"type":"Point"}
}