{
  "type": "Feature",
  "properties": {
    "iso:country":"US",
    "sg:address":"103 E College St",
    "sg:city":"Salemburg",
    "sg:classifiers":[
        {
            "category":"Shopping",
            "type":"Retail Goods"
        }
    ],
    "sg:phone":"+1 910 525 5010",
    "sg:postcode":"28385",
    "sg:province":"NC",
    "sg:tags":[
        "enforcement",
        "law",
        "supply"
    ],
    "wof:name":"Plea Bargain",
    "wof:placetype":"venue"
},
  "geometry": {"coordinates":[-78.50297500000001,35.015455],"type":"Point"}
}