{
  "type": "Feature",
  "properties": {
    "addr:full":"6147 Pigeon Rd Canton NC 28716",
    "addr:housenumber":"6147",
    "addr:postcode":"28716",
    "addr:street":"Pigeon Rd",
    "iso:country":"US",
    "sg:address":"6147 Pigeon Rd",
    "sg:city":"Canton",
    "sg:classifiers":[
        {
            "category":"Food & Beverages",
            "subcategory":"Groceries & Convenience Stores",
            "type":"Retail Goods"
        }
    ],
    "sg:phone":"+1 828 648 6672",
    "sg:postcode":"28716",
    "sg:province":"NC",
    "wof:name":"Single Stop",
    "wof:placetype":"venue"
},
  "geometry": {"coordinates":[-82.88854600000001,35.471314],"type":"Point"}
}