{
  "type": "Feature",
  "properties": {
    "addr:full":"1900 S Main St Lexington NC 27292",
    "addr:housenumber":"1900",
    "addr:postcode":"27292",
    "addr:street":"S Main St",
    "iso:country":"US",
    "sg:address":"1900 S Main St",
    "sg:city":"Lexington",
    "sg:classifiers":[
        {
            "category":"Utilities",
            "subcategory":"Electric",
            "type":"Services"
        }
    ],
    "sg:phone":"+1 336 249 3131",
    "sg:postcode":"27292",
    "sg:province":"NC",
    "sg:tags":[
        "company"
    ],
    "wof:name":"Energyunited",
    "wof:placetype":"venue"
},
  "geometry": {"coordinates":[-80.276774,35.805986],"type":"Point"}
}