{
  "type": "Feature",
  "properties": {
    "addr:full":"5100 Minnow Rd Greensboro NC 27405",
    "addr:housenumber":"5100",
    "addr:postcode":"27405",
    "addr:street":"Minnow Rd",
    "iso:country":"US",
    "sg:address":"5100 Minnow Rd",
    "sg:city":"Greensboro",
    "sg:classifiers":[
        {
            "category":"Organizations",
            "subcategory":"Religious Organization",
            "type":"Services"
        }
    ],
    "sg:phone":"+1   ",
    "sg:postcode":"27405",
    "sg:province":"NC",
    "wof:name":"Purity For Christ Bptst Church",
    "wof:placetype":"venue"
},
  "geometry": {"coordinates":[-79.764044,36.147019],"type":"Point"}
}