{
  "type": "Feature",
  "properties": {
    "addr:full":"2742 Henderson Mill Rd Morganton NC 28655",
    "addr:housenumber":"2742",
    "addr:postcode":"28655",
    "addr:street":"Henderson Mill Rd",
    "iso:country":"US",
    "sg:address":"2742 Henderson Mill Rd",
    "sg:city":"Morganton",
    "sg:classifiers":[
        {
            "category":"Professional",
            "subcategory":"Secretarial Services",
            "type":"Services"
        }
    ],
    "sg:phone":"+1   ",
    "sg:postcode":"28655",
    "sg:province":"NC",
    "sg:tags":[
        "reporting"
    ],
    "wof:name":"Hamilton Covelli Crt Reporting",
    "wof:placetype":"venue"
},
  "geometry": {"coordinates":[-81.76102400000001,35.81372],"type":"Point"}
}