{
  "type": "Feature",
  "properties": {
    "iso:country":"US",
    "sg:address":"513 George St",
    "sg:city":"New Bern",
    "sg:classifiers":[
        {
            "category":"Insurance",
            "subcategory":"Insurance Agent",
            "type":"Services"
        }
    ],
    "sg:phone":"+1 252 633 9830",
    "sg:postcode":"28560",
    "sg:province":"NC",
    "wof:name":"Reed & Reed Insurance",
    "wof:placetype":"venue"
},
  "geometry": {"coordinates":[-77.04443499999999,35.109846],"type":"Point"}
}