{
  "type": "Feature",
  "properties": {
    "addr:full":"201 C St Cherryville NC 28021",
    "addr:housenumber":"201",
    "addr:postcode":"28021",
    "addr:street":"C St",
    "iso:country":"US",
    "sg:address":"201 C St",
    "sg:city":"Cherryville",
    "sg:classifiers":[
        {
            "category":"Autos & Motor Vehicles",
            "subcategory":"Auto Supplies",
            "type":"Retail Goods"
        }
    ],
    "sg:phone":"+1 704 435 6264",
    "sg:postcode":"28021",
    "sg:province":"NC",
    "wof:name":"Russell Jones Tires",
    "wof:placetype":"venue"
},
  "geometry": {"coordinates":[-81.38475,35.378539],"type":"Point"}
}