{
  "type": "Feature",
  "properties": {
    "addr:full":"635 Pressley Rd Charlotte NC 28217",
    "addr:housenumber":"635",
    "addr:postcode":"28217",
    "addr:street":"Pressley Rd",
    "iso:country":"US",
    "sg:address":"635 Pressley Rd",
    "sg:city":"Charlotte",
    "sg:classifiers":[
        {
            "category":"Shopping",
            "subcategory":"Gifts & Souvenirs",
            "type":"Retail Goods"
        }
    ],
    "sg:phone":"+1 704 521 8580",
    "sg:postcode":"28217",
    "sg:province":"NC",
    "sg:tags":[
        "basket",
        "parcel"
    ],
    "sg:website":"www.greatbasket.com",
    "wof:name":"Great American Gift Baskets",
    "wof:placetype":"venue"
},
  "geometry": {"coordinates":[-80.892661,35.188927],"type":"Point"}
}