{
  "type": "Feature",
  "properties": {
    "addr:full":"100 N Berkeley Blvd Goldsboro NC 27534",
    "addr:housenumber":"100",
    "addr:postcode":"27534",
    "addr:street":"N Berkeley Blvd",
    "iso:country":"US",
    "sg:address":"100 N Berkeley Blvd",
    "sg:city":"Goldsboro",
    "sg:classifiers":[
        {
            "category":"Restaurant",
            "type":"Food & Drink"
        }
    ],
    "sg:menulink":"http://www.allmenus.com/nc/goldsboro/153613-western-sizzlin/menu/",
    "sg:phone":"+1 919 778 7444",
    "sg:postcode":"27534",
    "sg:province":"NC",
    "sg:tags":[
        "american",
        "steakhouse"
    ],
    "wof:name":"Western Sizzlin",
    "wof:placetype":"venue"
},
  "geometry": {"coordinates":[-77.953014,35.371311],"type":"Point"}
}