{
  "type": "Feature",
  "properties": {
    "addr:full":"503 Lakeside Dr Garner NC 27529",
    "addr:housenumber":"503",
    "addr:postcode":"27529",
    "addr:street":"Lakeside Dr",
    "iso:country":"US",
    "sg:address":"503 Lakeside Dr",
    "sg:city":"Garner",
    "sg:classifiers":[
        {
            "category":"Social Services",
            "type":"Services"
        }
    ],
    "sg:phone":"+1   ",
    "sg:postcode":"27529",
    "sg:province":"NC",
    "wof:name":"Presbytrian Per Fmly Counselin",
    "wof:placetype":"venue"
},
  "geometry": {"coordinates":[-78.610888,35.698328],"type":"Point"}
}