{
  "type": "Feature",
  "properties": {
    "iso:country":"US",
    "sg:address":"4612 Main St",
    "sg:city":"South Brunswick",
    "sg:classifiers":[
        {
            "category":"Food & Beverages",
            "subcategory":"Groceries & Convenience Stores",
            "type":"Retail Goods"
        }
    ],
    "sg:phone":"+1 910 754 8620",
    "sg:postcode":"28470",
    "sg:province":"NC",
    "sg:tags":[
        "car",
        "station",
        "gas",
        "wash"
    ],
    "wof:name":"Ward's One Stop",
    "wof:placetype":"venue"
},
  "geometry": {"coordinates":[-78.37878499999999,33.977684],"type":"Point"}
}