{
  "type": "Feature",
  "properties": {
    "addr:full":"1648 N Market Dr Raleigh NC 27609",
    "addr:housenumber":"1648",
    "addr:postcode":"27609",
    "addr:street":"N Market Dr",
    "iso:country":"US",
    "sg:address":"1648 N Market Dr",
    "sg:city":"Raleigh",
    "sg:classifiers":[
        {
            "category":"Shopping",
            "subcategory":"Clothing, Apparel, & Fashions",
            "type":"Retail Goods"
        }
    ],
    "sg:phone":"+1 919 875 1391",
    "sg:postcode":"27609",
    "sg:province":"NC",
    "wof:name":"Nowells Clothing",
    "wof:placetype":"venue"
},
  "geometry": {"coordinates":[-78.60908000000001,35.840796],"type":"Point"}
}