{
  "type": "Feature",
  "properties": {
    "addr:full":"2050 Rosebriar Ln Fuquay Varina NC 27526",
    "addr:housenumber":"2050",
    "addr:postcode":"27526",
    "addr:street":"Rosebriar Ln",
    "iso:country":"US",
    "sg:address":"2050 Rosebriar Ln",
    "sg:city":"Fuquay Varina",
    "sg:classifiers":[
        {
            "category":"Shopping",
            "subcategory":"Discount & Variety Stores",
            "type":"Retail Goods"
        },
        {
            "category":"Real Estate",
            "subcategory":"Real Estate Agent",
            "type":"Services"
        }
    ],
    "sg:phone":"+1 919 577 2043",
    "sg:postcode":"27526",
    "sg:province":"NC",
    "sg:tags":[
        "merchandise",
        "general"
    ],
    "wof:name":"Ballentine Sales Office",
    "wof:placetype":"venue"
},
  "geometry": {"coordinates":[-78.772807,35.609908],"type":"Point"}
}