{
  "type": "Feature",
  "properties": {
    "addr:full":"4730 Dominion Rd Fayetteville NC 28306",
    "addr:housenumber":"4730",
    "addr:postcode":"28306",
    "addr:street":"Dominion Rd",
    "iso:country":"US",
    "sg:address":"4730 Dominion Rd",
    "sg:city":"Fayetteville",
    "sg:classifiers":[
        {
            "category":"Shopping",
            "type":"Retail Goods"
        }
    ],
    "sg:phone":"+1 910 527 7013",
    "sg:postcode":"28306",
    "sg:province":"NC",
    "sg:tags":[
        "merchandise"
    ],
    "wof:name":"Home Interiors and More",
    "wof:placetype":"venue"
},
  "geometry": {"coordinates":[-78.95035,35.007964],"type":"Point"}
}