{
  "type": "Feature",
  "properties": {
    "iso:country":"US",
    "sg:address":"1433 Wagon Ct",
    "sg:city":"Wilmington",
    "sg:classifiers":[
        {
            "category":"Building & Trades",
            "subcategory":"Cleaning & Sanitation",
            "type":"Services"
        }
    ],
    "sg:phone":"+1 910 395 5092",
    "sg:postcode":"28412",
    "sg:province":"NC",
    "sg:tags":[
        "janitor"
    ],
    "wof:name":"A-New Cleaning Co",
    "wof:placetype":"venue"
},
  "geometry": {"coordinates":[-77.91197099999999,34.173483],"type":"Point"}
}