{
  "type": "Feature",
  "properties": {
    "addr:full":"12820 York Rd Charlotte NC 28273",
    "addr:housenumber":"12820",
    "addr:postcode":"28273",
    "addr:street":"York Rd",
    "iso:country":"US",
    "sg:address":"12820 York Rd",
    "sg:city":"Charlotte",
    "sg:classifiers":[
        {
            "category":"Restaurant",
            "type":"Food & Drink"
        }
    ],
    "sg:menulink":"http://www.allmenus.com/nc/charlotte/47700-five-guys/menu/",
    "sg:phone":"+1 704 587 9204",
    "sg:postcode":"28273",
    "sg:province":"NC",
    "sg:tags":[
        "burger",
        "american",
        "hot",
        "dog"
    ],
    "wof:name":"Five Guys Burgers & Fries",
    "wof:placetype":"venue"
},
  "geometry": {"coordinates":[-80.986075,35.104099],"type":"Point"}
}