{
  "type": "Feature",
  "properties": {
    "iso:country":"US",
    "sg:address":"3613 Cape Center Dr",
    "sg:city":"Fayetteville",
    "sg:classifiers":[
        {
            "category":"Health Services",
            "subcategory":"Doctor",
            "type":"Services"
        }
    ],
    "sg:phone":"+1   ",
    "sg:postcode":"28304",
    "sg:province":"NC",
    "wof:name":"Fayetteville Center",
    "wof:placetype":"venue"
},
  "geometry": {"coordinates":[-78.935265,35.036472],"type":"Point"}
}