{
  "type": "Feature",
  "properties": {
    "iso:country":"US",
    "sg:address":"6541 Denver Industrial Park Rd",
    "sg:city":"Denver",
    "sg:classifiers":[
        {
            "category":"Building & Trades",
            "subcategory":"Construction",
            "type":"Services"
        }
    ],
    "sg:phone":"+1 704 483 2621",
    "sg:postcode":"28037",
    "sg:province":"NC",
    "sg:tags":[
        "siding",
        "contractor"
    ],
    "wof:name":"Flynn's Aluminum Inc",
    "wof:placetype":"venue"
},
  "geometry": {"coordinates":[-81.03909299999999,35.541525],"type":"Point"}
}