{
  "type": "Feature",
  "properties": {
    "addr:full":"1000 Truckstop Rd Kenly NC 27542",
    "addr:housenumber":"1000",
    "addr:postcode":"27542",
    "addr:street":"Truckstop Rd",
    "iso:country":"US",
    "sg:address":"1000 Truckstop Rd",
    "sg:city":"Kenly",
    "sg:classifiers":[
        {
            "category":"Restaurant",
            "type":"Food & Drink"
        }
    ],
    "sg:menulink":"http://www.allmenus.com/nc/beulah/158841-arbys/menu/",
    "sg:phone":"+1 919 284 5749",
    "sg:postcode":"27542",
    "sg:province":"NC",
    "sg:tags":[
        "burger",
        "american"
    ],
    "wof:name":"Arby's",
    "wof:placetype":"venue"
},
  "geometry": {"coordinates":[-78.148678,35.583248],"type":"Point"}
}