{
  "type": "Feature",
  "properties": {
    "iso:country":"US",
    "sg:address":"2130 New Garden Rd",
    "sg:city":"Greensboro",
    "sg:classifiers":[
        {
            "category":"Building & Trades",
            "subcategory":"Equipment Rental",
            "type":"Services"
        }
    ],
    "sg:phone":"+1   ",
    "sg:postcode":"27410",
    "sg:province":"NC",
    "wof:name":"Players Choice",
    "wof:placetype":"venue"
},
  "geometry": {"coordinates":[-79.85509999999999,36.129665],"type":"Point"}
}