{
  "type": "Feature",
  "properties": {
    "iso:country":"US",
    "sg:address":"4335 Stuart Andrew Blvd",
    "sg:city":"Charlotte",
    "sg:classifiers":[
        {
            "category":"Professional",
            "type":"Services"
        }
    ],
    "sg:phone":"+1 704 561 0012",
    "sg:postcode":"28217",
    "sg:province":"NC",
    "sg:tags":[
        "establishment"
    ],
    "wof:name":"Edsoftware",
    "wof:placetype":"venue"
},
  "geometry": {"coordinates":[-80.89011499999999,35.186709],"type":"Point"}
}