{
  "type": "Feature",
  "properties": {
    "addr:full":"10660 S Tryon St Charlotte NC 28273",
    "addr:housenumber":"10660",
    "addr:postcode":"28273",
    "addr:street":"S Tryon St",
    "iso:country":"US",
    "sg:address":"10660 S Tryon St",
    "sg:city":"Charlotte",
    "sg:classifiers":[
        {
            "category":"Freight",
            "type":"Transportation"
        }
    ],
    "sg:phone":"+1 704 504 1600",
    "sg:postcode":"28273",
    "sg:province":"NC",
    "sg:tags":[
        "mover"
    ],
    "wof:name":"A Plus Movers & Storage",
    "wof:placetype":"venue"
},
  "geometry": {"coordinates":[-80.955208,35.118599],"type":"Point"}
}