{
  "type": "Feature",
  "properties": {
    "addr:full":"8001 Leabourne Rd Colfax NC 27235",
    "addr:housenumber":"8001",
    "addr:postcode":"27235",
    "addr:street":"Leabourne Rd",
    "iso:country":"US",
    "sg:address":"8001 Leabourne Rd",
    "sg:city":"Colfax",
    "sg:classifiers":[
        {
            "category":"Organizations",
            "subcategory":"Non-profit Organization",
            "type":"Services"
        }
    ],
    "sg:phone":"+1 336 931 1424",
    "sg:postcode":"27235",
    "sg:province":"NC",
    "sg:tags":[
        "disability"
    ],
    "wof:name":"Horsepower Therapeutic Lrnng",
    "wof:placetype":"venue"
},
  "geometry": {"coordinates":[-79.97571499999999,36.135348],"type":"Point"}
}