{
  "type": "Feature",
  "properties": {
    "addr:full":"1839 E Garrison Blvd Gastonia NC 28054",
    "addr:housenumber":"1839",
    "addr:postcode":"28054",
    "addr:street":"E Garrison Blvd",
    "iso:country":"US",
    "sg:address":"1839 E Garrison Blvd",
    "sg:city":"Gastonia",
    "sg:classifiers":[
        {
            "category":"Health Services",
            "subcategory":"Doctor",
            "type":"Services"
        }
    ],
    "sg:phone":"+1 704 864 2685",
    "sg:postcode":"28054",
    "sg:province":"NC",
    "sg:tags":[
        "physician",
        "surgeon"
    ],
    "wof:name":"Gastonia Pediatric Assoc",
    "wof:placetype":"venue"
},
  "geometry": {"coordinates":[-81.150218,35.253148],"type":"Point"}
}