{
  "type": "Feature",
  "properties": {
    "addr:full":"32 20th Ave NW Hickory NC 28601",
    "addr:housenumber":"32",
    "addr:postcode":"28601",
    "addr:street":"20Th Ave Nw",
    "iso:country":"US",
    "sg:address":"32 20th Ave NW",
    "sg:city":"Hickory",
    "sg:classifiers":[
        {
            "category":"Building & Trades",
            "subcategory":"Construction",
            "type":"Services"
        }
    ],
    "sg:phone":"+1 828 324 8953",
    "sg:postcode":"28601",
    "sg:province":"NC",
    "sg:tags":[
        "fiber",
        "optics"
    ],
    "wof:name":"Lost Enterprises Inc",
    "wof:placetype":"venue"
},
  "geometry": {"coordinates":[-81.338483,35.760776],"type":"Point"}
}