{
  "type": "Feature",
  "properties": {
    "addr:full":"640 S Van Buren Rd Eden NC 27288",
    "addr:housenumber":"640",
    "addr:postcode":"27288",
    "addr:street":"S Van Buren Rd",
    "iso:country":"US",
    "sg:address":"640 S Van Buren Rd",
    "sg:city":"Eden",
    "sg:classifiers":[
        {
            "category":"Personal",
            "subcategory":"Beauty Salon",
            "type":"Services"
        }
    ],
    "sg:phone":"+1 336 627 4700",
    "sg:postcode":"27288",
    "sg:province":"NC",
    "sg:website":"www.greatclips.com",
    "wof:name":"Great Clips",
    "wof:placetype":"venue"
},
  "geometry": {"coordinates":[-79.740511,36.493165],"type":"Point"}
}