{
  "type": "Feature",
  "properties": {
    "addr:full":"2550 N Church St Rocky Mount NC 27804",
    "addr:housenumber":"2550",
    "addr:postcode":"27804",
    "addr:street":"N Church St",
    "iso:country":"US",
    "sg:address":"2550 N Church St",
    "sg:city":"Rocky Mount",
    "sg:classifiers":[
        {
            "category":"Wholesale",
            "subcategory":"Motor Vehicles",
            "type":"Manufacturing & Wholesale Goods"
        }
    ],
    "sg:phone":"+1 252 446 7166",
    "sg:postcode":"27804",
    "sg:province":"NC",
    "wof:name":"Youngs Truck Center Inc",
    "wof:placetype":"venue"
},
  "geometry": {"coordinates":[-77.78357699999999,35.979409],"type":"Point"}
}