{
  "type": "Feature",
  "properties": {
    "addr:full":"3001 Whitson Rd Gastonia NC 28054",
    "addr:housenumber":"3001",
    "addr:postcode":"28054",
    "addr:street":"Whitson Rd",
    "iso:country":"US",
    "sg:address":"3001 Whitson Rd",
    "sg:city":"Gastonia",
    "sg:classifiers":[
        {
            "category":"Professional",
            "subcategory":"Computer Services",
            "type":"Services"
        }
    ],
    "sg:phone":"+1 704 867 5249",
    "sg:postcode":"28054",
    "sg:province":"NC",
    "wof:name":"Data Bee Computer Svc",
    "wof:placetype":"venue"
},
  "geometry": {"coordinates":[-81.129088,35.255919],"type":"Point"}
}