{
  "type": "Feature",
  "properties": {
    "iso:country":"US",
    "sg:address":"15813 Agincourt Dr",
    "sg:city":"Huntersville",
    "sg:classifiers":[
        {
            "category":"Building & Trades",
            "subcategory":"Landscaping Services",
            "type":"Services"
        }
    ],
    "sg:phone":"+1 704 894 9658",
    "sg:postcode":"28078",
    "sg:province":"NC",
    "sg:tags":[
        "supply"
    ],
    "wof:name":"C & C Landscaping",
    "wof:placetype":"venue"
},
  "geometry": {"coordinates":[-80.887064,35.429508],"type":"Point"}
}