{
  "type": "Feature",
  "properties": {
    "addr:full":"2465 Mecklenburg Ave Charlotte NC 28205",
    "addr:housenumber":"2465",
    "addr:postcode":"28205",
    "addr:street":"Mecklenburg Ave",
    "iso:country":"US",
    "sg:address":"2465 Mecklenburg Ave",
    "sg:city":"Charlotte",
    "sg:classifiers":[
        {
            "category":"Shopping",
            "subcategory":"Bicycles & Sporting Goods",
            "type":"Retail Goods"
        },
        {
            "category":"Organizations",
            "subcategory":"Community Association",
            "type":"Services"
        }
    ],
    "sg:phone":"+1 704 334 0836",
    "sg:postcode":"28205",
    "sg:province":"NC",
    "sg:tags":[
        "club",
        "equipment",
        "golf"
    ],
    "sg:website":"www.charlottecountryclub.org",
    "wof:name":"Charlotte Country Club Pro Sp",
    "wof:placetype":"venue"
},
  "geometry": {"coordinates":[-80.79442299999999,35.229464],"type":"Point"}
}