{
  "type": "Feature",
  "properties": {
    "addr:full":"9612 Berryville Ct Raleigh NC 27617",
    "addr:housenumber":"9612",
    "addr:postcode":"27617",
    "addr:street":"Berryville Ct",
    "iso:country":"US",
    "sg:address":"9612 Berryville Ct",
    "sg:city":"Raleigh",
    "sg:classifiers":[
        {
            "category":"Banks & Credit Unions",
            "subcategory":"Financial Services",
            "type":"Services"
        }
    ],
    "sg:phone":"+1 919 848 0620",
    "sg:postcode":"27617",
    "sg:province":"NC",
    "sg:tags":[
        "investor"
    ],
    "wof:name":"Goldberg Investment Group LLC",
    "wof:placetype":"venue"
},
  "geometry": {"coordinates":[-78.739467,35.915466],"type":"Point"}
}