{
  "type": "Feature",
  "properties": {
    "iso:country":"US",
    "sg:address":"1741 US Hwy 117 N",
    "sg:city":"Burgaw",
    "sg:classifiers":[
        {
            "category":"Building & Trades",
            "subcategory":"Construction",
            "type":"Services"
        }
    ],
    "sg:phone":"+1 910 259 1757",
    "sg:postcode":"28425",
    "sg:province":"NC",
    "sg:tags":[
        "residential"
    ],
    "wof:name":"Cross Roads Construction Inc",
    "wof:placetype":"venue"
},
  "geometry": {"coordinates":[-77.924865,34.582308],"type":"Point"}
}