{
  "type": "Feature",
  "properties": {
    "iso:country":"US",
    "sg:address":"5142 Dysartsville Rd",
    "sg:city":"Morganton",
    "sg:classifiers":[
        {
            "category":"Personal",
            "subcategory":"Beauty Salon",
            "type":"Services"
        }
    ],
    "sg:phone":"+1 828 584 7017",
    "sg:postcode":"28655",
    "sg:province":"NC",
    "sg:tags":[
        "shop"
    ],
    "wof:name":"Divine Design",
    "wof:placetype":"venue"
},
  "geometry": {"coordinates":[-81.841306,35.662671],"type":"Point"}
}