{
  "type": "Feature",
  "properties": {
    "addr:full":"6910 Fayetteville Rd Durham NC 27713",
    "addr:housenumber":"6910",
    "addr:postcode":"27713",
    "addr:street":"Fayetteville Rd",
    "iso:country":"US",
    "sg:address":"6910 Fayetteville Rd",
    "sg:city":"Durham",
    "sg:classifiers":[
        {
            "category":"Bakery",
            "type":"Food & Drink"
        }
    ],
    "sg:menulink":"http://www.allmenus.com/nc/triangle/220115-auntie-annes-pretzels/menu/",
    "sg:phone":"+1 919 806 1886",
    "sg:postcode":"27713",
    "sg:province":"NC",
    "sg:tags":[
        "american",
        "pastry"
    ],
    "wof:name":"Auntie Anne's Pretzels",
    "wof:placetype":"venue"
},
  "geometry": {"coordinates":[-78.93948,35.902321],"type":"Point"}
}