{
  "type": "Feature",
  "properties": {
    "addr:full":"5818 Fisher Rd Fayetteville NC 28304",
    "addr:housenumber":"5818",
    "addr:postcode":"28304",
    "addr:street":"Fisher Rd",
    "iso:country":"US",
    "sg:address":"5818 Fisher Rd",
    "sg:city":"Fayetteville",
    "sg:classifiers":[
        {
            "category":"Professional",
            "type":"Services"
        }
    ],
    "sg:phone":"+1   ",
    "sg:postcode":"28304",
    "sg:province":"NC",
    "wof:name":"Reel Communication Inc",
    "wof:placetype":"venue"
},
  "geometry": {"coordinates":[-78.994411,35.003655],"type":"Point"}
}