{
  "type": "Feature",
  "properties": {
    "iso:country":"US",
    "sg:address":"2813 Susan Gray Ct",
    "sg:city":"Kinston",
    "sg:classifiers":[
        {
            "category":"Building & Trades",
            "subcategory":"Construction",
            "type":"Services"
        }
    ],
    "sg:phone":"+1 252 523 0911",
    "sg:postcode":"28504",
    "sg:province":"NC",
    "sg:tags":[
        "house",
        "general",
        "contractor"
    ],
    "wof:name":"C M Campbell Assoc Inc",
    "wof:placetype":"venue"
},
  "geometry": {"coordinates":[-77.69869300000001,35.298352],"type":"Point"}
}