{
  "type": "Feature",
  "properties": {
    "addr:full":"260 Kemper Rd Shelby NC 28152",
    "addr:housenumber":"260",
    "addr:postcode":"28152",
    "addr:street":"Kemper Rd",
    "iso:country":"US",
    "sg:address":"260 Kemper Rd",
    "sg:city":"Shelby",
    "sg:classifiers":[
        {
            "category":"Government",
            "subcategory":"Jail",
            "type":"Public Place"
        }
    ],
    "sg:phone":"+1 704 480 5428",
    "sg:postcode":"28152",
    "sg:province":"NC",
    "sg:tags":[
        "govt",
        "state",
        "institution"
    ],
    "sg:website":"www.doc.state.nc.us",
    "wof:name":"Corrections Dept",
    "wof:placetype":"venue"
},
  "geometry": {"coordinates":[-81.483766,35.283349],"type":"Point"}
}