{
  "type": "Feature",
  "properties": {
    "iso:country":"US",
    "sg:address":"2405 Paula St",
    "sg:city":"Raleigh",
    "sg:classifiers":[
        {
            "category":"Arts & Performance",
            "subcategory":"Theater",
            "type":"Entertainment"
        }
    ],
    "sg:phone":"+1 919 755 0399",
    "sg:postcode":"27608",
    "sg:province":"NC",
    "sg:tags":[
        "bureau"
    ],
    "wof:name":"World's Mine Entertainment",
    "wof:placetype":"venue"
},
  "geometry": {"coordinates":[-78.62499099999999,35.81477],"type":"Point"}
}