{
  "type": "Feature",
  "properties": {
    "addr:full":"5739 Old Monroe Rd Indian Trail NC 28079",
    "addr:housenumber":"5739",
    "addr:postcode":"28079",
    "addr:street":"Old Monroe Rd",
    "iso:country":"US",
    "sg:address":"5739 Old Monroe Rd",
    "sg:city":"Indian Trail",
    "sg:classifiers":[
        {
            "category":"Organizations",
            "subcategory":"Religious Organization",
            "type":"Services"
        }
    ],
    "sg:phone":"+1 704 821 9592",
    "sg:postcode":"28079",
    "sg:province":"NC",
    "sg:tags":[
        "church"
    ],
    "wof:name":"Grace Baptist Church",
    "wof:placetype":"venue"
},
  "geometry": {"coordinates":[-80.66108199999999,35.058621],"type":"Point"}
}