{
  "type": "Feature",
  "properties": {
    "iso:country":"US",
    "sg:address":"307 Jackson St",
    "sg:city":"Jamestown",
    "sg:classifiers":[
        {
            "category":"Professional",
            "type":"Services"
        }
    ],
    "sg:phone":"+1 336 454 4099",
    "sg:postcode":"27282",
    "sg:province":"NC",
    "wof:name":"Maryetta Professional Svc",
    "wof:placetype":"venue"
},
  "geometry": {"coordinates":[-79.930043,35.994298],"type":"Point"}
}