{
  "type": "Feature",
  "properties": {
    "iso:country":"US",
    "sg:address":"6120 Brookshire Blvd",
    "sg:city":"Charlotte",
    "sg:classifiers":[
        {
            "category":"Professional",
            "subcategory":"Research",
            "type":"Services"
        }
    ],
    "sg:phone":"+1   ",
    "sg:postcode":"28216",
    "sg:province":"NC",
    "sg:tags":[
        "equipment",
        "surveying"
    ],
    "wof:name":"Sur Con Products",
    "wof:placetype":"venue"
},
  "geometry": {"coordinates":[-80.909108,35.288023],"type":"Point"}
}