{
  "type": "Feature",
  "properties": {
    "iso:country":"US",
    "sg:address":"820 Gordon Woods Rd",
    "sg:city":"Wilmington",
    "sg:classifiers":[
        {
            "category":"Professional",
            "subcategory":"Business Services",
            "type":"Services"
        }
    ],
    "sg:phone":"+1 910 313 0393",
    "sg:postcode":"28411",
    "sg:province":"NC",
    "sg:tags":[
        "event"
    ],
    "wof:name":"Signature Special Events Svc",
    "wof:placetype":"venue"
},
  "geometry": {"coordinates":[-77.850633,34.276626],"type":"Point"}
}