{
  "type": "Feature",
  "properties": {
    "iso:country":"US",
    "sg:address":"6727 Bealgray Rd",
    "sg:city":"Kannapolis",
    "sg:classifiers":[
        {
            "category":"Building & Trades",
            "subcategory":"Plumbing",
            "type":"Services"
        }
    ],
    "sg:phone":"+1 704 932 9492",
    "sg:postcode":"28081",
    "sg:province":"NC",
    "sg:tags":[
        "contractor"
    ],
    "wof:name":"Custom Air Design",
    "wof:placetype":"venue"
},
  "geometry": {"coordinates":[-80.69108,35.489461],"type":"Point"}
}