{
  "type": "Feature",
  "properties": {
    "addr:full":"412 Ann St Wilmington NC 28401",
    "addr:housenumber":"412",
    "addr:postcode":"28401",
    "addr:street":"Ann St",
    "iso:country":"US",
    "sg:address":"412 Ann St",
    "sg:city":"Wilmington",
    "sg:classifiers":[
        {
            "category":"Health Services",
            "subcategory":"Clinic",
            "type":"Services"
        }
    ],
    "sg:phone":"+1 910 251 2120",
    "sg:postcode":"28401",
    "sg:province":"NC",
    "sg:tags":[
        "information",
        "program",
        "referral"
    ],
    "wof:name":"CARE/Coastal Aids Resource",
    "wof:placetype":"venue"
},
  "geometry": {"coordinates":[-77.94305900000001,34.231924],"type":"Point"}
}