{
  "type": "Feature",
  "properties": {
    "iso:country":"US",
    "sg:address":"559 Hastings Hill Rd",
    "sg:city":"Kernersville",
    "sg:classifiers":[
        {
            "category":"Cinema",
            "subcategory":"Movie Rental",
            "type":"Entertainment"
        }
    ],
    "sg:phone":"+1 336 785 3359",
    "sg:postcode":"27284",
    "sg:province":"NC",
    "sg:tags":[
        "video",
        "tape"
    ],
    "wof:name":"Video Works of Kernersville",
    "wof:placetype":"venue"
},
  "geometry": {"coordinates":[-80.11998,36.1066],"type":"Point"}
}