{
  "type": "Feature",
  "properties": {
    "iso:country":"US",
    "sg:address":"1334 N Post Rd",
    "sg:city":"Shelby",
    "sg:classifiers":[
        {
            "category":"Manufacturing",
            "subcategory":"Retail Goods",
            "type":"Manufacturing & Wholesale Goods"
        }
    ],
    "sg:phone":"+1 704 480 9390",
    "sg:postcode":"28150",
    "sg:province":"NC",
    "sg:tags":[
        "manufacturer"
    ],
    "wof:name":"Classic Lamp Designs Inc",
    "wof:placetype":"venue"
},
  "geometry": {"coordinates":[-81.495718,35.323219],"type":"Point"}
}