{
  "type": "Feature",
  "properties": {
    "addr:full":"740 Cornelius St Hillsborough NC 27278",
    "addr:housenumber":"740",
    "addr:postcode":"27278",
    "addr:street":"Cornelius St",
    "iso:country":"US",
    "sg:address":"740 Cornelius St",
    "sg:city":"Hillsborough",
    "sg:classifiers":[
        {
            "category":"Travel",
            "subcategory":"Hotels & Motels",
            "type":"Entertainment"
        }
    ],
    "sg:phone":"+1 919 732 2008",
    "sg:postcode":"27278",
    "sg:province":"NC",
    "sg:tags":[
        "operation"
    ],
    "wof:name":"Hillsborough Motor Lodge",
    "wof:placetype":"venue"
},
  "geometry": {"coordinates":[-79.117572,36.086373],"type":"Point"}
}