{
  "type": "Feature",
  "properties": {
    "iso:country":"US",
    "sg:address":"3302 S New Hope Rd Suite 200-A-B",
    "sg:city":"Gastonia",
    "sg:classifiers":[
        {
            "category":"Health Services",
            "subcategory":"Doctor",
            "type":"Services"
        },
        {
            "category":"Health Services",
            "subcategory":"Hospital",
            "type":"Services"
        },
        {
            "category":"Shopping",
            "subcategory":"Pharmacy",
            "type":"Retail Goods"
        }
    ],
    "sg:phone":"+1 704 823 1577",
    "sg:postcode":"28056",
    "sg:province":"NC",
    "sg:tags":[
        "product",
        "wellness",
        "colonic",
        "irrigation",
        "sleep",
        "treatment",
        "disorders-information"
    ],
    "sg:website":"http://www.HCWellnessCenter.com",
    "wof:name":"Healthy Connection",
    "wof:placetype":"venue"
},
  "geometry": {"coordinates":[-81.110786,35.226754],"type":"Point"}
}