{
  "type": "Feature",
  "properties": {
    "addr:full":"3713 Richfield Rd Greensboro NC 27410",
    "addr:housenumber":"3713",
    "addr:postcode":"27410",
    "addr:street":"Richfield Rd",
    "iso:country":"US",
    "sg:address":"3713 Richfield Rd",
    "sg:city":"Greensboro",
    "sg:classifiers":[
        {
            "category":"Professional",
            "type":"Services"
        }
    ],
    "sg:phone":"+1 336 288 2282",
    "sg:postcode":"27410",
    "sg:province":"NC",
    "sg:tags":[
        "establishment"
    ],
    "wof:name":"Carla Lang Dminpastoral Cnslr",
    "wof:placetype":"venue"
},
  "geometry": {"coordinates":[-79.85898299999999,36.128906],"type":"Point"}
}