{
  "type": "Feature",
  "properties": {
    "iso:country":"US",
    "sg:address":"9931 Rose Commons Dr",
    "sg:city":"Huntersville",
    "sg:classifiers":[
        {
            "category":"Shopping",
            "subcategory":"Gifts & Souvenirs",
            "type":"Retail Goods"
        }
    ],
    "sg:phone":"+1 704 875 7117",
    "sg:postcode":"28078",
    "sg:province":"NC",
    "sg:tags":[
        "shop"
    ],
    "wof:name":"Gift Tree",
    "wof:placetype":"venue"
},
  "geometry": {"coordinates":[-80.861655,35.40893],"type":"Point"}
}