{
  "type": "Feature",
  "properties": {
    "iso:country":"US",
    "sg:address":"3722 Bridges St",
    "sg:city":"Morehead City",
    "sg:classifiers":[
        {
            "category":"Social Services",
            "type":"Services"
        }
    ],
    "sg:phone":"+1 252 247 3300",
    "sg:postcode":"28557",
    "sg:province":"NC",
    "sg:tags":[
        "information",
        "center",
        "diabetes"
    ],
    "sg:website":"www.diabetes-careonline.com",
    "wof:name":"Diabetes Care & Education Inc",
    "wof:placetype":"venue"
},
  "geometry": {"coordinates":[-76.756686,34.726808],"type":"Point"}
}