{
  "type": "Feature",
  "properties": {
    "iso:country":"US",
    "sg:address":"3396 Six Forks Rd",
    "sg:city":"Raleigh",
    "sg:classifiers":[
        {
            "category":"Health Services",
            "subcategory":"Doctor",
            "type":"Services"
        }
    ],
    "sg:phone":"+1 919 781 8897",
    "sg:postcode":"27609",
    "sg:province":"NC",
    "sg:tags":[
        "physician",
        "family",
        "practice",
        "surgeons",
        "medicine",
        "surgeon"
    ],
    "wof:name":"Universal Family Medicine at Six Forks",
    "wof:placetype":"venue"
},
  "geometry": {"coordinates":[-78.634383,35.827819],"type":"Point"}
}