{
  "type": "Feature",
  "properties": {
    "addr:full":"405 Lewis Rd Hampstead NC 28443",
    "addr:housenumber":"405",
    "addr:postcode":"28443",
    "addr:street":"Lewis Rd",
    "iso:country":"US",
    "sg:address":"405 Lewis Rd",
    "sg:city":"Hampstead",
    "sg:classifiers":[
        {
            "category":"Shopping",
            "subcategory":"Bicycles & Sporting Goods",
            "type":"Retail Goods"
        }
    ],
    "sg:phone":"+1 910 270 2194",
    "sg:postcode":"28443",
    "sg:province":"NC",
    "sg:tags":[
        "bait",
        "fishing"
    ],
    "wof:name":"Lewis Mark Crew Boats Inc",
    "wof:placetype":"venue"
},
  "geometry": {"coordinates":[-77.60954,34.409821],"type":"Point"}
}