{
  "type": "Feature",
  "properties": {
    "iso:country":"US",
    "sg:address":"4821 Cobble Creek Cir",
    "sg:city":"Winston Salem",
    "sg:classifiers":[
        {
            "category":"Shopping",
            "subcategory":"News",
            "type":"Retail Goods"
        }
    ],
    "sg:phone":"+1 336 661 7631",
    "sg:postcode":"27105",
    "sg:province":"NC",
    "sg:tags":[
        "magazine"
    ],
    "wof:name":"Sell Your Home Magazine",
    "wof:placetype":"venue"
},
  "geometry": {"coordinates":[-80.284237,36.176636],"type":"Point"}
}