{
  "type": "Feature",
  "properties": {
    "addr:full":"16419 Northcross Dr Huntersville NC 28078",
    "addr:housenumber":"16419",
    "addr:postcode":"28078",
    "addr:street":"Northcross Dr",
    "iso:country":"US",
    "sg:address":"16419 Northcross Dr",
    "sg:city":"Huntersville",
    "sg:classifiers":[
        {
            "category":"Professional",
            "type":"Services"
        }
    ],
    "sg:phone":"+1 704 895 1206",
    "sg:postcode":"28078",
    "sg:province":"NC",
    "sg:tags":[
        "establishment"
    ],
    "sg:website":"www.aboutfwg.com",
    "wof:name":"Intercontinental Acceptance",
    "wof:placetype":"venue"
},
  "geometry": {"coordinates":[-80.87003900000001,35.435066],"type":"Point"}
}