{
  "type": "Feature",
  "properties": {
    "addr:full":"4431 Durham Rd Roxboro NC 27573",
    "addr:housenumber":"4431",
    "addr:postcode":"27573",
    "addr:street":"Durham Rd",
    "iso:country":"US",
    "sg:address":"4431 Durham Rd",
    "sg:city":"Roxboro",
    "sg:classifiers":[
        {
            "category":"Home & Garden",
            "subcategory":"Mobile Homes",
            "type":"Retail Goods"
        }
    ],
    "sg:phone":"+1 336 597 5223",
    "sg:postcode":"27573",
    "sg:province":"NC",
    "wof:name":"Home Place",
    "wof:placetype":"venue"
},
  "geometry": {"coordinates":[-78.97836,36.329994],"type":"Point"}
}