{
  "type": "Feature",
  "properties": {
    "addr:full":"1500 Cool Springs Rd Sanford NC 27330",
    "addr:housenumber":"1500",
    "addr:postcode":"27330",
    "addr:street":"Cool Springs Rd",
    "iso:country":"US",
    "sg:address":"1500 Cool Springs Rd",
    "sg:city":"Sanford",
    "sg:classifiers":[
        {
            "category":"Real Estate",
            "subcategory":"Real Estate Agent",
            "type":"Services"
        }
    ],
    "sg:phone":"+1 919 775 3035",
    "sg:postcode":"27330",
    "sg:province":"NC",
    "wof:name":"Harry Thomas Real Estate",
    "wof:placetype":"venue"
},
  "geometry": {"coordinates":[-79.228106,35.497707],"type":"Point"}
}