{
  "type": "Feature",
  "properties": {
    "iso:country":"US",
    "sg:address":"7990 Westcape Dr",
    "sg:city":"Denver",
    "sg:classifiers":[
        {
            "category":"Real Estate",
            "subcategory":"Real Estate Agent",
            "type":"Services"
        }
    ],
    "sg:phone":"+1 704 483 4811",
    "sg:postcode":"28037",
    "sg:province":"NC",
    "sg:tags":[
        "consulting",
        "management"
    ],
    "wof:name":"Private Properties Inc",
    "wof:placetype":"venue"
},
  "geometry": {"coordinates":[-80.96813899999999,35.515189],"type":"Point"}
}