{
  "type": "Feature",
  "properties": {
    "iso:country":"US",
    "sg:address":"321 N Front St",
    "sg:city":"Wilmington",
    "sg:classifiers":[
        {
            "category":"Professional",
            "subcategory":"Management & Consulting",
            "type":"Services"
        }
    ],
    "sg:phone":"+1   ",
    "sg:postcode":"28401",
    "sg:province":"NC",
    "sg:tags":[
        "business"
    ],
    "wof:name":"Port City Physical Therapy",
    "wof:placetype":"venue"
},
  "geometry": {"coordinates":[-77.94932300000001,34.239661],"type":"Point"}
}