{
  "type": "Feature",
  "properties": {
    "iso:country":"US",
    "sg:address":"31 Brookcliff Dr",
    "sg:city":"Asheville",
    "sg:classifiers":[
        {
            "category":"Real Estate",
            "subcategory":"Real Estate Agent",
            "type":"Services"
        }
    ],
    "sg:phone":"+1 828 251 0708",
    "sg:postcode":"28804",
    "sg:province":"NC",
    "wof:name":"JAS Properties",
    "wof:placetype":"venue"
},
  "geometry": {"coordinates":[-82.53005400000001,35.645746],"type":"Point"}
}