{
  "type": "Feature",
  "properties": {
    "addr:full":"4109 Halburton Rd Raleigh NC 27613",
    "addr:housenumber":"4109",
    "addr:postcode":"27613",
    "addr:street":"Halburton Rd",
    "iso:country":"US",
    "sg:address":"4109 Halburton Rd",
    "sg:city":"Raleigh",
    "sg:classifiers":[
        {
            "category":"Professional",
            "type":"Services"
        }
    ],
    "sg:phone":"+1 704 258 4840",
    "sg:postcode":"27613",
    "sg:province":"NC",
    "wof:name":"Netcomlogic",
    "wof:placetype":"venue"
},
  "geometry": {"coordinates":[-78.707464,35.907331],"type":"Point"}
}