{
  "type": "Feature",
  "properties": {
    "iso:country":"US",
    "sg:address":"403 Saint Andrews Dr",
    "sg:city":"Greenville",
    "sg:classifiers":[
        {
            "category":"Organizations",
            "subcategory":"Community Association",
            "type":"Services"
        }
    ],
    "sg:phone":"+1 252 355 7793",
    "sg:postcode":"27834",
    "sg:province":"NC",
    "sg:tags":[
        "military"
    ],
    "wof:name":"American Legion",
    "wof:placetype":"venue"
},
  "geometry": {"coordinates":[-77.394014,35.576622],"type":"Point"}
}