{
  "type": "Feature",
  "properties": {
    "addr:full":"214 Wax Myrtle Trl Kitty Hawk NC 27949",
    "addr:housenumber":"214",
    "addr:postcode":"27949",
    "addr:street":"Wax Myrtle Trl",
    "iso:country":"US",
    "sg:address":"214 Wax Myrtle Trl",
    "sg:city":"Kitty Hawk",
    "sg:classifiers":[
        {
            "category":"Utilities",
            "subcategory":"Telephone",
            "type":"Services"
        }
    ],
    "sg:phone":"+1 252 255 0107",
    "sg:postcode":"27949",
    "sg:province":"NC",
    "sg:tags":[
        "communications"
    ],
    "wof:name":"AMI MCI Thomas F Stone Jr",
    "wof:placetype":"venue"
},
  "geometry": {"coordinates":[-75.731843,36.129503],"type":"Point"}
}