{
  "type": "Feature",
  "properties": {
    "addr:full":"949 S Trade St Tryon NC 28782",
    "addr:housenumber":"949",
    "addr:postcode":"28782",
    "addr:street":"S Trade St",
    "iso:country":"US",
    "sg:address":"949 S Trade St",
    "sg:city":"Tryon",
    "sg:classifiers":[
        {
            "category":"Food & Beverages",
            "subcategory":"Groceries & Convenience Stores",
            "type":"Retail Goods"
        }
    ],
    "sg:phone":"+1 828 859 3005",
    "sg:postcode":"28782",
    "sg:province":"NC",
    "sg:tags":[
        "grocer"
    ],
    "wof:name":"Jon & Jay's Discount Groceries",
    "wof:placetype":"venue"
},
  "geometry": {"coordinates":[-82.23056699999999,35.197827],"type":"Point"}
}