{
  "type": "Feature",
  "properties": {
    "iso:country":"US",
    "sg:address":"8314 Pineville-Matthews Rd",
    "sg:city":"Charlotte",
    "sg:classifiers":[
        {
            "category":"Retail",
            "subcategory":"Laundry & Dry Cleaning",
            "type":"Services"
        }
    ],
    "sg:phone":"+1 704 541 6698",
    "sg:postcode":"28226",
    "sg:province":"NC",
    "sg:tags":[
        "cleaners"
    ],
    "wof:name":"Soap Suds Coin Laundry",
    "wof:placetype":"venue"
},
  "geometry": {"coordinates":[-80.861754,35.087616],"type":"Point"}
}