{
  "type": "Feature",
  "properties": {
    "addr:full":"7093 Forney Hill Rd Denver NC 28037",
    "addr:housenumber":"7093",
    "addr:postcode":"28037",
    "addr:street":"Forney Hill Rd",
    "iso:country":"US",
    "sg:address":"7093 Forney Hill Rd",
    "sg:city":"Denver",
    "sg:classifiers":[
        {
            "category":"Real Estate",
            "subcategory":"Real Estate Agent",
            "type":"Services"
        }
    ],
    "sg:phone":"+1 704 483 6019",
    "sg:postcode":"28037",
    "sg:province":"NC",
    "wof:name":"Holbrooks Real Estate Inc",
    "wof:placetype":"venue"
},
  "geometry": {"coordinates":[-81.04503200000001,35.518736],"type":"Point"}
}