{
  "type": "Feature",
  "properties": {
    "iso:country":"US",
    "sg:address":"10008 Beach Dr SW",
    "sg:city":"Calabash",
    "sg:classifiers":[
        {
            "category":"Restaurant",
            "type":"Food & Drink"
        }
    ],
    "sg:phone":"+1 910 575 1001",
    "sg:postcode":"28467",
    "sg:province":"NC",
    "sg:tags":[
        "eating"
    ],
    "wof:name":"Sunrise Pancake House",
    "wof:placetype":"venue"
},
  "geometry": {"coordinates":[-78.57142899999999,33.890864],"type":"Point"}
}