{
  "type": "Feature",
  "properties": {
    "addr:full":"150 16th Ave NW Hickory NC 28601",
    "addr:housenumber":"150",
    "addr:postcode":"28601",
    "addr:street":"16Th Ave Nw",
    "iso:country":"US",
    "sg:address":"150 16th Ave NW",
    "sg:city":"Hickory",
    "sg:classifiers":[
        {
            "category":"Organizations",
            "subcategory":"Religious Organization",
            "type":"Services"
        }
    ],
    "sg:phone":"+1 828 328 6196",
    "sg:postcode":"28601",
    "sg:province":"NC",
    "sg:tags":[
        "church"
    ],
    "wof:name":"Corinth Refrmd Untd Chc Chris",
    "wof:placetype":"venue"
},
  "geometry": {"coordinates":[-81.341556,35.754133],"type":"Point"}
}