{
  "type": "Feature",
  "properties": {
    "addr:full":"213 N Mc Rae St Burgaw NC 28425",
    "addr:housenumber":"213",
    "addr:postcode":"28425",
    "addr:street":"N Mc Rae St",
    "iso:country":"US",
    "sg:address":"213 N Mc Rae St",
    "sg:city":"Burgaw",
    "sg:classifiers":[
        {
            "category":"Retail",
            "subcategory":"Auto Repair",
            "type":"Services"
        }
    ],
    "sg:phone":"+1 910 259 4931",
    "sg:postcode":"28425",
    "sg:province":"NC",
    "sg:tags":[
        "general"
    ],
    "wof:name":"Town of Burgaw",
    "wof:placetype":"venue"
},
  "geometry": {"coordinates":[-77.930852,34.55216],"type":"Point"}
}