{
  "type": "Feature",
  "properties": {
    "iso:country":"US",
    "sg:address":"1320 Midway Rd SE",
    "sg:city":"Bolivia",
    "sg:classifiers":[
        {
            "category":"Freight",
            "type":"Transportation"
        }
    ],
    "sg:phone":"+1 910 253 6713",
    "sg:postcode":"28422",
    "sg:province":"NC",
    "sg:tags":[
        "operator",
        "local",
        "trucking"
    ],
    "wof:name":"Bull Dog Trucking",
    "wof:placetype":"venue"
},
  "geometry": {"coordinates":[-78.14662,34.01378],"type":"Point"}
}