{
  "type": "Feature",
  "properties": {
    "addr:full":"184 Drew St Raeford NC 28376",
    "addr:housenumber":"184",
    "addr:postcode":"28376",
    "addr:street":"Drew St",
    "iso:country":"US",
    "sg:address":"184 Drew St",
    "sg:city":"Raeford",
    "sg:classifiers":[
        {
            "category":"Health Services",
            "subcategory":"Health Practitioner",
            "type":"Services"
        }
    ],
    "sg:phone":"+1 910 848 0290",
    "sg:postcode":"28376",
    "sg:province":"NC",
    "sg:tags":[
        "nutritionist"
    ],
    "wof:name":"Lamb Nutrition & Fitness",
    "wof:placetype":"venue"
},
  "geometry": {"coordinates":[-79.106427,35.037029],"type":"Point"}
}