{
  "type": "Feature",
  "properties": {
    "addr:full":"8209 Zebulon Rd Youngsville NC 27596",
    "addr:housenumber":"8209",
    "addr:postcode":"27596",
    "addr:street":"Zebulon Rd",
    "iso:country":"US",
    "sg:address":"8209 Zebulon Rd",
    "sg:city":"Youngsville",
    "sg:classifiers":[
        {
            "category":"Manufacturing",
            "subcategory":"Signs",
            "type":"Manufacturing & Wholesale Goods"
        }
    ],
    "sg:phone":"+1 919 556 4604",
    "sg:postcode":"27596",
    "sg:province":"NC",
    "sg:tags":[
        "specialty",
        "mfg"
    ],
    "wof:name":"McNeill Neon",
    "wof:placetype":"venue"
},
  "geometry": {"coordinates":[-78.44776299999999,35.983345],"type":"Point"}
}