{
  "type": "Feature",
  "properties": {
    "addr:full":"131 N Front St Wilmington NC 28401",
    "addr:housenumber":"131",
    "addr:postcode":"28401",
    "addr:street":"N Front St",
    "iso:country":"US",
    "sg:address":"131 N Front St",
    "sg:city":"Wilmington",
    "sg:classifiers":[
        {
            "category":"Restaurant",
            "type":"Food & Drink"
        }
    ],
    "sg:menulink":"http://www.allmenus.com/nc/wilmington/136286-fat-tonys/menu/",
    "sg:phone":"+1 910 343 8881",
    "sg:postcode":"28401",
    "sg:province":"NC",
    "sg:tags":[
        "italian"
    ],
    "wof:name":"Fat Tony's",
    "wof:placetype":"venue"
},
  "geometry": {"coordinates":[-77.94890100000001,34.237165],"type":"Point"}
}