{
  "type": "Feature",
  "properties": {
    "iso:country":"US",
    "sg:address":"385 Winklers Creek Rd",
    "sg:city":"Boone",
    "sg:classifiers":[
        {
            "category":"Organizations",
            "subcategory":"Religious Organization",
            "type":"Services"
        }
    ],
    "sg:phone":"+1   ",
    "sg:postcode":"28607",
    "sg:province":"NC",
    "wof:name":"Central Assembly Of God",
    "wof:placetype":"venue"
},
  "geometry": {"coordinates":[-81.670964,36.199258],"type":"Point"}
}