{
  "type": "Feature",
  "properties": {
    "iso:country":"US",
    "sg:address":"2456 S Wesleyan Blvd",
    "sg:city":"Rocky Mount",
    "sg:classifiers":[
        {
            "category":"Retail",
            "subcategory":"Auto Repair",
            "type":"Services"
        }
    ],
    "sg:phone":"+1   ",
    "sg:postcode":"27803",
    "sg:province":"NC",
    "sg:tags":[
        "general"
    ],
    "wof:name":"301 Quick Change",
    "wof:placetype":"venue"
},
  "geometry": {"coordinates":[-77.82217799999999,35.88976],"type":"Point"}
}