{
  "type": "Feature",
  "properties": {
    "iso:country":"US",
    "sg:address":"1459 Sand Hill Rd Ste G33",
    "sg:city":"Candler",
    "sg:classifiers":[
        {
            "category":"Education",
            "subcategory":"University",
            "type":"Public Place"
        }
    ],
    "sg:phone":"+1 828 670 8810",
    "sg:postcode":"28715",
    "sg:province":"NC",
    "sg:tags":[
        "college"
    ],
    "sg:website":"www.wcu.edu",
    "wof:name":"Western Carolina University",
    "wof:placetype":"venue"
},
  "geometry": {"coordinates":[-82.656363,35.541557],"type":"Point"}
}