{
  "type": "Feature",
  "properties": {
    "iso:country":"US",
    "sg:address":"1817 S Wesleyan Blvd",
    "sg:city":"Rocky Mount",
    "sg:classifiers":[
        {
            "category":"Wholesale",
            "subcategory":"Electrical",
            "type":"Manufacturing & Wholesale Goods"
        }
    ],
    "sg:phone":"+1 252 442 9275",
    "sg:postcode":"27803",
    "sg:province":"NC",
    "sg:tags":[
        "repair",
        "electronic"
    ],
    "wof:name":"Eastern Communications",
    "wof:placetype":"venue"
},
  "geometry": {"coordinates":[-77.82687799999999,35.902496],"type":"Point"}
}