{
  "type": "Feature",
  "properties": {
    "iso:country":"US",
    "sg:address":"108 Brandywine Ct",
    "sg:city":"Rocky Mount",
    "sg:classifiers":[
        {
            "category":"Retail",
            "subcategory":"Car Wash",
            "type":"Services"
        }
    ],
    "sg:phone":"+1 252 451 7750",
    "sg:postcode":"27804",
    "sg:province":"NC",
    "sg:tags":[
        "automobile",
        "detail",
        "clean"
    ],
    "wof:name":"Carolina Mobile Car Care",
    "wof:placetype":"venue"
},
  "geometry": {"coordinates":[-77.84487300000001,35.984673],"type":"Point"}
}