{
  "type": "Feature",
  "properties": {
    "addr:full":"1043 N Main St Mooresville NC 28115",
    "addr:housenumber":"1043",
    "addr:postcode":"28115",
    "addr:street":"N Main St",
    "iso:country":"US",
    "sg:address":"1043 N Main St",
    "sg:city":"Mooresville",
    "sg:classifiers":[
        {
            "category":"Cafe",
            "type":"Food & Drink"
        },
        {
            "category":"Restaurant",
            "type":"Food & Drink"
        }
    ],
    "sg:menulink":"http://www.allmenus.com/nc/coddle-creek/229293-isy-bells-cafe/menu/",
    "sg:phone":"+1 704 663 6723",
    "sg:postcode":"28115",
    "sg:province":"NC",
    "sg:tags":[
        "american"
    ],
    "wof:name":"Isy Bell's Cafe",
    "wof:placetype":"venue"
},
  "geometry": {"coordinates":[-80.796628,35.58868],"type":"Point"}
}