{
  "type": "Feature",
  "properties": {
    "iso:country":"US",
    "sg:address":"4111 New Bern Ave Ste 101",
    "sg:city":"Raleigh",
    "sg:classifiers":[
        {
            "category":"Banks & Credit Unions",
            "subcategory":"Bank",
            "type":"Services"
        },
        {
            "category":"Banks & Credit Unions",
            "subcategory":"Financial Services",
            "type":"Services"
        }
    ],
    "sg:phone":"+1 919 212 0090",
    "sg:postcode":"27610",
    "sg:province":"NC",
    "sg:tags":[
        "loan",
        "financing"
    ],
    "sg:website":"http://www.SunTrust.com",
    "wof:name":"SunTrust Bank - New Bern Avenue Kroger",
    "wof:placetype":"venue"
},
  "geometry": {"coordinates":[-78.567198,35.79902],"type":"Point"}
}