{
  "type": "Feature",
  "properties": {
    "iso:country":"US",
    "sg:address":"3401 Marathon Ave",
    "sg:city":"Castle Hayne",
    "sg:classifiers":[
        {
            "category":"Shopping",
            "subcategory":"Discount & Variety Stores",
            "type":"Retail Goods"
        }
    ],
    "sg:phone":"+1 910 675 2528",
    "sg:postcode":"28429",
    "sg:province":"NC",
    "sg:tags":[
        "merchandise",
        "general"
    ],
    "wof:name":"Air Force Sergeants Assn",
    "wof:placetype":"venue"
},
  "geometry": {"coordinates":[-77.92258200000001,34.347378],"type":"Point"}
}