{
  "type": "Feature",
  "properties": {
    "addr:full":"150 Church St Whittier NC 28789",
    "addr:housenumber":"150",
    "addr:postcode":"28789",
    "addr:street":"Church St",
    "iso:country":"US",
    "sg:address":"150 Church St",
    "sg:city":"Whittier",
    "sg:classifiers":[
        {
            "category":"Organizations",
            "subcategory":"Religious Organization",
            "type":"Services"
        }
    ],
    "sg:phone":"+1 828 497 6245",
    "sg:postcode":"28789",
    "sg:province":"NC",
    "sg:tags":[
        "church"
    ],
    "wof:name":"Whittier United Methodist Chr",
    "wof:placetype":"venue"
},
  "geometry": {"coordinates":[-83.35886000000001,35.434442],"type":"Point"}
}