{
  "type": "Feature",
  "properties": {
    "iso:country":"US",
    "sg:address":"115 Dogwood Dr",
    "sg:city":"Weldon",
    "sg:classifiers":[
        {
            "category":"Organizations",
            "subcategory":"Religious Organization",
            "type":"Services"
        }
    ],
    "sg:phone":"+1   ",
    "sg:postcode":"27890",
    "sg:province":"NC",
    "wof:name":"Want More Labor Station",
    "wof:placetype":"venue"
},
  "geometry": {"coordinates":[-77.599722,36.414583],"type":"Point"}
}