{
  "type": "Feature",
  "properties": {
    "iso:country":"US",
    "sg:address":"105 S Caledonia Rd",
    "sg:city":"Laurinburg",
    "sg:classifiers":[
        {
            "category":"Organizations",
            "subcategory":"Religious Organization",
            "type":"Services"
        }
    ],
    "sg:phone":"+1 910 277 1868",
    "sg:postcode":"28352",
    "sg:province":"NC",
    "sg:tags":[
        "church"
    ],
    "wof:name":"St Margret Bible Pentecostal",
    "wof:placetype":"venue"
},
  "geometry": {"coordinates":[-79.45329,34.774412],"type":"Point"}
}