{
  "type": "Feature",
  "properties": {
    "addr:full":"2204 Hickory House Rd Sanford NC 27332",
    "addr:housenumber":"2204",
    "addr:postcode":"27332",
    "addr:street":"Hickory House Rd",
    "iso:country":"US",
    "sg:address":"2204 Hickory House Rd",
    "sg:city":"Sanford",
    "sg:classifiers":[
        {
            "category":"Recreation",
            "type":"Entertainment"
        }
    ],
    "sg:phone":"+1 919 776 4600",
    "sg:postcode":"27332",
    "sg:province":"NC",
    "sg:tags":[
        "course",
        "range",
        "practice",
        "golf",
        "public"
    ],
    "wof:name":"Scott's Outback Driving Range",
    "wof:placetype":"venue"
},
  "geometry": {"coordinates":[-79.21677800000001,35.421961],"type":"Point"}
}