{
  "type": "Feature",
  "properties": {
    "addr:full":"200 Davis Heights Dr Gastonia NC 28052",
    "addr:housenumber":"200",
    "addr:postcode":"28052",
    "addr:street":"Davis Heights Dr",
    "iso:country":"US",
    "sg:address":"200 Davis Heights Dr",
    "sg:city":"Gastonia",
    "sg:classifiers":[
        {
            "category":"Wholesale",
            "subcategory":"Machinery & Supplies",
            "type":"Manufacturing & Wholesale Goods"
        }
    ],
    "sg:phone":"+1 704 865 8351",
    "sg:postcode":"28052",
    "sg:province":"NC",
    "sg:tags":[
        "rubber",
        "product"
    ],
    "wof:name":"Abbot Industries Inc",
    "wof:placetype":"venue"
},
  "geometry": {"coordinates":[-81.21038900000001,35.196408],"type":"Point"}
}