{
  "type": "Feature",
  "properties": {
    "iso:country":"US",
    "sg:address":"2559 Ward Blvd",
    "sg:city":"Wilson",
    "sg:classifiers":[
        {
            "category":"Health Services",
            "subcategory":"Hospital",
            "type":"Services"
        }
    ],
    "sg:phone":"+1 252 291 6717",
    "sg:postcode":"27893",
    "sg:province":"NC",
    "sg:tags":[
        "mental"
    ],
    "wof:name":"Ald Foundation",
    "wof:placetype":"venue"
},
  "geometry": {"coordinates":[-77.934135,35.748295],"type":"Point"}
}