{
  "type": "Feature",
  "properties": {
    "iso:country":"US",
    "sg:address":"2410 Arendell St",
    "sg:city":"Morehead City",
    "sg:classifiers":[
        {
            "category":"Wholesale",
            "subcategory":"Stationery",
            "type":"Manufacturing & Wholesale Goods"
        }
    ],
    "sg:phone":"+1 252 240 2515",
    "sg:postcode":"28557",
    "sg:province":"NC",
    "sg:tags":[
        "school",
        "supply"
    ],
    "sg:website":"www.teacherscatalog.com",
    "wof:name":"Teacher's Pet Inc",
    "wof:placetype":"venue"
},
  "geometry": {"coordinates":[-76.73673100000001,34.723362],"type":"Point"}
}