{
  "type": "Feature",
  "properties": {
    "iso:country":"US",
    "sg:address":"1301 Burnetts Chapel Rd",
    "sg:city":"Greensboro",
    "sg:classifiers":[
        {
            "category":"Building & Trades",
            "subcategory":"Construction",
            "type":"Services"
        }
    ],
    "sg:phone":"+1 336 674 6618",
    "sg:postcode":"27406",
    "sg:province":"NC",
    "sg:tags":[
        "house"
    ],
    "wof:name":"Dlc & Son Inc",
    "wof:placetype":"venue"
},
  "geometry": {"coordinates":[-79.83638999999999,35.949961],"type":"Point"}
}