{
  "type": "Feature",
  "properties": {
    "iso:country":"US",
    "sg:address":"111 Garwin Dr W",
    "sg:city":"Wilson",
    "sg:classifiers":[
        {
            "category":"Professional",
            "subcategory":"Detective & Security Services",
            "type":"Services"
        }
    ],
    "sg:phone":"+1 252 399 0817",
    "sg:postcode":"27893",
    "sg:province":"NC",
    "sg:tags":[
        "guard",
        "patrol"
    ],
    "wof:name":"International Security Svc Inc",
    "wof:placetype":"venue"
},
  "geometry": {"coordinates":[-77.942319,35.724462],"type":"Point"}
}