{
  "type": "Feature",
  "properties": {
    "addr:full":"506 Dowd St Tarboro NC 27886",
    "addr:housenumber":"506",
    "addr:postcode":"27886",
    "addr:street":"Dowd St",
    "iso:country":"US",
    "sg:address":"506 Dowd St",
    "sg:city":"Tarboro",
    "sg:classifiers":[
        {
            "category":"Building & Trades",
            "subcategory":"Construction",
            "type":"Services"
        }
    ],
    "sg:phone":"+1 252 641 4234",
    "sg:postcode":"27886",
    "sg:province":"NC",
    "sg:tags":[
        "marking",
        "maintenance",
        "parking"
    ],
    "wof:name":"Tarboro Public Works Dept",
    "wof:placetype":"venue"
},
  "geometry": {"coordinates":[-77.54893300000001,35.89395],"type":"Point"}
}