{
  "type": "Feature",
  "properties": {
    "addr:full":"1038 Greenville Hwy Hendersonville NC 28792",
    "addr:housenumber":"1038",
    "addr:postcode":"28792",
    "addr:street":"Greenville Hwy",
    "iso:country":"US",
    "sg:address":"1038 Greenville Hwy",
    "sg:city":"Hendersonville",
    "sg:classifiers":[
        {
            "category":"Banks & Credit Unions",
            "subcategory":"Investment Brokerage",
            "type":"Services"
        }
    ],
    "sg:phone":"+1 828 692 5082",
    "sg:postcode":"28792",
    "sg:province":"NC",
    "sg:tags":[
        "security"
    ],
    "sg:website":"www.edwardjones.com",
    "wof:name":"Edward Jones Co",
    "wof:placetype":"venue"
},
  "geometry": {"coordinates":[-82.453458,35.299005],"type":"Point"}
}