{
  "type": "Feature",
  "properties": {
    "addr:full":"702 S Main St Randleman NC 27317",
    "addr:housenumber":"702",
    "addr:postcode":"27317",
    "addr:street":"S Main St",
    "iso:country":"US",
    "sg:address":"702 S Main St",
    "sg:city":"Randleman",
    "sg:classifiers":[
        {
            "category":"Health Services",
            "subcategory":"Doctor",
            "type":"Services"
        }
    ],
    "sg:phone":"+1 336 498 8500",
    "sg:postcode":"27317",
    "sg:province":"NC",
    "sg:tags":[
        "physician",
        "medical",
        "surgeon"
    ],
    "wof:name":"Randleman Medical Center",
    "wof:placetype":"venue"
},
  "geometry": {"coordinates":[-79.804052,35.808368],"type":"Point"}
}