{
  "type": "Feature",
  "properties": {
    "addr:full":"5500 Chapel Blvd Raleigh NC 27695",
    "addr:housenumber":"5500",
    "addr:postcode":"27695",
    "addr:street":"Chapel Blvd",
    "iso:country":"US",
    "sg:address":"5500 Chapel Blvd",
    "sg:city":"Raleigh",
    "sg:classifiers":[
        {
            "category":"Autos & Motor Vehicles",
            "subcategory":"Automobile Sales",
            "type":"Retail Goods"
        },
        {
            "category":"Retail",
            "subcategory":"Auto Repair",
            "type":"Services"
        }
    ],
    "sg:phone":"+1 919 872 5500",
    "sg:postcode":"27695",
    "sg:province":"NC",
    "sg:tags":[
        "car"
    ],
    "wof:name":"David O'neal Saab",
    "wof:placetype":"venue"
},
  "geometry": {"coordinates":[-78.72260300000001,35.813801],"type":"Point"}
}