{
  "type": "Feature",
  "properties": {
    "iso:country":"US",
    "sg:address":"308 W Cotton St",
    "sg:city":"Farmville",
    "sg:classifiers":[
        {
            "category":"Restaurant",
            "type":"Food & Drink"
        }
    ],
    "sg:phone":"+1 252 753 5128",
    "sg:postcode":"27828",
    "sg:province":"NC",
    "sg:tags":[
        "barbecue"
    ],
    "wof:name":"Jack Cobb's Barbecue Place",
    "wof:placetype":"venue"
},
  "geometry": {"coordinates":[-77.59173800000001,35.596303],"type":"Point"}
}