{
  "type": "Feature",
  "properties": {
    "addr:full":"5430 Barrier Georgeville Rd Mount Pleasant NC 28124",
    "addr:housenumber":"5430",
    "addr:postcode":"28124",
    "addr:street":"Barrier Georgeville Rd",
    "iso:country":"US",
    "sg:address":"5430 Barrier Georgeville Rd",
    "sg:city":"Mount Pleasant",
    "sg:classifiers":[
        {
            "category":"Building & Trades",
            "subcategory":"Plumbing",
            "type":"Services"
        }
    ],
    "sg:phone":"+1 704 786 2286",
    "sg:postcode":"28124",
    "sg:province":"NC",
    "sg:tags":[
        "install",
        "septic",
        "system"
    ],
    "wof:name":"Commercial Services Stanfield",
    "wof:placetype":"venue"
},
  "geometry": {"coordinates":[-80.43675500000001,35.342731],"type":"Point"}
}