{
  "type": "Feature",
  "properties": {
    "addr:full":"304 N Ashe Ave Dunn NC 28334",
    "addr:housenumber":"304",
    "addr:postcode":"28334",
    "addr:street":"N Ashe Ave",
    "iso:country":"US",
    "sg:address":"304 N Ashe Ave",
    "sg:city":"Dunn",
    "sg:classifiers":[
        {
            "category":"Building & Trades",
            "subcategory":"Electrical",
            "type":"Services"
        }
    ],
    "sg:phone":"+1 910 892 7706",
    "sg:postcode":"28334",
    "sg:province":"NC",
    "sg:tags":[
        "repair",
        "electrical",
        "electric",
        "contractor"
    ],
    "wof:name":"Walter Holmes Electrical Co",
    "wof:placetype":"venue"
},
  "geometry": {"coordinates":[-78.62079199999999,35.318239],"type":"Point"}
}