{
  "type": "Feature",
  "properties": {
    "addr:full":"4226 Surles Ct Durham NC 27703",
    "addr:housenumber":"4226",
    "addr:postcode":"27703",
    "addr:street":"Surles Ct",
    "iso:country":"US",
    "sg:address":"4226 Surles Ct",
    "sg:city":"Durham",
    "sg:classifiers":[
        {
            "category":"Wholesale",
            "subcategory":"Machinery & Supplies",
            "type":"Manufacturing & Wholesale Goods"
        }
    ],
    "sg:phone":"+1 919 313 0204",
    "sg:postcode":"27703",
    "sg:province":"NC",
    "sg:tags":[
        "equipment",
        "layer",
        "carpet"
    ],
    "sg:website":"www.designdist.com",
    "wof:name":"Design Distributing",
    "wof:placetype":"venue"
},
  "geometry": {"coordinates":[-78.84822699999999,35.86843],"type":"Point"}
}