{
  "type": "Feature",
  "properties": {
    "addr:full":"171 Jordan Rd Ramseur NC 27316",
    "addr:housenumber":"171",
    "addr:postcode":"27316",
    "addr:street":"Jordan Rd",
    "iso:country":"US",
    "sg:address":"171 Jordan Rd",
    "sg:city":"Ramseur",
    "sg:classifiers":[
        {
            "category":"Banks & Credit Unions",
            "subcategory":"Bank",
            "type":"Services"
        }
    ],
    "sg:phone":"+1 336 824 4171",
    "sg:postcode":"27316",
    "sg:province":"NC",
    "wof:name":"B B & T",
    "wof:placetype":"venue"
},
  "geometry": {"coordinates":[-79.657713,35.736857],"type":"Point"}
}