{
  "type": "Feature",
  "properties": {
    "addr:full":"6105 Parkton Rd Hope Mills NC 28348",
    "addr:housenumber":"6105",
    "addr:postcode":"28348",
    "addr:street":"Parkton Rd",
    "iso:country":"US",
    "sg:address":"6105 Parkton Rd",
    "sg:city":"Hope Mills",
    "sg:classifiers":[
        {
            "category":"Freight",
            "type":"Transportation"
        }
    ],
    "sg:phone":"+1 910 424 1569",
    "sg:postcode":"28348",
    "sg:province":"NC",
    "sg:tags":[
        "operator",
        "trucking"
    ],
    "wof:name":"Tri State Transporters Inc",
    "wof:placetype":"venue"
},
  "geometry": {"coordinates":[-78.9577,34.941689],"type":"Point"}
}