{
  "type": "Feature",
  "properties": {
    "iso:country":"US",
    "sg:address":"8098 Friendship Church Rd",
    "sg:city":"Reidsville",
    "sg:classifiers":[
        {
            "category":"Building & Trades",
            "subcategory":"Construction",
            "type":"Services"
        }
    ],
    "sg:phone":"+1 336 349 5514",
    "sg:postcode":"27320",
    "sg:province":"NC",
    "sg:tags":[
        "grading",
        "contractor"
    ],
    "wof:name":"J P Construction",
    "wof:placetype":"venue"
},
  "geometry": {"coordinates":[-79.647182,36.250728],"type":"Point"}
}