{
  "type": "Feature",
  "properties": {
    "addr:full":"739 Old Lenoir Rd Hickory NC 28601",
    "addr:housenumber":"739",
    "addr:postcode":"28601",
    "addr:street":"Old Lenoir Rd",
    "iso:country":"US",
    "sg:address":"739 Old Lenoir Rd",
    "sg:city":"Hickory",
    "sg:classifiers":[
        {
            "category":"Home & Garden",
            "subcategory":"Furniture",
            "type":"Retail Goods"
        }
    ],
    "sg:phone":"+1 828 326 1700",
    "sg:postcode":"28601",
    "sg:province":"NC",
    "wof:name":"Boyles Furniture",
    "wof:placetype":"venue"
},
  "geometry": {"coordinates":[-81.36010899999999,35.74314],"type":"Point"}
}