{
  "type": "Feature",
  "properties": {
    "iso:country":"US",
    "sg:address":"6230 Stockard Rd",
    "sg:city":"Graham",
    "sg:classifiers":[
        {
            "category":"Retail",
            "subcategory":"Repair Shop",
            "type":"Services"
        }
    ],
    "sg:phone":"+1   ",
    "sg:postcode":"27253",
    "sg:province":"NC",
    "wof:name":"Gary R Cooper Jr",
    "wof:placetype":"venue"
},
  "geometry": {"coordinates":[-79.329266,35.923649],"type":"Point"}
}