{
  "type": "Feature",
  "properties": {
    "iso:country":"US",
    "sg:address":"3420 Kendale Ave NW",
    "sg:city":"Concord",
    "sg:classifiers":[
        {
            "category":"Wholesale",
            "subcategory":"Groceries",
            "type":"Manufacturing & Wholesale Goods"
        }
    ],
    "sg:phone":"+1 704 782 8823",
    "sg:postcode":"28027",
    "sg:province":"NC",
    "sg:tags":[
        "food",
        "broker",
        "general"
    ],
    "wof:name":"Roseman Food Sales Inc",
    "wof:placetype":"venue"
},
  "geometry": {"coordinates":[-80.634446,35.428061],"type":"Point"}
}