{
  "type": "Feature",
  "properties": {
    "addr:full":"5810 Novaglen Rd Durham NC 27712",
    "addr:housenumber":"5810",
    "addr:postcode":"27712",
    "addr:street":"Novaglen Rd",
    "iso:country":"US",
    "sg:address":"5810 Novaglen Rd",
    "sg:city":"Durham",
    "sg:classifiers":[
        {
            "category":"Shopping",
            "subcategory":"Clothing, Apparel, & Fashions",
            "type":"Retail Goods"
        }
    ],
    "sg:phone":"+1 919 451 7387",
    "sg:postcode":"27712",
    "sg:province":"NC",
    "wof:name":"Suzipani' Couture Boutique",
    "wof:placetype":"venue"
},
  "geometry": {"coordinates":[-78.893159,36.106211],"type":"Point"}
}