{
  "type": "Feature",
  "properties": {
    "iso:country":"US",
    "sg:address":"908 N Graham Hopedale Rd",
    "sg:city":"Burlington",
    "sg:classifiers":[
        {
            "category":"Building & Trades",
            "subcategory":"Construction",
            "type":"Services"
        }
    ],
    "sg:phone":"+1 336 226 4988",
    "sg:postcode":"27217",
    "sg:province":"NC",
    "sg:tags":[
        "house"
    ],
    "wof:name":"Kimco Home Repair",
    "wof:placetype":"venue"
},
  "geometry": {"coordinates":[-79.402779,36.10777],"type":"Point"}
}