{
  "type": "Feature",
  "properties": {
    "iso:country":"US",
    "sg:address":"3348 State Hwy 30",
    "sg:city":"Stokes",
    "sg:classifiers":[
        {
            "category":"Farming",
            "subcategory":"Farm",
            "type":"Manufacturing & Wholesale Goods"
        }
    ],
    "sg:phone":"+1 252 752 9129",
    "sg:postcode":"27884",
    "sg:province":"NC",
    "wof:name":"Congleton Farms",
    "wof:placetype":"venue"
},
  "geometry": {"coordinates":[-77.251215,35.707501],"type":"Point"}
}