{
  "type": "Feature",
  "properties": {
    "iso:country":"US",
    "sg:address":"61 Dead Way",
    "sg:city":"Bunn",
    "sg:classifiers":[
        {
            "category":"Retail",
            "subcategory":"Auto Repair",
            "type":"Services"
        }
    ],
    "sg:phone":"+1   ",
    "sg:postcode":"27508",
    "sg:province":"NC",
    "sg:tags":[
        "general"
    ],
    "wof:name":"Manns Auto Repair",
    "wof:placetype":"venue"
},
  "geometry": {"coordinates":[-78.27428,35.948103],"type":"Point"}
}