{
  "type": "Feature",
  "properties": {
    "iso:country":"US",
    "sg:address":"4505 US Hwy 15/501",
    "sg:city":"Carthage",
    "sg:classifiers":[
        {
            "category":"Shopping",
            "subcategory":"Clothing, Apparel, & Fashions",
            "type":"Retail Goods"
        }
    ],
    "sg:phone":"+1 910 947 1984",
    "sg:postcode":"28327",
    "sg:province":"NC",
    "sg:tags":[
        "uniform"
    ],
    "wof:name":"All Things Medical",
    "wof:placetype":"venue"
},
  "geometry": {"coordinates":[-79.407872,35.324042],"type":"Point"}
}