{
  "type": "Feature",
  "properties": {
    "iso:country":"US",
    "sg:address":"4442 Bonnetsville Rd",
    "sg:city":"Clinton",
    "sg:classifiers":[
        {
            "category":"Organizations",
            "subcategory":"Religious Organization",
            "type":"Services"
        }
    ],
    "sg:phone":"+1   ",
    "sg:postcode":"28328",
    "sg:province":"NC",
    "wof:name":"Mount Plesnt Misnry Bpst Chrch",
    "wof:placetype":"venue"
},
  "geometry": {"coordinates":[-78.428076,35.009163],"type":"Point"}
}