{
  "type": "Feature",
  "properties": {
    "iso:country":"US",
    "sg:address":"335 W Plaza Dr",
    "sg:city":"Mooresville",
    "sg:classifiers":[
        {
            "category":"Personal",
            "type":"Services"
        }
    ],
    "sg:phone":"+1   ",
    "sg:postcode":"28117",
    "sg:province":"NC",
    "wof:name":"L A Weight Loss",
    "wof:placetype":"venue"
},
  "geometry": {"coordinates":[-80.855587,35.593336],"type":"Point"}
}