{
  "type": "Feature",
  "properties": {
    "iso:country":"US",
    "sg:address":"131 S Wilmington St",
    "sg:city":"Raleigh",
    "sg:classifiers":[
        {
            "category":"Shopping",
            "subcategory":"Florist",
            "type":"Retail Goods"
        }
    ],
    "sg:phone":"+1 919 828 7604",
    "sg:postcode":"27601",
    "sg:province":"NC",
    "wof:name":"Flower Box",
    "wof:placetype":"venue"
},
  "geometry": {"coordinates":[-78.63811699999999,35.778627],"type":"Point"}
}