{
  "type": "Feature",
  "properties": {
    "iso:country":"US",
    "sg:address":"224 S Main St",
    "sg:city":"Stanley",
    "sg:classifiers":[
        {
            "category":"Government",
            "subcategory":"Office",
            "type":"Public Place"
        }
    ],
    "sg:phone":"+1 704 263 4341",
    "sg:postcode":"28164",
    "sg:province":"NC",
    "sg:tags":[
        "village"
    ],
    "wof:name":"City Rescue",
    "wof:placetype":"venue"
},
  "geometry": {"coordinates":[-81.095168,35.358169],"type":"Point"}
}