{
  "type": "Feature",
  "properties": {
    "addr:full":"910 Falls Rd Rocky Mount NC 27804",
    "addr:housenumber":"910",
    "addr:postcode":"27804",
    "addr:street":"Falls Rd",
    "iso:country":"US",
    "sg:address":"910 Falls Rd",
    "sg:city":"Rocky Mount",
    "sg:classifiers":[
        {
            "category":"Professional",
            "type":"Services"
        }
    ],
    "sg:phone":"+1 252 407 7566",
    "sg:postcode":"27804",
    "sg:province":"NC",
    "sg:tags":[
        "establishment"
    ],
    "wof:name":"Preservaton Rocky Mt Archtctrl",
    "wof:placetype":"venue"
},
  "geometry": {"coordinates":[-77.800686,35.955981],"type":"Point"}
}