{
  "type": "Feature",
  "properties": {
    "iso:country":"US",
    "sg:address":"304 Village Dr",
    "sg:city":"Knightdale",
    "sg:classifiers":[
        {
            "category":"Recreation",
            "type":"Entertainment"
        }
    ],
    "sg:phone":"+1 919 266 4005",
    "sg:postcode":"27545",
    "sg:province":"NC",
    "sg:tags":[
        "instruction",
        "gymnastic"
    ],
    "wof:name":"Knightdale Academy-Gymnastics",
    "wof:placetype":"venue"
},
  "geometry": {"coordinates":[-78.476742,35.800024],"type":"Point"}
}