{
  "type": "Feature",
  "properties": {
    "addr:full":"1836 Berriedale Dr Fayetteville NC 28304",
    "addr:housenumber":"1836",
    "addr:postcode":"28304",
    "addr:street":"Berriedale Dr",
    "iso:country":"US",
    "sg:address":"1836 Berriedale Dr",
    "sg:city":"Fayetteville",
    "sg:classifiers":[
        {
            "category":"Shopping",
            "subcategory":"Discount & Variety Stores",
            "type":"Retail Goods"
        }
    ],
    "sg:phone":"+1 910 425 8966",
    "sg:postcode":"28304",
    "sg:province":"NC",
    "wof:name":"100 & Up",
    "wof:placetype":"venue"
},
  "geometry": {"coordinates":[-78.989863,35.019455],"type":"Point"}
}