{
  "type": "Feature",
  "properties": {
    "iso:country":"US",
    "sg:address":"1475 N Main St",
    "sg:city":"Kernersville",
    "sg:classifiers":[
        {
            "category":"Organizations",
            "subcategory":"Religious Organization",
            "type":"Services"
        }
    ],
    "sg:phone":"+1 336 996 8904",
    "sg:postcode":"27284",
    "sg:province":"NC",
    "sg:tags":[
        "church"
    ],
    "sg:website":"www.biblerevivalhour.com",
    "wof:name":"Bible Revival Ministries Ctr",
    "wof:placetype":"venue"
},
  "geometry": {"coordinates":[-80.044042,36.145846],"type":"Point"}
}