{
  "type": "Feature",
  "properties": {
    "addr:full":"2684 Mosquito Branch Rd SW Bolivia NC 28422",
    "addr:housenumber":"2684",
    "addr:postcode":"28422",
    "addr:street":"Mosquito Branch Rd",
    "iso:country":"US",
    "sg:address":"2684 Mosquito Branch Rd SW",
    "sg:city":"Bolivia",
    "sg:classifiers":[
        {
            "category":"Manufacturing",
            "subcategory":"Wood Products",
            "type":"Manufacturing & Wholesale Goods"
        }
    ],
    "sg:phone":"+1 910 253 6196",
    "sg:postcode":"28422",
    "sg:province":"NC",
    "sg:tags":[
        "preserving"
    ],
    "wof:name":"Coastal Piling",
    "wof:placetype":"venue"
},
  "geometry": {"coordinates":[-78.149472,33.972259],"type":"Point"}
}