{
  "type": "Feature",
  "properties": {
    "addr:full":"1006 Sumner Ct Thomasville NC 27360",
    "addr:housenumber":"1006",
    "addr:postcode":"27360",
    "addr:street":"Sumner Ct",
    "iso:country":"US",
    "sg:address":"1006 Sumner Ct",
    "sg:city":"Thomasville",
    "sg:classifiers":[
        {
            "category":"Building & Trades",
            "subcategory":"Plumbing",
            "type":"Services"
        }
    ],
    "sg:phone":"+1 336 476 3754",
    "sg:postcode":"27360",
    "sg:province":"NC",
    "sg:tags":[
        "contractor"
    ],
    "wof:name":"Bobs 24 Hour Heating Service",
    "wof:placetype":"venue"
},
  "geometry": {"coordinates":[-80.084582,35.834293],"type":"Point"}
}