{
  "type": "Feature",
  "properties": {
    "addr:full":"2827 Gray Fox Rd Monroe NC 28110",
    "addr:housenumber":"2827",
    "addr:postcode":"28110",
    "addr:street":"Gray Fox Rd",
    "iso:country":"US",
    "sg:address":"2827 Gray Fox Rd",
    "sg:city":"Monroe",
    "sg:classifiers":[
        {
            "category":"Wholesale",
            "subcategory":"Machinery & Supplies",
            "type":"Manufacturing & Wholesale Goods"
        }
    ],
    "sg:phone":"+1 704 296 9100",
    "sg:postcode":"28110",
    "sg:province":"NC",
    "sg:tags":[
        "machine",
        "tool"
    ],
    "wof:name":"King & Associates Inc",
    "wof:placetype":"venue"
},
  "geometry": {"coordinates":[-80.621776,35.057315],"type":"Point"}
}