{
  "type": "Feature",
  "properties": {
    "iso:country":"US",
    "sg:address":"4112 Campbell Rd",
    "sg:city":"Raleigh",
    "sg:classifiers":[
        {
            "category":"Real Estate",
            "subcategory":"Real Estate Agent",
            "type":"Services"
        }
    ],
    "sg:phone":"+1 919 233 0124",
    "sg:postcode":"27606",
    "sg:province":"NC",
    "wof:name":"Macedonia Funding I LLC",
    "wof:placetype":"venue"
},
  "geometry": {"coordinates":[-78.74684600000001,35.727251],"type":"Point"}
}