{
  "type": "Feature",
  "properties": {
    "iso:country":"US",
    "sg:address":"1710 Oleander Hill Ct",
    "sg:city":"Charlotte",
    "sg:classifiers":[
        {
            "category":"Freight",
            "type":"Transportation"
        }
    ],
    "sg:phone":"+1 704 222 7408",
    "sg:postcode":"28214",
    "sg:province":"NC",
    "sg:tags":[
        "courier"
    ],
    "wof:name":"Reliable Courier Svc",
    "wof:placetype":"venue"
},
  "geometry": {"coordinates":[-80.97321100000001,35.313311],"type":"Point"}
}