{
  "type": "Feature",
  "properties": {
    "addr:full":"1007 Pebble Dr Greensboro NC 27410",
    "addr:housenumber":"1007",
    "addr:postcode":"27410",
    "addr:street":"Pebble Dr",
    "iso:country":"US",
    "sg:address":"1007 Pebble Dr",
    "sg:city":"Greensboro",
    "sg:classifiers":[
        {
            "category":"Banks & Credit Unions",
            "subcategory":"Financial Services",
            "type":"Services"
        }
    ],
    "sg:phone":"+1 336 852 1382",
    "sg:postcode":"27410",
    "sg:province":"NC",
    "sg:tags":[
        "company",
        "holding"
    ],
    "wof:name":"Sibco Inc",
    "wof:placetype":"venue"
},
  "geometry": {"coordinates":[-79.857692,36.099262],"type":"Point"}
}