{
  "type": "Feature",
  "properties": {
    "iso:country":"US",
    "sg:address":"3107 S Evans St",
    "sg:city":"Greenville",
    "sg:classifiers":[
        {
            "category":"Professional",
            "subcategory":"Lawyer & Legal Services",
            "type":"Services"
        }
    ],
    "sg:phone":"+1 252 353 1440",
    "sg:postcode":"27834",
    "sg:province":"NC",
    "sg:tags":[
        "attorney"
    ],
    "wof:name":"Stroud Law Office",
    "wof:placetype":"venue"
},
  "geometry": {"coordinates":[-77.381697,35.577074],"type":"Point"}
}