{
  "type": "Feature",
  "properties": {
    "iso:country":"US",
    "sg:address":"1304 Coachman Dr",
    "sg:city":"Waxhaw",
    "sg:classifiers":[
        {
            "category":"Home & Garden",
            "subcategory":"Home Furnishings",
            "type":"Retail Goods"
        }
    ],
    "sg:phone":"+1 704 321 1119",
    "sg:postcode":"28173",
    "sg:province":"NC",
    "wof:name":"Distinctive Blinds Inc",
    "wof:placetype":"venue"
},
  "geometry": {"coordinates":[-80.79188000000001,35.009292],"type":"Point"}
}