{
  "type": "Feature",
  "properties": {
    "addr:full":"6204 Pleasant Grove Church Rd Nashville NC 27856",
    "addr:housenumber":"6204",
    "addr:postcode":"27856",
    "addr:street":"Pleasant;Church Rd",
    "iso:country":"US",
    "sg:address":"6204 Pleasant Grove Church Rd",
    "sg:city":"Nashville",
    "sg:classifiers":[
        {
            "category":"Farming",
            "subcategory":"Livestock Farm",
            "type":"Manufacturing & Wholesale Goods"
        }
    ],
    "sg:phone":"+1 252 459 6301",
    "sg:postcode":"27856",
    "sg:province":"NC",
    "sg:tags":[
        "hog",
        "or",
        "feedlot"
    ],
    "wof:name":"Gc W Hill Farms Inc",
    "wof:placetype":"venue"
},
  "geometry": {"coordinates":[-78.046969,35.993249],"type":"Point"}
}