{
  "type": "Feature",
  "properties": {
    "iso:country":"US",
    "sg:address":"220 N Bridge St",
    "sg:city":"Eden",
    "sg:classifiers":[
        {
            "category":"Building & Trades",
            "subcategory":"Construction",
            "type":"Services"
        }
    ],
    "sg:phone":"+1 336 623 9484",
    "sg:postcode":"27288",
    "sg:province":"NC",
    "sg:tags":[
        "maker",
        "cabinet"
    ],
    "wof:name":"Hill's Cabinet Shop",
    "wof:placetype":"venue"
},
  "geometry": {"coordinates":[-79.77177500000001,36.500596],"type":"Point"}
}