{
  "type": "Feature",
  "properties": {
    "iso:country":"US",
    "sg:address":"401 W Roosevelt Blvd",
    "sg:city":"Monroe",
    "sg:classifiers":[
        {
            "category":"Fast Food",
            "type":"Food & Drink"
        },
        {
            "category":"Restaurant",
            "type":"Food & Drink"
        }
    ],
    "sg:phone":"+1 704 226 8646",
    "sg:postcode":"28110",
    "sg:province":"NC",
    "sg:tags":[
        "mexican"
    ],
    "sg:website":"http://www.tacobell.com",
    "wof:name":"Taco Bell",
    "wof:placetype":"venue"
},
  "geometry": {"coordinates":[-80.529315,34.986117],"type":"Point"}
}