{
  "type": "Feature",
  "properties": {
    "addr:full":"40488 S Stanly School Rd Norwood NC 28128",
    "addr:housenumber":"40488",
    "addr:postcode":"28128",
    "addr:street":"S Stanly School Rd",
    "iso:country":"US",
    "sg:address":"40488 S Stanly School Rd",
    "sg:city":"Norwood",
    "sg:classifiers":[
        {
            "category":"Education",
            "subcategory":"School",
            "type":"Public Place"
        }
    ],
    "sg:phone":"+1 704 474 3155",
    "sg:postcode":"28128",
    "sg:province":"NC",
    "sg:tags":[
        "high"
    ],
    "wof:name":"South Stanley High School",
    "wof:placetype":"venue"
},
  "geometry": {"coordinates":[-80.163999,35.232791],"type":"Point"}
}