{
  "type": "Feature",
  "properties": {
    "iso:country":"US",
    "sg:address":"9600 Strickland Rd",
    "sg:city":"Raleigh",
    "sg:classifiers":[
        {
            "category":"Food & Beverages",
            "subcategory":"Supermarket",
            "type":"Retail Goods"
        },
        {
            "category":"Shopping",
            "subcategory":"Pharmacy",
            "type":"Retail Goods"
        },
        {
            "category":"Food & Beverages",
            "subcategory":"Groceries & Convenience Stores",
            "type":"Retail Goods"
        }
    ],
    "sg:phone":"+1 919 847 5661",
    "sg:postcode":"27615",
    "sg:province":"NC",
    "sg:tags":[
        "super"
    ],
    "sg:website":"http://www.lowesfood.com",
    "wof:name":"Lowes Foods",
    "wof:placetype":"venue"
},
  "geometry": {"coordinates":[-78.65630299999999,35.90168],"type":"Point"}
}