{
  "type": "Feature",
  "properties": {
    "iso:country":"US",
    "sg:address":"2100 Rexford Rd",
    "sg:city":"Charlotte",
    "sg:classifiers":[
        {
            "category":"Professional",
            "subcategory":"Business Services",
            "type":"Services"
        }
    ],
    "sg:phone":"+1   ",
    "sg:postcode":"28211",
    "sg:province":"NC",
    "sg:tags":[
        "patent",
        "licensing"
    ],
    "wof:name":"Castrip L L C",
    "wof:placetype":"venue"
},
  "geometry": {"coordinates":[-80.832218,35.158099],"type":"Point"}
}