{
  "type": "Feature",
  "properties": {
    "addr:full":"547 Poplar St Kinston NC 28504",
    "addr:housenumber":"547",
    "addr:postcode":"28504",
    "addr:street":"Poplar St",
    "iso:country":"US",
    "sg:address":"547 Poplar St",
    "sg:city":"Kinston",
    "sg:classifiers":[
        {
            "category":"Personal",
            "subcategory":"Beauty Salon",
            "type":"Services"
        }
    ],
    "sg:phone":"+1   ",
    "sg:postcode":"28504",
    "sg:province":"NC",
    "sg:tags":[
        "shop"
    ],
    "wof:name":"Frances Hair Styling",
    "wof:placetype":"venue"
},
  "geometry": {"coordinates":[-77.637716,35.221348],"type":"Point"}
}