{
  "type": "Feature",
  "properties": {
    "addr:full":"602 Shiloh Dr Durham NC 27703",
    "addr:housenumber":"602",
    "addr:postcode":"27703",
    "addr:street":"Shiloh Dr",
    "iso:country":"US",
    "sg:address":"602 Shiloh Dr",
    "sg:city":"Durham",
    "sg:classifiers":[
        {
            "category":"Building & Trades",
            "subcategory":"Construction",
            "type":"Services"
        }
    ],
    "sg:phone":"+1 919 596 2082",
    "sg:postcode":"27703",
    "sg:province":"NC",
    "sg:tags":[
        "contractor"
    ],
    "wof:name":"B & B Builders Of Durham",
    "wof:placetype":"venue"
},
  "geometry": {"coordinates":[-78.848254,35.963392],"type":"Point"}
}