{
  "type": "Feature",
  "properties": {
    "addr:full":"303 E Mountain St Kernersville NC 27284",
    "addr:housenumber":"303",
    "addr:postcode":"27284",
    "addr:street":"E Mountain St",
    "iso:country":"US",
    "sg:address":"303 E Mountain St",
    "sg:city":"Kernersville",
    "sg:classifiers":[
        {
            "category":"Shopping",
            "subcategory":"Computers & Home Electronics",
            "type":"Retail Goods"
        }
    ],
    "sg:phone":"+1 336 996 7727",
    "sg:postcode":"27284",
    "sg:province":"NC",
    "sg:tags":[
        "equipment",
        "dealer"
    ],
    "wof:name":"Computer Zone",
    "wof:placetype":"venue"
},
  "geometry": {"coordinates":[-80.068186,36.117796],"type":"Point"}
}