{
  "type": "Feature",
  "properties": {
    "addr:full":"1995 Bethabara Rd Winston Salem NC 27106",
    "addr:housenumber":"1995",
    "addr:postcode":"27106",
    "addr:street":"Bethabara Rd",
    "iso:country":"US",
    "sg:address":"1995 Bethabara Rd",
    "sg:city":"Winston Salem",
    "sg:classifiers":[
        {
            "category":"Health Services",
            "subcategory":"Doctor",
            "type":"Services"
        }
    ],
    "sg:phone":"+1 336 759 7596",
    "sg:postcode":"27106",
    "sg:province":"NC",
    "sg:tags":[
        "physician",
        "surgeon",
        "medical"
    ],
    "wof:name":"North Point Medical Associates",
    "wof:placetype":"venue"
},
  "geometry": {"coordinates":[-80.287246,36.149623],"type":"Point"}
}