{
  "type": "Feature",
  "properties": {
    "addr:full":"1303 Cherryville Hwy Dallas NC 28021",
    "addr:housenumber":"1303",
    "addr:postcode":"28021",
    "addr:street":"Cherryville Hwy",
    "iso:country":"US",
    "sg:address":"1303 Cherryville Hwy",
    "sg:city":"Dallas",
    "sg:classifiers":[
        {
            "category":"Government",
            "subcategory":"Office",
            "type":"Public Place"
        }
    ],
    "sg:phone":"+1 704 922 0302",
    "sg:postcode":"28021",
    "sg:province":"NC",
    "sg:tags":[
        "county",
        "program"
    ],
    "wof:name":"Family & Consumer Education",
    "wof:placetype":"venue"
},
  "geometry": {"coordinates":[-81.399563,35.405593],"type":"Point"}
}