{
  "type": "Feature",
  "properties": {
    "iso:country":"US",
    "sg:address":"3011 Fayetteville Rd",
    "sg:city":"Durham",
    "sg:classifiers":[
        {
            "category":"Food & Beverages",
            "subcategory":"Groceries & Convenience Stores",
            "type":"Retail Goods"
        }
    ],
    "sg:phone":"+1 919 686 0456",
    "sg:postcode":"27707",
    "sg:province":"NC",
    "wof:name":"United Eagle Village Food",
    "wof:placetype":"venue"
},
  "geometry": {"coordinates":[-78.908433,35.962422],"type":"Point"}
}