{
  "type": "Feature",
  "properties": {
    "iso:country":"US",
    "sg:address":"1387 McDaniel Dr",
    "sg:city":"Asheboro",
    "sg:classifiers":[
        {
            "category":"Manufacturing",
            "subcategory":"Pottery",
            "type":"Manufacturing & Wholesale Goods"
        }
    ],
    "sg:phone":"+1 336 625 1586",
    "sg:postcode":"27205",
    "sg:province":"NC",
    "sg:tags":[
        "product",
        "mfg"
    ],
    "wof:name":"Uglyjugs",
    "wof:placetype":"venue"
},
  "geometry": {"coordinates":[-79.892774,35.668693],"type":"Point"}
}