{
  "type": "Feature",
  "properties": {
    "addr:full":"103 E 4th St Tabor City NC 28463",
    "addr:housenumber":"103",
    "addr:postcode":"28463",
    "addr:street":"E 4Th St",
    "iso:country":"US",
    "sg:address":"103 E 4th St",
    "sg:city":"Tabor City",
    "sg:classifiers":[
        {
            "category":"Government",
            "subcategory":"Office",
            "type":"Public Place"
        }
    ],
    "sg:phone":"+1 910 653 4462",
    "sg:postcode":"28463",
    "sg:province":"NC",
    "sg:tags":[
        "city",
        "program"
    ],
    "wof:name":"Tabor City Drivers License Ofc",
    "wof:placetype":"venue"
},
  "geometry": {"coordinates":[-78.875484,34.147956],"type":"Point"}
}