{
  "type": "Feature",
  "properties": {
    "addr:full":"800 N Church St Rocky Mount NC 27804",
    "addr:housenumber":"800",
    "addr:postcode":"27804",
    "addr:street":"N Church St",
    "iso:country":"US",
    "sg:address":"800 N Church St",
    "sg:city":"Rocky Mount",
    "sg:classifiers":[
        {
            "category":"Insurance",
            "subcategory":"Insurance Agent",
            "type":"Services"
        }
    ],
    "sg:phone":"+1 252 446 5347",
    "sg:postcode":"27804",
    "sg:province":"NC",
    "wof:name":"Automatic Insurance",
    "wof:placetype":"venue"
},
  "geometry": {"coordinates":[-77.792581,35.953315],"type":"Point"}
}