{
  "type": "Feature",
  "properties": {
    "addr:full":"616 Andrew Hunter Rd Franklinville NC 27248",
    "addr:housenumber":"616",
    "addr:postcode":"27248",
    "addr:street":"Andrew Hunter Rd",
    "iso:country":"US",
    "sg:address":"616 Andrew Hunter Rd",
    "sg:city":"Franklinville",
    "sg:classifiers":[
        {
            "category":"Wholesale",
            "subcategory":"Machinery & Supplies",
            "type":"Manufacturing & Wholesale Goods"
        }
    ],
    "sg:phone":"+1 336 824 4182",
    "sg:postcode":"27248",
    "sg:province":"NC",
    "sg:tags":[
        "poultry",
        "equipment"
    ],
    "wof:name":"A G Supply Inc",
    "wof:placetype":"venue"
},
  "geometry": {"coordinates":[-79.709181,35.734976],"type":"Point"}
}