{
  "type": "Feature",
  "properties": {
    "addr:full":"1103 Haymarket Ln Wilmington NC 28412",
    "addr:housenumber":"1103",
    "addr:postcode":"28412",
    "addr:street":"Haymarket Ln",
    "iso:country":"US",
    "sg:address":"1103 Haymarket Ln",
    "sg:city":"Wilmington",
    "sg:classifiers":[
        {
            "category":"Professional",
            "subcategory":"Advertising",
            "type":"Services"
        }
    ],
    "sg:phone":"+1   ",
    "sg:postcode":"28412",
    "sg:province":"NC",
    "sg:tags":[
        "agency"
    ],
    "wof:name":"Mike Kennedy Enterpr",
    "wof:placetype":"venue"
},
  "geometry": {"coordinates":[-77.909251,34.167999],"type":"Point"}
}