{
  "type": "Feature",
  "properties": {
    "iso:country":"US",
    "sg:address":"2918 Hickory Blvd",
    "sg:city":"Hudson",
    "sg:classifiers":[
        {
            "category":"Manufacturing",
            "subcategory":"Metals",
            "type":"Manufacturing & Wholesale Goods"
        }
    ],
    "sg:phone":"+1 828 728 5152",
    "sg:postcode":"28638",
    "sg:province":"NC",
    "sg:tags":[
        "pipe"
    ],
    "wof:name":"Polyethylene Technology",
    "wof:placetype":"venue"
},
  "geometry": {"coordinates":[-81.480411,35.852439],"type":"Point"}
}