{
  "type": "Feature",
  "properties": {
    "iso:country":"US",
    "sg:address":"707 N Main St",
    "sg:city":"Hendersonville",
    "sg:classifiers":[
        {
            "category":"Banks & Credit Unions",
            "subcategory":"Bank",
            "type":"Services"
        }
    ],
    "sg:phone":"+1 828 697 3300",
    "sg:postcode":"28792",
    "sg:province":"NC",
    "sg:tags":[
        "institution",
        "business"
    ],
    "wof:name":"NationsBank",
    "wof:placetype":"venue"
},
  "geometry": {"coordinates":[-82.461187,35.320691],"type":"Point"}
}