{
  "type": "Feature",
  "properties": {
    "addr:full":"507 S Main St Graham NC 27253",
    "addr:housenumber":"507",
    "addr:postcode":"27253",
    "addr:street":"S Main St",
    "iso:country":"US",
    "sg:address":"507 S Main St",
    "sg:city":"Graham",
    "sg:classifiers":[
        {
            "category":"Restaurant",
            "type":"Food & Drink"
        }
    ],
    "sg:menulink":"http://www.allmenus.com/nc/graham/205187-taco-bell/menu/",
    "sg:phone":"+1 336 513 0095",
    "sg:postcode":"27253",
    "sg:province":"NC",
    "sg:tags":[
        "american",
        "mexican"
    ],
    "wof:name":"Taco Bell",
    "wof:placetype":"venue"
},
  "geometry": {"coordinates":[-79.400592,36.062605],"type":"Point"}
}