{
  "type": "Feature",
  "properties": {
    "iso:country":"US",
    "sg:address":"2609 N Center St",
    "sg:city":"Hickory",
    "sg:classifiers":[
        {
            "category":"Restaurant",
            "type":"Food & Drink"
        }
    ],
    "sg:menulink":"http://www.allmenus.com/nc/hickory/240668-china-king/menu/",
    "sg:phone":"+1 828 328 5259",
    "sg:postcode":"28601",
    "sg:province":"NC",
    "sg:tags":[
        "asian",
        "chinese"
    ],
    "wof:name":"China King",
    "wof:placetype":"venue"
},
  "geometry": {"coordinates":[-81.33262000000001,35.765873],"type":"Point"}
}