{
  "type": "Feature",
  "properties": {
    "addr:full":"3705 Shrewsbury St Durham NC 27707",
    "addr:housenumber":"3705",
    "addr:postcode":"27707",
    "addr:street":"Shrewsbury St",
    "iso:country":"US",
    "sg:address":"3705 Shrewsbury St",
    "sg:city":"Durham",
    "sg:classifiers":[
        {
            "category":"Professional",
            "type":"Services"
        }
    ],
    "sg:phone":"+1 919 489 5930",
    "sg:postcode":"27707",
    "sg:province":"NC",
    "wof:name":"Dennis Roland",
    "wof:placetype":"venue"
},
  "geometry": {"coordinates":[-78.944863,35.953548],"type":"Point"}
}