{
  "type": "Feature",
  "properties": {
    "iso:country":"US",
    "sg:address":"1207 E Courtyard Cir",
    "sg:city":"Goldsboro",
    "sg:classifiers":[
        {
            "category":"Professional",
            "type":"Services"
        }
    ],
    "sg:phone":"+1 919 734 6832",
    "sg:postcode":"27530",
    "sg:province":"NC",
    "wof:name":"Michael Byrd",
    "wof:placetype":"venue"
},
  "geometry": {"coordinates":[-77.987667,35.354571],"type":"Point"}
}