{
  "type": "Feature",
  "properties": {
    "iso:country":"US",
    "sg:address":"1385 Partee Ln",
    "sg:city":"China Grove",
    "sg:classifiers":[
        {
            "category":"Building & Trades",
            "subcategory":"Construction",
            "type":"Services"
        }
    ],
    "sg:phone":"+1 704 857 3013",
    "sg:postcode":"28023",
    "sg:province":"NC",
    "sg:tags":[
        "carpentry",
        "contractor"
    ],
    "wof:name":"Ricks Home Improvements",
    "wof:placetype":"venue"
},
  "geometry": {"coordinates":[-80.61777499999999,35.560165],"type":"Point"}
}