{
  "type": "Feature",
  "properties": {
    "iso:country":"US",
    "sg:address":"5045 Boone Trl",
    "sg:city":"Millers Creek",
    "sg:classifiers":[
        {
            "category":"Home & Garden",
            "subcategory":"Hardware",
            "type":"Retail Goods"
        }
    ],
    "sg:phone":"+1 336 838 9300",
    "sg:postcode":"28651",
    "sg:province":"NC",
    "wof:name":"Backyard To Barnyard",
    "wof:placetype":"venue"
},
  "geometry": {"coordinates":[-81.235252,36.187379],"type":"Point"}
}