{
  "type": "Feature",
  "properties": {
    "addr:full":"108 W Main St Jamestown NC 27282",
    "addr:housenumber":"108",
    "addr:postcode":"27282",
    "addr:street":"W Main St",
    "iso:country":"US",
    "sg:address":"108 W Main St",
    "sg:city":"Jamestown",
    "sg:classifiers":[
        {
            "category":"Personal",
            "subcategory":"Beauty Salon",
            "type":"Services"
        }
    ],
    "sg:phone":"+1 336 454 3438",
    "sg:postcode":"27282",
    "sg:province":"NC",
    "sg:tags":[
        "manicuring"
    ],
    "wof:name":"Pro Nail Care",
    "wof:placetype":"venue"
},
  "geometry": {"coordinates":[-79.935953,35.994028],"type":"Point"}
}