{
  "type": "Feature",
  "properties": {
    "iso:country":"US",
    "sg:address":"9 Little John Rd",
    "sg:city":"Chapel Hill",
    "sg:classifiers":[
        {
            "category":"Building & Trades",
            "subcategory":"Landscaping Services",
            "type":"Services"
        }
    ],
    "sg:phone":"+1 919 933 5820",
    "sg:postcode":"27517",
    "sg:province":"NC",
    "sg:tags":[
        "lawn",
        "maintenance",
        "grounds"
    ],
    "wof:name":"Rosales Land Shapers",
    "wof:placetype":"venue"
},
  "geometry": {"coordinates":[-79.00184299999999,35.902491],"type":"Point"}
}