{
  "type": "Feature",
  "properties": {
    "addr:full":"1405 Ann St Beaufort NC 28516",
    "addr:housenumber":"1405",
    "addr:postcode":"28516",
    "addr:street":"Ann St",
    "iso:country":"US",
    "sg:address":"1405 Ann St",
    "sg:city":"Beaufort",
    "sg:classifiers":[
        {
            "category":"Wholesale",
            "subcategory":"Farm Supplies",
            "type":"Manufacturing & Wholesale Goods"
        }
    ],
    "sg:phone":"+1 252 728 7645",
    "sg:postcode":"28516",
    "sg:province":"NC",
    "wof:name":"Atlantic Organic Fertilizer Co",
    "wof:placetype":"venue"
},
  "geometry": {"coordinates":[-76.65123800000001,34.714134],"type":"Point"}
}