{
  "type": "Feature",
  "properties": {
    "addr:full":"2000 Grassy Creek Rd Copperhill NC 37317",
    "addr:housenumber":"2000",
    "addr:postcode":"37317",
    "addr:street":"Grassy Creek Rd",
    "iso:country":"US",
    "sg:address":"2000 Grassy Creek Rd",
    "sg:city":"Copperhill",
    "sg:classifiers":[
        {
            "category":"Utilities",
            "subcategory":"Refuse",
            "type":"Services"
        }
    ],
    "sg:phone":"+1 423 496 1248",
    "sg:postcode":"37317",
    "sg:province":"NC",
    "sg:tags":[
        "garbage",
        "collection"
    ],
    "wof:name":"Appalachian Waste Systems",
    "wof:placetype":"venue"
},
  "geometry": {"coordinates":[-84.39426,35.004168],"type":"Point"}
}