{
  "type": "Feature",
  "properties": {
    "addr:full":"4111 Ed Dr Raleigh NC 27612",
    "addr:housenumber":"4111",
    "addr:postcode":"27612",
    "addr:street":"Ed Dr",
    "iso:country":"US",
    "sg:address":"4111 Ed Dr",
    "sg:city":"Raleigh",
    "sg:classifiers":[
        {
            "category":"Food & Beverages",
            "subcategory":"Bakery",
            "type":"Retail Goods"
        }
    ],
    "sg:phone":"+1 919 420 0260",
    "sg:postcode":"27612",
    "sg:province":"NC",
    "sg:tags":[
        "sandwich"
    ],
    "sg:website":"www.subway.com/",
    "wof:name":"Subway",
    "wof:placetype":"venue"
},
  "geometry": {"coordinates":[-78.70416299999999,35.825344],"type":"Point"}
}