{
  "type": "Feature",
  "properties": {
    "iso:country":"US",
    "sg:address":"970 Hudwal Rd",
    "sg:city":"Concord",
    "sg:classifiers":[
        {
            "category":"Manufacturing",
            "subcategory":"Lumber",
            "type":"Manufacturing & Wholesale Goods"
        }
    ],
    "sg:phone":"+1 704 436 2414",
    "sg:postcode":"28025",
    "sg:province":"NC",
    "sg:tags":[
        "logging"
    ],
    "wof:name":"Mark S Starnes Logging",
    "wof:placetype":"venue"
},
  "geometry": {"coordinates":[-80.46530199999999,35.43084],"type":"Point"}
}