{
  "type": "Feature",
  "properties": {
    "addr:full":"124 E Russell St Fayetteville NC 28301",
    "addr:housenumber":"124",
    "addr:postcode":"28301",
    "addr:street":"E Russell St",
    "iso:country":"US",
    "sg:address":"124 E Russell St",
    "sg:city":"Fayetteville",
    "sg:classifiers":[
        {
            "category":"Professional",
            "subcategory":"Detective & Security Services",
            "type":"Services"
        }
    ],
    "sg:phone":"+1 910 483 0007",
    "sg:postcode":"28301",
    "sg:province":"NC",
    "sg:tags":[
        "car",
        "investigator"
    ],
    "wof:name":"RDS Investigations Inc",
    "wof:placetype":"venue"
},
  "geometry": {"coordinates":[-78.878919,35.05043],"type":"Point"}
}