{
  "type": "Feature",
  "properties": {
    "addr:full":"405 Speight Ave Tarboro NC 27886",
    "addr:housenumber":"405",
    "addr:postcode":"27886",
    "addr:street":"Speight Ave",
    "iso:country":"US",
    "sg:address":"405 Speight Ave",
    "sg:city":"Tarboro",
    "sg:classifiers":[
        {
            "category":"Real Estate",
            "subcategory":"Real Estate Operator",
            "type":"Services"
        }
    ],
    "sg:phone":"+1 252 823 8767",
    "sg:postcode":"27886",
    "sg:province":"NC",
    "sg:tags":[
        "apartment"
    ],
    "wof:name":"Georgetowne Luxury Apartments",
    "wof:placetype":"venue"
},
  "geometry": {"coordinates":[-77.563377,35.905245],"type":"Point"}
}