{
  "type": "Feature",
  "properties": {
    "iso:country":"US",
    "sg:address":"132 Poplar St",
    "sg:city":"Vass",
    "sg:classifiers":[
        {
            "category":"Organizations",
            "subcategory":"Religious Organization",
            "type":"Services"
        }
    ],
    "sg:phone":"+1   ",
    "sg:postcode":"28394",
    "sg:province":"NC",
    "wof:name":"Christian Word Truth Center",
    "wof:placetype":"venue"
},
  "geometry": {"coordinates":[-79.275808,35.267891],"type":"Point"}
}