{
  "type": "Feature",
  "properties": {
    "iso:country":"US",
    "sg:address":"211 Todd Cir",
    "sg:city":"Wingate",
    "sg:classifiers":[
        {
            "category":"Building & Trades",
            "subcategory":"Electrical",
            "type":"Services"
        }
    ],
    "sg:phone":"+1 704 233 5954",
    "sg:postcode":"28174",
    "sg:province":"NC",
    "sg:tags":[
        "electrical",
        "contractor"
    ],
    "wof:name":"SA Lawrence Electric Inc",
    "wof:placetype":"venue"
},
  "geometry": {"coordinates":[-80.45146699999999,34.978938],"type":"Point"}
}