{
  "type": "Feature",
  "properties": {
    "iso:country":"US",
    "sg:address":"600 E Pine St",
    "sg:city":"Goldsboro",
    "sg:classifiers":[
        {
            "category":"Organizations",
            "subcategory":"Religious Organization",
            "type":"Services"
        }
    ],
    "sg:phone":"+1 919 735 1401",
    "sg:postcode":"27530",
    "sg:province":"NC",
    "sg:tags":[
        "church"
    ],
    "wof:name":"Holy Pentecostal Church",
    "wof:placetype":"venue"
},
  "geometry": {"coordinates":[-77.988213,35.377043],"type":"Point"}
}