{
  "type": "Feature",
  "properties": {
    "iso:country":"US",
    "sg:address":"4326 Bland Rd",
    "sg:city":"Raleigh",
    "sg:classifiers":[
        {
            "category":"Education",
            "subcategory":"Special Training",
            "type":"Public Place"
        }
    ],
    "sg:phone":"+1   ",
    "sg:postcode":"27609",
    "sg:province":"NC",
    "wof:name":"North Crlnans For HM Edcations",
    "wof:placetype":"venue"
},
  "geometry": {"coordinates":[-78.61419100000001,35.83887],"type":"Point"}
}