{
  "type": "Feature",
  "properties": {
    "iso:country":"US",
    "sg:address":"117 E Blue Ridge Rd",
    "sg:city":"East Flat Rock",
    "sg:classifiers":[
        {
            "category":"Banks & Credit Unions",
            "subcategory":"Bank",
            "type":"Services"
        }
    ],
    "sg:phone":"+1 828 693 3222",
    "sg:postcode":"28726",
    "sg:province":"NC",
    "sg:tags":[
        "federal"
    ],
    "wof:name":"Midwest America Federal Cr Un",
    "wof:placetype":"venue"
},
  "geometry": {"coordinates":[-82.42104,35.281555],"type":"Point"}
}