{
  "type": "Feature",
  "properties": {
    "addr:full":"100 S 8th St Carolina Beach NC 28428",
    "addr:housenumber":"100",
    "addr:postcode":"28428",
    "addr:street":"S 8Th St",
    "iso:country":"US",
    "sg:address":"100 S 8th St",
    "sg:city":"Carolina Beach",
    "sg:classifiers":[
        {
            "category":"Organizations",
            "subcategory":"Religious Organization",
            "type":"Services"
        }
    ],
    "sg:phone":"+1 910 458 9283",
    "sg:postcode":"28428",
    "sg:province":"NC",
    "sg:tags":[
        "church"
    ],
    "wof:name":"Seaside Chapel",
    "wof:placetype":"venue"
},
  "geometry": {"coordinates":[-77.90570099999999,34.035301],"type":"Point"}
}