{
  "type": "Feature",
  "properties": {
    "addr:full":"209 N Main St Oakboro NC 28129",
    "addr:housenumber":"209",
    "addr:postcode":"28129",
    "addr:street":"N Main St",
    "iso:country":"US",
    "sg:address":"209 N Main St",
    "sg:city":"Oakboro",
    "sg:classifiers":[
        {
            "category":"Food & Beverages",
            "subcategory":"Bakery",
            "type":"Retail Goods"
        }
    ],
    "sg:phone":"+1 704 485 2896",
    "sg:postcode":"28129",
    "sg:province":"NC",
    "sg:tags":[
        "baker"
    ],
    "wof:name":"Lizamorn's Bake Shop & Gift",
    "wof:placetype":"venue"
},
  "geometry": {"coordinates":[-80.326815,35.224179],"type":"Point"}
}