{
  "type": "Feature",
  "properties": {
    "iso:country":"US",
    "sg:address":"217 N Patterson St",
    "sg:city":"Statesville",
    "sg:classifiers":[
        {
            "category":"Building & Trades",
            "subcategory":"Construction",
            "type":"Services"
        }
    ],
    "sg:phone":"+1 704 872 9283",
    "sg:postcode":"28677",
    "sg:province":"NC",
    "sg:tags":[
        "painter"
    ],
    "wof:name":"Perfect Painting",
    "wof:placetype":"venue"
},
  "geometry": {"coordinates":[-80.902458,35.78391],"type":"Point"}
}