{
  "type": "Feature",
  "properties": {
    "iso:country":"US",
    "sg:address":"5249 Capital Blvd",
    "sg:city":"Raleigh",
    "sg:classifiers":[
        {
            "category":"Wholesale",
            "subcategory":"Durable Goods & Equipment",
            "type":"Manufacturing & Wholesale Goods"
        }
    ],
    "sg:phone":"+1 919 431 8979",
    "sg:postcode":"27616",
    "sg:province":"NC",
    "sg:tags":[
        "exporter"
    ],
    "wof:name":"Thales Mackay Radio Inc",
    "wof:placetype":"venue"
},
  "geometry": {"coordinates":[-78.58127399999999,35.856958],"type":"Point"}
}