{
  "type": "Feature",
  "properties": {
    "iso:country":"US",
    "sg:address":"1206 E 13th St",
    "sg:city":"Lumberton",
    "sg:classifiers":[
        {
            "category":"Professional",
            "type":"Services"
        }
    ],
    "sg:phone":"+1 910 737 6207",
    "sg:postcode":"28358",
    "sg:province":"NC",
    "wof:name":"Southeastern Grading",
    "wof:placetype":"venue"
},
  "geometry": {"coordinates":[-78.992322,34.625484],"type":"Point"}
}