{
  "type": "Feature",
  "properties": {
    "iso:country":"US",
    "sg:address":"9 Cedar Bluff Ct",
    "sg:city":"Durham",
    "sg:classifiers":[
        {
            "category":"Professional",
            "type":"Services"
        }
    ],
    "sg:phone":"+1 919 684 3645",
    "sg:postcode":"27704",
    "sg:province":"NC",
    "wof:name":"Steven A Guarisco",
    "wof:placetype":"venue"
},
  "geometry": {"coordinates":[-78.91190400000001,36.058919],"type":"Point"}
}