{
  "type": "Feature",
  "properties": {
    "addr:full":"241 Tolar St Fayetteville NC 28306",
    "addr:housenumber":"241",
    "addr:postcode":"28306",
    "addr:street":"Tolar St",
    "iso:country":"US",
    "sg:address":"241 Tolar St",
    "sg:city":"Fayetteville",
    "sg:classifiers":[
        {
            "category":"Recreation",
            "type":"Entertainment"
        }
    ],
    "sg:phone":"+1   ",
    "sg:postcode":"28306",
    "sg:province":"NC",
    "wof:name":"Wing Chun Kung Fu School",
    "wof:placetype":"venue"
},
  "geometry": {"coordinates":[-78.887283,35.041008],"type":"Point"}
}