{
  "type": "Feature",
  "properties": {
    "iso:country":"US",
    "sg:address":"128 Bull Mountain Rd",
    "sg:city":"Asheville",
    "sg:classifiers":[
        {
            "category":"Wholesale",
            "subcategory":"Machinery & Supplies",
            "type":"Manufacturing & Wholesale Goods"
        },
        {
            "category":"Retail",
            "subcategory":"Repair Shop",
            "type":"Services"
        }
    ],
    "sg:phone":"+1 828 231 7032",
    "sg:postcode":"28805",
    "sg:province":"NC",
    "sg:tags":[
        "equipment",
        "truck"
    ],
    "wof:name":"Mack's Lift Truck Repairs Inc",
    "wof:placetype":"venue"
},
  "geometry": {"coordinates":[-82.48667,35.594581],"type":"Point"}
}