{
  "type": "Feature",
  "properties": {
    "iso:country":"US",
    "sg:address":"4509 Bragg Blvd",
    "sg:city":"Fayetteville",
    "sg:classifiers":[
        {
            "category":"Autos & Motor Vehicles",
            "subcategory":"Automobile Sales",
            "type":"Retail Goods"
        }
    ],
    "sg:phone":"+1 910 826 0200",
    "sg:postcode":"28303",
    "sg:province":"NC",
    "sg:tags":[
        "car",
        "used",
        "dealer"
    ],
    "wof:name":"A A All Can Ride Auto Sales",
    "wof:placetype":"venue"
},
  "geometry": {"coordinates":[-78.95078700000001,35.086364],"type":"Point"}
}