{
  "type": "Feature",
  "properties": {
    "addr:full":"439 Pipers Gap Rd Mount Airy NC 27030",
    "addr:housenumber":"439",
    "addr:postcode":"27030",
    "addr:street":"Pipers Gap Rd",
    "iso:country":"US",
    "sg:address":"439 Pipers Gap Rd",
    "sg:city":"Mount Airy",
    "sg:classifiers":[
        {
            "category":"Autos & Motor Vehicles",
            "subcategory":"Automobile Sales",
            "type":"Retail Goods"
        }
    ],
    "sg:phone":"+1 336 789 4666",
    "sg:postcode":"27030",
    "sg:province":"NC",
    "sg:tags":[
        "used"
    ],
    "wof:name":"Shupes Body Shop",
    "wof:placetype":"venue"
},
  "geometry": {"coordinates":[-80.646573,36.51304],"type":"Point"}
}