{
  "type": "Feature",
  "properties": {
    "iso:country":"US",
    "sg:address":"4308 Brookfield Dr",
    "sg:city":"Charlotte",
    "sg:classifiers":[
        {
            "category":"Professional",
            "subcategory":"Business Services",
            "type":"Services"
        }
    ],
    "sg:phone":"+1   ",
    "sg:postcode":"28210",
    "sg:province":"NC",
    "wof:name":"Columbus Brand Group LLC",
    "wof:placetype":"venue"
},
  "geometry": {"coordinates":[-80.840335,35.134503],"type":"Point"}
}