{
  "type": "Feature",
  "properties": {
    "iso:country":"US",
    "sg:address":"723 Walnut St",
    "sg:city":"Laurel Hill",
    "sg:classifiers":[
        {
            "category":"Organizations",
            "subcategory":"Religious Organization",
            "type":"Services"
        }
    ],
    "sg:phone":"+1 910 462 2950",
    "sg:postcode":"28352",
    "sg:province":"NC",
    "sg:tags":[
        "church"
    ],
    "wof:name":"Beaver Dam United Methodist Ch",
    "wof:placetype":"venue"
},
  "geometry": {"coordinates":[-79.461286,34.767191],"type":"Point"}
}