{
  "type": "Feature",
  "properties": {
    "addr:full":"1614 National Hwy Thomasville NC 27360",
    "addr:housenumber":"1614",
    "addr:postcode":"27360",
    "addr:street":"National Hwy",
    "iso:country":"US",
    "sg:address":"1614 National Hwy",
    "sg:city":"Thomasville",
    "sg:classifiers":[
        {
            "category":"Shopping",
            "subcategory":"Used Merchandise",
            "type":"Retail Goods"
        }
    ],
    "sg:phone":"+1 336 885 9143",
    "sg:postcode":"27360",
    "sg:province":"NC",
    "sg:tags":[
        "shop",
        "thrift"
    ],
    "wof:name":"Second Avenue",
    "wof:placetype":"venue"
},
  "geometry": {"coordinates":[-80.062279,35.90796],"type":"Point"}
}