{
  "type": "Feature",
  "properties": {
    "iso:country":"US",
    "sg:address":"319 Dallas Young Rd",
    "sg:city":"Bakersville",
    "sg:classifiers":[
        {
            "category":"Travel",
            "subcategory":"Hotels & Motels",
            "type":"Entertainment"
        }
    ],
    "sg:phone":"+1 828 688 9333",
    "sg:postcode":"28705",
    "sg:province":"NC",
    "sg:tags":[
        "operation",
        "sporting"
    ],
    "wof:name":"Bicycle Inn  The",
    "wof:placetype":"venue"
},
  "geometry": {"coordinates":[-82.130171,36.027428],"type":"Point"}
}