{
  "type": "Feature",
  "properties": {
    "addr:full":"302 W Main St Carrboro NC 27510",
    "addr:housenumber":"302",
    "addr:postcode":"27510",
    "addr:street":"W Main St",
    "iso:country":"US",
    "sg:address":"302 W Main St",
    "sg:city":"Carrboro",
    "sg:classifiers":[
        {
            "category":"Cafe",
            "type":"Food & Drink"
        }
    ],
    "sg:menulink":"http://www.allmenus.com/nc/chapel-hill/140803-banditos-mexican-cafe/menu/",
    "sg:phone":"+1 919 932 1942",
    "sg:postcode":"27510",
    "sg:province":"NC",
    "sg:tags":[
        "mexican"
    ],
    "wof:name":"Banditos Mexican Cafe",
    "wof:placetype":"venue"
},
  "geometry": {"coordinates":[-79.07705900000001,35.911652],"type":"Point"}
}