{
  "type": "Feature",
  "properties": {
    "addr:full":"1300 Andover Rd Charlotte NC 28211",
    "addr:housenumber":"1300",
    "addr:postcode":"28211",
    "addr:street":"Andover Rd",
    "iso:country":"US",
    "sg:address":"1300 Andover Rd",
    "sg:city":"Charlotte",
    "sg:classifiers":[
        {
            "category":"Building & Trades",
            "subcategory":"Construction",
            "type":"Services"
        }
    ],
    "sg:phone":"+1 704 362 2832",
    "sg:postcode":"28211",
    "sg:province":"NC",
    "sg:tags":[
        "house"
    ],
    "wof:name":"Hudson Builders Inc",
    "wof:placetype":"venue"
},
  "geometry": {"coordinates":[-80.809746,35.178646],"type":"Point"}
}