{
  "type": "Feature",
  "properties": {
    "addr:full":"509 E Main Ave Taylorsville NC 28681",
    "addr:housenumber":"509",
    "addr:postcode":"28681",
    "addr:street":"E Main Ave",
    "iso:country":"US",
    "sg:address":"509 E Main Ave",
    "sg:city":"Taylorsville",
    "sg:classifiers":[
        {
            "category":"Personal",
            "subcategory":"Beauty Salon",
            "type":"Services"
        }
    ],
    "sg:phone":"+1 828 635 0200",
    "sg:postcode":"28681",
    "sg:province":"NC",
    "wof:name":"Fox Styling Co",
    "wof:placetype":"venue"
},
  "geometry": {"coordinates":[-81.166596,35.921797],"type":"Point"}
}