{
  "type": "Feature",
  "properties": {
    "iso:country":"US",
    "sg:address":"199 Wilkesboro Ave",
    "sg:city":"North Wilkesboro",
    "sg:classifiers":[
        {
            "category":"Recreation",
            "type":"Entertainment"
        }
    ],
    "sg:phone":"+1   ",
    "sg:postcode":"28659",
    "sg:province":"NC",
    "wof:name":"River Trippers Canoe Outf",
    "wof:placetype":"venue"
},
  "geometry": {"coordinates":[-81.14365599999999,36.157401],"type":"Point"}
}