{
  "type": "Feature",
  "properties": {
    "addr:full":"3311 Guess Rd Durham NC 27705",
    "addr:housenumber":"3311",
    "addr:postcode":"27705",
    "addr:street":"Guess Rd",
    "iso:country":"US",
    "sg:address":"3311 Guess Rd",
    "sg:city":"Durham",
    "sg:classifiers":[
        {
            "category":"Retail",
            "subcategory":"Repair Shop",
            "type":"Services"
        }
    ],
    "sg:phone":"+1 919 471 2070",
    "sg:postcode":"27705",
    "sg:province":"NC",
    "sg:tags":[
        "cleaners",
        "parts",
        "vacuum"
    ],
    "wof:name":"Kirby Co",
    "wof:placetype":"venue"
},
  "geometry": {"coordinates":[-78.929665,36.039549],"type":"Point"}
}