{
  "type": "Feature",
  "properties": {
    "addr:full":"3146 US Hwy 117 Magnolia NC 28453",
    "addr:housenumber":"3146",
    "addr:postcode":"28453",
    "addr:street":"Us Hwy 117",
    "iso:country":"US",
    "sg:address":"3146 US Hwy 117",
    "sg:city":"Magnolia",
    "sg:classifiers":[
        {
            "category":"Freight",
            "type":"Transportation"
        }
    ],
    "sg:phone":"+1 910 289 2823",
    "sg:postcode":"28453",
    "sg:province":"NC",
    "sg:tags":[
        "operator",
        "local",
        "trucking"
    ],
    "wof:name":"Wilson & Sons Trucking",
    "wof:placetype":"venue"
},
  "geometry": {"coordinates":[-78.043735,34.875225],"type":"Point"}
}