{
  "type": "Feature",
  "properties": {
    "iso:country":"US",
    "sg:address":"909 New Leicester Hwy",
    "sg:city":"Asheville",
    "sg:classifiers":[
        {
            "category":"Personal",
            "subcategory":"Beauty Salon",
            "type":"Services"
        }
    ],
    "sg:phone":"+1 828 683 6776",
    "sg:postcode":"28806",
    "sg:province":"NC",
    "wof:name":"Extremes",
    "wof:placetype":"venue"
},
  "geometry": {"coordinates":[-82.64758399999999,35.614519],"type":"Point"}
}