{
  "type": "Feature",
  "properties": {
    "iso:country":"US",
    "sg:address":"407 Norwalk St",
    "sg:city":"Greensboro",
    "sg:classifiers":[
        {
            "category":"Manufacturing",
            "subcategory":"Printing",
            "type":"Manufacturing & Wholesale Goods"
        }
    ],
    "sg:phone":"+1 336 547 8970",
    "sg:postcode":"27407",
    "sg:province":"NC",
    "sg:tags":[
        "publisher",
        "custom"
    ],
    "wof:name":"Vitality Communications",
    "wof:placetype":"venue"
},
  "geometry": {"coordinates":[-79.870503,36.063909],"type":"Point"}
}