{
  "type": "Feature",
  "properties": {
    "iso:country":"US",
    "sg:address":"108 S Reilly Rd",
    "sg:city":"Fayetteville",
    "sg:classifiers":[
        {
            "category":"Home & Garden",
            "subcategory":"Hardware",
            "type":"Retail Goods"
        }
    ],
    "sg:phone":"+1 910 864 3462",
    "sg:postcode":"28314",
    "sg:province":"NC",
    "sg:tags":[
        "lawn",
        "supply"
    ],
    "wof:name":"True Value Hardware",
    "wof:placetype":"venue"
},
  "geometry": {"coordinates":[-79.01017299999999,35.081368],"type":"Point"}
}