{
  "type": "Feature",
  "properties": {
    "iso:country":"US",
    "sg:address":"1818 Sharpe Rd",
    "sg:city":"Greensboro",
    "sg:classifiers":[
        {
            "category":"Professional",
            "type":"Services"
        }
    ],
    "sg:phone":"+1 336 373 0511",
    "sg:postcode":"27406",
    "sg:province":"NC",
    "wof:name":"Mayos Christian Brothers Home",
    "wof:placetype":"venue"
},
  "geometry": {"coordinates":[-79.73003300000001,36.048663],"type":"Point"}
}