{
  "type": "Feature",
  "properties": {
    "iso:country":"US",
    "sg:address":"6344 Burnt Poplar Rd",
    "sg:city":"Greensboro",
    "sg:classifiers":[
        {
            "category":"Wholesale",
            "subcategory":"Machinery & Supplies",
            "type":"Manufacturing & Wholesale Goods"
        }
    ],
    "sg:phone":"+1 336 852 2424",
    "sg:postcode":"27409",
    "sg:province":"NC",
    "sg:tags":[
        "equipment",
        "industrial"
    ],
    "wof:name":"Hughes Supply Div 007 T",
    "wof:placetype":"venue"
},
  "geometry": {"coordinates":[-79.93924699999999,36.075184],"type":"Point"}
}