{
  "type": "Feature",
  "properties": {
    "iso:country":"US",
    "sg:address":"2431 Leggett Rd",
    "sg:city":"Rocky Mount",
    "sg:phone":"+1 252 446 5487",
    "sg:postcode":"27801",
    "sg:province":"NC",
    "sg:tags":[
        "farm"
    ],
    "wof:name":"Irvin Rackley",
    "wof:placetype":"venue"
},
  "geometry": {"coordinates":[-77.743843,35.965849],"type":"Point"}
}