{
  "type": "Feature",
  "properties": {
    "addr:full":"40 Odell School Rd Concord NC 28027",
    "addr:housenumber":"40",
    "addr:postcode":"28027",
    "addr:street":"Odell School Rd",
    "iso:country":"US",
    "sg:address":"40 Odell School Rd",
    "sg:city":"Concord",
    "sg:classifiers":[
        {
            "category":"Home & Garden",
            "subcategory":"Building Materials",
            "type":"Retail Goods"
        }
    ],
    "sg:phone":"+1 704 786 4050",
    "sg:postcode":"28027",
    "sg:province":"NC",
    "sg:tags":[
        "glass",
        "window",
        "commercial",
        "residential",
        "plate"
    ],
    "sg:website":"www.futureglassandmirror.com",
    "wof:name":"Future Glass and Mirror LLC",
    "wof:placetype":"venue"
},
  "geometry": {"coordinates":[-80.709614,35.41319],"type":"Point"}
}