{
  "type": "Feature",
  "properties": {
    "addr:full":"8005 Maremont Ct Charlotte NC 28270",
    "addr:housenumber":"8005",
    "addr:postcode":"28270",
    "addr:street":"Maremont Ct",
    "iso:country":"US",
    "sg:address":"8005 Maremont Ct",
    "sg:city":"Charlotte",
    "sg:classifiers":[
        {
            "category":"Professional",
            "subcategory":"Accounting & Tax Preparation",
            "type":"Services"
        }
    ],
    "sg:phone":"+1 704 541 5333",
    "sg:postcode":"28270",
    "sg:province":"NC",
    "sg:tags":[
        "accountant"
    ],
    "wof:name":"Matthews Group LLC",
    "wof:placetype":"venue"
},
  "geometry": {"coordinates":[-80.77448099999999,35.098888],"type":"Point"}
}