{
  "type": "Feature",
  "properties": {
    "addr:full":"602 N Spence Ave Goldsboro NC 27534",
    "addr:housenumber":"602",
    "addr:postcode":"27534",
    "addr:street":"N Spence Ave",
    "iso:country":"US",
    "sg:address":"602 N Spence Ave",
    "sg:city":"Goldsboro",
    "sg:phone":"+1 919 751 1993",
    "sg:postcode":"27534",
    "sg:province":"NC",
    "sg:website":"http://national.citysearch.com/profile/external/6164029/goldsboro_nc/precision_tune_auto_care.html?publisher=yellowpages&reference_id=1&placement=ypwebsitemip",
    "wof:name":"Precision Tune Auto Care",
    "wof:placetype":"venue"
},
  "geometry": {"coordinates":[-77.94687399999999,35.378401],"type":"Point"}
}