{
  "type": "Feature",
  "properties": {
    "addr:full":"8628 Cornwall Rd Oxford NC 27565",
    "addr:housenumber":"8628",
    "addr:postcode":"27565",
    "addr:street":"Cornwall Rd",
    "iso:country":"US",
    "sg:address":"8628 Cornwall Rd",
    "sg:city":"Oxford",
    "sg:classifiers":[
        {
            "category":"Shopping",
            "subcategory":"Computers & Home Electronics",
            "type":"Retail Goods"
        }
    ],
    "sg:phone":"+1 919 693 6582",
    "sg:postcode":"27565",
    "sg:province":"NC",
    "sg:tags":[
        "equipment",
        "satellite",
        "system"
    ],
    "wof:name":"Elliott's",
    "wof:placetype":"venue"
},
  "geometry": {"coordinates":[-78.664326,36.469483],"type":"Point"}
}