{
  "type": "Feature",
  "properties": {
    "addr:full":"3736 Angier Ave Durham NC 27703",
    "addr:housenumber":"3736",
    "addr:postcode":"27703",
    "addr:street":"Angier Ave",
    "iso:country":"US",
    "sg:address":"3736 Angier Ave",
    "sg:city":"Durham",
    "sg:classifiers":[
        {
            "category":"Retail",
            "subcategory":"Auto Repair",
            "type":"Services"
        }
    ],
    "sg:phone":"+1 919 596 9588",
    "sg:postcode":"27703",
    "sg:province":"NC",
    "sg:tags":[
        "repairing",
        "automobile"
    ],
    "wof:name":"Woods Automotive Inc",
    "wof:placetype":"venue"
},
  "geometry": {"coordinates":[-78.851547,35.954502],"type":"Point"}
}