{
  "type": "Feature",
  "properties": {
    "addr:full":"5004 Towergate Dr NW Winston Salem NC 27106",
    "addr:postcode":"5004;27106",
    "addr:street":"Towergate Dr Nw",
    "iso:country":"US",
    "sg:address":"5004 Towergate Dr NW",
    "sg:city":"Winston Salem",
    "sg:classifiers":[
        {
            "category":"Professional",
            "type":"Services"
        }
    ],
    "sg:phone":"+1 336 399 9719",
    "sg:postcode":"27106",
    "sg:province":"NC",
    "wof:name":"J J & J Svc",
    "wof:placetype":"venue"
},
  "geometry": {"coordinates":[-80.31385899999999,36.163613],"type":"Point"}
}