{
  "type": "Feature",
  "properties": {
    "iso:country":"US",
    "sg:address":"6000 Carnegie Blvd",
    "sg:city":"Charlotte",
    "sg:classifiers":[
        {
            "category":"Building & Trades",
            "subcategory":"Equipment Rental",
            "type":"Services"
        }
    ],
    "sg:phone":"+1   ",
    "sg:postcode":"28209",
    "sg:province":"NC",
    "wof:name":"Maersk Equipment Service Inc",
    "wof:placetype":"venue"
},
  "geometry": {"coordinates":[-80.839338,35.155765],"type":"Point"}
}