{
  "type": "Feature",
  "properties": {
    "iso:country":"US",
    "sg:address":"6520 Pensford Ln",
    "sg:city":"Charlotte",
    "sg:classifiers":[
        {
            "category":"Professional",
            "subcategory":"Management & Consulting",
            "type":"Services"
        }
    ],
    "sg:phone":"+1 704 367 1172",
    "sg:postcode":"28270",
    "sg:province":"NC",
    "sg:tags":[
        "marketing",
        "consultant"
    ],
    "wof:name":"Marketing Extension Inc",
    "wof:placetype":"venue"
},
  "geometry": {"coordinates":[-80.776819,35.120685],"type":"Point"}
}