{
  "type": "Feature",
  "properties": {
    "addr:full":"65 Paragon Pkwy Clyde NC 28721",
    "addr:housenumber":"65",
    "addr:postcode":"28721",
    "addr:street":"Paragon Pkwy",
    "iso:country":"US",
    "sg:address":"65 Paragon Pkwy",
    "sg:city":"Clyde",
    "sg:classifiers":[
        {
            "category":"Restaurant",
            "type":"Food & Drink"
        }
    ],
    "sg:menulink":"http://www.allmenus.com/nc/waynesville/191171-burger-king/menu/",
    "sg:phone":"+1 828 452 1910",
    "sg:postcode":"28721",
    "sg:province":"NC",
    "sg:tags":[
        "burger",
        "american"
    ],
    "wof:name":"Burger King",
    "wof:placetype":"venue"
},
  "geometry": {"coordinates":[-82.95609899999999,35.524654],"type":"Point"}
}