{
  "type": "Feature",
  "properties": {
    "addr:full":"1317 Plaza Dr Burlington NC 27215",
    "addr:housenumber":"1317",
    "addr:postcode":"27215",
    "addr:street":"Plaza Dr",
    "iso:country":"US",
    "sg:address":"1317 Plaza Dr",
    "sg:city":"Burlington",
    "sg:classifiers":[
        {
            "category":"Home & Garden",
            "subcategory":"Furniture",
            "type":"Retail Goods"
        }
    ],
    "sg:phone":"+1 336 226 2343",
    "sg:postcode":"27215",
    "sg:province":"NC",
    "wof:name":"Welcome Home",
    "wof:placetype":"venue"
},
  "geometry": {"coordinates":[-79.431403,36.066394],"type":"Point"}
}