{
  "type": "Feature",
  "properties": {
    "addr:full":"2379 US Hwy 13 N Goldsboro NC 27534",
    "addr:housenumber":"2379",
    "addr:postcode":"27534",
    "addr:street":"Us Hwy 13 N",
    "iso:country":"US",
    "sg:address":"2379 US Hwy 13 N",
    "sg:city":"Goldsboro",
    "sg:classifiers":[
        {
            "category":"Retail",
            "subcategory":"Auto Repair",
            "type":"Services"
        }
    ],
    "sg:phone":"+1   ",
    "sg:postcode":"27534",
    "sg:province":"NC",
    "sg:tags":[
        "general"
    ],
    "wof:name":"Mike Saws",
    "wof:placetype":"venue"
},
  "geometry": {"coordinates":[-77.90209400000001,35.400672],"type":"Point"}
}