{
  "type": "Feature",
  "properties": {
    "iso:country":"US",
    "sg:address":"1231 Eastchester Dr",
    "sg:city":"High Point",
    "sg:classifiers":[
        {
            "category":"Shopping",
            "subcategory":"Clothing, Apparel, & Fashions",
            "type":"Retail Goods"
        }
    ],
    "sg:phone":"+1 336 887 6298",
    "sg:postcode":"27265",
    "sg:province":"NC",
    "wof:name":"Chico's Fas-Inc",
    "wof:placetype":"venue"
},
  "geometry": {"coordinates":[-79.998279,35.992836],"type":"Point"}
}