{
  "type": "Feature",
  "properties": {
    "addr:full":"5502 Grapevine Ct Greensboro NC 27405",
    "addr:housenumber":"5502",
    "addr:postcode":"27405",
    "addr:street":"Grapevine Ct",
    "iso:country":"US",
    "sg:address":"5502 Grapevine Ct",
    "sg:city":"Greensboro",
    "sg:classifiers":[
        {
            "category":"Organizations",
            "subcategory":"Religious Organization",
            "type":"Services"
        }
    ],
    "sg:phone":"+1   ",
    "sg:postcode":"27405",
    "sg:province":"NC",
    "wof:name":"Building Lives Inc",
    "wof:placetype":"venue"
},
  "geometry": {"coordinates":[-79.716005,36.155711],"type":"Point"}
}