{
  "type": "Feature",
  "properties": {
    "iso:country":"US",
    "sg:address":"1698 E Arlington Blvd",
    "sg:city":"Greenville",
    "sg:classifiers":[
        {
            "category":"Professional",
            "type":"Services"
        }
    ],
    "sg:phone":"+1 252 321 2020",
    "sg:postcode":"27858",
    "sg:province":"NC",
    "wof:name":"R Kent Stewart Inc",
    "wof:placetype":"venue"
},
  "geometry": {"coordinates":[-77.358857,35.57148],"type":"Point"}
}