{
  "type": "Feature",
  "properties": {
    "iso:country":"US",
    "sg:address":"3200 Union Rd",
    "sg:city":"Gastonia",
    "sg:classifiers":[
        {
            "category":"Retail",
            "subcategory":"Veterinary Services",
            "type":"Services"
        }
    ],
    "sg:phone":"+1 704 867 8318",
    "sg:postcode":"28056",
    "sg:province":"NC",
    "wof:name":"Forest Brook Animal Hlth Care",
    "wof:placetype":"venue"
},
  "geometry": {"coordinates":[-81.16513399999999,35.208864],"type":"Point"}
}