{
  "type": "Feature",
  "properties": {
    "iso:country":"US",
    "sg:address":"2 Echoview Cir",
    "sg:city":"Lexington",
    "sg:classifiers":[
        {
            "category":"Building & Trades",
            "subcategory":"Construction",
            "type":"Services"
        }
    ],
    "sg:phone":"+1 336 248 4980",
    "sg:postcode":"27292",
    "sg:province":"NC",
    "sg:tags":[
        "painting",
        "sandblasting",
        "contractor"
    ],
    "wof:name":"Simco Commercial & Indus Pntg",
    "wof:placetype":"venue"
},
  "geometry": {"coordinates":[-80.227487,35.797654],"type":"Point"}
}