{
  "type": "Feature",
  "properties": {
    "addr:full":"109 Gawain Rd Greenville NC 27858",
    "addr:housenumber":"109",
    "addr:postcode":"27858",
    "addr:street":"Gawain Rd",
    "iso:country":"US",
    "sg:address":"109 Gawain Rd",
    "sg:city":"Greenville",
    "sg:classifiers":[
        {
            "category":"Real Estate",
            "subcategory":"Real Estate Operator",
            "type":"Services"
        }
    ],
    "sg:phone":"+1 252 353 1061",
    "sg:postcode":"27858",
    "sg:province":"NC",
    "sg:tags":[
        "building",
        "nonresidential"
    ],
    "wof:name":"Dreamscape Properties LLC",
    "wof:placetype":"venue"
},
  "geometry": {"coordinates":[-77.334535,35.574928],"type":"Point"}
}