{
  "type": "Feature",
  "properties": {
    "iso:country":"US",
    "sg:address":"505 S Park St",
    "sg:city":"Asheboro",
    "sg:classifiers":[
        {
            "category":"Social Services",
            "subcategory":"Child Care",
            "type":"Services"
        }
    ],
    "sg:phone":"+1   ",
    "sg:postcode":"27203",
    "sg:province":"NC",
    "sg:tags":[
        "day"
    ],
    "wof:name":"After School Care At St Johns",
    "wof:placetype":"venue"
},
  "geometry": {"coordinates":[-79.820353,35.70122],"type":"Point"}
}