{
  "type": "Feature",
  "properties": {
    "addr:full":"100 Highlands Manor Ct Enka NC 28741",
    "addr:housenumber":"100",
    "addr:postcode":"28741",
    "addr:street":"Highlands Manor Ct",
    "iso:country":"US",
    "sg:address":"100 Highlands Manor Ct",
    "sg:city":"Enka",
    "sg:classifiers":[
        {
            "category":"Professional",
            "type":"Services"
        }
    ],
    "sg:phone":"+1 828 667 3253",
    "sg:postcode":"28741",
    "sg:province":"NC",
    "sg:tags":[
        "establishment"
    ],
    "wof:name":"West Carolina Freightliner Inc",
    "wof:placetype":"venue"
},
  "geometry": {"coordinates":[-83.193579,35.053649],"type":"Point"}
}