{
  "type": "Feature",
  "properties": {
    "iso:country":"US",
    "sg:address":"47 Forga Plz Lp",
    "sg:city":"Waynesville",
    "sg:classifiers":[
        {
            "category":"Shopping",
            "subcategory":"Computers & Home Electronics",
            "type":"Retail Goods"
        }
    ],
    "sg:phone":"+1 828 452 3835",
    "sg:postcode":"28786",
    "sg:province":"NC",
    "sg:tags":[
        "television",
        "radio"
    ],
    "wof:name":"Doug's TV",
    "wof:placetype":"venue"
},
  "geometry": {"coordinates":[-83.007324,35.48101],"type":"Point"}
}