{
  "type": "Feature",
  "properties": {
    "addr:full":"4716 Ridge Water Ct Holly Springs NC 27540",
    "addr:housenumber":"4716",
    "addr:postcode":"27540",
    "addr:street":"Ridge Water Ct",
    "iso:country":"US",
    "sg:address":"4716 Ridge Water Ct",
    "sg:city":"Holly Springs",
    "sg:classifiers":[
        {
            "category":"Professional",
            "subcategory":"Management & Consulting",
            "type":"Services"
        }
    ],
    "sg:phone":"+1 919 557 2371",
    "sg:postcode":"27540",
    "sg:province":"NC",
    "sg:tags":[
        "investor"
    ],
    "wof:name":"Entree Network LLC",
    "wof:placetype":"venue"
},
  "geometry": {"coordinates":[-78.79715400000001,35.650566],"type":"Point"}
}