{
  "type": "Feature",
  "properties": {
    "addr:full":"5 W Main St Franklin NC 28734",
    "addr:housenumber":"5",
    "addr:postcode":"nc 28734",
    "addr:street":"W Main St",
    "iso:country":"US",
    "sg:address":"5 W Main St",
    "sg:city":"Franklin",
    "sg:classifiers":[
        {
            "category":"Government",
            "subcategory":"Office",
            "type":"Public Place"
        }
    ],
    "sg:phone":"+1 828 349 2042",
    "sg:postcode":"28734",
    "sg:province":"NC",
    "sg:tags":[
        "county"
    ],
    "wof:name":"Macon County Clerk Of Court",
    "wof:placetype":"venue"
},
  "geometry": {"coordinates":[-83.38124000000001,35.181941],"type":"Point"}
}