{
  "type": "Feature",
  "properties": {
    "addr:full":"126 Roby Poe Rd Crumpler NC 28617",
    "addr:housenumber":"126",
    "addr:postcode":"28617",
    "addr:street":"Roby Poe Rd",
    "iso:country":"US",
    "sg:address":"126 Roby Poe Rd",
    "sg:city":"Crumpler",
    "sg:classifiers":[
        {
            "category":"Banks & Credit Unions",
            "subcategory":"Bank",
            "type":"Services"
        }
    ],
    "sg:phone":"+1 336 982 6020",
    "sg:postcode":"28617",
    "sg:province":"NC",
    "sg:tags":[
        "loan",
        "real estate"
    ],
    "wof:name":"Mt Jefferson Mortgage",
    "wof:placetype":"venue"
},
  "geometry": {"coordinates":[-81.421931,36.438862],"type":"Point"}
}