{
  "type": "Feature",
  "properties": {
    "addr:full":"912 E Hargett St Raleigh NC 27601",
    "addr:housenumber":"912",
    "addr:postcode":"27601",
    "addr:street":"E Hargett St",
    "iso:country":"US",
    "sg:address":"912 E Hargett St",
    "sg:city":"Raleigh",
    "sg:classifiers":[
        {
            "category":"Retail",
            "subcategory":"Self-service Laundry",
            "type":"Services"
        }
    ],
    "sg:phone":"+1   ",
    "sg:postcode":"27601",
    "sg:province":"NC",
    "sg:tags":[
        "coin"
    ],
    "wof:name":"Hargett Street Laundromat",
    "wof:placetype":"venue"
},
  "geometry": {"coordinates":[-78.623942,35.77768],"type":"Point"}
}