{
  "type": "Feature",
  "properties": {
    "addr:full":"15158 Yarmouth Rd Charlotte NC 28227",
    "addr:housenumber":"15158",
    "addr:postcode":"28227",
    "addr:street":"Yarmouth Rd",
    "iso:country":"US",
    "sg:address":"15158 Yarmouth Rd",
    "sg:city":"Charlotte",
    "sg:classifiers":[
        {
            "category":"Building & Trades",
            "subcategory":"Construction",
            "type":"Services"
        }
    ],
    "sg:phone":"+1 704 564 3925",
    "sg:postcode":"28227",
    "sg:province":"NC",
    "sg:tags":[
        "house"
    ],
    "wof:name":"Alvaro Montalvo Const Co",
    "wof:placetype":"venue"
},
  "geometry": {"coordinates":[-80.65353399999999,35.140432],"type":"Point"}
}