{
  "type": "Feature",
  "properties": {
    "iso:country":"US",
    "sg:address":"161 Salisbury St",
    "sg:city":"Robbins",
    "sg:classifiers":[
        {
            "category":"Home & Garden",
            "subcategory":"Carpets & Floor Coverings",
            "type":"Retail Goods"
        }
    ],
    "sg:phone":"+1 910 948 3921",
    "sg:postcode":"27325",
    "sg:province":"NC",
    "sg:tags":[
        "flooring"
    ],
    "wof:name":"Southern Flrcvg Interiors Inc",
    "wof:placetype":"venue"
},
  "geometry": {"coordinates":[-79.589006,35.433634],"type":"Point"}
}