{
  "type": "Feature",
  "properties": {
    "iso:country":"US",
    "sg:address":"2225 Old Grantham Rd",
    "sg:city":"Goldsboro",
    "sg:classifiers":[
        {
            "category":"Farming",
            "subcategory":"Farm",
            "type":"Manufacturing & Wholesale Goods"
        }
    ],
    "sg:phone":"+1 919 689 2556",
    "sg:postcode":"27530",
    "sg:province":"NC",
    "sg:tags":[
        "crop",
        "general"
    ],
    "wof:name":"Williams Farms Inc",
    "wof:placetype":"venue"
},
  "geometry": {"coordinates":[-78.115697,35.331779],"type":"Point"}
}