{
  "type": "Feature",
  "properties": {
    "iso:country":"US",
    "sg:address":"107 Brooks Ave",
    "sg:city":"Rockingham",
    "sg:classifiers":[
        {
            "category":"Manufacturing",
            "subcategory":"Food",
            "type":"Manufacturing & Wholesale Goods"
        }
    ],
    "sg:phone":"+1 910 895 0682",
    "sg:postcode":"28379",
    "sg:province":"NC",
    "sg:tags":[
        "product",
        "rice",
        "cup"
    ],
    "wof:name":"International Snacks & Sales",
    "wof:placetype":"venue"
},
  "geometry": {"coordinates":[-79.75331199999999,34.941862],"type":"Point"}
}