{
  "type": "Feature",
  "properties": {
    "addr:full":"1456 Worthington Rd Greenville NC 27858",
    "addr:housenumber":"1456",
    "addr:postcode":"27858",
    "addr:street":"Worthington Rd",
    "iso:country":"US",
    "sg:address":"1456 Worthington Rd",
    "sg:city":"Greenville",
    "sg:classifiers":[
        {
            "category":"Autos & Motor Vehicles",
            "subcategory":"Automobile Sales",
            "type":"Retail Goods"
        }
    ],
    "sg:phone":"+1 252 321 1236",
    "sg:postcode":"27858",
    "sg:province":"NC",
    "sg:tags":[
        "car",
        "dealer"
    ],
    "wof:name":"Right Myer Motors",
    "wof:placetype":"venue"
},
  "geometry": {"coordinates":[-77.348271,35.531762],"type":"Point"}
}