{
  "type": "Feature",
  "properties": {
    "addr:full":"260 Blueberry Hill Dr Statesville NC 28625",
    "addr:housenumber":"260",
    "addr:postcode":"28625",
    "addr:street":"Blueberry Hill Dr",
    "iso:country":"US",
    "sg:address":"260 Blueberry Hill Dr",
    "sg:city":"Statesville",
    "sg:classifiers":[
        {
            "category":"Professional",
            "subcategory":"Business Services",
            "type":"Services"
        }
    ],
    "sg:phone":"+1   ",
    "sg:postcode":"28625",
    "sg:province":"NC",
    "wof:name":"Rf Trevisan Enterprises Inc",
    "wof:placetype":"venue"
},
  "geometry": {"coordinates":[-80.74955,35.839095],"type":"Point"}
}