{
  "type": "Feature",
  "properties": {
    "iso:country":"US",
    "sg:address":"217 Pamlico Dr",
    "sg:city":"Washington",
    "sg:classifiers":[
        {
            "category":"Building & Trades",
            "subcategory":"Plumbing",
            "type":"Services"
        }
    ],
    "sg:phone":"+1 252 946 6922",
    "sg:postcode":"27889",
    "sg:province":"NC",
    "sg:tags":[
        "conditioning",
        "air",
        "system",
        "contractor"
    ],
    "wof:name":"Custom Air Systems",
    "wof:placetype":"venue"
},
  "geometry": {"coordinates":[-77.01169899999999,35.532104],"type":"Point"}
}