{
  "type": "Feature",
  "properties": {
    "addr:full":"9116 Moss Cove Ct Charlotte NC 28227",
    "addr:postcode":"9116;28227",
    "addr:street":"Moss Cove Ct",
    "iso:country":"US",
    "sg:address":"9116 Moss Cove Ct",
    "sg:city":"Charlotte",
    "sg:classifiers":[
        {
            "category":"Food & Beverages",
            "subcategory":"Bakery",
            "type":"Retail Goods"
        }
    ],
    "sg:phone":"+1 704 573 9663",
    "sg:postcode":"28227",
    "sg:province":"NC",
    "sg:tags":[
        "baker"
    ],
    "wof:name":"Cake Creations",
    "wof:placetype":"venue"
},
  "geometry": {"coordinates":[-80.69477000000001,35.182304],"type":"Point"}
}