{
  "type": "Feature",
  "properties": {
    "addr:full":"109 Hiatt Rd Thomasville NC 27360",
    "addr:housenumber":"109",
    "addr:postcode":"27360",
    "addr:street":"Hiatt Rd",
    "iso:country":"US",
    "sg:address":"109 Hiatt Rd",
    "sg:city":"Thomasville",
    "sg:classifiers":[
        {
            "category":"Organizations",
            "subcategory":"Religious Organization",
            "type":"Services"
        }
    ],
    "sg:phone":"+1   ",
    "sg:postcode":"27360",
    "sg:province":"NC",
    "wof:name":"Parsonage",
    "wof:placetype":"venue"
},
  "geometry": {"coordinates":[-80.11430799999999,35.869834],"type":"Point"}
}