{
  "type": "Feature",
  "properties": {
    "iso:country":"US",
    "sg:address":"100 Forest Rd",
    "sg:city":"Oxford",
    "sg:classifiers":[
        {
            "category":"Real Estate",
            "subcategory":"Developer",
            "type":"Services"
        }
    ],
    "sg:phone":"+1 919 693 5462",
    "sg:postcode":"27565",
    "sg:province":"NC",
    "wof:name":"Meadows Family Ltd Partnership",
    "wof:placetype":"venue"
},
  "geometry": {"coordinates":[-78.57587599999999,36.317389],"type":"Point"}
}