{
  "type": "Feature",
  "properties": {
    "addr:full":"1000 N 1st St Albemarle NC 28001",
    "addr:housenumber":"1000",
    "addr:postcode":"28001",
    "addr:street":"N 1St St",
    "iso:country":"US",
    "sg:address":"1000 N 1st St",
    "sg:city":"Albemarle",
    "sg:classifiers":[
        {
            "category":"Government",
            "subcategory":"Office",
            "type":"Public Place"
        }
    ],
    "sg:phone":"+1 704 986 3682",
    "sg:postcode":"28001",
    "sg:province":"NC",
    "sg:tags":[
        "county",
        "program",
        "adm"
    ],
    "wof:name":"Stanly County Economic Dev",
    "wof:placetype":"venue"
},
  "geometry": {"coordinates":[-80.198831,35.367594],"type":"Point"}
}