{
  "type": "Feature",
  "properties": {
    "iso:country":"US",
    "sg:address":"2005 Citation Dr",
    "sg:city":"Garner",
    "sg:classifiers":[
        {
            "category":"Building & Trades",
            "subcategory":"Construction",
            "type":"Services"
        }
    ],
    "sg:phone":"+1 919 662 8220",
    "sg:postcode":"27529",
    "sg:province":"NC",
    "sg:tags":[
        "drywall",
        "contractor"
    ],
    "wof:name":"Interior Motives",
    "wof:placetype":"venue"
},
  "geometry": {"coordinates":[-78.573559,35.726216],"type":"Point"}
}