{
  "type": "Feature",
  "properties": {
    "iso:country":"US",
    "sg:address":"1332 Baton Church Rd",
    "sg:city":"Granite Falls",
    "sg:classifiers":[
        {
            "category":"Organizations",
            "subcategory":"Religious Organization",
            "type":"Services"
        }
    ],
    "sg:phone":"+1 828 728 3563",
    "sg:postcode":"28630",
    "sg:province":"NC",
    "sg:tags":[
        "church"
    ],
    "wof:name":"Baton Baptist Church Inc",
    "wof:placetype":"venue"
},
  "geometry": {"coordinates":[-81.52270799999999,35.805955],"type":"Point"}
}