{
  "type": "Feature",
  "properties": {
    "iso:country":"US",
    "sg:address":"2332 Cpcc Ln",
    "sg:city":"Matthews",
    "sg:classifiers":[
        {
            "category":"Building & Trades",
            "subcategory":"Construction",
            "type":"Services"
        }
    ],
    "sg:phone":"+1 704 821 4293",
    "sg:postcode":"28105",
    "sg:province":"NC",
    "sg:tags":[
        "steel",
        "erection",
        "structural"
    ],
    "wof:name":"Cranes and Company Inc",
    "wof:placetype":"venue"
},
  "geometry": {"coordinates":[-80.690307,35.102635],"type":"Point"}
}