{
  "type": "Feature",
  "properties": {
    "addr:full":"43 Greenwood Rd Asheville NC 28803",
    "addr:housenumber":"43",
    "addr:postcode":"28803",
    "addr:street":"Greenwood Rd",
    "iso:country":"US",
    "sg:address":"43 Greenwood Rd",
    "sg:city":"Asheville",
    "sg:classifiers":[
        {
            "category":"Retail",
            "subcategory":"Animal Services",
            "type":"Services"
        }
    ],
    "sg:phone":"+1 828 648 7078",
    "sg:postcode":"28803",
    "sg:province":"NC",
    "wof:name":"E & L Kennels",
    "wof:placetype":"venue"
},
  "geometry": {"coordinates":[-82.50793,35.562559],"type":"Point"}
}