{
  "type": "Feature",
  "properties": {
    "addr:full":"213 W Railroad St Bethel NC 27812",
    "addr:housenumber":"213",
    "addr:postcode":"27812",
    "addr:street":"W Railroad St",
    "iso:country":"US",
    "sg:address":"213 W Railroad St",
    "sg:city":"Bethel",
    "sg:classifiers":[
        {
            "category":"Health Services",
            "subcategory":"Clinic",
            "type":"Services"
        }
    ],
    "sg:phone":"+1 252 825 3212",
    "sg:postcode":"27812",
    "sg:province":"NC",
    "sg:tags":[
        "home"
    ],
    "wof:name":"Carolina's Home Care",
    "wof:placetype":"venue"
},
  "geometry": {"coordinates":[-77.374894,35.807905],"type":"Point"}
}