{
  "type": "Feature",
  "properties": {
    "iso:country":"US",
    "sg:address":"1184 Sheriff Watson Rd",
    "sg:city":"Sanford",
    "sg:classifiers":[
        {
            "category":"Professional",
            "type":"Services"
        }
    ],
    "sg:phone":"+1 919 499 4137",
    "sg:postcode":"27332",
    "sg:province":"NC",
    "wof:name":"Fletcher F Phillips",
    "wof:placetype":"venue"
},
  "geometry": {"coordinates":[-79.161942,35.401325],"type":"Point"}
}