{
  "type": "Feature",
  "properties": {
    "iso:country":"US",
    "sg:address":"4011 McKinley St",
    "sg:city":"High Point",
    "sg:classifiers":[
        {
            "category":"Building & Trades",
            "subcategory":"Construction",
            "type":"Services"
        }
    ],
    "sg:phone":"+1 336 869 4939",
    "sg:postcode":"27265",
    "sg:province":"NC",
    "sg:tags":[
        "house"
    ],
    "wof:name":"Jim Lain Construction",
    "wof:placetype":"venue"
},
  "geometry": {"coordinates":[-80.004628,36.01756],"type":"Point"}
}