{
  "type": "Feature",
  "properties": {
    "iso:country":"US",
    "sg:address":"4327 Bragg Blvd",
    "sg:city":"Fayetteville",
    "sg:classifiers":[
        {
            "category":"Personal",
            "type":"Services"
        }
    ],
    "sg:phone":"+1   ",
    "sg:postcode":"28303",
    "sg:province":"NC",
    "wof:name":"Extreme Addiction Tattooing",
    "wof:placetype":"venue"
},
  "geometry": {"coordinates":[-78.942567,35.080478],"type":"Point"}
}