{
  "type": "Feature",
  "properties": {
    "addr:full":"221 Union St Cary NC 27511",
    "addr:housenumber":"221",
    "addr:postcode":"27511",
    "addr:street":"Union St",
    "iso:country":"US",
    "sg:address":"221 Union St",
    "sg:city":"Cary",
    "sg:classifiers":[
        {
            "category":"Organizations",
            "subcategory":"Religious Organization",
            "type":"Services"
        }
    ],
    "sg:phone":"+1 919 467 1477",
    "sg:postcode":"27511",
    "sg:province":"NC",
    "sg:website":"www.stpaulscary.org",
    "wof:name":"St Paul's Episcopal Church",
    "wof:placetype":"venue"
},
  "geometry": {"coordinates":[-78.79209899999999,35.7756],"type":"Point"}
}