{
  "type": "Feature",
  "properties": {
    "iso:country":"US",
    "sg:address":"450 S Myrtle School Rd",
    "sg:city":"Gastonia",
    "sg:classifiers":[
        {
            "category":"Organizations",
            "subcategory":"Religious Organization",
            "type":"Services"
        }
    ],
    "sg:phone":"+1   ",
    "sg:postcode":"28052",
    "sg:province":"NC",
    "wof:name":"West Frnklin Ave Baptst Church",
    "wof:placetype":"venue"
},
  "geometry": {"coordinates":[-81.222627,35.25252],"type":"Point"}
}