{
  "type": "Feature",
  "properties": {
    "iso:country":"US",
    "sg:address":"402 Burrington Ave",
    "sg:city":"Southport",
    "sg:classifiers":[
        {
            "category":"Building & Trades",
            "subcategory":"Plumbing",
            "type":"Services"
        }
    ],
    "sg:phone":"+1 910 457 4544",
    "sg:postcode":"28461",
    "sg:province":"NC",
    "sg:tags":[
        "contractor"
    ],
    "wof:name":"Robby W Hewett",
    "wof:placetype":"venue"
},
  "geometry": {"coordinates":[-78.025268,33.921884],"type":"Point"}
}