{
  "type": "Feature",
  "properties": {
    "addr:full":"6315 Brevard Rd Etowah NC 28729",
    "addr:housenumber":"6315",
    "addr:postcode":"28729",
    "addr:street":"Brevard Rd",
    "iso:country":"US",
    "sg:address":"6315 Brevard Rd",
    "sg:city":"Etowah",
    "sg:classifiers":[
        {
            "category":"Home & Garden",
            "subcategory":"Home Furnishings",
            "type":"Retail Goods"
        }
    ],
    "sg:phone":"+1 828 891 5661",
    "sg:postcode":"28729",
    "sg:province":"NC",
    "sg:tags":[
        "equipment",
        "fireplace"
    ],
    "wof:name":"Etowah Fireplace & Patio Inc",
    "wof:placetype":"venue"
},
  "geometry": {"coordinates":[-82.587192,35.318791],"type":"Point"}
}