{
  "type": "Feature",
  "properties": {
    "addr:full":"7448 McIlwaine Rd Huntersville NC 28078",
    "addr:housenumber":"7448",
    "addr:postcode":"28078",
    "addr:street":"Mcilwaine Rd",
    "iso:country":"US",
    "sg:address":"7448 McIlwaine Rd",
    "sg:city":"Huntersville",
    "sg:classifiers":[
        {
            "category":"Education",
            "subcategory":"Dance Studio",
            "type":"Public Place"
        }
    ],
    "sg:phone":"+1   ",
    "sg:postcode":"28078",
    "sg:province":"NC",
    "wof:name":"Cornerstone Dance",
    "wof:placetype":"venue"
},
  "geometry": {"coordinates":[-80.91166800000001,35.388933],"type":"Point"}
}