{
  "type": "Feature",
  "properties": {
    "addr:full":"235 W High Ave High Point NC 27260",
    "addr:housenumber":"235",
    "addr:postcode":"27260",
    "addr:street":"W High Ave",
    "iso:country":"US",
    "sg:address":"235 W High Ave",
    "sg:city":"High Point",
    "sg:classifiers":[
        {
            "category":"Professional",
            "type":"Services"
        },
        {
            "category":"Restaurant",
            "type":"Food & Drink"
        }
    ],
    "sg:phone":"+1 336 889 4271",
    "sg:postcode":"27260",
    "sg:province":"NC",
    "sg:tags":[
        "establishment",
        "eating"
    ],
    "wof:name":"Thanhardt Burger Corp",
    "wof:placetype":"venue"
},
  "geometry": {"coordinates":[-80.010003,35.95496],"type":"Point"}
}