{
  "type": "Feature",
  "properties": {
    "addr:full":"100 Main Ave NW Hickory NC 28601",
    "addr:housenumber":"100",
    "addr:postcode":"28601",
    "addr:street":"Main Ave Nw",
    "iso:country":"US",
    "sg:address":"100 Main Ave NW",
    "sg:city":"Hickory",
    "sg:classifiers":[
        {
            "category":"Building & Trades",
            "subcategory":"Construction",
            "type":"Services"
        }
    ],
    "sg:phone":"+1 828 327 4648",
    "sg:postcode":"28601",
    "sg:province":"NC",
    "sg:tags":[
        "designer"
    ],
    "wof:name":"Berry & Clark Design Assoc",
    "wof:placetype":"venue"
},
  "geometry": {"coordinates":[-81.339657,35.732073],"type":"Point"}
}