{
  "type": "Feature",
  "properties": {
    "iso:country":"US",
    "sg:address":"5614 Weddington Rd",
    "sg:city":"Monroe",
    "sg:classifiers":[
        {
            "category":"Building & Trades",
            "subcategory":"Plumbing",
            "type":"Services"
        }
    ],
    "sg:phone":"+1 704 289 8627",
    "sg:postcode":"28110",
    "sg:province":"NC",
    "sg:tags":[
        "conditioning",
        "air",
        "system",
        "contractor"
    ],
    "wof:name":"Lovin's Heating & Air",
    "wof:placetype":"venue"
},
  "geometry": {"coordinates":[-80.665924,35.006362],"type":"Point"}
}