{
  "type": "Feature",
  "properties": {
    "addr:full":"500 Franklin Sq Chapel Hill NC 27514",
    "addr:housenumber":"500",
    "addr:postcode":"27514",
    "addr:street":"Franklin Sq",
    "iso:country":"US",
    "sg:address":"500 Franklin Sq",
    "sg:city":"Chapel Hill",
    "sg:classifiers":[
        {
            "category":"Health Services",
            "subcategory":"Doctor",
            "type":"Services"
        },
        {
            "category":"Health Services",
            "subcategory":"Clinic",
            "type":"Services"
        }
    ],
    "sg:phone":"+1 919 933 2000",
    "sg:postcode":"27514",
    "sg:province":"NC",
    "sg:tags":[
        "counseling",
        "mental",
        "psychiatrist"
    ],
    "wof:name":"Thomas C Gualtieri MD",
    "wof:placetype":"venue"
},
  "geometry": {"coordinates":[-79.023499,35.9366],"type":"Point"}
}