{
  "type": "Feature",
  "properties": {
    "addr:full":"1000 Patton Avenue Asheville NC 28806",
    "addr:housenumber":"1000",
    "addr:postcode":"28806",
    "addr:street":"Patton Avenue",
    "iso:country":"US",
    "sg:address":"1000 Patton Avenue",
    "sg:city":"Asheville",
    "sg:classifiers":[
        {
            "category":"Fast Food",
            "type":"Food & Drink"
        }
    ],
    "sg:phone":"+1 828 254 1722",
    "sg:postcode":"28806",
    "sg:province":"NC",
    "sg:website":"www.wendys.com/",
    "wof:name":"Wendy's",
    "wof:placetype":"venue"
},
  "geometry": {"coordinates":[-82.590864,35.586707],"type":"Point"}
}