{
  "type": "Feature",
  "properties": {
    "addr:full":"1604 Ebb Dr Wilmington NC 28409",
    "addr:housenumber":"1604",
    "addr:postcode":"28409",
    "addr:street":"Ebb Dr",
    "iso:country":"US",
    "sg:address":"1604 Ebb Dr",
    "sg:city":"Wilmington",
    "sg:classifiers":[
        {
            "category":"Banks & Credit Unions",
            "subcategory":"Investment Brokerage",
            "type":"Services"
        }
    ],
    "sg:phone":"+1 910 392 9190",
    "sg:postcode":"28409",
    "sg:province":"NC",
    "sg:tags":[
        "advisory",
        "management"
    ],
    "wof:name":"Gull Investments LLC",
    "wof:placetype":"venue"
},
  "geometry": {"coordinates":[-77.88290499999999,34.106876],"type":"Point"}
}