{
  "type": "Feature",
  "properties": {
    "addr:full":"160 Log Cabin Rd Waynesville NC 28786",
    "addr:housenumber":"160",
    "addr:postcode":"28786",
    "addr:street":"Log Cabin Rd",
    "iso:country":"US",
    "sg:address":"160 Log Cabin Rd",
    "sg:city":"Waynesville",
    "sg:classifiers":[
        {
            "category":"Retail",
            "subcategory":"Auto Repair",
            "type":"Services"
        }
    ],
    "sg:phone":"+1 828 456 3390",
    "sg:postcode":"28786",
    "sg:province":"NC",
    "sg:tags":[
        "automobile",
        "inspection"
    ],
    "wof:name":"Rogers Automotive",
    "wof:placetype":"venue"
},
  "geometry": {"coordinates":[-83.027303,35.468354],"type":"Point"}
}