{
  "type": "Feature",
  "properties": {
    "iso:country":"US",
    "sg:address":"2041 36th St NE",
    "sg:city":"Hickory",
    "sg:classifiers":[
        {
            "category":"Building & Trades",
            "subcategory":"Construction",
            "type":"Services"
        }
    ],
    "sg:phone":"+1 828 256 4724",
    "sg:postcode":"28601",
    "sg:province":"NC",
    "sg:tags":[
        "hanging",
        "contractor"
    ],
    "wof:name":"Killian Painting",
    "wof:placetype":"venue"
},
  "geometry": {"coordinates":[-81.26740599999999,35.753215],"type":"Point"}
}