{
  "type": "Feature",
  "properties": {
    "addr:full":"302 White Springs Rd Blowing Rock NC 28605",
    "addr:housenumber":"302",
    "addr:postcode":"28605",
    "addr:street":"White Springs Rd",
    "iso:country":"US",
    "sg:address":"302 White Springs Rd",
    "sg:city":"Blowing Rock",
    "sg:classifiers":[
        {
            "category":"Building & Trades",
            "subcategory":"Plumbing",
            "type":"Services"
        }
    ],
    "sg:phone":"+1 828 295 9831",
    "sg:postcode":"28605",
    "sg:province":"NC",
    "sg:tags":[
        "plumbing",
        "contractor"
    ],
    "wof:name":"Bob Johnson Plumbing Co",
    "wof:placetype":"venue"
},
  "geometry": {"coordinates":[-81.723828,36.117788],"type":"Point"}
}