{
  "type": "Feature",
  "properties": {
    "iso:country":"US",
    "sg:address":"3418 Tuckaseegee Rd",
    "sg:city":"Charlotte",
    "sg:classifiers":[
        {
            "category":"Restaurant",
            "type":"Food & Drink"
        }
    ],
    "sg:phone":"+1 704 391 9636",
    "sg:postcode":"28208",
    "sg:province":"NC",
    "sg:tags":[
        "eating"
    ],
    "wof:name":"Soul Shack",
    "wof:placetype":"venue"
},
  "geometry": {"coordinates":[-80.88440900000001,35.245005],"type":"Point"}
}