{
  "type": "Feature",
  "properties": {
    "iso:country":"US",
    "sg:address":"1931 Hatchery Rd",
    "sg:city":"Burlington",
    "sg:classifiers":[
        {
            "category":"Real Estate",
            "subcategory":"Real Estate Agent",
            "type":"Services"
        }
    ],
    "sg:phone":"+1 336 227 4503",
    "sg:postcode":"27215",
    "sg:province":"NC",
    "wof:name":"Bruce Harris Real Estate",
    "wof:placetype":"venue"
},
  "geometry": {"coordinates":[-79.458894,36.059974],"type":"Point"}
}