{
  "type": "Feature",
  "properties": {
    "addr:full":"4802 Main St South Brunswick NC 28470",
    "addr:housenumber":"4802",
    "addr:postcode":"28470",
    "addr:street":"Main St",
    "iso:country":"US",
    "sg:address":"4802 Main St",
    "sg:city":"South Brunswick",
    "sg:classifiers":[
        {
            "category":"Professional",
            "subcategory":"Accounting & Tax Preparation",
            "type":"Services"
        }
    ],
    "sg:phone":"+1 910 754 8510",
    "sg:postcode":"28470",
    "sg:province":"NC",
    "sg:tags":[
        "return",
        "filing"
    ],
    "wof:name":"Jackson Hewitt Tax Svc",
    "wof:placetype":"venue"
},
  "geometry": {"coordinates":[-78.385825,33.973063],"type":"Point"}
}