{
  "type": "Feature",
  "properties": {
    "addr:full":"308 E King St Kings Mountain NC 28086",
    "addr:housenumber":"308",
    "addr:postcode":"28086",
    "addr:street":"E King St",
    "iso:country":"US",
    "sg:address":"308 E King St",
    "sg:city":"Kings Mountain",
    "sg:classifiers":[
        {
            "category":"Insurance",
            "subcategory":"Insurance Agent",
            "type":"Services"
        }
    ],
    "sg:phone":"+1 704 739 1820",
    "sg:postcode":"28086",
    "sg:province":"NC",
    "wof:name":"Allstate Insurance Co",
    "wof:placetype":"venue"
},
  "geometry": {"coordinates":[-81.337226,35.240873],"type":"Point"}
}