{
  "type": "Feature",
  "properties": {
    "addr:full":"2015 S 17th St Wilmington NC 28401",
    "addr:housenumber":"2015",
    "addr:postcode":"28401",
    "addr:street":"S 17Th St",
    "iso:country":"US",
    "sg:address":"2015 S 17th St",
    "sg:city":"Wilmington",
    "sg:classifiers":[
        {
            "category":"Banks & Credit Unions",
            "subcategory":"Bank",
            "type":"Services"
        }
    ],
    "sg:phone":"+1 910 772 8850",
    "sg:postcode":"28401",
    "sg:province":"NC",
    "sg:website":"www.centura.com",
    "wof:name":"RBC Centura Bank",
    "wof:placetype":"venue"
},
  "geometry": {"coordinates":[-77.924447,34.207301],"type":"Point"}
}