{
  "type": "Feature",
  "properties": {
    "addr:full":"3603 Plyler Mill Rd Monroe NC 28112",
    "addr:housenumber":"3603",
    "addr:postcode":"28112",
    "addr:street":"Plyler Mill Rd",
    "iso:country":"US",
    "sg:address":"3603 Plyler Mill Rd",
    "sg:city":"Monroe",
    "sg:classifiers":[
        {
            "category":"Food & Beverages",
            "subcategory":"Groceries & Convenience Stores",
            "type":"Retail Goods"
        }
    ],
    "sg:phone":"+1 704 764 3399",
    "sg:postcode":"28112",
    "sg:province":"NC",
    "wof:name":"Belk's Country Convenience",
    "wof:placetype":"venue"
},
  "geometry": {"coordinates":[-80.57756500000001,34.907384],"type":"Point"}
}