{
  "type": "Feature",
  "properties": {
    "addr:full":"2630 Cattail Cir Fayetteville NC 28312",
    "addr:housenumber":"2630",
    "addr:postcode":"28312",
    "addr:street":"Cattail Cir",
    "iso:country":"US",
    "sg:address":"2630 Cattail Cir",
    "sg:city":"Fayetteville",
    "sg:classifiers":[
        {
            "category":"Real Estate",
            "subcategory":"Real Estate Operator",
            "type":"Services"
        }
    ],
    "sg:phone":"+1 910 223 7515",
    "sg:postcode":"28312",
    "sg:province":"NC",
    "sg:tags":[
        "mobile",
        "home",
        "site"
    ],
    "wof:name":"Cape Fear Estates",
    "wof:placetype":"venue"
},
  "geometry": {"coordinates":[-78.84047099999999,35.037614],"type":"Point"}
}