{
  "type": "Feature",
  "properties": {
    "iso:country":"US",
    "sg:address":"5368 Beach Dr SW",
    "sg:city":"South Brunswick",
    "sg:classifiers":[
        {
            "category":"Real Estate",
            "subcategory":"Real Estate Agent",
            "type":"Services"
        }
    ],
    "sg:phone":"+1 910 755 6016",
    "sg:postcode":"28470",
    "sg:province":"NC",
    "wof:name":"United Country Coastal Homes",
    "wof:placetype":"venue"
},
  "geometry": {"coordinates":[-78.41213399999999,33.916922],"type":"Point"}
}