{
  "type": "Feature",
  "properties": {
    "addr:full":"1511 Harts Chapel Rd Tarboro NC 27886",
    "addr:housenumber":"1511",
    "addr:postcode":"27886",
    "addr:street":"Harts Chapel Rd",
    "iso:country":"US",
    "sg:address":"1511 Harts Chapel Rd",
    "sg:city":"Tarboro",
    "sg:classifiers":[
        {
            "category":"Government",
            "subcategory":"Office",
            "type":"Public Place"
        }
    ],
    "sg:phone":"+1 252 641 2795",
    "sg:postcode":"27886",
    "sg:province":"NC",
    "wof:name":"Harts Chapel Recycling Ctr",
    "wof:placetype":"venue"
},
  "geometry": {"coordinates":[-77.637871,35.916306],"type":"Point"}
}