{
  "type": "Feature",
  "properties": {
    "iso:country":"US",
    "sg:address":"6006 Ball Park Rd",
    "sg:city":"Thomasville",
    "sg:classifiers":[
        {
            "category":"Marine",
            "type":"Transportation"
        }
    ],
    "sg:phone":"+1 336 475 8208",
    "sg:postcode":"27360",
    "sg:province":"NC",
    "sg:tags":[
        "towing"
    ],
    "wof:name":"Southeast Marine & Rescue",
    "wof:placetype":"venue"
},
  "geometry": {"coordinates":[-80.063969,35.912009],"type":"Point"}
}