{
  "type": "Feature",
  "properties": {
    "addr:full":"402 N Norwood St Wallace NC 28466",
    "addr:housenumber":"402",
    "addr:postcode":"28466",
    "addr:street":"N Norwood St",
    "iso:country":"US",
    "sg:address":"402 N Norwood St",
    "sg:city":"Wallace",
    "sg:classifiers":[
        {
            "category":"Real Estate",
            "subcategory":"Real Estate Agent",
            "type":"Services"
        }
    ],
    "sg:phone":"+1 910 285 7454",
    "sg:postcode":"28466",
    "sg:province":"NC",
    "sg:website":"www.goldenkeyrealtyinc.com",
    "wof:name":"RCA Realty",
    "wof:placetype":"venue"
},
  "geometry": {"coordinates":[-77.99466099999999,34.740632],"type":"Point"}
}