{
  "type": "Feature",
  "properties": {
    "addr:full":"9524 Meadowmont Ln Raleigh NC 27615",
    "addr:housenumber":"9524",
    "addr:postcode":"27615",
    "addr:street":"Meadowmont Ln",
    "iso:country":"US",
    "sg:address":"9524 Meadowmont Ln",
    "sg:city":"Raleigh",
    "sg:classifiers":[
        {
            "category":"Wholesale",
            "subcategory":"Non-durable Goods",
            "type":"Manufacturing & Wholesale Goods"
        }
    ],
    "sg:phone":"+1 919 676 7588",
    "sg:postcode":"27615",
    "sg:province":"NC",
    "wof:name":"Carolina Specialty Advg Inc",
    "wof:placetype":"venue"
},
  "geometry": {"coordinates":[-78.59604400000001,35.905738],"type":"Point"}
}