{
  "type": "Feature",
  "properties": {
    "addr:full":"726 3rd Ave NE Conover NC 28613",
    "addr:housenumber":"726",
    "addr:postcode":"28613",
    "addr:street":"3Rd Ave Ne",
    "iso:country":"US",
    "sg:address":"726 3rd Ave NE",
    "sg:city":"Conover",
    "sg:classifiers":[
        {
            "category":"Building & Trades",
            "subcategory":"Construction",
            "type":"Services"
        }
    ],
    "sg:phone":"+1 828 464 4767",
    "sg:postcode":"28613",
    "sg:province":"NC",
    "sg:tags":[
        "house"
    ],
    "wof:name":"Kanipes Home Repair",
    "wof:placetype":"venue"
},
  "geometry": {"coordinates":[-81.207666,35.718757],"type":"Point"}
}