{
  "type": "Feature",
  "properties": {
    "addr:full":"398 Amelia Church Rd Clayton NC 27520",
    "addr:housenumber":"398",
    "addr:postcode":"27520",
    "addr:street":"Amelia Church Rd",
    "iso:country":"US",
    "sg:address":"398 Amelia Church Rd",
    "sg:city":"Clayton",
    "sg:classifiers":[
        {
            "category":"Building & Trades",
            "subcategory":"Landscaping Services",
            "type":"Services"
        }
    ],
    "sg:phone":"+1 919 550 9499",
    "sg:postcode":"27520",
    "sg:province":"NC",
    "sg:tags":[
        "landscape",
        "maintenance"
    ],
    "wof:name":"Crewcuts Landscape Maintenance",
    "wof:placetype":"venue"
},
  "geometry": {"coordinates":[-78.477242,35.649647],"type":"Point"}
}