{
  "type": "Feature",
  "properties": {
    "iso:country":"US",
    "sg:address":"1508 State Hwy 66 S",
    "sg:city":"Westfield",
    "sg:classifiers":[
        {
            "category":"Professional",
            "subcategory":"Business Services",
            "type":"Services"
        }
    ],
    "sg:phone":"+1   ",
    "sg:postcode":"27053",
    "sg:province":"NC",
    "wof:name":"Southern Ozone Systems",
    "wof:placetype":"venue"
},
  "geometry": {"coordinates":[-80.33238799999999,36.418495],"type":"Point"}
}