{
  "type": "Feature",
  "properties": {
    "iso:country":"US",
    "sg:address":"8400 Creedmoor Rd",
    "sg:city":"Raleigh",
    "sg:classifiers":[
        {
            "category":"Food & Beverages",
            "subcategory":"Groceries & Convenience Stores",
            "type":"Retail Goods"
        }
    ],
    "sg:phone":"+1 919 847 7650",
    "sg:postcode":"27615",
    "sg:province":"NC",
    "wof:name":"Handy Hugo 94",
    "wof:placetype":"venue"
},
  "geometry": {"coordinates":[-78.681377,35.905229],"type":"Point"}
}