{
  "type": "Feature",
  "properties": {
    "iso:country":"US",
    "sg:address":"171 Tilley McGee Ln",
    "sg:city":"Pinnacle",
    "sg:classifiers":[
        {
            "category":"Building & Trades",
            "subcategory":"Construction",
            "type":"Services"
        }
    ],
    "sg:phone":"+1 336 325 2739",
    "sg:postcode":"27043",
    "sg:province":"NC",
    "sg:tags":[
        "contractor"
    ],
    "wof:name":"Sherri McGee",
    "wof:placetype":"venue"
},
  "geometry": {"coordinates":[-80.507723,36.317523],"type":"Point"}
}