{
  "type": "Feature",
  "properties": {
    "addr:full":"1846 Frazier Rd Franklin NC 28734",
    "addr:housenumber":"1846",
    "addr:postcode":"nc 28734",
    "addr:street":"Frazier Rd",
    "iso:country":"US",
    "sg:address":"1846 Frazier Rd",
    "sg:city":"Franklin",
    "sg:classifiers":[
        {
            "category":"Real Estate",
            "subcategory":"Real Estate Agent",
            "type":"Services"
        }
    ],
    "sg:phone":"+1 828 369 2900",
    "sg:postcode":"28734",
    "sg:province":"NC",
    "wof:name":"Davis Realty",
    "wof:placetype":"venue"
},
  "geometry": {"coordinates":[-83.351918,35.132969],"type":"Point"}
}