{
  "type": "Feature",
  "properties": {
    "addr:full":"104 Edgedale Ct Kernersville NC 27284",
    "addr:housenumber":"104",
    "addr:postcode":"27284",
    "addr:street":"Edgedale Ct",
    "iso:country":"US",
    "sg:address":"104 Edgedale Ct",
    "sg:city":"Kernersville",
    "sg:classifiers":[
        {
            "category":"Professional",
            "subcategory":"Business Services",
            "type":"Services"
        }
    ],
    "sg:phone":"+1   ",
    "sg:postcode":"27284",
    "sg:province":"NC",
    "wof:name":"Elliotts Kc Enterprises",
    "wof:placetype":"venue"
},
  "geometry": {"coordinates":[-80.085824,36.10603],"type":"Point"}
}