{
  "type": "Feature",
  "properties": {
    "iso:country":"US",
    "sg:address":"169 Riverchase Trl",
    "sg:city":"Todd",
    "sg:classifiers":[
        {
            "category":"Organizations",
            "subcategory":"Religious Organization",
            "type":"Services"
        }
    ],
    "sg:phone":"+1   ",
    "sg:postcode":"28684",
    "sg:province":"NC",
    "wof:name":"World Harvest Ministries",
    "wof:placetype":"venue"
},
  "geometry": {"coordinates":[-81.57805399999999,36.289196],"type":"Point"}
}