{
  "type": "Feature",
  "properties": {
    "iso:country":"US",
    "sg:address":"16701 Northcross Dr",
    "sg:city":"Huntersville",
    "sg:classifiers":[
        {
            "category":"Social Services",
            "subcategory":"Child Care",
            "type":"Services"
        }
    ],
    "sg:phone":"+1 704 896 8942",
    "sg:postcode":"28078",
    "sg:province":"NC",
    "sg:tags":[
        "day"
    ],
    "sg:website":"www.universitychilddevelopment.com",
    "wof:name":"University Child Devmnt Ctr",
    "wof:placetype":"venue"
},
  "geometry": {"coordinates":[-80.874888,35.441788],"type":"Point"}
}