{
  "type": "Feature",
  "properties": {
    "iso:country":"US",
    "sg:address":"379 Harkers Island Rd",
    "sg:city":"Beaufort",
    "sg:classifiers":[
        {
            "category":"Manufacturing",
            "subcategory":"Watercraft",
            "type":"Manufacturing & Wholesale Goods"
        }
    ],
    "sg:phone":"+1 252 728 3903",
    "sg:postcode":"28516",
    "sg:province":"NC",
    "sg:tags":[
        "boat"
    ],
    "wof:name":"Chadwick Boatworks",
    "wof:placetype":"venue"
},
  "geometry": {"coordinates":[-76.552313,34.759732],"type":"Point"}
}