{
  "type": "Feature",
  "properties": {
    "addr:full":"524 Eastwood Dr Gastonia NC 28054",
    "addr:housenumber":"524",
    "addr:postcode":"28054",
    "addr:street":"Eastwood Dr",
    "iso:country":"US",
    "sg:address":"524 Eastwood Dr",
    "sg:city":"Gastonia",
    "sg:classifiers":[
        {
            "category":"Professional",
            "subcategory":"Business Services",
            "type":"Services"
        }
    ],
    "sg:phone":"+1 704 865 2413",
    "sg:postcode":"28054",
    "sg:province":"NC",
    "sg:tags":[
        "interior",
        "consultant",
        "design",
        "decorator"
    ],
    "wof:name":"Interior Designs LTD",
    "wof:placetype":"venue"
},
  "geometry": {"coordinates":[-81.12585799999999,35.256427],"type":"Point"}
}