{
  "type": "Feature",
  "properties": {
    "addr:full":"1006 Arnold St Greensboro NC 27405",
    "addr:housenumber":"1006",
    "addr:postcode":"27405",
    "addr:street":"Arnold St",
    "iso:country":"US",
    "sg:address":"1006 Arnold St",
    "sg:city":"Greensboro",
    "sg:classifiers":[
        {
            "category":"Manufacturing",
            "subcategory":"Printing",
            "type":"Manufacturing & Wholesale Goods"
        }
    ],
    "sg:phone":"+1 336 272 4310",
    "sg:postcode":"27405",
    "sg:province":"NC",
    "sg:tags":[
        "offset"
    ],
    "wof:name":"Johnson Printing & Pubg Co",
    "wof:placetype":"venue"
},
  "geometry": {"coordinates":[-79.76823,36.086219],"type":"Point"}
}