{
  "type": "Feature",
  "properties": {
    "addr:full":"310 Raleigh St Holly Springs NC 27540",
    "addr:housenumber":"310",
    "addr:postcode":"27540",
    "addr:street":"Raleigh St",
    "iso:country":"US",
    "sg:address":"310 Raleigh St",
    "sg:city":"Holly Springs",
    "sg:classifiers":[
        {
            "category":"Organizations",
            "subcategory":"Religious Organization",
            "type":"Services"
        }
    ],
    "sg:phone":"+1   ",
    "sg:postcode":"27540",
    "sg:province":"NC",
    "sg:website":"www.churchaliveag.org",
    "wof:name":"Church Alive",
    "wof:placetype":"venue"
},
  "geometry": {"coordinates":[-78.832643,35.651017],"type":"Point"}
}