{
  "type": "Feature",
  "properties": {
    "addr:full":"1106 Lillington Hwy Spring Lake NC 28390",
    "addr:housenumber":"1106",
    "addr:postcode":"28390",
    "addr:street":"Lillington Hwy",
    "iso:country":"US",
    "sg:address":"1106 Lillington Hwy",
    "sg:city":"Spring Lake",
    "sg:classifiers":[
        {
            "category":"Organizations",
            "subcategory":"Religious Organization",
            "type":"Services"
        }
    ],
    "sg:phone":"+1 910 960 9466",
    "sg:postcode":"28390",
    "sg:province":"NC",
    "sg:tags":[
        "church"
    ],
    "wof:name":"Full Gospel Zion Church",
    "wof:placetype":"venue"
},
  "geometry": {"coordinates":[-78.96447999999999,35.1827],"type":"Point"}
}