{
  "type": "Feature",
  "properties": {
    "addr:full":"1701 Lomond St Winston Salem NC 27127",
    "addr:housenumber":"1701",
    "addr:postcode":"27127",
    "addr:street":"Lomond St",
    "iso:country":"US",
    "sg:address":"1701 Lomond St",
    "sg:city":"Winston Salem",
    "sg:classifiers":[
        {
            "category":"Wholesale",
            "subcategory":"Computers",
            "type":"Manufacturing & Wholesale Goods"
        }
    ],
    "sg:phone":"+1 336 748 0500",
    "sg:postcode":"27127",
    "sg:province":"NC",
    "sg:tags":[
        "communications",
        "datum"
    ],
    "sg:website":"www.blackbox.com",
    "wof:name":"Black Box Network Svc",
    "wof:placetype":"venue"
},
  "geometry": {"coordinates":[-80.232784,36.073751],"type":"Point"}
}