{
  "type": "Feature",
  "properties": {
    "iso:country":"US",
    "sg:address":"3156 Heathstead Pl",
    "sg:city":"Charlotte",
    "sg:classifiers":[
        {
            "category":"Shopping",
            "subcategory":"Clothing, Apparel, & Fashions",
            "type":"Retail Goods"
        }
    ],
    "sg:phone":"+1 704 374 0948",
    "sg:postcode":"28210",
    "sg:province":"NC",
    "sg:tags":[
        "hair",
        "supply"
    ],
    "wof:name":"Dainty Girls",
    "wof:placetype":"venue"
},
  "geometry": {"coordinates":[-80.831298,35.13006],"type":"Point"}
}