{
  "type": "Feature",
  "properties": {
    "addr:full":"1449 Lackey Rd Danbury NC 27016",
    "addr:housenumber":"1449",
    "addr:postcode":"27016",
    "addr:street":"Lackey Rd",
    "iso:country":"US",
    "sg:address":"1449 Lackey Rd",
    "sg:city":"Danbury",
    "sg:classifiers":[
        {
            "category":"Building & Trades",
            "subcategory":"Plumbing",
            "type":"Services"
        }
    ],
    "sg:phone":"+1 336 593 8423",
    "sg:postcode":"27016",
    "sg:province":"NC",
    "sg:tags":[
        "conditioning",
        "air",
        "system",
        "contractor"
    ],
    "wof:name":"Bullins Heating Air & Refrig",
    "wof:placetype":"venue"
},
  "geometry": {"coordinates":[-80.208494,36.496103],"type":"Point"}
}