{
  "type": "Feature",
  "properties": {
    "iso:country":"US",
    "sg:address":"2224 Roxie St NE Ste 24",
    "sg:city":"Kannapolis",
    "sg:classifiers":[
        {
            "category":"Banks & Credit Unions",
            "subcategory":"Financial Services",
            "type":"Services"
        }
    ],
    "sg:phone":"+1 704 784 1436",
    "sg:postcode":"28083",
    "sg:province":"NC",
    "sg:website":"http://www.wellsfargofinancial.com",
    "wof:name":"Wells Fargo Financial",
    "wof:placetype":"venue"
},
  "geometry": {"coordinates":[-80.593338,35.464729],"type":"Point"}
}