{
  "type": "Feature",
  "properties": {
    "addr:full":"140 Wade Duvall Rd Grassy Creek NC 28631",
    "addr:housenumber":"140",
    "addr:postcode":"28631",
    "addr:street":"Wade Duvall Rd",
    "iso:country":"US",
    "sg:address":"140 Wade Duvall Rd",
    "sg:city":"Grassy Creek",
    "sg:classifiers":[
        {
            "category":"Building & Trades",
            "subcategory":"Landscaping Services",
            "type":"Services"
        }
    ],
    "sg:phone":"+1 336 384 2200",
    "sg:postcode":"28631",
    "sg:province":"NC",
    "sg:tags":[
        "landscape",
        "contractor"
    ],
    "wof:name":"Appalachian Landscapes",
    "wof:placetype":"venue"
},
  "geometry": {"coordinates":[-81.475475,36.579593],"type":"Point"}
}