{
  "type": "Feature",
  "properties": {
    "iso:country":"US",
    "sg:address":"3905 New Bern Ave",
    "sg:city":"Raleigh",
    "sg:classifiers":[
        {
            "category":"Education",
            "subcategory":"Special Training",
            "type":"Public Place"
        }
    ],
    "sg:phone":"+1 919 231 3289",
    "sg:postcode":"27610",
    "sg:province":"NC",
    "sg:tags":[
        "tutoring"
    ],
    "wof:name":"Center For Visual Learning",
    "wof:placetype":"venue"
},
  "geometry": {"coordinates":[-78.568816,35.799024],"type":"Point"}
}