{
  "type": "Feature",
  "properties": {
    "addr:full":"5032 Roberson Farm Rd Kernersville NC 27284",
    "addr:housenumber":"5032",
    "addr:postcode":"27284",
    "addr:street":"Roberson Farm Rd",
    "iso:country":"US",
    "sg:address":"5032 Roberson Farm Rd",
    "sg:city":"Kernersville",
    "sg:classifiers":[
        {
            "category":"Home & Garden",
            "subcategory":"Building Materials",
            "type":"Retail Goods"
        },
        {
            "category":"Building & Trades",
            "subcategory":"Construction",
            "type":"Services"
        }
    ],
    "sg:phone":"+1 336 595 3428",
    "sg:postcode":"27284",
    "sg:province":"NC",
    "sg:tags":[
        "carpentry",
        "improvement",
        "contractor"
    ],
    "wof:name":"Pro Formance Plus Inc",
    "wof:placetype":"venue"
},
  "geometry": {"coordinates":[-80.134078,36.150818],"type":"Point"}
}