{
  "type": "Feature",
  "properties": {
    "addr:full":"725 Deese St Monroe NC 28112",
    "addr:housenumber":"725",
    "addr:postcode":"28112",
    "addr:street":"Deese St",
    "iso:country":"US",
    "sg:address":"725 Deese St",
    "sg:city":"Monroe",
    "sg:classifiers":[
        {
            "category":"Organizations",
            "subcategory":"Religious Organization",
            "type":"Services"
        }
    ],
    "sg:phone":"+1 704 289 2773",
    "sg:postcode":"28112",
    "sg:province":"NC",
    "sg:tags":[
        "church"
    ],
    "sg:website":"www.rc.net",
    "wof:name":"Our Lady Of Lourdes Church",
    "wof:placetype":"venue"
},
  "geometry": {"coordinates":[-80.531257,34.975536],"type":"Point"}
}