{
  "type": "Feature",
  "properties": {
    "iso:country":"US",
    "sg:address":"501 E D St",
    "sg:city":"Butner",
    "sg:classifiers":[
        {
            "category":"Education",
            "subcategory":"School",
            "type":"Public Place"
        }
    ],
    "sg:phone":"+1 919 575 9429",
    "sg:postcode":"27509",
    "sg:province":"NC",
    "sg:website":"www.gcs.k12.nc.us/schools/bsms",
    "wof:name":"Butner-Stem Middle School",
    "wof:placetype":"venue"
},
  "geometry": {"coordinates":[-78.753502,36.1394],"type":"Point"}
}