{
  "type": "Feature",
  "properties": {
    "addr:full":"4726 Kimmerly Glen Ln Charlotte NC 28215",
    "addr:housenumber":"4726",
    "addr:postcode":"28215",
    "addr:street":"Kimmerly Glen Ln",
    "iso:country":"US",
    "sg:address":"4726 Kimmerly Glen Ln",
    "sg:city":"Charlotte",
    "sg:classifiers":[
        {
            "category":"Manufacturing",
            "subcategory":"Printing",
            "type":"Manufacturing & Wholesale Goods"
        }
    ],
    "sg:phone":"+1 704 531 6070",
    "sg:postcode":"28215",
    "sg:province":"NC",
    "sg:tags":[
        "newspaper"
    ],
    "sg:website":"www.migente.us",
    "wof:name":"MI Gente Magazine",
    "wof:placetype":"venue"
},
  "geometry": {"coordinates":[-80.740718,35.228335],"type":"Point"}
}