{
  "type": "Feature",
  "properties": {
    "addr:full":"322 Umstead Dr Chapel Hill NC 27516",
    "addr:housenumber":"322",
    "addr:postcode":"27516",
    "addr:street":"Umstead Dr",
    "iso:country":"US",
    "sg:address":"322 Umstead Dr",
    "sg:city":"Chapel Hill",
    "sg:classifiers":[
        {
            "category":"Professional",
            "subcategory":"Art Services",
            "type":"Services"
        }
    ],
    "sg:phone":"+1   ",
    "sg:postcode":"27516",
    "sg:province":"NC",
    "sg:tags":[
        "commercial",
        "design"
    ],
    "wof:name":"Switch Communications Inc",
    "wof:placetype":"venue"
},
  "geometry": {"coordinates":[-79.058441,35.923846],"type":"Point"}
}