{
  "type": "Feature",
  "properties": {
    "iso:country":"US",
    "sg:address":"8128 Providence Rd",
    "sg:city":"Charlotte",
    "sg:classifiers":[
        {
            "category":"Restaurant",
            "type":"Food & Drink"
        }
    ],
    "sg:phone":"+1 704 752 8080",
    "sg:postcode":"28277",
    "sg:province":"NC",
    "wof:name":"Mickey & Mooch",
    "wof:placetype":"venue"
},
  "geometry": {"coordinates":[-80.777344,35.0954],"type":"Point"}
}