{
  "type": "Feature",
  "properties": {
    "addr:full":"2430 Smokey Creek Rd Morganton NC 28655",
    "addr:housenumber":"2430",
    "addr:postcode":"28655",
    "addr:street":"Smokey Creek Rd",
    "iso:country":"US",
    "sg:address":"2430 Smokey Creek Rd",
    "sg:city":"Morganton",
    "sg:classifiers":[
        {
            "category":"Retail",
            "subcategory":"Auto Repair",
            "type":"Services"
        }
    ],
    "sg:phone":"+1   ",
    "sg:postcode":"28655",
    "sg:province":"NC",
    "sg:tags":[
        "general"
    ],
    "wof:name":"Smokey Creek Auto Sales",
    "wof:placetype":"venue"
},
  "geometry": {"coordinates":[-81.587805,35.798535],"type":"Point"}
}