{
  "type": "Feature",
  "properties": {
    "iso:country":"US",
    "sg:address":"8318 Pineville-Matthews Rd",
    "sg:city":"Charlotte",
    "sg:classifiers":[
        {
            "category":"Banks & Credit Unions",
            "subcategory":"Investment Brokerage",
            "type":"Services"
        }
    ],
    "sg:phone":"+1 704 542 0628",
    "sg:postcode":"28226",
    "sg:province":"NC",
    "sg:tags":[
        "consultant",
        "planning",
        "financial"
    ],
    "wof:name":"Davis Williams & Assoc Inc",
    "wof:placetype":"venue"
},
  "geometry": {"coordinates":[-80.861694,35.087617],"type":"Point"}
}