{
  "type": "Feature",
  "properties": {
    "iso:country":"US",
    "sg:address":"233 Tyler Dr",
    "sg:city":"Smithfield",
    "sg:classifiers":[
        {
            "category":"Building & Trades",
            "subcategory":"Plumbing",
            "type":"Services"
        }
    ],
    "sg:phone":"+1 919 934 9171",
    "sg:postcode":"27577",
    "sg:province":"NC",
    "sg:tags":[
        "plumbing",
        "contractor"
    ],
    "wof:name":"A W Rhodes Plumbing Inc",
    "wof:placetype":"venue"
},
  "geometry": {"coordinates":[-78.38344600000001,35.472773],"type":"Point"}
}