{
  "type": "Feature",
  "properties": {
    "iso:country":"US",
    "sg:address":"1337 Buck Jones Rd",
    "sg:city":"Raleigh",
    "sg:classifiers":[
        {
            "category":"Professional",
            "subcategory":"Computer Services",
            "type":"Services"
        }
    ],
    "sg:phone":"+1 919 465 9393",
    "sg:postcode":"27606",
    "sg:province":"NC",
    "sg:tags":[
        "repair"
    ],
    "sg:website":"www.biztekcomputersofcary.com/",
    "wof:name":"Biztek Computers of Cary",
    "wof:placetype":"venue"
},
  "geometry": {"coordinates":[-78.743104,35.764982],"type":"Point"}
}