{
  "type": "Feature",
  "properties": {
    "iso:country":"US",
    "sg:address":"240 Palomino Dr",
    "sg:city":"Salisbury",
    "sg:classifiers":[
        {
            "category":"Professional",
            "subcategory":"Computer Services",
            "type":"Services"
        }
    ],
    "sg:phone":"+1 704 637 6155",
    "sg:postcode":"28146",
    "sg:province":"NC",
    "sg:tags":[
        "design",
        "system"
    ],
    "wof:name":"Netway Solutions Inc",
    "wof:placetype":"venue"
},
  "geometry": {"coordinates":[-80.368768,35.63704],"type":"Point"}
}