{
  "type": "Feature",
  "properties": {
    "addr:full":"416 N Van Buren Rd Eden NC 27288",
    "addr:housenumber":"416",
    "addr:postcode":"27288",
    "addr:street":"N Van Buren Rd",
    "iso:country":"US",
    "sg:address":"416 N Van Buren Rd",
    "sg:city":"Eden",
    "sg:classifiers":[
        {
            "category":"Home & Garden",
            "subcategory":"Mobile Homes",
            "type":"Retail Goods"
        }
    ],
    "sg:phone":"+1 336 623 4663",
    "sg:postcode":"27288",
    "sg:province":"NC",
    "wof:name":"CMH",
    "wof:placetype":"venue"
},
  "geometry": {"coordinates":[-79.746128,36.511031],"type":"Point"}
}