{
  "type": "Feature",
  "properties": {
    "iso:country":"US",
    "sg:address":"1128 E Mountain St",
    "sg:city":"Kernersville",
    "sg:classifiers":[
        {
            "category":"Professional",
            "subcategory":"Accounting & Tax Preparation",
            "type":"Services"
        }
    ],
    "sg:phone":"+1 336 993 0396",
    "sg:postcode":"27284",
    "sg:province":"NC",
    "sg:tags":[
        "accountant"
    ],
    "wof:name":"AND Accounting",
    "wof:placetype":"venue"
},
  "geometry": {"coordinates":[-80.049908,36.111803],"type":"Point"}
}