{
  "type": "Feature",
  "properties": {
    "addr:full":"2 Cherry St Lexington NC 27292",
    "addr:housenumber":"2",
    "addr:postcode":"27292",
    "addr:street":"Cherry St",
    "iso:country":"US",
    "sg:address":"2 Cherry St",
    "sg:city":"Lexington",
    "sg:classifiers":[
        {
            "category":"Health Services",
            "subcategory":"Podiatrist",
            "type":"Services"
        }
    ],
    "sg:phone":"+1 336 249 1874",
    "sg:postcode":"27292",
    "sg:province":"NC",
    "wof:name":"Podiatry Associates",
    "wof:placetype":"venue"
},
  "geometry": {"coordinates":[-80.246483,35.820359],"type":"Point"}
}