{
  "type": "Feature",
  "properties": {
    "iso:country":"US",
    "sg:address":"635 Gilliam Mountain Rd",
    "sg:city":"Hendersonville",
    "sg:classifiers":[
        {
            "category":"Organizations",
            "subcategory":"Religious Organization",
            "type":"Services"
        }
    ],
    "sg:phone":"+1 828 685 7292",
    "sg:postcode":"28792",
    "sg:province":"NC",
    "sg:tags":[
        "church"
    ],
    "wof:name":"Mt Moriah Baptist Church",
    "wof:placetype":"venue"
},
  "geometry": {"coordinates":[-82.33132000000001,35.390216],"type":"Point"}
}