{
  "type": "Feature",
  "properties": {
    "iso:country":"US",
    "sg:address":"100 W 5th St",
    "sg:city":"Winston Salem",
    "sg:classifiers":[
        {
            "category":"Local Transit",
            "type":"Transportation"
        }
    ],
    "sg:phone":"+1 336 724 1429",
    "sg:postcode":"27101",
    "sg:province":"NC",
    "sg:tags":[
        "bus",
        "line"
    ],
    "wof:name":"Greyhound Bus Lines",
    "wof:placetype":"venue"
},
  "geometry": {"coordinates":[-80.24598899999999,36.09983],"type":"Point"}
}