{
  "type": "Feature",
  "properties": {
    "addr:full":"321 Washington St Williamston NC 27892",
    "addr:housenumber":"321",
    "addr:postcode":"27892",
    "addr:street":"Washington St",
    "iso:country":"US",
    "sg:address":"321 Washington St",
    "sg:city":"Williamston",
    "sg:classifiers":[
        {
            "category":"Retail",
            "subcategory":"Auto Repair",
            "type":"Services"
        }
    ],
    "sg:phone":"+1   ",
    "sg:postcode":"27892",
    "sg:province":"NC",
    "sg:tags":[
        "transmission"
    ],
    "wof:name":"Prices Transmission Repair",
    "wof:placetype":"venue"
},
  "geometry": {"coordinates":[-77.056568,35.850004],"type":"Point"}
}