{
  "type": "Feature",
  "properties": {
    "iso:country":"US",
    "sg:address":"629 Monroe St",
    "sg:city":"Eden",
    "sg:classifiers":[
        {
            "category":"Restaurant",
            "type":"Food & Drink"
        }
    ],
    "sg:phone":"+1 336 627 6300",
    "sg:postcode":"27288",
    "sg:province":"NC",
    "sg:tags":[
        "pizza"
    ],
    "wof:name":"Tiano's Pizza",
    "wof:placetype":"venue"
},
  "geometry": {"coordinates":[-79.764723,36.491747],"type":"Point"}
}