{
  "type": "Feature",
  "properties": {
    "iso:country":"US",
    "sg:address":"1403 N Franklin St",
    "sg:city":"Gastonia",
    "sg:classifiers":[
        {
            "category":"Organizations",
            "subcategory":"Religious Organization",
            "type":"Services"
        }
    ],
    "sg:phone":"+1   ",
    "sg:postcode":"28054",
    "sg:province":"NC",
    "wof:name":"Revive Ministries",
    "wof:placetype":"venue"
},
  "geometry": {"coordinates":[-81.131702,35.282625],"type":"Point"}
}