{
  "type": "Feature",
  "properties": {
    "addr:full":"538 Woodland Dr Greensboro NC 27408",
    "addr:housenumber":"538",
    "addr:postcode":"27408",
    "addr:street":"Woodland Dr",
    "iso:country":"US",
    "sg:address":"538 Woodland Dr",
    "sg:city":"Greensboro",
    "sg:classifiers":[
        {
            "category":"Banks & Credit Unions",
            "subcategory":"Financial Services",
            "type":"Services"
        }
    ],
    "sg:phone":"+1 336 378 9694",
    "sg:postcode":"27408",
    "sg:province":"NC",
    "sg:tags":[
        "trust",
        "nonprofit",
        "management"
    ],
    "wof:name":"Maness Family Foundation Inc",
    "wof:placetype":"venue"
},
  "geometry": {"coordinates":[-79.79626,36.093888],"type":"Point"}
}