{
  "type": "Feature",
  "properties": {
    "iso:country":"US",
    "sg:address":"4100 Carmel Rd",
    "sg:city":"Charlotte",
    "sg:classifiers":[
        {
            "category":"Restaurant",
            "type":"Food & Drink"
        }
    ],
    "sg:phone":"+1 704 543 8868",
    "sg:postcode":"28226",
    "sg:province":"NC",
    "sg:tags":[
        "eating"
    ],
    "wof:name":"Lotus Cuisine II",
    "wof:placetype":"venue"
},
  "geometry": {"coordinates":[-80.822429,35.11777],"type":"Point"}
}