{
  "type": "Feature",
  "properties": {
    "addr:full":"3645 Strollaway Ln Claremont NC 28610",
    "addr:housenumber":"3645",
    "addr:postcode":"28610",
    "addr:street":"Strollaway Ln",
    "iso:country":"US",
    "sg:address":"3645 Strollaway Ln",
    "sg:city":"Claremont",
    "sg:classifiers":[
        {
            "category":"Professional",
            "type":"Services"
        }
    ],
    "sg:phone":"+1 828 459 0392",
    "sg:postcode":"28610",
    "sg:province":"NC",
    "wof:name":"Barbara Boyd",
    "wof:placetype":"venue"
},
  "geometry": {"coordinates":[-81.135639,35.762248],"type":"Point"}
}