{
  "type": "Feature",
  "properties": {
    "iso:country":"US",
    "sg:address":"308 Greenville Blvd SE",
    "sg:city":"Greenville",
    "sg:classifiers":[
        {
            "category":"Shopping",
            "type":"Retail Goods"
        },
        {
            "category":"Wholesale",
            "subcategory":"Electrical",
            "type":"Manufacturing & Wholesale Goods"
        }
    ],
    "sg:phone":"+1 919 735 6998",
    "sg:postcode":"27858",
    "sg:province":"NC",
    "sg:tags":[
        "burglar",
        "alarm",
        "system",
        "contractor",
        "security",
        "merchandise"
    ],
    "wof:name":"Security Solutions Inc",
    "wof:placetype":"venue"
},
  "geometry": {"coordinates":[-77.379533,35.578574],"type":"Point"}
}