{
  "type": "Feature",
  "properties": {
    "addr:full":"307 Club Ct Wilmington NC 28412",
    "addr:housenumber":"307",
    "addr:postcode":"28412",
    "addr:street":"Club Ct",
    "iso:country":"US",
    "sg:address":"307 Club Ct",
    "sg:city":"Wilmington",
    "sg:classifiers":[
        {
            "category":"Building & Trades",
            "subcategory":"Plumbing",
            "type":"Services"
        }
    ],
    "sg:phone":"+1 910 791 1168",
    "sg:postcode":"28412",
    "sg:province":"NC",
    "wof:name":"Anderson Plumbing Co",
    "wof:placetype":"venue"
},
  "geometry": {"coordinates":[-77.91513399999999,34.073992],"type":"Point"}
}