{
  "type": "Feature",
  "properties": {
    "addr:full":"2271 State Hwy 119 Mebane NC 27302",
    "addr:housenumber":"2271",
    "addr:postcode":"27302",
    "addr:street":"State Hwy 119",
    "iso:country":"US",
    "sg:address":"2271 State Hwy 119",
    "sg:city":"Mebane",
    "sg:classifiers":[
        {
            "category":"Professional",
            "type":"Services"
        }
    ],
    "sg:phone":"+1 336 794 0830",
    "sg:postcode":"27302",
    "sg:province":"NC",
    "wof:name":"J Grissom PC",
    "wof:placetype":"venue"
},
  "geometry": {"coordinates":[-79.30932,36.056258],"type":"Point"}
}