{
  "type": "Feature",
  "properties": {
    "addr:full":"6905 Hickory Ridge Rd Harrisburg NC 28075",
    "addr:housenumber":"6905",
    "addr:postcode":"28075",
    "addr:street":"Hickory Ridge Rd",
    "iso:country":"US",
    "sg:address":"6905 Hickory Ridge Rd",
    "sg:city":"Harrisburg",
    "sg:classifiers":[
        {
            "category":"Building & Trades",
            "subcategory":"Construction",
            "type":"Services"
        }
    ],
    "sg:phone":"+1 704 455 9365",
    "sg:postcode":"28075",
    "sg:province":"NC",
    "sg:tags":[
        "hanging",
        "contractor"
    ],
    "wof:name":"Dp Painting",
    "wof:placetype":"venue"
},
  "geometry": {"coordinates":[-80.646784,35.311017],"type":"Point"}
}