{
  "type": "Feature",
  "properties": {
    "iso:country":"US",
    "sg:address":"1327 Headquarters Dr",
    "sg:city":"Greensboro",
    "sg:classifiers":[
        {
            "category":"Retail",
            "subcategory":"Repair Shop",
            "type":"Services"
        }
    ],
    "sg:phone":"+1   ",
    "sg:postcode":"27405",
    "sg:province":"NC",
    "sg:tags":[
        "electrical"
    ],
    "wof:name":"Tritech Electronics Inc",
    "wof:placetype":"venue"
},
  "geometry": {"coordinates":[-79.767488,36.08425],"type":"Point"}
}