{
  "type": "Feature",
  "properties": {
    "iso:country":"US",
    "sg:address":"204 Stevenson St",
    "sg:city":"Randleman",
    "sg:classifiers":[
        {
            "category":"Building & Trades",
            "subcategory":"Cleaning & Sanitation",
            "type":"Services"
        }
    ],
    "sg:phone":"+1   ",
    "sg:postcode":"27317",
    "sg:province":"NC",
    "sg:tags":[
        "maintenance"
    ],
    "wof:name":"T & L Janitorial",
    "wof:placetype":"venue"
},
  "geometry": {"coordinates":[-79.81049400000001,35.819901],"type":"Point"}
}