{
  "type": "Feature",
  "properties": {
    "iso:country":"US",
    "sg:address":"3897 Macgregor Downs Rd",
    "sg:city":"Greenville",
    "sg:classifiers":[
        {
            "category":"Building & Trades",
            "subcategory":"Electrical",
            "type":"Services"
        },
        {
            "category":"Building & Trades",
            "subcategory":"Construction",
            "type":"Services"
        }
    ],
    "sg:phone":"+1 252 752 8677",
    "sg:postcode":"27834",
    "sg:province":"NC",
    "sg:tags":[
        "fiber",
        "installation",
        "optic",
        "cable",
        "contractor",
        "utility"
    ],
    "wof:name":"Willis Cable Construction Inc",
    "wof:placetype":"venue"
},
  "geometry": {"coordinates":[-77.448126,35.613465],"type":"Point"}
}