{
  "type": "Feature",
  "properties": {
    "addr:full":"3476 Catherine Lake Rd Chinquapin NC 28521",
    "addr:housenumber":"3476",
    "addr:postcode":"28521",
    "addr:street":"Catherine Lake Rd",
    "iso:country":"US",
    "sg:address":"3476 Catherine Lake Rd",
    "sg:city":"Chinquapin",
    "sg:classifiers":[
        {
            "category":"Bars & Pubs",
            "type":"Food & Drink"
        }
    ],
    "sg:phone":"+1 910 324 1199",
    "sg:postcode":"28521",
    "sg:province":"NC",
    "sg:tags":[
        "club",
        "night"
    ],
    "wof:name":"Last Call Lounge",
    "wof:placetype":"venue"
},
  "geometry": {"coordinates":[-77.66297299999999,34.838738],"type":"Point"}
}