{
  "type": "Feature",
  "properties": {
    "addr:full":"5315 Boone Trl Millers Creek NC 28651",
    "addr:housenumber":"5315",
    "addr:postcode":"28651",
    "addr:street":"Boone Trl",
    "iso:country":"US",
    "sg:address":"5315 Boone Trl",
    "sg:city":"Millers Creek",
    "sg:classifiers":[
        {
            "category":"Restaurant",
            "type":"Food & Drink"
        }
    ],
    "sg:phone":"+1 336 838 5500",
    "sg:postcode":"28651",
    "sg:province":"NC",
    "sg:tags":[
        "shop",
        "coffee"
    ],
    "wof:name":"Java Hills Coffee & Ice Cream",
    "wof:placetype":"venue"
},
  "geometry": {"coordinates":[-81.23740599999999,36.1889],"type":"Point"}
}