{
  "type": "Feature",
  "properties": {
    "addr:full":"2511 Old Aberdeen Rd Rockingham NC 28379",
    "addr:housenumber":"2511",
    "addr:postcode":"28379",
    "addr:street":"Old Aberdeen Rd",
    "iso:country":"US",
    "sg:address":"2511 Old Aberdeen Rd",
    "sg:city":"Rockingham",
    "sg:classifiers":[
        {
            "category":"Freight",
            "type":"Transportation"
        }
    ],
    "sg:phone":"+1 910 997 4263",
    "sg:postcode":"28379",
    "sg:province":"NC",
    "sg:tags":[
        "operator",
        "local",
        "trucking"
    ],
    "wof:name":"Ken Craven Trucking",
    "wof:placetype":"venue"
},
  "geometry": {"coordinates":[-79.735602,34.960742],"type":"Point"}
}