{
  "type": "Feature",
  "properties": {
    "iso:country":"US",
    "sg:address":"400 S Main St",
    "sg:city":"Stanley",
    "sg:classifiers":[
        {
            "category":"Shopping",
            "type":"Retail Goods"
        }
    ],
    "sg:phone":"+1 704 263 6244",
    "sg:postcode":"28164",
    "sg:province":"NC",
    "sg:tags":[
        "webbing"
    ],
    "wof:name":"Murdock Webbing Co Inc",
    "wof:placetype":"venue"
},
  "geometry": {"coordinates":[-81.093645,35.355981],"type":"Point"}
}