{
  "type": "Feature",
  "properties": {
    "iso:country":"US",
    "sg:address":"210 Cherry St S",
    "sg:city":"Winston Salem",
    "sg:classifiers":[
        {
            "category":"Professional",
            "subcategory":"Advertising",
            "type":"Services"
        }
    ],
    "sg:phone":"+1 336 724 0450",
    "sg:postcode":"27101",
    "sg:province":"NC",
    "sg:tags":[
        "a",
        "graphic",
        "art",
        "des",
        "commercial",
        "agency"
    ],
    "sg:website":"www.woodbine.com",
    "wof:name":"Woodbine Agency",
    "wof:placetype":"venue"
},
  "geometry": {"coordinates":[-80.245818,36.090916],"type":"Point"}
}