{
  "type": "Feature",
  "properties": {
    "iso:country":"US",
    "sg:address":"29 Lovers Loop Rd",
    "sg:city":"Asheville",
    "sg:classifiers":[
        {
            "category":"Health Services",
            "subcategory":"Health Practitioner",
            "type":"Services"
        }
    ],
    "sg:phone":"+1 828 298 5454",
    "sg:postcode":"28803",
    "sg:province":"NC",
    "sg:tags":[
        "psychotherapist"
    ],
    "wof:name":"Gentle Bio-Energetics Inst",
    "wof:placetype":"venue"
},
  "geometry": {"coordinates":[-82.490706,35.55422],"type":"Point"}
}