{
  "type": "Feature",
  "properties": {
    "addr:full":"330 Shoreside Dr Swansboro NC 28584",
    "addr:housenumber":"330",
    "addr:postcode":"28584",
    "addr:street":"Shoreside Dr",
    "iso:country":"US",
    "sg:address":"330 Shoreside Dr",
    "sg:city":"Swansboro",
    "sg:classifiers":[
        {
            "category":"Professional",
            "subcategory":"Business Services",
            "type":"Services"
        }
    ],
    "sg:phone":"+1 252 393 4542",
    "sg:postcode":"28584",
    "sg:province":"NC",
    "sg:tags":[
        "information",
        "referral"
    ],
    "sg:website":"www.reedbusiness.com",
    "wof:name":"Reed Business Information",
    "wof:placetype":"venue"
},
  "geometry": {"coordinates":[-77.09835099999999,34.717684],"type":"Point"}
}