{
  "type": "Feature",
  "properties": {
    "addr:full":"3643 New Bern Ave Raleigh NC 27610",
    "addr:housenumber":"3643",
    "addr:postcode":"27610",
    "addr:street":"New Bern Ave",
    "iso:country":"US",
    "sg:address":"3643 New Bern Ave",
    "sg:city":"Raleigh",
    "sg:classifiers":[
        {
            "category":"Professional",
            "subcategory":"Accounting & Tax Preparation",
            "type":"Services"
        }
    ],
    "sg:phone":"+1 919 231 6229",
    "sg:postcode":"27610",
    "sg:province":"NC",
    "sg:tags":[
        "return",
        "filing"
    ],
    "wof:name":"AAA Tax Svc",
    "wof:placetype":"venue"
},
  "geometry": {"coordinates":[-78.58008,35.796008],"type":"Point"}
}