{
  "type": "Feature",
  "properties": {
    "addr:full":"345 Eastwood Dr Cramerton NC 28092",
    "addr:housenumber":"345",
    "addr:postcode":"28092",
    "addr:street":"Eastwood Dr",
    "iso:country":"US",
    "sg:address":"345 Eastwood Dr",
    "sg:city":"Cramerton",
    "sg:classifiers":[
        {
            "category":"Wholesale",
            "subcategory":"Chemicals & Plastics",
            "type":"Manufacturing & Wholesale Goods"
        }
    ],
    "sg:phone":"+1 704 825 6091",
    "sg:postcode":"28092",
    "sg:province":"NC",
    "sg:tags":[
        "textile",
        "dyer"
    ],
    "wof:name":"Lakewood Dyed Yarns",
    "wof:placetype":"venue"
},
  "geometry": {"coordinates":[-81.208338,35.484997],"type":"Point"}
}