{
  "type": "Feature",
  "properties": {
    "iso:country":"US",
    "sg:address":"8514 Furrier Dr",
    "sg:city":"Charlotte",
    "sg:classifiers":[
        {
            "category":"Real Estate",
            "subcategory":"Real Estate Agent",
            "type":"Services"
        }
    ],
    "sg:phone":"+1 704 400 6875",
    "sg:postcode":"28270",
    "sg:province":"NC",
    "wof:name":"Brent E Moore",
    "wof:placetype":"venue"
},
  "geometry": {"coordinates":[-80.749436,35.13067],"type":"Point"}
}