{
  "type": "Feature",
  "properties": {
    "addr:full":"10800 Sikes Pl Ste 230 Charlotte NC 28277",
    "addr:postcode":"10800;28277",
    "addr:street":"Sikes Pl Ste 230",
    "iso:country":"US",
    "sg:address":"10800 Sikes Pl Ste 230",
    "sg:city":"Charlotte",
    "sg:classifiers":[
        {
            "category":"Banks & Credit Unions",
            "subcategory":"Investment Brokerage",
            "type":"Services"
        },
        {
            "category":"Banks & Credit Unions",
            "subcategory":"Bank",
            "type":"Services"
        },
        {
            "category":"Banks & Credit Unions",
            "subcategory":"Financial Services",
            "type":"Services"
        }
    ],
    "sg:phone":"+1 888 335 2088",
    "sg:postcode":"28277",
    "sg:province":"NC",
    "sg:tags":[
        "advisory",
        "mutual",
        "retirement",
        "annuity",
        "broker",
        "fund",
        "planning",
        "plan",
        "consultant",
        "security",
        "bond",
        "insurance",
        "stock"
    ],
    "sg:website":"http://www.edwardjones.com",
    "wof:name":"Edward Jones - ANDY BELK",
    "wof:placetype":"venue"
},
  "geometry": {"coordinates":[-80.76853199999999,35.063179],"type":"Point"}
}