{
  "type": "Feature",
  "properties": {
    "addr:full":"1452 Carolyn Dr Charlotte NC 28205",
    "addr:housenumber":"1452",
    "addr:postcode":"28205",
    "addr:street":"Carolyn Dr",
    "iso:country":"US",
    "sg:address":"1452 Carolyn Dr",
    "sg:city":"Charlotte",
    "sg:classifiers":[
        {
            "category":"Building & Trades",
            "subcategory":"Plumbing",
            "type":"Services"
        }
    ],
    "sg:phone":"+1 704 537 5469",
    "sg:postcode":"28205",
    "sg:province":"NC",
    "sg:tags":[
        "contractor"
    ],
    "wof:name":"Sherdian Mechanical Contractor",
    "wof:placetype":"venue"
},
  "geometry": {"coordinates":[-80.78750599999999,35.212366],"type":"Point"}
}