{
  "type": "Feature",
  "properties": {
    "iso:country":"US",
    "sg:address":"935 Haws Run Rd",
    "sg:city":"Jacksonville",
    "sg:classifiers":[
        {
            "category":"Shopping",
            "subcategory":"Bicycles & Sporting Goods",
            "type":"Retail Goods"
        }
    ],
    "sg:phone":"+1 910 347 5499",
    "sg:postcode":"28540",
    "sg:province":"NC",
    "wof:name":"Millers Gun Shop",
    "wof:placetype":"venue"
},
  "geometry": {"coordinates":[-77.55107,34.695425],"type":"Point"}
}