{
  "type": "Feature",
  "properties": {
    "addr:full":"2530 Meridian Pkwy Durham NC 27713",
    "addr:housenumber":"2530",
    "addr:postcode":"27713",
    "addr:street":"Meridian Pkwy",
    "iso:country":"US",
    "sg:address":"2530 Meridian Pkwy",
    "sg:city":"Durham",
    "sg:classifiers":[
        {
            "category":"Professional",
            "type":"Services"
        }
    ],
    "sg:phone":"+1 919 806 4917",
    "sg:postcode":"27713",
    "sg:province":"NC",
    "wof:name":"Neogenesys Inc",
    "wof:placetype":"venue"
},
  "geometry": {"coordinates":[-78.902219,35.9118],"type":"Point"}
}