{
  "type": "Feature",
  "properties": {
    "iso:country":"US",
    "sg:address":"4615 W Market St",
    "sg:city":"Greensboro",
    "sg:classifiers":[
        {
            "category":"Retail",
            "subcategory":"Auto Repair",
            "type":"Services"
        }
    ],
    "sg:phone":"+1   ",
    "sg:postcode":"27407",
    "sg:province":"NC",
    "sg:tags":[
        "body"
    ],
    "wof:name":"Custom Car Care",
    "wof:placetype":"venue"
},
  "geometry": {"coordinates":[-79.863916,36.070251],"type":"Point"}
}