{
  "type": "Feature",
  "properties": {
    "addr:full":"2301 Trenton Rd Raleigh NC 27607",
    "addr:housenumber":"2301",
    "addr:postcode":"27607",
    "addr:street":"Trenton Rd",
    "iso:country":"US",
    "sg:address":"2301 Trenton Rd",
    "sg:city":"Raleigh",
    "sg:classifiers":[
        {
            "category":"Building & Trades",
            "subcategory":"Electrical",
            "type":"Services"
        }
    ],
    "sg:phone":"+1 919 851 9300",
    "sg:postcode":"27607",
    "sg:province":"NC",
    "sg:tags":[
        "electric",
        "contractor"
    ],
    "wof:name":"Port City Electric",
    "wof:placetype":"venue"
},
  "geometry": {"coordinates":[-78.745422,35.808963],"type":"Point"}
}