{
  "type": "Feature",
  "properties": {
    "iso:country":"US",
    "sg:address":"318 Spring St",
    "sg:city":"Thomasville",
    "sg:classifiers":[
        {
            "category":"Professional",
            "subcategory":"Business Services",
            "type":"Services"
        }
    ],
    "sg:phone":"+1   ",
    "sg:postcode":"27360",
    "sg:province":"NC",
    "wof:name":"Brookbank Agency Inc",
    "wof:placetype":"venue"
},
  "geometry": {"coordinates":[-80.090858,35.878327],"type":"Point"}
}