{
  "type": "Feature",
  "properties": {
    "addr:full":"252 NE 65th St Oak Island NC 28465",
    "addr:housenumber":"252",
    "addr:postcode":"28465",
    "addr:street":"Ne 65Th St",
    "iso:country":"US",
    "sg:address":"252 NE 65th St",
    "sg:city":"Oak Island",
    "sg:classifiers":[
        {
            "category":"Building & Trades",
            "subcategory":"Construction",
            "type":"Services"
        }
    ],
    "sg:phone":"+1 910 278 1906",
    "sg:postcode":"28465",
    "sg:province":"NC",
    "sg:tags":[
        "house"
    ],
    "wof:name":"Regancy Sales",
    "wof:placetype":"venue"
},
  "geometry": {"coordinates":[-78.098508,33.913324],"type":"Point"}
}