{
  "type": "Feature",
  "properties": {
    "iso:country":"US",
    "sg:address":"5567 W Market St",
    "sg:city":"Greensboro",
    "sg:classifiers":[
        {
            "category":"Retail",
            "subcategory":"Laundry & Dry Cleaning",
            "type":"Services"
        }
    ],
    "sg:phone":"+1   ",
    "sg:postcode":"27409",
    "sg:province":"NC",
    "sg:tags":[
        "drycleaning",
        "plant"
    ],
    "wof:name":"Quality 250 Cleaners",
    "wof:placetype":"venue"
},
  "geometry": {"coordinates":[-79.888561,36.074331],"type":"Point"}
}