{
  "type": "Feature",
  "properties": {
    "iso:country":"US",
    "sg:address":"1455 Fairchild Rd",
    "sg:city":"Winston Salem",
    "sg:classifiers":[
        {
            "category":"Professional",
            "subcategory":"Management & Consulting",
            "type":"Services"
        }
    ],
    "sg:phone":"+1   ",
    "sg:postcode":"27105",
    "sg:province":"NC",
    "wof:name":"Rta International Inc",
    "wof:placetype":"venue"
},
  "geometry": {"coordinates":[-80.228302,36.130766],"type":"Point"}
}