{
  "type": "Feature",
  "properties": {
    "iso:country":"US",
    "sg:address":"3073 Oakridge River Rd",
    "sg:city":"Fuquay Varina",
    "sg:classifiers":[
        {
            "category":"Manufacturing",
            "subcategory":"Glass & Minerals",
            "type":"Manufacturing & Wholesale Goods"
        }
    ],
    "sg:phone":"+1 919 552 9462",
    "sg:postcode":"27526",
    "sg:province":"NC",
    "sg:tags":[
        "precast",
        "product",
        "mfg",
        "concrete"
    ],
    "wof:name":"Buckhorn Concrete Products",
    "wof:placetype":"venue"
},
  "geometry": {"coordinates":[-78.87582999999999,35.527398],"type":"Point"}
}