{
  "type": "Feature",
  "properties": {
    "iso:country":"US",
    "sg:address":"1400 Church St Exd",
    "sg:city":"Elizabeth City",
    "sg:classifiers":[
        {
            "category":"Manufacturing",
            "subcategory":"Furniture",
            "type":"Manufacturing & Wholesale Goods"
        }
    ],
    "sg:phone":"+1 252 335 4191",
    "sg:postcode":"27909",
    "sg:province":"NC",
    "sg:website":"www.houtzandbarwick.com",
    "wof:name":"Houtz & Barwick Outdoor Furn",
    "wof:placetype":"venue"
},
  "geometry": {"coordinates":[-76.243797,36.29961],"type":"Point"}
}