{
  "type": "Feature",
  "properties": {
    "addr:full":"1116 Broad St Durham NC 27705",
    "addr:housenumber":"1116",
    "addr:postcode":"27705",
    "addr:street":"Broad St",
    "iso:country":"US",
    "sg:address":"1116 Broad St",
    "sg:city":"Durham",
    "sg:classifiers":[
        {
            "category":"Restaurant",
            "type":"Food & Drink"
        }
    ],
    "sg:phone":"+1 919 416 9707",
    "sg:postcode":"27705",
    "sg:province":"NC",
    "sg:tags":[
        "shop",
        "coffee"
    ],
    "wof:name":"Broad St Cafe",
    "wof:placetype":"venue"
},
  "geometry": {"coordinates":[-78.919099,36.016865],"type":"Point"}
}