{
  "type": "Feature",
  "properties": {
    "iso:country":"US",
    "sg:address":"4150 Hummingbird Pl",
    "sg:city":"Fayetteville",
    "sg:classifiers":[
        {
            "category":"Organizations",
            "subcategory":"Religious Organization",
            "type":"Services"
        }
    ],
    "sg:phone":"+1 910 485 7894",
    "sg:postcode":"28312",
    "sg:province":"NC",
    "sg:tags":[
        "church"
    ],
    "wof:name":"Shiloh United Church Of Christ",
    "wof:placetype":"venue"
},
  "geometry": {"coordinates":[-78.771856,35.054231],"type":"Point"}
}