{
  "type": "Feature",
  "properties": {
    "addr:full":"836 Wildwood Pointe Dr New Bern NC 28560",
    "addr:housenumber":"836",
    "addr:postcode":"28560",
    "addr:street":"Wildwood Pointe Dr",
    "iso:country":"US",
    "sg:address":"836 Wildwood Pointe Dr",
    "sg:city":"New Bern",
    "sg:classifiers":[
        {
            "category":"Wholesale",
            "subcategory":"Vending Machines",
            "type":"Manufacturing & Wholesale Goods"
        }
    ],
    "sg:phone":"+1 252 637 7022",
    "sg:postcode":"28560",
    "sg:province":"NC",
    "wof:name":"Lindon Enterprises Inc",
    "wof:placetype":"venue"
},
  "geometry": {"coordinates":[-77.05496100000001,35.170771],"type":"Point"}
}