{
  "type": "Feature",
  "properties": {
    "iso:country":"US",
    "sg:address":"3100 Edwards Mill Rd",
    "sg:city":"Raleigh",
    "sg:classifiers":[
        {
            "category":"Banks & Credit Unions",
            "subcategory":"Bank",
            "type":"Services"
        }
    ],
    "sg:phone":"+1 919 881 1501",
    "sg:postcode":"27612",
    "sg:province":"NC",
    "wof:name":"Southern Community Bank",
    "wof:placetype":"venue"
},
  "geometry": {"coordinates":[-78.705744,35.824417],"type":"Point"}
}