{
  "type": "Feature",
  "properties": {
    "addr:full":"117 Wisteria Dr Camden NC 27921",
    "addr:housenumber":"117",
    "addr:postcode":"27921",
    "addr:street":"Wisteria Dr",
    "iso:country":"US",
    "sg:address":"117 Wisteria Dr",
    "sg:city":"Camden",
    "sg:classifiers":[
        {
            "category":"Home & Garden",
            "subcategory":"Household Appliances",
            "type":"Retail Goods"
        }
    ],
    "sg:phone":"+1 252 335 5115",
    "sg:postcode":"27921",
    "sg:province":"NC",
    "wof:name":"Singer Sewing Ctr Elizabeth Cy",
    "wof:placetype":"venue"
},
  "geometry": {"coordinates":[-76.151312,36.293587],"type":"Point"}
}