{
  "type": "Feature",
  "properties": {
    "iso:country":"US",
    "sg:address":"105 E Jackson Blvd",
    "sg:city":"Erwin",
    "sg:classifiers":[
        {
            "category":"Autos & Motor Vehicles",
            "subcategory":"Automobile Sales",
            "type":"Retail Goods"
        }
    ],
    "sg:phone":"+1 910 897 3507",
    "sg:postcode":"28339",
    "sg:province":"NC",
    "sg:tags":[
        "car",
        "used",
        "dealer"
    ],
    "wof:name":"Napier's Standard Auto Sales",
    "wof:placetype":"venue"
},
  "geometry": {"coordinates":[-78.674497,35.33577],"type":"Point"}
}