{
  "type": "Feature",
  "properties": {
    "iso:country":"US",
    "sg:address":"185 Calvary Dr",
    "sg:city":"Olivia",
    "sg:classifiers":[
        {
            "category":"Organizations",
            "subcategory":"Religious Organization",
            "type":"Services"
        }
    ],
    "sg:phone":"+1 919 499 0264",
    "sg:postcode":"28364",
    "sg:province":"NC",
    "sg:tags":[
        "church"
    ],
    "wof:name":"Calvary Methodist Church",
    "wof:placetype":"venue"
},
  "geometry": {"coordinates":[-79.29497000000001,34.830584],"type":"Point"}
}