{
  "type": "Feature",
  "properties": {
    "iso:country":"US",
    "sg:address":"959 N Wesleyan Blvd",
    "sg:city":"Rocky Mount",
    "sg:classifiers":[
        {
            "category":"Utilities",
            "subcategory":"Mobile Phone",
            "type":"Services"
        }
    ],
    "sg:phone":"+1 252 407 4600",
    "sg:postcode":"27804",
    "sg:province":"NC",
    "sg:tags":[
        "telephone",
        "cellular"
    ],
    "wof:name":"Alltel Mobile",
    "wof:placetype":"venue"
},
  "geometry": {"coordinates":[-77.814487,35.968275],"type":"Point"}
}