{
  "type": "Feature",
  "properties": {
    "addr:full":"231 4th St SW Hickory NC 28602",
    "addr:housenumber":"231",
    "addr:postcode":"28602",
    "addr:street":"4Th St Sw",
    "iso:country":"US",
    "sg:address":"231 4th St SW",
    "sg:city":"Hickory",
    "sg:classifiers":[
        {
            "category":"Insurance",
            "subcategory":"Insurance Agent",
            "type":"Services"
        }
    ],
    "sg:phone":"+1 828 345 6294",
    "sg:postcode":"28602",
    "sg:province":"NC",
    "wof:name":"Horace Mann Insurance Co",
    "wof:placetype":"venue"
},
  "geometry": {"coordinates":[-81.344559,35.729165],"type":"Point"}
}