{
  "type": "Feature",
  "properties": {
    "iso:country":"US",
    "sg:address":"321 Gillburg Rd",
    "sg:city":"Henderson",
    "sg:classifiers":[
        {
            "category":"Government",
            "subcategory":"Office",
            "type":"Public Place"
        }
    ],
    "sg:phone":"+1 252 492 0111",
    "sg:postcode":"27537",
    "sg:province":"NC",
    "sg:tags":[
        "transportation"
    ],
    "wof:name":"Transportation NC Dept",
    "wof:placetype":"venue"
},
  "geometry": {"coordinates":[-78.36946399999999,36.271725],"type":"Point"}
}