{
  "type": "Feature",
  "properties": {
    "addr:full":"117 N College Ave Newton NC 28658",
    "addr:housenumber":"117",
    "addr:postcode":"28658",
    "addr:street":"N College Ave",
    "iso:country":"US",
    "sg:address":"117 N College Ave",
    "sg:city":"Newton",
    "sg:classifiers":[
        {
            "category":"Cinema",
            "subcategory":"Movie Theater",
            "type":"Entertainment"
        }
    ],
    "sg:phone":"+1 828 464 2171",
    "sg:postcode":"28658",
    "sg:province":"NC",
    "wof:name":"State Cinema",
    "wof:placetype":"venue"
},
  "geometry": {"coordinates":[-81.221006,35.664027],"type":"Point"}
}