{
  "type": "Feature",
  "properties": {
    "addr:full":"1727 N Garnett St Henderson NC 27536",
    "addr:housenumber":"1727",
    "addr:postcode":"27536",
    "addr:street":"N Garnett St",
    "iso:country":"US",
    "sg:address":"1727 N Garnett St",
    "sg:city":"Henderson",
    "sg:classifiers":[
        {
            "category":"Travel",
            "subcategory":"Hotels & Motels",
            "type":"Entertainment"
        }
    ],
    "sg:phone":"+1 252 492 2013",
    "sg:postcode":"27536",
    "sg:province":"NC",
    "wof:name":"Budget Host Inn",
    "wof:placetype":"venue"
},
  "geometry": {"coordinates":[-78.39496699999999,36.34119],"type":"Point"}
}