{
  "type": "Feature",
  "properties": {
    "addr:full":"305 US Hwy 117 S Goldsboro NC 27530",
    "addr:housenumber":"305",
    "addr:postcode":"27530",
    "addr:street":"Us Hwy 117 S",
    "iso:country":"US",
    "sg:address":"305 US Hwy 117 S",
    "sg:city":"Goldsboro",
    "sg:classifiers":[
        {
            "category":"Building & Trades",
            "subcategory":"Construction",
            "type":"Services"
        }
    ],
    "sg:phone":"+1 919 736 7831",
    "sg:postcode":"27530",
    "sg:province":"NC",
    "sg:tags":[
        "communication",
        "line",
        "contractor"
    ],
    "wof:name":"Ansco & Associates LLC",
    "wof:placetype":"venue"
},
  "geometry": {"coordinates":[-78.013535,35.382117],"type":"Point"}
}