{
  "type": "Feature",
  "properties": {
    "iso:country":"US",
    "sg:address":"1617 W Garrison Blvd",
    "sg:city":"Gastonia",
    "sg:classifiers":[
        {
            "category":"Insurance",
            "subcategory":"Hazard Insurance",
            "type":"Services"
        }
    ],
    "sg:phone":"+1 704 861 8266",
    "sg:postcode":"28052",
    "sg:province":"NC",
    "sg:website":"http://www.realpagessites.com/advantageautoins",
    "wof:name":"Advantage Auto Insurance",
    "wof:placetype":"venue"
},
  "geometry": {"coordinates":[-81.21019,35.257739],"type":"Point"}
}