{
  "type": "Feature",
  "properties": {
    "iso:country":"US",
    "sg:address":"5420 Collinwood Ct",
    "sg:city":"Wilmington",
    "sg:classifiers":[
        {
            "category":"Professional",
            "subcategory":"Engineering",
            "type":"Services"
        }
    ],
    "sg:phone":"+1   ",
    "sg:postcode":"28403",
    "sg:province":"NC",
    "wof:name":"Marek Yacht & Design",
    "wof:placetype":"venue"
},
  "geometry": {"coordinates":[-77.85588,34.222935],"type":"Point"}
}