{
  "type": "Feature",
  "properties": {
    "iso:country":"US",
    "sg:address":"2309 Rock Quarry Rd",
    "sg:city":"Raleigh",
    "sg:classifiers":[
        {
            "category":"Banks & Credit Unions",
            "subcategory":"Investment Brokerage",
            "type":"Services"
        }
    ],
    "sg:phone":"+1 919 829 1712",
    "sg:postcode":"27610",
    "sg:province":"NC",
    "sg:tags":[
        "management"
    ],
    "wof:name":"Bowens Investment Group Inc",
    "wof:placetype":"venue"
},
  "geometry": {"coordinates":[-78.609245,35.749992],"type":"Point"}
}