{
  "type": "Feature",
  "properties": {
    "addr:full":"2312 Corporation Pkwy Burlington NC 27215",
    "addr:housenumber":"2312",
    "addr:postcode":"27215",
    "addr:street":"Corporation Pkwy",
    "iso:country":"US",
    "sg:address":"2312 Corporation Pkwy",
    "sg:city":"Burlington",
    "sg:classifiers":[
        {
            "category":"Shopping",
            "subcategory":"Clothing, Apparel, & Fashions",
            "type":"Retail Goods"
        }
    ],
    "sg:phone":"+1 336 222 8842",
    "sg:postcode":"27215",
    "sg:province":"NC",
    "wof:name":"Hospice League Clothing Store",
    "wof:placetype":"venue"
},
  "geometry": {"coordinates":[-79.436491,36.065187],"type":"Point"}
}