{
  "type": "Feature",
  "properties": {
    "addr:full":"640 Merrimon Ave Asheville NC 28804",
    "addr:housenumber":"640",
    "addr:postcode":"28804",
    "addr:street":"Merrimon Ave",
    "iso:country":"US",
    "sg:address":"640 Merrimon Ave",
    "sg:city":"Asheville",
    "sg:classifiers":[
        {
            "category":"Professional",
            "subcategory":"Management & Consulting",
            "type":"Services"
        }
    ],
    "sg:phone":"+1   ",
    "sg:postcode":"28804",
    "sg:province":"NC",
    "sg:tags":[
        "business"
    ],
    "wof:name":"Kumon",
    "wof:placetype":"venue"
},
  "geometry": {"coordinates":[-82.554495,35.620689],"type":"Point"}
}