{
  "type": "Feature",
  "properties": {
    "addr:full":"101 3rd St SE Catawba NC 28609",
    "addr:housenumber":"101",
    "addr:postcode":"28609",
    "addr:street":"3Rd St Se",
    "iso:country":"US",
    "sg:address":"101 3rd St SE",
    "sg:city":"Catawba",
    "sg:classifiers":[
        {
            "category":"Building & Trades",
            "subcategory":"Construction",
            "type":"Services"
        }
    ],
    "sg:phone":"+1 828 241 2493",
    "sg:postcode":"28609",
    "sg:province":"NC",
    "sg:tags":[
        "clearing",
        "land",
        "leveling"
    ],
    "wof:name":"Allen Mildred",
    "wof:placetype":"venue"
},
  "geometry": {"coordinates":[-81.06617799999999,35.703085],"type":"Point"}
}