{
  "type": "Feature",
  "properties": {
    "iso:country":"US",
    "sg:address":"1568 Bryant Rd",
    "sg:city":"Mount Airy",
    "sg:classifiers":[
        {
            "category":"Autos & Motor Vehicles",
            "subcategory":"Motorcycle Sales",
            "type":"Retail Goods"
        }
    ],
    "sg:phone":"+1 336 320 3802",
    "sg:postcode":"27030",
    "sg:province":"NC",
    "sg:tags":[
        "repair"
    ],
    "wof:name":"Crossroads Custom Cycles",
    "wof:placetype":"venue"
},
  "geometry": {"coordinates":[-80.774967,36.523033],"type":"Point"}
}