{
  "type": "Feature",
  "properties": {
    "iso:country":"US",
    "sg:address":"3018 S Main St",
    "sg:city":"Salisbury",
    "sg:classifiers":[
        {
            "category":"Shopping",
            "subcategory":"Computers & Home Electronics",
            "type":"Retail Goods"
        }
    ],
    "sg:phone":"+1 704 633 0337",
    "sg:postcode":"28147",
    "sg:province":"NC",
    "sg:tags":[
        "communication",
        "radio",
        "equipment"
    ],
    "wof:name":"Coates Communications Corp",
    "wof:placetype":"venue"
},
  "geometry": {"coordinates":[-80.50838,35.642392],"type":"Point"}
}