{
  "type": "Feature",
  "properties": {
    "iso:country":"US",
    "sg:address":"3140 Lake Shore Rd S",
    "sg:city":"Denver",
    "sg:classifiers":[
        {
            "category":"Organizations",
            "subcategory":"Non-profit Organization",
            "type":"Services"
        }
    ],
    "sg:phone":"+1   ",
    "sg:postcode":"28037",
    "sg:province":"NC",
    "sg:tags":[
        "social"
    ],
    "wof:name":"Solmaz Gungor Foundation",
    "wof:placetype":"venue"
},
  "geometry": {"coordinates":[-80.97867100000001,35.498734],"type":"Point"}
}