{
  "type": "Feature",
  "properties": {
    "iso:country":"US",
    "sg:address":"5912 Greenevers Dr",
    "sg:city":"Raleigh",
    "sg:classifiers":[
        {
            "category":"Professional",
            "subcategory":"Business Services",
            "type":"Services"
        }
    ],
    "sg:phone":"+1   ",
    "sg:postcode":"27613",
    "sg:province":"NC",
    "wof:name":"J E S Services Inc",
    "wof:placetype":"venue"
},
  "geometry": {"coordinates":[-78.688233,35.945293],"type":"Point"}
}