{
  "type": "Feature",
  "properties": {
    "iso:country":"US",
    "sg:address":"104 Forest Ridge Dr",
    "sg:city":"Willow Spring",
    "sg:classifiers":[
        {
            "category":"Building & Trades",
            "subcategory":"Plumbing",
            "type":"Services"
        }
    ],
    "sg:phone":"+1 919 894 5767",
    "sg:postcode":"27592",
    "sg:province":"NC",
    "sg:tags":[
        "contractor"
    ],
    "wof:name":"Comfort Control Services Inc",
    "wof:placetype":"venue"
},
  "geometry": {"coordinates":[-78.58978399999999,35.543084],"type":"Point"}
}