{
  "type": "Feature",
  "properties": {
    "iso:country":"US",
    "sg:address":"2901 Wheelock Rd",
    "sg:city":"Charlotte",
    "sg:classifiers":[
        {
            "category":"Farming",
            "subcategory":"Farm",
            "type":"Manufacturing & Wholesale Goods"
        }
    ],
    "sg:phone":"+1 704 364 1217",
    "sg:postcode":"28211",
    "sg:province":"NC",
    "wof:name":"Woodard E Farmer",
    "wof:placetype":"venue"
},
  "geometry": {"coordinates":[-80.826365,35.163366],"type":"Point"}
}