{
  "type": "Feature",
  "properties": {
    "iso:country":"US",
    "sg:address":"601 East Blvd",
    "sg:city":"Charlotte",
    "sg:classifiers":[
        {
            "category":"Organizations",
            "subcategory":"Religious Organization",
            "type":"Services"
        }
    ],
    "sg:phone":"+1   ",
    "sg:postcode":"28203",
    "sg:province":"NC",
    "wof:name":"Mecklenburg Ministries",
    "wof:placetype":"venue"
},
  "geometry": {"coordinates":[-80.851989,35.207468],"type":"Point"}
}