{
  "type": "Feature",
  "properties": {
    "addr:full":"75 N Main St Granite Falls NC 28630",
    "addr:housenumber":"75",
    "addr:postcode":"28630",
    "addr:street":"N Main St",
    "iso:country":"US",
    "sg:address":"75 N Main St",
    "sg:city":"Granite Falls",
    "sg:classifiers":[
        {
            "category":"Wholesale",
            "subcategory":"Auto Parts",
            "type":"Manufacturing & Wholesale Goods"
        }
    ],
    "sg:phone":"+1 828 396 2151",
    "sg:postcode":"28630",
    "sg:province":"NC",
    "wof:name":"Flowers Company",
    "wof:placetype":"venue"
},
  "geometry": {"coordinates":[-81.437094,35.800548],"type":"Point"}
}