{
  "type": "Feature",
  "properties": {
    "iso:country":"US",
    "sg:address":"13006 Central Ave",
    "sg:city":"Huntersville",
    "sg:classifiers":[
        {
            "category":"Organizations",
            "subcategory":"Religious Organization",
            "type":"Services"
        }
    ],
    "sg:phone":"+1   ",
    "sg:postcode":"28078",
    "sg:province":"NC",
    "wof:name":"United House Of Prayer",
    "wof:placetype":"venue"
},
  "geometry": {"coordinates":[-80.836341,35.39888],"type":"Point"}
}