{
  "type": "Feature",
  "properties": {
    "iso:country":"US",
    "sg:address":"1408 Hillsborough St",
    "sg:city":"Raleigh",
    "sg:classifiers":[
        {
            "category":"Organizations",
            "subcategory":"Labor Organization",
            "type":"Services"
        }
    ],
    "sg:phone":"+1   ",
    "sg:postcode":"27605",
    "sg:province":"NC",
    "wof:name":"Communcatns Wrkrs America Lcl",
    "wof:placetype":"venue"
},
  "geometry": {"coordinates":[-78.65743500000001,35.784064],"type":"Point"}
}