{
  "type": "Feature",
  "properties": {
    "addr:full":"3648 Oak Haven Ln Shelby NC 28150",
    "addr:housenumber":"3648",
    "addr:postcode":"28150",
    "addr:street":"Oak Haven Ln",
    "iso:country":"US",
    "sg:address":"3648 Oak Haven Ln",
    "sg:city":"Shelby",
    "sg:classifiers":[
        {
            "category":"Manufacturing",
            "subcategory":"Tools & Machinery",
            "type":"Manufacturing & Wholesale Goods"
        }
    ],
    "sg:phone":"+1 704 487 0105",
    "sg:postcode":"28150",
    "sg:province":"NC",
    "sg:tags":[
        "electric",
        "motor"
    ],
    "wof:name":"Servo South",
    "wof:placetype":"venue"
},
  "geometry": {"coordinates":[-81.61671200000001,35.379283],"type":"Point"}
}