{
  "type": "Feature",
  "properties": {
    "iso:country":"US",
    "sg:address":"175 Persimmon Dr",
    "sg:city":"Pinebluff",
    "sg:classifiers":[
        {
            "category":"Travel",
            "subcategory":"Hotels & Motels",
            "type":"Entertainment"
        }
    ],
    "sg:phone":"+1 910 281 3165",
    "sg:postcode":"28373",
    "sg:province":"NC",
    "wof:name":"Sandhills Lodge",
    "wof:placetype":"venue"
},
  "geometry": {"coordinates":[-79.484623,35.082706],"type":"Point"}
}