{
  "type": "Feature",
  "properties": {
    "iso:country":"US",
    "sg:address":"1625 E Broad St",
    "sg:city":"Statesville",
    "sg:classifiers":[
        {
            "category":"Wholesale",
            "subcategory":"Jewelry",
            "type":"Manufacturing & Wholesale Goods"
        }
    ],
    "sg:phone":"+1 704 873 7395",
    "sg:postcode":"28625",
    "sg:province":"NC",
    "sg:tags":[
        "stone"
    ],
    "wof:name":"Silver Mine",
    "wof:placetype":"venue"
},
  "geometry": {"coordinates":[-80.862281,35.791258],"type":"Point"}
}