{
  "type": "Feature",
  "properties": {
    "addr:full":"428 Camelia Dr Washington NC 27889",
    "addr:housenumber":"428",
    "addr:postcode":"27889",
    "addr:street":"Camelia Dr",
    "iso:country":"US",
    "sg:address":"428 Camelia Dr",
    "sg:city":"Washington",
    "sg:classifiers":[
        {
            "category":"Building & Trades",
            "subcategory":"Construction",
            "type":"Services"
        }
    ],
    "sg:phone":"+1 252 974 2020",
    "sg:postcode":"27889",
    "sg:province":"NC",
    "sg:tags":[
        "house",
        "ma",
        "contractor"
    ],
    "wof:name":"Simply Sun Rooms",
    "wof:placetype":"venue"
},
  "geometry": {"coordinates":[-77.026995,35.550385],"type":"Point"}
}