{
  "type": "Feature",
  "properties": {
    "iso:country":"US",
    "sg:address":"7633 US Hwy 64 E",
    "sg:city":"Knightdale",
    "sg:classifiers":[
        {
            "category":"Health Services",
            "subcategory":"Doctor",
            "type":"Services"
        }
    ],
    "sg:phone":"+1 919 266 7778",
    "sg:postcode":"27545",
    "sg:province":"NC",
    "sg:tags":[
        "dentist"
    ],
    "wof:name":"Malek & Knight Family Dntstry",
    "wof:placetype":"venue"
},
  "geometry": {"coordinates":[-78.47260199999999,35.800077],"type":"Point"}
}