{
  "type": "Feature",
  "properties": {
    "addr:full":"2404 Remington Rd Raleigh NC 27610",
    "addr:housenumber":"2404",
    "addr:postcode":"27610",
    "addr:street":"Remington Rd",
    "iso:country":"US",
    "sg:address":"2404 Remington Rd",
    "sg:city":"Raleigh",
    "sg:classifiers":[
        {
            "category":"Recreation",
            "type":"Entertainment"
        }
    ],
    "sg:phone":"+1   ",
    "sg:postcode":"27610",
    "sg:province":"NC",
    "wof:name":"Bridget Hodge Martial",
    "wof:placetype":"venue"
},
  "geometry": {"coordinates":[-78.60102000000001,35.793586],"type":"Point"}
}