{
  "type": "Feature",
  "properties": {
    "iso:country":"US",
    "sg:address":"6848 Free Union Church Rd",
    "sg:city":"Pinetown",
    "sg:classifiers":[
        {
            "category":"Wholesale",
            "subcategory":"Construction Materials",
            "type":"Manufacturing & Wholesale Goods"
        },
        {
            "category":"Manufacturing",
            "subcategory":"Lumber",
            "type":"Manufacturing & Wholesale Goods"
        }
    ],
    "sg:phone":"+1 252 943 6805",
    "sg:postcode":"27808",
    "sg:province":"NC",
    "sg:tags":[
        "timberland",
        "company",
        "logging",
        "timber"
    ],
    "wof:name":"Cahoon Logging Inc",
    "wof:placetype":"venue"
},
  "geometry": {"coordinates":[-76.75730900000001,35.541276],"type":"Point"}
}