{
  "type": "Feature",
  "properties": {
    "iso:country":"US",
    "sg:address":"3708 Holloway St",
    "sg:city":"Durham",
    "sg:classifiers":[
        {
            "category":"Building & Trades",
            "subcategory":"Cleaning & Sanitation",
            "type":"Services"
        }
    ],
    "sg:phone":"+1 919 598 1889",
    "sg:postcode":"27703",
    "sg:province":"NC",
    "sg:tags":[
        "help",
        "maintenance",
        "supply"
    ],
    "wof:name":"Merry Maids",
    "wof:placetype":"venue"
},
  "geometry": {"coordinates":[-78.822294,35.981724],"type":"Point"}
}