{
  "type": "Feature",
  "properties": {
    "addr:full":"815 Person St Fayetteville NC 28301",
    "addr:housenumber":"815",
    "addr:postcode":"28301",
    "addr:street":"Person St",
    "iso:country":"US",
    "sg:address":"815 Person St",
    "sg:city":"Fayetteville",
    "sg:classifiers":[
        {
            "category":"Building & Trades",
            "subcategory":"Electrical",
            "type":"Services"
        }
    ],
    "sg:phone":"+1 910 486 8111",
    "sg:postcode":"28301",
    "sg:province":"NC",
    "sg:tags":[
        "electric",
        "contractor"
    ],
    "wof:name":"RLC Circuitry Inc",
    "wof:placetype":"venue"
},
  "geometry": {"coordinates":[-78.862621,35.047755],"type":"Point"}
}