{
  "type": "Feature",
  "properties": {
    "iso:country":"US",
    "sg:address":"157 Arrowood Rd",
    "sg:city":"Weaverville",
    "sg:classifiers":[
        {
            "category":"Shopping",
            "subcategory":"Clothing, Apparel, & Fashions",
            "type":"Retail Goods"
        }
    ],
    "sg:phone":"+1 828 645 3483",
    "sg:postcode":"28787",
    "sg:province":"NC",
    "sg:tags":[
        "salvage",
        "surplus",
        "merchandise"
    ],
    "wof:name":"Surplussalesco.Com Inc",
    "wof:placetype":"venue"
},
  "geometry": {"coordinates":[-82.508545,35.782676],"type":"Point"}
}