{
  "type": "Feature",
  "properties": {
    "iso:country":"US",
    "sg:address":"125 Cape Point Blvd",
    "sg:city":"Swansboro",
    "sg:classifiers":[
        {
            "category":"Professional",
            "type":"Services"
        }
    ],
    "sg:phone":"+1 252 393 6801",
    "sg:postcode":"28584",
    "sg:province":"NC",
    "sg:tags":[
        "establishment"
    ],
    "wof:name":"Betts Smoke",
    "wof:placetype":"venue"
},
  "geometry": {"coordinates":[-77.057912,34.692012],"type":"Point"}
}