{
  "type": "Feature",
  "properties": {
    "iso:country":"US",
    "sg:address":"1000 Amble Dr",
    "sg:city":"Charlotte",
    "sg:classifiers":[
        {
            "category":"Professional",
            "subcategory":"Detective & Security Services",
            "type":"Services"
        }
    ],
    "sg:phone":"+1 704 334 1494",
    "sg:postcode":"28206",
    "sg:province":"NC",
    "sg:tags":[
        "guard",
        "patrol"
    ],
    "sg:website":"www.buddgroup.com",
    "wof:name":"Budd Integrated Security Systs",
    "wof:placetype":"venue"
},
  "geometry": {"coordinates":[-80.806799,35.269439],"type":"Point"}
}