{
  "type": "Feature",
  "properties": {
    "iso:country":"US",
    "sg:address":"949 N Shore Dr",
    "sg:city":"Southport",
    "sg:classifiers":[
        {
            "category":"Social Services",
            "subcategory":"Adult Care",
            "type":"Services"
        }
    ],
    "sg:phone":"+1   ",
    "sg:postcode":"28461",
    "sg:province":"NC",
    "sg:tags":[
        "residential"
    ],
    "wof:name":"Wallbrown Home Inc",
    "wof:placetype":"venue"
},
  "geometry": {"coordinates":[-78.05291,34.040889],"type":"Point"}
}