{
  "type": "Feature",
  "properties": {
    "iso:country":"US",
    "sg:address":"262 Springs Grove Ln",
    "sg:city":"Thomasville",
    "sg:classifiers":[
        {
            "category":"Building & Trades",
            "subcategory":"Plumbing",
            "type":"Services"
        }
    ],
    "sg:phone":"+1 336 472 7942",
    "sg:postcode":"27360",
    "sg:province":"NC",
    "sg:tags":[
        "contractor"
    ],
    "wof:name":"Gallimore Enterprises",
    "wof:placetype":"venue"
},
  "geometry": {"coordinates":[-80.075441,35.852133],"type":"Point"}
}