{
  "type": "Feature",
  "properties": {
    "addr:full":"1480 US Hwy 421 Boone NC 28607",
    "addr:housenumber":"1480",
    "addr:postcode":"28607",
    "addr:street":"Us Hwy 421",
    "iso:country":"US",
    "sg:address":"1480 US Hwy 421",
    "sg:city":"Boone",
    "sg:classifiers":[
        {
            "category":"Health Services",
            "subcategory":"Health Practitioner",
            "type":"Services"
        }
    ],
    "sg:phone":"+1 828 264 4040",
    "sg:postcode":"28607",
    "sg:province":"NC",
    "sg:tags":[
        "audiologists"
    ],
    "wof:name":"Ear Technologies",
    "wof:placetype":"venue"
},
  "geometry": {"coordinates":[-81.695763,36.221994],"type":"Point"}
}