{
  "type": "Feature",
  "properties": {
    "addr:full":"228 W Edenton St Raleigh NC 27603",
    "addr:housenumber":"228",
    "addr:postcode":"27603",
    "addr:street":"W Edenton St",
    "iso:country":"US",
    "sg:address":"228 W Edenton St",
    "sg:city":"Raleigh",
    "sg:classifiers":[
        {
            "category":"Social Services",
            "subcategory":"Child Care",
            "type":"Services"
        }
    ],
    "sg:phone":"+1 919 832 2029",
    "sg:postcode":"27603",
    "sg:province":"NC",
    "wof:name":"Edenton Street United",
    "wof:placetype":"venue"
},
  "geometry": {"coordinates":[-78.64286300000001,35.781417],"type":"Point"}
}