{
  "type": "Feature",
  "properties": {
    "addr:full":"2638 Norwood St SW Lenoir NC 28645",
    "addr:housenumber":"2638",
    "addr:postcode":"28645",
    "addr:street":"Norwood St Sw",
    "iso:country":"US",
    "sg:address":"2638 Norwood St SW",
    "sg:city":"Lenoir",
    "sg:classifiers":[
        {
            "category":"Food & Beverages",
            "subcategory":"Groceries & Convenience Stores",
            "type":"Retail Goods"
        }
    ],
    "sg:phone":"+1 828 726 8599",
    "sg:postcode":"28645",
    "sg:province":"NC",
    "sg:tags":[
        "fuel",
        "sporting",
        "oil"
    ],
    "wof:name":"Holiday Foods",
    "wof:placetype":"venue"
},
  "geometry": {"coordinates":[-81.508583,35.866617],"type":"Point"}
}