{
  "type": "Feature",
  "properties": {
    "addr:full":"3257 Snow Creek Rd NE Hickory NC 28601",
    "addr:housenumber":"3257",
    "addr:postcode":"28601",
    "addr:street":"Snow Creek Rd Ne",
    "iso:country":"US",
    "sg:address":"3257 Snow Creek Rd NE",
    "sg:city":"Hickory",
    "sg:classifiers":[
        {
            "category":"Retail",
            "subcategory":"Repair Shop",
            "type":"Services"
        }
    ],
    "sg:phone":"+1 828 444 9911",
    "sg:postcode":"28601",
    "sg:province":"NC",
    "sg:tags":[
        "welding"
    ],
    "wof:name":"Catawba Welding Inc",
    "wof:placetype":"venue"
},
  "geometry": {"coordinates":[-81.265953,35.782306],"type":"Point"}
}