{
  "type": "Feature",
  "properties": {
    "iso:country":"US",
    "sg:address":"1016 Paddock Dr",
    "sg:city":"Raleigh",
    "sg:classifiers":[
        {
            "category":"Building & Trades",
            "subcategory":"Cleaning & Sanitation",
            "type":"Services"
        }
    ],
    "sg:phone":"+1 919 431 9643",
    "sg:postcode":"27609",
    "sg:province":"NC",
    "sg:tags":[
        "janitor"
    ],
    "wof:name":"Crystal Cleaning Svc",
    "wof:placetype":"venue"
},
  "geometry": {"coordinates":[-78.618556,35.851293],"type":"Point"}
}