{
  "type": "Feature",
  "properties": {
    "addr:full":"4412 Caratoke Hwy Barco NC 27923",
    "addr:housenumber":"4412",
    "addr:postcode":"27923",
    "addr:street":"Caratoke Hwy",
    "iso:country":"US",
    "sg:address":"4412 Caratoke Hwy",
    "sg:city":"Barco",
    "sg:classifiers":[
        {
            "category":"Food & Beverages",
            "subcategory":"Groceries & Convenience Stores",
            "type":"Retail Goods"
        }
    ],
    "sg:phone":"+1 252 453 2669",
    "sg:postcode":"27923",
    "sg:province":"NC",
    "wof:name":"DI Food Mart",
    "wof:placetype":"venue"
},
  "geometry": {"coordinates":[-75.968834,36.365451],"type":"Point"}
}