{
  "type": "Feature",
  "properties": {
    "iso:country":"US",
    "sg:address":"1510 Timber Creek Ln",
    "sg:city":"Kernersville",
    "sg:classifiers":[
        {
            "category":"Wholesale",
            "subcategory":"Non-durable Goods",
            "type":"Manufacturing & Wholesale Goods"
        }
    ],
    "sg:phone":"+1 336 869 0638",
    "sg:postcode":"27284",
    "sg:province":"NC",
    "wof:name":"Global Art Importers Inc",
    "wof:placetype":"venue"
},
  "geometry": {"coordinates":[-80.062743,36.049859],"type":"Point"}
}