{
  "type": "Feature",
  "properties": {
    "addr:full":"4185 Patterson Ave Winston Salem NC 27105",
    "addr:housenumber":"4185",
    "addr:postcode":"27105",
    "addr:street":"Patterson Ave",
    "iso:country":"US",
    "sg:address":"4185 Patterson Ave",
    "sg:city":"Winston Salem",
    "sg:classifiers":[
        {
            "category":"Freight",
            "type":"Transportation"
        }
    ],
    "sg:phone":"+1 336 767 2525",
    "sg:postcode":"27105",
    "sg:province":"NC",
    "sg:tags":[
        "trucking"
    ],
    "wof:name":"Sam L Gray Trucking",
    "wof:placetype":"venue"
},
  "geometry": {"coordinates":[-80.260795,36.167509],"type":"Point"}
}