{
  "type": "Feature",
  "properties": {
    "addr:full":"842 Mount Zion Church Rd Casar NC 28020",
    "addr:housenumber":"842",
    "addr:postcode":"28020",
    "addr:street":"Mount Zion Church Rd",
    "iso:country":"US",
    "sg:address":"842 Mount Zion Church Rd",
    "sg:city":"Casar",
    "sg:classifiers":[
        {
            "category":"Building & Trades",
            "subcategory":"Construction",
            "type":"Services"
        }
    ],
    "sg:phone":"+1 704 538 8500",
    "sg:postcode":"28020",
    "sg:province":"NC",
    "sg:tags":[
        "utility",
        "contractor"
    ],
    "wof:name":"Utility Investment Recovery",
    "wof:placetype":"venue"
},
  "geometry": {"coordinates":[-81.65764,35.516489],"type":"Point"}
}