{
  "type": "Feature",
  "properties": {
    "iso:country":"US",
    "sg:address":"3616 Hopson Rd",
    "sg:city":"Morrisville",
    "sg:classifiers":[
        {
            "category":"Recreation",
            "type":"Entertainment"
        }
    ],
    "sg:phone":"+1 919 851 3385",
    "sg:postcode":"27560",
    "sg:province":"NC",
    "sg:tags":[
        "club",
        "range",
        "pistol",
        "shooting",
        "rifle"
    ],
    "wof:name":"Durham County Wildlife Club",
    "wof:placetype":"venue"
},
  "geometry": {"coordinates":[-78.883954,35.877164],"type":"Point"}
}