{
  "type": "Feature",
  "properties": {
    "iso:country":"US",
    "sg:address":"2139 Textile Dr",
    "sg:city":"Greensboro",
    "sg:classifiers":[
        {
            "category":"Organizations",
            "subcategory":"Religious Organization",
            "type":"Services"
        }
    ],
    "sg:phone":"+1   ",
    "sg:postcode":"27405",
    "sg:province":"NC",
    "wof:name":"Church of First Born",
    "wof:placetype":"venue"
},
  "geometry": {"coordinates":[-79.75348,36.093607],"type":"Point"}
}