{
  "type": "Feature",
  "properties": {
    "addr:full":"5010 Albemarle Rd Charlotte NC 28205",
    "addr:housenumber":"5010",
    "addr:postcode":"28205",
    "addr:street":"Albemarle Rd",
    "iso:country":"US",
    "sg:address":"5010 Albemarle Rd",
    "sg:city":"Charlotte",
    "sg:classifiers":[
        {
            "category":"Insurance",
            "subcategory":"Insurance Agent",
            "type":"Services"
        }
    ],
    "sg:phone":"+1 704 568 5900",
    "sg:postcode":"28205",
    "sg:province":"NC",
    "wof:name":"Ameri Life & Health Services",
    "wof:placetype":"venue"
},
  "geometry": {"coordinates":[-80.761214,35.201429],"type":"Point"}
}