{
  "type": "Feature",
  "properties": {
    "addr:full":"1230 E Main St Albemarle NC 28001",
    "addr:housenumber":"1230",
    "addr:postcode":"28001",
    "addr:street":"E Main St",
    "iso:country":"US",
    "sg:address":"1230 E Main St",
    "sg:city":"Albemarle",
    "sg:classifiers":[
        {
            "category":"Restaurant",
            "type":"Food & Drink"
        }
    ],
    "sg:phone":"+1 704 983 6171",
    "sg:postcode":"28001",
    "sg:province":"NC",
    "wof:name":"Jay's Downtowner Restaurant",
    "wof:placetype":"venue"
},
  "geometry": {"coordinates":[-80.17954400000001,35.352474],"type":"Point"}
}