{
  "type": "Feature",
  "properties": {
    "addr:full":"4300 Ludgate St Lumberton NC 28358",
    "addr:housenumber":"4300",
    "addr:postcode":"28358",
    "addr:street":"Ludgate St",
    "iso:country":"US",
    "sg:address":"4300 Ludgate St",
    "sg:city":"Lumberton",
    "sg:classifiers":[
        {
            "category":"Health Services",
            "subcategory":"Doctor",
            "type":"Services"
        }
    ],
    "sg:phone":"+1 910 738 4465",
    "sg:postcode":"28358",
    "sg:province":"NC",
    "sg:tags":[
        "dentist"
    ],
    "wof:name":"Edward P Jessup DDS",
    "wof:placetype":"venue"
},
  "geometry": {"coordinates":[-79.00177600000001,34.653655],"type":"Point"}
}