{
  "type": "Feature",
  "properties": {
    "addr:full":"3 Spring Glen Ct Durham NC 27703",
    "addr:housenumber":"3",
    "addr:postcode":"27703",
    "addr:street":"Spring Glen Ct",
    "iso:country":"US",
    "sg:address":"3 Spring Glen Ct",
    "sg:city":"Durham",
    "sg:classifiers":[
        {
            "category":"Professional",
            "subcategory":"Business Services",
            "type":"Services"
        }
    ],
    "sg:phone":"+1   ",
    "sg:postcode":"27703",
    "sg:province":"NC",
    "wof:name":"Jlh Crushing Solutions",
    "wof:placetype":"venue"
},
  "geometry": {"coordinates":[-78.808199,35.980825],"type":"Point"}
}