{
  "type": "Feature",
  "properties": {
    "addr:full":"4963 Rosehill Rd Fayetteville NC 28311",
    "addr:housenumber":"4963",
    "addr:postcode":"28311",
    "addr:street":"Rosehill Rd",
    "iso:country":"US",
    "sg:address":"4963 Rosehill Rd",
    "sg:city":"Fayetteville",
    "sg:classifiers":[
        {
            "category":"Education",
            "subcategory":"School",
            "type":"Public Place"
        }
    ],
    "sg:phone":"+1 910 488 6650",
    "sg:postcode":"28311",
    "sg:province":"NC",
    "wof:name":"College Lakes Elementary Schl",
    "wof:placetype":"venue"
},
  "geometry": {"coordinates":[-78.899068,35.126437],"type":"Point"}
}