{
  "type": "Feature",
  "properties": {
    "addr:full":"124 Walter Rd Dudley NC 28327",
    "addr:housenumber":"124",
    "addr:postcode":"28327",
    "addr:street":"Walter Rd",
    "iso:country":"US",
    "sg:address":"124 Walter Rd",
    "sg:city":"Dudley",
    "sg:classifiers":[
        {
            "category":"Education",
            "subcategory":"School",
            "type":"Public Place"
        }
    ],
    "sg:phone":"+1 919 705 6060",
    "sg:postcode":"28327",
    "sg:province":"NC",
    "wof:name":"Southern Wayne High School",
    "wof:placetype":"venue"
},
  "geometry": {"coordinates":[-79.380768,35.306257],"type":"Point"}
}