{
  "type": "Feature",
  "properties": {
    "addr:full":"218 E 5th St Greenville NC 27858",
    "addr:housenumber":"218",
    "addr:postcode":"27858",
    "addr:street":"E 5Th St",
    "iso:country":"US",
    "sg:address":"218 E 5th St",
    "sg:city":"Greenville",
    "sg:classifiers":[
        {
            "category":"Bars & Pubs",
            "type":"Food & Drink"
        }
    ],
    "sg:phone":"+1 252 758 6227",
    "sg:postcode":"27858",
    "sg:province":"NC",
    "wof:name":"Scores Sports Bar",
    "wof:placetype":"venue"
},
  "geometry": {"coordinates":[-77.371852,35.610869],"type":"Point"}
}