{
  "type": "Feature",
  "properties": {
    "addr:full":"8281 Hillside Dr Raleigh NC 27612",
    "addr:housenumber":"8281",
    "addr:postcode":"27612",
    "addr:street":"Hillside Dr",
    "iso:country":"US",
    "sg:address":"8281 Hillside Dr",
    "sg:city":"Raleigh",
    "sg:classifiers":[
        {
            "category":"Social Services",
            "subcategory":"Job Training",
            "type":"Services"
        }
    ],
    "sg:phone":"+1   ",
    "sg:postcode":"27612",
    "sg:province":"NC",
    "wof:name":"Bpm Inc",
    "wof:placetype":"venue"
},
  "geometry": {"coordinates":[-78.734763,35.873335],"type":"Point"}
}