{
  "type": "Feature",
  "properties": {
    "addr:full":"1721 N Wesleyan Blvd Rocky Mount NC 27804",
    "addr:housenumber":"1721",
    "addr:postcode":"27804",
    "addr:street":"N Wesleyan Blvd",
    "iso:country":"US",
    "sg:address":"1721 N Wesleyan Blvd",
    "sg:city":"Rocky Mount",
    "sg:classifiers":[
        {
            "category":"Retail",
            "subcategory":"Auto Repair",
            "type":"Services"
        }
    ],
    "sg:phone":"+1 252 977 1450",
    "sg:postcode":"27804",
    "sg:province":"NC",
    "sg:tags":[
        "wrecker"
    ],
    "wof:name":"By-Pass Wrecker Svc-24 Hrs",
    "wof:placetype":"venue"
},
  "geometry": {"coordinates":[-77.784226,35.98527],"type":"Point"}
}