{
  "type": "Feature",
  "properties": {
    "iso:country":"US",
    "sg:address":"5003 Tewkesbury Rd",
    "sg:city":"Charlotte",
    "sg:classifiers":[
        {
            "category":"Health Services",
            "subcategory":"Nursing And Care Facility",
            "type":"Services"
        },
        {
            "category":"Health Services",
            "subcategory":"Health Practitioner",
            "type":"Services"
        },
        {
            "category":"Social Services",
            "subcategory":"Retirement Home",
            "type":"Services"
        },
        {
            "category":"Social Services",
            "subcategory":"Adult Care",
            "type":"Services"
        }
    ],
    "sg:phone":"+1 704 453 6753",
    "sg:postcode":"28269",
    "sg:province":"NC",
    "sg:tags":[
        "living",
        "assisted",
        "rest",
        "elder"
    ],
    "sg:website":"http://www.upfamilyhomecare.com",
    "wof:name":"Unlimited Possibilities Family Home Care",
    "wof:placetype":"venue"
},
  "geometry": {"coordinates":[-80.813,35.289766],"type":"Point"}
}