{
  "type": "Feature",
  "properties": {
    "iso:country":"US",
    "sg:address":"1772 Howard Gap Rd",
    "sg:city":"Hendersonville",
    "sg:classifiers":[
        {
            "category":"Retail",
            "subcategory":"Animal Services",
            "type":"Services"
        }
    ],
    "sg:phone":"+1 828 697 8797",
    "sg:postcode":"28792",
    "sg:province":"NC",
    "sg:tags":[
        "pet",
        "grooming"
    ],
    "wof:name":"Pampered Paws Pet Salon",
    "wof:placetype":"venue"
},
  "geometry": {"coordinates":[-82.473833,35.379156],"type":"Point"}
}