{
  "type": "Feature",
  "properties": {
    "iso:country":"US",
    "sg:address":"761 Tabor Rd",
    "sg:city":"Olin",
    "sg:classifiers":[
        {
            "category":"Freight",
            "type":"Transportation"
        }
    ],
    "sg:phone":"+1 704 546 2104",
    "sg:postcode":"28660",
    "sg:province":"NC",
    "sg:tags":[
        "operator",
        "local",
        "trucking"
    ],
    "wof:name":"Joe Louis Allison Trucking",
    "wof:placetype":"venue"
},
  "geometry": {"coordinates":[-80.805076,35.951139],"type":"Point"}
}