{
  "type": "Feature",
  "properties": {
    "addr:full":"3823 Durham-Chapel Hill Blvd Durham NC 27707",
    "addr:housenumber":"3823",
    "addr:postcode":"27707",
    "addr:street":"Durham-Chapel Hill Blvd",
    "iso:country":"US",
    "sg:address":"3823 Durham-Chapel Hill Blvd",
    "sg:city":"Durham",
    "sg:classifiers":[
        {
            "category":"Autos & Motor Vehicles",
            "subcategory":"Automobile Sales",
            "type":"Retail Goods"
        }
    ],
    "sg:phone":"+1 919 493 7411",
    "sg:postcode":"27707",
    "sg:province":"NC",
    "sg:tags":[
        "car",
        "dealer"
    ],
    "wof:name":"Southern State Volkswagen",
    "wof:placetype":"venue"
},
  "geometry": {"coordinates":[-78.95298,35.970786],"type":"Point"}
}