{
  "type": "Feature",
  "properties": {
    "iso:country":"US",
    "sg:address":"2966 S Church St",
    "sg:city":"Burlington",
    "sg:classifiers":[
        {
            "category":"Professional",
            "subcategory":"Business Services",
            "type":"Services"
        }
    ],
    "sg:phone":"+1 336 584 3030",
    "sg:postcode":"27215",
    "sg:province":"NC",
    "sg:tags":[
        "record",
        "medical"
    ],
    "wof:name":"Marketing Resources Inc",
    "wof:placetype":"venue"
},
  "geometry": {"coordinates":[-79.49529699999999,36.080125],"type":"Point"}
}