{
  "type": "Feature",
  "properties": {
    "addr:full":"2201 Randleman Rd Greensboro NC 27406",
    "addr:housenumber":"2201",
    "addr:postcode":"27406",
    "addr:street":"Randleman Rd",
    "iso:country":"US",
    "sg:address":"2201 Randleman Rd",
    "sg:city":"Greensboro",
    "sg:classifiers":[
        {
            "category":"Professional",
            "subcategory":"Accounting & Tax Preparation",
            "type":"Services"
        }
    ],
    "sg:phone":"+1 336 273 3344",
    "sg:postcode":"27406",
    "sg:province":"NC",
    "sg:tags":[
        "return",
        "filing"
    ],
    "wof:name":"H & R Block Tax Svc",
    "wof:placetype":"venue"
},
  "geometry": {"coordinates":[-79.80041799999999,36.044894],"type":"Point"}
}