{
  "type": "Feature",
  "properties": {
    "addr:full":"1203 Jackson Rd Gastonia NC 28052",
    "addr:housenumber":"1203",
    "addr:postcode":"28052",
    "addr:street":"Jackson Rd",
    "iso:country":"US",
    "sg:address":"1203 Jackson Rd",
    "sg:city":"Gastonia",
    "sg:classifiers":[
        {
            "category":"Insurance",
            "subcategory":"Hazard Insurance",
            "type":"Services"
        }
    ],
    "sg:phone":"+1 704 861 9403",
    "sg:postcode":"28052",
    "sg:province":"NC",
    "sg:website":"http://facebook.com/bradleygriffin.ins",
    "wof:name":"Bradley-Griffin Insurance",
    "wof:placetype":"venue"
},
  "geometry": {"coordinates":[-81.191261,35.248451],"type":"Point"}
}