{
  "type": "Feature",
  "properties": {
    "addr:full":"17 Colonial Dr Lexington NC 27292",
    "addr:housenumber":"17",
    "addr:postcode":"27292",
    "addr:street":"Colonial Dr",
    "iso:country":"US",
    "sg:address":"17 Colonial Dr",
    "sg:city":"Lexington",
    "sg:classifiers":[
        {
            "category":"Building & Trades",
            "subcategory":"Electrical",
            "type":"Services"
        }
    ],
    "sg:phone":"+1 336 249 1768",
    "sg:postcode":"27292",
    "sg:province":"NC",
    "sg:tags":[
        "electric",
        "contractor"
    ],
    "wof:name":"Moore Electric Co",
    "wof:placetype":"venue"
},
  "geometry": {"coordinates":[-80.22073899999999,35.798229],"type":"Point"}
}