{
  "type": "Feature",
  "properties": {
    "iso:country":"US",
    "sg:address":"100 Factory Shops Rd",
    "sg:city":"Morrisville",
    "sg:classifiers":[
        {
            "category":"Food & Beverages",
            "subcategory":"Groceries & Convenience Stores",
            "type":"Retail Goods"
        }
    ],
    "sg:phone":"+1 919 467 6009",
    "sg:postcode":"27560",
    "sg:province":"NC",
    "wof:name":"Kangaroo Express",
    "wof:placetype":"venue"
},
  "geometry": {"coordinates":[-78.819323,35.862966],"type":"Point"}
}