{
  "type": "Feature",
  "properties": {
    "iso:country":"US",
    "sg:address":"4132 Hickory Blvd",
    "sg:city":"Granite Falls",
    "sg:classifiers":[
        {
            "category":"Health Services",
            "subcategory":"Doctor",
            "type":"Services"
        }
    ],
    "sg:phone":"+1 828 396 3168",
    "sg:postcode":"28630",
    "sg:province":"NC",
    "sg:tags":[
        "physician",
        "surgeon"
    ],
    "wof:name":"Granite Falls Family Med Ctr",
    "wof:placetype":"venue"
},
  "geometry": {"coordinates":[-81.429614,35.808218],"type":"Point"}
}