{
  "type": "Feature",
  "properties": {
    "addr:full":"1676 Airport Rd Chapel Hill NC 27514",
    "addr:housenumber":"1676",
    "addr:postcode":"27514",
    "addr:street":"Airport Rd",
    "iso:country":"US",
    "sg:address":"1676 Airport Rd",
    "sg:city":"Chapel Hill",
    "sg:classifiers":[
        {
            "category":"Personal",
            "type":"Services"
        }
    ],
    "sg:phone":"+1   ",
    "sg:postcode":"27514",
    "sg:province":"NC",
    "wof:name":"Daniel Hartgrove",
    "wof:placetype":"venue"
},
  "geometry": {"coordinates":[-79.057957,35.963103],"type":"Point"}
}