{
  "type": "Feature",
  "properties": {
    "iso:country":"US",
    "sg:address":"10129 Katelyn Dr",
    "sg:city":"Charlotte",
    "sg:classifiers":[
        {
            "category":"Professional",
            "type":"Services"
        }
    ],
    "sg:phone":"+1 704 548 2578",
    "sg:postcode":"28269",
    "sg:province":"NC",
    "wof:name":"Paul Dehaan",
    "wof:placetype":"venue"
},
  "geometry": {"coordinates":[-80.77953599999999,35.351198],"type":"Point"}
}