{
  "type": "Feature",
  "properties": {
    "addr:full":"6181 US Hwy 421 Vilas NC 28692",
    "addr:housenumber":"6181",
    "addr:postcode":"28692",
    "addr:street":"Us Hwy 421",
    "iso:country":"US",
    "sg:address":"6181 US Hwy 421",
    "sg:city":"Vilas",
    "sg:classifiers":[
        {
            "category":"Retail",
            "subcategory":"Auto Repair",
            "type":"Services"
        }
    ],
    "sg:phone":"+1   ",
    "sg:postcode":"28692",
    "sg:province":"NC",
    "sg:tags":[
        "exhaust",
        "general"
    ],
    "wof:name":"High Country Muffler",
    "wof:placetype":"venue"
},
  "geometry": {"coordinates":[-81.767656,36.259742],"type":"Point"}
}