{
  "type": "Feature",
  "properties": {
    "addr:full":"2638 Willard Rd High Point NC 27265",
    "addr:housenumber":"2638",
    "addr:postcode":"27265",
    "addr:street":"Willard Rd",
    "iso:country":"US",
    "sg:address":"2638 Willard Rd",
    "sg:city":"High Point",
    "sg:classifiers":[
        {
            "category":"Wholesale",
            "subcategory":"Durable Goods & Equipment",
            "type":"Manufacturing & Wholesale Goods"
        }
    ],
    "sg:phone":"+1 336 812 9651",
    "sg:postcode":"27265",
    "sg:province":"NC",
    "sg:tags":[
        "importer"
    ],
    "wof:name":"Direct Access Intl",
    "wof:placetype":"venue"
},
  "geometry": {"coordinates":[-79.962771,36.013734],"type":"Point"}
}