{
  "type": "Feature",
  "properties": {
    "addr:full":"204 W Clay St Mebane NC 27302",
    "addr:housenumber":"204",
    "addr:postcode":"27302",
    "addr:street":"W Clay St",
    "iso:country":"US",
    "sg:address":"204 W Clay St",
    "sg:city":"Mebane",
    "sg:classifiers":[
        {
            "category":"Professional",
            "subcategory":"Engineering",
            "type":"Services"
        }
    ],
    "sg:phone":"+1 919 563 9041",
    "sg:postcode":"27302",
    "sg:province":"NC",
    "sg:tags":[
        "engineer"
    ],
    "wof:name":"Earthcentric Engineering",
    "wof:placetype":"venue"
},
  "geometry": {"coordinates":[-79.27060299999999,36.097962],"type":"Point"}
}