{
  "type": "Feature",
  "properties": {
    "addr:full":"102 Pritchard St Elizabeth City NC 27909",
    "addr:housenumber":"102",
    "addr:postcode":"27909",
    "addr:street":"Pritchard St",
    "iso:country":"US",
    "sg:address":"102 Pritchard St",
    "sg:city":"Elizabeth City",
    "sg:classifiers":[
        {
            "category":"Food & Beverages",
            "subcategory":"Specialty",
            "type":"Retail Goods"
        }
    ],
    "sg:phone":"+1 252 338 8062",
    "sg:postcode":"27909",
    "sg:province":"NC",
    "wof:name":"British American Tea & Coffee",
    "wof:placetype":"venue"
},
  "geometry": {"coordinates":[-76.237285,36.302911],"type":"Point"}
}