{
  "type": "Feature",
  "properties": {
    "addr:full":"112 N Main St Lowell NC 28098",
    "addr:housenumber":"112",
    "addr:postcode":"28098",
    "addr:street":"N Main St",
    "iso:country":"US",
    "sg:address":"112 N Main St",
    "sg:city":"Lowell",
    "sg:classifiers":[
        {
            "category":"Shopping",
            "type":"Retail Goods"
        }
    ],
    "sg:phone":"+1 704 823 7142",
    "sg:postcode":"28098",
    "sg:province":"NC",
    "sg:tags":[
        "candle",
        "merchandise"
    ],
    "sg:website":"www.elkcreekcandleco.com",
    "wof:name":"Elk Creek Candle Company",
    "wof:placetype":"venue"
},
  "geometry": {"coordinates":[-81.100341,35.267162],"type":"Point"}
}