{
  "type": "Feature",
  "properties": {
    "iso:country":"US",
    "sg:address":"14 W Haven Pl",
    "sg:city":"Durham",
    "sg:classifiers":[
        {
            "category":"Professional",
            "subcategory":"Lawyer & Legal Services",
            "type":"Services"
        }
    ],
    "sg:phone":"+1 919 382 9090",
    "sg:postcode":"27705",
    "sg:province":"NC",
    "sg:tags":[
        "attorney"
    ],
    "wof:name":"Frances Mock Attorney",
    "wof:placetype":"venue"
},
  "geometry": {"coordinates":[-78.964569,36.038099],"type":"Point"}
}