{
  "type": "Feature",
  "properties": {
    "addr:full":"2500 Chapel Hill Rd Durham NC 27707",
    "addr:housenumber":"2500",
    "addr:postcode":"27707",
    "addr:street":"Chapel Hill Rd",
    "iso:country":"US",
    "sg:address":"2500 Chapel Hill Rd",
    "sg:city":"Durham",
    "sg:classifiers":[
        {
            "category":"Organizations",
            "subcategory":"Religious Organization",
            "type":"Services"
        }
    ],
    "sg:phone":"+1 919 403 0452",
    "sg:postcode":"27707",
    "sg:province":"NC",
    "sg:tags":[
        "church"
    ],
    "wof:name":"Life Community Church",
    "wof:placetype":"venue"
},
  "geometry": {"coordinates":[-78.93431699999999,35.981148],"type":"Point"}
}