{
  "type": "Feature",
  "properties": {
    "addr:full":"152 Lees Lake Dr New Bern NC 28562",
    "addr:housenumber":"152",
    "addr:postcode":"28562",
    "addr:street":"Lees Lake Dr",
    "iso:country":"US",
    "sg:address":"152 Lees Lake Dr",
    "sg:city":"New Bern",
    "sg:classifiers":[
        {
            "category":"Shopping",
            "subcategory":"Jewelry",
            "type":"Retail Goods"
        }
    ],
    "sg:phone":"+1 252 349 5354",
    "sg:postcode":"28562",
    "sg:province":"NC",
    "wof:name":"Richard Michael Hearne",
    "wof:placetype":"venue"
},
  "geometry": {"coordinates":[-77.02477,35.020533],"type":"Point"}
}