{
  "type": "Feature",
  "properties": {
    "iso:country":"US",
    "sg:address":"214 Manchester Pl",
    "sg:city":"Greensboro",
    "sg:classifiers":[
        {
            "category":"Real Estate",
            "subcategory":"Real Estate Agent",
            "type":"Services"
        }
    ],
    "sg:phone":"+1 336 299 8628",
    "sg:postcode":"27410",
    "sg:province":"NC",
    "wof:name":"Ackermann & Assoc Inc",
    "wof:placetype":"venue"
},
  "geometry": {"coordinates":[-79.854563,36.07485],"type":"Point"}
}