{
  "type": "Feature",
  "properties": {
    "addr:full":"1349 Charlotte Hwy Fairview NC 28730",
    "addr:housenumber":"1349",
    "addr:postcode":"28730",
    "addr:street":"Charlotte Hwy",
    "iso:country":"US",
    "sg:address":"1349 Charlotte Hwy",
    "sg:city":"Fairview",
    "sg:classifiers":[
        {
            "category":"Building & Trades",
            "subcategory":"Construction",
            "type":"Services"
        }
    ],
    "sg:phone":"+1 828 628 2445",
    "sg:postcode":"28730",
    "sg:province":"NC",
    "sg:tags":[
        "contractor"
    ],
    "wof:name":"Innovative Building Concept",
    "wof:placetype":"venue"
},
  "geometry": {"coordinates":[-82.415117,35.523457],"type":"Point"}
}