{
  "type": "Feature",
  "properties": {
    "addr:full":"5140 Revere Rd Durham NC 27713",
    "addr:housenumber":"5140",
    "addr:postcode":"27713",
    "addr:street":"Revere Rd",
    "iso:country":"US",
    "sg:address":"5140 Revere Rd",
    "sg:city":"Durham",
    "sg:classifiers":[
        {
            "category":"Building & Trades",
            "subcategory":"Landscaping Services",
            "type":"Services"
        }
    ],
    "sg:phone":"+1 919 218 6374",
    "sg:postcode":"27713",
    "sg:province":"NC",
    "sg:tags":[
        "lawn",
        "landscape",
        "maintenance",
        "contractor"
    ],
    "sg:website":"http://www.addedtouchlandscaping.com",
    "wof:name":"Added Touch Landscaping",
    "wof:placetype":"venue"
},
  "geometry": {"coordinates":[-78.910274,35.894518],"type":"Point"}
}