{
  "type": "Feature",
  "properties": {
    "addr:full":"4820 South Blvd Charlotte NC 28217",
    "addr:housenumber":"4820",
    "addr:postcode":"28217",
    "addr:street":"South Blvd",
    "iso:country":"US",
    "sg:address":"4820 South Blvd",
    "sg:city":"Charlotte",
    "sg:classifiers":[
        {
            "category":"Restaurant",
            "type":"Food & Drink"
        }
    ],
    "sg:menulink":"http://www.allmenus.com/nc/charlotte/84160-papa-johns-pizza/menu/",
    "sg:phone":"+1 704 522 7272",
    "sg:postcode":"28217",
    "sg:province":"NC",
    "sg:tags":[
        "american",
        "pizza"
    ],
    "wof:name":"Papa John's Pizza",
    "wof:placetype":"venue"
},
  "geometry": {"coordinates":[-80.87647800000001,35.173137],"type":"Point"}
}