{
  "type": "Feature",
  "properties": {
    "iso:country":"US",
    "sg:address":"1671 E Marion St",
    "sg:city":"Shelby",
    "sg:classifiers":[
        {
            "category":"Shopping",
            "subcategory":"Used Merchandise",
            "type":"Retail Goods"
        }
    ],
    "sg:phone":"+1 704 482 4062",
    "sg:postcode":"28150",
    "sg:province":"NC",
    "sg:tags":[
        "antique"
    ],
    "wof:name":"Ken's Antiques",
    "wof:placetype":"venue"
},
  "geometry": {"coordinates":[-81.492282,35.28436],"type":"Point"}
}