{
  "type": "Feature",
  "properties": {
    "iso:country":"US",
    "sg:address":"206 S Collins St",
    "sg:city":"Nashville",
    "sg:classifiers":[
        {
            "category":"Shopping",
            "subcategory":"Musical Instruments",
            "type":"Retail Goods"
        }
    ],
    "sg:phone":"+1 252 442 4423",
    "sg:postcode":"27856",
    "sg:province":"NC",
    "sg:tags":[
        "piano"
    ],
    "wof:name":"Maus Music Ctr Inc",
    "wof:placetype":"venue"
},
  "geometry": {"coordinates":[-77.965227,35.971976],"type":"Point"}
}