{
  "type": "Feature",
  "properties": {
    "iso:country":"US",
    "sg:address":"923 Franklin St",
    "sg:city":"Durham",
    "sg:classifiers":[
        {
            "category":"Professional",
            "subcategory":"Accounting & Tax Preparation",
            "type":"Services"
        }
    ],
    "sg:phone":"+1 919 682 8534",
    "sg:postcode":"27701",
    "sg:province":"NC",
    "sg:tags":[
        "accountant"
    ],
    "wof:name":"Clifton R Stancil CPA Pa",
    "wof:placetype":"venue"
},
  "geometry": {"coordinates":[-78.889437,35.990456],"type":"Point"}
}