{
  "type": "Feature",
  "properties": {
    "addr:full":"450 View Rd Sapphire NC 28774",
    "addr:housenumber":"450",
    "addr:postcode":"28774",
    "addr:street":"View Rd",
    "iso:country":"US",
    "sg:address":"450 View Rd",
    "sg:city":"Sapphire",
    "sg:classifiers":[
        {
            "category":"Professional",
            "subcategory":"Management & Consulting",
            "type":"Services"
        }
    ],
    "sg:phone":"+1   ",
    "sg:postcode":"28774",
    "sg:province":"NC",
    "sg:tags":[
        "business"
    ],
    "wof:name":"Caskey Enterprises",
    "wof:placetype":"venue"
},
  "geometry": {"coordinates":[-83.075092,35.139948],"type":"Point"}
}