{
  "type": "Feature",
  "properties": {
    "addr:full":"221 Jefferson St Whiteville NC 28472",
    "addr:housenumber":"221",
    "addr:postcode":"28472",
    "addr:street":"Jefferson St",
    "iso:country":"US",
    "sg:address":"221 Jefferson St",
    "sg:city":"Whiteville",
    "sg:classifiers":[
        {
            "category":"Health Services",
            "subcategory":"Optometrist",
            "type":"Services"
        }
    ],
    "sg:phone":"+1 910 640 2020",
    "sg:postcode":"28472",
    "sg:province":"NC",
    "wof:name":"Vision Connection",
    "wof:placetype":"venue"
},
  "geometry": {"coordinates":[-78.70038,34.338405],"type":"Point"}
}