{
  "type": "Feature",
  "properties": {
    "addr:full":"4921 US Hwy 74 Monroe NC 28110",
    "addr:housenumber":"4921",
    "addr:postcode":"28110",
    "addr:street":"Us Hwy 74",
    "iso:country":"US",
    "sg:address":"4921 US Hwy 74",
    "sg:city":"Monroe",
    "sg:classifiers":[
        {
            "category":"Autos & Motor Vehicles",
            "subcategory":"Recreational Vehicle Sales",
            "type":"Retail Goods"
        }
    ],
    "sg:phone":"+1 704 291 9779",
    "sg:postcode":"28110",
    "sg:province":"NC",
    "sg:website":"www.suncoastrv.com",
    "wof:name":"Suncoast Rv",
    "wof:placetype":"venue"
},
  "geometry": {"coordinates":[-80.62161399999999,35.052123],"type":"Point"}
}