{
  "type": "Feature",
  "properties": {
    "addr:full":"2006 Fernwood Dr Greensboro NC 27408",
    "addr:housenumber":"2006",
    "addr:postcode":"27408",
    "addr:street":"Fernwood Dr",
    "iso:country":"US",
    "sg:address":"2006 Fernwood Dr",
    "sg:city":"Greensboro",
    "sg:classifiers":[
        {
            "category":"Real Estate",
            "subcategory":"Architect",
            "type":"Services"
        }
    ],
    "sg:phone":"+1   ",
    "sg:postcode":"27408",
    "sg:province":"NC",
    "sg:tags":[
        "architectural"
    ],
    "wof:name":"Brown Dog Designs Ltd",
    "wof:placetype":"venue"
},
  "geometry": {"coordinates":[-79.81707900000001,36.100395],"type":"Point"}
}