{
  "type": "Feature",
  "properties": {
    "iso:country":"US",
    "sg:address":"16 Lous Chapel Rd",
    "sg:city":"Spring Lake",
    "sg:classifiers":[
        {
            "category":"Organizations",
            "subcategory":"Religious Organization",
            "type":"Services"
        }
    ],
    "sg:phone":"+1 910 497 3330",
    "sg:postcode":"28390",
    "sg:province":"NC",
    "sg:tags":[
        "church"
    ],
    "wof:name":"Creeksville AME Zion Church",
    "wof:placetype":"venue"
},
  "geometry": {"coordinates":[-78.948723,35.222679],"type":"Point"}
}