{
  "type": "Feature",
  "properties": {
    "addr:full":"725 Demco Dr Salisbury NC 28147",
    "addr:housenumber":"725",
    "addr:postcode":"28147",
    "addr:street":"Demco Dr",
    "iso:country":"US",
    "sg:address":"725 Demco Dr",
    "sg:city":"Salisbury",
    "sg:classifiers":[
        {
            "category":"Wholesale",
            "subcategory":"Electrical",
            "type":"Manufacturing & Wholesale Goods"
        }
    ],
    "sg:phone":"+1 704 633 3709",
    "sg:postcode":"28147",
    "sg:province":"NC",
    "sg:tags":[
        "repair",
        "motor"
    ],
    "wof:name":"Delta Electric Inc",
    "wof:placetype":"venue"
},
  "geometry": {"coordinates":[-80.50093099999999,35.665778],"type":"Point"}
}