{
  "type": "Feature",
  "properties": {
    "addr:full":"495 Country Place Dr Boone NC 28607",
    "addr:housenumber":"495",
    "addr:postcode":"28607",
    "addr:street":"Country Place Dr",
    "iso:country":"US",
    "sg:address":"495 Country Place Dr",
    "sg:city":"Boone",
    "sg:classifiers":[
        {
            "category":"Banks & Credit Unions",
            "subcategory":"Financial Services",
            "type":"Services"
        }
    ],
    "sg:phone":"+1 828 265 3865",
    "sg:postcode":"28607",
    "sg:province":"NC",
    "sg:tags":[
        "trust",
        "investment",
        "real estate"
    ],
    "wof:name":"Bbg Properties Inc",
    "wof:placetype":"venue"
},
  "geometry": {"coordinates":[-81.617808,36.206611],"type":"Point"}
}