{
  "type": "Feature",
  "properties": {
    "iso:country":"US",
    "sg:address":"211 Gilmer St",
    "sg:city":"Reidsville",
    "sg:classifiers":[
        {
            "category":"Professional",
            "subcategory":"Lawyer & Legal Services",
            "type":"Services"
        }
    ],
    "sg:phone":"+1 336 342 2997",
    "sg:postcode":"27320",
    "sg:province":"NC",
    "sg:tags":[
        "attorney"
    ],
    "wof:name":"Holt & Watt",
    "wof:placetype":"venue"
},
  "geometry": {"coordinates":[-79.664913,36.360192],"type":"Point"}
}