{
  "type": "Feature",
  "properties": {
    "iso:country":"US",
    "sg:address":"113 S Buckoak St",
    "sg:city":"Stanley",
    "sg:classifiers":[
        {
            "category":"Manufacturing",
            "subcategory":"Textiles",
            "type":"Manufacturing & Wholesale Goods"
        }
    ],
    "sg:phone":"+1 704 263 4658",
    "sg:postcode":"28164",
    "sg:province":"NC",
    "sg:tags":[
        "blanket"
    ],
    "wof:name":"N J Enterprises",
    "wof:placetype":"venue"
},
  "geometry": {"coordinates":[-81.09732200000001,35.358832],"type":"Point"}
}