{
  "type": "Feature",
  "properties": {
    "addr:full":"100 Harbour Town Ct Mebane NC 27302",
    "addr:housenumber":"100",
    "addr:postcode":"27302",
    "addr:street":"Harbour Town Ct",
    "iso:country":"US",
    "sg:address":"100 Harbour Town Ct",
    "sg:city":"Mebane",
    "sg:classifiers":[
        {
            "category":"Wholesale",
            "subcategory":"Non-durable Goods",
            "type":"Manufacturing & Wholesale Goods"
        }
    ],
    "sg:phone":"+1 919 563 9839",
    "sg:postcode":"27302",
    "sg:province":"NC",
    "wof:name":"Redhead Embroidery",
    "wof:placetype":"venue"
},
  "geometry": {"coordinates":[-79.269927,36.130972],"type":"Point"}
}