{
  "type": "Feature",
  "properties": {
    "addr:full":"3300 US Hwy 70 Bus W Clayton NC 27520",
    "addr:housenumber":"3300",
    "addr:postcode":"27520",
    "addr:street":"Us Hwy 70 Bus W",
    "iso:country":"US",
    "sg:address":"3300 US Hwy 70 Bus W",
    "sg:city":"Clayton",
    "sg:classifiers":[
        {
            "category":"Restaurant",
            "type":"Food & Drink"
        }
    ],
    "sg:phone":"+1 919 989 9555",
    "sg:postcode":"27520",
    "sg:province":"NC",
    "wof:name":"Papa's Subs & Pizzas",
    "wof:placetype":"venue"
},
  "geometry": {"coordinates":[-78.388745,35.557383],"type":"Point"}
}