{
  "type": "Feature",
  "properties": {
    "addr:full":"2206 Jefferson Davis Hwy Sanford NC 27330",
    "addr:housenumber":"2206",
    "addr:postcode":"27330",
    "addr:street":"Jefferson Davis Hwy",
    "iso:country":"US",
    "sg:address":"2206 Jefferson Davis Hwy",
    "sg:city":"Sanford",
    "sg:classifiers":[
        {
            "category":"Autos & Motor Vehicles",
            "subcategory":"Fuel & Gas Station",
            "type":"Retail Goods"
        }
    ],
    "sg:phone":"+1 919 775 1929",
    "sg:postcode":"27330",
    "sg:province":"NC",
    "sg:tags":[
        "oil"
    ],
    "wof:name":"Fuel Mate No 7",
    "wof:placetype":"venue"
},
  "geometry": {"coordinates":[-79.216932,35.440413],"type":"Point"}
}