{
  "type": "Feature",
  "properties": {
    "iso:country":"US",
    "sg:address":"491 Sardis Road",
    "sg:city":"Asheville",
    "sg:classifiers":[
        {
            "category":"Coffee & Tea",
            "type":"Food & Drink"
        },
        {
            "category":"Food & Beverages",
            "subcategory":"Bakery",
            "type":"Retail Goods"
        }
    ],
    "sg:phone":"+1 828 665 1210",
    "sg:postcode":"28806",
    "sg:province":"NC",
    "sg:tags":[
        "sandwich"
    ],
    "wof:name":"Kim's Place",
    "wof:placetype":"venue"
},
  "geometry": {"coordinates":[-82.63592,35.542299],"type":"Point"}
}