{
  "type": "Feature",
  "properties": {
    "addr:full":"6021 The Plaza Charlotte NC 28215",
    "addr:housenumber":"6021",
    "addr:postcode":"28215",
    "addr:street":"The",
    "iso:country":"US",
    "sg:address":"6021 The Plaza",
    "sg:city":"Charlotte",
    "sg:classifiers":[
        {
            "category":"Wholesale",
            "subcategory":"Groceries",
            "type":"Manufacturing & Wholesale Goods"
        }
    ],
    "sg:phone":"+1 704 566 0478",
    "sg:postcode":"28215",
    "sg:province":"NC",
    "sg:tags":[
        "food",
        "product"
    ],
    "wof:name":"Distributor Esperanza",
    "wof:placetype":"venue"
},
  "geometry": {"coordinates":[-80.720625,35.228755],"type":"Point"}
}