{
  "type": "Feature",
  "properties": {
    "addr:full":"606 US Hwy 70 W Garner NC 27529",
    "addr:housenumber":"606",
    "addr:postcode":"27529",
    "addr:street":"Us Hwy 70 W",
    "iso:country":"US",
    "sg:address":"606 US Hwy 70 W",
    "sg:city":"Garner",
    "sg:classifiers":[
        {
            "category":"Retail",
            "subcategory":"Car Wash",
            "type":"Services"
        }
    ],
    "sg:phone":"+1   ",
    "sg:postcode":"27529",
    "sg:province":"NC",
    "sg:tags":[
        "carwash"
    ],
    "wof:name":"Keiths Detail & Car Wash",
    "wof:placetype":"venue"
},
  "geometry": {"coordinates":[-78.630336,35.714864],"type":"Point"}
}