{
  "type": "Feature",
  "properties": {
    "iso:country":"US",
    "sg:address":"148 Numa Byerly Rd",
    "sg:city":"Lexington",
    "sg:classifiers":[
        {
            "category":"Retail",
            "subcategory":"Repair Shop",
            "type":"Services"
        }
    ],
    "sg:phone":"+1   ",
    "sg:postcode":"27292",
    "sg:province":"NC",
    "wof:name":"Jds Upholstery",
    "wof:placetype":"venue"
},
  "geometry": {"coordinates":[-80.193546,35.827084],"type":"Point"}
}