{
  "type": "Feature",
  "properties": {
    "addr:full":"124 W Front St Burlington NC 27215",
    "addr:housenumber":"124",
    "addr:postcode":"27215",
    "addr:street":"W Front St",
    "iso:country":"US",
    "sg:address":"124 W Front St",
    "sg:city":"Burlington",
    "sg:classifiers":[
        {
            "category":"Social Services",
            "subcategory":"Adult Care",
            "type":"Services"
        }
    ],
    "sg:phone":"+1 336 222 8783",
    "sg:postcode":"27215",
    "sg:province":"NC",
    "sg:tags":[
        "foster"
    ],
    "wof:name":"Lifegains Inc",
    "wof:placetype":"venue"
},
  "geometry": {"coordinates":[-79.437197,36.094185],"type":"Point"}
}