{
  "type": "Feature",
  "properties": {
    "iso:country":"US",
    "sg:address":"422 N Chimney Rock Rd",
    "sg:city":"Greensboro",
    "sg:classifiers":[
        {
            "category":"Manufacturing",
            "subcategory":"Paper Products",
            "type":"Manufacturing & Wholesale Goods"
        }
    ],
    "sg:phone":"+1 336 574 4200",
    "sg:postcode":"27409",
    "sg:province":"NC",
    "sg:tags":[
        "converter"
    ],
    "sg:website":"www.shamrockgiftwrap.com",
    "wof:name":"Shamrock Corp",
    "wof:placetype":"venue"
},
  "geometry": {"coordinates":[-79.92484899999999,36.090704],"type":"Point"}
}