{
  "type": "Feature",
  "properties": {
    "addr:full":"222 N Lafayette St Shelby NC 28150",
    "addr:housenumber":"222",
    "addr:postcode":"28150",
    "addr:street":"N Lafayette St",
    "iso:country":"US",
    "sg:address":"222 N Lafayette St",
    "sg:city":"Shelby",
    "sg:classifiers":[
        {
            "category":"Social Services",
            "type":"Services"
        }
    ],
    "sg:phone":"+1   ",
    "sg:postcode":"28150",
    "sg:province":"NC",
    "sg:website":"www.eapc.org",
    "wof:name":"EAP & Counseling Assoc",
    "wof:placetype":"venue"
},
  "geometry": {"coordinates":[-81.53999399999999,35.294164],"type":"Point"}
}