{
  "type": "Feature",
  "properties": {
    "addr:full":"4222 Emperor Blvd Durham NC 27703",
    "addr:housenumber":"4222",
    "addr:postcode":"27703",
    "addr:street":"Emperor Blvd",
    "iso:country":"US",
    "sg:address":"4222 Emperor Blvd",
    "sg:city":"Durham",
    "sg:classifiers":[
        {
            "category":"Retail",
            "subcategory":"Repair Shop",
            "type":"Services"
        }
    ],
    "sg:phone":"+1 919 941 0157",
    "sg:postcode":"27703",
    "sg:province":"NC",
    "sg:tags":[
        "electrical"
    ],
    "wof:name":"Circuit City",
    "wof:placetype":"venue"
},
  "geometry": {"coordinates":[-78.847825,35.873279],"type":"Point"}
}