{
  "type": "Feature",
  "properties": {
    "addr:full":"3005 Huffines Dr Burlington NC 27217",
    "addr:housenumber":"3005",
    "addr:postcode":"27217",
    "addr:street":"Huffines Dr",
    "iso:country":"US",
    "sg:address":"3005 Huffines Dr",
    "sg:city":"Burlington",
    "sg:classifiers":[
        {
            "category":"Building & Trades",
            "subcategory":"Construction",
            "type":"Services"
        }
    ],
    "sg:phone":"+1 336 584 4884",
    "sg:postcode":"27217",
    "sg:province":"NC",
    "sg:tags":[
        "painter"
    ],
    "wof:name":"Great American Professionals",
    "wof:placetype":"venue"
},
  "geometry": {"coordinates":[-79.449938,36.148481],"type":"Point"}
}