{
  "type": "Feature",
  "properties": {
    "iso:country":"US",
    "sg:address":"3311 Merchant Ct",
    "sg:city":"Wilmington",
    "sg:classifiers":[
        {
            "category":"Professional",
            "type":"Services"
        }
    ],
    "sg:phone":"+1 910 395 0806",
    "sg:postcode":"28405",
    "sg:province":"NC",
    "wof:name":"Trim Down Nowus",
    "wof:placetype":"venue"
},
  "geometry": {"coordinates":[-77.875182,34.312289],"type":"Point"}
}