{
  "type": "Feature",
  "properties": {
    "addr:full":"5904 Barbee Rd Durham NC 27713",
    "addr:housenumber":"5904",
    "addr:postcode":"27713",
    "addr:street":"Barbee Rd",
    "iso:country":"US",
    "sg:address":"5904 Barbee Rd",
    "sg:city":"Durham",
    "sg:classifiers":[
        {
            "category":"Organizations",
            "subcategory":"Non-profit Organization",
            "type":"Services"
        }
    ],
    "sg:phone":"+1 919 572 9100",
    "sg:postcode":"27713",
    "sg:province":"NC",
    "sg:tags":[
        "action",
        "agency",
        "community"
    ],
    "wof:name":"Compassion Ministries-Durham",
    "wof:placetype":"venue"
},
  "geometry": {"coordinates":[-78.91754299999999,35.914801],"type":"Point"}
}