{
  "type": "Feature",
  "properties": {
    "addr:full":"1126 Farmer Rd Denton NC 27239",
    "addr:housenumber":"1126",
    "addr:postcode":"27239",
    "addr:street":"Farmer Rd",
    "iso:country":"US",
    "sg:address":"1126 Farmer Rd",
    "sg:city":"Denton",
    "sg:classifiers":[
        {
            "category":"Retail",
            "subcategory":"Auto Repair",
            "type":"Services"
        }
    ],
    "sg:phone":"+1 336 859 3517",
    "sg:postcode":"27239",
    "sg:province":"NC",
    "sg:tags":[
        "body",
        "automobile",
        "painting"
    ],
    "wof:name":"Don's Used Cars",
    "wof:placetype":"venue"
},
  "geometry": {"coordinates":[-80.08915,35.641562],"type":"Point"}
}