{
  "type": "Feature",
  "properties": {
    "addr:full":"5033 South Blvd Charlotte NC 28217",
    "addr:housenumber":"5033",
    "addr:postcode":"28217",
    "addr:street":"South Blvd",
    "iso:country":"US",
    "sg:address":"5033 South Blvd",
    "sg:city":"Charlotte",
    "sg:classifiers":[
        {
            "category":"Professional",
            "subcategory":"Employment Agencies",
            "type":"Services"
        }
    ],
    "sg:phone":"+1 704 549 8498",
    "sg:postcode":"28217",
    "sg:province":"NC",
    "sg:tags":[
        "help",
        "contractor"
    ],
    "sg:website":"www.manpower.com",
    "wof:name":"Manpower Temporary Svc",
    "wof:placetype":"venue"
},
  "geometry": {"coordinates":[-80.87589199999999,35.171603],"type":"Point"}
}