{
  "type": "Feature",
  "properties": {
    "iso:country":"US",
    "sg:address":"1132 Proam Dr",
    "sg:city":"Charlotte",
    "sg:classifiers":[
        {
            "category":"Wholesale",
            "subcategory":"Hardware",
            "type":"Manufacturing & Wholesale Goods"
        }
    ],
    "sg:phone":"+1 704 364 8545",
    "sg:postcode":"28211",
    "sg:province":"NC",
    "sg:tags":[
        "air",
        "parts",
        "conditioning",
        "supply"
    ],
    "wof:name":"Authorized Parts Inc",
    "wof:placetype":"venue"
},
  "geometry": {"coordinates":[-80.80262500000001,35.200506],"type":"Point"}
}