{
  "type": "Feature",
  "properties": {
    "iso:country":"US",
    "sg:address":"214 W Broad St",
    "sg:city":"Statesville",
    "sg:classifiers":[
        {
            "category":"Personal",
            "subcategory":"Beauty Salon",
            "type":"Services"
        }
    ],
    "sg:phone":"+1 704 871 2735",
    "sg:postcode":"28677",
    "sg:province":"NC",
    "wof:name":"Sharper Image Hair Salon",
    "wof:placetype":"venue"
},
  "geometry": {"coordinates":[-80.88999099999999,35.784164],"type":"Point"}
}