{
  "type": "Feature",
  "properties": {
    "addr:full":"201 N Chestnut St Winston Salem NC 27101",
    "addr:housenumber":"201",
    "addr:postcode":"27101",
    "addr:street":"N Chestnut St",
    "iso:country":"US",
    "sg:address":"201 N Chestnut St",
    "sg:city":"Winston Salem",
    "sg:classifiers":[
        {
            "category":"Government",
            "subcategory":"Court House",
            "type":"Public Place"
        }
    ],
    "sg:phone":"+1 336 703 2030",
    "sg:postcode":"27101",
    "sg:province":"NC",
    "sg:tags":[
        "county",
        "counsel"
    ],
    "sg:website":"www.co.forsyth.nc.us",
    "wof:name":"Forsyth County Attorney",
    "wof:placetype":"venue"
},
  "geometry": {"coordinates":[-80.241879,36.098057],"type":"Point"}
}