{
  "type": "Feature",
  "properties": {
    "iso:country":"US",
    "sg:address":"2153 Colony Rd",
    "sg:city":"Charlotte",
    "sg:classifiers":[
        {
            "category":"Professional",
            "subcategory":"Business Services",
            "type":"Services"
        }
    ],
    "sg:phone":"+1   ",
    "sg:postcode":"28209",
    "sg:province":"NC",
    "wof:name":"Generi Design Group LLC",
    "wof:placetype":"venue"
},
  "geometry": {"coordinates":[-80.836547,35.174176],"type":"Point"}
}