{
  "type": "Feature",
  "properties": {
    "iso:country":"US",
    "sg:address":"3020 Spanish Ct",
    "sg:city":"Raleigh",
    "sg:classifiers":[
        {
            "category":"Real Estate",
            "subcategory":"Real Estate Operator",
            "type":"Services"
        }
    ],
    "sg:phone":"+1 919 828 7903",
    "sg:postcode":"27607",
    "sg:province":"NC",
    "sg:tags":[
        "apartment"
    ],
    "wof:name":"Spanish Trace Apartments",
    "wof:placetype":"venue"
},
  "geometry": {"coordinates":[-78.677108,35.799368],"type":"Point"}
}