{
  "type": "Feature",
  "properties": {
    "addr:full":"511 S Main St Lexington NC 27292",
    "addr:housenumber":"511",
    "addr:postcode":"27292",
    "addr:street":"S Main St",
    "iso:country":"US",
    "sg:address":"511 S Main St",
    "sg:city":"Lexington",
    "sg:classifiers":[
        {
            "category":"Autos & Motor Vehicles",
            "subcategory":"Auto Supplies",
            "type":"Retail Goods"
        }
    ],
    "sg:phone":"+1 704 246 8527",
    "sg:postcode":"27292",
    "sg:province":"NC",
    "sg:tags":[
        "parts",
        "accessory"
    ],
    "sg:website":"www.autozone.com",
    "wof:name":"Autozone",
    "wof:placetype":"venue"
},
  "geometry": {"coordinates":[-80.257648,35.820059],"type":"Point"}
}