{
  "type": "Feature",
  "properties": {
    "iso:country":"US",
    "sg:address":"920 State Hwy 801",
    "sg:city":"Advance",
    "sg:classifiers":[
        {
            "category":"Building & Trades",
            "subcategory":"Landscaping Services",
            "type":"Services"
        }
    ],
    "sg:phone":"+1 336 998 9340",
    "sg:postcode":"27006",
    "sg:province":"NC",
    "sg:tags":[
        "landscape"
    ],
    "wof:name":"Land-Tek Grounds Mgt Svcs Inc",
    "wof:placetype":"venue"
},
  "geometry": {"coordinates":[-80.427666,35.976951],"type":"Point"}
}