{
  "type": "Feature",
  "properties": {
    "addr:full":"400 Millstone Dr Hillsborough NC 27278",
    "addr:housenumber":"400",
    "addr:postcode":"27278",
    "addr:street":"Millstone Dr",
    "iso:country":"US",
    "sg:address":"400 Millstone Dr",
    "sg:city":"Hillsborough",
    "sg:classifiers":[
        {
            "category":"Building & Trades",
            "subcategory":"Construction",
            "type":"Services"
        }
    ],
    "sg:phone":"+1 919 732 8200",
    "sg:postcode":"27278",
    "sg:province":"NC",
    "sg:website":"www.patriotbuilding.com",
    "wof:name":"Patriot Building Co Inc",
    "wof:placetype":"venue"
},
  "geometry": {"coordinates":[-79.09721500000001,36.051359],"type":"Point"}
}