{
  "type": "Feature",
  "properties": {
    "addr:full":"936 Fire Tower Rd Yanceyville NC 27312",
    "addr:housenumber":"936",
    "addr:postcode":"27312",
    "addr:street":"Fire Tower Rd",
    "iso:country":"US",
    "sg:address":"936 Fire Tower Rd",
    "sg:city":"Yanceyville",
    "sg:classifiers":[
        {
            "category":"Government",
            "subcategory":"Office",
            "type":"Public Place"
        }
    ],
    "sg:phone":"+1 336 694 4721",
    "sg:postcode":"27312",
    "sg:province":"NC",
    "sg:tags":[
        "transportation"
    ],
    "wof:name":"DMV License Tag Office",
    "wof:placetype":"venue"
},
  "geometry": {"coordinates":[-79.165649,35.721564],"type":"Point"}
}