{
  "type": "Feature",
  "properties": {
    "iso:country":"US",
    "sg:address":"6381 US Hwy 158",
    "sg:city":"Leasburg",
    "sg:classifiers":[
        {
            "category":"Government",
            "subcategory":"Fire Station",
            "type":"Public Place"
        }
    ],
    "sg:phone":"+1 336 694 5411",
    "sg:postcode":"27291",
    "sg:province":"NC",
    "sg:tags":[
        "department"
    ],
    "wof:name":"Leasburg Fire Dept",
    "wof:placetype":"venue"
},
  "geometry": {"coordinates":[-79.18042800000001,36.395935],"type":"Point"}
}