{
  "type": "Feature",
  "properties": {
    "iso:country":"US",
    "sg:address":"6416 Sassafras Ln",
    "sg:city":"Raleigh",
    "sg:classifiers":[
        {
            "category":"Manufacturing",
            "subcategory":"Printing",
            "type":"Manufacturing & Wholesale Goods"
        }
    ],
    "sg:phone":"+1 919 848 9475",
    "sg:postcode":"27614",
    "sg:province":"NC",
    "sg:tags":[
        "publisher"
    ],
    "wof:name":"Technical Publications Assoc",
    "wof:placetype":"venue"
},
  "geometry": {"coordinates":[-78.659769,35.96361],"type":"Point"}
}