{
  "type": "Feature",
  "properties": {
    "iso:country":"US",
    "sg:address":"182 W Court St",
    "sg:city":"Rutherfordton",
    "sg:classifiers":[
        {
            "category":"Health Services",
            "subcategory":"Health Practitioner",
            "type":"Services"
        }
    ],
    "sg:phone":"+1 828 287 7806",
    "sg:postcode":"28139",
    "sg:province":"NC",
    "sg:tags":[
        "psychologist"
    ],
    "wof:name":"Woodridge Psychological Assoc",
    "wof:placetype":"venue"
},
  "geometry": {"coordinates":[-81.959846,35.36737],"type":"Point"}
}