{
  "type": "Feature",
  "properties": {
    "iso:country":"US",
    "sg:address":"1024 S Main St",
    "sg:city":"Kernersville",
    "sg:classifiers":[
        {
            "category":"Coffee & Tea",
            "type":"Food & Drink"
        }
    ],
    "sg:menulink":"http://www.allmenus.com/nc/kernersville/125053-starbucks-coffee/menu/",
    "sg:phone":"+1 336 992 1680",
    "sg:postcode":"27284",
    "sg:province":"NC",
    "sg:tags":[
        "american"
    ],
    "wof:name":"Starbucks Coffee",
    "wof:placetype":"venue"
},
  "geometry": {"coordinates":[-80.09823799999999,36.107751],"type":"Point"}
}