{
  "type": "Feature",
  "properties": {
    "addr:full":"2767 George Owen Rd Fayetteville NC 28306",
    "addr:housenumber":"2767",
    "addr:postcode":"28306",
    "addr:street":"George Owen Rd",
    "iso:country":"US",
    "sg:address":"2767 George Owen Rd",
    "sg:city":"Fayetteville",
    "sg:classifiers":[
        {
            "category":"Health Services",
            "subcategory":"Clinic",
            "type":"Services"
        }
    ],
    "sg:phone":"+1 910 424 2540",
    "sg:postcode":"28306",
    "sg:province":"NC",
    "sg:tags":[
        "home"
    ],
    "wof:name":"Helping Hands",
    "wof:placetype":"venue"
},
  "geometry": {"coordinates":[-78.96377699999999,34.993014],"type":"Point"}
}