{
  "type": "Feature",
  "properties": {
    "addr:full":"4475 Tekoa Ln Winston Salem NC 27105",
    "addr:housenumber":"4475",
    "addr:postcode":"27105",
    "addr:street":"Tekoa Ln",
    "iso:country":"US",
    "sg:address":"4475 Tekoa Ln",
    "sg:city":"Winston Salem",
    "sg:classifiers":[
        {
            "category":"Professional",
            "subcategory":"Accounting & Tax Preparation",
            "type":"Services"
        }
    ],
    "sg:phone":"+1   ",
    "sg:postcode":"27105",
    "sg:province":"NC",
    "wof:name":"Monac Enterprises",
    "wof:placetype":"venue"
},
  "geometry": {"coordinates":[-80.219105,36.174334],"type":"Point"}
}