{
  "type": "Feature",
  "properties": {
    "addr:full":"316 Owen Dr Fayetteville NC 28304",
    "addr:housenumber":"316",
    "addr:postcode":"28304",
    "addr:street":"Owen Dr",
    "iso:country":"US",
    "sg:address":"316 Owen Dr",
    "sg:city":"Fayetteville",
    "sg:classifiers":[
        {
            "category":"Bars & Pubs",
            "type":"Food & Drink"
        },
        {
            "category":"Restaurant",
            "type":"Food & Drink"
        }
    ],
    "sg:menulink":"http://www.allmenus.com/nc/cross-creek/60541-316-oyster-bar--seafood-grill/menu/",
    "sg:phone":"+1 910 481 0530",
    "sg:postcode":"28304",
    "sg:province":"NC",
    "sg:tags":[
        "seafood",
        "american"
    ],
    "wof:name":"316 Oyster Bar & Seafood Grill",
    "wof:placetype":"venue"
},
  "geometry": {"coordinates":[-78.934338,35.039744],"type":"Point"}
}