{
  "type": "Feature",
  "properties": {
    "addr:full":"215 S Main St Davidson NC 28036",
    "addr:housenumber":"215",
    "addr:postcode":"28036",
    "addr:street":"S Main St",
    "iso:country":"US",
    "sg:address":"215 S Main St",
    "sg:city":"Davidson",
    "sg:classifiers":[
        {
            "category":"Autos & Motor Vehicles",
            "subcategory":"Fuel & Gas Station",
            "type":"Retail Goods"
        }
    ],
    "sg:phone":"+1 704 892 4868",
    "sg:postcode":"28036",
    "sg:province":"NC",
    "sg:tags":[
        "oil"
    ],
    "wof:name":"Stowe's Exxon Svc Ctr",
    "wof:placetype":"venue"
},
  "geometry": {"coordinates":[-80.84917299999999,35.497779],"type":"Point"}
}