{
  "type": "Feature",
  "properties": {
    "iso:country":"US",
    "sg:address":"213 Bell Rd",
    "sg:city":"Kings Mountain",
    "sg:classifiers":[
        {
            "category":"Home & Garden",
            "subcategory":"Carpets & Floor Coverings",
            "type":"Retail Goods"
        }
    ],
    "sg:phone":"+1 704 739 7413",
    "sg:postcode":"28086",
    "sg:province":"NC",
    "wof:name":"Mike Fitch Carpets",
    "wof:placetype":"venue"
},
  "geometry": {"coordinates":[-81.414316,35.269031],"type":"Point"}
}