{
  "type": "Feature",
  "properties": {
    "iso:country":"US",
    "sg:address":"1985 Tate Blvd SE",
    "sg:city":"Hickory",
    "sg:classifiers":[
        {
            "category":"Insurance",
            "subcategory":"Insurance Agent",
            "type":"Services"
        }
    ],
    "sg:phone":"+1 828 322 8574",
    "sg:postcode":"28602",
    "sg:province":"NC",
    "wof:name":"Dale Shuford",
    "wof:placetype":"venue"
},
  "geometry": {"coordinates":[-81.302632,35.728246],"type":"Point"}
}