{
  "type": "Feature",
  "properties": {
    "iso:country":"US",
    "sg:address":"1556 N Fayetteville St",
    "sg:city":"Asheboro",
    "sg:classifiers":[
        {
            "category":"Organizations",
            "subcategory":"Religious Organization",
            "type":"Services"
        }
    ],
    "sg:phone":"+1 336 672 9318",
    "sg:postcode":"27203",
    "sg:province":"NC",
    "sg:tags":[
        "church"
    ],
    "wof:name":"Bailey's Grove Baptist Church",
    "wof:placetype":"venue"
},
  "geometry": {"coordinates":[-79.80824699999999,35.738998],"type":"Point"}
}