{
  "type": "Feature",
  "properties": {
    "addr:full":"3842 US Hwy 158 Yanceyville NC 27379",
    "addr:housenumber":"3842",
    "addr:postcode":"27379",
    "addr:street":"Us Hwy 158",
    "iso:country":"US",
    "sg:address":"3842 US Hwy 158",
    "sg:city":"Yanceyville",
    "sg:classifiers":[
        {
            "category":"Professional",
            "type":"Services"
        }
    ],
    "sg:phone":"+1 336 694 5484",
    "sg:postcode":"27379",
    "sg:province":"NC",
    "sg:tags":[
        "establishment"
    ],
    "wof:name":"Four Points",
    "wof:placetype":"venue"
},
  "geometry": {"coordinates":[-79.387584,36.397511],"type":"Point"}
}