{
  "type": "Feature",
  "properties": {
    "iso:country":"US",
    "sg:address":"436 Buckner Branch Rd",
    "sg:city":"Mars Hill",
    "sg:classifiers":[
        {
            "category":"Recreation",
            "type":"Entertainment"
        }
    ],
    "sg:phone":"+1   ",
    "sg:postcode":"28754",
    "sg:province":"NC",
    "wof:name":"Zone Fitness & Karate Inc",
    "wof:placetype":"venue"
},
  "geometry": {"coordinates":[-82.48657,35.87558],"type":"Point"}
}