{
  "type": "Feature",
  "properties": {
    "addr:full":"3902 Hopkins Chapel Rd Zebulon NC 27597",
    "addr:housenumber":"3902",
    "addr:postcode":"27597",
    "addr:street":"Hopkins Chapel Rd",
    "iso:country":"US",
    "sg:address":"3902 Hopkins Chapel Rd",
    "sg:city":"Zebulon",
    "sg:classifiers":[
        {
            "category":"Building & Trades",
            "subcategory":"Plumbing",
            "type":"Services"
        }
    ],
    "sg:phone":"+1 919 404 5119",
    "sg:postcode":"27597",
    "sg:province":"NC",
    "sg:tags":[
        "contractor"
    ],
    "wof:name":"Matthews Plumbing",
    "wof:placetype":"venue"
},
  "geometry": {"coordinates":[-78.351615,35.889615],"type":"Point"}
}