{
  "type": "Feature",
  "properties": {
    "addr:full":"2531 E Lyon Station Rd Creedmoor NC 27522",
    "addr:housenumber":"2531",
    "addr:postcode":"27522",
    "addr:street":"E Lyon Station Rd",
    "iso:country":"US",
    "sg:address":"2531 E Lyon Station Rd",
    "sg:city":"Creedmoor",
    "sg:classifiers":[
        {
            "category":"Restaurant",
            "type":"Food & Drink"
        }
    ],
    "sg:menulink":"http://www.allmenus.com/nc/dutchville/85349-dominos-pizza/menu/",
    "sg:phone":"+1 919 528 2828",
    "sg:postcode":"27522",
    "sg:province":"NC",
    "sg:tags":[
        "american",
        "wing",
        "pizza"
    ],
    "wof:name":"Domino's Pizza",
    "wof:placetype":"venue"
},
  "geometry": {"coordinates":[-78.72845100000001,36.134678],"type":"Point"}
}