{
  "type": "Feature",
  "properties": {
    "iso:country":"US",
    "sg:address":"611 Tunnel Rd",
    "sg:city":"Asheville",
    "sg:classifiers":[
        {
            "category":"Shopping",
            "subcategory":"Gifts & Souvenirs",
            "type":"Retail Goods"
        }
    ],
    "sg:phone":"+1 828 298 2027",
    "sg:postcode":"28805",
    "sg:province":"NC",
    "sg:tags":[
        "shop"
    ],
    "wof:name":"Our Country Dreams",
    "wof:placetype":"venue"
},
  "geometry": {"coordinates":[-82.508287,35.586646],"type":"Point"}
}