{
  "type": "Feature",
  "properties": {
    "iso:country":"US",
    "sg:address":"3553 N Halifax Rd",
    "sg:city":"Rocky Mount",
    "sg:classifiers":[
        {
            "category":"Home & Garden",
            "subcategory":"Carpets & Floor Coverings",
            "type":"Retail Goods"
        }
    ],
    "sg:phone":"+1 252 443 0271",
    "sg:postcode":"27804",
    "sg:province":"NC",
    "sg:tags":[
        "dealer",
        "rug"
    ],
    "wof:name":"Dortches Rug Outlet",
    "wof:placetype":"venue"
},
  "geometry": {"coordinates":[-77.857101,36.013862],"type":"Point"}
}