{
  "type": "Feature",
  "properties": {
    "iso:country":"US",
    "sg:address":"325 Alexander St",
    "sg:city":"Fayetteville",
    "sg:classifiers":[
        {
            "category":"Professional",
            "subcategory":"Business Services",
            "type":"Services"
        }
    ],
    "sg:phone":"+1 910 678 8866",
    "sg:postcode":"28301",
    "sg:province":"NC",
    "sg:tags":[
        "repossessing"
    ],
    "wof:name":"Universal Services Of Nc Inc",
    "wof:placetype":"venue"
},
  "geometry": {"coordinates":[-78.87657299999999,35.046228],"type":"Point"}
}