{
  "type": "Feature",
  "properties": {
    "addr:full":"73 Gaston Mountain Rd Asheville NC 28806",
    "addr:housenumber":"73",
    "addr:postcode":"28806",
    "addr:street":"Gaston Mountain Rd",
    "iso:country":"US",
    "sg:address":"73 Gaston Mountain Rd",
    "sg:city":"Asheville",
    "sg:classifiers":[
        {
            "category":"Building & Trades",
            "subcategory":"Construction",
            "type":"Services"
        }
    ],
    "sg:phone":"+1 828 665 7034",
    "sg:postcode":"28806",
    "sg:province":"NC",
    "sg:tags":[
        "house"
    ],
    "wof:name":"Hale Construction Co LLC",
    "wof:placetype":"venue"
},
  "geometry": {"coordinates":[-82.628322,35.536857],"type":"Point"}
}