{
  "type": "Feature",
  "properties": {
    "iso:country":"US",
    "sg:address":"1608 Currituck Ave",
    "sg:city":"Dunn",
    "sg:classifiers":[
        {
            "category":"Real Estate",
            "subcategory":"Real Estate Agent",
            "type":"Services"
        }
    ],
    "sg:phone":"+1 910 892 3079",
    "sg:postcode":"28334",
    "sg:province":"NC",
    "sg:tags":[
        "management"
    ],
    "wof:name":"Cumberland Square Assoc",
    "wof:placetype":"venue"
},
  "geometry": {"coordinates":[-78.615568,35.327857],"type":"Point"}
}