{
  "type": "Feature",
  "properties": {
    "addr:full":"121 Seaboard Ave Raleigh NC 27604",
    "addr:housenumber":"121",
    "addr:postcode":"27604",
    "addr:street":"Seaboard Ave",
    "iso:country":"US",
    "sg:address":"121 Seaboard Ave",
    "sg:city":"Raleigh",
    "sg:classifiers":[
        {
            "category":"Home & Garden",
            "subcategory":"Furniture",
            "type":"Retail Goods"
        }
    ],
    "sg:phone":"+1 919 838 8244",
    "sg:postcode":"27604",
    "sg:province":"NC",
    "wof:name":"Seaboard Imports Inc",
    "wof:placetype":"venue"
},
  "geometry": {"coordinates":[-78.639745,35.788796],"type":"Point"}
}