{
  "type": "Feature",
  "properties": {
    "addr:full":"219 N Berkeley Blvd Goldsboro NC 27534",
    "addr:housenumber":"219",
    "addr:postcode":"27534",
    "addr:street":"N Berkeley Blvd",
    "iso:country":"US",
    "sg:address":"219 N Berkeley Blvd",
    "sg:city":"Goldsboro",
    "sg:classifiers":[
        {
            "category":"Personal",
            "subcategory":"Beauty Salon",
            "type":"Services"
        }
    ],
    "sg:phone":"+1   ",
    "sg:postcode":"27534",
    "sg:province":"NC",
    "sg:tags":[
        "shop"
    ],
    "wof:name":"Expert One",
    "wof:placetype":"venue"
},
  "geometry": {"coordinates":[-77.951528,35.372067],"type":"Point"}
}