{
  "type": "Feature",
  "properties": {
    "iso:country":"US",
    "sg:address":"655 Becktown Rd",
    "sg:city":"Mocksville",
    "sg:classifiers":[
        {
            "category":"Building & Trades",
            "subcategory":"Landscaping Services",
            "type":"Services"
        }
    ],
    "sg:phone":"+1 336 998 5149",
    "sg:postcode":"27028",
    "sg:province":"NC",
    "sg:tags":[
        "lawn",
        "maintenance",
        "grounds"
    ],
    "wof:name":"Hillstop Landscaping",
    "wof:placetype":"venue"
},
  "geometry": {"coordinates":[-80.496786,35.824193],"type":"Point"}
}