{
  "type": "Feature",
  "properties": {
    "addr:full":"375 Castle Ln Mocksville NC 27028",
    "addr:housenumber":"375",
    "addr:postcode":"27028",
    "addr:street":"Castle Ln",
    "iso:country":"US",
    "sg:address":"375 Castle Ln",
    "sg:city":"Mocksville",
    "sg:classifiers":[
        {
            "category":"Building & Trades",
            "subcategory":"Plumbing",
            "type":"Services"
        }
    ],
    "sg:phone":"+1 336 924 4500",
    "sg:postcode":"27028",
    "sg:province":"NC",
    "sg:tags":[
        "plumbing",
        "contractor"
    ],
    "wof:name":"Plumbing Works",
    "wof:placetype":"venue"
},
  "geometry": {"coordinates":[-80.66475199999999,35.932928],"type":"Point"}
}