{
  "type": "Feature",
  "properties": {
    "addr:full":"1707 Black Creek Rd SE Wilson NC 27893",
    "addr:housenumber":"1707",
    "addr:postcode":"27893",
    "addr:street":"Black Creek Rd Se",
    "iso:country":"US",
    "sg:address":"1707 Black Creek Rd SE",
    "sg:city":"Wilson",
    "sg:classifiers":[
        {
            "category":"Wholesale",
            "subcategory":"Farm Supplies",
            "type":"Manufacturing & Wholesale Goods"
        }
    ],
    "sg:phone":"+1 252 246 9100",
    "sg:postcode":"27893",
    "sg:province":"NC",
    "sg:tags":[
        "leaf",
        "tobacco"
    ],
    "wof:name":"United Tobacco Co LLC",
    "wof:placetype":"venue"
},
  "geometry": {"coordinates":[-77.90515499999999,35.706227],"type":"Point"}
}