{
  "type": "Feature",
  "properties": {
    "iso:country":"US",
    "sg:address":"3314 Wickslow Rd",
    "sg:city":"Wilmington",
    "sg:classifiers":[
        {
            "category":"Real Estate",
            "subcategory":"Real Estate Operator",
            "type":"Services"
        }
    ],
    "sg:phone":"+1 910 799 8300",
    "sg:postcode":"28412",
    "sg:province":"NC",
    "sg:tags":[
        "apartment"
    ],
    "wof:name":"Governours Square Apartments",
    "wof:placetype":"venue"
},
  "geometry": {"coordinates":[-77.892124,34.185812],"type":"Point"}
}