{
  "type": "Feature",
  "properties": {
    "addr:full":"1125 Walnut Acres Dr Hickory NC 28602",
    "addr:housenumber":"1125",
    "addr:postcode":"28602",
    "addr:street":"Walnut Acres Dr",
    "iso:country":"US",
    "sg:address":"1125 Walnut Acres Dr",
    "sg:city":"Hickory",
    "sg:classifiers":[
        {
            "category":"Real Estate",
            "subcategory":"Developer",
            "type":"Services"
        }
    ],
    "sg:phone":"+1 828 294 2068",
    "sg:postcode":"28602",
    "sg:province":"NC",
    "wof:name":"Linder Properties",
    "wof:placetype":"venue"
},
  "geometry": {"coordinates":[-81.367217,35.655981],"type":"Point"}
}