{
  "type": "Feature",
  "properties": {
    "iso:country":"US",
    "sg:address":"275 US Hwy 70 E",
    "sg:city":"Selma",
    "sg:classifiers":[
        {
            "category":"Professional",
            "subcategory":"Business Services",
            "type":"Services"
        }
    ],
    "sg:phone":"+1   ",
    "sg:postcode":"27576",
    "sg:province":"NC",
    "wof:name":"Community Express",
    "wof:placetype":"venue"
},
  "geometry": {"coordinates":[-78.29585299999999,35.522715],"type":"Point"}
}