{
  "type": "Feature",
  "properties": {
    "addr:full":"305 S Main St Farmville NC 27828",
    "addr:housenumber":"305",
    "addr:postcode":"27828",
    "addr:street":"S Main St",
    "iso:country":"US",
    "sg:address":"305 S Main St",
    "sg:city":"Farmville",
    "sg:classifiers":[
        {
            "category":"Shopping",
            "subcategory":"Florist",
            "type":"Retail Goods"
        }
    ],
    "sg:phone":"+1 252 753 5335",
    "sg:postcode":"27828",
    "sg:province":"NC",
    "wof:name":"Starlette & Joanne's Creative",
    "wof:placetype":"venue"
},
  "geometry": {"coordinates":[-77.587461,35.595105],"type":"Point"}
}