{
  "type": "Feature",
  "properties": {
    "addr:full":"100 W Union St Morganton NC 28655",
    "addr:housenumber":"100",
    "addr:postcode":"28655",
    "addr:street":"W Union St",
    "iso:country":"US",
    "sg:address":"100 W Union St",
    "sg:city":"Morganton",
    "sg:classifiers":[
        {
            "category":"Shopping",
            "subcategory":"Clothing, Apparel, & Fashions",
            "type":"Retail Goods"
        }
    ],
    "sg:phone":"+1 828 439 9180",
    "sg:postcode":"28655",
    "sg:province":"NC",
    "sg:tags":[
        "furnishing"
    ],
    "wof:name":"100 West Union",
    "wof:placetype":"venue"
},
  "geometry": {"coordinates":[-81.688085,35.745598],"type":"Point"}
}