{
  "type": "Feature",
  "properties": {
    "addr:full":"5517 Durham-Chapel Hill Blvd Durham NC 27707",
    "addr:housenumber":"5517",
    "addr:postcode":"27707",
    "addr:street":"Durham-Chapel Hill Blvd",
    "iso:country":"US",
    "sg:address":"5517 Durham-Chapel Hill Blvd",
    "sg:city":"Durham",
    "sg:classifiers":[
        {
            "category":"Professional",
            "subcategory":"Management & Consulting",
            "type":"Services"
        }
    ],
    "sg:phone":"+1   ",
    "sg:postcode":"27707",
    "sg:province":"NC",
    "sg:tags":[
        "business",
        "legal"
    ],
    "wof:name":"Peoples Medical Malpractice L",
    "wof:placetype":"venue"
},
  "geometry": {"coordinates":[-78.997299,35.951623],"type":"Point"}
}