{
  "type": "Feature",
  "properties": {
    "addr:full":"2628 Meadow Knoll Dr Charlotte NC 28269",
    "addr:housenumber":"2628",
    "addr:postcode":"28269",
    "addr:street":"Meadow Knoll Dr",
    "iso:country":"US",
    "sg:address":"2628 Meadow Knoll Dr",
    "sg:city":"Charlotte",
    "sg:classifiers":[
        {
            "category":"Building & Trades",
            "subcategory":"Construction",
            "type":"Services"
        }
    ],
    "sg:phone":"+1 704 688 0290",
    "sg:postcode":"28269",
    "sg:province":"NC",
    "sg:tags":[
        "home",
        "builder"
    ],
    "wof:name":"Mulvaney Homes",
    "wof:placetype":"venue"
},
  "geometry": {"coordinates":[-80.847483,35.285656],"type":"Point"}
}