{
  "type": "Feature",
  "properties": {
    "addr:full":"202 E Williams St Autryville NC 28318",
    "addr:housenumber":"202",
    "addr:postcode":"28318",
    "addr:street":"E Williams St",
    "iso:country":"US",
    "sg:address":"202 E Williams St",
    "sg:city":"Autryville",
    "sg:classifiers":[
        {
            "category":"Social Services",
            "subcategory":"Child Care",
            "type":"Services"
        }
    ],
    "sg:phone":"+1 910 525 5246",
    "sg:postcode":"28318",
    "sg:province":"NC",
    "wof:name":"Little Angels Nursery",
    "wof:placetype":"venue"
},
  "geometry": {"coordinates":[-78.640345,34.997547],"type":"Point"}
}