{
  "type": "Feature",
  "properties": {
    "iso:country":"US",
    "sg:address":"659 Walnut St SW",
    "sg:city":"Winston Salem",
    "sg:classifiers":[
        {
            "category":"Retail",
            "subcategory":"Auto Repair",
            "type":"Services"
        }
    ],
    "sg:phone":"+1   ",
    "sg:postcode":"27101",
    "sg:province":"NC",
    "sg:tags":[
        "body"
    ],
    "wof:name":"Jordans Paint & Body Shop Inc",
    "wof:placetype":"venue"
},
  "geometry": {"coordinates":[-80.24646,36.082066],"type":"Point"}
}