{
  "type": "Feature",
  "properties": {
    "addr:full":"5833 Saint Francis Dr Charlotte NC 28269",
    "addr:housenumber":"5833",
    "addr:postcode":"28269",
    "addr:street":"Saint Francis Dr",
    "iso:country":"US",
    "sg:address":"5833 Saint Francis Dr",
    "sg:city":"Charlotte",
    "sg:classifiers":[
        {
            "category":"Wholesale",
            "subcategory":"Farm Supplies",
            "type":"Manufacturing & Wholesale Goods"
        }
    ],
    "sg:phone":"+1 704 596 5353",
    "sg:postcode":"28269",
    "sg:province":"NC",
    "sg:tags":[
        "fertilizer"
    ],
    "wof:name":"Manale Landscaping LLC",
    "wof:placetype":"venue"
},
  "geometry": {"coordinates":[-80.84207000000001,35.334283],"type":"Point"}
}