{
  "type": "Feature",
  "properties": {
    "iso:country":"US",
    "sg:address":"118 Main St",
    "sg:city":"Oxford",
    "sg:classifiers":[
        {
            "category":"Health Services",
            "subcategory":"Health Practitioner",
            "type":"Services"
        }
    ],
    "sg:phone":"+1   ",
    "sg:postcode":"27565",
    "sg:province":"NC",
    "wof:name":"Judy K Plemons PHD",
    "wof:placetype":"venue"
},
  "geometry": {"coordinates":[-78.588399,36.311535],"type":"Point"}
}