{
  "type": "Feature",
  "properties": {
    "addr:full":"3739 National Dr Raleigh NC 27612",
    "addr:housenumber":"3739",
    "addr:postcode":"27612",
    "addr:street":"National Dr",
    "iso:country":"US",
    "sg:address":"3739 National Dr",
    "sg:city":"Raleigh",
    "sg:classifiers":[
        {
            "category":"Shopping",
            "subcategory":"Computers & Home Electronics",
            "type":"Retail Goods"
        }
    ],
    "sg:phone":"+1 919 789 0910",
    "sg:postcode":"27612",
    "sg:province":"NC",
    "sg:tags":[
        "software"
    ],
    "wof:name":"CIS Consulting Group",
    "wof:placetype":"venue"
},
  "geometry": {"coordinates":[-78.666011,35.835047],"type":"Point"}
}