{
  "type": "Feature",
  "properties": {
    "addr:full":"115 Mooresville Rd Salisbury NC 28144",
    "addr:housenumber":"115",
    "addr:postcode":"28144",
    "addr:street":"Mooresville Rd",
    "iso:country":"US",
    "sg:address":"115 Mooresville Rd",
    "sg:city":"Salisbury",
    "sg:classifiers":[
        {
            "category":"Retail",
            "subcategory":"Self-service Laundry",
            "type":"Services"
        }
    ],
    "sg:phone":"+1 704 637 6812",
    "sg:postcode":"28144",
    "sg:province":"NC",
    "wof:name":"Speedwash Laundromat",
    "wof:placetype":"venue"
},
  "geometry": {"coordinates":[-80.491068,35.656657],"type":"Point"}
}