{
  "type": "Feature",
  "properties": {
    "addr:full":"5929 Frieden Church Rd Gibsonville NC 27249",
    "addr:housenumber":"5929",
    "addr:postcode":"27249",
    "addr:street":"Frieden Church Rd",
    "iso:country":"US",
    "sg:address":"5929 Frieden Church Rd",
    "sg:city":"Gibsonville",
    "sg:classifiers":[
        {
            "category":"Manufacturing",
            "subcategory":"Lumber",
            "type":"Manufacturing & Wholesale Goods"
        }
    ],
    "sg:phone":"+1 336 698 0732",
    "sg:postcode":"27249",
    "sg:province":"NC",
    "sg:tags":[
        "logging"
    ],
    "wof:name":"Guilford Logging & Grading",
    "wof:placetype":"venue"
},
  "geometry": {"coordinates":[-79.625129,36.125995],"type":"Point"}
}