{
  "type": "Feature",
  "properties": {
    "addr:full":"310 Mount Olive Rd Newton Grove NC 28337",
    "addr:housenumber":"310",
    "addr:postcode":"28337",
    "addr:street":"Mount Olive Rd",
    "iso:country":"US",
    "sg:address":"310 Mount Olive Rd",
    "sg:city":"Newton Grove",
    "sg:classifiers":[
        {
            "category":"Organizations",
            "subcategory":"Religious Organization",
            "type":"Services"
        }
    ],
    "sg:phone":"+1   ",
    "sg:postcode":"28337",
    "sg:province":"NC",
    "wof:name":"Pleasant Union Christn Church",
    "wof:placetype":"venue"
},
  "geometry": {"coordinates":[-78.587041,34.587493],"type":"Point"}
}