{
  "type": "Feature",
  "properties": {
    "addr:full":"8701 Mallard Creek Rd Charlotte NC 28262",
    "addr:housenumber":"8701",
    "addr:postcode":"28262",
    "addr:street":"Mallard Creek Rd",
    "iso:country":"US",
    "sg:address":"8701 Mallard Creek Rd",
    "sg:city":"Charlotte",
    "sg:classifiers":[
        {
            "category":"Shopping",
            "subcategory":"Computers & Home Electronics",
            "type":"Retail Goods"
        }
    ],
    "sg:phone":"+1 704 547 7301",
    "sg:postcode":"28262",
    "sg:province":"NC",
    "sg:tags":[
        "software"
    ],
    "sg:website":"www.verian.com",
    "wof:name":"Verian Technologies",
    "wof:placetype":"venue"
},
  "geometry": {"coordinates":[-80.778255,35.319277],"type":"Point"}
}