{
  "type": "Feature",
  "properties": {
    "addr:full":"3201 N Tryon St Charlotte NC 28206",
    "addr:housenumber":"3201",
    "addr:postcode":"28206",
    "addr:street":"N Tryon St",
    "iso:country":"US",
    "sg:address":"3201 N Tryon St",
    "sg:city":"Charlotte",
    "sg:classifiers":[
        {
            "category":"Banks & Credit Unions",
            "subcategory":"Bank",
            "type":"Services"
        }
    ],
    "sg:phone":"+1 704 333 1805",
    "sg:postcode":"28206",
    "sg:province":"NC",
    "sg:tags":[
        "financing"
    ],
    "wof:name":"Carolina National Investments",
    "wof:placetype":"venue"
},
  "geometry": {"coordinates":[-80.808677,35.252605],"type":"Point"}
}