{
  "type": "Feature",
  "properties": {
    "addr:full":"2071 Horton Rd Apex NC 27545",
    "addr:housenumber":"2071",
    "addr:postcode":"27545",
    "addr:street":"Horton Rd",
    "iso:country":"US",
    "sg:address":"2071 Horton Rd",
    "sg:city":"Apex",
    "sg:classifiers":[
        {
            "category":"Wholesale",
            "subcategory":"Durable Goods & Equipment",
            "type":"Manufacturing & Wholesale Goods"
        }
    ],
    "sg:phone":"+1 919 303 1010",
    "sg:postcode":"27545",
    "sg:province":"NC",
    "wof:name":"Jordan Lake Antiques",
    "wof:placetype":"venue"
},
  "geometry": {"coordinates":[-78.463103,35.823503],"type":"Point"}
}