{
  "type": "Feature",
  "properties": {
    "addr:full":"416 Mccullough Dr Ste 215 Charlotte NC 28262",
    "addr:housenumber":"416",
    "addr:postcode":"28262",
    "addr:street":"Mccullough Dr Ste 215",
    "iso:country":"US",
    "sg:address":"416 Mccullough Dr Ste 215",
    "sg:city":"Charlotte",
    "sg:classifiers":[
        {
            "category":"Professional",
            "subcategory":"Employment Agencies",
            "type":"Services"
        }
    ],
    "sg:phone":"+1 704 510 0551",
    "sg:postcode":"28262",
    "sg:province":"NC",
    "sg:tags":[
        "opportunity"
    ],
    "sg:website":"http://www.spherion.com",
    "wof:name":"Spherion",
    "wof:placetype":"venue"
},
  "geometry": {"coordinates":[-80.756692,35.301884],"type":"Point"}
}