{
  "type": "Feature",
  "properties": {
    "addr:full":"3620 Chub Lake Rd Roxboro NC 27574",
    "addr:postcode":"3620;27574",
    "addr:street":"Chub Lake Rd",
    "iso:country":"US",
    "sg:address":"3620 Chub Lake Rd",
    "sg:city":"Roxboro",
    "sg:classifiers":[
        {
            "category":"Food & Beverages",
            "subcategory":"Groceries & Convenience Stores",
            "type":"Retail Goods"
        }
    ],
    "sg:phone":"+1 336 599 6511",
    "sg:postcode":"27574",
    "sg:province":"NC",
    "wof:name":"Country Club Convenience",
    "wof:placetype":"venue"
},
  "geometry": {"coordinates":[-78.99230799999999,36.442986],"type":"Point"}
}