{
  "type": "Feature",
  "properties": {
    "iso:country":"US",
    "sg:address":"10000 Mini Ranch Rd",
    "sg:city":"Waxhaw",
    "sg:classifiers":[
        {
            "category":"Home & Garden",
            "subcategory":"Garden Supply",
            "type":"Retail Goods"
        }
    ],
    "sg:phone":"+1 704 243 1723",
    "sg:postcode":"28173",
    "sg:province":"NC",
    "sg:tags":[
        "equipment"
    ],
    "wof:name":"Osborne Tool & Equipment",
    "wof:placetype":"venue"
},
  "geometry": {"coordinates":[-80.79156399999999,34.82931],"type":"Point"}
}