{
  "type": "Feature",
  "properties": {
    "iso:country":"US",
    "sg:address":"7949 State Hwy 87",
    "sg:city":"Snow Camp",
    "sg:classifiers":[
        {
            "category":"Wholesale",
            "subcategory":"Farm Supplies",
            "type":"Manufacturing & Wholesale Goods"
        }
    ],
    "sg:phone":"+1 336 376 9328",
    "sg:postcode":"27349",
    "sg:province":"NC",
    "sg:tags":[
        "feed"
    ],
    "wof:name":"Land O'Lakes Purina Feed",
    "wof:placetype":"venue"
},
  "geometry": {"coordinates":[-79.303917,35.898489],"type":"Point"}
}