{
  "type": "Feature",
  "properties": {
    "addr:full":"5746 Oleander Dr Wilmington NC 28403",
    "addr:housenumber":"5746",
    "addr:postcode":"28403",
    "addr:street":"Oleander Dr",
    "iso:country":"US",
    "sg:address":"5746 Oleander Dr",
    "sg:city":"Wilmington",
    "sg:classifiers":[
        {
            "category":"Home & Garden",
            "subcategory":"Carpets & Floor Coverings",
            "type":"Retail Goods"
        }
    ],
    "sg:phone":"+1 910 799 6870",
    "sg:postcode":"28403",
    "sg:province":"NC",
    "sg:tags":[
        "dealer",
        "rug"
    ],
    "wof:name":"Crystal Carpets Warehouse",
    "wof:placetype":"venue"
},
  "geometry": {"coordinates":[-77.847116,34.209079],"type":"Point"}
}