{
  "type": "Feature",
  "properties": {
    "iso:country":"US",
    "sg:address":"4005 Sunset Rd",
    "sg:city":"Charlotte",
    "sg:classifiers":[
        {
            "category":"Retail",
            "subcategory":"Laundry & Dry Cleaning",
            "type":"Services"
        }
    ],
    "sg:phone":"+1 704 393 0045",
    "sg:postcode":"28216",
    "sg:province":"NC",
    "sg:tags":[
        "cleaners"
    ],
    "wof:name":"New Cleaners",
    "wof:placetype":"venue"
},
  "geometry": {"coordinates":[-80.86076300000001,35.305041],"type":"Point"}
}