{
  "type": "Feature",
  "properties": {
    "iso:country":"US",
    "sg:address":"610 E Cumberland St",
    "sg:city":"Dunn",
    "sg:classifiers":[
        {
            "category":"Autos & Motor Vehicles",
            "subcategory":"Automobile Sales",
            "type":"Retail Goods"
        }
    ],
    "sg:phone":"+1 910 892 5763",
    "sg:postcode":"28334",
    "sg:province":"NC",
    "sg:tags":[
        "car",
        "dealer"
    ],
    "wof:name":"T J's Auto Sales",
    "wof:placetype":"venue"
},
  "geometry": {"coordinates":[-78.605935,35.304401],"type":"Point"}
}