{
  "type": "Feature",
  "properties": {
    "addr:full":"1000 N Long St Salisbury NC 28144",
    "addr:housenumber":"1000",
    "addr:postcode":"28144",
    "addr:street":"N Long St",
    "iso:country":"US",
    "sg:address":"1000 N Long St",
    "sg:city":"Salisbury",
    "sg:classifiers":[
        {
            "category":"Manufacturing",
            "subcategory":"Furniture",
            "type":"Manufacturing & Wholesale Goods"
        }
    ],
    "sg:phone":"+1 704 633 8000",
    "sg:postcode":"28144",
    "sg:province":"NC",
    "wof:name":"Carter's Inc",
    "wof:placetype":"venue"
},
  "geometry": {"coordinates":[-80.459324,35.670348],"type":"Point"}
}