{
  "type": "Feature",
  "properties": {
    "iso:country":"US",
    "sg:address":"4665 State Hwy 111",
    "sg:city":"Pikeville",
    "sg:classifiers":[
        {
            "category":"Education",
            "subcategory":"School",
            "type":"Public Place"
        }
    ],
    "sg:phone":"+1 919 705 6030",
    "sg:postcode":"27863",
    "sg:province":"NC",
    "sg:tags":[
        "elementary"
    ],
    "sg:website":"www.wcps.org",
    "wof:name":"Northeast Elementary School",
    "wof:placetype":"venue"
},
  "geometry": {"coordinates":[-77.89894,35.499635],"type":"Point"}
}