{
  "type": "Feature",
  "properties": {
    "addr:full":"909 James Dr Monroe NC 28110",
    "addr:housenumber":"909",
    "addr:postcode":"28110",
    "addr:street":"James Dr",
    "iso:country":"US",
    "sg:address":"909 James Dr",
    "sg:city":"Monroe",
    "sg:classifiers":[
        {
            "category":"Utilities",
            "subcategory":"Refuse",
            "type":"Services"
        }
    ],
    "sg:phone":"+1 704 282 0102",
    "sg:postcode":"28110",
    "sg:province":"NC",
    "sg:tags":[
        "disposal",
        "waste"
    ],
    "wof:name":"Hawks Waste Svc",
    "wof:placetype":"venue"
},
  "geometry": {"coordinates":[-80.618803,34.965264],"type":"Point"}
}