{
  "type": "Feature",
  "properties": {
    "addr:full":"1830 Owen Dr Fayetteville NC 28304",
    "addr:housenumber":"1830",
    "addr:postcode":"28304",
    "addr:street":"Owen Dr",
    "iso:country":"US",
    "sg:address":"1830 Owen Dr",
    "sg:city":"Fayetteville",
    "sg:classifiers":[
        {
            "category":"Health Services",
            "subcategory":"Hospital",
            "type":"Services"
        }
    ],
    "sg:phone":"+1 910 609 4600",
    "sg:postcode":"28304",
    "sg:province":"NC",
    "wof:name":"Passport To Health",
    "wof:placetype":"venue"
},
  "geometry": {"coordinates":[-78.929816,35.029704],"type":"Point"}
}