{
  "type": "Feature",
  "properties": {
    "iso:country":"US",
    "sg:address":"5540 McNeely Dr",
    "sg:city":"Raleigh",
    "sg:classifiers":[
        {
            "category":"Professional",
            "subcategory":"Engineering",
            "type":"Services"
        }
    ],
    "sg:phone":"+1 919 786 9919",
    "sg:postcode":"27612",
    "sg:province":"NC",
    "sg:tags":[
        "engineer"
    ],
    "sg:website":"www.cloughharbour.com",
    "wof:name":"Clough Harbour & Assoc LLP",
    "wof:placetype":"venue"
},
  "geometry": {"coordinates":[-78.71234200000001,35.852748],"type":"Point"}
}