{
  "type": "Feature",
  "properties": {
    "addr:full":"816 State Rd 11 Magnolia NC 28453",
    "addr:housenumber":"816;11",
    "addr:postcode":"28453",
    "addr:street":"State Rd",
    "iso:country":"US",
    "sg:address":"816 State Rd 11",
    "sg:city":"Magnolia",
    "sg:classifiers":[
        {
            "category":"Farming",
            "subcategory":"Farm",
            "type":"Manufacturing & Wholesale Goods"
        }
    ],
    "sg:phone":"+1 910 296 0373",
    "sg:postcode":"28453",
    "sg:province":"NC",
    "sg:tags":[
        "crop",
        "general"
    ],
    "wof:name":"Tommy B Chestnutt",
    "wof:placetype":"venue"
},
  "geometry": {"coordinates":[-77.981871,34.916487],"type":"Point"}
}