{
  "type": "Feature",
  "properties": {
    "addr:full":"2815 Clyde Dr Charlotte NC 28208",
    "addr:housenumber":"2815",
    "addr:postcode":"28208",
    "addr:street":"Clyde Dr",
    "iso:country":"US",
    "sg:address":"2815 Clyde Dr",
    "sg:city":"Charlotte",
    "sg:classifiers":[
        {
            "category":"Organizations",
            "subcategory":"Religious Organization",
            "type":"Services"
        }
    ],
    "sg:phone":"+1   ",
    "sg:postcode":"28208",
    "sg:province":"NC",
    "wof:name":"New Macedonia of Faith",
    "wof:placetype":"venue"
},
  "geometry": {"coordinates":[-80.87204800000001,35.250726],"type":"Point"}
}