{
  "type": "Feature",
  "properties": {
    "addr:full":"1801 Oaklawn Ave Charlotte NC 28216",
    "addr:housenumber":"1801",
    "addr:postcode":"28216",
    "addr:street":"Oaklawn Ave",
    "iso:country":"US",
    "sg:address":"1801 Oaklawn Ave",
    "sg:city":"Charlotte",
    "sg:classifiers":[
        {
            "category":"Place Of Worship",
            "subcategory":"Church",
            "type":"Public Place"
        },
        {
            "category":"Place Of Worship",
            "type":"Public Place"
        }
    ],
    "sg:phone":"+1 704 376 2785",
    "sg:postcode":"28216",
    "sg:province":"NC",
    "sg:tags":[
        "churches-baptist-general",
        "churches-baptist"
    ],
    "sg:website":"http://www.abc-usa.org",
    "wof:name":"First Baptist Church",
    "wof:placetype":"venue"
},
  "geometry": {"coordinates":[-80.850632,35.25058],"type":"Point"}
}