{
  "type": "Feature",
  "properties": {
    "addr:full":"3656 Cape Center Dr Fayetteville NC 28304",
    "addr:housenumber":"3656",
    "addr:postcode":"28304",
    "addr:street":"Cape Center Dr",
    "iso:country":"US",
    "sg:address":"3656 Cape Center Dr",
    "sg:city":"Fayetteville",
    "sg:classifiers":[
        {
            "category":"Health Services",
            "subcategory":"Doctor",
            "type":"Services"
        }
    ],
    "sg:phone":"+1 910 483 2700",
    "sg:postcode":"28304",
    "sg:province":"NC",
    "sg:tags":[
        "dentist"
    ],
    "sg:website":"www.ccdnc.net",
    "wof:name":"Cape Center Dentistry",
    "wof:placetype":"venue"
},
  "geometry": {"coordinates":[-78.939244,35.036737],"type":"Point"}
}