{
  "type": "Feature",
  "properties": {
    "addr:full":"2017 Downing Ct Burlington NC 27215",
    "addr:housenumber":"2017",
    "addr:postcode":"27215",
    "addr:street":"Downing Ct",
    "iso:country":"US",
    "sg:address":"2017 Downing Ct",
    "sg:city":"Burlington",
    "sg:classifiers":[
        {
            "category":"Professional",
            "type":"Services"
        }
    ],
    "sg:phone":"+1 336 584 8717",
    "sg:postcode":"27215",
    "sg:province":"NC",
    "wof:name":"Thomas L Coble Foundation",
    "wof:placetype":"venue"
},
  "geometry": {"coordinates":[-79.471654,36.090749],"type":"Point"}
}