{
  "type": "Feature",
  "properties": {
    "iso:country":"US",
    "sg:address":"6131 Falls of Neuse Rd",
    "sg:city":"Raleigh",
    "sg:classifiers":[
        {
            "category":"Building & Trades",
            "subcategory":"Electrical",
            "type":"Services"
        }
    ],
    "sg:phone":"+1 919 532 0629",
    "sg:postcode":"27609",
    "sg:province":"NC",
    "sg:tags":[
        "telecommunication",
        "contractor"
    ],
    "wof:name":"Exper Tech",
    "wof:placetype":"venue"
},
  "geometry": {"coordinates":[-78.62070799999999,35.866591],"type":"Point"}
}