{
  "type": "Feature",
  "properties": {
    "addr:full":"10230 Willow Rock Dr Charlotte NC 28277",
    "addr:housenumber":"10230",
    "addr:postcode":"28277",
    "addr:street":"Willow Rock Dr",
    "iso:country":"US",
    "sg:address":"10230 Willow Rock Dr",
    "sg:city":"Charlotte",
    "sg:classifiers":[
        {
            "category":"Real Estate",
            "subcategory":"Real Estate Agent",
            "type":"Services"
        }
    ],
    "sg:phone":"+1 704 541 2581",
    "sg:postcode":"28277",
    "sg:province":"NC",
    "wof:name":"One Realty LLC",
    "wof:placetype":"venue"
},
  "geometry": {"coordinates":[-80.833242,35.039005],"type":"Point"}
}