{
  "type": "Feature",
  "properties": {
    "addr:full":"900 Fredonia Dr Fayetteville NC 28311",
    "addr:housenumber":"900",
    "addr:postcode":"28311",
    "addr:street":"Fredonia Dr",
    "iso:country":"US",
    "sg:address":"900 Fredonia Dr",
    "sg:city":"Fayetteville",
    "sg:classifiers":[
        {
            "category":"Social Services",
            "subcategory":"Adult Care",
            "type":"Services"
        }
    ],
    "sg:phone":"+1   ",
    "sg:postcode":"28311",
    "sg:province":"NC",
    "sg:tags":[
        "home",
        "group",
        "for",
        "elderly",
        "child"
    ],
    "wof:name":"Todd Real Estate",
    "wof:placetype":"venue"
},
  "geometry": {"coordinates":[-78.86356499999999,35.223763],"type":"Point"}
}