{
  "type": "Feature",
  "properties": {
    "iso:country":"US",
    "sg:address":"1857 Gaston Day School Rd",
    "sg:city":"Gastonia",
    "sg:classifiers":[
        {
            "category":"Real Estate",
            "subcategory":"Real Estate Operator",
            "type":"Services"
        }
    ],
    "sg:phone":"+1 704 867 3574",
    "sg:postcode":"28056",
    "sg:province":"NC",
    "sg:tags":[
        "building",
        "nonresidential"
    ],
    "wof:name":"B & C Properties Metrolina LLC",
    "wof:placetype":"venue"
},
  "geometry": {"coordinates":[-81.14816399999999,35.207305],"type":"Point"}
}