{
  "type": "Feature",
  "properties": {
    "addr:full":"1843 Clear Creek Rd Marion NC 28752",
    "addr:housenumber":"1843",
    "addr:postcode":"28752",
    "addr:street":"Clear Creek Rd",
    "iso:country":"US",
    "sg:address":"1843 Clear Creek Rd",
    "sg:city":"Marion",
    "sg:classifiers":[
        {
            "category":"Wholesale",
            "subcategory":"Groceries",
            "type":"Manufacturing & Wholesale Goods"
        }
    ],
    "sg:phone":"+1 828 724 4435",
    "sg:postcode":"28752",
    "sg:province":"NC",
    "wof:name":"Fox Spring Water",
    "wof:placetype":"venue"
},
  "geometry": {"coordinates":[-82.098814,35.703951],"type":"Point"}
}