{
  "type": "Feature",
  "properties": {
    "iso:country":"US",
    "sg:address":"625 S Van Buren Rd",
    "sg:city":"Eden",
    "sg:classifiers":[
        {
            "category":"Shopping",
            "subcategory":"Pharmacy",
            "type":"Retail Goods"
        }
    ],
    "sg:phone":"+1 336 627 8460",
    "sg:postcode":"27288",
    "sg:province":"NC",
    "wof:name":"CVS",
    "wof:placetype":"venue"
},
  "geometry": {"coordinates":[-79.74033300000001,36.492254],"type":"Point"}
}