{
  "type": "Feature",
  "properties": {
    "addr:full":"9745 Fonville Rd Wake Forest NC 27587",
    "addr:housenumber":"9745",
    "addr:postcode":"27587",
    "addr:street":"Fonville Rd",
    "iso:country":"US",
    "sg:address":"9745 Fonville Rd",
    "sg:city":"Wake Forest",
    "sg:classifiers":[
        {
            "category":"Autos & Motor Vehicles",
            "subcategory":"Boat Sales",
            "type":"Retail Goods"
        }
    ],
    "sg:phone":"+1 919 866 1954",
    "sg:postcode":"27587",
    "sg:province":"NC",
    "sg:tags":[
        "canoe"
    ],
    "wof:name":"Pro Canoe & Kayaks",
    "wof:placetype":"venue"
},
  "geometry": {"coordinates":[-78.579725,35.939693],"type":"Point"}
}