{
  "type": "Feature",
  "properties": {
    "iso:country":"US",
    "sg:address":"3646 Morris Farm Dr",
    "sg:city":"Greensboro",
    "sg:classifiers":[
        {
            "category":"Professional",
            "subcategory":"Employment Agencies",
            "type":"Services"
        }
    ],
    "sg:phone":"+1 336 297 1315",
    "sg:postcode":"27409",
    "sg:province":"NC",
    "sg:tags":[
        "consultant",
        "search",
        "executive"
    ],
    "wof:name":"AKA Recruiting Assoc Inc",
    "wof:placetype":"venue"
},
  "geometry": {"coordinates":[-79.939441,36.042369],"type":"Point"}
}