{
  "type": "Feature",
  "properties": {
    "iso:country":"US",
    "sg:address":"1248 White Smith Rd",
    "sg:city":"Pittsboro",
    "sg:classifiers":[
        {
            "category":"Home & Garden",
            "subcategory":"Furniture",
            "type":"Retail Goods"
        }
    ],
    "sg:phone":"+1 919 742 3327",
    "sg:postcode":"27312",
    "sg:province":"NC",
    "wof:name":"Empty Cabinets",
    "wof:placetype":"venue"
},
  "geometry": {"coordinates":[-79.313565,35.787061],"type":"Point"}
}