{
  "type": "Feature",
  "properties": {
    "iso:country":"US",
    "sg:address":"16 Conifer Ct",
    "sg:city":"Whittier",
    "sg:classifiers":[
        {
            "category":"Travel",
            "subcategory":"Hotels & Motels",
            "type":"Entertainment"
        }
    ],
    "sg:phone":"+1   ",
    "sg:postcode":"28732",
    "sg:province":"NC",
    "sg:tags":[
        "operation"
    ],
    "wof:name":"Isle of Dreams Motel",
    "wof:placetype":"venue"
},
  "geometry": {"coordinates":[-82.40728900000001,35.447523],"type":"Point"}
}