{
  "type": "Feature",
  "properties": {
    "addr:full":"100 Executive Park Asheville NC 28801",
    "addr:housenumber":"100",
    "addr:postcode":"28801",
    "addr:street":"Executive Park",
    "iso:country":"US",
    "sg:address":"100 Executive Park",
    "sg:city":"Asheville",
    "sg:classifiers":[
        {
            "category":"Health Services",
            "subcategory":"Doctor",
            "type":"Services"
        }
    ],
    "sg:phone":"+1 828 254 1944",
    "sg:postcode":"28801",
    "sg:province":"NC",
    "sg:tags":[
        "dentist"
    ],
    "sg:website":"www.dentistrybyphillips.com",
    "wof:name":"Phillips & Rogers",
    "wof:placetype":"venue"
},
  "geometry": {"coordinates":[-82.545423,35.598344],"type":"Point"}
}