{
  "type": "Feature",
  "properties": {
    "addr:full":"8940 S Tryon St Charlotte NC 28273",
    "addr:housenumber":"8940",
    "addr:postcode":"28273",
    "addr:street":"S Tryon St",
    "iso:country":"US",
    "sg:address":"8940 S Tryon St",
    "sg:city":"Charlotte",
    "sg:classifiers":[
        {
            "category":"Autos & Motor Vehicles",
            "subcategory":"Auto Supplies",
            "type":"Retail Goods"
        },
        {
            "category":"Retail",
            "subcategory":"Auto Repair",
            "type":"Services"
        }
    ],
    "sg:phone":"+1 704 504 1575",
    "sg:postcode":"28273",
    "sg:province":"NC",
    "sg:tags":[
        "wheel",
        "tire",
        "retread",
        "balancing",
        "wheels-aligning",
        "recap",
        "brake"
    ],
    "sg:website":"http://www.tirekingdom.com",
    "wof:name":"Tire Kingdom",
    "wof:placetype":"venue"
},
  "geometry": {"coordinates":[-80.950665,35.120775],"type":"Point"}
}