{
  "type": "Feature",
  "properties": {
    "addr:full":"5112 Hunter Hill Dr Raleigh NC 27604",
    "addr:housenumber":"5112",
    "addr:postcode":"27604",
    "addr:street":"Hunter Hill Dr",
    "iso:country":"US",
    "sg:address":"5112 Hunter Hill Dr",
    "sg:city":"Raleigh",
    "sg:classifiers":[
        {
            "category":"Building & Trades",
            "subcategory":"Cleaning & Sanitation",
            "type":"Services"
        }
    ],
    "sg:phone":"+1   ",
    "sg:postcode":"27604",
    "sg:province":"NC",
    "sg:tags":[
        "maintenance"
    ],
    "wof:name":"Browns Cleaning Service",
    "wof:placetype":"venue"
},
  "geometry": {"coordinates":[-78.55287,35.824211],"type":"Point"}
}