{
  "type": "Feature",
  "properties": {
    "addr:full":"1238 N Wesleyan Blvd Rocky Mount NC 27804",
    "addr:housenumber":"1238",
    "addr:postcode":"27804",
    "addr:street":"N Wesleyan Blvd",
    "iso:country":"US",
    "sg:address":"1238 N Wesleyan Blvd",
    "sg:city":"Rocky Mount",
    "sg:classifiers":[
        {
            "category":"Shopping",
            "type":"Retail Goods"
        }
    ],
    "sg:phone":"+1 252 446 4600",
    "sg:postcode":"27804",
    "sg:province":"NC",
    "sg:tags":[
        "phone",
        "cellular"
    ],
    "wof:name":"Alltel",
    "wof:placetype":"venue"
},
  "geometry": {"coordinates":[-77.798922,35.975217],"type":"Point"}
}