{
  "type": "Feature",
  "properties": {
    "addr:full":"228 Zeb Robinson Rd Henderson NC 27537",
    "addr:housenumber":"228",
    "addr:postcode":"27537",
    "addr:street":"Zeb Robinson Rd",
    "iso:country":"US",
    "sg:address":"228 Zeb Robinson Rd",
    "sg:city":"Henderson",
    "sg:classifiers":[
        {
            "category":"Autos & Motor Vehicles",
            "subcategory":"Recreational Vehicle Sales",
            "type":"Retail Goods"
        }
    ],
    "sg:phone":"+1 252 430 7010",
    "sg:postcode":"27537",
    "sg:province":"NC",
    "sg:tags":[
        "canopy",
        "shell",
        "truck",
        "cap"
    ],
    "wof:name":"Leonard Buildings & Truck Cvrs",
    "wof:placetype":"venue"
},
  "geometry": {"coordinates":[-78.45228299999999,36.32586],"type":"Point"}
}