{
  "type": "Feature",
  "properties": {
    "addr:full":"4909 Raeford Rd Fayetteville NC 28304",
    "addr:housenumber":"4909",
    "addr:postcode":"28304",
    "addr:street":"Raeford Rd",
    "iso:country":"US",
    "sg:address":"4909 Raeford Rd",
    "sg:city":"Fayetteville",
    "sg:classifiers":[
        {
            "category":"Shopping",
            "type":"Retail Goods"
        }
    ],
    "sg:phone":"+1 910 426 3056",
    "sg:postcode":"28304",
    "sg:province":"NC",
    "sg:tags":[
        "plant",
        "flower",
        "tree",
        "artificial"
    ],
    "wof:name":"Joy Silk Flower Shop",
    "wof:placetype":"venue"
},
  "geometry": {"coordinates":[-78.96081599999999,35.042809],"type":"Point"}
}