{
  "type": "Feature",
  "properties": {
    "addr:full":"145 W High Ave High Point NC 27260",
    "addr:housenumber":"145",
    "addr:postcode":"27260",
    "addr:street":"W High Ave",
    "iso:country":"US",
    "sg:address":"145 W High Ave",
    "sg:city":"High Point",
    "sg:classifiers":[
        {
            "category":"Building & Trades",
            "subcategory":"Landscaping Services",
            "type":"Services"
        }
    ],
    "sg:phone":"+1 336 882 3344",
    "sg:postcode":"27260",
    "sg:province":"NC",
    "sg:tags":[
        "tree"
    ],
    "wof:name":"Sunshine Tree & Fence Inc",
    "wof:placetype":"venue"
},
  "geometry": {"coordinates":[-80.007244,35.956531],"type":"Point"}
}