{
  "type": "Feature",
  "properties": {
    "iso:country":"US",
    "sg:address":"200 Granville St",
    "sg:city":"Oxford",
    "sg:classifiers":[
        {
            "category":"Banks & Credit Unions",
            "subcategory":"Bank",
            "type":"Services"
        }
    ],
    "sg:phone":"+1 919 690 0006",
    "sg:postcode":"27565",
    "sg:province":"NC",
    "sg:tags":[
        "cashing",
        "check"
    ],
    "wof:name":"Check & Go Of Nc Inc",
    "wof:placetype":"venue"
},
  "geometry": {"coordinates":[-78.591211,36.308666],"type":"Point"}
}