{
  "type": "Feature",
  "properties": {
    "addr:full":"2811 Fairway Dr Raleigh NC 27603",
    "addr:housenumber":"2811",
    "addr:postcode":"27603",
    "addr:street":"Fairway Dr",
    "iso:country":"US",
    "sg:address":"2811 Fairway Dr",
    "sg:city":"Raleigh",
    "sg:classifiers":[
        {
            "category":"Wholesale",
            "subcategory":"Auto Parts",
            "type":"Manufacturing & Wholesale Goods"
        }
    ],
    "sg:phone":"+1 919 772 3878",
    "sg:postcode":"27603",
    "sg:province":"NC",
    "sg:tags":[
        "tool"
    ],
    "wof:name":"Murray Tool Co",
    "wof:placetype":"venue"
},
  "geometry": {"coordinates":[-78.665773,35.741901],"type":"Point"}
}