{
  "type": "Feature",
  "properties": {
    "iso:country":"US",
    "sg:address":"7102 Graburn Rd",
    "sg:city":"Charlotte",
    "sg:classifiers":[
        {
            "category":"Professional",
            "type":"Services"
        }
    ],
    "sg:phone":"+1 704 544 7878",
    "sg:postcode":"28226",
    "sg:province":"NC",
    "wof:name":"Culturlink Inc",
    "wof:placetype":"venue"
},
  "geometry": {"coordinates":[-80.84708999999999,35.07698],"type":"Point"}
}