{
  "type": "Feature",
  "properties": {
    "iso:country":"US",
    "sg:address":"907 Vernon St",
    "sg:city":"Garner",
    "sg:classifiers":[
        {
            "category":"Real Estate",
            "subcategory":"Real Estate Agent",
            "type":"Services"
        }
    ],
    "sg:phone":"+1 919 779 6938",
    "sg:postcode":"27529",
    "sg:province":"NC",
    "wof:name":"Kld LLC",
    "wof:placetype":"venue"
},
  "geometry": {"coordinates":[-78.60060900000001,35.692639],"type":"Point"}
}