{
  "type": "Feature",
  "properties": {
    "iso:country":"US",
    "sg:address":"4821 High Point Rd",
    "sg:city":"Greensboro",
    "sg:classifiers":[
        {
            "category":"Home & Garden",
            "subcategory":"Garden Supply",
            "type":"Retail Goods"
        }
    ],
    "sg:phone":"+1 336 272 6766",
    "sg:postcode":"27407",
    "sg:province":"NC",
    "wof:name":"Branson Tractor South",
    "wof:placetype":"venue"
},
  "geometry": {"coordinates":[-79.873486,36.026484],"type":"Point"}
}