{
  "type": "Feature",
  "properties": {
    "iso:country":"US",
    "sg:address":"3005 US Hwy 220 Bus",
    "sg:city":"Stoneville",
    "sg:classifiers":[
        {
            "category":"Building & Trades",
            "subcategory":"Construction",
            "type":"Services"
        },
        {
            "category":"Mining & Drilling",
            "type":"Manufacturing & Wholesale Goods"
        }
    ],
    "sg:phone":"+1 336 573 3040",
    "sg:postcode":"27048",
    "sg:province":"NC",
    "sg:tags":[
        "concrete",
        "product",
        "contractor",
        "stone",
        "mfg"
    ],
    "sg:website":"www.piedmontstone.com",
    "wof:name":"Piedmont Stone Inc",
    "wof:placetype":"venue"
},
  "geometry": {"coordinates":[-79.932371,36.444641],"type":"Point"}
}