{
  "type": "Feature",
  "properties": {
    "iso:country":"US",
    "sg:address":"61 Fernwood Ln",
    "sg:city":"Chapel Hill",
    "sg:classifiers":[
        {
            "category":"Professional",
            "subcategory":"Management & Consulting",
            "type":"Services"
        }
    ],
    "sg:phone":"+1   ",
    "sg:postcode":"27516",
    "sg:province":"NC",
    "sg:tags":[
        "public",
        "relations"
    ],
    "wof:name":"Thomas Db Inc",
    "wof:placetype":"venue"
},
  "geometry": {"coordinates":[-79.066909,35.920408],"type":"Point"}
}