{
  "type": "Feature",
  "properties": {
    "addr:full":"6160 River Sound Cir Southport NC 28461",
    "addr:housenumber":"6160",
    "addr:postcode":"28461",
    "addr:street":"River Sound Cir",
    "iso:country":"US",
    "sg:address":"6160 River Sound Cir",
    "sg:city":"Southport",
    "sg:classifiers":[
        {
            "category":"Building & Trades",
            "subcategory":"Construction",
            "type":"Services"
        }
    ],
    "sg:phone":"+1 910 454 0089",
    "sg:postcode":"28461",
    "sg:province":"NC",
    "sg:tags":[
        "house"
    ],
    "wof:name":"C Mark Williams Builders LLC",
    "wof:placetype":"venue"
},
  "geometry": {"coordinates":[-78.002516,33.930628],"type":"Point"}
}