{
  "type": "Feature",
  "properties": {
    "addr:full":"2115 E 7th St Ste 102 Charlotte NC 28204",
    "addr:housenumber":"2115",
    "addr:postcode":"28204",
    "addr:street":"E 7Th St Ste 102",
    "iso:country":"US",
    "sg:address":"2115 E 7th St Ste 102",
    "sg:city":"Charlotte",
    "sg:classifiers":[
        {
            "category":"Health Services",
            "subcategory":"Doctor",
            "type":"Services"
        }
    ],
    "sg:phone":"+1 704 372 3126",
    "sg:postcode":"28204",
    "sg:province":"NC",
    "sg:tags":[
        "physician",
        "oncology",
        "family",
        "practice",
        "surgeons",
        "hematology",
        "internal",
        "blood",
        "medicine",
        "surgeon"
    ],
    "wof:name":"Carolina Medical Associates",
    "wof:placetype":"venue"
},
  "geometry": {"coordinates":[-80.816588,35.21132],"type":"Point"}
}