{
  "type": "Feature",
  "properties": {
    "addr:full":"1739 Harrington Hwy Eden NC 27288",
    "addr:housenumber":"1739",
    "addr:postcode":"27288",
    "addr:street":"Harrington Hwy",
    "iso:country":"US",
    "sg:address":"1739 Harrington Hwy",
    "sg:city":"Eden",
    "sg:classifiers":[
        {
            "category":"Organizations",
            "subcategory":"Religious Organization",
            "type":"Services"
        }
    ],
    "sg:phone":"+1   ",
    "sg:postcode":"27288",
    "sg:province":"NC",
    "wof:name":"First Assembly Of God",
    "wof:placetype":"venue"
},
  "geometry": {"coordinates":[-79.77465100000001,36.460172],"type":"Point"}
}