{
  "type": "Feature",
  "properties": {
    "addr:full":"2512 Delaney Ave Wilmington NC 28403",
    "addr:housenumber":"2512",
    "addr:postcode":"28403",
    "addr:street":"Delaney Ave",
    "iso:country":"US",
    "sg:address":"2512 Delaney Ave",
    "sg:city":"Wilmington",
    "sg:classifiers":[
        {
            "category":"Health Services",
            "subcategory":"Doctor",
            "type":"Services"
        }
    ],
    "sg:phone":"+1   ",
    "sg:postcode":"28403",
    "sg:province":"NC",
    "sg:tags":[
        "medical"
    ],
    "wof:name":"Robert T Bennett MD",
    "wof:placetype":"venue"
},
  "geometry": {"coordinates":[-77.920407,34.198911],"type":"Point"}
}