{
  "type": "Feature",
  "properties": {
    "addr:full":"100 Cheerio Ln Asheville NC 28803",
    "addr:housenumber":"100",
    "addr:postcode":"28803",
    "addr:street":"Cheerio Ln",
    "iso:country":"US",
    "sg:address":"100 Cheerio Ln",
    "sg:city":"Asheville",
    "sg:classifiers":[
        {
            "category":"Real Estate",
            "subcategory":"Real Estate Agent",
            "type":"Services"
        }
    ],
    "sg:phone":"+1 828 298 9390",
    "sg:postcode":"28803",
    "sg:province":"NC",
    "wof:name":"Arrowhead Apartments",
    "wof:placetype":"venue"
},
  "geometry": {"coordinates":[-82.517456,35.570197],"type":"Point"}
}