{
  "type": "Feature",
  "properties": {
    "iso:country":"US",
    "sg:address":"634 Junction Rd",
    "sg:city":"Durham",
    "sg:classifiers":[
        {
            "category":"Building & Trades",
            "subcategory":"Electrical",
            "type":"Services"
        }
    ],
    "sg:phone":"+1 919 596 3909",
    "sg:postcode":"27703",
    "sg:province":"NC",
    "sg:tags":[
        "electrical",
        "contractor"
    ],
    "wof:name":"Rw Nance Electric Co",
    "wof:placetype":"venue"
},
  "geometry": {"coordinates":[-78.850556,35.999434],"type":"Point"}
}