{
  "type": "Feature",
  "properties": {
    "addr:full":"402 N Greene St Greenville NC 27834",
    "addr:housenumber":"402",
    "addr:postcode":"27834",
    "addr:street":"N Greene St",
    "iso:country":"US",
    "sg:address":"402 N Greene St",
    "sg:city":"Greenville",
    "sg:classifiers":[
        {
            "category":"Professional",
            "subcategory":"Computer Services",
            "type":"Services"
        }
    ],
    "sg:phone":"+1 252 931 9472",
    "sg:postcode":"27834",
    "sg:province":"NC",
    "wof:name":"Silicon Solutions Inc",
    "wof:placetype":"venue"
},
  "geometry": {"coordinates":[-77.373783,35.624608],"type":"Point"}
}