{
  "type": "Feature",
  "properties": {
    "iso:country":"US",
    "sg:address":"106 Beacon St",
    "sg:city":"Swannanoa",
    "sg:classifiers":[
        {
            "category":"Building & Trades",
            "subcategory":"Construction",
            "type":"Services"
        }
    ],
    "sg:phone":"+1 828 686 3638",
    "sg:postcode":"28778",
    "sg:province":"NC",
    "sg:tags":[
        "house"
    ],
    "wof:name":"Steves Home Repair",
    "wof:placetype":"venue"
},
  "geometry": {"coordinates":[-82.398595,35.599367],"type":"Point"}
}