{
  "type": "Feature",
  "properties": {
    "addr:full":"170 Joe Mooney Rd Clyde NC 28721",
    "addr:housenumber":"170",
    "addr:postcode":"28721",
    "addr:street":"Joe Mooney Rd",
    "iso:country":"US",
    "sg:address":"170 Joe Mooney Rd",
    "sg:city":"Clyde",
    "sg:classifiers":[
        {
            "category":"Organizations",
            "subcategory":"Religious Organization",
            "type":"Services"
        }
    ],
    "sg:phone":"+1   ",
    "sg:postcode":"28721",
    "sg:province":"NC",
    "wof:name":"Jehovah Raah Farm",
    "wof:placetype":"venue"
},
  "geometry": {"coordinates":[-82.9147,35.677067],"type":"Point"}
}