{
  "type": "Feature",
  "properties": {
    "iso:country":"US",
    "sg:address":"208 N Caldwell St",
    "sg:city":"Charlotte",
    "sg:classifiers":[
        {
            "category":"Organizations",
            "subcategory":"Religious Organization",
            "type":"Services"
        }
    ],
    "sg:phone":"+1 704 972 3601",
    "sg:postcode":"28202",
    "sg:province":"NC",
    "sg:tags":[
        "church"
    ],
    "wof:name":"Billy Graham Evangelist",
    "wof:placetype":"venue"
},
  "geometry": {"coordinates":[-80.836844,35.225188],"type":"Point"}
}