{
  "type": "Feature",
  "properties": {
    "addr:full":"7730 Campground Rd Denver NC 28037",
    "addr:housenumber":"7730",
    "addr:postcode":"28037",
    "addr:street":"Campground Rd",
    "iso:country":"US",
    "sg:address":"7730 Campground Rd",
    "sg:city":"Denver",
    "sg:classifiers":[
        {
            "category":"Manufacturing",
            "subcategory":"Tools & Machinery",
            "type":"Manufacturing & Wholesale Goods"
        }
    ],
    "sg:phone":"+1 704 489 6396",
    "sg:postcode":"28037",
    "sg:province":"NC",
    "sg:tags":[
        "conductive",
        "wiring",
        "devices",
        "mfg"
    ],
    "wof:name":"Bill Muncy Electric",
    "wof:placetype":"venue"
},
  "geometry": {"coordinates":[-81.001369,35.548411],"type":"Point"}
}