{
  "type": "Feature",
  "properties": {
    "addr:full":"11833 Doc Arnold Dr Raleigh NC 27614",
    "addr:housenumber":"11833",
    "addr:postcode":"27614",
    "addr:street":"Doc Arnold Dr",
    "iso:country":"US",
    "sg:address":"11833 Doc Arnold Dr",
    "sg:city":"Raleigh",
    "sg:classifiers":[
        {
            "category":"Freight",
            "type":"Transportation"
        }
    ],
    "sg:phone":"+1 919 870 0916",
    "sg:postcode":"27614",
    "sg:province":"NC",
    "sg:tags":[
        "trucking"
    ],
    "wof:name":"Woodson Transport Inc",
    "wof:placetype":"venue"
},
  "geometry": {"coordinates":[-78.685817,35.969379],"type":"Point"}
}