{
  "type": "Feature",
  "properties": {
    "addr:full":"495 Burlington Rd Roxboro NC 27573",
    "addr:housenumber":"495",
    "addr:postcode":"27573",
    "addr:street":"Burlington Rd",
    "iso:country":"US",
    "sg:address":"495 Burlington Rd",
    "sg:city":"Roxboro",
    "sg:classifiers":[
        {
            "category":"Recreation",
            "subcategory":"Amusement Park",
            "type":"Entertainment"
        }
    ],
    "sg:phone":"+1 336 597 3733",
    "sg:postcode":"27573",
    "sg:province":"NC",
    "wof:name":"Bingo World",
    "wof:placetype":"venue"
},
  "geometry": {"coordinates":[-79.001565,36.389718],"type":"Point"}
}