{
  "type": "Feature",
  "properties": {
    "iso:country":"US",
    "sg:address":"5288 Burton Rd",
    "sg:city":"Thomasville",
    "sg:classifiers":[
        {
            "category":"Personal",
            "subcategory":"Beauty Salon",
            "type":"Services"
        }
    ],
    "sg:phone":"+1 336 475 3117",
    "sg:postcode":"27360",
    "sg:province":"NC",
    "sg:tags":[
        "shop"
    ],
    "wof:name":"Everhart's Beauty Shop",
    "wof:placetype":"venue"
},
  "geometry": {"coordinates":[-80.100421,35.929052],"type":"Point"}
}