{
  "type": "Feature",
  "properties": {
    "iso:country":"US",
    "sg:address":"417 N Salisbury St",
    "sg:city":"Raleigh",
    "sg:classifiers":[
        {
            "category":"Government",
            "subcategory":"Office",
            "type":"Public Place"
        }
    ],
    "sg:phone":"+1 919 733 4646",
    "sg:postcode":"27603",
    "sg:province":"NC",
    "wof:name":"Capitol Police",
    "wof:placetype":"venue"
},
  "geometry": {"coordinates":[-78.639957,35.784414],"type":"Point"}
}