{
  "type": "Feature",
  "properties": {
    "iso:country":"US",
    "sg:address":"10 Spring Hollow Ln",
    "sg:city":"Fairview",
    "sg:classifiers":[
        {
            "category":"Real Estate",
            "subcategory":"Real Estate Agent",
            "type":"Services"
        }
    ],
    "sg:phone":"+1 828 628 1205",
    "sg:postcode":"28730",
    "sg:province":"NC",
    "wof:name":"Carolina Country Realty Inc",
    "wof:placetype":"venue"
},
  "geometry": {"coordinates":[-82.36422399999999,35.514462],"type":"Point"}
}