{
  "type": "Feature",
  "properties": {
    "iso:country":"US",
    "sg:address":"1858 Hillandale Rd",
    "sg:city":"Durham",
    "sg:classifiers":[
        {
            "category":"Health Services",
            "subcategory":"Doctor",
            "type":"Services"
        }
    ],
    "sg:phone":"+1 919 471 1064",
    "sg:postcode":"27705",
    "sg:province":"NC",
    "sg:tags":[
        "dentist"
    ],
    "wof:name":"Michael D Fleming DDS",
    "wof:placetype":"venue"
},
  "geometry": {"coordinates":[-78.935603,36.033103],"type":"Point"}
}