{
  "type": "Feature",
  "properties": {
    "iso:country":"US",
    "sg:address":"600 College St",
    "sg:city":"Clinton",
    "sg:classifiers":[
        {
            "category":"Professional",
            "subcategory":"Lawyer & Legal Services",
            "type":"Services"
        }
    ],
    "sg:phone":"+1 910 592 3111",
    "sg:postcode":"28328",
    "sg:province":"NC",
    "sg:tags":[
        "attorney"
    ],
    "wof:name":"Benjamin L Wright",
    "wof:placetype":"venue"
},
  "geometry": {"coordinates":[-78.317792,35.001853],"type":"Point"}
}