{
  "type": "Feature",
  "properties": {
    "addr:full":"248 W Main St Washington NC 27889",
    "addr:housenumber":"248",
    "addr:postcode":"27889",
    "addr:street":"W Main St",
    "iso:country":"US",
    "sg:address":"248 W Main St",
    "sg:city":"Washington",
    "sg:classifiers":[
        {
            "category":"Professional",
            "subcategory":"Accounting & Tax Preparation",
            "type":"Services"
        }
    ],
    "sg:phone":"+1 252 946 0545",
    "sg:postcode":"27889",
    "sg:province":"NC",
    "sg:tags":[
        "accountant"
    ],
    "sg:website":"www.nctaxhelp.com",
    "wof:name":"Wilson Jones & Co",
    "wof:placetype":"venue"
},
  "geometry": {"coordinates":[-77.05771799999999,35.543323],"type":"Point"}
}