{
  "type": "Feature",
  "properties": {
    "iso:country":"US",
    "sg:address":"16300 Statesville Rd",
    "sg:city":"Huntersville",
    "sg:classifiers":[
        {
            "category":"Restaurant",
            "type":"Food & Drink"
        }
    ],
    "sg:phone":"+1 704 895 6199",
    "sg:postcode":"28078",
    "sg:province":"NC",
    "sg:website":"www.showmars.com",
    "wof:name":"Showmars Restaurant-Hntrsvll",
    "wof:placetype":"venue"
},
  "geometry": {"coordinates":[-80.86534399999999,35.437404],"type":"Point"}
}