{
  "type": "Feature",
  "properties": {
    "iso:country":"US",
    "sg:address":"1315 State Hwy 87",
    "sg:city":"Spring Lake",
    "sg:classifiers":[
        {
            "category":"Retail",
            "subcategory":"Laundry & Dry Cleaning",
            "type":"Services"
        }
    ],
    "sg:phone":"+1 910 497 4580",
    "sg:postcode":"28390",
    "sg:province":"NC",
    "sg:tags":[
        "cleaners"
    ],
    "wof:name":"Glam-O-Rama Cleaners & Laundry",
    "wof:placetype":"venue"
},
  "geometry": {"coordinates":[-78.982891,35.184641],"type":"Point"}
}