{
  "type": "Feature",
  "properties": {
    "addr:full":"596 State Hwy 27 Midland NC 28107",
    "addr:housenumber":"596",
    "addr:postcode":"28107",
    "addr:street":"State Hwy 27",
    "iso:country":"US",
    "sg:address":"596 State Hwy 27",
    "sg:city":"Midland",
    "sg:classifiers":[
        {
            "category":"Shopping",
            "subcategory":"Hobbies, Toys, & Games",
            "type":"Retail Goods"
        }
    ],
    "sg:phone":"+1 704 888 3055",
    "sg:postcode":"28107",
    "sg:province":"NC",
    "sg:tags":[
        "doll"
    ],
    "wof:name":"Linda's Dolls & Varieties",
    "wof:placetype":"venue"
},
  "geometry": {"coordinates":[-80.583054,35.24716],"type":"Point"}
}