{
  "type": "Feature",
  "properties": {
    "iso:country":"US",
    "sg:address":"441 E Dixie Dr",
    "sg:city":"Asheboro",
    "sg:classifiers":[
        {
            "category":"Banks & Credit Unions",
            "subcategory":"Financial Services",
            "type":"Services"
        }
    ],
    "sg:phone":"+1 336 629 2294",
    "sg:postcode":"27203",
    "sg:province":"NC",
    "sg:tags":[
        "investor"
    ],
    "wof:name":"Davison Investments",
    "wof:placetype":"venue"
},
  "geometry": {"coordinates":[-79.81201799999999,35.688608],"type":"Point"}
}