{
  "type": "Feature",
  "properties": {
    "addr:full":"503 Aztec Dr Archdale NC 27263",
    "addr:housenumber":"503",
    "addr:postcode":"27263",
    "addr:street":"Aztec Dr",
    "iso:country":"US",
    "sg:address":"503 Aztec Dr",
    "sg:city":"Archdale",
    "sg:classifiers":[
        {
            "category":"Retail",
            "subcategory":"Repair Shop",
            "type":"Services"
        }
    ],
    "sg:phone":"+1 336 434 5420",
    "sg:postcode":"27263",
    "sg:province":"NC",
    "sg:tags":[
        "upholsterer"
    ],
    "wof:name":"Carolina Custom Furniture",
    "wof:placetype":"venue"
},
  "geometry": {"coordinates":[-79.959217,35.895307],"type":"Point"}
}