{
  "type": "Feature",
  "properties": {
    "addr:full":"106B S Sharon Amity Rd Charlotte NC 28211",
    "addr:housenumber":"106b",
    "addr:postcode":"28211",
    "addr:street":"S Sharon Amity Rd",
    "iso:country":"US",
    "sg:address":"106B S Sharon Amity Rd",
    "sg:city":"Charlotte",
    "sg:phone":"+1 704 366 3666",
    "sg:postcode":"28211",
    "sg:province":"NC",
    "wof:name":"Wolfman Pizza (cotswold)",
    "wof:placetype":"venue"
},
  "geometry": {"coordinates":[-80.79843,35.175903],"type":"Point"}
}