{
  "type": "Feature",
  "properties": {
    "iso:country":"US",
    "sg:address":"302 Concord St",
    "sg:city":"Greensboro",
    "sg:classifiers":[
        {
            "category":"Building & Trades",
            "subcategory":"Plumbing",
            "type":"Services"
        }
    ],
    "sg:phone":"+1 336 272 2442",
    "sg:postcode":"27406",
    "sg:province":"NC",
    "sg:tags":[
        "plumbing",
        "contractor"
    ],
    "wof:name":"Jones Plumbing Inc",
    "wof:placetype":"venue"
},
  "geometry": {"coordinates":[-79.800878,36.043441],"type":"Point"}
}