{
  "type": "Feature",
  "properties": {
    "addr:full":"650 Coliseum Dr NW Winston Salem NC 27106",
    "addr:housenumber":"650",
    "addr:postcode":"27106",
    "addr:street":"Coliseum Dr Nw",
    "iso:country":"US",
    "sg:address":"650 Coliseum Dr NW",
    "sg:city":"Winston Salem",
    "sg:classifiers":[
        {
            "category":"Health Services",
            "subcategory":"Doctor",
            "type":"Services"
        }
    ],
    "sg:phone":"+1 336 721 0529",
    "sg:postcode":"27106",
    "sg:province":"NC",
    "sg:tags":[
        "clinic"
    ],
    "wof:name":"Triad Blood Ctr",
    "wof:placetype":"venue"
},
  "geometry": {"coordinates":[-80.26137900000001,36.124191],"type":"Point"}
}