{
  "type": "Feature",
  "properties": {
    "iso:country":"US",
    "sg:address":"803 Washington St",
    "sg:city":"Williamston",
    "sg:classifiers":[
        {
            "category":"Personal",
            "type":"Services"
        }
    ],
    "sg:phone":"+1 252 792 0660",
    "sg:postcode":"27892",
    "sg:province":"NC",
    "sg:tags":[
        "merchandise"
    ],
    "wof:name":"Your Tailor",
    "wof:placetype":"venue"
},
  "geometry": {"coordinates":[-77.061106,35.844825],"type":"Point"}
}