{
  "type": "Feature",
  "properties": {
    "iso:country":"US",
    "sg:address":"3919 Fallston-Waco Rd",
    "sg:city":"Lawndale",
    "sg:classifiers":[
        {
            "category":"Wholesale",
            "subcategory":"Durable Goods & Equipment",
            "type":"Manufacturing & Wholesale Goods"
        }
    ],
    "sg:phone":"+1 704 482 2676",
    "sg:postcode":"28090",
    "sg:province":"NC",
    "sg:tags":[
        "fire",
        "extinguisher"
    ],
    "wof:name":"Jack's Fire Extinguisher Co",
    "wof:placetype":"venue"
},
  "geometry": {"coordinates":[-81.49185199999999,35.420519],"type":"Point"}
}