{
  "type": "Feature",
  "properties": {
    "iso:country":"US",
    "sg:address":"243 Weatherfield Ln",
    "sg:city":"Kernersville",
    "sg:classifiers":[
        {
            "category":"Building & Trades",
            "subcategory":"Construction",
            "type":"Services"
        }
    ],
    "sg:phone":"+1 336 993 4716",
    "sg:postcode":"27284",
    "sg:province":"NC",
    "sg:tags":[
        "carpentry",
        "contractor"
    ],
    "wof:name":"Thomas Hensley",
    "wof:placetype":"venue"
},
  "geometry": {"coordinates":[-80.104136,36.120821],"type":"Point"}
}