{
  "type": "Feature",
  "properties": {
    "iso:country":"US",
    "sg:address":"631 Harveydale Dr",
    "sg:city":"Fayetteville",
    "sg:classifiers":[
        {
            "category":"Building & Trades",
            "subcategory":"Landscaping Services",
            "type":"Services"
        }
    ],
    "sg:phone":"+1 910 494 1350",
    "sg:postcode":"28301",
    "sg:province":"NC",
    "sg:tags":[
        "tree"
    ],
    "wof:name":"Mc Neill Tree Svc",
    "wof:placetype":"venue"
},
  "geometry": {"coordinates":[-78.890945,35.1037],"type":"Point"}
}