{
  "type": "Feature",
  "properties": {
    "iso:country":"US",
    "sg:address":"604 Benton Express Ave",
    "sg:city":"Kings Mountain",
    "sg:classifiers":[
        {
            "category":"Freight",
            "type":"Transportation"
        }
    ],
    "sg:phone":"+1 704 730 0021",
    "sg:postcode":"28086",
    "sg:province":"NC",
    "sg:tags":[
        "water",
        "trucking"
    ],
    "sg:website":"www.bentonexpress.com",
    "wof:name":"Benton Express Inc",
    "wof:placetype":"venue"
},
  "geometry": {"coordinates":[-81.33046400000001,35.233127],"type":"Point"}
}