{
  "type": "Feature",
  "properties": {
    "iso:country":"US",
    "sg:address":"100 Hamlin Ct",
    "sg:city":"Jamestown",
    "sg:classifiers":[
        {
            "category":"Building & Trades",
            "subcategory":"Construction",
            "type":"Services"
        }
    ],
    "sg:phone":"+1 336 454 4388",
    "sg:postcode":"27282",
    "sg:province":"NC",
    "sg:tags":[
        "house"
    ],
    "wof:name":"S T C Construction Inc",
    "wof:placetype":"venue"
},
  "geometry": {"coordinates":[-79.936353,36.002702],"type":"Point"}
}