{
  "type": "Feature",
  "properties": {
    "addr:full":"690 Gaynor St Winston Salem NC 27105",
    "addr:housenumber":"690",
    "addr:postcode":"27105",
    "addr:street":"Gaynor St",
    "iso:country":"US",
    "sg:address":"690 Gaynor St",
    "sg:city":"Winston Salem",
    "sg:classifiers":[
        {
            "category":"Freight",
            "type":"Transportation"
        }
    ],
    "sg:phone":"+1 336 767 4900",
    "sg:postcode":"27105",
    "sg:province":"NC",
    "sg:tags":[
        "warehouse",
        "storage"
    ],
    "wof:name":"B & M Storage & Distribution",
    "wof:placetype":"venue"
},
  "geometry": {"coordinates":[-80.23584,36.136376],"type":"Point"}
}