{
  "type": "Feature",
  "properties": {
    "addr:full":"1589 Skeet Club Rd High Point NC 27265",
    "addr:housenumber":"1589",
    "addr:postcode":"27265",
    "addr:street":"Skeet Club Rd",
    "iso:country":"US",
    "sg:address":"1589 Skeet Club Rd",
    "sg:city":"High Point",
    "sg:classifiers":[
        {
            "category":"Shopping",
            "subcategory":"Discount & Variety Stores",
            "type":"Retail Goods"
        }
    ],
    "sg:phone":"+1 336 454 2170",
    "sg:postcode":"27265",
    "sg:province":"NC",
    "wof:name":"Mega Dollar",
    "wof:placetype":"venue"
},
  "geometry": {"coordinates":[-79.971616,36.033304],"type":"Point"}
}