{
  "type": "Feature",
  "properties": {
    "addr:full":"5204 Bedrock Rd Julian NC 27283",
    "addr:housenumber":"5204",
    "addr:postcode":"27283",
    "addr:street":"Bedrock Rd",
    "iso:country":"US",
    "sg:address":"5204 Bedrock Rd",
    "sg:city":"Julian",
    "sg:classifiers":[
        {
            "category":"Professional",
            "subcategory":"Detective & Security Services",
            "type":"Services"
        }
    ],
    "sg:phone":"+1   ",
    "sg:postcode":"27283",
    "sg:province":"NC",
    "sg:tags":[
        "car"
    ],
    "wof:name":"North Carolina Rangers Inc",
    "wof:placetype":"venue"
},
  "geometry": {"coordinates":[-79.669301,35.924714],"type":"Point"}
}