{
  "type": "Feature",
  "properties": {
    "addr:full":"2251 Cloverdale Ave Winston Salem NC 27103",
    "addr:housenumber":"2251",
    "addr:postcode":"27103",
    "addr:street":"Cloverdale Ave",
    "iso:country":"US",
    "sg:address":"2251 Cloverdale Ave",
    "sg:city":"Winston Salem",
    "sg:classifiers":[
        {
            "category":"Restaurant",
            "type":"Food & Drink"
        }
    ],
    "sg:phone":"+1 336 725 4701",
    "sg:postcode":"27103",
    "sg:province":"NC",
    "wof:name":"Cloverdale Kitchen",
    "wof:placetype":"venue"
},
  "geometry": {"coordinates":[-80.27471300000001,36.090238],"type":"Point"}
}