{
  "type": "Feature",
  "properties": {
    "addr:full":"1638 Old Bailey Hwy Nashville NC 27856",
    "addr:housenumber":"1638",
    "addr:postcode":"27856",
    "addr:street":"Old Bailey Hwy",
    "iso:country":"US",
    "sg:address":"1638 Old Bailey Hwy",
    "sg:city":"Nashville",
    "sg:classifiers":[
        {
            "category":"Retail",
            "subcategory":"Repair Shop",
            "type":"Services"
        }
    ],
    "sg:phone":"+1 252 459 4778",
    "sg:postcode":"27856",
    "sg:province":"NC",
    "sg:tags":[
        "upholsterer"
    ],
    "wof:name":"Monroe Sherrod's Shop",
    "wof:placetype":"venue"
},
  "geometry": {"coordinates":[-77.973443,35.954009],"type":"Point"}
}