{
  "type": "Feature",
  "properties": {
    "iso:country":"US",
    "sg:address":"233 Bernice Dr",
    "sg:city":"Stokesdale",
    "sg:classifiers":[
        {
            "category":"Building & Trades",
            "subcategory":"Construction",
            "type":"Services"
        }
    ],
    "sg:phone":"+1 336 644 0570",
    "sg:postcode":"27357",
    "sg:province":"NC",
    "sg:tags":[
        "contractor"
    ],
    "wof:name":"Bradshaw Carpet & Tile",
    "wof:placetype":"venue"
},
  "geometry": {"coordinates":[-79.982747,36.256005],"type":"Point"}
}