{
  "type": "Feature",
  "properties": {
    "iso:country":"US",
    "sg:address":"4604 Secrest Short Cut Rd",
    "sg:city":"Monroe",
    "sg:classifiers":[
        {
            "category":"Organizations",
            "subcategory":"Religious Organization",
            "type":"Services"
        }
    ],
    "sg:phone":"+1 704 225 0456",
    "sg:postcode":"28110",
    "sg:province":"NC",
    "sg:tags":[
        "church"
    ],
    "wof:name":"Morning Star AME Zion Chruch",
    "wof:placetype":"venue"
},
  "geometry": {"coordinates":[-80.585953,35.051228],"type":"Point"}
}