{
  "type": "Feature",
  "properties": {
    "addr:full":"521 W High Ave High Point NC 27260",
    "addr:housenumber":"521",
    "addr:postcode":"27260",
    "addr:street":"W High Ave",
    "iso:country":"US",
    "sg:address":"521 W High Ave",
    "sg:city":"High Point",
    "sg:classifiers":[
        {
            "category":"Freight",
            "type":"Transportation"
        }
    ],
    "sg:phone":"+1 336 841 7060",
    "sg:postcode":"27260",
    "sg:province":"NC",
    "sg:tags":[
        "arrangement"
    ],
    "wof:name":"Ariel Press",
    "wof:placetype":"venue"
},
  "geometry": {"coordinates":[-80.012585,35.953209],"type":"Point"}
}