{
  "type": "Feature",
  "properties": {
    "iso:country":"US",
    "sg:address":"1508 Waxhaw Indian Trail Rd",
    "sg:city":"Indian Trail",
    "sg:classifiers":[
        {
            "category":"Personal",
            "type":"Services"
        }
    ],
    "sg:phone":"+1   ",
    "sg:postcode":"28079",
    "sg:province":"NC",
    "wof:name":"Mr Gene",
    "wof:placetype":"venue"
},
  "geometry": {"coordinates":[-80.676433,35.070048],"type":"Point"}
}