{
  "type": "Feature",
  "properties": {
    "addr:full":"160 Timberbreak Dr Lexington NC 27295",
    "addr:housenumber":"160",
    "addr:postcode":"27295",
    "addr:street":"Timberbreak Dr",
    "iso:country":"US",
    "sg:address":"160 Timberbreak Dr",
    "sg:city":"Lexington",
    "sg:classifiers":[
        {
            "category":"Organizations",
            "subcategory":"Religious Organization",
            "type":"Services"
        }
    ],
    "sg:phone":"+1 336 787 4372",
    "sg:postcode":"27295",
    "sg:province":"NC",
    "sg:tags":[
        "clergy"
    ],
    "wof:name":"Gene Davis",
    "wof:placetype":"venue"
},
  "geometry": {"coordinates":[-80.302772,35.840802],"type":"Point"}
}