{
  "type": "Feature",
  "properties": {
    "iso:country":"US",
    "sg:address":"376 Broken Arrow Trl",
    "sg:city":"Hayesville",
    "sg:classifiers":[
        {
            "category":"Real Estate",
            "subcategory":"Real Estate Agent",
            "type":"Services"
        }
    ],
    "sg:phone":"+1 828 389 0180",
    "sg:postcode":"28904",
    "sg:province":"NC",
    "sg:tags":[
        "inspection"
    ],
    "wof:name":"National Property Inspections",
    "wof:placetype":"venue"
},
  "geometry": {"coordinates":[-83.73733,34.989864],"type":"Point"}
}