{
  "type": "Feature",
  "properties": {
    "iso:country":"US",
    "sg:address":"1200 State Hwy 90",
    "sg:city":"Taylorsville",
    "sg:classifiers":[
        {
            "category":"Restaurant",
            "type":"Food & Drink"
        }
    ],
    "sg:phone":"+1 828 632 8139",
    "sg:postcode":"28681",
    "sg:province":"NC",
    "sg:tags":[
        "caterer"
    ],
    "wof:name":"Alexander's Family Restaurant",
    "wof:placetype":"venue"
},
  "geometry": {"coordinates":[-81.15556100000001,35.917779],"type":"Point"}
}