{
  "type": "Feature",
  "properties": {
    "iso:country":"US",
    "sg:address":"115 Dublin Dr",
    "sg:city":"Winston Salem",
    "sg:classifiers":[
        {
            "category":"Arts & Performance",
            "subcategory":"Theater",
            "type":"Entertainment"
        }
    ],
    "sg:phone":"+1 336 771 0097",
    "sg:postcode":"27107",
    "sg:province":"NC",
    "sg:tags":[
        "group",
        "live",
        "music"
    ],
    "wof:name":"Music Xpress D J & Light Show",
    "wof:placetype":"venue"
},
  "geometry": {"coordinates":[-80.203585,35.997768],"type":"Point"}
}