{
  "type": "Feature",
  "properties": {
    "iso:country":"US",
    "sg:address":"1208 S Tryon St",
    "sg:city":"Charlotte",
    "sg:classifiers":[
        {
            "category":"Professional",
            "subcategory":"Lawyer & Legal Services",
            "type":"Services"
        }
    ],
    "sg:phone":"+1 704 714 6500",
    "sg:postcode":"28203",
    "sg:province":"NC",
    "sg:tags":[
        "attorney"
    ],
    "wof:name":"Workman Law Firm",
    "wof:placetype":"venue"
},
  "geometry": {"coordinates":[-80.853165,35.219024],"type":"Point"}
}