{
  "type": "Feature",
  "properties": {
    "iso:country":"US",
    "sg:address":"912 US Hwy 64",
    "sg:city":"Morganton",
    "sg:classifiers":[
        {
            "category":"Autos & Motor Vehicles",
            "subcategory":"Auto Supplies",
            "type":"Retail Goods"
        }
    ],
    "sg:phone":"+1 828 430 8922",
    "sg:postcode":"28655",
    "sg:province":"NC",
    "sg:tags":[
        "tire"
    ],
    "wof:name":"Custom Alignment & Brake Svc",
    "wof:placetype":"venue"
},
  "geometry": {"coordinates":[-81.685717,35.786236],"type":"Point"}
}