{
  "type": "Feature",
  "properties": {
    "addr:full":"1115 Oakridge Duncan Rd Fuquay Varina NC 27526",
    "addr:housenumber":"1115",
    "addr:postcode":"27526",
    "addr:street":"Oakridge Duncan Rd",
    "iso:country":"US",
    "sg:address":"1115 Oakridge Duncan Rd",
    "sg:city":"Fuquay Varina",
    "sg:classifiers":[
        {
            "category":"Building & Trades",
            "subcategory":"Construction",
            "type":"Services"
        }
    ],
    "sg:phone":"+1 919 557 4377",
    "sg:postcode":"27526",
    "sg:province":"NC",
    "sg:tags":[
        "house"
    ],
    "wof:name":"Denmark Homes Inc",
    "wof:placetype":"venue"
},
  "geometry": {"coordinates":[-78.867329,35.555014],"type":"Point"}
}