{
  "type": "Feature",
  "properties": {
    "iso:country":"US",
    "sg:address":"250 Executive Park Blvd",
    "sg:city":"Winston Salem",
    "sg:classifiers":[
        {
            "category":"Professional",
            "subcategory":"Lawyer & Legal Services",
            "type":"Services"
        }
    ],
    "sg:phone":"+1 336 760 9996",
    "sg:postcode":"27103",
    "sg:province":"NC",
    "sg:tags":[
        "attorney"
    ],
    "wof:name":"Lanier Law Group Pa",
    "wof:placetype":"venue"
},
  "geometry": {"coordinates":[-80.300562,36.082104],"type":"Point"}
}