{
  "type": "Feature",
  "properties": {
    "iso:country":"US",
    "sg:address":"2709 Old Williams Rd",
    "sg:city":"Raleigh",
    "sg:classifiers":[
        {
            "category":"Personal",
            "type":"Services"
        }
    ],
    "sg:phone":"+1   ",
    "sg:postcode":"27610",
    "sg:province":"NC",
    "wof:name":"M & M Handy Man Service",
    "wof:placetype":"venue"
},
  "geometry": {"coordinates":[-78.584693,35.743437],"type":"Point"}
}