{
  "type": "Feature",
  "properties": {
    "addr:full":"6729 Old Mount Holly Rd Charlotte NC 28214",
    "addr:housenumber":"6729",
    "addr:postcode":"28214",
    "addr:street":"Old Mount Holly Rd",
    "iso:country":"US",
    "sg:address":"6729 Old Mount Holly Rd",
    "sg:city":"Charlotte",
    "sg:classifiers":[
        {
            "category":"Organizations",
            "subcategory":"Religious Organization",
            "type":"Services"
        }
    ],
    "sg:phone":"+1 704 399 8254",
    "sg:postcode":"28214",
    "sg:province":"NC",
    "sg:tags":[
        "churches-united",
        "methodist",
        "church"
    ],
    "wof:name":"Homestead United Methodist Church",
    "wof:placetype":"venue"
},
  "geometry": {"coordinates":[-80.918359,35.282026],"type":"Point"}
}