{
  "type": "Feature",
  "properties": {
    "iso:country":"US",
    "sg:address":"2533 State Hwy 62",
    "sg:city":"Burlington",
    "sg:classifiers":[
        {
            "category":"Food & Beverages",
            "subcategory":"Groceries & Convenience Stores",
            "type":"Retail Goods"
        }
    ],
    "sg:phone":"+1 336 226 3845",
    "sg:postcode":"27217",
    "sg:province":"NC",
    "wof:name":"B & B Of Burlington Inc",
    "wof:placetype":"venue"
},
  "geometry": {"coordinates":[-79.42461900000001,36.138541],"type":"Point"}
}