{
  "type": "Feature",
  "properties": {
    "addr:full":"4342 Castle Hayne Rd Castle Hayne NC 28429",
    "addr:housenumber":"4342",
    "addr:postcode":"28429",
    "addr:street":"Castle Hayne Rd",
    "iso:country":"US",
    "sg:address":"4342 Castle Hayne Rd",
    "sg:city":"Castle Hayne",
    "sg:classifiers":[
        {
            "category":"Autos & Motor Vehicles",
            "subcategory":"Automobile Sales",
            "type":"Retail Goods"
        }
    ],
    "sg:phone":"+1 910 675 8458",
    "sg:postcode":"28429",
    "sg:province":"NC",
    "sg:tags":[
        "car",
        "dealer"
    ],
    "wof:name":"R C Performance",
    "wof:placetype":"venue"
},
  "geometry": {"coordinates":[-77.915322,34.331057],"type":"Point"}
}