{
  "type": "Feature",
  "properties": {
    "addr:full":"6004 Oleander Dr Wilmington NC 28403",
    "addr:housenumber":"6004",
    "addr:postcode":"28403",
    "addr:street":"Oleander Dr",
    "iso:country":"US",
    "sg:address":"6004 Oleander Dr",
    "sg:city":"Wilmington",
    "sg:classifiers":[
        {
            "category":"Retail",
            "subcategory":"Laundry & Dry Cleaning",
            "type":"Services"
        }
    ],
    "sg:phone":"+1 910 793 8200",
    "sg:postcode":"28403",
    "sg:province":"NC",
    "sg:tags":[
        "on",
        "plant",
        "carpet",
        "rug",
        "lo"
    ],
    "wof:name":"Oriental Rug Crpt Clg Spcalist",
    "wof:placetype":"venue"
},
  "geometry": {"coordinates":[-77.839264,34.209654],"type":"Point"}
}