{
  "type": "Feature",
  "properties": {
    "iso:country":"US",
    "sg:address":"7509 Hambright Rd",
    "sg:city":"Huntersville",
    "sg:classifiers":[
        {
            "category":"Building & Trades",
            "subcategory":"Plumbing",
            "type":"Services"
        }
    ],
    "sg:phone":"+1 704 875 2425",
    "sg:postcode":"28078",
    "sg:province":"NC",
    "sg:tags":[
        "septic"
    ],
    "wof:name":"C L Morrison Septic Tank Svc",
    "wof:placetype":"venue"
},
  "geometry": {"coordinates":[-80.90190200000001,35.380071],"type":"Point"}
}