{
  "type": "Feature",
  "properties": {
    "addr:full":"2591 Rabbit Hop Rd Spruce Pine NC 28777",
    "addr:housenumber":"2591",
    "addr:postcode":"28777",
    "addr:street":"Rabbit Hop Rd",
    "iso:country":"US",
    "sg:address":"2591 Rabbit Hop Rd",
    "sg:city":"Spruce Pine",
    "sg:classifiers":[
        {
            "category":"Professional",
            "subcategory":"Business Services",
            "type":"Services"
        }
    ],
    "sg:phone":"+1 828 765 1344",
    "sg:postcode":"28777",
    "sg:province":"NC",
    "sg:tags":[
        "interior",
        "consultant",
        "design",
        "decorator"
    ],
    "wof:name":"L & S Designs",
    "wof:placetype":"venue"
},
  "geometry": {"coordinates":[-82.14345299999999,35.929099],"type":"Point"}
}