{
  "type": "Feature",
  "properties": {
    "iso:country":"US",
    "sg:address":"10310 Couloak Dr",
    "sg:city":"Charlotte",
    "sg:classifiers":[
        {
            "category":"Health Services",
            "subcategory":"Podiatrist",
            "type":"Services"
        }
    ],
    "sg:phone":"+1 704 971 4000",
    "sg:postcode":"28216",
    "sg:province":"NC",
    "wof:name":"Carolina Foot & Ankle",
    "wof:placetype":"venue"
},
  "geometry": {"coordinates":[-80.948403,35.324916],"type":"Point"}
}