{
  "type": "Feature",
  "properties": {
    "addr:full":"1314 Earl Rd Shelby NC 28152",
    "addr:housenumber":"1314",
    "addr:postcode":"28152",
    "addr:street":"Earl Rd",
    "iso:country":"US",
    "sg:address":"1314 Earl Rd",
    "sg:city":"Shelby",
    "sg:classifiers":[
        {
            "category":"Personal",
            "subcategory":"Beauty Salon",
            "type":"Services"
        }
    ],
    "sg:phone":"+1   ",
    "sg:postcode":"28152",
    "sg:province":"NC",
    "sg:tags":[
        "shop"
    ],
    "wof:name":"Impressions Styling Salon",
    "wof:placetype":"venue"
},
  "geometry": {"coordinates":[-81.507138,35.255474],"type":"Point"}
}