{
  "type": "Feature",
  "properties": {
    "iso:country":"US",
    "sg:address":"4475 Technology Dr",
    "sg:city":"Wilson",
    "sg:classifiers":[
        {
            "category":"Manufacturing",
            "subcategory":"Metals",
            "type":"Manufacturing & Wholesale Goods"
        }
    ],
    "sg:phone":"+1 252 243 2383",
    "sg:postcode":"27896",
    "sg:province":"NC",
    "sg:tags":[
        "fabricator",
        "sheet"
    ],
    "wof:name":"S K Bowling Co",
    "wof:placetype":"venue"
},
  "geometry": {"coordinates":[-77.96478399999999,35.764818],"type":"Point"}
}