{
  "type": "Feature",
  "properties": {
    "iso:country":"US",
    "sg:address":"208 Herman St",
    "sg:city":"Spencer",
    "sg:classifiers":[
        {
            "category":"Banks & Credit Unions",
            "subcategory":"Financial Services",
            "type":"Services"
        }
    ],
    "sg:phone":"+1 704 639 0826",
    "sg:postcode":"28159",
    "sg:province":"NC",
    "sg:tags":[
        "company",
        "holding"
    ],
    "wof:name":"Cap Holdings LLC",
    "wof:placetype":"venue"
},
  "geometry": {"coordinates":[-80.420051,35.699203],"type":"Point"}
}