{
  "type": "Feature",
  "properties": {
    "iso:country":"US",
    "sg:address":"816 Old Spartanburg Rd",
    "sg:city":"Hendersonville",
    "sg:classifiers":[
        {
            "category":"Retail",
            "subcategory":"Auto Repair",
            "type":"Services"
        }
    ],
    "sg:phone":"+1 828 693 4541",
    "sg:postcode":"28792",
    "sg:province":"NC",
    "sg:tags":[
        "transmission"
    ],
    "wof:name":"Auto Barn",
    "wof:placetype":"venue"
},
  "geometry": {"coordinates":[-82.448814,35.306914],"type":"Point"}
}