{
  "type": "Feature",
  "properties": {
    "addr:full":"709 Carnegie Pl Greensboro NC 27409",
    "addr:housenumber":"709",
    "addr:postcode":"27409",
    "addr:street":"Carnegie Pl",
    "iso:country":"US",
    "sg:address":"709 Carnegie Pl",
    "sg:city":"Greensboro",
    "sg:classifiers":[
        {
            "category":"Shopping",
            "subcategory":"Bicycles & Sporting Goods",
            "type":"Retail Goods"
        }
    ],
    "sg:phone":"+1 336 852 2335",
    "sg:postcode":"27409",
    "sg:province":"NC",
    "sg:tags":[
        "apparel",
        "shoes"
    ],
    "wof:name":"Graham Sporting Gds Greensboro",
    "wof:placetype":"venue"
},
  "geometry": {"coordinates":[-79.881854,36.060289],"type":"Point"}
}