{
  "type": "Feature",
  "properties": {
    "addr:full":"935 Blowing Rock Blvd Lenoir NC 28645",
    "addr:housenumber":"935",
    "addr:postcode":"28645",
    "addr:street":"Blowing Rock Blvd",
    "iso:country":"US",
    "sg:address":"935 Blowing Rock Blvd",
    "sg:city":"Lenoir",
    "sg:classifiers":[
        {
            "category":"Home & Garden",
            "subcategory":"Building Materials",
            "type":"Retail Goods"
        }
    ],
    "sg:phone":"+1 828 758 0056",
    "sg:postcode":"28645",
    "sg:province":"NC",
    "sg:tags":[
        "center"
    ],
    "wof:name":"Lowe's",
    "wof:placetype":"venue"
},
  "geometry": {"coordinates":[-81.527078,35.928285],"type":"Point"}
}