{
  "type": "Feature",
  "properties": {
    "addr:full":"245 S French Broad Ave Asheville NC 28801",
    "addr:housenumber":"245",
    "addr:postcode":"28801",
    "addr:street":"S French Broad Ave",
    "iso:country":"US",
    "sg:address":"245 S French Broad Ave",
    "sg:city":"Asheville",
    "sg:classifiers":[
        {
            "category":"Health Services",
            "subcategory":"Health Practitioner",
            "type":"Services"
        }
    ],
    "sg:phone":"+1   ",
    "sg:postcode":"28801",
    "sg:province":"NC",
    "wof:name":"R Jey Hiott PHD",
    "wof:placetype":"venue"
},
  "geometry": {"coordinates":[-82.559364,35.587054],"type":"Point"}
}