{
  "type": "Feature",
  "properties": {
    "addr:full":"301 N Main St Troy NC 27371",
    "addr:housenumber":"301",
    "addr:postcode":"27371",
    "addr:street":"N Main St",
    "iso:country":"US",
    "sg:address":"301 N Main St",
    "sg:city":"Troy",
    "sg:classifiers":[
        {
            "category":"Professional",
            "subcategory":"Computer Services",
            "type":"Services"
        }
    ],
    "sg:phone":"+1 910 572 3383",
    "sg:postcode":"27371",
    "sg:province":"NC",
    "sg:tags":[
        "prepackaged",
        "software",
        "internet"
    ],
    "wof:name":"Montgomery On Line",
    "wof:placetype":"venue"
},
  "geometry": {"coordinates":[-79.89464099999999,35.362126],"type":"Point"}
}