{
  "type": "Feature",
  "properties": {
    "addr:full":"364 Clive Jacobs Rd Clinton NC 28328",
    "addr:housenumber":"364",
    "addr:postcode":"28328",
    "addr:street":"Clive Jacobs Rd",
    "iso:country":"US",
    "sg:address":"364 Clive Jacobs Rd",
    "sg:city":"Clinton",
    "sg:classifiers":[
        {
            "category":"Building & Trades",
            "subcategory":"Construction",
            "type":"Services"
        }
    ],
    "sg:phone":"+1 910 592 6935",
    "sg:postcode":"28328",
    "sg:province":"NC",
    "sg:tags":[
        "house"
    ],
    "wof:name":"Scicro P Flemming",
    "wof:placetype":"venue"
},
  "geometry": {"coordinates":[-78.284221,34.989669],"type":"Point"}
}