{
  "type": "Feature",
  "properties": {
    "addr:full":"103 E Main St Glen Alpine NC 28628",
    "addr:housenumber":"103",
    "addr:postcode":"28628",
    "addr:street":"E Main St Glen",
    "iso:country":"US",
    "sg:address":"103 E Main St",
    "sg:city":"Glen Alpine",
    "sg:classifiers":[
        {
            "category":"Personal",
            "subcategory":"Beauty Salon",
            "type":"Services"
        }
    ],
    "sg:phone":"+1 828 584 7021",
    "sg:postcode":"28628",
    "sg:province":"NC",
    "wof:name":"Mane Attraction Salon",
    "wof:placetype":"venue"
},
  "geometry": {"coordinates":[-81.77628199999999,35.728528],"type":"Point"}
}