{
  "type": "Feature",
  "properties": {
    "addr:full":"2210 Ione St Greenville NC 27834",
    "addr:housenumber":"2210",
    "addr:postcode":"27834",
    "addr:street":"Ione St",
    "iso:country":"US",
    "sg:address":"2210 Ione St",
    "sg:city":"Greenville",
    "sg:classifiers":[
        {
            "category":"Retail",
            "subcategory":"Repair Shop",
            "type":"Services"
        }
    ],
    "sg:phone":"+1 252 758 0600",
    "sg:postcode":"27834",
    "sg:province":"NC",
    "sg:tags":[
        "equipment",
        "welding"
    ],
    "wof:name":"Alex's Welding Svc",
    "wof:placetype":"venue"
},
  "geometry": {"coordinates":[-77.39370599999999,35.597939],"type":"Point"}
}