{
  "type": "Feature",
  "properties": {
    "iso:country":"US",
    "sg:address":"7701 Six Forks Rd",
    "sg:city":"Raleigh",
    "sg:classifiers":[
        {
            "category":"Real Estate",
            "subcategory":"Real Estate Agent",
            "type":"Services"
        }
    ],
    "sg:phone":"+1 919 882 5655",
    "sg:postcode":"27615",
    "sg:province":"NC",
    "wof:name":"Ruby Henderson",
    "wof:placetype":"venue"
},
  "geometry": {"coordinates":[-78.64679599999999,35.886711],"type":"Point"}
}