{
  "type": "Feature",
  "properties": {
    "addr:full":"400 2nd Ave NW Hickory NC 28601",
    "addr:housenumber":"400",
    "addr:postcode":"28601",
    "addr:street":"2Nd Ave Nw",
    "iso:country":"US",
    "sg:address":"400 2nd Ave NW",
    "sg:city":"Hickory",
    "sg:classifiers":[
        {
            "category":"Building & Trades",
            "subcategory":"Construction",
            "type":"Services"
        }
    ],
    "sg:phone":"+1 800 222 5607",
    "sg:postcode":"28601",
    "sg:province":"NC",
    "sg:tags":[
        "water",
        "system",
        "supply"
    ],
    "wof:name":"Surry Water Company Inc",
    "wof:placetype":"venue"
},
  "geometry": {"coordinates":[-81.34598099999999,35.73448],"type":"Point"}
}