{
  "type": "Feature",
  "properties": {
    "iso:country":"US",
    "sg:address":"141 W Main St",
    "sg:city":"Garner",
    "sg:classifiers":[
        {
            "category":"Personal",
            "subcategory":"Barber",
            "type":"Services"
        }
    ],
    "sg:phone":"+1 919 661 4580",
    "sg:postcode":"27529",
    "sg:province":"NC",
    "sg:tags":[
        "shop"
    ],
    "wof:name":"Roland's Barber Shop",
    "wof:placetype":"venue"
},
  "geometry": {"coordinates":[-78.60603999999999,35.70702],"type":"Point"}
}