{
  "type": "Feature",
  "properties": {
    "addr:full":"450 Addor Rd Aberdeen NC 28315",
    "addr:housenumber":"450",
    "addr:postcode":"28315",
    "addr:street":"Addor Rd",
    "iso:country":"US",
    "sg:address":"450 Addor Rd",
    "sg:city":"Aberdeen",
    "sg:classifiers":[
        {
            "category":"Retail",
            "subcategory":"Veterinary Services",
            "type":"Services"
        }
    ],
    "sg:phone":"+1 910 281 4845",
    "sg:postcode":"28315",
    "sg:province":"NC",
    "sg:tags":[
        "veterinarian"
    ],
    "sg:website":"www.amymiles.com",
    "wof:name":"Hassinger Farms",
    "wof:placetype":"venue"
},
  "geometry": {"coordinates":[-79.443668,35.048975],"type":"Point"}
}