{
  "type": "Feature",
  "properties": {
    "iso:country":"US",
    "sg:address":"4537 Ridge Rd",
    "sg:city":"Charlotte",
    "sg:classifiers":[
        {
            "category":"Building & Trades",
            "subcategory":"Electrical",
            "type":"Services"
        }
    ],
    "sg:phone":"+1 704 948 9566",
    "sg:postcode":"28269",
    "sg:province":"NC",
    "sg:tags":[
        "electrical",
        "contractor"
    ],
    "wof:name":"Rs Electrical Contractors Inc",
    "wof:placetype":"venue"
},
  "geometry": {"coordinates":[-80.774297,35.37431],"type":"Point"}
}