{
  "type": "Feature",
  "properties": {
    "addr:full":"3675 Marine Dr Greenville NC 27834",
    "addr:housenumber":"3675",
    "addr:postcode":"27834",
    "addr:street":"Marine Dr",
    "iso:country":"US",
    "sg:address":"3675 Marine Dr",
    "sg:city":"Greenville",
    "sg:classifiers":[
        {
            "category":"Professional",
            "subcategory":"Business Services",
            "type":"Services"
        }
    ],
    "sg:phone":"+1 252 756 3796",
    "sg:postcode":"27834",
    "sg:province":"NC",
    "sg:tags":[
        "drafting"
    ],
    "wof:name":"CADPRO Drafting Svc",
    "wof:placetype":"venue"
},
  "geometry": {"coordinates":[-77.326447,35.62344],"type":"Point"}
}