{
  "type": "Feature",
  "properties": {
    "addr:full":"218 Cedar Lodge Rd Thomasville NC 27360",
    "addr:housenumber":"218",
    "addr:postcode":"27360",
    "addr:street":"Cedar Lodge Rd",
    "iso:country":"US",
    "sg:address":"218 Cedar Lodge Rd",
    "sg:city":"Thomasville",
    "sg:classifiers":[
        {
            "category":"Wholesale",
            "subcategory":"Farm Supplies",
            "type":"Manufacturing & Wholesale Goods"
        }
    ],
    "sg:phone":"+1 336 476 5562",
    "sg:postcode":"27360",
    "sg:province":"NC",
    "sg:tags":[
        "feed"
    ],
    "wof:name":"Petsrmore",
    "wof:placetype":"venue"
},
  "geometry": {"coordinates":[-80.07839199999999,35.850424],"type":"Point"}
}