{
  "type": "Feature",
  "properties": {
    "addr:full":"3110 Edwards Mill Rd Ste 110 Raleigh NC 27612",
    "addr:housenumber":"3110",
    "addr:postcode":"27612",
    "addr:street":"Edwards Mill Rd Ste 110",
    "iso:country":"US",
    "sg:address":"3110 Edwards Mill Rd Ste 110",
    "sg:city":"Raleigh",
    "sg:classifiers":[
        {
            "category":"Utilities",
            "type":"Services"
        }
    ],
    "sg:phone":"+1 919 789 2300",
    "sg:postcode":"27612",
    "sg:province":"NC",
    "sg:tags":[
        "provider",
        "internet"
    ],
    "sg:website":"www.clearwire.com",
    "wof:name":"Clearwire Llc",
    "wof:placetype":"venue"
},
  "geometry": {"coordinates":[-78.706767,35.823867],"type":"Point"}
}