{
  "type": "Feature",
  "properties": {
    "addr:full":"505 E Main St Cherryville NC 28021",
    "addr:housenumber":"505",
    "addr:postcode":"28021",
    "addr:street":"E Main St",
    "iso:country":"US",
    "sg:address":"505 E Main St",
    "sg:city":"Cherryville",
    "sg:classifiers":[
        {
            "category":"Professional",
            "subcategory":"Accounting & Tax Preparation",
            "type":"Services"
        }
    ],
    "sg:phone":"+1 704 435 9679",
    "sg:postcode":"28021",
    "sg:province":"NC",
    "sg:tags":[
        "return",
        "filing"
    ],
    "wof:name":"York Tax Svc",
    "wof:placetype":"venue"
},
  "geometry": {"coordinates":[-81.37407399999999,35.38071],"type":"Point"}
}