{
  "type": "Feature",
  "properties": {
    "iso:country":"US",
    "sg:address":"2930 Circle C Rd",
    "sg:city":"Lenoir",
    "sg:classifiers":[
        {
            "category":"Retail",
            "subcategory":"Repair Shop",
            "type":"Services"
        }
    ],
    "sg:phone":"+1 828 754 5152",
    "sg:postcode":"28645",
    "sg:province":"NC",
    "sg:tags":[
        "equipment",
        "radio"
    ],
    "wof:name":"C and C Leasing",
    "wof:placetype":"venue"
},
  "geometry": {"coordinates":[-81.58971200000001,35.852609],"type":"Point"}
}