{
  "type": "Feature",
  "properties": {
    "iso:country":"US",
    "sg:address":"946 W Andrews Ave",
    "sg:city":"Henderson",
    "sg:classifiers":[
        {
            "category":"Sports & Exercise",
            "subcategory":"Gym",
            "type":"Entertainment"
        }
    ],
    "sg:phone":"+1 252 431 1445",
    "sg:postcode":"27536",
    "sg:province":"NC",
    "sg:tags":[
        "club",
        "health",
        "studio",
        "gymnasium"
    ],
    "wof:name":"Curves For Women",
    "wof:placetype":"venue"
},
  "geometry": {"coordinates":[-78.41012600000001,36.338878],"type":"Point"}
}