{
  "type": "Feature",
  "properties": {
    "addr:full":"120 Woodline Dr Troy NC 27371",
    "addr:housenumber":"120",
    "addr:postcode":"27371",
    "addr:street":"Woodline Dr",
    "iso:country":"US",
    "sg:address":"120 Woodline Dr",
    "sg:city":"Troy",
    "sg:classifiers":[
        {
            "category":"Retail",
            "subcategory":"Portrait Studio",
            "type":"Services"
        }
    ],
    "sg:phone":"+1   ",
    "sg:postcode":"27371",
    "sg:province":"NC",
    "sg:tags":[
        "photo"
    ],
    "wof:name":"Creative Photography",
    "wof:placetype":"venue"
},
  "geometry": {"coordinates":[-80.047185,35.363603],"type":"Point"}
}