{
  "type": "Feature",
  "properties": {
    "iso:country":"US",
    "sg:address":"609 Middle Bridge Rd",
    "sg:city":"Wake Forest",
    "sg:classifiers":[
        {
            "category":"Professional",
            "type":"Services"
        }
    ],
    "sg:phone":"+1   ",
    "sg:postcode":"27587",
    "sg:province":"NC",
    "wof:name":"Carolina Merchant Services",
    "wof:placetype":"venue"
},
  "geometry": {"coordinates":[-78.50408299999999,35.969666],"type":"Point"}
}