{
  "type": "Feature",
  "properties": {
    "addr:full":"5821 Fairview Rd Charlotte NC 28209",
    "addr:housenumber":"5821",
    "addr:postcode":"28209",
    "addr:street":"Fairview Rd",
    "iso:country":"US",
    "sg:address":"5821 Fairview Rd",
    "sg:city":"Charlotte",
    "sg:classifiers":[
        {
            "category":"Professional",
            "subcategory":"Lawyer & Legal Services",
            "type":"Services"
        }
    ],
    "sg:phone":"+1 704 643 0290",
    "sg:postcode":"28209",
    "sg:province":"NC",
    "sg:tags":[
        "attorney"
    ],
    "sg:website":"www.brockandscott.com",
    "wof:name":"BSI Executive Real Estate",
    "wof:placetype":"venue"
},
  "geometry": {"coordinates":[-80.841959,35.151747],"type":"Point"}
}