{
  "type": "Feature",
  "properties": {
    "iso:country":"US",
    "sg:address":"608 Forest Park Rd",
    "sg:city":"Elizabeth City",
    "sg:classifiers":[
        {
            "category":"Insurance",
            "subcategory":"Insurance Agent",
            "type":"Services"
        }
    ],
    "sg:phone":"+1 252 335 1566",
    "sg:postcode":"27909",
    "sg:province":"NC",
    "wof:name":"Albemarle Adjusters",
    "wof:placetype":"venue"
},
  "geometry": {"coordinates":[-76.259743,36.303681],"type":"Point"}
}