{
  "type": "Feature",
  "properties": {
    "iso:country":"US",
    "sg:address":"100 Europa Dr",
    "sg:city":"Chapel Hill",
    "sg:classifiers":[
        {
            "category":"Banks & Credit Unions",
            "subcategory":"Investment Brokerage",
            "type":"Services"
        }
    ],
    "sg:phone":"+1 919 942 8499",
    "sg:postcode":"27517",
    "sg:province":"NC",
    "sg:tags":[
        "advisory",
        "financial"
    ],
    "wof:name":"Community First Financial",
    "wof:placetype":"venue"
},
  "geometry": {"coordinates":[-79.01812099999999,35.940487],"type":"Point"}
}