{
  "type": "Feature",
  "properties": {
    "addr:full":"42 Deep River Rd Sanford NC 27330",
    "addr:housenumber":"42",
    "addr:postcode":"27330",
    "addr:street":"Deep River Rd",
    "iso:country":"US",
    "sg:address":"42 Deep River Rd",
    "sg:city":"Sanford",
    "sg:classifiers":[
        {
            "category":"Organizations",
            "subcategory":"Membership Organization",
            "type":"Services"
        }
    ],
    "sg:phone":"+1 919 774 9433",
    "sg:postcode":"27330",
    "sg:province":"NC",
    "sg:tags":[
        "animal"
    ],
    "wof:name":"Carolina Anmal Rescue Adaption",
    "wof:placetype":"venue"
},
  "geometry": {"coordinates":[-79.19117199999999,35.552741],"type":"Point"}
}