{
  "type": "Feature",
  "properties": {
    "addr:full":"334 Union Cemetery Rd SW Concord NC 28027",
    "addr:housenumber":"334",
    "addr:postcode":"28027",
    "addr:street":"Union Cemetery Rd Sw",
    "iso:country":"US",
    "sg:address":"334 Union Cemetery Rd SW",
    "sg:city":"Concord",
    "sg:classifiers":[
        {
            "category":"Personal",
            "subcategory":"Barber",
            "type":"Services"
        }
    ],
    "sg:phone":"+1   ",
    "sg:postcode":"28027",
    "sg:province":"NC",
    "sg:tags":[
        "shop"
    ],
    "wof:name":"Fleetwood Barber Shop",
    "wof:placetype":"venue"
},
  "geometry": {"coordinates":[-80.605885,35.387245],"type":"Point"}
}