{
  "type": "Feature",
  "properties": {
    "addr:full":"385 W Pennsylvania Ave Southern Pines NC 28387",
    "addr:housenumber":"385",
    "addr:postcode":"28387",
    "addr:street":"W Pennsylvania Ave",
    "iso:country":"US",
    "sg:address":"385 W Pennsylvania Ave",
    "sg:city":"Southern Pines",
    "sg:classifiers":[
        {
            "category":"Banks & Credit Unions",
            "subcategory":"Bank",
            "type":"Services"
        }
    ],
    "sg:phone":"+1 910 692 1199",
    "sg:postcode":"28387",
    "sg:province":"NC",
    "wof:name":"First Union",
    "wof:placetype":"venue"
},
  "geometry": {"coordinates":[-79.394263,35.176282],"type":"Point"}
}