{
  "type": "Feature",
  "properties": {
    "addr:full":"2246 Murray Town Rd Burgaw NC 28425",
    "addr:housenumber":"2246",
    "addr:postcode":"28425",
    "addr:street":"Murray Town Rd",
    "iso:country":"US",
    "sg:address":"2246 Murray Town Rd",
    "sg:city":"Burgaw",
    "sg:classifiers":[
        {
            "category":"Farming",
            "subcategory":"Farm",
            "type":"Manufacturing & Wholesale Goods"
        }
    ],
    "sg:phone":"+1 910 259 3731",
    "sg:postcode":"28425",
    "sg:province":"NC",
    "sg:tags":[
        "crop",
        "general"
    ],
    "wof:name":"Daniel W Rivenbark",
    "wof:placetype":"venue"
},
  "geometry": {"coordinates":[-77.889886,34.622515],"type":"Point"}
}