{
  "type": "Feature",
  "properties": {
    "addr:full":"439 Cedarland Dr Thomasville NC 27360",
    "addr:housenumber":"439",
    "addr:postcode":"27360",
    "addr:street":"Cedarland Dr",
    "iso:country":"US",
    "sg:address":"439 Cedarland Dr",
    "sg:city":"Thomasville",
    "sg:classifiers":[
        {
            "category":"Manufacturing",
            "subcategory":"Printing",
            "type":"Manufacturing & Wholesale Goods"
        }
    ],
    "sg:phone":"+1 336 476 7710",
    "sg:postcode":"27360",
    "sg:province":"NC",
    "sg:tags":[
        "screen",
        "commercial"
    ],
    "wof:name":"Design Illusions Inc",
    "wof:placetype":"venue"
},
  "geometry": {"coordinates":[-80.112719,35.841761],"type":"Point"}
}