{
  "type": "Feature",
  "properties": {
    "addr:full":"124 S Powell St Forest City NC 28043",
    "addr:housenumber":"124",
    "addr:postcode":"28043",
    "addr:street":"S Powell St",
    "iso:country":"US",
    "sg:address":"124 S Powell St",
    "sg:city":"Forest City",
    "sg:classifiers":[
        {
            "category":"Insurance",
            "subcategory":"Hazard Insurance",
            "type":"Services"
        }
    ],
    "sg:phone":"+1 828 245 4731",
    "sg:postcode":"28043",
    "sg:province":"NC",
    "sg:tags":[
        "casualty"
    ],
    "wof:name":"Bostic Insurance & Tax Svc",
    "wof:placetype":"venue"
},
  "geometry": {"coordinates":[-81.86357,35.33283],"type":"Point"}
}