{
  "type": "Feature",
  "properties": {
    "iso:country":"US",
    "sg:address":"2119 Sallies Ln",
    "sg:city":"Winston Salem",
    "sg:classifiers":[
        {
            "category":"Manufacturing",
            "subcategory":"Tools & Machinery",
            "type":"Manufacturing & Wholesale Goods"
        }
    ],
    "sg:phone":"+1 336 924 9396",
    "sg:postcode":"27106",
    "sg:province":"NC",
    "sg:tags":[
        "electric",
        "mfg"
    ],
    "wof:name":"Bos & Associates Inc",
    "wof:placetype":"venue"
},
  "geometry": {"coordinates":[-80.307473,36.181585],"type":"Point"}
}