{
  "type": "Feature",
  "properties": {
    "addr:full":"3910 Pamela Dr Durham NC 27704",
    "addr:housenumber":"3910",
    "addr:postcode":"27704",
    "addr:street":"Pamela Dr",
    "iso:country":"US",
    "sg:address":"3910 Pamela Dr",
    "sg:city":"Durham",
    "sg:classifiers":[
        {
            "category":"Professional",
            "type":"Services"
        }
    ],
    "sg:phone":"+1 919 682 2595",
    "sg:postcode":"27704",
    "sg:province":"NC",
    "wof:name":"Ruritan National Corp",
    "wof:placetype":"venue"
},
  "geometry": {"coordinates":[-78.77937300000001,36.044174],"type":"Point"}
}