{
  "type": "Feature",
  "properties": {
    "iso:country":"US",
    "sg:address":"106 Lilly St",
    "sg:city":"Dunn",
    "sg:classifiers":[
        {
            "category":"Building & Trades",
            "subcategory":"Construction",
            "type":"Services"
        }
    ],
    "sg:phone":"+1 910 892 0470",
    "sg:postcode":"28334",
    "sg:province":"NC",
    "sg:tags":[
        "resurfacing",
        "laying",
        "refinishing",
        "floor"
    ],
    "wof:name":"Floor Talk",
    "wof:placetype":"venue"
},
  "geometry": {"coordinates":[-78.609132,35.286501],"type":"Point"}
}