{
  "type": "Feature",
  "properties": {
    "iso:country":"US",
    "sg:address":"2623 Boone Trl",
    "sg:city":"North Wilkesboro",
    "sg:classifiers":[
        {
            "category":"Retail",
            "subcategory":"Repair Shop",
            "type":"Services"
        },
        {
            "category":"Shopping",
            "subcategory":"Bicycles & Sporting Goods",
            "type":"Retail Goods"
        }
    ],
    "sg:phone":"+1 336 667 8785",
    "sg:postcode":"28659",
    "sg:province":"NC",
    "sg:tags":[
        "small",
        "gunsmith",
        "arms",
        "gun",
        "mfg"
    ],
    "wof:name":"Baity's Custom Gunworks",
    "wof:placetype":"venue"
},
  "geometry": {"coordinates":[-81.196963,36.176815],"type":"Point"}
}