{
  "type": "Feature",
  "properties": {
    "addr:full":"4040 Ed Dr Raleigh NC 27612",
    "addr:postcode":"4040;27612",
    "addr:street":"Ed Dr",
    "iso:country":"US",
    "sg:address":"4040 Ed Dr",
    "sg:city":"Raleigh",
    "sg:classifiers":[
        {
            "category":"Retail",
            "subcategory":"Laundry & Dry Cleaning",
            "type":"Services"
        }
    ],
    "sg:phone":"+1 919 571 9559",
    "sg:postcode":"27612",
    "sg:province":"NC",
    "wof:name":"Olde Raleigh Cleaners",
    "wof:placetype":"venue"
},
  "geometry": {"coordinates":[-78.70356099999999,35.8248],"type":"Point"}
}