{
  "type": "Feature",
  "properties": {
    "addr:full":"302 E Main St Havelock NC 28532",
    "addr:housenumber":"302",
    "addr:postcode":"28532",
    "addr:street":"E Main St",
    "iso:country":"US",
    "sg:address":"302 E Main St",
    "sg:city":"Havelock",
    "sg:classifiers":[
        {
            "category":"Personal",
            "type":"Services"
        }
    ],
    "sg:phone":"+1 252 447 1100",
    "sg:postcode":"28532",
    "sg:province":"NC",
    "sg:tags":[
        "therapist",
        "massage"
    ],
    "wof:name":"Massage Solutions",
    "wof:placetype":"venue"
},
  "geometry": {"coordinates":[-76.90254299999999,34.873267],"type":"Point"}
}