{
  "type": "Feature",
  "properties": {
    "iso:country":"US",
    "sg:address":"1933 Tippah Ave",
    "sg:city":"Charlotte",
    "sg:classifiers":[
        {
            "category":"Building & Trades",
            "subcategory":"Landscaping Services",
            "type":"Services"
        }
    ],
    "sg:phone":"+1 704 577 4306",
    "sg:postcode":"28205",
    "sg:province":"NC",
    "sg:tags":[
        "designer",
        "landscape"
    ],
    "wof:name":"All Natural Streams Landscape",
    "wof:placetype":"venue"
},
  "geometry": {"coordinates":[-80.805437,35.22761],"type":"Point"}
}