{
  "type": "Feature",
  "properties": {
    "addr:full":"315 S Westgate Dr Greensboro NC 27407",
    "addr:housenumber":"315",
    "addr:postcode":"27407",
    "addr:street":"S Westgate Dr",
    "iso:country":"US",
    "sg:address":"315 S Westgate Dr",
    "sg:city":"Greensboro",
    "sg:classifiers":[
        {
            "category":"Wholesale",
            "subcategory":"Medical Equipment & Supplies",
            "type":"Manufacturing & Wholesale Goods"
        }
    ],
    "sg:phone":"+1 336 808 1260",
    "sg:postcode":"27407",
    "sg:province":"NC",
    "sg:tags":[
        "physician",
        "surgeon"
    ],
    "wof:name":"Carolina Mobility & Seating",
    "wof:placetype":"venue"
},
  "geometry": {"coordinates":[-79.85947899999999,36.064793],"type":"Point"}
}