{
  "type": "Feature",
  "properties": {
    "addr:full":"12 Tsataga Ct Brevard NC 28712",
    "addr:housenumber":"12",
    "addr:postcode":"28712",
    "addr:street":"Tsataga Ct",
    "iso:country":"US",
    "sg:address":"12 Tsataga Ct",
    "sg:city":"Brevard",
    "sg:classifiers":[
        {
            "category":"Professional",
            "subcategory":"Management & Consulting",
            "type":"Services"
        }
    ],
    "sg:phone":"+1   ",
    "sg:postcode":"28712",
    "sg:province":"NC",
    "wof:name":"Mk Taylor LLC",
    "wof:placetype":"venue"
},
  "geometry": {"coordinates":[-82.711527,35.141522],"type":"Point"}
}