{
  "type": "Feature",
  "properties": {
    "addr:full":"146 Dailey Rd Hayesville NC 28904",
    "addr:housenumber":"146",
    "addr:postcode":"28904",
    "addr:street":"Dailey Rd",
    "iso:country":"US",
    "sg:address":"146 Dailey Rd",
    "sg:city":"Hayesville",
    "sg:classifiers":[
        {
            "category":"Building & Trades",
            "subcategory":"Construction",
            "type":"Services"
        }
    ],
    "sg:phone":"+1 828 389 6171",
    "sg:postcode":"28904",
    "sg:province":"NC",
    "sg:tags":[
        "house"
    ],
    "wof:name":"Ledford Construction",
    "wof:placetype":"venue"
},
  "geometry": {"coordinates":[-83.663729,35.029533],"type":"Point"}
}