{
  "type": "Feature",
  "properties": {
    "addr:full":"108 E Main St Aberdeen NC 28315",
    "addr:housenumber":"108",
    "addr:postcode":"28315",
    "addr:street":"E Main St",
    "iso:country":"US",
    "sg:address":"108 E Main St",
    "sg:city":"Aberdeen",
    "sg:classifiers":[
        {
            "category":"Home & Garden",
            "subcategory":"Furniture",
            "type":"Retail Goods"
        }
    ],
    "sg:phone":"+1 910 944 1748",
    "sg:postcode":"28315",
    "sg:province":"NC",
    "wof:name":"Slate-Medlin Furniture Inc",
    "wof:placetype":"venue"
},
  "geometry": {"coordinates":[-79.427044,35.13166],"type":"Point"}
}