{
  "type": "Feature",
  "properties": {
    "addr:full":"1847 Windyrush Ln Gastonia NC 28054",
    "addr:housenumber":"1847",
    "addr:postcode":"28054",
    "addr:street":"Windyrush Ln",
    "iso:country":"US",
    "sg:address":"1847 Windyrush Ln",
    "sg:city":"Gastonia",
    "sg:classifiers":[
        {
            "category":"Professional",
            "type":"Services"
        }
    ],
    "sg:phone":"+1 704 867 0828",
    "sg:postcode":"28054",
    "sg:province":"NC",
    "wof:name":"Dragon Modifications LLC",
    "wof:placetype":"venue"
},
  "geometry": {"coordinates":[-81.144625,35.235787],"type":"Point"}
}