{
  "type": "Feature",
  "properties": {
    "addr:full":"2902 Tramway Rd Sanford NC 27332",
    "addr:housenumber":"2902",
    "addr:postcode":"27332",
    "addr:street":"Tramway Rd",
    "iso:country":"US",
    "sg:address":"2902 Tramway Rd",
    "sg:city":"Sanford",
    "sg:classifiers":[
        {
            "category":"Shopping",
            "type":"Retail Goods"
        }
    ],
    "sg:phone":"+1 919 776 3027",
    "sg:postcode":"27332",
    "sg:province":"NC",
    "sg:tags":[
        "merchandise"
    ],
    "wof:name":"Custom Picture Frames",
    "wof:placetype":"venue"
},
  "geometry": {"coordinates":[-79.206249,35.438089],"type":"Point"}
}