{
  "type": "Feature",
  "properties": {
    "addr:full":"8535 Cliff Cameron Dr Charlotte NC 28269",
    "addr:housenumber":"8535",
    "addr:postcode":"28269",
    "addr:street":"Cliff Cameron Dr",
    "iso:country":"US",
    "sg:address":"8535 Cliff Cameron Dr",
    "sg:city":"Charlotte",
    "sg:classifiers":[
        {
            "category":"Health Services",
            "subcategory":"Doctor",
            "type":"Services"
        }
    ],
    "sg:phone":"+1 704 503 4888",
    "sg:postcode":"28269",
    "sg:province":"NC",
    "sg:tags":[
        "physician",
        "surgeon",
        "medical"
    ],
    "wof:name":"Asthma and Allergy Specialists",
    "wof:placetype":"venue"
},
  "geometry": {"coordinates":[-80.780361,35.321203],"type":"Point"}
}