{
  "type": "Feature",
  "properties": {
    "iso:country":"US",
    "sg:address":"207 Regency Executive Park Dr Ste 1",
    "sg:city":"Charlotte",
    "sg:classifiers":[
        {
            "category":"Professional",
            "subcategory":"Computer Services",
            "type":"Services"
        }
    ],
    "sg:phone":"+1 704 926 1900",
    "sg:postcode":"28217",
    "sg:province":"NC",
    "sg:tags":[
        "isp",
        "provider",
        "internet"
    ],
    "wof:name":"Windstream Nuvox, Inc.",
    "wof:placetype":"venue"
},
  "geometry": {"coordinates":[-80.895713,35.151921],"type":"Point"}
}