{
  "type": "Feature",
  "properties": {
    "addr:full":"900 Main St Scotland Neck NC 27874",
    "addr:housenumber":"900",
    "addr:postcode":"27874",
    "addr:street":"Main St",
    "iso:country":"US",
    "sg:address":"900 Main St",
    "sg:city":"Scotland Neck",
    "sg:classifiers":[
        {
            "category":"Restaurant",
            "type":"Food & Drink"
        }
    ],
    "sg:phone":"+1 252 826 5711",
    "sg:postcode":"27874",
    "sg:province":"NC",
    "sg:tags":[
        "eating"
    ],
    "wof:name":"Whitikers Bar-B-Que Inc",
    "wof:placetype":"venue"
},
  "geometry": {"coordinates":[-77.422354,36.128678],"type":"Point"}
}