{
  "type": "Feature",
  "properties": {
    "iso:country":"US",
    "sg:address":"444 City View St",
    "sg:city":"Asheboro",
    "sg:classifiers":[
        {
            "category":"Building & Trades",
            "subcategory":"Construction",
            "type":"Services"
        }
    ],
    "sg:phone":"+1 336 629 7458",
    "sg:postcode":"27203",
    "sg:province":"NC",
    "sg:tags":[
        "contractor"
    ],
    "wof:name":"D R Jarrell Masonry",
    "wof:placetype":"venue"
},
  "geometry": {"coordinates":[-79.820211,35.71264],"type":"Point"}
}