{
  "type": "Feature",
  "properties": {
    "addr:full":"3105 Ward Blvd Wilson NC 27893",
    "addr:housenumber":"3105",
    "addr:postcode":"27893",
    "addr:street":"Ward Blvd",
    "iso:country":"US",
    "sg:address":"3105 Ward Blvd",
    "sg:city":"Wilson",
    "sg:classifiers":[
        {
            "category":"Freight",
            "type":"Transportation"
        }
    ],
    "sg:phone":"+1 252 237 0646",
    "sg:postcode":"27893",
    "sg:province":"NC",
    "sg:tags":[
        "commercial",
        "storage"
    ],
    "wof:name":"Brentwood Self Storage",
    "wof:placetype":"venue"
},
  "geometry": {"coordinates":[-77.919462,35.754904],"type":"Point"}
}