{
  "type": "Feature",
  "properties": {
    "addr:full":"3321 13th Avenue Ct NE Conover NC 28613",
    "addr:housenumber":"3321",
    "addr:postcode":"28613",
    "addr:street":"13Th Avenue Ct Ne",
    "iso:country":"US",
    "sg:address":"3321 13th Avenue Ct NE",
    "sg:city":"Conover",
    "sg:classifiers":[
        {
            "category":"Social Services",
            "type":"Services"
        }
    ],
    "sg:phone":"+1   ",
    "sg:postcode":"28613",
    "sg:province":"NC",
    "wof:name":"About Face Youth Boot Camp",
    "wof:placetype":"venue"
},
  "geometry": {"coordinates":[-81.26701300000001,35.740277],"type":"Point"}
}