{
  "type": "Feature",
  "properties": {
    "iso:country":"US",
    "sg:address":"305 Dogwood St",
    "sg:city":"Gastonia",
    "sg:classifiers":[
        {
            "category":"Utilities",
            "subcategory":"Recycling",
            "type":"Services"
        },
        {
            "category":"Wholesale",
            "subcategory":"Scrap",
            "type":"Manufacturing & Wholesale Goods"
        },
        {
            "category":"Autos & Motor Vehicles",
            "subcategory":"Auto Supplies",
            "type":"Retail Goods"
        }
    ],
    "sg:phone":"+1 704 827 9468",
    "sg:postcode":"28056",
    "sg:province":"NC",
    "sg:tags":[
        "automobile",
        "metal",
        "part",
        "supplies-used",
        "rebuilt"
    ],
    "wof:name":"Gaston Used Auto Parts & Recycling",
    "wof:placetype":"venue"
},
  "geometry": {"coordinates":[-81.064262,35.292271],"type":"Point"}
}