{
  "type": "Feature",
  "properties": {
    "addr:full":"231 Toney Rd Bostic NC 28018",
    "addr:housenumber":"231",
    "addr:postcode":"28018",
    "addr:street":"Toney Rd",
    "iso:country":"US",
    "sg:address":"231 Toney Rd",
    "sg:city":"Bostic",
    "sg:classifiers":[
        {
            "category":"Education",
            "subcategory":"School",
            "type":"Public Place"
        }
    ],
    "sg:phone":"+1 828 245 0658",
    "sg:postcode":"28018",
    "sg:province":"NC",
    "wof:name":"Sunshine Elementary School",
    "wof:placetype":"venue"
},
  "geometry": {"coordinates":[-81.81025699999999,35.453109],"type":"Point"}
}