{
  "type": "Feature",
  "properties": {
    "addr:full":"112 Jeffrey Ln Roanoke Rapids NC 27870",
    "addr:housenumber":"112",
    "addr:postcode":"27870",
    "addr:street":"Jeffrey Ln",
    "iso:country":"US",
    "sg:address":"112 Jeffrey Ln",
    "sg:city":"Roanoke Rapids",
    "sg:classifiers":[
        {
            "category":"Building & Trades",
            "subcategory":"Construction",
            "type":"Services"
        }
    ],
    "sg:phone":"+1 252 537 4260",
    "sg:postcode":"27870",
    "sg:province":"NC",
    "sg:tags":[
        "siding",
        "contractor"
    ],
    "wof:name":"Jenkins & Sons Vinyl Siding",
    "wof:placetype":"venue"
},
  "geometry": {"coordinates":[-77.677025,36.466022],"type":"Point"}
}