{
  "type": "Feature",
  "properties": {
    "iso:country":"US",
    "sg:address":"203 S Stratford Rd",
    "sg:city":"Winston Salem",
    "sg:classifiers":[
        {
            "category":"Real Estate",
            "subcategory":"Real Estate Agent",
            "type":"Services"
        }
    ],
    "sg:phone":"+1 336 499 3252",
    "sg:postcode":"27103",
    "sg:province":"NC",
    "wof:name":"Quantum Real Estate Capital",
    "wof:placetype":"venue"
},
  "geometry": {"coordinates":[-80.280012,36.092993],"type":"Point"}
}