{
  "type": "Feature",
  "properties": {
    "addr:full":"227 6th St Belmont NC 28012",
    "addr:housenumber":"227",
    "addr:postcode":"28012",
    "addr:street":"6Th St",
    "iso:country":"US",
    "sg:address":"227 6th St",
    "sg:city":"Belmont",
    "sg:classifiers":[
        {
            "category":"Food & Beverages",
            "subcategory":"Fruits & Vegetables",
            "type":"Retail Goods"
        }
    ],
    "sg:phone":"+1 704 829 6703",
    "sg:postcode":"28012",
    "sg:province":"NC",
    "wof:name":"Berry Fresh Produce",
    "wof:placetype":"venue"
},
  "geometry": {"coordinates":[-81.022908,35.244737],"type":"Point"}
}