{
  "type": "Feature",
  "properties": {
    "iso:country":"US",
    "sg:address":"4020 Joe St",
    "sg:city":"Charlotte",
    "sg:classifiers":[
        {
            "category":"Autos & Motor Vehicles",
            "subcategory":"Recreational Vehicle Sales",
            "type":"Retail Goods"
        }
    ],
    "sg:phone":"+1 704 598 0313",
    "sg:postcode":"28206",
    "sg:province":"NC",
    "sg:tags":[
        "parts",
        "trailer"
    ],
    "wof:name":"Fleet Equipment Inc",
    "wof:placetype":"venue"
},
  "geometry": {"coordinates":[-80.815237,35.270555],"type":"Point"}
}