{
  "type": "Feature",
  "properties": {
    "iso:country":"US",
    "sg:address":"3500 Lake Herman Dr",
    "sg:city":"Browns Summit",
    "sg:classifiers":[
        {
            "category":"Retail",
            "subcategory":"Auto Rental",
            "type":"Services"
        }
    ],
    "sg:phone":"+1   ",
    "sg:postcode":"27214",
    "sg:province":"NC",
    "sg:tags":[
        "truck"
    ],
    "wof:name":"Ryder",
    "wof:placetype":"venue"
},
  "geometry": {"coordinates":[-79.730268,36.168498],"type":"Point"}
}