{
  "type": "Feature",
  "properties": {
    "addr:full":"154 Forest Knolls Rd Goldsboro NC 27534",
    "addr:housenumber":"154",
    "addr:postcode":"27534",
    "addr:street":"Forest Knolls Rd",
    "iso:country":"US",
    "sg:address":"154 Forest Knolls Rd",
    "sg:city":"Goldsboro",
    "sg:classifiers":[
        {
            "category":"Building & Trades",
            "subcategory":"Cleaning & Sanitation",
            "type":"Services"
        }
    ],
    "sg:phone":"+1 919 751 1113",
    "sg:postcode":"27534",
    "sg:province":"NC",
    "sg:tags":[
        "janitor"
    ],
    "wof:name":"Klean-Rite Carpet Inc",
    "wof:placetype":"venue"
},
  "geometry": {"coordinates":[-77.929528,35.32548],"type":"Point"}
}