{
  "type": "Feature",
  "properties": {
    "iso:country":"US",
    "sg:address":"8816 Ross Ct",
    "sg:city":"Raleigh",
    "sg:classifiers":[
        {
            "category":"Health Services",
            "subcategory":"Doctor",
            "type":"Services"
        }
    ],
    "sg:phone":"+1 919 845 9221",
    "sg:postcode":"27613",
    "sg:province":"NC",
    "wof:name":"Michael J Harrison",
    "wof:placetype":"venue"
},
  "geometry": {"coordinates":[-78.686746,35.906662],"type":"Point"}
}