{
  "type": "Feature",
  "properties": {
    "iso:country":"US",
    "sg:address":"3731 N State Hwy 150",
    "sg:city":"Lexington",
    "sg:classifiers":[
        {
            "category":"Building & Trades",
            "subcategory":"Construction",
            "type":"Services"
        }
    ],
    "sg:phone":"+1 336 787 4175",
    "sg:postcode":"27295",
    "sg:province":"NC",
    "sg:tags":[
        "house"
    ],
    "wof:name":"Milsap Construction",
    "wof:placetype":"venue"
},
  "geometry": {"coordinates":[-80.322838,35.903648],"type":"Point"}
}