{
  "type": "Feature",
  "properties": {
    "iso:country":"US",
    "sg:address":"100 Johnson Ridge Rd",
    "sg:city":"Elkin",
    "sg:classifiers":[
        {
            "category":"Professional",
            "subcategory":"Accounting & Tax Preparation",
            "type":"Services"
        }
    ],
    "sg:phone":"+1   ",
    "sg:postcode":"28621",
    "sg:province":"NC",
    "wof:name":"Professional Billing Systems",
    "wof:placetype":"venue"
},
  "geometry": {"coordinates":[-80.82566799999999,36.252967],"type":"Point"}
}