{
  "type": "Feature",
  "properties": {
    "iso:country":"US",
    "sg:address":"935 Shelton Ave",
    "sg:city":"Statesville",
    "sg:classifiers":[
        {
            "category":"Manufacturing",
            "subcategory":"Motor Vehicles & Parts",
            "type":"Manufacturing & Wholesale Goods"
        }
    ],
    "sg:phone":"+1 704 883 0089",
    "sg:postcode":"28677",
    "sg:province":"NC",
    "sg:tags":[
        "equipment",
        "mfg",
        "transportation",
        "supply"
    ],
    "wof:name":"Tubular Resources Inc",
    "wof:placetype":"venue"
},
  "geometry": {"coordinates":[-80.884203,35.772182],"type":"Point"}
}