{
  "type": "Feature",
  "properties": {
    "addr:full":"809 Conway Rd Fair Bluff NC 28439",
    "addr:housenumber":"809",
    "addr:postcode":"28439",
    "addr:street":"Conway Rd",
    "iso:country":"US",
    "sg:address":"809 Conway Rd",
    "sg:city":"Fair Bluff",
    "sg:classifiers":[
        {
            "category":"Manufacturing",
            "subcategory":"Tools & Machinery",
            "type":"Manufacturing & Wholesale Goods"
        }
    ],
    "sg:phone":"+1 910 649 7813",
    "sg:postcode":"28439",
    "sg:province":"NC",
    "sg:tags":[
        "farm",
        "mfg"
    ],
    "wof:name":"John D Hilbourn",
    "wof:placetype":"venue"
},
  "geometry": {"coordinates":[-79.031496,34.31442],"type":"Point"}
}