{
  "type": "Feature",
  "properties": {
    "iso:country":"US",
    "sg:address":"317 Royster Ave",
    "sg:city":"Shelby",
    "sg:classifiers":[
        {
            "category":"Retail",
            "subcategory":"Auto Repair",
            "type":"Services"
        }
    ],
    "sg:phone":"+1 704 487 0984",
    "sg:postcode":"28150",
    "sg:province":"NC",
    "sg:tags":[
        "body",
        "automobile",
        "painting"
    ],
    "wof:name":"Mauney's Custom Creations",
    "wof:placetype":"venue"
},
  "geometry": {"coordinates":[-81.546042,35.281352],"type":"Point"}
}