{
  "type": "Feature",
  "properties": {
    "iso:country":"US",
    "sg:address":"2270 McPhail Rd",
    "sg:city":"Lumberton",
    "sg:classifiers":[
        {
            "category":"Organizations",
            "subcategory":"Religious Organization",
            "type":"Services"
        }
    ],
    "sg:phone":"+1 910 738 4200",
    "sg:postcode":"28358",
    "sg:province":"NC",
    "sg:tags":[
        "church"
    ],
    "wof:name":"Hyde Park Baptist Church",
    "wof:placetype":"venue"
},
  "geometry": {"coordinates":[-78.974101,34.619816],"type":"Point"}
}