{
  "type": "Feature",
  "properties": {
    "addr:full":"306 W Granville St Windsor NC 27983",
    "addr:housenumber":"306",
    "addr:postcode":"27983",
    "addr:street":"W Granville St",
    "iso:country":"US",
    "sg:address":"306 W Granville St",
    "sg:city":"Windsor",
    "sg:classifiers":[
        {
            "category":"Autos & Motor Vehicles",
            "subcategory":"Auto Supplies",
            "type":"Retail Goods"
        }
    ],
    "sg:phone":"+1 252 794 5259",
    "sg:postcode":"27983",
    "sg:province":"NC",
    "sg:tags":[
        "tire"
    ],
    "wof:name":"Copeland's Tire & Wheel",
    "wof:placetype":"venue"
},
  "geometry": {"coordinates":[-76.949231,35.997001],"type":"Point"}
}