{
  "type": "Feature",
  "properties": {
    "addr:full":"280 William Dr Salisbury NC 28146",
    "addr:housenumber":"280",
    "addr:postcode":"28146",
    "addr:street":"William Dr",
    "iso:country":"US",
    "sg:address":"280 William Dr",
    "sg:city":"Salisbury",
    "sg:classifiers":[
        {
            "category":"Retail",
            "subcategory":"Auto Repair",
            "type":"Services"
        }
    ],
    "sg:phone":"+1 704 202 0849",
    "sg:postcode":"28146",
    "sg:province":"NC",
    "sg:tags":[
        "wrecker"
    ],
    "wof:name":"Anytime Towing",
    "wof:placetype":"venue"
},
  "geometry": {"coordinates":[-80.392877,35.636972],"type":"Point"}
}