{
  "type": "Feature",
  "properties": {
    "addr:full":"119 E 8th St Charlotte NC 28202",
    "addr:housenumber":"119",
    "addr:postcode":"28202",
    "addr:street":"E 8Th St",
    "iso:country":"US",
    "sg:address":"119 E 8th St",
    "sg:city":"Charlotte",
    "sg:classifiers":[
        {
            "category":"Real Estate",
            "subcategory":"Architect",
            "type":"Services"
        }
    ],
    "sg:phone":"+1 704 334 7571",
    "sg:postcode":"28202",
    "sg:province":"NC",
    "sg:website":"www.wilkersonarch.com",
    "wof:name":"Wilkerson Associates",
    "wof:placetype":"venue"
},
  "geometry": {"coordinates":[-80.83776400000001,35.229552],"type":"Point"}
}