{
  "type": "Feature",
  "properties": {
    "addr:full":"4825 Renaissance Ridge Rd Charlotte NC 28217",
    "addr:housenumber":"4825",
    "addr:postcode":"28217",
    "addr:street":"Renaissance Ridge Rd",
    "iso:country":"US",
    "sg:address":"4825 Renaissance Ridge Rd",
    "sg:city":"Charlotte",
    "sg:classifiers":[
        {
            "category":"Building & Trades",
            "subcategory":"Construction",
            "type":"Services"
        }
    ],
    "sg:phone":"+1 704 357 3330",
    "sg:postcode":"28217",
    "sg:province":"NC",
    "sg:tags":[
        "maintenance",
        "contractor"
    ],
    "wof:name":"Quality Maintenance",
    "wof:placetype":"venue"
},
  "geometry": {"coordinates":[-80.89954299999999,35.184263],"type":"Point"}
}