{
  "type": "Feature",
  "properties": {
    "addr:full":"212 Lake Montonia Rd Kings Mountain NC 28086",
    "addr:housenumber":"212",
    "addr:postcode":"28086",
    "addr:street":"Lake Montonia Rd",
    "iso:country":"US",
    "sg:address":"212 Lake Montonia Rd",
    "sg:city":"Kings Mountain",
    "sg:classifiers":[
        {
            "category":"Organizations",
            "subcategory":"Religious Organization",
            "type":"Services"
        }
    ],
    "sg:phone":"+1 704 739 4636",
    "sg:postcode":"28086",
    "sg:province":"NC",
    "sg:tags":[
        "church"
    ],
    "wof:name":"Adams Chapel AME Zion Church",
    "wof:placetype":"venue"
},
  "geometry": {"coordinates":[-81.33026700000001,35.215385],"type":"Point"}
}