{
  "type": "Feature",
  "properties": {
    "addr:full":"400 S Elliott Rd Chapel Hill NC 27514",
    "addr:housenumber":"400",
    "addr:postcode":"27514",
    "addr:street":"S Elliott Rd",
    "iso:country":"US",
    "sg:address":"400 S Elliott Rd",
    "sg:city":"Chapel Hill",
    "sg:classifiers":[
        {
            "category":"Shopping",
            "subcategory":"Pets & Pet Supplies",
            "type":"Retail Goods"
        }
    ],
    "sg:postcode":"27514",
    "sg:province":"NC",
    "sg:tags":[
        "store"
    ],
    "sg:website":"phydeauxpets.com",
    "wof:name":"Phydeaux",
    "wof:placetype":"venue"
},
  "geometry": {"coordinates":[-79.02549999999999,35.932288],"type":"Point"}
}