{
  "type": "Feature",
  "properties": {
    "addr:full":"319 S Main St Salisbury NC 28144",
    "addr:housenumber":"319",
    "addr:postcode":"28144",
    "addr:street":"S Main St",
    "iso:country":"US",
    "sg:address":"319 S Main St",
    "sg:city":"Salisbury",
    "sg:classifiers":[
        {
            "category":"Shopping",
            "type":"Retail Goods"
        }
    ],
    "sg:phone":"+1 704 633 2614",
    "sg:postcode":"28144",
    "sg:province":"NC",
    "sg:tags":[
        "plant",
        "flower",
        "tree",
        "artificial"
    ],
    "wof:name":"A Prosthetic Care Ctr",
    "wof:placetype":"venue"
},
  "geometry": {"coordinates":[-80.47300199999999,35.664897],"type":"Point"}
}