{
  "type": "Feature",
  "properties": {
    "iso:country":"US",
    "sg:address":"105 Sterling Ct",
    "sg:city":"Salisbury",
    "sg:classifiers":[
        {
            "category":"Restaurant",
            "type":"Food & Drink"
        }
    ],
    "sg:phone":"+1 704 633 2452",
    "sg:postcode":"28144",
    "sg:province":"NC",
    "wof:name":"Church's Chicken",
    "wof:placetype":"venue"
},
  "geometry": {"coordinates":[-80.469352,35.708398],"type":"Point"}
}