{
  "type": "Feature",
  "properties": {
    "addr:full":"2211 Lake Lucas Rd Sophia NC 27350",
    "addr:housenumber":"2211",
    "addr:postcode":"27350",
    "addr:street":"Lake Lucas Rd",
    "iso:country":"US",
    "sg:address":"2211 Lake Lucas Rd",
    "sg:city":"Sophia",
    "sg:classifiers":[
        {
            "category":"Personal",
            "subcategory":"Beauty Salon",
            "type":"Services"
        }
    ],
    "sg:phone":"+1 336 629 5655",
    "sg:postcode":"27350",
    "sg:province":"NC",
    "sg:tags":[
        "shop"
    ],
    "wof:name":"Doris's Beauty Shop",
    "wof:placetype":"venue"
},
  "geometry": {"coordinates":[-79.864327,35.776159],"type":"Point"}
}