{
  "type": "Feature",
  "properties": {
    "addr:full":"2631 N Raleigh St Rocky Mount NC 27801",
    "addr:housenumber":"2631",
    "addr:postcode":"27801",
    "addr:street":"N Raleigh St",
    "iso:country":"US",
    "sg:address":"2631 N Raleigh St",
    "sg:city":"Rocky Mount",
    "sg:classifiers":[
        {
            "category":"Recreation",
            "type":"Entertainment"
        }
    ],
    "sg:phone":"+1 252 442 8137",
    "sg:postcode":"27801",
    "sg:province":"NC",
    "sg:tags":[
        "carnival"
    ],
    "wof:name":"Rocky Mt Fair Grounds",
    "wof:placetype":"venue"
},
  "geometry": {"coordinates":[-77.747356,35.94502],"type":"Point"}
}