{
  "type": "Feature",
  "properties": {
    "iso:country":"US",
    "sg:address":"106 N Long St",
    "sg:city":"Salisbury",
    "sg:classifiers":[
        {
            "category":"Retail",
            "subcategory":"Laundry & Dry Cleaning",
            "type":"Services"
        }
    ],
    "sg:phone":"+1 704 633 0949",
    "sg:postcode":"28144",
    "sg:province":"NC",
    "wof:name":"Vogue Cleaners",
    "wof:placetype":"venue"
},
  "geometry": {"coordinates":[-80.465658,35.665532],"type":"Point"}
}