{
  "type": "Feature",
  "properties": {
    "addr:full":"3531 Joel Turner Dr Charlotte NC 28216",
    "addr:housenumber":"3531",
    "addr:postcode":"28216",
    "addr:street":"Joel Turner Dr",
    "iso:country":"US",
    "sg:address":"3531 Joel Turner Dr",
    "sg:city":"Charlotte",
    "sg:classifiers":[
        {
            "category":"Shopping",
            "subcategory":"News",
            "type":"Retail Goods"
        }
    ],
    "sg:phone":"+1 704 391 2370",
    "sg:postcode":"28216",
    "sg:province":"NC",
    "sg:tags":[
        "magazine"
    ],
    "wof:name":"Transforming New Magazine",
    "wof:placetype":"venue"
},
  "geometry": {"coordinates":[-80.894042,35.317013],"type":"Point"}
}