{
  "type": "Feature",
  "properties": {
    "iso:country":"US",
    "sg:address":"134 NW Main St",
    "sg:city":"Rocky Mount",
    "sg:classifiers":[
        {
            "category":"Retail",
            "subcategory":"Repair Shop",
            "type":"Services"
        }
    ],
    "sg:phone":"+1   ",
    "sg:postcode":"27804",
    "sg:province":"NC",
    "wof:name":"Mueller & Cook",
    "wof:placetype":"venue"
},
  "geometry": {"coordinates":[-77.79571900000001,35.941914],"type":"Point"}
}