{
  "type": "Feature",
  "properties": {
    "addr:full":"96 Central Ave Asheville NC 28801",
    "addr:housenumber":"96",
    "addr:postcode":"28801",
    "addr:street":"Central Ave",
    "iso:country":"US",
    "sg:address":"96 Central Ave",
    "sg:city":"Asheville",
    "sg:classifiers":[
        {
            "category":"Real Estate",
            "subcategory":"Surveying",
            "type":"Services"
        }
    ],
    "sg:phone":"+1 828 252 1530",
    "sg:postcode":"28801",
    "sg:province":"NC",
    "sg:tags":[
        "surveyor"
    ],
    "sg:website":"www.wamapa.com",
    "wof:name":"WEBB A Morgan & Assoc",
    "wof:placetype":"venue"
},
  "geometry": {"coordinates":[-82.549859,35.602847],"type":"Point"}
}