{
  "type": "Feature",
  "properties": {
    "iso:country":"US",
    "sg:address":"130 Vandiver Dr",
    "sg:city":"Lincolnton",
    "sg:classifiers":[
        {
            "category":"Retail",
            "subcategory":"Self-service Laundry",
            "type":"Services"
        }
    ],
    "sg:phone":"+1 704 736 0510",
    "sg:postcode":"28092",
    "sg:province":"NC",
    "wof:name":"Family Coin Laundry",
    "wof:placetype":"venue"
},
  "geometry": {"coordinates":[-81.240791,35.494845],"type":"Point"}
}