{
  "type": "Feature",
  "properties": {
    "addr:full":"2314 Westdown Ter Kinston NC 28504",
    "addr:housenumber":"2314",
    "addr:postcode":"28504",
    "addr:street":"Westdown Ter",
    "iso:country":"US",
    "sg:address":"2314 Westdown Ter",
    "sg:city":"Kinston",
    "sg:classifiers":[
        {
            "category":"Real Estate",
            "subcategory":"Real Estate Operator",
            "type":"Services"
        }
    ],
    "sg:phone":"+1 252 522 2337",
    "sg:postcode":"28504",
    "sg:province":"NC",
    "sg:tags":[
        "building",
        "nonresidential"
    ],
    "wof:name":"Stallings Properties Inc",
    "wof:placetype":"venue"
},
  "geometry": {"coordinates":[-77.65407,35.304163],"type":"Point"}
}