{
  "type": "Feature",
  "properties": {
    "addr:full":"138 Bakertown Rd Fuquay Varina NC 27526",
    "addr:housenumber":"138",
    "addr:postcode":"27526",
    "addr:street":"Bakertown Rd",
    "iso:country":"US",
    "sg:address":"138 Bakertown Rd",
    "sg:city":"Fuquay Varina",
    "sg:classifiers":[
        {
            "category":"Building & Trades",
            "subcategory":"Construction",
            "type":"Services"
        }
    ],
    "sg:phone":"+1 919 552 1685",
    "sg:postcode":"27526",
    "sg:province":"NC",
    "sg:tags":[
        "house"
    ],
    "wof:name":"K&M Builders",
    "wof:placetype":"venue"
},
  "geometry": {"coordinates":[-78.871595,35.545815],"type":"Point"}
}