{
  "type": "Feature",
  "properties": {
    "iso:country":"US",
    "sg:address":"15800 John J Delaney Dr",
    "sg:city":"Charlotte",
    "sg:classifiers":[
        {
            "category":"Restaurant",
            "type":"Food & Drink"
        }
    ],
    "sg:phone":"+1 704 541 7985",
    "sg:postcode":"28277",
    "sg:province":"NC",
    "sg:tags":[
        "eating"
    ],
    "wof:name":"Yum Brands",
    "wof:placetype":"venue"
},
  "geometry": {"coordinates":[-80.85270800000001,35.058222],"type":"Point"}
}