{
  "type": "Feature",
  "properties": {
    "addr:full":"408 Comfort Rd Richlands NC 28574",
    "addr:housenumber":"408",
    "addr:postcode":"28574",
    "addr:street":"Comfort Rd",
    "iso:country":"US",
    "sg:address":"408 Comfort Rd",
    "sg:city":"Richlands",
    "sg:classifiers":[
        {
            "category":"Building & Trades",
            "subcategory":"Construction",
            "type":"Services"
        }
    ],
    "sg:phone":"+1 910 324 6846",
    "sg:postcode":"28574",
    "sg:province":"NC",
    "sg:tags":[
        "contractor"
    ],
    "wof:name":"B Js Drywall Service",
    "wof:placetype":"venue"
},
  "geometry": {"coordinates":[-77.52461599999999,34.922317],"type":"Point"}
}