{
  "type": "Feature",
  "properties": {
    "iso:country":"US",
    "sg:address":"2834 Capital Blvd",
    "sg:city":"Raleigh",
    "sg:classifiers":[
        {
            "category":"Shopping",
            "subcategory":"Clothing, Apparel, & Fashions",
            "type":"Retail Goods"
        }
    ],
    "sg:phone":"+1 919 872 3456",
    "sg:postcode":"27604",
    "sg:province":"NC",
    "sg:tags":[
        "furnishing"
    ],
    "wof:name":"Dr Stylz",
    "wof:placetype":"venue"
},
  "geometry": {"coordinates":[-78.598727,35.817755],"type":"Point"}
}