{
  "type": "Feature",
  "properties": {
    "iso:country":"US",
    "sg:address":"129 Southside Dr",
    "sg:city":"Charlotte",
    "sg:classifiers":[
        {
            "category":"Home & Garden",
            "subcategory":"Home Furnishings",
            "type":"Retail Goods"
        }
    ],
    "sg:phone":"+1 704 376 9747",
    "sg:postcode":"28217",
    "sg:province":"NC",
    "sg:tags":[
        "equipment",
        "fireplace"
    ],
    "sg:website":"www.homefiresusa.com",
    "wof:name":"Homefires SCS Inc",
    "wof:placetype":"venue"
},
  "geometry": {"coordinates":[-80.881254,35.186539],"type":"Point"}
}