{
  "type": "Feature",
  "properties": {
    "addr:full":"1003 Village Greenway Cary NC 27511",
    "addr:housenumber":"1003",
    "addr:postcode":"27511",
    "addr:street":"Village Greenway",
    "iso:country":"US",
    "sg:address":"1003 Village Greenway",
    "sg:city":"Cary",
    "sg:classifiers":[
        {
            "category":"Building & Trades",
            "subcategory":"Cleaning & Sanitation",
            "type":"Services"
        }
    ],
    "sg:phone":"+1   ",
    "sg:postcode":"27511",
    "sg:province":"NC",
    "sg:tags":[
        "maintenance"
    ],
    "wof:name":"Blue Moon Janitorial Service",
    "wof:placetype":"venue"
},
  "geometry": {"coordinates":[-78.760687,35.779288],"type":"Point"}
}