{
  "type": "Feature",
  "properties": {
    "iso:country":"US",
    "sg:address":"120 Thermal Dr",
    "sg:city":"Forest City",
    "sg:classifiers":[
        {
            "category":"Professional",
            "type":"Services"
        }
    ],
    "sg:phone":"+1 828 288 9618",
    "sg:postcode":"28043",
    "sg:province":"NC",
    "sg:tags":[
        "establishment"
    ],
    "wof:name":"Yelton Family Care Li",
    "wof:placetype":"venue"
},
  "geometry": {"coordinates":[-81.919448,35.330925],"type":"Point"}
}