{
  "type": "Feature",
  "properties": {
    "iso:country":"US",
    "sg:address":"947 E Main St",
    "sg:city":"Durham",
    "sg:classifiers":[
        {
            "category":"Organizations",
            "subcategory":"Religious Organization",
            "type":"Services"
        }
    ],
    "sg:phone":"+1 919 688 2200",
    "sg:postcode":"27701",
    "sg:province":"NC",
    "wof:name":"Sow Ministries",
    "wof:placetype":"venue"
},
  "geometry": {"coordinates":[-78.890265,35.989118],"type":"Point"}
}