{
  "type": "Feature",
  "properties": {
    "addr:full":"800 Tobe Hudson Rd Dobson NC 27017",
    "addr:housenumber":"800",
    "addr:postcode":"27017",
    "addr:street":"Tobe Hudson Rd",
    "iso:country":"US",
    "sg:address":"800 Tobe Hudson Rd",
    "sg:city":"Dobson",
    "sg:classifiers":[
        {
            "category":"Professional",
            "subcategory":"Business Services",
            "type":"Services"
        }
    ],
    "sg:phone":"+1   ",
    "sg:postcode":"27017",
    "sg:province":"NC",
    "wof:name":"Carolina Classic Horse Expo",
    "wof:placetype":"venue"
},
  "geometry": {"coordinates":[-80.767281,36.422574],"type":"Point"}
}