{
  "type": "Feature",
  "properties": {
    "addr:full":"6915 Wilkinson Blvd Belmont NC 28012",
    "addr:housenumber":"6915",
    "addr:postcode":"28012",
    "addr:street":"Wilkinson Blvd",
    "iso:country":"US",
    "sg:address":"6915 Wilkinson Blvd",
    "sg:city":"Belmont",
    "sg:classifiers":[
        {
            "category":"Restaurant",
            "type":"Food & Drink"
        },
        {
            "category":"Autos & Motor Vehicles",
            "subcategory":"Motorcycle Sales",
            "type":"Retail Goods"
        }
    ],
    "sg:phone":"+1 704 825 1996",
    "sg:postcode":"28012",
    "sg:province":"NC",
    "sg:tags":[
        "scooter",
        "eating"
    ],
    "wof:name":"Long John's Cycles",
    "wof:placetype":"venue"
},
  "geometry": {"coordinates":[-81.023235,35.249876],"type":"Point"}
}