{
  "type": "Feature",
  "properties": {
    "iso:country":"US",
    "sg:address":"10210 Statesville Blvd",
    "sg:city":"Cleveland",
    "sg:classifiers":[
        {
            "category":"Manufacturing",
            "subcategory":"Tools & Machinery",
            "type":"Manufacturing & Wholesale Goods"
        }
    ],
    "sg:phone":"+1 704 278 2221",
    "sg:postcode":"27013",
    "sg:province":"NC",
    "sg:tags":[
        "device",
        "fluid",
        "totalizing"
    ],
    "sg:website":"www.herseymeters.com",
    "wof:name":"Hersey Meters",
    "wof:placetype":"venue"
},
  "geometry": {"coordinates":[-80.65945000000001,35.721323],"type":"Point"}
}