{
  "type": "Feature",
  "properties": {
    "addr:full":"4210 Burlington Rd Greensboro NC 27405",
    "addr:housenumber":"4210",
    "addr:postcode":"27405",
    "addr:street":"Burlington Rd",
    "iso:country":"US",
    "sg:address":"4210 Burlington Rd",
    "sg:city":"Greensboro",
    "sg:classifiers":[
        {
            "category":"Restaurant",
            "type":"Food & Drink"
        }
    ],
    "sg:menulink":"http://www.allmenus.com/nc/gilmer/137345-subway/menu/",
    "sg:phone":"+1 336 375 4875",
    "sg:postcode":"27405",
    "sg:province":"NC",
    "sg:tags":[
        "american",
        "sandwich"
    ],
    "wof:name":"Subway",
    "wof:placetype":"venue"
},
  "geometry": {"coordinates":[-79.710109,36.086317],"type":"Point"}
}