{
  "type": "Feature",
  "properties": {
    "iso:country":"US",
    "sg:address":"16 Bradshaw Ln",
    "sg:city":"Candler",
    "sg:classifiers":[
        {
            "category":"Real Estate",
            "subcategory":"Surveying",
            "type":"Services"
        }
    ],
    "sg:phone":"+1   ",
    "sg:postcode":"28715",
    "sg:province":"NC",
    "wof:name":"Styles Alan B Land Surveying",
    "wof:placetype":"venue"
},
  "geometry": {"coordinates":[-82.689571,35.561476],"type":"Point"}
}