{
  "type": "Feature",
  "properties": {
    "addr:full":"Nc 54 Hwy Cary NC 27511",
    "addr:postcode":"27511",
    "addr:street":"Nc 54 Hwy",
    "iso:country":"US",
    "sg:address":"Nc 54 Hwy",
    "sg:city":"Cary",
    "sg:classifiers":[
        {
            "category":"Organizations",
            "subcategory":"Religious Organization",
            "type":"Services"
        }
    ],
    "sg:phone":"+1 919 469 0790",
    "sg:postcode":"27511",
    "sg:province":"NC",
    "wof:name":"Shiloh Baptist Church",
    "wof:placetype":"venue"
},
  "geometry": {"coordinates":[-78.778198,35.752602],"type":"Point"}
}