{
  "type": "Feature",
  "properties": {
    "addr:full":"15616 Louth Ct Huntersville NC 28078",
    "addr:housenumber":"15616",
    "addr:postcode":"28078",
    "addr:street":"Louth Ct",
    "iso:country":"US",
    "sg:address":"15616 Louth Ct",
    "sg:city":"Huntersville",
    "sg:classifiers":[
        {
            "category":"Professional",
            "subcategory":"Management & Consulting",
            "type":"Services"
        }
    ],
    "sg:phone":"+1   ",
    "sg:postcode":"28078",
    "sg:province":"NC",
    "wof:name":"Human Element LLC",
    "wof:placetype":"venue"
},
  "geometry": {"coordinates":[-80.878855,35.42022],"type":"Point"}
}