{
  "type": "Feature",
  "properties": {
    "addr:full":"1135 N Main St Marion NC 28752",
    "addr:housenumber":"1135",
    "addr:postcode":"28752",
    "addr:street":"N Main St",
    "iso:country":"US",
    "sg:address":"1135 N Main St",
    "sg:city":"Marion",
    "sg:classifiers":[
        {
            "category":"Health Services",
            "subcategory":"Chiropractor",
            "type":"Services"
        },
        {
            "category":"Health Services",
            "subcategory":"Doctor",
            "type":"Services"
        }
    ],
    "sg:phone":"+1 828 652 7746",
    "sg:postcode":"28752",
    "sg:province":"NC",
    "sg:tags":[
        "medical"
    ],
    "wof:name":"Area Pain & Wellness Center",
    "wof:placetype":"venue"
},
  "geometry": {"coordinates":[-82.024091,35.695792],"type":"Point"}
}