{
  "type": "Feature",
  "properties": {
    "iso:country":"US",
    "sg:address":"2201 Lynnwood Dr",
    "sg:city":"Wilmington",
    "sg:classifiers":[
        {
            "category":"Organizations",
            "subcategory":"Religious Organization",
            "type":"Services"
        }
    ],
    "sg:phone":"+1 910 762 0400",
    "sg:postcode":"28403",
    "sg:province":"NC",
    "sg:tags":[
        "church"
    ],
    "wof:name":"United Methodist Chr-Wlmngtn",
    "wof:placetype":"venue"
},
  "geometry": {"coordinates":[-77.915768,34.201099],"type":"Point"}
}