{
  "type": "Feature",
  "properties": {
    "addr:full":"15347 State Hwy 24/27 Eagle Springs NC 27242",
    "addr:housenumber":"15347;27",
    "addr:postcode":"27242",
    "addr:street":"State Hwy 24 /;Eagle Springs",
    "iso:country":"US",
    "sg:address":"15347 State Hwy 24/27",
    "sg:city":"Eagle Springs",
    "sg:classifiers":[
        {
            "category":"Shopping",
            "subcategory":"Florist",
            "type":"Retail Goods"
        }
    ],
    "sg:phone":"+1 910 948 3492",
    "sg:postcode":"27242",
    "sg:province":"NC",
    "wof:name":"Annie's Country Florist",
    "wof:placetype":"venue"
},
  "geometry": {"coordinates":[-79.64822599999999,35.389376],"type":"Point"}
}