{
  "type": "Feature",
  "properties": {
    "addr:full":"1913 Woodlawn St Kannapolis NC 28083",
    "addr:housenumber":"1913",
    "addr:postcode":"28083",
    "addr:street":"Woodlawn St",
    "iso:country":"US",
    "sg:address":"1913 Woodlawn St",
    "sg:city":"Kannapolis",
    "sg:classifiers":[
        {
            "category":"Home & Garden",
            "subcategory":"Garden Supply",
            "type":"Retail Goods"
        }
    ],
    "sg:phone":"+1 704 938 6205",
    "sg:postcode":"28083",
    "sg:province":"NC",
    "wof:name":"Joes Small Engine Service",
    "wof:placetype":"venue"
},
  "geometry": {"coordinates":[-80.59217599999999,35.505884],"type":"Point"}
}