{
  "type": "Feature",
  "properties": {
    "iso:country":"US",
    "sg:address":"867 Lobelia Rd",
    "sg:city":"Vass",
    "sg:classifiers":[
        {
            "category":"Personal",
            "subcategory":"Beauty Salon",
            "type":"Services"
        }
    ],
    "sg:phone":"+1 910 245 7291",
    "sg:postcode":"28394",
    "sg:province":"NC",
    "wof:name":"Doris's Beauty Shop",
    "wof:placetype":"venue"
},
  "geometry": {"coordinates":[-79.268152,35.245849],"type":"Point"}
}