{
  "type": "Feature",
  "properties": {
    "addr:full":"514 Bridgestone Ct Gastonia NC 28056",
    "addr:housenumber":"514",
    "addr:postcode":"28056",
    "addr:street":"Bridgestone Ct",
    "iso:country":"US",
    "sg:address":"514 Bridgestone Ct",
    "sg:city":"Gastonia",
    "sg:classifiers":[
        {
            "category":"Building & Trades",
            "subcategory":"Construction",
            "type":"Services"
        }
    ],
    "sg:phone":"+1 704 861 9300",
    "sg:postcode":"28056",
    "sg:province":"NC",
    "sg:tags":[
        "home",
        "builder"
    ],
    "wof:name":"Michael Spargo-Spargo Built",
    "wof:placetype":"venue"
},
  "geometry": {"coordinates":[-81.138295,35.16656],"type":"Point"}
}