{
  "type": "Feature",
  "properties": {
    "iso:country":"US",
    "sg:address":"2132 Radcliffe Ave",
    "sg:city":"Charlotte",
    "sg:classifiers":[
        {
            "category":"Education",
            "subcategory":"School",
            "type":"Public Place"
        }
    ],
    "sg:phone":"+1 980 343 5522",
    "sg:postcode":"28207",
    "sg:province":"NC",
    "sg:website":"www.myersparktraditional.com",
    "wof:name":"Myers Park Traditional Element",
    "wof:placetype":"venue"
},
  "geometry": {"coordinates":[-80.830893,35.189409],"type":"Point"}
}