{
  "type": "Feature",
  "properties": {
    "iso:country":"US",
    "sg:address":"511 Salter Path Rd",
    "sg:city":"Pine Knoll Shrs",
    "sg:classifiers":[
        {
            "category":"Restaurant",
            "type":"Food & Drink"
        }
    ],
    "sg:phone":"+1 252 247 4155",
    "sg:postcode":"28512",
    "sg:province":"NC",
    "sg:website":"www.clamdiggerramadainn.com",
    "wof:name":"Clamdigger Restaurant",
    "wof:placetype":"venue"
},
  "geometry": {"coordinates":[-76.84707,34.692042],"type":"Point"}
}