{
  "type": "Feature",
  "properties": {
    "addr:full":"1806 Bradford Dr Greenville NC 27858",
    "addr:housenumber":"1806",
    "addr:postcode":"27858",
    "addr:street":"Bradford Dr",
    "iso:country":"US",
    "sg:address":"1806 Bradford Dr",
    "sg:city":"Greenville",
    "sg:classifiers":[
        {
            "category":"Insurance",
            "subcategory":"Insurance Agent",
            "type":"Services"
        }
    ],
    "sg:phone":"+1 252 756 7000",
    "sg:postcode":"27858",
    "sg:province":"NC",
    "sg:tags":[
        "accident"
    ],
    "wof:name":"Jim Douglas",
    "wof:placetype":"venue"
},
  "geometry": {"coordinates":[-77.35878599999999,35.570165],"type":"Point"}
}