{
  "type": "Feature",
  "properties": {
    "addr:full":"1474 Winston Ave Statesville NC 28677",
    "addr:housenumber":"1474",
    "addr:postcode":"28677",
    "addr:street":"Winston Ave",
    "iso:country":"US",
    "sg:address":"1474 Winston Ave",
    "sg:city":"Statesville",
    "sg:classifiers":[
        {
            "category":"Wholesale",
            "subcategory":"Construction Materials",
            "type":"Manufacturing & Wholesale Goods"
        }
    ],
    "sg:phone":"+1 704 924 9400",
    "sg:postcode":"28677",
    "sg:province":"NC",
    "wof:name":"Building Mtls Whl & Ret Inc",
    "wof:placetype":"venue"
},
  "geometry": {"coordinates":[-80.90405800000001,35.769127],"type":"Point"}
}