{
  "type": "Feature",
  "properties": {
    "addr:full":"120 Pump Station Rd Statesville NC 28625",
    "addr:housenumber":"120",
    "addr:postcode":"28625",
    "addr:street":"Pump Station Rd",
    "iso:country":"US",
    "sg:address":"120 Pump Station Rd",
    "sg:city":"Statesville",
    "sg:classifiers":[
        {
            "category":"Retail",
            "subcategory":"Auto Rental",
            "type":"Services"
        }
    ],
    "sg:phone":"+1   ",
    "sg:postcode":"28625",
    "sg:province":"NC",
    "sg:tags":[
        "truck",
        "leasing"
    ],
    "wof:name":"U-Haul",
    "wof:placetype":"venue"
},
  "geometry": {"coordinates":[-80.879082,35.810196],"type":"Point"}
}