{
  "type": "Feature",
  "properties": {
    "addr:full":"2401 Womble St SW Wilson NC 27893",
    "addr:housenumber":"2401",
    "addr:postcode":"27893",
    "addr:street":"Womble St Sw",
    "iso:country":"US",
    "sg:address":"2401 Womble St SW",
    "sg:city":"Wilson",
    "sg:classifiers":[
        {
            "category":"Banks & Credit Unions",
            "subcategory":"Bank",
            "type":"Services"
        }
    ],
    "sg:phone":"+1 252 206 5720",
    "sg:postcode":"27893",
    "sg:province":"NC",
    "sg:tags":[
        "loan",
        "real estate"
    ],
    "wof:name":"All Fund Mortgage",
    "wof:placetype":"venue"
},
  "geometry": {"coordinates":[-77.940124,35.713988],"type":"Point"}
}