{
  "type": "Feature",
  "properties": {
    "addr:full":"6243 Benson Hardee Rd Benson NC 27504",
    "addr:housenumber":"6243",
    "addr:postcode":"27504",
    "addr:street":"Benson Hardee Rd",
    "iso:country":"US",
    "sg:address":"6243 Benson Hardee Rd",
    "sg:city":"Benson",
    "sg:classifiers":[
        {
            "category":"Professional",
            "type":"Services"
        }
    ],
    "sg:phone":"+1 919 894 2895",
    "sg:postcode":"27504",
    "sg:province":"NC",
    "wof:name":"Victor W Evans",
    "wof:placetype":"venue"
},
  "geometry": {"coordinates":[-78.612442,35.474359],"type":"Point"}
}