{
  "type": "Feature",
  "properties": {
    "addr:full":"1432 Mona Passage Ct New Bern NC 28560",
    "addr:housenumber":"1432",
    "addr:postcode":"nc 28560",
    "addr:street":"Mona Passage Ct",
    "iso:country":"US",
    "sg:address":"1432 Mona Passage Ct",
    "sg:city":"New Bern",
    "sg:classifiers":[
        {
            "category":"Professional",
            "subcategory":"Engineering",
            "type":"Services"
        }
    ],
    "sg:phone":"+1 252 637 7988",
    "sg:postcode":"28560",
    "sg:province":"NC",
    "sg:tags":[
        "engineer"
    ],
    "wof:name":"Us Asphalt Engineering Svc",
    "wof:placetype":"venue"
},
  "geometry": {"coordinates":[-76.956485,35.083038],"type":"Point"}
}