{
  "type": "Feature",
  "properties": {
    "iso:country":"US",
    "sg:address":"700 Forest Point Cir # 116",
    "sg:city":"Charlotte",
    "sg:classifiers":[
        {
            "category":"Professional",
            "subcategory":"Engineering",
            "type":"Services"
        }
    ],
    "sg:phone":"+1 704 527 2535",
    "sg:postcode":"28273",
    "sg:province":"NC",
    "sg:tags":[
        "civil",
        "consulting",
        "engineer"
    ],
    "sg:website":"http://www.taylorwiseman.com",
    "wof:name":"Taylor Wiseman & Taylor",
    "wof:placetype":"venue"
},
  "geometry": {"coordinates":[-80.904937,35.131111],"type":"Point"}
}