{
  "type": "Feature",
  "properties": {
    "addr:full":"1435 Perch Rd Pinnacle NC 27043",
    "addr:housenumber":"1435",
    "addr:postcode":"27043",
    "addr:street":"Perch Rd",
    "iso:country":"US",
    "sg:address":"1435 Perch Rd",
    "sg:city":"Pinnacle",
    "sg:classifiers":[
        {
            "category":"Professional",
            "type":"Services"
        },
        {
            "category":"Restaurant",
            "type":"Food & Drink"
        }
    ],
    "sg:phone":"+1 336 368 5559",
    "sg:postcode":"27043",
    "sg:province":"NC",
    "sg:tags":[
        "sandwich"
    ],
    "wof:name":"Trails and Grills",
    "wof:placetype":"venue"
},
  "geometry": {"coordinates":[-80.43682,36.31866],"type":"Point"}
}