{
  "type": "Feature",
  "properties": {
    "addr:full":"421 Statesville Blvd Salisbury NC 28144",
    "addr:housenumber":"421",
    "addr:postcode":"28144",
    "addr:street":"Statesville Blvd",
    "iso:country":"US",
    "sg:address":"421 Statesville Blvd",
    "sg:city":"Salisbury",
    "sg:classifiers":[
        {
            "category":"Banks & Credit Unions",
            "subcategory":"Investment Brokerage",
            "type":"Services"
        }
    ],
    "sg:phone":"+1 704 637 2700",
    "sg:postcode":"28144",
    "sg:province":"NC",
    "sg:tags":[
        "advisory"
    ],
    "wof:name":"Linsco Private Ledger",
    "wof:placetype":"venue"
},
  "geometry": {"coordinates":[-80.48997900000001,35.688395],"type":"Point"}
}