{
  "type": "Feature",
  "properties": {
    "addr:full":"834 Cherokee Rd Charlotte NC 28207",
    "addr:housenumber":"834",
    "addr:postcode":"28207",
    "addr:street":"Cherokee Rd",
    "iso:country":"US",
    "sg:address":"834 Cherokee Rd",
    "sg:city":"Charlotte",
    "sg:classifiers":[
        {
            "category":"Real Estate",
            "subcategory":"Real Estate Operator",
            "type":"Services"
        }
    ],
    "sg:phone":"+1 704 332 7416",
    "sg:postcode":"28207",
    "sg:province":"NC",
    "sg:tags":[
        "building",
        "nonresidential"
    ],
    "wof:name":"Medtrout Properties LLC",
    "wof:placetype":"venue"
},
  "geometry": {"coordinates":[-80.82415899999999,35.192234],"type":"Point"}
}