{
  "type": "Feature",
  "properties": {
    "iso:country":"US",
    "sg:address":"7212 Madiera Ct",
    "sg:city":"Raleigh",
    "sg:classifiers":[
        {
            "category":"Professional",
            "type":"Services"
        }
    ],
    "sg:phone":"+1 919 847 8780",
    "sg:postcode":"27615",
    "sg:province":"NC",
    "wof:name":"Shout Hallelujah Company Chef",
    "wof:placetype":"venue"
},
  "geometry": {"coordinates":[-78.62285,35.890631],"type":"Point"}
}