{
  "type": "Feature",
  "properties": {
    "iso:country":"US",
    "sg:address":"2450 Banner Elk Hwy",
    "sg:city":"Banner Elk",
    "sg:classifiers":[
        {
            "category":"Recreation",
            "type":"Entertainment"
        }
    ],
    "sg:phone":"+1 828 898 9885",
    "sg:postcode":"28604",
    "sg:province":"NC",
    "sg:tags":[
        "guide"
    ],
    "wof:name":"Lost Cove Trekking",
    "wof:placetype":"venue"
},
  "geometry": {"coordinates":[-81.915817,36.17314],"type":"Point"}
}