{
  "type": "Feature",
  "properties": {
    "iso:country":"US",
    "sg:address":"3457 Hillsborough Rd",
    "sg:city":"Durham",
    "sg:classifiers":[
        {
            "category":"Food & Beverages",
            "subcategory":"Groceries & Convenience Stores",
            "type":"Retail Goods"
        }
    ],
    "sg:phone":"+1 919 383 2249",
    "sg:postcode":"27705",
    "sg:province":"NC",
    "sg:tags":[
        "supermarket"
    ],
    "wof:name":"Kroger",
    "wof:placetype":"venue"
},
  "geometry": {"coordinates":[-78.94829900000001,36.020092],"type":"Point"}
}