{
  "type": "Feature",
  "properties": {
    "addr:full":"638 Shawnee Trl Wilmington NC 28412",
    "addr:housenumber":"638",
    "addr:postcode":"28412",
    "addr:street":"Shawnee Trl",
    "iso:country":"US",
    "sg:address":"638 Shawnee Trl",
    "sg:city":"Wilmington",
    "sg:classifiers":[
        {
            "category":"Building & Trades",
            "subcategory":"Construction",
            "type":"Services"
        }
    ],
    "sg:phone":"+1 910 791 0777",
    "sg:postcode":"28412",
    "sg:province":"NC",
    "sg:tags":[
        "contractor",
        "carpentry"
    ],
    "wof:name":"Atlantic Coastal Enterprises",
    "wof:placetype":"venue"
},
  "geometry": {"coordinates":[-77.91673900000001,34.1464],"type":"Point"}
}