{
  "type": "Feature",
  "properties": {
    "iso:country":"US",
    "sg:address":"2001 Castle St",
    "sg:city":"Wilmington",
    "sg:classifiers":[
        {
            "category":"Building & Trades",
            "subcategory":"Electrical",
            "type":"Services"
        }
    ],
    "sg:phone":"+1 910 762 1001",
    "sg:postcode":"28403",
    "sg:province":"NC",
    "sg:tags":[
        "electric",
        "contractor"
    ],
    "wof:name":"C W Harrelson Electric",
    "wof:placetype":"venue"
},
  "geometry": {"coordinates":[-77.922736,34.229848],"type":"Point"}
}