{
  "type": "Feature",
  "properties": {
    "addr:full":"127 Aurora Dr Asheville NC 28805",
    "addr:housenumber":"127",
    "addr:postcode":"28805",
    "addr:street":"Aurora Dr",
    "iso:country":"US",
    "sg:address":"127 Aurora Dr",
    "sg:city":"Asheville",
    "sg:classifiers":[
        {
            "category":"Professional",
            "subcategory":"Management & Consulting",
            "type":"Services"
        }
    ],
    "sg:phone":"+1   ",
    "sg:postcode":"28805",
    "sg:province":"NC",
    "sg:tags":[
        "business"
    ],
    "wof:name":"Bristol Engineering",
    "wof:placetype":"venue"
},
  "geometry": {"coordinates":[-82.535718,35.586034],"type":"Point"}
}