{
  "type": "Feature",
  "properties": {
    "addr:full":"5211 Weddington Rd Monroe NC 28110",
    "addr:housenumber":"5211",
    "addr:postcode":"28110",
    "addr:street":"Weddington Rd",
    "iso:country":"US",
    "sg:address":"5211 Weddington Rd",
    "sg:city":"Monroe",
    "sg:classifiers":[
        {
            "category":"Organizations",
            "subcategory":"Membership Organization",
            "type":"Services"
        }
    ],
    "sg:phone":"+1 704 821 4498",
    "sg:postcode":"28110",
    "sg:province":"NC",
    "sg:tags":[
        "athletic"
    ],
    "wof:name":"Weddington Athletic Assn",
    "wof:placetype":"venue"
},
  "geometry": {"coordinates":[-80.65328,35.004844],"type":"Point"}
}