{
  "type": "Feature",
  "properties": {
    "addr:full":"2016 W Vernon Ave Kinston NC 28504",
    "addr:housenumber":"2016",
    "addr:postcode":"28504",
    "addr:street":"W Vernon Ave",
    "iso:country":"US",
    "sg:address":"2016 W Vernon Ave",
    "sg:city":"Kinston",
    "sg:classifiers":[
        {
            "category":"Shopping",
            "subcategory":"Used Merchandise",
            "type":"Retail Goods"
        }
    ],
    "sg:phone":"+1 252 527 9398",
    "sg:postcode":"28504",
    "sg:province":"NC",
    "sg:tags":[
        "furniture"
    ],
    "wof:name":"Kinston Used Furniture",
    "wof:placetype":"venue"
},
  "geometry": {"coordinates":[-77.611193,35.269832],"type":"Point"}
}