{
  "type": "Feature",
  "properties": {
    "iso:country":"US",
    "sg:address":"390 Raleigh Rd",
    "sg:city":"Henderson",
    "sg:classifiers":[
        {
            "category":"Autos & Motor Vehicles",
            "subcategory":"Auto Supplies",
            "type":"Retail Goods"
        }
    ],
    "sg:phone":"+1 252 438 2049",
    "sg:postcode":"27536",
    "sg:province":"NC",
    "sg:tags":[
        "automobile",
        "parts"
    ],
    "sg:website":"www.advanceautoparts.com",
    "wof:name":"Advance Auto Parts Inc",
    "wof:placetype":"venue"
},
  "geometry": {"coordinates":[-78.41094699999999,36.316823],"type":"Point"}
}