{
  "type": "Feature",
  "properties": {
    "addr:full":"106 Trinity Rd Statesville NC 28625",
    "addr:housenumber":"106",
    "addr:postcode":"28625",
    "addr:street":"Trinity Rd",
    "iso:country":"US",
    "sg:address":"106 Trinity Rd",
    "sg:city":"Statesville",
    "sg:classifiers":[
        {
            "category":"Organizations",
            "subcategory":"Religious Organization",
            "type":"Services"
        }
    ],
    "sg:phone":"+1 704 876 0053",
    "sg:postcode":"28625",
    "sg:province":"NC",
    "wof:name":"Trinity United Methdst Church",
    "wof:placetype":"venue"
},
  "geometry": {"coordinates":[-80.951902,35.86268],"type":"Point"}
}