{
  "type": "Feature",
  "properties": {
    "iso:country":"US",
    "sg:address":"210 N Whitted St",
    "sg:city":"Hendersonville",
    "sg:classifiers":[
        {
            "category":"Organizations",
            "subcategory":"Religious Organization",
            "type":"Services"
        }
    ],
    "sg:phone":"+1 828 693 5119",
    "sg:postcode":"28739",
    "sg:province":"NC",
    "sg:tags":[
        "church"
    ],
    "wof:name":"Star Of Bethel Baptist Church",
    "wof:placetype":"venue"
},
  "geometry": {"coordinates":[-82.47094199999999,35.313169],"type":"Point"}
}