{
  "type": "Feature",
  "properties": {
    "iso:country":"US",
    "sg:address":"717 Ward Blvd",
    "sg:city":"Wilson",
    "sg:classifiers":[
        {
            "category":"Banks & Credit Unions",
            "subcategory":"Bank",
            "type":"Services"
        }
    ],
    "sg:phone":"+1 252 291 8850",
    "sg:postcode":"27893",
    "sg:province":"NC",
    "sg:tags":[
        "financing"
    ],
    "wof:name":"National Finance Co",
    "wof:placetype":"venue"
},
  "geometry": {"coordinates":[-77.933232,35.715615],"type":"Point"}
}