{
  "type": "Feature",
  "properties": {
    "iso:country":"US",
    "sg:address":"209 Boyette St",
    "sg:city":"Murfreesboro",
    "sg:classifiers":[
        {
            "category":"Organizations",
            "subcategory":"Religious Organization",
            "type":"Services"
        }
    ],
    "sg:phone":"+1 252 398 4775",
    "sg:postcode":"27855",
    "sg:province":"NC",
    "sg:tags":[
        "church"
    ],
    "wof:name":"First Baptist Church",
    "wof:placetype":"venue"
},
  "geometry": {"coordinates":[-77.085334,36.44248],"type":"Point"}
}