{
  "type": "Feature",
  "properties": {
    "addr:full":"2612 N Duke St Durham NC 27704",
    "addr:housenumber":"2612",
    "addr:postcode":"27704",
    "addr:street":"N Duke St",
    "iso:country":"US",
    "sg:address":"2612 N Duke St",
    "sg:city":"Durham",
    "sg:classifiers":[
        {
            "category":"Government",
            "subcategory":"Office",
            "type":"Public Place"
        }
    ],
    "sg:phone":"+1 919 560 6851",
    "sg:postcode":"27704",
    "sg:province":"NC",
    "sg:tags":[
        "div",
        "district",
        "hwy"
    ],
    "wof:name":"Division 5 Office",
    "wof:placetype":"venue"
},
  "geometry": {"coordinates":[-78.905451,36.031968],"type":"Point"}
}