{
  "type": "Feature",
  "properties": {
    "iso:country":"US",
    "sg:address":"113 N Elliott St",
    "sg:city":"Elizabeth City",
    "sg:classifiers":[
        {
            "category":"Government",
            "subcategory":"Jail",
            "type":"Public Place"
        }
    ],
    "sg:phone":"+1 252 331 4759",
    "sg:postcode":"27909",
    "sg:province":"NC",
    "sg:tags":[
        "govt",
        "state",
        "institution"
    ],
    "wof:name":"Juvenile Probation Ofc",
    "wof:placetype":"venue"
},
  "geometry": {"coordinates":[-76.222887,36.300782],"type":"Point"}
}