{
  "type": "Feature",
  "properties": {
    "iso:country":"US",
    "sg:address":"3801 Merton Dr",
    "sg:city":"Raleigh",
    "sg:classifiers":[
        {
            "category":"Building & Trades",
            "subcategory":"Construction",
            "type":"Services"
        }
    ],
    "sg:phone":"+1 919 786 0433",
    "sg:postcode":"27609",
    "sg:province":"NC",
    "sg:tags":[
        "house"
    ],
    "wof:name":"Jerry Wagoner Builder Inc",
    "wof:placetype":"venue"
},
  "geometry": {"coordinates":[-78.63155399999999,35.830966],"type":"Point"}
}