{
  "type": "Feature",
  "properties": {
    "iso:country":"US",
    "sg:address":"3109 Braddock Dr",
    "sg:city":"Raleigh",
    "sg:classifiers":[
        {
            "category":"Health Services",
            "subcategory":"Doctor",
            "type":"Services"
        }
    ],
    "sg:phone":"+1 919 782 6004",
    "sg:postcode":"27612",
    "sg:province":"NC",
    "wof:name":"Scott Harry W MD",
    "wof:placetype":"venue"
},
  "geometry": {"coordinates":[-78.69059799999999,35.865101],"type":"Point"}
}