{
  "type": "Feature",
  "properties": {
    "iso:country":"US",
    "sg:address":"119 W Union St",
    "sg:city":"Morganton",
    "sg:classifiers":[
        {
            "category":"Personal",
            "subcategory":"Beauty Salon",
            "type":"Services"
        }
    ],
    "sg:phone":"+1   ",
    "sg:postcode":"28655",
    "sg:province":"NC",
    "sg:tags":[
        "shop"
    ],
    "wof:name":"Elite Hair Styling",
    "wof:placetype":"venue"
},
  "geometry": {"coordinates":[-81.688181,35.745368],"type":"Point"}
}