{
  "type": "Feature",
  "properties": {
    "addr:full":"2501 N Tryon St Charlotte NC 28206",
    "addr:housenumber":"2501",
    "addr:postcode":"28206",
    "addr:street":"N Tryon St",
    "iso:country":"US",
    "sg:address":"2501 N Tryon St",
    "sg:city":"Charlotte",
    "sg:phone":"+1 704 332 2022",
    "sg:postcode":"28206",
    "sg:province":"NC",
    "sg:website":"http://www.bojangles.com",
    "wof:name":"Bojangles' Restaurant",
    "wof:placetype":"venue"
},
  "geometry": {"coordinates":[-80.817909,35.247131],"type":"Point"}
}