{
  "type": "Feature",
  "properties": {
    "iso:country":"US",
    "sg:address":"220 S Main St",
    "sg:city":"Staley",
    "sg:classifiers":[
        {
            "category":"Government",
            "subcategory":"Office",
            "type":"Public Place"
        }
    ],
    "sg:phone":"+1 336 622 3030",
    "sg:postcode":"27355",
    "sg:province":"NC",
    "sg:tags":[
        "city"
    ],
    "wof:name":"Staley Town Hall",
    "wof:placetype":"venue"
},
  "geometry": {"coordinates":[-79.55202,35.794714],"type":"Point"}
}