{
  "type": "Feature",
  "properties": {
    "iso:country":"US",
    "sg:address":"333 Merrimon Ave",
    "sg:city":"Asheville",
    "sg:classifiers":[
        {
            "category":"Food & Beverages",
            "subcategory":"Bakery",
            "type":"Retail Goods"
        }
    ],
    "sg:phone":"+1 828 254 2345",
    "sg:postcode":"28801",
    "sg:province":"NC",
    "sg:tags":[
        "bagel"
    ],
    "wof:name":"New York Bagels",
    "wof:placetype":"venue"
},
  "geometry": {"coordinates":[-82.554633,35.61024],"type":"Point"}
}