{
  "type": "Feature",
  "properties": {
    "addr:full":"12 East Rd Pittsboro NC 27312",
    "addr:housenumber":"12",
    "addr:postcode":"27312",
    "addr:street":"East Rd",
    "iso:country":"US",
    "sg:address":"12 East Rd",
    "sg:city":"Pittsboro",
    "sg:classifiers":[
        {
            "category":"Government",
            "subcategory":"Office",
            "type":"Public Place"
        }
    ],
    "sg:phone":"+1 919 542 8210",
    "sg:postcode":"27312",
    "sg:province":"NC",
    "wof:name":"Chatham County Finance",
    "wof:placetype":"venue"
},
  "geometry": {"coordinates":[-79.183893,35.773269],"type":"Point"}
}