{
  "type": "Feature",
  "properties": {
    "iso:country":"US",
    "sg:address":"444 Joe Brown Hwy N",
    "sg:city":"Chadbourn",
    "sg:classifiers":[
        {
            "category":"Retail",
            "subcategory":"Laundry & Dry Cleaning",
            "type":"Services"
        }
    ],
    "sg:phone":"+1 910 654 0100",
    "sg:postcode":"28431",
    "sg:province":"NC",
    "wof:name":"Flea Market Wash & Dry",
    "wof:placetype":"venue"
},
  "geometry": {"coordinates":[-78.827093,34.341987],"type":"Point"}
}