{
  "type": "Feature",
  "properties": {
    "addr:full":"39 Pomeroy Dr Pinehurst NC 28374",
    "addr:housenumber":"39",
    "addr:postcode":"28374",
    "addr:street":"Pomeroy Dr",
    "iso:country":"US",
    "sg:address":"39 Pomeroy Dr",
    "sg:city":"Pinehurst",
    "sg:classifiers":[
        {
            "category":"Manufacturing",
            "subcategory":"Leather Goods",
            "type":"Manufacturing & Wholesale Goods"
        }
    ],
    "sg:phone":"+1 910 255 0266",
    "sg:postcode":"28374",
    "sg:province":"NC",
    "sg:tags":[
        "mfg",
        "saddle"
    ],
    "wof:name":"Dg Stackhouse English Saddle M",
    "wof:placetype":"venue"
},
  "geometry": {"coordinates":[-79.513497,35.197364],"type":"Point"}
}