{
  "type": "Feature",
  "properties": {
    "addr:full":"1800 Four Seasons Blvd Hendersonville NC 28792",
    "addr:housenumber":"1800",
    "addr:postcode":"28792",
    "addr:street":"Four Seasons Blvd",
    "iso:country":"US",
    "sg:address":"1800 Four Seasons Blvd",
    "sg:city":"Hendersonville",
    "sg:classifiers":[
        {
            "category":"Banks & Credit Unions",
            "subcategory":"Bank",
            "type":"Services"
        }
    ],
    "sg:phone":"+1 828 697 2227",
    "sg:postcode":"28792",
    "sg:province":"NC",
    "sg:tags":[
        "machine",
        "teller",
        "automated"
    ],
    "wof:name":"Atm USA LLC",
    "wof:placetype":"venue"
},
  "geometry": {"coordinates":[-82.446693,35.335823],"type":"Point"}
}