{
  "type": "Feature",
  "properties": {
    "addr:full":"1847 Andrews Chapel Rd Roseboro NC 28382",
    "addr:housenumber":"1847",
    "addr:postcode":"28382",
    "addr:street":"Andrews Chapel Rd",
    "iso:country":"US",
    "sg:address":"1847 Andrews Chapel Rd",
    "sg:city":"Roseboro",
    "sg:classifiers":[
        {
            "category":"Farming",
            "subcategory":"Farm",
            "type":"Manufacturing & Wholesale Goods"
        }
    ],
    "sg:phone":"+1 910 564 4664",
    "sg:postcode":"28382",
    "sg:province":"NC",
    "wof:name":"F & W Farms",
    "wof:placetype":"venue"
},
  "geometry": {"coordinates":[-78.479193,34.931383],"type":"Point"}
}