{
  "type": "Feature",
  "properties": {
    "addr:full":"415 N Boundary St Raleigh NC 27604",
    "addr:housenumber":"415",
    "addr:postcode":"27604",
    "addr:street":"N Boundary St",
    "iso:country":"US",
    "sg:address":"415 N Boundary St",
    "sg:city":"Raleigh",
    "sg:classifiers":[
        {
            "category":"Shopping",
            "subcategory":"Florist",
            "type":"Retail Goods"
        }
    ],
    "sg:phone":"+1 919 839 5758",
    "sg:postcode":"27604",
    "sg:province":"NC",
    "sg:tags":[
        "vegetable",
        "gift",
        "arrangement",
        "floral",
        "fruit",
        "basket",
        "market"
    ],
    "wof:name":"Lucias Fruit Baskets & Gourmet",
    "wof:placetype":"venue"
},
  "geometry": {"coordinates":[-78.632633,35.788048],"type":"Point"}
}