{
  "type": "Feature",
  "properties": {
    "addr:full":"3926 New Garden Park Greensboro NC 27410",
    "addr:housenumber":"3926",
    "addr:postcode":"27410",
    "addr:street":"New Garden Park",
    "iso:country":"US",
    "sg:address":"3926 New Garden Park",
    "sg:city":"Greensboro",
    "sg:classifiers":[
        {
            "category":"Professional",
            "subcategory":"Business Services",
            "type":"Services"
        }
    ],
    "sg:phone":"+1   ",
    "sg:postcode":"27410",
    "sg:province":"NC",
    "wof:name":"Simple Pleasures Design Group",
    "wof:placetype":"venue"
},
  "geometry": {"coordinates":[-79.850337,36.131767],"type":"Point"}
}