{
  "type": "Feature",
  "properties": {
    "addr:full":"3300 Lake Shore Rd S Denver NC 28037",
    "addr:housenumber":"3300",
    "addr:postcode":"28037",
    "addr:street":"Lake Shore Rd",
    "iso:country":"US",
    "sg:address":"3300 Lake Shore Rd S",
    "sg:city":"Denver",
    "sg:classifiers":[
        {
            "category":"Food & Beverages",
            "subcategory":"Groceries & Convenience Stores",
            "type":"Retail Goods"
        },
        {
            "category":"Real Estate",
            "subcategory":"Real Estate Agent",
            "type":"Services"
        }
    ],
    "sg:phone":"+1 704 483 9999",
    "sg:postcode":"28037",
    "sg:province":"NC",
    "sg:tags":[
        "inspection"
    ],
    "wof:name":"Safeway Home Inspections LLC",
    "wof:placetype":"venue"
},
  "geometry": {"coordinates":[-80.977355,35.500867],"type":"Point"}
}