{
  "type": "Feature",
  "properties": {
    "iso:country":"US",
    "sg:address":"3105 Plain View Hwy",
    "sg:city":"Dunn",
    "sg:classifiers":[
        {
            "category":"Social Services",
            "subcategory":"Child Care",
            "type":"Services"
        }
    ],
    "sg:phone":"+1 910 892 9500",
    "sg:postcode":"28334",
    "sg:province":"NC",
    "wof:name":"Countryside Day Care",
    "wof:placetype":"venue"
},
  "geometry": {"coordinates":[-78.522407,35.228143],"type":"Point"}
}