{
  "type": "Feature",
  "properties": {
    "addr:full":"8905 Laurelwood Ln Waxhaw NC 28173",
    "addr:housenumber":"8905",
    "addr:postcode":"28173",
    "addr:street":"Laurelwood Ln",
    "iso:country":"US",
    "sg:address":"8905 Laurelwood Ln",
    "sg:city":"Waxhaw",
    "sg:classifiers":[
        {
            "category":"Bars & Pubs",
            "type":"Food & Drink"
        }
    ],
    "sg:phone":"+1 704 843 4456",
    "sg:postcode":"28173",
    "sg:province":"NC",
    "sg:tags":[
        "drinking"
    ],
    "wof:name":"ME Sports Bar Inc",
    "wof:placetype":"venue"
},
  "geometry": {"coordinates":[-80.790379,34.956428],"type":"Point"}
}