{
  "type": "Feature",
  "properties": {
    "addr:full":"912 Dixie St Lexington NC 27292",
    "addr:housenumber":"912",
    "addr:postcode":"27292",
    "addr:street":"Dixie St",
    "iso:country":"US",
    "sg:address":"912 Dixie St",
    "sg:city":"Lexington",
    "sg:classifiers":[
        {
            "category":"Organizations",
            "subcategory":"Religious Organization",
            "type":"Services"
        }
    ],
    "sg:phone":"+1 336 249 7134",
    "sg:postcode":"27292",
    "sg:province":"NC",
    "sg:tags":[
        "church"
    ],
    "wof:name":"Lexington Deliverance Tbrncl",
    "wof:placetype":"venue"
},
  "geometry": {"coordinates":[-80.26134,35.802466],"type":"Point"}
}