{
  "type": "Feature",
  "properties": {
    "iso:country":"US",
    "sg:address":"2505 Burch Pt",
    "sg:city":"High Point",
    "sg:classifiers":[
        {
            "category":"Shopping",
            "subcategory":"Used Merchandise",
            "type":"Retail Goods"
        },
        {
            "category":"Professional",
            "subcategory":"Business Services",
            "type":"Services"
        }
    ],
    "sg:phone":"+1 336 887 6389",
    "sg:postcode":"27265",
    "sg:province":"NC",
    "sg:tags":[
        "apparel",
        "design",
        "fashion",
        "clothing"
    ],
    "wof:name":"Amerisource Alliance Inc",
    "wof:placetype":"venue"
},
  "geometry": {"coordinates":[-79.998824,36.022084],"type":"Point"}
}