{
  "type": "Feature",
  "properties": {
    "iso:country":"US",
    "sg:address":"1508 N Main St",
    "sg:city":"Fuquay Varina",
    "sg:classifiers":[
        {
            "category":"Home & Garden",
            "subcategory":"Garden Supply",
            "type":"Retail Goods"
        }
    ],
    "sg:phone":"+1 919 552 0590",
    "sg:postcode":"27526",
    "sg:province":"NC",
    "sg:tags":[
        "center"
    ],
    "wof:name":"Garden Hut",
    "wof:placetype":"venue"
},
  "geometry": {"coordinates":[-78.76315099999999,35.59545],"type":"Point"}
}