{
  "type": "Feature",
  "properties": {
    "iso:country":"US",
    "sg:address":"386 Lee Layne Rd",
    "sg:city":"Ramseur",
    "sg:classifiers":[
        {
            "category":"Autos & Motor Vehicles",
            "subcategory":"Automobile Sales",
            "type":"Retail Goods"
        }
    ],
    "sg:phone":"+1 336 824 2026",
    "sg:postcode":"27316",
    "sg:province":"NC",
    "sg:tags":[
        "truck"
    ],
    "wof:name":"D J Sales-Truck & Equipment",
    "wof:placetype":"venue"
},
  "geometry": {"coordinates":[-79.618555,35.740802],"type":"Point"}
}