{
  "type": "Feature",
  "properties": {
    "iso:country":"US",
    "sg:address":"1298 Mark Twain Rd",
    "sg:city":"Charlotte",
    "sg:classifiers":[
        {
            "category":"Cafe",
            "type":"Food & Drink"
        }
    ],
    "sg:menulink":"http://www.allmenus.com/nc/charlotte/34810-wild-wing-cafe/menu/",
    "sg:phone":"+1 980 297 7000",
    "sg:postcode":"28213",
    "sg:province":"NC",
    "sg:tags":[
        "american"
    ],
    "wof:name":"Wild Wing Cafe",
    "wof:placetype":"venue"
},
  "geometry": {"coordinates":[-80.73340399999999,35.29875],"type":"Point"}
}