{
  "type": "Feature",
  "properties": {
    "addr:full":"7981 Rennert Rd Shannon NC 28386",
    "addr:housenumber":"7981",
    "addr:postcode":"28386",
    "addr:street":"Rennert Rd",
    "iso:country":"US",
    "sg:address":"7981 Rennert Rd",
    "sg:city":"Shannon",
    "sg:classifiers":[
        {
            "category":"Building & Trades",
            "subcategory":"Construction",
            "type":"Services"
        }
    ],
    "sg:phone":"+1 910 359 0009",
    "sg:postcode":"28386",
    "sg:province":"NC",
    "sg:tags":[
        "general",
        "contractor"
    ],
    "wof:name":"D & A Complete Constr Inc",
    "wof:placetype":"venue"
},
  "geometry": {"coordinates":[-79.0703,34.783407],"type":"Point"}
}