{
  "type": "Feature",
  "properties": {
    "iso:country":"US",
    "sg:address":"111 Ward St",
    "sg:city":"Cary",
    "sg:classifiers":[
        {
            "category":"Social Services",
            "type":"Services"
        }
    ],
    "sg:phone":"+1 919 462 3450",
    "sg:postcode":"27511",
    "sg:province":"NC",
    "sg:tags":[
        "elementary",
        "school"
    ],
    "sg:website":"www.pitterpatters.net",
    "wof:name":"Pitter Patters",
    "wof:placetype":"venue"
},
  "geometry": {"coordinates":[-78.773697,35.789398],"type":"Point"}
}