{
  "type": "Feature",
  "properties": {
    "iso:country":"US",
    "sg:address":"4011 Capital Blvd",
    "sg:city":"Raleigh",
    "sg:classifiers":[
        {
            "category":"Restaurant",
            "type":"Food & Drink"
        }
    ],
    "sg:phone":"+1 919 954 2295",
    "sg:postcode":"27604",
    "sg:province":"NC",
    "sg:tags":[
        "eating"
    ],
    "wof:name":"Christins Cafeteria",
    "wof:placetype":"venue"
},
  "geometry": {"coordinates":[-78.581726,35.836041],"type":"Point"}
}