{
  "type": "Feature",
  "properties": {
    "addr:full":"8817 Lomas Ct Raleigh NC 27615",
    "addr:housenumber":"8817",
    "addr:postcode":"27615",
    "addr:street":"Lomas Ct",
    "iso:country":"US",
    "sg:address":"8817 Lomas Ct",
    "sg:city":"Raleigh",
    "sg:classifiers":[
        {
            "category":"Insurance",
            "subcategory":"Insurance Agent",
            "type":"Services"
        }
    ],
    "sg:phone":"+1 919 846 0768",
    "sg:postcode":"27615",
    "sg:province":"NC",
    "wof:name":"AFLAC",
    "wof:placetype":"venue"
},
  "geometry": {"coordinates":[-78.609954,35.903635],"type":"Point"}
}