{
  "type": "Feature",
  "properties": {
    "addr:full":"109 N 7th St Mebane NC 27302",
    "addr:housenumber":"109",
    "addr:postcode":"27302",
    "addr:street":"N 7Th St",
    "iso:country":"US",
    "sg:address":"109 N 7th St",
    "sg:city":"Mebane",
    "sg:classifiers":[
        {
            "category":"Manufacturing",
            "subcategory":"Apparel",
            "type":"Manufacturing & Wholesale Goods"
        }
    ],
    "sg:phone":"+1 919 563 1082",
    "sg:postcode":"27302",
    "sg:province":"NC",
    "wof:name":"Carolina Threadworx",
    "wof:placetype":"venue"
},
  "geometry": {"coordinates":[-79.26343799999999,36.095685],"type":"Point"}
}