{
  "type": "Feature",
  "properties": {
    "addr:full":"108 W Gold St Kings Mountain NC 28086",
    "addr:housenumber":"108",
    "addr:postcode":"28086",
    "addr:street":"W Gold St",
    "iso:country":"US",
    "sg:address":"108 W Gold St",
    "sg:city":"Kings Mountain",
    "sg:classifiers":[
        {
            "category":"Food & Beverages",
            "subcategory":"Groceries & Convenience Stores",
            "type":"Retail Goods"
        }
    ],
    "sg:phone":"+1 704 734 1207",
    "sg:postcode":"28086",
    "sg:province":"NC",
    "sg:tags":[
        "grocer"
    ],
    "wof:name":"Super Discount Grocery",
    "wof:placetype":"venue"
},
  "geometry": {"coordinates":[-81.34314500000001,35.237682],"type":"Point"}
}