{
  "type": "Feature",
  "properties": {
    "iso:country":"US",
    "sg:address":"9198 Amis Chapel Rd",
    "sg:city":"Oxford",
    "sg:classifiers":[
        {
            "category":"Organizations",
            "subcategory":"Religious Organization",
            "type":"Services"
        }
    ],
    "sg:phone":"+1 919 693 3193",
    "sg:postcode":"27565",
    "sg:province":"NC",
    "sg:tags":[
        "church"
    ],
    "wof:name":"Amis Chapel Baptist Church",
    "wof:placetype":"venue"
},
  "geometry": {"coordinates":[-78.733002,36.520319],"type":"Point"}
}