{
  "type": "Feature",
  "properties": {
    "iso:country":"US",
    "sg:address":"2001 Baysdale Ln",
    "sg:city":"Apex",
    "sg:classifiers":[
        {
            "category":"Professional",
            "subcategory":"Employment Agencies",
            "type":"Services"
        }
    ],
    "sg:phone":"+1 919 303 5222",
    "sg:postcode":"27523",
    "sg:province":"NC",
    "wof:name":"Dibari Associates Inc",
    "wof:placetype":"venue"
},
  "geometry": {"coordinates":[-78.867189,35.763349],"type":"Point"}
}