{
  "type": "Feature",
  "properties": {
    "iso:country":"US",
    "sg:address":"8406 Creeks Edge Ct",
    "sg:city":"Oak Ridge",
    "sg:classifiers":[
        {
            "category":"Professional",
            "subcategory":"Engineering",
            "type":"Services"
        }
    ],
    "sg:phone":"+1   ",
    "sg:postcode":"27310",
    "sg:province":"NC",
    "wof:name":"Wright & Associates",
    "wof:placetype":"venue"
},
  "geometry": {"coordinates":[-79.986937,36.190242],"type":"Point"}
}