{
  "type": "Feature",
  "properties": {
    "iso:country":"US",
    "sg:address":"1308 Sherri St",
    "sg:city":"Greenville",
    "sg:classifiers":[
        {
            "category":"Building & Trades",
            "subcategory":"Landscaping Services",
            "type":"Services"
        }
    ],
    "sg:phone":"+1 252 830 1490",
    "sg:postcode":"27834",
    "sg:province":"NC",
    "wof:name":"Roberson Tree Ser",
    "wof:placetype":"venue"
},
  "geometry": {"coordinates":[-77.455724,35.605367],"type":"Point"}
}