{
  "type": "Feature",
  "properties": {
    "iso:country":"US",
    "sg:address":"611 Spartanburg Hwy",
    "sg:city":"Hendersonville",
    "sg:classifiers":[
        {
            "category":"Retail",
            "subcategory":"Repair Shop",
            "type":"Services"
        }
    ],
    "sg:phone":"+1 828 692 1037",
    "sg:postcode":"28792",
    "sg:province":"NC",
    "sg:tags":[
        "appliance"
    ],
    "wof:name":"Harding & Son Appliances",
    "wof:placetype":"venue"
},
  "geometry": {"coordinates":[-82.45762999999999,35.307226],"type":"Point"}
}