{
  "type": "Feature",
  "properties": {
    "iso:country":"US",
    "sg:address":"1512 Ivy Ln",
    "sg:city":"Raleigh",
    "sg:classifiers":[
        {
            "category":"Building & Trades",
            "subcategory":"Construction",
            "type":"Services"
        }
    ],
    "sg:phone":"+1 919 850 0056",
    "sg:postcode":"27609",
    "sg:province":"NC",
    "sg:tags":[
        "house"
    ],
    "wof:name":"J L III Builders",
    "wof:placetype":"venue"
},
  "geometry": {"coordinates":[-78.614456,35.855485],"type":"Point"}
}