{
  "type": "Feature",
  "properties": {
    "iso:country":"US",
    "sg:address":"25589 US Hwy 17",
    "sg:city":"Hampstead",
    "sg:classifiers":[
        {
            "category":"Autos & Motor Vehicles",
            "subcategory":"Auto Supplies",
            "type":"Retail Goods"
        }
    ],
    "sg:phone":"+1 910 329 6312",
    "sg:postcode":"28443",
    "sg:province":"NC",
    "sg:tags":[
        "tire"
    ],
    "wof:name":"A C Tire Clinic",
    "wof:placetype":"venue"
},
  "geometry": {"coordinates":[-77.576233,34.476116],"type":"Point"}
}