{
  "type": "Feature",
  "properties": {
    "iso:country":"US",
    "sg:address":"3371 Battleground Ave",
    "sg:city":"Greensboro",
    "sg:classifiers":[
        {
            "category":"Personal",
            "subcategory":"Beauty Salon",
            "type":"Services"
        }
    ],
    "sg:phone":"+1 336 288 3667",
    "sg:postcode":"27410",
    "sg:province":"NC",
    "wof:name":"Leon's Style Salons",
    "wof:placetype":"venue"
},
  "geometry": {"coordinates":[-79.84502500000001,36.122038],"type":"Point"}
}