{
  "type": "Feature",
  "properties": {
    "iso:country":"US",
    "sg:address":"559 Highlands Rd",
    "sg:city":"Franklin",
    "sg:classifiers":[
        {
            "category":"Recreation",
            "type":"Entertainment"
        }
    ],
    "sg:phone":"+1 828 349 3346",
    "sg:postcode":"28734",
    "sg:province":"NC",
    "sg:tags":[
        "martial",
        "arts",
        "instruction"
    ],
    "wof:name":"Dustin Chovanic's American",
    "wof:placetype":"venue"
},
  "geometry": {"coordinates":[-83.36713399999999,35.181789],"type":"Point"}
}