{
  "type": "Feature",
  "properties": {
    "addr:full":"3203 US Hwy 70 Newton NC 28658",
    "addr:housenumber":"3203",
    "addr:postcode":"28658",
    "addr:street":"Us Hwy 70",
    "iso:country":"US",
    "sg:address":"3203 US Hwy 70",
    "sg:city":"Newton",
    "sg:classifiers":[
        {
            "category":"Home & Garden",
            "subcategory":"Carpets & Floor Coverings",
            "type":"Retail Goods"
        }
    ],
    "sg:phone":"+1 828 465 6818",
    "sg:postcode":"28658",
    "sg:province":"NC",
    "sg:tags":[
        "dealer",
        "material",
        "rug",
        "contractor"
    ],
    "wof:name":"Carpet One Village Interiors",
    "wof:placetype":"venue"
},
  "geometry": {"coordinates":[-81.26740100000001,35.697748],"type":"Point"}
}