{
  "type": "Feature",
  "properties": {
    "addr:full":"9411 Willowglen Trl Charlotte NC 28215",
    "addr:postcode":"9411;28215",
    "addr:street":"Willowglen Trl",
    "iso:country":"US",
    "sg:address":"9411 Willowglen Trl",
    "sg:city":"Charlotte",
    "sg:classifiers":[
        {
            "category":"Professional",
            "type":"Services"
        }
    ],
    "sg:phone":"+1 704 597 5647",
    "sg:postcode":"28215",
    "sg:province":"NC",
    "wof:name":"Richard Kuklentz",
    "wof:placetype":"venue"
},
  "geometry": {"coordinates":[-80.69104299999999,35.268234],"type":"Point"}
}