{
  "type": "Feature",
  "properties": {
    "iso:country":"US",
    "sg:address":"5675 Lemon Springs Rd",
    "sg:city":"Sanford",
    "sg:classifiers":[
        {
            "category":"Professional",
            "subcategory":"Management & Consulting",
            "type":"Services"
        }
    ],
    "sg:phone":"+1 919 774 6024",
    "sg:postcode":"27332",
    "sg:province":"NC",
    "sg:tags":[
        "accident",
        "reconstruction"
    ],
    "wof:name":"Edward Livesay & Assoc",
    "wof:placetype":"venue"
},
  "geometry": {"coordinates":[-79.177581,35.405495],"type":"Point"}
}