{
  "type": "Feature",
  "properties": {
    "addr:full":"111 Mann Ct Kill Devil Hills NC 27948",
    "addr:housenumber":"111",
    "addr:postcode":"27948",
    "addr:street":"Mann Ct",
    "iso:country":"US",
    "sg:address":"111 Mann Ct",
    "sg:city":"Kill Devil Hills",
    "sg:classifiers":[
        {
            "category":"Building & Trades",
            "subcategory":"Construction",
            "type":"Services"
        }
    ],
    "sg:phone":"+1 252 441 4448",
    "sg:postcode":"27948",
    "sg:province":"NC",
    "sg:tags":[
        "house"
    ],
    "wof:name":"Carolina Craftsman",
    "wof:placetype":"venue"
},
  "geometry": {"coordinates":[-75.71164,36.012144],"type":"Point"}
}