{
  "type": "Feature",
  "properties": {
    "addr:full":"6314 Raeford Rd Fayetteville NC 28304",
    "addr:housenumber":"6314",
    "addr:postcode":"28304",
    "addr:street":"Raeford Rd",
    "iso:country":"US",
    "sg:address":"6314 Raeford Rd",
    "sg:city":"Fayetteville",
    "sg:classifiers":[
        {
            "category":"Wholesale",
            "subcategory":"Auto Parts",
            "type":"Manufacturing & Wholesale Goods"
        }
    ],
    "sg:phone":"+1 910 860 9263",
    "sg:postcode":"28304",
    "sg:province":"NC",
    "sg:tags":[
        "tire"
    ],
    "wof:name":"Franks Auto Svc",
    "wof:placetype":"venue"
},
  "geometry": {"coordinates":[-78.98657,35.043452],"type":"Point"}
}