{
  "type": "Feature",
  "properties": {
    "iso:country":"US",
    "sg:address":"18535 Old Statesville Rd",
    "sg:city":"Cornelius",
    "sg:classifiers":[
        {
            "category":"Home & Garden",
            "subcategory":"Home Furnishings",
            "type":"Retail Goods"
        }
    ],
    "sg:phone":"+1 704 655 7360",
    "sg:postcode":"28031",
    "sg:province":"NC",
    "sg:tags":[
        "venetian",
        "blind"
    ],
    "wof:name":"Budget Blinds Of Lake Norman",
    "wof:placetype":"venue"
},
  "geometry": {"coordinates":[-80.846214,35.463219],"type":"Point"}
}