{
  "type": "Feature",
  "properties": {
    "addr:full":"8816 Six Forks Rd Raleigh NC 27615",
    "addr:housenumber":"8816",
    "addr:postcode":"27615",
    "addr:street":"Six Forks Rd",
    "iso:country":"US",
    "sg:address":"8816 Six Forks Rd",
    "sg:city":"Raleigh",
    "sg:classifiers":[
        {
            "category":"Banks & Credit Unions",
            "subcategory":"Bank",
            "type":"Services"
        }
    ],
    "sg:phone":"+1 919 861 2050",
    "sg:postcode":"27615",
    "sg:province":"NC",
    "wof:name":"Capital Bank",
    "wof:placetype":"venue"
},
  "geometry": {"coordinates":[-78.652029,35.900679],"type":"Point"}
}