{
  "type": "Feature",
  "properties": {
    "addr:full":"2019 Beverly Dr Charlotte NC 28207",
    "addr:housenumber":"2019",
    "addr:postcode":"28207",
    "addr:street":"Beverly Dr",
    "iso:country":"US",
    "sg:address":"2019 Beverly Dr",
    "sg:city":"Charlotte",
    "sg:classifiers":[
        {
            "category":"Professional",
            "subcategory":"Business Services",
            "type":"Services"
        }
    ],
    "sg:phone":"+1   ",
    "sg:postcode":"28207",
    "sg:province":"NC",
    "wof:name":"Kpl Designs",
    "wof:placetype":"venue"
},
  "geometry": {"coordinates":[-80.82686,35.186636],"type":"Point"}
}