{
  "type": "Feature",
  "properties": {
    "addr:full":"1009 Stewart St Fuquay Varina NC 27526",
    "addr:housenumber":"1009",
    "addr:postcode":"27526",
    "addr:street":"Stewart St",
    "iso:country":"US",
    "sg:address":"1009 Stewart St",
    "sg:city":"Fuquay Varina",
    "sg:classifiers":[
        {
            "category":"Building & Trades",
            "subcategory":"Landscaping Services",
            "type":"Services"
        }
    ],
    "sg:phone":"+1 919 552 2010",
    "sg:postcode":"27526",
    "sg:province":"NC",
    "sg:tags":[
        "landscape"
    ],
    "wof:name":"First Rate Landscaping",
    "wof:placetype":"venue"
},
  "geometry": {"coordinates":[-78.789349,35.598784],"type":"Point"}
}