{
  "type": "Feature",
  "properties": {
    "addr:full":"252 10th St SW Hickory NC 28602",
    "addr:housenumber":"252",
    "addr:postcode":"28602",
    "addr:street":"10Th St Sw",
    "iso:country":"US",
    "sg:address":"252 10th St SW",
    "sg:city":"Hickory",
    "sg:classifiers":[
        {
            "category":"Manufacturing",
            "subcategory":"Building Materials",
            "type":"Manufacturing & Wholesale Goods"
        }
    ],
    "sg:phone":"+1 828 327 3435",
    "sg:postcode":"28602",
    "sg:province":"NC",
    "sg:tags":[
        "mfg",
        "furniture",
        "wood",
        "kitchen",
        "cabinet"
    ],
    "wof:name":"K & K Cabinet Shop",
    "wof:placetype":"venue"
},
  "geometry": {"coordinates":[-81.354609,35.726231],"type":"Point"}
}