{
  "type": "Feature",
  "properties": {
    "addr:full":"4700 Lebanon Rd Charlotte NC 28227",
    "addr:housenumber":"4700",
    "addr:postcode":"28227",
    "addr:street":"Lebanon Rd",
    "iso:country":"US",
    "sg:address":"4700 Lebanon Rd",
    "sg:city":"Charlotte",
    "sg:classifiers":[
        {
            "category":"Professional",
            "subcategory":"Research",
            "type":"Services"
        }
    ],
    "sg:phone":"+1 704 545 3844",
    "sg:postcode":"28227",
    "sg:province":"NC",
    "wof:name":"Concepts Research Corp",
    "wof:placetype":"venue"
},
  "geometry": {"coordinates":[-80.681859,35.14955],"type":"Point"}
}