{
  "type": "Feature",
  "properties": {
    "addr:full":"2237 Park Rd Charlotte NC 28203",
    "addr:housenumber":"2237",
    "addr:postcode":"28203",
    "addr:street":"Park Rd",
    "iso:country":"US",
    "sg:address":"2237 Park Rd",
    "sg:city":"Charlotte",
    "sg:classifiers":[
        {
            "category":"Health Services",
            "subcategory":"Health Practitioner",
            "type":"Services"
        }
    ],
    "sg:phone":"+1   ",
    "sg:postcode":"28203",
    "sg:province":"NC",
    "wof:name":"Center For Conflict Management",
    "wof:placetype":"venue"
},
  "geometry": {"coordinates":[-80.851964,35.199569],"type":"Point"}
}