{
  "type": "Feature",
  "properties": {
    "addr:full":"2195 US Hwy 421 N Clinton NC 28328",
    "addr:housenumber":"2195",
    "addr:postcode":"28328",
    "addr:street":"Us Hwy 421 N",
    "iso:country":"US",
    "sg:address":"2195 US Hwy 421 N",
    "sg:city":"Clinton",
    "sg:classifiers":[
        {
            "category":"Organizations",
            "subcategory":"Religious Organization",
            "type":"Services"
        }
    ],
    "sg:phone":"+1 910 590 2187",
    "sg:postcode":"28328",
    "sg:province":"NC",
    "sg:tags":[
        "church"
    ],
    "wof:name":"Bethesda Assembly Of God",
    "wof:placetype":"venue"
},
  "geometry": {"coordinates":[-78.34970300000001,35.026526],"type":"Point"}
}