{
  "type": "Feature",
  "properties": {
    "iso:country":"US",
    "sg:address":"1329 Turlington Rd",
    "sg:city":"Dunn",
    "sg:classifiers":[
        {
            "category":"Building & Trades",
            "subcategory":"Construction",
            "type":"Services"
        }
    ],
    "sg:phone":"+1 910 897 7312",
    "sg:postcode":"28334",
    "sg:province":"NC",
    "sg:tags":[
        "grading",
        "contractor"
    ],
    "wof:name":"W P Construction Co Inc",
    "wof:placetype":"venue"
},
  "geometry": {"coordinates":[-78.639186,35.375385],"type":"Point"}
}