{
  "type": "Feature",
  "properties": {
    "addr:full":"6400 Matthews-Mint Hill Rd Mint Hill NC 28227",
    "addr:postcode":"6400;28227",
    "addr:street":"Matthews-Mint Hill Rd",
    "iso:country":"US",
    "sg:address":"6400 Matthews-Mint Hill Rd",
    "sg:city":"Mint Hill",
    "sg:classifiers":[
        {
            "category":"Education",
            "subcategory":"School",
            "type":"Public Place"
        }
    ],
    "sg:phone":"+1 704 573 6611",
    "sg:postcode":"28227",
    "sg:province":"NC",
    "sg:website":"www.heritageacademies.com",
    "wof:name":"Queen's Grant Community School",
    "wof:placetype":"venue"
},
  "geometry": {"coordinates":[-80.66280999999999,35.169696],"type":"Point"}
}