{
  "type": "Feature",
  "properties": {
    "addr:full":"6128 Charleycote Dr Raleigh NC 27614",
    "addr:housenumber":"6128",
    "addr:postcode":"27614",
    "addr:street":"Charleycote Dr",
    "iso:country":"US",
    "sg:address":"6128 Charleycote Dr",
    "sg:city":"Raleigh",
    "sg:classifiers":[
        {
            "category":"Personal",
            "type":"Services"
        }
    ],
    "sg:phone":"+1   ",
    "sg:postcode":"27614",
    "sg:province":"NC",
    "sg:tags":[
        "interior",
        "planning",
        "design",
        "event"
    ],
    "wof:name":"Burke Designs",
    "wof:placetype":"venue"
},
  "geometry": {"coordinates":[-78.66690800000001,35.951743],"type":"Point"}
}