{
  "type": "Feature",
  "properties": {
    "iso:country":"US",
    "sg:address":"8066 N Point Blvd",
    "sg:city":"Winston Salem",
    "sg:classifiers":[
        {
            "category":"Professional",
            "subcategory":"Computer Services",
            "type":"Services"
        }
    ],
    "sg:phone":"+1 336 759 9947",
    "sg:postcode":"27106",
    "sg:province":"NC",
    "sg:tags":[
        "consultant",
        "designer"
    ],
    "wof:name":"Chipworks Technology Cnsltng",
    "wof:placetype":"venue"
},
  "geometry": {"coordinates":[-80.26948,36.148925],"type":"Point"}
}