{
  "type": "Feature",
  "properties": {
    "addr:full":"1937 Odat Trl Asheboro NC 27205",
    "addr:housenumber":"1937",
    "addr:postcode":"27205",
    "addr:street":"Odat Trl",
    "iso:country":"US",
    "sg:address":"1937 Odat Trl",
    "sg:city":"Asheboro",
    "sg:classifiers":[
        {
            "category":"Building & Trades",
            "subcategory":"Plumbing",
            "type":"Services"
        }
    ],
    "sg:phone":"+1 336 626 8927",
    "sg:postcode":"27205",
    "sg:province":"NC",
    "sg:tags":[
        "contractor"
    ],
    "wof:name":"Cagle Plumbing",
    "wof:placetype":"venue"
},
  "geometry": {"coordinates":[-79.738956,35.665679],"type":"Point"}
}