{
  "type": "Feature",
  "properties": {
    "addr:full":"1582 Hannah Branch Rd Burnsville NC 28714",
    "addr:housenumber":"1582",
    "addr:postcode":"28714",
    "addr:street":"Hannah Branch Rd",
    "iso:country":"US",
    "sg:address":"1582 Hannah Branch Rd",
    "sg:city":"Burnsville",
    "sg:classifiers":[
        {
            "category":"Professional",
            "subcategory":"Computer Services",
            "type":"Services"
        }
    ],
    "sg:phone":"+1   ",
    "sg:postcode":"28714",
    "sg:province":"NC",
    "sg:tags":[
        "medical",
        "datum"
    ],
    "wof:name":"Samepathcom",
    "wof:placetype":"venue"
},
  "geometry": {"coordinates":[-82.18089500000001,35.818552],"type":"Point"}
}