{
  "type": "Feature",
  "properties": {
    "iso:country":"US",
    "sg:address":"403 S Main St",
    "sg:city":"Lucama",
    "sg:classifiers":[
        {
            "category":"Organizations",
            "subcategory":"Religious Organization",
            "type":"Services"
        }
    ],
    "sg:phone":"+1 252 239 0818",
    "sg:postcode":"27851",
    "sg:province":"NC",
    "sg:tags":[
        "church"
    ],
    "wof:name":"Lucama United Methodist Church",
    "wof:placetype":"venue"
},
  "geometry": {"coordinates":[-78.00764100000001,35.641915],"type":"Point"}
}