{
  "type": "Feature",
  "properties": {
    "addr:full":"914 Carolina Ave Bessemer City NC 28052",
    "addr:housenumber":"914",
    "addr:postcode":"28052",
    "addr:street":"Carolina Ave",
    "iso:country":"US",
    "sg:address":"914 Carolina Ave",
    "sg:city":"Bessemer City",
    "sg:classifiers":[
        {
            "category":"Organizations",
            "subcategory":"Religious Organization",
            "type":"Services"
        }
    ],
    "sg:phone":"+1   ",
    "sg:postcode":"28052",
    "sg:province":"NC",
    "wof:name":"Kellys Chpel Untd Mthdst Chrch",
    "wof:placetype":"venue"
},
  "geometry": {"coordinates":[-81.20160300000001,35.245111],"type":"Point"}
}