{
  "type": "Feature",
  "properties": {
    "iso:country":"US",
    "sg:address":"443 Dillard Rd",
    "sg:city":"Hays",
    "sg:classifiers":[
        {
            "category":"Autos & Motor Vehicles",
            "subcategory":"Automobile Sales",
            "type":"Retail Goods"
        }
    ],
    "sg:phone":"+1 336 696 6255",
    "sg:postcode":"28635",
    "sg:province":"NC",
    "sg:tags":[
        "used"
    ],
    "wof:name":"Hometown Motors",
    "wof:placetype":"venue"
},
  "geometry": {"coordinates":[-81.140626,36.25807],"type":"Point"}
}