{
  "type": "Feature",
  "properties": {
    "iso:country":"US",
    "sg:address":"1587 Old Boxwood Cir",
    "sg:city":"Conover",
    "sg:classifiers":[
        {
            "category":"Building & Trades",
            "subcategory":"Plumbing",
            "type":"Services"
        }
    ],
    "sg:phone":"+1 828 256 2675",
    "sg:postcode":"28613",
    "sg:province":"NC",
    "sg:tags":[
        "conditioning",
        "contractor",
        "system",
        "air"
    ],
    "wof:name":"Huffman Heating & Air Cond",
    "wof:placetype":"venue"
},
  "geometry": {"coordinates":[-81.23854300000001,35.73589],"type":"Point"}
}