{
  "type": "Feature",
  "properties": {
    "addr:full":"247 Yarbro Rd Kings Mountain NC 28086",
    "addr:housenumber":"247",
    "addr:postcode":"28086",
    "addr:street":"Yarbro Rd",
    "iso:country":"US",
    "sg:address":"247 Yarbro Rd",
    "sg:city":"Kings Mountain",
    "sg:classifiers":[
        {
            "category":"Professional",
            "subcategory":"Management & Consulting",
            "type":"Services"
        }
    ],
    "sg:phone":"+1   ",
    "sg:postcode":"28086",
    "sg:province":"NC",
    "sg:tags":[
        "business"
    ],
    "wof:name":"Educational Gateway Services",
    "wof:placetype":"venue"
},
  "geometry": {"coordinates":[-81.40940000000001,35.23378],"type":"Point"}
}