{
  "type": "Feature",
  "properties": {
    "iso:country":"US",
    "sg:address":"3536 Vest Mill Rd",
    "sg:city":"Winston Salem",
    "sg:classifiers":[
        {
            "category":"Building & Trades",
            "subcategory":"Construction",
            "type":"Services"
        }
    ],
    "sg:phone":"+1 336 769 9406",
    "sg:postcode":"27103",
    "sg:province":"NC",
    "sg:tags":[
        "roofing",
        "contractor"
    ],
    "wof:name":"Asap Roofing & Remodeling",
    "wof:placetype":"venue"
},
  "geometry": {"coordinates":[-80.30798,36.074107],"type":"Point"}
}