{
  "type": "Feature",
  "properties": {
    "addr:full":"147 Franklin Ln Mocksville NC 27028",
    "addr:housenumber":"147",
    "addr:postcode":"27028",
    "addr:street":"Franklin Ln",
    "iso:country":"US",
    "sg:address":"147 Franklin Ln",
    "sg:city":"Mocksville",
    "sg:classifiers":[
        {
            "category":"Freight",
            "type":"Transportation"
        }
    ],
    "sg:phone":"+1 336 492 2120",
    "sg:postcode":"27028",
    "sg:province":"NC",
    "sg:tags":[
        "operator",
        "local",
        "trucking"
    ],
    "wof:name":"Tf White Trucking",
    "wof:placetype":"venue"
},
  "geometry": {"coordinates":[-80.649204,35.954573],"type":"Point"}
}