{
  "type": "Feature",
  "properties": {
    "iso:country":"US",
    "sg:address":"412 W Warren St",
    "sg:city":"Shelby",
    "sg:classifiers":[
        {
            "category":"Shopping",
            "subcategory":"Florist",
            "type":"Retail Goods"
        }
    ],
    "sg:phone":"+1 704 487 5013",
    "sg:postcode":"28150",
    "sg:province":"NC",
    "wof:name":"B & H Florist",
    "wof:placetype":"venue"
},
  "geometry": {"coordinates":[-81.546284,35.291202],"type":"Point"}
}