{
  "type": "Feature",
  "properties": {
    "iso:country":"US",
    "sg:address":"106 Guthrie Dr",
    "sg:city":"Newport",
    "sg:classifiers":[
        {
            "category":"Insurance",
            "subcategory":"Insurance Agent",
            "type":"Services"
        }
    ],
    "sg:phone":"+1 252 240 3674",
    "sg:postcode":"28570",
    "sg:province":"NC",
    "wof:name":"Statewide Security Inc",
    "wof:placetype":"venue"
},
  "geometry": {"coordinates":[-76.915746,34.730778],"type":"Point"}
}