{
  "type": "Feature",
  "properties": {
    "addr:full":"130 Wicker St Sanford NC 27330",
    "addr:housenumber":"130",
    "addr:postcode":"27330",
    "addr:street":"Wicker St",
    "iso:country":"US",
    "sg:address":"130 Wicker St",
    "sg:city":"Sanford",
    "sg:classifiers":[
        {
            "category":"Wholesale",
            "subcategory":"Machinery & Supplies",
            "type":"Manufacturing & Wholesale Goods"
        }
    ],
    "sg:phone":"+1 919 775 7318",
    "sg:postcode":"27330",
    "sg:province":"NC",
    "sg:tags":[
        "machine",
        "shredding",
        "paper"
    ],
    "sg:website":"www.intimus.com",
    "wof:name":"Schleicher & Co Of America Inc",
    "wof:placetype":"venue"
},
  "geometry": {"coordinates":[-79.177384,35.479943],"type":"Point"}
}