{
  "type": "Feature",
  "properties": {
    "addr:full":"2502 Beech Cliff Ln Greensboro NC 27455",
    "addr:housenumber":"2502",
    "addr:postcode":"27455",
    "addr:street":"Beech Cliff Ln",
    "iso:country":"US",
    "sg:address":"2502 Beech Cliff Ln",
    "sg:city":"Greensboro",
    "sg:classifiers":[
        {
            "category":"Professional",
            "subcategory":"Management & Consulting",
            "type":"Services"
        }
    ],
    "sg:phone":"+1   ",
    "sg:postcode":"27455",
    "sg:province":"NC",
    "wof:name":"Strategic Agility Resources",
    "wof:placetype":"venue"
},
  "geometry": {"coordinates":[-79.838678,36.158341],"type":"Point"}
}