{
  "type": "Feature",
  "properties": {
    "addr:full":"1802 Sharpe Rd Greensboro NC 27406",
    "addr:housenumber":"1802",
    "addr:postcode":"27406",
    "addr:street":"Sharpe Rd",
    "iso:country":"US",
    "sg:address":"1802 Sharpe Rd",
    "sg:city":"Greensboro",
    "sg:classifiers":[
        {
            "category":"Building & Trades",
            "subcategory":"Plumbing",
            "type":"Services"
        }
    ],
    "sg:phone":"+1 336 273 2627",
    "sg:postcode":"27406",
    "sg:province":"NC",
    "sg:tags":[
        "conditioning",
        "air",
        "system",
        "contractor"
    ],
    "wof:name":"Thomas Heating & Air Cond",
    "wof:placetype":"venue"
},
  "geometry": {"coordinates":[-79.745808,36.0448],"type":"Point"}
}