{
  "type": "Feature",
  "properties": {
    "addr:full":"2718 Cambridge Rd Raleigh NC 27608",
    "addr:housenumber":"2718",
    "addr:postcode":"27608",
    "addr:street":"Cambridge Rd",
    "iso:country":"US",
    "sg:address":"2718 Cambridge Rd",
    "sg:city":"Raleigh",
    "sg:classifiers":[
        {
            "category":"Professional",
            "subcategory":"Business Services",
            "type":"Services"
        }
    ],
    "sg:phone":"+1   ",
    "sg:postcode":"27608",
    "sg:province":"NC",
    "wof:name":"Iatridis Design",
    "wof:placetype":"venue"
},
  "geometry": {"coordinates":[-78.66391299999999,35.81343],"type":"Point"}
}