{
  "type": "Feature",
  "properties": {
    "addr:full":"622 N New River Dr Holly Ridge NC 28445",
    "addr:housenumber":"622",
    "addr:postcode":"28445",
    "addr:street":"N New River Dr",
    "iso:country":"US",
    "sg:address":"622 N New River Dr",
    "sg:city":"Holly Ridge",
    "sg:classifiers":[
        {
            "category":"Travel",
            "subcategory":"Hotels & Motels",
            "type":"Entertainment"
        }
    ],
    "sg:phone":"+1 910 328 3691",
    "sg:postcode":"28445",
    "sg:province":"NC",
    "sg:tags":[
        "operation"
    ],
    "wof:name":"Loggerhead Inn",
    "wof:placetype":"venue"
},
  "geometry": {"coordinates":[-77.538534,34.431165],"type":"Point"}
}