{
  "type": "Feature",
  "properties": {
    "addr:full":"7102 Poplar Grove Trl Greensboro NC 27410",
    "addr:housenumber":"7102",
    "addr:postcode":"27410",
    "addr:street":"Poplar Grove Trl",
    "iso:country":"US",
    "sg:address":"7102 Poplar Grove Trl",
    "sg:city":"Greensboro",
    "sg:classifiers":[
        {
            "category":"Organizations",
            "subcategory":"Professional Association",
            "type":"Services"
        }
    ],
    "sg:phone":"+1 336 665 0000",
    "sg:postcode":"27410",
    "sg:province":"NC",
    "wof:name":"North Carolina Assn-Fire",
    "wof:placetype":"venue"
},
  "geometry": {"coordinates":[-79.93939899999999,36.136701],"type":"Point"}
}