{
  "type": "Feature",
  "properties": {
    "iso:country":"US",
    "sg:address":"6040 Aaron Place Ln",
    "sg:city":"Kernersville",
    "sg:classifiers":[
        {
            "category":"Building & Trades",
            "subcategory":"Construction",
            "type":"Services"
        }
    ],
    "sg:phone":"+1 336 785 0741",
    "sg:postcode":"27284",
    "sg:province":"NC",
    "sg:tags":[
        "home",
        "builder"
    ],
    "wof:name":"Waddell Custom Homes Inc",
    "wof:placetype":"venue"
},
  "geometry": {"coordinates":[-80.12465,36.086772],"type":"Point"}
}