{
  "type": "Feature",
  "properties": {
    "addr:full":"6009 Bramblewood Dr Raleigh NC 27612",
    "addr:housenumber":"6009",
    "addr:postcode":"27612",
    "addr:street":"Bramblewood Dr",
    "iso:country":"US",
    "sg:address":"6009 Bramblewood Dr",
    "sg:city":"Raleigh",
    "sg:classifiers":[
        {
            "category":"Education",
            "subcategory":"School",
            "type":"Public Place"
        }
    ],
    "sg:phone":"+1 919 845 3282",
    "sg:postcode":"27612",
    "sg:province":"NC",
    "wof:name":"Puthenveet Reji",
    "wof:placetype":"venue"
},
  "geometry": {"coordinates":[-78.67940900000001,35.863044],"type":"Point"}
}