{
  "type": "Feature",
  "properties": {
    "iso:country":"US",
    "sg:address":"532 Kyle Rd",
    "sg:city":"Winston Salem",
    "sg:classifiers":[
        {
            "category":"Professional",
            "subcategory":"Computer Services",
            "type":"Services"
        }
    ],
    "sg:phone":"+1 336 760 8797",
    "sg:postcode":"27104",
    "sg:province":"NC",
    "sg:tags":[
        "consultant",
        "designer"
    ],
    "wof:name":"Chipworks Technology Consltng",
    "wof:placetype":"venue"
},
  "geometry": {"coordinates":[-80.323944,36.093561],"type":"Point"}
}