{
  "type": "Feature",
  "properties": {
    "iso:country":"US",
    "sg:address":"199 N Enochville Ave",
    "sg:city":"Kannapolis",
    "sg:classifiers":[
        {
            "category":"Organizations",
            "subcategory":"Religious Organization",
            "type":"Services"
        }
    ],
    "sg:phone":"+1 704 932 7300",
    "sg:postcode":"28081",
    "sg:province":"NC",
    "sg:tags":[
        "church"
    ],
    "sg:website":"www.enochvillecog.com",
    "wof:name":"Enochville Church Of God",
    "wof:placetype":"venue"
},
  "geometry": {"coordinates":[-80.67024000000001,35.516504],"type":"Point"}
}