{
  "type": "Feature",
  "properties": {
    "iso:country":"US",
    "sg:address":"403 Main St NW",
    "sg:city":"Lenoir",
    "sg:classifiers":[
        {
            "category":"Taxi",
            "type":"Transportation"
        }
    ],
    "sg:phone":"+1 828 754 3471",
    "sg:postcode":"28645",
    "sg:province":"NC",
    "sg:tags":[
        "taxicab"
    ],
    "wof:name":"Howard's Yellow Cab",
    "wof:placetype":"venue"
},
  "geometry": {"coordinates":[-81.541077,35.916557],"type":"Point"}
}