{
  "type": "Feature",
  "properties": {
    "addr:full":"2630 Pax Hill Rd Morganton NC 28655",
    "addr:postcode":"2630;28655",
    "addr:street":"Pax Hill Rd",
    "iso:country":"US",
    "sg:address":"2630 Pax Hill Rd",
    "sg:city":"Morganton",
    "sg:classifiers":[
        {
            "category":"Social Services",
            "subcategory":"Adult Care",
            "type":"Services"
        }
    ],
    "sg:phone":"+1 828 437 5164",
    "sg:postcode":"28655",
    "sg:province":"NC",
    "sg:tags":[
        "home",
        "residential"
    ],
    "wof:name":"Chesterfield Family Care Home",
    "wof:placetype":"venue"
},
  "geometry": {"coordinates":[-81.677498,35.819126],"type":"Point"}
}