{
  "type": "Feature",
  "properties": {
    "iso:country":"US",
    "sg:address":"503 Lakeside Dr",
    "sg:city":"Garner",
    "sg:classifiers":[
        {
            "category":"Organizations",
            "subcategory":"Religious Organization",
            "type":"Services"
        }
    ],
    "sg:phone":"+1 919 772 0727",
    "sg:postcode":"27529",
    "sg:province":"NC",
    "wof:name":"First Presbt Church Garner",
    "wof:placetype":"venue"
},
  "geometry": {"coordinates":[-78.610888,35.698328],"type":"Point"}
}