{
  "type": "Feature",
  "properties": {
    "addr:full":"5826 Woodleigh Oaks Dr Charlotte NC 28226",
    "addr:housenumber":"5826",
    "addr:postcode":"28226",
    "addr:street":"Woodleigh Oaks Dr",
    "iso:country":"US",
    "sg:address":"5826 Woodleigh Oaks Dr",
    "sg:city":"Charlotte",
    "sg:classifiers":[
        {
            "category":"Real Estate",
            "subcategory":"Real Estate Agent",
            "type":"Services"
        }
    ],
    "sg:phone":"+1 704 752 0265",
    "sg:postcode":"28226",
    "sg:province":"NC",
    "wof:name":"Veraset LLC",
    "wof:placetype":"venue"
},
  "geometry": {"coordinates":[-80.82921399999999,35.089348],"type":"Point"}
}