{
  "type": "Feature",
  "properties": {
    "addr:full":"847 Buffalo Shoals Rd Statesville NC 28677",
    "addr:housenumber":"847",
    "addr:postcode":"28677",
    "addr:street":"Buffalo Shoals Rd",
    "iso:country":"US",
    "sg:address":"847 Buffalo Shoals Rd",
    "sg:city":"Statesville",
    "sg:classifiers":[
        {
            "category":"Freight",
            "type":"Transportation"
        }
    ],
    "sg:phone":"+1 704 873 2866",
    "sg:postcode":"28677",
    "sg:province":"NC",
    "sg:tags":[
        "local",
        "trucking"
    ],
    "wof:name":"Jack B Wooten Co Inc",
    "wof:placetype":"venue"
},
  "geometry": {"coordinates":[-80.91646,35.764683],"type":"Point"}
}