{
  "type": "Feature",
  "properties": {
    "iso:country":"US",
    "sg:address":"132 New Salem Rd",
    "sg:city":"Randleman",
    "sg:classifiers":[
        {
            "category":"Freight",
            "type":"Transportation"
        }
    ],
    "sg:phone":"+1 336 498 7335",
    "sg:postcode":"27317",
    "sg:province":"NC",
    "sg:tags":[
        "operator",
        "local",
        "trucking"
    ],
    "wof:name":"Tim Wood",
    "wof:placetype":"venue"
},
  "geometry": {"coordinates":[-79.796565,35.835778],"type":"Point"}
}