{
  "type": "Feature",
  "properties": {
    "iso:country":"US",
    "sg:address":"12437 Green St",
    "sg:city":"Bailey",
    "sg:classifiers":[
        {
            "category":"Organizations",
            "subcategory":"Religious Organization",
            "type":"Services"
        }
    ],
    "sg:phone":"+1 252 235 4576",
    "sg:postcode":"27807",
    "sg:province":"NC",
    "sg:tags":[
        "church"
    ],
    "wof:name":"Bailey United Methodist Chr",
    "wof:placetype":"venue"
},
  "geometry": {"coordinates":[-78.111941,35.779577],"type":"Point"}
}