{
  "type": "Feature",
  "properties": {
    "iso:country":"US",
    "sg:address":"103 Seaview St",
    "sg:city":"Beaufort",
    "sg:classifiers":[
        {
            "category":"Real Estate",
            "subcategory":"Real Estate Operator",
            "type":"Services"
        }
    ],
    "sg:phone":"+1 252 728 5211",
    "sg:postcode":"28516",
    "sg:province":"NC",
    "sg:tags":[
        "building",
        "apartment"
    ],
    "wof:name":"Villager Apts",
    "wof:placetype":"venue"
},
  "geometry": {"coordinates":[-76.651715,34.71361],"type":"Point"}
}