{
  "type": "Feature",
  "properties": {
    "iso:country":"US",
    "sg:address":"324 Jonas Sims Rd",
    "sg:city":"Rutherfordton",
    "sg:classifiers":[
        {
            "category":"Wholesale",
            "subcategory":"Plants",
            "type":"Manufacturing & Wholesale Goods"
        },
        {
            "category":"Home & Garden",
            "subcategory":"Garden Supply",
            "type":"Retail Goods"
        }
    ],
    "sg:phone":"+1 828 286 3535",
    "sg:postcode":"28139",
    "sg:province":"NC",
    "sg:tags":[
        "nurseryman",
        "nursery"
    ],
    "wof:name":"Plant Masters Nursery LLC",
    "wof:placetype":"venue"
},
  "geometry": {"coordinates":[-81.97685799999999,35.333608],"type":"Point"}
}