{
  "type": "Feature",
  "properties": {
    "iso:country":"US",
    "sg:address":"5620 Kiwi Ct",
    "sg:city":"Concord",
    "sg:classifiers":[
        {
            "category":"Retail",
            "subcategory":"Auto Repair",
            "type":"Services"
        }
    ],
    "sg:phone":"+1 704 332 8645",
    "sg:postcode":"28025",
    "sg:province":"NC",
    "sg:tags":[
        "body",
        "shop",
        "paint"
    ],
    "wof:name":"Collision Body Shop Inc",
    "wof:placetype":"venue"
},
  "geometry": {"coordinates":[-80.567983,35.339091],"type":"Point"}
}