{
  "type": "Feature",
  "properties": {
    "addr:full":"305 W 15th St Washington NC 27889",
    "addr:housenumber":"305",
    "addr:postcode":"27889",
    "addr:street":"W 15Th St",
    "iso:country":"US",
    "sg:address":"305 W 15th St",
    "sg:city":"Washington",
    "sg:classifiers":[
        {
            "category":"Real Estate",
            "subcategory":"Real Estate Agent",
            "type":"Services"
        }
    ],
    "sg:phone":"+1 252 946 2986",
    "sg:postcode":"27889",
    "sg:province":"NC",
    "sg:tags":[
        "house",
        "construct"
    ],
    "wof:name":"Walker Rentals",
    "wof:placetype":"venue"
},
  "geometry": {"coordinates":[-77.050528,35.557296],"type":"Point"}
}