{
  "type": "Feature",
  "properties": {
    "addr:full":"105 Oakley Dr Harrisburg NC 28075",
    "addr:housenumber":"105",
    "addr:postcode":"28075",
    "addr:street":"Oakley Dr",
    "iso:country":"US",
    "sg:address":"105 Oakley Dr",
    "sg:city":"Harrisburg",
    "sg:classifiers":[
        {
            "category":"Utilities",
            "subcategory":"Electric",
            "type":"Services"
        },
        {
            "category":"Building & Trades",
            "subcategory":"Construction",
            "type":"Services"
        }
    ],
    "sg:phone":"+1 704 455 2608",
    "sg:postcode":"28075",
    "sg:province":"NC",
    "sg:tags":[
        "equipment-repair",
        "welder",
        "welding"
    ],
    "wof:name":"Welding Apparatus Repair Service, Inc.",
    "wof:placetype":"venue"
},
  "geometry": {"coordinates":[-80.659947,35.320043],"type":"Point"}
}