{
  "type": "Feature",
  "properties": {
    "addr:full":"573 3rd St SW Taylorsville NC 28681",
    "addr:housenumber":"573",
    "addr:postcode":"28681",
    "addr:street":"3Rd St Sw",
    "iso:country":"US",
    "sg:address":"573 3rd St SW",
    "sg:city":"Taylorsville",
    "sg:classifiers":[
        {
            "category":"Shopping",
            "subcategory":"Discount & Variety Stores",
            "type":"Retail Goods"
        }
    ],
    "sg:phone":"+1 828 632 2350",
    "sg:postcode":"28681",
    "sg:province":"NC",
    "wof:name":"Dollar Tree",
    "wof:placetype":"venue"
},
  "geometry": {"coordinates":[-81.17792799999999,35.912883],"type":"Point"}
}