{
  "type": "Feature",
  "properties": {
    "iso:country":"US",
    "sg:address":"2840 Armentrout Dr",
    "sg:city":"Concord",
    "sg:classifiers":[
        {
            "category":"Professional",
            "subcategory":"Business Services",
            "type":"Services"
        },
        {
            "category":"Manufacturing",
            "subcategory":"Apparel",
            "type":"Manufacturing & Wholesale Goods"
        }
    ],
    "sg:phone":"+1 704 784 1456",
    "sg:postcode":"28025",
    "sg:province":"NC",
    "sg:tags":[
        "embroidery"
    ],
    "wof:name":"Regal Designs Specialties",
    "wof:placetype":"venue"
},
  "geometry": {"coordinates":[-80.574895,35.378767],"type":"Point"}
}