{
  "type": "Feature",
  "properties": {
    "iso:country":"US",
    "sg:address":"5828 Oak Dr",
    "sg:city":"Charlotte",
    "sg:classifiers":[
        {
            "category":"Professional",
            "subcategory":"Business Services",
            "type":"Services"
        }
    ],
    "sg:phone":"+1 704 545 6151",
    "sg:postcode":"28227",
    "sg:province":"NC",
    "sg:tags":[
        "interior",
        "food",
        "design",
        "area"
    ],
    "sg:website":"www.foodesignassociates.com",
    "wof:name":"Foodesign Associates Inc",
    "wof:placetype":"venue"
},
  "geometry": {"coordinates":[-80.707342,35.174971],"type":"Point"}
}