{
  "type": "Feature",
  "properties": {
    "addr:full":"1215 Vann St Edenton NC 27932",
    "addr:housenumber":"1215",
    "addr:postcode":"27932",
    "addr:street":"Vann St",
    "iso:country":"US",
    "sg:address":"1215 Vann St",
    "sg:city":"Edenton",
    "sg:classifiers":[
        {
            "category":"Organizations",
            "subcategory":"Religious Organization",
            "type":"Services"
        }
    ],
    "sg:phone":"+1 252 482 4959",
    "sg:postcode":"27932",
    "sg:province":"NC",
    "sg:tags":[
        "church"
    ],
    "wof:name":"St Luke Church Of Christ",
    "wof:placetype":"venue"
},
  "geometry": {"coordinates":[-76.601432,36.075622],"type":"Point"}
}