{
  "type": "Feature",
  "properties": {
    "iso:country":"US",
    "sg:address":"204 N 4th St",
    "sg:city":"Mebane",
    "sg:classifiers":[
        {
            "category":"Retail",
            "subcategory":"Animal Services",
            "type":"Services"
        }
    ],
    "sg:phone":"+1 919 563 3647",
    "sg:postcode":"27302",
    "sg:province":"NC",
    "sg:tags":[
        "pet"
    ],
    "wof:name":"Luckey's Luxury Pet Resort",
    "wof:placetype":"venue"
},
  "geometry": {"coordinates":[-79.26724299999999,36.09766],"type":"Point"}
}