{
  "type": "Feature",
  "properties": {
    "addr:full":"157 N Trade St Tryon NC 28782",
    "addr:housenumber":"157",
    "addr:postcode":"28782",
    "addr:street":"N Trade St",
    "iso:country":"US",
    "sg:address":"157 N Trade St",
    "sg:city":"Tryon",
    "sg:classifiers":[
        {
            "category":"Shopping",
            "subcategory":"Florist",
            "type":"Retail Goods"
        },
        {
            "category":"Shopping",
            "subcategory":"Gifts & Souvenirs",
            "type":"Retail Goods"
        }
    ],
    "sg:phone":"+1 828 859 5440",
    "sg:postcode":"28782",
    "sg:province":"NC",
    "wof:name":"Sisters Going To Seed",
    "wof:placetype":"venue"
},
  "geometry": {"coordinates":[-82.238606,35.20899],"type":"Point"}
}