{
  "type": "Feature",
  "properties": {
    "iso:country":"US",
    "sg:address":"830 Raleigh Ct",
    "sg:city":"Gastonia",
    "sg:classifiers":[
        {
            "category":"Banks & Credit Unions",
            "subcategory":"Financial Services",
            "type":"Services"
        }
    ],
    "sg:phone":"+1 704 854 8797",
    "sg:postcode":"28054",
    "sg:province":"NC",
    "sg:tags":[
        "trust",
        "investment",
        "real estate"
    ],
    "wof:name":"Beasley Investitores LLC",
    "wof:placetype":"venue"
},
  "geometry": {"coordinates":[-81.16642299999999,35.217277],"type":"Point"}
}