{
  "type": "Feature",
  "properties": {
    "iso:country":"US",
    "sg:address":"1320 Hamilton Pl",
    "sg:city":"High Point",
    "sg:classifiers":[
        {
            "category":"Personal",
            "type":"Services"
        }
    ],
    "sg:phone":"+1 336 885 4670",
    "sg:postcode":"27262",
    "sg:province":"NC",
    "sg:tags":[
        "therapist",
        "massage"
    ],
    "wof:name":"Sara L Hoffman",
    "wof:placetype":"venue"
},
  "geometry": {"coordinates":[-80.01610700000001,35.97513],"type":"Point"}
}