{
  "type": "Feature",
  "properties": {
    "addr:full":"3204 Sunset Ave Rocky Mount NC 27804",
    "addr:housenumber":"3204",
    "addr:postcode":"27804",
    "addr:street":"Sunset Ave",
    "iso:country":"US",
    "sg:address":"3204 Sunset Ave",
    "sg:city":"Rocky Mount",
    "sg:classifiers":[
        {
            "category":"Travel",
            "subcategory":"Hotels & Motels",
            "type":"Entertainment"
        }
    ],
    "sg:phone":"+1   ",
    "sg:postcode":"27804",
    "sg:province":"NC",
    "sg:tags":[
        "operation"
    ],
    "wof:name":"Bodie Island Beach Club",
    "wof:placetype":"venue"
},
  "geometry": {"coordinates":[-77.842399,35.963393],"type":"Point"}
}