{
  "type": "Feature",
  "properties": {
    "iso:country":"US",
    "sg:address":"500 S Greene St",
    "sg:city":"Greenville",
    "sg:classifiers":[
        {
            "category":"Government",
            "subcategory":"Police Station",
            "type":"Public Place"
        }
    ],
    "sg:phone":"+1 252 329 4390",
    "sg:postcode":"27834",
    "sg:province":"NC",
    "sg:tags":[
        "department",
        "executive"
    ],
    "sg:website":"www.greenvillenc.gov",
    "wof:name":"Greenville Police Dept",
    "wof:placetype":"venue"
},
  "geometry": {"coordinates":[-77.375179,35.611513],"type":"Point"}
}