{
  "type": "Feature",
  "properties": {
    "iso:country":"US",
    "sg:address":"5260 New Bern Ave",
    "sg:city":"Raleigh",
    "sg:classifiers":[
        {
            "category":"Ice Cream",
            "type":"Food & Drink"
        }
    ],
    "sg:menulink":"http://www.allmenus.com/nc/st-matthews/167689-dairy-queen/menu/",
    "sg:phone":"+1 919 792 0127",
    "sg:postcode":"27610",
    "sg:province":"NC",
    "sg:tags":[
        "burger",
        "american"
    ],
    "wof:name":"Dairy Queen",
    "wof:placetype":"venue"
},
  "geometry": {"coordinates":[-78.54545299999999,35.79226],"type":"Point"}
}