{
  "type": "Feature",
  "properties": {
    "iso:country":"US",
    "sg:address":"2711 Burch Dr",
    "sg:city":"Charlotte",
    "sg:classifiers":[
        {
            "category":"Professional",
            "subcategory":"Engineering",
            "type":"Services"
        },
        {
            "category":"Building & Trades",
            "subcategory":"Cleaning & Sanitation",
            "type":"Services"
        },
        {
            "category":"Professional",
            "subcategory":"Business Services",
            "type":"Services"
        },
        {
            "category":"Professional",
            "subcategory":"Management & Consulting",
            "type":"Services"
        }
    ],
    "sg:phone":"+1 704 598 9782",
    "sg:postcode":"28269",
    "sg:province":"NC",
    "sg:tags":[
        "control",
        "product",
        "consultant",
        "hazardous",
        "material",
        "removal",
        "environmental",
        "ecological",
        "engineer"
    ],
    "sg:website":"http://www.hepaco.com",
    "wof:name":"Hepaco Inc",
    "wof:placetype":"venue"
},
  "geometry": {"coordinates":[-80.83275500000001,35.275932],"type":"Point"}
}