{
  "type": "Feature",
  "properties": {
    "addr:full":"596 Industry Dr Henderson NC 27537",
    "addr:housenumber":"596",
    "addr:postcode":"27537",
    "addr:street":"Industry Dr",
    "iso:country":"US",
    "sg:address":"596 Industry Dr",
    "sg:city":"Henderson",
    "sg:classifiers":[
        {
            "category":"Building & Trades",
            "subcategory":"Construction",
            "type":"Services"
        }
    ],
    "sg:phone":"+1 252 430 8280",
    "sg:postcode":"27537",
    "sg:province":"NC",
    "sg:tags":[
        "roofing",
        "contractor"
    ],
    "wof:name":"Kimball Roofing Co",
    "wof:placetype":"venue"
},
  "geometry": {"coordinates":[-78.438991,36.346118],"type":"Point"}
}