{
  "type": "Feature",
  "properties": {
    "addr:full":"119 N Wright St Burgaw NC 28425",
    "addr:housenumber":"119",
    "addr:postcode":"28425",
    "addr:street":"N Wright St",
    "iso:country":"US",
    "sg:address":"119 N Wright St",
    "sg:city":"Burgaw",
    "sg:classifiers":[
        {
            "category":"Shopping",
            "subcategory":"Pharmacy",
            "type":"Retail Goods"
        }
    ],
    "sg:phone":"+1 910 259 7788",
    "sg:postcode":"28425",
    "sg:province":"NC",
    "wof:name":"Cape Fear Compounding Ctr",
    "wof:placetype":"venue"
},
  "geometry": {"coordinates":[-77.927273,34.552409],"type":"Point"}
}