{
  "type": "Feature",
  "properties": {
    "iso:country":"US",
    "sg:address":"222 E Broad St",
    "sg:city":"Statesville",
    "sg:classifiers":[
        {
            "category":"Manufacturing",
            "subcategory":"Printing",
            "type":"Manufacturing & Wholesale Goods"
        }
    ],
    "sg:phone":"+1 704 873 1451",
    "sg:postcode":"28677",
    "sg:province":"NC",
    "sg:tags":[
        "newspaper"
    ],
    "wof:name":"Statesville Record & Landmark",
    "wof:placetype":"venue"
},
  "geometry": {"coordinates":[-80.883938,35.785913],"type":"Point"}
}