{
  "type": "Feature",
  "properties": {
    "iso:country":"US",
    "sg:address":"8535 Hankins Rd Ste B",
    "sg:city":"Charlotte",
    "sg:classifiers":[
        {
            "category":"Education",
            "subcategory":"Music School",
            "type":"Public Place"
        }
    ],
    "sg:phone":"+1 704 599 1230",
    "sg:postcode":"28269",
    "sg:province":"NC",
    "sg:tags":[
        "instruction-instrumental"
    ],
    "wof:name":"Music49 Inc",
    "wof:placetype":"venue"
},
  "geometry": {"coordinates":[-80.83287900000001,35.339642],"type":"Point"}
}