{
  "type": "Feature",
  "properties": {
    "iso:country":"US",
    "sg:address":"118 Wilshire Ln",
    "sg:city":"Four Oaks",
    "sg:classifiers":[
        {
            "category":"Retail",
            "subcategory":"Animal Services",
            "type":"Services"
        }
    ],
    "sg:phone":"+1 919 553 2777",
    "sg:postcode":"27524",
    "sg:province":"NC",
    "sg:tags":[
        "pet",
        "boarding",
        "sitting"
    ],
    "wof:name":"Two Paws Up Pet Sitting",
    "wof:placetype":"venue"
},
  "geometry": {"coordinates":[-78.512795,35.514034],"type":"Point"}
}