{
  "type": "Feature",
  "properties": {
    "iso:country":"US",
    "sg:address":"2929 Breezewood Ave",
    "sg:city":"Fayetteville",
    "sg:classifiers":[
        {
            "category":"Building & Trades",
            "subcategory":"Construction",
            "type":"Services"
        }
    ],
    "sg:phone":"+1 910 486 4864",
    "sg:postcode":"28303",
    "sg:province":"NC",
    "sg:tags":[
        "house",
        "general",
        "contractor"
    ],
    "sg:website":"www.hhconstructors.com",
    "wof:name":"H & H Constructors  Inc",
    "wof:placetype":"venue"
},
  "geometry": {"coordinates":[-78.92772100000001,35.043887],"type":"Point"}
}