{
  "type": "Feature",
  "properties": {
    "iso:country":"US",
    "sg:address":"140 Steve Basnight Rd",
    "sg:city":"Manteo",
    "sg:classifiers":[
        {
            "category":"Building & Trades",
            "subcategory":"Plumbing",
            "type":"Services"
        }
    ],
    "sg:phone":"+1 252 473 1032",
    "sg:postcode":"27954",
    "sg:province":"NC",
    "sg:tags":[
        "contractor"
    ],
    "wof:name":"Ocean Spray Plumbing Service",
    "wof:placetype":"venue"
},
  "geometry": {"coordinates":[-75.693629,35.927789],"type":"Point"}
}