{
  "type": "Feature",
  "properties": {
    "addr:full":"1638 Owen Dr Fayetteville NC 28304",
    "addr:housenumber":"1638",
    "addr:postcode":"28304",
    "addr:street":"Owen Dr",
    "iso:country":"US",
    "sg:address":"1638 Owen Dr",
    "sg:city":"Fayetteville",
    "sg:classifiers":[
        {
            "category":"Health Services",
            "subcategory":"Doctor",
            "type":"Services"
        }
    ],
    "sg:phone":"+1 910 609 7246",
    "sg:postcode":"28304",
    "sg:province":"NC",
    "sg:tags":[
        "physician",
        "surgeon"
    ],
    "wof:name":"Pain Management Ctr",
    "wof:placetype":"venue"
},
  "geometry": {"coordinates":[-78.930986,35.032014],"type":"Point"}
}