{
  "type": "Feature",
  "properties": {
    "addr:full":"409 Rodney Orr Byp Robbinsville NC 28771",
    "addr:housenumber":"409",
    "addr:postcode":"28771",
    "addr:street":"Rodney Orr Byp",
    "iso:country":"US",
    "sg:address":"409 Rodney Orr Byp",
    "sg:city":"Robbinsville",
    "sg:classifiers":[
        {
            "category":"Autos & Motor Vehicles",
            "subcategory":"Automobile Sales",
            "type":"Retail Goods"
        }
    ],
    "sg:phone":"+1 828 479 3785",
    "sg:postcode":"28771",
    "sg:province":"NC",
    "sg:tags":[
        "car",
        "dealer"
    ],
    "wof:name":"Collins Auto Sales",
    "wof:placetype":"venue"
},
  "geometry": {"coordinates":[-83.804706,35.326668],"type":"Point"}
}