{
  "type": "Feature",
  "properties": {
    "addr:full":"4025 Fairwind Dr Winston Salem NC 27106",
    "addr:housenumber":"4025",
    "addr:postcode":"27106",
    "addr:street":"Fairwind Dr",
    "iso:country":"US",
    "sg:address":"4025 Fairwind Dr",
    "sg:city":"Winston Salem",
    "sg:classifiers":[
        {
            "category":"Real Estate",
            "subcategory":"Real Estate Operator",
            "type":"Services"
        }
    ],
    "sg:phone":"+1 336 924 2607",
    "sg:postcode":"27106",
    "sg:province":"NC",
    "sg:tags":[
        "building",
        "nonresidential"
    ],
    "wof:name":"Fairwind Properties LLC",
    "wof:placetype":"venue"
},
  "geometry": {"coordinates":[-80.342913,36.12952],"type":"Point"}
}