{
  "type": "Feature",
  "properties": {
    "addr:full":"3161 State Hwy 10 E Claremont NC 28610",
    "addr:housenumber":"3161",
    "addr:postcode":"28610",
    "addr:street":"State Hwy 10 E",
    "iso:country":"US",
    "sg:address":"3161 State Hwy 10 E",
    "sg:city":"Claremont",
    "sg:classifiers":[
        {
            "category":"Restaurant",
            "type":"Food & Drink"
        }
    ],
    "sg:phone":"+1 828 465 4973",
    "sg:postcode":"28610",
    "sg:province":"NC",
    "sg:tags":[
        "eating"
    ],
    "wof:name":"Spuds Cafe & Bakery",
    "wof:placetype":"venue"
},
  "geometry": {"coordinates":[-81.15021299999999,35.673417],"type":"Point"}
}