{
  "type": "Feature",
  "properties": {
    "addr:full":"115 Birchland Dr Fuquay Varina NC 27526",
    "addr:housenumber":"115",
    "addr:postcode":"27526",
    "addr:street":"Birchland Dr",
    "iso:country":"US",
    "sg:address":"115 Birchland Dr",
    "sg:city":"Fuquay Varina",
    "sg:classifiers":[
        {
            "category":"Retail",
            "subcategory":"Portrait Studio",
            "type":"Services"
        }
    ],
    "sg:phone":"+1   ",
    "sg:postcode":"27526",
    "sg:province":"NC",
    "sg:tags":[
        "photo"
    ],
    "wof:name":"Robin Cotten Photography",
    "wof:placetype":"venue"
},
  "geometry": {"coordinates":[-78.79483,35.612786],"type":"Point"}
}