{
  "type": "Feature",
  "properties": {
    "addr:full":"9768 Ringwood Rd Enfield NC 27823",
    "addr:housenumber":"9768",
    "addr:postcode":"27823",
    "addr:street":"Ringwood Rd",
    "iso:country":"US",
    "sg:address":"9768 Ringwood Rd",
    "sg:city":"Enfield",
    "sg:classifiers":[
        {
            "category":"Government",
            "subcategory":"Fire Station",
            "type":"Public Place"
        }
    ],
    "sg:phone":"+1 252 445 9915",
    "sg:postcode":"27823",
    "sg:province":"NC",
    "sg:tags":[
        "department"
    ],
    "wof:name":"Enfield Fire Dept Sub Station",
    "wof:placetype":"venue"
},
  "geometry": {"coordinates":[-77.830551,36.216217],"type":"Point"}
}