{
  "type": "Feature",
  "properties": {
    "iso:country":"US",
    "sg:address":"2709 Water Ridge Pkwy",
    "sg:city":"Charlotte",
    "sg:classifiers":[
        {
            "category":"Professional",
            "type":"Services"
        }
    ],
    "sg:phone":"+1 704 329 2500",
    "sg:postcode":"28217",
    "sg:province":"NC",
    "wof:name":"Bibliostatcom",
    "wof:placetype":"venue"
},
  "geometry": {"coordinates":[-80.92533299999999,35.186744],"type":"Point"}
}