{
  "type": "Feature",
  "properties": {
    "addr:full":"310 Rollingwood Dr Dudley NC 28333",
    "addr:housenumber":"310",
    "addr:postcode":"28333",
    "addr:street":"Rollingwood Dr",
    "iso:country":"US",
    "sg:address":"310 Rollingwood Dr",
    "sg:city":"Dudley",
    "sg:classifiers":[
        {
            "category":"Professional",
            "type":"Services"
        }
    ],
    "sg:phone":"+1 919 734 4525",
    "sg:postcode":"28333",
    "sg:province":"NC",
    "wof:name":"Lance Wilder",
    "wof:placetype":"venue"
},
  "geometry": {"coordinates":[-78.02574799999999,35.29309],"type":"Point"}
}