{
  "type": "Feature",
  "properties": {
    "iso:country":"US",
    "sg:address":"27 Page Ave",
    "sg:city":"Asheville",
    "sg:classifiers":[
        {
            "category":"Professional",
            "type":"Services"
        }
    ],
    "sg:phone":"+1 828 253 8801",
    "sg:postcode":"28801",
    "sg:province":"NC",
    "sg:tags":[
        "establishment"
    ],
    "wof:name":"J Kimmel & Co",
    "wof:placetype":"venue"
},
  "geometry": {"coordinates":[-82.556009,35.595271],"type":"Point"}
}