{
  "type": "Feature",
  "properties": {
    "iso:country":"US",
    "sg:address":"109 Kemp Rd E",
    "sg:city":"Greensboro",
    "sg:classifiers":[
        {
            "category":"Restaurant",
            "type":"Food & Drink"
        }
    ],
    "sg:phone":"+1 336 299 1070",
    "sg:postcode":"27410",
    "sg:province":"NC",
    "sg:tags":[
        "eating"
    ],
    "wof:name":"Yoga Cafe Inc",
    "wof:placetype":"venue"
},
  "geometry": {"coordinates":[-79.854834,36.086406],"type":"Point"}
}