{
  "type": "Feature",
  "properties": {
    "addr:full":"100 Hospital Dr Fletcher NC 28721",
    "addr:housenumber":"100",
    "addr:postcode":"28721",
    "addr:street":"Hospital Dr",
    "iso:country":"US",
    "sg:address":"100 Hospital Dr",
    "sg:city":"Fletcher",
    "sg:classifiers":[
        {
            "category":"Health Services",
            "subcategory":"Hospital",
            "type":"Services"
        }
    ],
    "sg:phone":"+1 828 687 5281",
    "sg:postcode":"28721",
    "sg:province":"NC",
    "sg:website":"www.parkridgehospital.org",
    "wof:name":"Park Ridge Hosp Billing Inqrs",
    "wof:placetype":"venue"
},
  "geometry": {"coordinates":[-82.948796,35.526842],"type":"Point"}
}