{
  "type": "Feature",
  "properties": {
    "iso:country":"US",
    "sg:address":"140 Wintergreen Dr",
    "sg:city":"Lumberton",
    "sg:classifiers":[
        {
            "category":"Restaurant",
            "type":"Food & Drink"
        }
    ],
    "sg:menulink":"http://www.allmenus.com/nc/lumberton/101852-huddle-house/menu/",
    "sg:phone":"+1 910 739 6090",
    "sg:postcode":"28358",
    "sg:province":"NC",
    "sg:tags":[
        "american",
        "diner"
    ],
    "wof:name":"Huddle House",
    "wof:placetype":"venue"
},
  "geometry": {"coordinates":[-79.002792,34.669606],"type":"Point"}
}