{
  "type": "Feature",
  "properties": {
    "iso:country":"US",
    "sg:address":"208 Luck Rd",
    "sg:city":"Asheboro",
    "sg:classifiers":[
        {
            "category":"Manufacturing",
            "subcategory":"Petroleum Products",
            "type":"Manufacturing & Wholesale Goods"
        },
        {
            "category":"Home & Garden",
            "subcategory":"Building Materials",
            "type":"Retail Goods"
        }
    ],
    "sg:phone":"+1 336 625 9727",
    "sg:postcode":"27205",
    "sg:province":"NC",
    "sg:tags":[
        "asphalt",
        "mfg"
    ],
    "wof:name":"Triad Corrugated Metal Inc",
    "wof:placetype":"venue"
},
  "geometry": {"coordinates":[-79.771348,35.710244],"type":"Point"}
}