{
  "type": "Feature",
  "properties": {
    "iso:country":"US",
    "sg:address":"4918 Addison Dr",
    "sg:city":"Charlotte",
    "sg:classifiers":[
        {
            "category":"Education",
            "subcategory":"Special Training",
            "type":"Public Place"
        }
    ],
    "sg:phone":"+1 704 334 4631",
    "sg:postcode":"28211",
    "sg:province":"NC",
    "sg:tags":[
        "management"
    ],
    "wof:name":"Charlotte Outdoor Adventure",
    "wof:placetype":"venue"
},
  "geometry": {"coordinates":[-80.787513,35.172934],"type":"Point"}
}