{
  "type": "Feature",
  "properties": {
    "iso:country":"US",
    "sg:address":"5404 Clustermill Dr",
    "sg:city":"Greensboro",
    "sg:classifiers":[
        {
            "category":"Social Services",
            "type":"Services"
        }
    ],
    "sg:phone":"+1   ",
    "sg:postcode":"27407",
    "sg:province":"NC",
    "wof:name":"Motivational Achievements Inc",
    "wof:placetype":"venue"
},
  "geometry": {"coordinates":[-79.90604399999999,36.016207],"type":"Point"}
}