{
  "type": "Feature",
  "properties": {
    "iso:country":"US",
    "sg:address":"119 Amrita Ct",
    "sg:city":"Charlotte",
    "sg:classifiers":[
        {
            "category":"Communications",
            "subcategory":"Radio Station",
            "type":"Services"
        }
    ],
    "sg:phone":"+1 704 362 0108",
    "sg:postcode":"28211",
    "sg:province":"NC",
    "sg:tags":[
        "company",
        "broadcasting"
    ],
    "wof:name":"Jennings Communications Corp",
    "wof:placetype":"venue"
},
  "geometry": {"coordinates":[-80.78919500000001,35.162851],"type":"Point"}
}