{
  "type": "Feature",
  "properties": {
    "addr:full":"727 Westminster Dr Statesville NC 28677",
    "addr:housenumber":"727",
    "addr:postcode":"28677",
    "addr:street":"Westminster Dr",
    "iso:country":"US",
    "sg:address":"727 Westminster Dr",
    "sg:city":"Statesville",
    "sg:classifiers":[
        {
            "category":"Food & Beverages",
            "subcategory":"Specialty",
            "type":"Retail Goods"
        }
    ],
    "sg:phone":"+1 704 871 8935",
    "sg:postcode":"28677",
    "sg:province":"NC",
    "wof:name":"Product La Abuela",
    "wof:placetype":"venue"
},
  "geometry": {"coordinates":[-80.94225400000001,35.783014],"type":"Point"}
}