{
  "type": "Feature",
  "properties": {
    "iso:country":"US",
    "sg:address":"9101 State Hwy 11",
    "sg:city":"Willard",
    "sg:classifiers":[
        {
            "category":"Organizations",
            "subcategory":"Religious Organization",
            "type":"Services"
        }
    ],
    "sg:phone":"+1 910 285 8373",
    "sg:postcode":"28478",
    "sg:province":"NC",
    "sg:tags":[
        "church"
    ],
    "wof:name":"Undenominational Pentecostal",
    "wof:placetype":"venue"
},
  "geometry": {"coordinates":[-77.972005,34.693839],"type":"Point"}
}