{
  "type": "Feature",
  "properties": {
    "addr:full":"3101 Fayetteville Rd Durham NC 27707",
    "addr:housenumber":"3101",
    "addr:postcode":"27707",
    "addr:street":"Fayetteville Rd",
    "iso:country":"US",
    "sg:address":"3101 Fayetteville Rd",
    "sg:city":"Durham",
    "sg:classifiers":[
        {
            "category":"Autos & Motor Vehicles",
            "subcategory":"Automobile Sales",
            "type":"Retail Goods"
        }
    ],
    "sg:phone":"+1 919 688 0300",
    "sg:postcode":"27707",
    "sg:province":"NC",
    "sg:tags":[
        "car",
        "dealer"
    ],
    "wof:name":"A & F Auto Sales",
    "wof:placetype":"venue"
},
  "geometry": {"coordinates":[-78.909218,35.961576],"type":"Point"}
}