{
  "type": "Feature",
  "properties": {
    "addr:full":"2787 Richlands Hwy Jacksonville NC 28540",
    "addr:housenumber":"2787",
    "addr:postcode":"28540",
    "addr:street":"Richlands Hwy",
    "iso:country":"US",
    "sg:address":"2787 Richlands Hwy",
    "sg:city":"Jacksonville",
    "sg:classifiers":[
        {
            "category":"Retail",
            "subcategory":"Repair Shop",
            "type":"Services"
        },
        {
            "category":"Building & Trades",
            "subcategory":"Plumbing",
            "type":"Services"
        }
    ],
    "sg:phone":"+1 910 347 6181",
    "sg:postcode":"28540",
    "sg:province":"NC",
    "sg:tags":[
        "septic"
    ],
    "wof:name":"Roy Healths Septic Tank Svc",
    "wof:placetype":"venue"
},
  "geometry": {"coordinates":[-77.461713,34.7549],"type":"Point"}
}