{
  "type": "Feature",
  "properties": {
    "iso:country":"US",
    "sg:address":"2631 Brentwood Rd",
    "sg:city":"Raleigh",
    "sg:classifiers":[
        {
            "category":"Wholesale",
            "subcategory":"Machinery & Supplies",
            "type":"Manufacturing & Wholesale Goods"
        }
    ],
    "sg:phone":"+1 919 874 0303",
    "sg:postcode":"27604",
    "sg:province":"NC",
    "sg:tags":[
        "farm",
        "turf",
        "commercial"
    ],
    "wof:name":"Revels Tractor Co Inc",
    "wof:placetype":"venue"
},
  "geometry": {"coordinates":[-78.594427,35.809062],"type":"Point"}
}