{
  "type": "Feature",
  "properties": {
    "iso:country":"US",
    "sg:address":"2233 New Hope Church Rd",
    "sg:city":"Raleigh",
    "sg:classifiers":[
        {
            "category":"Insurance",
            "subcategory":"Insurance Agent",
            "type":"Services"
        }
    ],
    "sg:phone":"+1 919 872 0084",
    "sg:postcode":"27604",
    "sg:province":"NC",
    "wof:name":"Francisco Gonzalez Insurance",
    "wof:placetype":"venue"
},
  "geometry": {"coordinates":[-78.600077,35.834993],"type":"Point"}
}