{
  "type": "Feature",
  "properties": {
    "iso:country":"US",
    "sg:address":"511 Maymount Dr",
    "sg:city":"Durham",
    "sg:classifiers":[
        {
            "category":"Real Estate",
            "subcategory":"Developer",
            "type":"Services"
        }
    ],
    "sg:phone":"+1 919 477 1437",
    "sg:postcode":"27703",
    "sg:province":"NC",
    "wof:name":"Bridges Housing Corporation",
    "wof:placetype":"venue"
},
  "geometry": {"coordinates":[-78.828091,35.992593],"type":"Point"}
}