{
  "type": "Feature",
  "properties": {
    "iso:country":"US",
    "sg:address":"2450 Piney Grove Rd",
    "sg:city":"Kernersville",
    "sg:classifiers":[
        {
            "category":"Manufacturing",
            "subcategory":"Lumber",
            "type":"Manufacturing & Wholesale Goods"
        }
    ],
    "sg:phone":"+1 336 993 8477",
    "sg:postcode":"27284",
    "sg:province":"NC",
    "sg:tags":[
        "logging"
    ],
    "wof:name":"Nelson and Son Logging",
    "wof:placetype":"venue"
},
  "geometry": {"coordinates":[-80.059027,36.188373],"type":"Point"}
}