{
  "type": "Feature",
  "properties": {
    "addr:full":"37 Tree Top Dr Arden NC 28704",
    "addr:housenumber":"37",
    "addr:postcode":"28704",
    "addr:street":"Tree Top Dr",
    "iso:country":"US",
    "sg:address":"37 Tree Top Dr",
    "sg:city":"Arden",
    "sg:classifiers":[
        {
            "category":"Building & Trades",
            "subcategory":"Construction",
            "type":"Services"
        }
    ],
    "sg:phone":"+1 828 681 1788",
    "sg:postcode":"28704",
    "sg:province":"NC",
    "sg:tags":[
        "general",
        "contractor"
    ],
    "wof:name":"R L Franklin Inc",
    "wof:placetype":"venue"
},
  "geometry": {"coordinates":[-82.49402000000001,35.467165],"type":"Point"}
}