{
  "type": "Feature",
  "properties": {
    "addr:full":"119 Riverside Dr Asheville NC 28804",
    "addr:housenumber":"119",
    "addr:postcode":"28804",
    "addr:street":"Riverside Dr",
    "iso:country":"US",
    "sg:address":"119 Riverside Dr",
    "sg:city":"Asheville",
    "sg:classifiers":[
        {
            "category":"Health Services",
            "subcategory":"Optometrist",
            "type":"Services"
        }
    ],
    "sg:phone":"+1 828 254 0429",
    "sg:postcode":"28804",
    "sg:province":"NC",
    "wof:name":"Drain Vision",
    "wof:placetype":"venue"
},
  "geometry": {"coordinates":[-82.569525,35.588054],"type":"Point"}
}