{
  "type": "Feature",
  "properties": {
    "addr:full":"2201 Randleman Rd Greensboro NC 27406",
    "addr:housenumber":"2201",
    "addr:postcode":"27406",
    "addr:street":"Randleman Rd",
    "iso:country":"US",
    "sg:address":"2201 Randleman Rd",
    "sg:city":"Greensboro",
    "sg:classifiers":[
        {
            "category":"Building & Trades",
            "subcategory":"Construction",
            "type":"Services"
        }
    ],
    "sg:phone":"+1 336 288 6620",
    "sg:postcode":"27406",
    "sg:province":"NC",
    "sg:tags":[
        "contractor"
    ],
    "wof:name":"Triad Roofing & Construction",
    "wof:placetype":"venue"
},
  "geometry": {"coordinates":[-79.80041799999999,36.044894],"type":"Point"}
}