{
  "type": "Feature",
  "properties": {
    "addr:full":"6737 1st Ave Indian Trail NC 28079",
    "addr:housenumber":"6737",
    "addr:postcode":"28079",
    "addr:street":"1St Ave",
    "iso:country":"US",
    "sg:address":"6737 1st Ave",
    "sg:city":"Indian Trail",
    "sg:classifiers":[
        {
            "category":"Building & Trades",
            "subcategory":"Construction",
            "type":"Services"
        }
    ],
    "sg:phone":"+1 704 882 5498",
    "sg:postcode":"28079",
    "sg:province":"NC",
    "sg:tags":[
        "grading",
        "contractor"
    ],
    "wof:name":"Union County Public Works",
    "wof:placetype":"venue"
},
  "geometry": {"coordinates":[-80.646215,35.089451],"type":"Point"}
}