{
  "type": "Feature",
  "properties": {
    "addr:full":"519 Hardin Rd Forest City NC 28043",
    "addr:housenumber":"519",
    "addr:postcode":"28043",
    "addr:street":"Hardin Rd",
    "iso:country":"US",
    "sg:address":"519 Hardin Rd",
    "sg:city":"Forest City",
    "sg:classifiers":[
        {
            "category":"Personal",
            "subcategory":"Beauty Salon",
            "type":"Services"
        }
    ],
    "sg:phone":"+1   ",
    "sg:postcode":"28043",
    "sg:province":"NC",
    "sg:tags":[
        "shop"
    ],
    "wof:name":"Hair Productions",
    "wof:placetype":"venue"
},
  "geometry": {"coordinates":[-81.88131,35.333977],"type":"Point"}
}