{
  "type": "Feature",
  "properties": {
    "addr:full":"120 W Cornwallis Rd Durham NC 27707",
    "addr:housenumber":"120",
    "addr:postcode":"27707",
    "addr:street":"W Cornwallis Rd",
    "iso:country":"US",
    "sg:address":"120 W Cornwallis Rd",
    "sg:city":"Durham",
    "sg:classifiers":[
        {
            "category":"Professional",
            "subcategory":"Management & Consulting",
            "type":"Services"
        }
    ],
    "sg:phone":"+1   ",
    "sg:postcode":"27707",
    "sg:province":"NC",
    "sg:tags":[
        "business"
    ],
    "wof:name":"Clean Core",
    "wof:placetype":"venue"
},
  "geometry": {"coordinates":[-78.921685,35.966747],"type":"Point"}
}