{
  "type": "Feature",
  "properties": {
    "addr:full":"2660 Yonkers Rd Raleigh NC 27604",
    "addr:postcode":"2660;27604",
    "addr:street":"Yonkers Rd",
    "iso:country":"US",
    "sg:address":"2660 Yonkers Rd",
    "sg:city":"Raleigh",
    "sg:classifiers":[
        {
            "category":"Wholesale",
            "subcategory":"Hardware",
            "type":"Manufacturing & Wholesale Goods"
        },
        {
            "category":"Building & Trades",
            "subcategory":"Plumbing",
            "type":"Services"
        }
    ],
    "sg:phone":"+1 919 787 0376",
    "sg:postcode":"27604",
    "sg:province":"NC",
    "sg:tags":[
        "co",
        "system",
        "heating",
        "air",
        "conditioning",
        "representative",
        "contractor",
        "manufacturer"
    ],
    "sg:website":"www.fha-hvac.com",
    "wof:name":"Faulkner/Haynes Associates",
    "wof:placetype":"venue"
},
  "geometry": {"coordinates":[-78.59424199999999,35.802482],"type":"Point"}
}