{
  "type": "Feature",
  "properties": {
    "addr:full":"2565 Welcome School Rd Autryville NC 28318",
    "addr:housenumber":"2565",
    "addr:postcode":"28318",
    "addr:street":"Welcome School Rd",
    "iso:country":"US",
    "sg:address":"2565 Welcome School Rd",
    "sg:city":"Autryville",
    "sg:classifiers":[
        {
            "category":"Autos & Motor Vehicles",
            "subcategory":"Automobile Sales",
            "type":"Retail Goods"
        }
    ],
    "sg:phone":"+1 910 567 2367",
    "sg:postcode":"28318",
    "sg:province":"NC",
    "sg:tags":[
        "car",
        "dealer"
    ],
    "wof:name":"3 J's Auto Sale",
    "wof:placetype":"venue"
},
  "geometry": {"coordinates":[-78.601795,35.106078],"type":"Point"}
}