{
  "type": "Feature",
  "properties": {
    "iso:country":"US",
    "sg:address":"12510 State Hwy 50",
    "sg:city":"Holly Ridge",
    "sg:classifiers":[
        {
            "category":"Retail",
            "subcategory":"Repair Shop",
            "type":"Services"
        }
    ],
    "sg:phone":"+1   ",
    "sg:postcode":"28445",
    "sg:province":"NC",
    "sg:tags":[
        "welding"
    ],
    "wof:name":"A & A Welding",
    "wof:placetype":"venue"
},
  "geometry": {"coordinates":[-77.561331,34.462655],"type":"Point"}
}