{
  "type": "Feature",
  "properties": {
    "iso:country":"US",
    "sg:address":"2547 Palmer Ct",
    "sg:city":"Wake Forest",
    "sg:classifiers":[
        {
            "category":"Real Estate",
            "subcategory":"Real Estate Operator",
            "type":"Services"
        }
    ],
    "sg:phone":"+1 919 569 9580",
    "sg:postcode":"27587",
    "sg:province":"NC",
    "sg:tags":[
        "building",
        "nonresidential"
    ],
    "wof:name":"Haygood Properties LLC",
    "wof:placetype":"venue"
},
  "geometry": {"coordinates":[-78.537781,36.004624],"type":"Point"}
}