{
  "type": "Feature",
  "properties": {
    "addr:full":"174 Brisson Carrol Rd Tar Heel NC 28392",
    "addr:housenumber":"174",
    "addr:postcode":"28392",
    "addr:street":"Brisson Carrol Rd",
    "iso:country":"US",
    "sg:address":"174 Brisson Carrol Rd",
    "sg:city":"Tar Heel",
    "sg:classifiers":[
        {
            "category":"Building & Trades",
            "subcategory":"Construction",
            "type":"Services"
        }
    ],
    "sg:phone":"+1 910 647 2631",
    "sg:postcode":"28392",
    "sg:province":"NC",
    "sg:tags":[
        "roofing",
        "contractor"
    ],
    "wof:name":"Custom Foam Insulation",
    "wof:placetype":"venue"
},
  "geometry": {"coordinates":[-78.761653,34.680999],"type":"Point"}
}