{
  "type": "Feature",
  "properties": {
    "iso:country":"US",
    "sg:address":"124 Norwood James Ln",
    "sg:city":"Warsaw",
    "sg:classifiers":[
        {
            "category":"Farming",
            "subcategory":"Farm",
            "type":"Manufacturing & Wholesale Goods"
        }
    ],
    "sg:phone":"+1 910 293 4895",
    "sg:postcode":"28398",
    "sg:province":"NC",
    "wof:name":"James Farms",
    "wof:placetype":"venue"
},
  "geometry": {"coordinates":[-78.124449,35.051616],"type":"Point"}
}