{
  "type": "Feature",
  "properties": {
    "iso:country":"US",
    "sg:address":"211 Creek Ridge Rd",
    "sg:city":"Greensboro",
    "sg:classifiers":[
        {
            "category":"Autos & Motor Vehicles",
            "subcategory":"Auto Supplies",
            "type":"Retail Goods"
        }
    ],
    "sg:phone":"+1 336 271 2662",
    "sg:postcode":"27406",
    "sg:province":"NC",
    "sg:tags":[
        "automobile",
        "parts"
    ],
    "wof:name":"KOOL First",
    "wof:placetype":"venue"
},
  "geometry": {"coordinates":[-79.79521800000001,36.029793],"type":"Point"}
}