{
  "type": "Feature",
  "properties": {
    "iso:country":"US",
    "sg:address":"1060 Haywood Road",
    "sg:city":"Asheville",
    "sg:classifiers":[
        {
            "category":"Personal",
            "subcategory":"Barber",
            "type":"Services"
        }
    ],
    "sg:phone":"+1 828 252 8849",
    "sg:postcode":"28806",
    "sg:province":"NC",
    "wof:name":"Looking Good Barbershop",
    "wof:placetype":"venue"
},
  "geometry": {"coordinates":[-82.60445,35.581935],"type":"Point"}
}