{
  "type": "Feature",
  "properties": {
    "addr:full":"8326 State Hwy 53 Burgaw NC 28425",
    "addr:housenumber":"8326",
    "addr:postcode":"28425",
    "addr:street":"State Hwy 53",
    "iso:country":"US",
    "sg:address":"8326 State Hwy 53",
    "sg:city":"Burgaw",
    "sg:classifiers":[
        {
            "category":"Shopping",
            "subcategory":"Used Merchandise",
            "type":"Retail Goods"
        }
    ],
    "sg:phone":"+1 910 259 2283",
    "sg:postcode":"28425",
    "sg:province":"NC",
    "wof:name":"Barnyard Flea Market",
    "wof:placetype":"venue"
},
  "geometry": {"coordinates":[-78.06196799999999,34.537882],"type":"Point"}
}