{
  "type": "Feature",
  "properties": {
    "addr:full":"3011 Boone Trl Exd Fayetteville NC 28304",
    "addr:housenumber":"3011",
    "addr:postcode":"28304",
    "addr:street":"Boone Trl Exd",
    "iso:country":"US",
    "sg:address":"3011 Boone Trl Exd",
    "sg:city":"Fayetteville",
    "sg:classifiers":[
        {
            "category":"Insurance",
            "subcategory":"Insurance Agent",
            "type":"Services"
        }
    ],
    "sg:phone":"+1 910 321 1800",
    "sg:postcode":"28304",
    "sg:province":"NC",
    "wof:name":"Nation Wide Claims",
    "wof:placetype":"venue"
},
  "geometry": {"coordinates":[-78.924379,35.031429],"type":"Point"}
}