{
  "type": "Feature",
  "properties": {
    "iso:country":"US",
    "sg:address":"2200 W Main St",
    "sg:city":"Durham",
    "sg:classifiers":[
        {
            "category":"Professional",
            "subcategory":"Lawyer & Legal Services",
            "type":"Services"
        }
    ],
    "sg:phone":"+1 919 286 8097",
    "sg:postcode":"27705",
    "sg:province":"NC",
    "sg:tags":[
        "attorney"
    ],
    "wof:name":"Jennifer L Skord",
    "wof:placetype":"venue"
},
  "geometry": {"coordinates":[-78.92582299999999,36.007016],"type":"Point"}
}