{
  "type": "Feature",
  "properties": {
    "iso:country":"US",
    "sg:address":"106 Mathis St",
    "sg:city":"Jonesville",
    "sg:classifiers":[
        {
            "category":"Organizations",
            "subcategory":"Religious Organization",
            "type":"Services"
        }
    ],
    "sg:phone":"+1   ",
    "sg:postcode":"28642",
    "sg:province":"NC",
    "wof:name":"Mount Pleasant Baptist Church",
    "wof:placetype":"venue"
},
  "geometry": {"coordinates":[-80.85265099999999,36.227722],"type":"Point"}
}