{
  "type": "Feature",
  "properties": {
    "addr:full":"428 Carthage St Cameron NC 28326",
    "addr:housenumber":"428",
    "addr:postcode":"28326",
    "addr:street":"Carthage St",
    "iso:country":"US",
    "sg:address":"428 Carthage St",
    "sg:city":"Cameron",
    "sg:classifiers":[
        {
            "category":"Shopping",
            "subcategory":"Used Merchandise",
            "type":"Retail Goods"
        }
    ],
    "sg:phone":"+1 910 245 1165",
    "sg:postcode":"28326",
    "sg:province":"NC",
    "sg:tags":[
        "antique"
    ],
    "wof:name":"Whim",
    "wof:placetype":"venue"
},
  "geometry": {"coordinates":[-79.25277199999999,35.326161],"type":"Point"}
}