{
  "type": "Feature",
  "properties": {
    "iso:country":"US",
    "sg:address":"714 Montana Dr",
    "sg:city":"Charlotte",
    "sg:classifiers":[
        {
            "category":"Banks & Credit Unions",
            "subcategory":"Financial Services",
            "type":"Services"
        }
    ],
    "sg:phone":"+1 704 392 6500",
    "sg:postcode":"28216",
    "sg:province":"NC",
    "sg:tags":[
        "company",
        "holding"
    ],
    "wof:name":"Nuray Holdings",
    "wof:placetype":"venue"
},
  "geometry": {"coordinates":[-80.873124,35.266422],"type":"Point"}
}