{
  "type": "Feature",
  "properties": {
    "iso:country":"US",
    "sg:address":"2011 Canterwood Dr",
    "sg:city":"Charlotte",
    "sg:classifiers":[
        {
            "category":"Arts & Performance",
            "subcategory":"Theater",
            "type":"Entertainment"
        }
    ],
    "sg:phone":"+1   ",
    "sg:postcode":"28213",
    "sg:province":"NC",
    "sg:tags":[
        "group"
    ],
    "wof:name":"Yinks Productions",
    "wof:placetype":"venue"
},
  "geometry": {"coordinates":[-80.77203900000001,35.275658],"type":"Point"}
}