{
  "type": "Feature",
  "properties": {
    "iso:country":"US",
    "sg:address":"1104 Smokewood Dr",
    "sg:city":"Apex",
    "sg:classifiers":[
        {
            "category":"Professional",
            "type":"Services"
        }
    ],
    "sg:phone":"+1 919 387 1212",
    "sg:postcode":"27502",
    "sg:province":"NC",
    "wof:name":"Farrell Patrick",
    "wof:placetype":"venue"
},
  "geometry": {"coordinates":[-78.833417,35.740804],"type":"Point"}
}