{
  "type": "Feature",
  "properties": {
    "addr:full":"312 W Trade St Charlotte NC 28202",
    "addr:housenumber":"312",
    "addr:postcode":"28202",
    "addr:street":"W Trade St",
    "iso:country":"US",
    "sg:address":"312 W Trade St",
    "sg:city":"Charlotte",
    "sg:classifiers":[
        {
            "category":"Parking",
            "type":"Transportation"
        }
    ],
    "sg:phone":"+1 704 376 5559",
    "sg:postcode":"28202",
    "sg:province":"NC",
    "sg:tags":[
        "garage"
    ],
    "wof:name":"E-Z Parking",
    "wof:placetype":"venue"
},
  "geometry": {"coordinates":[-80.84555400000001,35.229416],"type":"Point"}
}