{
  "type": "Feature",
  "properties": {
    "addr:full":"6609 Waldos Beach Rd Fayetteville NC 28306",
    "addr:housenumber":"6609",
    "addr:postcode":"28306",
    "addr:street":"Waldos Beach Rd",
    "iso:country":"US",
    "sg:address":"6609 Waldos Beach Rd",
    "sg:city":"Fayetteville",
    "sg:classifiers":[
        {
            "category":"Building & Trades",
            "subcategory":"Construction",
            "type":"Services"
        }
    ],
    "sg:phone":"+1 910 424 6241",
    "sg:postcode":"28306",
    "sg:province":"NC",
    "sg:tags":[
        "downspouts",
        "gutter"
    ],
    "wof:name":"Gutter Connection",
    "wof:placetype":"venue"
},
  "geometry": {"coordinates":[-79.018914,34.960041],"type":"Point"}
}