{
  "type": "Feature",
  "properties": {
    "addr:full":"280 Pinehurst Ave Southern Pines NC 28387",
    "addr:housenumber":"280",
    "addr:postcode":"28387",
    "addr:street":"Pinehurst Ave",
    "iso:country":"US",
    "sg:address":"280 Pinehurst Ave",
    "sg:city":"Southern Pines",
    "sg:classifiers":[
        {
            "category":"Banks & Credit Unions",
            "subcategory":"Bank",
            "type":"Services"
        }
    ],
    "sg:phone":"+1 910 692 8874",
    "sg:postcode":"28387",
    "sg:province":"NC",
    "sg:tags":[
        "loan",
        "real estate"
    ],
    "wof:name":"Integrity Mortgage Group",
    "wof:placetype":"venue"
},
  "geometry": {"coordinates":[-79.41617599999999,35.15988],"type":"Point"}
}