{
  "type": "Feature",
  "properties": {
    "addr:full":"200 S McMorrine St Elizabeth City NC 27909",
    "addr:housenumber":"200",
    "addr:postcode":"27909",
    "addr:street":"S Mcmorrine St",
    "iso:country":"US",
    "sg:address":"200 S McMorrine St",
    "sg:city":"Elizabeth City",
    "sg:classifiers":[
        {
            "category":"Organizations",
            "subcategory":"Religious Organization",
            "type":"Services"
        }
    ],
    "sg:phone":"+1 252 338 1686",
    "sg:postcode":"27909",
    "sg:province":"NC",
    "sg:tags":[
        "church"
    ],
    "wof:name":"Christ Episcopal Church Inc",
    "wof:placetype":"venue"
},
  "geometry": {"coordinates":[-76.22060999999999,36.299155],"type":"Point"}
}