{
  "type": "Feature",
  "properties": {
    "addr:full":"205 Bivens St Wingate NC 28174",
    "addr:housenumber":"205",
    "addr:postcode":"28174",
    "addr:street":"Bivens St",
    "iso:country":"US",
    "sg:address":"205 Bivens St",
    "sg:city":"Wingate",
    "sg:classifiers":[
        {
            "category":"Social Services",
            "subcategory":"Child Care",
            "type":"Services"
        }
    ],
    "sg:phone":"+1 704 233 9414",
    "sg:postcode":"28174",
    "sg:province":"NC",
    "sg:tags":[
        "school",
        "program",
        "after"
    ],
    "wof:name":"Wingate Elmntry School Prgrm",
    "wof:placetype":"venue"
},
  "geometry": {"coordinates":[-80.453971,34.984244],"type":"Point"}
}