{
  "type": "Feature",
  "properties": {
    "iso:country":"US",
    "sg:address":"2076 Statesville Hwy",
    "sg:city":"Mooresville",
    "sg:classifiers":[
        {
            "category":"Building & Trades",
            "subcategory":"Construction",
            "type":"Services"
        }
    ],
    "sg:phone":"+1 704 664 5823",
    "sg:postcode":"28115",
    "sg:province":"NC",
    "sg:tags":[
        "contractor",
        "specialty",
        "mfg"
    ],
    "wof:name":"Signco Inc",
    "wof:placetype":"venue"
},
  "geometry": {"coordinates":[-80.826261,35.621214],"type":"Point"}
}