{
  "type": "Feature",
  "properties": {
    "addr:full":"1066 Old Durham Rd Roxboro NC 27573",
    "addr:housenumber":"1066",
    "addr:postcode":"27573",
    "addr:street":"Old Durham Rd",
    "iso:country":"US",
    "sg:address":"1066 Old Durham Rd",
    "sg:city":"Roxboro",
    "sg:classifiers":[
        {
            "category":"Real Estate",
            "subcategory":"Real Estate Agent",
            "type":"Services"
        }
    ],
    "sg:phone":"+1 336 599 1231",
    "sg:postcode":"27573",
    "sg:province":"NC",
    "sg:tags":[
        "appraiser"
    ],
    "wof:name":"D K Peterson Group",
    "wof:placetype":"venue"
},
  "geometry": {"coordinates":[-78.979322,36.36292],"type":"Point"}
}