{
  "type": "Feature",
  "properties": {
    "iso:country":"US",
    "sg:address":"925 S Kerr Ave",
    "sg:city":"Wilmington",
    "sg:classifiers":[
        {
            "category":"Retail",
            "subcategory":"Repair Shop",
            "type":"Services"
        }
    ],
    "sg:phone":"+1 910 395 2203",
    "sg:postcode":"28403",
    "sg:province":"NC",
    "sg:tags":[
        "copier",
        "related"
    ],
    "wof:name":"Complete Copier Repair Inc",
    "wof:placetype":"venue"
},
  "geometry": {"coordinates":[-77.886842,34.217718],"type":"Point"}
}