{
  "type": "Feature",
  "properties": {
    "iso:country":"US",
    "sg:address":"309 Mangrove Dr",
    "sg:city":"Emerald Isle",
    "sg:classifiers":[
        {
            "category":"Shopping",
            "subcategory":"Music",
            "type":"Retail Goods"
        }
    ],
    "sg:phone":"+1 252 354 9017",
    "sg:postcode":"28594",
    "sg:province":"NC",
    "wof:name":"Emerald Video",
    "wof:placetype":"venue"
},
  "geometry": {"coordinates":[-77.042242,34.663723],"type":"Point"}
}