{
  "type": "Feature",
  "properties": {
    "iso:country":"US",
    "sg:address":"120 Dillingham Cir",
    "sg:city":"Asheville",
    "sg:classifiers":[
        {
            "category":"Building & Trades",
            "subcategory":"Construction",
            "type":"Services"
        }
    ],
    "sg:phone":"+1 828 298 5327",
    "sg:postcode":"28805",
    "sg:province":"NC",
    "sg:tags":[
        "house"
    ],
    "wof:name":"Mbs Construction",
    "wof:placetype":"venue"
},
  "geometry": {"coordinates":[-82.44927199999999,35.622106],"type":"Point"}
}