{
  "type": "Feature",
  "properties": {
    "addr:full":"19293 Great Smoky Mountain Expy Waynesville NC 28786",
    "addr:housenumber":"19293",
    "addr:postcode":"28786",
    "addr:street":"Great Smoky;Expy",
    "iso:country":"US",
    "sg:address":"19293 Great Smoky Mountain Expy",
    "sg:city":"Waynesville",
    "sg:classifiers":[
        {
            "category":"Shopping",
            "type":"Retail Goods"
        }
    ],
    "sg:phone":"+1 828 452 0598",
    "sg:postcode":"28786",
    "sg:province":"NC",
    "sg:tags":[
        "art",
        "gallery",
        "dealer"
    ],
    "wof:name":"Eagle Art Inc",
    "wof:placetype":"venue"
},
  "geometry": {"coordinates":[-83.057383,35.452615],"type":"Point"}
}