{
  "type": "Feature",
  "properties": {
    "addr:full":"2933 Damascus Rd Fayetteville NC 28303",
    "addr:housenumber":"2933",
    "addr:postcode":"28303",
    "addr:street":"Damascus Rd",
    "iso:country":"US",
    "sg:address":"2933 Damascus Rd",
    "sg:city":"Fayetteville",
    "sg:classifiers":[
        {
            "category":"Building & Trades",
            "subcategory":"Pest Control",
            "type":"Services"
        }
    ],
    "sg:phone":"+1 910 864 1024",
    "sg:postcode":"28303",
    "sg:province":"NC",
    "wof:name":"Orkin Pest Control 326",
    "wof:placetype":"venue"
},
  "geometry": {"coordinates":[-78.94065399999999,35.076487],"type":"Point"}
}