{
  "type": "Feature",
  "properties": {
    "iso:country":"US",
    "sg:address":"2740 Phifer Rd",
    "sg:city":"Cleveland",
    "sg:classifiers":[
        {
            "category":"Manufacturing",
            "subcategory":"Lumber",
            "type":"Manufacturing & Wholesale Goods"
        }
    ],
    "sg:phone":"+1 704 278 4269",
    "sg:postcode":"27013",
    "sg:province":"NC",
    "sg:tags":[
        "logging"
    ],
    "wof:name":"John W Koontz",
    "wof:placetype":"venue"
},
  "geometry": {"coordinates":[-80.729596,35.792307],"type":"Point"}
}