{
  "type": "Feature",
  "properties": {
    "iso:country":"US",
    "sg:address":"1250 Bay Valley Rd",
    "sg:city":"Kenly",
    "sg:classifiers":[
        {
            "category":"Social Services",
            "subcategory":"Child Care",
            "type":"Services"
        }
    ],
    "sg:phone":"+1   ",
    "sg:postcode":"27542",
    "sg:province":"NC",
    "sg:tags":[
        "day"
    ],
    "wof:name":"Jennys Kiddie Kastle",
    "wof:placetype":"venue"
},
  "geometry": {"coordinates":[-78.146952,35.614902],"type":"Point"}
}