{
  "type": "Feature",
  "properties": {
    "iso:country":"US",
    "sg:address":"506 E Divine St",
    "sg:city":"Dunn",
    "sg:classifiers":[
        {
            "category":"Social Services",
            "subcategory":"Child Care",
            "type":"Services"
        }
    ],
    "sg:phone":"+1   ",
    "sg:postcode":"28334",
    "sg:province":"NC",
    "sg:tags":[
        "day"
    ],
    "wof:name":"Pennys Day Care Center",
    "wof:placetype":"venue"
},
  "geometry": {"coordinates":[-78.60731800000001,35.304049],"type":"Point"}
}