{
  "type": "Feature",
  "properties": {
    "iso:country":"US",
    "sg:address":"2009 Lejeune Blvd",
    "sg:city":"Jacksonville",
    "sg:classifiers":[
        {
            "category":"Personal",
            "subcategory":"Shoe Repair & Shine",
            "type":"Services"
        }
    ],
    "sg:phone":"+1 910 353 6969",
    "sg:postcode":"28546",
    "sg:province":"NC",
    "sg:tags":[
        "repairing",
        "parlor",
        "boot",
        "shoes"
    ],
    "wof:name":"Gary's Shoe Repair",
    "wof:placetype":"venue"
},
  "geometry": {"coordinates":[-77.370012,34.741586],"type":"Point"}
}