{
  "type": "Feature",
  "properties": {
    "addr:full":"5710 Arringdon Park Dr Morrisville NC 27560",
    "addr:housenumber":"5710",
    "addr:postcode":"27560",
    "addr:street":"Arringdon Park Dr",
    "iso:country":"US",
    "sg:address":"5710 Arringdon Park Dr",
    "sg:city":"Morrisville",
    "sg:classifiers":[
        {
            "category":"Real Estate",
            "subcategory":"Real Estate Operator",
            "type":"Services"
        }
    ],
    "sg:phone":"+1 919 490 4663",
    "sg:postcode":"27560",
    "sg:province":"NC",
    "sg:tags":[
        "building",
        "apartment"
    ],
    "wof:name":"Colonial Grand At Arringdon",
    "wof:placetype":"venue"
},
  "geometry": {"coordinates":[-78.829976,35.88251],"type":"Point"}
}