{
  "type": "Feature",
  "properties": {
    "addr:full":"9852 US Hwy 311 Archdale NC 27263",
    "addr:housenumber":"9852",
    "addr:postcode":"27263",
    "addr:street":"Us Hwy 311",
    "iso:country":"US",
    "sg:address":"9852 US Hwy 311",
    "sg:city":"Archdale",
    "sg:classifiers":[
        {
            "category":"Freight",
            "type":"Transportation"
        }
    ],
    "sg:phone":"+1 336 434 4795",
    "sg:postcode":"27263",
    "sg:province":"NC",
    "sg:tags":[
        "trucking"
    ],
    "wof:name":"Hill Enterprise-Trucking",
    "wof:placetype":"venue"
},
  "geometry": {"coordinates":[-79.93396799999999,35.889549],"type":"Point"}
}