{
  "type": "Feature",
  "properties": {
    "addr:full":"6600 Wilkinson Blvd Belmont NC 28012",
    "addr:housenumber":"6600",
    "addr:postcode":"28012",
    "addr:street":"Wilkinson Blvd",
    "iso:country":"US",
    "sg:address":"6600 Wilkinson Blvd",
    "sg:city":"Belmont",
    "sg:classifiers":[
        {
            "category":"Organizations",
            "subcategory":"Non-profit Organization",
            "type":"Services"
        }
    ],
    "sg:phone":"+1 704 825 4161",
    "sg:postcode":"28012",
    "sg:province":"NC",
    "sg:website":"www.holyangelsnc.org",
    "wof:name":"Holy Angels",
    "wof:placetype":"venue"
},
  "geometry": {"coordinates":[-81.033124,35.252145],"type":"Point"}
}