{
  "type": "Feature",
  "properties": {
    "addr:full":"211 Central Park Ave Pinehurst NC 28374",
    "addr:housenumber":"211",
    "addr:postcode":"28374",
    "addr:street":"Central Park Ave",
    "iso:country":"US",
    "sg:address":"211 Central Park Ave",
    "sg:city":"Pinehurst",
    "sg:classifiers":[
        {
            "category":"Banks & Credit Unions",
            "subcategory":"Investment Brokerage",
            "type":"Services"
        }
    ],
    "sg:phone":"+1 910 235 9098",
    "sg:postcode":"28374",
    "sg:province":"NC",
    "sg:tags":[
        "security"
    ],
    "sg:website":"www.edwardjones.com",
    "wof:name":"Edward Jones",
    "wof:placetype":"venue"
},
  "geometry": {"coordinates":[-79.482039,35.203879],"type":"Point"}
}