{
  "type": "Feature",
  "properties": {
    "addr:full":"1003 N Brightleaf Blvd Smithfield NC 27577",
    "addr:housenumber":"1003",
    "addr:postcode":"27577",
    "addr:street":"N Brightleaf Blvd",
    "iso:country":"US",
    "sg:address":"1003 N Brightleaf Blvd",
    "sg:city":"Smithfield",
    "sg:classifiers":[
        {
            "category":"Restaurant",
            "type":"Food & Drink"
        }
    ],
    "sg:phone":"+1 919 938 0950",
    "sg:postcode":"27577",
    "sg:province":"NC",
    "wof:name":"Sonic Drive-In",
    "wof:placetype":"venue"
},
  "geometry": {"coordinates":[-78.32101,35.517197],"type":"Point"}
}