{
  "type": "Feature",
  "properties": {
    "addr:full":"13825 Statesville Rd Huntersville NC 28078",
    "addr:housenumber":"13825",
    "addr:postcode":"28078",
    "addr:street":"Statesville Rd",
    "iso:country":"US",
    "sg:address":"13825 Statesville Rd",
    "sg:city":"Huntersville",
    "sg:classifiers":[
        {
            "category":"Autos & Motor Vehicles",
            "subcategory":"Automobile Sales",
            "type":"Retail Goods"
        }
    ],
    "sg:phone":"+1 704 875 6547",
    "sg:postcode":"28078",
    "sg:province":"NC",
    "sg:tags":[
        "car",
        "dealer"
    ],
    "sg:website":"www.huntersvilleford1.com",
    "wof:name":"Huntersville Ford",
    "wof:placetype":"venue"
},
  "geometry": {"coordinates":[-80.852616,35.401687],"type":"Point"}
}