{
  "type": "Feature",
  "properties": {
    "iso:country":"US",
    "sg:address":"1571 Riggs Rd",
    "sg:city":"Maysville",
    "sg:classifiers":[
        {
            "category":"Retail",
            "subcategory":"Auto Repair",
            "type":"Services"
        }
    ],
    "sg:phone":"+1 910 743 7348",
    "sg:postcode":"28555",
    "sg:province":"NC",
    "sg:tags":[
        "repairing",
        "automobile"
    ],
    "wof:name":"Rogers Auto & Truck Repair",
    "wof:placetype":"venue"
},
  "geometry": {"coordinates":[-77.23892499999999,34.809504],"type":"Point"}
}