{
  "type": "Feature",
  "properties": {
    "iso:country":"US",
    "sg:address":"14309 Youngblood Rd",
    "sg:city":"Charlotte",
    "sg:classifiers":[
        {
            "category":"Shopping",
            "subcategory":"Crafts & Fabrics",
            "type":"Retail Goods"
        },
        {
            "category":"Professional",
            "subcategory":"Art Services",
            "type":"Services"
        }
    ],
    "sg:phone":"+1 704 587 1121",
    "sg:postcode":"28278",
    "sg:province":"NC",
    "sg:tags":[
        "picture",
        "frame"
    ],
    "wof:name":"Steele Creek Group",
    "wof:placetype":"venue"
},
  "geometry": {"coordinates":[-81.00649199999999,35.091673],"type":"Point"}
}