{
  "type": "Feature",
  "properties": {
    "addr:full":"34 Creekside Cir Hayesville NC 28904",
    "addr:housenumber":"34",
    "addr:postcode":"28904",
    "addr:street":"Creekside Cir",
    "iso:country":"US",
    "sg:address":"34 Creekside Cir",
    "sg:city":"Hayesville",
    "sg:classifiers":[
        {
            "category":"Retail",
            "subcategory":"Repair Shop",
            "type":"Services"
        },
        {
            "category":"Shopping",
            "subcategory":"Bicycles & Sporting Goods",
            "type":"Retail Goods"
        }
    ],
    "sg:phone":"+1 828 389 2086",
    "sg:postcode":"28904",
    "sg:province":"NC",
    "sg:tags":[
        "gun",
        "gunsmith"
    ],
    "wof:name":"R S R Gunsmithing Inc",
    "wof:placetype":"venue"
},
  "geometry": {"coordinates":[-83.82414799999999,35.029189],"type":"Point"}
}