{
  "type": "Feature",
  "properties": {
    "addr:full":"4344 Saint James Church Rd Raleigh NC 27604",
    "addr:housenumber":"4344",
    "addr:postcode":"27604",
    "addr:street":"Saint James Church Rd",
    "iso:country":"US",
    "sg:address":"4344 Saint James Church Rd",
    "sg:city":"Raleigh",
    "sg:classifiers":[
        {
            "category":"Real Estate",
            "subcategory":"Real Estate Services",
            "type":"Services"
        }
    ],
    "sg:phone":"+1 866 388 0465",
    "sg:postcode":"27604",
    "sg:province":"NC",
    "sg:tags":[
        "apartment",
        "management",
        "rental",
        "finder"
    ],
    "sg:website":"http://raleigh.citysearch.com/profile/external/616914500/raleigh_nc/honeytree_apartments.html?publisher=yellowpages&reference_id=1&placement=ypwebsitemip",
    "wof:name":"Honeytree Apartments",
    "wof:placetype":"venue"
},
  "geometry": {"coordinates":[-78.574153,35.840113],"type":"Point"}
}