{
  "type": "Feature",
  "properties": {
    "addr:full":"4647 Mebane Oaks Rd Mebane NC 27302",
    "addr:postcode":"4647;27302",
    "addr:street":"Mebane Oaks Rd",
    "iso:country":"US",
    "sg:address":"4647 Mebane Oaks Rd",
    "sg:city":"Mebane",
    "sg:classifiers":[
        {
            "category":"Shopping",
            "subcategory":"Florist",
            "type":"Retail Goods"
        }
    ],
    "sg:phone":"+1 919 563 3091",
    "sg:postcode":"27302",
    "sg:province":"NC",
    "wof:name":"Christian Flower Shop",
    "wof:placetype":"venue"
},
  "geometry": {"coordinates":[-79.26329800000001,35.992897],"type":"Point"}
}