{
  "type": "Feature",
  "properties": {
    "iso:country":"US",
    "sg:address":"706 Jake Alexander Blvd W",
    "sg:city":"Salisbury",
    "sg:classifiers":[
        {
            "category":"Professional",
            "subcategory":"Advertising",
            "type":"Services"
        }
    ],
    "sg:phone":"+1 704 638 9922",
    "sg:postcode":"28147",
    "sg:province":"NC",
    "sg:tags":[
        "mailing",
        "shipping"
    ],
    "wof:name":"Packaging Store",
    "wof:placetype":"venue"
},
  "geometry": {"coordinates":[-80.500282,35.659249],"type":"Point"}
}