{
  "type": "Feature",
  "properties": {
    "addr:full":"521 Sorrell St Cary NC 27513",
    "addr:housenumber":"521",
    "addr:postcode":"27513",
    "addr:street":"Sorrell St",
    "iso:country":"US",
    "sg:address":"521 Sorrell St",
    "sg:city":"Cary",
    "sg:classifiers":[
        {
            "category":"Building & Trades",
            "subcategory":"Construction",
            "type":"Services"
        }
    ],
    "sg:phone":"+1 919 319 1531",
    "sg:postcode":"27513",
    "sg:province":"NC",
    "sg:tags":[
        "house"
    ],
    "wof:name":"McGhee Homes & Remodeling",
    "wof:placetype":"venue"
},
  "geometry": {"coordinates":[-78.77077,35.794028],"type":"Point"}
}