{
  "type": "Feature",
  "properties": {
    "iso:country":"US",
    "sg:address":"1704 Oberlin Rd",
    "sg:city":"Raleigh",
    "sg:classifiers":[
        {
            "category":"Organizations",
            "subcategory":"Religious Organization",
            "type":"Services"
        }
    ],
    "sg:phone":"+1 919 834 3424",
    "sg:postcode":"27608",
    "sg:province":"NC",
    "sg:tags":[
        "church"
    ],
    "sg:website":"www.whitememorial.org",
    "wof:name":"White Memorial Presbyterian",
    "wof:placetype":"venue"
},
  "geometry": {"coordinates":[-78.655776,35.806927],"type":"Point"}
}