{
  "type": "Feature",
  "properties": {
    "addr:full":"1950 State Hwy 172 Sneads Ferry NC 28460",
    "addr:housenumber":"1950",
    "addr:postcode":"28460",
    "addr:street":"State Hwy 172",
    "iso:country":"US",
    "sg:address":"1950 State Hwy 172",
    "sg:city":"Sneads Ferry",
    "sg:classifiers":[
        {
            "category":"Real Estate",
            "subcategory":"Real Estate Agent",
            "type":"Services"
        }
    ],
    "sg:phone":"+1 910 327 4444",
    "sg:postcode":"28460",
    "sg:province":"NC",
    "wof:name":"Treasure Realty",
    "wof:placetype":"venue"
},
  "geometry": {"coordinates":[-77.45162999999999,34.547002],"type":"Point"}
}