{
  "type": "Feature",
  "properties": {
    "iso:country":"US",
    "sg:address":"103B New Waverly Pl",
    "sg:city":"Cary",
    "sg:classifiers":[
        {
            "category":"Shopping",
            "subcategory":"Pharmacy",
            "type":"Retail Goods"
        }
    ],
    "sg:phone":"+1 919 851 3301",
    "sg:postcode":"27518",
    "sg:province":"NC",
    "sg:tags":[
        "drugstore"
    ],
    "sg:website":"www.riteaid.com",
    "wof:name":"Rite Aid Pharmacies",
    "wof:placetype":"venue"
},
  "geometry": {"coordinates":[-78.779324,35.736566],"type":"Point"}
}