{
  "type": "Feature",
  "properties": {
    "iso:country":"US",
    "sg:address":"3244 Reynolda Rd",
    "sg:city":"Winston Salem",
    "sg:classifiers":[
        {
            "category":"Wholesale",
            "subcategory":"Medical Equipment & Supplies",
            "type":"Manufacturing & Wholesale Goods"
        }
    ],
    "sg:phone":"+1 336 765 2522",
    "sg:postcode":"27106",
    "sg:province":"NC",
    "sg:tags":[
        "physician",
        "surgeon"
    ],
    "sg:website":"www.medicalvideosystems.com",
    "wof:name":"Medical Video Systems",
    "wof:placetype":"venue"
},
  "geometry": {"coordinates":[-80.311719,36.153382],"type":"Point"}
}