{
  "type": "Feature",
  "properties": {
    "iso:country":"US",
    "sg:address":"118 E South St",
    "sg:city":"Raleigh",
    "sg:classifiers":[
        {
            "category":"Shopping",
            "subcategory":"News",
            "type":"Retail Goods"
        }
    ],
    "sg:phone":"+1 919 546 8201",
    "sg:postcode":"27601",
    "sg:province":"NC",
    "sg:tags":[
        "dealer"
    ],
    "wof:name":"W Sha News Public Affairs",
    "wof:placetype":"venue"
},
  "geometry": {"coordinates":[-78.637755,35.772034],"type":"Point"}
}