{
  "type": "Feature",
  "properties": {
    "iso:country":"US",
    "sg:address":"216 Westview Loop",
    "sg:city":"Pinebluff",
    "sg:classifiers":[
        {
            "category":"Shopping",
            "type":"Retail Goods"
        }
    ],
    "sg:phone":"+1 910 281 4303",
    "sg:postcode":"28373",
    "sg:province":"NC",
    "sg:tags":[
        "merchandise"
    ],
    "wof:name":"Eastwood Florist & Monuments",
    "wof:placetype":"venue"
},
  "geometry": {"coordinates":[-79.491905,35.112302],"type":"Point"}
}