{
  "type": "Feature",
  "properties": {
    "iso:country":"US",
    "sg:address":"1201 Stafford St",
    "sg:city":"Monroe",
    "sg:classifiers":[
        {
            "category":"Shopping",
            "subcategory":"Jewelry",
            "type":"Retail Goods"
        }
    ],
    "sg:phone":"+1 704 296 5531",
    "sg:postcode":"28110",
    "sg:province":"NC",
    "sg:tags":[
        "jeweler"
    ],
    "wof:name":"Michael James & Co",
    "wof:placetype":"venue"
},
  "geometry": {"coordinates":[-80.543038,34.992868],"type":"Point"}
}