{
  "type": "Feature",
  "properties": {
    "iso:country":"US",
    "sg:address":"609 S Elm St",
    "sg:city":"Greensboro",
    "sg:classifiers":[
        {
            "category":"Professional",
            "subcategory":"Art Services",
            "type":"Services"
        }
    ],
    "sg:phone":"+1 336 370 4666",
    "sg:postcode":"27406",
    "sg:province":"NC",
    "sg:tags":[
        "artist"
    ],
    "wof:name":"Studio",
    "wof:placetype":"venue"
},
  "geometry": {"coordinates":[-79.790755,36.065364],"type":"Point"}
}