{
  "type": "Feature",
  "properties": {
    "addr:full":"1587 Eilwood Dr Greenville NC 27834",
    "addr:housenumber":"1587",
    "addr:postcode":"27834",
    "addr:street":"Eilwood Dr",
    "iso:country":"US",
    "sg:address":"1587 Eilwood Dr",
    "sg:city":"Greenville",
    "sg:classifiers":[
        {
            "category":"Shopping",
            "subcategory":"Beauty & Cosmetics",
            "type":"Retail Goods"
        }
    ],
    "sg:phone":"+1 252 757 1305",
    "sg:postcode":"27834",
    "sg:province":"NC",
    "sg:tags":[
        "merchandise"
    ],
    "wof:name":"Mary Kay Consultant",
    "wof:placetype":"venue"
},
  "geometry": {"coordinates":[-77.458445,35.601544],"type":"Point"}
}