{
  "type": "Feature",
  "properties": {
    "iso:country":"US",
    "sg:address":"2400 Pratt St",
    "sg:city":"Durham",
    "sg:classifiers":[
        {
            "category":"Health Services",
            "subcategory":"Doctor",
            "type":"Services"
        }
    ],
    "sg:phone":"+1 919 668 8775",
    "sg:postcode":"27705",
    "sg:province":"NC",
    "sg:tags":[
        "physician",
        "surgeon"
    ],
    "wof:name":"Duke University Medical Ctr",
    "wof:placetype":"venue"
},
  "geometry": {"coordinates":[-78.93724,36.010653],"type":"Point"}
}