{
  "type": "Feature",
  "properties": {
    "iso:country":"US",
    "sg:address":"6517 Amber Dr",
    "sg:city":"Mebane",
    "sg:classifiers":[
        {
            "category":"Organizations",
            "subcategory":"Labor Organization",
            "type":"Services"
        }
    ],
    "sg:phone":"+1   ",
    "sg:postcode":"27302",
    "sg:province":"NC",
    "wof:name":"Local Farm Inc",
    "wof:placetype":"venue"
},
  "geometry": {"coordinates":[-79.237346,36.106341],"type":"Point"}
}