{
  "type": "Feature",
  "properties": {
    "addr:full":"3345 Heathcliff Rd Concord NC 28025",
    "addr:housenumber":"3345",
    "addr:postcode":"28025",
    "addr:street":"Heathcliff Rd",
    "iso:country":"US",
    "sg:address":"3345 Heathcliff Rd",
    "sg:city":"Concord",
    "sg:classifiers":[
        {
            "category":"Organizations",
            "subcategory":"Religious Organization",
            "type":"Services"
        }
    ],
    "sg:phone":"+1   ",
    "sg:postcode":"28025",
    "sg:province":"NC",
    "wof:name":"Rocky Ridge Baptist Church",
    "wof:placetype":"venue"
},
  "geometry": {"coordinates":[-80.492774,35.369043],"type":"Point"}
}