{
  "type": "Feature",
  "properties": {
    "addr:full":"100 S Chatham Ave Siler City NC 27344",
    "addr:housenumber":"100",
    "addr:postcode":"27344",
    "addr:street":"S Chatham Ave",
    "iso:country":"US",
    "sg:address":"100 S Chatham Ave",
    "sg:city":"Siler City",
    "sg:classifiers":[
        {
            "category":"Personal",
            "subcategory":"Beauty Salon",
            "type":"Services"
        }
    ],
    "sg:phone":"+1 919 742 5041",
    "sg:postcode":"27344",
    "sg:province":"NC",
    "wof:name":"A Touch Of Elegance",
    "wof:placetype":"venue"
},
  "geometry": {"coordinates":[-79.462867,35.721993],"type":"Point"}
}