{
  "type": "Feature",
  "properties": {
    "addr:full":"709 Olive St Apex NC 27502",
    "addr:housenumber":"709",
    "addr:postcode":"27502",
    "addr:street":"Olive St",
    "iso:country":"US",
    "sg:address":"709 Olive St",
    "sg:city":"Apex",
    "sg:classifiers":[
        {
            "category":"Wholesale",
            "subcategory":"Vending Machines",
            "type":"Manufacturing & Wholesale Goods"
        }
    ],
    "sg:phone":"+1 919 231 5868",
    "sg:postcode":"27502",
    "sg:province":"NC",
    "wof:name":"Snack Max Inc",
    "wof:placetype":"venue"
},
  "geometry": {"coordinates":[-78.84495200000001,35.72673],"type":"Point"}
}