{
  "type": "Feature",
  "properties": {
    "iso:country":"US",
    "sg:address":"4400 Craftsman Dr",
    "sg:city":"Raleigh",
    "sg:classifiers":[
        {
            "category":"Restaurant",
            "type":"Food & Drink"
        }
    ],
    "sg:phone":"+1 919 876 7337",
    "sg:postcode":"27609",
    "sg:province":"NC",
    "sg:tags":[
        "nightclub"
    ],
    "wof:name":"Reds Beach Music",
    "wof:placetype":"venue"
},
  "geometry": {"coordinates":[-78.607214,35.835841],"type":"Point"}
}