{
  "type": "Feature",
  "properties": {
    "iso:country":"US",
    "sg:address":"333 Taylor Rd",
    "sg:city":"Stanley",
    "sg:classifiers":[
        {
            "category":"Organizations",
            "subcategory":"Religious Organization",
            "type":"Services"
        }
    ],
    "sg:phone":"+1   ",
    "sg:postcode":"28164",
    "sg:province":"NC",
    "wof:name":"New Hope Meth Church",
    "wof:placetype":"venue"
},
  "geometry": {"coordinates":[-81.103095,35.386103],"type":"Point"}
}