{
  "type": "Feature",
  "properties": {
    "addr:full":"324 S College Rd Wilmington NC 28403",
    "addr:housenumber":"324",
    "addr:postcode":"28403",
    "addr:street":"S College Rd",
    "iso:country":"US",
    "sg:address":"324 S College Rd",
    "sg:city":"Wilmington",
    "sg:classifiers":[
        {
            "category":"Shopping",
            "type":"Retail Goods"
        }
    ],
    "sg:phone":"+1 910 799 2472",
    "sg:postcode":"28403",
    "sg:province":"NC",
    "sg:tags":[
        "pet",
        "shop"
    ],
    "wof:name":"PETCO",
    "wof:placetype":"venue"
},
  "geometry": {"coordinates":[-77.874165,34.234901],"type":"Point"}
}