{
  "type": "Feature",
  "properties": {
    "addr:full":"200 Old US Hwy 74 Polkton NC 28135",
    "addr:housenumber":"200",
    "addr:postcode":"28135",
    "addr:street":"Old Us Hwy 74",
    "iso:country":"US",
    "sg:address":"200 Old US Hwy 74",
    "sg:city":"Polkton",
    "sg:classifiers":[
        {
            "category":"Wholesale",
            "subcategory":"Apparel",
            "type":"Manufacturing & Wholesale Goods"
        }
    ],
    "sg:phone":"+1 704 272 7626",
    "sg:postcode":"28135",
    "sg:province":"NC",
    "sg:tags":[
        "shirt"
    ],
    "wof:name":"Polkton Shirt Co",
    "wof:placetype":"venue"
},
  "geometry": {"coordinates":[-80.20344799999999,35.004982],"type":"Point"}
}