{
  "type": "Feature",
  "properties": {
    "addr:full":"4327 Arbor Way Charlotte NC 28211",
    "addr:housenumber":"4327",
    "addr:postcode":"28211",
    "addr:street":"Arbor Way",
    "iso:country":"US",
    "sg:address":"4327 Arbor Way",
    "sg:city":"Charlotte",
    "sg:classifiers":[
        {
            "category":"Professional",
            "subcategory":"Business Services",
            "type":"Services"
        }
    ],
    "sg:phone":"+1   ",
    "sg:postcode":"28211",
    "sg:province":"NC",
    "wof:name":"Lsc Enterprises Inc",
    "wof:placetype":"venue"
},
  "geometry": {"coordinates":[-80.80773499999999,35.15221],"type":"Point"}
}