{
  "type": "Feature",
  "properties": {
    "iso:country":"US",
    "sg:address":"515 N Marshall St",
    "sg:city":"Graham",
    "sg:classifiers":[
        {
            "category":"Organizations",
            "subcategory":"Religious Organization",
            "type":"Services"
        }
    ],
    "sg:phone":"+1   ",
    "sg:postcode":"27253",
    "sg:province":"NC",
    "sg:tags":[
        "church"
    ],
    "wof:name":"Tabernacle Baptist Church",
    "wof:placetype":"venue"
},
  "geometry": {"coordinates":[-79.398421,36.076704],"type":"Point"}
}