{
  "type": "Feature",
  "properties": {
    "addr:full":"119 W 4th St Greenville NC 27858",
    "addr:housenumber":"119",
    "addr:postcode":"27858",
    "addr:street":"W 4Th St",
    "iso:country":"US",
    "sg:address":"119 W 4th St",
    "sg:city":"Greenville",
    "sg:classifiers":[
        {
            "category":"Professional",
            "subcategory":"Lawyer & Legal Services",
            "type":"Services"
        }
    ],
    "sg:phone":"+1 252 758 8555",
    "sg:postcode":"27858",
    "sg:province":"NC",
    "sg:tags":[
        "attorney"
    ],
    "wof:name":"Judson H Blount III",
    "wof:placetype":"venue"
},
  "geometry": {"coordinates":[-77.37367999999999,35.612294],"type":"Point"}
}