{
  "type": "Feature",
  "properties": {
    "addr:full":"1000 Stallings Rd Durham NC 27703",
    "addr:housenumber":"1000",
    "addr:postcode":"27703",
    "addr:street":"Stallings Rd",
    "iso:country":"US",
    "sg:address":"1000 Stallings Rd",
    "sg:city":"Durham",
    "sg:classifiers":[
        {
            "category":"Farming",
            "subcategory":"Livestock Farm",
            "type":"Manufacturing & Wholesale Goods"
        }
    ],
    "sg:phone":"+1 919 596 7563",
    "sg:postcode":"27703",
    "sg:province":"NC",
    "sg:tags":[
        "beef",
        "feedlot",
        "cattle"
    ],
    "wof:name":"Madison Chandler",
    "wof:placetype":"venue"
},
  "geometry": {"coordinates":[-78.80043499999999,35.989031],"type":"Point"}
}