{
  "type": "Feature",
  "properties": {
    "addr:full":"431 Bobcat Cove Lexington NC 27292",
    "addr:housenumber":"431",
    "addr:postcode":"27292",
    "addr:street":"Bobcat Cove",
    "iso:country":"US",
    "sg:address":"431 Bobcat Cove",
    "sg:city":"Lexington",
    "sg:classifiers":[
        {
            "category":"Manufacturing",
            "subcategory":"Petroleum Products",
            "type":"Manufacturing & Wholesale Goods"
        }
    ],
    "sg:phone":"+1 336 249 1513",
    "sg:postcode":"27292",
    "sg:province":"NC",
    "sg:tags":[
        "asphalt",
        "mfg"
    ],
    "wof:name":"Everhart Asphalt Repair",
    "wof:placetype":"venue"
},
  "geometry": {"coordinates":[-80.193327,35.822432],"type":"Point"}
}