{
  "type": "Feature",
  "properties": {
    "addr:full":"411 Market St Wilmington NC 28401",
    "addr:housenumber":"411",
    "addr:postcode":"28401",
    "addr:street":"Market St",
    "iso:country":"US",
    "sg:address":"411 Market St",
    "sg:city":"Wilmington",
    "sg:classifiers":[
        {
            "category":"Recreation",
            "type":"Entertainment"
        }
    ],
    "sg:phone":"+1 910 799 7564",
    "sg:postcode":"28401",
    "sg:province":"NC",
    "sg:tags":[
        "center"
    ],
    "wof:name":"First Baptist Chr Activity Ctr",
    "wof:placetype":"venue"
},
  "geometry": {"coordinates":[-77.943544,34.235896],"type":"Point"}
}