{
  "type": "Feature",
  "properties": {
    "iso:country":"US",
    "sg:address":"626 Clark Dr",
    "sg:city":"Lincolnton",
    "sg:classifiers":[
        {
            "category":"Health Services",
            "subcategory":"Doctor",
            "type":"Services"
        }
    ],
    "sg:phone":"+1 704 732 7263",
    "sg:postcode":"28092",
    "sg:province":"NC",
    "sg:tags":[
        "physician",
        "surgeon"
    ],
    "wof:name":"Southern Pulmonary Ctr",
    "wof:placetype":"venue"
},
  "geometry": {"coordinates":[-81.240064,35.469457],"type":"Point"}
}