{
  "type": "Feature",
  "properties": {
    "iso:country":"US",
    "sg:address":"6300 Creedmoor Rd",
    "sg:city":"Raleigh",
    "sg:classifiers":[
        {
            "category":"Building & Trades",
            "subcategory":"Construction",
            "type":"Services"
        }
    ],
    "sg:phone":"+1 919 848 3325",
    "sg:postcode":"27612",
    "sg:province":"NC",
    "sg:tags":[
        "house",
        "builder",
        "deck"
    ],
    "wof:name":"Decorative Addition",
    "wof:placetype":"venue"
},
  "geometry": {"coordinates":[-78.679474,35.87297],"type":"Point"}
}