{
  "type": "Feature",
  "properties": {
    "iso:country":"US",
    "sg:address":"1168 Hyatt Creek Rd",
    "sg:city":"Waynesville",
    "sg:classifiers":[
        {
            "category":"Retail",
            "subcategory":"Repair Shop",
            "type":"Services"
        }
    ],
    "sg:phone":"+1   ",
    "sg:postcode":"28786",
    "sg:province":"NC",
    "sg:tags":[
        "tv"
    ],
    "wof:name":"Specks TV & Vcr Service",
    "wof:placetype":"venue"
},
  "geometry": {"coordinates":[-83.028863,35.465267],"type":"Point"}
}