{
  "type": "Feature",
  "properties": {
    "iso:country":"US",
    "sg:address":"31 W 2nd Ave",
    "sg:city":"Lexington",
    "sg:classifiers":[
        {
            "category":"Restaurant",
            "type":"Food & Drink"
        }
    ],
    "sg:phone":"+1 336 249 9734",
    "sg:postcode":"27292",
    "sg:province":"NC",
    "wof:name":"Texas Grill",
    "wof:placetype":"venue"
},
  "geometry": {"coordinates":[-80.254593,35.822903],"type":"Point"}
}