{
  "type": "Feature",
  "properties": {
    "addr:full":"14 Beckham Pl Durham NC 27703",
    "addr:housenumber":"14",
    "addr:postcode":"27703",
    "addr:street":"Beckham Pl",
    "iso:country":"US",
    "sg:address":"14 Beckham Pl",
    "sg:city":"Durham",
    "sg:classifiers":[
        {
            "category":"Building & Trades",
            "subcategory":"Construction",
            "type":"Services"
        }
    ],
    "sg:phone":"+1 919 596 1122",
    "sg:postcode":"27703",
    "sg:province":"NC",
    "sg:tags":[
        "hanging",
        "contractor"
    ],
    "wof:name":"Macks Painting Cleaning",
    "wof:placetype":"venue"
},
  "geometry": {"coordinates":[-78.851455,35.993586],"type":"Point"}
}