{
  "type": "Feature",
  "properties": {
    "addr:full":"1000 Park Dr Washington NC 27889",
    "addr:housenumber":"1000",
    "addr:postcode":"27889",
    "addr:street":"Park Dr",
    "iso:country":"US",
    "sg:address":"1000 Park Dr",
    "sg:city":"Washington",
    "sg:classifiers":[
        {
            "category":"Food & Beverages",
            "subcategory":"Groceries & Convenience Stores",
            "type":"Retail Goods"
        }
    ],
    "sg:phone":"+1 252 948 0715",
    "sg:postcode":"27889",
    "sg:province":"NC",
    "wof:name":"Stop & Go",
    "wof:placetype":"venue"
},
  "geometry": {"coordinates":[-77.04006800000001,35.536585],"type":"Point"}
}