{
  "type": "Feature",
  "properties": {
    "iso:country":"US",
    "sg:address":"1528 Leggett Rd",
    "sg:city":"Rocky Mount",
    "sg:classifiers":[
        {
            "category":"Social Services",
            "type":"Services"
        }
    ],
    "sg:phone":"+1   ",
    "sg:postcode":"27801",
    "sg:province":"NC",
    "wof:name":"Specialized Way Corp",
    "wof:placetype":"venue"
},
  "geometry": {"coordinates":[-77.76289300000001,35.962516],"type":"Point"}
}