{
  "type": "Feature",
  "properties": {
    "addr:full":"107 Todd St Carrboro NC 27510",
    "addr:housenumber":"107",
    "addr:postcode":"27510",
    "addr:street":"Todd St",
    "iso:country":"US",
    "sg:address":"107 Todd St",
    "sg:city":"Carrboro",
    "sg:classifiers":[
        {
            "category":"Professional",
            "subcategory":"Research",
            "type":"Services"
        }
    ],
    "sg:phone":"+1   ",
    "sg:postcode":"27510",
    "sg:province":"NC",
    "sg:tags":[
        "marketing",
        "datum",
        "collection"
    ],
    "wof:name":"Magna Access Services",
    "wof:placetype":"venue"
},
  "geometry": {"coordinates":[-79.07559500000001,35.917657],"type":"Point"}
}