{
  "type": "Feature",
  "properties": {
    "addr:full":"4101 Hearthside Dr Wilmington NC 28412",
    "addr:housenumber":"4101",
    "addr:postcode":"28412",
    "addr:street":"Hearthside Dr",
    "iso:country":"US",
    "sg:address":"4101 Hearthside Dr",
    "sg:city":"Wilmington",
    "sg:classifiers":[
        {
            "category":"Professional",
            "type":"Services"
        }
    ],
    "sg:phone":"+1 910 254 9426",
    "sg:postcode":"28412",
    "sg:province":"NC",
    "wof:name":"H2o Pros Inc",
    "wof:placetype":"venue"
},
  "geometry": {"coordinates":[-77.903578,34.173333],"type":"Point"}
}