{
  "type": "Feature",
  "properties": {
    "addr:full":"1220 Fort Bragg Rd Fayetteville NC 28305",
    "addr:housenumber":"1220",
    "addr:postcode":"28305",
    "addr:street":"Fort Bragg Rd",
    "iso:country":"US",
    "sg:address":"1220 Fort Bragg Rd",
    "sg:city":"Fayetteville",
    "sg:classifiers":[
        {
            "category":"Insurance",
            "subcategory":"Insurance Agent",
            "type":"Services"
        }
    ],
    "sg:phone":"+1 910 483 5283",
    "sg:postcode":"28305",
    "sg:province":"NC",
    "sg:tags":[
        "adjuster"
    ],
    "wof:name":"Atlantic Claims Co",
    "wof:placetype":"venue"
},
  "geometry": {"coordinates":[-78.90083199999999,35.057677],"type":"Point"}
}