{
  "type": "Feature",
  "properties": {
    "addr:full":"3009 E Bessemer Ave Greensboro NC 27405",
    "addr:housenumber":"3009",
    "addr:postcode":"27405",
    "addr:street":"E Bessemer Ave",
    "iso:country":"US",
    "sg:address":"3009 E Bessemer Ave",
    "sg:city":"Greensboro",
    "sg:classifiers":[
        {
            "category":"Social Services",
            "subcategory":"Child Care",
            "type":"Services"
        }
    ],
    "sg:phone":"+1 336 574 3901",
    "sg:postcode":"27405",
    "sg:province":"NC",
    "sg:tags":[
        "day"
    ],
    "wof:name":"Gods Heritage",
    "wof:placetype":"venue"
},
  "geometry": {"coordinates":[-79.74491,36.085057],"type":"Point"}
}