{
  "type": "Feature",
  "properties": {
    "addr:full":"1618 York St New Bern NC 28562",
    "addr:housenumber":"1618",
    "addr:postcode":"28562",
    "addr:street":"York St",
    "iso:country":"US",
    "sg:address":"1618 York St",
    "sg:city":"New Bern",
    "sg:classifiers":[
        {
            "category":"Shopping",
            "subcategory":"Catalog Store",
            "type":"Retail Goods"
        }
    ],
    "sg:phone":"+1 252 636 3455",
    "sg:postcode":"28562",
    "sg:province":"NC",
    "sg:tags":[
        "mail",
        "house"
    ],
    "wof:name":"Simply Charlease",
    "wof:placetype":"venue"
},
  "geometry": {"coordinates":[-77.097376,35.122797],"type":"Point"}
}