{
  "type": "Feature",
  "properties": {
    "addr:full":"107 Gordon St Sanford NC 27330",
    "addr:housenumber":"107",
    "addr:postcode":"27330",
    "addr:street":"Gordon St",
    "iso:country":"US",
    "sg:address":"107 Gordon St",
    "sg:city":"Sanford",
    "sg:classifiers":[
        {
            "category":"Professional",
            "subcategory":"Accounting & Tax Preparation",
            "type":"Services"
        }
    ],
    "sg:phone":"+1 919 776 4636",
    "sg:postcode":"27330",
    "sg:province":"NC",
    "sg:tags":[
        "accountant"
    ],
    "wof:name":"Richard M Carlson CPA",
    "wof:placetype":"venue"
},
  "geometry": {"coordinates":[-79.179286,35.48248],"type":"Point"}
}