{
  "type": "Feature",
  "properties": {
    "iso:country":"US",
    "sg:address":"1541 Durham Rd",
    "sg:city":"Roxboro",
    "sg:classifiers":[
        {
            "category":"Restaurant",
            "type":"Food & Drink"
        }
    ],
    "sg:phone":"+1 336 597 3377",
    "sg:postcode":"27573",
    "sg:province":"NC",
    "wof:name":"El Milenio Mexican Restaurant",
    "wof:placetype":"venue"
},
  "geometry": {"coordinates":[-78.98403500000001,36.379414],"type":"Point"}
}