{
  "type": "Feature",
  "properties": {
    "addr:full":"4117 Holder Farm Rd Liberty NC 27298",
    "addr:housenumber":"4117",
    "addr:postcode":"27298",
    "addr:street":"Holder Farm Rd",
    "iso:country":"US",
    "sg:address":"4117 Holder Farm Rd",
    "sg:city":"Liberty",
    "sg:classifiers":[
        {
            "category":"Building & Trades",
            "subcategory":"Construction",
            "type":"Services"
        }
    ],
    "sg:phone":"+1 336 622 3790",
    "sg:postcode":"27298",
    "sg:province":"NC",
    "sg:tags":[
        "heavy",
        "contractor"
    ],
    "wof:name":"Holder Backhoe & Hauling Svc",
    "wof:placetype":"venue"
},
  "geometry": {"coordinates":[-79.656662,35.860209],"type":"Point"}
}