{
  "type": "Feature",
  "properties": {
    "addr:full":"219 Wilmont Dr Gastonia NC 28054",
    "addr:housenumber":"219",
    "addr:postcode":"28054",
    "addr:street":"Wilmont Dr",
    "iso:country":"US",
    "sg:address":"219 Wilmont Dr",
    "sg:city":"Gastonia",
    "sg:classifiers":[
        {
            "category":"Professional",
            "subcategory":"Accounting & Tax Preparation",
            "type":"Services"
        }
    ],
    "sg:phone":"+1 704 867 2394",
    "sg:postcode":"28054",
    "sg:province":"NC",
    "sg:tags":[
        "accountant"
    ],
    "wof:name":"Middleswarth Bowers & Co LLP",
    "wof:placetype":"venue"
},
  "geometry": {"coordinates":[-81.1495,35.259452],"type":"Point"}
}