{
  "type": "Feature",
  "properties": {
    "addr:full":"5804 Somerton Pl Hope Mills NC 28348",
    "addr:housenumber":"5804",
    "addr:postcode":"28348",
    "addr:street":"Somerton Pl",
    "iso:country":"US",
    "sg:address":"5804 Somerton Pl",
    "sg:city":"Hope Mills",
    "sg:classifiers":[
        {
            "category":"Real Estate",
            "subcategory":"Real Estate Agent",
            "type":"Services"
        }
    ],
    "sg:phone":"+1 910 425 3850",
    "sg:postcode":"28348",
    "sg:province":"NC",
    "sg:tags":[
        "agency",
        "rental"
    ],
    "wof:name":"Hester's Rentals",
    "wof:placetype":"venue"
},
  "geometry": {"coordinates":[-78.892374,34.937025],"type":"Point"}
}