{
  "type": "Feature",
  "properties": {
    "iso:country":"US",
    "sg:address":"166 Perkins Rd",
    "sg:city":"Goldsboro",
    "sg:classifiers":[
        {
            "category":"Building & Trades",
            "subcategory":"Construction",
            "type":"Services"
        }
    ],
    "sg:phone":"+1 919 734 4673",
    "sg:postcode":"27530",
    "sg:province":"NC",
    "sg:tags":[
        "contractor"
    ],
    "wof:name":"Gene Garris Construction",
    "wof:placetype":"venue"
},
  "geometry": {"coordinates":[-78.00646999999999,35.449518],"type":"Point"}
}