{
  "type": "Feature",
  "properties": {
    "iso:country":"US",
    "sg:address":"2455 Spaugh Industrial Dr",
    "sg:city":"Winston Salem",
    "sg:classifiers":[
        {
            "category":"Home & Garden",
            "subcategory":"Building Materials",
            "type":"Retail Goods"
        },
        {
            "category":"Retail",
            "subcategory":"Auto Repair",
            "type":"Services"
        }
    ],
    "sg:phone":"+1 336 940 2054",
    "sg:postcode":"27103",
    "sg:province":"NC",
    "sg:tags":[
        "door",
        "general"
    ],
    "sg:website":"www.carolinagaragedoor.com",
    "wof:name":"Carolina Garage Door",
    "wof:placetype":"venue"
},
  "geometry": {"coordinates":[-80.317239,36.033573],"type":"Point"}
}