{
  "type": "Feature",
  "properties": {
    "addr:full":"308 Greenville Blvd SE Greenville NC 27858",
    "addr:housenumber":"308",
    "addr:postcode":"27858",
    "addr:street":"Greenville Blvd Se",
    "iso:country":"US",
    "sg:address":"308 Greenville Blvd SE",
    "sg:city":"Greenville",
    "sg:classifiers":[
        {
            "category":"Real Estate",
            "subcategory":"Real Estate Agent",
            "type":"Services"
        }
    ],
    "sg:phone":"+1 252 355 6000",
    "sg:postcode":"27858",
    "sg:province":"NC",
    "wof:name":"Kellerwilliams Realty",
    "wof:placetype":"venue"
},
  "geometry": {"coordinates":[-77.379533,35.578574],"type":"Point"}
}