{
  "type": "Feature",
  "properties": {
    "addr:full":"1135 Kildaire Farm Rd Cary NC 27511",
    "addr:housenumber":"1135",
    "addr:postcode":"27511",
    "addr:street":"Kildaire Farm Rd",
    "iso:country":"US",
    "sg:address":"1135 Kildaire Farm Rd",
    "sg:city":"Cary",
    "sg:classifiers":[
        {
            "category":"Building & Trades",
            "subcategory":"Plumbing",
            "type":"Services"
        }
    ],
    "sg:phone":"+1 919 657 0500",
    "sg:postcode":"27511",
    "sg:province":"NC",
    "wof:name":"National Drywall",
    "wof:placetype":"venue"
},
  "geometry": {"coordinates":[-78.782275,35.767396],"type":"Point"}
}