{
  "type": "Feature",
  "properties": {
    "addr:full":"2945 Derita Ave Charlotte NC 28269",
    "addr:housenumber":"2945",
    "addr:postcode":"28269",
    "addr:street":"Derita Ave",
    "iso:country":"US",
    "sg:address":"2945 Derita Ave",
    "sg:city":"Charlotte",
    "sg:classifiers":[
        {
            "category":"Organizations",
            "subcategory":"Religious Organization",
            "type":"Services"
        }
    ],
    "sg:phone":"+1 704 596 0430",
    "sg:postcode":"28269",
    "sg:province":"NC",
    "wof:name":"Empowered Love Ministries",
    "wof:placetype":"venue"
},
  "geometry": {"coordinates":[-80.80367200000001,35.300357],"type":"Point"}
}