{
  "type": "Feature",
  "properties": {
    "addr:full":"11 Sturbridge Ln Greensboro NC 27408",
    "addr:housenumber":"11",
    "addr:postcode":"27408",
    "addr:street":"Sturbridge Ln",
    "iso:country":"US",
    "sg:address":"11 Sturbridge Ln",
    "sg:city":"Greensboro",
    "sg:classifiers":[
        {
            "category":"Banks & Credit Unions",
            "subcategory":"Financial Services",
            "type":"Services"
        }
    ],
    "sg:phone":"+1 336 288 6169",
    "sg:postcode":"27408",
    "sg:province":"NC",
    "sg:tags":[
        "real estate"
    ],
    "wof:name":"Gray Court Properties LLC",
    "wof:placetype":"venue"
},
  "geometry": {"coordinates":[-79.79814399999999,36.119682],"type":"Point"}
}