{
  "type": "Feature",
  "properties": {
    "iso:country":"US",
    "sg:address":"1400 4th St",
    "sg:city":"Statesville",
    "sg:classifiers":[
        {
            "category":"Organizations",
            "subcategory":"Religious Organization",
            "type":"Services"
        }
    ],
    "sg:phone":"+1   ",
    "sg:postcode":"28677",
    "sg:province":"NC",
    "wof:name":"Fifth St Shelter Ministries",
    "wof:placetype":"venue"
},
  "geometry": {"coordinates":[-80.888941,35.766839],"type":"Point"}
}