{
  "type": "Feature",
  "properties": {
    "addr:full":"1518 S Main St Salisbury NC 28144",
    "addr:housenumber":"1518",
    "addr:postcode":"28144",
    "addr:street":"S Main St",
    "iso:country":"US",
    "sg:address":"1518 S Main St",
    "sg:city":"Salisbury",
    "sg:classifiers":[
        {
            "category":"Wholesale",
            "subcategory":"Medical Equipment & Supplies",
            "type":"Manufacturing & Wholesale Goods"
        }
    ],
    "sg:phone":"+1 704 636 8826",
    "sg:postcode":"28144",
    "sg:province":"NC",
    "sg:tags":[
        "x",
        "apparatus"
    ],
    "wof:name":"Echerd & Associates Inc",
    "wof:placetype":"venue"
},
  "geometry": {"coordinates":[-80.489861,35.656361],"type":"Point"}
}