{
  "type": "Feature",
  "properties": {
    "addr:full":"9115 Harris Corners Pkwy Charlotte NC 28269",
    "addr:housenumber":"9115",
    "addr:postcode":"28269",
    "addr:street":"Harris Corners Pkwy",
    "iso:country":"US",
    "sg:address":"9115 Harris Corners Pkwy",
    "sg:city":"Charlotte",
    "sg:classifiers":[
        {
            "category":"Professional",
            "subcategory":"Engineering",
            "type":"Services"
        }
    ],
    "sg:phone":"+1 704 598 0918",
    "sg:postcode":"28269",
    "sg:province":"NC",
    "sg:tags":[
        "consulting",
        "engineer"
    ],
    "wof:name":"Carollo Engineers",
    "wof:placetype":"venue"
},
  "geometry": {"coordinates":[-80.843028,35.346097],"type":"Point"}
}