{
  "type": "Feature",
  "properties": {
    "addr:full":"8417 Blockade Ct Charlotte NC 28226",
    "addr:housenumber":"8417",
    "addr:postcode":"28226",
    "addr:street":"Blockade Ct",
    "iso:country":"US",
    "sg:address":"8417 Blockade Ct",
    "sg:city":"Charlotte",
    "sg:classifiers":[
        {
            "category":"Manufacturing",
            "subcategory":"Toys & Sporting Goods",
            "type":"Manufacturing & Wholesale Goods"
        }
    ],
    "sg:phone":"+1 704 545 6616",
    "sg:postcode":"28226",
    "sg:province":"NC",
    "sg:tags":[
        "mfg"
    ],
    "wof:name":"Kelley Pools",
    "wof:placetype":"venue"
},
  "geometry": {"coordinates":[-80.859297,35.085195],"type":"Point"}
}