{
  "type": "Feature",
  "properties": {
    "addr:full":"15617 Andover Ln Wake Forest NC 27587",
    "addr:housenumber":"15617",
    "addr:postcode":"27587",
    "addr:street":"Andover Ln",
    "iso:country":"US",
    "sg:address":"15617 Andover Ln",
    "sg:city":"Wake Forest",
    "sg:classifiers":[
        {
            "category":"Professional",
            "subcategory":"Management & Consulting",
            "type":"Services"
        }
    ],
    "sg:phone":"+1 919 528 3562",
    "sg:postcode":"27587",
    "sg:province":"NC",
    "sg:tags":[
        "seafood",
        "direct",
        "sales",
        "home",
        "chicken",
        "steak"
    ],
    "wof:name":"B & D Food Distributors Inc",
    "wof:placetype":"venue"
},
  "geometry": {"coordinates":[-78.656673,36.027092],"type":"Point"}
}