{
  "type": "Feature",
  "properties": {
    "addr:full":"310 E King St King NC 27021",
    "addr:housenumber":"310",
    "addr:postcode":"27021",
    "addr:street":"E King St",
    "iso:country":"US",
    "sg:address":"310 E King St",
    "sg:city":"King",
    "sg:classifiers":[
        {
            "category":"Building & Trades",
            "subcategory":"Construction",
            "type":"Services"
        }
    ],
    "sg:phone":"+1 336 983 5701",
    "sg:postcode":"27021",
    "sg:province":"NC",
    "sg:tags":[
        "dry wall",
        "contractor"
    ],
    "wof:name":"Quality Dry Wall Inc",
    "wof:placetype":"venue"
},
  "geometry": {"coordinates":[-80.349997,36.279742],"type":"Point"}
}