{
  "type": "Feature",
  "properties": {
    "iso:country":"US",
    "sg:address":"1615 Hyde Ave",
    "sg:city":"Winston Salem",
    "sg:classifiers":[
        {
            "category":"Professional",
            "subcategory":"Business Services",
            "type":"Services"
        }
    ],
    "sg:phone":"+1 336 725 4935",
    "sg:postcode":"27104",
    "sg:province":"NC",
    "sg:tags":[
        "interior",
        "consultant",
        "design",
        "decorator"
    ],
    "wof:name":"R Neal Fine & Assoc Inc",
    "wof:placetype":"venue"
},
  "geometry": {"coordinates":[-80.268157,36.096566],"type":"Point"}
}