{
  "type": "Feature",
  "properties": {
    "iso:country":"US",
    "sg:address":"104 Wade Ave",
    "sg:city":"Louisburg",
    "sg:classifiers":[
        {
            "category":"Government",
            "subcategory":"Police Station",
            "type":"Public Place"
        }
    ],
    "sg:phone":"+1 919 496 4175",
    "sg:postcode":"27549",
    "sg:province":"NC",
    "sg:tags":[
        "protection"
    ],
    "wof:name":"Louisburg Police Dept",
    "wof:placetype":"venue"
},
  "geometry": {"coordinates":[-78.29803,36.098001],"type":"Point"}
}