{
  "type": "Feature",
  "properties": {
    "iso:country":"US",
    "sg:address":"1403 Keogh St",
    "sg:city":"Burlington",
    "sg:classifiers":[
        {
            "category":"Building & Trades",
            "subcategory":"Landscaping Services",
            "type":"Services"
        }
    ],
    "sg:phone":"+1 336 227 6723",
    "sg:postcode":"27215",
    "sg:province":"NC",
    "wof:name":"Gilliam Service Center",
    "wof:placetype":"venue"
},
  "geometry": {"coordinates":[-79.474767,36.102465],"type":"Point"}
}