{
  "type": "Feature",
  "properties": {
    "addr:full":"2537 Plantation Center Dr Matthews NC 28105",
    "addr:housenumber":"2537",
    "addr:postcode":"28105",
    "addr:street":"Plantation Center Dr",
    "iso:country":"US",
    "sg:address":"2537 Plantation Center Dr",
    "sg:city":"Matthews",
    "sg:classifiers":[
        {
            "category":"Restaurant",
            "type":"Food & Drink"
        },
        {
            "category":"Food & Beverages",
            "subcategory":"Meat & Fish",
            "type":"Retail Goods"
        }
    ],
    "sg:phone":"+1 704 847 5051",
    "sg:postcode":"28105",
    "sg:province":"NC",
    "sg:tags":[
        "seafood",
        "seafood-wholesale",
        "market"
    ],
    "wof:name":"Glenn Sales",
    "wof:placetype":"venue"
},
  "geometry": {"coordinates":[-80.733664,35.084657],"type":"Point"}
}