{
  "type": "Feature",
  "properties": {
    "addr:full":"9630 Falls of Neuse Rd Raleigh NC 27615",
    "addr:housenumber":"9630",
    "addr:postcode":"27615",
    "addr:street":"Falls Of Neuse Rd",
    "iso:country":"US",
    "sg:address":"9630 Falls of Neuse Rd",
    "sg:city":"Raleigh",
    "sg:classifiers":[
        {
            "category":"Restaurant",
            "type":"Food & Drink"
        }
    ],
    "sg:menulink":"http://www.allmenus.com/nc/neuse/87903-zpizza/menu/",
    "sg:phone":"+1 919 844 0065",
    "sg:postcode":"27615",
    "sg:province":"NC",
    "sg:tags":[
        "american",
        "pizza"
    ],
    "wof:name":"Zpizza",
    "wof:placetype":"venue"
},
  "geometry": {"coordinates":[-78.60187999999999,35.906211],"type":"Point"}
}