{
  "type": "Feature",
  "properties": {
    "addr:full":"3131 Wrightsville Ave Wilmington NC 28403",
    "addr:housenumber":"3131",
    "addr:postcode":"28403",
    "addr:street":"Wrightsville Ave",
    "iso:country":"US",
    "sg:address":"3131 Wrightsville Ave",
    "sg:city":"Wilmington",
    "sg:classifiers":[
        {
            "category":"Banks & Credit Unions",
            "subcategory":"Bank",
            "type":"Services"
        }
    ],
    "sg:phone":"+1 910 256 9110",
    "sg:postcode":"28403",
    "sg:province":"NC",
    "sg:tags":[
        "loan",
        "real estate"
    ],
    "sg:website":"www.atlanticbaymtg.com",
    "wof:name":"Atlantic Bay Mortgage Group",
    "wof:placetype":"venue"
},
  "geometry": {"coordinates":[-77.90376999999999,34.224678],"type":"Point"}
}