{
  "type": "Feature",
  "properties": {
    "iso:country":"US",
    "sg:address":"4081 Smyrna Rd",
    "sg:city":"Whiteville",
    "sg:classifiers":[
        {
            "category":"Shopping",
            "subcategory":"Used Merchandise",
            "type":"Retail Goods"
        }
    ],
    "sg:phone":"+1 910 642 4376",
    "sg:postcode":"28472",
    "sg:province":"NC",
    "sg:tags":[
        "antique"
    ],
    "wof:name":"Backyard Treasures",
    "wof:placetype":"venue"
},
  "geometry": {"coordinates":[-78.771095,34.371569],"type":"Point"}
}