{
  "type": "Feature",
  "properties": {
    "iso:country":"US",
    "sg:address":"6420 Amsterdam Way",
    "sg:city":"Wilmington",
    "sg:classifiers":[
        {
            "category":"Autos & Motor Vehicles",
            "subcategory":"Boat Sales",
            "type":"Retail Goods"
        }
    ],
    "sg:phone":"+1 910 796 8195",
    "sg:postcode":"28405",
    "sg:province":"NC",
    "sg:tags":[
        "top",
        "upholstery",
        "cover"
    ],
    "wof:name":"Salter Custom Canvass",
    "wof:placetype":"venue"
},
  "geometry": {"coordinates":[-77.847589,34.259929],"type":"Point"}
}