{
  "type": "Feature",
  "properties": {
    "iso:country":"US",
    "sg:address":"131 Clipper Ct",
    "sg:city":"Kill Devil Hills",
    "sg:classifiers":[
        {
            "category":"Building & Trades",
            "subcategory":"Construction",
            "type":"Services"
        }
    ],
    "sg:phone":"+1 252 480 1975",
    "sg:postcode":"27948",
    "sg:province":"NC",
    "sg:tags":[
        "house"
    ],
    "wof:name":"Frank Zapulla Jr",
    "wof:placetype":"venue"
},
  "geometry": {"coordinates":[-75.726866,36.021905],"type":"Point"}
}