{
  "type": "Feature",
  "properties": {
    "iso:country":"US",
    "sg:address":"4159 US Hwy 221",
    "sg:city":"Sparta",
    "sg:classifiers":[
        {
            "category":"Farming",
            "subcategory":"Farm",
            "type":"Manufacturing & Wholesale Goods"
        }
    ],
    "sg:phone":"+1 336 372 4579",
    "sg:postcode":"28675",
    "sg:province":"NC",
    "sg:tags":[
        "crop",
        "general"
    ],
    "wof:name":"Joines Jr Clay Edwin",
    "wof:placetype":"venue"
},
  "geometry": {"coordinates":[-81.22293000000001,36.508741],"type":"Point"}
}