{
  "type": "Feature",
  "properties": {
    "iso:country":"US",
    "sg:address":"7429 A C C Blvd",
    "sg:city":"Raleigh",
    "sg:classifiers":[
        {
            "category":"Wholesale",
            "subcategory":"Medical Equipment & Supplies",
            "type":"Manufacturing & Wholesale Goods"
        }
    ],
    "sg:phone":"+1 919 596 1755",
    "sg:postcode":"27617",
    "sg:province":"NC",
    "sg:tags":[
        "microscope"
    ],
    "wof:name":"Vashaw Scientific",
    "wof:placetype":"venue"
},
  "geometry": {"coordinates":[-78.764168,35.910372],"type":"Point"}
}