{
  "type": "Feature",
  "properties": {
    "iso:country":"US",
    "sg:address":"7113 Village Green Dr",
    "sg:city":"Charlotte",
    "sg:classifiers":[
        {
            "category":"Shopping",
            "subcategory":"Discount & Variety Stores",
            "type":"Retail Goods"
        }
    ],
    "sg:phone":"+1 704 536 6489",
    "sg:postcode":"28215",
    "sg:province":"NC",
    "sg:tags":[
        "merchandise",
        "general"
    ],
    "wof:name":"Gregory Kirkpatrick Retail",
    "wof:placetype":"venue"
},
  "geometry": {"coordinates":[-80.74499400000001,35.236573],"type":"Point"}
}