{
  "type": "Feature",
  "properties": {
    "addr:full":"226 Starlite Ln Rutherfordton NC 28139",
    "addr:housenumber":"226",
    "addr:postcode":"28139",
    "addr:street":"Starlite Ln",
    "iso:country":"US",
    "sg:address":"226 Starlite Ln",
    "sg:city":"Rutherfordton",
    "sg:classifiers":[
        {
            "category":"Manufacturing",
            "subcategory":"Lumber",
            "type":"Manufacturing & Wholesale Goods"
        }
    ],
    "sg:phone":"+1 704 472 8245",
    "sg:postcode":"28139",
    "sg:province":"NC",
    "sg:tags":[
        "logger",
        "contract"
    ],
    "wof:name":"Mast Contract Felling",
    "wof:placetype":"venue"
},
  "geometry": {"coordinates":[-82.01016799999999,35.452647],"type":"Point"}
}