{
  "type": "Feature",
  "properties": {
    "iso:country":"US",
    "sg:address":"313 New Bridge St",
    "sg:city":"Jacksonville",
    "sg:classifiers":[
        {
            "category":"Professional",
            "subcategory":"Lawyer & Legal Services",
            "type":"Services"
        }
    ],
    "sg:phone":"+1 910 455 3637",
    "sg:postcode":"28540",
    "sg:province":"NC",
    "sg:tags":[
        "attorney"
    ],
    "wof:name":"Ellis Hooper Warlick & Morgan",
    "wof:placetype":"venue"
},
  "geometry": {"coordinates":[-77.42740000000001,34.750453],"type":"Point"}
}