{
  "type": "Feature",
  "properties": {
    "iso:country":"US",
    "sg:address":"800 Arendell St",
    "sg:city":"Morehead City",
    "sg:classifiers":[
        {
            "category":"Banks & Credit Unions",
            "subcategory":"Bank",
            "type":"Services"
        }
    ],
    "sg:phone":"+1 252 240 6312",
    "sg:postcode":"28557",
    "sg:province":"NC",
    "wof:name":"Wachovia Bank",
    "wof:placetype":"venue"
},
  "geometry": {"coordinates":[-76.714021,34.721536],"type":"Point"}
}