{
  "type": "Feature",
  "properties": {
    "addr:full":"6328 Horseshoe Dr Raleigh NC 27603",
    "addr:housenumber":"6328",
    "addr:postcode":"27603",
    "addr:street":"Horseshoe Dr",
    "iso:country":"US",
    "sg:address":"6328 Horseshoe Dr",
    "sg:city":"Raleigh",
    "sg:classifiers":[
        {
            "category":"Building & Trades",
            "subcategory":"Construction",
            "type":"Services"
        }
    ],
    "sg:phone":"+1 919 795 3655",
    "sg:postcode":"27603",
    "sg:province":"NC",
    "sg:tags":[
        "painter"
    ],
    "wof:name":"L & S Painting",
    "wof:placetype":"venue"
},
  "geometry": {"coordinates":[-78.685062,35.699009],"type":"Point"}
}