{
  "type": "Feature",
  "properties": {
    "addr:full":"6933 Orange Grove Rd Hillsborough NC 27516",
    "addr:housenumber":"6933",
    "addr:postcode":"27516",
    "addr:street":"Orange Grove Rd",
    "iso:country":"US",
    "sg:address":"6933 Orange Grove Rd",
    "sg:city":"Hillsborough",
    "sg:classifiers":[
        {
            "category":"Retail",
            "subcategory":"Auto Repair",
            "type":"Services"
        }
    ],
    "sg:phone":"+1   ",
    "sg:postcode":"27516",
    "sg:province":"NC",
    "sg:tags":[
        "automotive"
    ],
    "wof:name":"Covington Automotive",
    "wof:placetype":"venue"
},
  "geometry": {"coordinates":[-79.19403800000001,35.977436],"type":"Point"}
}