{
  "type": "Feature",
  "properties": {
    "iso:country":"US",
    "sg:address":"5950 Semora Rd",
    "sg:city":"Roxboro",
    "sg:classifiers":[
        {
            "category":"Food & Beverages",
            "subcategory":"Groceries & Convenience Stores",
            "type":"Retail Goods"
        }
    ],
    "sg:phone":"+1 336 599 2925",
    "sg:postcode":"27574",
    "sg:province":"NC",
    "sg:tags":[
        "alcoholic"
    ],
    "wof:name":"Twins Country Mart Inc",
    "wof:placetype":"venue"
},
  "geometry": {"coordinates":[-79.068394,36.449377],"type":"Point"}
}