{
  "type": "Feature",
  "properties": {
    "addr:full":"180 Harris Rd Newport NC 28570",
    "addr:housenumber":"180",
    "addr:postcode":"28570",
    "addr:street":"Harris Rd",
    "iso:country":"US",
    "sg:address":"180 Harris Rd",
    "sg:city":"Newport",
    "sg:classifiers":[
        {
            "category":"Home & Garden",
            "subcategory":"Building Materials",
            "type":"Retail Goods"
        }
    ],
    "sg:phone":"+1 252 247 5100",
    "sg:postcode":"28570",
    "sg:province":"NC",
    "sg:tags":[
        "shutter"
    ],
    "wof:name":"Homeshield Hurricane Prtctn",
    "wof:placetype":"venue"
},
  "geometry": {"coordinates":[-76.809805,34.742225],"type":"Point"}
}