{
  "type": "Feature",
  "properties": {
    "addr:full":"5302 Tabor Ct Fayetteville NC 28303",
    "addr:housenumber":"5302",
    "addr:postcode":"28303",
    "addr:street":"Tabor Ct",
    "iso:country":"US",
    "sg:address":"5302 Tabor Ct",
    "sg:city":"Fayetteville",
    "sg:classifiers":[
        {
            "category":"Social Services",
            "subcategory":"Child Care",
            "type":"Services"
        }
    ],
    "sg:phone":"+1   ",
    "sg:postcode":"28303",
    "sg:province":"NC",
    "sg:tags":[
        "day"
    ],
    "wof:name":"Blossom Day Care",
    "wof:placetype":"venue"
},
  "geometry": {"coordinates":[-78.98072500000001,35.084693],"type":"Point"}
}