{
  "type": "Feature",
  "properties": {
    "addr:full":"660 Old Caroleen Rd Forest City NC 28043",
    "addr:housenumber":"660",
    "addr:postcode":"28043",
    "addr:street":"Old Caroleen Rd",
    "iso:country":"US",
    "sg:address":"660 Old Caroleen Rd",
    "sg:city":"Forest City",
    "sg:classifiers":[
        {
            "category":"Freight",
            "type":"Transportation"
        }
    ],
    "sg:phone":"+1 828 248 1191",
    "sg:postcode":"28043",
    "sg:province":"NC",
    "sg:tags":[
        "warehouse"
    ],
    "wof:name":"A G Industries Inc",
    "wof:placetype":"venue"
},
  "geometry": {"coordinates":[-81.842552,35.32392],"type":"Point"}
}