{
  "type": "Feature",
  "properties": {
    "iso:country":"US",
    "sg:address":"4465 Newton Grove Hwy",
    "sg:city":"Newton Grove",
    "sg:classifiers":[
        {
            "category":"Organizations",
            "subcategory":"Religious Organization",
            "type":"Services"
        }
    ],
    "sg:phone":"+1 910 567 2682",
    "sg:postcode":"28366",
    "sg:province":"NC",
    "sg:tags":[
        "church"
    ],
    "wof:name":"Little Field Baptist Church",
    "wof:placetype":"venue"
},
  "geometry": {"coordinates":[-78.41987899999999,35.208393],"type":"Point"}
}