{
  "type": "Feature",
  "properties": {
    "iso:country":"US",
    "sg:address":"108 Northwoods Village Dr",
    "sg:city":"Cary",
    "sg:classifiers":[
        {
            "category":"Professional",
            "subcategory":"Computer Services",
            "type":"Services"
        }
    ],
    "sg:phone":"+1   ",
    "sg:postcode":"27513",
    "sg:province":"NC",
    "sg:tags":[
        "programming",
        "consulting",
        "technology"
    ],
    "wof:name":"Helix Computing Systems LLC",
    "wof:placetype":"venue"
},
  "geometry": {"coordinates":[-78.77403,35.803841],"type":"Point"}
}