{
  "type": "Feature",
  "properties": {
    "iso:country":"US",
    "sg:address":"6303 Oleander Drive Suite 103-B",
    "sg:city":"Wilmington",
    "sg:classifiers":[
        {
            "category":"Professional",
            "subcategory":"Computer Services",
            "type":"Services"
        }
    ],
    "sg:phone":"+1 910 796 3909",
    "sg:postcode":"28403",
    "sg:province":"NC",
    "sg:website":"http://www.proformadocuments.com",
    "wof:name":"ProForma Document Management Services",
    "wof:placetype":"venue"
},
  "geometry": {"coordinates":[-77.835971,34.211285],"type":"Point"}
}