{
  "type": "Feature",
  "properties": {
    "addr:full":"5202 Carolina Beach Rd Wilmington NC 28412",
    "addr:housenumber":"5202",
    "addr:postcode":"28412",
    "addr:street":"Carolina Beach Rd",
    "iso:country":"US",
    "sg:address":"5202 Carolina Beach Rd",
    "sg:city":"Wilmington",
    "sg:classifiers":[
        {
            "category":"Building & Trades",
            "subcategory":"Cleaning & Sanitation",
            "type":"Services"
        },
        {
            "category":"Professional",
            "type":"Services"
        }
    ],
    "sg:phone":"+1 910 799 2530",
    "sg:postcode":"28412",
    "sg:province":"NC",
    "sg:tags":[
        "house",
        "establishment"
    ],
    "wof:name":"Matt Marshall & Co Inc",
    "wof:placetype":"venue"
},
  "geometry": {"coordinates":[-77.897015,34.143417],"type":"Point"}
}