{
  "type": "Feature",
  "properties": {
    "addr:full":"9101 Field Dove Ct Charlotte NC 28210",
    "addr:housenumber":"9101",
    "addr:postcode":"28210",
    "addr:street":"Field Dove Ct",
    "iso:country":"US",
    "sg:address":"9101 Field Dove Ct",
    "sg:city":"Charlotte",
    "sg:classifiers":[
        {
            "category":"Professional",
            "subcategory":"Business Services",
            "type":"Services"
        }
    ],
    "sg:phone":"+1   ",
    "sg:postcode":"28210",
    "sg:province":"NC",
    "wof:name":"Gladden Enterprises",
    "wof:placetype":"venue"
},
  "geometry": {"coordinates":[-80.85413,35.107151],"type":"Point"}
}