{
  "type": "Feature",
  "properties": {
    "addr:full":"2614 S Horner Blvd Sanford NC 27332",
    "addr:housenumber":"2614",
    "addr:postcode":"27332",
    "addr:street":"S Horner Blvd",
    "iso:country":"US",
    "sg:address":"2614 S Horner Blvd",
    "sg:city":"Sanford",
    "sg:classifiers":[
        {
            "category":"Travel",
            "subcategory":"Hotels & Motels",
            "type":"Entertainment"
        }
    ],
    "sg:phone":"+1 919 708 7400",
    "sg:postcode":"27332",
    "sg:province":"NC",
    "sg:tags":[
        "operation"
    ],
    "wof:name":"Jameson Inns",
    "wof:placetype":"venue"
},
  "geometry": {"coordinates":[-79.14339099999999,35.45823],"type":"Point"}
}