{
  "type": "Feature",
  "properties": {
    "iso:country":"US",
    "sg:address":"509 N Lincoln St",
    "sg:city":"Benson",
    "sg:classifiers":[
        {
            "category":"Real Estate",
            "subcategory":"Surveying",
            "type":"Services"
        }
    ],
    "sg:phone":"+1 919 894 3575",
    "sg:postcode":"27504",
    "sg:province":"NC",
    "sg:tags":[
        "surveyor"
    ],
    "wof:name":"Lambert Surveying Inc",
    "wof:placetype":"venue"
},
  "geometry": {"coordinates":[-78.55438700000001,35.390536],"type":"Point"}
}