{
  "type": "Feature",
  "properties": {
    "addr:full":"126 Wells Rd Lawndale NC 28090",
    "addr:housenumber":"126",
    "addr:postcode":"28090",
    "addr:street":"Wells Rd",
    "iso:country":"US",
    "sg:address":"126 Wells Rd",
    "sg:city":"Lawndale",
    "sg:classifiers":[
        {
            "category":"Shopping",
            "subcategory":"Bicycles & Sporting Goods",
            "type":"Retail Goods"
        }
    ],
    "sg:phone":"+1 704 538 0429",
    "sg:postcode":"28090",
    "sg:province":"NC",
    "wof:name":"Sportsmans Dream",
    "wof:placetype":"venue"
},
  "geometry": {"coordinates":[-81.496673,35.423327],"type":"Point"}
}