{
  "type": "Feature",
  "properties": {
    "iso:country":"US",
    "sg:address":"8334 Pineville Matthews Rd",
    "sg:city":"Charlotte",
    "sg:classifiers":[
        {
            "category":"Ice Cream",
            "type":"Food & Drink"
        }
    ],
    "sg:menulink":"http://www.allmenus.com/nc/pineville/167649-dairy-queen/menu/",
    "sg:phone":"+1 704 752 3751",
    "sg:postcode":"28226",
    "sg:province":"NC",
    "sg:tags":[
        "burger",
        "american"
    ],
    "wof:name":"Dairy Queen",
    "wof:placetype":"venue"
},
  "geometry": {"coordinates":[-80.85992299999999,35.087587],"type":"Point"}
}