{
  "type": "Feature",
  "properties": {
    "iso:country":"US",
    "sg:address":"195 Skyland Dr",
    "sg:city":"Sylva",
    "sg:classifiers":[
        {
            "category":"Social Services",
            "type":"Services"
        }
    ],
    "sg:phone":"+1 828 586 8228",
    "sg:postcode":"28779",
    "sg:province":"NC",
    "sg:tags":[
        "organization",
        "welfare"
    ],
    "wof:name":"United Christian Ministry",
    "wof:placetype":"venue"
},
  "geometry": {"coordinates":[-83.213938,35.38294],"type":"Point"}
}