{
  "type": "Feature",
  "properties": {
    "iso:country":"US",
    "sg:address":"3085 Richlands Hwy",
    "sg:city":"Jacksonville",
    "sg:classifiers":[
        {
            "category":"Shopping",
            "subcategory":"Pharmacy",
            "type":"Retail Goods"
        }
    ],
    "sg:phone":"+1 910 455 9222",
    "sg:postcode":"28540",
    "sg:province":"NC",
    "wof:name":"Johnson Drug Westpark",
    "wof:placetype":"venue"
},
  "geometry": {"coordinates":[-77.47388100000001,34.755582],"type":"Point"}
}