{
  "type": "Feature",
  "properties": {
    "iso:country":"US",
    "sg:address":"1837 Old Watauga River Rd",
    "sg:city":"Sugar Grove",
    "sg:classifiers":[
        {
            "category":"Retail",
            "subcategory":"Repair Shop",
            "type":"Services"
        }
    ],
    "sg:phone":"+1 828 297 3727",
    "sg:postcode":"28679",
    "sg:province":"NC",
    "sg:tags":[
        "upholsterer"
    ],
    "wof:name":"Jack Teague Upholstery",
    "wof:placetype":"venue"
},
  "geometry": {"coordinates":[-81.83403199999999,36.245514],"type":"Point"}
}