{
  "type": "Feature",
  "properties": {
    "addr:full":"101 Olive St Winston Salem NC 27103",
    "addr:housenumber":"101",
    "addr:postcode":"27103",
    "addr:street":"Olive St",
    "iso:country":"US",
    "sg:address":"101 Olive St",
    "sg:city":"Winston Salem",
    "sg:classifiers":[
        {
            "category":"Travel",
            "subcategory":"Travel Agent",
            "type":"Entertainment"
        }
    ],
    "sg:phone":"+1 336 768 1013",
    "sg:postcode":"27103",
    "sg:province":"NC",
    "sg:tags":[
        "agency",
        "bureau"
    ],
    "wof:name":"Voyager Travel Svc LTD",
    "wof:placetype":"venue"
},
  "geometry": {"coordinates":[-80.298339,36.081993],"type":"Point"}
}