{
  "type": "Feature",
  "properties": {
    "addr:full":"188 Ivey Rd Mount Olive NC 28365",
    "addr:housenumber":"188",
    "addr:postcode":"28365",
    "addr:street":"Ivey Rd",
    "iso:country":"US",
    "sg:address":"188 Ivey Rd",
    "sg:city":"Mount Olive",
    "sg:classifiers":[
        {
            "category":"Farming",
            "subcategory":"Livestock Farm",
            "type":"Manufacturing & Wholesale Goods"
        }
    ],
    "sg:phone":"+1 919 658 6475",
    "sg:postcode":"28365",
    "sg:province":"NC",
    "sg:tags":[
        "beef",
        "feedlot",
        "cattle"
    ],
    "wof:name":"Ivey Yates",
    "wof:placetype":"venue"
},
  "geometry": {"coordinates":[-77.98057900000001,35.102989],"type":"Point"}
}