{
  "type": "Feature",
  "properties": {
    "addr:full":"810 Fairgrove Church Rd Hickory NC 28613",
    "addr:housenumber":"810",
    "addr:postcode":"28613",
    "addr:street":"Fairgrove Church Rd",
    "iso:country":"US",
    "sg:address":"810 Fairgrove Church Rd",
    "sg:city":"Hickory",
    "sg:classifiers":[
        {
            "category":"Health Services",
            "subcategory":"Hospital",
            "type":"Services"
        }
    ],
    "sg:phone":"+1 828 324 2273",
    "sg:postcode":"28613",
    "sg:province":"NC",
    "wof:name":"CARE-Line",
    "wof:placetype":"venue"
},
  "geometry": {"coordinates":[-81.26495799999999,35.712273],"type":"Point"}
}