{
  "type": "Feature",
  "properties": {
    "addr:full":"127 W Graham St Shelby NC 28150",
    "addr:housenumber":"127",
    "addr:postcode":"28150",
    "addr:street":"W Graham St",
    "iso:country":"US",
    "sg:address":"127 W Graham St",
    "sg:city":"Shelby",
    "sg:classifiers":[
        {
            "category":"Professional",
            "type":"Services"
        }
    ],
    "sg:phone":"+1 704 487 0476",
    "sg:postcode":"28150",
    "sg:province":"NC",
    "sg:tags":[
        "establishment"
    ],
    "wof:name":"Isothermal Planning & Dev",
    "wof:placetype":"venue"
},
  "geometry": {"coordinates":[-81.54124299999999,35.289465],"type":"Point"}
}