{
  "type": "Feature",
  "properties": {
    "addr:full":"172 N Main St Waynesville NC 28786",
    "addr:housenumber":"172",
    "addr:postcode":"28786",
    "addr:street":"N Main St",
    "iso:country":"US",
    "sg:address":"172 N Main St",
    "sg:city":"Waynesville",
    "sg:classifiers":[
        {
            "category":"Restaurant",
            "type":"Food & Drink"
        }
    ],
    "sg:phone":"+1 828 452 4228",
    "sg:postcode":"28786",
    "sg:province":"NC",
    "wof:name":"O'Malley's On Main Pub & Grill",
    "wof:placetype":"venue"
},
  "geometry": {"coordinates":[-82.98734,35.491021],"type":"Point"}
}