{
  "type": "Feature",
  "properties": {
    "addr:full":"110 McWalker Rd Reidsville NC 27320",
    "addr:housenumber":"110",
    "addr:postcode":"27320",
    "addr:street":"Mcwalker Rd",
    "iso:country":"US",
    "sg:address":"110 McWalker Rd",
    "sg:city":"Reidsville",
    "sg:classifiers":[
        {
            "category":"Food & Beverages",
            "subcategory":"Groceries & Convenience Stores",
            "type":"Retail Goods"
        }
    ],
    "sg:phone":"+1 336 342 3007",
    "sg:postcode":"27320",
    "sg:province":"NC",
    "sg:tags":[
        "grocer"
    ],
    "wof:name":"D & J Foodmart",
    "wof:placetype":"venue"
},
  "geometry": {"coordinates":[-79.659649,36.254687],"type":"Point"}
}