{
  "type": "Feature",
  "properties": {
    "iso:country":"US",
    "sg:address":"1312 Ramseur Rd",
    "sg:city":"Bessemer City",
    "sg:classifiers":[
        {
            "category":"Professional",
            "subcategory":"Business Services",
            "type":"Services"
        }
    ],
    "sg:phone":"+1   ",
    "sg:postcode":"28016",
    "sg:province":"NC",
    "wof:name":"Timothy Conner Enterprises",
    "wof:placetype":"venue"
},
  "geometry": {"coordinates":[-81.30682,35.309597],"type":"Point"}
}