{
  "type": "Feature",
  "properties": {
    "iso:country":"US",
    "sg:address":"102 Willow Rd",
    "sg:city":"Salisbury",
    "sg:classifiers":[
        {
            "category":"Organizations",
            "subcategory":"Religious Organization",
            "type":"Services"
        }
    ],
    "sg:phone":"+1 336 634 2417",
    "sg:postcode":"28147",
    "sg:province":"NC",
    "sg:tags":[
        "church"
    ],
    "wof:name":"Bethel United Methodist Church",
    "wof:placetype":"venue"
},
  "geometry": {"coordinates":[-80.535651,35.706475],"type":"Point"}
}