{
  "type": "Feature",
  "properties": {
    "addr:full":"108 W Caswell St Kinston NC 28501",
    "addr:housenumber":"108",
    "addr:postcode":"28501",
    "addr:street":"W Caswell St",
    "iso:country":"US",
    "sg:address":"108 W Caswell St",
    "sg:city":"Kinston",
    "sg:classifiers":[
        {
            "category":"Government",
            "subcategory":"Office",
            "type":"Public Place"
        }
    ],
    "sg:phone":"+1 252 527 5622",
    "sg:postcode":"28501",
    "sg:province":"NC",
    "sg:tags":[
        "county"
    ],
    "wof:name":"Lenoir County Juvenile Day",
    "wof:placetype":"venue"
},
  "geometry": {"coordinates":[-77.58193300000001,35.260197],"type":"Point"}
}