{
  "type": "Feature",
  "properties": {
    "iso:country":"US",
    "sg:address":"8012 Country Haven Dr",
    "sg:city":"New Hill",
    "sg:classifiers":[
        {
            "category":"Professional",
            "type":"Services"
        }
    ],
    "sg:phone":"+1 919 387 3777",
    "sg:postcode":"27562",
    "sg:province":"NC",
    "wof:name":"King Family Inc",
    "wof:placetype":"venue"
},
  "geometry": {"coordinates":[-78.91523100000001,35.683225],"type":"Point"}
}