{
  "type": "Feature",
  "properties": {
    "addr:full":"1752 Elizabeth Dr Kinston NC 28504",
    "addr:housenumber":"1752",
    "addr:postcode":"28504",
    "addr:street":"Elizabeth Dr",
    "iso:country":"US",
    "sg:address":"1752 Elizabeth Dr",
    "sg:city":"Kinston",
    "sg:classifiers":[
        {
            "category":"Health Services",
            "subcategory":"Nursing And Care Facility",
            "type":"Services"
        }
    ],
    "sg:phone":"+1 252 522 2117",
    "sg:postcode":"28504",
    "sg:province":"NC",
    "sg:tags":[
        "home",
        "rest"
    ],
    "wof:name":"Barbara's Loving Care Home",
    "wof:placetype":"venue"
},
  "geometry": {"coordinates":[-77.60537100000001,35.274198],"type":"Point"}
}