{
  "type": "Feature",
  "properties": {
    "addr:full":"1204 N Memorial Dr Greenville NC 27834",
    "addr:housenumber":"1204",
    "addr:postcode":"27834",
    "addr:street":"N Memorial Dr",
    "iso:country":"US",
    "sg:address":"1204 N Memorial Dr",
    "sg:city":"Greenville",
    "sg:classifiers":[
        {
            "category":"Wholesale",
            "subcategory":"Groceries",
            "type":"Manufacturing & Wholesale Goods"
        }
    ],
    "sg:phone":"+1 252 758 2501",
    "sg:postcode":"27834",
    "sg:province":"NC",
    "sg:tags":[
        "frozen",
        "packaged",
        "general"
    ],
    "wof:name":"Nash Finch Company",
    "wof:placetype":"venue"
},
  "geometry": {"coordinates":[-77.379364,35.630886],"type":"Point"}
}