{
  "type": "Feature",
  "properties": {
    "iso:country":"US",
    "sg:address":"314 Jeribec Dr",
    "sg:city":"Willow Spring",
    "sg:classifiers":[
        {
            "category":"Building & Trades",
            "subcategory":"Construction",
            "type":"Services"
        }
    ],
    "sg:phone":"+1 919 669 4761",
    "sg:postcode":"27592",
    "sg:province":"NC",
    "sg:tags":[
        "contractor"
    ],
    "wof:name":"Terry W Johnson",
    "wof:placetype":"venue"
},
  "geometry": {"coordinates":[-78.622579,35.546416],"type":"Point"}
}