{
  "type": "Feature",
  "properties": {
    "iso:country":"US",
    "sg:address":"810 E Cumberland St",
    "sg:city":"Dunn",
    "sg:classifiers":[
        {
            "category":"Autos & Motor Vehicles",
            "subcategory":"Fuel & Gas Station",
            "type":"Retail Goods"
        }
    ],
    "sg:phone":"+1 910 892 1320",
    "sg:postcode":"28334",
    "sg:province":"NC",
    "sg:tags":[
        "oil"
    ],
    "wof:name":"Hess Gas Station",
    "wof:placetype":"venue"
},
  "geometry": {"coordinates":[-78.602828,35.302625],"type":"Point"}
}