{
  "type": "Feature",
  "properties": {
    "addr:full":"4940 US Hwy 421 Yadkinville NC 27055",
    "addr:housenumber":"4940",
    "addr:postcode":"27055",
    "addr:street":"Us Hwy 421",
    "iso:country":"US",
    "sg:address":"4940 US Hwy 421",
    "sg:city":"Yadkinville",
    "sg:classifiers":[
        {
            "category":"Home & Garden",
            "subcategory":"Mobile Homes",
            "type":"Retail Goods"
        }
    ],
    "sg:phone":"+1 336 468 1981",
    "sg:postcode":"27055",
    "sg:province":"NC",
    "wof:name":"Oak Creek Village",
    "wof:placetype":"venue"
},
  "geometry": {"coordinates":[-80.512151,36.104343],"type":"Point"}
}