{
  "type": "Feature",
  "properties": {
    "iso:country":"US",
    "sg:address":"304 S Main St",
    "sg:city":"Mooresville",
    "sg:classifiers":[
        {
            "category":"Arts & Performance",
            "subcategory":"Art Gallery",
            "type":"Entertainment"
        },
        {
            "category":"Museum",
            "type":"Entertainment"
        }
    ],
    "sg:phone":"+1 704 664 2927",
    "sg:postcode":"28115",
    "sg:province":"NC",
    "sg:tags":[
        "consultant",
        "galleries"
    ],
    "wof:name":"Mooresville Museum, The",
    "wof:placetype":"venue"
},
  "geometry": {"coordinates":[-80.81645399999999,35.57969],"type":"Point"}
}