{
  "type": "Feature",
  "properties": {
    "iso:country":"US",
    "sg:address":"5852 Farringdon Pl",
    "sg:city":"Raleigh",
    "sg:classifiers":[
        {
            "category":"Real Estate",
            "subcategory":"Real Estate Agent",
            "type":"Services"
        }
    ],
    "sg:phone":"+1 919 878 5080",
    "sg:postcode":"27609",
    "sg:province":"NC",
    "wof:name":"Picket Fence Realty",
    "wof:placetype":"venue"
},
  "geometry": {"coordinates":[-78.621718,35.861596],"type":"Point"}
}