{
  "type": "Feature",
  "properties": {
    "iso:country":"US",
    "sg:address":"370 Bengreen Industrial Park Rd",
    "sg:city":"Elizabethtown",
    "sg:classifiers":[
        {
            "category":"Manufacturing",
            "subcategory":"Tools & Machinery",
            "type":"Manufacturing & Wholesale Goods"
        }
    ],
    "sg:phone":"+1 910 862 2688",
    "sg:postcode":"28337",
    "sg:province":"NC",
    "sg:tags":[
        "equipment",
        "system",
        "automation"
    ],
    "wof:name":"Westwood Manufacturing Inc",
    "wof:placetype":"venue"
},
  "geometry": {"coordinates":[-78.583146,34.604107],"type":"Point"}
}