{
  "type": "Feature",
  "properties": {
    "addr:full":"402 Turner St Beaufort NC 28516",
    "addr:housenumber":"402",
    "addr:postcode":"28516",
    "addr:street":"Turner St",
    "iso:country":"US",
    "sg:address":"402 Turner St",
    "sg:city":"Beaufort",
    "sg:classifiers":[
        {
            "category":"Government",
            "subcategory":"Office",
            "type":"Public Place"
        }
    ],
    "sg:phone":"+1 252 728 6585",
    "sg:postcode":"28516",
    "sg:province":"NC",
    "sg:tags":[
        "county"
    ],
    "wof:name":"Carteret County Council",
    "wof:placetype":"venue"
},
  "geometry": {"coordinates":[-76.661975,34.721836],"type":"Point"}
}