{
  "type": "Feature",
  "properties": {
    "addr:full":"135 Spindale St Spindale NC 28160",
    "addr:housenumber":"135",
    "addr:postcode":"28160",
    "addr:street":"Spindale St",
    "iso:country":"US",
    "sg:address":"135 Spindale St",
    "sg:city":"Spindale",
    "sg:classifiers":[
        {
            "category":"Wholesale",
            "subcategory":"Metals & Minerals",
            "type":"Manufacturing & Wholesale Goods"
        }
    ],
    "sg:phone":"+1 828 287 1327",
    "sg:postcode":"28160",
    "sg:province":"NC",
    "sg:tags":[
        "salvage",
        "center"
    ],
    "wof:name":"D & D Salvage",
    "wof:placetype":"venue"
},
  "geometry": {"coordinates":[-81.92887399999999,35.358508],"type":"Point"}
}