{
  "type": "Feature",
  "properties": {
    "addr:full":"11 E 1st Ave Lexington NC 27292",
    "addr:housenumber":"11",
    "addr:postcode":"27292",
    "addr:street":"E 1St Ave",
    "iso:country":"US",
    "sg:address":"11 E 1st Ave",
    "sg:city":"Lexington",
    "sg:classifiers":[
        {
            "category":"Personal",
            "subcategory":"Beauty Salon",
            "type":"Services"
        }
    ],
    "sg:phone":"+1   ",
    "sg:postcode":"27292",
    "sg:province":"NC",
    "sg:tags":[
        "shop"
    ],
    "wof:name":"Lexington Beauty Shop",
    "wof:placetype":"venue"
},
  "geometry": {"coordinates":[-80.25380699999999,35.823225],"type":"Point"}
}