{
  "type": "Feature",
  "properties": {
    "addr:full":"2747 Maiden Hwy Lincolnton NC 28092",
    "addr:housenumber":"2747",
    "addr:postcode":"28092",
    "addr:street":"Maiden Hwy",
    "iso:country":"US",
    "sg:address":"2747 Maiden Hwy",
    "sg:city":"Lincolnton",
    "sg:classifiers":[
        {
            "category":"Retail",
            "subcategory":"Auto Repair",
            "type":"Services"
        }
    ],
    "sg:phone":"+1   ",
    "sg:postcode":"28092",
    "sg:province":"NC",
    "sg:tags":[
        "general"
    ],
    "wof:name":"Brothers Body Shop",
    "wof:placetype":"venue"
},
  "geometry": {"coordinates":[-81.23964700000001,35.5071],"type":"Point"}
}