{
  "type": "Feature",
  "properties": {
    "iso:country":"US",
    "sg:address":"2960 Corriher Grange Rd",
    "sg:city":"Mount Ulla",
    "sg:classifiers":[
        {
            "category":"Professional",
            "subcategory":"Engineering",
            "type":"Services"
        }
    ],
    "sg:phone":"+1   ",
    "sg:postcode":"28125",
    "sg:province":"NC",
    "wof:name":"Msmc Holdings LLC",
    "wof:placetype":"venue"
},
  "geometry": {"coordinates":[-80.68651800000001,35.615293],"type":"Point"}
}