{
  "type": "Feature",
  "properties": {
    "addr:full":"141 S Main St Kernersville NC 27284",
    "addr:housenumber":"141",
    "addr:postcode":"27284",
    "addr:street":"S Main St",
    "iso:country":"US",
    "sg:address":"141 S Main St",
    "sg:city":"Kernersville",
    "sg:classifiers":[
        {
            "category":"Shopping",
            "subcategory":"Clothing, Apparel, & Fashions",
            "type":"Retail Goods"
        }
    ],
    "sg:phone":"+1 336 993 5055",
    "sg:postcode":"27284",
    "sg:province":"NC",
    "wof:name":"Foxy Lady Boutique",
    "wof:placetype":"venue"
},
  "geometry": {"coordinates":[-80.07373200000001,36.119171],"type":"Point"}
}