{
  "type": "Feature",
  "properties": {
    "addr:full":"321 Mangrove Dr Emerald Isle NC 28594",
    "addr:housenumber":"321",
    "addr:postcode":"28594",
    "addr:street":"Mangrove Dr",
    "iso:country":"US",
    "sg:address":"321 Mangrove Dr",
    "sg:city":"Emerald Isle",
    "sg:classifiers":[
        {
            "category":"Retail",
            "subcategory":"Laundry & Dry Cleaning",
            "type":"Services"
        },
        {
            "category":"Personal",
            "type":"Services"
        }
    ],
    "sg:phone":"+1 252 354 9449",
    "sg:postcode":"28594",
    "sg:province":"NC",
    "sg:tags":[
        "cleaners"
    ],
    "wof:name":"Isle Beach Gear Co",
    "wof:placetype":"venue"
},
  "geometry": {"coordinates":[-77.04217199999999,34.663361],"type":"Point"}
}