{
  "type": "Feature",
  "properties": {
    "addr:full":"5 Sidbrook Ct Durham NC 27704",
    "addr:housenumber":"5",
    "addr:postcode":"27704",
    "addr:street":"Sidbrook Ct",
    "iso:country":"US",
    "sg:address":"5 Sidbrook Ct",
    "sg:city":"Durham",
    "sg:classifiers":[
        {
            "category":"Organizations",
            "subcategory":"Community Association",
            "type":"Services"
        }
    ],
    "sg:phone":"+1 919 620 8638",
    "sg:postcode":"27704",
    "sg:province":"NC",
    "sg:tags":[
        "support",
        "business"
    ],
    "wof:name":"C C's Creative Works",
    "wof:placetype":"venue"
},
  "geometry": {"coordinates":[-78.92069600000001,36.054367],"type":"Point"}
}