{
  "type": "Feature",
  "properties": {
    "iso:country":"US",
    "sg:address":"1058 Rocky Ford Rd",
    "sg:city":"Reidsville",
    "sg:classifiers":[
        {
            "category":"Manufacturing",
            "subcategory":"Retail Goods",
            "type":"Manufacturing & Wholesale Goods"
        }
    ],
    "sg:phone":"+1 336 342 0484",
    "sg:postcode":"27320",
    "sg:province":"NC",
    "sg:tags":[
        "assembly",
        "fabricating"
    ],
    "wof:name":"Wendy Patterson",
    "wof:placetype":"venue"
},
  "geometry": {"coordinates":[-79.616141,36.320717],"type":"Point"}
}