{
  "type": "Feature",
  "properties": {
    "addr:full":"514 W James St La Grange NC 28551",
    "addr:housenumber":"514",
    "addr:postcode":"28551",
    "addr:street":"W James St",
    "iso:country":"US",
    "sg:address":"514 W James St",
    "sg:city":"La Grange",
    "sg:classifiers":[
        {
            "category":"Social Services",
            "subcategory":"Child Care",
            "type":"Services"
        }
    ],
    "sg:phone":"+1 252 566 2242",
    "sg:postcode":"28551",
    "sg:province":"NC",
    "sg:tags":[
        "day"
    ],
    "wof:name":"Country Kids Day Care Ctr Inc",
    "wof:placetype":"venue"
},
  "geometry": {"coordinates":[-77.794822,35.311115],"type":"Point"}
}