{
  "type": "Feature",
  "properties": {
    "iso:country":"US",
    "sg:address":"1508 Main St",
    "sg:city":"Ramseur",
    "sg:classifiers":[
        {
            "category":"Professional",
            "subcategory":"Research",
            "type":"Services"
        }
    ],
    "sg:phone":"+1 336 824 5535",
    "sg:postcode":"27316",
    "sg:province":"NC",
    "sg:tags":[
        "laboratory"
    ],
    "wof:name":"National Health Lab",
    "wof:placetype":"venue"
},
  "geometry": {"coordinates":[-79.65463699999999,35.733892],"type":"Point"}
}