{
  "type": "Feature",
  "properties": {
    "iso:country":"US",
    "sg:address":"1451 Whiteoak Crk Rd",
    "sg:city":"Burnsville",
    "sg:classifiers":[
        {
            "category":"Home & Garden",
            "subcategory":"Building Materials",
            "type":"Retail Goods"
        }
    ],
    "sg:phone":"+1 828 675 4882",
    "sg:postcode":"28714",
    "sg:province":"NC",
    "sg:tags":[
        "truss"
    ],
    "wof:name":"Appalachian Truss",
    "wof:placetype":"venue"
},
  "geometry": {"coordinates":[-82.19315400000001,35.831217],"type":"Point"}
}