{
  "type": "Feature",
  "properties": {
    "addr:full":"2121 35th Avenue Dr NE Hickory NC 28601",
    "addr:housenumber":"2121",
    "addr:postcode":"28601",
    "addr:street":"35Th Avenue Dr Ne",
    "iso:country":"US",
    "sg:address":"2121 35th Avenue Dr NE",
    "sg:city":"Hickory",
    "sg:classifiers":[
        {
            "category":"Education",
            "subcategory":"School",
            "type":"Public Place"
        }
    ],
    "sg:phone":"+1 828 256 2769",
    "sg:postcode":"28601",
    "sg:province":"NC",
    "sg:tags":[
        "elementary"
    ],
    "wof:name":"Clyde Campbell Elementary Schl",
    "wof:placetype":"venue"
},
  "geometry": {"coordinates":[-81.287903,35.778214],"type":"Point"}
}