{
  "type": "Feature",
  "properties": {
    "iso:country":"US",
    "sg:address":"101 Sea Hawk Dr W",
    "sg:city":"Kitty Hawk",
    "sg:classifiers":[
        {
            "category":"Food & Beverages",
            "subcategory":"Groceries & Convenience Stores",
            "type":"Retail Goods"
        }
    ],
    "sg:phone":"+1 252 261 1280",
    "sg:postcode":"27949",
    "sg:province":"NC",
    "wof:name":"Duck Deli Express Inc",
    "wof:placetype":"venue"
},
  "geometry": {"coordinates":[-75.748068,36.155475],"type":"Point"}
}