{
  "type": "Feature",
  "properties": {
    "iso:country":"US",
    "sg:address":"2819 Sandia Dr",
    "sg:city":"Raleigh",
    "sg:classifiers":[
        {
            "category":"Professional",
            "subcategory":"Computer Services",
            "type":"Services"
        }
    ],
    "sg:phone":"+1   ",
    "sg:postcode":"27607",
    "sg:province":"NC",
    "sg:tags":[
        "related"
    ],
    "wof:name":"Digital Services Inc",
    "wof:placetype":"venue"
},
  "geometry": {"coordinates":[-78.68339899999999,35.821061],"type":"Point"}
}