{
  "type": "Feature",
  "properties": {
    "addr:full":"103 N Jefferson Ave West Jefferson NC 28694",
    "addr:housenumber":"103",
    "addr:postcode":"28694",
    "addr:street":"N Jefferson Ave",
    "iso:country":"US",
    "sg:address":"103 N Jefferson Ave",
    "sg:city":"West Jefferson",
    "sg:classifiers":[
        {
            "category":"Shopping",
            "subcategory":"Crafts & Fabrics",
            "type":"Retail Goods"
        }
    ],
    "sg:phone":"+1 336 246 5655",
    "sg:postcode":"28694",
    "sg:province":"NC",
    "sg:tags":[
        "material",
        "quilting",
        "supply"
    ],
    "wof:name":"Quilt Gathering",
    "wof:placetype":"venue"
},
  "geometry": {"coordinates":[-81.492723,36.402822],"type":"Point"}
}