{
  "type": "Feature",
  "properties": {
    "iso:country":"US",
    "sg:address":"8021 US Hwy 221",
    "sg:city":"Marion",
    "sg:classifiers":[
        {
            "category":"Retail",
            "subcategory":"Auto Repair",
            "type":"Services"
        }
    ],
    "sg:phone":"+1 828 756 4212",
    "sg:postcode":"28752",
    "sg:province":"NC",
    "sg:tags":[
        "shop",
        "tire"
    ],
    "wof:name":"Woodlawn Tire & Alignment",
    "wof:placetype":"venue"
},
  "geometry": {"coordinates":[-82.04001700000001,35.786481],"type":"Point"}
}