{
  "type": "Feature",
  "properties": {
    "addr:full":"5162 Highpoint Dr Nashville NC 27856",
    "addr:housenumber":"5162",
    "addr:postcode":"27856",
    "addr:street":"Highpoint Dr",
    "iso:country":"US",
    "sg:address":"5162 Highpoint Dr",
    "sg:city":"Nashville",
    "sg:classifiers":[
        {
            "category":"Insurance",
            "subcategory":"Insurance Agent",
            "type":"Services"
        }
    ],
    "sg:phone":"+1 252 459 8215",
    "sg:postcode":"27856",
    "sg:province":"NC",
    "sg:tags":[
        "processing"
    ],
    "wof:name":"JMG Billing Svc",
    "wof:placetype":"venue"
},
  "geometry": {"coordinates":[-78.037088,36.040616],"type":"Point"}
}