{
  "type": "Feature",
  "properties": {
    "iso:country":"US",
    "sg:address":"429 S Hughes Blvd",
    "sg:city":"Elizabeth City",
    "sg:classifiers":[
        {
            "category":"Real Estate",
            "subcategory":"Real Estate Agent",
            "type":"Services"
        }
    ],
    "sg:phone":"+1 252 338 5786",
    "sg:postcode":"27909",
    "sg:province":"NC",
    "wof:name":"David Cross Real Estate",
    "wof:placetype":"venue"
},
  "geometry": {"coordinates":[-76.24543799999999,36.296279],"type":"Point"}
}