{
  "type": "Feature",
  "properties": {
    "addr:full":"215 Tryon Rd Raleigh NC 27603",
    "addr:housenumber":"215",
    "addr:postcode":"27603",
    "addr:street":"Tryon Rd",
    "iso:country":"US",
    "sg:address":"215 Tryon Rd",
    "sg:city":"Raleigh",
    "sg:classifiers":[
        {
            "category":"Professional",
            "subcategory":"Accounting & Tax Preparation",
            "type":"Services"
        }
    ],
    "sg:phone":"+1   ",
    "sg:postcode":"27603",
    "sg:province":"NC",
    "wof:name":"Tax Solutions Inc",
    "wof:placetype":"venue"
},
  "geometry": {"coordinates":[-78.64519300000001,35.731468],"type":"Point"}
}