{
  "type": "Feature",
  "properties": {
    "addr:full":"111 Morgan Bend Ct Chapel Hill NC 27517",
    "addr:housenumber":"111",
    "addr:postcode":"27517",
    "addr:street":"Morgan Bend Ct",
    "iso:country":"US",
    "sg:address":"111 Morgan Bend Ct",
    "sg:city":"Chapel Hill",
    "sg:classifiers":[
        {
            "category":"Professional",
            "subcategory":"Management & Consulting",
            "type":"Services"
        }
    ],
    "sg:phone":"+1   ",
    "sg:postcode":"27517",
    "sg:province":"NC",
    "sg:tags":[
        "business"
    ],
    "wof:name":"Mwy Consulting LLC",
    "wof:placetype":"venue"
},
  "geometry": {"coordinates":[-79.046916,35.888905],"type":"Point"}
}