{
  "type": "Feature",
  "properties": {
    "iso:country":"US",
    "sg:address":"4401 Colwick Rd",
    "sg:city":"Charlotte",
    "sg:classifiers":[
        {
            "category":"Wholesale",
            "subcategory":"Electrical",
            "type":"Manufacturing & Wholesale Goods"
        },
        {
            "category":"Shopping",
            "subcategory":"Computers & Home Electronics",
            "type":"Retail Goods"
        }
    ],
    "sg:phone":"+1 704 442 0008",
    "sg:postcode":"28211",
    "sg:province":"NC",
    "sg:tags":[
        "sound",
        "equipment",
        "system"
    ],
    "wof:name":"S E Systems",
    "wof:placetype":"venue"
},
  "geometry": {"coordinates":[-80.797122,35.17626],"type":"Point"}
}