{
  "type": "Feature",
  "properties": {
    "iso:country":"US",
    "sg:address":"1618 National Hwy",
    "sg:city":"Thomasville",
    "sg:classifiers":[
        {
            "category":"Food & Beverages",
            "subcategory":"Groceries & Convenience Stores",
            "type":"Retail Goods"
        }
    ],
    "sg:phone":"+1 336 886 2464",
    "sg:postcode":"27360",
    "sg:province":"NC",
    "sg:tags":[
        "grocer"
    ],
    "sg:website":"www.foodlion.com",
    "wof:name":"Food Lion",
    "wof:placetype":"venue"
},
  "geometry": {"coordinates":[-80.062281,35.907937],"type":"Point"}
}