{
  "type": "Feature",
  "properties": {
    "iso:country":"US",
    "sg:address":"4704 Myers Ln",
    "sg:city":"Harrisburg",
    "sg:classifiers":[
        {
            "category":"Professional",
            "subcategory":"Business Services",
            "type":"Services"
        }
    ],
    "sg:phone":"+1   ",
    "sg:postcode":"28075",
    "sg:province":"NC",
    "wof:name":"Ramar Rental Enterprises Inc",
    "wof:placetype":"venue"
},
  "geometry": {"coordinates":[-80.658879,35.281493],"type":"Point"}
}