{
  "type": "Feature",
  "properties": {
    "addr:full":"2525 S 17th St Wilmington NC 28401",
    "addr:housenumber":"2525",
    "addr:postcode":"28401",
    "addr:street":"S 17Th St",
    "iso:country":"US",
    "sg:address":"2525 S 17th St",
    "sg:city":"Wilmington",
    "sg:classifiers":[
        {
            "category":"Shopping",
            "subcategory":"Jewelry",
            "type":"Retail Goods"
        }
    ],
    "sg:phone":"+1 910 350 3100",
    "sg:postcode":"28401",
    "sg:province":"NC",
    "sg:tags":[
        "store"
    ],
    "wof:name":"Sparkle LLC",
    "wof:placetype":"venue"
},
  "geometry": {"coordinates":[-77.921192,34.19609],"type":"Point"}
}