{
  "type": "Feature",
  "properties": {
    "iso:country":"US",
    "sg:address":"1 Acton Circle",
    "sg:city":"Asheville",
    "sg:classifiers":[
        {
            "category":"Travel",
            "subcategory":"Hotels & Motels",
            "type":"Entertainment"
        }
    ],
    "sg:phone":"+1 828 665 2100",
    "sg:postcode":"28806",
    "sg:province":"NC",
    "wof:name":"Budget Motel",
    "wof:placetype":"venue"
},
  "geometry": {"coordinates":[-82.642927,35.553271],"type":"Point"}
}