{
  "type": "Feature",
  "properties": {
    "addr:full":"5309 E Brewer St Raleigh NC 27610",
    "addr:housenumber":"5309",
    "addr:postcode":"27610",
    "addr:street":"E Brewer St",
    "iso:country":"US",
    "sg:address":"5309 E Brewer St",
    "sg:city":"Raleigh",
    "sg:classifiers":[
        {
            "category":"Shopping",
            "subcategory":"Music",
            "type":"Retail Goods"
        }
    ],
    "sg:phone":"+1 919 212 1289",
    "sg:postcode":"27610",
    "sg:province":"NC",
    "wof:name":"Flygirl Records/Sandy Kane",
    "wof:placetype":"venue"
},
  "geometry": {"coordinates":[-78.549847,35.760306],"type":"Point"}
}