{
  "type": "Feature",
  "properties": {
    "addr:full":"2607 Balls Creek Rd Newton NC 28658",
    "addr:housenumber":"2607",
    "addr:postcode":"28658",
    "addr:street":"Balls Creek Rd",
    "iso:country":"US",
    "sg:address":"2607 Balls Creek Rd",
    "sg:city":"Newton",
    "sg:classifiers":[
        {
            "category":"Home & Garden",
            "subcategory":"Garden Supply",
            "type":"Retail Goods"
        }
    ],
    "sg:phone":"+1 828 244 0906",
    "sg:postcode":"28658",
    "sg:province":"NC",
    "wof:name":"Balls Creek Farm & Garden",
    "wof:placetype":"venue"
},
  "geometry": {"coordinates":[-81.127892,35.63143],"type":"Point"}
}