{
  "type": "Feature",
  "properties": {
    "iso:country":"US",
    "sg:address":"511 Owen Dr",
    "sg:city":"Fayetteville",
    "sg:classifiers":[
        {
            "category":"Health Services",
            "subcategory":"Doctor",
            "type":"Services"
        }
    ],
    "sg:phone":"+1 910 323 5433",
    "sg:postcode":"28304",
    "sg:province":"NC",
    "sg:tags":[
        "medical"
    ],
    "wof:name":"Linda T McAlister Ob-Gyn",
    "wof:placetype":"venue"
},
  "geometry": {"coordinates":[-78.933042,35.037107],"type":"Point"}
}