{
  "type": "Feature",
  "properties": {
    "iso:country":"US",
    "sg:address":"941 Bryansplace Rd",
    "sg:city":"Winston Salem",
    "sg:classifiers":[
        {
            "category":"Health Services",
            "subcategory":"Doctor",
            "type":"Services"
        }
    ],
    "sg:phone":"+1   ",
    "sg:postcode":"27104",
    "sg:province":"NC",
    "sg:tags":[
        "physician"
    ],
    "wof:name":"Michael J Pollar M D",
    "wof:placetype":"venue"
},
  "geometry": {"coordinates":[-80.344657,36.103384],"type":"Point"}
}