{
  "type": "Feature",
  "properties": {
    "addr:full":"7761 US Hwy 158 Seaboard NC 27870",
    "addr:housenumber":"7761",
    "addr:postcode":"27870",
    "addr:street":"Us Hwy 158",
    "iso:country":"US",
    "sg:address":"7761 US Hwy 158",
    "sg:city":"Seaboard",
    "sg:classifiers":[
        {
            "category":"Shopping",
            "subcategory":"Florist",
            "type":"Retail Goods"
        }
    ],
    "sg:phone":"+1 252 534 1604",
    "sg:postcode":"27870",
    "sg:province":"NC",
    "wof:name":"Christie's",
    "wof:placetype":"venue"
},
  "geometry": {"coordinates":[-77.783406,36.451585],"type":"Point"}
}