{
  "type": "Feature",
  "properties": {
    "iso:country":"US",
    "sg:address":"4211 Tallwood Dr",
    "sg:city":"Greensboro",
    "sg:classifiers":[
        {
            "category":"Real Estate",
            "subcategory":"Real Estate Operator",
            "type":"Services"
        }
    ],
    "sg:phone":"+1 336 632 9456",
    "sg:postcode":"27410",
    "sg:province":"NC",
    "sg:tags":[
        "building",
        "nonresidential"
    ],
    "wof:name":"Triple J Properties Burling",
    "wof:placetype":"venue"
},
  "geometry": {"coordinates":[-79.859707,36.093213],"type":"Point"}
}