{
  "type": "Feature",
  "properties": {
    "iso:country":"US",
    "sg:address":"37 Thompson Ct",
    "sg:city":"Rocky Point",
    "sg:classifiers":[
        {
            "category":"Retail",
            "subcategory":"Repair Shop",
            "type":"Services"
        }
    ],
    "sg:phone":"+1   ",
    "sg:postcode":"28457",
    "sg:province":"NC",
    "sg:tags":[
        "electrical"
    ],
    "wof:name":"Reliable Appliance Repair",
    "wof:placetype":"venue"
},
  "geometry": {"coordinates":[-77.892672,34.455547],"type":"Point"}
}