{
  "type": "Feature",
  "properties": {
    "addr:full":"219 S Battleground Ave Kings Mountain NC 28086",
    "addr:housenumber":"219",
    "addr:postcode":"28086",
    "addr:street":"S Battleground Ave",
    "iso:country":"US",
    "sg:address":"219 S Battleground Ave",
    "sg:city":"Kings Mountain",
    "sg:classifiers":[
        {
            "category":"Professional",
            "subcategory":"Business Services",
            "type":"Services"
        }
    ],
    "sg:phone":"+1 704 730 0084",
    "sg:postcode":"28086",
    "sg:province":"NC",
    "sg:tags":[
        "embroidery"
    ],
    "wof:name":"Adventures In Advertising",
    "wof:placetype":"venue"
},
  "geometry": {"coordinates":[-81.344373,35.238642],"type":"Point"}
}