{
  "type": "Feature",
  "properties": {
    "addr:full":"254 Kemper Rd Shelby NC 28152",
    "addr:housenumber":"254",
    "addr:postcode":"28152",
    "addr:street":"Kemper Rd",
    "iso:country":"US",
    "sg:address":"254 Kemper Rd",
    "sg:city":"Shelby",
    "sg:classifiers":[
        {
            "category":"Government",
            "subcategory":"Office",
            "type":"Public Place"
        }
    ],
    "sg:phone":"+1 704 480 5425",
    "sg:postcode":"28152",
    "sg:province":"NC",
    "sg:tags":[
        "state",
        "program"
    ],
    "wof:name":"Transportation Dept Mntnc",
    "wof:placetype":"venue"
},
  "geometry": {"coordinates":[-81.484244,35.28335],"type":"Point"}
}