{
  "type": "Feature",
  "properties": {
    "addr:full":"10223 University City Blvd Charlotte NC 28213",
    "addr:housenumber":"10223",
    "addr:postcode":"28213",
    "addr:street":"University City Blvd",
    "iso:country":"US",
    "sg:address":"10223 University City Blvd",
    "sg:city":"Charlotte",
    "sg:classifiers":[
        {
            "category":"Shopping",
            "subcategory":"Pharmacy",
            "type":"Retail Goods"
        }
    ],
    "sg:phone":"+1 704 593 1321",
    "sg:postcode":"28213",
    "sg:province":"NC",
    "wof:name":"CVS",
    "wof:placetype":"venue"
},
  "geometry": {"coordinates":[-80.71346,35.310882],"type":"Point"}
}