{
  "type": "Feature",
  "properties": {
    "addr:full":"1388 Institute Rd Kinston NC 28504",
    "addr:housenumber":"1388",
    "addr:postcode":"28504",
    "addr:street":"Institute Rd",
    "iso:country":"US",
    "sg:address":"1388 Institute Rd",
    "sg:city":"Kinston",
    "sg:classifiers":[
        {
            "category":"Organizations",
            "subcategory":"Religious Organization",
            "type":"Services"
        }
    ],
    "sg:phone":"+1 252 527 7006",
    "sg:postcode":"28504",
    "sg:province":"NC",
    "sg:tags":[
        "church"
    ],
    "wof:name":"God's House Of Gifts",
    "wof:placetype":"venue"
},
  "geometry": {"coordinates":[-77.637355,35.344096],"type":"Point"}
}