{
  "type": "Feature",
  "properties": {
    "iso:country":"US",
    "sg:address":"57 Crestfield Ave",
    "sg:city":"Asheville",
    "sg:classifiers":[
        {
            "category":"Professional",
            "type":"Services"
        }
    ],
    "sg:phone":"+1 828 251 1225",
    "sg:postcode":"28804",
    "sg:province":"NC",
    "wof:name":"Ronnie K Goldsmith",
    "wof:placetype":"venue"
},
  "geometry": {"coordinates":[-82.587031,35.628138],"type":"Point"}
}