{
  "type": "Feature",
  "properties": {
    "addr:full":"2346 Smokey Dan Kennel Rd Vale NC 28168",
    "addr:housenumber":"2346",
    "addr:postcode":"28168",
    "addr:street":"Smokey Dan Kennel Rd",
    "iso:country":"US",
    "sg:address":"2346 Smokey Dan Kennel Rd",
    "sg:city":"Vale",
    "sg:classifiers":[
        {
            "category":"Wholesale",
            "subcategory":"Farm Supplies",
            "type":"Manufacturing & Wholesale Goods"
        }
    ],
    "sg:phone":"+1 704 276 1534",
    "sg:postcode":"28168",
    "sg:province":"NC",
    "sg:tags":[
        "feed"
    ],
    "wof:name":"Dan Smokey Hunting & Sporting",
    "wof:placetype":"venue"
},
  "geometry": {"coordinates":[-81.480768,35.566451],"type":"Point"}
}