{
  "type": "Feature",
  "properties": {
    "iso:country":"US",
    "sg:address":"5650 Reidsville Rd",
    "sg:city":"Belews Creek",
    "sg:classifiers":[
        {
            "category":"Autos & Motor Vehicles",
            "subcategory":"Motorcycle Sales",
            "type":"Retail Goods"
        }
    ],
    "sg:phone":"+1 336 595 8810",
    "sg:postcode":"27009",
    "sg:province":"NC",
    "sg:tags":[
        "car",
        "golf",
        "cart"
    ],
    "wof:name":"Mc Tron Inc",
    "wof:placetype":"venue"
},
  "geometry": {"coordinates":[-80.112398,36.185481],"type":"Point"}
}