{
  "type": "Feature",
  "properties": {
    "addr:full":"555 Twin Oaks Rd Elkin NC 28621",
    "addr:housenumber":"555",
    "addr:postcode":"28621",
    "addr:street":"Twin Oaks Rd",
    "iso:country":"US",
    "sg:address":"555 Twin Oaks Rd",
    "sg:city":"Elkin",
    "sg:classifiers":[
        {
            "category":"Organizations",
            "subcategory":"Religious Organization",
            "type":"Services"
        }
    ],
    "sg:phone":"+1 336 366 4722",
    "sg:postcode":"28621",
    "sg:province":"NC",
    "sg:tags":[
        "church"
    ],
    "wof:name":"Salem Fork Baptist Church",
    "wof:placetype":"venue"
},
  "geometry": {"coordinates":[-80.77643500000001,36.383819],"type":"Point"}
}