{
  "type": "Feature",
  "properties": {
    "addr:full":"2734 Mellon Rd Shelby NC 28150",
    "addr:housenumber":"2734",
    "addr:postcode":"28150",
    "addr:street":"Mellon Rd",
    "iso:country":"US",
    "sg:address":"2734 Mellon Rd",
    "sg:city":"Shelby",
    "sg:classifiers":[
        {
            "category":"Professional",
            "subcategory":"Business Services",
            "type":"Services"
        }
    ],
    "sg:phone":"+1   ",
    "sg:postcode":"28150",
    "sg:province":"NC",
    "wof:name":"Maverick International",
    "wof:placetype":"venue"
},
  "geometry": {"coordinates":[-81.65485700000001,35.333945],"type":"Point"}
}