{
  "type": "Feature",
  "properties": {
    "addr:full":"4634 Devonshire Dr Fayetteville NC 28304",
    "addr:housenumber":"4634",
    "addr:postcode":"28304",
    "addr:street":"Devonshire Dr",
    "iso:country":"US",
    "sg:address":"4634 Devonshire Dr",
    "sg:city":"Fayetteville",
    "sg:classifiers":[
        {
            "category":"Building & Trades",
            "subcategory":"Landscaping Services",
            "type":"Services"
        }
    ],
    "sg:phone":"+1 910 425 6872",
    "sg:postcode":"28304",
    "sg:province":"NC",
    "sg:tags":[
        "landscape"
    ],
    "wof:name":"G Srm Inc",
    "wof:placetype":"venue"
},
  "geometry": {"coordinates":[-78.954863,35.024125],"type":"Point"}
}