{
  "type": "Feature",
  "properties": {
    "iso:country":"US",
    "sg:address":"5000 Nations Crossing Rd",
    "sg:city":"Charlotte",
    "sg:classifiers":[
        {
            "category":"Professional",
            "subcategory":"Employment Agencies",
            "type":"Services"
        }
    ],
    "sg:phone":"+1 704 527 4747",
    "sg:postcode":"28217",
    "sg:province":"NC",
    "sg:tags":[
        "opportunity",
        "help",
        "supply"
    ],
    "wof:name":"Integra Staffing LLC",
    "wof:placetype":"venue"
},
  "geometry": {"coordinates":[-80.884235,35.178535],"type":"Point"}
}