{
  "type": "Feature",
  "properties": {
    "addr:full":"399 Craft Dr Winston Salem NC 27105",
    "addr:housenumber":"399",
    "addr:postcode":"27105",
    "addr:street":"Craft Dr",
    "iso:country":"US",
    "sg:address":"399 Craft Dr",
    "sg:city":"Winston Salem",
    "sg:classifiers":[
        {
            "category":"Government",
            "subcategory":"Office",
            "type":"Public Place"
        }
    ],
    "sg:phone":"+1 336 896 7021",
    "sg:postcode":"27105",
    "sg:province":"NC",
    "sg:tags":[
        "state",
        "program"
    ],
    "sg:website":"www.ncdot.org",
    "wof:name":"Transportation Dept Garage",
    "wof:placetype":"venue"
},
  "geometry": {"coordinates":[-80.26083,36.144586],"type":"Point"}
}