{
  "type": "Feature",
  "properties": {
    "addr:full":"245 Cunningham Rd Franklin NC 28734",
    "addr:housenumber":"245",
    "addr:postcode":"nc 28734",
    "addr:street":"Cunningham Rd",
    "iso:country":"US",
    "sg:address":"245 Cunningham Rd",
    "sg:city":"Franklin",
    "sg:classifiers":[
        {
            "category":"Banks & Credit Unions",
            "subcategory":"Bank",
            "type":"Services"
        }
    ],
    "sg:phone":"+1 828 369 3536",
    "sg:postcode":"28734",
    "sg:province":"NC",
    "sg:website":"www.ncsecu.org",
    "wof:name":"State Employees Credit Union",
    "wof:placetype":"venue"
},
  "geometry": {"coordinates":[-83.35637,35.184175],"type":"Point"}
}