{
  "type": "Feature",
  "properties": {
    "addr:full":"1211 Spring St Charlotte NC 28206",
    "addr:housenumber":"1211",
    "addr:postcode":"28206",
    "addr:street":"Spring St",
    "iso:country":"US",
    "sg:address":"1211 Spring St",
    "sg:city":"Charlotte",
    "sg:classifiers":[
        {
            "category":"Social Services",
            "type":"Services"
        }
    ],
    "sg:phone":"+1   ",
    "sg:postcode":"28206",
    "sg:province":"NC",
    "wof:name":"Greenvl Commnty Comb Youth Org",
    "wof:placetype":"venue"
},
  "geometry": {"coordinates":[-80.83952499999999,35.245039],"type":"Point"}
}