{
  "type": "Feature",
  "properties": {
    "iso:country":"US",
    "sg:address":"101 Smokehouse Ln",
    "sg:city":"Cary",
    "sg:classifiers":[
        {
            "category":"Building & Trades",
            "subcategory":"Plumbing",
            "type":"Services"
        }
    ],
    "sg:phone":"+1 919 961 4588",
    "sg:postcode":"27513",
    "sg:province":"NC",
    "wof:name":"Sparkle General Construction",
    "wof:placetype":"venue"
},
  "geometry": {"coordinates":[-78.76842000000001,35.807545],"type":"Point"}
}