{
  "type": "Feature",
  "properties": {
    "iso:country":"US",
    "sg:address":"862 Iron Works Rd",
    "sg:city":"Reidsville",
    "sg:classifiers":[
        {
            "category":"Organizations",
            "subcategory":"Religious Organization",
            "type":"Services"
        }
    ],
    "sg:phone":"+1   ",
    "sg:postcode":"27320",
    "sg:province":"NC",
    "wof:name":"Speedwell Presbyterian Church",
    "wof:placetype":"venue"
},
  "geometry": {"coordinates":[-79.728675,36.319851],"type":"Point"}
}