{
  "type": "Feature",
  "properties": {
    "addr:full":"1260 Airport Rd Shelby NC 28150",
    "addr:housenumber":"1260",
    "addr:postcode":"28150",
    "addr:street":"Airport Rd",
    "iso:country":"US",
    "sg:address":"1260 Airport Rd",
    "sg:city":"Shelby",
    "sg:classifiers":[
        {
            "category":"Social Services",
            "subcategory":"Child Care",
            "type":"Services"
        }
    ],
    "sg:phone":"+1 704 482 6502",
    "sg:postcode":"28150",
    "sg:province":"NC",
    "sg:tags":[
        "day"
    ],
    "wof:name":"Beginnings",
    "wof:placetype":"venue"
},
  "geometry": {"coordinates":[-81.501104,35.315438],"type":"Point"}
}