{
  "type": "Feature",
  "properties": {
    "iso:country":"US",
    "sg:address":"152 Friar Tuck Rd",
    "sg:city":"Forest City",
    "sg:classifiers":[
        {
            "category":"Manufacturing",
            "subcategory":"Printing",
            "type":"Manufacturing & Wholesale Goods"
        }
    ],
    "sg:phone":"+1 828 245 8011",
    "sg:postcode":"28043",
    "sg:province":"NC",
    "sg:tags":[
        "printer"
    ],
    "wof:name":"Mott Printing",
    "wof:placetype":"venue"
},
  "geometry": {"coordinates":[-81.88743700000001,35.327861],"type":"Point"}
}