{
  "type": "Feature",
  "properties": {
    "iso:country":"US",
    "sg:address":"518 Foxfield Ln",
    "sg:city":"Matthews",
    "sg:classifiers":[
        {
            "category":"Professional",
            "subcategory":"Secretarial Services",
            "type":"Services"
        }
    ],
    "sg:phone":"+1   ",
    "sg:postcode":"28105",
    "sg:province":"NC",
    "sg:tags":[
        "reporting"
    ],
    "wof:name":"Amy Waits",
    "wof:placetype":"venue"
},
  "geometry": {"coordinates":[-80.743686,35.106788],"type":"Point"}
}