{
  "type": "Feature",
  "properties": {
    "iso:country":"US",
    "sg:address":"8118 Reynolda Rd",
    "sg:city":"Pfafftown",
    "sg:classifiers":[
        {
            "category":"Professional",
            "subcategory":"Management & Consulting",
            "type":"Services"
        }
    ],
    "sg:phone":"+1 336 924 8100",
    "sg:postcode":"27040",
    "sg:province":"NC",
    "sg:tags":[
        "marketing",
        "consultant"
    ],
    "sg:website":"www.spevco.com",
    "wof:name":"Spevco",
    "wof:placetype":"venue"
},
  "geometry": {"coordinates":[-80.391667,36.201703],"type":"Point"}
}