{
  "type": "Feature",
  "properties": {
    "iso:country":"US",
    "sg:address":"930 Meacham Rd",
    "sg:city":"Statesville",
    "sg:classifiers":[
        {
            "category":"Manufacturing",
            "subcategory":"Paper Products",
            "type":"Manufacturing & Wholesale Goods"
        }
    ],
    "sg:phone":"+1 704 872 6541",
    "sg:postcode":"28677",
    "sg:province":"NC",
    "wof:name":"International Paper Co",
    "wof:placetype":"venue"
},
  "geometry": {"coordinates":[-80.921566,35.796999],"type":"Point"}
}