{
  "type": "Feature",
  "properties": {
    "iso:country":"US",
    "sg:address":"316 Euray Moore Rd",
    "sg:city":"Warsaw",
    "sg:phone":"+1 910 293 7076",
    "sg:postcode":"28398",
    "sg:province":"NC",
    "sg:tags":[
        "tobacco",
        "farm",
        "corn",
        "crop",
        "general",
        "soybean"
    ],
    "wof:name":"Moore Euray",
    "wof:placetype":"venue"
},
  "geometry": {"coordinates":[-78.062729,34.953981],"type":"Point"}
}