{
  "type": "Feature",
  "properties": {
    "iso:country":"US",
    "sg:address":"500 Nc Highway 9",
    "sg:city":"Black Mountain",
    "sg:classifiers":[
        {
            "category":"Restaurant",
            "type":"Food & Drink"
        }
    ],
    "sg:menulink":"http://www.allmenus.com/nc/black-mountain/101838-huddle-house/menu/",
    "sg:phone":"+1 828 669 5763",
    "sg:postcode":"28711",
    "sg:province":"NC",
    "sg:tags":[
        "american",
        "diner"
    ],
    "wof:name":"Huddle House",
    "wof:placetype":"venue"
},
  "geometry": {"coordinates":[-82.307118,35.588711],"type":"Point"}
}