{
  "type": "Feature",
  "properties": {
    "iso:country":"US",
    "sg:address":"107 Craigy Ct",
    "sg:city":"Kill Devil Hills",
    "sg:classifiers":[
        {
            "category":"Real Estate",
            "subcategory":"Real Estate Agent",
            "type":"Services"
        }
    ],
    "sg:phone":"+1 252 441 9222",
    "sg:postcode":"27948",
    "sg:province":"NC",
    "wof:name":"Dream Coast Realty",
    "wof:placetype":"venue"
},
  "geometry": {"coordinates":[-75.72450499999999,36.006447],"type":"Point"}
}