{
  "type": "Feature",
  "properties": {
    "addr:full":"609 Kimberly Dr Greensboro NC 27408",
    "addr:housenumber":"609",
    "addr:postcode":"27408",
    "addr:street":"Kimberly Dr",
    "iso:country":"US",
    "sg:address":"609 Kimberly Dr",
    "sg:city":"Greensboro",
    "sg:classifiers":[
        {
            "category":"Professional",
            "type":"Services"
        }
    ],
    "sg:phone":"+1 336 275 6283",
    "sg:postcode":"27408",
    "sg:province":"NC",
    "wof:name":"Creative Endeavours By K",
    "wof:placetype":"venue"
},
  "geometry": {"coordinates":[-79.799137,36.10489],"type":"Point"}
}