{
  "type": "Feature",
  "properties": {
    "addr:full":"5006 Fairview Church Rd Trinity NC 27370",
    "addr:housenumber":"5006",
    "addr:postcode":"27370",
    "addr:street":"Fairview Church Rd",
    "iso:country":"US",
    "sg:address":"5006 Fairview Church Rd",
    "sg:city":"Trinity",
    "sg:classifiers":[
        {
            "category":"Recreation",
            "type":"Entertainment"
        }
    ],
    "sg:phone":"+1 336 861 8334",
    "sg:postcode":"27370",
    "sg:province":"NC",
    "sg:tags":[
        "stable"
    ],
    "wof:name":"Trinity Stables",
    "wof:placetype":"venue"
},
  "geometry": {"coordinates":[-79.952725,35.852472],"type":"Point"}
}