{
  "type": "Feature",
  "properties": {
    "iso:country":"US",
    "sg:address":"455 S Church St",
    "sg:city":"Winston Salem",
    "sg:classifiers":[
        {
            "category":"Organizations",
            "subcategory":"Religious Organization",
            "type":"Services"
        }
    ],
    "sg:phone":"+1 336 725 2589",
    "sg:postcode":"27101",
    "sg:province":"NC",
    "sg:tags":[
        "church"
    ],
    "sg:website":"www.mmfa.info",
    "wof:name":"Moravian Ministries Foundation",
    "wof:placetype":"venue"
},
  "geometry": {"coordinates":[-80.241525,36.089218],"type":"Point"}
}