{
  "type": "Feature",
  "properties": {
    "iso:country":"US",
    "sg:address":"7233 Pineville-Matthews Rd",
    "sg:city":"Charlotte",
    "sg:classifiers":[
        {
            "category":"Building & Trades",
            "subcategory":"Pest Control",
            "type":"Services"
        }
    ],
    "sg:phone":"+1 704 752 3693",
    "sg:postcode":"28226",
    "sg:province":"NC",
    "wof:name":"Mosquito Squad Franchise Corp",
    "wof:placetype":"venue"
},
  "geometry": {"coordinates":[-80.839426,35.087076],"type":"Point"}
}