{
  "type": "Feature",
  "properties": {
    "addr:full":"3515 Cardwell Dr Burlington NC 27215",
    "addr:housenumber":"3515",
    "addr:postcode":"27215",
    "addr:street":"Cardwell Dr",
    "iso:country":"US",
    "sg:address":"3515 Cardwell Dr",
    "sg:city":"Burlington",
    "sg:classifiers":[
        {
            "category":"Personal",
            "subcategory":"Beauty Salon",
            "type":"Services"
        }
    ],
    "sg:phone":"+1 336 584 9194",
    "sg:postcode":"27215",
    "sg:province":"NC",
    "sg:tags":[
        "shop"
    ],
    "wof:name":"Beauty Boutique",
    "wof:placetype":"venue"
},
  "geometry": {"coordinates":[-79.483091,36.075102],"type":"Point"}
}