{
  "type": "Feature",
  "properties": {
    "addr:full":"4276 Helena St Hudson NC 28638",
    "addr:housenumber":"4276",
    "addr:postcode":"28638",
    "addr:street":"Helena St",
    "iso:country":"US",
    "sg:address":"4276 Helena St",
    "sg:city":"Hudson",
    "sg:classifiers":[
        {
            "category":"Manufacturing",
            "subcategory":"Signs",
            "type":"Manufacturing & Wholesale Goods"
        }
    ],
    "sg:phone":"+1 828 313 0996",
    "sg:postcode":"28638",
    "sg:province":"NC",
    "sg:tags":[
        "advertising",
        "specialty"
    ],
    "wof:name":"Patrick",
    "wof:placetype":"venue"
},
  "geometry": {"coordinates":[-81.47641400000001,35.82539],"type":"Point"}
}