{
  "type": "Feature",
  "properties": {
    "iso:country":"US",
    "sg:address":"6400 Fairview Rd",
    "sg:city":"Charlotte",
    "sg:classifiers":[
        {
            "category":"Restaurant",
            "type":"Food & Drink"
        }
    ],
    "sg:phone":"+1 704 364 4957",
    "sg:postcode":"28210",
    "sg:province":"NC",
    "sg:tags":[
        "pizza"
    ],
    "sg:website":"http://www.donatos.com",
    "wof:name":"Donato's Pizza Southpark",
    "wof:placetype":"venue"
},
  "geometry": {"coordinates":[-80.834518,35.149731],"type":"Point"}
}