{
  "type": "Feature",
  "properties": {
    "addr:full":"6320 Robinson Church Rd Charlotte NC 28215",
    "addr:housenumber":"6320",
    "addr:postcode":"28215",
    "addr:street":"Robinson Church Rd",
    "iso:country":"US",
    "sg:address":"6320 Robinson Church Rd",
    "sg:city":"Charlotte",
    "sg:classifiers":[
        {
            "category":"Shopping",
            "subcategory":"Crafts & Fabrics",
            "type":"Retail Goods"
        }
    ],
    "sg:phone":"+1 704 531 2154",
    "sg:postcode":"28215",
    "sg:province":"NC",
    "sg:tags":[
        "sewing"
    ],
    "wof:name":"Creative Sewing & Embroidery",
    "wof:placetype":"venue"
},
  "geometry": {"coordinates":[-80.727475,35.231541],"type":"Point"}
}