{
  "type": "Feature",
  "properties": {
    "addr:full":"120 Chadwick Ave Hendersonville NC 28792",
    "addr:housenumber":"120",
    "addr:postcode":"28792",
    "addr:street":"Chadwick Ave",
    "iso:country":"US",
    "sg:address":"120 Chadwick Ave",
    "sg:city":"Hendersonville",
    "sg:classifiers":[
        {
            "category":"Personal",
            "subcategory":"Beauty Salon",
            "type":"Services"
        }
    ],
    "sg:phone":"+1 828 692 1939",
    "sg:postcode":"28792",
    "sg:province":"NC",
    "sg:tags":[
        "shop"
    ],
    "wof:name":"Jackie's Beauty Salon",
    "wof:placetype":"venue"
},
  "geometry": {"coordinates":[-82.45542,35.303431],"type":"Point"}
}