{
  "type": "Feature",
  "properties": {
    "iso:country":"US",
    "sg:address":"718 N Reilly Rd",
    "sg:city":"Fayetteville",
    "sg:classifiers":[
        {
            "category":"Banks & Credit Unions",
            "subcategory":"Bank",
            "type":"Services"
        }
    ],
    "sg:phone":"+1 910 867 5987",
    "sg:postcode":"28303",
    "sg:province":"NC",
    "sg:tags":[
        "machine",
        "teller",
        "automated"
    ],
    "wof:name":"Atm USA LLC",
    "wof:placetype":"venue"
},
  "geometry": {"coordinates":[-79.010717,35.101672],"type":"Point"}
}