{
  "type": "Feature",
  "properties": {
    "addr:full":"14 N Main St Marion NC 28752",
    "addr:housenumber":"14",
    "addr:postcode":"28752",
    "addr:street":"N Main St",
    "iso:country":"US",
    "sg:address":"14 N Main St",
    "sg:city":"Marion",
    "sg:classifiers":[
        {
            "category":"Food & Beverages",
            "subcategory":"Bakery",
            "type":"Retail Goods"
        }
    ],
    "sg:phone":"+1 828 659 8618",
    "sg:postcode":"28752",
    "sg:province":"NC",
    "sg:tags":[
        "baker"
    ],
    "wof:name":"Village Bakery",
    "wof:placetype":"venue"
},
  "geometry": {"coordinates":[-82.009077,35.684392],"type":"Point"}
}