{
  "type": "Feature",
  "properties": {
    "iso:country":"US",
    "sg:address":"301 Trindale Rd",
    "sg:city":"Archdale",
    "sg:classifiers":[
        {
            "category":"Wholesale",
            "subcategory":"Groceries",
            "type":"Manufacturing & Wholesale Goods"
        }
    ],
    "sg:phone":"+1 336 434 4011",
    "sg:postcode":"27263",
    "sg:province":"NC",
    "sg:tags":[
        "grocer"
    ],
    "wof:name":"Southern Sales & Imports Inc",
    "wof:placetype":"venue"
},
  "geometry": {"coordinates":[-79.97703799999999,35.913112],"type":"Point"}
}