{
  "type": "Feature",
  "properties": {
    "iso:country":"US",
    "sg:address":"1732 Julian R Allsbrook Hwy",
    "sg:city":"Roanoke Rapids",
    "sg:classifiers":[
        {
            "category":"Shopping",
            "subcategory":"Department Store",
            "type":"Retail Goods"
        }
    ],
    "sg:phone":"+1 252 535 1855",
    "sg:postcode":"27870",
    "sg:province":"NC",
    "wof:name":"Citi Trends",
    "wof:placetype":"venue"
},
  "geometry": {"coordinates":[-77.634928,36.432821],"type":"Point"}
}