{
  "type": "Feature",
  "properties": {
    "addr:full":"5901 Oleander Dr Wilmington NC 28403",
    "addr:housenumber":"5901",
    "addr:postcode":"28403",
    "addr:street":"Oleander Dr",
    "iso:country":"US",
    "sg:address":"5901 Oleander Dr",
    "sg:city":"Wilmington",
    "sg:classifiers":[
        {
            "category":"Ice Cream",
            "type":"Food & Drink"
        }
    ],
    "sg:menulink":"http://www.allmenus.com/nc/wilmington/167621-dairy-queen/menu/",
    "sg:phone":"+1 910 799 2902",
    "sg:postcode":"28403",
    "sg:province":"NC",
    "sg:tags":[
        "burger",
        "american"
    ],
    "wof:name":"Dairy Queen",
    "wof:placetype":"venue"
},
  "geometry": {"coordinates":[-77.843323,34.209458],"type":"Point"}
}