{
  "type": "Feature",
  "properties": {
    "iso:country":"US",
    "sg:address":"5 Pine St",
    "sg:city":"Enka",
    "sg:classifiers":[
        {
            "category":"Wholesale",
            "subcategory":"Hardware",
            "type":"Manufacturing & Wholesale Goods"
        }
    ],
    "sg:phone":"+1 828 667 0041",
    "sg:postcode":"28728",
    "sg:province":"NC",
    "sg:tags":[
        "refrigerating"
    ],
    "wof:name":"Lewis Refrigeration Co",
    "wof:placetype":"venue"
},
  "geometry": {"coordinates":[-82.644238,35.539724],"type":"Point"}
}