{
  "type": "Feature",
  "properties": {
    "iso:country":"US",
    "sg:address":"205 Bradshaw St",
    "sg:city":"Fairmont",
    "sg:classifiers":[
        {
            "category":"Professional",
            "subcategory":"Accounting & Tax Preparation",
            "type":"Services"
        }
    ],
    "sg:phone":"+1 910 628 7422",
    "sg:postcode":"28340",
    "sg:province":"NC",
    "sg:tags":[
        "accountant"
    ],
    "wof:name":"Shaw's Accounting & Tax Svc",
    "wof:placetype":"venue"
},
  "geometry": {"coordinates":[-79.116249,34.501555],"type":"Point"}
}