{
  "type": "Feature",
  "properties": {
    "addr:full":"300 S Stratford Rd Winston Salem NC 27103",
    "addr:housenumber":"300",
    "addr:postcode":"27103",
    "addr:street":"S Stratford Rd",
    "iso:country":"US",
    "sg:address":"300 S Stratford Rd",
    "sg:city":"Winston Salem",
    "sg:classifiers":[
        {
            "category":"Shopping",
            "subcategory":"Tobacco",
            "type":"Retail Goods"
        }
    ],
    "sg:phone":"+1 336 723 1269",
    "sg:postcode":"27103",
    "sg:province":"NC",
    "sg:tags":[
        "shop",
        "smoke",
        "supply"
    ],
    "wof:name":"Pipes Etc",
    "wof:placetype":"venue"
},
  "geometry": {"coordinates":[-80.283931,36.090494],"type":"Point"}
}