{
  "type": "Feature",
  "properties": {
    "addr:full":"1807 US Hwy 258 Kinston NC 28504",
    "addr:housenumber":"1807",
    "addr:postcode":"28504",
    "addr:street":"Us Hwy 258",
    "iso:country":"US",
    "sg:address":"1807 US Hwy 258",
    "sg:city":"Kinston",
    "sg:classifiers":[
        {
            "category":"Building & Trades",
            "subcategory":"Construction",
            "type":"Services"
        }
    ],
    "sg:phone":"+1 252 522 5914",
    "sg:postcode":"28504",
    "sg:province":"NC",
    "sg:tags":[
        "house"
    ],
    "wof:name":"Edwards Construction Co",
    "wof:placetype":"venue"
},
  "geometry": {"coordinates":[-77.602558,35.235361],"type":"Point"}
}