{
  "type": "Feature",
  "properties": {
    "iso:country":"US",
    "sg:address":"2705 Ten Oaks Ln",
    "sg:city":"Raleigh",
    "sg:classifiers":[
        {
            "category":"Professional",
            "subcategory":"Business Services",
            "type":"Services"
        }
    ],
    "sg:phone":"+1 919 661 8909",
    "sg:postcode":"27606",
    "sg:province":"NC",
    "sg:tags":[
        "interior",
        "consultant",
        "design",
        "decorator"
    ],
    "wof:name":"Betsy's Cottage Decorating",
    "wof:placetype":"venue"
},
  "geometry": {"coordinates":[-78.735579,35.686784],"type":"Point"}
}