{
  "type": "Feature",
  "properties": {
    "iso:country":"US",
    "sg:address":"504 Summit Ave",
    "sg:city":"Greensboro",
    "sg:classifiers":[
        {
            "category":"Professional",
            "subcategory":"Business Services",
            "type":"Services"
        }
    ],
    "sg:phone":"+1   ",
    "sg:postcode":"27405",
    "sg:province":"NC",
    "sg:tags":[
        "financial"
    ],
    "wof:name":"American General Finance Corp",
    "wof:placetype":"venue"
},
  "geometry": {"coordinates":[-79.781784,36.079716],"type":"Point"}
}