{
  "type": "Feature",
  "properties": {
    "addr:full":"132 W High Ave High Point NC 27260",
    "addr:housenumber":"132",
    "addr:postcode":"27260",
    "addr:street":"W High Ave",
    "iso:country":"US",
    "sg:address":"132 W High Ave",
    "sg:city":"High Point",
    "sg:classifiers":[
        {
            "category":"Shopping",
            "subcategory":"Hobbies, Toys, & Games",
            "type":"Retail Goods"
        }
    ],
    "sg:phone":"+1 336 454 2308",
    "sg:postcode":"27260",
    "sg:province":"NC",
    "wof:name":"GMoodieville",
    "wof:placetype":"venue"
},
  "geometry": {"coordinates":[-80.00756199999999,35.956538],"type":"Point"}
}