{
  "type": "Feature",
  "properties": {
    "iso:country":"US",
    "sg:address":"432 W Holding Ave",
    "sg:city":"Wake Forest",
    "sg:classifiers":[
        {
            "category":"Retail",
            "subcategory":"Auto Repair",
            "type":"Services"
        }
    ],
    "sg:phone":"+1 919 414 4062",
    "sg:postcode":"27587",
    "sg:province":"NC",
    "sg:tags":[
        "automobile",
        "restoration",
        "classic"
    ],
    "wof:name":"Broadway Automotive Rstrtn",
    "wof:placetype":"venue"
},
  "geometry": {"coordinates":[-78.51759300000001,35.972229],"type":"Point"}
}