{
  "type": "Feature",
  "properties": {
    "addr:full":"10804 September Ct Raleigh NC 27614",
    "addr:housenumber":"10804",
    "addr:postcode":"27614",
    "addr:street":"September Ct",
    "iso:country":"US",
    "sg:address":"10804 September Ct",
    "sg:city":"Raleigh",
    "sg:classifiers":[
        {
            "category":"Manufacturing",
            "subcategory":"Chemicals & Compounds",
            "type":"Manufacturing & Wholesale Goods"
        }
    ],
    "sg:phone":"+1 919 870 0964",
    "sg:postcode":"27614",
    "sg:province":"NC",
    "sg:tags":[
        "plastic"
    ],
    "wof:name":"Triangle Polymers Inc",
    "wof:placetype":"venue"
},
  "geometry": {"coordinates":[-78.590729,35.920771],"type":"Point"}
}