{
  "type": "Feature",
  "properties": {
    "addr:full":"629 Monroe St Eden NC 27288",
    "addr:housenumber":"629",
    "addr:postcode":"27288",
    "addr:street":"Monroe St",
    "iso:country":"US",
    "sg:address":"629 Monroe St",
    "sg:city":"Eden",
    "sg:classifiers":[
        {
            "category":"Shopping",
            "subcategory":"Department Store",
            "type":"Retail Goods"
        }
    ],
    "sg:phone":"+1 336 627 5655",
    "sg:postcode":"27288",
    "sg:province":"NC",
    "wof:name":"Home Supply",
    "wof:placetype":"venue"
},
  "geometry": {"coordinates":[-79.764723,36.491747],"type":"Point"}
}