{
  "type": "Feature",
  "properties": {
    "iso:country":"US",
    "sg:address":"111 Tweed Pl",
    "sg:city":"Chapel Hill",
    "sg:classifiers":[
        {
            "category":"Professional",
            "subcategory":"Business Services",
            "type":"Services"
        }
    ],
    "sg:phone":"+1   ",
    "sg:postcode":"27517",
    "sg:province":"NC",
    "wof:name":"Lucas Enterprises Inc",
    "wof:placetype":"venue"
},
  "geometry": {"coordinates":[-79.00036,35.920495],"type":"Point"}
}