{
  "type": "Feature",
  "properties": {
    "addr:full":"1034 Cloverleaf Plz Kannapolis NC 28083",
    "addr:housenumber":"1034",
    "addr:postcode":"28083",
    "addr:street":"Cloverleaf Plz",
    "iso:country":"US",
    "sg:address":"1034 Cloverleaf Plz",
    "sg:city":"Kannapolis",
    "sg:classifiers":[
        {
            "category":"Manufacturing",
            "subcategory":"Tools & Machinery",
            "type":"Manufacturing & Wholesale Goods"
        },
        {
            "category":"Home & Garden",
            "subcategory":"Hardware",
            "type":"Retail Goods"
        }
    ],
    "sg:phone":"+1 704 723 4004",
    "sg:postcode":"28083",
    "sg:province":"NC",
    "sg:tags":[
        "store"
    ],
    "sg:website":"http://www.harborfreight.com",
    "wof:name":"Harbor Freight Tools Usa Inc",
    "wof:placetype":"venue"
},
  "geometry": {"coordinates":[-80.60818999999999,35.450584],"type":"Point"}
}