{
  "type": "Feature",
  "properties": {
    "iso:country":"US",
    "sg:address":"1139 Ingle Houser Rd",
    "sg:city":"Lincolnton",
    "sg:classifiers":[
        {
            "category":"Food & Beverages",
            "subcategory":"Groceries & Convenience Stores",
            "type":"Retail Goods"
        }
    ],
    "sg:phone":"+1 704 732 6007",
    "sg:postcode":"28092",
    "sg:province":"NC",
    "wof:name":"Ingles Graving Landscaping",
    "wof:placetype":"venue"
},
  "geometry": {"coordinates":[-81.287633,35.445142],"type":"Point"}
}