{
  "type": "Feature",
  "properties": {
    "iso:country":"US",
    "sg:address":"315 Brogden St",
    "sg:city":"Dudley",
    "sg:classifiers":[
        {
            "category":"Retail",
            "subcategory":"Auto Repair",
            "type":"Services"
        }
    ],
    "sg:phone":"+1   ",
    "sg:postcode":"28333",
    "sg:province":"NC",
    "sg:tags":[
        "body"
    ],
    "wof:name":"Exum Auto Paint & Bodywork",
    "wof:placetype":"venue"
},
  "geometry": {"coordinates":[-78.03330699999999,35.297384],"type":"Point"}
}