{
  "type": "Feature",
  "properties": {
    "addr:full":"18405 Statesville Rd Cornelius NC 28031",
    "addr:housenumber":"18405",
    "addr:postcode":"28031",
    "addr:street":"Statesville Rd",
    "iso:country":"US",
    "sg:address":"18405 Statesville Rd",
    "sg:city":"Cornelius",
    "sg:classifiers":[
        {
            "category":"Autos & Motor Vehicles",
            "subcategory":"Fuel & Gas Station",
            "type":"Retail Goods"
        }
    ],
    "sg:phone":"+1 704 894 9596",
    "sg:postcode":"28031",
    "sg:province":"NC",
    "sg:tags":[
        "station",
        "gasoline"
    ],
    "wof:name":"Cornelius Amoco",
    "wof:placetype":"venue"
},
  "geometry": {"coordinates":[-80.87222199999999,35.467136],"type":"Point"}
}