{
  "type": "Feature",
  "properties": {
    "iso:country":"US",
    "sg:address":"6207 Nile Pl",
    "sg:city":"Greensboro",
    "sg:classifiers":[
        {
            "category":"Professional",
            "type":"Services"
        }
    ],
    "sg:phone":"+1 336 299 0510",
    "sg:postcode":"27409",
    "sg:province":"NC",
    "wof:name":"Dristi Inc",
    "wof:placetype":"venue"
},
  "geometry": {"coordinates":[-79.90556100000001,36.072675],"type":"Point"}
}