{
  "type": "Feature",
  "properties": {
    "addr:full":"1808 S Miami Blvd Durham NC 27703",
    "addr:housenumber":"1808",
    "addr:postcode":"27703",
    "addr:street":"S Miami Blvd",
    "iso:country":"US",
    "sg:address":"1808 S Miami Blvd",
    "sg:city":"Durham",
    "sg:classifiers":[
        {
            "category":"Restaurant",
            "type":"Food & Drink"
        }
    ],
    "sg:menulink":"http://www.allmenus.com/nc/oak-grove/182225-wendys/menu/",
    "sg:phone":"+1 919 957 4887",
    "sg:postcode":"27703",
    "sg:province":"NC",
    "sg:tags":[
        "burger",
        "american",
        "soup"
    ],
    "wof:name":"Wendy's",
    "wof:placetype":"venue"
},
  "geometry": {"coordinates":[-78.83801,35.945105],"type":"Point"}
}