{
  "type": "Feature",
  "properties": {
    "iso:country":"US",
    "sg:address":"3025 Randleman Rd",
    "sg:city":"Greensboro",
    "sg:classifiers":[
        {
            "category":"Building & Trades",
            "subcategory":"Electrical",
            "type":"Services"
        },
        {
            "category":"Wholesale",
            "subcategory":"Electrical",
            "type":"Manufacturing & Wholesale Goods"
        }
    ],
    "sg:phone":"+1 336 273 0859",
    "sg:postcode":"27406",
    "sg:province":"NC",
    "sg:tags":[
        "burglar",
        "fire",
        "alarm",
        "system",
        "contractor",
        "burglary",
        "security"
    ],
    "sg:website":"www.tsfire.com",
    "wof:name":"T & S Fire and Security Inc",
    "wof:placetype":"venue"
},
  "geometry": {"coordinates":[-79.804406,36.013611],"type":"Point"}
}