{
  "type": "Feature",
  "properties": {
    "iso:country":"US",
    "sg:address":"1676 Hannah Branch Rd",
    "sg:city":"Burnsville",
    "sg:classifiers":[
        {
            "category":"Retail",
            "subcategory":"Repair Shop",
            "type":"Services"
        }
    ],
    "sg:phone":"+1   ",
    "sg:postcode":"28714",
    "sg:province":"NC",
    "wof:name":"Williams Piano Tuning & Repair",
    "wof:placetype":"venue"
},
  "geometry": {"coordinates":[-82.180667,35.818463],"type":"Point"}
}