{
  "type": "Feature",
  "properties": {
    "iso:country":"US",
    "sg:address":"190 Beaman Rd",
    "sg:city":"Troy",
    "sg:classifiers":[
        {
            "category":"Farming",
            "subcategory":"Farm",
            "type":"Manufacturing & Wholesale Goods"
        }
    ],
    "sg:phone":"+1 910 571 0709",
    "sg:postcode":"27371",
    "sg:province":"NC",
    "wof:name":"Vang's Farm",
    "wof:placetype":"venue"
},
  "geometry": {"coordinates":[-79.91442499999999,35.410975],"type":"Point"}
}