{
  "type": "Feature",
  "properties": {
    "iso:country":"US",
    "sg:address":"2329 E W T Harris Blvd",
    "sg:city":"Charlotte",
    "sg:classifiers":[
        {
            "category":"Health Services",
            "subcategory":"Clinic",
            "type":"Services"
        }
    ],
    "sg:phone":"+1 704 549 1700",
    "sg:postcode":"28213",
    "sg:province":"NC",
    "sg:tags":[
        "home"
    ],
    "sg:website":"www.bayada.com",
    "wof:name":"Bayada Nurses",
    "wof:placetype":"venue"
},
  "geometry": {"coordinates":[-80.72751100000001,35.276625],"type":"Point"}
}