{
  "type": "Feature",
  "properties": {
    "addr:full":"2042 Chapel Hill Rd Burlington NC 27215",
    "addr:housenumber":"2042",
    "addr:postcode":"27215",
    "addr:street":"Chapel Hill Rd",
    "iso:country":"US",
    "sg:address":"2042 Chapel Hill Rd",
    "sg:city":"Burlington",
    "sg:classifiers":[
        {
            "category":"Restaurant",
            "type":"Food & Drink"
        }
    ],
    "sg:phone":"+1 336 227 9817",
    "sg:postcode":"27215",
    "sg:province":"NC",
    "sg:tags":[
        "caterer"
    ],
    "wof:name":"Four Cooks' Delight",
    "wof:placetype":"venue"
},
  "geometry": {"coordinates":[-79.42991000000001,36.067724],"type":"Point"}
}