{
  "type": "Feature",
  "properties": {
    "iso:country":"US",
    "sg:address":"6383 Burnt Poplar Rd",
    "sg:city":"Greensboro",
    "sg:classifiers":[
        {
            "category":"Autos & Motor Vehicles",
            "subcategory":"Automobile Sales",
            "type":"Retail Goods"
        }
    ],
    "sg:phone":"+1 336 851 1600",
    "sg:postcode":"27409",
    "sg:province":"NC",
    "sg:tags":[
        "truck"
    ],
    "sg:website":"www.selectrucksofgreensboro.com",
    "wof:name":"Selectrucks Of Greensboro",
    "wof:placetype":"venue"
},
  "geometry": {"coordinates":[-79.938271,36.075567],"type":"Point"}
}