{
  "type": "Feature",
  "properties": {
    "iso:country":"US",
    "sg:address":"3020 Main St",
    "sg:city":"Walkertown",
    "sg:classifiers":[
        {
            "category":"Organizations",
            "subcategory":"Religious Organization",
            "type":"Services"
        }
    ],
    "sg:phone":"+1 336 595 2114",
    "sg:postcode":"27051",
    "sg:province":"NC",
    "sg:tags":[
        "church"
    ],
    "wof:name":"Love's United Methodist Church",
    "wof:placetype":"venue"
},
  "geometry": {"coordinates":[-80.153046,36.173418],"type":"Point"}
}