{
  "type": "Feature",
  "properties": {
    "addr:full":"8580 Orchard Loop Rd Leland NC 28451",
    "addr:housenumber":"8580",
    "addr:postcode":"28451",
    "addr:street":"Orchard Loop Rd",
    "iso:country":"US",
    "sg:address":"8580 Orchard Loop Rd",
    "sg:city":"Leland",
    "sg:classifiers":[
        {
            "category":"Building & Trades",
            "subcategory":"Construction",
            "type":"Services"
        }
    ],
    "sg:phone":"+1 910 383 0040",
    "sg:postcode":"28451",
    "sg:province":"NC",
    "sg:tags":[
        "house"
    ],
    "wof:name":"Sunrise Homes",
    "wof:placetype":"venue"
},
  "geometry": {"coordinates":[-78.05664400000001,34.21965],"type":"Point"}
}