{
  "type": "Feature",
  "properties": {
    "iso:country":"US",
    "sg:address":"3701 Clemmons Rd",
    "sg:city":"Clemmons",
    "sg:classifiers":[
        {
            "category":"Banks & Credit Unions",
            "subcategory":"Bank",
            "type":"Services"
        }
    ],
    "sg:phone":"+1 336 766 0581",
    "sg:postcode":"27012",
    "sg:province":"NC",
    "sg:tags":[
        "savings",
        "loan",
        "association"
    ],
    "wof:name":"Piedmont Federal S & L Assn",
    "wof:placetype":"venue"
},
  "geometry": {"coordinates":[-80.382007,36.021519],"type":"Point"}
}