{
  "type": "Feature",
  "properties": {
    "addr:full":"1121 Georgia Rd Franklin NC 28734",
    "addr:housenumber":"1121",
    "addr:postcode":"nc 28734",
    "addr:street":"Georgia Rd",
    "iso:country":"US",
    "sg:address":"1121 Georgia Rd",
    "sg:city":"Franklin",
    "sg:classifiers":[
        {
            "category":"Building & Trades",
            "subcategory":"Equipment Rental",
            "type":"Services"
        }
    ],
    "sg:phone":"+1 828 524 2100",
    "sg:postcode":"28734",
    "sg:province":"NC",
    "sg:tags":[
        "toilet"
    ],
    "wof:name":"Tim Bates Septic Tank",
    "wof:placetype":"venue"
},
  "geometry": {"coordinates":[-83.38452599999999,35.097087],"type":"Point"}
}