{
  "type": "Feature",
  "properties": {
    "iso:country":"US",
    "sg:address":"224 Warrensville Dr",
    "sg:city":"Warrensville",
    "sg:classifiers":[
        {
            "category":"Place Of Worship",
            "subcategory":"Church",
            "type":"Public Place"
        },
        {
            "category":"Place Of Worship",
            "type":"Public Place"
        }
    ],
    "sg:phone":"+1 336 384 2840",
    "sg:postcode":"28693",
    "sg:province":"NC",
    "sg:tags":[
        "churches-seventh-day",
        "adventist",
        "christian",
        "churches-advent"
    ],
    "sg:website":"http://www.adventist.org",
    "wof:name":"Warrensville 7th Day Adventist Church",
    "wof:placetype":"venue"
},
  "geometry": {"coordinates":[-81.515289,36.459438],"type":"Point"}
}