{
  "type": "Feature",
  "properties": {
    "iso:country":"US",
    "sg:address":"6078 Oxford School Rd",
    "sg:city":"Claremont",
    "sg:classifiers":[
        {
            "category":"Wholesale",
            "subcategory":"Stationery",
            "type":"Manufacturing & Wholesale Goods"
        }
    ],
    "sg:phone":"+1 828 459 0250",
    "sg:postcode":"28610",
    "sg:province":"NC",
    "sg:tags":[
        "paper"
    ],
    "wof:name":"Inter Continental Corporation",
    "wof:placetype":"venue"
},
  "geometry": {"coordinates":[-81.15422100000001,35.773661],"type":"Point"}
}