{
  "type": "Feature",
  "properties": {
    "addr:full":"104 Rosewood Ln Rutherfordton NC 28117",
    "addr:housenumber":"104",
    "addr:postcode":"28117",
    "addr:street":"Rosewood Ln",
    "iso:country":"US",
    "sg:address":"104 Rosewood Ln",
    "sg:city":"Rutherfordton",
    "sg:classifiers":[
        {
            "category":"Professional",
            "subcategory":"Business Services",
            "type":"Services"
        }
    ],
    "sg:phone":"+1   ",
    "sg:postcode":"28117",
    "sg:province":"NC",
    "wof:name":"Ardito Enterprises Inc",
    "wof:placetype":"venue"
},
  "geometry": {"coordinates":[-80.846121,35.594263],"type":"Point"}
}