{
  "type": "Feature",
  "properties": {
    "iso:country":"US",
    "sg:address":"3766 Buffalo Ford Rd",
    "sg:city":"Asheboro",
    "sg:classifiers":[
        {
            "category":"Real Estate",
            "subcategory":"Real Estate Operator",
            "type":"Services"
        }
    ],
    "sg:phone":"+1 336 879 3593",
    "sg:postcode":"27205",
    "sg:province":"NC",
    "sg:tags":[
        "mobile",
        "home",
        "site",
        "community"
    ],
    "wof:name":"Chilton's Mobile Home Park",
    "wof:placetype":"venue"
},
  "geometry": {"coordinates":[-79.710429,35.6788],"type":"Point"}
}