{
  "type": "Feature",
  "properties": {
    "iso:country":"US",
    "sg:address":"303 Queens Rd",
    "sg:city":"Newport",
    "sg:classifiers":[
        {
            "category":"Organizations",
            "subcategory":"Non-profit Organization",
            "type":"Services"
        }
    ],
    "sg:phone":"+1 252 223 1630",
    "sg:postcode":"28539",
    "sg:province":"NC",
    "sg:tags":[
        "action",
        "agency",
        "community"
    ],
    "sg:website":"www.coastalcommunityaction.com",
    "wof:name":"Coastal Community Action Inc",
    "wof:placetype":"venue"
},
  "geometry": {"coordinates":[-77.18117100000001,34.708327],"type":"Point"}
}