{
  "type": "Feature",
  "properties": {
    "iso:country":"US",
    "sg:address":"653 S Key St",
    "sg:city":"Pilot Mountain",
    "sg:classifiers":[
        {
            "category":"Banks & Credit Unions",
            "subcategory":"Bank",
            "type":"Services"
        }
    ],
    "sg:phone":"+1 336 368 3656",
    "sg:postcode":"27041",
    "sg:province":"NC",
    "sg:tags":[
        "loan"
    ],
    "wof:name":"Foothill Credit Corp",
    "wof:placetype":"venue"
},
  "geometry": {"coordinates":[-80.479488,36.378989],"type":"Point"}
}