{
  "type": "Feature",
  "properties": {
    "iso:country":"US",
    "sg:address":"149 Vale Rd",
    "sg:city":"Newland",
    "sg:phone":"+1 828 733 3731",
    "sg:postcode":"28657",
    "sg:province":"NC",
    "sg:tags":[
        "product",
        "petroleum"
    ],
    "wof:name":"Hcn Petroleum Eqp Sls & Svcs",
    "wof:placetype":"venue"
},
  "geometry": {"coordinates":[-81.929593,36.095094],"type":"Point"}
}