{
  "type": "Feature",
  "properties": {
    "addr:full":"47 Merrimon Pl Asheville NC 28801",
    "addr:housenumber":"47",
    "addr:postcode":"28801",
    "addr:street":"Merrimon Pl",
    "iso:country":"US",
    "sg:address":"47 Merrimon Pl",
    "sg:city":"Asheville",
    "sg:classifiers":[
        {
            "category":"Organizations",
            "subcategory":"Non-profit Organization",
            "type":"Services"
        }
    ],
    "sg:phone":"+1   ",
    "sg:postcode":"28801",
    "sg:province":"NC",
    "sg:tags":[
        "social"
    ],
    "wof:name":"Ayudas 1",
    "wof:placetype":"venue"
},
  "geometry": {"coordinates":[-82.55056,35.602266],"type":"Point"}
}