{
  "type": "Feature",
  "properties": {
    "addr:full":"426 Crompton St Charlotte NC 28273",
    "addr:housenumber":"426",
    "addr:postcode":"28273",
    "addr:street":"Crompton St",
    "iso:country":"US",
    "sg:address":"426 Crompton St",
    "sg:city":"Charlotte",
    "sg:classifiers":[
        {
            "category":"Wholesale",
            "subcategory":"Machinery & Supplies",
            "type":"Manufacturing & Wholesale Goods"
        }
    ],
    "sg:phone":"+1 704 588 5114",
    "sg:postcode":"28273",
    "sg:province":"NC",
    "sg:tags":[
        "equipment",
        "hydraulic"
    ],
    "wof:name":"Indesco Inc",
    "wof:placetype":"venue"
},
  "geometry": {"coordinates":[-80.916147,35.117249],"type":"Point"}
}