{
  "type": "Feature",
  "properties": {
    "iso:country":"US",
    "sg:address":"8111 Concord Mills Blvd Ste 621",
    "sg:city":"Concord",
    "sg:classifiers":[
        {
            "category":"Shopping",
            "subcategory":"Clothing, Apparel, & Fashions",
            "type":"Retail Goods"
        }
    ],
    "sg:phone":"+1 704 979 0990",
    "sg:postcode":"28027",
    "sg:province":"NC",
    "sg:tags":[
        "clothing",
        "store"
    ],
    "sg:website":"http://www.oldnavy.com",
    "wof:name":"Old Navy",
    "wof:placetype":"venue"
},
  "geometry": {"coordinates":[-80.71838099999999,35.371445],"type":"Point"}
}