{
  "type": "Feature",
  "properties": {
    "iso:country":"US",
    "sg:address":"515 Saint Marys St",
    "sg:city":"Raleigh",
    "sg:classifiers":[
        {
            "category":"Real Estate",
            "subcategory":"Architect",
            "type":"Services"
        }
    ],
    "sg:phone":"+1 919 828 2301",
    "sg:postcode":"27605",
    "sg:province":"NC",
    "sg:tags":[
        "designer",
        "architectural"
    ],
    "wof:name":"H H Architecture Pa",
    "wof:placetype":"venue"
},
  "geometry": {"coordinates":[-78.650955,35.787352],"type":"Point"}
}