{
  "type": "Feature",
  "properties": {
    "iso:country":"US",
    "sg:address":"1075 Sweeten Creek Rd",
    "sg:city":"Asheville",
    "sg:classifiers":[
        {
            "category":"Retail",
            "subcategory":"Repair Shop",
            "type":"Services"
        }
    ],
    "sg:phone":"+1 828 274 3787",
    "sg:postcode":"28803",
    "sg:province":"NC",
    "sg:tags":[
        "equipment",
        "electronic",
        "supply"
    ],
    "wof:name":"Robinson Electronics",
    "wof:placetype":"venue"
},
  "geometry": {"coordinates":[-82.521565,35.544017],"type":"Point"}
}