{
  "type": "Feature",
  "properties": {
    "addr:full":"2406 S 17th St Wilmington NC 28401",
    "addr:housenumber":"2406",
    "addr:postcode":"28401",
    "addr:street":"S 17Th St",
    "iso:country":"US",
    "sg:address":"2406 S 17th St",
    "sg:city":"Wilmington",
    "sg:classifiers":[
        {
            "category":"Insurance",
            "subcategory":"Hazard Insurance",
            "type":"Services"
        },
        {
            "category":"Insurance",
            "subcategory":"Insurance Agent",
            "type":"Services"
        },
        {
            "category":"Insurance",
            "subcategory":"Life Insurance",
            "type":"Services"
        },
        {
            "category":"Insurance",
            "subcategory":"Title Insurance",
            "type":"Services"
        }
    ],
    "sg:phone":"+1 910 791 5447",
    "sg:postcode":"28401",
    "sg:province":"NC",
    "sg:tags":[
        "auto",
        "homeowner"
    ],
    "sg:website":"http://www.nationwide.com/agent/Wilmington-NORTH-CAROLINA-insurance-agent/dan-parham/office.html",
    "wof:name":"Daniel R Parham - Nationwide Insurance",
    "wof:placetype":"venue"
},
  "geometry": {"coordinates":[-77.922042,34.198538],"type":"Point"}
}