{
  "type": "Feature",
  "properties": {
    "iso:country":"US",
    "sg:address":"1000 N Jefferson St",
    "sg:city":"Goldsboro",
    "sg:classifiers":[
        {
            "category":"Organizations",
            "subcategory":"Religious Organization",
            "type":"Services"
        }
    ],
    "sg:phone":"+1 919 734 5033",
    "sg:postcode":"27530",
    "sg:province":"NC",
    "sg:tags":[
        "church"
    ],
    "sg:website":"www.saintmarygoldsboro.org",
    "wof:name":"St Mary's Catholic Church",
    "wof:placetype":"venue"
},
  "geometry": {"coordinates":[-77.969894,35.386415],"type":"Point"}
}