{
  "type": "Feature",
  "properties": {
    "addr:full":"40 Westgate Pkwy Asheville NC 28806",
    "addr:housenumber":"40",
    "addr:postcode":"28806",
    "addr:street":"Westgate Pkwy",
    "iso:country":"US",
    "sg:address":"40 Westgate Pkwy",
    "sg:city":"Asheville",
    "sg:classifiers":[
        {
            "category":"Organizations",
            "subcategory":"Non-profit Organization",
            "type":"Services"
        }
    ],
    "sg:phone":"+1 828 254 8803",
    "sg:postcode":"28806",
    "sg:province":"NC",
    "wof:name":"Western Economic Dev Org",
    "wof:placetype":"venue"
},
  "geometry": {"coordinates":[-82.57522899999999,35.593474],"type":"Point"}
}