{
  "type": "Feature",
  "properties": {
    "addr:full":"4305 Shady Ln Kitty Hawk NC 27949",
    "addr:housenumber":"4305",
    "addr:postcode":"27949",
    "addr:street":"Shady Ln",
    "iso:country":"US",
    "sg:address":"4305 Shady Ln",
    "sg:city":"Kitty Hawk",
    "sg:classifiers":[
        {
            "category":"Building & Trades",
            "subcategory":"Construction",
            "type":"Services"
        }
    ],
    "sg:phone":"+1 252 255 1967",
    "sg:postcode":"27949",
    "sg:province":"NC",
    "sg:tags":[
        "builder",
        "repairer",
        "chimney"
    ],
    "wof:name":"Buchanan Chimney & Fireplace",
    "wof:placetype":"venue"
},
  "geometry": {"coordinates":[-75.70629599999999,36.07874],"type":"Point"}
}