{
  "type": "Feature",
  "properties": {
    "addr:full":"830 Shadowmoss Dr Fayetteville NC 28312",
    "addr:housenumber":"830",
    "addr:postcode":"28312",
    "addr:street":"Shadowmoss Dr",
    "iso:country":"US",
    "sg:address":"830 Shadowmoss Dr",
    "sg:city":"Fayetteville",
    "sg:classifiers":[
        {
            "category":"Professional",
            "type":"Services"
        }
    ],
    "sg:phone":"+1   ",
    "sg:postcode":"28312",
    "sg:province":"NC",
    "wof:name":"Atv Services",
    "wof:placetype":"venue"
},
  "geometry": {"coordinates":[-78.777519,35.064478],"type":"Point"}
}