{
  "type": "Feature",
  "properties": {
    "addr:full":"1605 Old Oxford Rd Chapel Hill NC 27514",
    "addr:housenumber":"1605",
    "addr:postcode":"27514",
    "addr:street":"Old Oxford Rd",
    "iso:country":"US",
    "sg:address":"1605 Old Oxford Rd",
    "sg:city":"Chapel Hill",
    "sg:classifiers":[
        {
            "category":"Organizations",
            "subcategory":"Membership Organization",
            "type":"Services"
        }
    ],
    "sg:phone":"+1 919 968 0303",
    "sg:postcode":"27514",
    "sg:province":"NC",
    "wof:name":"Tar Heel Aquatic Team",
    "wof:placetype":"venue"
},
  "geometry": {"coordinates":[-79.03150599999999,35.936554],"type":"Point"}
}