{
  "type": "Feature",
  "properties": {
    "addr:full":"624 W Palmer St Franklin NC 28734",
    "addr:housenumber":"624",
    "addr:postcode":"nc 28734",
    "addr:street":"W Palmer St",
    "iso:country":"US",
    "sg:address":"624 W Palmer St",
    "sg:city":"Franklin",
    "sg:classifiers":[
        {
            "category":"Health Services",
            "subcategory":"Doctor",
            "type":"Services"
        }
    ],
    "sg:phone":"+1 828 524 6111",
    "sg:postcode":"28734",
    "sg:province":"NC",
    "sg:tags":[
        "dentist"
    ],
    "wof:name":"David R Silverstein DDS PA",
    "wof:placetype":"venue"
},
  "geometry": {"coordinates":[-83.39546799999999,35.177469],"type":"Point"}
}