{
  "type": "Feature",
  "properties": {
    "iso:country":"US",
    "sg:address":"303 S Shore Dr",
    "sg:city":"Jacksonville",
    "sg:classifiers":[
        {
            "category":"Social Services",
            "subcategory":"Adult Care",
            "type":"Services"
        }
    ],
    "sg:phone":"+1 910 938 0670",
    "sg:postcode":"28540",
    "sg:province":"NC",
    "sg:tags":[
        "home",
        "group"
    ],
    "wof:name":"Martha's Group Home Inc",
    "wof:placetype":"venue"
},
  "geometry": {"coordinates":[-77.41314300000001,34.766439],"type":"Point"}
}