{
  "type": "Feature",
  "properties": {
    "addr:full":"154 Valley Oaks Dr Advance NC 27006",
    "addr:housenumber":"154",
    "addr:postcode":"27006",
    "addr:street":"Valley Oaks Dr",
    "iso:country":"US",
    "sg:address":"154 Valley Oaks Dr",
    "sg:city":"Advance",
    "sg:classifiers":[
        {
            "category":"Professional",
            "type":"Services"
        }
    ],
    "sg:phone":"+1 336 998 0350",
    "sg:postcode":"27006",
    "sg:province":"NC",
    "wof:name":"Pudding Ridge Limited",
    "wof:placetype":"venue"
},
  "geometry": {"coordinates":[-80.458456,36.03505],"type":"Point"}
}