{
  "type": "Feature",
  "properties": {
    "iso:country":"US",
    "sg:address":"1514 W D St",
    "sg:city":"North Wilkesboro",
    "sg:classifiers":[
        {
            "category":"Home & Garden",
            "subcategory":"Hardware",
            "type":"Retail Goods"
        }
    ],
    "sg:phone":"+1 336 838 2762",
    "sg:postcode":"28659",
    "sg:province":"NC",
    "wof:name":"Church Hardware Co",
    "wof:placetype":"venue"
},
  "geometry": {"coordinates":[-81.17045400000001,36.155106],"type":"Point"}
}