{
  "type": "Feature",
  "properties": {
    "iso:country":"US",
    "sg:address":"36 Hospital Dr",
    "sg:city":"Spruce Pine",
    "sg:classifiers":[
        {
            "category":"Health Services",
            "subcategory":"Doctor",
            "type":"Services"
        }
    ],
    "sg:phone":"+1 828 765 5888",
    "sg:postcode":"28777",
    "sg:province":"NC",
    "sg:tags":[
        "physician",
        "surgeon"
    ],
    "wof:name":"Boone Regional Ear Nose",
    "wof:placetype":"venue"
},
  "geometry": {"coordinates":[-82.063804,35.910797],"type":"Point"}
}