{
  "type": "Feature",
  "properties": {
    "iso:country":"US",
    "sg:address":"1002 Instrument Dr",
    "sg:city":"Rocky Mount",
    "sg:classifiers":[
        {
            "category":"Building & Trades",
            "subcategory":"Construction",
            "type":"Services"
        }
    ],
    "sg:phone":"+1 252 985 2021",
    "sg:postcode":"27804",
    "sg:province":"NC",
    "sg:tags":[
        "maintenance",
        "contractor"
    ],
    "wof:name":"Martin Industrial Maintenance",
    "wof:placetype":"venue"
},
  "geometry": {"coordinates":[-77.787806,36.006893],"type":"Point"}
}