{
  "type": "Feature",
  "properties": {
    "addr:full":"1205 N William St Goldsboro NC 27530",
    "addr:housenumber":"1205",
    "addr:postcode":"27530",
    "addr:street":"N William St",
    "iso:country":"US",
    "sg:address":"1205 N William St",
    "sg:city":"Goldsboro",
    "sg:classifiers":[
        {
            "category":"Restaurant",
            "type":"Food & Drink"
        }
    ],
    "sg:phone":"+1 919 734 0711",
    "sg:postcode":"27530",
    "sg:province":"NC",
    "wof:name":"Scott's Sauce Co Inc",
    "wof:placetype":"venue"
},
  "geometry": {"coordinates":[-77.986896,35.398326],"type":"Point"}
}