{
  "type": "Feature",
  "properties": {
    "addr:full":"101 W Poplar Ave Carrboro NC 27510",
    "addr:housenumber":"101",
    "addr:postcode":"27510",
    "addr:street":"W Poplar Ave",
    "iso:country":"US",
    "sg:address":"101 W Poplar Ave",
    "sg:city":"Carrboro",
    "sg:classifiers":[
        {
            "category":"Building & Trades",
            "subcategory":"Construction",
            "type":"Services"
        }
    ],
    "sg:phone":"+1 919 942 0322",
    "sg:postcode":"27510",
    "sg:province":"NC",
    "sg:tags":[
        "housing"
    ],
    "wof:name":"George Cole Builder",
    "wof:placetype":"venue"
},
  "geometry": {"coordinates":[-79.078856,35.913142],"type":"Point"}
}