{
  "type": "Feature",
  "properties": {
    "iso:country":"US",
    "sg:address":"1508 Old Milburnie Rd",
    "sg:city":"Raleigh",
    "sg:classifiers":[
        {
            "category":"Building & Trades",
            "subcategory":"Construction",
            "type":"Services"
        }
    ],
    "sg:phone":"+1 919 266 4155",
    "sg:postcode":"27604",
    "sg:province":"NC",
    "sg:tags":[
        "carpentry",
        "contractor"
    ],
    "wof:name":"Danny Duncan & Assoc Inc",
    "wof:placetype":"venue"
},
  "geometry": {"coordinates":[-78.529484,35.806112],"type":"Point"}
}