{
  "type": "Feature",
  "properties": {
    "addr:full":"10171 Foreman Ranch Rd Oakboro NC 28129",
    "addr:housenumber":"10171",
    "addr:postcode":"28129",
    "addr:street":"Foreman Ranch Rd",
    "iso:country":"US",
    "sg:address":"10171 Foreman Ranch Rd",
    "sg:city":"Oakboro",
    "sg:classifiers":[
        {
            "category":"Recreation",
            "type":"Entertainment"
        }
    ],
    "sg:phone":"+1   ",
    "sg:postcode":"28129",
    "sg:province":"NC",
    "wof:name":"Foreman Stables",
    "wof:placetype":"venue"
},
  "geometry": {"coordinates":[-80.263451,35.211297],"type":"Point"}
}