{
  "type": "Feature",
  "properties": {
    "iso:country":"US",
    "sg:address":"211 W 2nd Ave",
    "sg:city":"Gastonia",
    "sg:classifiers":[
        {
            "category":"Shopping",
            "type":"Retail Goods"
        }
    ],
    "sg:phone":"+1 704 865 8856",
    "sg:postcode":"28052",
    "sg:province":"NC",
    "sg:tags":[
        "used",
        "merchandise"
    ],
    "wof:name":"Frame Gallery Of Gastonia Inc",
    "wof:placetype":"venue"
},
  "geometry": {"coordinates":[-81.185531,35.260558],"type":"Point"}
}