{
  "type": "Feature",
  "properties": {
    "addr:full":"600 Auto Park Blvd Cary NC 27511",
    "addr:housenumber":"600",
    "addr:postcode":"27511",
    "addr:street":"Auto Park Blvd",
    "iso:country":"US",
    "sg:address":"600 Auto Park Blvd",
    "sg:city":"Cary",
    "sg:classifiers":[
        {
            "category":"Autos & Motor Vehicles",
            "subcategory":"Automobile Sales",
            "type":"Retail Goods"
        }
    ],
    "sg:phone":"+1 919 460 3800",
    "sg:postcode":"27511",
    "sg:province":"NC",
    "sg:tags":[
        "car"
    ],
    "sg:website":"www.leithaudi.com",
    "wof:name":"Leith Audi",
    "wof:placetype":"venue"
},
  "geometry": {"coordinates":[-78.81529999999999,35.740799],"type":"Point"}
}