{
  "type": "Feature",
  "properties": {
    "addr:full":"655 Winslow St Fayetteville NC 28306",
    "addr:housenumber":"655",
    "addr:postcode":"28306",
    "addr:street":"Winslow St",
    "iso:country":"US",
    "sg:address":"655 Winslow St",
    "sg:city":"Fayetteville",
    "sg:classifiers":[
        {
            "category":"Railroad",
            "type":"Transportation"
        }
    ],
    "sg:phone":"+1 910 483 8309",
    "sg:postcode":"28306",
    "sg:province":"NC",
    "wof:name":"Aberdeen & Rockfish Railroad",
    "wof:placetype":"venue"
},
  "geometry": {"coordinates":[-78.889948,35.043542],"type":"Point"}
}