{
  "type": "Feature",
  "properties": {
    "addr:full":"668 S Oliver Dr Henderson NC 27537",
    "addr:housenumber":"668",
    "addr:postcode":"27537",
    "addr:street":"S Oliver Dr",
    "iso:country":"US",
    "sg:address":"668 S Oliver Dr",
    "sg:city":"Henderson",
    "sg:classifiers":[
        {
            "category":"Retail",
            "subcategory":"Repair Shop",
            "type":"Services"
        }
    ],
    "sg:phone":"+1 252 438 4087",
    "sg:postcode":"27537",
    "sg:province":"NC",
    "wof:name":"Virginia Crlina Communications",
    "wof:placetype":"venue"
},
  "geometry": {"coordinates":[-78.360524,36.347884],"type":"Point"}
}