{
  "type": "Feature",
  "properties": {
    "addr:full":"680 Parkwood Medical Park Elkin NC 28621",
    "addr:housenumber":"680",
    "addr:postcode":"28621",
    "iso:country":"US",
    "sg:address":"680 Parkwood Medical Park",
    "sg:city":"Elkin",
    "sg:classifiers":[
        {
            "category":"Health Services",
            "subcategory":"Podiatrist",
            "type":"Services"
        }
    ],
    "sg:phone":"+1 336 835 7676",
    "sg:postcode":"28621",
    "sg:province":"NC",
    "wof:name":"Pediatric Medicine and Surgery",
    "wof:placetype":"venue"
},
  "geometry": {"coordinates":[-80.838818,36.263849],"type":"Point"}
}