{
  "type": "Feature",
  "properties": {
    "iso:country":"US",
    "sg:address":"1065 Thompson St",
    "sg:city":"Pittsboro",
    "sg:classifiers":[
        {
            "category":"Building & Trades",
            "subcategory":"Plumbing",
            "type":"Services"
        }
    ],
    "sg:phone":"+1 919 542 3233",
    "sg:postcode":"27312",
    "sg:province":"NC",
    "sg:tags":[
        "plumbing",
        "contractor"
    ],
    "wof:name":"Midway Plumbing Inc",
    "wof:placetype":"venue"
},
  "geometry": {"coordinates":[-79.15836299999999,35.720588],"type":"Point"}
}