{
  "type": "Feature",
  "properties": {
    "iso:country":"US",
    "sg:address":"12159 Autumn Winds Ln",
    "sg:city":"Pineville",
    "sg:classifiers":[
        {
            "category":"Professional",
            "subcategory":"Detective & Security Services",
            "type":"Services"
        }
    ],
    "sg:phone":"+1 704 889 2759",
    "sg:postcode":"28134",
    "sg:province":"NC",
    "sg:tags":[
        "monitor",
        "install",
        "system"
    ],
    "wof:name":"Comfort Security Inc",
    "wof:placetype":"venue"
},
  "geometry": {"coordinates":[-80.878484,35.057574],"type":"Point"}
}