{
  "type": "Feature",
  "properties": {
    "iso:country":"US",
    "sg:address":"1115 Glenway Dr",
    "sg:city":"Statesville",
    "sg:classifiers":[
        {
            "category":"Restaurant",
            "type":"Food & Drink"
        }
    ],
    "sg:menulink":"http://www.allmenus.com/nc/statesville/85133-applebees/menu/",
    "sg:phone":"+1 704 838 0052",
    "sg:postcode":"28625",
    "sg:province":"NC",
    "sg:tags":[
        "burger",
        "american",
        "sandwich",
        "soup"
    ],
    "wof:name":"Applebee's",
    "wof:placetype":"venue"
},
  "geometry": {"coordinates":[-80.86965600000001,35.809124],"type":"Point"}
}