{
  "type": "Feature",
  "properties": {
    "iso:country":"US",
    "sg:address":"106 N Sterling St",
    "sg:city":"Morganton",
    "sg:classifiers":[
        {
            "category":"Retail",
            "subcategory":"Laundry & Dry Cleaning",
            "type":"Services"
        },
        {
            "category":"Shopping",
            "subcategory":"Clothing, Apparel, & Fashions",
            "type":"Retail Goods"
        }
    ],
    "sg:phone":"+1 828 433 4656",
    "sg:postcode":"28655",
    "sg:province":"NC",
    "sg:tags":[
        "alteration"
    ],
    "wof:name":"Vivian's Sewing Shop",
    "wof:placetype":"venue"
},
  "geometry": {"coordinates":[-81.68804900000001,35.745469],"type":"Point"}
}