{
  "type": "Feature",
  "properties": {
    "iso:country":"US",
    "sg:address":"640 State Rd 24 Bus",
    "sg:city":"Kenansville",
    "sg:classifiers":[
        {
            "category":"Farming",
            "subcategory":"Livestock Farm",
            "type":"Manufacturing & Wholesale Goods"
        }
    ],
    "sg:phone":"+1 910 296 1947",
    "sg:postcode":"28349",
    "sg:province":"NC",
    "sg:tags":[
        "feedlot",
        "hog",
        "or",
        "beef",
        "cattle"
    ],
    "wof:name":"J & J Stroud Farms",
    "wof:placetype":"venue"
},
  "geometry": {"coordinates":[-77.968873,34.958586],"type":"Point"}
}