{
  "type": "Feature",
  "properties": {
    "addr:full":"134 Salem Towne Ct Apex NC 27502",
    "addr:housenumber":"134",
    "addr:postcode":"27502",
    "addr:street":"Salem Towne Ct",
    "iso:country":"US",
    "sg:address":"134 Salem Towne Ct",
    "sg:city":"Apex",
    "sg:classifiers":[
        {
            "category":"Health Services",
            "subcategory":"Health Practitioner",
            "type":"Services"
        }
    ],
    "sg:phone":"+1 919 362 6551",
    "sg:postcode":"27502",
    "sg:province":"NC",
    "wof:name":"Knead For Life",
    "wof:placetype":"venue"
},
  "geometry": {"coordinates":[-78.84940899999999,35.738891],"type":"Point"}
}