{
  "type": "Feature",
  "properties": {
    "addr:full":"423 Mallard Dr Pineville NC 28134",
    "addr:housenumber":"423",
    "addr:postcode":"28134",
    "addr:street":"Mallard Dr",
    "iso:country":"US",
    "sg:address":"423 Mallard Dr",
    "sg:city":"Pineville",
    "sg:classifiers":[
        {
            "category":"Building & Trades",
            "subcategory":"Construction",
            "type":"Services"
        }
    ],
    "sg:phone":"+1 704 889 7655",
    "sg:postcode":"28134",
    "sg:province":"NC",
    "sg:tags":[
        "house",
        "c",
        "hanging",
        "contractor"
    ],
    "wof:name":"Bockus Restoration Inc",
    "wof:placetype":"venue"
},
  "geometry": {"coordinates":[-80.89588000000001,35.076013],"type":"Point"}
}