{
  "type": "Feature",
  "properties": {
    "iso:country":"US",
    "sg:address":"702 E Hill St",
    "sg:city":"Benson",
    "sg:classifiers":[
        {
            "category":"Social Services",
            "subcategory":"Child Care",
            "type":"Services"
        }
    ],
    "sg:phone":"+1   ",
    "sg:postcode":"27504",
    "sg:province":"NC",
    "sg:tags":[
        "day"
    ],
    "wof:name":"Kiddie Korner",
    "wof:placetype":"venue"
},
  "geometry": {"coordinates":[-78.54024200000001,35.379418],"type":"Point"}
}