{
  "type": "Feature",
  "properties": {
    "iso:country":"US",
    "sg:address":"327 Stepp Mill Rd",
    "sg:city":"Hendersonville",
    "sg:classifiers":[
        {
            "category":"Building & Trades",
            "subcategory":"Plumbing",
            "type":"Services"
        }
    ],
    "sg:phone":"+1 828 693 4787",
    "sg:postcode":"28792",
    "sg:province":"NC",
    "sg:tags":[
        "plumbing",
        "fruit",
        "tree",
        "orchard",
        "contractor"
    ],
    "wof:name":"Jackson Arthur Plumbing Co",
    "wof:placetype":"venue"
},
  "geometry": {"coordinates":[-82.35845500000001,35.346733],"type":"Point"}
}