{
  "type": "Feature",
  "properties": {
    "iso:country":"US",
    "sg:address":"831 Seigle Ave",
    "sg:city":"Charlotte",
    "sg:classifiers":[
        {
            "category":"Real Estate",
            "subcategory":"Real Estate Agent",
            "type":"Services"
        }
    ],
    "sg:phone":"+1 704 353 0985",
    "sg:postcode":"28204",
    "sg:province":"NC",
    "sg:tags":[
        "authorities",
        "housing"
    ],
    "sg:website":"www.cha-nc.org",
    "wof:name":"Charlotte Housing Authority",
    "wof:placetype":"venue"
},
  "geometry": {"coordinates":[-80.82536,35.225113],"type":"Point"}
}