{
  "type": "Feature",
  "properties": {
    "iso:country":"US",
    "sg:address":"129 E Taft Ave",
    "sg:city":"Asheboro",
    "sg:classifiers":[
        {
            "category":"Education",
            "subcategory":"Dance Studio",
            "type":"Public Place"
        }
    ],
    "sg:phone":"+1 336 629 3963",
    "sg:postcode":"27203",
    "sg:province":"NC",
    "sg:tags":[
        "instruction",
        "dancing"
    ],
    "wof:name":"Studio J Dance Ctr",
    "wof:placetype":"venue"
},
  "geometry": {"coordinates":[-79.81462999999999,35.692202],"type":"Point"}
}