{
  "type": "Feature",
  "properties": {
    "iso:country":"US",
    "sg:address":"1420 E Franklin St",
    "sg:city":"Monroe",
    "sg:classifiers":[
        {
            "category":"Health Services",
            "subcategory":"Doctor",
            "type":"Services"
        }
    ],
    "sg:phone":"+1 704 289 8427",
    "sg:postcode":"28112",
    "sg:province":"NC",
    "sg:tags":[
        "clinic",
        "medical"
    ],
    "wof:name":"Monroe Family Medical Ctr P A",
    "wof:placetype":"venue"
},
  "geometry": {"coordinates":[-80.52351400000001,34.973883],"type":"Point"}
}