{
  "type": "Feature",
  "properties": {
    "iso:country":"US",
    "sg:address":"5301 Sharon Rd",
    "sg:city":"Charlotte",
    "sg:classifiers":[
        {
            "category":"Social Services",
            "subcategory":"Child Care",
            "type":"Services"
        }
    ],
    "sg:phone":"+1 704 553 0512",
    "sg:postcode":"28210",
    "sg:province":"NC",
    "wof:name":"Arbor Academy",
    "wof:placetype":"venue"
},
  "geometry": {"coordinates":[-80.83401499999999,35.142393],"type":"Point"}
}