{
  "type": "Feature",
  "properties": {
    "iso:country":"US",
    "sg:address":"1283 Audubon Dr",
    "sg:city":"Gastonia",
    "sg:classifiers":[
        {
            "category":"Real Estate",
            "subcategory":"Real Estate Operator",
            "type":"Services"
        }
    ],
    "sg:phone":"+1 704 866 7199",
    "sg:postcode":"28054",
    "sg:province":"NC",
    "sg:tags":[
        "building",
        "nonresidential"
    ],
    "wof:name":"Gibson Properties Ltd",
    "wof:placetype":"venue"
},
  "geometry": {"coordinates":[-81.155294,35.231011],"type":"Point"}
}