{
  "type": "Feature",
  "properties": {
    "iso:country":"US",
    "sg:address":"760 Antioch Rd",
    "sg:city":"New Bern",
    "sg:classifiers":[
        {
            "category":"Building & Trades",
            "subcategory":"Plumbing",
            "type":"Services"
        }
    ],
    "sg:phone":"+1 252 638 2891",
    "sg:postcode":"28560",
    "sg:province":"NC",
    "sg:tags":[
        "refrigeration",
        "contractor"
    ],
    "wof:name":"G&P Heating & Air Conditioning",
    "wof:placetype":"venue"
},
  "geometry": {"coordinates":[-77.048799,35.165665],"type":"Point"}
}