{
  "type": "Feature",
  "properties": {
    "addr:full":"3908 W Market St Greensboro NC 27407",
    "addr:housenumber":"3908",
    "addr:postcode":"27407",
    "addr:street":"W Market St",
    "iso:country":"US",
    "sg:address":"3908 W Market St",
    "sg:city":"Greensboro",
    "sg:classifiers":[
        {
            "category":"Personal",
            "subcategory":"Beauty Salon",
            "type":"Services"
        }
    ],
    "sg:phone":"+1   ",
    "sg:postcode":"27407",
    "sg:province":"NC",
    "sg:tags":[
        "shop"
    ],
    "wof:name":"Christine York Skin Solutions",
    "wof:placetype":"venue"
},
  "geometry": {"coordinates":[-79.85513899999999,36.069044],"type":"Point"}
}