{
  "type": "Feature",
  "properties": {
    "iso:country":"US",
    "sg:address":"6910 Fayetteville Rd",
    "sg:city":"Durham",
    "sg:classifiers":[
        {
            "category":"Shopping",
            "type":"Retail Goods"
        }
    ],
    "sg:phone":"+1 919 544 3278",
    "sg:postcode":"27713",
    "sg:province":"NC",
    "sg:tags":[
        "cosmetic",
        "perfume"
    ],
    "sg:website":"www.merlenorman.com",
    "wof:name":"Merle Norman Cosmetics",
    "wof:placetype":"venue"
},
  "geometry": {"coordinates":[-78.939689,35.90189],"type":"Point"}
}