{
  "type": "Feature",
  "properties": {
    "addr:full":"24 Weston Heights Dr Asheville NC 28803",
    "addr:housenumber":"24",
    "addr:postcode":"28803",
    "addr:street":"Weston Heights Dr",
    "iso:country":"US",
    "sg:address":"24 Weston Heights Dr",
    "sg:city":"Asheville",
    "sg:classifiers":[
        {
            "category":"Building & Trades",
            "subcategory":"Construction",
            "type":"Services"
        }
    ],
    "sg:phone":"+1 828 651 9703",
    "sg:postcode":"28803",
    "sg:province":"NC",
    "sg:tags":[
        "house"
    ],
    "wof:name":"Bassett Builders Inc",
    "wof:placetype":"venue"
},
  "geometry": {"coordinates":[-82.48732699999999,35.487609],"type":"Point"}
}