{
  "type": "Feature",
  "properties": {
    "iso:country":"US",
    "sg:address":"220 Lynch Colvard Rd",
    "sg:city":"Jefferson",
    "sg:classifiers":[
        {
            "category":"Organizations",
            "subcategory":"Religious Organization",
            "type":"Services"
        }
    ],
    "sg:phone":"+1 336 246 2979",
    "sg:postcode":"28640",
    "sg:province":"NC",
    "sg:tags":[
        "church"
    ],
    "wof:name":"Ashe Presbyterian Church",
    "wof:placetype":"venue"
},
  "geometry": {"coordinates":[-81.420143,36.400927],"type":"Point"}
}