{
  "type": "Feature",
  "properties": {
    "addr:full":"8 Elkmont Dr Asheville NC 28804",
    "addr:housenumber":"8",
    "addr:postcode":"28804",
    "addr:street":"Elkmont Dr",
    "iso:country":"US",
    "sg:address":"8 Elkmont Dr",
    "sg:city":"Asheville",
    "sg:classifiers":[
        {
            "category":"Real Estate",
            "subcategory":"Real Estate Agent",
            "type":"Services"
        }
    ],
    "sg:phone":"+1 828 255 4964",
    "sg:postcode":"28804",
    "sg:province":"NC",
    "sg:tags":[
        "appraiser"
    ],
    "wof:name":"Jbd Assoc Inc",
    "wof:placetype":"venue"
},
  "geometry": {"coordinates":[-82.57457700000001,35.637632],"type":"Point"}
}