{
  "type": "Feature",
  "properties": {
    "iso:country":"US",
    "sg:address":"2006 Phillips Ave",
    "sg:city":"Greensboro",
    "sg:classifiers":[
        {
            "category":"Retail",
            "subcategory":"Laundry & Dry Cleaning",
            "type":"Services"
        }
    ],
    "sg:phone":"+1 336 272 0845",
    "sg:postcode":"27405",
    "sg:province":"NC",
    "sg:tags":[
        "drycleaning",
        "plant"
    ],
    "wof:name":"Hunts Dry Cleaners",
    "wof:placetype":"venue"
},
  "geometry": {"coordinates":[-79.75324000000001,36.097114],"type":"Point"}
}