{
  "type": "Feature",
  "properties": {
    "addr:full":"521 Daniels St Raleigh NC 27605",
    "addr:housenumber":"521",
    "addr:postcode":"27605",
    "addr:street":"Daniels St",
    "iso:country":"US",
    "sg:address":"521 Daniels St",
    "sg:city":"Raleigh",
    "sg:classifiers":[
        {
            "category":"Restaurant",
            "type":"Food & Drink"
        }
    ],
    "sg:menulink":"http://www.allmenus.com/nc/raleigh/267808-fosters/menu/",
    "sg:phone":"+1 919 821 5969",
    "sg:postcode":"27605",
    "sg:province":"NC",
    "sg:tags":[
        "american"
    ],
    "wof:name":"Fosters",
    "wof:placetype":"venue"
},
  "geometry": {"coordinates":[-78.661141,35.791156],"type":"Point"}
}