{
  "type": "Feature",
  "properties": {
    "iso:country":"US",
    "sg:address":"3133 Yates Mill Dr SW",
    "sg:city":"Concord",
    "sg:classifiers":[
        {
            "category":"Building & Trades",
            "subcategory":"Landscaping Services",
            "type":"Services"
        }
    ],
    "sg:phone":"+1 704 786 3610",
    "sg:postcode":"28027",
    "sg:province":"NC",
    "sg:tags":[
        "landscape",
        "contractor"
    ],
    "wof:name":"Ect Properties",
    "wof:placetype":"venue"
},
  "geometry": {"coordinates":[-80.640215,35.371076],"type":"Point"}
}