{
  "type": "Feature",
  "properties": {
    "addr:full":"365 Bud Foster Rd Cleveland NC 27013",
    "addr:housenumber":"365",
    "addr:postcode":"27013",
    "addr:street":"Bud Foster Rd",
    "iso:country":"US",
    "sg:address":"365 Bud Foster Rd",
    "sg:city":"Cleveland",
    "sg:phone":"+1 704 278 2589",
    "sg:postcode":"27013",
    "sg:province":"NC",
    "sg:tags":[
        "beef",
        "farm",
        "corn",
        "soybean",
        "cattle",
        "feedlot"
    ],
    "wof:name":"Keith Foster",
    "wof:placetype":"venue"
},
  "geometry": {"coordinates":[-80.67028500000001,35.825229],"type":"Point"}
}