{
  "type": "Feature",
  "properties": {
    "iso:country":"US",
    "sg:address":"707 W King St",
    "sg:city":"Boone",
    "sg:classifiers":[
        {
            "category":"Manufacturing",
            "subcategory":"Printing",
            "type":"Manufacturing & Wholesale Goods"
        }
    ],
    "sg:phone":"+1 828 264 7653",
    "sg:postcode":"28607",
    "sg:province":"NC",
    "sg:tags":[
        "commercial"
    ],
    "wof:name":"Omega Tees Screenprinting LLC",
    "wof:placetype":"venue"
},
  "geometry": {"coordinates":[-81.68574099999999,36.219627],"type":"Point"}
}