{
  "type": "Feature",
  "properties": {
    "addr:full":"1016 Fuller Mill Rd Thomasville NC 27360",
    "addr:housenumber":"1016",
    "addr:postcode":"27360",
    "addr:street":"Fuller Mill Rd",
    "iso:country":"US",
    "sg:address":"1016 Fuller Mill Rd",
    "sg:city":"Thomasville",
    "sg:classifiers":[
        {
            "category":"Retail",
            "subcategory":"Laundry & Dry Cleaning",
            "type":"Services"
        }
    ],
    "sg:phone":"+1   ",
    "sg:postcode":"27360",
    "sg:province":"NC",
    "wof:name":"Houdini Carpet Cleaning",
    "wof:placetype":"venue"
},
  "geometry": {"coordinates":[-80.051767,35.837044],"type":"Point"}
}