{
  "type": "Feature",
  "properties": {
    "addr:full":"824 Lower Creek Dr NE Lenoir NC 28645",
    "addr:housenumber":"824",
    "addr:postcode":"28645",
    "addr:street":"Lower Creek Dr Ne",
    "iso:country":"US",
    "sg:address":"824 Lower Creek Dr NE",
    "sg:city":"Lenoir",
    "sg:classifiers":[
        {
            "category":"Insurance",
            "subcategory":"Insurance Agent",
            "type":"Services"
        }
    ],
    "sg:phone":"+1 828 754 8821",
    "sg:postcode":"28645",
    "sg:province":"NC",
    "wof:name":"Farm Bureau Insurance",
    "wof:placetype":"venue"
},
  "geometry": {"coordinates":[-81.507907,35.92481],"type":"Point"}
}