{
  "type": "Feature",
  "properties": {
    "addr:full":"1101 Old Forge Rd Rocky Mount NC 27804",
    "addr:housenumber":"1101",
    "addr:postcode":"27804",
    "addr:street":"Old Forge Rd",
    "iso:country":"US",
    "sg:address":"1101 Old Forge Rd",
    "sg:city":"Rocky Mount",
    "sg:classifiers":[
        {
            "category":"Professional",
            "type":"Services"
        }
    ],
    "sg:phone":"+1 252 451 5834",
    "sg:postcode":"27804",
    "sg:province":"NC",
    "wof:name":"Peniel Judgement Recovery",
    "wof:placetype":"venue"
},
  "geometry": {"coordinates":[-77.84199700000001,35.98451],"type":"Point"}
}