{
  "type": "Feature",
  "properties": {
    "addr:full":"700 Allister Dr Charlotte NC 28227",
    "addr:housenumber":"700",
    "addr:postcode":"28227",
    "addr:street":"Allister Dr",
    "iso:country":"US",
    "sg:address":"700 Allister Dr",
    "sg:city":"Charlotte",
    "sg:classifiers":[
        {
            "category":"Building & Trades",
            "subcategory":"Construction",
            "type":"Services"
        }
    ],
    "sg:phone":"+1 704 536 7946",
    "sg:postcode":"28227",
    "sg:province":"NC",
    "sg:tags":[
        "painter"
    ],
    "wof:name":"Jim Cron Paint & Wallcovering",
    "wof:placetype":"venue"
},
  "geometry": {"coordinates":[-80.720962,35.190486],"type":"Point"}
}