{
  "type": "Feature",
  "properties": {
    "iso:country":"US",
    "sg:address":"111 E Center St",
    "sg:city":"Mebane",
    "sg:classifiers":[
        {
            "category":"Professional",
            "subcategory":"Lawyer & Legal Services",
            "type":"Services"
        }
    ],
    "sg:phone":"+1 919 304 4200",
    "sg:postcode":"27302",
    "sg:province":"NC",
    "sg:tags":[
        "attorney"
    ],
    "wof:name":"J Wade Harrison",
    "wof:placetype":"venue"
},
  "geometry": {"coordinates":[-79.267762,36.096329],"type":"Point"}
}