{
  "type": "Feature",
  "properties": {
    "addr:full":"3124 E 10th St Greenville NC 27858",
    "addr:housenumber":"3124",
    "addr:postcode":"27858",
    "addr:street":"E 10Th St",
    "iso:country":"US",
    "sg:address":"3124 E 10th St",
    "sg:city":"Greenville",
    "sg:classifiers":[
        {
            "category":"Restaurant",
            "type":"Food & Drink"
        }
    ],
    "sg:phone":"+1 252 830 5393",
    "sg:postcode":"27858",
    "sg:province":"NC",
    "sg:tags":[
        "eating"
    ],
    "wof:name":"Lam's Garden",
    "wof:placetype":"venue"
},
  "geometry": {"coordinates":[-77.33367200000001,35.599753],"type":"Point"}
}