{
  "type": "Feature",
  "properties": {
    "addr:full":"725 Elm Ave Mt Holly NC 28120",
    "addr:housenumber":"725",
    "addr:postcode":"28120",
    "addr:street":"Elm Ave Mt",
    "iso:country":"US",
    "sg:address":"725 Elm Ave",
    "sg:city":"Mt Holly",
    "sg:classifiers":[
        {
            "category":"Building & Trades",
            "subcategory":"Construction",
            "type":"Services"
        }
    ],
    "sg:phone":"+1 704 827 9726",
    "sg:postcode":"28120",
    "sg:province":"NC",
    "sg:tags":[
        "marking",
        "maintenance",
        "parking"
    ],
    "sg:website":"www.mtholly.us",
    "wof:name":"Mt Holly Street Dept",
    "wof:placetype":"venue"
},
  "geometry": {"coordinates":[-81.005724,35.298755],"type":"Point"}
}