{
  "type": "Feature",
  "properties": {
    "iso:country":"US",
    "sg:address":"1934 N Fayetteville St",
    "sg:city":"Asheboro",
    "sg:classifiers":[
        {
            "category":"Real Estate",
            "subcategory":"Developer",
            "type":"Services"
        }
    ],
    "sg:phone":"+1 336 672 0031",
    "sg:postcode":"27203",
    "sg:province":"NC",
    "wof:name":"Community of Hope Development",
    "wof:placetype":"venue"
},
  "geometry": {"coordinates":[-79.80492599999999,35.753627],"type":"Point"}
}