{
  "type": "Feature",
  "properties": {
    "addr:full":"10167 N Main St Archdale NC 27263",
    "addr:housenumber":"10167",
    "addr:postcode":"27263",
    "addr:street":"N Main St",
    "iso:country":"US",
    "sg:address":"10167 N Main St",
    "sg:city":"Archdale",
    "sg:classifiers":[
        {
            "category":"Food & Beverages",
            "subcategory":"Groceries & Convenience Stores",
            "type":"Retail Goods"
        }
    ],
    "sg:phone":"+1 336 434 7192",
    "sg:postcode":"27263",
    "sg:province":"NC",
    "wof:name":"Amko Express Inc",
    "wof:placetype":"venue"
},
  "geometry": {"coordinates":[-79.958721,35.906012],"type":"Point"}
}