{
  "type": "Feature",
  "properties": {
    "addr:full":"315 Moore St Fayetteville NC 28301",
    "addr:housenumber":"315",
    "addr:postcode":"28301",
    "addr:street":"Moore St",
    "iso:country":"US",
    "sg:address":"315 Moore St",
    "sg:city":"Fayetteville",
    "sg:classifiers":[
        {
            "category":"Real Estate",
            "subcategory":"Real Estate Operator",
            "type":"Services"
        }
    ],
    "sg:phone":"+1 910 678 9916",
    "sg:postcode":"28301",
    "sg:province":"NC",
    "sg:tags":[
        "building",
        "apartment"
    ],
    "wof:name":"Edwards Place",
    "wof:placetype":"venue"
},
  "geometry": {"coordinates":[-78.879824,35.060412],"type":"Point"}
}