{
  "type": "Feature",
  "properties": {
    "addr:full":"1207 Central St Wilkesboro NC 28697",
    "addr:housenumber":"1207",
    "addr:postcode":"28697",
    "addr:street":"Central St",
    "iso:country":"US",
    "sg:address":"1207 Central St",
    "sg:city":"Wilkesboro",
    "sg:classifiers":[
        {
            "category":"Professional",
            "subcategory":"Computer Services",
            "type":"Services"
        }
    ],
    "sg:phone":"+1 336 667 6191",
    "sg:postcode":"28697",
    "sg:province":"NC",
    "sg:tags":[
        "internet"
    ],
    "wof:name":"Node",
    "wof:placetype":"venue"
},
  "geometry": {"coordinates":[-81.17976299999999,36.148664],"type":"Point"}
}