{
  "type": "Feature",
  "properties": {
    "iso:country":"US",
    "sg:address":"301 East Blvd",
    "sg:city":"Charlotte",
    "sg:classifiers":[
        {
            "category":"Real Estate",
            "subcategory":"Real Estate Agent",
            "type":"Services"
        }
    ],
    "sg:phone":"+1 704 377 2488",
    "sg:postcode":"28203",
    "sg:province":"NC",
    "wof:name":"Key Realty",
    "wof:placetype":"venue"
},
  "geometry": {"coordinates":[-80.85540399999999,35.210015],"type":"Point"}
}