{
  "type": "Feature",
  "properties": {
    "addr:full":"727 Wildwood Dr Clayton NC 27520",
    "addr:housenumber":"727",
    "addr:postcode":"27520",
    "addr:street":"Wildwood Dr",
    "iso:country":"US",
    "sg:address":"727 Wildwood Dr",
    "sg:city":"Clayton",
    "sg:classifiers":[
        {
            "category":"Shopping",
            "subcategory":"Hobbies, Toys, & Games",
            "type":"Retail Goods"
        }
    ],
    "sg:phone":"+1 919 553 6686",
    "sg:postcode":"27520",
    "sg:province":"NC",
    "sg:tags":[
        "equipment",
        "ceramic",
        "supply"
    ],
    "wof:name":"Rachel's Ceramics",
    "wof:placetype":"venue"
},
  "geometry": {"coordinates":[-78.437438,35.631186],"type":"Point"}
}