{
  "type": "Feature",
  "properties": {
    "addr:full":"2951 Reynolda Rd Winston Salem NC 27106",
    "addr:housenumber":"2951",
    "addr:postcode":"27106",
    "addr:street":"Reynolda Rd",
    "iso:country":"US",
    "sg:address":"2951 Reynolda Rd",
    "sg:city":"Winston Salem",
    "sg:classifiers":[
        {
            "category":"Retail",
            "subcategory":"Funeral Services",
            "type":"Services"
        }
    ],
    "sg:phone":"+1 336 722 6106",
    "sg:postcode":"27106",
    "sg:province":"NC",
    "sg:tags":[
        "director"
    ],
    "wof:name":"Voglers Funeral Homes",
    "wof:placetype":"venue"
},
  "geometry": {"coordinates":[-80.30524,36.147609],"type":"Point"}
}