{
  "type": "Feature",
  "properties": {
    "addr:full":"1204 S Main St Mount Holly NC 28120",
    "addr:housenumber":"1204",
    "addr:postcode":"28120",
    "addr:street":"S Main St",
    "iso:country":"US",
    "sg:address":"1204 S Main St",
    "sg:city":"Mount Holly",
    "sg:classifiers":[
        {
            "category":"Personal",
            "type":"Services"
        }
    ],
    "sg:phone":"+1   ",
    "sg:postcode":"28120",
    "sg:province":"NC",
    "wof:name":"Sun Solutions",
    "wof:placetype":"venue"
},
  "geometry": {"coordinates":[-81.027878,35.275377],"type":"Point"}
}