{
  "type": "Feature",
  "properties": {
    "addr:full":"306 N Elm St Lumberton NC 28358",
    "addr:housenumber":"306",
    "addr:postcode":"28358",
    "addr:street":"N Elm St",
    "iso:country":"US",
    "sg:address":"306 N Elm St",
    "sg:city":"Lumberton",
    "sg:classifiers":[
        {
            "category":"Organizations",
            "subcategory":"Religious Organization",
            "type":"Services"
        }
    ],
    "sg:phone":"+1 910 739 1215",
    "sg:postcode":"28358",
    "sg:province":"NC",
    "sg:tags":[
        "church"
    ],
    "wof:name":"Good Shepherd Community Church",
    "wof:placetype":"venue"
},
  "geometry": {"coordinates":[-79.00854200000001,34.619352],"type":"Point"}
}