{
  "type": "Feature",
  "properties": {
    "addr:full":"104 Mariposa Rd Stanley NC 28164",
    "addr:housenumber":"104",
    "addr:postcode":"28164",
    "addr:street":"Mariposa Rd",
    "iso:country":"US",
    "sg:address":"104 Mariposa Rd",
    "sg:city":"Stanley",
    "sg:classifiers":[
        {
            "category":"Food & Beverages",
            "subcategory":"Groceries & Convenience Stores",
            "type":"Retail Goods"
        }
    ],
    "sg:phone":"+1 704 263 2151",
    "sg:postcode":"28164",
    "sg:province":"NC",
    "wof:name":"Linda's Shop Around",
    "wof:placetype":"venue"
},
  "geometry": {"coordinates":[-81.09715,35.371294],"type":"Point"}
}