{
  "type": "Feature",
  "properties": {
    "iso:country":"US",
    "sg:address":"34 Brownstone Ln",
    "sg:city":"Greensboro",
    "sg:classifiers":[
        {
            "category":"Real Estate",
            "subcategory":"Real Estate Agent",
            "type":"Services"
        }
    ],
    "sg:phone":"+1 336 299 0826",
    "sg:postcode":"27410",
    "sg:province":"NC",
    "wof:name":"Hogewood Mary Ann Rl Est",
    "wof:placetype":"venue"
},
  "geometry": {"coordinates":[-79.89040199999999,36.08219],"type":"Point"}
}