{
  "type": "Feature",
  "properties": {
    "iso:country":"US",
    "sg:address":"1912 Cliffside Dr",
    "sg:city":"Pfafftown",
    "sg:classifiers":[
        {
            "category":"Manufacturing",
            "subcategory":"Rubber & Plastics",
            "type":"Manufacturing & Wholesale Goods"
        }
    ],
    "sg:phone":"+1 336 924 0874",
    "sg:postcode":"27040",
    "sg:province":"NC",
    "sg:tags":[
        "development",
        "lighted",
        "product",
        "tackle",
        "box"
    ],
    "wof:name":"Night-Rangertm",
    "wof:placetype":"venue"
},
  "geometry": {"coordinates":[-80.328456,36.196859],"type":"Point"}
}