{
  "type": "Feature",
  "properties": {
    "addr:full":"1000 State Hwy 27 Stanley NC 28164",
    "addr:housenumber":"1000",
    "addr:postcode":"28164",
    "addr:street":"State Hwy 27",
    "iso:country":"US",
    "sg:address":"1000 State Hwy 27",
    "sg:city":"Stanley",
    "sg:classifiers":[
        {
            "category":"Manufacturing",
            "subcategory":"Tools & Machinery",
            "type":"Manufacturing & Wholesale Goods"
        }
    ],
    "sg:phone":"+1 704 263 1991",
    "sg:postcode":"28164",
    "sg:province":"NC",
    "sg:tags":[
        "plate",
        "industrial",
        "mfg",
        "fabricated",
        "general",
        "w"
    ],
    "wof:name":"Flair Filtration",
    "wof:placetype":"venue"
},
  "geometry": {"coordinates":[-81.081931,35.344519],"type":"Point"}
}