{
  "type": "Feature",
  "properties": {
    "addr:full":"109 Market St Cramerton NC 28032",
    "addr:housenumber":"109",
    "addr:postcode":"28032",
    "addr:street":"Market St",
    "iso:country":"US",
    "sg:address":"109 Market St",
    "sg:city":"Cramerton",
    "sg:classifiers":[
        {
            "category":"Retail",
            "subcategory":"Repair Shop",
            "type":"Services"
        }
    ],
    "sg:phone":"+1 704 824 1651",
    "sg:postcode":"28032",
    "sg:province":"NC",
    "sg:tags":[
        "upholsterer"
    ],
    "wof:name":"Down Upholstery",
    "wof:placetype":"venue"
},
  "geometry": {"coordinates":[-81.082596,35.248484],"type":"Point"}
}