{
  "type": "Feature",
  "properties": {
    "iso:country":"US",
    "sg:address":"19621 State Hwy 73",
    "sg:city":"Cornelius",
    "sg:classifiers":[
        {
            "category":"Retail",
            "subcategory":"Laundry & Dry Cleaning",
            "type":"Services"
        }
    ],
    "sg:phone":"+1   ",
    "sg:postcode":"28001",
    "sg:province":"NC",
    "wof:name":"Alterations",
    "wof:placetype":"venue"
},
  "geometry": {"coordinates":[-80.342057,35.382846],"type":"Point"}
}