{
  "type": "Feature",
  "properties": {
    "iso:country":"US",
    "sg:address":"1275 Sand Hill Rd",
    "sg:city":"Candler",
    "sg:classifiers":[
        {
            "category":"Personal",
            "type":"Services"
        }
    ],
    "sg:phone":"+1 828 274 9077",
    "sg:postcode":"28715",
    "sg:province":"NC",
    "sg:tags":[
        "mover"
    ],
    "wof:name":"Smith Dray Line & Storage Co-United Van Lines Agnt",
    "wof:placetype":"venue"
},
  "geometry": {"coordinates":[-82.70169799999999,35.523701],"type":"Point"}
}