{
  "type": "Feature",
  "properties": {
    "iso:country":"US",
    "sg:address":"3820 Merton Dr",
    "sg:city":"Raleigh",
    "sg:classifiers":[
        {
            "category":"Social Services",
            "subcategory":"Adult Care",
            "type":"Services"
        },
        {
            "category":"Social Services",
            "subcategory":"Job Training",
            "type":"Services"
        }
    ],
    "sg:phone":"+1 919 787 1214",
    "sg:postcode":"27609",
    "sg:province":"NC",
    "sg:tags":[
        "mental",
        "work",
        "dev",
        "disabled",
        "retarded",
        "retardation"
    ],
    "wof:name":"Residential Support Services",
    "wof:placetype":"venue"
},
  "geometry": {"coordinates":[-78.63145900000001,35.830597],"type":"Point"}
}