{
  "type": "Feature",
  "properties": {
    "iso:country":"US",
    "sg:address":"5716 Plowfield Rd",
    "sg:city":"Mc Leansville",
    "sg:classifiers":[
        {
            "category":"Organizations",
            "subcategory":"Religious Organization",
            "type":"Services"
        }
    ],
    "sg:phone":"+1 336 954 1599",
    "sg:postcode":"27301",
    "sg:province":"NC",
    "sg:tags":[
        "church"
    ],
    "wof:name":"Unity Baptist Church",
    "wof:placetype":"venue"
},
  "geometry": {"coordinates":[-79.662052,36.168264],"type":"Point"}
}