{
  "type": "Feature",
  "properties": {
    "iso:country":"US",
    "sg:address":"322 S Gardner Ave",
    "sg:city":"Charlotte",
    "sg:classifiers":[
        {
            "category":"Wholesale",
            "subcategory":"Machinery & Supplies",
            "type":"Manufacturing & Wholesale Goods"
        }
    ],
    "sg:phone":"+1 704 374 1441",
    "sg:postcode":"28208",
    "sg:province":"NC",
    "sg:tags":[
        "abrasive"
    ],
    "wof:name":"A Child's Choice Learning Ctr",
    "wof:placetype":"venue"
},
  "geometry": {"coordinates":[-80.867661,35.243329],"type":"Point"}
}