{
  "type": "Feature",
  "properties": {
    "iso:country":"US",
    "sg:address":"360 Howardtown Cir",
    "sg:city":"Mocksville",
    "sg:classifiers":[
        {
            "category":"Building & Trades",
            "subcategory":"Construction",
            "type":"Services"
        }
    ],
    "sg:phone":"+1 336 940 6271",
    "sg:postcode":"27028",
    "sg:province":"NC",
    "sg:tags":[
        "excavating",
        "contractor"
    ],
    "wof:name":"Mc Danile Grading Hauling Inc",
    "wof:placetype":"venue"
},
  "geometry": {"coordinates":[-80.480929,35.973532],"type":"Point"}
}