{
  "type": "Feature",
  "properties": {
    "addr:full":"1329 Sycamore Dr Garner NC 27529",
    "addr:housenumber":"1329",
    "addr:postcode":"27529",
    "addr:street":"Sycamore Dr",
    "iso:country":"US",
    "sg:address":"1329 Sycamore Dr",
    "sg:city":"Garner",
    "sg:classifiers":[
        {
            "category":"Building & Trades",
            "subcategory":"Construction",
            "type":"Services"
        }
    ],
    "sg:phone":"+1 919 795 0696",
    "sg:postcode":"27529",
    "sg:province":"NC",
    "wof:name":"David Lane",
    "wof:placetype":"venue"
},
  "geometry": {"coordinates":[-78.625767,35.700297],"type":"Point"}
}