{
  "type": "Feature",
  "properties": {
    "iso:country":"US",
    "sg:address":"210 E 16th St",
    "sg:city":"Scotland Neck",
    "sg:classifiers":[
        {
            "category":"Wholesale",
            "subcategory":"Farm Supplies",
            "type":"Manufacturing & Wholesale Goods"
        }
    ],
    "sg:phone":"+1 252 826 5511",
    "sg:postcode":"27874",
    "sg:province":"NC",
    "sg:tags":[
        "peanut",
        "product"
    ],
    "wof:name":"Peanut Services Inc",
    "wof:placetype":"venue"
},
  "geometry": {"coordinates":[-77.41828,36.136062],"type":"Point"}
}