{
  "type": "Feature",
  "properties": {
    "iso:country":"US",
    "sg:address":"437 Stroud Rd",
    "sg:city":"Trenton",
    "sg:phone":"+1 252 448 5377",
    "sg:postcode":"28585",
    "sg:province":"NC",
    "sg:tags":[
        "farm",
        "tobacco"
    ],
    "wof:name":"Franklin Andrews",
    "wof:placetype":"venue"
},
  "geometry": {"coordinates":[-77.43808900000001,35.061017],"type":"Point"}
}