{
  "type": "Feature",
  "properties": {
    "iso:country":"US",
    "sg:address":"140 School Rd E",
    "sg:city":"Asheville",
    "sg:classifiers":[
        {
            "category":"Organizations",
            "subcategory":"Religious Organization",
            "type":"Services"
        }
    ],
    "sg:phone":"+1   ",
    "sg:postcode":"28803",
    "sg:province":"NC",
    "wof:name":"Oakley Gospel Tabernacle",
    "wof:placetype":"venue"
},
  "geometry": {"coordinates":[-82.511363,35.559384],"type":"Point"}
}