{
  "type": "Feature",
  "properties": {
    "addr:full":"5617 Alta Vista Ct Raleigh NC 27610",
    "addr:housenumber":"5617",
    "addr:postcode":"27610",
    "addr:street":"Alta Vista Ct",
    "iso:country":"US",
    "sg:address":"5617 Alta Vista Ct",
    "sg:city":"Raleigh",
    "sg:classifiers":[
        {
            "category":"Building & Trades",
            "subcategory":"Landscaping Services",
            "type":"Services"
        }
    ],
    "sg:phone":"+1 919 231 7949",
    "sg:postcode":"27610",
    "sg:province":"NC",
    "sg:tags":[
        "landscape",
        "contractor"
    ],
    "sg:website":"http://www.mcgilllandscaping.com",
    "wof:name":"Mcgill Landscaping",
    "wof:placetype":"venue"
},
  "geometry": {"coordinates":[-78.545732,35.76572],"type":"Point"}
}