{
  "type": "Feature",
  "properties": {
    "addr:full":"1120 N Main Ave Newton NC 28658",
    "addr:housenumber":"1120",
    "addr:postcode":"28658",
    "addr:street":"N Main Ave",
    "iso:country":"US",
    "sg:address":"1120 N Main Ave",
    "sg:city":"Newton",
    "sg:classifiers":[
        {
            "category":"Retail",
            "subcategory":"Auto Repair",
            "type":"Services"
        }
    ],
    "sg:phone":"+1 828 464 0432",
    "sg:postcode":"28658",
    "sg:province":"NC",
    "sg:tags":[
        "body",
        "automobile",
        "painting"
    ],
    "wof:name":"Hartsoe's Body Shop",
    "wof:placetype":"venue"
},
  "geometry": {"coordinates":[-81.220928,35.675369],"type":"Point"}
}