{
  "type": "Feature",
  "properties": {
    "iso:country":"US",
    "sg:address":"250 Culbreth Rd",
    "sg:city":"Chapel Hill",
    "sg:classifiers":[
        {
            "category":"Real Estate",
            "subcategory":"Real Estate Agent",
            "type":"Services"
        }
    ],
    "sg:phone":"+1 919 967 9992",
    "sg:postcode":"27516",
    "sg:province":"NC",
    "wof:name":"Jim Lilley Properties",
    "wof:placetype":"venue"
},
  "geometry": {"coordinates":[-79.064331,35.8917],"type":"Point"}
}