{
  "type": "Feature",
  "properties": {
    "iso:country":"US",
    "sg:address":"113 E Main St",
    "sg:city":"Lincolnton",
    "sg:classifiers":[
        {
            "category":"Professional",
            "subcategory":"Computer Services",
            "type":"Services"
        }
    ],
    "sg:phone":"+1 704 732 8181",
    "sg:postcode":"28092",
    "sg:province":"NC",
    "wof:name":"Syscon 1 Inc",
    "wof:placetype":"venue"
},
  "geometry": {"coordinates":[-81.25562499999999,35.471869],"type":"Point"}
}