{
  "type": "Feature",
  "properties": {
    "iso:country":"US",
    "sg:address":"1084 Carolina Ave",
    "sg:city":"Albemarle",
    "sg:classifiers":[
        {
            "category":"Organizations",
            "subcategory":"Religious Organization",
            "type":"Services"
        }
    ],
    "sg:phone":"+1   ",
    "sg:postcode":"28001",
    "sg:province":"NC",
    "wof:name":"Straitway Baptist Church",
    "wof:placetype":"venue"
},
  "geometry": {"coordinates":[-80.207973,35.360476],"type":"Point"}
}