{
  "type": "Feature",
  "properties": {
    "iso:country":"US",
    "sg:address":"5700 Executive Center Dr",
    "sg:city":"Charlotte",
    "sg:classifiers":[
        {
            "category":"Insurance",
            "subcategory":"Insurance Agent",
            "type":"Services"
        }
    ],
    "sg:phone":"+1 704 537 4950",
    "sg:postcode":"28212",
    "sg:province":"NC",
    "wof:name":"Coface North America",
    "wof:placetype":"venue"
},
  "geometry": {"coordinates":[-80.74423899999999,35.201908],"type":"Point"}
}