{
  "type": "Feature",
  "properties": {
    "addr:full":"6145 University Pkwy Winston Salem NC 27105",
    "addr:housenumber":"6145",
    "addr:postcode":"27105",
    "addr:street":"University Pkwy",
    "iso:country":"US",
    "sg:address":"6145 University Pkwy",
    "sg:city":"Winston Salem",
    "sg:classifiers":[
        {
            "category":"Autos & Motor Vehicles",
            "subcategory":"Motorcycle Sales",
            "type":"Retail Goods"
        }
    ],
    "sg:phone":"+1 336 377 9611",
    "sg:postcode":"27105",
    "sg:province":"NC",
    "wof:name":"Cycle Goodies",
    "wof:placetype":"venue"
},
  "geometry": {"coordinates":[-80.27866400000001,36.194218],"type":"Point"}
}