{
  "type": "Feature",
  "properties": {
    "addr:full":"295 Daniels Rd Salisbury NC 28144",
    "addr:housenumber":"295",
    "addr:postcode":"28144",
    "addr:street":"Daniels Rd",
    "iso:country":"US",
    "sg:address":"295 Daniels Rd",
    "sg:city":"Salisbury",
    "sg:classifiers":[
        {
            "category":"Recreation",
            "type":"Entertainment"
        }
    ],
    "sg:phone":"+1 704 630 0705",
    "sg:postcode":"28144",
    "sg:province":"NC",
    "sg:tags":[
        "paint",
        "ball",
        "sport"
    ],
    "wof:name":"Power Play Paintball",
    "wof:placetype":"venue"
},
  "geometry": {"coordinates":[-80.485956,35.718668],"type":"Point"}
}