{
  "type": "Feature",
  "properties": {
    "addr:full":"601 E Main St Havelock NC 28532",
    "addr:housenumber":"601",
    "addr:postcode":"28532",
    "addr:street":"E Main St",
    "iso:country":"US",
    "sg:address":"601 E Main St",
    "sg:city":"Havelock",
    "sg:classifiers":[
        {
            "category":"Home & Garden",
            "subcategory":"Furniture",
            "type":"Retail Goods"
        }
    ],
    "sg:phone":"+1 252 447 8535",
    "sg:postcode":"28532",
    "sg:province":"NC",
    "sg:tags":[
        "also",
        "bedding",
        "appliance"
    ],
    "wof:name":"A To Z Stores Inc",
    "wof:placetype":"venue"
},
  "geometry": {"coordinates":[-76.90067500000001,34.869329],"type":"Point"}
}