{
  "type": "Feature",
  "properties": {
    "addr:full":"1854 Montclair Ave Gastonia NC 28054",
    "addr:housenumber":"1854",
    "addr:postcode":"28054",
    "addr:street":"Montclair Ave",
    "iso:country":"US",
    "sg:address":"1854 Montclair Ave",
    "sg:city":"Gastonia",
    "sg:classifiers":[
        {
            "category":"Building & Trades",
            "subcategory":"Construction",
            "type":"Services"
        }
    ],
    "sg:phone":"+1 704 864 1528",
    "sg:postcode":"28054",
    "sg:province":"NC",
    "sg:tags":[
        "hanging",
        "contractor"
    ],
    "wof:name":"Ashley Jenkins Painting Contr",
    "wof:placetype":"venue"
},
  "geometry": {"coordinates":[-81.147094,35.256626],"type":"Point"}
}