{
  "type": "Feature",
  "properties": {
    "iso:country":"US",
    "sg:address":"12100 University City Blvd",
    "sg:city":"Harrisburg",
    "sg:classifiers":[
        {
            "category":"Autos & Motor Vehicles",
            "subcategory":"Automobile Sales",
            "type":"Retail Goods"
        }
    ],
    "sg:phone":"+1 704 455 6300",
    "sg:postcode":"28075",
    "sg:province":"NC",
    "sg:tags":[
        "car",
        "used",
        "dealer"
    ],
    "wof:name":"Haglers Used Cars",
    "wof:placetype":"venue"
},
  "geometry": {"coordinates":[-80.68022000000001,35.315728],"type":"Point"}
}