{
  "type": "Feature",
  "properties": {
    "iso:country":"US",
    "sg:address":"225 Burkwood Ln",
    "sg:city":"Raleigh",
    "sg:classifiers":[
        {
            "category":"Building & Trades",
            "subcategory":"Plumbing",
            "type":"Services"
        }
    ],
    "sg:phone":"+1 919 510 0419",
    "sg:postcode":"27609",
    "sg:province":"NC",
    "sg:tags":[
        "heating",
        "contractor"
    ],
    "wof:name":"Betts Heating & Air Conditioni",
    "wof:placetype":"venue"
},
  "geometry": {"coordinates":[-78.634828,35.856865],"type":"Point"}
}