{
  "type": "Feature",
  "properties": {
    "addr:full":"719 Chelwood Pl Charlotte NC 28217",
    "addr:housenumber":"719",
    "addr:postcode":"28217",
    "addr:street":"Chelwood Pl",
    "iso:country":"US",
    "sg:address":"719 Chelwood Pl",
    "sg:city":"Charlotte",
    "sg:classifiers":[
        {
            "category":"Social Services",
            "subcategory":"Child Care",
            "type":"Services"
        }
    ],
    "sg:phone":"+1 704 522 7904",
    "sg:postcode":"28217",
    "sg:province":"NC",
    "sg:tags":[
        "day"
    ],
    "wof:name":"Kidz Land Child Care",
    "wof:placetype":"venue"
},
  "geometry": {"coordinates":[-80.886668,35.152172],"type":"Point"}
}