{
  "type": "Feature",
  "properties": {
    "iso:country":"US",
    "sg:address":"960 Hindenburg Ln",
    "sg:city":"Germanton",
    "sg:classifiers":[
        {
            "category":"Professional",
            "subcategory":"Research",
            "type":"Services"
        }
    ],
    "sg:phone":"+1   ",
    "sg:postcode":"27019",
    "sg:province":"NC",
    "sg:tags":[
        "commercial",
        "physical"
    ],
    "wof:name":"Griffin Environmentl Srvc",
    "wof:placetype":"venue"
},
  "geometry": {"coordinates":[-80.24313100000001,36.258202],"type":"Point"}
}