{
  "type": "Feature",
  "properties": {
    "iso:country":"US",
    "sg:address":"6142 Lake Brandt Rd",
    "sg:city":"Greensboro",
    "sg:classifiers":[
        {
            "category":"Organizations",
            "subcategory":"Religious Organization",
            "type":"Services"
        }
    ],
    "sg:phone":"+1 336 643 7765",
    "sg:postcode":"27455",
    "sg:province":"NC",
    "wof:name":"Center United Methodist Church",
    "wof:placetype":"venue"
},
  "geometry": {"coordinates":[-79.84143299999999,36.194804],"type":"Point"}
}