{
  "type": "Feature",
  "properties": {
    "addr:full":"310 Williams St Farmville NC 27828",
    "addr:housenumber":"310",
    "addr:postcode":"27828",
    "addr:street":"Williams St",
    "iso:country":"US",
    "sg:address":"310 Williams St",
    "sg:city":"Farmville",
    "sg:classifiers":[
        {
            "category":"Organizations",
            "subcategory":"Religious Organization",
            "type":"Services"
        }
    ],
    "sg:phone":"+1 252 753 2403",
    "sg:postcode":"27828",
    "sg:province":"NC",
    "sg:tags":[
        "church"
    ],
    "wof:name":"St John's Free Will Baptist",
    "wof:placetype":"venue"
},
  "geometry": {"coordinates":[-77.594273,35.587113],"type":"Point"}
}