{
  "type": "Feature",
  "properties": {
    "addr:full":"320 S Tryon St Charlotte NC 28202",
    "addr:housenumber":"320",
    "addr:postcode":"28202",
    "addr:street":"S Tryon St",
    "iso:country":"US",
    "sg:address":"320 S Tryon St",
    "sg:city":"Charlotte",
    "sg:classifiers":[
        {
            "category":"Restaurant",
            "type":"Food & Drink"
        }
    ],
    "sg:menulink":"http://www.allmenus.com/nc/charlotte/115757-quiznos-sub/menu/",
    "sg:phone":"+1 704 372 8922",
    "sg:postcode":"28202",
    "sg:province":"NC",
    "sg:tags":[
        "wrap",
        "american",
        "sandwich"
    ],
    "wof:name":"Quiznos Sub",
    "wof:placetype":"venue"
},
  "geometry": {"coordinates":[-80.845933,35.225224],"type":"Point"}
}