{
  "type": "Feature",
  "properties": {
    "addr:full":"3917 Singletree Rd Charlotte NC 28227",
    "addr:housenumber":"3917",
    "addr:postcode":"28227",
    "addr:street":"Singletree Rd",
    "iso:country":"US",
    "sg:address":"3917 Singletree Rd",
    "sg:city":"Charlotte",
    "sg:classifiers":[
        {
            "category":"Home & Garden",
            "subcategory":"Home Furnishings",
            "type":"Retail Goods"
        }
    ],
    "sg:phone":"+1 704 545 7469",
    "sg:postcode":"28227",
    "sg:province":"NC",
    "wof:name":"Magnolia Marketplace Triangle",
    "wof:placetype":"venue"
},
  "geometry": {"coordinates":[-80.693929,35.163936],"type":"Point"}
}