{
  "type": "Feature",
  "properties": {
    "addr:full":"305 S Road St Elizabeth City NC 27909",
    "addr:housenumber":"305",
    "addr:postcode":"27909",
    "addr:street":"S Road St",
    "iso:country":"US",
    "sg:address":"305 S Road St",
    "sg:city":"Elizabeth City",
    "sg:classifiers":[
        {
            "category":"Education",
            "subcategory":"College",
            "type":"Public Place"
        }
    ],
    "sg:phone":"+1 252 337 9005",
    "sg:postcode":"27909",
    "sg:province":"NC",
    "sg:tags":[
        "academic",
        "school"
    ],
    "wof:name":"Workforce Proficiency Inst",
    "wof:placetype":"venue"
},
  "geometry": {"coordinates":[-76.224092,36.298877],"type":"Point"}
}