{
  "type": "Feature",
  "properties": {
    "addr:full":"3 Orchard Ridge Dr Asheville NC 28804",
    "addr:housenumber":"3",
    "addr:postcode":"28804",
    "addr:street":"Orchard Ridge Dr",
    "iso:country":"US",
    "sg:address":"3 Orchard Ridge Dr",
    "sg:city":"Asheville",
    "sg:classifiers":[
        {
            "category":"Real Estate",
            "subcategory":"Architect",
            "type":"Services"
        }
    ],
    "sg:phone":"+1 828 255 7684",
    "sg:postcode":"28804",
    "sg:province":"NC",
    "wof:name":"Wiegman Associates Architects",
    "wof:placetype":"venue"
},
  "geometry": {"coordinates":[-82.504789,35.654072],"type":"Point"}
}