{
  "type": "Feature",
  "properties": {
    "iso:country":"US",
    "sg:address":"5125 Hedrick Dr",
    "sg:city":"Greensboro",
    "sg:classifiers":[
        {
            "category":"Organizations",
            "subcategory":"Community Association",
            "type":"Services"
        }
    ],
    "sg:phone":"+1 336 288 4461",
    "sg:postcode":"27410",
    "sg:province":"NC",
    "sg:tags":[
        "club"
    ],
    "wof:name":"Greensboro Country Club",
    "wof:placetype":"venue"
},
  "geometry": {"coordinates":[-79.88193099999999,36.153953],"type":"Point"}
}