{
  "type": "Feature",
  "properties": {
    "addr:full":"5808 Leatherwood Ln Harrisburg NC 28075",
    "addr:housenumber":"5808",
    "addr:postcode":"28075",
    "addr:street":"Leatherwood Ln",
    "iso:country":"US",
    "sg:address":"5808 Leatherwood Ln",
    "sg:city":"Harrisburg",
    "sg:classifiers":[
        {
            "category":"Building & Trades",
            "subcategory":"Construction",
            "type":"Services"
        }
    ],
    "sg:phone":"+1 704 455 6379",
    "sg:postcode":"28075",
    "sg:province":"NC",
    "sg:tags":[
        "nonresidential"
    ],
    "wof:name":"Cebco Services Inc",
    "wof:placetype":"venue"
},
  "geometry": {"coordinates":[-80.672279,35.331057],"type":"Point"}
}