{
  "type": "Feature",
  "properties": {
    "addr:full":"189 Old Mill Rd High Point NC 27265",
    "addr:housenumber":"189",
    "addr:postcode":"27265",
    "addr:street":"Old Mill Rd",
    "iso:country":"US",
    "sg:address":"189 Old Mill Rd",
    "sg:city":"High Point",
    "sg:classifiers":[
        {
            "category":"Retail",
            "subcategory":"Auto Repair",
            "type":"Services"
        }
    ],
    "sg:phone":"+1 336 869 7199",
    "sg:postcode":"27265",
    "sg:province":"NC",
    "sg:tags":[
        "repairing",
        "automobile"
    ],
    "wof:name":"Welborn's Repair",
    "wof:placetype":"venue"
},
  "geometry": {"coordinates":[-80.028919,36.018245],"type":"Point"}
}