{
  "type": "Feature",
  "properties": {
    "addr:full":"83 Peachtree Rd Asheville NC 28803",
    "addr:housenumber":"83",
    "addr:postcode":"28803",
    "addr:street":"Peachtree Rd",
    "iso:country":"US",
    "sg:address":"83 Peachtree Rd",
    "sg:city":"Asheville",
    "sg:classifiers":[
        {
            "category":"Real Estate",
            "subcategory":"Real Estate Agent",
            "type":"Services"
        }
    ],
    "sg:phone":"+1 828 277 9670",
    "sg:postcode":"28803",
    "sg:province":"NC",
    "wof:name":"Spake Real Estate Inc",
    "wof:placetype":"venue"
},
  "geometry": {"coordinates":[-82.52584,35.514215],"type":"Point"}
}