{
  "type": "Feature",
  "properties": {
    "addr:full":"710 Deweese Ave Rockingham NC 28379",
    "addr:housenumber":"710",
    "addr:postcode":"28379",
    "addr:street":"Deweese Ave",
    "iso:country":"US",
    "sg:address":"710 Deweese Ave",
    "sg:city":"Rockingham",
    "sg:classifiers":[
        {
            "category":"Organizations",
            "subcategory":"Religious Organization",
            "type":"Services"
        }
    ],
    "sg:phone":"+1 910 997 2751",
    "sg:postcode":"28379",
    "sg:province":"NC",
    "sg:tags":[
        "church"
    ],
    "wof:name":"Jehovah's Witnesses",
    "wof:placetype":"venue"
},
  "geometry": {"coordinates":[-79.748238,34.955307],"type":"Point"}
}