{
  "type": "Feature",
  "properties": {
    "iso:country":"US",
    "sg:address":"3006 Industrial Dr",
    "sg:city":"Raleigh",
    "sg:classifiers":[
        {
            "category":"Professional",
            "subcategory":"Business Services",
            "type":"Services"
        }
    ],
    "sg:phone":"+1 919 828 0894",
    "sg:postcode":"27609",
    "sg:province":"NC",
    "sg:tags":[
        "record"
    ],
    "sg:website":"www.real-hr.com",
    "wof:name":"Recall Total Information Mgmt",
    "wof:placetype":"venue"
},
  "geometry": {"coordinates":[-78.61888500000001,35.820188],"type":"Point"}
}