{
  "type": "Feature",
  "properties": {
    "iso:country":"US",
    "sg:address":"1221 Bert Winston Rd",
    "sg:city":"Youngsville",
    "sg:classifiers":[
        {
            "category":"Professional",
            "subcategory":"Business Services",
            "type":"Services"
        }
    ],
    "sg:phone":"+1   ",
    "sg:postcode":"27596",
    "sg:province":"NC",
    "wof:name":"Diversified Funding Solutions",
    "wof:placetype":"venue"
},
  "geometry": {"coordinates":[-78.487528,36.059357],"type":"Point"}
}