{
  "type": "Feature",
  "properties": {
    "iso:country":"US",
    "sg:address":"333 Grassy Knob Rd",
    "sg:city":"Union Grove",
    "sg:classifiers":[
        {
            "category":"Organizations",
            "subcategory":"Religious Organization",
            "type":"Services"
        }
    ],
    "sg:phone":"+1   ",
    "sg:postcode":"28689",
    "sg:province":"NC",
    "wof:name":"Grassy Knob Baptist Church",
    "wof:placetype":"venue"
},
  "geometry": {"coordinates":[-80.920987,36.046284],"type":"Point"}
}