{
  "type": "Feature",
  "properties": {
    "iso:country":"US",
    "sg:address":"2804 Foxfire Rd",
    "sg:city":"Charlotte",
    "sg:classifiers":[
        {
            "category":"Shopping",
            "subcategory":"Shoes",
            "type":"Retail Goods"
        }
    ],
    "sg:phone":"+1 704 847 1184",
    "sg:postcode":"28270",
    "sg:province":"NC",
    "wof:name":"D Nightingale",
    "wof:placetype":"venue"
},
  "geometry": {"coordinates":[-80.742228,35.088639],"type":"Point"}
}