{
  "type": "Feature",
  "properties": {
    "iso:country":"US",
    "sg:address":"5520 Dillard Dr Ste 130",
    "sg:city":"Cary",
    "sg:classifiers":[
        {
            "category":"Real Estate",
            "subcategory":"Real Estate Services",
            "type":"Services"
        }
    ],
    "sg:phone":"+1 919 467 5051",
    "sg:postcode":"27518",
    "sg:province":"NC",
    "sg:tags":[
        "management",
        "property"
    ],
    "sg:website":"www.cfsrdu.com",
    "wof:name":"Corporate Facility Services",
    "wof:placetype":"venue"
},
  "geometry": {"coordinates":[-78.734365,35.755274],"type":"Point"}
}