{
  "type": "Feature",
  "properties": {
    "iso:country":"US",
    "sg:address":"2101 Hickswood Rd",
    "sg:city":"High Point",
    "sg:classifiers":[
        {
            "category":"Professional",
            "subcategory":"Business Services",
            "type":"Services"
        }
    ],
    "sg:phone":"+1   ",
    "sg:postcode":"27265",
    "sg:province":"NC",
    "sg:tags":[
        "interior",
        "showroom",
        "design"
    ],
    "wof:name":"Showcase Design Associates",
    "wof:placetype":"venue"
},
  "geometry": {"coordinates":[-79.96702999999999,36.007206],"type":"Point"}
}