{
  "type": "Feature",
  "properties": {
    "addr:full":"8500 Ellisboro Rd Stokesdale NC 27357",
    "addr:housenumber":"8500",
    "addr:postcode":"27357",
    "addr:street":"Ellisboro Rd",
    "iso:country":"US",
    "sg:address":"8500 Ellisboro Rd",
    "sg:city":"Stokesdale",
    "sg:classifiers":[
        {
            "category":"Wholesale",
            "subcategory":"Plants",
            "type":"Manufacturing & Wholesale Goods"
        }
    ],
    "sg:phone":"+1 336 643 1017",
    "sg:postcode":"27357",
    "sg:province":"NC",
    "sg:tags":[
        "floral",
        "supply"
    ],
    "wof:name":"Summerfield Designs",
    "wof:placetype":"venue"
},
  "geometry": {"coordinates":[-79.98329,36.241651],"type":"Point"}
}