{
  "type": "Feature",
  "properties": {
    "iso:country":"US",
    "sg:address":"120 W Elizabeth St",
    "sg:city":"Clinton",
    "sg:classifiers":[
        {
            "category":"Professional",
            "subcategory":"Employment Agencies",
            "type":"Services"
        }
    ],
    "sg:phone":"+1 910 592 5438",
    "sg:postcode":"28328",
    "sg:province":"NC",
    "sg:tags":[
        "opportunity"
    ],
    "wof:name":"Temporary Connections",
    "wof:placetype":"venue"
},
  "geometry": {"coordinates":[-78.322872,34.997466],"type":"Point"}
}