{
  "type": "Feature",
  "properties": {
    "addr:full":"120 Belk Rd Mooresville NC 28115",
    "addr:housenumber":"120",
    "addr:postcode":"28115",
    "addr:street":"Belk Rd",
    "iso:country":"US",
    "sg:address":"120 Belk Rd",
    "sg:city":"Mooresville",
    "sg:classifiers":[
        {
            "category":"Building & Trades",
            "subcategory":"Construction",
            "type":"Services"
        }
    ],
    "sg:phone":"+1 704 663 8895",
    "sg:postcode":"28115",
    "sg:province":"NC",
    "sg:tags":[
        "builder",
        "stair"
    ],
    "wof:name":"Carolina Wood Stairs",
    "wof:placetype":"venue"
},
  "geometry": {"coordinates":[-80.829133,35.631418],"type":"Point"}
}