{
  "type": "Feature",
  "properties": {
    "iso:country":"US",
    "sg:address":"405 Main St",
    "sg:city":"Columbia",
    "sg:classifiers":[
        {
            "category":"Government",
            "subcategory":"Police Station",
            "type":"Public Place"
        }
    ],
    "sg:phone":"+1 252 796 2251",
    "sg:postcode":"27925",
    "sg:province":"NC",
    "sg:tags":[
        "sheriff"
    ],
    "wof:name":"Tyrrell County Sheriff's Ofc",
    "wof:placetype":"venue"
},
  "geometry": {"coordinates":[-76.250944,35.917824],"type":"Point"}
}