{
  "type": "Feature",
  "properties": {
    "addr:full":"1405 Old Oxford Rd Durham NC 27704",
    "addr:housenumber":"1405",
    "addr:postcode":"27704",
    "addr:street":"Old Oxford Rd",
    "iso:country":"US",
    "sg:address":"1405 Old Oxford Rd",
    "sg:city":"Durham",
    "sg:classifiers":[
        {
            "category":"Food & Beverages",
            "subcategory":"Bakery",
            "type":"Retail Goods"
        }
    ],
    "sg:phone":"+1 919 477 8844",
    "sg:postcode":"27704",
    "sg:province":"NC",
    "sg:tags":[
        "baker"
    ],
    "wof:name":"Pop's Bakery",
    "wof:placetype":"venue"
},
  "geometry": {"coordinates":[-78.871538,36.053995],"type":"Point"}
}