{
  "type": "Feature",
  "properties": {
    "addr:full":"2740 Wright Ave Salisbury NC 28147",
    "addr:housenumber":"2740",
    "addr:postcode":"28147",
    "addr:street":"Wright Ave",
    "iso:country":"US",
    "sg:address":"2740 Wright Ave",
    "sg:city":"Salisbury",
    "sg:classifiers":[
        {
            "category":"Professional",
            "type":"Services"
        }
    ],
    "sg:phone":"+1 704 642 0108",
    "sg:postcode":"28147",
    "sg:province":"NC",
    "wof:name":"Essential Ease Inc",
    "wof:placetype":"venue"
},
  "geometry": {"coordinates":[-80.565192,35.650333],"type":"Point"}
}