{
  "type": "Feature",
  "properties": {
    "iso:country":"US",
    "sg:address":"80 Harold Sluder Rd",
    "sg:city":"Alexander",
    "sg:classifiers":[
        {
            "category":"Building & Trades",
            "subcategory":"Plumbing",
            "type":"Services"
        }
    ],
    "sg:phone":"+1 828 683 6116",
    "sg:postcode":"28701",
    "sg:province":"NC",
    "sg:tags":[
        "tank",
        "septic"
    ],
    "wof:name":"Mike's Septic Tank Svc",
    "wof:placetype":"venue"
},
  "geometry": {"coordinates":[-82.619502,35.67446],"type":"Point"}
}