{
  "type": "Feature",
  "properties": {
    "addr:full":"119 W Virgil St Whiteville NC 28472",
    "addr:housenumber":"119",
    "addr:postcode":"28472",
    "addr:street":"W Virgil St",
    "iso:country":"US",
    "sg:address":"119 W Virgil St",
    "sg:city":"Whiteville",
    "sg:classifiers":[
        {
            "category":"Organizations",
            "subcategory":"Religious Organization",
            "type":"Services"
        }
    ],
    "sg:phone":"+1 910 642 7327",
    "sg:postcode":"28472",
    "sg:province":"NC",
    "sg:tags":[
        "church"
    ],
    "wof:name":"St Mark AME Zion Church",
    "wof:placetype":"venue"
},
  "geometry": {"coordinates":[-78.70504,34.32454],"type":"Point"}
}