{
  "type": "Feature",
  "properties": {
    "addr:full":"3803 Wrightsville Ave Wilmington NC 28403",
    "addr:housenumber":"3803",
    "addr:postcode":"28403",
    "addr:street":"Wrightsville Ave",
    "iso:country":"US",
    "sg:address":"3803 Wrightsville Ave",
    "sg:city":"Wilmington",
    "sg:classifiers":[
        {
            "category":"Professional",
            "subcategory":"Accounting & Tax Preparation",
            "type":"Services"
        }
    ],
    "sg:phone":"+1 910 794 2223",
    "sg:postcode":"28403",
    "sg:province":"NC",
    "sg:tags":[
        "accountant"
    ],
    "wof:name":"Robbins & Fisscher CPA",
    "wof:placetype":"venue"
},
  "geometry": {"coordinates":[-77.896325,34.219391],"type":"Point"}
}