{
  "type": "Feature",
  "properties": {
    "iso:country":"US",
    "sg:address":"9760 Andrew Jackson Hwy",
    "sg:city":"Laurel Hill",
    "sg:classifiers":[
        {
            "category":"Restaurant",
            "type":"Food & Drink"
        }
    ],
    "sg:menulink":"http://www.allmenus.com/nc/williamson/156260-hardees/menu/",
    "sg:phone":"+1 910 462 4444",
    "sg:postcode":"28351",
    "sg:province":"NC",
    "sg:tags":[
        "burger",
        "american"
    ],
    "wof:name":"Hardee's",
    "wof:placetype":"venue"
},
  "geometry": {"coordinates":[-79.54797499999999,34.808457],"type":"Point"}
}