{
  "type": "Feature",
  "properties": {
    "addr:full":"209 E Wade St Wadesboro NC 28170",
    "addr:housenumber":"209",
    "addr:postcode":"28170",
    "addr:street":"E Wade St",
    "iso:country":"US",
    "sg:address":"209 E Wade St",
    "sg:city":"Wadesboro",
    "sg:classifiers":[
        {
            "category":"Real Estate",
            "subcategory":"Real Estate Services",
            "type":"Services"
        }
    ],
    "sg:phone":"+1 704 694 2999",
    "sg:postcode":"28170",
    "sg:province":"NC",
    "sg:tags":[
        "company",
        "title"
    ],
    "wof:name":"Crown Title Corp",
    "wof:placetype":"venue"
},
  "geometry": {"coordinates":[-80.07539199999999,34.96628],"type":"Point"}
}