{
  "type": "Feature",
  "properties": {
    "iso:country":"US",
    "sg:address":"404 Westwood Ave",
    "sg:city":"High Point",
    "sg:classifiers":[
        {
            "category":"Health Services",
            "subcategory":"Doctor",
            "type":"Services"
        }
    ],
    "sg:phone":"+1 336 878 6789",
    "sg:postcode":"27262",
    "sg:province":"NC",
    "sg:tags":[
        "clinic"
    ],
    "wof:name":"Wound Care Ctr",
    "wof:placetype":"venue"
},
  "geometry": {"coordinates":[-80.014357,35.960003],"type":"Point"}
}