{
  "type": "Feature",
  "properties": {
    "iso:country":"US",
    "sg:address":"5445 Denburg Ln",
    "sg:city":"Raleigh",
    "sg:classifiers":[
        {
            "category":"Professional",
            "subcategory":"Business Services",
            "type":"Services"
        }
    ],
    "sg:phone":"+1   ",
    "sg:postcode":"27606",
    "sg:province":"NC",
    "wof:name":"Panther Technologies",
    "wof:placetype":"venue"
},
  "geometry": {"coordinates":[-78.77027099999999,35.706014],"type":"Point"}
}