{
  "type": "Feature",
  "properties": {
    "iso:country":"US",
    "sg:address":"9453 Old River Rd",
    "sg:city":"Burgaw",
    "sg:classifiers":[
        {
            "category":"Retail",
            "subcategory":"Repair Shop",
            "type":"Services"
        }
    ],
    "sg:phone":"+1 910 259 7071",
    "sg:postcode":"28425",
    "sg:province":"NC",
    "sg:tags":[
        "water",
        "equipment",
        "softening"
    ],
    "wof:name":"Quality Water Conditioning",
    "wof:placetype":"venue"
},
  "geometry": {"coordinates":[-77.863703,34.480967],"type":"Point"}
}