{
  "type": "Feature",
  "properties": {
    "addr:full":"2036 Foxhorn Rd Jacksonville NC 28546",
    "addr:housenumber":"2036",
    "addr:postcode":"28546",
    "addr:street":"Foxhorn Rd",
    "iso:country":"US",
    "sg:address":"2036 Foxhorn Rd",
    "sg:city":"Jacksonville",
    "sg:classifiers":[
        {
            "category":"Building & Trades",
            "subcategory":"Construction",
            "type":"Services"
        }
    ],
    "sg:phone":"+1 910 455 5909",
    "sg:postcode":"28546",
    "sg:province":"NC",
    "sg:tags":[
        "general",
        "contractor"
    ],
    "wof:name":"Allphase Construction",
    "wof:placetype":"venue"
},
  "geometry": {"coordinates":[-77.39136999999999,34.783003],"type":"Point"}
}