{
  "type": "Feature",
  "properties": {
    "addr:full":"637 Martin Luther King Jr Dr Greensboro NC 27406",
    "addr:housenumber":"637",
    "addr:postcode":"27406",
    "addr:street":"Martin Luther King Jr Dr",
    "iso:country":"US",
    "sg:address":"637 Martin Luther King Jr Dr",
    "sg:city":"Greensboro",
    "sg:classifiers":[
        {
            "category":"Autos & Motor Vehicles",
            "subcategory":"Fuel & Gas Station",
            "type":"Retail Goods"
        }
    ],
    "sg:phone":"+1 336 272 3343",
    "sg:postcode":"27406",
    "sg:province":"NC",
    "sg:tags":[
        "oil"
    ],
    "wof:name":"Texaco Crown Cntrl Petrol Corp",
    "wof:placetype":"venue"
},
  "geometry": {"coordinates":[-79.78532199999999,36.061051],"type":"Point"}
}