{
  "type": "Feature",
  "properties": {
    "addr:full":"738 Newman Rd New Bern NC 28562",
    "addr:housenumber":"738",
    "addr:postcode":"28562",
    "addr:street":"Newman Rd",
    "iso:country":"US",
    "sg:address":"738 Newman Rd",
    "sg:city":"New Bern",
    "sg:classifiers":[
        {
            "category":"Health Services",
            "subcategory":"Doctor",
            "type":"Services"
        }
    ],
    "sg:phone":"+1 252 633 2010",
    "sg:postcode":"28562",
    "sg:province":"NC",
    "sg:tags":[
        "physician",
        "surgeon"
    ],
    "wof:name":"Carolina Orthopedic Associates",
    "wof:placetype":"venue"
},
  "geometry": {"coordinates":[-77.096051,35.109678],"type":"Point"}
}