{
  "type": "Feature",
  "properties": {
    "addr:full":"4020 Old Pineville Rd Charlotte NC 28217",
    "addr:housenumber":"4020",
    "addr:postcode":"28217",
    "addr:street":"Old Pineville Rd",
    "iso:country":"US",
    "sg:address":"4020 Old Pineville Rd",
    "sg:city":"Charlotte",
    "sg:classifiers":[
        {
            "category":"Building & Trades",
            "subcategory":"Construction",
            "type":"Services"
        }
    ],
    "sg:phone":"+1 704 529 6661",
    "sg:postcode":"28217",
    "sg:province":"NC",
    "sg:tags":[
        "commercial",
        "industrial",
        "shopping",
        "center",
        "co"
    ],
    "sg:website":"www.myers-chapman.com",
    "wof:name":"Myers & Chapman Inc",
    "wof:placetype":"venue"
},
  "geometry": {"coordinates":[-80.876932,35.187906],"type":"Point"}
}