{
  "type": "Feature",
  "properties": {
    "iso:country":"US",
    "sg:address":"3729 Simmons-Patton Rd",
    "sg:city":"Jonesville",
    "sg:classifiers":[
        {
            "category":"Building & Trades",
            "subcategory":"Electrical",
            "type":"Services"
        }
    ],
    "sg:phone":"+1 336 367 6355",
    "sg:postcode":"28642",
    "sg:province":"NC",
    "sg:tags":[
        "electrical",
        "contractor"
    ],
    "wof:name":"Security First",
    "wof:placetype":"venue"
},
  "geometry": {"coordinates":[-80.757955,36.220721],"type":"Point"}
}