{
  "type": "Feature",
  "properties": {
    "addr:full":"945 E Andrews Ave Henderson NC 27536",
    "addr:housenumber":"945",
    "addr:postcode":"27536",
    "addr:street":"E Andrews Ave",
    "iso:country":"US",
    "sg:address":"945 E Andrews Ave",
    "sg:city":"Henderson",
    "sg:classifiers":[
        {
            "category":"Wholesale",
            "subcategory":"Painting Supplies",
            "type":"Manufacturing & Wholesale Goods"
        },
        {
            "category":"Home & Garden",
            "subcategory":"Garden Supply",
            "type":"Retail Goods"
        },
        {
            "category":"Wholesale",
            "subcategory":"Construction Materials",
            "type":"Manufacturing & Wholesale Goods"
        },
        {
            "category":"Home & Garden",
            "subcategory":"Hardware",
            "type":"Retail Goods"
        }
    ],
    "sg:phone":"+1 252 492 3166",
    "sg:postcode":"27536",
    "sg:province":"NC",
    "sg:tags":[
        "lawn",
        "paint",
        "equipment",
        "part",
        "plumbing",
        "fixtures",
        "store"
    ],
    "sg:website":"http://www.truevalue.com",
    "wof:name":"A & P True Value Hardware",
    "wof:placetype":"venue"
},
  "geometry": {"coordinates":[-78.39062300000001,36.323317],"type":"Point"}
}