{
  "type": "Feature",
  "properties": {
    "iso:country":"US",
    "sg:address":"3702 Hayden Dr",
    "sg:city":"Charlotte",
    "sg:classifiers":[
        {
            "category":"Building & Trades",
            "subcategory":"Landscaping Services",
            "type":"Services"
        }
    ],
    "sg:phone":"+1 704 494 8699",
    "sg:postcode":"28269",
    "sg:province":"NC",
    "sg:tags":[
        "lawn",
        "maintenance",
        "grounds"
    ],
    "wof:name":"Caliber One Lawn Systems",
    "wof:placetype":"venue"
},
  "geometry": {"coordinates":[-80.794293,35.340372],"type":"Point"}
}