{
  "type": "Feature",
  "properties": {
    "iso:country":"US",
    "sg:address":"4604 Dundas Dr",
    "sg:city":"Greensboro",
    "sg:classifiers":[
        {
            "category":"Professional",
            "subcategory":"Advertising",
            "type":"Services"
        }
    ],
    "sg:phone":"+1 336 852 1088",
    "sg:postcode":"27407",
    "sg:province":"NC",
    "wof:name":"Design Advertising",
    "wof:placetype":"venue"
},
  "geometry": {"coordinates":[-79.86036900000001,36.06573],"type":"Point"}
}