{
  "type": "Feature",
  "properties": {
    "addr:full":"307 W Tremont Ave Ste I Charlotte NC 28203",
    "addr:housenumber":"307",
    "addr:postcode":"28203",
    "addr:street":"W Tremont Ave Ste I",
    "iso:country":"US",
    "sg:address":"307 W Tremont Ave Ste I",
    "sg:city":"Charlotte",
    "sg:classifiers":[
        {
            "category":"Professional",
            "subcategory":"Business Services",
            "type":"Services"
        }
    ],
    "sg:phone":"+1 704 332 3731",
    "sg:postcode":"28203",
    "sg:province":"NC",
    "sg:tags":[
        "mail",
        "messenger",
        "shipping"
    ],
    "wof:name":"Mary Tobia Miller Interior Design",
    "wof:placetype":"venue"
},
  "geometry": {"coordinates":[-80.864384,35.210928],"type":"Point"}
}