{
  "type": "Feature",
  "properties": {
    "addr:full":"102 W Enterprise St Durham NC 27707",
    "addr:housenumber":"102",
    "addr:postcode":"27707",
    "addr:street":"W Enterprise St",
    "iso:country":"US",
    "sg:address":"102 W Enterprise St",
    "sg:city":"Durham",
    "sg:classifiers":[
        {
            "category":"Organizations",
            "subcategory":"Religious Organization",
            "type":"Services"
        }
    ],
    "sg:phone":"+1   ",
    "sg:postcode":"27707",
    "sg:province":"NC",
    "wof:name":"Happy Rock Unity Holy Church",
    "wof:placetype":"venue"
},
  "geometry": {"coordinates":[-78.906187,35.983794],"type":"Point"}
}