{
  "type": "Feature",
  "properties": {
    "addr:full":"1039 N Madison Blvd Roxboro NC 27573",
    "addr:housenumber":"1039",
    "addr:postcode":"27573",
    "addr:street":"N Madison Blvd",
    "iso:country":"US",
    "sg:address":"1039 N Madison Blvd",
    "sg:city":"Roxboro",
    "sg:classifiers":[
        {
            "category":"Restaurant",
            "type":"Food & Drink"
        }
    ],
    "sg:menulink":"http://www.allmenus.com/nc/roxboro/183433-kfc---kentucky-fried-chicken/menu/",
    "sg:phone":"+1 910 599 2210",
    "sg:postcode":"27573",
    "sg:province":"NC",
    "sg:tags":[
        "american",
        "chicken"
    ],
    "wof:name":"KFC - Kentucky Fried Chicken",
    "wof:placetype":"venue"
},
  "geometry": {"coordinates":[-78.973994,36.409492],"type":"Point"}
}