{
  "type": "Feature",
  "properties": {
    "addr:full":"5201 Woods Rd Kitty Hawk NC 27949",
    "addr:housenumber":"5201",
    "addr:postcode":"27949",
    "addr:street":"Woods Rd",
    "iso:country":"US",
    "sg:address":"5201 Woods Rd",
    "sg:city":"Kitty Hawk",
    "sg:classifiers":[
        {
            "category":"Professional",
            "subcategory":"Computer Services",
            "type":"Services"
        }
    ],
    "sg:phone":"+1 252 449 8830",
    "sg:postcode":"27949",
    "sg:province":"NC",
    "sg:tags":[
        "website",
        "design"
    ],
    "wof:name":"L K & Assoc",
    "wof:placetype":"venue"
},
  "geometry": {"coordinates":[-75.730137,36.090747],"type":"Point"}
}