{
  "type": "Feature",
  "properties": {
    "addr:full":"435 W High Ave High Point NC 27260",
    "addr:housenumber":"435",
    "addr:postcode":"27260",
    "addr:street":"W High Ave",
    "iso:country":"US",
    "sg:address":"435 W High Ave",
    "sg:city":"High Point",
    "sg:classifiers":[
        {
            "category":"Manufacturing",
            "subcategory":"Furniture",
            "type":"Manufacturing & Wholesale Goods"
        }
    ],
    "sg:phone":"+1 336 887 1992",
    "sg:postcode":"27260",
    "sg:province":"NC",
    "sg:tags":[
        "upholstered",
        "household",
        "mfg"
    ],
    "wof:name":"Show Room",
    "wof:placetype":"venue"
},
  "geometry": {"coordinates":[-80.011374,35.954054],"type":"Point"}
}