{
  "type": "Feature",
  "properties": {
    "addr:full":"1536 Holden Rd Youngsville NC 27596",
    "addr:housenumber":"1536",
    "addr:postcode":"27596",
    "addr:street":"Holden Rd",
    "iso:country":"US",
    "sg:address":"1536 Holden Rd",
    "sg:city":"Youngsville",
    "sg:classifiers":[
        {
            "category":"Professional",
            "subcategory":"Computer Services",
            "type":"Services"
        }
    ],
    "sg:phone":"+1   ",
    "sg:postcode":"27596",
    "sg:province":"NC",
    "sg:tags":[
        "related"
    ],
    "wof:name":"Talisyn Consulting",
    "wof:placetype":"venue"
},
  "geometry": {"coordinates":[-78.54129,36.0275],"type":"Point"}
}