{
  "type": "Feature",
  "properties": {
    "iso:country":"US",
    "sg:address":"1413 Deep Creek Rd",
    "sg:city":"Fayetteville",
    "sg:classifiers":[
        {
            "category":"Organizations",
            "subcategory":"Religious Organization",
            "type":"Services"
        }
    ],
    "sg:phone":"+1 910 483 7486",
    "sg:postcode":"28312",
    "sg:province":"NC",
    "sg:tags":[
        "church"
    ],
    "wof:name":"Good Hope Baptist Church",
    "wof:placetype":"venue"
},
  "geometry": {"coordinates":[-78.85317999999999,35.025678],"type":"Point"}
}