{
  "type": "Feature",
  "properties": {
    "addr:full":"2633 Leaflet Church Rd Broadway NC 27505",
    "addr:housenumber":"2633",
    "addr:postcode":"27505",
    "addr:street":"Leaflet Church Rd",
    "iso:country":"US",
    "sg:address":"2633 Leaflet Church Rd",
    "sg:city":"Broadway",
    "sg:classifiers":[
        {
            "category":"Building & Trades",
            "subcategory":"Construction",
            "type":"Services"
        }
    ],
    "sg:phone":"+1 919 258 6383",
    "sg:postcode":"27505",
    "sg:province":"NC",
    "sg:tags":[
        "contractor"
    ],
    "wof:name":"Mid Carolina Insulation",
    "wof:placetype":"venue"
},
  "geometry": {"coordinates":[-78.96798099999999,35.369961],"type":"Point"}
}