{
  "type": "Feature",
  "properties": {
    "addr:full":"220 US Hwy 264 Manteo NC 27954",
    "addr:housenumber":"220",
    "addr:postcode":"27954",
    "addr:street":"Us Hwy 264",
    "iso:country":"US",
    "sg:address":"220 US Hwy 264",
    "sg:city":"Manteo",
    "sg:classifiers":[
        {
            "category":"Real Estate",
            "subcategory":"Real Estate Agent",
            "type":"Services"
        }
    ],
    "sg:phone":"+1 252 473 6338",
    "sg:postcode":"27954",
    "sg:province":"NC",
    "wof:name":"Ware Realty & Construction",
    "wof:placetype":"venue"
},
  "geometry": {"coordinates":[-75.67438900000001,35.906013],"type":"Point"}
}