{
  "type": "Feature",
  "properties": {
    "addr:full":"456 State Hwy 47 Denton NC 27239",
    "addr:housenumber":"456",
    "addr:postcode":"27239",
    "addr:street":"State Hwy 47",
    "iso:country":"US",
    "sg:address":"456 State Hwy 47",
    "sg:city":"Denton",
    "sg:classifiers":[
        {
            "category":"Professional",
            "subcategory":"Accounting & Tax Preparation",
            "type":"Services"
        }
    ],
    "sg:phone":"+1 336 859 5556",
    "sg:postcode":"27239",
    "sg:province":"NC",
    "sg:tags":[
        "accountant"
    ],
    "wof:name":"BCB Mgmt & Bus Consltnts",
    "wof:placetype":"venue"
},
  "geometry": {"coordinates":[-80.10197599999999,35.628489],"type":"Point"}
}