{
  "type": "Feature",
  "properties": {
    "iso:country":"US",
    "sg:address":"142 Vanhook Rd",
    "sg:city":"Franklin",
    "sg:classifiers":[
        {
            "category":"Building & Trades",
            "subcategory":"Construction",
            "type":"Services"
        }
    ],
    "sg:phone":"+1 828 369 3534",
    "sg:postcode":"28734",
    "sg:province":"NC",
    "sg:tags":[
        "excavation",
        "contractor"
    ],
    "wof:name":"Sodbusters",
    "wof:placetype":"venue"
},
  "geometry": {"coordinates":[-83.35947899999999,35.115328],"type":"Point"}
}