{
  "type": "Feature",
  "properties": {
    "iso:country":"US",
    "sg:address":"917 Londonderry Dr",
    "sg:city":"High Point",
    "sg:classifiers":[
        {
            "category":"Shopping",
            "subcategory":"Catalog Store",
            "type":"Retail Goods"
        }
    ],
    "sg:phone":"+1 336 442 8191",
    "sg:postcode":"27265",
    "sg:province":"NC",
    "sg:tags":[
        "internet"
    ],
    "wof:name":"Gotdakickz",
    "wof:placetype":"venue"
},
  "geometry": {"coordinates":[-80.04817300000001,35.988467],"type":"Point"}
}