{
  "type": "Feature",
  "properties": {
    "addr:full":"1501 S Scales St Reidsville NC 27320",
    "addr:housenumber":"1501",
    "addr:postcode":"27320",
    "addr:street":"S Scales St",
    "iso:country":"US",
    "sg:address":"1501 S Scales St",
    "sg:city":"Reidsville",
    "sg:classifiers":[
        {
            "category":"Personal",
            "subcategory":"Beauty Salon",
            "type":"Services"
        }
    ],
    "sg:phone":"+1   ",
    "sg:postcode":"27320",
    "sg:province":"NC",
    "sg:tags":[
        "shop"
    ],
    "wof:name":"Nice Nails",
    "wof:placetype":"venue"
},
  "geometry": {"coordinates":[-79.663377,36.341341],"type":"Point"}
}