{
  "type": "Feature",
  "properties": {
    "addr:full":"481 E 2nd St Ayden NC 28513",
    "addr:housenumber":"481",
    "addr:postcode":"28513",
    "addr:street":"E 2Nd St",
    "iso:country":"US",
    "sg:address":"481 E 2nd St",
    "sg:city":"Ayden",
    "sg:classifiers":[
        {
            "category":"Professional",
            "type":"Services"
        }
    ],
    "sg:phone":"+1 252 746 2834",
    "sg:postcode":"28513",
    "sg:province":"NC",
    "wof:name":"Allstar Motors Of Ayden",
    "wof:placetype":"venue"
},
  "geometry": {"coordinates":[-77.411928,35.47179],"type":"Point"}
}