{
  "type": "Feature",
  "properties": {
    "iso:country":"US",
    "sg:address":"6 Vance St",
    "sg:city":"Lexington",
    "sg:classifiers":[
        {
            "category":"Social Services",
            "type":"Services"
        }
    ],
    "sg:phone":"+1 336 248 2407",
    "sg:postcode":"27292",
    "sg:province":"NC",
    "wof:name":"Assoction For Rtarded Citizens",
    "wof:placetype":"venue"
},
  "geometry": {"coordinates":[-80.2581,35.827888],"type":"Point"}
}