{
  "type": "Feature",
  "properties": {
    "addr:full":"1922 Firetower Rd Louisburg NC 27549",
    "addr:housenumber":"1922",
    "addr:postcode":"27549",
    "addr:street":"Firetower Rd",
    "iso:country":"US",
    "sg:address":"1922 Firetower Rd",
    "sg:city":"Louisburg",
    "sg:classifiers":[
        {
            "category":"Retail",
            "subcategory":"Auto Repair",
            "type":"Services"
        }
    ],
    "sg:phone":"+1 919 496 5535",
    "sg:postcode":"27549",
    "sg:province":"NC",
    "sg:tags":[
        "body",
        "automobile",
        "painting"
    ],
    "wof:name":"Lee's Auto Refinishing",
    "wof:placetype":"venue"
},
  "geometry": {"coordinates":[-78.20540099999999,36.126251],"type":"Point"}
}