{
  "type": "Feature",
  "properties": {
    "iso:country":"US",
    "sg:address":"297 N Forest Ln NW",
    "sg:city":"Calabash",
    "sg:classifiers":[
        {
            "category":"Building & Trades",
            "subcategory":"Plumbing",
            "type":"Services"
        }
    ],
    "sg:phone":"+1 910 579 5358",
    "sg:postcode":"28467",
    "sg:province":"NC",
    "sg:tags":[
        "septic"
    ],
    "wof:name":"Drew Smith Svc",
    "wof:placetype":"venue"
},
  "geometry": {"coordinates":[-78.58990799999999,33.909288],"type":"Point"}
}