{
  "type": "Feature",
  "properties": {
    "iso:country":"US",
    "sg:address":"16562 US Hwy 52",
    "sg:city":"Norwood",
    "sg:classifiers":[
        {
            "category":"Organizations",
            "subcategory":"Religious Organization",
            "type":"Services"
        }
    ],
    "sg:phone":"+1 704 982 2811",
    "sg:postcode":"28128",
    "sg:province":"NC",
    "sg:tags":[
        "church"
    ],
    "wof:name":"Porter Baptist Church Inc",
    "wof:placetype":"venue"
},
  "geometry": {"coordinates":[-80.16839299999999,35.271294],"type":"Point"}
}