{
  "type": "Feature",
  "properties": {
    "addr:full":"1406 Christian Ave Durham NC 27705",
    "addr:housenumber":"1406",
    "addr:postcode":"27705",
    "addr:street":"Christian Ave",
    "iso:country":"US",
    "sg:address":"1406 Christian Ave",
    "sg:city":"Durham",
    "sg:classifiers":[
        {
            "category":"Retail",
            "subcategory":"Auto Repair",
            "type":"Services"
        }
    ],
    "sg:phone":"+1 919 382 0660",
    "sg:postcode":"27705",
    "sg:province":"NC",
    "sg:tags":[
        "body"
    ],
    "wof:name":"Maaco Auto Painting",
    "wof:placetype":"venue"
},
  "geometry": {"coordinates":[-78.952065,36.024218],"type":"Point"}
}