{
  "type": "Feature",
  "properties": {
    "addr:full":"119 W Dolphin St Siler City NC 27344",
    "addr:housenumber":"119",
    "addr:postcode":"27344",
    "addr:street":"W Dolphin St",
    "iso:country":"US",
    "sg:address":"119 W Dolphin St",
    "sg:city":"Siler City",
    "sg:phone":"+1 919 742 4165",
    "sg:postcode":"27344",
    "sg:province":"NC",
    "sg:tags":[
        "oil"
    ],
    "wof:name":"S & H Oil Co",
    "wof:placetype":"venue"
},
  "geometry": {"coordinates":[-79.461962,35.719268],"type":"Point"}
}