{
  "type": "Feature",
  "properties": {
    "iso:country":"US",
    "sg:address":"301 Berry Hill Dr",
    "sg:city":"Raleigh",
    "sg:classifiers":[
        {
            "category":"Professional",
            "subcategory":"Business Services",
            "type":"Services"
        }
    ],
    "sg:phone":"+1   ",
    "sg:postcode":"27615",
    "sg:province":"NC",
    "wof:name":"D Gene Stallings & Associates",
    "wof:placetype":"venue"
},
  "geometry": {"coordinates":[-78.64191,35.903859],"type":"Point"}
}