{
  "type": "Feature",
  "properties": {
    "addr:full":"10420 Centrum Pkwy Pineville NC 28134",
    "addr:housenumber":"10420",
    "addr:postcode":"28134",
    "addr:street":"Centrum Pkwy",
    "iso:country":"US",
    "sg:address":"10420 Centrum Pkwy",
    "sg:city":"Pineville",
    "sg:classifiers":[
        {
            "category":"Shopping",
            "subcategory":"Clothing, Apparel, & Fashions",
            "type":"Retail Goods"
        }
    ],
    "sg:phone":"+1 704 544 2228",
    "sg:postcode":"28134",
    "sg:province":"NC",
    "sg:tags":[
        "furnishing"
    ],
    "wof:name":"S & K Famous Brands Menswear",
    "wof:placetype":"venue"
},
  "geometry": {"coordinates":[-80.87663499999999,35.091754],"type":"Point"}
}