{
  "type": "Feature",
  "properties": {
    "iso:country":"US",
    "sg:address":"300 W Windsor St",
    "sg:city":"Monroe",
    "sg:classifiers":[
        {
            "category":"Insurance",
            "subcategory":"Insurance Agent",
            "type":"Services"
        }
    ],
    "sg:phone":"+1 704 289 2995",
    "sg:postcode":"28112",
    "sg:province":"NC",
    "sg:tags":[
        "agency",
        "full"
    ],
    "wof:name":"First Charter Insurance Svcs",
    "wof:placetype":"venue"
},
  "geometry": {"coordinates":[-80.55104799999999,34.98128],"type":"Point"}
}