{
  "type": "Feature",
  "properties": {
    "iso:country":"US",
    "sg:address":"1204 Deboy St",
    "sg:city":"Raleigh",
    "sg:classifiers":[
        {
            "category":"Health Services",
            "subcategory":"Doctor",
            "type":"Services"
        }
    ],
    "sg:phone":"+1   ",
    "sg:postcode":"27606",
    "sg:province":"NC",
    "sg:tags":[
        "medical"
    ],
    "wof:name":"Animal Dermatology & Alle",
    "wof:placetype":"venue"
},
  "geometry": {"coordinates":[-78.70853200000001,35.780714],"type":"Point"}
}