{
  "type": "Feature",
  "properties": {
    "iso:country":"US",
    "sg:address":"2834 Mount Hope Church Rd",
    "sg:city":"Julian",
    "sg:classifiers":[
        {
            "category":"Building & Trades",
            "subcategory":"Construction",
            "type":"Services"
        }
    ],
    "sg:phone":"+1 336 697 0963",
    "sg:postcode":"27283",
    "sg:province":"NC",
    "wof:name":"Owen Contracting Co Inc",
    "wof:placetype":"venue"
},
  "geometry": {"coordinates":[-79.596873,35.990897],"type":"Point"}
}