{
  "type": "Feature",
  "properties": {
    "iso:country":"US",
    "sg:address":"6824 E Independence Blvd",
    "sg:city":"Charlotte",
    "sg:classifiers":[
        {
            "category":"Autos & Motor Vehicles",
            "subcategory":"Automobile Sales",
            "type":"Retail Goods"
        }
    ],
    "sg:phone":"+1 704 531 3344",
    "sg:postcode":"28227",
    "sg:province":"NC",
    "sg:tags":[
        "car",
        "dealer"
    ],
    "sg:website":"www.hendrickporsche.com",
    "wof:name":"Hendrick Porsche",
    "wof:placetype":"venue"
},
  "geometry": {"coordinates":[-80.744416,35.170034],"type":"Point"}
}