{
  "type": "Feature",
  "properties": {
    "addr:full":"6416 Brookstone Ln Fayetteville NC 28314",
    "addr:housenumber":"6416",
    "addr:postcode":"28314",
    "addr:street":"Brookstone Ln",
    "iso:country":"US",
    "sg:address":"6416 Brookstone Ln",
    "sg:city":"Fayetteville",
    "sg:classifiers":[
        {
            "category":"Retail",
            "subcategory":"Veterinary Services",
            "type":"Services"
        }
    ],
    "sg:phone":"+1 910 487 5013",
    "sg:postcode":"28314",
    "sg:province":"NC",
    "sg:tags":[
        "veterinarian"
    ],
    "wof:name":"Cliffdale Animal Hospital Inc",
    "wof:placetype":"venue"
},
  "geometry": {"coordinates":[-79.010164,35.060964],"type":"Point"}
}