{
  "type": "Feature",
  "properties": {
    "iso:country":"US",
    "sg:address":"1503 S Battleground Ave",
    "sg:city":"Kings Mountain",
    "sg:classifiers":[
        {
            "category":"Manufacturing",
            "subcategory":"Retail Goods",
            "type":"Manufacturing & Wholesale Goods"
        }
    ],
    "sg:phone":"+1 704 739 3086",
    "sg:postcode":"28086",
    "sg:province":"NC",
    "sg:tags":[
        "assembly",
        "fabricating"
    ],
    "wof:name":"Fabrication Shop",
    "wof:placetype":"venue"
},
  "geometry": {"coordinates":[-81.389832,35.201455],"type":"Point"}
}