{
  "type": "Feature",
  "properties": {
    "addr:full":"11168 Nc Highway 87 S Eden NC 27288",
    "addr:housenumber":"11168",
    "addr:postcode":"27288",
    "addr:street":"Nc Highway 87 S",
    "iso:country":"US",
    "sg:address":"11168 Nc Highway 87 S",
    "sg:city":"Eden",
    "sg:classifiers":[
        {
            "category":"Building & Trades",
            "subcategory":"Construction",
            "type":"Services"
        }
    ],
    "sg:phone":"+1 336 623 5773",
    "sg:postcode":"27288",
    "sg:province":"NC",
    "sg:tags":[
        "system",
        "contractor",
        "air conditioning"
    ],
    "wof:name":"Donnie Scearce Heating Cl",
    "wof:placetype":"venue"
},
  "geometry": {"coordinates":[-79.76652199999999,36.45077],"type":"Point"}
}