{
  "type": "Feature",
  "properties": {
    "iso:country":"US",
    "sg:address":"4106 Old Cherry Point Rd",
    "sg:city":"New Bern",
    "sg:classifiers":[
        {
            "category":"Building & Trades",
            "subcategory":"Landscaping Services",
            "type":"Services"
        }
    ],
    "sg:phone":"+1 252 637 5883",
    "sg:postcode":"28560",
    "sg:province":"NC",
    "wof:name":"Williams Sod Farm",
    "wof:placetype":"venue"
},
  "geometry": {"coordinates":[-76.998368,35.035758],"type":"Point"}
}