{
  "type": "Feature",
  "properties": {
    "iso:country":"US",
    "sg:address":"307 W Spring St",
    "sg:city":"Lucama",
    "sg:classifiers":[
        {
            "category":"Organizations",
            "subcategory":"Religious Organization",
            "type":"Services"
        }
    ],
    "sg:phone":"+1 252 239 1098",
    "sg:postcode":"27851",
    "sg:province":"NC",
    "sg:tags":[
        "church"
    ],
    "wof:name":"Lucama Church Of God",
    "wof:placetype":"venue"
},
  "geometry": {"coordinates":[-78.012075,35.642964],"type":"Point"}
}