{
  "type": "Feature",
  "properties": {
    "addr:full":"1310 Westover Ter Greensboro NC 27408",
    "addr:housenumber":"1310",
    "addr:postcode":"27408",
    "addr:street":"Westover Ter",
    "iso:country":"US",
    "sg:address":"1310 Westover Ter",
    "sg:city":"Greensboro",
    "sg:classifiers":[
        {
            "category":"Travel",
            "subcategory":"Travel Agent",
            "type":"Entertainment"
        }
    ],
    "sg:phone":"+1 336 373 1066",
    "sg:postcode":"27408",
    "sg:province":"NC",
    "sg:tags":[
        "passenger",
        "agency",
        "transportation",
        "arrangement"
    ],
    "wof:name":"Aladdin Travel & Mtg Planners",
    "wof:placetype":"venue"
},
  "geometry": {"coordinates":[-79.81360599999999,36.088175],"type":"Point"}
}