{
  "type": "Feature",
  "properties": {
    "addr:full":"2321 S Tryon St Charlotte NC 28203",
    "addr:housenumber":"2321",
    "addr:postcode":"28203",
    "addr:street":"S Tryon St",
    "iso:country":"US",
    "sg:address":"2321 S Tryon St",
    "sg:city":"Charlotte",
    "sg:classifiers":[
        {
            "category":"Building & Trades",
            "subcategory":"Electrical",
            "type":"Services"
        }
    ],
    "sg:phone":"+1 704 333 7149",
    "sg:postcode":"28203",
    "sg:province":"NC",
    "sg:tags":[
        "electric",
        "industrial",
        "contractors-commercial",
        "contractor"
    ],
    "wof:name":"Interstate Electric Co",
    "wof:placetype":"venue"
},
  "geometry": {"coordinates":[-80.867599,35.20789],"type":"Point"}
}