{
  "type": "Feature",
  "properties": {
    "addr:full":"220 11th Ave NW Hickory NC 28601",
    "addr:housenumber":"220",
    "addr:postcode":"28601",
    "addr:street":"11Th Ave Nw",
    "iso:country":"US",
    "sg:address":"220 11th Ave NW",
    "sg:city":"Hickory",
    "sg:classifiers":[
        {
            "category":"Health Services",
            "subcategory":"Doctor",
            "type":"Services"
        }
    ],
    "sg:phone":"+1   ",
    "sg:postcode":"28601",
    "sg:province":"NC",
    "sg:tags":[
        "medical"
    ],
    "wof:name":"John E Wise MD",
    "wof:placetype":"venue"
},
  "geometry": {"coordinates":[-81.34099399999999,35.746972],"type":"Point"}
}