{
  "type": "Feature",
  "properties": {
    "iso:country":"US",
    "sg:address":"4201 Murrayhill Rd",
    "sg:city":"Charlotte",
    "sg:classifiers":[
        {
            "category":"Building & Trades",
            "subcategory":"Electrical",
            "type":"Services"
        }
    ],
    "sg:phone":"+1 704 527 6464",
    "sg:postcode":"28209",
    "sg:province":"NC",
    "sg:tags":[
        "electrician"
    ],
    "sg:website":"http://ace-electric.com",
    "wof:name":"Ace Electric Company",
    "wof:placetype":"venue"
},
  "geometry": {"coordinates":[-80.86690900000001,35.180492],"type":"Point"}
}