{
  "type": "Feature",
  "properties": {
    "addr:full":"123 Mariner Pointe Ln Mooresville NC 28117",
    "addr:housenumber":"123",
    "addr:postcode":"28117",
    "addr:street":"Mariner Pointe Ln",
    "iso:country":"US",
    "sg:address":"123 Mariner Pointe Ln",
    "sg:city":"Mooresville",
    "sg:classifiers":[
        {
            "category":"Building & Trades",
            "subcategory":"Construction",
            "type":"Services"
        }
    ],
    "sg:phone":"+1 704 662 9497",
    "sg:postcode":"28117",
    "sg:province":"NC",
    "sg:tags":[
        "house"
    ],
    "wof:name":"Gemini Homes Inc",
    "wof:placetype":"venue"
},
  "geometry": {"coordinates":[-80.938553,35.603337],"type":"Point"}
}