{
  "type": "Feature",
  "properties": {
    "addr:full":"8090 Claude Gilbert Trl Denver NC 28037",
    "addr:housenumber":"8090",
    "addr:postcode":"28037",
    "addr:street":"Claude Gilbert Trl",
    "iso:country":"US",
    "sg:address":"8090 Claude Gilbert Trl",
    "sg:city":"Denver",
    "sg:classifiers":[
        {
            "category":"Building & Trades",
            "subcategory":"Cleaning & Sanitation",
            "type":"Services"
        }
    ],
    "sg:phone":"+1 704 489 8709",
    "sg:postcode":"28037",
    "sg:province":"NC",
    "sg:tags":[
        "maintenance"
    ],
    "wof:name":"Facilitec Corp",
    "wof:placetype":"venue"
},
  "geometry": {"coordinates":[-80.977412,35.476923],"type":"Point"}
}