{
  "type": "Feature",
  "properties": {
    "addr:full":"3605 Mansfield Dr Rocky Mount NC 27803",
    "addr:housenumber":"3605",
    "addr:postcode":"27803",
    "addr:street":"Mansfield Dr",
    "iso:country":"US",
    "sg:address":"3605 Mansfield Dr",
    "sg:city":"Rocky Mount",
    "sg:classifiers":[
        {
            "category":"Restaurant",
            "type":"Food & Drink"
        }
    ],
    "sg:phone":"+1 252 937 2578",
    "sg:postcode":"27803",
    "sg:province":"NC",
    "sg:tags":[
        "franchised",
        "fast"
    ],
    "wof:name":"Hardees",
    "wof:placetype":"venue"
},
  "geometry": {"coordinates":[-77.858474,35.952419],"type":"Point"}
}