{
  "type": "Feature",
  "properties": {
    "iso:country":"US",
    "sg:address":"4516 Waterbury Rd",
    "sg:city":"Raleigh",
    "sg:classifiers":[
        {
            "category":"Shopping",
            "type":"Retail Goods"
        }
    ],
    "sg:phone":"+1 919 363 8968",
    "sg:postcode":"27604",
    "sg:province":"NC",
    "sg:tags":[
        "orthopedic",
        "appliance"
    ],
    "wof:name":"Hawley Maker",
    "wof:placetype":"venue"
},
  "geometry": {"coordinates":[-78.584548,35.84278],"type":"Point"}
}