{
  "type": "Feature",
  "properties": {
    "iso:country":"US",
    "sg:address":"1431 Berriedale Dr",
    "sg:city":"Fayetteville",
    "sg:classifiers":[
        {
            "category":"Local Transit",
            "type":"Transportation"
        }
    ],
    "sg:phone":"+1 910 867 0344",
    "sg:postcode":"28304",
    "sg:province":"NC",
    "sg:tags":[
        "passenger"
    ],
    "wof:name":"Imperial Lmsne Svc Fyetteville",
    "wof:placetype":"venue"
},
  "geometry": {"coordinates":[-78.99035000000001,35.033927],"type":"Point"}
}