{
  "type": "Feature",
  "properties": {
    "iso:country":"US",
    "sg:address":"616 State Rd 54 Bus",
    "sg:city":"Carrboro",
    "sg:classifiers":[
        {
            "category":"Manufacturing",
            "subcategory":"Building Materials",
            "type":"Manufacturing & Wholesale Goods"
        }
    ],
    "sg:phone":"+1 919 967 8988",
    "sg:postcode":"27510",
    "sg:province":"NC",
    "sg:website":"www.woodindustry.com",
    "wof:name":"Cleora Sterling Corp",
    "wof:placetype":"venue"
},
  "geometry": {"coordinates":[-79.07994600000001,35.91386],"type":"Point"}
}