{
  "type": "Feature",
  "properties": {
    "addr:full":"7710 Meadowdale Ln Charlotte NC 28212",
    "addr:housenumber":"7710",
    "addr:postcode":"28212",
    "addr:street":"Meadowdale Ln",
    "iso:country":"US",
    "sg:address":"7710 Meadowdale Ln",
    "sg:city":"Charlotte",
    "sg:classifiers":[
        {
            "category":"Real Estate",
            "subcategory":"Real Estate Agent",
            "type":"Services"
        }
    ],
    "sg:phone":"+1 704 569 4101",
    "sg:postcode":"28212",
    "sg:province":"NC",
    "wof:name":"Rl Acree Development",
    "wof:placetype":"venue"
},
  "geometry": {"coordinates":[-80.733468,35.189191],"type":"Point"}
}