{
  "type": "Feature",
  "properties": {
    "addr:full":"2110 Statesville Hwy Mooresville NC 28115",
    "addr:housenumber":"2110",
    "addr:postcode":"28115",
    "addr:street":"Statesville Hwy",
    "iso:country":"US",
    "sg:address":"2110 Statesville Hwy",
    "sg:city":"Mooresville",
    "sg:classifiers":[
        {
            "category":"Building & Trades",
            "subcategory":"Landscaping Services",
            "type":"Services"
        }
    ],
    "sg:phone":"+1 704 660 9830",
    "sg:postcode":"28115",
    "sg:province":"NC",
    "sg:tags":[
        "landscape",
        "contractor"
    ],
    "wof:name":"PRL Enterprises",
    "wof:placetype":"venue"
},
  "geometry": {"coordinates":[-80.82454199999999,35.618258],"type":"Point"}
}