{
  "type": "Feature",
  "properties": {
    "iso:country":"US",
    "sg:address":"2241 Rockford St",
    "sg:city":"Mount Airy",
    "sg:classifiers":[
        {
            "category":"Personal",
            "subcategory":"Beauty Salon",
            "type":"Services"
        }
    ],
    "sg:phone":"+1   ",
    "sg:postcode":"27030",
    "sg:province":"NC",
    "sg:tags":[
        "shop"
    ],
    "wof:name":"Nails Salon",
    "wof:placetype":"venue"
},
  "geometry": {"coordinates":[-80.621111,36.473262],"type":"Point"}
}