{
  "type": "Feature",
  "properties": {
    "addr:full":"127 Mill St Forest City NC 28043",
    "addr:housenumber":"127",
    "addr:postcode":"28043",
    "addr:street":"Mill St",
    "iso:country":"US",
    "sg:address":"127 Mill St",
    "sg:city":"Forest City",
    "sg:classifiers":[
        {
            "category":"Organizations",
            "subcategory":"Religious Organization",
            "type":"Services"
        }
    ],
    "sg:phone":"+1 828 247 0772",
    "sg:postcode":"28043",
    "sg:province":"NC",
    "sg:tags":[
        "church"
    ],
    "wof:name":"Greater New Hope Family Miracl",
    "wof:placetype":"venue"
},
  "geometry": {"coordinates":[-81.854674,35.310426],"type":"Point"}
}