{
  "type": "Feature",
  "properties": {
    "iso:country":"US",
    "sg:address":"708 Pembroke Rd",
    "sg:city":"Greensboro",
    "sg:classifiers":[
        {
            "category":"Restaurant",
            "type":"Food & Drink"
        }
    ],
    "sg:phone":"+1 336 299 9315",
    "sg:postcode":"27408",
    "sg:province":"NC",
    "sg:tags":[
        "eating"
    ],
    "wof:name":"Tex & Shirleys Restaurant",
    "wof:placetype":"venue"
},
  "geometry": {"coordinates":[-79.832848,36.087154],"type":"Point"}
}