{
  "type": "Feature",
  "properties": {
    "addr:full":"19040 Old Beatty Ford Rd Gold Hill NC 28071",
    "addr:housenumber":"19040",
    "addr:postcode":"28071",
    "addr:street":"Old Beatty Ford Rd",
    "iso:country":"US",
    "sg:address":"19040 Old Beatty Ford Rd",
    "sg:city":"Gold Hill",
    "sg:classifiers":[
        {
            "category":"Building & Trades",
            "subcategory":"Construction",
            "type":"Services"
        }
    ],
    "sg:phone":"+1 704 209 6036",
    "sg:postcode":"28071",
    "sg:province":"NC",
    "sg:tags":[
        "contractor"
    ],
    "wof:name":"R & R Welding",
    "wof:placetype":"venue"
},
  "geometry": {"coordinates":[-80.290559,35.51199],"type":"Point"}
}