{
  "type": "Feature",
  "properties": {
    "iso:country":"US",
    "sg:address":"13418 Spiveys Corner Hwy",
    "sg:city":"Roseboro",
    "sg:classifiers":[
        {
            "category":"Farming",
            "subcategory":"Dairy Farm",
            "type":"Manufacturing & Wholesale Goods"
        }
    ],
    "sg:phone":"+1 910 567 6747",
    "sg:postcode":"28382",
    "sg:province":"NC",
    "wof:name":"J T & L Dairy",
    "wof:placetype":"venue"
},
  "geometry": {"coordinates":[-78.464358,35.150399],"type":"Point"}
}