{
  "type": "Feature",
  "properties": {
    "iso:country":"US",
    "sg:address":"5254 Roxboro Rd",
    "sg:city":"Durham",
    "sg:classifiers":[
        {
            "category":"Retail",
            "subcategory":"Auto Repair",
            "type":"Services"
        }
    ],
    "sg:phone":"+1 919 479 1652",
    "sg:postcode":"27712",
    "sg:province":"NC",
    "sg:tags":[
        "transmission",
        "general"
    ],
    "wof:name":"Accurate Transmission Center",
    "wof:placetype":"venue"
},
  "geometry": {"coordinates":[-78.908872,36.072999],"type":"Point"}
}