{
  "type": "Feature",
  "properties": {
    "addr:full":"101 Palmwood Ct Cary NC 27519",
    "addr:housenumber":"101",
    "addr:postcode":"27519",
    "addr:street":"Palmwood Ct",
    "iso:country":"US",
    "sg:address":"101 Palmwood Ct",
    "sg:city":"Cary",
    "sg:classifiers":[
        {
            "category":"Real Estate",
            "subcategory":"Real Estate Agent",
            "type":"Services"
        }
    ],
    "sg:phone":"+1 919 469 1293",
    "sg:postcode":"27519",
    "sg:province":"NC",
    "wof:name":"Fonville Morisey Realtors",
    "wof:placetype":"venue"
},
  "geometry": {"coordinates":[-78.90288099999999,35.819222],"type":"Point"}
}