{
  "type": "Feature",
  "properties": {
    "addr:full":"169 Elk Mountain Rd Asheville NC 28804",
    "addr:housenumber":"169",
    "addr:postcode":"28804",
    "addr:street":"Elk Mountain Rd",
    "iso:country":"US",
    "sg:address":"169 Elk Mountain Rd",
    "sg:city":"Asheville",
    "sg:classifiers":[
        {
            "category":"Building & Trades",
            "subcategory":"Plumbing",
            "type":"Services"
        }
    ],
    "sg:phone":"+1 828 253 3621",
    "sg:postcode":"28804",
    "sg:province":"NC",
    "sg:tags":[
        "heating",
        "contractor"
    ],
    "wof:name":"Bolton Construction & Svc",
    "wof:placetype":"venue"
},
  "geometry": {"coordinates":[-82.59067400000001,35.633981],"type":"Point"}
}