{
  "type": "Feature",
  "properties": {
    "iso:country":"US",
    "sg:address":"411 Apple Ridge Rd",
    "sg:city":"Greensboro",
    "sg:classifiers":[
        {
            "category":"Retail",
            "subcategory":"Car Wash",
            "type":"Services"
        }
    ],
    "sg:phone":"+1   ",
    "sg:postcode":"27406",
    "sg:province":"NC",
    "sg:tags":[
        "carwash"
    ],
    "wof:name":"Fullers Mobile Detailing",
    "wof:placetype":"venue"
},
  "geometry": {"coordinates":[-79.809889,36.019519],"type":"Point"}
}