{
  "type": "Feature",
  "properties": {
    "addr:full":"416 E Fleming Dr Morganton NC 28655",
    "addr:housenumber":"416",
    "addr:postcode":"28655",
    "addr:street":"E Fleming Dr",
    "iso:country":"US",
    "sg:address":"416 E Fleming Dr",
    "sg:city":"Morganton",
    "sg:classifiers":[
        {
            "category":"Wholesale",
            "subcategory":"Construction Materials",
            "type":"Manufacturing & Wholesale Goods"
        }
    ],
    "sg:phone":"+1 828 437 9888",
    "sg:postcode":"28655",
    "sg:province":"NC",
    "sg:tags":[
        "lumber"
    ],
    "wof:name":"Stroud's Discount Lumber",
    "wof:placetype":"venue"
},
  "geometry": {"coordinates":[-81.660358,35.748678],"type":"Point"}
}