{
  "type": "Feature",
  "properties": {
    "addr:full":"11007 Dekalb Pl Charlotte NC 28262",
    "addr:housenumber":"11007",
    "addr:postcode":"28262",
    "addr:street":"Dekalb Pl",
    "iso:country":"US",
    "sg:address":"11007 Dekalb Pl",
    "sg:city":"Charlotte",
    "sg:classifiers":[
        {
            "category":"Manufacturing",
            "subcategory":"Retail Goods",
            "type":"Manufacturing & Wholesale Goods"
        }
    ],
    "sg:phone":"+1 704 594 9473",
    "sg:postcode":"28262",
    "sg:province":"NC",
    "sg:tags":[
        "product",
        "mfg"
    ],
    "wof:name":"Barbermate By Dupont LLC",
    "wof:placetype":"venue"
},
  "geometry": {"coordinates":[-80.699388,35.328318],"type":"Point"}
}