{
  "type": "Feature",
  "properties": {
    "addr:full":"301 W 13th St Salisbury NC 28144",
    "addr:housenumber":"301",
    "addr:postcode":"28144",
    "addr:street":"W 13Th St",
    "iso:country":"US",
    "sg:address":"301 W 13th St",
    "sg:city":"Salisbury",
    "sg:classifiers":[
        {
            "category":"Building & Trades",
            "subcategory":"Landscaping Services",
            "type":"Services"
        }
    ],
    "sg:phone":"+1 704 636 8836",
    "sg:postcode":"28144",
    "sg:province":"NC",
    "wof:name":"Thomas Gillis Maintanance",
    "wof:placetype":"venue"
},
  "geometry": {"coordinates":[-80.45823799999999,35.68143],"type":"Point"}
}