{
  "type": "Feature",
  "properties": {
    "addr:full":"43 Mulberry Ct Hendersonville NC 28739",
    "addr:housenumber":"43",
    "addr:postcode":"28739",
    "addr:street":"Mulberry Ct",
    "iso:country":"US",
    "sg:address":"43 Mulberry Ct",
    "sg:city":"Hendersonville",
    "sg:classifiers":[
        {
            "category":"Banks & Credit Unions",
            "subcategory":"Investment Brokerage",
            "type":"Services"
        }
    ],
    "sg:phone":"+1 828 692 0061",
    "sg:postcode":"28739",
    "sg:province":"NC",
    "sg:tags":[
        "advisory"
    ],
    "wof:name":"Linder Financial Services",
    "wof:placetype":"venue"
},
  "geometry": {"coordinates":[-82.503929,35.302609],"type":"Point"}
}