{
  "type": "Feature",
  "properties": {
    "addr:full":"435 Dolley Madison Rd Greensboro NC 27410",
    "addr:housenumber":"435",
    "addr:postcode":"27410",
    "addr:street":"Dolley Madison Rd",
    "iso:country":"US",
    "sg:address":"435 Dolley Madison Rd",
    "sg:city":"Greensboro",
    "sg:classifiers":[
        {
            "category":"Shopping",
            "subcategory":"Used Merchandise",
            "type":"Retail Goods"
        },
        {
            "category":"Shopping",
            "subcategory":"Department Store",
            "type":"Retail Goods"
        }
    ],
    "sg:phone":"+1 336 855 9914",
    "sg:postcode":"27410",
    "sg:province":"NC",
    "sg:tags":[
        "clothing",
        "furniture"
    ],
    "sg:website":"www.ouac.com",
    "wof:name":"Once Upon A Child",
    "wof:placetype":"venue"
},
  "geometry": {"coordinates":[-79.88562400000001,36.08546],"type":"Point"}
}