{
  "type": "Feature",
  "properties": {
    "addr:full":"1341 Main St Bryson City NC 28713",
    "addr:housenumber":"1341",
    "addr:postcode":"28713",
    "addr:street":"Main St",
    "iso:country":"US",
    "sg:address":"1341 Main St",
    "sg:city":"Bryson City",
    "sg:classifiers":[
        {
            "category":"Restaurant",
            "type":"Food & Drink"
        }
    ],
    "sg:phone":"+1 828 488 0353",
    "sg:postcode":"28713",
    "sg:province":"NC",
    "sg:tags":[
        "eating"
    ],
    "wof:name":"Riverside Cafe",
    "wof:placetype":"venue"
},
  "geometry": {"coordinates":[-83.427825,35.433296],"type":"Point"}
}