{
  "type": "Feature",
  "properties": {
    "iso:country":"US",
    "sg:address":"12923 Ballantyne Corporate Pl",
    "sg:city":"Charlotte",
    "sg:classifiers":[
        {
            "category":"Professional",
            "subcategory":"Business Services",
            "type":"Services"
        }
    ],
    "sg:phone":"+1   ",
    "sg:postcode":"28277",
    "sg:province":"NC",
    "wof:name":"Landscape Colours & Design",
    "wof:placetype":"venue"
},
  "geometry": {"coordinates":[-80.84340899999999,35.054299],"type":"Point"}
}