{
  "type": "Feature",
  "properties": {
    "iso:country":"US",
    "sg:address":"403 Edinborough Ave",
    "sg:city":"Red Springs",
    "sg:classifiers":[
        {
            "category":"Farming",
            "subcategory":"Livestock Farm",
            "type":"Manufacturing & Wholesale Goods"
        }
    ],
    "sg:phone":"+1 910 843 5574",
    "sg:postcode":"28377",
    "sg:province":"NC",
    "sg:tags":[
        "beef",
        "feedlot",
        "cattle"
    ],
    "wof:name":"McPhal & Buie",
    "wof:placetype":"venue"
},
  "geometry": {"coordinates":[-79.190241,34.821016],"type":"Point"}
}