{
  "type": "Feature",
  "properties": {
    "addr:full":"210 3rd Ave W Hendersonville NC 28739",
    "addr:housenumber":"210",
    "addr:postcode":"28739",
    "addr:street":"3Rd Ave W",
    "iso:country":"US",
    "sg:address":"210 3rd Ave W",
    "sg:city":"Hendersonville",
    "sg:classifiers":[
        {
            "category":"Professional",
            "subcategory":"Lawyer & Legal Services",
            "type":"Services"
        }
    ],
    "sg:phone":"+1 828 698 2345",
    "sg:postcode":"28739",
    "sg:province":"NC",
    "sg:tags":[
        "attorney"
    ],
    "wof:name":"Coiner & Harrelson Pa",
    "wof:placetype":"venue"
},
  "geometry": {"coordinates":[-82.461365,35.315574],"type":"Point"}
}