{
  "type": "Feature",
  "properties": {
    "iso:country":"US",
    "sg:address":"1420 US Hwy 1 S",
    "sg:city":"Manson",
    "sg:classifiers":[
        {
            "category":"Home & Garden",
            "subcategory":"Household Appliances",
            "type":"Retail Goods"
        }
    ],
    "sg:phone":"+1 252 456 3886",
    "sg:postcode":"27553",
    "sg:province":"NC",
    "sg:tags":[
        "cleaners",
        "vacuum"
    ],
    "wof:name":"Kirby Co",
    "wof:placetype":"venue"
},
  "geometry": {"coordinates":[-78.28354899999999,36.421865],"type":"Point"}
}