{
  "type": "Feature",
  "properties": {
    "iso:country":"US",
    "sg:address":"925 E Main St",
    "sg:city":"Havelock",
    "sg:classifiers":[
        {
            "category":"Health Services",
            "subcategory":"Doctor",
            "type":"Services"
        }
    ],
    "sg:phone":"+1 252 444 4699",
    "sg:postcode":"28532",
    "sg:province":"NC",
    "sg:tags":[
        "physician",
        "surgeon"
    ],
    "wof:name":"Havelock General Practice",
    "wof:placetype":"venue"
},
  "geometry": {"coordinates":[-76.89850800000001,34.864567],"type":"Point"}
}