{
  "type": "Feature",
  "properties": {
    "iso:country":"US",
    "sg:address":"1590 Skibo Rd",
    "sg:city":"Fayetteville",
    "sg:classifiers":[
        {
            "category":"Cinema",
            "subcategory":"Movie Rental",
            "type":"Entertainment"
        }
    ],
    "sg:phone":"+1 910 764 3400",
    "sg:postcode":"28303",
    "sg:province":"NC",
    "sg:tags":[
        "leasing",
        "video",
        "disc",
        "tape"
    ],
    "wof:name":"Hollywood Video",
    "wof:placetype":"venue"
},
  "geometry": {"coordinates":[-78.956632,35.079391],"type":"Point"}
}