{
  "type": "Feature",
  "properties": {
    "iso:country":"US",
    "sg:address":"100 Main Ave NW",
    "sg:city":"Hickory",
    "sg:classifiers":[
        {
            "category":"Professional",
            "subcategory":"Accounting & Tax Preparation",
            "type":"Services"
        }
    ],
    "sg:phone":"+1 828 326 9891",
    "sg:postcode":"28601",
    "sg:province":"NC",
    "sg:tags":[
        "accountant"
    ],
    "wof:name":"Bowman Pegg & Starr",
    "wof:placetype":"venue"
},
  "geometry": {"coordinates":[-81.339657,35.732073],"type":"Point"}
}