{
  "type": "Feature",
  "properties": {
    "iso:country":"US",
    "sg:address":"974 Vannoy Rd",
    "sg:city":"Millers Creek",
    "sg:classifiers":[
        {
            "category":"Farming",
            "subcategory":"Farm",
            "type":"Manufacturing & Wholesale Goods"
        }
    ],
    "sg:phone":"+1 336 973 2494",
    "sg:postcode":"28651",
    "sg:province":"NC",
    "wof:name":"Triple E Farm",
    "wof:placetype":"venue"
},
  "geometry": {"coordinates":[-81.274502,36.264365],"type":"Point"}
}