{
  "type": "Feature",
  "properties": {
    "iso:country":"US",
    "sg:address":"5320 Old Pineville Rd",
    "sg:city":"Charlotte",
    "sg:classifiers":[
        {
            "category":"Wholesale",
            "subcategory":"Electrical",
            "type":"Manufacturing & Wholesale Goods"
        }
    ],
    "sg:phone":"+1 704 395 1410",
    "sg:postcode":"28217",
    "sg:province":"NC",
    "sg:tags":[
        "control",
        "security",
        "system"
    ],
    "sg:website":"www.iverify.us",
    "wof:name":"Interactive Security Corp",
    "wof:placetype":"venue"
},
  "geometry": {"coordinates":[-80.878035,35.169101],"type":"Point"}
}