{
  "type": "Feature",
  "properties": {
    "addr:full":"200 State Hwy 9 Black Mountain NC 28711",
    "addr:housenumber":"200",
    "addr:postcode":"28711",
    "addr:street":"State Hwy 9",
    "iso:country":"US",
    "sg:address":"200 State Hwy 9",
    "sg:city":"Black Mountain",
    "sg:classifiers":[
        {
            "category":"Banks & Credit Unions",
            "subcategory":"Bank",
            "type":"Services"
        }
    ],
    "sg:phone":"+1 828 669 3568",
    "sg:postcode":"28711",
    "sg:province":"NC",
    "sg:website":"www.ccbonline.com",
    "wof:name":"Central Carolina Bank",
    "wof:placetype":"venue"
},
  "geometry": {"coordinates":[-82.321231,35.622249],"type":"Point"}
}