{
  "type": "Feature",
  "properties": {
    "addr:full":"2 Eagle St Asheville NC 28801",
    "addr:housenumber":"2",
    "addr:postcode":"28801",
    "addr:street":"Eagle St",
    "iso:country":"US",
    "sg:address":"2 Eagle St",
    "sg:city":"Asheville",
    "sg:classifiers":[
        {
            "category":"Personal",
            "type":"Services"
        }
    ],
    "sg:phone":"+1 828 252 0058",
    "sg:postcode":"28801",
    "sg:province":"NC",
    "sg:tags":[
        "therapist",
        "massage"
    ],
    "sg:website":"www.centerformassage.com",
    "wof:name":"Center-Massage & Natural Hlth",
    "wof:placetype":"venue"
},
  "geometry": {"coordinates":[-82.550828,35.59386],"type":"Point"}
}