{
  "type": "Feature",
  "properties": {
    "iso:country":"US",
    "sg:address":"21 Meadow Ridge Dr",
    "sg:city":"Hayesville",
    "sg:classifiers":[
        {
            "category":"Building & Trades",
            "subcategory":"Construction",
            "type":"Services"
        }
    ],
    "sg:phone":"+1 828 389 2626",
    "sg:postcode":"28904",
    "sg:province":"NC",
    "sg:tags":[
        "contractor"
    ],
    "wof:name":"Real Co Homes",
    "wof:placetype":"venue"
},
  "geometry": {"coordinates":[-83.73308900000001,35.045463],"type":"Point"}
}