{
  "type": "Feature",
  "properties": {
    "addr:full":"3430 Toringdon Way Charlotte NC 28277",
    "addr:housenumber":"3430",
    "addr:postcode":"28277",
    "addr:street":"Toringdon Way",
    "iso:country":"US",
    "sg:address":"3430 Toringdon Way",
    "sg:city":"Charlotte",
    "sg:classifiers":[
        {
            "category":"Real Estate",
            "subcategory":"Real Estate Agent",
            "type":"Services"
        }
    ],
    "sg:phone":"+1 704 887 6600",
    "sg:postcode":"28277",
    "sg:province":"NC",
    "wof:name":"Keller Williams Reality LLC",
    "wof:placetype":"venue"
},
  "geometry": {"coordinates":[-80.84017900000001,35.068637],"type":"Point"}
}