{
  "type": "Feature",
  "properties": {
    "addr:full":"1119 US Hwy 158 Eure NC 27937",
    "addr:housenumber":"1119",
    "addr:postcode":"27937",
    "addr:street":"Us Hwy 158",
    "iso:country":"US",
    "sg:address":"1119 US Hwy 158",
    "sg:city":"Eure",
    "sg:classifiers":[
        {
            "category":"Retail",
            "subcategory":"Auto Repair",
            "type":"Services"
        }
    ],
    "sg:phone":"+1   ",
    "sg:postcode":"27937",
    "sg:province":"NC",
    "sg:tags":[
        "body"
    ],
    "wof:name":"Gilberts Body Shop & Wrecker",
    "wof:placetype":"venue"
},
  "geometry": {"coordinates":[-76.79323599999999,36.448529],"type":"Point"}
}