{
  "type": "Feature",
  "properties": {
    "addr:full":"1914 N Tryon St Charlotte NC 28206",
    "addr:housenumber":"1914",
    "addr:postcode":"28206",
    "addr:street":"N Tryon St",
    "iso:country":"US",
    "sg:address":"1914 N Tryon St",
    "sg:city":"Charlotte",
    "sg:classifiers":[
        {
            "category":"Train Station",
            "subcategory":"Rail",
            "type":"Transportation"
        }
    ],
    "sg:phone":"+1 704 373 3263",
    "sg:postcode":"28206",
    "sg:province":"NC",
    "sg:tags":[
        "railroad"
    ],
    "sg:website":"http://www.nscorp.com",
    "wof:name":"Norfolk Southern",
    "wof:placetype":"venue"
},
  "geometry": {"coordinates":[-80.823691,35.241946],"type":"Point"}
}