{
  "type": "Feature",
  "properties": {
    "iso:country":"US",
    "sg:address":"6076 Piney Woods Rd",
    "sg:city":"Fairfield",
    "sg:classifiers":[
        {
            "category":"Manufacturing",
            "subcategory":"Lumber",
            "type":"Manufacturing & Wholesale Goods"
        }
    ],
    "sg:phone":"+1 252 926 1990",
    "sg:postcode":"27826",
    "sg:province":"NC",
    "sg:tags":[
        "operation",
        "timber",
        "tract"
    ],
    "wof:name":"Canal Wood Corporation",
    "wof:placetype":"venue"
},
  "geometry": {"coordinates":[-76.32373200000001,35.516601],"type":"Point"}
}