{
  "type": "Feature",
  "properties": {
    "addr:full":"221 E Graham St Shelby NC 28150",
    "addr:housenumber":"221",
    "addr:postcode":"28150",
    "addr:street":"E Graham St",
    "iso:country":"US",
    "sg:address":"221 E Graham St",
    "sg:city":"Shelby",
    "sg:classifiers":[
        {
            "category":"Government",
            "subcategory":"Fire Station",
            "type":"Public Place"
        }
    ],
    "sg:phone":"+1 704 487 5335",
    "sg:postcode":"28150",
    "sg:province":"NC",
    "sg:tags":[
        "department"
    ],
    "wof:name":"Cleveland Volunteer Fire Dept",
    "wof:placetype":"venue"
},
  "geometry": {"coordinates":[-81.538037,35.289435],"type":"Point"}
}