{
  "type": "Feature",
  "properties": {
    "iso:country":"US",
    "sg:address":"212 29th Ave NE",
    "sg:city":"Hickory",
    "sg:classifiers":[
        {
            "category":"Health Services",
            "subcategory":"Medical Lab",
            "type":"Services"
        }
    ],
    "sg:phone":"+1 828 322 3882",
    "sg:postcode":"28601",
    "sg:province":"NC",
    "sg:tags":[
        "laboratory"
    ],
    "wof:name":"Laboratory Corp Of America",
    "wof:placetype":"venue"
},
  "geometry": {"coordinates":[-81.32650700000001,35.770672],"type":"Point"}
}