{
  "type": "Feature",
  "properties": {
    "addr:full":"22 Hickory Tree Ln Angier NC 27501",
    "addr:housenumber":"22",
    "addr:postcode":"27501",
    "addr:street":"Hickory Tree Ln",
    "iso:country":"US",
    "sg:address":"22 Hickory Tree Ln",
    "sg:city":"Angier",
    "sg:classifiers":[
        {
            "category":"Building & Trades",
            "subcategory":"Plumbing",
            "type":"Services"
        }
    ],
    "sg:phone":"+1 910 897 5217",
    "sg:postcode":"27501",
    "sg:province":"NC",
    "sg:tags":[
        "conditioning",
        "air",
        "system",
        "contractor"
    ],
    "wof:name":"Jernigan's Heating & Cooling",
    "wof:placetype":"venue"
},
  "geometry": {"coordinates":[-78.685588,35.458204],"type":"Point"}
}