{
  "type": "Feature",
  "properties": {
    "iso:country":"US",
    "sg:address":"500 N Main St",
    "sg:city":"Marion",
    "sg:classifiers":[
        {
            "category":"Personal",
            "subcategory":"Beauty Salon",
            "type":"Services"
        }
    ],
    "sg:phone":"+1 828 659 5634",
    "sg:postcode":"28752",
    "sg:province":"NC",
    "sg:tags":[
        "manicuring"
    ],
    "wof:name":"Pro Nails",
    "wof:placetype":"venue"
},
  "geometry": {"coordinates":[-82.013227,35.68784],"type":"Point"}
}