{
  "type": "Feature",
  "properties": {
    "iso:country":"US",
    "sg:address":"500 S Salisbury Ave",
    "sg:city":"Spencer",
    "sg:classifiers":[
        {
            "category":"Shopping",
            "subcategory":"Hobbies, Toys, & Games",
            "type":"Retail Goods"
        }
    ],
    "sg:phone":"+1 704 637 8717",
    "sg:postcode":"28159",
    "sg:province":"NC",
    "sg:tags":[
        "model",
        "supply"
    ],
    "sg:website":"www.littlechoochooshop.com",
    "wof:name":"Little Choo Choo Shop Inc",
    "wof:placetype":"venue"
},
  "geometry": {"coordinates":[-80.435942,35.687537],"type":"Point"}
}