{
  "type": "Feature",
  "properties": {
    "addr:full":"633 Harris Pt Way Wake Forest NC 27587",
    "addr:housenumber":"633",
    "addr:postcode":"27587",
    "addr:street":"Harris Pt Way",
    "iso:country":"US",
    "sg:address":"633 Harris Pt Way",
    "sg:city":"Wake Forest",
    "sg:classifiers":[
        {
            "category":"Building & Trades",
            "subcategory":"Landscaping Services",
            "type":"Services"
        }
    ],
    "sg:phone":"+1 919 795 0093",
    "sg:postcode":"27587",
    "sg:province":"NC",
    "sg:tags":[
        "tree"
    ],
    "wof:name":"Arbor Concepts Inc",
    "wof:placetype":"venue"
},
  "geometry": {"coordinates":[-78.512556,35.998082],"type":"Point"}
}