{
  "type": "Feature",
  "properties": {
    "addr:full":"601 E Main St Elizabeth City NC 27909",
    "addr:housenumber":"601",
    "addr:postcode":"27909",
    "addr:street":"E Main St",
    "iso:country":"US",
    "sg:address":"601 E Main St",
    "sg:city":"Elizabeth City",
    "sg:classifiers":[
        {
            "category":"Professional",
            "subcategory":"Business Services",
            "type":"Services"
        }
    ],
    "sg:phone":"+1 252 335 4200",
    "sg:postcode":"27909",
    "sg:province":"NC",
    "sg:tags":[
        "interior",
        "consultant",
        "design",
        "decorator"
    ],
    "wof:name":"Main Street Interiors",
    "wof:placetype":"venue"
},
  "geometry": {"coordinates":[-76.21964199999999,36.299746],"type":"Point"}
}