{
  "type": "Feature",
  "properties": {
    "iso:country":"US",
    "sg:address":"3009 Market St",
    "sg:city":"Wilmington",
    "sg:classifiers":[
        {
            "category":"Insurance",
            "subcategory":"Insurance Agent",
            "type":"Services"
        },
        {
            "category":"Insurance",
            "subcategory":"Hazard Insurance",
            "type":"Services"
        },
        {
            "category":"Insurance",
            "subcategory":"Title Insurance",
            "type":"Services"
        }
    ],
    "sg:phone":"+1 910 254 1015",
    "sg:postcode":"28403",
    "sg:province":"NC",
    "sg:tags":[
        "auto",
        "commercial",
        "business",
        "homeowner"
    ],
    "wof:name":"AAC Insurance Group",
    "wof:placetype":"venue"
},
  "geometry": {"coordinates":[-77.907083,34.239829],"type":"Point"}
}