{
  "type": "Feature",
  "properties": {
    "addr:full":"909 W Market St Smithfield NC 27577",
    "addr:housenumber":"909",
    "addr:postcode":"27577",
    "addr:street":"W Market St",
    "iso:country":"US",
    "sg:address":"909 W Market St",
    "sg:city":"Smithfield",
    "sg:classifiers":[
        {
            "category":"Autos & Motor Vehicles",
            "subcategory":"Auto Supplies",
            "type":"Retail Goods"
        }
    ],
    "sg:phone":"+1 919 934 9458",
    "sg:postcode":"27577",
    "sg:province":"NC",
    "sg:tags":[
        "automobile",
        "parts"
    ],
    "wof:name":"Advance Auto Parts Inc",
    "wof:placetype":"venue"
},
  "geometry": {"coordinates":[-78.36087000000001,35.524257],"type":"Point"}
}