{
  "type": "Feature",
  "properties": {
    "addr:full":"143 Archie Pl Newport NC 28570",
    "addr:housenumber":"143",
    "addr:postcode":"28570",
    "addr:street":"Archie Pl",
    "iso:country":"US",
    "sg:address":"143 Archie Pl",
    "sg:city":"Newport",
    "sg:classifiers":[
        {
            "category":"Freight",
            "type":"Transportation"
        },
        {
            "category":"Real Estate",
            "subcategory":"Real Estate Operator",
            "type":"Services"
        }
    ],
    "sg:phone":"+1 252 240 0860",
    "sg:postcode":"28570",
    "sg:province":"NC",
    "sg:tags":[
        "mobile",
        "home",
        "site"
    ],
    "wof:name":"Eastern Mobile Home Services",
    "wof:placetype":"venue"
},
  "geometry": {"coordinates":[-76.921792,34.721241],"type":"Point"}
}