{
  "type": "Feature",
  "properties": {
    "addr:full":"160 US Hwy 158 Camden NC 27921",
    "addr:housenumber":"160",
    "addr:postcode":"27921",
    "addr:street":"Us Hwy 158",
    "iso:country":"US",
    "sg:address":"160 US Hwy 158",
    "sg:city":"Camden",
    "sg:classifiers":[
        {
            "category":"Health Services",
            "subcategory":"Doctor",
            "type":"Services"
        }
    ],
    "sg:phone":"+1 252 334 9527",
    "sg:postcode":"27921",
    "sg:province":"NC",
    "sg:tags":[
        "physician",
        "surgeon"
    ],
    "wof:name":"Albemarle Family Practice",
    "wof:placetype":"venue"
},
  "geometry": {"coordinates":[-76.176498,36.320509],"type":"Point"}
}