{
  "type": "Feature",
  "properties": {
    "addr:full":"101 Greenbriar Dr Greenville NC 27834",
    "addr:housenumber":"101",
    "addr:postcode":"27834",
    "addr:street":"Greenbriar Dr",
    "iso:country":"US",
    "sg:address":"101 Greenbriar Dr",
    "sg:city":"Greenville",
    "sg:classifiers":[
        {
            "category":"Social Services",
            "subcategory":"Child Care",
            "type":"Services"
        }
    ],
    "sg:phone":"+1 252 321 0813",
    "sg:postcode":"27834",
    "sg:province":"NC",
    "wof:name":"Mama Bunns House Child Care",
    "wof:placetype":"venue"
},
  "geometry": {"coordinates":[-77.391729,35.583227],"type":"Point"}
}