{
  "type": "Feature",
  "properties": {
    "iso:country":"US",
    "sg:address":"37 Court Sq",
    "sg:city":"Mocksville",
    "sg:classifiers":[
        {
            "category":"Shopping",
            "subcategory":"Discount & Variety Stores",
            "type":"Retail Goods"
        }
    ],
    "sg:phone":"+1 336 751 0587",
    "sg:postcode":"27028",
    "sg:province":"NC",
    "wof:name":"Crestwood Farms Co Store",
    "wof:placetype":"venue"
},
  "geometry": {"coordinates":[-80.561978,35.893883],"type":"Point"}
}