{
  "type": "Feature",
  "properties": {
    "addr:full":"280 Pine St Boone NC 28607",
    "addr:housenumber":"280",
    "addr:postcode":"28607",
    "addr:street":"Pine St",
    "iso:country":"US",
    "sg:address":"280 Pine St",
    "sg:city":"Boone",
    "sg:classifiers":[
        {
            "category":"Retail",
            "subcategory":"Auto Repair",
            "type":"Services"
        }
    ],
    "sg:phone":"+1   ",
    "sg:postcode":"28607",
    "sg:province":"NC",
    "sg:tags":[
        "automotive"
    ],
    "wof:name":"High Country Towing",
    "wof:placetype":"venue"
},
  "geometry": {"coordinates":[-81.673044,36.21252],"type":"Point"}
}