{
  "type": "Feature",
  "properties": {
    "iso:country":"US",
    "sg:address":"75 Ivy Ln",
    "sg:city":"Fletcher",
    "sg:classifiers":[
        {
            "category":"Building & Trades",
            "subcategory":"Plumbing",
            "type":"Services"
        }
    ],
    "sg:phone":"+1 828 628 3799",
    "sg:postcode":"28732",
    "sg:province":"NC",
    "sg:tags":[
        "septic"
    ],
    "wof:name":"Carolina Sewer & Drain Co",
    "wof:placetype":"venue"
},
  "geometry": {"coordinates":[-82.43997299999999,35.490941],"type":"Point"}
}