{
  "type": "Feature",
  "properties": {
    "addr:full":"114 Lake Boone Trl Raleigh NC 27608",
    "addr:housenumber":"114",
    "addr:postcode":"27608",
    "addr:street":"Lake Boone Trl",
    "iso:country":"US",
    "sg:address":"114 Lake Boone Trl",
    "sg:city":"Raleigh",
    "sg:classifiers":[
        {
            "category":"Building & Trades",
            "subcategory":"Construction",
            "type":"Services"
        }
    ],
    "sg:phone":"+1 919 783 0046",
    "sg:postcode":"27608",
    "sg:province":"NC",
    "sg:tags":[
        "general",
        "contractor"
    ],
    "wof:name":"Premier Development Group Inc",
    "wof:placetype":"venue"
},
  "geometry": {"coordinates":[-78.662147,35.817637],"type":"Point"}
}