{
  "type": "Feature",
  "properties": {
    "addr:full":"2040 S Stratford Rd Winston Salem NC 27103",
    "addr:housenumber":"2040",
    "addr:postcode":"27103",
    "addr:street":"S Stratford Rd",
    "iso:country":"US",
    "sg:address":"2040 S Stratford Rd",
    "sg:city":"Winston Salem",
    "sg:classifiers":[
        {
            "category":"Insurance",
            "subcategory":"Insurance Agent",
            "type":"Services"
        }
    ],
    "sg:phone":"+1 336 768 2322",
    "sg:postcode":"27103",
    "sg:province":"NC",
    "wof:name":"David D Norman",
    "wof:placetype":"venue"
},
  "geometry": {"coordinates":[-80.311673,36.061875],"type":"Point"}
}