{
  "type": "Feature",
  "properties": {
    "iso:country":"US",
    "sg:address":"3307 Green Needle Dr",
    "sg:city":"Greensboro",
    "sg:classifiers":[
        {
            "category":"Building & Trades",
            "subcategory":"Construction",
            "type":"Services"
        }
    ],
    "sg:phone":"+1 336 621 7398",
    "sg:postcode":"27405",
    "sg:province":"NC",
    "sg:tags":[
        "personal",
        "hanging",
        "contractor"
    ],
    "wof:name":"Sawdust & Assoc",
    "wof:placetype":"venue"
},
  "geometry": {"coordinates":[-79.770973,36.12154],"type":"Point"}
}