{
  "type": "Feature",
  "properties": {
    "addr:full":"1218 Hendersonville Rd Asheville NC 28803",
    "addr:housenumber":"1218",
    "addr:postcode":"28803",
    "addr:street":"Hendersonville Rd",
    "iso:country":"US",
    "sg:address":"1218 Hendersonville Rd",
    "sg:city":"Asheville",
    "sg:classifiers":[
        {
            "category":"Health Services",
            "subcategory":"Chiropractor",
            "type":"Services"
        }
    ],
    "sg:phone":"+1   ",
    "sg:postcode":"28803",
    "sg:province":"NC",
    "wof:name":"Comprehensive Chiropractic",
    "wof:placetype":"venue"
},
  "geometry": {"coordinates":[-82.528835,35.529323],"type":"Point"}
}