{
  "type": "Feature",
  "properties": {
    "iso:country":"US",
    "sg:address":"3200 Fairhill Dr",
    "sg:city":"Raleigh",
    "sg:classifiers":[
        {
            "category":"Professional",
            "subcategory":"Employment Agencies",
            "type":"Services"
        }
    ],
    "sg:phone":"+1 919 844 2900",
    "sg:postcode":"27612",
    "sg:province":"NC",
    "sg:tags":[
        "opportunity"
    ],
    "sg:website":"www.accstaffing.com",
    "wof:name":"ACC Staffing",
    "wof:placetype":"venue"
},
  "geometry": {"coordinates":[-78.69720599999999,35.851417],"type":"Point"}
}