{
  "type": "Feature",
  "properties": {
    "addr:full":"5029 College Acres Dr Wilmington NC 28403",
    "addr:housenumber":"5029",
    "addr:postcode":"28403",
    "addr:street":"College Acres Dr",
    "iso:country":"US",
    "sg:address":"5029 College Acres Dr",
    "sg:city":"Wilmington",
    "sg:classifiers":[
        {
            "category":"Organizations",
            "subcategory":"Non-profit Organization",
            "type":"Services"
        }
    ],
    "sg:phone":"+1 910 791 2180",
    "sg:postcode":"28403",
    "sg:province":"NC",
    "sg:tags":[
        "association",
        "social"
    ],
    "wof:name":"Cape Fear Chapter 3",
    "wof:placetype":"venue"
},
  "geometry": {"coordinates":[-77.86517000000001,34.235824],"type":"Point"}
}