{
  "type": "Feature",
  "properties": {
    "addr:full":"1169 Old Mocksville Rd Statesville NC 28625",
    "addr:housenumber":"1169",
    "addr:postcode":"28625",
    "addr:street":"Old Mocksville Rd",
    "iso:country":"US",
    "sg:address":"1169 Old Mocksville Rd",
    "sg:city":"Statesville",
    "sg:classifiers":[
        {
            "category":"Building & Trades",
            "subcategory":"Cleaning & Sanitation",
            "type":"Services"
        }
    ],
    "sg:phone":"+1   ",
    "sg:postcode":"28625",
    "sg:province":"NC",
    "sg:tags":[
        "maintenance"
    ],
    "wof:name":"Mocksville Floor Sweeps",
    "wof:placetype":"venue"
},
  "geometry": {"coordinates":[-80.812167,35.857217],"type":"Point"}
}