{
  "type": "Feature",
  "properties": {
    "iso:country":"US",
    "sg:address":"115 N Bragg Blvd",
    "sg:city":"Spring Lake",
    "sg:classifiers":[
        {
            "category":"Health Services",
            "subcategory":"Health Practitioner",
            "type":"Services"
        }
    ],
    "sg:phone":"+1 910 497 4880",
    "sg:postcode":"28390",
    "sg:province":"NC",
    "sg:tags":[
        "psychologist"
    ],
    "wof:name":"Neighborhood Para Social Work",
    "wof:placetype":"venue"
},
  "geometry": {"coordinates":[-78.97418399999999,35.170129],"type":"Point"}
}