{
  "type": "Feature",
  "properties": {
    "iso:country":"US",
    "sg:address":"1316 Beech Mountain Pkwy",
    "sg:city":"Banner Elk",
    "sg:classifiers":[
        {
            "category":"Professional",
            "type":"Services"
        }
    ],
    "sg:phone":"+1 828 387 4716",
    "sg:postcode":"28604",
    "sg:province":"NC",
    "wof:name":"Oteka N Lund",
    "wof:placetype":"venue"
},
  "geometry": {"coordinates":[-81.884156,36.203996],"type":"Point"}
}