{
  "type": "Feature",
  "properties": {
    "addr:full":"2378 Corporation Pkwy Burlington NC 27215",
    "addr:housenumber":"2378",
    "addr:postcode":"27215",
    "addr:street":"Corporation Pkwy",
    "iso:country":"US",
    "sg:address":"2378 Corporation Pkwy",
    "sg:city":"Burlington",
    "sg:classifiers":[
        {
            "category":"Restaurant",
            "type":"Food & Drink"
        }
    ],
    "sg:phone":"+1 336 222 1615",
    "sg:postcode":"27215",
    "sg:province":"NC",
    "wof:name":"Sam's Hotdogs",
    "wof:placetype":"venue"
},
  "geometry": {"coordinates":[-79.436009,36.066365],"type":"Point"}
}