{
  "type": "Feature",
  "properties": {
    "addr:full":"136 E Murphy St Madison NC 27025",
    "addr:housenumber":"136",
    "addr:postcode":"27025",
    "addr:street":"E Murphy St",
    "iso:country":"US",
    "sg:address":"136 E Murphy St",
    "sg:city":"Madison",
    "sg:classifiers":[
        {
            "category":"Sports & Exercise",
            "subcategory":"Gym",
            "type":"Entertainment"
        }
    ],
    "sg:phone":"+1 336 427 5858",
    "sg:postcode":"27025",
    "sg:province":"NC",
    "sg:tags":[
        "club",
        "health",
        "studio",
        "gymnasium"
    ],
    "wof:name":"Curves For Women",
    "wof:placetype":"venue"
},
  "geometry": {"coordinates":[-79.95950999999999,36.387452],"type":"Point"}
}