{
  "type": "Feature",
  "properties": {
    "addr:full":"21170 US Hwy 17 Hampstead NC 28443",
    "addr:postcode":"21170;28443",
    "addr:street":"Us Hwy 17",
    "iso:country":"US",
    "sg:address":"21170 US Hwy 17",
    "sg:city":"Hampstead",
    "sg:classifiers":[
        {
            "category":"Food & Beverages",
            "subcategory":"Groceries & Convenience Stores",
            "type":"Retail Goods"
        }
    ],
    "sg:phone":"+1 910 270 2710",
    "sg:postcode":"28443",
    "sg:province":"NC",
    "wof:name":"Hilltop Grocery Co",
    "wof:placetype":"venue"
},
  "geometry": {"coordinates":[-77.634325,34.431408],"type":"Point"}
}