{
  "type": "Feature",
  "properties": {
    "addr:full":"605 Lynndale Ct Greenville NC 27858",
    "addr:housenumber":"605",
    "addr:postcode":"27858",
    "addr:street":"Lynndale Ct",
    "iso:country":"US",
    "sg:address":"605 Lynndale Ct",
    "sg:city":"Greenville",
    "sg:classifiers":[
        {
            "category":"Health Services",
            "subcategory":"Health Practitioner",
            "type":"Services"
        },
        {
            "category":"Personal",
            "subcategory":"Beauty Salon",
            "type":"Services"
        }
    ],
    "sg:phone":"+1 252 355 5793",
    "sg:postcode":"27858",
    "sg:province":"NC",
    "sg:tags":[
        "treatment",
        "skin"
    ],
    "wof:name":"Skin Therapy Center",
    "wof:placetype":"venue"
},
  "geometry": {"coordinates":[-77.36912599999999,35.579498],"type":"Point"}
}