{
  "type": "Feature",
  "properties": {
    "addr:full":"218 Century Blvd Kernersville NC 27284",
    "addr:housenumber":"218",
    "addr:postcode":"27284",
    "addr:street":"Century Blvd",
    "iso:country":"US",
    "sg:address":"218 Century Blvd",
    "sg:city":"Kernersville",
    "sg:classifiers":[
        {
            "category":"Personal",
            "subcategory":"Tanning Parlor",
            "type":"Services"
        }
    ],
    "sg:phone":"+1 336 996 5220",
    "sg:postcode":"27284",
    "sg:province":"NC",
    "sg:tags":[
        "salon"
    ],
    "wof:name":"Tropical Rays Tanning Inc",
    "wof:placetype":"venue"
},
  "geometry": {"coordinates":[-80.09166399999999,36.106258],"type":"Point"}
}