{
  "type": "Feature",
  "properties": {
    "iso:country":"US",
    "sg:address":"3985 Asheville Hwy",
    "sg:city":"Pisgah Forest",
    "sg:classifiers":[
        {
            "category":"Building & Trades",
            "subcategory":"Cleaning & Sanitation",
            "type":"Services"
        }
    ],
    "sg:phone":"+1 828 884 9447",
    "sg:postcode":"28768",
    "sg:province":"NC",
    "sg:tags":[
        "house"
    ],
    "wof:name":"Tri-County Cleaning Svc",
    "wof:placetype":"venue"
},
  "geometry": {"coordinates":[-82.702823,35.275036],"type":"Point"}
}