{
  "type": "Feature",
  "properties": {
    "iso:country":"US",
    "sg:address":"3917 Sunset Ave",
    "sg:city":"Rocky Mount",
    "sg:classifiers":[
        {
            "category":"Manufacturing",
            "subcategory":"Lumber",
            "type":"Manufacturing & Wholesale Goods"
        }
    ],
    "sg:phone":"+1 252 443 2515",
    "sg:postcode":"27804",
    "sg:province":"NC",
    "sg:tags":[
        "forestry"
    ],
    "wof:name":"Forestry Consultants",
    "wof:placetype":"venue"
},
  "geometry": {"coordinates":[-77.87108600000001,35.965657],"type":"Point"}
}