{
  "type": "Feature",
  "properties": {
    "iso:country":"US",
    "sg:address":"1022 River St",
    "sg:city":"Wilkesboro",
    "sg:classifiers":[
        {
            "category":"Home & Garden",
            "subcategory":"Carpets & Floor Coverings",
            "type":"Retail Goods"
        }
    ],
    "sg:phone":"+1 336 903 8453",
    "sg:postcode":"28697",
    "sg:province":"NC",
    "sg:tags":[
        "material"
    ],
    "wof:name":"Wilkes Floor Covering",
    "wof:placetype":"venue"
},
  "geometry": {"coordinates":[-81.169209,36.142239],"type":"Point"}
}