{
  "type": "Feature",
  "properties": {
    "addr:full":"4006 Murchison Rd Fayetteville NC 28311",
    "addr:housenumber":"4006",
    "addr:postcode":"28311",
    "addr:street":"Murchison Rd",
    "iso:country":"US",
    "sg:address":"4006 Murchison Rd",
    "sg:city":"Fayetteville",
    "sg:classifiers":[
        {
            "category":"Organizations",
            "subcategory":"Religious Organization",
            "type":"Services"
        }
    ],
    "sg:phone":"+1 910 630 4300",
    "sg:postcode":"28311",
    "sg:province":"NC",
    "sg:tags":[
        "church"
    ],
    "wof:name":"Salem Missionary Baptist Chr",
    "wof:placetype":"venue"
},
  "geometry": {"coordinates":[-78.91910799999999,35.101217],"type":"Point"}
}