{
  "type": "Feature",
  "properties": {
    "iso:country":"US",
    "sg:address":"4431 S Alston Ave",
    "sg:city":"Durham",
    "sg:classifiers":[
        {
            "category":"Health Services",
            "subcategory":"Medical Lab",
            "type":"Services"
        }
    ],
    "sg:phone":"+1 919 544 3870",
    "sg:postcode":"27713",
    "sg:province":"NC",
    "sg:tags":[
        "laboratory"
    ],
    "wof:name":"Ortho Laboratory Inc",
    "wof:placetype":"venue"
},
  "geometry": {"coordinates":[-78.888873,35.913981],"type":"Point"}
}