{
  "type": "Feature",
  "properties": {
    "addr:full":"701 Main St Danbury NC 27016",
    "addr:housenumber":"701",
    "addr:postcode":"27016",
    "addr:street":"Main St",
    "iso:country":"US",
    "sg:address":"701 Main St",
    "sg:city":"Danbury",
    "sg:classifiers":[
        {
            "category":"Personal",
            "subcategory":"Beauty Salon",
            "type":"Services"
        }
    ],
    "sg:phone":"+1   ",
    "sg:postcode":"27016",
    "sg:province":"NC",
    "sg:tags":[
        "shop"
    ],
    "wof:name":"Total Perfection",
    "wof:placetype":"venue"
},
  "geometry": {"coordinates":[-80.210493,36.408892],"type":"Point"}
}