{
  "type": "Feature",
  "properties": {
    "iso:country":"US",
    "sg:address":"4621 Hillsborough Rd",
    "sg:city":"Durham",
    "sg:classifiers":[
        {
            "category":"Shopping",
            "subcategory":"Discount & Variety Stores",
            "type":"Retail Goods"
        }
    ],
    "sg:phone":"+1 919 382 0100",
    "sg:postcode":"27705",
    "sg:province":"NC",
    "wof:name":"Dollar General",
    "wof:placetype":"venue"
},
  "geometry": {"coordinates":[-78.98089400000001,36.032749],"type":"Point"}
}