{
  "type": "Feature",
  "properties": {
    "iso:country":"US",
    "sg:address":"1865 S Clearview Dr",
    "sg:city":"Henderson",
    "sg:classifiers":[
        {
            "category":"Building & Trades",
            "subcategory":"Electrical",
            "type":"Services"
        }
    ],
    "sg:phone":"+1 252 492 9842",
    "sg:postcode":"27536",
    "sg:province":"NC",
    "sg:tags":[
        "electrical",
        "contractor"
    ],
    "wof:name":"Masterpiece Electric",
    "wof:placetype":"venue"
},
  "geometry": {"coordinates":[-78.375563,36.315213],"type":"Point"}
}