{
  "type": "Feature",
  "properties": {
    "iso:country":"US",
    "sg:address":"113 Pamlico Ln",
    "sg:city":"Chocowinity",
    "sg:classifiers":[
        {
            "category":"Professional",
            "subcategory":"Computer Services",
            "type":"Services"
        }
    ],
    "sg:phone":"+1 252 946 7839",
    "sg:postcode":"27817",
    "sg:province":"NC",
    "sg:tags":[
        "equipment",
        "related"
    ],
    "wof:name":"Carolina Microfilm & Imaging",
    "wof:placetype":"venue"
},
  "geometry": {"coordinates":[-77.04303299999999,35.500051],"type":"Point"}
}