{
  "type": "Feature",
  "properties": {
    "addr:full":"1008 W Sterlington Pl Apex NC 27502",
    "addr:housenumber":"1008",
    "addr:postcode":"27502",
    "addr:street":"W Sterlington Pl",
    "iso:country":"US",
    "sg:address":"1008 W Sterlington Pl",
    "sg:city":"Apex",
    "sg:classifiers":[
        {
            "category":"Professional",
            "subcategory":"Computer Services",
            "type":"Services"
        }
    ],
    "sg:phone":"+1   ",
    "sg:postcode":"27502",
    "sg:province":"NC",
    "sg:tags":[
        "related"
    ],
    "wof:name":"ITR Technologies",
    "wof:placetype":"venue"
},
  "geometry": {"coordinates":[-78.821819,35.735391],"type":"Point"}
}