{
  "type": "Feature",
  "properties": {
    "iso:country":"US",
    "sg:address":"5207 Mulberry Ave",
    "sg:city":"Wilmington",
    "sg:classifiers":[
        {
            "category":"Education",
            "subcategory":"School",
            "type":"Public Place"
        }
    ],
    "sg:phone":"+1   ",
    "sg:postcode":"28403",
    "sg:province":"NC",
    "wof:name":"Middle Man Merchants",
    "wof:placetype":"venue"
},
  "geometry": {"coordinates":[-77.865235,34.209308],"type":"Point"}
}