{
  "type": "Feature",
  "properties": {
    "addr:full":"14 Jackson St Roanoke Rapids NC 27870",
    "addr:housenumber":"14",
    "addr:postcode":"27870",
    "addr:street":"Jackson St",
    "iso:country":"US",
    "sg:address":"14 Jackson St",
    "sg:city":"Roanoke Rapids",
    "sg:classifiers":[
        {
            "category":"Retail",
            "subcategory":"Auto Repair",
            "type":"Services"
        }
    ],
    "sg:phone":"+1 800 800 2727",
    "sg:postcode":"27870",
    "sg:province":"NC",
    "sg:tags":[
        "glass",
        "replacement"
    ],
    "wof:name":"Safelite Autoglass",
    "wof:placetype":"venue"
},
  "geometry": {"coordinates":[-77.650203,36.472432],"type":"Point"}
}