{
  "type": "Feature",
  "properties": {
    "addr:full":"113 Barwood Ter Trinity NC 27370",
    "addr:housenumber":"113",
    "addr:postcode":"27370",
    "addr:street":"Barwood Ter",
    "iso:country":"US",
    "sg:address":"113 Barwood Ter",
    "sg:city":"Trinity",
    "sg:classifiers":[
        {
            "category":"Building & Trades",
            "subcategory":"Cleaning & Sanitation",
            "type":"Services"
        }
    ],
    "sg:phone":"+1   ",
    "sg:postcode":"27370",
    "sg:province":"NC",
    "sg:tags":[
        "maintenance"
    ],
    "wof:name":"Shore General Maintenance",
    "wof:placetype":"venue"
},
  "geometry": {"coordinates":[-79.963244,35.890071],"type":"Point"}
}