{
  "type": "Feature",
  "properties": {
    "addr:full":"1229 Cedar Grove Rd SW Supply NC 28462",
    "addr:housenumber":"1229",
    "addr:postcode":"28462",
    "addr:street":"Cedar Grove Rd Sw",
    "iso:country":"US",
    "sg:address":"1229 Cedar Grove Rd SW",
    "sg:city":"Supply",
    "sg:classifiers":[
        {
            "category":"Organizations",
            "subcategory":"Religious Organization",
            "type":"Services"
        }
    ],
    "sg:phone":"+1   ",
    "sg:postcode":"28462",
    "sg:province":"NC",
    "wof:name":"Cedar Grove Baptist Church",
    "wof:placetype":"venue"
},
  "geometry": {"coordinates":[-78.29028599999999,33.958193],"type":"Point"}
}