{
  "type": "Feature",
  "properties": {
    "addr:full":"2715 Heathershire Ln Matthews NC 28105",
    "addr:housenumber":"2715",
    "addr:postcode":"28105",
    "addr:street":"Heathershire Ln",
    "iso:country":"US",
    "sg:address":"2715 Heathershire Ln",
    "sg:city":"Matthews",
    "sg:classifiers":[
        {
            "category":"Professional",
            "subcategory":"Management & Consulting",
            "type":"Services"
        }
    ],
    "sg:phone":"+1 704 321 2841",
    "sg:postcode":"28105",
    "sg:province":"NC",
    "sg:tags":[
        "marketing",
        "consultant"
    ],
    "wof:name":"Invision",
    "wof:placetype":"venue"
},
  "geometry": {"coordinates":[-80.68083,35.123163],"type":"Point"}
}