{
  "type": "Feature",
  "properties": {
    "addr:full":"445 W Grover St Shelby NC 28150",
    "addr:housenumber":"445",
    "addr:postcode":"28150",
    "addr:street":"W Grover St",
    "iso:country":"US",
    "sg:address":"445 W Grover St",
    "sg:city":"Shelby",
    "sg:classifiers":[
        {
            "category":"Wholesale",
            "subcategory":"Electrical",
            "type":"Manufacturing & Wholesale Goods"
        }
    ],
    "sg:phone":"+1 704 481 0782",
    "sg:postcode":"28150",
    "sg:province":"NC",
    "sg:tags":[
        "equipment",
        "generator"
    ],
    "wof:name":"Carolina Generator & Control",
    "wof:placetype":"venue"
},
  "geometry": {"coordinates":[-81.553055,35.302746],"type":"Point"}
}