{
  "type": "Feature",
  "properties": {
    "iso:country":"US",
    "sg:address":"112 Walnut Creek Rd",
    "sg:city":"Locust",
    "sg:classifiers":[
        {
            "category":"Building & Trades",
            "subcategory":"Construction",
            "type":"Services"
        }
    ],
    "sg:phone":"+1 704 888 6960",
    "sg:postcode":"28097",
    "sg:province":"NC",
    "sg:tags":[
        "floor",
        "laying",
        "contractor"
    ],
    "wof:name":"Coleman Co The",
    "wof:placetype":"venue"
},
  "geometry": {"coordinates":[-80.437062,35.262448],"type":"Point"}
}