{
  "type": "Feature",
  "properties": {
    "iso:country":"US",
    "sg:address":"4 S Jefferson Ave",
    "sg:city":"West Jefferson",
    "sg:classifiers":[
        {
            "category":"Shopping",
            "subcategory":"Used Merchandise",
            "type":"Retail Goods"
        }
    ],
    "sg:phone":"+1 336 246 3791",
    "sg:postcode":"28694",
    "sg:province":"NC",
    "sg:tags":[
        "pawnbroker"
    ],
    "wof:name":"Baldwin's Pawn Shop",
    "wof:placetype":"venue"
},
  "geometry": {"coordinates":[-81.492158,36.401793],"type":"Point"}
}