{
  "type": "Feature",
  "properties": {
    "addr:full":"801 State Hwy 45 N Plymouth NC 27962",
    "addr:housenumber":"801",
    "addr:postcode":"27962",
    "addr:street":"State Hwy 45 N",
    "iso:country":"US",
    "sg:address":"801 State Hwy 45 N",
    "sg:city":"Plymouth",
    "sg:classifiers":[
        {
            "category":"Farming",
            "subcategory":"Farm",
            "type":"Manufacturing & Wholesale Goods"
        }
    ],
    "sg:phone":"+1 252 793 2830",
    "sg:postcode":"27962",
    "sg:province":"NC",
    "sg:tags":[
        "crop",
        "general"
    ],
    "wof:name":"Modlin Farm",
    "wof:placetype":"venue"
},
  "geometry": {"coordinates":[-76.695993,35.882227],"type":"Point"}
}