{
  "type": "Feature",
  "properties": {
    "addr:full":"1915 W B St Butner NC 27509",
    "addr:housenumber":"1915",
    "addr:postcode":"27509",
    "addr:street":"W B St",
    "iso:country":"US",
    "sg:address":"1915 W B St",
    "sg:city":"Butner",
    "sg:classifiers":[
        {
            "category":"Professional",
            "subcategory":"Management & Consulting",
            "type":"Services"
        }
    ],
    "sg:phone":"+1   ",
    "sg:postcode":"27509",
    "sg:province":"NC",
    "sg:tags":[
        "diversity"
    ],
    "wof:name":"Strategic Diversity Solutions",
    "wof:placetype":"venue"
},
  "geometry": {"coordinates":[-78.78082999999999,36.105044],"type":"Point"}
}