{
  "type": "Feature",
  "properties": {
    "iso:country":"US",
    "sg:address":"1725 Brevard Rd",
    "sg:city":"Hendersonville",
    "sg:classifiers":[
        {
            "category":"Shopping",
            "subcategory":"Clothing, Apparel, & Fashions",
            "type":"Retail Goods"
        }
    ],
    "sg:phone":"+1 828 694 1245",
    "sg:postcode":"28791",
    "sg:province":"NC",
    "wof:name":"Christina",
    "wof:placetype":"venue"
},
  "geometry": {"coordinates":[-82.492048,35.320602],"type":"Point"}
}