{
  "type": "Feature",
  "properties": {
    "addr:full":"2113 Westhill Dr Fayetteville NC 28304",
    "addr:housenumber":"2113",
    "addr:postcode":"28304",
    "addr:street":"Westhill Dr",
    "iso:country":"US",
    "sg:address":"2113 Westhill Dr",
    "sg:city":"Fayetteville",
    "sg:classifiers":[
        {
            "category":"Personal",
            "type":"Services"
        }
    ],
    "sg:phone":"+1   ",
    "sg:postcode":"28304",
    "sg:province":"NC",
    "sg:tags":[
        "construction"
    ],
    "wof:name":"Rojas & Sons",
    "wof:placetype":"venue"
},
  "geometry": {"coordinates":[-78.941194,35.017955],"type":"Point"}
}