{
  "type": "Feature",
  "properties": {
    "addr:full":"3660 Southard Rd Lenoir NC 28645",
    "addr:postcode":"3660;28645",
    "addr:street":"Southard Rd",
    "iso:country":"US",
    "sg:address":"3660 Southard Rd",
    "sg:city":"Lenoir",
    "sg:classifiers":[
        {
            "category":"Retail",
            "subcategory":"Self-service Laundry",
            "type":"Services"
        }
    ],
    "sg:phone":"+1   ",
    "sg:postcode":"28645",
    "sg:province":"NC",
    "wof:name":"Southard Laundry",
    "wof:placetype":"venue"
},
  "geometry": {"coordinates":[-81.607567,35.847964],"type":"Point"}
}