{
  "type": "Feature",
  "properties": {
    "addr:full":"5780 Ramsey St Fayetteville NC 28311",
    "addr:housenumber":"5780",
    "addr:postcode":"28311",
    "addr:street":"Ramsey St",
    "iso:country":"US",
    "sg:address":"5780 Ramsey St",
    "sg:city":"Fayetteville",
    "sg:classifiers":[
        {
            "category":"Shopping",
            "subcategory":"Florist",
            "type":"Retail Goods"
        },
        {
            "category":"Wholesale",
            "subcategory":"Non-durable Goods",
            "type":"Manufacturing & Wholesale Goods"
        }
    ],
    "sg:phone":"+1 910 488 4177",
    "sg:postcode":"28311",
    "sg:province":"NC",
    "wof:name":"Ann's Flower Shop",
    "wof:placetype":"venue"
},
  "geometry": {"coordinates":[-78.874484,35.138988],"type":"Point"}
}