{
  "type": "Feature",
  "properties": {
    "addr:full":"15501 Hugh McAuley Rd Huntersville NC 28078",
    "addr:housenumber":"15501",
    "addr:postcode":"28078",
    "addr:street":"Hugh Mcauley Rd",
    "iso:country":"US",
    "sg:address":"15501 Hugh McAuley Rd",
    "sg:city":"Huntersville",
    "sg:classifiers":[
        {
            "category":"Professional",
            "subcategory":"Management & Consulting",
            "type":"Services"
        }
    ],
    "sg:phone":"+1   ",
    "sg:postcode":"28078",
    "sg:province":"NC",
    "sg:tags":[
        "business"
    ],
    "wof:name":"Concept Design Reality Corp",
    "wof:placetype":"venue"
},
  "geometry": {"coordinates":[-80.875052,35.429174],"type":"Point"}
}