{
  "type": "Feature",
  "properties": {
    "addr:full":"1512 State Hwy 49 Burlington NC 27217",
    "addr:housenumber":"1512",
    "addr:postcode":"27217",
    "addr:street":"State Hwy 49",
    "iso:country":"US",
    "sg:address":"1512 State Hwy 49",
    "sg:city":"Burlington",
    "sg:classifiers":[
        {
            "category":"Shopping",
            "subcategory":"Used Merchandise",
            "type":"Retail Goods"
        }
    ],
    "sg:phone":"+1 336 578 9660",
    "sg:postcode":"27217",
    "sg:province":"NC",
    "sg:tags":[
        "shop",
        "thrift"
    ],
    "wof:name":"Savers",
    "wof:placetype":"venue"
},
  "geometry": {"coordinates":[-79.34961800000001,36.122178],"type":"Point"}
}