{
  "type": "Feature",
  "properties": {
    "addr:full":"448 Old Hampton Rd Boone NC 28607",
    "addr:housenumber":"448",
    "addr:postcode":"28607",
    "addr:street":"Old Hampton Rd",
    "iso:country":"US",
    "sg:address":"448 Old Hampton Rd",
    "sg:city":"Boone",
    "sg:classifiers":[
        {
            "category":"Banks & Credit Unions",
            "subcategory":"Financial Services",
            "type":"Services"
        }
    ],
    "sg:phone":"+1 828 262 1163",
    "sg:postcode":"28607",
    "sg:province":"NC",
    "sg:tags":[
        "investor"
    ],
    "wof:name":"Regal International Capital",
    "wof:placetype":"venue"
},
  "geometry": {"coordinates":[-81.596244,36.180518],"type":"Point"}
}