{
  "type": "Feature",
  "properties": {
    "addr:full":"3024 Grasmere Dr Greensboro NC 27410",
    "addr:housenumber":"3024",
    "addr:postcode":"27410",
    "addr:street":"Grasmere Dr",
    "iso:country":"US",
    "sg:address":"3024 Grasmere Dr",
    "sg:city":"Greensboro",
    "sg:classifiers":[
        {
            "category":"Travel",
            "subcategory":"Campground",
            "type":"Entertainment"
        }
    ],
    "sg:phone":"+1   ",
    "sg:postcode":"27410",
    "sg:province":"NC",
    "sg:tags":[
        "facility",
        "camp",
        "physical",
        "fitness"
    ],
    "wof:name":"Greensboro Black Belt Academy",
    "wof:placetype":"venue"
},
  "geometry": {"coordinates":[-79.87763200000001,36.125321],"type":"Point"}
}