{
  "type": "Feature",
  "properties": {
    "iso:country":"US",
    "sg:address":"1207 Castle Hayne Rd",
    "sg:city":"Wilmington",
    "sg:classifiers":[
        {
            "category":"Home & Garden",
            "subcategory":"Building Materials",
            "type":"Retail Goods"
        }
    ],
    "sg:phone":"+1 910 762 7747",
    "sg:postcode":"28401",
    "sg:province":"NC",
    "sg:tags":[
        "lumber"
    ],
    "sg:website":"www.godwinlumber.com",
    "wof:name":"E W Godwin's Sons Inc",
    "wof:placetype":"venue"
},
  "geometry": {"coordinates":[-77.931101,34.265368],"type":"Point"}
}