{
  "type": "Feature",
  "properties": {
    "addr:full":"2009 Truman Rd Charlotte NC 28205",
    "addr:housenumber":"2009",
    "addr:postcode":"28205",
    "addr:street":"Truman Rd",
    "iso:country":"US",
    "sg:address":"2009 Truman Rd",
    "sg:city":"Charlotte",
    "sg:classifiers":[
        {
            "category":"Professional",
            "subcategory":"Accounting & Tax Preparation",
            "type":"Services"
        }
    ],
    "sg:phone":"+1   ",
    "sg:postcode":"28205",
    "sg:province":"NC",
    "sg:tags":[
        "return"
    ],
    "wof:name":"S & R Tax Service",
    "wof:placetype":"venue"
},
  "geometry": {"coordinates":[-80.799347,35.2221],"type":"Point"}
}