{
  "type": "Feature",
  "properties": {
    "addr:full":"903 N Marietta St Gastonia NC 28054",
    "addr:housenumber":"903",
    "addr:postcode":"28054",
    "addr:street":"N Marietta St",
    "iso:country":"US",
    "sg:address":"903 N Marietta St",
    "sg:city":"Gastonia",
    "sg:classifiers":[
        {
            "category":"Wholesale",
            "subcategory":"Stationery",
            "type":"Manufacturing & Wholesale Goods"
        }
    ],
    "sg:phone":"+1 704 865 8460",
    "sg:postcode":"28054",
    "sg:province":"NC",
    "sg:tags":[
        "supply"
    ],
    "wof:name":"Gaston Business Ctr Value",
    "wof:placetype":"venue"
},
  "geometry": {"coordinates":[-81.182029,35.277068],"type":"Point"}
}