{
  "type": "Feature",
  "properties": {
    "addr:full":"13154 Saddle Club Rd Oakboro NC 28129",
    "addr:housenumber":"13154",
    "addr:postcode":"28129",
    "addr:street":"Saddle Club Rd",
    "iso:country":"US",
    "sg:address":"13154 Saddle Club Rd",
    "sg:city":"Oakboro",
    "sg:classifiers":[
        {
            "category":"Recreation",
            "type":"Entertainment"
        }
    ],
    "sg:phone":"+1 704 485 2242",
    "sg:postcode":"28129",
    "sg:province":"NC",
    "sg:tags":[
        "club",
        "membership"
    ],
    "wof:name":"West Stanly Saddle Club",
    "wof:placetype":"venue"
},
  "geometry": {"coordinates":[-80.371746,35.23582],"type":"Point"}
}