{
  "type": "Feature",
  "properties": {
    "addr:full":"109 Railroad Bed Rd Roper NC 27970",
    "addr:housenumber":"109",
    "addr:postcode":"27970",
    "addr:street":"Bed Rd",
    "iso:country":"US",
    "sg:address":"109 Railroad Bed Rd",
    "sg:city":"Roper",
    "sg:phone":"+1 252 793 2234",
    "sg:postcode":"27970",
    "sg:province":"NC",
    "sg:tags":[
        "farm",
        "corn",
        "wheat",
        "soybean"
    ],
    "wof:name":"Wade Elliott",
    "wof:placetype":"venue"
},
  "geometry": {"coordinates":[-76.593559,35.837787],"type":"Point"}
}