{
  "type": "Feature",
  "properties": {
    "addr:full":"500 Tyvola Rd Charlotte NC 28217",
    "addr:housenumber":"500",
    "addr:postcode":"28217",
    "addr:street":"Tyvola Rd",
    "iso:country":"US",
    "sg:address":"500 Tyvola Rd",
    "sg:city":"Charlotte",
    "sg:classifiers":[
        {
            "category":"Shopping",
            "subcategory":"Department Store",
            "type":"Retail Goods"
        }
    ],
    "sg:phone":"+1 704 523 8272",
    "sg:postcode":"28217",
    "sg:province":"NC",
    "wof:name":"Target",
    "wof:placetype":"venue"
},
  "geometry": {"coordinates":[-80.88515,35.163899],"type":"Point"}
}