{
  "type": "Feature",
  "properties": {
    "iso:country":"US",
    "sg:address":"2906 Azalea Dr",
    "sg:city":"Greensboro",
    "sg:classifiers":[
        {
            "category":"Professional",
            "subcategory":"Management & Consulting",
            "type":"Services"
        }
    ],
    "sg:phone":"+1   ",
    "sg:postcode":"27407",
    "sg:province":"NC",
    "sg:tags":[
        "business"
    ],
    "wof:name":"Logical Implementatn",
    "wof:placetype":"venue"
},
  "geometry": {"coordinates":[-79.843096,36.029421],"type":"Point"}
}