{
  "type": "Feature",
  "properties": {
    "iso:country":"US",
    "sg:address":"3029 Stoneybrook Dr",
    "sg:city":"Raleigh",
    "sg:classifiers":[
        {
            "category":"Banks & Credit Unions",
            "subcategory":"Bank",
            "type":"Services"
        }
    ],
    "sg:phone":"+1 919 876 8400",
    "sg:postcode":"27604",
    "sg:province":"NC",
    "sg:tags":[
        "loan",
        "real estate"
    ],
    "sg:website":"www.mtgsouth.com",
    "wof:name":"Mortgage South Financial Svc",
    "wof:placetype":"venue"
},
  "geometry": {"coordinates":[-78.592501,35.817262],"type":"Point"}
}