{
  "type": "Feature",
  "properties": {
    "iso:country":"US",
    "sg:address":"600 Palmer Dr",
    "sg:city":"Sanford",
    "sg:classifiers":[
        {
            "category":"Building & Trades",
            "subcategory":"Cleaning & Sanitation",
            "type":"Services"
        }
    ],
    "sg:phone":"+1 919 718 6800",
    "sg:postcode":"27330",
    "sg:province":"NC",
    "sg:tags":[
        "janitor",
        "maintenance"
    ],
    "wof:name":"John's Window & House Cleaning",
    "wof:placetype":"venue"
},
  "geometry": {"coordinates":[-79.19158899999999,35.48186],"type":"Point"}
}