{
  "type": "Feature",
  "properties": {
    "iso:country":"US",
    "sg:address":"10717 Leslie Dr",
    "sg:city":"Raleigh",
    "sg:classifiers":[
        {
            "category":"Manufacturing",
            "subcategory":"Apparel",
            "type":"Manufacturing & Wholesale Goods"
        }
    ],
    "sg:phone":"+1 919 841 4896",
    "sg:postcode":"27615",
    "sg:province":"NC",
    "sg:tags":[
        "closet",
        "accessory"
    ],
    "wof:name":"Affordable Closets",
    "wof:placetype":"venue"
},
  "geometry": {"coordinates":[-78.661472,35.923542],"type":"Point"}
}