{
  "type": "Feature",
  "properties": {
    "addr:full":"214 S Main St Troy NC 27371",
    "addr:housenumber":"214",
    "addr:postcode":"27371",
    "addr:street":"S Main St",
    "iso:country":"US",
    "sg:address":"214 S Main St",
    "sg:city":"Troy",
    "sg:classifiers":[
        {
            "category":"Autos & Motor Vehicles",
            "subcategory":"Automobile Sales",
            "type":"Retail Goods"
        }
    ],
    "sg:phone":"+1 910 572 1351",
    "sg:postcode":"27371",
    "sg:province":"NC",
    "sg:tags":[
        "car",
        "dealer"
    ],
    "sg:website":"www.montgomerymotors.com",
    "wof:name":"Montgomery Motors Inc",
    "wof:placetype":"venue"
},
  "geometry": {"coordinates":[-79.893809,35.357567],"type":"Point"}
}