{
  "type": "Feature",
  "properties": {
    "iso:country":"US",
    "sg:address":"1613 Montford Dr",
    "sg:city":"Charlotte",
    "sg:classifiers":[
        {
            "category":"Personal",
            "subcategory":"Beauty Salon",
            "type":"Services"
        }
    ],
    "sg:phone":"+1 704 525 6684",
    "sg:postcode":"28209",
    "sg:province":"NC",
    "sg:tags":[
        "shop"
    ],
    "wof:name":"Royal Treatment Styling Studio",
    "wof:placetype":"venue"
},
  "geometry": {"coordinates":[-80.848477,35.170779],"type":"Point"}
}