{
  "type": "Feature",
  "properties": {
    "iso:country":"US",
    "sg:address":"101 West St",
    "sg:city":"Black Mountain",
    "sg:classifiers":[
        {
            "category":"Health Services",
            "subcategory":"Health Practitioner",
            "type":"Services"
        }
    ],
    "sg:phone":"+1 828 664 1522",
    "sg:postcode":"28711",
    "sg:province":"NC",
    "sg:tags":[
        "psychologist"
    ],
    "wof:name":"R Jey Hiott",
    "wof:placetype":"venue"
},
  "geometry": {"coordinates":[-82.320313,35.618991],"type":"Point"}
}