{
  "type": "Feature",
  "properties": {
    "iso:country":"US",
    "sg:address":"13 Rhododendron Way",
    "sg:city":"Candler",
    "sg:classifiers":[
        {
            "category":"Professional",
            "type":"Services"
        }
    ],
    "sg:phone":"+1   ",
    "sg:postcode":"28715",
    "sg:province":"NC",
    "wof:name":"Ministries Resouces",
    "wof:placetype":"venue"
},
  "geometry": {"coordinates":[-82.67444500000001,35.568947],"type":"Point"}
}