{
  "type": "Feature",
  "properties": {
    "iso:country":"US",
    "sg:address":"5901 Falls of Neuse Rd",
    "sg:city":"Raleigh",
    "sg:classifiers":[
        {
            "category":"Banks & Credit Unions",
            "subcategory":"Bank",
            "type":"Services"
        }
    ],
    "sg:phone":"+1 919 790 8300",
    "sg:postcode":"27609",
    "sg:province":"NC",
    "sg:tags":[
        "loan",
        "real estate"
    ],
    "wof:name":"Mortgage Mecca",
    "wof:placetype":"venue"
},
  "geometry": {"coordinates":[-78.620099,35.864281],"type":"Point"}
}