{
  "type": "Feature",
  "properties": {
    "iso:country":"US",
    "sg:address":"706 Henry St",
    "sg:city":"Shelby",
    "sg:classifiers":[
        {
            "category":"Shopping",
            "subcategory":"Beauty & Cosmetics",
            "type":"Retail Goods"
        }
    ],
    "sg:phone":"+1 704 481 9800",
    "sg:postcode":"28170",
    "sg:province":"NC",
    "sg:tags":[
        "merchandise"
    ],
    "wof:name":"Versatile Expressions",
    "wof:placetype":"venue"
},
  "geometry": {"coordinates":[-80.085279,34.971361],"type":"Point"}
}