{
  "type": "Feature",
  "properties": {
    "iso:country":"US",
    "sg:address":"2102 W Cumberland St",
    "sg:city":"Dunn",
    "sg:classifiers":[
        {
            "category":"Bars & Pubs",
            "type":"Food & Drink"
        }
    ],
    "sg:menulink":"http://www.allmenus.com/nc/averasboro/150996-smithfields-chicken-n-bar-b-q/menu/",
    "sg:phone":"+1 910 892 2693",
    "sg:postcode":"28334",
    "sg:province":"NC",
    "sg:tags":[
        "american"
    ],
    "wof:name":"Smithfield's Chicken 'n Bar-b-q ",
    "wof:placetype":"venue"
},
  "geometry": {"coordinates":[-78.633867,35.320327],"type":"Point"}
}