{
  "type": "Feature",
  "properties": {
    "addr:full":"2 Summitview Ct Greensboro NC 27405",
    "addr:housenumber":"2",
    "addr:postcode":"27405",
    "addr:street":"Summitview Ct",
    "iso:country":"US",
    "sg:address":"2 Summitview Ct",
    "sg:city":"Greensboro",
    "sg:classifiers":[
        {
            "category":"Professional",
            "type":"Services"
        }
    ],
    "sg:phone":"+1 336 375 3156",
    "sg:postcode":"27405",
    "sg:province":"NC",
    "wof:name":"Fletcher Donnell",
    "wof:placetype":"venue"
},
  "geometry": {"coordinates":[-79.749025,36.139086],"type":"Point"}
}