{
  "type": "Feature",
  "properties": {
    "addr:full":"1511 Airport Rd Hamlet NC 28345",
    "addr:housenumber":"1511",
    "addr:postcode":"28345",
    "addr:street":"Airport Rd",
    "iso:country":"US",
    "sg:address":"1511 Airport Rd",
    "sg:city":"Hamlet",
    "sg:classifiers":[
        {
            "category":"Building & Trades",
            "subcategory":"Construction",
            "type":"Services"
        }
    ],
    "sg:phone":"+1 910 582 4546",
    "sg:postcode":"28345",
    "sg:province":"NC",
    "sg:tags":[
        "contractor"
    ],
    "wof:name":"Ace Masonry Inc",
    "wof:placetype":"venue"
},
  "geometry": {"coordinates":[-79.73307800000001,34.850368],"type":"Point"}
}