{
  "type": "Feature",
  "properties": {
    "iso:country":"US",
    "sg:address":"304 White Rd",
    "sg:city":"Creswell",
    "sg:classifiers":[
        {
            "category":"Professional",
            "subcategory":"Business Services",
            "type":"Services"
        }
    ],
    "sg:phone":"+1 252 797 4528",
    "sg:postcode":"27928",
    "sg:province":"NC",
    "sg:tags":[
        "auctioneer"
    ],
    "wof:name":"Bill Forbes & Assoc",
    "wof:placetype":"venue"
},
  "geometry": {"coordinates":[-76.45115199999999,35.848222],"type":"Point"}
}