{
  "type": "Feature",
  "properties": {
    "iso:country":"US",
    "sg:address":"7538 Highlands Rd",
    "sg:city":"Franklin",
    "sg:classifiers":[
        {
            "category":"Building & Trades",
            "subcategory":"Landscaping Services",
            "type":"Services"
        }
    ],
    "sg:phone":"+1 828 369 6635",
    "sg:postcode":"28734",
    "sg:province":"NC",
    "wof:name":"Ronald Hooper",
    "wof:placetype":"venue"
},
  "geometry": {"coordinates":[-83.281328,35.131799],"type":"Point"}
}