{
  "type": "Feature",
  "properties": {
    "addr:full":"39 White Oak Trl Chapel Hill NC 27516",
    "addr:housenumber":"39",
    "addr:postcode":"27516",
    "addr:street":"White Oak Trl",
    "iso:country":"US",
    "sg:address":"39 White Oak Trl",
    "sg:city":"Chapel Hill",
    "sg:classifiers":[
        {
            "category":"Professional",
            "subcategory":"Business Services",
            "type":"Services"
        }
    ],
    "sg:phone":"+1   ",
    "sg:postcode":"27516",
    "sg:province":"NC",
    "wof:name":"Foushees Business MGT Svcs In",
    "wof:placetype":"venue"
},
  "geometry": {"coordinates":[-79.122917,35.84267],"type":"Point"}
}