{
  "type": "Feature",
  "properties": {
    "iso:country":"US",
    "sg:address":"2017 E 5th St",
    "sg:city":"Lumberton",
    "sg:classifiers":[
        {
            "category":"Manufacturing",
            "subcategory":"Tools & Machinery",
            "type":"Manufacturing & Wholesale Goods"
        }
    ],
    "sg:phone":"+1 910 739 3072",
    "sg:postcode":"28358",
    "sg:province":"NC",
    "sg:tags":[
        "machine",
        "shop"
    ],
    "wof:name":"Taylor Enterprises",
    "wof:placetype":"venue"
},
  "geometry": {"coordinates":[-78.977132,34.610617],"type":"Point"}
}