{
  "type": "Feature",
  "properties": {
    "addr:full":"5629 Quail Covey Ln Wendell NC 27591",
    "addr:housenumber":"5629",
    "addr:postcode":"27591",
    "addr:street":"Quail Covey Ln",
    "iso:country":"US",
    "sg:address":"5629 Quail Covey Ln",
    "sg:city":"Wendell",
    "sg:classifiers":[
        {
            "category":"Building & Trades",
            "subcategory":"Cleaning & Sanitation",
            "type":"Services"
        },
        {
            "category":"Building & Trades",
            "subcategory":"Construction",
            "type":"Services"
        }
    ],
    "sg:phone":"+1 919 261 0900",
    "sg:postcode":"27591",
    "sg:province":"NC",
    "sg:tags":[
        "maintenance",
        "contractor"
    ],
    "wof:name":"Four Seasons Maintenance Svc",
    "wof:placetype":"venue"
},
  "geometry": {"coordinates":[-78.44549499999999,35.83989],"type":"Point"}
}