{
  "type": "Feature",
  "properties": {
    "iso:country":"US",
    "sg:address":"211 Crockett Ave",
    "sg:city":"New Bern",
    "sg:classifiers":[
        {
            "category":"Building & Trades",
            "subcategory":"Electrical",
            "type":"Services"
        }
    ],
    "sg:phone":"+1 252 638 6371",
    "sg:postcode":"28560",
    "sg:province":"NC",
    "sg:tags":[
        "electrical",
        "electric",
        "contractor"
    ],
    "wof:name":"Fordham's Electrical Svc",
    "wof:placetype":"venue"
},
  "geometry": {"coordinates":[-77.014696,35.14237],"type":"Point"}
}