{
  "type": "Feature",
  "properties": {
    "iso:country":"US",
    "sg:address":"3307 Aspendale Ln",
    "sg:city":"Charlotte",
    "sg:classifiers":[
        {
            "category":"Building & Trades",
            "subcategory":"Landscaping Services",
            "type":"Services"
        }
    ],
    "sg:phone":"+1 704 569 1776",
    "sg:postcode":"28212",
    "sg:province":"NC",
    "sg:tags":[
        "tree"
    ],
    "wof:name":"Badeaux Arborscapes",
    "wof:placetype":"venue"
},
  "geometry": {"coordinates":[-80.754374,35.188402],"type":"Point"}
}