{
  "type": "Feature",
  "properties": {
    "addr:full":"5417 Thornburg Dr Wake Forest NC 27587",
    "addr:postcode":"5417;27587",
    "addr:street":"Thornburg Dr",
    "iso:country":"US",
    "sg:address":"5417 Thornburg Dr",
    "sg:city":"Wake Forest",
    "sg:classifiers":[
        {
            "category":"Professional",
            "subcategory":"Secretarial Services",
            "type":"Services"
        }
    ],
    "sg:phone":"+1   ",
    "sg:postcode":"27587",
    "sg:province":"NC",
    "sg:tags":[
        "reporting"
    ],
    "wof:name":"Architext Inc",
    "wof:placetype":"venue"
},
  "geometry": {"coordinates":[-78.42475399999999,35.927969],"type":"Point"}
}