{
  "type": "Feature",
  "properties": {
    "iso:country":"US",
    "sg:address":"625 E Country Day Rd",
    "sg:city":"Goldsboro",
    "sg:classifiers":[
        {
            "category":"Health Services",
            "subcategory":"Doctor",
            "type":"Services"
        }
    ],
    "sg:phone":"+1 919 731 4048",
    "sg:postcode":"27530",
    "sg:province":"NC",
    "sg:tags":[
        "physician",
        "surgeon",
        "medical"
    ],
    "sg:website":"www.goldsboroneurosurgery.com",
    "wof:name":"Goldsboro Neurological Surgery",
    "wof:placetype":"venue"
},
  "geometry": {"coordinates":[-77.96125600000001,35.404457],"type":"Point"}
}