{
  "type": "Feature",
  "properties": {
    "addr:full":"203 Trans Air Dr Morrisville NC 27560",
    "addr:housenumber":"203",
    "addr:postcode":"27560",
    "addr:street":"Trans Air Dr",
    "iso:country":"US",
    "sg:address":"203 Trans Air Dr",
    "sg:city":"Morrisville",
    "sg:classifiers":[
        {
            "category":"Wholesale",
            "subcategory":"Fruits & Vegetables",
            "type":"Manufacturing & Wholesale Goods"
        }
    ],
    "sg:phone":"+1 919 468 9441",
    "sg:postcode":"27560",
    "sg:province":"NC",
    "wof:name":"Overton Distributors Inc",
    "wof:placetype":"venue"
},
  "geometry": {"coordinates":[-78.818972,35.850628],"type":"Point"}
}