{
  "type": "Feature",
  "properties": {
    "addr:full":"3901 Capital Blvd Raleigh NC 27604",
    "addr:housenumber":"3901",
    "addr:postcode":"27604",
    "addr:street":"Capital Blvd",
    "iso:country":"US",
    "sg:address":"3901 Capital Blvd",
    "sg:city":"Raleigh",
    "sg:classifiers":[
        {
            "category":"Shopping",
            "subcategory":"Clothing, Apparel, & Fashions",
            "type":"Retail Goods"
        }
    ],
    "sg:phone":"+1 919 876 4248",
    "sg:postcode":"27604",
    "sg:province":"NC",
    "sg:tags":[
        "boutique"
    ],
    "wof:name":"Funky Rags Inc",
    "wof:placetype":"venue"
},
  "geometry": {"coordinates":[-78.58093599999999,35.837264],"type":"Point"}
}