{
  "type": "Feature",
  "properties": {
    "iso:country":"US",
    "sg:address":"8760 Kennebec Rd",
    "sg:city":"Willow Spring",
    "sg:classifiers":[
        {
            "category":"Recreation",
            "type":"Entertainment"
        }
    ],
    "sg:phone":"+1   ",
    "sg:postcode":"27592",
    "sg:province":"NC",
    "wof:name":"Saddletree Stables",
    "wof:placetype":"venue"
},
  "geometry": {"coordinates":[-78.72553499999999,35.549857],"type":"Point"}
}