{
  "type": "Feature",
  "properties": {
    "addr:full":"356 Carpenters Grove Church Rd Lawndale NC 28090",
    "addr:housenumber":"356",
    "addr:postcode":"28090",
    "addr:street":"Carpenters Grove Church Rd",
    "iso:country":"US",
    "sg:address":"356 Carpenters Grove Church Rd",
    "sg:city":"Lawndale",
    "sg:classifiers":[
        {
            "category":"Professional",
            "subcategory":"Detective & Security Services",
            "type":"Services"
        }
    ],
    "sg:phone":"+1   ",
    "sg:postcode":"28090",
    "sg:province":"NC",
    "sg:tags":[
        "car"
    ],
    "wof:name":"Lawn Patrol",
    "wof:placetype":"venue"
},
  "geometry": {"coordinates":[-81.533736,35.482486],"type":"Point"}
}