{
  "type": "Feature",
  "properties": {
    "addr:full":"312 Perry Williams Rd Hamlet NC 28345",
    "addr:housenumber":"312",
    "addr:postcode":"28345",
    "addr:street":"Perry Williams Rd",
    "iso:country":"US",
    "sg:address":"312 Perry Williams Rd",
    "sg:city":"Hamlet",
    "sg:classifiers":[
        {
            "category":"Bus Charters",
            "type":"Transportation"
        }
    ],
    "sg:phone":"+1 910 582 5899",
    "sg:postcode":"28345",
    "sg:province":"NC",
    "sg:tags":[
        "rental"
    ],
    "wof:name":"Travel Tours Unlimited Inc",
    "wof:placetype":"venue"
},
  "geometry": {"coordinates":[-79.675337,34.850247],"type":"Point"}
}