{
  "type": "Feature",
  "properties": {
    "addr:full":"158 Wakelon St Zebulon NC 27597",
    "addr:housenumber":"158",
    "addr:postcode":"27597",
    "addr:street":"Wakelon St",
    "iso:country":"US",
    "sg:address":"158 Wakelon St",
    "sg:city":"Zebulon",
    "sg:classifiers":[
        {
            "category":"Personal",
            "subcategory":"Beauty Salon",
            "type":"Services"
        }
    ],
    "sg:phone":"+1   ",
    "sg:postcode":"27597",
    "sg:province":"NC",
    "sg:tags":[
        "shop"
    ],
    "wof:name":"Lovely Nail",
    "wof:placetype":"venue"
},
  "geometry": {"coordinates":[-78.317711,35.833118],"type":"Point"}
}