{
  "type": "Feature",
  "properties": {
    "iso:country":"US",
    "sg:address":"5102 York Hwy",
    "sg:city":"Gastonia",
    "sg:classifiers":[
        {
            "category":"Restaurant",
            "type":"Food & Drink"
        }
    ],
    "sg:phone":"+1 704 867 1790",
    "sg:postcode":"28052",
    "sg:province":"NC",
    "sg:tags":[
        "eating"
    ],
    "wof:name":"Dans Quick Pik",
    "wof:placetype":"venue"
},
  "geometry": {"coordinates":[-81.203033,35.179214],"type":"Point"}
}