{
  "type": "Feature",
  "properties": {
    "addr:full":"301 Glenwood Ave Raleigh NC 27603",
    "addr:housenumber":"301",
    "addr:postcode":"27603",
    "addr:street":"Glenwood Ave",
    "iso:country":"US",
    "sg:address":"301 Glenwood Ave",
    "sg:city":"Raleigh",
    "sg:classifiers":[
        {
            "category":"Professional",
            "subcategory":"Management & Consulting",
            "type":"Services"
        }
    ],
    "sg:phone":"+1 919 829 0888",
    "sg:postcode":"27603",
    "sg:province":"NC",
    "sg:tags":[
        "facility",
        "consultant",
        "planning",
        "space"
    ],
    "wof:name":"Momentum Group",
    "wof:placetype":"venue"
},
  "geometry": {"coordinates":[-78.64733099999999,35.784908],"type":"Point"}
}