{
  "type": "Feature",
  "properties": {
    "iso:country":"US",
    "sg:address":"2630 Merritt Dr",
    "sg:city":"Greensboro",
    "sg:classifiers":[
        {
            "category":"Professional",
            "type":"Services"
        }
    ],
    "sg:phone":"+1 336 292 2438",
    "sg:postcode":"27407",
    "sg:province":"NC",
    "wof:name":"Betsys Best Inc",
    "wof:placetype":"venue"
},
  "geometry": {"coordinates":[-79.862044,36.031083],"type":"Point"}
}