{
  "type": "Feature",
  "properties": {
    "addr:full":"163 Moody Farm Rd Maggie Valley NC 28751",
    "addr:housenumber":"163",
    "addr:postcode":"28751",
    "addr:street":"Moody Farm Rd",
    "iso:country":"US",
    "sg:address":"163 Moody Farm Rd",
    "sg:city":"Maggie Valley",
    "sg:classifiers":[
        {
            "category":"Travel",
            "subcategory":"Hotels & Motels",
            "type":"Entertainment"
        }
    ],
    "sg:phone":"+1 828 926 1231",
    "sg:postcode":"28751",
    "sg:province":"NC",
    "sg:tags":[
        "house",
        "operation",
        "construction"
    ],
    "wof:name":"Cozy Creek Cottages",
    "wof:placetype":"venue"
},
  "geometry": {"coordinates":[-83.03971300000001,35.520681],"type":"Point"}
}