{
  "type": "Feature",
  "properties": {
    "iso:country":"US",
    "sg:address":"257 Taylor Town Rd",
    "sg:city":"Faison",
    "sg:classifiers":[
        {
            "category":"Farming",
            "subcategory":"Farm",
            "type":"Manufacturing & Wholesale Goods"
        }
    ],
    "sg:phone":"+1 910 293 4321",
    "sg:postcode":"28341",
    "sg:province":"NC",
    "sg:tags":[
        "crop",
        "general"
    ],
    "wof:name":"Marcus Taylor",
    "wof:placetype":"venue"
},
  "geometry": {"coordinates":[-78.070058,35.07725],"type":"Point"}
}