{
  "type": "Feature",
  "properties": {
    "iso:country":"US",
    "sg:address":"61 W Williams St",
    "sg:city":"Angier",
    "sg:classifiers":[
        {
            "category":"Food & Beverages",
            "subcategory":"Bakery",
            "type":"Retail Goods"
        }
    ],
    "sg:phone":"+1 919 639 6559",
    "sg:postcode":"27501",
    "sg:province":"NC",
    "sg:tags":[
        "baker"
    ],
    "wof:name":"LA Estrella",
    "wof:placetype":"venue"
},
  "geometry": {"coordinates":[-78.740219,35.508265],"type":"Point"}
}