{
  "type": "Feature",
  "properties": {
    "iso:country":"US",
    "sg:address":"106 Rockspring Rd",
    "sg:city":"High Point",
    "sg:classifiers":[
        {
            "category":"Shopping",
            "subcategory":"Computers & Home Electronics",
            "type":"Retail Goods"
        }
    ],
    "sg:phone":"+1 336 889 8429",
    "sg:postcode":"27262",
    "sg:province":"NC",
    "sg:tags":[
        "high",
        "fidelity",
        "stereophonic"
    ],
    "wof:name":"Car Stereo Connection",
    "wof:placetype":"venue"
},
  "geometry": {"coordinates":[-80.01993899999999,35.974994],"type":"Point"}
}