{
  "type": "Feature",
  "properties": {
    "iso:country":"US",
    "sg:address":"4430 Park Rd",
    "sg:city":"Charlotte",
    "sg:classifiers":[
        {
            "category":"Professional",
            "subcategory":"Lawyer & Legal Services",
            "type":"Services"
        }
    ],
    "sg:phone":"+1 704 525 1702",
    "sg:postcode":"28209",
    "sg:province":"NC",
    "sg:tags":[
        "attorney"
    ],
    "wof:name":"Lancaster & Trotter",
    "wof:placetype":"venue"
},
  "geometry": {"coordinates":[-80.85118,35.171806],"type":"Point"}
}