{
  "type": "Feature",
  "properties": {
    "iso:country":"US",
    "sg:address":"103 E Pine St",
    "sg:city":"Farmville",
    "sg:classifiers":[
        {
            "category":"Personal",
            "subcategory":"Beauty Salon",
            "type":"Services"
        }
    ],
    "sg:phone":"+1 252 753 4665",
    "sg:postcode":"27828",
    "sg:province":"NC",
    "wof:name":"Luann's Beauty Nook",
    "wof:placetype":"venue"
},
  "geometry": {"coordinates":[-77.58739799999999,35.595021],"type":"Point"}
}