{
  "type": "Feature",
  "properties": {
    "iso:country":"US",
    "sg:address":"112 Crooked Gulley Cir",
    "sg:city":"Sunset Beach",
    "sg:classifiers":[
        {
            "category":"Professional",
            "subcategory":"Computer Services",
            "type":"Services"
        }
    ],
    "sg:phone":"+1 910 579 2840",
    "sg:postcode":"28468",
    "sg:province":"NC",
    "sg:tags":[
        "consultant",
        "designer",
        "programing",
        "custom"
    ],
    "wof:name":"Dependable Data Base Inc",
    "wof:placetype":"venue"
},
  "geometry": {"coordinates":[-78.514785,33.894829],"type":"Point"}
}