{
  "type": "Feature",
  "properties": {
    "iso:country":"US",
    "sg:address":"106 Creedmore Dr",
    "sg:city":"Statesville",
    "sg:classifiers":[
        {
            "category":"Building & Trades",
            "subcategory":"Construction",
            "type":"Services"
        }
    ],
    "sg:phone":"+1 704 876 3800",
    "sg:postcode":"28625",
    "sg:province":"NC",
    "sg:tags":[
        "home",
        "builder"
    ],
    "wof:name":"Upright Builders",
    "wof:placetype":"venue"
},
  "geometry": {"coordinates":[-80.81972399999999,35.871206],"type":"Point"}
}