{
  "type": "Feature",
  "properties": {
    "addr:full":"2566 Chandy St Newton NC 28658",
    "addr:housenumber":"2566",
    "addr:postcode":"28658",
    "addr:street":"Chandy St",
    "iso:country":"US",
    "sg:address":"2566 Chandy St",
    "sg:city":"Newton",
    "sg:classifiers":[
        {
            "category":"Wholesale",
            "subcategory":"Durable Goods & Equipment",
            "type":"Manufacturing & Wholesale Goods"
        }
    ],
    "sg:phone":"+1 828 244 6092",
    "sg:postcode":"28658",
    "sg:province":"NC",
    "sg:tags":[
        "merchant",
        "import",
        "broker",
        "for"
    ],
    "wof:name":"T & L Distribution",
    "wof:placetype":"venue"
},
  "geometry": {"coordinates":[-81.274107,35.658908],"type":"Point"}
}