{
  "type": "Feature",
  "properties": {
    "addr:full":"731 Joseph Antoon Cir Stanley NC 28164",
    "addr:housenumber":"731",
    "addr:postcode":"28164",
    "addr:street":"Joseph Antoon Cir",
    "iso:country":"US",
    "sg:address":"731 Joseph Antoon Cir",
    "sg:city":"Stanley",
    "sg:classifiers":[
        {
            "category":"Professional",
            "subcategory":"Art Services",
            "type":"Services"
        }
    ],
    "sg:phone":"+1 704 263 2319",
    "sg:postcode":"28164",
    "sg:province":"NC",
    "sg:tags":[
        "graphic",
        "designer"
    ],
    "wof:name":"Ozmas Graphics",
    "wof:placetype":"venue"
},
  "geometry": {"coordinates":[-81.11726899999999,35.347239],"type":"Point"}
}