{
  "type": "Feature",
  "properties": {
    "addr:full":"908 E Main St Benson NC 27504",
    "addr:housenumber":"908",
    "addr:postcode":"27504",
    "addr:street":"E Main St",
    "iso:country":"US",
    "sg:address":"908 E Main St",
    "sg:city":"Benson",
    "sg:classifiers":[
        {
            "category":"Wholesale",
            "subcategory":"Fruits & Vegetables",
            "type":"Manufacturing & Wholesale Goods"
        }
    ],
    "sg:phone":"+1 919 894 3171",
    "sg:postcode":"27504",
    "sg:province":"NC",
    "wof:name":"C C Barefoot & Co",
    "wof:placetype":"venue"
},
  "geometry": {"coordinates":[-78.53769699999999,35.375296],"type":"Point"}
}