{
  "type": "Feature",
  "properties": {
    "addr:full":"822 Broad St Durham NC 27705",
    "addr:housenumber":"822",
    "addr:postcode":"27705",
    "addr:street":"Broad St",
    "iso:country":"US",
    "sg:address":"822 Broad St",
    "sg:city":"Durham",
    "sg:classifiers":[
        {
            "category":"Personal",
            "type":"Services"
        }
    ],
    "sg:phone":"+1 919 286 5877",
    "sg:postcode":"27705",
    "sg:province":"NC",
    "sg:tags":[
        "therapist",
        "massage"
    ],
    "wof:name":"Broad Street Rolfing",
    "wof:placetype":"venue"
},
  "geometry": {"coordinates":[-78.919434,36.011339],"type":"Point"}
}