{
  "type": "Feature",
  "properties": {
    "addr:full":"5672 Butler Rd Fairmont NC 28340",
    "addr:housenumber":"5672",
    "addr:postcode":"28340",
    "addr:street":"Butler Rd",
    "iso:country":"US",
    "sg:address":"5672 Butler Rd",
    "sg:city":"Fairmont",
    "sg:classifiers":[
        {
            "category":"Organizations",
            "subcategory":"Religious Organization",
            "type":"Services"
        }
    ],
    "sg:phone":"+1 910 422 9776",
    "sg:postcode":"28340",
    "sg:province":"NC",
    "sg:tags":[
        "church"
    ],
    "wof:name":"Rose Hill Baptist Church",
    "wof:placetype":"venue"
},
  "geometry": {"coordinates":[-79.247359,34.45478],"type":"Point"}
}