{
  "type": "Feature",
  "properties": {
    "iso:country":"US",
    "sg:address":"103 Shamrock Dr",
    "sg:city":"Morganton",
    "sg:classifiers":[
        {
            "category":"Professional",
            "subcategory":"Art Services",
            "type":"Services"
        }
    ],
    "sg:phone":"+1   ",
    "sg:postcode":"28655",
    "sg:province":"NC",
    "wof:name":"Randalls J Photography",
    "wof:placetype":"venue"
},
  "geometry": {"coordinates":[-81.68988400000001,35.702468],"type":"Point"}
}