{
  "type": "Feature",
  "properties": {
    "addr:full":"1409 Grove Point Rd Wilmington NC 28409",
    "addr:housenumber":"1409",
    "addr:postcode":"28409",
    "addr:street":"Grove Point Rd",
    "iso:country":"US",
    "sg:address":"1409 Grove Point Rd",
    "sg:city":"Wilmington",
    "sg:classifiers":[
        {
            "category":"Banks & Credit Unions",
            "subcategory":"Investment Brokerage",
            "type":"Services"
        }
    ],
    "sg:phone":"+1 910 395 0022",
    "sg:postcode":"28409",
    "sg:province":"NC",
    "sg:tags":[
        "security"
    ],
    "wof:name":"Main Street Management",
    "wof:placetype":"venue"
},
  "geometry": {"coordinates":[-77.892608,34.106393],"type":"Point"}
}