{
  "type": "Feature",
  "properties": {
    "iso:country":"US",
    "sg:address":"100 Maypatch Rd",
    "sg:city":"Jacksonville",
    "sg:classifiers":[
        {
            "category":"Professional",
            "subcategory":"Business Services",
            "type":"Services"
        }
    ],
    "sg:phone":"+1 910 577 1406",
    "sg:postcode":"28546",
    "sg:province":"NC",
    "wof:name":"Muzak",
    "wof:placetype":"venue"
},
  "geometry": {"coordinates":[-77.38584299999999,34.746513],"type":"Point"}
}