{
  "type": "Feature",
  "properties": {
    "iso:country":"US",
    "sg:address":"300 Setliff Rd",
    "sg:city":"Reidsville",
    "sg:classifiers":[
        {
            "category":"Social Services",
            "subcategory":"Child Care",
            "type":"Services"
        }
    ],
    "sg:phone":"+1   ",
    "sg:postcode":"27320",
    "sg:province":"NC",
    "sg:tags":[
        "day"
    ],
    "wof:name":"Creative World Inc",
    "wof:placetype":"venue"
},
  "geometry": {"coordinates":[-79.710572,36.38815],"type":"Point"}
}