{
  "type": "Feature",
  "properties": {
    "addr:full":"2400 Terminal Blvd Morrisville NC 27560",
    "addr:housenumber":"2400",
    "addr:postcode":"27560",
    "addr:street":"Terminal Blvd",
    "iso:country":"US",
    "sg:address":"2400 Terminal Blvd",
    "sg:city":"Morrisville",
    "sg:classifiers":[
        {
            "category":"Taxi",
            "type":"Transportation"
        }
    ],
    "sg:phone":"+1 919 840 5850",
    "sg:postcode":"27560",
    "sg:province":"NC",
    "sg:website":"www.rdctaxi.com",
    "wof:name":"Rdc Taxi Service",
    "wof:placetype":"venue"
},
  "geometry": {"coordinates":[-78.80399,35.867386],"type":"Point"}
}