{
  "type": "Feature",
  "properties": {
    "iso:country":"US",
    "sg:address":"4127 Park Rd",
    "sg:city":"Charlotte",
    "sg:classifiers":[
        {
            "category":"Restaurant",
            "type":"Food & Drink"
        }
    ],
    "sg:phone":"+1 704 523 0431",
    "sg:postcode":"28209",
    "sg:province":"NC",
    "wof:name":"Charlotte Cafe",
    "wof:placetype":"venue"
},
  "geometry": {"coordinates":[-80.851032,35.174822],"type":"Point"}
}