{
  "type": "Feature",
  "properties": {
    "iso:country":"US",
    "sg:address":"2900 Spring Forest Rd Ste 108",
    "sg:city":"Raleigh",
    "sg:classifiers":[
        {
            "category":"Personal",
            "subcategory":"Beauty Salon",
            "type":"Services"
        }
    ],
    "sg:phone":"+1 919 649 4932",
    "sg:postcode":"27616",
    "sg:province":"NC",
    "sg:tags":[
        "hair",
        "stylist"
    ],
    "wof:name":"Salon & Spa",
    "wof:placetype":"venue"
},
  "geometry": {"coordinates":[-78.591713,35.855549],"type":"Point"}
}