{
  "type": "Feature",
  "properties": {
    "addr:full":"335 Knollwood Dr Hampstead NC 28443",
    "addr:housenumber":"335",
    "addr:postcode":"28443",
    "addr:street":"Knollwood Dr",
    "iso:country":"US",
    "sg:address":"335 Knollwood Dr",
    "sg:city":"Hampstead",
    "sg:classifiers":[
        {
            "category":"Wholesale",
            "subcategory":"Machinery & Supplies",
            "type":"Manufacturing & Wholesale Goods"
        }
    ],
    "sg:phone":"+1 910 270 1460",
    "sg:postcode":"28443",
    "sg:province":"NC",
    "sg:tags":[
        "engine"
    ],
    "wof:name":"G & G Onsite",
    "wof:placetype":"venue"
},
  "geometry": {"coordinates":[-77.77774599999999,34.383603],"type":"Point"}
}