{
  "type": "Feature",
  "properties": {
    "addr:full":"302 E Colonial Ave Elizabeth City NC 27909",
    "addr:housenumber":"302",
    "addr:postcode":"27909",
    "addr:street":"E Colonial Ave",
    "iso:country":"US",
    "sg:address":"302 E Colonial Ave",
    "sg:city":"Elizabeth City",
    "sg:classifiers":[
        {
            "category":"Government",
            "subcategory":"Office",
            "type":"Public Place"
        }
    ],
    "sg:phone":"+1 252 337 6864",
    "sg:postcode":"27909",
    "sg:province":"NC",
    "sg:tags":[
        "city"
    ],
    "wof:name":"Elizabeth City Manager",
    "wof:placetype":"venue"
},
  "geometry": {"coordinates":[-76.221946,36.30082],"type":"Point"}
}