{
  "type": "Feature",
  "properties": {
    "iso:country":"US",
    "sg:address":"133 Clay Ridge Way",
    "sg:city":"Holly Springs",
    "sg:classifiers":[
        {
            "category":"Retail",
            "subcategory":"Animal Services",
            "type":"Services"
        }
    ],
    "sg:phone":"+1 919 557 2853",
    "sg:postcode":"27540",
    "sg:province":"NC",
    "sg:tags":[
        "training",
        "dog"
    ],
    "wof:name":"Best Paw Forward Dog Edu Inc",
    "wof:placetype":"venue"
},
  "geometry": {"coordinates":[-78.843017,35.651666],"type":"Point"}
}