{
  "type": "Feature",
  "properties": {
    "addr:full":"904 Queensbury Cir Durham NC 27713",
    "addr:housenumber":"904",
    "addr:postcode":"27713",
    "addr:street":"Queensbury Cir",
    "iso:country":"US",
    "sg:address":"904 Queensbury Cir",
    "sg:city":"Durham",
    "sg:classifiers":[
        {
            "category":"Manufacturing",
            "subcategory":"Chemicals & Compounds",
            "type":"Manufacturing & Wholesale Goods"
        }
    ],
    "sg:phone":"+1 919 361 1910",
    "sg:postcode":"27713",
    "sg:province":"NC",
    "sg:tags":[
        "mfg"
    ],
    "wof:name":"Hxtal Corp",
    "wof:placetype":"venue"
},
  "geometry": {"coordinates":[-78.927778,35.879276],"type":"Point"}
}