{
  "type": "Feature",
  "properties": {
    "addr:full":"341 Brandywine Rd Charlotte NC 28209",
    "addr:housenumber":"341",
    "addr:postcode":"28209",
    "addr:street":"Brandywine Rd",
    "iso:country":"US",
    "sg:address":"341 Brandywine Rd",
    "sg:city":"Charlotte",
    "sg:classifiers":[
        {
            "category":"Home & Garden",
            "subcategory":"Home Furnishings",
            "type":"Retail Goods"
        }
    ],
    "sg:phone":"+1 704 347 1712",
    "sg:postcode":"28209",
    "sg:province":"NC",
    "sg:tags":[
        "house",
        "decor"
    ],
    "wof:name":"Presenting",
    "wof:placetype":"venue"
},
  "geometry": {"coordinates":[-80.8436,35.173272],"type":"Point"}
}