{
  "type": "Feature",
  "properties": {
    "addr:full":"34 Warren Ave Council NC 28434",
    "addr:housenumber":"34",
    "addr:postcode":"28434",
    "addr:street":"Warren Ave",
    "iso:country":"US",
    "sg:address":"34 Warren Ave",
    "sg:city":"Council",
    "sg:classifiers":[
        {
            "category":"Organizations",
            "subcategory":"Religious Organization",
            "type":"Services"
        }
    ],
    "sg:phone":"+1 910 645 4588",
    "sg:postcode":"28434",
    "sg:province":"NC",
    "sg:tags":[
        "church"
    ],
    "wof:name":"Evangelistic Outreach Mnstrs",
    "wof:placetype":"venue"
},
  "geometry": {"coordinates":[-78.45682600000001,34.522196],"type":"Point"}
}