{
  "type": "Feature",
  "properties": {
    "addr:full":"1719 Montford Dr Charlotte NC 28209",
    "addr:housenumber":"1719",
    "addr:postcode":"28209",
    "addr:street":"Montford Dr",
    "iso:country":"US",
    "sg:address":"1719 Montford Dr",
    "sg:city":"Charlotte",
    "sg:classifiers":[
        {
            "category":"Shopping",
            "subcategory":"Clothing, Apparel, & Fashions",
            "type":"Retail Goods"
        },
        {
            "category":"Retail",
            "subcategory":"Laundry & Dry Cleaning",
            "type":"Services"
        }
    ],
    "sg:phone":"+1 704 529 0288",
    "sg:postcode":"28209",
    "sg:province":"NC",
    "sg:tags":[
        "costume",
        "costumes-renting"
    ],
    "wof:name":"Morris Costumes Halloween Express",
    "wof:placetype":"venue"
},
  "geometry": {"coordinates":[-80.848218,35.170735],"type":"Point"}
}