{
  "type": "Feature",
  "properties": {
    "iso:country":"US",
    "sg:address":"1144 E Stage Coach Trl",
    "sg:city":"Lawndale",
    "sg:classifiers":[
        {
            "category":"Restaurant",
            "type":"Food & Drink"
        }
    ],
    "sg:phone":"+1 704 538 5921",
    "sg:postcode":"28090",
    "sg:province":"NC",
    "wof:name":"Lil Yummys",
    "wof:placetype":"venue"
},
  "geometry": {"coordinates":[-81.477436,35.42796],"type":"Point"}
}