{
  "type": "Feature",
  "properties": {
    "addr:full":"280 Shipman Rd Havelock NC 28532",
    "addr:housenumber":"280",
    "addr:postcode":"28532",
    "addr:street":"Shipman Rd",
    "iso:country":"US",
    "sg:address":"280 Shipman Rd",
    "sg:city":"Havelock",
    "sg:classifiers":[
        {
            "category":"Freight",
            "type":"Transportation"
        }
    ],
    "sg:phone":"+1 252 447 6900",
    "sg:postcode":"28532",
    "sg:province":"NC",
    "sg:tags":[
        "commercial",
        "storage"
    ],
    "wof:name":"American Self Storage",
    "wof:placetype":"venue"
},
  "geometry": {"coordinates":[-76.89002600000001,34.881834],"type":"Point"}
}