{
  "type": "Feature",
  "properties": {
    "addr:full":"108 S Market St Madison NC 27025",
    "addr:housenumber":"108",
    "addr:postcode":"27025",
    "addr:street":"S Market St",
    "iso:country":"US",
    "sg:address":"108 S Market St",
    "sg:city":"Madison",
    "sg:classifiers":[
        {
            "category":"Real Estate",
            "subcategory":"Real Estate Agent",
            "type":"Services"
        }
    ],
    "sg:phone":"+1 336 427 6622",
    "sg:postcode":"27025",
    "sg:province":"NC",
    "wof:name":"L Don Warren & Assoc Realtors",
    "wof:placetype":"venue"
},
  "geometry": {"coordinates":[-79.959701,36.387438],"type":"Point"}
}