{
  "type": "Feature",
  "properties": {
    "iso:country":"US",
    "sg:address":"940 Joe Weaver Rd",
    "sg:city":"Lansing",
    "sg:classifiers":[
        {
            "category":"Wholesale",
            "subcategory":"Farm Supplies",
            "type":"Manufacturing & Wholesale Goods"
        }
    ],
    "sg:phone":"+1 336 384 2769",
    "sg:postcode":"28643",
    "sg:province":"NC",
    "sg:tags":[
        "livestock"
    ],
    "wof:name":"Joe Weaver Farm",
    "wof:placetype":"venue"
},
  "geometry": {"coordinates":[-81.52691299999999,36.574835],"type":"Point"}
}