{
  "type": "Feature",
  "properties": {
    "iso:country":"US",
    "sg:address":"4800 Grove Barton Rd",
    "sg:city":"Raleigh",
    "sg:classifiers":[
        {
            "category":"Personal",
            "subcategory":"Beauty Salon",
            "type":"Services"
        }
    ],
    "sg:phone":"+1   ",
    "sg:postcode":"27613",
    "sg:province":"NC",
    "sg:tags":[
        "shop"
    ],
    "wof:name":"Hair Champs",
    "wof:placetype":"venue"
},
  "geometry": {"coordinates":[-78.718565,35.872237],"type":"Point"}
}