{
  "type": "Feature",
  "properties": {
    "addr:full":"2 Highcross Ct Raleigh NC 27613",
    "addr:housenumber":"2",
    "addr:postcode":"27613",
    "addr:street":"Highcross Ct",
    "iso:country":"US",
    "sg:address":"2 Highcross Ct",
    "sg:city":"Raleigh",
    "sg:classifiers":[
        {
            "category":"Building & Trades",
            "subcategory":"Electrical",
            "type":"Services"
        }
    ],
    "sg:phone":"+1 919 992 7570",
    "sg:postcode":"27613",
    "sg:province":"NC",
    "sg:tags":[
        "electric",
        "contractor"
    ],
    "wof:name":"Bobby Wilson Electric Co",
    "wof:placetype":"venue"
},
  "geometry": {"coordinates":[-78.71949499999999,35.964538],"type":"Point"}
}