{
  "type": "Feature",
  "properties": {
    "iso:country":"US",
    "sg:address":"114 E Main St",
    "sg:city":"Whiteville",
    "sg:classifiers":[
        {
            "category":"Education",
            "subcategory":"Dance Studio",
            "type":"Public Place"
        }
    ],
    "sg:phone":"+1   ",
    "sg:postcode":"28472",
    "sg:province":"NC",
    "wof:name":"Wandas Schl Dance & Gymnastics",
    "wof:placetype":"venue"
},
  "geometry": {"coordinates":[-78.70100499999999,34.322175],"type":"Point"}
}