{
  "type": "Feature",
  "properties": {
    "iso:country":"US",
    "sg:address":"5101 Carolwood Ln",
    "sg:city":"Durham",
    "sg:classifiers":[
        {
            "category":"Professional",
            "subcategory":"Business Services",
            "type":"Services"
        }
    ],
    "sg:phone":"+1   ",
    "sg:postcode":"27713",
    "sg:province":"NC",
    "wof:name":"Jkm Business Services LLC",
    "wof:placetype":"venue"
},
  "geometry": {"coordinates":[-78.93946,35.932587],"type":"Point"}
}