{
  "type": "Feature",
  "properties": {
    "iso:country":"US",
    "sg:address":"719 W Rowan St",
    "sg:city":"Fayetteville",
    "sg:classifiers":[
        {
            "category":"Banks & Credit Unions",
            "subcategory":"Investment Brokerage",
            "type":"Services"
        }
    ],
    "sg:phone":"+1 910 223 9134",
    "sg:postcode":"28301",
    "sg:province":"NC",
    "sg:tags":[
        "advisory",
        "financial"
    ],
    "wof:name":"Omni Financial",
    "wof:placetype":"venue"
},
  "geometry": {"coordinates":[-78.890705,35.060774],"type":"Point"}
}