{
  "type": "Feature",
  "properties": {
    "iso:country":"US",
    "sg:address":"45 Maverick Ranch Rd",
    "sg:city":"Pittsboro",
    "sg:classifiers":[
        {
            "category":"Mining & Drilling",
            "type":"Manufacturing & Wholesale Goods"
        }
    ],
    "sg:phone":"+1 919 542 3704",
    "sg:postcode":"27312",
    "sg:province":"NC",
    "sg:tags":[
        "construction"
    ],
    "wof:name":"Maverick Ranch",
    "wof:placetype":"venue"
},
  "geometry": {"coordinates":[-79.10405900000001,35.692865],"type":"Point"}
}