{
  "type": "Feature",
  "properties": {
    "addr:full":"523 Melton Branch Rd Bakersville NC 28705",
    "addr:housenumber":"523",
    "addr:postcode":"28705",
    "addr:street":"Melton Branch Rd",
    "iso:country":"US",
    "sg:address":"523 Melton Branch Rd",
    "sg:city":"Bakersville",
    "sg:classifiers":[
        {
            "category":"Retail",
            "subcategory":"Auto Repair",
            "type":"Services"
        }
    ],
    "sg:phone":"+1   ",
    "sg:postcode":"28705",
    "sg:province":"NC",
    "sg:tags":[
        "general"
    ],
    "wof:name":"Martin Repair Service",
    "wof:placetype":"venue"
},
  "geometry": {"coordinates":[-82.233434,36.091765],"type":"Point"}
}