{
  "type": "Feature",
  "properties": {
    "iso:country":"US",
    "sg:address":"8636 Plantation Landing Dr",
    "sg:city":"Wilmington",
    "sg:classifiers":[
        {
            "category":"Wholesale",
            "subcategory":"Construction Materials",
            "type":"Manufacturing & Wholesale Goods"
        },
        {
            "category":"Building & Trades",
            "subcategory":"Construction",
            "type":"Services"
        }
    ],
    "sg:phone":"+1 910 279 3288",
    "sg:postcode":"28411",
    "sg:province":"NC",
    "sg:tags":[
        "fence",
        "contractor"
    ],
    "wof:name":"Bullard Fence & Deck",
    "wof:placetype":"venue"
},
  "geometry": {"coordinates":[-77.775825,34.300706],"type":"Point"}
}