{
  "type": "Feature",
  "properties": {
    "addr:full":"891 Broadway St Asheville NC 28801",
    "addr:housenumber":"891",
    "addr:postcode":"28801",
    "addr:street":"Broadway St",
    "iso:country":"US",
    "sg:address":"891 Broadway St",
    "sg:city":"Asheville",
    "sg:classifiers":[
        {
            "category":"Wholesale",
            "subcategory":"Medical Equipment & Supplies",
            "type":"Manufacturing & Wholesale Goods"
        }
    ],
    "sg:phone":"+1 828 277 1188",
    "sg:postcode":"28801",
    "sg:province":"NC",
    "sg:tags":[
        "product",
        "therapy"
    ],
    "sg:website":"www.bannertherapy.com",
    "wof:name":"Banner Therapy Products",
    "wof:placetype":"venue"
},
  "geometry": {"coordinates":[-82.57105199999999,35.613601],"type":"Point"}
}