{
  "type": "Feature",
  "properties": {
    "iso:country":"US",
    "sg:address":"1749 Gilead Shores Rd",
    "sg:city":"Blounts Creek",
    "sg:classifiers":[
        {
            "category":"Building & Trades",
            "subcategory":"Plumbing",
            "type":"Services"
        }
    ],
    "sg:phone":"+1 252 975 6559",
    "sg:postcode":"27814",
    "sg:province":"NC",
    "sg:tags":[
        "plumbing",
        "contractor"
    ],
    "wof:name":"Colonial Plumbing Svc",
    "wof:placetype":"venue"
},
  "geometry": {"coordinates":[-76.995757,35.464506],"type":"Point"}
}