{
  "type": "Feature",
  "properties": {
    "iso:country":"US",
    "sg:address":"3909 Sweeten Creek Rd",
    "sg:city":"Arden",
    "sg:classifiers":[
        {
            "category":"Freight",
            "type":"Transportation"
        }
    ],
    "sg:phone":"+1 828 684 6141",
    "sg:postcode":"28704",
    "sg:province":"NC",
    "sg:tags":[
        "commercial",
        "storage"
    ],
    "wof:name":"Storage Center",
    "wof:placetype":"venue"
},
  "geometry": {"coordinates":[-82.512351,35.463627],"type":"Point"}
}