{
  "type": "Feature",
  "properties": {
    "iso:country":"US",
    "sg:address":"555 Lucy Garrett Rd",
    "sg:city":"Roxboro",
    "sg:classifiers":[
        {
            "category":"Freight",
            "type":"Transportation"
        }
    ],
    "sg:phone":"+1 336 598 5016",
    "sg:postcode":"27574",
    "sg:province":"NC",
    "sg:tags":[
        "broker",
        "agent"
    ],
    "sg:website":"www.gkndriveline.com",
    "wof:name":"GKN Freight Svc Inc",
    "wof:placetype":"venue"
},
  "geometry": {"coordinates":[-78.97148199999999,36.342154],"type":"Point"}
}