{
  "type": "Feature",
  "properties": {
    "addr:full":"107 Parkwood Dr Snow Hill NC 28546",
    "addr:housenumber":"107",
    "addr:postcode":"28546",
    "addr:street":"Parkwood Dr",
    "iso:country":"US",
    "sg:address":"107 Parkwood Dr",
    "sg:city":"Snow Hill",
    "sg:classifiers":[
        {
            "category":"Health Services",
            "subcategory":"Optometrist",
            "type":"Services"
        }
    ],
    "sg:phone":"+1 252 747 8149",
    "sg:postcode":"28546",
    "sg:province":"NC",
    "wof:name":"Doctors Vision Center",
    "wof:placetype":"venue"
},
  "geometry": {"coordinates":[-77.38850100000001,34.778166],"type":"Point"}
}