{
  "type": "Feature",
  "properties": {
    "iso:country":"US",
    "sg:address":"1548 Old Hollow Rd",
    "sg:city":"Winston Salem",
    "sg:classifiers":[
        {
            "category":"Organizations",
            "subcategory":"Religious Organization",
            "type":"Services"
        }
    ],
    "sg:phone":"+1 336 744 7050",
    "sg:postcode":"27105",
    "sg:province":"NC",
    "sg:tags":[
        "church"
    ],
    "wof:name":"Liberty Baptist Church Inc",
    "wof:placetype":"venue"
},
  "geometry": {"coordinates":[-80.21044999999999,36.187884],"type":"Point"}
}