{
  "type": "Feature",
  "properties": {
    "iso:country":"US",
    "sg:address":"106 E Raleigh St",
    "sg:city":"Siler City",
    "sg:classifiers":[
        {
            "category":"Personal",
            "subcategory":"Beauty Salon",
            "type":"Services"
        }
    ],
    "sg:phone":"+1   ",
    "sg:postcode":"27344",
    "sg:province":"NC",
    "sg:tags":[
        "shop"
    ],
    "wof:name":"Hair World",
    "wof:placetype":"venue"
},
  "geometry": {"coordinates":[-79.462777,35.723066],"type":"Point"}
}