{
  "type": "Feature",
  "properties": {
    "addr:full":"927 E 9th Ave Gastonia NC 28054",
    "addr:housenumber":"927",
    "addr:postcode":"28054",
    "addr:street":"E 9Th Ave",
    "iso:country":"US",
    "sg:address":"927 E 9th Ave",
    "sg:city":"Gastonia",
    "sg:classifiers":[
        {
            "category":"Professional",
            "subcategory":"Management & Consulting",
            "type":"Services"
        }
    ],
    "sg:phone":"+1 704 867 1221",
    "sg:postcode":"28054",
    "sg:province":"NC",
    "sg:tags":[
        "consultant"
    ],
    "wof:name":"DBH Consulting",
    "wof:placetype":"venue"
},
  "geometry": {"coordinates":[-81.16691899999999,35.25103],"type":"Point"}
}