{
  "type": "Feature",
  "properties": {
    "iso:country":"US",
    "sg:address":"1600 Glenwood Ave",
    "sg:city":"Raleigh",
    "sg:classifiers":[
        {
            "category":"Building & Trades",
            "subcategory":"Pest Control",
            "type":"Services"
        }
    ],
    "sg:phone":"+1 919 834 2255",
    "sg:postcode":"27608",
    "sg:province":"NC",
    "wof:name":"Jtw Exterminating",
    "wof:placetype":"venue"
},
  "geometry": {"coordinates":[-78.645843,35.804023],"type":"Point"}
}