{
  "type": "Feature",
  "properties": {
    "addr:full":"204 Richlands Loop Rd Richlands NC 28574",
    "addr:housenumber":"204",
    "addr:postcode":"28574",
    "addr:street":"Richlands Loop Rd",
    "iso:country":"US",
    "sg:address":"204 Richlands Loop Rd",
    "sg:city":"Richlands",
    "sg:classifiers":[
        {
            "category":"Building & Trades",
            "subcategory":"Construction",
            "type":"Services"
        }
    ],
    "sg:phone":"+1 910 324 4256",
    "sg:postcode":"28574",
    "sg:province":"NC",
    "sg:tags":[
        "general",
        "contractor"
    ],
    "wof:name":"New Beginnings",
    "wof:placetype":"venue"
},
  "geometry": {"coordinates":[-77.55593399999999,34.913189],"type":"Point"}
}