{
  "type": "Feature",
  "properties": {
    "addr:full":"900 Hawkins Ave Sanford NC 27330",
    "addr:housenumber":"900",
    "addr:postcode":"27330",
    "addr:street":"Hawkins Ave",
    "iso:country":"US",
    "sg:address":"900 Hawkins Ave",
    "sg:city":"Sanford",
    "sg:classifiers":[
        {
            "category":"Professional",
            "subcategory":"Business Services",
            "type":"Services"
        }
    ],
    "sg:phone":"+1 919 775 7710",
    "sg:postcode":"27330",
    "sg:province":"NC",
    "sg:tags":[
        "embroidery"
    ],
    "wof:name":"Main St Monograms",
    "wof:placetype":"venue"
},
  "geometry": {"coordinates":[-79.180178,35.493618],"type":"Point"}
}