{
  "type": "Feature",
  "properties": {
    "addr:full":"3605 Glenwood Ave Raleigh NC 27612",
    "addr:housenumber":"3605",
    "addr:postcode":"27612",
    "addr:street":"Glenwood Ave",
    "iso:country":"US",
    "sg:address":"3605 Glenwood Ave",
    "sg:city":"Raleigh",
    "sg:classifiers":[
        {
            "category":"Banks & Credit Unions",
            "subcategory":"Investment Brokerage",
            "type":"Services"
        }
    ],
    "sg:phone":"+1 919 645 5900",
    "sg:postcode":"27612",
    "sg:province":"NC",
    "sg:tags":[
        "advisory",
        "financial"
    ],
    "wof:name":"Powell Johnson",
    "wof:placetype":"venue"
},
  "geometry": {"coordinates":[-78.666511,35.827831],"type":"Point"}
}