{
  "type": "Feature",
  "properties": {
    "iso:country":"US",
    "sg:address":"3791 NW Cary Pkwy",
    "sg:city":"Cary",
    "sg:classifiers":[
        {
            "category":"Shopping",
            "subcategory":"Clothing, Apparel, & Fashions",
            "type":"Retail Goods"
        }
    ],
    "sg:phone":"+1 919 467 4050",
    "sg:postcode":"27513",
    "sg:province":"NC",
    "wof:name":"Everything Dance",
    "wof:placetype":"venue"
},
  "geometry": {"coordinates":[-78.820232,35.792483],"type":"Point"}
}