{
  "type": "Feature",
  "properties": {
    "addr:full":"970 Valley River Ave Murphy NC 28906",
    "addr:housenumber":"970",
    "addr:postcode":"28906",
    "addr:street":"Valley River Ave",
    "iso:country":"US",
    "sg:address":"970 Valley River Ave",
    "sg:city":"Murphy",
    "sg:classifiers":[
        {
            "category":"Personal",
            "subcategory":"Beauty Salon",
            "type":"Services"
        }
    ],
    "sg:phone":"+1 828 837 7568",
    "sg:postcode":"28906",
    "sg:province":"NC",
    "wof:name":"Creative Designs",
    "wof:placetype":"venue"
},
  "geometry": {"coordinates":[-84.026642,35.095829],"type":"Point"}
}