{
  "type": "Feature",
  "properties": {
    "addr:full":"104 Bill Scott Trl Siloam NC 27047",
    "addr:housenumber":"104",
    "addr:postcode":"27047",
    "addr:street":"Bill Scott Trl",
    "iso:country":"US",
    "sg:address":"104 Bill Scott Trl",
    "sg:city":"Siloam",
    "sg:classifiers":[
        {
            "category":"Farming",
            "subcategory":"Farm",
            "type":"Manufacturing & Wholesale Goods"
        }
    ],
    "sg:phone":"+1 336 374 5767",
    "sg:postcode":"27047",
    "sg:province":"NC",
    "sg:tags":[
        "crop",
        "general"
    ],
    "wof:name":"Billy Scott",
    "wof:placetype":"venue"
},
  "geometry": {"coordinates":[-80.624368,36.304402],"type":"Point"}
}