{
  "type": "Feature",
  "properties": {
    "addr:full":"630 Jake Alexander Blvd W Salisbury NC 28147",
    "addr:housenumber":"630",
    "addr:postcode":"28147",
    "addr:street":"Jake Alexander Blvd W",
    "iso:country":"US",
    "sg:address":"630 Jake Alexander Blvd W",
    "sg:city":"Salisbury",
    "sg:classifiers":[
        {
            "category":"Banks & Credit Unions",
            "subcategory":"Bank",
            "type":"Services"
        }
    ],
    "sg:phone":"+1 704 633 7952",
    "sg:postcode":"28147",
    "sg:province":"NC",
    "sg:website":"www.fmbnc.com",
    "wof:name":"Farmers & Merchants Bank",
    "wof:placetype":"venue"
},
  "geometry": {"coordinates":[-80.50011600000001,35.655284],"type":"Point"}
}