{
  "type": "Feature",
  "properties": {
    "iso:country":"US",
    "sg:address":"112 E Main St",
    "sg:city":"Washington",
    "sg:classifiers":[
        {
            "category":"Wholesale",
            "subcategory":"Office Equipment",
            "type":"Manufacturing & Wholesale Goods"
        }
    ],
    "sg:phone":"+1 252 946 2197",
    "sg:postcode":"27889",
    "sg:province":"NC",
    "sg:tags":[
        "machine",
        "duplicating",
        "copying"
    ],
    "wof:name":"Renn-Taff Office Supplies Inc",
    "wof:placetype":"venue"
},
  "geometry": {"coordinates":[-77.054925,35.542059],"type":"Point"}
}