{
  "type": "Feature",
  "properties": {
    "iso:country":"US",
    "sg:address":"5760 Hester Store Rd",
    "sg:city":"Hurdle Mills",
    "sg:classifiers":[
        {
            "category":"Retail",
            "subcategory":"Animal Services",
            "type":"Services"
        }
    ],
    "sg:phone":"+1 336 597 5743",
    "sg:postcode":"27541",
    "sg:province":"NC",
    "wof:name":"Twin Oaks Farm LLC",
    "wof:placetype":"venue"
},
  "geometry": {"coordinates":[-79.12618999999999,36.331336],"type":"Point"}
}