{
  "type": "Feature",
  "properties": {
    "iso:country":"US",
    "sg:address":"145 Wall St",
    "sg:city":"Waynesville",
    "sg:classifiers":[
        {
            "category":"Shopping",
            "subcategory":"Gifts & Souvenirs",
            "type":"Retail Goods"
        }
    ],
    "sg:phone":"+1 828 452 3151",
    "sg:postcode":"28786",
    "sg:province":"NC",
    "sg:tags":[
        "shop"
    ],
    "wof:name":"Off The Wall",
    "wof:placetype":"venue"
},
  "geometry": {"coordinates":[-82.987239,35.490306],"type":"Point"}
}