{
  "type": "Feature",
  "properties": {
    "addr:full":"7301 Tall Tree Ln Charlotte NC 28214",
    "addr:housenumber":"7301",
    "addr:postcode":"28214",
    "addr:street":"Tall Tree Ln",
    "iso:country":"US",
    "sg:address":"7301 Tall Tree Ln",
    "sg:city":"Charlotte",
    "sg:classifiers":[
        {
            "category":"Building & Trades",
            "subcategory":"Cleaning & Sanitation",
            "type":"Services"
        }
    ],
    "sg:phone":"+1 704 910 0723",
    "sg:postcode":"28214",
    "sg:province":"NC",
    "sg:tags":[
        "fire",
        "water",
        "restoration",
        "damage"
    ],
    "wof:name":"Rk Restoration",
    "wof:placetype":"venue"
},
  "geometry": {"coordinates":[-80.95133199999999,35.259769],"type":"Point"}
}