{
  "type": "Feature",
  "properties": {
    "iso:country":"US",
    "sg:address":"823 Hebron Rd",
    "sg:city":"Durham",
    "sg:classifiers":[
        {
            "category":"Bus Charters",
            "type":"Transportation"
        }
    ],
    "sg:phone":"+1 919 477 2782",
    "sg:postcode":"27704",
    "sg:province":"NC",
    "sg:tags":[
        "operator",
        "tour",
        "rental"
    ],
    "wof:name":"J & R Charter Service Inc",
    "wof:placetype":"venue"
},
  "geometry": {"coordinates":[-78.87955599999999,36.059093],"type":"Point"}
}