{
  "type": "Feature",
  "properties": {
    "addr:full":"20819 N Main St Cornelius NC 28031",
    "addr:housenumber":"20819",
    "addr:postcode":"28031",
    "addr:street":"N Main St",
    "iso:country":"US",
    "sg:address":"20819 N Main St",
    "sg:city":"Cornelius",
    "sg:classifiers":[
        {
            "category":"Autos & Motor Vehicles",
            "subcategory":"Auto Supplies",
            "type":"Retail Goods"
        }
    ],
    "sg:phone":"+1 704 892 7755",
    "sg:postcode":"28031",
    "sg:province":"NC",
    "sg:tags":[
        "automobile",
        "parts"
    ],
    "wof:name":"Genuine Parts Co",
    "wof:placetype":"venue"
},
  "geometry": {"coordinates":[-80.857592,35.491665],"type":"Point"}
}