{
  "type": "Feature",
  "properties": {
    "addr:full":"1065 Heath Acres Dr Walnut Cove NC 27052",
    "addr:housenumber":"1065",
    "addr:postcode":"27052",
    "addr:street":"Heath Acres Dr Walnut Cove",
    "iso:country":"US",
    "sg:address":"1065 Heath Acres Dr",
    "sg:city":"Walnut Cove",
    "sg:classifiers":[
        {
            "category":"Building & Trades",
            "subcategory":"Construction",
            "type":"Services"
        }
    ],
    "sg:phone":"+1 336 994 9236",
    "sg:postcode":"27052",
    "sg:province":"NC",
    "sg:tags":[
        "house"
    ],
    "wof:name":"Heath Home Improvements",
    "wof:placetype":"venue"
},
  "geometry": {"coordinates":[-80.221332,36.347855],"type":"Point"}
}