{
  "type": "Feature",
  "properties": {
    "iso:country":"US",
    "sg:address":"3020 N Main St",
    "sg:city":"Hope Mills",
    "sg:classifiers":[
        {
            "category":"Banks & Credit Unions",
            "subcategory":"Bank",
            "type":"Services"
        }
    ],
    "sg:phone":"+1 910 424 3033",
    "sg:postcode":"28348",
    "sg:province":"NC",
    "sg:tags":[
        "financing"
    ],
    "wof:name":"Citi Financial",
    "wof:placetype":"venue"
},
  "geometry": {"coordinates":[-78.964491,34.983914],"type":"Point"}
}