{
  "type": "Feature",
  "properties": {
    "iso:country":"US",
    "sg:address":"1901 N Main St",
    "sg:city":"Kannapolis",
    "sg:classifiers":[
        {
            "category":"Home & Garden",
            "subcategory":"Furniture",
            "type":"Retail Goods"
        }
    ],
    "sg:phone":"+1 704 932 8371",
    "sg:postcode":"28081",
    "sg:province":"NC",
    "wof:name":"B & B Furniture & Mat Outl",
    "wof:placetype":"venue"
},
  "geometry": {"coordinates":[-80.614367,35.521373],"type":"Point"}
}