{
  "type": "Feature",
  "properties": {
    "iso:country":"US",
    "sg:address":"826 Purser Dr",
    "sg:city":"Raleigh",
    "sg:classifiers":[
        {
            "category":"Autos & Motor Vehicles",
            "subcategory":"Auto Supplies",
            "type":"Retail Goods"
        },
        {
            "category":"Retail",
            "subcategory":"Auto Repair",
            "type":"Services"
        }
    ],
    "sg:phone":"+1 919 772 7330",
    "sg:postcode":"27603",
    "sg:province":"NC",
    "sg:tags":[
        "body",
        "repairing",
        "part",
        "painting",
        "automobile"
    ],
    "wof:name":"Capital Bumper Company Inc",
    "wof:placetype":"venue"
},
  "geometry": {"coordinates":[-78.65774500000001,35.717559],"type":"Point"}
}