{
  "type": "Feature",
  "properties": {
    "iso:country":"US",
    "sg:address":"300 Violet Rd",
    "sg:city":"Lexington",
    "sg:classifiers":[
        {
            "category":"Building & Trades",
            "subcategory":"Cleaning & Sanitation",
            "type":"Services"
        }
    ],
    "sg:phone":"+1 336 249 9828",
    "sg:postcode":"27295",
    "sg:province":"NC",
    "sg:tags":[
        "maintenance"
    ],
    "wof:name":"Howards Floors",
    "wof:placetype":"venue"
},
  "geometry": {"coordinates":[-80.23742300000001,35.840818],"type":"Point"}
}