{
  "type": "Feature",
  "properties": {
    "addr:full":"337 Buncombe St Raleigh NC 27609",
    "addr:housenumber":"337",
    "addr:postcode":"27609",
    "addr:street":"Buncombe St",
    "iso:country":"US",
    "sg:address":"337 Buncombe St",
    "sg:city":"Raleigh",
    "sg:classifiers":[
        {
            "category":"Professional",
            "type":"Services"
        }
    ],
    "sg:phone":"+1 919 782 8142",
    "sg:postcode":"27609",
    "sg:province":"NC",
    "wof:name":"Equityresearchcom Inc",
    "wof:placetype":"venue"
},
  "geometry": {"coordinates":[-78.660611,35.832098],"type":"Point"}
}