{
  "type": "Feature",
  "properties": {
    "addr:full":"421 Fairfield Ln Blowing Rock NC 28605",
    "addr:housenumber":"421",
    "addr:postcode":"28605",
    "addr:street":"Fairfield Ln",
    "iso:country":"US",
    "sg:address":"421 Fairfield Ln",
    "sg:city":"Blowing Rock",
    "sg:classifiers":[
        {
            "category":"Manufacturing",
            "subcategory":"Printing",
            "type":"Manufacturing & Wholesale Goods"
        }
    ],
    "sg:phone":"+1 828 295 9829",
    "sg:postcode":"28605",
    "sg:province":"NC",
    "sg:tags":[
        "publisher"
    ],
    "wof:name":"Parkway Publishers",
    "wof:placetype":"venue"
},
  "geometry": {"coordinates":[-81.640103,36.153474],"type":"Point"}
}