{
  "type": "Feature",
  "properties": {
    "addr:full":"3000 Lemon Springs Rd Sanford NC 27332",
    "addr:housenumber":"3000",
    "addr:postcode":"27332",
    "addr:street":"Lemon Springs Rd",
    "iso:country":"US",
    "sg:address":"3000 Lemon Springs Rd",
    "sg:city":"Sanford",
    "sg:classifiers":[
        {
            "category":"Organizations",
            "subcategory":"Religious Organization",
            "type":"Services"
        }
    ],
    "sg:phone":"+1 919 774 8112",
    "sg:postcode":"27332",
    "sg:province":"NC",
    "sg:tags":[
        "church"
    ],
    "wof:name":"Sanford Free Will Holiness Chr",
    "wof:placetype":"venue"
},
  "geometry": {"coordinates":[-79.163736,35.445268],"type":"Point"}
}