{
  "type": "Feature",
  "properties": {
    "addr:full":"331 S Lafayette St Shelby NC 28150",
    "addr:housenumber":"331",
    "addr:postcode":"28150",
    "addr:street":"S Lafayette St",
    "iso:country":"US",
    "sg:address":"331 S Lafayette St",
    "sg:city":"Shelby",
    "sg:classifiers":[
        {
            "category":"Banks & Credit Unions",
            "subcategory":"Bank",
            "type":"Services"
        }
    ],
    "sg:phone":"+1 704 482 4580",
    "sg:postcode":"28150",
    "sg:province":"NC",
    "sg:tags":[
        "commercial"
    ],
    "wof:name":"Fidelity Bank",
    "wof:placetype":"venue"
},
  "geometry": {"coordinates":[-81.540346,35.288521],"type":"Point"}
}