{
  "type": "Feature",
  "properties": {
    "iso:country":"US",
    "sg:address":"3312 Forest Pine Dr",
    "sg:city":"East Bend",
    "sg:classifiers":[
        {
            "category":"Building & Trades",
            "subcategory":"Electrical",
            "type":"Services"
        }
    ],
    "sg:phone":"+1 336 699 4275",
    "sg:postcode":"27018",
    "sg:province":"NC",
    "sg:tags":[
        "electrical",
        "contractor"
    ],
    "wof:name":"Buck Run Electric",
    "wof:placetype":"venue"
},
  "geometry": {"coordinates":[-80.550603,36.222178],"type":"Point"}
}