{
  "type": "Feature",
  "properties": {
    "iso:country":"US",
    "sg:address":"1 Swallows Ridge Ct",
    "sg:city":"Durham",
    "sg:classifiers":[
        {
            "category":"Health Services",
            "subcategory":"Doctor",
            "type":"Services"
        }
    ],
    "sg:phone":"+1   ",
    "sg:postcode":"27713",
    "sg:province":"NC",
    "sg:tags":[
        "physician"
    ],
    "wof:name":"Dana Marzilli",
    "wof:placetype":"venue"
},
  "geometry": {"coordinates":[-78.92668999999999,35.933783],"type":"Point"}
}