{
  "type": "Feature",
  "properties": {
    "iso:country":"US",
    "sg:address":"10101 Goodview Ct",
    "sg:city":"Raleigh",
    "sg:classifiers":[
        {
            "category":"Professional",
            "type":"Services"
        }
    ],
    "sg:phone":"+1 919 866 1781",
    "sg:postcode":"27613",
    "sg:province":"NC",
    "sg:tags":[
        "establishment"
    ],
    "wof:name":"Arfocus",
    "wof:placetype":"venue"
},
  "geometry": {"coordinates":[-78.692111,35.912847],"type":"Point"}
}