{
  "type": "Feature",
  "properties": {
    "iso:country":"US",
    "sg:address":"412 N 12th St",
    "sg:city":"Bessemer City",
    "sg:classifiers":[
        {
            "category":"Retail",
            "subcategory":"Repair Shop",
            "type":"Services"
        }
    ],
    "sg:phone":"+1 704 629 3395",
    "sg:postcode":"28016",
    "sg:province":"NC",
    "sg:tags":[
        "lock",
        "locksmith"
    ],
    "wof:name":"Guardian Locksmith",
    "wof:placetype":"venue"
},
  "geometry": {"coordinates":[-81.282735,35.288669],"type":"Point"}
}