{
  "type": "Feature",
  "properties": {
    "iso:country":"US",
    "sg:address":"3489 US Hwy 17",
    "sg:city":"Chocowinity",
    "sg:classifiers":[
        {
            "category":"Retail",
            "subcategory":"Auto Repair",
            "type":"Services"
        }
    ],
    "sg:phone":"+1 252 946 3671",
    "sg:postcode":"27817",
    "sg:province":"NC",
    "sg:tags":[
        "repairing",
        "automobile"
    ],
    "wof:name":"Choco Service Ctr",
    "wof:placetype":"venue"
},
  "geometry": {"coordinates":[-77.09961800000001,35.513283],"type":"Point"}
}