{
  "type": "Feature",
  "properties": {
    "addr:full":"8067 US Hwy 17 Washington NC 27889",
    "addr:housenumber":"8067",
    "addr:postcode":"27889",
    "addr:street":"Us Hwy 17",
    "iso:country":"US",
    "sg:address":"8067 US Hwy 17",
    "sg:city":"Washington",
    "sg:classifiers":[
        {
            "category":"Organizations",
            "subcategory":"Religious Organization",
            "type":"Services"
        }
    ],
    "sg:phone":"+1 252 946 1274",
    "sg:postcode":"27889",
    "sg:province":"NC",
    "sg:tags":[
        "church"
    ],
    "wof:name":"Last Days Tabernacle Temple",
    "wof:placetype":"venue"
},
  "geometry": {"coordinates":[-77.079567,35.677973],"type":"Point"}
}