{
  "type": "Feature",
  "properties": {
    "iso:country":"US",
    "sg:address":"124 N McDowell St",
    "sg:city":"Charlotte",
    "sg:classifiers":[
        {
            "category":"Insurance",
            "subcategory":"Insurance Agent",
            "type":"Services"
        }
    ],
    "sg:phone":"+1 704 369 0200",
    "sg:postcode":"28204",
    "sg:province":"NC",
    "wof:name":"Empowered Benefits",
    "wof:placetype":"venue"
},
  "geometry": {"coordinates":[-80.834135,35.220896],"type":"Point"}
}