{
  "type": "Feature",
  "properties": {
    "iso:country":"US",
    "sg:address":"108 E Academy St",
    "sg:city":"Fuquay Varina",
    "sg:classifiers":[
        {
            "category":"Autos & Motor Vehicles",
            "subcategory":"Auto Supplies",
            "type":"Retail Goods"
        }
    ],
    "sg:phone":"+1 919 552 9090",
    "sg:postcode":"27591",
    "sg:province":"NC",
    "sg:tags":[
        "repair",
        "tire"
    ],
    "wof:name":"Goodyear Tire and Auto Ctr",
    "wof:placetype":"venue"
},
  "geometry": {"coordinates":[-78.36829,35.785751],"type":"Point"}
}