{
  "type": "Feature",
  "properties": {
    "iso:country":"US",
    "sg:address":"4118 Triangle Dr",
    "sg:city":"Charlotte",
    "sg:classifiers":[
        {
            "category":"Building & Trades",
            "subcategory":"Construction",
            "type":"Services"
        }
    ],
    "sg:phone":"+1 704 607 2218",
    "sg:postcode":"28208",
    "sg:province":"NC",
    "sg:tags":[
        "general",
        "contractor"
    ],
    "wof:name":"Moretti Construction Inc",
    "wof:placetype":"venue"
},
  "geometry": {"coordinates":[-80.894443,35.247183],"type":"Point"}
}