{
  "type": "Feature",
  "properties": {
    "iso:country":"US",
    "sg:address":"329 Bentpine Dr.",
    "sg:city":"Raleigh",
    "sg:classifiers":[
        {
            "category":"Professional",
            "subcategory":"Computer Services",
            "type":"Services"
        }
    ],
    "sg:phone":"+1 888 520 3621",
    "sg:postcode":"27603",
    "sg:province":"NC",
    "sg:tags":[
        "seo",
        "sem",
        "internet-video"
    ],
    "sg:website":"http://www.hiploose.com",
    "wof:name":"Hiploose Global Solutions",
    "wof:placetype":"venue"
},
  "geometry": {"coordinates":[-78.648231,35.715207],"type":"Point"}
}