{
  "type": "Feature",
  "properties": {
    "addr:full":"1476 Old Moore Rd Selma NC 27576",
    "addr:housenumber":"1476",
    "addr:postcode":"27576",
    "addr:street":"Old Moore Rd",
    "iso:country":"US",
    "sg:address":"1476 Old Moore Rd",
    "sg:city":"Selma",
    "sg:classifiers":[
        {
            "category":"Professional",
            "type":"Services"
        }
    ],
    "sg:phone":"+1 919 965 4014",
    "sg:postcode":"27576",
    "sg:province":"NC",
    "wof:name":"Johnnie M Dale Jr",
    "wof:placetype":"venue"
},
  "geometry": {"coordinates":[-78.26141200000001,35.618708],"type":"Point"}
}