{
  "type": "Feature",
  "properties": {
    "addr:full":"14125 US Hwy 601 Midland NC 28107",
    "addr:housenumber":"14125",
    "addr:postcode":"28107",
    "addr:street":"Us Hwy 601",
    "iso:country":"US",
    "sg:address":"14125 US Hwy 601",
    "sg:city":"Midland",
    "sg:classifiers":[
        {
            "category":"Food & Beverages",
            "subcategory":"Fruits & Vegetables",
            "type":"Retail Goods"
        },
        {
            "category":"Wholesale",
            "subcategory":"Fruits & Vegetables",
            "type":"Manufacturing & Wholesale Goods"
        }
    ],
    "sg:phone":"+1 704 888 9988",
    "sg:postcode":"28107",
    "sg:province":"NC",
    "sg:tags":[
        "produce"
    ],
    "wof:name":"Lemon's Farm Fresh Produce",
    "wof:placetype":"venue"
},
  "geometry": {"coordinates":[-80.512123,35.223051],"type":"Point"}
}