{
  "type": "Feature",
  "properties": {
    "addr:full":"901 Hearthridge Ct Raleigh NC 27609",
    "addr:housenumber":"901",
    "addr:postcode":"27609",
    "addr:street":"Hearthridge Ct",
    "iso:country":"US",
    "sg:address":"901 Hearthridge Ct",
    "sg:city":"Raleigh",
    "sg:classifiers":[
        {
            "category":"Professional",
            "subcategory":"Advertising",
            "type":"Services"
        }
    ],
    "sg:phone":"+1 919 217 4576",
    "sg:postcode":"27609",
    "sg:province":"NC",
    "sg:tags":[
        "counselor"
    ],
    "wof:name":"Sunrise Promotions",
    "wof:placetype":"venue"
},
  "geometry": {"coordinates":[-78.65213199999999,35.86914],"type":"Point"}
}