{
  "type": "Feature",
  "properties": {
    "addr:full":"7009 Breeders Cup Cir Charlotte NC 28215",
    "addr:housenumber":"7009",
    "addr:postcode":"28215",
    "addr:street":"Breeders Cup Cir",
    "iso:country":"US",
    "sg:address":"7009 Breeders Cup Cir",
    "sg:city":"Charlotte",
    "sg:classifiers":[
        {
            "category":"Social Services",
            "subcategory":"Child Care",
            "type":"Services"
        }
    ],
    "sg:phone":"+1 704 569 0560",
    "sg:postcode":"28215",
    "sg:province":"NC",
    "wof:name":"Tender Touch Home Child Care",
    "wof:placetype":"venue"
},
  "geometry": {"coordinates":[-80.71124500000001,35.238865],"type":"Point"}
}