{
  "type": "Feature",
  "properties": {
    "iso:country":"US",
    "sg:address":"1993 Neuse Rd",
    "sg:city":"Kinston",
    "sg:classifiers":[
        {
            "category":"Wholesale",
            "subcategory":"Auto Parts",
            "type":"Manufacturing & Wholesale Goods"
        }
    ],
    "sg:phone":"+1 252 527 3464",
    "sg:postcode":"28501",
    "sg:province":"NC",
    "sg:tags":[
        "used",
        "bod"
    ],
    "wof:name":"Joe Webbs Garage & Salvage",
    "wof:placetype":"venue"
},
  "geometry": {"coordinates":[-77.494097,35.277349],"type":"Point"}
}