{
  "type": "Feature",
  "properties": {
    "addr:full":"7106 Hebron Church Rd Mebane NC 27302",
    "addr:housenumber":"7106",
    "addr:postcode":"27302",
    "addr:street":"Hebron Church Rd",
    "iso:country":"US",
    "sg:address":"7106 Hebron Church Rd",
    "sg:city":"Mebane",
    "sg:classifiers":[
        {
            "category":"Professional",
            "type":"Services"
        }
    ],
    "sg:phone":"+1 919 563 1781",
    "sg:postcode":"27302",
    "sg:province":"NC",
    "wof:name":"4 Life Inc",
    "wof:placetype":"venue"
},
  "geometry": {"coordinates":[-79.22610400000001,36.070536],"type":"Point"}
}