{
  "type": "Feature",
  "properties": {
    "addr:full":"9208 Leeds Ct Raleigh NC 27615",
    "addr:housenumber":"9208",
    "addr:postcode":"27615",
    "addr:street":"Leeds Ct",
    "iso:country":"US",
    "sg:address":"9208 Leeds Ct",
    "sg:city":"Raleigh",
    "sg:classifiers":[
        {
            "category":"Manufacturing",
            "subcategory":"Apparel",
            "type":"Manufacturing & Wholesale Goods"
        }
    ],
    "sg:phone":"+1 919 845 3051",
    "sg:postcode":"27615",
    "sg:province":"NC",
    "sg:tags":[
        "equine",
        "sportswear",
        "mfg"
    ],
    "wof:name":"WUnderwear",
    "wof:placetype":"venue"
},
  "geometry": {"coordinates":[-78.644803,35.908374],"type":"Point"}
}