{
  "type": "Feature",
  "properties": {
    "iso:country":"US",
    "sg:address":"3601 Lubbock Dr",
    "sg:city":"Raleigh",
    "sg:classifiers":[
        {
            "category":"Professional",
            "type":"Services"
        }
    ],
    "sg:phone":"+1 919 782 4686",
    "sg:postcode":"27612",
    "sg:province":"NC",
    "wof:name":"Red Threads Inc",
    "wof:placetype":"venue"
},
  "geometry": {"coordinates":[-78.674877,35.823779],"type":"Point"}
}