{
  "type": "Feature",
  "properties": {
    "addr:full":"7312 Vanclaybon Rd Apex NC 27523",
    "addr:housenumber":"7312",
    "addr:postcode":"27523",
    "addr:street":"Vanclaybon Rd",
    "iso:country":"US",
    "sg:address":"7312 Vanclaybon Rd",
    "sg:city":"Apex",
    "sg:classifiers":[
        {
            "category":"Shopping",
            "subcategory":"Computers & Home Electronics",
            "type":"Retail Goods"
        }
    ],
    "sg:phone":"+1 919 363 4886",
    "sg:postcode":"27523",
    "sg:province":"NC",
    "sg:tags":[
        "software"
    ],
    "sg:website":"www.tls-us.com",
    "wof:name":"Translogic Systems",
    "wof:placetype":"venue"
},
  "geometry": {"coordinates":[-78.913573,35.744057],"type":"Point"}
}