{
  "type": "Feature",
  "properties": {
    "iso:country":"US",
    "sg:address":"815 Gillespie St",
    "sg:city":"Fayetteville",
    "sg:classifiers":[
        {
            "category":"Freight",
            "type":"Transportation"
        }
    ],
    "sg:phone":"+1 910 483 1386",
    "sg:postcode":"28306",
    "sg:province":"NC",
    "sg:tags":[
        "mover"
    ],
    "wof:name":"E-Z Move",
    "wof:placetype":"venue"
},
  "geometry": {"coordinates":[-78.884783,35.035213],"type":"Point"}
}