{
  "type": "Feature",
  "properties": {
    "iso:country":"US",
    "sg:address":"553 Cook Rd",
    "sg:city":"Elon College",
    "sg:classifiers":[
        {
            "category":"Shopping",
            "subcategory":"Used Merchandise",
            "type":"Retail Goods"
        }
    ],
    "sg:phone":"+1 336 449 4730",
    "sg:postcode":"27244",
    "sg:province":"NC",
    "wof:name":"Uniques/George Lentz",
    "wof:placetype":"venue"
},
  "geometry": {"coordinates":[-79.523444,36.091997],"type":"Point"}
}