{
  "type": "Feature",
  "properties": {
    "iso:country":"US",
    "sg:address":"112 E South Main St",
    "sg:city":"Waxhaw",
    "sg:classifiers":[
        {
            "category":"Restaurant",
            "type":"Food & Drink"
        }
    ],
    "sg:menulink":"http://www.allmenus.com/nc/jackson/236839-bridge--rail-restaurant/menu/",
    "sg:phone":"+1 704 843 5005",
    "sg:postcode":"28173",
    "sg:province":"NC",
    "sg:tags":[
        "american"
    ],
    "wof:name":"Bridge & Rail Restaurant",
    "wof:placetype":"venue"
},
  "geometry": {"coordinates":[-80.743427,34.924618],"type":"Point"}
}