{
  "type": "Feature",
  "properties": {
    "iso:country":"US",
    "sg:address":"3816 Latrobe Dr",
    "sg:city":"Charlotte",
    "sg:classifiers":[
        {
            "category":"Mining & Drilling",
            "type":"Manufacturing & Wholesale Goods"
        }
    ],
    "sg:phone":"+1 704 377 7983",
    "sg:postcode":"28211",
    "sg:province":"NC",
    "sg:tags":[
        "coal",
        "shipping"
    ],
    "wof:name":"Coal Clinics",
    "wof:placetype":"venue"
},
  "geometry": {"coordinates":[-80.796582,35.193816],"type":"Point"}
}