{
  "type": "Feature",
  "properties": {
    "addr:full":"5341 Greenville Loop Rd Wilmington NC 28409",
    "addr:housenumber":"5341",
    "addr:postcode":"28409",
    "addr:street":"Greenville Loop Rd",
    "iso:country":"US",
    "sg:address":"5341 Greenville Loop Rd",
    "sg:city":"Wilmington",
    "sg:classifiers":[
        {
            "category":"Professional",
            "subcategory":"Research",
            "type":"Services"
        }
    ],
    "sg:phone":"+1 910 799 6594",
    "sg:postcode":"28409",
    "sg:province":"NC",
    "sg:tags":[
        "foundation",
        "philanthropic"
    ],
    "wof:name":"North Carolina Foundation",
    "wof:placetype":"venue"
},
  "geometry": {"coordinates":[-77.858581,34.196377],"type":"Point"}
}