{
  "type": "Feature",
  "properties": {
    "iso:country":"US",
    "sg:address":"200 Bessie Foy Rd",
    "sg:city":"Richlands",
    "sg:classifiers":[
        {
            "category":"Building & Trades",
            "subcategory":"Construction",
            "type":"Services"
        }
    ],
    "sg:phone":"+1 910 989 2700",
    "sg:postcode":"28574",
    "sg:province":"NC",
    "sg:tags":[
        "water",
        "well",
        "drilling"
    ],
    "wof:name":"A & D Drilling",
    "wof:placetype":"venue"
},
  "geometry": {"coordinates":[-77.629969,34.762563],"type":"Point"}
}