{
  "type": "Feature",
  "properties": {
    "addr:full":"5617 Shell Road Village Dr Wilmington NC 28403",
    "addr:housenumber":"5617",
    "addr:postcode":"28403",
    "addr:street":"Shell Road Village Dr",
    "iso:country":"US",
    "sg:address":"5617 Shell Road Village Dr",
    "sg:city":"Wilmington",
    "sg:classifiers":[
        {
            "category":"Health Services",
            "subcategory":"Clinic",
            "type":"Services"
        }
    ],
    "sg:phone":"+1 910 395 5900",
    "sg:postcode":"28403",
    "sg:province":"NC",
    "wof:name":"GNC Store 9200",
    "wof:placetype":"venue"
},
  "geometry": {"coordinates":[-77.855008,34.215656],"type":"Point"}
}