{
  "type": "Feature",
  "properties": {
    "iso:country":"US",
    "sg:address":"2700 S Horner Blvd",
    "sg:city":"Sanford",
    "sg:classifiers":[
        {
            "category":"Manufacturing",
            "subcategory":"Tools & Machinery",
            "type":"Manufacturing & Wholesale Goods"
        }
    ],
    "sg:phone":"+1 919 774 1297",
    "sg:postcode":"27332",
    "sg:province":"NC",
    "sg:tags":[
        "measuring",
        "instrument",
        "electrical",
        "mfg"
    ],
    "wof:name":"Alotech Inc",
    "wof:placetype":"venue"
},
  "geometry": {"coordinates":[-79.14126899999999,35.456629],"type":"Point"}
}