{
  "type": "Feature",
  "properties": {
    "iso:country":"US",
    "sg:address":"7990 N Point Blvd",
    "sg:city":"Winston Salem",
    "sg:classifiers":[
        {
            "category":"Insurance",
            "subcategory":"Insurance Agent",
            "type":"Services"
        }
    ],
    "sg:phone":"+1 336 896 0345",
    "sg:postcode":"27106",
    "sg:province":"NC",
    "wof:name":"National Marrow Donor Program",
    "wof:placetype":"venue"
},
  "geometry": {"coordinates":[-80.272851,36.150679],"type":"Point"}
}