{
  "type": "Feature",
  "properties": {
    "addr:full":"35370 US Hwy 264 Engelhard NC 27824",
    "addr:postcode":"35370;27824",
    "addr:street":"Us Hwy 264",
    "iso:country":"US",
    "sg:address":"35370 US Hwy 264",
    "sg:city":"Engelhard",
    "sg:classifiers":[
        {
            "category":"Farming",
            "subcategory":"Fish & Marine Products",
            "type":"Manufacturing & Wholesale Goods"
        }
    ],
    "sg:phone":"+1 252 925 1887",
    "sg:postcode":"27824",
    "sg:province":"NC",
    "sg:tags":[
        "fishing"
    ],
    "wof:name":"Clifford Spencer",
    "wof:placetype":"venue"
},
  "geometry": {"coordinates":[-75.993973,35.512589],"type":"Point"}
}