{
  "type": "Feature",
  "properties": {
    "addr:full":"10262 Hasty Rd Laurinburg NC 28352",
    "addr:housenumber":"10262",
    "addr:postcode":"28352",
    "addr:street":"Hasty Rd",
    "iso:country":"US",
    "sg:address":"10262 Hasty Rd",
    "sg:city":"Laurinburg",
    "sg:classifiers":[
        {
            "category":"Restaurant",
            "type":"Food & Drink"
        }
    ],
    "sg:phone":"+1 910 276 7581",
    "sg:postcode":"28352",
    "sg:province":"NC",
    "sg:tags":[
        "eating"
    ],
    "wof:name":"General Mc Arthur S Resta",
    "wof:placetype":"venue"
},
  "geometry": {"coordinates":[-79.48800300000001,34.717559],"type":"Point"}
}