{
  "type": "Feature",
  "properties": {
    "addr:full":"5809 Old Pineville Rd Charlotte NC 28217",
    "addr:housenumber":"5809",
    "addr:postcode":"28217",
    "addr:street":"Old Pineville Rd",
    "iso:country":"US",
    "sg:address":"5809 Old Pineville Rd",
    "sg:city":"Charlotte",
    "sg:classifiers":[
        {
            "category":"Retail",
            "subcategory":"Auto Repair",
            "type":"Services"
        }
    ],
    "sg:phone":"+1 704 525 0946",
    "sg:postcode":"28217",
    "sg:province":"NC",
    "sg:tags":[
        "body",
        "painting",
        "repairing",
        "automobile"
    ],
    "sg:website":"http://www.uhaul.com/Locations/Rentals-near-Charlotte-NC-28217/026448",
    "wof:name":"U-Haul Neighborhood Dealer - Complete Automotive Shop",
    "wof:placetype":"venue"
},
  "geometry": {"coordinates":[-80.878434,35.160983],"type":"Point"}
}