{
  "type": "Feature",
  "properties": {
    "addr:full":"2901 Cloverleaf Pkwy Kannapolis NC 28083",
    "addr:housenumber":"2901",
    "addr:postcode":"28083",
    "addr:street":"Cloverleaf Pkwy",
    "iso:country":"US",
    "sg:address":"2901 Cloverleaf Pkwy",
    "sg:city":"Kannapolis",
    "sg:classifiers":[
        {
            "category":"Social Services",
            "type":"Services"
        }
    ],
    "sg:phone":"+1 704 788 2055",
    "sg:postcode":"28083",
    "sg:province":"NC",
    "sg:tags":[
        "church",
        "place",
        "worship",
        "welfare"
    ],
    "sg:website":"http://www.salvationarmyusa.org/",
    "wof:name":"The Salvation Army",
    "wof:placetype":"venue"
},
  "geometry": {"coordinates":[-80.608749,35.450581],"type":"Point"}
}