{
  "type": "Feature",
  "properties": {
    "iso:country":"US",
    "sg:address":"109 1st Ave NE",
    "sg:city":"Hildebran",
    "sg:classifiers":[
        {
            "category":"Building & Trades",
            "subcategory":"Electrical",
            "type":"Services"
        }
    ],
    "sg:phone":"+1 828 397 5553",
    "sg:postcode":"28637",
    "sg:province":"NC",
    "sg:tags":[
        "electrical",
        "electric",
        "contractor"
    ],
    "wof:name":"Recore Electrical Contractors",
    "wof:placetype":"venue"
},
  "geometry": {"coordinates":[-81.421841,35.716179],"type":"Point"}
}