{
  "type": "Feature",
  "properties": {
    "addr:full":"618 W 14th Ave Greenville NC 27834",
    "addr:housenumber":"618",
    "addr:postcode":"27834",
    "addr:street":"W 14Th Ave",
    "iso:country":"US",
    "sg:address":"618 W 14th Ave",
    "sg:city":"Greenville",
    "sg:classifiers":[
        {
            "category":"Education",
            "subcategory":"Library",
            "type":"Public Place"
        }
    ],
    "sg:phone":"+1 252 329 4583",
    "sg:postcode":"27834",
    "sg:province":"NC",
    "wof:name":"George Washington Carver Lib",
    "wof:placetype":"venue"
},
  "geometry": {"coordinates":[-77.387187,35.611799],"type":"Point"}
}