{
  "type": "Feature",
  "properties": {
    "iso:country":"US",
    "sg:address":"200 Clanton Rd",
    "sg:city":"Charlotte",
    "sg:classifiers":[
        {
            "category":"Manufacturing",
            "subcategory":"Retail Goods",
            "type":"Manufacturing & Wholesale Goods"
        }
    ],
    "sg:phone":"+1 704 523 1010",
    "sg:postcode":"28217",
    "sg:province":"NC",
    "sg:tags":[
        "assembly",
        "fabricating"
    ],
    "sg:website":"www.lifespanservices.org",
    "wof:name":"Life Span",
    "wof:placetype":"venue"
},
  "geometry": {"coordinates":[-80.875131,35.195091],"type":"Point"}
}