{
  "type": "Feature",
  "properties": {
    "iso:country":"US",
    "sg:address":"521 Nelson St",
    "sg:city":"Kernersville",
    "sg:classifiers":[
        {
            "category":"Banks & Credit Unions",
            "subcategory":"Bank",
            "type":"Services"
        }
    ],
    "sg:phone":"+1 336 992 5260",
    "sg:postcode":"27284",
    "sg:province":"NC",
    "sg:tags":[
        "depository",
        "banking"
    ],
    "wof:name":"Check Into Cash",
    "wof:placetype":"venue"
},
  "geometry": {"coordinates":[-80.068522,36.12756],"type":"Point"}
}