{
  "type": "Feature",
  "properties": {
    "iso:country":"US",
    "sg:address":"3455 University Pkwy",
    "sg:city":"Winston Salem",
    "sg:classifiers":[
        {
            "category":"Professional",
            "subcategory":"Management & Consulting",
            "type":"Services"
        }
    ],
    "sg:phone":"+1   ",
    "sg:postcode":"27106",
    "sg:province":"NC",
    "wof:name":"Incapita Inc",
    "wof:placetype":"venue"
},
  "geometry": {"coordinates":[-80.272184,36.137896],"type":"Point"}
}