{
  "type": "Feature",
  "properties": {
    "iso:country":"US",
    "sg:address":"5 Meadow Ridge Dr",
    "sg:city":"Asheville",
    "sg:classifiers":[
        {
            "category":"Real Estate",
            "subcategory":"Real Estate Operator",
            "type":"Services"
        }
    ],
    "sg:phone":"+1 828 281 3753",
    "sg:postcode":"28804",
    "sg:province":"NC",
    "sg:tags":[
        "building",
        "nonresidential"
    ],
    "wof:name":"Calco Properties LLC",
    "wof:placetype":"venue"
},
  "geometry": {"coordinates":[-82.50319399999999,35.630666],"type":"Point"}
}