{
  "type": "Feature",
  "properties": {
    "addr:full":"5118 N Causeway Dr Winston Salem NC 27106",
    "addr:housenumber":"5118",
    "addr:postcode":"27106",
    "addr:street":"N Causeway Dr",
    "iso:country":"US",
    "sg:address":"5118 N Causeway Dr",
    "sg:city":"Winston Salem",
    "sg:classifiers":[
        {
            "category":"Building & Trades",
            "subcategory":"Landscaping Services",
            "type":"Services"
        }
    ],
    "sg:phone":"+1 336 924 5911",
    "sg:postcode":"27106",
    "sg:province":"NC",
    "sg:tags":[
        "tree"
    ],
    "sg:website":"www.lusktree.com",
    "wof:name":"Lusk Tree Svc Inc",
    "wof:placetype":"venue"
},
  "geometry": {"coordinates":[-80.34527199999999,36.17357],"type":"Point"}
}