{
  "type": "Feature",
  "properties": {
    "iso:country":"US",
    "sg:address":"115 Red Banks Rd",
    "sg:city":"Greenville",
    "sg:classifiers":[
        {
            "category":"Personal",
            "subcategory":"Beauty Salon",
            "type":"Services"
        }
    ],
    "sg:phone":"+1 252 321 8456",
    "sg:postcode":"27858",
    "sg:province":"NC",
    "sg:tags":[
        "shop"
    ],
    "wof:name":"Salon Exposure",
    "wof:placetype":"venue"
},
  "geometry": {"coordinates":[-77.37588,35.582575],"type":"Point"}
}