{
  "type": "Feature",
  "properties": {
    "iso:country":"US",
    "sg:address":"131 Lamplighter Cir",
    "sg:city":"Winston Salem",
    "sg:classifiers":[
        {
            "category":"Health Services",
            "subcategory":"Health Practitioner",
            "type":"Services"
        }
    ],
    "sg:phone":"+1 336 768 8323",
    "sg:postcode":"27104",
    "sg:province":"NC",
    "sg:tags":[
        "psychologist"
    ],
    "wof:name":"Karnes Associates",
    "wof:placetype":"venue"
},
  "geometry": {"coordinates":[-80.357759,36.088615],"type":"Point"}
}