{
  "type": "Feature",
  "properties": {
    "addr:full":"9311 Morgan St Laurel Hill NC 28351",
    "addr:housenumber":"9311",
    "addr:postcode":"28351",
    "addr:street":"Morgan St",
    "iso:country":"US",
    "sg:address":"9311 Morgan St",
    "sg:city":"Laurel Hill",
    "sg:classifiers":[
        {
            "category":"Insurance",
            "subcategory":"Insurance Agent",
            "type":"Services"
        }
    ],
    "sg:phone":"+1 910 462 3140",
    "sg:postcode":"28351",
    "sg:province":"NC",
    "wof:name":"Charlie Fipps Agency",
    "wof:placetype":"venue"
},
  "geometry": {"coordinates":[-79.54581,34.812506],"type":"Point"}
}