{
  "type": "Feature",
  "properties": {
    "addr:full":"8189 Broad St Rural Hall NC 27045",
    "addr:housenumber":"8189",
    "addr:postcode":"27045",
    "addr:street":"Broad St",
    "iso:country":"US",
    "sg:address":"8189 Broad St",
    "sg:city":"Rural Hall",
    "sg:classifiers":[
        {
            "category":"Autos & Motor Vehicles",
            "subcategory":"Automobile Sales",
            "type":"Retail Goods"
        }
    ],
    "sg:phone":"+1 336 969 5777",
    "sg:postcode":"27045",
    "sg:province":"NC",
    "sg:tags":[
        "car",
        "dealer"
    ],
    "wof:name":"Bobby Marshall Used Cars",
    "wof:placetype":"venue"
},
  "geometry": {"coordinates":[-80.295117,36.242555],"type":"Point"}
}