{
  "type": "Feature",
  "properties": {
    "addr:full":"125 Racine Dr Wilmington NC 28403",
    "addr:housenumber":"125",
    "addr:postcode":"28403",
    "addr:street":"Racine Dr",
    "iso:country":"US",
    "sg:address":"125 Racine Dr",
    "sg:city":"Wilmington",
    "sg:classifiers":[
        {
            "category":"Banks & Credit Unions",
            "subcategory":"Bank",
            "type":"Services"
        }
    ],
    "sg:phone":"+1 910 392 6688",
    "sg:postcode":"28403",
    "sg:province":"NC",
    "sg:tags":[
        "state"
    ],
    "wof:name":"Corning Federal Credit Union",
    "wof:placetype":"venue"
},
  "geometry": {"coordinates":[-77.860967,34.242642],"type":"Point"}
}