{
  "type": "Feature",
  "properties": {
    "addr:full":"5103 W Market St Greensboro NC 27409",
    "addr:housenumber":"5103",
    "addr:postcode":"27409",
    "addr:street":"W Market St",
    "iso:country":"US",
    "sg:address":"5103 W Market St",
    "sg:city":"Greensboro",
    "sg:classifiers":[
        {
            "category":"Personal",
            "type":"Services"
        }
    ],
    "sg:phone":"+1 336 545 4209",
    "sg:postcode":"27409",
    "sg:province":"NC",
    "sg:tags":[
        "therapist",
        "massage"
    ],
    "wof:name":"Therapeutic Massage & Care",
    "wof:placetype":"venue"
},
  "geometry": {"coordinates":[-79.87948,36.069244],"type":"Point"}
}