{
  "type": "Feature",
  "properties": {
    "addr:full":"2022 S Miami Blvd Durham NC 27703",
    "addr:housenumber":"2022",
    "addr:postcode":"27703",
    "addr:street":"S Miami Blvd",
    "iso:country":"US",
    "sg:address":"2022 S Miami Blvd",
    "sg:city":"Durham",
    "sg:classifiers":[
        {
            "category":"Retail",
            "subcategory":"Repair Shop",
            "type":"Services"
        }
    ],
    "sg:phone":"+1 919 957 8740",
    "sg:postcode":"27703",
    "sg:province":"NC",
    "sg:tags":[
        "clocks",
        "parts"
    ],
    "wof:name":"Anthony's Clocks",
    "wof:placetype":"venue"
},
  "geometry": {"coordinates":[-78.83883299999999,35.941934],"type":"Point"}
}