{
  "type": "Feature",
  "properties": {
    "iso:country":"US",
    "sg:address":"510 Deese St",
    "sg:city":"Monroe",
    "sg:classifiers":[
        {
            "category":"Organizations",
            "subcategory":"Religious Organization",
            "type":"Services"
        }
    ],
    "sg:phone":"+1 704 283 4556",
    "sg:postcode":"28112",
    "sg:province":"NC",
    "sg:tags":[
        "church"
    ],
    "wof:name":"United Pentecostal Church",
    "wof:placetype":"venue"
},
  "geometry": {"coordinates":[-80.527883,34.978652],"type":"Point"}
}