{
  "type": "Feature",
  "properties": {
    "iso:country":"US",
    "sg:address":"101 Lochside Dr",
    "sg:city":"Cary",
    "sg:classifiers":[
        {
            "category":"Professional",
            "subcategory":"Engineering",
            "type":"Services"
        }
    ],
    "sg:phone":"+1   ",
    "sg:postcode":"27518",
    "sg:province":"NC",
    "wof:name":"Richard M Felder Dr",
    "wof:placetype":"venue"
},
  "geometry": {"coordinates":[-78.75742099999999,35.734173],"type":"Point"}
}