{
  "type": "Feature",
  "properties": {
    "iso:country":"US",
    "sg:address":"406 Becks Nursery Rd",
    "sg:city":"Lexington",
    "sg:classifiers":[
        {
            "category":"Building & Trades",
            "subcategory":"Construction",
            "type":"Services"
        }
    ],
    "sg:phone":"+1 336 746 5727",
    "sg:postcode":"27292",
    "sg:province":"NC",
    "sg:tags":[
        "water",
        "well",
        "drilling"
    ],
    "wof:name":"C A Hedrick Well Drilling Inc",
    "wof:placetype":"venue"
},
  "geometry": {"coordinates":[-80.185226,35.752944],"type":"Point"}
}