{
  "type": "Feature",
  "properties": {
    "iso:country":"US",
    "sg:address":"320 Salter Path Rd",
    "sg:city":"Atlantic Beach",
    "sg:classifiers":[
        {
            "category":"Personal",
            "subcategory":"Beauty Salon",
            "type":"Services"
        }
    ],
    "sg:phone":"+1 252 726 1844",
    "sg:postcode":"28512",
    "sg:province":"NC",
    "sg:tags":[
        "shop"
    ],
    "wof:name":"Judy's Hairstylists",
    "wof:placetype":"venue"
},
  "geometry": {"coordinates":[-76.82445300000001,34.694629],"type":"Point"}
}