{
  "type": "Feature",
  "properties": {
    "addr:full":"14017 Pytchley Ln Charlotte NC 28273",
    "addr:housenumber":"14017",
    "addr:postcode":"28273",
    "addr:street":"Pytchley Ln",
    "iso:country":"US",
    "sg:address":"14017 Pytchley Ln",
    "sg:city":"Charlotte",
    "sg:classifiers":[
        {
            "category":"Professional",
            "type":"Services"
        }
    ],
    "sg:phone":"+1 704 588 5230",
    "sg:postcode":"28273",
    "sg:province":"NC",
    "wof:name":"Top O Line Events",
    "wof:placetype":"venue"
},
  "geometry": {"coordinates":[-80.966047,35.102342],"type":"Point"}
}