{
  "type": "Feature",
  "properties": {
    "addr:full":"231 Fairway Dr Fayetteville NC 28305",
    "addr:housenumber":"231",
    "addr:postcode":"28305",
    "addr:street":"Fairway Dr",
    "iso:country":"US",
    "sg:address":"231 Fairway Dr",
    "sg:city":"Fayetteville",
    "sg:classifiers":[
        {
            "category":"Real Estate",
            "subcategory":"Real Estate Agent",
            "type":"Services"
        }
    ],
    "sg:phone":"+1 910 864 2626",
    "sg:postcode":"28305",
    "sg:province":"NC",
    "wof:name":"Franklin Johnson Commercial Rl",
    "wof:placetype":"venue"
},
  "geometry": {"coordinates":[-78.916545,35.043475],"type":"Point"}
}