{
  "type": "Feature",
  "properties": {
    "iso:country":"US",
    "sg:address":"781 Union St S",
    "sg:city":"Concord",
    "sg:classifiers":[
        {
            "category":"Professional",
            "subcategory":"Management & Consulting",
            "type":"Services"
        }
    ],
    "sg:phone":"+1   ",
    "sg:postcode":"28025",
    "sg:province":"NC",
    "sg:tags":[
        "training",
        "assessment"
    ],
    "wof:name":"Proed Associates Inc",
    "wof:placetype":"venue"
},
  "geometry": {"coordinates":[-80.562485,35.390185],"type":"Point"}
}