{
  "type": "Feature",
  "properties": {
    "addr:full":"184 Laurel Rd Arden NC 28704",
    "addr:housenumber":"184",
    "addr:postcode":"28704",
    "addr:street":"Laurel Rd",
    "iso:country":"US",
    "sg:address":"184 Laurel Rd",
    "sg:city":"Arden",
    "sg:classifiers":[
        {
            "category":"Sports & Exercise",
            "subcategory":"Bowling",
            "type":"Entertainment"
        }
    ],
    "sg:phone":"+1 828 687 9422",
    "sg:postcode":"28704",
    "sg:province":"NC",
    "sg:tags":[
        "center"
    ],
    "wof:name":"American Bowling Congress",
    "wof:placetype":"venue"
},
  "geometry": {"coordinates":[-82.507743,35.480423],"type":"Point"}
}