{
  "type": "Feature",
  "properties": {
    "iso:country":"US",
    "sg:address":"317 Atkinson St",
    "sg:city":"Laurinburg",
    "sg:classifiers":[
        {
            "category":"Shopping",
            "subcategory":"Department Store",
            "type":"Retail Goods"
        },
        {
            "category":"Shopping",
            "subcategory":"Clothing, Apparel, & Fashions",
            "type":"Retail Goods"
        }
    ],
    "sg:phone":"+1 910 277 0095",
    "sg:postcode":"28352",
    "sg:province":"NC",
    "sg:tags":[
        "family"
    ],
    "wof:name":"Johnny's Fashions",
    "wof:placetype":"venue"
},
  "geometry": {"coordinates":[-79.46345100000001,34.775536],"type":"Point"}
}