{
  "type": "Feature",
  "properties": {
    "iso:country":"US",
    "sg:address":"501 Nutt St",
    "sg:city":"Wilmington",
    "sg:classifiers":[
        {
            "category":"Professional",
            "subcategory":"Business Services",
            "type":"Services"
        }
    ],
    "sg:phone":"+1 910 763 6739",
    "sg:postcode":"28401",
    "sg:province":"NC",
    "sg:tags":[
        "convention",
        "meeting",
        "facility"
    ],
    "sg:website":"www.nccoastalevents.com",
    "wof:name":"Coast Line Convention Ctr",
    "wof:placetype":"venue"
},
  "geometry": {"coordinates":[-77.950226,34.241624],"type":"Point"}
}