{
  "type": "Feature",
  "properties": {
    "iso:country":"US",
    "sg:address":"3023 Devonshire Dr",
    "sg:city":"Raleigh",
    "sg:classifiers":[
        {
            "category":"Professional",
            "subcategory":"Engineering",
            "type":"Services"
        },
        {
            "category":"Professional",
            "subcategory":"Management & Consulting",
            "type":"Services"
        }
    ],
    "sg:phone":"+1 919 881 1290",
    "sg:postcode":"27607",
    "sg:province":"NC",
    "sg:tags":[
        "business",
        "engineer"
    ],
    "wof:name":"McCain Special Project Svcs",
    "wof:placetype":"venue"
},
  "geometry": {"coordinates":[-78.674666,35.811811],"type":"Point"}
}