{
  "type": "Feature",
  "properties": {
    "addr:full":"204 Jacksons Run Morganton NC 28655",
    "addr:housenumber":"204",
    "addr:postcode":"28655",
    "addr:street":"Jacksons Run",
    "iso:country":"US",
    "sg:address":"204 Jacksons Run",
    "sg:city":"Morganton",
    "sg:classifiers":[
        {
            "category":"Building & Trades",
            "subcategory":"Construction",
            "type":"Services"
        }
    ],
    "sg:phone":"+1 828 433 9667",
    "sg:postcode":"28655",
    "sg:province":"NC",
    "sg:tags":[
        "dry wall",
        "contractor"
    ],
    "wof:name":"Steven D Lovelace Drywall",
    "wof:placetype":"venue"
},
  "geometry": {"coordinates":[-81.649456,35.747378],"type":"Point"}
}