{
  "type": "Feature",
  "properties": {
    "iso:country":"US",
    "sg:address":"4744 Island Ford Rd",
    "sg:city":"Randleman",
    "sg:classifiers":[
        {
            "category":"Shopping",
            "subcategory":"Discount & Variety Stores",
            "type":"Retail Goods"
        }
    ],
    "sg:phone":"+1 336 495 6800",
    "sg:postcode":"27317",
    "sg:province":"NC",
    "sg:tags":[
        "merchandise",
        "general"
    ],
    "sg:website":"www.rheem.com",
    "wof:name":"Rheem Sales Co",
    "wof:placetype":"venue"
},
  "geometry": {"coordinates":[-79.83604800000001,35.823687],"type":"Point"}
}