{
  "type": "Feature",
  "properties": {
    "addr:full":"4670 Patterson Ave Winston Salem NC 27105",
    "addr:housenumber":"4670",
    "addr:postcode":"27105",
    "addr:street":"Patterson Ave",
    "iso:country":"US",
    "sg:address":"4670 Patterson Ave",
    "sg:city":"Winston Salem",
    "sg:classifiers":[
        {
            "category":"Organizations",
            "subcategory":"Religious Organization",
            "type":"Services"
        }
    ],
    "sg:phone":"+1 336 744 0089",
    "sg:postcode":"27105",
    "sg:province":"NC",
    "sg:tags":[
        "church"
    ],
    "wof:name":"Higher Hope Ministries Intl",
    "wof:placetype":"venue"
},
  "geometry": {"coordinates":[-80.274332,36.183029],"type":"Point"}
}