{
  "type": "Feature",
  "properties": {
    "iso:country":"US",
    "sg:address":"1478 Garner Station Blvd",
    "sg:city":"Raleigh",
    "sg:classifiers":[
        {
            "category":"Restaurant",
            "type":"Food & Drink"
        }
    ],
    "sg:menulink":"http://www.allmenus.com/nc/swift-creek/137544-subway/menu/",
    "sg:phone":"+1 919 772 2000",
    "sg:postcode":"27603",
    "sg:province":"NC",
    "sg:tags":[
        "american",
        "sandwich"
    ],
    "wof:name":"Subway",
    "wof:placetype":"venue"
},
  "geometry": {"coordinates":[-78.65406,35.72487],"type":"Point"}
}