{
  "type": "Feature",
  "properties": {
    "iso:country":"US",
    "sg:address":"3201 Easy St",
    "sg:city":"Dunn",
    "sg:classifiers":[
        {
            "category":"Social Services",
            "subcategory":"Child Care",
            "type":"Services"
        }
    ],
    "sg:phone":"+1 910 567 5510",
    "sg:postcode":"28334",
    "sg:province":"NC",
    "sg:tags":[
        "kindergarten",
        "academic",
        "school"
    ],
    "sg:website":"www.telamon.org",
    "wof:name":"St Martin's Migrant Headstart",
    "wof:placetype":"venue"
},
  "geometry": {"coordinates":[-78.450453,35.243606],"type":"Point"}
}