{
  "type": "Feature",
  "properties": {
    "iso:country":"US",
    "sg:address":"136 S Business Ct",
    "sg:city":"Rocky Mount",
    "sg:classifiers":[
        {
            "category":"Manufacturing",
            "subcategory":"Tools & Machinery",
            "type":"Manufacturing & Wholesale Goods"
        }
    ],
    "sg:phone":"+1 252 985 5933",
    "sg:postcode":"27804",
    "sg:province":"NC",
    "sg:tags":[
        "equipment",
        "tree",
        "supply"
    ],
    "wof:name":"Pro-Equip Sign System",
    "wof:placetype":"venue"
},
  "geometry": {"coordinates":[-77.776431,36.00415],"type":"Point"}
}