{
  "type": "Feature",
  "properties": {
    "iso:country":"US",
    "sg:address":"4272 Old Faison Rd",
    "sg:city":"Knightdale",
    "sg:classifiers":[
        {
            "category":"Organizations",
            "subcategory":"Religious Organization",
            "type":"Services"
        }
    ],
    "sg:phone":"+1 919 261 0568",
    "sg:postcode":"27545",
    "sg:province":"NC",
    "sg:tags":[
        "church"
    ],
    "wof:name":"Knightdale Church Of God",
    "wof:placetype":"venue"
},
  "geometry": {"coordinates":[-78.491361,35.777748],"type":"Point"}
}