{
  "type": "Feature",
  "properties": {
    "addr:full":"11662 US Hwy 23 Mars Hill NC 28754",
    "addr:housenumber":"11662",
    "addr:postcode":"28754",
    "addr:street":"Us Hwy 23",
    "iso:country":"US",
    "sg:address":"11662 US Hwy 23",
    "sg:city":"Mars Hill",
    "sg:classifiers":[
        {
            "category":"Real Estate",
            "subcategory":"Real Estate Agent",
            "type":"Services"
        }
    ],
    "sg:phone":"+1 828 680 9900",
    "sg:postcode":"28754",
    "sg:province":"NC",
    "wof:name":"Robert Burns Realty",
    "wof:placetype":"venue"
},
  "geometry": {"coordinates":[-82.555575,35.917154],"type":"Point"}
}