{
  "type": "Feature",
  "properties": {
    "iso:country":"US",
    "sg:address":"7001 Development Drive",
    "sg:city":"Research Triangle Park",
    "sg:classifiers":[
        {
            "category":"Manufacturing",
            "subcategory":"Electronics",
            "type":"Manufacturing & Wholesale Goods"
        }
    ],
    "sg:postcode":"27709 ",
    "sg:province":"NC",
    "sg:website":"http://www.sonyericsson.com/",
    "wof:name":"Sony Ericsson",
    "wof:placetype":"venue"
},
  "geometry": {"coordinates":[-78.93756999999999,36.003206],"type":"Point"}
}