{
  "type": "Feature",
  "properties": {
    "iso:country":"US",
    "sg:address":"1235 East Blvd",
    "sg:city":"Charlotte",
    "sg:classifiers":[
        {
            "category":"Place Of Worship",
            "subcategory":"Church",
            "type":"Public Place"
        },
        {
            "category":"Recreation",
            "type":"Entertainment"
        }
    ],
    "sg:phone":"+1 704 332 4204",
    "sg:postcode":"28203",
    "sg:province":"NC",
    "sg:tags":[
        "ceremony",
        "chapel",
        "marriage",
        "wedding"
    ],
    "wof:name":"Perfectly Planned",
    "wof:placetype":"venue"
},
  "geometry": {"coordinates":[-80.845529,35.202603],"type":"Point"}
}