{
  "type": "Feature",
  "properties": {
    "iso:country":"US",
    "sg:address":"2935 State Hwy 35",
    "sg:city":"Woodland",
    "sg:classifiers":[
        {
            "category":"Building & Trades",
            "subcategory":"Electrical",
            "type":"Services"
        }
    ],
    "sg:phone":"+1 252 587 1997",
    "sg:postcode":"27897",
    "sg:province":"NC",
    "sg:tags":[
        "electrical",
        "contractor"
    ],
    "wof:name":"Benet Electrical",
    "wof:placetype":"venue"
},
  "geometry": {"coordinates":[-77.232539,36.355343],"type":"Point"}
}