{
  "type": "Feature",
  "properties": {
    "addr:full":"6321 Robinson Church Rd Charlotte NC 28215",
    "addr:housenumber":"6321",
    "addr:postcode":"28215",
    "addr:street":"Robinson Church Rd",
    "iso:country":"US",
    "sg:address":"6321 Robinson Church Rd",
    "sg:city":"Charlotte",
    "sg:classifiers":[
        {
            "category":"Organizations",
            "subcategory":"Religious Organization",
            "type":"Services"
        }
    ],
    "sg:phone":"+1   ",
    "sg:postcode":"28215",
    "sg:province":"NC",
    "wof:name":"Gateway Baptist Church",
    "wof:placetype":"venue"
},
  "geometry": {"coordinates":[-80.72745500000001,35.23169],"type":"Point"}
}