{
  "type": "Feature",
  "properties": {
    "addr:full":"2101 State Hwy 5 Aberdeen NC 28315",
    "addr:housenumber":"2101",
    "addr:postcode":"28315",
    "addr:street":"State Hwy 5",
    "iso:country":"US",
    "sg:address":"2101 State Hwy 5",
    "sg:city":"Aberdeen",
    "sg:classifiers":[
        {
            "category":"Shopping",
            "subcategory":"Used Merchandise",
            "type":"Retail Goods"
        }
    ],
    "sg:phone":"+1 910 215 9264",
    "sg:postcode":"28315",
    "sg:province":"NC",
    "sg:tags":[
        "flea",
        "market"
    ],
    "wof:name":"Monica's Place",
    "wof:placetype":"venue"
},
  "geometry": {"coordinates":[-79.470868,35.152616],"type":"Point"}
}