{
  "type": "Feature",
  "properties": {
    "addr:full":"471 Bizzell Braswell Rd Princeton NC 27569",
    "addr:housenumber":"471",
    "addr:postcode":"27569",
    "addr:street":"Bizzell Braswell Rd",
    "iso:country":"US",
    "sg:address":"471 Bizzell Braswell Rd",
    "sg:city":"Princeton",
    "sg:classifiers":[
        {
            "category":"Building & Trades",
            "subcategory":"Construction",
            "type":"Services"
        }
    ],
    "sg:phone":"+1 919 202 0345",
    "sg:postcode":"27569",
    "sg:province":"NC",
    "sg:tags":[
        "hanging",
        "contractor"
    ],
    "wof:name":"Affordable Paint Co",
    "wof:placetype":"venue"
},
  "geometry": {"coordinates":[-78.208386,35.503354],"type":"Point"}
}