{
  "type": "Feature",
  "properties": {
    "addr:full":"5121 Raynor Rd Garner NC 27529",
    "addr:housenumber":"5121",
    "addr:postcode":"27529",
    "addr:street":"Raynor Rd",
    "iso:country":"US",
    "sg:address":"5121 Raynor Rd",
    "sg:city":"Garner",
    "sg:classifiers":[
        {
            "category":"Building & Trades",
            "subcategory":"Construction",
            "type":"Services"
        }
    ],
    "sg:phone":"+1 919 662 2708",
    "sg:postcode":"27529",
    "sg:province":"NC",
    "sg:tags":[
        "painter"
    ],
    "wof:name":"J T Painting",
    "wof:placetype":"venue"
},
  "geometry": {"coordinates":[-78.550462,35.682244],"type":"Point"}
}