{
  "type": "Feature",
  "properties": {
    "addr:full":"100 Staton Ct Greenville NC 27834",
    "addr:housenumber":"100",
    "addr:postcode":"27834",
    "addr:street":"Staton Ct",
    "iso:country":"US",
    "sg:address":"100 Staton Ct",
    "sg:city":"Greenville",
    "sg:classifiers":[
        {
            "category":"Wholesale",
            "subcategory":"Machinery & Supplies",
            "type":"Manufacturing & Wholesale Goods"
        },
        {
            "category":"Wholesale",
            "subcategory":"Electrical",
            "type":"Manufacturing & Wholesale Goods"
        }
    ],
    "sg:phone":"+1 252 756 8000",
    "sg:postcode":"27834",
    "sg:province":"NC",
    "sg:tags":[
        "transmission",
        "equipment",
        "industrial",
        "power"
    ],
    "wof:name":"Applied Industrial Tech Inc",
    "wof:placetype":"venue"
},
  "geometry": {"coordinates":[-77.35646,35.648182],"type":"Point"}
}