{
  "type": "Feature",
  "properties": {
    "addr:full":"160 Avgol Dr Mocksville NC 27028",
    "addr:housenumber":"160",
    "addr:postcode":"27028",
    "addr:street":"Avgol Dr",
    "iso:country":"US",
    "sg:address":"160 Avgol Dr",
    "sg:city":"Mocksville",
    "sg:classifiers":[
        {
            "category":"Manufacturing",
            "subcategory":"Food",
            "type":"Manufacturing & Wholesale Goods"
        }
    ],
    "sg:phone":"+1 336 751 0209",
    "sg:postcode":"27028",
    "sg:province":"NC",
    "sg:tags":[
        "preparation",
        "mfg"
    ],
    "wof:name":"El Metate Inc",
    "wof:placetype":"venue"
},
  "geometry": {"coordinates":[-80.561168,35.876204],"type":"Point"}
}