{
  "type": "Feature",
  "properties": {
    "iso:country":"US",
    "sg:address":"6235 Barcliff Dr",
    "sg:city":"Charlotte",
    "sg:classifiers":[
        {
            "category":"Social Services",
            "subcategory":"Child Care",
            "type":"Services"
        }
    ],
    "sg:phone":"+1   ",
    "sg:postcode":"28212",
    "sg:province":"NC",
    "sg:tags":[
        "day"
    ],
    "wof:name":"Tender Moments",
    "wof:placetype":"venue"
},
  "geometry": {"coordinates":[-80.740342,35.215112],"type":"Point"}
}