{
  "type": "Feature",
  "properties": {
    "iso:country":"US",
    "sg:address":"305 S 3rd St",
    "sg:city":"Wilmington",
    "sg:classifiers":[
        {
            "category":"Travel",
            "subcategory":"Hotels & Motels",
            "type":"Entertainment"
        }
    ],
    "sg:phone":"+1 910 762 6626",
    "sg:postcode":"28401",
    "sg:province":"NC",
    "sg:tags":[
        "breakfast",
        "accommodation",
        "bed"
    ],
    "wof:name":"Murchison House",
    "wof:placetype":"venue"
},
  "geometry": {"coordinates":[-77.94534,34.230591],"type":"Point"}
}