{
  "type": "Feature",
  "properties": {
    "addr:full":"4104 Ridgebluffs Ct Raleigh NC 27603",
    "addr:housenumber":"4104",
    "addr:postcode":"27603",
    "addr:street":"Ridgebluffs Ct",
    "iso:country":"US",
    "sg:address":"4104 Ridgebluffs Ct",
    "sg:city":"Raleigh",
    "sg:classifiers":[
        {
            "category":"Building & Trades",
            "subcategory":"Construction",
            "type":"Services"
        },
        {
            "category":"Professional",
            "subcategory":"Business Services",
            "type":"Services"
        },
        {
            "category":"Home & Garden",
            "subcategory":"Building Materials",
            "type":"Retail Goods"
        },
        {
            "category":"Recreation",
            "type":"Entertainment"
        },
        {
            "category":"Building & Trades",
            "subcategory":"Landscaping Services",
            "type":"Services"
        },
        {
            "category":"Building & Trades",
            "subcategory":"Cleaning & Sanitation",
            "type":"Services"
        }
    ],
    "sg:phone":"+1 919 424 3780",
    "sg:postcode":"27603",
    "sg:province":"NC",
    "sg:tags":[
        "repair",
        "lawn",
        "services-household",
        "light",
        "handyman",
        "bathroom",
        "improvement",
        "decoration",
        "window",
        "maintenance",
        "remodeling",
        "christmas",
        "organizing"
    ],
    "sg:website":"http://www.mrhandyman.com",
    "wof:name":"Mr Handyman",
    "wof:placetype":"venue"
},
  "geometry": {"coordinates":[-78.71144,35.664398],"type":"Point"}
}