{
  "type": "Feature",
  "properties": {
    "addr:full":"425 Lee Cochran Rd Bryson City NC 28713",
    "addr:housenumber":"425",
    "addr:postcode":"28713",
    "addr:street":"Lee Cochran Rd",
    "iso:country":"US",
    "sg:address":"425 Lee Cochran Rd",
    "sg:city":"Bryson City",
    "sg:classifiers":[
        {
            "category":"Building & Trades",
            "subcategory":"Construction",
            "type":"Services"
        }
    ],
    "sg:phone":"+1 828 488 8752",
    "sg:postcode":"28713",
    "sg:province":"NC",
    "sg:tags":[
        "downspouts",
        "gutter"
    ],
    "wof:name":"Parton's Seamless Gutters",
    "wof:placetype":"venue"
},
  "geometry": {"coordinates":[-83.47703799999999,35.379631],"type":"Point"}
}