{
  "type": "Feature",
  "properties": {
    "addr:full":"3096 State Rd 39 Louisburg NC 27549",
    "addr:housenumber":"3096;39",
    "addr:postcode":"27549",
    "addr:street":"State Rd",
    "iso:country":"US",
    "sg:address":"3096 State Rd 39",
    "sg:city":"Louisburg",
    "sg:classifiers":[
        {
            "category":"Health Services",
            "subcategory":"Health Practitioner",
            "type":"Services"
        }
    ],
    "sg:phone":"+1 919 496 2219",
    "sg:postcode":"27549",
    "sg:province":"NC",
    "sg:tags":[
        "pathologist",
        "speech"
    ],
    "wof:name":"Tar River Speech & Language",
    "wof:placetype":"venue"
},
  "geometry": {"coordinates":[-78.28903099999999,36.016472],"type":"Point"}
}