{
  "type": "Feature",
  "properties": {
    "addr:full":"164 Shenstone Ln Garner NC 27592",
    "addr:housenumber":"164",
    "addr:postcode":"27592",
    "addr:street":"Shenstone Ln",
    "iso:country":"US",
    "sg:address":"164 Shenstone Ln",
    "sg:city":"Garner",
    "sg:classifiers":[
        {
            "category":"Restaurant",
            "type":"Food & Drink"
        }
    ],
    "sg:phone":"+1 919 773 4545",
    "sg:postcode":"27592",
    "sg:province":"NC",
    "sg:tags":[
        "parlor",
        "ice",
        "cream"
    ],
    "sg:website":"www.coldstonecreamery.com",
    "wof:name":"Cold Stone Creamery",
    "wof:placetype":"venue"
},
  "geometry": {"coordinates":[-78.592889,35.565303],"type":"Point"}
}