{
  "type": "Feature",
  "properties": {
    "addr:full":"207 E Bodenhamer St Kernersville NC 27284",
    "addr:housenumber":"207",
    "addr:postcode":"27284",
    "addr:street":"E Bodenhamer St",
    "iso:country":"US",
    "sg:address":"207 E Bodenhamer St",
    "sg:city":"Kernersville",
    "sg:classifiers":[
        {
            "category":"Insurance",
            "subcategory":"Hazard Insurance",
            "type":"Services"
        }
    ],
    "sg:phone":"+1 336 993 3560",
    "sg:postcode":"27284",
    "sg:province":"NC",
    "sg:tags":[
        "bond"
    ],
    "wof:name":"Anytime Bonding",
    "wof:placetype":"venue"
},
  "geometry": {"coordinates":[-80.069158,36.120542],"type":"Point"}
}