{
  "type": "Feature",
  "properties": {
    "iso:country":"US",
    "sg:address":"5723 University Pkwy",
    "sg:city":"Winston Salem",
    "sg:classifiers":[
        {
            "category":"Restaurant",
            "type":"Food & Drink"
        }
    ],
    "sg:phone":"+1 336 744 3338",
    "sg:postcode":"27105",
    "sg:province":"NC",
    "wof:name":"New China",
    "wof:placetype":"venue"
},
  "geometry": {"coordinates":[-80.275565,36.177556],"type":"Point"}
}