{
  "type": "Feature",
  "properties": {
    "addr:full":"755 McCarthy Blvd New Bern NC 28562",
    "addr:housenumber":"755",
    "addr:postcode":"28562",
    "addr:street":"Mccarthy Blvd",
    "iso:country":"US",
    "sg:address":"755 McCarthy Blvd",
    "sg:city":"New Bern",
    "sg:classifiers":[
        {
            "category":"Shopping",
            "subcategory":"Pharmacy",
            "type":"Retail Goods"
        }
    ],
    "sg:phone":"+1 252 514 2900",
    "sg:postcode":"28562",
    "sg:province":"NC",
    "wof:name":"McCarthy Square Pharmacy LLC",
    "wof:placetype":"venue"
},
  "geometry": {"coordinates":[-77.098258,35.108798],"type":"Point"}
}