{
  "type": "Feature",
  "properties": {
    "iso:country":"US",
    "sg:address":"217 W Marion St",
    "sg:city":"Shelby",
    "sg:classifiers":[
        {
            "category":"Sports & Exercise",
            "subcategory":"Gym",
            "type":"Entertainment"
        }
    ],
    "sg:phone":"+1   ",
    "sg:postcode":"28150",
    "sg:province":"NC",
    "sg:tags":[
        "fitness",
        "physical",
        "facility"
    ],
    "wof:name":"Nautilus of Shelby",
    "wof:placetype":"venue"
},
  "geometry": {"coordinates":[-81.543498,35.292001],"type":"Point"}
}