{
  "type": "Feature",
  "properties": {
    "addr:full":"4212 Northside Dr Greensboro NC 27405",
    "addr:housenumber":"4212",
    "addr:postcode":"27405",
    "addr:street":"Northside Dr",
    "iso:country":"US",
    "sg:address":"4212 Northside Dr",
    "sg:city":"Greensboro",
    "sg:classifiers":[
        {
            "category":"Organizations",
            "subcategory":"Religious Organization",
            "type":"Services"
        }
    ],
    "sg:phone":"+1 336 852 1685",
    "sg:postcode":"27405",
    "sg:province":"NC",
    "sg:tags":[
        "church"
    ],
    "wof:name":"Faith Free Baptist Church",
    "wof:placetype":"venue"
},
  "geometry": {"coordinates":[-79.71292200000001,36.136762],"type":"Point"}
}