{
  "type": "Feature",
  "properties": {
    "iso:country":"US",
    "sg:address":"5950 Idlebrook Dr",
    "sg:city":"Charlotte",
    "sg:classifiers":[
        {
            "category":"Building & Trades",
            "subcategory":"Construction",
            "type":"Services"
        }
    ],
    "sg:phone":"+1 704 569 0334",
    "sg:postcode":"28212",
    "sg:province":"NC",
    "sg:tags":[
        "house"
    ],
    "wof:name":"Asian Home Improvement",
    "wof:placetype":"venue"
},
  "geometry": {"coordinates":[-80.732428,35.195232],"type":"Point"}
}