{
  "type": "Feature",
  "properties": {
    "iso:country":"US",
    "sg:address":"1374 Langley Rd",
    "sg:city":"Staley",
    "sg:classifiers":[
        {
            "category":"Building & Trades",
            "subcategory":"Construction",
            "type":"Services"
        }
    ],
    "sg:phone":"+1 336 622 2741",
    "sg:postcode":"27355",
    "sg:province":"NC",
    "sg:tags":[
        "restoration",
        "cleaning",
        "patio",
        "deck"
    ],
    "wof:name":"Coble's Pressure Washing",
    "wof:placetype":"venue"
},
  "geometry": {"coordinates":[-79.569525,35.781162],"type":"Point"}
}