{
  "type": "Feature",
  "properties": {
    "iso:country":"US",
    "sg:address":"125 W Marion St",
    "sg:city":"Shelby",
    "sg:classifiers":[
        {
            "category":"Shopping",
            "subcategory":"Bicycles & Sporting Goods",
            "type":"Retail Goods"
        }
    ],
    "sg:phone":"+1 704 484 0008",
    "sg:postcode":"28150",
    "sg:province":"NC",
    "wof:name":"Schanewolf's Cycle Sport",
    "wof:placetype":"venue"
},
  "geometry": {"coordinates":[-81.541748,35.29193],"type":"Point"}
}