{
  "type": "Feature",
  "properties": {
    "iso:country":"US",
    "sg:address":"3155 Potneck Rd",
    "sg:city":"Woodleaf",
    "sg:classifiers":[
        {
            "category":"Farming",
            "subcategory":"Livestock Farm",
            "type":"Manufacturing & Wholesale Goods"
        }
    ],
    "sg:phone":"+1 704 278 4803",
    "sg:postcode":"27054",
    "sg:province":"NC",
    "sg:tags":[
        "beef",
        "feedlot",
        "cattle"
    ],
    "wof:name":"Jerry Waller",
    "wof:placetype":"venue"
},
  "geometry": {"coordinates":[-80.571462,35.770599],"type":"Point"}
}