{
  "type": "Feature",
  "properties": {
    "addr:full":"3822 Statesville Ave Charlotte NC 28206",
    "addr:housenumber":"3822",
    "addr:postcode":"28206",
    "addr:street":"Statesville Ave",
    "iso:country":"US",
    "sg:address":"3822 Statesville Ave",
    "sg:city":"Charlotte",
    "sg:classifiers":[
        {
            "category":"Retail",
            "subcategory":"Repair Shop",
            "type":"Services"
        }
    ],
    "sg:phone":"+1 704 347 0023",
    "sg:postcode":"28206",
    "sg:province":"NC",
    "sg:tags":[
        "component",
        "sales",
        "hydraulic"
    ],
    "wof:name":"P M Actuators Inc",
    "wof:placetype":"venue"
},
  "geometry": {"coordinates":[-80.83707099999999,35.271366],"type":"Point"}
}