{
  "type": "Feature",
  "properties": {
    "iso:country":"US",
    "sg:address":"9010 Glenwater Dr Suite 105",
    "sg:city":"Charlotte",
    "sg:classifiers":[
        {
            "category":"Real Estate",
            "subcategory":"Real Estate Services",
            "type":"Services"
        },
        {
            "category":"Personal",
            "type":"Services"
        }
    ],
    "sg:phone":"+1 866 701 0886",
    "sg:postcode":"28262",
    "sg:province":"NC",
    "sg:tags":[
        "property",
        "management",
        "maintenance"
    ],
    "sg:website":"http://local.ingenio.com/Listings/Details.aspx?NUM=a%3a10311846%3a13%3a4859924%3a14%3a0%3a7",
    "wof:name":"Century 21 At the University",
    "wof:placetype":"venue"
},
  "geometry": {"coordinates":[-80.75191,35.314674],"type":"Point"}
}