{
  "type": "Feature",
  "properties": {
    "iso:country":"US",
    "sg:address":"2501 Montgomery Ct",
    "sg:city":"New Bern",
    "sg:classifiers":[
        {
            "category":"Shopping",
            "subcategory":"Used Merchandise",
            "type":"Retail Goods"
        }
    ],
    "sg:phone":"+1 252 635 1954",
    "sg:postcode":"28562",
    "sg:province":"NC",
    "sg:tags":[
        "antique"
    ],
    "wof:name":"Smith's Antiques",
    "wof:placetype":"venue"
},
  "geometry": {"coordinates":[-77.08113,35.099736],"type":"Point"}
}