{
  "type": "Feature",
  "properties": {
    "iso:country":"US",
    "sg:address":"1528 S Miami Blvd",
    "sg:city":"Durham",
    "sg:classifiers":[
        {
            "category":"Personal",
            "subcategory":"Beauty Salon",
            "type":"Services"
        }
    ],
    "sg:phone":"+1 919 957 4516",
    "sg:postcode":"27703",
    "sg:province":"NC",
    "wof:name":"African House Of Braids",
    "wof:placetype":"venue"
},
  "geometry": {"coordinates":[-78.83886099999999,35.951623],"type":"Point"}
}