{
  "type": "Feature",
  "properties": {
    "iso:country":"US",
    "sg:address":"2087 Eldridge Rd",
    "sg:city":"Newton Grove",
    "sg:classifiers":[
        {
            "category":"Organizations",
            "subcategory":"Community Association",
            "type":"Services"
        }
    ],
    "sg:phone":"+1   ",
    "sg:postcode":"28366",
    "sg:province":"NC",
    "wof:name":"North Carolina State Gran",
    "wof:placetype":"venue"
},
  "geometry": {"coordinates":[-78.408461,35.2788],"type":"Point"}
}