{
  "type": "Feature",
  "properties": {
    "addr:full":"336 I- 40 Access Rd SE Hickory NC 28602",
    "addr:housenumber":"336;40",
    "addr:postcode":"28602",
    "addr:street":"I;Access Rd Se",
    "iso:country":"US",
    "sg:address":"336 I- 40 Access Rd SE",
    "sg:city":"Hickory",
    "sg:classifiers":[
        {
            "category":"Autos & Motor Vehicles",
            "subcategory":"Automobile Sales",
            "type":"Retail Goods"
        }
    ],
    "sg:phone":"+1 828 397 2666",
    "sg:postcode":"28602",
    "sg:province":"NC",
    "sg:tags":[
        "used"
    ],
    "wof:name":"Competition Auto Sales",
    "wof:placetype":"venue"
},
  "geometry": {"coordinates":[-81.41680700000001,35.708109],"type":"Point"}
}