{
  "type": "Feature",
  "properties": {
    "addr:full":"3723 High Point Rd Greensboro NC 27407",
    "addr:housenumber":"3723",
    "addr:postcode":"27407",
    "addr:street":"High Point Rd",
    "iso:country":"US",
    "sg:address":"3723 High Point Rd",
    "sg:city":"Greensboro",
    "sg:classifiers":[
        {
            "category":"Cinema",
            "subcategory":"Movie Rental",
            "type":"Entertainment"
        }
    ],
    "sg:phone":"+1 336 851 9934",
    "sg:postcode":"27407",
    "sg:province":"NC",
    "sg:tags":[
        "video",
        "tape"
    ],
    "wof:name":"Hollywood Video",
    "wof:placetype":"venue"
},
  "geometry": {"coordinates":[-79.854148,36.038573],"type":"Point"}
}