{
  "type": "Feature",
  "properties": {
    "iso:country":"US",
    "sg:address":"6027 Stitt St",
    "sg:city":"Monroe",
    "sg:classifiers":[
        {
            "category":"Wholesale",
            "subcategory":"Machinery & Supplies",
            "type":"Manufacturing & Wholesale Goods"
        }
    ],
    "sg:phone":"+1 704 283 4667",
    "sg:postcode":"28110",
    "sg:province":"NC",
    "sg:tags":[
        "beauty"
    ],
    "wof:name":"Lucas International",
    "wof:placetype":"venue"
},
  "geometry": {"coordinates":[-80.486394,34.984378],"type":"Point"}
}