{
  "type": "Feature",
  "properties": {
    "addr:full":"1473 Henley Rd Sanford NC 27330",
    "addr:housenumber":"1473",
    "addr:postcode":"27330",
    "addr:street":"Henley Rd",
    "iso:country":"US",
    "sg:address":"1473 Henley Rd",
    "sg:city":"Sanford",
    "sg:classifiers":[
        {
            "category":"Building & Trades",
            "subcategory":"Electrical",
            "type":"Services"
        }
    ],
    "sg:phone":"+1 919 775 2307",
    "sg:postcode":"27330",
    "sg:province":"NC",
    "sg:tags":[
        "electric",
        "contractor"
    ],
    "wof:name":"Mace Electric Co Inc",
    "wof:placetype":"venue"
},
  "geometry": {"coordinates":[-79.24918099999999,35.441499],"type":"Point"}
}