{
  "type": "Feature",
  "properties": {
    "addr:full":"116 S Sterling St Morganton NC 28655",
    "addr:housenumber":"116",
    "addr:postcode":"28655",
    "addr:street":"S Sterling St",
    "iso:country":"US",
    "sg:address":"116 S Sterling St",
    "sg:city":"Morganton",
    "sg:classifiers":[
        {
            "category":"Professional",
            "subcategory":"Lawyer & Legal Services",
            "type":"Services"
        }
    ],
    "sg:phone":"+1 828 438 9098",
    "sg:postcode":"28655",
    "sg:province":"NC",
    "sg:tags":[
        "attorney"
    ],
    "wof:name":"John W Alexander",
    "wof:placetype":"venue"
},
  "geometry": {"coordinates":[-81.686863,35.74464],"type":"Point"}
}