{
  "type": "Feature",
  "properties": {
    "addr:full":"6608 Six Forks Rd Raleigh NC 27615",
    "addr:housenumber":"6608",
    "addr:postcode":"27615",
    "addr:street":"Six Forks Rd",
    "iso:country":"US",
    "sg:address":"6608 Six Forks Rd",
    "sg:city":"Raleigh",
    "sg:classifiers":[
        {
            "category":"Professional",
            "subcategory":"Management & Consulting",
            "type":"Services"
        }
    ],
    "sg:phone":"+1 919 845 8450",
    "sg:postcode":"27615",
    "sg:province":"NC",
    "sg:tags":[
        "conference",
        "consultant",
        "meeting"
    ],
    "wof:name":"PFS Corp",
    "wof:placetype":"venue"
},
  "geometry": {"coordinates":[-78.641442,35.871306],"type":"Point"}
}