{
  "type": "Feature",
  "properties": {
    "addr:full":"4672 First Flight Dr Charlotte NC 28208",
    "addr:housenumber":"4672",
    "addr:postcode":"28208",
    "addr:street":"First Flight Dr",
    "iso:country":"US",
    "sg:address":"4672 First Flight Dr",
    "sg:city":"Charlotte",
    "sg:classifiers":[
        {
            "category":"Professional",
            "type":"Services"
        }
    ],
    "sg:phone":"+1 704 359 0075",
    "sg:postcode":"28208",
    "sg:province":"NC",
    "sg:tags":[
        "establishment"
    ],
    "wof:name":"Westport Corp",
    "wof:placetype":"venue"
},
  "geometry": {"coordinates":[-80.929176,35.220389],"type":"Point"}
}