{
  "type": "Feature",
  "properties": {
    "iso:country":"US",
    "sg:address":"6021 Rock Creek Rd NE",
    "sg:city":"Leland",
    "sg:phone":"+1 910 253 6623",
    "sg:postcode":"28451",
    "sg:province":"NC",
    "sg:tags":[
        "farm",
        "tobacco"
    ],
    "wof:name":"Donald Padgett",
    "wof:placetype":"venue"
},
  "geometry": {"coordinates":[-78.11327300000001,34.170693],"type":"Point"}
}