{
  "type": "Feature",
  "properties": {
    "addr:full":"350 Depot St Franklin NC 28734",
    "addr:housenumber":"350",
    "addr:postcode":"nc 28734",
    "addr:street":"Depot St",
    "iso:country":"US",
    "sg:address":"350 Depot St",
    "sg:city":"Franklin",
    "sg:classifiers":[
        {
            "category":"Building & Trades",
            "subcategory":"Plumbing",
            "type":"Services"
        }
    ],
    "sg:phone":"+1 828 349 0504",
    "sg:postcode":"28734",
    "sg:province":"NC",
    "sg:tags":[
        "plumbing",
        "contractor"
    ],
    "wof:name":"Choice Plumbing",
    "wof:placetype":"venue"
},
  "geometry": {"coordinates":[-83.373408,35.176339],"type":"Point"}
}