{
  "type": "Feature",
  "properties": {
    "iso:country":"US",
    "sg:address":"5717 Country Club Rd",
    "sg:city":"Winston Salem",
    "sg:classifiers":[
        {
            "category":"Retail",
            "subcategory":"Auto Repair",
            "type":"Services"
        }
    ],
    "sg:phone":"+1 336 945 4120",
    "sg:postcode":"27104",
    "sg:province":"NC",
    "sg:tags":[
        "body",
        "automobile",
        "painting"
    ],
    "wof:name":"Don's Body Shop",
    "wof:placetype":"venue"
},
  "geometry": {"coordinates":[-80.375899,36.093673],"type":"Point"}
}