{
  "type": "Feature",
  "properties": {
    "iso:country":"US",
    "sg:address":"4132 Lisbon Rd",
    "sg:city":"Council",
    "sg:classifiers":[
        {
            "category":"Farming",
            "subcategory":"Farm",
            "type":"Manufacturing & Wholesale Goods"
        }
    ],
    "sg:phone":"+1 910 645 6697",
    "sg:postcode":"28434",
    "sg:province":"NC",
    "wof:name":"J B Priest Jr Farms",
    "wof:placetype":"venue"
},
  "geometry": {"coordinates":[-78.518818,34.516754],"type":"Point"}
}