{
  "type": "Feature",
  "properties": {
    "addr:full":"4710 Rudd Rd Greensboro NC 27405",
    "addr:housenumber":"4710",
    "addr:postcode":"27405",
    "addr:street":"Rudd Rd",
    "iso:country":"US",
    "sg:address":"4710 Rudd Rd",
    "sg:city":"Greensboro",
    "sg:classifiers":[
        {
            "category":"Building & Trades",
            "subcategory":"Cleaning & Sanitation",
            "type":"Services"
        }
    ],
    "sg:phone":"+1 336 669 5224",
    "sg:postcode":"27405",
    "sg:province":"NC",
    "sg:tags":[
        "janitor"
    ],
    "wof:name":"Crystal Clean Homes",
    "wof:placetype":"venue"
},
  "geometry": {"coordinates":[-79.751653,36.141183],"type":"Point"}
}