{
  "type": "Feature",
  "properties": {
    "addr:full":"10115 Kincey Ave Huntersville NC 28078",
    "addr:housenumber":"10115",
    "addr:postcode":"28078",
    "addr:street":"Kincey Ave",
    "iso:country":"US",
    "sg:address":"10115 Kincey Ave",
    "sg:city":"Huntersville",
    "sg:classifiers":[
        {
            "category":"Real Estate",
            "subcategory":"Real Estate Services",
            "type":"Services"
        },
        {
            "category":"Insurance",
            "subcategory":"Title Insurance",
            "type":"Services"
        },
        {
            "category":"Banks & Credit Unions",
            "subcategory":"Financial Services",
            "type":"Services"
        }
    ],
    "sg:phone":"+1 704 947 3755",
    "sg:postcode":"28078",
    "sg:province":"NC",
    "sg:tags":[
        "escrow"
    ],
    "wof:name":"Stewart Title Co",
    "wof:placetype":"venue"
},
  "geometry": {"coordinates":[-80.859008,35.401514],"type":"Point"}
}