{
  "type": "Feature",
  "properties": {
    "addr:full":"2708 Wooten Blvd SW Wilson NC 27893",
    "addr:housenumber":"2708",
    "addr:postcode":"27893",
    "addr:street":"Wooten Blvd Sw",
    "iso:country":"US",
    "sg:address":"2708 Wooten Blvd SW",
    "sg:city":"Wilson",
    "sg:classifiers":[
        {
            "category":"Building & Trades",
            "subcategory":"Electrical",
            "type":"Services"
        }
    ],
    "sg:phone":"+1 252 291 1845",
    "sg:postcode":"27893",
    "sg:province":"NC",
    "sg:tags":[
        "electric",
        "contractor"
    ],
    "wof:name":"Guy Boswell Electric Co",
    "wof:placetype":"venue"
},
  "geometry": {"coordinates":[-77.954573,35.716616],"type":"Point"}
}