{
  "type": "Feature",
  "properties": {
    "iso:country":"US",
    "sg:address":"10940 Raven Ridge Rd",
    "sg:city":"Raleigh",
    "sg:classifiers":[
        {
            "category":"Personal",
            "subcategory":"Massage",
            "type":"Services"
        },
        {
            "category":"Personal",
            "subcategory":"Beauty Salon",
            "type":"Services"
        },
        {
            "category":"Personal",
            "subcategory":"Day Spa",
            "type":"Services"
        },
        {
            "category":"Personal",
            "subcategory":"Skin Care",
            "type":"Services"
        }
    ],
    "sg:phone":"+1 919 870 7009",
    "sg:postcode":"27614",
    "sg:province":"NC",
    "sg:tags":[
        "therapist",
        "cosmetologist"
    ],
    "sg:website":"http://www.tanashairdesigns.com",
    "wof:name":"Tanas Hair Designs And Day Spa",
    "wof:placetype":"venue"
},
  "geometry": {"coordinates":[-78.590827,35.905382],"type":"Point"}
}