{
  "type": "Feature",
  "properties": {
    "iso:country":"US",
    "sg:address":"139 E Main St",
    "sg:city":"Forest City",
    "sg:classifiers":[
        {
            "category":"Shopping",
            "subcategory":"Pharmacy",
            "type":"Retail Goods"
        },
        {
            "category":"Health Services",
            "subcategory":"Clinic",
            "type":"Services"
        }
    ],
    "sg:phone":"+1 828 245 4591",
    "sg:postcode":"28043",
    "sg:province":"NC",
    "sg:tags":[
        "home",
        "drug",
        "store"
    ],
    "sg:website":"www.smithdrugs.com",
    "wof:name":"Smith's Drugs Vital Care",
    "wof:placetype":"venue"
},
  "geometry": {"coordinates":[-81.86393,35.333592],"type":"Point"}
}