{
  "type": "Feature",
  "properties": {
    "iso:country":"US",
    "sg:address":"556 Boomer Ferguson School Rd",
    "sg:city":"Boomer",
    "sg:classifiers":[
        {
            "category":"Government",
            "subcategory":"Office",
            "type":"Public Place"
        }
    ],
    "sg:phone":"+1 336 921 7020",
    "sg:postcode":"28606",
    "sg:province":"NC",
    "wof:name":"Wilkes County Offices 4H",
    "wof:placetype":"venue"
},
  "geometry": {"coordinates":[-81.299183,36.10094],"type":"Point"}
}