{
  "type": "Feature",
  "properties": {
    "addr:full":"820 N College Rd Wilmington NC 28405",
    "addr:housenumber":"820",
    "addr:postcode":"28405",
    "addr:street":"N College Rd",
    "iso:country":"US",
    "sg:address":"820 N College Rd",
    "sg:city":"Wilmington",
    "sg:classifiers":[
        {
            "category":"Food & Beverages",
            "subcategory":"Groceries & Convenience Stores",
            "type":"Retail Goods"
        }
    ],
    "sg:phone":"+1 910 392 1360",
    "sg:postcode":"28405",
    "sg:province":"NC",
    "sg:tags":[
        "grocer"
    ],
    "wof:name":"Handy Hugo",
    "wof:placetype":"venue"
},
  "geometry": {"coordinates":[-77.870069,34.259485],"type":"Point"}
}