{
  "type": "Feature",
  "properties": {
    "iso:country":"US",
    "sg:address":"1124 Skeet Club Rd",
    "sg:city":"High Point",
    "sg:classifiers":[
        {
            "category":"Building & Trades",
            "subcategory":"Construction",
            "type":"Services"
        }
    ],
    "sg:phone":"+1 336 841 1036",
    "sg:postcode":"27265",
    "sg:province":"NC",
    "sg:tags":[
        "floor",
        "laying",
        "contractor"
    ],
    "wof:name":"Flooring Specialties Inc",
    "wof:placetype":"venue"
},
  "geometry": {"coordinates":[-80.001407,36.039119],"type":"Point"}
}