{
  "type": "Feature",
  "properties": {
    "iso:country":"US",
    "sg:address":"3505 Masonboro Ct",
    "sg:city":"Hope Mills",
    "sg:classifiers":[
        {
            "category":"Building & Trades",
            "subcategory":"Construction",
            "type":"Services"
        }
    ],
    "sg:phone":"+1 910 423 0439",
    "sg:postcode":"28348",
    "sg:province":"NC",
    "sg:tags":[
        "contractor"
    ],
    "wof:name":"Quinn Roofing",
    "wof:placetype":"venue"
},
  "geometry": {"coordinates":[-78.923883,34.994058],"type":"Point"}
}