{
  "type": "Feature",
  "properties": {
    "iso:country":"US",
    "sg:address":"11333 Longhedge Ln",
    "sg:city":"Charlotte",
    "sg:classifiers":[
        {
            "category":"Professional",
            "subcategory":"Business Services",
            "type":"Services"
        }
    ],
    "sg:phone":"+1   ",
    "sg:postcode":"28273",
    "sg:province":"NC",
    "wof:name":"Interiors By Chanel",
    "wof:placetype":"venue"
},
  "geometry": {"coordinates":[-80.96498699999999,35.108222],"type":"Point"}
}