{
  "type": "Feature",
  "properties": {
    "iso:country":"US",
    "sg:address":"7842 Leisure Ln",
    "sg:city":"Huntersville",
    "sg:classifiers":[
        {
            "category":"Freight",
            "type":"Transportation"
        }
    ],
    "sg:phone":"+1 704 948 7109",
    "sg:postcode":"28078",
    "sg:province":"NC",
    "sg:tags":[
        "operator",
        "trucking"
    ],
    "wof:name":"Lt Enterprises Usa LLC",
    "wof:placetype":"venue"
},
  "geometry": {"coordinates":[-80.908548,35.400657],"type":"Point"}
}