{
  "type": "Feature",
  "properties": {
    "addr:full":"102 E Washington St Mebane NC 27302",
    "addr:housenumber":"102",
    "addr:postcode":"27302",
    "addr:street":"E Washington St",
    "iso:country":"US",
    "sg:address":"102 E Washington St",
    "sg:city":"Mebane",
    "sg:classifiers":[
        {
            "category":"Home & Garden",
            "subcategory":"Building Materials",
            "type":"Retail Goods"
        }
    ],
    "sg:phone":"+1 919 304 2149",
    "sg:postcode":"27302",
    "sg:province":"NC",
    "sg:tags":[
        "door"
    ],
    "wof:name":"Builders Door Svc",
    "wof:placetype":"venue"
},
  "geometry": {"coordinates":[-79.268084,36.095869],"type":"Point"}
}