{
  "type": "Feature",
  "properties": {
    "iso:country":"US",
    "sg:address":"2325 Stantonsburg Rd",
    "sg:city":"Greenville",
    "sg:classifiers":[
        {
            "category":"Health Services",
            "subcategory":"Doctor",
            "type":"Services"
        }
    ],
    "sg:phone":"+1 252 752 5156",
    "sg:postcode":"27834",
    "sg:province":"NC",
    "sg:tags":[
        "neurological",
        "surgeon"
    ],
    "wof:name":"Eastern Nrsurgical Spine Assoc",
    "wof:placetype":"venue"
},
  "geometry": {"coordinates":[-77.411384,35.605019],"type":"Point"}
}