{
  "type": "Feature",
  "properties": {
    "addr:full":"322 Cedar Fork Rd Beulaville NC 28518",
    "addr:housenumber":"322",
    "addr:postcode":"28518",
    "addr:street":"Cedar Fork Rd",
    "iso:country":"US",
    "sg:address":"322 Cedar Fork Rd",
    "sg:city":"Beulaville",
    "sg:classifiers":[
        {
            "category":"Shopping",
            "subcategory":"Bicycles & Sporting Goods",
            "type":"Retail Goods"
        }
    ],
    "sg:phone":"+1 910 324 1275",
    "sg:postcode":"28518",
    "sg:province":"NC",
    "wof:name":"Eastern Outfitters Inc",
    "wof:placetype":"venue"
},
  "geometry": {"coordinates":[-77.639466,34.847475],"type":"Point"}
}