{
  "type": "Feature",
  "properties": {
    "iso:country":"US",
    "sg:address":"116 Byron Pl",
    "sg:city":"Raleigh",
    "sg:classifiers":[
        {
            "category":"Professional",
            "type":"Services"
        }
    ],
    "sg:phone":"+1 919 781 9997",
    "sg:postcode":"27609",
    "sg:province":"NC",
    "wof:name":"Bruns Pak Worldwide Inc",
    "wof:placetype":"venue"
},
  "geometry": {"coordinates":[-78.634379,35.824727],"type":"Point"}
}