{
  "type": "Feature",
  "properties": {
    "addr:full":"514 Alston St Raleigh NC 27601",
    "addr:housenumber":"514",
    "addr:postcode":"27601",
    "addr:street":"Alston St",
    "iso:country":"US",
    "sg:address":"514 Alston St",
    "sg:city":"Raleigh",
    "sg:classifiers":[
        {
            "category":"Freight",
            "type":"Transportation"
        }
    ],
    "sg:phone":"+1 919 395 3113",
    "sg:postcode":"27601",
    "sg:province":"NC",
    "sg:tags":[
        "local",
        "storage",
        "trucking"
    ],
    "wof:name":"Thomas C Williams",
    "wof:placetype":"venue"
},
  "geometry": {"coordinates":[-78.627309,35.772834],"type":"Point"}
}