{
  "type": "Feature",
  "properties": {
    "addr:full":"225 Brown's Mountain Rd Scaly Mountain NC 28775",
    "addr:housenumber":"225",
    "addr:postcode":"28775",
    "addr:street":"Brown'S Mountain Rd",
    "iso:country":"US",
    "sg:address":"225 Brown's Mountain Rd",
    "sg:city":"Scaly Mountain",
    "sg:classifiers":[
        {
            "category":"Farming",
            "subcategory":"Farm",
            "type":"Manufacturing & Wholesale Goods"
        }
    ],
    "sg:phone":"+1 828 526 3185",
    "sg:postcode":"28775",
    "sg:province":"NC",
    "wof:name":"James Farms Nursery",
    "wof:placetype":"venue"
},
  "geometry": {"coordinates":[-83.315208,35.015094],"type":"Point"}
}