{
  "type": "Feature",
  "properties": {
    "iso:country":"US",
    "sg:address":"154 S Main St",
    "sg:city":"Troutman",
    "sg:classifiers":[
        {
            "category":"Insurance",
            "subcategory":"Insurance Agent",
            "type":"Services"
        }
    ],
    "sg:phone":"+1 704 528 4141",
    "sg:postcode":"28166",
    "sg:province":"NC",
    "wof:name":"Carney & Co Insurance Svc Inc",
    "wof:placetype":"venue"
},
  "geometry": {"coordinates":[-80.887806,35.70121],"type":"Point"}
}