{
  "type": "Feature",
  "properties": {
    "addr:full":"3300 Octavia St Raleigh NC 27606",
    "addr:housenumber":"3300",
    "addr:postcode":"27606",
    "addr:street":"Octavia St",
    "iso:country":"US",
    "sg:address":"3300 Octavia St",
    "sg:city":"Raleigh",
    "sg:classifiers":[
        {
            "category":"Professional",
            "subcategory":"Computer Services",
            "type":"Services"
        }
    ],
    "sg:phone":"+1 919 233 6601",
    "sg:postcode":"27606",
    "sg:province":"NC",
    "sg:tags":[
        "web",
        "design",
        "page"
    ],
    "wof:name":"Pageplan Inc",
    "wof:placetype":"venue"
},
  "geometry": {"coordinates":[-78.694293,35.769571],"type":"Point"}
}