{
  "type": "Feature",
  "properties": {
    "addr:full":"214 McCauley St Chapel Hill NC 27516",
    "addr:housenumber":"214",
    "addr:postcode":"27516",
    "addr:street":"Mccauley St",
    "iso:country":"US",
    "sg:address":"214 McCauley St",
    "sg:city":"Chapel Hill",
    "sg:classifiers":[
        {
            "category":"Health Services",
            "subcategory":"Health Practitioner",
            "type":"Services"
        }
    ],
    "sg:phone":"+1   ",
    "sg:postcode":"27516",
    "sg:province":"NC",
    "wof:name":"Pat Webster",
    "wof:placetype":"venue"
},
  "geometry": {"coordinates":[-79.055024,35.908075],"type":"Point"}
}