{
  "type": "Feature",
  "properties": {
    "iso:country":"US",
    "sg:address":"4125 Pilley Ave",
    "sg:city":"Pantego",
    "sg:classifiers":[
        {
            "category":"Building & Trades",
            "subcategory":"Electrical",
            "type":"Services"
        }
    ],
    "sg:phone":"+1 252 943 3540",
    "sg:postcode":"27860",
    "sg:province":"NC",
    "sg:tags":[
        "electric",
        "contractor"
    ],
    "wof:name":"Gibbs Electric Inc",
    "wof:placetype":"venue"
},
  "geometry": {"coordinates":[-76.75196,35.606521],"type":"Point"}
}