{
  "type": "Feature",
  "properties": {
    "addr:full":"6417 Mal Weathers Rd Raleigh NC 27603",
    "addr:housenumber":"6417",
    "addr:postcode":"27603",
    "addr:street":"Mal Weathers Rd",
    "iso:country":"US",
    "sg:address":"6417 Mal Weathers Rd",
    "sg:city":"Raleigh",
    "sg:classifiers":[
        {
            "category":"Professional",
            "type":"Services"
        }
    ],
    "sg:phone":"+1   ",
    "sg:postcode":"27603",
    "sg:province":"NC",
    "wof:name":"Concord Home Services",
    "wof:placetype":"venue"
},
  "geometry": {"coordinates":[-78.642385,35.602341],"type":"Point"}
}