{
  "type": "Feature",
  "properties": {
    "iso:country":"US",
    "sg:address":"2608 US Hwy 70",
    "sg:city":"Mebane",
    "sg:classifiers":[
        {
            "category":"Home & Garden",
            "subcategory":"Building Materials",
            "type":"Retail Goods"
        }
    ],
    "sg:phone":"+1 919 304 4500",
    "sg:postcode":"27302",
    "sg:province":"NC",
    "sg:tags":[
        "glass",
        "window",
        "plate"
    ],
    "wof:name":"Auto Glass Assoc",
    "wof:placetype":"venue"
},
  "geometry": {"coordinates":[-79.30196599999999,36.099017],"type":"Point"}
}