{
  "type": "Feature",
  "properties": {
    "addr:full":"6 Elysinia Ave Waynesville NC 28786",
    "addr:housenumber":"6",
    "addr:postcode":"28786",
    "addr:street":"Elysinia Ave",
    "iso:country":"US",
    "sg:address":"6 Elysinia Ave",
    "sg:city":"Waynesville",
    "sg:classifiers":[
        {
            "category":"Organizations",
            "subcategory":"Membership Organization",
            "type":"Services"
        },
        {
            "category":"Health Services",
            "subcategory":"Clinic",
            "type":"Services"
        }
    ],
    "sg:phone":"+1 828 456 7930",
    "sg:postcode":"28786",
    "sg:province":"NC",
    "sg:tags":[
        "profit",
        "home"
    ],
    "wof:name":"No Boundaries Intergrated Serv",
    "wof:placetype":"venue"
},
  "geometry": {"coordinates":[-83.00648099999999,35.480665],"type":"Point"}
}