{
  "type": "Feature",
  "properties": {
    "iso:country":"US",
    "sg:address":"2887 Mack Ballard Rd",
    "sg:city":"Denver",
    "sg:classifiers":[
        {
            "category":"Building & Trades",
            "subcategory":"Electrical",
            "type":"Services"
        }
    ],
    "sg:phone":"+1 704 483 8546",
    "sg:postcode":"28037",
    "sg:province":"NC",
    "sg:tags":[
        "electrical",
        "contractor"
    ],
    "wof:name":"Perkins Electric Co",
    "wof:placetype":"venue"
},
  "geometry": {"coordinates":[-81.09007200000001,35.522919],"type":"Point"}
}