{
  "type": "Feature",
  "properties": {
    "addr:full":"7852 Rea Rd Charlotte NC 28277",
    "addr:housenumber":"7852",
    "addr:postcode":"28277",
    "addr:street":"Rea Rd",
    "iso:country":"US",
    "sg:address":"7852 Rea Rd",
    "sg:city":"Charlotte",
    "sg:classifiers":[
        {
            "category":"Shopping",
            "subcategory":"Tobacco",
            "type":"Retail Goods"
        },
        {
            "category":"Manufacturing",
            "subcategory":"Paper Products",
            "type":"Manufacturing & Wholesale Goods"
        }
    ],
    "sg:phone":"+1 704 541 0034",
    "sg:postcode":"28277",
    "sg:province":"NC",
    "sg:tags":[
        "cigarette",
        "mill",
        "cigar",
        "machinery"
    ],
    "sg:website":"http://www.tinderboxcigars.com",
    "wof:name":"Tinder Box",
    "wof:placetype":"venue"
},
  "geometry": {"coordinates":[-80.813468,35.06074],"type":"Point"}
}