{
  "type": "Feature",
  "properties": {
    "addr:full":"2664 Dilworth Heights Ln Charlotte NC 28209",
    "addr:housenumber":"2664",
    "addr:postcode":"28209",
    "addr:street":"Dilworth Heights Ln",
    "iso:country":"US",
    "sg:address":"2664 Dilworth Heights Ln",
    "sg:city":"Charlotte",
    "sg:classifiers":[
        {
            "category":"Building & Trades",
            "subcategory":"Electrical",
            "type":"Services"
        }
    ],
    "sg:phone":"+1 704 376 0710",
    "sg:postcode":"28209",
    "sg:province":"NC",
    "sg:tags":[
        "electrical",
        "contractor"
    ],
    "wof:name":"Electric Lash LLC",
    "wof:placetype":"venue"
},
  "geometry": {"coordinates":[-80.850683,35.194959],"type":"Point"}
}