{
  "type": "Feature",
  "properties": {
    "iso:country":"US",
    "sg:address":"145 N Walnut St",
    "sg:city":"Pinebluff",
    "sg:classifiers":[
        {
            "category":"Autos & Motor Vehicles",
            "subcategory":"Automobile Sales",
            "type":"Retail Goods"
        }
    ],
    "sg:phone":"+1 910 281 0766",
    "sg:postcode":"28373",
    "sg:province":"NC",
    "sg:tags":[
        "used"
    ],
    "wof:name":"Jh Auto Sales",
    "wof:placetype":"venue"
},
  "geometry": {"coordinates":[-79.472312,35.109266],"type":"Point"}
}