{
  "type": "Feature",
  "properties": {
    "iso:country":"US",
    "sg:address":"16745 Old Beatty Ford Rd",
    "sg:city":"Gold Hill",
    "sg:classifiers":[
        {
            "category":"Mining & Drilling",
            "type":"Manufacturing & Wholesale Goods"
        }
    ],
    "sg:phone":"+1 704 279 5566",
    "sg:postcode":"28071",
    "sg:province":"NC",
    "sg:tags":[
        "stone"
    ],
    "wof:name":"Vulcan Materials Co",
    "wof:placetype":"venue"
},
  "geometry": {"coordinates":[-80.324907,35.507241],"type":"Point"}
}