{
  "type": "Feature",
  "properties": {
    "addr:full":"14216 Wyndfield Cir Raleigh NC 27615",
    "addr:postcode":"14216;27615",
    "addr:street":"Wyndfield Cir",
    "iso:country":"US",
    "sg:address":"14216 Wyndfield Cir",
    "sg:city":"Raleigh",
    "sg:classifiers":[
        {
            "category":"Professional",
            "type":"Services"
        }
    ],
    "sg:phone":"+1 919 870 6612",
    "sg:postcode":"27615",
    "sg:province":"NC",
    "wof:name":"Susan M Peddycord",
    "wof:placetype":"venue"
},
  "geometry": {"coordinates":[-78.655872,35.921984],"type":"Point"}
}