{
  "type": "Feature",
  "properties": {
    "iso:country":"US",
    "sg:address":"3801 Wake Forest Hwy",
    "sg:city":"Durham",
    "sg:classifiers":[
        {
            "category":"Shopping",
            "subcategory":"Florist",
            "type":"Retail Goods"
        }
    ],
    "sg:phone":"+1 919 957 3633",
    "sg:postcode":"27703",
    "sg:province":"NC",
    "wof:name":"Chandlers Flowers",
    "wof:placetype":"venue"
},
  "geometry": {"coordinates":[-78.816469,35.98034],"type":"Point"}
}