{
  "type": "Feature",
  "properties": {
    "addr:full":"2803 McConnell Rd Greensboro NC 27401",
    "addr:housenumber":"2803",
    "addr:postcode":"27401",
    "addr:street":"Mcconnell Rd",
    "iso:country":"US",
    "sg:address":"2803 McConnell Rd",
    "sg:city":"Greensboro",
    "sg:classifiers":[
        {
            "category":"Building & Trades",
            "subcategory":"Plumbing",
            "type":"Services"
        }
    ],
    "sg:phone":"+1 336 578 6140",
    "sg:postcode":"27401",
    "sg:province":"NC",
    "sg:tags":[
        "plumbing",
        "contractor"
    ],
    "wof:name":"T W Stanley & Son Pump Well",
    "wof:placetype":"venue"
},
  "geometry": {"coordinates":[-79.746391,36.063572],"type":"Point"}
}