{
  "type": "Feature",
  "properties": {
    "iso:country":"US",
    "sg:address":"335 S White St",
    "sg:city":"Wake Forest",
    "sg:classifiers":[
        {
            "category":"Building & Trades",
            "subcategory":"Construction",
            "type":"Services"
        }
    ],
    "sg:phone":"+1 919 556 4300",
    "sg:postcode":"27587",
    "sg:province":"NC",
    "sg:tags":[
        "contractor"
    ],
    "sg:website":"www.bannermanandcompany.com",
    "wof:name":"Bannerman & Co",
    "wof:placetype":"venue"
},
  "geometry": {"coordinates":[-78.510327,35.975979],"type":"Point"}
}