{
  "type": "Feature",
  "properties": {
    "iso:country":"US",
    "sg:address":"1205 Gunnison Pl",
    "sg:city":"Raleigh",
    "sg:classifiers":[
        {
            "category":"Restaurant",
            "type":"Food & Drink"
        }
    ],
    "sg:phone":"+1 919 349 7762",
    "sg:postcode":"27609",
    "sg:province":"NC",
    "sg:tags":[
        "eating"
    ],
    "wof:name":"Menu By Mark",
    "wof:placetype":"venue"
},
  "geometry": {"coordinates":[-78.657636,35.847731],"type":"Point"}
}