{
  "type": "Feature",
  "properties": {
    "iso:country":"US",
    "sg:address":"201 N Church St",
    "sg:city":"Mooresville",
    "sg:classifiers":[
        {
            "category":"Wholesale",
            "subcategory":"Machinery & Supplies",
            "type":"Manufacturing & Wholesale Goods"
        },
        {
            "category":"Home & Garden",
            "subcategory":"Hardware",
            "type":"Retail Goods"
        }
    ],
    "sg:phone":"+1 704 663 5257",
    "sg:postcode":"28115",
    "sg:province":"NC",
    "sg:tags":[
        "pump"
    ],
    "wof:name":"Hydro-Corp Inc",
    "wof:placetype":"venue"
},
  "geometry": {"coordinates":[-80.807569,35.584577],"type":"Point"}
}