{
  "type": "Feature",
  "properties": {
    "iso:country":"US",
    "sg:address":"3308 Archdale Rd",
    "sg:city":"Archdale",
    "sg:classifiers":[
        {
            "category":"Personal",
            "subcategory":"Beauty Salon",
            "type":"Services"
        }
    ],
    "sg:phone":"+1 336 431 6445",
    "sg:postcode":"27263",
    "sg:province":"NC",
    "wof:name":"Linda's Beauty & Tanning Salon",
    "wof:placetype":"venue"
},
  "geometry": {"coordinates":[-79.977951,35.915609],"type":"Point"}
}