{
  "type": "Feature",
  "properties": {
    "iso:country":"US",
    "sg:address":"2107 Thrift Rd",
    "sg:city":"Charlotte",
    "sg:classifiers":[
        {
            "category":"Wholesale",
            "subcategory":"Stationery",
            "type":"Manufacturing & Wholesale Goods"
        }
    ],
    "sg:phone":"+1 704 333 4188",
    "sg:postcode":"28208",
    "sg:province":"NC",
    "sg:tags":[
        "converter",
        "broker",
        "paper",
        "representative",
        "mill",
        "manufacturer"
    ],
    "wof:name":"Anchor Paper Corporation",
    "wof:placetype":"venue"
},
  "geometry": {"coordinates":[-80.872163,35.232696],"type":"Point"}
}