{
  "type": "Feature",
  "properties": {
    "addr:full":"3570 Faith Rd Salisbury NC 28146",
    "addr:housenumber":"3570",
    "addr:postcode":"28146",
    "addr:street":"Faith Rd",
    "iso:country":"US",
    "sg:address":"3570 Faith Rd",
    "sg:city":"Salisbury",
    "sg:classifiers":[
        {
            "category":"Shopping",
            "subcategory":"Bicycles & Sporting Goods",
            "type":"Retail Goods"
        }
    ],
    "sg:phone":"+1 704 279 2814",
    "sg:postcode":"28146",
    "sg:province":"NC",
    "wof:name":"T DS Rloading Components Guns",
    "wof:placetype":"venue"
},
  "geometry": {"coordinates":[-80.46444,35.596977],"type":"Point"}
}