{
  "type": "Feature",
  "properties": {
    "addr:full":"1060 Shoreline Dr Stanley NC 28164",
    "addr:housenumber":"1060",
    "addr:postcode":"28164",
    "addr:street":"Shoreline Dr",
    "iso:country":"US",
    "sg:address":"1060 Shoreline Dr",
    "sg:city":"Stanley",
    "sg:classifiers":[
        {
            "category":"Building & Trades",
            "subcategory":"Construction",
            "type":"Services"
        }
    ],
    "sg:phone":"+1 704 827 7456",
    "sg:postcode":"28164",
    "sg:province":"NC",
    "sg:tags":[
        "house"
    ],
    "wof:name":"Devonshire Construction Inc",
    "wof:placetype":"venue"
},
  "geometry": {"coordinates":[-80.961843,35.44694],"type":"Point"}
}