{
  "type": "Feature",
  "properties": {
    "iso:country":"US",
    "sg:address":"1059 N Moore Rd",
    "sg:city":"Robbins",
    "sg:classifiers":[
        {
            "category":"Shopping",
            "type":"Retail Goods"
        }
    ],
    "sg:phone":"+1 910 464 3397",
    "sg:postcode":"27325",
    "sg:province":"NC",
    "sg:tags":[
        "merchandise"
    ],
    "wof:name":"Purvis Cabinet Shop",
    "wof:placetype":"venue"
},
  "geometry": {"coordinates":[-79.545337,35.476669],"type":"Point"}
}