{
  "type": "Feature",
  "properties": {
    "addr:full":"111 W Main St Benson NC 27504",
    "addr:housenumber":"111",
    "addr:postcode":"27504",
    "addr:street":"W Main St",
    "iso:country":"US",
    "sg:address":"111 W Main St",
    "sg:city":"Benson",
    "sg:classifiers":[
        {
            "category":"Insurance",
            "subcategory":"Insurance Agent",
            "type":"Services"
        }
    ],
    "sg:phone":"+1 919 894 2077",
    "sg:postcode":"27504",
    "sg:province":"NC",
    "wof:name":"Jeff Stephenson Insurance",
    "wof:placetype":"venue"
},
  "geometry": {"coordinates":[-78.54796399999999,35.381429],"type":"Point"}
}