{
  "type": "Feature",
  "properties": {
    "addr:full":"140 Strawberry Ln Jacksonville NC 28540",
    "addr:housenumber":"140",
    "addr:postcode":"28540",
    "addr:street":"Strawberry Ln",
    "iso:country":"US",
    "sg:address":"140 Strawberry Ln",
    "sg:city":"Jacksonville",
    "sg:classifiers":[
        {
            "category":"Building & Trades",
            "subcategory":"Construction",
            "type":"Services"
        }
    ],
    "sg:phone":"+1 910 347 2208",
    "sg:postcode":"28540",
    "sg:province":"NC",
    "sg:tags":[
        "contractor"
    ],
    "wof:name":"Stephenson Building Co",
    "wof:placetype":"venue"
},
  "geometry": {"coordinates":[-77.498003,34.692794],"type":"Point"}
}