{
  "type": "Feature",
  "properties": {
    "addr:full":"1000 Hood St SW Wilson NC 27893",
    "addr:housenumber":"1000",
    "addr:postcode":"27893",
    "addr:street":"Hood St Sw",
    "iso:country":"US",
    "sg:address":"1000 Hood St SW",
    "sg:city":"Wilson",
    "sg:classifiers":[
        {
            "category":"Building & Trades",
            "subcategory":"Electrical",
            "type":"Services"
        }
    ],
    "sg:phone":"+1 252 237 6097",
    "sg:postcode":"27893",
    "sg:province":"NC",
    "sg:tags":[
        "electric",
        "contractor"
    ],
    "wof:name":"D/C Electrical Construction Co",
    "wof:placetype":"venue"
},
  "geometry": {"coordinates":[-77.92989799999999,35.710814],"type":"Point"}
}