{
  "type": "Feature",
  "properties": {
    "addr:full":"131 Becker Dr Roanoke Rapids NC 27870",
    "addr:housenumber":"131",
    "addr:postcode":"27870",
    "addr:street":"Becker Dr",
    "iso:country":"US",
    "sg:address":"131 Becker Dr",
    "sg:city":"Roanoke Rapids",
    "sg:classifiers":[
        {
            "category":"Food & Beverages",
            "subcategory":"Specialty",
            "type":"Retail Goods"
        }
    ],
    "sg:phone":"+1 252 535 3060",
    "sg:postcode":"27870",
    "sg:province":"NC",
    "wof:name":"GNC",
    "wof:placetype":"venue"
},
  "geometry": {"coordinates":[-77.640963,36.442597],"type":"Point"}
}