{
  "type": "Feature",
  "properties": {
    "addr:full":"2878 Park Rd Mayodan NC 27027",
    "addr:housenumber":"2878",
    "addr:postcode":"27027",
    "addr:street":"Park Rd",
    "iso:country":"US",
    "sg:address":"2878 Park Rd",
    "sg:city":"Mayodan",
    "sg:classifiers":[
        {
            "category":"Recreation",
            "type":"Entertainment"
        }
    ],
    "sg:phone":"+1 336 427 0124",
    "sg:postcode":"27027",
    "sg:province":"NC",
    "sg:tags":[
        "parks"
    ],
    "wof:name":"Farris Memorial Park",
    "wof:placetype":"venue"
},
  "geometry": {"coordinates":[-79.994534,36.434307],"type":"Point"}
}