{
  "type": "Feature",
  "properties": {
    "addr:full":"995 Airport Rd Rockingham NC 28379",
    "addr:housenumber":"995",
    "addr:postcode":"28379",
    "addr:street":"Airport Rd",
    "iso:country":"US",
    "sg:address":"995 Airport Rd",
    "sg:city":"Rockingham",
    "sg:classifiers":[
        {
            "category":"Personal",
            "subcategory":"Tanning Parlor",
            "type":"Services"
        },
        {
            "category":"Personal",
            "type":"Services"
        }
    ],
    "sg:phone":"+1 910 582 8120",
    "sg:postcode":"28379",
    "sg:province":"NC",
    "sg:tags":[
        "salon"
    ],
    "wof:name":"Kelly's Tanning & Gifts",
    "wof:placetype":"venue"
},
  "geometry": {"coordinates":[-79.74321500000001,34.876383],"type":"Point"}
}