{
  "type": "Feature",
  "properties": {
    "addr:full":"401 Keisler Dr Ste 100 Cary NC 27511",
    "addr:housenumber":"401",
    "addr:postcode":"27511",
    "addr:street":"Keisler Dr Ste 100",
    "iso:country":"US",
    "sg:address":"401 Keisler Dr Ste 100",
    "sg:city":"Cary",
    "sg:classifiers":[
        {
            "category":"Health Services",
            "subcategory":"Doctor",
            "type":"Services"
        }
    ],
    "sg:phone":"+1 919 851 5880",
    "sg:postcode":"27511",
    "sg:province":"NC",
    "sg:tags":[
        "orthopedist"
    ],
    "sg:website":"www.capitalortho.com",
    "wof:name":"Capital Orthopaedic & Sports Medicine Center PA",
    "wof:placetype":"venue"
},
  "geometry": {"coordinates":[-78.778503,35.7416],"type":"Point"}
}