{
  "type": "Feature",
  "properties": {
    "iso:country":"US",
    "sg:address":"118 Westwood Rd",
    "sg:city":"Asheville",
    "sg:classifiers":[
        {
            "category":"Professional",
            "type":"Services"
        }
    ],
    "sg:phone":"+1 828 254 4610",
    "sg:postcode":"28804",
    "sg:province":"NC",
    "wof:name":"Building Changes Inc",
    "wof:placetype":"venue"
},
  "geometry": {"coordinates":[-82.570061,35.635621],"type":"Point"}
}