{
  "type": "Feature",
  "properties": {
    "iso:country":"US",
    "sg:address":"3443 Gribble Rd",
    "sg:city":"Matthews",
    "sg:classifiers":[
        {
            "category":"Autos & Motor Vehicles",
            "subcategory":"Automobile Sales",
            "type":"Retail Goods"
        }
    ],
    "sg:phone":"+1 704 821 2060",
    "sg:postcode":"28104",
    "sg:province":"NC",
    "sg:tags":[
        "new",
        "car"
    ],
    "wof:name":"Honda Speciality And Tran",
    "wof:placetype":"venue"
},
  "geometry": {"coordinates":[-80.679801,35.085456],"type":"Point"}
}