{
  "type": "Feature",
  "properties": {
    "iso:country":"US",
    "sg:address":"224 E Fairground Ave",
    "sg:city":"Troy",
    "sg:classifiers":[
        {
            "category":"Organizations",
            "subcategory":"Religious Organization",
            "type":"Services"
        }
    ],
    "sg:phone":"+1   ",
    "sg:postcode":"27371",
    "sg:province":"NC",
    "wof:name":"Troy Chapel AME Zion Church",
    "wof:placetype":"venue"
},
  "geometry": {"coordinates":[-79.892416,35.354009],"type":"Point"}
}