{
  "type": "Feature",
  "properties": {
    "iso:country":"US",
    "sg:address":"1068 E 10th St",
    "sg:city":"Roanoke Rapids",
    "sg:classifiers":[
        {
            "category":"Health Services",
            "subcategory":"Doctor",
            "type":"Services"
        }
    ],
    "sg:phone":"+1 252 537 8822",
    "sg:postcode":"27870",
    "sg:province":"NC",
    "sg:tags":[
        "dentist"
    ],
    "wof:name":"Harrold & Assoc Pa",
    "wof:placetype":"venue"
},
  "geometry": {"coordinates":[-77.647507,36.451493],"type":"Point"}
}