{
  "type": "Feature",
  "properties": {
    "iso:country":"US",
    "sg:address":"111 Christopher Ln",
    "sg:city":"Clinton",
    "sg:phone":"+1 910 592 1944",
    "sg:postcode":"28328",
    "sg:province":"NC",
    "sg:tags":[
        "farm",
        "tobacco",
        "cotton"
    ],
    "wof:name":"Chris Pearson",
    "wof:placetype":"venue"
},
  "geometry": {"coordinates":[-78.30777399999999,35.017058],"type":"Point"}
}