{
  "type": "Feature",
  "properties": {
    "addr:full":"10902 N Main St Archdale NC 27263",
    "addr:housenumber":"10902",
    "addr:postcode":"27263",
    "addr:street":"N Main St",
    "iso:country":"US",
    "sg:address":"10902 N Main St",
    "sg:city":"Archdale",
    "sg:classifiers":[
        {
            "category":"Home & Garden",
            "subcategory":"Garden Supply",
            "type":"Retail Goods"
        }
    ],
    "sg:phone":"+1 336 431 6552",
    "sg:postcode":"27263",
    "sg:province":"NC",
    "sg:tags":[
        "center"
    ],
    "wof:name":"Covered Bridge Lawn & Garden",
    "wof:placetype":"venue"
},
  "geometry": {"coordinates":[-79.969202,35.910437],"type":"Point"}
}