{
  "type": "Feature",
  "properties": {
    "addr:full":"501 N Faison Ave Faison NC 28341",
    "addr:housenumber":"501",
    "addr:postcode":"28341",
    "addr:street":"N Faison Ave",
    "iso:country":"US",
    "sg:address":"501 N Faison Ave",
    "sg:city":"Faison",
    "sg:classifiers":[
        {
            "category":"Real Estate",
            "subcategory":"Real Estate Operator",
            "type":"Services"
        }
    ],
    "sg:phone":"+1 910 267 1337",
    "sg:postcode":"28341",
    "sg:province":"NC",
    "sg:tags":[
        "building",
        "apartment"
    ],
    "wof:name":"Pecan Grove Apartments",
    "wof:placetype":"venue"
},
  "geometry": {"coordinates":[-78.135578,35.123583],"type":"Point"}
}