{
  "type": "Feature",
  "properties": {
    "addr:full":"8404 Six Forks Rd Ste 203 Raleigh NC 27615",
    "addr:housenumber":"8404",
    "addr:postcode":"27615",
    "addr:street":"Six Forks Rd Ste 203",
    "iso:country":"US",
    "sg:address":"8404 Six Forks Rd Ste 203",
    "sg:city":"Raleigh",
    "sg:classifiers":[
        {
            "category":"Health Services",
            "subcategory":"Clinic",
            "type":"Services"
        },
        {
            "category":"Health Services",
            "subcategory":"Health Practitioner",
            "type":"Services"
        },
        {
            "category":"Health Services",
            "subcategory":"Chiropractor",
            "type":"Services"
        }
    ],
    "sg:phone":"+1 919 841 0081",
    "sg:postcode":"27615",
    "sg:province":"NC",
    "sg:tags":[
        "acupuncture",
        "medicine",
        "alternative",
        "chiropractic"
    ],
    "wof:name":"Askeland Chiropractic",
    "wof:placetype":"venue"
},
  "geometry": {"coordinates":[-78.64901999999999,35.893743],"type":"Point"}
}