{
  "type": "Feature",
  "properties": {
    "addr:full":"313 N Pryor St Gastonia NC 28052",
    "addr:housenumber":"313",
    "addr:postcode":"28052",
    "addr:street":"N Pryor St",
    "iso:country":"US",
    "sg:address":"313 N Pryor St",
    "sg:city":"Gastonia",
    "sg:classifiers":[
        {
            "category":"Building & Trades",
            "subcategory":"Construction",
            "type":"Services"
        }
    ],
    "sg:phone":"+1 704 867 0029",
    "sg:postcode":"28052",
    "sg:province":"NC",
    "sg:tags":[
        "repair",
        "welding",
        "contractor"
    ],
    "wof:name":"Mobile Welding & Fence Co",
    "wof:placetype":"venue"
},
  "geometry": {"coordinates":[-81.19216299999999,35.268741],"type":"Point"}
}