{
  "type": "Feature",
  "properties": {
    "addr:full":"100 E Wilmington St Burgaw NC 28425",
    "addr:housenumber":"100",
    "addr:postcode":"28425",
    "addr:street":"E Wilmington St",
    "iso:country":"US",
    "sg:address":"100 E Wilmington St",
    "sg:city":"Burgaw",
    "sg:classifiers":[
        {
            "category":"Recreation",
            "type":"Entertainment"
        }
    ],
    "sg:phone":"+1 910 259 2809",
    "sg:postcode":"28425",
    "sg:province":"NC",
    "sg:tags":[
        "course",
        "golf"
    ],
    "wof:name":"Coastal Carolina Country Club",
    "wof:placetype":"venue"
},
  "geometry": {"coordinates":[-77.925325,34.551632],"type":"Point"}
}