{
  "type": "Feature",
  "properties": {
    "iso:country":"US",
    "sg:address":"451 E Belvoir Rd",
    "sg:city":"Greenville",
    "sg:classifiers":[
        {
            "category":"Government",
            "subcategory":"Jail",
            "type":"Public Place"
        }
    ],
    "sg:phone":"+1 252 830 6590",
    "sg:postcode":"27834",
    "sg:province":"NC",
    "sg:tags":[
        "juvenile",
        "detention",
        "center"
    ],
    "wof:name":"Pitt Rgnal Jvnile Dtention Ctr",
    "wof:placetype":"venue"
},
  "geometry": {"coordinates":[-77.366536,35.637156],"type":"Point"}
}