{
  "type": "Feature",
  "properties": {
    "iso:country":"US",
    "sg:address":"230 Newton Rd",
    "sg:city":"Raleigh",
    "sg:classifiers":[
        {
            "category":"Professional",
            "subcategory":"Art Services",
            "type":"Services"
        }
    ],
    "sg:phone":"+1 919 518 1186",
    "sg:postcode":"27615",
    "sg:province":"NC",
    "sg:tags":[
        "photographer"
    ],
    "wof:name":"Neil Boyd Photography",
    "wof:placetype":"venue"
},
  "geometry": {"coordinates":[-78.644948,35.878928],"type":"Point"}
}