{
  "type": "Feature",
  "properties": {
    "iso:country":"US",
    "sg:address":"1110 Williamsboro St",
    "sg:city":"Oxford",
    "sg:classifiers":[
        {
            "category":"Professional",
            "type":"Services"
        }
    ],
    "sg:phone":"+1 919 693 6009",
    "sg:postcode":"27565",
    "sg:province":"NC",
    "sg:tags":[
        "establishment"
    ],
    "wof:name":"David Drye Co",
    "wof:placetype":"venue"
},
  "geometry": {"coordinates":[-78.56999999999999,36.315165],"type":"Point"}
}