{
  "type": "Feature",
  "properties": {
    "iso:country":"US",
    "sg:address":"400 N Center St",
    "sg:city":"Goldsboro",
    "sg:classifiers":[
        {
            "category":"Autos & Motor Vehicles",
            "subcategory":"Auto Supplies",
            "type":"Retail Goods"
        }
    ],
    "sg:phone":"+1 919 734 7455",
    "sg:postcode":"27530",
    "sg:province":"NC",
    "sg:tags":[
        "equipment",
        "air",
        "conditioning",
        "automobile"
    ],
    "wof:name":"Hall Auto Parts & Svc",
    "wof:placetype":"venue"
},
  "geometry": {"coordinates":[-77.994719,35.388295],"type":"Point"}
}