{
  "type": "Feature",
  "properties": {
    "iso:country":"US",
    "sg:address":"832 Cumberland St",
    "sg:city":"Fayetteville",
    "sg:classifiers":[
        {
            "category":"Real Estate",
            "subcategory":"Real Estate Agent",
            "type":"Services"
        }
    ],
    "sg:phone":"+1 910 483 8927",
    "sg:postcode":"28301",
    "sg:province":"NC",
    "wof:name":"Mc Neill & Sons Real Estate",
    "wof:placetype":"venue"
},
  "geometry": {"coordinates":[-78.890714,35.067575],"type":"Point"}
}