{
  "type": "Feature",
  "properties": {
    "addr:full":"610 Arendell St Morehead City NC 28557",
    "addr:housenumber":"610",
    "addr:postcode":"28557",
    "addr:street":"Arendell St",
    "iso:country":"US",
    "sg:address":"610 Arendell St",
    "sg:city":"Morehead City",
    "sg:classifiers":[
        {
            "category":"Professional",
            "subcategory":"Lawyer & Legal Services",
            "type":"Services"
        }
    ],
    "sg:phone":"+1 252 726 0001",
    "sg:postcode":"28557",
    "sg:province":"NC",
    "sg:tags":[
        "attorney"
    ],
    "wof:name":"Taylor & Taylor Law Office",
    "wof:placetype":"venue"
},
  "geometry": {"coordinates":[-76.711023,34.721356],"type":"Point"}
}