{
  "type": "Feature",
  "properties": {
    "iso:country":"US",
    "sg:address":"1506 Bridges St",
    "sg:city":"Morehead City",
    "sg:classifiers":[
        {
            "category":"Building & Trades",
            "subcategory":"Equipment Rental",
            "type":"Services"
        }
    ],
    "sg:phone":"+1 252 726 6219",
    "sg:postcode":"28557",
    "sg:province":"NC",
    "sg:tags":[
        "yard"
    ],
    "wof:name":"Chair & Equipment Rental",
    "wof:placetype":"venue"
},
  "geometry": {"coordinates":[-76.72383000000001,34.723218],"type":"Point"}
}