{
  "type": "Feature",
  "properties": {
    "addr:full":"751 Museum Dr Charlotte NC 28207",
    "addr:housenumber":"751",
    "addr:postcode":"28207",
    "addr:street":"Museum Dr",
    "iso:country":"US",
    "sg:address":"751 Museum Dr",
    "sg:city":"Charlotte",
    "sg:classifiers":[
        {
            "category":"Real Estate",
            "subcategory":"Real Estate Operator",
            "type":"Services"
        }
    ],
    "sg:phone":"+1 704 377 6799",
    "sg:postcode":"28207",
    "sg:province":"NC",
    "sg:tags":[
        "building",
        "apartment"
    ],
    "wof:name":"Queens West LLC",
    "wof:placetype":"venue"
},
  "geometry": {"coordinates":[-80.816605,35.189398],"type":"Point"}
}