{
  "type": "Feature",
  "properties": {
    "addr:full":"613 Broad St Durham NC 27705",
    "addr:housenumber":"613",
    "addr:postcode":"27705",
    "addr:street":"Broad St",
    "iso:country":"US",
    "sg:address":"613 Broad St",
    "sg:city":"Durham",
    "sg:classifiers":[
        {
            "category":"Personal",
            "subcategory":"Beauty Salon",
            "type":"Services"
        }
    ],
    "sg:phone":"+1 919 416 3168",
    "sg:postcode":"27705",
    "sg:province":"NC",
    "wof:name":"Hair Cuttery",
    "wof:placetype":"venue"
},
  "geometry": {"coordinates":[-78.919826,36.007274],"type":"Point"}
}