{
  "type": "Feature",
  "properties": {
    "iso:country":"US",
    "sg:address":"4342 Spicer Mountain Rd",
    "sg:city":"Sparta",
    "sg:classifiers":[
        {
            "category":"Shopping",
            "subcategory":"Crafts & Fabrics",
            "type":"Retail Goods"
        }
    ],
    "sg:phone":"+1 336 372 8303",
    "sg:postcode":"28675",
    "sg:province":"NC",
    "sg:tags":[
        "sewing"
    ],
    "wof:name":"Stable Stitches",
    "wof:placetype":"venue"
},
  "geometry": {"coordinates":[-81.167084,36.493823],"type":"Point"}
}