{
  "type": "Feature",
  "properties": {
    "addr:full":"4368 State Hwy 134 Asheboro NC 27205",
    "addr:housenumber":"4368",
    "addr:postcode":"27205",
    "addr:street":"State Hwy 134",
    "iso:country":"US",
    "sg:address":"4368 State Hwy 134",
    "sg:city":"Asheboro",
    "sg:classifiers":[
        {
            "category":"Organizations",
            "subcategory":"Religious Organization",
            "type":"Services"
        }
    ],
    "sg:phone":"+1 336 381 3988",
    "sg:postcode":"27205",
    "sg:province":"NC",
    "sg:tags":[
        "house",
        "retreat"
    ],
    "wof:name":"Aham Meditation Retreat Ctr",
    "wof:placetype":"venue"
},
  "geometry": {"coordinates":[-79.83280600000001,35.580006],"type":"Point"}
}