{
  "type": "Feature",
  "properties": {
    "addr:full":"117 Dick St Fayetteville NC 28301",
    "addr:housenumber":"117",
    "addr:postcode":"28301",
    "addr:street":"Dick St",
    "iso:country":"US",
    "sg:address":"117 Dick St",
    "sg:city":"Fayetteville",
    "sg:classifiers":[
        {
            "category":"Government",
            "subcategory":"Office",
            "type":"Public Place"
        }
    ],
    "sg:phone":"+1 910 678 7755",
    "sg:postcode":"28301",
    "sg:province":"NC",
    "wof:name":"County Payroll",
    "wof:placetype":"venue"
},
  "geometry": {"coordinates":[-78.877476,35.050263],"type":"Point"}
}