{
  "type": "Feature",
  "properties": {
    "addr:full":"424 W Finger St Maiden NC 28650",
    "addr:housenumber":"424",
    "addr:postcode":"28650",
    "addr:street":"W Finger St",
    "iso:country":"US",
    "sg:address":"424 W Finger St",
    "sg:city":"Maiden",
    "sg:classifiers":[
        {
            "category":"Building & Trades",
            "subcategory":"Construction",
            "type":"Services"
        }
    ],
    "sg:phone":"+1 828 428 3663",
    "sg:postcode":"28650",
    "sg:province":"NC",
    "sg:tags":[
        "maker",
        "cabinet"
    ],
    "wof:name":"Olde Country Woodworks LLC",
    "wof:placetype":"venue"
},
  "geometry": {"coordinates":[-81.220974,35.577232],"type":"Point"}
}