{
  "type": "Feature",
  "properties": {
    "addr:full":"427 Dixie Dr Selma NC 27576",
    "addr:housenumber":"427",
    "addr:postcode":"27576",
    "addr:street":"Dixie Dr",
    "iso:country":"US",
    "sg:address":"427 Dixie Dr",
    "sg:city":"Selma",
    "sg:classifiers":[
        {
            "category":"Real Estate",
            "subcategory":"Real Estate Agent",
            "type":"Services"
        }
    ],
    "sg:phone":"+1 919 965 9521",
    "sg:postcode":"27576",
    "sg:province":"NC",
    "wof:name":"Gary Jackson Rentals",
    "wof:placetype":"venue"
},
  "geometry": {"coordinates":[-78.274608,35.541004],"type":"Point"}
}