{
  "type": "Feature",
  "properties": {
    "addr:full":"1709 Legion Rd Chapel Hill NC 27517",
    "addr:housenumber":"1709",
    "addr:postcode":"27517",
    "addr:street":"Legion Rd",
    "iso:country":"US",
    "sg:address":"1709 Legion Rd",
    "sg:city":"Chapel Hill",
    "sg:classifiers":[
        {
            "category":"Banks & Credit Unions",
            "subcategory":"Atm",
            "type":"Services"
        }
    ],
    "sg:phone":"+1 919 533 5046",
    "sg:postcode":"27517",
    "sg:province":"NC",
    "sg:tags":[
        "bankruptcy"
    ],
    "sg:website":"brownerlaw.com",
    "wof:name":"Jeremy Browner Law Offices",
    "wof:placetype":"venue"
},
  "geometry": {"coordinates":[-79.019766,35.936598],"type":"Point"}
}