{
  "type": "Feature",
  "properties": {
    "addr:full":"200 Yaupon Dr Southport NC 28461",
    "addr:housenumber":"200",
    "addr:postcode":"28461",
    "addr:street":"Yaupon Dr",
    "iso:country":"US",
    "sg:address":"200 Yaupon Dr",
    "sg:city":"Southport",
    "sg:classifiers":[
        {
            "category":"Home & Garden",
            "subcategory":"Hardware",
            "type":"Retail Goods"
        }
    ],
    "sg:phone":"+1 910 278 3832",
    "sg:postcode":"28461",
    "sg:province":"NC",
    "wof:name":"Oak Island Ace Hardware",
    "wof:placetype":"venue"
},
  "geometry": {"coordinates":[-78.016446,33.933763],"type":"Point"}
}