{
  "type": "Feature",
  "properties": {
    "addr:full":"1112 W Davis St Burlington NC 27215",
    "addr:housenumber":"1112",
    "addr:postcode":"27215",
    "addr:street":"W Davis St",
    "iso:country":"US",
    "sg:address":"1112 W Davis St",
    "sg:city":"Burlington",
    "sg:classifiers":[
        {
            "category":"Manufacturing",
            "subcategory":"Apparel",
            "type":"Manufacturing & Wholesale Goods"
        }
    ],
    "sg:phone":"+1 336 227 2001",
    "sg:postcode":"27215",
    "sg:province":"NC",
    "sg:tags":[
        "outerwear",
        "mfg"
    ],
    "wof:name":"All That Jazz",
    "wof:placetype":"venue"
},
  "geometry": {"coordinates":[-79.45484,36.096291],"type":"Point"}
}