{
  "type": "Feature",
  "properties": {
    "iso:country":"US",
    "sg:address":"200 Main St",
    "sg:city":"North Wilkesboro",
    "sg:classifiers":[
        {
            "category":"Shopping",
            "subcategory":"Used Merchandise",
            "type":"Retail Goods"
        }
    ],
    "sg:phone":"+1 336 667 1801",
    "sg:postcode":"28659",
    "sg:province":"NC",
    "sg:tags":[
        "pawnbroker"
    ],
    "wof:name":"Yesterday's Antiques & Pawn",
    "wof:placetype":"venue"
},
  "geometry": {"coordinates":[-81.138267,36.162984],"type":"Point"}
}