{
  "type": "Feature",
  "properties": {
    "addr:full":"3056 State Hwy 54 Haw River NC 27258",
    "addr:housenumber":"3056",
    "addr:postcode":"27258",
    "addr:street":"State Hwy 54",
    "iso:country":"US",
    "sg:address":"3056 State Hwy 54",
    "sg:city":"Haw River",
    "sg:classifiers":[
        {
            "category":"Building & Trades",
            "subcategory":"Electrical",
            "type":"Services"
        }
    ],
    "sg:phone":"+1 336 578 2326",
    "sg:postcode":"27258",
    "sg:province":"NC",
    "sg:tags":[
        "electrical",
        "electric",
        "contractor"
    ],
    "wof:name":"Hartley's Custom Electric",
    "wof:placetype":"venue"
},
  "geometry": {"coordinates":[-79.334858,36.022528],"type":"Point"}
}