{
  "type": "Feature",
  "properties": {
    "addr:full":"100 Brickyard Rd Asheville NC 28806",
    "addr:housenumber":"100",
    "addr:postcode":"28806",
    "addr:street":"Brickyard Rd",
    "iso:country":"US",
    "sg:address":"100 Brickyard Rd",
    "sg:city":"Asheville",
    "sg:classifiers":[
        {
            "category":"Retail",
            "subcategory":"Auto Repair",
            "type":"Services"
        }
    ],
    "sg:phone":"+1   ",
    "sg:postcode":"28806",
    "sg:province":"NC",
    "sg:tags":[
        "automotive"
    ],
    "wof:name":"James Smart",
    "wof:placetype":"venue"
},
  "geometry": {"coordinates":[-82.598972,35.602506],"type":"Point"}
}