{
  "type": "Feature",
  "properties": {
    "iso:country":"US",
    "sg:address":"1700 Mintz Rd",
    "sg:city":"Roseboro",
    "sg:classifiers":[
        {
            "category":"Farming",
            "subcategory":"Farm",
            "type":"Manufacturing & Wholesale Goods"
        }
    ],
    "sg:phone":"+1 910 564 6020",
    "sg:postcode":"28382",
    "sg:province":"NC",
    "sg:tags":[
        "crop",
        "general"
    ],
    "wof:name":"Warren Christmas Tree Farm",
    "wof:placetype":"venue"
},
  "geometry": {"coordinates":[-78.467197,34.905701],"type":"Point"}
}