{
  "type": "Feature",
  "properties": {
    "addr:full":"309 S Main St Four Oaks NC 27524",
    "addr:housenumber":"309",
    "addr:postcode":"27524",
    "addr:street":"S Main St",
    "iso:country":"US",
    "sg:address":"309 S Main St",
    "sg:city":"Four Oaks",
    "sg:classifiers":[
        {
            "category":"Professional",
            "type":"Services"
        }
    ],
    "sg:phone":"+1 919 963 3190",
    "sg:postcode":"27524",
    "sg:province":"NC",
    "sg:tags":[
        "arts",
        "artist"
    ],
    "wof:name":"Barbara A Keen Studio",
    "wof:placetype":"venue"
},
  "geometry": {"coordinates":[-78.426495,35.439357],"type":"Point"}
}