{
  "type": "Feature",
  "properties": {
    "addr:full":"1508 Jupiter Hills Cir Wilmington NC 28411",
    "addr:housenumber":"1508",
    "addr:postcode":"28411",
    "addr:street":"Jupiter Hills Cir",
    "iso:country":"US",
    "sg:address":"1508 Jupiter Hills Cir",
    "sg:city":"Wilmington",
    "sg:classifiers":[
        {
            "category":"Wholesale",
            "subcategory":"Furniture",
            "type":"Manufacturing & Wholesale Goods"
        }
    ],
    "sg:phone":"+1 910 686 3277",
    "sg:postcode":"28411",
    "sg:province":"NC",
    "wof:name":"Carolina Closet Co",
    "wof:placetype":"venue"
},
  "geometry": {"coordinates":[-77.756255,34.290928],"type":"Point"}
}