{
  "type": "Feature",
  "properties": {
    "addr:full":"2302 Nash St NW Wilson NC 27896",
    "addr:housenumber":"2302",
    "addr:postcode":"27896",
    "addr:street":"Nash St Nw",
    "iso:country":"US",
    "sg:address":"2302 Nash St NW",
    "sg:city":"Wilson",
    "sg:classifiers":[
        {
            "category":"Shopping",
            "subcategory":"Clothing, Apparel, & Fashions",
            "type":"Retail Goods"
        }
    ],
    "sg:phone":"+1 252 291 9943",
    "sg:postcode":"27896",
    "sg:province":"NC",
    "sg:tags":[
        "infant",
        "wear"
    ],
    "wof:name":"Too Cute",
    "wof:placetype":"venue"
},
  "geometry": {"coordinates":[-77.932687,35.757216],"type":"Point"}
}