{
  "type": "Feature",
  "properties": {
    "addr:full":"5195 Canary Ct Granite Falls NC 28630",
    "addr:housenumber":"5195",
    "addr:postcode":"28630",
    "addr:street":"Canary Ct",
    "iso:country":"US",
    "sg:address":"5195 Canary Ct",
    "sg:city":"Granite Falls",
    "sg:classifiers":[
        {
            "category":"Building & Trades",
            "subcategory":"Electrical",
            "type":"Services"
        }
    ],
    "sg:phone":"+1 828 396 8175",
    "sg:postcode":"28630",
    "sg:province":"NC",
    "sg:tags":[
        "electrical",
        "electric",
        "contractor"
    ],
    "wof:name":"Barry Reece Electrical Service",
    "wof:placetype":"venue"
},
  "geometry": {"coordinates":[-81.35685100000001,35.815457],"type":"Point"}
}