{
  "type": "Feature",
  "properties": {
    "iso:country":"US",
    "sg:address":"102 Shepton Dr",
    "sg:city":"Cary",
    "sg:classifiers":[
        {
            "category":"Professional",
            "subcategory":"Advertising",
            "type":"Services"
        }
    ],
    "sg:phone":"+1 919 345 0428",
    "sg:postcode":"27519",
    "sg:province":"NC",
    "sg:tags":[
        "software"
    ],
    "wof:name":"Cnconsulting Inc",
    "wof:placetype":"venue"
},
  "geometry": {"coordinates":[-78.854832,35.803431],"type":"Point"}
}