{
  "type": "Feature",
  "properties": {
    "iso:country":"US",
    "sg:address":"16430 Big Lick Rd",
    "sg:city":"Oakboro",
    "sg:classifiers":[
        {
            "category":"Building & Trades",
            "subcategory":"Plumbing",
            "type":"Services"
        }
    ],
    "sg:phone":"+1 704 485 3671",
    "sg:postcode":"28129",
    "sg:province":"NC",
    "sg:tags":[
        "plumbing",
        "contractor"
    ],
    "wof:name":"Hatley Plumbing",
    "wof:placetype":"venue"
},
  "geometry": {"coordinates":[-80.356077,35.235036],"type":"Point"}
}