{
  "type": "Feature",
  "properties": {
    "iso:country":"US",
    "sg:address":"5780 High Pine Church Rd",
    "sg:city":"Asheboro",
    "sg:classifiers":[
        {
            "category":"Home & Garden",
            "subcategory":"Garden Supply",
            "type":"Retail Goods"
        }
    ],
    "sg:phone":"+1 336 381 3841",
    "sg:postcode":"27205",
    "sg:province":"NC",
    "wof:name":"JBT Nursery",
    "wof:placetype":"venue"
},
  "geometry": {"coordinates":[-79.916635,35.552421],"type":"Point"}
}