{
  "type": "Feature",
  "properties": {
    "addr:full":"506 Waco Rd Kings Mountain NC 28086",
    "addr:housenumber":"506",
    "addr:postcode":"28086",
    "addr:street":"Waco Rd",
    "iso:country":"US",
    "sg:address":"506 Waco Rd",
    "sg:city":"Kings Mountain",
    "sg:classifiers":[
        {
            "category":"Food & Beverages",
            "subcategory":"Groceries & Convenience Stores",
            "type":"Retail Goods"
        }
    ],
    "sg:phone":"+1 704 739 7500",
    "sg:postcode":"28086",
    "sg:province":"NC",
    "wof:name":"Mountain Market General Store",
    "wof:placetype":"venue"
},
  "geometry": {"coordinates":[-81.352783,35.249891],"type":"Point"}
}