{
  "type": "Feature",
  "properties": {
    "addr:full":"531 S Bickett Blvd Louisburg NC 27549",
    "addr:housenumber":"531",
    "addr:postcode":"27549",
    "addr:street":"S Bickett Blvd",
    "iso:country":"US",
    "sg:address":"531 S Bickett Blvd",
    "sg:city":"Louisburg",
    "sg:classifiers":[
        {
            "category":"Professional",
            "subcategory":"Accounting & Tax Preparation",
            "type":"Services"
        }
    ],
    "sg:phone":"+1 919 496 3041",
    "sg:postcode":"27549",
    "sg:province":"NC",
    "sg:tags":[
        "bookkeeping"
    ],
    "wof:name":"Scott H May Cpa",
    "wof:placetype":"venue"
},
  "geometry": {"coordinates":[-78.309776,36.083691],"type":"Point"}
}