{
  "type": "Feature",
  "properties": {
    "iso:country":"US",
    "sg:address":"710 Porter Rd",
    "sg:city":"Greenville",
    "sg:classifiers":[
        {
            "category":"Wholesale",
            "subcategory":"Durable Goods & Equipment",
            "type":"Manufacturing & Wholesale Goods"
        }
    ],
    "sg:phone":"+1 252 758 3473",
    "sg:postcode":"27834",
    "sg:province":"NC",
    "sg:tags":[
        "fire",
        "extinguisher"
    ],
    "wof:name":"Allstate Fire Protection Inc",
    "wof:placetype":"venue"
},
  "geometry": {"coordinates":[-77.46372,35.715274],"type":"Point"}
}