{
  "type": "Feature",
  "properties": {
    "iso:country":"US",
    "sg:address":"2518 Virginia Rd",
    "sg:city":"Edenton",
    "sg:classifiers":[
        {
            "category":"Retail",
            "subcategory":"Repair Shop",
            "type":"Services"
        }
    ],
    "sg:phone":"+1 252 221 8093",
    "sg:postcode":"27932",
    "sg:province":"NC",
    "sg:tags":[
        "appliance"
    ],
    "wof:name":"Cliff's Appliance Repair",
    "wof:placetype":"venue"
},
  "geometry": {"coordinates":[-76.65754200000001,36.21524],"type":"Point"}
}