{
  "type": "Feature",
  "properties": {
    "iso:country":"US",
    "sg:address":"7900 Saddleview Ct",
    "sg:city":"Charlotte",
    "sg:classifiers":[
        {
            "category":"Wholesale",
            "subcategory":"Construction Materials",
            "type":"Manufacturing & Wholesale Goods"
        }
    ],
    "sg:phone":"+1 704 568 9342",
    "sg:postcode":"28215",
    "sg:province":"NC",
    "sg:tags":[
        "contractor",
        "mason"
    ],
    "wof:name":"Joe Reid Masonry Inc",
    "wof:placetype":"venue"
},
  "geometry": {"coordinates":[-80.651878,35.261341],"type":"Point"}
}