{
  "type": "Feature",
  "properties": {
    "addr:full":"2071 Kenric Dr Lumberton NC 28360",
    "addr:housenumber":"2071",
    "addr:postcode":"28360",
    "addr:street":"Kenric Dr",
    "iso:country":"US",
    "sg:address":"2071 Kenric Dr",
    "sg:city":"Lumberton",
    "sg:classifiers":[
        {
            "category":"Retail",
            "subcategory":"Auto Repair",
            "type":"Services"
        }
    ],
    "sg:phone":"+1 910 738 6630",
    "sg:postcode":"28360",
    "sg:province":"NC",
    "sg:tags":[
        "body",
        "automobile",
        "painting"
    ],
    "wof:name":"Simpson's Paint & Body Shop",
    "wof:placetype":"venue"
},
  "geometry": {"coordinates":[-79.099137,34.604851],"type":"Point"}
}