{
  "type": "Feature",
  "properties": {
    "iso:country":"US",
    "sg:address":"18021 Bluff Inlet Rd",
    "sg:city":"Cornelius",
    "sg:classifiers":[
        {
            "category":"Professional",
            "subcategory":"Management & Consulting",
            "type":"Services"
        }
    ],
    "sg:phone":"+1   ",
    "sg:postcode":"28031",
    "sg:province":"NC",
    "sg:tags":[
        "business"
    ],
    "wof:name":"Terra Genius LLC",
    "wof:placetype":"venue"
},
  "geometry": {"coordinates":[-80.866758,35.491841],"type":"Point"}
}