{
  "type": "Feature",
  "properties": {
    "iso:country":"US",
    "sg:address":"130 Annaron Ct",
    "sg:city":"Raleigh",
    "sg:classifiers":[
        {
            "category":"Autos & Motor Vehicles",
            "subcategory":"Fuel & Gas Station",
            "type":"Retail Goods"
        },
        {
            "category":"Autos & Motor Vehicles",
            "subcategory":"Auto Supplies",
            "type":"Retail Goods"
        },
        {
            "category":"Retail",
            "subcategory":"Auto Repair",
            "type":"Services"
        }
    ],
    "sg:phone":"+1 919 779 3460",
    "sg:postcode":"27603",
    "sg:province":"NC",
    "sg:tags":[
        "exhaust",
        "automobile",
        "system",
        "diagnostic",
        "truck",
        "muffler",
        "inspection"
    ],
    "wof:name":"Mr. Transmission/Milex Auto Repair",
    "wof:placetype":"venue"
},
  "geometry": {"coordinates":[-78.65237500000001,35.720681],"type":"Point"}
}