{
  "type": "Feature",
  "properties": {
    "iso:country":"US",
    "sg:address":"203 E Horton St",
    "sg:city":"Zebulon",
    "sg:classifiers":[
        {
            "category":"Building & Trades",
            "subcategory":"Electrical",
            "type":"Services"
        }
    ],
    "sg:phone":"+1 919 269 2125",
    "sg:postcode":"27597",
    "sg:province":"NC",
    "sg:tags":[
        "electrical",
        "contractor"
    ],
    "wof:name":"BMW Electric of Zebulon Inc",
    "wof:placetype":"venue"
},
  "geometry": {"coordinates":[-78.30959,35.82383],"type":"Point"}
}