{
  "type": "Feature",
  "properties": {
    "addr:full":"1125 Cotton Grove Rd Lexington NC 27292",
    "addr:housenumber":"1125",
    "addr:postcode":"27292",
    "addr:street":"Cotton Grove Rd",
    "iso:country":"US",
    "sg:address":"1125 Cotton Grove Rd",
    "sg:city":"Lexington",
    "sg:classifiers":[
        {
            "category":"Food & Beverages",
            "subcategory":"Groceries & Convenience Stores",
            "type":"Retail Goods"
        }
    ],
    "sg:phone":"+1 336 236 6842",
    "sg:postcode":"27292",
    "sg:province":"NC",
    "wof:name":"Git It & Go",
    "wof:placetype":"venue"
},
  "geometry": {"coordinates":[-80.26215500000001,35.793972],"type":"Point"}
}