{
  "type": "Feature",
  "properties": {
    "addr:full":"717 Atlantic Beach Cswy Atlantic Beach NC 28512",
    "addr:housenumber":"717",
    "addr:postcode":"28512",
    "addr:street":"Atlantic;Cswy",
    "iso:country":"US",
    "sg:address":"717 Atlantic Beach Cswy",
    "sg:city":"Atlantic Beach",
    "sg:classifiers":[
        {
            "category":"Shopping",
            "subcategory":"Musical Instruments",
            "type":"Retail Goods"
        }
    ],
    "sg:phone":"+1 252 726 1889",
    "sg:postcode":"28512",
    "sg:province":"NC",
    "wof:name":"Miller Music & Studios",
    "wof:placetype":"venue"
},
  "geometry": {"coordinates":[-76.737267,34.710801],"type":"Point"}
}