{
  "type": "Feature",
  "properties": {
    "iso:country":"US",
    "sg:address":"3820 Rose Lake Dr",
    "sg:city":"Charlotte",
    "sg:classifiers":[
        {
            "category":"Shopping",
            "type":"Retail Goods"
        }
    ],
    "sg:phone":"+1 704 424 0800",
    "sg:postcode":"28217",
    "sg:province":"NC",
    "sg:tags":[
        "equipment",
        "telephone",
        "supply"
    ],
    "sg:website":"www.altcommunications.com",
    "wof:name":"ALT Communications Inc",
    "wof:placetype":"venue"
},
  "geometry": {"coordinates":[-80.925287,35.177539],"type":"Point"}
}