{
  "type": "Feature",
  "properties": {
    "addr:full":"3125 Springbank Ln Charlotte NC 28226",
    "addr:housenumber":"3125",
    "addr:postcode":"28226",
    "addr:street":"Springbank Ln",
    "iso:country":"US",
    "sg:address":"3125 Springbank Ln",
    "sg:city":"Charlotte",
    "sg:classifiers":[
        {
            "category":"Health Services",
            "subcategory":"Doctor",
            "type":"Services"
        }
    ],
    "sg:phone":"+1 704 341 1103",
    "sg:postcode":"28226",
    "sg:province":"NC",
    "sg:tags":[
        "physician",
        "surgeon"
    ],
    "wof:name":"Arboretum Obstetric & Gynclgy",
    "wof:placetype":"venue"
},
  "geometry": {"coordinates":[-80.781741,35.102036],"type":"Point"}
}