{
  "type": "Feature",
  "properties": {
    "addr:full":"101 Reliance Rd Kings Mountain NC 28086",
    "addr:housenumber":"101",
    "addr:postcode":"28086",
    "addr:street":"Reliance Rd",
    "iso:country":"US",
    "sg:address":"101 Reliance Rd",
    "sg:city":"Kings Mountain",
    "sg:classifiers":[
        {
            "category":"Manufacturing",
            "subcategory":"Tools & Machinery",
            "type":"Manufacturing & Wholesale Goods"
        }
    ],
    "sg:phone":"+1 704 739 0171",
    "sg:postcode":"28086",
    "sg:province":"NC",
    "sg:tags":[
        "electric",
        "motor"
    ],
    "wof:name":"Rockwell Automation",
    "wof:placetype":"venue"
},
  "geometry": {"coordinates":[-81.41073299999999,35.249477],"type":"Point"}
}