{
  "type": "Feature",
  "properties": {
    "iso:country":"US",
    "sg:address":"1748 Charlotte Hwy",
    "sg:city":"Mooresville",
    "sg:classifiers":[
        {
            "category":"Education",
            "subcategory":"School",
            "type":"Public Place"
        }
    ],
    "sg:phone":"+1 704 664 2582",
    "sg:postcode":"28115",
    "sg:province":"NC",
    "sg:website":"www.iss.k12.nc.us",
    "wof:name":"Shepherd Elementary School",
    "wof:placetype":"venue"
},
  "geometry": {"coordinates":[-80.82844,35.635457],"type":"Point"}
}