{
  "type": "Feature",
  "properties": {
    "addr:full":"526 S Elm St Greensboro NC 27406",
    "addr:housenumber":"526",
    "addr:postcode":"27406",
    "addr:street":"S Elm St",
    "iso:country":"US",
    "sg:address":"526 S Elm St",
    "sg:city":"Greensboro",
    "sg:classifiers":[
        {
            "category":"Home & Garden",
            "subcategory":"Furniture",
            "type":"Retail Goods"
        }
    ],
    "sg:phone":"+1 336 275 7563",
    "sg:postcode":"27406",
    "sg:province":"NC",
    "wof:name":"Hampton Antiques",
    "wof:placetype":"venue"
},
  "geometry": {"coordinates":[-79.79083799999999,36.06627],"type":"Point"}
}