{
  "type": "Feature",
  "properties": {
    "iso:country":"US",
    "sg:address":"202 Beeler Ave",
    "sg:city":"Hamlet",
    "sg:classifiers":[
        {
            "category":"Building & Trades",
            "subcategory":"Construction",
            "type":"Services"
        }
    ],
    "sg:phone":"+1 910 582 6248",
    "sg:postcode":"28345",
    "sg:province":"NC",
    "sg:tags":[
        "roofing",
        "contractor"
    ],
    "wof:name":"Bullard's Roofing",
    "wof:placetype":"venue"
},
  "geometry": {"coordinates":[-79.729421,34.900331],"type":"Point"}
}