{
  "type": "Feature",
  "properties": {
    "iso:country":"US",
    "sg:address":"912 W Chatham St",
    "sg:city":"Cary",
    "sg:classifiers":[
        {
            "category":"Organizations",
            "subcategory":"Religious Organization",
            "type":"Services"
        }
    ],
    "sg:phone":"+1 919 469 1815",
    "sg:postcode":"27511",
    "sg:province":"NC",
    "wof:name":"Community Of Christ",
    "wof:placetype":"venue"
},
  "geometry": {"coordinates":[-78.797117,35.779564],"type":"Point"}
}