{
  "type": "Feature",
  "properties": {
    "iso:country":"US",
    "sg:address":"5048 Allanbrooke Ln",
    "sg:city":"Fuquay Varina",
    "sg:classifiers":[
        {
            "category":"Professional",
            "subcategory":"Lawyer & Legal Services",
            "type":"Services"
        }
    ],
    "sg:phone":"+1   ",
    "sg:postcode":"27526",
    "sg:province":"NC",
    "wof:name":"Rhodes Rgel Attorney At Law PA",
    "wof:placetype":"venue"
},
  "geometry": {"coordinates":[-78.75493,35.622999],"type":"Point"}
}