{
  "type": "Feature",
  "properties": {
    "iso:country":"US",
    "sg:address":"6054 E Independence Blvd",
    "sg:city":"Charlotte",
    "sg:classifiers":[
        {
            "category":"Real Estate",
            "subcategory":"Real Estate Services",
            "type":"Services"
        },
        {
            "category":"Banks & Credit Unions",
            "subcategory":"Financial Services",
            "type":"Services"
        }
    ],
    "sg:phone":"+1 704 536 8111",
    "sg:postcode":"28212",
    "sg:province":"NC",
    "sg:tags":[
        "financing",
        "loan"
    ],
    "sg:website":"http://citi.bridgetrack.com/citifi/_redir.htm?BTData=302177C736961705A55424AB8BEBEABA298948493FBFBF6E9EAC5C2DECE67BE2&BT_TRF=10467&RedirectID=YLLWPGS_US_CTGRY_TRD_LNK_FNCL_SRVCS_CPC&creativeID=YP_Link",
    "wof:name":"CitiFinancial",
    "wof:placetype":"venue"
},
  "geometry": {"coordinates":[-80.752092,35.178711],"type":"Point"}
}