{
  "type": "Feature",
  "properties": {
    "iso:country":"US",
    "sg:address":"126 Airy Ln",
    "sg:city":"Sylva",
    "sg:classifiers":[
        {
            "category":"Real Estate",
            "subcategory":"Real Estate Agent",
            "type":"Services"
        }
    ],
    "sg:phone":"+1 828 586 9036",
    "sg:postcode":"28779",
    "sg:province":"NC",
    "wof:name":"Omr Inc",
    "wof:placetype":"venue"
},
  "geometry": {"coordinates":[-83.17954,35.356862],"type":"Point"}
}