{
  "type": "Feature",
  "properties": {
    "addr:full":"1701 Sunset Ave Rocky Mount NC 27804",
    "addr:housenumber":"1701",
    "addr:postcode":"27804",
    "addr:street":"Sunset Ave",
    "iso:country":"US",
    "sg:address":"1701 Sunset Ave",
    "sg:city":"Rocky Mount",
    "sg:classifiers":[
        {
            "category":"Health Services",
            "subcategory":"Clinic",
            "type":"Services"
        }
    ],
    "sg:phone":"+1 252 985 3614",
    "sg:postcode":"27804",
    "sg:province":"NC",
    "sg:tags":[
        "information",
        "program",
        "referral"
    ],
    "wof:name":"Sozo Ministries",
    "wof:placetype":"venue"
},
  "geometry": {"coordinates":[-77.819227,35.951381],"type":"Point"}
}