{
  "type": "Feature",
  "properties": {
    "addr:full":"504 Main St Maysville NC 28555",
    "addr:housenumber":"504",
    "addr:postcode":"28555",
    "addr:street":"Main St",
    "iso:country":"US",
    "sg:address":"504 Main St",
    "sg:city":"Maysville",
    "sg:classifiers":[
        {
            "category":"Shopping",
            "subcategory":"Clothing, Apparel, & Fashions",
            "type":"Retail Goods"
        }
    ],
    "sg:phone":"+1 910 743 0080",
    "sg:postcode":"28555",
    "sg:province":"NC",
    "wof:name":"Soup 2 Nuts",
    "wof:placetype":"venue"
},
  "geometry": {"coordinates":[-77.231534,34.904762],"type":"Point"}
}