{
  "type": "Feature",
  "properties": {
    "addr:full":"830 Hendersonville Rd Asheville NC 28803",
    "addr:housenumber":"830",
    "addr:postcode":"28803",
    "addr:street":"Hendersonville Rd",
    "iso:country":"US",
    "sg:address":"830 Hendersonville Rd",
    "sg:city":"Asheville",
    "sg:classifiers":[
        {
            "category":"Health Services",
            "subcategory":"Chiropractor",
            "type":"Services"
        }
    ],
    "sg:phone":"+1 828 277 7417",
    "sg:postcode":"28803",
    "sg:province":"NC",
    "wof:name":"Phillips Chiropractic",
    "wof:placetype":"venue"
},
  "geometry": {"coordinates":[-82.533109,35.543665],"type":"Point"}
}