{
  "type": "Feature",
  "properties": {
    "iso:country":"US",
    "sg:address":"342 Meredith St",
    "sg:city":"Raleigh",
    "sg:classifiers":[
        {
            "category":"Building & Trades",
            "subcategory":"Construction",
            "type":"Services"
        }
    ],
    "sg:phone":"+1 919 859 9463",
    "sg:postcode":"27606",
    "sg:province":"NC",
    "sg:tags":[
        "house"
    ],
    "wof:name":"Landis Construction Inc",
    "wof:placetype":"venue"
},
  "geometry": {"coordinates":[-78.727208,35.775643],"type":"Point"}
}