{
  "type": "Feature",
  "properties": {
    "iso:country":"US",
    "sg:address":"7 N Summit Ave",
    "sg:city":"Granite Falls",
    "sg:classifiers":[
        {
            "category":"Recreation",
            "type":"Entertainment"
        }
    ],
    "sg:phone":"+1 828 313 0022",
    "sg:postcode":"28630",
    "sg:province":"NC",
    "sg:tags":[
        "instruction",
        "golf"
    ],
    "wof:name":"Granite Golf Inc",
    "wof:placetype":"venue"
},
  "geometry": {"coordinates":[-81.44120700000001,35.805077],"type":"Point"}
}