{
  "type": "Feature",
  "properties": {
    "addr:full":"7040 E Independence Blvd Charlotte NC 28227",
    "addr:housenumber":"7040",
    "addr:postcode":"28227",
    "addr:street":"E Independence Blvd",
    "iso:country":"US",
    "sg:address":"7040 E Independence Blvd",
    "sg:city":"Charlotte",
    "sg:classifiers":[
        {
            "category":"Autos & Motor Vehicles",
            "subcategory":"Automobile Sales",
            "type":"Retail Goods"
        },
        {
            "category":"Autos & Motor Vehicles",
            "subcategory":"Auto Supplies",
            "type":"Retail Goods"
        },
        {
            "category":"Retail",
            "subcategory":"Auto Repair",
            "type":"Services"
        }
    ],
    "sg:phone":"+1 704 563 1000",
    "sg:postcode":"28227",
    "sg:province":"NC",
    "sg:tags":[
        "body",
        "cars-wholesale",
        "used",
        "car",
        "accessory",
        "dealers-used",
        "part",
        "new",
        "painting",
        "repairing"
    ],
    "sg:website":"http://www.volvocharlotte.com",
    "wof:name":"Volvo of Charlotte",
    "wof:placetype":"venue"
},
  "geometry": {"coordinates":[-80.741058,35.164371],"type":"Point"}
}