{
  "type": "Feature",
  "properties": {
    "addr:full":"243 Mill Creek Rd Princeton NC 27569",
    "addr:housenumber":"243",
    "addr:postcode":"27569",
    "addr:street":"Mill Creek Rd",
    "iso:country":"US",
    "sg:address":"243 Mill Creek Rd",
    "sg:city":"Princeton",
    "sg:classifiers":[
        {
            "category":"Building & Trades",
            "subcategory":"Construction",
            "type":"Services"
        }
    ],
    "sg:phone":"+1 919 689 3700",
    "sg:postcode":"27569",
    "sg:province":"NC",
    "sg:tags":[
        "concrete",
        "contractor"
    ],
    "wof:name":"Jeffreys Concrete Co",
    "wof:placetype":"venue"
},
  "geometry": {"coordinates":[-78.184556,35.338196],"type":"Point"}
}