{
  "type": "Feature",
  "properties": {
    "addr:full":"2550 N Wesleyan Blvd Rocky Mount NC 27804",
    "addr:housenumber":"2550",
    "addr:postcode":"27804",
    "addr:street":"N Wesleyan Blvd",
    "iso:country":"US",
    "sg:address":"2550 N Wesleyan Blvd",
    "sg:city":"Rocky Mount",
    "sg:classifiers":[
        {
            "category":"Autos & Motor Vehicles",
            "subcategory":"Automobile Sales",
            "type":"Retail Goods"
        }
    ],
    "sg:phone":"+1 252 972 6987",
    "sg:postcode":"27804",
    "sg:province":"NC",
    "sg:tags":[
        "used"
    ],
    "wof:name":"Compass Creek Motors",
    "wof:placetype":"venue"
},
  "geometry": {"coordinates":[-77.776753,35.99866],"type":"Point"}
}