{
  "type": "Feature",
  "properties": {
    "addr:full":"3035 Silk Hope Gum Spring Rd Pittsboro NC 27312",
    "addr:housenumber":"3035",
    "addr:postcode":"27312",
    "addr:street":"Silk Hope Gum Spring Rd",
    "iso:country":"US",
    "sg:address":"3035 Silk Hope Gum Spring Rd",
    "sg:city":"Pittsboro",
    "sg:classifiers":[
        {
            "category":"Health Services",
            "subcategory":"Nursing And Care Facility",
            "type":"Services"
        }
    ],
    "sg:phone":"+1 919 542 3089",
    "sg:postcode":"27312",
    "sg:province":"NC",
    "sg:tags":[
        "home",
        "rest"
    ],
    "wof:name":"Liselotte Rest Home",
    "wof:placetype":"venue"
},
  "geometry": {"coordinates":[-79.2831,35.77035],"type":"Point"}
}