{
  "type": "Feature",
  "properties": {
    "addr:full":"3100 E Market St Greensboro NC 27405",
    "addr:housenumber":"3100",
    "addr:postcode":"27405",
    "addr:street":"E Market St",
    "iso:country":"US",
    "sg:address":"3100 E Market St",
    "sg:city":"Greensboro",
    "sg:classifiers":[
        {
            "category":"Food & Beverages",
            "subcategory":"Liquor & Beverages",
            "type":"Retail Goods"
        }
    ],
    "sg:phone":"+1 336 274 5929",
    "sg:postcode":"27405",
    "sg:province":"NC",
    "wof:name":"ABC Stores",
    "wof:placetype":"venue"
},
  "geometry": {"coordinates":[-79.74061399999999,36.084064],"type":"Point"}
}