{
  "type": "Feature",
  "properties": {
    "addr:full":"1003 Max Rd Shelby NC 28152",
    "addr:housenumber":"1003",
    "addr:postcode":"28152",
    "addr:street":"Max Rd",
    "iso:country":"US",
    "sg:address":"1003 Max Rd",
    "sg:city":"Shelby",
    "sg:classifiers":[
        {
            "category":"Shopping",
            "subcategory":"Clothing, Apparel, & Fashions",
            "type":"Retail Goods"
        }
    ],
    "sg:phone":"+1 704 482 9946",
    "sg:postcode":"28152",
    "sg:province":"NC",
    "sg:tags":[
        "western"
    ],
    "sg:website":"www.thecowboyplace.com",
    "wof:name":"Cowboy Place",
    "wof:placetype":"venue"
},
  "geometry": {"coordinates":[-81.523285,35.27267],"type":"Point"}
}