{
  "type": "Feature",
  "properties": {
    "iso:country":"US",
    "sg:address":"532 Cimarron Dr",
    "sg:city":"Fayetteville",
    "sg:classifiers":[
        {
            "category":"Organizations",
            "subcategory":"Religious Organization",
            "type":"Services"
        }
    ],
    "sg:phone":"+1   ",
    "sg:postcode":"28303",
    "sg:province":"NC",
    "wof:name":"Korean Catholic Parsonage",
    "wof:placetype":"venue"
},
  "geometry": {"coordinates":[-78.972888,35.088678],"type":"Point"}
}