{
  "type": "Feature",
  "properties": {
    "iso:country":"US",
    "sg:address":"604 W Cornwall Rd",
    "sg:city":"Cary",
    "sg:classifiers":[
        {
            "category":"Personal",
            "subcategory":"Beauty Salon",
            "type":"Services"
        }
    ],
    "sg:phone":"+1 919 851 1001",
    "sg:postcode":"27511",
    "sg:province":"NC",
    "wof:name":"Lundie's Hair Salon",
    "wof:placetype":"venue"
},
  "geometry": {"coordinates":[-78.79527899999999,35.775304],"type":"Point"}
}