{
  "type": "Feature",
  "properties": {
    "addr:full":"390 Cedar Cliff Rd Hayesville NC 28904",
    "addr:housenumber":"390",
    "addr:postcode":"28904",
    "addr:street":"Cedar Cliff Rd",
    "iso:country":"US",
    "sg:address":"390 Cedar Cliff Rd",
    "sg:city":"Hayesville",
    "sg:classifiers":[
        {
            "category":"Building & Trades",
            "subcategory":"Construction",
            "type":"Services"
        }
    ],
    "sg:phone":"+1 828 389 4052",
    "sg:postcode":"28904",
    "sg:province":"NC",
    "sg:tags":[
        "house"
    ],
    "wof:name":"J&J Construction",
    "wof:placetype":"venue"
},
  "geometry": {"coordinates":[-83.685046,35.030412],"type":"Point"}
}