{
  "type": "Feature",
  "properties": {
    "iso:country":"US",
    "sg:address":"2625 N Stewart Ave",
    "sg:city":"Newton",
    "sg:classifiers":[
        {
            "category":"Wholesale",
            "subcategory":"Electrical",
            "type":"Manufacturing & Wholesale Goods"
        }
    ],
    "sg:phone":"+1 828 466 1247",
    "sg:postcode":"28658",
    "sg:province":"NC",
    "sg:tags":[
        "battery"
    ],
    "wof:name":"Twin State Battery",
    "wof:placetype":"venue"
},
  "geometry": {"coordinates":[-81.222734,35.691568],"type":"Point"}
}