{
  "type": "Feature",
  "properties": {
    "iso:country":"US",
    "sg:address":"5401 Bakers Mill Rd",
    "sg:city":"Durham",
    "sg:classifiers":[
        {
            "category":"Manufacturing",
            "subcategory":"Printing",
            "type":"Manufacturing & Wholesale Goods"
        }
    ],
    "sg:phone":"+1 919 401 9592",
    "sg:postcode":"27707",
    "sg:province":"NC",
    "sg:tags":[
        "lithographic",
        "commercial"
    ],
    "wof:name":"Carolina Golf Graphics",
    "wof:placetype":"venue"
},
  "geometry": {"coordinates":[-78.995818,35.935087],"type":"Point"}
}