{
  "type": "Feature",
  "properties": {
    "addr:full":"2504 Lynnoak Dr Greensboro NC 27406",
    "addr:housenumber":"2504",
    "addr:postcode":"27406",
    "addr:street":"Lynnoak Dr",
    "iso:country":"US",
    "sg:address":"2504 Lynnoak Dr",
    "sg:city":"Greensboro",
    "sg:classifiers":[
        {
            "category":"Retail",
            "subcategory":"Auto Repair",
            "type":"Services"
        }
    ],
    "sg:phone":"+1   ",
    "sg:postcode":"27406",
    "sg:province":"NC",
    "sg:tags":[
        "transmission"
    ],
    "wof:name":"Country Garage",
    "wof:placetype":"venue"
},
  "geometry": {"coordinates":[-79.841116,35.969484],"type":"Point"}
}