{
  "type": "Feature",
  "properties": {
    "iso:country":"US",
    "sg:address":"1406 S Scales St",
    "sg:city":"Reidsville",
    "sg:classifiers":[
        {
            "category":"Restaurant",
            "type":"Food & Drink"
        }
    ],
    "sg:phone":"+1 336 342 3304",
    "sg:postcode":"27320",
    "sg:province":"NC",
    "sg:tags":[
        "pizza"
    ],
    "sg:website":"www.pizzahut.com",
    "wof:name":"Pizza Hut",
    "wof:placetype":"venue"
},
  "geometry": {"coordinates":[-79.66385099999999,36.342969],"type":"Point"}
}