{
  "type": "Feature",
  "properties": {
    "addr:full":"7026 Market St Wilmington NC 28411",
    "addr:housenumber":"7026",
    "addr:postcode":"28411",
    "addr:street":"Market St",
    "iso:country":"US",
    "sg:address":"7026 Market St",
    "sg:city":"Wilmington",
    "sg:classifiers":[
        {
            "category":"Sports & Exercise",
            "subcategory":"Bowling",
            "type":"Entertainment"
        }
    ],
    "sg:phone":"+1 910 686 4223",
    "sg:postcode":"28411",
    "sg:province":"NC",
    "sg:tags":[
        "center"
    ],
    "sg:website":"www.cardinalnorth.com",
    "wof:name":"Cardinal Lanes",
    "wof:placetype":"venue"
},
  "geometry": {"coordinates":[-77.82452499999999,34.266787],"type":"Point"}
}