{
  "type": "Feature",
  "properties": {
    "addr:full":"201 Maumee Ct Cary NC 27513",
    "addr:housenumber":"201",
    "addr:postcode":"27513",
    "addr:street":"Maumee Ct",
    "iso:country":"US",
    "sg:address":"201 Maumee Ct",
    "sg:city":"Cary",
    "sg:classifiers":[
        {
            "category":"Organizations",
            "subcategory":"Community Association",
            "type":"Services"
        }
    ],
    "sg:phone":"+1 919 306 5236",
    "sg:postcode":"27513",
    "sg:province":"NC",
    "sg:tags":[
        "professional",
        "fraternal"
    ],
    "sg:website":"www.orderinthehouse.biz",
    "wof:name":"Order In the House",
    "wof:placetype":"venue"
},
  "geometry": {"coordinates":[-78.82530199999999,35.771702],"type":"Point"}
}