{
  "type": "Feature",
  "properties": {
    "iso:country":"US",
    "sg:address":"1655 20th Avenue Dr NE",
    "sg:city":"Hickory",
    "sg:classifiers":[
        {
            "category":"Arena",
            "subcategory":"Sports Club",
            "type":"Entertainment"
        }
    ],
    "sg:phone":"+1   ",
    "sg:postcode":"28601",
    "sg:province":"NC",
    "wof:name":"Sons of Thunder Inc",
    "wof:placetype":"venue"
},
  "geometry": {"coordinates":[-81.30322099999999,35.756132],"type":"Point"}
}