{
  "type": "Feature",
  "properties": {
    "addr:full":"1030 Mill Creek Rd SE Bolivia NC 28422",
    "addr:housenumber":"1030",
    "addr:postcode":"28422",
    "addr:street":"Mill Creek Rd Se",
    "iso:country":"US",
    "sg:address":"1030 Mill Creek Rd SE",
    "sg:city":"Bolivia",
    "sg:classifiers":[
        {
            "category":"Professional",
            "subcategory":"Business Services",
            "type":"Services"
        }
    ],
    "sg:phone":"+1 910 253 3110",
    "sg:postcode":"28422",
    "sg:province":"NC",
    "sg:tags":[
        "event"
    ],
    "wof:name":"Coastal Events",
    "wof:placetype":"venue"
},
  "geometry": {"coordinates":[-78.091447,34.096016],"type":"Point"}
}