{
  "type": "Feature",
  "properties": {
    "addr:full":"2720 Hiking Trl Raleigh NC 27615",
    "addr:housenumber":"2720",
    "addr:postcode":"27615",
    "addr:street":"Hiking Trl",
    "iso:country":"US",
    "sg:address":"2720 Hiking Trl",
    "sg:city":"Raleigh",
    "sg:classifiers":[
        {
            "category":"Organizations",
            "subcategory":"Religious Organization",
            "type":"Services"
        }
    ],
    "sg:phone":"+1 919 844 4227",
    "sg:postcode":"27615",
    "sg:province":"NC",
    "sg:tags":[
        "church"
    ],
    "wof:name":"Northview Community Church",
    "wof:placetype":"venue"
},
  "geometry": {"coordinates":[-78.592511,35.8986],"type":"Point"}
}