{
  "type": "Feature",
  "properties": {
    "addr:full":"203 Prospect St Lexington NC 27292",
    "addr:housenumber":"203",
    "addr:postcode":"27292",
    "addr:street":"Prospect St",
    "iso:country":"US",
    "sg:address":"203 Prospect St",
    "sg:city":"Lexington",
    "sg:classifiers":[
        {
            "category":"Manufacturing",
            "subcategory":"Tools & Machinery",
            "type":"Manufacturing & Wholesale Goods"
        }
    ],
    "sg:phone":"+1 336 243 7659",
    "sg:postcode":"27292",
    "sg:province":"NC",
    "sg:tags":[
        "machine",
        "shop"
    ],
    "wof:name":"Precision Machine & Welding",
    "wof:placetype":"venue"
},
  "geometry": {"coordinates":[-80.276979,35.802584],"type":"Point"}
}