{
  "type": "Feature",
  "properties": {
    "addr:full":"2011 Crown Point Dr Albemarle NC 28001",
    "addr:housenumber":"2011",
    "addr:postcode":"28001",
    "addr:street":"Crown Point Dr",
    "iso:country":"US",
    "sg:address":"2011 Crown Point Dr",
    "sg:city":"Albemarle",
    "sg:classifiers":[
        {
            "category":"Wholesale",
            "subcategory":"Machinery & Supplies",
            "type":"Manufacturing & Wholesale Goods"
        }
    ],
    "sg:phone":"+1 704 983 3188",
    "sg:postcode":"28001",
    "sg:province":"NC",
    "sg:tags":[
        "equipment",
        "conveyor",
        "conveying"
    ],
    "wof:name":"Industrial Products",
    "wof:placetype":"venue"
},
  "geometry": {"coordinates":[-80.219396,35.342117],"type":"Point"}
}