{
  "type": "Feature",
  "properties": {
    "iso:country":"US",
    "sg:address":"1033 Dresser Ct",
    "sg:city":"Raleigh",
    "sg:classifiers":[
        {
            "category":"Shopping",
            "subcategory":"Clothing, Apparel, & Fashions",
            "type":"Retail Goods"
        }
    ],
    "sg:phone":"+1 919 876 5511",
    "sg:postcode":"27609",
    "sg:province":"NC",
    "wof:name":"Tom James of Raleigh 57",
    "wof:placetype":"venue"
},
  "geometry": {"coordinates":[-78.620015,35.833664],"type":"Point"}
}