{
  "type": "Feature",
  "properties": {
    "addr:full":"301 S McDowell St Charlotte NC 28204",
    "addr:housenumber":"301",
    "addr:postcode":"28204",
    "addr:street":"S Mcdowell St",
    "iso:country":"US",
    "sg:address":"301 S McDowell St",
    "sg:city":"Charlotte",
    "sg:classifiers":[
        {
            "category":"Professional",
            "subcategory":"Lawyer & Legal Services",
            "type":"Services"
        }
    ],
    "sg:phone":"+1 704 344 1116",
    "sg:postcode":"28204",
    "sg:province":"NC",
    "sg:tags":[
        "attorney"
    ],
    "wof:name":"Olsen Law Offices",
    "wof:placetype":"venue"
},
  "geometry": {"coordinates":[-80.838753,35.217794],"type":"Point"}
}