{
  "type": "Feature",
  "properties": {
    "iso:country":"US",
    "sg:address":"13512 Roxboro Rd",
    "sg:city":"Rougemont",
    "sg:classifiers":[
        {
            "category":"Retail",
            "subcategory":"Repair Shop",
            "type":"Services"
        }
    ],
    "sg:phone":"+1 919 732 9400",
    "sg:postcode":"27572",
    "sg:province":"NC",
    "sg:tags":[
        "ironwork"
    ],
    "wof:name":"Flat Bottom Iron Werks",
    "wof:placetype":"venue"
},
  "geometry": {"coordinates":[-78.93033200000001,36.227153],"type":"Point"}
}