{
  "type": "Feature",
  "properties": {
    "iso:country":"US",
    "sg:address":"112 Pheasant Wood Ct Ste A",
    "sg:city":"Morrisville",
    "sg:classifiers":[
        {
            "category":"Building & Trades",
            "subcategory":"Construction",
            "type":"Services"
        }
    ],
    "sg:phone":"+1 919 463 6773",
    "sg:postcode":"27560",
    "sg:province":"NC",
    "sg:tags":[
        "contractor"
    ],
    "wof:name":"Archer Western Contractors",
    "wof:placetype":"venue"
},
  "geometry": {"coordinates":[-78.820609,35.810544],"type":"Point"}
}