{
  "type": "Feature",
  "properties": {
    "iso:country":"US",
    "sg:address":"407 W Bessemer Ave",
    "sg:city":"Greensboro",
    "sg:classifiers":[
        {
            "category":"Health Services",
            "subcategory":"Clinic",
            "type":"Services"
        }
    ],
    "sg:phone":"+1   ",
    "sg:postcode":"27401",
    "sg:province":"NC",
    "wof:name":"SDMC",
    "wof:placetype":"venue"
},
  "geometry": {"coordinates":[-79.794427,36.08579],"type":"Point"}
}