{
  "type": "Feature",
  "properties": {
    "iso:country":"US",
    "sg:address":"119 S Water St",
    "sg:city":"Wilmington",
    "sg:classifiers":[
        {
            "category":"Manufacturing",
            "subcategory":"Soap",
            "type":"Manufacturing & Wholesale Goods"
        }
    ],
    "sg:phone":"+1 910 343 9878",
    "sg:postcode":"28401",
    "sg:province":"NC",
    "sg:tags":[
        "detergent"
    ],
    "wof:name":"Out Of Eden Soaps",
    "wof:placetype":"venue"
},
  "geometry": {"coordinates":[-77.94938,34.234051],"type":"Point"}
}