{
  "type": "Feature",
  "properties": {
    "iso:country":"US",
    "sg:address":"923 Orient St",
    "sg:city":"Durham",
    "sg:classifiers":[
        {
            "category":"Professional",
            "type":"Services"
        }
    ],
    "sg:phone":"+1 919 956 7176",
    "sg:postcode":"27701",
    "sg:province":"NC",
    "wof:name":"Life Enhancement Svc",
    "wof:placetype":"venue"
},
  "geometry": {"coordinates":[-78.901804,36.007214],"type":"Point"}
}