{
  "type": "Feature",
  "properties": {
    "addr:full":"113 Kilborne Rd Mooresville NC 28117",
    "addr:housenumber":"113",
    "addr:postcode":"28117",
    "addr:street":"Kilborne Rd",
    "iso:country":"US",
    "sg:address":"113 Kilborne Rd",
    "sg:city":"Mooresville",
    "sg:classifiers":[
        {
            "category":"Banks & Credit Unions",
            "subcategory":"Bank",
            "type":"Services"
        }
    ],
    "sg:phone":"+1 704 663 1762",
    "sg:postcode":"28117",
    "sg:province":"NC",
    "sg:tags":[
        "personal",
        "institution"
    ],
    "wof:name":"PM Funding Inc",
    "wof:placetype":"venue"
},
  "geometry": {"coordinates":[-80.90143500000001,35.581988],"type":"Point"}
}