{
  "type": "Feature",
  "properties": {
    "addr:full":"8129 Blairtree Ct Charlotte NC 28227",
    "addr:housenumber":"8129",
    "addr:postcode":"28227",
    "addr:street":"Blairtree Ct",
    "iso:country":"US",
    "sg:address":"8129 Blairtree Ct",
    "sg:city":"Charlotte",
    "sg:classifiers":[
        {
            "category":"Building & Trades",
            "subcategory":"Construction",
            "type":"Services"
        }
    ],
    "sg:phone":"+1 704 532 5668",
    "sg:postcode":"28227",
    "sg:province":"NC",
    "sg:tags":[
        "home",
        "remodeling",
        "repair"
    ],
    "wof:name":"R A Bohling Construction",
    "wof:placetype":"venue"
},
  "geometry": {"coordinates":[-80.70105100000001,35.197124],"type":"Point"}
}