{
  "type": "Feature",
  "properties": {
    "iso:country":"US",
    "sg:address":"824 Fontana Blvd",
    "sg:city":"Havelock",
    "sg:classifiers":[
        {
            "category":"Manufacturing",
            "subcategory":"Metals",
            "type":"Manufacturing & Wholesale Goods"
        }
    ],
    "sg:phone":"+1 252 447 7155",
    "sg:postcode":"28532",
    "sg:province":"NC",
    "sg:tags":[
        "steel"
    ],
    "sg:website":"www.targetloc.com",
    "wof:name":"Tandemloc Inc",
    "wof:placetype":"venue"
},
  "geometry": {"coordinates":[-76.87494100000001,34.882228],"type":"Point"}
}