{
  "type": "Feature",
  "properties": {
    "addr:full":"4203 Fallston Rd Shelby NC 28150",
    "addr:housenumber":"4203",
    "addr:postcode":"28150",
    "addr:street":"Fallston Rd",
    "iso:country":"US",
    "sg:address":"4203 Fallston Rd",
    "sg:city":"Shelby",
    "sg:classifiers":[
        {
            "category":"Wholesale",
            "subcategory":"Machinery & Supplies",
            "type":"Manufacturing & Wholesale Goods"
        }
    ],
    "sg:phone":"+1 704 538 1094",
    "sg:postcode":"28150",
    "sg:province":"NC",
    "sg:tags":[
        "farm",
        "equipment"
    ],
    "wof:name":"Absolute Poultry Equipment",
    "wof:placetype":"venue"
},
  "geometry": {"coordinates":[-81.502731,35.40827],"type":"Point"}
}