{
  "type": "Feature",
  "properties": {
    "addr:full":"3601 Matthews-Mint Hill Rd Matthews NC 28105",
    "addr:housenumber":"3601",
    "addr:postcode":"28105",
    "addr:street":"Matthews-Mint Hill Rd",
    "iso:country":"US",
    "sg:address":"3601 Matthews-Mint Hill Rd",
    "sg:city":"Matthews",
    "sg:classifiers":[
        {
            "category":"Banks & Credit Unions",
            "subcategory":"Bank",
            "type":"Services"
        }
    ],
    "sg:phone":"+1 704 841 9410",
    "sg:postcode":"28105",
    "sg:province":"NC",
    "sg:tags":[
        "personal",
        "financing",
        "institution"
    ],
    "wof:name":"Citi Financial",
    "wof:placetype":"venue"
},
  "geometry": {"coordinates":[-80.68307299999999,35.138399],"type":"Point"}
}