{
  "type": "Feature",
  "properties": {
    "addr:full":"403 Fox Ridge Rd Warsaw NC 28398",
    "addr:housenumber":"403",
    "addr:postcode":"28398",
    "addr:street":"Fox Ridge Rd",
    "iso:country":"US",
    "sg:address":"403 Fox Ridge Rd",
    "sg:city":"Warsaw",
    "sg:classifiers":[
        {
            "category":"Farming",
            "subcategory":"Livestock Farm",
            "type":"Manufacturing & Wholesale Goods"
        }
    ],
    "sg:phone":"+1 910 293 4017",
    "sg:postcode":"28398",
    "sg:province":"NC",
    "sg:tags":[
        "animal",
        "general"
    ],
    "wof:name":"Briarwood Farms of Warsaw",
    "wof:placetype":"venue"
},
  "geometry": {"coordinates":[-78.053963,34.996716],"type":"Point"}
}