{
  "type": "Feature",
  "properties": {
    "iso:country":"US",
    "sg:address":"2504 Ivey Church Rd",
    "sg:city":"Lincolnton",
    "sg:classifiers":[
        {
            "category":"Real Estate",
            "subcategory":"Real Estate Agent",
            "type":"Services"
        }
    ],
    "sg:phone":"+1 704 735 3422",
    "sg:postcode":"28092",
    "sg:province":"NC",
    "wof:name":"Lqr Company",
    "wof:placetype":"venue"
},
  "geometry": {"coordinates":[-81.137771,35.532978],"type":"Point"}
}