{
  "type": "Feature",
  "properties": {
    "addr:full":"410 Oberlin Rd Raleigh NC 27605",
    "addr:housenumber":"410",
    "addr:postcode":"27605",
    "addr:street":"Oberlin Rd",
    "iso:country":"US",
    "sg:address":"410 Oberlin Rd",
    "sg:city":"Raleigh",
    "sg:classifiers":[
        {
            "category":"Real Estate",
            "subcategory":"Architect",
            "type":"Services"
        }
    ],
    "sg:phone":"+1 919 839 5554",
    "sg:postcode":"27605",
    "sg:province":"NC",
    "sg:tags":[
        "architectural"
    ],
    "wof:name":"Fieldstudio",
    "wof:placetype":"venue"
},
  "geometry": {"coordinates":[-78.662862,35.790196],"type":"Point"}
}