{
  "type": "Feature",
  "properties": {
    "addr:full":"2400 Crown Centre Dr Charlotte NC 28227",
    "addr:housenumber":"2400",
    "addr:postcode":"28227",
    "addr:street":"Crown Centre Dr",
    "iso:country":"US",
    "sg:address":"2400 Crown Centre Dr",
    "sg:city":"Charlotte",
    "sg:classifiers":[
        {
            "category":"Fast Food",
            "type":"Food & Drink"
        },
        {
            "category":"Restaurant",
            "type":"Food & Drink"
        }
    ],
    "sg:phone":"+1 704 846 1749",
    "sg:postcode":"28227",
    "sg:province":"NC",
    "sg:tags":[
        "hamburger",
        "hot",
        "dog",
        "american",
        "take",
        "chicken"
    ],
    "wof:name":"Mcdonald's",
    "wof:placetype":"venue"
},
  "geometry": {"coordinates":[-80.73195,35.145072],"type":"Point"}
}