{
  "type": "Feature",
  "properties": {
    "addr:full":"3528 Arlington St Durham NC 27707",
    "addr:housenumber":"3528",
    "addr:postcode":"27707",
    "addr:street":"Arlington St",
    "iso:country":"US",
    "sg:address":"3528 Arlington St",
    "sg:city":"Durham",
    "sg:classifiers":[
        {
            "category":"Social Services",
            "subcategory":"Child Care",
            "type":"Services"
        }
    ],
    "sg:phone":"+1 919 683 5526",
    "sg:postcode":"27707",
    "sg:province":"NC",
    "wof:name":"Treasures Of Joy Christian",
    "wof:placetype":"venue"
},
  "geometry": {"coordinates":[-78.907645,35.955184],"type":"Point"}
}