{
  "type": "Feature",
  "properties": {
    "addr:full":"1106 E Market St Greensboro NC 27401",
    "addr:housenumber":"1106",
    "addr:postcode":"27401",
    "addr:street":"E Market St",
    "iso:country":"US",
    "sg:address":"1106 E Market St",
    "sg:city":"Greensboro",
    "sg:classifiers":[
        {
            "category":"Professional",
            "subcategory":"Lawyer & Legal Services",
            "type":"Services"
        }
    ],
    "sg:phone":"+1 336 273 1698",
    "sg:postcode":"27401",
    "sg:province":"NC",
    "sg:tags":[
        "attorney"
    ],
    "wof:name":"Romallus O Murphy",
    "wof:placetype":"venue"
},
  "geometry": {"coordinates":[-79.773726,36.071765],"type":"Point"}
}