{
  "type": "Feature",
  "properties": {
    "iso:country":"US",
    "sg:address":"1023 S Caldwell St",
    "sg:city":"Charlotte",
    "sg:classifiers":[
        {
            "category":"Banks & Credit Unions",
            "subcategory":"Bank",
            "type":"Services"
        }
    ],
    "sg:phone":"+1 704 370 0916",
    "sg:postcode":"28203",
    "sg:province":"NC",
    "sg:tags":[
        "loan",
        "real estate"
    ],
    "wof:name":"HCI Mortgage Inc",
    "wof:placetype":"venue"
},
  "geometry": {"coordinates":[-80.849008,35.21674],"type":"Point"}
}