{
  "type": "Feature",
  "properties": {
    "iso:country":"US",
    "sg:address":"1285 N Brightleaf Blvd",
    "sg:city":"Smithfield",
    "sg:classifiers":[
        {
            "category":"Shopping",
            "subcategory":"Clothing, Apparel, & Fashions",
            "type":"Retail Goods"
        }
    ],
    "sg:phone":"+1 919 934 8343",
    "sg:postcode":"27577",
    "sg:province":"NC",
    "sg:tags":[
        "accessory"
    ],
    "wof:name":"Cato Fashion",
    "wof:placetype":"venue"
},
  "geometry": {"coordinates":[-78.30696399999999,35.521248],"type":"Point"}
}