{
  "type": "Feature",
  "properties": {
    "addr:full":"5100 US Hwy 70 E Princeton NC 27569",
    "addr:housenumber":"5100",
    "addr:postcode":"27569",
    "addr:street":"Us Hwy 70 E",
    "iso:country":"US",
    "sg:address":"5100 US Hwy 70 E",
    "sg:city":"Princeton",
    "sg:classifiers":[
        {
            "category":"Shopping",
            "subcategory":"Bicycles & Sporting Goods",
            "type":"Retail Goods"
        }
    ],
    "sg:phone":"+1 919 975 0760",
    "sg:postcode":"27569",
    "sg:province":"NC",
    "sg:tags":[
        "bait",
        "fishing"
    ],
    "wof:name":"Reel Time Tackle and Tours",
    "wof:placetype":"venue"
},
  "geometry": {"coordinates":[-78.222092,35.473637],"type":"Point"}
}