{
  "type": "Feature",
  "properties": {
    "addr:full":"6833 Turnipseed Rd Wendell NC 27591",
    "addr:postcode":"6833;27591",
    "addr:street":"Turnipseed Rd",
    "iso:country":"US",
    "sg:address":"6833 Turnipseed Rd",
    "sg:city":"Wendell",
    "sg:classifiers":[
        {
            "category":"Real Estate",
            "subcategory":"Surveying",
            "type":"Services"
        }
    ],
    "sg:phone":"+1 919 366 3438",
    "sg:postcode":"27591",
    "sg:province":"NC",
    "sg:tags":[
        "surveyor"
    ],
    "wof:name":"Joyner Surveying Inc",
    "wof:placetype":"venue"
},
  "geometry": {"coordinates":[-78.420547,35.73812],"type":"Point"}
}