{
  "type": "Feature",
  "properties": {
    "addr:full":"474 State St Marion NC 28752",
    "addr:housenumber":"474",
    "addr:postcode":"28752",
    "addr:street":"State St",
    "iso:country":"US",
    "sg:address":"474 State St",
    "sg:city":"Marion",
    "sg:classifiers":[
        {
            "category":"Social Services",
            "subcategory":"Child Care",
            "type":"Services"
        }
    ],
    "sg:phone":"+1 828 652 9630",
    "sg:postcode":"28752",
    "sg:province":"NC",
    "wof:name":"Mc Dowell County Childrens Ctr",
    "wof:placetype":"venue"
},
  "geometry": {"coordinates":[-81.999888,35.685875],"type":"Point"}
}