{
  "type": "Feature",
  "properties": {
    "addr:full":"4640 Rockingham Rd Laurel Hill NC 28351",
    "addr:housenumber":"4640",
    "addr:postcode":"28351",
    "addr:street":"Rockingham Rd",
    "iso:country":"US",
    "sg:address":"4640 Rockingham Rd",
    "sg:city":"Laurel Hill",
    "sg:classifiers":[
        {
            "category":"Freight",
            "type":"Transportation"
        }
    ],
    "sg:phone":"+1 910 268 9991",
    "sg:postcode":"28351",
    "sg:province":"NC",
    "sg:tags":[
        "operator",
        "trucking"
    ],
    "wof:name":"Cox Trucking",
    "wof:placetype":"venue"
},
  "geometry": {"coordinates":[-79.622895,34.816698],"type":"Point"}
}