{
  "type": "Feature",
  "properties": {
    "iso:country":"US",
    "sg:address":"1101 Slater Rd",
    "sg:city":"Durham",
    "sg:classifiers":[
        {
            "category":"Professional",
            "subcategory":"Lawyer & Legal Services",
            "type":"Services"
        }
    ],
    "sg:phone":"+1   ",
    "sg:postcode":"27703",
    "sg:province":"NC",
    "wof:name":"Schenck James S IV",
    "wof:placetype":"venue"
},
  "geometry": {"coordinates":[-78.8437,35.87798],"type":"Point"}
}