{
  "type": "Feature",
  "properties": {
    "addr:full":"1798 Farmington Rd Mocksville NC 27028",
    "addr:housenumber":"1798",
    "addr:postcode":"27028",
    "addr:street":"Farmington Rd",
    "iso:country":"US",
    "sg:address":"1798 Farmington Rd",
    "sg:city":"Mocksville",
    "sg:classifiers":[
        {
            "category":"Organizations",
            "subcategory":"Religious Organization",
            "type":"Services"
        }
    ],
    "sg:phone":"+1   ",
    "sg:postcode":"27028",
    "sg:province":"NC",
    "wof:name":"Bethel Forge",
    "wof:placetype":"venue"
},
  "geometry": {"coordinates":[-80.532106,36.011526],"type":"Point"}
}