{
  "type": "Feature",
  "properties": {
    "iso:country":"US",
    "sg:address":"151 Central St",
    "sg:city":"Rutherfordton",
    "sg:classifiers":[
        {
            "category":"Bars & Pubs",
            "type":"Food & Drink"
        }
    ],
    "sg:phone":"+1 828 287 1305",
    "sg:postcode":"28146",
    "sg:province":"NC",
    "sg:tags":[
        "drinking",
        "eating"
    ],
    "sg:website":"www.thekodiak.com",
    "wof:name":"Kodiak",
    "wof:placetype":"venue"
},
  "geometry": {"coordinates":[-80.420777,35.57365],"type":"Point"}
}