{
  "type": "Feature",
  "properties": {
    "iso:country":"US",
    "sg:address":"4008 Capital Blvd",
    "sg:city":"Raleigh",
    "sg:classifiers":[
        {
            "category":"Banks & Credit Unions",
            "subcategory":"Bank",
            "type":"Services"
        }
    ],
    "sg:phone":"+1 919 878 0904",
    "sg:postcode":"27604",
    "sg:province":"NC",
    "sg:tags":[
        "federal",
        "agency"
    ],
    "wof:name":"SLM Financial Corp",
    "wof:placetype":"venue"
},
  "geometry": {"coordinates":[-78.580805,35.837873],"type":"Point"}
}