{
  "type": "Feature",
  "properties": {
    "iso:country":"US",
    "sg:address":"154 Cumberland Rd",
    "sg:city":"Statesville",
    "sg:classifiers":[
        {
            "category":"Organizations",
            "subcategory":"Community Association",
            "type":"Services"
        }
    ],
    "sg:phone":"+1 704 881 0292",
    "sg:postcode":"28677",
    "sg:province":"NC",
    "sg:tags":[
        "club"
    ],
    "wof:name":"Amvets Post 895",
    "wof:placetype":"venue"
},
  "geometry": {"coordinates":[-80.89453,35.742471],"type":"Point"}
}