{
  "type": "Feature",
  "properties": {
    "addr:full":"109 State Rd 903 Kenansville NC 28349",
    "addr:housenumber":"109",
    "addr:postcode":"28349",
    "addr:street":"State Rd 903",
    "iso:country":"US",
    "sg:address":"109 State Rd 903",
    "sg:city":"Kenansville",
    "sg:classifiers":[
        {
            "category":"Home & Garden",
            "subcategory":"Hardware",
            "type":"Retail Goods"
        }
    ],
    "sg:phone":"+1 910 296 0296",
    "sg:postcode":"28349",
    "sg:province":"NC",
    "sg:tags":[
        "grading",
        "contractor"
    ],
    "wof:name":"Dunn Hardware",
    "wof:placetype":"venue"
},
  "geometry": {"coordinates":[-77.96294,34.961928],"type":"Point"}
}