{
  "type": "Feature",
  "properties": {
    "addr:full":"170 Park Dr Mocksville NC 27028",
    "addr:housenumber":"170",
    "addr:postcode":"27028",
    "addr:street":"Park Dr",
    "iso:country":"US",
    "sg:address":"170 Park Dr",
    "sg:city":"Mocksville",
    "sg:classifiers":[
        {
            "category":"Health Services",
            "subcategory":"Doctor",
            "type":"Services"
        }
    ],
    "sg:phone":"+1   ",
    "sg:postcode":"27028",
    "sg:province":"NC",
    "sg:tags":[
        "medical"
    ],
    "wof:name":"Salem Orthopaedic & Sports Med",
    "wof:placetype":"venue"
},
  "geometry": {"coordinates":[-80.558384,35.902722],"type":"Point"}
}