{
  "type": "Feature",
  "properties": {
    "addr:full":"400 Four Seasons Town Center Greensboro NC 27407",
    "addr:housenumber":"400",
    "addr:postcode":"27407",
    "addr:street":"Four Seasons",
    "iso:country":"US",
    "sg:address":"400 Four Seasons Town Center",
    "sg:city":"Greensboro",
    "sg:classifiers":[
        {
            "category":"Shopping",
            "subcategory":"Shoes",
            "type":"Retail Goods"
        }
    ],
    "sg:phone":"+1 336 294 6331",
    "sg:postcode":"27407",
    "sg:province":"NC",
    "sg:website":"www.footaction.com",
    "wof:name":"Footaction",
    "wof:placetype":"venue"
},
  "geometry": {"coordinates":[-79.840008,36.038607],"type":"Point"}
}