{
  "type": "Feature",
  "properties": {
    "iso:country":"US",
    "sg:address":"145 Lutomma Cir",
    "sg:city":"Charlotte",
    "sg:classifiers":[
        {
            "category":"Real Estate",
            "subcategory":"Real Estate Agent",
            "type":"Services"
        }
    ],
    "sg:phone":"+1 704 365 2254",
    "sg:postcode":"28270",
    "sg:province":"NC",
    "wof:name":"King Oil Company Inc",
    "wof:placetype":"venue"
},
  "geometry": {"coordinates":[-80.773428,35.14775],"type":"Point"}
}