{
  "type": "Feature",
  "properties": {
    "addr:full":"122 E Pine St Graham NC 27253",
    "addr:housenumber":"122",
    "addr:postcode":"27253",
    "addr:street":"E Pine St",
    "iso:country":"US",
    "sg:address":"122 E Pine St",
    "sg:city":"Graham",
    "sg:classifiers":[
        {
            "category":"Health Services",
            "subcategory":"Hospital",
            "type":"Services"
        }
    ],
    "sg:phone":"+1 336 229 5905",
    "sg:postcode":"27253",
    "sg:province":"NC",
    "sg:tags":[
        "mental"
    ],
    "wof:name":"Triumph",
    "wof:placetype":"venue"
},
  "geometry": {"coordinates":[-79.398996,36.067998],"type":"Point"}
}