{
  "type": "Feature",
  "properties": {
    "addr:full":"2813 Village Way Trent Woods NC 28562",
    "addr:housenumber":"2813",
    "addr:postcode":"28562",
    "addr:street":"Village Way Trent",
    "iso:country":"US",
    "sg:address":"2813 Village Way",
    "sg:city":"Trent Woods",
    "sg:classifiers":[
        {
            "category":"Professional",
            "subcategory":"Accounting & Tax Preparation",
            "type":"Services"
        }
    ],
    "sg:phone":"+1 252 633 5400",
    "sg:postcode":"28562",
    "sg:province":"NC",
    "sg:tags":[
        "accountant"
    ],
    "wof:name":"James C Briley Jr CPA",
    "wof:placetype":"venue"
},
  "geometry": {"coordinates":[-77.07048,35.084339],"type":"Point"}
}