{
  "type": "Feature",
  "properties": {
    "iso:country":"US",
    "sg:address":"2829 Reynolds Park Rd",
    "sg:city":"Winston Salem",
    "sg:classifiers":[
        {
            "category":"Manufacturing",
            "subcategory":"Metals",
            "type":"Manufacturing & Wholesale Goods"
        }
    ],
    "sg:phone":"+1 336 784 9051",
    "sg:postcode":"27107",
    "sg:province":"NC",
    "sg:tags":[
        "tower"
    ],
    "wof:name":"Piedmont Tower Maintenance",
    "wof:placetype":"venue"
},
  "geometry": {"coordinates":[-80.190836,36.08366],"type":"Point"}
}