{
  "type": "Feature",
  "properties": {
    "iso:country":"US",
    "sg:address":"2158 John B Carter Rd",
    "sg:city":"Fayetteville",
    "sg:classifiers":[
        {
            "category":"Place Of Worship",
            "type":"Public Place"
        },
        {
            "category":"Place Of Worship",
            "subcategory":"Temple",
            "type":"Public Place"
        }
    ],
    "sg:phone":"+1 910 323 2717",
    "sg:postcode":"28312",
    "sg:province":"NC",
    "sg:tags":[
        "church"
    ],
    "wof:name":"Deliverance Temple Christian 4",
    "wof:placetype":"venue"
},
  "geometry": {"coordinates":[-78.780509,34.992211],"type":"Point"}
}