{
  "type": "Feature",
  "properties": {
    "addr:full":"3350 Butler Nursery Rd Fayetteville NC 28306",
    "addr:housenumber":"3350",
    "addr:postcode":"28306",
    "addr:street":"Butler Nursery Rd",
    "iso:country":"US",
    "sg:address":"3350 Butler Nursery Rd",
    "sg:city":"Fayetteville",
    "sg:classifiers":[
        {
            "category":"Organizations",
            "subcategory":"Religious Organization",
            "type":"Services"
        }
    ],
    "sg:phone":"+1 910 485 5681",
    "sg:postcode":"28306",
    "sg:province":"NC",
    "sg:tags":[
        "baptist",
        "church"
    ],
    "wof:name":"Mount Pisgah Baptist Church",
    "wof:placetype":"venue"
},
  "geometry": {"coordinates":[-78.839253,34.953775],"type":"Point"}
}