{
  "type": "Feature",
  "properties": {
    "addr:full":"4939 S Main St Salisbury NC 28147",
    "addr:housenumber":"4939",
    "addr:postcode":"28147",
    "addr:street":"S Main St",
    "iso:country":"US",
    "sg:address":"4939 S Main St",
    "sg:city":"Salisbury",
    "sg:classifiers":[
        {
            "category":"Bars & Pubs",
            "type":"Food & Drink"
        }
    ],
    "sg:phone":"+1 704 633 8349",
    "sg:postcode":"28147",
    "sg:province":"NC",
    "sg:tags":[
        "drinking"
    ],
    "wof:name":"Foxy Lady",
    "wof:placetype":"venue"
},
  "geometry": {"coordinates":[-80.534677,35.61602],"type":"Point"}
}