{
  "type": "Feature",
  "properties": {
    "addr:full":"36 Gatewood Rd Asheville NC 28806",
    "addr:housenumber":"36",
    "addr:postcode":"28806",
    "addr:street":"Gatewood Rd",
    "iso:country":"US",
    "sg:address":"36 Gatewood Rd",
    "sg:city":"Asheville",
    "sg:classifiers":[
        {
            "category":"Social Services",
            "type":"Services"
        }
    ],
    "sg:phone":"+1 828 301 5298",
    "sg:postcode":"28806",
    "sg:province":"NC",
    "sg:tags":[
        "organization",
        "welfare"
    ],
    "wof:name":"Slavic Resource Ctr",
    "wof:placetype":"venue"
},
  "geometry": {"coordinates":[-82.597404,35.59866],"type":"Point"}
}