{
  "type": "Feature",
  "properties": {
    "addr:full":"420 Stadium Dr Wake Forest NC 27587",
    "addr:housenumber":"420",
    "addr:postcode":"27587",
    "addr:street":"Stadium Dr",
    "iso:country":"US",
    "sg:address":"420 Stadium Dr",
    "sg:city":"Wake Forest",
    "sg:classifiers":[
        {
            "category":"Education",
            "subcategory":"School",
            "type":"Public Place"
        }
    ],
    "sg:phone":"+1 919 554 8611",
    "sg:postcode":"27587",
    "sg:province":"NC",
    "sg:website":"www.wfrhs.net",
    "wof:name":"Wake Forest-Rolesville High",
    "wof:placetype":"venue"
},
  "geometry": {"coordinates":[-78.517628,35.983694],"type":"Point"}
}