{
  "type": "Feature",
  "properties": {
    "iso:country":"US",
    "sg:address":"120 Scarboro St",
    "sg:city":"Asheboro",
    "sg:classifiers":[
        {
            "category":"Professional",
            "subcategory":"Credit Reporting & Collection",
            "type":"Services"
        }
    ],
    "sg:phone":"+1 336 636 5114",
    "sg:postcode":"27203",
    "sg:province":"NC",
    "sg:tags":[
        "real estate"
    ],
    "wof:name":"Dorie Twiford Real Estate",
    "wof:placetype":"venue"
},
  "geometry": {"coordinates":[-79.813766,35.704869],"type":"Point"}
}