{
  "type": "Feature",
  "properties": {
    "addr:full":"415 Greensboro Rd Crumpler NC 28617",
    "addr:housenumber":"415",
    "addr:postcode":"28617",
    "addr:street":"Greensboro Rd",
    "iso:country":"US",
    "sg:address":"415 Greensboro Rd",
    "sg:city":"Crumpler",
    "sg:classifiers":[
        {
            "category":"Restaurant",
            "type":"Food & Drink"
        }
    ],
    "sg:phone":"+1 336 982 2196",
    "sg:postcode":"28617",
    "sg:province":"NC",
    "wof:name":"Tea Room",
    "wof:placetype":"venue"
},
  "geometry": {"coordinates":[-81.40617,36.447078],"type":"Point"}
}