{
  "type": "Feature",
  "properties": {
    "addr:full":"90 Old Shoals Rd Arden NC 28704",
    "addr:housenumber":"90",
    "addr:postcode":"28704",
    "addr:street":"Old Shoals Rd",
    "iso:country":"US",
    "sg:address":"90 Old Shoals Rd",
    "sg:city":"Arden",
    "sg:classifiers":[
        {
            "category":"Freight",
            "type":"Transportation"
        }
    ],
    "sg:phone":"+1 828 684 4855",
    "sg:postcode":"28704",
    "sg:province":"NC",
    "sg:tags":[
        "operator",
        "trucking"
    ],
    "sg:website":"www.myyellow.com",
    "wof:name":"Yellow Transportation Inc",
    "wof:placetype":"venue"
},
  "geometry": {"coordinates":[-82.526816,35.468316],"type":"Point"}
}