{
  "type": "Feature",
  "properties": {
    "iso:country":"US",
    "sg:address":"4180 Abbington Ter",
    "sg:city":"Wilmington",
    "sg:classifiers":[
        {
            "category":"Building & Trades",
            "subcategory":"Landscaping Services",
            "type":"Services"
        }
    ],
    "sg:phone":"+1 910 452 3531",
    "sg:postcode":"28403",
    "sg:province":"NC",
    "sg:tags":[
        "landscape"
    ],
    "wof:name":"Southern Landscaping",
    "wof:placetype":"venue"
},
  "geometry": {"coordinates":[-77.893627,34.20272],"type":"Point"}
}