{
  "type": "Feature",
  "properties": {
    "iso:country":"US",
    "sg:address":"199 Fairground Ave",
    "sg:city":"Hendersonville",
    "sg:classifiers":[
        {
            "category":"Building & Trades",
            "subcategory":"Plumbing",
            "type":"Services"
        }
    ],
    "sg:phone":"+1 828 692 2446",
    "sg:postcode":"28792",
    "sg:province":"NC",
    "sg:tags":[
        "contractor"
    ],
    "wof:name":"Quality Plumbing Repair",
    "wof:placetype":"venue"
},
  "geometry": {"coordinates":[-82.425557,35.298739],"type":"Point"}
}