{
  "type": "Feature",
  "properties": {
    "iso:country":"US",
    "sg:address":"4813 Atlantis Ct",
    "sg:city":"Wilmington",
    "sg:classifiers":[
        {
            "category":"Professional",
            "type":"Services"
        }
    ],
    "sg:phone":"+1 910 790 5879",
    "sg:postcode":"28403",
    "sg:province":"NC",
    "sg:tags":[
        "establishment"
    ],
    "wof:name":"Preferred Alternatives",
    "wof:placetype":"venue"
},
  "geometry": {"coordinates":[-77.88039000000001,34.218569],"type":"Point"}
}