{
  "type": "Feature",
  "properties": {
    "addr:full":"509 Brookdale Dr Statesville NC 28677",
    "addr:housenumber":"509",
    "addr:postcode":"28677",
    "addr:street":"Brookdale Dr",
    "iso:country":"US",
    "sg:address":"509 Brookdale Dr",
    "sg:city":"Statesville",
    "sg:classifiers":[
        {
            "category":"Health Services",
            "subcategory":"Doctor",
            "type":"Services"
        }
    ],
    "sg:phone":"+1 704 872 6343",
    "sg:postcode":"28677",
    "sg:province":"NC",
    "sg:tags":[
        "medical"
    ],
    "wof:name":"Walters Henry C Jr MD",
    "wof:placetype":"venue"
},
  "geometry": {"coordinates":[-80.876948,35.801228],"type":"Point"}
}