{
  "type": "Feature",
  "properties": {
    "addr:full":"308 Component Dr Smithfield NC 27577",
    "addr:housenumber":"308",
    "addr:postcode":"27577",
    "addr:street":"Component Dr",
    "iso:country":"US",
    "sg:address":"308 Component Dr",
    "sg:city":"Smithfield",
    "sg:classifiers":[
        {
            "category":"Manufacturing",
            "subcategory":"Tools & Machinery",
            "type":"Manufacturing & Wholesale Goods"
        }
    ],
    "sg:phone":"+1 919 934 3135",
    "sg:postcode":"27577",
    "sg:province":"NC",
    "sg:tags":[
        "switch"
    ],
    "sg:website":"www.shallco.com",
    "wof:name":"Shallco",
    "wof:placetype":"venue"
},
  "geometry": {"coordinates":[-78.312112,35.513178],"type":"Point"}
}