{
  "type": "Feature",
  "properties": {
    "iso:country":"US",
    "sg:address":"2220 Warrenton Rd",
    "sg:city":"Henderson",
    "sg:classifiers":[
        {
            "category":"Personal",
            "subcategory":"Beauty Salon",
            "type":"Services"
        }
    ],
    "sg:phone":"+1 252 433 8065",
    "sg:postcode":"27537",
    "sg:province":"NC",
    "wof:name":"Ellen's Beauty Spot",
    "wof:placetype":"venue"
},
  "geometry": {"coordinates":[-78.34334699999999,36.353097],"type":"Point"}
}