{
  "type": "Feature",
  "properties": {
    "iso:country":"US",
    "sg:address":"2040 Ridge Rd",
    "sg:city":"Raleigh",
    "sg:classifiers":[
        {
            "category":"Professional",
            "subcategory":"Lawyer & Legal Services",
            "type":"Services"
        }
    ],
    "sg:phone":"+1 919 786 0964",
    "sg:postcode":"27607",
    "sg:province":"NC",
    "wof:name":"Olson Kurt J Atty",
    "wof:placetype":"venue"
},
  "geometry": {"coordinates":[-78.67800099999999,35.818901],"type":"Point"}
}