{
  "type": "Feature",
  "properties": {
    "addr:full":"203 Bradshaw St Clinton NC 28328",
    "addr:housenumber":"203",
    "addr:postcode":"28328",
    "addr:street":"Bradshaw St",
    "iso:country":"US",
    "sg:address":"203 Bradshaw St",
    "sg:city":"Clinton",
    "sg:classifiers":[
        {
            "category":"Personal",
            "type":"Services"
        }
    ],
    "sg:phone":"+1   ",
    "sg:postcode":"28328",
    "sg:province":"NC",
    "wof:name":"Tipton Services Inc",
    "wof:placetype":"venue"
},
  "geometry": {"coordinates":[-78.318275,35.014117],"type":"Point"}
}