{
  "type": "Feature",
  "properties": {
    "iso:country":"US",
    "sg:address":"180 Dick Baker Rd",
    "sg:city":"Louisburg",
    "sg:classifiers":[
        {
            "category":"Building & Trades",
            "subcategory":"Construction",
            "type":"Services"
        }
    ],
    "sg:phone":"+1 919 496 5804",
    "sg:postcode":"27549",
    "sg:province":"NC",
    "sg:tags":[
        "carpentry",
        "contractor"
    ],
    "wof:name":"Commercial Concepts",
    "wof:placetype":"venue"
},
  "geometry": {"coordinates":[-78.295984,36.017911],"type":"Point"}
}