{
  "type": "Feature",
  "properties": {
    "iso:country":"US",
    "sg:address":"375 Pinehurst Ave",
    "sg:city":"Southern Pines",
    "sg:classifiers":[
        {
            "category":"Travel",
            "subcategory":"Travel Agent",
            "type":"Entertainment"
        }
    ],
    "sg:phone":"+1 910 692 7077",
    "sg:postcode":"28387",
    "sg:province":"NC",
    "sg:tags":[
        "agency",
        "bureau"
    ],
    "wof:name":"A Travel Ctr",
    "wof:placetype":"venue"
},
  "geometry": {"coordinates":[-79.4182,35.160994],"type":"Point"}
}