{
  "type": "Feature",
  "properties": {
    "addr:full":"739 Hicksboro Rd Henderson NC 27537",
    "addr:housenumber":"739",
    "addr:postcode":"27537",
    "addr:street":"Hicksboro Rd",
    "iso:country":"US",
    "sg:address":"739 Hicksboro Rd",
    "sg:city":"Henderson",
    "sg:classifiers":[
        {
            "category":"Retail",
            "subcategory":"Animal Services",
            "type":"Services"
        }
    ],
    "sg:phone":"+1 252 492 0396",
    "sg:postcode":"27537",
    "sg:province":"NC",
    "sg:tags":[
        "pet",
        "grooming",
        "washing"
    ],
    "wof:name":"Barbara Dillard Pet Grooming",
    "wof:placetype":"venue"
},
  "geometry": {"coordinates":[-78.462733,36.364234],"type":"Point"}
}