{
  "type": "Feature",
  "properties": {
    "iso:country":"US",
    "sg:address":"333 Jeremiah Blvd",
    "sg:city":"Charlotte",
    "sg:classifiers":[
        {
            "category":"Real Estate",
            "subcategory":"Developer",
            "type":"Services"
        }
    ],
    "sg:phone":"+1 704 596 5417",
    "sg:postcode":"28262",
    "sg:province":"NC",
    "sg:tags":[
        "cemetery"
    ],
    "wof:name":"Gethsemane Memorial Gardens",
    "wof:placetype":"venue"
},
  "geometry": {"coordinates":[-80.78382499999999,35.283348],"type":"Point"}
}