{
  "type": "Feature",
  "properties": {
    "addr:full":"8999 Lasater Rd Clemmons NC 27012",
    "addr:housenumber":"8999",
    "addr:postcode":"27012",
    "addr:street":"Lasater Rd",
    "iso:country":"US",
    "sg:address":"8999 Lasater Rd",
    "sg:city":"Clemmons",
    "sg:classifiers":[
        {
            "category":"Organizations",
            "subcategory":"Religious Organization",
            "type":"Services"
        }
    ],
    "sg:phone":"+1 336 766 6078",
    "sg:postcode":"27012",
    "sg:province":"NC",
    "sg:tags":[
        "place",
        "worship",
        "church"
    ],
    "sg:website":"http://www.warnerschapelchurchofchrist.org",
    "wof:name":"Warners Chapel Church Of Christ",
    "wof:placetype":"venue"
},
  "geometry": {"coordinates":[-80.416713,36.0553],"type":"Point"}
}