{
  "type": "Feature",
  "properties": {
    "addr:full":"4711 Hope Valley Rd Durham NC 27707",
    "addr:housenumber":"4711",
    "addr:postcode":"27707",
    "addr:street":"Hope Valley Rd",
    "iso:country":"US",
    "sg:address":"4711 Hope Valley Rd",
    "sg:city":"Durham",
    "sg:classifiers":[
        {
            "category":"Personal",
            "subcategory":"Shoe Repair & Shine",
            "type":"Services"
        }
    ],
    "sg:phone":"+1 919 489 3277",
    "sg:postcode":"27707",
    "sg:province":"NC",
    "sg:tags":[
        "repairing",
        "parlor",
        "boot"
    ],
    "wof:name":"Ko Shoe Repair & Alterations",
    "wof:placetype":"venue"
},
  "geometry": {"coordinates":[-78.95685,35.92254],"type":"Point"}
}