{
  "type": "Feature",
  "properties": {
    "iso:country":"US",
    "sg:address":"800 Garrett St",
    "sg:city":"Ahoskie",
    "sg:classifiers":[
        {
            "category":"Personal",
            "subcategory":"Beauty Salon",
            "type":"Services"
        }
    ],
    "sg:phone":"+1   ",
    "sg:postcode":"27910",
    "sg:province":"NC",
    "sg:tags":[
        "shop"
    ],
    "wof:name":"Brendas Hair Flair",
    "wof:placetype":"venue"
},
  "geometry": {"coordinates":[-76.978382,36.280758],"type":"Point"}
}