{
  "type": "Feature",
  "properties": {
    "iso:country":"US",
    "sg:address":"2254 Wilmington Hwy",
    "sg:city":"Jacksonville",
    "sg:classifiers":[
        {
            "category":"Shopping",
            "subcategory":"Used Merchandise",
            "type":"Retail Goods"
        }
    ],
    "sg:phone":"+1 910 347 8832",
    "sg:postcode":"28540",
    "sg:province":"NC",
    "sg:tags":[
        "furniture"
    ],
    "wof:name":"Joann Collectibles & Used Furn",
    "wof:placetype":"venue"
},
  "geometry": {"coordinates":[-77.477558,34.721145],"type":"Point"}
}