{
  "type": "Feature",
  "properties": {
    "addr:full":"210 Virginia Ave Carolina Beach NC 28428",
    "addr:housenumber":"210",
    "addr:postcode":"28428",
    "addr:street":"Virginia Ave",
    "iso:country":"US",
    "sg:address":"210 Virginia Ave",
    "sg:city":"Carolina Beach",
    "sg:classifiers":[
        {
            "category":"Building & Trades",
            "subcategory":"Construction",
            "type":"Services"
        }
    ],
    "sg:phone":"+1 910 458 4738",
    "sg:postcode":"28428",
    "sg:province":"NC",
    "sg:tags":[
        "contractor"
    ],
    "wof:name":"Magic Fence",
    "wof:placetype":"venue"
},
  "geometry": {"coordinates":[-77.886252,34.056193],"type":"Point"}
}