{
  "type": "Feature",
  "properties": {
    "addr:full":"7227 Gentle Valley Ln Raleigh NC 27603",
    "addr:housenumber":"7227",
    "addr:postcode":"27603",
    "addr:street":"Gentle Valley Ln",
    "iso:country":"US",
    "sg:address":"7227 Gentle Valley Ln",
    "sg:city":"Raleigh",
    "sg:classifiers":[
        {
            "category":"Building & Trades",
            "subcategory":"Construction",
            "type":"Services"
        }
    ],
    "sg:phone":"+1 919 662 1957",
    "sg:postcode":"27603",
    "sg:province":"NC",
    "sg:tags":[
        "house"
    ],
    "wof:name":"Hankins Construction Inc",
    "wof:placetype":"venue"
},
  "geometry": {"coordinates":[-78.65745200000001,35.679101],"type":"Point"}
}