{
  "type": "Feature",
  "properties": {
    "iso:country":"US",
    "sg:address":"108 Praley St SW",
    "sg:city":"Valdese",
    "sg:classifiers":[
        {
            "category":"Wholesale",
            "subcategory":"Apparel",
            "type":"Manufacturing & Wholesale Goods"
        },
        {
            "category":"Manufacturing",
            "subcategory":"Textiles",
            "type":"Manufacturing & Wholesale Goods"
        }
    ],
    "sg:phone":"+1 828 874 0069",
    "sg:postcode":"28690",
    "sg:province":"NC",
    "sg:tags":[
        "hosiery",
        "mfg"
    ],
    "wof:name":"Sierra Footworks Sales",
    "wof:placetype":"venue"
},
  "geometry": {"coordinates":[-81.565646,35.744163],"type":"Point"}
}