{
  "type": "Feature",
  "properties": {
    "addr:full":"3212 Randleman Rd Greensboro NC 27406",
    "addr:housenumber":"3212",
    "addr:postcode":"27406",
    "addr:street":"Randleman Rd",
    "iso:country":"US",
    "sg:address":"3212 Randleman Rd",
    "sg:city":"Greensboro",
    "sg:classifiers":[
        {
            "category":"Restaurant",
            "type":"Food & Drink"
        }
    ],
    "sg:menulink":"http://www.allmenus.com/nc/greensboro/137338-subway/menu/",
    "sg:phone":"+1 336 230 0495",
    "sg:postcode":"27406",
    "sg:province":"NC",
    "sg:tags":[
        "american",
        "sandwich"
    ],
    "wof:name":"Subway",
    "wof:placetype":"venue"
},
  "geometry": {"coordinates":[-79.805663,36.007036],"type":"Point"}
}