{
  "type": "Feature",
  "properties": {
    "addr:full":"100 Deerwood Ct Chapel Hill NC 27517",
    "addr:housenumber":"100",
    "addr:postcode":"27517",
    "addr:street":"Deerwood Ct",
    "iso:country":"US",
    "sg:address":"100 Deerwood Ct",
    "sg:city":"Chapel Hill",
    "sg:classifiers":[
        {
            "category":"Banks & Credit Unions",
            "subcategory":"Financial Services",
            "type":"Services"
        }
    ],
    "sg:phone":"+1 919 929 2285",
    "sg:postcode":"27517",
    "sg:province":"NC",
    "sg:tags":[
        "investor"
    ],
    "wof:name":"Capital Group LLP",
    "wof:placetype":"venue"
},
  "geometry": {"coordinates":[-79.016121,35.924558],"type":"Point"}
}