{
  "type": "Feature",
  "properties": {
    "addr:full":"6301 Falls of Neuse Rd Raleigh NC 27615",
    "addr:housenumber":"6301",
    "addr:postcode":"27615",
    "addr:street":"Falls Of Neuse Rd",
    "iso:country":"US",
    "sg:address":"6301 Falls of Neuse Rd",
    "sg:city":"Raleigh",
    "sg:classifiers":[
        {
            "category":"Restaurant",
            "type":"Food & Drink"
        }
    ],
    "sg:menulink":"http://www.allmenus.com/nc/neuse/131414-amante-gourmet-pizza/menu/",
    "sg:phone":"+1 919 790 8878",
    "sg:postcode":"27615",
    "sg:province":"NC",
    "sg:tags":[
        "american",
        "pizza"
    ],
    "wof:name":"Amante Gourmet Pizza",
    "wof:placetype":"venue"
},
  "geometry": {"coordinates":[-78.62082700000001,35.868257],"type":"Point"}
}