{
  "type": "Feature",
  "properties": {
    "addr:full":"4994 Indiana Ave Winston Salem NC 27106",
    "addr:housenumber":"4994",
    "addr:postcode":"27106",
    "addr:street":"Indiana Ave",
    "iso:country":"US",
    "sg:address":"4994 Indiana Ave",
    "sg:city":"Winston Salem",
    "sg:classifiers":[
        {
            "category":"Manufacturing",
            "subcategory":"Tools & Machinery",
            "type":"Manufacturing & Wholesale Goods"
        }
    ],
    "sg:phone":"+1 336 744 5541",
    "sg:postcode":"27106",
    "sg:province":"NC",
    "sg:tags":[
        "peripheral",
        "computer"
    ],
    "wof:name":"Hach Associates",
    "wof:placetype":"venue"
},
  "geometry": {"coordinates":[-80.278091,36.155294],"type":"Point"}
}