{
  "type": "Feature",
  "properties": {
    "addr:full":"5501 Creek Ridge Ln Raleigh NC 27607",
    "addr:housenumber":"5501",
    "addr:postcode":"27607",
    "addr:street":"Creek Ridge Ln",
    "iso:country":"US",
    "sg:address":"5501 Creek Ridge Ln",
    "sg:city":"Raleigh",
    "sg:classifiers":[
        {
            "category":"Utilities",
            "subcategory":"Telephone",
            "type":"Services"
        }
    ],
    "sg:phone":"+1 919 434 8570",
    "sg:postcode":"27607",
    "sg:province":"NC",
    "sg:tags":[
        "communications"
    ],
    "wof:name":"Air Walk Networks",
    "wof:placetype":"venue"
},
  "geometry": {"coordinates":[-78.73399499999999,35.805231],"type":"Point"}
}