{
  "type": "Feature",
  "properties": {
    "iso:country":"US",
    "sg:address":"311 Williamson Rd",
    "sg:city":"Mooresville",
    "sg:classifiers":[
        {
            "category":"Health Services",
            "subcategory":"Doctor",
            "type":"Services"
        }
    ],
    "sg:phone":"+1 704 664 2552",
    "sg:postcode":"28117",
    "sg:province":"NC",
    "sg:tags":[
        "physician",
        "surgeon"
    ],
    "wof:name":"Harborside Pediatrics",
    "wof:placetype":"venue"
},
  "geometry": {"coordinates":[-80.873825,35.584603],"type":"Point"}
}