{
  "type": "Feature",
  "properties": {
    "addr:full":"787 New Sterling Rd Stony Point NC 28678",
    "addr:housenumber":"787",
    "addr:postcode":"28678",
    "addr:street":"New Sterling Rd",
    "iso:country":"US",
    "sg:address":"787 New Sterling Rd",
    "sg:city":"Stony Point",
    "sg:classifiers":[
        {
            "category":"Professional",
            "type":"Services"
        }
    ],
    "sg:phone":"+1 704 872 6555",
    "sg:postcode":"28678",
    "sg:province":"NC",
    "wof:name":"Terrence Ashley Jenkins",
    "wof:placetype":"venue"
},
  "geometry": {"coordinates":[-81.038286,35.807665],"type":"Point"}
}