{
  "type": "Feature",
  "properties": {
    "addr:full":"11905 Vanstory Dr Huntersville NC 28078",
    "addr:housenumber":"11905",
    "addr:postcode":"28078",
    "addr:street":"Vanstory Dr",
    "iso:country":"US",
    "sg:address":"11905 Vanstory Dr",
    "sg:city":"Huntersville",
    "sg:classifiers":[
        {
            "category":"Professional",
            "subcategory":"Engineering",
            "type":"Services"
        },
        {
            "category":"Manufacturing",
            "subcategory":"Tools & Machinery",
            "type":"Manufacturing & Wholesale Goods"
        }
    ],
    "sg:phone":"+1 704 875 1605",
    "sg:postcode":"28078",
    "sg:province":"NC",
    "sg:tags":[
        "mfg",
        "electronic",
        "industry",
        "part",
        "specialized",
        "special",
        "engineer"
    ],
    "sg:website":"www.kellertechnology.com",
    "wof:name":"Keller Technology Corporation",
    "wof:placetype":"venue"
},
  "geometry": {"coordinates":[-80.86792199999999,35.391825],"type":"Point"}
}