{
  "type": "Feature",
  "properties": {
    "iso:country":"US",
    "sg:address":"114 S Big Horse Creek Rd",
    "sg:city":"Lansing",
    "sg:classifiers":[
        {
            "category":"Autos & Motor Vehicles",
            "subcategory":"Auto Supplies",
            "type":"Retail Goods"
        }
    ],
    "sg:phone":"+1 336 384 2403",
    "sg:postcode":"28643",
    "sg:province":"NC",
    "sg:tags":[
        "automobile",
        "parts"
    ],
    "wof:name":"Lansing Garage & Auto Parts",
    "wof:placetype":"venue"
},
  "geometry": {"coordinates":[-81.512524,36.500997],"type":"Point"}
}