{
  "type": "Feature",
  "properties": {
    "iso:country":"US",
    "sg:address":"10401 Rozzelles Ferry Rd",
    "sg:city":"Charlotte",
    "sg:classifiers":[
        {
            "category":"Insurance",
            "subcategory":"Insurance Agent",
            "type":"Services"
        }
    ],
    "sg:phone":"+1 704 394 6332",
    "sg:postcode":"28214",
    "sg:province":"NC",
    "sg:tags":[
        "audit"
    ],
    "wof:name":"Research Technical Svc",
    "wof:placetype":"venue"
},
  "geometry": {"coordinates":[-80.95287500000001,35.321109],"type":"Point"}
}