{
  "type": "Feature",
  "properties": {
    "iso:country":"US",
    "sg:address":"3001 US Hwy 70",
    "sg:city":"New Bern",
    "sg:classifiers":[
        {
            "category":"Building & Trades",
            "subcategory":"Construction",
            "type":"Services"
        }
    ],
    "sg:phone":"+1 252 633 1113",
    "sg:postcode":"28560",
    "sg:province":"NC",
    "wof:name":"D & J Distributors",
    "wof:placetype":"venue"
},
  "geometry": {"coordinates":[-77.015608,35.052408],"type":"Point"}
}