{
  "type": "Feature",
  "properties": {
    "iso:country":"US",
    "sg:address":"402 Orange Dr",
    "sg:city":"Elon College",
    "sg:classifiers":[
        {
            "category":"Building & Trades",
            "subcategory":"Landscaping Services",
            "type":"Services"
        }
    ],
    "sg:phone":"+1 336 584 1331",
    "sg:postcode":"27244",
    "sg:province":"NC",
    "sg:tags":[
        "landscape"
    ],
    "wof:name":"Sizemore Landscaping & Svcs",
    "wof:placetype":"venue"
},
  "geometry": {"coordinates":[-79.505307,36.089877],"type":"Point"}
}