{
  "type": "Feature",
  "properties": {
    "iso:country":"US",
    "sg:address":"1004 N Berkeley Blvd",
    "sg:city":"Goldsboro",
    "sg:classifiers":[
        {
            "category":"Building & Trades",
            "subcategory":"Construction",
            "type":"Services"
        }
    ],
    "sg:phone":"+1 919 759 0395",
    "sg:postcode":"27534",
    "sg:province":"NC",
    "sg:tags":[
        "driveway"
    ],
    "wof:name":"Essroc Cement",
    "wof:placetype":"venue"
},
  "geometry": {"coordinates":[-77.934169,35.37965],"type":"Point"}
}