{
  "type": "Feature",
  "properties": {
    "iso:country":"US",
    "sg:address":"3203 Gastonia Hwy",
    "sg:city":"Lincolnton",
    "sg:classifiers":[
        {
            "category":"Retail",
            "subcategory":"Auto Repair",
            "type":"Services"
        }
    ],
    "sg:phone":"+1 704 736 0023",
    "sg:postcode":"28092",
    "sg:province":"NC",
    "sg:tags":[
        "repairing",
        "automobile"
    ],
    "wof:name":"Rollins Automotive",
    "wof:placetype":"venue"
},
  "geometry": {"coordinates":[-81.21688,35.417209],"type":"Point"}
}