{
  "type": "Feature",
  "properties": {
    "iso:country":"US",
    "sg:address":"17 Reynolda Dr",
    "sg:city":"Asheville",
    "sg:classifiers":[
        {
            "category":"Banks & Credit Unions",
            "subcategory":"Investment Brokerage",
            "type":"Services"
        }
    ],
    "sg:phone":"+1 828 296 0090",
    "sg:postcode":"28803",
    "sg:province":"NC",
    "sg:tags":[
        "advisory",
        "financial"
    ],
    "wof:name":"Butler Financial Solutions",
    "wof:placetype":"venue"
},
  "geometry": {"coordinates":[-82.478815,35.55108],"type":"Point"}
}