{
  "type": "Feature",
  "properties": {
    "addr:full":"2150 Millersville Rd Taylorsville NC 28681",
    "addr:housenumber":"2150",
    "addr:postcode":"28681",
    "addr:street":"Millersville Rd",
    "iso:country":"US",
    "sg:address":"2150 Millersville Rd",
    "sg:city":"Taylorsville",
    "sg:classifiers":[
        {
            "category":"Freight",
            "type":"Transportation"
        }
    ],
    "sg:phone":"+1 828 632 7709",
    "sg:postcode":"28681",
    "sg:province":"NC",
    "sg:tags":[
        "operator",
        "trucking"
    ],
    "wof:name":"Teague & Son Trucking Inc",
    "wof:placetype":"venue"
},
  "geometry": {"coordinates":[-81.163219,35.862167],"type":"Point"}
}