{
  "type": "Feature",
  "properties": {
    "iso:country":"US",
    "sg:address":"803 N Queen St",
    "sg:city":"Kinston",
    "sg:classifiers":[
        {
            "category":"Banks & Credit Unions",
            "subcategory":"Bank",
            "type":"Services"
        }
    ],
    "sg:phone":"+1 252 527 1035",
    "sg:postcode":"28501",
    "sg:province":"NC",
    "sg:tags":[
        "financing"
    ],
    "wof:name":"Carolina Finance",
    "wof:placetype":"venue"
},
  "geometry": {"coordinates":[-77.580815,35.269535],"type":"Point"}
}