{
  "type": "Feature",
  "properties": {
    "iso:country":"US",
    "sg:address":"5808 Newman Davis Rd",
    "sg:city":"Greensboro",
    "sg:classifiers":[
        {
            "category":"Manufacturing",
            "subcategory":"Printing",
            "type":"Manufacturing & Wholesale Goods"
        }
    ],
    "sg:phone":"+1 336 674 6996",
    "sg:postcode":"27406",
    "sg:province":"NC",
    "sg:tags":[
        "commercial"
    ],
    "wof:name":"Phillips  Stampton",
    "wof:placetype":"venue"
},
  "geometry": {"coordinates":[-79.838888,35.968128],"type":"Point"}
}