{
  "type": "Feature",
  "properties": {
    "addr:full":"8416 Yucca Trl Raleigh NC 27615",
    "addr:housenumber":"8416",
    "addr:postcode":"27615",
    "addr:street":"Yucca Trl",
    "iso:country":"US",
    "sg:address":"8416 Yucca Trl",
    "sg:city":"Raleigh",
    "sg:classifiers":[
        {
            "category":"Professional",
            "subcategory":"Business Services",
            "type":"Services"
        }
    ],
    "sg:phone":"+1   ",
    "sg:postcode":"27615",
    "sg:province":"NC",
    "wof:name":"J E T Message Mint Purveyor",
    "wof:placetype":"venue"
},
  "geometry": {"coordinates":[-78.590771,35.89286],"type":"Point"}
}