{
  "type": "Feature",
  "properties": {
    "iso:country":"US",
    "sg:address":"605 Carthage Rd",
    "sg:city":"Lumberton",
    "sg:classifiers":[
        {
            "category":"Retail",
            "subcategory":"Funeral Services",
            "type":"Services"
        }
    ],
    "sg:phone":"+1   ",
    "sg:postcode":"28358",
    "sg:province":"NC",
    "wof:name":"Baker Home Products",
    "wof:placetype":"venue"
},
  "geometry": {"coordinates":[-79.01347800000001,34.627358],"type":"Point"}
}