{
  "type": "Feature",
  "properties": {
    "iso:country":"US",
    "sg:address":"513 N Polk St",
    "sg:city":"Pineville",
    "sg:classifiers":[
        {
            "category":"Banks & Credit Unions",
            "subcategory":"Bank",
            "type":"Services"
        }
    ],
    "sg:phone":"+1 704 889 4725",
    "sg:postcode":"28134",
    "sg:province":"NC",
    "sg:tags":[
        "loan",
        "real estate"
    ],
    "wof:name":"American General Finance Inc",
    "wof:placetype":"venue"
},
  "geometry": {"coordinates":[-80.885757,35.090557],"type":"Point"}
}