{
  "type": "Feature",
  "properties": {
    "iso:country":"US",
    "sg:address":"6422 University Pkwy",
    "sg:city":"Rural Hall",
    "sg:classifiers":[
        {
            "category":"Personal",
            "subcategory":"Beauty Salon",
            "type":"Services"
        }
    ],
    "sg:phone":"+1 336 377 9268",
    "sg:postcode":"27045",
    "sg:province":"NC",
    "wof:name":"Hair Gallery",
    "wof:placetype":"venue"
},
  "geometry": {"coordinates":[-80.280759,36.201507],"type":"Point"}
}