{
  "type": "Feature",
  "properties": {
    "addr:full":"82 Weaverville Rd Asheville NC 28804",
    "addr:housenumber":"82",
    "addr:postcode":"28804",
    "addr:street":"Weaverville Rd",
    "iso:country":"US",
    "sg:address":"82 Weaverville Rd",
    "sg:city":"Asheville",
    "sg:classifiers":[
        {
            "category":"Retail",
            "subcategory":"Auto Repair",
            "type":"Services"
        }
    ],
    "sg:phone":"+1 828 645 8678",
    "sg:postcode":"28804",
    "sg:province":"NC",
    "sg:tags":[
        "general"
    ],
    "wof:name":"B P Allens & Auto",
    "wof:placetype":"venue"
},
  "geometry": {"coordinates":[-82.579063,35.64117],"type":"Point"}
}