{
  "type": "Feature",
  "properties": {
    "addr:full":"111 N Greene St Wadesboro NC 28170",
    "addr:housenumber":"111",
    "addr:postcode":"28170",
    "addr:street":"N Greene St",
    "iso:country":"US",
    "sg:address":"111 N Greene St",
    "sg:city":"Wadesboro",
    "sg:classifiers":[
        {
            "category":"Government",
            "subcategory":"Office",
            "type":"Public Place"
        }
    ],
    "sg:phone":"+1 704 694 3072",
    "sg:postcode":"28170",
    "sg:province":"NC",
    "wof:name":"Anson County Board-Elections",
    "wof:placetype":"venue"
},
  "geometry": {"coordinates":[-80.071496,34.978951],"type":"Point"}
}