{
  "type": "Feature",
  "properties": {
    "iso:country":"US",
    "sg:address":"2334 N Old Carriage Rd",
    "sg:city":"Rocky Mount",
    "sg:classifiers":[
        {
            "category":"Building & Trades",
            "subcategory":"Plumbing",
            "type":"Services"
        }
    ],
    "sg:phone":"+1 252 937 4707",
    "sg:postcode":"27804",
    "sg:province":"NC",
    "sg:tags":[
        "heating",
        "contractor"
    ],
    "wof:name":"Shearin Heating & Cooling LLC",
    "wof:placetype":"venue"
},
  "geometry": {"coordinates":[-77.901543,35.993032],"type":"Point"}
}