{
  "type": "Feature",
  "properties": {
    "addr:full":"217 N Arendell Ave Zebulon NC 27597",
    "addr:housenumber":"217",
    "addr:postcode":"27597",
    "addr:street":"N Arendell Ave",
    "iso:country":"US",
    "sg:address":"217 N Arendell Ave",
    "sg:city":"Zebulon",
    "sg:classifiers":[
        {
            "category":"Shopping",
            "subcategory":"Pharmacy",
            "type":"Retail Goods"
        }
    ],
    "sg:phone":"+1 919 269 9176",
    "sg:postcode":"27597",
    "sg:province":"NC",
    "wof:name":"Malone Drugs",
    "wof:placetype":"venue"
},
  "geometry": {"coordinates":[-78.313858,35.822992],"type":"Point"}
}