{
  "type": "Feature",
  "properties": {
    "iso:country":"US",
    "sg:address":"113 N Main St",
    "sg:city":"Hendersonville",
    "sg:classifiers":[
        {
            "category":"Government",
            "subcategory":"Office",
            "type":"Public Place"
        }
    ],
    "sg:phone":"+1 828 697 4809",
    "sg:postcode":"28792",
    "sg:province":"NC",
    "sg:tags":[
        "executive"
    ],
    "wof:name":"Henderson Cnty Emrgncy Med Svc",
    "wof:placetype":"venue"
},
  "geometry": {"coordinates":[-82.459886,35.314822],"type":"Point"}
}