{
  "type": "Feature",
  "properties": {
    "iso:country":"US",
    "sg:address":"1116 Charmain St",
    "sg:city":"Fayetteville",
    "sg:classifiers":[
        {
            "category":"Wholesale",
            "subcategory":"Hardware",
            "type":"Manufacturing & Wholesale Goods"
        }
    ],
    "sg:phone":"+1 910 487 0038",
    "sg:postcode":"28311",
    "sg:province":"NC",
    "sg:tags":[
        "building",
        "supply"
    ],
    "wof:name":"Home Improvement Store",
    "wof:placetype":"venue"
},
  "geometry": {"coordinates":[-78.93665300000001,35.115782],"type":"Point"}
}