{
  "type": "Feature",
  "properties": {
    "iso:country":"US",
    "sg:address":"67 Logan St",
    "sg:city":"Marion",
    "sg:classifiers":[
        {
            "category":"Real Estate",
            "subcategory":"Real Estate Agent",
            "type":"Services"
        }
    ],
    "sg:phone":"+1 828 652 4330",
    "sg:postcode":"28752",
    "sg:province":"NC",
    "wof:name":"Harris Realty",
    "wof:placetype":"venue"
},
  "geometry": {"coordinates":[-82.009852,35.682684],"type":"Point"}
}