{
  "type": "Feature",
  "properties": {
    "iso:country":"US",
    "sg:address":"81 S Elliot Rd Whole Foods",
    "sg:city":"Chapel Hill",
    "sg:classifiers":[
        {
            "category":"Coffee & Tea",
            "type":"Food & Drink"
        },
        {
            "category":"Deli",
            "type":"Food & Drink"
        }
    ],
    "sg:phone":"+1 919 968 1983",
    "sg:postcode":"27514",
    "sg:province":"NC",
    "sg:website":"www.wholefoodsmarket.com/stores/...",
    "wof:name":"Penguins Cafe and Coffee Bar",
    "wof:placetype":"venue"
},
  "geometry": {"coordinates":[-79.02922,35.9368],"type":"Point"}
}