{
  "type": "Feature",
  "properties": {
    "addr:full":"3800 Patterson Ave Winston Salem NC 27105",
    "addr:housenumber":"3800",
    "addr:postcode":"27105",
    "addr:street":"Patterson Ave",
    "iso:country":"US",
    "sg:address":"3800 Patterson Ave",
    "sg:city":"Winston Salem",
    "sg:classifiers":[
        {
            "category":"Building & Trades",
            "subcategory":"Equipment Rental",
            "type":"Services"
        }
    ],
    "sg:phone":"+1 336 661 1211",
    "sg:postcode":"27105",
    "sg:province":"NC",
    "sg:tags":[
        "heavy",
        "hardware",
        "construction"
    ],
    "wof:name":"RSC 481",
    "wof:placetype":"venue"
},
  "geometry": {"coordinates":[-80.24413,36.149574],"type":"Point"}
}