{
  "type": "Feature",
  "properties": {
    "iso:country":"US",
    "sg:address":"6701 State Hwy 42 E",
    "sg:city":"Selma",
    "sg:classifiers":[
        {
            "category":"Organizations",
            "subcategory":"Religious Organization",
            "type":"Services"
        }
    ],
    "sg:phone":"+1   ",
    "sg:postcode":"27576",
    "sg:province":"NC",
    "wof:name":"Thanksgiving Baptist Church",
    "wof:placetype":"venue"
},
  "geometry": {"coordinates":[-78.30564699999999,35.658833],"type":"Point"}
}