{
  "type": "Feature",
  "properties": {
    "addr:full":"1401 S 16th St Wilmington NC 28401",
    "addr:housenumber":"1401",
    "addr:postcode":"28401",
    "addr:street":"S 16Th St",
    "iso:country":"US",
    "sg:address":"1401 S 16th St",
    "sg:city":"Wilmington",
    "sg:classifiers":[
        {
            "category":"Social Services",
            "subcategory":"Child Care",
            "type":"Services"
        }
    ],
    "sg:phone":"+1 910 815 0017",
    "sg:postcode":"28401",
    "sg:province":"NC",
    "sg:tags":[
        "day"
    ],
    "wof:name":"Adventure World Inc",
    "wof:placetype":"venue"
},
  "geometry": {"coordinates":[-77.926677,34.218012],"type":"Point"}
}