{
  "type": "Feature",
  "properties": {
    "iso:country":"US",
    "sg:address":"9570 Three Top Rd",
    "sg:city":"Todd",
    "sg:classifiers":[
        {
            "category":"Professional",
            "subcategory":"Business Services",
            "type":"Services"
        }
    ],
    "sg:phone":"+1   ",
    "sg:postcode":"28684",
    "sg:province":"NC",
    "wof:name":"Sherman Home Inspections Inc",
    "wof:placetype":"venue"
},
  "geometry": {"coordinates":[-81.601044,36.318613],"type":"Point"}
}