{
  "type": "Feature",
  "properties": {
    "addr:full":"489 Holland Rd Apex NC 27526",
    "addr:housenumber":"489",
    "addr:postcode":"27526",
    "addr:street":"Holland Rd",
    "iso:country":"US",
    "sg:address":"489 Holland Rd",
    "sg:city":"Apex",
    "sg:classifiers":[
        {
            "category":"Autos & Motor Vehicles",
            "subcategory":"Automobile Sales",
            "type":"Retail Goods"
        }
    ],
    "sg:phone":"+1 919 362 5825",
    "sg:postcode":"27526",
    "sg:province":"NC",
    "sg:tags":[
        "used"
    ],
    "wof:name":"Auto Exchange",
    "wof:placetype":"venue"
},
  "geometry": {"coordinates":[-78.790494,35.577708],"type":"Point"}
}