{
  "type": "Feature",
  "properties": {
    "addr:full":"1733 University Commercial Drive Charlotte NC 28213",
    "addr:housenumber":"1733",
    "addr:postcode":"28213",
    "addr:street":"University Commercial Drive",
    "iso:country":"US",
    "sg:address":"1733 University Commercial Drive",
    "sg:city":"Charlotte",
    "sg:classifiers":[
        {
            "category":"Building & Trades",
            "subcategory":"Construction",
            "type":"Services"
        }
    ],
    "sg:phone":"+1 704 372 2460",
    "sg:postcode":"28213",
    "sg:province":"NC",
    "sg:tags":[
        "contractor",
        "mechanical"
    ],
    "sg:website":"http://www.mcihvac.com",
    "wof:name":"Mechanical Contractors Inc",
    "wof:placetype":"venue"
},
  "geometry": {"coordinates":[-80.744291,35.264236],"type":"Point"}
}