{
  "type": "Feature",
  "properties": {
    "addr:full":"72 Sidon Dr Greensboro NC 27407",
    "addr:housenumber":"72",
    "addr:postcode":"27407",
    "addr:street":"Sidon Dr",
    "iso:country":"US",
    "sg:address":"72 Sidon Dr",
    "sg:city":"Greensboro",
    "sg:classifiers":[
        {
            "category":"Building & Trades",
            "subcategory":"Cleaning & Sanitation",
            "type":"Services"
        }
    ],
    "sg:phone":"+1   ",
    "sg:postcode":"27407",
    "sg:province":"NC",
    "sg:tags":[
        "maintenance"
    ],
    "wof:name":"Ceballos Guadalupe",
    "wof:placetype":"venue"
},
  "geometry": {"coordinates":[-79.875015,35.955128],"type":"Point"}
}