{
  "type": "Feature",
  "properties": {
    "addr:full":"6600 E Washington St Exd Mebane NC 27302",
    "addr:housenumber":"6600",
    "addr:postcode":"27302",
    "addr:street":"E Washington St Exd",
    "iso:country":"US",
    "sg:address":"6600 E Washington St Exd",
    "sg:city":"Mebane",
    "sg:classifiers":[
        {
            "category":"Building & Trades",
            "subcategory":"Construction",
            "type":"Services"
        }
    ],
    "sg:phone":"+1 919 563 5630",
    "sg:postcode":"27302",
    "sg:province":"NC",
    "sg:tags":[
        "fabricator",
        "metal"
    ],
    "sg:website":"www.forma-fab.com",
    "wof:name":"Forma-Fab Metals Inc",
    "wof:placetype":"venue"
},
  "geometry": {"coordinates":[-79.23846899999999,36.08734],"type":"Point"}
}