{
  "type": "Feature",
  "properties": {
    "addr:full":"425 W Kings Hwy Eden NC 27288",
    "addr:housenumber":"425",
    "addr:postcode":"27288",
    "addr:street":"W Kings Hwy",
    "iso:country":"US",
    "sg:address":"425 W Kings Hwy",
    "sg:city":"Eden",
    "sg:classifiers":[
        {
            "category":"Banks & Credit Unions",
            "subcategory":"Bank",
            "type":"Services"
        }
    ],
    "sg:phone":"+1 336 623 9171",
    "sg:postcode":"27288",
    "sg:province":"NC",
    "wof:name":"Bank Of Eden",
    "wof:placetype":"venue"
},
  "geometry": {"coordinates":[-79.756364,36.490645],"type":"Point"}
}