{
  "type": "Feature",
  "properties": {
    "addr:full":"3615 Old Charlotte Hwy Monroe NC 28110",
    "addr:housenumber":"3615",
    "addr:postcode":"28110",
    "addr:street":"Old Charlotte Hwy",
    "iso:country":"US",
    "sg:address":"3615 Old Charlotte Hwy",
    "sg:city":"Monroe",
    "sg:classifiers":[
        {
            "category":"Retail",
            "subcategory":"Auto Repair",
            "type":"Services"
        }
    ],
    "sg:phone":"+1 704 282 0321",
    "sg:postcode":"28110",
    "sg:province":"NC",
    "sg:tags":[
        "body",
        "automobile",
        "painting"
    ],
    "wof:name":"Hit Man Paintless Dent Removal",
    "wof:placetype":"venue"
},
  "geometry": {"coordinates":[-80.60343399999999,35.027222],"type":"Point"}
}