{
  "type": "Feature",
  "properties": {
    "iso:country":"US",
    "sg:address":"3055 Morton-Pulliam Rd",
    "sg:city":"Roxboro",
    "sg:classifiers":[
        {
            "category":"Personal",
            "subcategory":"Beauty Salon",
            "type":"Services"
        }
    ],
    "sg:phone":"+1 336 599 7973",
    "sg:postcode":"27574",
    "sg:province":"NC",
    "wof:name":"Alease's Beauty Shop",
    "wof:placetype":"venue"
},
  "geometry": {"coordinates":[-79.02290499999999,36.440222],"type":"Point"}
}