{
  "type": "Feature",
  "properties": {
    "iso:country":"US",
    "sg:address":"1330 Westover St",
    "sg:city":"Charlotte",
    "sg:classifiers":[
        {
            "category":"Government",
            "subcategory":"Office",
            "type":"Public Place"
        }
    ],
    "sg:phone":"+1 704 342 5145",
    "sg:postcode":"28205",
    "sg:province":"NC",
    "sg:tags":[
        "national",
        "security"
    ],
    "wof:name":"US Army Reserve 377 M I Battln",
    "wof:placetype":"venue"
},
  "geometry": {"coordinates":[-80.806692,35.219589],"type":"Point"}
}