{
  "type": "Feature",
  "properties": {
    "addr:full":"115 Dapple Ct Wilmington NC 28403",
    "addr:housenumber":"115",
    "addr:postcode":"28403",
    "addr:street":"Dapple Ct",
    "iso:country":"US",
    "sg:address":"115 Dapple Ct",
    "sg:city":"Wilmington",
    "sg:classifiers":[
        {
            "category":"Professional",
            "subcategory":"Lawyer & Legal Services",
            "type":"Services"
        }
    ],
    "sg:phone":"+1   ",
    "sg:postcode":"28403",
    "sg:province":"NC",
    "wof:name":"Grantham Legal Associates LLC",
    "wof:placetype":"venue"
},
  "geometry": {"coordinates":[-77.87835099999999,34.240247],"type":"Point"}
}