{
  "type": "Feature",
  "properties": {
    "addr:full":"120 Water's Edge Rd Kill Devil Hills NC 27948",
    "addr:housenumber":"120",
    "addr:postcode":"27948",
    "addr:street":"Water'S Edge Rd",
    "iso:country":"US",
    "sg:address":"120 Water's Edge Rd",
    "sg:city":"Kill Devil Hills",
    "sg:classifiers":[
        {
            "category":"Sports & Exercise",
            "subcategory":"Gym",
            "type":"Entertainment"
        }
    ],
    "sg:phone":"+1 252 480 2014",
    "sg:postcode":"27948",
    "sg:province":"NC",
    "sg:tags":[
        "spa",
        "health"
    ],
    "wof:name":"Aquadoc Pool & Spa Svc",
    "wof:placetype":"venue"
},
  "geometry": {"coordinates":[-75.693653,36.011113],"type":"Point"}
}