{
  "type": "Feature",
  "properties": {
    "iso:country":"US",
    "sg:address":"1298 Thompson Chapel Rd",
    "sg:city":"Wilson",
    "sg:classifiers":[
        {
            "category":"Farming",
            "subcategory":"Poultry Farm",
            "type":"Manufacturing & Wholesale Goods"
        }
    ],
    "sg:phone":"+1 252 243 4704",
    "sg:postcode":"27896",
    "sg:province":"NC",
    "sg:tags":[
        "hatchery"
    ],
    "wof:name":"Georgia B Williams",
    "wof:placetype":"venue"
},
  "geometry": {"coordinates":[-77.979377,35.819494],"type":"Point"}
}