{
  "type": "Feature",
  "properties": {
    "iso:country":"US",
    "sg:address":"915 Tunnel Rd",
    "sg:city":"Asheville",
    "sg:classifiers":[
        {
            "category":"Building & Trades",
            "subcategory":"Construction",
            "type":"Services"
        }
    ],
    "sg:phone":"+1 828 258 2040",
    "sg:postcode":"28805",
    "sg:province":"NC",
    "sg:tags":[
        "hanging",
        "contractor"
    ],
    "wof:name":"Paint Force",
    "wof:placetype":"venue"
},
  "geometry": {"coordinates":[-82.500981,35.588321],"type":"Point"}
}