{
  "type": "Feature",
  "properties": {
    "iso:country":"US",
    "sg:address":"2400 Perimeter Park Dr",
    "sg:city":"Morrisville",
    "sg:classifiers":[
        {
            "category":"Wholesale",
            "subcategory":"Office Equipment",
            "type":"Manufacturing & Wholesale Goods"
        }
    ],
    "sg:phone":"+1 919 804 6300",
    "sg:postcode":"27560",
    "sg:province":"NC",
    "sg:tags":[
        "machine",
        "duplicating",
        "copying"
    ],
    "sg:website":"www.ikon.com",
    "wof:name":"Ikon Office Solutions Inc",
    "wof:placetype":"venue"
},
  "geometry": {"coordinates":[-78.830157,35.850882],"type":"Point"}
}