{
  "type": "Feature",
  "properties": {
    "iso:country":"US",
    "sg:address":"14 E Hawthorne Dr",
    "sg:city":"Asheville",
    "sg:classifiers":[
        {
            "category":"Insurance",
            "subcategory":"Insurance Agent",
            "type":"Services"
        }
    ],
    "sg:phone":"+1 828 251 2248",
    "sg:postcode":"28805",
    "sg:province":"NC",
    "sg:tags":[
        "adjuster"
    ],
    "wof:name":"Frontier Adjusters Inc",
    "wof:placetype":"venue"
},
  "geometry": {"coordinates":[-82.49830300000001,35.585013],"type":"Point"}
}