{
  "type": "Feature",
  "properties": {
    "iso:country":"US",
    "sg:address":"300 Beaman St",
    "sg:city":"Clinton",
    "sg:classifiers":[
        {
            "category":"Building & Trades",
            "subcategory":"Cleaning & Sanitation",
            "type":"Services"
        }
    ],
    "sg:phone":"+1   ",
    "sg:postcode":"28328",
    "sg:province":"NC",
    "sg:tags":[
        "maintenance"
    ],
    "wof:name":"QSI",
    "wof:placetype":"venue"
},
  "geometry": {"coordinates":[-78.322373,35.004559],"type":"Point"}
}