{
  "type": "Feature",
  "properties": {
    "iso:country":"US",
    "sg:address":"304 Brunswick Dr",
    "sg:city":"Waynesville",
    "sg:classifiers":[
        {
            "category":"Travel",
            "subcategory":"Hotels & Motels",
            "type":"Entertainment"
        }
    ],
    "sg:phone":"+1 828 456 5110",
    "sg:postcode":"28786",
    "sg:province":"NC",
    "sg:tags":[
        "operation"
    ],
    "wof:name":"Gould John D Guest House",
    "wof:placetype":"venue"
},
  "geometry": {"coordinates":[-82.986946,35.46609],"type":"Point"}
}