{
  "type": "Feature",
  "properties": {
    "iso:country":"US",
    "sg:address":"1005 Dresser Ct",
    "sg:city":"Raleigh",
    "sg:classifiers":[
        {
            "category":"Place Of Worship",
            "subcategory":"Church",
            "type":"Public Place"
        },
        {
            "category":"Place Of Worship",
            "type":"Public Place"
        }
    ],
    "sg:phone":"+1 919 954 1600",
    "sg:postcode":"27609",
    "sg:province":"NC",
    "sg:tags":[
        "churches-salvation",
        "army"
    ],
    "wof:name":"Campus Crusades",
    "wof:placetype":"venue"
},
  "geometry": {"coordinates":[-78.620034,35.833604],"type":"Point"}
}