{
  "type": "Feature",
  "properties": {
    "iso:country":"US",
    "sg:address":"75 Liles Dean Rd",
    "sg:city":"Wendell",
    "sg:classifiers":[
        {
            "category":"Organizations",
            "subcategory":"Religious Organization",
            "type":"Services"
        }
    ],
    "sg:phone":"+1   ",
    "sg:postcode":"27591",
    "sg:province":"NC",
    "wof:name":"Grace Fellowship",
    "wof:placetype":"venue"
},
  "geometry": {"coordinates":[-78.382034,35.792405],"type":"Point"}
}