{
  "type": "Feature",
  "properties": {
    "iso:country":"US",
    "sg:address":"901 E Trinity Ave",
    "sg:city":"Durham",
    "sg:classifiers":[
        {
            "category":"Retail",
            "subcategory":"Car Wash",
            "type":"Services"
        }
    ],
    "sg:phone":"+1   ",
    "sg:postcode":"27704",
    "sg:province":"NC",
    "sg:tags":[
        "carwash"
    ],
    "wof:name":"Personal Touch Auto Detailing",
    "wof:placetype":"venue"
},
  "geometry": {"coordinates":[-78.88318700000001,36.007553],"type":"Point"}
}