{
  "type": "Feature",
  "properties": {
    "iso:country":"US",
    "sg:address":"200 Town Run Ln NW",
    "sg:city":"Winston Salem",
    "sg:classifiers":[
        {
            "category":"Professional",
            "subcategory":"Management & Consulting",
            "type":"Services"
        }
    ],
    "sg:phone":"+1 336 884 0639",
    "sg:postcode":"27101",
    "sg:province":"NC",
    "sg:tags":[
        "consultant"
    ],
    "wof:name":"Fiduciary Trust Consulting Svc",
    "wof:placetype":"venue"
},
  "geometry": {"coordinates":[-80.24609100000001,36.096754],"type":"Point"}
}