{
  "type": "Feature",
  "properties": {
    "iso:country":"US",
    "sg:address":"140 Ford St",
    "sg:city":"Robbinsville",
    "sg:classifiers":[
        {
            "category":"Building & Trades",
            "subcategory":"Construction",
            "type":"Services"
        }
    ],
    "sg:phone":"+1 828 479 6501",
    "sg:postcode":"28771",
    "sg:province":"NC",
    "sg:tags":[
        "general",
        "contractor"
    ],
    "wof:name":"Walco Inc",
    "wof:placetype":"venue"
},
  "geometry": {"coordinates":[-83.805643,35.323821],"type":"Point"}
}