{
  "type": "Feature",
  "properties": {
    "iso:country":"US",
    "sg:address":"3925 Sedgebrook St",
    "sg:city":"High Point",
    "sg:classifiers":[
        {
            "category":"Professional",
            "subcategory":"Advertising",
            "type":"Services"
        }
    ],
    "sg:phone":"+1   ",
    "sg:postcode":"27265",
    "sg:province":"NC",
    "sg:tags":[
        "agency"
    ],
    "wof:name":"For Sale By Owner Magazine",
    "wof:placetype":"venue"
},
  "geometry": {"coordinates":[-79.96266199999999,36.061015],"type":"Point"}
}