{
  "type": "Feature",
  "properties": {
    "addr:full":"4320 Dutch Garden Ct Raleigh NC 27613",
    "addr:housenumber":"4320",
    "addr:postcode":"27613",
    "addr:street":"Dutch Garden Ct",
    "iso:country":"US",
    "sg:address":"4320 Dutch Garden Ct",
    "sg:city":"Raleigh",
    "sg:classifiers":[
        {
            "category":"Professional",
            "subcategory":"Business Services",
            "type":"Services"
        }
    ],
    "sg:phone":"+1   ",
    "sg:postcode":"27613",
    "sg:province":"NC",
    "wof:name":"Worklife Design",
    "wof:placetype":"venue"
},
  "geometry": {"coordinates":[-78.705164,35.8682],"type":"Point"}
}