{
  "type": "Feature",
  "properties": {
    "iso:country":"US",
    "sg:address":"2709 Water Ridge Pkwy",
    "sg:city":"Charlotte",
    "sg:classifiers":[
        {
            "category":"Professional",
            "type":"Services"
        }
    ],
    "sg:phone":"+1 704 329 0750",
    "sg:postcode":"28217",
    "sg:province":"NC",
    "sg:tags":[
        "establishment"
    ],
    "wof:name":"Price Waterhousecoopers",
    "wof:placetype":"venue"
},
  "geometry": {"coordinates":[-80.92533299999999,35.186744],"type":"Point"}
}