{
  "type": "Feature",
  "properties": {
    "addr:full":"110 S Hill Ave Albemarle NC 28001",
    "addr:housenumber":"110",
    "addr:postcode":"28001",
    "addr:street":"S Hill Ave",
    "iso:country":"US",
    "sg:address":"110 S Hill Ave",
    "sg:city":"Albemarle",
    "sg:classifiers":[
        {
            "category":"Organizations",
            "subcategory":"Religious Organization",
            "type":"Services"
        }
    ],
    "sg:phone":"+1 704 982 1436",
    "sg:postcode":"28001",
    "sg:province":"NC",
    "sg:tags":[
        "church"
    ],
    "wof:name":"South Baptist Church",
    "wof:placetype":"venue"
},
  "geometry": {"coordinates":[-80.194275,35.337581],"type":"Point"}
}