{
  "type": "Feature",
  "properties": {
    "addr:full":"314 W Main St Murfreesboro NC 27855",
    "addr:housenumber":"314",
    "addr:postcode":"27855",
    "addr:street":"W Main St",
    "iso:country":"US",
    "sg:address":"314 W Main St",
    "sg:city":"Murfreesboro",
    "sg:classifiers":[
        {
            "category":"Retail",
            "subcategory":"Funeral Services",
            "type":"Services"
        }
    ],
    "sg:phone":"+1 252 398 3162",
    "sg:postcode":"27855",
    "sg:province":"NC",
    "sg:tags":[
        "director"
    ],
    "wof:name":"Garrett Funeral Home",
    "wof:placetype":"venue"
},
  "geometry": {"coordinates":[-77.104147,36.442632],"type":"Point"}
}