{
  "type": "Feature",
  "properties": {
    "addr:full":"4153 M L King Jr Blvd New Bern NC 28562",
    "addr:housenumber":"4153",
    "addr:postcode":"28562",
    "addr:street":"M L King Jr Blvd",
    "iso:country":"US",
    "sg:address":"4153 M L King Jr Blvd",
    "sg:city":"New Bern",
    "sg:classifiers":[
        {
            "category":"Manufacturing",
            "subcategory":"Printing",
            "type":"Manufacturing & Wholesale Goods"
        }
    ],
    "sg:phone":"+1 252 636 8337",
    "sg:postcode":"28562",
    "sg:province":"NC",
    "sg:tags":[
        "screen"
    ],
    "wof:name":"Van Baars Screen Printing",
    "wof:placetype":"venue"
},
  "geometry": {"coordinates":[-77.124792,35.094677],"type":"Point"}
}