{
  "type": "Feature",
  "properties": {
    "addr:full":"401 T P Sowers Rd Lexington NC 27295",
    "addr:housenumber":"401",
    "addr:postcode":"27295",
    "addr:street":"T P Sowers Rd",
    "iso:country":"US",
    "sg:address":"401 T P Sowers Rd",
    "sg:city":"Lexington",
    "sg:classifiers":[
        {
            "category":"Autos & Motor Vehicles",
            "subcategory":"Auto Supplies",
            "type":"Retail Goods"
        }
    ],
    "sg:phone":"+1 336 853 2069",
    "sg:postcode":"27295",
    "sg:province":"NC",
    "sg:tags":[
        "automobile",
        "parts"
    ],
    "wof:name":"Gayle's Auto Supply",
    "wof:placetype":"venue"
},
  "geometry": {"coordinates":[-80.42608,35.798924],"type":"Point"}
}