{
  "type": "Feature",
  "properties": {
    "addr:full":"4009 York Hwy Gastonia NC 28052",
    "addr:housenumber":"4009",
    "addr:postcode":"28052",
    "addr:street":"York Hwy",
    "iso:country":"US",
    "sg:address":"4009 York Hwy",
    "sg:city":"Gastonia",
    "sg:classifiers":[
        {
            "category":"Organizations",
            "subcategory":"Professional Association",
            "type":"Services"
        }
    ],
    "sg:phone":"+1 704 864 5711",
    "sg:postcode":"28052",
    "sg:province":"NC",
    "wof:name":"Firestone Men's Club",
    "wof:placetype":"venue"
},
  "geometry": {"coordinates":[-81.203991,35.208871],"type":"Point"}
}