{
  "type": "Feature",
  "properties": {
    "iso:country":"US",
    "sg:address":"112 Chillingham Rd",
    "sg:city":"Garner",
    "sg:classifiers":[
        {
            "category":"Insurance",
            "subcategory":"Insurance Agent",
            "type":"Services"
        }
    ],
    "sg:phone":"+1 919 772 1224",
    "sg:postcode":"27529",
    "sg:province":"NC",
    "wof:name":"Nationwide Mutual Insurance",
    "wof:placetype":"venue"
},
  "geometry": {"coordinates":[-78.617363,35.672588],"type":"Point"}
}