{
  "type": "Feature",
  "properties": {
    "addr:full":"2360 US Hwy 258 Bus Kinston NC 28504",
    "addr:housenumber":"2360",
    "addr:postcode":"28504",
    "addr:street":"Us Hwy 258 Bus",
    "iso:country":"US",
    "sg:address":"2360 US Hwy 258 Bus",
    "sg:city":"Kinston",
    "sg:classifiers":[
        {
            "category":"Government",
            "subcategory":"Office",
            "type":"Public Place"
        }
    ],
    "sg:phone":"+1 252 939 3237",
    "sg:postcode":"28504",
    "sg:province":"NC",
    "sg:tags":[
        "village"
    ],
    "sg:website":"www.ci.kinston.nc.us",
    "wof:name":"Kinston Engineering Dept",
    "wof:placetype":"venue"
},
  "geometry": {"coordinates":[-77.614642,35.269443],"type":"Point"}
}