{
  "type": "Feature",
  "properties": {
    "addr:full":"3221 Johnson St High Point NC 27263",
    "addr:housenumber":"3221",
    "addr:postcode":"27263",
    "addr:street":"Johnson St",
    "iso:country":"US",
    "sg:address":"3221 Johnson St",
    "sg:city":"High Point",
    "sg:classifiers":[
        {
            "category":"Home & Garden",
            "subcategory":"Furniture",
            "type":"Retail Goods"
        }
    ],
    "sg:phone":"+1 336 431 1998",
    "sg:postcode":"27263",
    "sg:province":"NC",
    "wof:name":"Deaton Furniture Distributors",
    "wof:placetype":"venue"
},
  "geometry": {"coordinates":[-79.908969,35.869642],"type":"Point"}
}