{
  "type": "Feature",
  "properties": {
    "addr:full":"9 W Salisbury St Denton NC 27239",
    "addr:housenumber":"9",
    "addr:postcode":"27239",
    "addr:street":"W Salisbury St",
    "iso:country":"US",
    "sg:address":"9 W Salisbury St",
    "sg:city":"Denton",
    "sg:classifiers":[
        {
            "category":"Insurance",
            "subcategory":"Insurance Agent",
            "type":"Services"
        }
    ],
    "sg:phone":"+1 336 859 2021",
    "sg:postcode":"27239",
    "sg:province":"NC",
    "wof:name":"Wilson Insurance Assoc",
    "wof:placetype":"venue"
},
  "geometry": {"coordinates":[-80.113505,35.633424],"type":"Point"}
}