{
  "type": "Feature",
  "properties": {
    "iso:country":"US",
    "sg:address":"2311 Princess Ann St",
    "sg:city":"Greensboro",
    "sg:classifiers":[
        {
            "category":"Farming",
            "subcategory":"Farm",
            "type":"Manufacturing & Wholesale Goods"
        }
    ],
    "sg:phone":"+1 336 282 1457",
    "sg:postcode":"27408",
    "sg:province":"NC",
    "sg:tags":[
        "crop",
        "general"
    ],
    "wof:name":"Shelburne Properties LLC",
    "wof:placetype":"venue"
},
  "geometry": {"coordinates":[-79.811753,36.102172],"type":"Point"}
}