{
  "type": "Feature",
  "properties": {
    "addr:full":"113 S Wilmington St Raleigh NC 27601",
    "addr:housenumber":"113",
    "addr:postcode":"27601",
    "addr:street":"S Wilmington St",
    "iso:country":"US",
    "sg:address":"113 S Wilmington St",
    "sg:city":"Raleigh",
    "sg:classifiers":[
        {
            "category":"Government",
            "subcategory":"Office",
            "type":"Public Place"
        }
    ],
    "sg:phone":"+1 919 832 4345",
    "sg:postcode":"27601",
    "sg:province":"NC",
    "sg:tags":[
        "village"
    ],
    "sg:website":"www.dhic.org",
    "wof:name":"Downtown Housing Improvement",
    "wof:placetype":"venue"
},
  "geometry": {"coordinates":[-78.638131,35.778386],"type":"Point"}
}