{
  "type": "Feature",
  "properties": {
    "addr:full":"102 Park Rise Ct Cary NC 27519",
    "addr:housenumber":"102",
    "addr:postcode":"27519",
    "addr:street":"Park Rise Ct",
    "iso:country":"US",
    "sg:address":"102 Park Rise Ct",
    "sg:city":"Cary",
    "sg:classifiers":[
        {
            "category":"Professional",
            "subcategory":"Management & Consulting",
            "type":"Services"
        }
    ],
    "sg:phone":"+1 919 387 6020",
    "sg:postcode":"27519",
    "sg:province":"NC",
    "sg:tags":[
        "consultant",
        "business"
    ],
    "wof:name":"Finan Management Inc",
    "wof:placetype":"venue"
},
  "geometry": {"coordinates":[-78.868318,35.777236],"type":"Point"}
}