{
  "type": "Feature",
  "properties": {
    "iso:country":"US",
    "sg:address":"6300 Limousine Dr",
    "sg:city":"Raleigh",
    "sg:classifiers":[
        {
            "category":"Professional",
            "subcategory":"Computer Services",
            "type":"Services"
        }
    ],
    "sg:phone":"+1 919 788 7757",
    "sg:postcode":"27613",
    "sg:province":"NC",
    "sg:tags":[
        "hardware",
        "provider",
        "internet",
        "software"
    ],
    "wof:name":"Freewebland",
    "wof:placetype":"venue"
},
  "geometry": {"coordinates":[-78.75888999999999,35.900776],"type":"Point"}
}