{
  "type": "Feature",
  "properties": {
    "addr:full":"5053 York Hwy Gastonia NC 28052",
    "addr:housenumber":"5053",
    "addr:postcode":"28052",
    "addr:street":"York Hwy",
    "iso:country":"US",
    "sg:address":"5053 York Hwy",
    "sg:city":"Gastonia",
    "sg:classifiers":[
        {
            "category":"Building & Trades",
            "subcategory":"Construction",
            "type":"Services"
        }
    ],
    "sg:phone":"+1 704 865 4681",
    "sg:postcode":"28052",
    "sg:province":"NC",
    "sg:tags":[
        "sandblasting"
    ],
    "wof:name":"Industrial Powder Coating",
    "wof:placetype":"venue"
},
  "geometry": {"coordinates":[-81.20496799999999,35.182316],"type":"Point"}
}