{
  "type": "Feature",
  "properties": {
    "iso:country":"US",
    "sg:address":"600 Mount Moriah Church Rd",
    "sg:city":"Clinton",
    "sg:classifiers":[
        {
            "category":"Building & Trades",
            "subcategory":"Construction",
            "type":"Services"
        }
    ],
    "sg:phone":"+1 910 272 9425",
    "sg:postcode":"28328",
    "sg:province":"NC",
    "sg:tags":[
        "home",
        "builder"
    ],
    "wof:name":"Glezen Family Care Home",
    "wof:placetype":"venue"
},
  "geometry": {"coordinates":[-78.394747,35.067865],"type":"Point"}
}