{
  "type": "Feature",
  "properties": {
    "iso:country":"US",
    "sg:address":"113 W Firetower Rd",
    "sg:city":"Winterville",
    "sg:classifiers":[
        {
            "category":"Real Estate",
            "subcategory":"Real Estate Agent",
            "type":"Services"
        }
    ],
    "sg:phone":"+1 252 215 2250",
    "sg:postcode":"28590",
    "sg:province":"NC",
    "sg:tags":[
        "appraiser"
    ],
    "wof:name":"Rasberry Shackelford & Assoc",
    "wof:placetype":"venue"
},
  "geometry": {"coordinates":[-77.385097,35.551509],"type":"Point"}
}