{
  "type": "Feature",
  "properties": {
    "iso:country":"US",
    "sg:address":"480 W Webb Ave",
    "sg:city":"Burlington",
    "sg:classifiers":[
        {
            "category":"Health Services",
            "subcategory":"Doctor",
            "type":"Services"
        }
    ],
    "sg:phone":"+1 336 226 7115",
    "sg:postcode":"27217",
    "sg:province":"NC",
    "sg:tags":[
        "dentist"
    ],
    "wof:name":"Joseph E Matsko DDS",
    "wof:placetype":"venue"
},
  "geometry": {"coordinates":[-79.43988,36.099052],"type":"Point"}
}