{
  "type": "Feature",
  "properties": {
    "iso:country":"US",
    "sg:address":"3313 Sanford Ln",
    "sg:city":"Monroe",
    "sg:classifiers":[
        {
            "category":"Organizations",
            "subcategory":"Religious Organization",
            "type":"Services"
        }
    ],
    "sg:phone":"+1   ",
    "sg:postcode":"28110",
    "sg:province":"NC",
    "wof:name":"Westfield Full Gospel Church",
    "wof:placetype":"venue"
},
  "geometry": {"coordinates":[-80.616603,34.9991],"type":"Point"}
}