{
  "type": "Feature",
  "properties": {
    "addr:full":"409 Long St West Jefferson NC 28694",
    "addr:housenumber":"409",
    "addr:postcode":"28694",
    "addr:street":"Long St",
    "iso:country":"US",
    "sg:address":"409 Long St",
    "sg:city":"West Jefferson",
    "sg:classifiers":[
        {
            "category":"Professional",
            "subcategory":"Business Services",
            "type":"Services"
        }
    ],
    "sg:phone":"+1 336 246 6428",
    "sg:postcode":"28694",
    "sg:province":"NC",
    "sg:tags":[
        "auctioneer"
    ],
    "wof:name":"William Jordan Auction & Rlty",
    "wof:placetype":"venue"
},
  "geometry": {"coordinates":[-81.496488,36.398758],"type":"Point"}
}