{
  "type": "Feature",
  "properties": {
    "iso:country":"US",
    "sg:address":"1307 Ramsey St",
    "sg:city":"Fayetteville",
    "sg:classifiers":[
        {
            "category":"Personal",
            "subcategory":"Beauty Salon",
            "type":"Services"
        }
    ],
    "sg:phone":"+1 910 829 1133",
    "sg:postcode":"28301",
    "sg:province":"NC",
    "wof:name":"African Braids In American Sty",
    "wof:placetype":"venue"
},
  "geometry": {"coordinates":[-78.880973,35.07507],"type":"Point"}
}