{
  "type": "Feature",
  "properties": {
    "addr:full":"2610 Neuse Blvd New Bern NC 28562",
    "addr:postcode":"2610;28562",
    "addr:street":"Neuse Blvd",
    "iso:country":"US",
    "sg:address":"2610 Neuse Blvd",
    "sg:city":"New Bern",
    "sg:classifiers":[
        {
            "category":"Social Services",
            "subcategory":"Child Care",
            "type":"Services"
        }
    ],
    "sg:phone":"+1 252 633 2505",
    "sg:postcode":"28562",
    "sg:province":"NC",
    "wof:name":"All About Children Day Camp",
    "wof:placetype":"venue"
},
  "geometry": {"coordinates":[-77.079797,35.119495],"type":"Point"}
}