{
  "type": "Feature",
  "properties": {
    "iso:country":"US",
    "sg:address":"1010 Morphus Bridge Rd",
    "sg:city":"Wendell",
    "sg:classifiers":[
        {
            "category":"Shopping",
            "subcategory":"Clothing, Apparel, & Fashions",
            "type":"Retail Goods"
        }
    ],
    "sg:phone":"+1 919 366 3310",
    "sg:postcode":"27591",
    "sg:province":"NC",
    "wof:name":"D's T Shirts",
    "wof:placetype":"venue"
},
  "geometry": {"coordinates":[-78.351866,35.781115],"type":"Point"}
}