{
  "type": "Feature",
  "properties": {
    "addr:full":"112 Freeland Ln Charlotte NC 28217",
    "addr:housenumber":"112",
    "addr:postcode":"28217",
    "addr:street":"Freeland Ln",
    "iso:country":"US",
    "sg:address":"112 Freeland Ln",
    "sg:city":"Charlotte",
    "sg:classifiers":[
        {
            "category":"Wholesale",
            "subcategory":"Machinery & Supplies",
            "type":"Manufacturing & Wholesale Goods"
        }
    ],
    "sg:phone":"+1 704 527 0337",
    "sg:postcode":"28217",
    "sg:province":"NC",
    "sg:tags":[
        "equipment",
        "industrial"
    ],
    "wof:name":"Northern Tool & Equipment Co",
    "wof:placetype":"venue"
},
  "geometry": {"coordinates":[-80.875427,35.189912],"type":"Point"}
}