{
  "type": "Feature",
  "properties": {
    "iso:country":"US",
    "sg:address":"1403 Dawson St",
    "sg:city":"Wilmington",
    "sg:classifiers":[
        {
            "category":"Personal",
            "subcategory":"Barber",
            "type":"Services"
        }
    ],
    "sg:phone":"+1 910 763 9203",
    "sg:postcode":"28401",
    "sg:province":"NC",
    "sg:tags":[
        "shop"
    ],
    "wof:name":"Thompson's Barber Shop",
    "wof:placetype":"venue"
},
  "geometry": {"coordinates":[-77.928904,34.225577],"type":"Point"}
}