{
  "type": "Feature",
  "properties": {
    "addr:full":"805 W Ehringhaus St Elizabeth City NC 27909",
    "addr:housenumber":"805",
    "addr:postcode":"27909",
    "addr:street":"W Ehringhaus St",
    "iso:country":"US",
    "sg:address":"805 W Ehringhaus St",
    "sg:city":"Elizabeth City",
    "sg:classifiers":[
        {
            "category":"Personal",
            "subcategory":"Beauty Salon",
            "type":"Services"
        }
    ],
    "sg:phone":"+1   ",
    "sg:postcode":"27909",
    "sg:province":"NC",
    "sg:tags":[
        "shop"
    ],
    "wof:name":"Bahama Mamas Styling Salon",
    "wof:placetype":"venue"
},
  "geometry": {"coordinates":[-76.231437,36.29564],"type":"Point"}
}