{
  "type": "Feature",
  "properties": {
    "addr:full":"18316 Taffrail Way Cornelius NC 28031",
    "addr:housenumber":"18316",
    "addr:postcode":"28031",
    "addr:street":"Taffrail Way",
    "iso:country":"US",
    "sg:address":"18316 Taffrail Way",
    "sg:city":"Cornelius",
    "sg:classifiers":[
        {
            "category":"Real Estate",
            "subcategory":"Real Estate Operator",
            "type":"Services"
        }
    ],
    "sg:phone":"+1 704 894 9053",
    "sg:postcode":"28031",
    "sg:province":"NC",
    "sg:tags":[
        "apartment"
    ],
    "wof:name":"Harborside Townhomes",
    "wof:placetype":"venue"
},
  "geometry": {"coordinates":[-80.890427,35.462867],"type":"Point"}
}