{
  "type": "Feature",
  "properties": {
    "addr:full":"812 Cedar Creek Rd Fayetteville NC 28312",
    "addr:housenumber":"812",
    "addr:postcode":"28312",
    "addr:street":"Cedar Creek Rd",
    "iso:country":"US",
    "sg:address":"812 Cedar Creek Rd",
    "sg:city":"Fayetteville",
    "sg:classifiers":[
        {
            "category":"Building & Trades",
            "subcategory":"Plumbing",
            "type":"Services"
        }
    ],
    "sg:phone":"+1 910 483 6419",
    "sg:postcode":"28312",
    "sg:province":"NC",
    "sg:tags":[
        "plumbing",
        "contractor"
    ],
    "wof:name":"John's Plumbing Co",
    "wof:placetype":"venue"
},
  "geometry": {"coordinates":[-78.844359,35.030763],"type":"Point"}
}