{
  "type": "Feature",
  "properties": {
    "iso:country":"US",
    "sg:address":"501 Paladin Dr",
    "sg:city":"Greenville",
    "sg:classifiers":[
        {
            "category":"Professional",
            "type":"Services"
        }
    ],
    "sg:phone":"+1   ",
    "sg:postcode":"27834",
    "sg:province":"NC",
    "wof:name":"Port Human Services Inc",
    "wof:placetype":"venue"
},
  "geometry": {"coordinates":[-77.41271999999999,35.618657],"type":"Point"}
}