{
  "type": "Feature",
  "properties": {
    "iso:country":"US",
    "sg:address":"119 S Water St",
    "sg:city":"Wilmington",
    "sg:classifiers":[
        {
            "category":"Shopping",
            "subcategory":"Clothing, Apparel, & Fashions",
            "type":"Retail Goods"
        }
    ],
    "sg:phone":"+1 910 762 9977",
    "sg:postcode":"28401",
    "sg:province":"NC",
    "sg:tags":[
        "hat"
    ],
    "wof:name":"Marty K Hats",
    "wof:placetype":"venue"
},
  "geometry": {"coordinates":[-77.94938,34.234051],"type":"Point"}
}