{
  "type": "Feature",
  "properties": {
    "addr:full":"3625 Williston Rd Walkertown NC 27051",
    "addr:housenumber":"3625",
    "addr:postcode":"27051",
    "addr:street":"Williston Rd",
    "iso:country":"US",
    "sg:address":"3625 Williston Rd",
    "sg:city":"Walkertown",
    "sg:classifiers":[
        {
            "category":"Freight",
            "type":"Transportation"
        }
    ],
    "sg:phone":"+1 336 595 2171",
    "sg:postcode":"27051",
    "sg:province":"NC",
    "sg:tags":[
        "local",
        "except",
        "trucking"
    ],
    "wof:name":"Allied Systems Ltd LLP",
    "wof:placetype":"venue"
},
  "geometry": {"coordinates":[-80.17703899999999,36.162377],"type":"Point"}
}