{
  "type": "Feature",
  "properties": {
    "addr:full":"9223 Timber Ln NE Leland NC 28451",
    "addr:housenumber":"9223",
    "addr:postcode":"28451",
    "addr:street":"Timber Ln Ne",
    "iso:country":"US",
    "sg:address":"9223 Timber Ln NE",
    "sg:city":"Leland",
    "sg:classifiers":[
        {
            "category":"Manufacturing",
            "subcategory":"Glass & Minerals",
            "type":"Manufacturing & Wholesale Goods"
        }
    ],
    "sg:phone":"+1 910 371 1402",
    "sg:postcode":"28451",
    "sg:province":"NC",
    "sg:tags":[
        "hydraulic",
        "cement",
        "mfg"
    ],
    "wof:name":"Family Masonry",
    "wof:placetype":"venue"
},
  "geometry": {"coordinates":[-78.037189,34.235233],"type":"Point"}
}