{
  "type": "Feature",
  "properties": {
    "addr:full":"53013 State Hwy 12 Frisco NC 27920",
    "addr:housenumber":"53013",
    "addr:postcode":"27920",
    "addr:street":"State Hwy 12",
    "iso:country":"US",
    "sg:address":"53013 State Hwy 12",
    "sg:city":"Frisco",
    "sg:classifiers":[
        {
            "category":"Professional",
            "type":"Services"
        },
        {
            "category":"Wholesale",
            "subcategory":"Home Furnishings",
            "type":"Manufacturing & Wholesale Goods"
        }
    ],
    "sg:phone":"+1 252 995 3320",
    "sg:postcode":"27920",
    "sg:province":"NC",
    "sg:tags":[
        "decor",
        "furniture",
        "accessory"
    ],
    "wof:name":"This Little Cottage Inc",
    "wof:placetype":"venue"
},
  "geometry": {"coordinates":[-75.622811,35.236378],"type":"Point"}
}