{
  "type": "Feature",
  "properties": {
    "iso:country":"US",
    "sg:address":"4301 Cold Springs Rd S",
    "sg:city":"Concord",
    "sg:classifiers":[
        {
            "category":"Personal",
            "subcategory":"Beauty Salon",
            "type":"Services"
        }
    ],
    "sg:phone":"+1   ",
    "sg:postcode":"28025",
    "sg:province":"NC",
    "sg:tags":[
        "shop",
        "business"
    ],
    "wof:name":"Karens Hairstyling",
    "wof:placetype":"venue"
},
  "geometry": {"coordinates":[-80.50991399999999,35.358134],"type":"Point"}
}