{
  "type": "Feature",
  "properties": {
    "iso:country":"US",
    "sg:address":"113 Ashley Brook Ct",
    "sg:city":"Cary",
    "sg:classifiers":[
        {
            "category":"Professional",
            "type":"Services"
        }
    ],
    "sg:phone":"+1 919 481 0836",
    "sg:postcode":"27513",
    "sg:province":"NC",
    "sg:tags":[
        "establishment"
    ],
    "wof:name":"Progressive",
    "wof:placetype":"venue"
},
  "geometry": {"coordinates":[-78.838317,35.779996],"type":"Point"}
}