{
  "type": "Feature",
  "properties": {
    "addr:full":"8282 Brogden Rd Smithfield NC 27577",
    "addr:housenumber":"8282",
    "addr:postcode":"27577",
    "addr:street":"Brogden Rd",
    "iso:country":"US",
    "sg:address":"8282 Brogden Rd",
    "sg:city":"Smithfield",
    "sg:classifiers":[
        {
            "category":"Manufacturing",
            "subcategory":"Watercraft",
            "type":"Manufacturing & Wholesale Goods"
        }
    ],
    "sg:phone":"+1 919 989 6671",
    "sg:postcode":"27577",
    "sg:province":"NC",
    "wof:name":"Outback Aluminum Boat Repr LLC",
    "wof:placetype":"venue"
},
  "geometry": {"coordinates":[-78.23334699999999,35.418279],"type":"Point"}
}