{
  "type": "Feature",
  "properties": {
    "addr:full":"8595 Brittian Rd Vale NC 28168",
    "addr:housenumber":"8595",
    "addr:postcode":"28168",
    "addr:street":"Brittian Rd",
    "iso:country":"US",
    "sg:address":"8595 Brittian Rd",
    "sg:city":"Vale",
    "sg:classifiers":[
        {
            "category":"Wholesale",
            "subcategory":"Machinery & Supplies",
            "type":"Manufacturing & Wholesale Goods"
        }
    ],
    "sg:phone":"+1 828 324 5453",
    "sg:postcode":"28168",
    "sg:province":"NC",
    "sg:tags":[
        "compressor",
        "gas"
    ],
    "wof:name":"Shufford Equipment & Repairs",
    "wof:placetype":"venue"
},
  "geometry": {"coordinates":[-81.47162299999999,35.634773],"type":"Point"}
}