{
  "type": "Feature",
  "properties": {
    "addr:full":"208 Conner Dr Chapel Hill NC 27514",
    "addr:housenumber":"208",
    "addr:postcode":"27514",
    "addr:street":"Conner Dr",
    "iso:country":"US",
    "sg:address":"208 Conner Dr",
    "sg:city":"Chapel Hill",
    "sg:classifiers":[
        {
            "category":"Real Estate",
            "subcategory":"Real Estate Operator",
            "type":"Services"
        }
    ],
    "sg:phone":"+1 919 942 0481",
    "sg:postcode":"27514",
    "sg:province":"NC",
    "sg:tags":[
        "apartment"
    ],
    "sg:website":"www.sunstoneapthomes.com/",
    "wof:name":"Sunstone Apartments",
    "wof:placetype":"venue"
},
  "geometry": {"coordinates":[-79.0261,35.928799],"type":"Point"}
}