{
  "type": "Feature",
  "properties": {
    "iso:country":"US",
    "sg:address":"3545 Willie Measley Rd",
    "sg:city":"La Grange",
    "sg:phone":"+1 252 566 4803",
    "sg:postcode":"28551",
    "sg:province":"NC",
    "sg:tags":[
        "farm",
        "tobacco"
    ],
    "wof:name":"Gordon Rouse",
    "wof:placetype":"venue"
},
  "geometry": {"coordinates":[-77.74527399999999,35.297847],"type":"Point"}
}