{
  "type": "Feature",
  "properties": {
    "iso:country":"US",
    "sg:address":"181 Oscar Hill Rd",
    "sg:city":"Dobson",
    "sg:classifiers":[
        {
            "category":"Shopping",
            "type":"Retail Goods"
        }
    ],
    "sg:phone":"+1 336 374 4391",
    "sg:postcode":"27017",
    "sg:province":"NC",
    "sg:tags":[
        "merchandise"
    ],
    "wof:name":"Johnson Custom Framing Inc",
    "wof:placetype":"venue"
},
  "geometry": {"coordinates":[-80.629563,36.33978],"type":"Point"}
}