{
  "type": "Feature",
  "properties": {
    "iso:country":"US",
    "sg:address":"44 E Moret Ave",
    "sg:city":"Havelock",
    "sg:classifiers":[
        {
            "category":"Social Services",
            "subcategory":"Child Care",
            "type":"Services"
        }
    ],
    "sg:phone":"+1   ",
    "sg:postcode":"28532",
    "sg:province":"NC",
    "sg:tags":[
        "worker",
        "day",
        "for",
        "chapel"
    ],
    "wof:name":"Jennifer Beatrice Templin",
    "wof:placetype":"venue"
},
  "geometry": {"coordinates":[-76.88766,34.8838],"type":"Point"}
}