{
  "type": "Feature",
  "properties": {
    "iso:country":"US",
    "sg:address":"75 Lowe St",
    "sg:city":"Canton",
    "sg:classifiers":[
        {
            "category":"Organizations",
            "subcategory":"Religious Organization",
            "type":"Services"
        }
    ],
    "sg:phone":"+1 828 648 5561",
    "sg:postcode":"28716",
    "sg:province":"NC",
    "sg:tags":[
        "church"
    ],
    "sg:website":"www.westcantonbaptist.org",
    "wof:name":"West Canton Baptist Church",
    "wof:placetype":"venue"
},
  "geometry": {"coordinates":[-82.859976,35.536072],"type":"Point"}
}