{
  "type": "Feature",
  "properties": {
    "iso:country":"US",
    "sg:address":"2550 Ravenhill Dr",
    "sg:city":"Fayetteville",
    "sg:classifiers":[
        {
            "category":"Professional",
            "type":"Services"
        }
    ],
    "sg:phone":"+1 910 223 0765",
    "sg:postcode":"28303",
    "sg:province":"NC",
    "sg:tags":[
        "establishment"
    ],
    "wof:name":"Highland Centre",
    "wof:placetype":"venue"
},
  "geometry": {"coordinates":[-78.925819,35.046746],"type":"Point"}
}