{
  "type": "Feature",
  "properties": {
    "iso:country":"US",
    "sg:address":"108 S Pitt St",
    "sg:city":"Greenville",
    "sg:classifiers":[
        {
            "category":"Professional",
            "subcategory":"Lawyer & Legal Services",
            "type":"Services"
        }
    ],
    "sg:phone":"+1 252 752 5505",
    "sg:postcode":"27834",
    "sg:province":"NC",
    "sg:tags":[
        "attorney"
    ],
    "wof:name":"Lanier & Taggart",
    "wof:placetype":"venue"
},
  "geometry": {"coordinates":[-77.375181,35.615772],"type":"Point"}
}