{
  "type": "Feature",
  "properties": {
    "iso:country":"US",
    "sg:address":"2 N Oak Forest Dr",
    "sg:city":"Asheville",
    "sg:classifiers":[
        {
            "category":"Professional",
            "type":"Services"
        }
    ],
    "sg:phone":"+1 828 279 7792",
    "sg:postcode":"28803",
    "sg:province":"NC",
    "wof:name":"Daniel Martinez",
    "wof:placetype":"venue"
},
  "geometry": {"coordinates":[-82.523448,35.49348],"type":"Point"}
}