{
  "type": "Feature",
  "properties": {
    "addr:full":"1511 Live Oak St Beaufort NC 28516",
    "addr:housenumber":"1511",
    "addr:postcode":"28516",
    "addr:street":"Live Oak St",
    "iso:country":"US",
    "sg:address":"1511 Live Oak St",
    "sg:city":"Beaufort",
    "sg:classifiers":[
        {
            "category":"Freight",
            "type":"Transportation"
        }
    ],
    "sg:phone":"+1 252 728 3523",
    "sg:postcode":"28516",
    "sg:province":"NC",
    "sg:tags":[
        "commercial",
        "storage"
    ],
    "wof:name":"Enviro Safe Storage",
    "wof:placetype":"venue"
},
  "geometry": {"coordinates":[-76.644764,34.72583],"type":"Point"}
}