{
  "type": "Feature",
  "properties": {
    "iso:country":"US",
    "sg:address":"151 17th St NW",
    "sg:city":"Hickory",
    "sg:classifiers":[
        {
            "category":"Professional",
            "subcategory":"Management & Consulting",
            "type":"Services"
        }
    ],
    "sg:phone":"+1   ",
    "sg:postcode":"28601",
    "sg:province":"NC",
    "wof:name":"Frye & Punch",
    "wof:placetype":"venue"
},
  "geometry": {"coordinates":[-81.367875,35.734258],"type":"Point"}
}