{
  "type": "Feature",
  "properties": {
    "iso:country":"US",
    "sg:address":"2424 Reynolda Rd",
    "sg:city":"Winston Salem",
    "sg:classifiers":[
        {
            "category":"Professional",
            "subcategory":"Management & Consulting",
            "type":"Services"
        }
    ],
    "sg:phone":"+1 336 773 1500",
    "sg:postcode":"27106",
    "sg:province":"NC",
    "sg:tags":[
        "consultant",
        "business"
    ],
    "wof:name":"Troyer Associates",
    "wof:placetype":"venue"
},
  "geometry": {"coordinates":[-80.289145,36.131005],"type":"Point"}
}