{
  "type": "Feature",
  "properties": {
    "addr:full":"1066 Benbrook Dr Nashville NC 27856",
    "addr:housenumber":"1066",
    "addr:postcode":"27856",
    "addr:street":"Benbrook Dr",
    "iso:country":"US",
    "sg:address":"1066 Benbrook Dr",
    "sg:city":"Nashville",
    "sg:classifiers":[
        {
            "category":"Building & Trades",
            "subcategory":"Construction",
            "type":"Services"
        }
    ],
    "sg:phone":"+1 252 459 6505",
    "sg:postcode":"27856",
    "sg:province":"NC",
    "sg:tags":[
        "home",
        "improvement"
    ],
    "wof:name":"Your Castle",
    "wof:placetype":"venue"
},
  "geometry": {"coordinates":[-77.92664600000001,35.956389],"type":"Point"}
}