{
  "type": "Feature",
  "properties": {
    "iso:country":"US",
    "sg:address":"4426 Arendell St",
    "sg:city":"Morehead City",
    "sg:classifiers":[
        {
            "category":"Shopping",
            "type":"Retail Goods"
        }
    ],
    "sg:phone":"+1 252 726 2333",
    "sg:postcode":"28557",
    "sg:province":"NC",
    "sg:tags":[
        "cosmetic",
        "perfume"
    ],
    "sg:website":"www.merlenorman.com",
    "wof:name":"Merle Norman Cosmetics",
    "wof:placetype":"venue"
},
  "geometry": {"coordinates":[-76.774742,34.729073],"type":"Point"}
}