{
  "type": "Feature",
  "properties": {
    "addr:full":"9510 Shannon Green Dr Charlotte NC 28213",
    "addr:housenumber":"9510",
    "addr:postcode":"28213",
    "addr:street":"Shannon Green Dr",
    "iso:country":"US",
    "sg:address":"9510 Shannon Green Dr",
    "sg:city":"Charlotte",
    "sg:classifiers":[
        {
            "category":"Retail",
            "subcategory":"Repair Shop",
            "type":"Services"
        }
    ],
    "sg:phone":"+1   ",
    "sg:postcode":"28213",
    "sg:province":"NC",
    "wof:name":"Paper Collage By Rae",
    "wof:placetype":"venue"
},
  "geometry": {"coordinates":[-80.726812,35.297205],"type":"Point"}
}