{
  "type": "Feature",
  "properties": {
    "addr:full":"500 Uwharrie Ct Ste A Raleigh NC 27606",
    "addr:housenumber":"500",
    "addr:postcode":"27606",
    "addr:street":"Uwharrie Ct Ste A",
    "iso:country":"US",
    "sg:address":"500 Uwharrie Ct Ste A",
    "sg:city":"Raleigh",
    "sg:classifiers":[
        {
            "category":"Professional",
            "subcategory":"Printing & Photocopies",
            "type":"Services"
        }
    ],
    "sg:phone":"+1 919 834 9313",
    "sg:postcode":"27606",
    "sg:province":"NC",
    "wof:name":"Griffin Printing Co",
    "wof:placetype":"venue"
},
  "geometry": {"coordinates":[-78.7033,35.792801],"type":"Point"}
}