{
  "type": "Feature",
  "properties": {
    "addr:full":"185 Horseshoe Rd Swansboro NC 28584",
    "addr:housenumber":"185",
    "addr:postcode":"28584",
    "addr:street":"Horseshoe Rd",
    "iso:country":"US",
    "sg:address":"185 Horseshoe Rd",
    "sg:city":"Swansboro",
    "sg:classifiers":[
        {
            "category":"Building & Trades",
            "subcategory":"Construction",
            "type":"Services"
        }
    ],
    "sg:phone":"+1 252 393 6676",
    "sg:postcode":"28584",
    "sg:province":"NC",
    "sg:tags":[
        "dry wall",
        "contractor"
    ],
    "wof:name":"Jay B Ammon Drywall & Painting",
    "wof:placetype":"venue"
},
  "geometry": {"coordinates":[-77.08703800000001,34.773967],"type":"Point"}
}