{
  "type": "Feature",
  "properties": {
    "addr:full":"245 S Bragg Blvd Spring Lake NC 28390",
    "addr:housenumber":"245",
    "addr:postcode":"28390",
    "addr:street":"S Bragg Blvd",
    "iso:country":"US",
    "sg:address":"245 S Bragg Blvd",
    "sg:city":"Spring Lake",
    "sg:classifiers":[
        {
            "category":"Banks & Credit Unions",
            "subcategory":"Bank",
            "type":"Services"
        }
    ],
    "sg:phone":"+1 910 495 9358",
    "sg:postcode":"28390",
    "sg:province":"NC",
    "sg:tags":[
        "financing"
    ],
    "wof:name":"Omni Military Loans",
    "wof:placetype":"venue"
},
  "geometry": {"coordinates":[-78.97202900000001,35.164423],"type":"Point"}
}