{
  "type": "Feature",
  "properties": {
    "addr:full":"3205 State Hwy 24 Newport NC 28570",
    "addr:housenumber":"3205",
    "addr:postcode":"28570",
    "addr:street":"State Hwy 24",
    "iso:country":"US",
    "sg:address":"3205 State Hwy 24",
    "sg:city":"Newport",
    "sg:classifiers":[
        {
            "category":"Real Estate",
            "subcategory":"Architect",
            "type":"Services"
        }
    ],
    "sg:phone":"+1 252 393 3726",
    "sg:postcode":"28570",
    "sg:province":"NC",
    "wof:name":"East Coast Design",
    "wof:placetype":"venue"
},
  "geometry": {"coordinates":[-76.947124,34.722473],"type":"Point"}
}