{
  "type": "Feature",
  "properties": {
    "addr:full":"5015 State Hwy 107 Glenville NC 28736",
    "addr:housenumber":"5015",
    "addr:postcode":"28736",
    "addr:street":"State Hwy 107",
    "iso:country":"US",
    "sg:address":"5015 State Hwy 107",
    "sg:city":"Glenville",
    "sg:classifiers":[
        {
            "category":"Building & Trades",
            "subcategory":"Plumbing",
            "type":"Services"
        }
    ],
    "sg:phone":"+1 828 743 0022",
    "sg:postcode":"28736",
    "sg:province":"NC",
    "sg:tags":[
        "conditioning",
        "air",
        "system",
        "contractor"
    ],
    "wof:name":"Cashiers Heat & Air LLC",
    "wof:placetype":"venue"
},
  "geometry": {"coordinates":[-83.125981,35.163584],"type":"Point"}
}