{
  "type": "Feature",
  "properties": {
    "iso:country":"US",
    "sg:address":"2205 Garnett St",
    "sg:city":"Henderson",
    "sg:classifiers":[
        {
            "category":"Real Estate",
            "subcategory":"Real Estate Operator",
            "type":"Services"
        }
    ],
    "sg:phone":"+1 252 438 3479",
    "sg:postcode":"27537",
    "sg:province":"NC",
    "sg:tags":[
        "building",
        "parks"
    ],
    "wof:name":"White's Utility Buildings",
    "wof:placetype":"venue"
},
  "geometry": {"coordinates":[-78.38433999999999,36.348532],"type":"Point"}
}