{
  "type": "Feature",
  "properties": {
    "addr:full":"385 Timber Rd Mooresville NC 28115",
    "addr:housenumber":"385",
    "addr:postcode":"28115",
    "addr:street":"Timber Rd",
    "iso:country":"US",
    "sg:address":"385 Timber Rd",
    "sg:city":"Mooresville",
    "sg:classifiers":[
        {
            "category":"Home & Garden",
            "subcategory":"Carpets & Floor Coverings",
            "type":"Retail Goods"
        }
    ],
    "sg:phone":"+1 704 662 9332",
    "sg:postcode":"28115",
    "sg:province":"NC",
    "wof:name":"A & A Mahdavans Rug Co",
    "wof:placetype":"venue"
},
  "geometry": {"coordinates":[-80.826525,35.560395],"type":"Point"}
}