{
  "type": "Feature",
  "properties": {
    "addr:full":"10 Eagle St Asheville NC 28801",
    "addr:housenumber":"10",
    "addr:postcode":"28801",
    "addr:street":"Eagle St",
    "iso:country":"US",
    "sg:address":"10 Eagle St",
    "sg:city":"Asheville",
    "sg:classifiers":[
        {
            "category":"Shopping",
            "subcategory":"Clothing, Apparel, & Fashions",
            "type":"Retail Goods"
        }
    ],
    "sg:phone":"+1 828 350 9661",
    "sg:postcode":"28801",
    "sg:province":"NC",
    "sg:tags":[
        "alteration"
    ],
    "wof:name":"Sewsi's Express Alterations",
    "wof:placetype":"venue"
},
  "geometry": {"coordinates":[-82.550196,35.594],"type":"Point"}
}