{
  "type": "Feature",
  "properties": {
    "addr:full":"4514 Thornwood Rd Charlotte NC 28213",
    "addr:housenumber":"4514",
    "addr:postcode":"28213",
    "addr:street":"Thornwood Rd",
    "iso:country":"US",
    "sg:address":"4514 Thornwood Rd",
    "sg:city":"Charlotte",
    "sg:classifiers":[
        {
            "category":"Banks & Credit Unions",
            "subcategory":"Financial Services",
            "type":"Services"
        }
    ],
    "sg:phone":"+1 704 596 4836",
    "sg:postcode":"28213",
    "sg:province":"NC",
    "sg:tags":[
        "investor"
    ],
    "wof:name":"Future Investment Co",
    "wof:placetype":"venue"
},
  "geometry": {"coordinates":[-80.787747,35.27023],"type":"Point"}
}