{
  "type": "Feature",
  "properties": {
    "addr:full":"196 Sparger Rd Mount Airy NC 27030",
    "addr:housenumber":"196",
    "addr:postcode":"27030",
    "addr:street":"Sparger Rd",
    "iso:country":"US",
    "sg:address":"196 Sparger Rd",
    "sg:city":"Mount Airy",
    "sg:classifiers":[
        {
            "category":"Building & Trades",
            "subcategory":"Landscaping Services",
            "type":"Services"
        }
    ],
    "sg:phone":"+1 336 789 4410",
    "sg:postcode":"27030",
    "sg:province":"NC",
    "wof:name":"Southern Pride Landscaping",
    "wof:placetype":"venue"
},
  "geometry": {"coordinates":[-80.666697,36.506016],"type":"Point"}
}