{
  "type": "Feature",
  "properties": {
    "iso:country":"US",
    "sg:address":"5021 Country Club Rd",
    "sg:city":"Winston Salem",
    "sg:classifiers":[
        {
            "category":"Insurance",
            "subcategory":"Insurance Agent",
            "type":"Services"
        }
    ],
    "sg:phone":"+1 336 760 6565",
    "sg:postcode":"27104",
    "sg:province":"NC",
    "sg:tags":[
        "agency"
    ],
    "wof:name":"Castor Insurance Agency Inc",
    "wof:placetype":"venue"
},
  "geometry": {"coordinates":[-80.35028800000001,36.084769],"type":"Point"}
}