{
  "type": "Feature",
  "properties": {
    "iso:country":"US",
    "sg:address":"253 US Hwy 258",
    "sg:city":"Como",
    "sg:classifiers":[
        {
            "category":"Professional",
            "subcategory":"Business Services",
            "type":"Services"
        }
    ],
    "sg:phone":"+1 252 398 5575",
    "sg:postcode":"27818",
    "sg:province":"NC",
    "sg:tags":[
        "event"
    ],
    "wof:name":"Diamond's Event Ctr",
    "wof:placetype":"venue"
},
  "geometry": {"coordinates":[-77.073407,36.460015],"type":"Point"}
}