{
  "type": "Feature",
  "properties": {
    "iso:country":"US",
    "sg:address":"915 Burke St NW",
    "sg:city":"Winston Salem",
    "sg:classifiers":[
        {
            "category":"Food & Beverages",
            "subcategory":"Liquor & Beverages",
            "type":"Retail Goods"
        },
        {
            "category":"Wholesale",
            "subcategory":"Groceries",
            "type":"Manufacturing & Wholesale Goods"
        }
    ],
    "sg:phone":"+1 336 722 2774",
    "sg:postcode":"27101",
    "sg:province":"NC",
    "sg:tags":[
        "beer",
        "ale"
    ],
    "sg:website":"www.citybeverage.com",
    "wof:name":"City Beverage Homebrew Supply",
    "wof:placetype":"venue"
},
  "geometry": {"coordinates":[-80.257166,36.095459],"type":"Point"}
}