{
  "type": "Feature",
  "properties": {
    "addr:full":"221 W Bank Dr Charlotte NC 28214",
    "addr:housenumber":"221",
    "addr:postcode":"28214",
    "addr:street":"W Bank Dr",
    "iso:country":"US",
    "sg:address":"221 W Bank Dr",
    "sg:city":"Charlotte",
    "sg:classifiers":[
        {
            "category":"Building & Trades",
            "subcategory":"Construction",
            "type":"Services"
        }
    ],
    "sg:phone":"+1 704 391 1411",
    "sg:postcode":"28214",
    "sg:province":"NC",
    "sg:tags":[
        "house"
    ],
    "wof:name":"C REA Builders Inc",
    "wof:placetype":"venue"
},
  "geometry": {"coordinates":[-80.94030600000001,35.293863],"type":"Point"}
}