{
  "type": "Feature",
  "properties": {
    "addr:full":"231 S White St Wake Forest NC 27587",
    "addr:housenumber":"231",
    "addr:postcode":"27587",
    "addr:street":"S White St",
    "iso:country":"US",
    "sg:address":"231 S White St",
    "sg:city":"Wake Forest",
    "sg:classifiers":[
        {
            "category":"Banks & Credit Unions",
            "subcategory":"Bank",
            "type":"Services"
        }
    ],
    "sg:phone":"+1 919 556 2021",
    "sg:postcode":"27587",
    "sg:province":"NC",
    "wof:name":"Fidelity Bank",
    "wof:placetype":"venue"
},
  "geometry": {"coordinates":[-78.509798,35.977626],"type":"Point"}
}