{
  "type": "Feature",
  "properties": {
    "iso:country":"US",
    "sg:address":"100 W B St",
    "sg:city":"Newton",
    "sg:classifiers":[
        {
            "category":"Government",
            "subcategory":"Court House",
            "type":"Public Place"
        }
    ],
    "sg:phone":"+1 828 466 6116",
    "sg:postcode":"28658",
    "sg:province":"NC",
    "sg:tags":[
        "county"
    ],
    "wof:name":"Catawba County Magistrate",
    "wof:placetype":"venue"
},
  "geometry": {"coordinates":[-81.22493900000001,35.66252],"type":"Point"}
}