{
  "type": "Feature",
  "properties": {
    "iso:country":"US",
    "sg:address":"162 McKnight Rd",
    "sg:city":"Advance",
    "sg:classifiers":[
        {
            "category":"Wholesale",
            "subcategory":"Construction Materials",
            "type":"Manufacturing & Wholesale Goods"
        }
    ],
    "sg:phone":"+1 336 998 4312",
    "sg:postcode":"27006",
    "sg:province":"NC",
    "sg:tags":[
        "fence"
    ],
    "wof:name":"Shore Custom Fencing LLC",
    "wof:placetype":"venue"
},
  "geometry": {"coordinates":[-80.488162,36.020898],"type":"Point"}
}