{
  "type": "Feature",
  "properties": {
    "addr:full":"201 Melanie Ct Clayton NC 27520",
    "addr:housenumber":"201",
    "addr:postcode":"27520",
    "addr:street":"Melanie Ct",
    "iso:country":"US",
    "sg:address":"201 Melanie Ct",
    "sg:city":"Clayton",
    "sg:classifiers":[
        {
            "category":"Manufacturing",
            "subcategory":"Tools & Machinery",
            "type":"Manufacturing & Wholesale Goods"
        }
    ],
    "sg:phone":"+1 919 359 1373",
    "sg:postcode":"27520",
    "sg:province":"NC",
    "sg:tags":[
        "industrial",
        "mfg"
    ],
    "wof:name":"Team Carbo LLC",
    "wof:placetype":"venue"
},
  "geometry": {"coordinates":[-78.50772499999999,35.551127],"type":"Point"}
}