{
  "type": "Feature",
  "properties": {
    "addr:full":"9733 Blackwell Rd SE Leland NC 28451",
    "addr:housenumber":"9733",
    "addr:postcode":"28451",
    "addr:street":"Blackwell Rd Se",
    "iso:country":"US",
    "sg:address":"9733 Blackwell Rd SE",
    "sg:city":"Leland",
    "sg:classifiers":[
        {
            "category":"Freight",
            "type":"Transportation"
        }
    ],
    "sg:phone":"+1 910 450 2110",
    "sg:postcode":"28451",
    "sg:province":"NC",
    "sg:tags":[
        "trucking"
    ],
    "wof:name":"Mansfield Transport",
    "wof:placetype":"venue"
},
  "geometry": {"coordinates":[-78.01116399999999,34.220608],"type":"Point"}
}