{
  "type": "Feature",
  "properties": {
    "addr:full":"30 Whiteville Plz Whiteville NC 28472",
    "addr:housenumber":"30",
    "addr:postcode":"28472",
    "addr:street":"Whiteville Plz",
    "iso:country":"US",
    "sg:address":"30 Whiteville Plz",
    "sg:city":"Whiteville",
    "sg:classifiers":[
        {
            "category":"Restaurant",
            "type":"Food & Drink"
        }
    ],
    "sg:phone":"+1 910 642 4500",
    "sg:postcode":"28472",
    "sg:province":"NC",
    "sg:website":"www.andyscheesesteaks.com",
    "wof:name":"Andy's Of Whiteville",
    "wof:placetype":"venue"
},
  "geometry": {"coordinates":[-78.71239,34.309349],"type":"Point"}
}