{
  "type": "Feature",
  "properties": {
    "addr:full":"101 Shore Lake Dr Greensboro NC 27455",
    "addr:housenumber":"101",
    "addr:postcode":"27455",
    "addr:street":"Shore Lake Dr",
    "iso:country":"US",
    "sg:address":"101 Shore Lake Dr",
    "sg:city":"Greensboro",
    "sg:classifiers":[
        {
            "category":"Real Estate",
            "subcategory":"Real Estate Agent",
            "type":"Services"
        }
    ],
    "sg:phone":"+1 336 545 1605",
    "sg:postcode":"27455",
    "sg:province":"NC",
    "sg:tags":[
        "finding",
        "apartment",
        "rental"
    ],
    "wof:name":"Waterford Place Apartments",
    "wof:placetype":"venue"
},
  "geometry": {"coordinates":[-79.810214,36.144888],"type":"Point"}
}