{
  "type": "Feature",
  "properties": {
    "iso:country":"US",
    "sg:address":"202 S Vance St",
    "sg:city":"Sanford",
    "sg:classifiers":[
        {
            "category":"Shopping",
            "subcategory":"Clothing, Apparel, & Fashions",
            "type":"Retail Goods"
        }
    ],
    "sg:phone":"+1 919 774 1665",
    "sg:postcode":"27330",
    "sg:province":"NC",
    "sg:tags":[
        "salvage",
        "surplus",
        "merchandise"
    ],
    "wof:name":"Stanley & Co",
    "wof:placetype":"venue"
},
  "geometry": {"coordinates":[-79.18203099999999,35.477207],"type":"Point"}
}