{
  "type": "Feature",
  "properties": {
    "iso:country":"US",
    "sg:address":"7638 Firethorn Dr",
    "sg:city":"Fayetteville",
    "sg:classifiers":[
        {
            "category":"Retail",
            "subcategory":"Auto Rental",
            "type":"Services"
        }
    ],
    "sg:phone":"+1 910 488 6436",
    "sg:postcode":"28311",
    "sg:province":"NC",
    "sg:tags":[
        "recreational",
        "leasing",
        "vehicle"
    ],
    "sg:website":"www.mobilervser.com",
    "wof:name":"H & S Mobile Rv SVC & Repair",
    "wof:placetype":"venue"
},
  "geometry": {"coordinates":[-78.874758,35.202875],"type":"Point"}
}