{
  "type": "Feature",
  "properties": {
    "addr:full":"798 Brevard Road Asheville NC 28801",
    "addr:housenumber":"798",
    "addr:postcode":"28801",
    "addr:street":"Brevard Road",
    "iso:country":"US",
    "sg:address":"798 Brevard Road",
    "sg:city":"Asheville",
    "sg:classifiers":[
        {
            "category":"Restaurant",
            "type":"Food & Drink"
        }
    ],
    "sg:phone":"+1 828 670 1153",
    "sg:postcode":"28801",
    "sg:province":"NC",
    "sg:tags":[
        "diner"
    ],
    "sg:website":"www.wafflehouse.com/",
    "wof:name":"Waffle House",
    "wof:placetype":"venue"
},
  "geometry": {"coordinates":[-82.601118,35.534663],"type":"Point"}
}