{
  "type": "Feature",
  "properties": {
    "addr:full":"2611 Richard Dr Greenville NC 27834",
    "addr:housenumber":"2611",
    "addr:postcode":"27834",
    "addr:street":"Richard Dr",
    "iso:country":"US",
    "sg:address":"2611 Richard Dr",
    "sg:city":"Greenville",
    "sg:classifiers":[
        {
            "category":"Professional",
            "type":"Services"
        }
    ],
    "sg:phone":"+1   ",
    "sg:postcode":"27834",
    "sg:province":"NC",
    "wof:name":"Total Care Services Inc",
    "wof:placetype":"venue"
},
  "geometry": {"coordinates":[-77.41176,35.622698],"type":"Point"}
}