{
  "type": "Feature",
  "properties": {
    "addr:full":"1439 Longleaf Ct Matthews NC 28104",
    "addr:housenumber":"1439",
    "addr:postcode":"28104",
    "addr:street":"Longleaf Ct",
    "iso:country":"US",
    "sg:address":"1439 Longleaf Ct",
    "sg:city":"Matthews",
    "sg:classifiers":[
        {
            "category":"Health Services",
            "subcategory":"Clinic",
            "type":"Services"
        }
    ],
    "sg:phone":"+1   ",
    "sg:postcode":"28104",
    "sg:province":"NC",
    "wof:name":"NC/Crna Inc",
    "wof:placetype":"venue"
},
  "geometry": {"coordinates":[-80.71880299999999,35.033994],"type":"Point"}
}