{
  "type": "Feature",
  "properties": {
    "addr:full":"316 E Lawyers Rd Monroe NC 28110",
    "addr:housenumber":"316",
    "addr:postcode":"28110",
    "addr:street":"E Lawyers Rd",
    "iso:country":"US",
    "sg:address":"316 E Lawyers Rd",
    "sg:city":"Monroe",
    "sg:classifiers":[
        {
            "category":"Utilities",
            "subcategory":"Refuse",
            "type":"Services"
        }
    ],
    "sg:phone":"+1 704 563 0290",
    "sg:postcode":"28110",
    "sg:province":"NC",
    "sg:tags":[
        "garbage",
        "collection",
        "system"
    ],
    "wof:name":"Aargone Rubbish Removal & Demo",
    "wof:placetype":"venue"
},
  "geometry": {"coordinates":[-80.531756,35.103171],"type":"Point"}
}