{
  "type": "Feature",
  "properties": {
    "iso:country":"US",
    "sg:address":"12233 Eastfield Rd",
    "sg:city":"Huntersville",
    "sg:classifiers":[
        {
            "category":"Real Estate",
            "subcategory":"Real Estate Agent",
            "type":"Services"
        }
    ],
    "sg:phone":"+1 704 948 7010",
    "sg:postcode":"28078",
    "sg:province":"NC",
    "sg:website":"www.charlottearearealtor.com",
    "wof:name":"Universal Realty",
    "wof:placetype":"venue"
},
  "geometry": {"coordinates":[-80.79652400000001,35.378869],"type":"Point"}
}