{
  "type": "Feature",
  "properties": {
    "iso:country":"US",
    "sg:address":"1670 US Hwy 601",
    "sg:city":"Mocksville",
    "sg:classifiers":[
        {
            "category":"Restaurant",
            "type":"Food & Drink"
        }
    ],
    "sg:phone":"+1 336 753 8100",
    "sg:postcode":"27028",
    "sg:province":"NC",
    "wof:name":"Dairy Queen",
    "wof:placetype":"venue"
},
  "geometry": {"coordinates":[-80.54938199999999,35.86062],"type":"Point"}
}