{
  "type": "Feature",
  "properties": {
    "addr:full":"1525 S Broad St Winston Salem NC 27101",
    "addr:housenumber":"1525",
    "addr:postcode":"27101",
    "addr:street":"S Broad St",
    "iso:country":"US",
    "sg:address":"1525 S Broad St",
    "sg:city":"Winston Salem",
    "sg:classifiers":[
        {
            "category":"Social Services",
            "type":"Services"
        }
    ],
    "sg:phone":"+1 336 722 8859",
    "sg:postcode":"27101",
    "sg:province":"NC",
    "sg:tags":[
        "organization",
        "welfare"
    ],
    "wof:name":"Salvation Army",
    "wof:placetype":"venue"
},
  "geometry": {"coordinates":[-80.24356899999999,36.076752],"type":"Point"}
}