{
  "type": "Feature",
  "properties": {
    "iso:country":"US",
    "sg:address":"551 Alpine Rd",
    "sg:city":"Winston Salem",
    "sg:classifiers":[
        {
            "category":"Health Services",
            "subcategory":"Health Practitioner",
            "type":"Services"
        }
    ],
    "sg:phone":"+1   ",
    "sg:postcode":"27104",
    "sg:province":"NC",
    "wof:name":"Sandy Aycoth Incorporated",
    "wof:placetype":"venue"
},
  "geometry": {"coordinates":[-80.338318,36.096672],"type":"Point"}
}