{
  "type": "Feature",
  "properties": {
    "iso:country":"US",
    "sg:address":"629 Rockwood Dr",
    "sg:city":"Graham",
    "sg:classifiers":[
        {
            "category":"Building & Trades",
            "subcategory":"Cleaning & Sanitation",
            "type":"Services"
        }
    ],
    "sg:phone":"+1   ",
    "sg:postcode":"27253",
    "sg:province":"NC",
    "wof:name":"Moores Sales & Service",
    "wof:placetype":"venue"
},
  "geometry": {"coordinates":[-79.417731,36.03979],"type":"Point"}
}