{
  "type": "Feature",
  "properties": {
    "iso:country":"US",
    "sg:address":"107 Lake Meadow Dr",
    "sg:city":"Apex",
    "sg:classifiers":[
        {
            "category":"Retail",
            "subcategory":"Auto Repair",
            "type":"Services"
        }
    ],
    "sg:phone":"+1 919 303 6180",
    "sg:postcode":"27502",
    "sg:province":"NC",
    "sg:tags":[
        "wrecker"
    ],
    "wof:name":"Apex Towing & Hauling",
    "wof:placetype":"venue"
},
  "geometry": {"coordinates":[-78.843034,35.729181],"type":"Point"}
}