{
  "type": "Feature",
  "properties": {
    "iso:country":"US",
    "sg:address":"4400 Sharon Rd",
    "sg:city":"Charlotte",
    "sg:classifiers":[
        {
            "category":"Professional",
            "subcategory":"Business Services",
            "type":"Services"
        }
    ],
    "sg:phone":"+1   ",
    "sg:postcode":"28211",
    "sg:province":"NC",
    "wof:name":"Space Design Inc",
    "wof:placetype":"venue"
},
  "geometry": {"coordinates":[-80.829365,35.150679],"type":"Point"}
}