{
  "type": "Feature",
  "properties": {
    "iso:country":"US",
    "sg:address":"1116 W Charlotte Ave",
    "sg:city":"Mount Holly",
    "sg:classifiers":[
        {
            "category":"Retail",
            "subcategory":"Auto Repair",
            "type":"Services"
        }
    ],
    "sg:phone":"+1   ",
    "sg:postcode":"28120",
    "sg:province":"NC",
    "sg:tags":[
        "automotive"
    ],
    "wof:name":"Hometown Automotive",
    "wof:placetype":"venue"
},
  "geometry": {"coordinates":[-81.03567,35.310132],"type":"Point"}
}