{
  "type": "Feature",
  "properties": {
    "iso:country":"US",
    "sg:address":"8309 Wilkinson Blvd",
    "sg:city":"Charlotte",
    "sg:classifiers":[
        {
            "category":"Manufacturing",
            "subcategory":"Chemicals & Compounds",
            "type":"Manufacturing & Wholesale Goods"
        }
    ],
    "sg:phone":"+1 704 393 0089",
    "sg:postcode":"28214",
    "sg:province":"NC",
    "sg:tags":[
        "textile",
        "plant",
        "paper"
    ],
    "wof:name":"Noveon Textile Chemicals Inc",
    "wof:placetype":"venue"
},
  "geometry": {"coordinates":[-80.982147,35.241336],"type":"Point"}
}