{
  "type": "Feature",
  "properties": {
    "addr:full":"322 Timber Rd Iron Station NC 28080",
    "addr:housenumber":"322",
    "addr:postcode":"28080",
    "addr:street":"Timber Rd",
    "iso:country":"US",
    "sg:address":"322 Timber Rd",
    "sg:city":"Iron Station",
    "sg:classifiers":[
        {
            "category":"Building & Trades",
            "subcategory":"Construction",
            "type":"Services"
        }
    ],
    "sg:phone":"+1 704 732 1424",
    "sg:postcode":"28080",
    "sg:province":"NC",
    "sg:tags":[
        "hanging",
        "contractor"
    ],
    "wof:name":"Quality House Painting",
    "wof:placetype":"venue"
},
  "geometry": {"coordinates":[-81.12615099999999,35.463425],"type":"Point"}
}