{
  "type": "Feature",
  "properties": {
    "addr:full":"4017 Country Club Rd Winston Salem NC 27104",
    "addr:housenumber":"4017",
    "addr:postcode":"27104",
    "addr:street":"Country Club Rd",
    "iso:country":"US",
    "sg:address":"4017 Country Club Rd",
    "sg:city":"Winston Salem",
    "sg:classifiers":[
        {
            "category":"Government",
            "subcategory":"Office",
            "type":"Public Place"
        }
    ],
    "sg:phone":"+1 336 659 9033",
    "sg:postcode":"27104",
    "sg:province":"NC",
    "sg:tags":[
        "sector",
        "regulation",
        "commercial"
    ],
    "wof:name":"Forsyth Municipal ABC Board",
    "wof:placetype":"venue"
},
  "geometry": {"coordinates":[-80.318215,36.089962],"type":"Point"}
}