{
  "type": "Feature",
  "properties": {
    "iso:country":"US",
    "sg:address":"306 Oak Grove Rd",
    "sg:city":"Boone",
    "sg:classifiers":[
        {
            "category":"Organizations",
            "subcategory":"Religious Organization",
            "type":"Services"
        }
    ],
    "sg:phone":"+1 828 264 2642",
    "sg:postcode":"28607",
    "sg:province":"NC",
    "sg:tags":[
        "church"
    ],
    "wof:name":"Oak Grove Baptist Church",
    "wof:placetype":"venue"
},
  "geometry": {"coordinates":[-81.704869,36.221923],"type":"Point"}
}