{
  "type": "Feature",
  "properties": {
    "addr:full":"2544 Grandview Cir SW Lenoir NC 28645",
    "addr:housenumber":"2544",
    "addr:postcode":"28645",
    "addr:street":"Grandview Cir Sw",
    "iso:country":"US",
    "sg:address":"2544 Grandview Cir SW",
    "sg:city":"Lenoir",
    "sg:classifiers":[
        {
            "category":"Health Services",
            "subcategory":"Nursing And Care Facility",
            "type":"Services"
        },
        {
            "category":"Social Services",
            "subcategory":"Adult Care",
            "type":"Services"
        }
    ],
    "sg:phone":"+1 828 757 0136",
    "sg:postcode":"28645",
    "sg:province":"NC",
    "sg:tags":[
        "home",
        "residential"
    ],
    "wof:name":"Grandview Villa Assisted Livin",
    "wof:placetype":"venue"
},
  "geometry": {"coordinates":[-81.57990700000001,35.886099],"type":"Point"}
}