{
  "type": "Feature",
  "properties": {
    "addr:full":"6213 Angus Dr Raleigh NC 27617",
    "addr:housenumber":"6213",
    "addr:postcode":"27617",
    "addr:street":"Angus Dr",
    "iso:country":"US",
    "sg:address":"6213 Angus Dr",
    "sg:city":"Raleigh",
    "sg:classifiers":[
        {
            "category":"Building & Trades",
            "subcategory":"Equipment Rental",
            "type":"Services"
        }
    ],
    "sg:phone":"+1 919 571 4131",
    "sg:postcode":"27617",
    "sg:province":"NC",
    "sg:tags":[
        "crane"
    ],
    "wof:name":"Crane Pro Svc",
    "wof:placetype":"venue"
},
  "geometry": {"coordinates":[-78.755152,35.898661],"type":"Point"}
}