{
  "type": "Feature",
  "properties": {
    "addr:full":"2038 Jonestown Rd Deep Run NC 28525",
    "addr:housenumber":"2038",
    "addr:postcode":"28525",
    "addr:street":"Jonestown Rd",
    "iso:country":"US",
    "sg:address":"2038 Jonestown Rd",
    "sg:city":"Deep Run",
    "sg:classifiers":[
        {
            "category":"Home & Garden",
            "subcategory":"Garden Supply",
            "type":"Retail Goods"
        }
    ],
    "sg:phone":"+1 252 568 3762",
    "sg:postcode":"28525",
    "sg:province":"NC",
    "sg:tags":[
        "nursery"
    ],
    "wof:name":"Smiths Nursery",
    "wof:placetype":"venue"
},
  "geometry": {"coordinates":[-77.699645,35.080058],"type":"Point"}
}