{
  "type": "Feature",
  "properties": {
    "addr:full":"133 Long Ridge Dr Wilmington NC 28405",
    "addr:housenumber":"133",
    "addr:postcode":"28405",
    "addr:street":"Long Ridge Dr",
    "iso:country":"US",
    "sg:address":"133 Long Ridge Dr",
    "sg:city":"Wilmington",
    "sg:classifiers":[
        {
            "category":"Professional",
            "subcategory":"Business Services",
            "type":"Services"
        }
    ],
    "sg:phone":"+1   ",
    "sg:postcode":"28405",
    "sg:province":"NC",
    "wof:name":"S & W Bonding",
    "wof:placetype":"venue"
},
  "geometry": {"coordinates":[-77.870328,34.295207],"type":"Point"}
}