{
  "type": "Feature",
  "properties": {
    "iso:country":"US",
    "sg:address":"956 Aquaview Dr",
    "sg:city":"Kernersville",
    "sg:classifiers":[
        {
            "category":"Building & Trades",
            "subcategory":"Cleaning & Sanitation",
            "type":"Services"
        }
    ],
    "sg:phone":"+1 336 399 9742",
    "sg:postcode":"27284",
    "sg:province":"NC",
    "sg:tags":[
        "window"
    ],
    "wof:name":"Crystal Clear Window Cleaning",
    "wof:placetype":"venue"
},
  "geometry": {"coordinates":[-80.07650099999999,36.14437],"type":"Point"}
}