{
  "type": "Feature",
  "properties": {
    "addr:full":"1561 S Aspen St Lincolnton NC 28092",
    "addr:housenumber":"1561",
    "addr:postcode":"28092",
    "addr:street":"S Aspen St",
    "iso:country":"US",
    "sg:address":"1561 S Aspen St",
    "sg:city":"Lincolnton",
    "sg:classifiers":[
        {
            "category":"Personal",
            "type":"Services"
        }
    ],
    "sg:phone":"+1 704 732 5620",
    "sg:postcode":"28092",
    "sg:province":"NC",
    "wof:name":"Village Tanning Center",
    "wof:placetype":"venue"
},
  "geometry": {"coordinates":[-81.24589,35.454937],"type":"Point"}
}