{
  "type": "Feature",
  "properties": {
    "addr:full":"111 Marshallberg Rd Smyrna NC 28579",
    "addr:housenumber":"111",
    "addr:postcode":"28579",
    "addr:street":"Marshallberg Rd",
    "iso:country":"US",
    "sg:address":"111 Marshallberg Rd",
    "sg:city":"Smyrna",
    "sg:classifiers":[
        {
            "category":"Food & Beverages",
            "subcategory":"Groceries & Convenience Stores",
            "type":"Retail Goods"
        }
    ],
    "sg:phone":"+1 252 729 8001",
    "sg:postcode":"28579",
    "sg:province":"NC",
    "sg:tags":[
        "grocer"
    ],
    "wof:name":"G & R Supermarket",
    "wof:placetype":"venue"
},
  "geometry": {"coordinates":[-76.52751600000001,34.759439],"type":"Point"}
}