{
  "type": "Feature",
  "properties": {
    "addr:full":"312 Dunnegan Rd Hillsborough NC 27278",
    "addr:housenumber":"312",
    "addr:postcode":"27278",
    "addr:street":"Dunnegan Rd",
    "iso:country":"US",
    "sg:address":"312 Dunnegan Rd",
    "sg:city":"Hillsborough",
    "sg:classifiers":[
        {
            "category":"Manufacturing",
            "subcategory":"Lumber",
            "type":"Manufacturing & Wholesale Goods"
        }
    ],
    "sg:phone":"+1 919 471 3686",
    "sg:postcode":"27278",
    "sg:province":"NC",
    "sg:tags":[
        "forester"
    ],
    "wof:name":"Bernard Consulting Forestry",
    "wof:placetype":"venue"
},
  "geometry": {"coordinates":[-78.96219600000001,36.118149],"type":"Point"}
}