{
  "type": "Feature",
  "properties": {
    "iso:country":"US",
    "sg:address":"1304 Hillsborough St",
    "sg:city":"Raleigh",
    "sg:classifiers":[
        {
            "category":"Professional",
            "subcategory":"Management & Consulting",
            "type":"Services"
        }
    ],
    "sg:phone":"+1   ",
    "sg:postcode":"27605",
    "sg:province":"NC",
    "sg:tags":[
        "business"
    ],
    "wof:name":"Evaluation Resources LLC",
    "wof:placetype":"venue"
},
  "geometry": {"coordinates":[-78.656524,35.783618],"type":"Point"}
}