{
  "type": "Feature",
  "properties": {
    "iso:country":"US",
    "sg:address":"109 W Ash St",
    "sg:city":"Goldsboro",
    "sg:classifiers":[
        {
            "category":"Organizations",
            "subcategory":"Religious Organization",
            "type":"Services"
        }
    ],
    "sg:phone":"+1 919 736 0012",
    "sg:postcode":"27530",
    "sg:province":"NC",
    "sg:tags":[
        "church"
    ],
    "wof:name":"Spirit-Filled Family Worship",
    "wof:placetype":"venue"
},
  "geometry": {"coordinates":[-77.997471,35.38622],"type":"Point"}
}