{
  "type": "Feature",
  "properties": {
    "iso:country":"US",
    "sg:address":"285 Lakefield Rd",
    "sg:city":"Stokesdale",
    "sg:classifiers":[
        {
            "category":"Shopping",
            "type":"Retail Goods"
        }
    ],
    "sg:phone":"+1 336 548 6376",
    "sg:postcode":"27357",
    "sg:province":"NC",
    "sg:tags":[
        "awning",
        "canopy"
    ],
    "wof:name":"Belews Lake Awning & Fab Svc",
    "wof:placetype":"venue"
},
  "geometry": {"coordinates":[-79.99567399999999,36.307004],"type":"Point"}
}