{
  "type": "Feature",
  "properties": {
    "iso:country":"US",
    "sg:address":"8151 Lasater Rd",
    "sg:city":"Clemmons",
    "sg:classifiers":[
        {
            "category":"Professional",
            "type":"Services"
        }
    ],
    "sg:phone":"+1 336 778 9116",
    "sg:postcode":"27012",
    "sg:province":"NC",
    "wof:name":"Audrey B Moore",
    "wof:placetype":"venue"
},
  "geometry": {"coordinates":[-80.424745,36.029317],"type":"Point"}
}