{
  "type": "Feature",
  "properties": {
    "iso:country":"US",
    "sg:address":"109 Hinton Ave",
    "sg:city":"Wilmington",
    "sg:classifiers":[
        {
            "category":"Manufacturing",
            "subcategory":"Printing",
            "type":"Manufacturing & Wholesale Goods"
        }
    ],
    "sg:phone":"+1 910 794 9994",
    "sg:postcode":"28403",
    "sg:province":"NC",
    "sg:tags":[
        "publisher",
        "guide"
    ],
    "wof:name":"Homes & Land Magazine",
    "wof:placetype":"venue"
},
  "geometry": {"coordinates":[-77.84905500000001,34.211765],"type":"Point"}
}