{
  "type": "Feature",
  "properties": {
    "iso:country":"US",
    "sg:address":"1617 East Blvd",
    "sg:city":"Charlotte",
    "sg:classifiers":[
        {
            "category":"Real Estate",
            "subcategory":"Real Estate Agent",
            "type":"Services"
        }
    ],
    "sg:phone":"+1 704 333 3373",
    "sg:postcode":"28203",
    "sg:province":"NC",
    "wof:name":"Chase Communications",
    "wof:placetype":"venue"
},
  "geometry": {"coordinates":[-80.840603,35.199101],"type":"Point"}
}