{
  "type": "Feature",
  "properties": {
    "iso:country":"US",
    "sg:address":"613 E Southerland St",
    "sg:city":"Wallace",
    "sg:classifiers":[
        {
            "category":"Professional",
            "type":"Services"
        }
    ],
    "sg:phone":"+1 910 285 9992",
    "sg:postcode":"28466",
    "sg:province":"NC",
    "wof:name":"Carolina Unwired",
    "wof:placetype":"venue"
},
  "geometry": {"coordinates":[-77.98817200000001,34.738741],"type":"Point"}
}