{
  "type": "Feature",
  "properties": {
    "iso:country":"US",
    "sg:address":"1148 Little Laurel Rd",
    "sg:city":"Boone",
    "sg:classifiers":[
        {
            "category":"Building & Trades",
            "subcategory":"Construction",
            "type":"Services"
        }
    ],
    "sg:phone":"+1 828 262 1860",
    "sg:postcode":"28607",
    "sg:province":"NC",
    "sg:tags":[
        "contractor"
    ],
    "wof:name":"Stan Hanna Cnstr & Insptn",
    "wof:placetype":"venue"
},
  "geometry": {"coordinates":[-81.58872,36.183773],"type":"Point"}
}