{
  "type": "Feature",
  "properties": {
    "iso:country":"US",
    "sg:address":"104 N Davis St",
    "sg:city":"Micro",
    "sg:classifiers":[
        {
            "category":"Retail",
            "subcategory":"Repair Shop",
            "type":"Services"
        }
    ],
    "sg:phone":"+1 919 284 2788",
    "sg:postcode":"27555",
    "sg:province":"NC",
    "sg:tags":[
        "upholsterer"
    ],
    "wof:name":"Bill's Upholstery",
    "wof:placetype":"venue"
},
  "geometry": {"coordinates":[-78.20393199999999,35.564504],"type":"Point"}
}