{
  "type": "Feature",
  "properties": {
    "iso:country":"US",
    "sg:address":"857 Merrimon Ave",
    "sg:city":"Asheville",
    "sg:classifiers":[
        {
            "category":"Personal",
            "subcategory":"Barber",
            "type":"Services"
        }
    ],
    "sg:phone":"+1 828 254 6028",
    "sg:postcode":"28804",
    "sg:province":"NC",
    "wof:name":"Jack L Bell's Barber Shop",
    "wof:placetype":"venue"
},
  "geometry": {"coordinates":[-82.55289500000001,35.627347],"type":"Point"}
}