{
  "type": "Feature",
  "properties": {
    "iso:country":"US",
    "sg:address":"824 Ellis Rd",
    "sg:city":"Durham",
    "sg:classifiers":[
        {
            "category":"Wholesale",
            "subcategory":"Construction Materials",
            "type":"Manufacturing & Wholesale Goods"
        }
    ],
    "sg:phone":"+1 919 596 1381",
    "sg:postcode":"27703",
    "sg:province":"NC",
    "sg:tags":[
        "cement"
    ],
    "wof:name":"Giant Portland Cement Co",
    "wof:placetype":"venue"
},
  "geometry": {"coordinates":[-78.87110800000001,35.961124],"type":"Point"}
}