{
  "type": "Feature",
  "properties": {
    "addr:full":"4208 Windsor Pl Raleigh NC 27609",
    "addr:housenumber":"4208",
    "addr:postcode":"27609",
    "addr:street":"Windsor Pl",
    "iso:country":"US",
    "sg:address":"4208 Windsor Pl",
    "sg:city":"Raleigh",
    "sg:classifiers":[
        {
            "category":"Professional",
            "subcategory":"Accounting & Tax Preparation",
            "type":"Services"
        }
    ],
    "sg:phone":"+1 919 782 1281",
    "sg:postcode":"27609",
    "sg:province":"NC",
    "sg:tags":[
        "bookkeeping",
        "general"
    ],
    "wof:name":"Tant Accounting Svc Inc",
    "wof:placetype":"venue"
},
  "geometry": {"coordinates":[-78.631336,35.839615],"type":"Point"}
}