{
  "type": "Feature",
  "properties": {
    "addr:full":"200 N Grove St Hendersonville NC 28792",
    "addr:housenumber":"200",
    "addr:postcode":"28792",
    "addr:street":"N Grove St",
    "iso:country":"US",
    "sg:address":"200 N Grove St",
    "sg:city":"Hendersonville",
    "sg:classifiers":[
        {
            "category":"Professional",
            "subcategory":"Business Services",
            "type":"Services"
        }
    ],
    "sg:phone":"+1 828 697 4854",
    "sg:postcode":"28792",
    "sg:province":"NC",
    "sg:tags":[
        "executive"
    ],
    "wof:name":"Justice Wide Area Network",
    "wof:placetype":"venue"
},
  "geometry": {"coordinates":[-82.45768099999999,35.316202],"type":"Point"}
}