{
  "type": "Feature",
  "properties": {
    "iso:country":"US",
    "sg:address":"4913 Chastain Ave",
    "sg:city":"Charlotte",
    "sg:classifiers":[
        {
            "category":"Organizations",
            "subcategory":"Professional Association",
            "type":"Services"
        }
    ],
    "sg:phone":"+1 704 522 1178",
    "sg:postcode":"28217",
    "sg:province":"NC",
    "wof:name":"Carolina Pro Saleswomen",
    "wof:placetype":"venue"
},
  "geometry": {"coordinates":[-80.88203300000001,35.173992],"type":"Point"}
}