{
  "type": "Feature",
  "properties": {
    "addr:full":"801 Fairview St Asheville NC 28803",
    "addr:housenumber":"801",
    "addr:postcode":"28803",
    "addr:street":"Fairview St",
    "iso:country":"US",
    "sg:address":"801 Fairview St",
    "sg:city":"Asheville",
    "sg:classifiers":[
        {
            "category":"Restaurant",
            "type":"Food & Drink"
        }
    ],
    "sg:phone":"+1 828 299 8999",
    "sg:postcode":"28803",
    "sg:province":"NC",
    "sg:tags":[
        "eating"
    ],
    "wof:name":"Subway",
    "wof:placetype":"venue"
},
  "geometry": {"coordinates":[-82.53622799999999,35.550024],"type":"Point"}
}