{
  "type": "Feature",
  "properties": {
    "addr:full":"2133 Park Summit Blvd Apex NC 27523",
    "addr:housenumber":"2133",
    "addr:postcode":"27523",
    "addr:street":"Park Summit Blvd",
    "iso:country":"US",
    "sg:address":"2133 Park Summit Blvd",
    "sg:city":"Apex",
    "sg:classifiers":[
        {
            "category":"Utilities",
            "subcategory":"Telephone",
            "type":"Services"
        }
    ],
    "sg:phone":"+1 919 460 1660",
    "sg:postcode":"27523",
    "sg:province":"NC",
    "sg:tags":[
        "telecommunication"
    ],
    "sg:website":"www.americantower.com",
    "wof:name":"American Tower Corp",
    "wof:placetype":"venue"
},
  "geometry": {"coordinates":[-78.82369799999999,35.747495],"type":"Point"}
}