{
  "type": "Feature",
  "properties": {
    "iso:country":"US",
    "sg:address":"230 Braswell Rd",
    "sg:city":"Goldsboro",
    "sg:classifiers":[
        {
            "category":"Restaurant",
            "type":"Food & Drink"
        }
    ],
    "sg:phone":"+1 919 735 8663",
    "sg:postcode":"27530",
    "sg:province":"NC",
    "sg:tags":[
        "eating"
    ],
    "wof:name":"Triangle Restaurant",
    "wof:placetype":"venue"
},
  "geometry": {"coordinates":[-78.081278,35.402357],"type":"Point"}
}