{
  "type": "Feature",
  "properties": {
    "addr:full":"532 Fielding Rd Charlotte NC 28214",
    "addr:housenumber":"532",
    "addr:postcode":"28214",
    "addr:street":"Fielding Rd",
    "iso:country":"US",
    "sg:address":"532 Fielding Rd",
    "sg:city":"Charlotte",
    "sg:classifiers":[
        {
            "category":"Freight",
            "type":"Transportation"
        }
    ],
    "sg:phone":"+1 704 394 1745",
    "sg:postcode":"28214",
    "sg:province":"NC",
    "sg:tags":[
        "operator",
        "local",
        "trucking"
    ],
    "wof:name":"James P Isenhour Sr",
    "wof:placetype":"venue"
},
  "geometry": {"coordinates":[-80.94259599999999,35.293152],"type":"Point"}
}