{
  "type": "Feature",
  "properties": {
    "addr:full":"202 N 3rd St Pinetops NC 27864",
    "addr:housenumber":"202",
    "addr:postcode":"27864",
    "addr:street":"N 3Rd St",
    "iso:country":"US",
    "sg:address":"202 N 3rd St",
    "sg:city":"Pinetops",
    "sg:classifiers":[
        {
            "category":"Recreation",
            "type":"Entertainment"
        }
    ],
    "sg:phone":"+1 252 827 4819",
    "sg:postcode":"27864",
    "sg:province":"NC",
    "sg:tags":[
        "historical"
    ],
    "wof:name":"Carlton Foundation Inc",
    "wof:placetype":"venue"
},
  "geometry": {"coordinates":[-77.63780300000001,35.793481],"type":"Point"}
}