{
  "type": "Feature",
  "properties": {
    "iso:country":"US",
    "sg:address":"825 Farmhurst Dr",
    "sg:city":"Charlotte",
    "sg:classifiers":[
        {
            "category":"Organizations",
            "subcategory":"Community Association",
            "type":"Services"
        }
    ],
    "sg:phone":"+1 704 525 8287",
    "sg:postcode":"28217",
    "sg:province":"NC",
    "wof:name":"Tree Top Condominiums",
    "wof:placetype":"venue"
},
  "geometry": {"coordinates":[-80.891966,35.146947],"type":"Point"}
}