{
  "type": "Feature",
  "properties": {
    "iso:country":"US",
    "sg:address":"1749 Williams Rd",
    "sg:city":"Monroe",
    "sg:classifiers":[
        {
            "category":"Professional",
            "type":"Services"
        }
    ],
    "sg:phone":"+1 704 226 1870",
    "sg:postcode":"28110",
    "sg:province":"NC",
    "sg:tags":[
        "establishment"
    ],
    "wof:name":"Miller's Inc",
    "wof:placetype":"venue"
},
  "geometry": {"coordinates":[-80.56844700000001,35.007925],"type":"Point"}
}