{
  "type": "Feature",
  "properties": {
    "addr:full":"3067 Kernersville Rd Winston Salem NC 27107",
    "addr:housenumber":"3067",
    "addr:postcode":"27107",
    "addr:street":"Kernersville Rd",
    "iso:country":"US",
    "sg:address":"3067 Kernersville Rd",
    "sg:city":"Winston Salem",
    "sg:classifiers":[
        {
            "category":"Personal",
            "subcategory":"Beauty Salon",
            "type":"Services"
        }
    ],
    "sg:phone":"+1 336 650 1555",
    "sg:postcode":"27107",
    "sg:province":"NC",
    "sg:tags":[
        "shop"
    ],
    "wof:name":"Carolina Hair Styles",
    "wof:placetype":"venue"
},
  "geometry": {"coordinates":[-80.177634,36.077081],"type":"Point"}
}