{
  "type": "Feature",
  "properties": {
    "iso:country":"US",
    "sg:address":"206 Forester Ave",
    "sg:city":"North Wilkesboro",
    "sg:classifiers":[
        {
            "category":"Organizations",
            "subcategory":"Non-profit Organization",
            "type":"Services"
        }
    ],
    "sg:phone":"+1 336 667 2800",
    "sg:postcode":"28659",
    "sg:province":"NC",
    "sg:tags":[
        "info",
        "addiction",
        "abuse",
        "treatment",
        "drug"
    ],
    "wof:name":"Narcotics Anonymous",
    "wof:placetype":"venue"
},
  "geometry": {"coordinates":[-81.14948,36.160462],"type":"Point"}
}