{
  "type": "Feature",
  "properties": {
    "addr:full":"412 E Main St Carrboro NC 27510",
    "addr:housenumber":"412",
    "addr:postcode":"27510",
    "addr:street":"E Main St",
    "iso:country":"US",
    "sg:address":"412 E Main St",
    "sg:city":"Carrboro",
    "sg:classifiers":[
        {
            "category":"Restaurant",
            "type":"Food & Drink"
        }
    ],
    "sg:menulink":"http://www.allmenus.com/nc/chapel-hill/85319-dominos-pizza/menu/",
    "sg:phone":"+1 919 929 0246",
    "sg:postcode":"27510",
    "sg:province":"NC",
    "sg:tags":[
        "american",
        "wing",
        "pizza"
    ],
    "wof:name":"Domino's Pizza",
    "wof:placetype":"venue"
},
  "geometry": {"coordinates":[-79.06661800000001,35.910533],"type":"Point"}
}