{
  "type": "Feature",
  "properties": {
    "iso:country":"US",
    "sg:address":"5097 Sykes Rd",
    "sg:city":"Nashville",
    "sg:classifiers":[
        {
            "category":"Building & Trades",
            "subcategory":"Plumbing",
            "type":"Services"
        }
    ],
    "sg:phone":"+1 252 459 3311",
    "sg:postcode":"27856",
    "sg:province":"NC",
    "sg:tags":[
        "conditioning",
        "air",
        "system",
        "contractor"
    ],
    "wof:name":"Beecham's Mobile Home Svc",
    "wof:placetype":"venue"
},
  "geometry": {"coordinates":[-78.023411,36.029538],"type":"Point"}
}