{
  "type": "Feature",
  "properties": {
    "addr:full":"124 E North St Albemarle NC 28001",
    "addr:housenumber":"124",
    "addr:postcode":"28001",
    "addr:street":"E North St",
    "iso:country":"US",
    "sg:address":"124 E North St",
    "sg:city":"Albemarle",
    "sg:classifiers":[
        {
            "category":"Social Services",
            "type":"Services"
        }
    ],
    "sg:phone":"+1   ",
    "sg:postcode":"28001",
    "sg:province":"NC",
    "sg:tags":[
        "clinic",
        "specialty",
        "outpatient"
    ],
    "wof:name":"Pregnncy Rsrce Ctr Stanly Coun",
    "wof:placetype":"venue"
},
  "geometry": {"coordinates":[-80.197675,35.352175],"type":"Point"}
}