{
  "type": "Feature",
  "properties": {
    "iso:country":"US",
    "sg:address":"2500 W Roosevelt Blvd",
    "sg:city":"Monroe",
    "sg:classifiers":[
        {
            "category":"Professional",
            "subcategory":"Management & Consulting",
            "type":"Services"
        }
    ],
    "sg:phone":"+1 704 292 7447",
    "sg:postcode":"28110",
    "sg:province":"NC",
    "sg:tags":[
        "fuel"
    ],
    "wof:name":"Griffin's Management",
    "wof:placetype":"venue"
},
  "geometry": {"coordinates":[-80.56989,35.014615],"type":"Point"}
}