{
  "type": "Feature",
  "properties": {
    "iso:country":"US",
    "sg:address":"419 Nash St E",
    "sg:city":"Wilson",
    "sg:classifiers":[
        {
            "category":"Personal",
            "subcategory":"Beauty Salon",
            "type":"Services"
        }
    ],
    "sg:phone":"+1 252 246 9200",
    "sg:postcode":"27893",
    "sg:province":"NC",
    "wof:name":"Tee's Beauty & Style Salon",
    "wof:placetype":"venue"
},
  "geometry": {"coordinates":[-77.907827,35.722695],"type":"Point"}
}