{
  "type": "Feature",
  "properties": {
    "iso:country":"US",
    "sg:address":"4520 Cumberland Rd",
    "sg:city":"Fayetteville",
    "sg:classifiers":[
        {
            "category":"Manufacturing",
            "subcategory":"Building Materials",
            "type":"Manufacturing & Wholesale Goods"
        }
    ],
    "sg:phone":"+1 910 425 4296",
    "sg:postcode":"28306",
    "sg:province":"NC",
    "sg:tags":[
        "mfg",
        "wood",
        "kitchen",
        "cabinet"
    ],
    "wof:name":"Bentley Cabinet Shop",
    "wof:placetype":"venue"
},
  "geometry": {"coordinates":[-78.959819,35.008694],"type":"Point"}
}