{
  "type": "Feature",
  "properties": {
    "addr:full":"9712 Mini Ranch Rd Waxhaw NC 28173",
    "addr:housenumber":"9712",
    "addr:postcode":"28173",
    "addr:street":"Mini Ranch Rd",
    "iso:country":"US",
    "sg:address":"9712 Mini Ranch Rd",
    "sg:city":"Waxhaw",
    "sg:classifiers":[
        {
            "category":"Building & Trades",
            "subcategory":"Plumbing",
            "type":"Services"
        }
    ],
    "sg:phone":"+1 704 843 5953",
    "sg:postcode":"28173",
    "sg:province":"NC",
    "sg:tags":[
        "contractor"
    ],
    "wof:name":"OLeary Heating & AC",
    "wof:placetype":"venue"
},
  "geometry": {"coordinates":[-80.786418,34.831491],"type":"Point"}
}