{
  "type": "Feature",
  "properties": {
    "iso:country":"US",
    "sg:address":"800 Bentwood Ct",
    "sg:city":"Matthews",
    "sg:classifiers":[
        {
            "category":"Real Estate",
            "subcategory":"Real Estate Agent",
            "type":"Services"
        }
    ],
    "sg:phone":"+1 704 847 5380",
    "sg:postcode":"28105",
    "sg:province":"NC",
    "wof:name":"Baker Real Estate",
    "wof:placetype":"venue"
},
  "geometry": {"coordinates":[-80.69745399999999,35.133852],"type":"Point"}
}