{
  "type": "Feature",
  "properties": {
    "iso:country":"US",
    "sg:address":"2046 Chapel Hill Rd",
    "sg:city":"Burlington",
    "sg:classifiers":[
        {
            "category":"Personal",
            "type":"Services"
        }
    ],
    "sg:phone":"+1 336 227 1200",
    "sg:postcode":"27215",
    "sg:province":"NC",
    "sg:tags":[
        "program",
        "physical",
        "exercise",
        "fitness"
    ],
    "wof:name":"Fitness Solution",
    "wof:placetype":"venue"
},
  "geometry": {"coordinates":[-79.429929,36.067728],"type":"Point"}
}