{
  "type": "Feature",
  "properties": {
    "iso:country":"US",
    "sg:address":"762 Spencer Ave",
    "sg:city":"Asheboro",
    "sg:classifiers":[
        {
            "category":"Professional",
            "type":"Services"
        }
    ],
    "sg:phone":"+1 336 879 1876",
    "sg:postcode":"27203",
    "sg:province":"NC",
    "wof:name":"Causekeepers",
    "wof:placetype":"venue"
},
  "geometry": {"coordinates":[-79.826302,35.695421],"type":"Point"}
}