{
  "type": "Feature",
  "properties": {
    "iso:country":"US",
    "sg:address":"1827 S Fayetteville St",
    "sg:city":"Asheboro",
    "sg:classifiers":[
        {
            "category":"Social Services",
            "subcategory":"Child Care",
            "type":"Services"
        }
    ],
    "sg:phone":"+1 336 629 3578",
    "sg:postcode":"27205",
    "sg:province":"NC",
    "wof:name":"Youth Care",
    "wof:placetype":"venue"
},
  "geometry": {"coordinates":[-79.817376,35.681204],"type":"Point"}
}