{
  "type": "Feature",
  "properties": {
    "iso:country":"US",
    "sg:address":"225 Chapman Royal Dr",
    "sg:city":"Clinton",
    "sg:classifiers":[
        {
            "category":"Professional",
            "subcategory":"Management & Consulting",
            "type":"Services"
        }
    ],
    "sg:phone":"+1 910 592 3734",
    "sg:postcode":"28328",
    "sg:province":"NC",
    "sg:tags":[
        "cards",
        "distance",
        "phone",
        "long",
        "calling"
    ],
    "wof:name":"Glen Bradshaw",
    "wof:placetype":"venue"
},
  "geometry": {"coordinates":[-78.355829,34.962723],"type":"Point"}
}