{
  "type": "Feature",
  "properties": {
    "iso:country":"US",
    "sg:address":"105 E Water St",
    "sg:city":"Plymouth",
    "sg:classifiers":[
        {
            "category":"Personal",
            "subcategory":"Beauty Salon",
            "type":"Services"
        }
    ],
    "sg:phone":"+1   ",
    "sg:postcode":"27962",
    "sg:province":"NC",
    "sg:tags":[
        "shop"
    ],
    "wof:name":"Salon Spectrum",
    "wof:placetype":"venue"
},
  "geometry": {"coordinates":[-76.750139,35.867417],"type":"Point"}
}