{
  "type": "Feature",
  "properties": {
    "iso:country":"US",
    "sg:address":"5249 Capital Blvd",
    "sg:city":"Raleigh",
    "sg:classifiers":[
        {
            "category":"Professional",
            "subcategory":"Computer Services",
            "type":"Services"
        }
    ],
    "sg:phone":"+1 919 878 7701",
    "sg:postcode":"27616",
    "sg:province":"NC",
    "sg:tags":[
        "consultant",
        "designer"
    ],
    "wof:name":"Innovative System Group",
    "wof:placetype":"venue"
},
  "geometry": {"coordinates":[-78.58127399999999,35.856958],"type":"Point"}
}