{
  "type": "Feature",
  "properties": {
    "iso:country":"US",
    "sg:address":"4221 Garrett Rd",
    "sg:city":"Durham",
    "sg:classifiers":[
        {
            "category":"Professional",
            "subcategory":"Printing & Photocopies",
            "type":"Services"
        }
    ],
    "sg:phone":"+1 919 493 0985",
    "sg:postcode":"27707",
    "sg:province":"NC",
    "sg:website":"www.inkie.com",
    "wof:name":"American Speedy Printing Centers",
    "wof:placetype":"venue"
},
  "geometry": {"coordinates":[-78.976799,35.961399],"type":"Point"}
}