{
  "type": "Feature",
  "properties": {
    "iso:country":"US",
    "sg:address":"1810 E Innes St",
    "sg:city":"Salisbury",
    "sg:classifiers":[
        {
            "category":"Recreation",
            "type":"Entertainment"
        },
        {
            "category":"Sports & Exercise",
            "subcategory":"Gym",
            "type":"Entertainment"
        }
    ],
    "sg:phone":"+1 704 637 0029",
    "sg:postcode":"28146",
    "sg:province":"NC",
    "sg:tags":[
        "arts",
        "facility",
        "instruction",
        "martial",
        "fitness",
        "physical"
    ],
    "wof:name":"Academy of Kempo Karate",
    "wof:placetype":"venue"
},
  "geometry": {"coordinates":[-80.455833,35.648917],"type":"Point"}
}