{
  "type": "Feature",
  "properties": {
    "iso:country":"US",
    "sg:address":"3248 S Holden Rd",
    "sg:city":"Greensboro",
    "sg:classifiers":[
        {
            "category":"Freight",
            "type":"Transportation"
        }
    ],
    "sg:phone":"+1 336 854 9300",
    "sg:postcode":"27407",
    "sg:province":"NC",
    "sg:tags":[
        "operator",
        "trucking"
    ],
    "wof:name":"R E Walker Trucking",
    "wof:placetype":"venue"
},
  "geometry": {"coordinates":[-79.846324,36.020427],"type":"Point"}
}