{
  "type": "Feature",
  "properties": {
    "addr:full":"676 State Hwy 27 Midland NC 28107",
    "addr:housenumber":"676",
    "addr:postcode":"28107",
    "addr:street":"State Hwy 27",
    "iso:country":"US",
    "sg:address":"676 State Hwy 27",
    "sg:city":"Midland",
    "sg:classifiers":[
        {
            "category":"Retail",
            "subcategory":"Repair Shop",
            "type":"Services"
        }
    ],
    "sg:phone":"+1 704 888 1434",
    "sg:postcode":"28107",
    "sg:province":"NC",
    "sg:tags":[
        "scooter",
        "motorcycle",
        "motor"
    ],
    "wof:name":"Down South Customs LLC",
    "wof:placetype":"venue"
},
  "geometry": {"coordinates":[-80.567871,35.248916],"type":"Point"}
}