{
  "type": "Feature",
  "properties": {
    "addr:full":"1039 Old Fort Rd Fairview NC 28730",
    "addr:housenumber":"1039",
    "addr:postcode":"28730",
    "addr:street":"Old Fort Rd",
    "iso:country":"US",
    "sg:address":"1039 Old Fort Rd",
    "sg:city":"Fairview",
    "sg:classifiers":[
        {
            "category":"Retail",
            "subcategory":"Repair Shop",
            "type":"Services"
        }
    ],
    "sg:phone":"+1 828 628 7844",
    "sg:postcode":"28730",
    "sg:province":"NC",
    "sg:tags":[
        "clocks",
        "parts"
    ],
    "wof:name":"Emperor Clocks",
    "wof:placetype":"venue"
},
  "geometry": {"coordinates":[-82.36121799999999,35.542144],"type":"Point"}
}