{
  "type": "Feature",
  "properties": {
    "iso:country":"US",
    "sg:address":"4149 Park Rd",
    "sg:city":"Charlotte",
    "sg:classifiers":[
        {
            "category":"Shopping",
            "subcategory":"Music",
            "type":"Retail Goods"
        }
    ],
    "sg:phone":"+1 704 752 0100",
    "sg:postcode":"28209",
    "sg:province":"NC",
    "sg:tags":[
        "compact",
        "record",
        "disc",
        "tape"
    ],
    "wof:name":"Record Exchange Inc",
    "wof:placetype":"venue"
},
  "geometry": {"coordinates":[-80.85100300000001,35.175228],"type":"Point"}
}