{
  "type": "Feature",
  "properties": {
    "iso:country":"US",
    "sg:address":"210 S Liberty St",
    "sg:city":"Winston Salem",
    "sg:classifiers":[
        {
            "category":"Wholesale",
            "subcategory":"Furniture",
            "type":"Manufacturing & Wholesale Goods"
        }
    ],
    "sg:phone":"+1 336 724 5194",
    "sg:postcode":"27101",
    "sg:province":"NC",
    "sg:website":"www.carswell-furniture.com",
    "wof:name":"Carswell Business Systems",
    "wof:placetype":"venue"
},
  "geometry": {"coordinates":[-80.243798,36.09274],"type":"Point"}
}