{
  "type": "Feature",
  "properties": {
    "iso:country":"US",
    "sg:address":"2441 O'Hara Dr",
    "sg:city":"Raeford",
    "sg:classifiers":[
        {
            "category":"Freight",
            "type":"Transportation"
        }
    ],
    "sg:phone":"+1 910 875 2951",
    "sg:postcode":"28376",
    "sg:province":"NC",
    "sg:tags":[
        "operator",
        "trucking"
    ],
    "wof:name":"William McKinley",
    "wof:placetype":"venue"
},
  "geometry": {"coordinates":[-79.207088,34.942707],"type":"Point"}
}