{
  "type": "Feature",
  "properties": {
    "iso:country":"US",
    "sg:address":"9878 Longbottom Rd",
    "sg:city":"Traphill",
    "sg:classifiers":[
        {
            "category":"Building & Trades",
            "subcategory":"Construction",
            "type":"Services"
        }
    ],
    "sg:phone":"+1 336 957 8176",
    "sg:postcode":"28685",
    "sg:province":"NC",
    "sg:tags":[
        "house"
    ],
    "wof:name":"Dale Sidden Const",
    "wof:placetype":"venue"
},
  "geometry": {"coordinates":[-81.102345,36.366677],"type":"Point"}
}