{
  "type": "Feature",
  "properties": {
    "addr:full":"104 E Green St Franklinton NC 27525",
    "addr:housenumber":"104",
    "addr:postcode":"27525",
    "addr:street":"E Green St",
    "iso:country":"US",
    "sg:address":"104 E Green St",
    "sg:city":"Franklinton",
    "sg:classifiers":[
        {
            "category":"Building & Trades",
            "subcategory":"Cleaning & Sanitation",
            "type":"Services"
        }
    ],
    "sg:phone":"+1 919 494 2848",
    "sg:postcode":"27525",
    "sg:province":"NC",
    "sg:tags":[
        "janitor"
    ],
    "wof:name":"Cornerstone Cleaning Svc",
    "wof:placetype":"venue"
},
  "geometry": {"coordinates":[-78.457441,36.10159],"type":"Point"}
}