{
  "type": "Feature",
  "properties": {
    "addr:full":"4685 US Hwy 70 New Bern NC 28562",
    "addr:housenumber":"4685",
    "addr:postcode":"28562",
    "addr:street":"Us Hwy 70",
    "iso:country":"US",
    "sg:address":"4685 US Hwy 70",
    "sg:city":"New Bern",
    "sg:classifiers":[
        {
            "category":"Building & Trades",
            "subcategory":"Construction",
            "type":"Services"
        }
    ],
    "sg:phone":"+1 252 637 3378",
    "sg:postcode":"28562",
    "sg:province":"NC",
    "sg:tags":[
        "maker",
        "cabinet"
    ],
    "wof:name":"Ken's Custom Cabinets",
    "wof:placetype":"venue"
},
  "geometry": {"coordinates":[-77.007229,35.037898],"type":"Point"}
}