{
  "type": "Feature",
  "properties": {
    "iso:country":"US",
    "sg:address":"1677 N Market Dr",
    "sg:city":"Raleigh",
    "sg:classifiers":[
        {
            "category":"Shopping",
            "subcategory":"Used Merchandise",
            "type":"Retail Goods"
        }
    ],
    "sg:phone":"+1 919 878 3933",
    "sg:postcode":"27609",
    "sg:province":"NC",
    "wof:name":"Goodwill Industries",
    "wof:placetype":"venue"
},
  "geometry": {"coordinates":[-78.610412,35.841729],"type":"Point"}
}