{
  "type": "Feature",
  "properties": {
    "iso:country":"US",
    "sg:address":"5779 Millie's Ln",
    "sg:city":"Vale",
    "sg:classifiers":[
        {
            "category":"Building & Trades",
            "subcategory":"Construction",
            "type":"Services"
        }
    ],
    "sg:phone":"+1 704 276 2282",
    "sg:postcode":"28168",
    "sg:province":"NC",
    "sg:tags":[
        "specializing",
        "tank",
        "septic",
        "well",
        "contractor",
        "water",
        "drilling"
    ],
    "wof:name":"Lincoln West Well Drilling",
    "wof:placetype":"venue"
},
  "geometry": {"coordinates":[-81.41460600000001,35.483938],"type":"Point"}
}