{
  "type": "Feature",
  "properties": {
    "addr:full":"117 W King St Hillsborough NC 27278",
    "addr:housenumber":"117",
    "addr:postcode":"27278",
    "addr:street":"W King St",
    "iso:country":"US",
    "sg:address":"117 W King St",
    "sg:city":"Hillsborough",
    "sg:classifiers":[
        {
            "category":"Professional",
            "subcategory":"Computer Services",
            "type":"Services"
        }
    ],
    "sg:phone":"+1   ",
    "sg:postcode":"27278",
    "sg:province":"NC",
    "sg:tags":[
        "prepackaged",
        "software"
    ],
    "wof:name":"Bay Data Inc",
    "wof:placetype":"venue"
},
  "geometry": {"coordinates":[-79.099788,36.07529],"type":"Point"}
}