{
  "type": "Feature",
  "properties": {
    "addr:full":"8170 US Hwy 70 Newport NC 28570",
    "addr:housenumber":"8170",
    "addr:postcode":"28570",
    "addr:street":"Us Hwy 70",
    "iso:country":"US",
    "sg:address":"8170 US Hwy 70",
    "sg:city":"Newport",
    "sg:classifiers":[
        {
            "category":"Organizations",
            "subcategory":"Religious Organization",
            "type":"Services"
        }
    ],
    "sg:phone":"+1   ",
    "sg:postcode":"28570",
    "sg:province":"NC",
    "sg:tags":[
        "school"
    ],
    "sg:website":"www.gramercychristian.org",
    "wof:name":"Gramercy Christian School",
    "wof:placetype":"venue"
},
  "geometry": {"coordinates":[-76.875874,34.825984],"type":"Point"}
}