{
  "type": "Feature",
  "properties": {
    "iso:country":"US",
    "sg:address":"2501 E Bessemer Ave",
    "sg:city":"Greensboro",
    "sg:classifiers":[
        {
            "category":"Personal",
            "subcategory":"Beauty Salon",
            "type":"Services"
        }
    ],
    "sg:phone":"+1 336 273 4755",
    "sg:postcode":"27405",
    "sg:province":"NC",
    "sg:tags":[
        "shop"
    ],
    "wof:name":"Miss & Mrs G's Beauty Salon",
    "wof:placetype":"venue"
},
  "geometry": {"coordinates":[-79.75367799999999,36.085134],"type":"Point"}
}