{
  "type": "Feature",
  "properties": {
    "iso:country":"US",
    "sg:address":"1542 Weeksville Rd",
    "sg:city":"Elizabeth City",
    "sg:classifiers":[
        {
            "category":"Food & Beverages",
            "subcategory":"Groceries & Convenience Stores",
            "type":"Retail Goods"
        }
    ],
    "sg:phone":"+1 252 330 2775",
    "sg:postcode":"27909",
    "sg:province":"NC",
    "wof:name":"J S Food Mart",
    "wof:placetype":"venue"
},
  "geometry": {"coordinates":[-76.176777,36.249447],"type":"Point"}
}