{
  "type": "Feature",
  "properties": {
    "iso:country":"US",
    "sg:address":"2010 Flat Mountain Rd",
    "sg:city":"Highlands",
    "sg:classifiers":[
        {
            "category":"Government",
            "subcategory":"Office",
            "type":"Public Place"
        }
    ],
    "sg:phone":"+1 828 526 3765",
    "sg:postcode":"28741",
    "sg:province":"NC",
    "wof:name":"US Ranger",
    "wof:placetype":"venue"
},
  "geometry": {"coordinates":[-83.216678,35.087914],"type":"Point"}
}