{
  "type": "Feature",
  "properties": {
    "iso:country":"US",
    "sg:address":"2300 Fowler Secrest Rd",
    "sg:city":"Monroe",
    "sg:classifiers":[
        {
            "category":"Shopping",
            "subcategory":"Catalog Store",
            "type":"Retail Goods"
        }
    ],
    "sg:phone":"+1 704 226 1977",
    "sg:postcode":"28110",
    "sg:province":"NC",
    "sg:tags":[
        "sell",
        "educational",
        "supply",
        "kit"
    ],
    "wof:name":"Tri-Alcon",
    "wof:placetype":"venue"
},
  "geometry": {"coordinates":[-80.580191,35.033209],"type":"Point"}
}