{
  "type": "Feature",
  "properties": {
    "iso:country":"US",
    "sg:address":"411 S Main St",
    "sg:city":"Rolesville",
    "sg:classifiers":[
        {
            "category":"Home & Garden",
            "subcategory":"Hardware",
            "type":"Retail Goods"
        }
    ],
    "sg:phone":"+1 919 562 0202",
    "sg:postcode":"27571",
    "sg:province":"NC",
    "sg:website":"www.acehardware.com",
    "wof:name":"Ace Hardware",
    "wof:placetype":"venue"
},
  "geometry": {"coordinates":[-78.465767,35.917997],"type":"Point"}
}