{
  "type": "Feature",
  "properties": {
    "addr:full":"202 Blueberry Ct Hubert NC 28539",
    "addr:housenumber":"202",
    "addr:postcode":"28539",
    "addr:street":"Blueberry Ct",
    "iso:country":"US",
    "sg:address":"202 Blueberry Ct",
    "sg:city":"Hubert",
    "sg:classifiers":[
        {
            "category":"Building & Trades",
            "subcategory":"Construction",
            "type":"Services"
        }
    ],
    "sg:phone":"+1 910 577 3362",
    "sg:postcode":"28539",
    "sg:province":"NC",
    "sg:tags":[
        "contractor"
    ],
    "wof:name":"Jumping Run Pressure Washing",
    "wof:placetype":"venue"
},
  "geometry": {"coordinates":[-77.23553800000001,34.738514],"type":"Point"}
}