{
  "type": "Feature",
  "properties": {
    "addr:full":"4803 Lon Parker Rd Waxhaw NC 28173",
    "addr:housenumber":"4803",
    "addr:postcode":"28173",
    "addr:street":"Lon Parker Rd",
    "iso:country":"US",
    "sg:address":"4803 Lon Parker Rd",
    "sg:city":"Waxhaw",
    "sg:classifiers":[
        {
            "category":"Recreation",
            "type":"Entertainment"
        }
    ],
    "sg:phone":"+1 704 243 0324",
    "sg:postcode":"28173",
    "sg:province":"NC",
    "sg:tags":[
        "farm",
        "equine"
    ],
    "wof:name":"Double R Ranch",
    "wof:placetype":"venue"
},
  "geometry": {"coordinates":[-80.67669600000001,34.95115],"type":"Point"}
}