{
  "type": "Feature",
  "properties": {
    "addr:full":"321 Bertie Dr Raleigh NC 27610",
    "addr:housenumber":"321",
    "addr:postcode":"27610",
    "addr:street":"Bertie Dr",
    "iso:country":"US",
    "sg:address":"321 Bertie Dr",
    "sg:city":"Raleigh",
    "sg:classifiers":[
        {
            "category":"Recreation",
            "type":"Entertainment"
        }
    ],
    "sg:phone":"+1 919 831 6343",
    "sg:postcode":"27610",
    "sg:province":"NC",
    "sg:tags":[
        "pool",
        "swimming"
    ],
    "wof:name":"Longview Pool",
    "wof:placetype":"venue"
},
  "geometry": {"coordinates":[-78.60912999999999,35.785263],"type":"Point"}
}