{
  "type": "Feature",
  "properties": {
    "addr:full":"2040 Stutts Rd Asheboro NC 27205",
    "addr:postcode":"2040;27205",
    "addr:street":"Stutts Rd",
    "iso:country":"US",
    "sg:address":"2040 Stutts Rd",
    "sg:city":"Asheboro",
    "sg:classifiers":[
        {
            "category":"Manufacturing",
            "subcategory":"Printing",
            "type":"Manufacturing & Wholesale Goods"
        }
    ],
    "sg:phone":"+1 336 629 1116",
    "sg:postcode":"27205",
    "sg:province":"NC",
    "sg:tags":[
        "screen"
    ],
    "wof:name":"Lanier's Screen Printing",
    "wof:placetype":"venue"
},
  "geometry": {"coordinates":[-79.87611200000001,35.701071],"type":"Point"}
}