{
  "type": "Feature",
  "properties": {
    "addr:full":"1843 Lejeune Blvd Jacksonville NC 28546",
    "addr:housenumber":"1843",
    "addr:postcode":"28546",
    "addr:street":"Lejeune Blvd",
    "iso:country":"US",
    "sg:address":"1843 Lejeune Blvd",
    "sg:city":"Jacksonville",
    "sg:classifiers":[
        {
            "category":"Restaurant",
            "type":"Food & Drink"
        }
    ],
    "sg:phone":"+1 910 353 7121",
    "sg:postcode":"28546",
    "sg:province":"NC",
    "sg:tags":[
        "eating"
    ],
    "wof:name":"Waffle Shoppe of Jacksonville",
    "wof:placetype":"venue"
},
  "geometry": {"coordinates":[-77.37846500000001,34.74284],"type":"Point"}
}