{
  "type": "Feature",
  "properties": {
    "iso:country":"US",
    "sg:address":"221 N 2nd St",
    "sg:city":"Wilmington",
    "sg:classifiers":[
        {
            "category":"Real Estate",
            "subcategory":"Architect",
            "type":"Services"
        }
    ],
    "sg:phone":"+1 910 762 5500",
    "sg:postcode":"28401",
    "sg:province":"NC",
    "wof:name":"Ballard Architects Inc",
    "wof:placetype":"venue"
},
  "geometry": {"coordinates":[-77.94788,34.238655],"type":"Point"}
}