{
  "type": "Feature",
  "properties": {
    "iso:country":"US",
    "sg:address":"110 Spring Brook Pl",
    "sg:city":"Cary",
    "sg:classifiers":[
        {
            "category":"Professional",
            "subcategory":"Computer Services",
            "type":"Services"
        }
    ],
    "sg:phone":"+1   ",
    "sg:postcode":"27511",
    "sg:province":"NC",
    "sg:tags":[
        "design",
        "system"
    ],
    "wof:name":"Wagner Computer Syst",
    "wof:placetype":"venue"
},
  "geometry": {"coordinates":[-78.77239299999999,35.739947],"type":"Point"}
}