{
  "type": "Feature",
  "properties": {
    "iso:country":"US",
    "sg:address":"1903 Alamance Church Rd",
    "sg:city":"Greensboro",
    "sg:classifiers":[
        {
            "category":"Manufacturing",
            "subcategory":"Metals",
            "type":"Manufacturing & Wholesale Goods"
        }
    ],
    "sg:phone":"+1 336 697 2206",
    "sg:postcode":"27406",
    "sg:province":"NC",
    "wof:name":"B & H Electroplating",
    "wof:placetype":"venue"
},
  "geometry": {"coordinates":[-79.716199,36.023298],"type":"Point"}
}