{
  "type": "Feature",
  "properties": {
    "iso:country":"US",
    "sg:address":"212 Johnston Ave",
    "sg:city":"Pikeville",
    "sg:classifiers":[
        {
            "category":"Retail",
            "subcategory":"Repair Shop",
            "type":"Services"
        },
        {
            "category":"Building & Trades",
            "subcategory":"Plumbing",
            "type":"Services"
        }
    ],
    "sg:phone":"+1 919 736 8858",
    "sg:postcode":"27863",
    "sg:province":"NC",
    "sg:tags":[
        "septic"
    ],
    "wof:name":"B & R Septic LLC",
    "wof:placetype":"venue"
},
  "geometry": {"coordinates":[-78.04982099999999,35.460619],"type":"Point"}
}