{
  "type": "Feature",
  "properties": {
    "addr:full":"405 Apache St Kill Devil Hills NC 27948",
    "addr:housenumber":"405",
    "addr:postcode":"27948",
    "addr:street":"Apache St",
    "iso:country":"US",
    "sg:address":"405 Apache St",
    "sg:city":"Kill Devil Hills",
    "sg:classifiers":[
        {
            "category":"Building & Trades",
            "subcategory":"Landscaping Services",
            "type":"Services"
        }
    ],
    "sg:phone":"+1 252 449 5000",
    "sg:postcode":"27948",
    "sg:province":"NC",
    "wof:name":"Sharpe Dressed Lawns",
    "wof:placetype":"venue"
},
  "geometry": {"coordinates":[-75.67625,36.027556],"type":"Point"}
}