{
  "type": "Feature",
  "properties": {
    "iso:country":"US",
    "sg:address":"19900 W Catawba Ave",
    "sg:city":"Cornelius",
    "sg:classifiers":[
        {
            "category":"Professional",
            "subcategory":"Management & Consulting",
            "type":"Services"
        }
    ],
    "sg:phone":"+1 704 987 1224",
    "sg:postcode":"28031",
    "sg:province":"NC",
    "sg:tags":[
        "marketing",
        "consultant"
    ],
    "wof:name":"Industry Business Solutions",
    "wof:placetype":"venue"
},
  "geometry": {"coordinates":[-80.883934,35.481808],"type":"Point"}
}