{
  "type": "Feature",
  "properties": {
    "iso:country":"US",
    "sg:address":"1943 N Old Greensboro Rd",
    "sg:city":"High Point",
    "sg:classifiers":[
        {
            "category":"Building & Trades",
            "subcategory":"Landscaping Services",
            "type":"Services"
        }
    ],
    "sg:phone":"+1 336 869 7888",
    "sg:postcode":"27265",
    "sg:province":"NC",
    "wof:name":"Davidson Landscape Nursery",
    "wof:placetype":"venue"
},
  "geometry": {"coordinates":[-80.08452200000001,35.971425],"type":"Point"}
}