{
  "type": "Feature",
  "properties": {
    "iso:country":"US",
    "sg:address":"8310 Medical Plaza Dr",
    "sg:city":"Charlotte",
    "sg:classifiers":[
        {
            "category":"Real Estate",
            "subcategory":"Real Estate Agent",
            "type":"Services"
        }
    ],
    "sg:phone":"+1 704 522 7229",
    "sg:postcode":"28262",
    "sg:province":"NC",
    "sg:website":"www.hopeadvantagerealty.com",
    "wof:name":"Hope Advantage Realty",
    "wof:placetype":"venue"
},
  "geometry": {"coordinates":[-80.77560200000001,35.319776],"type":"Point"}
}