{
  "type": "Feature",
  "properties": {
    "iso:country":"US",
    "sg:address":"320 Meacham Rd",
    "sg:city":"Statesville",
    "sg:classifiers":[
        {
            "category":"Manufacturing",
            "subcategory":"Metals",
            "type":"Manufacturing & Wholesale Goods"
        },
        {
            "category":"Manufacturing",
            "subcategory":"Printing",
            "type":"Manufacturing & Wholesale Goods"
        }
    ],
    "sg:phone":"+1 704 872 5798",
    "sg:postcode":"28677",
    "sg:province":"NC",
    "sg:tags":[
        "related"
    ],
    "wof:name":"United Engraving Inc",
    "wof:placetype":"venue"
},
  "geometry": {"coordinates":[-80.922918,35.790641],"type":"Point"}
}