{
  "type": "Feature",
  "properties": {
    "iso:country":"US",
    "sg:address":"1939 Hart Rd",
    "sg:city":"Charlotte",
    "sg:classifiers":[
        {
            "category":"Professional",
            "type":"Services"
        }
    ],
    "sg:phone":"+1 704 697 9187",
    "sg:postcode":"28214",
    "sg:province":"NC",
    "wof:name":"Charles D Redmon",
    "wof:placetype":"venue"
},
  "geometry": {"coordinates":[-80.975622,35.326085],"type":"Point"}
}