{
  "type": "Feature",
  "properties": {
    "addr:full":"1414 Camp Greene St Charlotte NC 28208",
    "addr:housenumber":"1414",
    "addr:postcode":"28208",
    "addr:street":"Camp Greene St",
    "iso:country":"US",
    "sg:address":"1414 Camp Greene St",
    "sg:city":"Charlotte",
    "sg:classifiers":[
        {
            "category":"Place Of Worship",
            "subcategory":"Church",
            "type":"Public Place"
        },
        {
            "category":"Place Of Worship",
            "type":"Public Place"
        }
    ],
    "sg:phone":"+1 704 394 7955",
    "sg:postcode":"28208",
    "sg:province":"NC",
    "sg:tags":[
        "churches-apostolic",
        "churches-pentecostal-apostolic"
    ],
    "wof:name":"Church Of The Lord Jesus Christ Of The Apostolic Faith",
    "wof:placetype":"venue"
},
  "geometry": {"coordinates":[-80.878027,35.237156],"type":"Point"}
}