{
  "type": "Feature",
  "properties": {
    "iso:country":"US",
    "sg:address":"28 Waverly Ct",
    "sg:city":"Asheville",
    "sg:classifiers":[
        {
            "category":"Building & Trades",
            "subcategory":"Landscaping Services",
            "type":"Services"
        }
    ],
    "sg:phone":"+1 828 299 0822",
    "sg:postcode":"28805",
    "sg:province":"NC",
    "sg:tags":[
        "landscape"
    ],
    "wof:name":"Garden Works",
    "wof:placetype":"venue"
},
  "geometry": {"coordinates":[-82.496229,35.581662],"type":"Point"}
}