{
  "type": "Feature",
  "properties": {
    "iso:country":"US",
    "sg:address":"903 E Webb Ave",
    "sg:city":"Burlington",
    "sg:classifiers":[
        {
            "category":"Personal",
            "subcategory":"Beauty Salon",
            "type":"Services"
        }
    ],
    "sg:phone":"+1 336 226 1417",
    "sg:postcode":"27217",
    "sg:province":"NC",
    "sg:tags":[
        "manicuring"
    ],
    "wof:name":"B N Nails",
    "wof:placetype":"venue"
},
  "geometry": {"coordinates":[-79.42661099999999,36.084719],"type":"Point"}
}