{
  "type": "Feature",
  "properties": {
    "addr:full":"5611 Carolina Beach Rd Wilmington NC 28412",
    "addr:housenumber":"5611",
    "addr:postcode":"28412",
    "addr:street":"Carolina Beach Rd",
    "iso:country":"US",
    "sg:address":"5611 Carolina Beach Rd",
    "sg:city":"Wilmington",
    "sg:classifiers":[
        {
            "category":"Professional",
            "subcategory":"Accounting & Tax Preparation",
            "type":"Services"
        }
    ],
    "sg:phone":"+1 910 793 8536",
    "sg:postcode":"28412",
    "sg:province":"NC",
    "wof:name":"H & R Block",
    "wof:placetype":"venue"
},
  "geometry": {"coordinates":[-77.894644,34.134959],"type":"Point"}
}