{
  "type": "Feature",
  "properties": {
    "addr:full":"207 South Rd Chapel Hill NC 27599",
    "addr:housenumber":"207",
    "addr:postcode":"27599",
    "addr:street":"South Rd",
    "iso:country":"US",
    "sg:address":"207 South Rd",
    "sg:city":"Chapel Hill",
    "sg:classifiers":[
        {
            "category":"Shopping",
            "subcategory":"Books",
            "type":"Retail Goods"
        },
        {
            "category":"Education",
            "subcategory":"University",
            "type":"Public Place"
        },
        {
            "category":"Wholesale",
            "subcategory":"Computers",
            "type":"Manufacturing & Wholesale Goods"
        }
    ],
    "sg:phone":"+1 919 962 5066",
    "sg:postcode":"27599",
    "sg:province":"NC",
    "sg:tags":[
        "bookstore",
        "college"
    ],
    "sg:website":"www.store.unc.edu",
    "wof:name":"UNC Student Stores",
    "wof:placetype":"venue"
},
  "geometry": {"coordinates":[-79.04826199999999,35.909647],"type":"Point"}
}