{
  "type": "Feature",
  "properties": {
    "iso:country":"US",
    "sg:address":"326 Chesapeake Dr",
    "sg:city":"Kannapolis",
    "sg:classifiers":[
        {
            "category":"Professional",
            "type":"Services"
        }
    ],
    "sg:phone":"+1 704 933 6187",
    "sg:postcode":"28083",
    "sg:province":"NC",
    "wof:name":"Ponswer",
    "wof:placetype":"venue"
},
  "geometry": {"coordinates":[-80.619345,35.480861],"type":"Point"}
}