{
  "type": "Feature",
  "properties": {
    "addr:full":"4974 Kotlik Dr Charlotte NC 28269",
    "addr:housenumber":"4974",
    "addr:postcode":"28269",
    "addr:street":"Kotlik Dr",
    "iso:country":"US",
    "sg:address":"4974 Kotlik Dr",
    "sg:city":"Charlotte",
    "sg:classifiers":[
        {
            "category":"Building & Trades",
            "subcategory":"Construction",
            "type":"Services"
        }
    ],
    "sg:phone":"+1 704 547 1830",
    "sg:postcode":"28269",
    "sg:province":"NC",
    "sg:tags":[
        "home",
        "builder"
    ],
    "wof:name":"Beazer Homes",
    "wof:placetype":"venue"
},
  "geometry": {"coordinates":[-80.78485000000001,35.364411],"type":"Point"}
}