{
  "type": "Feature",
  "properties": {
    "iso:country":"US",
    "sg:address":"302 Marist Ct",
    "sg:city":"Durham",
    "sg:classifiers":[
        {
            "category":"Real Estate",
            "subcategory":"Real Estate Agent",
            "type":"Services"
        }
    ],
    "sg:phone":"+1 919 361 3555",
    "sg:postcode":"27713",
    "sg:province":"NC",
    "sg:tags":[
        "appraiser"
    ],
    "wof:name":"Cash & Co Real Estate",
    "wof:placetype":"venue"
},
  "geometry": {"coordinates":[-78.94938399999999,35.886354],"type":"Point"}
}