{
  "type": "Feature",
  "properties": {
    "addr:full":"3518 S Holden Rd Greensboro NC 27407",
    "addr:housenumber":"3518",
    "addr:postcode":"27407",
    "addr:street":"S Holden Rd",
    "iso:country":"US",
    "sg:address":"3518 S Holden Rd",
    "sg:city":"Greensboro",
    "sg:classifiers":[
        {
            "category":"Home & Garden",
            "subcategory":"Furniture",
            "type":"Retail Goods"
        }
    ],
    "sg:phone":"+1 336 632 4794",
    "sg:postcode":"27407",
    "sg:province":"NC",
    "wof:name":"Dave's Discount Furn Warehouse",
    "wof:placetype":"venue"
},
  "geometry": {"coordinates":[-79.844489,36.017416],"type":"Point"}
}