{
  "type": "Feature",
  "properties": {
    "iso:country":"US",
    "sg:address":"729 Oakland Rd",
    "sg:city":"Spindale",
    "sg:classifiers":[
        {
            "category":"Restaurant",
            "type":"Food & Drink"
        }
    ],
    "sg:phone":"+1 828 286 1123",
    "sg:postcode":"28160",
    "sg:province":"NC",
    "wof:name":"Caulfield's Cafe",
    "wof:placetype":"venue"
},
  "geometry": {"coordinates":[-81.920147,35.338701],"type":"Point"}
}