{
  "type": "Feature",
  "properties": {
    "addr:full":"125 Millers Creek Dr Cary NC 27519",
    "addr:housenumber":"125",
    "addr:postcode":"27519",
    "addr:street":"Millers Creek Dr",
    "iso:country":"US",
    "sg:address":"125 Millers Creek Dr",
    "sg:city":"Cary",
    "sg:classifiers":[
        {
            "category":"Restaurant",
            "type":"Food & Drink"
        }
    ],
    "sg:phone":"+1 336 775 5330",
    "sg:postcode":"27519",
    "sg:province":"NC",
    "wof:name":"Henry James Family Dining",
    "wof:placetype":"venue"
},
  "geometry": {"coordinates":[-78.851119,35.772434],"type":"Point"}
}