{
  "type": "Feature",
  "properties": {
    "addr:full":"211 Cleveland Ave Kings Mountain NC 28086",
    "addr:housenumber":"211",
    "addr:postcode":"28086",
    "addr:street":"Cleveland Ave",
    "iso:country":"US",
    "sg:address":"211 Cleveland Ave",
    "sg:city":"Kings Mountain",
    "sg:classifiers":[
        {
            "category":"Organizations",
            "subcategory":"Membership Organization",
            "type":"Services"
        }
    ],
    "sg:phone":"+1 704 734 0449",
    "sg:postcode":"28086",
    "sg:province":"NC",
    "sg:tags":[
        "athletic"
    ],
    "wof:name":"Parks & Recreation",
    "wof:placetype":"venue"
},
  "geometry": {"coordinates":[-81.331003,35.24511],"type":"Point"}
}