{
  "type": "Feature",
  "properties": {
    "addr:full":"594 Mimosa Shores Dr Washington NC 27889",
    "addr:housenumber":"594",
    "addr:postcode":"27889",
    "addr:street":"Mimosa Shores Dr",
    "iso:country":"US",
    "sg:address":"594 Mimosa Shores Dr",
    "sg:city":"Washington",
    "sg:classifiers":[
        {
            "category":"Building & Trades",
            "subcategory":"Construction",
            "type":"Services"
        }
    ],
    "sg:phone":"+1 252 940 1298",
    "sg:postcode":"27889",
    "sg:province":"NC",
    "sg:tags":[
        "general",
        "commercial",
        "contractor"
    ],
    "wof:name":"Beach Builder Inc Richard",
    "wof:placetype":"venue"
},
  "geometry": {"coordinates":[-77.01701799999999,35.522254],"type":"Point"}
}