{
  "type": "Feature",
  "properties": {
    "iso:country":"US",
    "sg:address":"5 Haven Dr",
    "sg:city":"Arden",
    "sg:classifiers":[
        {
            "category":"Retail",
            "subcategory":"Auto Repair",
            "type":"Services"
        }
    ],
    "sg:phone":"+1 828 684 3263",
    "sg:postcode":"28721",
    "sg:province":"NC",
    "sg:tags":[
        "repairing",
        "automobile"
    ],
    "wof:name":"Tolley's Emergency Vehicle Svc",
    "wof:placetype":"venue"
},
  "geometry": {"coordinates":[-82.94368299999999,35.54249],"type":"Point"}
}