{
  "type": "Feature",
  "properties": {
    "iso:country":"US",
    "sg:address":"509 Shinnecock Ct",
    "sg:city":"New Bern",
    "sg:classifiers":[
        {
            "category":"Organizations",
            "subcategory":"Religious Organization",
            "type":"Services"
        }
    ],
    "sg:phone":"+1   ",
    "sg:postcode":"28562",
    "sg:province":"NC",
    "wof:name":"Jerry Rackley",
    "wof:placetype":"venue"
},
  "geometry": {"coordinates":[-77.111532,35.108694],"type":"Point"}
}