{
  "type": "Feature",
  "properties": {
    "iso:country":"US",
    "sg:address":"3837 Marathon Ave",
    "sg:city":"Castle Hayne",
    "sg:classifiers":[
        {
            "category":"Personal",
            "subcategory":"Beauty Salon",
            "type":"Services"
        }
    ],
    "sg:phone":"+1   ",
    "sg:postcode":"28429",
    "sg:province":"NC",
    "sg:tags":[
        "shop"
    ],
    "wof:name":"WD Hair Studio",
    "wof:placetype":"venue"
},
  "geometry": {"coordinates":[-77.910543,34.3437],"type":"Point"}
}