{
  "type": "Feature",
  "properties": {
    "addr:full":"1507 Live Oak St Beaufort NC 28516",
    "addr:housenumber":"1507",
    "addr:postcode":"28516",
    "addr:street":"Live Oak St",
    "iso:country":"US",
    "sg:address":"1507 Live Oak St",
    "sg:city":"Beaufort",
    "sg:classifiers":[
        {
            "category":"Personal",
            "subcategory":"Beauty Salon",
            "type":"Services"
        }
    ],
    "sg:phone":"+1 252 504 6355",
    "sg:postcode":"28516",
    "sg:province":"NC",
    "sg:tags":[
        "shop"
    ],
    "wof:name":"Hair By Jonathan Inc",
    "wof:placetype":"venue"
},
  "geometry": {"coordinates":[-76.64658799999999,34.724941],"type":"Point"}
}