{
  "type": "Feature",
  "properties": {
    "iso:country":"US",
    "sg:address":"2411 US Hwy 64 W",
    "sg:city":"Pittsboro",
    "sg:classifiers":[
        {
            "category":"Home & Garden",
            "subcategory":"Garden Supply",
            "type":"Retail Goods"
        }
    ],
    "sg:phone":"+1 919 542 5308",
    "sg:postcode":"27312",
    "sg:province":"NC",
    "sg:tags":[
        "center"
    ],
    "wof:name":"Flynthill Farm",
    "wof:placetype":"venue"
},
  "geometry": {"coordinates":[-79.217163,35.724749],"type":"Point"}
}