{
  "type": "Feature",
  "properties": {
    "iso:country":"US",
    "sg:address":"5100 Deer Chase Trl",
    "sg:city":"Wake Forest",
    "sg:classifiers":[
        {
            "category":"Professional",
            "subcategory":"Business Services",
            "type":"Services"
        }
    ],
    "sg:phone":"+1   ",
    "sg:postcode":"27587",
    "sg:province":"NC",
    "wof:name":"Verve Technology Inc",
    "wof:placetype":"venue"
},
  "geometry": {"coordinates":[-78.514983,35.921548],"type":"Point"}
}