{
  "type": "Feature",
  "properties": {
    "addr:full":"3005 Pisgah Ct Greensboro NC 27455",
    "addr:housenumber":"3005",
    "addr:postcode":"27455",
    "addr:street":"Pisgah Ct",
    "iso:country":"US",
    "sg:address":"3005 Pisgah Ct",
    "sg:city":"Greensboro",
    "sg:classifiers":[
        {
            "category":"Personal",
            "type":"Services"
        }
    ],
    "sg:phone":"+1 336 545 1935",
    "sg:postcode":"27455",
    "sg:province":"NC",
    "sg:tags":[
        "therapist",
        "massage"
    ],
    "wof:name":"Human Touch",
    "wof:placetype":"venue"
},
  "geometry": {"coordinates":[-79.833708,36.117529],"type":"Point"}
}