{
  "type": "Feature",
  "properties": {
    "iso:country":"US",
    "sg:address":"676 Community Dr",
    "sg:city":"Goldsboro",
    "sg:classifiers":[
        {
            "category":"Organizations",
            "subcategory":"Non-profit Organization",
            "type":"Services"
        }
    ],
    "sg:phone":"+1 919 393 9167",
    "sg:postcode":"27530",
    "sg:province":"NC",
    "wof:name":"Disaster Relief",
    "wof:placetype":"venue"
},
  "geometry": {"coordinates":[-78.085871,35.439619],"type":"Point"}
}