{
  "type": "Feature",
  "properties": {
    "iso:country":"US",
    "sg:address":"1815 Muncey Ln",
    "sg:city":"Greensboro",
    "sg:classifiers":[
        {
            "category":"Building & Trades",
            "subcategory":"Construction",
            "type":"Services"
        }
    ],
    "sg:phone":"+1 336 965 3388",
    "sg:postcode":"27401",
    "sg:province":"NC",
    "sg:tags":[
        "home",
        "improvement"
    ],
    "wof:name":"Martin's Home Improvement",
    "wof:placetype":"venue"
},
  "geometry": {"coordinates":[-79.758409,36.048444],"type":"Point"}
}