{
  "type": "Feature",
  "properties": {
    "addr:full":"111 E Bellevue Dr High Point NC 27265",
    "addr:housenumber":"111",
    "addr:postcode":"27265",
    "addr:street":"E Bellevue Dr",
    "iso:country":"US",
    "sg:address":"111 E Bellevue Dr",
    "sg:city":"High Point",
    "sg:classifiers":[
        {
            "category":"Personal",
            "subcategory":"Beauty Salon",
            "type":"Services"
        }
    ],
    "sg:phone":"+1   ",
    "sg:postcode":"27265",
    "sg:province":"NC",
    "sg:tags":[
        "shop"
    ],
    "wof:name":"Hair Shop",
    "wof:placetype":"venue"
},
  "geometry": {"coordinates":[-80.032676,36.003256],"type":"Point"}
}