{
  "type": "Feature",
  "properties": {
    "addr:full":"7924 Kieldon Ct Charlotte NC 28277",
    "addr:housenumber":"7924",
    "addr:postcode":"28277",
    "addr:street":"Kieldon Ct",
    "iso:country":"US",
    "sg:address":"7924 Kieldon Ct",
    "sg:city":"Charlotte",
    "sg:classifiers":[
        {
            "category":"Restaurant",
            "type":"Food & Drink"
        }
    ],
    "sg:phone":"+1 704 845 0520",
    "sg:postcode":"28277",
    "sg:province":"NC",
    "wof:name":"Red Pepper Ventures Inc",
    "wof:placetype":"venue"
},
  "geometry": {"coordinates":[-80.807338,35.076809],"type":"Point"}
}