{
  "type": "Feature",
  "properties": {
    "addr:full":"908 Beddingfield Dr Knightdale NC 27545",
    "addr:housenumber":"908",
    "addr:postcode":"27545",
    "addr:street":"Beddingfield Dr",
    "iso:country":"US",
    "sg:address":"908 Beddingfield Dr",
    "sg:city":"Knightdale",
    "sg:classifiers":[
        {
            "category":"Retail",
            "subcategory":"Animal Services",
            "type":"Services"
        }
    ],
    "sg:phone":"+1 919 217 5260",
    "sg:postcode":"27545",
    "sg:province":"NC",
    "wof:name":"Custom Canine Training LLC",
    "wof:placetype":"venue"
},
  "geometry": {"coordinates":[-78.506675,35.791942],"type":"Point"}
}