{
  "type": "Feature",
  "properties": {
    "iso:country":"US",
    "sg:address":"3804 Park Ave",
    "sg:city":"Wilmington",
    "sg:classifiers":[
        {
            "category":"Shopping",
            "subcategory":"Computers & Home Electronics",
            "type":"Retail Goods"
        }
    ],
    "sg:phone":"+1 910 395 2206",
    "sg:postcode":"28403",
    "sg:province":"NC",
    "sg:tags":[
        "software"
    ],
    "wof:name":"Engineering Software Solutions",
    "wof:placetype":"venue"
},
  "geometry": {"coordinates":[-77.897943,34.216253],"type":"Point"}
}