{
  "type": "Feature",
  "properties": {
    "addr:full":"3126 Milton Rd Charlotte NC 28215",
    "addr:housenumber":"3126",
    "addr:postcode":"28215",
    "addr:street":"Milton Rd",
    "iso:country":"US",
    "sg:address":"3126 Milton Rd",
    "sg:city":"Charlotte",
    "sg:classifiers":[
        {
            "category":"Professional",
            "subcategory":"Employment Agencies",
            "type":"Services"
        }
    ],
    "sg:phone":"+1 704 563 2277",
    "sg:postcode":"28215",
    "sg:province":"NC",
    "sg:tags":[
        "job",
        "listing"
    ],
    "wof:name":"Charlotte Job Finder",
    "wof:placetype":"venue"
},
  "geometry": {"coordinates":[-80.73627999999999,35.2367],"type":"Point"}
}