{
  "type": "Feature",
  "properties": {
    "iso:country":"US",
    "sg:address":"6320 Old Oak Ridge Rd",
    "sg:city":"Greensboro",
    "sg:classifiers":[
        {
            "category":"Social Services",
            "subcategory":"Child Care",
            "type":"Services"
        }
    ],
    "sg:phone":"+1 336 665 2777",
    "sg:postcode":"27410",
    "sg:province":"NC",
    "sg:tags":[
        "day"
    ],
    "wof:name":"Cardinal Child Care and Develo",
    "wof:placetype":"venue"
},
  "geometry": {"coordinates":[-79.93365799999999,36.127214],"type":"Point"}
}