{
  "type": "Feature",
  "properties": {
    "iso:country":"US",
    "sg:address":"230 Settle St",
    "sg:city":"Reidsville",
    "sg:classifiers":[
        {
            "category":"Taxi",
            "type":"Transportation"
        }
    ],
    "sg:phone":"+1 336 349 7077",
    "sg:postcode":"27320",
    "sg:province":"NC",
    "sg:tags":[
        "taxicab"
    ],
    "wof:name":"Central Taxi Service",
    "wof:placetype":"venue"
},
  "geometry": {"coordinates":[-79.66562399999999,36.35893],"type":"Point"}
}