{
  "type": "Feature",
  "properties": {
    "iso:country":"US",
    "sg:address":"6274 Glenwood Ave",
    "sg:city":"Raleigh",
    "sg:classifiers":[
        {
            "category":"Shopping",
            "subcategory":"Clothing, Apparel, & Fashions",
            "type":"Retail Goods"
        }
    ],
    "sg:phone":"+1 919 789 4780",
    "sg:postcode":"27612",
    "sg:province":"NC",
    "sg:tags":[
        "shoes",
        "uniform"
    ],
    "wof:name":"Life Uniform 180",
    "wof:placetype":"venue"
},
  "geometry": {"coordinates":[-78.700627,35.854971],"type":"Point"}
}