{
  "type": "Feature",
  "properties": {
    "iso:country":"US",
    "sg:address":"5115 Morganton Rd",
    "sg:city":"Fayetteville",
    "sg:classifiers":[
        {
            "category":"Home & Garden",
            "subcategory":"Mobile Homes",
            "type":"Retail Goods"
        }
    ],
    "sg:phone":"+1 910 867 7877",
    "sg:postcode":"28314",
    "sg:province":"NC",
    "wof:name":"Colony Village",
    "wof:placetype":"venue"
},
  "geometry": {"coordinates":[-78.967499,35.071561],"type":"Point"}
}