{
  "type": "Feature",
  "properties": {
    "iso:country":"US",
    "sg:address":"408 Roaring River Dr",
    "sg:city":"Blowing Rock",
    "sg:classifiers":[
        {
            "category":"Travel",
            "subcategory":"Hotels & Motels",
            "type":"Entertainment"
        }
    ],
    "sg:phone":"+1 828 295 3695",
    "sg:postcode":"28605",
    "sg:province":"NC",
    "sg:tags":[
        "resort"
    ],
    "wof:name":"Roaring River Chalets",
    "wof:placetype":"venue"
},
  "geometry": {"coordinates":[-81.653552,36.151228],"type":"Point"}
}