{
  "type": "Feature",
  "properties": {
    "addr:full":"4421 Six Forks Rd Raleigh NC 27609",
    "addr:housenumber":"4421",
    "addr:postcode":"27609",
    "addr:street":"Six Forks Rd",
    "iso:country":"US",
    "sg:address":"4421 Six Forks Rd",
    "sg:city":"Raleigh",
    "sg:classifiers":[
        {
            "category":"Shopping",
            "subcategory":"Shoes",
            "type":"Retail Goods"
        }
    ],
    "sg:phone":"+1 919 420 7755",
    "sg:postcode":"27609",
    "sg:province":"NC",
    "wof:name":"Plush",
    "wof:placetype":"venue"
},
  "geometry": {"coordinates":[-78.642788,35.841157],"type":"Point"}
}