{
  "type": "Feature",
  "properties": {
    "addr:full":"8326 Pineville-Matthews Rd Charlotte NC 28226",
    "addr:housenumber":"8326",
    "addr:postcode":"28226",
    "addr:street":"Pineville-Matthews Rd",
    "iso:country":"US",
    "sg:address":"8326 Pineville-Matthews Rd",
    "sg:city":"Charlotte",
    "sg:classifiers":[
        {
            "category":"Shopping",
            "subcategory":"Used Merchandise",
            "type":"Retail Goods"
        }
    ],
    "sg:phone":"+1 704 544 8006",
    "sg:postcode":"28226",
    "sg:province":"NC",
    "sg:tags":[
        "book",
        "rare",
        "dealer"
    ],
    "sg:website":"www.bookrack-franchise.com",
    "wof:name":"Book Rack",
    "wof:placetype":"venue"
},
  "geometry": {"coordinates":[-80.861574,35.087619],"type":"Point"}
}