{
  "type": "Feature",
  "properties": {
    "iso:country":"US",
    "sg:address":"906 S Main St",
    "sg:city":"Kannapolis",
    "sg:classifiers":[
        {
            "category":"Home & Garden",
            "subcategory":"Household Appliances",
            "type":"Retail Goods"
        }
    ],
    "sg:phone":"+1 704 932 1128",
    "sg:postcode":"28081",
    "sg:province":"NC",
    "sg:tags":[
        "cleaners",
        "vacuum"
    ],
    "wof:name":"Electro Vacuums",
    "wof:placetype":"venue"
},
  "geometry": {"coordinates":[-80.626999,35.482565],"type":"Point"}
}