{
  "type": "Feature",
  "properties": {
    "iso:country":"US",
    "sg:address":"1209 Ridge Rd Apt A",
    "sg:city":"Raleigh",
    "sg:classifiers":[
        {
            "category":"Building & Trades",
            "subcategory":"Cleaning & Sanitation",
            "type":"Services"
        }
    ],
    "sg:phone":"+1 919 832 3004",
    "sg:postcode":"27607",
    "sg:province":"NC",
    "sg:tags":[
        "home"
    ],
    "wof:name":"Maids In Waiting",
    "wof:placetype":"venue"
},
  "geometry": {"coordinates":[-78.68771700000001,35.803438],"type":"Point"}
}