{
  "type": "Feature",
  "properties": {
    "addr:full":"106 S Lafayette St Shelby NC 28150",
    "addr:housenumber":"106",
    "addr:postcode":"28150",
    "addr:street":"S Lafayette St",
    "iso:country":"US",
    "sg:address":"106 S Lafayette St",
    "sg:city":"Shelby",
    "sg:classifiers":[
        {
            "category":"Banks & Credit Unions",
            "subcategory":"Financial Services",
            "type":"Services"
        }
    ],
    "sg:phone":"+1 704 484 6215",
    "sg:postcode":"28150",
    "sg:province":"NC",
    "sg:tags":[
        "company",
        "bank",
        "holding"
    ],
    "wof:name":"Shelby Loan & Mortgage Corp",
    "wof:placetype":"venue"
},
  "geometry": {"coordinates":[-81.540284,35.291366],"type":"Point"}
}