{
  "type": "Feature",
  "properties": {
    "addr:full":"1950 Orchard Rd Flat Rock NC 28731",
    "addr:housenumber":"1950",
    "addr:postcode":"28731",
    "addr:street":"Orchard Rd",
    "iso:country":"US",
    "sg:address":"1950 Orchard Rd",
    "sg:city":"Flat Rock",
    "sg:classifiers":[
        {
            "category":"Personal",
            "subcategory":"Beauty Salon",
            "type":"Services"
        }
    ],
    "sg:phone":"+1   ",
    "sg:postcode":"28731",
    "sg:province":"NC",
    "sg:tags":[
        "shop"
    ],
    "wof:name":"Tanglez",
    "wof:placetype":"venue"
},
  "geometry": {"coordinates":[-82.37883600000001,35.323802],"type":"Point"}
}