{
  "type": "Feature",
  "properties": {
    "iso:country":"US",
    "sg:address":"2478 State Hwy 16",
    "sg:city":"Taylorsville",
    "sg:classifiers":[
        {
            "category":"Building & Trades",
            "subcategory":"Construction",
            "type":"Services"
        }
    ],
    "sg:phone":"+1 828 635 1242",
    "sg:postcode":"28681",
    "sg:province":"NC",
    "sg:tags":[
        "painter"
    ],
    "wof:name":"Mitchells Painting & Pressure",
    "wof:placetype":"venue"
},
  "geometry": {"coordinates":[-81.184174,35.888532],"type":"Point"}
}