{
  "type": "Feature",
  "properties": {
    "iso:country":"US",
    "sg:address":"3623 Oakwood Ave",
    "sg:city":"Charlotte",
    "sg:classifiers":[
        {
            "category":"Building & Trades",
            "subcategory":"Electrical",
            "type":"Services"
        }
    ],
    "sg:phone":"+1 704 332 8715",
    "sg:postcode":"28205",
    "sg:province":"NC",
    "sg:tags":[
        "electrical",
        "contractor"
    ],
    "wof:name":"Isenhour J D Electrical Contr",
    "wof:placetype":"venue"
},
  "geometry": {"coordinates":[-80.793128,35.245439],"type":"Point"}
}