{
  "type": "Feature",
  "properties": {
    "addr:full":"5400 Doemont Dr Apex NC 27539",
    "addr:postcode":"5400;27539",
    "addr:street":"Doemont Dr",
    "iso:country":"US",
    "sg:address":"5400 Doemont Dr",
    "sg:city":"Apex",
    "sg:classifiers":[
        {
            "category":"Real Estate",
            "subcategory":"Real Estate Agent",
            "type":"Services"
        }
    ],
    "sg:phone":"+1 919 661 6446",
    "sg:postcode":"27539",
    "sg:province":"NC",
    "wof:name":"Vernick & Associates",
    "wof:placetype":"venue"
},
  "geometry": {"coordinates":[-78.73435499999999,35.667381],"type":"Point"}
}