{
  "type": "Feature",
  "properties": {
    "addr:full":"11 S Main St Lexington NC 27292",
    "addr:housenumber":"11",
    "addr:postcode":"27292",
    "addr:street":"S Main St",
    "iso:country":"US",
    "sg:address":"11 S Main St",
    "sg:city":"Lexington",
    "sg:classifiers":[
        {
            "category":"Building & Trades",
            "subcategory":"Pest Control",
            "type":"Services"
        }
    ],
    "sg:phone":"+1   ",
    "sg:postcode":"27292",
    "sg:province":"NC",
    "sg:tags":[
        "exterminating"
    ],
    "wof:name":"Sure Kill Exterminating Servic",
    "wof:placetype":"venue"
},
  "geometry": {"coordinates":[-80.253359,35.823865],"type":"Point"}
}