{
  "type": "Feature",
  "properties": {
    "iso:country":"US",
    "sg:address":"11607 Kempsford Dr",
    "sg:city":"Charlotte",
    "sg:classifiers":[
        {
            "category":"Building & Trades",
            "subcategory":"Construction",
            "type":"Services"
        }
    ],
    "sg:phone":"+1 704 510 0705",
    "sg:postcode":"28262",
    "sg:province":"NC",
    "sg:tags":[
        "contractor"
    ],
    "wof:name":"Crestwood Pools Inc",
    "wof:placetype":"venue"
},
  "geometry": {"coordinates":[-80.709103,35.32259],"type":"Point"}
}