{
  "type": "Feature",
  "properties": {
    "addr:full":"1501 Buck Jones Rd Raleigh NC 27606",
    "addr:housenumber":"1501",
    "addr:postcode":"27606",
    "addr:street":"Buck Jones Rd",
    "iso:country":"US",
    "sg:address":"1501 Buck Jones Rd",
    "sg:city":"Raleigh",
    "sg:classifiers":[
        {
            "category":"Autos & Motor Vehicles",
            "subcategory":"Automobile Sales",
            "type":"Retail Goods"
        }
    ],
    "sg:phone":"+1 919 380 0380",
    "sg:postcode":"27606",
    "sg:province":"NC",
    "sg:tags":[
        "car",
        "used",
        "dealer"
    ],
    "wof:name":"Best Import Motors Inc",
    "wof:placetype":"venue"
},
  "geometry": {"coordinates":[-78.7443,35.763823],"type":"Point"}
}