{
  "type": "Feature",
  "properties": {
    "iso:country":"US",
    "sg:address":"107 Madora St",
    "sg:city":"Mount Holly",
    "sg:classifiers":[
        {
            "category":"Building & Trades",
            "subcategory":"Plumbing",
            "type":"Services"
        }
    ],
    "sg:phone":"+1 704 827 3421",
    "sg:postcode":"28120",
    "sg:province":"NC",
    "sg:tags":[
        "specializing",
        "i",
        "heating",
        "contractor",
        "conditioning",
        "air"
    ],
    "wof:name":"Mt Holly Heating & AC",
    "wof:placetype":"venue"
},
  "geometry": {"coordinates":[-81.02476799999999,35.291341],"type":"Point"}
}