{
  "type": "Feature",
  "properties": {
    "iso:country":"US",
    "sg:address":"400 Edwardia Dr",
    "sg:city":"Greensboro",
    "sg:classifiers":[
        {
            "category":"Airline",
            "type":"Transportation"
        }
    ],
    "sg:phone":"+1 336 294 6880",
    "sg:postcode":"27409",
    "sg:province":"NC",
    "sg:tags":[
        "cargo",
        "air"
    ],
    "sg:website":"www.lynden.com",
    "wof:name":"Lynden Air Freight",
    "wof:placetype":"venue"
},
  "geometry": {"coordinates":[-79.879926,36.063839],"type":"Point"}
}