{
  "type": "Feature",
  "properties": {
    "addr:full":"2625 Suffolk Ave High Point NC 27265",
    "addr:housenumber":"2625",
    "addr:postcode":"27265",
    "addr:street":"Suffolk Ave",
    "iso:country":"US",
    "sg:address":"2625 Suffolk Ave",
    "sg:city":"High Point",
    "sg:classifiers":[
        {
            "category":"Retail",
            "subcategory":"Repair Shop",
            "type":"Services"
        }
    ],
    "sg:phone":"+1   ",
    "sg:postcode":"27265",
    "sg:province":"NC",
    "wof:name":"Ethio Cleaning",
    "wof:placetype":"venue"
},
  "geometry": {"coordinates":[-79.97967,35.984837],"type":"Point"}
}