{
  "type": "Feature",
  "properties": {
    "iso:country":"US",
    "sg:address":"7557 State Hwy 43 S",
    "sg:city":"Greenville",
    "sg:classifiers":[
        {
            "category":"Education",
            "subcategory":"School",
            "type":"Public Place"
        }
    ],
    "sg:phone":"+1 252 746 2442",
    "sg:postcode":"27858",
    "sg:province":"NC",
    "sg:website":"www.pittcountyschools.com",
    "wof:name":"Chicod School",
    "wof:placetype":"venue"
},
  "geometry": {"coordinates":[-77.274204,35.463418],"type":"Point"}
}