{
  "type": "Feature",
  "properties": {
    "addr:full":"126 Mulberry St NW Lenoir NC 28645",
    "addr:housenumber":"126",
    "addr:postcode":"28645",
    "addr:street":"Mulberry St Nw",
    "iso:country":"US",
    "sg:address":"126 Mulberry St NW",
    "sg:city":"Lenoir",
    "sg:classifiers":[
        {
            "category":"Home & Garden",
            "subcategory":"Furniture",
            "type":"Retail Goods"
        }
    ],
    "sg:phone":"+1 828 758 5127",
    "sg:postcode":"28645",
    "sg:province":"NC",
    "wof:name":"W E Shaw Furniture Co Inc",
    "wof:placetype":"venue"
},
  "geometry": {"coordinates":[-81.53889599999999,35.914918],"type":"Point"}
}