{
  "type": "Feature",
  "properties": {
    "iso:country":"US",
    "sg:address":"3115 Old Charlotte Hwy",
    "sg:city":"Monroe",
    "sg:classifiers":[
        {
            "category":"Organizations",
            "subcategory":"Religious Organization",
            "type":"Services"
        }
    ],
    "sg:phone":"+1 704 283 9288",
    "sg:postcode":"28110",
    "sg:province":"NC",
    "sg:tags":[
        "church"
    ],
    "wof:name":"Rhema Fellowship Ministries In",
    "wof:placetype":"venue"
},
  "geometry": {"coordinates":[-80.592798,35.022144],"type":"Point"}
}