{
  "type": "Feature",
  "properties": {
    "addr:full":"542 W Sugar Creek Rd Charlotte NC 28213",
    "addr:housenumber":"542",
    "addr:postcode":"28213",
    "addr:street":"W Sugar Creek Rd",
    "iso:country":"US",
    "sg:address":"542 W Sugar Creek Rd",
    "sg:city":"Charlotte",
    "sg:classifiers":[
        {
            "category":"Building & Trades",
            "subcategory":"Construction",
            "type":"Services"
        }
    ],
    "sg:phone":"+1 704 904 9682",
    "sg:postcode":"28213",
    "sg:province":"NC",
    "sg:tags":[
        "system",
        "contractor",
        "air conditioning"
    ],
    "wof:name":"Affordable Heating Air",
    "wof:placetype":"venue"
},
  "geometry": {"coordinates":[-80.794972,35.2661],"type":"Point"}
}