{
  "type": "Feature",
  "properties": {
    "addr:full":"85 River Crest Dr Sylva NC 28779",
    "addr:housenumber":"85",
    "addr:postcode":"28779",
    "addr:street":"River Crest Dr",
    "iso:country":"US",
    "sg:address":"85 River Crest Dr",
    "sg:city":"Sylva",
    "sg:classifiers":[
        {
            "category":"Building & Trades",
            "subcategory":"Cleaning & Sanitation",
            "type":"Services"
        }
    ],
    "sg:phone":"+1 828 586 0999",
    "sg:postcode":"28779",
    "sg:province":"NC",
    "sg:tags":[
        "janitor"
    ],
    "wof:name":"Cherokee Cleaning Svc",
    "wof:placetype":"venue"
},
  "geometry": {"coordinates":[-83.201356,35.344934],"type":"Point"}
}