{
  "type": "Feature",
  "properties": {
    "addr:full":"1501 N Main St Fuquay Varina NC 27526",
    "addr:housenumber":"1501",
    "addr:postcode":"27526",
    "addr:street":"N Main St",
    "iso:country":"US",
    "sg:address":"1501 N Main St",
    "sg:city":"Fuquay Varina",
    "sg:classifiers":[
        {
            "category":"Retail",
            "subcategory":"Animal Services",
            "type":"Services"
        }
    ],
    "sg:phone":"+1 919 552 2966",
    "sg:postcode":"27526",
    "sg:province":"NC",
    "sg:tags":[
        "horse",
        "training"
    ],
    "wof:name":"Ricky's Auto Truck & Tractor",
    "wof:placetype":"venue"
},
  "geometry": {"coordinates":[-78.766288,35.594723],"type":"Point"}
}