{
  "type": "Feature",
  "properties": {
    "iso:country":"US",
    "sg:address":"39 S Market St",
    "sg:city":"Asheville",
    "sg:classifiers":[
        {
            "category":"Social Services",
            "type":"Services"
        }
    ],
    "sg:phone":"+1 828 236 1228",
    "sg:postcode":"28801",
    "sg:province":"NC",
    "sg:tags":[
        "youth",
        "organization",
        "center"
    ],
    "wof:name":"Asheville Buncombe Education",
    "wof:placetype":"venue"
},
  "geometry": {"coordinates":[-82.550434,35.594867],"type":"Point"}
}