{
  "type": "Feature",
  "properties": {
    "addr:full":"1771 Piney Green Rd Jacksonville NC 28546",
    "addr:housenumber":"1771",
    "addr:postcode":"28546",
    "addr:street":"Piney Green Rd",
    "iso:country":"US",
    "sg:address":"1771 Piney Green Rd",
    "sg:city":"Jacksonville",
    "sg:classifiers":[
        {
            "category":"Building & Trades",
            "subcategory":"Construction",
            "type":"Services"
        }
    ],
    "sg:phone":"+1 910 455 9100",
    "sg:postcode":"28546",
    "sg:province":"NC",
    "sg:tags":[
        "painter"
    ],
    "wof:name":"Hall's Painting",
    "wof:placetype":"venue"
},
  "geometry": {"coordinates":[-77.327663,34.753046],"type":"Point"}
}