{
  "type": "Feature",
  "properties": {
    "addr:full":"111 Rynal Dr Garner NC 27529",
    "addr:housenumber":"111",
    "addr:postcode":"27529",
    "addr:street":"Rynal Dr",
    "iso:country":"US",
    "sg:address":"111 Rynal Dr",
    "sg:city":"Garner",
    "sg:classifiers":[
        {
            "category":"Retail",
            "subcategory":"Laundry & Dry Cleaning",
            "type":"Services"
        }
    ],
    "sg:phone":"+1 919 662 3776",
    "sg:postcode":"27529",
    "sg:province":"NC",
    "sg:tags":[
        "water",
        "upholstery",
        "d",
        "restoration",
        "carpet"
    ],
    "wof:name":"Carpet - Pro Systems Inc",
    "wof:placetype":"venue"
},
  "geometry": {"coordinates":[-78.56311599999999,35.578817],"type":"Point"}
}