{
  "type": "Feature",
  "properties": {
    "iso:country":"US",
    "sg:address":"4005 Burton Ln",
    "sg:city":"Denver",
    "sg:classifiers":[
        {
            "category":"Professional",
            "type":"Services"
        }
    ],
    "sg:phone":"+1 704 489 6525",
    "sg:postcode":"28037",
    "sg:province":"NC",
    "wof:name":"D McDonald & Associates LLC",
    "wof:placetype":"venue"
},
  "geometry": {"coordinates":[-80.970294,35.511352],"type":"Point"}
}