{
  "type": "Feature",
  "properties": {
    "addr:full":"749 US Hwy 158 Byp Warrenton NC 27589",
    "addr:housenumber":"749",
    "addr:postcode":"27589",
    "addr:street":"Us Hwy 158 Byp",
    "iso:country":"US",
    "sg:address":"749 US Hwy 158 Byp",
    "sg:city":"Warrenton",
    "sg:classifiers":[
        {
            "category":"Building & Trades",
            "subcategory":"Construction",
            "type":"Services"
        }
    ],
    "sg:phone":"+1 252 257 1135",
    "sg:postcode":"27589",
    "sg:province":"NC",
    "sg:tags":[
        "home",
        "improvement"
    ],
    "wof:name":"B & B Home Maintenance",
    "wof:placetype":"venue"
},
  "geometry": {"coordinates":[-78.138035,36.436055],"type":"Point"}
}