{
  "type": "Feature",
  "properties": {
    "addr:full":"200 Mount Olive Rd Newton Grove NC 28337",
    "addr:housenumber":"200",
    "addr:postcode":"28337",
    "addr:street":"Mount Olive Rd",
    "iso:country":"US",
    "sg:address":"200 Mount Olive Rd",
    "sg:city":"Newton Grove",
    "sg:classifiers":[
        {
            "category":"Professional",
            "subcategory":"Business Services",
            "type":"Services"
        }
    ],
    "sg:phone":"+1 910 594 1172",
    "sg:postcode":"28337",
    "sg:province":"NC",
    "sg:tags":[
        "translator",
        "interpreter"
    ],
    "wof:name":"M & M Latino Svc",
    "wof:placetype":"venue"
},
  "geometry": {"coordinates":[-78.585815,34.588892],"type":"Point"}
}