{
  "type": "Feature",
  "properties": {
    "addr:full":"544 N Graham Ave Winston Salem NC 27101",
    "addr:housenumber":"544",
    "addr:postcode":"27101",
    "addr:street":"N Graham Ave",
    "iso:country":"US",
    "sg:address":"544 N Graham Ave",
    "sg:city":"Winston Salem",
    "sg:classifiers":[
        {
            "category":"Professional",
            "subcategory":"Accounting & Tax Preparation",
            "type":"Services"
        }
    ],
    "sg:phone":"+1 336 721 9991",
    "sg:postcode":"27101",
    "sg:province":"NC",
    "sg:tags":[
        "accountant"
    ],
    "wof:name":"Simmons Accounting & Tax Finan",
    "wof:placetype":"venue"
},
  "geometry": {"coordinates":[-80.224856,36.101374],"type":"Point"}
}