{
  "type": "Feature",
  "properties": {
    "iso:country":"US",
    "sg:address":"108 Arco Rd",
    "sg:city":"Asheville",
    "sg:classifiers":[
        {
            "category":"Building & Trades",
            "subcategory":"Construction",
            "type":"Services"
        }
    ],
    "sg:phone":"+1 828 298 8577",
    "sg:postcode":"28805",
    "sg:province":"NC",
    "sg:tags":[
        "siding",
        "contractor"
    ],
    "wof:name":"Lipe Home Exteriors",
    "wof:placetype":"venue"
},
  "geometry": {"coordinates":[-82.507273,35.587838],"type":"Point"}
}