{
  "type": "Feature",
  "properties": {
    "addr:full":"275 Bayleaf Rd New Bern NC 28560",
    "addr:housenumber":"275",
    "addr:postcode":"28560",
    "addr:street":"Bayleaf Rd",
    "iso:country":"US",
    "sg:address":"275 Bayleaf Rd",
    "sg:city":"New Bern",
    "sg:classifiers":[
        {
            "category":"Professional",
            "subcategory":"Advertising",
            "type":"Services"
        }
    ],
    "sg:phone":"+1 252 633 6396",
    "sg:postcode":"28560",
    "sg:province":"NC",
    "sg:tags":[
        "distribution"
    ],
    "wof:name":"J & L Distribution",
    "wof:placetype":"venue"
},
  "geometry": {"coordinates":[-76.96707499999999,35.140965],"type":"Point"}
}