{
  "type": "Feature",
  "properties": {
    "addr:full":"2406 Lake Brandt Pl Greensboro NC 27455",
    "addr:housenumber":"2406",
    "addr:postcode":"27455",
    "addr:street":"Lake Brandt Pl",
    "iso:country":"US",
    "sg:address":"2406 Lake Brandt Pl",
    "sg:city":"Greensboro",
    "sg:classifiers":[
        {
            "category":"Wholesale",
            "subcategory":"Jewelry",
            "type":"Manufacturing & Wholesale Goods"
        }
    ],
    "sg:phone":"+1 336 327 7648",
    "sg:postcode":"27455",
    "sg:province":"NC",
    "sg:tags":[
        "stone"
    ],
    "wof:name":"Computer Accessories Unlimited",
    "wof:placetype":"venue"
},
  "geometry": {"coordinates":[-79.846951,36.140941],"type":"Point"}
}