{
  "type": "Feature",
  "properties": {
    "addr:full":"2533 Old Mountain Rd Trinity NC 27370",
    "addr:housenumber":"2533",
    "addr:postcode":"27370",
    "addr:street":"Old Mountain Rd",
    "iso:country":"US",
    "sg:address":"2533 Old Mountain Rd",
    "sg:city":"Trinity",
    "sg:classifiers":[
        {
            "category":"Building & Trades",
            "subcategory":"Plumbing",
            "type":"Services"
        }
    ],
    "sg:phone":"+1 336 475 8564",
    "sg:postcode":"27370",
    "sg:province":"NC",
    "sg:tags":[
        "system",
        "contractor",
        "air conditioning"
    ],
    "sg:website":"http://www.electrip.com",
    "wof:name":"Electriplumb",
    "wof:placetype":"venue"
},
  "geometry": {"coordinates":[-80.034195,35.816645],"type":"Point"}
}