{
  "type": "Feature",
  "properties": {
    "addr:full":"221 E Water St Statesville NC 28677",
    "addr:housenumber":"221",
    "addr:postcode":"28677",
    "addr:street":"E Water St",
    "iso:country":"US",
    "sg:address":"221 E Water St",
    "sg:city":"Statesville",
    "sg:classifiers":[
        {
            "category":"Government",
            "subcategory":"Police Station",
            "type":"Public Place"
        }
    ],
    "sg:phone":"+1 704 878 3180",
    "sg:postcode":"28677",
    "sg:province":"NC",
    "sg:tags":[
        "protection"
    ],
    "wof:name":"County Detention Center",
    "wof:placetype":"venue"
},
  "geometry": {"coordinates":[-80.88636200000001,35.787026],"type":"Point"}
}