{
  "type": "Feature",
  "properties": {
    "addr:full":"42 Catawba St Belmont NC 28012",
    "addr:housenumber":"42",
    "addr:postcode":"28012",
    "addr:street":"Catawba St",
    "iso:country":"US",
    "sg:address":"42 Catawba St",
    "sg:city":"Belmont",
    "sg:classifiers":[
        {
            "category":"Banks & Credit Unions",
            "subcategory":"Bank",
            "type":"Services"
        }
    ],
    "sg:phone":"+1 704 825 9861",
    "sg:postcode":"28012",
    "sg:province":"NC",
    "sg:tags":[
        "savings",
        "loan",
        "association"
    ],
    "wof:name":"Belmont Federal Savings & Loan",
    "wof:placetype":"venue"
},
  "geometry": {"coordinates":[-81.035788,35.243647],"type":"Point"}
}