{
  "type": "Feature",
  "properties": {
    "iso:country":"US",
    "sg:address":"163 Canaan Dr",
    "sg:city":"Candler",
    "sg:classifiers":[
        {
            "category":"Organizations",
            "subcategory":"Religious Organization",
            "type":"Services"
        }
    ],
    "sg:phone":"+1 828 670 6449",
    "sg:postcode":"28715",
    "sg:province":"NC",
    "sg:tags":[
        "church"
    ],
    "wof:name":"His People Community Church",
    "wof:placetype":"venue"
},
  "geometry": {"coordinates":[-82.67464,35.556601],"type":"Point"}
}