{
  "type": "Feature",
  "properties": {
    "iso:country":"US",
    "sg:address":"3324 Bellemont-Mt Hermon Rd",
    "sg:city":"Burlington",
    "sg:classifiers":[
        {
            "category":"Building & Trades",
            "subcategory":"Construction",
            "type":"Services"
        }
    ],
    "sg:phone":"+1 336 229 5695",
    "sg:postcode":"27215",
    "sg:province":"NC",
    "sg:tags":[
        "contractor"
    ],
    "wof:name":"Padgett Masonry",
    "wof:placetype":"venue"
},
  "geometry": {"coordinates":[-79.437831,36.020952],"type":"Point"}
}