{
  "type": "Feature",
  "properties": {
    "addr:full":"3158 S Brightleaf Blvd Smithfield NC 27577",
    "addr:housenumber":"3158",
    "addr:postcode":"27577",
    "addr:street":"S Brightleaf Blvd",
    "iso:country":"US",
    "sg:address":"3158 S Brightleaf Blvd",
    "sg:city":"Smithfield",
    "sg:classifiers":[
        {
            "category":"Restaurant",
            "type":"Food & Drink"
        }
    ],
    "sg:phone":"+1 919 934 1069",
    "sg:postcode":"27577",
    "sg:province":"NC",
    "wof:name":"White Swan House Of Steaks",
    "wof:placetype":"venue"
},
  "geometry": {"coordinates":[-78.377725,35.476653],"type":"Point"}
}