{
  "type": "Feature",
  "properties": {
    "addr:full":"116 Drywood Pl Cary NC 27513",
    "addr:housenumber":"116",
    "addr:postcode":"27513",
    "addr:street":"Drywood Pl",
    "iso:country":"US",
    "sg:address":"116 Drywood Pl",
    "sg:city":"Cary",
    "sg:classifiers":[
        {
            "category":"Wholesale",
            "subcategory":"Vending Machines",
            "type":"Manufacturing & Wholesale Goods"
        }
    ],
    "sg:phone":"+1 919 463 9221",
    "sg:postcode":"27513",
    "sg:province":"NC",
    "sg:tags":[
        "operator"
    ],
    "wof:name":"Friendly Vending Inc",
    "wof:placetype":"venue"
},
  "geometry": {"coordinates":[-78.77819,35.801508],"type":"Point"}
}