{
  "type": "Feature",
  "properties": {
    "iso:country":"US",
    "sg:address":"1516 Brookside Camp Rd",
    "sg:city":"Hendersonville",
    "sg:classifiers":[
        {
            "category":"Personal",
            "subcategory":"Beauty Salon",
            "type":"Services"
        }
    ],
    "sg:phone":"+1   ",
    "sg:postcode":"28792",
    "sg:province":"NC",
    "sg:tags":[
        "shop"
    ],
    "wof:name":"Hair Accents",
    "wof:placetype":"venue"
},
  "geometry": {"coordinates":[-82.461091,35.380422],"type":"Point"}
}