{
  "type": "Feature",
  "properties": {
    "iso:country":"US",
    "sg:address":"8442 Sidbury Rd",
    "sg:city":"Wilmington",
    "sg:classifiers":[
        {
            "category":"Building & Trades",
            "subcategory":"Construction",
            "type":"Services"
        }
    ],
    "sg:phone":"+1 910 686 8854",
    "sg:postcode":"28411",
    "sg:province":"NC",
    "sg:tags":[
        "house"
    ],
    "wof:name":"Don OH Inc",
    "wof:placetype":"venue"
},
  "geometry": {"coordinates":[-77.79119300000001,34.33883],"type":"Point"}
}