{
  "type": "Feature",
  "properties": {
    "addr:full":"610 McNinch St Charlotte NC 28208",
    "addr:housenumber":"610",
    "addr:postcode":"28208",
    "addr:street":"Mcninch St",
    "iso:country":"US",
    "sg:address":"610 McNinch St",
    "sg:city":"Charlotte",
    "sg:classifiers":[
        {
            "category":"Wholesale",
            "subcategory":"Hardware",
            "type":"Manufacturing & Wholesale Goods"
        }
    ],
    "sg:phone":"+1 704 364 8877",
    "sg:postcode":"28208",
    "sg:province":"NC",
    "wof:name":"Blackmon J G & Associates",
    "wof:placetype":"venue"
},
  "geometry": {"coordinates":[-80.855958,35.230205],"type":"Point"}
}