{
  "type": "Feature",
  "properties": {
    "addr:full":"301 Faith Rd Salisbury NC 28146",
    "addr:housenumber":"301",
    "addr:postcode":"28146",
    "addr:street":"Faith Rd",
    "iso:country":"US",
    "sg:address":"301 Faith Rd",
    "sg:city":"Salisbury",
    "sg:classifiers":[
        {
            "category":"Restaurant",
            "type":"Food & Drink"
        }
    ],
    "sg:menulink":"http://www.allmenus.com/nc/salisbury/153742-zaxbys/menu/",
    "sg:phone":"+1 704 639 9929",
    "sg:postcode":"28146",
    "sg:province":"NC",
    "sg:tags":[
        "american",
        "wing"
    ],
    "wof:name":"Zaxby's",
    "wof:placetype":"venue"
},
  "geometry": {"coordinates":[-80.45801899999999,35.651807],"type":"Point"}
}