{
  "type": "Feature",
  "properties": {
    "addr:full":"214 Mulberry St SW Lenoir NC 28645",
    "addr:housenumber":"214",
    "addr:postcode":"28645",
    "addr:street":"Mulberry St Sw",
    "iso:country":"US",
    "sg:address":"214 Mulberry St SW",
    "sg:city":"Lenoir",
    "sg:classifiers":[
        {
            "category":"Freight",
            "type":"Transportation"
        }
    ],
    "sg:phone":"+1 828 757 8679",
    "sg:postcode":"28645",
    "sg:province":"NC",
    "sg:tags":[
        "consultant"
    ],
    "wof:name":"CCATS",
    "wof:placetype":"venue"
},
  "geometry": {"coordinates":[-81.537887,35.913017],"type":"Point"}
}