{
  "type": "Feature",
  "properties": {
    "addr:full":"4208 Six Forks Rd Raleigh NC 27609",
    "addr:housenumber":"4208",
    "addr:postcode":"27609",
    "addr:street":"Six Forks Rd",
    "iso:country":"US",
    "sg:address":"4208 Six Forks Rd",
    "sg:city":"Raleigh",
    "sg:classifiers":[
        {
            "category":"Organizations",
            "subcategory":"Religious Organization",
            "type":"Services"
        }
    ],
    "sg:phone":"+1 919 789 4401",
    "sg:postcode":"27609",
    "sg:province":"NC",
    "sg:tags":[
        "church"
    ],
    "wof:name":"Universities & Schools Fllwshp",
    "wof:placetype":"venue"
},
  "geometry": {"coordinates":[-78.641488,35.838096],"type":"Point"}
}