{
  "type": "Feature",
  "properties": {
    "addr:full":"800 Bellview Ave NE Valdese NC 28690",
    "addr:housenumber":"800",
    "addr:postcode":"28690",
    "addr:street":"Bellview Ave Ne",
    "iso:country":"US",
    "sg:address":"800 Bellview Ave NE",
    "sg:city":"Valdese",
    "sg:classifiers":[
        {
            "category":"Real Estate",
            "subcategory":"Real Estate Agent",
            "type":"Services"
        }
    ],
    "sg:phone":"+1 828 874 2524",
    "sg:postcode":"28690",
    "sg:province":"NC",
    "wof:name":"Ritchie Realty",
    "wof:placetype":"venue"
},
  "geometry": {"coordinates":[-81.55432500000001,35.74559],"type":"Point"}
}