{
  "type": "Feature",
  "properties": {
    "addr:full":"255 Indian Trl Indian Trail NC 28043",
    "addr:housenumber":"255",
    "addr:postcode":"28043",
    "addr:street":"Indian Trl;Trail",
    "iso:country":"US",
    "sg:address":"255 Indian Trl",
    "sg:city":"Indian Trail",
    "sg:classifiers":[
        {
            "category":"Home & Garden",
            "subcategory":"Building Materials",
            "type":"Retail Goods"
        }
    ],
    "sg:phone":"+1 704 684 0246",
    "sg:postcode":"28043",
    "sg:province":"NC",
    "wof:name":"Geraled B Cates Associates",
    "wof:placetype":"venue"
},
  "geometry": {"coordinates":[-81.91770200000001,35.38756],"type":"Point"}
}