{
  "type": "Feature",
  "properties": {
    "addr:full":"1800 Hendersonville Rd Asheville NC 28803",
    "addr:housenumber":"1800",
    "addr:postcode":"28803",
    "addr:street":"Hendersonville Rd",
    "iso:country":"US",
    "sg:address":"1800 Hendersonville Rd",
    "sg:city":"Asheville",
    "sg:classifiers":[
        {
            "category":"Ice Cream",
            "type":"Food & Drink"
        }
    ],
    "sg:menulink":"http://www.allmenus.com/nc/asheville/209187-tcby/menu/",
    "sg:phone":"+1 828 274 1100",
    "sg:postcode":"28803",
    "sg:province":"NC",
    "sg:tags":[
        "smoothy",
        "juice",
        "american"
    ],
    "wof:name":"TCBY",
    "wof:placetype":"venue"
},
  "geometry": {"coordinates":[-82.52429100000001,35.504399],"type":"Point"}
}