{
  "type": "Feature",
  "properties": {
    "addr:full":"4302 Holly Tree Rd Wilmington NC 28412",
    "addr:housenumber":"4302",
    "addr:postcode":"28412",
    "addr:street":"Holly Tree Rd",
    "iso:country":"US",
    "sg:address":"4302 Holly Tree Rd",
    "sg:city":"Wilmington",
    "sg:classifiers":[
        {
            "category":"Professional",
            "subcategory":"Research",
            "type":"Services"
        }
    ],
    "sg:phone":"+1 910 799 5500",
    "sg:postcode":"28412",
    "sg:province":"NC",
    "sg:tags":[
        "commercial",
        "physical"
    ],
    "sg:website":"www.piedmontmedical.com",
    "wof:name":"New Hanover Medical Research",
    "wof:placetype":"venue"
},
  "geometry": {"coordinates":[-77.894306,34.197886],"type":"Point"}
}