{
  "type": "Feature",
  "properties": {
    "addr:full":"4210 Summit Ave Greensboro NC 27405",
    "addr:housenumber":"4210",
    "addr:postcode":"27405",
    "addr:street":"Summit Ave",
    "iso:country":"US",
    "sg:address":"4210 Summit Ave",
    "sg:city":"Greensboro",
    "sg:classifiers":[
        {
            "category":"Wholesale",
            "subcategory":"Farm Supplies",
            "type":"Manufacturing & Wholesale Goods"
        }
    ],
    "sg:phone":"+1 336 621 4371",
    "sg:postcode":"27405",
    "sg:province":"NC",
    "sg:tags":[
        "tractor"
    ],
    "wof:name":"Clark Farm Lawn & Garden",
    "wof:placetype":"venue"
},
  "geometry": {"coordinates":[-79.76102400000001,36.131405],"type":"Point"}
}