{
  "type": "Feature",
  "properties": {
    "addr:full":"5311 Trade Winds Rd New Bern NC 28560",
    "addr:housenumber":"5311",
    "addr:postcode":"28560",
    "addr:street":"Trade Winds Rd",
    "iso:country":"US",
    "sg:address":"5311 Trade Winds Rd",
    "sg:city":"New Bern",
    "sg:classifiers":[
        {
            "category":"Wholesale",
            "subcategory":"Machinery & Supplies",
            "type":"Manufacturing & Wholesale Goods"
        }
    ],
    "sg:phone":"+1 252 634 3566",
    "sg:postcode":"28560",
    "sg:province":"NC",
    "sg:tags":[
        "equipment",
        "transportation"
    ],
    "wof:name":"Chatham Marine Supply Cor",
    "wof:placetype":"venue"
},
  "geometry": {"coordinates":[-76.976849,35.074959],"type":"Point"}
}