{
  "type": "Feature",
  "properties": {
    "iso:country":"US",
    "sg:address":"4090 Dentons Chapel Rd",
    "sg:city":"Morganton",
    "sg:classifiers":[
        {
            "category":"Building & Trades",
            "subcategory":"Electrical",
            "type":"Services"
        }
    ],
    "sg:phone":"+1 828 438 4205",
    "sg:postcode":"28655",
    "sg:province":"NC",
    "sg:tags":[
        "electrical",
        "contractor"
    ],
    "wof:name":"Industrial Control Technology",
    "wof:placetype":"venue"
},
  "geometry": {"coordinates":[-81.73446199999999,35.686389],"type":"Point"}
}