{
  "type": "Feature",
  "properties": {
    "addr:full":"725 Carr St Rocky Mount NC 27804",
    "addr:housenumber":"725",
    "addr:postcode":"27804",
    "addr:street":"Carr St",
    "iso:country":"US",
    "sg:address":"725 Carr St",
    "sg:city":"Rocky Mount",
    "sg:classifiers":[
        {
            "category":"Manufacturing",
            "subcategory":"Metals",
            "type":"Manufacturing & Wholesale Goods"
        }
    ],
    "sg:phone":"+1 252 972 4675",
    "sg:postcode":"27804",
    "sg:province":"NC",
    "sg:tags":[
        "fabricator",
        "sheet"
    ],
    "wof:name":"Howell Fabrication Inc",
    "wof:placetype":"venue"
},
  "geometry": {"coordinates":[-77.80334000000001,35.950677],"type":"Point"}
}