{
  "type": "Feature",
  "properties": {
    "addr:full":"814 W Innes St Salisbury NC 28144",
    "addr:housenumber":"814",
    "addr:postcode":"28144",
    "addr:street":"W Innes St",
    "iso:country":"US",
    "sg:address":"814 W Innes St",
    "sg:city":"Salisbury",
    "sg:classifiers":[
        {
            "category":"Organizations",
            "subcategory":"Labor Organization",
            "type":"Services"
        }
    ],
    "sg:phone":"+1   ",
    "sg:postcode":"28144",
    "sg:province":"NC",
    "wof:name":"Alloyworks Lc",
    "wof:placetype":"venue"
},
  "geometry": {"coordinates":[-80.479535,35.675042],"type":"Point"}
}