{
  "type": "Feature",
  "properties": {
    "addr:full":"1739 Beachwood Rd Mooresboro SC 28114",
    "addr:housenumber":"1739",
    "addr:postcode":"28114",
    "addr:street":"Beachwood Rd",
    "iso:country":"US",
    "sg:address":"1739 Beachwood Rd",
    "sg:city":"Mooresboro",
    "sg:classifiers":[
        {
            "category":"Building & Trades",
            "subcategory":"Electrical",
            "type":"Services"
        }
    ],
    "sg:phone":"+1 704 434 2253",
    "sg:postcode":"28114",
    "sg:province":"SC",
    "sg:tags":[
        "electrical",
        "contractor"
    ],
    "wof:name":"Jn Greene Electrical Contracti",
    "wof:placetype":"venue"
},
  "geometry": {"coordinates":[-81.70290199999999,35.191054],"type":"Point"}
}