{
  "type": "Feature",
  "properties": {
    "addr:full":"5405 Blue Sage Dr Raleigh NC 27606",
    "addr:housenumber":"5405",
    "addr:postcode":"27606",
    "addr:street":"Blue Sage Dr",
    "iso:country":"US",
    "sg:address":"5405 Blue Sage Dr",
    "sg:city":"Raleigh",
    "sg:classifiers":[
        {
            "category":"Building & Trades",
            "subcategory":"Construction",
            "type":"Services"
        }
    ],
    "sg:phone":"+1 919 833 1189",
    "sg:postcode":"27606",
    "sg:province":"NC",
    "sg:tags":[
        "general",
        "contractor"
    ],
    "wof:name":"Master Craft Builders",
    "wof:placetype":"venue"
},
  "geometry": {"coordinates":[-78.698971,35.705845],"type":"Point"}
}