{
  "type": "Feature",
  "properties": {
    "iso:country":"US",
    "sg:address":"2446 Startown Rd",
    "sg:city":"Newton",
    "sg:classifiers":[
        {
            "category":"Building & Trades",
            "subcategory":"Plumbing",
            "type":"Services"
        }
    ],
    "sg:phone":"+1 828 312 3589",
    "sg:postcode":"28658",
    "sg:province":"NC",
    "sg:tags":[
        "plumbing",
        "contractor"
    ],
    "wof:name":"RCI Plumbing",
    "wof:placetype":"venue"
},
  "geometry": {"coordinates":[-81.273645,35.68096],"type":"Point"}
}