{
  "type": "Feature",
  "properties": {
    "iso:country":"US",
    "sg:address":"250 River Birch Cir",
    "sg:city":"Mooresville",
    "sg:classifiers":[
        {
            "category":"Wholesale",
            "subcategory":"Durable Goods & Equipment",
            "type":"Manufacturing & Wholesale Goods"
        }
    ],
    "sg:phone":"+1 704 799 1759",
    "sg:postcode":"28115",
    "sg:province":"NC",
    "wof:name":"Hamlet & Smith Inc",
    "wof:placetype":"venue"
},
  "geometry": {"coordinates":[-80.795407,35.546032],"type":"Point"}
}