{
  "type": "Feature",
  "properties": {
    "addr:full":"202 N Church St Louisburg NC 27549",
    "addr:housenumber":"202",
    "addr:postcode":"27549",
    "addr:street":"N Church St",
    "iso:country":"US",
    "sg:address":"202 N Church St",
    "sg:city":"Louisburg",
    "sg:classifiers":[
        {
            "category":"Professional",
            "subcategory":"Business Services",
            "type":"Services"
        }
    ],
    "sg:phone":"+1   ",
    "sg:postcode":"27549",
    "sg:province":"NC",
    "wof:name":"Jwn Enterprises LLC",
    "wof:placetype":"venue"
},
  "geometry": {"coordinates":[-78.300673,36.101984],"type":"Point"}
}