{
  "type": "Feature",
  "properties": {
    "addr:full":"3586 Georgia Rd Franklin NC 28734",
    "addr:housenumber":"3586",
    "addr:postcode":"nc 28734",
    "addr:street":"Georgia Rd",
    "iso:country":"US",
    "sg:address":"3586 Georgia Rd",
    "sg:city":"Franklin",
    "sg:classifiers":[
        {
            "category":"Building & Trades",
            "subcategory":"Construction",
            "type":"Services"
        }
    ],
    "sg:phone":"+1 828 349 1877",
    "sg:postcode":"28734",
    "sg:province":"NC",
    "sg:tags":[
        "house"
    ],
    "wof:name":"Greenbriar Homes Inc",
    "wof:placetype":"venue"
},
  "geometry": {"coordinates":[-83.382085,35.023092],"type":"Point"}
}