{
  "type": "Feature",
  "properties": {
    "iso:country":"US",
    "sg:address":"4300 Chesapeake Dr",
    "sg:city":"Charlotte",
    "sg:classifiers":[
        {
            "category":"Wholesale",
            "subcategory":"Vending Machines",
            "type":"Manufacturing & Wholesale Goods"
        }
    ],
    "sg:phone":"+1 704 394 2964",
    "sg:postcode":"28216",
    "sg:province":"NC",
    "sg:tags":[
        "operator"
    ],
    "wof:name":"Quality Beverage Brands Vendin",
    "wof:placetype":"venue"
},
  "geometry": {"coordinates":[-80.876711,35.280258],"type":"Point"}
}