{
  "type": "Feature",
  "properties": {
    "addr:full":"4801 Grafton Rd Greensboro NC 27405",
    "addr:housenumber":"4801",
    "addr:postcode":"27405",
    "addr:street":"Grafton Rd",
    "iso:country":"US",
    "sg:address":"4801 Grafton Rd",
    "sg:city":"Greensboro",
    "sg:classifiers":[
        {
            "category":"Travel",
            "subcategory":"Hotels & Motels",
            "type":"Entertainment"
        }
    ],
    "sg:phone":"+1   ",
    "sg:postcode":"27405",
    "sg:province":"NC",
    "sg:tags":[
        "operation"
    ],
    "wof:name":"Star Motel",
    "wof:placetype":"venue"
},
  "geometry": {"coordinates":[-79.73279599999999,36.146972],"type":"Point"}
}