{
  "type": "Feature",
  "properties": {
    "iso:country":"US",
    "sg:address":"77 McDowell St",
    "sg:city":"Asheville",
    "sg:classifiers":[
        {
            "category":"Health Services",
            "subcategory":"Doctor",
            "type":"Services"
        }
    ],
    "sg:phone":"+1 828 254 5326",
    "sg:postcode":"28801",
    "sg:province":"NC",
    "sg:tags":[
        "physician",
        "medical",
        "surgeon"
    ],
    "wof:name":"Asheville Pediatric Assoc PA",
    "wof:placetype":"venue"
},
  "geometry": {"coordinates":[-82.555215,35.583678],"type":"Point"}
}