{
  "type": "Feature",
  "properties": {
    "addr:full":"618 Knollwood St Winston Salem NC 27103",
    "addr:housenumber":"618",
    "addr:postcode":"27103",
    "addr:street":"Knollwood St",
    "iso:country":"US",
    "sg:address":"618 Knollwood St",
    "sg:city":"Winston Salem",
    "sg:classifiers":[
        {
            "category":"Social Services",
            "type":"Services"
        }
    ],
    "sg:phone":"+1 336 774 8454",
    "sg:postcode":"27103",
    "sg:province":"NC",
    "sg:tags":[
        "community"
    ],
    "wof:name":"YMCA",
    "wof:placetype":"venue"
},
  "geometry": {"coordinates":[-80.286193,36.083512],"type":"Point"}
}