{
  "type": "Feature",
  "properties": {
    "iso:country":"US",
    "sg:address":"4351 Central Ave",
    "sg:city":"Charlotte",
    "sg:classifiers":[
        {
            "category":"Shopping",
            "subcategory":"Pharmacy",
            "type":"Retail Goods"
        }
    ],
    "sg:phone":"+1 704 535 5280",
    "sg:postcode":"28205",
    "sg:province":"NC",
    "sg:website":"www.cvs.com",
    "wof:name":"CVS Pharmacy",
    "wof:placetype":"venue"
},
  "geometry": {"coordinates":[-80.77189,35.214274],"type":"Point"}
}