{
  "type": "Feature",
  "properties": {
    "iso:country":"US",
    "sg:address":"2612 Gaston Day School Rd",
    "sg:city":"Gastonia",
    "sg:classifiers":[
        {
            "category":"Building & Trades",
            "subcategory":"Landscaping Services",
            "type":"Services"
        }
    ],
    "sg:phone":"+1 704 674 9664",
    "sg:postcode":"28056",
    "sg:province":"NC",
    "sg:tags":[
        "landscape",
        "contractor"
    ],
    "wof:name":"Creative Landscape & Irrgtn",
    "wof:placetype":"venue"
},
  "geometry": {"coordinates":[-81.13428999999999,35.205284],"type":"Point"}
}