{
  "type": "Feature",
  "properties": {
    "addr:full":"702 Davidson Ave Lexington NC 27292",
    "addr:housenumber":"702",
    "addr:postcode":"27292",
    "addr:street":"Davidson Ave",
    "iso:country":"US",
    "sg:address":"702 Davidson Ave",
    "sg:city":"Lexington",
    "sg:classifiers":[
        {
            "category":"Building & Trades",
            "subcategory":"Cleaning & Sanitation",
            "type":"Services"
        }
    ],
    "sg:phone":"+1   ",
    "sg:postcode":"27292",
    "sg:province":"NC",
    "sg:tags":[
        "maintenance"
    ],
    "wof:name":"Noel Mike Floor Service",
    "wof:placetype":"venue"
},
  "geometry": {"coordinates":[-80.19739300000001,35.81458],"type":"Point"}
}