{
  "type": "Feature",
  "properties": {
    "iso:country":"US",
    "sg:address":"1413 Avondale Dr",
    "sg:city":"Durham",
    "sg:classifiers":[
        {
            "category":"Communications",
            "type":"Services"
        }
    ],
    "sg:phone":"+1 919 683 9522",
    "sg:postcode":"27701",
    "sg:province":"NC",
    "sg:tags":[
        "communication"
    ],
    "wof:name":"One Hop Communications",
    "wof:placetype":"venue"
},
  "geometry": {"coordinates":[-78.885345,36.005998],"type":"Point"}
}