{
  "type": "Feature",
  "properties": {
    "addr:full":"1309 Cane Creek Dr Garner NC 27529",
    "addr:housenumber":"1309",
    "addr:postcode":"27529",
    "addr:street":"Cane Creek Dr",
    "iso:country":"US",
    "sg:address":"1309 Cane Creek Dr",
    "sg:city":"Garner",
    "sg:classifiers":[
        {
            "category":"Building & Trades",
            "subcategory":"Landscaping Services",
            "type":"Services"
        }
    ],
    "sg:phone":"+1 919 673 8701",
    "sg:postcode":"27529",
    "sg:province":"NC",
    "sg:tags":[
        "landscape",
        "contractor"
    ],
    "wof:name":"Pate's Landscaping & Trucking",
    "wof:placetype":"venue"
},
  "geometry": {"coordinates":[-78.64559,35.681692],"type":"Point"}
}