{
  "type": "Feature",
  "properties": {
    "iso:country":"US",
    "sg:address":"1088 W Dalton Rd",
    "sg:city":"King",
    "sg:classifiers":[
        {
            "category":"Shopping",
            "subcategory":"Florist",
            "type":"Retail Goods"
        }
    ],
    "sg:phone":"+1 336 983 4107",
    "sg:postcode":"27021",
    "sg:province":"NC",
    "sg:tags":[
        "retailer"
    ],
    "wof:name":"Mitchells Nursery & Greenhills",
    "wof:placetype":"venue"
},
  "geometry": {"coordinates":[-80.39117899999999,36.298959],"type":"Point"}
}