{
  "type": "Feature",
  "properties": {
    "iso:country":"US",
    "sg:address":"315 US Hwy 17 Bus",
    "sg:city":"Hertford",
    "sg:classifiers":[
        {
            "category":"Restaurant",
            "type":"Food & Drink"
        }
    ],
    "sg:phone":"+1 252 426 3397",
    "sg:postcode":"27944",
    "sg:province":"NC",
    "wof:name":"Ming Hing Restaurant",
    "wof:placetype":"venue"
},
  "geometry": {"coordinates":[-76.47494,36.18575],"type":"Point"}
}