{
  "type": "Feature",
  "properties": {
    "addr:full":"201 N Church St Mooresville NC 28115",
    "addr:housenumber":"201",
    "addr:postcode":"28115",
    "addr:street":"N Church St",
    "iso:country":"US",
    "sg:address":"201 N Church St",
    "sg:city":"Mooresville",
    "sg:classifiers":[
        {
            "category":"Manufacturing",
            "subcategory":"Food",
            "type":"Manufacturing & Wholesale Goods"
        }
    ],
    "sg:phone":"+1 704 660 6670",
    "sg:postcode":"28115",
    "sg:province":"NC",
    "sg:tags":[
        "product",
        "mfg"
    ],
    "wof:name":"Saralee Bakery",
    "wof:placetype":"venue"
},
  "geometry": {"coordinates":[-80.807569,35.584577],"type":"Point"}
}