{
  "type": "Feature",
  "properties": {
    "iso:country":"US",
    "sg:address":"283 Deerchase Cir",
    "sg:city":"Statesville",
    "sg:classifiers":[
        {
            "category":"Organizations",
            "subcategory":"Membership Organization",
            "type":"Services"
        }
    ],
    "sg:phone":"+1 704 873 5300",
    "sg:postcode":"28625",
    "sg:province":"NC",
    "wof:name":"Appalachian League-Pro Bsbll",
    "wof:placetype":"venue"
},
  "geometry": {"coordinates":[-80.75710599999999,35.877445],"type":"Point"}
}