{
  "type": "Feature",
  "properties": {
    "iso:country":"US",
    "sg:address":"2411 Gumtree Rd",
    "sg:city":"Winston Salem",
    "sg:classifiers":[
        {
            "category":"Wholesale",
            "subcategory":"Construction Materials",
            "type":"Manufacturing & Wholesale Goods"
        }
    ],
    "sg:phone":"+1 336 785 1200",
    "sg:postcode":"27107",
    "sg:province":"NC",
    "sg:tags":[
        "custom",
        "woodworking",
        "cabinetry",
        "furniture"
    ],
    "wof:name":"Architectural Woodworking",
    "wof:placetype":"venue"
},
  "geometry": {"coordinates":[-80.19623300000001,35.997758],"type":"Point"}
}