{
  "type": "Feature",
  "properties": {
    "addr:full":"1207 S Cox St Asheboro NC 27203",
    "addr:housenumber":"1207",
    "addr:postcode":"27203",
    "addr:street":"S Cox St",
    "iso:country":"US",
    "sg:address":"1207 S Cox St",
    "sg:city":"Asheboro",
    "sg:classifiers":[
        {
            "category":"Health Services",
            "subcategory":"Health Practitioner",
            "type":"Services"
        }
    ],
    "sg:phone":"+1 336 629 9919",
    "sg:postcode":"27203",
    "sg:province":"NC",
    "sg:tags":[
        "nurse",
        "registry"
    ],
    "wof:name":"Bayada Nurses",
    "wof:placetype":"venue"
},
  "geometry": {"coordinates":[-79.811176,35.690562],"type":"Point"}
}