{
  "type": "Feature",
  "properties": {
    "addr:full":"466 New Leicester Hwy Asheville NC 28806",
    "addr:housenumber":"466",
    "addr:postcode":"28806",
    "addr:street":"New Leicester Hwy",
    "iso:country":"US",
    "sg:address":"466 New Leicester Hwy",
    "sg:city":"Asheville",
    "sg:classifiers":[
        {
            "category":"Shopping",
            "subcategory":"Used Merchandise",
            "type":"Retail Goods"
        }
    ],
    "sg:phone":"+1 828 232 6722",
    "sg:postcode":"28806",
    "sg:province":"NC",
    "sg:tags":[
        "flea",
        "market"
    ],
    "wof:name":"Flea Market",
    "wof:placetype":"venue"
},
  "geometry": {"coordinates":[-82.62738299999999,35.609249],"type":"Point"}
}