{
  "type": "Feature",
  "properties": {
    "addr:full":"2471 23rd Avenue Pl NE Hickory NC 28601",
    "addr:housenumber":"2471",
    "addr:postcode":"28601",
    "addr:street":"23Rd Avenue Pl Ne",
    "iso:country":"US",
    "sg:address":"2471 23rd Avenue Pl NE",
    "sg:city":"Hickory",
    "sg:classifiers":[
        {
            "category":"Building & Trades",
            "subcategory":"Electrical",
            "type":"Services"
        }
    ],
    "sg:phone":"+1 828 256 8255",
    "sg:postcode":"28601",
    "sg:province":"NC",
    "sg:tags":[
        "electrical",
        "contractor"
    ],
    "wof:name":"Precision Electric Of Hickory",
    "wof:placetype":"venue"
},
  "geometry": {"coordinates":[-81.286839,35.758808],"type":"Point"}
}