{
  "type": "Feature",
  "properties": {
    "iso:country":"US",
    "sg:address":"3125 Gresham Lake Rd",
    "sg:city":"Raleigh",
    "sg:classifiers":[
        {
            "category":"Retail",
            "subcategory":"Repair Shop",
            "type":"Services"
        }
    ],
    "sg:phone":"+1   ",
    "sg:postcode":"27615",
    "sg:province":"NC",
    "sg:tags":[
        "refrigeration"
    ],
    "wof:name":"Air Filter Service Inc",
    "wof:placetype":"venue"
},
  "geometry": {"coordinates":[-78.582712,35.884842],"type":"Point"}
}