{
  "type": "Feature",
  "properties": {
    "iso:country":"US",
    "sg:address":"400 Bayberry Dr",
    "sg:city":"Chapel Hill",
    "sg:classifiers":[
        {
            "category":"Arts & Performance",
            "subcategory":"Theater",
            "type":"Entertainment"
        }
    ],
    "sg:phone":"+1   ",
    "sg:postcode":"27517",
    "sg:province":"NC",
    "sg:tags":[
        "theatrical"
    ],
    "wof:name":"Perihelion Productions",
    "wof:placetype":"venue"
},
  "geometry": {"coordinates":[-79.047605,35.886904],"type":"Point"}
}