{
  "type": "Feature",
  "properties": {
    "addr:full":"1910 N Church St Greensboro NC 27405",
    "addr:housenumber":"1910",
    "addr:postcode":"27405",
    "addr:street":"N Church St",
    "iso:country":"US",
    "sg:address":"1910 N Church St",
    "sg:city":"Greensboro",
    "sg:classifiers":[
        {
            "category":"Health Services",
            "subcategory":"Health Practitioner",
            "type":"Services"
        }
    ],
    "sg:phone":"+1 336 274 7480",
    "sg:postcode":"27405",
    "sg:province":"NC",
    "sg:tags":[
        "therapist",
        "physical"
    ],
    "wof:name":"Physical Therapy & Sports",
    "wof:placetype":"venue"
},
  "geometry": {"coordinates":[-79.78170299999999,36.099107],"type":"Point"}
}