{
  "type": "Feature",
  "properties": {
    "iso:country":"US",
    "sg:address":"1317 University Dr",
    "sg:city":"Durham",
    "sg:classifiers":[
        {
            "category":"Autos & Motor Vehicles",
            "subcategory":"Fuel & Gas Station",
            "type":"Retail Goods"
        }
    ],
    "sg:phone":"+1 919 489 4041",
    "sg:postcode":"27707",
    "sg:province":"NC",
    "sg:tags":[
        "oil"
    ],
    "wof:name":"Forest Hills Svc Ctr",
    "wof:placetype":"venue"
},
  "geometry": {"coordinates":[-78.91116599999999,35.984656],"type":"Point"}
}