{
  "type": "Feature",
  "properties": {
    "iso:country":"US",
    "sg:address":"2920 Oak Ridge Rd",
    "sg:city":"Oak Ridge",
    "sg:classifiers":[
        {
            "category":"Organizations",
            "subcategory":"Religious Organization",
            "type":"Services"
        }
    ],
    "sg:phone":"+1 336 643 5166",
    "sg:postcode":"27310",
    "sg:province":"NC",
    "sg:tags":[
        "church"
    ],
    "wof:name":"Moravia Moravian Church",
    "wof:placetype":"venue"
},
  "geometry": {"coordinates":[-79.958713,36.195528],"type":"Point"}
}