{
  "type": "Feature",
  "properties": {
    "iso:country":"US",
    "sg:address":"329 Rolling Hill Rd",
    "sg:city":"Mooresville",
    "sg:classifiers":[
        {
            "category":"Autos & Motor Vehicles",
            "subcategory":"Automobile Sales",
            "type":"Retail Goods"
        }
    ],
    "sg:phone":"+1 704 662 9570",
    "sg:postcode":"28117",
    "sg:province":"NC",
    "sg:tags":[
        "performance",
        "race",
        "dealer"
    ],
    "wof:name":"Race City Promotions",
    "wof:placetype":"venue"
},
  "geometry": {"coordinates":[-80.86086299999999,35.581646],"type":"Point"}
}