{
  "type": "Feature",
  "properties": {
    "addr:full":"906 Deer Spring Ln Wilmington NC 28409",
    "addr:housenumber":"906",
    "addr:postcode":"28409",
    "addr:street":"Deer Spring Ln",
    "iso:country":"US",
    "sg:address":"906 Deer Spring Ln",
    "sg:city":"Wilmington",
    "sg:classifiers":[
        {
            "category":"Insurance",
            "subcategory":"Insurance Agent",
            "type":"Services"
        }
    ],
    "sg:phone":"+1 910 798 6118",
    "sg:postcode":"28409",
    "sg:province":"NC",
    "wof:name":"Ballard Insurance Service",
    "wof:placetype":"venue"
},
  "geometry": {"coordinates":[-77.87358399999999,34.170992],"type":"Point"}
}