{
  "type": "Feature",
  "properties": {
    "addr:full":"136 Hollywood St Forest City NC 28043",
    "addr:housenumber":"136",
    "addr:postcode":"28043",
    "addr:street":"Hollywood St",
    "iso:country":"US",
    "sg:address":"136 Hollywood St",
    "sg:city":"Forest City",
    "sg:classifiers":[
        {
            "category":"Retail",
            "subcategory":"Laundry & Dry Cleaning",
            "type":"Services"
        }
    ],
    "sg:phone":"+1   ",
    "sg:postcode":"28043",
    "sg:province":"NC",
    "wof:name":"Quality Clean Carpet Care",
    "wof:placetype":"venue"
},
  "geometry": {"coordinates":[-81.84726499999999,35.291945],"type":"Point"}
}