{
  "type": "Feature",
  "properties": {
    "iso:country":"US",
    "sg:address":"5740 Ivanhoe Ct",
    "sg:city":"Fayetteville",
    "sg:classifiers":[
        {
            "category":"Building & Trades",
            "subcategory":"Construction",
            "type":"Services"
        }
    ],
    "sg:phone":"+1 910 864 4385",
    "sg:postcode":"28314",
    "sg:province":"NC",
    "sg:tags":[
        "contractor"
    ],
    "wof:name":"Weber Building Co",
    "wof:placetype":"venue"
},
  "geometry": {"coordinates":[-78.982012,35.075311],"type":"Point"}
}