{
  "type": "Feature",
  "properties": {
    "iso:country":"US",
    "sg:address":"1945 Eastchester Dr",
    "sg:city":"High Point",
    "sg:classifiers":[
        {
            "category":"Professional",
            "subcategory":"Business Services",
            "type":"Services"
        }
    ],
    "sg:phone":"+1   ",
    "sg:postcode":"27265",
    "sg:province":"NC",
    "wof:name":"Spruce Enterprises",
    "wof:placetype":"venue"
},
  "geometry": {"coordinates":[-79.979507,36.015576],"type":"Point"}
}