{
  "type": "Feature",
  "properties": {
    "addr:full":"2105 Belgrade-Swansboro Rd Maysville NC 28555",
    "addr:housenumber":"2105",
    "addr:postcode":"28555",
    "addr:street":"Belgrade-Swansboro Rd",
    "iso:country":"US",
    "sg:address":"2105 Belgrade-Swansboro Rd",
    "sg:city":"Maysville",
    "sg:classifiers":[
        {
            "category":"Building & Trades",
            "subcategory":"Construction",
            "type":"Services"
        }
    ],
    "sg:phone":"+1 910 743 0998",
    "sg:postcode":"28555",
    "sg:province":"NC",
    "sg:tags":[
        "house"
    ],
    "wof:name":"Simpkins Jl Home Improvements",
    "wof:placetype":"venue"
},
  "geometry": {"coordinates":[-77.228649,34.825357],"type":"Point"}
}