{
  "type": "Feature",
  "properties": {
    "addr:full":"8910 State Hwy 14 Eden NC 27288",
    "addr:housenumber":"8910",
    "addr:postcode":"27288",
    "addr:street":"State Hwy 14",
    "iso:country":"US",
    "sg:address":"8910 State Hwy 14",
    "sg:city":"Eden",
    "sg:classifiers":[
        {
            "category":"Personal",
            "subcategory":"Tanning Parlor",
            "type":"Services"
        }
    ],
    "sg:phone":"+1 336 623 7707",
    "sg:postcode":"27288",
    "sg:province":"NC",
    "sg:tags":[
        "salon"
    ],
    "wof:name":"Sun Tan Studio",
    "wof:placetype":"venue"
},
  "geometry": {"coordinates":[-79.79991,36.533535],"type":"Point"}
}