{
  "type": "Feature",
  "properties": {
    "addr:full":"700 Warton Ct Gastonia NC 28056",
    "addr:housenumber":"700",
    "addr:postcode":"28056",
    "addr:street":"Warton Ct",
    "iso:country":"US",
    "sg:address":"700 Warton Ct",
    "sg:city":"Gastonia",
    "sg:classifiers":[
        {
            "category":"Professional",
            "subcategory":"Management & Consulting",
            "type":"Services"
        }
    ],
    "sg:phone":"+1   ",
    "sg:postcode":"28056",
    "sg:province":"NC",
    "wof:name":"Cruises For Causes",
    "wof:placetype":"venue"
},
  "geometry": {"coordinates":[-81.14065600000001,35.167904],"type":"Point"}
}