{
  "type": "Feature",
  "properties": {
    "iso:country":"US",
    "sg:address":"2779 Alamance Rd",
    "sg:city":"Burlington",
    "sg:classifiers":[
        {
            "category":"Banks & Credit Unions",
            "subcategory":"Financial Services",
            "type":"Services"
        }
    ],
    "sg:phone":"+1 336 222 6857",
    "sg:postcode":"27215",
    "sg:province":"NC",
    "sg:tags":[
        "company",
        "holding"
    ],
    "wof:name":"Jorgan Holdings Inc",
    "wof:placetype":"venue"
},
  "geometry": {"coordinates":[-79.46993999999999,36.063488],"type":"Point"}
}