{
  "type": "Feature",
  "properties": {
    "addr:full":"921 Lejeune Blvd Jacksonville NC 28540",
    "addr:housenumber":"921",
    "addr:postcode":"28540",
    "addr:street":"Lejeune Blvd",
    "iso:country":"US",
    "sg:address":"921 Lejeune Blvd",
    "sg:city":"Jacksonville",
    "sg:classifiers":[
        {
            "category":"Building & Trades",
            "subcategory":"Construction",
            "type":"Services"
        }
    ],
    "sg:phone":"+1 910 938 8825",
    "sg:postcode":"28540",
    "sg:province":"NC",
    "sg:tags":[
        "contractor"
    ],
    "wof:name":"East Coast Contracting Svc Inc",
    "wof:placetype":"venue"
},
  "geometry": {"coordinates":[-77.416965,34.748713],"type":"Point"}
}