{
  "type": "Feature",
  "properties": {
    "iso:country":"US",
    "sg:address":"3475 Myer Lee Dr",
    "sg:city":"Winston Salem",
    "sg:classifiers":[
        {
            "category":"Professional",
            "subcategory":"Management & Consulting",
            "type":"Services"
        }
    ],
    "sg:phone":"+1 336 777 0007",
    "sg:postcode":"27101",
    "sg:province":"NC",
    "sg:tags":[
        "marketing",
        "program"
    ],
    "sg:website":"www.tsii.net",
    "wof:name":"TSI",
    "wof:placetype":"venue"
},
  "geometry": {"coordinates":[-80.168955,36.111176],"type":"Point"}
}