{
  "type": "Feature",
  "properties": {
    "addr:full":"404 Rustic Ridge Rd Cary NC 27511",
    "addr:housenumber":"404",
    "addr:postcode":"27511",
    "addr:street":"Rustic Ridge Rd",
    "iso:country":"US",
    "sg:address":"404 Rustic Ridge Rd",
    "sg:city":"Cary",
    "sg:classifiers":[
        {
            "category":"Museum",
            "type":"Entertainment"
        }
    ],
    "sg:phone":"+1   ",
    "sg:postcode":"27511",
    "sg:province":"NC",
    "sg:tags":[
        "gallery"
    ],
    "wof:name":"Postmark Museum",
    "wof:placetype":"venue"
},
  "geometry": {"coordinates":[-78.79093399999999,35.773855],"type":"Point"}
}