{
  "type": "Feature",
  "properties": {
    "iso:country":"US",
    "sg:address":"103 W Staton St",
    "sg:city":"Robersonville",
    "sg:classifiers":[
        {
            "category":"Freight",
            "type":"Transportation"
        }
    ],
    "sg:phone":"+1 252 236 7251",
    "sg:postcode":"27871",
    "sg:province":"NC",
    "sg:tags":[
        "cargo"
    ],
    "wof:name":"Grand Transport",
    "wof:placetype":"venue"
},
  "geometry": {"coordinates":[-77.244698,35.833592],"type":"Point"}
}