{
  "type": "Feature",
  "properties": {
    "iso:country":"US",
    "sg:address":"6820 Crescent Moon Ct",
    "sg:city":"Raleigh",
    "sg:classifiers":[
        {
            "category":"Professional",
            "type":"Services"
        }
    ],
    "sg:phone":"+1 919 851 7224",
    "sg:postcode":"27606",
    "sg:province":"NC",
    "wof:name":"Woodward Edition",
    "wof:placetype":"venue"
},
  "geometry": {"coordinates":[-78.74012399999999,35.77942],"type":"Point"}
}