{
  "type": "Feature",
  "properties": {
    "addr:full":"2775 Sea Aire Dr SW Supply NC 28462",
    "addr:housenumber":"2775",
    "addr:postcode":"28462",
    "addr:street":"Sea Aire Dr Sw",
    "iso:country":"US",
    "sg:address":"2775 Sea Aire Dr SW",
    "sg:city":"Supply",
    "sg:classifiers":[
        {
            "category":"Retail",
            "subcategory":"Laundry & Dry Cleaning",
            "type":"Services"
        }
    ],
    "sg:phone":"+1 910 842 9330",
    "sg:postcode":"28462",
    "sg:province":"NC",
    "sg:tags":[
        "cleaners",
        "rug",
        "carpet"
    ],
    "wof:name":"Pro-Clean Carpet Cleaning",
    "wof:placetype":"venue"
},
  "geometry": {"coordinates":[-78.291709,33.922668],"type":"Point"}
}