{
  "type": "Feature",
  "properties": {
    "iso:country":"US",
    "sg:address":"1410 Piney Green Rd",
    "sg:city":"Jacksonville",
    "sg:classifiers":[
        {
            "category":"Professional",
            "subcategory":"Business Services",
            "type":"Services"
        }
    ],
    "sg:phone":"+1 910 219 9781",
    "sg:postcode":"28546",
    "sg:province":"NC",
    "sg:tags":[
        "inspection"
    ],
    "wof:name":"Village Inspections",
    "wof:placetype":"venue"
},
  "geometry": {"coordinates":[-77.336394,34.759043],"type":"Point"}
}