{
  "type": "Feature",
  "properties": {
    "iso:country":"US",
    "sg:address":"4513 US Hwy 301",
    "sg:city":"Wilson",
    "sg:classifiers":[
        {
            "category":"Wholesale",
            "subcategory":"Machinery & Supplies",
            "type":"Manufacturing & Wholesale Goods"
        }
    ],
    "sg:phone":"+1 252 291 7050",
    "sg:postcode":"27893",
    "sg:province":"NC",
    "sg:tags":[
        "farm",
        "equipment"
    ],
    "wof:name":"Lely Corp",
    "wof:placetype":"venue"
},
  "geometry": {"coordinates":[-77.965884,35.664457],"type":"Point"}
}