{
  "type": "Feature",
  "properties": {
    "addr:full":"412 E Williams St Ste B Apex NC 27502",
    "addr:housenumber":"412",
    "addr:postcode":"27502",
    "addr:street":"E Williams St Ste B",
    "iso:country":"US",
    "sg:address":"412 E Williams St Ste B",
    "sg:city":"Apex",
    "sg:classifiers":[
        {
            "category":"Shopping",
            "subcategory":"Mobile Phones",
            "type":"Retail Goods"
        }
    ],
    "sg:phone":"+1 919 367 0497",
    "sg:postcode":"27502",
    "sg:province":"NC",
    "sg:website":"www.sprint.com",
    "wof:name":"Activate Cellular Inc",
    "wof:placetype":"venue"
},
  "geometry": {"coordinates":[-78.849699,35.72549],"type":"Point"}
}