{
  "type": "Feature",
  "properties": {
    "addr:full":"2835 Horse Pen Creek Rd Greensboro NC 27410",
    "addr:housenumber":"2835",
    "addr:postcode":"27410",
    "addr:street":"Horse Pen Creek Rd",
    "iso:country":"US",
    "sg:address":"2835 Horse Pen Creek Rd",
    "sg:city":"Greensboro",
    "sg:classifiers":[
        {
            "category":"Health Services",
            "subcategory":"Doctor",
            "type":"Services"
        }
    ],
    "sg:phone":"+1 336 605 0190",
    "sg:postcode":"27410",
    "sg:province":"NC",
    "sg:tags":[
        "physician",
        "surgeon"
    ],
    "wof:name":"Northwest Pediatrics",
    "wof:placetype":"venue"
},
  "geometry": {"coordinates":[-79.883549,36.123788],"type":"Point"}
}