{
  "type": "Feature",
  "properties": {
    "iso:country":"US",
    "sg:address":"113 S Griffin St",
    "sg:city":"Elizabeth City",
    "sg:classifiers":[
        {
            "category":"Building & Trades",
            "subcategory":"Plumbing",
            "type":"Services"
        }
    ],
    "sg:phone":"+1 252 331 2226",
    "sg:postcode":"27909",
    "sg:province":"NC",
    "sg:tags":[
        "contractor"
    ],
    "wof:name":"A W Rayfield Mechanical",
    "wof:placetype":"venue"
},
  "geometry": {"coordinates":[-76.233265,36.301759],"type":"Point"}
}