{
  "type": "Feature",
  "properties": {
    "iso:country":"US",
    "sg:address":"2850 Tynecastle Hwy",
    "sg:city":"Banner Elk",
    "sg:classifiers":[
        {
            "category":"Insurance",
            "subcategory":"Insurance Agent",
            "type":"Services"
        }
    ],
    "sg:phone":"+1 828 898 8350",
    "sg:postcode":"28604",
    "sg:province":"NC",
    "wof:name":"Tate's Insurance & Financial",
    "wof:placetype":"venue"
},
  "geometry": {"coordinates":[-81.861114,36.146802],"type":"Point"}
}