{
  "type": "Feature",
  "properties": {
    "addr:full":"5116 Butler Rd Liberty NC 27298",
    "addr:housenumber":"5116",
    "addr:postcode":"27298",
    "addr:street":"Butler Rd",
    "iso:country":"US",
    "sg:address":"5116 Butler Rd",
    "sg:city":"Liberty",
    "sg:classifiers":[
        {
            "category":"Real Estate",
            "subcategory":"Real Estate Operator",
            "type":"Services"
        }
    ],
    "sg:phone":"+1 336 622 3314",
    "sg:postcode":"27298",
    "sg:province":"NC",
    "sg:tags":[
        "mobile",
        "home",
        "site"
    ],
    "wof:name":"Ridge Lake Estates Mhp",
    "wof:placetype":"venue"
},
  "geometry": {"coordinates":[-79.545143,35.881897],"type":"Point"}
}