{
  "type": "Feature",
  "properties": {
    "iso:country":"US",
    "sg:address":"2515 Tuckaseegee Rd",
    "sg:city":"Charlotte",
    "sg:classifiers":[
        {
            "category":"Professional",
            "subcategory":"Accounting & Tax Preparation",
            "type":"Services"
        }
    ],
    "sg:phone":"+1 704 394 3156",
    "sg:postcode":"28208",
    "sg:province":"NC",
    "sg:tags":[
        "accountant"
    ],
    "wof:name":"T Allen Burris",
    "wof:placetype":"venue"
},
  "geometry": {"coordinates":[-80.875342,35.237995],"type":"Point"}
}