{
  "type": "Feature",
  "properties": {
    "iso:country":"US",
    "sg:address":"1022 Chancellors Ridge Dr",
    "sg:city":"Durham",
    "sg:classifiers":[
        {
            "category":"Building & Trades",
            "subcategory":"Construction",
            "type":"Services"
        }
    ],
    "sg:phone":"+1 919 484 4112",
    "sg:postcode":"27713",
    "sg:province":"NC",
    "sg:tags":[
        "general",
        "contractor"
    ],
    "wof:name":"Sun Star Homes",
    "wof:placetype":"venue"
},
  "geometry": {"coordinates":[-78.94729,35.887699],"type":"Point"}
}