{
  "type": "Feature",
  "properties": {
    "addr:full":"660 Cross Creek Mall Fayetteville NC 28303",
    "addr:housenumber":"660",
    "addr:postcode":"28303",
    "addr:street":"Cross Creek Mall",
    "iso:country":"US",
    "sg:address":"660 Cross Creek Mall",
    "sg:city":"Fayetteville",
    "sg:classifiers":[
        {
            "category":"Autos & Motor Vehicles",
            "subcategory":"Auto Supplies",
            "type":"Retail Goods"
        },
        {
            "category":"Retail",
            "subcategory":"Auto Repair",
            "type":"Services"
        }
    ],
    "sg:phone":"+1 910 864 4106",
    "sg:postcode":"28303",
    "sg:province":"NC",
    "sg:tags":[
        "lube",
        "oil",
        "tire"
    ],
    "sg:website":"http://www.firestonecompleteautocare.com/?s_kwcid=IYP_NTL",
    "wof:name":"Firestone Complete Auto Care Store",
    "wof:placetype":"venue"
},
  "geometry": {"coordinates":[-78.960413,35.069902],"type":"Point"}
}