{
  "type": "Feature",
  "properties": {
    "iso:country":"US",
    "sg:address":"612 S 17th St",
    "sg:city":"Wilmington",
    "sg:classifiers":[
        {
            "category":"Insurance",
            "subcategory":"Insurance Agent",
            "type":"Services"
        }
    ],
    "sg:phone":"+1 910 763 8577",
    "sg:postcode":"28401",
    "sg:province":"NC",
    "wof:name":"ILA Welfare Vacation Plan",
    "wof:placetype":"venue"
},
  "geometry": {"coordinates":[-77.926665,34.228389],"type":"Point"}
}