{
  "type": "Feature",
  "properties": {
    "addr:full":"1715 West Blvd Charlotte NC 28208",
    "addr:housenumber":"1715",
    "addr:postcode":"28208",
    "addr:street":"West Blvd",
    "iso:country":"US",
    "sg:address":"1715 West Blvd",
    "sg:city":"Charlotte",
    "sg:classifiers":[
        {
            "category":"Social Services",
            "subcategory":"Child Care",
            "type":"Services"
        }
    ],
    "sg:phone":"+1 704 333 3017",
    "sg:postcode":"28208",
    "sg:province":"NC",
    "wof:name":"Renettas Child Care",
    "wof:placetype":"venue"
},
  "geometry": {"coordinates":[-80.88692,35.215038],"type":"Point"}
}