{
  "type": "Feature",
  "properties": {
    "addr:full":"124 Riding Ridge Rd Fuquay Varina NC 27526",
    "addr:housenumber":"124",
    "addr:postcode":"27526",
    "addr:street":"Riding Ridge Rd",
    "iso:country":"US",
    "sg:address":"124 Riding Ridge Rd",
    "sg:city":"Fuquay Varina",
    "sg:classifiers":[
        {
            "category":"Professional",
            "subcategory":"Management & Consulting",
            "type":"Services"
        }
    ],
    "sg:phone":"+1   ",
    "sg:postcode":"27526",
    "sg:province":"NC",
    "sg:tags":[
        "public",
        "relations"
    ],
    "wof:name":"Kempin Communications Inc",
    "wof:placetype":"venue"
},
  "geometry": {"coordinates":[-78.80144,35.612098],"type":"Point"}
}