{
  "type": "Feature",
  "properties": {
    "iso:country":"US",
    "sg:address":"881 Airport Rd",
    "sg:city":"Chapel Hill",
    "sg:classifiers":[
        {
            "category":"Real Estate",
            "subcategory":"Real Estate Operator",
            "type":"Services"
        }
    ],
    "sg:phone":"+1 919 929 3015",
    "sg:postcode":"27514",
    "sg:province":"NC",
    "sg:tags":[
        "apartment"
    ],
    "wof:name":"Sharon Heights Garden Apts",
    "wof:placetype":"venue"
},
  "geometry": {"coordinates":[-79.054605,35.92907],"type":"Point"}
}