{
  "type": "Feature",
  "properties": {
    "addr:full":"100 N Greensboro St Chapel Hill NC 27514",
    "addr:housenumber":"100",
    "addr:postcode":"27514",
    "addr:street":"N Greensboro St",
    "iso:country":"US",
    "sg:address":"100 N Greensboro St",
    "sg:city":"Chapel Hill",
    "sg:classifiers":[
        {
            "category":"Shopping",
            "subcategory":"Pharmacy",
            "type":"Retail Goods"
        }
    ],
    "sg:phone":"+1 919 304 5436",
    "sg:postcode":"27514",
    "sg:province":"NC",
    "sg:tags":[
        "drugstore"
    ],
    "sg:website":"www.cvs.com/",
    "wof:name":"Cvs Pharmacy",
    "wof:placetype":"venue"
},
  "geometry": {"coordinates":[-79.046204,35.9352],"type":"Point"}
}