{
  "type": "Feature",
  "properties": {
    "addr:full":"2418 N Main St High Point NC 27262",
    "addr:housenumber":"2418",
    "addr:postcode":"27262",
    "addr:street":"N Main St",
    "iso:country":"US",
    "sg:address":"2418 N Main St",
    "sg:city":"High Point",
    "sg:classifiers":[
        {
            "category":"Recreation",
            "type":"Entertainment"
        }
    ],
    "sg:phone":"+1 336 869 4273",
    "sg:postcode":"27262",
    "sg:province":"NC",
    "sg:tags":[
        "course",
        "golf"
    ],
    "wof:name":"Putt Putt Golf & Games",
    "wof:placetype":"venue"
},
  "geometry": {"coordinates":[-80.027186,35.989374],"type":"Point"}
}