{
  "type": "Feature",
  "properties": {
    "addr:full":"1171 Charlie Thompson Rd Vilas NC 28692",
    "addr:housenumber":"1171",
    "addr:postcode":"28692",
    "addr:street":"Charlie Thompson Rd",
    "iso:country":"US",
    "sg:address":"1171 Charlie Thompson Rd",
    "sg:city":"Vilas",
    "sg:classifiers":[
        {
            "category":"Travel",
            "subcategory":"Campground",
            "type":"Entertainment"
        }
    ],
    "sg:phone":"+1   ",
    "sg:postcode":"28692",
    "sg:province":"NC",
    "sg:tags":[
        "trailer"
    ],
    "wof:name":"Vanderpool Campgrounds",
    "wof:placetype":"venue"
},
  "geometry": {"coordinates":[-81.758893,36.263735],"type":"Point"}
}