{
  "type": "Feature",
  "properties": {
    "iso:country":"US",
    "sg:address":"213 Bickett Blvd",
    "sg:city":"Raleigh",
    "sg:classifiers":[
        {
            "category":"Building & Trades",
            "subcategory":"Construction",
            "type":"Services"
        }
    ],
    "sg:phone":"+1 919 829 3949",
    "sg:postcode":"27608",
    "sg:province":"NC",
    "sg:tags":[
        "house",
        "improvement",
        "home"
    ],
    "wof:name":"Redwine Renovation",
    "wof:placetype":"venue"
},
  "geometry": {"coordinates":[-78.63889399999999,35.800887],"type":"Point"}
}