{
  "type": "Feature",
  "properties": {
    "addr:full":"419 Owens Rd Lexington NC 27292",
    "addr:housenumber":"419",
    "addr:postcode":"27292",
    "addr:street":"Owens Rd",
    "iso:country":"US",
    "sg:address":"419 Owens Rd",
    "sg:city":"Lexington",
    "sg:classifiers":[
        {
            "category":"Professional",
            "type":"Services"
        }
    ],
    "sg:phone":"+1 336 243 7459",
    "sg:postcode":"27292",
    "sg:province":"NC",
    "wof:name":"Jormac LLC",
    "wof:placetype":"venue"
},
  "geometry": {"coordinates":[-80.268225,35.765218],"type":"Point"}
}