{
  "type": "Feature",
  "properties": {
    "iso:country":"US",
    "sg:address":"4171 Kivett Dr",
    "sg:city":"Jamestown",
    "sg:classifiers":[
        {
            "category":"Building & Trades",
            "subcategory":"Construction",
            "type":"Services"
        }
    ],
    "sg:phone":"+1 336 885 0898",
    "sg:postcode":"27282",
    "sg:province":"NC",
    "sg:tags":[
        "dry wall",
        "contractor"
    ],
    "wof:name":"Johnson Lawrence Dry Wall",
    "wof:placetype":"venue"
},
  "geometry": {"coordinates":[-79.92102,35.954884],"type":"Point"}
}