{
  "type": "Feature",
  "properties": {
    "addr:full":"8419 Lancaster Hwy Waxhaw NC 28173",
    "addr:housenumber":"8419",
    "addr:postcode":"28173",
    "addr:street":"Lancaster Hwy",
    "iso:country":"US",
    "sg:address":"8419 Lancaster Hwy",
    "sg:city":"Waxhaw",
    "sg:classifiers":[
        {
            "category":"Arts & Performance",
            "subcategory":"Theater",
            "type":"Entertainment"
        }
    ],
    "sg:phone":"+1   ",
    "sg:postcode":"28173",
    "sg:province":"NC",
    "sg:tags":[
        "group"
    ],
    "wof:name":"Petting Zoo",
    "wof:placetype":"venue"
},
  "geometry": {"coordinates":[-80.69622200000001,34.864544],"type":"Point"}
}