{
  "type": "Feature",
  "properties": {
    "iso:country":"US",
    "sg:address":"125 Brassie Dr",
    "sg:city":"Grifton",
    "sg:classifiers":[
        {
            "category":"Building & Trades",
            "subcategory":"Construction",
            "type":"Services"
        }
    ],
    "sg:phone":"+1 252 524 5707",
    "sg:postcode":"28530",
    "sg:province":"NC",
    "sg:tags":[
        "house"
    ],
    "wof:name":"Grays Home Improvement",
    "wof:placetype":"venue"
},
  "geometry": {"coordinates":[-77.41530299999999,35.384672],"type":"Point"}
}