{
  "type": "Feature",
  "properties": {
    "iso:country":"US",
    "sg:address":"1309 N Road St",
    "sg:city":"Elizabeth City",
    "sg:classifiers":[
        {
            "category":"Retail",
            "subcategory":"Laundry & Dry Cleaning",
            "type":"Services"
        }
    ],
    "sg:phone":"+1 252 333 1110",
    "sg:postcode":"27909",
    "sg:province":"NC",
    "wof:name":"Magic Suds Car Wash & Laundry",
    "wof:placetype":"venue"
},
  "geometry": {"coordinates":[-76.227014,36.331264],"type":"Point"}
}