{
  "type": "Feature",
  "properties": {
    "iso:country":"US",
    "sg:address":"831 Stanford Church Rd",
    "sg:city":"Siloam",
    "sg:classifiers":[
        {
            "category":"Farming",
            "subcategory":"Farm",
            "type":"Manufacturing & Wholesale Goods"
        }
    ],
    "sg:phone":"+1 336 374 2441",
    "sg:postcode":"27047",
    "sg:province":"NC",
    "sg:tags":[
        "crop",
        "general"
    ],
    "wof:name":"Whitaker Farm",
    "wof:placetype":"venue"
},
  "geometry": {"coordinates":[-80.569878,36.33616],"type":"Point"}
}