{
  "type": "Feature",
  "properties": {
    "iso:country":"US",
    "sg:address":"110 Old St",
    "sg:city":"Fayetteville",
    "sg:classifiers":[
        {
            "category":"Organizations",
            "subcategory":"Religious Organization",
            "type":"Services"
        }
    ],
    "sg:phone":"+1 910 321 0222",
    "sg:postcode":"28301",
    "sg:province":"NC",
    "sg:tags":[
        "church"
    ],
    "wof:name":"Living Word Fellowship Church",
    "wof:placetype":"venue"
},
  "geometry": {"coordinates":[-78.87936999999999,35.053924],"type":"Point"}
}