{
  "type": "Feature",
  "properties": {
    "addr:full":"104 N Center St La Grange NC 28551",
    "addr:housenumber":"104",
    "addr:postcode":"28551",
    "addr:street":"N Center St",
    "iso:country":"US",
    "sg:address":"104 N Center St",
    "sg:city":"La Grange",
    "sg:classifiers":[
        {
            "category":"Building & Trades",
            "subcategory":"Landscaping Services",
            "type":"Services"
        }
    ],
    "sg:phone":"+1 252 566 3390",
    "sg:postcode":"28551",
    "sg:province":"NC",
    "sg:tags":[
        "lawn",
        "maintenance",
        "grounds"
    ],
    "sg:website":"www.spring-green.com",
    "wof:name":"Spring-Green Lawn Care",
    "wof:placetype":"venue"
},
  "geometry": {"coordinates":[-77.789917,35.309074],"type":"Point"}
}