{
  "type": "Feature",
  "properties": {
    "addr:full":"7 Glenwood Ave Raleigh NC 27603",
    "addr:housenumber":"7",
    "addr:postcode":"27603",
    "addr:street":"Glenwood Ave",
    "iso:country":"US",
    "sg:address":"7 Glenwood Ave",
    "sg:city":"Raleigh",
    "sg:classifiers":[
        {
            "category":"Professional",
            "subcategory":"Lawyer & Legal Services",
            "type":"Services"
        }
    ],
    "sg:phone":"+1   ",
    "sg:postcode":"27603",
    "sg:province":"NC",
    "wof:name":"Carolina Legal Assistance",
    "wof:placetype":"venue"
},
  "geometry": {"coordinates":[-78.64759100000001,35.781847],"type":"Point"}
}