{
  "type": "Feature",
  "properties": {
    "addr:full":"7331 Sherwood Forest Dr Charlotte NC 28226",
    "addr:housenumber":"7331",
    "addr:postcode":"28226",
    "addr:street":"Sherwood Forest Dr",
    "iso:country":"US",
    "sg:address":"7331 Sherwood Forest Dr",
    "sg:city":"Charlotte",
    "sg:classifiers":[
        {
            "category":"Shopping",
            "subcategory":"Crafts & Fabrics",
            "type":"Retail Goods"
        }
    ],
    "sg:phone":"+1 704 752 9224",
    "sg:postcode":"28226",
    "sg:province":"NC",
    "sg:tags":[
        "sewing"
    ],
    "wof:name":"Sherwood Fabrics",
    "wof:placetype":"venue"
},
  "geometry": {"coordinates":[-80.807259,35.115263],"type":"Point"}
}