{
  "type": "Feature",
  "properties": {
    "iso:country":"US",
    "sg:address":"103 C St",
    "sg:city":"Statesville",
    "sg:classifiers":[
        {
            "category":"Freight",
            "type":"Transportation"
        }
    ],
    "sg:phone":"+1 704 872 3123",
    "sg:postcode":"28677",
    "sg:province":"NC",
    "sg:tags":[
        "operator",
        "local",
        "trucking"
    ],
    "wof:name":"Chapman Group of The Carolinas",
    "wof:placetype":"venue"
},
  "geometry": {"coordinates":[-80.934669,35.793083],"type":"Point"}
}