{
  "type": "Feature",
  "properties": {
    "addr:full":"100 E Murphy St Madison NC 27025",
    "addr:housenumber":"100",
    "addr:postcode":"27025",
    "addr:street":"E Murphy St",
    "iso:country":"US",
    "sg:address":"100 E Murphy St",
    "sg:city":"Madison",
    "sg:classifiers":[
        {
            "category":"Wholesale",
            "subcategory":"Tobacco Products",
            "type":"Manufacturing & Wholesale Goods"
        }
    ],
    "sg:phone":"+1 336 548 1973",
    "sg:postcode":"27025",
    "sg:province":"NC",
    "sg:tags":[
        "cigarette",
        "cigar",
        "dealer"
    ],
    "wof:name":"Syd's Tobacco Co",
    "wof:placetype":"venue"
},
  "geometry": {"coordinates":[-79.95899199999999,36.387536],"type":"Point"}
}