{
  "type": "Feature",
  "properties": {
    "addr:full":"5941 Hampton Ridge Rd Raleigh NC 27603",
    "addr:housenumber":"5941",
    "addr:postcode":"27603",
    "addr:street":"Hampton Ridge Rd",
    "iso:country":"US",
    "sg:address":"5941 Hampton Ridge Rd",
    "sg:city":"Raleigh",
    "sg:classifiers":[
        {
            "category":"Building & Trades",
            "subcategory":"Plumbing",
            "type":"Services"
        }
    ],
    "sg:phone":"+1 919 772 3202",
    "sg:postcode":"27603",
    "sg:province":"NC",
    "sg:tags":[
        "contractor"
    ],
    "wof:name":"Angelelli Plumbing",
    "wof:placetype":"venue"
},
  "geometry": {"coordinates":[-78.657251,35.614588],"type":"Point"}
}