{
  "type": "Feature",
  "properties": {
    "iso:country":"US",
    "sg:address":"228 NE 48th St",
    "sg:city":"Oak Island",
    "sg:classifiers":[
        {
            "category":"Personal",
            "subcategory":"Beauty Salon",
            "type":"Services"
        }
    ],
    "sg:phone":"+1 910 457 0502",
    "sg:postcode":"28465",
    "sg:province":"NC",
    "wof:name":"Totally You Day Spa",
    "wof:placetype":"venue"
},
  "geometry": {"coordinates":[-78.113961,33.916916],"type":"Point"}
}