{
  "type": "Feature",
  "properties": {
    "iso:country":"US",
    "sg:address":"2025 Walker Rd",
    "sg:city":"Winston Salem",
    "sg:classifiers":[
        {
            "category":"Organizations",
            "subcategory":"Religious Organization",
            "type":"Services"
        }
    ],
    "sg:phone":"+1 336 924 2110",
    "sg:postcode":"27106",
    "sg:province":"NC",
    "wof:name":"William C Currie Rev",
    "wof:placetype":"venue"
},
  "geometry": {"coordinates":[-80.310424,36.188466],"type":"Point"}
}