{
  "type": "Feature",
  "properties": {
    "iso:country":"US",
    "sg:address":"3033 Mannington Dr",
    "sg:city":"Charlotte",
    "sg:classifiers":[
        {
            "category":"Building & Trades",
            "subcategory":"Construction",
            "type":"Services"
        }
    ],
    "sg:phone":"+1 704 507 3640",
    "sg:postcode":"28270",
    "sg:province":"NC",
    "sg:tags":[
        "concrete",
        "staining",
        "contractor"
    ],
    "wof:name":"Condor Concrete Mobile Mixer",
    "wof:placetype":"venue"
},
  "geometry": {"coordinates":[-80.734346,35.078567],"type":"Point"}
}