{
  "type": "Feature",
  "properties": {
    "addr:full":"484 Jenkins Moose Rd Taylorsville NC 28681",
    "addr:housenumber":"484",
    "addr:postcode":"28681",
    "addr:street":"Jenkins Moose Rd",
    "iso:country":"US",
    "sg:address":"484 Jenkins Moose Rd",
    "sg:city":"Taylorsville",
    "sg:classifiers":[
        {
            "category":"Building & Trades",
            "subcategory":"Pest Control",
            "type":"Services"
        }
    ],
    "sg:phone":"+1   ",
    "sg:postcode":"28681",
    "sg:province":"NC",
    "wof:name":"Johnson Exterminating Co",
    "wof:placetype":"venue"
},
  "geometry": {"coordinates":[-81.195948,35.906761],"type":"Point"}
}