{
  "type": "Feature",
  "properties": {
    "iso:country":"US",
    "sg:address":"1125 Little Elk Rd",
    "sg:city":"Elk Park",
    "sg:classifiers":[
        {
            "category":"Retail",
            "subcategory":"Laundry & Dry Cleaning",
            "type":"Services"
        }
    ],
    "sg:phone":"+1   ",
    "sg:postcode":"28622",
    "sg:province":"NC",
    "sg:tags":[
        "upholstery",
        "carpet"
    ],
    "wof:name":"Drycon Carpet",
    "wof:placetype":"venue"
},
  "geometry": {"coordinates":[-81.997319,36.154996],"type":"Point"}
}