{
  "type": "Feature",
  "properties": {
    "iso:country":"US",
    "sg:address":"115 Lodge St S",
    "sg:city":"Wilson",
    "sg:classifiers":[
        {
            "category":"Organizations",
            "subcategory":"Non-profit Organization",
            "type":"Services"
        }
    ],
    "sg:phone":"+1 252 234 0009",
    "sg:postcode":"27893",
    "sg:province":"NC",
    "sg:tags":[
        "human"
    ],
    "wof:name":"Habitat For Humanity Resale",
    "wof:placetype":"venue"
},
  "geometry": {"coordinates":[-77.908489,35.722987],"type":"Point"}
}