{
  "type": "Feature",
  "properties": {
    "iso:country":"US",
    "sg:address":"801 Cardinal Rd",
    "sg:city":"New Bern",
    "sg:classifiers":[
        {
            "category":"Education",
            "subcategory":"Dance Studio",
            "type":"Public Place"
        }
    ],
    "sg:phone":"+1 252 636 2811",
    "sg:postcode":"28562",
    "sg:province":"NC",
    "sg:tags":[
        "instruction",
        "dancing"
    ],
    "wof:name":"Wanda Kay's School Of Dance",
    "wof:placetype":"venue"
},
  "geometry": {"coordinates":[-77.099052,35.107966],"type":"Point"}
}