{
  "type": "Feature",
  "properties": {
    "iso:country":"US",
    "sg:address":"6350 Styers Ferry Rd",
    "sg:city":"Clemmons",
    "sg:classifiers":[
        {
            "category":"Organizations",
            "subcategory":"Religious Organization",
            "type":"Services"
        }
    ],
    "sg:phone":"+1   ",
    "sg:postcode":"27012",
    "sg:province":"NC",
    "wof:name":"Bible Baptist Church",
    "wof:placetype":"venue"
},
  "geometry": {"coordinates":[-80.409645,36.070269],"type":"Point"}
}