{
  "type": "Feature",
  "properties": {
    "addr:full":"5300 Blue Sage Dr Raleigh NC 27606",
    "addr:housenumber":"5300",
    "addr:postcode":"27606",
    "addr:street":"Blue Sage Dr",
    "iso:country":"US",
    "sg:address":"5300 Blue Sage Dr",
    "sg:city":"Raleigh",
    "sg:classifiers":[
        {
            "category":"Shopping",
            "subcategory":"Jewelry",
            "type":"Retail Goods"
        }
    ],
    "sg:phone":"+1 919 828 6761",
    "sg:postcode":"27606",
    "sg:province":"NC",
    "wof:name":"Brogans Jewelery",
    "wof:placetype":"venue"
},
  "geometry": {"coordinates":[-78.697884,35.705866],"type":"Point"}
}