{
  "type": "Feature",
  "properties": {
    "iso:country":"US",
    "sg:address":"53 Cabarrus Ave W",
    "sg:city":"Concord",
    "sg:classifiers":[
        {
            "category":"Communications",
            "subcategory":"Radio Station",
            "type":"Services"
        }
    ],
    "sg:phone":"+1 704 786 9108",
    "sg:postcode":"28025",
    "sg:province":"NC",
    "sg:tags":[
        "company",
        "broadcasting"
    ],
    "wof:name":"I AM 108",
    "wof:placetype":"venue"
},
  "geometry": {"coordinates":[-80.583575,35.408784],"type":"Point"}
}