{
  "type": "Feature",
  "properties": {
    "iso:country":"US",
    "sg:address":"2065 State Rd 98",
    "sg:city":"Louisburg",
    "sg:classifiers":[
        {
            "category":"Building & Trades",
            "subcategory":"Construction",
            "type":"Services"
        }
    ],
    "sg:phone":"+1 919 496 1995",
    "sg:postcode":"27549",
    "sg:province":"NC",
    "sg:tags":[
        "specializing",
        "stone",
        "work",
        "masonry",
        "contractor"
    ],
    "wof:name":"Professional Stone & Masonry",
    "wof:placetype":"venue"
},
  "geometry": {"coordinates":[-78.31929700000001,35.965797],"type":"Point"}
}