{
  "type": "Feature",
  "properties": {
    "iso:country":"US",
    "sg:address":"1021 N Harrison Ave",
    "sg:city":"Cary",
    "sg:classifiers":[
        {
            "category":"Deli",
            "type":"Food & Drink"
        }
    ],
    "sg:phone":"+1 919 462 1523",
    "sg:postcode":"27513",
    "sg:province":"NC",
    "sg:website":"www.schlotzskys.com",
    "wof:name":"Schlotzsky's Deli",
    "wof:placetype":"venue"
},
  "geometry": {"coordinates":[-78.783096,35.803101],"type":"Point"}
}