{
  "type": "Feature",
  "properties": {
    "addr:full":"7936 Lester Rd Stokesdale NC 27357",
    "addr:housenumber":"7936",
    "addr:postcode":"27357",
    "addr:street":"Lester Rd",
    "iso:country":"US",
    "sg:address":"7936 Lester Rd",
    "sg:city":"Stokesdale",
    "sg:classifiers":[
        {
            "category":"Building & Trades",
            "subcategory":"Construction",
            "type":"Services"
        }
    ],
    "sg:phone":"+1 336 644 9314",
    "sg:postcode":"27357",
    "sg:province":"NC",
    "sg:tags":[
        "contractor",
        "vehicle"
    ],
    "wof:name":"L & J Metal Fabrication",
    "wof:placetype":"venue"
},
  "geometry": {"coordinates":[-79.981504,36.246639],"type":"Point"}
}