{
  "type": "Feature",
  "properties": {
    "iso:country":"US",
    "sg:address":"3156 Stockton St",
    "sg:city":"Winston Salem",
    "sg:classifiers":[
        {
            "category":"Organizations",
            "subcategory":"Religious Organization",
            "type":"Services"
        }
    ],
    "sg:phone":"+1 336 725 5355",
    "sg:postcode":"27127",
    "sg:province":"NC",
    "sg:tags":[
        "church"
    ],
    "wof:name":"Holy Trinity Church",
    "wof:placetype":"venue"
},
  "geometry": {"coordinates":[-80.238173,36.054052],"type":"Point"}
}