{
  "type": "Feature",
  "properties": {
    "addr:full":"909 N Wendover Rd Charlotte NC 28211",
    "addr:housenumber":"909",
    "addr:postcode":"28211",
    "addr:street":"N Wendover Rd",
    "iso:country":"US",
    "sg:address":"909 N Wendover Rd",
    "sg:city":"Charlotte",
    "sg:classifiers":[
        {
            "category":"Personal",
            "subcategory":"Beauty Salon",
            "type":"Services"
        }
    ],
    "sg:phone":"+1 704 364 5353",
    "sg:postcode":"28211",
    "sg:province":"NC",
    "sg:tags":[
        "manicuring"
    ],
    "wof:name":"Nail Max",
    "wof:placetype":"venue"
},
  "geometry": {"coordinates":[-80.797049,35.190797],"type":"Point"}
}