{
  "type": "Feature",
  "properties": {
    "addr:full":"169 N Winstead Ave Rocky Mount NC 27804",
    "addr:housenumber":"169",
    "addr:postcode":"27804",
    "addr:street":"N Winstead Ave",
    "iso:country":"US",
    "sg:address":"169 N Winstead Ave",
    "sg:city":"Rocky Mount",
    "sg:classifiers":[
        {
            "category":"Professional",
            "subcategory":"Computer Services",
            "type":"Services"
        }
    ],
    "sg:phone":"+1 252 451 0686",
    "sg:postcode":"27804",
    "sg:province":"NC",
    "sg:tags":[
        "internet"
    ],
    "sg:website":"www.carolinainter.net",
    "wof:name":"Carolina Internet Svc",
    "wof:placetype":"venue"
},
  "geometry": {"coordinates":[-77.849442,35.964598],"type":"Point"}
}