{
  "type": "Feature",
  "properties": {
    "addr:full":"211 Oakwood Rd West Jefferson NC 28694",
    "addr:housenumber":"211",
    "addr:postcode":"28694",
    "addr:street":"Oakwood Rd",
    "iso:country":"US",
    "sg:address":"211 Oakwood Rd",
    "sg:city":"West Jefferson",
    "sg:classifiers":[
        {
            "category":"Professional",
            "type":"Services"
        }
    ],
    "sg:phone":"+1 336 246 5108",
    "sg:postcode":"28694",
    "sg:province":"NC",
    "wof:name":"Gjb LLC",
    "wof:placetype":"venue"
},
  "geometry": {"coordinates":[-81.47806300000001,36.38381],"type":"Point"}
}