{
  "type": "Feature",
  "properties": {
    "iso:country":"US",
    "sg:address":"400 N Bridge St",
    "sg:city":"Eden",
    "sg:classifiers":[
        {
            "category":"Organizations",
            "subcategory":"Religious Organization",
            "type":"Services"
        }
    ],
    "sg:phone":"+1   ",
    "sg:postcode":"27288",
    "sg:province":"NC",
    "wof:name":"United House Prayer For All",
    "wof:placetype":"venue"
},
  "geometry": {"coordinates":[-79.76907799999999,36.49783],"type":"Point"}
}