{
  "type": "Feature",
  "properties": {
    "iso:country":"US",
    "sg:address":"2533 Warwick Rd",
    "sg:city":"Winston Salem",
    "sg:classifiers":[
        {
            "category":"Professional",
            "type":"Services"
        }
    ],
    "sg:phone":"+1 336 724 3354",
    "sg:postcode":"27104",
    "sg:province":"NC",
    "wof:name":"Twinsco LLC",
    "wof:placetype":"venue"
},
  "geometry": {"coordinates":[-80.284344,36.100781],"type":"Point"}
}