{
  "type": "Feature",
  "properties": {
    "addr:full":"609 Pond St Albemarle NC 28001",
    "addr:housenumber":"609",
    "addr:postcode":"28001",
    "addr:street":"Pond St",
    "iso:country":"US",
    "sg:address":"609 Pond St",
    "sg:city":"Albemarle",
    "sg:classifiers":[
        {
            "category":"Retail",
            "subcategory":"Laundry & Dry Cleaning",
            "type":"Services"
        }
    ],
    "sg:phone":"+1 704 986 2300",
    "sg:postcode":"28001",
    "sg:province":"NC",
    "sg:tags":[
        "cleaners",
        "rug",
        "carpet"
    ],
    "wof:name":"Extreme Carpet Care & Concepts",
    "wof:placetype":"venue"
},
  "geometry": {"coordinates":[-80.166105,35.359263],"type":"Point"}
}