{
  "type": "Feature",
  "properties": {
    "iso:country":"US",
    "sg:address":"7365 Six Forks Rd",
    "sg:city":"Raleigh",
    "sg:classifiers":[
        {
            "category":"Shopping",
            "subcategory":"Clothing, Apparel, & Fashions",
            "type":"Retail Goods"
        },
        {
            "category":"Home & Garden",
            "subcategory":"Home Furnishings",
            "type":"Retail Goods"
        },
        {
            "category":"Manufacturing",
            "subcategory":"Textiles",
            "type":"Manufacturing & Wholesale Goods"
        },
        {
            "category":"Retail",
            "subcategory":"Laundry & Dry Cleaning",
            "type":"Services"
        },
        {
            "category":"Shopping",
            "subcategory":"Bridal",
            "type":"Retail Goods"
        },
        {
            "category":"Personal",
            "type":"Services"
        }
    ],
    "sg:phone":"+1 919 848 0531",
    "sg:postcode":"27615",
    "sg:province":"NC",
    "sg:tags":[
        "draperies",
        "cleaner",
        "shop",
        "dressmaker",
        "sewing",
        "alterations-clothing",
        "women's",
        "window",
        "tailor",
        "treatment",
        "apparel",
        "curtain",
        "contractor",
        "clothing",
        "boys'"
    ],
    "sg:website":"http://www.leestailorshop.com",
    "wof:name":"Lee's Tailor Shop",
    "wof:placetype":"venue"
},
  "geometry": {"coordinates":[-78.645771,35.879338],"type":"Point"}
}