{
  "type": "Feature",
  "properties": {
    "iso:country":"US",
    "sg:address":"401 Martin Luther King Jr Dr",
    "sg:city":"Greenville",
    "sg:classifiers":[
        {
            "category":"Insurance",
            "subcategory":"Insurance Agent",
            "type":"Services"
        }
    ],
    "sg:phone":"+1 252 758 3300",
    "sg:postcode":"27834",
    "sg:province":"NC",
    "wof:name":"Coras Insurance",
    "wof:placetype":"venue"
},
  "geometry": {"coordinates":[-77.37909999999999,35.61221],"type":"Point"}
}