{
  "type": "Feature",
  "properties": {
    "addr:full":"1680 Drexel Rd Valdese NC 28690",
    "addr:housenumber":"1680",
    "addr:postcode":"28690",
    "addr:street":"Drexel Rd",
    "iso:country":"US",
    "sg:address":"1680 Drexel Rd",
    "sg:city":"Valdese",
    "sg:classifiers":[
        {
            "category":"Retail",
            "subcategory":"Auto Repair",
            "type":"Services"
        }
    ],
    "sg:phone":"+1 828 874 2244",
    "sg:postcode":"28690",
    "sg:province":"NC",
    "wof:name":"High Performance Engineering",
    "wof:placetype":"venue"
},
  "geometry": {"coordinates":[-81.605418,35.740247],"type":"Point"}
}