{
  "type": "Feature",
  "properties": {
    "iso:country":"US",
    "sg:address":"45 Saunooke Rd",
    "sg:city":"Asheville",
    "sg:classifiers":[
        {
            "category":"Real Estate",
            "subcategory":"Real Estate Operator",
            "type":"Services"
        }
    ],
    "sg:phone":"+1 828 298 3822",
    "sg:postcode":"28805",
    "sg:province":"NC",
    "sg:tags":[
        "mobile",
        "home",
        "community"
    ],
    "wof:name":"Scenic Mobile Home Park",
    "wof:placetype":"venue"
},
  "geometry": {"coordinates":[-82.455161,35.585878],"type":"Point"}
}