{
  "type": "Feature",
  "properties": {
    "addr:full":"700 Dover St Southern Pines NC 28387",
    "addr:housenumber":"700",
    "addr:postcode":"28387",
    "addr:street":"Dover St",
    "iso:country":"US",
    "sg:address":"700 Dover St",
    "sg:city":"Southern Pines",
    "sg:classifiers":[
        {
            "category":"Wholesale",
            "subcategory":"Drugs",
            "type":"Manufacturing & Wholesale Goods"
        }
    ],
    "sg:phone":"+1 877 692 8809",
    "sg:postcode":"28387",
    "sg:province":"NC",
    "sg:tags":[
        "shop",
        "beauty"
    ],
    "wof:name":"Genevieve",
    "wof:placetype":"venue"
},
  "geometry": {"coordinates":[-79.350889,35.20366],"type":"Point"}
}