{
  "type": "Feature",
  "properties": {
    "addr:full":"1962 Coweeta Church Rd Otto NC 28763",
    "addr:housenumber":"1962",
    "addr:postcode":"28763",
    "addr:street":"Coweeta Church Rd",
    "iso:country":"US",
    "sg:address":"1962 Coweeta Church Rd",
    "sg:city":"Otto",
    "sg:classifiers":[
        {
            "category":"Retail",
            "subcategory":"Repair Shop",
            "type":"Services"
        }
    ],
    "sg:phone":"+1 828 524 5680",
    "sg:postcode":"28763",
    "sg:province":"NC",
    "sg:tags":[
        "repairing",
        "vault",
        "safe"
    ],
    "wof:name":"Hillside Fire & Safety",
    "wof:placetype":"venue"
},
  "geometry": {"coordinates":[-83.403897,35.067768],"type":"Point"}
}