{
  "type": "Feature",
  "properties": {
    "iso:country":"US",
    "sg:address":"405 Stutts Rd",
    "sg:city":"Mooresville",
    "sg:classifiers":[
        {
            "category":"Building & Trades",
            "subcategory":"Construction",
            "type":"Services"
        }
    ],
    "sg:phone":"+1 704 662 8749",
    "sg:postcode":"28117",
    "sg:province":"NC",
    "sg:tags":[
        "house"
    ],
    "wof:name":"R J Casucci Construction",
    "wof:placetype":"venue"
},
  "geometry": {"coordinates":[-80.896672,35.554277],"type":"Point"}
}