{
  "type": "Feature",
  "properties": {
    "iso:country":"US",
    "sg:address":"104 Steep Bank Dr",
    "sg:city":"Cary",
    "sg:classifiers":[
        {
            "category":"Shopping",
            "subcategory":"Clothing, Apparel, & Fashions",
            "type":"Retail Goods"
        }
    ],
    "sg:phone":"+1 919 233 9611",
    "sg:postcode":"27518",
    "sg:province":"NC",
    "sg:tags":[
        "wear"
    ],
    "wof:name":"Custom Creations For Kids",
    "wof:placetype":"venue"
},
  "geometry": {"coordinates":[-78.78963899999999,35.719934],"type":"Point"}
}