{
  "type": "Feature",
  "properties": {
    "iso:country":"US",
    "sg:address":"2063 Shiloh Rd",
    "sg:city":"Claremont",
    "sg:classifiers":[
        {
            "category":"Home & Garden",
            "subcategory":"Furniture",
            "type":"Retail Goods"
        }
    ],
    "sg:phone":"+1 828 241 2836",
    "sg:postcode":"28610",
    "sg:province":"NC",
    "sg:tags":[
        "builder",
        "custom"
    ],
    "wof:name":"Gram Furniture Co",
    "wof:placetype":"venue"
},
  "geometry": {"coordinates":[-81.103863,35.676466],"type":"Point"}
}