{
  "type": "Feature",
  "properties": {
    "iso:country":"US",
    "sg:address":"2009 Pactolus Hwy",
    "sg:city":"Greenville",
    "sg:classifiers":[
        {
            "category":"Education",
            "subcategory":"School",
            "type":"Public Place"
        }
    ],
    "sg:phone":"+1 252 551 1055",
    "sg:postcode":"27834",
    "sg:province":"NC",
    "sg:tags":[
        "religious"
    ],
    "sg:website":"www.greenvillecommunitychristian.com",
    "wof:name":"Community Christian Academy",
    "wof:placetype":"venue"
},
  "geometry": {"coordinates":[-77.33770199999999,35.626432],"type":"Point"}
}