{
  "type": "Feature",
  "properties": {
    "addr:full":"409 Goldfloss St Winston Salem NC 27127",
    "addr:housenumber":"409",
    "addr:postcode":"27127",
    "addr:street":"Goldfloss St",
    "iso:country":"US",
    "sg:address":"409 Goldfloss St",
    "sg:city":"Winston Salem",
    "sg:classifiers":[
        {
            "category":"Retail",
            "subcategory":"Self-service Laundry",
            "type":"Services"
        }
    ],
    "sg:phone":"+1 336 724 0366",
    "sg:postcode":"27127",
    "sg:province":"NC",
    "wof:name":"Southside Launderette",
    "wof:placetype":"venue"
},
  "geometry": {"coordinates":[-80.229827,36.067155],"type":"Point"}
}