{
  "type": "Feature",
  "properties": {
    "addr:full":"2974 Kildaire Farm Rd Cary NC 27511",
    "addr:housenumber":"2974",
    "addr:postcode":"27511",
    "addr:street":"Kildaire Farm Rd",
    "iso:country":"US",
    "sg:address":"2974 Kildaire Farm Rd",
    "sg:city":"Cary",
    "sg:classifiers":[
        {
            "category":"Coffee & Tea",
            "type":"Food & Drink"
        }
    ],
    "sg:phone":"+1 919 362 5266",
    "sg:postcode":"27511",
    "sg:province":"NC",
    "wof:name":"Javablu Espresso",
    "wof:placetype":"venue"
},
  "geometry": {"coordinates":[-78.78800200000001,35.716801],"type":"Point"}
}