{
  "type": "Feature",
  "properties": {
    "iso:country":"US",
    "sg:address":"401 W Vernon Ave",
    "sg:city":"Kinston",
    "sg:classifiers":[
        {
            "category":"Shopping",
            "type":"Retail Goods"
        }
    ],
    "sg:phone":"+1 252 527 0345",
    "sg:postcode":"28501",
    "sg:province":"NC",
    "sg:tags":[
        "machine"
    ],
    "wof:name":"Daughtys Office Eqp of Kinston",
    "wof:placetype":"venue"
},
  "geometry": {"coordinates":[-77.587352,35.269245],"type":"Point"}
}