{
  "type": "Feature",
  "properties": {
    "iso:country":"US",
    "sg:address":"14903 Santa Lucia Dr",
    "sg:city":"Charlotte",
    "sg:classifiers":[
        {
            "category":"Real Estate",
            "subcategory":"Real Estate Services",
            "type":"Services"
        }
    ],
    "sg:phone":"+1 704 542 7519",
    "sg:postcode":"28277",
    "sg:province":"NC",
    "sg:tags":[
        "management",
        "condominium"
    ],
    "wof:name":"Belle Vista Condominiums",
    "wof:placetype":"venue"
},
  "geometry": {"coordinates":[-80.852249,35.051892],"type":"Point"}
}