{
  "type": "Feature",
  "properties": {
    "iso:country":"US",
    "sg:address":"1915 Milton Rd",
    "sg:city":"Charlotte",
    "sg:classifiers":[
        {
            "category":"Communications",
            "subcategory":"Television Station",
            "type":"Services"
        }
    ],
    "sg:phone":"+1 704 222 1086",
    "sg:postcode":"28215",
    "sg:province":"NC",
    "sg:tags":[
        "network"
    ],
    "sg:website":"http://www.onewaysolution1.com",
    "wof:name":"Onewaysolution",
    "wof:placetype":"venue"
},
  "geometry": {"coordinates":[-80.752487,35.246458],"type":"Point"}
}