{
  "type": "Feature",
  "properties": {
    "addr:full":"315 Foushee St Durham NC 27704",
    "addr:housenumber":"315",
    "addr:postcode":"27704",
    "addr:street":"Foushee St",
    "iso:country":"US",
    "sg:address":"315 Foushee St",
    "sg:city":"Durham",
    "sg:classifiers":[
        {
            "category":"Restaurant",
            "type":"Food & Drink"
        }
    ],
    "sg:phone":"+1 919 220 8615",
    "sg:postcode":"27704",
    "sg:province":"NC",
    "wof:name":"Pollo Loco",
    "wof:placetype":"venue"
},
  "geometry": {"coordinates":[-78.88614200000001,36.016986],"type":"Point"}
}