{
  "type": "Feature",
  "properties": {
    "iso:country":"US",
    "sg:address":"8218 E Independence Blvd",
    "sg:city":"Charlotte",
    "sg:classifiers":[
        {
            "category":"Autos & Motor Vehicles",
            "subcategory":"Automobile Sales",
            "type":"Retail Goods"
        }
    ],
    "sg:phone":"+1 704 537 6859",
    "sg:postcode":"28227",
    "sg:province":"NC",
    "sg:tags":[
        "car",
        "dealer"
    ],
    "wof:name":"Crest Cadillac",
    "wof:placetype":"venue"
},
  "geometry": {"coordinates":[-80.72941299999999,35.152461],"type":"Point"}
}