{
  "type": "Feature",
  "properties": {
    "iso:country":"US",
    "sg:address":"1342 State Hwy 42 S",
    "sg:city":"Asheboro",
    "sg:classifiers":[
        {
            "category":"Social Services",
            "subcategory":"Adult Care",
            "type":"Services"
        }
    ],
    "sg:phone":"+1 336 328 0671",
    "sg:postcode":"27205",
    "sg:province":"NC",
    "sg:tags":[
        "residential"
    ],
    "wof:name":"Heath House",
    "wof:placetype":"venue"
},
  "geometry": {"coordinates":[-79.767803,35.684133],"type":"Point"}
}