{
  "type": "Feature",
  "properties": {
    "iso:country":"US",
    "sg:address":"797 Steed Rd",
    "sg:city":"Seagrove",
    "sg:classifiers":[
        {
            "category":"Professional",
            "subcategory":"Management & Consulting",
            "type":"Services"
        }
    ],
    "sg:phone":"+1 910 428 2922",
    "sg:postcode":"27341",
    "sg:province":"NC",
    "sg:tags":[
        "construction"
    ],
    "wof:name":"Helsabeck Frame Shop",
    "wof:placetype":"venue"
},
  "geometry": {"coordinates":[-79.767403,35.465382],"type":"Point"}
}