{
  "type": "Feature",
  "properties": {
    "addr:full":"1003 Brookstown Ave NW Winston Salem NC 27101",
    "addr:housenumber":"1003",
    "addr:postcode":"27101",
    "addr:street":"Brookstown Ave Nw",
    "iso:country":"US",
    "sg:address":"1003 Brookstown Ave NW",
    "sg:city":"Winston Salem",
    "sg:classifiers":[
        {
            "category":"Restaurant",
            "type":"Food & Drink"
        }
    ],
    "sg:phone":"+1 336 724 2363",
    "sg:postcode":"27101",
    "sg:province":"NC",
    "wof:name":"Flash Back Smoothies & Soda",
    "wof:placetype":"venue"
},
  "geometry": {"coordinates":[-80.25704,36.09704],"type":"Point"}
}