{
  "type": "Feature",
  "properties": {
    "iso:country":"US",
    "sg:address":"2190 Angelia M St",
    "sg:city":"Fayetteville",
    "sg:classifiers":[
        {
            "category":"Retail",
            "subcategory":"Auto Repair",
            "type":"Services"
        }
    ],
    "sg:phone":"+1 910 483 9507",
    "sg:postcode":"28312",
    "sg:province":"NC",
    "sg:tags":[
        "wrecker"
    ],
    "wof:name":"Mac's Towing Svc",
    "wof:placetype":"venue"
},
  "geometry": {"coordinates":[-78.836218,35.048952],"type":"Point"}
}