{
  "type": "Feature",
  "properties": {
    "iso:country":"US",
    "sg:address":"11703 Oakland Hills Pl",
    "sg:city":"Charlotte",
    "sg:classifiers":[
        {
            "category":"Wholesale",
            "subcategory":"Vending Machines",
            "type":"Manufacturing & Wholesale Goods"
        }
    ],
    "sg:phone":"+1 704 846 9891",
    "sg:postcode":"28277",
    "sg:province":"NC",
    "sg:tags":[
        "operator"
    ],
    "wof:name":"Bubble King LLC",
    "wof:placetype":"venue"
},
  "geometry": {"coordinates":[-80.788883,35.040756],"type":"Point"}
}