{
  "type": "Feature",
  "properties": {
    "addr:full":"670 Deep River Rd Sanford NC 27330",
    "addr:housenumber":"670",
    "addr:postcode":"27330",
    "addr:street":"Deep River Rd",
    "iso:country":"US",
    "sg:address":"670 Deep River Rd",
    "sg:city":"Sanford",
    "sg:classifiers":[
        {
            "category":"Freight",
            "type":"Transportation"
        }
    ],
    "sg:phone":"+1 919 776 3156",
    "sg:postcode":"27330",
    "sg:province":"NC",
    "sg:tags":[
        "distance",
        "long",
        "trucking"
    ],
    "wof:name":"East Trucking Inc",
    "wof:placetype":"venue"
},
  "geometry": {"coordinates":[-79.18234,35.557868],"type":"Point"}
}