{
  "type": "Feature",
  "properties": {
    "addr:full":"624 Tyvola Rd Charlotte NC 28217",
    "addr:housenumber":"624",
    "addr:postcode":"28217",
    "addr:street":"Tyvola Rd",
    "iso:country":"US",
    "sg:address":"624 Tyvola Rd",
    "sg:city":"Charlotte",
    "sg:classifiers":[
        {
            "category":"Shopping",
            "subcategory":"Clothing, Apparel, & Fashions",
            "type":"Retail Goods"
        }
    ],
    "sg:phone":"+1 704 525 3344",
    "sg:postcode":"28217",
    "sg:province":"NC",
    "wof:name":"Educational Outfitters",
    "wof:placetype":"venue"
},
  "geometry": {"coordinates":[-80.88442999999999,35.164105],"type":"Point"}
}