{
  "type": "Feature",
  "properties": {
    "addr:full":"6530 Brevard Rd Etowah NC 28729",
    "addr:housenumber":"6530",
    "addr:postcode":"28729",
    "addr:street":"Brevard Rd",
    "iso:country":"US",
    "sg:address":"6530 Brevard Rd",
    "sg:city":"Etowah",
    "sg:classifiers":[
        {
            "category":"Retail",
            "subcategory":"Auto Rental",
            "type":"Services"
        }
    ],
    "sg:phone":"+1   ",
    "sg:postcode":"28729",
    "sg:province":"NC",
    "sg:tags":[
        "trailer",
        "utility"
    ],
    "wof:name":"U-Haul",
    "wof:placetype":"venue"
},
  "geometry": {"coordinates":[-82.59522,35.317525],"type":"Point"}
}