{
  "type": "Feature",
  "properties": {
    "addr:full":"3000 E Franklin Blvd Gastonia NC 28056",
    "addr:housenumber":"3000",
    "addr:postcode":"28056",
    "addr:street":"E Franklin Blvd",
    "iso:country":"US",
    "sg:address":"3000 E Franklin Blvd",
    "sg:city":"Gastonia",
    "sg:classifiers":[
        {
            "category":"Personal",
            "subcategory":"Beauty Salon",
            "type":"Services"
        }
    ],
    "sg:phone":"+1   ",
    "sg:postcode":"28056",
    "sg:province":"NC",
    "sg:tags":[
        "shop"
    ],
    "wof:name":"Smartstyle",
    "wof:placetype":"venue"
},
  "geometry": {"coordinates":[-81.125249,35.2592],"type":"Point"}
}