{
  "type": "Feature",
  "properties": {
    "iso:country":"US",
    "sg:address":"148 Wycliff Ln",
    "sg:city":"Belmont",
    "sg:classifiers":[
        {
            "category":"Building & Trades",
            "subcategory":"Plumbing",
            "type":"Services"
        }
    ],
    "sg:phone":"+1 704 825 9399",
    "sg:postcode":"28012",
    "sg:province":"NC",
    "sg:tags":[
        "contractor"
    ],
    "wof:name":"Plumbing Connection",
    "wof:placetype":"venue"
},
  "geometry": {"coordinates":[-81.071663,35.199377],"type":"Point"}
}