{
  "type": "Feature",
  "properties": {
    "addr:full":"14015 US Hwy 74 Indian Trail NC 28079",
    "addr:housenumber":"14015",
    "addr:postcode":"28079",
    "addr:street":"Us Hwy 74;Trail",
    "iso:country":"US",
    "sg:address":"14015 US Hwy 74",
    "sg:city":"Indian Trail",
    "sg:classifiers":[
        {
            "category":"Shopping",
            "subcategory":"Used Merchandise",
            "type":"Retail Goods"
        }
    ],
    "sg:phone":"+1 704 893 0893",
    "sg:postcode":"28079",
    "sg:province":"NC",
    "sg:tags":[
        "shop",
        "consignment"
    ],
    "wof:name":"Little Bear's Closet",
    "wof:placetype":"venue"
},
  "geometry": {"coordinates":[-80.656505,35.080194],"type":"Point"}
}