{
  "type": "Feature",
  "properties": {
    "addr:full":"4201 Long Run Farm Rd Mount Pleasant NC 28124",
    "addr:housenumber":"4201",
    "addr:postcode":"28124",
    "addr:street":"Long Run Farm Rd",
    "iso:country":"US",
    "sg:address":"4201 Long Run Farm Rd",
    "sg:city":"Mount Pleasant",
    "sg:classifiers":[
        {
            "category":"Retail",
            "subcategory":"Portrait Studio",
            "type":"Services"
        }
    ],
    "sg:phone":"+1   ",
    "sg:postcode":"28124",
    "sg:province":"NC",
    "sg:tags":[
        "photo"
    ],
    "wof:name":"Photography By Mercedes",
    "wof:placetype":"venue"
},
  "geometry": {"coordinates":[-80.42042600000001,35.360564],"type":"Point"}
}