{
  "type": "Feature",
  "properties": {
    "addr:full":"128 Chaney Ave Jacksonville NC 28540",
    "addr:housenumber":"128",
    "addr:postcode":"28540",
    "addr:street":"Chaney Ave",
    "iso:country":"US",
    "sg:address":"128 Chaney Ave",
    "sg:city":"Jacksonville",
    "sg:classifiers":[
        {
            "category":"Retail",
            "subcategory":"Funeral Services",
            "type":"Services"
        }
    ],
    "sg:phone":"+1 910 478 9899",
    "sg:postcode":"28540",
    "sg:province":"NC",
    "sg:tags":[
        "director"
    ],
    "wof:name":"A & W Spicer Hardison Mortuary",
    "wof:placetype":"venue"
},
  "geometry": {"coordinates":[-77.429907,34.752206],"type":"Point"}
}