{
  "type": "Feature",
  "properties": {
    "addr:full":"211 Clubhouse Dr Dunn NC 28334",
    "addr:housenumber":"211",
    "addr:postcode":"28334",
    "addr:street":"Clubhouse Dr",
    "iso:country":"US",
    "sg:address":"211 Clubhouse Dr",
    "sg:city":"Dunn",
    "sg:classifiers":[
        {
            "category":"Real Estate",
            "subcategory":"Developer",
            "type":"Services"
        },
        {
            "category":"Organizations",
            "subcategory":"Community Association",
            "type":"Services"
        }
    ],
    "sg:phone":"+1 910 892 6424",
    "sg:postcode":"28334",
    "sg:province":"NC",
    "sg:tags":[
        "club",
        "membership"
    ],
    "wof:name":"Sandy Ridge Country Club Inc",
    "wof:placetype":"venue"
},
  "geometry": {"coordinates":[-78.53385900000001,35.227042],"type":"Point"}
}