{
  "type": "Feature",
  "properties": {
    "iso:country":"US",
    "sg:address":"112 S Pitt St",
    "sg:city":"Grifton",
    "sg:classifiers":[
        {
            "category":"Social Services",
            "subcategory":"Child Care",
            "type":"Services"
        }
    ],
    "sg:phone":"+1 252 524 4538",
    "sg:postcode":"28530",
    "sg:province":"NC",
    "wof:name":"New Beginning Christian Child",
    "wof:placetype":"venue"
},
  "geometry": {"coordinates":[-77.435739,35.371966],"type":"Point"}
}