{
  "type": "Feature",
  "properties": {
    "addr:full":"5737 Market St Wilmington NC 28405",
    "addr:housenumber":"5737",
    "addr:postcode":"28405",
    "addr:street":"Market St",
    "iso:country":"US",
    "sg:address":"5737 Market St",
    "sg:city":"Wilmington",
    "sg:classifiers":[
        {
            "category":"Recreation",
            "type":"Entertainment"
        }
    ],
    "sg:phone":"+1 910 452 0254",
    "sg:postcode":"28405",
    "sg:province":"NC",
    "sg:tags":[
        "amusement"
    ],
    "wof:name":"J Martin Motor Sports",
    "wof:placetype":"venue"
},
  "geometry": {"coordinates":[-77.85716499999999,34.250488],"type":"Point"}
}