{
  "type": "Feature",
  "properties": {
    "iso:country":"US",
    "sg:address":"29 Tennessee St",
    "sg:city":"Murphy",
    "sg:classifiers":[
        {
            "category":"Food & Beverages",
            "subcategory":"Bakery",
            "type":"Retail Goods"
        },
        {
            "category":"Wholesale",
            "subcategory":"Groceries",
            "type":"Manufacturing & Wholesale Goods"
        }
    ],
    "sg:phone":"+1 828 835 8986",
    "sg:postcode":"28906",
    "sg:province":"NC",
    "sg:tags":[
        "baker"
    ],
    "wof:name":"Dowtown Bakery",
    "wof:placetype":"venue"
},
  "geometry": {"coordinates":[-84.03478200000001,35.088633],"type":"Point"}
}