{
  "type": "Feature",
  "properties": {
    "addr:full":"4853 Winterwood Dr Raleigh NC 27613",
    "addr:housenumber":"4853",
    "addr:postcode":"27613",
    "addr:street":"Winterwood Dr",
    "iso:country":"US",
    "sg:address":"4853 Winterwood Dr",
    "sg:city":"Raleigh",
    "sg:classifiers":[
        {
            "category":"Social Services",
            "subcategory":"Job Training",
            "type":"Services"
        }
    ],
    "sg:phone":"+1   ",
    "sg:postcode":"27613",
    "sg:province":"NC",
    "sg:tags":[
        "related"
    ],
    "wof:name":"Engler Management",
    "wof:placetype":"venue"
},
  "geometry": {"coordinates":[-78.699961,35.947739],"type":"Point"}
}