{
  "type": "Feature",
  "properties": {
    "iso:country":"US",
    "sg:address":"1041 Classic Rd",
    "sg:city":"Apex",
    "sg:classifiers":[
        {
            "category":"Professional",
            "subcategory":"Advertising",
            "type":"Services"
        },
        {
            "category":"Professional",
            "subcategory":"Art Services",
            "type":"Services"
        }
    ],
    "sg:phone":"+1 919 290 3989",
    "sg:postcode":"27539",
    "sg:province":"NC",
    "sg:tags":[
        "photographer",
        "videographers"
    ],
    "sg:website":"www.imagin-photo.com",
    "wof:name":"Imagin Photojournalism",
    "wof:placetype":"venue"
},
  "geometry": {"coordinates":[-78.824354,35.716248],"type":"Point"}
}