{
  "type": "Feature",
  "properties": {
    "addr:full":"7516 E Old US Hwy 64 Lexington NC 27292",
    "addr:housenumber":"7516",
    "addr:postcode":"27292",
    "addr:street":"E Old Us Hwy 64",
    "iso:country":"US",
    "sg:address":"7516 E Old US Hwy 64",
    "sg:city":"Lexington",
    "sg:classifiers":[
        {
            "category":"Farming",
            "subcategory":"Farm & Veterinary Services",
            "type":"Manufacturing & Wholesale Goods"
        }
    ],
    "sg:phone":"+1 336 746 6205",
    "sg:postcode":"27292",
    "sg:province":"NC",
    "sg:tags":[
        "breeder",
        "livestock"
    ],
    "wof:name":"Granny's Farm",
    "wof:placetype":"venue"
},
  "geometry": {"coordinates":[-80.155609,35.754551],"type":"Point"}
}