{
  "type": "Feature",
  "properties": {
    "iso:country":"US",
    "sg:address":"455 Stewartsville Rd",
    "sg:city":"Laurinburg",
    "sg:classifiers":[
        {
            "category":"Social Services",
            "subcategory":"Child Care",
            "type":"Services"
        }
    ],
    "sg:phone":"+1 910 610 1819",
    "sg:postcode":"28352",
    "sg:province":"NC",
    "sg:tags":[
        "day"
    ],
    "wof:name":"Kiddie Kare Learning Center",
    "wof:placetype":"venue"
},
  "geometry": {"coordinates":[-79.456659,34.764794],"type":"Point"}
}