{
  "type": "Feature",
  "properties": {
    "addr:full":"362 N Main St Stanley NC 28164",
    "addr:housenumber":"362",
    "addr:postcode":"28164",
    "addr:street":"N Main St",
    "iso:country":"US",
    "sg:address":"362 N Main St",
    "sg:city":"Stanley",
    "sg:classifiers":[
        {
            "category":"Retail",
            "subcategory":"Laundry & Dry Cleaning",
            "type":"Services"
        }
    ],
    "sg:phone":"+1 704 263 2321",
    "sg:postcode":"28164",
    "sg:province":"NC",
    "sg:tags":[
        "cleaners"
    ],
    "wof:name":"Rudisill Cleaners",
    "wof:placetype":"venue"
},
  "geometry": {"coordinates":[-81.09765400000001,35.363106],"type":"Point"}
}