{
  "type": "Feature",
  "properties": {
    "iso:country":"US",
    "sg:address":"808 Rock Quarry Rd",
    "sg:city":"Raleigh",
    "sg:classifiers":[
        {
            "category":"Taxi",
            "type":"Transportation"
        }
    ],
    "sg:phone":"+1 919 831 9011",
    "sg:postcode":"27610",
    "sg:province":"NC",
    "wof:name":"Excel Taxi Inc",
    "wof:placetype":"venue"
},
  "geometry": {"coordinates":[-78.618118,35.769341],"type":"Point"}
}