{
  "type": "Feature",
  "properties": {
    "iso:country":"US",
    "sg:address":"808 N Main St",
    "sg:city":"Waynesville",
    "sg:classifiers":[
        {
            "category":"Food & Beverages",
            "subcategory":"Groceries & Convenience Stores",
            "type":"Retail Goods"
        }
    ],
    "sg:phone":"+1 828 456 4899",
    "sg:postcode":"28786",
    "sg:province":"NC",
    "wof:name":"Corner Stop",
    "wof:placetype":"venue"
},
  "geometry": {"coordinates":[-82.97949,35.497147],"type":"Point"}
}