{
  "type": "Feature",
  "properties": {
    "iso:country":"US",
    "sg:address":"2023 E Barden Rd",
    "sg:city":"Charlotte",
    "sg:classifiers":[
        {
            "category":"Professional",
            "type":"Services"
        }
    ],
    "sg:phone":"+1 704 365 6239",
    "sg:postcode":"28226",
    "sg:province":"NC",
    "sg:tags":[
        "arts",
        "artist"
    ],
    "wof:name":"Blue Aura Arts",
    "wof:placetype":"venue"
},
  "geometry": {"coordinates":[-80.791777,35.138522],"type":"Point"}
}