{
  "type": "Feature",
  "properties": {
    "addr:full":"1896 Old Field Creek Rd Grassy Creek NC 28631",
    "addr:housenumber":"1896",
    "addr:postcode":"28631",
    "addr:street":"Old Field Creek Rd",
    "iso:country":"US",
    "sg:address":"1896 Old Field Creek Rd",
    "sg:city":"Grassy Creek",
    "sg:classifiers":[
        {
            "category":"Restaurant",
            "type":"Food & Drink"
        }
    ],
    "sg:phone":"+1 336 982 2109",
    "sg:postcode":"28631",
    "sg:province":"NC",
    "sg:tags":[
        "breakfast",
        "inn",
        "bed"
    ],
    "sg:website":"www.riverhousenc.com",
    "wof:name":"River House Bed & Breakfast",
    "wof:placetype":"venue"
},
  "geometry": {"coordinates":[-81.409611,36.514711],"type":"Point"}
}