{
  "type": "Feature",
  "properties": {
    "addr:full":"479 Green Level Rd W Apex NC 27523",
    "addr:housenumber":"479",
    "addr:postcode":"27523",
    "addr:street":"Green Level Rd W",
    "iso:country":"US",
    "sg:address":"479 Green Level Rd W",
    "sg:city":"Apex",
    "sg:classifiers":[
        {
            "category":"Recreation",
            "type":"Entertainment"
        }
    ],
    "sg:phone":"+1   ",
    "sg:postcode":"27523",
    "sg:province":"NC",
    "wof:name":"Im Inc",
    "wof:placetype":"venue"
},
  "geometry": {"coordinates":[-78.948948,35.776325],"type":"Point"}
}