{
  "type": "Feature",
  "properties": {
    "iso:country":"US",
    "sg:address":"304 Pomona Dr",
    "sg:city":"Greensboro",
    "sg:classifiers":[
        {
            "category":"Manufacturing",
            "subcategory":"Printing",
            "type":"Manufacturing & Wholesale Goods"
        }
    ],
    "sg:phone":"+1 336 292 4140",
    "sg:postcode":"27407",
    "sg:province":"NC",
    "sg:tags":[
        "typesetting"
    ],
    "wof:name":"Perfect Type",
    "wof:placetype":"venue"
},
  "geometry": {"coordinates":[-79.866952,36.06599],"type":"Point"}
}