{
  "type": "Feature",
  "properties": {
    "addr:full":"3750 NW Cary Pkwy Cary NC 27513",
    "addr:housenumber":"3750",
    "addr:postcode":"27513",
    "addr:street":"Nw Cary Pkwy",
    "iso:country":"US",
    "sg:address":"3750 NW Cary Pkwy",
    "sg:city":"Cary",
    "sg:classifiers":[
        {
            "category":"Insurance",
            "subcategory":"Insurance Agent",
            "type":"Services"
        }
    ],
    "sg:phone":"+1 919 466 9400",
    "sg:postcode":"27513",
    "sg:province":"NC",
    "wof:name":"Akins Jay & Associates LLC",
    "wof:placetype":"venue"
},
  "geometry": {"coordinates":[-78.818828,35.793552],"type":"Point"}
}