{
  "type": "Feature",
  "properties": {
    "iso:country":"US",
    "sg:address":"5222 Monroe Rd",
    "sg:city":"Charlotte",
    "sg:classifiers":[
        {
            "category":"Professional",
            "subcategory":"Lawyer & Legal Services",
            "type":"Services"
        }
    ],
    "sg:phone":"+1   ",
    "sg:postcode":"28205",
    "sg:province":"NC",
    "wof:name":"Bentsi-Enchill Kofi",
    "wof:placetype":"venue"
},
  "geometry": {"coordinates":[-80.77449300000001,35.190386],"type":"Point"}
}