{
  "type": "Feature",
  "properties": {
    "addr:full":"521 W Main St Spindale NC 28160",
    "addr:housenumber":"521",
    "addr:postcode":"28160",
    "addr:street":"W Main St",
    "iso:country":"US",
    "sg:address":"521 W Main St",
    "sg:city":"Spindale",
    "sg:classifiers":[
        {
            "category":"Home & Garden",
            "subcategory":"Home Furnishings",
            "type":"Retail Goods"
        }
    ],
    "sg:phone":"+1 828 287 0140",
    "sg:postcode":"28160",
    "sg:province":"NC",
    "sg:tags":[
        "gas",
        "fireplace",
        "log"
    ],
    "wof:name":"Gas Logs & Udder Things",
    "wof:placetype":"venue"
},
  "geometry": {"coordinates":[-81.93437299999999,35.358685],"type":"Point"}
}