{
  "type": "Feature",
  "properties": {
    "addr:full":"150 Rowan St Fayetteville NC 28301",
    "addr:housenumber":"150",
    "addr:postcode":"28301",
    "addr:street":"Rowan St",
    "iso:country":"US",
    "sg:address":"150 Rowan St",
    "sg:city":"Fayetteville",
    "sg:classifiers":[
        {
            "category":"Shopping",
            "subcategory":"Used Merchandise",
            "type":"Retail Goods"
        }
    ],
    "sg:phone":"+1 910 486 6111",
    "sg:postcode":"28301",
    "sg:province":"NC",
    "sg:tags":[
        "antique"
    ],
    "wof:name":"Gas House Antiques & Gift Mall",
    "wof:placetype":"venue"
},
  "geometry": {"coordinates":[-78.878574,35.057878],"type":"Point"}
}