{
  "type": "Feature",
  "properties": {
    "addr:full":"2426 N William St Goldsboro NC 27530",
    "addr:housenumber":"2426",
    "addr:postcode":"27530",
    "addr:street":"N William St",
    "iso:country":"US",
    "sg:address":"2426 N William St",
    "sg:city":"Goldsboro",
    "sg:classifiers":[
        {
            "category":"Personal",
            "subcategory":"Beauty Salon",
            "type":"Services"
        }
    ],
    "sg:phone":"+1   ",
    "sg:postcode":"27530",
    "sg:province":"NC",
    "sg:tags":[
        "shop"
    ],
    "wof:name":"Cathys Cosmetology Center",
    "wof:placetype":"venue"
},
  "geometry": {"coordinates":[-77.981936,35.417873],"type":"Point"}
}