{
  "type": "Feature",
  "properties": {
    "iso:country":"US",
    "sg:address":"1928 Wedgewood Dr",
    "sg:city":"Sanford",
    "sg:classifiers":[
        {
            "category":"Wholesale",
            "subcategory":"Durable Goods & Equipment",
            "type":"Manufacturing & Wholesale Goods"
        }
    ],
    "sg:phone":"+1 919 499 4111",
    "sg:postcode":"27332",
    "sg:province":"NC",
    "sg:tags":[
        "representative",
        "manufacturer"
    ],
    "wof:name":"G T Assoc Inc",
    "wof:placetype":"venue"
},
  "geometry": {"coordinates":[-79.096164,35.418211],"type":"Point"}
}