{
  "type": "Feature",
  "properties": {
    "addr:full":"4003 N Main St High Point NC 27265",
    "addr:housenumber":"4003",
    "addr:postcode":"27265",
    "addr:street":"N Main St",
    "iso:country":"US",
    "sg:address":"4003 N Main St",
    "sg:city":"High Point",
    "sg:classifiers":[
        {
            "category":"Personal",
            "subcategory":"Barber",
            "type":"Services"
        }
    ],
    "sg:phone":"+1 336 887 5048",
    "sg:postcode":"27265",
    "sg:province":"NC",
    "sg:tags":[
        "shop"
    ],
    "wof:name":"Ralph's Barber Shop",
    "wof:placetype":"venue"
},
  "geometry": {"coordinates":[-80.057485,36.017674],"type":"Point"}
}