{
  "type": "Feature",
  "properties": {
    "addr:full":"1401 S Main St Kannapolis NC 28081",
    "addr:housenumber":"1401",
    "addr:postcode":"28081",
    "addr:street":"S Main St",
    "iso:country":"US",
    "sg:address":"1401 S Main St",
    "sg:city":"Kannapolis",
    "sg:classifiers":[
        {
            "category":"Real Estate",
            "subcategory":"Real Estate Agent",
            "type":"Services"
        }
    ],
    "sg:phone":"+1 704 932 6139",
    "sg:postcode":"28081",
    "sg:province":"NC",
    "sg:tags":[
        "builder",
        "speculative",
        "broker"
    ],
    "wof:name":"Moss CJ Real Estate Inc",
    "wof:placetype":"venue"
},
  "geometry": {"coordinates":[-80.624067,35.474844],"type":"Point"}
}