{
  "type": "Feature",
  "properties": {
    "iso:country":"US",
    "sg:address":"637 N Spring St",
    "sg:city":"Winston Salem",
    "sg:classifiers":[
        {
            "category":"Real Estate",
            "subcategory":"Architect",
            "type":"Services"
        }
    ],
    "sg:phone":"+1   ",
    "sg:postcode":"27101",
    "sg:province":"NC",
    "sg:tags":[
        "firm",
        "architectural"
    ],
    "wof:name":"Charles A Phillips Pllc",
    "wof:placetype":"venue"
},
  "geometry": {"coordinates":[-80.253997,36.102339],"type":"Point"}
}