{
  "type": "Feature",
  "properties": {
    "addr:full":"117 Gainswood Dr Mooresville NC 28117",
    "addr:housenumber":"117",
    "addr:postcode":"28117",
    "addr:street":"Gainswood Dr",
    "iso:country":"US",
    "sg:address":"117 Gainswood Dr",
    "sg:city":"Mooresville",
    "sg:classifiers":[
        {
            "category":"Building & Trades",
            "subcategory":"Construction",
            "type":"Services"
        }
    ],
    "sg:phone":"+1 704 662 3046",
    "sg:postcode":"28117",
    "sg:province":"NC",
    "sg:tags":[
        "house"
    ],
    "wof:name":"JD Jones Builders",
    "wof:placetype":"venue"
},
  "geometry": {"coordinates":[-80.93929799999999,35.513521],"type":"Point"}
}