{
  "type": "Feature",
  "properties": {
    "addr:full":"1823 W Franklin Blvd Gastonia NC 28052",
    "addr:housenumber":"1823",
    "addr:postcode":"28052",
    "addr:street":"W Franklin Blvd",
    "iso:country":"US",
    "sg:address":"1823 W Franklin Blvd",
    "sg:city":"Gastonia",
    "sg:classifiers":[
        {
            "category":"Wholesale",
            "subcategory":"Auto Parts",
            "type":"Manufacturing & Wholesale Goods"
        }
    ],
    "sg:phone":"+1 704 866 8857",
    "sg:postcode":"28052",
    "sg:province":"NC",
    "sg:tags":[
        "changing",
        "tire",
        "equipment"
    ],
    "wof:name":"Auto Center Equipment",
    "wof:placetype":"venue"
},
  "geometry": {"coordinates":[-81.213528,35.259968],"type":"Point"}
}