{
  "type": "Feature",
  "properties": {
    "addr:full":"2201 S Sterling St Morganton NC 28655",
    "addr:housenumber":"2201",
    "addr:postcode":"28655",
    "addr:street":"S Sterling St",
    "iso:country":"US",
    "sg:address":"2201 S Sterling St",
    "sg:city":"Morganton",
    "sg:classifiers":[
        {
            "category":"Health Services",
            "subcategory":"Clinic",
            "type":"Services"
        }
    ],
    "sg:phone":"+1 828 580 6816",
    "sg:postcode":"28655",
    "sg:province":"NC",
    "sg:tags":[
        "specialty",
        "outpatient"
    ],
    "wof:name":"Rehabilitation Services",
    "wof:placetype":"venue"
},
  "geometry": {"coordinates":[-81.65875800000001,35.724074],"type":"Point"}
}