{
  "type": "Feature",
  "properties": {
    "iso:country":"US",
    "sg:address":"20037 State Hwy 27",
    "sg:city":"Oakboro",
    "sg:classifiers":[
        {
            "category":"Farming",
            "subcategory":"Farm & Veterinary Services",
            "type":"Manufacturing & Wholesale Goods"
        }
    ],
    "sg:phone":"+1 704 485 3954",
    "sg:postcode":"28129",
    "sg:province":"NC",
    "sg:tags":[
        "livestock"
    ],
    "wof:name":"Silo View Farm",
    "wof:placetype":"venue"
},
  "geometry": {"coordinates":[-80.353049,35.267902],"type":"Point"}
}