{
  "type": "Feature",
  "properties": {
    "addr:full":"3313 Stacy Ct Winston Salem NC 27107",
    "addr:housenumber":"3313",
    "addr:postcode":"27107",
    "addr:street":"Stacy Ct",
    "iso:country":"US",
    "sg:address":"3313 Stacy Ct",
    "sg:city":"Winston Salem",
    "sg:classifiers":[
        {
            "category":"Building & Trades",
            "subcategory":"Construction",
            "type":"Services"
        }
    ],
    "sg:phone":"+1 336 254 3165",
    "sg:postcode":"27107",
    "sg:province":"NC",
    "sg:tags":[
        "residential"
    ],
    "wof:name":"Bascom Homes LLC",
    "wof:placetype":"venue"
},
  "geometry": {"coordinates":[-80.12630900000001,36.052194],"type":"Point"}
}