{
  "type": "Feature",
  "properties": {
    "iso:country":"US",
    "sg:address":"210 Fisher Dr",
    "sg:city":"Clinton",
    "sg:classifiers":[
        {
            "category":"Government",
            "subcategory":"Office",
            "type":"Public Place"
        }
    ],
    "sg:phone":"+1 910 592 7787",
    "sg:postcode":"28328",
    "sg:province":"NC",
    "wof:name":"Adult Day Care Sampson County",
    "wof:placetype":"venue"
},
  "geometry": {"coordinates":[-78.322991,35.000043],"type":"Point"}
}