{
  "type": "Feature",
  "properties": {
    "iso:country":"US",
    "sg:address":"1110 Chatham St",
    "sg:city":"Newport",
    "sg:classifiers":[
        {
            "category":"Shopping",
            "subcategory":"Used Merchandise",
            "type":"Retail Goods"
        }
    ],
    "sg:phone":"+1 252 223 2828",
    "sg:postcode":"28570",
    "sg:province":"NC",
    "sg:tags":[
        "flea",
        "market"
    ],
    "wof:name":"Best Little Flea Mart In Nc",
    "wof:placetype":"venue"
},
  "geometry": {"coordinates":[-76.873138,34.818634],"type":"Point"}
}