{
  "type": "Feature",
  "properties": {
    "iso:country":"US",
    "sg:address":"30 Paint Fork Rd",
    "sg:city":"Barnardsville",
    "sg:classifiers":[
        {
            "category":"Manufacturing",
            "subcategory":"Tools & Machinery",
            "type":"Manufacturing & Wholesale Goods"
        }
    ],
    "sg:phone":"+1 828 626 2901",
    "sg:postcode":"28709",
    "sg:province":"NC",
    "sg:tags":[
        "electric",
        "motor"
    ],
    "sg:website":"www.ohioelectricmotors.com",
    "wof:name":"Ohio Electric Motors",
    "wof:placetype":"venue"
},
  "geometry": {"coordinates":[-82.459028,35.776163],"type":"Point"}
}