{
  "type": "Feature",
  "properties": {
    "addr:full":"3135 Wide Country Rd Pfafftown NC 27040",
    "addr:housenumber":"3135",
    "addr:postcode":"27040",
    "addr:street":"Wide Country Rd",
    "iso:country":"US",
    "sg:address":"3135 Wide Country Rd",
    "sg:city":"Pfafftown",
    "sg:classifiers":[
        {
            "category":"Building & Trades",
            "subcategory":"Equipment Rental",
            "type":"Services"
        }
    ],
    "sg:phone":"+1 336 922 9125",
    "sg:postcode":"27040",
    "sg:province":"NC",
    "sg:tags":[
        "party",
        "supply"
    ],
    "wof:name":"A Higher Bounce",
    "wof:placetype":"venue"
},
  "geometry": {"coordinates":[-80.351035,36.204612],"type":"Point"}
}