{
  "type": "Feature",
  "properties": {
    "addr:full":"608 Country Ln Holly Springs NC 27540",
    "addr:housenumber":"608",
    "addr:postcode":"27540",
    "addr:street":"Country Ln",
    "iso:country":"US",
    "sg:address":"608 Country Ln",
    "sg:city":"Holly Springs",
    "sg:classifiers":[
        {
            "category":"Professional",
            "subcategory":"Computer Services",
            "type":"Services"
        }
    ],
    "sg:phone":"+1   ",
    "sg:postcode":"27540",
    "sg:province":"NC",
    "sg:tags":[
        "design",
        "system",
        "related"
    ],
    "wof:name":"Carter Hill Technologies LLC",
    "wof:placetype":"venue"
},
  "geometry": {"coordinates":[-78.838778,35.643313],"type":"Point"}
}