{
  "type": "Feature",
  "properties": {
    "iso:country":"US",
    "sg:address":"200 Wellesley Trade Ln",
    "sg:city":"Cary",
    "sg:classifiers":[
        {
            "category":"Health Services",
            "subcategory":"Doctor",
            "type":"Services"
        }
    ],
    "sg:phone":"+1 919 363 7546",
    "sg:postcode":"27519",
    "sg:province":"NC",
    "sg:tags":[
        "dermatologist"
    ],
    "sg:website":"www.caryskincenter.com",
    "wof:name":"Cary Skin Center",
    "wof:placetype":"venue"
},
  "geometry": {"coordinates":[-78.871399,35.789001],"type":"Point"}
}