{
  "type": "Feature",
  "properties": {
    "addr:full":"1100 Falls Creek Ln Charlotte NC 28209",
    "addr:housenumber":"1100",
    "addr:postcode":"28209",
    "addr:street":"Falls Creek Ln",
    "iso:country":"US",
    "sg:address":"1100 Falls Creek Ln",
    "sg:city":"Charlotte",
    "sg:classifiers":[
        {
            "category":"Real Estate",
            "subcategory":"Real Estate Operator",
            "type":"Services"
        }
    ],
    "sg:phone":"+1 704 527 4606",
    "sg:postcode":"28209",
    "sg:province":"NC",
    "sg:tags":[
        "apartment"
    ],
    "wof:name":"Camden Timber Creek Apts",
    "wof:placetype":"venue"
},
  "geometry": {"coordinates":[-80.863072,35.178563],"type":"Point"}
}