{
  "type": "Feature",
  "properties": {
    "iso:country":"US",
    "sg:address":"20109 Knox Rd",
    "sg:city":"Cornelius",
    "sg:classifiers":[
        {
            "category":"Health Services",
            "subcategory":"Health Practitioner",
            "type":"Services"
        }
    ],
    "sg:phone":"+1 704 987 0006",
    "sg:postcode":"28031",
    "sg:province":"NC",
    "wof:name":"Sapphire Spa & Retreat",
    "wof:placetype":"venue"
},
  "geometry": {"coordinates":[-80.877853,35.486928],"type":"Point"}
}