{
  "type": "Feature",
  "properties": {
    "iso:country":"US",
    "sg:address":"1700 N Market St",
    "sg:city":"Washington",
    "sg:classifiers":[
        {
            "category":"Organizations",
            "subcategory":"Religious Organization",
            "type":"Services"
        }
    ],
    "sg:phone":"+1 252 974 7679",
    "sg:postcode":"27889",
    "sg:province":"NC",
    "wof:name":"Washington Seventh Day Church",
    "wof:placetype":"venue"
},
  "geometry": {"coordinates":[-77.045096,35.556699],"type":"Point"}
}