{
  "type": "Feature",
  "properties": {
    "addr:full":"318 Harris Ave Raeford NC 28376",
    "addr:housenumber":"318",
    "addr:postcode":"28376",
    "addr:street":"Harris Ave",
    "iso:country":"US",
    "sg:address":"318 Harris Ave",
    "sg:city":"Raeford",
    "sg:classifiers":[
        {
            "category":"Home & Garden",
            "subcategory":"Furniture",
            "type":"Retail Goods"
        }
    ],
    "sg:phone":"+1 910 848 2188",
    "sg:postcode":"28376",
    "sg:province":"NC",
    "wof:name":"Jack's Furniture",
    "wof:placetype":"venue"
},
  "geometry": {"coordinates":[-79.22959299999999,34.9777],"type":"Point"}
}