{
  "type": "Feature",
  "properties": {
    "addr:full":"2366 E Boiling Spring Rd Southport NC 28461",
    "addr:housenumber":"2366",
    "addr:postcode":"28461",
    "addr:street":"E Boiling Spring Rd",
    "iso:country":"US",
    "sg:address":"2366 E Boiling Spring Rd",
    "sg:city":"Southport",
    "sg:classifiers":[
        {
            "category":"Building & Trades",
            "subcategory":"Construction",
            "type":"Services"
        }
    ],
    "sg:phone":"+1 910 845 8759",
    "sg:postcode":"28461",
    "sg:province":"NC",
    "sg:tags":[
        "general",
        "contractor"
    ],
    "wof:name":"Carolina Coast Construction",
    "wof:placetype":"venue"
},
  "geometry": {"coordinates":[-78.03361099999999,34.063155],"type":"Point"}
}