{
  "type": "Feature",
  "properties": {
    "addr:full":"175 W New Hampshire Ave Southern Pines NC 28387",
    "addr:housenumber":"175",
    "addr:postcode":"28387",
    "addr:street":"W New Hampshire Ave",
    "iso:country":"US",
    "sg:address":"175 W New Hampshire Ave",
    "sg:city":"Southern Pines",
    "sg:classifiers":[
        {
            "category":"Health Services",
            "subcategory":"Health Practitioner",
            "type":"Services"
        }
    ],
    "sg:phone":"+1   ",
    "sg:postcode":"28387",
    "sg:province":"NC",
    "wof:name":"Keeping In Touch",
    "wof:placetype":"venue"
},
  "geometry": {"coordinates":[-79.39154000000001,35.17565],"type":"Point"}
}