{
  "type": "Feature",
  "properties": {
    "iso:country":"US",
    "sg:address":"1761 W Williams St",
    "sg:city":"Apex",
    "sg:classifiers":[
        {
            "category":"Restaurant",
            "type":"Food & Drink"
        }
    ],
    "sg:phone":"+1 919 363 6453",
    "sg:postcode":"27523",
    "sg:province":"NC",
    "sg:website":"www.jerseymikes.com",
    "wof:name":"Jersey Mike's Giant Submarines & Catering",
    "wof:placetype":"venue"
},
  "geometry": {"coordinates":[-78.87599899999999,35.760201],"type":"Point"}
}