{
  "type": "Feature",
  "properties": {
    "iso:country":"US",
    "sg:address":"6148 Brookshire Blvd",
    "sg:city":"Charlotte",
    "sg:classifiers":[
        {
            "category":"Building & Trades",
            "subcategory":"Cleaning & Sanitation",
            "type":"Services"
        },
        {
            "category":"Retail",
            "subcategory":"Laundry & Dry Cleaning",
            "type":"Services"
        },
        {
            "category":"Home & Garden",
            "subcategory":"Carpets & Floor Coverings",
            "type":"Retail Goods"
        }
    ],
    "sg:phone":"+1 704 393 7890",
    "sg:postcode":"28216",
    "sg:province":"NC",
    "sg:tags":[
        "cleaner",
        "fire",
        "cleaners-water",
        "damage",
        "rug",
        "water",
        "extraction",
        "restoration",
        "remediation",
        "mold"
    ],
    "sg:website":"http://www.servpronwcharlotte.com",
    "wof:name":"Servpro Of Northwest Charlotte",
    "wof:placetype":"venue"
},
  "geometry": {"coordinates":[-80.904419,35.284383],"type":"Point"}
}