{
  "type": "Feature",
  "properties": {
    "addr:full":"1214 Knox St Statesville NC 28677",
    "addr:housenumber":"1214",
    "addr:postcode":"28677",
    "addr:street":"Knox St",
    "iso:country":"US",
    "sg:address":"1214 Knox St",
    "sg:city":"Statesville",
    "sg:classifiers":[
        {
            "category":"Building & Trades",
            "subcategory":"Cleaning & Sanitation",
            "type":"Services"
        }
    ],
    "sg:phone":"+1 704 872 1536",
    "sg:postcode":"28677",
    "sg:province":"NC",
    "sg:tags":[
        "janitor"
    ],
    "wof:name":"Willow Inc",
    "wof:placetype":"venue"
},
  "geometry": {"coordinates":[-80.867062,35.794244],"type":"Point"}
}