{
  "type": "Feature",
  "properties": {
    "addr:full":"32 Twin Oaks Dr Castle Hayne NC 28429",
    "addr:housenumber":"32",
    "addr:postcode":"28429",
    "addr:street":"Twin Oaks Dr",
    "iso:country":"US",
    "sg:address":"32 Twin Oaks Dr",
    "sg:city":"Castle Hayne",
    "sg:classifiers":[
        {
            "category":"Restaurant",
            "type":"Food & Drink"
        }
    ],
    "sg:phone":"+1 910 675 1512",
    "sg:postcode":"28429",
    "sg:province":"NC",
    "sg:tags":[
        "eating"
    ],
    "wof:name":"Personal Touch Catering Servic",
    "wof:placetype":"venue"
},
  "geometry": {"coordinates":[-77.883855,34.338835],"type":"Point"}
}