{
  "type": "Feature",
  "properties": {
    "addr:full":"3111 Yanceyville St Greensboro NC 27405",
    "addr:housenumber":"3111",
    "addr:postcode":"27405",
    "addr:street":"Yanceyville St",
    "iso:country":"US",
    "sg:address":"3111 Yanceyville St",
    "sg:city":"Greensboro",
    "sg:classifiers":[
        {
            "category":"Food & Beverages",
            "subcategory":"Groceries & Convenience Stores",
            "type":"Retail Goods"
        }
    ],
    "sg:phone":"+1 336 621 2004",
    "sg:postcode":"27405",
    "sg:province":"NC",
    "sg:tags":[
        "grocer"
    ],
    "wof:name":"Save-A-Lot",
    "wof:placetype":"venue"
},
  "geometry": {"coordinates":[-79.775295,36.113404],"type":"Point"}
}