{
  "type": "Feature",
  "properties": {
    "iso:country":"US",
    "sg:address":"1469 Zion Church Rd",
    "sg:city":"Hickory",
    "sg:classifiers":[
        {
            "category":"Building & Trades",
            "subcategory":"Plumbing",
            "type":"Services"
        }
    ],
    "sg:phone":"+1 828 294 4746",
    "sg:postcode":"28602",
    "sg:province":"NC",
    "sg:tags":[
        "contractor"
    ],
    "wof:name":"T Setzer Plumbing and Pump",
    "wof:placetype":"venue"
},
  "geometry": {"coordinates":[-81.346722,35.681505],"type":"Point"}
}