{
  "type": "Feature",
  "properties": {
    "iso:country":"US",
    "sg:address":"914 Tyrrell Rd",
    "sg:city":"Raleigh",
    "sg:classifiers":[
        {
            "category":"Insurance",
            "subcategory":"Insurance Agent",
            "type":"Services"
        }
    ],
    "sg:phone":"+1 919 781 8888",
    "sg:postcode":"27609",
    "sg:province":"NC",
    "wof:name":"Senior Health Plans",
    "wof:placetype":"venue"
},
  "geometry": {"coordinates":[-78.656533,35.841701],"type":"Point"}
}