{
  "type": "Feature",
  "properties": {
    "addr:full":"12 Turner St Raleigh NC 27607",
    "addr:housenumber":"12",
    "addr:postcode":"27607",
    "addr:street":"Turner St",
    "iso:country":"US",
    "sg:address":"12 Turner St",
    "sg:city":"Raleigh",
    "sg:classifiers":[
        {
            "category":"Shopping",
            "subcategory":"Computers & Home Electronics",
            "type":"Retail Goods"
        }
    ],
    "sg:phone":"+1 919 828 3400",
    "sg:postcode":"27607",
    "sg:province":"NC",
    "sg:tags":[
        "audio"
    ],
    "sg:website":"www.sirtage.com",
    "wof:name":"Sirtage Av/Video/Sound Systems",
    "wof:placetype":"venue"
},
  "geometry": {"coordinates":[-78.68461000000001,35.791842],"type":"Point"}
}