{
  "type": "Feature",
  "properties": {
    "iso:country":"US",
    "sg:address":"1865 Hendersonville Rd",
    "sg:city":"Asheville",
    "sg:classifiers":[
        {
            "category":"Health Services",
            "subcategory":"Chiropractor",
            "type":"Services"
        }
    ],
    "sg:phone":"+1 828 230 2795",
    "sg:postcode":"28803",
    "sg:province":"NC",
    "wof:name":"South Asheville Chiropractic",
    "wof:placetype":"venue"
},
  "geometry": {"coordinates":[-82.521254,35.498445],"type":"Point"}
}