{
  "type": "Feature",
  "properties": {
    "addr:full":"1195 Chicken Farm Rd Dunn NC 28334",
    "addr:housenumber":"1195",
    "addr:postcode":"28334",
    "addr:street":"Chicken Farm Rd",
    "iso:country":"US",
    "sg:address":"1195 Chicken Farm Rd",
    "sg:city":"Dunn",
    "sg:classifiers":[
        {
            "category":"Manufacturing",
            "subcategory":"Textiles",
            "type":"Manufacturing & Wholesale Goods"
        }
    ],
    "sg:phone":"+1 910 892 2317",
    "sg:postcode":"28334",
    "sg:province":"NC",
    "sg:tags":[
        "cotton"
    ],
    "wof:name":"Alsey B Johnson",
    "wof:placetype":"venue"
},
  "geometry": {"coordinates":[-78.62315599999999,35.301717],"type":"Point"}
}