{
  "type": "Feature",
  "properties": {
    "iso:country":"US",
    "sg:address":"1301 Combs St",
    "sg:city":"Shelby",
    "sg:classifiers":[
        {
            "category":"Building & Trades",
            "subcategory":"Construction",
            "type":"Services"
        }
    ],
    "sg:phone":"+1 704 482 4859",
    "sg:postcode":"28152",
    "sg:province":"NC",
    "sg:tags":[
        "industrial"
    ],
    "wof:name":"H&J Contractors",
    "wof:placetype":"venue"
},
  "geometry": {"coordinates":[-81.54481699999999,35.270437],"type":"Point"}
}