{
  "type": "Feature",
  "properties": {
    "iso:country":"US",
    "sg:address":"1015 Wave Rd",
    "sg:city":"Chapel Hill",
    "sg:classifiers":[
        {
            "category":"Shopping",
            "subcategory":"Optical Goods",
            "type":"Retail Goods"
        }
    ],
    "sg:phone":"+1 919 932 9288",
    "sg:postcode":"27517",
    "sg:province":"NC",
    "sg:tags":[
        "optician"
    ],
    "wof:name":"Zeiss Inc",
    "wof:placetype":"venue"
},
  "geometry": {"coordinates":[-79.06845800000001,35.871081],"type":"Point"}
}