{
  "type": "Feature",
  "properties": {
    "addr:full":"202 Shelton St Carrboro NC 27510",
    "addr:housenumber":"202",
    "addr:postcode":"27510",
    "addr:street":"Shelton St",
    "iso:country":"US",
    "sg:address":"202 Shelton St",
    "sg:city":"Carrboro",
    "sg:classifiers":[
        {
            "category":"Professional",
            "subcategory":"Research",
            "type":"Services"
        }
    ],
    "sg:phone":"+1   ",
    "sg:postcode":"27510",
    "sg:province":"NC",
    "sg:tags":[
        "electronics"
    ],
    "wof:name":"Sigma Analog Research",
    "wof:placetype":"venue"
},
  "geometry": {"coordinates":[-79.075093,35.914061],"type":"Point"}
}