{
  "type": "Feature",
  "properties": {
    "addr:full":"6413 Smithwood Rd Liberty NC 27298",
    "addr:housenumber":"6413",
    "addr:postcode":"27298",
    "addr:street":"Smithwood Rd",
    "iso:country":"US",
    "sg:address":"6413 Smithwood Rd",
    "sg:city":"Liberty",
    "sg:phone":"+1 336 685 4875",
    "sg:postcode":"27298",
    "sg:province":"NC",
    "sg:tags":[
        "farm",
        "tobacco"
    ],
    "wof:name":"Humble Hurman",
    "wof:placetype":"venue"
},
  "geometry": {"coordinates":[-79.578276,35.913489],"type":"Point"}
}