{
  "type": "Feature",
  "properties": {
    "addr:full":"1400 Metals Dr Charlotte NC 28206",
    "addr:housenumber":"1400",
    "addr:postcode":"28206",
    "addr:street":"Metals Dr",
    "iso:country":"US",
    "sg:address":"1400 Metals Dr",
    "sg:city":"Charlotte",
    "sg:classifiers":[
        {
            "category":"Retail",
            "subcategory":"Auto Repair",
            "type":"Services"
        }
    ],
    "sg:phone":"+1 704 598 1066",
    "sg:postcode":"28206",
    "sg:province":"NC",
    "sg:tags":[
        "automobile",
        "truck",
        "general"
    ],
    "wof:name":"Commercial Service Center Auto",
    "wof:placetype":"venue"
},
  "geometry": {"coordinates":[-80.809483,35.272706],"type":"Point"}
}