{
  "type": "Feature",
  "properties": {
    "addr:full":"714 Greenville Blvd SE Greenville NC 27858",
    "addr:housenumber":"714",
    "addr:postcode":"27858",
    "addr:street":"Greenville Blvd Se",
    "iso:country":"US",
    "sg:address":"714 Greenville Blvd SE",
    "sg:city":"Greenville",
    "sg:classifiers":[
        {
            "category":"Shopping",
            "subcategory":"Clothing, Apparel, & Fashions",
            "type":"Retail Goods"
        }
    ],
    "sg:phone":"+1 252 321 4007",
    "sg:postcode":"27858",
    "sg:province":"NC",
    "sg:tags":[
        "restaurant"
    ],
    "sg:website":"http://www.express.com/",
    "wof:name":"Express",
    "wof:placetype":"venue"
},
  "geometry": {"coordinates":[-77.369743,35.58679],"type":"Point"}
}