{
  "type": "Feature",
  "properties": {
    "iso:country":"US",
    "sg:address":"6603 Earnhardt Dr",
    "sg:city":"Greensboro",
    "sg:classifiers":[
        {
            "category":"Building & Trades",
            "subcategory":"Cleaning & Sanitation",
            "type":"Services"
        }
    ],
    "sg:phone":"+1 336 218 0441",
    "sg:postcode":"27410",
    "sg:province":"NC",
    "sg:tags":[
        "janitor"
    ],
    "wof:name":"Sunshine Cleaning Svc Inc",
    "wof:placetype":"venue"
},
  "geometry": {"coordinates":[-79.90447399999999,36.09031],"type":"Point"}
}