{
  "type": "Feature",
  "properties": {
    "addr:full":"813 N Bridge St Elkin NC 28621",
    "addr:housenumber":"813",
    "addr:postcode":"28621",
    "addr:street":"N Bridge St",
    "iso:country":"US",
    "sg:address":"813 N Bridge St",
    "sg:city":"Elkin",
    "sg:classifiers":[
        {
            "category":"Communications",
            "subcategory":"Radio Station",
            "type":"Services"
        }
    ],
    "sg:phone":"+1 336 835 2511",
    "sg:postcode":"28621",
    "sg:province":"NC",
    "sg:tags":[
        "company",
        "broadcasting"
    ],
    "wof:name":"WIFM",
    "wof:placetype":"venue"
},
  "geometry": {"coordinates":[-80.847883,36.258308],"type":"Point"}
}