{
  "type": "Feature",
  "properties": {
    "addr:full":"2222 S Fayetteville St Asheboro NC 27205",
    "addr:housenumber":"2222",
    "addr:postcode":"27205",
    "addr:street":"S Fayetteville St",
    "iso:country":"US",
    "sg:address":"2222 S Fayetteville St",
    "sg:city":"Asheboro",
    "sg:classifiers":[
        {
            "category":"Government",
            "subcategory":"Office",
            "type":"Public Place"
        }
    ],
    "sg:phone":"+1 336 318 6262",
    "sg:postcode":"27205",
    "sg:province":"NC",
    "sg:tags":[
        "county",
        "program"
    ],
    "wof:name":"Environmental Health",
    "wof:placetype":"venue"
},
  "geometry": {"coordinates":[-79.819351,35.676239],"type":"Point"}
}