{
  "type": "Feature",
  "properties": {
    "addr:full":"108 S Randolph St Rockingham NC 28379",
    "addr:housenumber":"108",
    "addr:postcode":"28379",
    "addr:street":"S Randolph St",
    "iso:country":"US",
    "sg:address":"108 S Randolph St",
    "sg:city":"Rockingham",
    "sg:classifiers":[
        {
            "category":"Social Services",
            "subcategory":"Child Care",
            "type":"Services"
        }
    ],
    "sg:phone":"+1 910 997 3773",
    "sg:postcode":"28379",
    "sg:province":"NC",
    "wof:name":"Richmond County Partnership",
    "wof:placetype":"venue"
},
  "geometry": {"coordinates":[-79.771135,34.939544],"type":"Point"}
}