{
  "type": "Feature",
  "properties": {
    "iso:country":"US",
    "sg:address":"6240 Robin Hollow Dr",
    "sg:city":"Charlotte",
    "sg:classifiers":[
        {
            "category":"Building & Trades",
            "subcategory":"Construction",
            "type":"Services"
        }
    ],
    "sg:phone":"+1 704 573 2454",
    "sg:postcode":"28227",
    "sg:province":"NC",
    "sg:tags":[
        "home",
        "builder"
    ],
    "wof:name":"Dublin Homes",
    "wof:placetype":"venue"
},
  "geometry": {"coordinates":[-80.671519,35.168408],"type":"Point"}
}