{
  "type": "Feature",
  "properties": {
    "iso:country":"US",
    "sg:address":"252 Concord Pkwy S",
    "sg:city":"Concord",
    "sg:phone":"+1 704 788 7000",
    "sg:postcode":"28027",
    "sg:province":"NC",
    "sg:website":"http://charlotte.citysearch.com/profile/external/6239200/concord_nc/precision_tune_auto_care.html?publisher=yellowpages&reference_id=1&placement=ypwebsitemip",
    "wof:name":"Precision Tune Auto Care",
    "wof:placetype":"venue"
},
  "geometry": {"coordinates":[-80.608503,35.399992],"type":"Point"}
}