{
  "type": "Feature",
  "properties": {
    "addr:full":"4280 US-15 501 Carthage NC 28327",
    "addr:housenumber":"4280;501",
    "addr:postcode":"28327",
    "addr:street":"Us-15",
    "iso:country":"US",
    "sg:address":"4280 US-15 501",
    "sg:city":"Carthage",
    "sg:classifiers":[
        {
            "category":"Restaurant",
            "type":"Food & Drink"
        }
    ],
    "sg:menulink":"http://www.allmenus.com/nc/carthage/73314-pizza-hut/menu/",
    "sg:phone":"+1 910 947 2552",
    "sg:postcode":"28327",
    "sg:province":"NC",
    "sg:tags":[
        "american",
        "pizza"
    ],
    "wof:name":"Pizza Hut",
    "wof:placetype":"venue"
},
  "geometry": {"coordinates":[-79.403289,35.330275],"type":"Point"}
}