{
  "type": "Feature",
  "properties": {
    "iso:country":"US",
    "sg:address":"203 Browers Mill Rd",
    "sg:city":"Eagle Springs",
    "sg:classifiers":[
        {
            "category":"Personal",
            "subcategory":"Beauty Salon",
            "type":"Services"
        }
    ],
    "sg:phone":"+1   ",
    "sg:postcode":"27242",
    "sg:province":"NC",
    "sg:tags":[
        "shop"
    ],
    "wof:name":"Davis Beauty Shop",
    "wof:placetype":"venue"
},
  "geometry": {"coordinates":[-79.675308,35.386174],"type":"Point"}
}