{
  "type": "Feature",
  "properties": {
    "addr:full":"3725 Flowerfield Rd Charlotte NC 28210",
    "addr:postcode":"3725;28210",
    "addr:street":"Flowerfield Rd",
    "iso:country":"US",
    "sg:address":"3725 Flowerfield Rd",
    "sg:city":"Charlotte",
    "sg:classifiers":[
        {
            "category":"Manufacturing",
            "subcategory":"Tools & Machinery",
            "type":"Manufacturing & Wholesale Goods"
        }
    ],
    "sg:phone":"+1 704 553 1674",
    "sg:postcode":"28210",
    "sg:province":"NC",
    "sg:tags":[
        "equipment",
        "electric"
    ],
    "wof:name":"C Alley & Assoc",
    "wof:placetype":"venue"
},
  "geometry": {"coordinates":[-80.847114,35.138372],"type":"Point"}
}