{
  "type": "Feature",
  "properties": {
    "iso:country":"US",
    "sg:address":"230 E Water St",
    "sg:city":"Lincolnton",
    "sg:classifiers":[
        {
            "category":"Education",
            "subcategory":"Dance Studio",
            "type":"Public Place"
        }
    ],
    "sg:phone":"+1 704 735 2277",
    "sg:postcode":"28092",
    "sg:province":"NC",
    "sg:tags":[
        "instruction",
        "dancing"
    ],
    "wof:name":"Alternative Steps Dance Studio",
    "wof:placetype":"venue"
},
  "geometry": {"coordinates":[-81.254234,35.471369],"type":"Point"}
}