{
  "type": "Feature",
  "properties": {
    "iso:country":"US",
    "sg:address":"102 Statesville Rd",
    "sg:city":"Huntersville",
    "sg:classifiers":[
        {
            "category":"Shopping",
            "subcategory":"Bicycles & Sporting Goods",
            "type":"Retail Goods"
        }
    ],
    "sg:phone":"+1 704 948 6677",
    "sg:postcode":"28078",
    "sg:province":"NC",
    "sg:tags":[
        "equipment",
        "golf",
        "supply"
    ],
    "wof:name":"Golf USA",
    "wof:placetype":"venue"
},
  "geometry": {"coordinates":[-80.85539799999999,35.411577],"type":"Point"}
}