{
  "type": "Feature",
  "properties": {
    "addr:full":"107 Airport Rd Kinston NC 28501",
    "addr:housenumber":"107",
    "addr:postcode":"28501",
    "addr:street":"Airport Rd",
    "iso:country":"US",
    "sg:address":"107 Airport Rd",
    "sg:city":"Kinston",
    "sg:classifiers":[
        {
            "category":"Health Services",
            "subcategory":"Doctor",
            "type":"Services"
        }
    ],
    "sg:phone":"+1 252 527 4146",
    "sg:postcode":"28501",
    "sg:province":"NC",
    "sg:tags":[
        "medical"
    ],
    "wof:name":"Joseph E Agsten MD",
    "wof:placetype":"venue"
},
  "geometry": {"coordinates":[-77.583359,35.292999],"type":"Point"}
}