{
  "type": "Feature",
  "properties": {
    "iso:country":"US",
    "sg:address":"610 Fontana Blvd",
    "sg:city":"Havelock",
    "sg:classifiers":[
        {
            "category":"Social Services",
            "subcategory":"Child Care",
            "type":"Services"
        }
    ],
    "sg:phone":"+1 252 447 5437",
    "sg:postcode":"28532",
    "sg:province":"NC",
    "sg:website":"www.childcarenetwork.net",
    "wof:name":"Child Care Network Inc",
    "wof:placetype":"venue"
},
  "geometry": {"coordinates":[-76.88976,34.882332],"type":"Point"}
}