{
  "type": "Feature",
  "properties": {
    "iso:country":"US",
    "sg:address":"1218 Industrial Dr",
    "sg:city":"Matthews",
    "sg:classifiers":[
        {
            "category":"Home & Garden",
            "subcategory":"Carpets & Floor Coverings",
            "type":"Retail Goods"
        }
    ],
    "sg:phone":"+1 704 847 3913",
    "sg:postcode":"28105",
    "sg:province":"NC",
    "wof:name":"Georgia Carpet Warehouse Inc",
    "wof:placetype":"venue"
},
  "geometry": {"coordinates":[-80.72837699999999,35.131014],"type":"Point"}
}