{
  "type": "Feature",
  "properties": {
    "iso:country":"US",
    "sg:address":"1431 Nicholas St",
    "sg:city":"Henderson",
    "sg:classifiers":[
        {
            "category":"Home & Garden",
            "subcategory":"Building Materials",
            "type":"Retail Goods"
        }
    ],
    "sg:phone":"+1 252 430 0030",
    "sg:postcode":"27536",
    "sg:province":"NC",
    "sg:tags":[
        "lumber"
    ],
    "wof:name":"Idaho Timber Corp Of NC",
    "wof:placetype":"venue"
},
  "geometry": {"coordinates":[-78.40628599999999,36.311325],"type":"Point"}
}