{
  "type": "Feature",
  "properties": {
    "addr:full":"6207 Rockwell Dr Indian Trail NC 28079",
    "addr:housenumber":"6207",
    "addr:postcode":"28079",
    "addr:street":"Rockwell Dr",
    "iso:country":"US",
    "sg:address":"6207 Rockwell Dr",
    "sg:city":"Indian Trail",
    "sg:classifiers":[
        {
            "category":"Freight",
            "type":"Transportation"
        }
    ],
    "sg:phone":"+1 704 882 4533",
    "sg:postcode":"28079",
    "sg:province":"NC",
    "sg:tags":[
        "operator",
        "trucking"
    ],
    "wof:name":"Landstar",
    "wof:placetype":"venue"
},
  "geometry": {"coordinates":[-80.63475200000001,35.115089],"type":"Point"}
}