{
  "type": "Feature",
  "properties": {
    "addr:full":"715 Doak St Thomasville NC 27360",
    "addr:housenumber":"715",
    "addr:postcode":"27360",
    "addr:street":"Doak St",
    "iso:country":"US",
    "sg:address":"715 Doak St",
    "sg:city":"Thomasville",
    "sg:classifiers":[
        {
            "category":"Building & Trades",
            "subcategory":"Landscaping Services",
            "type":"Services"
        }
    ],
    "sg:phone":"+1 336 475 7561",
    "sg:postcode":"27360",
    "sg:province":"NC",
    "sg:tags":[
        "landscape",
        "contractor"
    ],
    "wof:name":"Whitaker Junior Landscaping",
    "wof:placetype":"venue"
},
  "geometry": {"coordinates":[-80.097759,35.892814],"type":"Point"}
}