{
  "type": "Feature",
  "properties": {
    "iso:country":"US",
    "sg:address":"817 E Morehead St",
    "sg:city":"Charlotte",
    "sg:classifiers":[
        {
            "category":"Banks & Credit Unions",
            "subcategory":"Bank",
            "type":"Services"
        }
    ],
    "sg:phone":"+1 704 358 8000",
    "sg:postcode":"28202",
    "sg:province":"NC",
    "sg:tags":[
        "broker",
        "mortgage"
    ],
    "wof:name":"U S Mortgage Group Inc",
    "wof:placetype":"venue"
},
  "geometry": {"coordinates":[-80.8449,35.21424],"type":"Point"}
}