{
  "type": "Feature",
  "properties": {
    "addr:full":"150 Burton Ln Piney Creek NC 28663",
    "addr:housenumber":"150",
    "addr:postcode":"28663",
    "addr:street":"Burton Ln",
    "iso:country":"US",
    "sg:address":"150 Burton Ln",
    "sg:city":"Piney Creek",
    "sg:classifiers":[
        {
            "category":"Farming",
            "subcategory":"Dairy Farm",
            "type":"Manufacturing & Wholesale Goods"
        }
    ],
    "sg:phone":"+1 336 359 2765",
    "sg:postcode":"28663",
    "sg:province":"NC",
    "wof:name":"Burton Osborne Dairy Inc",
    "wof:placetype":"venue"
},
  "geometry": {"coordinates":[-81.322773,36.546264],"type":"Point"}
}