{
  "type": "Feature",
  "properties": {
    "iso:country":"US",
    "sg:address":"800 Atlanta Ave",
    "sg:city":"Carolina Beach",
    "sg:classifiers":[
        {
            "category":"Home & Garden",
            "subcategory":"Building Materials",
            "type":"Retail Goods"
        }
    ],
    "sg:phone":"+1 910 458 8795",
    "sg:postcode":"28428",
    "sg:province":"NC",
    "wof:name":"Lynda Hicks & Chicken",
    "wof:placetype":"venue"
},
  "geometry": {"coordinates":[-77.907276,34.033409],"type":"Point"}
}