{
  "type": "Feature",
  "properties": {
    "iso:country":"US",
    "sg:address":"900 NE Maynard Rd",
    "sg:city":"Cary",
    "sg:classifiers":[
        {
            "category":"Banks & Credit Unions",
            "subcategory":"Bank",
            "type":"Services"
        }
    ],
    "sg:phone":"+1 919 460 1326",
    "sg:postcode":"27513",
    "sg:province":"NC",
    "sg:tags":[
        "cashing",
        "check"
    ],
    "wof:name":"Nationwide Money",
    "wof:placetype":"venue"
},
  "geometry": {"coordinates":[-78.76755,35.801327],"type":"Point"}
}