{
  "type": "Feature",
  "properties": {
    "addr:full":"6415 Lakeview Rd Charlotte NC 28269",
    "addr:housenumber":"6415",
    "addr:postcode":"28269",
    "addr:street":"Lakeview Rd",
    "iso:country":"US",
    "sg:address":"6415 Lakeview Rd",
    "sg:city":"Charlotte",
    "sg:classifiers":[
        {
            "category":"Building & Trades",
            "subcategory":"Construction",
            "type":"Services"
        }
    ],
    "sg:phone":"+1 704 598 0818",
    "sg:postcode":"28269",
    "sg:province":"NC",
    "sg:tags":[
        "general",
        "contractor"
    ],
    "sg:website":"www.hallcontracting.com",
    "wof:name":"Hall Contracting Corp",
    "wof:placetype":"venue"
},
  "geometry": {"coordinates":[-80.828136,35.33907],"type":"Point"}
}