{
  "type": "Feature",
  "properties": {
    "addr:full":"3469 US Hwy 601 S Concord NC 28025",
    "addr:housenumber":"3469",
    "addr:postcode":"28025",
    "addr:street":"Us Hwy 601 S",
    "iso:country":"US",
    "sg:address":"3469 US Hwy 601 S",
    "sg:city":"Concord",
    "sg:classifiers":[
        {
            "category":"Retail",
            "subcategory":"Laundry & Dry Cleaning",
            "type":"Services"
        }
    ],
    "sg:phone":"+1 704 786 5542",
    "sg:postcode":"28025",
    "sg:province":"NC",
    "sg:tags":[
        "drycleaning",
        "plant",
        "power"
    ],
    "wof:name":"County Cleaners",
    "wof:placetype":"venue"
},
  "geometry": {"coordinates":[-80.549311,35.370325],"type":"Point"}
}