{
  "type": "Feature",
  "properties": {
    "iso:country":"US",
    "sg:address":"98 S Main St",
    "sg:city":"Granite Falls",
    "sg:classifiers":[
        {
            "category":"Professional",
            "subcategory":"Employment Agencies",
            "type":"Services"
        }
    ],
    "sg:phone":"+1   ",
    "sg:postcode":"28630",
    "sg:province":"NC",
    "sg:tags":[
        "building",
        "help",
        "maintenance",
        "supply"
    ],
    "wof:name":"Regency Cleaning Professionals",
    "wof:placetype":"venue"
},
  "geometry": {"coordinates":[-81.426323,35.79246],"type":"Point"}
}