{
  "type": "Feature",
  "properties": {
    "addr:full":"309 Saint Matthews Rd Erwin NC 28339",
    "addr:housenumber":"309",
    "addr:postcode":"28339",
    "addr:street":"Saint Matthews Rd",
    "iso:country":"US",
    "sg:address":"309 Saint Matthews Rd",
    "sg:city":"Erwin",
    "sg:classifiers":[
        {
            "category":"Professional",
            "subcategory":"Accounting & Tax Preparation",
            "type":"Services"
        }
    ],
    "sg:phone":"+1   ",
    "sg:postcode":"28339",
    "sg:province":"NC",
    "sg:tags":[
        "return"
    ],
    "wof:name":"Mityco Inc",
    "wof:placetype":"venue"
},
  "geometry": {"coordinates":[-78.651132,35.324626],"type":"Point"}
}