{
  "type": "Feature",
  "properties": {
    "addr:full":"4707 Revere Rd Durham NC 27713",
    "addr:housenumber":"4707",
    "addr:postcode":"27713",
    "addr:street":"Revere Rd",
    "iso:country":"US",
    "sg:address":"4707 Revere Rd",
    "sg:city":"Durham",
    "sg:classifiers":[
        {
            "category":"Professional",
            "subcategory":"Advertising",
            "type":"Services"
        },
        {
            "category":"Wholesale",
            "subcategory":"Auto Parts",
            "type":"Manufacturing & Wholesale Goods"
        }
    ],
    "sg:phone":"+1 919 544 4334",
    "sg:postcode":"27713",
    "sg:province":"NC",
    "sg:tags":[
        "equipment",
        "distribution",
        "automotive"
    ],
    "wof:name":"D J Enterprises",
    "wof:placetype":"venue"
},
  "geometry": {"coordinates":[-78.911339,35.901677],"type":"Point"}
}