{
  "type": "Feature",
  "properties": {
    "addr:full":"2403 US Hwy 52 Albemarle NC 28001",
    "addr:housenumber":"2403",
    "addr:postcode":"28001",
    "addr:street":"Us Hwy 52",
    "iso:country":"US",
    "sg:address":"2403 US Hwy 52",
    "sg:city":"Albemarle",
    "sg:classifiers":[
        {
            "category":"Utilities",
            "subcategory":"Cable",
            "type":"Services"
        }
    ],
    "sg:phone":"+1 704 938 5156",
    "sg:postcode":"28001",
    "sg:province":"NC",
    "sg:tags":[
        "television"
    ],
    "wof:name":"Time Warner",
    "wof:placetype":"venue"
},
  "geometry": {"coordinates":[-80.200688,35.397366],"type":"Point"}
}