{
  "type": "Feature",
  "properties": {
    "addr:full":"3080 Richlands Hwy Jacksonville NC 28540",
    "addr:postcode":"3080;28540",
    "addr:street":"Richlands Hwy",
    "iso:country":"US",
    "sg:address":"3080 Richlands Hwy",
    "sg:city":"Jacksonville",
    "sg:classifiers":[
        {
            "category":"Shopping",
            "subcategory":"Discount & Variety Stores",
            "type":"Retail Goods"
        }
    ],
    "sg:phone":"+1 910 938 0021",
    "sg:postcode":"28540",
    "sg:province":"NC",
    "wof:name":"Dollar General",
    "wof:placetype":"venue"
},
  "geometry": {"coordinates":[-77.47404,34.755735],"type":"Point"}
}