{
  "type": "Feature",
  "properties": {
    "iso:country":"US",
    "sg:address":"5287 US Hwy 258",
    "sg:city":"Farmville",
    "sg:classifiers":[
        {
            "category":"Building & Trades",
            "subcategory":"Construction",
            "type":"Services"
        }
    ],
    "sg:phone":"+1 252 753 2274",
    "sg:postcode":"27828",
    "sg:province":"NC",
    "sg:tags":[
        "repairing",
        "remodeling",
        "contractor"
    ],
    "wof:name":"M G Carter Inc",
    "wof:placetype":"venue"
},
  "geometry": {"coordinates":[-77.609112,35.620898],"type":"Point"}
}