{
  "type": "Feature",
  "properties": {
    "addr:full":"1618 Amelia Church Rd Clayton NC 27520",
    "addr:housenumber":"1618",
    "addr:postcode":"27520",
    "addr:street":"Amelia Church Rd",
    "iso:country":"US",
    "sg:address":"1618 Amelia Church Rd",
    "sg:city":"Clayton",
    "sg:classifiers":[
        {
            "category":"Home & Garden",
            "subcategory":"Household Appliances",
            "type":"Retail Goods"
        },
        {
            "category":"Retail",
            "subcategory":"Repair Shop",
            "type":"Services"
        },
        {
            "category":"Utilities",
            "subcategory":"Natural Gas",
            "type":"Services"
        }
    ],
    "sg:phone":"+1 919 553 6205",
    "sg:postcode":"27520",
    "sg:province":"NC",
    "sg:tags":[
        "small",
        "major",
        "refinishing",
        "appliances-small"
    ],
    "wof:name":"Stewart's Appliance & Gas Co",
    "wof:placetype":"venue"
},
  "geometry": {"coordinates":[-78.494276,35.638955],"type":"Point"}
}