{
  "type": "Feature",
  "properties": {
    "addr:full":"509 US Hwy 70 Beaufort NC 28516",
    "addr:housenumber":"509",
    "addr:postcode":"28516",
    "addr:street":"Us Hwy 70",
    "iso:country":"US",
    "sg:address":"509 US Hwy 70",
    "sg:city":"Beaufort",
    "sg:classifiers":[
        {
            "category":"Government",
            "subcategory":"Fire Station",
            "type":"Public Place"
        }
    ],
    "sg:phone":"+1 252 728 3150",
    "sg:postcode":"28516",
    "sg:province":"NC",
    "sg:tags":[
        "department"
    ],
    "wof:name":"Otway Volunteer Fire Dept",
    "wof:placetype":"venue"
},
  "geometry": {"coordinates":[-76.65487400000001,34.719616],"type":"Point"}
}