{
  "type": "Feature",
  "properties": {
    "iso:country":"US",
    "sg:address":"7304 Beaverwood Dr",
    "sg:city":"Raleigh",
    "sg:classifiers":[
        {
            "category":"Autos & Motor Vehicles",
            "subcategory":"Auto Supplies",
            "type":"Retail Goods"
        }
    ],
    "sg:phone":"+1 919 878 3362",
    "sg:postcode":"27616",
    "sg:province":"NC",
    "sg:tags":[
        "automobile",
        "parts"
    ],
    "wof:name":"My Auto Decals",
    "wof:placetype":"venue"
},
  "geometry": {"coordinates":[-78.547433,35.877139],"type":"Point"}
}