{
  "type": "Feature",
  "properties": {
    "addr:full":"1751 S Main St Wake Forest NC 27587",
    "addr:housenumber":"1751",
    "addr:postcode":"27587",
    "addr:street":"S Main St",
    "iso:country":"US",
    "sg:address":"1751 S Main St",
    "sg:city":"Wake Forest",
    "sg:classifiers":[
        {
            "category":"Health Services",
            "subcategory":"Doctor",
            "type":"Services"
        }
    ],
    "sg:phone":"+1   ",
    "sg:postcode":"27587",
    "sg:province":"NC",
    "sg:tags":[
        "medical"
    ],
    "wof:name":"Wake Forest Internal Medicine",
    "wof:placetype":"venue"
},
  "geometry": {"coordinates":[-78.525493,35.955238],"type":"Point"}
}