{
  "type": "Feature",
  "properties": {
    "addr:full":"107 Gates Dr Winterville NC 28590",
    "addr:housenumber":"107",
    "addr:postcode":"28590",
    "addr:street":"Gates Dr",
    "iso:country":"US",
    "sg:address":"107 Gates Dr",
    "sg:city":"Winterville",
    "sg:classifiers":[
        {
            "category":"Organizations",
            "subcategory":"Religious Organization",
            "type":"Services"
        }
    ],
    "sg:phone":"+1   ",
    "sg:postcode":"28590",
    "sg:province":"NC",
    "wof:name":"Matthew E Stockard Rev",
    "wof:placetype":"venue"
},
  "geometry": {"coordinates":[-77.379728,35.550764],"type":"Point"}
}