{
  "type": "Feature",
  "properties": {
    "iso:country":"US",
    "sg:address":"296 Church St N",
    "sg:city":"Concord",
    "sg:classifiers":[
        {
            "category":"Health Services",
            "subcategory":"Clinic",
            "type":"Services"
        }
    ],
    "sg:phone":"+1 704 782 4311",
    "sg:postcode":"28025",
    "sg:province":"NC",
    "sg:tags":[
        "retardation",
        "information",
        "mental",
        "center"
    ],
    "wof:name":"Cabarrus County Group Homes",
    "wof:placetype":"venue"
},
  "geometry": {"coordinates":[-80.588708,35.418766],"type":"Point"}
}