{
  "type": "Feature",
  "properties": {
    "iso:country":"US",
    "sg:address":"1535 W May Ave",
    "sg:city":"Gastonia",
    "sg:classifiers":[
        {
            "category":"Building & Trades",
            "subcategory":"Construction",
            "type":"Services"
        }
    ],
    "sg:phone":"+1 704 864 0344",
    "sg:postcode":"28052",
    "sg:province":"NC",
    "sg:tags":[
        "system",
        "specialty",
        "heating",
        "contractor",
        "air conditioning"
    ],
    "wof:name":"GSM Heating And Air",
    "wof:placetype":"venue"
},
  "geometry": {"coordinates":[-81.21223999999999,35.265747],"type":"Point"}
}