{
  "type": "Feature",
  "properties": {
    "addr:full":"3730 Old Creek Rd Greenville NC 27834",
    "addr:housenumber":"3730",
    "addr:postcode":"27834",
    "addr:street":"Old Creek Rd",
    "iso:country":"US",
    "sg:address":"3730 Old Creek Rd",
    "sg:city":"Greenville",
    "sg:classifiers":[
        {
            "category":"Retail",
            "subcategory":"Laundry & Dry Cleaning",
            "type":"Services"
        }
    ],
    "sg:phone":"+1 252 329 8479",
    "sg:postcode":"27834",
    "sg:province":"NC",
    "sg:tags":[
        "cleaners",
        "rug",
        "carpet"
    ],
    "wof:name":"Jansen Carpet Cleaning",
    "wof:placetype":"venue"
},
  "geometry": {"coordinates":[-77.266924,35.653151],"type":"Point"}
}