{
  "type": "Feature",
  "properties": {
    "addr:full":"5722 Germanton Rd Winston Salem NC 27105",
    "addr:postcode":"5722;27105",
    "addr:street":"Germanton Rd",
    "iso:country":"US",
    "sg:address":"5722 Germanton Rd",
    "sg:city":"Winston Salem",
    "sg:classifiers":[
        {
            "category":"Retail",
            "subcategory":"Repair Shop",
            "type":"Services"
        }
    ],
    "sg:phone":"+1 336 744 0711",
    "sg:postcode":"27105",
    "sg:province":"NC",
    "sg:tags":[
        "repairing",
        "lawn",
        "mower"
    ],
    "wof:name":"Tom's Lawn Mower Repair",
    "wof:placetype":"venue"
},
  "geometry": {"coordinates":[-80.252921,36.202458],"type":"Point"}
}