{
  "type": "Feature",
  "properties": {
    "iso:country":"US",
    "sg:address":"300 N Cansler St",
    "sg:city":"Kings Mountain",
    "sg:classifiers":[
        {
            "category":"Personal",
            "subcategory":"Barber",
            "type":"Services"
        }
    ],
    "sg:phone":"+1   ",
    "sg:postcode":"28086",
    "sg:province":"NC",
    "sg:tags":[
        "shop"
    ],
    "wof:name":"Trinity Barber Shop",
    "wof:placetype":"venue"
},
  "geometry": {"coordinates":[-81.34666799999999,35.245127],"type":"Point"}
}