{
  "type": "Feature",
  "properties": {
    "addr:full":"19750 W Catawba Ave Cornelius NC 28031",
    "addr:housenumber":"19750",
    "addr:postcode":"28031",
    "addr:street":"W Catawba Ave",
    "iso:country":"US",
    "sg:address":"19750 W Catawba Ave",
    "sg:city":"Cornelius",
    "sg:classifiers":[
        {
            "category":"Retail",
            "subcategory":"Laundry & Dry Cleaning",
            "type":"Services"
        }
    ],
    "sg:phone":"+1 704 896 6702",
    "sg:postcode":"28031",
    "sg:province":"NC",
    "sg:tags":[
        "cleaners",
        "plant",
        "drycleaning"
    ],
    "wof:name":"Hangers Cleaners",
    "wof:placetype":"venue"
},
  "geometry": {"coordinates":[-80.88704300000001,35.480693],"type":"Point"}
}