{
  "type": "Feature",
  "properties": {
    "addr:full":"208 N Chatham Ave Siler City NC 27344",
    "addr:housenumber":"208",
    "addr:postcode":"27344",
    "addr:street":"N Chatham Ave",
    "iso:country":"US",
    "sg:address":"208 N Chatham Ave",
    "sg:city":"Siler City",
    "sg:classifiers":[
        {
            "category":"Shopping",
            "subcategory":"Clothing, Apparel, & Fashions",
            "type":"Retail Goods"
        }
    ],
    "sg:phone":"+1 919 742 5559",
    "sg:postcode":"27344",
    "sg:province":"NC",
    "wof:name":"Yoly's Fashion",
    "wof:placetype":"venue"
},
  "geometry": {"coordinates":[-79.464521,35.724699],"type":"Point"}
}