{
  "type": "Feature",
  "properties": {
    "addr:full":"1437 E Dixie Dr Asheboro NC 27203",
    "addr:housenumber":"1437",
    "addr:postcode":"27203",
    "addr:street":"E Dixie Dr",
    "iso:country":"US",
    "sg:address":"1437 E Dixie Dr",
    "sg:city":"Asheboro",
    "sg:classifiers":[
        {
            "category":"Shopping",
            "subcategory":"Clothing, Apparel, & Fashions",
            "type":"Retail Goods"
        }
    ],
    "sg:phone":"+1 336 629 5582",
    "sg:postcode":"27203",
    "sg:province":"NC",
    "sg:tags":[
        "sportswear"
    ],
    "sg:website":"www.ae.com",
    "wof:name":"American Eagle Outfitters",
    "wof:placetype":"venue"
},
  "geometry": {"coordinates":[-79.78600400000001,35.699571],"type":"Point"}
}