{
  "type": "Feature",
  "properties": {
    "addr:full":"114 Goguen Rd Newport NC 28570",
    "addr:housenumber":"114",
    "addr:postcode":"28570",
    "addr:street":"Goguen Rd",
    "iso:country":"US",
    "sg:address":"114 Goguen Rd",
    "sg:city":"Newport",
    "sg:classifiers":[
        {
            "category":"Manufacturing",
            "subcategory":"Apparel",
            "type":"Manufacturing & Wholesale Goods"
        }
    ],
    "sg:phone":"+1 252 393 8426",
    "sg:postcode":"28570",
    "sg:province":"NC",
    "sg:tags":[
        "mfg"
    ],
    "wof:name":"Southern Soldier Mercantile",
    "wof:placetype":"venue"
},
  "geometry": {"coordinates":[-77.03936,34.70259],"type":"Point"}
}