{
  "type": "Feature",
  "properties": {
    "addr:full":"132 Wiley Oaks Dr Wendell NC 27591",
    "addr:housenumber":"132",
    "addr:postcode":"27591",
    "addr:street":"Wiley Oaks Dr",
    "iso:country":"US",
    "sg:address":"132 Wiley Oaks Dr",
    "sg:city":"Wendell",
    "sg:classifiers":[
        {
            "category":"Professional",
            "subcategory":"Management & Consulting",
            "type":"Services"
        }
    ],
    "sg:phone":"+1   ",
    "sg:postcode":"27591",
    "sg:province":"NC",
    "sg:tags":[
        "business"
    ],
    "wof:name":"Wencon Systems",
    "wof:placetype":"venue"
},
  "geometry": {"coordinates":[-78.408568,35.773996],"type":"Point"}
}