{
  "type": "Feature",
  "properties": {
    "addr:full":"400 Everidge Rd Winston Salem NC 27103",
    "addr:housenumber":"400",
    "addr:postcode":"27103",
    "addr:street":"Everidge Rd",
    "iso:country":"US",
    "sg:address":"400 Everidge Rd",
    "sg:city":"Winston Salem",
    "sg:classifiers":[
        {
            "category":"Recreation",
            "type":"Entertainment"
        }
    ],
    "sg:phone":"+1   ",
    "sg:postcode":"27103",
    "sg:province":"NC",
    "wof:name":"L Carter Renan",
    "wof:placetype":"venue"
},
  "geometry": {"coordinates":[-80.311267,36.049],"type":"Point"}
}