{
  "type": "Feature",
  "properties": {
    "iso:country":"US",
    "sg:address":"170 Rosscraggon Rd",
    "sg:city":"Asheville",
    "sg:classifiers":[
        {
            "category":"Bars & Pubs",
            "type":"Food & Drink"
        }
    ],
    "sg:phone":"+1 828 687 1623",
    "sg:postcode":"28776",
    "sg:province":"NC",
    "sg:tags":[
        "drinking"
    ],
    "wof:name":"Reflections Sports Club",
    "wof:placetype":"venue"
},
  "geometry": {"coordinates":[-82.52188099999999,35.48381],"type":"Point"}
}