{
  "type": "Feature",
  "properties": {
    "addr:full":"6340 Quadrangle Dr Chapel Hill NC 27517",
    "addr:postcode":"6340;27517",
    "addr:street":"Quadrangle Dr",
    "iso:country":"US",
    "sg:address":"6340 Quadrangle Dr",
    "sg:city":"Chapel Hill",
    "sg:classifiers":[
        {
            "category":"Health Services",
            "subcategory":"Doctor",
            "type":"Services"
        }
    ],
    "sg:phone":"+1 919 493 6580",
    "sg:postcode":"27517",
    "sg:province":"NC",
    "sg:tags":[
        "physician",
        "surgeon",
        "medical"
    ],
    "wof:name":"Carolina Allergy & Asthma Cons",
    "wof:placetype":"venue"
},
  "geometry": {"coordinates":[-78.979299,35.913938],"type":"Point"}
}