{
  "type": "Feature",
  "properties": {
    "addr:full":"11 Memory Ln Arden NC 28704",
    "addr:housenumber":"11",
    "addr:postcode":"28704",
    "addr:street":"Memory Ln",
    "iso:country":"US",
    "sg:address":"11 Memory Ln",
    "sg:city":"Arden",
    "sg:classifiers":[
        {
            "category":"Manufacturing",
            "subcategory":"Tools & Machinery",
            "type":"Manufacturing & Wholesale Goods"
        }
    ],
    "sg:phone":"+1 828 684 9747",
    "sg:postcode":"28704",
    "sg:province":"NC",
    "sg:tags":[
        "industrial",
        "mfg"
    ],
    "wof:name":"Bucwood Tool and Machine Inc",
    "wof:placetype":"venue"
},
  "geometry": {"coordinates":[-82.567696,35.477284],"type":"Point"}
}