{
  "type": "Feature",
  "properties": {
    "addr:full":"5701 Brookshire Blvd Charlotte NC 28216",
    "addr:housenumber":"5701",
    "addr:postcode":"28216",
    "addr:street":"Brookshire Blvd",
    "iso:country":"US",
    "sg:address":"5701 Brookshire Blvd",
    "sg:city":"Charlotte",
    "sg:classifiers":[
        {
            "category":"Freight",
            "type":"Transportation"
        }
    ],
    "sg:phone":"+1 704 394 5625",
    "sg:postcode":"28216",
    "sg:province":"NC",
    "sg:tags":[
        "general"
    ],
    "wof:name":"Brookshire Mini Storage",
    "wof:placetype":"venue"
},
  "geometry": {"coordinates":[-80.903387,35.283595],"type":"Point"}
}