{
  "type": "Feature",
  "properties": {
    "iso:country":"US",
    "sg:address":"119 Mill Pond Rd",
    "sg:city":"Jacksonville",
    "sg:classifiers":[
        {
            "category":"Building & Trades",
            "subcategory":"Construction",
            "type":"Services"
        }
    ],
    "sg:phone":"+1 910 330 4290",
    "sg:postcode":"28546",
    "sg:province":"NC",
    "sg:tags":[
        "tile",
        "dealer"
    ],
    "wof:name":"J & L Tile Works",
    "wof:placetype":"venue"
},
  "geometry": {"coordinates":[-77.46248,34.837863],"type":"Point"}
}