{
  "type": "Feature",
  "properties": {
    "iso:country":"US",
    "sg:address":"114 Rowan St",
    "sg:city":"Fayetteville",
    "sg:classifiers":[
        {
            "category":"Insurance",
            "subcategory":"Insurance Agent",
            "type":"Services"
        }
    ],
    "sg:phone":"+1 910 435 3600",
    "sg:postcode":"28301",
    "sg:province":"NC",
    "wof:name":"B B & T Insurance Svc",
    "wof:placetype":"venue"
},
  "geometry": {"coordinates":[-78.87710199999999,35.057345],"type":"Point"}
}