{
  "type": "Feature",
  "properties": {
    "addr:full":"445 S Cannon Blvd Kannapolis NC 28083",
    "addr:housenumber":"445",
    "addr:postcode":"28083",
    "addr:street":"S Cannon Blvd",
    "iso:country":"US",
    "sg:address":"445 S Cannon Blvd",
    "sg:city":"Kannapolis",
    "sg:classifiers":[
        {
            "category":"Shopping",
            "subcategory":"Hobbies, Toys, & Games",
            "type":"Retail Goods"
        }
    ],
    "sg:phone":"+1 704 933 2646",
    "sg:postcode":"28083",
    "sg:province":"NC",
    "sg:tags":[
        "model",
        "supply"
    ],
    "wof:name":"Pro Formance Hobbies",
    "wof:placetype":"venue"
},
  "geometry": {"coordinates":[-80.611046,35.490936],"type":"Point"}
}