{
  "type": "Feature",
  "properties": {
    "addr:full":"3132 Roxboro Rd Durham NC 27704",
    "addr:housenumber":"3132",
    "addr:postcode":"27704",
    "addr:street":"Roxboro Rd",
    "iso:country":"US",
    "sg:address":"3132 Roxboro Rd",
    "sg:city":"Durham",
    "sg:classifiers":[
        {
            "category":"Social Services",
            "subcategory":"Adult Care",
            "type":"Services"
        }
    ],
    "sg:phone":"+1 919 560 5790",
    "sg:postcode":"27704",
    "sg:province":"NC",
    "sg:tags":[
        "residential",
        "consulting",
        "business"
    ],
    "sg:website":"www.wrightschool.org",
    "wof:name":"Wright School",
    "wof:placetype":"venue"
},
  "geometry": {"coordinates":[-78.890626,36.031217],"type":"Point"}
}