{
  "type": "Feature",
  "properties": {
    "addr:full":"2909 Kinsey Loop Winterville NC 28590",
    "addr:housenumber":"2909",
    "addr:postcode":"28590",
    "addr:street":"Kinsey Loop",
    "iso:country":"US",
    "sg:address":"2909 Kinsey Loop",
    "sg:city":"Winterville",
    "sg:classifiers":[
        {
            "category":"Banks & Credit Unions",
            "subcategory":"Investment Brokerage",
            "type":"Services"
        }
    ],
    "sg:phone":"+1 252 355 8833",
    "sg:postcode":"28590",
    "sg:province":"NC",
    "sg:tags":[
        "stock",
        "bond"
    ],
    "wof:name":"Ameriprise Financial",
    "wof:placetype":"venue"
},
  "geometry": {"coordinates":[-77.401053,35.517808],"type":"Point"}
}