{
  "type": "Feature",
  "properties": {
    "addr:full":"900 Raleigh Rd Clinton NC 28328",
    "addr:housenumber":"900",
    "addr:postcode":"28328",
    "addr:street":"Raleigh Rd",
    "iso:country":"US",
    "sg:address":"900 Raleigh Rd",
    "sg:city":"Clinton",
    "sg:classifiers":[
        {
            "category":"Retail",
            "subcategory":"Repair Shop",
            "type":"Services"
        }
    ],
    "sg:phone":"+1   ",
    "sg:postcode":"28328",
    "sg:province":"NC",
    "sg:tags":[
        "equipment"
    ],
    "wof:name":"Quality Office Machine Svcs",
    "wof:placetype":"venue"
},
  "geometry": {"coordinates":[-78.317047,35.016918],"type":"Point"}
}