{
  "type": "Feature",
  "properties": {
    "addr:full":"11413 State Hwy 42 E Middlesex NC 27557",
    "addr:housenumber":"11413",
    "addr:postcode":"27557",
    "addr:street":"State Hwy 42 E",
    "iso:country":"US",
    "sg:address":"11413 State Hwy 42 E",
    "sg:city":"Middlesex",
    "sg:classifiers":[
        {
            "category":"Wholesale",
            "subcategory":"Groceries",
            "type":"Manufacturing & Wholesale Goods"
        }
    ],
    "sg:phone":"+1 919 284 2069",
    "sg:postcode":"27557",
    "sg:province":"NC",
    "wof:name":"Bg & G Inc",
    "wof:placetype":"venue"
},
  "geometry": {"coordinates":[-78.213711,35.681961],"type":"Point"}
}