{
  "type": "Feature",
  "properties": {
    "iso:country":"US",
    "sg:address":"3819 Cat Square Rd",
    "sg:city":"Vale",
    "sg:classifiers":[
        {
            "category":"Social Services",
            "subcategory":"Child Care",
            "type":"Services"
        }
    ],
    "sg:phone":"+1 704 462 2435",
    "sg:postcode":"28168",
    "sg:province":"NC",
    "sg:tags":[
        "center",
        "day"
    ],
    "wof:name":"Papaw Patch LLC",
    "wof:placetype":"venue"
},
  "geometry": {"coordinates":[-81.43890500000001,35.581762],"type":"Point"}
}