{
  "type": "Feature",
  "properties": {
    "iso:country":"US",
    "sg:address":"1934 Spring Garden St",
    "sg:city":"Greensboro",
    "sg:classifiers":[
        {
            "category":"Professional",
            "subcategory":"Accounting & Tax Preparation",
            "type":"Services"
        }
    ],
    "sg:phone":"+1 336 370 1060",
    "sg:postcode":"27403",
    "sg:province":"NC",
    "sg:tags":[
        "return"
    ],
    "wof:name":"Liberty Tax Service",
    "wof:placetype":"venue"
},
  "geometry": {"coordinates":[-79.825667,36.06391],"type":"Point"}
}