{
  "type": "Feature",
  "properties": {
    "addr:full":"9601 Brookdale Dr Charlotte NC 28215",
    "addr:housenumber":"9601",
    "addr:postcode":"28215",
    "addr:street":"Brookdale Dr",
    "iso:country":"US",
    "sg:address":"9601 Brookdale Dr",
    "sg:city":"Charlotte",
    "sg:classifiers":[
        {
            "category":"Restaurant",
            "type":"Food & Drink"
        }
    ],
    "sg:phone":"+1 704 494 3944",
    "sg:postcode":"28215",
    "sg:province":"NC",
    "sg:tags":[
        "asian",
        "chinese",
        "pan"
    ],
    "wof:name":"Best China",
    "wof:placetype":"venue"
},
  "geometry": {"coordinates":[-80.66783100000001,35.283428],"type":"Point"}
}