{
  "type": "Feature",
  "properties": {
    "iso:country":"US",
    "sg:address":"317 Waterside Dr",
    "sg:city":"Sanford",
    "sg:classifiers":[
        {
            "category":"Personal",
            "subcategory":"Beauty Salon",
            "type":"Services"
        }
    ],
    "sg:phone":"+1   ",
    "sg:postcode":"27330",
    "sg:province":"NC",
    "sg:tags":[
        "shop"
    ],
    "wof:name":"Norma Bryant",
    "wof:placetype":"venue"
},
  "geometry": {"coordinates":[-79.235828,35.485396],"type":"Point"}
}