{
  "type": "Feature",
  "properties": {
    "addr:full":"1801 W Market St Greensboro NC 27403",
    "addr:housenumber":"1801",
    "addr:postcode":"27403",
    "addr:street":"W Market St",
    "iso:country":"US",
    "sg:address":"1801 W Market St",
    "sg:city":"Greensboro",
    "sg:classifiers":[
        {
            "category":"Professional",
            "type":"Services"
        }
    ],
    "sg:phone":"+1 336 272 8215",
    "sg:postcode":"27403",
    "sg:province":"NC",
    "wof:name":"Atelier Sk LLC",
    "wof:placetype":"venue"
},
  "geometry": {"coordinates":[-79.818484,36.073909],"type":"Point"}
}