{
  "type": "Feature",
  "properties": {
    "iso:country":"US",
    "sg:address":"6803 Alamosa Dr",
    "sg:city":"Wilmington",
    "sg:classifiers":[
        {
            "category":"Real Estate",
            "subcategory":"Real Estate Agent",
            "type":"Services"
        }
    ],
    "sg:phone":"+1 910 313 1792",
    "sg:postcode":"28411",
    "sg:province":"NC",
    "wof:name":"Alamosa Place Model Home",
    "wof:placetype":"venue"
},
  "geometry": {"coordinates":[-77.84141,34.28222],"type":"Point"}
}