{
  "type": "Feature",
  "properties": {
    "iso:country":"US",
    "sg:address":"250 Beech St",
    "sg:city":"Greenville",
    "sg:classifiers":[
        {
            "category":"Professional",
            "type":"Services"
        }
    ],
    "sg:phone":"+1 252 752 7088",
    "sg:postcode":"27858",
    "sg:province":"NC",
    "wof:name":"Wavelength Beech St Villas",
    "wof:placetype":"venue"
},
  "geometry": {"coordinates":[-77.341826,35.608965],"type":"Point"}
}