{
  "type": "Feature",
  "properties": {
    "iso:country":"US",
    "sg:address":"7274 Pearces Rd",
    "sg:city":"Louisburg",
    "sg:classifiers":[
        {
            "category":"Building & Trades",
            "subcategory":"Construction",
            "type":"Services"
        }
    ],
    "sg:phone":"+1 919 497 0311",
    "sg:postcode":"27549",
    "sg:province":"NC",
    "sg:tags":[
        "excavation",
        "contractor"
    ],
    "wof:name":"Uhl Excavation",
    "wof:placetype":"venue"
},
  "geometry": {"coordinates":[-78.275211,35.981703],"type":"Point"}
}