{
  "type": "Feature",
  "properties": {
    "addr:full":"3879 Hendersonville Rd Fletcher NC 28732",
    "addr:housenumber":"3879",
    "addr:postcode":"28732",
    "addr:street":"Hendersonville Rd",
    "iso:country":"US",
    "sg:address":"3879 Hendersonville Rd",
    "sg:city":"Fletcher",
    "sg:classifiers":[
        {
            "category":"Personal",
            "subcategory":"Barber",
            "type":"Services"
        }
    ],
    "sg:phone":"+1 828 684 0751",
    "sg:postcode":"28732",
    "sg:province":"NC",
    "wof:name":"Fletcher Plaza Barber & Style",
    "wof:placetype":"venue"
},
  "geometry": {"coordinates":[-82.501507,35.428664],"type":"Point"}
}