{
  "type": "Feature",
  "properties": {
    "addr:full":"1046 Rulnick St Fayetteville NC 28304",
    "addr:housenumber":"1046",
    "addr:postcode":"28304",
    "addr:street":"Rulnick St",
    "iso:country":"US",
    "sg:address":"1046 Rulnick St",
    "sg:city":"Fayetteville",
    "sg:classifiers":[
        {
            "category":"Manufacturing",
            "subcategory":"Furniture",
            "type":"Manufacturing & Wholesale Goods"
        }
    ],
    "sg:phone":"+1 910 237 7616",
    "sg:postcode":"28304",
    "sg:province":"NC",
    "sg:tags":[
        "mini"
    ],
    "wof:name":"Td Improvement",
    "wof:placetype":"venue"
},
  "geometry": {"coordinates":[-78.981578,35.041222],"type":"Point"}
}