{
  "type": "Feature",
  "properties": {
    "iso:country":"US",
    "sg:address":"106 N Graham St Ste C",
    "sg:city":"Chapel Hill",
    "sg:classifiers":[
        {
            "category":"Shopping",
            "subcategory":"Mobile Phones",
            "type":"Retail Goods"
        }
    ],
    "sg:phone":"+1 919 969 2700",
    "sg:postcode":"27516",
    "sg:province":"NC",
    "wof:name":"Graham Street Market",
    "wof:placetype":"venue"
},
  "geometry": {"coordinates":[-79.06425299999999,35.909987],"type":"Point"}
}