{
  "type": "Feature",
  "properties": {
    "addr:full":"603 Eastchester Dr High Point NC 27262",
    "addr:housenumber":"603",
    "addr:postcode":"27262",
    "addr:street":"Eastchester Dr",
    "iso:country":"US",
    "sg:address":"603 Eastchester Dr",
    "sg:city":"High Point",
    "sg:classifiers":[
        {
            "category":"Shopping",
            "subcategory":"Clothing, Apparel, & Fashions",
            "type":"Retail Goods"
        }
    ],
    "sg:phone":"+1 336 882 5207",
    "sg:postcode":"27262",
    "sg:province":"NC",
    "wof:name":"Ten Toes Socks",
    "wof:placetype":"venue"
},
  "geometry": {"coordinates":[-80.008425,35.984145],"type":"Point"}
}