{
  "type": "Feature",
  "properties": {
    "addr:full":"4300 Bland Rd Raleigh NC 27609",
    "addr:housenumber":"4300",
    "addr:postcode":"27609",
    "addr:street":"Bland Rd",
    "iso:country":"US",
    "sg:address":"4300 Bland Rd",
    "sg:city":"Raleigh",
    "sg:classifiers":[
        {
            "category":"Building & Trades",
            "subcategory":"Construction",
            "type":"Services"
        }
    ],
    "sg:phone":"+1 919 876 4759",
    "sg:postcode":"27609",
    "sg:province":"NC",
    "sg:tags":[
        "handyman"
    ],
    "wof:name":"Allgard",
    "wof:placetype":"venue"
},
  "geometry": {"coordinates":[-78.614082,35.83734],"type":"Point"}
}