{
  "type": "Feature",
  "properties": {
    "iso:country":"US",
    "sg:address":"1163 J V Parker Dr",
    "sg:city":"Hickory",
    "sg:classifiers":[
        {
            "category":"Wholesale",
            "subcategory":"Construction Materials",
            "type":"Manufacturing & Wholesale Goods"
        },
        {
            "category":"Home & Garden",
            "subcategory":"Furniture",
            "type":"Retail Goods"
        }
    ],
    "sg:phone":"+1 828 267 0000",
    "sg:postcode":"28602",
    "sg:province":"NC",
    "sg:tags":[
        "cabinet"
    ],
    "wof:name":"Fletcher's Cabinets & Doors",
    "wof:placetype":"venue"
},
  "geometry": {"coordinates":[-81.429411,35.652848],"type":"Point"}
}