{
  "type": "Feature",
  "properties": {
    "addr:full":"1427 E 10th St Charlotte NC 28204",
    "addr:housenumber":"1427",
    "addr:postcode":"28204",
    "addr:street":"E 10Th St",
    "iso:country":"US",
    "sg:address":"1427 E 10th St",
    "sg:city":"Charlotte",
    "sg:classifiers":[
        {
            "category":"Arts & Performance",
            "subcategory":"Theater",
            "type":"Entertainment"
        }
    ],
    "sg:phone":"+1   ",
    "sg:postcode":"28204",
    "sg:province":"NC",
    "sg:tags":[
        "theatrical"
    ],
    "wof:name":"Honest Pats Playhouse",
    "wof:placetype":"venue"
},
  "geometry": {"coordinates":[-80.821687,35.222022],"type":"Point"}
}