{
  "type": "Feature",
  "properties": {
    "addr:full":"280 Roberts Ln Hiddenite NC 28636",
    "addr:housenumber":"280",
    "addr:postcode":"28636",
    "addr:street":"Roberts Ln",
    "iso:country":"US",
    "sg:address":"280 Roberts Ln",
    "sg:city":"Hiddenite",
    "sg:classifiers":[
        {
            "category":"Wholesale",
            "subcategory":"Durable Goods & Equipment",
            "type":"Manufacturing & Wholesale Goods"
        }
    ],
    "sg:phone":"+1 828 396 1389",
    "sg:postcode":"28636",
    "sg:province":"NC",
    "wof:name":"Roberta Williams",
    "wof:placetype":"venue"
},
  "geometry": {"coordinates":[-81.109049,35.859942],"type":"Point"}
}