{
  "type": "Feature",
  "properties": {
    "addr:full":"1855 Springs Rd NE Hickory NC 28601",
    "addr:housenumber":"1855",
    "addr:postcode":"28601",
    "addr:street":"Springs Rd Ne",
    "iso:country":"US",
    "sg:address":"1855 Springs Rd NE",
    "sg:city":"Hickory",
    "sg:classifiers":[
        {
            "category":"Autos & Motor Vehicles",
            "subcategory":"Auto Supplies",
            "type":"Retail Goods"
        }
    ],
    "sg:phone":"+1 828 327 8502",
    "sg:postcode":"28601",
    "sg:province":"NC",
    "sg:tags":[
        "automobile",
        "parts"
    ],
    "sg:website":"www.advanceautoparts.com",
    "wof:name":"Advance Auto Parts Inc",
    "wof:placetype":"venue"
},
  "geometry": {"coordinates":[-81.300404,35.743016],"type":"Point"}
}