{
  "type": "Feature",
  "properties": {
    "addr:full":"2105 E State Hwy 54 Durham NC 27713",
    "addr:housenumber":"2105",
    "addr:postcode":"27713",
    "addr:street":"E State Hwy 54",
    "iso:country":"US",
    "sg:address":"2105 E State Hwy 54",
    "sg:city":"Durham",
    "sg:classifiers":[
        {
            "category":"Real Estate",
            "subcategory":"Real Estate Agent",
            "type":"Services"
        }
    ],
    "sg:phone":"+1 919 544 2891",
    "sg:postcode":"27713",
    "sg:province":"NC",
    "wof:name":"York Properties",
    "wof:placetype":"venue"
},
  "geometry": {"coordinates":[-78.893406,35.901916],"type":"Point"}
}