{
  "type": "Feature",
  "properties": {
    "addr:full":"3325 State Rd 27 Lincolnton NC 28092",
    "addr:housenumber":"3325;27",
    "addr:postcode":"28092",
    "addr:street":"State Rd",
    "iso:country":"US",
    "sg:address":"3325 State Rd 27",
    "sg:city":"Lincolnton",
    "sg:classifiers":[
        {
            "category":"Manufacturing",
            "subcategory":"Building Materials",
            "type":"Manufacturing & Wholesale Goods"
        }
    ],
    "sg:phone":"+1 704 735 5755",
    "sg:postcode":"28092",
    "sg:province":"NC",
    "sg:tags":[
        "mfg",
        "wood",
        "kitchen",
        "cabinet"
    ],
    "wof:name":"Housers Cabinet Shop Inc",
    "wof:placetype":"venue"
},
  "geometry": {"coordinates":[-81.185418,35.478157],"type":"Point"}
}