{
  "type": "Feature",
  "properties": {
    "addr:full":"617 E Main St Cherryville NC 28021",
    "addr:housenumber":"617",
    "addr:postcode":"28021",
    "addr:street":"E Main St",
    "iso:country":"US",
    "sg:address":"617 E Main St",
    "sg:city":"Cherryville",
    "sg:classifiers":[
        {
            "category":"Manufacturing",
            "subcategory":"Metals",
            "type":"Manufacturing & Wholesale Goods"
        }
    ],
    "sg:phone":"+1 704 445 1710",
    "sg:postcode":"28021",
    "sg:province":"NC",
    "wof:name":"Carolina Custom Metal Fnshng",
    "wof:placetype":"venue"
},
  "geometry": {"coordinates":[-81.372851,35.381085],"type":"Point"}
}