{
  "type": "Feature",
  "properties": {
    "addr:full":"4309 Big Tree Way Greensboro NC 27409",
    "addr:housenumber":"4309",
    "addr:postcode":"27409",
    "addr:street":"Big Tree Way",
    "iso:country":"US",
    "sg:address":"4309 Big Tree Way",
    "sg:city":"Greensboro",
    "sg:classifiers":[
        {
            "category":"Organizations",
            "subcategory":"Religious Organization",
            "type":"Services"
        }
    ],
    "sg:phone":"+1   ",
    "sg:postcode":"27409",
    "sg:province":"NC",
    "wof:name":"Emmanuels House of Charity",
    "wof:placetype":"venue"
},
  "geometry": {"coordinates":[-79.89204100000001,36.059083],"type":"Point"}
}