{
  "type": "Feature",
  "properties": {
    "iso:country":"US",
    "sg:address":"2917 Weck Dr",
    "sg:city":"Resrch Trngle Pk",
    "sg:classifiers":[
        {
            "category":"Manufacturing",
            "subcategory":"Tools & Machinery",
            "type":"Manufacturing & Wholesale Goods"
        }
    ],
    "sg:phone":"+1 919 544 8000",
    "sg:postcode":"27703",
    "sg:province":"NC",
    "sg:tags":[
        "instrument",
        "surgical"
    ],
    "wof:name":"Teleflex Inc",
    "wof:placetype":"venue"
},
  "geometry": {"coordinates":[-78.849745,35.931041],"type":"Point"}
}