{
  "type": "Feature",
  "properties": {
    "iso:country":"US",
    "sg:address":"15551 Eagleview Dr",
    "sg:city":"Charlotte",
    "sg:classifiers":[
        {
            "category":"Real Estate",
            "subcategory":"Real Estate Agent",
            "type":"Services"
        }
    ],
    "sg:phone":"+1 704 583 4469",
    "sg:postcode":"28278",
    "sg:province":"NC",
    "sg:tags":[
        "management"
    ],
    "wof:name":"JEH & Assoc Inc",
    "wof:placetype":"venue"
},
  "geometry": {"coordinates":[-81.0296,35.099142],"type":"Point"}
}