{
  "type": "Feature",
  "properties": {
    "iso:country":"US",
    "sg:address":"310 S 1st St",
    "sg:city":"Nashville",
    "sg:classifiers":[
        {
            "category":"Professional",
            "type":"Services"
        }
    ],
    "sg:phone":"+1 252 462 0102",
    "sg:postcode":"27856",
    "sg:province":"NC",
    "wof:name":"Andrew D Baker",
    "wof:placetype":"venue"
},
  "geometry": {"coordinates":[-77.96225200000001,35.970555],"type":"Point"}
}