{
  "type": "Feature",
  "properties": {
    "iso:country":"US",
    "sg:address":"1515 N Pointe Dr",
    "sg:city":"Durham",
    "sg:classifiers":[
        {
            "category":"Shopping",
            "subcategory":"Department Store",
            "type":"Retail Goods"
        }
    ],
    "sg:phone":"+1 919 220 9900",
    "sg:postcode":"27705",
    "sg:province":"NC",
    "sg:tags":[
        "shop"
    ],
    "sg:website":"www.pier1.com",
    "wof:name":"Pier 1 Imports",
    "wof:placetype":"venue"
},
  "geometry": {"coordinates":[-78.91678899999999,36.0282],"type":"Point"}
}