{
  "type": "Feature",
  "properties": {
    "iso:country":"US",
    "sg:address":"219 Ray Rd",
    "sg:city":"Robbins",
    "sg:classifiers":[
        {
            "category":"Mining & Drilling",
            "type":"Manufacturing & Wholesale Goods"
        }
    ],
    "sg:phone":"+1 910 948 2880",
    "sg:postcode":"27325",
    "sg:province":"NC",
    "sg:tags":[
        "stone"
    ],
    "wof:name":"William E Sanders",
    "wof:placetype":"venue"
},
  "geometry": {"coordinates":[-79.660158,35.427452],"type":"Point"}
}