{
  "type": "Feature",
  "properties": {
    "iso:country":"US",
    "sg:address":"296 Gentry Rd",
    "sg:city":"Elkin",
    "sg:classifiers":[
        {
            "category":"Building & Trades",
            "subcategory":"Equipment Rental",
            "type":"Services"
        },
        {
            "category":"Building & Trades",
            "subcategory":"Construction",
            "type":"Services"
        }
    ],
    "sg:phone":"+1 336 835 1424",
    "sg:postcode":"28621",
    "sg:province":"NC",
    "sg:tags":[
        "builder",
        "stair"
    ],
    "sg:website":"www.ecmd.com",
    "wof:name":"Crown Heritage Inc",
    "wof:placetype":"venue"
},
  "geometry": {"coordinates":[-80.786342,36.261666],"type":"Point"}
}