{
  "type": "Feature",
  "properties": {
    "addr:full":"206 N Lake Park Blvd Carolina Beach NC 28449",
    "addr:housenumber":"206",
    "addr:postcode":"28449",
    "addr:street":"N Lake Park Blvd",
    "iso:country":"US",
    "sg:address":"206 N Lake Park Blvd",
    "sg:city":"Carolina Beach",
    "sg:classifiers":[
        {
            "category":"Restaurant",
            "type":"Food & Drink"
        },
        {
            "category":"Food & Beverages",
            "subcategory":"Meat & Fish",
            "type":"Retail Goods"
        }
    ],
    "sg:phone":"+1 910 458 7761",
    "sg:postcode":"28449",
    "sg:province":"NC",
    "sg:tags":[
        "seafood",
        "market"
    ],
    "sg:website":"www.mikescfood.com",
    "wof:name":"Michael's Seafood Restaurant & Catering",
    "wof:placetype":"venue"
},
  "geometry": {"coordinates":[-77.893677,34.035455],"type":"Point"}
}