{
  "type": "Feature",
  "properties": {
    "iso:country":"US",
    "sg:address":"2520 Sardis Rd N",
    "sg:city":"Charlotte",
    "sg:classifiers":[
        {
            "category":"Social Services",
            "subcategory":"Child Care",
            "type":"Services"
        }
    ],
    "sg:phone":"+1 704 849 8800",
    "sg:postcode":"28227",
    "sg:province":"NC",
    "wof:name":"First Metroplitan Mortgage",
    "wof:placetype":"venue"
},
  "geometry": {"coordinates":[-80.724318,35.147133],"type":"Point"}
}