{
  "type": "Feature",
  "properties": {
    "iso:country":"US",
    "sg:address":"6274 Yadkinville Rd",
    "sg:city":"Pfafftown",
    "sg:classifiers":[
        {
            "category":"Social Services",
            "subcategory":"Child Care",
            "type":"Services"
        }
    ],
    "sg:phone":"+1 336 945 2547",
    "sg:postcode":"27040",
    "sg:province":"NC",
    "sg:tags":[
        "day"
    ],
    "wof:name":"Brookstown School Care",
    "wof:placetype":"venue"
},
  "geometry": {"coordinates":[-80.40452999999999,36.136983],"type":"Point"}
}