{
  "type": "Feature",
  "properties": {
    "iso:country":"US",
    "sg:address":"900 W Northwest Blvd",
    "sg:city":"Winston Salem",
    "sg:classifiers":[
        {
            "category":"Home & Garden",
            "subcategory":"Building Materials",
            "type":"Retail Goods"
        }
    ],
    "sg:phone":"+1 336 721 3070",
    "sg:postcode":"27101",
    "sg:province":"NC",
    "sg:tags":[
        "glass",
        "window",
        "plate"
    ],
    "wof:name":"Quality Glass Svc Inc",
    "wof:placetype":"venue"
},
  "geometry": {"coordinates":[-80.258528,36.104543],"type":"Point"}
}