{
  "type": "Feature",
  "properties": {
    "addr:full":"10200 Couloak Dr Charlotte NC 28216",
    "addr:housenumber":"10200",
    "addr:postcode":"28216",
    "addr:street":"Couloak Dr",
    "iso:country":"US",
    "sg:address":"10200 Couloak Dr",
    "sg:city":"Charlotte",
    "sg:classifiers":[
        {
            "category":"Banks & Credit Unions",
            "subcategory":"Bank",
            "type":"Services"
        }
    ],
    "sg:phone":"+1 704 971 1675",
    "sg:postcode":"28216",
    "sg:province":"NC",
    "sg:tags":[
        "loan",
        "real estate"
    ],
    "wof:name":"Residential Mortgage Ctr Inc",
    "wof:placetype":"venue"
},
  "geometry": {"coordinates":[-80.948921,35.32579],"type":"Point"}
}