{
  "type": "Feature",
  "properties": {
    "iso:country":"US",
    "sg:address":"9007 Dartington Ln",
    "sg:city":"Waxhaw",
    "sg:classifiers":[
        {
            "category":"Banks & Credit Unions",
            "subcategory":"Financial Services",
            "type":"Services"
        }
    ],
    "sg:phone":"+1 704 849 2547",
    "sg:postcode":"28173",
    "sg:province":"NC",
    "sg:tags":[
        "investor"
    ],
    "wof:name":"Yabuts LLC",
    "wof:placetype":"venue"
},
  "geometry": {"coordinates":[-80.805717,35.021456],"type":"Point"}
}