{
  "type": "Feature",
  "properties": {
    "iso:country":"US",
    "sg:address":"1993 Robinwood Rd",
    "sg:city":"Gastonia",
    "sg:classifiers":[
        {
            "category":"Building & Trades",
            "subcategory":"Construction",
            "type":"Services"
        }
    ],
    "sg:phone":"+1 704 867 4705",
    "sg:postcode":"28054",
    "sg:province":"NC",
    "sg:tags":[
        "contractor"
    ],
    "wof:name":"Quality Taping",
    "wof:placetype":"venue"
},
  "geometry": {"coordinates":[-81.15225,35.238075],"type":"Point"}
}