{
  "type": "Feature",
  "properties": {
    "iso:country":"US",
    "sg:address":"288 Penny Rd",
    "sg:city":"Angier",
    "sg:phone":"+1 919 894 3096",
    "sg:postcode":"27501",
    "sg:province":"NC",
    "sg:tags":[
        "farm",
        "tobacco"
    ],
    "wof:name":"Clarence Honeycutt",
    "wof:placetype":"venue"
},
  "geometry": {"coordinates":[-78.57602900000001,35.48408],"type":"Point"}
}