{
  "type": "Feature",
  "properties": {
    "iso:country":"US",
    "sg:address":"7412 Wapiti Ct",
    "sg:city":"Charlotte",
    "sg:classifiers":[
        {
            "category":"Professional",
            "subcategory":"Advertising",
            "type":"Services"
        }
    ],
    "sg:phone":"+1   ",
    "sg:postcode":"28273",
    "sg:province":"NC",
    "sg:tags":[
        "agency"
    ],
    "wof:name":"Strategic Advertising Group",
    "wof:placetype":"venue"
},
  "geometry": {"coordinates":[-80.92777,35.152766],"type":"Point"}
}