{
  "type": "Feature",
  "properties": {
    "iso:country":"US",
    "sg:address":"211 Dundalk Way",
    "sg:city":"Cary",
    "sg:classifiers":[
        {
            "category":"Personal",
            "type":"Services"
        }
    ],
    "sg:phone":"+1 919 362 9443",
    "sg:postcode":"27511",
    "sg:province":"NC",
    "sg:tags":[
        "therapist",
        "massage"
    ],
    "wof:name":"Integrated Massage Therapy",
    "wof:placetype":"venue"
},
  "geometry": {"coordinates":[-78.82006699999999,35.758715],"type":"Point"}
}