{
  "type": "Feature",
  "properties": {
    "addr:full":"4106 US Hwy 70 Morehead City NC 28557",
    "addr:housenumber":"4106",
    "addr:postcode":"28557",
    "addr:street":"Us Hwy 70",
    "iso:country":"US",
    "sg:address":"4106 US Hwy 70",
    "sg:city":"Morehead City",
    "sg:classifiers":[
        {
            "category":"Autos & Motor Vehicles",
            "subcategory":"Auto Supplies",
            "type":"Retail Goods"
        }
    ],
    "sg:phone":"+1 252 726 1016",
    "sg:postcode":"28557",
    "sg:province":"NC",
    "sg:tags":[
        "automobile",
        "parts"
    ],
    "wof:name":"Carquest Auto Parts-Morehead",
    "wof:placetype":"venue"
},
  "geometry": {"coordinates":[-76.768711,34.726863],"type":"Point"}
}