{
  "type": "Feature",
  "properties": {
    "addr:full":"1924 Lantana Dr Winston Salem NC 27127",
    "addr:housenumber":"1924",
    "addr:postcode":"27127",
    "addr:street":"Lantana Dr",
    "iso:country":"US",
    "sg:address":"1924 Lantana Dr",
    "sg:city":"Winston Salem",
    "sg:classifiers":[
        {
            "category":"Building & Trades",
            "subcategory":"Construction",
            "type":"Services"
        }
    ],
    "sg:phone":"+1 336 785 0994",
    "sg:postcode":"27127",
    "sg:province":"NC",
    "sg:tags":[
        "house"
    ],
    "wof:name":"Sias Construction Inc",
    "wof:placetype":"venue"
},
  "geometry": {"coordinates":[-80.275592,36.058033],"type":"Point"}
}