{
  "type": "Feature",
  "properties": {
    "addr:full":"4752 Country Club Rd Winston Salem NC 27104",
    "addr:housenumber":"4752",
    "addr:postcode":"27104",
    "addr:street":"Country Club Rd",
    "iso:country":"US",
    "sg:address":"4752 Country Club Rd",
    "sg:city":"Winston Salem",
    "sg:classifiers":[
        {
            "category":"Autos & Motor Vehicles",
            "subcategory":"Auto Supplies",
            "type":"Retail Goods"
        }
    ],
    "sg:phone":"+1 336 768 2093",
    "sg:postcode":"27104",
    "sg:province":"NC",
    "sg:tags":[
        "tire"
    ],
    "wof:name":"Mock Beroth Tire & Auto Inc",
    "wof:placetype":"venue"
},
  "geometry": {"coordinates":[-80.338224,36.080665],"type":"Point"}
}