{
  "type": "Feature",
  "properties": {
    "iso:country":"US",
    "sg:address":"11025 Carolina Place Pkwy",
    "sg:city":"Pineville",
    "sg:classifiers":[
        {
            "category":"Ice Cream",
            "type":"Food & Drink"
        }
    ],
    "sg:menulink":"http://www.allmenus.com/nc/pineville/227477-dippin-dots/menu/",
    "sg:postcode":"28134",
    "sg:province":"NC",
    "sg:tags":[
        "american"
    ],
    "wof:name":"Dippin' Dots",
    "wof:placetype":"venue"
},
  "geometry": {"coordinates":[-80.879409,35.08267],"type":"Point"}
}