{
  "type": "Feature",
  "properties": {
    "addr:full":"2011 Elk Rd SW Supply NC 28462",
    "addr:housenumber":"2011",
    "addr:postcode":"28462",
    "addr:street":"Elk Rd Sw",
    "iso:country":"US",
    "sg:address":"2011 Elk Rd SW",
    "sg:city":"Supply",
    "sg:classifiers":[
        {
            "category":"Building & Trades",
            "subcategory":"Construction",
            "type":"Services"
        }
    ],
    "sg:phone":"+1 910 842 4003",
    "sg:postcode":"28462",
    "sg:province":"NC",
    "sg:tags":[
        "paving",
        "contractor"
    ],
    "wof:name":"F & R Development",
    "wof:placetype":"venue"
},
  "geometry": {"coordinates":[-78.311353,33.947627],"type":"Point"}
}