{
  "type": "Feature",
  "properties": {
    "addr:full":"202 Prospect St Lexington NC 27292",
    "addr:housenumber":"202",
    "addr:postcode":"27292",
    "addr:street":"Prospect St",
    "iso:country":"US",
    "sg:address":"202 Prospect St",
    "sg:city":"Lexington",
    "sg:classifiers":[
        {
            "category":"Manufacturing",
            "subcategory":"Metals",
            "type":"Manufacturing & Wholesale Goods"
        }
    ],
    "sg:phone":"+1 336 248 2419",
    "sg:postcode":"27292",
    "sg:province":"NC",
    "sg:tags":[
        "steel",
        "met",
        "structural",
        "stampings",
        "mfg"
    ],
    "sg:website":"www.borderconcepts.com",
    "wof:name":"Border Concepts Inc",
    "wof:placetype":"venue"
},
  "geometry": {"coordinates":[-80.277129,35.802579],"type":"Point"}
}