{
  "type": "Feature",
  "properties": {
    "iso:country":"US",
    "sg:address":"6230 Carolina Beach Rd",
    "sg:city":"Wilmington",
    "sg:classifiers":[
        {
            "category":"Manufacturing",
            "subcategory":"Printing",
            "type":"Manufacturing & Wholesale Goods"
        }
    ],
    "sg:phone":"+1 910 392 1300",
    "sg:postcode":"28412",
    "sg:province":"NC",
    "sg:tags":[
        "publisher",
        "guide"
    ],
    "wof:name":"Vista Graphics Visitor Guides",
    "wof:placetype":"venue"
},
  "geometry": {"coordinates":[-77.90056800000001,34.112641],"type":"Point"}
}