{
  "type": "Feature",
  "properties": {
    "addr:full":"1112 Clifton Rd Jacksonville NC 28540",
    "addr:housenumber":"1112",
    "addr:postcode":"28540",
    "addr:street":"Clifton Rd",
    "iso:country":"US",
    "sg:address":"1112 Clifton Rd",
    "sg:city":"Jacksonville",
    "sg:classifiers":[
        {
            "category":"Health Services",
            "subcategory":"Health Practitioner",
            "type":"Services"
        }
    ],
    "sg:phone":"+1   ",
    "sg:postcode":"28540",
    "sg:province":"NC",
    "sg:tags":[
        "consultant"
    ],
    "wof:name":"Sandra D Besper",
    "wof:placetype":"venue"
},
  "geometry": {"coordinates":[-77.43683799999999,34.777178],"type":"Point"}
}