{
  "type": "Feature",
  "properties": {
    "addr:full":"752 Darrell Dr Greenville NC 27834",
    "addr:housenumber":"752",
    "addr:postcode":"27834",
    "addr:street":"Darrell Dr",
    "iso:country":"US",
    "sg:address":"752 Darrell Dr",
    "sg:city":"Greenville",
    "sg:classifiers":[
        {
            "category":"Banks & Credit Unions",
            "subcategory":"Investment Brokerage",
            "type":"Services"
        }
    ],
    "sg:phone":"+1 252 756 4770",
    "sg:postcode":"27834",
    "sg:province":"NC",
    "sg:tags":[
        "advisory"
    ],
    "wof:name":"Gene McCreary Financial",
    "wof:placetype":"venue"
},
  "geometry": {"coordinates":[-77.43705199999999,35.56243],"type":"Point"}
}