{
  "type": "Feature",
  "properties": {
    "addr:full":"255 Fork Lake Dr Clinton NC 28328",
    "addr:housenumber":"255",
    "addr:postcode":"28328",
    "addr:street":"Fork Lake Dr",
    "iso:country":"US",
    "sg:address":"255 Fork Lake Dr",
    "sg:city":"Clinton",
    "sg:classifiers":[
        {
            "category":"Organizations",
            "subcategory":"Political Organization",
            "type":"Services"
        }
    ],
    "sg:phone":"+1 910 592 0362",
    "sg:postcode":"28328",
    "sg:province":"NC",
    "wof:name":"Political Venture",
    "wof:placetype":"venue"
},
  "geometry": {"coordinates":[-78.271057,34.95406],"type":"Point"}
}