{
  "type": "Feature",
  "properties": {
    "addr:full":"1207 W Bessemer Ave Greensboro NC 27408",
    "addr:housenumber":"1207",
    "addr:postcode":"27408",
    "addr:street":"W Bessemer Ave",
    "iso:country":"US",
    "sg:address":"1207 W Bessemer Ave",
    "sg:city":"Greensboro",
    "sg:classifiers":[
        {
            "category":"Real Estate",
            "subcategory":"Real Estate Agent",
            "type":"Services"
        }
    ],
    "sg:phone":"+1 336 574 0440",
    "sg:postcode":"27408",
    "sg:province":"NC",
    "wof:name":"Walker Property Management",
    "wof:placetype":"venue"
},
  "geometry": {"coordinates":[-79.806135,36.086026],"type":"Point"}
}