{
  "type": "Feature",
  "properties": {
    "addr:full":"106 Ventana Ct Mooresville NC 28117",
    "addr:housenumber":"106",
    "addr:postcode":"28117",
    "addr:street":"Ventana Ct",
    "iso:country":"US",
    "sg:address":"106 Ventana Ct",
    "sg:city":"Mooresville",
    "sg:classifiers":[
        {
            "category":"Professional",
            "subcategory":"Management & Consulting",
            "type":"Services"
        }
    ],
    "sg:phone":"+1   ",
    "sg:postcode":"28117",
    "sg:province":"NC",
    "sg:tags":[
        "business"
    ],
    "wof:name":"Proex Consultants LLC",
    "wof:placetype":"venue"
},
  "geometry": {"coordinates":[-80.896106,35.515918],"type":"Point"}
}