{
  "type": "Feature",
  "properties": {
    "iso:country":"US",
    "sg:address":"211 Tunis Rd",
    "sg:city":"Winton",
    "sg:classifiers":[
        {
            "category":"Farming",
            "subcategory":"Aquatic Farm",
            "type":"Manufacturing & Wholesale Goods"
        }
    ],
    "sg:phone":"+1 252 358 1421",
    "sg:postcode":"27986",
    "sg:province":"NC",
    "sg:tags":[
        "fish"
    ],
    "wof:name":"Tunis Fishery Inc",
    "wof:placetype":"venue"
},
  "geometry": {"coordinates":[-76.889107,36.381323],"type":"Point"}
}