{
  "type": "Feature",
  "properties": {
    "iso:country":"US",
    "sg:address":"1353 Pearl St",
    "sg:city":"Statesville",
    "sg:classifiers":[
        {
            "category":"Government",
            "subcategory":"Office",
            "type":"Public Place"
        }
    ],
    "sg:phone":"+1 704 871 8804",
    "sg:postcode":"28677",
    "sg:province":"NC",
    "sg:tags":[
        "housing",
        "program"
    ],
    "wof:name":"Pine Acres Community Center",
    "wof:placetype":"venue"
},
  "geometry": {"coordinates":[-80.910383,35.786964],"type":"Point"}
}