{
  "type": "Feature",
  "properties": {
    "iso:country":"US",
    "sg:address":"350 Eastwood Dr",
    "sg:city":"Cramerton",
    "sg:classifiers":[
        {
            "category":"Manufacturing",
            "subcategory":"Textiles",
            "type":"Manufacturing & Wholesale Goods"
        }
    ],
    "sg:phone":"+1 704 825 0547",
    "sg:postcode":"28092",
    "sg:province":"NC",
    "sg:tags":[
        "mills",
        "yarn"
    ],
    "wof:name":"B R Jenkins Inc",
    "wof:placetype":"venue"
},
  "geometry": {"coordinates":[-81.20825600000001,35.485143],"type":"Point"}
}