{
  "type": "Feature",
  "properties": {
    "iso:country":"US",
    "sg:address":"302 S Church St",
    "sg:city":"Gastonia",
    "sg:classifiers":[
        {
            "category":"Professional",
            "subcategory":"Engineering",
            "type":"Services"
        }
    ],
    "sg:phone":"+1 704 853 0800",
    "sg:postcode":"28054",
    "sg:province":"NC",
    "sg:tags":[
        "engineer"
    ],
    "wof:name":"Excel Civil-Environmental",
    "wof:placetype":"venue"
},
  "geometry": {"coordinates":[-81.16820300000001,35.25962],"type":"Point"}
}