{
  "type": "Feature",
  "properties": {
    "addr:full":"4420 Creedmoor Rd Raleigh NC 27612",
    "addr:housenumber":"4420",
    "addr:postcode":"27612",
    "addr:street":"Creedmoor Rd",
    "iso:country":"US",
    "sg:address":"4420 Creedmoor Rd",
    "sg:city":"Raleigh",
    "sg:classifiers":[
        {
            "category":"Restaurant",
            "type":"Food & Drink"
        }
    ],
    "sg:phone":"+1 919 781 5517",
    "sg:postcode":"27612",
    "sg:province":"NC",
    "sg:tags":[
        "lounge"
    ],
    "wof:name":"Steak and Ale",
    "wof:placetype":"venue"
},
  "geometry": {"coordinates":[-78.68777799999999,35.839291],"type":"Point"}
}