{
  "type": "Feature",
  "properties": {
    "iso:country":"US",
    "sg:address":"234 S Powell St",
    "sg:city":"Forest City",
    "sg:classifiers":[
        {
            "category":"Food & Beverages",
            "subcategory":"Fruits & Vegetables",
            "type":"Retail Goods"
        }
    ],
    "sg:phone":"+1 828 245 8148",
    "sg:postcode":"28043",
    "sg:province":"NC",
    "sg:tags":[
        "produce"
    ],
    "wof:name":"Brier Patch Curb Market",
    "wof:placetype":"venue"
},
  "geometry": {"coordinates":[-81.863798,35.330423],"type":"Point"}
}