{
  "type": "Feature",
  "properties": {
    "iso:country":"US",
    "sg:address":"460 Old Farm Rd",
    "sg:city":"Roanoke Rapids",
    "sg:classifiers":[
        {
            "category":"Freight",
            "type":"Transportation"
        }
    ],
    "sg:phone":"+1 252 535 4356",
    "sg:postcode":"27870",
    "sg:province":"NC",
    "sg:tags":[
        "commercial",
        "storage"
    ],
    "wof:name":"Old Farm Road Self Storage",
    "wof:placetype":"venue"
},
  "geometry": {"coordinates":[-77.635677,36.449116],"type":"Point"}
}