{
  "type": "Feature",
  "properties": {
    "addr:full":"120 Pullen Cir Lawndale NC 28090",
    "addr:housenumber":"120",
    "addr:postcode":"28090",
    "addr:street":"Pullen Cir",
    "iso:country":"US",
    "sg:address":"120 Pullen Cir",
    "sg:city":"Lawndale",
    "sg:classifiers":[
        {
            "category":"Freight",
            "type":"Transportation"
        }
    ],
    "sg:phone":"+1 704 538 5905",
    "sg:postcode":"28090",
    "sg:province":"NC",
    "sg:tags":[
        "operator",
        "local",
        "trucking"
    ],
    "wof:name":"McCabe Trucking",
    "wof:placetype":"venue"
},
  "geometry": {"coordinates":[-81.570277,35.412478],"type":"Point"}
}