{
  "type": "Feature",
  "properties": {
    "iso:country":"US",
    "sg:address":"188 W Main St",
    "sg:city":"Franklin",
    "sg:classifiers":[
        {
            "category":"Government",
            "subcategory":"Office",
            "type":"Public Place"
        }
    ],
    "sg:phone":"+1 828 524 2516",
    "sg:postcode":"28734",
    "sg:province":"NC",
    "sg:tags":[
        "village"
    ],
    "sg:website":"www.franklinnc.com",
    "wof:name":"Franklin Town Office",
    "wof:placetype":"venue"
},
  "geometry": {"coordinates":[-83.38305200000001,35.181259],"type":"Point"}
}