{
  "type": "Feature",
  "properties": {
    "addr:full":"150 Sunset Ave Asheboro NC 27203",
    "addr:housenumber":"150",
    "addr:postcode":"27203",
    "addr:street":"Sunset Ave",
    "iso:country":"US",
    "sg:address":"150 Sunset Ave",
    "sg:city":"Asheboro",
    "sg:classifiers":[
        {
            "category":"Retail",
            "subcategory":"Repair Shop",
            "type":"Services"
        }
    ],
    "sg:phone":"+1 336 629 3396",
    "sg:postcode":"27203",
    "sg:province":"NC",
    "sg:tags":[
        "instrument",
        "musical"
    ],
    "wof:name":"Tone Zone",
    "wof:placetype":"venue"
},
  "geometry": {"coordinates":[-79.816321,35.705851],"type":"Point"}
}