{
  "type": "Feature",
  "properties": {
    "addr:full":"3925 Sedgebrook St High Point NC 27265",
    "addr:housenumber":"3925",
    "addr:postcode":"27265",
    "addr:street":"Sedgebrook St",
    "iso:country":"US",
    "sg:address":"3925 Sedgebrook St",
    "sg:city":"High Point",
    "sg:classifiers":[
        {
            "category":"Freight",
            "type":"Transportation"
        }
    ],
    "sg:phone":"+1 336 812 8060",
    "sg:postcode":"27265",
    "sg:province":"NC",
    "sg:tags":[
        "forwarding"
    ],
    "wof:name":"McIvey Transportation Systems",
    "wof:placetype":"venue"
},
  "geometry": {"coordinates":[-79.96266199999999,36.061015],"type":"Point"}
}