{
  "type": "Feature",
  "properties": {
    "addr:full":"508 Warren St Williamston NC 27892",
    "addr:housenumber":"508",
    "addr:postcode":"27892",
    "addr:street":"Warren St",
    "iso:country":"US",
    "sg:address":"508 Warren St",
    "sg:city":"Williamston",
    "sg:classifiers":[
        {
            "category":"Shopping",
            "type":"Retail Goods"
        }
    ],
    "sg:phone":"+1 252 792 6305",
    "sg:postcode":"27892",
    "sg:province":"NC",
    "sg:tags":[
        "hearing",
        "equipment",
        "supply",
        "impaired"
    ],
    "wof:name":"Williamston Hearing Aid Svc",
    "wof:placetype":"venue"
},
  "geometry": {"coordinates":[-77.052532,35.851342],"type":"Point"}
}