{
  "type": "Feature",
  "properties": {
    "addr:full":"202 Chance St Fayetteville NC 28301",
    "addr:housenumber":"202",
    "addr:postcode":"28301",
    "addr:street":"Chance St",
    "iso:country":"US",
    "sg:address":"202 Chance St",
    "sg:city":"Fayetteville",
    "sg:classifiers":[
        {
            "category":"Retail",
            "subcategory":"Auto Repair",
            "type":"Services"
        }
    ],
    "sg:phone":"+1 910 486 6600",
    "sg:postcode":"28301",
    "sg:province":"NC",
    "sg:tags":[
        "body",
        "automobile",
        "painting"
    ],
    "wof:name":"Ben's Paint & Body Shop",
    "wof:placetype":"venue"
},
  "geometry": {"coordinates":[-78.880188,35.063586],"type":"Point"}
}