{
  "type": "Feature",
  "properties": {
    "addr:full":"230 Charlotte Hwy Asheville NC 28803",
    "addr:housenumber":"230",
    "addr:postcode":"28803",
    "addr:street":"Charlotte Hwy",
    "iso:country":"US",
    "sg:address":"230 Charlotte Hwy",
    "sg:city":"Asheville",
    "sg:classifiers":[
        {
            "category":"Restaurant",
            "type":"Food & Drink"
        }
    ],
    "sg:phone":"+1 828 299 8883",
    "sg:postcode":"28803",
    "sg:province":"NC",
    "wof:name":"D J's Cafe & Diner",
    "wof:placetype":"venue"
},
  "geometry": {"coordinates":[-82.46653999999999,35.549416],"type":"Point"}
}