{
  "type": "Feature",
  "properties": {
    "addr:full":"2416 Moir Farm Rd Lawsonville NC 27022",
    "addr:housenumber":"2416",
    "addr:postcode":"27022",
    "addr:street":"Moir Farm Rd",
    "iso:country":"US",
    "sg:address":"2416 Moir Farm Rd",
    "sg:city":"Lawsonville",
    "sg:phone":"+1 336 871 2589",
    "sg:postcode":"27022",
    "sg:province":"NC",
    "sg:tags":[
        "farm",
        "tobacco"
    ],
    "wof:name":"James Martin",
    "wof:placetype":"venue"
},
  "geometry": {"coordinates":[-80.152351,36.475722],"type":"Point"}
}