{
  "type": "Feature",
  "properties": {
    "iso:country":"US",
    "sg:address":"712 Dickinson Ave",
    "sg:city":"Greenville",
    "sg:classifiers":[
        {
            "category":"Retail",
            "subcategory":"Funeral Services",
            "type":"Services"
        }
    ],
    "sg:phone":"+1   ",
    "sg:postcode":"27834",
    "sg:province":"NC",
    "wof:name":"Roundtree and Assoc Fnrl Hm",
    "wof:placetype":"venue"
},
  "geometry": {"coordinates":[-77.37600399999999,35.609593],"type":"Point"}
}