{
  "type": "Feature",
  "properties": {
    "iso:country":"US",
    "sg:address":"94 James Chapel Rd",
    "sg:city":"Clyde",
    "sg:classifiers":[
        {
            "category":"Organizations",
            "subcategory":"Religious Organization",
            "type":"Services"
        }
    ],
    "sg:phone":"+1   ",
    "sg:postcode":"28721",
    "sg:province":"NC",
    "wof:name":"James Chapel Church",
    "wof:placetype":"venue"
},
  "geometry": {"coordinates":[-82.89050400000001,35.634304],"type":"Point"}
}