{
  "type": "Feature",
  "properties": {
    "addr:full":"53 Clayton St Asheville NC 28801",
    "addr:housenumber":"53",
    "addr:postcode":"28801",
    "addr:street":"Clayton St",
    "iso:country":"US",
    "sg:address":"53 Clayton St",
    "sg:city":"Asheville",
    "sg:classifiers":[
        {
            "category":"Real Estate",
            "subcategory":"Real Estate Agent",
            "type":"Services"
        }
    ],
    "sg:phone":"+1 828 254 0580",
    "sg:postcode":"28801",
    "sg:province":"NC",
    "sg:tags":[
        "appraiser"
    ],
    "wof:name":"David Moore",
    "wof:placetype":"venue"
},
  "geometry": {"coordinates":[-82.548378,35.601754],"type":"Point"}
}