{
  "type": "Feature",
  "properties": {
    "addr:full":"1090 Burke St NW Winston Salem NC 27101",
    "addr:housenumber":"1090",
    "addr:postcode":"27101",
    "addr:street":"Burke St Nw",
    "iso:country":"US",
    "sg:address":"1090 Burke St NW",
    "sg:city":"Winston Salem",
    "sg:classifiers":[
        {
            "category":"Wholesale",
            "subcategory":"Electrical",
            "type":"Manufacturing & Wholesale Goods"
        }
    ],
    "sg:phone":"+1 336 723 3068",
    "sg:postcode":"27101",
    "sg:province":"NC",
    "sg:tags":[
        "household",
        "appliance"
    ],
    "wof:name":"D & L Parts Co Inc",
    "wof:placetype":"venue"
},
  "geometry": {"coordinates":[-80.257586,36.095309],"type":"Point"}
}