{
  "type": "Feature",
  "properties": {
    "addr:full":"500 Rocky Run Rd New Bern NC 28562",
    "addr:housenumber":"500",
    "addr:postcode":"28562",
    "addr:street":"Rocky Run Rd",
    "iso:country":"US",
    "sg:address":"500 Rocky Run Rd",
    "sg:city":"New Bern",
    "sg:classifiers":[
        {
            "category":"Organizations",
            "subcategory":"Religious Organization",
            "type":"Services"
        }
    ],
    "sg:phone":"+1 252 638 3402",
    "sg:postcode":"28562",
    "sg:province":"NC",
    "sg:tags":[
        "church"
    ],
    "wof:name":"St James AME Zion Church",
    "wof:placetype":"venue"
},
  "geometry": {"coordinates":[-77.14580599999999,35.090697],"type":"Point"}
}