{
  "type": "Feature",
  "properties": {
    "iso:country":"US",
    "sg:address":"150 Providence Rd Ste 201",
    "sg:city":"Chapel Hill",
    "sg:classifiers":[
        {
            "category":"Health Services",
            "subcategory":"Clinic",
            "type":"Services"
        }
    ],
    "sg:phone":"+1 919 490 1996",
    "sg:postcode":"27514",
    "sg:province":"NC",
    "sg:tags":[
        "counseling",
        "mental"
    ],
    "wof:name":"Perault Nancy K Lcsw",
    "wof:placetype":"venue"
},
  "geometry": {"coordinates":[-79.00749999999999,35.9515],"type":"Point"}
}