{
  "type": "Feature",
  "properties": {
    "iso:country":"US",
    "sg:address":"4301 Shamrock Dr",
    "sg:city":"Charlotte",
    "sg:classifiers":[
        {
            "category":"Organizations",
            "subcategory":"Religious Organization",
            "type":"Services"
        }
    ],
    "sg:phone":"+1 704 563 3349",
    "sg:postcode":"28215",
    "sg:province":"NC",
    "sg:tags":[
        "church"
    ],
    "wof:name":"Shamrock Drive Baptist Church",
    "wof:placetype":"venue"
},
  "geometry": {"coordinates":[-80.75147,35.22951],"type":"Point"}
}