{
  "type": "Feature",
  "properties": {
    "addr:full":"12059 University City Blvd Harrisburg NC 28075",
    "addr:housenumber":"12059",
    "addr:postcode":"28075",
    "addr:street":"University City Blvd",
    "iso:country":"US",
    "sg:address":"12059 University City Blvd",
    "sg:city":"Harrisburg",
    "sg:classifiers":[
        {
            "category":"Social Services",
            "subcategory":"Job Training",
            "type":"Services"
        },
        {
            "category":"Retail",
            "subcategory":"Repair Shop",
            "type":"Services"
        },
        {
            "category":"Shopping",
            "subcategory":"Computers & Home Electronics",
            "type":"Retail Goods"
        },
        {
            "category":"Education",
            "subcategory":"School",
            "type":"Public Place"
        },
        {
            "category":"Professional",
            "subcategory":"Computer Services",
            "type":"Services"
        }
    ],
    "sg:phone":"+1 704 455 8414",
    "sg:postcode":"28075",
    "sg:province":"NC",
    "sg:tags":[
        "recovery",
        "supply",
        "repair-business",
        "k-",
        "hardware",
        "video",
        "private",
        "games-service",
        "data",
        "software"
    ],
    "wof:name":"CTRL ALT DeleteComputers",
    "wof:placetype":"venue"
},
  "geometry": {"coordinates":[-80.680612,35.315804],"type":"Point"}
}