{
  "type": "Feature",
  "properties": {
    "iso:country":"US",
    "sg:address":"5850 Farringdon Pl",
    "sg:city":"Raleigh",
    "sg:classifiers":[
        {
            "category":"Professional",
            "subcategory":"Accounting & Tax Preparation",
            "type":"Services"
        }
    ],
    "sg:phone":"+1 919 873 0890",
    "sg:postcode":"27609",
    "sg:province":"NC",
    "sg:tags":[
        "accountant"
    ],
    "wof:name":"Todd Rivenbark & Puryear",
    "wof:placetype":"venue"
},
  "geometry": {"coordinates":[-78.621723,35.861618],"type":"Point"}
}