{
  "type": "Feature",
  "properties": {
    "addr:full":"7330 Old Wake Forest Rd Raleigh NC 27616",
    "addr:housenumber":"7330",
    "addr:postcode":"27616",
    "addr:street":"Old Wake Forest Rd",
    "iso:country":"US",
    "sg:address":"7330 Old Wake Forest Rd",
    "sg:city":"Raleigh",
    "sg:classifiers":[
        {
            "category":"Home & Garden",
            "subcategory":"Carpets & Floor Coverings",
            "type":"Retail Goods"
        },
        {
            "category":"Home & Garden",
            "subcategory":"Building Materials",
            "type":"Retail Goods"
        },
        {
            "category":"Building & Trades",
            "subcategory":"Construction",
            "type":"Services"
        },
        {
            "category":"Manufacturing",
            "subcategory":"Building Materials",
            "type":"Manufacturing & Wholesale Goods"
        },
        {
            "category":"Home & Garden",
            "subcategory":"Furniture",
            "type":"Retail Goods"
        }
    ],
    "sg:phone":"+1 877 760 8339",
    "sg:postcode":"27616",
    "sg:province":"NC",
    "sg:tags":[
        "roofing",
        "cabinet",
        "gutter",
        "supply",
        "consultant",
        "rug",
        "improvement",
        "downspouts",
        "equipment",
        "window",
        "siding",
        "doors",
        "tile-contractors",
        "frames",
        "contractor",
        "equipment-household",
        "accessory",
        "kitchen"
    ],
    "sg:website":"http://raleigh.citysearch.com/profile/external/603830182/raleigh_nc/sears_home_improvement_products.html?publisher=yellowpages&reference_id=1&placement=ypwebsitemip",
    "wof:name":"Sears Home Improvement Products",
    "wof:placetype":"venue"
},
  "geometry": {"coordinates":[-78.57128400000001,35.867477],"type":"Point"}
}