{
  "type": "Feature",
  "properties": {
    "iso:country":"US",
    "sg:address":"2006 Sandpiper Rd",
    "sg:city":"Corolla",
    "sg:classifiers":[
        {
            "category":"Professional",
            "type":"Services"
        }
    ],
    "sg:phone":"+1   ",
    "sg:postcode":"27927",
    "sg:province":"NC",
    "wof:name":"McCabe Services LLC",
    "wof:placetype":"venue"
},
  "geometry": {"coordinates":[-75.860142,36.498669],"type":"Point"}
}