{
  "type": "Feature",
  "properties": {
    "addr:full":"51 3rd St SE Hickory NC 28602",
    "addr:housenumber":"51",
    "addr:postcode":"28602",
    "addr:street":"3Rd St Se",
    "iso:country":"US",
    "sg:address":"51 3rd St SE",
    "sg:city":"Hickory",
    "sg:classifiers":[
        {
            "category":"Manufacturing",
            "subcategory":"Glass & Minerals",
            "type":"Manufacturing & Wholesale Goods"
        },
        {
            "category":"Manufacturing",
            "subcategory":"Rubber & Plastics",
            "type":"Manufacturing & Wholesale Goods"
        }
    ],
    "sg:phone":"+1 828 324 6488",
    "sg:postcode":"28602",
    "sg:province":"NC",
    "sg:tags":[
        "fabricator",
        "product",
        "fiber",
        "mfg"
    ],
    "sg:website":"www.diversified-composites.com",
    "wof:name":"Diversified Composites  Inc",
    "wof:placetype":"venue"
},
  "geometry": {"coordinates":[-81.332358,35.731356],"type":"Point"}
}