{
  "type": "Feature",
  "properties": {
    "iso:country":"US",
    "sg:address":"4026 S Tryon St",
    "sg:city":"Charlotte",
    "sg:classifiers":[
        {
            "category":"Shopping",
            "subcategory":"Music",
            "type":"Retail Goods"
        }
    ],
    "sg:phone":"+1 704 527 7427",
    "sg:postcode":"28217",
    "sg:province":"NC",
    "wof:name":"Nu World Records & Production",
    "wof:placetype":"venue"
},
  "geometry": {"coordinates":[-80.88126200000001,35.190848],"type":"Point"}
}