{
  "type": "Feature",
  "properties": {
    "iso:country":"US",
    "sg:address":"229 Hillsboro St",
    "sg:city":"Oxford",
    "sg:classifiers":[
        {
            "category":"Organizations",
            "subcategory":"Non-profit Organization",
            "type":"Services"
        }
    ],
    "sg:phone":"+1 919 693 9396",
    "sg:postcode":"27565",
    "sg:province":"NC",
    "sg:tags":[
        "information",
        "alcoholism",
        "treatment"
    ],
    "wof:name":"Caring Hearts Counseling Svc",
    "wof:placetype":"venue"
},
  "geometry": {"coordinates":[-78.591779,36.310156],"type":"Point"}
}