{
  "type": "Feature",
  "properties": {
    "iso:country":"US",
    "sg:address":"7020 Tabor Ln",
    "sg:city":"Charlotte",
    "sg:classifiers":[
        {
            "category":"Professional",
            "subcategory":"Advertising",
            "type":"Services"
        }
    ],
    "sg:phone":"+1   ",
    "sg:postcode":"28211",
    "sg:province":"NC",
    "wof:name":"Exhibit Service",
    "wof:placetype":"venue"
},
  "geometry": {"coordinates":[-80.765593,35.152317],"type":"Point"}
}