{
  "type": "Feature",
  "properties": {
    "addr:full":"2513 Clark Ave Raleigh NC 27607",
    "addr:housenumber":"2513",
    "addr:postcode":"27607",
    "addr:street":"Clark Ave",
    "iso:country":"US",
    "sg:address":"2513 Clark Ave",
    "sg:city":"Raleigh",
    "sg:classifiers":[
        {
            "category":"Organizations",
            "subcategory":"Community Association",
            "type":"Services"
        }
    ],
    "sg:phone":"+1 919 829 0111",
    "sg:postcode":"27607",
    "sg:province":"NC",
    "sg:tags":[
        "club"
    ],
    "wof:name":"Sigma Pi",
    "wof:placetype":"venue"
},
  "geometry": {"coordinates":[-78.66870400000001,35.789871],"type":"Point"}
}