{
  "type": "Feature",
  "properties": {
    "addr:full":"117 Western Blvd Jacksonville NC 28546",
    "addr:housenumber":"117",
    "addr:postcode":"28546",
    "addr:street":"Western Blvd",
    "iso:country":"US",
    "sg:address":"117 Western Blvd",
    "sg:city":"Jacksonville",
    "sg:classifiers":[
        {
            "category":"Restaurant",
            "type":"Food & Drink"
        }
    ],
    "sg:menulink":"http://www.allmenus.com/nc/jacksonville/205209-taco-bell/menu/",
    "sg:phone":"+1 910 353 1832",
    "sg:postcode":"28546",
    "sg:province":"NC",
    "sg:tags":[
        "american",
        "mexican"
    ],
    "wof:name":"Taco Bell",
    "wof:placetype":"venue"
},
  "geometry": {"coordinates":[-77.38034399999999,34.747129],"type":"Point"}
}