{
  "type": "Feature",
  "properties": {
    "addr:full":"576 Executive Pl Fayetteville NC 28305",
    "addr:housenumber":"576",
    "addr:postcode":"28305",
    "addr:street":"Executive Pl",
    "iso:country":"US",
    "sg:address":"576 Executive Pl",
    "sg:city":"Fayetteville",
    "sg:classifiers":[
        {
            "category":"Insurance",
            "subcategory":"Insurance Agent",
            "type":"Services"
        }
    ],
    "sg:phone":"+1 910 323 2588",
    "sg:postcode":"28305",
    "sg:province":"NC",
    "wof:name":"Michael L Warren Insurance",
    "wof:placetype":"venue"
},
  "geometry": {"coordinates":[-78.924311,35.049282],"type":"Point"}
}