{
  "type": "Feature",
  "properties": {
    "addr:full":"2518 Carolina Beach Rd Wilmington NC 28401",
    "addr:housenumber":"2518",
    "addr:postcode":"28401",
    "addr:street":"Carolina Beach Rd",
    "iso:country":"US",
    "sg:address":"2518 Carolina Beach Rd",
    "sg:city":"Wilmington",
    "sg:classifiers":[
        {
            "category":"Restaurant",
            "type":"Food & Drink"
        }
    ],
    "sg:menulink":"http://www.allmenus.com/nc/wilmington/154661-hardees/menu/",
    "sg:phone":"+1 910 762 3904",
    "sg:postcode":"28401",
    "sg:province":"NC",
    "sg:tags":[
        "burger",
        "american"
    ],
    "wof:name":"Hardee's",
    "wof:placetype":"venue"
},
  "geometry": {"coordinates":[-77.93511599999999,34.19286],"type":"Point"}
}