{
  "type": "Feature",
  "properties": {
    "iso:country":"US",
    "sg:address":"105 Charles Ct",
    "sg:city":"Chocowinity",
    "sg:classifiers":[
        {
            "category":"Professional",
            "type":"Services"
        }
    ],
    "sg:phone":"+1 252 946 8915",
    "sg:postcode":"27817",
    "sg:province":"NC",
    "wof:name":"Pdma Inc",
    "wof:placetype":"venue"
},
  "geometry": {"coordinates":[-77.04671999999999,35.494997],"type":"Point"}
}