{
  "type": "Feature",
  "properties": {
    "addr:full":"2005 James Winston Rd Oxford NC 27565",
    "addr:housenumber":"2005",
    "addr:postcode":"27565",
    "addr:street":"James Winston Rd",
    "iso:country":"US",
    "sg:address":"2005 James Winston Rd",
    "sg:city":"Oxford",
    "sg:classifiers":[
        {
            "category":"Professional",
            "subcategory":"Business Services",
            "type":"Services"
        }
    ],
    "sg:phone":"+1   ",
    "sg:postcode":"27565",
    "sg:province":"NC",
    "wof:name":"Larry Smith",
    "wof:placetype":"venue"
},
  "geometry": {"coordinates":[-78.684521,36.511213],"type":"Point"}
}