{
  "type": "Feature",
  "properties": {
    "addr:full":"304 E Wallace St Burgaw NC 28425",
    "addr:housenumber":"304",
    "addr:postcode":"28425",
    "addr:street":"E Wallace St",
    "iso:country":"US",
    "sg:address":"304 E Wallace St",
    "sg:city":"Burgaw",
    "sg:classifiers":[
        {
            "category":"Government",
            "subcategory":"Office",
            "type":"Public Place"
        }
    ],
    "sg:phone":"+1 910 259 5003",
    "sg:postcode":"28425",
    "sg:province":"NC",
    "sg:tags":[
        "village"
    ],
    "wof:name":"Town Of Burgaw Waste Water",
    "wof:placetype":"venue"
},
  "geometry": {"coordinates":[-77.92528900000001,34.556221],"type":"Point"}
}