{
  "type": "Feature",
  "properties": {
    "addr:full":"726 Tyvola Rd Charlotte NC 28217",
    "addr:housenumber":"726",
    "addr:postcode":"28217",
    "addr:street":"Tyvola Rd",
    "iso:country":"US",
    "sg:address":"726 Tyvola Rd",
    "sg:city":"Charlotte",
    "sg:classifiers":[
        {
            "category":"Health Services",
            "subcategory":"Optometrist",
            "type":"Services"
        }
    ],
    "sg:phone":"+1 704 522 8000",
    "sg:postcode":"28217",
    "sg:province":"NC",
    "sg:tags":[
        "clinic",
        "eye",
        "care"
    ],
    "wof:name":"Eye Care Clinic Od-PA",
    "wof:placetype":"venue"
},
  "geometry": {"coordinates":[-80.881094,35.165383],"type":"Point"}
}