{
  "type": "Feature",
  "properties": {
    "iso:country":"US",
    "sg:address":"802 S Graham Hopedale Rd",
    "sg:city":"Burlington",
    "sg:classifiers":[
        {
            "category":"Retail",
            "subcategory":"Repair Shop",
            "type":"Services"
        }
    ],
    "sg:phone":"+1 336 570 9739",
    "sg:postcode":"27217",
    "sg:province":"NC",
    "sg:tags":[
        "textile"
    ],
    "wof:name":"Cortina Fabrics",
    "wof:placetype":"venue"
},
  "geometry": {"coordinates":[-79.40613399999999,36.089417],"type":"Point"}
}