{
  "type": "Feature",
  "properties": {
    "addr:full":"1105 Fairchild Rd Winston Salem NC 27105",
    "addr:housenumber":"1105",
    "addr:postcode":"27105",
    "addr:street":"Fairchild Rd",
    "iso:country":"US",
    "sg:address":"1105 Fairchild Rd",
    "sg:city":"Winston Salem",
    "sg:classifiers":[
        {
            "category":"Professional",
            "subcategory":"Accounting & Tax Preparation",
            "type":"Services"
        }
    ],
    "sg:phone":"+1 336 776 1105",
    "sg:postcode":"27105",
    "sg:province":"NC",
    "sg:tags":[
        "laser",
        "printing",
        "mailing"
    ],
    "wof:name":"Arista Information Systems",
    "wof:placetype":"venue"
},
  "geometry": {"coordinates":[-80.223617,36.128803],"type":"Point"}
}