{
  "type": "Feature",
  "properties": {
    "addr:full":"324 Leafmore Dr Charlotte NC 28213",
    "addr:housenumber":"324",
    "addr:postcode":"28213",
    "addr:street":"Leafmore Dr",
    "iso:country":"US",
    "sg:address":"324 Leafmore Dr",
    "sg:city":"Charlotte",
    "sg:classifiers":[
        {
            "category":"Building & Trades",
            "subcategory":"Construction",
            "type":"Services"
        },
        {
            "category":"Manufacturing",
            "subcategory":"Printing",
            "type":"Manufacturing & Wholesale Goods"
        }
    ],
    "sg:phone":"+1 704 596 5640",
    "sg:postcode":"28213",
    "sg:province":"NC",
    "sg:tags":[
        "hanging",
        "printer",
        "contractor"
    ],
    "wof:name":"Robert's Printing",
    "wof:placetype":"venue"
},
  "geometry": {"coordinates":[-80.784493,35.254926],"type":"Point"}
}