{
  "type": "Feature",
  "properties": {
    "addr:full":"1874 Quail Ridge Rd Greenville NC 27858",
    "addr:housenumber":"1874",
    "addr:postcode":"27858",
    "addr:street":"Quail Ridge Rd",
    "iso:country":"US",
    "sg:address":"1874 Quail Ridge Rd",
    "sg:city":"Greenville",
    "sg:classifiers":[
        {
            "category":"Real Estate",
            "subcategory":"Real Estate Agent",
            "type":"Services"
        }
    ],
    "sg:phone":"+1 252 756 2645",
    "sg:postcode":"27858",
    "sg:province":"NC",
    "wof:name":"Wo & Jane Moore Rental",
    "wof:placetype":"venue"
},
  "geometry": {"coordinates":[-77.34335900000001,35.582169],"type":"Point"}
}