{
  "type": "Feature",
  "properties": {
    "iso:country":"US",
    "sg:address":"413 W Queen St",
    "sg:city":"Edenton",
    "sg:classifiers":[
        {
            "category":"Shopping",
            "subcategory":"Discount & Variety Stores",
            "type":"Retail Goods"
        }
    ],
    "sg:phone":"+1 252 482 8096",
    "sg:postcode":"27932",
    "sg:province":"NC",
    "sg:website":"http://www.dollargeneral.com",
    "wof:name":"Dollar General",
    "wof:placetype":"venue"
},
  "geometry": {"coordinates":[-76.61773700000001,36.061779],"type":"Point"}
}