{
  "type": "Feature",
  "properties": {
    "addr:full":"1248 Gordon Rd Pinnacle NC 27043",
    "addr:housenumber":"1248",
    "addr:postcode":"27043",
    "addr:street":"Gordon Rd",
    "iso:country":"US",
    "sg:address":"1248 Gordon Rd",
    "sg:city":"Pinnacle",
    "sg:classifiers":[
        {
            "category":"Building & Trades",
            "subcategory":"Plumbing",
            "type":"Services"
        }
    ],
    "sg:phone":"+1 336 368 3163",
    "sg:postcode":"27043",
    "sg:province":"NC",
    "sg:tags":[
        "plumbing",
        "contractor"
    ],
    "wof:name":"Baker Plumbing & Utilities",
    "wof:placetype":"venue"
},
  "geometry": {"coordinates":[-80.43696199999999,36.361746],"type":"Point"}
}