{
  "type": "Feature",
  "properties": {
    "addr:full":"4420 Lake Boone Trl Raleigh NC 27607",
    "addr:housenumber":"4420",
    "addr:postcode":"27607",
    "addr:street":"Lake Boone Trl",
    "iso:country":"US",
    "sg:address":"4420 Lake Boone Trl",
    "sg:city":"Raleigh",
    "sg:classifiers":[
        {
            "category":"Health Services",
            "subcategory":"Doctor",
            "type":"Services"
        }
    ],
    "sg:phone":"+1 919 784 3023",
    "sg:postcode":"27607",
    "sg:province":"NC",
    "sg:tags":[
        "physician",
        "surgeon",
        "radiology",
        "surgeons"
    ],
    "wof:name":"Raleigh Radiology",
    "wof:placetype":"venue"
},
  "geometry": {"coordinates":[-78.704095,35.815497],"type":"Point"}
}