{
  "type": "Feature",
  "properties": {
    "addr:full":"536 Autrytown Rd Elizabethtown NC 28337",
    "addr:housenumber":"536",
    "addr:postcode":"28337",
    "addr:street":"Autrytown Rd",
    "iso:country":"US",
    "sg:address":"536 Autrytown Rd",
    "sg:city":"Elizabethtown",
    "sg:classifiers":[
        {
            "category":"Manufacturing",
            "subcategory":"Lumber",
            "type":"Manufacturing & Wholesale Goods"
        }
    ],
    "sg:phone":"+1 910 588 4793",
    "sg:postcode":"28337",
    "sg:province":"NC",
    "sg:tags":[
        "logging"
    ],
    "wof:name":"Autry Logging",
    "wof:placetype":"venue"
},
  "geometry": {"coordinates":[-78.487897,34.706067],"type":"Point"}
}