{
  "type": "Feature",
  "properties": {
    "iso:country":"US",
    "sg:address":"4701 Equipment Dr",
    "sg:city":"Charlotte",
    "sg:classifiers":[
        {
            "category":"Manufacturing",
            "subcategory":"Motor Vehicles & Parts",
            "type":"Manufacturing & Wholesale Goods"
        },
        {
            "category":"Wholesale",
            "subcategory":"Auto Parts",
            "type":"Manufacturing & Wholesale Goods"
        },
        {
            "category":"Retail",
            "subcategory":"Auto Repair",
            "type":"Services"
        },
        {
            "category":"Autos & Motor Vehicles",
            "subcategory":"Auto Supplies",
            "type":"Retail Goods"
        }
    ],
    "sg:phone":"+1 704 598 0570",
    "sg:postcode":"28269",
    "sg:province":"NC",
    "sg:tags":[
        "body",
        "shop",
        "tire",
        "automobile",
        "supply-wholesale",
        "accessory",
        "equipment",
        "retread",
        "recap",
        "service-equipment",
        "repairing",
        "manufacturer"
    ],
    "sg:website":"http://www.wingfootct.com",
    "wof:name":"Wingfoot Commercial Tire Systems",
    "wof:placetype":"venue"
},
  "geometry": {"coordinates":[-80.80349,35.276649],"type":"Point"}
}