{
  "type": "Feature",
  "properties": {
    "iso:country":"US",
    "sg:address":"4225 State Hwy 11 S",
    "sg:city":"Winterville",
    "sg:classifiers":[
        {
            "category":"Utilities",
            "subcategory":"Mobile Phone",
            "type":"Services"
        }
    ],
    "sg:phone":"+1 252 321 2666",
    "sg:postcode":"28590",
    "sg:province":"NC",
    "sg:tags":[
        "telephone",
        "cellular"
    ],
    "wof:name":"Us Cellular Inc",
    "wof:placetype":"venue"
},
  "geometry": {"coordinates":[-77.40808699999999,35.527191],"type":"Point"}
}