{
  "type": "Feature",
  "properties": {
    "addr:full":"207 Center St Spindale NC 28160",
    "addr:housenumber":"207",
    "addr:postcode":"28160",
    "addr:street":"Center St",
    "iso:country":"US",
    "sg:address":"207 Center St",
    "sg:city":"Spindale",
    "sg:classifiers":[
        {
            "category":"Shopping",
            "subcategory":"Catalog Store",
            "type":"Retail Goods"
        }
    ],
    "sg:phone":"+1 828 288 8207",
    "sg:postcode":"28160",
    "sg:province":"NC",
    "sg:tags":[
        "mail",
        "house"
    ],
    "wof:name":"Lynz Carz",
    "wof:placetype":"venue"
},
  "geometry": {"coordinates":[-81.929542,35.354392],"type":"Point"}
}