{
  "type": "Feature",
  "properties": {
    "addr:full":"675 Britt Rd Newton Grove NC 28366",
    "addr:housenumber":"675",
    "addr:postcode":"28366",
    "addr:street":"Britt Rd",
    "iso:country":"US",
    "sg:address":"675 Britt Rd",
    "sg:city":"Newton Grove",
    "sg:classifiers":[
        {
            "category":"Farming",
            "subcategory":"Farm",
            "type":"Manufacturing & Wholesale Goods"
        }
    ],
    "sg:phone":"+1 910 594 3392",
    "sg:postcode":"28366",
    "sg:province":"NC",
    "sg:tags":[
        "crop",
        "general"
    ],
    "wof:name":"Tjm Farms Inc",
    "wof:placetype":"venue"
},
  "geometry": {"coordinates":[-78.34208700000001,35.1997],"type":"Point"}
}