{
  "type": "Feature",
  "properties": {
    "addr:full":"205 Alderney Ct Waxhaw NC 28173",
    "addr:housenumber":"205",
    "addr:postcode":"28173",
    "addr:street":"Alderney Ct",
    "iso:country":"US",
    "sg:address":"205 Alderney Ct",
    "sg:city":"Waxhaw",
    "sg:classifiers":[
        {
            "category":"Retail",
            "subcategory":"Auto Repair",
            "type":"Services"
        }
    ],
    "sg:phone":"+1   ",
    "sg:postcode":"28173",
    "sg:province":"NC",
    "sg:tags":[
        "dent"
    ],
    "wof:name":"Dent Demon Inc",
    "wof:placetype":"venue"
},
  "geometry": {"coordinates":[-80.758134,35.002396],"type":"Point"}
}