{
  "type": "Feature",
  "properties": {
    "iso:country":"US",
    "sg:address":"828 Smoky Park Hwy",
    "sg:city":"Candler",
    "sg:classifiers":[
        {
            "category":"Organizations",
            "subcategory":"Religious Organization",
            "type":"Services"
        }
    ],
    "sg:phone":"+1 828 667 8867",
    "sg:postcode":"28715",
    "sg:province":"NC",
    "sg:website":"www.goodnewsnc.net",
    "wof:name":"Good News Baptist Church",
    "wof:placetype":"venue"
},
  "geometry": {"coordinates":[-82.65089500000001,35.548387],"type":"Point"}
}