{
  "type": "Feature",
  "properties": {
    "addr:full":"1329 Stallings Rd Matthews NC 28104",
    "addr:housenumber":"1329",
    "addr:postcode":"28104",
    "addr:street":"Stallings Rd",
    "iso:country":"US",
    "sg:address":"1329 Stallings Rd",
    "sg:city":"Matthews",
    "sg:classifiers":[
        {
            "category":"Organizations",
            "subcategory":"Religious Organization",
            "type":"Services"
        }
    ],
    "sg:phone":"+1 704 821 4175",
    "sg:postcode":"28104",
    "sg:province":"NC",
    "sg:tags":[
        "church"
    ],
    "wof:name":"Grace Covenant Community Chr",
    "wof:placetype":"venue"
},
  "geometry": {"coordinates":[-80.680949,35.09444],"type":"Point"}
}