{
  "type": "Feature",
  "properties": {
    "addr:full":"1220 Morgan St Gastonia NC 28054",
    "addr:housenumber":"1220",
    "addr:postcode":"28054",
    "addr:street":"Morgan St",
    "iso:country":"US",
    "sg:address":"1220 Morgan St",
    "sg:city":"Gastonia",
    "sg:classifiers":[
        {
            "category":"Professional",
            "subcategory":"Accounting & Tax Preparation",
            "type":"Services"
        }
    ],
    "sg:phone":"+1   ",
    "sg:postcode":"28054",
    "sg:province":"NC",
    "sg:tags":[
        "return"
    ],
    "wof:name":"Lama Services",
    "wof:placetype":"venue"
},
  "geometry": {"coordinates":[-81.178456,35.244672],"type":"Point"}
}