{
  "type": "Feature",
  "properties": {
    "iso:country":"US",
    "sg:address":"109 Hill St",
    "sg:city":"Elizabethtown",
    "sg:classifiers":[
        {
            "category":"Social Services",
            "type":"Services"
        }
    ],
    "sg:phone":"+1 910 862 2608",
    "sg:postcode":"28337",
    "sg:province":"NC",
    "sg:tags":[
        "youth",
        "organization",
        "center"
    ],
    "wof:name":"Girl Scouts",
    "wof:placetype":"venue"
},
  "geometry": {"coordinates":[-78.597692,34.626119],"type":"Point"}
}