{
  "type": "Feature",
  "properties": {
    "iso:country":"US",
    "sg:address":"14135 Ballantyne Corporate Pl # 225",
    "sg:city":"Charlotte",
    "sg:classifiers":[
        {
            "category":"Health Services",
            "subcategory":"Doctor",
            "type":"Services"
        }
    ],
    "sg:phone":"+1 704 542 8521",
    "sg:postcode":"28277",
    "sg:province":"NC",
    "sg:tags":[
        "physician",
        "immunology",
        "allergy",
        "surgeons",
        "treatment",
        "surgeon"
    ],
    "sg:website":"http://www.carolinaasthma.com",
    "wof:name":"Roberts, Richard S, Md - Carolina Asthma & Allergy Ctr",
    "wof:placetype":"venue"
},
  "geometry": {"coordinates":[-80.857482,35.058338],"type":"Point"}
}