{
  "type": "Feature",
  "properties": {
    "addr:full":"3521 Carver School Rd Winston Salem NC 27105",
    "addr:housenumber":"3521",
    "addr:postcode":"27105",
    "addr:street":"Carver School Rd",
    "iso:country":"US",
    "sg:address":"3521 Carver School Rd",
    "sg:city":"Winston Salem",
    "sg:classifiers":[
        {
            "category":"Recreation",
            "type":"Entertainment"
        }
    ],
    "sg:phone":"+1 336 727 2580",
    "sg:postcode":"27105",
    "sg:province":"NC",
    "sg:tags":[
        "hall",
        "auditorium"
    ],
    "wof:name":"Carl H Russell Community Ctr",
    "wof:placetype":"venue"
},
  "geometry": {"coordinates":[-80.208702,36.134288],"type":"Point"}
}