{
  "type": "Feature",
  "properties": {
    "addr:full":"939 Ideal Way Charlotte NC 28203",
    "addr:housenumber":"939",
    "addr:postcode":"28203",
    "addr:street":"Ideal Way",
    "iso:country":"US",
    "sg:address":"939 Ideal Way",
    "sg:city":"Charlotte",
    "sg:classifiers":[
        {
            "category":"Organizations",
            "subcategory":"Religious Organization",
            "type":"Services"
        }
    ],
    "sg:phone":"+1 704 373 2065",
    "sg:postcode":"28203",
    "sg:province":"NC",
    "sg:tags":[
        "church"
    ],
    "wof:name":"Catholic Church St Peters",
    "wof:placetype":"venue"
},
  "geometry": {"coordinates":[-80.850543,35.201568],"type":"Point"}
}