{
  "type": "Feature",
  "properties": {
    "iso:country":"US",
    "sg:address":"1125 Kildaire Farm Rd",
    "sg:city":"Cary",
    "sg:classifiers":[
        {
            "category":"Health Services",
            "subcategory":"Doctor",
            "type":"Services"
        }
    ],
    "sg:phone":"+1 919 388 4450",
    "sg:postcode":"27511",
    "sg:province":"NC",
    "wof:name":"Stadiem Michael MD",
    "wof:placetype":"venue"
},
  "geometry": {"coordinates":[-78.781673,35.769379],"type":"Point"}
}