{
  "type": "Feature",
  "properties": {
    "addr:full":"8100 Arrowridge Blvd Charlotte NC 28273",
    "addr:housenumber":"8100",
    "addr:postcode":"28273",
    "addr:street":"Arrowridge Blvd",
    "iso:country":"US",
    "sg:address":"8100 Arrowridge Blvd",
    "sg:city":"Charlotte",
    "sg:classifiers":[
        {
            "category":"Wholesale",
            "subcategory":"Machinery & Supplies",
            "type":"Manufacturing & Wholesale Goods"
        }
    ],
    "sg:phone":"+1 704 522 1106",
    "sg:postcode":"28273",
    "sg:province":"NC",
    "sg:tags":[
        "equipment",
        "safety",
        "clothing"
    ],
    "wof:name":"Lehigh Safety Shoe Co",
    "wof:placetype":"venue"
},
  "geometry": {"coordinates":[-80.91231399999999,35.129888],"type":"Point"}
}