{
  "type": "Feature",
  "properties": {
    "addr:full":"9300 Harris Corners Pkwy Charlotte NC 28269",
    "addr:housenumber":"9300",
    "addr:postcode":"28269",
    "addr:street":"Harris Corners Pkwy",
    "iso:country":"US",
    "sg:address":"9300 Harris Corners Pkwy",
    "sg:city":"Charlotte",
    "sg:classifiers":[
        {
            "category":"Health Services",
            "subcategory":"Doctor",
            "type":"Services"
        }
    ],
    "sg:phone":"+1 704 921 5663",
    "sg:postcode":"28269",
    "sg:province":"NC",
    "sg:tags":[
        "physician",
        "surgeon"
    ],
    "wof:name":"Passport Health",
    "wof:placetype":"venue"
},
  "geometry": {"coordinates":[-80.845997,35.345923],"type":"Point"}
}