{
  "type": "Feature",
  "properties": {
    "iso:country":"US",
    "sg:address":"215 S Fir Ave",
    "sg:city":"Siler City",
    "sg:classifiers":[
        {
            "category":"Professional",
            "subcategory":"Business Services",
            "type":"Services"
        }
    ],
    "sg:phone":"+1 919 663 5650",
    "sg:postcode":"27344",
    "sg:province":"NC",
    "sg:tags":[
        "arbitration"
    ],
    "wof:name":"Mediation Network Of Nc",
    "wof:placetype":"venue"
},
  "geometry": {"coordinates":[-79.469008,35.720024],"type":"Point"}
}