{
  "type": "Feature",
  "properties": {
    "iso:country":"US",
    "sg:address":"2408 Sunset Ave",
    "sg:city":"Rocky Mount",
    "sg:classifiers":[
        {
            "category":"Retail",
            "subcategory":"Laundry & Dry Cleaning",
            "type":"Services"
        }
    ],
    "sg:phone":"+1 252 443 4700",
    "sg:postcode":"27804",
    "sg:province":"NC",
    "wof:name":"Clean-Clean Dry Cleaners",
    "wof:placetype":"venue"
},
  "geometry": {"coordinates":[-77.82656900000001,35.960612],"type":"Point"}
}