{
  "type": "Feature",
  "properties": {
    "addr:full":"366 S Main St Jefferson NC 28640",
    "addr:housenumber":"366",
    "addr:postcode":"28640",
    "addr:street":"S Main St",
    "iso:country":"US",
    "sg:address":"366 S Main St",
    "sg:city":"Jefferson",
    "sg:classifiers":[
        {
            "category":"Real Estate",
            "subcategory":"Real Estate Agent",
            "type":"Services"
        }
    ],
    "sg:phone":"+1 336 846 8977",
    "sg:postcode":"28640",
    "sg:province":"NC",
    "wof:name":"Buyers Choice Realty",
    "wof:placetype":"venue"
},
  "geometry": {"coordinates":[-81.475391,36.417233],"type":"Point"}
}