{
  "type": "Feature",
  "properties": {
    "iso:country":"US",
    "sg:address":"4316 Bayliner Dr",
    "sg:city":"Raleigh",
    "sg:classifiers":[
        {
            "category":"Real Estate",
            "subcategory":"Real Estate Agent",
            "type":"Services"
        }
    ],
    "sg:phone":"+1 919 850 2222",
    "sg:postcode":"27604",
    "sg:province":"NC",
    "sg:tags":[
        "investment"
    ],
    "wof:name":"FCI Inc",
    "wof:placetype":"venue"
},
  "geometry": {"coordinates":[-78.59626299999999,35.840831],"type":"Point"}
}