{
  "type": "Feature",
  "properties": {
    "iso:country":"US",
    "sg:address":"26 Sardis Rd",
    "sg:city":"Asheville",
    "sg:classifiers":[
        {
            "category":"Wholesale",
            "subcategory":"Non-durable Goods",
            "type":"Manufacturing & Wholesale Goods"
        }
    ],
    "sg:phone":"+1 828 667 4444",
    "sg:postcode":"28806",
    "sg:province":"NC",
    "wof:name":"Jacksons Imports Inc",
    "wof:placetype":"venue"
},
  "geometry": {"coordinates":[-82.61085199999999,35.527471],"type":"Point"}
}