{
  "type": "Feature",
  "properties": {
    "addr:full":"1290 Corbett Rd Clayton NC 27520",
    "addr:housenumber":"1290",
    "addr:postcode":"27520",
    "addr:street":"Corbett Rd",
    "iso:country":"US",
    "sg:address":"1290 Corbett Rd",
    "sg:city":"Clayton",
    "sg:classifiers":[
        {
            "category":"Home & Garden",
            "subcategory":"Hardware",
            "type":"Retail Goods"
        }
    ],
    "sg:phone":"+1 919 553 8665",
    "sg:postcode":"27520",
    "sg:province":"NC",
    "wof:name":"Skinner Tools Inc",
    "wof:placetype":"venue"
},
  "geometry": {"coordinates":[-78.50012099999999,35.608186],"type":"Point"}
}