{
  "type": "Feature",
  "properties": {
    "iso:country":"US",
    "sg:address":"5511 Greenfield Way",
    "sg:city":"Mc Leansville",
    "sg:classifiers":[
        {
            "category":"Building & Trades",
            "subcategory":"Landscaping Services",
            "type":"Services"
        }
    ],
    "sg:phone":"+1 336 908 0030",
    "sg:postcode":"27301",
    "sg:province":"NC",
    "sg:tags":[
        "lawn",
        "maintenance",
        "grounds"
    ],
    "wof:name":"A B Lawn Care",
    "wof:placetype":"venue"
},
  "geometry": {"coordinates":[-79.652249,36.142594],"type":"Point"}
}