{
  "type": "Feature",
  "properties": {
    "iso:country":"US",
    "sg:address":"4516 Purnell Rd",
    "sg:city":"Wake Forest",
    "sg:classifiers":[
        {
            "category":"Shopping",
            "subcategory":"Computers & Home Electronics",
            "type":"Retail Goods"
        }
    ],
    "sg:phone":"+1 919 562 0387",
    "sg:postcode":"27587",
    "sg:province":"NC",
    "sg:tags":[
        "equipment",
        "satellite",
        "system"
    ],
    "wof:name":"CBO Satellite",
    "wof:placetype":"venue"
},
  "geometry": {"coordinates":[-78.599519,36.014759],"type":"Point"}
}