{
  "type": "Feature",
  "properties": {
    "addr:full":"5392 State Hwy 150 Browns Summit NC 27214",
    "addr:housenumber":"5392",
    "addr:postcode":"27214",
    "addr:street":"State Hwy 150",
    "iso:country":"US",
    "sg:address":"5392 State Hwy 150",
    "sg:city":"Browns Summit",
    "sg:classifiers":[
        {
            "category":"Home & Garden",
            "subcategory":"Garden Supply",
            "type":"Retail Goods"
        }
    ],
    "sg:phone":"+1 336 656 7881",
    "sg:postcode":"27214",
    "sg:province":"NC",
    "sg:tags":[
        "center"
    ],
    "wof:name":"A & A Plants",
    "wof:placetype":"venue"
},
  "geometry": {"coordinates":[-79.633877,36.219781],"type":"Point"}
}