{
  "type": "Feature",
  "properties": {
    "addr:full":"509 Montlieu Ave High Point NC 27262",
    "addr:housenumber":"509",
    "addr:postcode":"27262",
    "addr:street":"Montlieu Ave",
    "iso:country":"US",
    "sg:address":"509 Montlieu Ave",
    "sg:city":"High Point",
    "sg:classifiers":[
        {
            "category":"Building & Trades",
            "subcategory":"Construction",
            "type":"Services"
        }
    ],
    "sg:phone":"+1 336 885 1038",
    "sg:postcode":"27262",
    "sg:province":"NC",
    "sg:tags":[
        "house"
    ],
    "wof:name":"Luffman Remodeling",
    "wof:placetype":"venue"
},
  "geometry": {"coordinates":[-80.002056,35.968369],"type":"Point"}
}