{
  "type": "Feature",
  "properties": {
    "addr:full":"10710 Sikes Pl Ste 125 Charlotte NC 28277",
    "addr:housenumber":"10710",
    "addr:postcode":"28277",
    "addr:street":"Sikes Pl Ste 125",
    "iso:country":"US",
    "sg:address":"10710 Sikes Pl Ste 125",
    "sg:city":"Charlotte",
    "sg:classifiers":[
        {
            "category":"Real Estate",
            "subcategory":"Architect",
            "type":"Services"
        }
    ],
    "sg:phone":"+1 704 846 1977",
    "sg:postcode":"28277",
    "sg:province":"NC",
    "sg:tags":[
        "architects'",
        "specification",
        "builders'",
        "construction",
        "architectural",
        "engineer"
    ],
    "sg:website":"http://www.warebonsall.com",
    "wof:name":"Ware Bonsall Architects Inc",
    "wof:placetype":"venue"
},
  "geometry": {"coordinates":[-80.768474,35.062017],"type":"Point"}
}