{
  "type": "Feature",
  "properties": {
    "addr:full":"105 E Humber St Sanford NC 27330",
    "addr:housenumber":"105",
    "addr:postcode":"27330",
    "addr:street":"E Humber St",
    "iso:country":"US",
    "sg:address":"105 E Humber St",
    "sg:city":"Sanford",
    "sg:classifiers":[
        {
            "category":"Manufacturing",
            "subcategory":"Metals",
            "type":"Manufacturing & Wholesale Goods"
        }
    ],
    "sg:phone":"+1 919 775 3628",
    "sg:postcode":"27330",
    "sg:province":"NC",
    "sg:tags":[
        "gray",
        "ductile",
        "foundry",
        "iron"
    ],
    "sg:website":"www.hallmanfoundry.com",
    "wof:name":"Hallman Foundry",
    "wof:placetype":"venue"
},
  "geometry": {"coordinates":[-79.15060099999999,35.458601],"type":"Point"}
}