{
  "type": "Feature",
  "properties": {
    "addr:full":"506 E Union St Morganton NC 28655",
    "addr:housenumber":"506",
    "addr:postcode":"28655",
    "addr:street":"E Union St",
    "iso:country":"US",
    "sg:address":"506 E Union St",
    "sg:city":"Morganton",
    "sg:classifiers":[
        {
            "category":"Health Services",
            "subcategory":"Health Practitioner",
            "type":"Services"
        }
    ],
    "sg:phone":"+1 828 437 8538",
    "sg:postcode":"28655",
    "sg:province":"NC",
    "sg:tags":[
        "psychotherapist"
    ],
    "wof:name":"Serenity Center",
    "wof:placetype":"venue"
},
  "geometry": {"coordinates":[-81.683002,35.750255],"type":"Point"}
}