{
  "type": "Feature",
  "properties": {
    "addr:full":"5545 Main St Walkertown NC 27051",
    "addr:housenumber":"5545",
    "addr:postcode":"27051",
    "addr:street":"Main St",
    "iso:country":"US",
    "sg:address":"5545 Main St",
    "sg:city":"Walkertown",
    "sg:classifiers":[
        {
            "category":"Organizations",
            "subcategory":"Religious Organization",
            "type":"Services"
        }
    ],
    "sg:phone":"+1 336 595 4746",
    "sg:postcode":"27051",
    "sg:province":"NC",
    "sg:tags":[
        "church"
    ],
    "wof:name":"Faith Of God Ministries",
    "wof:placetype":"venue"
},
  "geometry": {"coordinates":[-80.156406,36.183169],"type":"Point"}
}