{
  "type": "Feature",
  "properties": {
    "iso:country":"US",
    "sg:address":"2405 United Dr",
    "sg:city":"Greenville",
    "sg:classifiers":[
        {
            "category":"Autos & Motor Vehicles",
            "subcategory":"Auto Supplies",
            "type":"Retail Goods"
        },
        {
            "category":"Wholesale",
            "subcategory":"Auto Parts",
            "type":"Manufacturing & Wholesale Goods"
        }
    ],
    "sg:phone":"+1 252 758 3033",
    "sg:postcode":"27834",
    "sg:province":"NC",
    "sg:tags":[
        "equipment",
        "truck"
    ],
    "wof:name":"Canadys Heavy Truck Parts Inc",
    "wof:placetype":"venue"
},
  "geometry": {"coordinates":[-77.354676,35.652823],"type":"Point"}
}