{
  "type": "Feature",
  "properties": {
    "iso:country":"US",
    "sg:address":"3811 Ferncliff Rd",
    "sg:city":"Gastonia",
    "sg:classifiers":[
        {
            "category":"Building & Trades",
            "subcategory":"Construction",
            "type":"Services"
        }
    ],
    "sg:phone":"+1 704 867 8851",
    "sg:postcode":"28056",
    "sg:province":"NC",
    "sg:tags":[
        "roofing",
        "contractor"
    ],
    "wof:name":"Able-Dockery Roofing Co",
    "wof:placetype":"venue"
},
  "geometry": {"coordinates":[-81.161642,35.190965],"type":"Point"}
}