{
  "type": "Feature",
  "properties": {
    "iso:country":"US",
    "sg:address":"1208 Main St",
    "sg:city":"Scotland Neck",
    "sg:classifiers":[
        {
            "category":"Health Services",
            "subcategory":"Clinic",
            "type":"Services"
        }
    ],
    "sg:phone":"+1 252 826 2713",
    "sg:postcode":"27874",
    "sg:province":"NC",
    "sg:tags":[
        "home"
    ],
    "wof:name":"Home Life Care Inc",
    "wof:placetype":"venue"
},
  "geometry": {"coordinates":[-77.42135500000001,36.132253],"type":"Point"}
}