{
  "type": "Feature",
  "properties": {
    "addr:full":"1823 Sunset Ave Rocky Mount NC 27804",
    "addr:housenumber":"1823",
    "addr:postcode":"27804",
    "addr:street":"Sunset Ave",
    "iso:country":"US",
    "sg:address":"1823 Sunset Ave",
    "sg:city":"Rocky Mount",
    "sg:classifiers":[
        {
            "category":"Autos & Motor Vehicles",
            "subcategory":"Auto Supplies",
            "type":"Retail Goods"
        }
    ],
    "sg:phone":"+1 252 446 7105",
    "sg:postcode":"27804",
    "sg:province":"NC",
    "sg:tags":[
        "automobile",
        "parts"
    ],
    "wof:name":"Carquest Auto Parts Of Rocky",
    "wof:placetype":"venue"
},
  "geometry": {"coordinates":[-77.821426,35.954681],"type":"Point"}
}