{
  "type": "Feature",
  "properties": {
    "iso:country":"US",
    "sg:address":"742 N Broad St",
    "sg:city":"Mooresville",
    "sg:classifiers":[
        {
            "category":"Building & Trades",
            "subcategory":"Construction",
            "type":"Services"
        }
    ],
    "sg:phone":"+1 704 663 7132",
    "sg:postcode":"28115",
    "sg:province":"NC",
    "sg:tags":[
        "siding",
        "contractor"
    ],
    "sg:website":"www.gandscontracting.com",
    "wof:name":"G & S Contracting Inc",
    "wof:placetype":"venue"
},
  "geometry": {"coordinates":[-80.809718,35.598584],"type":"Point"}
}