{
  "type": "Feature",
  "properties": {
    "iso:country":"US",
    "sg:address":"4512 Fairvista Dr",
    "sg:city":"Charlotte",
    "sg:classifiers":[
        {
            "category":"Banks & Credit Unions",
            "subcategory":"Financial Services",
            "type":"Services"
        }
    ],
    "sg:phone":"+1 704 875 1779",
    "sg:postcode":"28269",
    "sg:province":"NC",
    "sg:tags":[
        "investor"
    ],
    "wof:name":"Venture Investments of NC LLC",
    "wof:placetype":"venue"
},
  "geometry": {"coordinates":[-80.77600700000001,35.378432],"type":"Point"}
}