{
  "type": "Feature",
  "properties": {
    "addr:full":"3104 Brinkley Dr Spring Lake NC 28390",
    "addr:housenumber":"3104",
    "addr:postcode":"28390",
    "addr:street":"Brinkley Dr",
    "iso:country":"US",
    "sg:address":"3104 Brinkley Dr",
    "sg:city":"Spring Lake",
    "sg:classifiers":[
        {
            "category":"Retail",
            "subcategory":"Repair Shop",
            "type":"Services"
        }
    ],
    "sg:phone":"+1   ",
    "sg:postcode":"28390",
    "sg:province":"NC",
    "wof:name":"Affordable Locksmith",
    "wof:placetype":"venue"
},
  "geometry": {"coordinates":[-78.95257599999999,35.211701],"type":"Point"}
}