{
  "type": "Feature",
  "properties": {
    "addr:full":"603 Smokey Shadows Ln Maggie Valley NC 28751",
    "addr:housenumber":"603",
    "addr:postcode":"28751",
    "addr:street":"Smokey Shadows Ln",
    "iso:country":"US",
    "sg:address":"603 Smokey Shadows Ln",
    "sg:city":"Maggie Valley",
    "sg:classifiers":[
        {
            "category":"Building & Trades",
            "subcategory":"Electrical",
            "type":"Services"
        }
    ],
    "sg:phone":"+1 828 926 7728",
    "sg:postcode":"28751",
    "sg:province":"NC",
    "sg:tags":[
        "electric",
        "contractor"
    ],
    "wof:name":"K W Electric Group Inc",
    "wof:placetype":"venue"
},
  "geometry": {"coordinates":[-83.10445900000001,35.535262],"type":"Point"}
}