{
  "type": "Feature",
  "properties": {
    "iso:country":"US",
    "sg:address":"306 Riverwood Dr",
    "sg:city":"Elkin",
    "sg:classifiers":[
        {
            "category":"Banks & Credit Unions",
            "subcategory":"Financial Services",
            "type":"Services"
        }
    ],
    "sg:phone":"+1 336 835 5477",
    "sg:postcode":"28621",
    "sg:province":"NC",
    "sg:tags":[
        "investor"
    ],
    "wof:name":"Devney Investments Inc",
    "wof:placetype":"venue"
},
  "geometry": {"coordinates":[-80.86721,36.240948],"type":"Point"}
}