{
  "type": "Feature",
  "properties": {
    "addr:full":"1413 Hardimont Rd Raleigh NC 27609",
    "addr:housenumber":"1413",
    "addr:postcode":"27609",
    "addr:street":"Hardimont Rd",
    "iso:country":"US",
    "sg:address":"1413 Hardimont Rd",
    "sg:city":"Raleigh",
    "sg:classifiers":[
        {
            "category":"Building & Trades",
            "subcategory":"Cleaning & Sanitation",
            "type":"Services"
        }
    ],
    "sg:phone":"+1   ",
    "sg:postcode":"27609",
    "sg:province":"NC",
    "sg:tags":[
        "maintenance"
    ],
    "wof:name":"Classic Janitorial Services",
    "wof:placetype":"venue"
},
  "geometry": {"coordinates":[-78.616911,35.837415],"type":"Point"}
}