{
  "type": "Feature",
  "properties": {
    "addr:full":"3735 Battleground Ave Greensboro NC 27410",
    "addr:housenumber":"3735",
    "addr:postcode":"27410",
    "addr:street":"Battleground Ave",
    "iso:country":"US",
    "sg:address":"3735 Battleground Ave",
    "sg:city":"Greensboro",
    "sg:classifiers":[
        {
            "category":"Restaurant",
            "type":"Food & Drink"
        }
    ],
    "sg:menulink":"http://www.allmenus.com/nc/greensboro/73390-pizza-hut/menu/",
    "sg:phone":"+1 336 288 4245",
    "sg:postcode":"27410",
    "sg:province":"NC",
    "sg:tags":[
        "american",
        "pizza"
    ],
    "wof:name":"Pizza Hut",
    "wof:placetype":"venue"
},
  "geometry": {"coordinates":[-79.857497,36.133226],"type":"Point"}
}