{
  "type": "Feature",
  "properties": {
    "addr:full":"314 Tryon St Burlington NC 27217",
    "addr:housenumber":"314",
    "addr:postcode":"27217",
    "addr:street":"Tryon St",
    "iso:country":"US",
    "sg:address":"314 Tryon St",
    "sg:city":"Burlington",
    "sg:classifiers":[
        {
            "category":"Building & Trades",
            "subcategory":"Construction",
            "type":"Services"
        }
    ],
    "sg:phone":"+1 336 570 0825",
    "sg:postcode":"27217",
    "sg:province":"NC",
    "sg:tags":[
        "hanging",
        "contractor"
    ],
    "wof:name":"Four Seasons Painting Dctg",
    "wof:placetype":"venue"
},
  "geometry": {"coordinates":[-79.398403,36.099648],"type":"Point"}
}