{
  "type": "Feature",
  "properties": {
    "addr:full":"2075 Southfork Dr Morganton NC 28655",
    "addr:housenumber":"2075",
    "addr:postcode":"28655",
    "addr:street":"Southfork Dr",
    "iso:country":"US",
    "sg:address":"2075 Southfork Dr",
    "sg:city":"Morganton",
    "sg:classifiers":[
        {
            "category":"Banks & Credit Unions",
            "subcategory":"Bank",
            "type":"Services"
        }
    ],
    "sg:phone":"+1 828 430 7440",
    "sg:postcode":"28655",
    "sg:province":"NC",
    "sg:tags":[
        "mortgage"
    ],
    "wof:name":"Burke Mortgage Assoc Inc",
    "wof:placetype":"venue"
},
  "geometry": {"coordinates":[-81.73761,35.679983],"type":"Point"}
}