{
  "type": "Feature",
  "properties": {
    "iso:country":"US",
    "sg:address":"1922 White Hollow Dr",
    "sg:city":"Greenville",
    "sg:classifiers":[
        {
            "category":"Professional",
            "type":"Services"
        }
    ],
    "sg:phone":"+1 252 355 3587",
    "sg:postcode":"27858",
    "sg:province":"NC",
    "wof:name":"John Chandler",
    "wof:placetype":"venue"
},
  "geometry": {"coordinates":[-77.34379,35.587117],"type":"Point"}
}