{
  "type": "Feature",
  "properties": {
    "addr:full":"2424 Atlantic Ave Raleigh NC 27604",
    "addr:housenumber":"2424",
    "addr:postcode":"27604",
    "addr:street":"Atlantic Ave",
    "iso:country":"US",
    "sg:address":"2424 Atlantic Ave",
    "sg:city":"Raleigh",
    "sg:classifiers":[
        {
            "category":"Professional",
            "subcategory":"Business Services",
            "type":"Services"
        }
    ],
    "sg:phone":"+1   ",
    "sg:postcode":"27604",
    "sg:province":"NC",
    "wof:name":"Signs Now",
    "wof:placetype":"venue"
},
  "geometry": {"coordinates":[-78.61642999999999,35.816598],"type":"Point"}
}