{
  "type": "Feature",
  "properties": {
    "addr:full":"503 McDuffie Rd Biscoe NC 27209",
    "addr:housenumber":"503",
    "addr:postcode":"27209",
    "addr:street":"Mcduffie Rd",
    "iso:country":"US",
    "sg:address":"503 McDuffie Rd",
    "sg:city":"Biscoe",
    "sg:classifiers":[
        {
            "category":"Organizations",
            "subcategory":"Religious Organization",
            "type":"Services"
        }
    ],
    "sg:phone":"+1 910 673 1596",
    "sg:postcode":"27209",
    "sg:province":"NC",
    "sg:tags":[
        "church"
    ],
    "wof:name":"Bensalem Presbyterian Church",
    "wof:placetype":"venue"
},
  "geometry": {"coordinates":[-79.67940299999999,35.35499],"type":"Point"}
}