{
  "type": "Feature",
  "properties": {
    "addr:full":"116 Country Club Dr Fayetteville NC 28301",
    "addr:housenumber":"116",
    "addr:postcode":"28301",
    "addr:street":"Country Club Dr",
    "iso:country":"US",
    "sg:address":"116 Country Club Dr",
    "sg:city":"Fayetteville",
    "sg:classifiers":[
        {
            "category":"Health Services",
            "subcategory":"Chiropractor",
            "type":"Services"
        }
    ],
    "sg:phone":"+1   ",
    "sg:postcode":"28301",
    "sg:province":"NC",
    "sg:tags":[
        "clinic",
        "chiropractic"
    ],
    "wof:name":"Accident Fmly Chrprctic Clinic",
    "wof:placetype":"venue"
},
  "geometry": {"coordinates":[-78.88246100000001,35.104771],"type":"Point"}
}