{
  "type": "Feature",
  "properties": {
    "addr:full":"2081 Winston Rd Creedmoor NC 27581",
    "addr:housenumber":"2081",
    "addr:postcode":"27581",
    "addr:street":"Winston Rd",
    "iso:country":"US",
    "sg:address":"2081 Winston Rd",
    "sg:city":"Creedmoor",
    "sg:classifiers":[
        {
            "category":"Professional",
            "subcategory":"Computer Services",
            "type":"Services"
        }
    ],
    "sg:phone":"+1 919 599 2599",
    "sg:postcode":"27581",
    "sg:province":"NC",
    "sg:tags":[
        "related"
    ],
    "wof:name":"Computer Trooblershooters",
    "wof:placetype":"venue"
},
  "geometry": {"coordinates":[-78.67997200000001,36.161431],"type":"Point"}
}