{
  "type": "Feature",
  "properties": {
    "addr:full":"407 W Gannon Ave Zebulon NC 27597",
    "addr:housenumber":"407",
    "addr:postcode":"27597",
    "addr:street":"W Gannon Ave",
    "iso:country":"US",
    "sg:address":"407 W Gannon Ave",
    "sg:city":"Zebulon",
    "sg:classifiers":[
        {
            "category":"Shopping",
            "subcategory":"Music",
            "type":"Retail Goods"
        },
        {
            "category":"Cinema",
            "subcategory":"Movie Rental",
            "type":"Entertainment"
        }
    ],
    "sg:phone":"+1 919 404 1488",
    "sg:postcode":"27597",
    "sg:province":"NC",
    "sg:tags":[
        "video",
        "disc",
        "tape",
        "cassette"
    ],
    "wof:name":"Box Office Video of NC",
    "wof:placetype":"venue"
},
  "geometry": {"coordinates":[-78.321253,35.821315],"type":"Point"}
}