{
  "type": "Feature",
  "properties": {
    "addr:full":"5000 Main St Gibson NC 28343",
    "addr:housenumber":"5000",
    "addr:postcode":"28343",
    "addr:street":"Main St",
    "iso:country":"US",
    "sg:address":"5000 Main St",
    "sg:city":"Gibson",
    "sg:classifiers":[
        {
            "category":"Organizations",
            "subcategory":"Religious Organization",
            "type":"Services"
        }
    ],
    "sg:phone":"+1 910 268 2727",
    "sg:postcode":"28343",
    "sg:province":"NC",
    "wof:name":"United Global Ministries",
    "wof:placetype":"venue"
},
  "geometry": {"coordinates":[-79.601889,34.760386],"type":"Point"}
}