{
  "type": "Feature",
  "properties": {
    "iso:country":"US",
    "sg:address":"448 W 6th St",
    "sg:city":"Ayden",
    "sg:classifiers":[
        {
            "category":"Government",
            "subcategory":"Office",
            "type":"Public Place"
        }
    ],
    "sg:phone":"+1 252 746 8210",
    "sg:postcode":"28513",
    "sg:province":"NC",
    "sg:tags":[
        "investor"
    ],
    "wof:name":"Dorcell Properties  LLC",
    "wof:placetype":"venue"
},
  "geometry": {"coordinates":[-77.42213700000001,35.468183],"type":"Point"}
}