{
  "type": "Feature",
  "properties": {
    "iso:country":"US",
    "sg:address":"609 Turnersburg Hwy",
    "sg:city":"Statesville",
    "sg:classifiers":[
        {
            "category":"Personal",
            "subcategory":"Beauty Salon",
            "type":"Services"
        }
    ],
    "sg:phone":"+1   ",
    "sg:postcode":"28625",
    "sg:province":"NC",
    "sg:tags":[
        "shop"
    ],
    "wof:name":"Northwind Hair Designers",
    "wof:placetype":"venue"
},
  "geometry": {"coordinates":[-80.874607,35.827487],"type":"Point"}
}