{
  "type": "Feature",
  "properties": {
    "iso:country":"US",
    "sg:address":"100 Abbey Fields Ln",
    "sg:city":"Hendersonville",
    "sg:classifiers":[
        {
            "category":"Restaurant",
            "type":"Food & Drink"
        }
    ],
    "sg:phone":"+1 828 696 3128",
    "sg:postcode":"28792",
    "sg:province":"NC",
    "sg:tags":[
        "eating",
        "contractor"
    ],
    "wof:name":"James K Pryor",
    "wof:placetype":"venue"
},
  "geometry": {"coordinates":[-82.46163799999999,35.370905],"type":"Point"}
}