{
  "type": "Feature",
  "properties": {
    "iso:country":"US",
    "sg:address":"8504 Bromley Rd",
    "sg:city":"Hillsborough",
    "sg:classifiers":[
        {
            "category":"Professional",
            "subcategory":"Engineering",
            "type":"Services"
        }
    ],
    "sg:phone":"+1 919 479 5577",
    "sg:postcode":"27278",
    "sg:province":"NC",
    "sg:tags":[
        "engineer"
    ],
    "wof:name":"Stamer Engineering PA",
    "wof:placetype":"venue"
},
  "geometry": {"coordinates":[-78.96101400000001,36.154383],"type":"Point"}
}