{
  "type": "Feature",
  "properties": {
    "addr:full":"201 E Water St Statesville NC 28677",
    "addr:housenumber":"201",
    "addr:postcode":"28677",
    "addr:street":"E Water St",
    "iso:country":"US",
    "sg:address":"201 E Water St",
    "sg:city":"Statesville",
    "sg:classifiers":[
        {
            "category":"Government",
            "subcategory":"Office",
            "type":"Public Place"
        }
    ],
    "sg:phone":"+1 704 873 7242",
    "sg:postcode":"28677",
    "sg:province":"NC",
    "sg:tags":[
        "development",
        "federal",
        "planning",
        "dev",
        "rural"
    ],
    "wof:name":"USDA Rural Development",
    "wof:placetype":"venue"
},
  "geometry": {"coordinates":[-80.88597900000001,35.787102],"type":"Point"}
}