{
  "type": "Feature",
  "properties": {
    "iso:country":"US",
    "sg:address":"13948 Capital Blvd",
    "sg:city":"Wake Forest",
    "sg:classifiers":[
        {
            "category":"Autos & Motor Vehicles",
            "subcategory":"Motorcycle Sales",
            "type":"Retail Goods"
        }
    ],
    "sg:phone":"+1 919 562 6686",
    "sg:postcode":"27587",
    "sg:province":"NC",
    "sg:tags":[
        "scooter"
    ],
    "wof:name":"Full Throttle Parts & Services",
    "wof:placetype":"venue"
},
  "geometry": {"coordinates":[-78.517719,36.012222],"type":"Point"}
}