{
  "type": "Feature",
  "properties": {
    "addr:full":"234 Morganton Blvd SW Lenoir NC 28645",
    "addr:housenumber":"234",
    "addr:postcode":"28645",
    "addr:street":"Morganton Blvd Sw",
    "iso:country":"US",
    "sg:address":"234 Morganton Blvd SW",
    "sg:city":"Lenoir",
    "sg:classifiers":[
        {
            "category":"Personal",
            "subcategory":"Beauty Salon",
            "type":"Services"
        }
    ],
    "sg:phone":"+1   ",
    "sg:postcode":"28645",
    "sg:province":"NC",
    "sg:tags":[
        "shop"
    ],
    "wof:name":"Hair Shack",
    "wof:placetype":"venue"
},
  "geometry": {"coordinates":[-81.528622,35.912168],"type":"Point"}
}