{
  "type": "Feature",
  "properties": {
    "addr:full":"7530 Orr Rd Charlotte NC 28213",
    "addr:housenumber":"7530",
    "addr:postcode":"28213",
    "addr:street":"Orr Rd",
    "iso:country":"US",
    "sg:address":"7530 Orr Rd",
    "sg:city":"Charlotte",
    "sg:classifiers":[
        {
            "category":"Wholesale",
            "subcategory":"Hardware",
            "type":"Manufacturing & Wholesale Goods"
        }
    ],
    "sg:phone":"+1 704 596 1777",
    "sg:postcode":"28213",
    "sg:province":"NC",
    "sg:tags":[
        "refrigerating"
    ],
    "wof:name":"Eastern Refrigeration Svc Inc",
    "wof:placetype":"venue"
},
  "geometry": {"coordinates":[-80.74122300000001,35.269346],"type":"Point"}
}