{
  "type": "Feature",
  "properties": {
    "addr:full":"728 Hartness Rd Statesville NC 28677",
    "addr:housenumber":"728",
    "addr:postcode":"28677",
    "addr:street":"Hartness Rd",
    "iso:country":"US",
    "sg:address":"728 Hartness Rd",
    "sg:city":"Statesville",
    "sg:classifiers":[
        {
            "category":"Health Services",
            "subcategory":"Doctor",
            "type":"Services"
        }
    ],
    "sg:phone":"+1 704 873 7850",
    "sg:postcode":"28677",
    "sg:province":"NC",
    "sg:tags":[
        "physician",
        "surgeon"
    ],
    "wof:name":"Piedmont Healthcare Specialty",
    "wof:placetype":"venue"
},
  "geometry": {"coordinates":[-80.88050699999999,35.79874],"type":"Point"}
}