{
  "type": "Feature",
  "properties": {
    "addr:full":"2941 Hamptonville Rd Hamptonville NC 27020",
    "addr:housenumber":"2941",
    "addr:postcode":"27020",
    "addr:street":"Hamptonville Rd",
    "iso:country":"US",
    "sg:address":"2941 Hamptonville Rd",
    "sg:city":"Hamptonville",
    "sg:classifiers":[
        {
            "category":"Building & Trades",
            "subcategory":"Electrical",
            "type":"Services"
        }
    ],
    "sg:phone":"+1 336 468 8778",
    "sg:postcode":"27020",
    "sg:province":"NC",
    "sg:tags":[
        "electrical",
        "contractor"
    ],
    "wof:name":"Millennium Electrical Co",
    "wof:placetype":"venue"
},
  "geometry": {"coordinates":[-80.79372100000001,36.065286],"type":"Point"}
}