{
  "type": "Feature",
  "properties": {
    "iso:country":"US",
    "sg:address":"1006 Lamond Ave",
    "sg:city":"Durham",
    "sg:classifiers":[
        {
            "category":"Health Services",
            "subcategory":"Doctor",
            "type":"Services"
        }
    ],
    "sg:phone":"+1 919 688 4100",
    "sg:postcode":"27701",
    "sg:province":"NC",
    "wof:name":"Durham Family Dental Care",
    "wof:placetype":"venue"
},
  "geometry": {"coordinates":[-78.91108699999999,36.002356],"type":"Point"}
}