{
  "type": "Feature",
  "properties": {
    "addr:full":"8107 Arrowridge Blvd Charlotte NC 28273",
    "addr:housenumber":"8107",
    "addr:postcode":"28273",
    "addr:street":"Arrowridge Blvd",
    "iso:country":"US",
    "sg:address":"8107 Arrowridge Blvd",
    "sg:city":"Charlotte",
    "sg:classifiers":[
        {
            "category":"Manufacturing",
            "subcategory":"Printing",
            "type":"Manufacturing & Wholesale Goods"
        }
    ],
    "sg:phone":"+1 704 522 1295",
    "sg:postcode":"28273",
    "sg:province":"NC",
    "sg:tags":[
        "label"
    ],
    "wof:name":"Calico Tag & Label Inc",
    "wof:placetype":"venue"
},
  "geometry": {"coordinates":[-80.912234,35.129877],"type":"Point"}
}