{
  "type": "Feature",
  "properties": {
    "addr:full":"1238 Huffman Mill Rd Burlington NC 27215",
    "addr:housenumber":"1238",
    "addr:postcode":"27215",
    "addr:street":"Huffman Mill Rd",
    "iso:country":"US",
    "sg:address":"1238 Huffman Mill Rd",
    "sg:city":"Burlington",
    "sg:classifiers":[
        {
            "category":"Health Services",
            "subcategory":"Doctor",
            "type":"Services"
        }
    ],
    "sg:phone":"+1 336 585 1869",
    "sg:postcode":"27215",
    "sg:province":"NC",
    "sg:tags":[
        "physician",
        "surgeon"
    ],
    "wof:name":"Hearn's Vascular LLC",
    "wof:placetype":"venue"
},
  "geometry": {"coordinates":[-79.501954,36.064122],"type":"Point"}
}