{
  "type": "Feature",
  "properties": {
    "addr:full":"7130 Lynbrook Creek Rd Denver NC 28037",
    "addr:housenumber":"7130",
    "addr:postcode":"28037",
    "addr:street":"Lynbrook Creek Rd",
    "iso:country":"US",
    "sg:address":"7130 Lynbrook Creek Rd",
    "sg:city":"Denver",
    "sg:classifiers":[
        {
            "category":"Professional",
            "subcategory":"Computer Services",
            "type":"Services"
        }
    ],
    "sg:phone":"+1 704 489 8992",
    "sg:postcode":"28037",
    "sg:province":"NC",
    "sg:tags":[
        "consultant",
        "designer",
        "datum",
        "system",
        "related"
    ],
    "wof:name":"Information Consolidation LLC",
    "wof:placetype":"venue"
},
  "geometry": {"coordinates":[-81.01475600000001,35.56802],"type":"Point"}
}