{
  "type": "Feature",
  "properties": {
    "addr:full":"9435 Squirrel Hollow Ln Charlotte NC 28270",
    "addr:housenumber":"9435",
    "addr:postcode":"28270",
    "addr:street":"Squirrel Hollow Ln",
    "iso:country":"US",
    "sg:address":"9435 Squirrel Hollow Ln",
    "sg:city":"Charlotte",
    "sg:classifiers":[
        {
            "category":"Building & Trades",
            "subcategory":"Construction",
            "type":"Services"
        }
    ],
    "sg:phone":"+1 704 664 3231",
    "sg:postcode":"28270",
    "sg:province":"NC",
    "sg:tags":[
        "house"
    ],
    "wof:name":"Dickson & Lowery Builders",
    "wof:placetype":"venue"
},
  "geometry": {"coordinates":[-80.767484,35.080347],"type":"Point"}
}