{
  "type": "Feature",
  "properties": {
    "addr:full":"111 Payne Rd Thomasville NC 27360",
    "addr:housenumber":"111",
    "addr:postcode":"27360",
    "addr:street":"Payne Rd",
    "iso:country":"US",
    "sg:address":"111 Payne Rd",
    "sg:city":"Thomasville",
    "sg:classifiers":[
        {
            "category":"Professional",
            "type":"Services"
        }
    ],
    "sg:phone":"+1 336 472 1178",
    "sg:postcode":"27360",
    "sg:province":"NC",
    "wof:name":"Expert Newsrack Svc",
    "wof:placetype":"venue"
},
  "geometry": {"coordinates":[-80.074724,35.910291],"type":"Point"}
}