{
  "type": "Feature",
  "properties": {
    "addr:full":"6527 Raeford Rd Fayetteville NC 28304",
    "addr:housenumber":"6527",
    "addr:postcode":"28304",
    "addr:street":"Raeford Rd",
    "iso:country":"US",
    "sg:address":"6527 Raeford Rd",
    "sg:city":"Fayetteville",
    "sg:classifiers":[
        {
            "category":"Insurance",
            "subcategory":"Insurance Agent",
            "type":"Services"
        }
    ],
    "sg:phone":"+1 910 860 3735",
    "sg:postcode":"28304",
    "sg:province":"NC",
    "wof:name":"Car Insurance Agency",
    "wof:placetype":"venue"
},
  "geometry": {"coordinates":[-78.997377,35.040103],"type":"Point"}
}