{
  "type": "Feature",
  "properties": {
    "addr:full":"7016 Apple Mill Rd Efland NC 27243",
    "addr:housenumber":"7016",
    "addr:postcode":"27243",
    "addr:street":"Apple Mill Rd",
    "iso:country":"US",
    "sg:address":"7016 Apple Mill Rd",
    "sg:city":"Efland",
    "sg:classifiers":[
        {
            "category":"Building & Trades",
            "subcategory":"Construction",
            "type":"Services"
        }
    ],
    "sg:phone":"+1 919 563 9403",
    "sg:postcode":"27243",
    "sg:province":"NC",
    "sg:tags":[
        "contractor"
    ],
    "wof:name":"Roger Apple Construction",
    "wof:placetype":"venue"
},
  "geometry": {"coordinates":[-79.234089,35.977056],"type":"Point"}
}