{
  "type": "Feature",
  "properties": {
    "iso:country":"US",
    "sg:address":"108 Symphony Ct",
    "sg:city":"Cary",
    "sg:classifiers":[
        {
            "category":"Banks & Credit Unions",
            "subcategory":"Financial Services",
            "type":"Services"
        }
    ],
    "sg:phone":"+1 919 460 8504",
    "sg:postcode":"27518",
    "sg:province":"NC",
    "sg:tags":[
        "trust",
        "investment",
        "real estate"
    ],
    "wof:name":"Meredith Suites LLC",
    "wof:placetype":"venue"
},
  "geometry": {"coordinates":[-78.795434,35.722469],"type":"Point"}
}