{
  "type": "Feature",
  "properties": {
    "addr:full":"1701 Davie Ave Statesville NC 28677",
    "addr:housenumber":"1701",
    "addr:postcode":"28677",
    "addr:street":"Davie Ave",
    "iso:country":"US",
    "sg:address":"1701 Davie Ave",
    "sg:city":"Statesville",
    "sg:classifiers":[
        {
            "category":"Health Services",
            "subcategory":"Doctor",
            "type":"Services"
        }
    ],
    "sg:phone":"+1 704 924 7650",
    "sg:postcode":"28677",
    "sg:province":"NC",
    "sg:tags":[
        "dentist"
    ],
    "wof:name":"Robert S Nance DDS",
    "wof:placetype":"venue"
},
  "geometry": {"coordinates":[-80.864785,35.800301],"type":"Point"}
}