{
  "type": "Feature",
  "properties": {
    "addr:full":"5014 Wainwright Rd Mc Leansville NC 27301",
    "addr:housenumber":"5014",
    "addr:postcode":"27301",
    "addr:street":"Wainwright Rd",
    "iso:country":"US",
    "sg:address":"5014 Wainwright Rd",
    "sg:city":"Mc Leansville",
    "sg:classifiers":[
        {
            "category":"Travel",
            "subcategory":"Hotels & Motels",
            "type":"Entertainment"
        }
    ],
    "sg:phone":"+1 336 698 0416",
    "sg:postcode":"27301",
    "sg:province":"NC",
    "sg:tags":[
        "resort"
    ],
    "wof:name":"Woodmen Of The World Lodge 26",
    "wof:placetype":"venue"
},
  "geometry": {"coordinates":[-79.678578,36.078683],"type":"Point"}
}