{
  "type": "Feature",
  "properties": {
    "iso:country":"US",
    "sg:address":"440 College St",
    "sg:city":"Jacksonville",
    "sg:classifiers":[
        {
            "category":"Education",
            "subcategory":"School",
            "type":"Public Place"
        }
    ],
    "sg:phone":"+1 910 346 6222",
    "sg:postcode":"28540",
    "sg:province":"NC",
    "wof:name":"Thompson Early Childhood Ctr",
    "wof:placetype":"venue"
},
  "geometry": {"coordinates":[-77.427224,34.749096],"type":"Point"}
}