{
  "type": "Feature",
  "properties": {
    "iso:country":"US",
    "sg:address":"2533 Atlantic Ave",
    "sg:city":"Raleigh",
    "sg:classifiers":[
        {
            "category":"Home & Garden",
            "subcategory":"Hardware",
            "type":"Retail Goods"
        }
    ],
    "sg:phone":"+1 919 832 2025",
    "sg:postcode":"27604",
    "sg:province":"NC",
    "wof:name":"Briggs Hardware",
    "wof:placetype":"venue"
},
  "geometry": {"coordinates":[-78.61608699999999,35.817663],"type":"Point"}
}