{
  "type": "Feature",
  "properties": {
    "addr:full":"119 Sandwedge Rd Wilkesboro NC 28697",
    "addr:housenumber":"119",
    "addr:postcode":"28697",
    "addr:street":"Sandwedge Rd",
    "iso:country":"US",
    "sg:address":"119 Sandwedge Rd",
    "sg:city":"Wilkesboro",
    "sg:classifiers":[
        {
            "category":"Banks & Credit Unions",
            "subcategory":"Financial Services",
            "type":"Services"
        }
    ],
    "sg:phone":"+1 336 838 7034",
    "sg:postcode":"28697",
    "sg:province":"NC",
    "sg:tags":[
        "trust",
        "investment",
        "real estate"
    ],
    "wof:name":"Day Properties LLC",
    "wof:placetype":"venue"
},
  "geometry": {"coordinates":[-81.150442,36.117017],"type":"Point"}
}