{
  "type": "Feature",
  "properties": {
    "addr:full":"4021 State Hwy 109 N Troy NC 27371",
    "addr:housenumber":"4021",
    "addr:postcode":"27371",
    "addr:street":"State Hwy 109 N",
    "iso:country":"US",
    "sg:address":"4021 State Hwy 109 N",
    "sg:city":"Troy",
    "sg:classifiers":[
        {
            "category":"Recreation",
            "type":"Entertainment"
        }
    ],
    "sg:phone":"+1 910 572 3473",
    "sg:postcode":"27371",
    "sg:province":"NC",
    "sg:tags":[
        "stable"
    ],
    "wof:name":"Uwharrie Horse Necessities",
    "wof:placetype":"venue"
},
  "geometry": {"coordinates":[-80.020377,35.443666],"type":"Point"}
}