{
  "type": "Feature",
  "properties": {
    "iso:country":"US",
    "sg:address":"2068 Kildaire Farm Rd",
    "sg:city":"Cary",
    "sg:classifiers":[
        {
            "category":"Shopping",
            "subcategory":"Gifts & Souvenirs",
            "type":"Retail Goods"
        }
    ],
    "sg:phone":"+1 919 852 1009",
    "sg:postcode":"27518",
    "sg:province":"NC",
    "sg:tags":[
        "announcement",
        "invitation"
    ],
    "wof:name":"Paper Co",
    "wof:placetype":"venue"
},
  "geometry": {"coordinates":[-78.780188,35.738297],"type":"Point"}
}