{
  "type": "Feature",
  "properties": {
    "iso:country":"US",
    "sg:address":"8907 Steelechase Dr",
    "sg:city":"Charlotte",
    "sg:classifiers":[
        {
            "category":"Restaurant",
            "type":"Food & Drink"
        }
    ],
    "sg:phone":"+1 704 372 6401",
    "sg:postcode":"28273",
    "sg:province":"NC",
    "wof:name":"Eggroll King",
    "wof:placetype":"venue"
},
  "geometry": {"coordinates":[-80.948988,35.146523],"type":"Point"}
}