{
  "type": "Feature",
  "properties": {
    "iso:country":"US",
    "sg:address":"231 State Hwy 58",
    "sg:city":"Kinston",
    "sg:classifiers":[
        {
            "category":"Professional",
            "subcategory":"Management & Consulting",
            "type":"Services"
        }
    ],
    "sg:phone":"+1 252 523 3382",
    "sg:postcode":"28504",
    "sg:province":"NC",
    "wof:name":"Group III Management Inc",
    "wof:placetype":"venue"
},
  "geometry": {"coordinates":[-77.585155,35.244365],"type":"Point"}
}