{
  "type": "Feature",
  "properties": {
    "iso:country":"US",
    "sg:address":"1115 Perkins St",
    "sg:city":"Greensboro",
    "sg:classifiers":[
        {
            "category":"Professional",
            "subcategory":"Computer Services",
            "type":"Services"
        }
    ],
    "sg:phone":"+1   ",
    "sg:postcode":"27401",
    "sg:province":"NC",
    "sg:tags":[
        "datum"
    ],
    "wof:name":"K L S Sites",
    "wof:placetype":"venue"
},
  "geometry": {"coordinates":[-79.77328199999999,36.070034],"type":"Point"}
}