{
  "type": "Feature",
  "properties": {
    "iso:country":"US",
    "sg:address":"116 W College St",
    "sg:city":"Warsaw",
    "sg:classifiers":[
        {
            "category":"Personal",
            "subcategory":"Beauty Salon",
            "type":"Services"
        }
    ],
    "sg:phone":"+1 910 293 4549",
    "sg:postcode":"28398",
    "sg:province":"NC",
    "wof:name":"Uptown Barber & Beauty Shop",
    "wof:placetype":"venue"
},
  "geometry": {"coordinates":[-78.09255400000001,34.999149],"type":"Point"}
}