{
  "type": "Feature",
  "properties": {
    "addr:full":"1121 Military Cutoff Rd Wilmington NC 28405",
    "addr:housenumber":"1121",
    "addr:postcode":"28405",
    "addr:street":"Military Cutoff Rd",
    "iso:country":"US",
    "sg:address":"1121 Military Cutoff Rd",
    "sg:city":"Wilmington",
    "sg:classifiers":[
        {
            "category":"Sports & Exercise",
            "subcategory":"Gym",
            "type":"Entertainment"
        }
    ],
    "sg:phone":"+1 910 509 4131",
    "sg:postcode":"28405",
    "sg:province":"NC",
    "sg:tags":[
        "club",
        "health",
        "studio",
        "gymnasium"
    ],
    "wof:name":"Beyond Fitness",
    "wof:placetype":"venue"
},
  "geometry": {"coordinates":[-77.828487,34.23679],"type":"Point"}
}