{
  "type": "Feature",
  "properties": {
    "addr:full":"1409 E Main St Cherryville NC 28021",
    "addr:housenumber":"1409",
    "addr:postcode":"28021",
    "addr:street":"E Main St",
    "iso:country":"US",
    "sg:address":"1409 E Main St",
    "sg:city":"Cherryville",
    "sg:classifiers":[
        {
            "category":"Food & Beverages",
            "subcategory":"Groceries & Convenience Stores",
            "type":"Retail Goods"
        }
    ],
    "sg:phone":"+1 704 435 8688",
    "sg:postcode":"28021",
    "sg:province":"NC",
    "wof:name":"USA Food Mart Inc",
    "wof:placetype":"venue"
},
  "geometry": {"coordinates":[-81.358914,35.385372],"type":"Point"}
}