{
  "type": "Feature",
  "properties": {
    "iso:country":"US",
    "sg:address":"3100 US Hwy 321 Bus",
    "sg:city":"Newton",
    "sg:classifiers":[
        {
            "category":"Building & Trades",
            "subcategory":"Construction",
            "type":"Services"
        }
    ],
    "sg:phone":"+1 828 428 9188",
    "sg:postcode":"28658",
    "sg:province":"NC",
    "sg:tags":[
        "paving",
        "contractor"
    ],
    "wof:name":"Long Grading Co",
    "wof:placetype":"venue"
},
  "geometry": {"coordinates":[-81.21624300000001,35.606522],"type":"Point"}
}