{
  "type": "Feature",
  "properties": {
    "addr:full":"5130 Carmel Club Dr Charlotte NC 28226",
    "addr:housenumber":"5130",
    "addr:postcode":"28226",
    "addr:street":"Carmel Club Dr",
    "iso:country":"US",
    "sg:address":"5130 Carmel Club Dr",
    "sg:city":"Charlotte",
    "sg:classifiers":[
        {
            "category":"Professional",
            "subcategory":"Business Services",
            "type":"Services"
        }
    ],
    "sg:phone":"+1   ",
    "sg:postcode":"28226",
    "sg:province":"NC",
    "sg:tags":[
        "interior",
        "design"
    ],
    "wof:name":"Barbara V Bolz Interiors",
    "wof:placetype":"venue"
},
  "geometry": {"coordinates":[-80.823267,35.099982],"type":"Point"}
}