{
  "type": "Feature",
  "properties": {
    "iso:country":"US",
    "sg:address":"136 Remount Rd",
    "sg:city":"Charlotte",
    "sg:classifiers":[
        {
            "category":"Professional",
            "subcategory":"Employment Agencies",
            "type":"Services"
        }
    ],
    "sg:phone":"+1 704 333 5656",
    "sg:postcode":"28203",
    "sg:province":"NC",
    "sg:tags":[
        "opportunity"
    ],
    "sg:website":"www.staffmasters-usa.com",
    "wof:name":"Staffmasters USA",
    "wof:placetype":"venue"
},
  "geometry": {"coordinates":[-80.86689,35.203661],"type":"Point"}
}