{
  "type": "Feature",
  "properties": {
    "iso:country":"US",
    "sg:address":"4459 Cumberland Rd",
    "sg:city":"Fayetteville",
    "sg:classifiers":[
        {
            "category":"Professional",
            "type":"Services"
        }
    ],
    "sg:phone":"+1 910 423 0606",
    "sg:postcode":"28306",
    "sg:province":"NC",
    "sg:tags":[
        "establishment"
    ],
    "wof:name":"Proserve Inc",
    "wof:placetype":"venue"
},
  "geometry": {"coordinates":[-78.957438,35.009193],"type":"Point"}
}