{
  "type": "Feature",
  "properties": {
    "iso:country":"US",
    "sg:address":"943 W Andrews Ave",
    "sg:city":"Henderson",
    "sg:classifiers":[
        {
            "category":"Shopping",
            "subcategory":"Clothing, Apparel, & Fashions",
            "type":"Retail Goods"
        }
    ],
    "sg:phone":"+1 252 438 2992",
    "sg:postcode":"27536",
    "sg:province":"NC",
    "sg:tags":[
        "alteration"
    ],
    "wof:name":"Terry's Alterations & Unique",
    "wof:placetype":"venue"
},
  "geometry": {"coordinates":[-78.410319,36.338959],"type":"Point"}
}