{
  "type": "Feature",
  "properties": {
    "addr:full":"276 Cranes Creek Rd Cameron NC 28326",
    "addr:housenumber":"276",
    "addr:postcode":"28326",
    "addr:street":"Cranes Creek Rd",
    "iso:country":"US",
    "sg:address":"276 Cranes Creek Rd",
    "sg:city":"Cameron",
    "sg:classifiers":[
        {
            "category":"Government",
            "subcategory":"Office",
            "type":"Public Place"
        }
    ],
    "sg:phone":"+1 910 245 2994",
    "sg:postcode":"28326",
    "sg:province":"NC",
    "sg:tags":[
        "county",
        "program"
    ],
    "wof:name":"Moore County Solid Waste Ctr",
    "wof:placetype":"venue"
},
  "geometry": {"coordinates":[-79.290722,35.313368],"type":"Point"}
}