{
  "type": "Feature",
  "properties": {
    "addr:full":"4839 Amity Pl Charlotte NC 28212",
    "addr:housenumber":"4839",
    "addr:postcode":"28212",
    "addr:street":"Amity Pl",
    "iso:country":"US",
    "sg:address":"4839 Amity Pl",
    "sg:city":"Charlotte",
    "sg:classifiers":[
        {
            "category":"Building & Trades",
            "subcategory":"Construction",
            "type":"Services"
        }
    ],
    "sg:phone":"+1 704 568 5001",
    "sg:postcode":"28212",
    "sg:province":"NC",
    "sg:tags":[
        "contractor"
    ],
    "wof:name":"Jones & Cross Ceramic Tile",
    "wof:placetype":"venue"
},
  "geometry": {"coordinates":[-80.761022,35.194856],"type":"Point"}
}