{
  "type": "Feature",
  "properties": {
    "iso:country":"US",
    "sg:address":"722 W College St",
    "sg:city":"Warsaw",
    "sg:classifiers":[
        {
            "category":"Taxi",
            "type":"Transportation"
        }
    ],
    "sg:phone":"+1 910 293 7083",
    "sg:postcode":"28398",
    "sg:province":"NC",
    "sg:tags":[
        "taxicab"
    ],
    "wof:name":"Baggett's Taxi",
    "wof:placetype":"venue"
},
  "geometry": {"coordinates":[-78.108577,34.994992],"type":"Point"}
}