{
  "type": "Feature",
  "properties": {
    "addr:full":"645 State Hwy 801 Advance NC 27006",
    "addr:housenumber":"645",
    "addr:postcode":"27006",
    "addr:street":"State Hwy 801",
    "iso:country":"US",
    "sg:address":"645 State Hwy 801",
    "sg:city":"Advance",
    "sg:classifiers":[
        {
            "category":"Organizations",
            "subcategory":"Religious Organization",
            "type":"Services"
        }
    ],
    "sg:phone":"+1   ",
    "sg:postcode":"27006",
    "sg:province":"NC",
    "wof:name":"Sandy Creek Baptist Church",
    "wof:placetype":"venue"
},
  "geometry": {"coordinates":[-80.460031,36.013253],"type":"Point"}
}