{
  "type": "Feature",
  "properties": {
    "addr:full":"1359 Ambrose Rd Creswell NC 27928",
    "addr:housenumber":"1359",
    "addr:postcode":"27928",
    "addr:street":"Ambrose Rd",
    "iso:country":"US",
    "sg:address":"1359 Ambrose Rd",
    "sg:city":"Creswell",
    "sg:classifiers":[
        {
            "category":"Farming",
            "subcategory":"Farm",
            "type":"Manufacturing & Wholesale Goods"
        }
    ],
    "sg:phone":"+1 252 797 4149",
    "sg:postcode":"27928",
    "sg:province":"NC",
    "sg:tags":[
        "crop",
        "general"
    ],
    "wof:name":"Selvie K James",
    "wof:placetype":"venue"
},
  "geometry": {"coordinates":[-76.439519,35.844428],"type":"Point"}
}