{
  "type": "Feature",
  "properties": {
    "iso:country":"US",
    "sg:address":"4042 John S Raboteau Wynd",
    "sg:city":"Raleigh",
    "sg:classifiers":[
        {
            "category":"Banks & Credit Unions",
            "subcategory":"Investment Brokerage",
            "type":"Services"
        }
    ],
    "sg:phone":"+1 919 782 4870",
    "sg:postcode":"27612",
    "sg:province":"NC",
    "wof:name":"Etc Investments",
    "wof:placetype":"venue"
},
  "geometry": {"coordinates":[-78.709159,35.833969],"type":"Point"}
}