{
  "type": "Feature",
  "properties": {
    "addr:full":"3713 University Dr Durham NC 27707",
    "addr:housenumber":"3713",
    "addr:postcode":"27707",
    "addr:street":"University Dr",
    "iso:country":"US",
    "sg:address":"3713 University Dr",
    "sg:city":"Durham",
    "sg:classifiers":[
        {
            "category":"Health Services",
            "subcategory":"Doctor",
            "type":"Services"
        }
    ],
    "sg:phone":"+1 919 401 6212",
    "sg:postcode":"27707",
    "sg:province":"NC",
    "sg:tags":[
        "physician",
        "surgeon"
    ],
    "wof:name":"Triangle Neuropsychiatry Pllc",
    "wof:placetype":"venue"
},
  "geometry": {"coordinates":[-78.950253,35.966741],"type":"Point"}
}