{
  "type": "Feature",
  "properties": {
    "addr:full":"887 Mazeppa Rd Mooresville NC 28115",
    "addr:housenumber":"887",
    "addr:postcode":"28115",
    "addr:street":"Mazeppa Rd",
    "iso:country":"US",
    "sg:address":"887 Mazeppa Rd",
    "sg:city":"Mooresville",
    "sg:classifiers":[
        {
            "category":"Building & Trades",
            "subcategory":"Construction",
            "type":"Services"
        }
    ],
    "sg:phone":"+1 704 663 4745",
    "sg:postcode":"28115",
    "sg:province":"NC",
    "sg:tags":[
        "grading",
        "contractor"
    ],
    "wof:name":"C Wayne Orbison & Sons Inc",
    "wof:placetype":"venue"
},
  "geometry": {"coordinates":[-80.772206,35.64244],"type":"Point"}
}