{
  "type": "Feature",
  "properties": {
    "addr:full":"2109 Coliseum Blvd Greensboro NC 27403",
    "addr:housenumber":"2109",
    "addr:postcode":"27403",
    "addr:street":"Coliseum Blvd",
    "iso:country":"US",
    "sg:address":"2109 Coliseum Blvd",
    "sg:city":"Greensboro",
    "sg:classifiers":[
        {
            "category":"Professional",
            "type":"Services"
        }
    ],
    "sg:phone":"+1 336 294 9336",
    "sg:postcode":"27403",
    "sg:province":"NC",
    "sg:tags":[
        "establishment"
    ],
    "wof:name":"Oxford House Coliseum",
    "wof:placetype":"venue"
},
  "geometry": {"coordinates":[-79.82215100000001,36.049062],"type":"Point"}
}