{
  "type": "Feature",
  "properties": {
    "iso:country":"US",
    "sg:address":"2751 N Roberts Ave",
    "sg:city":"Lumberton",
    "sg:classifiers":[
        {
            "category":"Professional",
            "type":"Services"
        }
    ],
    "sg:phone":"+1 910 272 8336",
    "sg:postcode":"28358",
    "sg:province":"NC",
    "wof:name":"Dreamcatcher",
    "wof:placetype":"venue"
},
  "geometry": {"coordinates":[-79.01185599999999,34.64473],"type":"Point"}
}