{
  "type": "Feature",
  "properties": {
    "addr:full":"1533 Jennings St Charlotte NC 28216",
    "addr:housenumber":"1533",
    "addr:postcode":"28216",
    "addr:street":"Jennings St",
    "iso:country":"US",
    "sg:address":"1533 Jennings St",
    "sg:city":"Charlotte",
    "sg:classifiers":[
        {
            "category":"Retail",
            "subcategory":"Funeral Services",
            "type":"Services"
        }
    ],
    "sg:phone":"+1   ",
    "sg:postcode":"28216",
    "sg:province":"NC",
    "wof:name":"Sneads Mortuary Services",
    "wof:placetype":"venue"
},
  "geometry": {"coordinates":[-80.849721,35.256494],"type":"Point"}
}