{
  "type": "Feature",
  "properties": {
    "addr:full":"5886 Farringdon Pl Raleigh NC 27609",
    "addr:housenumber":"5886",
    "addr:postcode":"27609",
    "addr:street":"Farringdon Pl",
    "iso:country":"US",
    "sg:address":"5886 Farringdon Pl",
    "sg:city":"Raleigh",
    "sg:classifiers":[
        {
            "category":"Building & Trades",
            "subcategory":"Cleaning & Sanitation",
            "type":"Services"
        }
    ],
    "sg:phone":"+1 919 878 8880",
    "sg:postcode":"27609",
    "sg:province":"NC",
    "sg:tags":[
        "janitor"
    ],
    "wof:name":"Pam's Personal Touch Cleaning",
    "wof:placetype":"venue"
},
  "geometry": {"coordinates":[-78.62158700000001,35.861218],"type":"Point"}
}