{
  "type": "Feature",
  "properties": {
    "iso:country":"US",
    "sg:address":"309 Raleigh St",
    "sg:city":"Wilmington",
    "sg:classifiers":[
        {
            "category":"Home & Garden",
            "subcategory":"Home Furnishings",
            "type":"Retail Goods"
        },
        {
            "category":"Shopping",
            "subcategory":"Gifts & Souvenirs",
            "type":"Retail Goods"
        }
    ],
    "sg:phone":"+1 910 791 4312",
    "sg:postcode":"28412",
    "sg:province":"NC",
    "sg:tags":[
        "decorative",
        "shop",
        "accessory"
    ],
    "sg:website":"www.welchome.com",
    "wof:name":"Welcome Home LLC",
    "wof:placetype":"venue"
},
  "geometry": {"coordinates":[-77.935239,34.17996],"type":"Point"}
}