{
  "type": "Feature",
  "properties": {
    "addr:full":"6640 Carmel Rd Charlotte NC 28226",
    "addr:housenumber":"6640",
    "addr:postcode":"28226",
    "addr:street":"Carmel Rd",
    "iso:country":"US",
    "sg:address":"6640 Carmel Rd",
    "sg:city":"Charlotte",
    "sg:classifiers":[
        {
            "category":"Restaurant",
            "type":"Food & Drink"
        }
    ],
    "sg:phone":"+1 704 541 0356",
    "sg:postcode":"28226",
    "sg:province":"NC",
    "sg:tags":[
        "parlor",
        "ice",
        "cream"
    ],
    "sg:website":"www.baskinrobbins.com",
    "wof:name":"Baskin-Robbins",
    "wof:placetype":"venue"
},
  "geometry": {"coordinates":[-80.846366,35.084756],"type":"Point"}
}