{
  "type": "Feature",
  "properties": {
    "addr:full":"1079 Boyette Rd Four Oaks NC 27524",
    "addr:housenumber":"1079",
    "addr:postcode":"27524",
    "addr:street":"Boyette Rd",
    "iso:country":"US",
    "sg:address":"1079 Boyette Rd",
    "sg:city":"Four Oaks",
    "sg:classifiers":[
        {
            "category":"Building & Trades",
            "subcategory":"Plumbing",
            "type":"Services"
        }
    ],
    "sg:phone":"+1 919 963 3180",
    "sg:postcode":"27524",
    "sg:province":"NC",
    "sg:tags":[
        "plumbing",
        "contractor"
    ],
    "wof:name":"Graylon Dixon's Plumbing",
    "wof:placetype":"venue"
},
  "geometry": {"coordinates":[-78.40998,35.445069],"type":"Point"}
}