{
  "type": "Feature",
  "properties": {
    "addr:full":"2161 Phibbs Rd Elon College NC 27244",
    "addr:housenumber":"2161",
    "addr:postcode":"27244",
    "addr:street":"Phibbs Rd Elon",
    "iso:country":"US",
    "sg:address":"2161 Phibbs Rd",
    "sg:city":"Elon College",
    "sg:classifiers":[
        {
            "category":"Building & Trades",
            "subcategory":"Construction",
            "type":"Services"
        }
    ],
    "sg:phone":"+1 336 584 8708",
    "sg:postcode":"27244",
    "sg:province":"NC",
    "sg:tags":[
        "painter"
    ],
    "wof:name":"Huffman Painting",
    "wof:placetype":"venue"
},
  "geometry": {"coordinates":[-79.498204,36.135246],"type":"Point"}
}