{
  "type": "Feature",
  "properties": {
    "iso:country":"US",
    "sg:address":"1700 Teledyne Rd",
    "sg:city":"Monroe",
    "sg:classifiers":[
        {
            "category":"Wholesale",
            "subcategory":"Metals & Minerals",
            "type":"Manufacturing & Wholesale Goods"
        }
    ],
    "sg:phone":"+1 704 289 4511",
    "sg:postcode":"28110",
    "sg:province":"NC",
    "sg:tags":[
        "nickel"
    ],
    "sg:website":"http://www.alleghenyludlum.com",
    "wof:name":"Ati Allvac",
    "wof:placetype":"venue"
},
  "geometry": {"coordinates":[-80.613998,35.02256],"type":"Point"}
}