{
  "type": "Feature",
  "properties": {
    "addr:full":"6000 Quiet Cove Ct Charlotte NC 28215",
    "addr:housenumber":"6000",
    "addr:postcode":"28215",
    "addr:street":"Quiet Cove Ct",
    "iso:country":"US",
    "sg:address":"6000 Quiet Cove Ct",
    "sg:city":"Charlotte",
    "sg:classifiers":[
        {
            "category":"Social Services",
            "subcategory":"Child Care",
            "type":"Services"
        }
    ],
    "sg:phone":"+1 704 531 5973",
    "sg:postcode":"28215",
    "sg:province":"NC",
    "wof:name":"A Mother's Love FCCH",
    "wof:placetype":"venue"
},
  "geometry": {"coordinates":[-80.741309,35.255102],"type":"Point"}
}