{
  "type": "Feature",
  "properties": {
    "addr:full":"10056 E Independence Blvd Matthews NC 28105",
    "addr:housenumber":"10056",
    "addr:postcode":"28105",
    "addr:street":"E Independence Blvd",
    "iso:country":"US",
    "sg:address":"10056 E Independence Blvd",
    "sg:city":"Matthews",
    "sg:classifiers":[
        {
            "category":"Restaurant",
            "type":"Food & Drink"
        }
    ],
    "sg:menulink":"http://www.allmenus.com/nc/morning-star/12437-bonefish-grill/menu/",
    "sg:phone":"+1 704 845 8001",
    "sg:postcode":"28105",
    "sg:province":"NC",
    "sg:tags":[
        "seafood",
        "american"
    ],
    "wof:name":"Bonefish Grill",
    "wof:placetype":"venue"
},
  "geometry": {"coordinates":[-80.71150400000001,35.132447],"type":"Point"}
}