{
  "type": "Feature",
  "properties": {
    "iso:country":"US",
    "sg:address":"2116 N Bridge St",
    "sg:city":"Elkin",
    "sg:classifiers":[
        {
            "category":"Wholesale",
            "subcategory":"Hardware",
            "type":"Manufacturing & Wholesale Goods"
        },
        {
            "category":"Home & Garden",
            "subcategory":"Garden Supply",
            "type":"Retail Goods"
        },
        {
            "category":"Retail",
            "subcategory":"Repair Shop",
            "type":"Services"
        }
    ],
    "sg:phone":"+1 336 835 1600",
    "sg:postcode":"28621",
    "sg:province":"NC",
    "sg:tags":[
        "renting",
        "lawn",
        "outdoor",
        "power",
        "landscaping",
        "equipment-sales",
        "equipment",
        "saw"
    ],
    "sg:website":"http://www.stihldealer.net/default-dealer-020059.aspx",
    "wof:name":"Price Power Equipment",
    "wof:placetype":"venue"
},
  "geometry": {"coordinates":[-80.851669,36.248104],"type":"Point"}
}