{
  "type": "Feature",
  "properties": {
    "iso:country":"US",
    "sg:address":"301 Dominion Drive, Suite E",
    "sg:city":"Morrisville",
    "sg:classifiers":[
        {
            "category":"Building & Trades",
            "subcategory":"Cleaning & Sanitation",
            "type":"Services"
        },
        {
            "category":"Building & Trades",
            "subcategory":"Construction",
            "type":"Services"
        }
    ],
    "sg:phone":"+1 919 862 8600",
    "sg:postcode":"27560",
    "sg:province":"NC",
    "sg:tags":[
        "control",
        "hazardous",
        "material",
        "preservation",
        "contractor",
        "restoration",
        "board",
        "removal"
    ],
    "sg:website":"http://www.afterdisaster.com",
    "wof:name":"AFTERDISASTER",
    "wof:placetype":"venue"
},
  "geometry": {"coordinates":[-78.810373,35.841542],"type":"Point"}
}