{
  "type": "Feature",
  "properties": {
    "iso:country":"US",
    "sg:address":"111 Cloister Ct",
    "sg:city":"Chapel Hill",
    "sg:classifiers":[
        {
            "category":"Real Estate",
            "subcategory":"Developer",
            "type":"Services"
        }
    ],
    "sg:phone":"+1 919 402 0411",
    "sg:postcode":"27514",
    "sg:province":"NC",
    "wof:name":"Adair Properties",
    "wof:placetype":"venue"
},
  "geometry": {"coordinates":[-79.00505800000001,35.95333],"type":"Point"}
}