{
  "type": "Feature",
  "properties": {
    "addr:full":"456 Central Ave Lexington NC 27292",
    "addr:housenumber":"456",
    "addr:postcode":"27292",
    "addr:street":"Central Ave",
    "iso:country":"US",
    "sg:address":"456 Central Ave",
    "sg:city":"Lexington",
    "sg:classifiers":[
        {
            "category":"Manufacturing",
            "subcategory":"Printing",
            "type":"Manufacturing & Wholesale Goods"
        }
    ],
    "sg:phone":"+1 336 249 3148",
    "sg:postcode":"27292",
    "sg:province":"NC",
    "sg:tags":[
        "commercial",
        "offset"
    ],
    "wof:name":"Young Graphics Inc",
    "wof:placetype":"venue"
},
  "geometry": {"coordinates":[-80.274912,35.826098],"type":"Point"}
}