{
  "type": "Feature",
  "properties": {
    "iso:country":"US",
    "sg:address":"125 E Pennsylvania Ave",
    "sg:city":"Southern Pines",
    "sg:classifiers":[
        {
            "category":"Insurance",
            "subcategory":"Insurance Agent",
            "type":"Services"
        }
    ],
    "sg:phone":"+1 910 693 1414",
    "sg:postcode":"28387",
    "sg:province":"NC",
    "wof:name":"New York Life",
    "wof:placetype":"venue"
},
  "geometry": {"coordinates":[-79.391588,35.173479],"type":"Point"}
}