{
  "type": "Feature",
  "properties": {
    "iso:country":"US",
    "sg:address":"415 N 7th St",
    "sg:city":"Smithfield",
    "sg:classifiers":[
        {
            "category":"Health Services",
            "subcategory":"Doctor",
            "type":"Services"
        }
    ],
    "sg:phone":"+1 919 934 3636",
    "sg:postcode":"27577",
    "sg:province":"NC",
    "sg:tags":[
        "dentist",
        "medical"
    ],
    "wof:name":"Henry N Wright DDS",
    "wof:placetype":"venue"
},
  "geometry": {"coordinates":[-78.337895,35.513615],"type":"Point"}
}