{
  "type": "Feature",
  "properties": {
    "addr:full":"10504 Tavernay Pkwy Charlotte NC 28262",
    "addr:housenumber":"10504",
    "addr:postcode":"28262",
    "addr:street":"Tavernay Pkwy",
    "iso:country":"US",
    "sg:address":"10504 Tavernay Pkwy",
    "sg:city":"Charlotte",
    "sg:classifiers":[
        {
            "category":"Wholesale",
            "subcategory":"Machinery & Supplies",
            "type":"Manufacturing & Wholesale Goods"
        }
    ],
    "sg:phone":"+1 704 593 0595",
    "sg:postcode":"28262",
    "sg:province":"NC",
    "sg:tags":[
        "equipment",
        "industrial"
    ],
    "wof:name":"European Machine Tools Inc",
    "wof:placetype":"venue"
},
  "geometry": {"coordinates":[-80.75267100000001,35.345751],"type":"Point"}
}