{
  "type": "Feature",
  "properties": {
    "addr:full":"123 Goa Way Rutherfordton NC 28139",
    "addr:housenumber":"123",
    "addr:postcode":"28139",
    "addr:street":"Goa Way",
    "iso:country":"US",
    "sg:address":"123 Goa Way",
    "sg:city":"Rutherfordton",
    "sg:classifiers":[
        {
            "category":"Building & Trades",
            "subcategory":"Construction",
            "type":"Services"
        }
    ],
    "sg:phone":"+1 828 286 2752",
    "sg:postcode":"28139",
    "sg:province":"NC",
    "sg:tags":[
        "house"
    ],
    "wof:name":"Jim Barrett Construction",
    "wof:placetype":"venue"
},
  "geometry": {"coordinates":[-82.116924,35.430354],"type":"Point"}
}