{
  "type": "Feature",
  "properties": {
    "addr:full":"63 Mountain Laurel Dr Spruce Pine NC 28777",
    "addr:housenumber":"63",
    "addr:postcode":"28777",
    "addr:street":"Mountain Laurel Dr",
    "iso:country":"US",
    "sg:address":"63 Mountain Laurel Dr",
    "sg:city":"Spruce Pine",
    "sg:classifiers":[
        {
            "category":"Shopping",
            "subcategory":"Gifts & Souvenirs",
            "type":"Retail Goods"
        }
    ],
    "sg:phone":"+1 828 765 6869",
    "sg:postcode":"28777",
    "sg:province":"NC",
    "sg:tags":[
        "collectible"
    ],
    "wof:name":"Rich Long's Custom Ships",
    "wof:placetype":"venue"
},
  "geometry": {"coordinates":[-82.06173200000001,35.893094],"type":"Point"}
}