{
  "type": "Feature",
  "properties": {
    "iso:country":"US",
    "sg:address":"3910 Vance St Exd",
    "sg:city":"Reidsville",
    "sg:classifiers":[
        {
            "category":"Organizations",
            "subcategory":"Religious Organization",
            "type":"Services"
        }
    ],
    "sg:phone":"+1 336 634 1979",
    "sg:postcode":"27320",
    "sg:province":"NC",
    "sg:tags":[
        "church"
    ],
    "wof:name":"Noah's Ark Full Gospel Baptist",
    "wof:placetype":"venue"
},
  "geometry": {"coordinates":[-79.716219,36.359496],"type":"Point"}
}