{
  "type": "Feature",
  "properties": {
    "iso:country":"US",
    "sg:address":"107 Hill St",
    "sg:city":"Louisburg",
    "sg:classifiers":[
        {
            "category":"Personal",
            "subcategory":"Beauty Salon",
            "type":"Services"
        }
    ],
    "sg:phone":"+1   ",
    "sg:postcode":"27549",
    "sg:province":"NC",
    "sg:tags":[
        "shop"
    ],
    "wof:name":"Styles Unlimited Beauty Salon",
    "wof:placetype":"venue"
},
  "geometry": {"coordinates":[-78.300709,36.09238],"type":"Point"}
}