{
  "type": "Feature",
  "properties": {
    "iso:country":"US",
    "sg:address":"1116 Spring Forest Dr",
    "sg:city":"Rocky Mount",
    "sg:classifiers":[
        {
            "category":"Wholesale",
            "subcategory":"Durable Goods & Equipment",
            "type":"Manufacturing & Wholesale Goods"
        }
    ],
    "sg:phone":"+1 252 567 8098",
    "sg:postcode":"27803",
    "sg:province":"NC",
    "sg:tags":[
        "robotics"
    ],
    "wof:name":"Openware Logistx Inc",
    "wof:placetype":"venue"
},
  "geometry": {"coordinates":[-77.852514,35.936533],"type":"Point"}
}