{
  "type": "Feature",
  "properties": {
    "iso:country":"US",
    "sg:address":"1884 N Graham St",
    "sg:city":"Charlotte",
    "sg:classifiers":[
        {
            "category":"Food & Beverages",
            "subcategory":"Groceries & Convenience Stores",
            "type":"Retail Goods"
        }
    ],
    "sg:phone":"+1 704 333 6104",
    "sg:postcode":"28206",
    "sg:province":"NC",
    "sg:tags":[
        "station",
        "gasoline"
    ],
    "wof:name":"Circle K",
    "wof:placetype":"venue"
},
  "geometry": {"coordinates":[-80.831559,35.244952],"type":"Point"}
}