{
  "type": "Feature",
  "properties": {
    "addr:full":"4712 S New Hope Rd Belmont NC 28012",
    "addr:housenumber":"4712",
    "addr:postcode":"28012",
    "addr:street":"S New Hope Rd",
    "iso:country":"US",
    "sg:address":"4712 S New Hope Rd",
    "sg:city":"Belmont",
    "sg:classifiers":[
        {
            "category":"Building & Trades",
            "subcategory":"Pest Control",
            "type":"Services"
        }
    ],
    "sg:phone":"+1 704 825 1310",
    "sg:postcode":"28012",
    "sg:province":"NC",
    "sg:tags":[
        "industrial",
        "services-commercial"
    ],
    "wof:name":"Lake Wylie Exterminating Company",
    "wof:placetype":"venue"
},
  "geometry": {"coordinates":[-81.07380999999999,35.205226],"type":"Point"}
}