{
  "type": "Feature",
  "properties": {
    "addr:full":"4896 Country Club Rd Winston Salem NC 27104",
    "addr:housenumber":"4896",
    "addr:postcode":"27104",
    "addr:street":"Country Club Rd",
    "iso:country":"US",
    "sg:address":"4896 Country Club Rd",
    "sg:city":"Winston Salem",
    "sg:classifiers":[
        {
            "category":"Retail",
            "subcategory":"Auto Repair",
            "type":"Services"
        }
    ],
    "sg:phone":"+1 336 765 0940",
    "sg:postcode":"27104",
    "sg:province":"NC",
    "sg:tags":[
        "automobile",
        "lubrication"
    ],
    "wof:name":"Qwik Lube",
    "wof:placetype":"venue"
},
  "geometry": {"coordinates":[-80.343115,36.082585],"type":"Point"}
}