{
  "type": "Feature",
  "properties": {
    "addr:full":"1841 Noahtown Rd Thomasville NC 27360",
    "addr:housenumber":"1841",
    "addr:postcode":"27360",
    "addr:street":"Noahtown Rd",
    "iso:country":"US",
    "sg:address":"1841 Noahtown Rd",
    "sg:city":"Thomasville",
    "sg:classifiers":[
        {
            "category":"Real Estate",
            "subcategory":"Real Estate Operator",
            "type":"Services"
        }
    ],
    "sg:phone":"+1 336 472 6540",
    "sg:postcode":"27360",
    "sg:province":"NC",
    "sg:tags":[
        "mobile",
        "home",
        "site"
    ],
    "wof:name":"Rocky Ridge Mobile Home Park",
    "wof:placetype":"venue"
},
  "geometry": {"coordinates":[-80.070802,35.782295],"type":"Point"}
}