{
  "type": "Feature",
  "properties": {
    "iso:country":"US",
    "sg:address":"66 Passmore Rd",
    "sg:city":"Franklin",
    "sg:classifiers":[
        {
            "category":"Building & Trades",
            "subcategory":"Construction",
            "type":"Services"
        }
    ],
    "sg:phone":"+1 828 349 1494",
    "sg:postcode":"28734",
    "sg:province":"NC",
    "wof:name":"Sue Passmore",
    "wof:placetype":"venue"
},
  "geometry": {"coordinates":[-83.453523,35.165962],"type":"Point"}
}