{
  "type": "Feature",
  "properties": {
    "iso:country":"US",
    "sg:address":"1203 Old Dallas Rd",
    "sg:city":"Dallas",
    "sg:classifiers":[
        {
            "category":"Autos & Motor Vehicles",
            "subcategory":"Fuel & Gas Station",
            "type":"Retail Goods"
        }
    ],
    "sg:phone":"+1 704 922 0228",
    "sg:postcode":"28034",
    "sg:province":"NC",
    "sg:tags":[
        "oil"
    ],
    "wof:name":"Field's Exxon",
    "wof:placetype":"venue"
},
  "geometry": {"coordinates":[-81.179478,35.301404],"type":"Point"}
}