{
  "type": "Feature",
  "properties": {
    "iso:country":"US",
    "sg:address":"6230 Fairview Rd",
    "sg:city":"Charlotte",
    "sg:classifiers":[
        {
            "category":"Real Estate",
            "subcategory":"Real Estate Agent",
            "type":"Services"
        }
    ],
    "sg:phone":"+1 704 364 3328",
    "sg:postcode":"28210",
    "sg:province":"NC",
    "wof:name":"C B Richard Ellis",
    "wof:placetype":"venue"
},
  "geometry": {"coordinates":[-80.834847,35.149909],"type":"Point"}
}