{
  "type": "Feature",
  "properties": {
    "addr:full":"910 Tate Blvd SE Hickory NC 28602",
    "addr:housenumber":"910",
    "addr:postcode":"28602",
    "addr:street":"Tate Blvd Se",
    "iso:country":"US",
    "sg:address":"910 Tate Blvd SE",
    "sg:city":"Hickory",
    "sg:classifiers":[
        {
            "category":"Insurance",
            "subcategory":"Insurance Agent",
            "type":"Services"
        }
    ],
    "sg:phone":"+1 828 304 5600",
    "sg:postcode":"28602",
    "sg:province":"NC",
    "wof:name":"GMAC Insurance Claims Ofc",
    "wof:placetype":"venue"
},
  "geometry": {"coordinates":[-81.32265200000001,35.730498],"type":"Point"}
}