{
  "type": "Feature",
  "properties": {
    "iso:country":"US",
    "sg:address":"7829 Portia Pl",
    "sg:city":"Charlotte",
    "sg:classifiers":[
        {
            "category":"Shopping",
            "subcategory":"Gifts & Souvenirs",
            "type":"Retail Goods"
        }
    ],
    "sg:phone":"+1 704 537 4263",
    "sg:postcode":"28227",
    "sg:province":"NC",
    "sg:tags":[
        "basket",
        "parcel"
    ],
    "wof:name":"Harpanells Essential Elements",
    "wof:placetype":"venue"
},
  "geometry": {"coordinates":[-80.702275,35.217949],"type":"Point"}
}