{
  "type": "Feature",
  "properties": {
    "iso:country":"US",
    "sg:address":"610 Kenion Rd",
    "sg:city":"Hillsborough",
    "sg:classifiers":[
        {
            "category":"Professional",
            "type":"Services"
        }
    ],
    "sg:phone":"+1 919 644 6038",
    "sg:postcode":"27278",
    "sg:province":"NC",
    "wof:name":"Hugo Clark",
    "wof:placetype":"venue"
},
  "geometry": {"coordinates":[-79.130059,36.134968],"type":"Point"}
}