{
  "type": "Feature",
  "properties": {
    "iso:country":"US",
    "sg:address":"1777 Robinhood Dr",
    "sg:city":"Burlington",
    "sg:classifiers":[
        {
            "category":"Banks & Credit Unions",
            "subcategory":"Financial Services",
            "type":"Services"
        }
    ],
    "sg:phone":"+1 336 584 8065",
    "sg:postcode":"27217",
    "sg:province":"NC",
    "sg:tags":[
        "investor"
    ],
    "wof:name":"Whitt Investments of Triad",
    "wof:placetype":"venue"
},
  "geometry": {"coordinates":[-79.482759,36.126615],"type":"Point"}
}