{
  "type": "Feature",
  "properties": {
    "addr:full":"1109 Princeton Dr Wilmington NC 28403",
    "addr:housenumber":"1109",
    "addr:postcode":"28403",
    "addr:street":"Princeton Dr",
    "iso:country":"US",
    "sg:address":"1109 Princeton Dr",
    "sg:city":"Wilmington",
    "sg:classifiers":[
        {
            "category":"Professional",
            "subcategory":"Management & Consulting",
            "type":"Services"
        }
    ],
    "sg:phone":"+1   ",
    "sg:postcode":"28403",
    "sg:province":"NC",
    "sg:tags":[
        "rep",
        "sales",
        "for"
    ],
    "wof:name":"Dunn & Co",
    "wof:placetype":"venue"
},
  "geometry": {"coordinates":[-77.907543,34.224322],"type":"Point"}
}