{
  "type": "Feature",
  "properties": {
    "iso:country":"US",
    "sg:address":"4101 Hodges Chapel Rd",
    "sg:city":"Dunn",
    "sg:classifiers":[
        {
            "category":"Wholesale",
            "subcategory":"Machinery & Supplies",
            "type":"Manufacturing & Wholesale Goods"
        }
    ],
    "sg:phone":"+1 910 897 4555",
    "sg:postcode":"28334",
    "sg:province":"NC",
    "sg:tags":[
        "truck"
    ],
    "wof:name":"Big Red Inc",
    "wof:placetype":"venue"
},
  "geometry": {"coordinates":[-78.555502,35.338124],"type":"Point"}
}