{
  "type": "Feature",
  "properties": {
    "iso:country":"US",
    "sg:address":"814 Union St S",
    "sg:city":"Concord",
    "sg:classifiers":[
        {
            "category":"Personal",
            "subcategory":"Beauty Salon",
            "type":"Services"
        }
    ],
    "sg:phone":"+1   ",
    "sg:postcode":"28025",
    "sg:province":"NC",
    "sg:tags":[
        "shop"
    ],
    "wof:name":"Modern Beauty Salon",
    "wof:placetype":"venue"
},
  "geometry": {"coordinates":[-80.56146200000001,35.388745],"type":"Point"}
}