{
  "type": "Feature",
  "properties": {
    "iso:country":"US",
    "sg:address":"4219 Lake Ridge Dr",
    "sg:city":"Raleigh",
    "sg:classifiers":[
        {
            "category":"Organizations",
            "subcategory":"Religious Organization",
            "type":"Services"
        }
    ],
    "sg:phone":"+1   ",
    "sg:postcode":"27604",
    "sg:province":"NC",
    "wof:name":"Family Worship Assembly",
    "wof:placetype":"venue"
},
  "geometry": {"coordinates":[-78.582719,35.840322],"type":"Point"}
}