{
  "type": "Feature",
  "properties": {
    "iso:country":"US",
    "sg:address":"360 Crestview Ln",
    "sg:city":"Banner Elk",
    "sg:classifiers":[
        {
            "category":"Real Estate",
            "subcategory":"Developer",
            "type":"Services"
        }
    ],
    "sg:phone":"+1 828 898 2431",
    "sg:postcode":"28604",
    "sg:province":"NC",
    "wof:name":"D K Development",
    "wof:placetype":"venue"
},
  "geometry": {"coordinates":[-81.868742,36.134368],"type":"Point"}
}