{
  "type": "Feature",
  "properties": {
    "addr:full":"201 E Six Forks Rd Raleigh NC 27609",
    "addr:housenumber":"201",
    "addr:postcode":"27609",
    "addr:street":"E Six Forks Rd",
    "iso:country":"US",
    "sg:address":"201 E Six Forks Rd",
    "sg:city":"Raleigh",
    "sg:classifiers":[
        {
            "category":"Social Services",
            "subcategory":"Child Care",
            "type":"Services"
        }
    ],
    "sg:phone":"+1 919 834 0677",
    "sg:postcode":"27609",
    "sg:province":"NC",
    "sg:website":"www.childcarenetwork.net",
    "wof:name":"Child Care Network Inc",
    "wof:placetype":"venue"
},
  "geometry": {"coordinates":[-78.62959499999999,35.821671],"type":"Point"}
}