{
  "type": "Feature",
  "properties": {
    "iso:country":"US",
    "sg:address":"126 7th St SW",
    "sg:city":"Taylorsville",
    "sg:classifiers":[
        {
            "category":"Social Services",
            "type":"Services"
        }
    ],
    "sg:phone":"+1 828 635 8850",
    "sg:postcode":"28681",
    "sg:province":"NC",
    "sg:tags":[
        "organization",
        "welfare"
    ],
    "wof:name":"Domestic Violence Alexander",
    "wof:placetype":"venue"
},
  "geometry": {"coordinates":[-81.18236,35.919863],"type":"Point"}
}