{
  "type": "Feature",
  "properties": {
    "iso:country":"US",
    "sg:address":"238 Emma Jane Rd",
    "sg:city":"Saint Pauls",
    "sg:classifiers":[
        {
            "category":"Building & Trades",
            "subcategory":"Construction",
            "type":"Services"
        }
    ],
    "sg:phone":"+1 910 739 0054",
    "sg:postcode":"28384",
    "sg:province":"NC",
    "sg:tags":[
        "hanging",
        "contractor"
    ],
    "wof:name":"Scott Painting Drywall",
    "wof:placetype":"venue"
},
  "geometry": {"coordinates":[-79.019868,34.761219],"type":"Point"}
}