{
  "type": "Feature",
  "properties": {
    "iso:country":"US",
    "sg:address":"150 Rugby Forest Ln",
    "sg:city":"Hendersonville",
    "sg:classifiers":[
        {
            "category":"Building & Trades",
            "subcategory":"Construction",
            "type":"Services"
        }
    ],
    "sg:phone":"+1 828 697 9221",
    "sg:postcode":"28791",
    "sg:province":"NC",
    "sg:tags":[
        "house"
    ],
    "wof:name":"Heatherly Construction Inc",
    "wof:placetype":"venue"
},
  "geometry": {"coordinates":[-82.51514899999999,35.389016],"type":"Point"}
}