{
  "type": "Feature",
  "properties": {
    "addr:full":"3004 Sandia Dr Raleigh NC 27607",
    "addr:housenumber":"3004",
    "addr:postcode":"27607",
    "addr:street":"Sandia Dr",
    "iso:country":"US",
    "sg:address":"3004 Sandia Dr",
    "sg:city":"Raleigh",
    "sg:classifiers":[
        {
            "category":"Banks & Credit Unions",
            "subcategory":"Financial Services",
            "type":"Services"
        }
    ],
    "sg:phone":"+1 919 782 8900",
    "sg:postcode":"27607",
    "sg:province":"NC",
    "sg:tags":[
        "company",
        "holding"
    ],
    "wof:name":"D M Holding Co",
    "wof:placetype":"venue"
},
  "geometry": {"coordinates":[-78.681134,35.82253],"type":"Point"}
}