{
  "type": "Feature",
  "properties": {
    "addr:full":"601 N 8th St Smithfield NC 27577",
    "addr:housenumber":"601",
    "addr:postcode":"27577",
    "addr:street":"N 8Th St",
    "iso:country":"US",
    "sg:address":"601 N 8th St",
    "sg:city":"Smithfield",
    "sg:classifiers":[
        {
            "category":"Health Services",
            "subcategory":"Doctor",
            "type":"Services"
        }
    ],
    "sg:phone":"+1 919 934 8977",
    "sg:postcode":"27577",
    "sg:province":"NC",
    "sg:tags":[
        "physician",
        "medical",
        "surgeon"
    ],
    "wof:name":"Woodrow Batten MD PA",
    "wof:placetype":"venue"
},
  "geometry": {"coordinates":[-78.334419,35.51607],"type":"Point"}
}