{
  "type": "Feature",
  "properties": {
    "addr:full":"311 Orville Wright Dr Greensboro NC 27409",
    "addr:housenumber":"311",
    "addr:postcode":"27409",
    "addr:street":"Orville Wright Dr",
    "iso:country":"US",
    "sg:address":"311 Orville Wright Dr",
    "sg:city":"Greensboro",
    "sg:classifiers":[
        {
            "category":"Building & Trades",
            "subcategory":"Landscaping Services",
            "type":"Services"
        }
    ],
    "sg:phone":"+1 336 605 3762",
    "sg:postcode":"27409",
    "sg:province":"NC",
    "sg:tags":[
        "landscape",
        "contractor"
    ],
    "wof:name":"Plymouth Nursery & Landscaping",
    "wof:placetype":"venue"
},
  "geometry": {"coordinates":[-79.951848,36.087894],"type":"Point"}
}