{
  "type": "Feature",
  "properties": {
    "addr:full":"1288 N Wesleyan Blvd Rocky Mount NC 27804",
    "addr:housenumber":"1288",
    "addr:postcode":"27804",
    "addr:street":"N Wesleyan Blvd",
    "iso:country":"US",
    "sg:address":"1288 N Wesleyan Blvd",
    "sg:city":"Rocky Mount",
    "sg:classifiers":[
        {
            "category":"Retail",
            "subcategory":"Auto Repair",
            "type":"Services"
        }
    ],
    "sg:phone":"+1 252 451 4227",
    "sg:postcode":"27804",
    "sg:province":"NC",
    "sg:tags":[
        "automobile",
        "inspection"
    ],
    "wof:name":"Inspect A Car",
    "wof:placetype":"venue"
},
  "geometry": {"coordinates":[-77.799136,35.975129],"type":"Point"}
}