{
  "type": "Feature",
  "properties": {
    "addr:full":"602 Topwater Ln Greensboro NC 27455",
    "addr:housenumber":"602",
    "addr:postcode":"27455",
    "addr:street":"Topwater Ln",
    "iso:country":"US",
    "sg:address":"602 Topwater Ln",
    "sg:city":"Greensboro",
    "sg:classifiers":[
        {
            "category":"Wholesale",
            "subcategory":"Durable Goods & Equipment",
            "type":"Manufacturing & Wholesale Goods"
        }
    ],
    "sg:phone":"+1 336 282 6881",
    "sg:postcode":"27455",
    "sg:province":"NC",
    "sg:tags":[
        "representative",
        "manufacturer"
    ],
    "wof:name":"Jacobson & Mosher Inc",
    "wof:placetype":"venue"
},
  "geometry": {"coordinates":[-79.806937,36.161005],"type":"Point"}
}