{
  "type": "Feature",
  "properties": {
    "iso:country":"US",
    "sg:address":"3742 S Main St",
    "sg:city":"Farmville",
    "sg:classifiers":[
        {
            "category":"Restaurant",
            "type":"Food & Drink"
        }
    ],
    "sg:phone":"+1 252 753 5333",
    "sg:postcode":"27828",
    "sg:province":"NC",
    "wof:name":"Farmville Cafe",
    "wof:placetype":"venue"
},
  "geometry": {"coordinates":[-77.585646,35.59692],"type":"Point"}
}