{
  "type": "Feature",
  "properties": {
    "iso:country":"US",
    "sg:address":"9229 Peakwood Dr SW",
    "sg:city":"Calabash",
    "sg:classifiers":[
        {
            "category":"Building & Trades",
            "subcategory":"Equipment Rental",
            "type":"Services"
        }
    ],
    "sg:phone":"+1   ",
    "sg:postcode":"28467",
    "sg:province":"NC",
    "wof:name":"D&M Rental Development Inc",
    "wof:placetype":"venue"
},
  "geometry": {"coordinates":[-78.549302,33.874333],"type":"Point"}
}