{
  "type": "Feature",
  "properties": {
    "addr:full":"670 Clyde Pearce Rd Zebulon NC 27597",
    "addr:housenumber":"670",
    "addr:postcode":"27597",
    "addr:street":"Clyde Pearce Rd",
    "iso:country":"US",
    "sg:address":"670 Clyde Pearce Rd",
    "sg:city":"Zebulon",
    "sg:phone":"+1 919 269 8466",
    "sg:postcode":"27597",
    "sg:province":"NC",
    "sg:tags":[
        "farm",
        "tobacco"
    ],
    "wof:name":"Wallace Stallings",
    "wof:placetype":"venue"
},
  "geometry": {"coordinates":[-78.27125700000001,35.886725],"type":"Point"}
}