{
  "type": "Feature",
  "properties": {
    "addr:full":"12509 Hammersmith Ct Charlotte NC 28262",
    "addr:housenumber":"12509",
    "addr:postcode":"28262",
    "addr:street":"Hammersmith Ct",
    "iso:country":"US",
    "sg:address":"12509 Hammersmith Ct",
    "sg:city":"Charlotte",
    "sg:classifiers":[
        {
            "category":"Professional",
            "subcategory":"Business Services",
            "type":"Services"
        }
    ],
    "sg:phone":"+1   ",
    "sg:postcode":"28262",
    "sg:province":"NC",
    "sg:tags":[
        "architectural"
    ],
    "wof:name":"House Plan Service",
    "wof:placetype":"venue"
},
  "geometry": {"coordinates":[-80.71052400000001,35.34436],"type":"Point"}
}