{
  "type": "Feature",
  "properties": {
    "iso:country":"US",
    "sg:address":"1116 Wedgeland Dr",
    "sg:city":"Raleigh",
    "sg:classifiers":[
        {
            "category":"Professional",
            "subcategory":"Management & Consulting",
            "type":"Services"
        }
    ],
    "sg:phone":"+1   ",
    "sg:postcode":"27615",
    "sg:province":"NC",
    "sg:tags":[
        "business"
    ],
    "wof:name":"Blairs Consulting",
    "wof:placetype":"venue"
},
  "geometry": {"coordinates":[-78.659301,35.878956],"type":"Point"}
}