{
  "type": "Feature",
  "properties": {
    "iso:country":"US",
    "sg:address":"375 Newton Dr",
    "sg:city":"Southern Pines",
    "sg:classifiers":[
        {
            "category":"Professional",
            "subcategory":"Management & Consulting",
            "type":"Services"
        }
    ],
    "sg:phone":"+1   ",
    "sg:postcode":"28387",
    "sg:province":"NC",
    "wof:name":"Sab Investing/Cnsltn",
    "wof:placetype":"venue"
},
  "geometry": {"coordinates":[-79.39235499999999,35.20414],"type":"Point"}
}