{
  "type": "Feature",
  "properties": {
    "addr:full":"1608 East Blvd Charlotte NC 28203",
    "addr:housenumber":"1608",
    "addr:postcode":"28203",
    "addr:street":"East Blvd",
    "iso:country":"US",
    "sg:address":"1608 East Blvd",
    "sg:city":"Charlotte",
    "sg:classifiers":[
        {
            "category":"Restaurant",
            "type":"Food & Drink"
        }
    ],
    "sg:menulink":"http://www.allmenus.com/nc/charlotte/47559-sole-spanish-grille/menu/",
    "sg:phone":"+1 704 343 9890",
    "sg:postcode":"28203",
    "sg:province":"NC",
    "sg:tags":[
        "spanish"
    ],
    "wof:name":"Sole Spanish Grille",
    "wof:placetype":"venue"
},
  "geometry": {"coordinates":[-80.841325,35.199516],"type":"Point"}
}