{
  "type": "Feature",
  "properties": {
    "iso:country":"US",
    "sg:address":"821 Perry Rd",
    "sg:city":"Apex",
    "sg:classifiers":[
        {
            "category":"Health Services",
            "subcategory":"Optometrist",
            "type":"Services"
        }
    ],
    "sg:phone":"+1 919 362 1962",
    "sg:postcode":"27502",
    "sg:province":"NC",
    "wof:name":"Toler Robert L",
    "wof:placetype":"venue"
},
  "geometry": {"coordinates":[-78.844584,35.720207],"type":"Point"}
}