{
  "type": "Feature",
  "properties": {
    "addr:full":"603 Cook Rd Durham NC 27713",
    "addr:housenumber":"603",
    "addr:postcode":"27713",
    "addr:street":"Cook Rd",
    "iso:country":"US",
    "sg:address":"603 Cook Rd",
    "sg:city":"Durham",
    "sg:classifiers":[
        {
            "category":"Personal",
            "subcategory":"Beauty Salon",
            "type":"Services"
        }
    ],
    "sg:phone":"+1 919 680 4686",
    "sg:postcode":"27713",
    "sg:province":"NC",
    "wof:name":"Shondra's Mamas Hair Design",
    "wof:placetype":"venue"
},
  "geometry": {"coordinates":[-78.913877,35.951076],"type":"Point"}
}