{
  "type": "Feature",
  "properties": {
    "addr:full":"6105 Hilco Dr Fayetteville NC 28314",
    "addr:housenumber":"6105",
    "addr:postcode":"28314",
    "addr:street":"Hilco Dr",
    "iso:country":"US",
    "sg:address":"6105 Hilco Dr",
    "sg:city":"Fayetteville",
    "sg:classifiers":[
        {
            "category":"Shopping",
            "subcategory":"Clothing, Apparel, & Fashions",
            "type":"Retail Goods"
        }
    ],
    "sg:phone":"+1 910 867 6631",
    "sg:postcode":"28314",
    "sg:province":"NC",
    "wof:name":"Cole Tailoring",
    "wof:placetype":"venue"
},
  "geometry": {"coordinates":[-78.98849199999999,35.047987],"type":"Point"}
}