{
  "type": "Feature",
  "properties": {
    "iso:country":"US",
    "sg:address":"205 Shawn Rd",
    "sg:city":"Mount Holly",
    "sg:classifiers":[
        {
            "category":"Food & Beverages",
            "subcategory":"Groceries & Convenience Stores",
            "type":"Retail Goods"
        }
    ],
    "sg:phone":"+1 704 263 1728",
    "sg:postcode":"28120",
    "sg:province":"NC",
    "wof:name":"Somebodys Discount Foods",
    "wof:placetype":"venue"
},
  "geometry": {"coordinates":[-81.08130300000001,35.324889],"type":"Point"}
}