{
  "type": "Feature",
  "properties": {
    "addr:full":"372 Crompton St Charlotte NC 28273",
    "addr:housenumber":"372",
    "addr:postcode":"28273",
    "addr:street":"Crompton St",
    "iso:country":"US",
    "sg:address":"372 Crompton St",
    "sg:city":"Charlotte",
    "sg:classifiers":[
        {
            "category":"Organizations",
            "subcategory":"Membership Organization",
            "type":"Services"
        }
    ],
    "sg:phone":"+1   ",
    "sg:postcode":"28273",
    "sg:province":"NC",
    "wof:name":"Aci Carolinas Chaptr",
    "wof:placetype":"venue"
},
  "geometry": {"coordinates":[-80.914866,35.116705],"type":"Point"}
}