{
  "type": "Feature",
  "properties": {
    "iso:country":"US",
    "sg:address":"1829 Woolie Rd",
    "sg:city":"Lincolnton",
    "sg:classifiers":[
        {
            "category":"Retail",
            "subcategory":"Repair Shop",
            "type":"Services"
        }
    ],
    "sg:phone":"+1   ",
    "sg:postcode":"28092",
    "sg:province":"NC",
    "wof:name":"Connor Piano",
    "wof:placetype":"venue"
},
  "geometry": {"coordinates":[-81.198306,35.501706],"type":"Point"}
}