{
  "type": "Feature",
  "properties": {
    "iso:country":"US",
    "sg:address":"1300 N College Dr",
    "sg:city":"High Point",
    "sg:classifiers":[
        {
            "category":"Organizations",
            "subcategory":"Religious Organization",
            "type":"Services"
        }
    ],
    "sg:phone":"+1 336 889 4777",
    "sg:postcode":"27262",
    "sg:province":"NC",
    "wof:name":"Christ United Methodist Church",
    "wof:placetype":"venue"
},
  "geometry": {"coordinates":[-79.99704199999999,35.981449],"type":"Point"}
}