{
  "type": "Feature",
  "properties": {
    "addr:full":"508 Smith Cir Elizabethtown NC 28337",
    "addr:housenumber":"508",
    "addr:postcode":"28337",
    "addr:street":"Smith Cir",
    "iso:country":"US",
    "sg:address":"508 Smith Cir",
    "sg:city":"Elizabethtown",
    "sg:classifiers":[
        {
            "category":"Professional",
            "type":"Services"
        }
    ],
    "sg:phone":"+1 910 862 3859",
    "sg:postcode":"28337",
    "sg:province":"NC",
    "sg:tags":[
        "establishment"
    ],
    "wof:name":"Beatty Roderick",
    "wof:placetype":"venue"
},
  "geometry": {"coordinates":[-78.60539799999999,34.615585],"type":"Point"}
}