{
  "type": "Feature",
  "properties": {
    "addr:full":"12209 Kane Alexander Dr Huntersville NC 28078",
    "addr:housenumber":"12209",
    "addr:postcode":"28078",
    "addr:street":"Kane Alexander Dr",
    "iso:country":"US",
    "sg:address":"12209 Kane Alexander Dr",
    "sg:city":"Huntersville",
    "sg:classifiers":[
        {
            "category":"Insurance",
            "subcategory":"Insurance Agent",
            "type":"Services"
        }
    ],
    "sg:phone":"+1 704 947 9564",
    "sg:postcode":"28078",
    "sg:province":"NC",
    "sg:tags":[
        "accident"
    ],
    "wof:name":"Affordable Health Care Solutio",
    "wof:placetype":"venue"
},
  "geometry": {"coordinates":[-80.830399,35.425752],"type":"Point"}
}