{
  "type": "Feature",
  "properties": {
    "addr:full":"3516 University Dr Durham NC 27707",
    "addr:housenumber":"3516",
    "addr:postcode":"27707",
    "addr:street":"University Dr",
    "iso:country":"US",
    "sg:address":"3516 University Dr",
    "sg:city":"Durham",
    "sg:classifiers":[
        {
            "category":"Health Services",
            "subcategory":"Medical Lab",
            "type":"Services"
        }
    ],
    "sg:phone":"+1   ",
    "sg:postcode":"27707",
    "sg:province":"NC",
    "sg:tags":[
        "laboratory",
        "dental"
    ],
    "wof:name":"Central Carolina Dental Lab",
    "wof:placetype":"venue"
},
  "geometry": {"coordinates":[-78.948866,35.967193],"type":"Point"}
}