{
  "type": "Feature",
  "properties": {
    "iso:country":"US",
    "sg:address":"190 Ruby Ln",
    "sg:city":"Littleton",
    "sg:classifiers":[
        {
            "category":"Freight",
            "type":"Transportation"
        }
    ],
    "sg:phone":"+1 252 586 0855",
    "sg:postcode":"27850",
    "sg:province":"NC",
    "sg:tags":[
        "operator",
        "trucking"
    ],
    "wof:name":"Kevin Irby Trucking",
    "wof:placetype":"venue"
},
  "geometry": {"coordinates":[-77.97898499999999,36.542336],"type":"Point"}
}