{
  "type": "Feature",
  "properties": {
    "addr:full":"201 E Morgan St Brevard SC 28712",
    "addr:housenumber":"201",
    "addr:postcode":"28712",
    "addr:street":"E Morgan St",
    "iso:country":"US",
    "sg:address":"201 E Morgan St",
    "sg:city":"Brevard",
    "sg:classifiers":[
        {
            "category":"Government",
            "subcategory":"Police Station",
            "type":"Public Place"
        }
    ],
    "sg:phone":"+1 828 884 4232",
    "sg:postcode":"28712",
    "sg:province":"SC",
    "sg:tags":[
        "state"
    ],
    "wof:name":"Highway Patrol",
    "wof:placetype":"venue"
},
  "geometry": {"coordinates":[-82.735292,35.232234],"type":"Point"}
}