{
  "type": "Feature",
  "properties": {
    "iso:country":"US",
    "sg:address":"105 Hines Dr",
    "sg:city":"Winston Salem",
    "sg:classifiers":[
        {
            "category":"Restaurant",
            "type":"Food & Drink"
        }
    ],
    "sg:phone":"+1 336 794 2033",
    "sg:postcode":"27107",
    "sg:province":"NC",
    "sg:website":"www.panerabread.com",
    "wof:name":"Panera Bread",
    "wof:placetype":"venue"
},
  "geometry": {"coordinates":[-80.170269,36.073608],"type":"Point"}
}