{
  "type": "Feature",
  "properties": {
    "iso:country":"US",
    "sg:address":"3302 Yanceyville St",
    "sg:city":"Greensboro",
    "sg:classifiers":[
        {
            "category":"Banks & Credit Unions",
            "subcategory":"Financial Services",
            "type":"Services"
        }
    ],
    "sg:phone":"+1 336 375 0875",
    "sg:postcode":"27405",
    "sg:province":"NC",
    "sg:tags":[
        "investor"
    ],
    "wof:name":"Two Eaves Investment Prpts",
    "wof:placetype":"venue"
},
  "geometry": {"coordinates":[-79.77347,36.120102],"type":"Point"}
}