{
  "type": "Feature",
  "properties": {
    "addr:full":"4147 Old Lexington Rd Winston Salem NC 27107",
    "addr:housenumber":"4147",
    "addr:postcode":"27107",
    "addr:street":"Old Lexington Rd",
    "iso:country":"US",
    "sg:address":"4147 Old Lexington Rd",
    "sg:city":"Winston Salem",
    "sg:classifiers":[
        {
            "category":"Building & Trades",
            "subcategory":"Construction",
            "type":"Services"
        }
    ],
    "sg:phone":"+1 336 785 2781",
    "sg:postcode":"27107",
    "sg:province":"NC",
    "sg:tags":[
        "house"
    ],
    "wof:name":"Dexperts of Carolina Inc",
    "wof:placetype":"venue"
},
  "geometry": {"coordinates":[-80.2152,36.028202],"type":"Point"}
}