{
  "type": "Feature",
  "properties": {
    "addr:full":"4200 Bob Perry Rd Kitty Hawk NC 27949",
    "addr:housenumber":"4200",
    "addr:postcode":"27949",
    "addr:street":"Bob Perry Rd",
    "iso:country":"US",
    "sg:address":"4200 Bob Perry Rd",
    "sg:city":"Kitty Hawk",
    "sg:classifiers":[
        {
            "category":"Home & Garden",
            "subcategory":"Garden Supply",
            "type":"Retail Goods"
        }
    ],
    "sg:phone":"+1 252 261 4488",
    "sg:postcode":"27949",
    "sg:province":"NC",
    "sg:tags":[
        "landscaping",
        "equipment"
    ],
    "sg:website":"www.werocktheouterbanks.com",
    "wof:name":"Earth Resources Inc",
    "wof:placetype":"venue"
},
  "geometry": {"coordinates":[-75.720844,36.05448],"type":"Point"}
}