{
  "type": "Feature",
  "properties": {
    "iso:country":"US",
    "sg:address":"3100 Stoneybrook Dr",
    "sg:city":"Raleigh",
    "sg:classifiers":[
        {
            "category":"Retail",
            "subcategory":"Auto Repair",
            "type":"Services"
        }
    ],
    "sg:phone":"+1 919 872 3658",
    "sg:postcode":"27604",
    "sg:province":"NC",
    "sg:tags":[
        "shop",
        "automotive",
        "customizing"
    ],
    "wof:name":"Earps Upholstery",
    "wof:placetype":"venue"
},
  "geometry": {"coordinates":[-78.59222200000001,35.817347],"type":"Point"}
}