{
  "type": "Feature",
  "properties": {
    "addr:full":"301 S Flint St Lincolnton NC 28092",
    "addr:housenumber":"301",
    "addr:postcode":"28092",
    "addr:street":"S Flint St",
    "iso:country":"US",
    "sg:address":"301 S Flint St",
    "sg:city":"Lincolnton",
    "sg:classifiers":[
        {
            "category":"Utilities",
            "subcategory":"Mobile Phone",
            "type":"Services"
        }
    ],
    "sg:phone":"+1 704 736 1770",
    "sg:postcode":"28092",
    "sg:province":"NC",
    "sg:tags":[
        "telephone",
        "cellular"
    ],
    "wof:name":"Alltel",
    "wof:placetype":"venue"
},
  "geometry": {"coordinates":[-81.247423,35.472902],"type":"Point"}
}