{
  "type": "Feature",
  "properties": {
    "addr:full":"610 Boone Rd Eden NC 27288",
    "addr:housenumber":"610",
    "addr:postcode":"27288",
    "addr:street":"Boone Rd",
    "iso:country":"US",
    "sg:address":"610 Boone Rd",
    "sg:city":"Eden",
    "sg:classifiers":[
        {
            "category":"Retail",
            "subcategory":"Auto Repair",
            "type":"Services"
        }
    ],
    "sg:phone":"+1 336 623 3113",
    "sg:postcode":"27288",
    "sg:province":"NC",
    "sg:tags":[
        "body",
        "automobile",
        "painting"
    ],
    "wof:name":"Gearhart's Paint & Body Shop",
    "wof:placetype":"venue"
},
  "geometry": {"coordinates":[-79.76214,36.493507],"type":"Point"}
}