{
  "type": "Feature",
  "properties": {
    "addr:full":"3522 James B White Hwy S Whiteville NC 28472",
    "addr:housenumber":"3522",
    "addr:postcode":"28472",
    "addr:street":"James B White Hwy S",
    "iso:country":"US",
    "sg:address":"3522 James B White Hwy S",
    "sg:city":"Whiteville",
    "sg:classifiers":[
        {
            "category":"Retail",
            "subcategory":"Veterinary Services",
            "type":"Services"
        }
    ],
    "sg:phone":"+1 910 642 3221",
    "sg:postcode":"28472",
    "sg:province":"NC",
    "wof:name":"Dr John A Stih",
    "wof:placetype":"venue"
},
  "geometry": {"coordinates":[-78.729641,34.294318],"type":"Point"}
}