{
  "type": "Feature",
  "properties": {
    "addr:full":"1519 S York Rd Gastonia NC 28052",
    "addr:housenumber":"1519",
    "addr:postcode":"28052",
    "addr:street":"S York Rd",
    "iso:country":"US",
    "sg:address":"1519 S York Rd",
    "sg:city":"Gastonia",
    "sg:classifiers":[
        {
            "category":"Shopping",
            "subcategory":"Pharmacy",
            "type":"Retail Goods"
        }
    ],
    "sg:phone":"+1 704 867 2161",
    "sg:postcode":"28052",
    "sg:province":"NC",
    "sg:website":"www.kerrdrug.com",
    "wof:name":"KERR Drug",
    "wof:placetype":"venue"
},
  "geometry": {"coordinates":[-81.194031,35.242916],"type":"Point"}
}