{
  "type": "Feature",
  "properties": {
    "iso:country":"US",
    "sg:address":"3100 Tower Blvd",
    "sg:city":"Durham",
    "sg:classifiers":[
        {
            "category":"Banks & Credit Unions",
            "subcategory":"Bank",
            "type":"Services"
        }
    ],
    "sg:phone":"+1 919 419 7448",
    "sg:postcode":"27707",
    "sg:province":"NC",
    "sg:tags":[
        "loan",
        "real estate"
    ],
    "sg:website":"www.verityinvest.com",
    "wof:name":"Verity Lending Svc",
    "wof:placetype":"venue"
},
  "geometry": {"coordinates":[-78.957925,35.972798],"type":"Point"}
}