{
  "type": "Feature",
  "properties": {
    "iso:country":"US",
    "sg:address":"815 E 3rd St",
    "sg:city":"Ayden",
    "sg:classifiers":[
        {
            "category":"Organizations",
            "subcategory":"Religious Organization",
            "type":"Services"
        }
    ],
    "sg:phone":"+1 252 746 6255",
    "sg:postcode":"28513",
    "sg:province":"NC",
    "wof:name":"Corporation of President of Th",
    "wof:placetype":"venue"
},
  "geometry": {"coordinates":[-77.408191,35.470565],"type":"Point"}
}