{
  "type": "Feature",
  "properties": {
    "addr:full":"221 Main St Ahoskie NC 27910",
    "addr:housenumber":"221",
    "addr:postcode":"27910",
    "addr:street":"Main St",
    "iso:country":"US",
    "sg:address":"221 Main St",
    "sg:city":"Ahoskie",
    "sg:classifiers":[
        {
            "category":"Retail",
            "subcategory":"Auto Repair",
            "type":"Services"
        }
    ],
    "sg:phone":"+1 252 332 3918",
    "sg:postcode":"27910",
    "sg:province":"NC",
    "sg:tags":[
        "repairing",
        "radiator",
        "automobile",
        "air",
        "glass",
        "s",
        "conditioning",
        "automotive"
    ],
    "wof:name":"Ahoskie Radiator & Glass Inc",
    "wof:placetype":"venue"
},
  "geometry": {"coordinates":[-76.98441800000001,36.284809],"type":"Point"}
}