{
  "type": "Feature",
  "properties": {
    "addr:full":"186 Pine Ridge Dr Carthage NC 28327",
    "addr:housenumber":"186",
    "addr:postcode":"28327",
    "addr:street":"Pine Ridge Dr",
    "iso:country":"US",
    "sg:address":"186 Pine Ridge Dr",
    "sg:city":"Carthage",
    "sg:classifiers":[
        {
            "category":"Professional",
            "subcategory":"Management & Consulting",
            "type":"Services"
        }
    ],
    "sg:phone":"+1   ",
    "sg:postcode":"28327",
    "sg:province":"NC",
    "sg:tags":[
        "business"
    ],
    "wof:name":"Aviation Consulting Service",
    "wof:placetype":"venue"
},
  "geometry": {"coordinates":[-79.387162,35.252746],"type":"Point"}
}