{
  "type": "Feature",
  "properties": {
    "iso:country":"US",
    "sg:address":"505 Owen Dr",
    "sg:city":"Fayetteville",
    "sg:classifiers":[
        {
            "category":"Social Services",
            "type":"Services"
        }
    ],
    "sg:phone":"+1 910 484 2639",
    "sg:postcode":"28304",
    "sg:province":"NC",
    "sg:tags":[
        "youth",
        "organization",
        "center"
    ],
    "wof:name":"Boys' & Girls' Club",
    "wof:placetype":"venue"
},
  "geometry": {"coordinates":[-78.93259,35.036305],"type":"Point"}
}