{
  "type": "Feature",
  "properties": {
    "addr:full":"27 Griffin Branch Rd Leicester NC 28748",
    "addr:housenumber":"27",
    "addr:postcode":"28748",
    "addr:street":"Griffin Branch Rd",
    "iso:country":"US",
    "sg:address":"27 Griffin Branch Rd",
    "sg:city":"Leicester",
    "sg:classifiers":[
        {
            "category":"Building & Trades",
            "subcategory":"Landscaping Services",
            "type":"Services"
        }
    ],
    "sg:phone":"+1 828 683 6622",
    "sg:postcode":"28748",
    "sg:province":"NC",
    "sg:tags":[
        "landscape"
    ],
    "wof:name":"Sunset Ridge Landscapes Inc",
    "wof:placetype":"venue"
},
  "geometry": {"coordinates":[-82.668043,35.688767],"type":"Point"}
}