{
  "type": "Feature",
  "properties": {
    "addr:full":"116 Starr Ln Statesville NC 28677",
    "addr:housenumber":"116",
    "addr:postcode":"28677",
    "addr:street":"Starr Ln",
    "iso:country":"US",
    "sg:address":"116 Starr Ln",
    "sg:city":"Statesville",
    "sg:classifiers":[
        {
            "category":"Retail",
            "subcategory":"Repair Shop",
            "type":"Services"
        }
    ],
    "sg:phone":"+1   ",
    "sg:postcode":"28677",
    "sg:province":"NC",
    "wof:name":"Kris Shoemakers Repairs",
    "wof:placetype":"venue"
},
  "geometry": {"coordinates":[-81.011223,35.747359],"type":"Point"}
}