{
  "type": "Feature",
  "properties": {
    "iso:country":"US",
    "sg:address":"626 W Mallard Creek Church Rd",
    "sg:city":"Charlotte",
    "sg:classifiers":[
        {
            "category":"Retail",
            "subcategory":"Veterinary Services",
            "type":"Services"
        }
    ],
    "sg:phone":"+1 704 717 0616",
    "sg:postcode":"28262",
    "sg:province":"NC",
    "sg:tags":[
        "hospital",
        "animal"
    ],
    "sg:website":"www.stoneycreek.vetsuite.com",
    "wof:name":"Stoney Creek Animal Hospital",
    "wof:placetype":"venue"
},
  "geometry": {"coordinates":[-80.737587,35.327963],"type":"Point"}
}