{
  "type": "Feature",
  "properties": {
    "addr:full":"7338 State Rd 27 Vale NC 28168",
    "addr:housenumber":"7338;27",
    "addr:postcode":"28168",
    "addr:street":"State Rd",
    "iso:country":"US",
    "sg:address":"7338 State Rd 27",
    "sg:city":"Vale",
    "sg:classifiers":[
        {
            "category":"Farming",
            "subcategory":"Livestock Farm",
            "type":"Manufacturing & Wholesale Goods"
        }
    ],
    "sg:phone":"+1 704 276 1193",
    "sg:postcode":"28168",
    "sg:province":"NC",
    "sg:tags":[
        "beef",
        "feedlot",
        "cattle"
    ],
    "wof:name":"Jeff Lingerfelt Farm",
    "wof:placetype":"venue"
},
  "geometry": {"coordinates":[-81.473935,35.516395],"type":"Point"}
}