{
  "type": "Feature",
  "properties": {
    "iso:country":"US",
    "sg:address":"4289 Barefoot Rd",
    "sg:city":"Fayetteville",
    "sg:classifiers":[
        {
            "category":"Retail",
            "subcategory":"Auto Repair",
            "type":"Services"
        }
    ],
    "sg:phone":"+1   ",
    "sg:postcode":"28306",
    "sg:province":"NC",
    "sg:tags":[
        "automotive"
    ],
    "wof:name":"Fastlane Racing News",
    "wof:placetype":"venue"
},
  "geometry": {"coordinates":[-79.051506,34.99696],"type":"Point"}
}