{
  "type": "Feature",
  "properties": {
    "addr:full":"381 Bellewood Dr Henderson NC 27536",
    "addr:housenumber":"381",
    "addr:postcode":"27536",
    "addr:street":"Bellewood Dr",
    "iso:country":"US",
    "sg:address":"381 Bellewood Dr",
    "sg:city":"Henderson",
    "sg:classifiers":[
        {
            "category":"Professional",
            "type":"Services"
        }
    ],
    "sg:phone":"+1   ",
    "sg:postcode":"27536",
    "sg:province":"NC",
    "wof:name":"M J W Educational Services",
    "wof:placetype":"venue"
},
  "geometry": {"coordinates":[-78.429625,36.317777],"type":"Point"}
}