{
  "type": "Feature",
  "properties": {
    "addr:full":"13925 Ballantyne Corporate Pl Charlotte NC 28277",
    "addr:housenumber":"13925",
    "addr:postcode":"28277",
    "addr:street":"Ballantyne Corporate Pl",
    "iso:country":"US",
    "sg:address":"13925 Ballantyne Corporate Pl",
    "sg:city":"Charlotte",
    "sg:classifiers":[
        {
            "category":"Insurance",
            "subcategory":"Insurance Agent",
            "type":"Services"
        }
    ],
    "sg:phone":"+1 704 752 7784",
    "sg:postcode":"28277",
    "sg:province":"NC",
    "wof:name":"Gen America Financial",
    "wof:placetype":"venue"
},
  "geometry": {"coordinates":[-80.854859,35.060782],"type":"Point"}
}