{
  "type": "Feature",
  "properties": {
    "iso:country":"US",
    "sg:address":"580 Will Isaacs Rd",
    "sg:city":"Zionville",
    "sg:classifiers":[
        {
            "category":"Building & Trades",
            "subcategory":"Construction",
            "type":"Services"
        }
    ],
    "sg:phone":"+1 828 297 7528",
    "sg:postcode":"28698",
    "sg:province":"NC",
    "sg:tags":[
        "house",
        "general",
        "contractor"
    ],
    "wof:name":"Smith Mike Builders",
    "wof:placetype":"venue"
},
  "geometry": {"coordinates":[-81.743387,36.293775],"type":"Point"}
}