{
  "type": "Feature",
  "properties": {
    "iso:country":"US",
    "sg:address":"4209 Summit Ave",
    "sg:city":"Greensboro",
    "sg:classifiers":[
        {
            "category":"Communications",
            "subcategory":"Film & Video Production",
            "type":"Services"
        }
    ],
    "sg:phone":"+1 336 282 9944",
    "sg:postcode":"27405",
    "sg:province":"NC",
    "sg:tags":[
        "motion"
    ],
    "wof:name":"XYZ Inc",
    "wof:placetype":"venue"
},
  "geometry": {"coordinates":[-79.757149,36.136737],"type":"Point"}
}