{
  "type": "Feature",
  "properties": {
    "addr:full":"3318 Tuckaseegee Rd Charlotte NC 28208",
    "addr:housenumber":"3318",
    "addr:postcode":"28208",
    "addr:street":"Tuckaseegee Rd",
    "iso:country":"US",
    "sg:address":"3318 Tuckaseegee Rd",
    "sg:city":"Charlotte",
    "sg:classifiers":[
        {
            "category":"Place Of Worship",
            "subcategory":"Church",
            "type":"Public Place"
        },
        {
            "category":"Place Of Worship",
            "type":"Public Place"
        }
    ],
    "sg:phone":"+1 704 394 8833",
    "sg:postcode":"28208",
    "sg:province":"NC",
    "sg:tags":[
        "churches-holiness"
    ],
    "wof:name":"New Testament Mission",
    "wof:placetype":"venue"
},
  "geometry": {"coordinates":[-80.88253400000001,35.244071],"type":"Point"}
}