{
  "type": "Feature",
  "properties": {
    "addr:full":"303 Wilkesboro St Mocksville NC 27028",
    "addr:housenumber":"303",
    "addr:postcode":"27028",
    "addr:street":"Wilkesboro St",
    "iso:country":"US",
    "sg:address":"303 Wilkesboro St",
    "sg:city":"Mocksville",
    "sg:classifiers":[
        {
            "category":"Wholesale",
            "subcategory":"Farm Supplies",
            "type":"Manufacturing & Wholesale Goods"
        }
    ],
    "sg:phone":"+1 336 751 5021",
    "sg:postcode":"27028",
    "sg:province":"NC",
    "sg:tags":[
        "feed"
    ],
    "wof:name":"DAVIE Farm Svc Inc",
    "wof:placetype":"venue"
},
  "geometry": {"coordinates":[-80.56679200000001,35.898632],"type":"Point"}
}