{
  "type": "Feature",
  "properties": {
    "addr:full":"77 Biltmore Ave Asheville NC 28801",
    "addr:housenumber":"77",
    "addr:postcode":"28801",
    "addr:street":"Biltmore Ave",
    "iso:country":"US",
    "sg:address":"77 Biltmore Ave",
    "sg:city":"Asheville",
    "sg:classifiers":[
        {
            "category":"Shopping",
            "subcategory":"Florist",
            "type":"Retail Goods"
        }
    ],
    "sg:phone":"+1 828 350 1722",
    "sg:postcode":"28801",
    "sg:province":"NC",
    "wof:name":"Kabloom Of Ashville",
    "wof:placetype":"venue"
},
  "geometry": {"coordinates":[-82.550884,35.591894],"type":"Point"}
}