{
  "type": "Feature",
  "properties": {
    "addr:full":"612 Wade Ave Raleigh NC 27605",
    "addr:housenumber":"612",
    "addr:postcode":"27605",
    "addr:street":"Wade Ave",
    "iso:country":"US",
    "sg:address":"612 Wade Ave",
    "sg:city":"Raleigh",
    "sg:classifiers":[
        {
            "category":"Organizations",
            "subcategory":"Non-profit Organization",
            "type":"Services"
        }
    ],
    "sg:phone":"+1 919 828 8320",
    "sg:postcode":"27605",
    "sg:province":"NC",
    "wof:name":"Interact",
    "wof:placetype":"venue"
},
  "geometry": {"coordinates":[-78.651599,35.796113],"type":"Point"}
}