{
  "type": "Feature",
  "properties": {
    "addr:full":"3105 Audubon Pl NW Wilson NC 27896",
    "addr:housenumber":"3105",
    "addr:postcode":"27896",
    "addr:street":"Audubon Pl Nw",
    "iso:country":"US",
    "sg:address":"3105 Audubon Pl NW",
    "sg:city":"Wilson",
    "sg:classifiers":[
        {
            "category":"Building & Trades",
            "subcategory":"Construction",
            "type":"Services"
        }
    ],
    "sg:phone":"+1 252 478 7022",
    "sg:postcode":"27896",
    "sg:province":"NC",
    "sg:tags":[
        "house"
    ],
    "wof:name":"Hutch Construction Inc",
    "wof:placetype":"venue"
},
  "geometry": {"coordinates":[-77.958471,35.740358],"type":"Point"}
}