{
  "type": "Feature",
  "properties": {
    "iso:country":"US",
    "sg:address":"111 Industrial Ave",
    "sg:city":"Greensboro",
    "sg:classifiers":[
        {
            "category":"Wholesale",
            "subcategory":"Groceries",
            "type":"Manufacturing & Wholesale Goods"
        }
    ],
    "sg:phone":"+1 336 274 1075",
    "sg:postcode":"27406",
    "sg:province":"NC",
    "sg:tags":[
        "baker"
    ],
    "wof:name":"Florida Bakery",
    "wof:placetype":"venue"
},
  "geometry": {"coordinates":[-79.789973,36.029192],"type":"Point"}
}