{
  "type": "Feature",
  "properties": {
    "iso:country":"US",
    "sg:address":"217 State Hwy 49 S",
    "sg:city":"Asheboro",
    "sg:classifiers":[
        {
            "category":"Autos & Motor Vehicles",
            "subcategory":"Automobile Sales",
            "type":"Retail Goods"
        }
    ],
    "sg:phone":"+1 336 629 0499",
    "sg:postcode":"27205",
    "sg:province":"NC",
    "sg:tags":[
        "car",
        "used",
        "dealer"
    ],
    "wof:name":"D G Motor Sports",
    "wof:placetype":"venue"
},
  "geometry": {"coordinates":[-79.83867100000001,35.684646],"type":"Point"}
}