{
  "type": "Feature",
  "properties": {
    "addr:full":"5515 Lazy Creek Ln Summerfield NC 27358",
    "addr:housenumber":"5515",
    "addr:postcode":"27358",
    "addr:street":"Lazy Creek Ln",
    "iso:country":"US",
    "sg:address":"5515 Lazy Creek Ln",
    "sg:city":"Summerfield",
    "sg:classifiers":[
        {
            "category":"Building & Trades",
            "subcategory":"Construction",
            "type":"Services"
        }
    ],
    "sg:phone":"+1 336 643 5159",
    "sg:postcode":"27358",
    "sg:province":"NC",
    "sg:tags":[
        "house"
    ],
    "wof:name":"Alan B Pegram Builders Inc",
    "wof:placetype":"venue"
},
  "geometry": {"coordinates":[-79.91461099999999,36.15551],"type":"Point"}
}