{
  "type": "Feature",
  "properties": {
    "iso:country":"US",
    "sg:address":"9503 Ocean Dr",
    "sg:city":"Emerald Isle",
    "sg:classifiers":[
        {
            "category":"Retail",
            "subcategory":"Repair Shop",
            "type":"Services"
        }
    ],
    "sg:phone":"+1 252 354 7331",
    "sg:postcode":"28594",
    "sg:province":"NC",
    "sg:tags":[
        "equipment",
        "refrigeration",
        "conditioning",
        "air"
    ],
    "wof:name":"Emerald Isle Heating & AC",
    "wof:placetype":"venue"
},
  "geometry": {"coordinates":[-77.071012,34.652299],"type":"Point"}
}