{
  "type": "Feature",
  "properties": {
    "iso:country":"US",
    "sg:address":"3616 Denise Dr",
    "sg:city":"Indian Trail",
    "sg:classifiers":[
        {
            "category":"Health Services",
            "subcategory":"Optometrist",
            "type":"Services"
        }
    ],
    "sg:phone":"+1   ",
    "sg:postcode":"28079",
    "sg:province":"NC",
    "wof:name":"OD Enterprises",
    "wof:placetype":"venue"
},
  "geometry": {"coordinates":[-80.63123400000001,35.080765],"type":"Point"}
}