{
  "type": "Feature",
  "properties": {
    "iso:country":"US",
    "sg:address":"1315 Daugherty Rd",
    "sg:city":"China Grove",
    "sg:classifiers":[
        {
            "category":"Building & Trades",
            "subcategory":"Construction",
            "type":"Services"
        }
    ],
    "sg:phone":"+1 704 363 9869",
    "sg:postcode":"28023",
    "sg:province":"NC",
    "sg:tags":[
        "house",
        "builder",
        "home"
    ],
    "wof:name":"Jim Daugherty Construction Inc",
    "wof:placetype":"venue"
},
  "geometry": {"coordinates":[-80.565575,35.542128],"type":"Point"}
}