{
  "type": "Feature",
  "properties": {
    "iso:country":"US",
    "sg:address":"2222 Statesville Ave",
    "sg:city":"Charlotte",
    "sg:classifiers":[
        {
            "category":"Retail",
            "subcategory":"Self-service Laundry",
            "type":"Services"
        },
        {
            "category":"Retail",
            "subcategory":"Laundry & Dry Cleaning",
            "type":"Services"
        }
    ],
    "sg:phone":"+1 704 377 0144",
    "sg:postcode":"28206",
    "sg:province":"NC",
    "sg:tags":[
        "coin"
    ],
    "wof:name":"Druid Hills Laundry",
    "wof:placetype":"venue"
},
  "geometry": {"coordinates":[-80.835853,35.252033],"type":"Point"}
}