{
  "type": "Feature",
  "properties": {
    "iso:country":"US",
    "sg:address":"2063 S Main St",
    "sg:city":"Mount Airy",
    "sg:classifiers":[
        {
            "category":"Social Services",
            "subcategory":"Child Care",
            "type":"Services"
        },
        {
            "category":"Organizations",
            "subcategory":"Religious Organization",
            "type":"Services"
        }
    ],
    "sg:phone":"+1 336 789 0431",
    "sg:postcode":"27030",
    "sg:province":"NC",
    "sg:tags":[
        "day"
    ],
    "wof:name":"Bannertown Wesleyan Child Care",
    "wof:placetype":"venue"
},
  "geometry": {"coordinates":[-80.585607,36.483626],"type":"Point"}
}