{
  "type": "Feature",
  "properties": {
    "addr:full":"19 Forsythe St Asheville NC 28801",
    "addr:housenumber":"19",
    "addr:postcode":"28801",
    "addr:street":"Forsythe St",
    "iso:country":"US",
    "sg:address":"19 Forsythe St",
    "sg:city":"Asheville",
    "sg:classifiers":[
        {
            "category":"Organizations",
            "subcategory":"Religious Organization",
            "type":"Services"
        }
    ],
    "sg:phone":"+1 828 254 4981",
    "sg:postcode":"28801",
    "sg:province":"NC",
    "sg:tags":[
        "church"
    ],
    "wof:name":"Garden Of Prayer Sanctuary",
    "wof:placetype":"venue"
},
  "geometry": {"coordinates":[-82.559268,35.60637],"type":"Point"}
}