{
  "type": "Feature",
  "properties": {
    "iso:country":"US",
    "sg:address":"6008 Oleander Dr",
    "sg:city":"Wilmington",
    "sg:classifiers":[
        {
            "category":"Home & Garden",
            "subcategory":"Building Materials",
            "type":"Retail Goods"
        }
    ],
    "sg:phone":"+1 910 313 1895",
    "sg:postcode":"28403",
    "sg:province":"NC",
    "wof:name":"Auto Tint Specialist",
    "wof:placetype":"venue"
},
  "geometry": {"coordinates":[-77.83932900000001,34.209649],"type":"Point"}
}