{
  "type": "Feature",
  "properties": {
    "addr:full":"102 N Statesville Rd Huntersville NC 28078",
    "addr:housenumber":"102",
    "addr:postcode":"28078",
    "addr:street":"N Statesville Rd",
    "iso:country":"US",
    "sg:address":"102 N Statesville Rd",
    "sg:city":"Huntersville",
    "sg:classifiers":[
        {
            "category":"Restaurant",
            "type":"Food & Drink"
        }
    ],
    "sg:menulink":"http://www.allmenus.com/nc/huntersville/137402-subway/menu/",
    "sg:phone":"+1 704 948 1551",
    "sg:postcode":"28078",
    "sg:province":"NC",
    "sg:tags":[
        "american",
        "sandwich"
    ],
    "wof:name":"Subway",
    "wof:placetype":"venue"
},
  "geometry": {"coordinates":[-80.853514,35.411371],"type":"Point"}
}