{
  "type": "Feature",
  "properties": {
    "iso:country":"US",
    "sg:address":"4220 E Greensboro Chapel Hill Rd",
    "sg:city":"Graham",
    "sg:classifiers":[
        {
            "category":"Retail",
            "subcategory":"Auto Repair",
            "type":"Services"
        }
    ],
    "sg:phone":"+1 336 376 1792",
    "sg:postcode":"27253",
    "sg:province":"NC",
    "sg:tags":[
        "repairing",
        "automobile"
    ],
    "wof:name":"Tinn Top Auto & Body Shop",
    "wof:placetype":"venue"
},
  "geometry": {"coordinates":[-79.29755299999999,35.905283],"type":"Point"}
}