{
  "type": "Feature",
  "properties": {
    "iso:country":"US",
    "sg:address":"206 Everette St",
    "sg:city":"Rockingham",
    "sg:classifiers":[
        {
            "category":"Restaurant",
            "type":"Food & Drink"
        }
    ],
    "sg:phone":"+1 910 895 4029",
    "sg:postcode":"28379",
    "sg:province":"NC",
    "sg:tags":[
        "eating"
    ],
    "wof:name":"Lazy Bean Coffee House",
    "wof:placetype":"venue"
},
  "geometry": {"coordinates":[-79.77410500000001,34.941094],"type":"Point"}
}