{
  "type": "Feature",
  "properties": {
    "addr:full":"4343 Park Rd Charlotte NC 28209",
    "addr:housenumber":"4343",
    "addr:postcode":"28209",
    "addr:street":"Park Rd",
    "iso:country":"US",
    "sg:address":"4343 Park Rd",
    "sg:city":"Charlotte",
    "sg:classifiers":[
        {
            "category":"Restaurant",
            "type":"Food & Drink"
        }
    ],
    "sg:menulink":"http://www.allmenus.com/nc/charlotte/211657-mcdonalds/menu/",
    "sg:phone":"+1 704 523 9777",
    "sg:postcode":"28209",
    "sg:province":"NC",
    "sg:tags":[
        "burger",
        "american"
    ],
    "wof:name":"McDonald's",
    "wof:placetype":"venue"
},
  "geometry": {"coordinates":[-80.850849,35.172458],"type":"Point"}
}