{
  "type": "Feature",
  "properties": {
    "iso:country":"US",
    "sg:address":"123 Branch St",
    "sg:city":"Lowell",
    "sg:classifiers":[
        {
            "category":"Wholesale",
            "subcategory":"Electrical",
            "type":"Manufacturing & Wholesale Goods"
        }
    ],
    "sg:phone":"+1 704 823 8077",
    "sg:postcode":"28098",
    "sg:province":"NC",
    "sg:tags":[
        "equipment"
    ],
    "wof:name":"County Electric Supply",
    "wof:placetype":"venue"
},
  "geometry": {"coordinates":[-81.101488,35.263457],"type":"Point"}
}