{
  "type": "Feature",
  "properties": {
    "addr:full":"6707 Staley Lake Rd Liberty NC 27298",
    "addr:housenumber":"6707",
    "addr:postcode":"27298",
    "addr:street":"Staley Lake Rd",
    "iso:country":"US",
    "sg:address":"6707 Staley Lake Rd",
    "sg:city":"Liberty",
    "sg:classifiers":[
        {
            "category":"Building & Trades",
            "subcategory":"Plumbing",
            "type":"Services"
        }
    ],
    "sg:phone":"+1 336 685 4441",
    "sg:postcode":"27298",
    "sg:province":"NC",
    "sg:tags":[
        "contractor"
    ],
    "wof:name":"Jones Heating & Cooling",
    "wof:placetype":"venue"
},
  "geometry": {"coordinates":[-79.595817,35.931637],"type":"Point"}
}