{
  "type": "Feature",
  "properties": {
    "addr:full":"594 River Hwy Mooresville NC 28117",
    "addr:housenumber":"594",
    "addr:postcode":"28117",
    "addr:street":"River Hwy",
    "iso:country":"US",
    "sg:address":"594 River Hwy",
    "sg:city":"Mooresville",
    "sg:classifiers":[
        {
            "category":"Health Services",
            "subcategory":"Optometrist",
            "type":"Services"
        }
    ],
    "sg:phone":"+1 704 662 3909",
    "sg:postcode":"28117",
    "sg:province":"NC",
    "wof:name":"H D Boyles OD",
    "wof:placetype":"venue"
},
  "geometry": {"coordinates":[-80.876341,35.595954],"type":"Point"}
}