{
  "type": "Feature",
  "properties": {
    "addr:full":"5949 Cress Rd Concord NC 28025",
    "addr:housenumber":"5949",
    "addr:postcode":"28025",
    "addr:street":"Cress Rd",
    "iso:country":"US",
    "sg:address":"5949 Cress Rd",
    "sg:city":"Concord",
    "sg:classifiers":[
        {
            "category":"Building & Trades",
            "subcategory":"Construction",
            "type":"Services"
        }
    ],
    "sg:phone":"+1 704 436 2644",
    "sg:postcode":"28025",
    "sg:province":"NC",
    "sg:tags":[
        "contractor"
    ],
    "wof:name":"Donnie Ledbetter Construction",
    "wof:placetype":"venue"
},
  "geometry": {"coordinates":[-80.475989,35.438762],"type":"Point"}
}