{
  "type": "Feature",
  "properties": {
    "iso:country":"US",
    "sg:address":"7912 Coral Ridge Dr",
    "sg:city":"Charlotte",
    "sg:classifiers":[
        {
            "category":"Wholesale",
            "subcategory":"Farm Supplies",
            "type":"Manufacturing & Wholesale Goods"
        }
    ],
    "sg:phone":"+1 704 545 2778",
    "sg:postcode":"28227",
    "sg:province":"NC",
    "sg:tags":[
        "equipment",
        "greenhouse"
    ],
    "wof:name":"Church Hearn Enterprises",
    "wof:placetype":"venue"
},
  "geometry": {"coordinates":[-80.611445,35.185284],"type":"Point"}
}