{
  "type": "Feature",
  "properties": {
    "iso:country":"US",
    "sg:address":"300 Old Dairy Rd",
    "sg:city":"Wilmington",
    "sg:classifiers":[
        {
            "category":"Retail",
            "subcategory":"Repair Shop",
            "type":"Services"
        }
    ],
    "sg:phone":"+1 910 799 4545",
    "sg:postcode":"28405",
    "sg:province":"NC",
    "sg:tags":[
        "furniture"
    ],
    "wof:name":"Mastors Touch",
    "wof:placetype":"venue"
},
  "geometry": {"coordinates":[-77.84079,34.262664],"type":"Point"}
}