{
  "type": "Feature",
  "properties": {
    "addr:full":"2521 Dick Smith Rd Kittrell NC 27544",
    "addr:housenumber":"2521",
    "addr:postcode":"27544",
    "addr:street":"Dick Smith Rd",
    "iso:country":"US",
    "sg:address":"2521 Dick Smith Rd",
    "sg:city":"Kittrell",
    "sg:classifiers":[
        {
            "category":"Professional",
            "subcategory":"Computer Services",
            "type":"Services"
        }
    ],
    "sg:phone":"+1 252 492 5405",
    "sg:postcode":"27544",
    "sg:province":"NC",
    "sg:tags":[
        "repair"
    ],
    "wof:name":"Pro Techs On Call",
    "wof:placetype":"venue"
},
  "geometry": {"coordinates":[-78.41458900000001,36.181577],"type":"Point"}
}