{
  "type": "Feature",
  "properties": {
    "addr:full":"1300 Oakview Dr Greenville NC 27858",
    "addr:housenumber":"1300",
    "addr:postcode":"27858",
    "addr:street":"Oakview Dr",
    "iso:country":"US",
    "sg:address":"1300 Oakview Dr",
    "sg:city":"Greenville",
    "sg:phone":"+1 252 756 3803",
    "sg:postcode":"27858",
    "sg:province":"NC",
    "sg:tags":[
        "farm",
        "corn",
        "tobacco",
        "soybean",
        "cotton"
    ],
    "wof:name":"Seldom Rest Farm LLC",
    "wof:placetype":"venue"
},
  "geometry": {"coordinates":[-77.356933,35.585639],"type":"Point"}
}