{
  "type": "Feature",
  "properties": {
    "addr:full":"620 Mary Alexander Pl Charlotte NC 28262",
    "addr:housenumber":"620",
    "addr:postcode":"28262",
    "addr:street":"Mary Alexander Pl",
    "iso:country":"US",
    "sg:address":"620 Mary Alexander Pl",
    "sg:city":"Charlotte",
    "sg:classifiers":[
        {
            "category":"Travel",
            "subcategory":"Travel Agent",
            "type":"Entertainment"
        }
    ],
    "sg:phone":"+1 704 593 1366",
    "sg:postcode":"28262",
    "sg:province":"NC",
    "sg:tags":[
        "operator",
        "tour"
    ],
    "wof:name":"South Tour Farms",
    "wof:placetype":"venue"
},
  "geometry": {"coordinates":[-80.727622,35.316373],"type":"Point"}
}