{
  "type": "Feature",
  "properties": {
    "addr:full":"2005 Eastwood Rd Wilmington NC 28403",
    "addr:housenumber":"2005",
    "addr:postcode":"28403",
    "addr:street":"Eastwood Rd",
    "iso:country":"US",
    "sg:address":"2005 Eastwood Rd",
    "sg:city":"Wilmington",
    "sg:classifiers":[
        {
            "category":"Insurance",
            "subcategory":"Insurance Agent",
            "type":"Services"
        }
    ],
    "sg:phone":"+1 910 509 1300",
    "sg:postcode":"28403",
    "sg:province":"NC",
    "sg:tags":[
        "adjuster"
    ],
    "wof:name":"Atlantic Claims Inc",
    "wof:placetype":"venue"
},
  "geometry": {"coordinates":[-77.819513,34.221903],"type":"Point"}
}