{
  "type": "Feature",
  "properties": {
    "addr:full":"9535 South Blvd Charlotte NC 28273",
    "addr:housenumber":"9535",
    "addr:postcode":"28273",
    "addr:street":"South Blvd",
    "iso:country":"US",
    "sg:address":"9535 South Blvd",
    "sg:city":"Charlotte",
    "sg:classifiers":[
        {
            "category":"Shopping",
            "subcategory":"Shoes",
            "type":"Retail Goods"
        }
    ],
    "sg:phone":"+1 704 554 6606",
    "sg:postcode":"28273",
    "sg:province":"NC",
    "wof:name":"Dsw Shoe Warehouse",
    "wof:placetype":"venue"
},
  "geometry": {"coordinates":[-80.88135200000001,35.1074],"type":"Point"}
}