{
  "type": "Feature",
  "properties": {
    "addr:full":"957 Corbett Town Rd Snow Hill NC 28580",
    "addr:housenumber":"957",
    "addr:postcode":"28580",
    "addr:street":"Corbett Town Rd",
    "iso:country":"US",
    "sg:address":"957 Corbett Town Rd",
    "sg:city":"Snow Hill",
    "sg:phone":"+1 252 747 5532",
    "sg:postcode":"28580",
    "sg:province":"NC",
    "sg:tags":[
        "farm",
        "tobacco"
    ],
    "wof:name":"Allen & Irma Crobett",
    "wof:placetype":"venue"
},
  "geometry": {"coordinates":[-77.736863,35.466079],"type":"Point"}
}