{
  "type": "Feature",
  "properties": {
    "addr:full":"1616 Shipyard Blvd Wilmington NC 28412",
    "addr:housenumber":"1616",
    "addr:postcode":"28412",
    "addr:street":"Shipyard Blvd",
    "iso:country":"US",
    "sg:address":"1616 Shipyard Blvd",
    "sg:city":"Wilmington",
    "sg:classifiers":[
        {
            "category":"Restaurant",
            "type":"Food & Drink"
        }
    ],
    "sg:menulink":"http://www.allmenus.com/nc/wilmington/235105-roly-poly-sandwiches/menu/",
    "sg:phone":"+1 910 796 0045",
    "sg:postcode":"28412",
    "sg:province":"NC",
    "sg:tags":[
        "wrap",
        "american",
        "sandwich"
    ],
    "wof:name":"Roly Poly Sandwiches",
    "wof:placetype":"venue"
},
  "geometry": {"coordinates":[-77.920931,34.193151],"type":"Point"}
}