{
  "type": "Feature",
  "properties": {
    "addr:full":"2235 W Lee St Greensboro NC 27403",
    "addr:housenumber":"2235",
    "addr:postcode":"27403",
    "addr:street":"W Lee St",
    "iso:country":"US",
    "sg:address":"2235 W Lee St",
    "sg:city":"Greensboro",
    "sg:classifiers":[
        {
            "category":"Shopping",
            "subcategory":"Stationery & Office Supplies",
            "type":"Retail Goods"
        },
        {
            "category":"Professional",
            "type":"Services"
        }
    ],
    "sg:phone":"+1 336 854 4501",
    "sg:postcode":"27403",
    "sg:province":"NC",
    "sg:tags":[
        "album",
        "scrapbook"
    ],
    "wof:name":"Take2 Memories",
    "wof:placetype":"venue"
},
  "geometry": {"coordinates":[-79.82725000000001,36.060406],"type":"Point"}
}