{
  "type": "Feature",
  "properties": {
    "iso:country":"US",
    "sg:address":"2008 Matheson Ave",
    "sg:city":"Charlotte",
    "sg:classifiers":[
        {
            "category":"Building & Trades",
            "subcategory":"Landscaping Services",
            "type":"Services"
        }
    ],
    "sg:phone":"+1 704 376 8249",
    "sg:postcode":"28205",
    "sg:province":"NC",
    "sg:tags":[
        "designer",
        "landscape"
    ],
    "wof:name":"Wahler Design Group Inc",
    "wof:placetype":"venue"
},
  "geometry": {"coordinates":[-80.795576,35.23092],"type":"Point"}
}