{
  "type": "Feature",
  "properties": {
    "iso:country":"US",
    "sg:address":"5215 Guess Rd",
    "sg:city":"Durham",
    "sg:classifiers":[
        {
            "category":"Retail",
            "subcategory":"Repair Shop",
            "type":"Services"
        }
    ],
    "sg:phone":"+1 919 687 5181",
    "sg:postcode":"27712",
    "sg:province":"NC",
    "sg:tags":[
        "refrigeration"
    ],
    "wof:name":"Durham Refrigeration",
    "wof:placetype":"venue"
},
  "geometry": {"coordinates":[-78.933819,36.087729],"type":"Point"}
}