{
  "type": "Feature",
  "properties": {
    "addr:full":"401 S South St Mt Airy NC 27030",
    "addr:housenumber":"401",
    "addr:postcode":"27030",
    "addr:street":"S South St",
    "iso:country":"US",
    "sg:address":"401 S South St",
    "sg:city":"Mt Airy",
    "sg:classifiers":[
        {
            "category":"Social Services",
            "subcategory":"Child Care",
            "type":"Services"
        }
    ],
    "sg:phone":"+1 336 719 0500",
    "sg:postcode":"27030",
    "sg:province":"NC",
    "wof:name":"Mayberry Learning Ctr",
    "wof:placetype":"venue"
},
  "geometry": {"coordinates":[-80.61433100000001,36.495678],"type":"Point"}
}