{
  "type": "Feature",
  "properties": {
    "addr:full":"2736 Castle Hayne Rd Wilmington NC 28401",
    "addr:housenumber":"2736",
    "addr:postcode":"28401",
    "addr:street":"Castle Hayne Rd",
    "iso:country":"US",
    "sg:address":"2736 Castle Hayne Rd",
    "sg:city":"Wilmington",
    "sg:classifiers":[
        {
            "category":"Social Services",
            "subcategory":"Child Care",
            "type":"Services"
        }
    ],
    "sg:phone":"+1 910 763 1771",
    "sg:postcode":"28401",
    "sg:province":"NC",
    "sg:tags":[
        "day"
    ],
    "wof:name":"Wrightsboro Baptist Church",
    "wof:placetype":"venue"
},
  "geometry": {"coordinates":[-77.921097,34.2929],"type":"Point"}
}