{
  "type": "Feature",
  "properties": {
    "addr:full":"111 Travelers Ct Wilmington NC 28412",
    "addr:housenumber":"111",
    "addr:postcode":"28412",
    "addr:street":"Travelers Ct",
    "iso:country":"US",
    "sg:address":"111 Travelers Ct",
    "sg:city":"Wilmington",
    "sg:classifiers":[
        {
            "category":"Building & Trades",
            "subcategory":"Construction",
            "type":"Services"
        }
    ],
    "sg:phone":"+1 910 350 2592",
    "sg:postcode":"28412",
    "sg:province":"NC",
    "sg:tags":[
        "house"
    ],
    "wof:name":"Jcw Construction Co LLC",
    "wof:placetype":"venue"
},
  "geometry": {"coordinates":[-77.920551,34.10378],"type":"Point"}
}