{
  "type": "Feature",
  "properties": {
    "addr:full":"5548 Trade St Hope Mills NC 28348",
    "addr:housenumber":"5548",
    "addr:postcode":"28348",
    "addr:street":"Trade St",
    "iso:country":"US",
    "sg:address":"5548 Trade St",
    "sg:city":"Hope Mills",
    "sg:classifiers":[
        {
            "category":"Personal",
            "subcategory":"Beauty Salon",
            "type":"Services"
        }
    ],
    "sg:phone":"+1 910 424 2317",
    "sg:postcode":"28348",
    "sg:province":"NC",
    "wof:name":"Professional Creations",
    "wof:placetype":"venue"
},
  "geometry": {"coordinates":[-78.94695,34.971456],"type":"Point"}
}