{
  "type": "Feature",
  "properties": {
    "iso:country":"US",
    "sg:address":"1000 W Catawba Ave",
    "sg:city":"Mount Holly",
    "sg:classifiers":[
        {
            "category":"Personal",
            "type":"Services"
        }
    ],
    "sg:phone":"+1   ",
    "sg:postcode":"28120",
    "sg:province":"NC",
    "wof:name":"Sandys Tanning and Variety",
    "wof:placetype":"venue"
},
  "geometry": {"coordinates":[-81.03657699999999,35.291933],"type":"Point"}
}