{
  "type": "Feature",
  "properties": {
    "addr:full":"5 Ashton Sq Greensboro NC 27408",
    "addr:housenumber":"5",
    "addr:postcode":"27408",
    "addr:street":"Ashton Sq",
    "iso:country":"US",
    "sg:address":"5 Ashton Sq",
    "sg:city":"Greensboro",
    "sg:classifiers":[
        {
            "category":"Banks & Credit Unions",
            "subcategory":"Financial Services",
            "type":"Services"
        }
    ],
    "sg:phone":"+1 336 288 4948",
    "sg:postcode":"27408",
    "sg:province":"NC",
    "sg:tags":[
        "investment",
        "closed"
    ],
    "wof:name":"Greens Crossing Investment Cor",
    "wof:placetype":"venue"
},
  "geometry": {"coordinates":[-79.79276299999999,36.116157],"type":"Point"}
}