{
  "type": "Feature",
  "properties": {
    "iso:country":"US",
    "sg:address":"1258 12th Street Pl NW",
    "sg:city":"Hickory",
    "sg:classifiers":[
        {
            "category":"Personal",
            "type":"Services"
        }
    ],
    "sg:phone":"+1 828 324 7908",
    "sg:postcode":"28601",
    "sg:province":"NC",
    "sg:tags":[
        "consultant",
        "program",
        "health",
        "fitness"
    ],
    "wof:name":"CMC",
    "wof:placetype":"venue"
},
  "geometry": {"coordinates":[-81.365103,35.748681],"type":"Point"}
}