{
  "type": "Feature",
  "properties": {
    "addr:full":"200 Seneca Rd Greensboro NC 27406",
    "addr:housenumber":"200",
    "addr:postcode":"27406",
    "addr:street":"Seneca Rd",
    "iso:country":"US",
    "sg:address":"200 Seneca Rd",
    "sg:city":"Greensboro",
    "sg:classifiers":[
        {
            "category":"Wholesale",
            "subcategory":"Machinery & Supplies",
            "type":"Manufacturing & Wholesale Goods"
        }
    ],
    "sg:phone":"+1 336 378 0444",
    "sg:postcode":"27406",
    "sg:province":"NC",
    "sg:tags":[
        "hardware",
        "landscaping",
        "equipment"
    ],
    "sg:website":"www.wtsherrill.com",
    "wof:name":"Sherrill Arborist Supply",
    "wof:placetype":"venue"
},
  "geometry": {"coordinates":[-79.78345299999999,36.037667],"type":"Point"}
}