{
  "type": "Feature",
  "properties": {
    "addr:full":"2200 Charlotte Hwy Mooresville NC 28117",
    "addr:housenumber":"2200",
    "addr:postcode":"28117",
    "addr:street":"Charlotte Hwy",
    "iso:country":"US",
    "sg:address":"2200 Charlotte Hwy",
    "sg:city":"Mooresville",
    "sg:classifiers":[
        {
            "category":"Professional",
            "subcategory":"Business Services",
            "type":"Services"
        }
    ],
    "sg:phone":"+1 704 799 8787",
    "sg:postcode":"28117",
    "sg:province":"NC",
    "sg:tags":[
        "sales",
        "estate"
    ],
    "wof:name":"Southern Sisters",
    "wof:placetype":"venue"
},
  "geometry": {"coordinates":[-80.83364899999999,35.613669],"type":"Point"}
}