{
  "type": "Feature",
  "properties": {
    "addr:full":"5291 Capital Blvd Raleigh NC 27616",
    "addr:housenumber":"5291",
    "addr:postcode":"27616",
    "addr:street":"Capital Blvd",
    "iso:country":"US",
    "sg:address":"5291 Capital Blvd",
    "sg:city":"Raleigh",
    "sg:classifiers":[
        {
            "category":"Professional",
            "subcategory":"Computer Services",
            "type":"Services"
        }
    ],
    "sg:phone":"+1 919 878 8717",
    "sg:postcode":"27616",
    "sg:province":"NC",
    "sg:tags":[
        "equipment",
        "consulting",
        "sales"
    ],
    "wof:name":"Cad Futures",
    "wof:placetype":"venue"
},
  "geometry": {"coordinates":[-78.581225,35.856442],"type":"Point"}
}