{
  "type": "Feature",
  "properties": {
    "addr:full":"243 State Hwy 53 W Elizabethtown NC 28337",
    "addr:housenumber":"243",
    "addr:postcode":"28337",
    "addr:street":"State Hwy 53 W",
    "iso:country":"US",
    "sg:address":"243 State Hwy 53 W",
    "sg:city":"Elizabethtown",
    "sg:classifiers":[
        {
            "category":"Manufacturing",
            "subcategory":"Lumber",
            "type":"Manufacturing & Wholesale Goods"
        }
    ],
    "sg:phone":"+1 910 862 2556",
    "sg:postcode":"28337",
    "sg:province":"NC",
    "sg:tags":[
        "planing",
        "mills",
        "sawmill"
    ],
    "wof:name":"Ward Lumber Co",
    "wof:placetype":"venue"
},
  "geometry": {"coordinates":[-78.59451799999999,34.645687],"type":"Point"}
}