{
  "type": "Feature",
  "properties": {
    "addr:full":"1032 S Church St Burlington NC 27215",
    "addr:housenumber":"1032",
    "addr:postcode":"27215",
    "addr:street":"S Church St",
    "iso:country":"US",
    "sg:address":"1032 S Church St",
    "sg:city":"Burlington",
    "sg:classifiers":[
        {
            "category":"Insurance",
            "subcategory":"Insurance Agent",
            "type":"Services"
        }
    ],
    "sg:phone":"+1 336 229 5801",
    "sg:postcode":"27215",
    "sg:province":"NC",
    "wof:name":"Lincoln National Life Ins Co",
    "wof:placetype":"venue"
},
  "geometry": {"coordinates":[-79.447053,36.089738],"type":"Point"}
}