{
  "type": "Feature",
  "properties": {
    "addr:full":"103 Higgins Rd Fletcher NC 28732",
    "addr:housenumber":"103",
    "addr:postcode":"28732",
    "addr:street":"Higgins Rd",
    "iso:country":"US",
    "sg:address":"103 Higgins Rd",
    "sg:city":"Fletcher",
    "sg:classifiers":[
        {
            "category":"Freight",
            "type":"Transportation"
        }
    ],
    "sg:phone":"+1 828 684 8977",
    "sg:postcode":"28732",
    "sg:province":"NC",
    "sg:tags":[
        "logistics",
        "party",
        "third"
    ],
    "wof:name":"Sun Logistics Group Inc",
    "wof:placetype":"venue"
},
  "geometry": {"coordinates":[-82.525704,35.433893],"type":"Point"}
}