{
  "type": "Feature",
  "properties": {
    "addr:full":"533 S Main St King NC 27021",
    "addr:housenumber":"533",
    "addr:postcode":"27021",
    "addr:street":"S Main St",
    "iso:country":"US",
    "sg:address":"533 S Main St",
    "sg:city":"King",
    "sg:classifiers":[
        {
            "category":"Retail",
            "subcategory":"Auto Repair",
            "type":"Services"
        }
    ],
    "sg:phone":"+1   ",
    "sg:postcode":"27021",
    "sg:province":"NC",
    "sg:tags":[
        "automotive"
    ],
    "wof:name":"Braddys Automotive",
    "wof:placetype":"venue"
},
  "geometry": {"coordinates":[-80.361092,36.275524],"type":"Point"}
}