{
  "type": "Feature",
  "properties": {
    "addr:full":"2605 Shiloh Church Rd Winston Salem NC 27105",
    "addr:housenumber":"2605",
    "addr:postcode":"27105",
    "addr:street":"Shiloh Church Rd",
    "iso:country":"US",
    "sg:address":"2605 Shiloh Church Rd",
    "sg:city":"Winston Salem",
    "sg:classifiers":[
        {
            "category":"Building & Trades",
            "subcategory":"Landscaping Services",
            "type":"Services"
        }
    ],
    "sg:phone":"+1 336 744 5146",
    "sg:postcode":"27105",
    "sg:province":"NC",
    "sg:tags":[
        "lawn",
        "maintenance",
        "grounds"
    ],
    "wof:name":"Rush Lawn Svc",
    "wof:placetype":"venue"
},
  "geometry": {"coordinates":[-80.227819,36.213355],"type":"Point"}
}