{
  "type": "Feature",
  "properties": {
    "addr:full":"5201 W Oaks Dr Fuquay Varina NC 27526",
    "addr:housenumber":"5201",
    "addr:postcode":"27526",
    "addr:street":"W Oaks Dr",
    "iso:country":"US",
    "sg:address":"5201 W Oaks Dr",
    "sg:city":"Fuquay Varina",
    "sg:classifiers":[
        {
            "category":"Professional",
            "subcategory":"Management & Consulting",
            "type":"Services"
        }
    ],
    "sg:phone":"+1   ",
    "sg:postcode":"27526",
    "sg:province":"NC",
    "wof:name":"North State Assoc Inc",
    "wof:placetype":"venue"
},
  "geometry": {"coordinates":[-78.74223600000001,35.633372],"type":"Point"}
}