{
  "type": "Feature",
  "properties": {
    "iso:country":"US",
    "sg:address":"511 Hoffman Rd",
    "sg:city":"Lincolnton",
    "sg:classifiers":[
        {
            "category":"Manufacturing",
            "subcategory":"Paper Products",
            "type":"Manufacturing & Wholesale Goods"
        }
    ],
    "sg:phone":"+1 704 735 0464",
    "sg:postcode":"28092",
    "sg:province":"NC",
    "sg:tags":[
        "packaging",
        "container"
    ],
    "wof:name":"Sonoco Products Co",
    "wof:placetype":"venue"
},
  "geometry": {"coordinates":[-81.224628,35.409447],"type":"Point"}
}