{
  "type": "Feature",
  "properties": {
    "iso:country":"US",
    "sg:address":"2475 Springs Rd NE",
    "sg:city":"Hickory",
    "sg:classifiers":[
        {
            "category":"Personal",
            "subcategory":"Beauty Salon",
            "type":"Services"
        }
    ],
    "sg:phone":"+1   ",
    "sg:postcode":"28601",
    "sg:province":"NC",
    "sg:tags":[
        "shop"
    ],
    "wof:name":"Corte Latino",
    "wof:placetype":"venue"
},
  "geometry": {"coordinates":[-81.28719700000001,35.75164],"type":"Point"}
}