{
  "type": "Feature",
  "properties": {
    "addr:full":"5224 Hollyridge Dr Raleigh NC 27612",
    "addr:housenumber":"5224",
    "addr:postcode":"27612",
    "addr:street":"Hollyridge Dr",
    "iso:country":"US",
    "sg:address":"5224 Hollyridge Dr",
    "sg:city":"Raleigh",
    "sg:classifiers":[
        {
            "category":"Insurance",
            "subcategory":"Insurance Agent",
            "type":"Services"
        }
    ],
    "sg:phone":"+1 919 787 1330",
    "sg:postcode":"27612",
    "sg:province":"NC",
    "wof:name":"Simpson Insurance Agency Inc",
    "wof:placetype":"venue"
},
  "geometry": {"coordinates":[-78.70079,35.854042],"type":"Point"}
}