{
  "type": "Feature",
  "properties": {
    "addr:full":"1708 Musselwhite Rd Wingate NC 28174",
    "addr:housenumber":"1708",
    "addr:postcode":"28174",
    "addr:street":"Musselwhite Rd",
    "iso:country":"US",
    "sg:address":"1708 Musselwhite Rd",
    "sg:city":"Wingate",
    "sg:classifiers":[
        {
            "category":"Building & Trades",
            "subcategory":"Construction",
            "type":"Services"
        }
    ],
    "sg:phone":"+1 704 289 4249",
    "sg:postcode":"28174",
    "sg:province":"NC",
    "sg:tags":[
        "residential"
    ],
    "wof:name":"GC&g",
    "wof:placetype":"venue"
},
  "geometry": {"coordinates":[-80.462937,34.929611],"type":"Point"}
}