{
  "type": "Feature",
  "properties": {
    "addr:full":"273 Vogler Rd Advance NC 27006",
    "addr:housenumber":"273",
    "addr:postcode":"27006",
    "addr:street":"Vogler Rd",
    "iso:country":"US",
    "sg:address":"273 Vogler Rd",
    "sg:city":"Advance",
    "sg:classifiers":[
        {
            "category":"Manufacturing",
            "subcategory":"Tools & Machinery",
            "type":"Manufacturing & Wholesale Goods"
        }
    ],
    "sg:phone":"+1 336 998 5751",
    "sg:postcode":"27006",
    "sg:province":"NC",
    "sg:tags":[
        "engine",
        "internal",
        "combustion",
        "mfg"
    ],
    "wof:name":"Marine Repair",
    "wof:placetype":"venue"
},
  "geometry": {"coordinates":[-80.395991,35.959623],"type":"Point"}
}