{
  "type": "Feature",
  "properties": {
    "iso:country":"US",
    "sg:address":"118 S Walnut St",
    "sg:city":"Granite Quarry",
    "sg:classifiers":[
        {
            "category":"Education",
            "subcategory":"School",
            "type":"Public Place"
        }
    ],
    "sg:phone":"+1 704 279 2154",
    "sg:postcode":"28081",
    "sg:province":"NC",
    "wof:name":"Granite Quarry Elementary Schl",
    "wof:placetype":"venue"
},
  "geometry": {"coordinates":[-80.63077800000001,35.50098],"type":"Point"}
}