{
  "type": "Feature",
  "properties": {
    "addr:full":"4602 Woodcreek Dr Nashville NC 27856",
    "addr:housenumber":"4602",
    "addr:postcode":"27856",
    "addr:street":"Woodcreek Dr",
    "iso:country":"US",
    "sg:address":"4602 Woodcreek Dr",
    "sg:city":"Nashville",
    "sg:classifiers":[
        {
            "category":"Building & Trades",
            "subcategory":"Construction",
            "type":"Services"
        }
    ],
    "sg:phone":"+1 252 451 4328",
    "sg:postcode":"27856",
    "sg:province":"NC",
    "sg:tags":[
        "system",
        "specialty",
        "heating",
        "contractor",
        "air conditioning"
    ],
    "wof:name":"Pinnacle Heating & Air",
    "wof:placetype":"venue"
},
  "geometry": {"coordinates":[-77.918357,35.893029],"type":"Point"}
}