{
  "type": "Feature",
  "properties": {
    "addr:full":"1501 Hooks Rd Fremont NC 27830",
    "addr:housenumber":"1501",
    "addr:postcode":"27830",
    "addr:street":"Hooks Rd",
    "iso:country":"US",
    "sg:address":"1501 Hooks Rd",
    "sg:city":"Fremont",
    "sg:classifiers":[
        {
            "category":"Farming",
            "subcategory":"Poultry Farm",
            "type":"Manufacturing & Wholesale Goods"
        }
    ],
    "sg:phone":"+1 919 242 5598",
    "sg:postcode":"27830",
    "sg:province":"NC",
    "sg:tags":[
        "hatchery",
        "corn",
        "tobacco"
    ],
    "wof:name":"Hooks Farm",
    "wof:placetype":"venue"
},
  "geometry": {"coordinates":[-77.99822,35.564524],"type":"Point"}
}