{
  "type": "Feature",
  "properties": {
    "iso:country":"US",
    "sg:address":"1306 E 11th St",
    "sg:city":"Lumberton",
    "sg:classifiers":[
        {
            "category":"Professional",
            "type":"Services"
        }
    ],
    "sg:phone":"+1 910 738 8906",
    "sg:postcode":"28358",
    "sg:province":"NC",
    "wof:name":"Allen Townsend",
    "wof:placetype":"venue"
},
  "geometry": {"coordinates":[-78.991237,34.624186],"type":"Point"}
}