{
  "type": "Feature",
  "properties": {
    "iso:country":"US",
    "sg:address":"168 Rocky Branch Ln",
    "sg:city":"Hayesville",
    "sg:classifiers":[
        {
            "category":"Retail",
            "subcategory":"Auto Repair",
            "type":"Services"
        }
    ],
    "sg:phone":"+1 828 389 3424",
    "sg:postcode":"28904",
    "sg:province":"NC",
    "sg:tags":[
        "body",
        "re",
        "automobile",
        "glass",
        "automotive",
        "painting",
        "replacement"
    ],
    "wof:name":"Lowes Body Shop Inc",
    "wof:placetype":"venue"
},
  "geometry": {"coordinates":[-83.852158,35.020764],"type":"Point"}
}