{
  "type": "Feature",
  "properties": {
    "addr:full":"328 Griffin Rd Snow Camp NC 27349",
    "addr:housenumber":"328",
    "addr:postcode":"27349",
    "addr:street":"Griffin Rd",
    "iso:country":"US",
    "sg:address":"328 Griffin Rd",
    "sg:city":"Snow Camp",
    "sg:classifiers":[
        {
            "category":"Insurance",
            "subcategory":"Insurance Agent",
            "type":"Services"
        }
    ],
    "sg:phone":"+1 336 376 0099",
    "sg:postcode":"27349",
    "sg:province":"NC",
    "wof:name":"Aaron Zachary & Assoc",
    "wof:placetype":"venue"
},
  "geometry": {"coordinates":[-79.42090899999999,35.889589],"type":"Point"}
}