{
  "type": "Feature",
  "properties": {
    "iso:country":"US",
    "sg:address":"23 Central St",
    "sg:city":"Sylva",
    "sg:classifiers":[
        {
            "category":"Organizations",
            "subcategory":"Non-profit Organization",
            "type":"Services"
        }
    ],
    "sg:phone":"+1 828 631 9254",
    "sg:postcode":"28779",
    "sg:province":"NC",
    "sg:tags":[
        "social"
    ],
    "wof:name":"Jackson Cnty Council On Aging",
    "wof:placetype":"venue"
},
  "geometry": {"coordinates":[-83.224345,35.375831],"type":"Point"}
}