{
  "type": "Feature",
  "properties": {
    "iso:country":"US",
    "sg:address":"8914 Steele Creek Rd",
    "sg:city":"Charlotte",
    "sg:classifiers":[
        {
            "category":"Government",
            "subcategory":"Office",
            "type":"Public Place"
        }
    ],
    "sg:phone":"+1 704 583 9061",
    "sg:postcode":"28273",
    "sg:province":"NC",
    "sg:tags":[
        "transportation"
    ],
    "wof:name":"Steele Creek Field House",
    "wof:placetype":"venue"
},
  "geometry": {"coordinates":[-80.965968,35.166542],"type":"Point"}
}