{
  "type": "Feature",
  "properties": {
    "addr:full":"11395 Old US Hwy 52 Winston Salem NC 27107",
    "addr:housenumber":"11395",
    "addr:postcode":"27107",
    "addr:street":"Old Us Hwy 52",
    "iso:country":"US",
    "sg:address":"11395 Old US Hwy 52",
    "sg:city":"Winston Salem",
    "sg:classifiers":[
        {
            "category":"Professional",
            "subcategory":"Business Services",
            "type":"Services"
        }
    ],
    "sg:phone":"+1   ",
    "sg:postcode":"27107",
    "sg:province":"NC",
    "wof:name":"Coastal Development Group LLC",
    "wof:placetype":"venue"
},
  "geometry": {"coordinates":[-80.224371,35.972806],"type":"Point"}
}