{
  "type": "Feature",
  "properties": {
    "addr:full":"129 Gary Ln Mt Airy NC 27030",
    "addr:housenumber":"129",
    "addr:postcode":"27030",
    "addr:street":"Gary Ln",
    "iso:country":"US",
    "sg:address":"129 Gary Ln",
    "sg:city":"Mt Airy",
    "sg:classifiers":[
        {
            "category":"Autos & Motor Vehicles",
            "subcategory":"Automobile Sales",
            "type":"Retail Goods"
        }
    ],
    "sg:phone":"+1 336 789 2224",
    "sg:postcode":"27030",
    "sg:province":"NC",
    "sg:tags":[
        "car",
        "dealer"
    ],
    "wof:name":"Gary's Auto Sales",
    "wof:placetype":"venue"
},
  "geometry": {"coordinates":[-80.698364,36.539533],"type":"Point"}
}