{
  "type": "Feature",
  "properties": {
    "addr:full":"2101 Frissell Ave Apex NC 27502",
    "addr:housenumber":"2101",
    "addr:postcode":"27502",
    "addr:street":"Frissell Ave",
    "iso:country":"US",
    "sg:address":"2101 Frissell Ave",
    "sg:city":"Apex",
    "sg:classifiers":[
        {
            "category":"Manufacturing",
            "subcategory":"Retail Goods",
            "type":"Manufacturing & Wholesale Goods"
        },
        {
            "category":"Wholesale",
            "subcategory":"Durable Goods & Equipment",
            "type":"Manufacturing & Wholesale Goods"
        }
    ],
    "sg:phone":"+1 919 303 1630",
    "sg:postcode":"27502",
    "sg:province":"NC",
    "sg:tags":[
        "product",
        "mfg",
        "representative",
        "manufacturer"
    ],
    "wof:name":"Legson Sales Associates",
    "wof:placetype":"venue"
},
  "geometry": {"coordinates":[-78.89744,35.718722],"type":"Point"}
}