{
  "type": "Feature",
  "properties": {
    "addr:full":"1924 Old Pageland Monroe Rd Monroe NC 28112",
    "addr:housenumber":"1924",
    "addr:postcode":"28112",
    "addr:street":"Old Pageland Monroe Rd",
    "iso:country":"US",
    "sg:address":"1924 Old Pageland Monroe Rd",
    "sg:city":"Monroe",
    "sg:classifiers":[
        {
            "category":"Organizations",
            "subcategory":"Religious Organization",
            "type":"Services"
        }
    ],
    "sg:phone":"+1   ",
    "sg:postcode":"28112",
    "sg:province":"NC",
    "wof:name":"Solid Rock Baptist Church",
    "wof:placetype":"venue"
},
  "geometry": {"coordinates":[-80.47622699999999,34.934402],"type":"Point"}
}