{
  "type": "Feature",
  "properties": {
    "iso:country":"US",
    "sg:address":"203 Harrison Ave",
    "sg:city":"Henderson",
    "sg:classifiers":[
        {
            "category":"Retail",
            "subcategory":"Auto Repair",
            "type":"Services"
        }
    ],
    "sg:phone":"+1   ",
    "sg:postcode":"27536",
    "sg:province":"NC",
    "sg:tags":[
        "glass",
        "replacement"
    ],
    "wof:name":"Magic Touch Windshield Repair",
    "wof:placetype":"venue"
},
  "geometry": {"coordinates":[-78.397617,36.324707],"type":"Point"}
}