{
  "type": "Feature",
  "properties": {
    "iso:country":"US",
    "sg:address":"415 7th Ave SW",
    "sg:city":"Hickory",
    "sg:classifiers":[
        {
            "category":"Professional",
            "subcategory":"Computer Services",
            "type":"Services"
        }
    ],
    "sg:phone":"+1 828 324 1900",
    "sg:postcode":"28602",
    "sg:province":"NC",
    "wof:name":"Valpak Of Catawba Valley",
    "wof:placetype":"venue"
},
  "geometry": {"coordinates":[-81.346563,35.723614],"type":"Point"}
}