{
  "type": "Feature",
  "properties": {
    "addr:full":"6840 Melody Ln Charlotte NC 28215",
    "addr:housenumber":"6840",
    "addr:postcode":"28215",
    "addr:street":"Melody Ln",
    "iso:country":"US",
    "sg:address":"6840 Melody Ln",
    "sg:city":"Charlotte",
    "sg:classifiers":[
        {
            "category":"Wholesale",
            "subcategory":"Machinery & Supplies",
            "type":"Manufacturing & Wholesale Goods"
        }
    ],
    "sg:phone":"+1 704 201 5071",
    "sg:postcode":"28215",
    "sg:province":"NC",
    "sg:tags":[
        "equipment",
        "hydraulic"
    ],
    "wof:name":"Eastside Hydraulics",
    "wof:placetype":"venue"
},
  "geometry": {"coordinates":[-80.714186,35.236191],"type":"Point"}
}