{
  "type": "Feature",
  "properties": {
    "iso:country":"US",
    "sg:address":"604 Edgehill Rd",
    "sg:city":"New Bern",
    "sg:classifiers":[
        {
            "category":"Real Estate",
            "subcategory":"Real Estate Agent",
            "type":"Services"
        }
    ],
    "sg:phone":"+1 252 636 2979",
    "sg:postcode":"28562",
    "sg:province":"NC",
    "wof:name":"Gnik Inc",
    "wof:placetype":"venue"
},
  "geometry": {"coordinates":[-77.10661899999999,35.083729],"type":"Point"}
}