{
  "type": "Feature",
  "properties": {
    "addr:full":"2830 Montclair Rd Winston Salem NC 27106",
    "addr:housenumber":"2830",
    "addr:postcode":"27106",
    "addr:street":"Montclair Rd",
    "iso:country":"US",
    "sg:address":"2830 Montclair Rd",
    "sg:city":"Winston Salem",
    "sg:classifiers":[
        {
            "category":"Wholesale",
            "subcategory":"Furniture",
            "type":"Manufacturing & Wholesale Goods"
        }
    ],
    "sg:phone":"+1 336 723 7637",
    "sg:postcode":"27106",
    "sg:province":"NC",
    "sg:tags":[
        "table",
        "rep",
        "top"
    ],
    "wof:name":"Five Star Associates Inc",
    "wof:placetype":"venue"
},
  "geometry": {"coordinates":[-80.26842600000001,36.125392],"type":"Point"}
}