{
  "type": "Feature",
  "properties": {
    "addr:full":"6429 Butler Nursery Rd Fayetteville NC 28306",
    "addr:housenumber":"6429",
    "addr:postcode":"28306",
    "addr:street":"Butler Nursery Rd",
    "iso:country":"US",
    "sg:address":"6429 Butler Nursery Rd",
    "sg:city":"Fayetteville",
    "sg:classifiers":[
        {
            "category":"Manufacturing",
            "subcategory":"Wood Products",
            "type":"Manufacturing & Wholesale Goods"
        }
    ],
    "sg:phone":"+1 910 485 6838",
    "sg:postcode":"28306",
    "sg:province":"NC",
    "sg:tags":[
        "woodworking"
    ],
    "wof:name":"Bynum Woodworking",
    "wof:placetype":"venue"
},
  "geometry": {"coordinates":[-78.827217,34.896888],"type":"Point"}
}