{
  "type": "Feature",
  "properties": {
    "iso:country":"US",
    "sg:address":"3122 Garden Rd",
    "sg:city":"Burlington",
    "sg:classifiers":[
        {
            "category":"Restaurant",
            "type":"Food & Drink"
        }
    ],
    "sg:phone":"+1 336 586 0457",
    "sg:postcode":"27215",
    "sg:province":"NC",
    "wof:name":"Daigaku",
    "wof:placetype":"venue"
},
  "geometry": {"coordinates":[-79.49952500000001,36.069023],"type":"Point"}
}