{
  "type": "Feature",
  "properties": {
    "addr:full":"309 Dale Dr Jacksonville NC 28540",
    "addr:housenumber":"309",
    "addr:postcode":"28540",
    "addr:street":"Dale Dr",
    "iso:country":"US",
    "sg:address":"309 Dale Dr",
    "sg:city":"Jacksonville",
    "sg:classifiers":[
        {
            "category":"Retail",
            "subcategory":"Portrait Studio",
            "type":"Services"
        }
    ],
    "sg:phone":"+1 910 938 9690",
    "sg:postcode":"28540",
    "sg:province":"NC",
    "sg:tags":[
        "photographer"
    ],
    "wof:name":"Libra Arts Photography & Video",
    "wof:placetype":"venue"
},
  "geometry": {"coordinates":[-77.458338,34.803427],"type":"Point"}
}