{
  "type": "Feature",
  "properties": {
    "iso:country":"US",
    "sg:address":"3455 US Hwy 117 N",
    "sg:city":"Goldsboro",
    "sg:classifiers":[
        {
            "category":"Freight",
            "type":"Transportation"
        }
    ],
    "sg:phone":"+1 919 735 8889",
    "sg:postcode":"27530",
    "sg:province":"NC",
    "sg:tags":[
        "commercial",
        "storage"
    ],
    "wof:name":"AJL Ministorage",
    "wof:placetype":"venue"
},
  "geometry": {"coordinates":[-77.97781999999999,35.45213],"type":"Point"}
}