{
  "type": "Feature",
  "properties": {
    "addr:full":"426 Church St N Concord NC 28025",
    "addr:housenumber":"426",
    "addr:postcode":"28025",
    "addr:street":"Church St N",
    "iso:country":"US",
    "sg:address":"426 Church St N",
    "sg:city":"Concord",
    "sg:classifiers":[
        {
            "category":"Professional",
            "subcategory":"Business Services",
            "type":"Services"
        }
    ],
    "sg:phone":"+1 704 792 1659",
    "sg:postcode":"28025",
    "sg:province":"NC",
    "sg:tags":[
        "real estate"
    ],
    "wof:name":"Medlin Real Estate",
    "wof:placetype":"venue"
},
  "geometry": {"coordinates":[-80.59128,35.422156],"type":"Point"}
}