{
  "type": "Feature",
  "properties": {
    "addr:full":"2015 Hephzibah Church Rd Bessemer City NC 28016",
    "addr:housenumber":"2015",
    "addr:postcode":"28016",
    "addr:street":"Hephzibah Church Rd",
    "iso:country":"US",
    "sg:address":"2015 Hephzibah Church Rd",
    "sg:city":"Bessemer City",
    "sg:classifiers":[
        {
            "category":"Manufacturing",
            "subcategory":"Tools & Machinery",
            "type":"Manufacturing & Wholesale Goods"
        }
    ],
    "sg:phone":"+1 704 865 9528",
    "sg:postcode":"28016",
    "sg:province":"NC",
    "sg:tags":[
        "cutting",
        "gear"
    ],
    "wof:name":"Stine Gear & Machine Co",
    "wof:placetype":"venue"
},
  "geometry": {"coordinates":[-81.28649,35.36567],"type":"Point"}
}