{
  "type": "Feature",
  "properties": {
    "iso:country":"US",
    "sg:address":"2902 Asbury Ter",
    "sg:city":"Greensboro",
    "sg:classifiers":[
        {
            "category":"Professional",
            "subcategory":"Business Services",
            "type":"Services"
        }
    ],
    "sg:phone":"+1 336 545 9275",
    "sg:postcode":"27408",
    "sg:province":"NC",
    "sg:tags":[
        "interior",
        "consultant",
        "design",
        "decorator"
    ],
    "wof:name":"V Designs",
    "wof:placetype":"venue"
},
  "geometry": {"coordinates":[-79.807796,36.115435],"type":"Point"}
}