{
  "type": "Feature",
  "properties": {
    "iso:country":"US",
    "sg:address":"1497 Concord Pkwy N",
    "sg:city":"Concord",
    "sg:classifiers":[
        {
            "category":"Restaurant",
            "type":"Food & Drink"
        }
    ],
    "sg:menulink":"http://www.allmenus.com/nc/concord/89615-moes-southwest-grill/menu/",
    "sg:phone":"+1 704 262 7992",
    "sg:postcode":"28025",
    "sg:province":"NC",
    "sg:tags":[
        "mexican"
    ],
    "wof:name":"Moe's Southwest Grill",
    "wof:placetype":"venue"
},
  "geometry": {"coordinates":[-80.606298,35.439324],"type":"Point"}
}