{
  "type": "Feature",
  "properties": {
    "iso:country":"US",
    "sg:address":"5417 Central Ave",
    "sg:city":"Charlotte",
    "sg:classifiers":[
        {
            "category":"Restaurant",
            "type":"Food & Drink"
        }
    ],
    "sg:phone":"+1 704 569 3333",
    "sg:postcode":"28212",
    "sg:province":"NC",
    "wof:name":"Primavera Cafe",
    "wof:placetype":"venue"
},
  "geometry": {"coordinates":[-80.752883,35.207394],"type":"Point"}
}