{
  "type": "Feature",
  "properties": {
    "iso:country":"US",
    "sg:address":"6051 Rockfish Rd",
    "sg:city":"Hope Mills",
    "sg:classifiers":[
        {
            "category":"Retail",
            "subcategory":"Auto Repair",
            "type":"Services"
        }
    ],
    "sg:phone":"+1 910 425 0391",
    "sg:postcode":"28348",
    "sg:province":"NC",
    "sg:tags":[
        "wrecker"
    ],
    "wof:name":"Brocks Towing Inc",
    "wof:placetype":"venue"
},
  "geometry": {"coordinates":[-78.984042,34.977036],"type":"Point"}
}