{
  "type": "Feature",
  "properties": {
    "addr:full":"3330 Tranquil Trl Mebane NC 27302",
    "addr:housenumber":"3330",
    "addr:postcode":"27302",
    "addr:street":"Tranquil Trl",
    "iso:country":"US",
    "sg:address":"3330 Tranquil Trl",
    "sg:city":"Mebane",
    "sg:classifiers":[
        {
            "category":"Real Estate",
            "subcategory":"Real Estate Operator",
            "type":"Services"
        }
    ],
    "sg:phone":"+1 919 563 6518",
    "sg:postcode":"27302",
    "sg:province":"NC",
    "sg:tags":[
        "property",
        "lessor"
    ],
    "wof:name":"Ron Sauers",
    "wof:placetype":"venue"
},
  "geometry": {"coordinates":[-79.253002,36.018607],"type":"Point"}
}