{
  "type": "Feature",
  "properties": {
    "iso:country":"US",
    "sg:address":"3525 New Walkertown Rd NE",
    "sg:city":"Winston Salem",
    "sg:classifiers":[
        {
            "category":"Building & Trades",
            "subcategory":"Construction",
            "type":"Services"
        }
    ],
    "sg:phone":"+1 336 722 4487",
    "sg:postcode":"27105",
    "sg:province":"NC",
    "sg:tags":[
        "renovation",
        "family",
        "contractor"
    ],
    "wof:name":"Patterson Construction Co",
    "wof:placetype":"venue"
},
  "geometry": {"coordinates":[-80.199541,36.132772],"type":"Point"}
}