{
  "type": "Feature",
  "properties": {
    "iso:country":"US",
    "sg:address":"2801 N Main St",
    "sg:city":"High Point",
    "sg:classifiers":[
        {
            "category":"Restaurant",
            "type":"Food & Drink"
        }
    ],
    "sg:phone":"+1 336 886 1048",
    "sg:postcode":"27265",
    "sg:province":"NC",
    "sg:tags":[
        "eating"
    ],
    "wof:name":"Club Fusion",
    "wof:placetype":"venue"
},
  "geometry": {"coordinates":[-80.03335800000001,35.996728],"type":"Point"}
}