{
  "type": "Feature",
  "properties": {
    "iso:country":"US",
    "sg:address":"312 W Wilmington St",
    "sg:city":"Burgaw",
    "sg:classifiers":[
        {
            "category":"Personal",
            "subcategory":"Beauty Salon",
            "type":"Services"
        }
    ],
    "sg:phone":"+1   ",
    "sg:postcode":"28425",
    "sg:province":"NC",
    "sg:tags":[
        "shop"
    ],
    "wof:name":"A Nu Look",
    "wof:placetype":"venue"
},
  "geometry": {"coordinates":[-77.930294,34.550446],"type":"Point"}
}