{
  "type": "Feature",
  "properties": {
    "iso:country":"US",
    "sg:address":"113 Brooks St",
    "sg:city":"Wake Forest",
    "sg:classifiers":[
        {
            "category":"Retail",
            "subcategory":"Auto Repair",
            "type":"Services"
        }
    ],
    "sg:phone":"+1 919 554 1215",
    "sg:postcode":"27587",
    "sg:province":"NC",
    "sg:tags":[
        "repairing",
        "tire"
    ],
    "wof:name":"Barney's Tire Svc",
    "wof:placetype":"venue"
},
  "geometry": {"coordinates":[-78.508225,35.978435],"type":"Point"}
}