{
  "type": "Feature",
  "properties": {
    "iso:country":"US",
    "sg:address":"3302 Warwick Dr",
    "sg:city":"Jamestown",
    "sg:classifiers":[
        {
            "category":"Retail",
            "subcategory":"Repair Shop",
            "type":"Services"
        }
    ],
    "sg:phone":"+1 336 454 4826",
    "sg:postcode":"27282",
    "sg:province":"NC",
    "wof:name":"Flying Wheels",
    "wof:placetype":"venue"
},
  "geometry": {"coordinates":[-79.94067099999999,35.97614],"type":"Point"}
}