{
  "type": "Feature",
  "properties": {
    "iso:country":"US",
    "sg:address":"522 Junction St",
    "sg:city":"Mount Airy",
    "sg:classifiers":[
        {
            "category":"Shopping",
            "type":"Retail Goods"
        }
    ],
    "sg:phone":"+1 336 789 6000",
    "sg:postcode":"27030",
    "sg:province":"NC",
    "sg:tags":[
        "merchandise"
    ],
    "wof:name":"Total Communications Systems &",
    "wof:placetype":"venue"
},
  "geometry": {"coordinates":[-80.604298,36.505094],"type":"Point"}
}