{
  "type": "Feature",
  "properties": {
    "addr:full":"1936 E Market St Greensboro NC 27401",
    "addr:housenumber":"1936",
    "addr:postcode":"27401",
    "addr:street":"E Market St",
    "iso:country":"US",
    "sg:address":"1936 E Market St",
    "sg:city":"Greensboro",
    "sg:classifiers":[
        {
            "category":"Professional",
            "subcategory":"Management & Consulting",
            "type":"Services"
        }
    ],
    "sg:phone":"+1 336 370 0705",
    "sg:postcode":"27401",
    "sg:province":"NC",
    "wof:name":"BVD Management",
    "wof:placetype":"venue"
},
  "geometry": {"coordinates":[-79.76722100000001,36.073256],"type":"Point"}
}