{
  "type": "Feature",
  "properties": {
    "addr:full":"4913 Chastain Ave Charlotte NC 28217",
    "addr:housenumber":"4913",
    "addr:postcode":"28217",
    "addr:street":"Chastain Ave",
    "iso:country":"US",
    "sg:address":"4913 Chastain Ave",
    "sg:city":"Charlotte",
    "sg:classifiers":[
        {
            "category":"Professional",
            "subcategory":"Business Services",
            "type":"Services"
        },
        {
            "category":"Government",
            "subcategory":"Post Office",
            "type":"Public Place"
        }
    ],
    "sg:phone":"+1 704 665 8550",
    "sg:postcode":"28217",
    "sg:province":"NC",
    "sg:tags":[
        "delivery",
        "messenger",
        "courier"
    ],
    "wof:name":"Road Runner B M Services",
    "wof:placetype":"venue"
},
  "geometry": {"coordinates":[-80.882312,35.174746],"type":"Point"}
}