{
  "type": "Feature",
  "properties": {
    "iso:country":"US",
    "sg:address":"59 Westall Ave",
    "sg:city":"Asheville",
    "sg:classifiers":[
        {
            "category":"Wholesale",
            "subcategory":"Non-durable Goods",
            "type":"Manufacturing & Wholesale Goods"
        }
    ],
    "sg:phone":"+1 828 258 0029",
    "sg:postcode":"28804",
    "sg:province":"NC",
    "sg:tags":[
        "product",
        "promotion",
        "sales"
    ],
    "wof:name":"Hall Marketing Co",
    "wof:placetype":"venue"
},
  "geometry": {"coordinates":[-82.55085,35.618849],"type":"Point"}
}