{
  "type": "Feature",
  "properties": {
    "iso:country":"US",
    "sg:address":"101 Huntley St",
    "sg:city":"Spindale",
    "sg:classifiers":[
        {
            "category":"Insurance",
            "subcategory":"Hazard Insurance",
            "type":"Services"
        }
    ],
    "sg:phone":"+1 828 286 2384",
    "sg:postcode":"28160",
    "sg:province":"NC",
    "sg:tags":[
        "casualty"
    ],
    "wof:name":"Maxwell B Hamrick Insurance",
    "wof:placetype":"venue"
},
  "geometry": {"coordinates":[-81.93643299999999,35.359967],"type":"Point"}
}