{
  "type": "Feature",
  "properties": {
    "iso:country":"US",
    "sg:address":"8119 Lariat Dr",
    "sg:city":"Summerfield",
    "sg:classifiers":[
        {
            "category":"Building & Trades",
            "subcategory":"Construction",
            "type":"Services"
        }
    ],
    "sg:phone":"+1 336 643 0322",
    "sg:postcode":"27358",
    "sg:province":"NC",
    "sg:tags":[
        "concrete",
        "contractor"
    ],
    "wof:name":"Concrete Impressions",
    "wof:placetype":"venue"
},
  "geometry": {"coordinates":[-79.87332499999999,36.228723],"type":"Point"}
}