{
  "type": "Feature",
  "properties": {
    "addr:full":"4814 Fox Chase Rd Greensboro NC 27410",
    "addr:housenumber":"4814",
    "addr:postcode":"27410",
    "addr:street":"Fox Chase Rd",
    "iso:country":"US",
    "sg:address":"4814 Fox Chase Rd",
    "sg:city":"Greensboro",
    "sg:classifiers":[
        {
            "category":"Building & Trades",
            "subcategory":"Construction",
            "type":"Services"
        }
    ],
    "sg:phone":"+1 336 362 7473",
    "sg:postcode":"27410",
    "sg:province":"NC",
    "sg:tags":[
        "home",
        "builder"
    ],
    "wof:name":"Taylormade Homes Inc",
    "wof:placetype":"venue"
},
  "geometry": {"coordinates":[-79.896777,36.11323],"type":"Point"}
}