{
  "type": "Feature",
  "properties": {
    "addr:full":"800 N Hughes Blvd Elizabeth City NC 27909",
    "addr:housenumber":"800",
    "addr:postcode":"27909",
    "addr:street":"N Hughes Blvd",
    "iso:country":"US",
    "sg:address":"800 N Hughes Blvd",
    "sg:city":"Elizabeth City",
    "sg:classifiers":[
        {
            "category":"Restaurant",
            "type":"Food & Drink"
        }
    ],
    "sg:phone":"+1 252 335 0150",
    "sg:postcode":"27909",
    "sg:province":"NC",
    "sg:tags":[
        "pizza"
    ],
    "wof:name":"Van's Pizza House",
    "wof:placetype":"venue"
},
  "geometry": {"coordinates":[-76.221868,36.311519],"type":"Point"}
}