{
  "type": "Feature",
  "properties": {
    "iso:country":"US",
    "sg:address":"205 Chaney Ave",
    "sg:city":"Jacksonville",
    "sg:classifiers":[
        {
            "category":"Organizations",
            "subcategory":"Religious Organization",
            "type":"Services"
        }
    ],
    "sg:phone":"+1 910 478 9835",
    "sg:postcode":"28540",
    "sg:province":"NC",
    "sg:tags":[
        "church"
    ],
    "wof:name":"Infant Of Prague Catholic Chr",
    "wof:placetype":"venue"
},
  "geometry": {"coordinates":[-77.425802,34.753478],"type":"Point"}
}