{
  "type": "Feature",
  "properties": {
    "addr:full":"2464 Statesville Blvd Salisbury NC 28147",
    "addr:housenumber":"2464",
    "addr:postcode":"28147",
    "addr:street":"Statesville Blvd",
    "iso:country":"US",
    "sg:address":"2464 Statesville Blvd",
    "sg:city":"Salisbury",
    "sg:classifiers":[
        {
            "category":"Personal",
            "subcategory":"Beauty Salon",
            "type":"Services"
        }
    ],
    "sg:phone":"+1 704 639 9901",
    "sg:postcode":"28147",
    "sg:province":"NC",
    "wof:name":"Your Style Salon",
    "wof:placetype":"venue"
},
  "geometry": {"coordinates":[-80.53080199999999,35.698561],"type":"Point"}
}