{
  "type": "Feature",
  "properties": {
    "addr:full":"304 Indian Trail Rd Indian Trail NC 28079",
    "addr:housenumber":"304",
    "addr:postcode":"28079",
    "addr:street":"Indian Trail Rd",
    "iso:country":"US",
    "sg:address":"304 Indian Trail Rd",
    "sg:city":"Indian Trail",
    "sg:classifiers":[
        {
            "category":"Retail",
            "subcategory":"Repair Shop",
            "type":"Services"
        }
    ],
    "sg:phone":"+1   ",
    "sg:postcode":"28079",
    "sg:province":"NC",
    "sg:tags":[
        "welding"
    ],
    "wof:name":"SW White Welding & Pipefitting",
    "wof:placetype":"venue"
},
  "geometry": {"coordinates":[-80.673146,35.073385],"type":"Point"}
}