{
  "type": "Feature",
  "properties": {
    "iso:country":"US",
    "sg:address":"221 Meek Rd",
    "sg:city":"Gastonia",
    "sg:classifiers":[
        {
            "category":"Shopping",
            "type":"Retail Goods"
        }
    ],
    "sg:phone":"+1 704 868 9551",
    "sg:postcode":"28056",
    "sg:province":"NC",
    "sg:tags":[
        "banner"
    ],
    "wof:name":"Carolina Banners",
    "wof:placetype":"venue"
},
  "geometry": {"coordinates":[-81.148526,35.169483],"type":"Point"}
}