{
  "type": "Feature",
  "properties": {
    "iso:country":"US",
    "sg:address":"1027 US Hwy 70 W",
    "sg:city":"Garner",
    "sg:classifiers":[
        {
            "category":"Real Estate",
            "subcategory":"Real Estate Agent",
            "type":"Services"
        }
    ],
    "sg:phone":"+1 919 772 1338",
    "sg:postcode":"27529",
    "sg:province":"NC",
    "wof:name":"Dewey Gamble Real Estate",
    "wof:placetype":"venue"
},
  "geometry": {"coordinates":[-78.63102499999999,35.714842],"type":"Point"}
}