{
  "type": "Feature",
  "properties": {
    "addr:full":"3454 E Broad St Statesville NC 28625",
    "addr:housenumber":"3454",
    "addr:postcode":"28625",
    "addr:street":"E Broad St",
    "iso:country":"US",
    "sg:address":"3454 E Broad St",
    "sg:city":"Statesville",
    "sg:classifiers":[
        {
            "category":"Home & Garden",
            "subcategory":"Carpets & Floor Coverings",
            "type":"Retail Goods"
        }
    ],
    "sg:phone":"+1 704 838 0371",
    "sg:postcode":"28625",
    "sg:province":"NC",
    "sg:tags":[
        "dealer",
        "rug"
    ],
    "sg:website":"www.floorcoveringsinternational.com",
    "wof:name":"Floor Coverings Intl",
    "wof:placetype":"venue"
},
  "geometry": {"coordinates":[-80.853275,35.790266],"type":"Point"}
}