{
  "type": "Feature",
  "properties": {
    "iso:country":"US",
    "sg:address":"620 US Hwy 21",
    "sg:city":"State Road",
    "sg:classifiers":[
        {
            "category":"Personal",
            "subcategory":"Beauty Salon",
            "type":"Services"
        }
    ],
    "sg:phone":"+1 336 874 2901",
    "sg:postcode":"28676",
    "sg:province":"NC",
    "wof:name":"Charme' Beauty Salon",
    "wof:placetype":"venue"
},
  "geometry": {"coordinates":[-80.861681,36.318857],"type":"Point"}
}