{
  "type": "Feature",
  "properties": {
    "iso:country":"US",
    "sg:address":"11388 US Hwy 501",
    "sg:city":"Maxton",
    "sg:classifiers":[
        {
            "category":"Social Services",
            "type":"Services"
        }
    ],
    "sg:phone":"+1   ",
    "sg:postcode":"28364",
    "sg:province":"NC",
    "wof:name":"Southeastern Community Action",
    "wof:placetype":"venue"
},
  "geometry": {"coordinates":[-79.375873,34.653866],"type":"Point"}
}