{
  "type": "Feature",
  "properties": {
    "addr:full":"349 Keystone Dr Summerfield NC 27358",
    "addr:housenumber":"349",
    "addr:postcode":"27358",
    "addr:street":"Keystone Dr",
    "iso:country":"US",
    "sg:address":"349 Keystone Dr",
    "sg:city":"Summerfield",
    "sg:classifiers":[
        {
            "category":"Shopping",
            "subcategory":"Computers & Home Electronics",
            "type":"Retail Goods"
        }
    ],
    "sg:phone":"+1 336 643 8284",
    "sg:postcode":"27358",
    "sg:province":"NC",
    "sg:tags":[
        "repair"
    ],
    "wof:name":"Northwest Camcorder Repair",
    "wof:placetype":"venue"
},
  "geometry": {"coordinates":[-79.896478,36.262668],"type":"Point"}
}