{
  "type": "Feature",
  "properties": {
    "iso:country":"US",
    "sg:address":"120 E Carver St",
    "sg:city":"Durham",
    "sg:classifiers":[
        {
            "category":"Health Services",
            "subcategory":"Hospital",
            "type":"Services"
        }
    ],
    "sg:phone":"+1 919 470 1000",
    "sg:postcode":"27704",
    "sg:province":"NC",
    "wof:name":"Davis Ambulatory Svc Ctr",
    "wof:placetype":"venue"
},
  "geometry": {"coordinates":[-78.898409,36.040294],"type":"Point"}
}