{
  "type": "Feature",
  "properties": {
    "addr:full":"820 Charles Taylor Rd Aulander NC 27805",
    "addr:housenumber":"820",
    "addr:postcode":"27805",
    "addr:street":"Charles Taylor Rd",
    "iso:country":"US",
    "sg:address":"820 Charles Taylor Rd",
    "sg:city":"Aulander",
    "sg:classifiers":[
        {
            "category":"Organizations",
            "subcategory":"Religious Organization",
            "type":"Services"
        }
    ],
    "sg:phone":"+1 252 794 3508",
    "sg:postcode":"27805",
    "sg:province":"NC",
    "sg:tags":[
        "church"
    ],
    "wof:name":"Mt Herman Baptist Church",
    "wof:placetype":"venue"
},
  "geometry": {"coordinates":[-77.035466,36.108693],"type":"Point"}
}