{
  "type": "Feature",
  "properties": {
    "iso:country":"US",
    "sg:address":"9700 Reed Mine Rd",
    "sg:city":"Midland",
    "sg:classifiers":[
        {
            "category":"Retail",
            "subcategory":"Repair Shop",
            "type":"Services"
        }
    ],
    "sg:phone":"+1   ",
    "sg:postcode":"28107",
    "sg:province":"NC",
    "wof:name":"Cabarrus Tool Service",
    "wof:placetype":"venue"
},
  "geometry": {"coordinates":[-80.473872,35.280835],"type":"Point"}
}