{
  "type": "Feature",
  "properties": {
    "addr:full":"615 Eugene Ct Greensboro NC 27401",
    "addr:housenumber":"615",
    "addr:postcode":"27401",
    "addr:street":"Eugene Ct",
    "iso:country":"US",
    "sg:address":"615 Eugene Ct",
    "sg:city":"Greensboro",
    "sg:classifiers":[
        {
            "category":"Retail",
            "subcategory":"Auto Repair",
            "type":"Services"
        }
    ],
    "sg:phone":"+1 336 370 4404",
    "sg:postcode":"27401",
    "sg:province":"NC",
    "sg:tags":[
        "automotive",
        "axle"
    ],
    "wof:name":"Axles & Auto Repair",
    "wof:placetype":"venue"
},
  "geometry": {"coordinates":[-79.79489100000001,36.067079],"type":"Point"}
}