{
  "type": "Feature",
  "properties": {
    "iso:country":"US",
    "sg:address":"18727 Ronceverte Dr",
    "sg:city":"Cornelius",
    "sg:classifiers":[
        {
            "category":"Manufacturing",
            "subcategory":"Metals",
            "type":"Manufacturing & Wholesale Goods"
        }
    ],
    "sg:phone":"+1 704 896 9982",
    "sg:postcode":"28031",
    "sg:province":"NC",
    "sg:tags":[
        "plumbing",
        "fitting",
        "fixture",
        "mfg"
    ],
    "wof:name":"Masco",
    "wof:placetype":"venue"
},
  "geometry": {"coordinates":[-80.86287,35.461516],"type":"Point"}
}