{
  "type": "Feature",
  "properties": {
    "iso:country":"US",
    "sg:address":"4823 N Rocky River Rd",
    "sg:city":"Indian Trail",
    "sg:classifiers":[
        {
            "category":"Manufacturing",
            "subcategory":"Watercraft",
            "type":"Manufacturing & Wholesale Goods"
        }
    ],
    "sg:phone":"+1 704 882 2776",
    "sg:postcode":"28079",
    "sg:province":"NC",
    "wof:name":"Spirit Custom Boats",
    "wof:placetype":"venue"
},
  "geometry": {"coordinates":[-80.58528099999999,35.089652],"type":"Point"}
}