{
  "type": "Feature",
  "properties": {
    "iso:country":"US",
    "sg:address":"7301 Louisburg Rd",
    "sg:city":"Raleigh",
    "sg:classifiers":[
        {
            "category":"Building & Trades",
            "subcategory":"Construction",
            "type":"Services"
        }
    ],
    "sg:phone":"+1 919 524 0045",
    "sg:postcode":"27616",
    "sg:province":"NC",
    "sg:tags":[
        "concrete",
        "contractor"
    ],
    "wof:name":"H & W Contracting Inc",
    "wof:placetype":"venue"
},
  "geometry": {"coordinates":[-78.54143000000001,35.875075],"type":"Point"}
}