{
  "type": "Feature",
  "properties": {
    "addr:full":"407 Tate St Greensboro NC 27403",
    "addr:housenumber":"407",
    "addr:postcode":"27403",
    "addr:street":"Tate St",
    "iso:country":"US",
    "sg:address":"407 Tate St",
    "sg:city":"Greensboro",
    "sg:classifiers":[
        {
            "category":"Restaurant",
            "type":"Food & Drink"
        }
    ],
    "sg:menulink":"http://www.allmenus.com/nc/greensboro/137344-subway/menu/",
    "sg:phone":"+1 336 275 6055",
    "sg:postcode":"27403",
    "sg:province":"NC",
    "sg:tags":[
        "american",
        "sandwich"
    ],
    "wof:name":"Subway",
    "wof:placetype":"venue"
},
  "geometry": {"coordinates":[-79.805532,36.067731],"type":"Point"}
}