{
  "type": "Feature",
  "properties": {
    "addr:full":"20 Battery Park Ave Asheville NC 28801",
    "addr:housenumber":"20",
    "addr:postcode":"28801",
    "addr:street":"Battery Park Ave",
    "iso:country":"US",
    "sg:address":"20 Battery Park Ave",
    "sg:city":"Asheville",
    "sg:classifiers":[
        {
            "category":"Personal",
            "subcategory":"Beauty Salon",
            "type":"Services"
        }
    ],
    "sg:phone":"+1 828 252 3161",
    "sg:postcode":"28801",
    "sg:province":"NC",
    "sg:tags":[
        "shop"
    ],
    "wof:name":"Marie's Beauty Salon",
    "wof:placetype":"venue"
},
  "geometry": {"coordinates":[-82.555791,35.59498],"type":"Point"}
}