{
  "type": "Feature",
  "properties": {
    "iso:country":"US",
    "sg:address":"4708 High Point Rd",
    "sg:city":"Greensboro",
    "sg:classifiers":[
        {
            "category":"Banks & Credit Unions",
            "subcategory":"Bank",
            "type":"Services"
        }
    ],
    "sg:phone":"+1 336 412 4070",
    "sg:postcode":"27407",
    "sg:province":"NC",
    "wof:name":"First-Citizens Bank & Trust Co",
    "wof:placetype":"venue"
},
  "geometry": {"coordinates":[-79.86828800000001,36.030663],"type":"Point"}
}