{
  "type": "Feature",
  "properties": {
    "iso:country":"US",
    "sg:address":"320 Green St",
    "sg:city":"Fayetteville",
    "sg:classifiers":[
        {
            "category":"Banks & Credit Unions",
            "subcategory":"Bank",
            "type":"Services"
        }
    ],
    "sg:phone":"+1 910 483 1131",
    "sg:postcode":"28301",
    "sg:province":"NC",
    "sg:website":"www.onb.com",
    "wof:name":"Omni National Bank",
    "wof:placetype":"venue"
},
  "geometry": {"coordinates":[-78.87699499999999,35.055928],"type":"Point"}
}