{
  "type": "Feature",
  "properties": {
    "addr:full":"1413 Sedan Ave Kannapolis NC 28083",
    "addr:housenumber":"1413",
    "addr:postcode":"28083",
    "addr:street":"Sedan Ave",
    "iso:country":"US",
    "sg:address":"1413 Sedan Ave",
    "sg:city":"Kannapolis",
    "sg:classifiers":[
        {
            "category":"Real Estate",
            "subcategory":"Real Estate Operator",
            "type":"Services"
        }
    ],
    "sg:phone":"+1 704 933 8885",
    "sg:postcode":"28083",
    "sg:province":"NC",
    "sg:tags":[
        "building",
        "apartment",
        "dwelling"
    ],
    "wof:name":"Tcb",
    "wof:placetype":"venue"
},
  "geometry": {"coordinates":[-80.6148,35.479158],"type":"Point"}
}