{
  "type": "Feature",
  "properties": {
    "addr:full":"2980 Cupelo Rd Farmville NC 27828",
    "addr:housenumber":"2980",
    "addr:postcode":"27828",
    "addr:street":"Cupelo Rd",
    "iso:country":"US",
    "sg:address":"2980 Cupelo Rd",
    "sg:city":"Farmville",
    "sg:classifiers":[
        {
            "category":"Building & Trades",
            "subcategory":"Construction",
            "type":"Services"
        }
    ],
    "sg:phone":"+1 252 753 4295",
    "sg:postcode":"27828",
    "sg:province":"NC",
    "sg:tags":[
        "house"
    ],
    "wof:name":"Cales Home Improvement",
    "wof:placetype":"venue"
},
  "geometry": {"coordinates":[-77.667905,35.555022],"type":"Point"}
}