{
  "type": "Feature",
  "properties": {
    "addr:full":"3 Sadisco Rd Clayton NC 27520",
    "addr:housenumber":"3",
    "addr:postcode":"27520",
    "addr:street":"Sadisco Rd",
    "iso:country":"US",
    "sg:address":"3 Sadisco Rd",
    "sg:city":"Clayton",
    "sg:classifiers":[
        {
            "category":"Building & Trades",
            "subcategory":"Construction",
            "type":"Services"
        }
    ],
    "sg:phone":"+1 919 553 0008",
    "sg:postcode":"27520",
    "sg:province":"NC",
    "sg:tags":[
        "contractor"
    ],
    "wof:name":"Trogdon Masonry Inc",
    "wof:placetype":"venue"
},
  "geometry": {"coordinates":[-78.408694,35.592414],"type":"Point"}
}