{
  "type": "Feature",
  "properties": {
    "iso:country":"US",
    "sg:address":"2180 Stedman Cedar Creek Rd",
    "sg:city":"Stedman",
    "sg:classifiers":[
        {
            "category":"Place Of Worship",
            "subcategory":"Church",
            "type":"Public Place"
        },
        {
            "category":"Place Of Worship",
            "type":"Public Place"
        }
    ],
    "sg:phone":"+1 910 303 9921",
    "sg:postcode":"28391",
    "sg:province":"NC",
    "sg:tags":[
        "churches-baptist-general",
        "churches-baptist"
    ],
    "wof:name":"Macedonia Bapt Church Pre-Sch",
    "wof:placetype":"venue"
},
  "geometry": {"coordinates":[-78.709722,34.97461],"type":"Point"}
}