{
  "type": "Feature",
  "properties": {
    "iso:country":"US",
    "sg:address":"1136 Western Blvd",
    "sg:city":"Jacksonville",
    "sg:classifiers":[
        {
            "category":"Shopping",
            "subcategory":"Jewelry",
            "type":"Retail Goods"
        }
    ],
    "sg:phone":"+1 910 455 2994",
    "sg:postcode":"28546",
    "sg:province":"NC",
    "wof:name":"Brynn Marr Jewelers",
    "wof:placetype":"venue"
},
  "geometry": {"coordinates":[-77.39516500000001,34.779886],"type":"Point"}
}