{
  "type": "Feature",
  "properties": {
    "iso:country":"US",
    "sg:address":"1470 Salisbury Rd",
    "sg:city":"Statesville",
    "sg:classifiers":[
        {
            "category":"Wholesale",
            "subcategory":"Machinery & Supplies",
            "type":"Manufacturing & Wholesale Goods"
        }
    ],
    "sg:phone":"+1 704 873 0531",
    "sg:postcode":"28625",
    "sg:province":"NC",
    "sg:tags":[
        "farm",
        "equipment"
    ],
    "wof:name":"Tri State Distributors",
    "wof:placetype":"venue"
},
  "geometry": {"coordinates":[-80.856466,35.770762],"type":"Point"}
}