{
  "type": "Feature",
  "properties": {
    "iso:country":"US",
    "sg:address":"319 Hidden Valley Rd",
    "sg:city":"Wilmington",
    "sg:classifiers":[
        {
            "category":"Building & Trades",
            "subcategory":"Construction",
            "type":"Services"
        }
    ],
    "sg:phone":"+1 910 392 0115",
    "sg:postcode":"28409",
    "sg:province":"NC",
    "sg:tags":[
        "carpentry",
        "contractor"
    ],
    "wof:name":"Randys Interior Trim",
    "wof:placetype":"venue"
},
  "geometry": {"coordinates":[-77.876684,34.148224],"type":"Point"}
}