{
  "type": "Feature",
  "properties": {
    "addr:full":"1707 Tucker St Burlington NC 27215",
    "addr:housenumber":"1707",
    "addr:postcode":"27215",
    "addr:street":"Tucker St",
    "iso:country":"US",
    "sg:address":"1707 Tucker St",
    "sg:city":"Burlington",
    "sg:classifiers":[
        {
            "category":"Retail",
            "subcategory":"Repair Shop",
            "type":"Services"
        }
    ],
    "sg:phone":"+1 336 227 1216",
    "sg:postcode":"27215",
    "sg:province":"NC",
    "sg:tags":[
        "home",
        "entertainment"
    ],
    "wof:name":"Professional Electronics",
    "wof:placetype":"venue"
},
  "geometry": {"coordinates":[-79.444489,36.073672],"type":"Point"}
}