{
  "type": "Feature",
  "properties": {
    "addr:full":"7515 Peters Ln Wilmington NC 28411",
    "addr:housenumber":"7515",
    "addr:postcode":"28411",
    "addr:street":"Peters Ln",
    "iso:country":"US",
    "sg:address":"7515 Peters Ln",
    "sg:city":"Wilmington",
    "sg:classifiers":[
        {
            "category":"Building & Trades",
            "subcategory":"Landscaping Services",
            "type":"Services"
        }
    ],
    "sg:phone":"+1 910 686 6494",
    "sg:postcode":"28411",
    "sg:province":"NC",
    "sg:tags":[
        "lawn",
        "landscape",
        "maintenance",
        "grounds"
    ],
    "wof:name":"Nelson Landscape Services Inc",
    "wof:placetype":"venue"
},
  "geometry": {"coordinates":[-77.816222,34.28375],"type":"Point"}
}