{
  "type": "Feature",
  "properties": {
    "iso:country":"US",
    "sg:address":"2405 Stone Mountain Rd",
    "sg:city":"Vilas",
    "sg:classifiers":[
        {
            "category":"Retail",
            "subcategory":"Animal Services",
            "type":"Services"
        }
    ],
    "sg:phone":"+1 828 297 1389",
    "sg:postcode":"28692",
    "sg:province":"NC",
    "sg:tags":[
        "pet",
        "grooming",
        "washing"
    ],
    "wof:name":"Canine Companions",
    "wof:placetype":"venue"
},
  "geometry": {"coordinates":[-81.87765,36.308733],"type":"Point"}
}