{
  "type": "Feature",
  "properties": {
    "addr:full":"39 Boone Trl North Wilkesboro NC 28659",
    "addr:housenumber":"39",
    "addr:postcode":"28659",
    "addr:street":"Boone Trl",
    "iso:country":"US",
    "sg:address":"39 Boone Trl",
    "sg:city":"North Wilkesboro",
    "sg:classifiers":[
        {
            "category":"Personal",
            "subcategory":"Beauty Salon",
            "type":"Services"
        }
    ],
    "sg:phone":"+1 336 667 5264",
    "sg:postcode":"28659",
    "sg:province":"NC",
    "wof:name":"Lang & Co Salon & Spa",
    "wof:placetype":"venue"
},
  "geometry": {"coordinates":[-81.16288,36.158127],"type":"Point"}
}