{
  "type": "Feature",
  "properties": {
    "addr:full":"250 Middle St New Bern NC 28560",
    "addr:housenumber":"250",
    "addr:postcode":"28560",
    "addr:street":"Middle St",
    "iso:country":"US",
    "sg:address":"250 Middle St",
    "sg:city":"New Bern",
    "sg:classifiers":[
        {
            "category":"Shopping",
            "subcategory":"Gifts & Souvenirs",
            "type":"Retail Goods"
        }
    ],
    "sg:phone":"+1 252 637 7900",
    "sg:postcode":"28560",
    "sg:province":"NC",
    "sg:tags":[
        "shop"
    ],
    "wof:name":"Treasures On The Trent",
    "wof:placetype":"venue"
},
  "geometry": {"coordinates":[-77.039952,35.105903],"type":"Point"}
}