{
  "type": "Feature",
  "properties": {
    "addr:full":"300 W Arlington Blvd Greenville NC 27834",
    "addr:housenumber":"300",
    "addr:postcode":"27834",
    "addr:street":"W Arlington Blvd",
    "iso:country":"US",
    "sg:address":"300 W Arlington Blvd",
    "sg:city":"Greenville",
    "sg:classifiers":[
        {
            "category":"Personal",
            "subcategory":"Beauty Salon",
            "type":"Services"
        }
    ],
    "sg:phone":"+1   ",
    "sg:postcode":"27834",
    "sg:province":"NC",
    "sg:tags":[
        "shop"
    ],
    "wof:name":"Salon 300 West Bty Salon",
    "wof:placetype":"venue"
},
  "geometry": {"coordinates":[-77.382282,35.591953],"type":"Point"}
}