{
  "type": "Feature",
  "properties": {
    "addr:full":"1142 SE Maynard Rd Cary NC 27511",
    "addr:housenumber":"1142",
    "addr:postcode":"27511",
    "addr:street":"Se Maynard Rd",
    "iso:country":"US",
    "sg:address":"1142 SE Maynard Rd",
    "sg:city":"Cary",
    "sg:classifiers":[
        {
            "category":"Government",
            "subcategory":"Police Station",
            "type":"Public Place"
        }
    ],
    "sg:phone":"+1 919 319 1523",
    "sg:postcode":"27511",
    "sg:province":"NC",
    "sg:tags":[
        "state"
    ],
    "wof:name":"Highway Patrol Hdqrs",
    "wof:placetype":"venue"
},
  "geometry": {"coordinates":[-78.76419199999999,35.784338],"type":"Point"}
}