{
  "type": "Feature",
  "properties": {
    "iso:country":"US",
    "sg:address":"109 Mooresville Rd",
    "sg:city":"Salisbury",
    "sg:classifiers":[
        {
            "category":"Personal",
            "subcategory":"Beauty Salon",
            "type":"Services"
        }
    ],
    "sg:phone":"+1   ",
    "sg:postcode":"28144",
    "sg:province":"NC",
    "sg:tags":[
        "shop"
    ],
    "wof:name":"New Image Hair Care",
    "wof:placetype":"venue"
},
  "geometry": {"coordinates":[-80.49112,35.656698],"type":"Point"}
}