{
  "type": "Feature",
  "properties": {
    "addr:full":"5270 Six Forks Rd Raleigh NC 27609",
    "addr:housenumber":"5270",
    "addr:postcode":"27609",
    "addr:street":"Six Forks Rd",
    "iso:country":"US",
    "sg:address":"5270 Six Forks Rd",
    "sg:city":"Raleigh",
    "sg:classifiers":[
        {
            "category":"Health Services",
            "subcategory":"Clinic",
            "type":"Services"
        }
    ],
    "sg:phone":"+1   ",
    "sg:postcode":"27609",
    "sg:province":"NC",
    "wof:name":"Nutritional Health Enhancement",
    "wof:placetype":"venue"
},
  "geometry": {"coordinates":[-78.64267599999999,35.852618],"type":"Point"}
}