{
  "type": "Feature",
  "properties": {
    "iso:country":"US",
    "sg:address":"3152 State Hwy 18 S",
    "sg:city":"Morganton",
    "sg:classifiers":[
        {
            "category":"Home & Garden",
            "subcategory":"Hardware",
            "type":"Retail Goods"
        },
        {
            "category":"Shopping",
            "type":"Retail Goods"
        }
    ],
    "sg:phone":"+1 828 433 7944",
    "sg:postcode":"28655",
    "sg:province":"NC",
    "sg:tags":[
        "merchandise"
    ],
    "wof:name":"M & B General Hardware",
    "wof:placetype":"venue"
},
  "geometry": {"coordinates":[-81.63896200000001,35.707552],"type":"Point"}
}