{
  "type": "Feature",
  "properties": {
    "addr:full":"249 Hunter Ridge Ln Carthage NC 28327",
    "addr:housenumber":"249",
    "addr:postcode":"28327",
    "addr:street":"Hunter Ridge Ln",
    "iso:country":"US",
    "sg:address":"249 Hunter Ridge Ln",
    "sg:city":"Carthage",
    "sg:classifiers":[
        {
            "category":"Manufacturing",
            "subcategory":"Lumber",
            "type":"Manufacturing & Wholesale Goods"
        }
    ],
    "sg:phone":"+1 910 464 2300",
    "sg:postcode":"28327",
    "sg:province":"NC",
    "sg:tags":[
        "logging"
    ],
    "wof:name":"Ashworth Logging",
    "wof:placetype":"venue"
},
  "geometry": {"coordinates":[-79.47382399999999,35.442234],"type":"Point"}
}