{
  "type": "Feature",
  "properties": {
    "addr:full":"4651 Paragon Park Rd Raleigh NC 27616",
    "addr:housenumber":"4651",
    "addr:postcode":"27616",
    "addr:street":"Paragon Park Rd",
    "iso:country":"US",
    "sg:address":"4651 Paragon Park Rd",
    "sg:city":"Raleigh",
    "sg:classifiers":[
        {
            "category":"Professional",
            "subcategory":"Computer Services",
            "type":"Services"
        }
    ],
    "sg:phone":"+1 919 954 8321",
    "sg:postcode":"27616",
    "sg:province":"NC",
    "sg:tags":[
        "communication",
        "installation",
        "system",
        "sales"
    ],
    "wof:name":"SOS",
    "wof:placetype":"venue"
},
  "geometry": {"coordinates":[-78.561391,35.889005],"type":"Point"}
}