{
  "type": "Feature",
  "properties": {
    "addr:full":"1124 Floral Pkwy Wilmington NC 28403",
    "addr:housenumber":"1124",
    "addr:postcode":"28403",
    "addr:street":"Floral Pkwy",
    "iso:country":"US",
    "sg:address":"1124 Floral Pkwy",
    "sg:city":"Wilmington",
    "sg:classifiers":[
        {
            "category":"Personal",
            "subcategory":"Beauty Salon",
            "type":"Services"
        }
    ],
    "sg:phone":"+1 910 452 0072",
    "sg:postcode":"28403",
    "sg:province":"NC",
    "sg:website":"www.salonbeyondbasics.com",
    "wof:name":"Salon Beyond Basics",
    "wof:placetype":"venue"
},
  "geometry": {"coordinates":[-77.89897499999999,34.218543],"type":"Point"}
}