{
  "type": "Feature",
  "properties": {
    "iso:country":"US",
    "sg:address":"1331 S Wesleyan Blvd",
    "sg:city":"Rocky Mount",
    "sg:classifiers":[
        {
            "category":"Wholesale",
            "subcategory":"Auto Parts",
            "type":"Manufacturing & Wholesale Goods"
        }
    ],
    "sg:phone":"+1 252 985 1234",
    "sg:postcode":"27803",
    "sg:province":"NC",
    "sg:tags":[
        "equipment",
        "truck"
    ],
    "sg:website":"www.fleetpride.com",
    "wof:name":"Fleet Pride Inc",
    "wof:placetype":"venue"
},
  "geometry": {"coordinates":[-77.831757,35.917392],"type":"Point"}
}