{
  "type": "Feature",
  "properties": {
    "iso:country":"US",
    "sg:address":"4011 Lake Charles Way",
    "sg:city":"Indian Trail",
    "sg:classifiers":[
        {
            "category":"Professional",
            "subcategory":"Business Services",
            "type":"Services"
        }
    ],
    "sg:phone":"+1   ",
    "sg:postcode":"28079",
    "sg:province":"NC",
    "wof:name":"Morris Brooks Design",
    "wof:placetype":"venue"
},
  "geometry": {"coordinates":[-80.62762600000001,35.086803],"type":"Point"}
}