{
  "type": "Feature",
  "properties": {
    "iso:country":"US",
    "sg:address":"4519 Franklin Ave",
    "sg:city":"Wilmington",
    "sg:classifiers":[
        {
            "category":"Shopping",
            "subcategory":"Computers & Home Electronics",
            "type":"Retail Goods"
        }
    ],
    "sg:phone":"+1 910 350 8086",
    "sg:postcode":"28403",
    "sg:province":"NC",
    "wof:name":"Flux",
    "wof:placetype":"venue"
},
  "geometry": {"coordinates":[-77.886064,34.238912],"type":"Point"}
}