{
  "type": "Feature",
  "properties": {
    "iso:country":"US",
    "sg:address":"4001 Tuckaseegee Rd",
    "sg:city":"Charlotte",
    "sg:classifiers":[
        {
            "category":"Restaurant",
            "type":"Food & Drink"
        }
    ],
    "sg:menulink":"http://www.allmenus.com/nc/charlotte/47024-tung-hoy/menu/",
    "sg:phone":"+1 704 394 9700",
    "sg:postcode":"28208",
    "sg:province":"NC",
    "sg:tags":[
        "asian",
        "chinese"
    ],
    "wof:name":"Tung-Hoy",
    "wof:placetype":"venue"
},
  "geometry": {"coordinates":[-80.89198399999999,35.246322],"type":"Point"}
}