{
  "type": "Feature",
  "properties": {
    "addr:full":"519 S Main St Biscoe NC 27209",
    "addr:housenumber":"519",
    "addr:postcode":"27209",
    "addr:street":"S Main St",
    "iso:country":"US",
    "sg:address":"519 S Main St",
    "sg:city":"Biscoe",
    "sg:classifiers":[
        {
            "category":"Food & Beverages",
            "subcategory":"Groceries & Convenience Stores",
            "type":"Retail Goods"
        }
    ],
    "sg:phone":"+1 910 428 4099",
    "sg:postcode":"27209",
    "sg:province":"NC",
    "wof:name":"Biscoe Mart",
    "wof:placetype":"venue"
},
  "geometry": {"coordinates":[-79.781099,35.352669],"type":"Point"}
}