{
  "type": "Feature",
  "properties": {
    "addr:full":"7009 Weant Rd Archdale NC 27263",
    "addr:housenumber":"7009",
    "addr:postcode":"27263",
    "addr:street":"Weant Rd",
    "iso:country":"US",
    "sg:address":"7009 Weant Rd",
    "sg:city":"Archdale",
    "sg:classifiers":[
        {
            "category":"Organizations",
            "subcategory":"Religious Organization",
            "type":"Services"
        }
    ],
    "sg:phone":"+1 336 431 1336",
    "sg:postcode":"27263",
    "sg:province":"NC",
    "sg:tags":[
        "church"
    ],
    "wof:name":"First Church Of God",
    "wof:placetype":"venue"
},
  "geometry": {"coordinates":[-79.93415299999999,35.915051],"type":"Point"}
}