{
  "type": "Feature",
  "properties": {
    "iso:country":"US",
    "sg:address":"300 Waller Rd",
    "sg:city":"Mount Olive",
    "sg:classifiers":[
        {
            "category":"Wholesale",
            "subcategory":"Farm Supplies",
            "type":"Manufacturing & Wholesale Goods"
        }
    ],
    "sg:phone":"+1 919 658 5074",
    "sg:postcode":"28365",
    "sg:province":"NC",
    "sg:tags":[
        "livestock"
    ],
    "wof:name":"Monsanto",
    "wof:placetype":"venue"
},
  "geometry": {"coordinates":[-78.116175,35.199139],"type":"Point"}
}