{
  "type": "Feature",
  "properties": {
    "addr:full":"306 Estes Drive Ext Carrboro NC 27510",
    "addr:housenumber":"306",
    "addr:postcode":"27510",
    "addr:street":"Estes Drive Ext",
    "iso:country":"US",
    "sg:address":"306 Estes Drive Ext",
    "sg:city":"Carrboro",
    "sg:classifiers":[
        {
            "category":"Real Estate",
            "subcategory":"Real Estate Operator",
            "type":"Services"
        }
    ],
    "sg:phone":"+1 919 967 2234",
    "sg:postcode":"27510",
    "sg:province":"NC",
    "sg:tags":[
        "apartment"
    ],
    "wof:name":"Estes Park Apartments",
    "wof:placetype":"venue"
},
  "geometry": {"coordinates":[-79.072098,35.921101],"type":"Point"}
}