{
  "type": "Feature",
  "properties": {
    "addr:full":"880 State Hwy 32 S Plymouth NC 27962",
    "addr:housenumber":"880",
    "addr:postcode":"27962",
    "addr:street":"State Hwy 32 S",
    "iso:country":"US",
    "sg:address":"880 State Hwy 32 S",
    "sg:city":"Plymouth",
    "sg:classifiers":[
        {
            "category":"Freight",
            "type":"Transportation"
        }
    ],
    "sg:phone":"+1 252 793 4518",
    "sg:postcode":"27962",
    "sg:province":"NC",
    "sg:tags":[
        "general"
    ],
    "wof:name":"Plymouth Storage",
    "wof:placetype":"venue"
},
  "geometry": {"coordinates":[-76.741919,35.845493],"type":"Point"}
}