{
  "type": "Feature",
  "properties": {
    "addr:full":"8055 Pleasant Hill Church Rd Snow Camp NC 27349",
    "addr:housenumber":"8055",
    "addr:postcode":"27349",
    "addr:street":"Pleasant Hill Church Rd",
    "iso:country":"US",
    "sg:address":"8055 Pleasant Hill Church Rd",
    "sg:city":"Snow Camp",
    "sg:classifiers":[
        {
            "category":"Sports & Exercise",
            "subcategory":"Golf",
            "type":"Entertainment"
        }
    ],
    "sg:phone":"+1 336 376 8166",
    "sg:postcode":"27349",
    "sg:province":"NC",
    "sg:tags":[
        "course"
    ],
    "wof:name":"Sourwood Golf Course",
    "wof:placetype":"venue"
},
  "geometry": {"coordinates":[-79.45827800000001,35.885266],"type":"Point"}
}