{
  "type": "Feature",
  "properties": {
    "iso:country":"US",
    "sg:address":"1620 Sound Watch Dr",
    "sg:city":"Wilmington",
    "sg:classifiers":[
        {
            "category":"Farming",
            "subcategory":"Farm",
            "type":"Manufacturing & Wholesale Goods"
        }
    ],
    "sg:phone":"+1 910 791 5201",
    "sg:postcode":"28409",
    "sg:province":"NC",
    "sg:tags":[
        "crop",
        "general"
    ],
    "wof:name":"Robinsons Farm Inc",
    "wof:placetype":"venue"
},
  "geometry": {"coordinates":[-77.877172,34.117397],"type":"Point"}
}