{
  "type": "Feature",
  "properties": {
    "iso:country":"US",
    "sg:address":"3833 Ramsey St",
    "sg:city":"Fayetteville",
    "sg:classifiers":[
        {
            "category":"Cinema",
            "subcategory":"Movie Rental",
            "type":"Entertainment"
        }
    ],
    "sg:phone":"+1 910 482 8585",
    "sg:postcode":"28311",
    "sg:province":"NC",
    "sg:tags":[
        "video",
        "tape"
    ],
    "wof:name":"Blockbuster",
    "wof:placetype":"venue"
},
  "geometry": {"coordinates":[-78.87970799999999,35.113092],"type":"Point"}
}