{
  "type": "Feature",
  "properties": {
    "addr:full":"1374 Argonne Blvd Winston Salem NC 27107",
    "addr:housenumber":"1374",
    "addr:postcode":"27107",
    "addr:street":"Argonne Blvd",
    "iso:country":"US",
    "sg:address":"1374 Argonne Blvd",
    "sg:city":"Winston Salem",
    "sg:classifiers":[
        {
            "category":"Real Estate",
            "subcategory":"Real Estate Operator",
            "type":"Services"
        }
    ],
    "sg:phone":"+1 336 650 0176",
    "sg:postcode":"27107",
    "sg:province":"NC",
    "sg:tags":[
        "property",
        "lessor"
    ],
    "wof:name":"Cole Tamika",
    "wof:placetype":"venue"
},
  "geometry": {"coordinates":[-80.21332700000001,36.079881],"type":"Point"}
}