{
  "type": "Feature",
  "properties": {
    "addr:full":"226 S 5th Ave Kure Beach NC 28449",
    "addr:housenumber":"226",
    "addr:postcode":"28449",
    "addr:street":"S 5Th Ave",
    "iso:country":"US",
    "sg:address":"226 S 5th Ave",
    "sg:city":"Kure Beach",
    "sg:classifiers":[
        {
            "category":"Organizations",
            "subcategory":"Religious Organization",
            "type":"Services"
        }
    ],
    "sg:phone":"+1   ",
    "sg:postcode":"28449",
    "sg:province":"NC",
    "wof:name":"W Eugene Watkins Rev",
    "wof:placetype":"venue"
},
  "geometry": {"coordinates":[-77.909921,33.996411],"type":"Point"}
}