{
  "type": "Feature",
  "properties": {
    "iso:country":"US",
    "sg:address":"1128 Middle Rd",
    "sg:city":"Fayetteville",
    "sg:classifiers":[
        {
            "category":"Building & Trades",
            "subcategory":"Landscaping Services",
            "type":"Services"
        }
    ],
    "sg:phone":"+1 910 483 3236",
    "sg:postcode":"28312",
    "sg:province":"NC",
    "sg:tags":[
        "landscape",
        "contractor"
    ],
    "wof:name":"Snow's Landscaping & Lawncare",
    "wof:placetype":"venue"
},
  "geometry": {"coordinates":[-78.836142,35.073903],"type":"Point"}
}