{
  "type": "Feature",
  "properties": {
    "iso:country":"US",
    "sg:address":"447 Ned Cove Rd",
    "sg:city":"Waynesville",
    "sg:classifiers":[
        {
            "category":"Building & Trades",
            "subcategory":"Construction",
            "type":"Services"
        }
    ],
    "sg:phone":"+1 828 926 1928",
    "sg:postcode":"28785",
    "sg:province":"NC",
    "sg:tags":[
        "concrete",
        "pumping"
    ],
    "wof:name":"Allison's Concrete Pumping",
    "wof:placetype":"venue"
},
  "geometry": {"coordinates":[-83.053219,35.569229],"type":"Point"}
}