{
  "type": "Feature",
  "properties": {
    "addr:full":"1204 Terrell Dr High Point NC 27262",
    "addr:housenumber":"1204",
    "addr:postcode":"27262",
    "addr:street":"Terrell Dr",
    "iso:country":"US",
    "sg:address":"1204 Terrell Dr",
    "sg:city":"High Point",
    "sg:classifiers":[
        {
            "category":"Recreation",
            "type":"Entertainment"
        }
    ],
    "sg:phone":"+1   ",
    "sg:postcode":"27262",
    "sg:province":"NC",
    "wof:name":"Wallys World Entertainment",
    "wof:placetype":"venue"
},
  "geometry": {"coordinates":[-79.992166,35.979276],"type":"Point"}
}