{
  "type": "Feature",
  "properties": {
    "iso:country":"US",
    "sg:address":"557 N Main St",
    "sg:city":"Mooresville",
    "sg:classifiers":[
        {
            "category":"Manufacturing",
            "subcategory":"Motor Vehicles & Parts",
            "type":"Manufacturing & Wholesale Goods"
        }
    ],
    "sg:phone":"+1 704 799 1888",
    "sg:postcode":"28115",
    "sg:province":"NC",
    "sg:tags":[
        "equipment",
        "truck"
    ],
    "wof:name":"Hicks Total Performance",
    "wof:placetype":"venue"
},
  "geometry": {"coordinates":[-80.80530899999999,35.58626],"type":"Point"}
}