{
  "type": "Feature",
  "properties": {
    "addr:full":"403 Carthage St Sanford NC 27330",
    "addr:housenumber":"403",
    "addr:postcode":"27330",
    "addr:street":"Carthage St",
    "iso:country":"US",
    "sg:address":"403 Carthage St",
    "sg:city":"Sanford",
    "sg:classifiers":[
        {
            "category":"Shopping",
            "subcategory":"Gifts & Souvenirs",
            "type":"Retail Goods"
        }
    ],
    "sg:phone":"+1 919 777 9070",
    "sg:postcode":"27330",
    "sg:province":"NC",
    "wof:name":"Tearoom Treasures",
    "wof:placetype":"venue"
},
  "geometry": {"coordinates":[-79.18207,35.479034],"type":"Point"}
}