{
  "type": "Feature",
  "properties": {
    "addr:full":"1701 Matthews Township Pkwy Matthews NC 28105",
    "addr:housenumber":"1701",
    "addr:postcode":"28105",
    "addr:street":"Matthews Township Pkwy",
    "iso:country":"US",
    "sg:address":"1701 Matthews Township Pkwy",
    "sg:city":"Matthews",
    "sg:classifiers":[
        {
            "category":"Restaurant",
            "type":"Food & Drink"
        }
    ],
    "sg:menulink":"http://www.allmenus.com/nc/morning-star/92879-fuddruckers/menu/",
    "sg:phone":"+1 704 849 6360",
    "sg:postcode":"28105",
    "sg:province":"NC",
    "sg:tags":[
        "burger",
        "american"
    ],
    "wof:name":"Fuddruckers",
    "wof:placetype":"venue"
},
  "geometry": {"coordinates":[-80.710453,35.122407],"type":"Point"}
}