{
  "type": "Feature",
  "properties": {
    "iso:country":"US",
    "sg:address":"1403 Audubon Blvd",
    "sg:city":"Wilmington",
    "sg:classifiers":[
        {
            "category":"Health Services",
            "subcategory":"Health Practitioner",
            "type":"Services"
        }
    ],
    "sg:phone":"+1   ",
    "sg:postcode":"28403",
    "sg:province":"NC",
    "wof:name":"Southern Acupuncture",
    "wof:placetype":"venue"
},
  "geometry": {"coordinates":[-77.89726899999999,34.212876],"type":"Point"}
}