{
  "type": "Feature",
  "properties": {
    "addr:full":"109 Covington St Wadesboro NC 28170",
    "addr:housenumber":"109",
    "addr:postcode":"28170",
    "addr:street":"Covington St",
    "iso:country":"US",
    "sg:address":"109 Covington St",
    "sg:city":"Wadesboro",
    "sg:classifiers":[
        {
            "category":"Real Estate",
            "subcategory":"Real Estate Agent",
            "type":"Services"
        }
    ],
    "sg:phone":"+1 704 694 6161",
    "sg:postcode":"28170",
    "sg:province":"NC",
    "wof:name":"Burroughs Realty Corp",
    "wof:placetype":"venue"
},
  "geometry": {"coordinates":[-80.07659700000001,34.962807],"type":"Point"}
}