{
  "type": "Feature",
  "properties": {
    "addr:full":"133 W Mountain St Kings Mountain NC 28086",
    "addr:housenumber":"133",
    "addr:postcode":"28086",
    "addr:street":"W Mountain St",
    "iso:country":"US",
    "sg:address":"133 W Mountain St",
    "sg:city":"Kings Mountain",
    "sg:classifiers":[
        {
            "category":"Manufacturing",
            "subcategory":"Printing",
            "type":"Manufacturing & Wholesale Goods"
        }
    ],
    "sg:phone":"+1 704 739 6356",
    "sg:postcode":"28086",
    "sg:province":"NC",
    "sg:tags":[
        "commercial"
    ],
    "wof:name":"Teds Trophies & Awards",
    "wof:placetype":"venue"
},
  "geometry": {"coordinates":[-81.343468,35.239243],"type":"Point"}
}