{
  "type": "Feature",
  "properties": {
    "addr:full":"1148 Executive Cir Cary NC 27511",
    "addr:housenumber":"1148",
    "addr:postcode":"27511",
    "addr:street":"Executive Cir",
    "iso:country":"US",
    "sg:address":"1148 Executive Cir",
    "sg:city":"Cary",
    "sg:classifiers":[
        {
            "category":"Retail",
            "subcategory":"Portrait Studio",
            "type":"Services"
        }
    ],
    "sg:phone":"+1 919 466 7478",
    "sg:postcode":"27511",
    "sg:province":"NC",
    "sg:tags":[
        "photographer",
        "photo"
    ],
    "wof:name":"Designer Images By Victoria In",
    "wof:placetype":"venue"
},
  "geometry": {"coordinates":[-78.781025,35.766156],"type":"Point"}
}