{
  "type": "Feature",
  "properties": {
    "addr:full":"709 Green St Durham NC 27701",
    "addr:housenumber":"709",
    "addr:postcode":"27701",
    "addr:street":"Green St",
    "iso:country":"US",
    "sg:address":"709 Green St",
    "sg:city":"Durham",
    "sg:classifiers":[
        {
            "category":"Building & Trades",
            "subcategory":"Electrical",
            "type":"Services"
        }
    ],
    "sg:phone":"+1 919 730 1050",
    "sg:postcode":"27701",
    "sg:province":"NC",
    "sg:tags":[
        "electric",
        "contractor"
    ],
    "wof:name":"D Humphrey Electrical Co",
    "wof:placetype":"venue"
},
  "geometry": {"coordinates":[-78.902294,36.010927],"type":"Point"}
}