{
  "type": "Feature",
  "properties": {
    "addr:full":"2803 Slater Rd Ste 215 Morrisville NC 27560",
    "addr:housenumber":"2803",
    "addr:postcode":"27560",
    "addr:street":"Slater Rd Ste 215",
    "iso:country":"US",
    "sg:address":"2803 Slater Rd Ste 215",
    "sg:city":"Morrisville",
    "sg:classifiers":[
        {
            "category":"Insurance",
            "subcategory":"Insurance Agent",
            "type":"Services"
        },
        {
            "category":"Insurance",
            "subcategory":"Hazard Insurance",
            "type":"Services"
        }
    ],
    "sg:phone":"+1 919 463 1655",
    "sg:postcode":"27560",
    "sg:province":"NC",
    "sg:tags":[
        "adjuster"
    ],
    "sg:website":"http://www.csallc.com",
    "wof:name":"Cahaba Safeguard Administrators",
    "wof:placetype":"venue"
},
  "geometry": {"coordinates":[-78.82231899999999,35.86154],"type":"Point"}
}