{
  "type": "Feature",
  "properties": {
    "addr:full":"2998 Hickory Blvd Hudson NC 28638",
    "addr:housenumber":"2998",
    "addr:postcode":"28638",
    "addr:street":"Hickory Blvd",
    "iso:country":"US",
    "sg:address":"2998 Hickory Blvd",
    "sg:city":"Hudson",
    "sg:classifiers":[
        {
            "category":"Shopping",
            "subcategory":"Crafts & Fabrics",
            "type":"Retail Goods"
        }
    ],
    "sg:phone":"+1 828 728 7891",
    "sg:postcode":"28638",
    "sg:province":"NC",
    "sg:tags":[
        "decorative",
        "wholesale",
        "upholstery",
        "draper"
    ],
    "wof:name":"Fleming Decorative Fabrics",
    "wof:placetype":"venue"
},
  "geometry": {"coordinates":[-81.47702200000001,35.848995],"type":"Point"}
}