{
  "type": "Feature",
  "properties": {
    "addr:full":"1208 Gordon St Charlotte NC 28205",
    "addr:housenumber":"1208",
    "addr:postcode":"28205",
    "addr:street":"Gordon St",
    "iso:country":"US",
    "sg:address":"1208 Gordon St",
    "sg:city":"Charlotte",
    "sg:classifiers":[
        {
            "category":"Taxi",
            "type":"Transportation"
        }
    ],
    "sg:phone":"+1 704 371 4444",
    "sg:postcode":"28205",
    "sg:province":"NC",
    "sg:tags":[
        "taxicab"
    ],
    "wof:name":"King Cab",
    "wof:placetype":"venue"
},
  "geometry": {"coordinates":[-80.81345399999999,35.219952],"type":"Point"}
}