{
  "type": "Feature",
  "properties": {
    "iso:country":"US",
    "sg:address":"318 Elkin Creek Mill Rd",
    "sg:city":"Elkin",
    "sg:classifiers":[
        {
            "category":"Manufacturing",
            "subcategory":"Food",
            "type":"Manufacturing & Wholesale Goods"
        }
    ],
    "sg:phone":"+1 336 526 5119",
    "sg:postcode":"28621",
    "sg:province":"NC",
    "sg:tags":[
        "winery"
    ],
    "wof:name":"Elkin Creek Winery",
    "wof:placetype":"venue"
},
  "geometry": {"coordinates":[-80.87533999999999,36.279638],"type":"Point"}
}