{
  "type": "Feature",
  "properties": {
    "addr:full":"1337 Heritage Club Ave Wake Forest NC 27587",
    "addr:housenumber":"1337",
    "addr:postcode":"27587",
    "addr:street":"Heritage Club Ave",
    "iso:country":"US",
    "sg:address":"1337 Heritage Club Ave",
    "sg:city":"Wake Forest",
    "sg:classifiers":[
        {
            "category":"Wholesale",
            "subcategory":"Durable Goods & Equipment",
            "type":"Manufacturing & Wholesale Goods"
        }
    ],
    "sg:phone":"+1 919 453 0295",
    "sg:postcode":"27587",
    "sg:province":"NC",
    "wof:name":"Choice Distributing Inc",
    "wof:placetype":"venue"
},
  "geometry": {"coordinates":[-78.49548900000001,35.954086],"type":"Point"}
}