{
  "type": "Feature",
  "properties": {
    "iso:country":"US",
    "sg:address":"1 Page Ave",
    "sg:city":"Asheville",
    "sg:classifiers":[
        {
            "category":"Restaurant",
            "type":"Food & Drink"
        }
    ],
    "sg:phone":"+1 828 253 2366",
    "sg:postcode":"28801",
    "sg:province":"NC",
    "wof:name":"Ali Baba Middle Eastern Rstrnt",
    "wof:placetype":"venue"
},
  "geometry": {"coordinates":[-82.556399,35.596302],"type":"Point"}
}