{
  "type": "Feature",
  "properties": {
    "addr:full":"108 N Woods Rd Henderson NC 27536",
    "addr:housenumber":"108",
    "addr:postcode":"27536",
    "addr:street":"N Woods Rd",
    "iso:country":"US",
    "sg:address":"108 N Woods Rd",
    "sg:city":"Henderson",
    "sg:classifiers":[
        {
            "category":"Retail",
            "subcategory":"Repair Shop",
            "type":"Services"
        }
    ],
    "sg:phone":"+1   ",
    "sg:postcode":"27536",
    "sg:province":"NC",
    "wof:name":"Hester Willanski",
    "wof:placetype":"venue"
},
  "geometry": {"coordinates":[-78.398965,36.347606],"type":"Point"}
}