{
  "type": "Feature",
  "properties": {
    "iso:country":"US",
    "sg:address":"715 Farris Ave W",
    "sg:city":"High Point",
    "sg:classifiers":[
        {
            "category":"Education",
            "subcategory":"School",
            "type":"Public Place"
        }
    ],
    "sg:phone":"+1 336 819 2905",
    "sg:postcode":"27262",
    "sg:province":"NC",
    "wof:name":"Kirkman Park Elementary School",
    "wof:placetype":"venue"
},
  "geometry": {"coordinates":[-80.023838,35.9694],"type":"Point"}
}