{
  "type": "Feature",
  "properties": {
    "addr:full":"803 N Main St High Point NC 27262",
    "addr:housenumber":"803",
    "addr:postcode":"27262",
    "addr:street":"N Main St",
    "iso:country":"US",
    "sg:address":"803 N Main St",
    "sg:city":"High Point",
    "sg:classifiers":[
        {
            "category":"Personal",
            "type":"Services"
        }
    ],
    "sg:phone":"+1 336 841 4025",
    "sg:postcode":"27262",
    "sg:province":"NC",
    "sg:tags":[
        "electrolysis"
    ],
    "sg:website":"www.advancedelectrolysislaser.com",
    "wof:name":"Advanced Electrolysis & Laser",
    "wof:placetype":"venue"
},
  "geometry": {"coordinates":[-80.01253699999999,35.965572],"type":"Point"}
}