{
  "type": "Feature",
  "properties": {
    "iso:country":"US",
    "sg:address":"200 Laver Dr",
    "sg:city":"Cary",
    "sg:classifiers":[
        {
            "category":"Professional",
            "subcategory":"Computer Services",
            "type":"Services"
        }
    ],
    "sg:phone":"+1   ",
    "sg:postcode":"27511",
    "sg:province":"NC",
    "sg:tags":[
        "programing",
        "custom"
    ],
    "sg:website":"www.objectdomain.com",
    "wof:name":"Object Domain Systems Inc",
    "wof:placetype":"venue"
},
  "geometry": {"coordinates":[-78.78103900000001,35.749551],"type":"Point"}
}