{
  "type": "Feature",
  "properties": {
    "iso:country":"US",
    "sg:address":"1435 Tunnel Rd",
    "sg:city":"Asheville",
    "sg:classifiers":[
        {
            "category":"Travel",
            "subcategory":"Hotels & Motels",
            "type":"Entertainment"
        }
    ],
    "sg:phone":"+1 828 298 4434",
    "sg:postcode":"28805",
    "sg:province":"NC",
    "sg:tags":[
        "operation"
    ],
    "wof:name":"Days Inn",
    "wof:placetype":"venue"
},
  "geometry": {"coordinates":[-82.463156,35.583974],"type":"Point"}
}