{
  "type": "Feature",
  "properties": {
    "iso:country":"US",
    "sg:address":"10865 US Hwy 421",
    "sg:city":"Broadway",
    "sg:classifiers":[
        {
            "category":"Autos & Motor Vehicles",
            "subcategory":"Automobile Sales",
            "type":"Retail Goods"
        }
    ],
    "sg:phone":"+1 919 258 0625",
    "sg:postcode":"27505",
    "sg:province":"NC",
    "sg:tags":[
        "car",
        "dealer"
    ],
    "wof:name":"Lett's Premier Auto Ctr",
    "wof:placetype":"venue"
},
  "geometry": {"coordinates":[-79.003593,35.433048],"type":"Point"}
}