{
  "type": "Feature",
  "properties": {
    "iso:country":"US",
    "sg:address":"712 Cecil St",
    "sg:city":"Durham",
    "sg:classifiers":[
        {
            "category":"Education",
            "subcategory":"School",
            "type":"Public Place"
        }
    ],
    "sg:phone":"+1 919 530 7793",
    "sg:postcode":"27707",
    "sg:province":"NC",
    "sg:website":"www.dpsnc.net",
    "wof:name":"Clement Early College High Sch",
    "wof:placetype":"venue"
},
  "geometry": {"coordinates":[-78.896102,35.971112],"type":"Point"}
}