{
  "type": "Feature",
  "properties": {
    "addr:full":"324 Barrington Park Ln Kernersville NC 27284",
    "addr:housenumber":"324",
    "addr:postcode":"27284",
    "addr:street":"Barrington Park Ln",
    "iso:country":"US",
    "sg:address":"324 Barrington Park Ln",
    "sg:city":"Kernersville",
    "sg:classifiers":[
        {
            "category":"Recreation",
            "type":"Entertainment"
        }
    ],
    "sg:phone":"+1   ",
    "sg:postcode":"27284",
    "sg:province":"NC",
    "wof:name":"American Combat Ju Jitsu Inc",
    "wof:placetype":"venue"
},
  "geometry": {"coordinates":[-80.114852,36.118363],"type":"Point"}
}