{
  "type": "Feature",
  "properties": {
    "iso:country":"US",
    "sg:address":"211 W Stallings St",
    "sg:city":"Clayton",
    "sg:classifiers":[
        {
            "category":"Local Transit",
            "type":"Transportation"
        }
    ],
    "sg:phone":"+1 919 359 0359",
    "sg:postcode":"27520",
    "sg:province":"NC",
    "sg:tags":[
        "limousine"
    ],
    "wof:name":"Triangle Luxury Limousine",
    "wof:placetype":"venue"
},
  "geometry": {"coordinates":[-78.460022,35.655781],"type":"Point"}
}