{
  "type": "Feature",
  "properties": {
    "addr:full":"2110 3rd Street Pl SE Hickory NC 28602",
    "addr:housenumber":"2110",
    "addr:postcode":"28602",
    "addr:street":"3Rd Street Pl Se",
    "iso:country":"US",
    "sg:address":"2110 3rd Street Pl SE",
    "sg:city":"Hickory",
    "sg:classifiers":[
        {
            "category":"Building & Trades",
            "subcategory":"Landscaping Services",
            "type":"Services"
        }
    ],
    "sg:phone":"+1 828 328 6440",
    "sg:postcode":"28602",
    "sg:province":"NC",
    "sg:tags":[
        "tree"
    ],
    "wof:name":"Evans Tree Svc Stump Grinding",
    "wof:placetype":"venue"
},
  "geometry": {"coordinates":[-81.331586,35.701202],"type":"Point"}
}