{
  "type": "Feature",
  "properties": {
    "iso:country":"US",
    "sg:address":"210 W Main St",
    "sg:city":"Carrboro",
    "sg:classifiers":[
        {
            "category":"Shopping",
            "subcategory":"Musical Instruments",
            "type":"Retail Goods"
        }
    ],
    "sg:phone":"+1 919 929 5506",
    "sg:postcode":"27510",
    "sg:province":"NC",
    "wof:name":"Bryan's Guitars & Music",
    "wof:placetype":"venue"
},
  "geometry": {"coordinates":[-79.07520100000001,35.910125],"type":"Point"}
}