{
  "type": "Feature",
  "properties": {
    "iso:country":"US",
    "sg:address":"2000 Flint Glenn Ln",
    "sg:city":"Charlotte",
    "sg:classifiers":[
        {
            "category":"Shopping",
            "subcategory":"Clothing, Apparel, & Fashions",
            "type":"Retail Goods"
        }
    ],
    "sg:phone":"+1 704 547 0092",
    "sg:postcode":"28262",
    "sg:province":"NC",
    "sg:tags":[
        "industrial",
        "glove"
    ],
    "wof:name":"Able Safety & Glove Co",
    "wof:placetype":"venue"
},
  "geometry": {"coordinates":[-80.70232300000001,35.3209],"type":"Point"}
}