{
  "type": "Feature",
  "properties": {
    "iso:country":"US",
    "sg:address":"515 W 15th St",
    "sg:city":"Washington",
    "sg:classifiers":[
        {
            "category":"Health Services",
            "subcategory":"Doctor",
            "type":"Services"
        }
    ],
    "sg:phone":"+1 252 975 3709",
    "sg:postcode":"27889",
    "sg:province":"NC",
    "sg:tags":[
        "dentist",
        "medical"
    ],
    "wof:name":"J H Chesson DDS Inc",
    "wof:placetype":"venue"
},
  "geometry": {"coordinates":[-77.052905,35.558375],"type":"Point"}
}