{
  "type": "Feature",
  "properties": {
    "addr:full":"140 N Main St Belmont NC 28012",
    "addr:housenumber":"140",
    "addr:postcode":"28012",
    "addr:street":"N Main St",
    "iso:country":"US",
    "sg:address":"140 N Main St",
    "sg:city":"Belmont",
    "sg:classifiers":[
        {
            "category":"Shopping",
            "subcategory":"Stationery & Office Supplies",
            "type":"Retail Goods"
        }
    ],
    "sg:phone":"+1 704 825 2322",
    "sg:postcode":"28012",
    "sg:province":"NC",
    "sg:tags":[
        "educational",
        "material"
    ],
    "sg:website":"www.school-resources.com",
    "wof:name":"School Resources Co",
    "wof:placetype":"venue"
},
  "geometry": {"coordinates":[-81.038372,35.244851],"type":"Point"}
}