{
  "type": "Feature",
  "properties": {
    "addr:full":"2100 S Main St Winston Salem NC 27127",
    "addr:housenumber":"2100",
    "addr:postcode":"27127",
    "addr:street":"S Main St",
    "iso:country":"US",
    "sg:address":"2100 S Main St",
    "sg:city":"Winston Salem",
    "sg:classifiers":[
        {
            "category":"Retail",
            "subcategory":"Auto Repair",
            "type":"Services"
        }
    ],
    "sg:phone":"+1   ",
    "sg:postcode":"27127",
    "sg:province":"NC",
    "sg:tags":[
        "general"
    ],
    "wof:name":"City Auto",
    "wof:placetype":"venue"
},
  "geometry": {"coordinates":[-80.23916699999999,36.070938],"type":"Point"}
}