{
  "type": "Feature",
  "properties": {
    "addr:full":"7633 Pineville-Matthews Rd Charlotte NC 28226",
    "addr:housenumber":"7633",
    "addr:postcode":"28226",
    "addr:street":"Pineville-Matthews Rd",
    "iso:country":"US",
    "sg:address":"7633 Pineville-Matthews Rd",
    "sg:city":"Charlotte",
    "sg:classifiers":[
        {
            "category":"Shopping",
            "subcategory":"Florist",
            "type":"Retail Goods"
        }
    ],
    "sg:phone":"+1 704 542 8769",
    "sg:postcode":"28226",
    "sg:province":"NC",
    "wof:name":"Todd's Flowers",
    "wof:placetype":"venue"
},
  "geometry": {"coordinates":[-80.846396,35.087666],"type":"Point"}
}