{
  "type": "Feature",
  "properties": {
    "iso:country":"US",
    "sg:address":"6521 Santa Cruz Trl",
    "sg:city":"Charlotte",
    "sg:classifiers":[
        {
            "category":"Building & Trades",
            "subcategory":"Plumbing",
            "type":"Services"
        }
    ],
    "sg:phone":"+1 704 567 8671",
    "sg:postcode":"28227",
    "sg:province":"NC",
    "sg:tags":[
        "contractor"
    ],
    "wof:name":"Kirby Plumbing Co",
    "wof:placetype":"venue"
},
  "geometry": {"coordinates":[-80.71528000000001,35.22115],"type":"Point"}
}