{
  "type": "Feature",
  "properties": {
    "iso:country":"US",
    "sg:address":"7113 Cape Harbor Dr",
    "sg:city":"Wilmington",
    "sg:classifiers":[
        {
            "category":"Real Estate",
            "subcategory":"Real Estate Operator",
            "type":"Services"
        }
    ],
    "sg:phone":"+1 910 392 5411",
    "sg:postcode":"28411",
    "sg:province":"NC",
    "sg:tags":[
        "apartment"
    ],
    "wof:name":"Cape Harbor Apartments",
    "wof:placetype":"venue"
},
  "geometry": {"coordinates":[-77.83201800000001,34.265122],"type":"Point"}
}