{
  "type": "Feature",
  "properties": {
    "addr:full":"6603 English Hills Dr Charlotte NC 28212",
    "addr:housenumber":"6603",
    "addr:postcode":"28212",
    "addr:street":"English Hills Dr",
    "iso:country":"US",
    "sg:address":"6603 English Hills Dr",
    "sg:city":"Charlotte",
    "sg:classifiers":[
        {
            "category":"Arts & Performance",
            "subcategory":"Theater",
            "type":"Entertainment"
        }
    ],
    "sg:phone":"+1 704 497 7984",
    "sg:postcode":"28212",
    "sg:province":"NC",
    "sg:tags":[
        "musician"
    ],
    "wof:name":"Infinite Productions",
    "wof:placetype":"venue"
},
  "geometry": {"coordinates":[-80.732252,35.206374],"type":"Point"}
}