{
  "type": "Feature",
  "properties": {
    "iso:country":"US",
    "sg:address":"605 Goldeneye Ct",
    "sg:city":"Wilmington",
    "sg:classifiers":[
        {
            "category":"Social Services",
            "subcategory":"Child Care",
            "type":"Services"
        }
    ],
    "sg:phone":"+1   ",
    "sg:postcode":"28411",
    "sg:province":"NC",
    "sg:tags":[
        "day"
    ],
    "wof:name":"Tot Services Inc",
    "wof:placetype":"venue"
},
  "geometry": {"coordinates":[-77.799521,34.28545],"type":"Point"}
}