{
  "type": "Feature",
  "properties": {
    "addr:full":"7505 Caldwell Rd Harrisburg NC 28075",
    "addr:housenumber":"7505",
    "addr:postcode":"28075",
    "addr:street":"Caldwell Rd",
    "iso:country":"US",
    "sg:address":"7505 Caldwell Rd",
    "sg:city":"Harrisburg",
    "sg:classifiers":[
        {
            "category":"Professional",
            "type":"Services"
        }
    ],
    "sg:phone":"+1 704 455 8900",
    "sg:postcode":"28075",
    "sg:province":"NC",
    "wof:name":"Jenco",
    "wof:placetype":"venue"
},
  "geometry": {"coordinates":[-80.672552,35.314706],"type":"Point"}
}