{
  "type": "Feature",
  "properties": {
    "addr:full":"2216 Maybrook Dr Raleigh NC 27610",
    "addr:housenumber":"2216",
    "addr:postcode":"27610",
    "addr:street":"Maybrook Dr",
    "iso:country":"US",
    "sg:address":"2216 Maybrook Dr",
    "sg:city":"Raleigh",
    "sg:classifiers":[
        {
            "category":"Manufacturing",
            "subcategory":"Tools & Machinery",
            "type":"Manufacturing & Wholesale Goods"
        },
        {
            "category":"Building & Trades",
            "subcategory":"Plumbing",
            "type":"Services"
        }
    ],
    "sg:phone":"+1 410 383 4790",
    "sg:postcode":"27610",
    "sg:province":"NC",
    "sg:tags":[
        "jig",
        "fixture",
        "maker",
        "die"
    ],
    "wof:name":"Zion Tools Inc.",
    "wof:placetype":"venue"
},
  "geometry": {"coordinates":[-78.55814700000001,35.751504],"type":"Point"}
}