{
  "type": "Feature",
  "properties": {
    "iso:country":"US",
    "sg:address":"3629 Sunset Ave",
    "sg:city":"Rocky Mount",
    "sg:classifiers":[
        {
            "category":"Restaurant",
            "type":"Food & Drink"
        }
    ],
    "sg:phone":"+1 252 937 7299",
    "sg:postcode":"27804",
    "sg:province":"NC",
    "sg:tags":[
        "eating"
    ],
    "wof:name":"Westridge Grill",
    "wof:placetype":"venue"
},
  "geometry": {"coordinates":[-77.85236,35.963713],"type":"Point"}
}