{
  "type": "Feature",
  "properties": {
    "iso:country":"US",
    "sg:address":"1609 Ketch Ln",
    "sg:city":"Kill Devil Hills",
    "sg:classifiers":[
        {
            "category":"Building & Trades",
            "subcategory":"Construction",
            "type":"Services"
        }
    ],
    "sg:phone":"+1 252 441 8254",
    "sg:postcode":"27948",
    "sg:province":"NC",
    "sg:tags":[
        "residential"
    ],
    "wof:name":"Outer Banks Homes",
    "wof:placetype":"venue"
},
  "geometry": {"coordinates":[-75.679401,36.025539],"type":"Point"}
}