{
  "type": "Feature",
  "properties": {
    "iso:country":"US",
    "sg:address":"1116 E Main St",
    "sg:city":"Lincolnton",
    "sg:classifiers":[
        {
            "category":"Retail",
            "subcategory":"Auto Repair",
            "type":"Services"
        }
    ],
    "sg:phone":"+1 704 748 9292",
    "sg:postcode":"28092",
    "sg:province":"NC",
    "sg:tags":[
        "repairing",
        "automobile"
    ],
    "wof:name":"Duncan's Auto Repair",
    "wof:placetype":"venue"
},
  "geometry": {"coordinates":[-81.24194,35.476072],"type":"Point"}
}