{
  "type": "Feature",
  "properties": {
    "iso:country":"US",
    "sg:address":"16132 Blackberry Hills Dr",
    "sg:city":"Midland",
    "sg:classifiers":[
        {
            "category":"Building & Trades",
            "subcategory":"Construction",
            "type":"Services"
        }
    ],
    "sg:phone":"+1 704 545 2022",
    "sg:postcode":"28107",
    "sg:province":"NC",
    "sg:tags":[
        "house"
    ],
    "wof:name":"Apple Orchard Log Homes Cha",
    "wof:placetype":"venue"
},
  "geometry": {"coordinates":[-80.58228099999999,35.224474],"type":"Point"}
}