{
  "type": "Feature",
  "properties": {
    "addr:full":"3614 Mill Run Raleigh NC 27612",
    "addr:housenumber":"3614",
    "addr:postcode":"27612",
    "addr:street":"Mill Run",
    "iso:country":"US",
    "sg:address":"3614 Mill Run",
    "sg:city":"Raleigh",
    "sg:classifiers":[
        {
            "category":"Professional",
            "subcategory":"Lawyer & Legal Services",
            "type":"Services"
        }
    ],
    "sg:phone":"+1 919 715 0607",
    "sg:postcode":"27612",
    "sg:province":"NC",
    "sg:tags":[
        "attorney"
    ],
    "wof:name":"Dewey T O'Kelley III",
    "wof:placetype":"venue"
},
  "geometry": {"coordinates":[-78.711381,35.826028],"type":"Point"}
}