{
  "type": "Feature",
  "properties": {
    "iso:country":"US",
    "sg:address":"6608 Marshville Blvd",
    "sg:city":"Marshville",
    "sg:classifiers":[
        {
            "category":"Wholesale",
            "subcategory":"Meat",
            "type":"Manufacturing & Wholesale Goods"
        }
    ],
    "sg:phone":"+1 704 624 6628",
    "sg:postcode":"28103",
    "sg:province":"NC",
    "sg:tags":[
        "process",
        "turkey"
    ],
    "wof:name":"Stegall Smoked Turkey Inc",
    "wof:placetype":"venue"
},
  "geometry": {"coordinates":[-80.35781299999999,34.986607],"type":"Point"}
}