{
  "type": "Feature",
  "properties": {
    "addr:full":"1811 Sardis Rd N Charlotte NC 28270",
    "addr:housenumber":"1811",
    "addr:postcode":"28270",
    "addr:street":"Sardis Rd N",
    "iso:country":"US",
    "sg:address":"1811 Sardis Rd N",
    "sg:city":"Charlotte",
    "sg:classifiers":[
        {
            "category":"Health Services",
            "subcategory":"Clinic",
            "type":"Services"
        }
    ],
    "sg:phone":"+1 704 844 6708",
    "sg:postcode":"28270",
    "sg:province":"NC",
    "wof:name":"Healthier Resources Inc",
    "wof:placetype":"venue"
},
  "geometry": {"coordinates":[-80.73608900000001,35.140008],"type":"Point"}
}