{
  "type": "Feature",
  "properties": {
    "iso:country":"US",
    "sg:address":"10532 Parkton Rd",
    "sg:city":"Charlotte",
    "sg:classifiers":[
        {
            "category":"Wholesale",
            "subcategory":"Motor Vehicles",
            "type":"Manufacturing & Wholesale Goods"
        }
    ],
    "sg:phone":"+1 704 753 9008",
    "sg:postcode":"28215",
    "sg:province":"NC",
    "sg:tags":[
        "auto"
    ],
    "wof:name":"Steves Foreign Cars",
    "wof:placetype":"venue"
},
  "geometry": {"coordinates":[-80.668654,35.209359],"type":"Point"}
}