{
  "type": "Feature",
  "properties": {
    "addr:full":"1628 Sweetgum Cir Fayetteville NC 28304",
    "addr:housenumber":"1628",
    "addr:postcode":"28304",
    "addr:street":"Sweetgum Cir",
    "iso:country":"US",
    "sg:address":"1628 Sweetgum Cir",
    "sg:city":"Fayetteville",
    "sg:classifiers":[
        {
            "category":"Real Estate",
            "subcategory":"Real Estate Operator",
            "type":"Services"
        }
    ],
    "sg:phone":"+1 910 860 0000",
    "sg:postcode":"28304",
    "sg:province":"NC",
    "wof:name":"Stinson Properties",
    "wof:placetype":"venue"
},
  "geometry": {"coordinates":[-79.00957699999999,35.024488],"type":"Point"}
}