{
  "type": "Feature",
  "properties": {
    "iso:country":"US",
    "sg:address":"152 County Line Rd",
    "sg:city":"Tyner",
    "sg:classifiers":[
        {
            "category":"Wholesale",
            "subcategory":"Construction Materials",
            "type":"Manufacturing & Wholesale Goods"
        },
        {
            "category":"Manufacturing",
            "subcategory":"Lumber",
            "type":"Manufacturing & Wholesale Goods"
        }
    ],
    "sg:phone":"+1 252 221 3007",
    "sg:postcode":"27980",
    "sg:province":"NC",
    "sg:tags":[
        "timberland",
        "company",
        "logging",
        "contract",
        "timber"
    ],
    "wof:name":"Billy Harrell Logging Inc",
    "wof:placetype":"venue"
},
  "geometry": {"coordinates":[-76.604974,36.216835],"type":"Point"}
}