{
  "type": "Feature",
  "properties": {
    "addr:full":"5806 Spanish Oak Dr Greensboro NC 27409",
    "addr:housenumber":"5806",
    "addr:postcode":"27409",
    "addr:street":"Spanish Oak Dr",
    "iso:country":"US",
    "sg:address":"5806 Spanish Oak Dr",
    "sg:city":"Greensboro",
    "sg:classifiers":[
        {
            "category":"Professional",
            "subcategory":"Advertising",
            "type":"Services"
        }
    ],
    "sg:phone":"+1 336 315 2203",
    "sg:postcode":"27409",
    "sg:province":"NC",
    "wof:name":"Broach Media",
    "wof:placetype":"venue"
},
  "geometry": {"coordinates":[-79.896934,36.065687],"type":"Point"}
}