{
  "type": "Feature",
  "properties": {
    "addr:full":"5500 McNeely Dr Raleigh NC 27612",
    "addr:housenumber":"5500",
    "addr:postcode":"27612",
    "addr:street":"Mcneely Dr",
    "iso:country":"US",
    "sg:address":"5500 McNeely Dr",
    "sg:city":"Raleigh",
    "sg:classifiers":[
        {
            "category":"Professional",
            "subcategory":"Computer Services",
            "type":"Services"
        },
        {
            "category":"Shopping",
            "subcategory":"Computers & Home Electronics",
            "type":"Retail Goods"
        }
    ],
    "sg:phone":"+1 919 781 8044",
    "sg:postcode":"27612",
    "sg:province":"NC",
    "sg:tags":[
        "prepackaged",
        "software"
    ],
    "wof:name":"Data Performance Company",
    "wof:placetype":"venue"
},
  "geometry": {"coordinates":[-78.71168,35.853702],"type":"Point"}
}