{
  "type": "Feature",
  "properties": {
    "iso:country":"US",
    "sg:address":"225 Hawthorne Ln",
    "sg:city":"Charlotte",
    "sg:classifiers":[
        {
            "category":"Organizations",
            "subcategory":"Religious Organization",
            "type":"Services"
        }
    ],
    "sg:phone":"+1   ",
    "sg:postcode":"28204",
    "sg:province":"NC",
    "wof:name":"Presbyterian Healthcare",
    "wof:placetype":"venue"
},
  "geometry": {"coordinates":[-80.824601,35.213788],"type":"Point"}
}