{
  "type": "Feature",
  "properties": {
    "iso:country":"US",
    "sg:address":"3026 W Cornwallis Rd",
    "sg:city":"Durham",
    "sg:classifiers":[
        {
            "category":"Manufacturing",
            "subcategory":"Tools & Machinery",
            "type":"Manufacturing & Wholesale Goods"
        }
    ],
    "sg:phone":"+1 919 314 2202",
    "sg:postcode":"27705",
    "sg:province":"NC",
    "sg:tags":[
        "fluid",
        "devices",
        "mfg"
    ],
    "wof:name":"Cronos Integrated Microsystems",
    "wof:placetype":"venue"
},
  "geometry": {"coordinates":[-78.972926,35.993354],"type":"Point"}
}