{
  "type": "Feature",
  "properties": {
    "addr:full":"152 Walker Rd Statesville NC 28625",
    "addr:housenumber":"152",
    "addr:postcode":"28625",
    "addr:street":"Walker Rd",
    "iso:country":"US",
    "sg:address":"152 Walker Rd",
    "sg:city":"Statesville",
    "sg:classifiers":[
        {
            "category":"Wholesale",
            "subcategory":"Chemicals & Plastics",
            "type":"Manufacturing & Wholesale Goods"
        }
    ],
    "sg:phone":"+1 704 872 0763",
    "sg:postcode":"28625",
    "sg:province":"NC",
    "sg:tags":[
        "adhesive",
        "glue"
    ],
    "wof:name":"Bradley Technologies Nc Inc",
    "wof:placetype":"venue"
},
  "geometry": {"coordinates":[-80.933971,35.803493],"type":"Point"}
}