{
  "type": "Feature",
  "properties": {
    "addr:full":"5087 Big Woods Rd Chapel Hill NC 27517",
    "addr:housenumber":"5087",
    "addr:postcode":"27517",
    "addr:street":"Big Woods Rd",
    "iso:country":"US",
    "sg:address":"5087 Big Woods Rd",
    "sg:city":"Chapel Hill",
    "sg:classifiers":[
        {
            "category":"Building & Trades",
            "subcategory":"Construction",
            "type":"Services"
        }
    ],
    "sg:phone":"+1 919 942 9590",
    "sg:postcode":"27517",
    "sg:province":"NC",
    "sg:tags":[
        "contractor"
    ],
    "wof:name":"Bill Willis Stone Masonry",
    "wof:placetype":"venue"
},
  "geometry": {"coordinates":[-79.030568,35.806054],"type":"Point"}
}