{
  "type": "Feature",
  "properties": {
    "iso:country":"US",
    "sg:address":"3906 Nash St",
    "sg:city":"Greensboro",
    "sg:classifiers":[
        {
            "category":"Professional",
            "type":"Services"
        }
    ],
    "sg:phone":"+1 336 691 6447",
    "sg:postcode":"27401",
    "sg:province":"NC",
    "wof:name":"Simply Spectacular",
    "wof:placetype":"venue"
},
  "geometry": {"coordinates":[-79.741575,36.078038],"type":"Point"}
}