{
  "type": "Feature",
  "properties": {
    "addr:full":"101 W Roseboro St Roseboro NC 28382",
    "addr:housenumber":"101",
    "addr:postcode":"28382",
    "addr:street":"W Roseboro St",
    "iso:country":"US",
    "sg:address":"101 W Roseboro St",
    "sg:city":"Roseboro",
    "sg:classifiers":[
        {
            "category":"Shopping",
            "subcategory":"Computers & Home Electronics",
            "type":"Retail Goods"
        }
    ],
    "sg:phone":"+1 910 525 5300",
    "sg:postcode":"28382",
    "sg:province":"NC",
    "wof:name":"Radio Shack",
    "wof:placetype":"venue"
},
  "geometry": {"coordinates":[-78.510549,34.952723],"type":"Point"}
}