{
  "type": "Feature",
  "properties": {
    "addr:full":"4408 Innsbrook Ct Greensboro NC 27410",
    "addr:housenumber":"4408",
    "addr:postcode":"27410",
    "addr:street":"Innsbrook Ct",
    "iso:country":"US",
    "sg:address":"4408 Innsbrook Ct",
    "sg:city":"Greensboro",
    "sg:classifiers":[
        {
            "category":"Shopping",
            "subcategory":"Discount & Variety Stores",
            "type":"Retail Goods"
        },
        {
            "category":"Professional",
            "subcategory":"Management & Consulting",
            "type":"Services"
        }
    ],
    "sg:phone":"+1 336 665 9103",
    "sg:postcode":"27410",
    "sg:province":"NC",
    "sg:tags":[
        "sales",
        "direct",
        "merchandise",
        "general"
    ],
    "wof:name":"Kim's Creations",
    "wof:placetype":"venue"
},
  "geometry": {"coordinates":[-79.92353,36.13682],"type":"Point"}
}