{
  "type": "Feature",
  "properties": {
    "iso:country":"US",
    "sg:address":"4409 Country Club Rd",
    "sg:city":"Morehead City",
    "sg:classifiers":[
        {
            "category":"Health Services",
            "subcategory":"Doctor",
            "type":"Services"
        }
    ],
    "sg:phone":"+1 252 726 4352",
    "sg:postcode":"28557",
    "sg:province":"NC",
    "sg:tags":[
        "dentist"
    ],
    "wof:name":"Carteret Co Dental Unit",
    "wof:placetype":"venue"
},
  "geometry": {"coordinates":[-76.778891,34.735783],"type":"Point"}
}