{
  "type": "Feature",
  "properties": {
    "addr:full":"28224 US Hwy 264 E Belhaven NC 27860",
    "addr:postcode":"28224;27860",
    "addr:street":"Us Hwy 264 E Belhaven",
    "iso:country":"US",
    "sg:address":"28224 US Hwy 264 E",
    "sg:city":"Belhaven",
    "sg:classifiers":[
        {
            "category":"Retail",
            "subcategory":"Auto Repair",
            "type":"Services"
        }
    ],
    "sg:phone":"+1 252 943 3326",
    "sg:postcode":"27860",
    "sg:province":"NC",
    "sg:tags":[
        "repairing",
        "automobile"
    ],
    "wof:name":"Paul's Service Ctr",
    "wof:placetype":"venue"
},
  "geometry": {"coordinates":[-76.646378,35.579928],"type":"Point"}
}