{
  "type": "Feature",
  "properties": {
    "iso:country":"US",
    "sg:address":"318 Montgomery Ave",
    "sg:city":"Albemarle",
    "sg:classifiers":[
        {
            "category":"Personal",
            "subcategory":"Beauty Salon",
            "type":"Services"
        }
    ],
    "sg:phone":"+1 704 986 2200",
    "sg:postcode":"28001",
    "sg:province":"NC",
    "wof:name":"Signature Salon",
    "wof:placetype":"venue"
},
  "geometry": {"coordinates":[-80.194389,35.355513],"type":"Point"}
}