{
  "type": "Feature",
  "properties": {
    "addr:full":"1619 Cavell Ct Hillsborough NC 27278",
    "addr:housenumber":"1619",
    "addr:postcode":"27278",
    "addr:street":"Cavell Ct",
    "iso:country":"US",
    "sg:address":"1619 Cavell Ct",
    "sg:city":"Hillsborough",
    "sg:classifiers":[
        {
            "category":"Professional",
            "type":"Services"
        }
    ],
    "sg:phone":"+1 919 732 2021",
    "sg:postcode":"27278",
    "sg:province":"NC",
    "wof:name":"Gulf To Bay Seafood Inc",
    "wof:placetype":"venue"
},
  "geometry": {"coordinates":[-79.074901,36.086413],"type":"Point"}
}