{
  "type": "Feature",
  "properties": {
    "addr:full":"266 Merrimon Ave Asheville NC 28801",
    "addr:housenumber":"266",
    "addr:postcode":"28801",
    "addr:street":"Merrimon Ave",
    "iso:country":"US",
    "sg:address":"266 Merrimon Ave",
    "sg:city":"Asheville",
    "sg:classifiers":[
        {
            "category":"Health Services",
            "subcategory":"Nursing And Care Facility",
            "type":"Services"
        },
        {
            "category":"Professional",
            "type":"Services"
        }
    ],
    "sg:phone":"+1 828 253 6712",
    "sg:postcode":"28801",
    "sg:province":"NC",
    "sg:tags":[
        "skilled",
        "establishment"
    ],
    "wof:name":"Brooks Howell Home",
    "wof:placetype":"venue"
},
  "geometry": {"coordinates":[-82.553847,35.60746],"type":"Point"}
}