{
  "type": "Feature",
  "properties": {
    "iso:country":"US",
    "sg:address":"4639 Hartland Rd",
    "sg:city":"Lenoir",
    "sg:classifiers":[
        {
            "category":"Shopping",
            "subcategory":"Florist",
            "type":"Retail Goods"
        }
    ],
    "sg:phone":"+1 828 759 1411",
    "sg:postcode":"28645",
    "sg:province":"NC",
    "wof:name":"Unique Cottage Designs",
    "wof:placetype":"venue"
},
  "geometry": {"coordinates":[-81.602236,35.865645],"type":"Point"}
}