{
  "type": "Feature",
  "properties": {
    "iso:country":"US",
    "sg:address":"2711 Randolph Rd",
    "sg:city":"Charlotte",
    "sg:classifiers":[
        {
            "category":"Health Services",
            "subcategory":"Doctor",
            "type":"Services"
        }
    ],
    "sg:phone":"+1 704 342 1900",
    "sg:postcode":"28207",
    "sg:province":"NC",
    "sg:tags":[
        "physician",
        "surgeon"
    ],
    "wof:name":"Oncology Specialists",
    "wof:placetype":"venue"
},
  "geometry": {"coordinates":[-80.813074,35.19997],"type":"Point"}
}