{
  "type": "Feature",
  "properties": {
    "addr:full":"600 Victoria Dr N Hillsborough NC 27278",
    "addr:housenumber":"600",
    "addr:postcode":"27278",
    "addr:street":"Victoria Dr N",
    "iso:country":"US",
    "sg:address":"600 Victoria Dr N",
    "sg:city":"Hillsborough",
    "sg:classifiers":[
        {
            "category":"Manufacturing",
            "subcategory":"Signs",
            "type":"Manufacturing & Wholesale Goods"
        }
    ],
    "sg:phone":"+1 919 644 0044",
    "sg:postcode":"27278",
    "sg:province":"NC",
    "wof:name":"Mark Gordon Signs",
    "wof:placetype":"venue"
},
  "geometry": {"coordinates":[-79.08751100000001,36.093824],"type":"Point"}
}