{
  "type": "Feature",
  "properties": {
    "addr:full":"7521 Whitaker Dr Summerfield NC 27358",
    "addr:housenumber":"7521",
    "addr:postcode":"27358",
    "addr:street":"Whitaker Dr",
    "iso:country":"US",
    "sg:address":"7521 Whitaker Dr",
    "sg:city":"Summerfield",
    "sg:classifiers":[
        {
            "category":"Professional",
            "type":"Services"
        }
    ],
    "sg:phone":"+1 336 643 5007",
    "sg:postcode":"27358",
    "sg:province":"NC",
    "wof:name":"Dennis Willis",
    "wof:placetype":"venue"
},
  "geometry": {"coordinates":[-79.94538900000001,36.206088],"type":"Point"}
}