{
  "type": "Feature",
  "properties": {
    "addr:full":"663 Barossa Valley Dr NW Concord NC 28027",
    "addr:housenumber":"663",
    "addr:postcode":"28027",
    "addr:street":"Barossa Valley Dr Nw",
    "iso:country":"US",
    "sg:address":"663 Barossa Valley Dr NW",
    "sg:city":"Concord",
    "sg:classifiers":[
        {
            "category":"Community Center",
            "type":"Public Place"
        }
    ],
    "sg:phone":"+1 704 796 1358",
    "sg:postcode":"28027",
    "sg:province":"NC",
    "sg:tags":[
        "medical"
    ],
    "wof:name":"Carolina Medical Diagnostics",
    "wof:placetype":"venue"
},
  "geometry": {"coordinates":[-80.755472,35.404139],"type":"Point"}
}