{
  "type": "Feature",
  "properties": {
    "addr:full":"1541 16th St NE Hickory NC 28601",
    "addr:housenumber":"1541",
    "addr:postcode":"28601",
    "addr:street":"16Th St Ne",
    "iso:country":"US",
    "sg:address":"1541 16th St NE",
    "sg:city":"Hickory",
    "sg:classifiers":[
        {
            "category":"Personal",
            "subcategory":"Beauty Salon",
            "type":"Services"
        }
    ],
    "sg:phone":"+1   ",
    "sg:postcode":"28601",
    "sg:province":"NC",
    "sg:tags":[
        "shop"
    ],
    "wof:name":"Hair Salon 2000",
    "wof:placetype":"venue"
},
  "geometry": {"coordinates":[-81.303405,35.748762],"type":"Point"}
}