{
  "type": "Feature",
  "properties": {
    "iso:country":"US",
    "sg:address":"10711 US Hwy 17",
    "sg:city":"Williamston",
    "sg:classifiers":[
        {
            "category":"Autos & Motor Vehicles",
            "subcategory":"Automobile Sales",
            "type":"Retail Goods"
        }
    ],
    "sg:phone":"+1 252 809 0350",
    "sg:postcode":"27892",
    "sg:province":"NC",
    "sg:tags":[
        "car",
        "used"
    ],
    "wof:name":"Lee Elisha",
    "wof:placetype":"venue"
},
  "geometry": {"coordinates":[-77.072552,35.705544],"type":"Point"}
}