{
  "type": "Feature",
  "properties": {
    "iso:country":"US",
    "sg:address":"3391 US Hwy 17",
    "sg:city":"Chocowinity",
    "sg:classifiers":[
        {
            "category":"Government",
            "subcategory":"Office",
            "type":"Public Place"
        }
    ],
    "sg:phone":"+1 252 946 6568",
    "sg:postcode":"27817",
    "sg:province":"NC",
    "sg:tags":[
        "city"
    ],
    "wof:name":"Chocowinity Town Hall",
    "wof:placetype":"venue"
},
  "geometry": {"coordinates":[-77.094763,35.51723],"type":"Point"}
}