{
  "type": "Feature",
  "properties": {
    "iso:country":"US",
    "sg:address":"2206 Slate Rd",
    "sg:city":"King",
    "sg:classifiers":[
        {
            "category":"Real Estate",
            "subcategory":"Real Estate Agent",
            "type":"Services"
        }
    ],
    "sg:phone":"+1 336 971 7357",
    "sg:postcode":"27021",
    "sg:province":"NC",
    "sg:tags":[
        "appraiser"
    ],
    "wof:name":"Kathryn Crouse Appraisals",
    "wof:placetype":"venue"
},
  "geometry": {"coordinates":[-80.28913,36.294782],"type":"Point"}
}