{
  "type": "Feature",
  "properties": {
    "addr:full":"8308 Tintinhull Ln Waxhaw NC 28173",
    "addr:housenumber":"8308",
    "addr:postcode":"28173",
    "addr:street":"Tintinhull Ln",
    "iso:country":"US",
    "sg:address":"8308 Tintinhull Ln",
    "sg:city":"Waxhaw",
    "sg:classifiers":[
        {
            "category":"Shopping",
            "subcategory":"Computers & Home Electronics",
            "type":"Retail Goods"
        }
    ],
    "sg:phone":"+1 704 847 0631",
    "sg:postcode":"28173",
    "sg:province":"NC",
    "sg:tags":[
        "equipment",
        "dealer"
    ],
    "wof:name":"Champion Solutions Group",
    "wof:placetype":"venue"
},
  "geometry": {"coordinates":[-80.804581,35.024702],"type":"Point"}
}