{
  "type": "Feature",
  "properties": {
    "iso:country":"US",
    "sg:address":"858 2nd St NE",
    "sg:city":"Hickory",
    "sg:classifiers":[
        {
            "category":"Health Services",
            "subcategory":"Doctor",
            "type":"Services"
        }
    ],
    "sg:phone":"+1 828 345 6257",
    "sg:postcode":"28601",
    "sg:province":"NC",
    "sg:tags":[
        "physician",
        "surgeon"
    ],
    "wof:name":"Graystone Ophthalmology Assoc",
    "wof:placetype":"venue"
},
  "geometry": {"coordinates":[-81.33516899999999,35.744338],"type":"Point"}
}