{
  "type": "Feature",
  "properties": {
    "iso:country":"US",
    "sg:address":"305 Hunting Ridge Rd",
    "sg:city":"Roanoke Rapids",
    "sg:classifiers":[
        {
            "category":"Professional",
            "subcategory":"Business Services",
            "type":"Services"
        }
    ],
    "sg:phone":"+1 252 537 5151",
    "sg:postcode":"27870",
    "sg:province":"NC",
    "wof:name":"Keshav Enterprises LLC",
    "wof:placetype":"venue"
},
  "geometry": {"coordinates":[-77.638357,36.44506],"type":"Point"}
}