{
  "type": "Feature",
  "properties": {
    "addr:full":"398 Old Charlotte Rd SW Concord NC 28027",
    "addr:housenumber":"398",
    "addr:postcode":"28027",
    "addr:street":"Old Charlotte Rd Sw",
    "iso:country":"US",
    "sg:address":"398 Old Charlotte Rd SW",
    "sg:city":"Concord",
    "sg:classifiers":[
        {
            "category":"Wholesale",
            "subcategory":"Auto Parts",
            "type":"Manufacturing & Wholesale Goods"
        }
    ],
    "sg:phone":"+1 704 788 4013",
    "sg:postcode":"28027",
    "sg:province":"NC",
    "sg:tags":[
        "automotive",
        "rebuilt"
    ],
    "wof:name":"Blackwelder Core Supply",
    "wof:placetype":"venue"
},
  "geometry": {"coordinates":[-80.59313899999999,35.399396],"type":"Point"}
}