{
  "type": "Feature",
  "properties": {
    "iso:country":"US",
    "sg:address":"116 W Main St",
    "sg:city":"Wallace",
    "sg:classifiers":[
        {
            "category":"Shopping",
            "subcategory":"Clothing, Apparel, & Fashions",
            "type":"Retail Goods"
        }
    ],
    "sg:phone":"+1 910 285 8877",
    "sg:postcode":"28466",
    "sg:province":"NC",
    "sg:tags":[
        "lingerie"
    ],
    "wof:name":"Frolic",
    "wof:placetype":"venue"
},
  "geometry": {"coordinates":[-77.996714,34.734745],"type":"Point"}
}