{
  "type": "Feature",
  "properties": {
    "addr:full":"512 Nowell Rd Raleigh NC 27607",
    "addr:housenumber":"512",
    "addr:postcode":"27607",
    "addr:street":"Nowell Rd",
    "iso:country":"US",
    "sg:address":"512 Nowell Rd",
    "sg:city":"Raleigh",
    "sg:classifiers":[
        {
            "category":"Building & Trades",
            "subcategory":"Construction",
            "type":"Services"
        }
    ],
    "sg:phone":"+1 919 859 4464",
    "sg:postcode":"27607",
    "sg:province":"NC",
    "sg:tags":[
        "masonry",
        "contractor"
    ],
    "wof:name":"Bates Masonry Inc",
    "wof:placetype":"venue"
},
  "geometry": {"coordinates":[-78.732607,35.787093],"type":"Point"}
}