{
  "type": "Feature",
  "properties": {
    "iso:country":"US",
    "sg:address":"110 Guymon Ct",
    "sg:city":"Morrisville",
    "sg:classifiers":[
        {
            "category":"Food & Beverages",
            "subcategory":"Groceries & Convenience Stores",
            "type":"Retail Goods"
        }
    ],
    "sg:phone":"+1 919 678 8571",
    "sg:postcode":"27560",
    "sg:province":"NC",
    "wof:name":"Greenville Flea Market LL",
    "wof:placetype":"venue"
},
  "geometry": {"coordinates":[-78.813868,35.821188],"type":"Point"}
}