{
  "type": "Feature",
  "properties": {
    "addr:full":"4217 W Wendover Ave Greensboro NC 27407",
    "addr:housenumber":"4217",
    "addr:postcode":"27407",
    "addr:street":"W Wendover Ave",
    "iso:country":"US",
    "sg:address":"4217 W Wendover Ave",
    "sg:city":"Greensboro",
    "sg:classifiers":[
        {
            "category":"Shopping",
            "subcategory":"Computers & Home Electronics",
            "type":"Retail Goods"
        }
    ],
    "sg:phone":"+1 336 547 0208",
    "sg:postcode":"27407",
    "sg:province":"NC",
    "sg:tags":[
        "equipment",
        "electronic",
        "supply"
    ],
    "wof:name":"Circuit City",
    "wof:placetype":"venue"
},
  "geometry": {"coordinates":[-79.887604,36.058013],"type":"Point"}
}