{
  "type": "Feature",
  "properties": {
    "addr:full":"1622 Manning Rd Greenville NC 27858",
    "addr:housenumber":"1622",
    "addr:postcode":"27858",
    "addr:street":"Manning Rd",
    "iso:country":"US",
    "sg:address":"1622 Manning Rd",
    "sg:city":"Greenville",
    "sg:classifiers":[
        {
            "category":"Recreation",
            "type":"Entertainment"
        }
    ],
    "sg:phone":"+1 252 321 7344",
    "sg:postcode":"27858",
    "sg:province":"NC",
    "sg:tags":[
        "tennis",
        "court"
    ],
    "wof:name":"Match Point Racquet Club",
    "wof:placetype":"venue"
},
  "geometry": {"coordinates":[-77.335628,35.520661],"type":"Point"}
}