{
  "type": "Feature",
  "properties": {
    "addr:full":"2361 W Pleasant Hill Rd Pink Hill NC 28572",
    "addr:housenumber":"2361",
    "addr:postcode":"28572",
    "addr:street":"W Pleasant Hill Rd",
    "iso:country":"US",
    "sg:address":"2361 W Pleasant Hill Rd",
    "sg:city":"Pink Hill",
    "sg:classifiers":[
        {
            "category":"Building & Trades",
            "subcategory":"Construction",
            "type":"Services"
        }
    ],
    "sg:phone":"+1 252 568 5533",
    "sg:postcode":"28572",
    "sg:province":"NC",
    "wof:name":"Hot Patch",
    "wof:placetype":"venue"
},
  "geometry": {"coordinates":[-77.711213,35.046642],"type":"Point"}
}