{
  "type": "Feature",
  "properties": {
    "addr:full":"3310 Springs Rd NE Hickory NC 28601",
    "addr:housenumber":"3310",
    "addr:postcode":"28601",
    "addr:street":"Springs Rd Ne",
    "iso:country":"US",
    "sg:address":"3310 Springs Rd NE",
    "sg:city":"Hickory",
    "sg:classifiers":[
        {
            "category":"Banks & Credit Unions",
            "subcategory":"Bank",
            "type":"Services"
        }
    ],
    "sg:phone":"+1 828 256 9229",
    "sg:postcode":"28601",
    "sg:province":"NC",
    "wof:name":"Peoples Bank",
    "wof:placetype":"venue"
},
  "geometry": {"coordinates":[-81.27207,35.758835],"type":"Point"}
}