{
  "type": "Feature",
  "properties": {
    "addr:full":"5029 Huntmaster Trl Wake Forest NC 27587",
    "addr:housenumber":"5029",
    "addr:postcode":"27587",
    "addr:street":"Huntmaster Trl",
    "iso:country":"US",
    "sg:address":"5029 Huntmaster Trl",
    "sg:city":"Wake Forest",
    "sg:classifiers":[
        {
            "category":"Restaurant",
            "type":"Food & Drink"
        }
    ],
    "sg:phone":"+1 919 554 9644",
    "sg:postcode":"27587",
    "sg:province":"NC",
    "sg:tags":[
        "eating"
    ],
    "wof:name":"Mama Bows Etc",
    "wof:placetype":"venue"
},
  "geometry": {"coordinates":[-78.487505,35.9228],"type":"Point"}
}