{
  "type": "Feature",
  "properties": {
    "addr:full":"497 Fairview Rd Asheville NC 28803",
    "addr:housenumber":"497",
    "addr:postcode":"28803",
    "addr:street":"Fairview Rd",
    "iso:country":"US",
    "sg:address":"497 Fairview Rd",
    "sg:city":"Asheville",
    "sg:classifiers":[
        {
            "category":"Manufacturing",
            "subcategory":"Wood Products",
            "type":"Manufacturing & Wholesale Goods"
        }
    ],
    "sg:phone":"+1 828 274 9099",
    "sg:postcode":"28803",
    "sg:province":"NC",
    "sg:tags":[
        "preserving"
    ],
    "wof:name":"Cross Ties Inc",
    "wof:placetype":"venue"
},
  "geometry": {"coordinates":[-82.52413,35.566515],"type":"Point"}
}