{
  "type": "Feature",
  "properties": {
    "addr:full":"3000 Commonwealth Ave Charlotte NC 28205",
    "addr:housenumber":"3000",
    "addr:postcode":"28205",
    "addr:street":"Commonwealth Ave",
    "iso:country":"US",
    "sg:address":"3000 Commonwealth Ave",
    "sg:city":"Charlotte",
    "sg:classifiers":[
        {
            "category":"Organizations",
            "subcategory":"Religious Organization",
            "type":"Services"
        }
    ],
    "sg:phone":"+1 704 373 2223",
    "sg:postcode":"28205",
    "sg:province":"NC",
    "wof:name":"Clean Heart Ministries Inc",
    "wof:placetype":"venue"
},
  "geometry": {"coordinates":[-80.79639400000001,35.210513],"type":"Point"}
}