{
  "type": "Feature",
  "properties": {
    "addr:full":"6425 Littlewood Rd Kernersville NC 27284",
    "addr:housenumber":"6425",
    "addr:postcode":"27284",
    "addr:street":"Littlewood Rd",
    "iso:country":"US",
    "sg:address":"6425 Littlewood Rd",
    "sg:city":"Kernersville",
    "sg:classifiers":[
        {
            "category":"Retail",
            "subcategory":"Auto Repair",
            "type":"Services"
        }
    ],
    "sg:phone":"+1   ",
    "sg:postcode":"27284",
    "sg:province":"NC",
    "sg:tags":[
        "automotive"
    ],
    "wof:name":"Valvoline Express Care",
    "wof:placetype":"venue"
},
  "geometry": {"coordinates":[-80.10268600000001,36.116068],"type":"Point"}
}