{
  "type": "Feature",
  "properties": {
    "addr:full":"104 S Sharon Amity Rd Charlotte NC 28211",
    "addr:housenumber":"104",
    "addr:postcode":"28211",
    "addr:street":"S Sharon Amity Rd",
    "iso:country":"US",
    "sg:address":"104 S Sharon Amity Rd",
    "sg:city":"Charlotte",
    "sg:classifiers":[
        {
            "category":"Retail",
            "subcategory":"Laundry & Dry Cleaning",
            "type":"Services"
        }
    ],
    "sg:phone":"+1 704 366 6565",
    "sg:postcode":"28211",
    "sg:province":"NC",
    "sg:tags":[
        "cleaners"
    ],
    "wof:name":"Cunningham Cleaners Inc",
    "wof:placetype":"venue"
},
  "geometry": {"coordinates":[-80.80289999999999,35.174216],"type":"Point"}
}