{
  "type": "Feature",
  "properties": {
    "addr:full":"18145 Deerfield Ln Locust NC 28097",
    "addr:housenumber":"18145",
    "addr:postcode":"28097",
    "addr:street":"Deerfield Ln",
    "iso:country":"US",
    "sg:address":"18145 Deerfield Ln",
    "sg:city":"Locust",
    "sg:classifiers":[
        {
            "category":"Building & Trades",
            "subcategory":"Construction",
            "type":"Services"
        }
    ],
    "sg:phone":"+1 704 485 8323",
    "sg:postcode":"28097",
    "sg:province":"NC",
    "sg:tags":[
        "house"
    ],
    "wof:name":"Greenfield Home Construction",
    "wof:placetype":"venue"
},
  "geometry": {"coordinates":[-80.355728,35.277751],"type":"Point"}
}