{
  "type": "Feature",
  "properties": {
    "addr:full":"3516 Bush St Raleigh NC 27609",
    "addr:housenumber":"3516",
    "addr:postcode":"27609",
    "addr:street":"Bush St",
    "iso:country":"US",
    "sg:address":"3516 Bush St",
    "sg:city":"Raleigh",
    "sg:classifiers":[
        {
            "category":"Professional",
            "subcategory":"Engineering",
            "type":"Services"
        }
    ],
    "sg:phone":"+1 919 871 1070",
    "sg:postcode":"27609",
    "sg:province":"NC",
    "sg:tags":[
        "engineer"
    ],
    "wof:name":"Crenshaw Consulting Engineers",
    "wof:placetype":"venue"
},
  "geometry": {"coordinates":[-78.612295,35.830291],"type":"Point"}
}