{
  "type": "Feature",
  "properties": {
    "iso:country":"US",
    "sg:address":"132 Crest Rd",
    "sg:city":"East Flat Rock",
    "sg:classifiers":[
        {
            "category":"Building & Trades",
            "subcategory":"Construction",
            "type":"Services"
        }
    ],
    "sg:phone":"+1 828 693 1200",
    "sg:postcode":"28726",
    "sg:province":"NC",
    "sg:tags":[
        "water",
        "well",
        "drilling"
    ],
    "wof:name":"Green River Well & Pump Co",
    "wof:placetype":"venue"
},
  "geometry": {"coordinates":[-82.417534,35.29037],"type":"Point"}
}