{
  "type": "Feature",
  "properties": {
    "iso:country":"US",
    "sg:address":"3875 Reid Rd",
    "sg:city":"Tobaccoville",
    "sg:classifiers":[
        {
            "category":"Building & Trades",
            "subcategory":"Construction",
            "type":"Services"
        }
    ],
    "sg:phone":"+1 336 983 6947",
    "sg:postcode":"27050",
    "sg:province":"NC",
    "sg:tags":[
        "residential"
    ],
    "wof:name":"Culler Construction",
    "wof:placetype":"venue"
},
  "geometry": {"coordinates":[-80.37577,36.214999],"type":"Point"}
}