{
  "type": "Feature",
  "properties": {
    "iso:country":"US",
    "sg:address":"3521 Haworth Dr",
    "sg:city":"Raleigh",
    "sg:classifiers":[
        {
            "category":"Professional",
            "subcategory":"Research",
            "type":"Services"
        }
    ],
    "sg:phone":"+1 919 783 4895",
    "sg:postcode":"27609",
    "sg:province":"NC",
    "wof:name":"Multi Specialty Research Of Nc",
    "wof:placetype":"venue"
},
  "geometry": {"coordinates":[-78.633746,35.829165],"type":"Point"}
}