{
  "type": "Feature",
  "properties": {
    "addr:full":"12414 Dixie Ann Dr Charlotte NC 28262",
    "addr:housenumber":"12414",
    "addr:postcode":"28262",
    "addr:street":"Dixie Ann Dr",
    "iso:country":"US",
    "sg:address":"12414 Dixie Ann Dr",
    "sg:city":"Charlotte",
    "sg:classifiers":[
        {
            "category":"Freight",
            "type":"Transportation"
        }
    ],
    "sg:phone":"+1 704 494 0400",
    "sg:postcode":"28262",
    "sg:province":"NC",
    "sg:tags":[
        "courier"
    ],
    "wof:name":"Help Personal Errands & Svcs",
    "wof:placetype":"venue"
},
  "geometry": {"coordinates":[-80.709396,35.347651],"type":"Point"}
}