{
  "type": "Feature",
  "properties": {
    "addr:full":"95 Smokey Park Hwy Asheville NC 28806",
    "addr:housenumber":"95",
    "addr:postcode":"28806",
    "addr:street":"Smokey Park Hwy",
    "iso:country":"US",
    "sg:address":"95 Smokey Park Hwy",
    "sg:city":"Asheville",
    "sg:classifiers":[
        {
            "category":"Home & Garden",
            "subcategory":"Building Materials",
            "type":"Retail Goods"
        }
    ],
    "sg:phone":"+1 828 255 9113",
    "sg:postcode":"28806",
    "sg:province":"NC",
    "wof:name":"Lowes",
    "wof:placetype":"venue"
},
  "geometry": {"coordinates":[-82.626306,35.565947],"type":"Point"}
}