{
  "type": "Feature",
  "properties": {
    "iso:country":"US",
    "sg:address":"532 Cedar Mountain Rd",
    "sg:city":"Mayodan",
    "sg:classifiers":[
        {
            "category":"Home & Garden",
            "subcategory":"Home Furnishings",
            "type":"Retail Goods"
        }
    ],
    "sg:phone":"+1 336 548 9450",
    "sg:postcode":"27027",
    "sg:province":"NC",
    "wof:name":"Griffin Berlin",
    "wof:placetype":"venue"
},
  "geometry": {"coordinates":[-79.960272,36.410964],"type":"Point"}
}