{
  "type": "Feature",
  "properties": {
    "iso:country":"US",
    "sg:address":"2218 Chestnut Ln",
    "sg:city":"Matthews",
    "sg:classifiers":[
        {
            "category":"Local Transit",
            "type":"Transportation"
        }
    ],
    "sg:phone":"+1 704 846 6458",
    "sg:postcode":"28104",
    "sg:province":"NC",
    "sg:tags":[
        "airport",
        "pas"
    ],
    "sg:website":"http://www.parkplace-nc.com",
    "wof:name":"Park Place Limousine",
    "wof:placetype":"venue"
},
  "geometry": {"coordinates":[-80.714996,35.064602],"type":"Point"}
}