{
  "type": "Feature",
  "properties": {
    "iso:country":"US",
    "sg:address":"5980 University Pkwy",
    "sg:city":"Winston Salem",
    "sg:classifiers":[
        {
            "category":"Restaurant",
            "type":"Food & Drink"
        }
    ],
    "sg:phone":"+1 336 377 2400",
    "sg:postcode":"27105",
    "sg:province":"NC",
    "sg:website":"www.fazolis.com",
    "wof:name":"Fazoli's",
    "wof:placetype":"venue"
},
  "geometry": {"coordinates":[-80.277052,36.18942],"type":"Point"}
}