{
  "type": "Feature",
  "properties": {
    "addr:full":"712 SE Maynard Rd Cary NC 27511",
    "addr:housenumber":"712",
    "addr:postcode":"27511",
    "addr:street":"Se Maynard Rd",
    "iso:country":"US",
    "sg:address":"712 SE Maynard Rd",
    "sg:city":"Cary",
    "sg:classifiers":[
        {
            "category":"Fast Food",
            "type":"Food & Drink"
        }
    ],
    "sg:phone":"+1 919 467 7577",
    "sg:postcode":"27511",
    "sg:province":"NC",
    "sg:tags":[
        "burger"
    ],
    "sg:website":"www.fiveguys.com",
    "wof:name":"Five Guys Famous Burgers and Fries",
    "wof:placetype":"venue"
},
  "geometry": {"coordinates":[-78.76415299999999,35.768964],"type":"Point"}
}