{
  "type": "Feature",
  "properties": {
    "iso:country":"US",
    "sg:address":"5882 Farringdon Pl",
    "sg:city":"Raleigh",
    "sg:classifiers":[
        {
            "category":"Professional",
            "subcategory":"Computer Services",
            "type":"Services"
        }
    ],
    "sg:phone":"+1 919 862 0123",
    "sg:postcode":"27609",
    "sg:province":"NC",
    "wof:name":"Comexperts",
    "wof:placetype":"venue"
},
  "geometry": {"coordinates":[-78.62159800000001,35.861263],"type":"Point"}
}