{
  "type": "Feature",
  "properties": {
    "addr:full":"207 Central Ave Butner NC 27509",
    "addr:housenumber":"207",
    "addr:postcode":"27509",
    "addr:street":"Central Ave",
    "iso:country":"US",
    "sg:address":"207 Central Ave",
    "sg:city":"Butner",
    "sg:classifiers":[
        {
            "category":"Shopping",
            "subcategory":"Bicycles & Sporting Goods",
            "type":"Retail Goods"
        }
    ],
    "sg:phone":"+1 919 575 8811",
    "sg:postcode":"27509",
    "sg:province":"NC",
    "sg:tags":[
        "gun",
        "gunsmith"
    ],
    "wof:name":"Rudder's Gun Svc Inc",
    "wof:placetype":"venue"
},
  "geometry": {"coordinates":[-78.757811,36.133285],"type":"Point"}
}