{
  "type": "Feature",
  "properties": {
    "addr:full":"501 Eastowne Dr Ste 150 Chapel Hill NC 27514",
    "addr:housenumber":"501",
    "addr:postcode":"27514",
    "addr:street":"Eastowne Dr Ste 150",
    "iso:country":"US",
    "sg:address":"501 Eastowne Dr Ste 150",
    "sg:city":"Chapel Hill",
    "sg:classifiers":[
        {
            "category":"Health Services",
            "subcategory":"Dentist",
            "type":"Services"
        }
    ],
    "sg:phone":"+1 919 251 9313",
    "sg:postcode":"27514",
    "sg:province":"NC",
    "wof:name":"Lohman and Sood Dental",
    "wof:placetype":"venue"
},
  "geometry": {"coordinates":[-79.006525,35.951479],"type":"Point"}
}