{
  "type": "Feature",
  "properties": {
    "iso:country":"US",
    "sg:address":"907 Cherry St",
    "sg:city":"North Wilkesboro",
    "sg:classifiers":[
        {
            "category":"Personal",
            "subcategory":"Beauty Salon",
            "type":"Services"
        }
    ],
    "sg:phone":"+1 336 838 8340",
    "sg:postcode":"28659",
    "sg:province":"NC",
    "wof:name":"Center Stage Beauty Salon",
    "wof:placetype":"venue"
},
  "geometry": {"coordinates":[-81.145664,36.158228],"type":"Point"}
}