{
  "type": "Feature",
  "properties": {
    "iso:country":"US",
    "sg:address":"11425 Candlelight Ct",
    "sg:city":"Charlotte",
    "sg:classifiers":[
        {
            "category":"Personal",
            "subcategory":"Tattoo Parlor",
            "type":"Services"
        },
        {
            "category":"Personal",
            "subcategory":"Piercing",
            "type":"Services"
        }
    ],
    "sg:phone":"+1 704 540 8422",
    "sg:postcode":"28226",
    "sg:province":"NC",
    "sg:tags":[
        "body"
    ],
    "wof:name":"Achilles Tattoo Studio",
    "wof:placetype":"venue"
},
  "geometry": {"coordinates":[-80.8673,35.076408],"type":"Point"}
}