{
  "type": "Feature",
  "properties": {
    "iso:country":"US",
    "sg:address":"171 Saint Jiles Dr",
    "sg:city":"Clayton",
    "sg:classifiers":[
        {
            "category":"Professional",
            "subcategory":"Computer Services",
            "type":"Services"
        }
    ],
    "sg:phone":"+1   ",
    "sg:postcode":"27520",
    "sg:province":"NC",
    "sg:tags":[
        "design",
        "web",
        "backup",
        "remote",
        "page"
    ],
    "wof:name":"Cyberweb Solutions",
    "wof:placetype":"venue"
},
  "geometry": {"coordinates":[-78.534808,35.620257],"type":"Point"}
}