{
  "type": "Feature",
  "properties": {
    "addr:full":"2013 Upper Ridgewood Blvd Hendersonville NC 28791",
    "addr:housenumber":"2013",
    "addr:postcode":"28791",
    "addr:street":"Upper Ridgewood Blvd",
    "iso:country":"US",
    "sg:address":"2013 Upper Ridgewood Blvd",
    "sg:city":"Hendersonville",
    "sg:classifiers":[
        {
            "category":"Building & Trades",
            "subcategory":"Plumbing",
            "type":"Services"
        }
    ],
    "sg:phone":"+1 828 692 7306",
    "sg:postcode":"28791",
    "sg:province":"NC",
    "sg:tags":[
        "contractor"
    ],
    "wof:name":"Mitchell Plumbing & Gas Piping",
    "wof:placetype":"venue"
},
  "geometry": {"coordinates":[-82.47565,35.33467],"type":"Point"}
}