{
  "type": "Feature",
  "properties": {
    "addr:full":"8088 Flay Rd Lawndale NC 28090",
    "addr:housenumber":"8088",
    "addr:postcode":"28090",
    "addr:street":"Flay Rd",
    "iso:country":"US",
    "sg:address":"8088 Flay Rd",
    "sg:city":"Lawndale",
    "sg:classifiers":[
        {
            "category":"Farming",
            "subcategory":"Livestock Farm",
            "type":"Manufacturing & Wholesale Goods"
        }
    ],
    "sg:phone":"+1 704 435 5807",
    "sg:postcode":"28090",
    "sg:province":"NC",
    "sg:tags":[
        "beef",
        "feedlot",
        "cattle"
    ],
    "wof:name":"Farm",
    "wof:placetype":"venue"
},
  "geometry": {"coordinates":[-81.47547,35.473168],"type":"Point"}
}