{
  "type": "Feature",
  "properties": {
    "iso:country":"US",
    "sg:address":"1702 Candlewood Ln",
    "sg:city":"New Bern",
    "sg:classifiers":[
        {
            "category":"Restaurant",
            "type":"Food & Drink"
        }
    ],
    "sg:phone":"+1 252 638 1188",
    "sg:postcode":"28562",
    "sg:province":"NC",
    "sg:tags":[
        "eating"
    ],
    "wof:name":"Great Wall of China Restaurant",
    "wof:placetype":"venue"
},
  "geometry": {"coordinates":[-77.091058,35.109758],"type":"Point"}
}