{
  "type": "Feature",
  "properties": {
    "iso:country":"US",
    "sg:address":"7706 Matthews-Mint Hill Rd",
    "sg:city":"Charlotte",
    "sg:classifiers":[
        {
            "category":"Professional",
            "subcategory":"Printing & Photocopies",
            "type":"Services"
        }
    ],
    "sg:phone":"+1 704 545 6776",
    "sg:postcode":"28227",
    "sg:province":"NC",
    "sg:tags":[
        "blueprinting"
    ],
    "wof:name":"Spectrum Detail Group",
    "wof:placetype":"venue"
},
  "geometry": {"coordinates":[-80.648505,35.179218],"type":"Point"}
}