{
  "type": "Feature",
  "properties": {
    "addr:full":"2627 Indian Woods Rd Windsor NC 27983",
    "addr:housenumber":"2627",
    "addr:postcode":"27983",
    "addr:street":"Indian Woods Rd",
    "iso:country":"US",
    "sg:address":"2627 Indian Woods Rd",
    "sg:city":"Windsor",
    "sg:classifiers":[
        {
            "category":"Food & Beverages",
            "subcategory":"Candy",
            "type":"Retail Goods"
        }
    ],
    "sg:phone":"+1 252 794 2245",
    "sg:postcode":"27983",
    "sg:province":"NC",
    "wof:name":"Gates County Peanut Co Inc",
    "wof:placetype":"venue"
},
  "geometry": {"coordinates":[-77.046277,35.968612],"type":"Point"}
}