{
  "type": "Feature",
  "properties": {
    "addr:full":"325 Rhyne Rd Charlotte NC 28214",
    "addr:housenumber":"325",
    "addr:postcode":"28214",
    "addr:street":"Rhyne Rd",
    "iso:country":"US",
    "sg:address":"325 Rhyne Rd",
    "sg:city":"Charlotte",
    "sg:classifiers":[
        {
            "category":"Manufacturing",
            "subcategory":"Wood Products",
            "type":"Manufacturing & Wholesale Goods"
        },
        {
            "category":"Professional",
            "subcategory":"Art Services",
            "type":"Services"
        }
    ],
    "sg:phone":"+1 704 399 9779",
    "sg:postcode":"28214",
    "sg:province":"NC",
    "sg:tags":[
        "picture",
        "frame",
        "frames-wholesale",
        "manufacturer"
    ],
    "wof:name":"Art N Frames By Ross, Harry",
    "wof:placetype":"venue"
},
  "geometry": {"coordinates":[-80.970591,35.286632],"type":"Point"}
}