{
  "type": "Feature",
  "properties": {
    "addr:full":"2225 Sedgemont Dr Winston Salem NC 27103",
    "addr:housenumber":"2225",
    "addr:postcode":"27103",
    "addr:street":"Sedgemont Dr",
    "iso:country":"US",
    "sg:address":"2225 Sedgemont Dr",
    "sg:city":"Winston Salem",
    "sg:classifiers":[
        {
            "category":"Building & Trades",
            "subcategory":"Construction",
            "type":"Services"
        }
    ],
    "sg:phone":"+1 336 659 4627",
    "sg:postcode":"27103",
    "sg:province":"NC",
    "sg:tags":[
        "floor",
        "laying",
        "contractor"
    ],
    "wof:name":"Premier Hardwood Flooring",
    "wof:placetype":"venue"
},
  "geometry": {"coordinates":[-80.369839,36.057201],"type":"Point"}
}