{
  "type": "Feature",
  "properties": {
    "iso:country":"US",
    "sg:address":"412 W 3rd St",
    "sg:city":"Pembroke",
    "sg:classifiers":[
        {
            "category":"Shopping",
            "subcategory":"Tobacco",
            "type":"Retail Goods"
        }
    ],
    "sg:phone":"+1 910 522 0606",
    "sg:postcode":"28372",
    "sg:province":"NC",
    "sg:tags":[
        "cigarette",
        "cigar",
        "dealer"
    ],
    "wof:name":"1 Stop Tobacco Shop",
    "wof:placetype":"venue"
},
  "geometry": {"coordinates":[-79.19807400000001,34.682682],"type":"Point"}
}