{
  "type": "Feature",
  "properties": {
    "addr:full":"345 Rocky Hills Rd Pittsboro NC 27312",
    "addr:housenumber":"345",
    "addr:postcode":"27312",
    "addr:street":"Rocky Hills Rd",
    "iso:country":"US",
    "sg:address":"345 Rocky Hills Rd",
    "sg:city":"Pittsboro",
    "sg:classifiers":[
        {
            "category":"Professional",
            "subcategory":"Business Services",
            "type":"Services"
        }
    ],
    "sg:phone":"+1   ",
    "sg:postcode":"27312",
    "sg:province":"NC",
    "wof:name":"Umbrella Technologies Inc",
    "wof:placetype":"venue"
},
  "geometry": {"coordinates":[-79.222177,35.696728],"type":"Point"}
}