{
  "type": "Feature",
  "properties": {
    "addr:full":"4015 Baytree Ct High Point NC 27265",
    "addr:housenumber":"4015",
    "addr:postcode":"27265",
    "addr:street":"Baytree Ct",
    "iso:country":"US",
    "sg:address":"4015 Baytree Ct",
    "sg:city":"High Point",
    "sg:classifiers":[
        {
            "category":"Banks & Credit Unions",
            "subcategory":"Financial Services",
            "type":"Services"
        }
    ],
    "sg:phone":"+1 336 887 6380",
    "sg:postcode":"27265",
    "sg:province":"NC",
    "sg:tags":[
        "company",
        "holding"
    ],
    "wof:name":"Chapmans Mirror & Glass",
    "wof:placetype":"venue"
},
  "geometry": {"coordinates":[-80.00060999999999,36.032687],"type":"Point"}
}