{
  "type": "Feature",
  "properties": {
    "addr:full":"2597 W Franklin Blvd Gastonia NC 28052",
    "addr:housenumber":"2597",
    "addr:postcode":"28052",
    "addr:street":"W Franklin Blvd",
    "iso:country":"US",
    "sg:address":"2597 W Franklin Blvd",
    "sg:city":"Gastonia",
    "sg:classifiers":[
        {
            "category":"Banks & Credit Unions",
            "subcategory":"Bank",
            "type":"Services"
        }
    ],
    "sg:phone":"+1 704 861 1965",
    "sg:postcode":"28052",
    "sg:province":"NC",
    "sg:tags":[
        "cashing",
        "check"
    ],
    "sg:website":"www.acecashexpress.com",
    "wof:name":"ACE Cash Express",
    "wof:placetype":"venue"
},
  "geometry": {"coordinates":[-81.230236,35.258361],"type":"Point"}
}