{
  "type": "Feature",
  "properties": {
    "addr:full":"1101 Court Dr Charlotte NC 28211",
    "addr:housenumber":"1101",
    "addr:postcode":"28211",
    "addr:street":"Court Dr",
    "iso:country":"US",
    "sg:address":"1101 Court Dr",
    "sg:city":"Charlotte",
    "sg:classifiers":[
        {
            "category":"Manufacturing",
            "subcategory":"Tools & Machinery",
            "type":"Manufacturing & Wholesale Goods"
        }
    ],
    "sg:phone":"+1 704 365 4110",
    "sg:postcode":"28211",
    "sg:province":"NC",
    "sg:tags":[
        "textile",
        "mfg"
    ],
    "wof:name":"Brintech",
    "wof:placetype":"venue"
},
  "geometry": {"coordinates":[-80.761625,35.16253],"type":"Point"}
}