{
  "type": "Feature",
  "properties": {
    "iso:country":"US",
    "sg:address":"333 E Six Forks Rd",
    "sg:city":"Raleigh",
    "sg:classifiers":[
        {
            "category":"Professional",
            "subcategory":"Employment Agencies",
            "type":"Services"
        }
    ],
    "sg:phone":"+1 919 828 8006",
    "sg:postcode":"27609",
    "sg:province":"NC",
    "sg:tags":[
        "opportunity"
    ],
    "wof:name":"Ultimate Staffing",
    "wof:placetype":"venue"
},
  "geometry": {"coordinates":[-78.62583600000001,35.82046],"type":"Point"}
}