{
  "type": "Feature",
  "properties": {
    "iso:country":"US",
    "sg:address":"410 N 11th St",
    "sg:city":"Wilmington",
    "sg:classifiers":[
        {
            "category":"Professional",
            "type":"Services"
        }
    ],
    "sg:phone":"+1 910 341 7721",
    "sg:postcode":"28401",
    "sg:province":"NC",
    "sg:tags":[
        "establishment"
    ],
    "wof:name":"Rankin Terrace",
    "wof:placetype":"venue"
},
  "geometry": {"coordinates":[-77.93585899999999,34.241376],"type":"Point"}
}