{
  "type": "Feature",
  "properties": {
    "iso:country":"US",
    "sg:address":"600 Griffith Rd",
    "sg:city":"Charlotte",
    "sg:classifiers":[
        {
            "category":"Wholesale",
            "subcategory":"Groceries",
            "type":"Manufacturing & Wholesale Goods"
        }
    ],
    "sg:phone":"+1 704 529 4456",
    "sg:postcode":"28217",
    "sg:province":"NC",
    "sg:tags":[
        "food",
        "product"
    ],
    "wof:name":"Distribuidora LA Victoria",
    "wof:placetype":"venue"
},
  "geometry": {"coordinates":[-80.878406,35.161257],"type":"Point"}
}