{
  "type": "Feature",
  "properties": {
    "addr:full":"4400 State Hwy 49 S Harrisburg NC 28075",
    "addr:housenumber":"4400",
    "addr:postcode":"28075",
    "addr:street":"State Hwy 49 S",
    "iso:country":"US",
    "sg:address":"4400 State Hwy 49 S",
    "sg:city":"Harrisburg",
    "sg:classifiers":[
        {
            "category":"Personal",
            "subcategory":"Barber",
            "type":"Services"
        }
    ],
    "sg:phone":"+1 704 455 2955",
    "sg:postcode":"28075",
    "sg:province":"NC",
    "wof:name":"Harrisburg Barber Shop",
    "wof:placetype":"venue"
},
  "geometry": {"coordinates":[-80.649629,35.322212],"type":"Point"}
}