{
  "type": "Feature",
  "properties": {
    "iso:country":"US",
    "sg:address":"128 Huntsmoor Dr",
    "sg:city":"Charlotte",
    "sg:classifiers":[
        {
            "category":"Wholesale",
            "subcategory":"Machinery & Supplies",
            "type":"Manufacturing & Wholesale Goods"
        }
    ],
    "sg:phone":"+1 704 527 9771",
    "sg:postcode":"28217",
    "sg:province":"NC",
    "sg:tags":[
        "dyer",
        "cleaners",
        "equipment"
    ],
    "wof:name":"Fetterson Dry Cleaning Svc",
    "wof:placetype":"venue"
},
  "geometry": {"coordinates":[-80.892948,35.137177],"type":"Point"}
}