{
  "type": "Feature",
  "properties": {
    "iso:country":"US",
    "sg:address":"215 N 35th St",
    "sg:city":"Morehead City",
    "sg:classifiers":[
        {
            "category":"Professional",
            "type":"Services"
        }
    ],
    "sg:phone":"+1 252 247 2413",
    "sg:postcode":"28557",
    "sg:province":"NC",
    "sg:tags":[
        "establishment"
    ],
    "wof:name":"Sleep Analysis Inc",
    "wof:placetype":"venue"
},
  "geometry": {"coordinates":[-76.753516,34.727543],"type":"Point"}
}