{
  "type": "Feature",
  "properties": {
    "addr:full":"1103 East St Pittsboro NC 27312",
    "addr:housenumber":"1103",
    "addr:postcode":"27312",
    "addr:street":"East St",
    "iso:country":"US",
    "sg:address":"1103 East St",
    "sg:city":"Pittsboro",
    "sg:classifiers":[
        {
            "category":"Wholesale",
            "subcategory":"Farm Supplies",
            "type":"Manufacturing & Wholesale Goods"
        },
        {
            "category":"Shopping",
            "type":"Retail Goods"
        }
    ],
    "sg:phone":"+1 919 542 2454",
    "sg:postcode":"27312",
    "sg:province":"NC",
    "sg:tags":[
        "feed",
        "animal"
    ],
    "wof:name":"Pittsboro Farms & Garden Inc",
    "wof:placetype":"venue"
},
  "geometry": {"coordinates":[-79.157932,35.719644],"type":"Point"}
}