{
  "type": "Feature",
  "properties": {
    "iso:country":"US",
    "sg:address":"201 S Estes Dr",
    "sg:city":"Chapel Hill",
    "sg:classifiers":[
        {
            "category":"Shopping",
            "subcategory":"Jewelry",
            "type":"Retail Goods"
        }
    ],
    "sg:phone":"+1 919 967 2976",
    "sg:postcode":"27514",
    "sg:province":"NC",
    "sg:tags":[
        "jeweler"
    ],
    "wof:name":"Saslow's Jewelers",
    "wof:placetype":"venue"
},
  "geometry": {"coordinates":[-79.02960899999999,35.927358],"type":"Point"}
}