{
  "type": "Feature",
  "properties": {
    "iso:country":"US",
    "sg:address":"200 N Greensboro St",
    "sg:city":"Carrboro",
    "sg:classifiers":[
        {
            "category":"Professional",
            "subcategory":"Business Services",
            "type":"Services"
        }
    ],
    "sg:phone":"+1 919 932 9662",
    "sg:postcode":"27510",
    "sg:province":"NC",
    "sg:tags":[
        "interior",
        "consultant",
        "design",
        "decorator"
    ],
    "wof:name":"Gwyn Ronsick Design",
    "wof:placetype":"venue"
},
  "geometry": {"coordinates":[-79.072249,35.911958],"type":"Point"}
}