{
  "type": "Feature",
  "properties": {
    "addr:full":"90 Elk Mountain Rd Asheville NC 28804",
    "addr:housenumber":"90",
    "addr:postcode":"28804",
    "addr:street":"Elk Mountain Rd",
    "iso:country":"US",
    "sg:address":"90 Elk Mountain Rd",
    "sg:city":"Asheville",
    "sg:classifiers":[
        {
            "category":"Government",
            "subcategory":"Police Station",
            "type":"Public Place"
        }
    ],
    "sg:phone":"+1 828 253 4887",
    "sg:postcode":"28804",
    "sg:province":"NC",
    "sg:tags":[
        "protection"
    ],
    "wof:name":"Town of Woodfin",
    "wof:placetype":"venue"
},
  "geometry": {"coordinates":[-82.58266399999999,35.631692],"type":"Point"}
}