{
  "type": "Feature",
  "properties": {
    "iso:country":"US",
    "sg:address":"4047 Cates Loop Rd",
    "sg:city":"Burlington",
    "sg:classifiers":[
        {
            "category":"Building & Trades",
            "subcategory":"Plumbing",
            "type":"Services"
        }
    ],
    "sg:phone":"+1 336 578 9151",
    "sg:postcode":"27217",
    "sg:province":"NC",
    "sg:tags":[
        "contractor"
    ],
    "wof:name":"Eastwood Shtmtl Fabrication",
    "wof:placetype":"venue"
},
  "geometry": {"coordinates":[-79.31978599999999,36.185468],"type":"Point"}
}