{
  "type": "Feature",
  "properties": {
    "addr:full":"1238 Union Cross Rd Kernersville NC 27284",
    "addr:housenumber":"1238",
    "addr:postcode":"27284",
    "addr:street":"Union Cross Rd",
    "iso:country":"US",
    "sg:address":"1238 Union Cross Rd",
    "sg:city":"Kernersville",
    "sg:classifiers":[
        {
            "category":"Railroad",
            "type":"Transportation"
        }
    ],
    "sg:phone":"+1 336 993 1803",
    "sg:postcode":"27284",
    "sg:province":"NC",
    "sg:tags":[
        "operator",
        "line"
    ],
    "wof:name":"RR Sign Maintenance",
    "wof:placetype":"venue"
},
  "geometry": {"coordinates":[-80.08437000000001,36.098899],"type":"Point"}
}