{
  "type": "Feature",
  "properties": {
    "iso:country":"US",
    "sg:address":"155 Charles Rd",
    "sg:city":"King",
    "sg:classifiers":[
        {
            "category":"Retail",
            "subcategory":"Auto Repair",
            "type":"Services"
        }
    ],
    "sg:phone":"+1 336 983 5927",
    "sg:postcode":"27021",
    "sg:province":"NC",
    "sg:tags":[
        "repairing",
        "automobile"
    ],
    "wof:name":"Hawkins Automotive",
    "wof:placetype":"venue"
},
  "geometry": {"coordinates":[-80.37964100000001,36.273092],"type":"Point"}
}