{
  "type": "Feature",
  "properties": {
    "addr:full":"322 E Fisher St Salisbury NC 28144",
    "addr:housenumber":"322",
    "addr:postcode":"28144",
    "addr:street":"E Fisher St",
    "iso:country":"US",
    "sg:address":"322 E Fisher St",
    "sg:city":"Salisbury",
    "sg:classifiers":[
        {
            "category":"Autos & Motor Vehicles",
            "subcategory":"Fuel & Gas Station",
            "type":"Retail Goods"
        }
    ],
    "sg:phone":"+1 704 883 0400",
    "sg:postcode":"28144",
    "sg:province":"NC",
    "sg:tags":[
        "station",
        "gasoline"
    ],
    "wof:name":"Broad Street Shell",
    "wof:placetype":"venue"
},
  "geometry": {"coordinates":[-80.46801499999999,35.664043],"type":"Point"}
}