{
  "type": "Feature",
  "properties": {
    "iso:country":"US",
    "sg:address":"510 Realty St SW",
    "sg:city":"Lenoir",
    "sg:classifiers":[
        {
            "category":"Education",
            "subcategory":"Dance Studio",
            "type":"Public Place"
        }
    ],
    "sg:phone":"+1 828 754 9633",
    "sg:postcode":"28645",
    "sg:province":"NC",
    "sg:tags":[
        "instruction",
        "dancing"
    ],
    "wof:name":"Starsteps Dance Ctr",
    "wof:placetype":"venue"
},
  "geometry": {"coordinates":[-81.543723,35.904122],"type":"Point"}
}