{
  "type": "Feature",
  "properties": {
    "addr:full":"7631 Sharon Lakes Rd Charlotte NC 28210",
    "addr:housenumber":"7631",
    "addr:postcode":"28210",
    "addr:street":"Sharon Lakes Rd",
    "iso:country":"US",
    "sg:address":"7631 Sharon Lakes Rd",
    "sg:city":"Charlotte",
    "sg:classifiers":[
        {
            "category":"Personal",
            "subcategory":"Beauty Salon",
            "type":"Services"
        }
    ],
    "sg:phone":"+1 704 752 6155",
    "sg:postcode":"28210",
    "sg:province":"NC",
    "wof:name":"Nu Faces",
    "wof:placetype":"venue"
},
  "geometry": {"coordinates":[-80.87564500000001,35.127777],"type":"Point"}
}