{
  "type": "Feature",
  "properties": {
    "iso:country":"US",
    "sg:address":"941 Camp Creek Rd",
    "sg:city":"Iron Station",
    "sg:classifiers":[
        {
            "category":"Professional",
            "type":"Services"
        }
    ],
    "sg:phone":"+1 704 732 0954",
    "sg:postcode":"28080",
    "sg:province":"NC",
    "wof:name":"Davis Tree Works Inc",
    "wof:placetype":"venue"
},
  "geometry": {"coordinates":[-81.142715,35.481948],"type":"Point"}
}