{
  "type": "Feature",
  "properties": {
    "addr:full":"1309 Carthage St Sanford NC 27330",
    "addr:housenumber":"1309",
    "addr:postcode":"27330",
    "addr:street":"Carthage St",
    "iso:country":"US",
    "sg:address":"1309 Carthage St",
    "sg:city":"Sanford",
    "sg:classifiers":[
        {
            "category":"Health Services",
            "subcategory":"Doctor",
            "type":"Services"
        }
    ],
    "sg:phone":"+1 919 776 7550",
    "sg:postcode":"27330",
    "sg:province":"NC",
    "sg:tags":[
        "physician",
        "surgeon"
    ],
    "wof:name":"Asheville Hematology & Onclgy",
    "wof:placetype":"venue"
},
  "geometry": {"coordinates":[-79.191205,35.463265],"type":"Point"}
}