{
  "type": "Feature",
  "properties": {
    "addr:full":"6869 Bethel Church Rd Gibsonville NC 27249",
    "addr:housenumber":"6869",
    "addr:postcode":"27249",
    "addr:street":"Bethel Church Rd",
    "iso:country":"US",
    "sg:address":"6869 Bethel Church Rd",
    "sg:city":"Gibsonville",
    "sg:classifiers":[
        {
            "category":"Retail",
            "subcategory":"Repair Shop",
            "type":"Services"
        }
    ],
    "sg:phone":"+1 336 449 6604",
    "sg:postcode":"27249",
    "sg:province":"NC",
    "sg:tags":[
        "taxidermist"
    ],
    "wof:name":"Wyrick's Taxidermy",
    "wof:placetype":"venue"
},
  "geometry": {"coordinates":[-79.55762,36.103554],"type":"Point"}
}