{
  "type": "Feature",
  "properties": {
    "addr:full":"2040 Rankin Mill Rd Greensboro NC 27405",
    "addr:housenumber":"2040",
    "addr:postcode":"27405",
    "addr:street":"Rankin Mill Rd",
    "iso:country":"US",
    "sg:address":"2040 Rankin Mill Rd",
    "sg:city":"Greensboro",
    "sg:classifiers":[
        {
            "category":"Personal",
            "subcategory":"Beauty Salon",
            "type":"Services"
        }
    ],
    "sg:phone":"+1   ",
    "sg:postcode":"27405",
    "sg:province":"NC",
    "sg:tags":[
        "shop"
    ],
    "wof:name":"Queen Nails",
    "wof:placetype":"venue"
},
  "geometry": {"coordinates":[-79.710954,36.147057],"type":"Point"}
}