{
  "type": "Feature",
  "properties": {
    "iso:country":"US",
    "sg:address":"1831 Weeksville Rd",
    "sg:city":"Elizabeth City",
    "sg:classifiers":[
        {
            "category":"Shopping",
            "subcategory":"Gifts & Souvenirs",
            "type":"Retail Goods"
        }
    ],
    "sg:phone":"+1 252 331 1430",
    "sg:postcode":"27909",
    "sg:province":"NC",
    "sg:tags":[
        "shop"
    ],
    "sg:website":"www.hoffergallery.com",
    "wof:name":"Hoffer Gallery",
    "wof:placetype":"venue"
},
  "geometry": {"coordinates":[-76.21379399999999,36.276931],"type":"Point"}
}