{
  "type": "Feature",
  "properties": {
    "iso:country":"US",
    "sg:address":"2910 Mount Holly-Huntersville Rd",
    "sg:city":"Charlotte",
    "sg:classifiers":[
        {
            "category":"Personal",
            "subcategory":"Beauty Salon",
            "type":"Services"
        }
    ],
    "sg:phone":"+1 704 394 1878",
    "sg:postcode":"28214",
    "sg:province":"NC",
    "wof:name":"Nails 4",
    "wof:placetype":"venue"
},
  "geometry": {"coordinates":[-80.95255400000001,35.320637],"type":"Point"}
}