{
  "type": "Feature",
  "properties": {
    "addr:full":"1503 Elm St Sanford NC 27330",
    "addr:housenumber":"1503",
    "addr:postcode":"27330",
    "addr:street":"Elm St",
    "iso:country":"US",
    "sg:address":"1503 Elm St",
    "sg:city":"Sanford",
    "sg:classifiers":[
        {
            "category":"Professional",
            "subcategory":"Lawyer & Legal Services",
            "type":"Services"
        }
    ],
    "sg:phone":"+1   ",
    "sg:postcode":"27330",
    "sg:province":"NC",
    "sg:tags":[
        "law"
    ],
    "wof:name":"Wishart Jr Frank W Atty At Lw",
    "wof:placetype":"venue"
},
  "geometry": {"coordinates":[-79.162825,35.466522],"type":"Point"}
}