{
  "type": "Feature",
  "properties": {
    "iso:country":"US",
    "sg:address":"915 S Main St",
    "sg:city":"Laurinburg",
    "sg:classifiers":[
        {
            "category":"Health Services",
            "subcategory":"Health Practitioner",
            "type":"Services"
        }
    ],
    "sg:phone":"+1 910 276 1125",
    "sg:postcode":"28352",
    "sg:province":"NC",
    "sg:tags":[
        "audiologists"
    ],
    "wof:name":"Avada Audiology & Hearing Care",
    "wof:placetype":"venue"
},
  "geometry": {"coordinates":[-79.46651300000001,34.767029],"type":"Point"}
}