{
  "type": "Feature",
  "properties": {
    "iso:country":"US",
    "sg:address":"341 Bayshore Dr",
    "sg:city":"Wilmington",
    "sg:classifiers":[
        {
            "category":"Building & Trades",
            "subcategory":"Construction",
            "type":"Services"
        }
    ],
    "sg:phone":"+1 910 686 6881",
    "sg:postcode":"28411",
    "sg:province":"NC",
    "sg:tags":[
        "contractor"
    ],
    "wof:name":"Pendover Development Inc",
    "wof:placetype":"venue"
},
  "geometry": {"coordinates":[-77.803416,34.277859],"type":"Point"}
}