{
  "type": "Feature",
  "properties": {
    "addr:full":"33 N College Ave Newton NC 28658",
    "addr:housenumber":"33",
    "addr:postcode":"28658",
    "addr:street":"N College Ave",
    "iso:country":"US",
    "sg:address":"33 N College Ave",
    "sg:city":"Newton",
    "sg:classifiers":[
        {
            "category":"Shopping",
            "subcategory":"Pharmacy",
            "type":"Retail Goods"
        }
    ],
    "sg:phone":"+1 828 464 1222",
    "sg:postcode":"28658",
    "sg:province":"NC",
    "sg:tags":[
        "equipment",
        "hospital",
        "supply"
    ],
    "wof:name":"Walker's Pharmacy",
    "wof:placetype":"venue"
},
  "geometry": {"coordinates":[-81.221521,35.662862],"type":"Point"}
}