{
  "type": "Feature",
  "properties": {
    "addr:full":"356 Turtle Shell Rd Richlands NC 28574",
    "addr:housenumber":"356",
    "addr:postcode":"28574",
    "addr:street":"Turtle Shell Rd",
    "iso:country":"US",
    "sg:address":"356 Turtle Shell Rd",
    "sg:city":"Richlands",
    "sg:classifiers":[
        {
            "category":"Farming",
            "subcategory":"Poultry Farm",
            "type":"Manufacturing & Wholesale Goods"
        }
    ],
    "sg:phone":"+1 910 324 1156",
    "sg:postcode":"28574",
    "sg:province":"NC",
    "sg:tags":[
        "egg"
    ],
    "wof:name":"Sandlins Inc",
    "wof:placetype":"venue"
},
  "geometry": {"coordinates":[-77.573954,34.883328],"type":"Point"}
}