{
  "type": "Feature",
  "properties": {
    "iso:country":"US",
    "sg:address":"3305 Healy Dr",
    "sg:city":"Winston Salem",
    "sg:classifiers":[
        {
            "category":"Professional",
            "subcategory":"Lawyer & Legal Services",
            "type":"Services"
        }
    ],
    "sg:phone":"+1 336 768 1515",
    "sg:postcode":"27103",
    "sg:province":"NC",
    "sg:tags":[
        "attorney"
    ],
    "wof:name":"Tash & Kurtz",
    "wof:placetype":"venue"
},
  "geometry": {"coordinates":[-80.30612000000001,36.075531],"type":"Point"}
}