{
  "type": "Feature",
  "properties": {
    "iso:country":"US",
    "sg:address":"3728 Beckerdite Rd",
    "sg:city":"Sophia",
    "sg:classifiers":[
        {
            "category":"Building & Trades",
            "subcategory":"Construction",
            "type":"Services"
        }
    ],
    "sg:phone":"+1 336 495 1811",
    "sg:postcode":"27350",
    "sg:province":"NC",
    "sg:tags":[
        "paving",
        "contractor"
    ],
    "wof:name":"Loflin's Paving",
    "wof:placetype":"venue"
},
  "geometry": {"coordinates":[-79.89279500000001,35.797149],"type":"Point"}
}