{
  "type": "Feature",
  "properties": {
    "addr:full":"2557 S Church St Burlington NC 27215",
    "addr:housenumber":"2557",
    "addr:postcode":"27215",
    "addr:street":"S Church St",
    "iso:country":"US",
    "sg:address":"2557 S Church St",
    "sg:city":"Burlington",
    "sg:classifiers":[
        {
            "category":"Personal",
            "subcategory":"Beauty Salon",
            "type":"Services"
        }
    ],
    "sg:phone":"+1 336 584 9672",
    "sg:postcode":"27215",
    "sg:province":"NC",
    "sg:tags":[
        "shop"
    ],
    "wof:name":"Sheer Styles Salon",
    "wof:placetype":"venue"
},
  "geometry": {"coordinates":[-79.480018,36.081002],"type":"Point"}
}