{
  "type": "Feature",
  "properties": {
    "addr:full":"6207 New Hope Church Rd Marshville NC 28103",
    "addr:housenumber":"6207",
    "addr:postcode":"28103",
    "addr:street":"New Hope Church Rd",
    "iso:country":"US",
    "sg:address":"6207 New Hope Church Rd",
    "sg:city":"Marshville",
    "sg:classifiers":[
        {
            "category":"Professional",
            "type":"Services"
        }
    ],
    "sg:phone":"+1 704 385 9735",
    "sg:postcode":"28103",
    "sg:province":"NC",
    "wof:name":"CCS",
    "wof:placetype":"venue"
},
  "geometry": {"coordinates":[-80.39243999999999,35.100563],"type":"Point"}
}