{
  "type": "Feature",
  "properties": {
    "iso:country":"US",
    "sg:address":"6804 Idlewild Brook Ln",
    "sg:city":"Charlotte",
    "sg:classifiers":[
        {
            "category":"Wholesale",
            "subcategory":"Vending Machines",
            "type":"Manufacturing & Wholesale Goods"
        }
    ],
    "sg:phone":"+1 704 531 6552",
    "sg:postcode":"28212",
    "sg:province":"NC",
    "sg:tags":[
        "operator"
    ],
    "wof:name":"Pyramid Vending",
    "wof:placetype":"venue"
},
  "geometry": {"coordinates":[-80.735405,35.182871],"type":"Point"}
}