{
  "type": "Feature",
  "properties": {
    "addr:full":"500 W Main St Glen Alpine NC 28655",
    "addr:housenumber":"500",
    "addr:postcode":"28655",
    "addr:street":"W Main St Glen",
    "iso:country":"US",
    "sg:address":"500 W Main St",
    "sg:city":"Glen Alpine",
    "sg:classifiers":[
        {
            "category":"Restaurant",
            "type":"Food & Drink"
        }
    ],
    "sg:phone":"+1 828 584 4111",
    "sg:postcode":"28655",
    "sg:province":"NC",
    "wof:name":"Doogie's Pizza",
    "wof:placetype":"venue"
},
  "geometry": {"coordinates":[-81.78305899999999,35.726022],"type":"Point"}
}