{
  "type": "Feature",
  "properties": {
    "addr:full":"310 N Tryon St Charlotte NC 28202",
    "addr:housenumber":"310",
    "addr:postcode":"28202",
    "addr:street":"N Tryon St",
    "iso:country":"US",
    "sg:address":"310 N Tryon St",
    "sg:city":"Charlotte",
    "sg:classifiers":[
        {
            "category":"Education",
            "subcategory":"Library",
            "type":"Public Place"
        }
    ],
    "sg:phone":"+1 704 336 2980",
    "sg:postcode":"28202",
    "sg:province":"NC",
    "wof:name":"Robinson-Spangler Carolina Rm",
    "wof:placetype":"venue"
},
  "geometry": {"coordinates":[-80.839822,35.229374],"type":"Point"}
}