{
  "type": "Feature",
  "properties": {
    "iso:country":"US",
    "sg:address":"7907 Buck Deans Rd",
    "sg:city":"Middlesex",
    "sg:classifiers":[
        {
            "category":"Social Services",
            "type":"Services"
        }
    ],
    "sg:phone":"+1 252 235 2161",
    "sg:postcode":"27557",
    "sg:province":"NC",
    "sg:tags":[
        "organization",
        "welfare"
    ],
    "sg:website":"www.fwbchildrenshome.org",
    "wof:name":"Free Will Baptist Children's",
    "wof:placetype":"venue"
},
  "geometry": {"coordinates":[-78.209585,35.815867],"type":"Point"}
}