{
  "type": "Feature",
  "properties": {
    "iso:country":"US",
    "sg:address":"100 Beechtree Dr",
    "sg:city":"Shiloh",
    "sg:classifiers":[
        {
            "category":"Professional",
            "type":"Services"
        }
    ],
    "sg:phone":"+1 252 336 4726",
    "sg:postcode":"27974",
    "sg:province":"NC",
    "wof:name":"Richard C King Dr",
    "wof:placetype":"venue"
},
  "geometry": {"coordinates":[-76.09293099999999,36.254047],"type":"Point"}
}