{
  "type": "Feature",
  "properties": {
    "iso:country":"US",
    "sg:address":"371 Friendly Grove Church Rd",
    "sg:city":"Millers Creek",
    "sg:classifiers":[
        {
            "category":"Personal",
            "subcategory":"Beauty Salon",
            "type":"Services"
        }
    ],
    "sg:phone":"+1 336 838 5613",
    "sg:postcode":"28651",
    "sg:province":"NC",
    "sg:tags":[
        "shop"
    ],
    "wof:name":"Patricia's Hair Cutting",
    "wof:placetype":"venue"
},
  "geometry": {"coordinates":[-81.22413299999999,36.195214],"type":"Point"}
}