{
  "type": "Feature",
  "properties": {
    "iso:country":"US",
    "sg:address":"180 Glenn Bridge Rd",
    "sg:city":"Arden",
    "sg:classifiers":[
        {
            "category":"Shopping",
            "subcategory":"Stationery & Office Supplies",
            "type":"Retail Goods"
        }
    ],
    "sg:phone":"+1 828 681 8797",
    "sg:postcode":"28704",
    "sg:province":"NC",
    "sg:tags":[
        "stamp",
        "janitorial",
        "form",
        "custom"
    ],
    "wof:name":"Hoyle Office Supplies Inc",
    "wof:placetype":"venue"
},
  "geometry": {"coordinates":[-82.528628,35.462584],"type":"Point"}
}