{
  "type": "Feature",
  "properties": {
    "addr:full":"12 Culvern St Asheville NC 28804",
    "addr:housenumber":"12",
    "addr:postcode":"28804",
    "addr:street":"Culvern St",
    "iso:country":"US",
    "sg:address":"12 Culvern St",
    "sg:city":"Asheville",
    "sg:classifiers":[
        {
            "category":"Education",
            "subcategory":"School",
            "type":"Public Place"
        }
    ],
    "sg:phone":"+1 828 252 7896",
    "sg:postcode":"28804",
    "sg:province":"NC",
    "sg:tags":[
        "organization",
        "religious"
    ],
    "sg:website":"www.ashevillecatholic.org",
    "wof:name":"Asheville Catholic School",
    "wof:placetype":"venue"
},
  "geometry": {"coordinates":[-82.551114,35.630972],"type":"Point"}
}