{
  "type": "Feature",
  "properties": {
    "iso:country":"US",
    "sg:address":"109 E Broad St",
    "sg:city":"Elizabethtown",
    "sg:classifiers":[
        {
            "category":"Shopping",
            "type":"Retail Goods"
        }
    ],
    "sg:phone":"+1 910 879 1002",
    "sg:postcode":"28337",
    "sg:province":"NC",
    "sg:tags":[
        "mexican"
    ],
    "wof:name":"Nelly's Mexican Store",
    "wof:placetype":"venue"
},
  "geometry": {"coordinates":[-78.605695,34.62895],"type":"Point"}
}