{
  "type": "Feature",
  "properties": {
    "iso:country":"US",
    "sg:address":"2250 7th St",
    "sg:city":"Salisbury",
    "sg:classifiers":[
        {
            "category":"Personal",
            "type":"Services"
        },
        {
            "category":"Personal",
            "subcategory":"Beauty Salon",
            "type":"Services"
        }
    ],
    "sg:phone":"+1 704 637 9648",
    "sg:postcode":"28144",
    "sg:province":"NC",
    "sg:tags":[
        "shop"
    ],
    "wof:name":"Vallie's Place",
    "wof:placetype":"venue"
},
  "geometry": {"coordinates":[-80.45650000000001,35.705452],"type":"Point"}
}