{
  "type": "Feature",
  "properties": {
    "addr:full":"28 Durham St Asheville NC 28806",
    "addr:housenumber":"28",
    "addr:postcode":"28806",
    "addr:street":"Durham St",
    "iso:country":"US",
    "sg:address":"28 Durham St",
    "sg:city":"Asheville",
    "sg:classifiers":[
        {
            "category":"Professional",
            "subcategory":"Management & Consulting",
            "type":"Services"
        }
    ],
    "sg:phone":"+1   ",
    "sg:postcode":"28806",
    "sg:province":"NC",
    "sg:tags":[
        "business"
    ],
    "wof:name":"Tri Star",
    "wof:placetype":"venue"
},
  "geometry": {"coordinates":[-82.58795600000001,35.572022],"type":"Point"}
}