{
  "type": "Feature",
  "properties": {
    "iso:country":"US",
    "sg:address":"3503 Weddington Rd",
    "sg:city":"Monroe",
    "sg:classifiers":[
        {
            "category":"Food & Beverages",
            "subcategory":"Groceries & Convenience Stores",
            "type":"Retail Goods"
        }
    ],
    "sg:phone":"+1 704 226 1138",
    "sg:postcode":"28110",
    "sg:province":"NC",
    "wof:name":"Saveway",
    "wof:placetype":"venue"
},
  "geometry": {"coordinates":[-80.614746,34.987227],"type":"Point"}
}