{
  "type": "Feature",
  "properties": {
    "iso:country":"US",
    "sg:address":"1271 Stanley St",
    "sg:city":"Mount Holly",
    "sg:classifiers":[
        {
            "category":"Retail",
            "subcategory":"Auto Repair",
            "type":"Services"
        }
    ],
    "sg:phone":"+1   ",
    "sg:postcode":"28144",
    "sg:province":"NC",
    "sg:tags":[
        "automotive"
    ],
    "wof:name":"Hansel Alignment Service",
    "wof:placetype":"venue"
},
  "geometry": {"coordinates":[-80.49252300000001,35.663033],"type":"Point"}
}