{
  "type": "Feature",
  "properties": {
    "iso:country":"US",
    "sg:address":"301 E Park Ave",
    "sg:city":"Charlotte",
    "sg:classifiers":[
        {
            "category":"Professional",
            "type":"Services"
        }
    ],
    "sg:phone":"+1 704 370 0983",
    "sg:postcode":"28203",
    "sg:province":"NC",
    "wof:name":"Homeroom Inc",
    "wof:placetype":"venue"
},
  "geometry": {"coordinates":[-80.853281,35.211937],"type":"Point"}
}