{
  "type": "Feature",
  "properties": {
    "addr:full":"119 Diggie Do Dr Chocowinity NC 27817",
    "addr:housenumber":"119",
    "addr:postcode":"27817",
    "addr:street":"Diggie Do Dr",
    "iso:country":"US",
    "sg:address":"119 Diggie Do Dr",
    "sg:city":"Chocowinity",
    "sg:classifiers":[
        {
            "category":"Freight",
            "type":"Transportation"
        }
    ],
    "sg:phone":"+1 252 946 7663",
    "sg:postcode":"27817",
    "sg:province":"NC",
    "sg:tags":[
        "mobile",
        "home"
    ],
    "wof:name":"Danny's Mobile Home Movers",
    "wof:placetype":"venue"
},
  "geometry": {"coordinates":[-77.098024,35.478403],"type":"Point"}
}