{
  "type": "Feature",
  "properties": {
    "addr:full":"6321 Andrew Jackson Hwy Laurel Hill NC 28351",
    "addr:housenumber":"6321",
    "addr:postcode":"28351",
    "addr:street":"Andrew Jackson Hwy",
    "iso:country":"US",
    "sg:address":"6321 Andrew Jackson Hwy",
    "sg:city":"Laurel Hill",
    "sg:classifiers":[
        {
            "category":"Home & Garden",
            "subcategory":"Furniture",
            "type":"Retail Goods"
        }
    ],
    "sg:phone":"+1 910 462 2500",
    "sg:postcode":"28351",
    "sg:province":"NC",
    "sg:website":"www.eastcoastumbrella.com",
    "wof:name":"East Coast Umbrella Inc",
    "wof:placetype":"venue"
},
  "geometry": {"coordinates":[-79.59836199999999,34.83753],"type":"Point"}
}