{
  "type": "Feature",
  "properties": {
    "iso:country":"US",
    "sg:address":"1301 Beaver Creek Commons Dr",
    "sg:city":"Apex",
    "sg:classifiers":[
        {
            "category":"Shopping",
            "subcategory":"Department Store",
            "type":"Retail Goods"
        }
    ],
    "sg:phone":"+1 919 387 7499",
    "sg:postcode":"27502",
    "sg:province":"NC",
    "sg:website":"www.kohls.com",
    "wof:name":"Kohl's Store",
    "wof:placetype":"venue"
},
  "geometry": {"coordinates":[-78.87647,35.746057],"type":"Point"}
}