{
  "type": "Feature",
  "properties": {
    "addr:full":"2628 Melrose Ave Durham NC 27704",
    "addr:housenumber":"2628",
    "addr:postcode":"27704",
    "addr:street":"Melrose Ave",
    "iso:country":"US",
    "sg:address":"2628 Melrose Ave",
    "sg:city":"Durham",
    "sg:classifiers":[
        {
            "category":"Social Services",
            "subcategory":"Adult Care",
            "type":"Services"
        }
    ],
    "sg:phone":"+1 919 688 4493",
    "sg:postcode":"27704",
    "sg:province":"NC",
    "sg:tags":[
        "residential"
    ],
    "wof:name":"Boonehaven LLC",
    "wof:placetype":"venue"
},
  "geometry": {"coordinates":[-78.849783,36.013295],"type":"Point"}
}