{
  "type": "Feature",
  "properties": {
    "iso:country":"US",
    "sg:address":"101 W Main St",
    "sg:city":"Rockwell",
    "sg:classifiers":[
        {
            "category":"Personal",
            "subcategory":"Beauty Salon",
            "type":"Services"
        }
    ],
    "sg:phone":"+1 704 279 2179",
    "sg:postcode":"28138",
    "sg:province":"NC",
    "wof:name":"Brenda's Beauty Shop",
    "wof:placetype":"venue"
},
  "geometry": {"coordinates":[-80.40795799999999,35.552171],"type":"Point"}
}