{
  "type": "Feature",
  "properties": {
    "iso:country":"US",
    "sg:address":"111 W Twelve Oaks Rd",
    "sg:city":"Raeford",
    "sg:classifiers":[
        {
            "category":"Building & Trades",
            "subcategory":"Construction",
            "type":"Services"
        }
    ],
    "sg:phone":"+1 910 425 6800",
    "sg:postcode":"28376",
    "sg:province":"NC",
    "sg:tags":[
        "house"
    ],
    "wof:name":"Vics Home Improvement & Repair",
    "wof:placetype":"venue"
},
  "geometry": {"coordinates":[-79.042941,34.959362],"type":"Point"}
}