{
  "type": "Feature",
  "properties": {
    "iso:country":"US",
    "sg:address":"2208 Van Aiken Cir",
    "sg:city":"Shelby",
    "sg:classifiers":[
        {
            "category":"Real Estate",
            "subcategory":"Real Estate Agent",
            "type":"Services"
        }
    ],
    "sg:phone":"+1 704 481 2989",
    "sg:postcode":"28150",
    "sg:province":"NC",
    "wof:name":"AM Rentals LLC",
    "wof:placetype":"venue"
},
  "geometry": {"coordinates":[-81.460078,35.287085],"type":"Point"}
}