{
  "type": "Feature",
  "properties": {
    "addr:full":"1309 Canal Dr Sunset Beach NC 28468",
    "addr:housenumber":"1309",
    "addr:postcode":"28468",
    "addr:street":"Canal Dr",
    "iso:country":"US",
    "sg:address":"1309 Canal Dr",
    "sg:city":"Sunset Beach",
    "sg:classifiers":[
        {
            "category":"Professional",
            "type":"Services"
        },
        {
            "category":"Organizations",
            "subcategory":"Community Association",
            "type":"Services"
        }
    ],
    "sg:phone":"+1 910 579 2227",
    "sg:postcode":"28468",
    "sg:province":"NC",
    "sg:tags":[
        "establishment"
    ],
    "wof:name":"Wit's End",
    "wof:placetype":"venue"
},
  "geometry": {"coordinates":[-78.498319,33.87121],"type":"Point"}
}