{
  "type": "Feature",
  "properties": {
    "addr:full":"3301 Jones Sausage Rd Garner NC 27529",
    "addr:housenumber":"3301",
    "addr:postcode":"27529",
    "addr:street":"Jones Sausage Rd",
    "iso:country":"US",
    "sg:address":"3301 Jones Sausage Rd",
    "sg:city":"Garner",
    "sg:classifiers":[
        {
            "category":"Freight",
            "type":"Transportation"
        }
    ],
    "sg:phone":"+1 919 779 4334",
    "sg:postcode":"27529",
    "sg:province":"NC",
    "sg:tags":[
        "trucking"
    ],
    "wof:name":"Hayes Transport",
    "wof:placetype":"venue"
},
  "geometry": {"coordinates":[-78.573387,35.735879],"type":"Point"}
}