{
  "type": "Feature",
  "properties": {
    "iso:country":"US",
    "sg:address":"121 Ashford Hollow Ln",
    "sg:city":"Mooresville",
    "sg:classifiers":[
        {
            "category":"Health Services",
            "subcategory":"Health Practitioner",
            "type":"Services"
        },
        {
            "category":"Communications",
            "type":"Services"
        }
    ],
    "sg:phone":"+1 704 895 3404",
    "sg:postcode":"28117",
    "sg:province":"NC",
    "sg:tags":[
        "pathologist",
        "speech-language",
        "myofunctional",
        "therapy"
    ],
    "wof:name":"Lucinda M Heavlin",
    "wof:placetype":"venue"
},
  "geometry": {"coordinates":[-80.878334,35.522619],"type":"Point"}
}