{
  "type": "Feature",
  "properties": {
    "iso:country":"US",
    "sg:address":"3588 Yadkin College Rd",
    "sg:city":"Lexington",
    "sg:classifiers":[
        {
            "category":"Building & Trades",
            "subcategory":"Construction",
            "type":"Services"
        }
    ],
    "sg:phone":"+1 336 787 4910",
    "sg:postcode":"27295",
    "sg:province":"NC",
    "sg:tags":[
        "underground",
        "trenching",
        "contractor"
    ],
    "wof:name":"Johnny Walser Backhoe Svc",
    "wof:placetype":"venue"
},
  "geometry": {"coordinates":[-80.389709,35.880521],"type":"Point"}
}