{
  "type": "Feature",
  "properties": {
    "addr:full":"3000 N Center St Hickory NC 28601",
    "addr:housenumber":"3000",
    "addr:postcode":"28601",
    "addr:street":"N Center St",
    "iso:country":"US",
    "sg:address":"3000 N Center St",
    "sg:city":"Hickory",
    "sg:classifiers":[
        {
            "category":"Cinema",
            "subcategory":"Movie Rental",
            "type":"Entertainment"
        }
    ],
    "sg:phone":"+1 828 322 2224",
    "sg:postcode":"28601",
    "sg:province":"NC",
    "sg:tags":[
        "leasing",
        "video",
        "disc",
        "tape"
    ],
    "wof:name":"Blockbuster Video",
    "wof:placetype":"venue"
},
  "geometry": {"coordinates":[-81.329646,35.772178],"type":"Point"}
}