{
  "type": "Feature",
  "properties": {
    "iso:country":"US",
    "sg:address":"2630 N Church St",
    "sg:city":"Burlington",
    "sg:classifiers":[
        {
            "category":"Restaurant",
            "type":"Food & Drink"
        }
    ],
    "sg:phone":"+1 336 578 9166",
    "sg:postcode":"27217",
    "sg:province":"NC",
    "wof:name":"Larry's East 70 Diner",
    "wof:placetype":"venue"
},
  "geometry": {"coordinates":[-79.385931,36.091013],"type":"Point"}
}