{
  "type": "Feature",
  "properties": {
    "iso:country":"US",
    "sg:address":"2218 Statesville Blvd",
    "sg:city":"Salisbury",
    "sg:classifiers":[
        {
            "category":"Wholesale",
            "subcategory":"Groceries",
            "type":"Manufacturing & Wholesale Goods"
        }
    ],
    "sg:phone":"+1 704 633 6073",
    "sg:postcode":"28147",
    "sg:province":"NC",
    "sg:tags":[
        "baker"
    ],
    "wof:name":"Merita Bakery",
    "wof:placetype":"venue"
},
  "geometry": {"coordinates":[-80.521711,35.695902],"type":"Point"}
}