{
  "type": "Feature",
  "properties": {
    "addr:full":"370 Ivey Rd Mount Olive NC 28365",
    "addr:housenumber":"370",
    "addr:postcode":"28365",
    "addr:street":"Ivey Rd",
    "iso:country":"US",
    "sg:address":"370 Ivey Rd",
    "sg:city":"Mount Olive",
    "sg:phone":"+1 919 658 4860",
    "sg:postcode":"28365",
    "sg:province":"NC",
    "sg:tags":[
        "farm",
        "tobacco"
    ],
    "wof:name":"Cindy K Ivey",
    "wof:placetype":"venue"
},
  "geometry": {"coordinates":[-77.991184,35.101167],"type":"Point"}
}