{
  "type": "Feature",
  "properties": {
    "iso:country":"US",
    "sg:address":"118 Zillicoa St",
    "sg:city":"Asheville",
    "sg:classifiers":[
        {
            "category":"Professional",
            "type":"Services"
        }
    ],
    "sg:phone":"+1 828 254 6224",
    "sg:postcode":"28801",
    "sg:province":"NC",
    "sg:tags":[
        "establishment"
    ],
    "wof:name":"Campus Advantage",
    "wof:placetype":"venue"
},
  "geometry": {"coordinates":[-82.568916,35.60822],"type":"Point"}
}