{
  "type": "Feature",
  "properties": {
    "iso:country":"US",
    "sg:address":"5301 Maxwell Rd",
    "sg:city":"Autryville",
    "sg:classifiers":[
        {
            "category":"Food & Beverages",
            "subcategory":"Groceries & Convenience Stores",
            "type":"Retail Goods"
        },
        {
            "category":"Shopping",
            "subcategory":"Discount & Variety Stores",
            "type":"Retail Goods"
        }
    ],
    "sg:phone":"+1 910 567 6512",
    "sg:postcode":"28318",
    "sg:province":"NC",
    "sg:tags":[
        "farm",
        "grocer",
        "general",
        "merchandise",
        "supply"
    ],
    "wof:name":"Carroll's Supermarket",
    "wof:placetype":"venue"
},
  "geometry": {"coordinates":[-78.623796,35.096635],"type":"Point"}
}