{
  "type": "Feature",
  "properties": {
    "iso:country":"US",
    "sg:address":"1715 Almond St",
    "sg:city":"Albemarle",
    "sg:classifiers":[
        {
            "category":"Wholesale",
            "subcategory":"Construction Materials",
            "type":"Manufacturing & Wholesale Goods"
        }
    ],
    "sg:phone":"+1 704 986 1753",
    "sg:postcode":"28001",
    "sg:province":"NC",
    "sg:tags":[
        "fence"
    ],
    "wof:name":"Residential Installers",
    "wof:placetype":"venue"
},
  "geometry": {"coordinates":[-80.19255200000001,35.381419],"type":"Point"}
}