{
  "type": "Feature",
  "properties": {
    "iso:country":"US",
    "sg:address":"220 E Meadow Rd",
    "sg:city":"Eden",
    "sg:classifiers":[
        {
            "category":"Professional",
            "subcategory":"Accounting & Tax Preparation",
            "type":"Services"
        }
    ],
    "sg:phone":"+1 336 627 7011",
    "sg:postcode":"27288",
    "sg:province":"NC",
    "sg:tags":[
        "accountant"
    ],
    "wof:name":"Edwina W Webster CPA",
    "wof:placetype":"venue"
},
  "geometry": {"coordinates":[-79.73876,36.508188],"type":"Point"}
}