{
  "type": "Feature",
  "properties": {
    "addr:full":"1432 1st Ave SW Hickory NC 28602",
    "addr:housenumber":"1432",
    "addr:postcode":"28602",
    "addr:street":"1St Ave Sw",
    "iso:country":"US",
    "sg:address":"1432 1st Ave SW",
    "sg:city":"Hickory",
    "sg:classifiers":[
        {
            "category":"Home & Garden",
            "subcategory":"Furniture",
            "type":"Retail Goods"
        }
    ],
    "sg:phone":"+1 828 256 8021",
    "sg:postcode":"28602",
    "sg:province":"NC",
    "wof:name":"Farm House Furnishings",
    "wof:placetype":"venue"
},
  "geometry": {"coordinates":[-81.363809,35.729869],"type":"Point"}
}