{
  "type": "Feature",
  "properties": {
    "iso:country":"US",
    "sg:address":"108 N Depot St",
    "sg:city":"Pilot Mountain",
    "sg:classifiers":[
        {
            "category":"Organizations",
            "subcategory":"Religious Organization",
            "type":"Services"
        }
    ],
    "sg:phone":"+1 336 368 4574",
    "sg:postcode":"27041",
    "sg:province":"NC",
    "sg:tags":[
        "church"
    ],
    "wof:name":"Lovells Chapel United Methdst",
    "wof:placetype":"venue"
},
  "geometry": {"coordinates":[-80.466516,36.385732],"type":"Point"}
}