{
  "type": "Feature",
  "properties": {
    "iso:country":"US",
    "sg:address":"201 College St",
    "sg:city":"Pineville",
    "sg:classifiers":[
        {
            "category":"Professional",
            "subcategory":"Business Services",
            "type":"Services"
        }
    ],
    "sg:phone":"+1   ",
    "sg:postcode":"28134",
    "sg:province":"NC",
    "wof:name":"B & G Courier",
    "wof:placetype":"venue"
},
  "geometry": {"coordinates":[-80.88829800000001,35.086222],"type":"Point"}
}