{
  "type": "Feature",
  "properties": {
    "iso:country":"US",
    "sg:address":"1425 N Tryon St",
    "sg:city":"Charlotte",
    "sg:classifiers":[
        {
            "category":"Freight",
            "type":"Transportation"
        }
    ],
    "sg:phone":"+1 704 377 6116",
    "sg:postcode":"28206",
    "sg:province":"NC",
    "sg:tags":[
        "trucking"
    ],
    "wof:name":"Enterprize Intermodial Svc",
    "wof:placetype":"venue"
},
  "geometry": {"coordinates":[-80.82804299999999,35.238481],"type":"Point"}
}