{
  "type": "Feature",
  "properties": {
    "addr:full":"7199 Bridlewood Dr Trinity NC 27370",
    "addr:housenumber":"7199",
    "addr:postcode":"27370",
    "addr:street":"Bridlewood Dr",
    "iso:country":"US",
    "sg:address":"7199 Bridlewood Dr",
    "sg:city":"Trinity",
    "sg:classifiers":[
        {
            "category":"Professional",
            "subcategory":"Management & Consulting",
            "type":"Services"
        }
    ],
    "sg:phone":"+1 336 475 5693",
    "sg:postcode":"27370",
    "sg:province":"NC",
    "sg:tags":[
        "consultant",
        "educational"
    ],
    "wof:name":"D B Saunders",
    "wof:placetype":"venue"
},
  "geometry": {"coordinates":[-80.03576700000001,35.856083],"type":"Point"}
}