{
  "type": "Feature",
  "properties": {
    "iso:country":"US",
    "sg:address":"241 Crestview Rd",
    "sg:city":"Southern Pines",
    "sg:classifiers":[
        {
            "category":"Professional",
            "type":"Services"
        }
    ],
    "sg:phone":"+1 910 693 9958",
    "sg:postcode":"28387",
    "sg:province":"NC",
    "wof:name":"Dezinit LLC",
    "wof:placetype":"venue"
},
  "geometry": {"coordinates":[-79.383528,35.181578],"type":"Point"}
}