{
  "type": "Feature",
  "properties": {
    "addr:full":"1005 Beatties Ford Rd Charlotte NC 28216",
    "addr:housenumber":"1005",
    "addr:postcode":"28216",
    "addr:street":"Beatties Ford Rd",
    "iso:country":"US",
    "sg:address":"1005 Beatties Ford Rd",
    "sg:city":"Charlotte",
    "sg:classifiers":[
        {
            "category":"Personal",
            "subcategory":"Beauty Salon",
            "type":"Services"
        }
    ],
    "sg:phone":"+1 704 331 0181",
    "sg:postcode":"28216",
    "sg:province":"NC",
    "wof:name":"African Hair Braiding Explsn",
    "wof:placetype":"venue"
},
  "geometry": {"coordinates":[-80.856211,35.252618],"type":"Point"}
}