{
  "type": "Feature",
  "properties": {
    "iso:country":"US",
    "sg:address":"357 Dunn Rd",
    "sg:city":"Fayetteville",
    "sg:classifiers":[
        {
            "category":"Wholesale",
            "subcategory":"Auto Parts",
            "type":"Manufacturing & Wholesale Goods"
        }
    ],
    "sg:phone":"+1 910 483 5107",
    "sg:postcode":"28312",
    "sg:province":"NC",
    "sg:tags":[
        "equipment",
        "truck"
    ],
    "wof:name":"T & H Brake Svc",
    "wof:placetype":"venue"
},
  "geometry": {"coordinates":[-78.85483499999999,35.049312],"type":"Point"}
}