{
  "type": "Feature",
  "properties": {
    "addr:full":"729 Springs Rd Washington NC 27889",
    "addr:housenumber":"729",
    "addr:postcode":"27889",
    "addr:street":"Springs Rd",
    "iso:country":"US",
    "sg:address":"729 Springs Rd",
    "sg:city":"Washington",
    "sg:classifiers":[
        {
            "category":"Airline",
            "type":"Transportation"
        }
    ],
    "sg:phone":"+1 252 946 6292",
    "sg:postcode":"27889",
    "sg:province":"NC",
    "sg:tags":[
        "helicopter",
        "rental"
    ],
    "sg:website":"www.eastcarolinahelicopters.com",
    "wof:name":"East Carolina Helicopters",
    "wof:placetype":"venue"
},
  "geometry": {"coordinates":[-77.058092,35.581483],"type":"Point"}
}