{
  "type": "Feature",
  "properties": {
    "iso:country":"US",
    "sg:address":"318 N Main St",
    "sg:city":"Salisbury",
    "sg:classifiers":[
        {
            "category":"Social Services",
            "type":"Services"
        }
    ],
    "sg:phone":"+1 704 633 5636",
    "sg:postcode":"28144",
    "sg:province":"NC",
    "sg:tags":[
        "organization",
        "welfare"
    ],
    "wof:name":"Rowan County Youth Svc Bureau",
    "wof:placetype":"venue"
},
  "geometry": {"coordinates":[-80.466757,35.669871],"type":"Point"}
}