{
  "type": "Feature",
  "properties": {
    "iso:country":"US",
    "sg:address":"4170 Wendell Blvd",
    "sg:city":"Wendell",
    "sg:classifiers":[
        {
            "category":"Organizations",
            "subcategory":"Religious Organization",
            "type":"Services"
        }
    ],
    "sg:phone":"+1 919 366 2083",
    "sg:postcode":"27591",
    "sg:province":"NC",
    "sg:tags":[
        "church"
    ],
    "wof:name":"Genesis True Worship Tabernacl",
    "wof:placetype":"venue"
},
  "geometry": {"coordinates":[-78.358622,35.785159],"type":"Point"}
}