{
  "type": "Feature",
  "properties": {
    "iso:country":"US",
    "sg:address":"9115 Old Statesville Rd",
    "sg:city":"Charlotte",
    "sg:classifiers":[
        {
            "category":"Home & Garden",
            "subcategory":"Building Materials",
            "type":"Retail Goods"
        }
    ],
    "sg:phone":"+1 704 597 1002",
    "sg:postcode":"28269",
    "sg:province":"NC",
    "sg:tags":[
        "garage",
        "opener",
        "door"
    ],
    "wof:name":"All American Overhead Door",
    "wof:placetype":"venue"
},
  "geometry": {"coordinates":[-80.823894,35.345578],"type":"Point"}
}