{
  "type": "Feature",
  "properties": {
    "addr:full":"1857 Cascade St Fayetteville NC 28301",
    "addr:housenumber":"1857",
    "addr:postcode":"28301",
    "addr:street":"Cascade St",
    "iso:country":"US",
    "sg:address":"1857 Cascade St",
    "sg:city":"Fayetteville",
    "sg:classifiers":[
        {
            "category":"Real Estate",
            "subcategory":"Real Estate Agent",
            "type":"Services"
        }
    ],
    "sg:phone":"+1 910 488 6882",
    "sg:postcode":"28301",
    "sg:province":"NC",
    "wof:name":"Haynes Rental",
    "wof:placetype":"venue"
},
  "geometry": {"coordinates":[-78.88965399999999,35.084029],"type":"Point"}
}