{
  "type": "Feature",
  "properties": {
    "addr:full":"3020 US Hwy 301 S Smithfield NC 27577",
    "addr:housenumber":"3020",
    "addr:postcode":"27577",
    "addr:street":"Us Hwy 301 S",
    "iso:country":"US",
    "sg:address":"3020 US Hwy 301 S",
    "sg:city":"Smithfield",
    "sg:classifiers":[
        {
            "category":"Organizations",
            "subcategory":"Religious Organization",
            "type":"Services"
        }
    ],
    "sg:phone":"+1 919 934 4471",
    "sg:postcode":"27577",
    "sg:province":"NC",
    "sg:tags":[
        "church"
    ],
    "wof:name":"Pentecostals Of Smithfield",
    "wof:placetype":"venue"
},
  "geometry": {"coordinates":[-78.37490200000001,35.478399],"type":"Point"}
}