{
  "type": "Feature",
  "properties": {
    "iso:country":"US",
    "sg:address":"9820 Northcross Center Ct",
    "sg:city":"Huntersville",
    "sg:classifiers":[
        {
            "category":"Manufacturing",
            "subcategory":"Printing",
            "type":"Manufacturing & Wholesale Goods"
        }
    ],
    "sg:phone":"+1 704 948 4103",
    "sg:postcode":"28078",
    "sg:province":"NC",
    "sg:tags":[
        "publisher",
        "software"
    ],
    "wof:name":"Coss Development Corp",
    "wof:placetype":"venue"
},
  "geometry": {"coordinates":[-80.864814,35.447662],"type":"Point"}
}