{
  "type": "Feature",
  "properties": {
    "addr:full":"2821 US Hwy 421 Wilmington NC 28401",
    "addr:housenumber":"2821",
    "addr:postcode":"28401",
    "addr:street":"Us Hwy 421",
    "iso:country":"US",
    "sg:address":"2821 US Hwy 421",
    "sg:city":"Wilmington",
    "sg:classifiers":[
        {
            "category":"Manufacturing",
            "subcategory":"Tools & Machinery",
            "type":"Manufacturing & Wholesale Goods"
        }
    ],
    "sg:phone":"+1 910 763 7633",
    "sg:postcode":"28401",
    "sg:province":"NC",
    "sg:tags":[
        "machine",
        "shop"
    ],
    "wof:name":"D & G Machine Shop Inc",
    "wof:placetype":"venue"
},
  "geometry": {"coordinates":[-77.964496,34.282869],"type":"Point"}
}