{
  "type": "Feature",
  "properties": {
    "iso:country":"US",
    "sg:address":"4608 Summit Ave",
    "sg:city":"Greensboro",
    "sg:classifiers":[
        {
            "category":"Food & Beverages",
            "subcategory":"Groceries & Convenience Stores",
            "type":"Retail Goods"
        }
    ],
    "sg:phone":"+1 336 375 4300",
    "sg:postcode":"27405",
    "sg:province":"NC",
    "sg:tags":[
        "grocer"
    ],
    "wof:name":"Tip Top Grocery",
    "wof:placetype":"venue"
},
  "geometry": {"coordinates":[-79.750096,36.140359],"type":"Point"}
}