{
  "type": "Feature",
  "properties": {
    "iso:country":"US",
    "sg:address":"2454 S McKinney Rd",
    "sg:city":"Mount Airy",
    "sg:classifiers":[
        {
            "category":"School Buses",
            "type":"Transportation"
        }
    ],
    "sg:phone":"+1 336 789 0025",
    "sg:postcode":"27030",
    "sg:province":"NC",
    "wof:name":"Meadows Used Buses",
    "wof:placetype":"venue"
},
  "geometry": {"coordinates":[-80.64489,36.458887],"type":"Point"}
}