{
  "type": "Feature",
  "properties": {
    "addr:full":"1909 Tee Dee St Raleigh NC 27610",
    "addr:housenumber":"1909",
    "addr:postcode":"27610",
    "addr:street":"Tee;St",
    "iso:country":"US",
    "sg:address":"1909 Tee Dee St",
    "sg:city":"Raleigh",
    "sg:classifiers":[
        {
            "category":"Building & Trades",
            "subcategory":"Construction",
            "type":"Services"
        }
    ],
    "sg:phone":"+1 919 832 7150",
    "sg:postcode":"27610",
    "sg:province":"NC",
    "sg:tags":[
        "contractor"
    ],
    "wof:name":"Raleigh Demo Construction Co",
    "wof:placetype":"venue"
},
  "geometry": {"coordinates":[-78.606677,35.749769],"type":"Point"}
}