{
  "type": "Feature",
  "properties": {
    "iso:country":"US",
    "sg:address":"2240 Camp Greene St",
    "sg:city":"Charlotte",
    "sg:classifiers":[
        {
            "category":"Restaurant",
            "type":"Food & Drink"
        }
    ],
    "sg:phone":"+1 704 392 8344",
    "sg:postcode":"28208",
    "sg:province":"NC",
    "wof:name":"Southern Style Bar Grill",
    "wof:placetype":"venue"
},
  "geometry": {"coordinates":[-80.884546,35.224915],"type":"Point"}
}