{
  "type": "Feature",
  "properties": {
    "iso:country":"US",
    "sg:address":"102 10th St NW",
    "sg:city":"Conover",
    "sg:classifiers":[
        {
            "category":"Restaurant",
            "type":"Food & Drink"
        }
    ],
    "sg:phone":"+1 828 695 9347",
    "sg:postcode":"28613",
    "sg:province":"NC",
    "wof:name":"10th Street Restaurant",
    "wof:placetype":"venue"
},
  "geometry": {"coordinates":[-81.221209,35.719996],"type":"Point"}
}