{
  "type": "Feature",
  "properties": {
    "addr:full":"2021 Griffith Rd Winston Salem NC 27103",
    "addr:housenumber":"2021",
    "addr:postcode":"27103",
    "addr:street":"Griffith Rd",
    "iso:country":"US",
    "sg:address":"2021 Griffith Rd",
    "sg:city":"Winston Salem",
    "sg:classifiers":[
        {
            "category":"Building & Trades",
            "subcategory":"Construction",
            "type":"Services"
        }
    ],
    "sg:phone":"+1 336 760 9201",
    "sg:postcode":"27103",
    "sg:province":"NC",
    "sg:tags":[
        "home",
        "builder"
    ],
    "wof:name":"Schumacher Homes - Winston Slm",
    "wof:placetype":"venue"
},
  "geometry": {"coordinates":[-80.309248,36.062509],"type":"Point"}
}