{
  "type": "Feature",
  "properties": {
    "iso:country":"US",
    "sg:address":"510 E Park Ave",
    "sg:city":"Charlotte",
    "sg:classifiers":[
        {
            "category":"Government",
            "subcategory":"Office",
            "type":"Public Place"
        }
    ],
    "sg:phone":"+1 704 336 2533",
    "sg:postcode":"28203",
    "sg:province":"NC",
    "sg:tags":[
        "conservation"
    ],
    "wof:name":"Parks & Recreation Dept",
    "wof:placetype":"venue"
},
  "geometry": {"coordinates":[-80.851567,35.210003],"type":"Point"}
}