{
  "type": "Feature",
  "properties": {
    "addr:full":"2425 S Alston Ave Durham NC 27713",
    "addr:housenumber":"2425",
    "addr:postcode":"27713",
    "addr:street":"S Alston Ave",
    "iso:country":"US",
    "sg:address":"2425 S Alston Ave",
    "sg:city":"Durham",
    "sg:classifiers":[
        {
            "category":"Manufacturing",
            "subcategory":"Rubber & Plastics",
            "type":"Manufacturing & Wholesale Goods"
        }
    ],
    "sg:phone":"+1 919 596 0668",
    "sg:postcode":"27713",
    "sg:province":"NC",
    "sg:website":"www.foamdesign.com",
    "wof:name":"Foam Design",
    "wof:placetype":"venue"
},
  "geometry": {"coordinates":[-78.882137,35.953128],"type":"Point"}
}