{
  "type": "Feature",
  "properties": {
    "iso:country":"US",
    "sg:address":"7023 Streamside Dr",
    "sg:city":"Charlotte",
    "sg:classifiers":[
        {
            "category":"Real Estate",
            "subcategory":"Surveying",
            "type":"Services"
        }
    ],
    "sg:phone":"+1 704 333 0169",
    "sg:postcode":"28212",
    "sg:province":"NC",
    "sg:tags":[
        "surveyor"
    ],
    "wof:name":"Rhyne Land Surveying",
    "wof:placetype":"venue"
},
  "geometry": {"coordinates":[-80.74032099999999,35.178513],"type":"Point"}
}