{
  "type": "Feature",
  "properties": {
    "addr:full":"7104 Conifer Cir Indian Trail NC 28079",
    "addr:housenumber":"7104",
    "addr:postcode":"28079",
    "addr:street":"Conifer Cir;Trail",
    "iso:country":"US",
    "sg:address":"7104 Conifer Cir",
    "sg:city":"Indian Trail",
    "sg:classifiers":[
        {
            "category":"Building & Trades",
            "subcategory":"Cleaning & Sanitation",
            "type":"Services"
        }
    ],
    "sg:phone":"+1   ",
    "sg:postcode":"28079",
    "sg:province":"NC",
    "sg:tags":[
        "repair",
        "maintenance"
    ],
    "wof:name":"Morris Cleaning",
    "wof:placetype":"venue"
},
  "geometry": {"coordinates":[-80.63609700000001,35.08933],"type":"Point"}
}