{
  "type": "Feature",
  "properties": {
    "addr:full":"4724 Cedarfield Dr Raleigh NC 27606",
    "addr:postcode":"4724;27606",
    "addr:street":"Cedarfield Dr",
    "iso:country":"US",
    "sg:address":"4724 Cedarfield Dr",
    "sg:city":"Raleigh",
    "sg:classifiers":[
        {
            "category":"Shopping",
            "subcategory":"Used Merchandise",
            "type":"Retail Goods"
        }
    ],
    "sg:phone":"+1 919 851 4313",
    "sg:postcode":"27606",
    "sg:province":"NC",
    "sg:tags":[
        "boat"
    ],
    "wof:name":"Darkim Inc",
    "wof:placetype":"venue"
},
  "geometry": {"coordinates":[-78.711805,35.717437],"type":"Point"}
}