{
  "type": "Feature",
  "properties": {
    "addr:full":"19530 Dufour Ct Cornelius NC 28031",
    "addr:postcode":"19530;28031",
    "addr:street":"Dufour Ct",
    "iso:country":"US",
    "sg:address":"19530 Dufour Ct",
    "sg:city":"Cornelius",
    "sg:classifiers":[
        {
            "category":"Professional",
            "subcategory":"Management & Consulting",
            "type":"Services"
        }
    ],
    "sg:phone":"+1 704 896 2204",
    "sg:postcode":"28031",
    "sg:province":"NC",
    "sg:tags":[
        "consultant",
        "business"
    ],
    "wof:name":"Jason Lott",
    "wof:placetype":"venue"
},
  "geometry": {"coordinates":[-80.883624,35.489755],"type":"Point"}
}