{
  "type": "Feature",
  "properties": {
    "addr:full":"1047 Haywood Rd Asheville NC 28806",
    "addr:housenumber":"1047",
    "addr:postcode":"28806",
    "addr:street":"Haywood Rd",
    "iso:country":"US",
    "sg:address":"1047 Haywood Rd",
    "sg:city":"Asheville",
    "sg:classifiers":[
        {
            "category":"Restaurant",
            "type":"Food & Drink"
        }
    ],
    "sg:phone":"+1 828 255 5148",
    "sg:postcode":"28806",
    "sg:province":"NC",
    "wof:name":"El Paraiso Mexican Grill",
    "wof:placetype":"venue"
},
  "geometry": {"coordinates":[-82.580494,35.577925],"type":"Point"}
}