{
  "type": "Feature",
  "properties": {
    "iso:country":"US",
    "sg:address":"118 1st St",
    "sg:city":"Atlantic Beach",
    "sg:classifiers":[
        {
            "category":"Building & Trades",
            "subcategory":"Construction",
            "type":"Services"
        }
    ],
    "sg:phone":"+1 252 726 9702",
    "sg:postcode":"28512",
    "sg:province":"NC",
    "sg:tags":[
        "house"
    ],
    "wof:name":"Mechanical Plant Service",
    "wof:placetype":"venue"
},
  "geometry": {"coordinates":[-76.743616,34.709222],"type":"Point"}
}