{
  "type": "Feature",
  "properties": {
    "addr:full":"206 Stone Monument Dr Wake Forest NC 27587",
    "addr:housenumber":"206",
    "addr:postcode":"27587",
    "addr:street":"Stone Monument Dr",
    "iso:country":"US",
    "sg:address":"206 Stone Monument Dr",
    "sg:city":"Wake Forest",
    "sg:classifiers":[
        {
            "category":"Shopping",
            "subcategory":"Discount & Variety Stores",
            "type":"Retail Goods"
        }
    ],
    "sg:phone":"+1 919 562 9898",
    "sg:postcode":"27587",
    "sg:province":"NC",
    "sg:tags":[
        "merchandise",
        "general"
    ],
    "wof:name":"Park Place Sales",
    "wof:placetype":"venue"
},
  "geometry": {"coordinates":[-78.52686799999999,35.95729],"type":"Point"}
}