{
  "type": "Feature",
  "properties": {
    "iso:country":"US",
    "sg:address":"357 Bent Creek Trl",
    "sg:city":"Kernersville",
    "sg:classifiers":[
        {
            "category":"Professional",
            "subcategory":"Computer Services",
            "type":"Services"
        }
    ],
    "sg:phone":"+1   ",
    "sg:postcode":"27284",
    "sg:province":"NC",
    "sg:tags":[
        "prepackaged",
        "software"
    ],
    "wof:name":"Best Software Inc",
    "wof:placetype":"venue"
},
  "geometry": {"coordinates":[-80.111138,36.113819],"type":"Point"}
}