{
  "type": "Feature",
  "properties": {
    "addr:full":"513 Jones Cove Rd Clyde NC 28721",
    "addr:housenumber":"513",
    "addr:postcode":"28721",
    "addr:street":"Jones Cove Rd",
    "iso:country":"US",
    "sg:address":"513 Jones Cove Rd",
    "sg:city":"Clyde",
    "sg:classifiers":[
        {
            "category":"Building & Trades",
            "subcategory":"Plumbing",
            "type":"Services"
        }
    ],
    "sg:phone":"+1 828 627 9216",
    "sg:postcode":"28721",
    "sg:province":"NC",
    "sg:tags":[
        "product",
        "management",
        "energy",
        "system"
    ],
    "wof:name":"Progess Energy",
    "wof:placetype":"venue"
},
  "geometry": {"coordinates":[-82.939241,35.525887],"type":"Point"}
}