{
  "type": "Feature",
  "properties": {
    "iso:country":"US",
    "sg:address":"4508 Alden Ct",
    "sg:city":"Wilmington",
    "sg:classifiers":[
        {
            "category":"Professional",
            "subcategory":"Business Services",
            "type":"Services"
        }
    ],
    "sg:phone":"+1   ",
    "sg:postcode":"28412",
    "sg:province":"NC",
    "sg:tags":[
        "drafting"
    ],
    "wof:name":"Deminsions",
    "wof:placetype":"venue"
},
  "geometry": {"coordinates":[-77.917991,34.152835],"type":"Point"}
}