{
  "type": "Feature",
  "properties": {
    "addr:full":"537 Becker Dr Roanoke Rapids NC 27870",
    "addr:housenumber":"537",
    "addr:postcode":"27870",
    "addr:street":"Becker Dr",
    "iso:country":"US",
    "sg:address":"537 Becker Dr",
    "sg:city":"Roanoke Rapids",
    "sg:classifiers":[
        {
            "category":"Personal",
            "subcategory":"Massage",
            "type":"Services"
        }
    ],
    "sg:phone":"+1 252 535 9400",
    "sg:postcode":"27870",
    "sg:province":"NC",
    "wof:name":"A Touch Of Life Therapeutic",
    "wof:placetype":"venue"
},
  "geometry": {"coordinates":[-77.63350699999999,36.43898],"type":"Point"}
}