{
  "type": "Feature",
  "properties": {
    "addr:full":"6574 Cove Creek Dr Charlotte NC 28215",
    "addr:housenumber":"6574",
    "addr:postcode":"28215",
    "addr:street":"Cove Creek Dr",
    "iso:country":"US",
    "sg:address":"6574 Cove Creek Dr",
    "sg:city":"Charlotte",
    "sg:classifiers":[
        {
            "category":"Social Services",
            "subcategory":"Adult Care",
            "type":"Services"
        }
    ],
    "sg:phone":"+1   ",
    "sg:postcode":"28215",
    "sg:province":"NC",
    "sg:tags":[
        "handicap",
        "home",
        "group",
        "child"
    ],
    "wof:name":"Touch of Hope Inc",
    "wof:placetype":"venue"
},
  "geometry": {"coordinates":[-80.750283,35.258268],"type":"Point"}
}