{
  "type": "Feature",
  "properties": {
    "addr:full":"2315 Fayetteville Rd Durham NC 27707",
    "addr:housenumber":"2315",
    "addr:postcode":"27707",
    "addr:street":"Fayetteville Rd",
    "iso:country":"US",
    "sg:address":"2315 Fayetteville Rd",
    "sg:city":"Durham",
    "sg:classifiers":[
        {
            "category":"Organizations",
            "subcategory":"Religious Organization",
            "type":"Services"
        }
    ],
    "sg:phone":"+1   ",
    "sg:postcode":"27707",
    "sg:province":"NC",
    "wof:name":"Solid Rock Full Gospel",
    "wof:placetype":"venue"
},
  "geometry": {"coordinates":[-78.901349,35.970437],"type":"Point"}
}