{
  "type": "Feature",
  "properties": {
    "iso:country":"US",
    "sg:address":"2700 Barton Ct",
    "sg:city":"Elon College",
    "sg:classifiers":[
        {
            "category":"Building & Trades",
            "subcategory":"Cleaning & Sanitation",
            "type":"Services"
        }
    ],
    "sg:phone":"+1   ",
    "sg:postcode":"27244",
    "sg:province":"NC",
    "sg:tags":[
        "maintenance"
    ],
    "wof:name":"Patricks Cleaning Service",
    "wof:placetype":"venue"
},
  "geometry": {"coordinates":[-79.51293699999999,36.152332],"type":"Point"}
}