{
  "type": "Feature",
  "properties": {
    "addr:full":"116 Emry St Roanoke Rapids NC 27870",
    "addr:housenumber":"116",
    "addr:postcode":"27870",
    "addr:street":"Emry St",
    "iso:country":"US",
    "sg:address":"116 Emry St",
    "sg:city":"Roanoke Rapids",
    "sg:classifiers":[
        {
            "category":"Organizations",
            "subcategory":"Religious Organization",
            "type":"Services"
        }
    ],
    "sg:phone":"+1 252 537 0207",
    "sg:postcode":"27870",
    "sg:province":"NC",
    "sg:tags":[
        "church"
    ],
    "wof:name":"Church Of Jesus Christ",
    "wof:placetype":"venue"
},
  "geometry": {"coordinates":[-77.663127,36.447698],"type":"Point"}
}