{
  "type": "Feature",
  "properties": {
    "iso:country":"US",
    "sg:address":"203 Dundee St",
    "sg:city":"Windsor",
    "sg:classifiers":[
        {
            "category":"Professional",
            "subcategory":"Lawyer & Legal Services",
            "type":"Services"
        }
    ],
    "sg:phone":"+1 252 794 3161",
    "sg:postcode":"27983",
    "sg:province":"NC",
    "sg:tags":[
        "attorney"
    ],
    "sg:website":"www.windsorlaw.com",
    "wof:name":"Pritchett & Burch",
    "wof:placetype":"venue"
},
  "geometry": {"coordinates":[-76.944129,35.997878],"type":"Point"}
}