{
  "type": "Feature",
  "properties": {
    "addr:full":"325 Arlington Ave Charlotte NC 28203",
    "addr:housenumber":"325",
    "addr:postcode":"28203",
    "addr:street":"Arlington Ave",
    "iso:country":"US",
    "sg:address":"325 Arlington Ave",
    "sg:city":"Charlotte",
    "sg:classifiers":[
        {
            "category":"Professional",
            "subcategory":"Lawyer & Legal Services",
            "type":"Services"
        }
    ],
    "sg:phone":"+1 704 332 2830",
    "sg:postcode":"28203",
    "sg:province":"NC",
    "sg:tags":[
        "attorney"
    ],
    "sg:website":"www.sbhlaw.net",
    "wof:name":"Stiles Byrum & Horn",
    "wof:placetype":"venue"
},
  "geometry": {"coordinates":[-80.85221199999999,35.216622],"type":"Point"}
}