{
  "type": "Feature",
  "properties": {
    "iso:country":"US",
    "sg:address":"6024 Stratton Pl",
    "sg:city":"Raleigh",
    "sg:classifiers":[
        {
            "category":"Home & Garden",
            "subcategory":"Building Materials",
            "type":"Retail Goods"
        }
    ],
    "sg:phone":"+1 919 846 5154",
    "sg:postcode":"27609",
    "sg:province":"NC",
    "wof:name":"Larry Williams Paint & Power W",
    "wof:placetype":"venue"
},
  "geometry": {"coordinates":[-78.64741600000001,35.866254],"type":"Point"}
}