{
  "type": "Feature",
  "properties": {
    "addr:full":"104 S Carpenter St Kings Mountain NC 28086",
    "addr:housenumber":"104",
    "addr:postcode":"28086",
    "addr:street":"S Carpenter St",
    "iso:country":"US",
    "sg:address":"104 S Carpenter St",
    "sg:city":"Kings Mountain",
    "sg:classifiers":[
        {
            "category":"Professional",
            "subcategory":"Management & Consulting",
            "type":"Services"
        }
    ],
    "sg:phone":"+1 704 734 1040",
    "sg:postcode":"28086",
    "sg:province":"NC",
    "sg:tags":[
        "consultant",
        "resource",
        "human"
    ],
    "wof:name":"Carpenter's House",
    "wof:placetype":"venue"
},
  "geometry": {"coordinates":[-81.338413,35.240293],"type":"Point"}
}