{
  "type": "Feature",
  "properties": {
    "iso:country":"US",
    "sg:address":"9922 Spring Harvest Dr",
    "sg:city":"Charlotte",
    "sg:classifiers":[
        {
            "category":"Professional",
            "subcategory":"Business Services",
            "type":"Services"
        }
    ],
    "sg:phone":"+1   ",
    "sg:postcode":"28227",
    "sg:province":"NC",
    "wof:name":"Davis Business Services",
    "wof:placetype":"venue"
},
  "geometry": {"coordinates":[-80.70180000000001,35.173659],"type":"Point"}
}