{
  "type": "Feature",
  "properties": {
    "iso:country":"US",
    "sg:address":"5851 Holly Springs Rd",
    "sg:city":"Raleigh",
    "sg:classifiers":[
        {
            "category":"Restaurant",
            "type":"Food & Drink"
        }
    ],
    "sg:phone":"+1 919 859 3555",
    "sg:postcode":"27606",
    "sg:province":"NC",
    "wof:name":"Barry's Cafe",
    "wof:placetype":"venue"
},
  "geometry": {"coordinates":[-78.74045,35.74512],"type":"Point"}
}