{
  "type": "Feature",
  "properties": {
    "addr:full":"820 E 2nd St Lumberton NC 28358",
    "addr:housenumber":"820",
    "addr:postcode":"28358",
    "addr:street":"E 2Nd St",
    "iso:country":"US",
    "sg:address":"820 E 2nd St",
    "sg:city":"Lumberton",
    "sg:classifiers":[
        {
            "category":"Wholesale",
            "subcategory":"Groceries",
            "type":"Manufacturing & Wholesale Goods"
        }
    ],
    "sg:phone":"+1 910 618 9402",
    "sg:postcode":"28358",
    "sg:province":"NC",
    "sg:tags":[
        "food",
        "snack"
    ],
    "wof:name":"P J Snacks",
    "wof:placetype":"venue"
},
  "geometry": {"coordinates":[-78.99937,34.617618],"type":"Point"}
}