{
  "type": "Feature",
  "properties": {
    "iso:country":"US",
    "sg:address":"10051 US Hwy 70 W",
    "sg:city":"Clayton",
    "sg:classifiers":[
        {
            "category":"Autos & Motor Vehicles",
            "subcategory":"Automobile Sales",
            "type":"Retail Goods"
        }
    ],
    "sg:phone":"+1 919 550 5393",
    "sg:postcode":"27520",
    "sg:province":"NC",
    "sg:tags":[
        "used"
    ],
    "sg:website":"www.shumakers.com",
    "wof:name":"Shumaker Motors Inc",
    "wof:placetype":"venue"
},
  "geometry": {"coordinates":[-78.44426900000001,35.637483],"type":"Point"}
}