{
  "type": "Feature",
  "properties": {
    "addr:full":"200 Certainteed Dr Oxford NC 27565",
    "addr:housenumber":"200",
    "addr:postcode":"27565",
    "addr:street":"Certainteed Dr",
    "iso:country":"US",
    "sg:address":"200 Certainteed Dr",
    "sg:city":"Oxford",
    "sg:classifiers":[
        {
            "category":"Manufacturing",
            "subcategory":"Lumber",
            "type":"Manufacturing & Wholesale Goods"
        }
    ],
    "sg:phone":"+1 919 693 1141",
    "sg:postcode":"27565",
    "sg:province":"NC",
    "sg:tags":[
        "shingles",
        "shake"
    ],
    "sg:website":"www.certainteed.com",
    "wof:name":"Certainteed Corp",
    "wof:placetype":"venue"
},
  "geometry": {"coordinates":[-78.612095,36.293618],"type":"Point"}
}