{
  "type": "Feature",
  "properties": {
    "addr:full":"286 Woltz Atkins Rd Mount Airy NC 27030",
    "addr:housenumber":"286",
    "addr:postcode":"27030",
    "addr:street":"Woltz Atkins Rd",
    "iso:country":"US",
    "sg:address":"286 Woltz Atkins Rd",
    "sg:city":"Mount Airy",
    "sg:classifiers":[
        {
            "category":"Building & Trades",
            "subcategory":"Construction",
            "type":"Services"
        }
    ],
    "sg:phone":"+1 336 352 3155",
    "sg:postcode":"27030",
    "sg:province":"NC",
    "sg:tags":[
        "house"
    ],
    "wof:name":"Piedmont Builders",
    "wof:placetype":"venue"
},
  "geometry": {"coordinates":[-80.789506,36.472064],"type":"Point"}
}