{
  "type": "Feature",
  "properties": {
    "iso:country":"US",
    "sg:address":"124 W Grubb St",
    "sg:city":"Hertford",
    "sg:classifiers":[
        {
            "category":"Real Estate",
            "subcategory":"Real Estate Operator",
            "type":"Services"
        }
    ],
    "sg:phone":"+1 252 426 1138",
    "sg:postcode":"27944",
    "sg:province":"NC",
    "sg:tags":[
        "residential",
        "property"
    ],
    "wof:name":"Matthews W Crafton",
    "wof:placetype":"venue"
},
  "geometry": {"coordinates":[-76.46791399999999,36.189954],"type":"Point"}
}