{
  "type": "Feature",
  "properties": {
    "addr:full":"1501 Brookford Rd Kernersville NC 27284",
    "addr:housenumber":"1501",
    "addr:postcode":"27284",
    "addr:street":"Brookford Rd",
    "iso:country":"US",
    "sg:address":"1501 Brookford Rd",
    "sg:city":"Kernersville",
    "sg:classifiers":[
        {
            "category":"Freight",
            "type":"Transportation"
        }
    ],
    "sg:phone":"+1 336 996 6753",
    "sg:postcode":"27284",
    "sg:province":"NC",
    "sg:tags":[
        "commercial",
        "storage"
    ],
    "wof:name":"Johnson's Attic",
    "wof:placetype":"venue"
},
  "geometry": {"coordinates":[-80.056466,36.092441],"type":"Point"}
}