{
  "type": "Feature",
  "properties": {
    "addr:full":"335 Walnut Creek Ln Asheboro NC 27205",
    "addr:housenumber":"335",
    "addr:postcode":"27205",
    "addr:street":"Walnut Creek Ln",
    "iso:country":"US",
    "sg:address":"335 Walnut Creek Ln",
    "sg:city":"Asheboro",
    "sg:classifiers":[
        {
            "category":"Freight",
            "type":"Transportation"
        }
    ],
    "sg:phone":"+1 336 328 1009",
    "sg:postcode":"27205",
    "sg:province":"NC",
    "sg:tags":[
        "operator",
        "local",
        "trucking"
    ],
    "wof:name":"Triad Trucking LLC",
    "wof:placetype":"venue"
},
  "geometry": {"coordinates":[-79.717063,35.717152],"type":"Point"}
}