{
  "type": "Feature",
  "properties": {
    "iso:country":"US",
    "sg:address":"504 S Duke St",
    "sg:city":"Durham",
    "sg:classifiers":[
        {
            "category":"Banks & Credit Unions",
            "subcategory":"Bank",
            "type":"Services"
        }
    ],
    "sg:phone":"+1 919 682 9602",
    "sg:postcode":"27701",
    "sg:province":"NC",
    "sg:tags":[
        "state"
    ],
    "sg:website":"www.ncsecu.org",
    "wof:name":"State Employees Credit Union",
    "wof:placetype":"venue"
},
  "geometry": {"coordinates":[-78.90888,35.995212],"type":"Point"}
}