{
  "type": "Feature",
  "properties": {
    "iso:country":"US",
    "sg:address":"210 N Main St",
    "sg:city":"Kernersville",
    "sg:classifiers":[
        {
            "category":"Organizations",
            "subcategory":"Religious Organization",
            "type":"Services"
        }
    ],
    "sg:phone":"+1 336 996 9400",
    "sg:postcode":"27284",
    "sg:province":"NC",
    "sg:tags":[
        "church"
    ],
    "wof:name":"Greater Deliverance Worship",
    "wof:placetype":"venue"
},
  "geometry": {"coordinates":[-80.07195900000001,36.121375],"type":"Point"}
}