{
  "type": "Feature",
  "properties": {
    "addr:full":"281 Oak View Ln Asheboro NC 27205",
    "addr:housenumber":"281",
    "addr:postcode":"27205",
    "addr:street":"Oak View Ln",
    "iso:country":"US",
    "sg:address":"281 Oak View Ln",
    "sg:city":"Asheboro",
    "sg:classifiers":[
        {
            "category":"Home & Garden",
            "subcategory":"Household Appliances",
            "type":"Retail Goods"
        }
    ],
    "sg:phone":"+1 336 302 3460",
    "sg:postcode":"27205",
    "sg:province":"NC",
    "sg:tags":[
        "equipment",
        "air",
        "filtration",
        "purification"
    ],
    "wof:name":"Ecoquest Independent Dealers",
    "wof:placetype":"venue"
},
  "geometry": {"coordinates":[-79.787037,35.565169],"type":"Point"}
}