{
  "type": "Feature",
  "properties": {
    "iso:country":"US",
    "sg:address":"118 Dehart Dr",
    "sg:city":"Shelby",
    "sg:classifiers":[
        {
            "category":"Real Estate",
            "subcategory":"Surveying",
            "type":"Services"
        }
    ],
    "sg:phone":"+1   ",
    "sg:postcode":"28152",
    "sg:province":"NC",
    "wof:name":"Johnson & Johnson Surveying",
    "wof:placetype":"venue"
},
  "geometry": {"coordinates":[-81.670799,35.256058],"type":"Point"}
}