{
  "type": "Feature",
  "properties": {
    "iso:country":"US",
    "sg:address":"3410 Capuano St",
    "sg:city":"Lumberton",
    "sg:classifiers":[
        {
            "category":"Banks & Credit Unions",
            "subcategory":"Bank",
            "type":"Services"
        }
    ],
    "sg:phone":"+1 910 738 5868",
    "sg:postcode":"28358",
    "sg:province":"NC",
    "sg:tags":[
        "mortgage"
    ],
    "wof:name":"Principle Residential Mortgage",
    "wof:placetype":"venue"
},
  "geometry": {"coordinates":[-79.01563299999999,34.641922],"type":"Point"}
}