{
  "type": "Feature",
  "properties": {
    "addr:full":"4735 Sharon Rd Charlotte NC 28210",
    "addr:housenumber":"4735",
    "addr:postcode":"28210",
    "addr:street":"Sharon Rd",
    "iso:country":"US",
    "sg:address":"4735 Sharon Rd",
    "sg:city":"Charlotte",
    "sg:classifiers":[
        {
            "category":"Banks & Credit Unions",
            "subcategory":"Bank",
            "type":"Services"
        },
        {
            "category":"Banks & Credit Unions",
            "subcategory":"Financial Services",
            "type":"Services"
        }
    ],
    "sg:phone":"+1 704 367 7700",
    "sg:postcode":"28210",
    "sg:province":"NC",
    "sg:tags":[
        "loan",
        "financing"
    ],
    "sg:website":"http://www.SunTrust.com",
    "wof:name":"SunTrust Bank - Sharon Road",
    "wof:placetype":"venue"
},
  "geometry": {"coordinates":[-80.83153,35.147071],"type":"Point"}
}