{
  "type": "Feature",
  "properties": {
    "addr:full":"10506 Flennigan Way Charlotte NC 28277",
    "addr:housenumber":"10506",
    "addr:postcode":"28277",
    "addr:street":"Flennigan Way",
    "iso:country":"US",
    "sg:address":"10506 Flennigan Way",
    "sg:city":"Charlotte",
    "sg:classifiers":[
        {
            "category":"Professional",
            "subcategory":"Management & Consulting",
            "type":"Services"
        }
    ],
    "sg:phone":"+1   ",
    "sg:postcode":"28277",
    "sg:province":"NC",
    "wof:name":"Mym Consulting",
    "wof:placetype":"venue"
},
  "geometry": {"coordinates":[-80.83748900000001,35.050134],"type":"Point"}
}