{
  "type": "Feature",
  "properties": {
    "addr:full":"7005 Wilkinson Blvd Belmont NC 28012",
    "addr:housenumber":"7005",
    "addr:postcode":"28012",
    "addr:street":"Wilkinson Blvd",
    "iso:country":"US",
    "sg:address":"7005 Wilkinson Blvd",
    "sg:city":"Belmont",
    "sg:classifiers":[
        {
            "category":"Professional",
            "subcategory":"Accounting & Tax Preparation",
            "type":"Services"
        }
    ],
    "sg:phone":"+1 704 825 3935",
    "sg:postcode":"28012",
    "sg:province":"NC",
    "sg:tags":[
        "return",
        "filing"
    ],
    "sg:website":"www.hrblock.com",
    "wof:name":"H & R Block Tax Svc",
    "wof:placetype":"venue"
},
  "geometry": {"coordinates":[-81.02232600000001,35.249512],"type":"Point"}
}