{
  "type": "Feature",
  "properties": {
    "iso:country":"US",
    "sg:address":"196 Glenwood Loop",
    "sg:city":"Marion",
    "sg:classifiers":[
        {
            "category":"Building & Trades",
            "subcategory":"Construction",
            "type":"Services"
        }
    ],
    "sg:phone":"+1 828 738 4642",
    "sg:postcode":"28752",
    "sg:province":"NC",
    "sg:tags":[
        "roofing",
        "contractor"
    ],
    "wof:name":"Vance Roofing & Building Co",
    "wof:placetype":"venue"
},
  "geometry": {"coordinates":[-81.975324,35.61362],"type":"Point"}
}