{
  "type": "Feature",
  "properties": {
    "iso:country":"US",
    "sg:address":"3791 S Alston Ave",
    "sg:city":"Durham",
    "sg:classifiers":[
        {
            "category":"Manufacturing",
            "subcategory":"Printing",
            "type":"Manufacturing & Wholesale Goods"
        }
    ],
    "sg:phone":"+1 919 767 6400",
    "sg:postcode":"27713",
    "sg:province":"NC",
    "sg:tags":[
        "publisher",
        "for",
        "information",
        "solution",
        "au",
        "education"
    ],
    "wof:name":"Proquest Company",
    "wof:placetype":"venue"
},
  "geometry": {"coordinates":[-78.887721,35.923882],"type":"Point"}
}