{
  "type": "Feature",
  "properties": {
    "addr:full":"111 N Hall St Archdale NC 27263",
    "addr:housenumber":"111",
    "addr:postcode":"27263",
    "addr:street":"N Hall St",
    "iso:country":"US",
    "sg:address":"111 N Hall St",
    "sg:city":"Archdale",
    "sg:classifiers":[
        {
            "category":"Building & Trades",
            "subcategory":"Electrical",
            "type":"Services"
        }
    ],
    "sg:phone":"+1 336 431 3387",
    "sg:postcode":"27263",
    "sg:province":"NC",
    "sg:tags":[
        "electric",
        "contractor"
    ],
    "wof:name":"Archdale Electric",
    "wof:placetype":"venue"
},
  "geometry": {"coordinates":[-79.96525099999999,35.926486],"type":"Point"}
}