{
  "type": "Feature",
  "properties": {
    "iso:country":"US",
    "sg:address":"35 Sparger Springs Ln",
    "sg:city":"Durham",
    "sg:classifiers":[
        {
            "category":"Insurance",
            "subcategory":"Insurance Agent",
            "type":"Services"
        }
    ],
    "sg:phone":"+1 919 383 7720",
    "sg:postcode":"27705",
    "sg:province":"NC",
    "sg:tags":[
        "sure",
        "business",
        "agency",
        "engaged",
        "general",
        "bonding",
        "writing"
    ],
    "wof:name":"Archer Bonding & Insur Agcy",
    "wof:placetype":"venue"
},
  "geometry": {"coordinates":[-78.980431,36.039072],"type":"Point"}
}