{
  "type": "Feature",
  "properties": {
    "iso:country":"US",
    "sg:address":"10915 Monroe Rd",
    "sg:city":"Matthews",
    "sg:classifiers":[
        {
            "category":"Restaurant",
            "type":"Food & Drink"
        }
    ],
    "sg:phone":"+1 704 847 5035",
    "sg:postcode":"28105",
    "sg:province":"NC",
    "sg:tags":[
        "eating"
    ],
    "wof:name":"Greg S Barbecue of Matthe",
    "wof:placetype":"venue"
},
  "geometry": {"coordinates":[-80.728589,35.122415],"type":"Point"}
}