{
  "type": "Feature",
  "properties": {
    "addr:full":"664 Long Branch Rd Dunn NC 28334",
    "addr:housenumber":"664",
    "addr:postcode":"28334",
    "addr:street":"Long Branch Rd",
    "iso:country":"US",
    "sg:address":"664 Long Branch Rd",
    "sg:city":"Dunn",
    "sg:classifiers":[
        {
            "category":"Real Estate",
            "subcategory":"Real Estate Operator",
            "type":"Services"
        }
    ],
    "sg:phone":"+1 910 892 3507",
    "sg:postcode":"28334",
    "sg:province":"NC",
    "sg:tags":[
        "property",
        "lessor"
    ],
    "wof:name":"Fred Hawley",
    "wof:placetype":"venue"
},
  "geometry": {"coordinates":[-78.618247,35.270935],"type":"Point"}
}