{
  "type": "Feature",
  "properties": {
    "iso:country":"US",
    "sg:address":"50 Ellington Rd",
    "sg:city":"Siler City",
    "sg:classifiers":[
        {
            "category":"Home & Garden",
            "subcategory":"Building Materials",
            "type":"Retail Goods"
        }
    ],
    "sg:phone":"+1 919 663 6155",
    "sg:postcode":"27344",
    "sg:province":"NC",
    "wof:name":"Home Imprv Depo Hsing Ctr",
    "wof:placetype":"venue"
},
  "geometry": {"coordinates":[-79.499651,35.733346],"type":"Point"}
}