{
  "type": "Feature",
  "properties": {
    "addr:full":"2085 Frontis Plaza Blvd Winston Salem NC 27103",
    "addr:housenumber":"2085",
    "addr:postcode":"27103",
    "addr:street":"Frontis Plaza Blvd",
    "iso:country":"US",
    "sg:address":"2085 Frontis Plaza Blvd",
    "sg:city":"Winston Salem",
    "sg:classifiers":[
        {
            "category":"Coffee & Tea",
            "type":"Food & Drink"
        }
    ],
    "sg:menulink":"http://www.allmenus.com/nc/winston/125094-starbucks-coffee/menu/",
    "sg:phone":"+1 336 765 2716",
    "sg:postcode":"27103",
    "sg:province":"NC",
    "sg:tags":[
        "american"
    ],
    "wof:name":"Starbucks Coffee",
    "wof:placetype":"venue"
},
  "geometry": {"coordinates":[-80.30404900000001,36.060088],"type":"Point"}
}