{
  "type": "Feature",
  "properties": {
    "addr:full":"1437 Military Cutoff Rd Wilmington NC 28405",
    "addr:housenumber":"1437",
    "addr:postcode":"28405",
    "addr:street":"Military Cutoff Rd",
    "iso:country":"US",
    "sg:address":"1437 Military Cutoff Rd",
    "sg:city":"Wilmington",
    "sg:classifiers":[
        {
            "category":"Professional",
            "subcategory":"Lawyer & Legal Services",
            "type":"Services"
        }
    ],
    "sg:phone":"+1 910 864 3068",
    "sg:postcode":"28405",
    "sg:province":"NC",
    "sg:tags":[
        "attorney"
    ],
    "wof:name":"Hutchens Senter Law Firm",
    "wof:placetype":"venue"
},
  "geometry": {"coordinates":[-77.82983,34.225863],"type":"Point"}
}