{
  "type": "Feature",
  "properties": {
    "iso:country":"US",
    "sg:address":"3721 University Dr",
    "sg:city":"Durham",
    "sg:classifiers":[
        {
            "category":"Professional",
            "subcategory":"Accounting & Tax Preparation",
            "type":"Services"
        }
    ],
    "sg:phone":"+1   ",
    "sg:postcode":"27707",
    "sg:province":"NC",
    "wof:name":"Brian Nay",
    "wof:placetype":"venue"
},
  "geometry": {"coordinates":[-78.950333,35.966724],"type":"Point"}
}