{
  "type": "Feature",
  "properties": {
    "iso:country":"US",
    "sg:address":"2008 Yonkers Rd",
    "sg:city":"Raleigh",
    "sg:classifiers":[
        {
            "category":"Wholesale",
            "subcategory":"Auto Parts",
            "type":"Manufacturing & Wholesale Goods"
        }
    ],
    "sg:phone":"+1 919 828 0073",
    "sg:postcode":"27604",
    "sg:province":"NC",
    "wof:name":"Automotive Parts Express Inc",
    "wof:placetype":"venue"
},
  "geometry": {"coordinates":[-78.60315,35.810873],"type":"Point"}
}