{
  "type": "Feature",
  "properties": {
    "addr:full":"765 Oak Stump Rd Elizabeth City NC 27909",
    "addr:housenumber":"765",
    "addr:postcode":"27909",
    "addr:street":"Oak Stump Rd",
    "iso:country":"US",
    "sg:address":"765 Oak Stump Rd",
    "sg:city":"Elizabeth City",
    "sg:classifiers":[
        {
            "category":"Organizations",
            "subcategory":"Religious Organization",
            "type":"Services"
        }
    ],
    "sg:phone":"+1 252 331 7008",
    "sg:postcode":"27909",
    "sg:province":"NC",
    "sg:tags":[
        "church"
    ],
    "wof:name":"Harvest Christian Fellowship",
    "wof:placetype":"venue"
},
  "geometry": {"coordinates":[-76.273898,36.268437],"type":"Point"}
}