{
  "type": "Feature",
  "properties": {
    "iso:country":"US",
    "sg:address":"250 N New Hope Rd",
    "sg:city":"Gastonia",
    "sg:classifiers":[
        {
            "category":"Shopping",
            "type":"Retail Goods"
        }
    ],
    "sg:phone":"+1 704 852 4466",
    "sg:postcode":"28054",
    "sg:province":"NC",
    "sg:tags":[
        "art",
        "gallery",
        "dealer"
    ],
    "wof:name":"Art Mercato",
    "wof:placetype":"venue"
},
  "geometry": {"coordinates":[-81.151754,35.264058],"type":"Point"}
}