{
  "type": "Feature",
  "properties": {
    "iso:country":"US",
    "sg:address":"420 Minuet Ln",
    "sg:city":"Charlotte",
    "sg:classifiers":[
        {
            "category":"Professional",
            "subcategory":"Advertising",
            "type":"Services"
        }
    ],
    "sg:phone":"+1 704 523 6059",
    "sg:postcode":"28217",
    "sg:province":"NC",
    "sg:tags":[
        "distribution"
    ],
    "wof:name":"Distribution Info Systems Corp",
    "wof:placetype":"venue"
},
  "geometry": {"coordinates":[-80.879696,35.169899],"type":"Point"}
}