{
  "type": "Feature",
  "properties": {
    "addr:full":"712 Barksdale Rd Wilmington NC 28409",
    "addr:housenumber":"712",
    "addr:postcode":"28409",
    "addr:street":"Barksdale Rd",
    "iso:country":"US",
    "sg:address":"712 Barksdale Rd",
    "sg:city":"Wilmington",
    "sg:classifiers":[
        {
            "category":"Professional",
            "subcategory":"Art Services",
            "type":"Services"
        }
    ],
    "sg:phone":"+1   ",
    "sg:postcode":"28409",
    "sg:province":"NC",
    "sg:tags":[
        "photography",
        "commercial"
    ],
    "wof:name":"Marino Group Inc",
    "wof:placetype":"venue"
},
  "geometry": {"coordinates":[-77.875816,34.166852],"type":"Point"}
}