{
  "type": "Feature",
  "properties": {
    "addr:full":"1791 Pharview Dr SW Ocean Isle Beach NC 28469",
    "addr:housenumber":"1791",
    "addr:postcode":"28469",
    "addr:street":"Pharview Dr Sw;Isle",
    "iso:country":"US",
    "sg:address":"1791 Pharview Dr SW",
    "sg:city":"Ocean Isle Beach",
    "sg:classifiers":[
        {
            "category":"Wholesale",
            "subcategory":"Non-durable Goods",
            "type":"Manufacturing & Wholesale Goods"
        }
    ],
    "sg:phone":"+1 910 575 4040",
    "sg:postcode":"28469",
    "sg:province":"NC",
    "sg:tags":[
        "advertising",
        "specialty"
    ],
    "wof:name":"Smart Advertising Inc",
    "wof:placetype":"venue"
},
  "geometry": {"coordinates":[-78.463769,33.897149],"type":"Point"}
}