{
  "type": "Feature",
  "properties": {
    "iso:country":"US",
    "sg:address":"109 Livingstone Dr",
    "sg:city":"Cary",
    "sg:classifiers":[
        {
            "category":"Travel",
            "subcategory":"Travel Agent",
            "type":"Entertainment"
        }
    ],
    "sg:phone":"+1 919 460 7925",
    "sg:postcode":"27513",
    "sg:province":"NC",
    "sg:tags":[
        "agency"
    ],
    "wof:name":"Eagle Quest Travel Inc",
    "wof:placetype":"venue"
},
  "geometry": {"coordinates":[-78.77652399999999,35.818231],"type":"Point"}
}