{
  "type": "Feature",
  "properties": {
    "addr:full":"935 Trexler Rd Salisbury NC 28146",
    "addr:housenumber":"935",
    "addr:postcode":"28146",
    "addr:street":"Trexler Rd",
    "iso:country":"US",
    "sg:address":"935 Trexler Rd",
    "sg:city":"Salisbury",
    "sg:classifiers":[
        {
            "category":"Building & Trades",
            "subcategory":"Construction",
            "type":"Services"
        }
    ],
    "sg:phone":"+1 704 636 9415",
    "sg:postcode":"28146",
    "sg:province":"NC",
    "sg:tags":[
        "contractor"
    ],
    "wof:name":"Steven Trexler",
    "wof:placetype":"venue"
},
  "geometry": {"coordinates":[-80.369146,35.600276],"type":"Point"}
}