{
  "type": "Feature",
  "properties": {
    "addr:full":"314 Central Ave Butner NC 27509",
    "addr:housenumber":"314",
    "addr:postcode":"27509",
    "addr:street":"Central Ave",
    "iso:country":"US",
    "sg:address":"314 Central Ave",
    "sg:city":"Butner",
    "sg:classifiers":[
        {
            "category":"Personal",
            "subcategory":"Beauty Salon",
            "type":"Services"
        }
    ],
    "sg:phone":"+1 919 575 9467",
    "sg:postcode":"27509",
    "sg:province":"NC",
    "wof:name":"Phyllis's Touch Beauty Salon",
    "wof:placetype":"venue"
},
  "geometry": {"coordinates":[-78.759406,36.135109],"type":"Point"}
}