{
  "type": "Feature",
  "properties": {
    "addr:full":"1525 S Stratford Rd Winston Salem NC 27103",
    "addr:housenumber":"1525",
    "addr:postcode":"27103",
    "addr:street":"S Stratford Rd",
    "iso:country":"US",
    "sg:address":"1525 S Stratford Rd",
    "sg:city":"Winston Salem",
    "sg:classifiers":[
        {
            "category":"Building & Trades",
            "subcategory":"Equipment Rental",
            "type":"Services"
        }
    ],
    "sg:phone":"+1 336 275 4848",
    "sg:postcode":"27103",
    "sg:province":"NC",
    "sg:tags":[
        "yard"
    ],
    "sg:website":"www.hauserrentalservice.com",
    "wof:name":"Hauser Rental Svc",
    "wof:placetype":"venue"
},
  "geometry": {"coordinates":[-80.303408,36.072758],"type":"Point"}
}