{
  "type": "Feature",
  "properties": {
    "iso:country":"US",
    "sg:address":"2003 Athena Ct",
    "sg:city":"Greensboro",
    "sg:classifiers":[
        {
            "category":"Travel",
            "subcategory":"Hotels & Motels",
            "type":"Entertainment"
        }
    ],
    "sg:phone":"+1 336 294 9922",
    "sg:postcode":"27407",
    "sg:province":"NC",
    "wof:name":"Ramada Inn Convention/Coliseum",
    "wof:placetype":"venue"
},
  "geometry": {"coordinates":[-79.844341,36.04376],"type":"Point"}
}