{
  "type": "Feature",
  "properties": {
    "addr:full":"3012 High Point Rd Greensboro NC 27403",
    "addr:housenumber":"3012",
    "addr:postcode":"27403",
    "addr:street":"High Point Rd",
    "iso:country":"US",
    "sg:address":"3012 High Point Rd",
    "sg:city":"Greensboro",
    "sg:classifiers":[
        {
            "category":"Personal",
            "type":"Services"
        }
    ],
    "sg:phone":"+1 336 852 7449",
    "sg:postcode":"27403",
    "sg:province":"NC",
    "sg:tags":[
        "merchandise"
    ],
    "wof:name":"Raveen Hair Replacement",
    "wof:placetype":"venue"
},
  "geometry": {"coordinates":[-79.83626099999999,36.047943],"type":"Point"}
}