{
  "type": "Feature",
  "properties": {
    "iso:country":"US",
    "sg:address":"61 Sun Rd",
    "sg:city":"Lumberton",
    "sg:classifiers":[
        {
            "category":"Building & Trades",
            "subcategory":"Construction",
            "type":"Services"
        }
    ],
    "sg:phone":"+1 910 739 7545",
    "sg:postcode":"28358",
    "sg:province":"NC",
    "sg:tags":[
        "roofing",
        "contractor"
    ],
    "wof:name":"Jerry Woods Roofing",
    "wof:placetype":"venue"
},
  "geometry": {"coordinates":[-78.998464,34.726729],"type":"Point"}
}