{
  "type": "Feature",
  "properties": {
    "addr:full":"1009 W C St Kannapolis NC 28081",
    "addr:housenumber":"1009",
    "addr:postcode":"28081",
    "addr:street":"W C St",
    "iso:country":"US",
    "sg:address":"1009 W C St",
    "sg:city":"Kannapolis",
    "sg:classifiers":[
        {
            "category":"Social Services",
            "subcategory":"Child Care",
            "type":"Services"
        }
    ],
    "sg:phone":"+1   ",
    "sg:postcode":"28081",
    "sg:province":"NC",
    "sg:tags":[
        "day"
    ],
    "wof:name":"Village Day Care",
    "wof:placetype":"venue"
},
  "geometry": {"coordinates":[-80.636235,35.503399],"type":"Point"}
}