{
  "type": "Feature",
  "properties": {
    "iso:country":"US",
    "sg:address":"570 Brevard Rd",
    "sg:city":"Asheville",
    "sg:classifiers":[
        {
            "category":"Wholesale",
            "subcategory":"Dairy",
            "type":"Manufacturing & Wholesale Goods"
        }
    ],
    "sg:phone":"+1 828 258 3969",
    "sg:postcode":"28806",
    "sg:province":"NC",
    "sg:tags":[
        "shop",
        "cheese"
    ],
    "sg:website":"www.mtnsunshinefarms.com",
    "wof:name":"Mountain Sunshine Farms",
    "wof:placetype":"venue"
},
  "geometry": {"coordinates":[-82.59989899999999,35.553902],"type":"Point"}
}