{
  "type": "Feature",
  "properties": {
    "addr:full":"503 Oakview Rd High Point NC 27265",
    "addr:housenumber":"503",
    "addr:postcode":"27265",
    "addr:street":"Oakview Rd",
    "iso:country":"US",
    "sg:address":"503 Oakview Rd",
    "sg:city":"High Point",
    "sg:classifiers":[
        {
            "category":"Communications",
            "subcategory":"Film & Video Production",
            "type":"Services"
        }
    ],
    "sg:phone":"+1   ",
    "sg:postcode":"27265",
    "sg:province":"NC",
    "sg:tags":[
        "motion"
    ],
    "wof:name":"Twin Engines Productions Inc",
    "wof:placetype":"venue"
},
  "geometry": {"coordinates":[-80.02145,35.998928],"type":"Point"}
}