{
  "type": "Feature",
  "properties": {
    "addr:full":"908 Wayland St Windsor NC 27983",
    "addr:housenumber":"908",
    "addr:postcode":"27983",
    "addr:street":"Wayland St",
    "iso:country":"US",
    "sg:address":"908 Wayland St",
    "sg:city":"Windsor",
    "sg:classifiers":[
        {
            "category":"Building & Trades",
            "subcategory":"Cleaning & Sanitation",
            "type":"Services"
        }
    ],
    "sg:phone":"+1 252 794 9343",
    "sg:postcode":"27983",
    "sg:province":"NC",
    "sg:tags":[
        "fireplace",
        "chimney"
    ],
    "wof:name":"Under The Rainbow",
    "wof:placetype":"venue"
},
  "geometry": {"coordinates":[-76.960279,36.002285],"type":"Point"}
}