{
  "type": "Feature",
  "properties": {
    "iso:country":"US",
    "sg:address":"2704 Neuse Blvd",
    "sg:city":"New Bern",
    "sg:classifiers":[
        {
            "category":"Personal",
            "type":"Services"
        }
    ],
    "sg:phone":"+1   ",
    "sg:postcode":"28562",
    "sg:province":"NC",
    "sg:tags":[
        "shop",
        "beauty"
    ],
    "wof:name":"Totally Tan",
    "wof:placetype":"venue"
},
  "geometry": {"coordinates":[-77.080322,35.11978],"type":"Point"}
}