{
  "type": "Feature",
  "properties": {
    "addr:full":"209 Park St Belmont NC 28012",
    "addr:housenumber":"209",
    "addr:postcode":"28012",
    "addr:street":"Park St",
    "iso:country":"US",
    "sg:address":"209 Park St",
    "sg:city":"Belmont",
    "sg:classifiers":[
        {
            "category":"Health Services",
            "subcategory":"Doctor",
            "type":"Services"
        }
    ],
    "sg:phone":"+1 704 825 3388",
    "sg:postcode":"28012",
    "sg:province":"NC",
    "sg:tags":[
        "medical"
    ],
    "wof:name":"Charlotte Eye Ear Nose and",
    "wof:placetype":"venue"
},
  "geometry": {"coordinates":[-81.03144399999999,35.245991],"type":"Point"}
}