{
  "type": "Feature",
  "properties": {
    "iso:country":"US",
    "sg:address":"2800 Rowland Rd",
    "sg:city":"Raleigh",
    "sg:classifiers":[
        {
            "category":"Home & Garden",
            "subcategory":"Household Appliances",
            "type":"Retail Goods"
        },
        {
            "category":"Utilities",
            "type":"Services"
        },
        {
            "category":"Building & Trades",
            "subcategory":"Construction",
            "type":"Services"
        },
        {
            "category":"Professional",
            "subcategory":"Engineering",
            "type":"Services"
        }
    ],
    "sg:phone":"+1 919 878 0008",
    "sg:postcode":"27615",
    "sg:province":"NC",
    "sg:tags":[
        "repair",
        "pump",
        "system",
        "specialty",
        "equipment",
        "geothermal",
        "heating",
        "contractor",
        "cooling",
        "heat",
        "air conditioning"
    ],
    "sg:website":"http://www.raleighheatingandair.com",
    "wof:name":"Raleigh Heating & Air Inc",
    "wof:placetype":"venue"
},
  "geometry": {"coordinates":[-78.590692,35.879723],"type":"Point"}
}