{
  "type": "Feature",
  "properties": {
    "iso:country":"US",
    "sg:address":"4139 Indian Trl",
    "sg:city":"Oxford",
    "sg:classifiers":[
        {
            "category":"Retail",
            "subcategory":"Portrait Studio",
            "type":"Services"
        }
    ],
    "sg:phone":"+1   ",
    "sg:postcode":"27565",
    "sg:province":"NC",
    "sg:tags":[
        "photo"
    ],
    "wof:name":"Paul Heidepriem Photography",
    "wof:placetype":"venue"
},
  "geometry": {"coordinates":[-78.53456799999999,36.336798],"type":"Point"}
}