{
  "type": "Feature",
  "properties": {
    "iso:country":"US",
    "sg:address":"101 E Bodenhamer St",
    "sg:city":"Kernersville",
    "sg:classifiers":[
        {
            "category":"Retail",
            "subcategory":"Auto Repair",
            "type":"Services"
        }
    ],
    "sg:phone":"+1 336 996 7968",
    "sg:postcode":"27284",
    "sg:province":"NC",
    "sg:tags":[
        "muffler",
        "exhaust",
        "system"
    ],
    "wof:name":"Perfection Exhaust Inc",
    "wof:placetype":"venue"
},
  "geometry": {"coordinates":[-80.069704,36.121164],"type":"Point"}
}