{
  "type": "Feature",
  "properties": {
    "addr:full":"321 W Main St Durham NC 27701",
    "addr:housenumber":"321",
    "addr:postcode":"27701",
    "addr:street":"W Main St",
    "iso:country":"US",
    "sg:address":"321 W Main St",
    "sg:city":"Durham",
    "sg:classifiers":[
        {
            "category":"Manufacturing",
            "subcategory":"Printing",
            "type":"Manufacturing & Wholesale Goods"
        }
    ],
    "sg:phone":"+1 919 683 2078",
    "sg:postcode":"27701",
    "sg:province":"NC",
    "sg:tags":[
        "commercial",
        "offset"
    ],
    "wof:name":"Faulkner Bus Prtg & Off Sup",
    "wof:placetype":"venue"
},
  "geometry": {"coordinates":[-78.90373099999999,35.996645],"type":"Point"}
}