{
  "type": "Feature",
  "properties": {
    "addr:full":"1001 S Sterling St Morganton NC 28655",
    "addr:housenumber":"1001",
    "addr:postcode":"28655",
    "addr:street":"S Sterling St",
    "iso:country":"US",
    "sg:address":"1001 S Sterling St",
    "sg:city":"Morganton",
    "sg:classifiers":[
        {
            "category":"Organizations",
            "subcategory":"Non-profit Organization",
            "type":"Services"
        }
    ],
    "sg:phone":"+1 828 433 4719",
    "sg:postcode":"28655",
    "sg:province":"NC",
    "sg:tags":[
        "human"
    ],
    "wof:name":"Turning Point Svc",
    "wof:placetype":"venue"
},
  "geometry": {"coordinates":[-81.67715699999999,35.736782],"type":"Point"}
}