{
  "type": "Feature",
  "properties": {
    "addr:full":"571 N Bridge St Eden NC 27288",
    "addr:housenumber":"571",
    "addr:postcode":"27288",
    "addr:street":"N Bridge St",
    "iso:country":"US",
    "sg:address":"571 N Bridge St",
    "sg:city":"Eden",
    "sg:classifiers":[
        {
            "category":"Professional",
            "subcategory":"Management & Consulting",
            "type":"Services"
        }
    ],
    "sg:phone":"+1 336 623 7355",
    "sg:postcode":"27288",
    "sg:province":"NC",
    "sg:tags":[
        "consultant",
        "safety"
    ],
    "wof:name":"Draeger Safety",
    "wof:placetype":"venue"
},
  "geometry": {"coordinates":[-79.76482900000001,36.493416],"type":"Point"}
}