{
  "type": "Feature",
  "properties": {
    "iso:country":"US",
    "sg:address":"4809 E Fork Ln",
    "sg:city":"Monroe",
    "sg:classifiers":[
        {
            "category":"Wholesale",
            "subcategory":"Machinery & Supplies",
            "type":"Manufacturing & Wholesale Goods"
        }
    ],
    "sg:phone":"+1 704 289 5099",
    "sg:postcode":"28110",
    "sg:province":"NC",
    "sg:tags":[
        "ball",
        "valve"
    ],
    "wof:name":"Starline Americas Inc",
    "wof:placetype":"venue"
},
  "geometry": {"coordinates":[-80.613953,35.059656],"type":"Point"}
}