{
  "type": "Feature",
  "properties": {
    "addr:full":"16501 Northcross Dr Huntersville NC 28078",
    "addr:housenumber":"16501",
    "addr:postcode":"28078",
    "addr:street":"Northcross Dr",
    "iso:country":"US",
    "sg:address":"16501 Northcross Dr",
    "sg:city":"Huntersville",
    "sg:classifiers":[
        {
            "category":"Health Services",
            "subcategory":"Health Practitioner",
            "type":"Services"
        }
    ],
    "sg:phone":"+1   ",
    "sg:postcode":"28078",
    "sg:province":"NC",
    "wof:name":"Therapeutic Massage Bdy Works",
    "wof:placetype":"venue"
},
  "geometry": {"coordinates":[-80.870197,35.434455],"type":"Point"}
}