{
  "type": "Feature",
  "properties": {
    "iso:country":"US",
    "sg:address":"102 W Main St",
    "sg:city":"Aberdeen",
    "sg:classifiers":[
        {
            "category":"Building & Trades",
            "subcategory":"Construction",
            "type":"Services"
        }
    ],
    "sg:phone":"+1 910 944 0944",
    "sg:postcode":"28315",
    "sg:province":"NC",
    "sg:tags":[
        "general",
        "contractor"
    ],
    "wof:name":"Dent's Construction Co",
    "wof:placetype":"venue"
},
  "geometry": {"coordinates":[-79.428173,35.132327],"type":"Point"}
}