{
  "type": "Feature",
  "properties": {
    "iso:country":"US",
    "sg:address":"1806 W Markham Ave",
    "sg:city":"Durham",
    "sg:classifiers":[
        {
            "category":"Personal",
            "subcategory":"Beauty Salon",
            "type":"Services"
        }
    ],
    "sg:phone":"+1 919 286 1818",
    "sg:postcode":"27705",
    "sg:province":"NC",
    "wof:name":"Redz Hair Studio",
    "wof:placetype":"venue"
},
  "geometry": {"coordinates":[-78.920744,36.010052],"type":"Point"}
}