{
  "type": "Feature",
  "properties": {
    "addr:full":"13693 Garland Hwy Garland NC 28441",
    "addr:housenumber":"13693",
    "addr:postcode":"28441",
    "addr:street":"Garland Hwy",
    "iso:country":"US",
    "sg:address":"13693 Garland Hwy",
    "sg:city":"Garland",
    "sg:classifiers":[
        {
            "category":"Retail",
            "subcategory":"Auto Repair",
            "type":"Services"
        }
    ],
    "sg:phone":"+1 910 529 4466",
    "sg:postcode":"28441",
    "sg:province":"NC",
    "sg:tags":[
        "repairing",
        "automobile"
    ],
    "wof:name":"Barnes & Son Wrecker & Auto",
    "wof:placetype":"venue"
},
  "geometry": {"coordinates":[-78.36193400000001,34.817719],"type":"Point"}
}