{
  "type": "Feature",
  "properties": {
    "addr:full":"2834 Exeter Cir Raleigh NC 27608",
    "addr:housenumber":"2834",
    "addr:postcode":"27608",
    "addr:street":"Exeter Cir",
    "iso:country":"US",
    "sg:address":"2834 Exeter Cir",
    "sg:city":"Raleigh",
    "sg:classifiers":[
        {
            "category":"Banks & Credit Unions",
            "subcategory":"Financial Services",
            "type":"Services"
        }
    ],
    "sg:phone":"+1 919 510 0303",
    "sg:postcode":"27608",
    "sg:province":"NC",
    "sg:tags":[
        "investor"
    ],
    "wof:name":"Cast Investment Group Inc",
    "wof:placetype":"venue"
},
  "geometry": {"coordinates":[-78.66388999999999,35.814969],"type":"Point"}
}