{
  "type": "Feature",
  "properties": {
    "addr:full":"148 Fairview Ave Asheville NC 28803",
    "addr:housenumber":"148",
    "addr:postcode":"28803",
    "addr:street":"Fairview Ave",
    "iso:country":"US",
    "sg:address":"148 Fairview Ave",
    "sg:city":"Asheville",
    "sg:classifiers":[
        {
            "category":"Real Estate",
            "subcategory":"Real Estate Operator",
            "type":"Services"
        }
    ],
    "sg:phone":"+1 828 277 6000",
    "sg:postcode":"28803",
    "sg:province":"NC",
    "sg:tags":[
        "building",
        "parks"
    ],
    "wof:name":"River Bend Business Park",
    "wof:placetype":"venue"
},
  "geometry": {"coordinates":[-82.510891,35.566592],"type":"Point"}
}