{
  "type": "Feature",
  "properties": {
    "iso:country":"US",
    "sg:address":"1001 Waughtown St",
    "sg:city":"Winston Salem",
    "sg:classifiers":[
        {
            "category":"Restaurant",
            "type":"Food & Drink"
        }
    ],
    "sg:phone":"+1 336 788 6888",
    "sg:postcode":"27107",
    "sg:province":"NC",
    "sg:tags":[
        "eating"
    ],
    "wof:name":"LA Perlita Tacos Y Restaurante",
    "wof:placetype":"venue"
},
  "geometry": {"coordinates":[-80.21825699999999,36.069205],"type":"Point"}
}