{
  "type": "Feature",
  "properties": {
    "iso:country":"US",
    "sg:address":"1114 Millstream Ct",
    "sg:city":"Leland",
    "sg:classifiers":[
        {
            "category":"Professional",
            "subcategory":"Computer Services",
            "type":"Services"
        }
    ],
    "sg:phone":"+1 910 371 5999",
    "sg:postcode":"28451",
    "sg:province":"NC",
    "wof:name":"P C Solutions",
    "wof:placetype":"venue"
},
  "geometry": {"coordinates":[-78.03617,34.228327],"type":"Point"}
}