{
  "type": "Feature",
  "properties": {
    "iso:country":"US",
    "sg:address":"821 New Hope Rd",
    "sg:city":"Raleigh",
    "sg:classifiers":[
        {
            "category":"Organizations",
            "subcategory":"Religious Organization",
            "type":"Services"
        },
        {
            "category":"Building & Trades",
            "subcategory":"Landscaping Services",
            "type":"Services"
        }
    ],
    "sg:phone":"+1 919 231 9962",
    "sg:postcode":"27610",
    "sg:province":"NC",
    "sg:tags":[
        "tree",
        "church"
    ],
    "wof:name":"Burning Bush Ministries",
    "wof:placetype":"venue"
},
  "geometry": {"coordinates":[-78.559549,35.764775],"type":"Point"}
}