{
  "type": "Feature",
  "properties": {
    "iso:country":"US",
    "sg:address":"4552 Cindy Ln",
    "sg:city":"Concord",
    "sg:classifiers":[
        {
            "category":"Building & Trades",
            "subcategory":"Plumbing",
            "type":"Services"
        }
    ],
    "sg:phone":"+1 704 792 0617",
    "sg:postcode":"28025",
    "sg:province":"NC",
    "sg:tags":[
        "contractor"
    ],
    "wof:name":"Tnc Heating Air Inc",
    "wof:placetype":"venue"
},
  "geometry": {"coordinates":[-80.505838,35.475495],"type":"Point"}
}