{
  "type": "Feature",
  "properties": {
    "addr:full":"869 Town Centre Blvd Clayton NC 27520",
    "addr:housenumber":"869",
    "addr:postcode":"27520",
    "addr:street":"Town Centre Blvd",
    "iso:country":"US",
    "sg:address":"869 Town Centre Blvd",
    "sg:city":"Clayton",
    "sg:classifiers":[
        {
            "category":"Personal",
            "subcategory":"Beauty Salon",
            "type":"Services"
        }
    ],
    "sg:phone":"+1 919 553 9835",
    "sg:postcode":"27520",
    "sg:province":"NC",
    "sg:tags":[
        "manicuring"
    ],
    "wof:name":"E T Nails",
    "wof:placetype":"venue"
},
  "geometry": {"coordinates":[-78.496566,35.663455],"type":"Point"}
}