{
  "type": "Feature",
  "properties": {
    "iso:country":"US",
    "sg:address":"125 Cottage Pl",
    "sg:city":"Charlotte",
    "sg:classifiers":[
        {
            "category":"Insurance",
            "subcategory":"Insurance Agent",
            "type":"Services"
        }
    ],
    "sg:phone":"+1 704 376 7434",
    "sg:postcode":"28207",
    "sg:province":"NC",
    "wof:name":"Greenspon & Assoc",
    "wof:placetype":"venue"
},
  "geometry": {"coordinates":[-80.821224,35.198346],"type":"Point"}
}