{
  "type": "Feature",
  "properties": {
    "addr:full":"1237 Plaza Dr Burlington NC 27215",
    "addr:housenumber":"1237",
    "addr:postcode":"27215",
    "addr:street":"Plaza Dr",
    "iso:country":"US",
    "sg:address":"1237 Plaza Dr",
    "sg:city":"Burlington",
    "sg:classifiers":[
        {
            "category":"Shopping",
            "subcategory":"Clothing, Apparel, & Fashions",
            "type":"Retail Goods"
        }
    ],
    "sg:phone":"+1 336 229 0862",
    "sg:postcode":"27215",
    "sg:province":"NC",
    "sg:tags":[
        "infant",
        "wear"
    ],
    "wof:name":"Carter's Childrenswear",
    "wof:placetype":"venue"
},
  "geometry": {"coordinates":[-79.430418,36.065861],"type":"Point"}
}