{
  "type": "Feature",
  "properties": {
    "addr:full":"1601 Wayne St Sanford NC 27330",
    "addr:housenumber":"1601",
    "addr:postcode":"27330",
    "addr:street":"Wayne St",
    "iso:country":"US",
    "sg:address":"1601 Wayne St",
    "sg:city":"Sanford",
    "sg:classifiers":[
        {
            "category":"Building & Trades",
            "subcategory":"Construction",
            "type":"Services"
        }
    ],
    "sg:phone":"+1 919 774 0606",
    "sg:postcode":"27330",
    "sg:province":"NC",
    "sg:tags":[
        "masonry",
        "contractor"
    ],
    "wof:name":"Rollins Masonry Corporation",
    "wof:placetype":"venue"
},
  "geometry": {"coordinates":[-79.17682499999999,35.499594],"type":"Point"}
}