{
  "type": "Feature",
  "properties": {
    "iso:country":"US",
    "sg:address":"11 Edgebrook Cir",
    "sg:city":"Durham",
    "sg:classifiers":[
        {
            "category":"Building & Trades",
            "subcategory":"Construction",
            "type":"Services"
        }
    ],
    "sg:phone":"+1 919 559 7509",
    "sg:postcode":"27703",
    "sg:province":"NC",
    "sg:tags":[
        "painter"
    ],
    "wof:name":"Supreme Painting",
    "wof:placetype":"venue"
},
  "geometry": {"coordinates":[-78.84460799999999,35.938876],"type":"Point"}
}