{
  "type": "Feature",
  "properties": {
    "addr:full":"7309 Haymarket Ln Raleigh NC 27615",
    "addr:housenumber":"7309",
    "addr:postcode":"27615",
    "addr:street":"Haymarket Ln",
    "iso:country":"US",
    "sg:address":"7309 Haymarket Ln",
    "sg:city":"Raleigh",
    "sg:classifiers":[
        {
            "category":"Professional",
            "subcategory":"Management & Consulting",
            "type":"Services"
        }
    ],
    "sg:phone":"+1 919 848 1668",
    "sg:postcode":"27615",
    "sg:province":"NC",
    "sg:tags":[
        "export",
        "business"
    ],
    "wof:name":"Teknitrade Ltd",
    "wof:placetype":"venue"
},
  "geometry": {"coordinates":[-78.609157,35.886009],"type":"Point"}
}