{
  "type": "Feature",
  "properties": {
    "addr:full":"108 Canal St Wilmington NC 28405",
    "addr:housenumber":"108",
    "addr:postcode":"28405",
    "addr:street":"Canal St",
    "iso:country":"US",
    "sg:address":"108 Canal St",
    "sg:city":"Wilmington",
    "sg:classifiers":[
        {
            "category":"Government",
            "subcategory":"Office",
            "type":"Public Place"
        }
    ],
    "sg:phone":"+1 910 256 3035",
    "sg:postcode":"28405",
    "sg:province":"NC",
    "sg:tags":[
        "state",
        "program",
        "health"
    ],
    "wof:name":"Environment Health & Natural",
    "wof:placetype":"venue"
},
  "geometry": {"coordinates":[-77.816889,34.220582],"type":"Point"}
}