{
  "type": "Feature",
  "properties": {
    "iso:country":"US",
    "sg:address":"5520 Capital Center Dr",
    "sg:city":"Raleigh",
    "sg:classifiers":[
        {
            "category":"Utilities",
            "subcategory":"Mobile Phone",
            "type":"Services"
        }
    ],
    "sg:phone":"+1 919 233 3249",
    "sg:postcode":"27606",
    "sg:province":"NC",
    "sg:tags":[
        "communication",
        "radiotelephone"
    ],
    "wof:name":"Alltel",
    "wof:placetype":"venue"
},
  "geometry": {"coordinates":[-78.726009,35.768864],"type":"Point"}
}