{
  "type": "Feature",
  "properties": {
    "iso:country":"US",
    "sg:address":"561 Conley Rd",
    "sg:city":"Morganton",
    "sg:classifiers":[
        {
            "category":"Retail",
            "subcategory":"Auto Repair",
            "type":"Services"
        }
    ],
    "sg:phone":"+1 828 584 4485",
    "sg:postcode":"28655",
    "sg:province":"NC",
    "sg:tags":[
        "wrecker",
        "towing",
        "grading"
    ],
    "wof:name":"Branch's Towing & Grading",
    "wof:placetype":"venue"
},
  "geometry": {"coordinates":[-81.76090499999999,35.704659],"type":"Point"}
}