{
  "type": "Feature",
  "properties": {
    "iso:country":"US",
    "sg:address":"4627 Dellfield Way",
    "sg:city":"Charlotte",
    "sg:classifiers":[
        {
            "category":"Professional",
            "subcategory":"Management & Consulting",
            "type":"Services"
        }
    ],
    "sg:phone":"+1 704 595 1789",
    "sg:postcode":"28269",
    "sg:province":"NC",
    "sg:tags":[
        "consultant",
        "business"
    ],
    "wof:name":"Leading To Change Inc",
    "wof:placetype":"venue"
},
  "geometry": {"coordinates":[-80.785404,35.343283],"type":"Point"}
}