{
  "type": "Feature",
  "properties": {
    "addr:full":"1101 Nicholas St Henderson NC 27536",
    "addr:housenumber":"1101",
    "addr:postcode":"27536",
    "addr:street":"Nicholas St",
    "iso:country":"US",
    "sg:address":"1101 Nicholas St",
    "sg:city":"Henderson",
    "sg:classifiers":[
        {
            "category":"Restaurant",
            "type":"Food & Drink"
        }
    ],
    "sg:phone":"+1 252 492 9173",
    "sg:postcode":"27536",
    "sg:province":"NC",
    "wof:name":"Henderson Mexican Restaurant",
    "wof:placetype":"venue"
},
  "geometry": {"coordinates":[-78.405614,36.316375],"type":"Point"}
}