{
  "type": "Feature",
  "properties": {
    "addr:full":"1978 Old Mountain Rd Statesville NC 28625",
    "addr:housenumber":"1978",
    "addr:postcode":"28625",
    "addr:street":"Old Mountain Rd",
    "iso:country":"US",
    "sg:address":"1978 Old Mountain Rd",
    "sg:city":"Statesville",
    "sg:classifiers":[
        {
            "category":"Food & Beverages",
            "subcategory":"Groceries & Convenience Stores",
            "type":"Retail Goods"
        }
    ],
    "sg:phone":"+1 704 838 0740",
    "sg:postcode":"28625",
    "sg:province":"NC",
    "wof:name":"Prospt",
    "wof:placetype":"venue"
},
  "geometry": {"coordinates":[-80.99905099999999,35.774003],"type":"Point"}
}