{
  "type": "Feature",
  "properties": {
    "addr:full":"1641 US Hwy 70 E Garner NC 27529",
    "addr:housenumber":"1641",
    "addr:postcode":"27529",
    "addr:street":"Us Hwy 70 E",
    "iso:country":"US",
    "sg:address":"1641 US Hwy 70 E",
    "sg:city":"Garner",
    "sg:classifiers":[
        {
            "category":"Home & Garden",
            "subcategory":"Building Materials",
            "type":"Retail Goods"
        }
    ],
    "sg:phone":"+1 919 771 2833",
    "sg:postcode":"27529",
    "sg:province":"NC",
    "wof:name":"Medical Plastics",
    "wof:placetype":"venue"
},
  "geometry": {"coordinates":[-78.55596,35.6897],"type":"Point"}
}