{
  "type": "Feature",
  "properties": {
    "iso:country":"US",
    "sg:address":"3006 Sikes Mill Rd",
    "sg:city":"Monroe",
    "sg:classifiers":[
        {
            "category":"Education",
            "subcategory":"School",
            "type":"Public Place"
        }
    ],
    "sg:phone":"+1 704 753 2810",
    "sg:postcode":"28110",
    "sg:province":"NC",
    "wof:name":"Piedmont High School",
    "wof:placetype":"venue"
},
  "geometry": {"coordinates":[-80.493217,35.094273],"type":"Point"}
}