{
  "type": "Feature",
  "properties": {
    "addr:full":"3154 Mount Misery Rd NE Leland NC 28451",
    "addr:housenumber":"3154",
    "addr:postcode":"28451",
    "addr:street":"Mount Misery Rd Ne",
    "iso:country":"US",
    "sg:address":"3154 Mount Misery Rd NE",
    "sg:city":"Leland",
    "sg:classifiers":[
        {
            "category":"Shopping",
            "subcategory":"Florist",
            "type":"Retail Goods"
        }
    ],
    "sg:phone":"+1 910 383 2002",
    "sg:postcode":"28451",
    "sg:province":"NC",
    "wof:name":"Coastal Oasis Grnhse & Grdns",
    "wof:placetype":"venue"
},
  "geometry": {"coordinates":[-78.076858,34.304237],"type":"Point"}
}