{
  "type": "Feature",
  "properties": {
    "iso:country":"US",
    "sg:address":"1400 US Hwy 17",
    "sg:city":"New Bern",
    "sg:classifiers":[
        {
            "category":"Wholesale",
            "subcategory":"Machinery & Supplies",
            "type":"Manufacturing & Wholesale Goods"
        }
    ],
    "sg:phone":"+1 252 638 6021",
    "sg:postcode":"28560",
    "sg:province":"NC",
    "sg:tags":[
        "equipment",
        "construction",
        "rent"
    ],
    "wof:name":"Stewart Equipment Co Inc",
    "wof:placetype":"venue"
},
  "geometry": {"coordinates":[-77.027917,35.137705],"type":"Point"}
}