{
  "type": "Feature",
  "properties": {
    "iso:country":"US",
    "sg:address":"200 S 2nd St",
    "sg:city":"Albemarle",
    "sg:classifiers":[
        {
            "category":"Professional",
            "subcategory":"Lawyer & Legal Services",
            "type":"Services"
        }
    ],
    "sg:phone":"+1 704 985 1332",
    "sg:postcode":"28001",
    "sg:province":"NC",
    "sg:tags":[
        "attorney"
    ],
    "wof:name":"Parnell Law Firm",
    "wof:placetype":"venue"
},
  "geometry": {"coordinates":[-80.19812899999999,35.349393],"type":"Point"}
}