{
  "type": "Feature",
  "properties": {
    "addr:full":"866 Comer Rd Stoneville NC 27048",
    "addr:housenumber":"866",
    "addr:postcode":"27048",
    "addr:street":"Comer Rd",
    "iso:country":"US",
    "sg:address":"866 Comer Rd",
    "sg:city":"Stoneville",
    "sg:classifiers":[
        {
            "category":"Building & Trades",
            "subcategory":"Construction",
            "type":"Services"
        }
    ],
    "sg:phone":"+1 336 573 3281",
    "sg:postcode":"27048",
    "sg:province":"NC",
    "sg:tags":[
        "contractor"
    ],
    "wof:name":"Hundley Seamless Guttering",
    "wof:placetype":"venue"
},
  "geometry": {"coordinates":[-79.888064,36.449052],"type":"Point"}
}