{
  "type": "Feature",
  "properties": {
    "addr:full":"2007 Pratt Cir Franklinton NC 27525",
    "addr:housenumber":"2007",
    "addr:postcode":"27525",
    "addr:street":"Pratt Cir",
    "iso:country":"US",
    "sg:address":"2007 Pratt Cir",
    "sg:city":"Franklinton",
    "sg:classifiers":[
        {
            "category":"Building & Trades",
            "subcategory":"Construction",
            "type":"Services"
        }
    ],
    "sg:phone":"+1 919 529 1936",
    "sg:postcode":"27525",
    "sg:province":"NC",
    "sg:tags":[
        "general",
        "contractor"
    ],
    "wof:name":"H B Construction",
    "wof:placetype":"venue"
},
  "geometry": {"coordinates":[-78.565575,36.114254],"type":"Point"}
}