{
  "type": "Feature",
  "properties": {
    "iso:country":"US",
    "sg:address":"5945 W Wilkinson Blvd",
    "sg:city":"Belmont",
    "sg:classifiers":[
        {
            "category":"Restaurant",
            "type":"Food & Drink"
        }
    ],
    "sg:menulink":"http://www.allmenus.com/nc/south-point/54179-buddysbq/menu/",
    "sg:phone":"+1 704 825 8777",
    "sg:postcode":"28012",
    "sg:province":"NC",
    "sg:tags":[
        "barbecue",
        "american"
    ],
    "wof:name":"Buddy'sbq",
    "wof:placetype":"venue"
},
  "geometry": {"coordinates":[-81.059466,35.248936],"type":"Point"}
}