{
  "type": "Feature",
  "properties": {
    "iso:country":"US",
    "sg:address":"411 S Main St",
    "sg:city":"Jefferson",
    "sg:classifiers":[
        {
            "category":"Sports & Exercise",
            "subcategory":"Race Track",
            "type":"Entertainment"
        }
    ],
    "sg:phone":"+1 336 846 1234",
    "sg:postcode":"28640",
    "sg:province":"NC",
    "wof:name":"L A Racing",
    "wof:placetype":"venue"
},
  "geometry": {"coordinates":[-81.47631800000001,36.416024],"type":"Point"}
}