{
  "type": "Feature",
  "properties": {
    "iso:country":"US",
    "sg:address":"19826 River Falls Dr",
    "sg:city":"Davidson",
    "sg:classifiers":[
        {
            "category":"Professional",
            "subcategory":"Business Services",
            "type":"Services"
        }
    ],
    "sg:phone":"+1   ",
    "sg:postcode":"28036",
    "sg:province":"NC",
    "wof:name":"Beau Bally Enterprises Inc",
    "wof:placetype":"venue"
},
  "geometry": {"coordinates":[-80.79373099999999,35.467609],"type":"Point"}
}