{
  "type": "Feature",
  "properties": {
    "iso:country":"US",
    "sg:address":"1207 Spring Dr",
    "sg:city":"Shelby",
    "sg:classifiers":[
        {
            "category":"Real Estate",
            "subcategory":"Real Estate Operator",
            "type":"Services"
        }
    ],
    "sg:phone":"+1 704 482 7100",
    "sg:postcode":"28150",
    "sg:province":"NC",
    "sg:tags":[
        "property",
        "lessor"
    ],
    "wof:name":"McCarver & Sons",
    "wof:placetype":"venue"
},
  "geometry": {"coordinates":[-81.506112,35.300939],"type":"Point"}
}