{
  "type": "Feature",
  "properties": {
    "addr:full":"150 E Cedar St Cary NC 27511",
    "addr:housenumber":"150",
    "addr:postcode":"27511",
    "addr:street":"E Cedar St",
    "iso:country":"US",
    "sg:address":"150 E Cedar St",
    "sg:city":"Cary",
    "sg:classifiers":[
        {
            "category":"Manufacturing",
            "subcategory":"Motor Vehicles & Parts",
            "type":"Manufacturing & Wholesale Goods"
        }
    ],
    "sg:phone":"+1 919 380 1717",
    "sg:postcode":"27511",
    "sg:province":"NC",
    "sg:tags":[
        "screen",
        "printer",
        "advertising",
        "specialty"
    ],
    "wof:name":"Custom Screen Printing",
    "wof:placetype":"venue"
},
  "geometry": {"coordinates":[-78.780024,35.788009],"type":"Point"}
}