{
  "type": "Feature",
  "properties": {
    "iso:country":"US",
    "sg:address":"311 Mangrove Dr",
    "sg:city":"Emerald Isle",
    "sg:classifiers":[
        {
            "category":"Bars & Pubs",
            "type":"Food & Drink"
        }
    ],
    "sg:menulink":"http://www.allmenus.com/nc/white-oak/141262-flipperz-family-bar--grill/menu/",
    "sg:phone":"+1 252 354 7775",
    "sg:postcode":"28594",
    "sg:province":"NC",
    "sg:tags":[
        "american"
    ],
    "wof:name":"Flipperz Family Bar & Grill",
    "wof:placetype":"venue"
},
  "geometry": {"coordinates":[-77.04216700000001,34.663551],"type":"Point"}
}