{
  "type": "Feature",
  "properties": {
    "iso:country":"US",
    "sg:address":"12337 Lazy Oak Ln",
    "sg:city":"Charlotte",
    "sg:classifiers":[
        {
            "category":"Shopping",
            "subcategory":"Computers & Home Electronics",
            "type":"Retail Goods"
        }
    ],
    "sg:phone":"+1 704 583 4376",
    "sg:postcode":"28273",
    "sg:province":"NC",
    "sg:tags":[
        "repair"
    ],
    "wof:name":"Networking Specialists Of Nc",
    "wof:placetype":"venue"
},
  "geometry": {"coordinates":[-80.970799,35.123301],"type":"Point"}
}