{
  "type": "Feature",
  "properties": {
    "addr:full":"2605 Branchwood Dr Greensboro NC 27408",
    "addr:housenumber":"2605",
    "addr:postcode":"27408",
    "addr:street":"Branchwood Dr",
    "iso:country":"US",
    "sg:address":"2605 Branchwood Dr",
    "sg:city":"Greensboro",
    "sg:classifiers":[
        {
            "category":"Home & Garden",
            "subcategory":"Carpets & Floor Coverings",
            "type":"Retail Goods"
        }
    ],
    "sg:phone":"+1 336 282 8210",
    "sg:postcode":"27408",
    "sg:province":"NC",
    "sg:tags":[
        "dealer",
        "rug"
    ],
    "wof:name":"Sharp-Carter Corp",
    "wof:placetype":"venue"
},
  "geometry": {"coordinates":[-79.82362500000001,36.105901],"type":"Point"}
}