{
  "type": "Feature",
  "properties": {
    "addr:full":"1411 Anthony Rd Burlington NC 27215",
    "addr:housenumber":"1411",
    "addr:postcode":"27215",
    "addr:street":"Anthony Rd",
    "iso:country":"US",
    "sg:address":"1411 Anthony Rd",
    "sg:city":"Burlington",
    "sg:classifiers":[
        {
            "category":"Professional",
            "subcategory":"Art Services",
            "type":"Services"
        }
    ],
    "sg:phone":"+1   ",
    "sg:postcode":"27215",
    "sg:province":"NC",
    "sg:tags":[
        "photography",
        "commercial"
    ],
    "wof:name":"Roy King Photography",
    "wof:placetype":"venue"
},
  "geometry": {"coordinates":[-79.442606,36.05576],"type":"Point"}
}