{
  "type": "Feature",
  "properties": {
    "addr:full":"1258 Cedar Point Rd Newton Grove NC 28366",
    "addr:housenumber":"1258",
    "addr:postcode":"28366",
    "addr:street":"Cedar Point Rd",
    "iso:country":"US",
    "sg:address":"1258 Cedar Point Rd",
    "sg:city":"Newton Grove",
    "sg:classifiers":[
        {
            "category":"Organizations",
            "subcategory":"Religious Organization",
            "type":"Services"
        }
    ],
    "sg:phone":"+1   ",
    "sg:postcode":"28366",
    "sg:province":"NC",
    "wof:name":"Cedar Point Disciple Church",
    "wof:placetype":"venue"
},
  "geometry": {"coordinates":[-78.33711599999999,35.208666],"type":"Point"}
}