{
  "type": "Feature",
  "properties": {
    "iso:country":"US",
    "sg:address":"4064 Colony Rd",
    "sg:city":"Charlotte",
    "sg:classifiers":[
        {
            "category":"Banks & Credit Unions",
            "subcategory":"Investment Brokerage",
            "type":"Services"
        }
    ],
    "sg:phone":"+1 704 372 8670",
    "sg:postcode":"28211",
    "sg:province":"NC",
    "sg:tags":[
        "advisory",
        "financial"
    ],
    "sg:website":"www.sterling-capital.com",
    "wof:name":"Sterling Capital Management Co",
    "wof:placetype":"venue"
},
  "geometry": {"coordinates":[-80.82236,35.153226],"type":"Point"}
}