{
  "type": "Feature",
  "properties": {
    "iso:country":"US",
    "sg:address":"5560 Dona Rd",
    "sg:city":"Julian",
    "sg:classifiers":[
        {
            "category":"Banks & Credit Unions",
            "subcategory":"Financial Services",
            "type":"Services"
        }
    ],
    "sg:phone":"+1 336 685 4327",
    "sg:postcode":"27283",
    "sg:province":"NC",
    "sg:tags":[
        "management",
        "open",
        "investment"
    ],
    "wof:name":"Applied Management Inc",
    "wof:placetype":"venue"
},
  "geometry": {"coordinates":[-79.656666,35.933396],"type":"Point"}
}