{
  "type": "Feature",
  "properties": {
    "addr:full":"1672 Mount Pisgah Rd SW Supply NC 28462",
    "addr:housenumber":"1672",
    "addr:postcode":"28462",
    "addr:street":"Mount Pisgah Rd Sw",
    "iso:country":"US",
    "sg:address":"1672 Mount Pisgah Rd SW",
    "sg:city":"Supply",
    "sg:classifiers":[
        {
            "category":"Organizations",
            "subcategory":"Religious Organization",
            "type":"Services"
        }
    ],
    "sg:phone":"+1   ",
    "sg:postcode":"28462",
    "sg:province":"NC",
    "wof:name":"Brunswick Island Baptst Church",
    "wof:placetype":"venue"
},
  "geometry": {"coordinates":[-78.31080900000001,33.951723],"type":"Point"}
}