{
  "type": "Feature",
  "properties": {
    "iso:country":"US",
    "sg:address":"2801 Bevill Oaks Rd",
    "sg:city":"Browns Summit",
    "sg:classifiers":[
        {
            "category":"Real Estate",
            "subcategory":"Real Estate Agent",
            "type":"Services"
        }
    ],
    "sg:phone":"+1 336 656 9887",
    "sg:postcode":"27214",
    "sg:province":"NC",
    "wof:name":"Jeanette Lake Realty",
    "wof:placetype":"venue"
},
  "geometry": {"coordinates":[-79.740596,36.244859],"type":"Point"}
}