{
  "type": "Feature",
  "properties": {
    "addr:full":"3011 S Church St Burlington NC 27215",
    "addr:housenumber":"3011",
    "addr:postcode":"27215",
    "addr:street":"S Church St",
    "iso:country":"US",
    "sg:address":"3011 S Church St",
    "sg:city":"Burlington",
    "sg:classifiers":[
        {
            "category":"Professional",
            "subcategory":"Lawyer & Legal Services",
            "type":"Services"
        }
    ],
    "sg:phone":"+1 336 524 0183",
    "sg:postcode":"27215",
    "sg:province":"NC",
    "sg:tags":[
        "attorney"
    ],
    "wof:name":"Tuggle & Royster",
    "wof:placetype":"venue"
},
  "geometry": {"coordinates":[-79.494474,36.0803],"type":"Point"}
}