{
  "type": "Feature",
  "properties": {
    "addr:full":"3405 Market St Wilmington NC 28403",
    "addr:housenumber":"3405",
    "addr:postcode":"28403",
    "addr:street":"Market St",
    "iso:country":"US",
    "sg:address":"3405 Market St",
    "sg:city":"Wilmington",
    "sg:classifiers":[
        {
            "category":"Shopping",
            "type":"Retail Goods"
        }
    ],
    "sg:phone":"+1 910 762 3231",
    "sg:postcode":"28403",
    "sg:province":"NC",
    "sg:tags":[
        "miscellaneous",
        "store"
    ],
    "wof:name":"Retail Merchants Systems",
    "wof:placetype":"venue"
},
  "geometry": {"coordinates":[-77.902494,34.240671],"type":"Point"}
}