{
  "type": "Feature",
  "properties": {
    "addr:full":"104 Crystal Ct Cary NC 27513",
    "addr:housenumber":"104",
    "addr:postcode":"27513",
    "addr:street":"Crystal Ct",
    "iso:country":"US",
    "sg:address":"104 Crystal Ct",
    "sg:city":"Cary",
    "sg:classifiers":[
        {
            "category":"Utilities",
            "subcategory":"Refuse",
            "type":"Services"
        }
    ],
    "sg:phone":"+1 919 463 9997",
    "sg:postcode":"27513",
    "sg:province":"NC",
    "sg:tags":[
        "garbage",
        "collection"
    ],
    "wof:name":"Poole & Assoc",
    "wof:placetype":"venue"
},
  "geometry": {"coordinates":[-78.773926,35.807122],"type":"Point"}
}