{
  "type": "Feature",
  "properties": {
    "addr:full":"56 Edgewood Ave NE Concord NC 28025",
    "addr:housenumber":"56",
    "addr:postcode":"28025",
    "addr:street":"Edgewood Ave Ne",
    "iso:country":"US",
    "sg:address":"56 Edgewood Ave NE",
    "sg:city":"Concord",
    "sg:classifiers":[
        {
            "category":"Building & Trades",
            "subcategory":"Construction",
            "type":"Services"
        }
    ],
    "sg:phone":"+1 704 788 4049",
    "sg:postcode":"28025",
    "sg:province":"NC",
    "sg:tags":[
        "house"
    ],
    "wof:name":"Newells Cnstr & Remodling",
    "wof:placetype":"venue"
},
  "geometry": {"coordinates":[-80.582065,35.414493],"type":"Point"}
}