{
  "type": "Feature",
  "properties": {
    "iso:country":"US",
    "sg:address":"3414 Hillsborough Rd",
    "sg:city":"Durham",
    "sg:classifiers":[
        {
            "category":"Autos & Motor Vehicles",
            "subcategory":"Fuel & Gas Station",
            "type":"Retail Goods"
        }
    ],
    "sg:phone":"+1 919 309 7477",
    "sg:postcode":"27705",
    "sg:province":"NC",
    "sg:tags":[
        "oil"
    ],
    "wof:name":"University Shell",
    "wof:placetype":"venue"
},
  "geometry": {"coordinates":[-78.945285,36.018964],"type":"Point"}
}