{
  "type": "Feature",
  "properties": {
    "addr:full":"125 Remount Rd Charlotte NC 28203",
    "addr:housenumber":"125",
    "addr:postcode":"28203",
    "addr:street":"Remount Rd",
    "iso:country":"US",
    "sg:address":"125 Remount Rd",
    "sg:city":"Charlotte",
    "sg:classifiers":[
        {
            "category":"Shopping",
            "subcategory":"Clothing, Apparel, & Fashions",
            "type":"Retail Goods"
        }
    ],
    "sg:phone":"+1 704 527 5772",
    "sg:postcode":"28203",
    "sg:province":"NC",
    "wof:name":"Art Styles",
    "wof:placetype":"venue"
},
  "geometry": {"coordinates":[-80.867092,35.203619],"type":"Point"}
}