{
  "type": "Feature",
  "properties": {
    "addr:full":"605 N Garnett St Henderson NC 27536",
    "addr:housenumber":"605",
    "addr:postcode":"27536",
    "addr:street":"N Garnett St",
    "iso:country":"US",
    "sg:address":"605 N Garnett St",
    "sg:city":"Henderson",
    "sg:classifiers":[
        {
            "category":"Personal",
            "subcategory":"Beauty Salon",
            "type":"Services"
        }
    ],
    "sg:phone":"+1 252 438 7433",
    "sg:postcode":"27536",
    "sg:province":"NC",
    "sg:tags":[
        "shop"
    ],
    "wof:name":"Styl-Ees Beauty Salon",
    "wof:placetype":"venue"
},
  "geometry": {"coordinates":[-78.397113,36.331452],"type":"Point"}
}