{
  "type": "Feature",
  "properties": {
    "iso:country":"US",
    "sg:address":"3360 Smith Farm Rd",
    "sg:city":"Matthews",
    "sg:classifiers":[
        {
            "category":"Home & Garden",
            "subcategory":"Building Materials",
            "type":"Retail Goods"
        }
    ],
    "sg:phone":"+1 704 821 8116",
    "sg:postcode":"28104",
    "sg:province":"NC",
    "wof:name":"Banner Kitchens",
    "wof:placetype":"venue"
},
  "geometry": {"coordinates":[-80.68028099999999,35.089034],"type":"Point"}
}