{
  "type": "Feature",
  "properties": {
    "addr:full":"712 Montville Ct Wake Forest NC 27587",
    "addr:housenumber":"712",
    "addr:postcode":"27587",
    "addr:street":"Montville Ct",
    "iso:country":"US",
    "sg:address":"712 Montville Ct",
    "sg:city":"Wake Forest",
    "sg:classifiers":[
        {
            "category":"Building & Trades",
            "subcategory":"Cleaning & Sanitation",
            "type":"Services"
        }
    ],
    "sg:phone":"+1 919 562 4343",
    "sg:postcode":"27587",
    "sg:province":"NC",
    "sg:tags":[
        "janitor"
    ],
    "wof:name":"National Cleaning Corp",
    "wof:placetype":"venue"
},
  "geometry": {"coordinates":[-78.506382,35.967207],"type":"Point"}
}