{
  "type": "Feature",
  "properties": {
    "addr:full":"4486 Raceway Dr SW Concord NC 28027",
    "addr:housenumber":"4486",
    "addr:postcode":"28027",
    "addr:street":"Raceway Dr Sw",
    "iso:country":"US",
    "sg:address":"4486 Raceway Dr SW",
    "sg:city":"Concord",
    "sg:classifiers":[
        {
            "category":"Manufacturing",
            "subcategory":"Metals",
            "type":"Manufacturing & Wholesale Goods"
        }
    ],
    "sg:phone":"+1 704 455 3717",
    "sg:postcode":"28027",
    "sg:province":"NC",
    "sg:tags":[
        "work",
        "structural"
    ],
    "sg:website":"www.flawtech.com",
    "wof:name":"Flawtech Inc",
    "wof:placetype":"venue"
},
  "geometry": {"coordinates":[-80.61756800000001,35.354081],"type":"Point"}
}