{
  "type": "Feature",
  "properties": {
    "iso:country":"US",
    "sg:address":"1270 Jacobs Ln",
    "sg:city":"Morganton",
    "sg:classifiers":[
        {
            "category":"Freight",
            "type":"Transportation"
        }
    ],
    "sg:phone":"+1 828 437 9643",
    "sg:postcode":"28655",
    "sg:province":"NC",
    "sg:tags":[
        "operator",
        "local",
        "trucking"
    ],
    "wof:name":"Gary Allison Hauling",
    "wof:placetype":"venue"
},
  "geometry": {"coordinates":[-81.704843,35.691699],"type":"Point"}
}