{
  "type": "Feature",
  "properties": {
    "addr:full":"741 Erwin Rd Durham NC 27707",
    "addr:housenumber":"741",
    "addr:postcode":"27707",
    "addr:street":"Erwin Rd",
    "iso:country":"US",
    "sg:address":"741 Erwin Rd",
    "sg:city":"Durham",
    "sg:classifiers":[
        {
            "category":"Building & Trades",
            "subcategory":"Construction",
            "type":"Services"
        }
    ],
    "sg:phone":"+1 919 493 2125",
    "sg:postcode":"27707",
    "sg:province":"NC",
    "sg:tags":[
        "tennis",
        "court"
    ],
    "wof:name":"Oehler Court Co",
    "wof:placetype":"venue"
},
  "geometry": {"coordinates":[-78.99991,35.98021],"type":"Point"}
}