{
  "type": "Feature",
  "properties": {
    "iso:country":"US",
    "sg:address":"3008 Hendersonville Rd",
    "sg:city":"Fletcher",
    "sg:classifiers":[
        {
            "category":"Autos & Motor Vehicles",
            "subcategory":"Auto Supplies",
            "type":"Retail Goods"
        }
    ],
    "sg:phone":"+1 828 684 2322",
    "sg:postcode":"28732",
    "sg:province":"NC",
    "sg:tags":[
        "automobile",
        "parts"
    ],
    "wof:name":"R & D Automotive Outlet",
    "wof:placetype":"venue"
},
  "geometry": {"coordinates":[-82.504615,35.440533],"type":"Point"}
}