{
  "type": "Feature",
  "properties": {
    "iso:country":"US",
    "sg:address":"1729 E Garrison Blvd",
    "sg:city":"Gastonia",
    "sg:classifiers":[
        {
            "category":"Organizations",
            "subcategory":"Religious Organization",
            "type":"Services"
        }
    ],
    "sg:phone":"+1 704 864 3681",
    "sg:postcode":"28054",
    "sg:province":"NC",
    "wof:name":"Parkwood Baptist Church",
    "wof:placetype":"venue"
},
  "geometry": {"coordinates":[-81.15181,35.252905],"type":"Point"}
}