{
  "type": "Feature",
  "properties": {
    "iso:country":"US",
    "sg:address":"102 E College St",
    "sg:city":"Salemburg",
    "sg:classifiers":[
        {
            "category":"Banks & Credit Unions",
            "subcategory":"Financial Services",
            "type":"Services"
        }
    ],
    "sg:phone":"+1 910 525 3411",
    "sg:postcode":"28365",
    "sg:province":"NC",
    "sg:tags":[
        "company",
        "holding"
    ],
    "wof:name":"WHB Holding Co Inc",
    "wof:placetype":"venue"
},
  "geometry": {"coordinates":[-78.06440499999999,35.198237],"type":"Point"}
}