{
  "type": "Feature",
  "properties": {
    "addr:full":"806 Courtland Ave Reidsville NC 27320",
    "addr:housenumber":"806",
    "addr:postcode":"27320",
    "addr:street":"Courtland Ave",
    "iso:country":"US",
    "sg:address":"806 Courtland Ave",
    "sg:city":"Reidsville",
    "sg:classifiers":[
        {
            "category":"Professional",
            "subcategory":"Business Services",
            "type":"Services"
        }
    ],
    "sg:phone":"+1   ",
    "sg:postcode":"27320",
    "sg:province":"NC",
    "wof:name":"House Works",
    "wof:placetype":"venue"
},
  "geometry": {"coordinates":[-79.67103400000001,36.348299],"type":"Point"}
}