{
  "type": "Feature",
  "properties": {
    "iso:country":"US",
    "sg:address":"812 N Charlotte Ave",
    "sg:city":"Monroe",
    "sg:classifiers":[
        {
            "category":"Food & Beverages",
            "subcategory":"Groceries & Convenience Stores",
            "type":"Retail Goods"
        }
    ],
    "sg:phone":"+1 704 289 3306",
    "sg:postcode":"28110",
    "sg:province":"NC",
    "wof:name":"Quick One Food Mart",
    "wof:placetype":"venue"
},
  "geometry": {"coordinates":[-80.55407599999999,34.989232],"type":"Point"}
}