{
  "type": "Feature",
  "properties": {
    "iso:country":"US",
    "sg:address":"3312 Battleground Ave",
    "sg:city":"Greensboro",
    "sg:classifiers":[
        {
            "category":"Health Services",
            "subcategory":"Doctor",
            "type":"Services"
        }
    ],
    "sg:phone":"+1 336 288 8523",
    "sg:postcode":"27410",
    "sg:province":"NC",
    "sg:tags":[
        "physician",
        "surgeon"
    ],
    "wof:name":"Tlc Laser Eye Ctr",
    "wof:placetype":"venue"
},
  "geometry": {"coordinates":[-79.84232799999999,36.120136],"type":"Point"}
}