{
  "type": "Feature",
  "properties": {
    "iso:country":"US",
    "sg:address":"126 Victoria Dr",
    "sg:city":"Wilmington",
    "sg:classifiers":[
        {
            "category":"Professional",
            "subcategory":"Research",
            "type":"Services"
        }
    ],
    "sg:phone":"+1   ",
    "sg:postcode":"28401",
    "sg:province":"NC",
    "sg:tags":[
        "commercial",
        "physical"
    ],
    "wof:name":"Voodoo Technologies Inc",
    "wof:placetype":"venue"
},
  "geometry": {"coordinates":[-77.932861,34.272478],"type":"Point"}
}