{
  "type": "Feature",
  "properties": {
    "addr:full":"4320 Kernersville Rd Kernersville NC 27284",
    "addr:postcode":"4320;27284",
    "addr:street":"Kernersville Rd",
    "iso:country":"US",
    "sg:address":"4320 Kernersville Rd",
    "sg:city":"Kernersville",
    "sg:classifiers":[
        {
            "category":"Real Estate",
            "subcategory":"Real Estate Agent",
            "type":"Services"
        }
    ],
    "sg:phone":"+1 336 650 1600",
    "sg:postcode":"27284",
    "sg:province":"NC",
    "wof:name":"October Realty Inc",
    "wof:placetype":"venue"
},
  "geometry": {"coordinates":[-80.138216,36.092234],"type":"Point"}
}