{
  "type": "Feature",
  "properties": {
    "iso:country":"US",
    "sg:address":"601 Greenfield St",
    "sg:city":"Wilmington",
    "sg:classifiers":[
        {
            "category":"Manufacturing",
            "subcategory":"Metals",
            "type":"Manufacturing & Wholesale Goods"
        }
    ],
    "sg:phone":"+1 910 251 0999",
    "sg:postcode":"28401",
    "sg:province":"NC",
    "sg:tags":[
        "coating"
    ],
    "wof:name":"Coastal Coatings Prot Coatngs",
    "wof:placetype":"venue"
},
  "geometry": {"coordinates":[-77.939061,34.217003],"type":"Point"}
}