{
  "type": "Feature",
  "properties": {
    "iso:country":"US",
    "sg:address":"118 Mackenan Dr",
    "sg:city":"Cary",
    "sg:classifiers":[
        {
            "category":"Health Services",
            "subcategory":"Medical Lab",
            "type":"Services"
        }
    ],
    "sg:phone":"+1 919 465 4310",
    "sg:postcode":"27511",
    "sg:province":"NC",
    "sg:tags":[
        "laboratory"
    ],
    "sg:website":"www.copernicusgroup.com",
    "wof:name":"Copernicus Group",
    "wof:placetype":"venue"
},
  "geometry": {"coordinates":[-78.809394,35.736978],"type":"Point"}
}