{
  "type": "Feature",
  "properties": {
    "iso:country":"US",
    "sg:address":"8601 Six Forks Rd",
    "sg:city":"Raleigh",
    "sg:classifiers":[
        {
            "category":"Professional",
            "subcategory":"Advertising",
            "type":"Services"
        }
    ],
    "sg:phone":"+1 919 848 2600",
    "sg:postcode":"27615",
    "sg:province":"NC",
    "sg:tags":[
        "counselor"
    ],
    "sg:website":"www.ossentials.com",
    "wof:name":"Rockett Brukhead Lewis/Winslow",
    "wof:placetype":"venue"
},
  "geometry": {"coordinates":[-78.65028599999999,35.897207],"type":"Point"}
}