{
  "type": "Feature",
  "properties": {
    "iso:country":"US",
    "sg:address":"320 1st Ave NW",
    "sg:city":"Hickory",
    "sg:classifiers":[
        {
            "category":"Building & Trades",
            "subcategory":"Plumbing",
            "type":"Services"
        }
    ],
    "sg:phone":"+1 828 322 2892",
    "sg:postcode":"28601",
    "sg:province":"NC",
    "sg:tags":[
        "contractor"
    ],
    "wof:name":"Alberts Heating & Air Conditi",
    "wof:placetype":"venue"
},
  "geometry": {"coordinates":[-81.34235,35.733366],"type":"Point"}
}