{
  "type": "Feature",
  "properties": {
    "addr:full":"1403 Dickinson Ave Greenville NC 27834",
    "addr:housenumber":"1403",
    "addr:postcode":"27834",
    "addr:street":"Dickinson Ave",
    "iso:country":"US",
    "sg:address":"1403 Dickinson Ave",
    "sg:city":"Greenville",
    "sg:classifiers":[
        {
            "category":"Personal",
            "subcategory":"Beauty Salon",
            "type":"Services"
        }
    ],
    "sg:phone":"+1   ",
    "sg:postcode":"27834",
    "sg:province":"NC",
    "sg:tags":[
        "shop"
    ],
    "wof:name":"Golden Touch Beauty Salon",
    "wof:placetype":"venue"
},
  "geometry": {"coordinates":[-77.384229,35.604917],"type":"Point"}
}