{
  "type": "Feature",
  "properties": {
    "addr:full":"806 Carolina Beach Ave N Carolina Beach NC 28428",
    "addr:housenumber":"806",
    "addr:postcode":"28428",
    "addr:street":"Carolina Beach Ave N Carolina Beach",
    "iso:country":"US",
    "sg:address":"806 Carolina Beach Ave N",
    "sg:city":"Carolina Beach",
    "sg:classifiers":[
        {
            "category":"Wholesale",
            "subcategory":"Machinery & Supplies",
            "type":"Manufacturing & Wholesale Goods"
        }
    ],
    "sg:phone":"+1 910 458 0690",
    "sg:postcode":"28428",
    "sg:province":"NC",
    "sg:tags":[
        "instrument",
        "radioactivity"
    ],
    "wof:name":"Two Tigers Radiological",
    "wof:placetype":"venue"
},
  "geometry": {"coordinates":[-77.88775800000001,34.044566],"type":"Point"}
}