{
  "type": "Feature",
  "properties": {
    "addr:full":"998 W Pine St Mount Airy NC 27030",
    "addr:housenumber":"998",
    "addr:postcode":"27030",
    "addr:street":"W Pine St",
    "iso:country":"US",
    "sg:address":"998 W Pine St",
    "sg:city":"Mount Airy",
    "sg:classifiers":[
        {
            "category":"Wholesale",
            "subcategory":"Electrical",
            "type":"Manufacturing & Wholesale Goods"
        }
    ],
    "sg:phone":"+1 336 786 9816",
    "sg:postcode":"27030",
    "sg:province":"NC",
    "sg:tags":[
        "equipment"
    ],
    "wof:name":"Ligon Electrical Sup Mt Airy",
    "wof:placetype":"venue"
},
  "geometry": {"coordinates":[-80.629122,36.500767],"type":"Point"}
}