{
  "type": "Feature",
  "properties": {
    "iso:country":"US",
    "sg:address":"9107 S Tryon St",
    "sg:city":"Charlotte",
    "sg:classifiers":[
        {
            "category":"Restaurant",
            "type":"Food & Drink"
        }
    ],
    "sg:menulink":"http://www.allmenus.com/nc/charlotte/47768-taqueria-allende/menu/",
    "sg:phone":"+1 704 588 8585",
    "sg:postcode":"28273",
    "sg:province":"NC",
    "sg:tags":[
        "mexican"
    ],
    "wof:name":"Taqueria Allende",
    "wof:placetype":"venue"
},
  "geometry": {"coordinates":[-80.939087,35.134023],"type":"Point"}
}