{
  "type": "Feature",
  "properties": {
    "iso:country":"US",
    "sg:address":"90 Church St",
    "sg:city":"Asheville",
    "sg:classifiers":[
        {
            "category":"Real Estate",
            "subcategory":"Architect",
            "type":"Services"
        }
    ],
    "sg:phone":"+1 828 252 0355",
    "sg:postcode":"28801",
    "sg:province":"NC",
    "sg:tags":[
        "architectural"
    ],
    "wof:name":"ADS",
    "wof:placetype":"venue"
},
  "geometry": {"coordinates":[-82.55306,35.592888],"type":"Point"}
}