{
  "type": "Feature",
  "properties": {
    "iso:country":"US",
    "sg:address":"18802 Halyard Pointe Ln",
    "sg:city":"Cornelius",
    "sg:classifiers":[
        {
            "category":"Banks & Credit Unions",
            "subcategory":"Financial Services",
            "type":"Services"
        }
    ],
    "sg:phone":"+1 704 896 8708",
    "sg:postcode":"28031",
    "sg:province":"NC",
    "sg:tags":[
        "investor"
    ],
    "wof:name":"Jcrs Properties LLC",
    "wof:placetype":"venue"
},
  "geometry": {"coordinates":[-80.90777,35.469858],"type":"Point"}
}