{
  "type": "Feature",
  "properties": {
    "iso:country":"US",
    "sg:address":"407 S 13th St",
    "sg:city":"Bessemer City",
    "sg:classifiers":[
        {
            "category":"Shopping",
            "subcategory":"Bicycles & Sporting Goods",
            "type":"Retail Goods"
        }
    ],
    "sg:phone":"+1 704 868 3110",
    "sg:postcode":"28016",
    "sg:province":"NC",
    "wof:name":"Off The Wall Entertainment",
    "wof:placetype":"venue"
},
  "geometry": {"coordinates":[-81.28677,35.282265],"type":"Point"}
}