{
  "type": "Feature",
  "properties": {
    "addr:full":"6252 Flower Hill Rd Kenly NC 27542",
    "addr:housenumber":"6252",
    "addr:postcode":"27542",
    "addr:street":"Flower Hill Rd",
    "iso:country":"US",
    "sg:address":"6252 Flower Hill Rd",
    "sg:city":"Kenly",
    "sg:classifiers":[
        {
            "category":"Building & Trades",
            "subcategory":"Construction",
            "type":"Services"
        }
    ],
    "sg:phone":"+1 919 284 6617",
    "sg:postcode":"27542",
    "sg:province":"NC",
    "sg:tags":[
        "contractor"
    ],
    "wof:name":"Mozingos Insulation Inc",
    "wof:placetype":"venue"
},
  "geometry": {"coordinates":[-78.17398900000001,35.688902],"type":"Point"}
}