{
  "type": "Feature",
  "properties": {
    "iso:country":"US",
    "sg:address":"500 Pine Valley Dr",
    "sg:city":"Wilmington",
    "sg:classifiers":[
        {
            "category":"Recreation",
            "type":"Entertainment"
        }
    ],
    "sg:phone":"+1 910 791 3971",
    "sg:postcode":"28412",
    "sg:province":"NC",
    "sg:tags":[
        "club",
        "country",
        "membership"
    ],
    "wof:name":"Pine Valley Country Club Inc",
    "wof:placetype":"venue"
},
  "geometry": {"coordinates":[-77.89922199999999,34.189047],"type":"Point"}
}