{
  "type": "Feature",
  "properties": {
    "addr:full":"110 Broad St Oxford NC 27565",
    "addr:housenumber":"110",
    "addr:postcode":"27565",
    "addr:street":"Broad St",
    "iso:country":"US",
    "sg:address":"110 Broad St",
    "sg:city":"Oxford",
    "sg:classifiers":[
        {
            "category":"Professional",
            "subcategory":"Management & Consulting",
            "type":"Services"
        }
    ],
    "sg:phone":"+1 919 690 8755",
    "sg:postcode":"27565",
    "sg:province":"NC",
    "sg:tags":[
        "marketing",
        "consultant"
    ],
    "wof:name":"Carolina Marketing Group",
    "wof:placetype":"venue"
},
  "geometry": {"coordinates":[-78.59139399999999,36.311116],"type":"Point"}
}