{
  "type": "Feature",
  "properties": {
    "addr:full":"10 Gaines Ave Asheville NC 28803",
    "addr:housenumber":"10",
    "addr:postcode":"28803",
    "addr:street":"Gaines Ave",
    "iso:country":"US",
    "sg:address":"10 Gaines Ave",
    "sg:city":"Asheville",
    "sg:classifiers":[
        {
            "category":"Health Services",
            "subcategory":"Nursing And Care Facility",
            "type":"Services"
        }
    ],
    "sg:phone":"+1 828 274 7660",
    "sg:postcode":"28803",
    "sg:province":"NC",
    "sg:tags":[
        "organization",
        "religious"
    ],
    "wof:name":"Robert E Hrris Evnglstic Assoc",
    "wof:placetype":"venue"
},
  "geometry": {"coordinates":[-82.532661,35.547408],"type":"Point"}
}