{
  "type": "Feature",
  "properties": {
    "addr:full":"2431 Spring Forest Rd Raleigh NC 27615",
    "addr:housenumber":"2431",
    "addr:postcode":"27615",
    "addr:street":"Spring Forest Rd",
    "iso:country":"US",
    "sg:address":"2431 Spring Forest Rd",
    "sg:city":"Raleigh",
    "sg:classifiers":[
        {
            "category":"Recreation",
            "type":"Entertainment"
        }
    ],
    "sg:phone":"+1 919 872 6699",
    "sg:postcode":"27615",
    "sg:province":"NC",
    "sg:tags":[
        "parlor",
        "billiard"
    ],
    "wof:name":"New York Billiards & Cafe",
    "wof:placetype":"venue"
},
  "geometry": {"coordinates":[-78.599638,35.860986],"type":"Point"}
}