{
  "type": "Feature",
  "properties": {
    "iso:country":"US",
    "sg:address":"6104 Dodsworth Dr",
    "sg:city":"Raleigh",
    "sg:classifiers":[
        {
            "category":"Building & Trades",
            "subcategory":"Construction",
            "type":"Services"
        }
    ],
    "sg:phone":"+1 919 427 7758",
    "sg:postcode":"27612",
    "sg:province":"NC",
    "sg:tags":[
        "contractor"
    ],
    "wof:name":"Browns Construction And Home",
    "wof:placetype":"venue"
},
  "geometry": {"coordinates":[-78.691411,35.864403],"type":"Point"}
}