{
  "type": "Feature",
  "properties": {
    "iso:country":"US",
    "sg:address":"129 W End Ln",
    "sg:city":"West End",
    "sg:classifiers":[
        {
            "category":"Retail",
            "subcategory":"Repair Shop",
            "type":"Services"
        }
    ],
    "sg:phone":"+1   ",
    "sg:postcode":"27376",
    "sg:province":"NC",
    "wof:name":"Melonies Custom Framing",
    "wof:placetype":"venue"
},
  "geometry": {"coordinates":[-79.56505300000001,35.238958],"type":"Point"}
}