{
  "type": "Feature",
  "properties": {
    "iso:country":"US",
    "sg:address":"4060 Henry River Rd",
    "sg:city":"Hickory",
    "sg:classifiers":[
        {
            "category":"Shopping",
            "subcategory":"Florist",
            "type":"Retail Goods"
        }
    ],
    "sg:phone":"+1 828 397 6776",
    "sg:postcode":"28602",
    "sg:province":"NC",
    "wof:name":"Flower Cottage",
    "wof:placetype":"venue"
},
  "geometry": {"coordinates":[-81.42684199999999,35.70279],"type":"Point"}
}