{
  "type": "Feature",
  "properties": {
    "addr:full":"1016 N Brightleaf Blvd Smithfield NC 27577",
    "addr:housenumber":"1016",
    "addr:postcode":"27577",
    "addr:street":"N Brightleaf Blvd",
    "iso:country":"US",
    "sg:address":"1016 N Brightleaf Blvd",
    "sg:city":"Smithfield",
    "sg:classifiers":[
        {
            "category":"Autos & Motor Vehicles",
            "subcategory":"Fuel & Gas Station",
            "type":"Retail Goods"
        }
    ],
    "sg:phone":"+1 919 934 6530",
    "sg:postcode":"27577",
    "sg:province":"NC",
    "sg:tags":[
        "oil"
    ],
    "wof:name":"Service Distributing Co",
    "wof:placetype":"venue"
},
  "geometry": {"coordinates":[-78.321133,35.516978],"type":"Point"}
}