{
  "type": "Feature",
  "properties": {
    "addr:full":"193 Hope Dr Lexington NC 27295",
    "addr:housenumber":"193",
    "addr:postcode":"27295",
    "addr:street":"Hope Dr",
    "iso:country":"US",
    "sg:address":"193 Hope Dr",
    "sg:city":"Lexington",
    "sg:classifiers":[
        {
            "category":"Freight",
            "type":"Transportation"
        }
    ],
    "sg:phone":"+1 336 764 9537",
    "sg:postcode":"27295",
    "sg:province":"NC",
    "sg:tags":[
        "operator",
        "local",
        "trucking"
    ],
    "wof:name":"Veon Trucking",
    "wof:placetype":"venue"
},
  "geometry": {"coordinates":[-80.336867,35.926304],"type":"Point"}
}