{
  "type": "Feature",
  "properties": {
    "iso:country":"US",
    "sg:address":"125 Edinburgh Dr",
    "sg:city":"Cary",
    "sg:classifiers":[
        {
            "category":"Professional",
            "subcategory":"Management & Consulting",
            "type":"Services"
        }
    ],
    "sg:phone":"+1   ",
    "sg:postcode":"27511",
    "sg:province":"NC",
    "wof:name":"Institute of Global Competitiv",
    "wof:placetype":"venue"
},
  "geometry": {"coordinates":[-78.798365,35.741603],"type":"Point"}
}