{
  "type": "Feature",
  "properties": {
    "iso:country":"US",
    "sg:address":"213 N Harrington St",
    "sg:city":"Raleigh",
    "sg:classifiers":[
        {
            "category":"Professional",
            "type":"Services"
        }
    ],
    "sg:phone":"+1 919 754 0825",
    "sg:postcode":"27603",
    "sg:province":"NC",
    "sg:tags":[
        "establishment"
    ],
    "wof:name":"Palmetto Net Inc",
    "wof:placetype":"venue"
},
  "geometry": {"coordinates":[-78.644904,35.783908],"type":"Point"}
}