{
  "type": "Feature",
  "properties": {
    "addr:full":"320 S Bickett Blvd Louisburg NC 27549",
    "addr:housenumber":"320",
    "addr:postcode":"27549",
    "addr:street":"S Bickett Blvd",
    "iso:country":"US",
    "sg:address":"320 S Bickett Blvd",
    "sg:city":"Louisburg",
    "sg:classifiers":[
        {
            "category":"Personal",
            "subcategory":"Beauty Salon",
            "type":"Services"
        }
    ],
    "sg:phone":"+1   ",
    "sg:postcode":"27549",
    "sg:province":"NC",
    "sg:tags":[
        "shop"
    ],
    "wof:name":"Cuts & Curls",
    "wof:placetype":"venue"
},
  "geometry": {"coordinates":[-78.300065,36.090991],"type":"Point"}
}