{
  "type": "Feature",
  "properties": {
    "iso:country":"US",
    "sg:address":"2206 Union Rd",
    "sg:city":"Gastonia",
    "sg:classifiers":[
        {
            "category":"Shopping",
            "subcategory":"Pharmacy",
            "type":"Retail Goods"
        }
    ],
    "sg:phone":"+1 704 864 8749",
    "sg:postcode":"28054",
    "sg:province":"NC",
    "wof:name":"CVS Pharmacy",
    "wof:placetype":"venue"
},
  "geometry": {"coordinates":[-81.16928299999999,35.2312],"type":"Point"}
}