{
  "type": "Feature",
  "properties": {
    "addr:full":"1100 Haynes St Raleigh NC 27604",
    "addr:housenumber":"1100",
    "addr:postcode":"27604",
    "addr:street":"Haynes St",
    "iso:country":"US",
    "sg:address":"1100 Haynes St",
    "sg:city":"Raleigh",
    "sg:classifiers":[
        {
            "category":"Social Services",
            "type":"Services"
        }
    ],
    "sg:phone":"+1 919 833 3883",
    "sg:postcode":"27604",
    "sg:province":"NC",
    "sg:tags":[
        "organization",
        "welfare"
    ],
    "wof:name":"YWCA",
    "wof:placetype":"venue"
},
  "geometry": {"coordinates":[-78.637182,35.796331],"type":"Point"}
}