{
  "type": "Feature",
  "properties": {
    "iso:country":"US",
    "sg:address":"811 Leonard Rd",
    "sg:city":"Lexington",
    "sg:classifiers":[
        {
            "category":"Manufacturing",
            "subcategory":"Glass & Minerals",
            "type":"Manufacturing & Wholesale Goods"
        }
    ],
    "sg:phone":"+1 336 249 2153",
    "sg:postcode":"27295",
    "sg:province":"NC",
    "sg:tags":[
        "concrete",
        "product",
        "mfg"
    ],
    "wof:name":"Parkway Dcorative Stone Masnry",
    "wof:placetype":"venue"
},
  "geometry": {"coordinates":[-80.251396,35.866765],"type":"Point"}
}