{
  "type": "Feature",
  "properties": {
    "addr:full":"5424 Dennis Ct Charlotte NC 28213",
    "addr:housenumber":"5424",
    "addr:postcode":"28213",
    "addr:street":"Dennis Ct",
    "iso:country":"US",
    "sg:address":"5424 Dennis Ct",
    "sg:city":"Charlotte",
    "sg:classifiers":[
        {
            "category":"Social Services",
            "subcategory":"Child Care",
            "type":"Services"
        }
    ],
    "sg:phone":"+1   ",
    "sg:postcode":"28213",
    "sg:province":"NC",
    "sg:tags":[
        "day"
    ],
    "wof:name":"Vision Love",
    "wof:placetype":"venue"
},
  "geometry": {"coordinates":[-80.7816,35.268397],"type":"Point"}
}