{
  "type": "Feature",
  "properties": {
    "addr:full":"2321 Wilkinson Blvd Charlotte NC 28208",
    "addr:housenumber":"2321",
    "addr:postcode":"28208",
    "addr:street":"Wilkinson Blvd",
    "iso:country":"US",
    "sg:address":"2321 Wilkinson Blvd",
    "sg:city":"Charlotte",
    "sg:classifiers":[
        {
            "category":"Retail",
            "subcategory":"Laundry & Dry Cleaning",
            "type":"Services"
        }
    ],
    "sg:phone":"+1 704 375 1705",
    "sg:postcode":"28208",
    "sg:province":"NC",
    "sg:tags":[
        "linen",
        "supply"
    ],
    "wof:name":"Aramark",
    "wof:placetype":"venue"
},
  "geometry": {"coordinates":[-80.879358,35.223782],"type":"Point"}
}