{
  "type": "Feature",
  "properties": {
    "addr:full":"1714 Trolleystone Ct Cary NC 27519",
    "addr:housenumber":"1714",
    "addr:postcode":"27519",
    "addr:street":"Trolleystone Ct",
    "iso:country":"US",
    "sg:address":"1714 Trolleystone Ct",
    "sg:city":"Cary",
    "sg:classifiers":[
        {
            "category":"Autos & Motor Vehicles",
            "subcategory":"Fuel & Gas Station",
            "type":"Retail Goods"
        }
    ],
    "sg:phone":"+1 919 839 0507",
    "sg:postcode":"27519",
    "sg:province":"NC",
    "sg:tags":[
        "oil"
    ],
    "wof:name":"Wolf's Den",
    "wof:placetype":"venue"
},
  "geometry": {"coordinates":[-78.85283,35.788957],"type":"Point"}
}