{
  "type": "Feature",
  "properties": {
    "iso:country":"US",
    "sg:address":"10024 Capital Blvd",
    "sg:city":"Wake Forest",
    "sg:classifiers":[
        {
            "category":"Autos & Motor Vehicles",
            "subcategory":"Automobile Sales",
            "type":"Retail Goods"
        }
    ],
    "sg:phone":"+1 919 556 3980",
    "sg:postcode":"27587",
    "sg:province":"NC",
    "sg:tags":[
        "car",
        "dealer"
    ],
    "wof:name":"R E Schodt & Sons",
    "wof:placetype":"venue"
},
  "geometry": {"coordinates":[-78.548159,35.916422],"type":"Point"}
}