{
  "type": "Feature",
  "properties": {
    "addr:full":"1512 N Fayetteville St Asheboro NC 27203",
    "addr:housenumber":"1512",
    "addr:postcode":"27203",
    "addr:street":"N;St",
    "iso:country":"US",
    "sg:address":"1512 N Fayetteville St",
    "sg:city":"Asheboro",
    "sg:classifiers":[
        {
            "category":"Government",
            "subcategory":"Office",
            "type":"Public Place"
        }
    ],
    "sg:phone":"+1 336 683 8000",
    "sg:postcode":"27203",
    "sg:province":"NC",
    "sg:tags":[
        "county",
        "resource"
    ],
    "wof:name":"Randolph County Social Svc",
    "wof:placetype":"venue"
},
  "geometry": {"coordinates":[-79.808295,35.736161],"type":"Point"}
}