{
  "type": "Feature",
  "properties": {
    "iso:country":"US",
    "sg:address":"7815 Lucy Ln",
    "sg:city":"Sherrills Ford",
    "sg:classifiers":[
        {
            "category":"Recreation",
            "type":"Entertainment"
        }
    ],
    "sg:phone":"+1   ",
    "sg:postcode":"28673",
    "sg:province":"NC",
    "wof:name":"Norman Lake Ventures Inc",
    "wof:placetype":"venue"
},
  "geometry": {"coordinates":[-80.98859299999999,35.550332],"type":"Point"}
}