{
  "type": "Feature",
  "properties": {
    "iso:country":"US",
    "sg:address":"644 Sparger Rd",
    "sg:city":"Mount Airy",
    "sg:classifiers":[
        {
            "category":"Shopping",
            "subcategory":"Used Merchandise",
            "type":"Retail Goods"
        }
    ],
    "sg:phone":"+1 336 786 6906",
    "sg:postcode":"27030",
    "sg:province":"NC",
    "wof:name":"Sparger Guy & Mary Antiques",
    "wof:placetype":"venue"
},
  "geometry": {"coordinates":[-80.677263,36.512182],"type":"Point"}
}