{
  "type": "Feature",
  "properties": {
    "iso:country":"US",
    "sg:address":"140 S Main St",
    "sg:city":"Mocksville",
    "sg:classifiers":[
        {
            "category":"Government",
            "subcategory":"Court House",
            "type":"Public Place"
        }
    ],
    "sg:phone":"+1 336 634 3507",
    "sg:postcode":"27028",
    "sg:province":"NC",
    "sg:tags":[
        "county"
    ],
    "wof:name":"Davie County Superior Court",
    "wof:placetype":"venue"
},
  "geometry": {"coordinates":[-80.56180000000001,35.893461],"type":"Point"}
}