{
  "type": "Feature",
  "properties": {
    "addr:full":"10205 Kirkmont Dr Charlotte NC 28269",
    "addr:housenumber":"10205",
    "addr:postcode":"28269",
    "addr:street":"Kirkmont Dr",
    "iso:country":"US",
    "sg:address":"10205 Kirkmont Dr",
    "sg:city":"Charlotte",
    "sg:classifiers":[
        {
            "category":"Communications",
            "subcategory":"Newspaper",
            "type":"Services"
        }
    ],
    "sg:phone":"+1 704 948 5616",
    "sg:postcode":"28269",
    "sg:province":"NC",
    "wof:name":"Kidsville News Cabarrus Inc",
    "wof:placetype":"venue"
},
  "geometry": {"coordinates":[-80.74744699999999,35.391795],"type":"Point"}
}