{
  "type": "Feature",
  "properties": {
    "iso:country":"US",
    "sg:address":"3188 Sugarloaf Mountain Rd",
    "sg:city":"Hendersonville",
    "sg:classifiers":[
        {
            "category":"Retail",
            "subcategory":"Repair Shop",
            "type":"Services"
        }
    ],
    "sg:phone":"+1   ",
    "sg:postcode":"28792",
    "sg:province":"NC",
    "wof:name":"Budget Locksmith Inc",
    "wof:placetype":"venue"
},
  "geometry": {"coordinates":[-82.267922,35.396903],"type":"Point"}
}