{
  "type": "Feature",
  "properties": {
    "addr:full":"5620 Glen Oaks Dr Durham NC 27712",
    "addr:housenumber":"5620",
    "addr:postcode":"27712",
    "addr:street":"Glen Oaks Dr",
    "iso:country":"US",
    "sg:address":"5620 Glen Oaks Dr",
    "sg:city":"Durham",
    "sg:classifiers":[
        {
            "category":"Sports & Exercise",
            "subcategory":"Bowling",
            "type":"Entertainment"
        }
    ],
    "sg:phone":"+1 919 477 2665",
    "sg:postcode":"27712",
    "sg:province":"NC",
    "sg:tags":[
        "center"
    ],
    "wof:name":"Betty Bowling",
    "wof:placetype":"venue"
},
  "geometry": {"coordinates":[-78.884997,36.097296],"type":"Point"}
}