{
  "type": "Feature",
  "properties": {
    "addr:full":"1117 Capital Blvd Raleigh NC 27604",
    "addr:housenumber":"1117",
    "addr:postcode":"27604",
    "addr:street":"Capital Blvd",
    "iso:country":"US",
    "sg:address":"1117 Capital Blvd",
    "sg:city":"Raleigh",
    "sg:classifiers":[
        {
            "category":"Wholesale",
            "subcategory":"Hardware",
            "type":"Manufacturing & Wholesale Goods"
        }
    ],
    "sg:phone":"+1 919 832 2071",
    "sg:postcode":"27604",
    "sg:province":"NC",
    "sg:tags":[
        "plumbing",
        "supply"
    ],
    "wof:name":"Noland Company",
    "wof:placetype":"venue"
},
  "geometry": {"coordinates":[-78.639672,35.798102],"type":"Point"}
}