{
  "type": "Feature",
  "properties": {
    "iso:country":"US",
    "sg:address":"1025 Blue Ridge Rd",
    "sg:city":"Raleigh",
    "sg:classifiers":[
        {
            "category":"Professional",
            "subcategory":"Management & Consulting",
            "type":"Services"
        }
    ],
    "sg:phone":"+1   ",
    "sg:postcode":"27607",
    "sg:province":"NC",
    "sg:tags":[
        "market",
        "research"
    ],
    "wof:name":"TMI Research",
    "wof:placetype":"venue"
},
  "geometry": {"coordinates":[-78.704983,35.792216],"type":"Point"}
}