{
  "type": "Feature",
  "properties": {
    "iso:country":"US",
    "sg:address":"1690 N Garnett St",
    "sg:city":"Henderson",
    "sg:classifiers":[
        {
            "category":"Banks & Credit Unions",
            "subcategory":"Bank",
            "type":"Services"
        }
    ],
    "sg:phone":"+1 252 431 0015",
    "sg:postcode":"27536",
    "sg:province":"NC",
    "sg:tags":[
        "cashing",
        "check"
    ],
    "wof:name":"Checks 2 Cash",
    "wof:placetype":"venue"
},
  "geometry": {"coordinates":[-78.394842,36.341],"type":"Point"}
}