{
  "type": "Feature",
  "properties": {
    "addr:full":"5050 Fayetteville Rd Lumberton NC 28358",
    "addr:housenumber":"5050",
    "addr:postcode":"28358",
    "addr:street":"Fayetteville Rd",
    "iso:country":"US",
    "sg:address":"5050 Fayetteville Rd",
    "sg:city":"Lumberton",
    "sg:classifiers":[
        {
            "category":"Bars & Pubs",
            "type":"Food & Drink"
        }
    ],
    "sg:menulink":"http://www.allmenus.com/nc/lumberton/245246-smithfields-chicken-n-bar-b-q/menu/",
    "sg:phone":"+1 910 618 9542",
    "sg:postcode":"28358",
    "sg:province":"NC",
    "sg:tags":[
        "barbecue",
        "american"
    ],
    "wof:name":"Smithfield's Chicken 'n Bar-b-q",
    "wof:placetype":"venue"
},
  "geometry": {"coordinates":[-79.00254,34.666526],"type":"Point"}
}