{
  "type": "Feature",
  "properties": {
    "addr:full":"9009 Sandpiper Dr Charlotte NC 28277",
    "addr:housenumber":"9009",
    "addr:postcode":"28277",
    "addr:street":"Sandpiper Dr",
    "iso:country":"US",
    "sg:address":"9009 Sandpiper Dr",
    "sg:city":"Charlotte",
    "sg:classifiers":[
        {
            "category":"Building & Trades",
            "subcategory":"Construction",
            "type":"Services"
        }
    ],
    "sg:phone":"+1 704 341 0829",
    "sg:postcode":"28277",
    "sg:province":"NC",
    "sg:tags":[
        "house"
    ],
    "wof:name":"Belmontes Handyman Services",
    "wof:placetype":"venue"
},
  "geometry": {"coordinates":[-80.82003899999999,35.08165],"type":"Point"}
}