{
  "type": "Feature",
  "properties": {
    "iso:country":"US",
    "sg:address":"1105 Hope Mills Rd",
    "sg:city":"Fayetteville",
    "sg:classifiers":[
        {
            "category":"Home & Garden",
            "subcategory":"Household Appliances",
            "type":"Retail Goods"
        }
    ],
    "sg:phone":"+1 910 423 1333",
    "sg:postcode":"28304",
    "sg:province":"NC",
    "wof:name":"Alfano Sewing Machines",
    "wof:placetype":"venue"
},
  "geometry": {"coordinates":[-78.960881,35.027739],"type":"Point"}
}