{
  "type": "Feature",
  "properties": {
    "iso:country":"US",
    "sg:address":"100 Sugarloaf Rd",
    "sg:city":"Hendersonville",
    "sg:classifiers":[
        {
            "category":"Restaurant",
            "type":"Food & Drink"
        }
    ],
    "sg:menulink":"http://www.allmenus.com/nc/hendersonville/111372-waffle-house/menu/",
    "sg:phone":"+1 828 697 1994",
    "sg:postcode":"28792",
    "sg:province":"NC",
    "sg:tags":[
        "american"
    ],
    "wof:name":"Waffle House",
    "wof:placetype":"venue"
},
  "geometry": {"coordinates":[-82.435401,35.344031],"type":"Point"}
}