{
  "type": "Feature",
  "properties": {
    "addr:full":"502 E Colonial Ave Elizabeth City NC 27909",
    "addr:housenumber":"502",
    "addr:postcode":"27909",
    "addr:street":"E Colonial Ave",
    "iso:country":"US",
    "sg:address":"502 E Colonial Ave",
    "sg:city":"Elizabeth City",
    "sg:classifiers":[
        {
            "category":"Restaurant",
            "type":"Food & Drink"
        }
    ],
    "sg:phone":"+1 252 333 1888",
    "sg:postcode":"27909",
    "sg:province":"NC",
    "sg:tags":[
        "eating"
    ],
    "wof:name":"Subway",
    "wof:placetype":"venue"
},
  "geometry": {"coordinates":[-76.220309,36.300601],"type":"Point"}
}