{
  "type": "Feature",
  "properties": {
    "addr:full":"1551 National Hwy Thomasville NC 27360",
    "addr:housenumber":"1551",
    "addr:postcode":"27360",
    "addr:street":"National Hwy",
    "iso:country":"US",
    "sg:address":"1551 National Hwy",
    "sg:city":"Thomasville",
    "sg:classifiers":[
        {
            "category":"Government",
            "subcategory":"Office",
            "type":"Public Place"
        }
    ],
    "sg:phone":"+1 336 885 9741",
    "sg:postcode":"27360",
    "sg:province":"NC",
    "sg:tags":[
        "county"
    ],
    "wof:name":"County Line Truck Repair",
    "wof:placetype":"venue"
},
  "geometry": {"coordinates":[-80.06214900000001,35.907798],"type":"Point"}
}