{
  "type": "Feature",
  "properties": {
    "addr:full":"406 S Chestnut St Mount Olive NC 28365",
    "addr:housenumber":"406",
    "addr:postcode":"28365",
    "addr:street":"S Chestnut St",
    "iso:country":"US",
    "sg:address":"406 S Chestnut St",
    "sg:city":"Mount Olive",
    "sg:classifiers":[
        {
            "category":"Freight",
            "type":"Transportation"
        }
    ],
    "sg:phone":"+1 919 658 2681",
    "sg:postcode":"28365",
    "sg:province":"NC",
    "sg:tags":[
        "operator",
        "trucking"
    ],
    "wof:name":"Mason Glynn Trucking",
    "wof:placetype":"venue"
},
  "geometry": {"coordinates":[-78.071369,35.192804],"type":"Point"}
}