{
  "type": "Feature",
  "properties": {
    "iso:country":"US",
    "sg:address":"1730 Clayhole Rd",
    "sg:city":"Coats",
    "sg:classifiers":[
        {
            "category":"Organizations",
            "subcategory":"Community Association",
            "type":"Services"
        }
    ],
    "sg:phone":"+1   ",
    "sg:postcode":"27521",
    "sg:province":"NC",
    "wof:name":"Order of Eastern Star of",
    "wof:placetype":"venue"
},
  "geometry": {"coordinates":[-78.687749,35.389198],"type":"Point"}
}