{
  "type": "Feature",
  "properties": {
    "iso:country":"US",
    "sg:address":"804 State St",
    "sg:city":"Marion",
    "sg:classifiers":[
        {
            "category":"Organizations",
            "subcategory":"Religious Organization",
            "type":"Services"
        }
    ],
    "sg:phone":"+1 828 652 1410",
    "sg:postcode":"28752",
    "sg:province":"NC",
    "sg:tags":[
        "church"
    ],
    "wof:name":"Christian Clothing Ctr",
    "wof:placetype":"venue"
},
  "geometry": {"coordinates":[-81.994293,35.689357],"type":"Point"}
}