{
  "type": "Feature",
  "properties": {
    "iso:country":"US",
    "sg:address":"6621 Barkley Farm Rd",
    "sg:city":"Huntersville",
    "sg:classifiers":[
        {
            "category":"Building & Trades",
            "subcategory":"Landscaping Services",
            "type":"Services"
        }
    ],
    "sg:phone":"+1 704 948 0172",
    "sg:postcode":"28078",
    "sg:province":"NC",
    "sg:tags":[
        "landscape"
    ],
    "sg:website":"www.creativeponds.com",
    "wof:name":"Creative Ponds Landscaping",
    "wof:placetype":"venue"
},
  "geometry": {"coordinates":[-80.920276,35.384509],"type":"Point"}
}