{
  "type": "Feature",
  "properties": {
    "iso:country":"US",
    "sg:address":"1305 Coach Rd",
    "sg:city":"Reidsville",
    "sg:classifiers":[
        {
            "category":"Health Services",
            "subcategory":"Clinic",
            "type":"Services"
        },
        {
            "category":"Health Services",
            "subcategory":"Health Practitioner",
            "type":"Services"
        }
    ],
    "sg:phone":"+1 336 349 5553",
    "sg:postcode":"27320",
    "sg:province":"NC",
    "sg:tags":[
        "psychologist",
        "specialty",
        "outpatient"
    ],
    "wof:name":"Julia M Brannon PHD",
    "wof:placetype":"venue"
},
  "geometry": {"coordinates":[-79.67908199999999,36.344985],"type":"Point"}
}