{
  "type": "Feature",
  "properties": {
    "iso:country":"US",
    "sg:address":"4475 Paysour Pond Rd",
    "sg:city":"Iron Station",
    "sg:classifiers":[
        {
            "category":"Retail",
            "subcategory":"Auto Repair",
            "type":"Services"
        }
    ],
    "sg:phone":"+1 704 363 8725",
    "sg:postcode":"28080",
    "sg:province":"NC",
    "sg:tags":[
        "truck",
        "sales"
    ],
    "wof:name":"R A Grigg Services",
    "wof:placetype":"venue"
},
  "geometry": {"coordinates":[-81.101325,35.425051],"type":"Point"}
}