{
  "type": "Feature",
  "properties": {
    "iso:country":"US",
    "sg:address":"1715 Taylors Creek Dr",
    "sg:city":"Asheboro",
    "sg:classifiers":[
        {
            "category":"Building & Trades",
            "subcategory":"Construction",
            "type":"Services"
        }
    ],
    "sg:phone":"+1 336 626 4715",
    "sg:postcode":"27205",
    "sg:province":"NC",
    "sg:tags":[
        "house",
        "residential"
    ],
    "wof:name":"R & D Construction",
    "wof:placetype":"venue"
},
  "geometry": {"coordinates":[-79.911575,35.667029],"type":"Point"}
}