{
  "type": "Feature",
  "properties": {
    "addr:full":"474 Weaverville Rd Asheville NC 28804",
    "addr:housenumber":"474",
    "addr:postcode":"28804",
    "addr:street":"Weaverville Rd",
    "iso:country":"US",
    "sg:address":"474 Weaverville Rd",
    "sg:city":"Asheville",
    "sg:classifiers":[
        {
            "category":"Retail",
            "subcategory":"Auto Rental",
            "type":"Services"
        }
    ],
    "sg:phone":"+1 828 645 7108",
    "sg:postcode":"28804",
    "sg:province":"NC",
    "sg:tags":[
        "renting",
        "truck",
        "leasing"
    ],
    "wof:name":"U-Haul Co",
    "wof:placetype":"venue"
},
  "geometry": {"coordinates":[-82.582329,35.672059],"type":"Point"}
}