{
  "type": "Feature",
  "properties": {
    "addr:full":"2345 River Rd Henrico NC 27842",
    "addr:housenumber":"2345",
    "addr:postcode":"27842",
    "addr:street":"River Rd",
    "iso:country":"US",
    "sg:address":"2345 River Rd",
    "sg:city":"Henrico",
    "sg:classifiers":[
        {
            "category":"Real Estate",
            "subcategory":"Real Estate Agent",
            "type":"Services"
        }
    ],
    "sg:phone":"+1 252 537 4111",
    "sg:postcode":"27842",
    "sg:province":"NC",
    "sg:website":"www.lakegastondreamhomes.com",
    "wof:name":"Wilkie Real Estate Inc",
    "wof:placetype":"venue"
},
  "geometry": {"coordinates":[-77.86321599999999,36.519307],"type":"Point"}
}