{
  "type": "Feature",
  "properties": {
    "addr:full":"3203 Eastway Dr Charlotte NC 28205",
    "addr:housenumber":"3203",
    "addr:postcode":"28205",
    "addr:street":"Eastway Dr",
    "iso:country":"US",
    "sg:address":"3203 Eastway Dr",
    "sg:city":"Charlotte",
    "sg:classifiers":[
        {
            "category":"Retail",
            "subcategory":"Laundry & Dry Cleaning",
            "type":"Services"
        }
    ],
    "sg:phone":"+1 704 531 8084",
    "sg:postcode":"28205",
    "sg:province":"NC",
    "sg:tags":[
        "cleaners"
    ],
    "wof:name":"Benlee's Dry Cleanings",
    "wof:placetype":"venue"
},
  "geometry": {"coordinates":[-80.78161900000001,35.212137],"type":"Point"}
}