{
  "type": "Feature",
  "properties": {
    "addr:full":"1370 Alvin Hough Rd Midland NC 28107",
    "addr:housenumber":"1370",
    "addr:postcode":"28107",
    "addr:street":"Alvin Hough Rd",
    "iso:country":"US",
    "sg:address":"1370 Alvin Hough Rd",
    "sg:city":"Midland",
    "sg:classifiers":[
        {
            "category":"Wholesale",
            "subcategory":"Durable Goods & Equipment",
            "type":"Manufacturing & Wholesale Goods"
        }
    ],
    "sg:phone":"+1 704 888 2433",
    "sg:postcode":"28107",
    "sg:province":"NC",
    "sg:tags":[
        "representative",
        "manufacturer"
    ],
    "wof:name":"Connection",
    "wof:placetype":"venue"
},
  "geometry": {"coordinates":[-80.59559400000001,35.232795],"type":"Point"}
}