{
  "type": "Feature",
  "properties": {
    "addr:full":"27 Kirkland Rd Franklin NC 28734",
    "addr:housenumber":"27",
    "addr:postcode":"nc 28734",
    "addr:street":"Kirkland Rd",
    "iso:country":"US",
    "sg:address":"27 Kirkland Rd",
    "sg:city":"Franklin",
    "sg:classifiers":[
        {
            "category":"Building & Trades",
            "subcategory":"Plumbing",
            "type":"Services"
        }
    ],
    "sg:phone":"+1 828 369 8612",
    "sg:postcode":"28734",
    "sg:province":"NC",
    "sg:tags":[
        "heating",
        "contractor"
    ],
    "wof:name":"Mc Coy Contractors Inc",
    "wof:placetype":"venue"
},
  "geometry": {"coordinates":[-83.354784,35.221631],"type":"Point"}
}