{
  "type": "Feature",
  "properties": {
    "addr:full":"661 W King St Boone NC 28607",
    "addr:housenumber":"661",
    "addr:postcode":"28607",
    "addr:street":"W King St",
    "iso:country":"US",
    "sg:address":"661 W King St",
    "sg:city":"Boone",
    "sg:classifiers":[
        {
            "category":"Home & Garden",
            "subcategory":"Hardware",
            "type":"Retail Goods"
        }
    ],
    "sg:phone":"+1 828 264 8801",
    "sg:postcode":"28607",
    "sg:province":"NC",
    "wof:name":"Farmers Hardware & Supply Co",
    "wof:placetype":"venue"
},
  "geometry": {"coordinates":[-81.684552,36.218967],"type":"Point"}
}