{
  "type": "Feature",
  "properties": {
    "addr:full":"2505 Country View Dr Lexington NC 27292",
    "addr:housenumber":"2505",
    "addr:postcode":"27292",
    "addr:street":"Country View Dr",
    "iso:country":"US",
    "sg:address":"2505 Country View Dr",
    "sg:city":"Lexington",
    "sg:classifiers":[
        {
            "category":"Freight",
            "type":"Transportation"
        }
    ],
    "sg:phone":"+1 336 746 6176",
    "sg:postcode":"27292",
    "sg:province":"NC",
    "sg:tags":[
        "trucking"
    ],
    "wof:name":"Bluegrass Express",
    "wof:placetype":"venue"
},
  "geometry": {"coordinates":[-80.188802,35.76234],"type":"Point"}
}