{
  "type": "Feature",
  "properties": {
    "iso:country":"US",
    "sg:address":"2010 Hampton St",
    "sg:city":"Kill Devil Hills",
    "sg:classifiers":[
        {
            "category":"Building & Trades",
            "subcategory":"Construction",
            "type":"Services"
        }
    ],
    "sg:phone":"+1 252 449 4910",
    "sg:postcode":"27948",
    "sg:province":"NC",
    "sg:tags":[
        "contractor"
    ],
    "wof:name":"Spa Doc",
    "wof:placetype":"venue"
},
  "geometry": {"coordinates":[-75.682957,36.036178],"type":"Point"}
}