{
  "type": "Feature",
  "properties": {
    "iso:country":"US",
    "sg:address":"100 Maypatch Rd",
    "sg:city":"Jacksonville",
    "sg:classifiers":[
        {
            "category":"Organizations",
            "subcategory":"Religious Organization",
            "type":"Services"
        }
    ],
    "sg:phone":"+1 910 353 7805",
    "sg:postcode":"28546",
    "sg:province":"NC",
    "sg:tags":[
        "church"
    ],
    "wof:name":"Living Word Full Gospel Mnstrs",
    "wof:placetype":"venue"
},
  "geometry": {"coordinates":[-77.38584299999999,34.746513],"type":"Point"}
}