{
  "type": "Feature",
  "properties": {
    "addr:full":"725 Fix St Burlington NC 27215",
    "addr:housenumber":"725",
    "addr:postcode":"27215",
    "addr:street":"Fix St",
    "iso:country":"US",
    "sg:address":"725 Fix St",
    "sg:city":"Burlington",
    "sg:classifiers":[
        {
            "category":"Manufacturing",
            "subcategory":"Metals",
            "type":"Manufacturing & Wholesale Goods"
        }
    ],
    "sg:phone":"+1 336 570 3694",
    "sg:postcode":"27215",
    "sg:province":"NC",
    "sg:tags":[
        "fabrication",
        "structural"
    ],
    "wof:name":"J T Portable Welding",
    "wof:placetype":"venue"
},
  "geometry": {"coordinates":[-79.436194,36.082556],"type":"Point"}
}