{
  "type": "Feature",
  "properties": {
    "iso:country":"US",
    "sg:address":"3520 Drawbridge Pkwy",
    "sg:city":"Greensboro",
    "sg:classifiers":[
        {
            "category":"Building & Trades",
            "subcategory":"Cleaning & Sanitation",
            "type":"Services"
        }
    ],
    "sg:phone":"+1 336 288 5611",
    "sg:postcode":"27410",
    "sg:province":"NC",
    "sg:tags":[
        "janitor"
    ],
    "wof:name":"Bibi's Commercial Cleaning",
    "wof:placetype":"venue"
},
  "geometry": {"coordinates":[-79.865768,36.138166],"type":"Point"}
}