{
  "type": "Feature",
  "properties": {
    "addr:full":"2461 Spaugh Industrial Dr Winston Salem NC 27103",
    "addr:housenumber":"2461",
    "addr:postcode":"27103",
    "addr:street":"Spaugh Industrial Dr",
    "iso:country":"US",
    "sg:address":"2461 Spaugh Industrial Dr",
    "sg:city":"Winston Salem",
    "sg:classifiers":[
        {
            "category":"Manufacturing",
            "subcategory":"Tools & Machinery",
            "type":"Manufacturing & Wholesale Goods"
        }
    ],
    "sg:phone":"+1 336 768 5586",
    "sg:postcode":"27103",
    "sg:province":"NC",
    "sg:tags":[
        "machine",
        "shop"
    ],
    "wof:name":"Jamie Cass Machine",
    "wof:placetype":"venue"
},
  "geometry": {"coordinates":[-80.31744,36.033572],"type":"Point"}
}