{
  "type": "Feature",
  "properties": {
    "iso:country":"US",
    "sg:address":"111 W Commerce St",
    "sg:city":"Whiteville",
    "sg:classifiers":[
        {
            "category":"Professional",
            "type":"Services"
        }
    ],
    "sg:phone":"+1   ",
    "sg:postcode":"28472",
    "sg:province":"NC",
    "wof:name":"Dunns Satellite Service",
    "wof:placetype":"venue"
},
  "geometry": {"coordinates":[-78.704481,34.321484],"type":"Point"}
}