{
  "type": "Feature",
  "properties": {
    "addr:full":"2938 Beaty Rd Gastonia NC 28056",
    "addr:housenumber":"2938",
    "addr:postcode":"28056",
    "addr:street":"Beaty Rd",
    "iso:country":"US",
    "sg:address":"2938 Beaty Rd",
    "sg:city":"Gastonia",
    "sg:classifiers":[
        {
            "category":"Organizations",
            "subcategory":"Religious Organization",
            "type":"Services"
        }
    ],
    "sg:phone":"+1   ",
    "sg:postcode":"28056",
    "sg:province":"NC",
    "wof:name":"Eliphelet Ministries",
    "wof:placetype":"venue"
},
  "geometry": {"coordinates":[-81.107349,35.209772],"type":"Point"}
}