{
  "type": "Feature",
  "properties": {
    "addr:full":"1191 State Line Church Rd Westfield NC 27053",
    "addr:housenumber":"1191",
    "addr:postcode":"27053",
    "addr:street":"State;Church Rd",
    "iso:country":"US",
    "sg:address":"1191 State Line Church Rd",
    "sg:city":"Westfield",
    "sg:classifiers":[
        {
            "category":"Farming",
            "subcategory":"Farm",
            "type":"Manufacturing & Wholesale Goods"
        }
    ],
    "sg:phone":"+1 336 351 2852",
    "sg:postcode":"27053",
    "sg:province":"NC",
    "sg:tags":[
        "crop",
        "general"
    ],
    "wof:name":"Kenneth A Rogers",
    "wof:placetype":"venue"
},
  "geometry": {"coordinates":[-80.36083499999999,36.540159],"type":"Point"}
}