{
  "type": "Feature",
  "properties": {
    "addr:full":"40 Brettwood Trce Clyde NC 28721",
    "addr:housenumber":"40",
    "addr:postcode":"28721",
    "addr:street":"Brettwood Trce",
    "iso:country":"US",
    "sg:address":"40 Brettwood Trce",
    "sg:city":"Clyde",
    "sg:classifiers":[
        {
            "category":"Health Services",
            "subcategory":"Doctor",
            "type":"Services"
        }
    ],
    "sg:phone":"+1 828 452 3110",
    "sg:postcode":"28721",
    "sg:province":"NC",
    "sg:tags":[
        "physician",
        "surgeon"
    ],
    "wof:name":"Alfred A Mina MD",
    "wof:placetype":"venue"
},
  "geometry": {"coordinates":[-82.948431,35.524593],"type":"Point"}
}