{
  "type": "Feature",
  "properties": {
    "addr:full":"4111 New Bern Ave Raleigh NC 27610",
    "addr:housenumber":"4111",
    "addr:postcode":"27610",
    "addr:street":"New Bern Ave",
    "iso:country":"US",
    "sg:address":"4111 New Bern Ave",
    "sg:city":"Raleigh",
    "sg:classifiers":[
        {
            "category":"Personal",
            "subcategory":"Beauty Salon",
            "type":"Services"
        }
    ],
    "sg:phone":"+1   ",
    "sg:postcode":"27610",
    "sg:province":"NC",
    "sg:tags":[
        "shop"
    ],
    "wof:name":"Linda Ray Vijgons",
    "wof:placetype":"venue"
},
  "geometry": {"coordinates":[-78.56618899999999,35.798718],"type":"Point"}
}