{
  "type": "Feature",
  "properties": {
    "addr:full":"1342 Benvenue Rd Rocky Mount NC 27804",
    "addr:housenumber":"1342",
    "addr:postcode":"27804",
    "addr:street":"Benvenue Rd",
    "iso:country":"US",
    "sg:address":"1342 Benvenue Rd",
    "sg:city":"Rocky Mount",
    "sg:classifiers":[
        {
            "category":"Retail",
            "subcategory":"Laundry & Dry Cleaning",
            "type":"Services"
        }
    ],
    "sg:phone":"+1 252 977 9895",
    "sg:postcode":"27804",
    "sg:province":"NC",
    "sg:tags":[
        "cleaners"
    ],
    "wof:name":"Quality Laundry & Cleaners",
    "wof:placetype":"venue"
},
  "geometry": {"coordinates":[-77.805998,35.977871],"type":"Point"}
}