{
  "type": "Feature",
  "properties": {
    "iso:country":"US",
    "sg:address":"4332 Castle Hayne Rd",
    "sg:city":"Castle Hayne",
    "sg:classifiers":[
        {
            "category":"Retail",
            "subcategory":"Auto Repair",
            "type":"Services"
        }
    ],
    "sg:phone":"+1 910 675 2721",
    "sg:postcode":"28429",
    "sg:province":"NC",
    "sg:tags":[
        "automotive",
        "wrecker"
    ],
    "wof:name":"Robinson Car Cleaning & Towing",
    "wof:placetype":"venue"
},
  "geometry": {"coordinates":[-77.916167,34.330315],"type":"Point"}
}