{
  "type": "Feature",
  "properties": {
    "iso:country":"US",
    "sg:address":"503 Brook Forest Dr",
    "sg:city":"Belmont",
    "sg:classifiers":[
        {
            "category":"Government",
            "subcategory":"Fire Station",
            "type":"Public Place"
        }
    ],
    "sg:phone":"+1 704 825 3166",
    "sg:postcode":"28012",
    "sg:province":"NC",
    "sg:tags":[
        "department"
    ],
    "wof:name":"South Point Volunteer Fire Department Inc",
    "wof:placetype":"venue"
},
  "geometry": {"coordinates":[-81.027215,35.203249],"type":"Point"}
}