{
  "type": "Feature",
  "properties": {
    "addr:full":"925 Ellis St Fayetteville NC 28305",
    "addr:housenumber":"925",
    "addr:postcode":"28305",
    "addr:street":"Ellis St",
    "iso:country":"US",
    "sg:address":"925 Ellis St",
    "sg:city":"Fayetteville",
    "sg:classifiers":[
        {
            "category":"Organizations",
            "subcategory":"Religious Organization",
            "type":"Services"
        }
    ],
    "sg:phone":"+1 910 829 7180",
    "sg:postcode":"28305",
    "sg:province":"NC",
    "sg:tags":[
        "church"
    ],
    "wof:name":"New Mount Hebrew UHCA",
    "wof:placetype":"venue"
},
  "geometry": {"coordinates":[-78.898472,35.05017],"type":"Point"}
}