{
  "type": "Feature",
  "properties": {
    "iso:country":"US",
    "sg:address":"35 Wall St",
    "sg:city":"Asheville",
    "sg:classifiers":[
        {
            "category":"Manufacturing",
            "subcategory":"Jewelry",
            "type":"Manufacturing & Wholesale Goods"
        },
        {
            "category":"Shopping",
            "subcategory":"Jewelry",
            "type":"Retail Goods"
        }
    ],
    "sg:phone":"+1 828 258 1761",
    "sg:postcode":"28801",
    "sg:province":"NC",
    "sg:tags":[
        "precious",
        "designer",
        "metal",
        "mfg"
    ],
    "wof:name":"Overstrom Studio Inc",
    "wof:placetype":"venue"
},
  "geometry": {"coordinates":[-82.556245,35.594655],"type":"Point"}
}