{
  "type": "Feature",
  "properties": {
    "iso:country":"US",
    "sg:address":"5812 Ridgeview Rd",
    "sg:city":"Durham",
    "sg:classifiers":[
        {
            "category":"Professional",
            "subcategory":"Business Services",
            "type":"Services"
        }
    ],
    "sg:phone":"+1 919 477 0997",
    "sg:postcode":"27712",
    "sg:province":"NC",
    "sg:tags":[
        "real estate"
    ],
    "wof:name":"Keeton Real Estate",
    "wof:placetype":"venue"
},
  "geometry": {"coordinates":[-78.91637799999999,36.106107],"type":"Point"}
}