{
  "type": "Feature",
  "properties": {
    "addr:full":"115 S 2nd St Albemarle NC 28001",
    "addr:housenumber":"115",
    "addr:postcode":"28001",
    "addr:street":"S 2Nd St",
    "iso:country":"US",
    "sg:address":"115 S 2nd St",
    "sg:city":"Albemarle",
    "sg:classifiers":[
        {
            "category":"Social Services",
            "type":"Services"
        }
    ],
    "sg:phone":"+1 704 983 3330",
    "sg:postcode":"28001",
    "sg:province":"NC",
    "sg:tags":[
        "abuse",
        "testing"
    ],
    "wof:name":"Genesis Anb",
    "wof:placetype":"venue"
},
  "geometry": {"coordinates":[-80.198032,35.350199],"type":"Point"}
}