{
  "type": "Feature",
  "properties": {
    "iso:country":"US",
    "sg:address":"822 S Aycock St",
    "sg:city":"Greensboro",
    "sg:classifiers":[
        {
            "category":"Professional",
            "type":"Services"
        }
    ],
    "sg:phone":"+1 336 574 0049",
    "sg:postcode":"27403",
    "sg:province":"NC",
    "sg:tags":[
        "establishment"
    ],
    "wof:name":"Spoony's",
    "wof:placetype":"venue"
},
  "geometry": {"coordinates":[-79.81559300000001,36.062009],"type":"Point"}
}