{
  "type": "Feature",
  "properties": {
    "addr:full":"339 County Complex Rd Clinton NC 28328",
    "addr:housenumber":"339",
    "addr:postcode":"28328",
    "addr:street":"County Complex Rd",
    "iso:country":"US",
    "sg:address":"339 County Complex Rd",
    "sg:city":"Clinton",
    "sg:classifiers":[
        {
            "category":"Government",
            "subcategory":"Office",
            "type":"Public Place"
        }
    ],
    "sg:phone":"+1 910 592 4124",
    "sg:postcode":"28328",
    "sg:province":"NC",
    "wof:name":"Sampson Employment Office",
    "wof:placetype":"venue"
},
  "geometry": {"coordinates":[-78.293899,34.979632],"type":"Point"}
}