{
  "type": "Feature",
  "properties": {
    "iso:country":"US",
    "sg:address":"705 Robin Rd",
    "sg:city":"Morehead City",
    "sg:classifiers":[
        {
            "category":"Manufacturing",
            "subcategory":"Wood Products",
            "type":"Manufacturing & Wholesale Goods"
        }
    ],
    "sg:phone":"+1 252 247 7263",
    "sg:postcode":"28557",
    "sg:province":"NC",
    "sg:tags":[
        "figurine",
        "sales",
        "gift",
        "mfg"
    ],
    "wof:name":"Woodcrest Creations Inc",
    "wof:placetype":"venue"
},
  "geometry": {"coordinates":[-76.77224699999999,34.735595],"type":"Point"}
}