{
  "type": "Feature",
  "properties": {
    "addr:full":"1295 Conleys Creek Rd Whittier NC 28789",
    "addr:housenumber":"1295",
    "addr:postcode":"28789",
    "addr:street":"Conleys Creek Rd",
    "iso:country":"US",
    "sg:address":"1295 Conleys Creek Rd",
    "sg:city":"Whittier",
    "sg:classifiers":[
        {
            "category":"Restaurant",
            "type":"Food & Drink"
        }
    ],
    "sg:phone":"+1 828 497 6400",
    "sg:postcode":"28789",
    "sg:province":"NC",
    "wof:name":"Oaks Restaurants",
    "wof:placetype":"venue"
},
  "geometry": {"coordinates":[-83.36709999999999,35.415451],"type":"Point"}
}