{
  "type": "Feature",
  "properties": {
    "iso:country":"US",
    "sg:address":"76 Pinedale Rd",
    "sg:city":"Asheville",
    "sg:classifiers":[
        {
            "category":"Restaurant",
            "type":"Food & Drink"
        }
    ],
    "sg:phone":"+1 828 225 2920",
    "sg:postcode":"28805",
    "sg:province":"NC",
    "sg:tags":[
        "eating"
    ],
    "wof:name":"Gadders Inc",
    "wof:placetype":"venue"
},
  "geometry": {"coordinates":[-82.498198,35.596648],"type":"Point"}
}