{
  "type": "Feature",
  "properties": {
    "iso:country":"US",
    "sg:address":"7741 Market St",
    "sg:city":"Wilmington",
    "sg:classifiers":[
        {
            "category":"Building & Trades",
            "subcategory":"Construction",
            "type":"Services"
        }
    ],
    "sg:phone":"+1 910 686 1800",
    "sg:postcode":"28411",
    "sg:province":"NC",
    "sg:tags":[
        "home",
        "builder"
    ],
    "wof:name":"B & B Custom Homes Inc",
    "wof:placetype":"venue"
},
  "geometry": {"coordinates":[-77.80546099999999,34.285998],"type":"Point"}
}