{
  "type": "Feature",
  "properties": {
    "iso:country":"US",
    "sg:address":"402 Joe Collins Rd",
    "sg:city":"Monroe",
    "sg:classifiers":[
        {
            "category":"Building & Trades",
            "subcategory":"Landscaping Services",
            "type":"Services"
        }
    ],
    "sg:phone":"+1 704 764 7807",
    "sg:postcode":"28112",
    "sg:province":"NC",
    "sg:tags":[
        "landscape"
    ],
    "wof:name":"Creative Landscaping & Designs",
    "wof:placetype":"venue"
},
  "geometry": {"coordinates":[-80.547893,34.901049],"type":"Point"}
}