{
  "type": "Feature",
  "properties": {
    "iso:country":"US",
    "sg:address":"1906 Pot Shoals Rd",
    "sg:city":"Saluda",
    "sg:classifiers":[
        {
            "category":"Professional",
            "subcategory":"Business Services",
            "type":"Services"
        }
    ],
    "sg:phone":"+1   ",
    "sg:postcode":"28773",
    "sg:province":"NC",
    "wof:name":"Blue Ridge Industrial Services",
    "wof:placetype":"venue"
},
  "geometry": {"coordinates":[-82.37575099999999,35.253607],"type":"Point"}
}