{
  "type": "Feature",
  "properties": {
    "addr:full":"414 Shepard School Rd Zebulon NC 27597",
    "addr:housenumber":"414",
    "addr:postcode":"27597",
    "addr:street":"Shepard School Rd",
    "iso:country":"US",
    "sg:address":"414 Shepard School Rd",
    "sg:city":"Zebulon",
    "sg:classifiers":[
        {
            "category":"Restaurant",
            "type":"Food & Drink"
        }
    ],
    "sg:phone":"+1 919 269 2764",
    "sg:postcode":"27597",
    "sg:province":"NC",
    "wof:name":"El Sombrero",
    "wof:placetype":"venue"
},
  "geometry": {"coordinates":[-78.312977,35.826345],"type":"Point"}
}