{
  "type": "Feature",
  "properties": {
    "addr:full":"621 John Small Ave Washington NC 27889",
    "addr:housenumber":"621",
    "addr:postcode":"27889",
    "addr:street":"John Small Ave",
    "iso:country":"US",
    "sg:address":"621 John Small Ave",
    "sg:city":"Washington",
    "sg:classifiers":[
        {
            "category":"Personal",
            "subcategory":"Beauty Salon",
            "type":"Services"
        }
    ],
    "sg:phone":"+1   ",
    "sg:postcode":"27889",
    "sg:province":"NC",
    "sg:tags":[
        "shop"
    ],
    "wof:name":"Town & Country Beauty Salon",
    "wof:placetype":"venue"
},
  "geometry": {"coordinates":[-77.045562,35.54583],"type":"Point"}
}