{
  "type": "Feature",
  "properties": {
    "iso:country":"US",
    "sg:address":"427 Tate St",
    "sg:city":"Greensboro",
    "sg:classifiers":[
        {
            "category":"Restaurant",
            "type":"Food & Drink"
        }
    ],
    "sg:phone":"+1 336 274 3699",
    "sg:postcode":"27403",
    "sg:province":"NC",
    "sg:tags":[
        "eating"
    ],
    "wof:name":"Phonesavanh Thai Garden Inc",
    "wof:placetype":"venue"
},
  "geometry": {"coordinates":[-79.805458,36.066851],"type":"Point"}
}