{
  "type": "Feature",
  "properties": {
    "addr:full":"6415 Isaac St Tobaccoville NC 27050",
    "addr:housenumber":"6415",
    "addr:postcode":"27050",
    "addr:street":"Isaac St",
    "iso:country":"US",
    "sg:address":"6415 Isaac St",
    "sg:city":"Tobaccoville",
    "sg:classifiers":[
        {
            "category":"Professional",
            "subcategory":"Detective & Security Services",
            "type":"Services"
        }
    ],
    "sg:phone":"+1 336 924 8325",
    "sg:postcode":"27050",
    "sg:province":"NC",
    "sg:tags":[
        "investigator"
    ],
    "wof:name":"Unlimited Credentialing Inc",
    "wof:placetype":"venue"
},
  "geometry": {"coordinates":[-80.381844,36.204664],"type":"Point"}
}