{
  "type": "Feature",
  "properties": {
    "iso:country":"US",
    "sg:address":"1319 Military Cutoff Rd",
    "sg:city":"Wilmington",
    "sg:classifiers":[
        {
            "category":"Shopping",
            "type":"Retail Goods"
        }
    ],
    "sg:phone":"+1 910 509 2820",
    "sg:postcode":"28405",
    "sg:province":"NC",
    "sg:tags":[
        "art",
        "gallery",
        "dealer"
    ],
    "wof:name":"Serenity Place Gallery",
    "wof:placetype":"venue"
},
  "geometry": {"coordinates":[-77.829275,34.230049],"type":"Point"}
}