{
  "type": "Feature",
  "properties": {
    "addr:full":"111 Buckingham Ave Fayetteville NC 28301",
    "addr:housenumber":"111",
    "addr:postcode":"28301",
    "addr:street":"Buckingham Ave",
    "iso:country":"US",
    "sg:address":"111 Buckingham Ave",
    "sg:city":"Fayetteville",
    "sg:classifiers":[
        {
            "category":"Building & Trades",
            "subcategory":"Landscaping Services",
            "type":"Services"
        }
    ],
    "sg:phone":"+1 910 824 1876",
    "sg:postcode":"28301",
    "sg:province":"NC",
    "sg:tags":[
        "lawn",
        "maintenance",
        "grounds"
    ],
    "wof:name":"Total Lawn Care",
    "wof:placetype":"venue"
},
  "geometry": {"coordinates":[-78.879318,35.076932],"type":"Point"}
}