{
  "type": "Feature",
  "properties": {
    "iso:country":"US",
    "sg:address":"978 Sullivan Rd",
    "sg:city":"Thomasville",
    "sg:classifiers":[
        {
            "category":"Professional",
            "subcategory":"Advertising",
            "type":"Services"
        }
    ],
    "sg:phone":"+1   ",
    "sg:postcode":"27360",
    "sg:province":"NC",
    "sg:tags":[
        "representative"
    ],
    "wof:name":"Kelvin J Kanoy Inc",
    "wof:placetype":"venue"
},
  "geometry": {"coordinates":[-80.126436,35.825179],"type":"Point"}
}