{
  "type": "Feature",
  "properties": {
    "iso:country":"US",
    "sg:address":"245 Kelly Dr",
    "sg:city":"Salisbury",
    "sg:classifiers":[
        {
            "category":"Building & Trades",
            "subcategory":"Cleaning & Sanitation",
            "type":"Services"
        }
    ],
    "sg:phone":"+1   ",
    "sg:postcode":"28147",
    "sg:province":"NC",
    "sg:tags":[
        "maintenance"
    ],
    "wof:name":"Jt S Commercial Cleaning",
    "wof:placetype":"venue"
},
  "geometry": {"coordinates":[-80.50162,35.634422],"type":"Point"}
}