{
  "type": "Feature",
  "properties": {
    "addr:full":"74 Highland St Weaverville NC 28787",
    "addr:housenumber":"74",
    "addr:postcode":"28787",
    "addr:street":"Highland St",
    "iso:country":"US",
    "sg:address":"74 Highland St",
    "sg:city":"Weaverville",
    "sg:classifiers":[
        {
            "category":"Retail",
            "subcategory":"Auto Repair",
            "type":"Services"
        }
    ],
    "sg:phone":"+1 828 645 6454",
    "sg:postcode":"28787",
    "sg:province":"NC",
    "sg:tags":[
        "body",
        "automobile",
        "painting"
    ],
    "wof:name":"Ken's Body Shop",
    "wof:placetype":"venue"
},
  "geometry": {"coordinates":[-82.57048,35.694088],"type":"Point"}
}