{
  "type": "Feature",
  "properties": {
    "iso:country":"US",
    "sg:address":"1012 College St",
    "sg:city":"Oxford",
    "sg:classifiers":[
        {
            "category":"Health Services",
            "subcategory":"Doctor",
            "type":"Services"
        }
    ],
    "sg:phone":"+1 919 693 7108",
    "sg:postcode":"27565",
    "sg:province":"NC",
    "sg:tags":[
        "practice",
        "family",
        "general"
    ],
    "wof:name":"Lake Country Weight Loss Ctr",
    "wof:placetype":"venue"
},
  "geometry": {"coordinates":[-78.594617,36.325753],"type":"Point"}
}