{
  "type": "Feature",
  "properties": {
    "iso:country":"US",
    "sg:address":"108 Park Dr",
    "sg:city":"Enfield",
    "sg:classifiers":[
        {
            "category":"Social Services",
            "type":"Services"
        }
    ],
    "sg:phone":"+1 252 445 4529",
    "sg:postcode":"27823",
    "sg:province":"NC",
    "sg:tags":[
        "youth",
        "organization",
        "center"
    ],
    "wof:name":"Boys & Girls Club",
    "wof:placetype":"venue"
},
  "geometry": {"coordinates":[-77.669774,36.185616],"type":"Point"}
}