{
  "type": "Feature",
  "properties": {
    "addr:full":"1221 Park Ave Greensboro NC 27405",
    "addr:housenumber":"1221",
    "addr:postcode":"27405",
    "addr:street":"Park Ave",
    "iso:country":"US",
    "sg:address":"1221 Park Ave",
    "sg:city":"Greensboro",
    "sg:classifiers":[
        {
            "category":"Building & Trades",
            "subcategory":"Construction",
            "type":"Services"
        }
    ],
    "sg:phone":"+1 336 274 6379",
    "sg:postcode":"27405",
    "sg:province":"NC",
    "sg:tags":[
        "contractor"
    ],
    "wof:name":"A-1 G Varner Siding & Roofing",
    "wof:placetype":"venue"
},
  "geometry": {"coordinates":[-79.77042899999999,36.091608],"type":"Point"}
}