{
  "type": "Feature",
  "properties": {
    "addr:full":"2459 Simonton Rd Statesville NC 28625",
    "addr:housenumber":"2459",
    "addr:postcode":"28625",
    "addr:street":"Simonton Rd",
    "iso:country":"US",
    "sg:address":"2459 Simonton Rd",
    "sg:city":"Statesville",
    "sg:classifiers":[
        {
            "category":"Freight",
            "type":"Transportation"
        }
    ],
    "sg:phone":"+1 704 924 9898",
    "sg:postcode":"28625",
    "sg:province":"NC",
    "sg:tags":[
        "operator",
        "trucking"
    ],
    "wof:name":"William Dejong Enterprises",
    "wof:placetype":"venue"
},
  "geometry": {"coordinates":[-80.84617299999999,35.806973],"type":"Point"}
}