{
  "type": "Feature",
  "properties": {
    "iso:country":"US",
    "sg:address":"466 Stancil Rd",
    "sg:city":"Angier",
    "sg:classifiers":[
        {
            "category":"Building & Trades",
            "subcategory":"Construction",
            "type":"Services"
        }
    ],
    "sg:phone":"+1 919 639 2073",
    "sg:postcode":"27501",
    "sg:province":"NC",
    "sg:tags":[
        "grading",
        "contractor"
    ],
    "wof:name":"Sks Grading Inc",
    "wof:placetype":"venue"
},
  "geometry": {"coordinates":[-78.67035199999999,35.527603],"type":"Point"}
}