{
  "type": "Feature",
  "properties": {
    "iso:country":"US",
    "sg:address":"4110 Randall Pkwy",
    "sg:city":"Wilmington",
    "sg:classifiers":[
        {
            "category":"Building & Trades",
            "subcategory":"Cleaning & Sanitation",
            "type":"Services"
        }
    ],
    "sg:phone":"+1 910 297 1969",
    "sg:postcode":"28403",
    "sg:province":"NC",
    "sg:tags":[
        "ventilating",
        "system"
    ],
    "wof:name":"Efficient Air Flow",
    "wof:placetype":"venue"
},
  "geometry": {"coordinates":[-77.890816,34.231062],"type":"Point"}
}