{
  "type": "Feature",
  "properties": {
    "addr:full":"1293 Flippin Rd Mount Airy NC 27030",
    "addr:housenumber":"1293",
    "addr:postcode":"27030",
    "addr:street":"Flippin Rd",
    "iso:country":"US",
    "sg:address":"1293 Flippin Rd",
    "sg:city":"Mount Airy",
    "sg:classifiers":[
        {
            "category":"Personal",
            "subcategory":"Beauty Salon",
            "type":"Services"
        }
    ],
    "sg:phone":"+1   ",
    "sg:postcode":"27030",
    "sg:province":"NC",
    "sg:tags":[
        "shop"
    ],
    "wof:name":"Kountry Kurl & Style",
    "wof:placetype":"venue"
},
  "geometry": {"coordinates":[-80.417749,36.538301],"type":"Point"}
}