{
  "type": "Feature",
  "properties": {
    "addr:full":"17905 Delmas Dr Cornelius NC 28031",
    "addr:housenumber":"17905",
    "addr:postcode":"28031",
    "addr:street":"Delmas Dr",
    "iso:country":"US",
    "sg:address":"17905 Delmas Dr",
    "sg:city":"Cornelius",
    "sg:classifiers":[
        {
            "category":"Professional",
            "type":"Services"
        }
    ],
    "sg:phone":"+1 704 987 9197",
    "sg:postcode":"28031",
    "sg:province":"NC",
    "sg:tags":[
        "establishment"
    ],
    "wof:name":"Terraces At Oakhurst",
    "wof:placetype":"venue"
},
  "geometry": {"coordinates":[-80.863259,35.458505],"type":"Point"}
}