{
  "type": "Feature",
  "properties": {
    "iso:country":"US",
    "sg:address":"115 Gumberry Rd",
    "sg:city":"Camden",
    "sg:classifiers":[
        {
            "category":"Retail",
            "subcategory":"Auto Repair",
            "type":"Services"
        }
    ],
    "sg:phone":"+1 252 338 6410",
    "sg:postcode":"27921",
    "sg:province":"NC",
    "sg:tags":[
        "transmission"
    ],
    "wof:name":"Davenport & Sons Transmission",
    "wof:placetype":"venue"
},
  "geometry": {"coordinates":[-76.16752700000001,36.328743],"type":"Point"}
}