{
  "type": "Feature",
  "properties": {
    "addr:full":"1600 E Woodlawn Rd Charlotte NC 28209",
    "addr:housenumber":"1600",
    "addr:postcode":"28209",
    "addr:street":"E Woodlawn Rd",
    "iso:country":"US",
    "sg:address":"1600 E Woodlawn Rd",
    "sg:city":"Charlotte",
    "sg:classifiers":[
        {
            "category":"Real Estate",
            "subcategory":"Architect",
            "type":"Services"
        }
    ],
    "sg:phone":"+1 704 372 0116",
    "sg:postcode":"28209",
    "sg:province":"NC",
    "sg:website":"www.dmra.biz",
    "wof:name":"DMR Architecture Pllc",
    "wof:placetype":"venue"
},
  "geometry": {"coordinates":[-80.849062,35.172164],"type":"Point"}
}