{
  "type": "Feature",
  "properties": {
    "addr:full":"5089 Ramillie Run Winston Salem NC 27106",
    "addr:housenumber":"5089",
    "addr:postcode":"27106",
    "addr:street":"Ramillie Run",
    "iso:country":"US",
    "sg:address":"5089 Ramillie Run",
    "sg:city":"Winston Salem",
    "sg:classifiers":[
        {
            "category":"Retail",
            "subcategory":"Animal Services",
            "type":"Services"
        }
    ],
    "sg:phone":"+1 336 922 0878",
    "sg:postcode":"27106",
    "sg:province":"NC",
    "wof:name":"Good Dog",
    "wof:placetype":"venue"
},
  "geometry": {"coordinates":[-80.312786,36.180812],"type":"Point"}
}