{
  "type": "Feature",
  "properties": {
    "addr:full":"2740 E W T Harris Blvd Charlotte NC 28213",
    "addr:housenumber":"2740",
    "addr:postcode":"28213",
    "addr:street":"E W T Harris Blvd",
    "iso:country":"US",
    "sg:address":"2740 E W T Harris Blvd",
    "sg:city":"Charlotte",
    "sg:classifiers":[
        {
            "category":"Utilities",
            "subcategory":"Telephone",
            "type":"Services"
        }
    ],
    "sg:phone":"+1 704 509 9852",
    "sg:postcode":"28213",
    "sg:province":"NC",
    "sg:tags":[
        "communications"
    ],
    "wof:name":"US Telelink Corp",
    "wof:placetype":"venue"
},
  "geometry": {"coordinates":[-80.724233,35.281885],"type":"Point"}
}