{
  "type": "Feature",
  "properties": {
    "addr:full":"508 10th St NW Conover NC 28613",
    "addr:housenumber":"508",
    "addr:postcode":"28613",
    "addr:street":"10Th St Nw",
    "iso:country":"US",
    "sg:address":"508 10th St NW",
    "sg:city":"Conover",
    "sg:classifiers":[
        {
            "category":"Shopping",
            "subcategory":"Tobacco",
            "type":"Retail Goods"
        }
    ],
    "sg:phone":"+1 828 466 6001",
    "sg:postcode":"28613",
    "sg:province":"NC",
    "sg:tags":[
        "cigarette",
        "cigar",
        "dealer"
    ],
    "wof:name":"Smoker Friendly",
    "wof:placetype":"venue"
},
  "geometry": {"coordinates":[-81.228067,35.71604],"type":"Point"}
}