{
  "type": "Feature",
  "properties": {
    "addr:full":"425 Loop Rd Garner NC 27529",
    "addr:housenumber":"425",
    "addr:postcode":"27529",
    "addr:street":"Loop Rd",
    "iso:country":"US",
    "sg:address":"425 Loop Rd",
    "sg:city":"Garner",
    "sg:classifiers":[
        {
            "category":"Retail",
            "subcategory":"Auto Repair",
            "type":"Services"
        }
    ],
    "sg:phone":"+1 919 772 3966",
    "sg:postcode":"27529",
    "sg:province":"NC",
    "sg:tags":[
        "repairing",
        "automobile",
        "radiator"
    ],
    "wof:name":"Sapps Welding & Radiator Svc",
    "wof:placetype":"venue"
},
  "geometry": {"coordinates":[-78.63280899999999,35.720192],"type":"Point"}
}