{
  "type": "Feature",
  "properties": {
    "addr:full":"3057 Bonbrook Dr Winston Salem NC 27106",
    "addr:housenumber":"3057",
    "addr:postcode":"27106",
    "addr:street":"Bonbrook Dr",
    "iso:country":"US",
    "sg:address":"3057 Bonbrook Dr",
    "sg:city":"Winston Salem",
    "sg:classifiers":[
        {
            "category":"Social Services",
            "type":"Services"
        }
    ],
    "sg:phone":"+1 336 723 4933",
    "sg:postcode":"27106",
    "sg:province":"NC",
    "sg:tags":[
        "counselor",
        "marriage",
        "family"
    ],
    "wof:name":"Piedmont Attachment Ctr Inc",
    "wof:placetype":"venue"
},
  "geometry": {"coordinates":[-80.30418,36.149654],"type":"Point"}
}