{
  "type": "Feature",
  "properties": {
    "addr:full":"2487 Charlotte Hwy Mooresville NC 28117",
    "addr:housenumber":"2487",
    "addr:postcode":"28117",
    "addr:street":"Charlotte Hwy",
    "iso:country":"US",
    "sg:address":"2487 Charlotte Hwy",
    "sg:city":"Mooresville",
    "sg:classifiers":[
        {
            "category":"Education",
            "subcategory":"School",
            "type":"Public Place"
        }
    ],
    "sg:phone":"+1 704 663 3441",
    "sg:postcode":"28117",
    "sg:province":"NC",
    "wof:name":"Mooresville Christian Academy",
    "wof:placetype":"venue"
},
  "geometry": {"coordinates":[-80.838604,35.598572],"type":"Point"}
}