{
  "type": "Feature",
  "properties": {
    "addr:full":"801 S Queen St Kinston NC 28501",
    "addr:housenumber":"801",
    "addr:postcode":"28501",
    "addr:street":"S Queen St",
    "iso:country":"US",
    "sg:address":"801 S Queen St",
    "sg:city":"Kinston",
    "sg:classifiers":[
        {
            "category":"Wholesale",
            "subcategory":"Machinery & Supplies",
            "type":"Manufacturing & Wholesale Goods"
        }
    ],
    "sg:phone":"+1 252 527 8083",
    "sg:postcode":"28501",
    "sg:province":"NC",
    "sg:tags":[
        "farm",
        "equipment"
    ],
    "sg:website":"www.millslawngarden.com",
    "wof:name":"Mills International Inc",
    "wof:placetype":"venue"
},
  "geometry": {"coordinates":[-77.581504,35.252937],"type":"Point"}
}