{
  "type": "Feature",
  "properties": {
    "iso:country":"US",
    "sg:address":"3405 Old Charlotte Hwy",
    "sg:city":"Monroe",
    "sg:classifiers":[
        {
            "category":"Organizations",
            "subcategory":"Religious Organization",
            "type":"Services"
        }
    ],
    "sg:phone":"+1   ",
    "sg:postcode":"28110",
    "sg:province":"NC",
    "wof:name":"Monroe Pntcstalholiness Church",
    "wof:placetype":"venue"
},
  "geometry": {"coordinates":[-80.59724199999999,35.024735],"type":"Point"}
}