{
  "type": "Feature",
  "properties": {
    "iso:country":"US",
    "sg:address":"13426 Old Mine Rd",
    "sg:city":"Gold Hill",
    "sg:classifiers":[
        {
            "category":"Freight",
            "type":"Transportation"
        }
    ],
    "sg:phone":"+1 704 279 4820",
    "sg:postcode":"28071",
    "sg:province":"NC",
    "sg:tags":[
        "operator",
        "local",
        "trucking"
    ],
    "wof:name":"Robin T Wagoner Hauling",
    "wof:placetype":"venue"
},
  "geometry": {"coordinates":[-80.354322,35.497214],"type":"Point"}
}