{
  "type": "Feature",
  "properties": {
    "iso:country":"US",
    "sg:address":"315 S Lexington Ave",
    "sg:city":"Burlington",
    "sg:classifiers":[
        {
            "category":"Wholesale",
            "subcategory":"Vending Machines",
            "type":"Manufacturing & Wholesale Goods"
        }
    ],
    "sg:phone":"+1 336 228 6594",
    "sg:postcode":"27215",
    "sg:province":"NC",
    "sg:tags":[
        "operator"
    ],
    "wof:name":"Collegiate Vending",
    "wof:placetype":"venue"
},
  "geometry": {"coordinates":[-79.43569100000001,36.091559],"type":"Point"}
}