{
  "type": "Feature",
  "properties": {
    "iso:country":"US",
    "sg:address":"1941 Vanstory St",
    "sg:city":"Greensboro",
    "sg:classifiers":[
        {
            "category":"Social Services",
            "type":"Services"
        }
    ],
    "sg:phone":"+1 336 292 9390",
    "sg:postcode":"27403",
    "sg:province":"NC",
    "sg:tags":[
        "counseling"
    ],
    "wof:name":"Advocate Counseling Ctr",
    "wof:placetype":"venue"
},
  "geometry": {"coordinates":[-79.83351399999999,36.049131],"type":"Point"}
}