{
  "type": "Feature",
  "properties": {
    "addr:full":"2094 Sugar Mountain Dr Banner Elk NC 28657",
    "addr:housenumber":"2094",
    "addr:postcode":"28657",
    "addr:street":"Sugar Mountain Dr Banner",
    "iso:country":"US",
    "sg:address":"2094 Sugar Mountain Dr",
    "sg:city":"Banner Elk",
    "sg:classifiers":[
        {
            "category":"Professional",
            "subcategory":"Business Services",
            "type":"Services"
        }
    ],
    "sg:phone":"+1   ",
    "sg:postcode":"28657",
    "sg:province":"NC",
    "wof:name":"Mountaineer Associates",
    "wof:placetype":"venue"
},
  "geometry": {"coordinates":[-81.855929,36.129637],"type":"Point"}
}