{
  "type": "Feature",
  "properties": {
    "addr:full":"1337 Wood Branch Dr Charlotte NC 28273",
    "addr:housenumber":"1337",
    "addr:postcode":"28273",
    "addr:street":"Wood Branch Dr",
    "iso:country":"US",
    "sg:address":"1337 Wood Branch Dr",
    "sg:city":"Charlotte",
    "sg:classifiers":[
        {
            "category":"Manufacturing",
            "subcategory":"Printing",
            "type":"Manufacturing & Wholesale Goods"
        }
    ],
    "sg:phone":"+1 704 588 4280",
    "sg:postcode":"28273",
    "sg:province":"NC",
    "sg:tags":[
        "printer"
    ],
    "sg:website":"www.cadmus.com",
    "wof:name":"Cadmus Communications Corp",
    "wof:placetype":"venue"
},
  "geometry": {"coordinates":[-80.92532199999999,35.124314],"type":"Point"}
}