{
  "type": "Feature",
  "properties": {
    "addr:full":"756 W King St Boone NC 28607",
    "addr:housenumber":"756",
    "addr:postcode":"28607",
    "addr:street":"W King St",
    "iso:country":"US",
    "sg:address":"756 W King St",
    "sg:city":"Boone",
    "sg:classifiers":[
        {
            "category":"Professional",
            "type":"Services"
        }
    ],
    "sg:phone":"+1 828 263 8860",
    "sg:postcode":"28607",
    "sg:province":"NC",
    "wof:name":"David J Turlington III",
    "wof:placetype":"venue"
},
  "geometry": {"coordinates":[-81.685058,36.219342],"type":"Point"}
}