{
  "type": "Feature",
  "properties": {
    "addr:full":"818 Woodcote St Winston Salem NC 27107",
    "addr:housenumber":"818",
    "addr:postcode":"27107",
    "addr:street":"Woodcote St",
    "iso:country":"US",
    "sg:address":"818 Woodcote St",
    "sg:city":"Winston Salem",
    "sg:classifiers":[
        {
            "category":"Arts & Performance",
            "subcategory":"Theater",
            "type":"Entertainment"
        }
    ],
    "sg:phone":"+1   ",
    "sg:postcode":"27107",
    "sg:province":"NC",
    "sg:tags":[
        "group"
    ],
    "wof:name":"Tarheel Assn Storytellers",
    "wof:placetype":"venue"
},
  "geometry": {"coordinates":[-80.222032,36.058202],"type":"Point"}
}