{
  "type": "Feature",
  "properties": {
    "iso:country":"US",
    "sg:address":"433 Lance Ave",
    "sg:city":"Hot Springs",
    "sg:classifiers":[
        {
            "category":"Travel",
            "subcategory":"Hotels & Motels",
            "type":"Entertainment"
        }
    ],
    "sg:phone":"+1 828 622 7621",
    "sg:postcode":"28743",
    "sg:province":"NC",
    "sg:tags":[
        "breakfast",
        "accommodation",
        "bed"
    ],
    "sg:website":"www.ducketthouseinn.com",
    "wof:name":"Duckett House Inn & Farm",
    "wof:placetype":"venue"
},
  "geometry": {"coordinates":[-82.829762,35.887323],"type":"Point"}
}