{
  "type": "Feature",
  "properties": {
    "iso:country":"US",
    "sg:address":"10821 N Main St",
    "sg:city":"Archdale",
    "sg:classifiers":[
        {
            "category":"Professional",
            "subcategory":"Lawyer & Legal Services",
            "type":"Services"
        }
    ],
    "sg:phone":"+1 336 431 9155",
    "sg:postcode":"27263",
    "sg:province":"NC",
    "sg:tags":[
        "attorney"
    ],
    "wof:name":"James L Tennant",
    "wof:placetype":"venue"
},
  "geometry": {"coordinates":[-79.96821199999999,35.909293],"type":"Point"}
}