{
  "type": "Feature",
  "properties": {
    "iso:country":"US",
    "sg:address":"10111 Tallent Ln",
    "sg:city":"Huntersville",
    "sg:classifiers":[
        {
            "category":"Shopping",
            "subcategory":"Jewelry",
            "type":"Retail Goods"
        }
    ],
    "sg:phone":"+1 704 896 8371",
    "sg:postcode":"28078",
    "sg:province":"NC",
    "wof:name":"Sterling Treasures",
    "wof:placetype":"venue"
},
  "geometry": {"coordinates":[-80.85908999999999,35.436118],"type":"Point"}
}