{
  "type": "Feature",
  "properties": {
    "iso:country":"US",
    "sg:address":"1601 High House Rd",
    "sg:city":"Cary",
    "sg:classifiers":[
        {
            "category":"Professional",
            "type":"Services"
        }
    ],
    "sg:phone":"+1 919 466 9366",
    "sg:postcode":"27513",
    "sg:province":"NC",
    "sg:tags":[
        "establishment"
    ],
    "wof:name":"Searstone",
    "wof:placetype":"venue"
},
  "geometry": {"coordinates":[-78.83978399999999,35.792942],"type":"Point"}
}