{
  "type": "Feature",
  "properties": {
    "iso:country":"US",
    "sg:address":"595 School Rd E",
    "sg:city":"Asheville",
    "sg:classifiers":[
        {
            "category":"Building & Trades",
            "subcategory":"Construction",
            "type":"Services"
        }
    ],
    "sg:phone":"+1 828 681 0541",
    "sg:postcode":"28803",
    "sg:province":"NC",
    "sg:tags":[
        "hanging",
        "contractor"
    ],
    "wof:name":"Larry Ingle Paint Service",
    "wof:placetype":"venue"
},
  "geometry": {"coordinates":[-82.494455,35.495643],"type":"Point"}
}