{
  "type": "Feature",
  "properties": {
    "addr:full":"712 Brookdale Dr Thomasville NC 27360",
    "addr:housenumber":"712",
    "addr:postcode":"27360",
    "addr:street":"Brookdale Dr",
    "iso:country":"US",
    "sg:address":"712 Brookdale Dr",
    "sg:city":"Thomasville",
    "sg:classifiers":[
        {
            "category":"Retail",
            "subcategory":"Animal Services",
            "type":"Services"
        }
    ],
    "sg:phone":"+1 336 476 5080",
    "sg:postcode":"27360",
    "sg:province":"NC",
    "sg:tags":[
        "pet",
        "grooming",
        "washing"
    ],
    "wof:name":"Thomasville Pet Ctr",
    "wof:placetype":"venue"
},
  "geometry": {"coordinates":[-80.06687700000001,35.900544],"type":"Point"}
}