{
  "type": "Feature",
  "properties": {
    "iso:country":"US",
    "sg:address":"761 Nashville Rd",
    "sg:city":"Rocky Mount",
    "sg:classifiers":[
        {
            "category":"Building & Trades",
            "subcategory":"Cleaning & Sanitation",
            "type":"Services"
        }
    ],
    "sg:phone":"+1 252 442 2111",
    "sg:postcode":"27803",
    "sg:province":"NC",
    "sg:tags":[
        "ventilating",
        "system",
        "maintenance"
    ],
    "wof:name":"A Air Care Duct Cleaning Svc",
    "wof:placetype":"venue"
},
  "geometry": {"coordinates":[-77.815305,35.928305],"type":"Point"}
}