{
  "type": "Feature",
  "properties": {
    "addr:full":"4811 Hope Valley Rd Durham NC 27707",
    "addr:housenumber":"4811",
    "addr:postcode":"27707",
    "addr:street":"Hope Valley Rd",
    "iso:country":"US",
    "sg:address":"4811 Hope Valley Rd",
    "sg:city":"Durham",
    "sg:classifiers":[
        {
            "category":"Banks & Credit Unions",
            "subcategory":"Bank",
            "type":"Services"
        }
    ],
    "sg:phone":"+1 919 956 2263",
    "sg:postcode":"27707",
    "sg:province":"NC",
    "sg:tags":[
        "national",
        "commercial"
    ],
    "wof:name":"Bank Of America",
    "wof:placetype":"venue"
},
  "geometry": {"coordinates":[-78.95927,35.920369],"type":"Point"}
}