{
  "type": "Feature",
  "properties": {
    "iso:country":"US",
    "sg:address":"316 E Murray St",
    "sg:city":"Wallace",
    "sg:classifiers":[
        {
            "category":"Government",
            "subcategory":"Court House",
            "type":"Public Place"
        }
    ],
    "sg:phone":"+1 910 285 3351",
    "sg:postcode":"28466",
    "sg:province":"NC",
    "sg:tags":[
        "city"
    ],
    "wof:name":"Wallace Magistrates Office",
    "wof:placetype":"venue"
},
  "geometry": {"coordinates":[-77.99332,34.738179],"type":"Point"}
}