{
  "type": "Feature",
  "properties": {
    "iso:country":"US",
    "sg:address":"1342 N Ohenry Blvd",
    "sg:city":"Greensboro",
    "sg:classifiers":[
        {
            "category":"Building & Trades",
            "subcategory":"Construction",
            "type":"Services"
        }
    ],
    "sg:phone":"+1 336 272 5724",
    "sg:postcode":"27405",
    "sg:province":"NC",
    "sg:tags":[
        "house"
    ],
    "wof:name":"Cost Plus Construction",
    "wof:placetype":"venue"
},
  "geometry": {"coordinates":[-79.76589800000001,36.089544],"type":"Point"}
}