{
  "type": "Feature",
  "properties": {
    "addr:full":"2872 Rocky Cliff Trl Burlington NC 27215",
    "addr:housenumber":"2872",
    "addr:postcode":"27215",
    "addr:street":"Rocky Cliff Trl",
    "iso:country":"US",
    "sg:address":"2872 Rocky Cliff Trl",
    "sg:city":"Burlington",
    "sg:classifiers":[
        {
            "category":"Insurance",
            "subcategory":"Insurance Agent",
            "type":"Services"
        }
    ],
    "sg:phone":"+1 336 226 4263",
    "sg:postcode":"27215",
    "sg:province":"NC",
    "wof:name":"David Fox",
    "wof:placetype":"venue"
},
  "geometry": {"coordinates":[-79.451457,36.024005],"type":"Point"}
}