{
  "type": "Feature",
  "properties": {
    "addr:full":"1260 NW Maynard Rd Cary NC 27513",
    "addr:housenumber":"1260",
    "addr:postcode":"27513",
    "addr:street":"Nw Maynard Rd",
    "iso:country":"US",
    "sg:address":"1260 NW Maynard Rd",
    "sg:city":"Cary",
    "sg:classifiers":[
        {
            "category":"Restaurant",
            "type":"Food & Drink"
        }
    ],
    "sg:phone":"+1 919 319 3232",
    "sg:postcode":"27513",
    "sg:province":"NC",
    "sg:tags":[
        "eating",
        "pizza"
    ],
    "wof:name":"Brooklyn Boys Pizzeria",
    "wof:placetype":"venue"
},
  "geometry": {"coordinates":[-78.809601,35.785301],"type":"Point"}
}