{
  "type": "Feature",
  "properties": {
    "iso:country":"US",
    "sg:address":"1610 Landis Hwy",
    "sg:city":"Mooresville",
    "sg:classifiers":[
        {
            "category":"Retail",
            "subcategory":"Repair Shop",
            "type":"Services"
        }
    ],
    "sg:phone":"+1 704 663 1991",
    "sg:postcode":"28115",
    "sg:province":"NC",
    "sg:tags":[
        "electric",
        "motor"
    ],
    "wof:name":"Qualified Electric Mtr Svc Co",
    "wof:placetype":"venue"
},
  "geometry": {"coordinates":[-80.77920399999999,35.598172],"type":"Point"}
}