{
  "type": "Feature",
  "properties": {
    "iso:country":"US",
    "sg:address":"1028 N Madison Blvd",
    "sg:city":"Roxboro",
    "sg:classifiers":[
        {
            "category":"Retail",
            "subcategory":"Self-service Laundry",
            "type":"Services"
        }
    ],
    "sg:phone":"+1   ",
    "sg:postcode":"27573",
    "sg:province":"NC",
    "sg:tags":[
        "coin"
    ],
    "wof:name":"Boulevard Laundry",
    "wof:placetype":"venue"
},
  "geometry": {"coordinates":[-78.975638,36.408657],"type":"Point"}
}