{
  "type": "Feature",
  "properties": {
    "iso:country":"US",
    "sg:address":"215 S McDowell St",
    "sg:city":"Raleigh",
    "sg:classifiers":[
        {
            "category":"Insurance",
            "subcategory":"Hazard Insurance",
            "type":"Services"
        }
    ],
    "sg:phone":"+1 919 829 4666",
    "sg:postcode":"27601",
    "sg:province":"NC",
    "sg:tags":[
        "fund"
    ],
    "wof:name":"Welfare Fund of Employees Inc",
    "wof:placetype":"venue"
},
  "geometry": {"coordinates":[-78.64180899999999,35.777194],"type":"Point"}
}