{
  "type": "Feature",
  "properties": {
    "iso:country":"US",
    "sg:address":"120 Kilmayne Dr",
    "sg:city":"Cary",
    "sg:classifiers":[
        {
            "category":"Travel",
            "subcategory":"Travel Agent",
            "type":"Entertainment"
        }
    ],
    "sg:phone":"+1 919 380 1555",
    "sg:postcode":"27511",
    "sg:province":"NC",
    "wof:name":"Travel Experts of Cary",
    "wof:placetype":"venue"
},
  "geometry": {"coordinates":[-78.78371,35.769587],"type":"Point"}
}