{
  "type": "Feature",
  "properties": {
    "addr:full":"11616 Pacesferry Dr Raleigh NC 27614",
    "addr:housenumber":"11616",
    "addr:postcode":"27614",
    "addr:street":"Pacesferry Dr",
    "iso:country":"US",
    "sg:address":"11616 Pacesferry Dr",
    "sg:city":"Raleigh",
    "sg:classifiers":[
        {
            "category":"Professional",
            "type":"Services"
        }
    ],
    "sg:phone":"+1 919 676 9255",
    "sg:postcode":"27614",
    "sg:province":"NC",
    "wof:name":"Kiku Designs",
    "wof:placetype":"venue"
},
  "geometry": {"coordinates":[-78.617998,35.940417],"type":"Point"}
}