{
  "type": "Feature",
  "properties": {
    "iso:country":"US",
    "sg:address":"244 Fairview Dr",
    "sg:city":"Lexington",
    "sg:classifiers":[
        {
            "category":"Insurance",
            "subcategory":"Insurance Agent",
            "type":"Services"
        }
    ],
    "sg:phone":"+1 336 249 8132",
    "sg:postcode":"27292",
    "sg:province":"NC",
    "sg:tags":[
        "agency"
    ],
    "wof:name":"Dan Garrison Insurance Agency",
    "wof:placetype":"venue"
},
  "geometry": {"coordinates":[-80.25031799999999,35.816713],"type":"Point"}
}