{
  "type": "Feature",
  "properties": {
    "addr:full":"116 Elm St Carrboro NC 27510",
    "addr:housenumber":"116",
    "addr:postcode":"27510",
    "addr:street":"Elm St",
    "iso:country":"US",
    "sg:address":"116 Elm St",
    "sg:city":"Carrboro",
    "sg:classifiers":[
        {
            "category":"Retail",
            "subcategory":"Animal Services",
            "type":"Services"
        }
    ],
    "sg:phone":"+1 919 918 7995",
    "sg:postcode":"27510",
    "sg:province":"NC",
    "sg:tags":[
        "pet",
        "boarding",
        "sitting"
    ],
    "wof:name":"Happy At Home",
    "wof:placetype":"venue"
},
  "geometry": {"coordinates":[-79.07621399999999,35.912775],"type":"Point"}
}