{
  "type": "Feature",
  "properties": {
    "iso:country":"US",
    "sg:address":"111 Wicker St",
    "sg:city":"Sanford",
    "sg:classifiers":[
        {
            "category":"Shopping",
            "subcategory":"Gifts & Souvenirs",
            "type":"Retail Goods"
        }
    ],
    "sg:phone":"+1 919 777 0440",
    "sg:postcode":"27330",
    "sg:province":"NC",
    "sg:tags":[
        "basket",
        "parcel"
    ],
    "wof:name":"Unique Designs",
    "wof:placetype":"venue"
},
  "geometry": {"coordinates":[-79.177121,35.479941],"type":"Point"}
}