{
  "type": "Feature",
  "properties": {
    "addr:full":"285 Old Conrad Farm Rd Thomasville NC 27360",
    "addr:housenumber":"285",
    "addr:postcode":"27360",
    "addr:street":"Old Conrad Farm Rd",
    "iso:country":"US",
    "sg:address":"285 Old Conrad Farm Rd",
    "sg:city":"Thomasville",
    "sg:classifiers":[
        {
            "category":"Shopping",
            "subcategory":"Computers & Home Electronics",
            "type":"Retail Goods"
        }
    ],
    "sg:phone":"+1 336 475 0279",
    "sg:postcode":"27360",
    "sg:province":"NC",
    "sg:tags":[
        "equipment",
        "satellite",
        "system"
    ],
    "wof:name":"Campbell Enterprises",
    "wof:placetype":"venue"
},
  "geometry": {"coordinates":[-80.149788,35.896378],"type":"Point"}
}