{
  "type": "Feature",
  "properties": {
    "iso:country":"US",
    "sg:address":"68 W Peacock Ave",
    "sg:city":"Denton",
    "sg:classifiers":[
        {
            "category":"Home & Garden",
            "subcategory":"Garden Supply",
            "type":"Retail Goods"
        }
    ],
    "sg:phone":"+1 336 859 3752",
    "sg:postcode":"27239",
    "sg:province":"NC",
    "sg:tags":[
        "feed",
        "fertilizer"
    ],
    "wof:name":"Better Farm Service Inc",
    "wof:placetype":"venue"
},
  "geometry": {"coordinates":[-80.11407699999999,35.63042],"type":"Point"}
}