{
  "type": "Feature",
  "properties": {
    "addr:full":"312 Franklin Dr Forest City NC 28043",
    "addr:housenumber":"312",
    "addr:postcode":"28043",
    "addr:street":"Franklin Dr",
    "iso:country":"US",
    "sg:address":"312 Franklin Dr",
    "sg:city":"Forest City",
    "sg:classifiers":[
        {
            "category":"Freight",
            "type":"Transportation"
        }
    ],
    "sg:phone":"+1 828 247 0582",
    "sg:postcode":"28043",
    "sg:province":"NC",
    "sg:tags":[
        "commercial",
        "storage"
    ],
    "wof:name":"Forrestal Apts & Storage",
    "wof:placetype":"venue"
},
  "geometry": {"coordinates":[-81.881266,35.324297],"type":"Point"}
}