{
  "type": "Feature",
  "properties": {
    "addr:full":"6615 Litchford Rd Raleigh NC 27615",
    "addr:housenumber":"6615",
    "addr:postcode":"27615",
    "addr:street":"Litchford Rd",
    "iso:country":"US",
    "sg:address":"6615 Litchford Rd",
    "sg:city":"Raleigh",
    "sg:classifiers":[
        {
            "category":"Building & Trades",
            "subcategory":"Landscaping Services",
            "type":"Services"
        }
    ],
    "sg:phone":"+1 919 878 0079",
    "sg:postcode":"27615",
    "sg:province":"NC",
    "sg:tags":[
        "lawn",
        "maintenance",
        "grounds"
    ],
    "wof:name":"Fetsko Lawn Care",
    "wof:placetype":"venue"
},
  "geometry": {"coordinates":[-78.59669599999999,35.872235],"type":"Point"}
}