{
  "type": "Feature",
  "properties": {
    "addr:full":"869 Lakeview Dr Thomasville NC 27360",
    "addr:housenumber":"869",
    "addr:postcode":"27360",
    "addr:street":"Lakeview Dr",
    "iso:country":"US",
    "sg:address":"869 Lakeview Dr",
    "sg:city":"Thomasville",
    "sg:classifiers":[
        {
            "category":"Personal",
            "subcategory":"Beauty Salon",
            "type":"Services"
        }
    ],
    "sg:phone":"+1 336 476 7050",
    "sg:postcode":"27360",
    "sg:province":"NC",
    "wof:name":"Sylvia's Salon",
    "wof:placetype":"venue"
},
  "geometry": {"coordinates":[-80.081363,35.838757],"type":"Point"}
}