{
  "type": "Feature",
  "properties": {
    "iso:country":"US",
    "sg:address":"38206 Gold Hill Rd",
    "sg:city":"Richfield",
    "sg:classifiers":[
        {
            "category":"Farming",
            "subcategory":"Livestock Farm",
            "type":"Manufacturing & Wholesale Goods"
        }
    ],
    "sg:phone":"+1 704 463 1460",
    "sg:postcode":"28137",
    "sg:province":"NC",
    "sg:tags":[
        "beef",
        "feedlot",
        "cattle"
    ],
    "wof:name":"Vanhoy Farm",
    "wof:placetype":"venue"
},
  "geometry": {"coordinates":[-80.331264,35.41383],"type":"Point"}
}