{
  "type": "Feature",
  "properties": {
    "addr:full":"104 White Pine Dr Durham NC 27705",
    "addr:housenumber":"104",
    "addr:postcode":"27705",
    "addr:street":"White Pine Dr",
    "iso:country":"US",
    "sg:address":"104 White Pine Dr",
    "sg:city":"Durham",
    "sg:classifiers":[
        {
            "category":"Professional",
            "type":"Services"
        }
    ],
    "sg:phone":"+1 919 309 4859",
    "sg:postcode":"27705",
    "sg:province":"NC",
    "wof:name":"Autonmous Rcnnaissance Systems",
    "wof:placetype":"venue"
},
  "geometry": {"coordinates":[-78.96637699999999,36.011632],"type":"Point"}
}