{
  "type": "Feature",
  "properties": {
    "addr:full":"130 N Old Carriage Rd Rocky Mount NC 27804",
    "addr:housenumber":"130",
    "addr:postcode":"27804",
    "addr:street":"N Old Carriage Rd",
    "iso:country":"US",
    "sg:address":"130 N Old Carriage Rd",
    "sg:city":"Rocky Mount",
    "sg:classifiers":[
        {
            "category":"Utilities",
            "subcategory":"Natural Gas",
            "type":"Services"
        }
    ],
    "sg:phone":"+1 252 445 5131",
    "sg:postcode":"27804",
    "sg:province":"NC",
    "sg:tags":[
        "company"
    ],
    "wof:name":"Eastern Petroleum",
    "wof:placetype":"venue"
},
  "geometry": {"coordinates":[-77.90143999999999,35.992414],"type":"Point"}
}