{
  "type": "Feature",
  "properties": {
    "addr:full":"187 Oak Ridge Ln Beulaville NC 28518",
    "addr:housenumber":"187",
    "addr:postcode":"28518",
    "addr:street":"Oak Ridge Ln",
    "iso:country":"US",
    "sg:address":"187 Oak Ridge Ln",
    "sg:city":"Beulaville",
    "sg:classifiers":[
        {
            "category":"Building & Trades",
            "subcategory":"Electrical",
            "type":"Services"
        }
    ],
    "sg:phone":"+1 910 298 4268",
    "sg:postcode":"28518",
    "sg:province":"NC",
    "sg:tags":[
        "electric",
        "contractor"
    ],
    "wof:name":"James Earl Edwards Electric Co",
    "wof:placetype":"venue"
},
  "geometry": {"coordinates":[-77.66816799999999,34.920769],"type":"Point"}
}