{
  "type": "Feature",
  "properties": {
    "addr:full":"1590 Westbrook Plaza Dr Winston Salem NC 27103",
    "addr:housenumber":"1590",
    "addr:postcode":"27103",
    "addr:street":"Westbrook Plaza Dr",
    "iso:country":"US",
    "sg:address":"1590 Westbrook Plaza Dr",
    "sg:city":"Winston Salem",
    "sg:classifiers":[
        {
            "category":"Shopping",
            "subcategory":"Computers & Home Electronics",
            "type":"Retail Goods"
        }
    ],
    "sg:phone":"+1 336 774 2171",
    "sg:postcode":"27103",
    "sg:province":"NC",
    "sg:tags":[
        "software"
    ],
    "sg:website":"www.ecaos.com",
    "wof:name":"Intelligent Business Solutions",
    "wof:placetype":"venue"
},
  "geometry": {"coordinates":[-80.313793,36.069422],"type":"Point"}
}