{
  "type": "Feature",
  "properties": {
    "iso:country":"US",
    "sg:address":"100 Countryside Dr",
    "sg:city":"Edenton",
    "sg:classifiers":[
        {
            "category":"Organizations",
            "subcategory":"Religious Organization",
            "type":"Services"
        }
    ],
    "sg:phone":"+1 252 482 3788",
    "sg:postcode":"27932",
    "sg:province":"NC",
    "sg:tags":[
        "church"
    ],
    "wof:name":"Countryside Church Of Christ",
    "wof:placetype":"venue"
},
  "geometry": {"coordinates":[-76.66104300000001,36.057401],"type":"Point"}
}