{
  "type": "Feature",
  "properties": {
    "addr:full":"5257 Hathaway St Battleboro NC 27809",
    "addr:housenumber":"5257",
    "addr:postcode":"27809",
    "addr:street":"Hathaway St",
    "iso:country":"US",
    "sg:address":"5257 Hathaway St",
    "sg:city":"Battleboro",
    "sg:classifiers":[
        {
            "category":"Retail",
            "subcategory":"Auto Repair",
            "type":"Services"
        }
    ],
    "sg:phone":"+1 252 442 9140",
    "sg:postcode":"27809",
    "sg:province":"NC",
    "sg:tags":[
        "truck"
    ],
    "wof:name":"Bryan's Auto Truck Svc",
    "wof:placetype":"venue"
},
  "geometry": {"coordinates":[-77.749925,36.052922],"type":"Point"}
}