{
  "type": "Feature",
  "properties": {
    "iso:country":"US",
    "sg:address":"2210 N Cannon Blvd",
    "sg:city":"Kannapolis",
    "sg:classifiers":[
        {
            "category":"Retail",
            "subcategory":"Repair Shop",
            "type":"Services"
        }
    ],
    "sg:phone":"+1   ",
    "sg:postcode":"28083",
    "sg:province":"NC",
    "sg:tags":[
        "welding"
    ],
    "wof:name":"Barnes Cycle Repair",
    "wof:placetype":"venue"
},
  "geometry": {"coordinates":[-80.611332,35.524531],"type":"Point"}
}