{
  "type": "Feature",
  "properties": {
    "addr:full":"1037 Ridgefield Dr Indian Trail NC 28079",
    "addr:housenumber":"1037",
    "addr:postcode":"28079",
    "addr:street":"Ridgefield Dr",
    "iso:country":"US",
    "sg:address":"1037 Ridgefield Dr",
    "sg:city":"Indian Trail",
    "sg:classifiers":[
        {
            "category":"Building & Trades",
            "subcategory":"Construction",
            "type":"Services"
        }
    ],
    "sg:phone":"+1 704 821 0569",
    "sg:postcode":"28079",
    "sg:province":"NC",
    "sg:tags":[
        "contractor"
    ],
    "wof:name":"Blueline Roofing & Constructio",
    "wof:placetype":"venue"
},
  "geometry": {"coordinates":[-80.65390499999999,35.070594],"type":"Point"}
}