{
  "type": "Feature",
  "properties": {
    "iso:country":"US",
    "sg:address":"305 1st Ave S",
    "sg:city":"Conover",
    "sg:classifiers":[
        {
            "category":"Retail",
            "subcategory":"Repair Shop",
            "type":"Services"
        }
    ],
    "sg:phone":"+1 828 465 1525",
    "sg:postcode":"28613",
    "sg:province":"NC",
    "sg:tags":[
        "lock",
        "locksmith"
    ],
    "wof:name":"Walt's Lock & Key Inc",
    "wof:placetype":"venue"
},
  "geometry": {"coordinates":[-81.220296,35.704343],"type":"Point"}
}