{
  "type": "Feature",
  "properties": {
    "addr:full":"910 Airport Rd Chapel Hill NC 27514",
    "addr:housenumber":"910",
    "addr:postcode":"27514",
    "addr:street":"Airport Rd",
    "iso:country":"US",
    "sg:address":"910 Airport Rd",
    "sg:city":"Chapel Hill",
    "sg:classifiers":[
        {
            "category":"Health Services",
            "subcategory":"Optometrist",
            "type":"Services"
        }
    ],
    "sg:phone":"+1 919 942 8531",
    "sg:postcode":"27514",
    "sg:province":"NC",
    "wof:name":"Kroninger David L Dr Optmtrst",
    "wof:placetype":"venue"
},
  "geometry": {"coordinates":[-79.05500000000001,35.930698],"type":"Point"}
}