{
  "type": "Feature",
  "properties": {
    "iso:country":"US",
    "sg:address":"1300 Asheville Hwy",
    "sg:city":"Brevard",
    "sg:classifiers":[
        {
            "category":"Retail",
            "subcategory":"Auto Repair",
            "type":"Services"
        }
    ],
    "sg:phone":"+1 828 884 3534",
    "sg:postcode":"28712",
    "sg:province":"SC",
    "sg:tags":[
        "repairing",
        "automobile"
    ],
    "wof:name":"Brown's Transmission Svc",
    "wof:placetype":"venue"
},
  "geometry": {"coordinates":[-82.70824399999999,35.270286],"type":"Point"}
}