{
  "type": "Feature",
  "properties": {
    "addr:full":"201 S Sharpe St Selma NC 27576",
    "addr:housenumber":"201",
    "addr:postcode":"27576",
    "addr:street":"S Sharpe St",
    "iso:country":"US",
    "sg:address":"201 S Sharpe St",
    "sg:city":"Selma",
    "sg:classifiers":[
        {
            "category":"Social Services",
            "type":"Services"
        }
    ],
    "sg:phone":"+1 919 965 6478",
    "sg:postcode":"27576",
    "sg:province":"NC",
    "sg:tags":[
        "organization",
        "welfare"
    ],
    "wof:name":"Selma Senior Ctr",
    "wof:placetype":"venue"
},
  "geometry": {"coordinates":[-78.282382,35.533501],"type":"Point"}
}