{
  "type": "Feature",
  "properties": {
    "iso:country":"US",
    "sg:address":"32122 Canton Rd",
    "sg:city":"Albemarle",
    "sg:classifiers":[
        {
            "category":"Real Estate",
            "subcategory":"Real Estate Agent",
            "type":"Services"
        }
    ],
    "sg:phone":"+1 704 986 4400",
    "sg:postcode":"28001",
    "sg:province":"NC",
    "sg:tags":[
        "appraiser"
    ],
    "wof:name":"Smith & Assoc",
    "wof:placetype":"venue"
},
  "geometry": {"coordinates":[-80.235094,35.332776],"type":"Point"}
}