{
  "type": "Feature",
  "properties": {
    "iso:country":"US",
    "sg:address":"104 Cooper Hill Rd",
    "sg:city":"Windsor",
    "sg:classifiers":[
        {
            "category":"Education",
            "subcategory":"Special Training",
            "type":"Public Place"
        }
    ],
    "sg:phone":"+1 252 794 5428",
    "sg:postcode":"27983",
    "sg:province":"NC",
    "sg:tags":[
        "reading",
        "instruction",
        "improvement"
    ],
    "wof:name":"Even Start Program",
    "wof:placetype":"venue"
},
  "geometry": {"coordinates":[-76.923466,35.98932],"type":"Point"}
}