{
  "type": "Feature",
  "properties": {
    "iso:country":"US",
    "sg:address":"5217 Gorham Dr",
    "sg:city":"Charlotte",
    "sg:classifiers":[
        {
            "category":"Professional",
            "subcategory":"Business Services",
            "type":"Services"
        }
    ],
    "sg:phone":"+1   ",
    "sg:postcode":"28226",
    "sg:province":"NC",
    "wof:name":"Dwellings",
    "wof:placetype":"venue"
},
  "geometry": {"coordinates":[-80.79293800000001,35.135825],"type":"Point"}
}