{
  "type": "Feature",
  "properties": {
    "iso:country":"US",
    "sg:address":"3707 Neil St",
    "sg:city":"Raleigh",
    "sg:classifiers":[
        {
            "category":"Manufacturing",
            "subcategory":"Signs",
            "type":"Manufacturing & Wholesale Goods"
        }
    ],
    "sg:phone":"+1 919 836 0970",
    "sg:postcode":"27607",
    "sg:province":"NC",
    "sg:tags":[
        "specialty",
        "mfg"
    ],
    "wof:name":"Eye Got It",
    "wof:placetype":"venue"
},
  "geometry": {"coordinates":[-78.68788499999999,35.793425],"type":"Point"}
}