{
  "type": "Feature",
  "properties": {
    "addr:full":"221 Jacobs St Clinton NC 28328",
    "addr:housenumber":"221",
    "addr:postcode":"28328",
    "addr:street":"Jacobs St",
    "iso:country":"US",
    "sg:address":"221 Jacobs St",
    "sg:city":"Clinton",
    "sg:classifiers":[
        {
            "category":"Organizations",
            "subcategory":"Religious Organization",
            "type":"Services"
        }
    ],
    "sg:phone":"+1 910 592 4954",
    "sg:postcode":"28328",
    "sg:province":"NC",
    "sg:tags":[
        "church"
    ],
    "wof:name":"Preparation & Prayer Holy Chr",
    "wof:placetype":"venue"
},
  "geometry": {"coordinates":[-78.31316700000001,35.004202],"type":"Point"}
}