{
  "type": "Feature",
  "properties": {
    "addr:full":"807 W King St Elizabethtown NC 28337",
    "addr:housenumber":"807",
    "addr:postcode":"28337",
    "addr:street":"W King St",
    "iso:country":"US",
    "sg:address":"807 W King St",
    "sg:city":"Elizabethtown",
    "sg:classifiers":[
        {
            "category":"Organizations",
            "subcategory":"Religious Organization",
            "type":"Services"
        }
    ],
    "sg:phone":"+1 910 862 8300",
    "sg:postcode":"28337",
    "sg:province":"NC",
    "wof:name":"Presbyteria Coastal Carolina",
    "wof:placetype":"venue"
},
  "geometry": {"coordinates":[-78.61541800000001,34.630186],"type":"Point"}
}