{
  "type": "Feature",
  "properties": {
    "iso:country":"US",
    "sg:address":"705 Herbert Dr",
    "sg:city":"Kinston",
    "sg:classifiers":[
        {
            "category":"Building & Trades",
            "subcategory":"Cleaning & Sanitation",
            "type":"Services"
        }
    ],
    "sg:phone":"+1 252 523 0439",
    "sg:postcode":"28501",
    "sg:province":"NC",
    "sg:tags":[
        "janitor"
    ],
    "wof:name":"J J's Janitorial & Carpet",
    "wof:placetype":"venue"
},
  "geometry": {"coordinates":[-77.546778,35.266801],"type":"Point"}
}