{
  "type": "Feature",
  "properties": {
    "iso:country":"US",
    "sg:address":"181 Old Mill Rd",
    "sg:city":"Fuquay Varina",
    "sg:classifiers":[
        {
            "category":"Farming",
            "subcategory":"Farm",
            "type":"Manufacturing & Wholesale Goods"
        }
    ],
    "sg:phone":"+1 919 557 2898",
    "sg:postcode":"27526",
    "sg:province":"NC",
    "wof:name":"Hector's Creek Farm",
    "wof:placetype":"venue"
},
  "geometry": {"coordinates":[-78.845454,35.529658],"type":"Point"}
}