{
  "type": "Feature",
  "properties": {
    "iso:country":"US",
    "sg:address":"1047 Bragg Blvd",
    "sg:city":"Fayetteville",
    "sg:classifiers":[
        {
            "category":"Retail",
            "subcategory":"Auto Repair",
            "type":"Services"
        }
    ],
    "sg:phone":"+1 910 864 3277",
    "sg:postcode":"28301",
    "sg:province":"NC",
    "sg:tags":[
        "repairing",
        "automobile"
    ],
    "sg:website":"www.aamco.com",
    "wof:name":"AAMCO Transmissions",
    "wof:placetype":"venue"
},
  "geometry": {"coordinates":[-78.89706,35.065021],"type":"Point"}
}