{
  "type": "Feature",
  "properties": {
    "addr:full":"2253 Liberty Church Rd Hickory NC 28601",
    "addr:housenumber":"2253",
    "addr:postcode":"28601",
    "addr:street":"Liberty Church Rd",
    "iso:country":"US",
    "sg:address":"2253 Liberty Church Rd",
    "sg:city":"Hickory",
    "sg:classifiers":[
        {
            "category":"Organizations",
            "subcategory":"Religious Organization",
            "type":"Services"
        }
    ],
    "sg:phone":"+1   ",
    "sg:postcode":"28601",
    "sg:province":"NC",
    "wof:name":"Liberty Baptist Church",
    "wof:placetype":"venue"
},
  "geometry": {"coordinates":[-81.40903400000001,35.752953],"type":"Point"}
}