{
  "type": "Feature",
  "properties": {
    "addr:full":"324 Bradsher Rd Hillsborough NC 27278",
    "addr:housenumber":"324",
    "addr:postcode":"27278",
    "addr:street":"Bradsher Rd",
    "iso:country":"US",
    "sg:address":"324 Bradsher Rd",
    "sg:city":"Hillsborough",
    "sg:classifiers":[
        {
            "category":"Professional",
            "subcategory":"Computer Services",
            "type":"Services"
        }
    ],
    "sg:phone":"+1   ",
    "sg:postcode":"27278",
    "sg:province":"NC",
    "sg:tags":[
        "related"
    ],
    "wof:name":"Rcf Enterprises Inc",
    "wof:placetype":"venue"
},
  "geometry": {"coordinates":[-79.12378099999999,36.171201],"type":"Point"}
}