{
  "type": "Feature",
  "properties": {
    "addr:full":"10107 Robert Bost Rd Midland NC 28107",
    "addr:housenumber":"10107",
    "addr:postcode":"28107",
    "addr:street":"Robert Bost Rd",
    "iso:country":"US",
    "sg:address":"10107 Robert Bost Rd",
    "sg:city":"Midland",
    "sg:classifiers":[
        {
            "category":"Building & Trades",
            "subcategory":"Construction",
            "type":"Services"
        }
    ],
    "sg:phone":"+1 704 888 5272",
    "sg:postcode":"28107",
    "sg:province":"NC",
    "sg:tags":[
        "roofing",
        "contractor"
    ],
    "wof:name":"Able Exterior Remodeling",
    "wof:placetype":"venue"
},
  "geometry": {"coordinates":[-80.52770200000001,35.276856],"type":"Point"}
}