{
  "type": "Feature",
  "properties": {
    "addr:full":"2101 Sardis Rd N Ste 103 Charlotte NC 28227",
    "addr:housenumber":"2101",
    "addr:postcode":"28227",
    "addr:street":"Sardis Rd N Ste 103",
    "iso:country":"US",
    "sg:address":"2101 Sardis Rd N Ste 103",
    "sg:city":"Charlotte",
    "sg:classifiers":[
        {
            "category":"Insurance",
            "subcategory":"Hazard Insurance",
            "type":"Services"
        },
        {
            "category":"Insurance",
            "subcategory":"Insurance Agent",
            "type":"Services"
        },
        {
            "category":"Insurance",
            "subcategory":"Life Insurance",
            "type":"Services"
        },
        {
            "category":"Insurance",
            "subcategory":"Title Insurance",
            "type":"Services"
        }
    ],
    "sg:phone":"+1 704 847 7070",
    "sg:postcode":"28227",
    "sg:province":"NC",
    "sg:tags":[
        "auto",
        "homeowner"
    ],
    "sg:website":"http://www.nationwide.com/agent/Charlotte-NORTH-CAROLINA-insurance-agent/dave-hemric/office.html",
    "wof:name":"David R Hemric - Nationwide Insurance",
    "wof:placetype":"venue"
},
  "geometry": {"coordinates":[-80.73226200000001,35.142811],"type":"Point"}
}