{
  "type": "Feature",
  "properties": {
    "addr:full":"5701 Yadkin Rd Fayetteville NC 28303",
    "addr:housenumber":"5701",
    "addr:postcode":"28303",
    "addr:street":"Yadkin Rd",
    "iso:country":"US",
    "sg:address":"5701 Yadkin Rd",
    "sg:city":"Fayetteville",
    "sg:classifiers":[
        {
            "category":"Food & Beverages",
            "subcategory":"Groceries & Convenience Stores",
            "type":"Retail Goods"
        }
    ],
    "sg:phone":"+1 910 864 5011",
    "sg:postcode":"28303",
    "sg:province":"NC",
    "sg:tags":[
        "grocer"
    ],
    "wof:name":"Winn-Dixie",
    "wof:placetype":"venue"
},
  "geometry": {"coordinates":[-78.984156,35.091657],"type":"Point"}
}