{
  "type": "Feature",
  "properties": {
    "addr:full":"2124 Fayetteville Rd Rockingham NC 28379",
    "addr:housenumber":"2124",
    "addr:postcode":"28379",
    "addr:street":"Fayetteville Rd",
    "iso:country":"US",
    "sg:address":"2124 Fayetteville Rd",
    "sg:city":"Rockingham",
    "sg:classifiers":[
        {
            "category":"Shopping",
            "subcategory":"Music",
            "type":"Retail Goods"
        }
    ],
    "sg:phone":"+1 910 997 6884",
    "sg:postcode":"28379",
    "sg:province":"NC",
    "wof:name":"Videos Unlimited",
    "wof:placetype":"venue"
},
  "geometry": {"coordinates":[-79.74311400000001,34.950699],"type":"Point"}
}