{
  "type": "Feature",
  "properties": {
    "addr:full":"20959 US Hwy 17 Hampstead NC 28443",
    "addr:housenumber":"20959",
    "addr:postcode":"28443",
    "addr:street":"Us Hwy 17",
    "iso:country":"US",
    "sg:address":"20959 US Hwy 17",
    "sg:city":"Hampstead",
    "sg:classifiers":[
        {
            "category":"Social Services",
            "type":"Services"
        }
    ],
    "sg:phone":"+1 910 270 0708",
    "sg:postcode":"28443",
    "sg:province":"NC",
    "sg:tags":[
        "senior",
        "citizen"
    ],
    "wof:name":"Topsail Senior Center",
    "wof:placetype":"venue"
},
  "geometry": {"coordinates":[-77.63229,34.433718],"type":"Point"}
}