{
  "type": "Feature",
  "properties": {
    "iso:country":"US",
    "sg:address":"106 S Elliott Rd",
    "sg:city":"Chapel Hill",
    "sg:classifiers":[
        {
            "category":"Professional",
            "subcategory":"Management & Consulting",
            "type":"Services"
        },
        {
            "category":"Government",
            "subcategory":"Office",
            "type":"Public Place"
        }
    ],
    "sg:phone":"+1 919 942 2197",
    "sg:postcode":"27514",
    "sg:province":"NC",
    "sg:tags":[
        "consultant",
        "housing",
        "program",
        "business"
    ],
    "wof:name":"Inter Church Council Housing",
    "wof:placetype":"venue"
},
  "geometry": {"coordinates":[-79.028283,35.93372],"type":"Point"}
}