{
  "type": "Feature",
  "properties": {
    "addr:full":"2218 Shirley Rd Wilmington NC 28405",
    "addr:housenumber":"2218",
    "addr:postcode":"28405",
    "addr:street":"Shirley Rd",
    "iso:country":"US",
    "sg:address":"2218 Shirley Rd",
    "sg:city":"Wilmington",
    "sg:classifiers":[
        {
            "category":"Social Services",
            "subcategory":"Child Care",
            "type":"Services"
        }
    ],
    "sg:phone":"+1 910 763 3909",
    "sg:postcode":"28405",
    "sg:province":"NC",
    "sg:tags":[
        "day"
    ],
    "wof:name":"Love Train Christian Day Care",
    "wof:placetype":"venue"
},
  "geometry": {"coordinates":[-77.920597,34.247116],"type":"Point"}
}