{
  "type": "Feature",
  "properties": {
    "addr:full":"16318 State Hwy 71 N Shannon NC 28386",
    "addr:housenumber":"16318",
    "addr:postcode":"28386",
    "addr:street":"State Hwy 71 N",
    "iso:country":"US",
    "sg:address":"16318 State Hwy 71 N",
    "sg:city":"Shannon",
    "sg:classifiers":[
        {
            "category":"Social Services",
            "type":"Services"
        }
    ],
    "sg:phone":"+1 910 843 9911",
    "sg:postcode":"28386",
    "sg:province":"NC",
    "sg:tags":[
        "community"
    ],
    "wof:name":"American Indian Mothers",
    "wof:placetype":"venue"
},
  "geometry": {"coordinates":[-79.11109,34.856496],"type":"Point"}
}