{
  "type": "Feature",
  "properties": {
    "addr:full":"706 Flat Top Mountain Rd Fairview NC 28730",
    "addr:housenumber":"706",
    "addr:postcode":"28730",
    "addr:street":"Flat Top Mountain Rd",
    "iso:country":"US",
    "sg:address":"706 Flat Top Mountain Rd",
    "sg:city":"Fairview",
    "sg:classifiers":[
        {
            "category":"Banks & Credit Unions",
            "subcategory":"Financial Services",
            "type":"Services"
        }
    ],
    "sg:phone":"+1 828 628 7988",
    "sg:postcode":"28730",
    "sg:province":"NC",
    "sg:tags":[
        "investor"
    ],
    "wof:name":"Kilby Investments LLC",
    "wof:placetype":"venue"
},
  "geometry": {"coordinates":[-82.37794100000001,35.565325],"type":"Point"}
}