{
  "type": "Feature",
  "properties": {
    "iso:country":"US",
    "sg:address":"3205 Greenbriar Dr",
    "sg:city":"Yadkinville",
    "sg:classifiers":[
        {
            "category":"Farming",
            "subcategory":"Poultry Farm",
            "type":"Manufacturing & Wholesale Goods"
        }
    ],
    "sg:phone":"+1 336 961 6794",
    "sg:postcode":"27055",
    "sg:province":"NC",
    "wof:name":"Bart Davis",
    "wof:placetype":"venue"
},
  "geometry": {"coordinates":[-80.56854,36.122415],"type":"Point"}
}