{
  "type": "Feature",
  "properties": {
    "iso:country":"US",
    "sg:address":"1960 Derita Rd",
    "sg:city":"Concord",
    "sg:classifiers":[
        {
            "category":"Freight",
            "type":"Transportation"
        }
    ],
    "sg:phone":"+1 704 788 8603",
    "sg:postcode":"28027",
    "sg:province":"NC",
    "sg:tags":[
        "forwarder"
    ],
    "wof:name":"Klx Incorporated",
    "wof:placetype":"venue"
},
  "geometry": {"coordinates":[-80.719908,35.386883],"type":"Point"}
}