{
  "type": "Feature",
  "properties": {
    "iso:country":"US",
    "sg:address":"2531 E Lyon Station Rd",
    "sg:city":"Creedmoor",
    "sg:classifiers":[
        {
            "category":"Shopping",
            "subcategory":"Discount & Variety Stores",
            "type":"Retail Goods"
        }
    ],
    "sg:phone":"+1 919 528 8560",
    "sg:postcode":"27522",
    "sg:province":"NC",
    "wof:name":"Dollar Tree",
    "wof:placetype":"venue"
},
  "geometry": {"coordinates":[-78.726974,36.128311],"type":"Point"}
}