{
  "type": "Feature",
  "properties": {
    "addr:full":"680 Rock House Rd Hot Springs NC 28743",
    "addr:housenumber":"680",
    "addr:postcode":"28743",
    "addr:street":"Rock House Rd",
    "iso:country":"US",
    "sg:address":"680 Rock House Rd",
    "sg:city":"Hot Springs",
    "sg:classifiers":[
        {
            "category":"Professional",
            "subcategory":"Art Services",
            "type":"Services"
        }
    ],
    "sg:phone":"+1   ",
    "sg:postcode":"28743",
    "sg:province":"NC",
    "sg:tags":[
        "commercial",
        "design",
        "gallery"
    ],
    "wof:name":"Dreaming Heart Art Works Inc",
    "wof:placetype":"venue"
},
  "geometry": {"coordinates":[-82.883084,35.749542],"type":"Point"}
}