{
  "type": "Feature",
  "properties": {
    "addr:full":"809 Guilford Rd Jamestown NC 27282",
    "addr:housenumber":"809",
    "addr:postcode":"27282",
    "addr:street":"Guilford Rd",
    "iso:country":"US",
    "sg:address":"809 Guilford Rd",
    "sg:city":"Jamestown",
    "sg:classifiers":[
        {
            "category":"Professional",
            "subcategory":"Business Services",
            "type":"Services"
        }
    ],
    "sg:phone":"+1   ",
    "sg:postcode":"27282",
    "sg:province":"NC",
    "wof:name":"Brewer & Assoc",
    "wof:placetype":"venue"
},
  "geometry": {"coordinates":[-79.93106400000001,36.009717],"type":"Point"}
}