{
  "type": "Feature",
  "properties": {
    "iso:country":"US",
    "sg:address":"117 W Laurel Knob Rd",
    "sg:city":"Todd",
    "sg:classifiers":[
        {
            "category":"Professional",
            "subcategory":"Lawyer & Legal Services",
            "type":"Services"
        }
    ],
    "sg:phone":"+1   ",
    "sg:postcode":"28684",
    "sg:province":"NC",
    "wof:name":"Dianne Upson Atty",
    "wof:placetype":"venue"
},
  "geometry": {"coordinates":[-81.56495,36.318976],"type":"Point"}
}