{
  "type": "Feature",
  "properties": {
    "addr:full":"7400 Tuckaseegee Rd Charlotte NC 28214",
    "addr:housenumber":"7400",
    "addr:postcode":"28214",
    "addr:street":"Tuckaseegee Rd",
    "iso:country":"US",
    "sg:address":"7400 Tuckaseegee Rd",
    "sg:city":"Charlotte",
    "sg:classifiers":[
        {
            "category":"Government",
            "subcategory":"Office",
            "type":"Public Place"
        }
    ],
    "sg:phone":"+1 704 398 8063",
    "sg:postcode":"28214",
    "sg:province":"NC",
    "sg:tags":[
        "national",
        "security"
    ],
    "wof:name":"Afjrotc",
    "wof:placetype":"venue"
},
  "geometry": {"coordinates":[-80.95272799999999,35.24633],"type":"Point"}
}