{
  "type": "Feature",
  "properties": {
    "iso:country":"US",
    "sg:address":"105 Hilliary St",
    "sg:city":"Randleman",
    "sg:classifiers":[
        {
            "category":"Government",
            "subcategory":"Fire Station",
            "type":"Public Place"
        }
    ],
    "sg:phone":"+1 336 495 7530",
    "sg:postcode":"27317",
    "sg:province":"NC",
    "sg:tags":[
        "department"
    ],
    "wof:name":"Randleman Fire Dept",
    "wof:placetype":"venue"
},
  "geometry": {"coordinates":[-79.80519700000001,35.817242],"type":"Point"}
}