{
  "type": "Feature",
  "properties": {
    "addr:full":"8542 US Hwy 17 Vanceboro NC 28586",
    "addr:housenumber":"8542",
    "addr:postcode":"28586",
    "addr:street":"Us Hwy 17",
    "iso:country":"US",
    "sg:address":"8542 US Hwy 17",
    "sg:city":"Vanceboro",
    "sg:classifiers":[
        {
            "category":"Manufacturing",
            "subcategory":"Chemicals & Compounds",
            "type":"Manufacturing & Wholesale Goods"
        }
    ],
    "sg:phone":"+1 252 244 1490",
    "sg:postcode":"28586",
    "sg:province":"NC",
    "sg:tags":[
        "fertilizer"
    ],
    "wof:name":"Royster-Clark Inc",
    "wof:placetype":"venue"
},
  "geometry": {"coordinates":[-77.140996,35.31417],"type":"Point"}
}