{
  "type": "Feature",
  "properties": {
    "iso:country":"US",
    "sg:address":"875 Calabash Rd NW",
    "sg:city":"Calabash",
    "sg:classifiers":[
        {
            "category":"Building & Trades",
            "subcategory":"Construction",
            "type":"Services"
        }
    ],
    "sg:phone":"+1 910 287 4792",
    "sg:postcode":"28467",
    "sg:province":"NC",
    "sg:tags":[
        "house"
    ],
    "wof:name":"Faulk Builders",
    "wof:placetype":"venue"
},
  "geometry": {"coordinates":[-78.60968699999999,33.924257],"type":"Point"}
}