{
  "type": "Feature",
  "properties": {
    "iso:country":"US",
    "sg:address":"128 Overhill Dr",
    "sg:city":"Mooresville",
    "sg:classifiers":[
        {
            "category":"Restaurant",
            "type":"Food & Drink"
        }
    ],
    "sg:phone":"+1 704 660 6470",
    "sg:postcode":"28117",
    "sg:province":"NC",
    "sg:tags":[
        "caterer"
    ],
    "wof:name":"Catered Occasions",
    "wof:placetype":"venue"
},
  "geometry": {"coordinates":[-80.849402,35.599404],"type":"Point"}
}