{
  "type": "Feature",
  "properties": {
    "iso:country":"US",
    "sg:address":"5115 Hollyridge Dr",
    "sg:city":"Raleigh",
    "sg:classifiers":[
        {
            "category":"Professional",
            "type":"Services"
        },
        {
            "category":"Organizations",
            "subcategory":"Religious Organization",
            "type":"Services"
        }
    ],
    "sg:phone":"+1 919 841 5806",
    "sg:postcode":"27612",
    "sg:province":"NC",
    "sg:tags":[
        "establishment"
    ],
    "wof:name":"Mentorlink International",
    "wof:placetype":"venue"
},
  "geometry": {"coordinates":[-78.70073600000001,35.854293],"type":"Point"}
}