{
  "type": "Feature",
  "properties": {
    "iso:country":"US",
    "sg:address":"901 N Queen St",
    "sg:city":"Kinston",
    "sg:classifiers":[
        {
            "category":"Government",
            "subcategory":"Office",
            "type":"Public Place"
        }
    ],
    "sg:phone":"+1 252 523 0541",
    "sg:postcode":"28501",
    "sg:province":"NC",
    "wof:name":"Rural Fund For Development",
    "wof:placetype":"venue"
},
  "geometry": {"coordinates":[-77.58089699999999,35.270453],"type":"Point"}
}