{
  "type": "Feature",
  "properties": {
    "addr:full":"561 Liberty St Durham NC 27701",
    "addr:housenumber":"561",
    "addr:postcode":"27701",
    "addr:street":"Liberty St",
    "iso:country":"US",
    "sg:address":"561 Liberty St",
    "sg:city":"Durham",
    "sg:classifiers":[
        {
            "category":"Personal",
            "subcategory":"Beauty Salon",
            "type":"Services"
        }
    ],
    "sg:phone":"+1   ",
    "sg:postcode":"27701",
    "sg:province":"NC",
    "sg:tags":[
        "shop"
    ],
    "wof:name":"Michelle Harris Hair Styler",
    "wof:placetype":"venue"
},
  "geometry": {"coordinates":[-78.893225,35.99292],"type":"Point"}
}