{
  "type": "Feature",
  "properties": {
    "addr:full":"1215 Old Lilesville Rd Wadesboro NC 28170",
    "addr:housenumber":"1215",
    "addr:postcode":"28170",
    "addr:street":"Old Lilesville Rd",
    "iso:country":"US",
    "sg:address":"1215 Old Lilesville Rd",
    "sg:city":"Wadesboro",
    "sg:classifiers":[
        {
            "category":"Organizations",
            "subcategory":"Religious Organization",
            "type":"Services"
        }
    ],
    "sg:phone":"+1   ",
    "sg:postcode":"28170",
    "sg:province":"NC",
    "wof:name":"Cathedral Baptist Church",
    "wof:placetype":"venue"
},
  "geometry": {"coordinates":[-80.054844,34.960066],"type":"Point"}
}