{
  "type": "Feature",
  "properties": {
    "iso:country":"US",
    "sg:address":"5605 Greenville Blvd NE",
    "sg:city":"Greenville",
    "sg:classifiers":[
        {
            "category":"Wholesale",
            "subcategory":"Machinery & Supplies",
            "type":"Manufacturing & Wholesale Goods"
        }
    ],
    "sg:phone":"+1 252 830 5377",
    "sg:postcode":"27834",
    "sg:province":"NC",
    "sg:tags":[
        "truck"
    ],
    "wof:name":"Yale Mrtl Handling-Dougherty",
    "wof:placetype":"venue"
},
  "geometry": {"coordinates":[-77.349915,35.655527],"type":"Point"}
}