{
  "type": "Feature",
  "properties": {
    "addr:full":"5319 McChesney Dr Charlotte NC 28269",
    "addr:housenumber":"5319",
    "addr:postcode":"28269",
    "addr:street":"Mcchesney Dr",
    "iso:country":"US",
    "sg:address":"5319 McChesney Dr",
    "sg:city":"Charlotte",
    "sg:classifiers":[
        {
            "category":"Health Services",
            "subcategory":"Clinic",
            "type":"Services"
        }
    ],
    "sg:phone":"+1   ",
    "sg:postcode":"28269",
    "sg:province":"NC",
    "wof:name":"William T Kays",
    "wof:placetype":"venue"
},
  "geometry": {"coordinates":[-80.760357,35.38243],"type":"Point"}
}