{
  "type": "Feature",
  "properties": {
    "addr:full":"8721 Glenwood Ave Raleigh NC 27617",
    "addr:housenumber":"8721",
    "addr:postcode":"27617",
    "addr:street":"Glenwood Ave",
    "iso:country":"US",
    "sg:address":"8721 Glenwood Ave",
    "sg:city":"Raleigh",
    "sg:classifiers":[
        {
            "category":"Shopping",
            "type":"Retail Goods"
        }
    ],
    "sg:phone":"+1 919 783 7447",
    "sg:postcode":"27617",
    "sg:province":"NC",
    "sg:tags":[
        "spa",
        "hot",
        "tub"
    ],
    "sg:website":"www.atlanticwhirlpools.com",
    "wof:name":"Atlantic Spas & Billiards",
    "wof:placetype":"venue"
},
  "geometry": {"coordinates":[-78.74665,35.8882],"type":"Point"}
}