{
  "type": "Feature",
  "properties": {
    "iso:country":"US",
    "sg:address":"1407 S Main St",
    "sg:city":"Laurinburg",
    "sg:classifiers":[
        {
            "category":"Building & Trades",
            "subcategory":"Construction",
            "type":"Services"
        }
    ],
    "sg:phone":"+1 910 276 8242",
    "sg:postcode":"28352",
    "sg:province":"NC",
    "sg:tags":[
        "repair",
        "automotive",
        "contractor",
        "carwash",
        "gene",
        "special"
    ],
    "wof:name":"Precision Car Care",
    "wof:placetype":"venue"
},
  "geometry": {"coordinates":[-79.470122,34.760059],"type":"Point"}
}