{
  "type": "Feature",
  "properties": {
    "addr:full":"713 Severt Cir Lenoir NC 28645",
    "addr:housenumber":"713",
    "addr:postcode":"28645",
    "addr:street":"Severt Cir",
    "iso:country":"US",
    "sg:address":"713 Severt Cir",
    "sg:city":"Lenoir",
    "sg:classifiers":[
        {
            "category":"Social Services",
            "type":"Services"
        }
    ],
    "sg:phone":"+1 828 754 3078",
    "sg:postcode":"28645",
    "sg:province":"NC",
    "sg:tags":[
        "center",
        "community"
    ],
    "wof:name":"McNairy Group Home",
    "wof:placetype":"venue"
},
  "geometry": {"coordinates":[-81.506715,35.937335],"type":"Point"}
}