{
  "type": "Feature",
  "properties": {
    "iso:country":"US",
    "sg:address":"315 Unionville Indian Trail Rd",
    "sg:city":"Indian Trail",
    "sg:classifiers":[
        {
            "category":"Building & Trades",
            "subcategory":"Construction",
            "type":"Services"
        }
    ],
    "sg:phone":"+1 704 840 4394",
    "sg:postcode":"28079",
    "sg:province":"NC",
    "sg:tags":[
        "contractor"
    ],
    "wof:name":"D&S Roofing",
    "wof:placetype":"venue"
},
  "geometry": {"coordinates":[-80.66564099999999,35.079617],"type":"Point"}
}