{
  "type": "Feature",
  "properties": {
    "iso:country":"US",
    "sg:address":"6700 Elgywood Ln",
    "sg:city":"Charlotte",
    "sg:classifiers":[
        {
            "category":"Professional",
            "type":"Services"
        }
    ],
    "sg:phone":"+1 704 509 4117",
    "sg:postcode":"28213",
    "sg:province":"NC",
    "sg:tags":[
        "establishment"
    ],
    "wof:name":"Jamika Co",
    "wof:placetype":"venue"
},
  "geometry": {"coordinates":[-80.77400799999999,35.27887],"type":"Point"}
}