{
  "type": "Feature",
  "properties": {
    "addr:full":"633 Edwards Ln Greenville NC 27834",
    "addr:housenumber":"633",
    "addr:postcode":"27834",
    "addr:street":"Edwards Ln",
    "iso:country":"US",
    "sg:address":"633 Edwards Ln",
    "sg:city":"Greenville",
    "sg:classifiers":[
        {
            "category":"Farming",
            "subcategory":"Farm",
            "type":"Manufacturing & Wholesale Goods"
        }
    ],
    "sg:phone":"+1 252 752 6300",
    "sg:postcode":"27834",
    "sg:province":"NC",
    "sg:tags":[
        "crop",
        "general"
    ],
    "wof:name":"Edwards Williams R",
    "wof:placetype":"venue"
},
  "geometry": {"coordinates":[-77.219993,35.630951],"type":"Point"}
}