{
  "type": "Feature",
  "properties": {
    "addr:full":"8410 Six Forks Rd Raleigh NC 27615",
    "addr:housenumber":"8410",
    "addr:postcode":"27615",
    "addr:street":"Six Forks Rd",
    "iso:country":"US",
    "sg:address":"8410 Six Forks Rd",
    "sg:city":"Raleigh",
    "sg:classifiers":[
        {
            "category":"Shopping",
            "subcategory":"Computers & Home Electronics",
            "type":"Retail Goods"
        }
    ],
    "sg:phone":"+1 919 847 3474",
    "sg:postcode":"27615",
    "sg:province":"NC",
    "sg:tags":[
        "software"
    ],
    "wof:name":"Extreme Software",
    "wof:placetype":"venue"
},
  "geometry": {"coordinates":[-78.649062,35.894033],"type":"Point"}
}