{
  "type": "Feature",
  "properties": {
    "addr:full":"9042 State Hwy 704 Madison NC 27025",
    "addr:housenumber":"9042",
    "addr:postcode":"27025",
    "addr:street":"State Hwy 704",
    "iso:country":"US",
    "sg:address":"9042 State Hwy 704",
    "sg:city":"Madison",
    "sg:classifiers":[
        {
            "category":"Farming",
            "subcategory":"Farm",
            "type":"Manufacturing & Wholesale Goods"
        }
    ],
    "sg:phone":"+1 336 427 6747",
    "sg:postcode":"27025",
    "sg:province":"NC",
    "wof:name":"Beaver Creek Farm Inc",
    "wof:placetype":"venue"
},
  "geometry": {"coordinates":[-80.042005,36.451231],"type":"Point"}
}