{
  "type": "Feature",
  "properties": {
    "addr:full":"3904 Bishop Rd Battleboro NC 27809",
    "addr:housenumber":"3904",
    "addr:postcode":"27809",
    "addr:street":"Bishop Rd",
    "iso:country":"US",
    "sg:address":"3904 Bishop Rd",
    "sg:city":"Battleboro",
    "sg:classifiers":[
        {
            "category":"Health Services",
            "subcategory":"Clinic",
            "type":"Services"
        }
    ],
    "sg:phone":"+1 252 451 1307",
    "sg:postcode":"27809",
    "sg:province":"NC",
    "sg:tags":[
        "home",
        "care"
    ],
    "sg:website":"www.buyscrubsonline.com",
    "wof:name":"Home Life Solutions Inc",
    "wof:placetype":"venue"
},
  "geometry": {"coordinates":[-77.769443,36.022376],"type":"Point"}
}