{
  "type": "Feature",
  "properties": {
    "addr:full":"516 Oak Grove Church Rd Winston Salem NC 27107",
    "addr:housenumber":"516",
    "addr:postcode":"27107",
    "addr:street":"Oak Grove Church Rd",
    "iso:country":"US",
    "sg:address":"516 Oak Grove Church Rd",
    "sg:city":"Winston Salem",
    "sg:classifiers":[
        {
            "category":"Building & Trades",
            "subcategory":"Construction",
            "type":"Services"
        }
    ],
    "sg:phone":"+1 336 788 2102",
    "sg:postcode":"27107",
    "sg:province":"NC",
    "sg:tags":[
        "house",
        "nonresidential",
        "general",
        "contractor"
    ],
    "wof:name":"Spirit Construction Co",
    "wof:placetype":"venue"
},
  "geometry": {"coordinates":[-80.131418,36.072742],"type":"Point"}
}