{
  "type": "Feature",
  "properties": {
    "iso:country":"US",
    "sg:address":"19511 Sunnypoint Ct",
    "sg:city":"Cornelius",
    "sg:classifiers":[
        {
            "category":"Personal",
            "type":"Services"
        }
    ],
    "sg:phone":"+1   ",
    "sg:postcode":"28031",
    "sg:province":"NC",
    "wof:name":"Core Business Solutions Inc",
    "wof:placetype":"venue"
},
  "geometry": {"coordinates":[-80.911153,35.47881],"type":"Point"}
}