{
  "type": "Feature",
  "properties": {
    "iso:country":"US",
    "sg:address":"311 Cothren St",
    "sg:city":"Wilkesboro",
    "sg:classifiers":[
        {
            "category":"Health Services",
            "subcategory":"Clinic",
            "type":"Services"
        }
    ],
    "sg:phone":"+1   ",
    "sg:postcode":"28697",
    "sg:province":"NC",
    "sg:tags":[
        "specialty",
        "outpatient"
    ],
    "wof:name":"New River-Recovery Center",
    "wof:placetype":"venue"
},
  "geometry": {"coordinates":[-81.14612099999999,36.15019],"type":"Point"}
}