{
  "type": "Feature",
  "properties": {
    "iso:country":"US",
    "sg:address":"2214 Golden Gate Dr",
    "sg:city":"Greensboro",
    "sg:classifiers":[
        {
            "category":"Shopping",
            "type":"Retail Goods"
        },
        {
            "category":"Shopping",
            "subcategory":"Clothing, Apparel, & Fashions",
            "type":"Retail Goods"
        }
    ],
    "sg:phone":"+1 336 271 8491",
    "sg:postcode":"27405",
    "sg:province":"NC",
    "sg:tags":[
        "factory",
        "family",
        "outlet"
    ],
    "wof:name":"Rolane Factory Outlet Inc",
    "wof:placetype":"venue"
},
  "geometry": {"coordinates":[-79.784064,36.103989],"type":"Point"}
}