{
  "type": "Feature",
  "properties": {
    "addr:full":"420 Industrial Park Ave Asheboro NC 27205",
    "addr:housenumber":"420",
    "addr:postcode":"27205",
    "addr:street":"Industrial Park Ave",
    "iso:country":"US",
    "sg:address":"420 Industrial Park Ave",
    "sg:city":"Asheboro",
    "sg:classifiers":[
        {
            "category":"Manufacturing",
            "subcategory":"Tools & Machinery",
            "type":"Manufacturing & Wholesale Goods"
        }
    ],
    "sg:phone":"+1 336 625 1122",
    "sg:postcode":"27205",
    "sg:province":"NC",
    "sg:tags":[
        "machine",
        "shop"
    ],
    "sg:website":"www.allenprecision-ind.com",
    "wof:name":"Allen Precision Industries Inc",
    "wof:placetype":"venue"
},
  "geometry": {"coordinates":[-79.82634,35.674114],"type":"Point"}
}