{
  "type": "Feature",
  "properties": {
    "addr:full":"341 Wooten Rd Maple Hill NC 28454",
    "addr:housenumber":"341",
    "addr:postcode":"28454",
    "addr:street":"Wooten Rd",
    "iso:country":"US",
    "sg:address":"341 Wooten Rd",
    "sg:city":"Maple Hill",
    "sg:classifiers":[
        {
            "category":"Food & Beverages",
            "subcategory":"Groceries & Convenience Stores",
            "type":"Retail Goods"
        }
    ],
    "sg:phone":"+1 910 259 6999",
    "sg:postcode":"28454",
    "sg:province":"NC",
    "wof:name":"Sharpless Grocery",
    "wof:placetype":"venue"
},
  "geometry": {"coordinates":[-77.665215,34.668122],"type":"Point"}
}