{
  "type": "Feature",
  "properties": {
    "addr:full":"627 Wedgewood Rd Whiteville NC 28472",
    "addr:housenumber":"627",
    "addr:postcode":"28472",
    "addr:street":"Wedgewood Rd",
    "iso:country":"US",
    "sg:address":"627 Wedgewood Rd",
    "sg:city":"Whiteville",
    "sg:classifiers":[
        {
            "category":"Professional",
            "subcategory":"Business Services",
            "type":"Services"
        }
    ],
    "sg:phone":"+1   ",
    "sg:postcode":"28472",
    "sg:province":"NC",
    "wof:name":"Doras Home Interiors",
    "wof:placetype":"venue"
},
  "geometry": {"coordinates":[-78.687787,34.345883],"type":"Point"}
}