{
  "type": "Feature",
  "properties": {
    "iso:country":"US",
    "sg:address":"8814 Fieldcroft Dr",
    "sg:city":"Charlotte",
    "sg:classifiers":[
        {
            "category":"Real Estate",
            "subcategory":"Real Estate Agent",
            "type":"Services"
        }
    ],
    "sg:phone":"+1 704 905 9792",
    "sg:postcode":"28277",
    "sg:province":"NC",
    "sg:tags":[
        "investment"
    ],
    "wof:name":"White Investment Properties",
    "wof:placetype":"venue"
},
  "geometry": {"coordinates":[-80.811735,35.034336],"type":"Point"}
}