{
  "type": "Feature",
  "properties": {
    "iso:country":"US",
    "sg:address":"2107 Amity Hill Rd",
    "sg:city":"Statesville",
    "sg:classifiers":[
        {
            "category":"Shopping",
            "subcategory":"Gifts & Souvenirs",
            "type":"Retail Goods"
        }
    ],
    "sg:phone":"+1 704 878 6800",
    "sg:postcode":"28677",
    "sg:province":"NC",
    "sg:tags":[
        "racing"
    ],
    "wof:name":"NAs Cards",
    "wof:placetype":"venue"
},
  "geometry": {"coordinates":[-80.883199,35.755837],"type":"Point"}
}