{
  "type": "Feature",
  "properties": {
    "addr:full":"4864 US Hwy 70 E Princeton NC 27569",
    "addr:housenumber":"4864",
    "addr:postcode":"27569",
    "addr:street":"Us Hwy 70 E",
    "iso:country":"US",
    "sg:address":"4864 US Hwy 70 E",
    "sg:city":"Princeton",
    "sg:phone":"+1 919 965 6318",
    "sg:postcode":"27569",
    "sg:province":"NC",
    "sg:tags":[
        "farm",
        "tobacco"
    ],
    "wof:name":"Billy Worley",
    "wof:placetype":"venue"
},
  "geometry": {"coordinates":[-78.22551,35.476246],"type":"Point"}
}