{
  "type": "Feature",
  "properties": {
    "iso:country":"US",
    "sg:address":"215 S Brown St",
    "sg:city":"Chadbourn",
    "sg:classifiers":[
        {
            "category":"Education",
            "subcategory":"Vocational School",
            "type":"Public Place"
        }
    ],
    "sg:phone":"+1 910 654 5300",
    "sg:postcode":"28431",
    "sg:province":"NC",
    "sg:tags":[
        "technical",
        "trade"
    ],
    "wof:name":"Fishing School Inc",
    "wof:placetype":"venue"
},
  "geometry": {"coordinates":[-78.826369,34.321277],"type":"Point"}
}