{
  "type": "Feature",
  "properties": {
    "addr:full":"1113 Walker Dr Kinston NC 28501",
    "addr:housenumber":"1113",
    "addr:postcode":"28501",
    "addr:street":"Walker Dr",
    "iso:country":"US",
    "sg:address":"1113 Walker Dr",
    "sg:city":"Kinston",
    "sg:classifiers":[
        {
            "category":"Real Estate",
            "subcategory":"Real Estate Operator",
            "type":"Services"
        }
    ],
    "sg:phone":"+1 252 527 2668",
    "sg:postcode":"28501",
    "sg:province":"NC",
    "sg:tags":[
        "property",
        "lessor"
    ],
    "wof:name":"E L Wooten Jr",
    "wof:placetype":"venue"
},
  "geometry": {"coordinates":[-77.595828,35.274191],"type":"Point"}
}