{
  "type": "Feature",
  "properties": {
    "addr:full":"6306 Tunston Ln Charlotte NC 28269",
    "addr:housenumber":"6306",
    "addr:postcode":"28269",
    "addr:street":"Tunston Ln",
    "iso:country":"US",
    "sg:address":"6306 Tunston Ln",
    "sg:city":"Charlotte",
    "sg:classifiers":[
        {
            "category":"Professional",
            "subcategory":"Management & Consulting",
            "type":"Services"
        }
    ],
    "sg:phone":"+1   ",
    "sg:postcode":"28269",
    "sg:province":"NC",
    "sg:tags":[
        "business"
    ],
    "wof:name":"Comx Consulting LLC",
    "wof:placetype":"venue"
},
  "geometry": {"coordinates":[-80.754739,35.372378],"type":"Point"}
}