{
  "type": "Feature",
  "properties": {
    "addr:full":"214 Matthews Xing Matthews NC 28105",
    "addr:housenumber":"214",
    "addr:postcode":"28105",
    "addr:street":"Matthews Xing",
    "iso:country":"US",
    "sg:address":"214 Matthews Xing",
    "sg:city":"Matthews",
    "sg:classifiers":[
        {
            "category":"Professional",
            "subcategory":"Business Services",
            "type":"Services"
        }
    ],
    "sg:phone":"+1   ",
    "sg:postcode":"28105",
    "sg:province":"NC",
    "wof:name":"Organizing Solutions",
    "wof:placetype":"venue"
},
  "geometry": {"coordinates":[-80.720303,35.110643],"type":"Point"}
}