{
  "type": "Feature",
  "properties": {
    "iso:country":"US",
    "sg:address":"2086 Richardson Bass Rd",
    "sg:city":"Kenly",
    "sg:classifiers":[
        {
            "category":"Freight",
            "type":"Transportation"
        }
    ],
    "sg:phone":"+1 919 284 6654",
    "sg:postcode":"27542",
    "sg:province":"NC",
    "sg:tags":[
        "operator",
        "local",
        "trucking"
    ],
    "wof:name":"Freddy Worley Transportation",
    "wof:placetype":"venue"
},
  "geometry": {"coordinates":[-78.12208800000001,35.562249],"type":"Point"}
}