{
  "type": "Feature",
  "properties": {
    "addr:full":"12021 State Hwy 226 Nebo NC 28761",
    "addr:housenumber":"12021",
    "addr:postcode":"28761",
    "addr:street":"State Hwy 226",
    "iso:country":"US",
    "sg:address":"12021 State Hwy 226",
    "sg:city":"Nebo",
    "sg:classifiers":[
        {
            "category":"Building & Trades",
            "subcategory":"Construction",
            "type":"Services"
        }
    ],
    "sg:phone":"+1 828 766 2694",
    "sg:postcode":"28761",
    "sg:province":"NC",
    "sg:tags":[
        "contractor"
    ],
    "wof:name":"Thomas Maggiolo & Assoc",
    "wof:placetype":"venue"
},
  "geometry": {"coordinates":[-81.863632,35.598176],"type":"Point"}
}