{
  "type": "Feature",
  "properties": {
    "iso:country":"US",
    "sg:address":"4703 Carolina Ave",
    "sg:city":"New Bern",
    "sg:classifiers":[
        {
            "category":"Education",
            "subcategory":"Vocational School",
            "type":"Public Place"
        }
    ],
    "sg:phone":"+1   ",
    "sg:postcode":"28562",
    "sg:province":"NC",
    "wof:name":"Promised Lan Computing Inc",
    "wof:placetype":"venue"
},
  "geometry": {"coordinates":[-77.09678,35.083613],"type":"Point"}
}