{
  "type": "Feature",
  "properties": {
    "addr:full":"200 Eastbrook Dr Greenville NC 27858",
    "addr:housenumber":"200",
    "addr:postcode":"27858",
    "addr:street":"Eastbrook Dr",
    "iso:country":"US",
    "sg:address":"200 Eastbrook Dr",
    "sg:city":"Greenville",
    "sg:classifiers":[
        {
            "category":"Health Services",
            "subcategory":"Clinic",
            "type":"Services"
        }
    ],
    "sg:phone":"+1   ",
    "sg:postcode":"27858",
    "sg:province":"NC",
    "sg:tags":[
        "management",
        "disability"
    ],
    "wof:name":"Crawford & Company",
    "wof:placetype":"venue"
},
  "geometry": {"coordinates":[-77.336091,35.596355],"type":"Point"}
}