{
  "type": "Feature",
  "properties": {
    "addr:full":"909 Creed Pittman Rd Spruce Pine NC 28777",
    "addr:housenumber":"909",
    "addr:postcode":"28777",
    "addr:street":"Creed Pittman Rd",
    "iso:country":"US",
    "sg:address":"909 Creed Pittman Rd",
    "sg:city":"Spruce Pine",
    "sg:classifiers":[
        {
            "category":"Government",
            "subcategory":"Office",
            "type":"Public Place"
        }
    ],
    "sg:phone":"+1 828 765 3007",
    "sg:postcode":"28777",
    "sg:province":"NC",
    "sg:tags":[
        "village"
    ],
    "wof:name":"Spruce Pine Sewer Treatment",
    "wof:placetype":"venue"
},
  "geometry": {"coordinates":[-82.079995,35.921991],"type":"Point"}
}