{
  "type": "Feature",
  "properties": {
    "addr:full":"6752 Fairview Church Rd Trinity NC 27370",
    "addr:housenumber":"6752",
    "addr:postcode":"27370",
    "addr:street":"Fairview Church Rd",
    "iso:country":"US",
    "sg:address":"6752 Fairview Church Rd",
    "sg:city":"Trinity",
    "sg:classifiers":[
        {
            "category":"Home & Garden",
            "subcategory":"Furniture",
            "type":"Retail Goods"
        }
    ],
    "sg:phone":"+1 336 861 3876",
    "sg:postcode":"27370",
    "sg:province":"NC",
    "wof:name":"Factory Direct Furniture Inc",
    "wof:placetype":"venue"
},
  "geometry": {"coordinates":[-79.965594,35.882427],"type":"Point"}
}