{
  "type": "Feature",
  "properties": {
    "addr:full":"614 Washington St Eden NC 27288",
    "addr:housenumber":"614",
    "addr:postcode":"27288",
    "addr:street":"Washington St",
    "iso:country":"US",
    "sg:address":"614 Washington St",
    "sg:city":"Eden",
    "sg:classifiers":[
        {
            "category":"Personal",
            "subcategory":"Beauty Salon",
            "type":"Services"
        }
    ],
    "sg:phone":"+1   ",
    "sg:postcode":"27288",
    "sg:province":"NC",
    "sg:tags":[
        "shop"
    ],
    "wof:name":"Jennifer & Co",
    "wof:placetype":"venue"
},
  "geometry": {"coordinates":[-79.76290899999999,36.490998],"type":"Point"}
}