{
  "type": "Feature",
  "properties": {
    "iso:country":"US",
    "sg:address":"227 Sunset Ave",
    "sg:city":"Asheboro",
    "sg:classifiers":[
        {
            "category":"Health Services",
            "subcategory":"Clinic",
            "type":"Services"
        }
    ],
    "sg:phone":"+1 336 633 3092",
    "sg:postcode":"27203",
    "sg:province":"NC",
    "sg:website":"www.getfitasheboro.com",
    "wof:name":"Asheboro Health & Fitness",
    "wof:placetype":"venue"
},
  "geometry": {"coordinates":[-79.816836,35.705723],"type":"Point"}
}