{
  "type": "Feature",
  "properties": {
    "iso:country":"US",
    "sg:address":"3006 Eaker Dr",
    "sg:city":"Cherryville",
    "sg:classifiers":[
        {
            "category":"Professional",
            "type":"Services"
        },
        {
            "category":"Wholesale",
            "subcategory":"Non-durable Goods",
            "type":"Manufacturing & Wholesale Goods"
        }
    ],
    "sg:phone":"+1 704 435 8847",
    "sg:postcode":"28021",
    "sg:province":"NC",
    "sg:tags":[
        "advertising"
    ],
    "wof:name":"Promo Comp Inc",
    "wof:placetype":"venue"
},
  "geometry": {"coordinates":[-81.402306,35.388137],"type":"Point"}
}