{
  "type": "Feature",
  "properties": {
    "addr:full":"1105 Peeler Rd Salisbury NC 28146",
    "addr:housenumber":"1105",
    "addr:postcode":"28146",
    "addr:street":"Peeler Rd",
    "iso:country":"US",
    "sg:address":"1105 Peeler Rd",
    "sg:city":"Salisbury",
    "sg:classifiers":[
        {
            "category":"Restaurant",
            "type":"Food & Drink"
        }
    ],
    "sg:phone":"+1 704 636 0025",
    "sg:postcode":"28146",
    "sg:province":"NC",
    "sg:tags":[
        "caterer"
    ],
    "wof:name":"Derrick Travel Plz & C W's",
    "wof:placetype":"venue"
},
  "geometry": {"coordinates":[-80.514574,35.607818],"type":"Point"}
}