{
  "type": "Feature",
  "properties": {
    "addr:full":"112 Hidden Pastures Dr Cramerton NC 28032",
    "addr:housenumber":"112",
    "addr:postcode":"28032",
    "addr:street":"Hidden Pastures Dr",
    "iso:country":"US",
    "sg:address":"112 Hidden Pastures Dr",
    "sg:city":"Cramerton",
    "sg:classifiers":[
        {
            "category":"Building & Trades",
            "subcategory":"Plumbing",
            "type":"Services"
        }
    ],
    "sg:phone":"+1 704 824 3005",
    "sg:postcode":"28032",
    "sg:province":"NC",
    "sg:tags":[
        "mechanical",
        "contractor"
    ],
    "wof:name":"Hvac Service Corp",
    "wof:placetype":"venue"
},
  "geometry": {"coordinates":[-81.08251799999999,35.229946],"type":"Point"}
}