{
  "type": "Feature",
  "properties": {
    "addr:full":"86 Ivanhoe Ct Waynesville NC 28785",
    "addr:housenumber":"86",
    "addr:postcode":"28785",
    "addr:street":"Ivanhoe Ct",
    "iso:country":"US",
    "sg:address":"86 Ivanhoe Ct",
    "sg:city":"Waynesville",
    "sg:classifiers":[
        {
            "category":"Building & Trades",
            "subcategory":"Electrical",
            "type":"Services"
        }
    ],
    "sg:phone":"+1 828 926 3051",
    "sg:postcode":"28785",
    "sg:province":"NC",
    "sg:tags":[
        "electrical",
        "contractor"
    ],
    "wof:name":"Eavenson Electric",
    "wof:placetype":"venue"
},
  "geometry": {"coordinates":[-82.998812,35.532941],"type":"Point"}
}