{
  "type": "Feature",
  "properties": {
    "addr:full":"1340 Patton Ave Asheville NC 28806",
    "addr:housenumber":"1340",
    "addr:postcode":"28806",
    "addr:street":"Patton Ave",
    "iso:country":"US",
    "sg:address":"1340 Patton Ave",
    "sg:city":"Asheville",
    "sg:classifiers":[
        {
            "category":"Home & Garden",
            "subcategory":"Mobile Homes",
            "type":"Retail Goods"
        }
    ],
    "sg:phone":"+1 828 694 3921",
    "sg:postcode":"28806",
    "sg:province":"NC",
    "wof:name":"Asheville Manufactured Home",
    "wof:placetype":"venue"
},
  "geometry": {"coordinates":[-82.603185,35.584706],"type":"Point"}
}