{
  "type": "Feature",
  "properties": {
    "iso:country":"US",
    "sg:address":"227 Beval Rd",
    "sg:city":"Wilmington",
    "sg:classifiers":[
        {
            "category":"Building & Trades",
            "subcategory":"Plumbing",
            "type":"Services"
        }
    ],
    "sg:phone":"+1 910 763 3031",
    "sg:postcode":"28401",
    "sg:province":"NC",
    "sg:tags":[
        "conditioning",
        "air",
        "system",
        "contractor"
    ],
    "wof:name":"Merritt Heating & Air Cond",
    "wof:placetype":"venue"
},
  "geometry": {"coordinates":[-77.97136500000001,34.286065],"type":"Point"}
}