{
  "type": "Feature",
  "properties": {
    "iso:country":"US",
    "sg:address":"8100 Arrowridge Blvd",
    "sg:city":"Charlotte",
    "sg:classifiers":[
        {
            "category":"Professional",
            "subcategory":"Advertising",
            "type":"Services"
        }
    ],
    "sg:phone":"+1 704 527 8001",
    "sg:postcode":"28273",
    "sg:province":"NC",
    "sg:tags":[
        "designer",
        "display",
        "producer"
    ],
    "wof:name":"Holt Group",
    "wof:placetype":"venue"
},
  "geometry": {"coordinates":[-80.91231399999999,35.129888],"type":"Point"}
}