{
  "type": "Feature",
  "properties": {
    "addr:full":"1 Iona Cir Asheville NC 28806",
    "addr:housenumber":"1",
    "addr:postcode":"28806",
    "addr:street":"Iona Cir",
    "iso:country":"US",
    "sg:address":"1 Iona Cir",
    "sg:city":"Asheville",
    "sg:classifiers":[
        {
            "category":"Real Estate",
            "subcategory":"Real Estate Agent",
            "type":"Services"
        }
    ],
    "sg:phone":"+1 828 285 2600",
    "sg:postcode":"28806",
    "sg:province":"NC",
    "sg:tags":[
        "manager"
    ],
    "wof:name":"Peppertree Vacation Club",
    "wof:placetype":"venue"
},
  "geometry": {"coordinates":[-82.61850099999999,35.589037],"type":"Point"}
}