{
  "type": "Feature",
  "properties": {
    "addr:full":"110 Limestone Rd Kenansville NC 28349",
    "addr:housenumber":"110",
    "addr:postcode":"28349",
    "addr:street":"Limestone Rd",
    "iso:country":"US",
    "sg:address":"110 Limestone Rd",
    "sg:city":"Kenansville",
    "sg:classifiers":[
        {
            "category":"Restaurant",
            "type":"Food & Drink"
        }
    ],
    "sg:menulink":"http://www.allmenus.com/nc/kenansville/156253-hardees/menu/",
    "sg:phone":"+1 910 296 0015",
    "sg:postcode":"28349",
    "sg:province":"NC",
    "sg:tags":[
        "burger",
        "american"
    ],
    "wof:name":"Hardee's",
    "wof:placetype":"venue"
},
  "geometry": {"coordinates":[-77.96160999999999,34.961218],"type":"Point"}
}