{
  "type": "Feature",
  "properties": {
    "addr:full":"10800 Sikes Pl Charlotte NC 28277",
    "addr:postcode":"10800;28277",
    "addr:street":"Sikes Pl",
    "iso:country":"US",
    "sg:address":"10800 Sikes Pl",
    "sg:city":"Charlotte",
    "sg:classifiers":[
        {
            "category":"Wholesale",
            "subcategory":"Machinery & Supplies",
            "type":"Manufacturing & Wholesale Goods"
        },
        {
            "category":"Manufacturing",
            "subcategory":"Tools & Machinery",
            "type":"Manufacturing & Wholesale Goods"
        }
    ],
    "sg:phone":"+1 704 321 9884",
    "sg:postcode":"28277",
    "sg:province":"NC",
    "sg:tags":[
        "equipment",
        "industrial",
        "system",
        "vacuum"
    ],
    "wof:name":"Busch Inc",
    "wof:placetype":"venue"
},
  "geometry": {"coordinates":[-80.768519,35.063134],"type":"Point"}
}