{
  "type": "Feature",
  "properties": {
    "addr:full":"217 Teresa Dr Rolesville NC 27571",
    "addr:housenumber":"217",
    "addr:postcode":"27571",
    "addr:street":"Teresa Dr",
    "iso:country":"US",
    "sg:address":"217 Teresa Dr",
    "sg:city":"Rolesville",
    "sg:classifiers":[
        {
            "category":"Professional",
            "subcategory":"Secretarial Services",
            "type":"Services"
        }
    ],
    "sg:phone":"+1   ",
    "sg:postcode":"27571",
    "sg:province":"NC",
    "sg:tags":[
        "reporting"
    ],
    "wof:name":"Gray Court Reporting",
    "wof:placetype":"venue"
},
  "geometry": {"coordinates":[-78.46032700000001,35.93733],"type":"Point"}
}