{
  "type": "Feature",
  "properties": {
    "iso:country":"US",
    "sg:address":"125 Avery St",
    "sg:city":"Garner",
    "sg:classifiers":[
        {
            "category":"Recreation",
            "type":"Entertainment"
        }
    ],
    "sg:phone":"+1 919 662 5051",
    "sg:postcode":"27529",
    "sg:province":"NC",
    "sg:tags":[
        "parks"
    ],
    "wof:name":"Avery Street Recreation Dept",
    "wof:placetype":"venue"
},
  "geometry": {"coordinates":[-78.61063900000001,35.712737],"type":"Point"}
}