{
  "type": "Feature",
  "properties": {
    "iso:country":"US",
    "sg:address":"810 Summit Rd",
    "sg:city":"Goldsboro",
    "sg:classifiers":[
        {
            "category":"Professional",
            "subcategory":"Computer Services",
            "type":"Services"
        }
    ],
    "sg:phone":"+1   ",
    "sg:postcode":"27534",
    "sg:province":"NC",
    "sg:tags":[
        "datum"
    ],
    "wof:name":"Freelance Media Group",
    "wof:placetype":"venue"
},
  "geometry": {"coordinates":[-77.936599,35.376514],"type":"Point"}
}