{
  "type": "Feature",
  "properties": {
    "addr:full":"9020 Albemarle Rd Charlotte NC 28227",
    "addr:housenumber":"9020",
    "addr:postcode":"28227",
    "addr:street":"Albemarle Rd",
    "iso:country":"US",
    "sg:address":"9020 Albemarle Rd",
    "sg:city":"Charlotte",
    "sg:classifiers":[
        {
            "category":"Shopping",
            "subcategory":"Optical Goods",
            "type":"Retail Goods"
        }
    ],
    "sg:phone":"+1 704 532 6303",
    "sg:postcode":"28227",
    "sg:province":"NC",
    "wof:name":"Factory Eyeglass",
    "wof:placetype":"venue"
},
  "geometry": {"coordinates":[-80.695628,35.211086],"type":"Point"}
}