{
  "type": "Feature",
  "properties": {
    "addr:full":"101 Cantiberry Dr Salisbury NC 28146",
    "addr:housenumber":"101",
    "addr:postcode":"28146",
    "addr:street":"Cantiberry Dr",
    "iso:country":"US",
    "sg:address":"101 Cantiberry Dr",
    "sg:city":"Salisbury",
    "sg:classifiers":[
        {
            "category":"Travel",
            "subcategory":"Hotels & Motels",
            "type":"Entertainment"
        }
    ],
    "sg:phone":"+1 704 637 2333",
    "sg:postcode":"28146",
    "sg:province":"NC",
    "sg:tags":[
        "membership",
        "lodging"
    ],
    "wof:name":"Alpha Delta Kappa Sorority",
    "wof:placetype":"venue"
},
  "geometry": {"coordinates":[-80.426118,35.605588],"type":"Point"}
}