{
  "type": "Feature",
  "properties": {
    "addr:full":"615 E Contentnea Dr Grifton NC 28530",
    "addr:housenumber":"615",
    "addr:postcode":"28530",
    "addr:street":"E Contentnea Dr",
    "iso:country":"US",
    "sg:address":"615 E Contentnea Dr",
    "sg:city":"Grifton",
    "sg:classifiers":[
        {
            "category":"Organizations",
            "subcategory":"Religious Organization",
            "type":"Services"
        }
    ],
    "sg:phone":"+1 252 524 4210",
    "sg:postcode":"28530",
    "sg:province":"NC",
    "sg:tags":[
        "church"
    ],
    "wof:name":"Grifton Chapel Freewill Baptis",
    "wof:placetype":"venue"
},
  "geometry": {"coordinates":[-77.446367,35.369017],"type":"Point"}
}