{
  "type": "Feature",
  "properties": {
    "addr:full":"25525 State Hwy 561 Enfield NC 27823",
    "addr:housenumber":"25525",
    "addr:postcode":"27823",
    "addr:street":"State Hwy 561",
    "iso:country":"US",
    "sg:address":"25525 State Hwy 561",
    "sg:city":"Enfield",
    "sg:classifiers":[
        {
            "category":"Organizations",
            "subcategory":"Religious Organization",
            "type":"Services"
        }
    ],
    "sg:phone":"+1   ",
    "sg:postcode":"27823",
    "sg:province":"NC",
    "wof:name":"Missionary Baptist Church",
    "wof:placetype":"venue"
},
  "geometry": {"coordinates":[-77.744739,36.266829],"type":"Point"}
}