{
  "type": "Feature",
  "properties": {
    "addr:full":"206 Laver Dr Cary NC 27511",
    "addr:housenumber":"206",
    "addr:postcode":"27511",
    "addr:street":"Laver Dr",
    "iso:country":"US",
    "sg:address":"206 Laver Dr",
    "sg:city":"Cary",
    "sg:classifiers":[
        {
            "category":"Real Estate",
            "subcategory":"Real Estate Agent",
            "type":"Services"
        }
    ],
    "sg:phone":"+1 919 481 9992",
    "sg:postcode":"27511",
    "sg:province":"NC",
    "wof:name":"Etta Adams",
    "wof:placetype":"venue"
},
  "geometry": {"coordinates":[-78.78103299999999,35.749331],"type":"Point"}
}