{
  "type": "Feature",
  "properties": {
    "addr:full":"377 Bethel Church Rd Lincolnton NC 28092",
    "addr:housenumber":"377",
    "addr:postcode":"28092",
    "addr:street":"Bethel Church Rd",
    "iso:country":"US",
    "sg:address":"377 Bethel Church Rd",
    "sg:city":"Lincolnton",
    "sg:classifiers":[
        {
            "category":"Building & Trades",
            "subcategory":"Construction",
            "type":"Services"
        }
    ],
    "sg:phone":"+1 704 732 8984",
    "sg:postcode":"28092",
    "sg:province":"NC",
    "sg:tags":[
        "contractor",
        "laying",
        "floor",
        "covering"
    ],
    "wof:name":"Bridges Floor Sanding",
    "wof:placetype":"venue"
},
  "geometry": {"coordinates":[-81.239636,35.50483],"type":"Point"}
}