{
  "type": "Feature",
  "properties": {
    "iso:country":"US",
    "sg:address":"2025 N Marine Blvd",
    "sg:city":"Jacksonville",
    "sg:classifiers":[
        {
            "category":"Professional",
            "subcategory":"Accounting & Tax Preparation",
            "type":"Services"
        }
    ],
    "sg:phone":"+1 910 455 2762",
    "sg:postcode":"28546",
    "sg:province":"NC",
    "sg:tags":[
        "return",
        "filing"
    ],
    "wof:name":"Jackson Hewitt Tax Svc",
    "wof:placetype":"venue"
},
  "geometry": {"coordinates":[-77.39114499999999,34.778569],"type":"Point"}
}