{
  "type": "Feature",
  "properties": {
    "iso:country":"US",
    "sg:address":"23 Glendale Dr",
    "sg:city":"Pittsboro",
    "sg:classifiers":[
        {
            "category":"Building & Trades",
            "subcategory":"Construction",
            "type":"Services"
        }
    ],
    "sg:phone":"+1 919 942 3315",
    "sg:postcode":"27312",
    "sg:province":"NC",
    "sg:tags":[
        "hanging",
        "contractor"
    ],
    "wof:name":"Coulon Painting Greg",
    "wof:placetype":"venue"
},
  "geometry": {"coordinates":[-79.101983,35.805262],"type":"Point"}
}