{
  "type": "Feature",
  "properties": {
    "addr:full":"3806 Henderson Dr Jacksonville NC 28546",
    "addr:housenumber":"3806",
    "addr:postcode":"28546",
    "addr:street":"Henderson Dr",
    "iso:country":"US",
    "sg:address":"3806 Henderson Dr",
    "sg:city":"Jacksonville",
    "sg:classifiers":[
        {
            "category":"Personal",
            "subcategory":"Massage",
            "type":"Services"
        },
        {
            "category":"Personal",
            "subcategory":"Beauty Salon",
            "type":"Services"
        },
        {
            "category":"Personal",
            "subcategory":"Hair Removal",
            "type":"Services"
        },
        {
            "category":"Personal",
            "subcategory":"Day Spa",
            "type":"Services"
        },
        {
            "category":"Personal",
            "subcategory":"Nail Salon",
            "type":"Services"
        }
    ],
    "sg:phone":"+1 910 346 9899",
    "sg:postcode":"28546",
    "sg:province":"NC",
    "sg:tags":[
        "therapist"
    ],
    "sg:website":"http://www.deluxedayspaonline.com",
    "wof:name":"Deluxe Day Spa Llc",
    "wof:placetype":"venue"
},
  "geometry": {"coordinates":[-77.415024,34.793753],"type":"Point"}
}