{
  "type": "Feature",
  "properties": {
    "addr:full":"6405 Westgate Rd Raleigh NC 27617",
    "addr:housenumber":"6405",
    "addr:postcode":"27617",
    "addr:street":"Westgate Rd",
    "iso:country":"US",
    "sg:address":"6405 Westgate Rd",
    "sg:city":"Raleigh",
    "sg:classifiers":[
        {
            "category":"Home & Garden",
            "subcategory":"Household Appliances",
            "type":"Retail Goods"
        }
    ],
    "sg:phone":"+1 919 787 8020",
    "sg:postcode":"27617",
    "sg:province":"NC",
    "sg:tags":[
        "schooling-supplies"
    ],
    "wof:name":"Secure Watch",
    "wof:placetype":"venue"
},
  "geometry": {"coordinates":[-78.76107399999999,35.9022],"type":"Point"}
}