{
  "type": "Feature",
  "properties": {
    "iso:country":"US",
    "sg:address":"1016 Mary Chapel Rd",
    "sg:city":"Halifax",
    "sg:classifiers":[
        {
            "category":"Cinema",
            "subcategory":"Movie Rental",
            "type":"Entertainment"
        }
    ],
    "sg:phone":"+1   ",
    "sg:postcode":"27839",
    "sg:province":"NC",
    "sg:tags":[
        "video",
        "tape"
    ],
    "wof:name":"Turnage Video Service",
    "wof:placetype":"venue"
},
  "geometry": {"coordinates":[-77.49124399999999,36.227993],"type":"Point"}
}