{
  "type": "Feature",
  "properties": {
    "addr:full":"1610 Westchester Dr High Point NC 27262",
    "addr:housenumber":"1610",
    "addr:postcode":"27262",
    "addr:street":"Westchester Dr",
    "iso:country":"US",
    "sg:address":"1610 Westchester Dr",
    "sg:city":"High Point",
    "sg:classifiers":[
        {
            "category":"Professional",
            "subcategory":"Management & Consulting",
            "type":"Services"
        }
    ],
    "sg:phone":"+1   ",
    "sg:postcode":"27262",
    "sg:province":"NC",
    "wof:name":"Assured Financial Planning",
    "wof:placetype":"venue"
},
  "geometry": {"coordinates":[-80.03345299999999,35.952193],"type":"Point"}
}