{
  "type": "Feature",
  "properties": {
    "iso:country":"US",
    "sg:address":"243 Wicker St",
    "sg:city":"Sanford",
    "sg:classifiers":[
        {
            "category":"Shopping",
            "subcategory":"Shoes",
            "type":"Retail Goods"
        }
    ],
    "sg:phone":"+1 919 775 1204",
    "sg:postcode":"27330",
    "sg:province":"NC",
    "wof:name":"Heels & Soles Shoes",
    "wof:placetype":"venue"
},
  "geometry": {"coordinates":[-79.178556,35.47909],"type":"Point"}
}