{
  "type": "Feature",
  "properties": {
    "iso:country":"US",
    "sg:address":"1920 Front St",
    "sg:city":"Durham",
    "sg:classifiers":[
        {
            "category":"Health Services",
            "subcategory":"Doctor",
            "type":"Services"
        }
    ],
    "sg:phone":"+1 919 383 6696",
    "sg:postcode":"27705",
    "sg:province":"NC",
    "sg:tags":[
        "physician",
        "surgeon",
        "medical"
    ],
    "wof:name":"Garrett S Bressler MD",
    "wof:placetype":"venue"
},
  "geometry": {"coordinates":[-78.937408,36.030312],"type":"Point"}
}