{
  "type": "Feature",
  "properties": {
    "addr:full":"4033 Max Dr Winston Salem NC 27106",
    "addr:housenumber":"4033",
    "addr:postcode":"27106",
    "addr:street":"Max Dr",
    "iso:country":"US",
    "sg:address":"4033 Max Dr",
    "sg:city":"Winston Salem",
    "sg:classifiers":[
        {
            "category":"Professional",
            "subcategory":"Business Services",
            "type":"Services"
        }
    ],
    "sg:phone":"+1   ",
    "sg:postcode":"27106",
    "sg:province":"NC",
    "wof:name":"Crastenado Ltd Partnership",
    "wof:placetype":"venue"
},
  "geometry": {"coordinates":[-80.379395,36.139856],"type":"Point"}
}