{
  "type": "Feature",
  "properties": {
    "iso:country":"US",
    "sg:address":"525 N Polk St",
    "sg:city":"Pineville",
    "sg:classifiers":[
        {
            "category":"Organizations",
            "subcategory":"Religious Organization",
            "type":"Services"
        }
    ],
    "sg:phone":"+1   ",
    "sg:postcode":"28134",
    "sg:province":"NC",
    "wof:name":"Interntl Minuet Press",
    "wof:placetype":"venue"
},
  "geometry": {"coordinates":[-80.88546100000001,35.090986],"type":"Point"}
}