{
  "type": "Feature",
  "properties": {
    "iso:country":"US",
    "sg:address":"2210 Pace Rd",
    "sg:city":"Hendersonville",
    "sg:classifiers":[
        {
            "category":"Home & Garden",
            "subcategory":"Garden Supply",
            "type":"Retail Goods"
        }
    ],
    "sg:phone":"+1 828 272 6193",
    "sg:postcode":"28792",
    "sg:province":"NC",
    "sg:tags":[
        "center"
    ],
    "wof:name":"Potting Shed",
    "wof:placetype":"venue"
},
  "geometry": {"coordinates":[-82.371675,35.368273],"type":"Point"}
}