{
  "type": "Feature",
  "properties": {
    "iso:country":"US",
    "sg:address":"1114 S Main St",
    "sg:city":"Randleman",
    "sg:classifiers":[
        {
            "category":"Food & Beverages",
            "subcategory":"Groceries & Convenience Stores",
            "type":"Retail Goods"
        }
    ],
    "sg:phone":"+1 336 498 7251",
    "sg:postcode":"27317",
    "sg:province":"NC",
    "wof:name":"Quick 'n Easy Food Store",
    "wof:placetype":"venue"
},
  "geometry": {"coordinates":[-79.81310499999999,35.79692],"type":"Point"}
}