{
  "type": "Feature",
  "properties": {
    "iso:country":"US",
    "sg:address":"3644 Reynolda Rd",
    "sg:city":"Winston Salem",
    "sg:classifiers":[
        {
            "category":"Restaurant",
            "type":"Food & Drink"
        }
    ],
    "sg:menulink":"http://www.allmenus.com/nc/winston/205279-taco-bell/menu/",
    "sg:phone":"+1 336 922 6166",
    "sg:postcode":"27106",
    "sg:province":"NC",
    "sg:tags":[
        "american",
        "mexican"
    ],
    "wof:name":"Taco Bell",
    "wof:placetype":"venue"
},
  "geometry": {"coordinates":[-80.316442,36.156151],"type":"Point"}
}