{
  "type": "Feature",
  "properties": {
    "addr:full":"6121 Code's Ridge Rd Raleigh NC 27612",
    "addr:housenumber":"6121",
    "addr:postcode":"27612",
    "addr:street":"Code'S Ridge Rd",
    "iso:country":"US",
    "sg:address":"6121 Code's Ridge Rd",
    "sg:city":"Raleigh",
    "sg:classifiers":[
        {
            "category":"Professional",
            "subcategory":"Art Services",
            "type":"Services"
        }
    ],
    "sg:phone":"+1 919 789 0030",
    "sg:postcode":"27612",
    "sg:province":"NC",
    "sg:tags":[
        "photographer"
    ],
    "wof:name":"Genes Child Creative Photo",
    "wof:placetype":"venue"
},
  "geometry": {"coordinates":[-78.715762,35.861596],"type":"Point"}
}