{
  "type": "Feature",
  "properties": {
    "iso:country":"US",
    "sg:address":"300 Lighthouse Rd",
    "sg:city":"Ocracoke",
    "sg:classifiers":[
        {
            "category":"Restaurant",
            "type":"Food & Drink"
        }
    ],
    "sg:phone":"+1 252 928 3354",
    "sg:postcode":"27960",
    "sg:province":"NC",
    "wof:name":"Cat Ridge Deli",
    "wof:placetype":"venue"
},
  "geometry": {"coordinates":[-75.986231,35.107608],"type":"Point"}
}