{
  "type": "Feature",
  "properties": {
    "iso:country":"US",
    "sg:address":"6400 Bragg Blvd",
    "sg:city":"Fayetteville",
    "sg:classifiers":[
        {
            "category":"Professional",
            "subcategory":"Business Services",
            "type":"Services"
        }
    ],
    "sg:phone":"+1   ",
    "sg:postcode":"28303",
    "sg:province":"NC",
    "sg:tags":[
        "personal",
        "bureau",
        "broker",
        "agent"
    ],
    "wof:name":"Tint Pros",
    "wof:placetype":"venue"
},
  "geometry": {"coordinates":[-78.96096799999999,35.111794],"type":"Point"}
}