{
  "type": "Feature",
  "properties": {
    "addr:full":"5940 Old Smithfield Rd Apex NC 27539",
    "addr:housenumber":"5940",
    "addr:postcode":"27539",
    "addr:street":"Old Smithfield Rd",
    "iso:country":"US",
    "sg:address":"5940 Old Smithfield Rd",
    "sg:city":"Apex",
    "sg:classifiers":[
        {
            "category":"Utilities",
            "subcategory":"Refuse",
            "type":"Services"
        }
    ],
    "sg:phone":"+1 919 367 2895",
    "sg:postcode":"27539",
    "sg:province":"NC",
    "sg:tags":[
        "landfill",
        "system"
    ],
    "wof:name":"Highway 55 C & D Landfill",
    "wof:placetype":"venue"
},
  "geometry": {"coordinates":[-78.840585,35.684527],"type":"Point"}
}