{
  "type": "Feature",
  "properties": {
    "iso:country":"US",
    "sg:address":"320 Zion Church Rd",
    "sg:city":"Rockingham",
    "sg:classifiers":[
        {
            "category":"Retail",
            "subcategory":"Auto Repair",
            "type":"Services"
        }
    ],
    "sg:phone":"+1 910 997 2732",
    "sg:postcode":"28379",
    "sg:province":"NC",
    "sg:tags":[
        "repairing",
        "automobile",
        "general"
    ],
    "wof:name":"Nichols Performance Center",
    "wof:placetype":"venue"
},
  "geometry": {"coordinates":[-79.83590599999999,34.940253],"type":"Point"}
}