{
  "type": "Feature",
  "properties": {
    "addr:full":"1148 State Rd 343 Shiloh NC 27974",
    "addr:housenumber":"1148;343",
    "addr:postcode":"27974",
    "addr:street":"State Rd",
    "iso:country":"US",
    "sg:address":"1148 State Rd 343",
    "sg:city":"Shiloh",
    "sg:classifiers":[
        {
            "category":"Freight",
            "type":"Transportation"
        }
    ],
    "sg:phone":"+1 252 336 4197",
    "sg:postcode":"27974",
    "sg:province":"NC",
    "wof:name":"Planet Transport Inc",
    "wof:placetype":"venue"
},
  "geometry": {"coordinates":[-76.050038,36.268279],"type":"Point"}
}