{
  "type": "Feature",
  "properties": {
    "addr:full":"157 Charlotte Ave Sanford NC 27330",
    "addr:housenumber":"157",
    "addr:postcode":"27330",
    "addr:street":"Charlotte Ave",
    "iso:country":"US",
    "sg:address":"157 Charlotte Ave",
    "sg:city":"Sanford",
    "sg:classifiers":[
        {
            "category":"Manufacturing",
            "subcategory":"Metals",
            "type":"Manufacturing & Wholesale Goods"
        }
    ],
    "sg:phone":"+1 919 776 5118",
    "sg:postcode":"27330",
    "sg:province":"NC",
    "sg:tags":[
        "fabricator",
        "sheet"
    ],
    "wof:name":"King Heating & Air Cond",
    "wof:placetype":"venue"
},
  "geometry": {"coordinates":[-79.175135,35.48224],"type":"Point"}
}