{
  "type": "Feature",
  "properties": {
    "iso:country":"US",
    "sg:address":"8237 State Hwy 210 S",
    "sg:city":"Autryville",
    "sg:classifiers":[
        {
            "category":"Organizations",
            "subcategory":"Religious Organization",
            "type":"Services"
        }
    ],
    "sg:phone":"+1 910 531 4173",
    "sg:postcode":"28323",
    "sg:province":"NC",
    "sg:tags":[
        "church"
    ],
    "wof:name":"Holy Temple Church",
    "wof:placetype":"venue"
},
  "geometry": {"coordinates":[-78.89371,35.299786],"type":"Point"}
}