{
  "type": "Feature",
  "properties": {
    "addr:full":"4519 Bull Run Creek Rd Franklinville NC 27248",
    "addr:housenumber":"4519",
    "addr:postcode":"27248",
    "addr:street":"Bull Run Creek Rd",
    "iso:country":"US",
    "sg:address":"4519 Bull Run Creek Rd",
    "sg:city":"Franklinville",
    "sg:classifiers":[
        {
            "category":"Building & Trades",
            "subcategory":"Electrical",
            "type":"Services"
        }
    ],
    "sg:phone":"+1 336 498 2735",
    "sg:postcode":"27248",
    "sg:province":"NC",
    "sg:tags":[
        "electrical",
        "contractor"
    ],
    "wof:name":"Pugh Electric",
    "wof:placetype":"venue"
},
  "geometry": {"coordinates":[-79.763345,35.832627],"type":"Point"}
}