{
  "type": "Feature",
  "properties": {
    "iso:country":"US",
    "sg:address":"434 Kevin Way",
    "sg:city":"Cary",
    "sg:classifiers":[
        {
            "category":"Professional",
            "subcategory":"Computer Services",
            "type":"Services"
        }
    ],
    "sg:phone":"+1   ",
    "sg:postcode":"27511",
    "sg:province":"NC",
    "sg:tags":[
        "programing",
        "custom"
    ],
    "wof:name":"Netsmith",
    "wof:placetype":"venue"
},
  "geometry": {"coordinates":[-78.800337,35.752253],"type":"Point"}
}