{
  "type": "Feature",
  "properties": {
    "iso:country":"US",
    "sg:address":"421 E Cornelius Harnett Blvd",
    "sg:city":"Lillington",
    "sg:classifiers":[
        {
            "category":"Shopping",
            "subcategory":"Used Merchandise",
            "type":"Retail Goods"
        }
    ],
    "sg:phone":"+1 910 893 5008",
    "sg:postcode":"27546",
    "sg:province":"NC",
    "sg:tags":[
        "furniture"
    ],
    "wof:name":"Used Furniture Shop",
    "wof:placetype":"venue"
},
  "geometry": {"coordinates":[-78.797437,35.414982],"type":"Point"}
}