{
  "type": "Feature",
  "properties": {
    "addr:full":"1501 Asheville Hwy Brevard SC 28712",
    "addr:housenumber":"1501",
    "addr:postcode":"28712",
    "addr:street":"Asheville Hwy",
    "iso:country":"US",
    "sg:address":"1501 Asheville Hwy",
    "sg:city":"Brevard",
    "sg:classifiers":[
        {
            "category":"Building & Trades",
            "subcategory":"Construction",
            "type":"Services"
        }
    ],
    "sg:phone":"+1 828 966 9584",
    "sg:postcode":"28712",
    "sg:province":"SC",
    "sg:tags":[
        "contractor"
    ],
    "wof:name":"Michael J Rogers Masonry",
    "wof:placetype":"venue"
},
  "geometry": {"coordinates":[-82.709289,35.269522],"type":"Point"}
}