{
  "type": "Feature",
  "properties": {
    "addr:full":"1475 Patton Avenue Asheville NC 28806",
    "addr:housenumber":"1475",
    "addr:postcode":"28806",
    "addr:street":"Patton Avenue",
    "iso:country":"US",
    "sg:address":"1475 Patton Avenue",
    "sg:city":"Asheville",
    "sg:classifiers":[
        {
            "category":"Restaurant",
            "type":"Food & Drink"
        }
    ],
    "sg:phone":"+1 828 255 0000",
    "sg:postcode":"28806",
    "sg:province":"NC",
    "sg:tags":[
        "pizza"
    ],
    "sg:website":"www.papajohns.com",
    "wof:name":"Papa John's Pizza",
    "wof:placetype":"venue"
},
  "geometry": {"coordinates":[-82.609933,35.577866],"type":"Point"}
}