{
  "type": "Feature",
  "properties": {
    "iso:country":"US",
    "sg:address":"2076 Welcome-Bethesda Rd",
    "sg:city":"Lexington",
    "sg:classifiers":[
        {
            "category":"Utilities",
            "subcategory":"Refuse",
            "type":"Services"
        }
    ],
    "sg:phone":"+1 336 475 0657",
    "sg:postcode":"27295",
    "sg:province":"NC",
    "sg:tags":[
        "garbage",
        "collection"
    ],
    "wof:name":"North Davidson Garbage Corp",
    "wof:placetype":"venue"
},
  "geometry": {"coordinates":[-80.22366700000001,35.903363],"type":"Point"}
}