{
  "type": "Feature",
  "properties": {
    "iso:country":"US",
    "sg:address":"3705 Airport Cir",
    "sg:city":"Wilson",
    "sg:classifiers":[
        {
            "category":"Building & Trades",
            "subcategory":"Pest Control",
            "type":"Services"
        }
    ],
    "sg:phone":"+1 252 237 3813",
    "sg:postcode":"27896",
    "sg:province":"NC",
    "wof:name":"Terminix International Co",
    "wof:placetype":"venue"
},
  "geometry": {"coordinates":[-77.956934,35.758798],"type":"Point"}
}