{
  "type": "Feature",
  "properties": {
    "addr:full":"4300 Triple Crown Dr SW Concord NC 28027",
    "addr:housenumber":"4300",
    "addr:postcode":"28027",
    "addr:street":"Triple Crown Dr Sw",
    "iso:country":"US",
    "sg:address":"4300 Triple Crown Dr SW",
    "sg:city":"Concord",
    "sg:classifiers":[
        {
            "category":"Autos & Motor Vehicles",
            "subcategory":"Auto Supplies",
            "type":"Retail Goods"
        }
    ],
    "sg:phone":"+1 704 786 7223",
    "sg:postcode":"28027",
    "sg:province":"NC",
    "sg:tags":[
        "equipment",
        "racing",
        "car",
        "automobile"
    ],
    "wof:name":"Harris Racing Inc",
    "wof:placetype":"venue"
},
  "geometry": {"coordinates":[-80.62188399999999,35.352863],"type":"Point"}
}