{
  "type": "Feature",
  "properties": {
    "addr:full":"820 Varsity Dr Fayetteville NC 28301",
    "addr:housenumber":"820",
    "addr:postcode":"28301",
    "addr:street":"Varsity Dr",
    "iso:country":"US",
    "sg:address":"820 Varsity Dr",
    "sg:city":"Fayetteville",
    "sg:classifiers":[
        {
            "category":"Professional",
            "type":"Services"
        }
    ],
    "sg:phone":"+1 910 480 0287",
    "sg:postcode":"28301",
    "sg:province":"NC",
    "sg:tags":[
        "establishment"
    ],
    "wof:name":"Miguel M Anderson & Assoc",
    "wof:placetype":"venue"
},
  "geometry": {"coordinates":[-78.90172200000001,35.090363],"type":"Point"}
}