{
  "type": "Feature",
  "properties": {
    "addr:full":"104 Currituck Commercial Dr Moyock NC 27958",
    "addr:housenumber":"104",
    "addr:postcode":"27958",
    "addr:street":"Currituck Commercial Dr",
    "iso:country":"US",
    "sg:address":"104 Currituck Commercial Dr",
    "sg:city":"Moyock",
    "sg:classifiers":[
        {
            "category":"Shopping",
            "subcategory":"Discount & Variety Stores",
            "type":"Retail Goods"
        }
    ],
    "sg:phone":"+1 252 232 0753",
    "sg:postcode":"27958",
    "sg:province":"NC",
    "wof:name":"Dollar General",
    "wof:placetype":"venue"
},
  "geometry": {"coordinates":[-76.16886,36.515327],"type":"Point"}
}