{
  "type": "Feature",
  "properties": {
    "iso:country":"US",
    "sg:address":"682 Cary Towne Blvd",
    "sg:city":"Cary",
    "sg:classifiers":[
        {
            "category":"Deli",
            "type":"Food & Drink"
        }
    ],
    "sg:phone":"+1 919 465 7340",
    "sg:postcode":"27511",
    "sg:province":"NC",
    "wof:name":"Yankee Doodle Deli",
    "wof:placetype":"venue"
},
  "geometry": {"coordinates":[-78.76633699999999,35.775514],"type":"Point"}
}