{
  "type": "Feature",
  "properties": {
    "iso:country":"US",
    "sg:address":"440 S Church St Ste 800",
    "sg:city":"Charlotte",
    "sg:classifiers":[
        {
            "category":"Real Estate",
            "subcategory":"Real Estate Services",
            "type":"Services"
        }
    ],
    "sg:phone":"+1 704 372 8822",
    "sg:postcode":"28202",
    "sg:province":"NC",
    "sg:tags":[
        "consultant",
        "commercial"
    ],
    "wof:name":"Trinity Partners",
    "wof:placetype":"venue"
},
  "geometry": {"coordinates":[-80.848637,35.225031],"type":"Point"}
}