{
  "type": "Feature",
  "properties": {
    "addr:full":"111 E 3rd St Greenville NC 27858",
    "addr:housenumber":"111",
    "addr:postcode":"27858",
    "addr:street":"E 3Rd St",
    "iso:country":"US",
    "sg:address":"111 E 3rd St",
    "sg:city":"Greenville",
    "sg:classifiers":[
        {
            "category":"Professional",
            "subcategory":"Lawyer & Legal Services",
            "type":"Services"
        }
    ],
    "sg:phone":"+1 252 758 2111",
    "sg:postcode":"27858",
    "sg:province":"NC",
    "sg:tags":[
        "attorney"
    ],
    "wof:name":"William I Wooten Jr",
    "wof:placetype":"venue"
},
  "geometry": {"coordinates":[-77.372407,35.613256],"type":"Point"}
}