{
  "type": "Feature",
  "properties": {
    "iso:country":"US",
    "sg:address":"1401 Tripp Rd",
    "sg:city":"Chapel Hill",
    "sg:classifiers":[
        {
            "category":"Building & Trades",
            "subcategory":"Construction",
            "type":"Services"
        }
    ],
    "sg:phone":"+1 919 929 9193",
    "sg:postcode":"27516",
    "sg:province":"NC",
    "sg:tags":[
        "excavating",
        "contractor"
    ],
    "wof:name":"Arnold Smith Excavating Barn",
    "wof:placetype":"venue"
},
  "geometry": {"coordinates":[-79.18831,35.890251],"type":"Point"}
}