{
  "type": "Feature",
  "properties": {
    "iso:country":"US",
    "sg:address":"1402 Holloway St",
    "sg:city":"Durham",
    "sg:classifiers":[
        {
            "category":"Professional",
            "subcategory":"Management & Consulting",
            "type":"Services"
        }
    ],
    "sg:phone":"+1 919 682 0546",
    "sg:postcode":"27703",
    "sg:province":"NC",
    "sg:tags":[
        "consultant",
        "educational"
    ],
    "wof:name":"Agape Corner Boarding School",
    "wof:placetype":"venue"
},
  "geometry": {"coordinates":[-78.875784,35.994192],"type":"Point"}
}