{
  "type": "Feature",
  "properties": {
    "iso:country":"US",
    "sg:address":"887 Seven Oaks Rd",
    "sg:city":"Boone",
    "sg:classifiers":[
        {
            "category":"Shopping",
            "subcategory":"Pharmacy",
            "type":"Retail Goods"
        }
    ],
    "sg:phone":"+1 828 263 0780",
    "sg:postcode":"28618",
    "sg:province":"NC",
    "sg:tags":[
        "resistant",
        "product",
        "allergy"
    ],
    "wof:name":"Dust Busters",
    "wof:placetype":"venue"
},
  "geometry": {"coordinates":[-81.619676,36.232788],"type":"Point"}
}