{
  "type": "Feature",
  "properties": {
    "addr:full":"4154 Main At North Hills St Raleigh NC 27609",
    "addr:housenumber":"4154",
    "addr:postcode":"27609",
    "addr:street":"Main At North Hills St",
    "iso:country":"US",
    "sg:address":"4154 Main At North Hills St",
    "sg:city":"Raleigh",
    "sg:classifiers":[
        {
            "category":"Restaurant",
            "type":"Food & Drink"
        }
    ],
    "sg:menulink":"http://www.allmenus.com/nc/raleigh/178960-chick-fil-a/menu/",
    "sg:phone":"+1 919 510 0100",
    "sg:postcode":"27609",
    "sg:province":"NC",
    "sg:tags":[
        "wrap",
        "soup",
        "american",
        "sandwich",
        "salad"
    ],
    "wof:name":"Chick-Fil-A",
    "wof:placetype":"venue"
},
  "geometry": {"coordinates":[-78.643134,35.83681],"type":"Point"}
}