{
  "type": "Feature",
  "properties": {
    "addr:full":"8521 X-Way Rd Gibson NC 28343",
    "addr:housenumber":"8521",
    "addr:postcode":"28343",
    "addr:street":"X-Way Rd",
    "iso:country":"US",
    "sg:address":"8521 X-Way Rd",
    "sg:city":"Gibson",
    "sg:classifiers":[
        {
            "category":"Professional",
            "subcategory":"Business Services",
            "type":"Services"
        }
    ],
    "sg:phone":"+1   ",
    "sg:postcode":"28343",
    "sg:province":"NC",
    "wof:name":"Superior Interior S",
    "wof:placetype":"venue"
},
  "geometry": {"coordinates":[-79.56458000000001,34.737425],"type":"Point"}
}