{
  "type": "Feature",
  "properties": {
    "addr:full":"2101 Foy Rd Gastonia NC 28052",
    "addr:housenumber":"2101",
    "addr:postcode":"28052",
    "addr:street":"Foy Rd",
    "iso:country":"US",
    "sg:address":"2101 Foy Rd",
    "sg:city":"Gastonia",
    "sg:classifiers":[
        {
            "category":"Government",
            "subcategory":"Fire Station",
            "type":"Public Place"
        }
    ],
    "sg:phone":"+1 704 864 5326",
    "sg:postcode":"28052",
    "sg:province":"NC",
    "sg:tags":[
        "department"
    ],
    "wof:name":"Crowders Mountain Vol Fire",
    "wof:placetype":"venue"
},
  "geometry": {"coordinates":[-81.255793,35.233857],"type":"Point"}
}