{
  "type": "Feature",
  "properties": {
    "addr:full":"200 Walnut St Cary NC 27511",
    "addr:housenumber":"200",
    "addr:postcode":"27511",
    "addr:street":"Walnut St",
    "iso:country":"US",
    "sg:address":"200 Walnut St",
    "sg:city":"Cary",
    "sg:classifiers":[
        {
            "category":"Education",
            "subcategory":"Special Training",
            "type":"Public Place"
        }
    ],
    "sg:phone":"+1   ",
    "sg:postcode":"27511",
    "sg:province":"NC",
    "wof:name":"Linda Youngs Piano Studio",
    "wof:placetype":"venue"
},
  "geometry": {"coordinates":[-78.776371,35.781822],"type":"Point"}
}