{
  "type": "Feature",
  "properties": {
    "iso:country":"US",
    "sg:address":"265 Owensby Rd",
    "sg:city":"Mill Spring",
    "sg:classifiers":[
        {
            "category":"Building & Trades",
            "subcategory":"Construction",
            "type":"Services"
        }
    ],
    "sg:phone":"+1 828 894 3636",
    "sg:postcode":"28792",
    "sg:province":"NC",
    "sg:tags":[
        "underground",
        "trenching",
        "contractor"
    ],
    "wof:name":"Owensby's Backhoe Svc",
    "wof:placetype":"venue"
},
  "geometry": {"coordinates":[-82.36568200000001,35.340788],"type":"Point"}
}