{
  "type": "Feature",
  "properties": {
    "iso:country":"US",
    "sg:address":"225 Buttercup Dr",
    "sg:city":"Jamestown",
    "sg:classifiers":[
        {
            "category":"Autos & Motor Vehicles",
            "subcategory":"Automobile Sales",
            "type":"Retail Goods"
        }
    ],
    "sg:phone":"+1 336 315 8555",
    "sg:postcode":"27282",
    "sg:province":"NC",
    "sg:tags":[
        "used"
    ],
    "wof:name":"International Motorcars Inc",
    "wof:placetype":"venue"
},
  "geometry": {"coordinates":[-79.937501,36.020012],"type":"Point"}
}