{
  "type": "Feature",
  "properties": {
    "addr:full":"4006 Oak St Morehead City NC 28557",
    "addr:housenumber":"4006",
    "addr:postcode":"28557",
    "addr:street":"Oak St",
    "iso:country":"US",
    "sg:address":"4006 Oak St",
    "sg:city":"Morehead City",
    "sg:classifiers":[
        {
            "category":"Organizations",
            "subcategory":"Community Association",
            "type":"Services"
        }
    ],
    "sg:phone":"+1 252 726 3615",
    "sg:postcode":"28557",
    "sg:province":"NC",
    "sg:tags":[
        "fraternal"
    ],
    "wof:name":"Masonic Lodge",
    "wof:placetype":"venue"
},
  "geometry": {"coordinates":[-76.76448499999999,34.724202],"type":"Point"}
}