{
  "type": "Feature",
  "properties": {
    "iso:country":"US",
    "sg:address":"1120 Stanley Hall Rd",
    "sg:city":"Dunn",
    "sg:classifiers":[
        {
            "category":"Farming",
            "subcategory":"Farm",
            "type":"Manufacturing & Wholesale Goods"
        }
    ],
    "sg:phone":"+1 910 891 5853",
    "sg:postcode":"28334",
    "sg:province":"NC",
    "wof:name":"West Farms",
    "wof:placetype":"venue"
},
  "geometry": {"coordinates":[-78.556606,35.197494],"type":"Point"}
}