{
  "type": "Feature",
  "properties": {
    "iso:country":"US",
    "sg:address":"831 2nd Ave SW",
    "sg:city":"Hickory",
    "sg:classifiers":[
        {
            "category":"Building & Trades",
            "subcategory":"Construction",
            "type":"Services"
        }
    ],
    "sg:phone":"+1 828 322 3202",
    "sg:postcode":"28602",
    "sg:province":"NC",
    "sg:tags":[
        "resurfacing",
        "laying",
        "refinishing",
        "floor"
    ],
    "wof:name":"Pilot Mountain Hardwood",
    "wof:placetype":"venue"
},
  "geometry": {"coordinates":[-81.352283,35.729943],"type":"Point"}
}