{
  "type": "Feature",
  "properties": {
    "addr:full":"401 Fayetteville Street Mall Raleigh NC 27601",
    "addr:housenumber":"401",
    "addr:postcode":"27601",
    "addr:street":"Fayetteville Street Mall",
    "iso:country":"US",
    "sg:address":"401 Fayetteville Street Mall",
    "sg:city":"Raleigh",
    "sg:classifiers":[
        {
            "category":"Personal",
            "subcategory":"Barber",
            "type":"Services"
        }
    ],
    "sg:phone":"+1 919 832 4354",
    "sg:postcode":"27601",
    "sg:province":"NC",
    "wof:name":"Hair Shop & Tanning Salon",
    "wof:placetype":"venue"
},
  "geometry": {"coordinates":[-78.63942299999999,35.774238],"type":"Point"}
}