{
  "type": "Feature",
  "properties": {
    "iso:country":"US",
    "sg:address":"1296 Bear Creek Church Rd",
    "sg:city":"Mocksville",
    "sg:classifiers":[
        {
            "category":"Food & Beverages",
            "subcategory":"Groceries & Convenience Stores",
            "type":"Retail Goods"
        }
    ],
    "sg:phone":"+1 704 546 7535",
    "sg:postcode":"27028",
    "sg:province":"NC",
    "wof:name":"Turkeyfoot Country Market",
    "wof:placetype":"venue"
},
  "geometry": {"coordinates":[-80.68423900000001,36.003205],"type":"Point"}
}