{
  "type": "Feature",
  "properties": {
    "addr:full":"403 W State St Black Mountain NC 28711",
    "addr:housenumber":"403",
    "addr:postcode":"28711",
    "addr:street":"W State St",
    "iso:country":"US",
    "sg:address":"403 W State St",
    "sg:city":"Black Mountain",
    "sg:classifiers":[
        {
            "category":"Retail",
            "subcategory":"Portrait Studio",
            "type":"Services"
        }
    ],
    "sg:phone":"+1 828 669 3883",
    "sg:postcode":"28711",
    "sg:province":"NC",
    "sg:tags":[
        "photographer"
    ],
    "wof:name":"Blake Madden Photography",
    "wof:placetype":"venue"
},
  "geometry": {"coordinates":[-82.324155,35.614678],"type":"Point"}
}