{
  "type": "Feature",
  "properties": {
    "addr:full":"448 Horse N Carriage Ln Cameron NC 28326",
    "addr:housenumber":"448",
    "addr:postcode":"28326",
    "addr:street":"Horse N Carriage Ln",
    "iso:country":"US",
    "sg:address":"448 Horse N Carriage Ln",
    "sg:city":"Cameron",
    "sg:classifiers":[
        {
            "category":"Health Services",
            "subcategory":"Clinic",
            "type":"Services"
        }
    ],
    "sg:phone":"+1   ",
    "sg:postcode":"28326",
    "sg:province":"NC",
    "wof:name":"Cameron Medical Associates PA",
    "wof:placetype":"venue"
},
  "geometry": {"coordinates":[-79.22472500000001,35.258177],"type":"Point"}
}