{
  "type": "Feature",
  "properties": {
    "iso:country":"US",
    "sg:address":"8421 Old Statesville Rd",
    "sg:city":"Charlotte",
    "sg:classifiers":[
        {
            "category":"Building & Trades",
            "subcategory":"Plumbing",
            "type":"Services"
        }
    ],
    "sg:phone":"+1 704 494 4784",
    "sg:postcode":"28269",
    "sg:province":"NC",
    "sg:tags":[
        "balancing",
        "air"
    ],
    "wof:name":"Balance Palmetto Air & Water",
    "wof:placetype":"venue"
},
  "geometry": {"coordinates":[-80.824563,35.337462],"type":"Point"}
}