{
  "type": "Feature",
  "properties": {
    "iso:country":"US",
    "sg:address":"428 Alamance Rd",
    "sg:city":"Burlington",
    "sg:classifiers":[
        {
            "category":"Organizations",
            "subcategory":"Non-profit Organization",
            "type":"Services"
        }
    ],
    "sg:phone":"+1 336 524 9969",
    "sg:postcode":"27215",
    "sg:province":"NC",
    "sg:tags":[
        "fund",
        "counselor",
        "raising"
    ],
    "wof:name":"Piedmont School Sales Inc",
    "wof:placetype":"venue"
},
  "geometry": {"coordinates":[-79.46550999999999,36.074594],"type":"Point"}
}