{
  "type": "Feature",
  "properties": {
    "iso:country":"US",
    "sg:address":"5516 Roxboro Rd",
    "sg:city":"Durham",
    "sg:classifiers":[
        {
            "category":"Organizations",
            "subcategory":"Religious Organization",
            "type":"Services"
        }
    ],
    "sg:phone":"+1 919 471 0220",
    "sg:postcode":"27712",
    "sg:province":"NC",
    "sg:tags":[
        "church"
    ],
    "wof:name":"Christian Assembly Church",
    "wof:placetype":"venue"
},
  "geometry": {"coordinates":[-78.91032800000001,36.093559],"type":"Point"}
}