{
  "type": "Feature",
  "properties": {
    "addr:full":"23 Zion Church Rd Sanford NC 27330",
    "addr:housenumber":"23",
    "addr:postcode":"27330",
    "addr:street":"Zion Church Rd",
    "iso:country":"US",
    "sg:address":"23 Zion Church Rd",
    "sg:city":"Sanford",
    "sg:classifiers":[
        {
            "category":"Organizations",
            "subcategory":"Religious Organization",
            "type":"Services"
        }
    ],
    "sg:phone":"+1   ",
    "sg:postcode":"27330",
    "sg:province":"NC",
    "wof:name":"Zion Christian Church",
    "wof:placetype":"venue"
},
  "geometry": {"coordinates":[-79.128518,35.572896],"type":"Point"}
}