{
  "type": "Feature",
  "properties": {
    "iso:country":"US",
    "sg:address":"3100 Smoketree Ct",
    "sg:city":"Raleigh",
    "sg:classifiers":[
        {
            "category":"Wholesale",
            "subcategory":"Electrical",
            "type":"Manufacturing & Wholesale Goods"
        }
    ],
    "sg:phone":"+1 919 981 0477",
    "sg:postcode":"27604",
    "sg:province":"NC",
    "sg:tags":[
        "control",
        "security",
        "system"
    ],
    "sg:website":"www.thephoenixgroup.com",
    "wof:name":"Phoenix Group Intl",
    "wof:placetype":"venue"
},
  "geometry": {"coordinates":[-78.605599,35.820872],"type":"Point"}
}