{
  "type": "Feature",
  "properties": {
    "addr:full":"3543 S Church St Burlington NC 27215",
    "addr:housenumber":"3543",
    "addr:postcode":"27215",
    "addr:street":"S Church St",
    "iso:country":"US",
    "sg:address":"3543 S Church St",
    "sg:city":"Burlington",
    "sg:classifiers":[
        {
            "category":"Personal",
            "subcategory":"Beauty Salon",
            "type":"Services"
        }
    ],
    "sg:phone":"+1 336 584 1533",
    "sg:postcode":"27215",
    "sg:province":"NC",
    "sg:tags":[
        "shop"
    ],
    "wof:name":"Hair Masters",
    "wof:placetype":"venue"
},
  "geometry": {"coordinates":[-79.52145299999999,36.080389],"type":"Point"}
}