{
  "type": "Feature",
  "properties": {
    "iso:country":"US",
    "sg:address":"18 Aman Ct",
    "sg:city":"Durham",
    "sg:classifiers":[
        {
            "category":"Professional",
            "subcategory":"Lawyer & Legal Services",
            "type":"Services"
        }
    ],
    "sg:phone":"+1   ",
    "sg:postcode":"27713",
    "sg:province":"NC",
    "wof:name":"Westrom Brian Atty At Law",
    "wof:placetype":"venue"
},
  "geometry": {"coordinates":[-78.927154,35.88793],"type":"Point"}
}