{
  "type": "Feature",
  "properties": {
    "iso:country":"US",
    "sg:address":"3700 Davis Dr",
    "sg:city":"Charlotte",
    "sg:classifiers":[
        {
            "category":"Wholesale",
            "subcategory":"Apparel",
            "type":"Manufacturing & Wholesale Goods"
        }
    ],
    "sg:phone":"+1 704 844 6808",
    "sg:postcode":"28270",
    "sg:province":"NC",
    "sg:tags":[
        "sportswear"
    ],
    "wof:name":"Tawk Chawk",
    "wof:placetype":"venue"
},
  "geometry": {"coordinates":[-80.74117099999999,35.074253],"type":"Point"}
}