{
  "type": "Feature",
  "properties": {
    "iso:country":"US",
    "sg:address":"105 S Main St",
    "sg:city":"Rolesville",
    "sg:classifiers":[
        {
            "category":"Professional",
            "subcategory":"Lawyer & Legal Services",
            "type":"Services"
        }
    ],
    "sg:phone":"+1 919 554 4606",
    "sg:postcode":"27571",
    "sg:province":"NC",
    "sg:tags":[
        "attorney"
    ],
    "wof:name":"Joseph M Kosko PA",
    "wof:placetype":"venue"
},
  "geometry": {"coordinates":[-78.457447,35.923143],"type":"Point"}
}