{
  "type": "Feature",
  "properties": {
    "addr:full":"147 Ellenburg Rd Statesville NC 28625",
    "addr:housenumber":"147",
    "addr:postcode":"28625",
    "addr:street":"Ellenburg Rd",
    "iso:country":"US",
    "sg:address":"147 Ellenburg Rd",
    "sg:city":"Statesville",
    "sg:classifiers":[
        {
            "category":"Building & Trades",
            "subcategory":"Plumbing",
            "type":"Services"
        }
    ],
    "sg:phone":"+1 704 872 2089",
    "sg:postcode":"28625",
    "sg:province":"NC",
    "sg:tags":[
        "heating",
        "contractor"
    ],
    "wof:name":"Ellenburg Sheet Metal Co",
    "wof:placetype":"venue"
},
  "geometry": {"coordinates":[-80.920084,35.826766],"type":"Point"}
}