{
  "type": "Feature",
  "properties": {
    "iso:country":"US",
    "sg:address":"185 Charlois Blvd",
    "sg:city":"Winston Salem",
    "sg:classifiers":[
        {
            "category":"Health Services",
            "subcategory":"Health Practitioner",
            "type":"Services"
        }
    ],
    "sg:phone":"+1 336 659 3343",
    "sg:postcode":"27103",
    "sg:province":"NC",
    "sg:tags":[
        "therapist",
        "physical"
    ],
    "wof:name":"Myocare Inc",
    "wof:placetype":"venue"
},
  "geometry": {"coordinates":[-80.30305199999999,36.08451],"type":"Point"}
}