{
  "type": "Feature",
  "properties": {
    "iso:country":"US",
    "sg:address":"9524 Robert Burns Ct",
    "sg:city":"Charlotte",
    "sg:classifiers":[
        {
            "category":"Professional",
            "type":"Services"
        }
    ],
    "sg:phone":"+1 704 549 1513",
    "sg:postcode":"28213",
    "sg:province":"NC",
    "wof:name":"Caster Demond D L",
    "wof:placetype":"venue"
},
  "geometry": {"coordinates":[-80.72865400000001,35.295884],"type":"Point"}
}