{
  "type": "Feature",
  "properties": {
    "iso:country":"US",
    "sg:address":"132 S Salisbury St",
    "sg:city":"Raleigh",
    "sg:classifiers":[
        {
            "category":"Professional",
            "subcategory":"Management & Consulting",
            "type":"Services"
        }
    ],
    "sg:phone":"+1 919 754 8644",
    "sg:postcode":"27602",
    "sg:province":"NC",
    "sg:tags":[
        "consultant"
    ],
    "wof:name":"Capitol City Consulting LLC",
    "wof:placetype":"venue"
},
  "geometry": {"coordinates":[-78.64023299999999,35.778727],"type":"Point"}
}