{
  "type": "Feature",
  "properties": {
    "iso:country":"US",
    "sg:address":"362 Glen Dancy Rd",
    "sg:city":"Hays",
    "sg:classifiers":[
        {
            "category":"Building & Trades",
            "subcategory":"Construction",
            "type":"Services"
        }
    ],
    "sg:phone":"+1 336 696 3100",
    "sg:postcode":"28635",
    "sg:province":"NC",
    "sg:tags":[
        "hanging",
        "painter",
        "contractor"
    ],
    "wof:name":"Piedmont Paint Co Inc",
    "wof:placetype":"venue"
},
  "geometry": {"coordinates":[-81.128123,36.258432],"type":"Point"}
}