{
  "type": "Feature",
  "properties": {
    "addr:full":"2 Herman Ave Asheville NC 28803",
    "addr:housenumber":"2",
    "addr:postcode":"28803",
    "addr:street":"Herman Ave",
    "iso:country":"US",
    "sg:address":"2 Herman Ave",
    "sg:city":"Asheville",
    "sg:classifiers":[
        {
            "category":"Real Estate",
            "subcategory":"Architect",
            "type":"Services"
        }
    ],
    "sg:phone":"+1 828 687 2445",
    "sg:postcode":"28803",
    "sg:province":"NC",
    "wof:name":"Peter G Knowland",
    "wof:placetype":"venue"
},
  "geometry": {"coordinates":[-82.522395,35.489329],"type":"Point"}
}