{
  "type": "Feature",
  "properties": {
    "addr:full":"1200 Stoneferry Ln Raleigh NC 27606",
    "addr:housenumber":"1200",
    "addr:postcode":"27606",
    "addr:street":"Stoneferry Ln",
    "iso:country":"US",
    "sg:address":"1200 Stoneferry Ln",
    "sg:city":"Raleigh",
    "sg:phone":"+1 919 946 1737",
    "sg:postcode":"27606",
    "sg:province":"NC",
    "wof:name":"Core Results Personal Training",
    "wof:placetype":"venue"
},
  "geometry": {"coordinates":[-78.714333,35.765671],"type":"Point"}
}