{
  "type": "Feature",
  "properties": {
    "iso:country":"US",
    "sg:address":"1119 Jones St",
    "sg:city":"Winterville",
    "sg:classifiers":[
        {
            "category":"Farming",
            "subcategory":"Livestock Farm",
            "type":"Manufacturing & Wholesale Goods"
        }
    ],
    "sg:phone":"+1 252 756 6620",
    "sg:postcode":"28590",
    "sg:province":"NC",
    "sg:tags":[
        "feeding"
    ],
    "wof:name":"Allen Farms",
    "wof:placetype":"venue"
},
  "geometry": {"coordinates":[-77.39778699999999,35.535038],"type":"Point"}
}