{
  "type": "Feature",
  "properties": {
    "iso:country":"US",
    "sg:address":"1649 E Broad St",
    "sg:city":"Statesville",
    "sg:classifiers":[
        {
            "category":"Shopping",
            "subcategory":"Department Store",
            "type":"Retail Goods"
        }
    ],
    "sg:phone":"+1 704 873 0561",
    "sg:postcode":"28625",
    "sg:province":"NC",
    "wof:name":"JC Penney",
    "wof:placetype":"venue"
},
  "geometry": {"coordinates":[-80.862122,35.791246],"type":"Point"}
}