{
  "type": "Feature",
  "properties": {
    "addr:full":"Carmen's Cuban Cafe & Lounge 108 Factory Shops Rd Morrisville NC 27560",
    "addr:housenumber":"108",
    "addr:postcode":"27560",
    "addr:street":"Factory Shops Rd",
    "iso:country":"US",
    "sg:address":"Carmen's Cuban Cafe & Lounge 108 Factory Shops Rd",
    "sg:city":"Morrisville",
    "sg:classifiers":[
        {
            "category":"Arts & Performance",
            "subcategory":"Dance",
            "type":"Entertainment"
        }
    ],
    "sg:phone":"+1 919 467 8080",
    "sg:postcode":"27560",
    "sg:province":"NC",
    "sg:tags":[
        "school"
    ],
    "sg:website":"www.mambodinamico.com",
    "wof:name":"Mambo Dinamico Dance Company",
    "wof:placetype":"venue"
},
  "geometry": {"coordinates":[-78.818292,35.862384],"type":"Point"}
}