{
  "type": "Feature",
  "properties": {
    "addr:full":"10083 Straight Gate Rd Whitakers NC 27891",
    "addr:postcode":"10083;27891",
    "addr:street":"Straight Gate Rd",
    "iso:country":"US",
    "sg:address":"10083 Straight Gate Rd",
    "sg:city":"Whitakers",
    "sg:classifiers":[
        {
            "category":"Organizations",
            "subcategory":"Religious Organization",
            "type":"Services"
        }
    ],
    "sg:phone":"+1 252 985 3465",
    "sg:postcode":"27891",
    "sg:province":"NC",
    "sg:tags":[
        "church"
    ],
    "wof:name":"Shady Grove United Pentecostal",
    "wof:placetype":"venue"
},
  "geometry": {"coordinates":[-77.83774699999999,36.101294],"type":"Point"}
}