{
  "type": "Feature",
  "properties": {
    "iso:country":"US",
    "sg:address":"721 Windy Trl",
    "sg:city":"Newport",
    "sg:classifiers":[
        {
            "category":"Professional",
            "subcategory":"Business Services",
            "type":"Services"
        }
    ],
    "sg:phone":"+1   ",
    "sg:postcode":"28570",
    "sg:province":"NC",
    "wof:name":"Interior Essentials",
    "wof:placetype":"venue"
},
  "geometry": {"coordinates":[-76.86702200000001,34.803273],"type":"Point"}
}