{
  "type": "Feature",
  "properties": {
    "addr:full":"19836 Madison Village Dr Cornelius NC 28031",
    "addr:housenumber":"19836",
    "addr:postcode":"28031",
    "addr:street":"Madison Village Dr",
    "iso:country":"US",
    "sg:address":"19836 Madison Village Dr",
    "sg:city":"Cornelius",
    "sg:classifiers":[
        {
            "category":"Wholesale",
            "subcategory":"Machinery & Supplies",
            "type":"Manufacturing & Wholesale Goods"
        }
    ],
    "sg:phone":"+1 704 892 1224",
    "sg:postcode":"28031",
    "sg:province":"NC",
    "sg:tags":[
        "equipment"
    ],
    "wof:name":"Drillco Tools",
    "wof:placetype":"venue"
},
  "geometry": {"coordinates":[-80.894415,35.485814],"type":"Point"}
}