{
  "type": "Feature",
  "properties": {
    "addr:full":"335 Sanford Ave Mocksville NC 27028",
    "addr:housenumber":"335",
    "addr:postcode":"27028",
    "addr:street":"Sanford Ave",
    "iso:country":"US",
    "sg:address":"335 Sanford Ave",
    "sg:city":"Mocksville",
    "sg:classifiers":[
        {
            "category":"Government",
            "subcategory":"Fire Station",
            "type":"Public Place"
        }
    ],
    "sg:phone":"+1 336 751 5782",
    "sg:postcode":"27028",
    "sg:province":"NC",
    "sg:tags":[
        "department",
        "protection"
    ],
    "wof:name":"Mocksville Fire Department",
    "wof:placetype":"venue"
},
  "geometry": {"coordinates":[-80.564127,35.892351],"type":"Point"}
}