{
  "type": "Feature",
  "properties": {
    "addr:full":"5344 Central Ave Charlotte NC 28212",
    "addr:housenumber":"5344",
    "addr:postcode":"28212",
    "addr:street":"Central Ave",
    "iso:country":"US",
    "sg:address":"5344 Central Ave",
    "sg:city":"Charlotte",
    "sg:classifiers":[
        {
            "category":"Health Services",
            "subcategory":"Chiropractor",
            "type":"Services"
        }
    ],
    "sg:phone":"+1 704 568 4195",
    "sg:postcode":"28212",
    "sg:province":"NC",
    "wof:name":"Keith Clinic Chiropractic PA",
    "wof:placetype":"venue"
},
  "geometry": {"coordinates":[-80.751768,35.206583],"type":"Point"}
}