{
  "type": "Feature",
  "properties": {
    "iso:country":"US",
    "sg:address":"1805 Crepe Myrtle Dr",
    "sg:city":"Sanford",
    "sg:classifiers":[
        {
            "category":"Professional",
            "subcategory":"Management & Consulting",
            "type":"Services"
        }
    ],
    "sg:phone":"+1   ",
    "sg:postcode":"27330",
    "sg:province":"NC",
    "wof:name":"Dossenbach Associates LLC",
    "wof:placetype":"venue"
},
  "geometry": {"coordinates":[-79.220764,35.492644],"type":"Point"}
}