{
  "type": "Feature",
  "properties": {
    "addr:full":"1737 Gold Hill Rd Asheboro NC 27203",
    "addr:housenumber":"1737",
    "addr:postcode":"27203",
    "addr:street":"Gold Hill Rd",
    "iso:country":"US",
    "sg:address":"1737 Gold Hill Rd",
    "sg:city":"Asheboro",
    "sg:classifiers":[
        {
            "category":"Retail",
            "subcategory":"Auto Repair",
            "type":"Services"
        }
    ],
    "sg:phone":"+1   ",
    "sg:postcode":"27203",
    "sg:province":"NC",
    "sg:tags":[
        "body"
    ],
    "wof:name":"Auto Body Shop",
    "wof:placetype":"venue"
},
  "geometry": {"coordinates":[-79.784297,35.744622],"type":"Point"}
}