{
  "type": "Feature",
  "properties": {
    "iso:country":"US",
    "sg:address":"3161 Long Run Farm Rd",
    "sg:city":"Mount Pleasant",
    "sg:classifiers":[
        {
            "category":"Professional",
            "type":"Services"
        }
    ],
    "sg:phone":"+1 704 436 2768",
    "sg:postcode":"28124",
    "sg:province":"NC",
    "wof:name":"Hahn Atlas & Marsha",
    "wof:placetype":"venue"
},
  "geometry": {"coordinates":[-80.42160699999999,35.374774],"type":"Point"}
}