{
  "type": "Feature",
  "properties": {
    "addr:full":"2118 Lawndale Dr Greensboro NC 27408",
    "addr:housenumber":"2118",
    "addr:postcode":"27408",
    "addr:street":"Lawndale Dr",
    "iso:country":"US",
    "sg:address":"2118 Lawndale Dr",
    "sg:city":"Greensboro",
    "sg:classifiers":[
        {
            "category":"Shopping",
            "subcategory":"Used Merchandise",
            "type":"Retail Goods"
        }
    ],
    "sg:phone":"+1 336 274 4448",
    "sg:postcode":"27408",
    "sg:province":"NC",
    "sg:tags":[
        "book"
    ],
    "wof:name":"Phillip Jacobson",
    "wof:placetype":"venue"
},
  "geometry": {"coordinates":[-79.817375,36.097307],"type":"Point"}
}