{
  "type": "Feature",
  "properties": {
    "iso:country":"US",
    "sg:address":"202 Abbey Ln",
    "sg:city":"Apex",
    "sg:classifiers":[
        {
            "category":"Professional",
            "subcategory":"Computer Services",
            "type":"Services"
        }
    ],
    "sg:phone":"+1   ",
    "sg:postcode":"27511",
    "sg:province":"NC",
    "sg:tags":[
        "related"
    ],
    "wof:name":"Eddie Glenny",
    "wof:placetype":"venue"
},
  "geometry": {"coordinates":[-78.768607,35.781509],"type":"Point"}
}