{
  "type": "Feature",
  "properties": {
    "addr:full":"922 S Main St Star NC 27356",
    "addr:housenumber":"922",
    "addr:postcode":"27356",
    "addr:street":"S Main St",
    "iso:country":"US",
    "sg:address":"922 S Main St",
    "sg:city":"Star",
    "sg:classifiers":[
        {
            "category":"Autos & Motor Vehicles",
            "subcategory":"Automobile Sales",
            "type":"Retail Goods"
        }
    ],
    "sg:phone":"+1 910 428 4898",
    "sg:postcode":"27356",
    "sg:province":"NC",
    "sg:tags":[
        "car",
        "dealer"
    ],
    "wof:name":"Green's Auto Sales",
    "wof:placetype":"venue"
},
  "geometry": {"coordinates":[-79.778611,35.38086],"type":"Point"}
}