{
  "type": "Feature",
  "properties": {
    "addr:full":"3327 Live Oak Hog County Rd Deep Run NC 28525",
    "addr:housenumber":"3327",
    "addr:postcode":"28525",
    "addr:street":"Live Oak Hog County Rd",
    "iso:country":"US",
    "sg:address":"3327 Live Oak Hog County Rd",
    "sg:city":"Deep Run",
    "sg:classifiers":[
        {
            "category":"Wholesale",
            "subcategory":"Farm Supplies",
            "type":"Manufacturing & Wholesale Goods"
        },
        {
            "category":"Professional",
            "subcategory":"Business Services",
            "type":"Services"
        }
    ],
    "sg:phone":"+1 252 568 1147",
    "sg:postcode":"28525",
    "sg:province":"NC",
    "sg:tags":[
        "purchasing"
    ],
    "wof:name":"Eastern Foods Inc",
    "wof:placetype":"venue"
},
  "geometry": {"coordinates":[-77.69129,35.10675],"type":"Point"}
}