{
  "type": "Feature",
  "properties": {
    "iso:country":"US",
    "sg:address":"3908 Market St",
    "sg:city":"Wilmington",
    "sg:classifiers":[
        {
            "category":"Insurance",
            "subcategory":"Insurance Agent",
            "type":"Services"
        }
    ],
    "sg:phone":"+1 910 343 0030",
    "sg:postcode":"28403",
    "sg:province":"NC",
    "wof:name":"Atlantic Coast Auto Insurance",
    "wof:placetype":"venue"
},
  "geometry": {"coordinates":[-77.896789,34.241567],"type":"Point"}
}