{
  "type": "Feature",
  "properties": {
    "iso:country":"US",
    "sg:address":"3502 US Hwy 117 N",
    "sg:city":"Goldsboro",
    "sg:classifiers":[
        {
            "category":"Manufacturing",
            "subcategory":"Building Materials",
            "type":"Manufacturing & Wholesale Goods"
        }
    ],
    "sg:phone":"+1 919 734 1663",
    "sg:postcode":"27530",
    "sg:province":"NC",
    "sg:tags":[
        "hardware",
        "mfg",
        "wood",
        "kitchen",
        "cabinet"
    ],
    "wof:name":"Mc Fatter Woodworks Inc",
    "wof:placetype":"venue"
},
  "geometry": {"coordinates":[-77.97781999999999,35.45213],"type":"Point"}
}