{
  "type": "Feature",
  "properties": {
    "iso:country":"US",
    "sg:address":"2119 Holland Ave",
    "sg:city":"Burlington",
    "sg:classifiers":[
        {
            "category":"Building & Trades",
            "subcategory":"Cleaning & Sanitation",
            "type":"Services"
        }
    ],
    "sg:phone":"+1   ",
    "sg:postcode":"27217",
    "sg:province":"NC",
    "sg:tags":[
        "maintenance"
    ],
    "wof:name":"Cleantech Janitorial Service",
    "wof:placetype":"venue"
},
  "geometry": {"coordinates":[-79.398695,36.102582],"type":"Point"}
}