{
  "type": "Feature",
  "properties": {
    "addr:full":"161 Biltmore Ave Asheville NC 28801",
    "addr:housenumber":"161",
    "addr:postcode":"28801",
    "addr:street":"Biltmore Ave",
    "iso:country":"US",
    "sg:address":"161 Biltmore Ave",
    "sg:city":"Asheville",
    "sg:classifiers":[
        {
            "category":"Cafe",
            "type":"Food & Drink"
        }
    ],
    "sg:menulink":"http://www.allmenus.com/nc/asheville/141511-wild-wing-cafe/menu/",
    "sg:phone":"+1 828 253 3066",
    "sg:postcode":"28801",
    "sg:province":"NC",
    "sg:tags":[
        "american",
        "pub"
    ],
    "wof:name":"Wild Wing Cafe",
    "wof:placetype":"venue"
},
  "geometry": {"coordinates":[-82.551453,35.589591],"type":"Point"}
}