{
  "type": "Feature",
  "properties": {
    "iso:country":"US",
    "sg:address":"411 Owen Dr",
    "sg:city":"Fayetteville",
    "sg:classifiers":[
        {
            "category":"Shopping",
            "type":"Retail Goods"
        }
    ],
    "sg:phone":"+1 910 484 2509",
    "sg:postcode":"28304",
    "sg:province":"NC",
    "sg:tags":[
        "orthopedic",
        "appliance",
        "prosthetic"
    ],
    "wof:name":"Delaby Brace and Limb Co Inc",
    "wof:placetype":"venue"
},
  "geometry": {"coordinates":[-78.93305100000001,35.037825],"type":"Point"}
}