{
  "type": "Feature",
  "properties": {
    "addr:full":"9571 Chapel Hill Rd Morrisville NC 27560",
    "addr:housenumber":"9571",
    "addr:postcode":"27560",
    "addr:street":"Chapel Hill Rd",
    "iso:country":"US",
    "sg:address":"9571 Chapel Hill Rd",
    "sg:city":"Morrisville",
    "sg:classifiers":[
        {
            "category":"Personal",
            "subcategory":"Beauty Salon",
            "type":"Services"
        }
    ],
    "sg:phone":"+1 919 465 9850",
    "sg:postcode":"27560",
    "sg:province":"NC",
    "sg:tags":[
        "hair",
        "shop"
    ],
    "sg:website":"www.supercuts.com",
    "wof:name":"Supercuts",
    "wof:placetype":"venue"
},
  "geometry": {"coordinates":[-78.809848,35.806179],"type":"Point"}
}