{
  "type": "Feature",
  "properties": {
    "iso:country":"US",
    "sg:address":"4755 Hedgemore Dr",
    "sg:city":"Charlotte",
    "sg:classifiers":[
        {
            "category":"Professional",
            "subcategory":"Management & Consulting",
            "type":"Services"
        }
    ],
    "sg:phone":"+1   ",
    "sg:postcode":"28209",
    "sg:province":"NC",
    "wof:name":"Masters In Management Inc",
    "wof:placetype":"venue"
},
  "geometry": {"coordinates":[-80.847538,35.165888],"type":"Point"}
}