{
  "type": "Feature",
  "properties": {
    "addr:full":"104 W Colonial Dr Thomasville NC 27360",
    "addr:housenumber":"104",
    "addr:postcode":"27360",
    "addr:street":"W Colonial Dr",
    "iso:country":"US",
    "sg:address":"104 W Colonial Dr",
    "sg:city":"Thomasville",
    "sg:classifiers":[
        {
            "category":"Organizations",
            "subcategory":"Religious Organization",
            "type":"Services"
        }
    ],
    "sg:phone":"+1 336 472 2186",
    "sg:postcode":"27360",
    "sg:province":"NC",
    "sg:tags":[
        "church"
    ],
    "wof:name":"Thomasville World Outreach Ctr",
    "wof:placetype":"venue"
},
  "geometry": {"coordinates":[-80.085308,35.878997],"type":"Point"}
}