{
  "type": "Feature",
  "properties": {
    "addr:full":"7239 Pineville-Matthews Rd Charlotte NC 28226",
    "addr:housenumber":"7239",
    "addr:postcode":"28226",
    "addr:street":"Pineville-Matthews Rd",
    "iso:country":"US",
    "sg:address":"7239 Pineville-Matthews Rd",
    "sg:city":"Charlotte",
    "sg:classifiers":[
        {
            "category":"Banks & Credit Unions",
            "subcategory":"Bank",
            "type":"Services"
        }
    ],
    "sg:phone":"+1 704 287 3137",
    "sg:postcode":"28226",
    "sg:province":"NC",
    "sg:tags":[
        "loan",
        "real estate"
    ],
    "wof:name":"Citizens Home Loan",
    "wof:placetype":"venue"
},
  "geometry": {"coordinates":[-80.839319,35.087057],"type":"Point"}
}