{
  "type": "Feature",
  "properties": {
    "iso:country":"US",
    "sg:address":"304 N Hoyle St",
    "sg:city":"Cherryville",
    "sg:classifiers":[
        {
            "category":"Airline",
            "type":"Transportation"
        }
    ],
    "sg:phone":"+1 704 435 2304",
    "sg:postcode":"28021",
    "sg:province":"NC",
    "sg:tags":[
        "courier",
        "air"
    ],
    "wof:name":"Bridges Express",
    "wof:placetype":"venue"
},
  "geometry": {"coordinates":[-81.37445700000001,35.385417],"type":"Point"}
}