{
  "type": "Feature",
  "properties": {
    "iso:country":"US",
    "sg:address":"1710 Chardale Dr",
    "sg:city":"Clemmons",
    "sg:classifiers":[
        {
            "category":"Building & Trades",
            "subcategory":"Electrical",
            "type":"Services"
        }
    ],
    "sg:phone":"+1 336 766 3024",
    "sg:postcode":"27012",
    "sg:province":"NC",
    "sg:tags":[
        "electrical",
        "electric",
        "contractor"
    ],
    "wof:name":"Chapel Electric LLC",
    "wof:placetype":"venue"
},
  "geometry": {"coordinates":[-80.39998799999999,36.070931],"type":"Point"}
}