{
  "type": "Feature",
  "properties": {
    "iso:country":"US",
    "sg:address":"100 Cambridge Plaza Dr",
    "sg:city":"Winston Salem",
    "sg:classifiers":[
        {
            "category":"Building & Trades",
            "subcategory":"Construction",
            "type":"Services"
        }
    ],
    "sg:phone":"+1 336 659 6905",
    "sg:postcode":"27104",
    "sg:province":"NC",
    "sg:tags":[
        "company"
    ],
    "wof:name":"Platinum Construction Co",
    "wof:placetype":"venue"
},
  "geometry": {"coordinates":[-80.33524,36.081603],"type":"Point"}
}