{
  "type": "Feature",
  "properties": {
    "addr:full":"240 Loblolly Cir Louisburg NC 27549",
    "addr:housenumber":"240",
    "addr:postcode":"27549",
    "addr:street":"Loblolly Cir",
    "iso:country":"US",
    "sg:address":"240 Loblolly Cir",
    "sg:city":"Louisburg",
    "sg:classifiers":[
        {
            "category":"Professional",
            "subcategory":"Business Services",
            "type":"Services"
        }
    ],
    "sg:phone":"+1   ",
    "sg:postcode":"27549",
    "sg:province":"NC",
    "wof:name":"Lesoy Candle Inc",
    "wof:placetype":"venue"
},
  "geometry": {"coordinates":[-78.24327599999999,35.999946],"type":"Point"}
}