{
  "type": "Feature",
  "properties": {
    "addr:full":"5184 Old Haywood Rd Fletcher NC 28732",
    "addr:housenumber":"5184",
    "addr:postcode":"28732",
    "addr:street":"Old Haywood Rd",
    "iso:country":"US",
    "sg:address":"5184 Old Haywood Rd",
    "sg:city":"Fletcher",
    "sg:classifiers":[
        {
            "category":"Autos & Motor Vehicles",
            "subcategory":"Auto Supplies",
            "type":"Retail Goods"
        }
    ],
    "sg:phone":"+1 828 890 0655",
    "sg:postcode":"28732",
    "sg:province":"NC",
    "sg:tags":[
        "alternator",
        "generator"
    ],
    "wof:name":"Starters Alternators & Brakes",
    "wof:placetype":"venue"
},
  "geometry": {"coordinates":[-82.569654,35.405425],"type":"Point"}
}