{
  "type": "Feature",
  "properties": {
    "iso:country":"US",
    "sg:address":"156 Bunny Run Ln",
    "sg:city":"Waynesville",
    "sg:classifiers":[
        {
            "category":"Shopping",
            "subcategory":"Bicycles & Sporting Goods",
            "type":"Retail Goods"
        }
    ],
    "sg:phone":"+1 828 926 8307",
    "sg:postcode":"28785",
    "sg:province":"NC",
    "sg:tags":[
        "equipment",
        "archery",
        "supply"
    ],
    "wof:name":"Right On Target Family Archery",
    "wof:placetype":"venue"
},
  "geometry": {"coordinates":[-83.01787299999999,35.578011],"type":"Point"}
}