{
  "type": "Feature",
  "properties": {
    "addr:full":"2474 Bell Arthur Rd Greenville NC 27834",
    "addr:housenumber":"2474",
    "addr:postcode":"27834",
    "addr:street":"Bell Arthur Rd",
    "iso:country":"US",
    "sg:address":"2474 Bell Arthur Rd",
    "sg:city":"Greenville",
    "sg:classifiers":[
        {
            "category":"Utilities",
            "subcategory":"Water",
            "type":"Services"
        }
    ],
    "sg:phone":"+1 252 752 6252",
    "sg:postcode":"27834",
    "sg:province":"NC",
    "sg:tags":[
        "company",
        "sewage"
    ],
    "wof:name":"Bellarthur Water Corp",
    "wof:placetype":"venue"
},
  "geometry": {"coordinates":[-77.512028,35.588738],"type":"Point"}
}