{
  "type": "Feature",
  "properties": {
    "addr:full":"418 Sidney-Cherry Grove Rd Clarendon NC 28432",
    "addr:housenumber":"418",
    "addr:postcode":"28432",
    "addr:street":"Sidney-Cherry Grove Rd",
    "iso:country":"US",
    "sg:address":"418 Sidney-Cherry Grove Rd",
    "sg:city":"Clarendon",
    "sg:classifiers":[
        {
            "category":"Building & Trades",
            "subcategory":"Construction",
            "type":"Services"
        }
    ],
    "sg:phone":"+1 910 653 4037",
    "sg:postcode":"28432",
    "sg:province":"NC",
    "sg:tags":[
        "contractor"
    ],
    "wof:name":"Garrell Cabinet Works",
    "wof:placetype":"venue"
},
  "geometry": {"coordinates":[-78.821001,34.194913],"type":"Point"}
}