{
  "type": "Feature",
  "properties": {
    "addr:full":"4713 College Acres Dr Wilmington NC 28403",
    "addr:housenumber":"4713",
    "addr:postcode":"28403",
    "addr:street":"College Acres Dr",
    "iso:country":"US",
    "sg:address":"4713 College Acres Dr",
    "sg:city":"Wilmington",
    "sg:classifiers":[
        {
            "category":"Health Services",
            "subcategory":"Doctor",
            "type":"Services"
        }
    ],
    "sg:phone":"+1 910 799 2238",
    "sg:postcode":"28403",
    "sg:province":"NC",
    "sg:tags":[
        "dentist"
    ],
    "wof:name":"Picklesimer & Plasky",
    "wof:placetype":"venue"
},
  "geometry": {"coordinates":[-77.871555,34.23],"type":"Point"}
}