{
  "type": "Feature",
  "properties": {
    "addr:full":"2123 Rockford St Mount Airy NC 27030",
    "addr:housenumber":"2123",
    "addr:postcode":"27030",
    "addr:street":"Rockford St",
    "iso:country":"US",
    "sg:address":"2123 Rockford St",
    "sg:city":"Mount Airy",
    "sg:classifiers":[
        {
            "category":"Retail",
            "subcategory":"Laundry & Dry Cleaning",
            "type":"Services"
        }
    ],
    "sg:phone":"+1   ",
    "sg:postcode":"27030",
    "sg:province":"NC",
    "sg:tags":[
        "drycleaning",
        "plant"
    ],
    "wof:name":"Forest Oaks Cleaners",
    "wof:placetype":"venue"
},
  "geometry": {"coordinates":[-80.617981,36.477158],"type":"Point"}
}