{
  "type": "Feature",
  "properties": {
    "addr:full":"515 Walnut St S Wilson NC 27893",
    "addr:housenumber":"515",
    "addr:postcode":"27893",
    "addr:street":"Walnut St S",
    "iso:country":"US",
    "sg:address":"515 Walnut St S",
    "sg:city":"Wilson",
    "sg:classifiers":[
        {
            "category":"Food & Beverages",
            "subcategory":"Groceries & Convenience Stores",
            "type":"Retail Goods"
        }
    ],
    "sg:phone":"+1 252 291 1413",
    "sg:postcode":"27893",
    "sg:province":"NC",
    "sg:tags":[
        "grocer"
    ],
    "wof:name":"Whole Truth Grocery",
    "wof:placetype":"venue"
},
  "geometry": {"coordinates":[-77.91458799999999,35.717216],"type":"Point"}
}