{
  "type": "Feature",
  "properties": {
    "iso:country":"US",
    "sg:address":"117 S Main St",
    "sg:city":"Broadway",
    "sg:classifiers":[
        {
            "category":"Government",
            "subcategory":"Office",
            "type":"Public Place"
        },
        {
            "category":"Government",
            "subcategory":"Police Station",
            "type":"Public Place"
        }
    ],
    "sg:phone":"+1 919 258 9232",
    "sg:postcode":"27505",
    "sg:province":"NC",
    "sg:tags":[
        "department",
        "executive"
    ],
    "wof:name":"Broadway Police Department",
    "wof:placetype":"venue"
},
  "geometry": {"coordinates":[-79.052864,35.456761],"type":"Point"}
}