{
  "type": "Feature",
  "properties": {
    "addr:full":"1828 Catawba Valley Blvd SE Hickory NC 28602",
    "addr:housenumber":"1828",
    "addr:postcode":"28602",
    "addr:street":"Catawba Valley Blvd Se",
    "iso:country":"US",
    "sg:address":"1828 Catawba Valley Blvd SE",
    "sg:city":"Hickory",
    "sg:classifiers":[
        {
            "category":"Utilities",
            "subcategory":"Mobile Phone",
            "type":"Services"
        }
    ],
    "sg:phone":"+1 828 328 2343",
    "sg:postcode":"28602",
    "sg:province":"NC",
    "sg:tags":[
        "communication",
        "radiotelephone"
    ],
    "wof:name":"Sprint",
    "wof:placetype":"venue"
},
  "geometry": {"coordinates":[-81.309674,35.702955],"type":"Point"}
}