{
  "type": "Feature",
  "properties": {
    "iso:country":"US",
    "sg:address":"127 E Innes St",
    "sg:city":"Salisbury",
    "sg:classifiers":[
        {
            "category":"Shopping",
            "subcategory":"Computers & Home Electronics",
            "type":"Retail Goods"
        }
    ],
    "sg:phone":"+1 704 633 1965",
    "sg:postcode":"28144",
    "sg:province":"NC",
    "wof:name":"Dr Neutron",
    "wof:placetype":"venue"
},
  "geometry": {"coordinates":[-80.469123,35.666642],"type":"Point"}
}