{
  "type": "Feature",
  "properties": {
    "iso:country":"US",
    "sg:address":"3003 Clarendon Blvd",
    "sg:city":"New Bern",
    "sg:classifiers":[
        {
            "category":"Retail",
            "subcategory":"Photofinishing",
            "type":"Services"
        }
    ],
    "sg:phone":"+1   ",
    "sg:postcode":"28562",
    "sg:province":"NC",
    "wof:name":"12 Hour Photo Inc",
    "wof:placetype":"venue"
},
  "geometry": {"coordinates":[-77.085168,35.103498],"type":"Point"}
}