{
  "type": "Feature",
  "properties": {
    "addr:full":"4705 Twinwood Ct Raleigh NC 27613",
    "addr:housenumber":"4705",
    "addr:postcode":"27613",
    "addr:street":"Twinwood Ct",
    "iso:country":"US",
    "sg:address":"4705 Twinwood Ct",
    "sg:city":"Raleigh",
    "sg:classifiers":[
        {
            "category":"Manufacturing",
            "subcategory":"Printing",
            "type":"Manufacturing & Wholesale Goods"
        }
    ],
    "sg:phone":"+1 919 848 9743",
    "sg:postcode":"27613",
    "sg:province":"NC",
    "sg:tags":[
        "publishing"
    ],
    "wof:name":"Sweetwater Press Inc",
    "wof:placetype":"venue"
},
  "geometry": {"coordinates":[-78.71061899999999,35.922305],"type":"Point"}
}