{
  "type": "Feature",
  "properties": {
    "iso:country":"US",
    "sg:address":"825 Goshen St",
    "sg:city":"Oxford",
    "sg:classifiers":[
        {
            "category":"Organizations",
            "subcategory":"Religious Organization",
            "type":"Services"
        }
    ],
    "sg:phone":"+1   ",
    "sg:postcode":"27565",
    "sg:province":"NC",
    "wof:name":"New Light Baptist Church",
    "wof:placetype":"venue"
},
  "geometry": {"coordinates":[-78.600159,36.318496],"type":"Point"}
}