{
  "type": "Feature",
  "properties": {
    "addr:full":"2306 Dunavant St Charlotte NC 28203",
    "addr:housenumber":"2306",
    "addr:postcode":"28203",
    "addr:street":"Dunavant St",
    "iso:country":"US",
    "sg:address":"2306 Dunavant St",
    "sg:city":"Charlotte",
    "sg:classifiers":[
        {
            "category":"Home & Garden",
            "subcategory":"Home Furnishings",
            "type":"Retail Goods"
        },
        {
            "category":"Home & Garden",
            "subcategory":"Building Materials",
            "type":"Retail Goods"
        },
        {
            "category":"Building & Trades",
            "subcategory":"Construction",
            "type":"Services"
        }
    ],
    "sg:phone":"+1 704 759 3920",
    "sg:postcode":"28203",
    "sg:province":"NC",
    "sg:tags":[
        "repair",
        "bathroom",
        "handyman",
        "improvement",
        "planning",
        "design",
        "maintenance",
        "remodeling",
        "kitchen"
    ],
    "sg:website":"http://www.caseremodeling.com",
    "wof:name":"Case Handyman and Remodeling",
    "wof:placetype":"venue"
},
  "geometry": {"coordinates":[-80.865021,35.206481],"type":"Point"}
}