{
  "type": "Feature",
  "properties": {
    "iso:country":"US",
    "sg:address":"230 Industrial Park Dr",
    "sg:city":"Smithfield",
    "sg:classifiers":[
        {
            "category":"Shopping",
            "type":"Retail Goods"
        }
    ],
    "sg:phone":"+1 919 934 0548",
    "sg:postcode":"27577",
    "sg:province":"NC",
    "sg:tags":[
        "factory",
        "outlet"
    ],
    "wof:name":"L'Eggs Hanes Bali",
    "wof:placetype":"venue"
},
  "geometry": {"coordinates":[-78.322305,35.505637],"type":"Point"}
}