{
  "type": "Feature",
  "properties": {
    "iso:country":"US",
    "sg:address":"2917 Creech Rd",
    "sg:city":"Raleigh",
    "sg:classifiers":[
        {
            "category":"Real Estate",
            "subcategory":"Real Estate Services",
            "type":"Services"
        },
        {
            "category":"Real Estate",
            "subcategory":"Real Estate Operator",
            "type":"Services"
        }
    ],
    "sg:phone":"+1 919 834 7327",
    "sg:postcode":"27610",
    "sg:province":"NC",
    "sg:tags":[
        "apartment",
        "vacancy",
        "listing",
        "rental",
        "finder"
    ],
    "wof:name":"Elders Peak Senior Apartments",
    "wof:placetype":"venue"
},
  "geometry": {"coordinates":[-78.60700799999999,35.738973],"type":"Point"}
}