{
  "type": "Feature",
  "properties": {
    "addr:full":"1267 Cb Eller School Rd Elkin NC 28621",
    "addr:housenumber":"1267",
    "addr:postcode":"28621",
    "addr:street":"Cb Eller School Rd",
    "iso:country":"US",
    "sg:address":"1267 Cb Eller School Rd",
    "sg:city":"Elkin",
    "sg:classifiers":[
        {
            "category":"Personal",
            "subcategory":"Beauty Salon",
            "type":"Services"
        }
    ],
    "sg:phone":"+1   ",
    "sg:postcode":"28621",
    "sg:province":"NC",
    "sg:tags":[
        "shop"
    ],
    "wof:name":"Hair Care",
    "wof:placetype":"venue"
},
  "geometry": {"coordinates":[-80.890964,36.277146],"type":"Point"}
}