{
  "type": "Feature",
  "properties": {
    "iso:country":"US",
    "sg:address":"601 Brevard Rd",
    "sg:city":"Asheville",
    "sg:classifiers":[
        {
            "category":"Retail",
            "subcategory":"Auto Repair",
            "type":"Services"
        }
    ],
    "sg:phone":"+1 828 667 0191",
    "sg:postcode":"28806",
    "sg:province":"NC",
    "sg:tags":[
        "wrecker"
    ],
    "wof:name":"191 Towing",
    "wof:placetype":"venue"
},
  "geometry": {"coordinates":[-82.60046699999999,35.55136],"type":"Point"}
}