{
  "type": "Feature",
  "properties": {
    "iso:country":"US",
    "sg:address":"2421 N Center St",
    "sg:city":"Hickory",
    "sg:classifiers":[
        {
            "category":"Utilities",
            "subcategory":"Telephone",
            "type":"Services"
        }
    ],
    "sg:phone":"+1 828 327 3332",
    "sg:postcode":"28601",
    "sg:province":"NC",
    "sg:tags":[
        "communications",
        "radiotelephone",
        "communication"
    ],
    "wof:name":"MCI Worldcom Network Services",
    "wof:placetype":"venue"
},
  "geometry": {"coordinates":[-81.332848,35.764537],"type":"Point"}
}