{
  "type": "Feature",
  "properties": {
    "addr:full":"3340 Jaeckle Dr Wilmington NC 28403",
    "addr:housenumber":"3340",
    "addr:postcode":"28403",
    "addr:street":"Jaeckle Dr",
    "iso:country":"US",
    "sg:address":"3340 Jaeckle Dr",
    "sg:city":"Wilmington",
    "sg:classifiers":[
        {
            "category":"Building & Trades",
            "subcategory":"Construction",
            "type":"Services"
        }
    ],
    "sg:phone":"+1 910 772 6385",
    "sg:postcode":"28403",
    "sg:province":"NC",
    "sg:tags":[
        "general",
        "contractor"
    ],
    "wof:name":"Baldwin Construction",
    "wof:placetype":"venue"
},
  "geometry": {"coordinates":[-77.89953300000001,34.231573],"type":"Point"}
}