{
  "type": "Feature",
  "properties": {
    "addr:full":"291 Fairview Rd Andrews NC 28901",
    "addr:housenumber":"291",
    "addr:postcode":"28901",
    "addr:street":"Fairview Rd",
    "iso:country":"US",
    "sg:address":"291 Fairview Rd",
    "sg:city":"Andrews",
    "sg:classifiers":[
        {
            "category":"Shopping",
            "subcategory":"Bicycles & Sporting Goods",
            "type":"Retail Goods"
        }
    ],
    "sg:phone":"+1 828 321 9898",
    "sg:postcode":"28901",
    "sg:province":"NC",
    "wof:name":"G & S Bait",
    "wof:placetype":"venue"
},
  "geometry": {"coordinates":[-83.836297,35.19387],"type":"Point"}
}