{
  "type": "Feature",
  "properties": {
    "addr:full":"1809 Blue Clay Rd Wilmington NC 28405",
    "addr:housenumber":"1809",
    "addr:postcode":"28405",
    "addr:street":"Blue Clay Rd",
    "iso:country":"US",
    "sg:address":"1809 Blue Clay Rd",
    "sg:city":"Wilmington",
    "sg:classifiers":[
        {
            "category":"Manufacturing",
            "subcategory":"Metals",
            "type":"Manufacturing & Wholesale Goods"
        }
    ],
    "sg:phone":"+1 910 762 1350",
    "sg:postcode":"28405",
    "sg:province":"NC",
    "sg:tags":[
        "steel"
    ],
    "wof:name":"J & R Rebar Inc",
    "wof:placetype":"venue"
},
  "geometry": {"coordinates":[-77.919451,34.274994],"type":"Point"}
}