{
  "type": "Feature",
  "properties": {
    "addr:full":"4849 Hudson Church Rd Indian Trail NC 28079",
    "addr:housenumber":"4849",
    "addr:postcode":"28079",
    "addr:street":"Hudson Church Rd",
    "iso:country":"US",
    "sg:address":"4849 Hudson Church Rd",
    "sg:city":"Indian Trail",
    "sg:classifiers":[
        {
            "category":"Organizations",
            "subcategory":"Religious Organization",
            "type":"Services"
        }
    ],
    "sg:phone":"+1   ",
    "sg:postcode":"28079",
    "sg:province":"NC",
    "wof:name":"Zion H Church",
    "wof:placetype":"venue"
},
  "geometry": {"coordinates":[-80.68789200000001,35.028566],"type":"Point"}
}