{
  "type": "Feature",
  "properties": {
    "iso:country":"US",
    "sg:address":"3022 Forestdale Dr",
    "sg:city":"Burlington",
    "sg:classifiers":[
        {
            "category":"Shopping",
            "subcategory":"Clothing, Apparel, & Fashions",
            "type":"Retail Goods"
        }
    ],
    "sg:phone":"+1 336 275 8511",
    "sg:postcode":"27215",
    "sg:province":"NC",
    "sg:tags":[
        "family",
        "merchandise",
        "general"
    ],
    "wof:name":"Glitters",
    "wof:placetype":"venue"
},
  "geometry": {"coordinates":[-79.494855,36.083611],"type":"Point"}
}