{
  "type": "Feature",
  "properties": {
    "addr:full":"400 W Bodenhamer St Kernersville NC 27284",
    "addr:housenumber":"400",
    "addr:postcode":"27284",
    "addr:street":"W Bodenhamer St",
    "iso:country":"US",
    "sg:address":"400 W Bodenhamer St",
    "sg:city":"Kernersville",
    "sg:classifiers":[
        {
            "category":"Government",
            "subcategory":"Fire Station",
            "type":"Public Place"
        }
    ],
    "sg:phone":"+1 336 996 6791",
    "sg:postcode":"27284",
    "sg:province":"NC",
    "sg:tags":[
        "department"
    ],
    "wof:name":"Kernersville Fire Marshal",
    "wof:placetype":"venue"
},
  "geometry": {"coordinates":[-80.07781,36.129464],"type":"Point"}
}