{
  "type": "Feature",
  "properties": {
    "iso:country":"US",
    "sg:address":"402 US Hwy 301 N",
    "sg:city":"Micro",
    "sg:classifiers":[
        {
            "category":"Food & Beverages",
            "subcategory":"Groceries & Convenience Stores",
            "type":"Retail Goods"
        }
    ],
    "sg:phone":"+1 919 284 0299",
    "sg:postcode":"27555",
    "sg:province":"NC",
    "sg:tags":[
        "grocer"
    ],
    "wof:name":"Piggly Wiggly",
    "wof:placetype":"venue"
},
  "geometry": {"coordinates":[-78.198324,35.565742],"type":"Point"}
}