{
  "type": "Feature",
  "properties": {
    "iso:country":"US",
    "sg:address":"178 Westwood Pl",
    "sg:city":"Asheville",
    "sg:classifiers":[
        {
            "category":"Professional",
            "subcategory":"Art Services",
            "type":"Services"
        }
    ],
    "sg:phone":"+1 828 350 8677",
    "sg:postcode":"28806",
    "sg:province":"NC",
    "sg:tags":[
        "artist"
    ],
    "wof:name":"Studio Of Naomi Stuecker",
    "wof:placetype":"venue"
},
  "geometry": {"coordinates":[-82.57652400000001,35.586163],"type":"Point"}
}