{
  "type": "Feature",
  "properties": {
    "addr:full":"213 N Chatham Ave Siler City NC 27344",
    "addr:housenumber":"213",
    "addr:postcode":"27344",
    "addr:street":"N Chatham Ave",
    "iso:country":"US",
    "sg:address":"213 N Chatham Ave",
    "sg:city":"Siler City",
    "sg:classifiers":[
        {
            "category":"Personal",
            "subcategory":"Beauty Salon",
            "type":"Services"
        }
    ],
    "sg:phone":"+1   ",
    "sg:postcode":"27344",
    "sg:province":"NC",
    "sg:tags":[
        "shop"
    ],
    "wof:name":"Jade Nails",
    "wof:placetype":"venue"
},
  "geometry": {"coordinates":[-79.464635,35.724591],"type":"Point"}
}