{
  "type": "Feature",
  "properties": {
    "iso:country":"US",
    "sg:address":"1910 Ballard Dr",
    "sg:city":"Gastonia",
    "sg:classifiers":[
        {
            "category":"Building & Trades",
            "subcategory":"Landscaping Services",
            "type":"Services"
        }
    ],
    "sg:phone":"+1 704 810 0051",
    "sg:postcode":"28054",
    "sg:province":"NC",
    "wof:name":"Landscaping Technology & Maint",
    "wof:placetype":"venue"
},
  "geometry": {"coordinates":[-81.153441,35.287786],"type":"Point"}
}