{
  "type": "Feature",
  "properties": {
    "iso:country":"US",
    "sg:address":"2900 Eastway Dr",
    "sg:city":"Charlotte",
    "sg:classifiers":[
        {
            "category":"Retail",
            "subcategory":"Auto Repair",
            "type":"Services"
        }
    ],
    "sg:phone":"+1 704 531 0005",
    "sg:postcode":"28205",
    "sg:province":"NC",
    "sg:tags":[
        "repairing",
        "automobile"
    ],
    "wof:name":"Automax Lube N Tune & Brakes",
    "wof:placetype":"venue"
},
  "geometry": {"coordinates":[-80.780737,35.217549],"type":"Point"}
}