{
  "type": "Feature",
  "properties": {
    "iso:country":"US",
    "sg:address":"1803 E Wendover Ave",
    "sg:city":"Greensboro",
    "sg:classifiers":[
        {
            "category":"Insurance",
            "subcategory":"Insurance Agent",
            "type":"Services"
        }
    ],
    "sg:phone":"+1 336 273 7526",
    "sg:postcode":"27405",
    "sg:province":"NC",
    "wof:name":"De Pinto Tax Insurance",
    "wof:placetype":"venue"
},
  "geometry": {"coordinates":[-79.761439,36.087489],"type":"Point"}
}