{
  "type": "Feature",
  "properties": {
    "addr:full":"3250 High Point Rd Winston Salem NC 27107",
    "addr:housenumber":"3250",
    "addr:postcode":"27107",
    "addr:street":"High Point Rd",
    "iso:country":"US",
    "sg:address":"3250 High Point Rd",
    "sg:city":"Winston Salem",
    "sg:classifiers":[
        {
            "category":"Real Estate",
            "subcategory":"Developer",
            "type":"Services"
        }
    ],
    "sg:phone":"+1 336 788 0894",
    "sg:postcode":"27107",
    "sg:province":"NC",
    "sg:tags":[
        "cemetery"
    ],
    "wof:name":"Oaklawn Memorial Gardens",
    "wof:placetype":"venue"
},
  "geometry": {"coordinates":[-80.172056,36.075626],"type":"Point"}
}