{
  "type": "Feature",
  "properties": {
    "addr:full":"3926 Melshire Ln Charlotte NC 28269",
    "addr:housenumber":"3926",
    "addr:postcode":"28269",
    "addr:street":"Melshire Ln",
    "iso:country":"US",
    "sg:address":"3926 Melshire Ln",
    "sg:city":"Charlotte",
    "sg:classifiers":[
        {
            "category":"Place Of Worship",
            "subcategory":"Church",
            "type":"Public Place"
        },
        {
            "category":"Place Of Worship",
            "type":"Public Place"
        }
    ],
    "sg:phone":"+1 704 921 0954",
    "sg:postcode":"28269",
    "sg:province":"NC",
    "sg:tags":[
        "churches-greek",
        "churches-eastern",
        "orthodox"
    ],
    "wof:name":"St George Syrian Orthodox",
    "wof:placetype":"venue"
},
  "geometry": {"coordinates":[-80.79753700000001,35.34437],"type":"Point"}
}