{
  "type": "Feature",
  "properties": {
    "iso:country":"US",
    "sg:address":"209 S Columbia St",
    "sg:city":"Chapel Hill",
    "sg:classifiers":[
        {
            "category":"Recreation",
            "type":"Entertainment"
        }
    ],
    "sg:phone":"+1 919 688 0310",
    "sg:postcode":"27516",
    "sg:province":"NC",
    "sg:tags":[
        "psychic",
        "medium"
    ],
    "wof:name":"Lady Wallace",
    "wof:placetype":"venue"
},
  "geometry": {"coordinates":[-79.054255,35.910531],"type":"Point"}
}