{
  "type": "Feature",
  "properties": {
    "iso:country":"US",
    "sg:address":"340 Rosebush Trl",
    "sg:city":"Mount Airy",
    "sg:classifiers":[
        {
            "category":"Real Estate",
            "subcategory":"Real Estate Operator",
            "type":"Services"
        }
    ],
    "sg:phone":"+1 336 320 2781",
    "sg:postcode":"27030",
    "sg:province":"NC",
    "sg:tags":[
        "building",
        "nonresidential"
    ],
    "wof:name":"Bjcl Properties LLC",
    "wof:placetype":"venue"
},
  "geometry": {"coordinates":[-80.69680200000001,36.451685],"type":"Point"}
}