{
  "type": "Feature",
  "properties": {
    "iso:country":"US",
    "sg:address":"3800 Baptist Ln",
    "sg:city":"Concord",
    "sg:classifiers":[
        {
            "category":"Organizations",
            "subcategory":"Religious Organization",
            "type":"Services"
        }
    ],
    "sg:phone":"+1 704 788 2223",
    "sg:postcode":"28025",
    "sg:province":"NC",
    "sg:tags":[
        "church"
    ],
    "wof:name":"Howell's Baptist Church",
    "wof:placetype":"venue"
},
  "geometry": {"coordinates":[-80.51170999999999,35.298161],"type":"Point"}
}