{
  "type": "Feature",
  "properties": {
    "addr:full":"201 N Lee St Salisbury NC 28144",
    "addr:housenumber":"201",
    "addr:postcode":"28144",
    "addr:street":"N Lee St",
    "iso:country":"US",
    "sg:address":"201 N Lee St",
    "sg:city":"Salisbury",
    "sg:classifiers":[
        {
            "category":"Real Estate",
            "subcategory":"Real Estate Operator",
            "type":"Services"
        }
    ],
    "sg:phone":"+1 704 633 7981",
    "sg:postcode":"28144",
    "sg:province":"NC",
    "sg:tags":[
        "handicapped",
        "apartment",
        "complex",
        "elderly",
        "for"
    ],
    "wof:name":"Yadkin House Apartments",
    "wof:placetype":"venue"
},
  "geometry": {"coordinates":[-80.46654599999999,35.668171],"type":"Point"}
}