{
  "type": "Feature",
  "properties": {
    "addr:full":"1312 Annapolis Dr Raleigh NC 27608",
    "addr:housenumber":"1312",
    "addr:postcode":"27608",
    "addr:street":"Annapolis Dr",
    "iso:country":"US",
    "sg:address":"1312 Annapolis Dr",
    "sg:city":"Raleigh",
    "sg:classifiers":[
        {
            "category":"Organizations",
            "subcategory":"Professional Association",
            "type":"Services"
        }
    ],
    "sg:phone":"+1 919 832 1413",
    "sg:postcode":"27608",
    "sg:province":"NC",
    "sg:website":"www.ncatl.org",
    "wof:name":"N C Academy Of Trial Lawyers",
    "wof:placetype":"venue"
},
  "geometry": {"coordinates":[-78.658023,35.799305],"type":"Point"}
}