{
  "type": "Feature",
  "properties": {
    "addr:full":"1113 Jonathan Creek Rd Waynesville NC 28785",
    "addr:housenumber":"1113",
    "addr:postcode":"28785",
    "addr:street":"Jonathan Creek Rd",
    "iso:country":"US",
    "sg:address":"1113 Jonathan Creek Rd",
    "sg:city":"Waynesville",
    "sg:classifiers":[
        {
            "category":"Personal",
            "subcategory":"Tanning Parlor",
            "type":"Services"
        }
    ],
    "sg:phone":"+1 828 926 1083",
    "sg:postcode":"28785",
    "sg:province":"NC",
    "sg:tags":[
        "salon"
    ],
    "wof:name":"Penny Saver Video & Tanning",
    "wof:placetype":"venue"
},
  "geometry": {"coordinates":[-83.026055,35.53748],"type":"Point"}
}