{
  "type": "Feature",
  "properties": {
    "addr:full":"600 S Pine St Spring Hope NC 27882",
    "addr:housenumber":"600",
    "addr:postcode":"27882",
    "addr:street":"S Pine St",
    "iso:country":"US",
    "sg:address":"600 S Pine St",
    "sg:city":"Spring Hope",
    "sg:classifiers":[
        {
            "category":"Education",
            "subcategory":"School",
            "type":"Public Place"
        }
    ],
    "sg:phone":"+1 252 478 4839",
    "sg:postcode":"27882",
    "sg:province":"NC",
    "wof:name":"Spaulding Early Childhood Ctr",
    "wof:placetype":"venue"
},
  "geometry": {"coordinates":[-78.108301,35.938773],"type":"Point"}
}