{
  "type": "Feature",
  "properties": {
    "iso:country":"US",
    "sg:address":"1209 W Front St",
    "sg:city":"Statesville",
    "sg:classifiers":[
        {
            "category":"Retail",
            "subcategory":"Car Wash",
            "type":"Services"
        }
    ],
    "sg:phone":"+1   ",
    "sg:postcode":"28677",
    "sg:province":"NC",
    "sg:tags":[
        "carwash"
    ],
    "wof:name":"Ride With Pride Car Wash",
    "wof:placetype":"venue"
},
  "geometry": {"coordinates":[-80.910492,35.782827],"type":"Point"}
}