{
  "type": "Feature",
  "properties": {
    "addr:full":"829 Albemarle Rd Troy NC 27371",
    "addr:housenumber":"829",
    "addr:postcode":"27371",
    "addr:street":"Albemarle Rd",
    "iso:country":"US",
    "sg:address":"829 Albemarle Rd",
    "sg:city":"Troy",
    "sg:classifiers":[
        {
            "category":"Restaurant",
            "type":"Food & Drink"
        }
    ],
    "sg:menulink":"http://www.allmenus.com/nc/troy/85499-dominos-pizza/menu/",
    "sg:phone":"+1 910 572 1111",
    "sg:postcode":"27371",
    "sg:province":"NC",
    "sg:tags":[
        "american",
        "wing",
        "pizza"
    ],
    "wof:name":"Domino's Pizza",
    "wof:placetype":"venue"
},
  "geometry": {"coordinates":[-79.90813799999999,35.350317],"type":"Point"}
}