{
  "type": "Feature",
  "properties": {
    "addr:full":"7702 Mill Branch Rd Rocky Mount NC 27803",
    "addr:housenumber":"7702",
    "addr:postcode":"27803",
    "addr:street":"Mill Branch Rd",
    "iso:country":"US",
    "sg:address":"7702 Mill Branch Rd",
    "sg:city":"Rocky Mount",
    "sg:classifiers":[
        {
            "category":"Home & Garden",
            "subcategory":"Furniture",
            "type":"Retail Goods"
        }
    ],
    "sg:phone":"+1 252 972 0717",
    "sg:postcode":"27803",
    "sg:province":"NC",
    "sg:tags":[
        "top",
        "counter"
    ],
    "wof:name":"Goddard's Counter Tops",
    "wof:placetype":"venue"
},
  "geometry": {"coordinates":[-77.85878599999999,35.888022],"type":"Point"}
}