{
  "type": "Feature",
  "properties": {
    "iso:country":"US",
    "sg:address":"16411 Old Stone Crossing Dr",
    "sg:city":"Charlotte",
    "sg:classifiers":[
        {
            "category":"Building & Trades",
            "subcategory":"Construction",
            "type":"Services"
        }
    ],
    "sg:phone":"+1 704 971 1111",
    "sg:postcode":"28213",
    "sg:province":"NC",
    "sg:tags":[
        "home",
        "builder"
    ],
    "wof:name":"Don Galloway Homes",
    "wof:placetype":"venue"
},
  "geometry": {"coordinates":[-80.688329,35.290861],"type":"Point"}
}