{
  "type": "Feature",
  "properties": {
    "iso:country":"US",
    "sg:address":"1900 Crestdale Dr",
    "sg:city":"Charlotte",
    "sg:classifiers":[
        {
            "category":"Organizations",
            "subcategory":"Membership Organization",
            "type":"Services"
        }
    ],
    "sg:phone":"+1   ",
    "sg:postcode":"28216",
    "sg:province":"NC",
    "wof:name":"Alpha Lambda Omega",
    "wof:placetype":"venue"
},
  "geometry": {"coordinates":[-80.85055199999999,35.26933],"type":"Point"}
}