{
  "type": "Feature",
  "properties": {
    "addr:full":"261 Chatham St Newport NC 28570",
    "addr:housenumber":"261",
    "addr:postcode":"28570",
    "addr:street":"Chatham St",
    "iso:country":"US",
    "sg:address":"261 Chatham St",
    "sg:city":"Newport",
    "sg:classifiers":[
        {
            "category":"Autos & Motor Vehicles",
            "subcategory":"Automobile Sales",
            "type":"Retail Goods"
        }
    ],
    "sg:phone":"+1 252 223 5331",
    "sg:postcode":"28570",
    "sg:province":"NC",
    "sg:tags":[
        "car",
        "dealer"
    ],
    "wof:name":"Newport Motor Co Inc",
    "wof:placetype":"venue"
},
  "geometry": {"coordinates":[-76.85973799999999,34.792055],"type":"Point"}
}