{
  "type": "Feature",
  "properties": {
    "addr:full":"630 Union St S Concord NC 28025",
    "addr:housenumber":"630",
    "addr:postcode":"28025",
    "addr:street":"Union St S",
    "iso:country":"US",
    "sg:address":"630 Union St S",
    "sg:city":"Concord",
    "sg:classifiers":[
        {
            "category":"Professional",
            "type":"Services"
        }
    ],
    "sg:phone":"+1 704 788 1860",
    "sg:postcode":"28025",
    "sg:province":"NC",
    "wof:name":"Racers Reward Inc",
    "wof:placetype":"venue"
},
  "geometry": {"coordinates":[-80.56531699999999,35.393454],"type":"Point"}
}