{
  "type": "Feature",
  "properties": {
    "iso:country":"US",
    "sg:address":"8043 Oak Grove Church Rd",
    "sg:city":"Liberty",
    "sg:classifiers":[
        {
            "category":"Organizations",
            "subcategory":"Religious Organization",
            "type":"Services"
        }
    ],
    "sg:phone":"+1 336 622 3888",
    "sg:postcode":"27298",
    "sg:province":"NC",
    "sg:tags":[
        "church"
    ],
    "wof:name":"Oak Grove Baptist Church",
    "wof:placetype":"venue"
},
  "geometry": {"coordinates":[-79.532444,35.887487],"type":"Point"}
}