{
  "type": "Feature",
  "properties": {
    "addr:full":"340 McCullers St Clayton NC 27520",
    "addr:housenumber":"340",
    "addr:postcode":"27520",
    "addr:street":"Mccullers St",
    "iso:country":"US",
    "sg:address":"340 McCullers St",
    "sg:city":"Clayton",
    "sg:classifiers":[
        {
            "category":"Recreation",
            "type":"Entertainment"
        }
    ],
    "sg:phone":"+1 919 553 1550",
    "sg:postcode":"27520",
    "sg:province":"NC",
    "sg:tags":[
        "parks"
    ],
    "sg:website":"www.townofclaytonnc.org",
    "wof:name":"Clayton Parks & Recreations",
    "wof:placetype":"venue"
},
  "geometry": {"coordinates":[-78.464603,35.660808],"type":"Point"}
}