{
  "type": "Feature",
  "properties": {
    "iso:country":"US",
    "sg:address":"445 9th St SE",
    "sg:city":"Hickory",
    "sg:classifiers":[
        {
            "category":"Building & Trades",
            "subcategory":"Construction",
            "type":"Services"
        }
    ],
    "sg:phone":"+1 828 328 3909",
    "sg:postcode":"28602",
    "sg:province":"NC",
    "sg:tags":[
        "product",
        "asphalt"
    ],
    "wof:name":"Carolina Paving Of Hickory Inc",
    "wof:placetype":"venue"
},
  "geometry": {"coordinates":[-81.321201,35.727623],"type":"Point"}
}