{
  "type": "Feature",
  "properties": {
    "iso:country":"US",
    "sg:address":"607 Deerfield Rd",
    "sg:city":"Shelby",
    "sg:classifiers":[
        {
            "category":"Retail",
            "subcategory":"Repair Shop",
            "type":"Services"
        }
    ],
    "sg:phone":"+1   ",
    "sg:postcode":"28150",
    "sg:province":"NC",
    "wof:name":"Reliable Repairs Inc",
    "wof:placetype":"venue"
},
  "geometry": {"coordinates":[-81.498929,35.372374],"type":"Point"}
}