{
  "type": "Feature",
  "properties": {
    "addr:full":"1013 Englewood Ave Durham NC 27701",
    "addr:housenumber":"1013",
    "addr:postcode":"27701",
    "addr:street":"Englewood Ave",
    "iso:country":"US",
    "sg:address":"1013 Englewood Ave",
    "sg:city":"Durham",
    "sg:classifiers":[
        {
            "category":"Real Estate",
            "subcategory":"Architect",
            "type":"Services"
        }
    ],
    "sg:phone":"+1 919 682 0379",
    "sg:postcode":"27701",
    "sg:province":"NC",
    "wof:name":"Samuel C Hodges Jr Assoc",
    "wof:placetype":"venue"
},
  "geometry": {"coordinates":[-78.909459,36.014901],"type":"Point"}
}