{
  "type": "Feature",
  "properties": {
    "addr:full":"6815 Gordon Rd Wilmington NC 28411",
    "addr:housenumber":"6815",
    "addr:postcode":"28411",
    "addr:street":"Gordon Rd",
    "iso:country":"US",
    "sg:address":"6815 Gordon Rd",
    "sg:city":"Wilmington",
    "sg:classifiers":[
        {
            "category":"Retail",
            "subcategory":"Laundry & Dry Cleaning",
            "type":"Services"
        }
    ],
    "sg:phone":"+1 910 452 5700",
    "sg:postcode":"28411",
    "sg:province":"NC",
    "sg:tags":[
        "drycleaning",
        "plant"
    ],
    "wof:name":"A Cleaner World",
    "wof:placetype":"venue"
},
  "geometry": {"coordinates":[-77.829384,34.262563],"type":"Point"}
}