{
  "type": "Feature",
  "properties": {
    "iso:country":"US",
    "sg:address":"2401 Weston Pkwy",
    "sg:city":"Cary",
    "sg:classifiers":[
        {
            "category":"Building & Trades",
            "subcategory":"Construction",
            "type":"Services"
        }
    ],
    "sg:phone":"+1 919 678 9007",
    "sg:postcode":"27513",
    "sg:province":"NC",
    "sg:tags":[
        "home",
        "builder"
    ],
    "wof:name":"Baker Residential",
    "wof:placetype":"venue"
},
  "geometry": {"coordinates":[-78.78014,35.831382],"type":"Point"}
}