{
  "type": "Feature",
  "properties": {
    "iso:country":"US",
    "sg:address":"164 Billet's Bridge Rd",
    "sg:city":"Camden",
    "sg:classifiers":[
        {
            "category":"Building & Trades",
            "subcategory":"Construction",
            "type":"Services"
        }
    ],
    "sg:phone":"+1 252 336 2355",
    "sg:postcode":"27921",
    "sg:province":"NC",
    "sg:tags":[
        "contractor"
    ],
    "wof:name":"Eastern Siding Remodling",
    "wof:placetype":"venue"
},
  "geometry": {"coordinates":[-76.128294,36.296468],"type":"Point"}
}