{
  "type": "Feature",
  "properties": {
    "iso:country":"US",
    "sg:address":"367 Yacht Club Dr",
    "sg:city":"Newport",
    "sg:classifiers":[
        {
            "category":"Building & Trades",
            "subcategory":"Electrical",
            "type":"Services"
        }
    ],
    "sg:phone":"+1 252 393 8924",
    "sg:postcode":"28570",
    "sg:province":"NC",
    "sg:tags":[
        "electrical",
        "contractor"
    ],
    "wof:name":"Watt Electric Inc Ed",
    "wof:placetype":"venue"
},
  "geometry": {"coordinates":[-76.96023700000001,34.711557],"type":"Point"}
}