{
  "type": "Feature",
  "properties": {
    "addr:full":"2922 Baltic Ave Greensboro NC 27406",
    "addr:housenumber":"2922",
    "addr:postcode":"27406",
    "addr:street":"Baltic Ave",
    "iso:country":"US",
    "sg:address":"2922 Baltic Ave",
    "sg:city":"Greensboro",
    "sg:classifiers":[
        {
            "category":"Shopping",
            "subcategory":"Computers & Home Electronics",
            "type":"Retail Goods"
        }
    ],
    "sg:phone":"+1 336 274 6730",
    "sg:postcode":"27406",
    "sg:province":"NC",
    "sg:tags":[
        "parts",
        "supply"
    ],
    "wof:name":"Laser Tech Co",
    "wof:placetype":"venue"
},
  "geometry": {"coordinates":[-79.789377,36.029396],"type":"Point"}
}