{
  "type": "Feature",
  "properties": {
    "addr:full":"5019 Duncan Rd Monroe NC 28110",
    "addr:housenumber":"5019",
    "addr:postcode":"28110",
    "addr:street":"Duncan Rd",
    "iso:country":"US",
    "sg:address":"5019 Duncan Rd",
    "sg:city":"Monroe",
    "sg:classifiers":[
        {
            "category":"Building & Trades",
            "subcategory":"Plumbing",
            "type":"Services"
        }
    ],
    "sg:phone":"+1 704 283 1697",
    "sg:postcode":"28110",
    "sg:province":"NC",
    "sg:tags":[
        "tank",
        "septic"
    ],
    "wof:name":"Joseph Laney Septic Tank Svc",
    "wof:placetype":"venue"
},
  "geometry": {"coordinates":[-80.548006,35.08852],"type":"Point"}
}