{
  "type": "Feature",
  "properties": {
    "iso:country":"US",
    "sg:address":"600 N Cannon Blvd",
    "sg:city":"Kannapolis",
    "sg:classifiers":[
        {
            "category":"Food & Beverages",
            "subcategory":"Groceries & Convenience Stores",
            "type":"Retail Goods"
        },
        {
            "category":"Autos & Motor Vehicles",
            "subcategory":"Fuel & Gas Station",
            "type":"Retail Goods"
        }
    ],
    "sg:phone":"+1 704 932 8915",
    "sg:postcode":"28083",
    "sg:province":"NC",
    "sg:tags":[
        "oil"
    ],
    "wof:name":"Kannapolis Amoco",
    "wof:placetype":"venue"
},
  "geometry": {"coordinates":[-80.609099,35.502913],"type":"Point"}
}