{
  "type": "Feature",
  "properties": {
    "addr:full":"885 Liberty Church Rd Thomasville NC 27360",
    "addr:housenumber":"885",
    "addr:postcode":"27360",
    "addr:street":"Liberty Church Rd",
    "iso:country":"US",
    "sg:address":"885 Liberty Church Rd",
    "sg:city":"Thomasville",
    "sg:classifiers":[
        {
            "category":"Retail",
            "subcategory":"Repair Shop",
            "type":"Services"
        }
    ],
    "sg:phone":"+1   ",
    "sg:postcode":"27360",
    "sg:province":"NC",
    "wof:name":"H R Racing",
    "wof:placetype":"venue"
},
  "geometry": {"coordinates":[-80.08018199999999,35.784949],"type":"Point"}
}