{
  "type": "Feature",
  "properties": {
    "iso:country":"US",
    "sg:address":"56 Central Ave",
    "sg:city":"Asheville",
    "sg:classifiers":[
        {
            "category":"Real Estate",
            "subcategory":"Real Estate Services",
            "type":"Services"
        }
    ],
    "sg:phone":"+1 828 285 9892",
    "sg:postcode":"28801",
    "sg:province":"NC",
    "sg:tags":[
        "company",
        "title"
    ],
    "wof:name":"Investor's Title",
    "wof:placetype":"venue"
},
  "geometry": {"coordinates":[-82.550129,35.600416],"type":"Point"}
}