{
  "type": "Feature",
  "properties": {
    "addr:full":"2140 Grierview Ln Charlotte NC 28213",
    "addr:housenumber":"2140",
    "addr:postcode":"28213",
    "addr:street":"Grierview Ln",
    "iso:country":"US",
    "sg:address":"2140 Grierview Ln",
    "sg:city":"Charlotte",
    "sg:classifiers":[
        {
            "category":"Building & Trades",
            "subcategory":"Cleaning & Sanitation",
            "type":"Services"
        }
    ],
    "sg:phone":"+1   ",
    "sg:postcode":"28213",
    "sg:province":"NC",
    "sg:tags":[
        "maintenance"
    ],
    "wof:name":"Deluxe Cleaning Solutions",
    "wof:placetype":"venue"
},
  "geometry": {"coordinates":[-80.742699,35.265488],"type":"Point"}
}