{
  "type": "Feature",
  "properties": {
    "addr:full":"18107 Watercraft Pl Cornelius NC 28031",
    "addr:postcode":"18107;28031",
    "addr:street":"Pl",
    "iso:country":"US",
    "sg:address":"18107 Watercraft Pl",
    "sg:city":"Cornelius",
    "sg:classifiers":[
        {
            "category":"Banks & Credit Unions",
            "subcategory":"Investment Brokerage",
            "type":"Services"
        }
    ],
    "sg:phone":"+1 704 892 4828",
    "sg:postcode":"28031",
    "sg:province":"NC",
    "sg:tags":[
        "advisory"
    ],
    "wof:name":"Lakeside Financial Svcs LLC",
    "wof:placetype":"venue"
},
  "geometry": {"coordinates":[-80.922061,35.460943],"type":"Point"}
}