{
  "type": "Feature",
  "properties": {
    "addr:full":"816 Roanoke Dr Cary NC 27513",
    "addr:housenumber":"816",
    "addr:postcode":"27513",
    "addr:street":"Roanoke Dr",
    "iso:country":"US",
    "sg:address":"816 Roanoke Dr",
    "sg:city":"Cary",
    "sg:classifiers":[
        {
            "category":"Building & Trades",
            "subcategory":"Construction",
            "type":"Services"
        }
    ],
    "sg:phone":"+1 919 427 2920",
    "sg:postcode":"27513",
    "sg:province":"NC",
    "sg:tags":[
        "house"
    ],
    "wof:name":"Highland Construction Co Inc",
    "wof:placetype":"venue"
},
  "geometry": {"coordinates":[-78.78171399999999,35.799589],"type":"Point"}
}