{
  "type": "Feature",
  "properties": {
    "iso:country":"US",
    "sg:address":"1948 US Hwy 158",
    "sg:city":"Mocksville",
    "sg:classifiers":[
        {
            "category":"Building & Trades",
            "subcategory":"Landscaping Services",
            "type":"Services"
        }
    ],
    "sg:phone":"+1 336 751 4500",
    "sg:postcode":"27028",
    "sg:province":"NC",
    "sg:tags":[
        "landscape"
    ],
    "wof:name":"Lonnie R McCulloh",
    "wof:placetype":"venue"
},
  "geometry": {"coordinates":[-80.54569600000001,35.929069],"type":"Point"}
}