{
  "type": "Feature",
  "properties": {
    "iso:country":"US",
    "sg:address":"48405 Gold Branch Rd",
    "sg:city":"Richfield",
    "sg:classifiers":[
        {
            "category":"Real Estate",
            "subcategory":"Surveying",
            "type":"Services"
        }
    ],
    "sg:phone":"+1 704 983 1377",
    "sg:postcode":"28137",
    "sg:province":"NC",
    "sg:tags":[
        "surveyor"
    ],
    "sg:website":"www.surveytech.net",
    "wof:name":"Surveytech",
    "wof:placetype":"venue"
},
  "geometry": {"coordinates":[-80.252016,35.487211],"type":"Point"}
}