{
  "type": "Feature",
  "properties": {
    "iso:country":"US",
    "sg:address":"500 Center St",
    "sg:city":"Asheville",
    "sg:classifiers":[
        {
            "category":"Professional",
            "type":"Services"
        }
    ],
    "sg:phone":"+1 828 225 0248",
    "sg:postcode":"28803",
    "sg:province":"NC",
    "sg:tags":[
        "establishment"
    ],
    "wof:name":"A2c",
    "wof:placetype":"venue"
},
  "geometry": {"coordinates":[-82.537046,35.551716],"type":"Point"}
}