{
  "type": "Feature",
  "properties": {
    "iso:country":"US",
    "sg:address":"2021 Woodland Ave",
    "sg:city":"Sanford",
    "sg:classifiers":[
        {
            "category":"Organizations",
            "subcategory":"Religious Organization",
            "type":"Services"
        }
    ],
    "sg:phone":"+1 919 542 5519",
    "sg:postcode":"27330",
    "sg:province":"NC",
    "sg:tags":[
        "church"
    ],
    "wof:name":"Bible Baptist Church",
    "wof:placetype":"venue"
},
  "geometry": {"coordinates":[-79.158748,35.460824],"type":"Point"}
}