{
  "type": "Feature",
  "properties": {
    "iso:country":"US",
    "sg:address":"175 Weaverville Hwy",
    "sg:city":"Asheville",
    "sg:classifiers":[
        {
            "category":"Building & Trades",
            "subcategory":"Electrical",
            "type":"Services"
        }
    ],
    "sg:phone":"+1 828 658 9498",
    "sg:postcode":"28804",
    "sg:province":"NC",
    "sg:tags":[
        "electric",
        "contractor"
    ],
    "wof:name":"Paco Electric",
    "wof:placetype":"venue"
},
  "geometry": {"coordinates":[-82.581121,35.649062],"type":"Point"}
}