{
  "type": "Feature",
  "properties": {
    "iso:country":"US",
    "sg:address":"504 Radar Rd",
    "sg:city":"Greensboro",
    "sg:classifiers":[
        {
            "category":"Wholesale",
            "subcategory":"Construction Materials",
            "type":"Manufacturing & Wholesale Goods"
        }
    ],
    "sg:phone":"+1 336 808 3625",
    "sg:postcode":"27410",
    "sg:province":"NC",
    "sg:tags":[
        "repair"
    ],
    "wof:name":"Cannon Dock & Door Inc",
    "wof:placetype":"venue"
},
  "geometry": {"coordinates":[-79.92210799999999,36.096057],"type":"Point"}
}