{
  "type": "Feature",
  "properties": {
    "iso:country":"US",
    "sg:address":"4 Celtic Ct",
    "sg:city":"Arden",
    "sg:classifiers":[
        {
            "category":"Food & Beverages",
            "subcategory":"Specialty",
            "type":"Retail Goods"
        }
    ],
    "sg:phone":"+1 828 299 9005",
    "sg:postcode":"28786",
    "sg:province":"NC",
    "sg:tags":[
        "health",
        "diet"
    ],
    "sg:website":"www.celticseasalt.com",
    "wof:name":"Grain & Salt Society",
    "wof:placetype":"venue"
},
  "geometry": {"coordinates":[-82.983407,35.476651],"type":"Point"}
}