{
  "type": "Feature",
  "properties": {
    "addr:full":"4117 Sudbury Rd Charlotte NC 28205",
    "addr:housenumber":"4117",
    "addr:postcode":"28205",
    "addr:street":"Sudbury Rd",
    "iso:country":"US",
    "sg:address":"4117 Sudbury Rd",
    "sg:city":"Charlotte",
    "sg:classifiers":[
        {
            "category":"Arts & Performance",
            "subcategory":"Theater",
            "type":"Entertainment"
        }
    ],
    "sg:phone":"+1   ",
    "sg:postcode":"28205",
    "sg:province":"NC",
    "sg:tags":[
        "group"
    ],
    "wof:name":"A Sound Connection",
    "wof:placetype":"venue"
},
  "geometry": {"coordinates":[-80.75615500000001,35.222507],"type":"Point"}
}