{
  "type": "Feature",
  "properties": {
    "iso:country":"US",
    "sg:address":"102 N Reilly Rd",
    "sg:city":"Fayetteville",
    "sg:classifiers":[
        {
            "category":"Banks & Credit Unions",
            "subcategory":"Bank",
            "type":"Services"
        }
    ],
    "sg:phone":"+1 910 864 6831",
    "sg:postcode":"28303",
    "sg:province":"NC",
    "sg:tags":[
        "cashing",
        "check"
    ],
    "wof:name":"Nationwide Money Svc",
    "wof:placetype":"venue"
},
  "geometry": {"coordinates":[-79.010108,35.082863],"type":"Point"}
}