{
  "type": "Feature",
  "properties": {
    "addr:full":"750 Cabarrus Ave W Concord NC 28027",
    "addr:housenumber":"750",
    "addr:postcode":"28027",
    "addr:street":"Cabarrus Ave W",
    "iso:country":"US",
    "sg:address":"750 Cabarrus Ave W",
    "sg:city":"Concord",
    "sg:classifiers":[
        {
            "category":"Restaurant",
            "type":"Food & Drink"
        }
    ],
    "sg:menulink":"http://www.allmenus.com/nc/poplar-tent/153197-bojangles/menu/",
    "sg:phone":"+1 704 788 9131",
    "sg:postcode":"28027",
    "sg:province":"NC",
    "sg:tags":[
        "chicken",
        "sandwich",
        "american"
    ],
    "wof:name":"Bojangle's",
    "wof:placetype":"venue"
},
  "geometry": {"coordinates":[-80.609178,35.396636],"type":"Point"}
}