{
  "type": "Feature",
  "properties": {
    "iso:country":"US",
    "sg:address":"701 N James St",
    "sg:city":"Goldsboro",
    "sg:classifiers":[
        {
            "category":"Bars & Pubs",
            "type":"Food & Drink"
        }
    ],
    "sg:phone":"+1 919 735 0090",
    "sg:postcode":"27530",
    "sg:province":"NC",
    "wof:name":"Charleen's Corner Tavern",
    "wof:placetype":"venue"
},
  "geometry": {"coordinates":[-77.994906,35.392624],"type":"Point"}
}