{
  "type": "Feature",
  "properties": {
    "iso:country":"US",
    "sg:address":"123 Grassy Knob Rd",
    "sg:city":"Union Grove",
    "sg:classifiers":[
        {
            "category":"Professional",
            "subcategory":"Business Services",
            "type":"Services"
        }
    ],
    "sg:phone":"+1   ",
    "sg:postcode":"28689",
    "sg:province":"NC",
    "wof:name":"Felts Enterprises LLC",
    "wof:placetype":"venue"
},
  "geometry": {"coordinates":[-80.924261,36.036231],"type":"Point"}
}