{
  "type": "Feature",
  "properties": {
    "iso:country":"US",
    "sg:address":"14 Rosebay Ln",
    "sg:city":"Greensboro",
    "sg:classifiers":[
        {
            "category":"Shopping",
            "subcategory":"Gifts & Souvenirs",
            "type":"Retail Goods"
        }
    ],
    "sg:phone":"+1 336 574 1430",
    "sg:postcode":"27455",
    "sg:province":"NC",
    "wof:name":"Gift & Blessing",
    "wof:placetype":"venue"
},
  "geometry": {"coordinates":[-79.808758,36.146597],"type":"Point"}
}