{
  "type": "Feature",
  "properties": {
    "iso:country":"US",
    "sg:address":"1798 Possum Trot Rd",
    "sg:city":"New Bern",
    "sg:classifiers":[
        {
            "category":"Building & Trades",
            "subcategory":"Construction",
            "type":"Services"
        }
    ],
    "sg:phone":"+1 252 638 4738",
    "sg:postcode":"28562",
    "sg:province":"NC",
    "sg:tags":[
        "nonresidential"
    ],
    "wof:name":"Sharps Construction",
    "wof:placetype":"venue"
},
  "geometry": {"coordinates":[-77.084587,35.064453],"type":"Point"}
}