{
  "type": "Feature",
  "properties": {
    "addr:full":"5380 Willow Green Rd Farmville NC 27828",
    "addr:housenumber":"5380",
    "addr:postcode":"27828",
    "addr:street":"Willow Green Rd",
    "iso:country":"US",
    "sg:address":"5380 Willow Green Rd",
    "sg:city":"Farmville",
    "sg:phone":"+1 252 753 5565",
    "sg:postcode":"27828",
    "sg:province":"NC",
    "sg:tags":[
        "farm",
        "soybean"
    ],
    "wof:name":"James Stroud",
    "wof:placetype":"venue"
},
  "geometry": {"coordinates":[-77.553494,35.516983],"type":"Point"}
}