{
  "type": "Feature",
  "properties": {
    "iso:country":"US",
    "sg:address":"1111 Birch Tree Way",
    "sg:city":"Greensboro",
    "sg:classifiers":[
        {
            "category":"Shopping",
            "subcategory":"Clothing, Apparel, & Fashions",
            "type":"Retail Goods"
        }
    ],
    "sg:phone":"+1 336 856 7682",
    "sg:postcode":"27410",
    "sg:province":"NC",
    "sg:tags":[
        "tailor"
    ],
    "wof:name":"Le's Professional Tailoring",
    "wof:placetype":"venue"
},
  "geometry": {"coordinates":[-79.900271,36.104554],"type":"Point"}
}