{
  "type": "Feature",
  "properties": {
    "addr:full":"521 E Morehead St Charlotte NC 28202",
    "addr:housenumber":"521",
    "addr:postcode":"28202",
    "addr:street":"E Morehead St",
    "iso:country":"US",
    "sg:address":"521 E Morehead St",
    "sg:city":"Charlotte",
    "sg:classifiers":[
        {
            "category":"Professional",
            "subcategory":"Advertising",
            "type":"Services"
        }
    ],
    "sg:phone":"+1 704 332 9071",
    "sg:postcode":"28202",
    "sg:province":"NC",
    "sg:tags":[
        "counselor"
    ],
    "sg:website":"www.wwlcreative.com",
    "wof:name":"WRAY-Ward-Laseter",
    "wof:placetype":"venue"
},
  "geometry": {"coordinates":[-80.84672500000001,35.216234],"type":"Point"}
}