{
  "type": "Feature",
  "properties": {
    "addr:full":"601 Normandy St Cary NC 27511",
    "addr:housenumber":"601",
    "addr:postcode":"27511",
    "addr:street":"Normandy St",
    "iso:country":"US",
    "sg:address":"601 Normandy St",
    "sg:city":"Cary",
    "sg:classifiers":[
        {
            "category":"Professional",
            "subcategory":"Management & Consulting",
            "type":"Services"
        }
    ],
    "sg:phone":"+1   ",
    "sg:postcode":"27511",
    "sg:province":"NC",
    "sg:tags":[
        "business"
    ],
    "wof:name":"Dynamic Alliances",
    "wof:placetype":"venue"
},
  "geometry": {"coordinates":[-78.794923,35.777863],"type":"Point"}
}