{
  "type": "Feature",
  "properties": {
    "iso:country":"US",
    "sg:address":"1062 Sumac Ln",
    "sg:city":"Granite Falls",
    "sg:classifiers":[
        {
            "category":"Manufacturing",
            "subcategory":"Lumber",
            "type":"Manufacturing & Wholesale Goods"
        }
    ],
    "sg:phone":"+1 828 728 3754",
    "sg:postcode":"28630",
    "sg:province":"NC",
    "sg:tags":[
        "product",
        "forest",
        "gathering"
    ],
    "wof:name":"Jetts Investments LLC",
    "wof:placetype":"venue"
},
  "geometry": {"coordinates":[-81.528041,35.800235],"type":"Point"}
}