{
  "type": "Feature",
  "properties": {
    "iso:country":"US",
    "sg:address":"2830 Industrial Dr",
    "sg:city":"Raleigh",
    "sg:classifiers":[
        {
            "category":"Wholesale",
            "subcategory":"Apparel",
            "type":"Manufacturing & Wholesale Goods"
        }
    ],
    "sg:phone":"+1 919 821 9488",
    "sg:postcode":"27609",
    "sg:province":"NC",
    "sg:tags":[
        "shirt",
        "t",
        "sweat"
    ],
    "wof:name":"Great American T's & Sweats",
    "wof:placetype":"venue"
},
  "geometry": {"coordinates":[-78.62029800000001,35.817561],"type":"Point"}
}