{
  "type": "Feature",
  "properties": {
    "iso:country":"US",
    "sg:address":"10700 Kettering Dr",
    "sg:city":"Charlotte",
    "sg:classifiers":[
        {
            "category":"Sports & Exercise",
            "subcategory":"Gym",
            "type":"Entertainment"
        }
    ],
    "sg:phone":"+1 704 541 1246",
    "sg:postcode":"28226",
    "sg:province":"NC",
    "sg:tags":[
        "personal",
        "trainer"
    ],
    "wof:name":"All Body Systems",
    "wof:placetype":"venue"
},
  "geometry": {"coordinates":[-80.861634,35.090261],"type":"Point"}
}