{
  "type": "Feature",
  "properties": {
    "iso:country":"US",
    "sg:address":"704 E 7th St",
    "sg:city":"Charlotte",
    "sg:classifiers":[
        {
            "category":"Building & Trades",
            "subcategory":"Equipment Rental",
            "type":"Services"
        }
    ],
    "sg:phone":"+1 704 378 6804",
    "sg:postcode":"28202",
    "sg:province":"NC",
    "sg:tags":[
        "leasing"
    ],
    "wof:name":"Bovis Lend Lease Inc",
    "wof:placetype":"venue"
},
  "geometry": {"coordinates":[-80.83304,35.22346],"type":"Point"}
}