{
  "type": "Feature",
  "properties": {
    "addr:full":"626 Channel Blvd Topsail Beach NC 28445",
    "addr:housenumber":"626",
    "addr:postcode":"28445",
    "addr:street":"Channel Blvd",
    "iso:country":"US",
    "sg:address":"626 Channel Blvd",
    "sg:city":"Topsail Beach",
    "sg:classifiers":[
        {
            "category":"Travel",
            "subcategory":"Hotels & Motels",
            "type":"Entertainment"
        }
    ],
    "sg:phone":"+1 910 328 7751",
    "sg:postcode":"28445",
    "sg:province":"NC",
    "wof:name":"Breezeway Motel",
    "wof:placetype":"venue"
},
  "geometry": {"coordinates":[-77.62791900000001,34.368751],"type":"Point"}
}