{
  "type": "Feature",
  "properties": {
    "iso:country":"US",
    "sg:address":"116 E Main St",
    "sg:city":"Beulaville",
    "sg:classifiers":[
        {
            "category":"Health Services",
            "subcategory":"Doctor",
            "type":"Services"
        }
    ],
    "sg:phone":"+1 910 298 6550",
    "sg:postcode":"28518",
    "sg:province":"NC",
    "sg:tags":[
        "physician",
        "surgeon"
    ],
    "wof:name":"Kinston Pediatric",
    "wof:placetype":"venue"
},
  "geometry": {"coordinates":[-77.77260699999999,34.923459],"type":"Point"}
}