{
  "type": "Feature",
  "properties": {
    "iso:country":"US",
    "sg:address":"719 E Whitaker Mill Rd",
    "sg:city":"Raleigh",
    "sg:classifiers":[
        {
            "category":"Shopping",
            "subcategory":"Clothing, Apparel, & Fashions",
            "type":"Retail Goods"
        }
    ],
    "sg:phone":"+1 919 856 0448",
    "sg:postcode":"27608",
    "sg:province":"NC",
    "wof:name":"Unique Batik",
    "wof:placetype":"venue"
},
  "geometry": {"coordinates":[-78.62632000000001,35.807421],"type":"Point"}
}