{
  "type": "Feature",
  "properties": {
    "iso:country":"US",
    "sg:address":"3906 Hickory Grove Rd",
    "sg:city":"Mount Holly",
    "sg:classifiers":[
        {
            "category":"Home & Garden",
            "subcategory":"Building Materials",
            "type":"Retail Goods"
        }
    ],
    "sg:phone":"+1 704 820 9375",
    "sg:postcode":"28120",
    "sg:province":"NC",
    "wof:name":"Double D",
    "wof:placetype":"venue"
},
  "geometry": {"coordinates":[-81.07880400000001,35.305089],"type":"Point"}
}