{
  "type": "Feature",
  "properties": {
    "iso:country":"US",
    "sg:address":"755 N Main St",
    "sg:city":"Hendersonville",
    "sg:classifiers":[
        {
            "category":"Personal",
            "type":"Services"
        }
    ],
    "sg:phone":"+1 828 699 0192",
    "sg:postcode":"28792",
    "sg:province":"NC",
    "sg:tags":[
        "therapist",
        "massage"
    ],
    "wof:name":"ADP Massage Therapy",
    "wof:placetype":"venue"
},
  "geometry": {"coordinates":[-82.461018,35.319806],"type":"Point"}
}