{
  "type": "Feature",
  "properties": {
    "addr:full":"3916 Spies Rd Star NC 27356",
    "addr:housenumber":"3916",
    "addr:postcode":"27356",
    "addr:street":"Spies Rd",
    "iso:country":"US",
    "sg:address":"3916 Spies Rd",
    "sg:city":"Star",
    "sg:classifiers":[
        {
            "category":"Home & Garden",
            "subcategory":"Home Furnishings",
            "type":"Retail Goods"
        }
    ],
    "sg:phone":"+1 910 428 1450",
    "sg:postcode":"27356",
    "sg:province":"NC",
    "sg:tags":[
        "pottery",
        "product",
        "mfg"
    ],
    "wof:name":"Earth Avenue",
    "wof:placetype":"venue"
},
  "geometry": {"coordinates":[-79.70743299999999,35.418042],"type":"Point"}
}