{
  "type": "Feature",
  "properties": {
    "addr:full":"725 Main St North Wilkesboro NC 28659",
    "addr:housenumber":"725",
    "addr:postcode":"28659",
    "addr:street":"Main St",
    "iso:country":"US",
    "sg:address":"725 Main St",
    "sg:city":"North Wilkesboro",
    "sg:classifiers":[
        {
            "category":"Government",
            "subcategory":"Office",
            "type":"Public Place"
        }
    ],
    "sg:phone":"+1 336 838 8412",
    "sg:postcode":"28659",
    "sg:province":"NC",
    "sg:tags":[
        "state",
        "taxation"
    ],
    "wof:name":"Revenue Dept",
    "wof:placetype":"venue"
},
  "geometry": {"coordinates":[-81.143804,36.160483],"type":"Point"}
}