{
  "type": "Feature",
  "properties": {
    "addr:full":"279 Shiloh Rd Forest City NC 28043",
    "addr:housenumber":"279",
    "addr:postcode":"28043",
    "addr:street":"Shiloh Rd",
    "iso:country":"US",
    "sg:address":"279 Shiloh Rd",
    "sg:city":"Forest City",
    "sg:classifiers":[
        {
            "category":"Professional",
            "type":"Services"
        }
    ],
    "sg:phone":"+1 828 248 9655",
    "sg:postcode":"28043",
    "sg:province":"NC",
    "wof:name":"Valentine Spa Inc",
    "wof:placetype":"venue"
},
  "geometry": {"coordinates":[-81.91304100000001,35.296889],"type":"Point"}
}