{
  "type": "Feature",
  "properties": {
    "iso:country":"US",
    "sg:address":"915 Brookstown Ave NW",
    "sg:city":"Winston Salem",
    "sg:classifiers":[
        {
            "category":"Professional",
            "subcategory":"Business Services",
            "type":"Services"
        }
    ],
    "sg:phone":"+1 336 725 5700",
    "sg:postcode":"27101",
    "sg:province":"NC",
    "sg:tags":[
        "interior",
        "consultant",
        "design",
        "decorator"
    ],
    "wof:name":"Expressions Home Decor",
    "wof:placetype":"venue"
},
  "geometry": {"coordinates":[-80.256111,36.096237],"type":"Point"}
}