{
  "type": "Feature",
  "properties": {
    "iso:country":"US",
    "sg:address":"1317 Headquarters Dr",
    "sg:city":"Greensboro",
    "sg:classifiers":[
        {
            "category":"Wholesale",
            "subcategory":"Home Furnishings",
            "type":"Manufacturing & Wholesale Goods"
        }
    ],
    "sg:phone":"+1 336 275 9975",
    "sg:postcode":"27405",
    "sg:province":"NC",
    "sg:tags":[
        "lamp"
    ],
    "wof:name":"Burch Carr LTD",
    "wof:placetype":"venue"
},
  "geometry": {"coordinates":[-79.76737300000001,36.084132],"type":"Point"}
}