{
  "type": "Feature",
  "properties": {
    "addr:full":"1000 Lancaster Ave Monroe NC 28112",
    "addr:housenumber":"1000",
    "addr:postcode":"28112",
    "addr:street":"Lancaster Ave",
    "iso:country":"US",
    "sg:address":"1000 Lancaster Ave",
    "sg:city":"Monroe",
    "sg:classifiers":[
        {
            "category":"Restaurant",
            "type":"Food & Drink"
        }
    ],
    "sg:phone":"+1 704 283 1123",
    "sg:postcode":"28112",
    "sg:province":"NC",
    "wof:name":"Palace Restaurants",
    "wof:placetype":"venue"
},
  "geometry": {"coordinates":[-80.557585,34.974547],"type":"Point"}
}