{
  "type": "Feature",
  "properties": {
    "iso:country":"US",
    "sg:address":"3510 Mount Holly Huntersville Rd",
    "sg:city":"Charlotte",
    "sg:classifiers":[
        {
            "category":"Restaurant",
            "type":"Food & Drink"
        }
    ],
    "sg:menulink":"http://www.allmenus.com/nc/charlotte/153173-bojangles/menu/",
    "sg:phone":"+1 704 398 1101",
    "sg:postcode":"28216",
    "sg:province":"NC",
    "sg:tags":[
        "chicken",
        "sandwich",
        "american"
    ],
    "wof:name":"Bojangle's",
    "wof:placetype":"venue"
},
  "geometry": {"coordinates":[-80.947594,35.323769],"type":"Point"}
}