{
  "type": "Feature",
  "properties": {
    "addr:full":"4119 Hearthside Dr Wilmington NC 28412",
    "addr:housenumber":"4119",
    "addr:postcode":"28412",
    "addr:street":"Hearthside Dr",
    "iso:country":"US",
    "sg:address":"4119 Hearthside Dr",
    "sg:city":"Wilmington",
    "sg:classifiers":[
        {
            "category":"Taxi",
            "type":"Transportation"
        }
    ],
    "sg:phone":"+1 910 200 4002",
    "sg:postcode":"28412",
    "sg:province":"NC",
    "sg:tags":[
        "taxicab"
    ],
    "wof:name":"Water Taxi Inc",
    "wof:placetype":"venue"
},
  "geometry": {"coordinates":[-77.90264500000001,34.173156],"type":"Point"}
}