{
  "type": "Feature",
  "properties": {
    "addr:full":"1519 Central Ave Charlotte NC 28205",
    "addr:housenumber":"1519",
    "addr:postcode":"28205",
    "addr:street":"Central Ave",
    "iso:country":"US",
    "sg:address":"1519 Central Ave",
    "sg:city":"Charlotte",
    "sg:classifiers":[
        {
            "category":"Retail",
            "subcategory":"Repair Shop",
            "type":"Services"
        }
    ],
    "sg:phone":"+1 704 376 7754",
    "sg:postcode":"28205",
    "sg:province":"NC",
    "sg:tags":[
        "reupholstery",
        "furniture"
    ],
    "wof:name":"Design Upholstery",
    "wof:placetype":"venue"
},
  "geometry": {"coordinates":[-80.812427,35.22042],"type":"Point"}
}