{
  "type": "Feature",
  "properties": {
    "iso:country":"US",
    "sg:address":"3825 W Market St",
    "sg:city":"Greensboro",
    "sg:classifiers":[
        {
            "category":"Banks & Credit Unions",
            "subcategory":"Investment Brokerage",
            "type":"Services"
        }
    ],
    "sg:phone":"+1 336 856 1897",
    "sg:postcode":"27407",
    "sg:province":"NC",
    "sg:tags":[
        "funds",
        "mutual",
        "security"
    ],
    "wof:name":"George S Mc Clellan",
    "wof:placetype":"venue"
},
  "geometry": {"coordinates":[-79.849746,36.070927],"type":"Point"}
}