{
  "type": "Feature",
  "properties": {
    "iso:country":"US",
    "sg:address":"4623 Tom Starnes Rd",
    "sg:city":"Waxhaw",
    "sg:classifiers":[
        {
            "category":"Building & Trades",
            "subcategory":"Construction",
            "type":"Services"
        }
    ],
    "sg:phone":"+1 704 843 4766",
    "sg:postcode":"28173",
    "sg:province":"NC",
    "sg:tags":[
        "house"
    ],
    "wof:name":"Home Remedies",
    "wof:placetype":"venue"
},
  "geometry": {"coordinates":[-80.654349,34.852803],"type":"Point"}
}