{
  "type": "Feature",
  "properties": {
    "iso:country":"US",
    "sg:address":"129 Badin Shores Resort Dr",
    "sg:city":"New London",
    "sg:classifiers":[
        {
            "category":"Recreation",
            "subcategory":"Marina",
            "type":"Entertainment"
        }
    ],
    "sg:phone":"+1 336 461 2733",
    "sg:postcode":"28127",
    "sg:province":"NC",
    "sg:tags":[
        "storage",
        "boat"
    ],
    "wof:name":"D & P Rentals",
    "wof:placetype":"venue"
},
  "geometry": {"coordinates":[-80.12674699999999,35.486773],"type":"Point"}
}