{
  "type": "Feature",
  "properties": {
    "iso:country":"US",
    "sg:address":"2240 Martin Luther King Jr Dr",
    "sg:city":"Greensboro",
    "sg:classifiers":[
        {
            "category":"Restaurant",
            "type":"Food & Drink"
        }
    ],
    "sg:menulink":"http://www.allmenus.com/nc/gilmer/191093-burger-king/menu/",
    "sg:phone":"+1 336 370 9507",
    "sg:postcode":"27406",
    "sg:province":"NC",
    "sg:tags":[
        "burger",
        "american"
    ],
    "wof:name":"Burger King",
    "wof:placetype":"venue"
},
  "geometry": {"coordinates":[-79.773651,36.042755],"type":"Point"}
}