{
  "type": "Feature",
  "properties": {
    "addr:full":"7622 E Langley Rd Elm City NC 27822",
    "addr:housenumber":"7622",
    "addr:postcode":"27822",
    "addr:street":"E Langley Rd",
    "iso:country":"US",
    "sg:address":"7622 E Langley Rd",
    "sg:city":"Elm City",
    "sg:classifiers":[
        {
            "category":"Wholesale",
            "subcategory":"Auto Parts",
            "type":"Manufacturing & Wholesale Goods"
        }
    ],
    "sg:phone":"+1 252 236 4127",
    "sg:postcode":"27822",
    "sg:province":"NC",
    "sg:tags":[
        "automobile",
        "rebuilt"
    ],
    "wof:name":"Cox Auto Salvage",
    "wof:placetype":"venue"
},
  "geometry": {"coordinates":[-77.788977,35.817311],"type":"Point"}
}