{
  "type": "Feature",
  "properties": {
    "iso:country":"US",
    "sg:address":"3907 Atlas Dr",
    "sg:city":"Charlotte",
    "sg:classifiers":[
        {
            "category":"Professional",
            "subcategory":"Management & Consulting",
            "type":"Services"
        }
    ],
    "sg:phone":"+1   ",
    "sg:postcode":"28269",
    "sg:province":"NC",
    "sg:tags":[
        "business"
    ],
    "wof:name":"Holliday Business Forms",
    "wof:placetype":"venue"
},
  "geometry": {"coordinates":[-80.83080699999999,35.289679],"type":"Point"}
}