{
  "type": "Feature",
  "properties": {
    "addr:full":"6729 E Independence Blvd Charlotte NC 28212",
    "addr:housenumber":"6729",
    "addr:postcode":"28212",
    "addr:street":"E Independence Blvd",
    "iso:country":"US",
    "sg:address":"6729 E Independence Blvd",
    "sg:city":"Charlotte",
    "sg:classifiers":[
        {
            "category":"Autos & Motor Vehicles",
            "subcategory":"Auto Supplies",
            "type":"Retail Goods"
        }
    ],
    "sg:phone":"+1 704 535 3493",
    "sg:postcode":"28212",
    "sg:province":"NC",
    "sg:tags":[
        "automobile",
        "tire",
        "repair"
    ],
    "wof:name":"Goodyear",
    "wof:placetype":"venue"
},
  "geometry": {"coordinates":[-80.742526,35.166944],"type":"Point"}
}