{
  "type": "Feature",
  "properties": {
    "iso:country":"US",
    "sg:address":"1767 Ashleys Grove Rd",
    "sg:city":"Conway",
    "sg:classifiers":[
        {
            "category":"Wholesale",
            "subcategory":"Non-durable Goods",
            "type":"Manufacturing & Wholesale Goods"
        }
    ],
    "sg:phone":"+1 252 587 0488",
    "sg:postcode":"27820",
    "sg:province":"NC",
    "sg:tags":[
        "advertising"
    ],
    "wof:name":"South Eastern Assoc Group",
    "wof:placetype":"venue"
},
  "geometry": {"coordinates":[-77.19129100000001,36.385375],"type":"Point"}
}