{
  "type": "Feature",
  "properties": {
    "iso:country":"US",
    "sg:address":"1906 E Dixon Blvd",
    "sg:city":"Shelby",
    "sg:classifiers":[
        {
            "category":"Autos & Motor Vehicles",
            "subcategory":"Fuel & Gas Station",
            "type":"Retail Goods"
        }
    ],
    "sg:phone":"+1 704 482 1445",
    "sg:postcode":"28152",
    "sg:province":"NC",
    "sg:tags":[
        "product",
        "petroleum"
    ],
    "wof:name":"A&W One Stop",
    "wof:placetype":"venue"
},
  "geometry": {"coordinates":[-81.483519,35.266785],"type":"Point"}
}