{
  "type": "Feature",
  "properties": {
    "iso:country":"US",
    "sg:address":"632 Northwoods Dr",
    "sg:city":"Cary",
    "sg:classifiers":[
        {
            "category":"Manufacturing",
            "subcategory":"Lumber",
            "type":"Manufacturing & Wholesale Goods"
        }
    ],
    "sg:phone":"+1 919 625 0755",
    "sg:postcode":"27513",
    "sg:province":"NC",
    "sg:tags":[
        "mill"
    ],
    "wof:name":"Delzer Construction",
    "wof:placetype":"venue"
},
  "geometry": {"coordinates":[-78.78800099999999,35.79708],"type":"Point"}
}