{
  "type": "Feature",
  "properties": {
    "iso:country":"US",
    "sg:address":"2250 Ivy Rd",
    "sg:city":"Greenville",
    "sg:classifiers":[
        {
            "category":"Retail",
            "subcategory":"Repair Shop",
            "type":"Services"
        }
    ],
    "sg:phone":"+1 252 355 6766",
    "sg:postcode":"27858",
    "sg:province":"NC",
    "sg:tags":[
        "appliance"
    ],
    "wof:name":"All Around Repair",
    "wof:placetype":"venue"
},
  "geometry": {"coordinates":[-77.325199,35.504783],"type":"Point"}
}