{
  "type": "Feature",
  "properties": {
    "addr:full":"3531 New Bern Hwy Jacksonville NC 28546",
    "addr:housenumber":"3531",
    "addr:postcode":"28546",
    "addr:street":"New Bern Hwy",
    "iso:country":"US",
    "sg:address":"3531 New Bern Hwy",
    "sg:city":"Jacksonville",
    "sg:classifiers":[
        {
            "category":"Food & Beverages",
            "subcategory":"Groceries & Convenience Stores",
            "type":"Retail Goods"
        }
    ],
    "sg:phone":"+1 910 937 7737",
    "sg:postcode":"28546",
    "sg:province":"NC",
    "sg:tags":[
        "grocer"
    ],
    "wof:name":"Xpress Grocery",
    "wof:placetype":"venue"
},
  "geometry": {"coordinates":[-77.360732,34.80092],"type":"Point"}
}