{
  "type": "Feature",
  "properties": {
    "iso:country":"US",
    "sg:address":"603 Ocean Hwy W",
    "sg:city":"Supply",
    "sg:classifiers":[
        {
            "category":"Retail",
            "subcategory":"Funeral Services",
            "type":"Services"
        }
    ],
    "sg:phone":"+1 910 754 6848",
    "sg:postcode":"28462",
    "sg:province":"NC",
    "sg:tags":[
        "director"
    ],
    "wof:name":"Coble Ward Smith Funueral Svc",
    "wof:placetype":"venue"
},
  "geometry": {"coordinates":[-78.29001100000001,34.011273],"type":"Point"}
}