{
  "type": "Feature",
  "properties": {
    "iso:country":"US",
    "sg:address":"601 Nichole Ln",
    "sg:city":"Rocky Mount",
    "sg:classifiers":[
        {
            "category":"Building & Trades",
            "subcategory":"Equipment Rental",
            "type":"Services"
        }
    ],
    "sg:phone":"+1   ",
    "sg:postcode":"27803",
    "sg:province":"NC",
    "wof:name":"Steven N Broughton Rentals LLC",
    "wof:placetype":"venue"
},
  "geometry": {"coordinates":[-77.85196999999999,35.948731],"type":"Point"}
}