{
  "type": "Feature",
  "properties": {
    "addr:full":"705 Wesley Pines Rd Lumberton NC 28358",
    "addr:housenumber":"705",
    "addr:postcode":"28358",
    "addr:street":"Wesley Pines Rd",
    "iso:country":"US",
    "sg:address":"705 Wesley Pines Rd",
    "sg:city":"Lumberton",
    "sg:classifiers":[
        {
            "category":"Utilities",
            "subcategory":"Telephone",
            "type":"Services"
        },
        {
            "category":"Professional",
            "subcategory":"Computer Services",
            "type":"Services"
        }
    ],
    "sg:phone":"+1 910 618 9790",
    "sg:postcode":"28358",
    "sg:province":"NC",
    "sg:tags":[
        "communications"
    ],
    "wof:name":"Carolina Online",
    "wof:placetype":"venue"
},
  "geometry": {"coordinates":[-78.999796,34.656802],"type":"Point"}
}