{
  "type": "Feature",
  "properties": {
    "addr:full":"1601 Lane St SE Wilson NC 27893",
    "addr:housenumber":"1601",
    "addr:postcode":"27893",
    "addr:street":"Lane St Se",
    "iso:country":"US",
    "sg:address":"1601 Lane St SE",
    "sg:city":"Wilson",
    "sg:classifiers":[
        {
            "category":"Organizations",
            "subcategory":"Religious Organization",
            "type":"Services"
        }
    ],
    "sg:phone":"+1 252 243 2367",
    "sg:postcode":"27893",
    "sg:province":"NC",
    "sg:tags":[
        "church"
    ],
    "wof:name":"Tabernacle Of Prayer For All",
    "wof:placetype":"venue"
},
  "geometry": {"coordinates":[-77.897049,35.712066],"type":"Point"}
}