{
  "type": "Feature",
  "properties": {
    "addr:full":"4503 Crystal Creek Ct Indian Trail NC 28079",
    "addr:housenumber":"4503",
    "addr:postcode":"28079",
    "addr:street":"Crystal Creek Ct",
    "iso:country":"US",
    "sg:address":"4503 Crystal Creek Ct",
    "sg:city":"Indian Trail",
    "sg:classifiers":[
        {
            "category":"Professional",
            "type":"Services"
        }
    ],
    "sg:phone":"+1 704 882 5292",
    "sg:postcode":"28079",
    "sg:province":"NC",
    "wof:name":"Michael York Co Inc",
    "wof:placetype":"venue"
},
  "geometry": {"coordinates":[-80.63883199999999,35.080152],"type":"Point"}
}