{
  "type": "Feature",
  "properties": {
    "iso:country":"US",
    "sg:address":"5509 Suncrest Ct",
    "sg:city":"Charlotte",
    "sg:classifiers":[
        {
            "category":"Professional",
            "type":"Services"
        }
    ],
    "sg:phone":"+1 704 840 5556",
    "sg:postcode":"28215",
    "sg:province":"NC",
    "wof:name":"Ferrell Services-R & F Ent",
    "wof:placetype":"venue"
},
  "geometry": {"coordinates":[-80.665938,35.235286],"type":"Point"}
}