{
  "type": "Feature",
  "properties": {
    "iso:country":"US",
    "sg:address":"1118 Ramsey St",
    "sg:city":"Fayetteville",
    "sg:classifiers":[
        {
            "category":"Restaurant",
            "type":"Food & Drink"
        }
    ],
    "sg:phone":"+1 910 485 3644",
    "sg:postcode":"28301",
    "sg:province":"NC",
    "sg:tags":[
        "eating"
    ],
    "wof:name":"Hot Diggidy Dog",
    "wof:placetype":"venue"
},
  "geometry": {"coordinates":[-78.879766,35.070712],"type":"Point"}
}