{
  "type": "Feature",
  "properties": {
    "addr:full":"3601 S New Hope Rd Gastonia NC 28056",
    "addr:housenumber":"3601",
    "addr:postcode":"28056",
    "addr:street":"S New Hope Rd",
    "iso:country":"US",
    "sg:address":"3601 S New Hope Rd",
    "sg:city":"Gastonia",
    "sg:classifiers":[
        {
            "category":"Retail",
            "subcategory":"Laundry & Dry Cleaning",
            "type":"Services"
        }
    ],
    "sg:phone":"+1   ",
    "sg:postcode":"28056",
    "sg:province":"NC",
    "wof:name":"Steam Masters Inc",
    "wof:placetype":"venue"
},
  "geometry": {"coordinates":[-81.10120499999999,35.222989],"type":"Point"}
}