{
  "type": "Feature",
  "properties": {
    "iso:country":"US",
    "sg:address":"32 Windsor Cir",
    "sg:city":"Thomasville",
    "sg:classifiers":[
        {
            "category":"Manufacturing",
            "subcategory":"Apparel",
            "type":"Manufacturing & Wholesale Goods"
        }
    ],
    "sg:phone":"+1 336 472 5646",
    "sg:postcode":"27360",
    "sg:province":"NC",
    "wof:name":"Stitchworks Of Nc",
    "wof:placetype":"venue"
},
  "geometry": {"coordinates":[-80.10979,35.93354],"type":"Point"}
}