{
  "type": "Feature",
  "properties": {
    "iso:country":"US",
    "sg:address":"522 Plato Lee Rd",
    "sg:city":"Shelby",
    "sg:classifiers":[
        {
            "category":"Manufacturing",
            "subcategory":"Retail Goods",
            "type":"Manufacturing & Wholesale Goods"
        },
        {
            "category":"Wholesale",
            "subcategory":"Electrical",
            "type":"Manufacturing & Wholesale Goods"
        }
    ],
    "sg:phone":"+1 704 434 4820",
    "sg:postcode":"28150",
    "sg:province":"NC",
    "sg:tags":[
        "decoration",
        "light",
        "product",
        "christmas",
        "mfg"
    ],
    "sg:website":"www.carpenterdecorating.com",
    "wof:name":"Carpenter Decorating Company",
    "wof:placetype":"venue"
},
  "geometry": {"coordinates":[-81.62056200000001,35.314382],"type":"Point"}
}