{
  "type": "Feature",
  "properties": {
    "iso:country":"US",
    "sg:address":"405 Stanton Ct",
    "sg:city":"Winston Salem",
    "sg:classifiers":[
        {
            "category":"Shopping",
            "type":"Retail Goods"
        }
    ],
    "sg:phone":"+1 336 723 8066",
    "sg:postcode":"27106",
    "sg:province":"NC",
    "sg:tags":[
        "craft",
        "gallery",
        "dealer"
    ],
    "wof:name":"Fine Lines",
    "wof:placetype":"venue"
},
  "geometry": {"coordinates":[-80.30954800000001,36.133249],"type":"Point"}
}