{
  "type": "Feature",
  "properties": {
    "addr:full":"146 Panda Trl Waynesville NC 28785",
    "addr:housenumber":"146",
    "addr:postcode":"28785",
    "addr:street":"Panda Trl",
    "iso:country":"US",
    "sg:address":"146 Panda Trl",
    "sg:city":"Waynesville",
    "sg:classifiers":[
        {
            "category":"Real Estate",
            "subcategory":"Real Estate Agent",
            "type":"Services"
        }
    ],
    "sg:phone":"+1 828 452 0802",
    "sg:postcode":"28785",
    "sg:province":"NC",
    "wof:name":"Mountain Vu Rentals",
    "wof:placetype":"venue"
},
  "geometry": {"coordinates":[-82.955935,35.531201],"type":"Point"}
}