{
  "type": "Feature",
  "properties": {
    "addr:full":"313 Capistrane Dr Cary NC 27519",
    "addr:housenumber":"313",
    "addr:postcode":"27519",
    "addr:street":"Capistrane Dr",
    "iso:country":"US",
    "sg:address":"313 Capistrane Dr",
    "sg:city":"Cary",
    "sg:classifiers":[
        {
            "category":"Professional",
            "type":"Services"
        }
    ],
    "sg:phone":"+1 919 363 0607",
    "sg:postcode":"27519",
    "sg:province":"NC",
    "sg:tags":[
        "establishment"
    ],
    "wof:name":"Ashley Woods",
    "wof:placetype":"venue"
},
  "geometry": {"coordinates":[-78.874449,35.785558],"type":"Point"}
}