{
  "type": "Feature",
  "properties": {
    "addr:full":"111 Henry Ln Salisbury NC 28147",
    "addr:housenumber":"111",
    "addr:postcode":"28147",
    "addr:street":"Henry Ln",
    "iso:country":"US",
    "sg:address":"111 Henry Ln",
    "sg:city":"Salisbury",
    "sg:classifiers":[
        {
            "category":"Wholesale",
            "subcategory":"Sporting Goods",
            "type":"Manufacturing & Wholesale Goods"
        }
    ],
    "sg:phone":"+1 704 636 5588",
    "sg:postcode":"28147",
    "sg:province":"NC",
    "wof:name":"Jdi Sports Inc",
    "wof:placetype":"venue"
},
  "geometry": {"coordinates":[-80.506435,35.73059],"type":"Point"}
}