{
  "type": "Feature",
  "properties": {
    "addr:full":"4321 Medical Park Dr Durham NC 27704",
    "addr:housenumber":"4321",
    "addr:postcode":"27704",
    "addr:street":"Medical Park Dr",
    "iso:country":"US",
    "sg:address":"4321 Medical Park Dr",
    "sg:city":"Durham",
    "sg:classifiers":[
        {
            "category":"Building & Trades",
            "subcategory":"Construction",
            "type":"Services"
        }
    ],
    "sg:phone":"+1 919 471 2895",
    "sg:postcode":"27704",
    "sg:province":"NC",
    "sg:tags":[
        "general",
        "contractor"
    ],
    "sg:website":"www.gmhock.com",
    "wof:name":"G M Hock Construction Co",
    "wof:placetype":"venue"
},
  "geometry": {"coordinates":[-78.894949,36.048086],"type":"Point"}
}