{
  "type": "Feature",
  "properties": {
    "addr:full":"4200 Graham Newton Rd Raleigh NC 27606",
    "addr:housenumber":"4200",
    "addr:postcode":"27606",
    "addr:street":"Graham Newton Rd",
    "iso:country":"US",
    "sg:address":"4200 Graham Newton Rd",
    "sg:city":"Raleigh",
    "sg:classifiers":[
        {
            "category":"Professional",
            "subcategory":"Management & Consulting",
            "type":"Services"
        }
    ],
    "sg:phone":"+1   ",
    "sg:postcode":"27606",
    "sg:province":"NC",
    "sg:tags":[
        "business"
    ],
    "wof:name":"JKH Group Inc",
    "wof:placetype":"venue"
},
  "geometry": {"coordinates":[-78.73618500000001,35.693893],"type":"Point"}
}