{
  "type": "Feature",
  "properties": {
    "addr:full":"1800 Cannon Ave Charlotte NC 28269",
    "addr:housenumber":"1800",
    "addr:postcode":"28269",
    "addr:street":"Cannon Ave",
    "iso:country":"US",
    "sg:address":"1800 Cannon Ave",
    "sg:city":"Charlotte",
    "sg:classifiers":[
        {
            "category":"Professional",
            "subcategory":"Art Services",
            "type":"Services"
        }
    ],
    "sg:phone":"+1 704 509 2213",
    "sg:postcode":"28269",
    "sg:province":"NC",
    "sg:tags":[
        "agent",
        "artist"
    ],
    "wof:name":"Cord Management",
    "wof:placetype":"venue"
},
  "geometry": {"coordinates":[-80.804131,35.28022],"type":"Point"}
}