{
  "type": "Feature",
  "properties": {
    "addr:full":"104 Nc Highway 54 # C Carrboro NC 27510",
    "addr:housenumber":"104",
    "addr:postcode":"27510",
    "addr:street":"Nc Highway 54 # C",
    "iso:country":"US",
    "sg:address":"104 Nc Highway 54 # C",
    "sg:city":"Carrboro",
    "sg:classifiers":[
        {
            "category":"Restaurant",
            "type":"Food & Drink"
        }
    ],
    "sg:phone":"+1 919 929 9988",
    "sg:postcode":"27510",
    "sg:province":"NC",
    "sg:tags":[
        "chinese"
    ],
    "wof:name":"China Wok",
    "wof:placetype":"venue"
},
  "geometry": {"coordinates":[-79.098242,35.919075],"type":"Point"}
}