{
  "type": "Feature",
  "properties": {
    "addr:full":"1724 Corcus Ferry Rd Hampstead NC 28443",
    "addr:housenumber":"1724",
    "addr:postcode":"28443",
    "addr:street":"Corcus Ferry Rd",
    "iso:country":"US",
    "sg:address":"1724 Corcus Ferry Rd",
    "sg:city":"Hampstead",
    "sg:classifiers":[
        {
            "category":"Professional",
            "subcategory":"Business Services",
            "type":"Services"
        }
    ],
    "sg:phone":"+1   ",
    "sg:postcode":"28443",
    "sg:province":"NC",
    "wof:name":"Red Dog Enterprise LLC",
    "wof:placetype":"venue"
},
  "geometry": {"coordinates":[-77.680105,34.359229],"type":"Point"}
}