{
  "type": "Feature",
  "properties": {
    "addr:full":"5246 Greens Dairy Rd Raleigh NC 27616",
    "addr:housenumber":"5246",
    "addr:postcode":"27616",
    "addr:street":"Greens Dairy Rd",
    "iso:country":"US",
    "sg:address":"5246 Greens Dairy Rd",
    "sg:city":"Raleigh",
    "sg:classifiers":[
        {
            "category":"Utilities",
            "subcategory":"Electric",
            "type":"Services"
        }
    ],
    "sg:phone":"+1 919 876 1541",
    "sg:postcode":"27616",
    "sg:province":"NC",
    "sg:tags":[
        "company"
    ],
    "wof:name":"North Carolina Electric",
    "wof:placetype":"venue"
},
  "geometry": {"coordinates":[-78.577898,35.858762],"type":"Point"}
}