{
  "type": "Feature",
  "properties": {
    "addr:full":"1703 Mill Rd Pinetown NC 27889",
    "addr:housenumber":"1703",
    "addr:postcode":"27889",
    "addr:street":"Mill Rd",
    "iso:country":"US",
    "sg:address":"1703 Mill Rd",
    "sg:city":"Pinetown",
    "sg:classifiers":[
        {
            "category":"Wholesale",
            "subcategory":"Construction Materials",
            "type":"Manufacturing & Wholesale Goods"
        }
    ],
    "sg:phone":"+1 252 943 6805",
    "sg:postcode":"27889",
    "sg:province":"NC",
    "sg:tags":[
        "timberland",
        "company",
        "timber"
    ],
    "wof:name":"Cahoon Logging Inc",
    "wof:placetype":"venue"
},
  "geometry": {"coordinates":[-77.03083599999999,35.617121],"type":"Point"}
}