{
  "type": "Feature",
  "properties": {
    "addr:full":"4261 State Hwy 101 Newport NC 28570",
    "addr:housenumber":"4261",
    "addr:postcode":"28570",
    "addr:street":"State Hwy 101",
    "iso:country":"US",
    "sg:address":"4261 State Hwy 101",
    "sg:city":"Newport",
    "sg:classifiers":[
        {
            "category":"Government",
            "subcategory":"Office",
            "type":"Public Place"
        }
    ],
    "sg:phone":"+1 252 222 0860",
    "sg:postcode":"28570",
    "sg:province":"NC",
    "sg:tags":[
        "county"
    ],
    "wof:name":"Carteret County Elections",
    "wof:placetype":"venue"
},
  "geometry": {"coordinates":[-76.732373,34.822903],"type":"Point"}
}