{
  "type": "Feature",
  "properties": {
    "iso:country":"US",
    "sg:address":"131 Manley Ave",
    "sg:city":"Greensboro",
    "sg:classifiers":[
        {
            "category":"Organizations",
            "subcategory":"Religious Organization",
            "type":"Services"
        }
    ],
    "sg:phone":"+1 336 299 1636",
    "sg:postcode":"27407",
    "sg:province":"NC",
    "sg:tags":[
        "church"
    ],
    "wof:name":"Door Of Hope",
    "wof:placetype":"venue"
},
  "geometry": {"coordinates":[-79.868573,36.06705],"type":"Point"}
}