{
  "type": "Feature",
  "properties": {
    "iso:country":"US",
    "sg:address":"4000 Sam Wilson Rd",
    "sg:city":"Charlotte",
    "sg:classifiers":[
        {
            "category":"Manufacturing",
            "subcategory":"Motor Vehicles & Parts",
            "type":"Manufacturing & Wholesale Goods"
        }
    ],
    "sg:phone":"+1 704 392 4624",
    "sg:postcode":"28214",
    "sg:province":"NC",
    "sg:tags":[
        "body",
        "truck"
    ],
    "sg:website":"www.aatac.com",
    "wof:name":"A & A Truck & Auto Ctr Inc",
    "wof:placetype":"venue"
},
  "geometry": {"coordinates":[-80.98407899999999,35.236821],"type":"Point"}
}