{
  "type": "Feature",
  "properties": {
    "iso:country":"US",
    "sg:address":"8031 S Old Oregon Inlet Rd",
    "sg:city":"Nags Head",
    "sg:classifiers":[
        {
            "category":"Travel",
            "subcategory":"Hotels & Motels",
            "type":"Entertainment"
        }
    ],
    "sg:phone":"+1 252 441 6315",
    "sg:postcode":"27959",
    "sg:province":"NC",
    "wof:name":"Comfort Inn Oceanfront South",
    "wof:placetype":"venue"
},
  "geometry": {"coordinates":[-75.591033,35.896648],"type":"Point"}
}