{
  "type": "Feature",
  "properties": {
    "iso:country":"US",
    "sg:address":"103 Daniel Paul Dr",
    "sg:city":"Archdale",
    "sg:classifiers":[
        {
            "category":"Organizations",
            "subcategory":"Religious Organization",
            "type":"Services"
        }
    ],
    "sg:phone":"+1 336 431 7254",
    "sg:postcode":"27263",
    "sg:province":"NC",
    "sg:tags":[
        "clergy"
    ],
    "wof:name":"Church Of God Parsonage",
    "wof:placetype":"venue"
},
  "geometry": {"coordinates":[-80.00248000000001,35.904725],"type":"Point"}
}