{
  "type": "Feature",
  "properties": {
    "addr:full":"208 Charles St Havelock NC 28532",
    "addr:housenumber":"208",
    "addr:postcode":"28532",
    "addr:street":"Charles St",
    "iso:country":"US",
    "sg:address":"208 Charles St",
    "sg:city":"Havelock",
    "sg:classifiers":[
        {
            "category":"Building & Trades",
            "subcategory":"Cleaning & Sanitation",
            "type":"Services"
        }
    ],
    "sg:phone":"+1   ",
    "sg:postcode":"28532",
    "sg:province":"NC",
    "sg:tags":[
        "janitorial",
        "maintenance"
    ],
    "wof:name":"Precision Interior & Exterior",
    "wof:placetype":"venue"
},
  "geometry": {"coordinates":[-76.894508,34.871148],"type":"Point"}
}