{
  "type": "Feature",
  "properties": {
    "addr:full":"4701 Central Ave Charlotte NC 28205",
    "addr:housenumber":"4701",
    "addr:postcode":"28205",
    "addr:street":"Central Ave",
    "iso:country":"US",
    "sg:address":"4701 Central Ave",
    "sg:city":"Charlotte",
    "sg:classifiers":[
        {
            "category":"Shopping",
            "subcategory":"Clothing, Apparel, & Fashions",
            "type":"Retail Goods"
        },
        {
            "category":"Personal",
            "subcategory":"Beauty Salon",
            "type":"Services"
        },
        {
            "category":"Retail",
            "subcategory":"Laundry & Dry Cleaning",
            "type":"Services"
        },
        {
            "category":"Personal",
            "type":"Services"
        },
        {
            "category":"Personal",
            "subcategory":"Shoe Repair & Shine",
            "type":"Services"
        }
    ],
    "sg:phone":"+1 704 536 5827",
    "sg:postcode":"28205",
    "sg:province":"NC",
    "sg:tags":[
        "cleaner",
        "gown",
        "tailoring",
        "alteration",
        "preservation",
        "alterations-clothing",
        "wedding",
        "bridal"
    ],
    "sg:website":"http://www.realpages.com/sites/cinderellacleaners",
    "wof:name":"Cinderella-A Cleaners & Laundry",
    "wof:placetype":"venue"
},
  "geometry": {"coordinates":[-80.76432,35.212521],"type":"Point"}
}