{
  "type": "Feature",
  "properties": {
    "addr:full":"1100 E King St Boone NC 28607",
    "addr:housenumber":"1100",
    "addr:postcode":"28607",
    "addr:street":"E King St",
    "iso:country":"US",
    "sg:address":"1100 E King St",
    "sg:city":"Boone",
    "sg:classifiers":[
        {
            "category":"Retail",
            "subcategory":"Auto Rental",
            "type":"Services"
        }
    ],
    "sg:phone":"+1 828 265 1367",
    "sg:postcode":"28607",
    "sg:province":"NC",
    "sg:tags":[
        "renting",
        "truck",
        "leasing"
    ],
    "wof:name":"U-Haul Co",
    "wof:placetype":"venue"
},
  "geometry": {"coordinates":[-81.665927,36.217023],"type":"Point"}
}