{
  "type": "Feature",
  "properties": {
    "addr:full":"10 Pedder Ct Durham NC 27713",
    "addr:housenumber":"10",
    "addr:postcode":"27713",
    "addr:street":"Pedder Ct",
    "iso:country":"US",
    "sg:address":"10 Pedder Ct",
    "sg:city":"Durham",
    "sg:classifiers":[
        {
            "category":"Professional",
            "subcategory":"Computer Services",
            "type":"Services"
        }
    ],
    "sg:phone":"+1   ",
    "sg:postcode":"27713",
    "sg:province":"NC",
    "sg:tags":[
        "sales"
    ],
    "wof:name":"10r Consulting",
    "wof:placetype":"venue"
},
  "geometry": {"coordinates":[-78.912823,35.9484],"type":"Point"}
}