{
  "type": "Feature",
  "properties": {
    "iso:country":"US",
    "sg:address":"738 Bragg Blvd",
    "sg:city":"Fayetteville",
    "sg:classifiers":[
        {
            "category":"Bars & Pubs",
            "type":"Food & Drink"
        },
        {
            "category":"Organizations",
            "subcategory":"Community Association",
            "type":"Services"
        }
    ],
    "sg:phone":"+1 910 484 5404",
    "sg:postcode":"28301",
    "sg:province":"NC",
    "sg:tags":[
        "club",
        "drinking"
    ],
    "wof:name":"Bottom's Up",
    "wof:placetype":"venue"
},
  "geometry": {"coordinates":[-78.888942,35.061411],"type":"Point"}
}