{
  "type": "Feature",
  "properties": {
    "iso:country":"US",
    "sg:address":"8547 Mount Holly Rd",
    "sg:city":"Charlotte",
    "sg:classifiers":[
        {
            "category":"Personal",
            "subcategory":"Beauty Salon",
            "type":"Services"
        }
    ],
    "sg:phone":"+1   ",
    "sg:postcode":"28214",
    "sg:province":"NC",
    "sg:tags":[
        "hair"
    ],
    "wof:name":"One West Gallery Hair Salon",
    "wof:placetype":"venue"
},
  "geometry": {"coordinates":[-80.951093,35.28488],"type":"Point"}
}