{
  "type": "Feature",
  "properties": {
    "iso:country":"US",
    "sg:address":"2731 Beatties Ford Rd",
    "sg:city":"Charlotte",
    "sg:classifiers":[
        {
            "category":"Personal",
            "subcategory":"Beauty Salon",
            "type":"Services"
        }
    ],
    "sg:phone":"+1 704 393 3075",
    "sg:postcode":"28216",
    "sg:province":"NC",
    "wof:name":"Backstage Beauty Salon II",
    "wof:placetype":"venue"
},
  "geometry": {"coordinates":[-80.854202,35.271343],"type":"Point"}
}