{
  "type": "Feature",
  "properties": {
    "iso:country":"US",
    "sg:address":"1246 Chub Lake Loop Rd",
    "sg:city":"Roxboro",
    "sg:classifiers":[
        {
            "category":"Retail",
            "subcategory":"Repair Shop",
            "type":"Services"
        }
    ],
    "sg:phone":"+1   ",
    "sg:postcode":"27574",
    "sg:province":"NC",
    "wof:name":"S Lawnmower Strange Sales",
    "wof:placetype":"venue"
},
  "geometry": {"coordinates":[-79.00319399999999,36.444223],"type":"Point"}
}