{
  "type": "Feature",
  "properties": {
    "iso:country":"US",
    "sg:address":"510 Merrimon Ave",
    "sg:city":"Asheville",
    "sg:classifiers":[
        {
            "category":"Freight",
            "type":"Transportation"
        }
    ],
    "sg:phone":"+1 828 258 1223",
    "sg:postcode":"28804",
    "sg:province":"NC",
    "sg:tags":[
        "operator",
        "local",
        "truck",
        "trucking"
    ],
    "wof:name":"Independent Transfer",
    "wof:placetype":"venue"
},
  "geometry": {"coordinates":[-82.55465599999999,35.616306],"type":"Point"}
}