{
  "type": "Feature",
  "properties": {
    "iso:country":"US",
    "sg:address":"201 Marsh Harbor Rd SW",
    "sg:city":"Calabash",
    "sg:classifiers":[
        {
            "category":"Sports & Exercise",
            "subcategory":"Golf",
            "type":"Entertainment"
        }
    ],
    "sg:phone":"+1 910 579 8097",
    "sg:postcode":"28467",
    "sg:province":"NC",
    "sg:tags":[
        "course"
    ],
    "wof:name":"Marsh Harbour Golf Links",
    "wof:placetype":"venue"
},
  "geometry": {"coordinates":[-78.577544,33.88661],"type":"Point"}
}