{
  "type": "Feature",
  "properties": {
    "iso:country":"US",
    "sg:address":"2403 Castle Hayne Rd",
    "sg:city":"Wilmington",
    "sg:classifiers":[
        {
            "category":"Retail",
            "subcategory":"Auto Repair",
            "type":"Services"
        }
    ],
    "sg:phone":"+1   ",
    "sg:postcode":"28401",
    "sg:province":"NC",
    "sg:tags":[
        "general"
    ],
    "wof:name":"Big DS Transmission Service",
    "wof:placetype":"venue"
},
  "geometry": {"coordinates":[-77.92106099999999,34.28672],"type":"Point"}
}