{
  "type": "Feature",
  "properties": {
    "addr:full":"2301 Greenbrook Pkwy Matthews NC 28104",
    "addr:housenumber":"2301",
    "addr:postcode":"28104",
    "addr:street":"Greenbrook Pkwy",
    "iso:country":"US",
    "sg:address":"2301 Greenbrook Pkwy",
    "sg:city":"Matthews",
    "sg:classifiers":[
        {
            "category":"Wholesale",
            "subcategory":"Stationery",
            "type":"Manufacturing & Wholesale Goods"
        }
    ],
    "sg:phone":"+1 704 841 8006",
    "sg:postcode":"28104",
    "sg:province":"NC",
    "sg:tags":[
        "product",
        "paper"
    ],
    "sg:website":"www.sappi.com",
    "wof:name":"Sappi Fine Paper",
    "wof:placetype":"venue"
},
  "geometry": {"coordinates":[-80.74343399999999,35.042199],"type":"Point"}
}