{
  "type": "Feature",
  "properties": {
    "addr:full":"675 Biltmore Ave Asheville NC 28801",
    "addr:housenumber":"675",
    "addr:postcode":"28801",
    "addr:street":"Biltmore Ave",
    "iso:country":"US",
    "sg:address":"675 Biltmore Ave",
    "sg:city":"Asheville",
    "sg:classifiers":[
        {
            "category":"Health Services",
            "subcategory":"Doctor",
            "type":"Services"
        }
    ],
    "sg:phone":"+1 828 250 9418",
    "sg:postcode":"28801",
    "sg:province":"NC",
    "sg:tags":[
        "medical",
        "optical",
        "good"
    ],
    "wof:name":"Ear Nose & Throat Center PA",
    "wof:placetype":"venue"
},
  "geometry": {"coordinates":[-82.545998,35.573844],"type":"Point"}
}