{
  "type": "Feature",
  "properties": {
    "addr:full":"575 Gate Rd Thomasville NC 27360",
    "addr:housenumber":"575",
    "addr:postcode":"27360",
    "addr:street":"Gate Rd",
    "iso:country":"US",
    "sg:address":"575 Gate Rd",
    "sg:city":"Thomasville",
    "sg:classifiers":[
        {
            "category":"Manufacturing",
            "subcategory":"Toys & Sporting Goods",
            "type":"Manufacturing & Wholesale Goods"
        }
    ],
    "sg:phone":"+1 336 472 9277",
    "sg:postcode":"27360",
    "sg:province":"NC",
    "sg:tags":[
        "mfg"
    ],
    "wof:name":"Craven Enterprises",
    "wof:placetype":"venue"
},
  "geometry": {"coordinates":[-80.12888700000001,35.905092],"type":"Point"}
}