{
  "type": "Feature",
  "properties": {
    "iso:country":"US",
    "sg:address":"307 Dowdle Mountain Rd",
    "sg:city":"Franklin",
    "sg:classifiers":[
        {
            "category":"Freight",
            "type":"Transportation"
        }
    ],
    "sg:phone":"+1 828 369 9803",
    "sg:postcode":"28734",
    "sg:province":"NC",
    "sg:tags":[
        "commercial",
        "storage"
    ],
    "wof:name":"Spacemakers Mini Storage",
    "wof:placetype":"venue"
},
  "geometry": {"coordinates":[-83.36831100000001,35.16716],"type":"Point"}
}