{
  "type": "Feature",
  "properties": {
    "iso:country":"US",
    "sg:address":"2625 Appliance Ct",
    "sg:city":"Raleigh",
    "sg:classifiers":[
        {
            "category":"Government",
            "subcategory":"Office",
            "type":"Public Place"
        }
    ],
    "sg:phone":"+1 919 834 7535",
    "sg:postcode":"27604",
    "sg:province":"NC",
    "sg:tags":[
        "military",
        "installation"
    ],
    "wof:name":"Meps",
    "wof:placetype":"venue"
},
  "geometry": {"coordinates":[-78.60119400000001,35.81187],"type":"Point"}
}