{
  "type": "Feature",
  "properties": {
    "iso:country":"US",
    "sg:address":"134 Signal Hill Dr",
    "sg:city":"Statesville",
    "sg:classifiers":[
        {
            "category":"Organizations",
            "subcategory":"Membership Organization",
            "type":"Services"
        }
    ],
    "sg:phone":"+1   ",
    "sg:postcode":"28625",
    "sg:province":"NC",
    "wof:name":"Mormon Missionaries",
    "wof:placetype":"venue"
},
  "geometry": {"coordinates":[-80.85612500000001,35.791244],"type":"Point"}
}