{
  "type": "Feature",
  "properties": {
    "iso:country":"US",
    "sg:address":"112 Spihnaker Cove",
    "sg:city":"Rocky Mount",
    "sg:classifiers":[
        {
            "category":"Manufacturing",
            "subcategory":"Metals",
            "type":"Manufacturing & Wholesale Goods"
        }
    ],
    "sg:phone":"+1 252 977 1157",
    "sg:postcode":"27804",
    "sg:province":"NC",
    "sg:tags":[
        "metalwork",
        "sheet",
        "mfg"
    ],
    "wof:name":"Wilfab Metal Corporation",
    "wof:placetype":"venue"
},
  "geometry": {"coordinates":[-77.796201,35.989263],"type":"Point"}
}