{
  "type": "Feature",
  "properties": {
    "iso:country":"US",
    "sg:address":"1606 Paramore Dr",
    "sg:city":"Greenville",
    "sg:classifiers":[
        {
            "category":"Building & Trades",
            "subcategory":"Construction",
            "type":"Services"
        }
    ],
    "sg:phone":"+1 252 353 5633",
    "sg:postcode":"27858",
    "sg:province":"NC",
    "sg:tags":[
        "house"
    ],
    "wof:name":"De Spain Construction Co",
    "wof:placetype":"venue"
},
  "geometry": {"coordinates":[-77.34621199999999,35.582539],"type":"Point"}
}