{
  "type": "Feature",
  "properties": {
    "addr:full":"239 W Acadia Ave Winston Salem NC 27127",
    "addr:housenumber":"239",
    "addr:postcode":"27127",
    "addr:street":"W Acadia Ave",
    "iso:country":"US",
    "sg:address":"239 W Acadia Ave",
    "sg:city":"Winston Salem",
    "sg:classifiers":[
        {
            "category":"Retail",
            "subcategory":"Auto Repair",
            "type":"Services"
        }
    ],
    "sg:phone":"+1 336 725 1761",
    "sg:postcode":"27127",
    "sg:province":"NC",
    "sg:tags":[
        "repairing",
        "automobile"
    ],
    "wof:name":"USA Tire & Battery Auto Svc",
    "wof:placetype":"venue"
},
  "geometry": {"coordinates":[-80.24422800000001,36.071336],"type":"Point"}
}