{
  "type": "Feature",
  "properties": {
    "iso:country":"US",
    "sg:address":"570 Emmaus Church Rd",
    "sg:city":"Dudley",
    "sg:classifiers":[
        {
            "category":"Government",
            "subcategory":"Fire Station",
            "type":"Public Place"
        }
    ],
    "sg:phone":"+1 919 736 4310",
    "sg:postcode":"28333",
    "sg:province":"NC",
    "sg:tags":[
        "protection"
    ],
    "wof:name":"Arrington Volunteer Fire Dept",
    "wof:placetype":"venue"
},
  "geometry": {"coordinates":[-77.973551,35.301808],"type":"Point"}
}