{
  "type": "Feature",
  "properties": {
    "addr:full":"604 River Hwy Mooresville NC 28117",
    "addr:housenumber":"604",
    "addr:postcode":"28117",
    "addr:street":"River Hwy",
    "iso:country":"US",
    "sg:address":"604 River Hwy",
    "sg:city":"Mooresville",
    "sg:classifiers":[
        {
            "category":"Restaurant",
            "type":"Food & Drink"
        }
    ],
    "sg:phone":"+1 704 799 8571",
    "sg:postcode":"28117",
    "sg:province":"NC",
    "wof:name":"O'Charley's",
    "wof:placetype":"venue"
},
  "geometry": {"coordinates":[-80.87641600000001,35.596118],"type":"Point"}
}