{
  "type": "Feature",
  "properties": {
    "iso:country":"US",
    "sg:address":"101 Forest St",
    "sg:city":"Forest City",
    "sg:classifiers":[
        {
            "category":"Social Services",
            "type":"Services"
        }
    ],
    "sg:phone":"+1 828 286 8260",
    "sg:postcode":"28043",
    "sg:province":"NC",
    "sg:tags":[
        "youth",
        "organization",
        "center"
    ],
    "wof:name":"Rutherfordton Little League",
    "wof:placetype":"venue"
},
  "geometry": {"coordinates":[-81.871472,35.334628],"type":"Point"}
}