{
  "type": "Feature",
  "properties": {
    "iso:country":"US",
    "sg:address":"23970 State Hwy 561",
    "sg:city":"Enfield",
    "sg:classifiers":[
        {
            "category":"Autos & Motor Vehicles",
            "subcategory":"Fuel & Gas Station",
            "type":"Retail Goods"
        }
    ],
    "sg:phone":"+1 252 445 3980",
    "sg:postcode":"27823",
    "sg:province":"NC",
    "sg:tags":[
        "oil"
    ],
    "wof:name":"Robbie's Inc",
    "wof:placetype":"venue"
},
  "geometry": {"coordinates":[-77.724144,36.268518],"type":"Point"}
}