{
  "type": "Feature",
  "properties": {
    "addr:full":"433 Morris Ford Rd Colerain NC 27924",
    "addr:housenumber":"433",
    "addr:postcode":"27924",
    "addr:street":"Morris Ford Rd",
    "iso:country":"US",
    "sg:address":"433 Morris Ford Rd",
    "sg:city":"Colerain",
    "sg:classifiers":[
        {
            "category":"Farming",
            "subcategory":"Poultry Farm",
            "type":"Manufacturing & Wholesale Goods"
        }
    ],
    "sg:phone":"+1 252 356 4344",
    "sg:postcode":"27924",
    "sg:province":"NC",
    "sg:tags":[
        "chicken"
    ],
    "wof:name":"Mack Perry Farm",
    "wof:placetype":"venue"
},
  "geometry": {"coordinates":[-76.864935,36.176596],"type":"Point"}
}