{
  "type": "Feature",
  "properties": {
    "addr:full":"2807 South Blvd Charlotte NC 28209",
    "addr:housenumber":"2807",
    "addr:postcode":"28209",
    "addr:street":"South Blvd",
    "iso:country":"US",
    "sg:address":"2807 South Blvd",
    "sg:city":"Charlotte",
    "sg:classifiers":[
        {
            "category":"Personal",
            "subcategory":"Beauty Salon",
            "type":"Services"
        }
    ],
    "sg:phone":"+1   ",
    "sg:postcode":"28209",
    "sg:province":"NC",
    "sg:tags":[
        "shop"
    ],
    "wof:name":"Beautiful Nails By Kim",
    "wof:placetype":"venue"
},
  "geometry": {"coordinates":[-80.86771899999999,35.198904],"type":"Point"}
}