{
  "type": "Feature",
  "properties": {
    "addr:full":"1440 Whitmire St Hendersonville NC 28791",
    "addr:housenumber":"1440",
    "addr:postcode":"28791",
    "addr:street":"Whitmire St",
    "iso:country":"US",
    "sg:address":"1440 Whitmire St",
    "sg:city":"Hendersonville",
    "sg:classifiers":[
        {
            "category":"Organizations",
            "subcategory":"Religious Organization",
            "type":"Services"
        }
    ],
    "sg:phone":"+1 828 698 1870",
    "sg:postcode":"28791",
    "sg:province":"NC",
    "sg:tags":[
        "church"
    ],
    "wof:name":"Calvary Chapel Hendersonville",
    "wof:placetype":"venue"
},
  "geometry": {"coordinates":[-82.47304800000001,35.328283],"type":"Point"}
}