{
  "type": "Feature",
  "properties": {
    "iso:country":"US",
    "sg:address":"1999 Tram Rd",
    "sg:city":"Mt Olive",
    "sg:classifiers":[
        {
            "category":"Organizations",
            "subcategory":"Religious Organization",
            "type":"Services"
        }
    ],
    "sg:phone":"+1 919 658 0044",
    "sg:postcode":"28365",
    "sg:province":"NC",
    "sg:tags":[
        "church"
    ],
    "wof:name":"Piney Green Free Will Baptist",
    "wof:placetype":"venue"
},
  "geometry": {"coordinates":[-77.889824,35.085901],"type":"Point"}
}