{
  "type": "Feature",
  "properties": {
    "addr:full":"204 Bainbridge Cir Garner NC 27529",
    "addr:housenumber":"204",
    "addr:postcode":"27529",
    "addr:street":"Bainbridge Cir",
    "iso:country":"US",
    "sg:address":"204 Bainbridge Cir",
    "sg:city":"Garner",
    "sg:classifiers":[
        {
            "category":"Building & Trades",
            "subcategory":"Construction",
            "type":"Services"
        }
    ],
    "sg:phone":"+1 919 779 2816",
    "sg:postcode":"27529",
    "sg:province":"NC",
    "sg:tags":[
        "equipment",
        "industrial",
        "installation",
        "elevator"
    ],
    "wof:name":"Triangle Elevator Service",
    "wof:placetype":"venue"
},
  "geometry": {"coordinates":[-78.59790099999999,35.688778],"type":"Point"}
}