{
  "type": "Feature",
  "properties": {
    "addr:full":"8800 Autumn Winds Dr Raleigh NC 27615",
    "addr:housenumber":"8800",
    "addr:postcode":"27615",
    "addr:street":"Autumn Winds Dr",
    "iso:country":"US",
    "sg:address":"8800 Autumn Winds Dr",
    "sg:city":"Raleigh",
    "sg:classifiers":[
        {
            "category":"Professional",
            "subcategory":"Management & Consulting",
            "type":"Services"
        }
    ],
    "sg:phone":"+1   ",
    "sg:postcode":"27615",
    "sg:province":"NC",
    "sg:tags":[
        "business"
    ],
    "wof:name":"Strategic Pk Consulting LLC",
    "wof:placetype":"venue"
},
  "geometry": {"coordinates":[-78.65989399999999,35.904424],"type":"Point"}
}