{
  "type": "Feature",
  "properties": {
    "addr:full":"956 S Talbert Blvd Lexington NC 27292",
    "addr:housenumber":"956",
    "addr:postcode":"27292",
    "addr:street":"S Talbert Blvd",
    "iso:country":"US",
    "sg:address":"956 S Talbert Blvd",
    "sg:city":"Lexington",
    "sg:classifiers":[
        {
            "category":"Personal",
            "subcategory":"Tanning Parlor",
            "type":"Services"
        }
    ],
    "sg:phone":"+1 336 249 2556",
    "sg:postcode":"27292",
    "sg:province":"NC",
    "sg:tags":[
        "salon"
    ],
    "wof:name":"Tanning Down Under",
    "wof:placetype":"venue"
},
  "geometry": {"coordinates":[-80.260456,35.813482],"type":"Point"}
}