{
  "type": "Feature",
  "properties": {
    "iso:country":"US",
    "sg:address":"200 Forest Hills Rd NW",
    "sg:city":"Wilson",
    "sg:classifiers":[
        {
            "category":"Banks & Credit Unions",
            "subcategory":"Bank",
            "type":"Services"
        },
        {
            "category":"Banks & Credit Unions",
            "subcategory":"Financial Services",
            "type":"Services"
        }
    ],
    "sg:phone":"+1 252 206 8545",
    "sg:postcode":"27896",
    "sg:province":"NC",
    "sg:tags":[
        "commercial",
        "financing",
        "saving",
        "loan"
    ],
    "wof:name":"Carter Bank & Trust",
    "wof:placetype":"venue"
},
  "geometry": {"coordinates":[-77.931877,35.750912],"type":"Point"}
}