{
  "type": "Feature",
  "properties": {
    "addr:full":"1604 N William St Goldsboro NC 27530",
    "addr:housenumber":"1604",
    "addr:postcode":"27530",
    "addr:street":"N William St",
    "iso:country":"US",
    "sg:address":"1604 N William St",
    "sg:city":"Goldsboro",
    "sg:classifiers":[
        {
            "category":"Autos & Motor Vehicles",
            "subcategory":"Automobile Sales",
            "type":"Retail Goods"
        }
    ],
    "sg:phone":"+1 919 734 2922",
    "sg:postcode":"27530",
    "sg:province":"NC",
    "sg:tags":[
        "car",
        "dealer"
    ],
    "wof:name":"Top Motor Sales",
    "wof:placetype":"venue"
},
  "geometry": {"coordinates":[-77.984381,35.402583],"type":"Point"}
}