{
  "type": "Feature",
  "properties": {
    "addr:full":"523 Worthville St Randleman NC 27317",
    "addr:housenumber":"523",
    "addr:postcode":"27317",
    "addr:street":"Worthville St",
    "iso:country":"US",
    "sg:address":"523 Worthville St",
    "sg:city":"Randleman",
    "sg:classifiers":[
        {
            "category":"Building & Trades",
            "subcategory":"Plumbing",
            "type":"Services"
        }
    ],
    "sg:phone":"+1 336 495 9240",
    "sg:postcode":"27317",
    "sg:province":"NC",
    "sg:tags":[
        "contractor"
    ],
    "wof:name":"Juan Egusquiza Office",
    "wof:placetype":"venue"
},
  "geometry": {"coordinates":[-79.79521,35.816443],"type":"Point"}
}