{
  "type": "Feature",
  "properties": {
    "iso:country":"US",
    "sg:address":"225 Hidden Woods Ln",
    "sg:city":"Hendersonville",
    "sg:classifiers":[
        {
            "category":"Building & Trades",
            "subcategory":"Construction",
            "type":"Services"
        }
    ],
    "sg:phone":"+1 828 891 9421",
    "sg:postcode":"28791",
    "sg:province":"NC",
    "sg:tags":[
        "contractor"
    ],
    "wof:name":"Bill Foster Grading",
    "wof:placetype":"venue"
},
  "geometry": {"coordinates":[-82.517629,35.334564],"type":"Point"}
}