{
  "type": "Feature",
  "properties": {
    "addr:full":"4717 Rosehill Rd Fayetteville NC 28311",
    "addr:housenumber":"4717",
    "addr:postcode":"28311",
    "addr:street":"Rosehill Rd",
    "iso:country":"US",
    "sg:address":"4717 Rosehill Rd",
    "sg:city":"Fayetteville",
    "sg:classifiers":[
        {
            "category":"Freight",
            "type":"Transportation"
        }
    ],
    "sg:phone":"+1 910 488 7910",
    "sg:postcode":"28311",
    "sg:province":"NC",
    "sg:tags":[
        "operator",
        "local",
        "trucking"
    ],
    "wof:name":"Tall Pine Inc",
    "wof:placetype":"venue"
},
  "geometry": {"coordinates":[-78.904538,35.122269],"type":"Point"}
}