{
  "type": "Feature",
  "properties": {
    "addr:full":"224 State Hwy 27 Midland NC 28107",
    "addr:housenumber":"224",
    "addr:postcode":"28107",
    "addr:street":"State Hwy 27",
    "iso:country":"US",
    "sg:address":"224 State Hwy 27",
    "sg:city":"Midland",
    "sg:classifiers":[
        {
            "category":"Personal",
            "subcategory":"Beauty Salon",
            "type":"Services"
        }
    ],
    "sg:phone":"+1 704 888 5116",
    "sg:postcode":"28107",
    "sg:province":"NC",
    "wof:name":"Hair Topia",
    "wof:placetype":"venue"
},
  "geometry": {"coordinates":[-80.56963500000001,35.248875],"type":"Point"}
}