{
  "type": "Feature",
  "properties": {
    "addr:full":"5616 Chimney Swift Dr Wake Forest NC 27587",
    "addr:housenumber":"5616",
    "addr:postcode":"27587",
    "addr:street":"Chimney Swift Dr",
    "iso:country":"US",
    "sg:address":"5616 Chimney Swift Dr",
    "sg:city":"Wake Forest",
    "sg:classifiers":[
        {
            "category":"Sports & Exercise",
            "subcategory":"Gym",
            "type":"Entertainment"
        }
    ],
    "sg:phone":"+1 919 570 6000",
    "sg:postcode":"27587",
    "sg:province":"NC",
    "sg:tags":[
        "club",
        "health",
        "studio",
        "gymnasium"
    ],
    "wof:name":"Star Trac Fitness",
    "wof:placetype":"venue"
},
  "geometry": {"coordinates":[-78.519865,35.928132],"type":"Point"}
}