{
  "type": "Feature",
  "properties": {
    "iso:country":"US",
    "sg:address":"3525 Matthews-Mint Hill Rd",
    "sg:city":"Matthews",
    "sg:classifiers":[
        {
            "category":"Insurance",
            "subcategory":"Insurance Agent",
            "type":"Services"
        }
    ],
    "sg:phone":"+1 704 844 8290",
    "sg:postcode":"28105",
    "sg:province":"NC",
    "wof:name":"Michael Littauer Insurance",
    "wof:placetype":"venue"
},
  "geometry": {"coordinates":[-80.682918,35.139113],"type":"Point"}
}