{
  "type": "Feature",
  "properties": {
    "addr:full":"116 Broadfoot Ave Fayetteville NC 28305",
    "addr:housenumber":"116",
    "addr:postcode":"28305",
    "addr:street":"Broadfoot Ave",
    "iso:country":"US",
    "sg:address":"116 Broadfoot Ave",
    "sg:city":"Fayetteville",
    "sg:classifiers":[
        {
            "category":"Professional",
            "subcategory":"Management & Consulting",
            "type":"Services"
        }
    ],
    "sg:phone":"+1 910 484 2040",
    "sg:postcode":"28305",
    "sg:province":"NC",
    "wof:name":"Teamlease Inc",
    "wof:placetype":"venue"
},
  "geometry": {"coordinates":[-78.900452,35.055385],"type":"Point"}
}