{
  "type": "Feature",
  "properties": {
    "addr:full":"1827 Spring Garden St Greensboro NC 27403",
    "addr:housenumber":"1827",
    "addr:postcode":"27403",
    "addr:street":"Spring Garden St",
    "iso:country":"US",
    "sg:address":"1827 Spring Garden St",
    "sg:city":"Greensboro",
    "sg:classifiers":[
        {
            "category":"Professional",
            "subcategory":"Business Services",
            "type":"Services"
        }
    ],
    "sg:phone":"+1   ",
    "sg:postcode":"27403",
    "sg:province":"NC",
    "wof:name":"Stringfellows Living Designs",
    "wof:placetype":"venue"
},
  "geometry": {"coordinates":[-79.822963,36.063694],"type":"Point"}
}