{
  "type": "Feature",
  "properties": {
    "addr:full":"102 Middleton Dr Charlotte NC 28207",
    "addr:housenumber":"102",
    "addr:postcode":"28207",
    "addr:street":"Middleton Dr",
    "iso:country":"US",
    "sg:address":"102 Middleton Dr",
    "sg:city":"Charlotte",
    "sg:classifiers":[
        {
            "category":"Shopping",
            "subcategory":"Antiques",
            "type":"Retail Goods"
        }
    ],
    "sg:phone":"+1 704 373 1200",
    "sg:postcode":"28207",
    "sg:province":"NC",
    "sg:tags":[
        "dealers-wholesale"
    ],
    "wof:name":"Heather Wharton",
    "wof:placetype":"venue"
},
  "geometry": {"coordinates":[-80.82323,35.197512],"type":"Point"}
}