{
  "type": "Feature",
  "properties": {
    "addr:full":"3639 Durham-Chapel Hill Blvd Durham NC 27707",
    "addr:housenumber":"3639",
    "addr:postcode":"27707",
    "addr:street":"Durham-Chapel Hill Blvd",
    "iso:country":"US",
    "sg:address":"3639 Durham-Chapel Hill Blvd",
    "sg:city":"Durham",
    "sg:classifiers":[
        {
            "category":"Retail",
            "subcategory":"Car Wash",
            "type":"Services"
        }
    ],
    "sg:phone":"+1 919 490 6868",
    "sg:postcode":"27707",
    "sg:province":"NC",
    "sg:tags":[
        "polishing",
        "washing"
    ],
    "wof:name":"Durham Ritz Touchless Carwash",
    "wof:placetype":"venue"
},
  "geometry": {"coordinates":[-78.951184,35.971117],"type":"Point"}
}