{
  "type": "Feature",
  "properties": {
    "addr:full":"106 Landing Dr Chapel Hill NC 27514",
    "addr:housenumber":"106",
    "addr:postcode":"27514",
    "addr:street":"Landing Dr",
    "iso:country":"US",
    "sg:address":"106 Landing Dr",
    "sg:city":"Chapel Hill",
    "sg:classifiers":[
        {
            "category":"Real Estate",
            "subcategory":"Real Estate Agent",
            "type":"Services"
        }
    ],
    "sg:phone":"+1 919 408 0033",
    "sg:postcode":"27514",
    "sg:province":"NC",
    "wof:name":"ML Commercial Real Estate LLC",
    "wof:placetype":"venue"
},
  "geometry": {"coordinates":[-79.02526400000001,35.964394],"type":"Point"}
}