{
  "type": "Feature",
  "properties": {
    "addr:full":"1006 Union Rd Gastonia NC 28054",
    "addr:housenumber":"1006",
    "addr:postcode":"28054",
    "addr:street":"Union Rd",
    "iso:country":"US",
    "sg:address":"1006 Union Rd",
    "sg:city":"Gastonia",
    "sg:classifiers":[
        {
            "category":"Social Services",
            "type":"Services"
        },
        {
            "category":"Health Services",
            "subcategory":"Clinic",
            "type":"Services"
        }
    ],
    "sg:phone":"+1 704 865 8819",
    "sg:postcode":"28054",
    "sg:province":"NC",
    "sg:tags":[
        "product",
        "mental",
        "developmentally",
        "disabled",
        "need",
        "special"
    ],
    "wof:name":"Comserv Inc",
    "wof:placetype":"venue"
},
  "geometry": {"coordinates":[-81.17533400000001,35.249917],"type":"Point"}
}