{
  "type": "Feature",
  "properties": {
    "iso:country":"US",
    "sg:address":"70 Cabbage Patch Rd",
    "sg:city":"Burnsville",
    "sg:classifiers":[
        {
            "category":"Manufacturing",
            "subcategory":"Lumber",
            "type":"Manufacturing & Wholesale Goods"
        }
    ],
    "sg:phone":"+1 828 675 4300",
    "sg:postcode":"28714",
    "sg:province":"NC",
    "sg:tags":[
        "logging"
    ],
    "wof:name":"Huskins Logging",
    "wof:placetype":"venue"
},
  "geometry": {"coordinates":[-82.15732800000001,35.84388],"type":"Point"}
}