{
  "type": "Feature",
  "properties": {
    "addr:full":"532 School Rd Windsor NC 27983",
    "addr:housenumber":"532",
    "addr:postcode":"27983",
    "addr:street":"School Rd",
    "iso:country":"US",
    "sg:address":"532 School Rd",
    "sg:city":"Windsor",
    "sg:classifiers":[
        {
            "category":"Building & Trades",
            "subcategory":"Plumbing",
            "type":"Services"
        }
    ],
    "sg:phone":"+1 252 794 1345",
    "sg:postcode":"27983",
    "sg:province":"NC",
    "sg:tags":[
        "plumbing",
        "contractor"
    ],
    "wof:name":"Tyro Plumbing",
    "wof:placetype":"venue"
},
  "geometry": {"coordinates":[-77.008381,36.041378],"type":"Point"}
}