{
  "type": "Feature",
  "properties": {
    "addr:full":"308 Armistead Ct Waxhaw NC 28173",
    "addr:housenumber":"308",
    "addr:postcode":"28173",
    "addr:street":"Armistead Ct",
    "iso:country":"US",
    "sg:address":"308 Armistead Ct",
    "sg:city":"Waxhaw",
    "sg:classifiers":[
        {
            "category":"Professional",
            "subcategory":"Business Services",
            "type":"Services"
        }
    ],
    "sg:phone":"+1   ",
    "sg:postcode":"28173",
    "sg:province":"NC",
    "wof:name":"South Park Youth Assoc Inc",
    "wof:placetype":"venue"
},
  "geometry": {"coordinates":[-80.802373,35.009624],"type":"Point"}
}