{
  "type": "Feature",
  "properties": {
    "iso:country":"US",
    "sg:address":"160 Iowa Ln",
    "sg:city":"Cary",
    "sg:classifiers":[
        {
            "category":"Professional",
            "subcategory":"Lawyer & Legal Services",
            "type":"Services"
        }
    ],
    "sg:phone":"+1 919 234 4260",
    "sg:postcode":"27511",
    "sg:province":"NC",
    "wof:name":"Davis and McCabe PA",
    "wof:placetype":"venue"
},
  "geometry": {"coordinates":[-78.785431,35.76961],"type":"Point"}
}