{
  "type": "Feature",
  "properties": {
    "addr:full":"110 N Gaston St Dallas NC 28034",
    "addr:housenumber":"110",
    "addr:postcode":"28034",
    "addr:street":"N Gaston St",
    "iso:country":"US",
    "sg:address":"110 N Gaston St",
    "sg:city":"Dallas",
    "sg:classifiers":[
        {
            "category":"Retail",
            "subcategory":"Laundry & Dry Cleaning",
            "type":"Services"
        }
    ],
    "sg:phone":"+1 704 922 9461",
    "sg:postcode":"28034",
    "sg:province":"NC",
    "sg:tags":[
        "drycleaning",
        "plant",
        "cleaners"
    ],
    "wof:name":"Shelton Dry Cleaners",
    "wof:placetype":"venue"
},
  "geometry": {"coordinates":[-81.175776,35.31642],"type":"Point"}
}