{
  "type": "Feature",
  "properties": {
    "iso:country":"US",
    "sg:address":"810 W Vernon Ave",
    "sg:city":"Kinston",
    "sg:classifiers":[
        {
            "category":"Food & Beverages",
            "subcategory":"Specialty",
            "type":"Retail Goods"
        }
    ],
    "sg:phone":"+1 252 527 8560",
    "sg:postcode":"28501",
    "sg:province":"NC",
    "wof:name":"Hiding Place",
    "wof:placetype":"venue"
},
  "geometry": {"coordinates":[-77.59213699999999,35.26965],"type":"Point"}
}