{
  "type": "Feature",
  "properties": {
    "addr:full":"915 Raleigh Rd Rocky Mount NC 27803",
    "addr:housenumber":"915",
    "addr:postcode":"27803",
    "addr:street":"Raleigh Rd",
    "iso:country":"US",
    "sg:address":"915 Raleigh Rd",
    "sg:city":"Rocky Mount",
    "sg:classifiers":[
        {
            "category":"Personal",
            "subcategory":"Beauty Salon",
            "type":"Services"
        }
    ],
    "sg:phone":"+1   ",
    "sg:postcode":"27803",
    "sg:province":"NC",
    "sg:tags":[
        "shop"
    ],
    "wof:name":"Hair By Tasha",
    "wof:placetype":"venue"
},
  "geometry": {"coordinates":[-77.811792,35.931962],"type":"Point"}
}