{
  "type": "Feature",
  "properties": {
    "addr:full":"13400 Windward Cove Charlotte NC 28278",
    "addr:housenumber":"13400",
    "addr:postcode":"28278",
    "addr:street":"Windward Cove",
    "iso:country":"US",
    "sg:address":"13400 Windward Cove",
    "sg:city":"Charlotte",
    "sg:classifiers":[
        {
            "category":"Travel",
            "subcategory":"Travel Agent",
            "type":"Entertainment"
        }
    ],
    "sg:phone":"+1 704 583 8400",
    "sg:postcode":"28278",
    "sg:province":"NC",
    "sg:tags":[
        "agency"
    ],
    "wof:name":"Cruise One",
    "wof:placetype":"venue"
},
  "geometry": {"coordinates":[-81.022851,35.119295],"type":"Point"}
}