{
  "type": "Feature",
  "properties": {
    "iso:country":"US",
    "sg:address":"1510 Buffaloe St",
    "sg:city":"Roanoke Rapids",
    "sg:classifiers":[
        {
            "category":"Personal",
            "subcategory":"Beauty Salon",
            "type":"Services"
        }
    ],
    "sg:phone":"+1 252 535 2684",
    "sg:postcode":"27870",
    "sg:province":"NC",
    "wof:name":"Cut-N Up Salon & Tanning",
    "wof:placetype":"venue"
},
  "geometry": {"coordinates":[-77.647651,36.438644],"type":"Point"}
}