{
  "type": "Feature",
  "properties": {
    "iso:country":"US",
    "sg:address":"7829 Littlejohn Ct",
    "sg:city":"Charlotte",
    "sg:classifiers":[
        {
            "category":"Shopping",
            "subcategory":"Used Merchandise",
            "type":"Retail Goods"
        }
    ],
    "sg:phone":"+1 704 537 7728",
    "sg:postcode":"28227",
    "sg:province":"NC",
    "wof:name":"Sisters Hidden Treasures",
    "wof:placetype":"venue"
},
  "geometry": {"coordinates":[-80.71163300000001,35.197219],"type":"Point"}
}