{
  "type": "Feature",
  "properties": {
    "iso:country":"US",
    "sg:address":"3364 S Church St",
    "sg:city":"Burlington",
    "sg:classifiers":[
        {
            "category":"Shopping",
            "type":"Retail Goods"
        }
    ],
    "sg:phone":"+1 336 586 0504",
    "sg:postcode":"27215",
    "sg:province":"NC",
    "sg:tags":[
        "equipment",
        "supply"
    ],
    "wof:name":"Carolina Restaurant Supply Inc",
    "wof:placetype":"venue"
},
  "geometry": {"coordinates":[-79.51502000000001,36.080278],"type":"Point"}
}