{
  "type": "Feature",
  "properties": {
    "iso:country":"US",
    "sg:address":"1400 Julian R Allsbrook Hwy",
    "sg:city":"Weldon",
    "sg:classifiers":[
        {
            "category":"Restaurant",
            "type":"Food & Drink"
        }
    ],
    "sg:phone":"+1 252 536 2102",
    "sg:postcode":"27890",
    "sg:province":"NC",
    "wof:name":"Ralph's Barbecue",
    "wof:placetype":"venue"
},
  "geometry": {"coordinates":[-77.623981,36.430334],"type":"Point"}
}