{
  "type": "Feature",
  "properties": {
    "addr:full":"1551 Rains Crossroads Rd Princeton NC 27569",
    "addr:housenumber":"1551",
    "addr:postcode":"27569",
    "addr:street":"Rains Crossroads Rd",
    "iso:country":"US",
    "sg:address":"1551 Rains Crossroads Rd",
    "sg:city":"Princeton",
    "sg:classifiers":[
        {
            "category":"Building & Trades",
            "subcategory":"Construction",
            "type":"Services"
        }
    ],
    "sg:phone":"+1 919 965 6287",
    "sg:postcode":"27569",
    "sg:province":"NC",
    "sg:tags":[
        "excavation",
        "work"
    ],
    "wof:name":"Steven W Braswell",
    "wof:placetype":"venue"
},
  "geometry": {"coordinates":[-78.208288,35.516905],"type":"Point"}
}