{
  "type": "Feature",
  "properties": {
    "iso:country":"US",
    "sg:address":"3643 Hillsborough Rd",
    "sg:city":"Durham",
    "sg:classifiers":[
        {
            "category":"Building & Trades",
            "subcategory":"Equipment Rental",
            "type":"Services"
        },
        {
            "category":"Manufacturing",
            "subcategory":"Chemicals & Compounds",
            "type":"Manufacturing & Wholesale Goods"
        }
    ],
    "sg:phone":"+1 919 383 9421",
    "sg:postcode":"27705",
    "sg:province":"NC",
    "sg:tags":[
        "water",
        "lease",
        "purification",
        "mfg"
    ],
    "wof:name":"Dracor Water Systems",
    "wof:placetype":"venue"
},
  "geometry": {"coordinates":[-78.95474900000001,36.022865],"type":"Point"}
}