{
  "type": "Feature",
  "properties": {
    "addr:full":"2525 Jones Franklin Rd Raleigh NC 27606",
    "addr:housenumber":"2525",
    "addr:postcode":"27606",
    "addr:street":"Jones Franklin Rd",
    "iso:country":"US",
    "sg:address":"2525 Jones Franklin Rd",
    "sg:city":"Raleigh",
    "sg:classifiers":[
        {
            "category":"Food & Beverages",
            "subcategory":"Groceries & Convenience Stores",
            "type":"Retail Goods"
        }
    ],
    "sg:phone":"+1 919 851 2791",
    "sg:postcode":"27606",
    "sg:province":"NC",
    "sg:website":"www.carolinapetro.com",
    "wof:name":"Carolina Petro Products",
    "wof:placetype":"venue"
},
  "geometry": {"coordinates":[-78.736006,35.74883],"type":"Point"}
}