{
  "type": "Feature",
  "properties": {
    "iso:country":"US",
    "sg:address":"22 Smokey Mountain Dr",
    "sg:city":"Swannanoa",
    "sg:classifiers":[
        {
            "category":"Communications",
            "type":"Services"
        }
    ],
    "sg:phone":"+1 828 296 7481",
    "sg:postcode":"28778",
    "sg:province":"NC",
    "sg:tags":[
        "telecommunication"
    ],
    "wof:name":"Swickle Technologies",
    "wof:placetype":"venue"
},
  "geometry": {"coordinates":[-82.426137,35.624219],"type":"Point"}
}