{
  "type": "Feature",
  "properties": {
    "iso:country":"US",
    "sg:address":"440 Lomax Dr",
    "sg:city":"Gold Hill",
    "sg:classifiers":[
        {
            "category":"Professional",
            "type":"Services"
        }
    ],
    "sg:phone":"+1 727 207 1532",
    "sg:postcode":"28071",
    "sg:province":"NC",
    "wof:name":"Netvictoria",
    "wof:placetype":"venue"
},
  "geometry": {"coordinates":[-80.35647,35.551304],"type":"Point"}
}