{
  "type": "Feature",
  "properties": {
    "addr:full":"8001 Knebford Cir Wake Forest NC 27587",
    "addr:housenumber":"8001",
    "addr:postcode":"27587",
    "addr:street":"Knebford Cir",
    "iso:country":"US",
    "sg:address":"8001 Knebford Cir",
    "sg:city":"Wake Forest",
    "sg:classifiers":[
        {
            "category":"Shopping",
            "subcategory":"Discount & Variety Stores",
            "type":"Retail Goods"
        }
    ],
    "sg:phone":"+1 919 554 9898",
    "sg:postcode":"27587",
    "sg:province":"NC",
    "sg:tags":[
        "merchandise",
        "general"
    ],
    "wof:name":"Glenmor Sales Ctr",
    "wof:placetype":"venue"
},
  "geometry": {"coordinates":[-78.556101,35.994951],"type":"Point"}
}