{
  "type": "Feature",
  "properties": {
    "iso:country":"US",
    "sg:address":"11621 Norkett Dr",
    "sg:city":"Charlotte",
    "sg:classifiers":[
        {
            "category":"Cinema",
            "subcategory":"Movie Rental",
            "type":"Entertainment"
        }
    ],
    "sg:phone":"+1 704 807 1052",
    "sg:postcode":"28215",
    "sg:province":"NC",
    "sg:tags":[
        "picture",
        "exchange",
        "motion",
        "distributor",
        "film"
    ],
    "wof:name":"One Dream Productions",
    "wof:placetype":"venue"
},
  "geometry": {"coordinates":[-80.669794,35.259089],"type":"Point"}
}