{
  "type": "Feature",
  "properties": {
    "iso:country":"US",
    "sg:address":"613 Quality Rd",
    "sg:city":"Fayetteville",
    "sg:classifiers":[
        {
            "category":"Social Services",
            "subcategory":"Adult Care",
            "type":"Services"
        }
    ],
    "sg:phone":"+1 910 484 9393",
    "sg:postcode":"28306",
    "sg:province":"NC",
    "sg:tags":[
        "residential"
    ],
    "wof:name":"Myrover-Reese Fellowship Home",
    "wof:placetype":"venue"
},
  "geometry": {"coordinates":[-78.90380399999999,35.025893],"type":"Point"}
}