{
  "type": "Feature",
  "properties": {
    "addr:full":"1117 Mount Hope Church Rd Mc Leansville NC 27301",
    "addr:housenumber":"1117",
    "addr:postcode":"27301",
    "addr:street":"Mount Hope Church Rd",
    "iso:country":"US",
    "sg:address":"1117 Mount Hope Church Rd",
    "sg:city":"Mc Leansville",
    "sg:classifiers":[
        {
            "category":"Organizations",
            "subcategory":"Religious Organization",
            "type":"Services"
        }
    ],
    "sg:phone":"+1   ",
    "sg:postcode":"27301",
    "sg:province":"NC",
    "wof:name":"One Way Baptist Chapel",
    "wof:placetype":"venue"
},
  "geometry": {"coordinates":[-79.67889099999999,36.089925],"type":"Point"}
}