{
  "type": "Feature",
  "properties": {
    "addr:full":"600 Maness Rd Star NC 27356",
    "addr:housenumber":"600",
    "addr:postcode":"27356",
    "addr:street":"Maness Rd",
    "iso:country":"US",
    "sg:address":"600 Maness Rd",
    "sg:city":"Star",
    "sg:classifiers":[
        {
            "category":"Wholesale",
            "subcategory":"Farm Supplies",
            "type":"Manufacturing & Wholesale Goods"
        }
    ],
    "sg:phone":"+1 910 576 8911",
    "sg:postcode":"27356",
    "sg:province":"NC",
    "sg:tags":[
        "livestock"
    ],
    "wof:name":"Jeffery L Maness",
    "wof:placetype":"venue"
},
  "geometry": {"coordinates":[-79.850769,35.464181],"type":"Point"}
}