{
  "type": "Feature",
  "properties": {
    "addr:full":"7110 Eastridge Dr Apex NC 27539",
    "addr:housenumber":"7110",
    "addr:postcode":"27539",
    "addr:street":"Eastridge Dr",
    "iso:country":"US",
    "sg:address":"7110 Eastridge Dr",
    "sg:city":"Apex",
    "sg:classifiers":[
        {
            "category":"Health Services",
            "subcategory":"Medical Lab",
            "type":"Services"
        }
    ],
    "sg:phone":"+1 919 662 3972",
    "sg:postcode":"27539",
    "sg:province":"NC",
    "sg:tags":[
        "laboratory"
    ],
    "wof:name":"Dynamic Devices",
    "wof:placetype":"venue"
},
  "geometry": {"coordinates":[-78.753705,35.69186],"type":"Point"}
}