{
  "type": "Feature",
  "properties": {
    "iso:country":"US",
    "sg:address":"500 Bennett Dr",
    "sg:city":"Selma",
    "sg:classifiers":[
        {
            "category":"Professional",
            "subcategory":"Business Services",
            "type":"Services"
        }
    ],
    "sg:phone":"+1   ",
    "sg:postcode":"27576",
    "sg:province":"NC",
    "wof:name":"Pipers Mike Private HM Insptn",
    "wof:placetype":"venue"
},
  "geometry": {"coordinates":[-78.268863,35.542906],"type":"Point"}
}