{
  "type": "Feature",
  "properties": {
    "addr:full":"1590 State Rd 772 Pine Hall NC 27042",
    "addr:housenumber":"1590;772",
    "addr:postcode":"27042",
    "addr:street":"State Rd",
    "iso:country":"US",
    "sg:address":"1590 State Rd 772",
    "sg:city":"Pine Hall",
    "sg:classifiers":[
        {
            "category":"Organizations",
            "subcategory":"Religious Organization",
            "type":"Services"
        }
    ],
    "sg:phone":"+1   ",
    "sg:postcode":"27042",
    "sg:province":"NC",
    "wof:name":"Morning Star Baptist",
    "wof:placetype":"venue"
},
  "geometry": {"coordinates":[-80.05998200000001,36.354902],"type":"Point"}
}