{
  "type": "Feature",
  "properties": {
    "iso:country":"US",
    "sg:address":"642 S Main St",
    "sg:city":"Jefferson",
    "sg:classifiers":[
        {
            "category":"Shopping",
            "subcategory":"Used Merchandise",
            "type":"Retail Goods"
        }
    ],
    "sg:phone":"+1 336 846 9055",
    "sg:postcode":"28640",
    "sg:province":"NC",
    "sg:tags":[
        "antique"
    ],
    "wof:name":"Midtown Antiques",
    "wof:placetype":"venue"
},
  "geometry": {"coordinates":[-81.48018399999999,36.411222],"type":"Point"}
}