{
  "type": "Feature",
  "properties": {
    "addr:full":"600 Glenview Ave Hendersonville NC 28791",
    "addr:housenumber":"600",
    "addr:postcode":"28791",
    "addr:street":"Glenview Ave",
    "iso:country":"US",
    "sg:address":"600 Glenview Ave",
    "sg:city":"Hendersonville",
    "sg:classifiers":[
        {
            "category":"Building & Trades",
            "subcategory":"Landscaping Services",
            "type":"Services"
        }
    ],
    "sg:phone":"+1 828 697 5734",
    "sg:postcode":"28791",
    "sg:province":"NC",
    "sg:tags":[
        "tree"
    ],
    "wof:name":"Osteen's Tree Svc",
    "wof:placetype":"venue"
},
  "geometry": {"coordinates":[-82.485912,35.337477],"type":"Point"}
}