{
  "type": "Feature",
  "properties": {
    "addr:full":"668 N Washington St Rutherfordton NC 28139",
    "addr:housenumber":"668",
    "addr:postcode":"28139",
    "addr:street":"N Washington St",
    "iso:country":"US",
    "sg:address":"668 N Washington St",
    "sg:city":"Rutherfordton",
    "sg:classifiers":[
        {
            "category":"Organizations",
            "subcategory":"Religious Organization",
            "type":"Services"
        }
    ],
    "sg:phone":"+1 828 286 9278",
    "sg:postcode":"28139",
    "sg:province":"NC",
    "wof:name":"Green River Baptist Assn Inc",
    "wof:placetype":"venue"
},
  "geometry": {"coordinates":[-81.95801899999999,35.370967],"type":"Point"}
}