{
  "type": "Feature",
  "properties": {
    "iso:country":"US",
    "sg:address":"601 Sloan Dr",
    "sg:city":"Cary",
    "sg:classifiers":[
        {
            "category":"Retail",
            "subcategory":"Auto Repair",
            "type":"Services"
        }
    ],
    "sg:phone":"+1   ",
    "sg:postcode":"27511",
    "sg:province":"NC",
    "sg:tags":[
        "automotive"
    ],
    "wof:name":"A W Mobile",
    "wof:placetype":"venue"
},
  "geometry": {"coordinates":[-78.769122,35.785882],"type":"Point"}
}