{
  "type": "Feature",
  "properties": {
    "iso:country":"US",
    "sg:address":"3211 Bramer Dr",
    "sg:city":"Raleigh",
    "sg:classifiers":[
        {
            "category":"Professional",
            "subcategory":"Management & Consulting",
            "type":"Services"
        }
    ],
    "sg:phone":"+1 919 862 9300",
    "sg:postcode":"27604",
    "sg:province":"NC",
    "sg:tags":[
        "marketing",
        "business",
        "consultant"
    ],
    "wof:name":"Capitol Communications Inc",
    "wof:placetype":"venue"
},
  "geometry": {"coordinates":[-78.604874,35.826921],"type":"Point"}
}