{
  "type": "Feature",
  "properties": {
    "iso:country":"US",
    "sg:address":"3723 Benson Dr",
    "sg:city":"Raleigh",
    "sg:classifiers":[
        {
            "category":"Real Estate",
            "subcategory":"Real Estate Agent",
            "type":"Services"
        }
    ],
    "sg:phone":"+1 919 872 1400",
    "sg:postcode":"27609",
    "sg:province":"NC",
    "sg:tags":[
        "appraiser"
    ],
    "wof:name":"Shaw Boykin & Morris Inc",
    "wof:placetype":"venue"
},
  "geometry": {"coordinates":[-78.618745,35.834761],"type":"Point"}
}