{
  "type": "Feature",
  "properties": {
    "iso:country":"US",
    "sg:address":"207 Wickersham Dr",
    "sg:city":"Statesville",
    "sg:classifiers":[
        {
            "category":"Home & Garden",
            "subcategory":"Home Furnishings",
            "type":"Retail Goods"
        }
    ],
    "sg:phone":"+1 704 872 9292",
    "sg:postcode":"28625",
    "sg:province":"NC",
    "sg:tags":[
        "fireplace"
    ],
    "wof:name":"Schaefer Fireplace Products",
    "wof:placetype":"venue"
},
  "geometry": {"coordinates":[-80.810429,35.801241],"type":"Point"}
}