{
  "type": "Feature",
  "properties": {
    "addr:full":"1815 Conifer Cir Charlotte NC 28213",
    "addr:housenumber":"1815",
    "addr:postcode":"28213",
    "addr:street":"Conifer Cir",
    "iso:country":"US",
    "sg:address":"1815 Conifer Cir",
    "sg:city":"Charlotte",
    "sg:classifiers":[
        {
            "category":"Insurance",
            "subcategory":"Insurance Agent",
            "type":"Services"
        }
    ],
    "sg:phone":"+1 704 258 7690",
    "sg:postcode":"28213",
    "sg:province":"NC",
    "sg:tags":[
        "broker"
    ],
    "wof:name":"Cygnus Group",
    "wof:placetype":"venue"
},
  "geometry": {"coordinates":[-80.72045300000001,35.303637],"type":"Point"}
}