{
  "type": "Feature",
  "properties": {
    "iso:country":"US",
    "sg:address":"4507 Redcedar Rd",
    "sg:city":"Mc Leansville",
    "sg:classifiers":[
        {
            "category":"Real Estate",
            "subcategory":"Architect",
            "type":"Services"
        }
    ],
    "sg:phone":"+1   ",
    "sg:postcode":"27301",
    "sg:province":"NC",
    "sg:tags":[
        "architectural"
    ],
    "wof:name":"David Cecil",
    "wof:placetype":"venue"
},
  "geometry": {"coordinates":[-79.655782,36.144038],"type":"Point"}
}