{
  "type": "Feature",
  "properties": {
    "addr:full":"117 Market Rd Mooresville NC 28115",
    "addr:housenumber":"117",
    "addr:postcode":"28115",
    "addr:street":"Market Rd",
    "iso:country":"US",
    "sg:address":"117 Market Rd",
    "sg:city":"Mooresville",
    "sg:classifiers":[
        {
            "category":"Building & Trades",
            "subcategory":"Plumbing",
            "type":"Services"
        }
    ],
    "sg:phone":"+1 704 663 3482",
    "sg:postcode":"28115",
    "sg:province":"NC",
    "sg:tags":[
        "heating",
        "contractor"
    ],
    "wof:name":"Donaldson Heating & Cooling",
    "wof:placetype":"venue"
},
  "geometry": {"coordinates":[-80.837087,35.556535],"type":"Point"}
}