{
  "type": "Feature",
  "properties": {
    "addr:full":"505 White Hawk Ln Banner Elk NC 28604",
    "addr:housenumber":"505",
    "addr:postcode":"28604",
    "addr:street":"White Hawk Ln",
    "iso:country":"US",
    "sg:address":"505 White Hawk Ln",
    "sg:city":"Banner Elk",
    "sg:classifiers":[
        {
            "category":"Retail",
            "subcategory":"Photofinishing",
            "type":"Services"
        }
    ],
    "sg:phone":"+1   ",
    "sg:postcode":"28604",
    "sg:province":"NC",
    "sg:tags":[
        "laboratory"
    ],
    "wof:name":"Griffith DOT Photographic",
    "wof:placetype":"venue"
},
  "geometry": {"coordinates":[-81.870636,36.139487],"type":"Point"}
}