{
  "type": "Feature",
  "properties": {
    "addr:full":"3720 N Center St Hickory NC 28601",
    "addr:housenumber":"3720",
    "addr:postcode":"28601",
    "addr:street":"N Center St",
    "iso:country":"US",
    "sg:address":"3720 N Center St",
    "sg:city":"Hickory",
    "sg:classifiers":[
        {
            "category":"Social Services",
            "subcategory":"Child Care",
            "type":"Services"
        }
    ],
    "sg:phone":"+1 828 322 1090",
    "sg:postcode":"28601",
    "sg:province":"NC",
    "wof:name":"Primrose School-Lake Hickory",
    "wof:placetype":"venue"
},
  "geometry": {"coordinates":[-81.323442,35.780544],"type":"Point"}
}