{
  "type": "Feature",
  "properties": {
    "addr:full":"1620 Ann St Wilmington NC 28401",
    "addr:housenumber":"1620",
    "addr:postcode":"28401",
    "addr:street":"Ann St",
    "iso:country":"US",
    "sg:address":"1620 Ann St",
    "sg:city":"Wilmington",
    "sg:classifiers":[
        {
            "category":"Retail",
            "subcategory":"Auto Rental",
            "type":"Services"
        }
    ],
    "sg:phone":"+1   ",
    "sg:postcode":"28401",
    "sg:province":"NC",
    "sg:tags":[
        "passenger",
        "car"
    ],
    "wof:name":"Gents For Rent",
    "wof:placetype":"venue"
},
  "geometry": {"coordinates":[-77.92739,34.233205],"type":"Point"}
}