{
  "type": "Feature",
  "properties": {
    "addr:full":"514 Corliss St Greensboro NC 27406",
    "addr:housenumber":"514",
    "addr:postcode":"27406",
    "addr:street":"Corliss St",
    "iso:country":"US",
    "sg:address":"514 Corliss St",
    "sg:city":"Greensboro",
    "sg:classifiers":[
        {
            "category":"Retail",
            "subcategory":"Laundry & Dry Cleaning",
            "type":"Services"
        }
    ],
    "sg:phone":"+1 336 272 7182",
    "sg:postcode":"27406",
    "sg:province":"NC",
    "sg:tags":[
        "linen",
        "supply"
    ],
    "sg:website":"www.alsco.com",
    "wof:name":"Alsco Inc",
    "wof:placetype":"venue"
},
  "geometry": {"coordinates":[-79.802054,36.024041],"type":"Point"}
}