{
  "type": "Feature",
  "properties": {
    "addr:full":"1328 Asheville Hwy Hendersonville NC 28791",
    "addr:housenumber":"1328",
    "addr:postcode":"28791",
    "addr:street":"Asheville Hwy",
    "iso:country":"US",
    "sg:address":"1328 Asheville Hwy",
    "sg:city":"Hendersonville",
    "sg:classifiers":[
        {
            "category":"Restaurant",
            "type":"Food & Drink"
        }
    ],
    "sg:phone":"+1 828 693 0665",
    "sg:postcode":"28791",
    "sg:province":"NC",
    "sg:tags":[
        "pizza"
    ],
    "wof:name":"Patelli's Pizza",
    "wof:placetype":"venue"
},
  "geometry": {"coordinates":[-82.467619,35.327829],"type":"Point"}
}