{
  "type": "Feature",
  "properties": {
    "iso:country":"US",
    "sg:address":"101 Clubhouse Rd",
    "sg:city":"Hertford",
    "sg:classifiers":[
        {
            "category":"Restaurant",
            "type":"Food & Drink"
        }
    ],
    "sg:phone":"+1 252 426 2252",
    "sg:postcode":"27944",
    "sg:province":"NC",
    "sg:tags":[
        "eating"
    ],
    "wof:name":"South Side Grill Inc",
    "wof:placetype":"venue"
},
  "geometry": {"coordinates":[-76.383712,36.083894],"type":"Point"}
}