{
  "type": "Feature",
  "properties": {
    "iso:country":"US",
    "sg:address":"110 Courthouse Plz",
    "sg:city":"Kenansville",
    "sg:classifiers":[
        {
            "category":"Organizations",
            "subcategory":"Non-profit Organization",
            "type":"Services"
        }
    ],
    "sg:phone":"+1 910 296 9696",
    "sg:postcode":"28349",
    "sg:province":"NC",
    "sg:tags":[
        "information",
        "alcoholism",
        "treatment"
    ],
    "wof:name":"CDTEG",
    "wof:placetype":"venue"
},
  "geometry": {"coordinates":[-77.96172900000001,34.963051],"type":"Point"}
}