{
  "type": "Feature",
  "properties": {
    "addr:full":"138 Kenansville Hwy Warsaw NC 28398",
    "addr:housenumber":"138",
    "addr:postcode":"28398",
    "addr:street":"Kenansville Hwy",
    "iso:country":"US",
    "sg:address":"138 Kenansville Hwy",
    "sg:city":"Warsaw",
    "sg:classifiers":[
        {
            "category":"Restaurant",
            "type":"Food & Drink"
        }
    ],
    "sg:phone":"+1 910 293 3000",
    "sg:postcode":"28398",
    "sg:province":"NC",
    "wof:name":"P J Pizza LLC",
    "wof:placetype":"venue"
},
  "geometry": {"coordinates":[-78.07971499999999,35.001973],"type":"Point"}
}