{
  "type": "Feature",
  "properties": {
    "iso:country":"US",
    "sg:address":"7951 State Hwy 41 E",
    "sg:city":"Elizabethtown",
    "sg:classifiers":[
        {
            "category":"Manufacturing",
            "subcategory":"Electronics",
            "type":"Manufacturing & Wholesale Goods"
        }
    ],
    "sg:phone":"+1 910 862 2153",
    "sg:postcode":"28337",
    "sg:province":"NC",
    "sg:tags":[
        "equipment",
        "electronic",
        "supply"
    ],
    "wof:name":"Seiber Electronics Corp",
    "wof:placetype":"venue"
},
  "geometry": {"coordinates":[-78.48283499999999,34.654494],"type":"Point"}
}