{
  "type": "Feature",
  "properties": {
    "iso:country":"US",
    "sg:address":"6997 US Hwy 70",
    "sg:city":"Newport",
    "sg:classifiers":[
        {
            "category":"Autos & Motor Vehicles",
            "subcategory":"Motorcycle Sales",
            "type":"Retail Goods"
        }
    ],
    "sg:phone":"+1 252 726 7482",
    "sg:postcode":"28570",
    "sg:province":"NC",
    "sg:tags":[
        "scooter"
    ],
    "wof:name":"Bike Doctor Inc",
    "wof:placetype":"venue"
},
  "geometry": {"coordinates":[-76.874268,34.782057],"type":"Point"}
}