{
  "type": "Feature",
  "properties": {
    "iso:country":"US",
    "sg:address":"3424 Highland Ave NE",
    "sg:city":"Hickory",
    "sg:classifiers":[
        {
            "category":"Restaurant",
            "type":"Food & Drink"
        }
    ],
    "sg:phone":"+1 828 325 0470",
    "sg:postcode":"28601",
    "sg:province":"NC",
    "wof:name":"Anita's Diner",
    "wof:placetype":"venue"
},
  "geometry": {"coordinates":[-81.26436200000001,35.722762],"type":"Point"}
}