{
  "type": "Feature",
  "properties": {
    "iso:country":"US",
    "sg:address":"312 W Tremont Ave",
    "sg:city":"Charlotte",
    "sg:classifiers":[
        {
            "category":"Building & Trades",
            "subcategory":"Construction",
            "type":"Services"
        }
    ],
    "sg:phone":"+1 704 376 8568",
    "sg:postcode":"28203",
    "sg:province":"NC",
    "sg:tags":[
        "builder",
        "dry wall",
        "contractor",
        "home"
    ],
    "sg:website":"http://www.bbcontractingco.com",
    "wof:name":"B & B Contracting Co. Inc.",
    "wof:placetype":"venue"
},
  "geometry": {"coordinates":[-80.864525,35.210942],"type":"Point"}
}