{
  "type": "Feature",
  "properties": {
    "iso:country":"US",
    "sg:address":"2753 Lassiter Mill Rd",
    "sg:city":"Asheboro",
    "sg:classifiers":[
        {
            "category":"Building & Trades",
            "subcategory":"Construction",
            "type":"Services"
        }
    ],
    "sg:phone":"+1 336 857 2869",
    "sg:postcode":"27205",
    "sg:province":"NC",
    "sg:tags":[
        "contractor"
    ],
    "wof:name":"Newlin Masonry",
    "wof:placetype":"venue"
},
  "geometry": {"coordinates":[-79.936437,35.649854],"type":"Point"}
}