{
  "type": "Feature",
  "properties": {
    "addr:full":"1624 E Main St Albemarle NC 28001",
    "addr:housenumber":"1624",
    "addr:postcode":"28001",
    "addr:street":"E Main St",
    "iso:country":"US",
    "sg:address":"1624 E Main St",
    "sg:city":"Albemarle",
    "sg:classifiers":[
        {
            "category":"Autos & Motor Vehicles",
            "subcategory":"Automobile Sales",
            "type":"Retail Goods"
        }
    ],
    "sg:phone":"+1 704 982 4747",
    "sg:postcode":"28001",
    "sg:province":"NC",
    "sg:tags":[
        "used"
    ],
    "wof:name":"On Spot Auto Center Inc",
    "wof:placetype":"venue"
},
  "geometry": {"coordinates":[-80.171094,35.350379],"type":"Point"}
}