{
  "type": "Feature",
  "properties": {
    "iso:country":"US",
    "sg:address":"521 Summit Lake Dr",
    "sg:city":"Apex",
    "sg:classifiers":[
        {
            "category":"Professional",
            "type":"Services"
        }
    ],
    "sg:phone":"+1 919 363 2256",
    "sg:postcode":"27523",
    "sg:province":"NC",
    "wof:name":"Creswell Coaching Inc",
    "wof:placetype":"venue"
},
  "geometry": {"coordinates":[-78.81818699999999,35.746123],"type":"Point"}
}