{
  "type": "Feature",
  "properties": {
    "addr:full":"2303 Burch Bridge Rd Burlington NC 27217",
    "addr:housenumber":"2303",
    "addr:postcode":"27217",
    "addr:street":"Burch Bridge Rd",
    "iso:country":"US",
    "sg:address":"2303 Burch Bridge Rd",
    "sg:city":"Burlington",
    "sg:classifiers":[
        {
            "category":"Restaurant",
            "type":"Food & Drink"
        }
    ],
    "sg:phone":"+1 336 227 0999",
    "sg:postcode":"27217",
    "sg:province":"NC",
    "sg:tags":[
        "eating"
    ],
    "wof:name":"Burch Bridge Cafe",
    "wof:placetype":"venue"
},
  "geometry": {"coordinates":[-79.462532,36.125992],"type":"Point"}
}