{
  "type": "Feature",
  "properties": {
    "iso:country":"US",
    "sg:address":"800 Watson Ave",
    "sg:city":"Winston Salem",
    "sg:classifiers":[
        {
            "category":"Wholesale",
            "subcategory":"Home Furnishings",
            "type":"Manufacturing & Wholesale Goods"
        }
    ],
    "sg:phone":"+1 336 723 0199",
    "sg:postcode":"27103",
    "sg:province":"NC",
    "wof:name":"Haunted Headstones",
    "wof:placetype":"venue"
},
  "geometry": {"coordinates":[-80.26907799999999,36.079884],"type":"Point"}
}