{
  "type": "Feature",
  "properties": {
    "addr:full":"13701 Idlewild Rd Matthews NC 28105",
    "addr:housenumber":"13701",
    "addr:postcode":"28105",
    "addr:street":"Idlewild Rd",
    "iso:country":"US",
    "sg:address":"13701 Idlewild Rd",
    "sg:city":"Matthews",
    "sg:classifiers":[
        {
            "category":"Professional",
            "type":"Services"
        }
    ],
    "sg:phone":"+1 704 847 4297",
    "sg:postcode":"28105",
    "sg:province":"NC",
    "wof:name":"Collins Jl Inc",
    "wof:placetype":"venue"
},
  "geometry": {"coordinates":[-80.669611,35.134223],"type":"Point"}
}