{
  "type": "Feature",
  "properties": {
    "addr:full":"5605 Long Ferry Rd Salisbury NC 28146",
    "addr:housenumber":"5605",
    "addr:postcode":"28146",
    "addr:street":"Long Ferry Rd",
    "iso:country":"US",
    "sg:address":"5605 Long Ferry Rd",
    "sg:city":"Salisbury",
    "sg:classifiers":[
        {
            "category":"Professional",
            "subcategory":"Business Services",
            "type":"Services"
        }
    ],
    "sg:phone":"+1   ",
    "sg:postcode":"28146",
    "sg:province":"NC",
    "wof:name":"Rcpoa",
    "wof:placetype":"venue"
},
  "geometry": {"coordinates":[-80.328262,35.66917],"type":"Point"}
}