{
  "type": "Feature",
  "properties": {
    "addr:full":"52 Glen Rd Garner NC 27529",
    "addr:housenumber":"52",
    "addr:postcode":"27529",
    "addr:street":"Glen Rd",
    "iso:country":"US",
    "sg:address":"52 Glen Rd",
    "sg:city":"Garner",
    "sg:classifiers":[
        {
            "category":"Retail",
            "subcategory":"Laundry & Dry Cleaning",
            "type":"Services"
        }
    ],
    "sg:phone":"+1 919 661 0437",
    "sg:postcode":"27529",
    "sg:province":"NC",
    "sg:tags":[
        "cleaners"
    ],
    "wof:name":"Quality Cleaners & Alterations",
    "wof:placetype":"venue"
},
  "geometry": {"coordinates":[-78.567277,35.607785],"type":"Point"}
}