{
  "type": "Feature",
  "properties": {
    "addr:full":"412 Carthage St Cameron NC 28326",
    "addr:housenumber":"412",
    "addr:postcode":"28326",
    "addr:street":"Carthage St",
    "iso:country":"US",
    "sg:address":"412 Carthage St",
    "sg:city":"Cameron",
    "sg:classifiers":[
        {
            "category":"Autos & Motor Vehicles",
            "subcategory":"Fuel & Gas Station",
            "type":"Retail Goods"
        }
    ],
    "sg:phone":"+1 910 245 7593",
    "sg:postcode":"28326",
    "sg:province":"NC",
    "sg:tags":[
        "oil"
    ],
    "wof:name":"J's Cash Mart",
    "wof:placetype":"venue"
},
  "geometry": {"coordinates":[-79.253272,35.326243],"type":"Point"}
}