{
  "type": "Feature",
  "properties": {
    "addr:full":"800 S Main St King NC 27021",
    "addr:housenumber":"800",
    "addr:postcode":"27021",
    "addr:street":"S Main St",
    "iso:country":"US",
    "sg:address":"800 S Main St",
    "sg:city":"King",
    "sg:classifiers":[
        {
            "category":"Shopping",
            "subcategory":"Discount & Variety Stores",
            "type":"Retail Goods"
        }
    ],
    "sg:phone":"+1 336 983 0086",
    "sg:postcode":"27021",
    "sg:province":"NC",
    "sg:tags":[
        "merchandise",
        "general"
    ],
    "wof:name":"K J's Express Stores Inc",
    "wof:placetype":"venue"
},
  "geometry": {"coordinates":[-80.36426299999999,36.26108],"type":"Point"}
}