{
  "type": "Feature",
  "properties": {
    "iso:country":"US",
    "sg:address":"9801 Providence Forest Ln",
    "sg:city":"Charlotte",
    "sg:classifiers":[
        {
            "category":"Retail",
            "subcategory":"Portrait Studio",
            "type":"Services"
        }
    ],
    "sg:phone":"+1 704 844 0113",
    "sg:postcode":"28270",
    "sg:province":"NC",
    "sg:tags":[
        "photographer"
    ],
    "sg:website":"www.sports-section.com",
    "wof:name":"Sports Section",
    "wof:placetype":"venue"
},
  "geometry": {"coordinates":[-80.754661,35.072331],"type":"Point"}
}