{
  "type": "Feature",
  "properties": {
    "addr:full":"139 Rand St Sanford NC 27332",
    "addr:housenumber":"139",
    "addr:postcode":"27332",
    "addr:street":"Rand St",
    "iso:country":"US",
    "sg:address":"139 Rand St",
    "sg:city":"Sanford",
    "sg:classifiers":[
        {
            "category":"Sports & Exercise",
            "subcategory":"Bowling",
            "type":"Entertainment"
        }
    ],
    "sg:phone":"+1 919 776 0729",
    "sg:postcode":"27332",
    "sg:province":"NC",
    "sg:tags":[
        "center"
    ],
    "wof:name":"Kendale Lanes",
    "wof:placetype":"venue"
},
  "geometry": {"coordinates":[-79.146355,35.450708],"type":"Point"}
}