{
  "type": "Feature",
  "properties": {
    "addr:full":"1251 Floyd Stalcup Rd Murphy NC 28906",
    "addr:housenumber":"1251",
    "addr:postcode":"28906",
    "addr:street":"Floyd Stalcup Rd",
    "iso:country":"US",
    "sg:address":"1251 Floyd Stalcup Rd",
    "sg:city":"Murphy",
    "sg:classifiers":[
        {
            "category":"Professional",
            "subcategory":"Accounting & Tax Preparation",
            "type":"Services"
        }
    ],
    "sg:phone":"+1 828 835 3030",
    "sg:postcode":"28906",
    "sg:province":"NC",
    "sg:tags":[
        "billing"
    ],
    "wof:name":"University Internal Medicine",
    "wof:placetype":"venue"
},
  "geometry": {"coordinates":[-84.02607399999999,35.031317],"type":"Point"}
}