{
  "type": "Feature",
  "properties": {
    "addr:full":"780 State Rd 751 Apex NC 27502",
    "addr:housenumber":"780;751",
    "addr:postcode":"27502",
    "addr:street":"State Rd",
    "iso:country":"US",
    "sg:address":"780 State Rd 751",
    "sg:city":"Apex",
    "sg:classifiers":[
        {
            "category":"Building & Trades",
            "subcategory":"Plumbing",
            "type":"Services"
        }
    ],
    "sg:phone":"+1 919 362 3979",
    "sg:postcode":"27502",
    "sg:province":"NC",
    "sg:tags":[
        "conditioning",
        "air",
        "system",
        "contractor"
    ],
    "wof:name":"Chatham Mechanical Services",
    "wof:placetype":"venue"
},
  "geometry": {"coordinates":[-78.953278,35.744992],"type":"Point"}
}