{
  "type": "Feature",
  "properties": {
    "addr:full":"228 S Scales St Reidsville NC 27320",
    "addr:housenumber":"228",
    "addr:postcode":"27320",
    "addr:street":"S Scales St",
    "iso:country":"US",
    "sg:address":"228 S Scales St",
    "sg:city":"Reidsville",
    "sg:classifiers":[
        {
            "category":"Personal",
            "type":"Services"
        }
    ],
    "sg:phone":"+1   ",
    "sg:postcode":"27320",
    "sg:province":"NC",
    "wof:name":"J & S Tanning",
    "wof:placetype":"venue"
},
  "geometry": {"coordinates":[-79.66433499999999,36.359897],"type":"Point"}
}