{
  "type": "Feature",
  "properties": {
    "iso:country":"US",
    "sg:address":"800 US Hwy 70 Bus",
    "sg:city":"New Bern",
    "sg:classifiers":[
        {
            "category":"Manufacturing",
            "subcategory":"Glass & Minerals",
            "type":"Manufacturing & Wholesale Goods"
        }
    ],
    "sg:phone":"+1 252 637 7706",
    "sg:postcode":"28560",
    "sg:province":"NC",
    "sg:tags":[
        "product",
        "mfg"
    ],
    "wof:name":"Down East Stained Glass",
    "wof:placetype":"venue"
},
  "geometry": {"coordinates":[-77.047769,35.108253],"type":"Point"}
}