{
  "type": "Feature",
  "properties": {
    "iso:country":"US",
    "sg:address":"323 N Avon St",
    "sg:city":"Gastonia",
    "sg:classifiers":[
        {
            "category":"Retail",
            "subcategory":"Auto Repair",
            "type":"Services"
        }
    ],
    "sg:phone":"+1 704 867 5047",
    "sg:postcode":"28054",
    "sg:province":"NC",
    "sg:tags":[
        "repairing",
        "automobile"
    ],
    "wof:name":"Gaston Precision Automotive",
    "wof:placetype":"venue"
},
  "geometry": {"coordinates":[-81.172944,35.266308],"type":"Point"}
}