{
  "type": "Feature",
  "properties": {
    "iso:country":"US",
    "sg:address":"505 Cure Dr",
    "sg:city":"Madison",
    "sg:classifiers":[
        {
            "category":"Organizations",
            "subcategory":"Religious Organization",
            "type":"Services"
        }
    ],
    "sg:phone":"+1 336 427 8924",
    "sg:postcode":"27025",
    "sg:province":"NC",
    "sg:tags":[
        "church"
    ],
    "wof:name":"Mt Caramel Holiness Church",
    "wof:placetype":"venue"
},
  "geometry": {"coordinates":[-79.97568800000001,36.39287],"type":"Point"}
}