{
  "type": "Feature",
  "properties": {
    "addr:full":"113 North Salem St Apex NC 27502",
    "addr:housenumber":"113",
    "addr:postcode":"27502",
    "addr:street":"North Salem St",
    "iso:country":"US",
    "sg:address":"113 North Salem St",
    "sg:city":"Apex",
    "sg:classifiers":[
        {
            "category":"Restaurant",
            "type":"Food & Drink"
        }
    ],
    "sg:phone":"+1 919 387 9992",
    "sg:postcode":"27502",
    "sg:province":"NC",
    "sg:tags":[
        "traditional",
        "american"
    ],
    "sg:website":"www.salemstreetpub.com",
    "wof:name":"Salem Street Pub",
    "wof:placetype":"venue"
},
  "geometry": {"coordinates":[-78.851533,35.730883],"type":"Point"}
}