{
  "type": "Feature",
  "properties": {
    "iso:country":"US",
    "sg:address":"190 Charlois Blvd",
    "sg:city":"Winston Salem",
    "sg:classifiers":[
        {
            "category":"Professional",
            "subcategory":"Business Services",
            "type":"Services"
        }
    ],
    "sg:phone":"+1   ",
    "sg:postcode":"27103",
    "sg:province":"NC",
    "wof:name":"Piedmont Relocation Management",
    "wof:placetype":"venue"
},
  "geometry": {"coordinates":[-80.30355900000001,36.08284],"type":"Point"}
}