{
  "type": "Feature",
  "properties": {
    "iso:country":"US",
    "sg:address":"15 S Front St",
    "sg:city":"Wilmington",
    "sg:classifiers":[
        {
            "category":"Bars & Pubs",
            "type":"Food & Drink"
        }
    ],
    "sg:phone":"+1 910 342 0505",
    "sg:postcode":"28401",
    "sg:province":"NC",
    "sg:tags":[
        "club",
        "night"
    ],
    "wof:name":"Maarz Theatre",
    "wof:placetype":"venue"
},
  "geometry": {"coordinates":[-77.948617,34.235203],"type":"Point"}
}