{
  "type": "Feature",
  "properties": {
    "iso:country":"US",
    "sg:address":"603 Rigsbee Ave",
    "sg:city":"Durham",
    "sg:classifiers":[
        {
            "category":"Freight",
            "type":"Transportation"
        }
    ],
    "sg:phone":"+1 919 688 6791",
    "sg:postcode":"27701",
    "sg:province":"NC",
    "sg:tags":[
        "warehouse",
        "tobacco"
    ],
    "wof:name":"Liberty Warehouses",
    "wof:placetype":"venue"
},
  "geometry": {"coordinates":[-78.900066,36.001978],"type":"Point"}
}