{
  "type": "Feature",
  "properties": {
    "addr:full":"111 Providence Rd Chapel Hill NC 27514",
    "addr:housenumber":"111",
    "addr:postcode":"27514",
    "addr:street":"Providence Rd",
    "iso:country":"US",
    "sg:address":"111 Providence Rd",
    "sg:city":"Chapel Hill",
    "sg:classifiers":[
        {
            "category":"Professional",
            "subcategory":"Accounting & Tax Preparation",
            "type":"Services"
        }
    ],
    "sg:phone":"+1 919 489 8000",
    "sg:postcode":"27514",
    "sg:province":"NC",
    "wof:name":"Pricewaterhousecoopers LLP",
    "wof:placetype":"venue"
},
  "geometry": {"coordinates":[-79.00738699999999,35.951022],"type":"Point"}
}