{
  "type": "Feature",
  "properties": {
    "addr:full":"104 Kettlebridge Dr Cary NC 27511",
    "addr:housenumber":"104",
    "addr:postcode":"27511",
    "addr:street":"Kettlebridge Dr",
    "iso:country":"US",
    "sg:address":"104 Kettlebridge Dr",
    "sg:city":"Cary",
    "sg:classifiers":[
        {
            "category":"Professional",
            "type":"Services"
        }
    ],
    "sg:phone":"+1 919 363 8938",
    "sg:postcode":"27511",
    "sg:province":"NC",
    "sg:tags":[
        "establishment"
    ],
    "wof:name":"Railinc Co",
    "wof:placetype":"venue"
},
  "geometry": {"coordinates":[-78.812679,35.75003],"type":"Point"}
}