{
  "type": "Feature",
  "properties": {
    "iso:country":"US",
    "sg:address":"700 Belvin Maynard Rd",
    "sg:city":"Harrells",
    "sg:classifiers":[
        {
            "category":"Farming",
            "subcategory":"Farm",
            "type":"Manufacturing & Wholesale Goods"
        }
    ],
    "sg:phone":"+1 910 532 2458",
    "sg:postcode":"28444",
    "sg:province":"NC",
    "wof:name":"Peterson Farms",
    "wof:placetype":"venue"
},
  "geometry": {"coordinates":[-78.230328,34.711609],"type":"Point"}
}