{
  "type": "Feature",
  "properties": {
    "addr:full":"1621 Canstaff Dr Kernersville NC 27284",
    "addr:housenumber":"1621",
    "addr:postcode":"27284",
    "addr:street":"Canstaff Dr",
    "iso:country":"US",
    "sg:address":"1621 Canstaff Dr",
    "sg:city":"Kernersville",
    "sg:classifiers":[
        {
            "category":"Travel",
            "subcategory":"Hotels & Motels",
            "type":"Entertainment"
        }
    ],
    "sg:phone":"+1   ",
    "sg:postcode":"27284",
    "sg:province":"NC",
    "sg:tags":[
        "operation"
    ],
    "wof:name":"Elephant Oaks Farm & Guest Hse",
    "wof:placetype":"venue"
},
  "geometry": {"coordinates":[-80.058035,36.054729],"type":"Point"}
}