{
  "type": "Feature",
  "properties": {
    "iso:country":"US",
    "sg:address":"6381 Pineview St",
    "sg:city":"Fayetteville",
    "sg:classifiers":[
        {
            "category":"Building & Trades",
            "subcategory":"Construction",
            "type":"Services"
        }
    ],
    "sg:phone":"+1 910 822 8744",
    "sg:postcode":"28311",
    "sg:province":"NC",
    "sg:tags":[
        "contractor"
    ],
    "wof:name":"Southeastern Fence Co",
    "wof:placetype":"venue"
},
  "geometry": {"coordinates":[-78.90532,35.148791],"type":"Point"}
}