{
  "type": "Feature",
  "properties": {
    "addr:full":"751 Dickens Rd Broadway NC 27505",
    "addr:housenumber":"751",
    "addr:postcode":"27505",
    "addr:street":"Dickens Rd",
    "iso:country":"US",
    "sg:address":"751 Dickens Rd",
    "sg:city":"Broadway",
    "sg:classifiers":[
        {
            "category":"Building & Trades",
            "subcategory":"Electrical",
            "type":"Services"
        }
    ],
    "sg:phone":"+1 919 258 9956",
    "sg:postcode":"27505",
    "sg:province":"NC",
    "sg:tags":[
        "electric",
        "contractor"
    ],
    "wof:name":"Kilowatts Electric",
    "wof:placetype":"venue"
},
  "geometry": {"coordinates":[-78.978286,35.482342],"type":"Point"}
}