{
  "type": "Feature",
  "properties": {
    "iso:country":"US",
    "sg:address":"11430 N Community House Rd",
    "sg:city":"Charlotte",
    "sg:classifiers":[
        {
            "category":"Insurance",
            "subcategory":"Insurance Agent",
            "type":"Services"
        }
    ],
    "sg:phone":"+1 704 887 2920",
    "sg:postcode":"28277",
    "sg:province":"NC",
    "sg:website":"www.theremigroup.com",
    "wof:name":"Remi Group",
    "wof:placetype":"venue"
},
  "geometry": {"coordinates":[-80.837665,35.060239],"type":"Point"}
}