{
  "type": "Feature",
  "properties": {
    "addr:full":"1050 Gold Mine Dr Catawba NC 28609",
    "addr:housenumber":"1050",
    "addr:postcode":"28609",
    "addr:street":"Gold Mine Dr",
    "iso:country":"US",
    "sg:address":"1050 Gold Mine Dr",
    "sg:city":"Catawba",
    "sg:classifiers":[
        {
            "category":"Professional",
            "type":"Services"
        }
    ],
    "sg:phone":"+1 828 241 2971",
    "sg:postcode":"28609",
    "sg:province":"NC",
    "wof:name":"R Dowell",
    "wof:placetype":"venue"
},
  "geometry": {"coordinates":[-81.057558,35.664089],"type":"Point"}
}