{
  "type": "Feature",
  "properties": {
    "addr:full":"159 Lyday Loop Rd Pisgah Forest NC 28768",
    "addr:housenumber":"159",
    "addr:postcode":"28768",
    "addr:street":"Lyday Loop Rd",
    "iso:country":"US",
    "sg:address":"159 Lyday Loop Rd",
    "sg:city":"Pisgah Forest",
    "sg:classifiers":[
        {
            "category":"Real Estate",
            "subcategory":"Architect",
            "type":"Services"
        }
    ],
    "sg:phone":"+1 828 884 2552",
    "sg:postcode":"28768",
    "sg:province":"NC",
    "wof:name":"Daniels-Worley Architectural",
    "wof:placetype":"venue"
},
  "geometry": {"coordinates":[-82.654718,35.278249],"type":"Point"}
}