{
  "type": "Feature",
  "properties": {
    "iso:country":"US",
    "sg:address":"420 Austin Dr",
    "sg:city":"Charlotte",
    "sg:classifiers":[
        {
            "category":"Building & Trades",
            "subcategory":"Construction",
            "type":"Services"
        }
    ],
    "sg:phone":"+1 704 596 8700",
    "sg:postcode":"28213",
    "sg:province":"NC",
    "sg:tags":[
        "excavation",
        "contractor"
    ],
    "wof:name":"Hendrix Backhoe Service",
    "wof:placetype":"venue"
},
  "geometry": {"coordinates":[-80.77661999999999,35.267195],"type":"Point"}
}