{
  "type": "Feature",
  "properties": {
    "iso:country":"US",
    "sg:address":"121 E 3rd St",
    "sg:city":"Ayden",
    "sg:classifiers":[
        {
            "category":"Shopping",
            "subcategory":"Gifts & Souvenirs",
            "type":"Retail Goods"
        }
    ],
    "sg:phone":"+1 252 746 4022",
    "sg:postcode":"28513",
    "sg:province":"NC",
    "sg:tags":[
        "shop"
    ],
    "wof:name":"G M Fashion & Things",
    "wof:placetype":"venue"
},
  "geometry": {"coordinates":[-77.41735300000001,35.471024],"type":"Point"}
}