{
  "type": "Feature",
  "properties": {
    "addr:full":"118 Carolina Ave Wilmington NC 28451",
    "addr:housenumber":"118",
    "addr:postcode":"28451",
    "addr:street":"Carolina Ave",
    "iso:country":"US",
    "sg:address":"118 Carolina Ave",
    "sg:city":"Wilmington",
    "sg:classifiers":[
        {
            "category":"Taxi",
            "type":"Transportation"
        }
    ],
    "sg:phone":"+1 910 836 0276",
    "sg:postcode":"28451",
    "sg:province":"NC",
    "sg:tags":[
        "taxicab"
    ],
    "wof:name":"River City Cab Co",
    "wof:placetype":"venue"
},
  "geometry": {"coordinates":[-78.00211899999999,34.234348],"type":"Point"}
}