{
  "type": "Feature",
  "properties": {
    "iso:country":"US",
    "sg:address":"2658 Caratoke Hwy",
    "sg:city":"Moyock",
    "sg:phone":"+1 252 232 2706",
    "sg:postcode":"27958",
    "sg:province":"NC",
    "sg:tags":[
        "farm",
        "corn"
    ],
    "wof:name":"West Manly",
    "wof:placetype":"venue"
},
  "geometry": {"coordinates":[-76.043713,36.454851],"type":"Point"}
}