{
  "type": "Feature",
  "properties": {
    "iso:country":"US",
    "sg:address":"826 N Elm St",
    "sg:city":"Greensboro",
    "sg:classifiers":[
        {
            "category":"Professional",
            "subcategory":"Lawyer & Legal Services",
            "type":"Services"
        }
    ],
    "sg:phone":"+1 336 333 6400",
    "sg:postcode":"27401",
    "sg:province":"NC",
    "sg:tags":[
        "attorney"
    ],
    "sg:website":"www.sharpless-stavola.com",
    "wof:name":"Sharpless & Stavola",
    "wof:placetype":"venue"
},
  "geometry": {"coordinates":[-79.789275,36.084334],"type":"Point"}
}