{
  "type": "Feature",
  "properties": {
    "addr:full":"911 E Morehead St Charlotte NC 28204",
    "addr:housenumber":"911",
    "addr:postcode":"28204",
    "addr:street":"E Morehead St",
    "iso:country":"US",
    "sg:address":"911 E Morehead St",
    "sg:city":"Charlotte",
    "sg:classifiers":[
        {
            "category":"Personal",
            "subcategory":"Beauty Salon",
            "type":"Services"
        }
    ],
    "sg:phone":"+1 704 333 1957",
    "sg:postcode":"28204",
    "sg:province":"NC",
    "sg:tags":[
        "shop"
    ],
    "wof:name":"Varji & Varji Salon",
    "wof:placetype":"venue"
},
  "geometry": {"coordinates":[-80.843828,35.213059],"type":"Point"}
}