{
  "type": "Feature",
  "properties": {
    "iso:country":"US",
    "sg:address":"2938 Capital Blvd",
    "sg:city":"Raleigh",
    "sg:classifiers":[
        {
            "category":"Shopping",
            "type":"Retail Goods"
        }
    ],
    "sg:phone":"+1 919 791 1888",
    "sg:postcode":"27604",
    "sg:province":"NC",
    "sg:tags":[
        "merchandise"
    ],
    "wof:name":"A And M Mini Mart Ii Inc",
    "wof:placetype":"venue"
},
  "geometry": {"coordinates":[-78.59486200000001,35.819264],"type":"Point"}
}