{
  "type": "Feature",
  "properties": {
    "iso:country":"US",
    "sg:address":"308 Clanton Rd",
    "sg:city":"Charlotte",
    "sg:classifiers":[
        {
            "category":"Real Estate",
            "subcategory":"Architect",
            "type":"Services"
        }
    ],
    "sg:phone":"+1 704 525 7737",
    "sg:postcode":"28217",
    "sg:province":"NC",
    "wof:name":"Design Haus Architect",
    "wof:placetype":"venue"
},
  "geometry": {"coordinates":[-80.876501,35.195644],"type":"Point"}
}