{
  "type": "Feature",
  "properties": {
    "iso:country":"US",
    "sg:address":"5310 Shipman Rd",
    "sg:city":"Hope Mills",
    "sg:classifiers":[
        {
            "category":"Building & Trades",
            "subcategory":"Construction",
            "type":"Services"
        }
    ],
    "sg:phone":"+1 910 424 4971",
    "sg:postcode":"28348",
    "sg:province":"NC",
    "sg:tags":[
        "water",
        "well",
        "drilling"
    ],
    "wof:name":"Bd Well Drilling",
    "wof:placetype":"venue"
},
  "geometry": {"coordinates":[-78.93188000000001,34.945535],"type":"Point"}
}