{
  "type": "Feature",
  "properties": {
    "iso:country":"US",
    "sg:address":"2487 Hurt Dr",
    "sg:city":"Rocky Mount",
    "sg:classifiers":[
        {
            "category":"Retail",
            "subcategory":"Repair Shop",
            "type":"Services"
        }
    ],
    "sg:phone":"+1 252 937 7233",
    "sg:postcode":"27804",
    "sg:province":"NC",
    "sg:tags":[
        "equipment",
        "medical"
    ],
    "wof:name":"Impotence Management",
    "wof:placetype":"venue"
},
  "geometry": {"coordinates":[-77.83750999999999,35.986238],"type":"Point"}
}