{
  "type": "Feature",
  "properties": {
    "iso:country":"US",
    "sg:address":"1100 Situs Ct",
    "sg:city":"Raleigh",
    "sg:classifiers":[
        {
            "category":"Professional",
            "subcategory":"Computer Services",
            "type":"Services"
        }
    ],
    "sg:phone":"+1 919 859 3212",
    "sg:postcode":"27606",
    "sg:province":"NC",
    "sg:tags":[
        "datum",
        "related"
    ],
    "wof:name":"Paragon Cmpt Professionals Inc",
    "wof:placetype":"venue"
},
  "geometry": {"coordinates":[-78.729237,35.766293],"type":"Point"}
}