{
  "type": "Feature",
  "properties": {
    "iso:country":"US",
    "sg:address":"60 Mintz Cemetery Rd NW",
    "sg:city":"Ocean Isle Beach",
    "sg:classifiers":[
        {
            "category":"Home & Garden",
            "subcategory":"Garden Supply",
            "type":"Retail Goods"
        }
    ],
    "sg:phone":"+1 910 579 6594",
    "sg:postcode":"28469",
    "sg:province":"NC",
    "sg:tags":[
        "nursery"
    ],
    "wof:name":"Cedar Lane Nursery",
    "wof:placetype":"venue"
},
  "geometry": {"coordinates":[-78.47067199999999,33.954221],"type":"Point"}
}