{
  "type": "Feature",
  "properties": {
    "addr:full":"140 Piney Green Rd Jacksonville NC 28546",
    "addr:housenumber":"140",
    "addr:postcode":"28546",
    "addr:street":"Piney Green Rd",
    "iso:country":"US",
    "sg:address":"140 Piney Green Rd",
    "sg:city":"Jacksonville",
    "sg:classifiers":[
        {
            "category":"Organizations",
            "subcategory":"Religious Organization",
            "type":"Services"
        }
    ],
    "sg:phone":"+1 910 346 6617",
    "sg:postcode":"28546",
    "sg:province":"NC",
    "sg:tags":[
        "church"
    ],
    "wof:name":"United Pentecostal Church",
    "wof:placetype":"venue"
},
  "geometry": {"coordinates":[-77.377931,34.786335],"type":"Point"}
}