{
  "type": "Feature",
  "properties": {
    "iso:country":"US",
    "sg:address":"808 W Ehringhaus St",
    "sg:city":"Elizabeth City",
    "sg:classifiers":[
        {
            "category":"Health Services",
            "subcategory":"Chiropractor",
            "type":"Services"
        }
    ],
    "sg:phone":"+1 252 338 3206",
    "sg:postcode":"27909",
    "sg:province":"NC",
    "wof:name":"Albemarle Chiropractic Offices",
    "wof:placetype":"venue"
},
  "geometry": {"coordinates":[-76.23148999999999,36.295785],"type":"Point"}
}