{
  "type": "Feature",
  "properties": {
    "iso:country":"US",
    "sg:address":"101 W Antioch Dr",
    "sg:city":"Oxford",
    "sg:classifiers":[
        {
            "category":"Autos & Motor Vehicles",
            "subcategory":"Automobile Sales",
            "type":"Retail Goods"
        }
    ],
    "sg:phone":"+1 919 693 1612",
    "sg:postcode":"27565",
    "sg:province":"NC",
    "sg:tags":[
        "car",
        "dealer"
    ],
    "wof:name":"Boyd Brothers Ford Inc",
    "wof:placetype":"venue"
},
  "geometry": {"coordinates":[-78.5727,36.293689],"type":"Point"}
}