{
  "type": "Feature",
  "properties": {
    "iso:country":"US",
    "sg:address":"3300 Monroe Rd",
    "sg:city":"Charlotte",
    "sg:classifiers":[
        {
            "category":"Home & Garden",
            "subcategory":"Carpets & Floor Coverings",
            "type":"Retail Goods"
        }
    ],
    "sg:phone":"+1 704 376 8501",
    "sg:postcode":"28205",
    "sg:province":"NC",
    "sg:tags":[
        "material",
        "rug"
    ],
    "sg:website":"http://www.hallsflooring.com",
    "wof:name":"Hall's Flooring",
    "wof:placetype":"venue"
},
  "geometry": {"coordinates":[-80.800667,35.203411],"type":"Point"}
}