{
  "type": "Feature",
  "properties": {
    "iso:country":"US",
    "sg:address":"6300 Double Eagle Rd",
    "sg:city":"Whitsett",
    "sg:classifiers":[
        {
            "category":"Professional",
            "type":"Services"
        }
    ],
    "sg:phone":"+1   ",
    "sg:postcode":"27377",
    "sg:province":"NC",
    "wof:name":"Mid State Services LLC",
    "wof:placetype":"venue"
},
  "geometry": {"coordinates":[-79.60757599999999,36.06873],"type":"Point"}
}