{
  "type": "Feature",
  "properties": {
    "iso:country":"US",
    "sg:address":"1081 Recovery Rd",
    "sg:city":"China Grove",
    "sg:classifiers":[
        {
            "category":"Insurance",
            "subcategory":"Insurance Agent",
            "type":"Services"
        }
    ],
    "sg:phone":"+1 704 855 6340",
    "sg:postcode":"28023",
    "sg:province":"NC",
    "wof:name":"Nationwide Insurance",
    "wof:placetype":"venue"
},
  "geometry": {"coordinates":[-80.557187,35.578617],"type":"Point"}
}