{
  "type": "Feature",
  "properties": {
    "iso:country":"US",
    "sg:address":"3600 Courtland Dr",
    "sg:city":"Durham",
    "sg:classifiers":[
        {
            "category":"Professional",
            "subcategory":"Art Services",
            "type":"Services"
        }
    ],
    "sg:phone":"+1   ",
    "sg:postcode":"27707",
    "sg:province":"NC",
    "sg:tags":[
        "photography",
        "commercial"
    ],
    "wof:name":"Robert Campell Photography",
    "wof:placetype":"venue"
},
  "geometry": {"coordinates":[-78.932427,35.950212],"type":"Point"}
}