{
  "type": "Feature",
  "properties": {
    "addr:full":"3614 Philadelphia Church Rd Marshville NC 28103",
    "addr:housenumber":"3614",
    "addr:postcode":"28103",
    "addr:street":"Church Rd",
    "iso:country":"US",
    "sg:address":"3614 Philadelphia Church Rd",
    "sg:city":"Marshville",
    "sg:classifiers":[
        {
            "category":"Food & Beverages",
            "subcategory":"Groceries & Convenience Stores",
            "type":"Retail Goods"
        }
    ],
    "sg:phone":"+1 704 624 6805",
    "sg:postcode":"28103",
    "sg:province":"NC",
    "wof:name":"J W Moore Grocery",
    "wof:placetype":"venue"
},
  "geometry": {"coordinates":[-80.36883,34.898459],"type":"Point"}
}