{
  "type": "Feature",
  "properties": {
    "iso:country":"US",
    "sg:address":"1435 McBeth Dr",
    "sg:city":"Kannapolis",
    "sg:classifiers":[
        {
            "category":"Retail",
            "subcategory":"Repair Shop",
            "type":"Services"
        }
    ],
    "sg:phone":"+1   ",
    "sg:postcode":"28083",
    "sg:province":"NC",
    "wof:name":"Central Autobody & Repair Inc",
    "wof:placetype":"venue"
},
  "geometry": {"coordinates":[-80.59758600000001,35.487542],"type":"Point"}
}