{
  "type": "Feature",
  "properties": {
    "addr:full":"2800 Meridian Pkwy Durham NC 27713",
    "addr:housenumber":"2800",
    "addr:postcode":"27713",
    "addr:street":"Meridian Pkwy",
    "iso:country":"US",
    "sg:address":"2800 Meridian Pkwy",
    "sg:city":"Durham",
    "sg:classifiers":[
        {
            "category":"Manufacturing",
            "subcategory":"Tools & Machinery",
            "type":"Manufacturing & Wholesale Goods"
        }
    ],
    "sg:phone":"+1 919 259 9000",
    "sg:postcode":"27713",
    "sg:province":"NC",
    "sg:tags":[
        "equipment",
        "medical"
    ],
    "wof:name":"Trivirix International Inc",
    "wof:placetype":"venue"
},
  "geometry": {"coordinates":[-78.89988,35.914544],"type":"Point"}
}