{
  "type": "Feature",
  "properties": {
    "addr:full":"600 S Brightleaf Blvd Smithfield NC 27577",
    "addr:housenumber":"600",
    "addr:postcode":"27577",
    "addr:street":"S Brightleaf Blvd",
    "iso:country":"US",
    "sg:address":"600 S Brightleaf Blvd",
    "sg:city":"Smithfield",
    "sg:classifiers":[
        {
            "category":"Local Transit",
            "type":"Transportation"
        }
    ],
    "sg:phone":"+1 919 934 8272",
    "sg:postcode":"27577",
    "sg:province":"NC",
    "wof:name":"Bus Station",
    "wof:placetype":"venue"
},
  "geometry": {"coordinates":[-78.345018,35.502476],"type":"Point"}
}