{
  "type": "Feature",
  "properties": {
    "addr:full":"2610 E 7th St Charlotte NC 28204",
    "addr:housenumber":"2610",
    "addr:postcode":"28204",
    "addr:street":"E 7Th St",
    "iso:country":"US",
    "sg:address":"2610 E 7th St",
    "sg:city":"Charlotte",
    "sg:classifiers":[
        {
            "category":"Health Services",
            "subcategory":"Clinic",
            "type":"Services"
        }
    ],
    "sg:phone":"+1 704 375 8900",
    "sg:postcode":"28204",
    "sg:province":"NC",
    "sg:tags":[
        "comprehensive",
        "rehabilitation"
    ],
    "wof:name":"Health Rhbltation Psychologist",
    "wof:placetype":"venue"
},
  "geometry": {"coordinates":[-80.811359,35.206794],"type":"Point"}
}