{
  "type": "Feature",
  "properties": {
    "iso:country":"US",
    "sg:address":"2712 US Hwy 70",
    "sg:city":"Beaufort",
    "sg:classifiers":[
        {
            "category":"Building & Trades",
            "subcategory":"Construction",
            "type":"Services"
        }
    ],
    "sg:phone":"+1 252 728 1314",
    "sg:postcode":"28516",
    "sg:province":"NC",
    "sg:tags":[
        "home",
        "builder"
    ],
    "wof:name":"Larel Inc",
    "wof:placetype":"venue"
},
  "geometry": {"coordinates":[-76.627714,34.762899],"type":"Point"}
}