{
  "type": "Feature",
  "properties": {
    "iso:country":"US",
    "sg:address":"1791 Poplar Springs Rd",
    "sg:city":"Elkin",
    "sg:classifiers":[
        {
            "category":"Building & Trades",
            "subcategory":"Electrical",
            "type":"Services"
        }
    ],
    "sg:phone":"+1 336 366 2987",
    "sg:postcode":"28621",
    "sg:province":"NC",
    "sg:tags":[
        "electric",
        "contractor"
    ],
    "wof:name":"Dobbins Elec Co Of Elkin",
    "wof:placetype":"venue"
},
  "geometry": {"coordinates":[-80.79798599999999,36.325979],"type":"Point"}
}