{
  "type": "Feature",
  "properties": {
    "addr:full":"4364 Holly Spring Rd Ramseur NC 27316",
    "addr:housenumber":"4364",
    "addr:postcode":"27316",
    "addr:street":"Holly Spring Rd",
    "iso:country":"US",
    "sg:address":"4364 Holly Spring Rd",
    "sg:city":"Ramseur",
    "sg:classifiers":[
        {
            "category":"Restaurant",
            "type":"Food & Drink"
        }
    ],
    "sg:phone":"+1 336 879 4041",
    "sg:postcode":"27316",
    "sg:province":"NC",
    "sg:tags":[
        "eating"
    ],
    "wof:name":"Quzah Subway Inc",
    "wof:placetype":"venue"
},
  "geometry": {"coordinates":[-79.64904799999999,35.640761],"type":"Point"}
}