{
  "type": "Feature",
  "properties": {
    "addr:full":"2729 South Blvd Charlotte NC 28209",
    "addr:housenumber":"2729",
    "addr:postcode":"28209",
    "addr:street":"South Blvd",
    "iso:country":"US",
    "sg:address":"2729 South Blvd",
    "sg:city":"Charlotte",
    "sg:classifiers":[
        {
            "category":"Retail",
            "subcategory":"Laundry & Dry Cleaning",
            "type":"Services"
        }
    ],
    "sg:phone":"+1   ",
    "sg:postcode":"28209",
    "sg:province":"NC",
    "sg:tags":[
        "drycleaning",
        "plant"
    ],
    "wof:name":"Star Cleaners & Laundry",
    "wof:placetype":"venue"
},
  "geometry": {"coordinates":[-80.86672900000001,35.200214],"type":"Point"}
}