{
  "type": "Feature",
  "properties": {
    "addr:full":"1710 Pineview St Raleigh NC 27608",
    "addr:housenumber":"1710",
    "addr:postcode":"27608",
    "addr:street":"Pineview St",
    "iso:country":"US",
    "sg:address":"1710 Pineview St",
    "sg:city":"Raleigh",
    "sg:classifiers":[
        {
            "category":"Shopping",
            "subcategory":"Computers & Home Electronics",
            "type":"Retail Goods"
        }
    ],
    "sg:phone":"+1 919 856 0604",
    "sg:postcode":"27608",
    "sg:province":"NC",
    "sg:tags":[
        "store",
        "software"
    ],
    "wof:name":"Megatel Computer Co",
    "wof:placetype":"venue"
},
  "geometry": {"coordinates":[-78.655455,35.801398],"type":"Point"}
}