{
  "type": "Feature",
  "properties": {
    "iso:country":"US",
    "sg:address":"1205 Culbreth Dr",
    "sg:city":"Wilmington",
    "sg:classifiers":[
        {
            "category":"Insurance",
            "subcategory":"Insurance Agent",
            "type":"Services"
        }
    ],
    "sg:phone":"+1 910 392 7171",
    "sg:postcode":"28405",
    "sg:province":"NC",
    "wof:name":"Bankers Life",
    "wof:placetype":"venue"
},
  "geometry": {"coordinates":[-77.82867899999999,34.234125],"type":"Point"}
}