{
  "type": "Feature",
  "properties": {
    "iso:country":"US",
    "sg:address":"436 S Main St",
    "sg:city":"Norwood",
    "sg:classifiers":[
        {
            "category":"Social Services",
            "subcategory":"Adult Care",
            "type":"Services"
        }
    ],
    "sg:phone":"+1 704 474 3370",
    "sg:postcode":"28128",
    "sg:province":"NC",
    "sg:tags":[
        "home",
        "group"
    ],
    "wof:name":"Julius B Cohen Home",
    "wof:placetype":"venue"
},
  "geometry": {"coordinates":[-80.11547899999999,35.221826],"type":"Point"}
}