{
  "type": "Feature",
  "properties": {
    "addr:full":"536 W Main St Forest City NC 28043",
    "addr:housenumber":"536",
    "addr:postcode":"28043",
    "addr:street":"W Main St",
    "iso:country":"US",
    "sg:address":"536 W Main St",
    "sg:city":"Forest City",
    "sg:classifiers":[
        {
            "category":"Autos & Motor Vehicles",
            "subcategory":"Automobile Sales",
            "type":"Retail Goods"
        }
    ],
    "sg:phone":"+1 828 245 3491",
    "sg:postcode":"28043",
    "sg:province":"NC",
    "sg:tags":[
        "car",
        "dealer"
    ],
    "wof:name":"H & H Auto Sales",
    "wof:placetype":"venue"
},
  "geometry": {"coordinates":[-81.879648,35.340996],"type":"Point"}
}