{
  "type": "Feature",
  "properties": {
    "iso:country":"US",
    "sg:address":"4959 Chapel Grove Rd",
    "sg:city":"Gastonia",
    "sg:classifiers":[
        {
            "category":"Wholesale",
            "subcategory":"Machinery & Supplies",
            "type":"Manufacturing & Wholesale Goods"
        }
    ],
    "sg:phone":"+1 704 864 1813",
    "sg:postcode":"28052",
    "sg:province":"NC",
    "sg:tags":[
        "equipment",
        "industrial",
        "electrical",
        "contractor"
    ],
    "wof:name":"Huffstetler Overhauling",
    "wof:placetype":"venue"
},
  "geometry": {"coordinates":[-81.243613,35.213908],"type":"Point"}
}