{
  "type": "Feature",
  "properties": {
    "iso:country":"US",
    "sg:address":"1807 N Sandhills Blvd",
    "sg:city":"Aberdeen",
    "sg:classifiers":[
        {
            "category":"Restaurant",
            "type":"Food & Drink"
        }
    ],
    "sg:menulink":"http://www.allmenus.com/nc/sandhills/153146-bojangles/menu/",
    "sg:phone":"+1 910 692 5050",
    "sg:postcode":"28315",
    "sg:province":"NC",
    "sg:tags":[
        "chicken",
        "sandwich",
        "american"
    ],
    "wof:name":"Bojangle's",
    "wof:placetype":"venue"
},
  "geometry": {"coordinates":[-79.414019,35.156402],"type":"Point"}
}