{
  "type": "Feature",
  "properties": {
    "iso:country":"US",
    "sg:address":"601 N Lumina Ave",
    "sg:city":"Wrightsville Bch",
    "sg:classifiers":[
        {
            "category":"Banks & Credit Unions",
            "subcategory":"Investment Brokerage",
            "type":"Services"
        }
    ],
    "sg:phone":"+1 910 256 0036",
    "sg:postcode":"28480",
    "sg:province":"NC",
    "sg:tags":[
        "consultant",
        "financing"
    ],
    "wof:name":"Regulation D Resources Ent Inc",
    "wof:placetype":"venue"
},
  "geometry": {"coordinates":[-77.792215,34.213029],"type":"Point"}
}