{
  "type": "Feature",
  "properties": {
    "addr:full":"6125 Stadium Dr Clemmons NC 27012",
    "addr:housenumber":"6125",
    "addr:postcode":"27012",
    "addr:street":"Stadium Dr",
    "iso:country":"US",
    "sg:address":"6125 Stadium Dr",
    "sg:city":"Clemmons",
    "sg:classifiers":[
        {
            "category":"Utilities",
            "subcategory":"Telephone",
            "type":"Services"
        }
    ],
    "sg:phone":"+1 910 725 0668",
    "sg:postcode":"27012",
    "sg:province":"NC",
    "sg:tags":[
        "communications",
        "radiotelephone",
        "communication"
    ],
    "wof:name":"Lucent Technologies Inc",
    "wof:placetype":"venue"
},
  "geometry": {"coordinates":[-80.375181,36.026356],"type":"Point"}
}