{
  "type": "Feature",
  "properties": {
    "iso:country":"US",
    "sg:address":"239 W Main St",
    "sg:city":"Washington",
    "sg:classifiers":[
        {
            "category":"Banks & Credit Unions",
            "subcategory":"Bank",
            "type":"Services"
        }
    ],
    "sg:phone":"+1 252 940 5012",
    "sg:postcode":"27889",
    "sg:province":"NC",
    "sg:website":"www.firstsouthnc.com",
    "wof:name":"First South Bank",
    "wof:placetype":"venue"
},
  "geometry": {"coordinates":[-77.05789300000001,35.543245],"type":"Point"}
}