{
  "type": "Feature",
  "properties": {
    "iso:country":"US",
    "sg:address":"8 Hillview Rd",
    "sg:city":"Asheville",
    "sg:classifiers":[
        {
            "category":"Food & Beverages",
            "subcategory":"Specialty",
            "type":"Retail Goods"
        }
    ],
    "sg:phone":"+1 828 298 5732",
    "sg:postcode":"28805",
    "sg:province":"NC",
    "wof:name":"Harmons Health Products",
    "wof:placetype":"venue"
},
  "geometry": {"coordinates":[-82.506263,35.612461],"type":"Point"}
}