{
  "type": "Feature",
  "properties": {
    "addr:full":"631 Ben Williams Rd Jacksonville NC 28540",
    "addr:housenumber":"631",
    "addr:postcode":"28540",
    "addr:street":"Ben Williams Rd",
    "iso:country":"US",
    "sg:address":"631 Ben Williams Rd",
    "sg:city":"Jacksonville",
    "sg:classifiers":[
        {
            "category":"Freight",
            "type":"Transportation"
        }
    ],
    "sg:phone":"+1 910 346 8577",
    "sg:postcode":"28540",
    "sg:province":"NC",
    "sg:tags":[
        "operator",
        "local",
        "trucking"
    ],
    "wof:name":"L&B Trucking",
    "wof:placetype":"venue"
},
  "geometry": {"coordinates":[-77.591106,34.78022],"type":"Point"}
}