{
  "type": "Feature",
  "properties": {
    "addr:full":"7204 Abalone Way Wendell NC 27591",
    "addr:housenumber":"7204",
    "addr:postcode":"27591",
    "addr:street":"Abalone Way",
    "iso:country":"US",
    "sg:address":"7204 Abalone Way",
    "sg:city":"Wendell",
    "sg:classifiers":[
        {
            "category":"Building & Trades",
            "subcategory":"Construction",
            "type":"Services"
        }
    ],
    "sg:phone":"+1 919 366 2775",
    "sg:postcode":"27591",
    "sg:province":"NC",
    "sg:tags":[
        "dry wall",
        "contractor"
    ],
    "wof:name":"Ferrell's Drywall",
    "wof:placetype":"venue"
},
  "geometry": {"coordinates":[-78.39062800000001,35.818913],"type":"Point"}
}