{
  "type": "Feature",
  "properties": {
    "iso:country":"US",
    "sg:address":"167 Lake Rd",
    "sg:city":"Newport",
    "sg:classifiers":[
        {
            "category":"Real Estate",
            "subcategory":"Real Estate Operator",
            "type":"Services"
        }
    ],
    "sg:phone":"+1 252 223 4859",
    "sg:postcode":"28570",
    "sg:province":"NC",
    "sg:tags":[
        "property",
        "lessor"
    ],
    "wof:name":"Garner Artis",
    "wof:placetype":"venue"
},
  "geometry": {"coordinates":[-76.928023,34.792446],"type":"Point"}
}