{
  "type": "Feature",
  "properties": {
    "iso:country":"US",
    "sg:address":"131 Matthews Station St",
    "sg:city":"Matthews",
    "sg:classifiers":[
        {
            "category":"Professional",
            "subcategory":"Management & Consulting",
            "type":"Services"
        }
    ],
    "sg:phone":"+1   ",
    "sg:postcode":"28105",
    "sg:province":"NC",
    "wof:name":"Enerdyne Management Services L",
    "wof:placetype":"venue"
},
  "geometry": {"coordinates":[-80.719508,35.116724],"type":"Point"}
}