{
  "type": "Feature",
  "properties": {
    "iso:country":"US",
    "sg:address":"701 Riverview Church Rd",
    "sg:city":"Asheville",
    "sg:classifiers":[
        {
            "category":"Organizations",
            "subcategory":"Religious Organization",
            "type":"Services"
        }
    ],
    "sg:phone":"+1 828 225 4920",
    "sg:postcode":"28806",
    "sg:province":"NC",
    "sg:tags":[
        "church"
    ],
    "wof:name":"Refuge Christian Ctr",
    "wof:placetype":"venue"
},
  "geometry": {"coordinates":[-82.601107,35.617706],"type":"Point"}
}