{
  "type": "Feature",
  "properties": {
    "iso:country":"US",
    "sg:address":"618 Knollwood Village",
    "sg:city":"Southern Pines",
    "sg:classifiers":[
        {
            "category":"Building & Trades",
            "subcategory":"Construction",
            "type":"Services"
        }
    ],
    "sg:phone":"+1 910 692 9589",
    "sg:postcode":"28387",
    "sg:province":"NC",
    "sg:tags":[
        "concrete",
        "contractor"
    ],
    "wof:name":"Quick Pour Concrete",
    "wof:placetype":"venue"
},
  "geometry": {"coordinates":[-79.40495,35.194196],"type":"Point"}
}