{
  "type": "Feature",
  "properties": {
    "addr:full":"1577 River Rd Fayetteville NC 28395",
    "addr:housenumber":"1577",
    "addr:postcode":"28395",
    "addr:street":"River Rd",
    "iso:country":"US",
    "sg:address":"1577 River Rd",
    "sg:city":"Fayetteville",
    "sg:classifiers":[
        {
            "category":"Building & Trades",
            "subcategory":"Equipment Rental",
            "type":"Services"
        }
    ],
    "sg:phone":"+1   ",
    "sg:postcode":"28395",
    "sg:province":"NC",
    "sg:tags":[
        "toilet",
        "portable"
    ],
    "wof:name":"Affordble Prtbles of Fyttville",
    "wof:placetype":"venue"
},
  "geometry": {"coordinates":[-78.84825499999999,35.084028],"type":"Point"}
}