{
  "type": "Feature",
  "properties": {
    "iso:country":"US",
    "sg:address":"4135 Thomasville Rd",
    "sg:city":"Winston Salem",
    "sg:classifiers":[
        {
            "category":"Education",
            "subcategory":"School",
            "type":"Public Place"
        }
    ],
    "sg:phone":"+1 336 785 0527",
    "sg:postcode":"27107",
    "sg:province":"NC",
    "wof:name":"Christian Berean School",
    "wof:placetype":"venue"
},
  "geometry": {"coordinates":[-80.180995,36.039517],"type":"Point"}
}