{
  "type": "Feature",
  "properties": {
    "iso:country":"US",
    "sg:address":"2616 Lawndale Dr",
    "sg:city":"Greensboro",
    "sg:classifiers":[
        {
            "category":"Shopping",
            "type":"Retail Goods"
        }
    ],
    "sg:phone":"+1 336 691 0111",
    "sg:postcode":"27408",
    "sg:province":"NC",
    "sg:tags":[
        "outdoor",
        "lighting",
        "specialty"
    ],
    "wof:name":"Caryl's Christmas Shop",
    "wof:placetype":"venue"
},
  "geometry": {"coordinates":[-79.819024,36.104886],"type":"Point"}
}