{
  "type": "Feature",
  "properties": {
    "iso:country":"US",
    "sg:address":"527 Big Windfall Rd",
    "sg:city":"Lansing",
    "sg:classifiers":[
        {
            "category":"Building & Trades",
            "subcategory":"Construction",
            "type":"Services"
        }
    ],
    "sg:phone":"+1 336 384 2098",
    "sg:postcode":"28643",
    "sg:province":"NC",
    "sg:tags":[
        "concrete",
        "contractor"
    ],
    "wof:name":"D & S Pools",
    "wof:placetype":"venue"
},
  "geometry": {"coordinates":[-81.53574999999999,36.530726],"type":"Point"}
}