{
  "type": "Feature",
  "properties": {
    "iso:country":"US",
    "sg:address":"5039 Lanier Rd",
    "sg:city":"Asheboro",
    "sg:classifiers":[
        {
            "category":"Farming",
            "subcategory":"Farm",
            "type":"Manufacturing & Wholesale Goods"
        }
    ],
    "sg:phone":"+1 336 381 1398",
    "sg:postcode":"27205",
    "sg:province":"NC",
    "wof:name":"Loflin Farm",
    "wof:placetype":"venue"
},
  "geometry": {"coordinates":[-79.896884,35.563158],"type":"Point"}
}