{
  "type": "Feature",
  "properties": {
    "iso:country":"US",
    "sg:address":"10340 Park Rd",
    "sg:city":"Charlotte",
    "sg:classifiers":[
        {
            "category":"Health Services",
            "subcategory":"Medical Lab",
            "type":"Services"
        }
    ],
    "sg:phone":"+1 704 384 1344",
    "sg:postcode":"28210",
    "sg:province":"NC",
    "sg:tags":[
        "laboratory"
    ],
    "sg:website":"www.bradfordclinic.com",
    "wof:name":"Bradford Clinic",
    "wof:placetype":"venue"
},
  "geometry": {"coordinates":[-80.86799999999999,35.094029],"type":"Point"}
}