{
  "type": "Feature",
  "properties": {
    "addr:full":"1123 S Church St Charlotte NC 28203",
    "addr:housenumber":"1123",
    "addr:postcode":"28203",
    "addr:street":"S Church St",
    "iso:country":"US",
    "sg:address":"1123 S Church St",
    "sg:city":"Charlotte",
    "sg:classifiers":[
        {
            "category":"Place Of Worship",
            "subcategory":"Church",
            "type":"Public Place"
        }
    ],
    "sg:phone":"+1 704 370 6299",
    "sg:postcode":"28203",
    "sg:province":"NC",
    "sg:tags":[
        "churches-catholic"
    ],
    "wof:name":"Catholic Diocese Of Charlotte Housing Corporation",
    "wof:placetype":"venue"
},
  "geometry": {"coordinates":[-80.85402000000001,35.221337],"type":"Point"}
}