{
  "type": "Feature",
  "properties": {
    "iso:country":"US",
    "sg:address":"214 Middle St",
    "sg:city":"New Bern",
    "sg:classifiers":[
        {
            "category":"Shopping",
            "subcategory":"Hobbies, Toys, & Games",
            "type":"Retail Goods"
        }
    ],
    "sg:phone":"+1 252 514 6770",
    "sg:postcode":"28560",
    "sg:province":"NC",
    "wof:name":"Snap Dragon Inc",
    "wof:placetype":"venue"
},
  "geometry": {"coordinates":[-77.03984699999999,35.106604],"type":"Point"}
}