{
  "type": "Feature",
  "properties": {
    "addr:full":"112 Cullasaja Cir Franklin NC 28734",
    "addr:housenumber":"112",
    "addr:postcode":"nc 28734",
    "addr:street":"Cullasaja Cir",
    "iso:country":"US",
    "sg:address":"112 Cullasaja Cir",
    "sg:city":"Franklin",
    "sg:classifiers":[
        {
            "category":"Building & Trades",
            "subcategory":"Construction",
            "type":"Services"
        }
    ],
    "sg:phone":"+1 828 524 3579",
    "sg:postcode":"28734",
    "sg:province":"NC",
    "sg:tags":[
        "contractor",
        "painting",
        "hanging"
    ],
    "wof:name":"Denis Birdsall Painting &",
    "wof:placetype":"venue"
},
  "geometry": {"coordinates":[-83.31434,35.163396],"type":"Point"}
}