{
  "type": "Feature",
  "properties": {
    "iso:country":"US",
    "sg:address":"607 N 2nd St",
    "sg:city":"Albemarle",
    "sg:classifiers":[
        {
            "category":"Insurance",
            "subcategory":"Insurance Agent",
            "type":"Services"
        }
    ],
    "sg:phone":"+1 704 983 3105",
    "sg:postcode":"28001",
    "sg:province":"NC",
    "sg:tags":[
        "consulting",
        "management"
    ],
    "wof:name":"McGowen David R Ins Ofc",
    "wof:placetype":"venue"
},
  "geometry": {"coordinates":[-80.198257,35.36015],"type":"Point"}
}