{
  "type": "Feature",
  "properties": {
    "iso:country":"US",
    "sg:address":"4350 Main St",
    "sg:city":"Harrisburg",
    "sg:classifiers":[
        {
            "category":"Health Services",
            "subcategory":"Health Practitioner",
            "type":"Services"
        }
    ],
    "sg:phone":"+1 704 455 7441",
    "sg:postcode":"28075",
    "sg:province":"NC",
    "sg:tags":[
        "therapist",
        "physical"
    ],
    "wof:name":"Thomas Physical & Hand Therapy",
    "wof:placetype":"venue"
},
  "geometry": {"coordinates":[-80.646761,35.327524],"type":"Point"}
}