{
  "type": "Feature",
  "properties": {
    "iso:country":"US",
    "sg:address":"1103 Arsenal Ave",
    "sg:city":"Fayetteville",
    "sg:classifiers":[
        {
            "category":"Shopping",
            "subcategory":"Bicycles & Sporting Goods",
            "type":"Retail Goods"
        }
    ],
    "sg:phone":"+1 910 485 2090",
    "sg:postcode":"28305",
    "sg:province":"NC",
    "sg:tags":[
        "health"
    ],
    "wof:name":"Sports Nutrition",
    "wof:placetype":"venue"
},
  "geometry": {"coordinates":[-78.89915000000001,35.054922],"type":"Point"}
}