{
  "type": "Feature",
  "properties": {
    "addr:full":"3 Sunset Vw Asheville NC 28804",
    "addr:housenumber":"3",
    "addr:postcode":"28804",
    "addr:street":"Sunset Vw",
    "iso:country":"US",
    "sg:address":"3 Sunset Vw",
    "sg:city":"Asheville",
    "sg:classifiers":[
        {
            "category":"Professional",
            "subcategory":"Lawyer & Legal Services",
            "type":"Services"
        }
    ],
    "sg:phone":"+1 828 252 5349",
    "sg:postcode":"28804",
    "sg:province":"NC",
    "sg:tags":[
        "attorney"
    ],
    "wof:name":"Patent Mc Kenzie Inc",
    "wof:placetype":"venue"
},
  "geometry": {"coordinates":[-82.53848499999999,35.603345],"type":"Point"}
}