{
  "type": "Feature",
  "properties": {
    "addr:full":"5660 McDougald Rd Lillington NC 27546",
    "addr:housenumber":"5660",
    "addr:postcode":"27546",
    "addr:street":"Mcdougald Rd",
    "iso:country":"US",
    "sg:address":"5660 McDougald Rd",
    "sg:city":"Lillington",
    "sg:classifiers":[
        {
            "category":"Building & Trades",
            "subcategory":"Construction",
            "type":"Services"
        }
    ],
    "sg:phone":"+1 910 893 2372",
    "sg:postcode":"27546",
    "sg:province":"NC",
    "sg:tags":[
        "water",
        "hardware",
        "well",
        "drilling"
    ],
    "wof:name":"Jackson Well Drilling & Pump",
    "wof:placetype":"venue"
},
  "geometry": {"coordinates":[-78.937382,35.384174],"type":"Point"}
}