{
  "type": "Feature",
  "properties": {
    "iso:country":"US",
    "sg:address":"302 Primrose Pl",
    "sg:city":"Zebulon",
    "sg:classifiers":[
        {
            "category":"Real Estate",
            "subcategory":"Real Estate Operator",
            "type":"Services"
        }
    ],
    "sg:phone":"+1 919 269 6464",
    "sg:postcode":"27597",
    "sg:province":"NC",
    "sg:tags":[
        "apartment"
    ],
    "wof:name":"Maples Apartments",
    "wof:placetype":"venue"
},
  "geometry": {"coordinates":[-78.31412400000001,35.816365],"type":"Point"}
}