{
  "type": "Feature",
  "properties": {
    "addr:full":"903 Pineburr Ave SE Valdese NC 28690",
    "addr:housenumber":"903",
    "addr:postcode":"28690",
    "addr:street":"Pineburr Ave Se",
    "iso:country":"US",
    "sg:address":"903 Pineburr Ave SE",
    "sg:city":"Valdese",
    "sg:classifiers":[
        {
            "category":"Real Estate",
            "subcategory":"Real Estate Operator",
            "type":"Services"
        }
    ],
    "sg:phone":"+1 828 874 0079",
    "sg:postcode":"28690",
    "sg:province":"NC",
    "wof:name":"Blue Ridge Apartments",
    "wof:placetype":"venue"
},
  "geometry": {"coordinates":[-81.551709,35.737476],"type":"Point"}
}