{
  "type": "Feature",
  "properties": {
    "iso:country":"US",
    "sg:address":"5924 Knollrock Dr",
    "sg:city":"Raleigh",
    "sg:classifiers":[
        {
            "category":"Building & Trades",
            "subcategory":"Landscaping Services",
            "type":"Services"
        }
    ],
    "sg:phone":"+1 919 870 7252",
    "sg:postcode":"27612",
    "sg:province":"NC",
    "sg:tags":[
        "landscape",
        "contractor"
    ],
    "wof:name":"Edge Of Distinction",
    "wof:placetype":"venue"
},
  "geometry": {"coordinates":[-78.671648,35.861537],"type":"Point"}
}