{
  "type": "Feature",
  "properties": {
    "iso:country":"US",
    "sg:address":"1319 N Brightleaf Blvd",
    "sg:city":"Smithfield",
    "sg:classifiers":[
        {
            "category":"Restaurant",
            "type":"Food & Drink"
        }
    ],
    "sg:phone":"+1 919 934 0508",
    "sg:postcode":"27577",
    "sg:province":"NC",
    "sg:tags":[
        "eating"
    ],
    "wof:name":"Golden Corral",
    "wof:placetype":"venue"
},
  "geometry": {"coordinates":[-78.310334,35.520092],"type":"Point"}
}