{
  "type": "Feature",
  "properties": {
    "addr:full":"5114 Little Brook Ln Charlotte NC 28226",
    "addr:housenumber":"5114",
    "addr:postcode":"28226",
    "addr:street":"Little Brook Ln",
    "iso:country":"US",
    "sg:address":"5114 Little Brook Ln",
    "sg:city":"Charlotte",
    "sg:classifiers":[
        {
            "category":"Professional",
            "type":"Services"
        }
    ],
    "sg:phone":"+1 704 442 5405",
    "sg:postcode":"28226",
    "sg:province":"NC",
    "sg:tags":[
        "establishment"
    ],
    "wof:name":"Intervoice Brite",
    "wof:placetype":"venue"
},
  "geometry": {"coordinates":[-80.816793,35.138976],"type":"Point"}
}