{
  "type": "Feature",
  "properties": {
    "addr:full":"225 Amboy Rd Asheville NC 28806",
    "addr:housenumber":"225",
    "addr:postcode":"28806",
    "addr:street":"Amboy Rd",
    "iso:country":"US",
    "sg:address":"225 Amboy Rd",
    "sg:city":"Asheville",
    "sg:classifiers":[
        {
            "category":"Retail",
            "subcategory":"Repair Shop",
            "type":"Services"
        }
    ],
    "sg:phone":"+1 828 254 4676",
    "sg:postcode":"28806",
    "sg:province":"NC",
    "sg:tags":[
        "mobile",
        "automotive",
        "spring",
        "r",
        "v",
        "home"
    ],
    "wof:name":"Wilsons Mobile Home Repairs",
    "wof:placetype":"venue"
},
  "geometry": {"coordinates":[-82.58595699999999,35.567561],"type":"Point"}
}