{
  "type": "Feature",
  "properties": {
    "addr:full":"1725 N Fayetteville St Asheboro NC 27203",
    "addr:housenumber":"1725",
    "addr:postcode":"27203",
    "addr:street":"N;St",
    "iso:country":"US",
    "sg:address":"1725 N Fayetteville St",
    "sg:city":"Asheboro",
    "sg:classifiers":[
        {
            "category":"Retail",
            "subcategory":"Auto Repair",
            "type":"Services"
        }
    ],
    "sg:phone":"+1 336 672 2133",
    "sg:postcode":"27203",
    "sg:province":"NC",
    "sg:tags":[
        "repairing",
        "automobile"
    ],
    "wof:name":"Affordable Auto Repair",
    "wof:placetype":"venue"
},
  "geometry": {"coordinates":[-79.807699,35.743594],"type":"Point"}
}