{
  "type": "Feature",
  "properties": {
    "addr:full":"1876 John Mewborne Rd Kinston NC 28504",
    "addr:housenumber":"1876",
    "addr:postcode":"28504",
    "addr:street":"John Mewborne Rd",
    "iso:country":"US",
    "sg:address":"1876 John Mewborne Rd",
    "sg:city":"Kinston",
    "sg:classifiers":[
        {
            "category":"Organizations",
            "subcategory":"Religious Organization",
            "type":"Services"
        }
    ],
    "sg:phone":"+1 252 522 1367",
    "sg:postcode":"28504",
    "sg:province":"NC",
    "wof:name":"Burning Bush Holiness Church",
    "wof:placetype":"venue"
},
  "geometry": {"coordinates":[-77.59984300000001,35.316728],"type":"Point"}
}