{
  "type": "Feature",
  "properties": {
    "iso:country":"US",
    "sg:address":"501 Jasmine Ln",
    "sg:city":"Jacksonville",
    "sg:classifiers":[
        {
            "category":"Retail",
            "subcategory":"Repair Shop",
            "type":"Services"
        }
    ],
    "sg:phone":"+1   ",
    "sg:postcode":"28546",
    "sg:province":"NC",
    "wof:name":"Anointed Cleaning Service",
    "wof:placetype":"venue"
},
  "geometry": {"coordinates":[-77.348574,34.753426],"type":"Point"}
}