{
  "type": "Feature",
  "properties": {
    "iso:country":"US",
    "sg:address":"1200 Corporation Dr",
    "sg:city":"Archdale",
    "sg:classifiers":[
        {
            "category":"Wholesale",
            "subcategory":"Durable Goods & Equipment",
            "type":"Manufacturing & Wholesale Goods"
        }
    ],
    "sg:phone":"+1 336 861 5386",
    "sg:postcode":"27263",
    "sg:province":"NC",
    "sg:tags":[
        "importer"
    ],
    "wof:name":"Schat Import Agencies",
    "wof:placetype":"venue"
},
  "geometry": {"coordinates":[-80.00551299999999,35.916215],"type":"Point"}
}