{
  "type": "Feature",
  "properties": {
    "iso:country":"US",
    "sg:address":"141 Lambs Grill Rd",
    "sg:city":"Rutherfordton",
    "sg:classifiers":[
        {
            "category":"Food & Beverages",
            "subcategory":"Groceries & Convenience Stores",
            "type":"Retail Goods"
        }
    ],
    "sg:phone":"+1 828 863 4709",
    "sg:postcode":"28139",
    "sg:province":"NC",
    "sg:tags":[
        "grocer"
    ],
    "wof:name":"Lamb's Grocery",
    "wof:placetype":"venue"
},
  "geometry": {"coordinates":[-81.970651,35.202959],"type":"Point"}
}