{
  "type": "Feature",
  "properties": {
    "addr:full":"233 S Broad St Mooresville NC 28115",
    "addr:housenumber":"233",
    "addr:postcode":"28115",
    "addr:street":"S Broad St",
    "iso:country":"US",
    "sg:address":"233 S Broad St",
    "sg:city":"Mooresville",
    "sg:classifiers":[
        {
            "category":"Restaurant",
            "type":"Food & Drink"
        }
    ],
    "sg:menulink":"http://www.allmenus.com/nc/coddle-creek/43220-gregs/menu/",
    "sg:phone":"+1 704 847 5035",
    "sg:postcode":"28115",
    "sg:province":"NC",
    "sg:tags":[
        "barbecue",
        "american"
    ],
    "wof:name":"Greg's",
    "wof:placetype":"venue"
},
  "geometry": {"coordinates":[-80.81491200000001,35.581308],"type":"Point"}
}