{
  "type": "Feature",
  "properties": {
    "iso:country":"US",
    "sg:address":"3216 Libeth St",
    "sg:city":"Charlotte",
    "sg:classifiers":[
        {
            "category":"Manufacturing",
            "subcategory":"Tools & Machinery",
            "type":"Manufacturing & Wholesale Goods"
        }
    ],
    "sg:phone":"+1 704 535 8053",
    "sg:postcode":"28205",
    "sg:province":"NC",
    "sg:tags":[
        "metalworking",
        "mfg"
    ],
    "wof:name":"Omax Corp",
    "wof:placetype":"venue"
},
  "geometry": {"coordinates":[-80.786109,35.235131],"type":"Point"}
}