{
  "type": "Feature",
  "properties": {
    "addr:full":"216 W Broad St Statesville NC 28677",
    "addr:housenumber":"216",
    "addr:postcode":"28677",
    "addr:street":"W Broad St",
    "iso:country":"US",
    "sg:address":"216 W Broad St",
    "sg:city":"Statesville",
    "sg:classifiers":[
        {
            "category":"Manufacturing",
            "subcategory":"Tools & Machinery",
            "type":"Manufacturing & Wholesale Goods"
        }
    ],
    "sg:phone":"+1 704 873 7888",
    "sg:postcode":"28677",
    "sg:province":"NC",
    "sg:tags":[
        "physician",
        "surgeon"
    ],
    "wof:name":"Medi Garb Co Inc",
    "wof:placetype":"venue"
},
  "geometry": {"coordinates":[-80.89001399999999,35.784154],"type":"Point"}
}