{
  "type": "Feature",
  "properties": {
    "iso:country":"US",
    "sg:address":"318 Pettigrew Dr",
    "sg:city":"Wilmington",
    "sg:classifiers":[
        {
            "category":"Shopping",
            "subcategory":"Beauty & Cosmetics",
            "type":"Retail Goods"
        }
    ],
    "sg:phone":"+1 910 794 9449",
    "sg:postcode":"28412",
    "sg:province":"NC",
    "sg:tags":[
        "merchandise"
    ],
    "wof:name":"Susan Godbey",
    "wof:placetype":"venue"
},
  "geometry": {"coordinates":[-77.910524,34.189603],"type":"Point"}
}