{
  "type": "Feature",
  "properties": {
    "addr:full":"2328 Stonehaven Rd Kernersville NC 27284",
    "addr:housenumber":"2328",
    "addr:postcode":"27284",
    "addr:street":"Stonehaven Rd",
    "iso:country":"US",
    "sg:address":"2328 Stonehaven Rd",
    "sg:city":"Kernersville",
    "sg:classifiers":[
        {
            "category":"Building & Trades",
            "subcategory":"Construction",
            "type":"Services"
        }
    ],
    "sg:phone":"+1 336 643 8870",
    "sg:postcode":"27284",
    "sg:province":"NC",
    "sg:tags":[
        "hanging",
        "contractor"
    ],
    "wof:name":"Keener Tom Prof Pntg Wllcvring",
    "wof:placetype":"venue"
},
  "geometry": {"coordinates":[-80.050145,36.046497],"type":"Point"}
}