{
  "type": "Feature",
  "properties": {
    "iso:country":"US",
    "sg:address":"412 W Probart St",
    "sg:city":"Brevard",
    "sg:classifiers":[
        {
            "category":"Travel",
            "subcategory":"Hotels & Motels",
            "type":"Entertainment"
        }
    ],
    "sg:phone":"+1 828 884 9349",
    "sg:postcode":"28712",
    "sg:province":"NC",
    "sg:tags":[
        "breakfast",
        "accommodation",
        "bed"
    ],
    "wof:name":"Red House Inn",
    "wof:placetype":"venue"
},
  "geometry": {"coordinates":[-82.738231,35.236596],"type":"Point"}
}