{
  "type": "Feature",
  "properties": {
    "iso:country":"US",
    "sg:address":"4235 Glenwood Ave",
    "sg:city":"Raleigh",
    "sg:classifiers":[
        {
            "category":"Shopping",
            "subcategory":"Clothing, Apparel, & Fashions",
            "type":"Retail Goods"
        }
    ],
    "sg:phone":"+1 919 788 8902",
    "sg:postcode":"27612",
    "sg:province":"NC",
    "sg:tags":[
        "t"
    ],
    "wof:name":"Pretty As A Picture",
    "wof:placetype":"venue"
},
  "geometry": {"coordinates":[-78.674054,35.838247],"type":"Point"}
}