{
  "type": "Feature",
  "properties": {
    "iso:country":"US",
    "sg:address":"3720 Williams Dairy Rd",
    "sg:city":"Greensboro",
    "sg:classifiers":[
        {
            "category":"Freight",
            "type":"Transportation"
        }
    ],
    "sg:phone":"+1 336 674 7164",
    "sg:postcode":"27406",
    "sg:province":"NC",
    "sg:tags":[
        "hauling",
        "milk"
    ],
    "wof:name":"C & T Durham Trucking Co Inc",
    "wof:placetype":"venue"
},
  "geometry": {"coordinates":[-79.712846,36.011205],"type":"Point"}
}