{
  "type": "Feature",
  "properties": {
    "addr:full":"742 Court St Jacksonville NC 28540",
    "addr:housenumber":"742",
    "addr:postcode":"28540",
    "addr:street":"Court St",
    "iso:country":"US",
    "sg:address":"742 Court St",
    "sg:city":"Jacksonville",
    "sg:classifiers":[
        {
            "category":"Social Services",
            "type":"Services"
        }
    ],
    "sg:phone":"+1 910 455 4826",
    "sg:postcode":"28540",
    "sg:province":"NC",
    "sg:tags":[
        "probation"
    ],
    "wof:name":"Probation Dept",
    "wof:placetype":"venue"
},
  "geometry": {"coordinates":[-77.43047,34.752272],"type":"Point"}
}