{
  "type": "Feature",
  "properties": {
    "iso:country":"US",
    "sg:address":"4721 Atlantic Ave",
    "sg:city":"Raleigh",
    "sg:classifiers":[
        {
            "category":"Manufacturing",
            "subcategory":"Signs",
            "type":"Manufacturing & Wholesale Goods"
        }
    ],
    "sg:phone":"+1 919 872 1070",
    "sg:postcode":"27616",
    "sg:province":"NC",
    "sg:tags":[
        "specialty",
        "mfg"
    ],
    "sg:website":"www.signarama.com",
    "wof:name":"Sign-A-Rama",
    "wof:placetype":"venue"
},
  "geometry": {"coordinates":[-78.601609,35.845676],"type":"Point"}
}