{
  "type": "Feature",
  "properties": {
    "addr:full":"2109 N Marine Blvd Jacksonville NC 28546",
    "addr:housenumber":"2109",
    "addr:postcode":"28546",
    "addr:street":"N Marine Blvd",
    "iso:country":"US",
    "sg:address":"2109 N Marine Blvd",
    "sg:city":"Jacksonville",
    "sg:classifiers":[
        {
            "category":"Restaurant",
            "type":"Food & Drink"
        }
    ],
    "sg:phone":"+1 910 346 3690",
    "sg:postcode":"28546",
    "sg:province":"NC",
    "wof:name":"Sharp Shooters Sports Bar",
    "wof:placetype":"venue"
},
  "geometry": {"coordinates":[-77.38994599999999,34.779419],"type":"Point"}
}