{
  "type": "Feature",
  "properties": {
    "addr:full":"3880 State Hwy 11 Willard NC 28478",
    "addr:housenumber":"3880",
    "addr:postcode":"28478",
    "addr:street":"State Hwy 11",
    "iso:country":"US",
    "sg:address":"3880 State Hwy 11",
    "sg:city":"Willard",
    "sg:classifiers":[
        {
            "category":"Organizations",
            "subcategory":"Religious Organization",
            "type":"Services"
        }
    ],
    "sg:phone":"+1 910 285 2528",
    "sg:postcode":"28478",
    "sg:province":"NC",
    "sg:tags":[
        "church"
    ],
    "wof:name":"Penderlea Assembly Of God Chr",
    "wof:placetype":"venue"
},
  "geometry": {"coordinates":[-78.049297,34.659269],"type":"Point"}
}