{
  "type": "Feature",
  "properties": {
    "addr:full":"705 National Hwy Thomasville NC 27360",
    "addr:housenumber":"705",
    "addr:postcode":"27360",
    "addr:street":"National Hwy",
    "iso:country":"US",
    "sg:address":"705 National Hwy",
    "sg:city":"Thomasville",
    "sg:classifiers":[
        {
            "category":"Food & Beverages",
            "subcategory":"Groceries & Convenience Stores",
            "type":"Retail Goods"
        }
    ],
    "sg:phone":"+1 336 475 4836",
    "sg:postcode":"27360",
    "sg:province":"NC",
    "wof:name":"Kangaroo Express",
    "wof:placetype":"venue"
},
  "geometry": {"coordinates":[-80.06729900000001,35.898913],"type":"Point"}
}