{
  "type": "Feature",
  "properties": {
    "iso:country":"US",
    "sg:address":"2704 State Hwy 210 W",
    "sg:city":"Garland",
    "sg:classifiers":[
        {
            "category":"Restaurant",
            "type":"Food & Drink"
        }
    ],
    "sg:phone":"+1 910 588 4397",
    "sg:postcode":"28441",
    "sg:province":"NC",
    "sg:tags":[
        "eating"
    ],
    "wof:name":"Cypress Creek Gro & Grill",
    "wof:placetype":"venue"
},
  "geometry": {"coordinates":[-78.454559,34.775588],"type":"Point"}
}