{
  "type": "Feature",
  "properties": {
    "addr:full":"117 E Hornes Church Rd Wilson NC 27896",
    "addr:housenumber":"117",
    "addr:postcode":"27896",
    "addr:street":"E Hornes Church Rd",
    "iso:country":"US",
    "sg:address":"117 E Hornes Church Rd",
    "sg:city":"Wilson",
    "sg:classifiers":[
        {
            "category":"Retail",
            "subcategory":"Repair Shop",
            "type":"Services"
        }
    ],
    "sg:phone":"+1   ",
    "sg:postcode":"27896",
    "sg:province":"NC",
    "wof:name":"Ajs Motorcycle & Atv Repairs",
    "wof:placetype":"venue"
},
  "geometry": {"coordinates":[-78.00167399999999,35.810146],"type":"Point"}
}