{
  "type": "Feature",
  "properties": {
    "addr:full":"280 Broad St Kernersville NC 27284",
    "addr:housenumber":"280",
    "addr:postcode":"27284",
    "addr:street":"Broad St",
    "iso:country":"US",
    "sg:address":"280 Broad St",
    "sg:city":"Kernersville",
    "sg:classifiers":[
        {
            "category":"Health Services",
            "subcategory":"Doctor",
            "type":"Services"
        }
    ],
    "sg:phone":"+1 336 993 0870",
    "sg:postcode":"27284",
    "sg:province":"NC",
    "sg:tags":[
        "physician",
        "surgeon"
    ],
    "wof:name":"Salem Neurological Ctr PA",
    "wof:placetype":"venue"
},
  "geometry": {"coordinates":[-80.071958,36.11342],"type":"Point"}
}