{
  "type": "Feature",
  "properties": {
    "iso:country":"US",
    "sg:address":"1205 Country Ridge Dr",
    "sg:city":"Raleigh",
    "sg:classifiers":[
        {
            "category":"Professional",
            "subcategory":"Management & Consulting",
            "type":"Services"
        }
    ],
    "sg:phone":"+1   ",
    "sg:postcode":"27609",
    "sg:province":"NC",
    "sg:tags":[
        "business"
    ],
    "wof:name":"Norman Plaks PHD Consultant",
    "wof:placetype":"venue"
},
  "geometry": {"coordinates":[-78.61497300000001,35.847973],"type":"Point"}
}