{
  "type": "Feature",
  "properties": {
    "iso:country":"US",
    "sg:address":"517 SALISBURY AVE",
    "sg:city":"ALBEMARLE",
    "sg:classifiers":[
        {
            "category":"Shopping",
            "subcategory":"Bicycles & Sporting Goods",
            "type":"Retail Goods"
        },
        {
            "category":"Wholesale",
            "subcategory":"Apparel",
            "type":"Manufacturing & Wholesale Goods"
        },
        {
            "category":"Shopping",
            "subcategory":"Shoes",
            "type":"Retail Goods"
        },
        {
            "category":"Personal",
            "subcategory":"Shoe Repair & Shine",
            "type":"Services"
        }
    ],
    "sg:phone":"+1 704 982 7463",
    "sg:postcode":"28001",
    "sg:province":"NC",
    "sg:tags":[
        "made",
        "boots-retail",
        "boots-custom",
        "shoes-wholesale",
        "store",
        "manufacturer"
    ],
    "wof:name":"Cooper Shoes",
    "wof:placetype":"venue"
},
  "geometry": {"coordinates":[-80.20474900000001,35.361501],"type":"Point"}
}