{
  "type": "Feature",
  "properties": {
    "addr:full":"7600 Mine Shaft Rd Raleigh NC 27615",
    "addr:housenumber":"7600",
    "addr:postcode":"27615",
    "addr:street":"Mine Shaft Rd",
    "iso:country":"US",
    "sg:address":"7600 Mine Shaft Rd",
    "sg:city":"Raleigh",
    "sg:classifiers":[
        {
            "category":"Building & Trades",
            "subcategory":"Cleaning & Sanitation",
            "type":"Services"
        }
    ],
    "sg:phone":"+1   ",
    "sg:postcode":"27615",
    "sg:province":"NC",
    "sg:tags":[
        "maintenance"
    ],
    "wof:name":"Meeras Building Cleaning",
    "wof:placetype":"venue"
},
  "geometry": {"coordinates":[-78.65567799999999,35.881783],"type":"Point"}
}