{
  "type": "Feature",
  "properties": {
    "addr:full":"1001 N Salisbury Ave Spencer NC 28159",
    "addr:housenumber":"1001",
    "addr:postcode":"28159",
    "addr:street":"N Salisbury Ave",
    "iso:country":"US",
    "sg:address":"1001 N Salisbury Ave",
    "sg:city":"Spencer",
    "sg:classifiers":[
        {
            "category":"Organizations",
            "subcategory":"Professional Association",
            "type":"Services"
        }
    ],
    "sg:phone":"+1 704 638 6263",
    "sg:postcode":"28159",
    "sg:province":"NC",
    "wof:name":"Pride Of Salisbury Elk Lodge",
    "wof:placetype":"venue"
},
  "geometry": {"coordinates":[-80.41884400000001,35.698608],"type":"Point"}
}