{
  "type": "Feature",
  "properties": {
    "iso:country":"US",
    "sg:address":"320 Nash St E",
    "sg:city":"Wilson",
    "sg:classifiers":[
        {
            "category":"Local Transit",
            "type":"Transportation"
        }
    ],
    "sg:phone":"+1 252 243 3279",
    "sg:postcode":"27893",
    "sg:province":"NC",
    "sg:tags":[
        "bus",
        "line"
    ],
    "wof:name":"Carolina Trailways",
    "wof:placetype":"venue"
},
  "geometry": {"coordinates":[-77.909288,35.723891],"type":"Point"}
}