{
  "type": "Feature",
  "properties": {
    "addr:full":"1500 Mount Zion Pl Winston Salem NC 27101",
    "addr:housenumber":"1500",
    "addr:postcode":"27101",
    "addr:street":"Mount Zion Pl",
    "iso:country":"US",
    "sg:address":"1500 Mount Zion Pl",
    "sg:city":"Winston Salem",
    "sg:classifiers":[
        {
            "category":"Personal",
            "subcategory":"Beauty Salon",
            "type":"Services"
        }
    ],
    "sg:phone":"+1 336 721 2938",
    "sg:postcode":"27101",
    "sg:province":"NC",
    "wof:name":"Sassy Styles By Shannon",
    "wof:placetype":"venue"
},
  "geometry": {"coordinates":[-80.228612,36.104186],"type":"Point"}
}