{
  "type": "Feature",
  "properties": {
    "addr:full":"8424 State Rd 49 N Mt Pleasant NC 28124",
    "addr:housenumber":"8424;49",
    "addr:postcode":"28124",
    "addr:street":"State Rd;N",
    "iso:country":"US",
    "sg:address":"8424 State Rd 49 N",
    "sg:city":"Mt Pleasant",
    "sg:classifiers":[
        {
            "category":"Autos & Motor Vehicles",
            "subcategory":"Fuel & Gas Station",
            "type":"Retail Goods"
        }
    ],
    "sg:phone":"+1 704 436 9914",
    "sg:postcode":"28124",
    "sg:province":"NC",
    "sg:tags":[
        "station",
        "gasoline",
        "oil"
    ],
    "wof:name":"Fisher Earnhardt Oil Co",
    "wof:placetype":"venue"
},
  "geometry": {"coordinates":[-80.44802,35.366216],"type":"Point"}
}