{
  "type": "Feature",
  "properties": {
    "addr:full":"7032 Brighton Brook Dr Charlotte NC 28212",
    "addr:housenumber":"7032",
    "addr:postcode":"28212",
    "addr:street":"Brighton Brook Dr",
    "iso:country":"US",
    "sg:address":"7032 Brighton Brook Dr",
    "sg:city":"Charlotte",
    "sg:classifiers":[
        {
            "category":"Personal",
            "subcategory":"Beauty Salon",
            "type":"Services"
        }
    ],
    "sg:phone":"+1 704 545 5523",
    "sg:postcode":"28212",
    "sg:province":"NC",
    "wof:name":"Great Clips",
    "wof:placetype":"venue"
},
  "geometry": {"coordinates":[-80.74718300000001,35.179795],"type":"Point"}
}