{
  "type": "Feature",
  "properties": {
    "addr:full":"501 Louise Ave Charlotte NC 28204",
    "addr:housenumber":"501",
    "addr:postcode":"28204",
    "addr:street":"Louise Ave",
    "iso:country":"US",
    "sg:address":"501 Louise Ave",
    "sg:city":"Charlotte",
    "sg:classifiers":[
        {
            "category":"Building & Trades",
            "subcategory":"Plumbing",
            "type":"Services"
        }
    ],
    "sg:phone":"+1 704 334 1404",
    "sg:postcode":"28204",
    "sg:province":"NC",
    "sg:tags":[
        "contractor"
    ],
    "wof:name":"J T Holzinger Plumbing",
    "wof:placetype":"venue"
},
  "geometry": {"coordinates":[-80.82249,35.218458],"type":"Point"}
}