{
  "type": "Feature",
  "properties": {
    "iso:country":"US",
    "sg:address":"436 Colington Dr",
    "sg:city":"Kill Devil Hills",
    "sg:classifiers":[
        {
            "category":"Travel",
            "subcategory":"Travel Agent",
            "type":"Entertainment"
        }
    ],
    "sg:phone":"+1 252 441 6738",
    "sg:postcode":"27948",
    "sg:province":"NC",
    "sg:tags":[
        "operator",
        "tour"
    ],
    "wof:name":"Sandy Beach Tours LLC",
    "wof:placetype":"venue"
},
  "geometry": {"coordinates":[-75.71569,36.018103],"type":"Point"}
}