{
  "type": "Feature",
  "properties": {
    "addr:full":"500 Lincolnton Rd Salisbury NC 28144",
    "addr:housenumber":"500",
    "addr:postcode":"28144",
    "addr:street":"Lincolnton Rd",
    "iso:country":"US",
    "sg:address":"500 Lincolnton Rd",
    "sg:city":"Salisbury",
    "sg:classifiers":[
        {
            "category":"Education",
            "subcategory":"School",
            "type":"Public Place"
        }
    ],
    "sg:phone":"+1 704 636 1221",
    "sg:postcode":"28144",
    "sg:province":"NC",
    "sg:website":"www.shs-hornets.com",
    "wof:name":"Salisbury High School",
    "wof:placetype":"venue"
},
  "geometry": {"coordinates":[-80.482176,35.663767],"type":"Point"}
}