{
  "type": "Feature",
  "properties": {
    "iso:country":"US",
    "sg:address":"145 Rowan St",
    "sg:city":"Fayetteville",
    "sg:classifiers":[
        {
            "category":"Communications",
            "subcategory":"Radio Station",
            "type":"Services"
        }
    ],
    "sg:phone":"+1 910 483 6111",
    "sg:postcode":"28301",
    "sg:province":"NC",
    "sg:tags":[
        "company",
        "broadcasting"
    ],
    "sg:website":"www.widu.net",
    "wof:name":"WIDU",
    "wof:placetype":"venue"
},
  "geometry": {"coordinates":[-78.87869600000001,35.057767],"type":"Point"}
}