{
  "type": "Feature",
  "properties": {
    "addr:full":"6201 Westgate Rd Raleigh NC 27617",
    "addr:housenumber":"6201",
    "addr:postcode":"27617",
    "addr:street":"Westgate Rd",
    "iso:country":"US",
    "sg:address":"6201 Westgate Rd",
    "sg:city":"Raleigh",
    "sg:classifiers":[
        {
            "category":"Wholesale",
            "subcategory":"Machinery & Supplies",
            "type":"Manufacturing & Wholesale Goods"
        }
    ],
    "sg:phone":"+1 919 782 7732",
    "sg:postcode":"27617",
    "sg:province":"NC",
    "wof:name":"Viasys Services Inc",
    "wof:placetype":"venue"
},
  "geometry": {"coordinates":[-78.75476399999999,35.904125],"type":"Point"}
}