{
  "type": "Feature",
  "properties": {
    "addr:full":"726 S Main St Mount Holly NC 28120",
    "addr:housenumber":"726",
    "addr:postcode":"28120",
    "addr:street":"S Main St",
    "iso:country":"US",
    "sg:address":"726 S Main St",
    "sg:city":"Mount Holly",
    "sg:classifiers":[
        {
            "category":"Building & Trades",
            "subcategory":"Construction",
            "type":"Services"
        }
    ],
    "sg:phone":"+1 704 827 7500",
    "sg:postcode":"28120",
    "sg:province":"NC",
    "sg:tags":[
        "concrete",
        "contractor"
    ],
    "wof:name":"Custom Concrete Work",
    "wof:placetype":"venue"
},
  "geometry": {"coordinates":[-81.020954,35.287886],"type":"Point"}
}