{
  "type": "Feature",
  "properties": {
    "iso:country":"US",
    "sg:address":"215 Sacco St",
    "sg:city":"Belmont",
    "sg:classifiers":[
        {
            "category":"Organizations",
            "subcategory":"Religious Organization",
            "type":"Services"
        }
    ],
    "sg:phone":"+1 704 825 6007",
    "sg:postcode":"28012",
    "sg:province":"NC",
    "sg:tags":[
        "church"
    ],
    "wof:name":"Hood Memorial AME Zion Church",
    "wof:placetype":"venue"
},
  "geometry": {"coordinates":[-81.046924,35.247193],"type":"Point"}
}