{
  "type": "Feature",
  "properties": {
    "iso:country":"US",
    "sg:address":"1221 Salisbury Ave",
    "sg:city":"Albemarle",
    "sg:classifiers":[
        {
            "category":"Personal",
            "type":"Services"
        }
    ],
    "sg:phone":"+1 704 983 5633",
    "sg:postcode":"28001",
    "sg:province":"NC",
    "sg:tags":[
        "consultant",
        "wedding"
    ],
    "wof:name":"Bride's Choice",
    "wof:placetype":"venue"
},
  "geometry": {"coordinates":[-80.20873899999999,35.366144],"type":"Point"}
}