{
  "type": "Feature",
  "properties": {
    "addr:full":"1305 Lakewood Rd Four Oaks NC 27524",
    "addr:housenumber":"1305",
    "addr:postcode":"27524",
    "addr:street":"Lakewood Rd",
    "iso:country":"US",
    "sg:address":"1305 Lakewood Rd",
    "sg:city":"Four Oaks",
    "sg:classifiers":[
        {
            "category":"Retail",
            "subcategory":"Animal Services",
            "type":"Services"
        }
    ],
    "sg:phone":"+1 919 934 1344",
    "sg:postcode":"27524",
    "sg:province":"NC",
    "wof:name":"Bm Stables",
    "wof:placetype":"venue"
},
  "geometry": {"coordinates":[-78.48718,35.502943],"type":"Point"}
}