{
  "type": "Feature",
  "properties": {
    "iso:country":"US",
    "sg:address":"1901 Lake Pine Dr",
    "sg:city":"Apex",
    "sg:classifiers":[
        {
            "category":"Retail",
            "subcategory":"Auto Repair",
            "type":"Services"
        }
    ],
    "sg:phone":"+1 919 363 7077",
    "sg:postcode":"27511",
    "sg:province":"NC",
    "sg:tags":[
        "repairing",
        "automobile"
    ],
    "wof:name":"Peak Automotive",
    "wof:placetype":"venue"
},
  "geometry": {"coordinates":[-78.821359,35.74359],"type":"Point"}
}