{
  "type": "Feature",
  "properties": {
    "iso:country":"US",
    "sg:address":"830 Westbrook Dr",
    "sg:city":"Newton",
    "sg:classifiers":[
        {
            "category":"Professional",
            "subcategory":"Business Services",
            "type":"Services"
        }
    ],
    "sg:phone":"+1   ",
    "sg:postcode":"28658",
    "sg:province":"NC",
    "sg:tags":[
        "individual",
        "grant"
    ],
    "wof:name":"McMahan  Newell C",
    "wof:placetype":"venue"
},
  "geometry": {"coordinates":[-81.234977,35.677815],"type":"Point"}
}