{
  "type": "Feature",
  "properties": {
    "iso:country":"US",
    "sg:address":"603 Highland Ave",
    "sg:city":"Henderson",
    "sg:classifiers":[
        {
            "category":"Building & Trades",
            "subcategory":"Construction",
            "type":"Services"
        }
    ],
    "sg:phone":"+1 252 767 5229",
    "sg:postcode":"27536",
    "sg:province":"NC",
    "sg:tags":[
        "remodeling"
    ],
    "wof:name":"D & B Home Improvement",
    "wof:placetype":"venue"
},
  "geometry": {"coordinates":[-78.39483300000001,36.330047],"type":"Point"}
}