{
  "type": "Feature",
  "properties": {
    "iso:country":"US",
    "sg:address":"1401 West Rd",
    "sg:city":"Camp Lejeune",
    "sg:classifiers":[
        {
            "category":"Travel",
            "subcategory":"Travel Agent",
            "type":"Entertainment"
        }
    ],
    "sg:phone":"+1 910 451 3788",
    "sg:postcode":"28501",
    "sg:province":"NC",
    "sg:tags":[
        "agency",
        "bureau"
    ],
    "wof:name":"All Points Travel",
    "wof:placetype":"venue"
},
  "geometry": {"coordinates":[-77.59216499999999,35.277389],"type":"Point"}
}