{
  "type": "Feature",
  "properties": {
    "addr:full":"1624 S Hawthorne Rd Winston Salem NC 27103",
    "addr:housenumber":"1624",
    "addr:postcode":"27103",
    "addr:street":"S Hawthorne Rd",
    "iso:country":"US",
    "sg:address":"1624 S Hawthorne Rd",
    "sg:city":"Winston Salem",
    "sg:classifiers":[
        {
            "category":"Insurance",
            "subcategory":"Insurance Agent",
            "type":"Services"
        }
    ],
    "sg:phone":"+1 336 765 0301",
    "sg:postcode":"27103",
    "sg:province":"NC",
    "wof:name":"State Farm Insurance",
    "wof:placetype":"venue"
},
  "geometry": {"coordinates":[-80.29068100000001,36.078164],"type":"Point"}
}