{
  "type": "Feature",
  "properties": {
    "iso:country":"US",
    "sg:address":"615 Mathis Farm Rd",
    "sg:city":"Roaring River",
    "sg:classifiers":[
        {
            "category":"Farming",
            "subcategory":"Farm",
            "type":"Manufacturing & Wholesale Goods"
        }
    ],
    "sg:phone":"+1 336 984 3380",
    "sg:postcode":"28669",
    "sg:province":"NC",
    "wof:name":"Mathis ASJ Farms",
    "wof:placetype":"venue"
},
  "geometry": {"coordinates":[-80.99072,36.150639],"type":"Point"}
}