{
  "type": "Feature",
  "properties": {
    "addr:full":"1101 Matthews-Mint Hill Rd Matthews NC 28105",
    "addr:housenumber":"1101",
    "addr:postcode":"28105",
    "addr:street":"Matthews-Mint Hill Rd",
    "iso:country":"US",
    "sg:address":"1101 Matthews-Mint Hill Rd",
    "sg:city":"Matthews",
    "sg:classifiers":[
        {
            "category":"Utilities",
            "subcategory":"Telephone",
            "type":"Services"
        }
    ],
    "sg:phone":"+1 704 847 1664",
    "sg:postcode":"28105",
    "sg:province":"NC",
    "sg:tags":[
        "communications"
    ],
    "wof:name":"Alltel",
    "wof:placetype":"venue"
},
  "geometry": {"coordinates":[-80.702572,35.11791],"type":"Point"}
}