{
  "type": "Feature",
  "properties": {
    "iso:country":"US",
    "sg:address":"142 Consumer Square Dr",
    "sg:city":"Mooresville",
    "sg:classifiers":[
        {
            "category":"Restaurant",
            "type":"Food & Drink"
        }
    ],
    "sg:phone":"+1 704 658 9215",
    "sg:postcode":"28117",
    "sg:province":"NC",
    "sg:website":"www.roadhousegrill.com",
    "wof:name":"Roadhouse Grill Inc",
    "wof:placetype":"venue"
},
  "geometry": {"coordinates":[-80.857496,35.59316],"type":"Point"}
}