{
  "type": "Feature",
  "properties": {
    "iso:country":"US",
    "sg:address":"931 S Fayetteville St",
    "sg:city":"Asheboro",
    "sg:classifiers":[
        {
            "category":"Autos & Motor Vehicles",
            "subcategory":"Automobile Sales",
            "type":"Retail Goods"
        }
    ],
    "sg:phone":"+1 336 629 2020",
    "sg:postcode":"27203",
    "sg:province":"NC",
    "sg:tags":[
        "car",
        "used",
        "dealer"
    ],
    "sg:website":"www.qualityautoonline.com",
    "wof:name":"Quality Auto Sales Corporation",
    "wof:placetype":"venue"
},
  "geometry": {"coordinates":[-79.81531,35.694978],"type":"Point"}
}