{
  "type": "Feature",
  "properties": {
    "addr:full":"404 Peerless Ln Lowell NC 28098",
    "addr:housenumber":"404",
    "addr:postcode":"28098",
    "addr:street":"Peerless Ln",
    "iso:country":"US",
    "sg:address":"404 Peerless Ln",
    "sg:city":"Lowell",
    "sg:classifiers":[
        {
            "category":"Manufacturing",
            "subcategory":"Textiles",
            "type":"Manufacturing & Wholesale Goods"
        }
    ],
    "sg:phone":"+1 704 824 3855",
    "sg:postcode":"28098",
    "sg:province":"NC",
    "sg:tags":[
        "mills",
        "yarn"
    ],
    "wof:name":"Parkdale Mills Inc",
    "wof:placetype":"venue"
},
  "geometry": {"coordinates":[-81.10499799999999,35.27053],"type":"Point"}
}