{
  "type": "Feature",
  "properties": {
    "iso:country":"US",
    "sg:address":"5646 Hampton Rd",
    "sg:city":"Clemmons",
    "sg:classifiers":[
        {
            "category":"Shopping",
            "subcategory":"Jewelry",
            "type":"Retail Goods"
        }
    ],
    "sg:phone":"+1 336 766 7397",
    "sg:postcode":"27012",
    "sg:province":"NC",
    "wof:name":"Lucky Finds Inc",
    "wof:placetype":"venue"
},
  "geometry": {"coordinates":[-80.367195,35.9742],"type":"Point"}
}