{
  "type": "Feature",
  "properties": {
    "addr:full":"6357 Pittman Grove Church Rd Raeford NC 28376",
    "addr:housenumber":"6357",
    "addr:postcode":"28376",
    "addr:street":"Pittman Grove Church Rd",
    "iso:country":"US",
    "sg:address":"6357 Pittman Grove Church Rd",
    "sg:city":"Raeford",
    "sg:classifiers":[
        {
            "category":"Professional",
            "subcategory":"Management & Consulting",
            "type":"Services"
        }
    ],
    "sg:phone":"+1   ",
    "sg:postcode":"28376",
    "sg:province":"NC",
    "sg:tags":[
        "marketing"
    ],
    "wof:name":"DSA Marketing & Associates",
    "wof:placetype":"venue"
},
  "geometry": {"coordinates":[-79.058324,34.951803],"type":"Point"}
}