{
  "type": "Feature",
  "properties": {
    "addr:full":"812 W King St Kings Mountain NC 28086",
    "addr:housenumber":"812",
    "addr:postcode":"28086",
    "addr:street":"W King St",
    "iso:country":"US",
    "sg:address":"812 W King St",
    "sg:city":"Kings Mountain",
    "sg:classifiers":[
        {
            "category":"Health Services",
            "subcategory":"Doctor",
            "type":"Services"
        }
    ],
    "sg:phone":"+1 704 730 8877",
    "sg:postcode":"28086",
    "sg:province":"NC",
    "sg:tags":[
        "physician",
        "surgeon"
    ],
    "wof:name":"Nephrology Associates",
    "wof:placetype":"venue"
},
  "geometry": {"coordinates":[-81.358138,35.240459],"type":"Point"}
}