{
  "type": "Feature",
  "properties": {
    "iso:country":"US",
    "sg:address":"216 Pepperidge Ln",
    "sg:city":"Monroe",
    "sg:classifiers":[
        {
            "category":"Professional",
            "type":"Services"
        }
    ],
    "sg:phone":"+1 704 282 2391",
    "sg:postcode":"28110",
    "sg:province":"NC",
    "wof:name":"Davis Metal Components",
    "wof:placetype":"venue"
},
  "geometry": {"coordinates":[-80.5438,35.01978],"type":"Point"}
}