{
  "type": "Feature",
  "properties": {
    "addr:full":"112 E 7th Ave Chadbourn NC 28431",
    "addr:housenumber":"112",
    "addr:postcode":"28431",
    "addr:street":"E 7Th Ave",
    "iso:country":"US",
    "sg:address":"112 E 7th Ave",
    "sg:city":"Chadbourn",
    "sg:classifiers":[
        {
            "category":"Wholesale",
            "subcategory":"Drugs",
            "type":"Manufacturing & Wholesale Goods"
        }
    ],
    "sg:phone":"+1 910 654 5735",
    "sg:postcode":"28431",
    "sg:province":"NC",
    "wof:name":"Kuntz Drug Co Inc",
    "wof:placetype":"venue"
},
  "geometry": {"coordinates":[-78.826289,34.329631],"type":"Point"}
}