{
  "type": "Feature",
  "properties": {
    "addr:full":"4211 Foxmoor Dr Charlotte NC 28226",
    "addr:housenumber":"4211",
    "addr:postcode":"28226",
    "addr:street":"Foxmoor Dr",
    "iso:country":"US",
    "sg:address":"4211 Foxmoor Dr",
    "sg:city":"Charlotte",
    "sg:classifiers":[
        {
            "category":"Building & Trades",
            "subcategory":"Construction",
            "type":"Services"
        }
    ],
    "sg:phone":"+1 704 424 5555",
    "sg:postcode":"28226",
    "sg:province":"NC",
    "sg:tags":[
        "painter"
    ],
    "wof:name":"Painting Pros",
    "wof:placetype":"venue"
},
  "geometry": {"coordinates":[-80.82682800000001,35.107936],"type":"Point"}
}