{
  "type": "Feature",
  "properties": {
    "addr:full":"4900 Green Rd Raleigh NC 27616",
    "addr:housenumber":"4900",
    "addr:postcode":"27616",
    "addr:street":"Green Rd",
    "iso:country":"US",
    "sg:address":"4900 Green Rd",
    "sg:city":"Raleigh",
    "sg:classifiers":[
        {
            "category":"Shopping",
            "subcategory":"Musical Instruments",
            "type":"Retail Goods"
        }
    ],
    "sg:phone":"+1 919 872 0211",
    "sg:postcode":"27616",
    "sg:province":"NC",
    "sg:website":"www.burrage.com",
    "wof:name":"Burrage Music Co",
    "wof:placetype":"venue"
},
  "geometry": {"coordinates":[-78.586512,35.849447],"type":"Point"}
}