{
  "type": "Feature",
  "properties": {
    "iso:country":"US",
    "sg:address":"140 Southcenter Ct",
    "sg:city":"Morrisville",
    "sg:classifiers":[
        {
            "category":"Freight",
            "type":"Transportation"
        }
    ],
    "sg:phone":"+1 919 465 0499",
    "sg:postcode":"27560",
    "sg:province":"NC",
    "sg:tags":[
        "forwarding",
        "foreign"
    ],
    "wof:name":"Nippon Express USA Inc",
    "wof:placetype":"venue"
},
  "geometry": {"coordinates":[-78.814421,35.837782],"type":"Point"}
}