{
  "type": "Feature",
  "properties": {
    "addr:full":"964 Baptist Chapel Rd Autryville NC 28318",
    "addr:housenumber":"964",
    "addr:postcode":"28318",
    "addr:street":"Baptist Chapel Rd",
    "iso:country":"US",
    "sg:address":"964 Baptist Chapel Rd",
    "sg:city":"Autryville",
    "sg:classifiers":[
        {
            "category":"Building & Trades",
            "subcategory":"Construction",
            "type":"Services"
        }
    ],
    "sg:phone":"+1 910 567 2735",
    "sg:postcode":"28318",
    "sg:province":"NC",
    "sg:tags":[
        "carpentry",
        "contractor"
    ],
    "wof:name":"Honeycutt Custom Cabinets",
    "wof:placetype":"venue"
},
  "geometry": {"coordinates":[-78.551765,35.124723],"type":"Point"}
}