{
  "type": "Feature",
  "properties": {
    "addr:full":"291 S Talbert Blvd Lexington NC 27292",
    "addr:housenumber":"291",
    "addr:postcode":"27292",
    "addr:street":"S Talbert Blvd",
    "iso:country":"US",
    "sg:address":"291 S Talbert Blvd",
    "sg:city":"Lexington",
    "sg:classifiers":[
        {
            "category":"Food & Beverages",
            "subcategory":"Groceries & Convenience Stores",
            "type":"Retail Goods"
        }
    ],
    "sg:phone":"+1 336 243 2346",
    "sg:postcode":"27292",
    "sg:province":"NC",
    "sg:tags":[
        "grocer"
    ],
    "sg:website":"www.foodlion.com",
    "wof:name":"Food Lion",
    "wof:placetype":"venue"
},
  "geometry": {"coordinates":[-80.25144,35.814685],"type":"Point"}
}