{
  "type": "Feature",
  "properties": {
    "iso:country":"US",
    "sg:address":"1 Grouse Pt",
    "sg:city":"Cashiers",
    "sg:classifiers":[
        {
            "category":"Shopping",
            "subcategory":"Florist",
            "type":"Retail Goods"
        }
    ],
    "sg:phone":"+1 828 743 3858",
    "sg:postcode":"28762",
    "sg:province":"NC",
    "wof:name":"Petal Pusher Florist",
    "wof:placetype":"venue"
},
  "geometry": {"coordinates":[-82.17320599999999,35.536927],"type":"Point"}
}