{
  "type": "Feature",
  "properties": {
    "iso:country":"US",
    "sg:address":"115 Joy Ln",
    "sg:city":"Roxboro",
    "sg:classifiers":[
        {
            "category":"Organizations",
            "subcategory":"Religious Organization",
            "type":"Services"
        }
    ],
    "sg:phone":"+1 336 599 5843",
    "sg:postcode":"27574",
    "sg:province":"NC",
    "sg:tags":[
        "church"
    ],
    "wof:name":"Mt Road Baptist Church",
    "wof:placetype":"venue"
},
  "geometry": {"coordinates":[-78.922878,36.391253],"type":"Point"}
}