{
  "type": "Feature",
  "properties": {
    "addr:full":"3005 Phillips Rd Wilson NC 27896",
    "addr:housenumber":"3005",
    "addr:postcode":"27896",
    "addr:street":"Phillips Rd",
    "iso:country":"US",
    "sg:address":"3005 Phillips Rd",
    "sg:city":"Wilson",
    "sg:classifiers":[
        {
            "category":"Professional",
            "subcategory":"Computer Services",
            "type":"Services"
        }
    ],
    "sg:phone":"+1 252 243 1819",
    "sg:postcode":"27896",
    "sg:province":"NC",
    "sg:tags":[
        "website",
        "design"
    ],
    "sg:website":"www.tarheelsearch.com",
    "wof:name":"TARHEELSEARCH.COM",
    "wof:placetype":"venue"
},
  "geometry": {"coordinates":[-77.91522999999999,35.777813],"type":"Point"}
}