{
  "type": "Feature",
  "properties": {
    "iso:country":"US",
    "sg:address":"6870 Towbridge Rd",
    "sg:city":"Fayetteville",
    "sg:classifiers":[
        {
            "category":"Professional",
            "type":"Services"
        }
    ],
    "sg:phone":"+1   ",
    "sg:postcode":"28306",
    "sg:province":"NC",
    "wof:name":"Marstine Services Inc",
    "wof:placetype":"venue"
},
  "geometry": {"coordinates":[-79.014353,34.991962],"type":"Point"}
}