{
  "type": "Feature",
  "properties": {
    "addr:full":"301 Bunn Rd Louisburg NC 27549",
    "addr:housenumber":"301",
    "addr:postcode":"27549",
    "addr:street":"Bunn Rd",
    "iso:country":"US",
    "sg:address":"301 Bunn Rd",
    "sg:city":"Louisburg",
    "sg:classifiers":[
        {
            "category":"Professional",
            "type":"Services"
        }
    ],
    "sg:phone":"+1 919 497 0002",
    "sg:postcode":"27549",
    "sg:province":"NC",
    "sg:tags":[
        "establishment"
    ],
    "wof:name":"Bluebird Habitat Inc",
    "wof:placetype":"venue"
},
  "geometry": {"coordinates":[-78.30468399999999,36.089065],"type":"Point"}
}