{
  "type": "Feature",
  "properties": {
    "addr:full":"402 Old Farm Rd Thomasville NC 27360",
    "addr:housenumber":"402",
    "addr:postcode":"27360",
    "addr:street":"Old Farm Rd",
    "iso:country":"US",
    "sg:address":"402 Old Farm Rd",
    "sg:city":"Thomasville",
    "sg:classifiers":[
        {
            "category":"Manufacturing",
            "subcategory":"Paper Products",
            "type":"Manufacturing & Wholesale Goods"
        }
    ],
    "sg:phone":"+1 336 472 4977",
    "sg:postcode":"27360",
    "sg:province":"NC",
    "sg:tags":[
        "mill"
    ],
    "wof:name":"Pactiv Corporation",
    "wof:placetype":"venue"
},
  "geometry": {"coordinates":[-80.05194899999999,35.848692],"type":"Point"}
}