{
  "type": "Feature",
  "properties": {
    "iso:country":"US",
    "sg:address":"214 Sneads Ferry Rd",
    "sg:city":"Sneads Ferry",
    "sg:classifiers":[
        {
            "category":"Real Estate",
            "subcategory":"Real Estate Agent",
            "type":"Services"
        }
    ],
    "sg:phone":"+1 910 327 6161",
    "sg:postcode":"28460",
    "sg:province":"NC",
    "wof:name":"Davis Real Estate",
    "wof:placetype":"venue"
},
  "geometry": {"coordinates":[-77.397378,34.552828],"type":"Point"}
}