{
  "type": "Feature",
  "properties": {
    "iso:country":"US",
    "sg:address":"200 Crossroads Blvd",
    "sg:city":"Cary",
    "sg:classifiers":[
        {
            "category":"Restaurant",
            "type":"Food & Drink"
        }
    ],
    "sg:phone":"+1 919 859 2454",
    "sg:postcode":"27518",
    "sg:province":"NC",
    "sg:tags":[
        "steak"
    ],
    "wof:name":"Ryans",
    "wof:placetype":"venue"
},
  "geometry": {"coordinates":[-78.74186899999999,35.761321],"type":"Point"}
}