{
  "type": "Feature",
  "properties": {
    "addr:full":"5832 Fayetteville Rd Durham NC 27713",
    "addr:housenumber":"5832",
    "addr:postcode":"27713",
    "addr:street":"Fayetteville Rd",
    "iso:country":"US",
    "sg:address":"5832 Fayetteville Rd",
    "sg:city":"Durham",
    "sg:classifiers":[
        {
            "category":"Health Services",
            "subcategory":"Doctor",
            "type":"Services"
        }
    ],
    "sg:phone":"+1 919 544 7777",
    "sg:postcode":"27713",
    "sg:province":"NC",
    "sg:tags":[
        "dentist"
    ],
    "wof:name":"Renaissance Family Dentistry",
    "wof:placetype":"venue"
},
  "geometry": {"coordinates":[-78.927431,35.922835],"type":"Point"}
}