{
  "type": "Feature",
  "properties": {
    "iso:country":"US",
    "sg:address":"825 Sink Farm Rd",
    "sg:city":"Lexington",
    "sg:classifiers":[
        {
            "category":"Professional",
            "subcategory":"Business Services",
            "type":"Services"
        }
    ],
    "sg:phone":"+1   ",
    "sg:postcode":"27295",
    "sg:province":"NC",
    "wof:name":"Astoria Pacific Internation Al",
    "wof:placetype":"venue"
},
  "geometry": {"coordinates":[-80.34737199999999,35.80903],"type":"Point"}
}