{
  "type": "Feature",
  "properties": {
    "iso:country":"US",
    "sg:address":"1021 Parkwood Ave",
    "sg:city":"Charlotte",
    "sg:classifiers":[
        {
            "category":"Organizations",
            "subcategory":"Religious Organization",
            "type":"Services"
        }
    ],
    "sg:phone":"+1 704 332 8007",
    "sg:postcode":"28205",
    "sg:province":"NC",
    "sg:tags":[
        "church"
    ],
    "wof:name":"Helton Community CME",
    "wof:placetype":"venue"
},
  "geometry": {"coordinates":[-80.815245,35.233577],"type":"Point"}
}