{
  "type": "Feature",
  "properties": {
    "addr:full":"4467 Rual Dr Granite Falls NC 28630",
    "addr:housenumber":"4467",
    "addr:postcode":"28630",
    "addr:street":"Rual Dr",
    "iso:country":"US",
    "sg:address":"4467 Rual Dr",
    "sg:city":"Granite Falls",
    "sg:classifiers":[
        {
            "category":"Farming",
            "subcategory":"Farm",
            "type":"Manufacturing & Wholesale Goods"
        }
    ],
    "sg:phone":"+1 828 396 7187",
    "sg:postcode":"28630",
    "sg:province":"NC",
    "sg:tags":[
        "crop",
        "general"
    ],
    "wof:name":"Maynard H Annas Jr",
    "wof:placetype":"venue"
},
  "geometry": {"coordinates":[-81.47328899999999,35.820153],"type":"Point"}
}