{
  "type": "Feature",
  "properties": {
    "addr:full":"2427 Shell Point Rd SW South Brunswick NC 28470",
    "addr:housenumber":"2427",
    "addr:postcode":"28470",
    "addr:street":"Shell Point Rd Sw",
    "iso:country":"US",
    "sg:address":"2427 Shell Point Rd SW",
    "sg:city":"South Brunswick",
    "sg:classifiers":[
        {
            "category":"Freight",
            "type":"Transportation"
        }
    ],
    "sg:phone":"+1 910 754 8569",
    "sg:postcode":"28470",
    "sg:province":"NC",
    "sg:tags":[
        "operator",
        "local",
        "trucking"
    ],
    "wof:name":"T Johnson Trucking Co",
    "wof:placetype":"venue"
},
  "geometry": {"coordinates":[-78.33415599999999,33.962169],"type":"Point"}
}