{
  "type": "Feature",
  "properties": {
    "iso:country":"US",
    "sg:address":"6286-108 Glenwood Ave",
    "sg:city":"Raleigh",
    "sg:classifiers":[
        {
            "category":"Home & Garden",
            "subcategory":"Carpets & Floor Coverings",
            "type":"Retail Goods"
        }
    ],
    "sg:phone":"+1 919 781 1035",
    "sg:postcode":"27612",
    "sg:province":"NC",
    "sg:tags":[
        "mattress"
    ],
    "sg:website":"www.agoodnightsleepstore.com",
    "wof:name":"A Goodnight Sleepstore",
    "wof:placetype":"venue"
},
  "geometry": {"coordinates":[-78.700951,35.855169],"type":"Point"}
}