{
  "type": "Feature",
  "properties": {
    "addr:full":"1500 Sunday Dr Raleigh NC 27607",
    "addr:housenumber":"1500",
    "addr:postcode":"27607",
    "addr:street":"Sunday Dr",
    "iso:country":"US",
    "sg:address":"1500 Sunday Dr",
    "sg:city":"Raleigh",
    "sg:classifiers":[
        {
            "category":"Building & Trades",
            "subcategory":"Construction",
            "type":"Services"
        }
    ],
    "sg:phone":"+1 919 854 2475",
    "sg:postcode":"27607",
    "sg:province":"NC",
    "sg:tags":[
        "contractor"
    ],
    "wof:name":"Turner Constructions",
    "wof:placetype":"venue"
},
  "geometry": {"coordinates":[-78.730598,35.800159],"type":"Point"}
}