{
  "type": "Feature",
  "properties": {
    "iso:country":"US",
    "sg:address":"220 Postal St",
    "sg:city":"Boone",
    "sg:classifiers":[
        {
            "category":"Autos & Motor Vehicles",
            "subcategory":"Auto Supplies",
            "type":"Retail Goods"
        }
    ],
    "sg:phone":"+1 828 265 1511",
    "sg:postcode":"28607",
    "sg:province":"NC",
    "sg:tags":[
        "automobile",
        "stereo",
        "radio"
    ],
    "wof:name":"Audio & Chrome",
    "wof:placetype":"venue"
},
  "geometry": {"coordinates":[-81.661772,36.20024],"type":"Point"}
}