{
  "type": "Feature",
  "properties": {
    "addr:full":"1581 Benvenue Rd Rocky Mount NC 27804",
    "addr:housenumber":"1581",
    "addr:postcode":"27804",
    "addr:street":"Benvenue Rd",
    "iso:country":"US",
    "sg:address":"1581 Benvenue Rd",
    "sg:city":"Rocky Mount",
    "sg:classifiers":[
        {
            "category":"Shopping",
            "subcategory":"Computers & Home Electronics",
            "type":"Retail Goods"
        }
    ],
    "sg:phone":"+1 252 212 5603",
    "sg:postcode":"27804",
    "sg:province":"NC",
    "wof:name":"Electronics Boutique",
    "wof:placetype":"venue"
},
  "geometry": {"coordinates":[-77.80774099999999,35.979396],"type":"Point"}
}