{
  "type": "Feature",
  "properties": {
    "iso:country":"US",
    "sg:address":"130 Feed Mill Rd",
    "sg:city":"Advance",
    "sg:classifiers":[
        {
            "category":"Organizations",
            "subcategory":"Community Association",
            "type":"Services"
        }
    ],
    "sg:phone":"+1   ",
    "sg:postcode":"27006",
    "sg:province":"NC",
    "wof:name":"VFW Post 8719",
    "wof:placetype":"venue"
},
  "geometry": {"coordinates":[-80.41125599999999,35.94149],"type":"Point"}
}