{
  "type": "Feature",
  "properties": {
    "addr:full":"444 Vinson Blvd Whiteville NC 28472",
    "addr:housenumber":"444",
    "addr:postcode":"28472",
    "addr:street":"Vinson Blvd",
    "iso:country":"US",
    "sg:address":"444 Vinson Blvd",
    "sg:city":"Whiteville",
    "sg:classifiers":[
        {
            "category":"Wholesale",
            "subcategory":"Machinery & Supplies",
            "type":"Manufacturing & Wholesale Goods"
        }
    ],
    "sg:phone":"+1 910 642 6642",
    "sg:postcode":"28472",
    "sg:province":"NC",
    "sg:tags":[
        "truck"
    ],
    "wof:name":"Whiteville Forklift & Equip",
    "wof:placetype":"venue"
},
  "geometry": {"coordinates":[-78.708321,34.296822],"type":"Point"}
}