{
  "type": "Feature",
  "properties": {
    "iso:country":"US",
    "sg:address":"1988 Jericho Church Rd",
    "sg:city":"Mocksville",
    "sg:classifiers":[
        {
            "category":"Travel",
            "subcategory":"Campground",
            "type":"Entertainment"
        }
    ],
    "sg:phone":"+1 336 492 7802",
    "sg:postcode":"27028",
    "sg:province":"NC",
    "sg:tags":[
        "camp"
    ],
    "wof:name":"Carolina Bible Camp Inc",
    "wof:placetype":"venue"
},
  "geometry": {"coordinates":[-80.60336,35.867834],"type":"Point"}
}