{
  "type": "Feature",
  "properties": {
    "iso:country":"US",
    "sg:address":"106 N Water St",
    "sg:city":"Wilmington",
    "sg:classifiers":[
        {
            "category":"Real Estate",
            "subcategory":"Real Estate Agent",
            "type":"Services"
        }
    ],
    "sg:phone":"+1 910 763 7646",
    "sg:postcode":"28401",
    "sg:province":"NC",
    "wof:name":"Carolinian Realty",
    "wof:placetype":"venue"
},
  "geometry": {"coordinates":[-77.950098,34.237117],"type":"Point"}
}