{
  "type": "Feature",
  "properties": {
    "iso:country":"US",
    "sg:address":"300 Killian Ct",
    "sg:city":"Matthews",
    "sg:classifiers":[
        {
            "category":"Professional",
            "subcategory":"Management & Consulting",
            "type":"Services"
        }
    ],
    "sg:phone":"+1   ",
    "sg:postcode":"28104",
    "sg:province":"NC",
    "sg:tags":[
        "business"
    ],
    "wof:name":"Tolliver Associates Inc",
    "wof:placetype":"venue"
},
  "geometry": {"coordinates":[-80.64337500000001,35.1263],"type":"Point"}
}