{
  "type": "Feature",
  "properties": {
    "iso:country":"US",
    "sg:address":"304 Forsythia Ct",
    "sg:city":"Hendersonville",
    "sg:classifiers":[
        {
            "category":"Professional",
            "subcategory":"Management & Consulting",
            "type":"Services"
        }
    ],
    "sg:phone":"+1   ",
    "sg:postcode":"28739",
    "sg:province":"NC",
    "wof:name":"A E C Inc",
    "wof:placetype":"venue"
},
  "geometry": {"coordinates":[-82.579919,35.306776],"type":"Point"}
}