{
  "type": "Feature",
  "properties": {
    "addr:full":"4307 Norris Store Rd Ayden NC 28513",
    "addr:housenumber":"4307",
    "addr:postcode":"28513",
    "addr:street":"Norris Store Rd",
    "iso:country":"US",
    "sg:address":"4307 Norris Store Rd",
    "sg:city":"Ayden",
    "sg:phone":"+1 252 746 4977",
    "sg:postcode":"28513",
    "sg:province":"NC",
    "sg:tags":[
        "farm",
        "corn",
        "grain",
        "cash",
        "tobacco"
    ],
    "wof:name":"Cannon Farms Inc",
    "wof:placetype":"venue"
},
  "geometry": {"coordinates":[-77.46478,35.486245],"type":"Point"}
}