{
  "type": "Feature",
  "properties": {
    "addr:full":"220 S East Ave Ayden NC 28513",
    "addr:housenumber":"220",
    "addr:postcode":"28513",
    "addr:street":"S East Ave",
    "iso:country":"US",
    "sg:address":"220 S East Ave",
    "sg:city":"Ayden",
    "sg:classifiers":[
        {
            "category":"Autos & Motor Vehicles",
            "subcategory":"Auto Supplies",
            "type":"Retail Goods"
        }
    ],
    "sg:phone":"+1 252 746 3311",
    "sg:postcode":"28513",
    "sg:province":"NC",
    "sg:tags":[
        "tire"
    ],
    "wof:name":"Tripp's Tire Svc Inc",
    "wof:placetype":"venue"
},
  "geometry": {"coordinates":[-77.415842,35.471838],"type":"Point"}
}