{
  "type": "Feature",
  "properties": {
    "iso:country":"US",
    "sg:address":"117 Bruce Nifong Rd",
    "sg:city":"Winston Salem",
    "sg:classifiers":[
        {
            "category":"Building & Trades",
            "subcategory":"Landscaping Services",
            "type":"Services"
        }
    ],
    "sg:phone":"+1 336 788 9605",
    "sg:postcode":"27107",
    "sg:province":"NC",
    "sg:tags":[
        "lawn",
        "maintenance",
        "grounds"
    ],
    "wof:name":"Grass Pro Landscaping & Lawn",
    "wof:placetype":"venue"
},
  "geometry": {"coordinates":[-80.197834,36.02116],"type":"Point"}
}