{
  "type": "Feature",
  "properties": {
    "addr:full":"444 Hunter Ln Charlotte NC 28211",
    "addr:housenumber":"444",
    "addr:postcode":"28211",
    "addr:street":"Hunter Ln",
    "iso:country":"US",
    "sg:address":"444 Hunter Ln",
    "sg:city":"Charlotte",
    "sg:classifiers":[
        {
            "category":"Professional",
            "subcategory":"Business Services",
            "type":"Services"
        }
    ],
    "sg:phone":"+1 704 367 0634",
    "sg:postcode":"28211",
    "sg:province":"NC",
    "sg:tags":[
        "interior",
        "consultant",
        "design",
        "decorator"
    ],
    "wof:name":"Castles Interiors",
    "wof:placetype":"venue"
},
  "geometry": {"coordinates":[-80.78925,35.171642],"type":"Point"}
}