{
  "type": "Feature",
  "properties": {
    "iso:country":"US",
    "sg:address":"13509 S Point Blvd",
    "sg:city":"Charlotte",
    "sg:classifiers":[
        {
            "category":"Manufacturing",
            "subcategory":"Tools & Machinery",
            "type":"Manufacturing & Wholesale Goods"
        }
    ],
    "sg:phone":"+1 704 583 1193",
    "sg:postcode":"28273",
    "sg:province":"NC",
    "sg:tags":[
        "machine"
    ],
    "wof:name":"D M G America Inc",
    "wof:placetype":"venue"
},
  "geometry": {"coordinates":[-80.957573,35.110746],"type":"Point"}
}