{
  "type": "Feature",
  "properties": {
    "addr:full":"1121 3rd St Exd Robersonville NC 27871",
    "addr:housenumber":"1121",
    "addr:postcode":"27871",
    "addr:street":"3Rd St Exd",
    "iso:country":"US",
    "sg:address":"1121 3rd St Exd",
    "sg:city":"Robersonville",
    "sg:classifiers":[
        {
            "category":"Education",
            "subcategory":"School",
            "type":"Public Place"
        }
    ],
    "sg:phone":"+1 252 795 4775",
    "sg:postcode":"27871",
    "sg:province":"NC",
    "sg:tags":[
        "elementary"
    ],
    "wof:name":"East End Elementary School",
    "wof:placetype":"venue"
},
  "geometry": {"coordinates":[-77.24350200000001,35.822172],"type":"Point"}
}