{
  "type": "Feature",
  "properties": {
    "iso:country":"US",
    "sg:address":"3 Meadow Cir",
    "sg:city":"Arden",
    "sg:classifiers":[
        {
            "category":"Building & Trades",
            "subcategory":"Construction",
            "type":"Services"
        }
    ],
    "sg:phone":"+1 828 681 5240",
    "sg:postcode":"28704",
    "sg:province":"NC",
    "sg:tags":[
        "house"
    ],
    "wof:name":"Cookson Construction Co",
    "wof:placetype":"venue"
},
  "geometry": {"coordinates":[-82.49376599999999,35.455797],"type":"Point"}
}