{
  "type": "Feature",
  "properties": {
    "addr:full":"210 W Main Ave Taylorsville NC 28681",
    "addr:housenumber":"210",
    "addr:postcode":"28681",
    "addr:street":"W Main Ave",
    "iso:country":"US",
    "sg:address":"210 W Main Ave",
    "sg:city":"Taylorsville",
    "sg:classifiers":[
        {
            "category":"Organizations",
            "subcategory":"Non-profit Organization",
            "type":"Services"
        }
    ],
    "sg:phone":"+1 828 635 7889",
    "sg:postcode":"28681",
    "sg:province":"NC",
    "sg:tags":[
        "charitable",
        "institution"
    ],
    "wof:name":"Alexander County Habitat",
    "wof:placetype":"venue"
},
  "geometry": {"coordinates":[-81.178825,35.921991],"type":"Point"}
}