{
  "type": "Feature",
  "properties": {
    "addr:full":"11957 Ramah Church Rd Huntersville NC 28078",
    "addr:housenumber":"11957",
    "addr:postcode":"28078",
    "addr:street":"Ramah Church Rd",
    "iso:country":"US",
    "sg:address":"11957 Ramah Church Rd",
    "sg:city":"Huntersville",
    "sg:classifiers":[
        {
            "category":"Wholesale",
            "subcategory":"Stationery",
            "type":"Manufacturing & Wholesale Goods"
        }
    ],
    "sg:phone":"+1 704 948 6277",
    "sg:postcode":"28078",
    "sg:province":"NC",
    "sg:tags":[
        "map"
    ],
    "sg:website":"www.qualitymaps.com",
    "wof:name":"Quality Maps Inc",
    "wof:placetype":"venue"
},
  "geometry": {"coordinates":[-80.83046299999999,35.422493],"type":"Point"}
}