{
  "type": "Feature",
  "properties": {
    "iso:country":"US",
    "sg:address":"1618 S Miami Blvd",
    "sg:city":"Durham",
    "sg:classifiers":[
        {
            "category":"Banks & Credit Unions",
            "subcategory":"Bank",
            "type":"Services"
        }
    ],
    "sg:phone":"+1 919 680 3688",
    "sg:postcode":"27703",
    "sg:province":"NC",
    "sg:tags":[
        "cashing",
        "check"
    ],
    "wof:name":"Cash Advance Check Cashing",
    "wof:placetype":"venue"
},
  "geometry": {"coordinates":[-78.83832200000001,35.950353],"type":"Point"}
}