{
  "type": "Feature",
  "properties": {
    "iso:country":"US",
    "sg:address":"1030 Rogers Ln",
    "sg:city":"Raleigh",
    "sg:classifiers":[
        {
            "category":"Restaurant",
            "type":"Food & Drink"
        }
    ],
    "sg:phone":"+1 919 449 0950",
    "sg:postcode":"27610",
    "sg:province":"NC",
    "wof:name":"Ribs R Us",
    "wof:placetype":"venue"
},
  "geometry": {"coordinates":[-78.548812,35.790638],"type":"Point"}
}