{
  "type": "Feature",
  "properties": {
    "iso:country":"US",
    "sg:address":"10397 Nugget Pl",
    "sg:city":"Midland",
    "sg:classifiers":[
        {
            "category":"Utilities",
            "subcategory":"Telephone",
            "type":"Services"
        }
    ],
    "sg:phone":"+1 704 344 7490",
    "sg:postcode":"28107",
    "sg:province":"NC",
    "sg:tags":[
        "communications"
    ],
    "wof:name":"BellSouth",
    "wof:placetype":"venue"
},
  "geometry": {"coordinates":[-80.45947700000001,35.277065],"type":"Point"}
}