{
  "type": "Feature",
  "properties": {
    "iso:country":"US",
    "sg:address":"1650 Greenfield St",
    "sg:city":"Wilmington",
    "sg:classifiers":[
        {
            "category":"Organizations",
            "subcategory":"Non-profit Organization",
            "type":"Services"
        }
    ],
    "sg:phone":"+1 910 341 4700",
    "sg:postcode":"28401",
    "sg:province":"NC",
    "sg:tags":[
        "social"
    ],
    "wof:name":"New Hanover County of",
    "wof:placetype":"venue"
},
  "geometry": {"coordinates":[-77.925915,34.217992],"type":"Point"}
}