{
  "type": "Feature",
  "properties": {
    "addr:full":"117 N Circle Dr Rocky Mount NC 27804",
    "addr:housenumber":"117",
    "addr:postcode":"27804",
    "addr:street":"N Circle Dr",
    "iso:country":"US",
    "sg:address":"117 N Circle Dr",
    "sg:city":"Rocky Mount",
    "sg:classifiers":[
        {
            "category":"Insurance",
            "subcategory":"Insurance Agent",
            "type":"Services"
        }
    ],
    "sg:phone":"+1 252 937 6913",
    "sg:postcode":"27804",
    "sg:province":"NC",
    "wof:name":"Gus H Tulloss Insurance",
    "wof:placetype":"venue"
},
  "geometry": {"coordinates":[-77.83375700000001,35.964433],"type":"Point"}
}