{
  "type": "Feature",
  "properties": {
    "addr:full":"6542 Coltrane Mill Rd Greensboro NC 27406",
    "addr:housenumber":"6542",
    "addr:postcode":"27406",
    "addr:street":"Coltrane Mill Rd",
    "iso:country":"US",
    "sg:address":"6542 Coltrane Mill Rd",
    "sg:city":"Greensboro",
    "sg:phone":"+1 336 674 0665",
    "sg:postcode":"27406",
    "sg:province":"NC",
    "sg:tags":[
        "farm",
        "tobacco"
    ],
    "wof:name":"Thomas M Marsh Jr",
    "wof:placetype":"venue"
},
  "geometry": {"coordinates":[-79.83506300000001,35.938296],"type":"Point"}
}