{
  "type": "Feature",
  "properties": {
    "iso:country":"US",
    "sg:address":"1830 Westbrook Cir",
    "sg:city":"Gastonia",
    "sg:classifiers":[
        {
            "category":"Social Services",
            "subcategory":"Adult Care",
            "type":"Services"
        }
    ],
    "sg:phone":"+1 704 866 4166",
    "sg:postcode":"28052",
    "sg:province":"NC",
    "sg:tags":[
        "home",
        "residential"
    ],
    "wof:name":"SCW Residential Care",
    "wof:placetype":"venue"
},
  "geometry": {"coordinates":[-81.204167,35.247657],"type":"Point"}
}