{
  "type": "Feature",
  "properties": {
    "addr:full":"13526 US Hwy 221 S Fleetwood NC 28626",
    "addr:housenumber":"13526",
    "addr:postcode":"28626",
    "addr:street":"Us Hwy 221 S",
    "iso:country":"US",
    "sg:address":"13526 US Hwy 221 S",
    "sg:city":"Fleetwood",
    "sg:classifiers":[
        {
            "category":"Home & Garden",
            "subcategory":"Garden Supply",
            "type":"Retail Goods"
        }
    ],
    "sg:phone":"+1 336 877 5480",
    "sg:postcode":"28626",
    "sg:province":"NC",
    "sg:tags":[
        "tree",
        "christmas"
    ],
    "wof:name":"Church's Nursery & Evergreens",
    "wof:placetype":"venue"
},
  "geometry": {"coordinates":[-81.499773,36.254768],"type":"Point"}
}