{
  "type": "Feature",
  "properties": {
    "addr:full":"4624 Bragg Blvd Fayetteville NC 28303",
    "addr:housenumber":"4624",
    "addr:postcode":"28303",
    "addr:street":"Bragg Blvd",
    "iso:country":"US",
    "sg:address":"4624 Bragg Blvd",
    "sg:city":"Fayetteville",
    "sg:classifiers":[
        {
            "category":"Organizations",
            "subcategory":"Community Association",
            "type":"Services"
        }
    ],
    "sg:phone":"+1 910 867 2364",
    "sg:postcode":"28303",
    "sg:province":"NC",
    "sg:tags":[
        "club"
    ],
    "wof:name":"Legends Pub",
    "wof:placetype":"venue"
},
  "geometry": {"coordinates":[-78.95396,35.090492],"type":"Point"}
}