{
  "type": "Feature",
  "properties": {
    "addr:full":"2527 Glencoe St Burlington NC 27217",
    "addr:housenumber":"2527",
    "addr:postcode":"27217",
    "addr:street":"Glencoe St",
    "iso:country":"US",
    "sg:address":"2527 Glencoe St",
    "sg:city":"Burlington",
    "sg:classifiers":[
        {
            "category":"Arts & Performance",
            "subcategory":"Theater",
            "type":"Entertainment"
        }
    ],
    "sg:phone":"+1 336 222 9249",
    "sg:postcode":"27217",
    "sg:province":"NC",
    "sg:tags":[
        "live",
        "music"
    ],
    "wof:name":"Tarheel Karaoke & DJ SVC",
    "wof:placetype":"venue"
},
  "geometry": {"coordinates":[-79.42757899999999,36.139342],"type":"Point"}
}