{
  "type": "Feature",
  "properties": {
    "iso:country":"US",
    "sg:address":"2 Prestwick Rd",
    "sg:city":"Chapel Hill",
    "sg:classifiers":[
        {
            "category":"Education",
            "subcategory":"School",
            "type":"Public Place"
        }
    ],
    "sg:phone":"+1 919 968 3473",
    "sg:postcode":"27517",
    "sg:province":"NC",
    "wof:name":"Chapel Hill-Carrboro City Schools",
    "wof:placetype":"venue"
},
  "geometry": {"coordinates":[-79.018688,35.904737],"type":"Point"}
}