{
  "type": "Feature",
  "properties": {
    "addr:full":"1109 Agricultural St Raleigh NC 27603",
    "addr:housenumber":"1109",
    "addr:postcode":"27603",
    "addr:street":"Agricultural St",
    "iso:country":"US",
    "sg:address":"1109 Agricultural St",
    "sg:city":"Raleigh",
    "sg:classifiers":[
        {
            "category":"Wholesale",
            "subcategory":"Fruits & Vegetables",
            "type":"Manufacturing & Wholesale Goods"
        }
    ],
    "sg:phone":"+1 919 828 4161",
    "sg:postcode":"27603",
    "sg:province":"NC",
    "sg:tags":[
        "fresh"
    ],
    "wof:name":"Wards Fruit & Produce Co Inc",
    "wof:placetype":"venue"
},
  "geometry": {"coordinates":[-78.664281,35.765987],"type":"Point"}
}