{
  "type": "Feature",
  "properties": {
    "iso:country":"US",
    "sg:address":"2121 Village Lake Dr",
    "sg:city":"Charlotte",
    "sg:classifiers":[
        {
            "category":"Real Estate",
            "subcategory":"Real Estate Operator",
            "type":"Services"
        }
    ],
    "sg:phone":"+1 704 568 5350",
    "sg:postcode":"28212",
    "sg:province":"NC",
    "sg:tags":[
        "building",
        "apartment"
    ],
    "wof:name":"Villa East Apartments",
    "wof:placetype":"venue"
},
  "geometry": {"coordinates":[-80.743315,35.16159],"type":"Point"}
}