{
  "type": "Feature",
  "properties": {
    "iso:country":"US",
    "sg:address":"5821 Reddman Rd",
    "sg:city":"Charlotte",
    "sg:classifiers":[
        {
            "category":"Real Estate",
            "subcategory":"Real Estate Operator",
            "type":"Services"
        }
    ],
    "sg:phone":"+1 704 535 1705",
    "sg:postcode":"28212",
    "sg:province":"NC",
    "sg:tags":[
        "apartment"
    ],
    "wof:name":"Lion's Head Apartments",
    "wof:placetype":"venue"
},
  "geometry": {"coordinates":[-80.75082399999999,35.201327],"type":"Point"}
}