{
  "type": "Feature",
  "properties": {
    "iso:country":"US",
    "sg:address":"1714 East Blvd",
    "sg:city":"Charlotte",
    "sg:classifiers":[
        {
            "category":"Wholesale",
            "subcategory":"Durable Goods & Equipment",
            "type":"Manufacturing & Wholesale Goods"
        }
    ],
    "sg:phone":"+1 704 334 1677",
    "sg:postcode":"28203",
    "sg:province":"NC",
    "sg:tags":[
        "exporter"
    ],
    "wof:name":"Starboard Inc",
    "wof:placetype":"venue"
},
  "geometry": {"coordinates":[-80.839901,35.19795],"type":"Point"}
}