{
  "type": "Feature",
  "properties": {
    "addr:full":"2707 Henry St Greensboro NC 27405",
    "addr:housenumber":"2707",
    "addr:postcode":"27405",
    "addr:street":"Henry St",
    "iso:country":"US",
    "sg:address":"2707 Henry St",
    "sg:city":"Greensboro",
    "sg:classifiers":[
        {
            "category":"Health Services",
            "subcategory":"Doctor",
            "type":"Services"
        }
    ],
    "sg:phone":"+1 336 375 2300",
    "sg:postcode":"27405",
    "sg:province":"NC",
    "sg:tags":[
        "medical"
    ],
    "wof:name":"Southastern Orthpd Specialists",
    "wof:placetype":"venue"
},
  "geometry": {"coordinates":[-79.782647,36.114923],"type":"Point"}
}