{
  "type": "Feature",
  "properties": {
    "addr:full":"3240 Zebulon Rd Rocky Mount NC 27804",
    "addr:housenumber":"3240",
    "addr:postcode":"27804",
    "addr:street":"Zebulon Rd",
    "iso:country":"US",
    "sg:address":"3240 Zebulon Rd",
    "sg:city":"Rocky Mount",
    "sg:classifiers":[
        {
            "category":"Retail",
            "subcategory":"Animal Services",
            "type":"Services"
        }
    ],
    "sg:phone":"+1 252 937 7205",
    "sg:postcode":"27804",
    "sg:province":"NC",
    "sg:tags":[
        "pet",
        "grooming",
        "washing"
    ],
    "wof:name":"Pet's Best Friend Inc",
    "wof:placetype":"venue"
},
  "geometry": {"coordinates":[-77.839991,35.966051],"type":"Point"}
}