{
  "type": "Feature",
  "properties": {
    "iso:country":"US",
    "sg:address":"125 Oak Ln",
    "sg:city":"Mars Hill",
    "sg:classifiers":[
        {
            "category":"Health Services",
            "subcategory":"Chiropractor",
            "type":"Services"
        }
    ],
    "sg:phone":"+1   ",
    "sg:postcode":"28741",
    "sg:province":"NC",
    "wof:name":"Kind Hands Chiropractic Center",
    "wof:placetype":"venue"
},
  "geometry": {"coordinates":[-83.201554,35.057266],"type":"Point"}
}