{
  "type": "Feature",
  "properties": {
    "iso:country":"US",
    "sg:address":"214 W Prospect Ave",
    "sg:city":"Raeford",
    "sg:classifiers":[
        {
            "category":"Education",
            "subcategory":"Dance Studio",
            "type":"Public Place"
        }
    ],
    "sg:phone":"+1   ",
    "sg:postcode":"28376",
    "sg:province":"NC",
    "wof:name":"Raeford Dance Arts",
    "wof:placetype":"venue"
},
  "geometry": {"coordinates":[-79.226887,34.984309],"type":"Point"}
}