{
  "type": "Feature",
  "properties": {
    "iso:country":"US",
    "sg:address":"1698 E Booker Dairy Rd",
    "sg:city":"Smithfield",
    "sg:classifiers":[
        {
            "category":"Autos & Motor Vehicles",
            "subcategory":"Automobile Sales",
            "type":"Retail Goods"
        }
    ],
    "sg:phone":"+1 919 934 6500",
    "sg:postcode":"27577",
    "sg:province":"NC",
    "sg:tags":[
        "car",
        "dealer"
    ],
    "sg:website":"www.classicford-lin-mer.com",
    "wof:name":"Classic Ford-Lincoln-Mercury",
    "wof:placetype":"venue"
},
  "geometry": {"coordinates":[-78.315749,35.523229],"type":"Point"}
}