{
  "type": "Feature",
  "properties": {
    "iso:country":"US",
    "sg:address":"371 Riveredge Dr",
    "sg:city":"Stoneville",
    "sg:classifiers":[
        {
            "category":"Professional",
            "subcategory":"Business Services",
            "type":"Services"
        }
    ],
    "sg:phone":"+1   ",
    "sg:postcode":"27048",
    "sg:province":"NC",
    "wof:name":"A2z Sales & Service LLC",
    "wof:placetype":"venue"
},
  "geometry": {"coordinates":[-79.981071,36.487005],"type":"Point"}
}