{
  "type": "Feature",
  "properties": {
    "addr:full":"109 N Chatham Ave Siler City NC 27344",
    "addr:housenumber":"109",
    "addr:postcode":"27344",
    "addr:street":"N Chatham Ave",
    "iso:country":"US",
    "sg:address":"109 N Chatham Ave",
    "sg:city":"Siler City",
    "sg:classifiers":[
        {
            "category":"Recreation",
            "type":"Entertainment"
        }
    ],
    "sg:phone":"+1   ",
    "sg:postcode":"27344",
    "sg:province":"NC",
    "sg:tags":[
        "martial",
        "arts",
        "instructional"
    ],
    "wof:name":"Southeastern Karate Assn",
    "wof:placetype":"venue"
},
  "geometry": {"coordinates":[-79.464029,35.72364],"type":"Point"}
}