{
  "type": "Feature",
  "properties": {
    "iso:country":"US",
    "sg:address":"135 McBrayer Ct",
    "sg:city":"Forest City",
    "sg:classifiers":[
        {
            "category":"Health Services",
            "subcategory":"Doctor",
            "type":"Services"
        }
    ],
    "sg:phone":"+1 828 287 2343",
    "sg:postcode":"28043",
    "sg:province":"NC",
    "sg:tags":[
        "dentist"
    ],
    "wof:name":"Oral & Maxillofacial Surgery",
    "wof:placetype":"venue"
},
  "geometry": {"coordinates":[-81.85315900000001,35.331695],"type":"Point"}
}