{
  "type": "Feature",
  "properties": {
    "iso:country":"US",
    "sg:address":"70 Lake Dr",
    "sg:city":"Elizabethtown",
    "sg:classifiers":[
        {
            "category":"Travel",
            "subcategory":"Campground",
            "type":"Entertainment"
        }
    ],
    "sg:phone":"+1 910 862 4849",
    "sg:postcode":"28337",
    "sg:province":"NC",
    "wof:name":"Park Shore's Campground",
    "wof:placetype":"venue"
},
  "geometry": {"coordinates":[-78.499224,34.63218],"type":"Point"}
}