{
  "type": "Feature",
  "properties": {
    "addr:full":"208 Plyersmill Rd Cary NC 27519",
    "addr:housenumber":"208",
    "addr:postcode":"27519",
    "addr:street":"Plyersmill Rd",
    "iso:country":"US",
    "sg:address":"208 Plyersmill Rd",
    "sg:city":"Cary",
    "sg:classifiers":[
        {
            "category":"Professional",
            "type":"Services"
        }
    ],
    "sg:phone":"+1 919 468 4661",
    "sg:postcode":"27519",
    "sg:province":"NC",
    "wof:name":"Ani Exquisite LLC",
    "wof:placetype":"venue"
},
  "geometry": {"coordinates":[-78.85311400000001,35.785747],"type":"Point"}
}