{
  "type": "Feature",
  "properties": {
    "iso:country":"US",
    "sg:address":"103 S Devimy Ct",
    "sg:city":"Cary",
    "sg:classifiers":[
        {
            "category":"Health Services",
            "subcategory":"Doctor",
            "type":"Services"
        }
    ],
    "sg:phone":"+1   ",
    "sg:postcode":"27511",
    "sg:province":"NC",
    "sg:tags":[
        "medical"
    ],
    "wof:name":"Deborah C Neel PHD",
    "wof:placetype":"venue"
},
  "geometry": {"coordinates":[-78.807647,35.751561],"type":"Point"}
}