{
  "type": "Feature",
  "properties": {
    "iso:country":"US",
    "sg:address":"1312 Prospectors Ct",
    "sg:city":"Monroe",
    "sg:classifiers":[
        {
            "category":"Professional",
            "subcategory":"Business Services",
            "type":"Services"
        }
    ],
    "sg:phone":"+1   ",
    "sg:postcode":"28110",
    "sg:province":"NC",
    "wof:name":"V Express Inc",
    "wof:placetype":"venue"
},
  "geometry": {"coordinates":[-80.60160999999999,35.008348],"type":"Point"}
}