{
  "type": "Feature",
  "properties": {
    "addr:full":"2915 Raeford Rd Fayetteville NC 28303",
    "addr:housenumber":"2915",
    "addr:postcode":"28303",
    "addr:street":"Raeford Rd",
    "iso:country":"US",
    "sg:address":"2915 Raeford Rd",
    "sg:city":"Fayetteville",
    "sg:classifiers":[
        {
            "category":"Health Services",
            "subcategory":"Clinic",
            "type":"Services"
        }
    ],
    "sg:phone":"+1 910 438 9096",
    "sg:postcode":"28303",
    "sg:province":"NC",
    "sg:tags":[
        "medical",
        "examination"
    ],
    "wof:name":"Portamedic",
    "wof:placetype":"venue"
},
  "geometry": {"coordinates":[-78.92898,35.044939],"type":"Point"}
}