{
  "type": "Feature",
  "properties": {
    "iso:country":"US",
    "sg:address":"4905 Pine Cone Dr Ste C1",
    "sg:city":"Durham",
    "sg:classifiers":[
        {
            "category":"Communications",
            "subcategory":"Newspaper",
            "type":"Services"
        }
    ],
    "sg:phone":"+1 919 489 1916",
    "sg:postcode":"27707",
    "sg:province":"NC",
    "sg:tags":[
        "print",
        "medium"
    ],
    "wof:name":"Journalistic Incorp",
    "wof:placetype":"venue"
},
  "geometry": {"coordinates":[-78.984802,35.941002],"type":"Point"}
}