{
  "type": "Feature",
  "properties": {
    "iso:country":"US",
    "sg:address":"5411 Ramsey St",
    "sg:city":"Fayetteville",
    "sg:classifiers":[
        {
            "category":"Professional",
            "subcategory":"Accounting & Tax Preparation",
            "type":"Services"
        }
    ],
    "sg:phone":"+1 910 488 6757",
    "sg:postcode":"28311",
    "sg:province":"NC",
    "sg:tags":[
        "accountant"
    ],
    "wof:name":"Harris Management Svc Inc",
    "wof:placetype":"venue"
},
  "geometry": {"coordinates":[-78.877448,35.132543],"type":"Point"}
}