{
  "type": "Feature",
  "properties": {
    "addr:full":"1307 W Broad St Elizabethtown NC 28337",
    "addr:housenumber":"1307",
    "addr:postcode":"28337",
    "addr:street":"W Broad St",
    "iso:country":"US",
    "sg:address":"1307 W Broad St",
    "sg:city":"Elizabethtown",
    "sg:classifiers":[
        {
            "category":"Shopping",
            "subcategory":"Clothing, Apparel, & Fashions",
            "type":"Retail Goods"
        }
    ],
    "sg:phone":"+1 910 862 2381",
    "sg:postcode":"28337",
    "sg:province":"NC",
    "sg:website":"www.catofashions.com",
    "wof:name":"Cato",
    "wof:placetype":"venue"
},
  "geometry": {"coordinates":[-78.619744,34.632388],"type":"Point"}
}