{
  "type": "Feature",
  "properties": {
    "addr:full":"100 One Eagle Pl Gastonia NC 28056",
    "addr:housenumber":"100",
    "addr:postcode":"28056",
    "addr:street":"One Eagle Pl",
    "iso:country":"US",
    "sg:address":"100 One Eagle Pl",
    "sg:city":"Gastonia",
    "sg:classifiers":[
        {
            "category":"Manufacturing",
            "subcategory":"Signs",
            "type":"Manufacturing & Wholesale Goods"
        }
    ],
    "sg:phone":"+1 704 823 3344",
    "sg:postcode":"28056",
    "sg:province":"NC",
    "sg:tags":[
        "advertising",
        "specialty"
    ],
    "wof:name":"Custom D Sign",
    "wof:placetype":"venue"
},
  "geometry": {"coordinates":[-81.080017,35.161127],"type":"Point"}
}