{
  "type": "Feature",
  "properties": {
    "iso:country":"US",
    "sg:address":"6 N Lake Park Blvd",
    "sg:city":"Carolina Beach",
    "sg:classifiers":[
        {
            "category":"Personal",
            "subcategory":"Beauty Salon",
            "type":"Services"
        }
    ],
    "sg:phone":"+1   ",
    "sg:postcode":"28428",
    "sg:province":"NC",
    "sg:tags":[
        "shop"
    ],
    "wof:name":"Lake Park Salon",
    "wof:placetype":"venue"
},
  "geometry": {"coordinates":[-77.89393800000001,34.034107],"type":"Point"}
}