{
  "type": "Feature",
  "properties": {
    "addr:full":"180 Wildwood Ct Stoneville NC 27048",
    "addr:housenumber":"180",
    "addr:postcode":"27048",
    "addr:street":"Wildwood Ct",
    "iso:country":"US",
    "sg:address":"180 Wildwood Ct",
    "sg:city":"Stoneville",
    "sg:classifiers":[
        {
            "category":"Retail",
            "subcategory":"Auto Repair",
            "type":"Services"
        }
    ],
    "sg:phone":"+1   ",
    "sg:postcode":"27048",
    "sg:province":"NC",
    "sg:tags":[
        "automotive"
    ],
    "wof:name":"Breakdown Road Service Inc",
    "wof:placetype":"venue"
},
  "geometry": {"coordinates":[-79.86365000000001,36.476223],"type":"Point"}
}