{
  "type": "Feature",
  "properties": {
    "addr:full":"508 Loop Rd Cove City NC 28523",
    "addr:housenumber":"508",
    "addr:postcode":"28523",
    "addr:street":"Loop Rd",
    "iso:country":"US",
    "sg:address":"508 Loop Rd",
    "sg:city":"Cove City",
    "sg:classifiers":[
        {
            "category":"Personal",
            "subcategory":"Beauty Salon",
            "type":"Services"
        }
    ],
    "sg:phone":"+1 252 634 2976",
    "sg:postcode":"28523",
    "sg:province":"NC",
    "sg:tags":[
        "shop"
    ],
    "wof:name":"Faye's Beauty Salon",
    "wof:placetype":"venue"
},
  "geometry": {"coordinates":[-77.299663,35.225266],"type":"Point"}
}