{
  "type": "Feature",
  "properties": {
    "addr:full":"4685 Yadkinville Rd Pfafftown NC 27040",
    "addr:housenumber":"4685",
    "addr:postcode":"27040",
    "addr:street":"Yadkinville Rd",
    "iso:country":"US",
    "sg:address":"4685 Yadkinville Rd",
    "sg:city":"Pfafftown",
    "sg:classifiers":[
        {
            "category":"Shopping",
            "subcategory":"Bicycles & Sporting Goods",
            "type":"Retail Goods"
        }
    ],
    "sg:phone":"+1 336 922 9090",
    "sg:postcode":"27040",
    "sg:province":"NC",
    "sg:tags":[
        "equipment",
        "archery",
        "supply"
    ],
    "wof:name":"Deer Run Archery Inc",
    "wof:placetype":"venue"
},
  "geometry": {"coordinates":[-80.35978299999999,36.15319],"type":"Point"}
}