{
  "type": "Feature",
  "properties": {
    "iso:country":"US",
    "sg:address":"1312 Patton Ave",
    "sg:city":"Asheville",
    "sg:classifiers":[
        {
            "category":"Health Services",
            "subcategory":"Doctor",
            "type":"Services"
        }
    ],
    "sg:phone":"+1 828 252 9833",
    "sg:postcode":"28806",
    "sg:province":"NC",
    "sg:tags":[
        "cardiologist"
    ],
    "sg:website":"www.gsmcweb.com",
    "wof:name":"Wilson John L Jr MD",
    "wof:placetype":"venue"
},
  "geometry": {"coordinates":[-82.6045,35.584],"type":"Point"}
}