{
  "type": "Feature",
  "properties": {
    "iso:country":"US",
    "sg:address":"324 Warren Pl",
    "sg:city":"Washington",
    "sg:classifiers":[
        {
            "category":"Professional",
            "type":"Services"
        }
    ],
    "sg:phone":"+1 252 923 0063",
    "sg:postcode":"27889",
    "sg:province":"NC",
    "wof:name":"Walter J Sawyer",
    "wof:placetype":"venue"
},
  "geometry": {"coordinates":[-76.89895300000001,35.478455],"type":"Point"}
}