{
  "type": "Feature",
  "properties": {
    "addr:full":"2287 Hartland Rd Morganton NC 28655",
    "addr:housenumber":"2287",
    "addr:postcode":"28655",
    "addr:street":"Hartland Rd",
    "iso:country":"US",
    "sg:address":"2287 Hartland Rd",
    "sg:city":"Morganton",
    "sg:classifiers":[
        {
            "category":"Social Services",
            "subcategory":"Adult Care",
            "type":"Services"
        }
    ],
    "sg:phone":"+1 828 433 5630",
    "sg:postcode":"28655",
    "sg:province":"NC",
    "sg:tags":[
        "residential"
    ],
    "wof:name":"Chesterfield Group Home",
    "wof:placetype":"venue"
},
  "geometry": {"coordinates":[-81.657056,35.816092],"type":"Point"}
}