{
  "type": "Feature",
  "properties": {
    "iso:country":"US",
    "sg:address":"2105 Eaton Ferry Rd",
    "sg:city":"Littleton",
    "sg:classifiers":[
        {
            "category":"Real Estate",
            "subcategory":"Real Estate Agent",
            "type":"Services"
        }
    ],
    "sg:phone":"+1 252 586 7720",
    "sg:postcode":"27850",
    "sg:province":"NC",
    "wof:name":"Rainbow Realty At Lake Gaston",
    "wof:placetype":"venue"
},
  "geometry": {"coordinates":[-77.958241,36.523017],"type":"Point"}
}