{
  "type": "Feature",
  "properties": {
    "iso:country":"US",
    "sg:address":"2816 Saxapahaw-Bethlehem Church Rd",
    "sg:city":"Graham",
    "sg:classifiers":[
        {
            "category":"Farming",
            "subcategory":"Farm",
            "type":"Manufacturing & Wholesale Goods"
        }
    ],
    "sg:phone":"+1 336 376 0282",
    "sg:postcode":"27253",
    "sg:province":"NC",
    "wof:name":"Greystone Farms",
    "wof:placetype":"venue"
},
  "geometry": {"coordinates":[-79.28128700000001,35.955642],"type":"Point"}
}