{
  "type": "Feature",
  "properties": {
    "addr:full":"2410 E Nc Highway 54 Durham NC 27713",
    "addr:housenumber":"2410",
    "addr:postcode":"27713",
    "addr:street":"E Nc Highway 54",
    "iso:country":"US",
    "sg:address":"2410 E Nc Highway 54",
    "sg:city":"Durham",
    "sg:classifiers":[
        {
            "category":"Professional",
            "subcategory":"Printing & Photocopies",
            "type":"Services"
        }
    ],
    "sg:phone":"+1 919 361 5809",
    "sg:postcode":"27713",
    "sg:province":"NC",
    "sg:tags":[
        "services-commercial",
        "duplicating",
        "copying"
    ],
    "sg:website":"http://www.universalprinting.com",
    "wof:name":"Universal Printing & Publishing Co Of Raleigh",
    "wof:placetype":"venue"
},
  "geometry": {"coordinates":[-78.888634,35.900668],"type":"Point"}
}