{
  "type": "Feature",
  "properties": {
    "iso:country":"US",
    "sg:address":"134 Jake Storie Rd",
    "sg:city":"Boone",
    "sg:classifiers":[
        {
            "category":"Farming",
            "subcategory":"Nursery",
            "type":"Manufacturing & Wholesale Goods"
        }
    ],
    "sg:phone":"+1 828 264 7574",
    "sg:postcode":"28607",
    "sg:province":"NC",
    "sg:tags":[
        "timber",
        "ornamental",
        "operation",
        "tract",
        "landscaping"
    ],
    "wof:name":"Yates Ldscpg & Christmas Trees",
    "wof:placetype":"venue"
},
  "geometry": {"coordinates":[-81.624098,36.159704],"type":"Point"}
}