{
  "type": "Feature",
  "properties": {
    "iso:country":"US",
    "sg:address":"12 Carnes Rd SW",
    "sg:city":"Winston Salem",
    "sg:classifiers":[
        {
            "category":"Wholesale",
            "subcategory":"Electrical",
            "type":"Manufacturing & Wholesale Goods"
        }
    ],
    "sg:phone":"+1 336 788 3212",
    "sg:postcode":"27127",
    "sg:province":"NC",
    "sg:tags":[
        "electric",
        "motor"
    ],
    "wof:name":"Mike's Motors",
    "wof:placetype":"venue"
},
  "geometry": {"coordinates":[-80.24354,36.03926],"type":"Point"}
}