{
  "type": "Feature",
  "properties": {
    "iso:country":"US",
    "sg:address":"127 Acton Cir",
    "sg:city":"Asheville",
    "sg:classifiers":[
        {
            "category":"Home & Garden",
            "subcategory":"Hardware",
            "type":"Retail Goods"
        }
    ],
    "sg:phone":"+1 828 667 9298",
    "sg:postcode":"28806",
    "sg:province":"NC",
    "sg:tags":[
        "store"
    ],
    "sg:website":"www.homedepot.com",
    "wof:name":"Home Depot the",
    "wof:placetype":"venue"
},
  "geometry": {"coordinates":[-82.636803,35.556599],"type":"Point"}
}