{
  "type": "Feature",
  "properties": {
    "iso:country":"US",
    "sg:address":"116 S Beaumont Ave",
    "sg:city":"Burlington",
    "sg:classifiers":[
        {
            "category":"Shopping",
            "subcategory":"Used Merchandise",
            "type":"Retail Goods"
        }
    ],
    "sg:phone":"+1 336 222 9690",
    "sg:postcode":"27217",
    "sg:province":"NC",
    "sg:tags":[
        "shop",
        "thrift"
    ],
    "wof:name":"Mebane Street Thrift Shop",
    "wof:placetype":"venue"
},
  "geometry": {"coordinates":[-79.41408699999999,36.0963],"type":"Point"}
}