{
  "type": "Feature",
  "properties": {
    "iso:country":"US",
    "sg:address":"811 Doggett Rd",
    "sg:city":"Forest City",
    "sg:classifiers":[
        {
            "category":"Organizations",
            "subcategory":"Religious Organization",
            "type":"Services"
        }
    ],
    "sg:phone":"+1   ",
    "sg:postcode":"28043",
    "sg:province":"NC",
    "wof:name":"Missionary Wesleyan Church",
    "wof:placetype":"venue"
},
  "geometry": {"coordinates":[-81.877387,35.305368],"type":"Point"}
}