{
  "type": "Feature",
  "properties": {
    "addr:full":"1111 Woodmont Dr Hendersonville NC 28791",
    "addr:housenumber":"1111",
    "addr:postcode":"28791",
    "addr:street":"Woodmont Dr",
    "iso:country":"US",
    "sg:address":"1111 Woodmont Dr",
    "sg:city":"Hendersonville",
    "sg:classifiers":[
        {
            "category":"Organizations",
            "subcategory":"Community Association",
            "type":"Services"
        }
    ],
    "sg:phone":"+1   ",
    "sg:postcode":"28791",
    "sg:province":"NC",
    "wof:name":"Towne Forest Property Home",
    "wof:placetype":"venue"
},
  "geometry": {"coordinates":[-82.477678,35.323664],"type":"Point"}
}