{
  "type": "Feature",
  "properties": {
    "addr:full":"5445 McGhees Mill Rd Semora NC 27343",
    "addr:housenumber":"5445",
    "addr:postcode":"27343",
    "addr:street":"Mcghees Mill Rd",
    "iso:country":"US",
    "sg:address":"5445 McGhees Mill Rd",
    "sg:city":"Semora",
    "sg:classifiers":[
        {
            "category":"Organizations",
            "subcategory":"Religious Organization",
            "type":"Services"
        }
    ],
    "sg:phone":"+1 336 599 2714",
    "sg:postcode":"27343",
    "sg:province":"NC",
    "sg:tags":[
        "church"
    ],
    "wof:name":"Christian Apostolic Holiness",
    "wof:placetype":"venue"
},
  "geometry": {"coordinates":[-79.05206,36.535763],"type":"Point"}
}