{
  "type": "Feature",
  "properties": {
    "addr:full":"30 Playhouse Rd Maggie Valley NC 28751",
    "addr:postcode":"28751",
    "addr:street":"Playhouse Rd",
    "iso:country":"US",
    "sg:address":"30 Playhouse Rd",
    "sg:city":"Maggie Valley",
    "sg:classifiers":[
        {
            "category":"Retail",
            "subcategory":"Auto Repair",
            "type":"Services"
        }
    ],
    "sg:phone":"+1 828 926 9650",
    "sg:postcode":"28751",
    "sg:province":"NC",
    "sg:tags":[
        "recreational",
        "vehicle"
    ],
    "wof:name":"Salty's Camping Plus",
    "wof:placetype":"venue"
},
  "geometry": {"coordinates":[-83.095595,35.517566],"type":"Point"}
}