{
  "type": "Feature",
  "properties": {
    "iso:country":"US",
    "sg:address":"206 Connors Cir",
    "sg:city":"Cary",
    "sg:classifiers":[
        {
            "category":"Recreation",
            "type":"Entertainment"
        }
    ],
    "sg:phone":"+1 919 481 9496",
    "sg:postcode":"27511",
    "sg:province":"NC",
    "sg:tags":[
        "camps-recreational"
    ],
    "wof:name":"Southern Spirit Unlimited",
    "wof:placetype":"venue"
},
  "geometry": {"coordinates":[-78.77909200000001,35.753665],"type":"Point"}
}