{
  "type": "Feature",
  "properties": {
    "addr:full":"5708 N Sharon Amity Rd Charlotte NC 28215",
    "addr:housenumber":"5708",
    "addr:postcode":"28215",
    "addr:street":"N Sharon Amity Rd",
    "iso:country":"US",
    "sg:address":"5708 N Sharon Amity Rd",
    "sg:city":"Charlotte",
    "sg:classifiers":[
        {
            "category":"Restaurant",
            "type":"Food & Drink"
        }
    ],
    "sg:menulink":"http://www.allmenus.com/nc/charlotte/39248-golden-gate/menu/",
    "sg:phone":"+1 704 536 7748",
    "sg:postcode":"28215",
    "sg:province":"NC",
    "sg:tags":[
        "asian",
        "chinese"
    ],
    "wof:name":"Golden Gate",
    "wof:placetype":"venue"
},
  "geometry": {"coordinates":[-80.73865600000001,35.234171],"type":"Point"}
}