{
  "type": "Feature",
  "properties": {
    "iso:country":"US",
    "sg:address":"400 W Morgan St",
    "sg:city":"Raleigh",
    "sg:classifiers":[
        {
            "category":"Bars & Pubs",
            "type":"Food & Drink"
        }
    ],
    "sg:phone":"+1 919 828 8525",
    "sg:postcode":"27603",
    "sg:province":"NC",
    "sg:tags":[
        "lounge",
        "cocktail"
    ],
    "wof:name":"Aries Lounge",
    "wof:placetype":"venue"
},
  "geometry": {"coordinates":[-78.645955,35.779837],"type":"Point"}
}