{
  "type": "Feature",
  "properties": {
    "iso:country":"US",
    "sg:address":"1502 Old Cherry Point Rd",
    "sg:city":"New Bern",
    "sg:classifiers":[
        {
            "category":"Retail",
            "subcategory":"Auto Repair",
            "type":"Services"
        }
    ],
    "sg:phone":"+1 252 635 6950",
    "sg:postcode":"28560",
    "sg:province":"NC",
    "sg:tags":[
        "engine",
        "shop",
        "machine",
        "automobile",
        "automotive"
    ],
    "wof:name":"Craven Automotive Machine Svcs",
    "wof:placetype":"venue"
},
  "geometry": {"coordinates":[-77.026061,35.075596],"type":"Point"}
}