{
  "type": "Feature",
  "properties": {
    "iso:country":"US",
    "sg:address":"1204 S Fulton St",
    "sg:city":"Salisbury",
    "sg:classifiers":[
        {
            "category":"Education",
            "subcategory":"Special Training",
            "type":"Public Place"
        }
    ],
    "sg:phone":"+1 704 645 2222",
    "sg:postcode":"28144",
    "sg:province":"NC",
    "sg:tags":[
        "modeling",
        "school"
    ],
    "wof:name":"Fashion One Modeling School",
    "wof:placetype":"venue"
},
  "geometry": {"coordinates":[-80.48659000000001,35.659288],"type":"Point"}
}