{
  "type": "Feature",
  "properties": {
    "iso:country":"US",
    "sg:address":"3525 Mossdale Ave",
    "sg:city":"Durham",
    "sg:classifiers":[
        {
            "category":"Professional",
            "subcategory":"Art Services",
            "type":"Services"
        }
    ],
    "sg:phone":"+1   ",
    "sg:postcode":"27707",
    "sg:province":"NC",
    "sg:tags":[
        "commercial",
        "design"
    ],
    "wof:name":"Aboutface Graphics",
    "wof:placetype":"venue"
},
  "geometry": {"coordinates":[-78.942303,35.960821],"type":"Point"}
}