{
  "type": "Feature",
  "properties": {
    "iso:country":"US",
    "sg:address":"1305 E Innes St",
    "sg:city":"Salisbury",
    "sg:classifiers":[
        {
            "category":"Wholesale",
            "subcategory":"Stationery",
            "type":"Manufacturing & Wholesale Goods"
        }
    ],
    "sg:phone":"+1 704 633 2061",
    "sg:postcode":"28146",
    "sg:province":"NC",
    "sg:tags":[
        "product",
        "paper"
    ],
    "wof:name":"Swicegood Paper Corp",
    "wof:placetype":"venue"
},
  "geometry": {"coordinates":[-80.459513,35.657527],"type":"Point"}
}