{
  "type": "Feature",
  "properties": {
    "addr:full":"1337 Hundred Oaks Dr Charlotte NC 28217",
    "addr:housenumber":"1337",
    "addr:postcode":"28217",
    "addr:street":"Hundred Oaks Dr",
    "iso:country":"US",
    "sg:address":"1337 Hundred Oaks Dr",
    "sg:city":"Charlotte",
    "sg:classifiers":[
        {
            "category":"Building & Trades",
            "subcategory":"Equipment Rental",
            "type":"Services"
        }
    ],
    "sg:phone":"+1 704 348 2676",
    "sg:postcode":"28217",
    "sg:province":"NC",
    "sg:tags":[
        "holding",
        "company",
        "it",
        "through",
        "rent",
        "which"
    ],
    "wof:name":"Ashtead US Holdings Dgp",
    "wof:placetype":"venue"
},
  "geometry": {"coordinates":[-80.905877,35.143671],"type":"Point"}
}