{
  "type": "Feature",
  "properties": {
    "iso:country":"US",
    "sg:address":"1911 Hunterwoods Dr",
    "sg:city":"High Point",
    "sg:classifiers":[
        {
            "category":"Health Services",
            "subcategory":"Doctor",
            "type":"Services"
        }
    ],
    "sg:phone":"+1   ",
    "sg:postcode":"27265",
    "sg:province":"NC",
    "sg:tags":[
        "medical"
    ],
    "wof:name":"Travelers Protective Assn",
    "wof:placetype":"venue"
},
  "geometry": {"coordinates":[-80.00658900000001,36.03446],"type":"Point"}
}