{
  "type": "Feature",
  "properties": {
    "iso:country":"US",
    "sg:address":"221 Clear Springs Rd",
    "sg:city":"Mooresville",
    "sg:classifiers":[
        {
            "category":"Building & Trades",
            "subcategory":"Construction",
            "type":"Services"
        }
    ],
    "sg:phone":"+1 980 722 1651",
    "sg:postcode":"28115",
    "sg:province":"NC",
    "sg:tags":[
        "house"
    ],
    "wof:name":"Remodeling Property Maint",
    "wof:placetype":"venue"
},
  "geometry": {"coordinates":[-80.853768,35.646966],"type":"Point"}
}