{
  "type": "Feature",
  "properties": {
    "addr:full":"3943 Chesapeake Dr Charlotte NC 28216",
    "addr:housenumber":"3943",
    "addr:postcode":"28216",
    "addr:street":"Chesapeake Dr",
    "iso:country":"US",
    "sg:address":"3943 Chesapeake Dr",
    "sg:city":"Charlotte",
    "sg:classifiers":[
        {
            "category":"Wholesale",
            "subcategory":"Vending Machines",
            "type":"Manufacturing & Wholesale Goods"
        }
    ],
    "sg:phone":"+1 704 622 1606",
    "sg:postcode":"28216",
    "sg:province":"NC",
    "wof:name":"Amerivend Inc",
    "wof:placetype":"venue"
},
  "geometry": {"coordinates":[-80.86994799999999,35.272805],"type":"Point"}
}