{
  "type": "Feature",
  "properties": {
    "iso:country":"US",
    "sg:address":"9645 US Hwy 64",
    "sg:city":"Taylorsville",
    "sg:classifiers":[
        {
            "category":"Shopping",
            "subcategory":"Discount & Variety Stores",
            "type":"Retail Goods"
        }
    ],
    "sg:phone":"+1 828 495 4553",
    "sg:postcode":"28681",
    "sg:province":"NC",
    "wof:name":"Thrifty Dollar",
    "wof:placetype":"venue"
},
  "geometry": {"coordinates":[-81.339026,35.909381],"type":"Point"}
}