{
  "type": "Feature",
  "properties": {
    "addr:full":"1223 Badger Ct Charlotte NC 28206",
    "addr:housenumber":"1223",
    "addr:postcode":"28206",
    "addr:street":"Badger Ct",
    "iso:country":"US",
    "sg:address":"1223 Badger Ct",
    "sg:city":"Charlotte",
    "sg:classifiers":[
        {
            "category":"Personal",
            "subcategory":"Barber",
            "type":"Services"
        }
    ],
    "sg:phone":"+1   ",
    "sg:postcode":"28206",
    "sg:province":"NC",
    "sg:tags":[
        "shop"
    ],
    "wof:name":"Stylz Barber Stylist",
    "wof:placetype":"venue"
},
  "geometry": {"coordinates":[-80.836461,35.25333],"type":"Point"}
}