{
  "type": "Feature",
  "properties": {
    "addr:full":"4408 Colwick Rd Charlotte NC 28211",
    "addr:housenumber":"4408",
    "addr:postcode":"28211",
    "addr:street":"Colwick Rd",
    "iso:country":"US",
    "sg:address":"4408 Colwick Rd",
    "sg:city":"Charlotte",
    "sg:classifiers":[
        {
            "category":"Retail",
            "subcategory":"Laundry & Dry Cleaning",
            "type":"Services"
        }
    ],
    "sg:phone":"+1 704 442 7200",
    "sg:postcode":"28211",
    "sg:province":"NC",
    "sg:tags":[
        "cleaners"
    ],
    "wof:name":"Cleaner Options",
    "wof:placetype":"venue"
},
  "geometry": {"coordinates":[-80.797225,35.176317],"type":"Point"}
}