{
  "type": "Feature",
  "properties": {
    "iso:country":"US",
    "sg:address":"2253 Autumn Dr",
    "sg:city":"Kinston",
    "sg:classifiers":[
        {
            "category":"Banks & Credit Unions",
            "subcategory":"Financial Services",
            "type":"Services"
        }
    ],
    "sg:phone":"+1 252 527 5376",
    "sg:postcode":"28501",
    "sg:province":"NC",
    "sg:tags":[
        "company",
        "holding"
    ],
    "wof:name":"Enc Holdings LLC",
    "wof:placetype":"venue"
},
  "geometry": {"coordinates":[-77.56263800000001,35.305354],"type":"Point"}
}