{
  "type": "Feature",
  "properties": {
    "iso:country":"US",
    "sg:address":"230 Livermore Dr",
    "sg:city":"Fayetteville",
    "sg:classifiers":[
        {
            "category":"Utilities",
            "type":"Services"
        }
    ],
    "sg:phone":"+1 910 867 9525",
    "sg:postcode":"28314",
    "sg:province":"NC",
    "sg:tags":[
        "sanitary",
        "landscape"
    ],
    "wof:name":"Commercial Sweping Ldscp Maint",
    "wof:placetype":"venue"
},
  "geometry": {"coordinates":[-79.003006,35.07471],"type":"Point"}
}