{
  "type": "Feature",
  "properties": {
    "addr:full":"2245 N Hills Dr Raleigh NC 27612",
    "addr:housenumber":"2245",
    "addr:postcode":"27612",
    "addr:street":"N Hills Dr",
    "iso:country":"US",
    "sg:address":"2245 N Hills Dr",
    "sg:city":"Raleigh",
    "sg:classifiers":[
        {
            "category":"Health Services",
            "subcategory":"Health Practitioner",
            "type":"Services"
        }
    ],
    "sg:phone":"+1 919 787 3818",
    "sg:postcode":"27612",
    "sg:province":"NC",
    "sg:tags":[
        "therapist",
        "physical"
    ],
    "wof:name":"Center For Creative Healing",
    "wof:placetype":"venue"
},
  "geometry": {"coordinates":[-78.67187199999999,35.839756],"type":"Point"}
}