{
  "type": "Feature",
  "properties": {
    "addr:full":"399 Windward Cir Mocksville NC 27028",
    "addr:housenumber":"399",
    "addr:postcode":"27028",
    "addr:street":"Windward Cir",
    "iso:country":"US",
    "sg:address":"399 Windward Cir",
    "sg:city":"Mocksville",
    "sg:classifiers":[
        {
            "category":"Building & Trades",
            "subcategory":"Landscaping Services",
            "type":"Services"
        }
    ],
    "sg:phone":"+1 336 751 2099",
    "sg:postcode":"27028",
    "sg:province":"NC",
    "sg:tags":[
        "landscape"
    ],
    "wof:name":"J & J Services",
    "wof:placetype":"venue"
},
  "geometry": {"coordinates":[-80.52710500000001,35.901143],"type":"Point"}
}