{
  "type": "Feature",
  "properties": {
    "iso:country":"US",
    "sg:address":"1314 Duck Rd",
    "sg:city":"Kitty Hawk",
    "sg:classifiers":[
        {
            "category":"Recreation",
            "type":"Entertainment"
        }
    ],
    "sg:phone":"+1 252 261 2900",
    "sg:postcode":"27949",
    "sg:province":"NC",
    "sg:tags":[
        "charter",
        "boat"
    ],
    "wof:name":"Nor'Banks Sailing",
    "wof:placetype":"venue"
},
  "geometry": {"coordinates":[-75.76467599999999,36.20038],"type":"Point"}
}