{
  "type": "Feature",
  "properties": {
    "addr:full":"1732 Quail Ridge Rd Raleigh NC 27609",
    "addr:housenumber":"1732",
    "addr:postcode":"27609",
    "addr:street":"Quail Ridge Rd",
    "iso:country":"US",
    "sg:address":"1732 Quail Ridge Rd",
    "sg:city":"Raleigh",
    "sg:classifiers":[
        {
            "category":"Professional",
            "subcategory":"Management & Consulting",
            "type":"Services"
        }
    ],
    "sg:phone":"+1   ",
    "sg:postcode":"27609",
    "sg:province":"NC",
    "sg:tags":[
        "consultant",
        "real estate"
    ],
    "wof:name":"G L French & Associates Inc",
    "wof:placetype":"venue"
},
  "geometry": {"coordinates":[-78.60901,35.855535],"type":"Point"}
}