{
  "type": "Feature",
  "properties": {
    "iso:country":"US",
    "sg:address":"706 Tulls Creek Rd",
    "sg:city":"Moyock",
    "sg:classifiers":[
        {
            "category":"Wholesale",
            "subcategory":"Construction Materials",
            "type":"Manufacturing & Wholesale Goods"
        }
    ],
    "sg:phone":"+1 252 207 4638",
    "sg:postcode":"27958",
    "sg:province":"NC",
    "sg:tags":[
        "sand",
        "gravel"
    ],
    "wof:name":"Tulls Creek Sand",
    "wof:placetype":"venue"
},
  "geometry": {"coordinates":[-76.1665,36.522774],"type":"Point"}
}