{
  "type": "Feature",
  "properties": {
    "addr:full":"7795 Turnpike Rd Swanquarter NC 27885",
    "addr:housenumber":"7795",
    "addr:postcode":"27885",
    "addr:street":"Turnpike Rd",
    "iso:country":"US",
    "sg:address":"7795 Turnpike Rd",
    "sg:city":"Swanquarter",
    "sg:classifiers":[
        {
            "category":"Farming",
            "subcategory":"Farm",
            "type":"Manufacturing & Wholesale Goods"
        }
    ],
    "sg:phone":"+1 252 926 7081",
    "sg:postcode":"27885",
    "sg:province":"NC",
    "sg:tags":[
        "crop",
        "general"
    ],
    "wof:name":"J P Oneal & Sons",
    "wof:placetype":"venue"
},
  "geometry": {"coordinates":[-76.376865,35.461764],"type":"Point"}
}