{
  "type": "Feature",
  "properties": {
    "addr:full":"1500 Old Cherry Point Rd New Bern NC 28560",
    "addr:housenumber":"1500",
    "addr:postcode":"28560",
    "addr:street":"Old Cherry Point Rd",
    "iso:country":"US",
    "sg:address":"1500 Old Cherry Point Rd",
    "sg:city":"New Bern",
    "sg:classifiers":[
        {
            "category":"Retail",
            "subcategory":"Auto Repair",
            "type":"Services"
        }
    ],
    "sg:phone":"+1   ",
    "sg:postcode":"28560",
    "sg:province":"NC",
    "sg:tags":[
        "general"
    ],
    "wof:name":"Bennetts Automotive Inc",
    "wof:placetype":"venue"
},
  "geometry": {"coordinates":[-77.02612999999999,35.075562],"type":"Point"}
}