{
  "type": "Feature",
  "properties": {
    "addr:full":"5458 US Hwy 70 Morehead City NC 28557",
    "addr:housenumber":"5458",
    "addr:postcode":"28557",
    "addr:street":"Us Hwy 70",
    "iso:country":"US",
    "sg:address":"5458 US Hwy 70",
    "sg:city":"Morehead City",
    "sg:classifiers":[
        {
            "category":"Organizations",
            "subcategory":"Religious Organization",
            "type":"Services"
        }
    ],
    "sg:phone":"+1 252 247 0199",
    "sg:postcode":"28557",
    "sg:province":"NC",
    "wof:name":"Gideons International",
    "wof:placetype":"venue"
},
  "geometry": {"coordinates":[-76.82741300000001,34.743943],"type":"Point"}
}