{
  "type": "Feature",
  "properties": {
    "iso:country":"US",
    "sg:address":"1368 Shearers Rd",
    "sg:city":"Mooresville",
    "sg:classifiers":[
        {
            "category":"Manufacturing",
            "subcategory":"Tools & Machinery",
            "type":"Manufacturing & Wholesale Goods"
        }
    ],
    "sg:phone":"+1 704 664 4579",
    "sg:postcode":"28115",
    "sg:province":"NC",
    "sg:tags":[
        "textile",
        "machine",
        "shop",
        "mfg"
    ],
    "wof:name":"Sherrill Hal L Machine Co",
    "wof:placetype":"venue"
},
  "geometry": {"coordinates":[-80.809595,35.55236],"type":"Point"}
}