{
  "type": "Feature",
  "properties": {
    "addr:full":"3308 Patriot Pl Graham NC 27253",
    "addr:housenumber":"3308",
    "addr:postcode":"27253",
    "addr:street":"Patriot Pl",
    "iso:country":"US",
    "sg:address":"3308 Patriot Pl",
    "sg:city":"Graham",
    "sg:classifiers":[
        {
            "category":"Building & Trades",
            "subcategory":"Electrical",
            "type":"Services"
        }
    ],
    "sg:phone":"+1 336 227 3707",
    "sg:postcode":"27253",
    "sg:province":"NC",
    "sg:tags":[
        "electrical",
        "contractor"
    ],
    "wof:name":"AG Neese Electric Co",
    "wof:placetype":"venue"
},
  "geometry": {"coordinates":[-79.399928,35.992812],"type":"Point"}
}