{
  "type": "Feature",
  "properties": {
    "iso:country":"US",
    "sg:address":"8020 Providence Rd",
    "sg:city":"Charlotte",
    "sg:classifiers":[
        {
            "category":"Shopping",
            "subcategory":"Bicycles & Sporting Goods",
            "type":"Retail Goods"
        }
    ],
    "sg:phone":"+1 704 544 8859",
    "sg:postcode":"28277",
    "sg:province":"NC",
    "sg:tags":[
        "equipment",
        "exercise"
    ],
    "wof:name":"Lifestyle Fitness Equipment",
    "wof:placetype":"venue"
},
  "geometry": {"coordinates":[-80.778764,35.099801],"type":"Point"}
}