{
  "type": "Feature",
  "properties": {
    "addr:full":"3917 Sedgebrook St High Point NC 27265",
    "addr:postcode":"3917;27265",
    "addr:street":"Sedgebrook St",
    "iso:country":"US",
    "sg:address":"3917 Sedgebrook St",
    "sg:city":"High Point",
    "sg:classifiers":[
        {
            "category":"Personal",
            "type":"Services"
        },
        {
            "category":"Restaurant",
            "type":"Food & Drink"
        }
    ],
    "sg:phone":"+1 336 887 3473",
    "sg:postcode":"27265",
    "sg:province":"NC",
    "sg:tags":[
        "eating"
    ],
    "wof:name":"Fire & Sticks Japanese Steakho",
    "wof:placetype":"venue"
},
  "geometry": {"coordinates":[-79.962805,36.060808],"type":"Point"}
}