{
  "type": "Feature",
  "properties": {
    "addr:full":"1303 Timber Dr Garner NC 27529",
    "addr:housenumber":"1303",
    "addr:postcode":"27529",
    "addr:street":"Timber Dr",
    "iso:country":"US",
    "sg:address":"1303 Timber Dr",
    "sg:city":"Garner",
    "sg:classifiers":[
        {
            "category":"Personal",
            "type":"Services"
        }
    ],
    "sg:phone":"+1   ",
    "sg:postcode":"27529",
    "sg:province":"NC",
    "wof:name":"Weight Management 4u Inc",
    "wof:placetype":"venue"
},
  "geometry": {"coordinates":[-78.62749100000001,35.686175],"type":"Point"}
}