{
  "type": "Feature",
  "properties": {
    "iso:country":"US",
    "sg:address":"5213 Treybrooke Dr",
    "sg:city":"Wilmington",
    "sg:classifiers":[
        {
            "category":"Professional",
            "type":"Services"
        }
    ],
    "sg:phone":"+1 910 392 1377",
    "sg:postcode":"28409",
    "sg:province":"NC",
    "sg:tags":[
        "establishment"
    ],
    "wof:name":"Affordable Housing Group",
    "wof:placetype":"venue"
},
  "geometry": {"coordinates":[-77.864009,34.171643],"type":"Point"}
}