{
  "type": "Feature",
  "properties": {
    "iso:country":"US",
    "sg:address":"2777 New Leicester Hwy",
    "sg:city":"Leicester",
    "sg:classifiers":[
        {
            "category":"Shopping",
            "subcategory":"Used Merchandise",
            "type":"Retail Goods"
        }
    ],
    "sg:phone":"+1 828 683 3551",
    "sg:postcode":"28748",
    "sg:province":"NC",
    "sg:tags":[
        "flea",
        "market"
    ],
    "wof:name":"A W New & Used",
    "wof:placetype":"venue"
},
  "geometry": {"coordinates":[-82.695402,35.655096],"type":"Point"}
}