{
  "type": "Feature",
  "properties": {
    "addr:full":"299 Pine Tree Dr Henrico NC 27842",
    "addr:housenumber":"299",
    "addr:postcode":"27842",
    "addr:street":"Pine Tree Dr",
    "iso:country":"US",
    "sg:address":"299 Pine Tree Dr",
    "sg:city":"Henrico",
    "sg:classifiers":[
        {
            "category":"Structure",
            "subcategory":"Office Building",
            "type":"Public Place"
        }
    ],
    "sg:phone":"+1 252 537 8109",
    "sg:postcode":"27842",
    "sg:province":"NC",
    "sg:tags":[
        "park"
    ],
    "wof:name":"Noell Properties",
    "wof:placetype":"venue"
},
  "geometry": {"coordinates":[-77.83911500000001,36.519008],"type":"Point"}
}