{
  "type": "Feature",
  "properties": {
    "addr:full":"2782 Fairview Dr Gastonia NC 28052",
    "addr:housenumber":"2782",
    "addr:postcode":"28052",
    "addr:street":"Fairview Dr",
    "iso:country":"US",
    "sg:address":"2782 Fairview Dr",
    "sg:city":"Gastonia",
    "sg:classifiers":[
        {
            "category":"Organizations",
            "subcategory":"Religious Organization",
            "type":"Services"
        }
    ],
    "sg:phone":"+1   ",
    "sg:postcode":"28052",
    "sg:province":"NC",
    "wof:name":"Midway Baptist Church",
    "wof:placetype":"venue"
},
  "geometry": {"coordinates":[-81.216599,35.291812],"type":"Point"}
}