{
  "type": "Feature",
  "properties": {
    "addr:full":"602 Holden St Raleigh NC 27604",
    "addr:housenumber":"602",
    "addr:postcode":"27604",
    "addr:street":"Holden St",
    "iso:country":"US",
    "sg:address":"602 Holden St",
    "sg:city":"Raleigh",
    "sg:classifiers":[
        {
            "category":"Building & Trades",
            "subcategory":"Landscaping Services",
            "type":"Services"
        }
    ],
    "sg:phone":"+1 919 755 0758",
    "sg:postcode":"27604",
    "sg:province":"NC",
    "sg:tags":[
        "landscape"
    ],
    "wof:name":"Hyde Park Landscaping Inc",
    "wof:placetype":"venue"
},
  "geometry": {"coordinates":[-78.628491,35.790582],"type":"Point"}
}