{
  "type": "Feature",
  "properties": {
    "addr:full":"1311 N Elm St Greensboro NC 27401",
    "addr:housenumber":"1311",
    "addr:postcode":"27401",
    "addr:street":"N Elm St",
    "iso:country":"US",
    "sg:address":"1311 N Elm St",
    "sg:city":"Greensboro",
    "sg:classifiers":[
        {
            "category":"Health Services",
            "subcategory":"Chiropractor",
            "type":"Services"
        }
    ],
    "sg:phone":"+1   ",
    "sg:postcode":"27401",
    "sg:province":"NC",
    "wof:name":"Eugene A Lewis Dr",
    "wof:placetype":"venue"
},
  "geometry": {"coordinates":[-79.788768,36.092562],"type":"Point"}
}