{
  "type": "Feature",
  "properties": {
    "iso:country":"US",
    "sg:address":"127 Fairview Rd",
    "sg:city":"Leland",
    "sg:classifiers":[
        {
            "category":"Professional",
            "type":"Services"
        }
    ],
    "sg:phone":"+1 910 371 9850",
    "sg:postcode":"28451",
    "sg:province":"NC",
    "wof:name":"Fairfax Alton",
    "wof:placetype":"venue"
},
  "geometry": {"coordinates":[-77.995672,34.239239],"type":"Point"}
}