{
  "type": "Feature",
  "properties": {
    "addr:full":"5306 Six Forks Rd Raleigh NC 27609",
    "addr:housenumber":"5306",
    "addr:postcode":"27609",
    "addr:street":"Six Forks Rd",
    "iso:country":"US",
    "sg:address":"5306 Six Forks Rd",
    "sg:city":"Raleigh",
    "sg:classifiers":[
        {
            "category":"Real Estate",
            "subcategory":"Real Estate Agent",
            "type":"Services"
        }
    ],
    "sg:phone":"+1 919 881 9787",
    "sg:postcode":"27609",
    "sg:province":"NC",
    "wof:name":"Park Real Estate",
    "wof:placetype":"venue"
},
  "geometry": {"coordinates":[-78.64214699999999,35.854371],"type":"Point"}
}