{
  "type": "Feature",
  "properties": {
    "iso:country":"US",
    "sg:address":"1005 Maple Ave",
    "sg:city":"Burlington",
    "sg:classifiers":[
        {
            "category":"Building & Trades",
            "subcategory":"Construction",
            "type":"Services"
        }
    ],
    "sg:phone":"+1 336 227 2345",
    "sg:postcode":"27215",
    "sg:province":"NC",
    "sg:tags":[
        "house"
    ],
    "wof:name":"Moran Home Improvements",
    "wof:placetype":"venue"
},
  "geometry": {"coordinates":[-79.429377,36.083079],"type":"Point"}
}