{
  "type": "Feature",
  "properties": {
    "addr:full":"10120 Albemarle Rd Charlotte NC 28227",
    "addr:housenumber":"10120",
    "addr:postcode":"28227",
    "addr:street":"Albemarle Rd",
    "iso:country":"US",
    "sg:address":"10120 Albemarle Rd",
    "sg:city":"Charlotte",
    "sg:classifiers":[
        {
            "category":"Retail",
            "subcategory":"Auto Repair",
            "type":"Services"
        }
    ],
    "sg:phone":"+1 704 573 7189",
    "sg:postcode":"28227",
    "sg:province":"NC",
    "sg:tags":[
        "transmission"
    ],
    "sg:website":"www.aamco.com",
    "wof:name":"AAMCO Transmissions",
    "wof:placetype":"venue"
},
  "geometry": {"coordinates":[-80.67171399999999,35.208565],"type":"Point"}
}