{
  "type": "Feature",
  "properties": {
    "iso:country":"US",
    "sg:address":"111 W Davis St",
    "sg:city":"Burlington",
    "sg:classifiers":[
        {
            "category":"Shopping",
            "subcategory":"Shoes",
            "type":"Retail Goods"
        }
    ],
    "sg:phone":"+1 336 226 0687",
    "sg:postcode":"27215",
    "sg:province":"NC",
    "sg:tags":[
        "retailer",
        "shoe"
    ],
    "wof:name":"H & K Bootery Inc",
    "wof:placetype":"venue"
},
  "geometry": {"coordinates":[-79.438112,36.093747],"type":"Point"}
}