{
  "type": "Feature",
  "properties": {
    "addr:full":"2408 Finchley Dr Charlotte NC 28215",
    "addr:housenumber":"2408",
    "addr:postcode":"28215",
    "addr:street":"Finchley Dr",
    "iso:country":"US",
    "sg:address":"2408 Finchley Dr",
    "sg:city":"Charlotte",
    "sg:classifiers":[
        {
            "category":"Home & Garden",
            "subcategory":"Home Furnishings",
            "type":"Retail Goods"
        }
    ],
    "sg:phone":"+1 704 563 7797",
    "sg:postcode":"28215",
    "sg:province":"NC",
    "wof:name":"Katherine Huey Draperies",
    "wof:placetype":"venue"
},
  "geometry": {"coordinates":[-80.77181,35.238268],"type":"Point"}
}