{
  "type": "Feature",
  "properties": {
    "addr:full":"4950 Smoke Wood Rd Randleman NC 27317",
    "addr:housenumber":"4950",
    "addr:postcode":"27317",
    "addr:street":"Smoke Wood Rd",
    "iso:country":"US",
    "sg:address":"4950 Smoke Wood Rd",
    "sg:city":"Randleman",
    "sg:classifiers":[
        {
            "category":"Building & Trades",
            "subcategory":"Construction",
            "type":"Services"
        }
    ],
    "sg:phone":"+1 336 498 7155",
    "sg:postcode":"27317",
    "sg:province":"NC",
    "sg:tags":[
        "roofing",
        "contractor"
    ],
    "wof:name":"Thornburg Roofing Co",
    "wof:placetype":"venue"
},
  "geometry": {"coordinates":[-79.79422599999999,35.853175],"type":"Point"}
}