{
  "type": "Feature",
  "properties": {
    "iso:country":"US",
    "sg:address":"234 Highlands Rd",
    "sg:city":"Franklin",
    "sg:classifiers":[
        {
            "category":"Restaurant",
            "type":"Food & Drink"
        }
    ],
    "sg:phone":"+1 828 349 3465",
    "sg:postcode":"28734",
    "sg:province":"NC",
    "sg:tags":[
        "eating"
    ],
    "wof:name":"Salvatores Restaurant",
    "wof:placetype":"venue"
},
  "geometry": {"coordinates":[-83.369546,35.185156],"type":"Point"}
}