{
  "type": "Feature",
  "properties": {
    "addr:full":"3325 Statesville Blvd Salisbury NC 28147",
    "addr:housenumber":"3325",
    "addr:postcode":"28147",
    "addr:street":"Statesville Blvd",
    "iso:country":"US",
    "sg:address":"3325 Statesville Blvd",
    "sg:city":"Salisbury",
    "sg:classifiers":[
        {
            "category":"Social Services",
            "subcategory":"Child Care",
            "type":"Services"
        }
    ],
    "sg:phone":"+1 704 639 0081",
    "sg:postcode":"28147",
    "sg:province":"NC",
    "sg:tags":[
        "day"
    ],
    "wof:name":"Noah's Ark Daycare",
    "wof:placetype":"venue"
},
  "geometry": {"coordinates":[-80.546514,35.704557],"type":"Point"}
}