{
  "type": "Feature",
  "properties": {
    "iso:country":"US",
    "sg:address":"3017 Parkway Ave",
    "sg:city":"Charlotte",
    "sg:classifiers":[
        {
            "category":"Personal",
            "subcategory":"Beauty Salon",
            "type":"Services"
        }
    ],
    "sg:phone":"+1 704 398 9030",
    "sg:postcode":"28208",
    "sg:province":"NC",
    "wof:name":"This Becomes You",
    "wof:placetype":"venue"
},
  "geometry": {"coordinates":[-80.87723099999999,35.244248],"type":"Point"}
}