{
  "type": "Feature",
  "properties": {
    "iso:country":"US",
    "sg:address":"121 Sherron Rd",
    "sg:city":"Durham",
    "sg:classifiers":[
        {
            "category":"Insurance",
            "subcategory":"Insurance Agent",
            "type":"Services"
        }
    ],
    "sg:phone":"+1 919 596 0671",
    "sg:postcode":"27703",
    "sg:province":"NC",
    "sg:tags":[
        "agency"
    ],
    "wof:name":"Bull City Insurance Agency",
    "wof:placetype":"venue"
},
  "geometry": {"coordinates":[-78.793882,35.975662],"type":"Point"}
}