{
  "type": "Feature",
  "properties": {
    "iso:country":"US",
    "sg:address":"209 Creeks Edge",
    "sg:city":"Chapel Hill",
    "sg:classifiers":[
        {
            "category":"Airline",
            "type":"Transportation"
        }
    ],
    "sg:phone":"+1 919 225 9516",
    "sg:postcode":"27516",
    "sg:province":"NC",
    "sg:tags":[
        "nonscheduled",
        "air"
    ],
    "wof:name":"Central Air Charter Inc",
    "wof:placetype":"venue"
},
  "geometry": {"coordinates":[-79.094554,35.832362],"type":"Point"}
}