{
  "type": "Feature",
  "properties": {
    "iso:country":"US",
    "sg:address":"1913 Essex Rd",
    "sg:city":"Durham",
    "sg:classifiers":[
        {
            "category":"Social Services",
            "subcategory":"Child Care",
            "type":"Services"
        }
    ],
    "sg:phone":"+1   ",
    "sg:postcode":"27704",
    "sg:province":"NC",
    "sg:tags":[
        "day"
    ],
    "wof:name":"Peggie Moore Day Care",
    "wof:placetype":"venue"
},
  "geometry": {"coordinates":[-78.87178299999999,36.00636],"type":"Point"}
}