{
  "type": "Feature",
  "properties": {
    "addr:full":"819 Martin Luther King Jr Dr Asheboro NC 27203",
    "addr:housenumber":"819",
    "addr:postcode":"27203",
    "addr:street":"Martin Luther King Jr Dr",
    "iso:country":"US",
    "sg:address":"819 Martin Luther King Jr Dr",
    "sg:city":"Asheboro",
    "sg:classifiers":[
        {
            "category":"Organizations",
            "subcategory":"Religious Organization",
            "type":"Services"
        }
    ],
    "sg:phone":"+1 336 625 1808",
    "sg:postcode":"27203",
    "sg:province":"NC",
    "sg:tags":[
        "church"
    ],
    "wof:name":"St Johns Baptist Church",
    "wof:placetype":"venue"
},
  "geometry": {"coordinates":[-79.800516,35.708749],"type":"Point"}
}