{
  "type": "Feature",
  "properties": {
    "addr:full":"2245 N Hills Dr Ste C Raleigh NC 27612",
    "addr:housenumber":"2245",
    "addr:postcode":"27612",
    "addr:street":"N Hills Dr Ste C",
    "iso:country":"US",
    "sg:address":"2245 N Hills Dr Ste C",
    "sg:city":"Raleigh",
    "sg:phone":"+1 919 781 8830",
    "sg:postcode":"27612",
    "sg:province":"NC",
    "wof:name":"Crabtree Chiropractic Ctr",
    "wof:placetype":"venue"
},
  "geometry": {"coordinates":[-78.672541,35.839751],"type":"Point"}
}