{
  "type": "Feature",
  "properties": {
    "addr:full":"40 W 12th Ave Lexington NC 27292",
    "addr:housenumber":"40",
    "addr:postcode":"27292",
    "addr:street":"W 12Th Ave",
    "iso:country":"US",
    "sg:address":"40 W 12th Ave",
    "sg:city":"Lexington",
    "sg:classifiers":[
        {
            "category":"Wholesale",
            "subcategory":"Home Furnishings",
            "type":"Manufacturing & Wholesale Goods"
        }
    ],
    "sg:phone":"+1 336 248 2076",
    "sg:postcode":"27292",
    "sg:province":"NC",
    "sg:tags":[
        "picture",
        "frame"
    ],
    "wof:name":"Picture Frame Outlet",
    "wof:placetype":"venue"
},
  "geometry": {"coordinates":[-80.26754200000001,35.813851],"type":"Point"}
}