{
  "type": "Feature",
  "properties": {
    "addr:full":"4120 Fowler Ridge Dr Raleigh NC 27616",
    "addr:housenumber":"4120",
    "addr:postcode":"27616",
    "addr:street":"Fowler Ridge Dr",
    "iso:country":"US",
    "sg:address":"4120 Fowler Ridge Dr",
    "sg:city":"Raleigh",
    "sg:classifiers":[
        {
            "category":"Wholesale",
            "subcategory":"Machinery & Supplies",
            "type":"Manufacturing & Wholesale Goods"
        }
    ],
    "sg:phone":"+1 919 872 3543",
    "sg:postcode":"27616",
    "sg:province":"NC",
    "wof:name":"Small Engine Supply Inc",
    "wof:placetype":"venue"
},
  "geometry": {"coordinates":[-78.56114599999999,35.834389],"type":"Point"}
}