{
  "type": "Feature",
  "properties": {
    "iso:country":"US",
    "sg:address":"60 Pelican Dr",
    "sg:city":"Wrightsville Beach",
    "sg:classifiers":[
        {
            "category":"Real Estate",
            "subcategory":"Real Estate Operator",
            "type":"Services"
        }
    ],
    "sg:phone":"+1 910 256 6910",
    "sg:postcode":"28480",
    "sg:province":"NC",
    "sg:tags":[
        "building",
        "nonresidential"
    ],
    "wof:name":"Neighborhood Properties Co LLC",
    "wof:placetype":"venue"
},
  "geometry": {"coordinates":[-77.798254,34.21831],"type":"Point"}
}