{
  "type": "Feature",
  "properties": {
    "iso:country":"US",
    "sg:address":"716 Barington Pl",
    "sg:city":"Matthews",
    "sg:classifiers":[
        {
            "category":"Banks & Credit Unions",
            "subcategory":"Financial Services",
            "type":"Services"
        }
    ],
    "sg:phone":"+1 704 841 7210",
    "sg:postcode":"28105",
    "sg:province":"NC",
    "sg:tags":[
        "company",
        "holding"
    ],
    "wof:name":"Plano Holdings LLC",
    "wof:placetype":"venue"
},
  "geometry": {"coordinates":[-80.74743700000001,35.102668],"type":"Point"}
}