{
  "type": "Feature",
  "properties": {
    "addr:full":"2301 Patterson Ave Winston Salem NC 27105",
    "addr:housenumber":"2301",
    "addr:postcode":"27105",
    "addr:street":"Patterson Ave",
    "iso:country":"US",
    "sg:address":"2301 Patterson Ave",
    "sg:city":"Winston Salem",
    "sg:classifiers":[
        {
            "category":"Government",
            "subcategory":"Office",
            "type":"Public Place"
        }
    ],
    "sg:phone":"+1 336 727 2975",
    "sg:postcode":"27105",
    "sg:province":"NC",
    "sg:tags":[
        "village"
    ],
    "wof:name":"Black-Phillips-Smith Gvrnmnt",
    "wof:placetype":"venue"
},
  "geometry": {"coordinates":[-80.241895,36.118114],"type":"Point"}
}