{
  "type": "Feature",
  "properties": {
    "addr:full":"5626 Birch Dr Durham NC 27712",
    "addr:housenumber":"5626",
    "addr:postcode":"27712",
    "addr:street":"Birch Dr",
    "iso:country":"US",
    "sg:address":"5626 Birch Dr",
    "sg:city":"Durham",
    "sg:classifiers":[
        {
            "category":"Professional",
            "subcategory":"Business Services",
            "type":"Services"
        }
    ],
    "sg:phone":"+1   ",
    "sg:postcode":"27712",
    "sg:province":"NC",
    "wof:name":"Deatons Mobile Pressure Wash",
    "wof:placetype":"venue"
},
  "geometry": {"coordinates":[-78.92478199999999,36.097149],"type":"Point"}
}