{
  "type": "Feature",
  "properties": {
    "addr:full":"3026 White Cross Rd Chapel Hill NC 27516",
    "addr:housenumber":"3026",
    "addr:postcode":"27516",
    "addr:street":"White Cross Rd",
    "iso:country":"US",
    "sg:address":"3026 White Cross Rd",
    "sg:city":"Chapel Hill",
    "sg:classifiers":[
        {
            "category":"Retail",
            "subcategory":"Repair Shop",
            "type":"Services"
        }
    ],
    "sg:phone":"+1 919 968 3004",
    "sg:postcode":"27516",
    "sg:province":"NC",
    "sg:tags":[
        "sewing"
    ],
    "wof:name":"Superior Furniture Upholstery",
    "wof:placetype":"venue"
},
  "geometry": {"coordinates":[-79.187512,35.921198],"type":"Point"}
}