{
  "type": "Feature",
  "properties": {
    "addr:full":"6100 Old Mount Holly Rd Charlotte NC 28208",
    "addr:housenumber":"6100",
    "addr:postcode":"28208",
    "addr:street":"Old Mount Holly Rd",
    "iso:country":"US",
    "sg:address":"6100 Old Mount Holly Rd",
    "sg:city":"Charlotte",
    "sg:classifiers":[
        {
            "category":"Freight",
            "type":"Transportation"
        }
    ],
    "sg:phone":"+1 704 392 2232",
    "sg:postcode":"28208",
    "sg:province":"NC",
    "sg:tags":[
        "operator",
        "dry",
        "bulk",
        "local",
        "trucking"
    ],
    "wof:name":"Pope Transport Co",
    "wof:placetype":"venue"
},
  "geometry": {"coordinates":[-80.907302,35.281261],"type":"Point"}
}