{
  "type": "Feature",
  "properties": {
    "addr:full":"1508 Bizzell Grove Church Rd Selma NC 27576",
    "addr:housenumber":"1508",
    "addr:postcode":"27576",
    "addr:street":"Bizzell Grove Church Rd",
    "iso:country":"US",
    "sg:address":"1508 Bizzell Grove Church Rd",
    "sg:city":"Selma",
    "sg:classifiers":[
        {
            "category":"Bars & Pubs",
            "type":"Food & Drink"
        }
    ],
    "sg:phone":"+1 919 284 3957",
    "sg:postcode":"27576",
    "sg:province":"NC",
    "wof:name":"Bill's",
    "wof:placetype":"venue"
},
  "geometry": {"coordinates":[-78.179605,35.543197],"type":"Point"}
}