{
  "type": "Feature",
  "properties": {
    "addr:full":"1061 X Ray Dr Gastonia NC 28054",
    "addr:housenumber":"1061 x",
    "addr:postcode":"28054",
    "addr:street":"Ray Dr",
    "iso:country":"US",
    "sg:address":"1061 X Ray Dr",
    "sg:city":"Gastonia",
    "sg:classifiers":[
        {
            "category":"Health Services",
            "subcategory":"Doctor",
            "type":"Services"
        }
    ],
    "sg:phone":"+1   ",
    "sg:postcode":"28054",
    "sg:province":"NC",
    "sg:tags":[
        "medical"
    ],
    "wof:name":"W B Shannon MD",
    "wof:placetype":"venue"
},
  "geometry": {"coordinates":[-81.138504,35.275489],"type":"Point"}
}