{
  "type": "Feature",
  "properties": {
    "iso:country":"US",
    "sg:address":"2219 Garden Pl",
    "sg:city":"Raleigh",
    "sg:classifiers":[
        {
            "category":"Manufacturing",
            "subcategory":"Tools & Machinery",
            "type":"Manufacturing & Wholesale Goods"
        }
    ],
    "sg:phone":"+1 919 833 9084",
    "sg:postcode":"27607",
    "sg:province":"NC",
    "sg:tags":[
        "computer",
        "electronic",
        "mfg"
    ],
    "wof:name":"Custom",
    "wof:placetype":"venue"
},
  "geometry": {"coordinates":[-78.664776,35.788611],"type":"Point"}
}