{
  "type": "Feature",
  "properties": {
    "iso:country":"US",
    "sg:address":"308 Indian Trail Rd",
    "sg:city":"Indian Trail",
    "sg:classifiers":[
        {
            "category":"Real Estate",
            "subcategory":"Real Estate Agent",
            "type":"Services"
        }
    ],
    "sg:phone":"+1 704 882 6533",
    "sg:postcode":"28079",
    "sg:province":"NC",
    "wof:name":"Burdette Realty",
    "wof:placetype":"venue"
},
  "geometry": {"coordinates":[-80.665496,35.079552],"type":"Point"}
}