{
  "type": "Feature",
  "properties": {
    "addr:full":"6625 Falls of Neuse Rd Raleigh NC 27615",
    "addr:housenumber":"6625",
    "addr:postcode":"27615",
    "addr:street":"Falls Of Neuse Rd",
    "iso:country":"US",
    "sg:address":"6625 Falls of Neuse Rd",
    "sg:city":"Raleigh",
    "sg:classifiers":[
        {
            "category":"Professional",
            "subcategory":"Business Services",
            "type":"Services"
        }
    ],
    "sg:phone":"+1 919 846 2440",
    "sg:postcode":"27615",
    "sg:province":"NC",
    "sg:tags":[
        "interior",
        "consultant",
        "design",
        "decorator"
    ],
    "wof:name":"Today's Windows & Interiors",
    "wof:placetype":"venue"
},
  "geometry": {"coordinates":[-78.623085,35.874678],"type":"Point"}
}