{
  "type": "Feature",
  "properties": {
    "addr:full":"1801 Fairway Rd Asheboro NC 27205",
    "addr:housenumber":"1801",
    "addr:postcode":"27205",
    "addr:street":"Fairway Rd",
    "iso:country":"US",
    "sg:address":"1801 Fairway Rd",
    "sg:city":"Asheboro",
    "sg:classifiers":[
        {
            "category":"Professional",
            "subcategory":"Business Services",
            "type":"Services"
        }
    ],
    "sg:phone":"+1   ",
    "sg:postcode":"27205",
    "sg:province":"NC",
    "wof:name":"Ciervo Knitting Enterprises LL",
    "wof:placetype":"venue"
},
  "geometry": {"coordinates":[-79.823802,35.682748],"type":"Point"}
}