{
  "type": "Feature",
  "properties": {
    "iso:country":"US",
    "sg:address":"1003 S 17th St",
    "sg:city":"Wilmington",
    "sg:classifiers":[
        {
            "category":"Education",
            "subcategory":"Library",
            "type":"Public Place"
        }
    ],
    "sg:phone":"+1 910 343 2309",
    "sg:postcode":"28401",
    "sg:province":"NC",
    "sg:tags":[
        "special",
        "interest"
    ],
    "wof:name":"Wilmington Star-News Library",
    "wof:placetype":"venue"
},
  "geometry": {"coordinates":[-77.925968,34.223803],"type":"Point"}
}