{
  "type": "Feature",
  "properties": {
    "addr:full":"801 Mount Vernon Rd Raleigh NC 27607",
    "addr:housenumber":"801",
    "addr:postcode":"27607",
    "addr:street":"Mount Vernon Rd",
    "iso:country":"US",
    "sg:address":"801 Mount Vernon Rd",
    "sg:city":"Raleigh",
    "sg:classifiers":[
        {
            "category":"Home & Garden",
            "subcategory":"Building Materials",
            "type":"Retail Goods"
        }
    ],
    "sg:phone":"+1 919 851 8448",
    "sg:postcode":"27607",
    "sg:province":"NC",
    "sg:tags":[
        "door"
    ],
    "sg:website":"www.escdoors.com",
    "wof:name":"Engineering Specialties Co",
    "wof:placetype":"venue"
},
  "geometry": {"coordinates":[-78.720822,35.791328],"type":"Point"}
}