{
  "type": "Feature",
  "properties": {
    "iso:country":"US",
    "sg:address":"5201 Eagles Landing Dr",
    "sg:city":"Raleigh",
    "sg:classifiers":[
        {
            "category":"Wholesale",
            "subcategory":"Vending Machines",
            "type":"Manufacturing & Wholesale Goods"
        }
    ],
    "sg:phone":"+1 919 790 9569",
    "sg:postcode":"27616",
    "sg:province":"NC",
    "sg:tags":[
        "operator"
    ],
    "wof:name":"Customized Vending Service",
    "wof:placetype":"venue"
},
  "geometry": {"coordinates":[-78.55206099999999,35.848967],"type":"Point"}
}