{
  "type": "Feature",
  "properties": {
    "addr:full":"8437 Cunningham Rd Zebulon NC 27597",
    "addr:housenumber":"8437",
    "addr:postcode":"27597",
    "addr:street":"Cunningham Rd",
    "iso:country":"US",
    "sg:address":"8437 Cunningham Rd",
    "sg:city":"Zebulon",
    "sg:classifiers":[
        {
            "category":"Professional",
            "type":"Services"
        }
    ],
    "sg:phone":"+1 919 269 0067",
    "sg:postcode":"27597",
    "sg:province":"NC",
    "wof:name":"Dennis B & Linda S Branna",
    "wof:placetype":"venue"
},
  "geometry": {"coordinates":[-78.349744,35.850109],"type":"Point"}
}