{
  "type": "Feature",
  "properties": {
    "addr:full":"4913 Universal Dr Wake Forest NC 27587",
    "addr:housenumber":"4913",
    "addr:postcode":"27587",
    "addr:street":"Universal Dr",
    "iso:country":"US",
    "sg:address":"4913 Universal Dr",
    "sg:city":"Wake Forest",
    "sg:classifiers":[
        {
            "category":"Organizations",
            "subcategory":"Religious Organization",
            "type":"Services"
        }
    ],
    "sg:phone":"+1 919 217 0980",
    "sg:postcode":"27587",
    "sg:province":"NC",
    "sg:tags":[
        "church"
    ],
    "wof:name":"Universal Church-Pryr & Dlvrnc",
    "wof:placetype":"venue"
},
  "geometry": {"coordinates":[-78.481036,35.888263],"type":"Point"}
}