{
  "type": "Feature",
  "properties": {
    "addr:full":"1020 Cedar Creek Rd Fayetteville NC 28312",
    "addr:housenumber":"1020",
    "addr:postcode":"28312",
    "addr:street":"Cedar Creek Rd",
    "iso:country":"US",
    "sg:address":"1020 Cedar Creek Rd",
    "sg:city":"Fayetteville",
    "sg:classifiers":[
        {
            "category":"Retail",
            "subcategory":"Laundry & Dry Cleaning",
            "type":"Services"
        },
        {
            "category":"Building & Trades",
            "subcategory":"Construction",
            "type":"Services"
        }
    ],
    "sg:phone":"+1 910 484 1326",
    "sg:postcode":"28312",
    "sg:province":"NC",
    "sg:tags":[
        "fire",
        "cleaners",
        "rug",
        "damage",
        "restoration",
        "carpet"
    ],
    "wof:name":"Dowe S Cleaning & Restoration",
    "wof:placetype":"venue"
},
  "geometry": {"coordinates":[-78.84430399999999,35.030623],"type":"Point"}
}