{
  "type": "Feature",
  "properties": {
    "iso:country":"US",
    "sg:address":"5384 James B White Hwy S",
    "sg:city":"Whiteville",
    "sg:classifiers":[
        {
            "category":"Organizations",
            "subcategory":"Religious Organization",
            "type":"Services"
        }
    ],
    "sg:phone":"+1   ",
    "sg:postcode":"28472",
    "sg:province":"NC",
    "wof:name":"Abundant Life Assembly Of God",
    "wof:placetype":"venue"
},
  "geometry": {"coordinates":[-78.742194,34.272494],"type":"Point"}
}