{
  "type": "Feature",
  "properties": {
    "iso:country":"US",
    "sg:address":"821 Burke St NW",
    "sg:city":"Winston Salem",
    "sg:classifiers":[
        {
            "category":"Retail",
            "subcategory":"Repair Shop",
            "type":"Services"
        }
    ],
    "sg:phone":"+1   ",
    "sg:postcode":"27101",
    "sg:province":"NC",
    "wof:name":"Aqua Doc Waterscapes",
    "wof:placetype":"venue"
},
  "geometry": {"coordinates":[-80.256224,36.09653],"type":"Point"}
}