{
  "type": "Feature",
  "properties": {
    "addr:full":"1015 Forest Lake Dr Asheboro NC 27205",
    "addr:housenumber":"1015",
    "addr:postcode":"27205",
    "addr:street":"Forest Lake Dr",
    "iso:country":"US",
    "sg:address":"1015 Forest Lake Dr",
    "sg:city":"Asheboro",
    "sg:classifiers":[
        {
            "category":"Professional",
            "type":"Services"
        }
    ],
    "sg:phone":"+1 336 626 5045",
    "sg:postcode":"27205",
    "sg:province":"NC",
    "sg:tags":[
        "establishment"
    ],
    "wof:name":"Jewels",
    "wof:placetype":"venue"
},
  "geometry": {"coordinates":[-79.975414,35.759646],"type":"Point"}
}