{
  "type": "Feature",
  "properties": {
    "iso:country":"US",
    "sg:address":"1133 Atando Ave",
    "sg:city":"Charlotte",
    "sg:classifiers":[
        {
            "category":"Wholesale",
            "subcategory":"Wine & Distilled Alcoholic Beverages",
            "type":"Manufacturing & Wholesale Goods"
        }
    ],
    "sg:phone":"+1 704 332 2420",
    "sg:postcode":"28206",
    "sg:province":"NC",
    "sg:website":"www.mutualdistributing.com",
    "wof:name":"Mutual Distributing Co",
    "wof:placetype":"venue"
},
  "geometry": {"coordinates":[-80.822712,35.261538],"type":"Point"}
}