{
  "type": "Feature",
  "properties": {
    "iso:country":"US",
    "sg:address":"2206 Brandon Station Rd",
    "sg:city":"Pleasant Garden",
    "sg:classifiers":[
        {
            "category":"Building & Trades",
            "subcategory":"Construction",
            "type":"Services"
        }
    ],
    "sg:phone":"+1 336 674 3304",
    "sg:postcode":"27313",
    "sg:province":"NC",
    "sg:tags":[
        "house",
        "construct",
        "contractor"
    ],
    "wof:name":"Locklear Roofing Service Inc",
    "wof:placetype":"venue"
},
  "geometry": {"coordinates":[-79.746061,35.943642],"type":"Point"}
}