{
  "type": "Feature",
  "properties": {
    "addr:full":"98 Western Blvd Jacksonville NC 28546",
    "addr:housenumber":"98",
    "addr:postcode":"28546",
    "addr:street":"Western Blvd",
    "iso:country":"US",
    "sg:address":"98 Western Blvd",
    "sg:city":"Jacksonville",
    "sg:classifiers":[
        {
            "category":"Freight",
            "type":"Transportation"
        }
    ],
    "sg:phone":"+1 910 353 1303",
    "sg:postcode":"28546",
    "sg:province":"NC",
    "sg:tags":[
        "operator",
        "mover",
        "local",
        "trucking"
    ],
    "wof:name":"Merchant's Moving & Storage",
    "wof:placetype":"venue"
},
  "geometry": {"coordinates":[-77.378985,34.742875],"type":"Point"}
}