{
  "type": "Feature",
  "properties": {
    "iso:country":"US",
    "sg:address":"450 W Pennsylvania Ave",
    "sg:city":"Pinehurst",
    "sg:classifiers":[
        {
            "category":"Real Estate",
            "subcategory":"Real Estate Agent",
            "type":"Services"
        }
    ],
    "sg:phone":"+1 910 246 1500",
    "sg:postcode":"28387",
    "sg:province":"NC",
    "wof:name":"Re Essentials",
    "wof:placetype":"venue"
},
  "geometry": {"coordinates":[-79.395612,35.177618],"type":"Point"}
}