{
  "type": "Feature",
  "properties": {
    "iso:country":"US",
    "sg:address":"2617 US Hwy 301",
    "sg:city":"Wilson",
    "sg:classifiers":[
        {
            "category":"Travel",
            "subcategory":"Hotels & Motels",
            "type":"Entertainment"
        }
    ],
    "sg:phone":"+1 252 237 1178",
    "sg:postcode":"27893",
    "sg:province":"NC",
    "wof:name":"Deluxe Inn Of Wilson",
    "wof:placetype":"venue"
},
  "geometry": {"coordinates":[-77.937884,35.695901],"type":"Point"}
}