{
  "type": "Feature",
  "properties": {
    "iso:country":"US",
    "sg:address":"2533 Raeford Rd",
    "sg:city":"Fayetteville",
    "sg:classifiers":[
        {
            "category":"Banks & Credit Unions",
            "subcategory":"Investment Brokerage",
            "type":"Services"
        }
    ],
    "sg:phone":"+1 910 484 5006",
    "sg:postcode":"28305",
    "sg:province":"NC",
    "sg:tags":[
        "consultant",
        "planning",
        "financial"
    ],
    "wof:name":"Delta Financial Advisors Inc",
    "wof:placetype":"venue"
},
  "geometry": {"coordinates":[-78.918807,35.046073],"type":"Point"}
}