{
  "type": "Feature",
  "properties": {
    "addr:full":"280 Glade Ridge Rd Burgaw NC 28425",
    "addr:housenumber":"280",
    "addr:postcode":"28425",
    "addr:street":"Glade Ridge Rd",
    "iso:country":"US",
    "sg:address":"280 Glade Ridge Rd",
    "sg:city":"Burgaw",
    "sg:phone":"+1 910 259 2403",
    "sg:postcode":"28425",
    "sg:province":"NC",
    "sg:tags":[
        "farm",
        "corn"
    ],
    "wof:name":"Bettye Lanier",
    "wof:placetype":"venue"
},
  "geometry": {"coordinates":[-77.788183,34.6004],"type":"Point"}
}