{
  "type": "Feature",
  "properties": {
    "iso:country":"US",
    "sg:address":"500 N Main St",
    "sg:city":"Monroe",
    "sg:classifiers":[
        {
            "category":"Government",
            "subcategory":"Office",
            "type":"Public Place"
        }
    ],
    "sg:phone":"+1 704 283 3855",
    "sg:postcode":"28112",
    "sg:province":"NC",
    "wof:name":"Union County Veteran's Svc",
    "wof:placetype":"venue"
},
  "geometry": {"coordinates":[-80.550327,34.983612],"type":"Point"}
}