{
  "type": "Feature",
  "properties": {
    "iso:country":"US",
    "sg:address":"3562 Gillespie St",
    "sg:city":"Fayetteville",
    "sg:classifiers":[
        {
            "category":"Retail",
            "subcategory":"Auto Repair",
            "type":"Services"
        }
    ],
    "sg:phone":"+1 910 867 8303",
    "sg:postcode":"28306",
    "sg:province":"NC",
    "sg:tags":[
        "body",
        "automobile",
        "painting"
    ],
    "wof:name":"Simon's Paint & Body Shop",
    "wof:placetype":"venue"
},
  "geometry": {"coordinates":[-78.90724400000001,34.981858],"type":"Point"}
}