{
  "type": "Feature",
  "properties": {
    "addr:full":"2117 S Main St Wake Forest NC 27587",
    "addr:housenumber":"2117",
    "addr:postcode":"27587",
    "addr:street":"S Main St",
    "iso:country":"US",
    "sg:address":"2117 S Main St",
    "sg:city":"Wake Forest",
    "sg:classifiers":[
        {
            "category":"Autos & Motor Vehicles",
            "subcategory":"Auto Supplies",
            "type":"Retail Goods"
        }
    ],
    "sg:phone":"+1 919 562 5731",
    "sg:postcode":"27587",
    "sg:province":"NC",
    "sg:tags":[
        "automobile",
        "parts"
    ],
    "wof:name":"Advance Auto Parts Inc",
    "wof:placetype":"venue"
},
  "geometry": {"coordinates":[-78.53424,35.948141],"type":"Point"}
}