{
  "type": "Feature",
  "properties": {
    "addr:full":"1019 Shaw St Laurinburg NC 28352",
    "addr:housenumber":"1019",
    "addr:postcode":"28352",
    "addr:street":"Shaw St",
    "iso:country":"US",
    "sg:address":"1019 Shaw St",
    "sg:city":"Laurinburg",
    "sg:classifiers":[
        {
            "category":"Organizations",
            "subcategory":"Religious Organization",
            "type":"Services"
        }
    ],
    "sg:phone":"+1 910 276 9106",
    "sg:postcode":"28352",
    "sg:province":"NC",
    "wof:name":"Union Grove Baptist Church",
    "wof:placetype":"venue"
},
  "geometry": {"coordinates":[-79.443116,34.785578],"type":"Point"}
}