{
  "type": "Feature",
  "properties": {
    "addr:full":"529 N Bridge St Eden NC 27288",
    "addr:housenumber":"529",
    "addr:postcode":"27288",
    "addr:street":"N Bridge St",
    "iso:country":"US",
    "sg:address":"529 N Bridge St",
    "sg:city":"Eden",
    "sg:classifiers":[
        {
            "category":"Professional",
            "subcategory":"Art Services",
            "type":"Services"
        }
    ],
    "sg:phone":"+1   ",
    "sg:postcode":"27288",
    "sg:province":"NC",
    "sg:tags":[
        "commercial",
        "design"
    ],
    "wof:name":"Big Daddy Graphics",
    "wof:placetype":"venue"
},
  "geometry": {"coordinates":[-79.76633099999999,36.494762],"type":"Point"}
}