{
  "type": "Feature",
  "properties": {
    "addr:full":"2818 Old US Hwy 29 Pelham NC 27311",
    "addr:housenumber":"2818",
    "addr:postcode":"27311",
    "addr:street":"Old Us Hwy 29",
    "iso:country":"US",
    "sg:address":"2818 Old US Hwy 29",
    "sg:city":"Pelham",
    "sg:classifiers":[
        {
            "category":"Retail",
            "subcategory":"Auto Repair",
            "type":"Services"
        }
    ],
    "sg:phone":"+1 336 388 0484",
    "sg:postcode":"27311",
    "sg:province":"NC",
    "sg:tags":[
        "wrecker"
    ],
    "wof:name":"Mike's Towing & Recovery Inc",
    "wof:placetype":"venue"
},
  "geometry": {"coordinates":[-79.45485100000001,36.516466],"type":"Point"}
}