{
  "type": "Feature",
  "properties": {
    "addr:full":"2700 Lakebay Rd Vass NC 28394",
    "addr:housenumber":"2700",
    "addr:postcode":"28394",
    "addr:street":"Lakebay Rd",
    "iso:country":"US",
    "sg:address":"2700 Lakebay Rd",
    "sg:city":"Vass",
    "sg:classifiers":[
        {
            "category":"Farming",
            "subcategory":"Farm",
            "type":"Manufacturing & Wholesale Goods"
        }
    ],
    "sg:phone":"+1 910 245 2358",
    "sg:postcode":"28394",
    "sg:province":"NC",
    "sg:tags":[
        "crop",
        "general"
    ],
    "wof:name":"Knightsbridge Farm LLC",
    "wof:placetype":"venue"
},
  "geometry": {"coordinates":[-79.27556800000001,35.211033],"type":"Point"}
}