{
  "type": "Feature",
  "properties": {
    "iso:country":"US",
    "sg:address":"344 River Loop Rd",
    "sg:city":"Horse Shoe",
    "sg:classifiers":[
        {
            "category":"Wholesale",
            "subcategory":"Auto Parts",
            "type":"Manufacturing & Wholesale Goods"
        }
    ],
    "sg:phone":"+1 828 891 6425",
    "sg:postcode":"28759",
    "sg:province":"NC",
    "wof:name":"Bike Center Inc",
    "wof:placetype":"venue"
},
  "geometry": {"coordinates":[-79.334388,35.412526],"type":"Point"}
}