{
  "type": "Feature",
  "properties": {
    "addr:full":"101 W 14th St Greenville NC 27834",
    "addr:housenumber":"101",
    "addr:postcode":"27834",
    "addr:street":"W 14Th St",
    "iso:country":"US",
    "sg:address":"101 W 14th St",
    "sg:city":"Greenville",
    "sg:classifiers":[
        {
            "category":"Freight",
            "type":"Transportation"
        }
    ],
    "sg:phone":"+1 252 757 0373",
    "sg:postcode":"27834",
    "sg:province":"NC",
    "sg:tags":[
        "commercial",
        "storage"
    ],
    "wof:name":"Flowers & Taylor Warehousing",
    "wof:placetype":"venue"
},
  "geometry": {"coordinates":[-77.376486,35.601946],"type":"Point"}
}