{
  "type": "Feature",
  "properties": {
    "iso:country":"US",
    "sg:address":"133 Jefferson Church Rd",
    "sg:city":"King",
    "sg:classifiers":[
        {
            "category":"Retail",
            "subcategory":"Auto Repair",
            "type":"Services"
        }
    ],
    "sg:phone":"+1 336 983 8431",
    "sg:postcode":"27021",
    "sg:province":"NC",
    "sg:tags":[
        "body",
        "automobile",
        "painting"
    ],
    "wof:name":"Harris Body Shop",
    "wof:placetype":"venue"
},
  "geometry": {"coordinates":[-80.359888,36.26413],"type":"Point"}
}