{
  "type": "Feature",
  "properties": {
    "iso:country":"US",
    "sg:address":"505 Holly Ridge Dr",
    "sg:city":"Winston Salem",
    "sg:classifiers":[
        {
            "category":"Real Estate",
            "subcategory":"Real Estate Agent",
            "type":"Services"
        }
    ],
    "sg:phone":"+1 336 377 9805",
    "sg:postcode":"27105",
    "sg:province":"NC",
    "wof:name":"N & N Properties",
    "wof:placetype":"venue"
},
  "geometry": {"coordinates":[-80.26169400000001,36.197587],"type":"Point"}
}