{
  "type": "Feature",
  "properties": {
    "iso:country":"US",
    "sg:address":"221 Foxwood Trl",
    "sg:city":"New Bern",
    "sg:classifiers":[
        {
            "category":"Freight",
            "type":"Transportation"
        }
    ],
    "sg:phone":"+1 252 745 3338",
    "sg:postcode":"28560",
    "sg:province":"NC",
    "sg:tags":[
        "operator",
        "local",
        "trucking"
    ],
    "wof:name":"Jarvis Trucking",
    "wof:placetype":"venue"
},
  "geometry": {"coordinates":[-76.91692999999999,35.12369],"type":"Point"}
}