{
  "type": "Feature",
  "properties": {
    "addr:full":"605 Friendly Center Rd Greensboro NC 27408",
    "addr:housenumber":"605",
    "addr:postcode":"27408",
    "addr:street":"Friendly Center Rd",
    "iso:country":"US",
    "sg:address":"605 Friendly Center Rd",
    "sg:city":"Greensboro",
    "sg:classifiers":[
        {
            "category":"Shopping",
            "subcategory":"Clothing, Apparel, & Fashions",
            "type":"Retail Goods"
        }
    ],
    "sg:phone":"+1 336 854 2805",
    "sg:postcode":"27408",
    "sg:province":"NC",
    "wof:name":"Mi Mi Maternity",
    "wof:placetype":"venue"
},
  "geometry": {"coordinates":[-79.830758,36.084986],"type":"Point"}
}