{
  "type": "Feature",
  "properties": {
    "iso:country":"US",
    "sg:address":"2678 Antioch Rd",
    "sg:city":"Pikeville",
    "sg:classifiers":[
        {
            "category":"Farming",
            "subcategory":"Farm",
            "type":"Manufacturing & Wholesale Goods"
        }
    ],
    "sg:phone":"+1 919 739 0013",
    "sg:postcode":"27863",
    "sg:province":"NC",
    "wof:name":"Goldsboro Hog Farms Inc",
    "wof:placetype":"venue"
},
  "geometry": {"coordinates":[-77.90284699999999,35.500449],"type":"Point"}
}