{
  "type": "Feature",
  "properties": {
    "iso:country":"US",
    "sg:address":"102 Bonnie Ln",
    "sg:city":"Statesville",
    "sg:classifiers":[
        {
            "category":"Wholesale",
            "subcategory":"Machinery & Supplies",
            "type":"Manufacturing & Wholesale Goods"
        }
    ],
    "sg:phone":"+1 704 876 3987",
    "sg:postcode":"28625",
    "sg:province":"NC",
    "sg:tags":[
        "equipment",
        "industrial"
    ],
    "wof:name":"Sugino Corp",
    "wof:placetype":"venue"
},
  "geometry": {"coordinates":[-80.834935,35.840679],"type":"Point"}
}