{
  "type": "Feature",
  "properties": {
    "iso:country":"US",
    "sg:address":"7025 US Hwy 70",
    "sg:city":"Newport",
    "sg:classifiers":[
        {
            "category":"Shopping",
            "subcategory":"Music",
            "type":"Retail Goods"
        }
    ],
    "sg:phone":"+1 252 223 3294",
    "sg:postcode":"28570",
    "sg:province":"NC",
    "sg:tags":[
        "video",
        "disc",
        "tape",
        "cassette"
    ],
    "wof:name":"Newport Video",
    "wof:placetype":"venue"
},
  "geometry": {"coordinates":[-76.87626,34.789116],"type":"Point"}
}