{
  "type": "Feature",
  "properties": {
    "iso:country":"US",
    "sg:address":"218 Linwood Dr",
    "sg:city":"Jacksonville",
    "sg:classifiers":[
        {
            "category":"Home & Garden",
            "subcategory":"Building Materials",
            "type":"Retail Goods"
        }
    ],
    "sg:phone":"+1 910 346 1946",
    "sg:postcode":"28546",
    "sg:province":"NC",
    "sg:tags":[
        "door"
    ],
    "wof:name":"Stage Door Music Productions",
    "wof:placetype":"venue"
},
  "geometry": {"coordinates":[-77.42188299999999,34.793587],"type":"Point"}
}