{
  "type": "Feature",
  "properties": {
    "iso:country":"US",
    "sg:address":"500 Solano Dr",
    "sg:city":"Charlotte",
    "sg:classifiers":[
        {
            "category":"Real Estate",
            "subcategory":"Real Estate Operator",
            "type":"Services"
        }
    ],
    "sg:phone":"+1 704 503 0077",
    "sg:postcode":"28262",
    "sg:province":"NC",
    "sg:tags":[
        "apartment"
    ],
    "wof:name":"Berkeley Place Apartments",
    "wof:placetype":"venue"
},
  "geometry": {"coordinates":[-80.738705,35.326421],"type":"Point"}
}