{
  "type": "Feature",
  "properties": {
    "addr:full":"3475 Sandhill Ct Hudson NC 28638",
    "addr:housenumber":"3475",
    "addr:postcode":"28638",
    "addr:street":"Sandhill Ct",
    "iso:country":"US",
    "sg:address":"3475 Sandhill Ct",
    "sg:city":"Hudson",
    "sg:classifiers":[
        {
            "category":"Building & Trades",
            "subcategory":"Construction",
            "type":"Services"
        }
    ],
    "sg:phone":"+1 828 217 5341",
    "sg:postcode":"28638",
    "sg:province":"NC",
    "sg:tags":[
        "roofing",
        "contractor"
    ],
    "wof:name":"Champ Roofing",
    "wof:placetype":"venue"
},
  "geometry": {"coordinates":[-81.432948,35.83402],"type":"Point"}
}