{
  "type": "Feature",
  "properties": {
    "addr:full":"4617 Cardinal Grove Blvd Raleigh NC 27616",
    "addr:housenumber":"4617",
    "addr:postcode":"27616",
    "addr:street":"Cardinal Grove Blvd",
    "iso:country":"US",
    "sg:address":"4617 Cardinal Grove Blvd",
    "sg:city":"Raleigh",
    "sg:classifiers":[
        {
            "category":"Building & Trades",
            "subcategory":"Construction",
            "type":"Services"
        }
    ],
    "sg:phone":"+1 919 850 0598",
    "sg:postcode":"27616",
    "sg:province":"NC",
    "sg:tags":[
        "concrete",
        "contractor"
    ],
    "wof:name":"AK Concrete",
    "wof:placetype":"venue"
},
  "geometry": {"coordinates":[-78.547055,35.841549],"type":"Point"}
}