{
  "type": "Feature",
  "properties": {
    "addr:full":"4015 Baptist Camp Rd Connellys Springs NC 28612",
    "addr:housenumber":"4015",
    "addr:postcode":"28612",
    "addr:street":"Baptist Camp Rd Connellys Springs",
    "iso:country":"US",
    "sg:address":"4015 Baptist Camp Rd",
    "sg:city":"Connellys Springs",
    "sg:classifiers":[
        {
            "category":"Health Services",
            "subcategory":"Nursing And Care Facility",
            "type":"Services"
        }
    ],
    "sg:phone":"+1   ",
    "sg:postcode":"28612",
    "sg:province":"NC",
    "wof:name":"Baptist Camp Group Home",
    "wof:placetype":"venue"
},
  "geometry": {"coordinates":[-81.589606,35.616787],"type":"Point"}
}