{
  "type": "Feature",
  "properties": {
    "addr:full":"714 N Front St Warsaw NC 28398",
    "addr:housenumber":"714",
    "addr:postcode":"28398",
    "addr:street":"N Front St",
    "iso:country":"US",
    "sg:address":"714 N Front St",
    "sg:city":"Warsaw",
    "sg:classifiers":[
        {
            "category":"Building & Trades",
            "subcategory":"Plumbing",
            "type":"Services"
        }
    ],
    "sg:phone":"+1 910 293 4658",
    "sg:postcode":"28398",
    "sg:province":"NC",
    "sg:tags":[
        "plumbing",
        "contractor"
    ],
    "wof:name":"Blackburn Plumbing Servic",
    "wof:placetype":"venue"
},
  "geometry": {"coordinates":[-78.096144,35.006021],"type":"Point"}
}