{
  "type": "Feature",
  "properties": {
    "iso:country":"US",
    "sg:address":"575 Mocksville Hwy",
    "sg:city":"Statesville",
    "sg:classifiers":[
        {
            "category":"Retail",
            "subcategory":"Auto Repair",
            "type":"Services"
        }
    ],
    "sg:phone":"+1 704 871 1464",
    "sg:postcode":"28625",
    "sg:province":"NC",
    "sg:tags":[
        "body",
        "automobile",
        "painting"
    ],
    "wof:name":"Mc Williams Collision Ctr",
    "wof:placetype":"venue"
},
  "geometry": {"coordinates":[-80.809831,35.807878],"type":"Point"}
}