{
  "type": "Feature",
  "properties": {
    "addr:full":"1627 Pamela Lorraine Dr Charlotte NC 28213",
    "addr:housenumber":"1627",
    "addr:postcode":"28213",
    "addr:street":"Pamela Lorraine Dr",
    "iso:country":"US",
    "sg:address":"1627 Pamela Lorraine Dr",
    "sg:city":"Charlotte",
    "sg:classifiers":[
        {
            "category":"Professional",
            "subcategory":"Business Services",
            "type":"Services"
        }
    ],
    "sg:phone":"+1 704 549 4334",
    "sg:postcode":"28213",
    "sg:province":"NC",
    "sg:tags":[
        "information",
        "referral"
    ],
    "wof:name":"We-Search Information Retrievl",
    "wof:placetype":"venue"
},
  "geometry": {"coordinates":[-80.72545100000001,35.294096],"type":"Point"}
}