{
  "type": "Feature",
  "properties": {
    "addr:full":"10742 Alexander Mill Dr Charlotte NC 28277",
    "addr:housenumber":"10742",
    "addr:postcode":"28277",
    "addr:street":"Alexander Mill Dr",
    "iso:country":"US",
    "sg:address":"10742 Alexander Mill Dr",
    "sg:city":"Charlotte",
    "sg:classifiers":[
        {
            "category":"Health Services",
            "subcategory":"Clinic",
            "type":"Services"
        }
    ],
    "sg:phone":"+1   ",
    "sg:postcode":"28277",
    "sg:province":"NC",
    "wof:name":"Heart Foundation Health Educa",
    "wof:placetype":"venue"
},
  "geometry": {"coordinates":[-80.84066900000001,35.045305],"type":"Point"}
}