{
  "type": "Feature",
  "properties": {
    "iso:country":"US",
    "sg:address":"3001 Cove Rd",
    "sg:city":"Union Mills",
    "sg:classifiers":[
        {
            "category":"Retail",
            "subcategory":"Auto Repair",
            "type":"Services"
        }
    ],
    "sg:phone":"+1 828 288 0439",
    "sg:postcode":"28167",
    "sg:province":"NC",
    "sg:tags":[
        "glass",
        "coating",
        "tinting"
    ],
    "wof:name":"Tint Shack",
    "wof:placetype":"venue"
},
  "geometry": {"coordinates":[-82.070543,35.481212],"type":"Point"}
}