{
  "type": "Feature",
  "properties": {
    "addr:full":"4638 Quail Canyon Dr Charlotte NC 28226",
    "addr:housenumber":"4638",
    "addr:postcode":"28226",
    "addr:street":"Quail Canyon Dr",
    "iso:country":"US",
    "sg:address":"4638 Quail Canyon Dr",
    "sg:city":"Charlotte",
    "sg:classifiers":[
        {
            "category":"Professional",
            "subcategory":"Business Services",
            "type":"Services"
        }
    ],
    "sg:phone":"+1   ",
    "sg:postcode":"28226",
    "sg:province":"NC",
    "wof:name":"Leisure Sales Ltd",
    "wof:placetype":"venue"
},
  "geometry": {"coordinates":[-80.827895,35.108791],"type":"Point"}
}