{
  "type": "Feature",
  "properties": {
    "addr:full":"3410 Old Mocksville Rd Salisbury NC 28144",
    "addr:housenumber":"3410",
    "addr:postcode":"28144",
    "addr:street":"Old Mocksville Rd",
    "iso:country":"US",
    "sg:address":"3410 Old Mocksville Rd",
    "sg:city":"Salisbury",
    "sg:classifiers":[
        {
            "category":"Education",
            "subcategory":"Dance Studio",
            "type":"Public Place"
        }
    ],
    "sg:phone":"+1   ",
    "sg:postcode":"28144",
    "sg:province":"NC",
    "wof:name":"Toni Hudson Dance Company Inc",
    "wof:placetype":"venue"
},
  "geometry": {"coordinates":[-80.465344,35.725277],"type":"Point"}
}