{
  "type": "Feature",
  "properties": {
    "addr:full":"2095 Stantonsburg Rd Greenville NC 27834",
    "addr:housenumber":"2095",
    "addr:postcode":"27834",
    "addr:street":"Stantonsburg Rd",
    "iso:country":"US",
    "sg:address":"2095 Stantonsburg Rd",
    "sg:city":"Greenville",
    "sg:classifiers":[
        {
            "category":"Travel",
            "subcategory":"Hotels & Motels",
            "type":"Entertainment"
        }
    ],
    "sg:phone":"+1 252 752 2122",
    "sg:postcode":"27834",
    "sg:province":"NC",
    "sg:tags":[
        "operation",
        "lodging"
    ],
    "wof:name":"East Carolina Inn",
    "wof:placetype":"venue"
},
  "geometry": {"coordinates":[-77.400796,35.605822],"type":"Point"}
}