{
  "type": "Feature",
  "properties": {
    "iso:country":"US",
    "sg:address":"103 E Main St",
    "sg:city":"Aulander",
    "sg:classifiers":[
        {
            "category":"Retail",
            "subcategory":"Repair Shop",
            "type":"Services"
        }
    ],
    "sg:phone":"+1   ",
    "sg:postcode":"27805",
    "sg:province":"NC",
    "wof:name":"Roys TV",
    "wof:placetype":"venue"
},
  "geometry": {"coordinates":[-77.113173,36.230044],"type":"Point"}
}