{
  "type": "Feature",
  "properties": {
    "iso:country":"US",
    "sg:address":"728 Queens Rd",
    "sg:city":"Charlotte",
    "sg:classifiers":[
        {
            "category":"Shopping",
            "subcategory":"Used Merchandise",
            "type":"Retail Goods"
        }
    ],
    "sg:phone":"+1 704 332 5577",
    "sg:postcode":"28207",
    "sg:province":"NC",
    "wof:name":"Antiques Abroad LTD",
    "wof:placetype":"venue"
},
  "geometry": {"coordinates":[-80.83024,35.205714],"type":"Point"}
}