{
  "type": "Feature",
  "properties": {
    "addr:full":"4019 Sentry Post Rd Charlotte NC 28208",
    "addr:housenumber":"4019",
    "addr:postcode":"28208",
    "addr:street":"Sentry Post Rd",
    "iso:country":"US",
    "sg:address":"4019 Sentry Post Rd",
    "sg:city":"Charlotte",
    "sg:classifiers":[
        {
            "category":"Building & Trades",
            "subcategory":"Construction",
            "type":"Services"
        }
    ],
    "sg:phone":"+1 704 393 3242",
    "sg:postcode":"28208",
    "sg:province":"NC",
    "sg:tags":[
        "warehouse"
    ],
    "wof:name":"Charlotte Bonded Warehouse",
    "wof:placetype":"venue"
},
  "geometry": {"coordinates":[-80.93127,35.203263],"type":"Point"}
}