{
  "type": "Feature",
  "properties": {
    "iso:country":"US",
    "sg:address":"9831 Brookford St",
    "sg:city":"Charlotte",
    "sg:classifiers":[
        {
            "category":"Mining & Drilling",
            "type":"Manufacturing & Wholesale Goods"
        },
        {
            "category":"Building & Trades",
            "subcategory":"Equipment Rental",
            "type":"Services"
        }
    ],
    "sg:phone":"+1 704 504 3600",
    "sg:postcode":"28273",
    "sg:province":"NC",
    "sg:tags":[
        "gravel",
        "sand",
        "handling",
        "supply"
    ],
    "sg:website":"http://www.mdmoody-intl.com",
    "wof:name":"Md Woody And Sons Machinery",
    "wof:placetype":"venue"
},
  "geometry": {"coordinates":[-80.937533,35.123524],"type":"Point"}
}