{
  "type": "Feature",
  "properties": {
    "addr:full":"737 Chatuge Village Cir Hayesville NC 28904",
    "addr:housenumber":"737",
    "addr:postcode":"28904",
    "addr:street":"Chatuge Village Cir",
    "iso:country":"US",
    "sg:address":"737 Chatuge Village Cir",
    "sg:city":"Hayesville",
    "sg:classifiers":[
        {
            "category":"Manufacturing",
            "subcategory":"Lumber",
            "type":"Manufacturing & Wholesale Goods"
        }
    ],
    "sg:phone":"+1 828 389 9437",
    "sg:postcode":"28904",
    "sg:province":"NC",
    "sg:tags":[
        "mill"
    ],
    "wof:name":"Lean On ME Walking Sticks",
    "wof:placetype":"venue"
},
  "geometry": {"coordinates":[-83.746787,35.033988],"type":"Point"}
}