{
  "type": "Feature",
  "properties": {
    "iso:country":"US",
    "sg:address":"1904 S Wilmington St",
    "sg:city":"Raleigh",
    "sg:classifiers":[
        {
            "category":"Food & Beverages",
            "subcategory":"Groceries & Convenience Stores",
            "type":"Retail Goods"
        }
    ],
    "sg:phone":"+1 919 856 9343",
    "sg:postcode":"27603",
    "sg:province":"NC",
    "wof:name":"Quick Shop Mart",
    "wof:placetype":"venue"
},
  "geometry": {"coordinates":[-78.640496,35.756816],"type":"Point"}
}