{
  "type": "Feature",
  "properties": {
    "iso:country":"US",
    "sg:address":"127 Porter Cross Rd",
    "sg:city":"Harkers Island",
    "sg:classifiers":[
        {
            "category":"Organizations",
            "subcategory":"Religious Organization",
            "type":"Services"
        }
    ],
    "sg:phone":"+1   ",
    "sg:postcode":"28531",
    "sg:province":"NC",
    "wof:name":"Grace Holiness Parsonage",
    "wof:placetype":"venue"
},
  "geometry": {"coordinates":[-76.53793899999999,34.693684],"type":"Point"}
}