{
  "type": "Feature",
  "properties": {
    "addr:full":"162 Cherry Tree Ln Stanfield NC 28163",
    "addr:housenumber":"162",
    "addr:postcode":"28163",
    "addr:street":"Cherry Tree Ln",
    "iso:country":"US",
    "sg:address":"162 Cherry Tree Ln",
    "sg:city":"Stanfield",
    "sg:classifiers":[
        {
            "category":"Building & Trades",
            "subcategory":"Construction",
            "type":"Services"
        }
    ],
    "sg:phone":"+1 704 888 3756",
    "sg:postcode":"28163",
    "sg:province":"NC",
    "sg:tags":[
        "carpentry",
        "contractor"
    ],
    "wof:name":"Dana S Hatley",
    "wof:placetype":"venue"
},
  "geometry": {"coordinates":[-80.41602399999999,35.233209],"type":"Point"}
}