{
  "type": "Feature",
  "properties": {
    "addr:full":"700 Saint Marys St Raleigh NC 27605",
    "addr:housenumber":"700",
    "addr:postcode":"27605",
    "addr:street":"Saint Marys St",
    "iso:country":"US",
    "sg:address":"700 Saint Marys St",
    "sg:city":"Raleigh",
    "sg:classifiers":[
        {
            "category":"Shopping",
            "subcategory":"Florist",
            "type":"Retail Goods"
        }
    ],
    "sg:phone":"+1 919 836 8121",
    "sg:postcode":"27605",
    "sg:province":"NC",
    "sg:website":"www.fallonsflowers.com",
    "wof:name":"Fallons Creative Flowers",
    "wof:placetype":"venue"
},
  "geometry": {"coordinates":[-78.65166000000001,35.791106],"type":"Point"}
}