{
  "type": "Feature",
  "properties": {
    "addr:full":"4918 Reedy Branch Rd Winterville NC 28590",
    "addr:housenumber":"4918",
    "addr:postcode":"28590",
    "addr:street":"Reedy Branch Rd",
    "iso:country":"US",
    "sg:address":"4918 Reedy Branch Rd",
    "sg:city":"Winterville",
    "sg:classifiers":[
        {
            "category":"Home & Garden",
            "subcategory":"Building Materials",
            "type":"Retail Goods"
        }
    ],
    "sg:phone":"+1 252 756 1317",
    "sg:postcode":"28590",
    "sg:province":"NC",
    "sg:tags":[
        "windows"
    ],
    "wof:name":"Southeastern Exteriors",
    "wof:placetype":"venue"
},
  "geometry": {"coordinates":[-77.41679499999999,35.529463],"type":"Point"}
}