{
  "type": "Feature",
  "properties": {
    "addr:full":"7428 W Nc 10 Hwy Vale NC 28168",
    "addr:housenumber":"7428",
    "addr:postcode":"28168",
    "addr:street":"W Nc 10 Hwy",
    "iso:country":"US",
    "sg:address":"7428 W Nc 10 Hwy",
    "sg:city":"Vale",
    "sg:classifiers":[
        {
            "category":"Shopping",
            "subcategory":"Used Merchandise",
            "type":"Retail Goods"
        },
        {
            "category":"Shopping",
            "subcategory":"Books",
            "type":"Retail Goods"
        }
    ],
    "sg:phone":"+1 704 462 4800",
    "sg:postcode":"28168",
    "sg:province":"NC",
    "sg:tags":[
        "rare",
        "dealer"
    ],
    "wof:name":"Preowned Books and Videos Etc",
    "wof:placetype":"venue"
},
  "geometry": {"coordinates":[-81.42643700000001,35.583365],"type":"Point"}
}