{
  "type": "Feature",
  "properties": {
    "addr:full":"165 Azalea Lake Dr Salisbury NC 28146",
    "addr:housenumber":"165",
    "addr:postcode":"28146",
    "addr:street":"Azalea Lake Dr",
    "iso:country":"US",
    "sg:address":"165 Azalea Lake Dr",
    "sg:city":"Salisbury",
    "sg:classifiers":[
        {
            "category":"Professional",
            "subcategory":"Computer Services",
            "type":"Services"
        }
    ],
    "sg:phone":"+1 704 202 8390",
    "sg:postcode":"28146",
    "sg:province":"NC",
    "sg:tags":[
        "development",
        "software"
    ],
    "wof:name":"Precedence International Inc",
    "wof:placetype":"venue"
},
  "geometry": {"coordinates":[-80.376914,35.575255],"type":"Point"}
}