{
  "type": "Feature",
  "properties": {
    "iso:country":"US",
    "sg:address":"1890 Spartanburg Hwy",
    "sg:city":"Hendersonville",
    "sg:classifiers":[
        {
            "category":"Retail",
            "subcategory":"Auto Repair",
            "type":"Services"
        }
    ],
    "sg:phone":"+1 828 693 3129",
    "sg:postcode":"28792",
    "sg:province":"NC",
    "sg:tags":[
        "exhaust",
        "automotive",
        "re",
        "general"
    ],
    "wof:name":"Jims Towing Service",
    "wof:placetype":"venue"
},
  "geometry": {"coordinates":[-82.43226300000001,35.294503],"type":"Point"}
}