{
  "type": "Feature",
  "properties": {
    "addr:full":"1200 W Sportsman Dr Kill Devil Hills NC 27948",
    "addr:housenumber":"1200",
    "addr:postcode":"27948",
    "addr:street":"W Sportsman Dr",
    "iso:country":"US",
    "sg:address":"1200 W Sportsman Dr",
    "sg:city":"Kill Devil Hills",
    "sg:classifiers":[
        {
            "category":"Building & Trades",
            "subcategory":"Construction",
            "type":"Services"
        }
    ],
    "sg:phone":"+1 252 207 1491",
    "sg:postcode":"27948",
    "sg:province":"NC",
    "sg:tags":[
        "resurfacing",
        "laying",
        "refinishing",
        "floor"
    ],
    "wof:name":"Advantage Home Repairs & Mntnc",
    "wof:placetype":"venue"
},
  "geometry": {"coordinates":[-75.687017,36.038836],"type":"Point"}
}