{
  "type": "Feature",
  "properties": {
    "iso:country":"US",
    "sg:address":"1501 N Charlotte Ave",
    "sg:city":"Monroe",
    "sg:classifiers":[
        {
            "category":"Banks & Credit Unions",
            "subcategory":"Investment Brokerage",
            "type":"Services"
        }
    ],
    "sg:phone":"+1 704 282 8328",
    "sg:postcode":"28110",
    "sg:province":"NC",
    "sg:tags":[
        "security"
    ],
    "wof:name":"Bruce Walters Financial",
    "wof:placetype":"venue"
},
  "geometry": {"coordinates":[-80.561055,34.99639],"type":"Point"}
}