{
  "type": "Feature",
  "properties": {
    "iso:country":"US",
    "sg:address":"105 Duncan Hill Rd",
    "sg:city":"Hendersonville",
    "sg:classifiers":[
        {
            "category":"Restaurant",
            "type":"Food & Drink"
        }
    ],
    "sg:phone":"+1 828 685 8581",
    "sg:postcode":"28792",
    "sg:province":"NC",
    "sg:tags":[
        "eating"
    ],
    "wof:name":"Giovannis Italian Cafe",
    "wof:placetype":"venue"
},
  "geometry": {"coordinates":[-82.450682,35.332003],"type":"Point"}
}