{
  "type": "Feature",
  "properties": {
    "addr:full":"1606 Morganton Rd Fayetteville NC 28305",
    "addr:housenumber":"1606",
    "addr:postcode":"28305",
    "addr:street":"Morganton Rd",
    "iso:country":"US",
    "sg:address":"1606 Morganton Rd",
    "sg:city":"Fayetteville",
    "sg:classifiers":[
        {
            "category":"Health Services",
            "subcategory":"Doctor",
            "type":"Services"
        }
    ],
    "sg:phone":"+1 910 484 3121",
    "sg:postcode":"28305",
    "sg:province":"NC",
    "sg:tags":[
        "physician",
        "surgeon"
    ],
    "wof:name":"Fayetteville Children's Clinic",
    "wof:placetype":"venue"
},
  "geometry": {"coordinates":[-78.90764,35.058922],"type":"Point"}
}