{
  "type": "Feature",
  "properties": {
    "addr:full":"123 Pocosin Rd Windsor NC 27983",
    "addr:housenumber":"123",
    "addr:postcode":"27983",
    "addr:street":"Pocosin Rd",
    "iso:country":"US",
    "sg:address":"123 Pocosin Rd",
    "sg:city":"Windsor",
    "sg:classifiers":[
        {
            "category":"Retail",
            "subcategory":"Auto Repair",
            "type":"Services"
        }
    ],
    "sg:phone":"+1   ",
    "sg:postcode":"27983",
    "sg:province":"NC",
    "sg:tags":[
        "general"
    ],
    "wof:name":"Dexters Diesel Shop",
    "wof:placetype":"venue"
},
  "geometry": {"coordinates":[-76.948778,36.088161],"type":"Point"}
}