{
  "type": "Feature",
  "properties": {
    "addr:full":"5501 Commercial Ave Raleigh NC 27612",
    "addr:housenumber":"5501",
    "addr:postcode":"27612",
    "addr:street":"Commercial Ave",
    "iso:country":"US",
    "sg:address":"5501 Commercial Ave",
    "sg:city":"Raleigh",
    "sg:classifiers":[
        {
            "category":"Bars & Pubs",
            "subcategory":"Nightclub",
            "type":"Food & Drink"
        },
        {
            "category":"Sports & Exercise",
            "subcategory":"Bowling",
            "type":"Entertainment"
        }
    ],
    "sg:phone":"+1 919 783 0080",
    "sg:postcode":"27612",
    "sg:province":"NC",
    "sg:tags":[
        "nightlife"
    ],
    "sg:website":"www.amf.com/pleasantvalleylanes/",
    "wof:name":"AMF Pleasant Valley Lines",
    "wof:placetype":"venue"
},
  "geometry": {"coordinates":[-78.708603,35.857101],"type":"Point"}
}