{
  "type": "Feature",
  "properties": {
    "addr:full":"418 Becker Dr Roanoke Rapids NC 27870",
    "addr:housenumber":"418",
    "addr:postcode":"27870",
    "addr:street":"Becker Dr",
    "iso:country":"US",
    "sg:address":"418 Becker Dr",
    "sg:city":"Roanoke Rapids",
    "sg:classifiers":[
        {
            "category":"Professional",
            "subcategory":"Computer Services",
            "type":"Services"
        }
    ],
    "sg:phone":"+1 252 535 0937",
    "sg:postcode":"27870",
    "sg:province":"NC",
    "sg:tags":[
        "repair"
    ],
    "sg:website":"www.elliottscomputers.com",
    "wof:name":"Elliott's Computer Corner",
    "wof:placetype":"venue"
},
  "geometry": {"coordinates":[-77.63657499999999,36.440674],"type":"Point"}
}