{
  "type": "Feature",
  "properties": {
    "addr:full":"4025 Trevor Cir Durham NC 27705",
    "addr:housenumber":"4025",
    "addr:postcode":"27705",
    "addr:street":"Trevor Cir",
    "iso:country":"US",
    "sg:address":"4025 Trevor Cir",
    "sg:city":"Durham",
    "sg:classifiers":[
        {
            "category":"Building & Trades",
            "subcategory":"Cleaning & Sanitation",
            "type":"Services"
        }
    ],
    "sg:phone":"+1   ",
    "sg:postcode":"27705",
    "sg:province":"NC",
    "sg:tags":[
        "maintenance"
    ],
    "wof:name":"J&R Home Maintenance",
    "wof:placetype":"venue"
},
  "geometry": {"coordinates":[-78.929456,36.066364],"type":"Point"}
}