{
  "type": "Feature",
  "properties": {
    "addr:full":"808 Tuckaseegee Rd Charlotte NC 28208",
    "addr:housenumber":"808",
    "addr:postcode":"28208",
    "addr:street":"Tuckaseegee Rd",
    "iso:country":"US",
    "sg:address":"808 Tuckaseegee Rd",
    "sg:city":"Charlotte",
    "sg:classifiers":[
        {
            "category":"Freight",
            "type":"Transportation"
        }
    ],
    "sg:phone":"+1 704 334 5051",
    "sg:postcode":"28208",
    "sg:province":"NC",
    "sg:tags":[
        "operator",
        "local",
        "hauling",
        "trucking"
    ],
    "wof:name":"Charlotte Trucking Solutions L",
    "wof:placetype":"venue"
},
  "geometry": {"coordinates":[-80.869185,35.236729],"type":"Point"}
}