{
  "type": "Feature",
  "properties": {
    "addr:full":"105 E 3rd St Washington NC 27889",
    "addr:housenumber":"105",
    "addr:postcode":"27889",
    "addr:street":"E 3Rd St",
    "iso:country":"US",
    "sg:address":"105 E 3rd St",
    "sg:city":"Washington",
    "sg:classifiers":[
        {
            "category":"Health Services",
            "subcategory":"Health Practitioner",
            "type":"Services"
        }
    ],
    "sg:phone":"+1 252 975 2027",
    "sg:postcode":"27889",
    "sg:province":"NC",
    "sg:tags":[
        "psychotherapist"
    ],
    "wof:name":"Pamlico Counseling Ctr",
    "wof:placetype":"venue"
},
  "geometry": {"coordinates":[-77.053499,35.544283],"type":"Point"}
}