{
  "type": "Feature",
  "properties": {
    "addr:full":"1449 Smokey Park Hwy Candler NC 28715",
    "addr:housenumber":"1449",
    "addr:postcode":"28715",
    "addr:street":"Smokey Park Hwy",
    "iso:country":"US",
    "sg:address":"1449 Smokey Park Hwy",
    "sg:city":"Candler",
    "sg:classifiers":[
        {
            "category":"Building & Trades",
            "subcategory":"Construction",
            "type":"Services"
        }
    ],
    "sg:phone":"+1 828 667 2305",
    "sg:postcode":"28715",
    "sg:province":"NC",
    "sg:tags":[
        "dry wall",
        "contractor"
    ],
    "wof:name":"Blue Ridge Dry Wall Co",
    "wof:placetype":"venue"
},
  "geometry": {"coordinates":[-82.679507,35.545086],"type":"Point"}
}