{
  "type": "Feature",
  "properties": {
    "iso:country":"US",
    "sg:address":"1407 Baker Rd",
    "sg:city":"Raleigh",
    "sg:classifiers":[
        {
            "category":"Building & Trades",
            "subcategory":"Construction",
            "type":"Services"
        }
    ],
    "sg:phone":"+1 919 233 0521",
    "sg:postcode":"27607",
    "sg:province":"NC",
    "sg:tags":[
        "house"
    ],
    "wof:name":"Craft Construction",
    "wof:placetype":"venue"
},
  "geometry": {"coordinates":[-78.756624,35.801034],"type":"Point"}
}