{
  "type": "Feature",
  "properties": {
    "addr:full":"2505 Richardson Dr Reidsville NC 27320",
    "addr:housenumber":"2505",
    "addr:postcode":"27320",
    "addr:street":"Richardson Dr",
    "iso:country":"US",
    "sg:address":"2505 Richardson Dr",
    "sg:city":"Reidsville",
    "sg:classifiers":[
        {
            "category":"Food & Beverages",
            "subcategory":"Groceries & Convenience Stores",
            "type":"Retail Goods"
        }
    ],
    "sg:phone":"+1 336 349 3801",
    "sg:postcode":"27320",
    "sg:province":"NC",
    "wof:name":"Hemco",
    "wof:placetype":"venue"
},
  "geometry": {"coordinates":[-79.691166,36.334306],"type":"Point"}
}