{
  "type": "Feature",
  "properties": {
    "iso:country":"US",
    "sg:address":"104 Fairway Shopping Center",
    "sg:city":"Hudson",
    "sg:classifiers":[
        {
            "category":"Professional",
            "subcategory":"Accounting & Tax Preparation",
            "type":"Services"
        }
    ],
    "sg:phone":"+1 828 726 1666",
    "sg:postcode":"28638",
    "sg:province":"NC",
    "sg:tags":[
        "return",
        "filing"
    ],
    "sg:website":"www.jacksonhewitt.com",
    "wof:name":"Jackson Hewitt Tax Svc",
    "wof:placetype":"venue"
},
  "geometry": {"coordinates":[-81.495769,35.848492],"type":"Point"}
}