{
  "type": "Feature",
  "properties": {
    "iso:country":"US",
    "sg:address":"308 W Palmer St",
    "sg:city":"Charlotte",
    "sg:classifiers":[
        {
            "category":"Manufacturing",
            "subcategory":"Tools & Machinery",
            "type":"Manufacturing & Wholesale Goods"
        }
    ],
    "sg:phone":"+1 704 333 2987",
    "sg:postcode":"28203",
    "sg:province":"NC",
    "sg:tags":[
        "machine",
        "shop"
    ],
    "wof:name":"Electrical Apparatus Co",
    "wof:placetype":"venue"
},
  "geometry": {"coordinates":[-80.856121,35.222021],"type":"Point"}
}