{
  "type": "Feature",
  "properties": {
    "addr:full":"514 S Eastern Blvd Fayetteville NC 28301",
    "addr:housenumber":"514",
    "addr:postcode":"28301",
    "addr:street":"S Eastern Blvd",
    "iso:country":"US",
    "sg:address":"514 S Eastern Blvd",
    "sg:city":"Fayetteville",
    "sg:classifiers":[
        {
            "category":"Retail",
            "subcategory":"Repair Shop",
            "type":"Services"
        }
    ],
    "sg:phone":"+1 910 323 2295",
    "sg:postcode":"28301",
    "sg:province":"NC",
    "sg:website":"www.chromerite.com",
    "wof:name":"Chrome-Rite Plating Inc",
    "wof:placetype":"venue"
},
  "geometry": {"coordinates":[-78.866607,35.039606],"type":"Point"}
}