{
  "type": "Feature",
  "properties": {
    "iso:country":"US",
    "sg:address":"407 S Griffin St",
    "sg:city":"Elizabeth City",
    "sg:classifiers":[
        {
            "category":"Professional",
            "subcategory":"Lawyer & Legal Services",
            "type":"Services"
        },
        {
            "category":"Professional",
            "subcategory":"Accounting & Tax Preparation",
            "type":"Services"
        }
    ],
    "sg:phone":"+1 252 335 9298",
    "sg:postcode":"27909",
    "sg:province":"NC",
    "sg:tags":[
        "accountant"
    ],
    "wof:name":"Bailey King & Associates",
    "wof:placetype":"venue"
},
  "geometry": {"coordinates":[-76.234375,36.296589],"type":"Point"}
}