{
  "type": "Feature",
  "properties": {
    "addr:full":"3485 Amity Hill Rd Cleveland NC 27013",
    "addr:housenumber":"3485",
    "addr:postcode":"27013",
    "addr:street":"Amity Hill Rd",
    "iso:country":"US",
    "sg:address":"3485 Amity Hill Rd",
    "sg:city":"Cleveland",
    "sg:phone":"+1 704 278 2660",
    "sg:postcode":"27013",
    "sg:province":"NC",
    "sg:tags":[
        "farm",
        "corn",
        "wheat",
        "soybean"
    ],
    "wof:name":"KNOX Grain Farms",
    "wof:placetype":"venue"
},
  "geometry": {"coordinates":[-80.743532,35.710611],"type":"Point"}
}