{
  "type": "Feature",
  "properties": {
    "addr:full":"217 Atwell Ave Greensboro NC 27406",
    "addr:housenumber":"217",
    "addr:postcode":"27406",
    "addr:street":"Atwell Ave",
    "iso:country":"US",
    "sg:address":"217 Atwell Ave",
    "sg:city":"Greensboro",
    "sg:classifiers":[
        {
            "category":"Retail",
            "subcategory":"Auto Rental",
            "type":"Services"
        }
    ],
    "sg:phone":"+1 336 373 1822",
    "sg:postcode":"27406",
    "sg:province":"NC",
    "sg:tags":[
        "equipment",
        "r",
        "truck",
        "trailer",
        "utility"
    ],
    "wof:name":"Ryder",
    "wof:placetype":"venue"
},
  "geometry": {"coordinates":[-79.786905,36.030463],"type":"Point"}
}