{
  "type": "Feature",
  "properties": {
    "addr:full":"1418 Cessna Ln Conover NC 28613",
    "addr:housenumber":"1418",
    "addr:postcode":"28613",
    "addr:street":"Cessna Ln",
    "iso:country":"US",
    "sg:address":"1418 Cessna Ln",
    "sg:city":"Conover",
    "sg:classifiers":[
        {
            "category":"Taxi",
            "type":"Transportation"
        }
    ],
    "sg:phone":"+1 828 465 0988",
    "sg:postcode":"28613",
    "sg:province":"NC",
    "sg:tags":[
        "taxicab"
    ],
    "wof:name":"Half Price Taxi",
    "wof:placetype":"venue"
},
  "geometry": {"coordinates":[-81.20360700000001,35.755031],"type":"Point"}
}