{
  "type": "Feature",
  "properties": {
    "iso:country":"US",
    "sg:address":"1802 Niagara Carthage Rd",
    "sg:city":"Carthage",
    "sg:classifiers":[
        {
            "category":"Organizations",
            "subcategory":"Religious Organization",
            "type":"Services"
        }
    ],
    "sg:phone":"+1   ",
    "sg:postcode":"28327",
    "sg:province":"NC",
    "wof:name":"Trinity Bible Church",
    "wof:placetype":"venue"
},
  "geometry": {"coordinates":[-79.376577,35.288642],"type":"Point"}
}