{
  "type": "Feature",
  "properties": {
    "addr:full":"601 N Heritage St Kinston NC 28501",
    "addr:housenumber":"601",
    "addr:postcode":"28501",
    "addr:street":"N Heritage St",
    "iso:country":"US",
    "sg:address":"601 N Heritage St",
    "sg:city":"Kinston",
    "sg:classifiers":[
        {
            "category":"Retail",
            "subcategory":"Auto Repair",
            "type":"Services"
        }
    ],
    "sg:phone":"+1 252 527 5019",
    "sg:postcode":"28501",
    "sg:province":"NC",
    "sg:tags":[
        "repairing",
        "automobile"
    ],
    "wof:name":"Auto Generator & Starter Svc",
    "wof:placetype":"venue"
},
  "geometry": {"coordinates":[-77.58266399999999,35.267736],"type":"Point"}
}