{
  "type": "Feature",
  "properties": {
    "iso:country":"US",
    "sg:address":"75 Camby Dr",
    "sg:city":"Fairview",
    "sg:classifiers":[
        {
            "category":"Professional",
            "subcategory":"Business Services",
            "type":"Services"
        }
    ],
    "sg:phone":"+1   ",
    "sg:postcode":"28730",
    "sg:province":"NC",
    "wof:name":"Art Agency Production Inc",
    "wof:placetype":"venue"
},
  "geometry": {"coordinates":[-82.392335,35.507043],"type":"Point"}
}