{
  "type": "Feature",
  "properties": {
    "addr:full":"403 Village Rd NE Leland NC 28451",
    "addr:housenumber":"403",
    "addr:postcode":"28451",
    "addr:street":"Village Rd Ne",
    "iso:country":"US",
    "sg:address":"403 Village Rd NE",
    "sg:city":"Leland",
    "sg:classifiers":[
        {
            "category":"Restaurant",
            "type":"Food & Drink"
        }
    ],
    "sg:phone":"+1 910 371 3665",
    "sg:postcode":"28451",
    "sg:province":"NC",
    "sg:tags":[
        "parlor",
        "ice",
        "cream"
    ],
    "wof:name":"Mr Frosty's Subs & Ice Cream",
    "wof:placetype":"venue"
},
  "geometry": {"coordinates":[-78.004221,34.236482],"type":"Point"}
}