{
  "type": "Feature",
  "properties": {
    "addr:full":"845 Asbury Rd Waynesville NC 28785",
    "addr:housenumber":"845",
    "addr:postcode":"28785",
    "addr:street":"Asbury Rd",
    "iso:country":"US",
    "sg:address":"845 Asbury Rd",
    "sg:city":"Waynesville",
    "sg:classifiers":[
        {
            "category":"Professional",
            "subcategory":"Business Services",
            "type":"Services"
        }
    ],
    "sg:phone":"+1 828 926 2874",
    "sg:postcode":"28785",
    "sg:province":"NC",
    "wof:name":"Killiam Knife Grinding",
    "wof:placetype":"venue"
},
  "geometry": {"coordinates":[-83.008712,35.543087],"type":"Point"}
}