{
  "type": "Feature",
  "properties": {
    "addr:full":"2280 Mount Gilead Church Rd Pittsboro NC 27312",
    "addr:housenumber":"2280",
    "addr:postcode":"27312",
    "addr:street":"Mount Gilead Church Rd",
    "iso:country":"US",
    "sg:address":"2280 Mount Gilead Church Rd",
    "sg:city":"Pittsboro",
    "sg:classifiers":[
        {
            "category":"Real Estate",
            "subcategory":"Real Estate Agent",
            "type":"Services"
        }
    ],
    "sg:phone":"+1 919 642 0130",
    "sg:postcode":"27312",
    "sg:province":"NC",
    "wof:name":"Valerie Hudson Realty",
    "wof:placetype":"venue"
},
  "geometry": {"coordinates":[-79.092742,35.768228],"type":"Point"}
}