{
  "type": "Feature",
  "properties": {
    "iso:country":"US",
    "sg:address":"101 Cloister Ct",
    "sg:city":"Chapel Hill",
    "sg:classifiers":[
        {
            "category":"Health Services",
            "subcategory":"Doctor",
            "type":"Services"
        }
    ],
    "sg:phone":"+1   ",
    "sg:postcode":"27514",
    "sg:province":"NC",
    "sg:tags":[
        "medical"
    ],
    "wof:name":"Peter Z Perault Dr",
    "wof:placetype":"venue"
},
  "geometry": {"coordinates":[-79.00493299999999,35.953328],"type":"Point"}
}