{
  "type": "Feature",
  "properties": {
    "addr:full":"7336 Meadowdale Ln Charlotte NC 28212",
    "addr:housenumber":"7336",
    "addr:postcode":"28212",
    "addr:street":"Meadowdale Ln",
    "iso:country":"US",
    "sg:address":"7336 Meadowdale Ln",
    "sg:city":"Charlotte",
    "sg:classifiers":[
        {
            "category":"Cinema",
            "subcategory":"Movie Rental",
            "type":"Entertainment"
        }
    ],
    "sg:phone":"+1 704 957 5450",
    "sg:postcode":"28212",
    "sg:province":"NC",
    "sg:tags":[
        "motion",
        "picture",
        "distributor",
        "film",
        "exchange"
    ],
    "wof:name":"Deann Productions",
    "wof:placetype":"venue"
},
  "geometry": {"coordinates":[-80.73969700000001,35.191878],"type":"Point"}
}