{
  "type": "Feature",
  "properties": {
    "iso:country":"US",
    "sg:address":"205 Hoover Rd",
    "sg:city":"Mebane",
    "sg:classifiers":[
        {
            "category":"Retail",
            "subcategory":"Repair Shop",
            "type":"Services"
        }
    ],
    "sg:phone":"+1   ",
    "sg:postcode":"27302",
    "sg:province":"NC",
    "sg:tags":[
        "refrigeration"
    ],
    "wof:name":"John E Evans Refrigeration",
    "wof:placetype":"venue"
},
  "geometry": {"coordinates":[-79.240751,36.095908],"type":"Point"}
}