{
  "type": "Feature",
  "properties": {
    "iso:country":"US",
    "sg:address":"231 Askewville Rd",
    "sg:city":"Windsor",
    "sg:classifiers":[
        {
            "category":"Retail",
            "subcategory":"Auto Repair",
            "type":"Services"
        }
    ],
    "sg:phone":"+1 252 794 5049",
    "sg:postcode":"27924",
    "sg:province":"NC",
    "sg:tags":[
        "body",
        "automobile",
        "painting"
    ],
    "wof:name":"White's Body Shop",
    "wof:placetype":"venue"
},
  "geometry": {"coordinates":[-76.953884,36.116496],"type":"Point"}
}