{
  "type": "Feature",
  "properties": {
    "iso:country":"US",
    "sg:address":"1550 Kelly Dr",
    "sg:city":"Sanford",
    "sg:classifiers":[
        {
            "category":"Education",
            "subcategory":"Special Training",
            "type":"Public Place"
        }
    ],
    "sg:phone":"+1   ",
    "sg:postcode":"27330",
    "sg:province":"NC",
    "wof:name":"Stepping Stone Learning Center",
    "wof:placetype":"venue"
},
  "geometry": {"coordinates":[-79.137379,35.475747],"type":"Point"}
}