{
  "type": "Feature",
  "properties": {
    "iso:country":"US",
    "sg:address":"2487 Armstrong Dr",
    "sg:city":"Winston Salem",
    "sg:classifiers":[
        {
            "category":"Building & Trades",
            "subcategory":"Plumbing",
            "type":"Services"
        }
    ],
    "sg:phone":"+1 336 768 3887",
    "sg:postcode":"27103",
    "sg:province":"NC",
    "sg:tags":[
        "plumbing",
        "contractor"
    ],
    "wof:name":"Excel Plumbing",
    "wof:placetype":"venue"
},
  "geometry": {"coordinates":[-80.315612,36.039892],"type":"Point"}
}