{
  "type": "Feature",
  "properties": {
    "addr:full":"5292 Roxboro Rd Durham NC 27712",
    "addr:housenumber":"5292",
    "addr:postcode":"27712",
    "addr:street":"Roxboro Rd",
    "iso:country":"US",
    "sg:address":"5292 Roxboro Rd",
    "sg:city":"Durham",
    "sg:classifiers":[
        {
            "category":"Food & Beverages",
            "subcategory":"Groceries & Convenience Stores",
            "type":"Retail Goods"
        }
    ],
    "sg:phone":"+1 919 471 4148",
    "sg:postcode":"27712",
    "sg:province":"NC",
    "wof:name":"B P Eno",
    "wof:placetype":"venue"
},
  "geometry": {"coordinates":[-78.90973,36.076502],"type":"Point"}
}