{
  "type": "Feature",
  "properties": {
    "iso:country":"US",
    "sg:address":"2710 N Center St",
    "sg:city":"Hickory",
    "sg:classifiers":[
        {
            "category":"Restaurant",
            "type":"Food & Drink"
        }
    ],
    "sg:menulink":"http://www.allmenus.com/nc/hickory/240670-bts-burgerjoint/menu/",
    "sg:phone":"+1 828 322 3323",
    "sg:postcode":"28601",
    "sg:province":"NC",
    "sg:tags":[
        "burger",
        "american"
    ],
    "wof:name":"Bt's Burgerjoint",
    "wof:placetype":"venue"
},
  "geometry": {"coordinates":[-81.331299,35.767166],"type":"Point"}
}