{
  "type": "Feature",
  "properties": {
    "iso:country":"US",
    "sg:address":"4709 Morrowood Ln",
    "sg:city":"Charlotte",
    "sg:classifiers":[
        {
            "category":"Personal",
            "subcategory":"Beauty Salon",
            "type":"Services"
        }
    ],
    "sg:phone":"+1   ",
    "sg:postcode":"28216",
    "sg:province":"NC",
    "sg:tags":[
        "shop"
    ],
    "wof:name":"Total Image Hair Designers",
    "wof:placetype":"venue"
},
  "geometry": {"coordinates":[-80.934184,35.334347],"type":"Point"}
}