{
  "type": "Feature",
  "properties": {
    "iso:country":"US",
    "sg:address":"2107 Hamlin Rd",
    "sg:city":"Durham",
    "sg:phone":"+1 919 471 0266",
    "sg:postcode":"27704",
    "sg:province":"NC",
    "sg:tags":[
        "farm",
        "tobacco"
    ],
    "wof:name":"Powell Tobacco Farms",
    "wof:placetype":"venue"
},
  "geometry": {"coordinates":[-78.840379,36.063861],"type":"Point"}
}