{
  "type": "Feature",
  "properties": {
    "addr:full":"501 W Morehead St Charlotte NC 28208",
    "addr:housenumber":"501",
    "addr:postcode":"28208",
    "addr:street":"W Morehead St",
    "iso:country":"US",
    "sg:address":"501 W Morehead St",
    "sg:city":"Charlotte",
    "sg:classifiers":[
        {
            "category":"Professional",
            "subcategory":"Employment Agencies",
            "type":"Services"
        }
    ],
    "sg:phone":"+1 704 333 1428",
    "sg:postcode":"28208",
    "sg:province":"NC",
    "sg:tags":[
        "discrimination",
        "attorney"
    ],
    "wof:name":"Fosbinder Law Office",
    "wof:placetype":"venue"
},
  "geometry": {"coordinates":[-80.855614,35.22546],"type":"Point"}
}