{
  "type": "Feature",
  "properties": {
    "iso:country":"US",
    "sg:address":"100 Patterson Dr",
    "sg:city":"Rocky Mount",
    "sg:classifiers":[
        {
            "category":"Banks & Credit Unions",
            "subcategory":"Bank",
            "type":"Services"
        }
    ],
    "sg:phone":"+1 252 451 2500",
    "sg:postcode":"27804",
    "sg:province":"NC",
    "sg:tags":[
        "financing"
    ],
    "wof:name":"Time Financing Svc",
    "wof:placetype":"venue"
},
  "geometry": {"coordinates":[-77.83834400000001,35.962945],"type":"Point"}
}