{
  "type": "Feature",
  "properties": {
    "addr:full":"514 Hawthorne Dr Asheboro NC 27205",
    "addr:housenumber":"514",
    "addr:postcode":"27205",
    "addr:street":"Hawthorne Dr",
    "iso:country":"US",
    "sg:address":"514 Hawthorne Dr",
    "sg:city":"Asheboro",
    "sg:classifiers":[
        {
            "category":"Building & Trades",
            "subcategory":"Cleaning & Sanitation",
            "type":"Services"
        }
    ],
    "sg:phone":"+1 336 626 4901",
    "sg:postcode":"27205",
    "sg:province":"NC",
    "sg:tags":[
        "floor",
        "laying",
        "maintenance",
        "contractor"
    ],
    "wof:name":"Cagle Floor Care",
    "wof:placetype":"venue"
},
  "geometry": {"coordinates":[-79.815275,35.664845],"type":"Point"}
}