{
  "type": "Feature",
  "properties": {
    "addr:full":"231 Main St Vass NC 28394",
    "addr:housenumber":"231",
    "addr:postcode":"28394",
    "addr:street":"Main St",
    "iso:country":"US",
    "sg:address":"231 Main St",
    "sg:city":"Vass",
    "sg:classifiers":[
        {
            "category":"Shopping",
            "subcategory":"Florist",
            "type":"Retail Goods"
        }
    ],
    "sg:phone":"+1 910 245 3880",
    "sg:postcode":"28394",
    "sg:province":"NC",
    "wof:name":"Brendas Younique Floral Creat",
    "wof:placetype":"venue"
},
  "geometry": {"coordinates":[-79.279888,35.255142],"type":"Point"}
}