{
  "type": "Feature",
  "properties": {
    "iso:country":"US",
    "sg:address":"8101 Statesville Rd",
    "sg:city":"Charlotte",
    "sg:classifiers":[
        {
            "category":"Wholesale",
            "subcategory":"Machinery & Supplies",
            "type":"Manufacturing & Wholesale Goods"
        }
    ],
    "sg:phone":"+1 704 597 5101",
    "sg:postcode":"28269",
    "sg:province":"NC",
    "sg:tags":[
        "cargo",
        "container",
        "freight"
    ],
    "wof:name":"Panthres Intl Inc",
    "wof:placetype":"venue"
},
  "geometry": {"coordinates":[-80.84293,35.333816],"type":"Point"}
}