{
  "type": "Feature",
  "properties": {
    "addr:full":"1574 Red Oak Dr Roxboro NC 27573",
    "addr:housenumber":"1574",
    "addr:postcode":"27573",
    "addr:street":"Red Oak Dr",
    "iso:country":"US",
    "sg:address":"1574 Red Oak Dr",
    "sg:city":"Roxboro",
    "sg:classifiers":[
        {
            "category":"Real Estate",
            "subcategory":"Real Estate Operator",
            "type":"Services"
        }
    ],
    "sg:phone":"+1 336 599 4048",
    "sg:postcode":"27573",
    "sg:province":"NC",
    "sg:tags":[
        "apartment"
    ],
    "wof:name":"Pine Ridge Apartments",
    "wof:placetype":"venue"
},
  "geometry": {"coordinates":[-78.974598,36.424106],"type":"Point"}
}