{
  "type": "Feature",
  "properties": {
    "iso:country":"US",
    "sg:address":"101 Black Tie Ln",
    "sg:city":"Chapel Hill",
    "sg:classifiers":[
        {
            "category":"Professional",
            "subcategory":"Research",
            "type":"Services"
        }
    ],
    "sg:phone":"+1   ",
    "sg:postcode":"27514",
    "sg:province":"NC",
    "sg:tags":[
        "nonphysical",
        "commercial"
    ],
    "wof:name":"Mingju Huhang",
    "wof:placetype":"venue"
},
  "geometry": {"coordinates":[-79.057104,35.956289],"type":"Point"}
}