{
  "type": "Feature",
  "properties": {
    "addr:full":"318 W Montcastle Dr Greensboro NC 27406",
    "addr:housenumber":"318",
    "addr:postcode":"27406",
    "addr:street":"W Montcastle Dr",
    "iso:country":"US",
    "sg:address":"318 W Montcastle Dr",
    "sg:city":"Greensboro",
    "sg:classifiers":[
        {
            "category":"Organizations",
            "subcategory":"Religious Organization",
            "type":"Services"
        }
    ],
    "sg:phone":"+1   ",
    "sg:postcode":"27406",
    "sg:province":"NC",
    "wof:name":"Soul Works Ministries Inc",
    "wof:placetype":"venue"
},
  "geometry": {"coordinates":[-79.797209,36.018094],"type":"Point"}
}