{
  "type": "Feature",
  "properties": {
    "addr:full":"556 Huffman Mill Rd Burlington NC 27215",
    "addr:housenumber":"556",
    "addr:postcode":"27215",
    "addr:street":"Huffman Mill Rd",
    "iso:country":"US",
    "sg:address":"556 Huffman Mill Rd",
    "sg:city":"Burlington",
    "sg:classifiers":[
        {
            "category":"Food & Beverages",
            "subcategory":"Bakery",
            "type":"Retail Goods"
        }
    ],
    "sg:phone":"+1 336 584 0013",
    "sg:postcode":"27215",
    "sg:province":"NC",
    "sg:tags":[
        "baker"
    ],
    "wof:name":"Emily's Cookie Mix Shoppe",
    "wof:placetype":"venue"
},
  "geometry": {"coordinates":[-79.4893,36.075273],"type":"Point"}
}