{
  "type": "Feature",
  "properties": {
    "iso:country":"US",
    "sg:address":"1600 Old London Way",
    "sg:city":"Apex",
    "sg:classifiers":[
        {
            "category":"Wholesale",
            "subcategory":"Machinery & Supplies",
            "type":"Manufacturing & Wholesale Goods"
        }
    ],
    "sg:phone":"+1 919 572 0126",
    "sg:postcode":"27523",
    "sg:province":"NC",
    "sg:tags":[
        "equipment",
        "material",
        "handling"
    ],
    "wof:name":"Nova Industries Inc",
    "wof:placetype":"venue"
},
  "geometry": {"coordinates":[-78.84166399999999,35.759184],"type":"Point"}
}