{
  "type": "Feature",
  "properties": {
    "addr:full":"318 Village Rd NE Leland NC 28451",
    "addr:housenumber":"318",
    "addr:postcode":"28451",
    "addr:street":"Village Rd Ne",
    "iso:country":"US",
    "sg:address":"318 Village Rd NE",
    "sg:city":"Leland",
    "sg:classifiers":[
        {
            "category":"Restaurant",
            "type":"Food & Drink"
        }
    ],
    "sg:phone":"+1 910 383 0822",
    "sg:postcode":"28451",
    "sg:province":"NC",
    "sg:tags":[
        "eating"
    ],
    "wof:name":"Bagles Cafe",
    "wof:placetype":"venue"
},
  "geometry": {"coordinates":[-78.00913799999999,34.239644],"type":"Point"}
}