{
  "type": "Feature",
  "properties": {
    "iso:country":"US",
    "sg:address":"156 US Hwy 70",
    "sg:city":"Havelock",
    "sg:classifiers":[
        {
            "category":"Wholesale",
            "subcategory":"Machinery & Supplies",
            "type":"Manufacturing & Wholesale Goods"
        }
    ],
    "sg:phone":"+1 252 447 4247",
    "sg:postcode":"28532",
    "sg:province":"NC",
    "sg:tags":[
        "engine",
        "aircraft"
    ],
    "wof:name":"Aeronautical Solutions Inc",
    "wof:placetype":"venue"
},
  "geometry": {"coordinates":[-76.91122900000001,34.883487],"type":"Point"}
}