{
  "type": "Feature",
  "properties": {
    "addr:full":"1421 S Glenburnie Rd New Bern NC 28562",
    "addr:housenumber":"1421",
    "addr:postcode":"28562",
    "addr:street":"S Glenburnie Rd",
    "iso:country":"US",
    "sg:address":"1421 S Glenburnie Rd",
    "sg:city":"New Bern",
    "sg:classifiers":[
        {
            "category":"Health Services",
            "subcategory":"Doctor",
            "type":"Services"
        }
    ],
    "sg:phone":"+1 252 633 9800",
    "sg:postcode":"28562",
    "sg:province":"NC",
    "wof:name":"Hoard Dr J Stphen Fmly Dntstry",
    "wof:placetype":"venue"
},
  "geometry": {"coordinates":[-77.09168699999999,35.118404],"type":"Point"}
}