{
  "type": "Feature",
  "properties": {
    "addr:full":"216 Coddies Ter Franklin NC 28734",
    "addr:housenumber":"216",
    "addr:postcode":"nc 28734",
    "addr:street":"Coddies Ter",
    "iso:country":"US",
    "sg:address":"216 Coddies Ter",
    "sg:city":"Franklin",
    "sg:classifiers":[
        {
            "category":"Wholesale",
            "subcategory":"Machinery & Supplies",
            "type":"Manufacturing & Wholesale Goods"
        }
    ],
    "sg:phone":"+1 828 524 6293",
    "sg:postcode":"28734",
    "sg:province":"NC",
    "sg:tags":[
        "equipment",
        "veterinarian"
    ],
    "sg:website":"www.kissmfg.com",
    "wof:name":"Kiss Manufacturing Co",
    "wof:placetype":"venue"
},
  "geometry": {"coordinates":[-83.448587,35.10511],"type":"Point"}
}