{
  "type": "Feature",
  "properties": {
    "iso:country":"US",
    "sg:address":"3739 Vance St Exd",
    "sg:city":"Reidsville",
    "sg:classifiers":[
        {
            "category":"Personal",
            "subcategory":"Beauty Salon",
            "type":"Services"
        }
    ],
    "sg:phone":"+1   ",
    "sg:postcode":"27320",
    "sg:province":"NC",
    "sg:tags":[
        "shop"
    ],
    "wof:name":"Hair By Design",
    "wof:placetype":"venue"
},
  "geometry": {"coordinates":[-79.717579,36.365053],"type":"Point"}
}