{
  "type": "Feature",
  "properties": {
    "addr:full":"6806 S State Hwy 18 Boomer NC 28606",
    "addr:housenumber":"6806",
    "addr:postcode":"28606",
    "addr:street":"S State Hwy 18",
    "iso:country":"US",
    "sg:address":"6806 S State Hwy 18",
    "sg:city":"Boomer",
    "sg:classifiers":[
        {
            "category":"Wholesale",
            "subcategory":"Electrical",
            "type":"Manufacturing & Wholesale Goods"
        }
    ],
    "sg:phone":"+1 336 921 4375",
    "sg:postcode":"28606",
    "sg:province":"NC",
    "sg:tags":[
        "television"
    ],
    "wof:name":"Integrity Electric & Elctrncs",
    "wof:placetype":"venue"
},
  "geometry": {"coordinates":[-81.278256,36.052319],"type":"Point"}
}