{
  "type": "Feature",
  "properties": {
    "addr:full":"1795 Graham Ave Henderson NC 27536",
    "addr:housenumber":"1795",
    "addr:postcode":"27536",
    "addr:street":"Graham Ave",
    "iso:country":"US",
    "sg:address":"1795 Graham Ave",
    "sg:city":"Henderson",
    "sg:classifiers":[
        {
            "category":"Banks & Credit Unions",
            "subcategory":"Bank",
            "type":"Services"
        }
    ],
    "sg:phone":"+1 252 492 0168",
    "sg:postcode":"27536",
    "sg:province":"NC",
    "sg:tags":[
        "state"
    ],
    "sg:website":"www.ncsecu.org",
    "wof:name":"State Employees Credit Union",
    "wof:placetype":"venue"
},
  "geometry": {"coordinates":[-78.443449,36.325951],"type":"Point"}
}