{
  "type": "Feature",
  "properties": {
    "iso:country":"US",
    "sg:address":"25575 State Hwy 125",
    "sg:city":"Scotland Neck",
    "sg:classifiers":[
        {
            "category":"Farming",
            "subcategory":"Farm",
            "type":"Manufacturing & Wholesale Goods"
        }
    ],
    "sg:phone":"+1 252 826 5198",
    "sg:postcode":"27874",
    "sg:province":"NC",
    "wof:name":"Gallberry Farms Inc",
    "wof:placetype":"venue"
},
  "geometry": {"coordinates":[-77.43518400000001,36.135174],"type":"Point"}
}