{
  "type": "Feature",
  "properties": {
    "addr:full":"556 Bucket Rd Lumberton NC 28358",
    "addr:housenumber":"556",
    "addr:postcode":"28358",
    "addr:street":"Bucket Rd",
    "iso:country":"US",
    "sg:address":"556 Bucket Rd",
    "sg:city":"Lumberton",
    "sg:classifiers":[
        {
            "category":"Building & Trades",
            "subcategory":"Construction",
            "type":"Services"
        }
    ],
    "sg:phone":"+1 910 671 0769",
    "sg:postcode":"28358",
    "sg:province":"NC",
    "sg:tags":[
        "contractor"
    ],
    "wof:name":"Roof Solutions Inc",
    "wof:placetype":"venue"
},
  "geometry": {"coordinates":[-79.00426,34.725365],"type":"Point"}
}