{
  "type": "Feature",
  "properties": {
    "iso:country":"US",
    "sg:address":"233 S Graham Hopedale Rd",
    "sg:city":"Burlington",
    "sg:classifiers":[
        {
            "category":"Sports & Exercise",
            "subcategory":"Gym",
            "type":"Entertainment"
        }
    ],
    "sg:phone":"+1 336 513 4747",
    "sg:postcode":"27217",
    "sg:province":"NC",
    "sg:tags":[
        "club",
        "health",
        "studio",
        "gymnasium"
    ],
    "wof:name":"Curves",
    "wof:placetype":"venue"
},
  "geometry": {"coordinates":[-79.40610700000001,36.09397],"type":"Point"}
}