{
  "type": "Feature",
  "properties": {
    "addr:full":"1 Mitchell St Bryson City NC 28752",
    "addr:housenumber":"1",
    "addr:postcode":"28752",
    "addr:street":"Mitchell St",
    "iso:country":"US",
    "sg:address":"1 Mitchell St",
    "sg:city":"Bryson City",
    "sg:classifiers":[
        {
            "category":"Social Services",
            "type":"Services"
        }
    ],
    "sg:phone":"+1 828 488 6224",
    "sg:postcode":"28752",
    "sg:province":"NC",
    "sg:tags":[
        "organization",
        "welfare"
    ],
    "wof:name":"Guardian Ad Litem",
    "wof:placetype":"venue"
},
  "geometry": {"coordinates":[-82.016217,35.675118],"type":"Point"}
}