{
  "type": "Feature",
  "properties": {
    "iso:country":"US",
    "sg:address":"346 Grant Rd",
    "sg:city":"Vass",
    "sg:classifiers":[
        {
            "category":"Home & Garden",
            "subcategory":"Furniture",
            "type":"Retail Goods"
        }
    ],
    "sg:phone":"+1 910 245 4977",
    "sg:postcode":"28394",
    "sg:province":"NC",
    "wof:name":"Transit Damaged Freight Inc",
    "wof:placetype":"venue"
},
  "geometry": {"coordinates":[-79.31534000000001,35.231518],"type":"Point"}
}