{
  "type": "Feature",
  "properties": {
    "iso:country":"US",
    "sg:address":"4728 N Croatan Hwy",
    "sg:city":"Kitty Hawk",
    "sg:classifiers":[
        {
            "category":"Food & Beverages",
            "subcategory":"Liquor & Beverages",
            "type":"Retail Goods"
        }
    ],
    "sg:phone":"+1 252 261 3948",
    "sg:postcode":"27949",
    "sg:province":"NC",
    "sg:tags":[
        "alcoholic"
    ],
    "wof:name":"Brew Thru of Kitty Hawk",
    "wof:placetype":"venue"
},
  "geometry": {"coordinates":[-75.70989899999999,36.092953],"type":"Point"}
}