{
  "type": "Feature",
  "properties": {
    "addr:full":"4000 Westchase Blvd Ste 500 Raleigh NC 27607",
    "addr:housenumber":"4000",
    "addr:postcode":"27607",
    "addr:street":"Westchase Blvd Ste 500",
    "iso:country":"US",
    "sg:address":"4000 Westchase Blvd Ste 500",
    "sg:city":"Raleigh",
    "sg:classifiers":[
        {
            "category":"Professional",
            "subcategory":"Lawyer & Legal Services",
            "type":"Services"
        }
    ],
    "sg:phone":"+1 919 755 1068",
    "sg:postcode":"27607",
    "sg:province":"NC",
    "sg:tags":[
        "personal",
        "injury"
    ],
    "wof:name":"Becton Slifkin & Bell PA",
    "wof:placetype":"venue"
},
  "geometry": {"coordinates":[-78.69090300000001,35.804001],"type":"Point"}
}