{
  "type": "Feature",
  "properties": {
    "iso:country":"US",
    "sg:address":"2031 Pony Farm Rd",
    "sg:city":"Jacksonville",
    "sg:classifiers":[
        {
            "category":"Government",
            "subcategory":"Fire Station",
            "type":"Public Place"
        }
    ],
    "sg:phone":"+1 910 347 2820",
    "sg:postcode":"28540",
    "sg:province":"NC",
    "sg:tags":[
        "department"
    ],
    "wof:name":"South West Volunteer Fire Dept",
    "wof:placetype":"venue"
},
  "geometry": {"coordinates":[-77.512781,34.748699],"type":"Point"}
}