{
  "type": "Feature",
  "properties": {
    "addr:full":"1705 Brentwood Ct Newton NC 28658",
    "addr:housenumber":"1705",
    "addr:postcode":"28658",
    "addr:street":"Brentwood Ct",
    "iso:country":"US",
    "sg:address":"1705 Brentwood Ct",
    "sg:city":"Newton",
    "sg:classifiers":[
        {
            "category":"Professional",
            "subcategory":"Business Services",
            "type":"Services"
        }
    ],
    "sg:phone":"+1 828 465 4499",
    "sg:postcode":"28658",
    "sg:province":"NC",
    "sg:tags":[
        "interior",
        "consultant",
        "design",
        "decorator"
    ],
    "wof:name":"Yvonne Mc Ree Interiors",
    "wof:placetype":"venue"
},
  "geometry": {"coordinates":[-81.227966,35.640328],"type":"Point"}
}