{
  "type": "Feature",
  "properties": {
    "iso:country":"US",
    "sg:address":"1812 Prospect Dr",
    "sg:city":"Charlotte",
    "sg:classifiers":[
        {
            "category":"Shopping",
            "subcategory":"Discount & Variety Stores",
            "type":"Retail Goods"
        }
    ],
    "sg:phone":"+1 704 597 8277",
    "sg:postcode":"28213",
    "sg:province":"NC",
    "sg:tags":[
        "merchandise",
        "general"
    ],
    "wof:name":"Brenda G Grier Retail",
    "wof:placetype":"venue"
},
  "geometry": {"coordinates":[-80.78778699999999,35.277151],"type":"Point"}
}