{
  "type": "Feature",
  "properties": {
    "addr:full":"1668 Blowing Rock Rd Boone NC 28607",
    "addr:housenumber":"1668",
    "addr:postcode":"28607",
    "addr:street":"Blowing Rock Rd",
    "iso:country":"US",
    "sg:address":"1668 Blowing Rock Rd",
    "sg:city":"Boone",
    "sg:classifiers":[
        {
            "category":"Restaurant",
            "type":"Food & Drink"
        }
    ],
    "sg:menulink":"http://www.allmenus.com/nc/new-river/183288-kfc---kentucky-fried-chicken/menu/",
    "sg:phone":"+1 828 262 4405",
    "sg:postcode":"28607",
    "sg:province":"NC",
    "sg:tags":[
        "american",
        "chicken"
    ],
    "wof:name":"KFC - Kentucky Fried Chicken",
    "wof:placetype":"venue"
},
  "geometry": {"coordinates":[-81.659415,36.199668],"type":"Point"}
}