{
  "type": "Feature",
  "properties": {
    "addr:full":"6400 Prett Ct Charlotte NC 28270",
    "addr:postcode":"6400;28270",
    "addr:street":"Prett Ct",
    "iso:country":"US",
    "sg:address":"6400 Prett Ct",
    "sg:city":"Charlotte",
    "sg:classifiers":[
        {
            "category":"Education",
            "subcategory":"School",
            "type":"Public Place"
        }
    ],
    "sg:phone":"+1 704 343 6733",
    "sg:postcode":"28270",
    "sg:province":"NC",
    "wof:name":"Lansdowne Elementary School",
    "wof:placetype":"venue"
},
  "geometry": {"coordinates":[-80.781499,35.143952],"type":"Point"}
}