{
  "type": "Feature",
  "properties": {
    "iso:country":"US",
    "sg:address":"612 Pastuer Dr",
    "sg:city":"Greensboro",
    "sg:classifiers":[
        {
            "category":"Personal",
            "type":"Services"
        }
    ],
    "sg:phone":"+1 336 834 0100",
    "sg:postcode":"27403",
    "sg:province":"NC",
    "sg:tags":[
        "therapist",
        "massage"
    ],
    "wof:name":"Body Mind Ctr",
    "wof:placetype":"venue"
},
  "geometry": {"coordinates":[-79.824243,36.082121],"type":"Point"}
}