{
  "type": "Feature",
  "properties": {
    "addr:full":"1150 Red Brush Rd Mount Airy NC 27030",
    "addr:housenumber":"1150",
    "addr:postcode":"27030",
    "addr:street":"Red Brush Rd",
    "iso:country":"US",
    "sg:address":"1150 Red Brush Rd",
    "sg:city":"Mount Airy",
    "sg:classifiers":[
        {
            "category":"Autos & Motor Vehicles",
            "subcategory":"Automobile Sales",
            "type":"Retail Goods"
        }
    ],
    "sg:phone":"+1 336 786 8410",
    "sg:postcode":"27030",
    "sg:province":"NC",
    "wof:name":"Sunset Motors",
    "wof:placetype":"venue"
},
  "geometry": {"coordinates":[-80.674254,36.490628],"type":"Point"}
}