{
  "type": "Feature",
  "properties": {
    "iso:country":"US",
    "sg:address":"409 Edward St",
    "sg:city":"Durham",
    "sg:classifiers":[
        {
            "category":"Building & Trades",
            "subcategory":"Cleaning & Sanitation",
            "type":"Services"
        }
    ],
    "sg:phone":"+1   ",
    "sg:postcode":"27701",
    "sg:province":"NC",
    "sg:tags":[
        "maintenance"
    ],
    "wof:name":"Rogers Cleaning Service",
    "wof:placetype":"venue"
},
  "geometry": {"coordinates":[-78.886764,36.005119],"type":"Point"}
}