{
  "type": "Feature",
  "properties": {
    "iso:country":"US",
    "sg:address":"4102 Soco Rd",
    "sg:city":"Maggie Valley",
    "sg:classifiers":[
        {
            "category":"Restaurant",
            "type":"Food & Drink"
        }
    ],
    "sg:phone":"+1 828 926 9978",
    "sg:postcode":"28751",
    "sg:province":"NC",
    "wof:name":"Smokey Mountain Cafe",
    "wof:placetype":"venue"
},
  "geometry": {"coordinates":[-83.09689,35.518008],"type":"Point"}
}