{
  "type": "Feature",
  "properties": {
    "iso:country":"US",
    "sg:address":"314 Rensselaer Ave",
    "sg:city":"Charlotte",
    "sg:classifiers":[
        {
            "category":"Professional",
            "subcategory":"Advertising",
            "type":"Services"
        }
    ],
    "sg:phone":"+1 704 334 2232",
    "sg:postcode":"28203",
    "sg:province":"NC",
    "wof:name":"Creative Cubes",
    "wof:placetype":"venue"
},
  "geometry": {"coordinates":[-80.853585,35.213755],"type":"Point"}
}