{
  "type": "Feature",
  "properties": {
    "iso:country":"US",
    "sg:address":"2511 Battleground Avenue. Suite B",
    "sg:city":"Greensboro",
    "sg:classifiers":[
        {
            "category":"Fast Food",
            "type":"Food & Drink"
        },
        {
            "category":"Restaurant",
            "type":"Food & Drink"
        },
        {
            "category":"Food & Beverages",
            "subcategory":"Groceries & Convenience Stores",
            "type":"Retail Goods"
        }
    ],
    "sg:phone":"+1 336 282 9000",
    "sg:postcode":"27408",
    "sg:province":"NC",
    "sg:tags":[
        "shop",
        "sandwich",
        "take"
    ],
    "sg:website":"http://www.rolypoly.com",
    "wof:name":"Roly Poly",
    "wof:placetype":"venue"
},
  "geometry": {"coordinates":[-79.826072,36.105411],"type":"Point"}
}