{
  "type": "Feature",
  "properties": {
    "iso:country":"US",
    "sg:address":"14 Twin Willow Rd",
    "sg:city":"Hendersonville",
    "sg:classifiers":[
        {
            "category":"Manufacturing",
            "subcategory":"Rubber & Plastics",
            "type":"Manufacturing & Wholesale Goods"
        }
    ],
    "sg:phone":"+1 828 685 0940",
    "sg:postcode":"28792",
    "sg:province":"NC",
    "sg:tags":[
        "forming"
    ],
    "wof:name":"Fiberglass & Plastics",
    "wof:placetype":"venue"
},
  "geometry": {"coordinates":[-82.33818599999999,35.397887],"type":"Point"}
}