{
  "type": "Feature",
  "properties": {
    "iso:country":"US",
    "sg:address":"120 W Gordon St",
    "sg:city":"Kinston",
    "sg:classifiers":[
        {
            "category":"Manufacturing",
            "subcategory":"Printing",
            "type":"Manufacturing & Wholesale Goods"
        }
    ],
    "sg:phone":"+1 252 523 8133",
    "sg:postcode":"28501",
    "sg:province":"NC",
    "sg:tags":[
        "commercial"
    ],
    "wof:name":"Advantage Printing & Design",
    "wof:placetype":"venue"
},
  "geometry": {"coordinates":[-77.58130300000001,35.261554],"type":"Point"}
}