{
  "type": "Feature",
  "properties": {
    "addr:full":"110 E 36th St Charlotte NC 28206",
    "addr:housenumber":"110",
    "addr:postcode":"28206",
    "addr:street":"E 36Th St",
    "iso:country":"US",
    "sg:address":"110 E 36th St",
    "sg:city":"Charlotte",
    "sg:classifiers":[
        {
            "category":"Retail",
            "subcategory":"Auto Repair",
            "type":"Services"
        }
    ],
    "sg:phone":"+1 704 334 0804",
    "sg:postcode":"28206",
    "sg:province":"NC",
    "sg:tags":[
        "repairing",
        "automobile"
    ],
    "wof:name":"Jim's Auto Repair",
    "wof:placetype":"venue"
},
  "geometry": {"coordinates":[-80.807637,35.251852],"type":"Point"}
}