{
  "type": "Feature",
  "properties": {
    "iso:country":"US",
    "sg:address":"160 Pinehurst Ave",
    "sg:city":"Southern Pines",
    "sg:classifiers":[
        {
            "category":"Insurance",
            "subcategory":"Insurance Agent",
            "type":"Services"
        }
    ],
    "sg:phone":"+1 910 695 1127",
    "sg:postcode":"28387",
    "sg:province":"NC",
    "sg:tags":[
        "adjuster",
        "vehicle"
    ],
    "wof:name":"Pmac Insurance",
    "wof:placetype":"venue"
},
  "geometry": {"coordinates":[-79.414134,35.15892],"type":"Point"}
}