{
  "type": "Feature",
  "properties": {
    "addr:full":"771 Park Centre Dr Kernersville NC 27284",
    "addr:housenumber":"771",
    "addr:postcode":"27284",
    "addr:street":"Park Centre Dr",
    "iso:country":"US",
    "sg:address":"771 Park Centre Dr",
    "sg:city":"Kernersville",
    "sg:classifiers":[
        {
            "category":"Government",
            "subcategory":"Jail",
            "type":"Public Place"
        }
    ],
    "sg:phone":"+1 336 996 4398",
    "sg:postcode":"27284",
    "sg:province":"NC",
    "sg:tags":[
        "govt",
        "state",
        "institution"
    ],
    "sg:website":"www.doc.state.nc.us",
    "wof:name":"Corrections Dept",
    "wof:placetype":"venue"
},
  "geometry": {"coordinates":[-80.063614,36.098541],"type":"Point"}
}