{
  "type": "Feature",
  "properties": {
    "addr:full":"154 N Bridge St Jonesville NC 28642",
    "addr:housenumber":"154",
    "addr:postcode":"28642",
    "addr:street":"N Bridge St",
    "iso:country":"US",
    "sg:address":"154 N Bridge St",
    "sg:city":"Jonesville",
    "sg:classifiers":[
        {
            "category":"Professional",
            "subcategory":"Accounting & Tax Preparation",
            "type":"Services"
        }
    ],
    "sg:phone":"+1   ",
    "sg:postcode":"28642",
    "sg:province":"NC",
    "sg:tags":[
        "return"
    ],
    "wof:name":"Taxaco",
    "wof:placetype":"venue"
},
  "geometry": {"coordinates":[-80.846463,36.240961],"type":"Point"}
}