{
  "type": "Feature",
  "properties": {
    "addr:full":"8230 Tomahawk Hwy Harrells NC 28441",
    "addr:housenumber":"8230",
    "addr:postcode":"28441",
    "addr:street":"Tomahawk Hwy",
    "iso:country":"US",
    "sg:address":"8230 Tomahawk Hwy",
    "sg:city":"Harrells",
    "sg:classifiers":[
        {
            "category":"Wholesale",
            "subcategory":"Farm Supplies",
            "type":"Manufacturing & Wholesale Goods"
        }
    ],
    "sg:phone":"+1 910 532 2066",
    "sg:postcode":"28441",
    "sg:province":"NC",
    "sg:tags":[
        "fertilizer",
        "dist"
    ],
    "wof:name":"Olsen Harold",
    "wof:placetype":"venue"
},
  "geometry": {"coordinates":[-78.326932,34.71159],"type":"Point"}
}