{
  "type": "Feature",
  "properties": {
    "addr:full":"131 Mount Zion Church Rd Seagrove NC 27357",
    "addr:housenumber":"131",
    "addr:postcode":"27357",
    "addr:street":"Mount Zion Church Rd",
    "iso:country":"US",
    "sg:address":"131 Mount Zion Church Rd",
    "sg:city":"Seagrove",
    "sg:classifiers":[
        {
            "category":"Manufacturing",
            "subcategory":"Furniture",
            "type":"Manufacturing & Wholesale Goods"
        }
    ],
    "sg:phone":"+1 336 873 4845",
    "sg:postcode":"27357",
    "sg:province":"NC",
    "wof:name":"Mc Neill Upholstery",
    "wof:placetype":"venue"
},
  "geometry": {"coordinates":[-80.00588999999999,36.290858],"type":"Point"}
}