{
  "type": "Feature",
  "properties": {
    "iso:country":"US",
    "sg:address":"7124 Hwy 58 N",
    "sg:city":"Stantonsburg",
    "sg:classifiers":[
        {
            "category":"Retail",
            "subcategory":"Repair Shop",
            "type":"Services"
        }
    ],
    "sg:phone":"+1   ",
    "sg:postcode":"27883",
    "sg:province":"NC",
    "wof:name":"H&F Equipment Service",
    "wof:placetype":"venue"
},
  "geometry": {"coordinates":[-77.784502,35.523906],"type":"Point"}
}