{
  "type": "Feature",
  "properties": {
    "iso:country":"US",
    "sg:address":"7817 S Colorado Dr",
    "sg:city":"Raleigh",
    "sg:classifiers":[
        {
            "category":"Building & Trades",
            "subcategory":"Construction",
            "type":"Services"
        }
    ],
    "sg:phone":"+1 919 422 4272",
    "sg:postcode":"27616",
    "sg:province":"NC",
    "sg:tags":[
        "contractor"
    ],
    "wof:name":"Guererro Masonry",
    "wof:placetype":"venue"
},
  "geometry": {"coordinates":[-78.563354,35.881621],"type":"Point"}
}