{
  "type": "Feature",
  "properties": {
    "addr:full":"970 Corriher Springs Rd China Grove NC 28023",
    "addr:housenumber":"970",
    "addr:postcode":"28023",
    "addr:street":"Corriher Springs Rd",
    "iso:country":"US",
    "sg:address":"970 Corriher Springs Rd",
    "sg:city":"China Grove",
    "sg:classifiers":[
        {
            "category":"Building & Trades",
            "subcategory":"Construction",
            "type":"Services"
        }
    ],
    "sg:phone":"+1 704 855 2359",
    "sg:postcode":"28023",
    "sg:province":"NC",
    "sg:tags":[
        "house"
    ],
    "wof:name":"Countryside Construction Inc",
    "wof:placetype":"venue"
},
  "geometry": {"coordinates":[-80.66883799999999,35.585608],"type":"Point"}
}