{
  "type": "Feature",
  "properties": {
    "addr:full":"310 E F St Erwin NC 28339",
    "addr:housenumber":"310",
    "addr:postcode":"28339",
    "addr:street":"E F St",
    "iso:country":"US",
    "sg:address":"310 E F St",
    "sg:city":"Erwin",
    "sg:classifiers":[
        {
            "category":"Social Services",
            "subcategory":"Child Care",
            "type":"Services"
        }
    ],
    "sg:phone":"+1 910 897 4385",
    "sg:postcode":"28339",
    "sg:province":"NC",
    "wof:name":"Bullfrogs & Butterflies Day Cr",
    "wof:placetype":"venue"
},
  "geometry": {"coordinates":[-78.672573,35.326027],"type":"Point"}
}