{
  "type": "Feature",
  "properties": {
    "iso:country":"US",
    "sg:address":"1812 Whitfield Ave",
    "sg:city":"Rocky Mount",
    "sg:classifiers":[
        {
            "category":"Personal",
            "subcategory":"Beauty Salon",
            "type":"Services"
        }
    ],
    "sg:phone":"+1   ",
    "sg:postcode":"27801",
    "sg:province":"NC",
    "sg:tags":[
        "shop"
    ],
    "wof:name":"Juanitas Place",
    "wof:placetype":"venue"
},
  "geometry": {"coordinates":[-77.761477,35.963926],"type":"Point"}
}