{
  "type": "Feature",
  "properties": {
    "addr:full":"135 E Pennsylvania Ave Southern Pines NC 28387",
    "addr:housenumber":"135",
    "addr:postcode":"28387",
    "addr:street":"E Pennsylvania Ave",
    "iso:country":"US",
    "sg:address":"135 E Pennsylvania Ave",
    "sg:city":"Southern Pines",
    "sg:classifiers":[
        {
            "category":"Personal",
            "subcategory":"Beauty Salon",
            "type":"Services"
        }
    ],
    "sg:phone":"+1   ",
    "sg:postcode":"28387",
    "sg:province":"NC",
    "sg:tags":[
        "shop"
    ],
    "wof:name":"Maes Hair Salon",
    "wof:placetype":"venue"
},
  "geometry": {"coordinates":[-79.391508,35.173371],"type":"Point"}
}