{
  "type": "Feature",
  "properties": {
    "iso:country":"US",
    "sg:address":"127 Toler Rd",
    "sg:city":"Manteo",
    "sg:classifiers":[
        {
            "category":"Professional",
            "type":"Services"
        }
    ],
    "sg:phone":"+1 252 473 4624",
    "sg:postcode":"27954",
    "sg:province":"NC",
    "wof:name":"Fish Inc",
    "wof:placetype":"venue"
},
  "geometry": {"coordinates":[-75.663584,35.879655],"type":"Point"}
}