{
  "type": "Feature",
  "properties": {
    "iso:country":"US",
    "sg:address":"798 Church St N",
    "sg:city":"Concord",
    "sg:classifiers":[
        {
            "category":"Shopping",
            "subcategory":"Clothing, Apparel, & Fashions",
            "type":"Retail Goods"
        }
    ],
    "sg:phone":"+1 704 786 6211",
    "sg:postcode":"28025",
    "sg:province":"NC",
    "wof:name":"Ginnys Uniform",
    "wof:placetype":"venue"
},
  "geometry": {"coordinates":[-80.602177,35.432414],"type":"Point"}
}