{
  "type": "Feature",
  "properties": {
    "iso:country":"US",
    "sg:address":"11404 Spreading Oak Ln",
    "sg:city":"Charlotte",
    "sg:classifiers":[
        {
            "category":"Food & Beverages",
            "subcategory":"Specialty",
            "type":"Retail Goods"
        },
        {
            "category":"Food & Beverages",
            "subcategory":"Liquor & Beverages",
            "type":"Retail Goods"
        },
        {
            "category":"Food & Beverages",
            "subcategory":"Groceries & Convenience Stores",
            "type":"Retail Goods"
        }
    ],
    "sg:phone":"+1 704 332 4024",
    "sg:postcode":"28226",
    "sg:province":"NC",
    "sg:tags":[
        "grocers-specialty"
    ],
    "wof:name":"Rons Grocery",
    "wof:placetype":"venue"
},
  "geometry": {"coordinates":[-80.85458800000001,35.070621],"type":"Point"}
}