{
  "type": "Feature",
  "properties": {
    "addr:full":"117 Chappell Creek Dr Richlands NC 28574",
    "addr:housenumber":"117",
    "addr:postcode":"28574",
    "addr:street":"Chappell Creek Dr",
    "iso:country":"US",
    "sg:address":"117 Chappell Creek Dr",
    "sg:city":"Richlands",
    "sg:classifiers":[
        {
            "category":"Professional",
            "subcategory":"Management & Consulting",
            "type":"Services"
        }
    ],
    "sg:phone":"+1   ",
    "sg:postcode":"28574",
    "sg:province":"NC",
    "sg:tags":[
        "consultant"
    ],
    "wof:name":"Harold G Stevens",
    "wof:placetype":"venue"
},
  "geometry": {"coordinates":[-77.570609,34.841946],"type":"Point"}
}