{
  "type": "Feature",
  "properties": {
    "iso:country":"US",
    "sg:address":"1801 N Tryon St",
    "sg:city":"Charlotte",
    "sg:classifiers":[
        {
            "category":"Health Services",
            "subcategory":"Nursing And Care Facility",
            "type":"Services"
        },
        {
            "category":"Social Services",
            "subcategory":"Retirement Home",
            "type":"Services"
        }
    ],
    "sg:phone":"+1 704 405 1467",
    "sg:postcode":"28206",
    "sg:province":"NC",
    "sg:tags":[
        "personal",
        "convalescent"
    ],
    "wof:name":"Faithfull Servant Home Care",
    "wof:placetype":"venue"
},
  "geometry": {"coordinates":[-80.824883,35.240959],"type":"Point"}
}