{
  "type": "Feature",
  "properties": {
    "addr:full":"7372 Stoney Hill Church Rd Bailey NC 27807",
    "addr:housenumber":"7372",
    "addr:postcode":"27807",
    "addr:street":"Stoney Hill Church Rd",
    "iso:country":"US",
    "sg:address":"7372 Stoney Hill Church Rd",
    "sg:city":"Bailey",
    "sg:classifiers":[
        {
            "category":"Retail",
            "subcategory":"Auto Repair",
            "type":"Services"
        }
    ],
    "sg:phone":"+1 252 235 3696",
    "sg:postcode":"27807",
    "sg:province":"NC",
    "sg:tags":[
        "transmission"
    ],
    "wof:name":"Marks Transmission Svc",
    "wof:placetype":"venue"
},
  "geometry": {"coordinates":[-78.13076100000001,35.808718],"type":"Point"}
}