{
  "type": "Feature",
  "properties": {
    "iso:country":"US",
    "sg:address":"4494 Alwood Ln",
    "sg:city":"Rocky Mount",
    "sg:classifiers":[
        {
            "category":"Professional",
            "subcategory":"Business Services",
            "type":"Services"
        }
    ],
    "sg:phone":"+1 252 451 1836",
    "sg:postcode":"27804",
    "sg:province":"NC",
    "sg:tags":[
        "inventory"
    ],
    "wof:name":"Carolina East Inventory LLC",
    "wof:placetype":"venue"
},
  "geometry": {"coordinates":[-77.85129999999999,36.023239],"type":"Point"}
}