{
  "type": "Feature",
  "properties": {
    "iso:country":"US",
    "sg:address":"12454 US Hwy 52",
    "sg:city":"Norwood",
    "sg:classifiers":[
        {
            "category":"Retail",
            "subcategory":"Repair Shop",
            "type":"Services"
        },
        {
            "category":"Wholesale",
            "subcategory":"Scrap",
            "type":"Manufacturing & Wholesale Goods"
        }
    ],
    "sg:phone":"+1 704 474 4366",
    "sg:postcode":"28128",
    "sg:province":"NC",
    "sg:tags":[
        "metal",
        "iron"
    ],
    "wof:name":"Butch's Scrap Metals",
    "wof:placetype":"venue"
},
  "geometry": {"coordinates":[-80.14206799999999,35.237874],"type":"Point"}
}