{
  "type": "Feature",
  "properties": {
    "iso:country":"US",
    "sg:address":"303 Mangrove Dr",
    "sg:city":"Emerald Isle",
    "sg:classifiers":[
        {
            "category":"Restaurant",
            "type":"Food & Drink"
        }
    ],
    "sg:phone":"+1 252 354 9700",
    "sg:postcode":"28594",
    "sg:province":"NC",
    "wof:name":"South Banks Grill",
    "wof:placetype":"venue"
},
  "geometry": {"coordinates":[-77.042277,34.663904],"type":"Point"}
}