{
  "type": "Feature",
  "properties": {
    "addr:full":"106 S Main St Candor NC 27229",
    "addr:housenumber":"106",
    "addr:postcode":"27229",
    "addr:street":"S Main St",
    "iso:country":"US",
    "sg:address":"106 S Main St",
    "sg:city":"Candor",
    "sg:classifiers":[
        {
            "category":"Food & Beverages",
            "subcategory":"Groceries & Convenience Stores",
            "type":"Retail Goods"
        }
    ],
    "sg:phone":"+1 910 974 7534",
    "sg:postcode":"27229",
    "sg:province":"NC",
    "wof:name":"Tienda Modelo",
    "wof:placetype":"venue"
},
  "geometry": {"coordinates":[-79.745723,35.294038],"type":"Point"}
}