{
  "type": "Feature",
  "properties": {
    "iso:country":"US",
    "sg:address":"5 Eastwood Rd",
    "sg:city":"Asheville",
    "sg:classifiers":[
        {
            "category":"Banks & Credit Unions",
            "subcategory":"Bank",
            "type":"Services"
        }
    ],
    "sg:phone":"+1 828 298 8711",
    "sg:postcode":"28803",
    "sg:province":"NC",
    "sg:tags":[
        "federal",
        "savings",
        "institution"
    ],
    "wof:name":"Asheville Savings Bank S S B",
    "wof:placetype":"venue"
},
  "geometry": {"coordinates":[-82.53038599999999,35.529443],"type":"Point"}
}