{
  "type": "Feature",
  "properties": {
    "addr:full":"101 Court Square Dr Lincolnton NC 28092",
    "addr:housenumber":"101",
    "addr:postcode":"28092",
    "addr:street":"Court Square Dr",
    "iso:country":"US",
    "sg:address":"101 Court Square Dr",
    "sg:city":"Lincolnton",
    "sg:classifiers":[
        {
            "category":"Professional",
            "subcategory":"Business Services",
            "type":"Services"
        }
    ],
    "sg:phone":"+1 704 735 9901",
    "sg:postcode":"28092",
    "sg:province":"NC",
    "sg:tags":[
        "paging",
        "answering"
    ],
    "wof:name":"Telephone Answering Svc",
    "wof:placetype":"venue"
},
  "geometry": {"coordinates":[-81.26377599999999,35.205299],"type":"Point"}
}