{
  "type": "Feature",
  "properties": {
    "addr:full":"2545 Zacks Farm Rd Lenoir NC 28645",
    "addr:housenumber":"2545",
    "addr:postcode":"28645",
    "addr:street":"Zacks Farm Rd",
    "iso:country":"US",
    "sg:address":"2545 Zacks Farm Rd",
    "sg:city":"Lenoir",
    "sg:classifiers":[
        {
            "category":"Building & Trades",
            "subcategory":"Construction",
            "type":"Services"
        }
    ],
    "sg:phone":"+1 828 758 4756",
    "sg:postcode":"28645",
    "sg:province":"NC",
    "sg:tags":[
        "house"
    ],
    "wof:name":"Arlen Kanagy Builder",
    "wof:placetype":"venue"
},
  "geometry": {"coordinates":[-81.490566,35.961541],"type":"Point"}
}