{
  "type": "Feature",
  "properties": {
    "addr:full":"300 N 3rd St Wilmington NC 28401",
    "addr:housenumber":"300",
    "addr:postcode":"28401",
    "addr:street":"N 3Rd St",
    "iso:country":"US",
    "sg:address":"300 N 3rd St",
    "sg:city":"Wilmington",
    "sg:classifiers":[
        {
            "category":"Professional",
            "subcategory":"Lawyer & Legal Services",
            "type":"Services"
        }
    ],
    "sg:phone":"+1 910 251 7001",
    "sg:postcode":"28401",
    "sg:province":"NC",
    "sg:tags":[
        "attorney"
    ],
    "wof:name":"Smith Moore LLP",
    "wof:placetype":"venue"
},
  "geometry": {"coordinates":[-77.94659799999999,34.240109],"type":"Point"}
}