{
  "type": "Feature",
  "properties": {
    "iso:country":"US",
    "sg:address":"6225 McIlwaine Rd",
    "sg:city":"Huntersville",
    "sg:classifiers":[
        {
            "category":"Professional",
            "type":"Services"
        }
    ],
    "sg:phone":"+1 704 947 7835",
    "sg:postcode":"28078",
    "sg:province":"NC",
    "wof:name":"Leslie H Mullins",
    "wof:placetype":"venue"
},
  "geometry": {"coordinates":[-80.928231,35.385183],"type":"Point"}
}