{
  "type": "Feature",
  "properties": {
    "iso:country":"US",
    "sg:address":"3025 Big Daddy's Rd",
    "sg:city":"Pikeville",
    "sg:classifiers":[
        {
            "category":"Farming",
            "subcategory":"Farm",
            "type":"Manufacturing & Wholesale Goods"
        }
    ],
    "sg:phone":"+1 919 242 8941",
    "sg:postcode":"27863",
    "sg:province":"NC",
    "sg:tags":[
        "crop",
        "general"
    ],
    "wof:name":"Brent A Tyndall",
    "wof:placetype":"venue"
},
  "geometry": {"coordinates":[-77.853143,35.501644],"type":"Point"}
}