{
  "type": "Feature",
  "properties": {
    "addr:full":"962 Coventry Rd Kannapolis NC 28081",
    "addr:housenumber":"962",
    "addr:postcode":"28081",
    "addr:street":"Coventry Rd",
    "iso:country":"US",
    "sg:address":"962 Coventry Rd",
    "sg:city":"Kannapolis",
    "sg:classifiers":[
        {
            "category":"Retail",
            "subcategory":"Portrait Studio",
            "type":"Services"
        }
    ],
    "sg:phone":"+1 704 938 6542",
    "sg:postcode":"28081",
    "sg:province":"NC",
    "sg:tags":[
        "photographer"
    ],
    "wof:name":"P G Kiser Photography",
    "wof:placetype":"venue"
},
  "geometry": {"coordinates":[-80.635876,35.46177],"type":"Point"}
}