{
  "type": "Feature",
  "properties": {
    "iso:country":"US",
    "sg:address":"6200 Old Plank Rd",
    "sg:city":"High Point",
    "sg:classifiers":[
        {
            "category":"Real Estate",
            "subcategory":"Real Estate Agent",
            "type":"Services"
        }
    ],
    "sg:phone":"+1 336 882 4215",
    "sg:postcode":"27265",
    "sg:province":"NC",
    "wof:name":"Charles Bivens Realtor",
    "wof:placetype":"venue"
},
  "geometry": {"coordinates":[-80.04575800000001,36.003941],"type":"Point"}
}