{
  "type": "Feature",
  "properties": {
    "iso:country":"US",
    "sg:address":"318 US Hwy 70 E",
    "sg:city":"Selma",
    "sg:classifiers":[
        {
            "category":"Travel",
            "subcategory":"Hotels & Motels",
            "type":"Entertainment"
        }
    ],
    "sg:phone":"+1 919 965 3771",
    "sg:postcode":"27576",
    "sg:province":"NC",
    "wof:name":"Masters Inn",
    "wof:placetype":"venue"
},
  "geometry": {"coordinates":[-78.295001,35.521959],"type":"Point"}
}