{
  "type": "Feature",
  "properties": {
    "addr:full":"3604 Harrison St Kinston NC 28504",
    "addr:housenumber":"3604",
    "addr:postcode":"28504",
    "addr:street":"Harrison St",
    "iso:country":"US",
    "sg:address":"3604 Harrison St",
    "sg:city":"Kinston",
    "sg:classifiers":[
        {
            "category":"Building & Trades",
            "subcategory":"Construction",
            "type":"Services"
        }
    ],
    "sg:phone":"+1 252 523 4633",
    "sg:postcode":"28504",
    "sg:province":"NC",
    "sg:tags":[
        "dry wall",
        "contractor"
    ],
    "wof:name":"Heath's Drywall Contractors",
    "wof:placetype":"venue"
},
  "geometry": {"coordinates":[-77.637698,35.267709],"type":"Point"}
}