{
  "type": "Feature",
  "properties": {
    "iso:country":"US",
    "sg:address":"44 S Garden St",
    "sg:city":"Marion",
    "sg:classifiers":[
        {
            "category":"Insurance",
            "subcategory":"Insurance Agent",
            "type":"Services"
        }
    ],
    "sg:phone":"+1 828 659 8009",
    "sg:postcode":"28752",
    "sg:province":"NC",
    "wof:name":"Poole & Assoc Insurance Svc",
    "wof:placetype":"venue"
},
  "geometry": {"coordinates":[-82.00755599999999,35.683921],"type":"Point"}
}