{
  "type": "Feature",
  "properties": {
    "iso:country":"US",
    "sg:address":"4700 Hilltop Rd",
    "sg:city":"Greensboro",
    "sg:classifiers":[
        {
            "category":"Professional",
            "subcategory":"Business Services",
            "type":"Services"
        }
    ],
    "sg:phone":"+1   ",
    "sg:postcode":"27407",
    "sg:province":"NC",
    "wof:name":"Dhg Enterprises Inc",
    "wof:placetype":"venue"
},
  "geometry": {"coordinates":[-79.883444,36.034715],"type":"Point"}
}