{
  "type": "Feature",
  "properties": {
    "addr:full":"2892 Sandy Cross Rd Reidsville NC 27320",
    "addr:housenumber":"2892",
    "addr:postcode":"27320",
    "addr:street":"Sandy Cross Rd",
    "iso:country":"US",
    "sg:address":"2892 Sandy Cross Rd",
    "sg:city":"Reidsville",
    "sg:classifiers":[
        {
            "category":"Retail",
            "subcategory":"Auto Repair",
            "type":"Services"
        }
    ],
    "sg:phone":"+1   ",
    "sg:postcode":"27320",
    "sg:province":"NC",
    "sg:tags":[
        "general"
    ],
    "wof:name":"Roy B Cox Jr",
    "wof:placetype":"venue"
},
  "geometry": {"coordinates":[-79.785477,36.320185],"type":"Point"}
}