{
  "type": "Feature",
  "properties": {
    "addr:full":"714 Old Barn Cir Pilot Mountain NC 27041",
    "addr:housenumber":"714",
    "addr:postcode":"27041",
    "addr:street":"Old Barn Cir",
    "iso:country":"US",
    "sg:address":"714 Old Barn Cir",
    "sg:city":"Pilot Mountain",
    "sg:classifiers":[
        {
            "category":"Professional",
            "subcategory":"Computer Services",
            "type":"Services"
        }
    ],
    "sg:phone":"+1   ",
    "sg:postcode":"27041",
    "sg:province":"NC",
    "wof:name":"Computer Handyman",
    "wof:placetype":"venue"
},
  "geometry": {"coordinates":[-80.479247,36.38479],"type":"Point"}
}