{
  "type": "Feature",
  "properties": {
    "iso:country":"US",
    "sg:address":"253 W Kings Hwy",
    "sg:city":"Eden",
    "sg:classifiers":[
        {
            "category":"Insurance",
            "subcategory":"Insurance Agent",
            "type":"Services"
        }
    ],
    "sg:phone":"+1 336 623 9744",
    "sg:postcode":"27288",
    "sg:province":"NC",
    "sg:website":"www.westernsouthernlife.com",
    "wof:name":"Western-Southern Life Ins Co",
    "wof:placetype":"venue"
},
  "geometry": {"coordinates":[-79.746306,36.492292],"type":"Point"}
}