{
  "type": "Feature",
  "properties": {
    "iso:country":"US",
    "sg:address":"811 Brent Rd",
    "sg:city":"Raleigh",
    "sg:classifiers":[
        {
            "category":"Building & Trades",
            "subcategory":"Construction",
            "type":"Services"
        }
    ],
    "sg:phone":"+1 919 859 3280",
    "sg:postcode":"27606",
    "sg:province":"NC",
    "sg:tags":[
        "repairing",
        "remodeling",
        "contractor"
    ],
    "wof:name":"Commercial Kitchen Svc",
    "wof:placetype":"venue"
},
  "geometry": {"coordinates":[-78.696409,35.769471],"type":"Point"}
}