{
  "type": "Feature",
  "properties": {
    "addr:full":"3614 Murchison Rd Fayetteville NC 28311",
    "addr:postcode":"3614;28311",
    "addr:street":"Murchison Rd",
    "iso:country":"US",
    "sg:address":"3614 Murchison Rd",
    "sg:city":"Fayetteville",
    "sg:classifiers":[
        {
            "category":"Freight",
            "type":"Transportation"
        }
    ],
    "sg:phone":"+1 910 630 2311",
    "sg:postcode":"28311",
    "sg:province":"NC",
    "sg:tags":[
        "commercial",
        "storage"
    ],
    "wof:name":"American Flag Self Storage",
    "wof:placetype":"venue"
},
  "geometry": {"coordinates":[-78.91599600000001,35.097282],"type":"Point"}
}