{
  "type": "Feature",
  "properties": {
    "addr:full":"1811 Price Rd Eden NC 27288",
    "addr:housenumber":"1811",
    "addr:postcode":"27288",
    "addr:street":"Price Rd",
    "iso:country":"US",
    "sg:address":"1811 Price Rd",
    "sg:city":"Eden",
    "sg:classifiers":[
        {
            "category":"Building & Trades",
            "subcategory":"Construction",
            "type":"Services"
        }
    ],
    "sg:phone":"+1 336 623 7275",
    "sg:postcode":"27288",
    "sg:province":"NC",
    "sg:tags":[
        "house"
    ],
    "wof:name":"T&D Mobile Home Repair",
    "wof:placetype":"venue"
},
  "geometry": {"coordinates":[-79.798903,36.497276],"type":"Point"}
}