{
  "type": "Feature",
  "properties": {
    "addr:full":"102 N York St Windsor NC 27983",
    "addr:housenumber":"102",
    "addr:postcode":"27983",
    "addr:street":"N York St",
    "iso:country":"US",
    "sg:address":"102 N York St",
    "sg:city":"Windsor",
    "sg:classifiers":[
        {
            "category":"Government",
            "subcategory":"Office",
            "type":"Public Place"
        }
    ],
    "sg:phone":"+1 252 794 9402",
    "sg:postcode":"27983",
    "sg:province":"NC",
    "sg:tags":[
        "county"
    ],
    "wof:name":"Bertie County Arts Council",
    "wof:placetype":"venue"
},
  "geometry": {"coordinates":[-76.946793,36.00192],"type":"Point"}
}