{
  "type": "Feature",
  "properties": {
    "addr:full":"5244 State Hwy 43 S Greenville NC 27858",
    "addr:housenumber":"5244",
    "addr:postcode":"27858",
    "addr:street":"State Hwy 43 S",
    "iso:country":"US",
    "sg:address":"5244 State Hwy 43 S",
    "sg:city":"Greenville",
    "sg:classifiers":[
        {
            "category":"Food & Beverages",
            "subcategory":"Groceries & Convenience Stores",
            "type":"Retail Goods"
        }
    ],
    "sg:phone":"+1 252 756 6403",
    "sg:postcode":"27858",
    "sg:province":"NC",
    "sg:tags":[
        "grocer"
    ],
    "wof:name":"Hollywood Grocery & Grill",
    "wof:placetype":"venue"
},
  "geometry": {"coordinates":[-77.319154,35.523386],"type":"Point"}
}