{
  "type": "Feature",
  "properties": {
    "addr:full":"1047 Bragg Blvd Fayetteville NC 28301",
    "addr:housenumber":"1047",
    "addr:postcode":"28301",
    "addr:street":"Bragg Blvd",
    "iso:country":"US",
    "sg:address":"1047 Bragg Blvd",
    "sg:city":"Fayetteville",
    "sg:classifiers":[
        {
            "category":"Wholesale",
            "subcategory":"Durable Goods & Equipment",
            "type":"Manufacturing & Wholesale Goods"
        }
    ],
    "sg:phone":"+1 910 323 4000",
    "sg:postcode":"28301",
    "sg:province":"NC",
    "sg:tags":[
        "supply"
    ],
    "wof:name":"Extreme Auto",
    "wof:placetype":"venue"
},
  "geometry": {"coordinates":[-78.89706,35.065021],"type":"Point"}
}