{
  "type": "Feature",
  "properties": {
    "iso:country":"US",
    "sg:address":"3679 N Halifax Rd",
    "sg:city":"Rocky Mount",
    "sg:classifiers":[
        {
            "category":"Professional",
            "type":"Services"
        }
    ],
    "sg:phone":"+1 252 443 1400",
    "sg:postcode":"27804",
    "sg:province":"NC",
    "wof:name":"Stretch A Dollar",
    "wof:placetype":"venue"
},
  "geometry": {"coordinates":[-77.857196,36.016469],"type":"Point"}
}