{
  "type": "Feature",
  "properties": {
    "addr:full":"2614 Spring Glen Ave Charlotte NC 28212",
    "addr:housenumber":"2614",
    "addr:postcode":"28212",
    "addr:street":"Spring Glen Ave",
    "iso:country":"US",
    "sg:address":"2614 Spring Glen Ave",
    "sg:city":"Charlotte",
    "sg:classifiers":[
        {
            "category":"Personal",
            "subcategory":"Beauty Salon",
            "type":"Services"
        }
    ],
    "sg:phone":"+1   ",
    "sg:postcode":"28212",
    "sg:province":"NC",
    "sg:tags":[
        "shop"
    ],
    "wof:name":"Commonwealth Salon",
    "wof:placetype":"venue"
},
  "geometry": {"coordinates":[-80.741041,35.182682],"type":"Point"}
}