{
  "type": "Feature",
  "properties": {
    "addr:full":"279 W State Hwy 54 Durham NC 27713",
    "addr:housenumber":"279",
    "addr:postcode":"27713",
    "addr:street":"W State Hwy 54",
    "iso:country":"US",
    "sg:address":"279 W State Hwy 54",
    "sg:city":"Durham",
    "sg:classifiers":[
        {
            "category":"Shopping",
            "subcategory":"Computers & Home Electronics",
            "type":"Retail Goods"
        }
    ],
    "sg:phone":"+1 919 544 9043",
    "sg:postcode":"27713",
    "sg:province":"NC",
    "sg:tags":[
        "accessory"
    ],
    "wof:name":"Tri-Met Computers Inc",
    "wof:placetype":"venue"
},
  "geometry": {"coordinates":[-78.93987199999999,35.911005],"type":"Point"}
}