{
  "type": "Feature",
  "properties": {
    "addr:full":"1208 Lincolnton Rd Salisbury NC 28147",
    "addr:housenumber":"1208",
    "addr:postcode":"28147",
    "addr:street":"Lincolnton Rd",
    "iso:country":"US",
    "sg:address":"1208 Lincolnton Rd",
    "sg:city":"Salisbury",
    "sg:classifiers":[
        {
            "category":"Sports & Exercise",
            "subcategory":"Gym",
            "type":"Entertainment"
        }
    ],
    "sg:phone":"+1 704 216 9622",
    "sg:postcode":"28147",
    "sg:province":"NC",
    "sg:tags":[
        "club",
        "health",
        "studio",
        "gymnasium"
    ],
    "wof:name":"YMCA Of Rowan County",
    "wof:placetype":"venue"
},
  "geometry": {"coordinates":[-80.499281,35.664477],"type":"Point"}
}