{
  "type": "Feature",
  "properties": {
    "addr:full":"2120 Highsmith Rd Burgaw NC 28425",
    "addr:housenumber":"2120",
    "addr:postcode":"28425",
    "addr:street":"Highsmith Rd",
    "iso:country":"US",
    "sg:address":"2120 Highsmith Rd",
    "sg:city":"Burgaw",
    "sg:classifiers":[
        {
            "category":"Professional",
            "type":"Services"
        }
    ],
    "sg:phone":"+1 910 259 4485",
    "sg:postcode":"28425",
    "sg:province":"NC",
    "sg:tags":[
        "establishment"
    ],
    "sg:website":"www.mschelp.com",
    "wof:name":"Coastal Instrument & Electrncs",
    "wof:placetype":"venue"
},
  "geometry": {"coordinates":[-77.935771,34.521806],"type":"Point"}
}