{
  "type": "Feature",
  "properties": {
    "iso:country":"US",
    "sg:address":"11 Price Rd",
    "sg:city":"Lexington",
    "sg:classifiers":[
        {
            "category":"Retail",
            "subcategory":"Auto Repair",
            "type":"Services"
        }
    ],
    "sg:phone":"+1   ",
    "sg:postcode":"27295",
    "sg:province":"NC",
    "sg:tags":[
        "general"
    ],
    "wof:name":"Wards Automotive Center",
    "wof:placetype":"venue"
},
  "geometry": {"coordinates":[-80.25532800000001,35.847556],"type":"Point"}
}