{
  "type": "Feature",
  "properties": {
    "addr:full":"1625 Miller Rd China Grove NC 28023",
    "addr:housenumber":"1625",
    "addr:postcode":"28023",
    "addr:street":"Miller Rd",
    "iso:country":"US",
    "sg:address":"1625 Miller Rd",
    "sg:city":"China Grove",
    "sg:classifiers":[
        {
            "category":"Building & Trades",
            "subcategory":"Construction",
            "type":"Services"
        }
    ],
    "sg:phone":"+1 704 857 6622",
    "sg:postcode":"28023",
    "sg:province":"NC",
    "sg:tags":[
        "general",
        "commercial",
        "contractor"
    ],
    "wof:name":"Speck Builders Inc",
    "wof:placetype":"venue"
},
  "geometry": {"coordinates":[-80.590862,35.599692],"type":"Point"}
}