{
  "type": "Feature",
  "properties": {
    "iso:country":"US",
    "sg:address":"840 Robeson St",
    "sg:city":"Fayetteville",
    "sg:classifiers":[
        {
            "category":"Insurance",
            "subcategory":"Insurance Agent",
            "type":"Services"
        }
    ],
    "sg:phone":"+1 910 323 3740",
    "sg:postcode":"28305",
    "sg:province":"NC",
    "wof:name":"Blake Donna Agency Inc",
    "wof:placetype":"venue"
},
  "geometry": {"coordinates":[-78.89646999999999,35.042065],"type":"Point"}
}