{
  "type": "Feature",
  "properties": {
    "addr:full":"4325 Glenwood Ave Raleigh NC 27612",
    "addr:housenumber":"4325",
    "addr:postcode":"27612",
    "addr:street":"Glenwood Ave",
    "iso:country":"US",
    "sg:address":"4325 Glenwood Ave",
    "sg:city":"Raleigh",
    "sg:classifiers":[
        {
            "category":"Bakery",
            "type":"Food & Drink"
        }
    ],
    "sg:menulink":"http://www.allmenus.com/nc/house-creek/106002-panera-bread/menu/",
    "sg:phone":"+1 919 785 9093",
    "sg:postcode":"27612",
    "sg:province":"NC",
    "sg:tags":[
        "american",
        "sandwich",
        "pastry"
    ],
    "wof:name":"Panera Bread",
    "wof:placetype":"venue"
},
  "geometry": {"coordinates":[-78.679022,35.83932],"type":"Point"}
}