{
  "type": "Feature",
  "properties": {
    "iso:country":"US",
    "sg:address":"7251 Pineville-Matthews Rd",
    "sg:city":"Charlotte",
    "sg:classifiers":[
        {
            "category":"Professional",
            "subcategory":"Management & Consulting",
            "type":"Services"
        }
    ],
    "sg:phone":"+1 704 543 7500",
    "sg:postcode":"28226",
    "sg:province":"NC",
    "sg:tags":[
        "employee",
        "consultant",
        "benefit"
    ],
    "wof:name":"Benefits Department",
    "wof:placetype":"venue"
},
  "geometry": {"coordinates":[-80.838655,35.087019],"type":"Point"}
}