{
  "type": "Feature",
  "properties": {
    "iso:country":"US",
    "sg:address":"1139 Virginia Blvd",
    "sg:city":"Murfreesboro",
    "sg:classifiers":[
        {
            "category":"Restaurant",
            "type":"Food & Drink"
        }
    ],
    "sg:phone":"+1 252 396 0771",
    "sg:postcode":"27855",
    "sg:province":"NC",
    "sg:tags":[
        "eating"
    ],
    "wof:name":"C & J's Country Cooking",
    "wof:placetype":"venue"
},
  "geometry": {"coordinates":[-77.086136,36.443979],"type":"Point"}
}