{
  "type": "Feature",
  "properties": {
    "addr:full":"7311 Mill Grove Rd Indian Trail NC 28079",
    "addr:housenumber":"7311",
    "addr:postcode":"28079",
    "addr:street":"Mill Grove Rd",
    "iso:country":"US",
    "sg:address":"7311 Mill Grove Rd",
    "sg:city":"Indian Trail",
    "sg:classifiers":[
        {
            "category":"Organizations",
            "subcategory":"Religious Organization",
            "type":"Services"
        }
    ],
    "sg:phone":"+1 704 882 2151",
    "sg:postcode":"28079",
    "sg:province":"NC",
    "sg:tags":[
        "church"
    ],
    "wof:name":"Zion United Methodist Church",
    "wof:placetype":"venue"
},
  "geometry": {"coordinates":[-80.602974,35.124807],"type":"Point"}
}