{
  "type": "Feature",
  "properties": {
    "iso:country":"US",
    "sg:address":"345 W Spring St",
    "sg:city":"Seven Springs",
    "sg:classifiers":[
        {
            "category":"Manufacturing",
            "subcategory":"Furniture",
            "type":"Manufacturing & Wholesale Goods"
        }
    ],
    "sg:phone":"+1 919 778 9488",
    "sg:postcode":"28578",
    "sg:province":"NC",
    "sg:tags":[
        "building",
        "public",
        "mfg"
    ],
    "wof:name":"East Dist Office",
    "wof:placetype":"venue"
},
  "geometry": {"coordinates":[-77.85502099999999,35.221453],"type":"Point"}
}