{
  "type": "Feature",
  "properties": {
    "iso:country":"US",
    "sg:address":"1598 State Hwy 56",
    "sg:city":"Creedmoor",
    "sg:classifiers":[
        {
            "category":"Professional",
            "subcategory":"Employment Agencies",
            "type":"Services"
        }
    ],
    "sg:phone":"+1 919 528 9742",
    "sg:postcode":"27522",
    "sg:province":"NC",
    "sg:tags":[
        "help",
        "supply"
    ],
    "wof:name":"Manpower",
    "wof:placetype":"venue"
},
  "geometry": {"coordinates":[-78.722109,36.14438],"type":"Point"}
}