{
  "type": "Feature",
  "properties": {
    "addr:full":"5101 Elevation Rd Benson NC 27504",
    "addr:housenumber":"5101",
    "addr:postcode":"27504",
    "addr:street":"Elevation Rd",
    "iso:country":"US",
    "sg:address":"5101 Elevation Rd",
    "sg:city":"Benson",
    "sg:classifiers":[
        {
            "category":"Organizations",
            "subcategory":"Religious Organization",
            "type":"Services"
        }
    ],
    "sg:phone":"+1   ",
    "sg:postcode":"27504",
    "sg:province":"NC",
    "wof:name":"Elevation Methodist Church",
    "wof:placetype":"venue"
},
  "geometry": {"coordinates":[-78.547668,35.446549],"type":"Point"}
}