{
  "type": "Feature",
  "properties": {
    "addr:full":"1800 Westridge Rd Greensboro NC 27410",
    "addr:housenumber":"1800",
    "addr:postcode":"27410",
    "addr:street":"Westridge Rd",
    "iso:country":"US",
    "sg:address":"1800 Westridge Rd",
    "sg:city":"Greensboro",
    "sg:classifiers":[
        {
            "category":"Social Services",
            "subcategory":"Child Care",
            "type":"Services"
        },
        {
            "category":"Social Services",
            "type":"Services"
        }
    ],
    "sg:phone":"+1 336 288 8971",
    "sg:postcode":"27410",
    "sg:province":"NC",
    "wof:name":"Shorty's Home Daycare",
    "wof:placetype":"venue"
},
  "geometry": {"coordinates":[-79.844751,36.118477],"type":"Point"}
}