{
  "type": "Feature",
  "properties": {
    "iso:country":"US",
    "sg:address":"1302 Legacy Ln",
    "sg:city":"Wilmington",
    "sg:classifiers":[
        {
            "category":"Shopping",
            "subcategory":"Discount & Variety Stores",
            "type":"Retail Goods"
        }
    ],
    "sg:phone":"+1 910 686 2661",
    "sg:postcode":"28411",
    "sg:province":"NC",
    "sg:tags":[
        "merchandise",
        "general"
    ],
    "wof:name":"Laurel Lea Sales Office",
    "wof:placetype":"venue"
},
  "geometry": {"coordinates":[-77.764306,34.282549],"type":"Point"}
}