{
  "type": "Feature",
  "properties": {
    "addr:full":"1001 Airport Blvd Ste 300 Morrisville NC 27560",
    "addr:housenumber":"1001",
    "addr:postcode":"27560",
    "addr:street":"Airport Blvd Ste 300",
    "iso:country":"US",
    "sg:address":"1001 Airport Blvd Ste 300",
    "sg:city":"Morrisville",
    "sg:classifiers":[
        {
            "category":"Shopping",
            "subcategory":"Clothing, Apparel, & Fashions",
            "type":"Retail Goods"
        },
        {
            "category":"Shopping",
            "subcategory":"Discount & Variety Stores",
            "type":"Retail Goods"
        }
    ],
    "sg:phone":"+1 919 469 9700",
    "sg:postcode":"27560",
    "sg:province":"NC",
    "sg:tags":[
        "accessory",
        "clothing",
        "outlet",
        "women's"
    ],
    "wof:name":"Tanner Factory Store",
    "wof:placetype":"venue"
},
  "geometry": {"coordinates":[-78.819397,35.859299],"type":"Point"}
}