{
  "type": "Feature",
  "properties": {
    "iso:country":"US",
    "sg:address":"106 Murray Manor Ln",
    "sg:city":"Rockingham",
    "sg:classifiers":[
        {
            "category":"Social Services",
            "subcategory":"Child Care",
            "type":"Services"
        }
    ],
    "sg:phone":"+1 910 997 3080",
    "sg:postcode":"28379",
    "sg:province":"NC",
    "wof:name":"Murray Manor Kidz Rezort",
    "wof:placetype":"venue"
},
  "geometry": {"coordinates":[-79.787138,34.972576],"type":"Point"}
}