{
  "type": "Feature",
  "properties": {
    "iso:country":"US",
    "sg:address":"969 Old Durham Rd",
    "sg:city":"Roxboro",
    "sg:classifiers":[
        {
            "category":"Home & Garden",
            "subcategory":"Garden Supply",
            "type":"Retail Goods"
        }
    ],
    "sg:phone":"+1 336 599 8398",
    "sg:postcode":"27573",
    "sg:province":"NC",
    "sg:tags":[
        "lawn"
    ],
    "wof:name":"Rolling Hills Garden Supply",
    "wof:placetype":"venue"
},
  "geometry": {"coordinates":[-78.97861,36.36716],"type":"Point"}
}