{
  "type": "Feature",
  "properties": {
    "iso:country":"US",
    "sg:address":"1206 Fairgrove Church Rd",
    "sg:city":"Hickory",
    "sg:classifiers":[
        {
            "category":"Organizations",
            "subcategory":"Non-profit Organization",
            "type":"Services"
        }
    ],
    "sg:phone":"+1 828 464 1172",
    "sg:postcode":"28602",
    "sg:province":"NC",
    "sg:tags":[
        "info",
        "addiction",
        "abuse",
        "treatment",
        "drug"
    ],
    "sg:website":"www.mcleodcenter.com",
    "wof:name":"Mc Leod Ctr",
    "wof:placetype":"venue"
},
  "geometry": {"coordinates":[-81.26449700000001,35.70939],"type":"Point"}
}