{
  "type": "Feature",
  "properties": {
    "addr:full":"1424 Cross Beam Dr Charlotte NC 28217",
    "addr:housenumber":"1424",
    "addr:postcode":"28217",
    "addr:street":"Cross Beam Dr",
    "iso:country":"US",
    "sg:address":"1424 Cross Beam Dr",
    "sg:city":"Charlotte",
    "sg:classifiers":[
        {
            "category":"Wholesale",
            "subcategory":"Durable Goods & Equipment",
            "type":"Manufacturing & Wholesale Goods"
        }
    ],
    "sg:phone":"+1 704 357 8710",
    "sg:postcode":"28217",
    "sg:province":"NC",
    "sg:tags":[
        "importer"
    ],
    "wof:name":"Geo Logistics America Inc",
    "wof:placetype":"venue"
},
  "geometry": {"coordinates":[-80.923264,35.179705],"type":"Point"}
}