{
  "type": "Feature",
  "properties": {
    "iso:country":"US",
    "sg:address":"865 Craigmont Ln NW",
    "sg:city":"Concord",
    "sg:classifiers":[
        {
            "category":"Real Estate",
            "subcategory":"Architect",
            "type":"Services"
        }
    ],
    "sg:phone":"+1   ",
    "sg:postcode":"28027",
    "sg:province":"NC",
    "sg:tags":[
        "architectural"
    ],
    "wof:name":"Dialect LLC",
    "wof:placetype":"venue"
},
  "geometry": {"coordinates":[-80.673339,35.401793],"type":"Point"}
}