{
  "type": "Feature",
  "properties": {
    "addr:full":"1768 Savannah Rd Tabor City NC 28463",
    "addr:housenumber":"1768",
    "addr:postcode":"28463",
    "addr:street":"Savannah Rd",
    "iso:country":"US",
    "sg:address":"1768 Savannah Rd",
    "sg:city":"Tabor City",
    "sg:classifiers":[
        {
            "category":"Manufacturing",
            "subcategory":"Lumber",
            "type":"Manufacturing & Wholesale Goods"
        }
    ],
    "sg:phone":"+1 910 653 5186",
    "sg:postcode":"28463",
    "sg:province":"NC",
    "sg:tags":[
        "logging"
    ],
    "wof:name":"Roger Suggs Logging",
    "wof:placetype":"venue"
},
  "geometry": {"coordinates":[-78.68490199999999,34.042758],"type":"Point"}
}