{
  "type": "Feature",
  "properties": {
    "addr:full":"292 Beech Retreat Dr Lexington NC 27292",
    "addr:housenumber":"292",
    "addr:postcode":"27292",
    "addr:street":"Beech Retreat Dr",
    "iso:country":"US",
    "sg:address":"292 Beech Retreat Dr",
    "sg:city":"Lexington",
    "sg:classifiers":[
        {
            "category":"Building & Trades",
            "subcategory":"Electrical",
            "type":"Services"
        }
    ],
    "sg:phone":"+1 336 798 3674",
    "sg:postcode":"27292",
    "sg:province":"NC",
    "sg:tags":[
        "electrical",
        "contractor"
    ],
    "wof:name":"Jsm Electric Inc",
    "wof:placetype":"venue"
},
  "geometry": {"coordinates":[-80.25002499999999,35.689818],"type":"Point"}
}