{
  "type": "Feature",
  "properties": {
    "iso:country":"US",
    "sg:address":"7212 Brown Summit Rd",
    "sg:city":"Browns Summit",
    "sg:classifiers":[
        {
            "category":"Retail",
            "subcategory":"Auto Repair",
            "type":"Services"
        }
    ],
    "sg:phone":"+1   ",
    "sg:postcode":"27214",
    "sg:province":"NC",
    "sg:tags":[
        "general"
    ],
    "wof:name":"Preferred Auto Care",
    "wof:placetype":"venue"
},
  "geometry": {"coordinates":[-79.71397,36.208067],"type":"Point"}
}