{
  "type": "Feature",
  "properties": {
    "iso:country":"US",
    "sg:address":"824 E King St",
    "sg:city":"Kings Mountain",
    "sg:classifiers":[
        {
            "category":"Manufacturing",
            "subcategory":"Printing",
            "type":"Manufacturing & Wholesale Goods"
        }
    ],
    "sg:phone":"+1 704 739 7496",
    "sg:postcode":"28086",
    "sg:province":"NC",
    "sg:tags":[
        "newspaper"
    ],
    "wof:name":"Kings Mountain Herald",
    "wof:placetype":"venue"
},
  "geometry": {"coordinates":[-81.328593,35.240759],"type":"Point"}
}