{
  "type": "Feature",
  "properties": {
    "iso:country":"US",
    "sg:address":"224 S Grove St",
    "sg:city":"Hendersonville",
    "sg:classifiers":[
        {
            "category":"Organizations",
            "subcategory":"Professional Association",
            "type":"Services"
        }
    ],
    "sg:phone":"+1   ",
    "sg:postcode":"28792",
    "sg:province":"NC",
    "sg:tags":[
        "business"
    ],
    "wof:name":"Global Commerce",
    "wof:placetype":"venue"
},
  "geometry": {"coordinates":[-82.45702300000001,35.313505],"type":"Point"}
}