{
  "type": "Feature",
  "properties": {
    "iso:country":"US",
    "sg:address":"11301 Smoke Tree Ln",
    "sg:city":"Charlotte",
    "sg:classifiers":[
        {
            "category":"Building & Trades",
            "subcategory":"Construction",
            "type":"Services"
        }
    ],
    "sg:phone":"+1 704 544 0645",
    "sg:postcode":"28226",
    "sg:province":"NC",
    "sg:tags":[
        "contractor"
    ],
    "wof:name":"Bogdans Construction Co",
    "wof:placetype":"venue"
},
  "geometry": {"coordinates":[-80.856639,35.069658],"type":"Point"}
}