{
  "type": "Feature",
  "properties": {
    "addr:full":"65 McCachern Blvd SE Concord NC 28025",
    "addr:housenumber":"65",
    "addr:postcode":"28025",
    "addr:street":"Mccachern Blvd Se",
    "iso:country":"US",
    "sg:address":"65 McCachern Blvd SE",
    "sg:city":"Concord",
    "sg:classifiers":[
        {
            "category":"Professional",
            "subcategory":"Lawyer & Legal Services",
            "type":"Services"
        }
    ],
    "sg:phone":"+1 704 788 3211",
    "sg:postcode":"28025",
    "sg:province":"NC",
    "sg:tags":[
        "attorney"
    ],
    "sg:website":"www.fspa.net",
    "wof:name":"Ferguson Scarbrough & Hayes",
    "wof:placetype":"venue"
},
  "geometry": {"coordinates":[-80.577139,35.410457],"type":"Point"}
}