{
  "type": "Feature",
  "properties": {
    "iso:country":"US",
    "sg:address":"800 N Poplar St",
    "sg:city":"Aberdeen",
    "sg:classifiers":[
        {
            "category":"Education",
            "subcategory":"Special Training",
            "type":"Public Place"
        }
    ],
    "sg:phone":"+1   ",
    "sg:postcode":"28315",
    "sg:province":"NC",
    "wof:name":"Nancy Arnold",
    "wof:placetype":"venue"
},
  "geometry": {"coordinates":[-79.419611,35.143207],"type":"Point"}
}