{
  "type": "Feature",
  "properties": {
    "addr:full":"1445 Patton Avenue Asheville NC 28806",
    "addr:housenumber":"1445",
    "addr:postcode":"28806",
    "addr:street":"Patton Avenue",
    "iso:country":"US",
    "sg:address":"1445 Patton Avenue",
    "sg:city":"Asheville",
    "sg:classifiers":[
        {
            "category":"Restaurant",
            "type":"Food & Drink"
        }
    ],
    "sg:phone":"+1 828 285 0940",
    "sg:postcode":"28806",
    "sg:province":"NC",
    "sg:tags":[
        "seafood"
    ],
    "wof:name":"Fisherman's Quarters II",
    "wof:placetype":"venue"
},
  "geometry": {"coordinates":[-82.60849899999999,35.579329],"type":"Point"}
}