{
  "type": "Feature",
  "properties": {
    "addr:full":"6001 Castlebrook Dr Raleigh NC 27604",
    "addr:housenumber":"6001",
    "addr:postcode":"27604",
    "addr:street":"Castlebrook Dr",
    "iso:country":"US",
    "sg:address":"6001 Castlebrook Dr",
    "sg:city":"Raleigh",
    "sg:classifiers":[
        {
            "category":"Retail",
            "subcategory":"Repair Shop",
            "type":"Services"
        }
    ],
    "sg:phone":"+1 919 981 0722",
    "sg:postcode":"27604",
    "sg:province":"NC",
    "sg:tags":[
        "plumbing",
        "drain",
        "cleaning",
        "sewer"
    ],
    "wof:name":"Best Drainage Systems Inc",
    "wof:placetype":"venue"
},
  "geometry": {"coordinates":[-78.5478,35.829219],"type":"Point"}
}