{
  "type": "Feature",
  "properties": {
    "iso:country":"US",
    "sg:address":"216 S Main St",
    "sg:city":"Stanley",
    "sg:classifiers":[
        {
            "category":"Personal",
            "subcategory":"Tanning Parlor",
            "type":"Services"
        }
    ],
    "sg:phone":"+1 704 263 2010",
    "sg:postcode":"28164",
    "sg:province":"NC",
    "sg:tags":[
        "salon"
    ],
    "wof:name":"Dark Side",
    "wof:placetype":"venue"
},
  "geometry": {"coordinates":[-81.095213,35.358256],"type":"Point"}
}