{
  "type": "Feature",
  "properties": {
    "addr:full":"1115 Sharview Cir Charlotte NC 28217",
    "addr:housenumber":"1115",
    "addr:postcode":"28217",
    "addr:street":"Sharview Cir",
    "iso:country":"US",
    "sg:address":"1115 Sharview Cir",
    "sg:city":"Charlotte",
    "sg:classifiers":[
        {
            "category":"Autos & Motor Vehicles",
            "subcategory":"Automobile Sales",
            "type":"Retail Goods"
        }
    ],
    "sg:phone":"+1 704 586 0883",
    "sg:postcode":"28217",
    "sg:province":"NC",
    "sg:tags":[
        "used"
    ],
    "wof:name":"Autos On Demand",
    "wof:placetype":"venue"
},
  "geometry": {"coordinates":[-80.90049,35.161726],"type":"Point"}
}