{
  "type": "Feature",
  "properties": {
    "addr:full":"362 Northfield Dr King NC 27021",
    "addr:housenumber":"362",
    "addr:postcode":"27021",
    "addr:street":"Northfield Dr",
    "iso:country":"US",
    "sg:address":"362 Northfield Dr",
    "sg:city":"King",
    "sg:classifiers":[
        {
            "category":"Building & Trades",
            "subcategory":"Construction",
            "type":"Services"
        }
    ],
    "sg:phone":"+1 336 983 4988",
    "sg:postcode":"27021",
    "sg:province":"NC",
    "wof:name":"Road Runner Asphalt Maintenanc",
    "wof:placetype":"venue"
},
  "geometry": {"coordinates":[-80.328394,36.317878],"type":"Point"}
}