{
  "type": "Feature",
  "properties": {
    "iso:country":"US",
    "sg:address":"4110 Beatty Dr",
    "sg:city":"Charlotte",
    "sg:classifiers":[
        {
            "category":"Freight",
            "type":"Transportation"
        }
    ],
    "sg:phone":"+1 704 391 2604",
    "sg:postcode":"28214",
    "sg:province":"NC",
    "sg:tags":[
        "operator",
        "local",
        "trucking"
    ],
    "wof:name":"4 Ms Trucking Inc",
    "wof:placetype":"venue"
},
  "geometry": {"coordinates":[-81.00114600000001,35.235229],"type":"Point"}
}