{
  "type": "Feature",
  "properties": {
    "iso:country":"US",
    "sg:address":"4533 Gainesborough Rd",
    "sg:city":"Charlotte",
    "sg:classifiers":[
        {
            "category":"Building & Trades",
            "subcategory":"Cleaning & Sanitation",
            "type":"Services"
        }
    ],
    "sg:phone":"+1   ",
    "sg:postcode":"28205",
    "sg:province":"NC",
    "sg:tags":[
        "maintenance"
    ],
    "wof:name":"Rh and A General Maintena",
    "wof:placetype":"venue"
},
  "geometry": {"coordinates":[-80.75,35.225677],"type":"Point"}
}