{
  "type": "Feature",
  "properties": {
    "iso:country":"US",
    "sg:address":"1320 Ferguson Rd",
    "sg:city":"Chapel Hill",
    "sg:classifiers":[
        {
            "category":"Building & Trades",
            "subcategory":"Construction",
            "type":"Services"
        }
    ],
    "sg:phone":"+1 919 942 0029",
    "sg:postcode":"27516",
    "sg:province":"NC",
    "sg:tags":[
        "excavation",
        "contractor",
        "grading"
    ],
    "wof:name":"Baldwin Excavating",
    "wof:placetype":"venue"
},
  "geometry": {"coordinates":[-79.155709,35.894635],"type":"Point"}
}