{
  "type": "Feature",
  "properties": {
    "addr:full":"1548 Vance St Rocky Mount NC 27801",
    "addr:housenumber":"1548",
    "addr:postcode":"27801",
    "addr:street":"Vance St",
    "iso:country":"US",
    "sg:address":"1548 Vance St",
    "sg:city":"Rocky Mount",
    "sg:classifiers":[
        {
            "category":"Wholesale",
            "subcategory":"Beer",
            "type":"Manufacturing & Wholesale Goods"
        }
    ],
    "sg:phone":"+1 252 442 4447",
    "sg:postcode":"27801",
    "sg:province":"NC",
    "sg:tags":[
        "ale"
    ],
    "wof:name":"Dodd Distributing Co Inc",
    "wof:placetype":"venue"
},
  "geometry": {"coordinates":[-77.79779000000001,35.921137],"type":"Point"}
}