{
  "type": "Feature",
  "properties": {
    "iso:country":"US",
    "sg:address":"39 S Market St",
    "sg:city":"Asheville",
    "sg:classifiers":[
        {
            "category":"Recreation",
            "type":"Entertainment"
        }
    ],
    "sg:phone":"+1 828 252 4614",
    "sg:postcode":"28801",
    "sg:province":"NC",
    "sg:tags":[
        "amusement"
    ],
    "sg:website":"www.ymicc.org",
    "wof:name":"Ymi Cultural Ctr",
    "wof:placetype":"venue"
},
  "geometry": {"coordinates":[-82.550434,35.594867],"type":"Point"}
}