{
  "type": "Feature",
  "properties": {
    "iso:country":"US",
    "sg:address":"6260 Glenwood Ave",
    "sg:city":"Raleigh",
    "sg:phone":"+1 919 782 7776",
    "sg:postcode":"27612",
    "sg:province":"NC",
    "sg:website":"http://raleigh.citysearch.com/profile/external/6190844/raleigh_nc/dr_ronald_wahler_d_c_.html?publisher=yellowpages&reference_id=1&placement=ypwebsitemip",
    "wof:name":"Dr. Ronald Wahler, D.C.",
    "wof:placetype":"venue"
},
  "geometry": {"coordinates":[-78.703369,35.85685],"type":"Point"}
}