{
  "type": "Feature",
  "properties": {
    "iso:country":"US",
    "sg:address":"16 S College Ave",
    "sg:city":"Newton",
    "sg:classifiers":[
        {
            "category":"Government",
            "subcategory":"Police Station",
            "type":"Public Place"
        },
        {
            "category":"Professional",
            "subcategory":"Lawyer & Legal Services",
            "type":"Services"
        }
    ],
    "sg:phone":"+1 828 464 5871",
    "sg:postcode":"28658",
    "sg:province":"NC",
    "sg:tags":[
        "attorney",
        "law",
        "family",
        "divorce",
        "practice",
        "traffic",
        "criminal"
    ],
    "sg:website":"http://www.cutchlaw.com",
    "wof:name":"Cutchin, John F PA",
    "wof:placetype":"venue"
},
  "geometry": {"coordinates":[-81.221653,35.662498],"type":"Point"}
}