{
  "type": "Feature",
  "properties": {
    "addr:full":"114 Graceland Pikeville NC 27863",
    "addr:housenumber":"114",
    "addr:postcode":"27863",
    "addr:street":"Graceland",
    "iso:country":"US",
    "sg:address":"114 Graceland",
    "sg:city":"Pikeville",
    "sg:classifiers":[
        {
            "category":"Building & Trades",
            "subcategory":"Construction",
            "type":"Services"
        }
    ],
    "sg:phone":"+1 919 242 4669",
    "sg:postcode":"27863",
    "sg:province":"NC",
    "sg:tags":[
        "tile",
        "work",
        "terrazzo",
        "mosaic",
        "marble"
    ],
    "wof:name":"J Hardy Tile Co Inc",
    "wof:placetype":"venue"
},
  "geometry": {"coordinates":[-77.981037,35.511912],"type":"Point"}
}