{
  "type": "Feature",
  "properties": {
    "iso:country":"US",
    "sg:address":"6302 Glengarrie Ln",
    "sg:city":"Huntersville",
    "sg:classifiers":[
        {
            "category":"Professional",
            "subcategory":"Business Services",
            "type":"Services"
        }
    ],
    "sg:phone":"+1   ",
    "sg:postcode":"28078",
    "sg:province":"NC",
    "wof:name":"Dtn Service Associates",
    "wof:placetype":"venue"
},
  "geometry": {"coordinates":[-80.93294400000001,35.405935],"type":"Point"}
}