{
  "type": "Feature",
  "properties": {
    "iso:country":"US",
    "sg:address":"127 E H St",
    "sg:city":"Erwin",
    "sg:classifiers":[
        {
            "category":"Restaurant",
            "type":"Food & Drink"
        }
    ],
    "sg:phone":"+1 910 897 2850",
    "sg:postcode":"28339",
    "sg:province":"NC",
    "wof:name":"Peerless Cafe & Bakery",
    "wof:placetype":"venue"
},
  "geometry": {"coordinates":[-78.67565999999999,35.327793],"type":"Point"}
}