{
  "type": "Feature",
  "properties": {
    "iso:country":"US",
    "sg:address":"807 Post St",
    "sg:city":"Greensboro",
    "sg:classifiers":[
        {
            "category":"Professional",
            "subcategory":"Management & Consulting",
            "type":"Services"
        }
    ],
    "sg:phone":"+1   ",
    "sg:postcode":"27405",
    "sg:province":"NC",
    "wof:name":"North Carolina Property M",
    "wof:placetype":"venue"
},
  "geometry": {"coordinates":[-79.765052,36.083278],"type":"Point"}
}