{
  "type": "Feature",
  "properties": {
    "iso:country":"US",
    "sg:address":"18977 S State Hwy 109",
    "sg:city":"Denton",
    "sg:classifiers":[
        {
            "category":"Building & Trades",
            "subcategory":"Construction",
            "type":"Services"
        }
    ],
    "sg:phone":"+1 336 859 5017",
    "sg:postcode":"27239",
    "sg:province":"NC",
    "sg:tags":[
        "welding"
    ],
    "wof:name":"Markham Welding LLC",
    "wof:placetype":"venue"
},
  "geometry": {"coordinates":[-80.104731,35.618362],"type":"Point"}
}