{
  "type": "Feature",
  "properties": {
    "addr:full":"502 Georgetown Rd Jacksonville NC 28540",
    "addr:housenumber":"502",
    "addr:postcode":"28540",
    "addr:street":"Georgetown Rd",
    "iso:country":"US",
    "sg:address":"502 Georgetown Rd",
    "sg:city":"Jacksonville",
    "sg:classifiers":[
        {
            "category":"Organizations",
            "subcategory":"Religious Organization",
            "type":"Services"
        }
    ],
    "sg:phone":"+1 910 455 8712",
    "sg:postcode":"28540",
    "sg:province":"NC",
    "wof:name":"Evening Vw Mssn Baptst CHR Inc",
    "wof:placetype":"venue"
},
  "geometry": {"coordinates":[-77.440699,34.742233],"type":"Point"}
}