{
  "type": "Feature",
  "properties": {
    "addr:full":"448 Conover Blvd E Conover NC 28613",
    "addr:housenumber":"448",
    "addr:postcode":"28613",
    "addr:street":"Conover Blvd E Conover",
    "iso:country":"US",
    "sg:address":"448 Conover Blvd E",
    "sg:city":"Conover",
    "sg:classifiers":[
        {
            "category":"Home & Garden",
            "subcategory":"Home Furnishings",
            "type":"Retail Goods"
        }
    ],
    "sg:phone":"+1 828 324 6337",
    "sg:postcode":"28613",
    "sg:province":"NC",
    "wof:name":"Gallery of Lights",
    "wof:placetype":"venue"
},
  "geometry": {"coordinates":[-81.21196,35.702137],"type":"Point"}
}