{
  "type": "Feature",
  "properties": {
    "iso:country":"US",
    "sg:address":"2912 Peter Springs Dr",
    "sg:city":"Castle Hayne",
    "sg:classifiers":[
        {
            "category":"Real Estate",
            "subcategory":"Real Estate Agent",
            "type":"Services"
        }
    ],
    "sg:phone":"+1 910 675 8973",
    "sg:postcode":"28429",
    "sg:province":"NC",
    "wof:name":"Mlc Appraisal Co",
    "wof:placetype":"venue"
},
  "geometry": {"coordinates":[-77.908924,34.333134],"type":"Point"}
}