{
  "type": "Feature",
  "properties": {
    "iso:country":"US",
    "sg:address":"1819 Lyndhurst Ave",
    "sg:city":"Charlotte",
    "sg:classifiers":[
        {
            "category":"Health Services",
            "subcategory":"Doctor",
            "type":"Services"
        }
    ],
    "sg:phone":"+1 704 376 0550",
    "sg:postcode":"28203",
    "sg:province":"NC",
    "sg:tags":[
        "physician",
        "surgeon"
    ],
    "wof:name":"Judithm Thorne MD",
    "wof:placetype":"venue"
},
  "geometry": {"coordinates":[-80.855124,35.208324],"type":"Point"}
}