{
  "type": "Feature",
  "properties": {
    "iso:country":"US",
    "sg:address":"3124 Eastway Dr",
    "sg:city":"Charlotte",
    "sg:classifiers":[
        {
            "category":"Restaurant",
            "type":"Food & Drink"
        }
    ],
    "sg:menulink":"http://www.allmenus.com/nc/charlotte/62051-little--china-restaurant/menu/",
    "sg:phone":"+1 704 537 1700",
    "sg:postcode":"28205",
    "sg:province":"NC",
    "sg:tags":[
        "asian",
        "chinese"
    ],
    "wof:name":"Little  China-Restaurant",
    "wof:placetype":"venue"
},
  "geometry": {"coordinates":[-80.78368399999999,35.212433],"type":"Point"}
}