{
  "type": "Feature",
  "properties": {
    "addr:full":"9 Adams St NE Concord NC 28025",
    "addr:housenumber":"9",
    "addr:postcode":"28025",
    "addr:street":"Adams St Ne",
    "iso:country":"US",
    "sg:address":"9 Adams St NE",
    "sg:city":"Concord",
    "sg:classifiers":[
        {
            "category":"Shopping",
            "subcategory":"Computers & Home Electronics",
            "type":"Retail Goods"
        }
    ],
    "sg:phone":"+1 704 784 1793",
    "sg:postcode":"28025",
    "sg:province":"NC",
    "wof:name":"PC Workstations",
    "wof:placetype":"venue"
},
  "geometry": {"coordinates":[-80.57472300000001,35.416926],"type":"Point"}
}