{
  "type": "Feature",
  "properties": {
    "addr:full":"680 Hanes Mall Blvd Winston Salem NC 27103",
    "addr:housenumber":"680",
    "addr:postcode":"27103",
    "addr:street":"Hanes Mall Blvd",
    "iso:country":"US",
    "sg:address":"680 Hanes Mall Blvd",
    "sg:city":"Winston Salem",
    "sg:classifiers":[
        {
            "category":"Professional",
            "type":"Services"
        }
    ],
    "sg:phone":"+1 336 659 1465",
    "sg:postcode":"27103",
    "sg:province":"NC",
    "sg:tags":[
        "establishment"
    ],
    "wof:name":"Dial Page Of The Triad Inc",
    "wof:placetype":"venue"
},
  "geometry": {"coordinates":[-80.301108,36.063834],"type":"Point"}
}