{
  "type": "Feature",
  "properties": {
    "iso:country":"US",
    "sg:address":"201 E Davie St",
    "sg:city":"Raleigh",
    "sg:classifiers":[
        {
            "category":"Professional",
            "subcategory":"Detective & Security Services",
            "type":"Services"
        }
    ],
    "sg:phone":"+1 919 838 0755",
    "sg:postcode":"27601",
    "sg:province":"NC",
    "sg:tags":[
        "information",
        "bureau"
    ],
    "sg:website":"http://www.mcraystudios.com",
    "wof:name":"Mcray Studios",
    "wof:placetype":"venue"
},
  "geometry": {"coordinates":[-78.636719,35.775501],"type":"Point"}
}