{
  "type": "Feature",
  "properties": {
    "iso:country":"US",
    "sg:address":"2740 Gray Fox Rd",
    "sg:city":"Monroe",
    "sg:classifiers":[
        {
            "category":"Manufacturing",
            "subcategory":"Chemicals & Compounds",
            "type":"Manufacturing & Wholesale Goods"
        }
    ],
    "sg:phone":"+1 704 752 0031",
    "sg:postcode":"28110",
    "sg:province":"NC",
    "wof:name":"Clift Industries",
    "wof:placetype":"venue"
},
  "geometry": {"coordinates":[-80.626244,35.055858],"type":"Point"}
}