{
  "type": "Feature",
  "properties": {
    "addr:full":"2207 Shoreham St Durham NC 27707",
    "addr:housenumber":"2207",
    "addr:postcode":"27707",
    "addr:street":"Shoreham St",
    "iso:country":"US",
    "sg:address":"2207 Shoreham St",
    "sg:city":"Durham",
    "sg:classifiers":[
        {
            "category":"Social Services",
            "subcategory":"Child Care",
            "type":"Services"
        }
    ],
    "sg:phone":"+1   ",
    "sg:postcode":"27707",
    "sg:province":"NC",
    "sg:tags":[
        "day"
    ],
    "wof:name":"A Brilliant Beginning Early",
    "wof:placetype":"venue"
},
  "geometry": {"coordinates":[-78.921693,35.974295],"type":"Point"}
}