{
  "type": "Feature",
  "properties": {
    "iso:country":"US",
    "sg:address":"754 Baker Dr",
    "sg:city":"Haw River",
    "sg:classifiers":[
        {
            "category":"Freight",
            "type":"Transportation"
        }
    ],
    "sg:phone":"+1 336 578 5020",
    "sg:postcode":"27258",
    "sg:province":"NC",
    "sg:tags":[
        "operator",
        "trucking"
    ],
    "wof:name":"Jmac & Co Inc",
    "wof:placetype":"venue"
},
  "geometry": {"coordinates":[-79.333597,36.078168],"type":"Point"}
}