{
  "type": "Feature",
  "properties": {
    "iso:country":"US",
    "sg:address":"3141 Piper Ln",
    "sg:city":"Charlotte",
    "sg:classifiers":[
        {
            "category":"Personal",
            "subcategory":"Beauty Salon",
            "type":"Services"
        }
    ],
    "sg:phone":"+1 704 357 1289",
    "sg:postcode":"28208",
    "sg:province":"NC",
    "sg:tags":[
        "shop"
    ],
    "wof:name":"Judy's Hair Designs",
    "wof:placetype":"venue"
},
  "geometry": {"coordinates":[-80.927643,35.194662],"type":"Point"}
}