{
  "type": "Feature",
  "properties": {
    "iso:country":"US",
    "sg:address":"2304 Estes Rd",
    "sg:city":"Ruffin",
    "sg:phone":"+1 336 939 2940",
    "sg:postcode":"27320",
    "sg:province":"NC",
    "sg:tags":[
        "farm",
        "tobacco"
    ],
    "wof:name":"Harold Page",
    "wof:placetype":"venue"
},
  "geometry": {"coordinates":[-79.62929699999999,36.437358],"type":"Point"}
}