{
  "type": "Feature",
  "properties": {
    "addr:full":"1476 Bird Cage Rd Chadbourn NC 28431",
    "addr:housenumber":"1476",
    "addr:postcode":"28431",
    "addr:street":"Bird Cage Rd",
    "iso:country":"US",
    "sg:address":"1476 Bird Cage Rd",
    "sg:city":"Chadbourn",
    "sg:classifiers":[
        {
            "category":"Organizations",
            "subcategory":"Religious Organization",
            "type":"Services"
        }
    ],
    "sg:phone":"+1 910 653 9284",
    "sg:postcode":"28431",
    "sg:province":"NC",
    "sg:tags":[
        "church"
    ],
    "wof:name":"Pentecostal Free-Will Bapt Chr",
    "wof:placetype":"venue"
},
  "geometry": {"coordinates":[-78.839795,34.349627],"type":"Point"}
}