{
  "type": "Feature",
  "properties": {
    "addr:full":"317 Apollo Dr Wilmington NC 28405",
    "addr:housenumber":"317",
    "addr:postcode":"28405",
    "addr:street":"Apollo Dr",
    "iso:country":"US",
    "sg:address":"317 Apollo Dr",
    "sg:city":"Wilmington",
    "sg:classifiers":[
        {
            "category":"Building & Trades",
            "subcategory":"Construction",
            "type":"Services"
        }
    ],
    "sg:phone":"+1 910 350 1281",
    "sg:postcode":"28405",
    "sg:province":"NC",
    "sg:tags":[
        "concrete",
        "contractor"
    ],
    "wof:name":"Carolina Concrete Paving Co",
    "wof:placetype":"venue"
},
  "geometry": {"coordinates":[-77.837626,34.250599],"type":"Point"}
}