{
  "type": "Feature",
  "properties": {
    "addr:full":"7268 Harris Rd Bailey NC 27807",
    "addr:housenumber":"7268",
    "addr:postcode":"27807",
    "addr:street":"Harris Rd",
    "iso:country":"US",
    "sg:address":"7268 Harris Rd",
    "sg:city":"Bailey",
    "sg:classifiers":[
        {
            "category":"Wholesale",
            "subcategory":"Jewelry",
            "type":"Manufacturing & Wholesale Goods"
        }
    ],
    "sg:phone":"+1 252 235 3467",
    "sg:postcode":"27807",
    "sg:province":"NC",
    "sg:tags":[
        "stone"
    ],
    "wof:name":"Judith F Jones",
    "wof:placetype":"venue"
},
  "geometry": {"coordinates":[-78.116484,35.826277],"type":"Point"}
}