{
  "type": "Feature",
  "properties": {
    "iso:country":"US",
    "sg:address":"300 Dominion Dr Suite 425",
    "sg:city":"Morrisville",
    "sg:classifiers":[
        {
            "category":"Recreation",
            "subcategory":"Playground",
            "type":"Entertainment"
        }
    ],
    "sg:phone":"+1 919 459 1459",
    "sg:postcode":"27560",
    "sg:province":"NC",
    "sg:website":"www.playnationparties.com",
    "wof:name":"PlayNation",
    "wof:placetype":"venue"
},
  "geometry": {"coordinates":[-78.811817,35.841702],"type":"Point"}
}