{
  "type": "Feature",
  "properties": {
    "addr:full":"806 John Lookabill Rd Lexington NC 27292",
    "addr:housenumber":"806",
    "addr:postcode":"27292",
    "addr:street":"John Lookabill Rd",
    "iso:country":"US",
    "sg:address":"806 John Lookabill Rd",
    "sg:city":"Lexington",
    "sg:classifiers":[
        {
            "category":"Building & Trades",
            "subcategory":"Electrical",
            "type":"Services"
        }
    ],
    "sg:phone":"+1 336 746 5802",
    "sg:postcode":"27292",
    "sg:province":"NC",
    "sg:tags":[
        "electrical",
        "contractor"
    ],
    "wof:name":"Koonts Electric",
    "wof:placetype":"venue"
},
  "geometry": {"coordinates":[-80.148698,35.743076],"type":"Point"}
}