{
  "type": "Feature",
  "properties": {
    "addr:full":"215 Stage Coach Trl Greensboro NC 27410",
    "addr:housenumber":"215",
    "addr:postcode":"27410",
    "addr:street":"Stage Coach Trl",
    "iso:country":"US",
    "sg:address":"215 Stage Coach Trl",
    "sg:city":"Greensboro",
    "sg:classifiers":[
        {
            "category":"Retail",
            "subcategory":"Portrait Studio",
            "type":"Services"
        }
    ],
    "sg:phone":"+1   ",
    "sg:postcode":"27410",
    "sg:province":"NC",
    "sg:tags":[
        "photo"
    ],
    "wof:name":"Lloyds Photography Center",
    "wof:placetype":"venue"
},
  "geometry": {"coordinates":[-79.91305,36.082206],"type":"Point"}
}