{
  "type": "Feature",
  "properties": {
    "addr:full":"9206 Monroe Rd Charlotte NC 28270",
    "addr:housenumber":"9206",
    "addr:postcode":"28270",
    "addr:street":"Monroe Rd",
    "iso:country":"US",
    "sg:address":"9206 Monroe Rd",
    "sg:city":"Charlotte",
    "sg:classifiers":[
        {
            "category":"Building & Trades",
            "subcategory":"Plumbing",
            "type":"Services"
        }
    ],
    "sg:phone":"+1 704 847 4458",
    "sg:postcode":"28270",
    "sg:province":"NC",
    "sg:tags":[
        "heating",
        "air",
        "conditioning",
        "mechanical",
        "plumbing",
        "contractor"
    ],
    "wof:name":"Tompkins-Johnston Co Inc",
    "wof:placetype":"venue"
},
  "geometry": {"coordinates":[-80.743683,35.145941],"type":"Point"}
}