{
  "type": "Feature",
  "properties": {
    "iso:country":"US",
    "sg:address":"214 E Mountain St",
    "sg:city":"Kernersville",
    "sg:classifiers":[
        {
            "category":"Professional",
            "subcategory":"Lawyer & Legal Services",
            "type":"Services"
        }
    ],
    "sg:phone":"+1 336 993 2818",
    "sg:postcode":"27284",
    "sg:province":"NC",
    "sg:tags":[
        "attorney"
    ],
    "sg:website":"www.ericmorgan.com",
    "wof:name":"Eric C Morgan Pa",
    "wof:placetype":"venue"
},
  "geometry": {"coordinates":[-80.071259,36.119031],"type":"Point"}
}