{
  "type": "Feature",
  "properties": {
    "addr:full":"3605 Horseshoe Rd Yadkinville NC 27055",
    "addr:housenumber":"3605",
    "addr:postcode":"27055",
    "addr:street":"Horseshoe Rd",
    "iso:country":"US",
    "sg:address":"3605 Horseshoe Rd",
    "sg:city":"Yadkinville",
    "sg:classifiers":[
        {
            "category":"Recreation",
            "type":"Entertainment"
        }
    ],
    "sg:phone":"+1   ",
    "sg:postcode":"27055",
    "sg:province":"NC",
    "wof:name":"Dickens Farm Paint Ball Field",
    "wof:placetype":"venue"
},
  "geometry": {"coordinates":[-80.545276,36.100739],"type":"Point"}
}