{
  "type": "Feature",
  "properties": {
    "addr:full":"150 Piedmont Ave SW Winston Salem NC 27101",
    "addr:housenumber":"150",
    "addr:postcode":"27101",
    "addr:street":"Piedmont Ave Sw",
    "iso:country":"US",
    "sg:address":"150 Piedmont Ave SW",
    "sg:city":"Winston Salem",
    "sg:classifiers":[
        {
            "category":"Retail",
            "subcategory":"Portrait Studio",
            "type":"Services"
        },
        {
            "category":"Professional",
            "subcategory":"Art Services",
            "type":"Services"
        }
    ],
    "sg:phone":"+1 336 722 7053",
    "sg:postcode":"27101",
    "sg:province":"NC",
    "sg:tags":[
        "photographer",
        "photo"
    ],
    "wof:name":"R Jackson Smith Photography",
    "wof:placetype":"venue"
},
  "geometry": {"coordinates":[-80.25906500000001,36.091594],"type":"Point"}
}