{
  "type": "Feature",
  "properties": {
    "iso:country":"US",
    "sg:address":"6101 Westgate Rd",
    "sg:city":"Raleigh",
    "sg:classifiers":[
        {
            "category":"Airline",
            "type":"Transportation"
        }
    ],
    "sg:phone":"+1 919 787 0511",
    "sg:postcode":"27617",
    "sg:province":"NC",
    "sg:tags":[
        "cargo",
        "air"
    ],
    "sg:website":"www.pilotair.com",
    "wof:name":"Pilot Air Freight Corp",
    "wof:placetype":"venue"
},
  "geometry": {"coordinates":[-78.749055,35.902789],"type":"Point"}
}