{
  "type": "Feature",
  "properties": {
    "addr:full":"1234 Old Mill Creek Rd SE Winnabow NC 28479",
    "addr:housenumber":"1234",
    "addr:postcode":"28479",
    "addr:street":"Old Mill Creek Rd Se",
    "iso:country":"US",
    "sg:address":"1234 Old Mill Creek Rd SE",
    "sg:city":"Winnabow",
    "sg:classifiers":[
        {
            "category":"Social Services",
            "subcategory":"Child Care",
            "type":"Services"
        }
    ],
    "sg:phone":"+1   ",
    "sg:postcode":"28479",
    "sg:province":"NC",
    "sg:tags":[
        "day"
    ],
    "wof:name":"Cheryls Childcare",
    "wof:placetype":"venue"
},
  "geometry": {"coordinates":[-78.082886,34.094412],"type":"Point"}
}