{
  "type": "Feature",
  "properties": {
    "addr:full":"2714 Red Run Ct High Point NC 27265",
    "addr:housenumber":"2714",
    "addr:postcode":"27265",
    "addr:street":"Red Run Ct",
    "iso:country":"US",
    "sg:address":"2714 Red Run Ct",
    "sg:city":"High Point",
    "sg:classifiers":[
        {
            "category":"Professional",
            "subcategory":"Computer Services",
            "type":"Services"
        }
    ],
    "sg:phone":"+1 336 882 6674",
    "sg:postcode":"27265",
    "sg:province":"NC",
    "sg:tags":[
        "website",
        "design"
    ],
    "wof:name":"Calico Web Design Svc",
    "wof:placetype":"venue"
},
  "geometry": {"coordinates":[-79.987371,36.00137],"type":"Point"}
}