{
  "type": "Feature",
  "properties": {
    "iso:country":"US",
    "sg:address":"107 Mountain St",
    "sg:city":"Black Mountain",
    "sg:classifiers":[
        {
            "category":"Professional",
            "type":"Services"
        }
    ],
    "sg:phone":"+1 828 669 1982",
    "sg:postcode":"28711",
    "sg:province":"NC",
    "sg:tags":[
        "establishment"
    ],
    "wof:name":"Camino's",
    "wof:placetype":"venue"
},
  "geometry": {"coordinates":[-82.322714,35.622272],"type":"Point"}
}