{
  "type": "Feature",
  "properties": {
    "addr:full":"1603 N Road St Elizabeth City NC 27909",
    "addr:housenumber":"1603",
    "addr:postcode":"27909",
    "addr:street":"N Road St",
    "iso:country":"US",
    "sg:address":"1603 N Road St",
    "sg:city":"Elizabeth City",
    "sg:classifiers":[
        {
            "category":"Home & Garden",
            "subcategory":"Mobile Homes",
            "type":"Retail Goods"
        }
    ],
    "sg:phone":"+1 252 338 8759",
    "sg:postcode":"27909",
    "sg:province":"NC",
    "wof:name":"Forbes Homes Inc",
    "wof:placetype":"venue"
},
  "geometry": {"coordinates":[-76.22671200000001,36.330722],"type":"Point"}
}