{
  "type": "Feature",
  "properties": {
    "addr:full":"15 Seeley Dr Canton NC 28716",
    "addr:housenumber":"15",
    "addr:postcode":"28716",
    "addr:street":"Seeley Dr",
    "iso:country":"US",
    "sg:address":"15 Seeley Dr",
    "sg:city":"Canton",
    "sg:classifiers":[
        {
            "category":"Organizations",
            "subcategory":"Religious Organization",
            "type":"Services"
        }
    ],
    "sg:phone":"+1   ",
    "sg:postcode":"28716",
    "sg:province":"NC",
    "wof:name":"Canton Freewill Bapti",
    "wof:placetype":"venue"
},
  "geometry": {"coordinates":[-82.827585,35.527064],"type":"Point"}
}