{
  "type": "Feature",
  "properties": {
    "iso:country":"US",
    "sg:address":"1272 Tory Ln",
    "sg:city":"Asheboro",
    "sg:classifiers":[
        {
            "category":"Retail",
            "subcategory":"Auto Repair",
            "type":"Services"
        }
    ],
    "sg:phone":"+1   ",
    "sg:postcode":"27205",
    "sg:province":"NC",
    "sg:tags":[
        "general"
    ],
    "wof:name":"Lambe Garage",
    "wof:placetype":"venue"
},
  "geometry": {"coordinates":[-79.84330300000001,35.754205],"type":"Point"}
}