{
  "type": "Feature",
  "properties": {
    "iso:country":"US",
    "sg:address":"8700 Pineville-Matthews Rd",
    "sg:city":"Charlotte",
    "sg:classifiers":[
        {
            "category":"Personal",
            "subcategory":"Tanning Parlor",
            "type":"Services"
        }
    ],
    "sg:phone":"+1 704 540 8277",
    "sg:postcode":"28226",
    "sg:province":"NC",
    "sg:tags":[
        "salon"
    ],
    "wof:name":"Hot Spot Super Tanning Club",
    "wof:placetype":"venue"
},
  "geometry": {"coordinates":[-80.86993699999999,35.089256],"type":"Point"}
}