{
  "type": "Feature",
  "properties": {
    "addr:full":"1330 Edmond Matthis Rd Clinton NC 28328",
    "addr:housenumber":"1330",
    "addr:postcode":"28328",
    "addr:street":"Edmond Matthis Rd",
    "iso:country":"US",
    "sg:address":"1330 Edmond Matthis Rd",
    "sg:city":"Clinton",
    "sg:classifiers":[
        {
            "category":"Farming",
            "subcategory":"Livestock Farm",
            "type":"Manufacturing & Wholesale Goods"
        }
    ],
    "sg:phone":"+1 910 592 3862",
    "sg:postcode":"28328",
    "sg:province":"NC",
    "sg:tags":[
        "hog",
        "beef",
        "cattle",
        "egg",
        "or",
        "feedlot"
    ],
    "wof:name":"T P Farms",
    "wof:placetype":"venue"
},
  "geometry": {"coordinates":[-78.275644,34.854626],"type":"Point"}
}