{
  "type": "Feature",
  "properties": {
    "iso:country":"US",
    "sg:address":"1660 Pacolet Ct",
    "sg:city":"Gastonia",
    "sg:classifiers":[
        {
            "category":"Manufacturing",
            "subcategory":"Signs",
            "type":"Manufacturing & Wholesale Goods"
        },
        {
            "category":"Building & Trades",
            "subcategory":"Construction",
            "type":"Services"
        }
    ],
    "sg:phone":"+1 704 868 4500",
    "sg:postcode":"28052",
    "sg:province":"NC",
    "sg:tags":[
        "manufacture",
        "el",
        "installation",
        "contract"
    ],
    "sg:website":"www.signcon.com",
    "wof:name":"Sign Connection Inc",
    "wof:placetype":"venue"
},
  "geometry": {"coordinates":[-81.224366,35.287295],"type":"Point"}
}