{
  "type": "Feature",
  "properties": {
    "addr:full":"5476 Apex Peakway Apex NC 27502",
    "addr:housenumber":"5476",
    "addr:postcode":"27502",
    "addr:street":"Apex Peakway",
    "iso:country":"US",
    "sg:address":"5476 Apex Peakway",
    "sg:city":"Apex",
    "sg:classifiers":[
        {
            "category":"Shopping",
            "subcategory":"Bicycles & Sporting Goods",
            "type":"Retail Goods"
        }
    ],
    "sg:phone":"+1 919 387 0033",
    "sg:postcode":"27502",
    "sg:province":"NC",
    "sg:tags":[
        "bike"
    ],
    "wof:name":"Cycling Spoken Here Inc",
    "wof:placetype":"venue"
},
  "geometry": {"coordinates":[-78.867897,35.7365],"type":"Point"}
}