{
  "type": "Feature",
  "properties": {
    "addr:full":"2716 Chapel Hill Rd Durham NC 27707",
    "addr:housenumber":"2716",
    "addr:postcode":"27707",
    "addr:street":"Chapel Hill Rd",
    "iso:country":"US",
    "sg:address":"2716 Chapel Hill Rd",
    "sg:city":"Durham",
    "sg:classifiers":[
        {
            "category":"Organizations",
            "subcategory":"Membership Organization",
            "type":"Services"
        }
    ],
    "sg:phone":"+1   ",
    "sg:postcode":"27707",
    "sg:province":"NC",
    "wof:name":"PMG Arts Management",
    "wof:placetype":"venue"
},
  "geometry": {"coordinates":[-78.936457,35.976424],"type":"Point"}
}