{
  "type": "Feature",
  "properties": {
    "iso:country":"US",
    "sg:address":"404 Mundy Field Rd",
    "sg:city":"Burnsville",
    "sg:classifiers":[
        {
            "category":"Building & Trades",
            "subcategory":"Construction",
            "type":"Services"
        }
    ],
    "sg:phone":"+1 828 682 7771",
    "sg:postcode":"28716",
    "sg:province":"NC",
    "sg:tags":[
        "dry wall",
        "contractor"
    ],
    "wof:name":"Appalachian Drywall Systems",
    "wof:placetype":"venue"
},
  "geometry": {"coordinates":[-82.86935,35.458186],"type":"Point"}
}