{
  "type": "Feature",
  "properties": {
    "addr:full":"220 N Franklin Rd Mount Airy NC 27030",
    "addr:housenumber":"220",
    "addr:postcode":"27030",
    "addr:street":"N Franklin Rd",
    "iso:country":"US",
    "sg:address":"220 N Franklin Rd",
    "sg:city":"Mount Airy",
    "sg:classifiers":[
        {
            "category":"Retail",
            "subcategory":"Auto Repair",
            "type":"Services"
        }
    ],
    "sg:phone":"+1   ",
    "sg:postcode":"27030",
    "sg:province":"NC",
    "sg:tags":[
        "transmission"
    ],
    "wof:name":"Hodges Transmission Service",
    "wof:placetype":"venue"
},
  "geometry": {"coordinates":[-80.635024,36.50556],"type":"Point"}
}