{
  "type": "Feature",
  "properties": {
    "iso:country":"US",
    "sg:address":"1405 Burgaw Hwy",
    "sg:city":"Jacksonville",
    "sg:classifiers":[
        {
            "category":"Manufacturing",
            "subcategory":"Signs",
            "type":"Manufacturing & Wholesale Goods"
        }
    ],
    "sg:phone":"+1 910 346 8919",
    "sg:postcode":"28540",
    "sg:province":"NC",
    "sg:tags":[
        "specialty",
        "mfg"
    ],
    "wof:name":"Lanier Signs",
    "wof:placetype":"venue"
},
  "geometry": {"coordinates":[-77.481172,34.748295],"type":"Point"}
}