{
  "type": "Feature",
  "properties": {
    "addr:full":"215 Stoney Branch Rd New Bern NC 28562",
    "addr:housenumber":"215",
    "addr:postcode":"28562",
    "addr:street":"Stoney Branch Rd",
    "iso:country":"US",
    "sg:address":"215 Stoney Branch Rd",
    "sg:city":"New Bern",
    "sg:classifiers":[
        {
            "category":"Building & Trades",
            "subcategory":"Construction",
            "type":"Services"
        }
    ],
    "sg:phone":"+1 252 670 9299",
    "sg:postcode":"28562",
    "sg:province":"NC",
    "sg:tags":[
        "floor",
        "laying",
        "contractor"
    ],
    "wof:name":"Dunrite Floor and Tile LLC",
    "wof:placetype":"venue"
},
  "geometry": {"coordinates":[-77.168504,35.217492],"type":"Point"}
}