{
  "type": "Feature",
  "properties": {
    "iso:country":"US",
    "sg:address":"214 Thompson St",
    "sg:city":"Hendersonville",
    "sg:classifiers":[
        {
            "category":"Shopping",
            "subcategory":"Computers & Home Electronics",
            "type":"Retail Goods"
        }
    ],
    "sg:phone":"+1 828 692 1819",
    "sg:postcode":"28792",
    "sg:province":"NC",
    "wof:name":"Radio Shack",
    "wof:placetype":"venue"
},
  "geometry": {"coordinates":[-82.44692000000001,35.33994],"type":"Point"}
}