{
  "type": "Feature",
  "properties": {
    "addr:full":"1507 Dennbriar Dr NW Concord NC 28027",
    "addr:housenumber":"1507",
    "addr:postcode":"28027",
    "addr:street":"Dennbriar Dr Nw",
    "iso:country":"US",
    "sg:address":"1507 Dennbriar Dr NW",
    "sg:city":"Concord",
    "sg:classifiers":[
        {
            "category":"Professional",
            "type":"Services"
        }
    ],
    "sg:phone":"+1 704 784 8092",
    "sg:postcode":"28027",
    "sg:province":"NC",
    "sg:tags":[
        "establishment"
    ],
    "wof:name":"Crawford International Corp",
    "wof:placetype":"venue"
},
  "geometry": {"coordinates":[-80.640659,35.436212],"type":"Point"}
}