{
  "type": "Feature",
  "properties": {
    "addr:full":"154 Brisson Rd Saint Pauls NC 28384",
    "addr:housenumber":"154",
    "addr:postcode":"28384",
    "addr:street":"Brisson Rd",
    "iso:country":"US",
    "sg:address":"154 Brisson Rd",
    "sg:city":"Saint Pauls",
    "sg:classifiers":[
        {
            "category":"Real Estate",
            "subcategory":"Real Estate Operator",
            "type":"Services"
        }
    ],
    "sg:phone":"+1 910 865 4314",
    "sg:postcode":"28384",
    "sg:province":"NC",
    "sg:tags":[
        "property",
        "lessor"
    ],
    "wof:name":"Homer Brissen Farm",
    "wof:placetype":"venue"
},
  "geometry": {"coordinates":[-78.914601,34.818762],"type":"Point"}
}