{
  "type": "Feature",
  "properties": {
    "addr:full":"596 S Broadway St Forest City NC 28043",
    "addr:housenumber":"596",
    "addr:postcode":"28043",
    "addr:street":"S Broadway St",
    "iso:country":"US",
    "sg:address":"596 S Broadway St",
    "sg:city":"Forest City",
    "sg:classifiers":[
        {
            "category":"Shopping",
            "subcategory":"Used Merchandise",
            "type":"Retail Goods"
        }
    ],
    "sg:phone":"+1 828 245 3551",
    "sg:postcode":"28043",
    "sg:province":"NC",
    "sg:tags":[
        "shop",
        "pawnbroker",
        "pawn"
    ],
    "wof:name":"B & D Thrift Store & Loan Inc",
    "wof:placetype":"venue"
},
  "geometry": {"coordinates":[-81.858954,35.320182],"type":"Point"}
}