{
  "type": "Feature",
  "properties": {
    "iso:country":"US",
    "sg:address":"1841 Meadow Glen Ln",
    "sg:city":"Winston Salem",
    "sg:classifiers":[
        {
            "category":"Wholesale",
            "subcategory":"Machinery & Supplies",
            "type":"Manufacturing & Wholesale Goods"
        }
    ],
    "sg:phone":"+1 336 764 1130",
    "sg:postcode":"27127",
    "sg:province":"NC",
    "sg:tags":[
        "lift",
        "parts",
        "hydraulic"
    ],
    "wof:name":"Lifters Inc",
    "wof:placetype":"venue"
},
  "geometry": {"coordinates":[-80.278267,35.990254],"type":"Point"}
}