{
  "type": "Feature",
  "properties": {
    "iso:country":"US",
    "sg:address":"522 Joe Cloninger Rd",
    "sg:city":"Bessemer City",
    "sg:classifiers":[
        {
            "category":"Building & Trades",
            "subcategory":"Construction",
            "type":"Services"
        }
    ],
    "sg:phone":"+1 704 922 0236",
    "sg:postcode":"28016",
    "sg:province":"NC",
    "sg:tags":[
        "surfacing",
        "paving"
    ],
    "wof:name":"Cloninger Grading & Paving",
    "wof:placetype":"venue"
},
  "geometry": {"coordinates":[-81.245107,35.32213],"type":"Point"}
}