{
  "type": "Feature",
  "properties": {
    "iso:country":"US",
    "sg:address":"4123 Woodleaf Rd",
    "sg:city":"Charlotte",
    "sg:classifiers":[
        {
            "category":"Building & Trades",
            "subcategory":"Electrical",
            "type":"Services"
        }
    ],
    "sg:phone":"+1 704 532 6900",
    "sg:postcode":"28205",
    "sg:province":"NC",
    "sg:tags":[
        "electric",
        "contractor"
    ],
    "wof:name":"Alternate Power Svc",
    "wof:placetype":"venue"
},
  "geometry": {"coordinates":[-80.756269,35.221136],"type":"Point"}
}