{
  "type": "Feature",
  "properties": {
    "iso:country":"US",
    "sg:address":"104 E Mulberry St",
    "sg:city":"Goldsboro",
    "sg:classifiers":[
        {
            "category":"Personal",
            "subcategory":"Shoe Repair & Shine",
            "type":"Services"
        }
    ],
    "sg:phone":"+1 919 735 4177",
    "sg:postcode":"27530",
    "sg:province":"NC",
    "sg:tags":[
        "parlor",
        "shoes"
    ],
    "wof:name":"Rex Shoe Shop",
    "wof:placetype":"venue"
},
  "geometry": {"coordinates":[-77.99500500000001,35.383871],"type":"Point"}
}