{
  "type": "Feature",
  "properties": {
    "iso:country":"US",
    "sg:address":"236 Barrington Pl",
    "sg:city":"Winston Salem",
    "sg:classifiers":[
        {
            "category":"Farming",
            "subcategory":"Livestock Farm",
            "type":"Manufacturing & Wholesale Goods"
        }
    ],
    "sg:phone":"+1 336 659 0591",
    "sg:postcode":"27104",
    "sg:province":"NC",
    "sg:tags":[
        "beef",
        "feedlot",
        "cattle"
    ],
    "wof:name":"Katyna Spach - Chandecle",
    "wof:placetype":"venue"
},
  "geometry": {"coordinates":[-80.355103,36.077835],"type":"Point"}
}