{
  "type": "Feature",
  "properties": {
    "iso:country":"US",
    "sg:address":"3650 Patterson Ave",
    "sg:city":"Winston Salem",
    "sg:classifiers":[
        {
            "category":"Wholesale",
            "subcategory":"Medical Equipment & Supplies",
            "type":"Manufacturing & Wholesale Goods"
        }
    ],
    "sg:phone":"+1 336 776 1599",
    "sg:postcode":"27105",
    "sg:province":"NC",
    "sg:tags":[
        "hospital"
    ],
    "wof:name":"Restorative Solutions",
    "wof:placetype":"venue"
},
  "geometry": {"coordinates":[-80.243956,36.14137],"type":"Point"}
}