{
  "type": "Feature",
  "properties": {
    "iso:country":"US",
    "sg:address":"308 Fleming Dr",
    "sg:city":"Durham",
    "sg:classifiers":[
        {
            "category":"Travel",
            "subcategory":"Travel Agent",
            "type":"Entertainment"
        }
    ],
    "sg:phone":"+1 919 383 4304",
    "sg:postcode":"27712",
    "sg:province":"NC",
    "sg:tags":[
        "operator",
        "tour"
    ],
    "wof:name":"Carousel Tours Corp",
    "wof:placetype":"venue"
},
  "geometry": {"coordinates":[-78.963216,36.048713],"type":"Point"}
}