{
  "type": "Feature",
  "properties": {
    "addr:full":"3066 Happy Hill Rd Lexington NC 27295",
    "addr:housenumber":"3066",
    "addr:postcode":"27295",
    "addr:street":"Happy Hill Rd",
    "iso:country":"US",
    "sg:address":"3066 Happy Hill Rd",
    "sg:city":"Lexington",
    "sg:classifiers":[
        {
            "category":"Building & Trades",
            "subcategory":"Construction",
            "type":"Services"
        }
    ],
    "sg:phone":"+1 336 787 5449",
    "sg:postcode":"27295",
    "sg:province":"NC",
    "sg:tags":[
        "equipment",
        "masonry",
        "commercial",
        "rental",
        "contractor"
    ],
    "wof:name":"Triad Industrial Sup & Rentl",
    "wof:placetype":"venue"
},
  "geometry": {"coordinates":[-80.31153399999999,35.851666],"type":"Point"}
}