{
  "type": "Feature",
  "properties": {
    "iso:country":"US",
    "sg:address":"743 Walker Rd",
    "sg:city":"Elon College",
    "sg:classifiers":[
        {
            "category":"Manufacturing",
            "subcategory":"Tools & Machinery",
            "type":"Manufacturing & Wholesale Goods"
        }
    ],
    "sg:phone":"+1 336 584 7811",
    "sg:postcode":"27244",
    "sg:province":"NC",
    "sg:tags":[
        "transformer",
        "mfg"
    ],
    "wof:name":"Des Enterprises",
    "wof:placetype":"venue"
},
  "geometry": {"coordinates":[-79.495842,36.118454],"type":"Point"}
}