{
  "type": "Feature",
  "properties": {
    "iso:country":"US",
    "sg:address":"320 Sanford Dr",
    "sg:city":"Morganton",
    "sg:classifiers":[
        {
            "category":"Government",
            "subcategory":"Post Office",
            "type":"Public Place"
        }
    ],
    "sg:phone":"+1 828 437 3484",
    "sg:postcode":"28655",
    "sg:province":"NC",
    "wof:name":"US Post Office",
    "wof:placetype":"venue"
},
  "geometry": {"coordinates":[-81.70421,35.747961],"type":"Point"}
}