{
  "type": "Feature",
  "properties": {
    "iso:country":"US",
    "sg:address":"1722 Cotton Grove Rd",
    "sg:city":"Lexington",
    "sg:classifiers":[
        {
            "category":"Professional",
            "subcategory":"Employment Agencies",
            "type":"Services"
        }
    ],
    "sg:phone":"+1   ",
    "sg:postcode":"27292",
    "sg:province":"NC",
    "wof:name":"Ablest Staffing Services",
    "wof:placetype":"venue"
},
  "geometry": {"coordinates":[-80.259444,35.77578],"type":"Point"}
}