{
  "type": "Feature",
  "properties": {
    "addr:full":"171 Barnes Rd Eden NC 27288",
    "addr:housenumber":"171",
    "addr:postcode":"27288",
    "addr:street":"Barnes Rd",
    "iso:country":"US",
    "sg:address":"171 Barnes Rd",
    "sg:city":"Eden",
    "sg:classifiers":[
        {
            "category":"Retail",
            "subcategory":"Auto Repair",
            "type":"Services"
        }
    ],
    "sg:phone":"+1 336 623 2859",
    "sg:postcode":"27288",
    "sg:province":"NC",
    "sg:tags":[
        "body",
        "wrecker"
    ],
    "wof:name":"Stegall's Wrecker Svc",
    "wof:placetype":"venue"
},
  "geometry": {"coordinates":[-79.85369799999999,36.51057],"type":"Point"}
}