{
  "type": "Feature",
  "properties": {
    "iso:country":"US",
    "sg:address":"290 Miller Rd",
    "sg:city":"Mount Airy",
    "sg:classifiers":[
        {
            "category":"Building & Trades",
            "subcategory":"Cleaning & Sanitation",
            "type":"Services"
        }
    ],
    "sg:phone":"+1   ",
    "sg:postcode":"27030",
    "sg:province":"NC",
    "sg:tags":[
        "repair",
        "maintenance"
    ],
    "wof:name":"Virtually Spotless Clean",
    "wof:placetype":"venue"
},
  "geometry": {"coordinates":[-80.654871,36.543074],"type":"Point"}
}