{
  "type": "Feature",
  "properties": {
    "iso:country":"US",
    "sg:address":"14071 State Hwy 903",
    "sg:city":"Halifax",
    "sg:classifiers":[
        {
            "category":"Government",
            "subcategory":"Office",
            "type":"Public Place"
        }
    ],
    "sg:phone":"+1 252 583 3383",
    "sg:postcode":"27839",
    "sg:province":"NC",
    "sg:tags":[
        "merchandise",
        "general"
    ],
    "wof:name":"Doc Halifax Vehicle Shop",
    "wof:placetype":"venue"
},
  "geometry": {"coordinates":[-77.575766,36.251792],"type":"Point"}
}