{
  "type": "Feature",
  "properties": {
    "addr:full":"4 Pine Tree Ln Chapel Hill NC 27514",
    "addr:housenumber":"4",
    "addr:postcode":"27514",
    "addr:street":"Pine Tree Ln",
    "iso:country":"US",
    "sg:address":"4 Pine Tree Ln",
    "sg:city":"Chapel Hill",
    "sg:classifiers":[
        {
            "category":"Manufacturing",
            "subcategory":"Chemicals & Compounds",
            "type":"Manufacturing & Wholesale Goods"
        }
    ],
    "sg:phone":"+1 919 489 7325",
    "sg:postcode":"27514",
    "sg:province":"NC",
    "sg:tags":[
        "preparation",
        "toilet",
        "mfg"
    ],
    "wof:name":"Sukkah Project The",
    "wof:placetype":"venue"
},
  "geometry": {"coordinates":[-79.031448,35.973008],"type":"Point"}
}