{
  "type": "Feature",
  "properties": {
    "iso:country":"US",
    "sg:address":"121 Linda Dr",
    "sg:city":"Madison",
    "sg:classifiers":[
        {
            "category":"Manufacturing",
            "subcategory":"Lumber",
            "type":"Manufacturing & Wholesale Goods"
        }
    ],
    "sg:phone":"+1 336 548 6955",
    "sg:postcode":"27025",
    "sg:province":"NC",
    "sg:tags":[
        "logging"
    ],
    "wof:name":"Bullins Logging",
    "wof:placetype":"venue"
},
  "geometry": {"coordinates":[-79.914119,36.383594],"type":"Point"}
}