{
  "type": "Feature",
  "properties": {
    "iso:country":"US",
    "sg:address":"2221 Wellesley Ave",
    "sg:city":"Charlotte",
    "sg:classifiers":[
        {
            "category":"Organizations",
            "subcategory":"Community Association",
            "type":"Services"
        }
    ],
    "sg:phone":"+1   ",
    "sg:postcode":"28207",
    "sg:province":"NC",
    "wof:name":"PHI Mu Frat",
    "wof:placetype":"venue"
},
  "geometry": {"coordinates":[-80.833665,35.187392],"type":"Point"}
}