{
  "type": "Feature",
  "properties": {
    "addr:full":"602 Thomasboro Rd SW Calabash NC 28467",
    "addr:housenumber":"602",
    "addr:postcode":"28467",
    "addr:street":"Thomasboro Rd Sw",
    "iso:country":"US",
    "sg:address":"602 Thomasboro Rd SW",
    "sg:city":"Calabash",
    "sg:classifiers":[
        {
            "category":"Health Services",
            "subcategory":"Doctor",
            "type":"Services"
        }
    ],
    "sg:phone":"+1 910 579 1872",
    "sg:postcode":"28467",
    "sg:province":"NC",
    "sg:tags":[
        "physician",
        "surgeon"
    ],
    "wof:name":"Intramed Family Practice Urgen",
    "wof:placetype":"venue"
},
  "geometry": {"coordinates":[-78.55513000000001,33.922001],"type":"Point"}
}