{
  "type": "Feature",
  "properties": {
    "addr:full":"1807 N Berkeley Blvd Goldsboro NC 27534",
    "addr:housenumber":"1807",
    "addr:postcode":"27534",
    "addr:street":"N Berkeley Blvd",
    "iso:country":"US",
    "sg:address":"1807 N Berkeley Blvd",
    "sg:city":"Goldsboro",
    "sg:classifiers":[
        {
            "category":"Restaurant",
            "type":"Food & Drink"
        }
    ],
    "sg:phone":"+1 919 778 5884",
    "sg:postcode":"27534",
    "sg:province":"NC",
    "sg:tags":[
        "eating"
    ],
    "wof:name":"China Eight",
    "wof:placetype":"venue"
},
  "geometry": {"coordinates":[-77.92202899999999,35.387504],"type":"Point"}
}