{
  "type": "Feature",
  "properties": {
    "addr:full":"3211 Kendale Ave NW Concord NC 28027",
    "addr:housenumber":"3211",
    "addr:postcode":"28027",
    "addr:street":"Kendale Ave Nw",
    "iso:country":"US",
    "sg:address":"3211 Kendale Ave NW",
    "sg:city":"Concord",
    "sg:classifiers":[
        {
            "category":"Retail",
            "subcategory":"Animal Services",
            "type":"Services"
        }
    ],
    "sg:phone":"+1 704 782 7387",
    "sg:postcode":"28027",
    "sg:province":"NC",
    "sg:tags":[
        "pet",
        "grooming",
        "washing"
    ],
    "wof:name":"VIP Mobile Pet Grooming Salon",
    "wof:placetype":"venue"
},
  "geometry": {"coordinates":[-80.631269,35.426686],"type":"Point"}
}