{
  "type": "Feature",
  "properties": {
    "iso:country":"US",
    "sg:address":"3513 US Hwy 74",
    "sg:city":"Monroe",
    "sg:classifiers":[
        {
            "category":"Professional",
            "subcategory":"Employment Agencies",
            "type":"Services"
        }
    ],
    "sg:phone":"+1 704 291 7731",
    "sg:postcode":"28110",
    "sg:province":"NC",
    "sg:tags":[
        "opportunity"
    ],
    "wof:name":"Management Recruiters-Monroe",
    "wof:placetype":"venue"
},
  "geometry": {"coordinates":[-80.590081,35.029209],"type":"Point"}
}