{
  "type": "Feature",
  "properties": {
    "iso:country":"US",
    "sg:address":"1213 S 15th St",
    "sg:city":"Wilmington",
    "sg:classifiers":[
        {
            "category":"Home & Garden",
            "subcategory":"Building Materials",
            "type":"Retail Goods"
        }
    ],
    "sg:phone":"+1 910 762 2160",
    "sg:postcode":"28401",
    "sg:province":"NC",
    "sg:tags":[
        "glass",
        "window",
        "plate"
    ],
    "wof:name":"Lee's Glass Svc Co",
    "wof:placetype":"venue"
},
  "geometry": {"coordinates":[-77.928217,34.220599],"type":"Point"}
}