{
  "type": "Feature",
  "properties": {
    "iso:country":"US",
    "sg:address":"1934 Colwell Ave",
    "sg:city":"Wilmington",
    "sg:classifiers":[
        {
            "category":"Wholesale",
            "subcategory":"Medical Equipment & Supplies",
            "type":"Manufacturing & Wholesale Goods"
        }
    ],
    "sg:phone":"+1 910 762 8512",
    "sg:postcode":"28403",
    "sg:province":"NC",
    "sg:tags":[
        "physician",
        "surgeon"
    ],
    "wof:name":"Tarheel Physician's Supply",
    "wof:placetype":"venue"
},
  "geometry": {"coordinates":[-77.9238,34.227726],"type":"Point"}
}