{
  "type": "Feature",
  "properties": {
    "addr:full":"39 Meadowood Glen Way Greensboro NC 27409",
    "addr:housenumber":"39",
    "addr:postcode":"27409",
    "addr:street":"Meadowood Glen Way",
    "iso:country":"US",
    "sg:address":"39 Meadowood Glen Way",
    "sg:city":"Greensboro",
    "sg:classifiers":[
        {
            "category":"Utilities",
            "subcategory":"Telephone",
            "type":"Services"
        }
    ],
    "sg:phone":"+1 336 299 9338",
    "sg:postcode":"27409",
    "sg:province":"NC",
    "sg:tags":[
        "host",
        "internet"
    ],
    "wof:name":"Domisell Inc",
    "wof:placetype":"venue"
},
  "geometry": {"coordinates":[-79.889583,36.066934],"type":"Point"}
}