{
  "type": "Feature",
  "properties": {
    "addr:full":"4593 Belltown Rd Oxford NC 27565",
    "addr:postcode":"4593;27565",
    "addr:street":"Belltown Rd",
    "iso:country":"US",
    "sg:address":"4593 Belltown Rd",
    "sg:city":"Oxford",
    "sg:classifiers":[
        {
            "category":"Building & Trades",
            "subcategory":"Construction",
            "type":"Services"
        }
    ],
    "sg:phone":"+1 919 690 8411",
    "sg:postcode":"27565",
    "sg:province":"NC",
    "wof:name":"Watts Construction Inc",
    "wof:placetype":"venue"
},
  "geometry": {"coordinates":[-78.62632600000001,36.256412],"type":"Point"}
}