{
  "type": "Feature",
  "properties": {
    "addr:full":"2419 Damascus Dr Monroe NC 28110",
    "addr:housenumber":"2419",
    "addr:postcode":"28110",
    "addr:street":"Damascus Dr",
    "iso:country":"US",
    "sg:address":"2419 Damascus Dr",
    "sg:city":"Monroe",
    "sg:classifiers":[
        {
            "category":"Real Estate",
            "subcategory":"Real Estate Agent",
            "type":"Services"
        }
    ],
    "sg:phone":"+1 704 282 4909",
    "sg:postcode":"28110",
    "sg:province":"NC",
    "wof:name":"Garry D Smith Homes",
    "wof:placetype":"venue"
},
  "geometry": {"coordinates":[-80.63829800000001,35.027588],"type":"Point"}
}