{
  "type": "Feature",
  "properties": {
    "addr:full":"315 S Main St Landis NC 28088",
    "addr:housenumber":"315",
    "addr:postcode":"28088",
    "addr:street":"S Main St",
    "iso:country":"US",
    "sg:address":"315 S Main St",
    "sg:city":"Landis",
    "sg:classifiers":[
        {
            "category":"Professional",
            "type":"Services"
        }
    ],
    "sg:phone":"+1 704 857 7955",
    "sg:postcode":"28088",
    "sg:province":"NC",
    "wof:name":"Krish Corporation",
    "wof:placetype":"venue"
},
  "geometry": {"coordinates":[-80.613192,35.5444],"type":"Point"}
}