{
  "type": "Feature",
  "properties": {
    "iso:country":"US",
    "sg:address":"1221 W 2nd Ave",
    "sg:city":"Gastonia",
    "sg:classifiers":[
        {
            "category":"Manufacturing",
            "subcategory":"Tools & Machinery",
            "type":"Manufacturing & Wholesale Goods"
        }
    ],
    "sg:phone":"+1 704 864 5528",
    "sg:postcode":"28052",
    "sg:province":"NC",
    "sg:tags":[
        "machine",
        "shop"
    ],
    "wof:name":"Pioneer Machine Works Inc",
    "wof:placetype":"venue"
},
  "geometry": {"coordinates":[-81.204525,35.259864],"type":"Point"}
}