{
  "type": "Feature",
  "properties": {
    "iso:country":"US",
    "sg:address":"92 Stoney Hill Ct",
    "sg:city":"Asheville",
    "sg:classifiers":[
        {
            "category":"Banks & Credit Unions",
            "subcategory":"Bank",
            "type":"Services"
        }
    ],
    "sg:phone":"+1 828 645 3578",
    "sg:postcode":"28804",
    "sg:province":"NC",
    "sg:tags":[
        "mortgage"
    ],
    "wof:name":"Country Roads Mortgage Inc",
    "wof:placetype":"venue"
},
  "geometry": {"coordinates":[-82.577905,35.677432],"type":"Point"}
}