{
  "type": "Feature",
  "properties": {
    "iso:country":"US",
    "sg:address":"2400 Ferguson Rd",
    "sg:city":"Raleigh",
    "sg:classifiers":[
        {
            "category":"Professional",
            "type":"Services"
        }
    ],
    "sg:phone":"+1 919 848 9892",
    "sg:postcode":"27612",
    "sg:province":"NC",
    "wof:name":"Cyb Wiz Inc",
    "wof:placetype":"venue"
},
  "geometry": {"coordinates":[-78.677279,35.876036],"type":"Point"}
}