{
  "type": "Feature",
  "properties": {
    "iso:country":"US",
    "sg:address":"1909 Poole Rd",
    "sg:city":"Raleigh",
    "sg:classifiers":[
        {
            "category":"Shopping",
            "subcategory":"Clothing, Apparel, & Fashions",
            "type":"Retail Goods"
        }
    ],
    "sg:phone":"+1 919 329 2657",
    "sg:postcode":"27610",
    "sg:province":"NC",
    "sg:tags":[
        "hair",
        "supply",
        "beauty",
        "accessory"
    ],
    "wof:name":"Dejavu Sounds and Style",
    "wof:placetype":"venue"
},
  "geometry": {"coordinates":[-78.610607,35.776525],"type":"Point"}
}