{
  "type": "Feature",
  "properties": {
    "addr:full":"415 Church St Bladenboro NC 28320",
    "addr:housenumber":"415",
    "addr:postcode":"28320",
    "addr:street":"Church St",
    "iso:country":"US",
    "sg:address":"415 Church St",
    "sg:city":"Bladenboro",
    "sg:classifiers":[
        {
            "category":"Retail",
            "subcategory":"Repair Shop",
            "type":"Services"
        }
    ],
    "sg:phone":"+1 910 863 3357",
    "sg:postcode":"28320",
    "sg:province":"NC",
    "sg:tags":[
        "scooter",
        "motorcycle",
        "motor"
    ],
    "wof:name":"Smith Cycle & Atv",
    "wof:placetype":"venue"
},
  "geometry": {"coordinates":[-78.800721,34.548854],"type":"Point"}
}