{
  "type": "Feature",
  "properties": {
    "iso:country":"US",
    "sg:address":"524 W Airline Ave",
    "sg:city":"Gastonia",
    "sg:classifiers":[
        {
            "category":"Professional",
            "subcategory":"Business Services",
            "type":"Services"
        }
    ],
    "sg:phone":"+1 704 867 1275",
    "sg:postcode":"28052",
    "sg:province":"NC",
    "wof:name":"Ray Smith Bonding Co",
    "wof:placetype":"venue"
},
  "geometry": {"coordinates":[-81.18943,35.265241],"type":"Point"}
}