{
  "type": "Feature",
  "properties": {
    "addr:full":"109 Brewer Ln Carrboro NC 27510",
    "addr:housenumber":"109",
    "addr:postcode":"27510",
    "addr:street":"Brewer Ln",
    "iso:country":"US",
    "sg:address":"109 Brewer Ln",
    "sg:city":"Carrboro",
    "sg:classifiers":[
        {
            "category":"Retail",
            "subcategory":"Repair Shop",
            "type":"Services"
        },
        {
            "category":"Building & Trades",
            "subcategory":"Construction",
            "type":"Services"
        }
    ],
    "sg:phone":"+1 919 969 0031",
    "sg:postcode":"27510",
    "sg:province":"NC",
    "sg:tags":[
        "welding",
        "contractor"
    ],
    "wof:name":"Metal Shop",
    "wof:placetype":"venue"
},
  "geometry": {"coordinates":[-79.065349,35.909572],"type":"Point"}
}