{
  "type": "Feature",
  "properties": {
    "addr:full":"1719 John Small Ave Washington NC 27889",
    "addr:housenumber":"1719",
    "addr:postcode":"27889",
    "addr:street":"John Small Ave",
    "iso:country":"US",
    "sg:address":"1719 John Small Ave",
    "sg:city":"Washington",
    "sg:classifiers":[
        {
            "category":"Retail",
            "subcategory":"Repair Shop",
            "type":"Services"
        }
    ],
    "sg:phone":"+1   ",
    "sg:postcode":"27889",
    "sg:province":"NC",
    "wof:name":"All Secure Lock & Key",
    "wof:placetype":"venue"
},
  "geometry": {"coordinates":[-77.01789599999999,35.543809],"type":"Point"}
}