{
  "type": "Feature",
  "properties": {
    "iso:country":"US",
    "sg:address":"2529 Blackjack-Simpson Rd",
    "sg:city":"Greenville",
    "sg:classifiers":[
        {
            "category":"Home & Garden",
            "subcategory":"Home Furnishings",
            "type":"Retail Goods"
        }
    ],
    "sg:phone":"+1 252 758 3560",
    "sg:postcode":"27858",
    "sg:province":"NC",
    "sg:tags":[
        "curtain",
        "made",
        "drapery"
    ],
    "wof:name":"Black Jack Drapery & Fabric",
    "wof:placetype":"venue"
},
  "geometry": {"coordinates":[-77.254597,35.516408],"type":"Point"}
}