{
  "type": "Feature",
  "properties": {
    "iso:country":"US",
    "sg:address":"115 Jones St",
    "sg:city":"Trenton",
    "sg:classifiers":[
        {
            "category":"Health Services",
            "subcategory":"Chiropractor",
            "type":"Services"
        }
    ],
    "sg:phone":"+1 252 448 4561",
    "sg:postcode":"28585",
    "sg:province":"NC",
    "wof:name":"Yanni Chiropractic Ctr",
    "wof:placetype":"venue"
},
  "geometry": {"coordinates":[-77.35361399999999,35.063596],"type":"Point"}
}