{
  "type": "Feature",
  "properties": {
    "iso:country":"US",
    "sg:address":"1066 Hillcroft Rd",
    "sg:city":"Browns Summit",
    "sg:classifiers":[
        {
            "category":"Food & Beverages",
            "subcategory":"Meat & Fish",
            "type":"Retail Goods"
        }
    ],
    "sg:phone":"+1 336 621 0664",
    "sg:postcode":"27214",
    "sg:province":"NC",
    "wof:name":"Richards Delicious Seasoning",
    "wof:placetype":"venue"
},
  "geometry": {"coordinates":[-79.761752,36.153086],"type":"Point"}
}