{
  "type": "Feature",
  "properties": {
    "iso:country":"US",
    "sg:address":"1115 Lejeune Blvd",
    "sg:city":"Jacksonville",
    "sg:classifiers":[
        {
            "category":"Organizations",
            "subcategory":"Religious Organization",
            "type":"Services"
        }
    ],
    "sg:phone":"+1 910 347 2207",
    "sg:postcode":"28540",
    "sg:province":"NC",
    "sg:tags":[
        "church"
    ],
    "wof:name":"Lutheran Church Of Our Savior",
    "wof:placetype":"venue"
},
  "geometry": {"coordinates":[-77.41520300000001,34.748439],"type":"Point"}
}