{
  "type": "Feature",
  "properties": {
    "addr:full":"2959 Winston Dr NW Concord NC 28027",
    "addr:housenumber":"2959",
    "addr:postcode":"28027",
    "addr:street":"Winston Dr Nw",
    "iso:country":"US",
    "sg:address":"2959 Winston Dr NW",
    "sg:city":"Concord",
    "sg:classifiers":[
        {
            "category":"Freight",
            "type":"Transportation"
        }
    ],
    "sg:phone":"+1 704 782 9686",
    "sg:postcode":"28027",
    "sg:province":"NC",
    "sg:tags":[
        "haulage",
        "truck",
        "dump"
    ],
    "wof:name":"Charles Hood Trucking",
    "wof:placetype":"venue"
},
  "geometry": {"coordinates":[-80.62611699999999,35.404748],"type":"Point"}
}