{
  "type": "Feature",
  "properties": {
    "addr:full":"521 Treasure Ln Gastonia NC 28054",
    "addr:housenumber":"521",
    "addr:postcode":"28054",
    "addr:street":"Treasure Ln",
    "iso:country":"US",
    "sg:address":"521 Treasure Ln",
    "sg:city":"Gastonia",
    "sg:classifiers":[
        {
            "category":"Shopping",
            "subcategory":"Beauty & Cosmetics",
            "type":"Retail Goods"
        }
    ],
    "sg:phone":"+1 704 864 4224",
    "sg:postcode":"28054",
    "sg:province":"NC",
    "sg:tags":[
        "merchandise"
    ],
    "wof:name":"Merle Norman Cosmetics",
    "wof:placetype":"venue"
},
  "geometry": {"coordinates":[-81.12920699999999,35.256149],"type":"Point"}
}