{
  "type": "Feature",
  "properties": {
    "iso:country":"US",
    "sg:address":"3524 Airport Rd",
    "sg:city":"Maiden",
    "sg:classifiers":[
        {
            "category":"Banks & Credit Unions",
            "subcategory":"Financial Services",
            "type":"Services"
        }
    ],
    "sg:phone":"+1 828 464 8753",
    "sg:postcode":"28650",
    "sg:province":"NC",
    "sg:tags":[
        "company",
        "holding"
    ],
    "wof:name":"Air Transportation Holding Co",
    "wof:placetype":"venue"
},
  "geometry": {"coordinates":[-81.081321,35.596273],"type":"Point"}
}