{
  "type": "Feature",
  "properties": {
    "addr:full":"336 Sherwee Dr Raleigh NC 27603",
    "addr:housenumber":"336",
    "addr:postcode":"27603",
    "addr:street":"Sherwee Dr",
    "iso:country":"US",
    "sg:address":"336 Sherwee Dr",
    "sg:city":"Raleigh",
    "sg:classifiers":[
        {
            "category":"Organizations",
            "subcategory":"Religious Organization",
            "type":"Services"
        }
    ],
    "sg:phone":"+1 919 662 5072",
    "sg:postcode":"27603",
    "sg:province":"NC",
    "sg:tags":[
        "church"
    ],
    "wof:name":"Increasing In Christ Mnstrs",
    "wof:placetype":"venue"
},
  "geometry": {"coordinates":[-78.64649300000001,35.733402],"type":"Point"}
}