{
  "type": "Feature",
  "properties": {
    "iso:country":"US",
    "sg:address":"61 Craven St",
    "sg:city":"Asheville",
    "sg:classifiers":[
        {
            "category":"Retail",
            "subcategory":"Auto Repair",
            "type":"Services"
        }
    ],
    "sg:phone":"+1 828 252 6464",
    "sg:postcode":"28806",
    "sg:province":"NC",
    "sg:tags":[
        "alternator",
        "generator"
    ],
    "wof:name":"Main Auto Parts Inc",
    "wof:placetype":"venue"
},
  "geometry": {"coordinates":[-82.57256099999999,35.586726],"type":"Point"}
}