{
  "type": "Feature",
  "properties": {
    "addr:full":"949 Fisher Ferry St Thomasville NC 27360",
    "addr:housenumber":"949",
    "addr:postcode":"27360",
    "addr:street":"Fisher Ferry St",
    "iso:country":"US",
    "sg:address":"949 Fisher Ferry St",
    "sg:city":"Thomasville",
    "sg:classifiers":[
        {
            "category":"Personal",
            "subcategory":"Beauty Salon",
            "type":"Services"
        }
    ],
    "sg:phone":"+1 336 475 0024",
    "sg:postcode":"27360",
    "sg:province":"NC",
    "sg:tags":[
        "shop",
        "manicuring"
    ],
    "wof:name":"Two Thumbs Up Nail & Tan Salon",
    "wof:placetype":"venue"
},
  "geometry": {"coordinates":[-80.088937,35.863898],"type":"Point"}
}