{
  "type": "Feature",
  "properties": {
    "iso:country":"US",
    "sg:address":"38 SW Court Sq",
    "sg:city":"Graham",
    "sg:classifiers":[
        {
            "category":"Professional",
            "subcategory":"Lawyer & Legal Services",
            "type":"Services"
        }
    ],
    "sg:phone":"+1 336 228 0273",
    "sg:postcode":"27253",
    "sg:province":"NC",
    "sg:tags":[
        "attorney"
    ],
    "wof:name":"Frederick J Sternberg",
    "wof:placetype":"venue"
},
  "geometry": {"coordinates":[-79.400623,36.069195],"type":"Point"}
}