{
  "type": "Feature",
  "properties": {
    "addr:full":"2003 N Fayetteville St Asheboro NC 27203",
    "addr:housenumber":"2003",
    "addr:postcode":"27203",
    "addr:street":"N;St",
    "iso:country":"US",
    "sg:address":"2003 N Fayetteville St",
    "sg:city":"Asheboro",
    "sg:classifiers":[
        {
            "category":"Restaurant",
            "type":"Food & Drink"
        }
    ],
    "sg:menulink":"http://www.allmenus.com/nc/asheboro/156154-hardees/menu/",
    "sg:phone":"+1 336 672 1099",
    "sg:postcode":"27203",
    "sg:province":"NC",
    "sg:tags":[
        "burger",
        "american"
    ],
    "wof:name":"Hardee's",
    "wof:placetype":"venue"
},
  "geometry": {"coordinates":[-79.805694,35.753835],"type":"Point"}
}