{
  "type": "Feature",
  "properties": {
    "addr:full":"306 Whitaker Ln Andrews NC 28901",
    "addr:housenumber":"306",
    "addr:postcode":"28901",
    "addr:street":"Whitaker Ln",
    "iso:country":"US",
    "sg:address":"306 Whitaker Ln",
    "sg:city":"Andrews",
    "sg:classifiers":[
        {
            "category":"Wholesale",
            "subcategory":"Painting Supplies",
            "type":"Manufacturing & Wholesale Goods"
        },
        {
            "category":"Home & Garden",
            "subcategory":"Garden Supply",
            "type":"Retail Goods"
        },
        {
            "category":"Home & Garden",
            "subcategory":"Building Materials",
            "type":"Retail Goods"
        },
        {
            "category":"Home & Garden",
            "subcategory":"Hardware",
            "type":"Retail Goods"
        }
    ],
    "sg:phone":"+1 828 321 4275",
    "sg:postcode":"28901",
    "sg:province":"NC",
    "sg:tags":[
        "paint",
        "store"
    ],
    "wof:name":"Andrews Ace Hardware",
    "wof:placetype":"venue"
},
  "geometry": {"coordinates":[-83.835865,35.19982],"type":"Point"}
}