{
  "type": "Feature",
  "properties": {
    "iso:country":"US",
    "sg:address":"110 Crosslake Park Dr",
    "sg:city":"Mooresville",
    "sg:classifiers":[
        {
            "category":"Manufacturing",
            "subcategory":"Motor Vehicles & Parts",
            "type":"Manufacturing & Wholesale Goods"
        }
    ],
    "sg:phone":"+1 704 664 8866",
    "sg:postcode":"28117",
    "sg:province":"NC",
    "sg:tags":[
        "manufacture",
        "disc",
        "brake",
        "power",
        "kit"
    ],
    "wof:name":"Master Power Brakes LTD",
    "wof:placetype":"venue"
},
  "geometry": {"coordinates":[-80.868897,35.589705],"type":"Point"}
}