{
  "type": "Feature",
  "properties": {
    "addr:full":"2531 N Sharon Amity Rd Charlotte NC 28205",
    "addr:housenumber":"2531",
    "addr:postcode":"28205",
    "addr:street":"N Sharon Amity Rd",
    "iso:country":"US",
    "sg:address":"2531 N Sharon Amity Rd",
    "sg:city":"Charlotte",
    "sg:classifiers":[
        {
            "category":"Restaurant",
            "type":"Food & Drink"
        }
    ],
    "sg:menulink":"http://www.allmenus.com/nc/charlotte/39251-oasis-place/menu/",
    "sg:phone":"+1 704 537 5940",
    "sg:postcode":"28205",
    "sg:province":"NC",
    "sg:tags":[
        "american"
    ],
    "wof:name":"Oasis Place",
    "wof:placetype":"venue"
},
  "geometry": {"coordinates":[-80.766837,35.194145],"type":"Point"}
}