{
  "type": "Feature",
  "properties": {
    "addr:full":"3410 Healy Dr Winston Salem NC 27103",
    "addr:housenumber":"3410",
    "addr:postcode":"27103",
    "addr:street":"Healy Dr",
    "iso:country":"US",
    "sg:address":"3410 Healy Dr",
    "sg:city":"Winston Salem",
    "sg:classifiers":[
        {
            "category":"Professional",
            "subcategory":"Lawyer & Legal Services",
            "type":"Services"
        }
    ],
    "sg:phone":"+1 336 774 3124",
    "sg:postcode":"27103",
    "sg:province":"NC",
    "sg:tags":[
        "attorney"
    ],
    "wof:name":"Weidemann Law Firm",
    "wof:placetype":"venue"
},
  "geometry": {"coordinates":[-80.312189,36.076721],"type":"Point"}
}