{
  "type": "Feature",
  "properties": {
    "addr:full":"35 Brookdale Rd Asheville NC 28804",
    "addr:housenumber":"35",
    "addr:postcode":"28804",
    "addr:street":"Brookdale Rd",
    "iso:country":"US",
    "sg:address":"35 Brookdale Rd",
    "sg:city":"Asheville",
    "sg:classifiers":[
        {
            "category":"Real Estate",
            "subcategory":"Real Estate Operator",
            "type":"Services"
        }
    ],
    "sg:phone":"+1 828 253 5071",
    "sg:postcode":"28804",
    "sg:province":"NC",
    "sg:tags":[
        "mobile",
        "home",
        "community"
    ],
    "wof:name":"Valley Park Mobile Home Court",
    "wof:placetype":"venue"
},
  "geometry": {"coordinates":[-82.578389,35.632933],"type":"Point"}
}