{
  "type": "Feature",
  "properties": {
    "iso:country":"US",
    "sg:address":"4821 Rembert Dr",
    "sg:city":"Raleigh",
    "sg:classifiers":[
        {
            "category":"Professional",
            "subcategory":"Management & Consulting",
            "type":"Services"
        }
    ],
    "sg:phone":"+1 919 781 1288",
    "sg:postcode":"27612",
    "sg:province":"NC",
    "sg:tags":[
        "consultant",
        "business"
    ],
    "sg:website":"www.raleighconsulting.com",
    "wof:name":"Raleigh Consulting Group Inc",
    "wof:placetype":"venue"
},
  "geometry": {"coordinates":[-78.689041,35.852841],"type":"Point"}
}