{
  "type": "Feature",
  "properties": {
    "iso:country":"US",
    "sg:address":"756 Tyvola Rd",
    "sg:city":"Charlotte",
    "sg:classifiers":[
        {
            "category":"Professional",
            "subcategory":"Business Services",
            "type":"Services"
        }
    ],
    "sg:phone":"+1 704 643 9954",
    "sg:postcode":"28217",
    "sg:province":"NC",
    "sg:tags":[
        "packaging"
    ],
    "wof:name":"Unishippers Of Charlotte",
    "wof:placetype":"venue"
},
  "geometry": {"coordinates":[-80.881671,35.165237],"type":"Point"}
}