{
  "type": "Feature",
  "properties": {
    "iso:country":"US",
    "sg:address":"193 State Hwy 149",
    "sg:city":"Plymouth",
    "sg:classifiers":[
        {
            "category":"Wholesale",
            "subcategory":"Construction Materials",
            "type":"Manufacturing & Wholesale Goods"
        }
    ],
    "sg:phone":"+1 252 793 1111",
    "sg:postcode":"27962",
    "sg:province":"NC",
    "sg:tags":[
        "pallet",
        "skid"
    ],
    "sg:website":"www.carolinamat.com",
    "wof:name":"Plymouth Pallet Co Inc",
    "wof:placetype":"venue"
},
  "geometry": {"coordinates":[-76.76894900000001,35.841394],"type":"Point"}
}