{
  "type": "Feature",
  "properties": {
    "iso:country":"US",
    "sg:address":"1047 Silas Creek Pkwy",
    "sg:city":"Winston Salem",
    "sg:classifiers":[
        {
            "category":"Professional",
            "subcategory":"Accounting & Tax Preparation",
            "type":"Services"
        }
    ],
    "sg:phone":"+1 336 722 9202",
    "sg:postcode":"27103",
    "sg:province":"NC",
    "sg:tags":[
        "return",
        "filing"
    ],
    "wof:name":"Tax Time",
    "wof:placetype":"venue"
},
  "geometry": {"coordinates":[-80.25676199999999,36.06616],"type":"Point"}
}