{
  "type": "Feature",
  "properties": {
    "addr:full":"4301 Burlington Rd Greensboro NC 27405",
    "addr:housenumber":"4301",
    "addr:postcode":"27405",
    "addr:street":"Burlington Rd",
    "iso:country":"US",
    "sg:address":"4301 Burlington Rd",
    "sg:city":"Greensboro",
    "sg:classifiers":[
        {
            "category":"Home & Garden",
            "subcategory":"Furniture",
            "type":"Retail Goods"
        }
    ],
    "sg:phone":"+1 336 954 1612",
    "sg:postcode":"27405",
    "sg:province":"NC",
    "sg:tags":[
        "mattress"
    ],
    "wof:name":"That Mattress Place",
    "wof:placetype":"venue"
},
  "geometry": {"coordinates":[-79.70149499999999,36.089799],"type":"Point"}
}