{
  "type": "Feature",
  "properties": {
    "iso:country":"US",
    "sg:address":"300 Copeland Rd",
    "sg:city":"Beaufort",
    "sg:classifiers":[
        {
            "category":"Building & Trades",
            "subcategory":"Construction",
            "type":"Services"
        }
    ],
    "sg:phone":"+1 252 728 7242",
    "sg:postcode":"28516",
    "sg:province":"NC",
    "sg:tags":[
        "dredging",
        "designer",
        "marine",
        "contractor"
    ],
    "wof:name":"King Dredging Company Inc",
    "wof:placetype":"venue"
},
  "geometry": {"coordinates":[-76.65864500000001,34.742816],"type":"Point"}
}