{
  "type": "Feature",
  "properties": {
    "addr:full":"108 N Raiford St Selma NC 27576",
    "addr:housenumber":"108",
    "addr:postcode":"27576",
    "addr:street":"N Raiford St",
    "iso:country":"US",
    "sg:address":"108 N Raiford St",
    "sg:city":"Selma",
    "sg:classifiers":[
        {
            "category":"Shopping",
            "subcategory":"Jewelry",
            "type":"Retail Goods"
        }
    ],
    "sg:phone":"+1 919 965 8582",
    "sg:postcode":"27576",
    "sg:province":"NC",
    "sg:tags":[
        "jeweler"
    ],
    "wof:name":"Selma Jewelry & Music Co",
    "wof:placetype":"venue"
},
  "geometry": {"coordinates":[-78.282776,35.536505],"type":"Point"}
}