{
  "type": "Feature",
  "properties": {
    "addr:full":"3525 Lackey St Lumberton NC 28360",
    "addr:housenumber":"3525",
    "addr:postcode":"28360",
    "addr:street":"Lackey St",
    "iso:country":"US",
    "sg:address":"3525 Lackey St",
    "sg:city":"Lumberton",
    "sg:classifiers":[
        {
            "category":"Autos & Motor Vehicles",
            "subcategory":"Automobile Sales",
            "type":"Retail Goods"
        }
    ],
    "sg:phone":"+1 910 735 0900",
    "sg:postcode":"28360",
    "sg:province":"NC",
    "sg:tags":[
        "car",
        "dealer"
    ],
    "wof:name":"Dan's Golf Cars",
    "wof:placetype":"venue"
},
  "geometry": {"coordinates":[-79.016746,34.641408],"type":"Point"}
}