{
  "type": "Feature",
  "properties": {
    "addr:full":"816 S College Rd Wilmington NC 28403",
    "addr:housenumber":"816",
    "addr:postcode":"28403",
    "addr:street":"S College Rd",
    "iso:country":"US",
    "sg:address":"816 S College Rd",
    "sg:city":"Wilmington",
    "sg:classifiers":[
        {
            "category":"Shopping",
            "subcategory":"Bicycles & Sporting Goods",
            "type":"Retail Goods"
        }
    ],
    "sg:phone":"+1 910 793 1904",
    "sg:postcode":"28403",
    "sg:province":"NC",
    "wof:name":"Dick's Sporting Goods Inc",
    "wof:placetype":"venue"
},
  "geometry": {"coordinates":[-77.883827,34.220529],"type":"Point"}
}