{
  "type": "Feature",
  "properties": {
    "iso:country":"US",
    "sg:address":"6230 Fairview Rd",
    "sg:city":"Charlotte",
    "sg:classifiers":[
        {
            "category":"Professional",
            "type":"Services"
        }
    ],
    "sg:phone":"+1 704 366 7362",
    "sg:postcode":"28210",
    "sg:province":"NC",
    "sg:tags":[
        "establishment"
    ],
    "wof:name":"Fairview Center",
    "wof:placetype":"venue"
},
  "geometry": {"coordinates":[-80.834847,35.149909],"type":"Point"}
}