{
  "type": "Feature",
  "properties": {
    "iso:country":"US",
    "sg:address":"91 Winston Rd",
    "sg:city":"Clayton",
    "sg:classifiers":[
        {
            "category":"Home & Garden",
            "subcategory":"Carpets & Floor Coverings",
            "type":"Retail Goods"
        }
    ],
    "sg:phone":"+1 919 553 6512",
    "sg:postcode":"27520",
    "sg:province":"NC",
    "wof:name":"Mitchells Carpet Service",
    "wof:placetype":"venue"
},
  "geometry": {"coordinates":[-78.533872,35.638345],"type":"Point"}
}