{
  "type": "Feature",
  "properties": {
    "iso:country":"US",
    "sg:address":"10516 Park Rd",
    "sg:city":"Charlotte",
    "sg:classifiers":[
        {
            "category":"Health Services",
            "subcategory":"Doctor",
            "type":"Services"
        }
    ],
    "sg:phone":"+1   ",
    "sg:postcode":"28210",
    "sg:province":"NC",
    "sg:tags":[
        "medical"
    ],
    "wof:name":"First Charlotte Physicians",
    "wof:placetype":"venue"
},
  "geometry": {"coordinates":[-80.870593,35.0896],"type":"Point"}
}