{
  "type": "Feature",
  "properties": {
    "iso:country":"US",
    "sg:address":"110 Duxbury Rd",
    "sg:city":"Mooresville",
    "sg:classifiers":[
        {
            "category":"Building & Trades",
            "subcategory":"Construction",
            "type":"Services"
        }
    ],
    "sg:phone":"+1 704 895 1311",
    "sg:postcode":"28115",
    "sg:province":"NC",
    "sg:tags":[
        "house"
    ],
    "wof:name":"Joyal Construction Inc",
    "wof:placetype":"venue"
},
  "geometry": {"coordinates":[-80.83095299999999,35.542821],"type":"Point"}
}