{
  "type": "Feature",
  "properties": {
    "addr:full":"59 Haywood Office Pk Waynesville NC 28785",
    "addr:housenumber":"59",
    "addr:postcode":"28785",
    "addr:street":"Pk",
    "iso:country":"US",
    "sg:address":"59 Haywood Office Pk",
    "sg:city":"Waynesville",
    "sg:classifiers":[
        {
            "category":"Wholesale",
            "subcategory":"Medical Equipment & Supplies",
            "type":"Manufacturing & Wholesale Goods"
        }
    ],
    "sg:phone":"+1 828 456 8782",
    "sg:postcode":"28785",
    "sg:province":"NC",
    "sg:tags":[
        "physician",
        "surgeon"
    ],
    "wof:name":"Rotech Healthcare",
    "wof:placetype":"venue"
},
  "geometry": {"coordinates":[-82.960708,35.527966],"type":"Point"}
}