{
  "type": "Feature",
  "properties": {
    "addr:full":"3510 Rose of Sharon Rd Durham NC 27712",
    "addr:housenumber":"3510",
    "addr:postcode":"27712",
    "addr:street":"Rose Of Sharon Rd",
    "iso:country":"US",
    "sg:address":"3510 Rose of Sharon Rd",
    "sg:city":"Durham",
    "sg:classifiers":[
        {
            "category":"Social Services",
            "subcategory":"Child Care",
            "type":"Services"
        }
    ],
    "sg:phone":"+1   ",
    "sg:postcode":"27712",
    "sg:province":"NC",
    "sg:tags":[
        "day"
    ],
    "wof:name":"Julias Child Care",
    "wof:placetype":"venue"
},
  "geometry": {"coordinates":[-78.957471,36.04392],"type":"Point"}
}