{
  "type": "Feature",
  "properties": {
    "addr:full":"6640 Wilkinson Blvd Belmont NC 28012",
    "addr:housenumber":"6640",
    "addr:postcode":"28012",
    "addr:street":"Wilkinson Blvd",
    "iso:country":"US",
    "sg:address":"6640 Wilkinson Blvd",
    "sg:city":"Belmont",
    "sg:classifiers":[
        {
            "category":"Travel",
            "subcategory":"Hotels & Motels",
            "type":"Entertainment"
        }
    ],
    "sg:phone":"+1 704 825 2160",
    "sg:postcode":"28012",
    "sg:province":"NC",
    "sg:tags":[
        "operation"
    ],
    "wof:name":"Delux Motel",
    "wof:placetype":"venue"
},
  "geometry": {"coordinates":[-81.035262,35.252211],"type":"Point"}
}