{
  "type": "Feature",
  "properties": {
    "iso:country":"US",
    "sg:address":"104 Connecticut Dr",
    "sg:city":"Chocowinity",
    "sg:classifiers":[
        {
            "category":"Wholesale",
            "subcategory":"Machinery & Supplies",
            "type":"Manufacturing & Wholesale Goods"
        },
        {
            "category":"Shopping",
            "type":"Retail Goods"
        }
    ],
    "sg:phone":"+1 252 940 4608",
    "sg:postcode":"27817",
    "sg:province":"NC",
    "sg:tags":[
        "equipment",
        "marine",
        "merchandise"
    ],
    "wof:name":"Preston Marine LLC",
    "wof:placetype":"venue"
},
  "geometry": {"coordinates":[-77.04671999999999,35.494997],"type":"Point"}
}