{
  "type": "Feature",
  "properties": {
    "addr:full":"6345 State Hwy 87 W Dublin NC 28332",
    "addr:housenumber":"6345",
    "addr:postcode":"28332",
    "addr:street":"State Hwy 87 W",
    "iso:country":"US",
    "sg:address":"6345 State Hwy 87 W",
    "sg:city":"Dublin",
    "sg:classifiers":[
        {
            "category":"Manufacturing",
            "subcategory":"Lumber",
            "type":"Manufacturing & Wholesale Goods"
        }
    ],
    "sg:phone":"+1 910 862 2929",
    "sg:postcode":"28332",
    "sg:province":"NC",
    "sg:tags":[
        "company",
        "logging"
    ],
    "wof:name":"Brisson Wood",
    "wof:placetype":"venue"
},
  "geometry": {"coordinates":[-78.712047,34.649731],"type":"Point"}
}