{
  "type": "Feature",
  "properties": {
    "iso:country":"US",
    "sg:address":"4630 Tower Rd",
    "sg:city":"Greensboro",
    "sg:classifiers":[
        {
            "category":"Building & Trades",
            "subcategory":"Construction",
            "type":"Services"
        }
    ],
    "sg:phone":"+1 336 854 0806",
    "sg:postcode":"27410",
    "sg:province":"NC",
    "sg:tags":[
        "general",
        "contractor"
    ],
    "wof:name":"Bar Construction Co",
    "wof:placetype":"venue"
},
  "geometry": {"coordinates":[-79.86760599999999,36.079405],"type":"Point"}
}