{
  "type": "Feature",
  "properties": {
    "addr:full":"111 E Broad St St Pauls NC 28384",
    "addr:housenumber":"111",
    "addr:postcode":"28384",
    "addr:street":"E Broad St",
    "iso:country":"US",
    "sg:address":"111 E Broad St",
    "sg:city":"St Pauls",
    "sg:classifiers":[
        {
            "category":"Shopping",
            "subcategory":"Musical Instruments",
            "type":"Retail Goods"
        }
    ],
    "sg:phone":"+1 910 865 3888",
    "sg:postcode":"28384",
    "sg:province":"NC",
    "sg:tags":[
        "music",
        "dealer"
    ],
    "wof:name":"Restoration Music Inc",
    "wof:placetype":"venue"
},
  "geometry": {"coordinates":[-78.97094300000001,34.806658],"type":"Point"}
}