{
  "type": "Feature",
  "properties": {
    "addr:full":"1900 Runnymede Ln Charlotte NC 28211",
    "addr:housenumber":"1900",
    "addr:postcode":"28211",
    "addr:street":"Runnymede Ln",
    "iso:country":"US",
    "sg:address":"1900 Runnymede Ln",
    "sg:city":"Charlotte",
    "sg:classifiers":[
        {
            "category":"Education",
            "subcategory":"School",
            "type":"Public Place"
        }
    ],
    "sg:phone":"+1 704 343 5835",
    "sg:postcode":"28211",
    "sg:province":"NC",
    "wof:name":"Selwyn Elementary School",
    "wof:placetype":"venue"
},
  "geometry": {"coordinates":[-80.833883,35.16555],"type":"Point"}
}