{
  "type": "Feature",
  "properties": {
    "addr:full":"1235 Wright Brothers Ave Goldsboro NC 27533",
    "addr:housenumber":"1235",
    "addr:postcode":"27533",
    "addr:street":"Wright Brothers Ave",
    "iso:country":"US",
    "sg:address":"1235 Wright Brothers Ave",
    "sg:city":"Goldsboro",
    "sg:classifiers":[
        {
            "category":"Travel",
            "subcategory":"Hotels & Motels",
            "type":"Entertainment"
        }
    ],
    "sg:phone":"+1 919 722 0385",
    "sg:postcode":"27533",
    "sg:province":"NC",
    "sg:tags":[
        "lodging"
    ],
    "wof:name":"Army and Air Force Exch Svc",
    "wof:placetype":"venue"
},
  "geometry": {"coordinates":[-77.963667,35.356379],"type":"Point"}
}