{
  "type": "Feature",
  "properties": {
    "addr:full":"4402 Stuart Andrew Blvd Charlotte NC 28217",
    "addr:housenumber":"4402",
    "addr:postcode":"28217",
    "addr:street":"Stuart Andrew Blvd",
    "iso:country":"US",
    "sg:address":"4402 Stuart Andrew Blvd",
    "sg:city":"Charlotte",
    "sg:classifiers":[
        {
            "category":"Shopping",
            "type":"Retail Goods"
        }
    ],
    "sg:phone":"+1 704 527 5100",
    "sg:postcode":"28217",
    "sg:province":"NC",
    "sg:tags":[
        "merchandise"
    ],
    "wof:name":"Business Telephone Systems",
    "wof:placetype":"venue"
},
  "geometry": {"coordinates":[-80.88952399999999,35.187946],"type":"Point"}
}