{
  "type": "Feature",
  "properties": {
    "addr:full":"5601 Roanne Way Greensboro NC 27409",
    "addr:housenumber":"5601",
    "addr:postcode":"27409",
    "addr:street":"Roanne Way",
    "iso:country":"US",
    "sg:address":"5601 Roanne Way",
    "sg:city":"Greensboro",
    "sg:classifiers":[
        {
            "category":"Building & Trades",
            "subcategory":"Construction",
            "type":"Services"
        }
    ],
    "sg:phone":"+1 336 852 0441",
    "sg:postcode":"27409",
    "sg:province":"NC",
    "sg:tags":[
        "general",
        "nonresidential",
        "contractor"
    ],
    "wof:name":"Cape Fear Construction Co Inc",
    "wof:placetype":"venue"
},
  "geometry": {"coordinates":[-79.91112,36.063289],"type":"Point"}
}