{
  "type": "Feature",
  "properties": {
    "addr:full":"3800 Lily Farm Rd Greensboro NC 27406",
    "addr:housenumber":"3800",
    "addr:postcode":"27406",
    "addr:street":"Lily Farm Rd",
    "iso:country":"US",
    "sg:address":"3800 Lily Farm Rd",
    "sg:city":"Greensboro",
    "sg:classifiers":[
        {
            "category":"Building & Trades",
            "subcategory":"Construction",
            "type":"Services"
        }
    ],
    "sg:phone":"+1 336 674 6563",
    "sg:postcode":"27406",
    "sg:province":"NC",
    "sg:tags":[
        "house"
    ],
    "wof:name":"Scott Wards Custom Homes LLC",
    "wof:placetype":"venue"
},
  "geometry": {"coordinates":[-79.71257,36.015062],"type":"Point"}
}