{
  "type": "Feature",
  "properties": {
    "addr:full":"105 Hawthorne Dr Wilmington NC 28403",
    "addr:housenumber":"105",
    "addr:postcode":"28403",
    "addr:street":"Hawthorne Dr",
    "iso:country":"US",
    "sg:address":"105 Hawthorne Dr",
    "sg:city":"Wilmington",
    "sg:classifiers":[
        {
            "category":"Personal",
            "subcategory":"Beauty Salon",
            "type":"Services"
        }
    ],
    "sg:phone":"+1   ",
    "sg:postcode":"28403",
    "sg:province":"NC",
    "sg:tags":[
        "shop"
    ],
    "wof:name":"Shear Magic",
    "wof:placetype":"venue"
},
  "geometry": {"coordinates":[-77.86394199999999,34.209166],"type":"Point"}
}