{
  "type": "Feature",
  "properties": {
    "iso:country":"US",
    "sg:address":"3606 N Elm St Suite K",
    "sg:city":"Greensboro",
    "sg:classifiers":[
        {
            "category":"Banks & Credit Unions",
            "subcategory":"Investment Brokerage",
            "type":"Services"
        },
        {
            "category":"Banks & Credit Unions",
            "subcategory":"Bank",
            "type":"Services"
        },
        {
            "category":"Banks & Credit Unions",
            "subcategory":"Financial Services",
            "type":"Services"
        }
    ],
    "sg:phone":"+1 336 282 4328",
    "sg:postcode":"27455",
    "sg:province":"NC",
    "sg:tags":[
        "mutual",
        "retirement",
        "broker",
        "fund",
        "planning",
        "security",
        "bond",
        "stock"
    ],
    "sg:website":"http://www.edwardjones.com/en_US/fa/index.html&CIRN=937102",
    "wof:name":"Edward Jones - Financial Advisor: MIKE STIPANOV",
    "wof:placetype":"venue"
},
  "geometry": {"coordinates":[-79.79782299999999,36.131388],"type":"Point"}
}