{
  "type": "Feature",
  "properties": {
    "iso:country":"US",
    "sg:address":"2314 Sweet Home Church Rd",
    "sg:city":"Elizabethtown",
    "sg:classifiers":[
        {
            "category":"Freight",
            "type":"Transportation"
        }
    ],
    "sg:phone":"+1 910 588 4112",
    "sg:postcode":"28337",
    "sg:province":"NC",
    "sg:tags":[
        "operator",
        "trucking"
    ],
    "wof:name":"Back Woods Frieght Inc",
    "wof:placetype":"venue"
},
  "geometry": {"coordinates":[-78.56025,34.681104],"type":"Point"}
}