{
  "type": "Feature",
  "properties": {
    "iso:country":"US",
    "sg:address":"219 Oakland St",
    "sg:city":"Lowell",
    "sg:classifiers":[
        {
            "category":"Manufacturing",
            "subcategory":"Printing",
            "type":"Manufacturing & Wholesale Goods"
        }
    ],
    "sg:phone":"+1 704 824 2667",
    "sg:postcode":"28098",
    "sg:province":"NC",
    "sg:tags":[
        "screen"
    ],
    "wof:name":"KEDS Inc",
    "wof:placetype":"venue"
},
  "geometry": {"coordinates":[-81.107124,35.276746],"type":"Point"}
}