{
  "type": "Feature",
  "properties": {
    "iso:country":"US",
    "sg:address":"131 Oliver St",
    "sg:city":"Randleman",
    "sg:classifiers":[
        {
            "category":"Manufacturing",
            "subcategory":"Furniture",
            "type":"Manufacturing & Wholesale Goods"
        }
    ],
    "sg:phone":"+1 336 495 1131",
    "sg:postcode":"27317",
    "sg:province":"NC",
    "wof:name":"Motion Eaze NC Lbr Plant 1",
    "wof:placetype":"venue"
},
  "geometry": {"coordinates":[-79.808465,35.809942],"type":"Point"}
}