{
  "type": "Feature",
  "properties": {
    "addr:full":"1005 Monroe St Carthage NC 28327",
    "addr:housenumber":"1005",
    "addr:postcode":"28327",
    "addr:street":"Monroe St",
    "iso:country":"US",
    "sg:address":"1005 Monroe St",
    "sg:city":"Carthage",
    "sg:classifiers":[
        {
            "category":"Restaurant",
            "type":"Food & Drink"
        }
    ],
    "sg:menulink":"http://www.allmenus.com/nc/carthage/54898-peking-wok/menu/",
    "sg:phone":"+1 910 947 7770",
    "sg:postcode":"28327",
    "sg:province":"NC",
    "sg:tags":[
        "asian",
        "chinese"
    ],
    "wof:name":"Peking Wok",
    "wof:placetype":"venue"
},
  "geometry": {"coordinates":[-79.401663,35.341007],"type":"Point"}
}