{
  "type": "Feature",
  "properties": {
    "iso:country":"US",
    "sg:address":"1547 West Blvd",
    "sg:city":"Charlotte",
    "sg:classifiers":[
        {
            "category":"Insurance",
            "subcategory":"Insurance Agent",
            "type":"Services"
        }
    ],
    "sg:phone":"+1 704 334 4363",
    "sg:postcode":"28208",
    "sg:province":"NC",
    "wof:name":"Value American Insurance",
    "wof:placetype":"venue"
},
  "geometry": {"coordinates":[-80.881092,35.21661],"type":"Point"}
}