{
  "type": "Feature",
  "properties": {
    "addr:full":"2125 Austin Chaney Rd Wingate NC 28174",
    "addr:housenumber":"2125",
    "addr:postcode":"28174",
    "addr:street":"Austin Chaney Rd",
    "iso:country":"US",
    "sg:address":"2125 Austin Chaney Rd",
    "sg:city":"Wingate",
    "sg:classifiers":[
        {
            "category":"Government",
            "subcategory":"Office",
            "type":"Public Place"
        }
    ],
    "sg:phone":"+1 704 233 1477",
    "sg:postcode":"28174",
    "sg:province":"NC",
    "wof:name":"Union County Transfer Station",
    "wof:placetype":"venue"
},
  "geometry": {"coordinates":[-80.456127,35.045758],"type":"Point"}
}