{
  "type": "Feature",
  "properties": {
    "addr:full":"2302 S Horner Blvd Sanford NC 27330",
    "addr:housenumber":"2302",
    "addr:postcode":"27330",
    "addr:street":"S Horner Blvd",
    "iso:country":"US",
    "sg:address":"2302 S Horner Blvd",
    "sg:city":"Sanford",
    "sg:classifiers":[
        {
            "category":"Retail",
            "subcategory":"Laundry & Dry Cleaning",
            "type":"Services"
        }
    ],
    "sg:phone":"+1 919 776 1020",
    "sg:postcode":"27330",
    "sg:province":"NC",
    "wof:name":"Town & Country Laundry",
    "wof:placetype":"venue"
},
  "geometry": {"coordinates":[-79.14733,35.460828],"type":"Point"}
}