{
  "type": "Feature",
  "properties": {
    "addr:full":"305 Trueblood Rd Halifax NC 27839",
    "addr:housenumber":"305",
    "addr:postcode":"27839",
    "addr:street":"Trueblood Rd",
    "iso:country":"US",
    "sg:address":"305 Trueblood Rd",
    "sg:city":"Halifax",
    "sg:classifiers":[
        {
            "category":"Building & Trades",
            "subcategory":"Construction",
            "type":"Services"
        }
    ],
    "sg:phone":"+1 252 536 2617",
    "sg:postcode":"27839",
    "sg:province":"NC",
    "sg:tags":[
        "carpentry",
        "contractor"
    ],
    "wof:name":"James Littlefield",
    "wof:placetype":"venue"
},
  "geometry": {"coordinates":[-77.615464,36.396048],"type":"Point"}
}