{
  "type": "Feature",
  "properties": {
    "addr:full":"6441 Windyrush Rd Charlotte NC 28226",
    "addr:housenumber":"6441",
    "addr:postcode":"28226",
    "addr:street":"Windyrush Rd",
    "iso:country":"US",
    "sg:address":"6441 Windyrush Rd",
    "sg:city":"Charlotte",
    "sg:classifiers":[
        {
            "category":"Recreation",
            "type":"Entertainment"
        }
    ],
    "sg:phone":"+1 704 542 9645",
    "sg:postcode":"28226",
    "sg:province":"NC",
    "sg:tags":[
        "club",
        "membership"
    ],
    "wof:name":"Windyrush Country Club",
    "wof:placetype":"venue"
},
  "geometry": {"coordinates":[-80.80023799999999,35.116383],"type":"Point"}
}