{
  "type": "Feature",
  "properties": {
    "iso:country":"US",
    "sg:address":"615 Fairbluff Dr",
    "sg:city":"Hope Mills",
    "sg:classifiers":[
        {
            "category":"Building & Trades",
            "subcategory":"Construction",
            "type":"Services"
        }
    ],
    "sg:phone":"+1 910 426 8646",
    "sg:postcode":"28348",
    "sg:province":"NC",
    "sg:tags":[
        "house"
    ],
    "wof:name":"Pami Remodeling Co",
    "wof:placetype":"venue"
},
  "geometry": {"coordinates":[-78.917314,34.975163],"type":"Point"}
}