{
  "type": "Feature",
  "properties": {
    "iso:country":"US",
    "sg:address":"6770 Buttermere Dr",
    "sg:city":"Fayetteville",
    "sg:classifiers":[
        {
            "category":"Shopping",
            "subcategory":"Clothing, Apparel, & Fashions",
            "type":"Retail Goods"
        }
    ],
    "sg:phone":"+1 910 487 5569",
    "sg:postcode":"28314",
    "sg:province":"NC",
    "wof:name":"Call First Ladies",
    "wof:placetype":"venue"
},
  "geometry": {"coordinates":[-79.062719,35.061792],"type":"Point"}
}