{
  "type": "Feature",
  "properties": {
    "addr:full":"4113 McManus Rd Monroe NC 28112",
    "addr:housenumber":"4113",
    "addr:postcode":"28112",
    "addr:street":"Mcmanus Rd",
    "iso:country":"US",
    "sg:address":"4113 McManus Rd",
    "sg:city":"Monroe",
    "sg:classifiers":[
        {
            "category":"Building & Trades",
            "subcategory":"Construction",
            "type":"Services"
        }
    ],
    "sg:phone":"+1 704 764 9750",
    "sg:postcode":"28112",
    "sg:province":"NC",
    "sg:tags":[
        "hanging",
        "contractor"
    ],
    "wof:name":"Brush Stroke",
    "wof:placetype":"venue"
},
  "geometry": {"coordinates":[-80.592184,34.888461],"type":"Point"}
}