{
  "type": "Feature",
  "properties": {
    "addr:full":"2401 S Horner Blvd Sanford NC 27330",
    "addr:housenumber":"2401",
    "addr:postcode":"27330",
    "addr:street":"S Horner Blvd",
    "iso:country":"US",
    "sg:address":"2401 S Horner Blvd",
    "sg:city":"Sanford",
    "sg:classifiers":[
        {
            "category":"Restaurant",
            "type":"Food & Drink"
        }
    ],
    "sg:phone":"+1 919 776 1122",
    "sg:postcode":"27330",
    "sg:province":"NC",
    "sg:tags":[
        "eating"
    ],
    "wof:name":"Brass Kettle Family Restaurant",
    "wof:placetype":"venue"
},
  "geometry": {"coordinates":[-79.146367,35.460091],"type":"Point"}
}