{
  "type": "Feature",
  "properties": {
    "iso:country":"US",
    "sg:address":"2300 Red Forest Rd",
    "sg:city":"Greensboro",
    "sg:classifiers":[
        {
            "category":"Insurance",
            "subcategory":"Insurance Agent",
            "type":"Services"
        }
    ],
    "sg:phone":"+1 336 282 4960",
    "sg:postcode":"27410",
    "sg:province":"NC",
    "sg:tags":[
        "accident"
    ],
    "wof:name":"Bullock & Assoc",
    "wof:placetype":"venue"
},
  "geometry": {"coordinates":[-79.84961800000001,36.11138],"type":"Point"}
}