{
  "type": "Feature",
  "properties": {
    "addr:full":"2682 Hester Rd Oxford NC 27522",
    "addr:housenumber":"2682",
    "addr:postcode":"27522",
    "addr:street":"Hester Rd",
    "iso:country":"US",
    "sg:address":"2682 Hester Rd",
    "sg:city":"Oxford",
    "sg:phone":"+1 919 528 0016",
    "sg:postcode":"27522",
    "sg:province":"NC",
    "sg:tags":[
        "farm",
        "tobacco"
    ],
    "wof:name":"Al Fuller",
    "wof:placetype":"venue"
},
  "geometry": {"coordinates":[-78.641987,36.167505],"type":"Point"}
}