{
  "type": "Feature",
  "properties": {
    "addr:full":"6011 Fayetteville Rd Durham NC 27713",
    "addr:housenumber":"6011",
    "addr:postcode":"27713",
    "addr:street":"Fayetteville Rd",
    "iso:country":"US",
    "sg:address":"6011 Fayetteville Rd",
    "sg:city":"Durham",
    "sg:classifiers":[
        {
            "category":"Professional",
            "subcategory":"Employment Agencies",
            "type":"Services"
        }
    ],
    "sg:phone":"+1 919 732 6272",
    "sg:postcode":"27713",
    "sg:province":"NC",
    "sg:tags":[
        "consultant",
        "search",
        "executive",
        "business"
    ],
    "wof:name":"Management Recruiters Intl",
    "wof:placetype":"venue"
},
  "geometry": {"coordinates":[-78.93228499999999,35.915238],"type":"Point"}
}