{
  "type": "Feature",
  "properties": {
    "iso:country":"US",
    "sg:address":"306 Beaman St",
    "sg:city":"Clinton",
    "sg:classifiers":[
        {
            "category":"Health Services",
            "subcategory":"Doctor",
            "type":"Services"
        }
    ],
    "sg:phone":"+1 910 592 5164",
    "sg:postcode":"28328",
    "sg:province":"NC",
    "sg:tags":[
        "physician",
        "surgeon"
    ],
    "wof:name":"John C Merritt MD",
    "wof:placetype":"venue"
},
  "geometry": {"coordinates":[-78.322284,35.004528],"type":"Point"}
}