{
  "type": "Feature",
  "properties": {
    "iso:country":"US",
    "sg:address":"40 Maitland Dr",
    "sg:city":"Roanoke Rapids",
    "sg:classifiers":[
        {
            "category":"Building & Trades",
            "subcategory":"Construction",
            "type":"Services"
        }
    ],
    "sg:phone":"+1 252 537 7295",
    "sg:postcode":"27870",
    "sg:province":"NC",
    "sg:tags":[
        "residential"
    ],
    "wof:name":"Arthur M Davis",
    "wof:placetype":"venue"
},
  "geometry": {"coordinates":[-77.669875,36.433395],"type":"Point"}
}