{
  "type": "Feature",
  "properties": {
    "iso:country":"US",
    "sg:address":"506 Roxboro St SE",
    "sg:city":"Bolivia",
    "sg:classifiers":[
        {
            "category":"Food & Beverages",
            "subcategory":"Meat & Fish",
            "type":"Retail Goods"
        }
    ],
    "sg:phone":"+1 910 842 8388",
    "sg:postcode":"28422",
    "sg:province":"NC",
    "sg:tags":[
        "preparation",
        "capture",
        "seafood",
        "sale"
    ],
    "wof:name":"Sunset Harbor Seafood",
    "wof:placetype":"venue"
},
  "geometry": {"coordinates":[-78.203991,33.923067],"type":"Point"}
}