{
  "type": "Feature",
  "properties": {
    "iso:country":"US",
    "sg:address":"6011 Plaza Ln",
    "sg:city":"Charlotte",
    "sg:classifiers":[
        {
            "category":"Professional",
            "subcategory":"Business Services",
            "type":"Services"
        }
    ],
    "sg:phone":"+1   ",
    "sg:postcode":"28215",
    "sg:province":"NC",
    "wof:name":"Mood Musical Audio & Video",
    "wof:placetype":"venue"
},
  "geometry": {"coordinates":[-80.743116,35.254198],"type":"Point"}
}