{
  "type": "Feature",
  "properties": {
    "addr:full":"2501 Richardson Dr Reidsville NC 27320",
    "addr:housenumber":"2501",
    "addr:postcode":"27320",
    "addr:street":"Richardson Dr",
    "iso:country":"US",
    "sg:address":"2501 Richardson Dr",
    "sg:city":"Reidsville",
    "sg:classifiers":[
        {
            "category":"Home & Garden",
            "subcategory":"Building Materials",
            "type":"Retail Goods"
        },
        {
            "category":"Wholesale",
            "subcategory":"Hardware",
            "type":"Manufacturing & Wholesale Goods"
        }
    ],
    "sg:phone":"+1 336 616 1717",
    "sg:postcode":"27320",
    "sg:province":"NC",
    "sg:tags":[
        "plumbing",
        "fixture",
        "merchandise",
        "supply"
    ],
    "wof:name":"Mid State Plumbing Supply Inc",
    "wof:placetype":"venue"
},
  "geometry": {"coordinates":[-79.69114,36.334314],"type":"Point"}
}