{
  "type": "Feature",
  "properties": {
    "addr:full":"161 Funder Rd Mocksville NC 27028",
    "addr:housenumber":"161",
    "addr:postcode":"27028",
    "addr:street":"Funder Rd",
    "iso:country":"US",
    "sg:address":"161 Funder Rd",
    "sg:city":"Mocksville",
    "sg:classifiers":[
        {
            "category":"Manufacturing",
            "subcategory":"Apparel",
            "type":"Manufacturing & Wholesale Goods"
        }
    ],
    "sg:phone":"+1 336 751 0878",
    "sg:postcode":"27028",
    "sg:province":"NC",
    "sg:tags":[
        "sewing",
        "contractor"
    ],
    "sg:website":"www.southeasternsewing.net",
    "wof:name":"Southeastern Sewing Svc Inc",
    "wof:placetype":"venue"
},
  "geometry": {"coordinates":[-80.537909,35.900072],"type":"Point"}
}