{
  "type": "Feature",
  "properties": {
    "iso:country":"US",
    "sg:address":"15 Miller St",
    "sg:city":"Belmont",
    "sg:classifiers":[
        {
            "category":"Real Estate",
            "subcategory":"Real Estate Agent",
            "type":"Services"
        }
    ],
    "sg:phone":"+1 704 827 4961",
    "sg:postcode":"28012",
    "sg:province":"NC",
    "sg:tags":[
        "development",
        "management"
    ],
    "wof:name":"Parkdale Mills Propert MGT",
    "wof:placetype":"venue"
},
  "geometry": {"coordinates":[-81.048013,35.278569],"type":"Point"}
}