{
  "type": "Feature",
  "properties": {
    "addr:full":"12019 State Hwy 150 Linwood NC 27299",
    "addr:housenumber":"12019",
    "addr:postcode":"27299",
    "addr:street":"State Hwy 150",
    "iso:country":"US",
    "sg:address":"12019 State Hwy 150",
    "sg:city":"Linwood",
    "sg:phone":"+1 336 752 2660",
    "sg:postcode":"27299",
    "sg:province":"NC",
    "sg:tags":[
        "oil"
    ],
    "wof:name":"Lakeview Oil Co",
    "wof:placetype":"venue"
},
  "geometry": {"coordinates":[-80.37762499999999,35.737264],"type":"Point"}
}