{
  "type": "Feature",
  "properties": {
    "iso:country":"US",
    "sg:address":"986 Trinity Rd",
    "sg:city":"Raleigh",
    "sg:classifiers":[
        {
            "category":"Fast Food",
            "type":"Food & Drink"
        }
    ],
    "sg:phone":"+1 919 816 8491",
    "sg:postcode":"27607",
    "sg:province":"NC",
    "sg:tags":[
        "chicken",
        "wing"
    ],
    "wof:name":"Carolina Chicken Inc",
    "wof:placetype":"venue"
},
  "geometry": {"coordinates":[-78.75160200000001,35.7911],"type":"Point"}
}