{
  "type": "Feature",
  "properties": {
    "addr:full":"9005 Sharpe Rd Rocky Mount NC 27803",
    "addr:housenumber":"9005",
    "addr:postcode":"27803",
    "addr:street":"Sharpe Rd",
    "iso:country":"US",
    "sg:address":"9005 Sharpe Rd",
    "sg:city":"Rocky Mount",
    "sg:classifiers":[
        {
            "category":"Retail",
            "subcategory":"Animal Services",
            "type":"Services"
        }
    ],
    "sg:phone":"+1 252 446 5557",
    "sg:postcode":"27803",
    "sg:province":"NC",
    "sg:tags":[
        "pet",
        "boarding",
        "sitting"
    ],
    "wof:name":"Sisters Two Pet Crew Inc",
    "wof:placetype":"venue"
},
  "geometry": {"coordinates":[-77.840485,35.86422],"type":"Point"}
}