{
  "type": "Feature",
  "properties": {
    "addr:full":"285 Haywood Rd Asheville NC 28806",
    "addr:housenumber":"285",
    "addr:postcode":"28806",
    "addr:street":"Haywood Rd",
    "iso:country":"US",
    "sg:address":"285 Haywood Rd",
    "sg:city":"Asheville",
    "sg:classifiers":[
        {
            "category":"Social Services",
            "subcategory":"Child Care",
            "type":"Services"
        }
    ],
    "sg:phone":"+1 828 254 1080",
    "sg:postcode":"28806",
    "sg:province":"NC",
    "wof:name":"Guardian Angel Learning Acad",
    "wof:placetype":"venue"
},
  "geometry": {"coordinates":[-82.574826,35.57779],"type":"Point"}
}