{
  "type": "Feature",
  "properties": {
    "addr:full":"7332 Michaels Landing Dr Charlotte NC 28262",
    "addr:housenumber":"7332",
    "addr:postcode":"28262",
    "addr:street":"Michaels Landing Dr",
    "iso:country":"US",
    "sg:address":"7332 Michaels Landing Dr",
    "sg:city":"Charlotte",
    "sg:classifiers":[
        {
            "category":"Real Estate",
            "subcategory":"Real Estate Operator",
            "type":"Services"
        }
    ],
    "sg:phone":"+1 704 597 5006",
    "sg:postcode":"28262",
    "sg:province":"NC",
    "sg:tags":[
        "townhouses"
    ],
    "wof:name":"Michaels Landing Townhomes",
    "wof:placetype":"venue"
},
  "geometry": {"coordinates":[-80.790851,35.295185],"type":"Point"}
}