{
  "type": "Feature",
  "properties": {
    "iso:country":"US",
    "sg:address":"251 S Kerr Ave",
    "sg:city":"Wilmington",
    "sg:classifiers":[
        {
            "category":"Real Estate",
            "subcategory":"Real Estate Agent",
            "type":"Services"
        }
    ],
    "sg:phone":"+1 910 395 1000",
    "sg:postcode":"28403",
    "sg:province":"NC",
    "sg:tags":[
        "consultant"
    ],
    "wof:name":"Buddy Blake Realtor",
    "wof:placetype":"venue"
},
  "geometry": {"coordinates":[-77.88861,34.237084],"type":"Point"}
}