{
  "type": "Feature",
  "properties": {
    "iso:country":"US",
    "sg:address":"3121 3rd Street Dr NW",
    "sg:city":"Hickory",
    "sg:classifiers":[
        {
            "category":"Building & Trades",
            "subcategory":"Construction",
            "type":"Services"
        }
    ],
    "sg:phone":"+1 828 324 0515",
    "sg:postcode":"28601",
    "sg:province":"NC",
    "sg:tags":[
        "home",
        "custom"
    ],
    "wof:name":"Greathouse Jones Cnstr Co",
    "wof:placetype":"venue"
},
  "geometry": {"coordinates":[-81.33707099999999,35.777206],"type":"Point"}
}