{
  "type": "Feature",
  "properties": {
    "addr:full":"329 16th Ave NW Hickory NC 28601",
    "addr:housenumber":"329",
    "addr:postcode":"28601",
    "addr:street":"16Th Ave Nw",
    "iso:country":"US",
    "sg:address":"329 16th Ave NW",
    "sg:city":"Hickory",
    "sg:classifiers":[
        {
            "category":"Professional",
            "subcategory":"Computer Services",
            "type":"Services"
        }
    ],
    "sg:phone":"+1 828 324 5524",
    "sg:postcode":"28601",
    "sg:province":"NC",
    "wof:name":"Evans Technologies",
    "wof:placetype":"venue"
},
  "geometry": {"coordinates":[-81.342945,35.754212],"type":"Point"}
}