{
  "type": "Feature",
  "properties": {
    "addr:full":"1530 Ardsley St Winston Salem NC 27103",
    "addr:housenumber":"1530",
    "addr:postcode":"27103",
    "addr:street":"Ardsley St",
    "iso:country":"US",
    "sg:address":"1530 Ardsley St",
    "sg:city":"Winston Salem",
    "sg:classifiers":[
        {
            "category":"Real Estate",
            "subcategory":"Real Estate Operator",
            "type":"Services"
        }
    ],
    "sg:phone":"+1 336 723 8708",
    "sg:postcode":"27103",
    "sg:province":"NC",
    "sg:tags":[
        "building",
        "apartment"
    ],
    "wof:name":"96 Ardsleys Apts",
    "wof:placetype":"venue"
},
  "geometry": {"coordinates":[-80.260893,36.078727],"type":"Point"}
}