{
  "type": "Feature",
  "properties": {
    "addr:full":"254 Normans Ln Winston Salem NC 27107",
    "addr:housenumber":"254",
    "addr:postcode":"27107",
    "addr:street":"Normans Ln",
    "iso:country":"US",
    "sg:address":"254 Normans Ln",
    "sg:city":"Winston Salem",
    "sg:classifiers":[
        {
            "category":"Retail",
            "subcategory":"Laundry & Dry Cleaning",
            "type":"Services"
        }
    ],
    "sg:phone":"+1 336 784 6282",
    "sg:postcode":"27107",
    "sg:province":"NC",
    "sg:tags":[
        "cleaners",
        "rug",
        "carpet"
    ],
    "wof:name":"DMP Pro Carpet Cleaners",
    "wof:placetype":"venue"
},
  "geometry": {"coordinates":[-80.190102,36.006929],"type":"Point"}
}