{
  "type": "Feature",
  "properties": {
    "iso:country":"US",
    "sg:address":"101 Parkgrace Rd",
    "sg:city":"Kings Mountain",
    "sg:classifiers":[
        {
            "category":"Restaurant",
            "type":"Food & Drink"
        }
    ],
    "sg:phone":"+1 704 739 8116",
    "sg:postcode":"28086",
    "sg:province":"NC",
    "wof:name":"Wendells Bar B Que & Catering",
    "wof:placetype":"venue"
},
  "geometry": {"coordinates":[-81.36192699999999,35.220651],"type":"Point"}
}