{
  "type": "Feature",
  "properties": {
    "iso:country":"US",
    "sg:address":"129 Industrial Ave",
    "sg:city":"Greensboro",
    "sg:classifiers":[
        {
            "category":"Organizations",
            "subcategory":"Labor Organization",
            "type":"Services"
        }
    ],
    "sg:phone":"+1 336 275 8966",
    "sg:postcode":"27406",
    "sg:province":"NC",
    "wof:name":"Professional Firefighters Assn",
    "wof:placetype":"venue"
},
  "geometry": {"coordinates":[-79.79160899999999,36.029151],"type":"Point"}
}