{
  "type": "Feature",
  "properties": {
    "addr:full":"2320 E Broad St Statesville NC 28625",
    "addr:housenumber":"2320",
    "addr:postcode":"28625",
    "addr:street":"E Broad St",
    "iso:country":"US",
    "sg:address":"2320 E Broad St",
    "sg:city":"Statesville",
    "sg:classifiers":[
        {
            "category":"Organizations",
            "subcategory":"Religious Organization",
            "type":"Services"
        }
    ],
    "sg:phone":"+1   ",
    "sg:postcode":"28625",
    "sg:province":"NC",
    "wof:name":"Diamond Hill Baptist Church",
    "wof:placetype":"venue"
},
  "geometry": {"coordinates":[-80.859093,35.790822],"type":"Point"}
}