{
  "type": "Feature",
  "properties": {
    "iso:country":"US",
    "sg:address":"2222 S Fayetteville St",
    "sg:city":"Asheboro",
    "sg:classifiers":[
        {
            "category":"Education",
            "subcategory":"College",
            "type":"Public Place"
        }
    ],
    "sg:phone":"+1 336 625 4793",
    "sg:postcode":"27205",
    "sg:province":"NC",
    "sg:tags":[
        "academic",
        "school"
    ],
    "wof:name":"North Carolina State Univ",
    "wof:placetype":"venue"
},
  "geometry": {"coordinates":[-79.819351,35.676239],"type":"Point"}
}