{
  "type": "Feature",
  "properties": {
    "addr:full":"5600 Albemarle Rd Charlotte NC 28212",
    "addr:housenumber":"5600",
    "addr:postcode":"28212",
    "addr:street":"Albemarle Rd",
    "iso:country":"US",
    "sg:address":"5600 Albemarle Rd",
    "sg:city":"Charlotte",
    "sg:classifiers":[
        {
            "category":"Personal",
            "subcategory":"Barber",
            "type":"Services"
        }
    ],
    "sg:phone":"+1 704 568 7162",
    "sg:postcode":"28212",
    "sg:province":"NC",
    "sg:tags":[
        "shop"
    ],
    "wof:name":"Top Notch Barber Shop Inc",
    "wof:placetype":"venue"
},
  "geometry": {"coordinates":[-80.752616,35.203916],"type":"Point"}
}