{
  "type": "Feature",
  "properties": {
    "iso:country":"US",
    "sg:address":"3510 Brushy Ln",
    "sg:city":"Charlotte",
    "sg:classifiers":[
        {
            "category":"Retail",
            "subcategory":"Animal Services",
            "type":"Services"
        }
    ],
    "sg:phone":"+1 704 844 9657",
    "sg:postcode":"28270",
    "sg:province":"NC",
    "sg:tags":[
        "pet",
        "boarding",
        "kennel"
    ],
    "wof:name":"Macdawg's Pet Watch",
    "wof:placetype":"venue"
},
  "geometry": {"coordinates":[-80.748943,35.075098],"type":"Point"}
}