{
  "type": "Feature",
  "properties": {
    "addr:full":"1113 Winslow Rd Robersonville NC 27871",
    "addr:housenumber":"1113",
    "addr:postcode":"27871",
    "addr:street":"Winslow Rd",
    "iso:country":"US",
    "sg:address":"1113 Winslow Rd",
    "sg:city":"Robersonville",
    "sg:classifiers":[
        {
            "category":"Autos & Motor Vehicles",
            "subcategory":"Automobile Sales",
            "type":"Retail Goods"
        },
        {
            "category":"Retail",
            "subcategory":"Auto Repair",
            "type":"Services"
        }
    ],
    "sg:phone":"+1 252 795 3612",
    "sg:postcode":"27871",
    "sg:province":"NC",
    "sg:tags":[
        "car",
        "dealer",
        "general"
    ],
    "wof:name":"Williams Service Center",
    "wof:placetype":"venue"
},
  "geometry": {"coordinates":[-77.24096400000001,35.869668],"type":"Point"}
}