{
  "type": "Feature",
  "properties": {
    "iso:country":"US",
    "sg:address":"1605 Southport-Supply Rd SE",
    "sg:city":"Bolivia",
    "sg:classifiers":[
        {
            "category":"Retail",
            "subcategory":"Auto Repair",
            "type":"Services"
        }
    ],
    "sg:phone":"+1   ",
    "sg:postcode":"28422",
    "sg:province":"NC",
    "sg:tags":[
        "transmission"
    ],
    "wof:name":"Jimmys Transm & Auto Repr",
    "wof:placetype":"venue"
},
  "geometry": {"coordinates":[-78.21838099999999,33.992913],"type":"Point"}
}