{
  "type": "Feature",
  "properties": {
    "iso:country":"US",
    "sg:address":"800 Trinity St",
    "sg:city":"Thomasville",
    "sg:classifiers":[
        {
            "category":"Autos & Motor Vehicles",
            "subcategory":"Automobile Sales",
            "type":"Retail Goods"
        }
    ],
    "sg:phone":"+1 336 476 1449",
    "sg:postcode":"27360",
    "sg:province":"NC",
    "sg:tags":[
        "car",
        "dealer"
    ],
    "wof:name":"Watson's Automotive",
    "wof:placetype":"venue"
},
  "geometry": {"coordinates":[-80.07229100000001,35.8863],"type":"Point"}
}