{
  "type": "Feature",
  "properties": {
    "iso:country":"US",
    "sg:address":"7262 Honeysuckle Ln",
    "sg:city":"Bailey",
    "sg:classifiers":[
        {
            "category":"Professional",
            "type":"Services"
        }
    ],
    "sg:phone":"+1 252 235 6033",
    "sg:postcode":"27807",
    "sg:province":"NC",
    "wof:name":"Robert D Gray",
    "wof:placetype":"venue"
},
  "geometry": {"coordinates":[-78.124782,35.824928],"type":"Point"}
}