{
  "type": "Feature",
  "properties": {
    "iso:country":"US",
    "sg:address":"4408 Murchison Rd",
    "sg:city":"Fayetteville",
    "sg:classifiers":[
        {
            "category":"Parking",
            "type":"Transportation"
        }
    ],
    "sg:phone":"+1   ",
    "sg:postcode":"28311",
    "sg:province":"NC",
    "sg:tags":[
        "automobile"
    ],
    "wof:name":"Sandhilld Off Road & Truc",
    "wof:placetype":"venue"
},
  "geometry": {"coordinates":[-78.920513,35.102857],"type":"Point"}
}