{
  "type": "Feature",
  "properties": {
    "addr:full":"1540 Hanes Mall Blvd Winston Salem NC 27103",
    "addr:housenumber":"1540",
    "addr:postcode":"27103",
    "addr:street":"Hanes Mall Blvd",
    "iso:country":"US",
    "sg:address":"1540 Hanes Mall Blvd",
    "sg:city":"Winston Salem",
    "sg:classifiers":[
        {
            "category":"Retail",
            "subcategory":"Auto Repair",
            "type":"Services"
        }
    ],
    "sg:phone":"+1 336 724 1966",
    "sg:postcode":"27103",
    "sg:province":"NC",
    "sg:tags":[
        "body",
        "automobile",
        "painting"
    ],
    "sg:website":"www.iansbodyshop.com",
    "wof:name":"Ian's Body Shop Inc",
    "wof:placetype":"venue"
},
  "geometry": {"coordinates":[-80.331844,36.06904],"type":"Point"}
}