{
  "type": "Feature",
  "properties": {
    "addr:full":"1226 Weymouth Ln Charlotte NC 28270",
    "addr:housenumber":"1226",
    "addr:postcode":"28270",
    "addr:street":"Weymouth Ln",
    "iso:country":"US",
    "sg:address":"1226 Weymouth Ln",
    "sg:city":"Charlotte",
    "sg:classifiers":[
        {
            "category":"Shopping",
            "subcategory":"Used Merchandise",
            "type":"Retail Goods"
        }
    ],
    "sg:phone":"+1 704 846 8023",
    "sg:postcode":"28270",
    "sg:province":"NC",
    "wof:name":"Then & Again Antiques",
    "wof:placetype":"venue"
},
  "geometry": {"coordinates":[-80.764382,35.117448],"type":"Point"}
}