{
  "type": "Feature",
  "properties": {
    "addr:full":"1118 E Caswell St Wadesboro NC 28170",
    "addr:housenumber":"1118",
    "addr:postcode":"28170",
    "addr:street":"E Caswell St",
    "iso:country":"US",
    "sg:address":"1118 E Caswell St",
    "sg:city":"Wadesboro",
    "sg:classifiers":[
        {
            "category":"Restaurant",
            "type":"Food & Drink"
        }
    ],
    "sg:menulink":"http://www.allmenus.com/nc/wadesboro/73392-pizza-hut/menu/",
    "sg:phone":"+1 704 694 9472",
    "sg:postcode":"28170",
    "sg:province":"NC",
    "sg:tags":[
        "american",
        "pizza"
    ],
    "wof:name":"Pizza Hut",
    "wof:placetype":"venue"
},
  "geometry": {"coordinates":[-80.05954699999999,34.964819],"type":"Point"}
}