{
  "type": "Feature",
  "properties": {
    "iso:country":"US",
    "sg:address":"827 S Kerr Ave",
    "sg:city":"Wilmington",
    "sg:classifiers":[
        {
            "category":"Personal",
            "subcategory":"Tanning Parlor",
            "type":"Services"
        }
    ],
    "sg:phone":"+1 910 392 5596",
    "sg:postcode":"28403",
    "sg:province":"NC",
    "sg:tags":[
        "salon"
    ],
    "wof:name":"KWIK Tan",
    "wof:placetype":"venue"
},
  "geometry": {"coordinates":[-77.886313,34.221046],"type":"Point"}
}