{
  "type": "Feature",
  "properties": {
    "iso:country":"US",
    "sg:address":"128 E Carteret St",
    "sg:city":"Edenton",
    "sg:classifiers":[
        {
            "category":"Building & Trades",
            "subcategory":"Electrical",
            "type":"Services"
        }
    ],
    "sg:phone":"+1 252 482 3540",
    "sg:postcode":"27932",
    "sg:province":"NC",
    "sg:tags":[
        "electrical",
        "contractor"
    ],
    "wof:name":"Satterfield Electrical Service",
    "wof:placetype":"venue"
},
  "geometry": {"coordinates":[-76.60625899999999,36.063638],"type":"Point"}
}