{
  "type": "Feature",
  "properties": {
    "iso:country":"US",
    "sg:address":"17700 Mesa Range Dr",
    "sg:city":"Cornelius",
    "sg:classifiers":[
        {
            "category":"Building & Trades",
            "subcategory":"Construction",
            "type":"Services"
        }
    ],
    "sg:phone":"+1 704 892 7223",
    "sg:postcode":"28031",
    "sg:province":"NC",
    "sg:tags":[
        "general",
        "contractor"
    ],
    "wof:name":"Rick Howell Enterprises",
    "wof:placetype":"venue"
},
  "geometry": {"coordinates":[-80.889043,35.45772],"type":"Point"}
}