{
  "type": "Feature",
  "properties": {
    "iso:country":"US",
    "sg:address":"8 Wendy Ct",
    "sg:city":"Greensboro",
    "sg:classifiers":[
        {
            "category":"Building & Trades",
            "subcategory":"Construction",
            "type":"Services"
        }
    ],
    "sg:phone":"+1 804 674 1540",
    "sg:postcode":"27409",
    "sg:province":"NC",
    "sg:tags":[
        "insulation",
        "contractor"
    ],
    "wof:name":"Old Dominion Insulation Inc",
    "wof:placetype":"venue"
},
  "geometry": {"coordinates":[-79.897651,36.075591],"type":"Point"}
}