{
  "type": "Feature",
  "properties": {
    "iso:country":"US",
    "sg:address":"304 Abbey St",
    "sg:city":"Cramerton",
    "sg:classifiers":[
        {
            "category":"Building & Trades",
            "subcategory":"Construction",
            "type":"Services"
        }
    ],
    "sg:phone":"+1 704 922 9070",
    "sg:postcode":"28032",
    "sg:province":"NC",
    "sg:tags":[
        "hanging",
        "contractor"
    ],
    "wof:name":"Perfection Painting",
    "wof:placetype":"venue"
},
  "geometry": {"coordinates":[-81.084942,35.253867],"type":"Point"}
}