{
  "type": "Feature",
  "properties": {
    "addr:full":"821 S Main St Kernersville NC 27284",
    "addr:housenumber":"821",
    "addr:postcode":"27284",
    "addr:street":"S Main St",
    "iso:country":"US",
    "sg:address":"821 S Main St",
    "sg:city":"Kernersville",
    "sg:classifiers":[
        {
            "category":"Shopping",
            "subcategory":"Computers & Home Electronics",
            "type":"Retail Goods"
        }
    ],
    "sg:phone":"+1 336 996 7804",
    "sg:postcode":"27284",
    "sg:province":"NC",
    "wof:name":"Radio Shack",
    "wof:placetype":"venue"
},
  "geometry": {"coordinates":[-80.087242,36.111718],"type":"Point"}
}