{
  "type": "Feature",
  "properties": {
    "iso:country":"US",
    "sg:address":"276 Kentwood Ln",
    "sg:city":"Lexington",
    "sg:classifiers":[
        {
            "category":"Building & Trades",
            "subcategory":"Electrical",
            "type":"Services"
        }
    ],
    "sg:phone":"+1 336 249 9311",
    "sg:postcode":"27295",
    "sg:province":"NC",
    "sg:tags":[
        "electric",
        "contractor"
    ],
    "wof:name":"Precision Technical",
    "wof:placetype":"venue"
},
  "geometry": {"coordinates":[-80.30505599999999,35.866941],"type":"Point"}
}