{
  "type": "Feature",
  "properties": {
    "iso:country":"US",
    "sg:address":"5301 Capital Blvd",
    "sg:city":"Raleigh",
    "sg:classifiers":[
        {
            "category":"Professional",
            "subcategory":"Testing Lab",
            "type":"Services"
        },
        {
            "category":"Professional",
            "subcategory":"Engineering",
            "type":"Services"
        }
    ],
    "sg:phone":"+1 919 872 8788",
    "sg:postcode":"27616",
    "sg:province":"NC",
    "sg:tags":[
        "consultant",
        "consulting",
        "forensic",
        "engineer"
    ],
    "wof:name":"Forensic Analysis Engrg Corp",
    "wof:placetype":"venue"
},
  "geometry": {"coordinates":[-78.581214,35.856319],"type":"Point"}
}