{
  "type": "Feature",
  "properties": {
    "iso:country":"US",
    "sg:address":"145 W Lexington Ave",
    "sg:city":"High Point",
    "sg:classifiers":[
        {
            "category":"Home & Garden",
            "subcategory":"Carpets & Floor Coverings",
            "type":"Retail Goods"
        }
    ],
    "sg:phone":"+1 336 889 3348",
    "sg:postcode":"27262",
    "sg:province":"NC",
    "sg:tags":[
        "material"
    ],
    "wof:name":"Parks Floor Covering Inc",
    "wof:placetype":"venue"
},
  "geometry": {"coordinates":[-80.018956,35.972975],"type":"Point"}
}