{
  "type": "Feature",
  "properties": {
    "addr:full":"12301 Silveroak Ln Charlotte NC 28277",
    "addr:housenumber":"12301",
    "addr:postcode":"28277",
    "addr:street":"Silveroak Ln",
    "iso:country":"US",
    "sg:address":"12301 Silveroak Ln",
    "sg:city":"Charlotte",
    "sg:classifiers":[
        {
            "category":"Manufacturing",
            "subcategory":"Metals",
            "type":"Manufacturing & Wholesale Goods"
        }
    ],
    "sg:phone":"+1 704 759 0804",
    "sg:postcode":"28277",
    "sg:province":"NC",
    "sg:tags":[
        "fabrication",
        "structural"
    ],
    "wof:name":"Division Five Steel Inc",
    "wof:placetype":"venue"
},
  "geometry": {"coordinates":[-80.865944,35.041086],"type":"Point"}
}