{
  "type": "Feature",
  "properties": {
    "iso:country":"US",
    "sg:address":"420 Finley Rd",
    "sg:city":"Marion",
    "sg:classifiers":[
        {
            "category":"Recreation",
            "type":"Entertainment"
        }
    ],
    "sg:phone":"+1 828 652 2626",
    "sg:postcode":"28752",
    "sg:province":"NC",
    "sg:tags":[
        "center"
    ],
    "wof:name":"Lightning Strike Sports Ctr",
    "wof:placetype":"venue"
},
  "geometry": {"coordinates":[-82.020202,35.683006],"type":"Point"}
}