{
  "type": "Feature",
  "properties": {
    "iso:country":"US",
    "sg:address":"2686 Johnsontown Rd",
    "sg:city":"Thomasville",
    "sg:classifiers":[
        {
            "category":"Food & Beverages",
            "subcategory":"Groceries & Convenience Stores",
            "type":"Retail Goods"
        }
    ],
    "sg:phone":"+1 336 472 9703",
    "sg:postcode":"27360",
    "sg:province":"NC",
    "wof:name":"Gordon's General Store",
    "wof:placetype":"venue"
},
  "geometry": {"coordinates":[-80.11789,35.838062],"type":"Point"}
}