{
  "type": "Feature",
  "properties": {
    "addr:full":"4601 Western Blvd Raleigh NC 27606",
    "addr:housenumber":"4601",
    "addr:postcode":"27606",
    "addr:street":"Western Blvd",
    "iso:country":"US",
    "sg:address":"4601 Western Blvd",
    "sg:city":"Raleigh",
    "sg:classifiers":[
        {
            "category":"Building & Trades",
            "subcategory":"Construction",
            "type":"Services"
        }
    ],
    "sg:phone":"+1 919 859 3570",
    "sg:postcode":"27606",
    "sg:province":"NC",
    "sg:tags":[
        "general",
        "contractor"
    ],
    "wof:name":"Dakova Construction Co",
    "wof:placetype":"venue"
},
  "geometry": {"coordinates":[-78.70279600000001,35.784719],"type":"Point"}
}