{
  "type": "Feature",
  "properties": {
    "iso:country":"US",
    "sg:address":"210 Rampart St",
    "sg:city":"Charlotte",
    "sg:classifiers":[
        {
            "category":"Shopping",
            "subcategory":"Computers & Home Electronics",
            "type":"Retail Goods"
        }
    ],
    "sg:phone":"+1 704 375 3700",
    "sg:postcode":"28203",
    "sg:province":"NC",
    "sg:tags":[
        "audio"
    ],
    "wof:name":"S E Systems",
    "wof:placetype":"venue"
},
  "geometry": {"coordinates":[-80.866725,35.20961],"type":"Point"}
}