{
  "type": "Feature",
  "properties": {
    "addr:full":"507 David St Elizabethtown NC 28337",
    "addr:housenumber":"507",
    "addr:postcode":"28337",
    "addr:street":"David St",
    "iso:country":"US",
    "sg:address":"507 David St",
    "sg:city":"Elizabethtown",
    "sg:classifiers":[
        {
            "category":"Retail",
            "subcategory":"Laundry & Dry Cleaning",
            "type":"Services"
        }
    ],
    "sg:phone":"+1 910 862 6644",
    "sg:postcode":"28337",
    "sg:province":"NC",
    "sg:tags":[
        "cleaners",
        "rug",
        "carpet"
    ],
    "wof:name":"Nye's Carpet Care",
    "wof:placetype":"venue"
},
  "geometry": {"coordinates":[-78.599006,34.621653],"type":"Point"}
}