{
  "type": "Feature",
  "properties": {
    "iso:country":"US",
    "sg:address":"717 W Virgil St",
    "sg:city":"Whiteville",
    "sg:classifiers":[
        {
            "category":"Professional",
            "type":"Services"
        }
    ],
    "sg:phone":"+1 910 640 1654",
    "sg:postcode":"28472",
    "sg:province":"NC",
    "wof:name":"Mary Gowans",
    "wof:placetype":"venue"
},
  "geometry": {"coordinates":[-78.713326,34.324576],"type":"Point"}
}