{
  "type": "Feature",
  "properties": {
    "iso:country":"US",
    "sg:address":"1220 Bridford Pkwy",
    "sg:city":"Greensboro",
    "sg:classifiers":[
        {
            "category":"Banks & Credit Unions",
            "subcategory":"Bank",
            "type":"Services"
        }
    ],
    "sg:phone":"+1 336 412 4085",
    "sg:postcode":"27407",
    "sg:province":"NC",
    "wof:name":"First-Citizens Bank & Trust Co",
    "wof:placetype":"venue"
},
  "geometry": {"coordinates":[-79.90325,36.058469],"type":"Point"}
}