{
  "type": "Feature",
  "properties": {
    "iso:country":"US",
    "sg:address":"918 West Ave NW",
    "sg:city":"Lenoir",
    "sg:classifiers":[
        {
            "category":"Manufacturing",
            "subcategory":"Rubber & Plastics",
            "type":"Manufacturing & Wholesale Goods"
        }
    ],
    "sg:phone":"+1 828 758 5511",
    "sg:postcode":"28645",
    "sg:province":"NC",
    "sg:tags":[
        "product"
    ],
    "wof:name":"Wayne Teague Enterprises",
    "wof:placetype":"venue"
},
  "geometry": {"coordinates":[-81.54069800000001,35.91454],"type":"Point"}
}