{
  "type": "Feature",
  "properties": {
    "addr:full":"9140 Arrowpoint Blvd Charlotte NC 28273",
    "addr:postcode":"9140;28273",
    "addr:street":"Arrowpoint Blvd",
    "iso:country":"US",
    "sg:address":"9140 Arrowpoint Blvd",
    "sg:city":"Charlotte",
    "sg:classifiers":[
        {
            "category":"Education",
            "subcategory":"Vocational School",
            "type":"Public Place"
        }
    ],
    "sg:phone":"+1 704 522 9747",
    "sg:postcode":"28273",
    "sg:province":"NC",
    "sg:tags":[
        "training",
        "computer"
    ],
    "wof:name":"New Horizons Computer Learning",
    "wof:placetype":"venue"
},
  "geometry": {"coordinates":[-80.913769,35.139521],"type":"Point"}
}