{
  "type": "Feature",
  "properties": {
    "iso:country":"US",
    "sg:address":"224 Micro Tower Rd",
    "sg:city":"Lillington",
    "sg:classifiers":[
        {
            "category":"Home & Garden",
            "subcategory":"Garden Supply",
            "type":"Retail Goods"
        }
    ],
    "sg:phone":"+1 910 893 8306",
    "sg:postcode":"27546",
    "sg:province":"NC",
    "wof:name":"Bethea Lawn/Garden",
    "wof:placetype":"venue"
},
  "geometry": {"coordinates":[-78.99686800000001,35.319226],"type":"Point"}
}