{
  "type": "Feature",
  "properties": {
    "addr:full":"7000 Harps Mill Rd Raleigh NC 27615",
    "addr:housenumber":"7000",
    "addr:postcode":"27615",
    "addr:street":"Harps Mill Rd",
    "iso:country":"US",
    "sg:address":"7000 Harps Mill Rd",
    "sg:city":"Raleigh",
    "sg:classifiers":[
        {
            "category":"Real Estate",
            "subcategory":"Real Estate Agent",
            "type":"Services"
        }
    ],
    "sg:phone":"+1 919 846 0222",
    "sg:postcode":"27615",
    "sg:province":"NC",
    "sg:tags":[
        "appraiser"
    ],
    "sg:website":"www.stokesappraisal.com",
    "wof:name":"Stokes Appraisal Svc",
    "wof:placetype":"venue"
},
  "geometry": {"coordinates":[-78.62582399999999,35.881201],"type":"Point"}
}