{
  "type": "Feature",
  "properties": {
    "addr:full":"3325 Carlton Dr Lenoir NC 28645",
    "addr:housenumber":"3325",
    "addr:postcode":"28645",
    "addr:street":"Carlton Dr",
    "iso:country":"US",
    "sg:address":"3325 Carlton Dr",
    "sg:city":"Lenoir",
    "sg:classifiers":[
        {
            "category":"Manufacturing",
            "subcategory":"Tools & Machinery",
            "type":"Manufacturing & Wholesale Goods"
        }
    ],
    "sg:phone":"+1 828 728 3037",
    "sg:postcode":"28645",
    "sg:province":"NC",
    "sg:tags":[
        "machine",
        "shop"
    ],
    "wof:name":"Precision Machine Shop",
    "wof:placetype":"venue"
},
  "geometry": {"coordinates":[-81.614806,35.878775],"type":"Point"}
}