{
  "type": "Feature",
  "properties": {
    "addr:full":"4846 Lindstrom Dr Charlotte NC 28226",
    "addr:housenumber":"4846",
    "addr:postcode":"28226",
    "addr:street":"Lindstrom Dr",
    "iso:country":"US",
    "sg:address":"4846 Lindstrom Dr",
    "sg:city":"Charlotte",
    "sg:classifiers":[
        {
            "category":"Wholesale",
            "subcategory":"Groceries",
            "type":"Manufacturing & Wholesale Goods"
        }
    ],
    "sg:phone":"+1 704 341 3764",
    "sg:postcode":"28226",
    "sg:province":"NC",
    "sg:tags":[
        "product",
        "related"
    ],
    "wof:name":"Norssi International Inc",
    "wof:placetype":"venue"
},
  "geometry": {"coordinates":[-80.840232,35.108214],"type":"Point"}
}