{
  "type": "Feature",
  "properties": {
    "addr:full":"136 Hazelwood Dr Mocksville NC 27028",
    "addr:housenumber":"136",
    "addr:postcode":"27028",
    "addr:street":"Hazelwood Dr",
    "iso:country":"US",
    "sg:address":"136 Hazelwood Dr",
    "sg:city":"Mocksville",
    "sg:classifiers":[
        {
            "category":"Real Estate",
            "subcategory":"Real Estate Agent",
            "type":"Services"
        }
    ],
    "sg:phone":"+1 336 998 0918",
    "sg:postcode":"27028",
    "sg:province":"NC",
    "wof:name":"Burch & Yates LLC",
    "wof:placetype":"venue"
},
  "geometry": {"coordinates":[-80.47996500000001,35.888076],"type":"Point"}
}