{
  "type": "Feature",
  "properties": {
    "iso:country":"US",
    "sg:address":"17 Waverly Rd",
    "sg:city":"Asheville",
    "sg:classifiers":[
        {
            "category":"Building & Trades",
            "subcategory":"Electrical",
            "type":"Services"
        }
    ],
    "sg:phone":"+1 828 254 9146",
    "sg:postcode":"28803",
    "sg:province":"NC",
    "sg:tags":[
        "electrical",
        "contractor"
    ],
    "wof:name":"J R Hayes Electric",
    "wof:placetype":"venue"
},
  "geometry": {"coordinates":[-82.534549,35.578525],"type":"Point"}
}