{
  "type": "Feature",
  "properties": {
    "iso:country":"US",
    "sg:address":"1408 Biltmore Dr",
    "sg:city":"Charlotte",
    "sg:classifiers":[
        {
            "category":"Banks & Credit Unions",
            "subcategory":"Financial Services",
            "type":"Services"
        }
    ],
    "sg:phone":"+1 704 375 3888",
    "sg:postcode":"28207",
    "sg:province":"NC",
    "sg:tags":[
        "investor"
    ],
    "wof:name":"Carolinas Capital Inv Corp",
    "wof:placetype":"venue"
},
  "geometry": {"coordinates":[-80.81966300000001,35.185029],"type":"Point"}
}