{
  "type": "Feature",
  "properties": {
    "iso:country":"US",
    "sg:address":"102 N 4th St",
    "sg:city":"Wilmington",
    "sg:classifiers":[
        {
            "category":"Real Estate",
            "subcategory":"Real Estate Agent",
            "type":"Services"
        }
    ],
    "sg:phone":"+1 910 251 0311",
    "sg:postcode":"28401",
    "sg:province":"NC",
    "sg:tags":[
        "inspection"
    ],
    "wof:name":"Your Home Inspection Co",
    "wof:placetype":"venue"
},
  "geometry": {"coordinates":[-77.94488200000001,34.237849],"type":"Point"}
}