{
  "type": "Feature",
  "properties": {
    "addr:full":"108 Green St Elon College NC 27244",
    "addr:housenumber":"108",
    "addr:postcode":"27244",
    "addr:street":"Green St",
    "iso:country":"US",
    "sg:address":"108 Green St",
    "sg:city":"Elon College",
    "sg:classifiers":[
        {
            "category":"Wholesale",
            "subcategory":"Durable Goods & Equipment",
            "type":"Manufacturing & Wholesale Goods"
        }
    ],
    "sg:phone":"+1 336 584 0879",
    "sg:postcode":"27244",
    "sg:province":"NC",
    "sg:tags":[
        "laboratory",
        "supply"
    ],
    "wof:name":"Fisher Scientific",
    "wof:placetype":"venue"
},
  "geometry": {"coordinates":[-79.51192899999999,36.090768],"type":"Point"}
}