{
  "type": "Feature",
  "properties": {
    "addr:full":"4101 Beechwood Dr Greensboro NC 27410",
    "addr:housenumber":"4101",
    "addr:postcode":"27410",
    "addr:street":"Beechwood Dr",
    "iso:country":"US",
    "sg:address":"4101 Beechwood Dr",
    "sg:city":"Greensboro",
    "sg:classifiers":[
        {
            "category":"Wholesale",
            "subcategory":"Machinery & Supplies",
            "type":"Manufacturing & Wholesale Goods"
        }
    ],
    "sg:phone":"+1 336 294 3838",
    "sg:postcode":"27410",
    "sg:province":"NC",
    "sg:tags":[
        "pump"
    ],
    "sg:website":"www.heattransfersales.com",
    "wof:name":"Heat Transfer Sales Inc",
    "wof:placetype":"venue"
},
  "geometry": {"coordinates":[-79.945932,36.053829],"type":"Point"}
}