{
  "type": "Feature",
  "properties": {
    "addr:full":"2444 Owen Dr Fayetteville NC 28306",
    "addr:housenumber":"2444",
    "addr:postcode":"28306",
    "addr:street":"Owen Dr",
    "iso:country":"US",
    "sg:address":"2444 Owen Dr",
    "sg:city":"Fayetteville",
    "sg:classifiers":[
        {
            "category":"Social Services",
            "subcategory":"Child Care",
            "type":"Services"
        }
    ],
    "sg:phone":"+1 910 486 7000",
    "sg:postcode":"28306",
    "sg:province":"NC",
    "sg:tags":[
        "daycare"
    ],
    "wof:name":"Time For Tots Academy Inc",
    "wof:placetype":"venue"
},
  "geometry": {"coordinates":[-78.91254000000001,35.017857],"type":"Point"}
}