{
  "type": "Feature",
  "properties": {
    "iso:country":"US",
    "sg:address":"3500 Terrault Dr",
    "sg:city":"Greensboro",
    "sg:classifiers":[
        {
            "category":"Health Services",
            "subcategory":"Optometrist",
            "type":"Services"
        }
    ],
    "sg:phone":"+1 336 294 8004",
    "sg:postcode":"27410",
    "sg:province":"NC",
    "sg:tags":[
        "good",
        "optical"
    ],
    "wof:name":"Neese, Charles Matthews",
    "wof:placetype":"venue"
},
  "geometry": {"coordinates":[-79.877762,36.125278],"type":"Point"}
}