{
  "type": "Feature",
  "properties": {
    "iso:country":"US",
    "sg:address":"211 Forest Creek Dr",
    "sg:city":"Fayetteville",
    "sg:classifiers":[
        {
            "category":"Health Services",
            "subcategory":"Nursing And Care Facility",
            "type":"Services"
        }
    ],
    "sg:phone":"+1 910 864 0245",
    "sg:postcode":"28303",
    "sg:province":"NC",
    "sg:tags":[
        "hospice"
    ],
    "wof:name":"Advantage Hospice & Home Care",
    "wof:placetype":"venue"
},
  "geometry": {"coordinates":[-78.94661499999999,35.062899],"type":"Point"}
}