{
  "type": "Feature",
  "properties": {
    "iso:country":"US",
    "sg:address":"1778 Metromedical Dr",
    "sg:city":"Fayetteville",
    "sg:classifiers":[
        {
            "category":"Professional",
            "type":"Services"
        }
    ],
    "sg:phone":"+1 910 323 1785",
    "sg:postcode":"28304",
    "sg:province":"NC",
    "sg:tags":[
        "establishment"
    ],
    "wof:name":"QDI",
    "wof:placetype":"venue"
},
  "geometry": {"coordinates":[-78.92855,35.031669],"type":"Point"}
}