{
  "type": "Feature",
  "properties": {
    "iso:country":"US",
    "sg:address":"12040 Goodrich Dr",
    "sg:city":"Charlotte",
    "sg:classifiers":[
        {
            "category":"Wholesale",
            "subcategory":"Scrap",
            "type":"Manufacturing & Wholesale Goods"
        }
    ],
    "sg:phone":"+1 704 588 3771",
    "sg:postcode":"28273",
    "sg:province":"NC",
    "sg:tags":[
        "recycling",
        "center"
    ],
    "wof:name":"Oil Filters Recyclers",
    "wof:placetype":"venue"
},
  "geometry": {"coordinates":[-80.96430599999999,35.125862],"type":"Point"}
}