{
  "type": "Feature",
  "properties": {
    "addr:full":"998 Hoyd Ln Kernersville NC 27284",
    "addr:housenumber":"998",
    "addr:postcode":"27284",
    "addr:street":"Hoyd Ln",
    "iso:country":"US",
    "sg:address":"998 Hoyd Ln",
    "sg:city":"Kernersville",
    "sg:classifiers":[
        {
            "category":"Retail",
            "subcategory":"Auto Repair",
            "type":"Services"
        }
    ],
    "sg:phone":"+1 336 993 4903",
    "sg:postcode":"27284",
    "sg:province":"NC",
    "sg:tags":[
        "repairing",
        "automobile"
    ],
    "wof:name":"Corvette Specialist",
    "wof:placetype":"venue"
},
  "geometry": {"coordinates":[-80.108969,36.136815],"type":"Point"}
}