{
  "type": "Feature",
  "properties": {
    "iso:country":"US",
    "sg:address":"116 Southside Dr",
    "sg:city":"Charlotte",
    "sg:classifiers":[
        {
            "category":"Home & Garden",
            "subcategory":"Carpets & Floor Coverings",
            "type":"Retail Goods"
        }
    ],
    "sg:phone":"+1 704 523 6301",
    "sg:postcode":"28217",
    "sg:province":"NC",
    "sg:tags":[
        "material"
    ],
    "wof:name":"Invironmentalists",
    "wof:placetype":"venue"
},
  "geometry": {"coordinates":[-80.881244,35.18679],"type":"Point"}
}