{
  "type": "Feature",
  "properties": {
    "iso:country":"US",
    "sg:address":"2100 Sunnyside Ave",
    "sg:city":"Winston Salem",
    "sg:classifiers":[
        {
            "category":"Banks & Credit Unions",
            "subcategory":"Bank",
            "type":"Services"
        }
    ],
    "sg:phone":"+1 336 723 3075",
    "sg:postcode":"27127",
    "sg:province":"NC",
    "sg:tags":[
        "broker",
        "mortgage"
    ],
    "wof:name":"Evelyn Dean",
    "wof:placetype":"venue"
},
  "geometry": {"coordinates":[-80.237447,36.072209],"type":"Point"}
}