{
  "type": "Feature",
  "properties": {
    "addr:full":"619 Oberlin Rd Raleigh NC 27605",
    "addr:housenumber":"619",
    "addr:postcode":"27605",
    "addr:street":"Oberlin Rd",
    "iso:country":"US",
    "sg:address":"619 Oberlin Rd",
    "sg:city":"Raleigh",
    "sg:classifiers":[
        {
            "category":"Professional",
            "subcategory":"Engineering",
            "type":"Services"
        }
    ],
    "sg:phone":"+1 919 828 2880",
    "sg:postcode":"27605",
    "sg:province":"NC",
    "sg:tags":[
        "firm",
        "structural",
        "engineer"
    ],
    "wof:name":"Morrison Engineers Pllc",
    "wof:placetype":"venue"
},
  "geometry": {"coordinates":[-78.662824,35.791737],"type":"Point"}
}