{
  "type": "Feature",
  "properties": {
    "iso:country":"US",
    "sg:address":"101 Byrd Rd",
    "sg:city":"Fairmont",
    "sg:classifiers":[
        {
            "category":"Professional",
            "subcategory":"Accounting & Tax Preparation",
            "type":"Services"
        }
    ],
    "sg:phone":"+1 910 628 9630",
    "sg:postcode":"28340",
    "sg:province":"NC",
    "sg:tags":[
        "accountant"
    ],
    "wof:name":"Collins & Kemp Pllc",
    "wof:placetype":"venue"
},
  "geometry": {"coordinates":[-79.04077100000001,34.458415],"type":"Point"}
}