{
  "type": "Feature",
  "properties": {
    "iso:country":"US",
    "sg:address":"306 Millstone Rd",
    "sg:city":"Ellerbe",
    "sg:classifiers":[
        {
            "category":"Social Services",
            "subcategory":"Adult Care",
            "type":"Services"
        }
    ],
    "sg:phone":"+1 910 652 6006",
    "sg:postcode":"28338",
    "sg:province":"NC",
    "sg:tags":[
        "organization",
        "senior",
        "citizen"
    ],
    "wof:name":"Ellerbe Senior Ctr",
    "wof:placetype":"venue"
},
  "geometry": {"coordinates":[-79.75437599999999,35.070717],"type":"Point"}
}