{
  "type": "Feature",
  "properties": {
    "iso:country":"US",
    "sg:address":"1203 W Woodcroft Pkwy",
    "sg:city":"Durham",
    "sg:classifiers":[
        {
            "category":"Recreation",
            "type":"Entertainment"
        }
    ],
    "sg:phone":"+1 919 489 7705",
    "sg:postcode":"27713",
    "sg:province":"NC",
    "sg:tags":[
        "club",
        "membership",
        "tennis",
        "instruction",
        "s"
    ],
    "wof:name":"Woodcroft Swim and Tennis Club",
    "wof:placetype":"venue"
},
  "geometry": {"coordinates":[-78.955382,35.922527],"type":"Point"}
}