{
  "type": "Feature",
  "properties": {
    "iso:country":"US",
    "sg:address":"4304 Big Tree Way",
    "sg:city":"Greensboro",
    "sg:classifiers":[
        {
            "category":"Travel",
            "subcategory":"Hotels & Motels",
            "type":"Entertainment"
        }
    ],
    "sg:phone":"+1 336 547 7007",
    "sg:postcode":"27409",
    "sg:province":"NC",
    "sg:website":"www.microtel-inns.com",
    "wof:name":"Microtel Inn & Suites",
    "wof:placetype":"venue"
},
  "geometry": {"coordinates":[-79.892183,36.059226],"type":"Point"}
}