{
  "type": "Feature",
  "properties": {
    "iso:country":"US",
    "sg:address":"1125 E Geer St",
    "sg:city":"Durham",
    "sg:classifiers":[
        {
            "category":"Retail",
            "subcategory":"Funeral Services",
            "type":"Services"
        }
    ],
    "sg:phone":"+1 919 683 1497",
    "sg:postcode":"27704",
    "sg:province":"NC",
    "sg:tags":[
        "crematory"
    ],
    "wof:name":"Durham Creamation Svc",
    "wof:placetype":"venue"
},
  "geometry": {"coordinates":[-78.87350499999999,36.005705],"type":"Point"}
}