{
  "type": "Feature",
  "properties": {
    "iso:country":"US",
    "sg:address":"2601 E 7th St",
    "sg:city":"Charlotte",
    "sg:classifiers":[
        {
            "category":"Real Estate",
            "subcategory":"Real Estate Agent",
            "type":"Services"
        }
    ],
    "sg:phone":"+1 704 545 8397",
    "sg:postcode":"28204",
    "sg:province":"NC",
    "wof:name":"Passaly Real Estate Co Inc",
    "wof:placetype":"venue"
},
  "geometry": {"coordinates":[-80.81116900000001,35.206789],"type":"Point"}
}