{
  "type": "Feature",
  "properties": {
    "addr:full":"1529 S Miami Blvd Durham NC 27703",
    "addr:housenumber":"1529",
    "addr:postcode":"27703",
    "addr:street":"S Miami Blvd",
    "iso:country":"US",
    "sg:address":"1529 S Miami Blvd",
    "sg:city":"Durham",
    "sg:classifiers":[
        {
            "category":"Autos & Motor Vehicles",
            "subcategory":"Fuel & Gas Station",
            "type":"Retail Goods"
        }
    ],
    "sg:phone":"+1 919 596 1098",
    "sg:postcode":"27703",
    "sg:province":"NC",
    "sg:tags":[
        "grocery",
        "station",
        "gasoline"
    ],
    "wof:name":"B P Exploration & Oil Inc",
    "wof:placetype":"venue"
},
  "geometry": {"coordinates":[-78.83872100000001,35.951676],"type":"Point"}
}