{
  "type": "Feature",
  "properties": {
    "iso:country":"US",
    "sg:address":"736 Stony Point Rd",
    "sg:city":"Kings Mountain",
    "sg:classifiers":[
        {
            "category":"Food & Beverages",
            "subcategory":"Groceries & Convenience Stores",
            "type":"Retail Goods"
        }
    ],
    "sg:phone":"+1 704 739 2958",
    "sg:postcode":"28086",
    "sg:province":"NC",
    "sg:tags":[
        "carwash",
        "independent",
        "laundromat",
        "t"
    ],
    "wof:name":"Toms Coin Laundry",
    "wof:placetype":"venue"
},
  "geometry": {"coordinates":[-81.424566,35.272995],"type":"Point"}
}