{
  "type": "Feature",
  "properties": {
    "addr:full":"3112 Martin Luther King Dr Elizabethtown NC 28337",
    "addr:housenumber":"3112",
    "addr:postcode":"28337",
    "addr:street":"Martin Luther King Dr",
    "iso:country":"US",
    "sg:address":"3112 Martin Luther King Dr",
    "sg:city":"Elizabethtown",
    "sg:classifiers":[
        {
            "category":"Utilities",
            "subcategory":"Telephone",
            "type":"Services"
        }
    ],
    "sg:phone":"+1 910 645 1111",
    "sg:postcode":"28337",
    "sg:province":"NC",
    "sg:tags":[
        "company"
    ],
    "wof:name":"Star Telephone Membership Corp",
    "wof:placetype":"venue"
},
  "geometry": {"coordinates":[-78.63293,34.602789],"type":"Point"}
}