{
  "type": "Feature",
  "properties": {
    "addr:full":"101 Wyrick St Chapel Hill NC 27516",
    "addr:housenumber":"101",
    "addr:postcode":"27516",
    "addr:street":"Wyrick St",
    "iso:country":"US",
    "sg:address":"101 Wyrick St",
    "sg:city":"Chapel Hill",
    "sg:classifiers":[
        {
            "category":"Professional",
            "subcategory":"Business Services",
            "type":"Services"
        }
    ],
    "sg:phone":"+1   ",
    "sg:postcode":"27516",
    "sg:province":"NC",
    "sg:tags":[
        "training",
        "leadership"
    ],
    "wof:name":"PM Rosenthal Consulting",
    "wof:placetype":"venue"
},
  "geometry": {"coordinates":[-79.060374,35.928933],"type":"Point"}
}