{
  "type": "Feature",
  "properties": {
    "addr:full":"6405 Rock Service Station Rd Raleigh NC 27603",
    "addr:housenumber":"6405",
    "addr:postcode":"27603",
    "addr:street":"Rock;Station Rd",
    "iso:country":"US",
    "sg:address":"6405 Rock Service Station Rd",
    "sg:city":"Raleigh",
    "sg:classifiers":[
        {
            "category":"Building & Trades",
            "subcategory":"Plumbing",
            "type":"Services"
        }
    ],
    "sg:phone":"+1 919 772 1467",
    "sg:postcode":"27603",
    "sg:province":"NC",
    "sg:tags":[
        "plumber",
        "industrial",
        "contractors-commercial"
    ],
    "wof:name":"H&H Plumbing Service",
    "wof:placetype":"venue"
},
  "geometry": {"coordinates":[-78.657031,35.603286],"type":"Point"}
}