{
  "type": "Feature",
  "properties": {
    "addr:full":"23 Market St Wilmington NC 28401",
    "addr:housenumber":"23",
    "addr:postcode":"28401",
    "addr:street":"Market St",
    "iso:country":"US",
    "sg:address":"23 Market St",
    "sg:city":"Wilmington",
    "sg:classifiers":[
        {
            "category":"Bars & Pubs",
            "type":"Food & Drink"
        }
    ],
    "sg:phone":"+1 910 362 0809",
    "sg:postcode":"28401",
    "sg:province":"NC",
    "sg:tags":[
        "drinking"
    ],
    "wof:name":"Liquid Room",
    "wof:placetype":"venue"
},
  "geometry": {"coordinates":[-77.948915,34.23533],"type":"Point"}
}