{
  "type": "Feature",
  "properties": {
    "iso:country":"US",
    "sg:address":"41912 Carter Acres Rd",
    "sg:city":"Albemarle",
    "sg:classifiers":[
        {
            "category":"Building & Trades",
            "subcategory":"Cleaning & Sanitation",
            "type":"Services"
        }
    ],
    "sg:phone":"+1 704 982 2898",
    "sg:postcode":"28001",
    "sg:province":"NC",
    "sg:tags":[
        "maintenance"
    ],
    "wof:name":"D & J Carpet & Flooring",
    "wof:placetype":"venue"
},
  "geometry": {"coordinates":[-80.146164,35.399715],"type":"Point"}
}