{
  "type": "Feature",
  "properties": {
    "iso:country":"US",
    "sg:address":"608 Indian Trail Rd",
    "sg:city":"Indian Trail",
    "sg:classifiers":[
        {
            "category":"Real Estate",
            "subcategory":"Real Estate Agent",
            "type":"Services"
        }
    ],
    "sg:phone":"+1 704 821 0723",
    "sg:postcode":"28079",
    "sg:province":"NC",
    "wof:name":"Help U Sell Rocky River",
    "wof:placetype":"venue"
},
  "geometry": {"coordinates":[-80.676045,35.070531],"type":"Point"}
}