{
  "type": "Feature",
  "properties": {
    "iso:country":"US",
    "sg:address":"6779 Beach Dr SW",
    "sg:city":"Ocean Isle Beach",
    "sg:classifiers":[
        {
            "category":"Wholesale",
            "subcategory":"Machinery & Supplies",
            "type":"Manufacturing & Wholesale Goods"
        }
    ],
    "sg:phone":"+1 910 612 4950",
    "sg:postcode":"28469",
    "sg:province":"NC",
    "sg:tags":[
        "equipment",
        "hydraulic"
    ],
    "wof:name":"Shallotte Battery & Hydraulics",
    "wof:placetype":"venue"
},
  "geometry": {"coordinates":[-78.458472,33.900225],"type":"Point"}
}