{
  "type": "Feature",
  "properties": {
    "iso:country":"US",
    "sg:address":"3402 S Main St",
    "sg:city":"Salisbury",
    "sg:classifiers":[
        {
            "category":"Building & Trades",
            "subcategory":"Construction",
            "type":"Services"
        }
    ],
    "sg:phone":"+1 704 636 7051",
    "sg:postcode":"28147",
    "sg:province":"NC",
    "wof:name":"Carolina Building Systems Inc",
    "wof:placetype":"venue"
},
  "geometry": {"coordinates":[-80.514736,35.636377],"type":"Point"}
}