{
  "type": "Feature",
  "properties": {
    "iso:country":"US",
    "sg:address":"2673 Matthews Mill Pond Rd",
    "sg:city":"Angier",
    "sg:classifiers":[
        {
            "category":"Farming",
            "subcategory":"Livestock Farm",
            "type":"Manufacturing & Wholesale Goods"
        }
    ],
    "sg:phone":"+1 919 639 2316",
    "sg:postcode":"27501",
    "sg:province":"NC",
    "sg:tags":[
        "beef",
        "feedlot",
        "cattle"
    ],
    "wof:name":"Newton Farms",
    "wof:placetype":"venue"
},
  "geometry": {"coordinates":[-78.75934700000001,35.460163],"type":"Point"}
}