{
  "type": "Feature",
  "properties": {
    "addr:full":"1446 Turnpike Rd Swanquarter NC 27885",
    "addr:housenumber":"1446",
    "addr:postcode":"27885",
    "addr:street":"Turnpike Rd",
    "iso:country":"US",
    "sg:address":"1446 Turnpike Rd",
    "sg:city":"Swanquarter",
    "sg:classifiers":[
        {
            "category":"Farming",
            "subcategory":"Farm",
            "type":"Manufacturing & Wholesale Goods"
        }
    ],
    "sg:phone":"+1 252 926 3531",
    "sg:postcode":"27885",
    "sg:province":"NC",
    "sg:tags":[
        "car",
        "crop",
        "general"
    ],
    "wof:name":"Timothy Henry Hodges",
    "wof:placetype":"venue"
},
  "geometry": {"coordinates":[-76.27947,35.442723],"type":"Point"}
}