{
  "type": "Feature",
  "properties": {
    "iso:country":"US",
    "sg:address":"3641 Central Ave",
    "sg:city":"Charlotte",
    "sg:classifiers":[
        {
            "category":"Social Services",
            "subcategory":"Child Care",
            "type":"Services"
        },
        {
            "category":"Education",
            "subcategory":"School",
            "type":"Public Place"
        }
    ],
    "sg:phone":"+1 704 566 0915",
    "sg:postcode":"28205",
    "sg:province":"NC",
    "wof:name":"Noah's Academy",
    "wof:placetype":"venue"
},
  "geometry": {"coordinates":[-80.78197299999999,35.215787],"type":"Point"}
}