{
  "type": "Feature",
  "properties": {
    "addr:full":"2806 McNeill Hobbs Rd Bunnlevel NC 28323",
    "addr:housenumber":"2806",
    "addr:postcode":"28323",
    "addr:street":"Mcneill Hobbs Rd",
    "iso:country":"US",
    "sg:address":"2806 McNeill Hobbs Rd",
    "sg:city":"Bunnlevel",
    "sg:classifiers":[
        {
            "category":"Professional",
            "subcategory":"Accounting & Tax Preparation",
            "type":"Services"
        }
    ],
    "sg:phone":"+1 910 893 4694",
    "sg:postcode":"28323",
    "sg:province":"NC",
    "sg:tags":[
        "return",
        "filing"
    ],
    "wof:name":"G Emery Hobbs Accountant",
    "wof:placetype":"venue"
},
  "geometry": {"coordinates":[-78.81088099999999,35.330558],"type":"Point"}
}