{
  "type": "Feature",
  "properties": {
    "addr:full":"1239 Buck Jones Rd Raleigh NC 27606",
    "addr:housenumber":"1239",
    "addr:postcode":"27606",
    "addr:street":"Buck Jones Rd",
    "iso:country":"US",
    "sg:address":"1239 Buck Jones Rd",
    "sg:city":"Raleigh",
    "sg:classifiers":[
        {
            "category":"Professional",
            "subcategory":"Business Services",
            "type":"Services"
        }
    ],
    "sg:phone":"+1 919 388 7246",
    "sg:postcode":"27606",
    "sg:province":"NC",
    "sg:tags":[
        "consultant",
        "coach"
    ],
    "wof:name":"Tom's Train Station",
    "wof:placetype":"venue"
},
  "geometry": {"coordinates":[-78.74118199999999,35.767028],"type":"Point"}
}