{
  "type": "Feature",
  "properties": {
    "addr:full":"146 Greenville Blvd SW Greenville NC 27834",
    "addr:housenumber":"146",
    "addr:postcode":"27834",
    "addr:street":"Greenville Blvd Sw",
    "iso:country":"US",
    "sg:address":"146 Greenville Blvd SW",
    "sg:city":"Greenville",
    "sg:classifiers":[
        {
            "category":"Shopping",
            "subcategory":"Department Store",
            "type":"Retail Goods"
        },
        {
            "category":"Shopping",
            "subcategory":"Clothing, Apparel, & Fashions",
            "type":"Retail Goods"
        }
    ],
    "sg:phone":"+1 252 321 0352",
    "sg:postcode":"27834",
    "sg:province":"NC",
    "sg:tags":[
        "family"
    ],
    "wof:name":"Goodys Family Clothing 147",
    "wof:placetype":"venue"
},
  "geometry": {"coordinates":[-77.385599,35.574918],"type":"Point"}
}