{
  "type": "Feature",
  "properties": {
    "addr:full":"9431 Holly Bend Ln Huntersville NC 28078",
    "addr:housenumber":"9431",
    "addr:postcode":"28078",
    "addr:street":"Holly Bend Ln",
    "iso:country":"US",
    "sg:address":"9431 Holly Bend Ln",
    "sg:city":"Huntersville",
    "sg:classifiers":[
        {
            "category":"Organizations",
            "subcategory":"Religious Organization",
            "type":"Services"
        }
    ],
    "sg:phone":"+1   ",
    "sg:postcode":"28078",
    "sg:province":"NC",
    "wof:name":"King of Kings Family Church",
    "wof:placetype":"venue"
},
  "geometry": {"coordinates":[-80.875362,35.39624],"type":"Point"}
}