{
  "type": "Feature",
  "properties": {
    "iso:country":"US",
    "sg:address":"40 Homes Development Ln",
    "sg:city":"Taylorsville",
    "sg:classifiers":[
        {
            "category":"Retail",
            "subcategory":"Animal Services",
            "type":"Services"
        }
    ],
    "sg:phone":"+1 828 495 8691",
    "sg:postcode":"28681",
    "sg:province":"NC",
    "sg:tags":[
        "pet",
        "grooming",
        "washing"
    ],
    "wof:name":"Blue Ribbon Grooming",
    "wof:placetype":"venue"
},
  "geometry": {"coordinates":[-81.30119999999999,35.856486],"type":"Point"}
}