{
  "type": "Feature",
  "properties": {
    "addr:full":"3645 Prairie Trl Denver NC 28037",
    "addr:housenumber":"3645",
    "addr:postcode":"28037",
    "addr:street":"Prairie Trl",
    "iso:country":"US",
    "sg:address":"3645 Prairie Trl",
    "sg:city":"Denver",
    "sg:classifiers":[
        {
            "category":"Building & Trades",
            "subcategory":"Landscaping Services",
            "type":"Services"
        }
    ],
    "sg:phone":"+1 704 489 0900",
    "sg:postcode":"28037",
    "sg:province":"NC",
    "sg:tags":[
        "lawn",
        "maintenance",
        "grounds"
    ],
    "wof:name":"Lawn and Garden Care",
    "wof:placetype":"venue"
},
  "geometry": {"coordinates":[-81.012455,35.523917],"type":"Point"}
}