{
  "type": "Feature",
  "properties": {
    "addr:full":"619 S Cedar St Charlotte NC 28202",
    "addr:housenumber":"619",
    "addr:postcode":"28202",
    "addr:street":"S Cedar St",
    "iso:country":"US",
    "sg:address":"619 S Cedar St",
    "sg:city":"Charlotte",
    "sg:classifiers":[
        {
            "category":"Wholesale",
            "subcategory":"Furniture",
            "type":"Manufacturing & Wholesale Goods"
        }
    ],
    "sg:phone":"+1 704 376 6497",
    "sg:postcode":"28202",
    "sg:province":"NC",
    "wof:name":"Darnell & Co",
    "wof:placetype":"venue"
},
  "geometry": {"coordinates":[-80.855473,35.227908],"type":"Point"}
}