{
  "type": "Feature",
  "properties": {
    "addr:full":"850 Merrimon Ave Asheville NC 28804",
    "addr:housenumber":"850",
    "addr:postcode":"28804",
    "addr:street":"Merrimon Ave",
    "iso:country":"US",
    "sg:address":"850 Merrimon Ave",
    "sg:city":"Asheville",
    "sg:classifiers":[
        {
            "category":"Banks & Credit Unions",
            "subcategory":"Bank",
            "type":"Services"
        }
    ],
    "sg:phone":"+1 828 225 2160",
    "sg:postcode":"28804",
    "sg:province":"NC",
    "wof:name":"B B & T",
    "wof:placetype":"venue"
},
  "geometry": {"coordinates":[-82.55295700000001,35.627595],"type":"Point"}
}