{
  "type": "Feature",
  "properties": {
    "addr:full":"3958 Bittle Rd Gibsonville NC 27249",
    "addr:housenumber":"3958",
    "addr:postcode":"27249",
    "addr:street":"Bittle Rd",
    "iso:country":"US",
    "sg:address":"3958 Bittle Rd",
    "sg:city":"Gibsonville",
    "sg:classifiers":[
        {
            "category":"Personal",
            "subcategory":"Beauty Salon",
            "type":"Services"
        }
    ],
    "sg:phone":"+1   ",
    "sg:postcode":"27249",
    "sg:province":"NC",
    "sg:tags":[
        "shop"
    ],
    "wof:name":"Beauty Nook",
    "wof:placetype":"venue"
},
  "geometry": {"coordinates":[-79.624595,36.145553],"type":"Point"}
}