{
  "type": "Feature",
  "properties": {
    "iso:country":"US",
    "sg:address":"138 Scotch Irish Ln",
    "sg:city":"Troutman",
    "sg:classifiers":[
        {
            "category":"Professional",
            "subcategory":"Business Services",
            "type":"Services"
        }
    ],
    "sg:phone":"+1   ",
    "sg:postcode":"28166",
    "sg:province":"NC",
    "wof:name":"Alaimo Enterprises Inc",
    "wof:placetype":"venue"
},
  "geometry": {"coordinates":[-80.903075,35.683811],"type":"Point"}
}