{
  "type": "Feature",
  "properties": {
    "iso:country":"US",
    "sg:address":"9252 Aylesbury Ln",
    "sg:city":"Charlotte",
    "sg:classifiers":[
        {
            "category":"Shopping",
            "subcategory":"Computers & Home Electronics",
            "type":"Retail Goods"
        }
    ],
    "sg:phone":"+1 704 661 3200",
    "sg:postcode":"28227",
    "sg:province":"NC",
    "wof:name":"BT Enterprises",
    "wof:placetype":"venue"
},
  "geometry": {"coordinates":[-80.68357399999999,35.186753],"type":"Point"}
}