{
  "type": "Feature",
  "properties": {
    "iso:country":"US",
    "sg:address":"7176 Gum Branch Rd",
    "sg:city":"Richlands",
    "sg:classifiers":[
        {
            "category":"Organizations",
            "subcategory":"Religious Organization",
            "type":"Services"
        }
    ],
    "sg:phone":"+1 910 324 2471",
    "sg:postcode":"28574",
    "sg:province":"NC",
    "sg:tags":[
        "church"
    ],
    "wof:name":"St Paul Free Will Baptist Chr",
    "wof:placetype":"venue"
},
  "geometry": {"coordinates":[-77.523032,34.882386],"type":"Point"}
}