{
  "type": "Feature",
  "properties": {
    "addr:full":"800 Stadium Dr Durham NC 27704",
    "addr:housenumber":"800",
    "addr:postcode":"27704",
    "addr:street":"Stadium Dr",
    "iso:country":"US",
    "sg:address":"800 Stadium Dr",
    "sg:city":"Durham",
    "sg:classifiers":[
        {
            "category":"Recreation",
            "subcategory":"Amusement Park",
            "type":"Entertainment"
        },
        {
            "category":"Recreation",
            "type":"Entertainment"
        }
    ],
    "sg:phone":"+1 919 317 1816",
    "sg:postcode":"27704",
    "sg:province":"NC",
    "wof:name":"Amusements Of Rockchester",
    "wof:placetype":"venue"
},
  "geometry": {"coordinates":[-78.89957,36.03358],"type":"Point"}
}