{
  "type": "Feature",
  "properties": {
    "addr:full":"160 Royal Pines Dr Arden NC 28704",
    "addr:housenumber":"160",
    "addr:postcode":"dr;28704",
    "addr:street":"Royal Pines",
    "iso:country":"US",
    "sg:address":"160 Royal Pines Dr",
    "sg:city":"Arden",
    "sg:classifiers":[
        {
            "category":"Professional",
            "type":"Services"
        }
    ],
    "sg:phone":"+1 828 651 9936",
    "sg:postcode":"28704",
    "sg:province":"NC",
    "sg:tags":[
        "establishment"
    ],
    "wof:name":"Guastucci Global Commercial",
    "wof:placetype":"venue"
},
  "geometry": {"coordinates":[-82.517223,35.474686],"type":"Point"}
}