{
  "type": "Feature",
  "properties": {
    "iso:country":"US",
    "sg:address":"19722 One Norman Blvd",
    "sg:city":"Cornelius",
    "sg:classifiers":[
        {
            "category":"Wholesale",
            "subcategory":"Metals & Minerals",
            "type":"Manufacturing & Wholesale Goods"
        }
    ],
    "sg:phone":"+1 704 896 2525",
    "sg:postcode":"28031",
    "sg:province":"NC",
    "sg:tags":[
        "specialty"
    ],
    "wof:name":"Coastline Specialty Supply",
    "wof:placetype":"venue"
},
  "geometry": {"coordinates":[-80.882668,35.481672],"type":"Point"}
}