{
  "type": "Feature",
  "properties": {
    "addr:full":"3117 Cokey Rd Rocky Mount NC 27801",
    "addr:housenumber":"3117",
    "addr:postcode":"27801",
    "addr:street":"Cokey Rd",
    "iso:country":"US",
    "sg:address":"3117 Cokey Rd",
    "sg:city":"Rocky Mount",
    "sg:classifiers":[
        {
            "category":"Local Transit",
            "type":"Transportation"
        }
    ],
    "sg:phone":"+1 252 972 9972",
    "sg:postcode":"27801",
    "sg:province":"NC",
    "sg:tags":[
        "limousine"
    ],
    "wof:name":"A 1 First Class Limousine Svc",
    "wof:placetype":"venue"
},
  "geometry": {"coordinates":[-77.757125,35.915154],"type":"Point"}
}