{
  "type": "Feature",
  "properties": {
    "addr:full":"115 Micmac Trl Hertford NC 27944",
    "addr:housenumber":"115",
    "addr:postcode":"27944",
    "addr:street":"Micmac Trl",
    "iso:country":"US",
    "sg:address":"115 Micmac Trl",
    "sg:city":"Hertford",
    "sg:classifiers":[
        {
            "category":"Building & Trades",
            "subcategory":"Cleaning & Sanitation",
            "type":"Services"
        }
    ],
    "sg:phone":"+1 252 426 7820",
    "sg:postcode":"27944",
    "sg:province":"NC",
    "sg:tags":[
        "janitor",
        "maintenance"
    ],
    "wof:name":"Dependable Cleaning Service",
    "wof:placetype":"venue"
},
  "geometry": {"coordinates":[-76.421104,36.084118],"type":"Point"}
}