{
  "type": "Feature",
  "properties": {
    "iso:country":"US",
    "sg:address":"6219 Underwood Ave",
    "sg:city":"Charlotte",
    "sg:classifiers":[
        {
            "category":"Education",
            "subcategory":"Dance Studio",
            "type":"Public Place"
        }
    ],
    "sg:phone":"+1   ",
    "sg:postcode":"28213",
    "sg:province":"NC",
    "wof:name":"Precision Dance Center",
    "wof:placetype":"venue"
},
  "geometry": {"coordinates":[-80.68028099999999,35.304644],"type":"Point"}
}