{
  "type": "Feature",
  "properties": {
    "iso:country":"US",
    "sg:address":"530 Murray Fork Dr",
    "sg:city":"Fayetteville",
    "sg:classifiers":[
        {
            "category":"Travel",
            "subcategory":"Travel Agent",
            "type":"Entertainment"
        }
    ],
    "sg:phone":"+1 910 867 8769",
    "sg:postcode":"28314",
    "sg:province":"NC",
    "sg:tags":[
        "operator",
        "tour"
    ],
    "wof:name":"Amport Tours",
    "wof:placetype":"venue"
},
  "geometry": {"coordinates":[-78.986087,35.07589],"type":"Point"}
}