{
  "type": "Feature",
  "properties": {
    "iso:country":"US",
    "sg:address":"2603 Glenwood Ave",
    "sg:city":"Raleigh",
    "sg:classifiers":[
        {
            "category":"Banks & Credit Unions",
            "subcategory":"Investment Brokerage",
            "type":"Services"
        }
    ],
    "sg:phone":"+1 919 788 0276",
    "sg:postcode":"27608",
    "sg:province":"NC",
    "sg:tags":[
        "security"
    ],
    "sg:website":"www.edwardjones.com",
    "wof:name":"Edward Jones",
    "wof:placetype":"venue"
},
  "geometry": {"coordinates":[-78.66213,35.817495],"type":"Point"}
}