{
  "type": "Feature",
  "properties": {
    "iso:country":"US",
    "sg:address":"4961 Home Rd NW",
    "sg:city":"Winston Salem",
    "sg:classifiers":[
        {
            "category":"Shopping",
            "type":"Retail Goods"
        },
        {
            "category":"Manufacturing",
            "subcategory":"Chemicals & Compounds",
            "type":"Manufacturing & Wholesale Goods"
        }
    ],
    "sg:phone":"+1 336 767 9390",
    "sg:postcode":"27106",
    "sg:province":"NC",
    "sg:tags":[
        "synthetic",
        "webbing",
        "sling",
        "for",
        "used",
        "overhead",
        "lifting",
        "weave"
    ],
    "sg:website":"www.wear-flex.com",
    "wof:name":"American Webbing Fittings Inc",
    "wof:placetype":"venue"
},
  "geometry": {"coordinates":[-80.278387,36.159887],"type":"Point"}
}