{
  "type": "Feature",
  "properties": {
    "addr:full":"1463 N Main St Mooresville NC 28115",
    "addr:housenumber":"1463",
    "addr:postcode":"28115",
    "addr:street":"N Main St",
    "iso:country":"US",
    "sg:address":"1463 N Main St",
    "sg:city":"Mooresville",
    "sg:classifiers":[
        {
            "category":"Building & Trades",
            "subcategory":"Construction",
            "type":"Services"
        }
    ],
    "sg:phone":"+1 704 662 9374",
    "sg:postcode":"28115",
    "sg:province":"NC",
    "sg:tags":[
        "handyman"
    ],
    "wof:name":"Maintenance Solution Inc",
    "wof:placetype":"venue"
},
  "geometry": {"coordinates":[-80.788382,35.592465],"type":"Point"}
}