{
  "type": "Feature",
  "properties": {
    "addr:full":"201 S Elm St Williamston NC 27892",
    "addr:housenumber":"201",
    "addr:postcode":"27892",
    "addr:street":"S Elm St",
    "iso:country":"US",
    "sg:address":"201 S Elm St",
    "sg:city":"Williamston",
    "sg:classifiers":[
        {
            "category":"Wholesale",
            "subcategory":"Electrical",
            "type":"Manufacturing & Wholesale Goods"
        }
    ],
    "sg:phone":"+1 252 792 7155",
    "sg:postcode":"27892",
    "sg:province":"NC",
    "sg:tags":[
        "fire",
        "equipment",
        "protection"
    ],
    "sg:website":"www.ffpsafety.com",
    "wof:name":"Fire Fighter Products",
    "wof:placetype":"venue"
},
  "geometry": {"coordinates":[-77.057644,35.85169],"type":"Point"}
}