{
  "type": "Feature",
  "properties": {
    "iso:country":"US",
    "sg:address":"310 Harper Ave",
    "sg:city":"Carolina Beach",
    "sg:classifiers":[
        {
            "category":"Travel",
            "subcategory":"Hotels & Motels",
            "type":"Entertainment"
        }
    ],
    "sg:phone":"+1 910 458 9747",
    "sg:postcode":"28428",
    "sg:province":"NC",
    "wof:name":"Pleasure Island Motel",
    "wof:placetype":"venue"
},
  "geometry": {"coordinates":[-77.89702200000001,34.036433],"type":"Point"}
}