{
  "type": "Feature",
  "properties": {
    "iso:country":"US",
    "sg:address":"272 Forest Hill Dr",
    "sg:city":"Marion",
    "sg:classifiers":[
        {
            "category":"Retail",
            "subcategory":"Auto Repair",
            "type":"Services"
        }
    ],
    "sg:phone":"+1 828 724 9280",
    "sg:postcode":"28752",
    "sg:province":"NC",
    "sg:tags":[
        "recreational",
        "vehicle"
    ],
    "wof:name":"Becker's Rv Svc",
    "wof:placetype":"venue"
},
  "geometry": {"coordinates":[-82.08223099999999,35.682767],"type":"Point"}
}