{
  "type": "Feature",
  "properties": {
    "addr:full":"2005 Bowman Ln Raleigh NC 27610",
    "addr:housenumber":"2005",
    "addr:postcode":"27610",
    "addr:street":"Bowman Ln",
    "iso:country":"US",
    "sg:address":"2005 Bowman Ln",
    "sg:city":"Raleigh",
    "sg:classifiers":[
        {
            "category":"Real Estate",
            "subcategory":"Real Estate Agent",
            "type":"Services"
        }
    ],
    "sg:phone":"+1 919 264 9748",
    "sg:postcode":"27610",
    "sg:province":"NC",
    "sg:tags":[
        "investing"
    ],
    "wof:name":"Metropolitan Designs",
    "wof:placetype":"venue"
},
  "geometry": {"coordinates":[-78.608653,35.750797],"type":"Point"}
}