{
  "type": "Feature",
  "properties": {
    "addr:full":"621 Autry Hwy Roseboro NC 28382",
    "addr:housenumber":"621",
    "addr:postcode":"28382",
    "addr:street":"Autry Hwy",
    "iso:country":"US",
    "sg:address":"621 Autry Hwy",
    "sg:city":"Roseboro",
    "sg:classifiers":[
        {
            "category":"Wholesale",
            "subcategory":"Fruits & Vegetables",
            "type":"Manufacturing & Wholesale Goods"
        }
    ],
    "sg:phone":"+1 910 525 5331",
    "sg:postcode":"28382",
    "sg:province":"NC",
    "sg:tags":[
        "shipper"
    ],
    "wof:name":"Roseboro Produce Market",
    "wof:placetype":"venue"
},
  "geometry": {"coordinates":[-78.520386,34.960144],"type":"Point"}
}