{
  "type": "Feature",
  "properties": {
    "iso:country":"US",
    "sg:address":"1811 Dunleith Way",
    "sg:city":"Greensboro",
    "sg:classifiers":[
        {
            "category":"Professional",
            "subcategory":"Management & Consulting",
            "type":"Services"
        }
    ],
    "sg:phone":"+1   ",
    "sg:postcode":"27455",
    "sg:province":"NC",
    "wof:name":"Innovtons Cons Dsgners Dvlpers",
    "wof:placetype":"venue"
},
  "geometry": {"coordinates":[-79.81666,36.12422],"type":"Point"}
}