{
  "type": "Feature",
  "properties": {
    "addr:full":"721 Riverside Ave Elizabeth City NC 27909",
    "addr:housenumber":"721",
    "addr:postcode":"27909",
    "addr:street":"Riverside Ave",
    "iso:country":"US",
    "sg:address":"721 Riverside Ave",
    "sg:city":"Elizabeth City",
    "sg:classifiers":[
        {
            "category":"Personal",
            "type":"Services"
        }
    ],
    "sg:phone":"+1 252 335 2440",
    "sg:postcode":"27909",
    "sg:province":"NC",
    "sg:tags":[
        "therapist",
        "massage"
    ],
    "wof:name":"Riverside Massage Therapy",
    "wof:placetype":"venue"
},
  "geometry": {"coordinates":[-76.21650699999999,36.295859],"type":"Point"}
}