{
  "type": "Feature",
  "properties": {
    "iso:country":"US",
    "sg:address":"1314 Ashleybrook Ln",
    "sg:city":"Winston Salem",
    "sg:classifiers":[
        {
            "category":"Retail",
            "subcategory":"Repair Shop",
            "type":"Services"
        }
    ],
    "sg:phone":"+1 336 794 2787",
    "sg:postcode":"27103",
    "sg:province":"NC",
    "sg:tags":[
        "equipment",
        "industrial"
    ],
    "wof:name":"Rotating Equipment Specialist",
    "wof:placetype":"venue"
},
  "geometry": {"coordinates":[-80.312116,36.074303],"type":"Point"}
}