{
  "type": "Feature",
  "properties": {
    "addr:full":"924 Dickinson Ave Greenville NC 27834",
    "addr:housenumber":"924",
    "addr:postcode":"27834",
    "addr:street":"Dickinson Ave",
    "iso:country":"US",
    "sg:address":"924 Dickinson Ave",
    "sg:city":"Greenville",
    "sg:classifiers":[
        {
            "category":"Shopping",
            "subcategory":"Used Merchandise",
            "type":"Retail Goods"
        }
    ],
    "sg:phone":"+1 252 916 8027",
    "sg:postcode":"27834",
    "sg:province":"NC",
    "sg:tags":[
        "antique"
    ],
    "wof:name":"Antiques Valaries",
    "wof:placetype":"venue"
},
  "geometry": {"coordinates":[-77.379317,35.60778],"type":"Point"}
}