{
  "type": "Feature",
  "properties": {
    "addr:full":"923 Hanover St Gastonia NC 28054",
    "addr:housenumber":"923",
    "addr:postcode":"28054",
    "addr:street":"Hanover St",
    "iso:country":"US",
    "sg:address":"923 Hanover St",
    "sg:city":"Gastonia",
    "sg:classifiers":[
        {
            "category":"Retail",
            "subcategory":"Auto Repair",
            "type":"Services"
        }
    ],
    "sg:phone":"+1 704 864 4918",
    "sg:postcode":"28054",
    "sg:province":"NC",
    "sg:tags":[
        "wrecker"
    ],
    "wof:name":"Star Towing & Recovery",
    "wof:placetype":"venue"
},
  "geometry": {"coordinates":[-81.180071,35.276332],"type":"Point"}
}