{
  "type": "Feature",
  "properties": {
    "iso:country":"US",
    "sg:address":"5811 Harvest Springs Dr",
    "sg:city":"Greensboro",
    "sg:classifiers":[
        {
            "category":"Social Services",
            "subcategory":"Child Care",
            "type":"Services"
        }
    ],
    "sg:phone":"+1   ",
    "sg:postcode":"27406",
    "sg:province":"NC",
    "sg:tags":[
        "day"
    ],
    "wof:name":"Victorious Living Inc",
    "wof:placetype":"venue"
},
  "geometry": {"coordinates":[-79.820404,35.934278],"type":"Point"}
}