{
  "type": "Feature",
  "properties": {
    "iso:country":"US",
    "sg:address":"102 Idlewood Dr",
    "sg:city":"Asheville",
    "sg:classifiers":[
        {
            "category":"Organizations",
            "subcategory":"Religious Organization",
            "type":"Services"
        }
    ],
    "sg:phone":"+1   ",
    "sg:postcode":"28806",
    "sg:province":"NC",
    "wof:name":"Catholic War Veterans of",
    "wof:placetype":"venue"
},
  "geometry": {"coordinates":[-82.612632,35.511758],"type":"Point"}
}