{
  "type": "Feature",
  "properties": {
    "iso:country":"US",
    "sg:address":"6058 Clinton Rd",
    "sg:city":"Stedman",
    "sg:classifiers":[
        {
            "category":"Retail",
            "subcategory":"Auto Repair",
            "type":"Services"
        }
    ],
    "sg:phone":"+1 910 485 7786",
    "sg:postcode":"28391",
    "sg:province":"NC",
    "sg:tags":[
        "repairing",
        "automobile"
    ],
    "wof:name":"Baker's Alignment & Repair",
    "wof:placetype":"venue"
},
  "geometry": {"coordinates":[-78.688183,35.011195],"type":"Point"}
}