{
  "type": "Feature",
  "properties": {
    "addr:full":"5001 South Blvd Charlotte NC 28217",
    "addr:housenumber":"5001",
    "addr:postcode":"28217",
    "addr:street":"South Blvd",
    "iso:country":"US",
    "sg:address":"5001 South Blvd",
    "sg:city":"Charlotte",
    "sg:classifiers":[
        {
            "category":"Building & Trades",
            "subcategory":"Construction",
            "type":"Services"
        }
    ],
    "sg:phone":"+1 704 522 0074",
    "sg:postcode":"28217",
    "sg:province":"NC",
    "sg:tags":[
        "home",
        "builder"
    ],
    "wof:name":"Ken Bradshaw Co",
    "wof:placetype":"venue"
},
  "geometry": {"coordinates":[-80.8759,35.171062],"type":"Point"}
}