{
  "type": "Feature",
  "properties": {
    "iso:country":"US",
    "sg:address":"15 S Main St",
    "sg:city":"Belmont",
    "sg:classifiers":[
        {
            "category":"Shopping",
            "subcategory":"Computers & Home Electronics",
            "type":"Retail Goods"
        }
    ],
    "sg:phone":"+1 704 829 1082",
    "sg:postcode":"28012",
    "sg:province":"NC",
    "sg:tags":[
        "audio"
    ],
    "wof:name":"Visual Cleaning Concepts",
    "wof:placetype":"venue"
},
  "geometry": {"coordinates":[-81.038017,35.241817],"type":"Point"}
}