{
  "type": "Feature",
  "properties": {
    "iso:country":"US",
    "sg:address":"4605 Hedgemore Dr",
    "sg:city":"Charlotte",
    "sg:classifiers":[
        {
            "category":"Communications",
            "subcategory":"Film & Video Production",
            "type":"Services"
        }
    ],
    "sg:phone":"+1   ",
    "sg:postcode":"28209",
    "sg:province":"NC",
    "sg:tags":[
        "motion"
    ],
    "wof:name":"Camp TV Media",
    "wof:placetype":"venue"
},
  "geometry": {"coordinates":[-80.848325,35.169251],"type":"Point"}
}