{
  "type": "Feature",
  "properties": {
    "iso:country":"US",
    "sg:address":"3680 Neuse Blvd",
    "sg:city":"New Bern",
    "sg:classifiers":[
        {
            "category":"Health Services",
            "subcategory":"Doctor",
            "type":"Services"
        }
    ],
    "sg:phone":"+1 252 638 1864",
    "sg:postcode":"28560",
    "sg:province":"NC",
    "sg:tags":[
        "dentist"
    ],
    "wof:name":"Freshwater & Howdy PA",
    "wof:placetype":"venue"
},
  "geometry": {"coordinates":[-77.09863799999999,35.136987],"type":"Point"}
}