{
  "type": "Feature",
  "properties": {
    "addr:full":"702 E 3rd St Siler City NC 27344",
    "addr:housenumber":"702",
    "addr:postcode":"27344",
    "addr:street":"E 3Rd St",
    "iso:country":"US",
    "sg:address":"702 E 3rd St",
    "sg:city":"Siler City",
    "sg:classifiers":[
        {
            "category":"Retail",
            "subcategory":"Auto Repair",
            "type":"Services"
        }
    ],
    "sg:phone":"+1 919 742 5991",
    "sg:postcode":"27344",
    "sg:province":"NC",
    "sg:tags":[
        "shop",
        "automotive",
        "automobile",
        "repairing",
        "general"
    ],
    "wof:name":"Siler City Radiator and Auto",
    "wof:placetype":"venue"
},
  "geometry": {"coordinates":[-79.45178900000001,35.730154],"type":"Point"}
}