{
  "type": "Feature",
  "properties": {
    "addr:full":"10960 Winds Crossing Dr Charlotte NC 28273",
    "addr:postcode":"10960;28273",
    "addr:street":"Winds Crossing Dr",
    "iso:country":"US",
    "sg:address":"10960 Winds Crossing Dr",
    "sg:city":"Charlotte",
    "sg:classifiers":[
        {
            "category":"Personal",
            "subcategory":"Beauty Salon",
            "type":"Services"
        }
    ],
    "sg:phone":"+1 704 504 2253",
    "sg:postcode":"28273",
    "sg:province":"NC",
    "wof:name":"Forever Young Salon & Spa",
    "wof:placetype":"venue"
},
  "geometry": {"coordinates":[-80.95885,35.115578],"type":"Point"}
}