{
  "type": "Feature",
  "properties": {
    "iso:country":"US",
    "sg:address":"1450 Raleigh Rd Ste 300",
    "sg:city":"Chapel Hill",
    "sg:classifiers":[
        {
            "category":"Professional",
            "subcategory":"Lawyer & Legal Services",
            "type":"Services"
        }
    ],
    "sg:phone":"+1 704 377 8392",
    "sg:postcode":"27517",
    "sg:province":"NC",
    "wof:name":"Hart Jeffrey C Atty",
    "wof:placetype":"venue"
},
  "geometry": {"coordinates":[-79.007886,35.90195],"type":"Point"}
}