{
  "type": "Feature",
  "properties": {
    "addr:full":"2897 Owen Dr Fayetteville NC 28306",
    "addr:housenumber":"2897",
    "addr:postcode":"28306",
    "addr:street":"Owen Dr",
    "iso:country":"US",
    "sg:address":"2897 Owen Dr",
    "sg:city":"Fayetteville",
    "sg:classifiers":[
        {
            "category":"Professional",
            "subcategory":"Accounting & Tax Preparation",
            "type":"Services"
        }
    ],
    "sg:phone":"+1 866 871 1040",
    "sg:postcode":"28306",
    "sg:province":"NC",
    "sg:tags":[
        "return",
        "preparation-business"
    ],
    "sg:website":"http://www.libertytax.com/",
    "wof:name":"Liberty Tax Service",
    "wof:placetype":"venue"
},
  "geometry": {"coordinates":[-78.900803,35.018998],"type":"Point"}
}