{
  "type": "Feature",
  "properties": {
    "iso:country":"US",
    "sg:address":"366 N Gregory Rd",
    "sg:city":"Shawboro",
    "sg:classifiers":[
        {
            "category":"Building & Trades",
            "subcategory":"Landscaping Services",
            "type":"Services"
        }
    ],
    "sg:phone":"+1 252 338 2479",
    "sg:postcode":"27973",
    "sg:province":"NC",
    "sg:tags":[
        "landscape"
    ],
    "wof:name":"Countryscapes Landscaping Inc",
    "wof:placetype":"venue"
},
  "geometry": {"coordinates":[-76.123706,36.384752],"type":"Point"}
}