{
  "type": "Feature",
  "properties": {
    "iso:country":"US",
    "sg:address":"360 Union Bethel Rd",
    "sg:city":"Hampstead",
    "sg:classifiers":[
        {
            "category":"Freight",
            "type":"Transportation"
        }
    ],
    "sg:phone":"+1 910 270 2669",
    "sg:postcode":"28443",
    "sg:province":"NC",
    "sg:tags":[
        "operator",
        "local",
        "trucking"
    ],
    "wof:name":"Moore & Son Trucking Inc",
    "wof:placetype":"venue"
},
  "geometry": {"coordinates":[-77.63458300000001,34.423752],"type":"Point"}
}