{
  "type": "Feature",
  "properties": {
    "iso:country":"US",
    "sg:address":"327 N Queen St",
    "sg:city":"Kinston",
    "sg:classifiers":[
        {
            "category":"Building & Trades",
            "subcategory":"Equipment Rental",
            "type":"Services"
        }
    ],
    "sg:phone":"+1 252 522 8004",
    "sg:postcode":"28501",
    "sg:province":"NC",
    "sg:tags":[
        "crane"
    ],
    "wof:name":"Consumer Credit Counseling Svc",
    "wof:placetype":"venue"
},
  "geometry": {"coordinates":[-77.581008,35.263371],"type":"Point"}
}