{
  "type": "Feature",
  "properties": {
    "addr:full":"3405 Yankee Hall Rd Greenville NC 27834",
    "addr:housenumber":"3405",
    "addr:postcode":"27834",
    "addr:street":"Yankee Hall Rd",
    "iso:country":"US",
    "sg:address":"3405 Yankee Hall Rd",
    "sg:city":"Greenville",
    "sg:classifiers":[
        {
            "category":"Education",
            "subcategory":"School",
            "type":"Public Place"
        }
    ],
    "sg:phone":"+1 252 752 6941",
    "sg:postcode":"27834",
    "sg:province":"NC",
    "sg:tags":[
        "elementary"
    ],
    "sg:website":"www.pactolusschool.com",
    "wof:name":"Pactolus Elementary School",
    "wof:placetype":"venue"
},
  "geometry": {"coordinates":[-77.223944,35.622177],"type":"Point"}
}