{
  "type": "Feature",
  "properties": {
    "iso:country":"US",
    "sg:address":"44 Nevada Ct",
    "sg:city":"Spring Lake",
    "sg:classifiers":[
        {
            "category":"Building & Trades",
            "subcategory":"Construction",
            "type":"Services"
        }
    ],
    "sg:phone":"+1 910 497 0669",
    "sg:postcode":"28390",
    "sg:province":"NC",
    "sg:tags":[
        "house",
        "c"
    ],
    "wof:name":"West Services",
    "wof:placetype":"venue"
},
  "geometry": {"coordinates":[-78.94407,35.252468],"type":"Point"}
}