{
  "type": "Feature",
  "properties": {
    "addr:full":"3201 Glenwood Ave Raleigh NC 27612",
    "addr:housenumber":"3201",
    "addr:postcode":"27612",
    "addr:street":"Glenwood Ave",
    "iso:country":"US",
    "sg:address":"3201 Glenwood Ave",
    "sg:city":"Raleigh",
    "sg:classifiers":[
        {
            "category":"Professional",
            "subcategory":"Lawyer & Legal Services",
            "type":"Services"
        }
    ],
    "sg:phone":"+1 919 881 2111",
    "sg:postcode":"27612",
    "sg:province":"NC",
    "sg:tags":[
        "attorney"
    ],
    "sg:website":"www.kirby-holt.com",
    "wof:name":"Kirby & Holt",
    "wof:placetype":"venue"
},
  "geometry": {"coordinates":[-78.66608600000001,35.826291],"type":"Point"}
}