{
  "type": "Feature",
  "properties": {
    "iso:country":"US",
    "sg:address":"701 Stevens Mill Rd",
    "sg:city":"Goldsboro",
    "sg:classifiers":[
        {
            "category":"Government",
            "subcategory":"Jail",
            "type":"Public Place"
        }
    ],
    "sg:phone":"+1 919 731 2023",
    "sg:postcode":"27530",
    "sg:province":"NC",
    "sg:tags":[
        "govt",
        "state",
        "institution"
    ],
    "sg:website":"www.doc.state.nc.us",
    "wof:name":"Neuse Correctional Institute",
    "wof:placetype":"venue"
},
  "geometry": {"coordinates":[-78.03402699999999,35.387882],"type":"Point"}
}