{
  "type": "Feature",
  "properties": {
    "addr:full":"8721 Stephenson Rd Apex NC 27539",
    "addr:housenumber":"8721",
    "addr:postcode":"27539",
    "addr:street":"Stephenson Rd",
    "iso:country":"US",
    "sg:address":"8721 Stephenson Rd",
    "sg:city":"Apex",
    "sg:classifiers":[
        {
            "category":"Retail",
            "subcategory":"Repair Shop",
            "type":"Services"
        }
    ],
    "sg:phone":"+1 919 362 1321",
    "sg:postcode":"27539",
    "sg:province":"NC",
    "sg:tags":[
        "upholsterer"
    ],
    "wof:name":"Bowden's Upholstery",
    "wof:placetype":"venue"
},
  "geometry": {"coordinates":[-78.807339,35.683589],"type":"Point"}
}