{
  "type": "Feature",
  "properties": {
    "iso:country":"US",
    "sg:address":"439 Beaver Creek Rd",
    "sg:city":"Lexington",
    "sg:classifiers":[
        {
            "category":"Recreation",
            "type":"Entertainment"
        }
    ],
    "sg:phone":"+1 336 956 6245",
    "sg:postcode":"27295",
    "sg:province":"NC",
    "sg:tags":[
        "course",
        "golf"
    ],
    "wof:name":"Sapona Country Club Inc",
    "wof:placetype":"venue"
},
  "geometry": {"coordinates":[-80.314207,35.80374],"type":"Point"}
}