{
  "type": "Feature",
  "properties": {
    "addr:full":"399 Mutton Creek Ln Boone NC 28607",
    "addr:housenumber":"399",
    "addr:postcode":"28607",
    "addr:street":"Mutton Creek Ln",
    "iso:country":"US",
    "sg:address":"399 Mutton Creek Ln",
    "sg:city":"Boone",
    "sg:classifiers":[
        {
            "category":"Building & Trades",
            "subcategory":"Construction",
            "type":"Services"
        }
    ],
    "sg:phone":"+1 828 964 9306",
    "sg:postcode":"28607",
    "sg:province":"NC",
    "sg:tags":[
        "general",
        "contractor"
    ],
    "wof:name":"Michael Reed Construction Inc",
    "wof:placetype":"venue"
},
  "geometry": {"coordinates":[-81.622575,36.203747],"type":"Point"}
}