{
  "type": "Feature",
  "properties": {
    "addr:full":"919 3rd St SE Hickory NC 28602",
    "addr:housenumber":"919",
    "addr:postcode":"28602",
    "addr:street":"3Rd St Se",
    "iso:country":"US",
    "sg:address":"919 3rd St SE",
    "sg:city":"Hickory",
    "sg:classifiers":[
        {
            "category":"Professional",
            "subcategory":"Management & Consulting",
            "type":"Services"
        }
    ],
    "sg:phone":"+1   ",
    "sg:postcode":"28602",
    "sg:province":"NC",
    "wof:name":"B&D Consulting Inc",
    "wof:placetype":"venue"
},
  "geometry": {"coordinates":[-81.333015,35.721493],"type":"Point"}
}