{
  "type": "Feature",
  "properties": {
    "addr:full":"7219 Dunn Rd Roseboro NC 28382",
    "addr:housenumber":"7219",
    "addr:postcode":"28382",
    "addr:street":"Dunn Rd",
    "iso:country":"US",
    "sg:address":"7219 Dunn Rd",
    "sg:city":"Roseboro",
    "sg:classifiers":[
        {
            "category":"Restaurant",
            "type":"Food & Drink"
        }
    ],
    "sg:phone":"+1 910 486 8151",
    "sg:postcode":"28382",
    "sg:province":"NC",
    "wof:name":"Main Street Grill",
    "wof:placetype":"venue"
},
  "geometry": {"coordinates":[-78.555931,35.053351],"type":"Point"}
}