{
  "type": "Feature",
  "properties": {
    "iso:country":"US",
    "sg:address":"2030 Garner Station Blvd",
    "sg:city":"Raleigh",
    "sg:classifiers":[
        {
            "category":"Wholesale",
            "subcategory":"Metals & Minerals",
            "type":"Manufacturing & Wholesale Goods"
        }
    ],
    "sg:phone":"+1 919 773 9338",
    "sg:postcode":"27603",
    "sg:province":"NC",
    "sg:tags":[
        "pipe",
        "center"
    ],
    "wof:name":"Robert James Sales Inc",
    "wof:placetype":"venue"
},
  "geometry": {"coordinates":[-78.661168,35.724683],"type":"Point"}
}