{
  "type": "Feature",
  "properties": {
    "iso:country":"US",
    "sg:address":"2737 W Sugar Creek Rd",
    "sg:city":"Charlotte",
    "sg:classifiers":[
        {
            "category":"Restaurant",
            "type":"Food & Drink"
        }
    ],
    "sg:phone":"+1 704 596 6106",
    "sg:postcode":"28262",
    "sg:province":"NC",
    "sg:tags":[
        "parlor",
        "eating",
        "ice",
        "cream"
    ],
    "wof:name":"J R's Dairy Bar",
    "wof:placetype":"venue"
},
  "geometry": {"coordinates":[-80.80057600000001,35.298979],"type":"Point"}
}