{
  "type": "Feature",
  "properties": {
    "iso:country":"US",
    "sg:address":"4150 Tite Rd",
    "sg:city":"Stanfield",
    "sg:classifiers":[
        {
            "category":"Building & Trades",
            "subcategory":"Construction",
            "type":"Services"
        }
    ],
    "sg:phone":"+1 704 888 1924",
    "sg:postcode":"28163",
    "sg:province":"NC",
    "sg:tags":[
        "residential"
    ],
    "wof:name":"Wood Details",
    "wof:placetype":"venue"
},
  "geometry": {"coordinates":[-80.467668,35.183721],"type":"Point"}
}