{
  "type": "Feature",
  "properties": {
    "iso:country":"US",
    "sg:address":"101 Deaton Ave",
    "sg:city":"Lincolnton",
    "sg:classifiers":[
        {
            "category":"Social Services",
            "subcategory":"Child Care",
            "type":"Services"
        }
    ],
    "sg:phone":"+1 704 732 3201",
    "sg:postcode":"28092",
    "sg:province":"NC",
    "wof:name":"Deaton Street Headstart",
    "wof:placetype":"venue"
},
  "geometry": {"coordinates":[-81.259321,35.4854],"type":"Point"}
}