{
  "type": "Feature",
  "properties": {
    "addr:full":"412 S Brightleaf Blvd Smithfield NC 27577",
    "addr:housenumber":"412",
    "addr:postcode":"27577",
    "addr:street":"S Brightleaf Blvd",
    "iso:country":"US",
    "sg:address":"412 S Brightleaf Blvd",
    "sg:city":"Smithfield",
    "sg:classifiers":[
        {
            "category":"Home & Garden",
            "subcategory":"Home Furnishings",
            "type":"Retail Goods"
        }
    ],
    "sg:phone":"+1 919 934 0363",
    "sg:postcode":"27577",
    "sg:province":"NC",
    "sg:tags":[
        "lighting",
        "household",
        "fixture",
        "sales",
        "accessory"
    ],
    "wof:name":"Smithfield Lighting Center",
    "wof:placetype":"venue"
},
  "geometry": {"coordinates":[-78.34175399999999,35.505542],"type":"Point"}
}