{
  "type": "Feature",
  "properties": {
    "addr:full":"371 Morse St Mocksville NC 27028",
    "addr:housenumber":"371",
    "addr:postcode":"27028",
    "addr:street":"Morse St",
    "iso:country":"US",
    "sg:address":"371 Morse St",
    "sg:city":"Mocksville",
    "sg:classifiers":[
        {
            "category":"Professional",
            "subcategory":"Business Services",
            "type":"Services"
        },
        {
            "category":"Insurance",
            "subcategory":"Insurance Agent",
            "type":"Services"
        }
    ],
    "sg:phone":"+1 336 751 5416",
    "sg:postcode":"27028",
    "sg:province":"NC",
    "wof:name":"Steele & Associates",
    "wof:placetype":"venue"
},
  "geometry": {"coordinates":[-80.529336,35.904481],"type":"Point"}
}