{
  "type": "Feature",
  "properties": {
    "addr:full":"80 Toot- Toot St Saint Pauls NC 28384",
    "addr:housenumber":"80",
    "addr:postcode":"28384",
    "addr:street":"Toot Toot St",
    "iso:country":"US",
    "sg:address":"80 Toot- Toot St",
    "sg:city":"Saint Pauls",
    "sg:classifiers":[
        {
            "category":"Organizations",
            "subcategory":"Religious Organization",
            "type":"Services"
        }
    ],
    "sg:phone":"+1   ",
    "sg:postcode":"28384",
    "sg:province":"NC",
    "wof:name":"Pinbrooke Assembly of God",
    "wof:placetype":"venue"
},
  "geometry": {"coordinates":[-78.920068,34.792642],"type":"Point"}
}