{
  "type": "Feature",
  "properties": {
    "addr:full":"681 Penland Rd Franklin NC 28734",
    "addr:housenumber":"681",
    "addr:postcode":"nc 28734",
    "addr:street":"Penland Rd",
    "iso:country":"US",
    "sg:address":"681 Penland Rd",
    "sg:city":"Franklin",
    "sg:classifiers":[
        {
            "category":"Real Estate",
            "subcategory":"Real Estate Agent",
            "type":"Services"
        }
    ],
    "sg:phone":"+1 828 369 3801",
    "sg:postcode":"28734",
    "sg:province":"NC",
    "wof:name":"Edward J Sullivan Inc",
    "wof:placetype":"venue"
},
  "geometry": {"coordinates":[-83.506496,35.165211],"type":"Point"}
}