{
  "type": "Feature",
  "properties": {
    "addr:full":"60 E Main St Franklin NC 28734",
    "addr:housenumber":"60",
    "addr:postcode":"nc 28734",
    "addr:street":"E Main St",
    "iso:country":"US",
    "sg:address":"60 E Main St",
    "sg:city":"Franklin",
    "sg:classifiers":[
        {
            "category":"Shopping",
            "subcategory":"Books",
            "type":"Retail Goods"
        }
    ],
    "sg:phone":"+1 828 369 7942",
    "sg:postcode":"28734",
    "sg:province":"NC",
    "sg:tags":[
        "communications",
        "telegraph"
    ],
    "wof:name":"Books Unlimited",
    "wof:placetype":"venue"
},
  "geometry": {"coordinates":[-83.379746,35.182343],"type":"Point"}
}