{
  "type": "Feature",
  "properties": {
    "addr:full":"6941 Woody Ridge Rd Snow Camp NC 27253",
    "addr:housenumber":"6941",
    "addr:postcode":"27253",
    "addr:street":"Woody Ridge Rd",
    "iso:country":"US",
    "sg:address":"6941 Woody Ridge Rd",
    "sg:city":"Snow Camp",
    "sg:classifiers":[
        {
            "category":"Building & Trades",
            "subcategory":"Electrical",
            "type":"Services"
        }
    ],
    "sg:phone":"+1 336 376 8862",
    "sg:postcode":"27253",
    "sg:province":"NC",
    "sg:tags":[
        "electrical",
        "electric",
        "contractor"
    ],
    "wof:name":"Affordable Residential Elec",
    "wof:placetype":"venue"
},
  "geometry": {"coordinates":[-79.34415,35.902485],"type":"Point"}
}