{
  "type": "Feature",
  "properties": {
    "addr:full":"512 Martin Luther King Jr Dr Greensboro NC 27406",
    "addr:housenumber":"512",
    "addr:postcode":"27406",
    "addr:street":"Martin Luther King Jr Dr",
    "iso:country":"US",
    "sg:address":"512 Martin Luther King Jr Dr",
    "sg:city":"Greensboro",
    "sg:classifiers":[
        {
            "category":"Retail",
            "subcategory":"Funeral Services",
            "type":"Services"
        }
    ],
    "sg:phone":"+1   ",
    "sg:postcode":"27406",
    "sg:province":"NC",
    "sg:tags":[
        "home"
    ],
    "wof:name":"Smith-Hinnant Funeral Services",
    "wof:placetype":"venue"
},
  "geometry": {"coordinates":[-79.785753,36.062523],"type":"Point"}
}