{
  "type": "Feature",
  "properties": {
    "iso:country":"US",
    "sg:address":"804 Lewis St",
    "sg:city":"Oxford",
    "sg:classifiers":[
        {
            "category":"Travel",
            "subcategory":"Hotels & Motels",
            "type":"Entertainment"
        }
    ],
    "sg:phone":"+1   ",
    "sg:postcode":"27565",
    "sg:province":"NC",
    "sg:tags":[
        "operation"
    ],
    "wof:name":"Crown Motel",
    "wof:placetype":"venue"
},
  "geometry": {"coordinates":[-78.60401400000001,36.291646],"type":"Point"}
}