{
  "type": "Feature",
  "properties": {
    "iso:country":"US",
    "sg:address":"4456 Legion Rd",
    "sg:city":"Hope Mills",
    "sg:classifiers":[
        {
            "category":"Organizations",
            "subcategory":"Religious Organization",
            "type":"Services"
        }
    ],
    "sg:phone":"+1 910 425 5305",
    "sg:postcode":"28348",
    "sg:province":"NC",
    "wof:name":"Highland Bptst Chrch Hope Mlls",
    "wof:placetype":"venue"
},
  "geometry": {"coordinates":[-78.935637,34.979678],"type":"Point"}
}