{
  "type": "Feature",
  "properties": {
    "iso:country":"US",
    "sg:address":"460 Troxler Rd",
    "sg:city":"Rockwell",
    "sg:classifiers":[
        {
            "category":"Retail",
            "subcategory":"Auto Repair",
            "type":"Services"
        }
    ],
    "sg:phone":"+1 704 633 8982",
    "sg:postcode":"28146",
    "sg:province":"NC",
    "sg:tags":[
        "engine",
        "el",
        "mfg",
        "automotive",
        "parts",
        "motor",
        "vehicle"
    ],
    "wof:name":"Salisbury Auto Truck Electric",
    "wof:placetype":"venue"
},
  "geometry": {"coordinates":[-80.383309,35.565066],"type":"Point"}
}