{
  "type": "Feature",
  "properties": {
    "addr:full":"412 W 5th St Washington NC 27889",
    "addr:housenumber":"412",
    "addr:postcode":"27889",
    "addr:street":"W 5Th St",
    "iso:country":"US",
    "sg:address":"412 W 5th St",
    "sg:city":"Washington",
    "sg:classifiers":[
        {
            "category":"Autos & Motor Vehicles",
            "subcategory":"Automobile Sales",
            "type":"Retail Goods"
        }
    ],
    "sg:phone":"+1 252 946 3126",
    "sg:postcode":"27889",
    "sg:province":"NC",
    "sg:tags":[
        "car",
        "dealer"
    ],
    "wof:name":"Moore Motor Co GMC Chrysler",
    "wof:placetype":"venue"
},
  "geometry": {"coordinates":[-77.05761200000001,35.549327],"type":"Point"}
}