{
  "type": "Feature",
  "properties": {
    "iso:country":"US",
    "sg:address":"610 Burton St",
    "sg:city":"Madison",
    "sg:classifiers":[
        {
            "category":"Shopping",
            "subcategory":"Department Store",
            "type":"Retail Goods"
        }
    ],
    "sg:phone":"+1 336 427 4605",
    "sg:postcode":"27025",
    "sg:province":"NC",
    "sg:tags":[
        "variety"
    ],
    "sg:website":"http://www.familydollar.com",
    "wof:name":"Family Dollar Stores",
    "wof:placetype":"venue"
},
  "geometry": {"coordinates":[-79.970659,36.401794],"type":"Point"}
}