{
  "type": "Feature",
  "properties": {
    "iso:country":"US",
    "sg:address":"352 S College Rd",
    "sg:city":"Wilmington",
    "sg:classifiers":[
        {
            "category":"Shopping",
            "subcategory":"Crafts & Fabrics",
            "type":"Retail Goods"
        }
    ],
    "sg:phone":"+1 910 799 9377",
    "sg:postcode":"28403",
    "sg:province":"NC",
    "sg:tags":[
        "shop"
    ],
    "wof:name":"Jo-Ann Fabrics & Crafts",
    "wof:placetype":"venue"
},
  "geometry": {"coordinates":[-77.873362,34.235896],"type":"Point"}
}