{
  "type": "Feature",
  "properties": {
    "addr:full":"275 Waynick Blvd Wrightsville Beach NC 28480",
    "addr:housenumber":"275",
    "addr:postcode":"28480",
    "addr:street":"Waynick Blvd",
    "iso:country":"US",
    "sg:address":"275 Waynick Blvd",
    "sg:city":"Wrightsville Beach",
    "sg:classifiers":[
        {
            "category":"Organizations",
            "subcategory":"Professional Association",
            "type":"Services"
        }
    ],
    "sg:phone":"+1   ",
    "sg:postcode":"28480",
    "sg:province":"NC",
    "sg:tags":[
        "business"
    ],
    "wof:name":"Wjb Inc",
    "wof:placetype":"venue"
},
  "geometry": {"coordinates":[-77.800049,34.202665],"type":"Point"}
}