{
  "type": "Feature",
  "properties": {
    "iso:country":"US",
    "sg:address":"604 S Hamilton St",
    "sg:city":"Eden",
    "sg:classifiers":[
        {
            "category":"Insurance",
            "subcategory":"Insurance Agent",
            "type":"Services"
        }
    ],
    "sg:phone":"+1 336 627 9996",
    "sg:postcode":"27288",
    "sg:province":"NC",
    "wof:name":"Primerica Financial Svc",
    "wof:placetype":"venue"
},
  "geometry": {"coordinates":[-79.76837999999999,36.490319],"type":"Point"}
}