{
  "type": "Feature",
  "properties": {
    "iso:country":"US",
    "sg:address":"67 2nd St",
    "sg:city":"Tar Heel",
    "sg:classifiers":[
        {
            "category":"Personal",
            "subcategory":"Beauty Salon",
            "type":"Services"
        }
    ],
    "sg:phone":"+1 910 862 2708",
    "sg:postcode":"28332",
    "sg:province":"NC",
    "wof:name":"Jean's Hairstyling",
    "wof:placetype":"venue"
},
  "geometry": {"coordinates":[-78.727666,34.658238],"type":"Point"}
}