{
  "type": "Feature",
  "properties": {
    "addr:full":"163 Sloan Rd Franklin NC 28734",
    "addr:housenumber":"163",
    "addr:postcode":"nc 28734",
    "addr:street":"Sloan Rd",
    "iso:country":"US",
    "sg:address":"163 Sloan Rd",
    "sg:city":"Franklin",
    "sg:classifiers":[
        {
            "category":"Health Services",
            "subcategory":"Chiropractor",
            "type":"Services"
        }
    ],
    "sg:phone":"+1   ",
    "sg:postcode":"28734",
    "sg:province":"NC",
    "wof:name":"Rosalyn Miller MD",
    "wof:placetype":"venue"
},
  "geometry": {"coordinates":[-83.407661,35.167635],"type":"Point"}
}