{
  "type": "Feature",
  "properties": {
    "iso:country":"US",
    "sg:address":"802 Parker St",
    "sg:city":"Durham",
    "sg:classifiers":[
        {
            "category":"Professional",
            "subcategory":"Business Services",
            "type":"Services"
        }
    ],
    "sg:phone":"+1 919 680 2464",
    "sg:postcode":"27701",
    "sg:province":"NC",
    "sg:tags":[
        "recording",
        "studio"
    ],
    "wof:name":"Sound Scripture Studios",
    "wof:placetype":"venue"
},
  "geometry": {"coordinates":[-78.914286,35.993],"type":"Point"}
}