{
  "type": "Feature",
  "properties": {
    "iso:country":"US",
    "sg:address":"6860 Kelly Coltrane Dr",
    "sg:city":"Randleman",
    "sg:classifiers":[
        {
            "category":"Manufacturing",
            "subcategory":"Toys & Sporting Goods",
            "type":"Manufacturing & Wholesale Goods"
        }
    ],
    "sg:phone":"+1 336 674 6869",
    "sg:postcode":"27317",
    "sg:province":"NC",
    "sg:tags":[
        "mfg"
    ],
    "wof:name":"Hammer Racing Concepts",
    "wof:placetype":"venue"
},
  "geometry": {"coordinates":[-79.805662,35.902821],"type":"Point"}
}