{
  "type": "Feature",
  "properties": {
    "addr:full":"122 Landmark Aly Statesville NC 28677",
    "addr:housenumber":"122",
    "addr:postcode":"28677",
    "addr:street":"Landmark Aly",
    "iso:country":"US",
    "sg:address":"122 Landmark Aly",
    "sg:city":"Statesville",
    "sg:classifiers":[
        {
            "category":"Restaurant",
            "type":"Food & Drink"
        }
    ],
    "sg:phone":"+1 704 924 7000",
    "sg:postcode":"28677",
    "sg:province":"NC",
    "sg:tags":[
        "eating"
    ],
    "wof:name":"Pizza Factory",
    "wof:placetype":"venue"
},
  "geometry": {"coordinates":[-80.889619,35.785346],"type":"Point"}
}