{
  "type": "Feature",
  "properties": {
    "iso:country":"US",
    "sg:address":"19 Meadows Ln",
    "sg:city":"Arden",
    "sg:classifiers":[
        {
            "category":"Real Estate",
            "subcategory":"Real Estate Agent",
            "type":"Services"
        }
    ],
    "sg:phone":"+1 828 654 0510",
    "sg:postcode":"28751",
    "sg:province":"NC",
    "wof:name":"Commercial Management LLC",
    "wof:placetype":"venue"
},
  "geometry": {"coordinates":[-83.083472,35.518419],"type":"Point"}
}