{
  "type": "Feature",
  "properties": {
    "addr:full":"1200C The Plz Charlotte NC 28205",
    "addr:housenumber":"1200c",
    "addr:postcode":"28205",
    "addr:street":"The Plz",
    "iso:country":"US",
    "sg:address":"1200C The Plz",
    "sg:city":"Charlotte",
    "sg:classifiers":[
        {
            "category":"Insurance",
            "subcategory":"Insurance Agent",
            "type":"Services"
        },
        {
            "category":"Insurance",
            "subcategory":"Hazard Insurance",
            "type":"Services"
        }
    ],
    "sg:phone":"+1 704 377 5802",
    "sg:postcode":"28205",
    "sg:province":"NC",
    "sg:tags":[
        "auto"
    ],
    "wof:name":"Associates Insurance Group",
    "wof:placetype":"venue"
},
  "geometry": {"coordinates":[-80.811066,35.218361],"type":"Point"}
}