{
  "type": "Feature",
  "properties": {
    "addr:full":"110 W Main St Biscoe NC 27209",
    "addr:housenumber":"110",
    "addr:postcode":"27209",
    "addr:street":"W Main St",
    "iso:country":"US",
    "sg:address":"110 W Main St",
    "sg:city":"Biscoe",
    "sg:classifiers":[
        {
            "category":"Government",
            "subcategory":"Fire Station",
            "type":"Public Place"
        }
    ],
    "sg:phone":"+1 910 428 4541",
    "sg:postcode":"27209",
    "sg:province":"NC",
    "sg:tags":[
        "department"
    ],
    "wof:name":"Biscoe Volunteer Fire Dept",
    "wof:placetype":"venue"
},
  "geometry": {"coordinates":[-79.78049,35.359852],"type":"Point"}
}