{
  "type": "Feature",
  "properties": {
    "iso:country":"US",
    "sg:address":"7922 Rea Rd",
    "sg:city":"Charlotte",
    "sg:classifiers":[
        {
            "category":"Education",
            "subcategory":"School",
            "type":"Public Place"
        }
    ],
    "sg:phone":"+1 704 542 9496",
    "sg:postcode":"28277",
    "sg:province":"NC",
    "sg:tags":[
        "academic",
        "special"
    ],
    "wof:name":"Fastrackids Academy",
    "wof:placetype":"venue"
},
  "geometry": {"coordinates":[-80.812517,35.05865],"type":"Point"}
}