{
  "type": "Feature",
  "properties": {
    "addr:full":"1003 Hay St Fayetteville NC 28305",
    "addr:housenumber":"1003",
    "addr:postcode":"28305",
    "addr:street":"Hay St",
    "iso:country":"US",
    "sg:address":"1003 Hay St",
    "sg:city":"Fayetteville",
    "sg:classifiers":[
        {
            "category":"Real Estate",
            "subcategory":"Architect",
            "type":"Services"
        }
    ],
    "sg:phone":"+1   ",
    "sg:postcode":"28305",
    "sg:province":"NC",
    "sg:tags":[
        "architectural"
    ],
    "wof:name":"Gordon Johnson Architect",
    "wof:placetype":"venue"
},
  "geometry": {"coordinates":[-78.896513,35.056135],"type":"Point"}
}