{
  "type": "Feature",
  "properties": {
    "addr:full":"3102 Martin Luther King Jr Dr Lumberton NC 28358",
    "addr:housenumber":"3102",
    "addr:postcode":"28358",
    "addr:street":"Martin Luther King Jr Dr",
    "iso:country":"US",
    "sg:address":"3102 Martin Luther King Jr Dr",
    "sg:city":"Lumberton",
    "sg:classifiers":[
        {
            "category":"Food & Beverages",
            "subcategory":"Groceries & Convenience Stores",
            "type":"Retail Goods"
        }
    ],
    "sg:phone":"+1 910 739 2406",
    "sg:postcode":"28358",
    "sg:province":"NC",
    "wof:name":"Starlite Food Mart",
    "wof:placetype":"venue"
},
  "geometry": {"coordinates":[-79.034796,34.598893],"type":"Point"}
}