{
  "type": "Feature",
  "properties": {
    "iso:country":"US",
    "sg:address":"100 N Depot St",
    "sg:city":"Cleveland",
    "sg:classifiers":[
        {
            "category":"Government",
            "subcategory":"Police Station",
            "type":"Public Place"
        }
    ],
    "sg:phone":"+1 704 278 1900",
    "sg:postcode":"27013",
    "sg:province":"NC",
    "sg:tags":[
        "department"
    ],
    "wof:name":"Cleveland Police Dept",
    "wof:placetype":"venue"
},
  "geometry": {"coordinates":[-80.676872,35.733716],"type":"Point"}
}