{
  "type": "Feature",
  "properties": {
    "addr:full":"1202 Alamance Church Rd Greensboro NC 27406",
    "addr:housenumber":"1202",
    "addr:postcode":"27406",
    "addr:street":"Alamance Church Rd",
    "iso:country":"US",
    "sg:address":"1202 Alamance Church Rd",
    "sg:city":"Greensboro",
    "sg:classifiers":[
        {
            "category":"Professional",
            "subcategory":"Business Services",
            "type":"Services"
        }
    ],
    "sg:phone":"+1 336 272 2869",
    "sg:postcode":"27406",
    "sg:province":"NC",
    "wof:name":"Ken Free Scholarship Fund",
    "wof:placetype":"venue"
},
  "geometry": {"coordinates":[-79.76351,36.036827],"type":"Point"}
}