{
  "type": "Feature",
  "properties": {
    "addr:full":"4741 Lake Wilson Rd Elm City NC 27822",
    "addr:housenumber":"4741",
    "addr:postcode":"27822",
    "addr:street":"Lake Wilson Rd",
    "iso:country":"US",
    "sg:address":"4741 Lake Wilson Rd",
    "sg:city":"Elm City",
    "sg:classifiers":[
        {
            "category":"Retail",
            "subcategory":"Animal Services",
            "type":"Services"
        }
    ],
    "sg:phone":"+1 252 291 7562",
    "sg:postcode":"27822",
    "sg:province":"NC",
    "sg:tags":[
        "pet",
        "grooming",
        "washing"
    ],
    "wof:name":"Dog Grooming Center",
    "wof:placetype":"venue"
},
  "geometry": {"coordinates":[-77.91489799999999,35.790294],"type":"Point"}
}