{
  "type": "Feature",
  "properties": {
    "iso:country":"US",
    "sg:address":"2009 Quail Ridge Rd",
    "sg:city":"Raleigh",
    "sg:classifiers":[
        {
            "category":"Building & Trades",
            "subcategory":"Cleaning & Sanitation",
            "type":"Services"
        }
    ],
    "sg:phone":"+1 919 790 8688",
    "sg:postcode":"27609",
    "sg:province":"NC",
    "sg:tags":[
        "janitor"
    ],
    "wof:name":"All Clean Building Maintenance",
    "wof:placetype":"venue"
},
  "geometry": {"coordinates":[-78.605603,35.861303],"type":"Point"}
}