{
  "type": "Feature",
  "properties": {
    "iso:country":"US",
    "sg:address":"265 Harper St",
    "sg:city":"Winston Salem",
    "sg:classifiers":[
        {
            "category":"Recreation",
            "type":"Entertainment"
        }
    ],
    "sg:phone":"+1   ",
    "sg:postcode":"27104",
    "sg:province":"NC",
    "sg:tags":[
        "club",
        "membership",
        "tennis",
        "swimming"
    ],
    "wof:name":"Westwood Club Inc",
    "wof:placetype":"venue"
},
  "geometry": {"coordinates":[-80.30949099999999,36.086501],"type":"Point"}
}