{
  "type": "Feature",
  "properties": {
    "addr:full":"328 Parktown Rd Warrenton NC 27589",
    "addr:housenumber":"328",
    "addr:postcode":"27589",
    "addr:street":"Parktown Rd",
    "iso:country":"US",
    "sg:address":"328 Parktown Rd",
    "sg:city":"Warrenton",
    "sg:classifiers":[
        {
            "category":"Home & Garden",
            "subcategory":"Building Materials",
            "type":"Retail Goods"
        }
    ],
    "sg:phone":"+1 252 257 5533",
    "sg:postcode":"27589",
    "sg:province":"NC",
    "wof:name":"Smallwoods Clay Sculpture",
    "wof:placetype":"venue"
},
  "geometry": {"coordinates":[-78.202319,36.328437],"type":"Point"}
}