{
  "type": "Feature",
  "properties": {
    "iso:country":"US",
    "sg:address":"1323 Capital Blvd",
    "sg:city":"Raleigh",
    "sg:classifiers":[
        {
            "category":"Organizations",
            "subcategory":"Professional Association",
            "type":"Services"
        }
    ],
    "sg:phone":"+1 919 832 8326",
    "sg:postcode":"27603",
    "sg:province":"NC",
    "wof:name":"American Lung Assn",
    "wof:placetype":"venue"
},
  "geometry": {"coordinates":[-78.637663,35.7989],"type":"Point"}
}