{
  "type": "Feature",
  "properties": {
    "addr:full":"4603 Malor Dr Wake Forest NC 27587",
    "addr:housenumber":"4603",
    "addr:postcode":"27587",
    "addr:street":"Malor Dr",
    "iso:country":"US",
    "sg:address":"4603 Malor Dr",
    "sg:city":"Wake Forest",
    "sg:classifiers":[
        {
            "category":"Communications",
            "type":"Services"
        }
    ],
    "sg:phone":"+1 919 771 4078",
    "sg:postcode":"27587",
    "sg:province":"NC",
    "wof:name":"Prism Communications",
    "wof:placetype":"venue"
},
  "geometry": {"coordinates":[-78.482096,35.894173],"type":"Point"}
}