{
  "type": "Feature",
  "properties": {
    "iso:country":"US",
    "sg:address":"10703 Park Rd",
    "sg:city":"Charlotte",
    "sg:classifiers":[
        {
            "category":"Sports & Exercise",
            "subcategory":"Gym",
            "type":"Entertainment"
        },
        {
            "category":"Health Services",
            "subcategory":"Health Practitioner",
            "type":"Services"
        }
    ],
    "sg:phone":"+1 704 541 3636",
    "sg:postcode":"28210",
    "sg:province":"NC",
    "sg:tags":[
        "nutritionist",
        "personal",
        "gymnasium",
        "trainer",
        "fitness"
    ],
    "wof:name":"Heat Pro Fitness",
    "wof:placetype":"venue"
},
  "geometry": {"coordinates":[-80.869806,35.090817],"type":"Point"}
}