{
  "type": "Feature",
  "properties": {
    "addr:full":"2336 Mount Vernon Church Rd Raleigh NC 27614",
    "addr:housenumber":"2336",
    "addr:postcode":"27614",
    "addr:street":"Mount Vernon Church Rd",
    "iso:country":"US",
    "sg:address":"2336 Mount Vernon Church Rd",
    "sg:city":"Raleigh",
    "sg:classifiers":[
        {
            "category":"Wholesale",
            "subcategory":"Non-durable Goods",
            "type":"Manufacturing & Wholesale Goods"
        }
    ],
    "sg:phone":"+1 919 676 6175",
    "sg:postcode":"27614",
    "sg:province":"NC",
    "wof:name":"Wilder Designs",
    "wof:placetype":"venue"
},
  "geometry": {"coordinates":[-78.68061400000001,35.963928],"type":"Point"}
}