{
  "type": "Feature",
  "properties": {
    "addr:full":"115 Woodpecker Rd Statesville NC 28625",
    "addr:housenumber":"115",
    "addr:postcode":"28625",
    "addr:street":"Woodpecker Rd",
    "iso:country":"US",
    "sg:address":"115 Woodpecker Rd",
    "sg:city":"Statesville",
    "sg:classifiers":[
        {
            "category":"Arena",
            "subcategory":"Sports Club",
            "type":"Entertainment"
        }
    ],
    "sg:phone":"+1   ",
    "sg:postcode":"28625",
    "sg:province":"NC",
    "wof:name":"Tomlin Mill Pullers L L C",
    "wof:placetype":"venue"
},
  "geometry": {"coordinates":[-80.861048,35.922185],"type":"Point"}
}