{
  "type": "Feature",
  "properties": {
    "iso:country":"US",
    "sg:address":"9124 S Tryon St",
    "sg:city":"Charlotte",
    "sg:classifiers":[
        {
            "category":"Personal",
            "subcategory":"Beauty Salon",
            "type":"Services"
        }
    ],
    "sg:phone":"+1 704 583 2511",
    "sg:postcode":"28273",
    "sg:province":"NC",
    "wof:name":"L A Forman",
    "wof:placetype":"venue"
},
  "geometry": {"coordinates":[-80.940555,35.132536],"type":"Point"}
}