{
  "type": "Feature",
  "properties": {
    "addr:full":"1302 Castle St Wilmington NC 28401",
    "addr:housenumber":"1302",
    "addr:postcode":"28401",
    "addr:street":"Castle St",
    "iso:country":"US",
    "sg:address":"1302 Castle St",
    "sg:city":"Wilmington",
    "sg:classifiers":[
        {
            "category":"Home & Garden",
            "subcategory":"Building Materials",
            "type":"Retail Goods"
        }
    ],
    "sg:phone":"+1 910 763 7488",
    "sg:postcode":"28401",
    "sg:province":"NC",
    "sg:tags":[
        "paint"
    ],
    "wof:name":"Stevens Paint Ctr",
    "wof:placetype":"venue"
},
  "geometry": {"coordinates":[-77.930639,34.229111],"type":"Point"}
}