{
  "type": "Feature",
  "properties": {
    "iso:country":"US",
    "sg:address":"1918 Rosebud Rd",
    "sg:city":"Walnut Cove",
    "sg:classifiers":[
        {
            "category":"Organizations",
            "subcategory":"Religious Organization",
            "type":"Services"
        }
    ],
    "sg:phone":"+1 336 591 3182",
    "sg:postcode":"27052",
    "sg:province":"NC",
    "sg:tags":[
        "church"
    ],
    "sg:website":"www.rosebudchristianchurch.org",
    "wof:name":"Rosebud Christian Church",
    "wof:placetype":"venue"
},
  "geometry": {"coordinates":[-80.18203699999999,36.308184],"type":"Point"}
}