{
  "type": "Feature",
  "properties": {
    "addr:full":"1101 E Williams St Apex NC 27502",
    "addr:housenumber":"1101",
    "addr:postcode":"27502",
    "addr:street":"E Williams St",
    "iso:country":"US",
    "sg:address":"1101 E Williams St",
    "sg:city":"Apex",
    "sg:classifiers":[
        {
            "category":"Restaurant",
            "type":"Food & Drink"
        }
    ],
    "sg:phone":"+1 919 362 0051",
    "sg:postcode":"27502",
    "sg:province":"NC",
    "sg:tags":[
        "southern"
    ],
    "sg:website":"www.dallasfamouschicken.com/",
    "wof:name":"Dallas Famous Chicken",
    "wof:placetype":"venue"
},
  "geometry": {"coordinates":[-78.84323999999999,35.720495],"type":"Point"}
}