{
  "type": "Feature",
  "properties": {
    "iso:country":"US",
    "sg:address":"5206 NW School Rd",
    "sg:city":"Greensboro",
    "sg:classifiers":[
        {
            "category":"Banks & Credit Unions",
            "subcategory":"Investment Brokerage",
            "type":"Services"
        },
        {
            "category":"Banks & Credit Unions",
            "subcategory":"Financial Services",
            "type":"Services"
        }
    ],
    "sg:phone":"+1 336 668 9004",
    "sg:postcode":"27409",
    "sg:province":"NC",
    "sg:tags":[
        "trust",
        "real estate"
    ],
    "wof:name":"Williamson Investments LLC",
    "wof:placetype":"venue"
},
  "geometry": {"coordinates":[-79.954689,36.149355],"type":"Point"}
}