{
  "type": "Feature",
  "properties": {
    "iso:country":"US",
    "sg:address":"2820 Lawndale Dr",
    "sg:city":"Greensboro",
    "sg:classifiers":[
        {
            "category":"Food & Beverages",
            "subcategory":"Groceries & Convenience Stores",
            "type":"Retail Goods"
        }
    ],
    "sg:phone":"+1 336 288 8116",
    "sg:postcode":"27408",
    "sg:province":"NC",
    "wof:name":"C&C Market",
    "wof:placetype":"venue"
},
  "geometry": {"coordinates":[-79.81905999999999,36.105962],"type":"Point"}
}