{
  "type": "Feature",
  "properties": {
    "addr:full":"3921 Blakeney Rd Monroe NC 28112",
    "addr:housenumber":"3921",
    "addr:postcode":"28112",
    "addr:street":"Blakeney Rd",
    "iso:country":"US",
    "sg:address":"3921 Blakeney Rd",
    "sg:city":"Monroe",
    "sg:classifiers":[
        {
            "category":"Organizations",
            "subcategory":"Religious Organization",
            "type":"Services"
        }
    ],
    "sg:phone":"+1 704 624 5989",
    "sg:postcode":"28112",
    "sg:province":"NC",
    "sg:tags":[
        "clergy"
    ],
    "wof:name":"Lonnie Blakeney",
    "wof:placetype":"venue"
},
  "geometry": {"coordinates":[-80.403896,34.863439],"type":"Point"}
}