{
  "type": "Feature",
  "properties": {
    "addr:full":"2136 Coddle Creek Hwy Mooresville NC 28115",
    "addr:housenumber":"2136",
    "addr:postcode":"28115",
    "addr:street":"Coddle Creek Hwy",
    "iso:country":"US",
    "sg:address":"2136 Coddle Creek Hwy",
    "sg:city":"Mooresville",
    "sg:classifiers":[
        {
            "category":"Manufacturing",
            "subcategory":"Tools & Machinery",
            "type":"Manufacturing & Wholesale Goods"
        }
    ],
    "sg:phone":"+1 704 660 5170",
    "sg:postcode":"28115",
    "sg:province":"NC",
    "sg:tags":[
        "body",
        "industrial",
        "m",
        "motor",
        "mfg"
    ],
    "wof:name":"Smith Fabrication Inc",
    "wof:placetype":"venue"
},
  "geometry": {"coordinates":[-80.769164,35.535893],"type":"Point"}
}