{
  "type": "Feature",
  "properties": {
    "addr:full":"4207 Long Run Farm Rd Mount Pleasant NC 28124",
    "addr:housenumber":"4207",
    "addr:postcode":"28124",
    "addr:street":"Long Run Farm Rd",
    "iso:country":"US",
    "sg:address":"4207 Long Run Farm Rd",
    "sg:city":"Mount Pleasant",
    "sg:classifiers":[
        {
            "category":"Utilities",
            "subcategory":"Fuel Oil & Lpg",
            "type":"Services"
        }
    ],
    "sg:phone":"+1 704 436 6792",
    "sg:postcode":"28124",
    "sg:province":"NC",
    "sg:tags":[
        "dealer"
    ],
    "wof:name":"Barrier Brothers",
    "wof:placetype":"venue"
},
  "geometry": {"coordinates":[-80.420418,35.360485],"type":"Point"}
}