{
  "type": "Feature",
  "properties": {
    "addr:full":"2 Davis Drive Research Triangle Park NC 27709",
    "addr:housenumber":"2",
    "addr:postcode":"27709",
    "addr:street":"Davis Drive",
    "iso:country":"US",
    "sg:address":"2 Davis Drive",
    "sg:city":"Research Triangle Park",
    "sg:classifiers":[
        {
            "category":"Professional",
            "subcategory":"Computer Services",
            "type":"Services"
        }
    ],
    "sg:postcode":"27709",
    "sg:province":"NC",
    "sg:website":"http://www.brandport.com/",
    "wof:name":"BrandPort",
    "wof:placetype":"venue"
},
  "geometry": {"coordinates":[-78.940862,36.006139],"type":"Point"}
}