{
  "type": "Feature",
  "properties": {
    "iso:country":"US",
    "sg:address":"2410 Crescent Ln",
    "sg:city":"Gastonia",
    "sg:classifiers":[
        {
            "category":"Organizations",
            "subcategory":"Religious Organization",
            "type":"Services"
        }
    ],
    "sg:phone":"+1 704 867 8895",
    "sg:postcode":"28052",
    "sg:province":"NC",
    "sg:tags":[
        "church"
    ],
    "wof:name":"Westside Hope Church Of God",
    "wof:placetype":"venue"
},
  "geometry": {"coordinates":[-81.225526,35.267396],"type":"Point"}
}