{
  "type": "Feature",
  "properties": {
    "addr:full":"331 Sanford Dr Morganton NC 28655",
    "addr:housenumber":"331",
    "addr:postcode":"28655",
    "addr:street":"Sanford Dr",
    "iso:country":"US",
    "sg:address":"331 Sanford Dr",
    "sg:city":"Morganton",
    "sg:classifiers":[
        {
            "category":"Insurance",
            "subcategory":"Insurance Agent",
            "type":"Services"
        }
    ],
    "sg:phone":"+1 828 437 5034",
    "sg:postcode":"28655",
    "sg:province":"NC",
    "wof:name":"Fox & Assoc Insurance Svc",
    "wof:placetype":"venue"
},
  "geometry": {"coordinates":[-81.704267,35.747662],"type":"Point"}
}