{
  "type": "Feature",
  "properties": {
    "iso:country":"US",
    "sg:address":"191 Johnson Dairy Rd",
    "sg:city":"Mooresville",
    "sg:classifiers":[
        {
            "category":"Building & Trades",
            "subcategory":"Electrical",
            "type":"Services"
        }
    ],
    "sg:phone":"+1 704 663 1209",
    "sg:postcode":"28115",
    "sg:province":"NC",
    "sg:tags":[
        "electric",
        "contractor"
    ],
    "wof:name":"Chuck Douthit Electrical",
    "wof:placetype":"venue"
},
  "geometry": {"coordinates":[-80.77167300000001,35.519708],"type":"Point"}
}