{
  "type": "Feature",
  "properties": {
    "addr:full":"1968 Dobbersville Rd Mount Olive NC 28365",
    "addr:housenumber":"1968",
    "addr:postcode":"28365",
    "addr:street":"Dobbersville Rd",
    "iso:country":"US",
    "sg:address":"1968 Dobbersville Rd",
    "sg:city":"Mount Olive",
    "sg:classifiers":[
        {
            "category":"Wholesale",
            "subcategory":"Machinery & Supplies",
            "type":"Manufacturing & Wholesale Goods"
        }
    ],
    "sg:phone":"+1 919 689 2885",
    "sg:postcode":"28365",
    "sg:province":"NC",
    "wof:name":"Lloyd Group NC Ltd",
    "wof:placetype":"venue"
},
  "geometry": {"coordinates":[-78.229934,35.265033],"type":"Point"}
}