{
  "type": "Feature",
  "properties": {
    "iso:country":"US",
    "sg:address":"8557 Hudson James Rd",
    "sg:city":"Summerfield",
    "sg:classifiers":[
        {
            "category":"Professional",
            "subcategory":"Business Services",
            "type":"Services"
        }
    ],
    "sg:phone":"+1   ",
    "sg:postcode":"27358",
    "sg:province":"NC",
    "wof:name":"Neas Enterprises",
    "wof:placetype":"venue"
},
  "geometry": {"coordinates":[-79.901763,36.244361],"type":"Point"}
}