{
  "type": "Feature",
  "properties": {
    "addr:full":"164 Mountain Valley Dr Glendale Springs NC 28685",
    "addr:housenumber":"164",
    "addr:postcode":"28685",
    "addr:street":"Mountain Valley Dr",
    "iso:country":"US",
    "sg:address":"164 Mountain Valley Dr",
    "sg:city":"Glendale Springs",
    "sg:classifiers":[
        {
            "category":"Travel",
            "subcategory":"Hotels & Motels",
            "type":"Entertainment"
        }
    ],
    "sg:phone":"+1 336 982 2233",
    "sg:postcode":"28685",
    "sg:province":"NC",
    "sg:tags":[
        "chalet",
        "rental",
        "cabin"
    ],
    "wof:name":"Mountain View Lodge & Cabins",
    "wof:placetype":"venue"
},
  "geometry": {"coordinates":[-80.98269000000001,36.356733],"type":"Point"}
}