{
  "type": "Feature",
  "properties": {
    "addr:full":"13180 Dorman Rd Pineville NC 28134",
    "addr:housenumber":"13180",
    "addr:postcode":"28134",
    "addr:street":"Dorman Rd",
    "iso:country":"US",
    "sg:address":"13180 Dorman Rd",
    "sg:city":"Pineville",
    "sg:classifiers":[
        {
            "category":"Social Services",
            "subcategory":"Retirement Home",
            "type":"Services"
        },
        {
            "category":"Social Services",
            "subcategory":"Adult Care",
            "type":"Services"
        }
    ],
    "sg:phone":"+1 704 540 8007",
    "sg:postcode":"28134",
    "sg:province":"NC",
    "sg:tags":[
        "living",
        "assisted",
        "elder",
        "facility"
    ],
    "wof:name":"The Laurels at Carolina Place",
    "wof:placetype":"venue"
},
  "geometry": {"coordinates":[-80.885057,35.066938],"type":"Point"}
}