{
  "type": "Feature",
  "properties": {
    "addr:full":"135 Moosehaven Rd Jacksonville NC 28546",
    "addr:housenumber":"135",
    "addr:postcode":"28546",
    "addr:street":"Moosehaven Rd",
    "iso:country":"US",
    "sg:address":"135 Moosehaven Rd",
    "sg:city":"Jacksonville",
    "sg:classifiers":[
        {
            "category":"Organizations",
            "subcategory":"Community Association",
            "type":"Services"
        }
    ],
    "sg:phone":"+1 910 346 4550",
    "sg:postcode":"28546",
    "sg:province":"NC",
    "sg:tags":[
        "fraternal"
    ],
    "wof:name":"Loyal Order Of Moose",
    "wof:placetype":"venue"
},
  "geometry": {"coordinates":[-77.393908,34.776371],"type":"Point"}
}