{
  "type": "Feature",
  "properties": {
    "iso:country":"US",
    "sg:address":"4145 Holly Hill Ln",
    "sg:city":"Winston Salem",
    "sg:classifiers":[
        {
            "category":"Retail",
            "subcategory":"Car Wash",
            "type":"Services"
        }
    ],
    "sg:phone":"+1   ",
    "sg:postcode":"27106",
    "sg:province":"NC",
    "sg:tags":[
        "carwash"
    ],
    "wof:name":"Absolute Mobile",
    "wof:placetype":"venue"
},
  "geometry": {"coordinates":[-80.344667,36.137641],"type":"Point"}
}