{
  "type": "Feature",
  "properties": {
    "addr:full":"1501 Independence Rd Greensboro NC 27408",
    "addr:housenumber":"1501",
    "addr:postcode":"27408",
    "addr:street":"Independence Rd",
    "iso:country":"US",
    "sg:address":"1501 Independence Rd",
    "sg:city":"Greensboro",
    "sg:classifiers":[
        {
            "category":"Professional",
            "subcategory":"Computer Services",
            "type":"Services"
        }
    ],
    "sg:phone":"+1   ",
    "sg:postcode":"27408",
    "sg:province":"NC",
    "sg:tags":[
        "related"
    ],
    "wof:name":"Friends of Nexus The",
    "wof:placetype":"venue"
},
  "geometry": {"coordinates":[-79.808655,36.104748],"type":"Point"}
}