{
  "type": "Feature",
  "properties": {
    "addr:full":"301 Bradford Dr Charlotte NC 28208",
    "addr:housenumber":"301",
    "addr:postcode":"28208",
    "addr:street":"Bradford Dr",
    "iso:country":"US",
    "sg:address":"301 Bradford Dr",
    "sg:city":"Charlotte",
    "sg:classifiers":[
        {
            "category":"Building & Trades",
            "subcategory":"Pest Control",
            "type":"Services"
        }
    ],
    "sg:phone":"+1 704 391 1191",
    "sg:postcode":"28208",
    "sg:province":"NC",
    "wof:name":"A A Wildlife Damage Control",
    "wof:placetype":"venue"
},
  "geometry": {"coordinates":[-80.897471,35.258742],"type":"Point"}
}