{
  "type": "Feature",
  "properties": {
    "addr:full":"7200 Albemarle Rd Charlotte NC 28227",
    "addr:housenumber":"7200",
    "addr:postcode":"28227",
    "addr:street":"Albemarle Rd",
    "iso:country":"US",
    "sg:address":"7200 Albemarle Rd",
    "sg:city":"Charlotte",
    "sg:classifiers":[
        {
            "category":"Food & Beverages",
            "subcategory":"Groceries & Convenience Stores",
            "type":"Retail Goods"
        },
        {
            "category":"Food & Beverages",
            "subcategory":"Specialty",
            "type":"Retail Goods"
        }
    ],
    "sg:phone":"+1 704 567 5916",
    "sg:postcode":"28227",
    "sg:province":"NC",
    "sg:tags":[
        "grocer"
    ],
    "wof:name":"Sunuvkriti Indian Store",
    "wof:placetype":"venue"
},
  "geometry": {"coordinates":[-80.71925400000001,35.204691],"type":"Point"}
}