{
  "type": "Feature",
  "properties": {
    "iso:country":"US",
    "sg:address":"5418 Chapel Hill Rd",
    "sg:city":"Raleigh",
    "sg:classifiers":[
        {
            "category":"Education",
            "subcategory":"School",
            "type":"Public Place"
        }
    ],
    "sg:phone":"+1 919 233 4313",
    "sg:postcode":"27607",
    "sg:province":"NC",
    "sg:tags":[
        "middle"
    ],
    "wof:name":"Mount Vernon Redirection Schl",
    "wof:placetype":"venue"
},
  "geometry": {"coordinates":[-78.71710899999999,35.79031],"type":"Point"}
}