{
  "type": "Feature",
  "properties": {
    "iso:country":"US",
    "sg:address":"640 Powell Page Rd",
    "sg:city":"Wallace",
    "sg:classifiers":[
        {
            "category":"Building & Trades",
            "subcategory":"Construction",
            "type":"Services"
        }
    ],
    "sg:phone":"+1 910 532 4147",
    "sg:postcode":"28466",
    "sg:province":"NC",
    "sg:tags":[
        "house"
    ],
    "wof:name":"Page Builders",
    "wof:placetype":"venue"
},
  "geometry": {"coordinates":[-78.166276,34.760951],"type":"Point"}
}