{
  "type": "Feature",
  "properties": {
    "addr:full":"1528 Stony Point Rd Shelby NC 28150",
    "addr:housenumber":"1528",
    "addr:postcode":"28150",
    "addr:street":"Stony Point Rd",
    "iso:country":"US",
    "sg:address":"1528 Stony Point Rd",
    "sg:city":"Shelby",
    "sg:classifiers":[
        {
            "category":"Restaurant",
            "type":"Food & Drink"
        }
    ],
    "sg:phone":"+1 704 471 2800",
    "sg:postcode":"28150",
    "sg:province":"NC",
    "wof:name":"Southern Charm Family Rstrnt",
    "wof:placetype":"venue"
},
  "geometry": {"coordinates":[-81.430933,35.307231],"type":"Point"}
}