{
  "type": "Feature",
  "properties": {
    "addr:full":"1911 Evans Rd Cary NC 27513",
    "addr:housenumber":"1911",
    "addr:postcode":"27513",
    "addr:street":"Evans Rd",
    "iso:country":"US",
    "sg:address":"1911 Evans Rd",
    "sg:city":"Cary",
    "sg:classifiers":[
        {
            "category":"Professional",
            "subcategory":"Management & Consulting",
            "type":"Services"
        }
    ],
    "sg:phone":"+1 919 481 2701",
    "sg:postcode":"27513",
    "sg:province":"NC",
    "sg:tags":[
        "consultant",
        "publishing"
    ],
    "wof:name":"Scriptorium Publishing Svc",
    "wof:placetype":"venue"
},
  "geometry": {"coordinates":[-78.802984,35.818999],"type":"Point"}
}