{
  "type": "Feature",
  "properties": {
    "iso:country":"US",
    "sg:address":"2121 Commonwealth Ave",
    "sg:city":"Charlotte",
    "sg:classifiers":[
        {
            "category":"Social Services",
            "type":"Services"
        }
    ],
    "sg:phone":"+1 704 358 3999",
    "sg:postcode":"28205",
    "sg:province":"NC",
    "sg:tags":[
        "worker"
    ],
    "wof:name":"Mc Cray V Benson",
    "wof:placetype":"venue"
},
  "geometry": {"coordinates":[-80.809639,35.217624],"type":"Point"}
}