{
  "type": "Feature",
  "properties": {
    "addr:full":"688 E Plaza Dr Mooresville NC 28115",
    "addr:housenumber":"688",
    "addr:postcode":"28115",
    "addr:street":"E Plaza Dr",
    "iso:country":"US",
    "sg:address":"688 E Plaza Dr",
    "sg:city":"Mooresville",
    "sg:classifiers":[
        {
            "category":"Shopping",
            "subcategory":"Used Merchandise",
            "type":"Retail Goods"
        }
    ],
    "sg:phone":"+1 704 662 7082",
    "sg:postcode":"28115",
    "sg:province":"NC",
    "sg:tags":[
        "shop",
        "thrift"
    ],
    "wof:name":"Goodwill Industries",
    "wof:placetype":"venue"
},
  "geometry": {"coordinates":[-80.812586,35.598715],"type":"Point"}
}