{
  "type": "Feature",
  "properties": {
    "addr:full":"2616 Raeford Rd Fayetteville NC 28303",
    "addr:housenumber":"2616",
    "addr:postcode":"28303",
    "addr:street":"Raeford Rd",
    "iso:country":"US",
    "sg:address":"2616 Raeford Rd",
    "sg:city":"Fayetteville",
    "sg:classifiers":[
        {
            "category":"Retail",
            "subcategory":"Laundry & Dry Cleaning",
            "type":"Services"
        }
    ],
    "sg:phone":"+1 910 484 8461",
    "sg:postcode":"28303",
    "sg:province":"NC",
    "sg:tags":[
        "garment",
        "agent",
        "cleaners"
    ],
    "wof:name":"Gene's Cleaners",
    "wof:placetype":"venue"
},
  "geometry": {"coordinates":[-78.921572,35.045934],"type":"Point"}
}