{
  "type": "Feature",
  "properties": {
    "addr:full":"1250 Ephesus Church Rd Apt J3 Chapel Hill NC 27517",
    "addr:housenumber":"1250",
    "addr:postcode":"27517",
    "addr:street":"Ephesus Church Rd;J3",
    "iso:country":"US",
    "sg:address":"1250 Ephesus Church Rd Apt J3",
    "sg:city":"Chapel Hill",
    "sg:classifiers":[
        {
            "category":"Taxi",
            "type":"Transportation"
        }
    ],
    "sg:phone":"+1 919 968 1139",
    "sg:postcode":"27517",
    "sg:province":"NC",
    "wof:name":"Destiny Transportation Inc",
    "wof:placetype":"venue"
},
  "geometry": {"coordinates":[-79.020938,35.934055],"type":"Point"}
}