{
  "type": "Feature",
  "properties": {
    "iso:country":"US",
    "sg:address":"7053 W Friendly Ave",
    "sg:city":"Greensboro",
    "sg:classifiers":[
        {
            "category":"Professional",
            "subcategory":"Research",
            "type":"Services"
        }
    ],
    "sg:phone":"+1   ",
    "sg:postcode":"27410",
    "sg:province":"NC",
    "sg:tags":[
        "related"
    ],
    "wof:name":"Perfect Numbers Inc",
    "wof:placetype":"venue"
},
  "geometry": {"coordinates":[-79.92127000000001,36.088608],"type":"Point"}
}