{
  "type": "Feature",
  "properties": {
    "addr:full":"1912 Forest Hill Dr Greenville NC 27858",
    "addr:housenumber":"1912",
    "addr:postcode":"27858",
    "addr:street":"Forest Hill Dr",
    "iso:country":"US",
    "sg:address":"1912 Forest Hill Dr",
    "sg:city":"Greenville",
    "sg:classifiers":[
        {
            "category":"Wholesale",
            "subcategory":"Construction Materials",
            "type":"Manufacturing & Wholesale Goods"
        }
    ],
    "sg:phone":"+1 252 756 6122",
    "sg:postcode":"27858",
    "sg:province":"NC",
    "wof:name":"Grayton Company Inc",
    "wof:placetype":"venue"
},
  "geometry": {"coordinates":[-77.363722,35.589654],"type":"Point"}
}