{
  "type": "Feature",
  "properties": {
    "iso:country":"US",
    "sg:address":"7400 Siler City Snow Camp Rd",
    "sg:city":"Siler City",
    "sg:classifiers":[
        {
            "category":"Retail",
            "subcategory":"Repair Shop",
            "type":"Services"
        }
    ],
    "sg:phone":"+1   ",
    "sg:postcode":"27344",
    "sg:province":"NC",
    "sg:tags":[
        "welding"
    ],
    "wof:name":"Terrys Welding & Repair",
    "wof:placetype":"venue"
},
  "geometry": {"coordinates":[-79.432042,35.811049],"type":"Point"}
}