{
  "type": "Feature",
  "properties": {
    "iso:country":"US",
    "sg:address":"93 Edgewater Ln",
    "sg:city":"Wilmington",
    "sg:classifiers":[
        {
            "category":"Building & Trades",
            "subcategory":"Landscaping Services",
            "type":"Services"
        }
    ],
    "sg:phone":"+1 910 796 1166",
    "sg:postcode":"28403",
    "sg:province":"NC",
    "sg:tags":[
        "contractor"
    ],
    "wof:name":"Freeman Landscape Inc",
    "wof:placetype":"venue"
},
  "geometry": {"coordinates":[-77.82366,34.218763],"type":"Point"}
}