{
  "type": "Feature",
  "properties": {
    "addr:full":"5731 Roxboro Rd Durham NC 27712",
    "addr:housenumber":"5731",
    "addr:postcode":"27712",
    "addr:street":"Roxboro Rd",
    "iso:country":"US",
    "sg:address":"5731 Roxboro Rd",
    "sg:city":"Durham",
    "sg:classifiers":[
        {
            "category":"Organizations",
            "subcategory":"Religious Organization",
            "type":"Services"
        }
    ],
    "sg:phone":"+1 919 471 0032",
    "sg:postcode":"27712",
    "sg:province":"NC",
    "sg:tags":[
        "church"
    ],
    "sg:website":"www.mtsylvan.org",
    "wof:name":"Mount Sylvan United Methodist",
    "wof:placetype":"venue"
},
  "geometry": {"coordinates":[-78.90992199999999,36.098426],"type":"Point"}
}