{
  "type": "Feature",
  "properties": {
    "iso:country":"US",
    "sg:address":"2828 Gray Fox Rd",
    "sg:city":"Monroe",
    "sg:classifiers":[
        {
            "category":"Retail",
            "subcategory":"Laundry & Dry Cleaning",
            "type":"Services"
        }
    ],
    "sg:phone":"+1 704 296 9336",
    "sg:postcode":"28110",
    "sg:province":"NC",
    "sg:tags":[
        "cleaners"
    ],
    "wof:name":"Elite Cleaners Inc",
    "wof:placetype":"venue"
},
  "geometry": {"coordinates":[-80.621728,35.057164],"type":"Point"}
}