{
  "type": "Feature",
  "properties": {
    "iso:country":"US",
    "sg:address":"3100 Duraleigh Rd Ste 100",
    "sg:city":"Raleigh",
    "sg:classifiers":[
        {
            "category":"Health Services",
            "subcategory":"Doctor",
            "type":"Services"
        }
    ],
    "sg:phone":"+1 919 571 6465",
    "sg:postcode":"27612",
    "sg:province":"NC",
    "sg:tags":[
        "physician",
        "family",
        "practice",
        "surgeons",
        "medicine",
        "surgeon",
        "surgery-general"
    ],
    "sg:website":"http://www.ebwmd.com",
    "wof:name":"Wilkins E Brooks Family Medicine PA",
    "wof:placetype":"venue"
},
  "geometry": {"coordinates":[-78.705489,35.822324],"type":"Point"}
}