{
  "type": "Feature",
  "properties": {
    "addr:full":"225 N Main St Tarboro NC 27886",
    "addr:housenumber":"225",
    "addr:postcode":"27886",
    "addr:street":"N Main St",
    "iso:country":"US",
    "sg:address":"225 N Main St",
    "sg:city":"Tarboro",
    "sg:classifiers":[
        {
            "category":"Shopping",
            "subcategory":"Clothing, Apparel, & Fashions",
            "type":"Retail Goods"
        }
    ],
    "sg:phone":"+1 252 641 6500",
    "sg:postcode":"27886",
    "sg:province":"NC",
    "wof:name":"S & R Factions",
    "wof:placetype":"venue"
},
  "geometry": {"coordinates":[-77.533916,35.896266],"type":"Point"}
}