{
  "type": "Feature",
  "properties": {
    "iso:country":"US",
    "sg:address":"4504 Binfords Ridge Rd",
    "sg:city":"Charlotte",
    "sg:classifiers":[
        {
            "category":"Professional",
            "type":"Services"
        }
    ],
    "sg:phone":"+1 704 341 5484",
    "sg:postcode":"28226",
    "sg:province":"NC",
    "wof:name":"Signature Inc Corporate",
    "wof:placetype":"venue"
},
  "geometry": {"coordinates":[-80.80538799999999,35.092751],"type":"Point"}
}