{
  "type": "Feature",
  "properties": {
    "addr:full":"7819 South Blvd Charlotte NC 28273",
    "addr:housenumber":"7819",
    "addr:postcode":"28273",
    "addr:street":"South Blvd",
    "iso:country":"US",
    "sg:address":"7819 South Blvd",
    "sg:city":"Charlotte",
    "sg:classifiers":[
        {
            "category":"Science Facility",
            "type":"Public Place"
        }
    ],
    "sg:phone":"+1 980 207 4113",
    "sg:postcode":"28273",
    "sg:province":"NC",
    "sg:tags":[
        "development",
        "laboratories-research"
    ],
    "wof:name":"M & R Technologies",
    "wof:placetype":"venue"
},
  "geometry": {"coordinates":[-80.87635400000001,35.12877],"type":"Point"}
}