{
  "type": "Feature",
  "properties": {
    "addr:full":"416 Dix Creek One Rd Leicester NC 28748",
    "addr:housenumber":"416",
    "addr:postcode":"28748",
    "addr:street":"Dix Creek One Rd",
    "iso:country":"US",
    "sg:address":"416 Dix Creek One Rd",
    "sg:city":"Leicester",
    "sg:classifiers":[
        {
            "category":"Personal",
            "type":"Services"
        }
    ],
    "sg:phone":"+1 828 683 4122",
    "sg:postcode":"28748",
    "sg:province":"NC",
    "sg:tags":[
        "towing"
    ],
    "wof:name":"Tommy's Used Auto Parts",
    "wof:placetype":"venue"
},
  "geometry": {"coordinates":[-82.688202,35.606602],"type":"Point"}
}