{
  "type": "Feature",
  "properties": {
    "addr:full":"860 Tiffany Blvd Rocky Mount NC 27804",
    "addr:housenumber":"860",
    "addr:postcode":"27804",
    "addr:street":"Tiffany Blvd",
    "iso:country":"US",
    "sg:address":"860 Tiffany Blvd",
    "sg:city":"Rocky Mount",
    "sg:classifiers":[
        {
            "category":"Professional",
            "subcategory":"Accounting & Tax Preparation",
            "type":"Services"
        }
    ],
    "sg:phone":"+1   ",
    "sg:postcode":"27804",
    "sg:province":"NC",
    "wof:name":"Morris R Wilder CPA",
    "wof:placetype":"venue"
},
  "geometry": {"coordinates":[-77.80141500000001,35.976911],"type":"Point"}
}