{
  "type": "Feature",
  "properties": {
    "iso:country":"US",
    "sg:address":"100 Western Blvd",
    "sg:city":"Jacksonville",
    "sg:classifiers":[
        {
            "category":"Retail",
            "subcategory":"Laundry & Dry Cleaning",
            "type":"Services"
        }
    ],
    "sg:phone":"+1 910 219 9689",
    "sg:postcode":"28546",
    "sg:province":"NC",
    "wof:name":"Brynnmarr Coin Laundry",
    "wof:placetype":"venue"
},
  "geometry": {"coordinates":[-77.379586,34.747187],"type":"Point"}
}