{
  "type": "Feature",
  "properties": {
    "addr:full":"1522 Middle Rd Fayetteville NC 28312",
    "addr:housenumber":"1522",
    "addr:postcode":"28312",
    "addr:street":"Middle Rd",
    "iso:country":"US",
    "sg:address":"1522 Middle Rd",
    "sg:city":"Fayetteville",
    "sg:classifiers":[
        {
            "category":"Farming",
            "subcategory":"Farm",
            "type":"Manufacturing & Wholesale Goods"
        }
    ],
    "sg:phone":"+1 910 483 9230",
    "sg:postcode":"28312",
    "sg:province":"NC",
    "sg:tags":[
        "crop",
        "general"
    ],
    "wof:name":"Margaret Beard",
    "wof:placetype":"venue"
},
  "geometry": {"coordinates":[-78.82857199999999,35.082296],"type":"Point"}
}