{
  "type": "Feature",
  "properties": {
    "iso:country":"US",
    "sg:address":"538 Wilkesboro Blvd SE",
    "sg:city":"Lenoir",
    "sg:classifiers":[
        {
            "category":"Retail",
            "subcategory":"Auto Rental",
            "type":"Services"
        }
    ],
    "sg:phone":"+1 828 758 8299",
    "sg:postcode":"28645",
    "sg:province":"NC",
    "sg:tags":[
        "renting",
        "truck",
        "leasing"
    ],
    "wof:name":"U-Haul Co",
    "wof:placetype":"venue"
},
  "geometry": {"coordinates":[-81.511803,35.918553],"type":"Point"}
}