{
  "type": "Feature",
  "properties": {
    "iso:country":"US",
    "sg:address":"3101 Hillsborough St",
    "sg:city":"Raleigh",
    "sg:classifiers":[
        {
            "category":"Wholesale",
            "subcategory":"Machinery & Supplies",
            "type":"Manufacturing & Wholesale Goods"
        }
    ],
    "sg:phone":"+1 919 833 4811",
    "sg:postcode":"27607",
    "sg:province":"NC",
    "sg:tags":[
        "contractor"
    ],
    "wof:name":"North Carolina Equipment Co",
    "wof:placetype":"venue"
},
  "geometry": {"coordinates":[-78.678994,35.790318],"type":"Point"}
}