{
  "type": "Feature",
  "properties": {
    "addr:full":"528 Nelson St Kernersville NC 27284",
    "addr:housenumber":"528",
    "addr:postcode":"27284",
    "addr:street":"Nelson St",
    "iso:country":"US",
    "sg:address":"528 Nelson St",
    "sg:city":"Kernersville",
    "sg:classifiers":[
        {
            "category":"Restaurant",
            "type":"Food & Drink"
        }
    ],
    "sg:menulink":"http://www.allmenus.com/nc/kernersville/199629-sonic/menu/",
    "sg:phone":"+1 336 992 9504",
    "sg:postcode":"27284",
    "sg:province":"NC",
    "sg:tags":[
        "burger",
        "american"
    ],
    "wof:name":"Sonic",
    "wof:placetype":"venue"
},
  "geometry": {"coordinates":[-80.06782800000001,36.127093],"type":"Point"}
}