{
  "type": "Feature",
  "properties": {
    "addr:full":"528 Albemarle Rd Asheboro NC 27203",
    "addr:housenumber":"528",
    "addr:postcode":"27203",
    "addr:street":"Albemarle Rd",
    "iso:country":"US",
    "sg:address":"528 Albemarle Rd",
    "sg:city":"Asheboro",
    "sg:classifiers":[
        {
            "category":"Professional",
            "subcategory":"Art Services",
            "type":"Services"
        }
    ],
    "sg:phone":"+1   ",
    "sg:postcode":"27203",
    "sg:province":"NC",
    "sg:tags":[
        "commercial",
        "design"
    ],
    "wof:name":"Dynamic Designs",
    "wof:placetype":"venue"
},
  "geometry": {"coordinates":[-79.820986,35.693091],"type":"Point"}
}