{
  "type": "Feature",
  "properties": {
    "addr:full":"1549 Northside Rd Creedmoor NC 27522",
    "addr:housenumber":"1549",
    "addr:postcode":"27522",
    "addr:street":"Northside Rd",
    "iso:country":"US",
    "sg:address":"1549 Northside Rd",
    "sg:city":"Creedmoor",
    "sg:phone":"+1 919 528 3263",
    "sg:postcode":"27522",
    "sg:province":"NC",
    "sg:tags":[
        "vegetable",
        "strawberry",
        "farm",
        "market",
        "farmer"
    ],
    "wof:name":"Lyon Farms",
    "wof:placetype":"venue"
},
  "geometry": {"coordinates":[-78.725379,36.090173],"type":"Point"}
}