{
  "type": "Feature",
  "properties": {
    "addr:full":"5421 Hazelnut Cir Apt K Charlotte NC 28212",
    "addr:housenumber":"5421",
    "addr:postcode":"28212",
    "addr:street":"Hazelnut Cir Apt K",
    "iso:country":"US",
    "sg:address":"5421 Hazelnut Cir Apt K",
    "sg:city":"Charlotte",
    "sg:classifiers":[
        {
            "category":"Health Services",
            "subcategory":"Doctor",
            "type":"Services"
        },
        {
            "category":"Health Services",
            "subcategory":"Hospital",
            "type":"Services"
        }
    ],
    "sg:phone":"+1 704 567 7734",
    "sg:postcode":"28212",
    "sg:province":"NC",
    "sg:tags":[
        "consultant",
        "medical",
        "practice",
        "nursing",
        "home"
    ],
    "wof:name":"Jerry Strum & Associates",
    "wof:placetype":"venue"
},
  "geometry": {"coordinates":[-80.73830700000001,35.206145],"type":"Point"}
}