{
  "type": "Feature",
  "properties": {
    "addr:full":"239 E Center St Lexington NC 27292",
    "addr:housenumber":"239",
    "addr:postcode":"27292",
    "addr:street":"E Center St",
    "iso:country":"US",
    "sg:address":"239 E Center St",
    "sg:city":"Lexington",
    "sg:classifiers":[
        {
            "category":"Insurance",
            "subcategory":"Insurance Agent",
            "type":"Services"
        }
    ],
    "sg:phone":"+1 336 249 8106",
    "sg:postcode":"27292",
    "sg:province":"NC",
    "wof:name":"State Farm Insurance",
    "wof:placetype":"venue"
},
  "geometry": {"coordinates":[-80.25005,35.821343],"type":"Point"}
}