{
  "type": "Feature",
  "properties": {
    "addr:full":"937 E Garrison Blvd Gastonia NC 28054",
    "addr:housenumber":"937",
    "addr:postcode":"28054",
    "addr:street":"E Garrison Blvd",
    "iso:country":"US",
    "sg:address":"937 E Garrison Blvd",
    "sg:city":"Gastonia",
    "sg:classifiers":[
        {
            "category":"Food & Beverages",
            "subcategory":"Groceries & Convenience Stores",
            "type":"Retail Goods"
        }
    ],
    "sg:phone":"+1 704 864 0114",
    "sg:postcode":"28054",
    "sg:province":"NC",
    "sg:tags":[
        "station",
        "gasoline"
    ],
    "wof:name":"Kingsway Enterprises Inc",
    "wof:placetype":"venue"
},
  "geometry": {"coordinates":[-81.167502,35.253119],"type":"Point"}
}