{
  "type": "Feature",
  "properties": {
    "addr:full":"600 Greenville Blvd SE Greenville NC 27858",
    "addr:housenumber":"600",
    "addr:postcode":"27858",
    "addr:street":"Greenville Blvd Se",
    "iso:country":"US",
    "sg:address":"600 Greenville Blvd SE",
    "sg:city":"Greenville",
    "sg:classifiers":[
        {
            "category":"Shopping",
            "type":"Retail Goods"
        }
    ],
    "sg:phone":"+1 252 756 7706",
    "sg:postcode":"27858",
    "sg:province":"NC",
    "sg:tags":[
        "pet",
        "food",
        "supply"
    ],
    "wof:name":"Pet Smart",
    "wof:placetype":"venue"
},
  "geometry": {"coordinates":[-77.37057,35.585682],"type":"Point"}
}