{
  "type": "Feature",
  "properties": {
    "iso:country":"US",
    "sg:address":"213 Dunn Rd",
    "sg:city":"Fayetteville",
    "sg:classifiers":[
        {
            "category":"Professional",
            "subcategory":"Detective & Security Services",
            "type":"Services"
        }
    ],
    "sg:phone":"+1   ",
    "sg:postcode":"28312",
    "sg:province":"NC",
    "sg:tags":[
        "car"
    ],
    "wof:name":"Brocks Screen Guards LLC",
    "wof:placetype":"venue"
},
  "geometry": {"coordinates":[-78.853379,35.051092],"type":"Point"}
}