{
  "type": "Feature",
  "properties": {
    "addr:full":"3800 Arendell St Morehead City NC 28557",
    "addr:postcode":"3800;28557",
    "addr:street":"Arendell St",
    "iso:country":"US",
    "sg:address":"3800 Arendell St",
    "sg:city":"Morehead City",
    "sg:classifiers":[
        {
            "category":"Wholesale",
            "subcategory":"Furniture",
            "type":"Manufacturing & Wholesale Goods"
        }
    ],
    "sg:phone":"+1 252 726 3933",
    "sg:postcode":"28557",
    "sg:province":"NC",
    "wof:name":"Morehead Office Equipment Co",
    "wof:placetype":"venue"
},
  "geometry": {"coordinates":[-76.759079,34.725181],"type":"Point"}
}