{
  "type": "Feature",
  "properties": {
    "addr:full":"1121 S Wesleyan Blvd Rocky Mount NC 27803",
    "addr:housenumber":"1121",
    "addr:postcode":"27803",
    "addr:street":"S Wesleyan Blvd",
    "iso:country":"US",
    "sg:address":"1121 S Wesleyan Blvd",
    "sg:city":"Rocky Mount",
    "sg:classifiers":[
        {
            "category":"Shopping",
            "type":"Retail Goods"
        }
    ],
    "sg:phone":"+1 252 442 1927",
    "sg:postcode":"27803",
    "sg:province":"NC",
    "sg:tags":[
        "cosmetic",
        "perfume"
    ],
    "wof:name":"Allen's Beauty Supply",
    "wof:placetype":"venue"
},
  "geometry": {"coordinates":[-77.831413,35.92098],"type":"Point"}
}