{
  "type": "Feature",
  "properties": {
    "iso:country":"US",
    "sg:address":"1 River Oaks Dr",
    "sg:city":"Greensboro",
    "sg:classifiers":[
        {
            "category":"Real Estate",
            "subcategory":"Real Estate Operator",
            "type":"Services"
        }
    ],
    "sg:phone":"+1 336 299 0172",
    "sg:postcode":"27409",
    "sg:province":"NC",
    "sg:tags":[
        "apartment"
    ],
    "wof:name":"Camden Apartments",
    "wof:placetype":"venue"
},
  "geometry": {"coordinates":[-79.897279,36.059681],"type":"Point"}
}