{
  "type": "Feature",
  "properties": {
    "iso:country":"US",
    "sg:address":"2708 Old Spartanburg Rd",
    "sg:city":"East Flat Rock",
    "sg:classifiers":[
        {
            "category":"Building & Trades",
            "subcategory":"Plumbing",
            "type":"Services"
        }
    ],
    "sg:phone":"+1 828 697 9669",
    "sg:postcode":"28726",
    "sg:province":"NC",
    "sg:tags":[
        "heating",
        "contractor"
    ],
    "wof:name":"Hendersonville Heating-Cooling",
    "wof:placetype":"venue"
},
  "geometry": {"coordinates":[-82.422101,35.287407],"type":"Point"}
}