{
  "type": "Feature",
  "properties": {
    "iso:country":"US",
    "sg:address":"614 S 16th St",
    "sg:city":"Wilmington",
    "sg:classifiers":[
        {
            "category":"Retail",
            "subcategory":"Auto Repair",
            "type":"Services"
        }
    ],
    "sg:phone":"+1   ",
    "sg:postcode":"28401",
    "sg:province":"NC",
    "sg:tags":[
        "automotive"
    ],
    "wof:name":"Boone Auto",
    "wof:placetype":"venue"
},
  "geometry": {"coordinates":[-77.92797,34.228308],"type":"Point"}
}