{
  "type": "Feature",
  "properties": {
    "addr:full":"131 Bridge St Willow Spring NC 27577",
    "addr:housenumber":"131",
    "addr:postcode":"27577",
    "addr:street":"Bridge St",
    "iso:country":"US",
    "sg:address":"131 Bridge St",
    "sg:city":"Willow Spring",
    "sg:classifiers":[
        {
            "category":"Building & Trades",
            "subcategory":"Plumbing",
            "type":"Services"
        }
    ],
    "sg:phone":"+1 919 235 2052",
    "sg:postcode":"27577",
    "sg:province":"NC",
    "sg:tags":[
        "plumbing",
        "contractor"
    ],
    "wof:name":"All About Plumbing & Backhoe",
    "wof:placetype":"venue"
},
  "geometry": {"coordinates":[-78.34775,35.51351],"type":"Point"}
}