{
  "type": "Feature",
  "properties": {
    "iso:country":"US",
    "sg:address":"1466 Bradford Mountain Rd",
    "sg:city":"Lenoir",
    "sg:classifiers":[
        {
            "category":"Building & Trades",
            "subcategory":"Construction",
            "type":"Services"
        }
    ],
    "sg:phone":"+1 828 758 1338",
    "sg:postcode":"28645",
    "sg:province":"NC",
    "wof:name":"Appalachian Paving & Cnstr Co",
    "wof:placetype":"venue"
},
  "geometry": {"coordinates":[-81.555605,35.87566],"type":"Point"}
}