{
  "type": "Feature",
  "properties": {
    "iso:country":"US",
    "sg:address":"14139 State Hwy 86",
    "sg:city":"Prospect Hill",
    "sg:classifiers":[
        {
            "category":"Shopping",
            "subcategory":"Crafts & Fabrics",
            "type":"Retail Goods"
        }
    ],
    "sg:phone":"+1 336 562 8101",
    "sg:postcode":"27314",
    "sg:province":"NC",
    "sg:tags":[
        "shop"
    ],
    "wof:name":"Fabric Editions LTD",
    "wof:placetype":"venue"
},
  "geometry": {"coordinates":[-79.193063,36.256213],"type":"Point"}
}