{
  "type": "Feature",
  "properties": {
    "iso:country":"US",
    "sg:address":"2200 W Main St",
    "sg:city":"Durham",
    "sg:classifiers":[
        {
            "category":"Restaurant",
            "type":"Food & Drink"
        }
    ],
    "sg:menulink":"http://www.allmenus.com/nc/durham/270815-baba-ghannouj/menu/",
    "sg:phone":"+1 919 286 6699",
    "sg:postcode":"27705",
    "sg:province":"NC",
    "sg:tags":[
        "mediterranean"
    ],
    "wof:name":"Baba Ghannouj",
    "wof:placetype":"venue"
},
  "geometry": {"coordinates":[-78.924694,36.006863],"type":"Point"}
}