{
  "type": "Feature",
  "properties": {
    "addr:full":"114 East St Fuquay Varina NC 27526",
    "addr:housenumber":"114",
    "addr:postcode":"27526",
    "addr:street":"East St",
    "iso:country":"US",
    "sg:address":"114 East St",
    "sg:city":"Fuquay Varina",
    "sg:classifiers":[
        {
            "category":"Shopping",
            "subcategory":"Catalog Store",
            "type":"Retail Goods"
        }
    ],
    "sg:phone":"+1 919 567 3646",
    "sg:postcode":"27526",
    "sg:province":"NC",
    "sg:tags":[
        "mail",
        "house"
    ],
    "wof:name":"Louise Geez",
    "wof:placetype":"venue"
},
  "geometry": {"coordinates":[-78.796015,35.585579],"type":"Point"}
}