{
  "type": "Feature",
  "properties": {
    "iso:country":"US",
    "sg:address":"8015 Chapel Hill Rd",
    "sg:city":"Cary",
    "sg:classifiers":[
        {
            "category":"Food & Beverages",
            "subcategory":"Groceries & Convenience Stores",
            "type":"Retail Goods"
        }
    ],
    "sg:phone":"+1 919 469 3734",
    "sg:postcode":"27513",
    "sg:province":"NC",
    "wof:name":"C Mini Mart Number 1",
    "wof:placetype":"venue"
},
  "geometry": {"coordinates":[-78.768,35.793893],"type":"Point"}
}