{
  "type": "Feature",
  "properties": {
    "addr:full":"313 W University Dr Chapel Hill NC 27516",
    "addr:housenumber":"313",
    "addr:postcode":"27516",
    "addr:street":"W University Dr",
    "iso:country":"US",
    "sg:address":"313 W University Dr",
    "sg:city":"Chapel Hill",
    "sg:classifiers":[
        {
            "category":"Banks & Credit Unions",
            "subcategory":"Financial Services",
            "type":"Services"
        }
    ],
    "sg:phone":"+1 919 932 3760",
    "sg:postcode":"27516",
    "sg:province":"NC",
    "sg:tags":[
        "investor"
    ],
    "wof:name":"Cbc Investments LLC",
    "wof:placetype":"venue"
},
  "geometry": {"coordinates":[-79.05835,35.904494],"type":"Point"}
}