{
  "type": "Feature",
  "properties": {
    "addr:full":"1120 East Blvd Charlotte NC 28203",
    "addr:housenumber":"1120",
    "addr:postcode":"28203",
    "addr:street":"East Blvd",
    "iso:country":"US",
    "sg:address":"1120 East Blvd",
    "sg:city":"Charlotte",
    "sg:classifiers":[
        {
            "category":"Professional",
            "subcategory":"Management & Consulting",
            "type":"Services"
        }
    ],
    "sg:phone":"+1 704 377 0629",
    "sg:postcode":"28203",
    "sg:province":"NC",
    "sg:tags":[
        "facility",
        "consultant",
        "planning",
        "space"
    ],
    "sg:website":"www.quantus.com",
    "wof:name":"Quantus Inc LLC",
    "wof:placetype":"venue"
},
  "geometry": {"coordinates":[-80.847013,35.203625],"type":"Point"}
}