{
  "type": "Feature",
  "properties": {
    "addr:full":"718 W Trade St Charlotte NC 28202",
    "addr:housenumber":"718",
    "addr:postcode":"28202",
    "addr:street":"W Trade St",
    "iso:country":"US",
    "sg:address":"718 W Trade St",
    "sg:city":"Charlotte",
    "sg:classifiers":[
        {
            "category":"Food & Beverages",
            "subcategory":"Specialty",
            "type":"Retail Goods"
        }
    ],
    "sg:phone":"+1 704 372 2500",
    "sg:postcode":"28202",
    "sg:province":"NC",
    "wof:name":"Kaldis Koffee",
    "wof:placetype":"venue"
},
  "geometry": {"coordinates":[-80.84970199999999,35.232836],"type":"Point"}
}