{
  "type": "Feature",
  "properties": {
    "addr:full":"1406 Heartland Dr Kernersville NC 27284",
    "addr:housenumber":"1406",
    "addr:postcode":"27284",
    "addr:street":"Heartland Dr",
    "iso:country":"US",
    "sg:address":"1406 Heartland Dr",
    "sg:city":"Kernersville",
    "sg:classifiers":[
        {
            "category":"Travel",
            "subcategory":"Hotels & Motels",
            "type":"Entertainment"
        }
    ],
    "sg:phone":"+1 336 993 6800",
    "sg:postcode":"27284",
    "sg:province":"NC",
    "sg:tags":[
        "operation"
    ],
    "wof:name":"Sleep Inn",
    "wof:placetype":"venue"
},
  "geometry": {"coordinates":[-80.06115,36.087677],"type":"Point"}
}