{
  "type": "Feature",
  "properties": {
    "addr:full":"7424 A C C Blvd Raleigh NC 27617",
    "addr:housenumber":"7424 a",
    "addr:postcode":"27617",
    "addr:street":"C C Blvd",
    "iso:country":"US",
    "sg:address":"7424 A C C Blvd",
    "sg:city":"Raleigh",
    "sg:classifiers":[
        {
            "category":"Professional",
            "type":"Services"
        }
    ],
    "sg:phone":"+1 919 293 1040",
    "sg:postcode":"27617",
    "sg:province":"NC",
    "sg:tags":[
        "establishment"
    ],
    "wof:name":"Coastal Cartworks Inc",
    "wof:placetype":"venue"
},
  "geometry": {"coordinates":[-78.764117,35.910596],"type":"Point"}
}