{
  "type": "Feature",
  "properties": {
    "addr:full":"123 W Main St Williamston NC 27892",
    "addr:housenumber":"123",
    "addr:postcode":"27892",
    "addr:street":"W Main St",
    "iso:country":"US",
    "sg:address":"123 W Main St",
    "sg:city":"Williamston",
    "sg:classifiers":[
        {
            "category":"Personal",
            "subcategory":"Beauty Salon",
            "type":"Services"
        }
    ],
    "sg:phone":"+1 252 799 4300",
    "sg:postcode":"27892",
    "sg:province":"NC",
    "wof:name":"New Beginnings",
    "wof:placetype":"venue"
},
  "geometry": {"coordinates":[-77.055892,35.854548],"type":"Point"}
}