{
  "type": "Feature",
  "properties": {
    "addr:full":"5751 Oleander Dr Wilmington NC 28403",
    "addr:housenumber":"5751",
    "addr:postcode":"28403",
    "addr:street":"Oleander Dr",
    "iso:country":"US",
    "sg:address":"5751 Oleander Dr",
    "sg:city":"Wilmington",
    "sg:classifiers":[
        {
            "category":"Shopping",
            "subcategory":"Books",
            "type":"Retail Goods"
        }
    ],
    "sg:phone":"+1 910 392 6647",
    "sg:postcode":"28403",
    "sg:province":"NC",
    "sg:tags":[
        "comic"
    ],
    "wof:name":"Memory Lane Comics",
    "wof:placetype":"venue"
},
  "geometry": {"coordinates":[-77.847286,34.209214],"type":"Point"}
}