{
  "type": "Feature",
  "properties": {
    "iso:country":"US",
    "sg:address":"13255 Rosedale Hill Ave",
    "sg:city":"Huntersville",
    "sg:classifiers":[
        {
            "category":"Real Estate",
            "subcategory":"Real Estate Operator",
            "type":"Services"
        }
    ],
    "sg:phone":"+1 704 875 3074",
    "sg:postcode":"28078",
    "sg:province":"NC",
    "sg:tags":[
        "apartment"
    ],
    "wof:name":"Baxley Crossing At Rosedale",
    "wof:placetype":"venue"
},
  "geometry": {"coordinates":[-80.86209700000001,35.411386],"type":"Point"}
}