{
  "type": "Feature",
  "properties": {
    "addr:full":"2780 Tynecastle Hwy Banner Elk NC 28604",
    "addr:housenumber":"2780",
    "addr:postcode":"28604",
    "addr:street":"Tynecastle Hwy",
    "iso:country":"US",
    "sg:address":"2780 Tynecastle Hwy",
    "sg:city":"Banner Elk",
    "sg:classifiers":[
        {
            "category":"Real Estate",
            "subcategory":"Real Estate Agent",
            "type":"Services"
        }
    ],
    "sg:phone":"+1 828 898 1880",
    "sg:postcode":"28604",
    "sg:province":"NC",
    "wof:name":"Reserve At Sugar Mountain",
    "wof:placetype":"venue"
},
  "geometry": {"coordinates":[-81.86108400000001,36.146904],"type":"Point"}
}