{
  "type": "Feature",
  "properties": {
    "iso:country":"US",
    "sg:address":"323 Main St",
    "sg:city":"Pineville",
    "sg:classifiers":[
        {
            "category":"Shopping",
            "subcategory":"Used Merchandise",
            "type":"Retail Goods"
        }
    ],
    "sg:phone":"+1 704 889 7454",
    "sg:postcode":"28134",
    "sg:province":"NC",
    "wof:name":"Antique Bank",
    "wof:placetype":"venue"
},
  "geometry": {"coordinates":[-80.89056600000001,35.085585],"type":"Point"}
}