{
  "type": "Feature",
  "properties": {
    "addr:full":"2200 Jack Roberson Rd Williamston NC 27892",
    "addr:housenumber":"2200",
    "addr:postcode":"27892",
    "addr:street":"Jack Roberson Rd",
    "iso:country":"US",
    "sg:address":"2200 Jack Roberson Rd",
    "sg:city":"Williamston",
    "sg:classifiers":[
        {
            "category":"Professional",
            "subcategory":"Business Services",
            "type":"Services"
        }
    ],
    "sg:phone":"+1   ",
    "sg:postcode":"27892",
    "sg:province":"NC",
    "wof:name":"Blast Off Power",
    "wof:placetype":"venue"
},
  "geometry": {"coordinates":[-77.143411,35.77965],"type":"Point"}
}