{
  "type": "Feature",
  "properties": {
    "iso:country":"US",
    "sg:address":"2815 Oaks Rd",
    "sg:city":"New Bern",
    "sg:classifiers":[
        {
            "category":"Organizations",
            "subcategory":"Religious Organization",
            "type":"Services"
        }
    ],
    "sg:phone":"+1 252 638 6423",
    "sg:postcode":"28560",
    "sg:province":"NC",
    "sg:tags":[
        "church"
    ],
    "wof:name":"Church Of God Of Prophecy",
    "wof:placetype":"venue"
},
  "geometry": {"coordinates":[-77.066208,35.130305],"type":"Point"}
}