{
  "type": "Feature",
  "properties": {
    "addr:full":"100 Steffey Ln Taylorsville NC 28681",
    "addr:housenumber":"100",
    "addr:postcode":"28681",
    "addr:street":"Steffey Ln",
    "iso:country":"US",
    "sg:address":"100 Steffey Ln",
    "sg:city":"Taylorsville",
    "sg:classifiers":[
        {
            "category":"Building & Trades",
            "subcategory":"Electrical",
            "type":"Services"
        }
    ],
    "sg:phone":"+1 828 495 4136",
    "sg:postcode":"28681",
    "sg:province":"NC",
    "sg:tags":[
        "electrical",
        "contractor"
    ],
    "wof:name":"C & S Cable Inc",
    "wof:placetype":"venue"
},
  "geometry": {"coordinates":[-81.31852499999999,35.847979],"type":"Point"}
}