{
  "type": "Feature",
  "properties": {
    "addr:full":"223 N Lumber St Nashville NC 27856",
    "addr:housenumber":"223",
    "addr:postcode":"27856",
    "addr:street":"N Lumber St",
    "iso:country":"US",
    "sg:address":"223 N Lumber St",
    "sg:city":"Nashville",
    "sg:classifiers":[
        {
            "category":"Social Services",
            "type":"Services"
        }
    ],
    "sg:phone":"+1 252 459 9294",
    "sg:postcode":"27856",
    "sg:province":"NC",
    "wof:name":"Trinity Retirement Villas I",
    "wof:placetype":"venue"
},
  "geometry": {"coordinates":[-77.957317,35.976626],"type":"Point"}
}