{
  "type": "Feature",
  "properties": {
    "addr:full":"5643 Creedmoor Rd Raleigh NC 27612",
    "addr:housenumber":"5643",
    "addr:postcode":"27612",
    "addr:street":"Creedmoor Rd",
    "iso:country":"US",
    "sg:address":"5643 Creedmoor Rd",
    "sg:city":"Raleigh",
    "sg:classifiers":[
        {
            "category":"Personal",
            "subcategory":"Shoe Repair & Shine",
            "type":"Services"
        }
    ],
    "sg:phone":"+1 919 787 0610",
    "sg:postcode":"27612",
    "sg:province":"NC",
    "sg:tags":[
        "repairing",
        "parlor",
        "boot"
    ],
    "wof:name":"Chungs Tailoring & Shoe Repair",
    "wof:placetype":"venue"
},
  "geometry": {"coordinates":[-78.68062,35.858791],"type":"Point"}
}