{
  "type": "Feature",
  "properties": {
    "addr:full":"4724 Old Murphy Rd Franklin NC 28734",
    "addr:housenumber":"4724",
    "addr:postcode":"nc 28734",
    "addr:street":"Old Murphy Rd",
    "iso:country":"US",
    "sg:address":"4724 Old Murphy Rd",
    "sg:city":"Franklin",
    "sg:classifiers":[
        {
            "category":"Travel",
            "subcategory":"Campground",
            "type":"Entertainment"
        }
    ],
    "sg:phone":"+1 828 524 4490",
    "sg:postcode":"28734",
    "sg:province":"NC",
    "wof:name":"Pines Rv Park",
    "wof:placetype":"venue"
},
  "geometry": {"coordinates":[-83.45231,35.164769],"type":"Point"}
}