{
  "type": "Feature",
  "properties": {
    "iso:country":"US",
    "sg:address":"1510 Beatties Ford Rd",
    "sg:city":"Charlotte",
    "sg:classifiers":[
        {
            "category":"Personal",
            "subcategory":"Beauty Salon",
            "type":"Services"
        }
    ],
    "sg:phone":"+1 704 392 2204",
    "sg:postcode":"28216",
    "sg:province":"NC",
    "wof:name":"Nails By Dre'a",
    "wof:placetype":"venue"
},
  "geometry": {"coordinates":[-80.855496,35.257187],"type":"Point"}
}