{
  "type": "Feature",
  "properties": {
    "iso:country":"US",
    "sg:address":"1105 Deer Run Ln",
    "sg:city":"Yadkinville",
    "sg:classifiers":[
        {
            "category":"Retail",
            "subcategory":"Auto Repair",
            "type":"Services"
        }
    ],
    "sg:phone":"+1   ",
    "sg:postcode":"27055",
    "sg:province":"NC",
    "sg:tags":[
        "general"
    ],
    "wof:name":"D & D Garage",
    "wof:placetype":"venue"
},
  "geometry": {"coordinates":[-80.606644,36.139232],"type":"Point"}
}