{
  "type": "Feature",
  "properties": {
    "iso:country":"US",
    "sg:address":"127 W Main St",
    "sg:city":"Albemarle",
    "sg:classifiers":[
        {
            "category":"Shopping",
            "subcategory":"Jewelry",
            "type":"Retail Goods"
        }
    ],
    "sg:phone":"+1 704 982 1013",
    "sg:postcode":"28001",
    "sg:province":"NC",
    "sg:tags":[
        "jeweler"
    ],
    "wof:name":"Starnes Jewelry Store",
    "wof:placetype":"venue"
},
  "geometry": {"coordinates":[-80.19924899999999,35.350295],"type":"Point"}
}