{
  "type": "Feature",
  "properties": {
    "iso:country":"US",
    "sg:address":"7259 Wayman Church Rd",
    "sg:city":"Enfield",
    "sg:classifiers":[
        {
            "category":"Farming",
            "subcategory":"Livestock Farm",
            "type":"Manufacturing & Wholesale Goods"
        }
    ],
    "sg:phone":"+1 252 445 3645",
    "sg:postcode":"27823",
    "sg:province":"NC",
    "sg:tags":[
        "feedlot",
        "field",
        "crop",
        "beef",
        "cattle"
    ],
    "wof:name":"Wayne Boseman",
    "wof:placetype":"venue"
},
  "geometry": {"coordinates":[-77.80447100000001,36.256695],"type":"Point"}
}