{
  "type": "Feature",
  "properties": {
    "addr:full":"7918 Antique Cir Waxhaw NC 28173",
    "addr:housenumber":"7918",
    "addr:postcode":"28173",
    "addr:street":"Antique Cir",
    "iso:country":"US",
    "sg:address":"7918 Antique Cir",
    "sg:city":"Waxhaw",
    "sg:classifiers":[
        {
            "category":"Professional",
            "type":"Services"
        }
    ],
    "sg:phone":"+1 704 243 0942",
    "sg:postcode":"28173",
    "sg:province":"NC",
    "sg:tags":[
        "establishment"
    ],
    "wof:name":"Beeler Marketing",
    "wof:placetype":"venue"
},
  "geometry": {"coordinates":[-80.754988,34.936013],"type":"Point"}
}