{
  "type": "Feature",
  "properties": {
    "iso:country":"US",
    "sg:address":"802 E Davis St",
    "sg:city":"Burlington",
    "sg:classifiers":[
        {
            "category":"Personal",
            "subcategory":"Barber",
            "type":"Services"
        }
    ],
    "sg:phone":"+1   ",
    "sg:postcode":"27215",
    "sg:province":"NC",
    "sg:tags":[
        "shop"
    ],
    "wof:name":"Jay Cees Final Image",
    "wof:placetype":"venue"
},
  "geometry": {"coordinates":[-79.428776,36.084921],"type":"Point"}
}