{
  "type": "Feature",
  "properties": {
    "addr:full":"2619 Haventree Ct Apex NC 27502",
    "addr:housenumber":"2619",
    "addr:postcode":"27502",
    "addr:street":"Haventree Ct",
    "iso:country":"US",
    "sg:address":"2619 Haventree Ct",
    "sg:city":"Apex",
    "sg:classifiers":[
        {
            "category":"Professional",
            "subcategory":"Business Services",
            "type":"Services"
        }
    ],
    "sg:phone":"+1   ",
    "sg:postcode":"27502",
    "sg:province":"NC",
    "wof:name":"Westco Enterprises LLC",
    "wof:placetype":"venue"
},
  "geometry": {"coordinates":[-78.81558200000001,35.728198],"type":"Point"}
}