{
  "type": "Feature",
  "properties": {
    "iso:country":"US",
    "sg:address":"4509 Sharon Chase Dr",
    "sg:city":"Charlotte",
    "sg:classifiers":[
        {
            "category":"Building & Trades",
            "subcategory":"Cleaning & Sanitation",
            "type":"Services"
        }
    ],
    "sg:phone":"+1 704 532 4405",
    "sg:postcode":"28215",
    "sg:province":"NC",
    "sg:tags":[
        "janitor"
    ],
    "wof:name":"Saavy Cleaning Svc",
    "wof:placetype":"venue"
},
  "geometry": {"coordinates":[-80.744371,35.230824],"type":"Point"}
}