{
  "type": "Feature",
  "properties": {
    "iso:country":"US",
    "sg:address":"367 Williamson Rd",
    "sg:city":"Mooresville",
    "sg:classifiers":[
        {
            "category":"Health Services",
            "subcategory":"Doctor",
            "type":"Services"
        }
    ],
    "sg:phone":"+1   ",
    "sg:postcode":"28117",
    "sg:province":"NC",
    "wof:name":"Greg M McCourt DDS",
    "wof:placetype":"venue"
},
  "geometry": {"coordinates":[-80.873154,35.581961],"type":"Point"}
}