{
  "type": "Feature",
  "properties": {
    "addr:full":"6509 Thamesmead Ln Charlotte NC 28227",
    "addr:postcode":"6509;28227",
    "addr:street":"Thamesmead Ln",
    "iso:country":"US",
    "sg:address":"6509 Thamesmead Ln",
    "sg:city":"Charlotte",
    "sg:classifiers":[
        {
            "category":"Building & Trades",
            "subcategory":"Construction",
            "type":"Services"
        }
    ],
    "sg:phone":"+1 704 573 7776",
    "sg:postcode":"28227",
    "sg:province":"NC",
    "sg:tags":[
        "residential"
    ],
    "wof:name":"Alan McKenzie Cnstr Svcs",
    "wof:placetype":"venue"
},
  "geometry": {"coordinates":[-80.678825,35.183341],"type":"Point"}
}