{
  "type": "Feature",
  "properties": {
    "iso:country":"US",
    "sg:address":"61 Betty Branch Rd",
    "sg:city":"Washington",
    "sg:classifiers":[
        {
            "category":"Personal",
            "type":"Services"
        }
    ],
    "sg:phone":"+1 252 948 0777",
    "sg:postcode":"27889",
    "sg:province":"NC",
    "sg:tags":[
        "therapist",
        "massage"
    ],
    "wof:name":"Washington Therapeutics",
    "wof:placetype":"venue"
},
  "geometry": {"coordinates":[-76.998394,35.507263],"type":"Point"}
}