{
  "type": "Feature",
  "properties": {
    "iso:country":"US",
    "sg:address":"4824 Yadkin Dr",
    "sg:city":"Raleigh",
    "sg:classifiers":[
        {
            "category":"Recreation",
            "type":"Entertainment"
        },
        {
            "category":"Organizations",
            "subcategory":"Community Association",
            "type":"Services"
        }
    ],
    "sg:phone":"+1 919 787 3655",
    "sg:postcode":"27609",
    "sg:province":"NC",
    "sg:tags":[
        "club",
        "swim",
        "tennis",
        "pool",
        "swimming"
    ],
    "wof:name":"North Hills Club Swimming Pool",
    "wof:placetype":"venue"
},
  "geometry": {"coordinates":[-78.65196400000001,35.847949],"type":"Point"}
}