{
  "type": "Feature",
  "properties": {
    "addr:full":"1138 Rocky Run Rd Midway Park NC 28544",
    "addr:housenumber":"1138",
    "addr:postcode":"28544",
    "addr:street":"Rocky Run Rd",
    "iso:country":"US",
    "sg:address":"1138 Rocky Run Rd",
    "sg:city":"Midway Park",
    "sg:classifiers":[
        {
            "category":"Real Estate",
            "subcategory":"Real Estate Operator",
            "type":"Services"
        }
    ],
    "sg:phone":"+1 910 353 2086",
    "sg:postcode":"28544",
    "sg:province":"NC",
    "sg:tags":[
        "mobile",
        "home",
        "park",
        "owns"
    ],
    "wof:name":"Collins Estate Mobile Home Pk",
    "wof:placetype":"venue"
},
  "geometry": {"coordinates":[-77.320127,34.736294],"type":"Point"}
}