{
  "type": "Feature",
  "properties": {
    "addr:full":"5676 Old Roxboro Rd Oxford NC 27565",
    "addr:housenumber":"5676",
    "addr:postcode":"27565",
    "addr:street":"Old Roxboro Rd",
    "iso:country":"US",
    "sg:address":"5676 Old Roxboro Rd",
    "sg:city":"Oxford",
    "sg:phone":"+1 919 693 5679",
    "sg:postcode":"27565",
    "sg:province":"NC",
    "sg:tags":[
        "farm",
        "tobacco",
        "cattle"
    ],
    "wof:name":"Henry N Thorp Jr",
    "wof:placetype":"venue"
},
  "geometry": {"coordinates":[-78.741815,36.323706],"type":"Point"}
}