{
  "type": "Feature",
  "properties": {
    "iso:country":"US",
    "sg:address":"253 Ruby Holland Rd",
    "sg:city":"Franklin",
    "sg:classifiers":[
        {
            "category":"Professional",
            "subcategory":"Business Services",
            "type":"Services"
        }
    ],
    "sg:phone":"+1   ",
    "sg:postcode":"28734",
    "sg:province":"NC",
    "wof:name":"Melton Enterprises",
    "wof:placetype":"venue"
},
  "geometry": {"coordinates":[-83.360085,35.236484],"type":"Point"}
}