{
  "type": "Feature",
  "properties": {
    "addr:full":"7879 Alcorn Rd Oak Ridge NC 27310",
    "addr:housenumber":"7879",
    "addr:postcode":"27310",
    "addr:street":"Alcorn Rd",
    "iso:country":"US",
    "sg:address":"7879 Alcorn Rd",
    "sg:city":"Oak Ridge",
    "sg:classifiers":[
        {
            "category":"Professional",
            "subcategory":"Research",
            "type":"Services"
        }
    ],
    "sg:phone":"+1 336 643 7706",
    "sg:postcode":"27310",
    "sg:province":"NC",
    "sg:tags":[
        "ergonomics"
    ],
    "wof:name":"Industrial Biomechanics",
    "wof:placetype":"venue"
},
  "geometry": {"coordinates":[-79.973131,36.157249],"type":"Point"}
}