{
  "type": "Feature",
  "properties": {
    "iso:country":"US",
    "sg:address":"525 S Roberts Ave",
    "sg:city":"Lumberton",
    "sg:classifiers":[
        {
            "category":"Freight",
            "type":"Transportation"
        }
    ],
    "sg:phone":"+1 910 272 9995",
    "sg:postcode":"28358",
    "sg:province":"NC",
    "sg:tags":[
        "commercial",
        "storage"
    ],
    "wof:name":"Backyard Storage & Decks Inc",
    "wof:placetype":"venue"
},
  "geometry": {"coordinates":[-78.979829,34.601772],"type":"Point"}
}