{
  "type": "Feature",
  "properties": {
    "addr:full":"1351 Scotland Crossing Dr Laurinburg NC 28352",
    "addr:housenumber":"1351",
    "addr:postcode":"28352",
    "addr:street":"Scotland Crossing Dr",
    "iso:country":"US",
    "sg:address":"1351 Scotland Crossing Dr",
    "sg:city":"Laurinburg",
    "sg:classifiers":[
        {
            "category":"Shopping",
            "subcategory":"Clothing, Apparel, & Fashions",
            "type":"Retail Goods"
        }
    ],
    "sg:phone":"+1 910 276 7589",
    "sg:postcode":"28352",
    "sg:province":"NC",
    "sg:website":"www.catofashions.com",
    "wof:name":"Cato",
    "wof:placetype":"venue"
},
  "geometry": {"coordinates":[-79.484206,34.759151],"type":"Point"}
}