{
  "type": "Feature",
  "properties": {
    "addr:full":"308 N Church St Hertford NC 27944",
    "addr:housenumber":"308",
    "addr:postcode":"27944",
    "addr:street":"N Church St",
    "iso:country":"US",
    "sg:address":"308 N Church St",
    "sg:city":"Hertford",
    "sg:classifiers":[
        {
            "category":"Shopping",
            "subcategory":"Bicycles & Sporting Goods",
            "type":"Retail Goods"
        }
    ],
    "sg:phone":"+1 252 426 1205",
    "sg:postcode":"27944",
    "sg:province":"NC",
    "wof:name":"Darrow's Archery",
    "wof:placetype":"venue"
},
  "geometry": {"coordinates":[-76.465256,36.192822],"type":"Point"}
}