{
  "type": "Feature",
  "properties": {
    "addr:full":"550 W Andrews Ave Henderson NC 27536",
    "addr:housenumber":"550",
    "addr:postcode":"27536",
    "addr:street":"W Andrews Ave",
    "iso:country":"US",
    "sg:address":"550 W Andrews Ave",
    "sg:city":"Henderson",
    "sg:classifiers":[
        {
            "category":"Home & Garden",
            "subcategory":"Household Appliances",
            "type":"Retail Goods"
        }
    ],
    "sg:phone":"+1 252 492 5201",
    "sg:postcode":"27536",
    "sg:province":"NC",
    "wof:name":"North Henderson Heights Apts",
    "wof:placetype":"venue"
},
  "geometry": {"coordinates":[-78.40357,36.334505],"type":"Point"}
}