{
  "type": "Feature",
  "properties": {
    "addr:full":"2395 Midway Rd SE Bolivia NC 28422",
    "addr:housenumber":"2395",
    "addr:postcode":"28422",
    "addr:street":"Midway Rd Se",
    "iso:country":"US",
    "sg:address":"2395 Midway Rd SE",
    "sg:city":"Bolivia",
    "sg:classifiers":[
        {
            "category":"Retail",
            "subcategory":"Auto Repair",
            "type":"Services"
        }
    ],
    "sg:phone":"+1 910 253 8081",
    "sg:postcode":"28422",
    "sg:province":"NC",
    "sg:tags":[
        "antique",
        "automobile",
        "restoration"
    ],
    "wof:name":"Complete Restorations Inc",
    "wof:placetype":"venue"
},
  "geometry": {"coordinates":[-78.13063699999999,33.973661],"type":"Point"}
}