{
  "type": "Feature",
  "properties": {
    "addr:full":"627 Gum St Mooresville NC 28115",
    "addr:housenumber":"627",
    "addr:postcode":"28115",
    "addr:street":"Gum St",
    "iso:country":"US",
    "sg:address":"627 Gum St",
    "sg:city":"Mooresville",
    "sg:classifiers":[
        {
            "category":"Retail",
            "subcategory":"Funeral Services",
            "type":"Services"
        }
    ],
    "sg:phone":"+1 704 663 3939",
    "sg:postcode":"28115",
    "sg:province":"NC",
    "sg:tags":[
        "director"
    ],
    "wof:name":"Neill Funeral Home & Chapel",
    "wof:placetype":"venue"
},
  "geometry": {"coordinates":[-80.802966,35.587891],"type":"Point"}
}