{
  "type": "Feature",
  "properties": {
    "iso:country":"US",
    "sg:address":"2301 Executive Park Cir",
    "sg:city":"Greenville",
    "sg:classifiers":[
        {
            "category":"Real Estate",
            "subcategory":"Real Estate Agent",
            "type":"Services"
        }
    ],
    "sg:phone":"+1 252 758 7000",
    "sg:postcode":"27834",
    "sg:province":"NC",
    "sg:tags":[
        "appraiser"
    ],
    "wof:name":"F Bruce Sauter & Assoc",
    "wof:placetype":"venue"
},
  "geometry": {"coordinates":[-77.407815,35.605075],"type":"Point"}
}