{
  "type": "Feature",
  "properties": {
    "addr:full":"207 S Broad St Gastonia NC 28052",
    "addr:housenumber":"207",
    "addr:postcode":"28052",
    "addr:street":"S Broad St",
    "iso:country":"US",
    "sg:address":"207 S Broad St",
    "sg:city":"Gastonia",
    "sg:classifiers":[
        {
            "category":"Shopping",
            "subcategory":"Clothing, Apparel, & Fashions",
            "type":"Retail Goods"
        }
    ],
    "sg:phone":"+1 704 864 7181",
    "sg:postcode":"28052",
    "sg:province":"NC",
    "sg:tags":[
        "shop",
        "bridal"
    ],
    "wof:name":"Social Butterfly Bridal & Btq",
    "wof:placetype":"venue"
},
  "geometry": {"coordinates":[-81.178788,35.260803],"type":"Point"}
}