{
  "type": "Feature",
  "properties": {
    "addr:full":"3224 US Hwy 70 Bus E Smithfield NC 27577",
    "addr:housenumber":"3224",
    "addr:postcode":"27577",
    "addr:street":"Us Hwy 70 Bus E",
    "iso:country":"US",
    "sg:address":"3224 US Hwy 70 Bus E",
    "sg:city":"Smithfield",
    "sg:classifiers":[
        {
            "category":"Shopping",
            "subcategory":"Discount & Variety Stores",
            "type":"Retail Goods"
        }
    ],
    "sg:phone":"+1 919 965 2600",
    "sg:postcode":"27577",
    "sg:province":"NC",
    "sg:tags":[
        "merchandise",
        "general"
    ],
    "wof:name":"Pine Valley Sales",
    "wof:placetype":"venue"
},
  "geometry": {"coordinates":[-78.30063699999999,35.497212],"type":"Point"}
}