{
  "type": "Feature",
  "properties": {
    "addr:full":"1851 Dickerson Blvd Monroe NC 28110",
    "addr:housenumber":"1851",
    "addr:postcode":"28110",
    "addr:street":"Dickerson Blvd",
    "iso:country":"US",
    "sg:address":"1851 Dickerson Blvd",
    "sg:city":"Monroe",
    "sg:classifiers":[
        {
            "category":"Professional",
            "type":"Services"
        }
    ],
    "sg:phone":"+1 704 226 9792",
    "sg:postcode":"28110",
    "sg:province":"NC",
    "sg:tags":[
        "establishment"
    ],
    "wof:name":"Alltec Group Inc",
    "wof:placetype":"venue"
},
  "geometry": {"coordinates":[-80.560417,35.007453],"type":"Point"}
}