{
  "type": "Feature",
  "properties": {
    "addr:full":"137 S Hamilton St Eden NC 27288",
    "addr:housenumber":"137",
    "addr:postcode":"27288",
    "addr:street":"S Hamilton St",
    "iso:country":"US",
    "sg:address":"137 S Hamilton St",
    "sg:city":"Eden",
    "sg:classifiers":[
        {
            "category":"Retail",
            "subcategory":"Auto Repair",
            "type":"Services"
        }
    ],
    "sg:phone":"+1   ",
    "sg:postcode":"27288",
    "sg:province":"NC",
    "sg:tags":[
        "automotive"
    ],
    "wof:name":"Eden Discount Tires",
    "wof:placetype":"venue"
},
  "geometry": {"coordinates":[-79.772741,36.50204],"type":"Point"}
}