{
  "type": "Feature",
  "properties": {
    "addr:full":"5120 Robinhood Rd Winston Salem NC 27106",
    "addr:housenumber":"5120",
    "addr:postcode":"27106",
    "addr:street":"Robinhood Rd",
    "iso:country":"US",
    "sg:address":"5120 Robinhood Rd",
    "sg:city":"Winston Salem",
    "sg:classifiers":[
        {
            "category":"Professional",
            "subcategory":"Secretarial Services",
            "type":"Services"
        }
    ],
    "sg:phone":"+1   ",
    "sg:postcode":"27106",
    "sg:province":"NC",
    "sg:tags":[
        "reporting"
    ],
    "wof:name":"Minority Designers & Technical",
    "wof:placetype":"venue"
},
  "geometry": {"coordinates":[-80.36544499999999,36.120158],"type":"Point"}
}