{
  "type": "Feature",
  "properties": {
    "addr:full":"206 Transco Rd Mooresville NC 28117",
    "addr:housenumber":"206",
    "addr:postcode":"28117",
    "addr:street":"Transco Rd",
    "iso:country":"US",
    "sg:address":"206 Transco Rd",
    "sg:city":"Mooresville",
    "sg:classifiers":[
        {
            "category":"Wholesale",
            "subcategory":"Furniture",
            "type":"Manufacturing & Wholesale Goods"
        },
        {
            "category":"Home & Garden",
            "subcategory":"Carpets & Floor Coverings",
            "type":"Retail Goods"
        },
        {
            "category":"Home & Garden",
            "subcategory":"Furniture",
            "type":"Retail Goods"
        }
    ],
    "sg:phone":"+1 704 896 8904",
    "sg:postcode":"28117",
    "sg:province":"NC",
    "sg:tags":[
        "store",
        "rug",
        "furniture-wholesale",
        "manufacturer"
    ],
    "sg:website":"http://www.dunrovenhouse.com",
    "wof:name":"Dunroven House",
    "wof:placetype":"venue"
},
  "geometry": {"coordinates":[-80.857831,35.521573],"type":"Point"}
}