{
  "type": "Feature",
  "properties": {
    "addr:full":"3622 Curtland Pl NW Concord NC 28027",
    "addr:housenumber":"3622",
    "addr:postcode":"28027",
    "addr:street":"Curtland Pl Nw",
    "iso:country":"US",
    "sg:address":"3622 Curtland Pl NW",
    "sg:city":"Concord",
    "sg:classifiers":[
        {
            "category":"Freight",
            "type":"Transportation"
        }
    ],
    "sg:phone":"+1 704 788 6537",
    "sg:postcode":"28027",
    "sg:province":"NC",
    "sg:tags":[
        "operator",
        "local",
        "trucking"
    ],
    "wof:name":"Dryclean Delivery",
    "wof:placetype":"venue"
},
  "geometry": {"coordinates":[-80.637745,35.43099],"type":"Point"}
}