{
  "type": "Feature",
  "properties": {
    "addr:full":"5017 New Hope Church Rd Monroe NC 28110",
    "addr:housenumber":"5017",
    "addr:postcode":"28110",
    "addr:street":"New Hope Church Rd",
    "iso:country":"US",
    "sg:address":"5017 New Hope Church Rd",
    "sg:city":"Monroe",
    "sg:classifiers":[
        {
            "category":"Building & Trades",
            "subcategory":"Plumbing",
            "type":"Services"
        }
    ],
    "sg:phone":"+1 704 753 1379",
    "sg:postcode":"28110",
    "sg:province":"NC",
    "sg:tags":[
        "contractor"
    ],
    "wof:name":"Greene Plumbing Co Monroe",
    "wof:placetype":"venue"
},
  "geometry": {"coordinates":[-80.419166,35.116716],"type":"Point"}
}