{
  "type": "Feature",
  "properties": {
    "iso:country":"US",
    "sg:address":"116 Crutchfield St",
    "sg:city":"Durham",
    "sg:classifiers":[
        {
            "category":"Health Services",
            "subcategory":"Optometrist",
            "type":"Services"
        }
    ],
    "sg:phone":"+1   ",
    "sg:postcode":"27704",
    "sg:province":"NC",
    "sg:tags":[
        "medical"
    ],
    "wof:name":"Wilcox William D MD PA",
    "wof:placetype":"venue"
},
  "geometry": {"coordinates":[-78.900589,36.038863],"type":"Point"}
}