{
  "type": "Feature",
  "properties": {
    "iso:country":"US",
    "sg:address":"3420 S College Rd",
    "sg:city":"Wilmington",
    "sg:classifiers":[
        {
            "category":"Personal",
            "subcategory":"Beauty Salon",
            "type":"Services"
        }
    ],
    "sg:phone":"+1   ",
    "sg:postcode":"28412",
    "sg:province":"NC",
    "sg:tags":[
        "shop"
    ],
    "wof:name":"Hair By Hallie",
    "wof:placetype":"venue"
},
  "geometry": {"coordinates":[-77.891094,34.181604],"type":"Point"}
}