{
  "type": "Feature",
  "properties": {
    "addr:full":"289 Indian Ridge Trl Hendersonville NC 28739",
    "addr:housenumber":"289",
    "addr:postcode":"28739",
    "addr:street":"Indian Ridge Trl",
    "iso:country":"US",
    "sg:address":"289 Indian Ridge Trl",
    "sg:city":"Hendersonville",
    "sg:classifiers":[
        {
            "category":"Real Estate",
            "subcategory":"Real Estate Operator",
            "type":"Services"
        }
    ],
    "sg:phone":"+1 828 712 8503",
    "sg:postcode":"28739",
    "sg:province":"NC",
    "sg:tags":[
        "building",
        "nonresidential"
    ],
    "wof:name":"NC Properties",
    "wof:placetype":"venue"
},
  "geometry": {"coordinates":[-82.60722199999999,35.275063],"type":"Point"}
}