{
  "type": "Feature",
  "properties": {
    "iso:country":"US",
    "sg:address":"848 Highland Ave SE",
    "sg:city":"Hickory",
    "sg:classifiers":[
        {
            "category":"Building & Trades",
            "subcategory":"Construction",
            "type":"Services"
        }
    ],
    "sg:phone":"+1 828 327 6677",
    "sg:postcode":"28602",
    "sg:province":"NC",
    "sg:tags":[
        "general",
        "contractor"
    ],
    "sg:website":"www.building-system.com",
    "wof:name":"Building Systems Of Catawba",
    "wof:placetype":"venue"
},
  "geometry": {"coordinates":[-81.327307,35.734094],"type":"Point"}
}