{
  "type": "Feature",
  "properties": {
    "iso:country":"US",
    "sg:address":"1007 Slater Rd",
    "sg:city":"Durham",
    "sg:classifiers":[
        {
            "category":"Restaurant",
            "type":"Food & Drink"
        }
    ],
    "sg:phone":"+1 919 474 8647",
    "sg:postcode":"27703",
    "sg:province":"NC",
    "wof:name":"Chelsea Cafe",
    "wof:placetype":"venue"
},
  "geometry": {"coordinates":[-78.846284,35.879265],"type":"Point"}
}