{
  "type": "Feature",
  "properties": {
    "addr:full":"1584 Yanceyville St Greensboro NC 27405",
    "addr:housenumber":"1584",
    "addr:postcode":"27405",
    "addr:street":"Yanceyville St",
    "iso:country":"US",
    "sg:address":"1584 Yanceyville St",
    "sg:city":"Greensboro",
    "sg:classifiers":[
        {
            "category":"Government",
            "subcategory":"Office",
            "type":"Public Place"
        }
    ],
    "sg:phone":"+1 336 334 3297",
    "sg:postcode":"27405",
    "sg:province":"NC",
    "sg:website":"www.ncdot.org",
    "wof:name":"Transportation-Resident Engr",
    "wof:placetype":"venue"
},
  "geometry": {"coordinates":[-79.782376,36.08867],"type":"Point"}
}