{
  "type": "Feature",
  "properties": {
    "addr:full":"2785 Hollybrook Ln Morganton NC 28655",
    "addr:housenumber":"2785",
    "addr:postcode":"28655",
    "addr:street":"Hollybrook Ln",
    "iso:country":"US",
    "sg:address":"2785 Hollybrook Ln",
    "sg:city":"Morganton",
    "sg:classifiers":[
        {
            "category":"Building & Trades",
            "subcategory":"Construction",
            "type":"Services"
        }
    ],
    "sg:phone":"+1 828 430 3223",
    "sg:postcode":"28655",
    "sg:province":"NC",
    "sg:tags":[
        "house"
    ],
    "wof:name":"Slate Construction",
    "wof:placetype":"venue"
},
  "geometry": {"coordinates":[-81.760364,35.817457],"type":"Point"}
}