{
  "type": "Feature",
  "properties": {
    "addr:full":"898 Ayersville Rd Mayodan NC 27027",
    "addr:housenumber":"898",
    "addr:postcode":"27027",
    "addr:street":"Ayersville Rd",
    "iso:country":"US",
    "sg:address":"898 Ayersville Rd",
    "sg:city":"Mayodan",
    "sg:classifiers":[
        {
            "category":"Home & Garden",
            "subcategory":"Garden Supply",
            "type":"Retail Goods"
        }
    ],
    "sg:phone":"+1 336 427 5657",
    "sg:postcode":"27027",
    "sg:province":"NC",
    "sg:tags":[
        "hardware",
        "repair"
    ],
    "wof:name":"Dougs Mower & Saw Shop",
    "wof:placetype":"venue"
},
  "geometry": {"coordinates":[-79.98175999999999,36.420469],"type":"Point"}
}