{
  "type": "Feature",
  "properties": {
    "iso:country":"US",
    "sg:address":"848 S Main St",
    "sg:city":"Graham",
    "sg:classifiers":[
        {
            "category":"Personal",
            "subcategory":"Beauty Salon",
            "type":"Services"
        }
    ],
    "sg:phone":"+1 336 228 0001",
    "sg:postcode":"27253",
    "sg:province":"NC",
    "wof:name":"Michaldawns Hair Studio",
    "wof:placetype":"venue"
},
  "geometry": {"coordinates":[-79.400178,36.059169],"type":"Point"}
}