{
  "type": "Feature",
  "properties": {
    "iso:country":"US",
    "sg:address":"2101 N Main St",
    "sg:city":"Kannapolis",
    "sg:classifiers":[
        {
            "category":"Retail",
            "subcategory":"Auto Repair",
            "type":"Services"
        }
    ],
    "sg:phone":"+1 704 933 5541",
    "sg:postcode":"28081",
    "sg:province":"NC",
    "sg:tags":[
        "body"
    ],
    "wof:name":"Kings Auto Body Co Inc",
    "wof:placetype":"venue"
},
  "geometry": {"coordinates":[-80.61427999999999,35.523264],"type":"Point"}
}