{
  "type": "Feature",
  "properties": {
    "iso:country":"US",
    "sg:address":"207 Phillips Ave",
    "sg:city":"Red Springs",
    "sg:classifiers":[
        {
            "category":"Education",
            "subcategory":"School",
            "type":"Public Place"
        }
    ],
    "sg:phone":"+1 910 843 9704",
    "sg:postcode":"28377",
    "sg:province":"NC",
    "sg:tags":[
        "academic",
        "special"
    ],
    "wof:name":"Created For You Learning Ctr",
    "wof:placetype":"venue"
},
  "geometry": {"coordinates":[-79.188393,34.811145],"type":"Point"}
}