{
  "type": "Feature",
  "properties": {
    "addr:full":"14328 State Hwy 210 Rocky Point NC 28457",
    "addr:housenumber":"14328",
    "addr:postcode":"28457",
    "addr:street":"State Hwy 210",
    "iso:country":"US",
    "sg:address":"14328 State Hwy 210",
    "sg:city":"Rocky Point",
    "sg:classifiers":[
        {
            "category":"Education",
            "subcategory":"School",
            "type":"Public Place"
        }
    ],
    "sg:phone":"+1 910 602 6810",
    "sg:postcode":"28457",
    "sg:province":"NC",
    "sg:website":"www.edline.net",
    "wof:name":"Heide Trask Senior High School",
    "wof:placetype":"venue"
},
  "geometry": {"coordinates":[-77.889729,34.434452],"type":"Point"}
}