{
  "type": "Feature",
  "properties": {
    "addr:full":"5862 Hunting Ridge Rd Hope Mills NC 28348",
    "addr:housenumber":"5862",
    "addr:postcode":"28348",
    "addr:street":"Hunting Ridge Rd",
    "iso:country":"US",
    "sg:address":"5862 Hunting Ridge Rd",
    "sg:city":"Hope Mills",
    "sg:classifiers":[
        {
            "category":"Retail",
            "subcategory":"Car Wash",
            "type":"Services"
        }
    ],
    "sg:phone":"+1 910 425 2009",
    "sg:postcode":"28348",
    "sg:province":"NC",
    "sg:tags":[
        "automobile",
        "detail",
        "clean"
    ],
    "wof:name":"Washington's Detailing",
    "wof:placetype":"venue"
},
  "geometry": {"coordinates":[-78.966944,34.976985],"type":"Point"}
}