{
  "type": "Feature",
  "properties": {
    "iso:country":"US",
    "sg:address":"128 Bryan Pl",
    "sg:city":"Jacksonville",
    "sg:classifiers":[
        {
            "category":"Building & Trades",
            "subcategory":"Construction",
            "type":"Services"
        }
    ],
    "sg:phone":"+1 910 346 3754",
    "sg:postcode":"28540",
    "sg:province":"NC",
    "sg:tags":[
        "wallpaper"
    ],
    "wof:name":"Paper Dolls Wall Covering Svc",
    "wof:placetype":"venue"
},
  "geometry": {"coordinates":[-77.40794200000001,34.759326],"type":"Point"}
}