{
  "type": "Feature",
  "properties": {
    "iso:country":"US",
    "sg:address":"318 Maness Rd",
    "sg:city":"Star",
    "sg:classifiers":[
        {
            "category":"Building & Trades",
            "subcategory":"Construction",
            "type":"Services"
        }
    ],
    "sg:phone":"+1 910 572 5406",
    "sg:postcode":"27356",
    "sg:province":"NC",
    "sg:tags":[
        "contractor"
    ],
    "wof:name":"David Smith Masonry",
    "wof:placetype":"venue"
},
  "geometry": {"coordinates":[-79.842951,35.472905],"type":"Point"}
}