{
  "type": "Feature",
  "properties": {
    "iso:country":"US",
    "sg:address":"6345 Cook Ave",
    "sg:city":"Clemmons",
    "sg:classifiers":[
        {
            "category":"Professional",
            "type":"Services"
        }
    ],
    "sg:phone":"+1   ",
    "sg:postcode":"27012",
    "sg:province":"NC",
    "wof:name":"B 4 & After Services Inc",
    "wof:placetype":"venue"
},
  "geometry": {"coordinates":[-80.37993400000001,36.027631],"type":"Point"}
}