{
  "type": "Feature",
  "properties": {
    "iso:country":"US",
    "sg:address":"1229 E Franklin St",
    "sg:city":"Chapel Hill",
    "sg:classifiers":[
        {
            "category":"Manufacturing",
            "subcategory":"Leather Goods",
            "type":"Manufacturing & Wholesale Goods"
        },
        {
            "category":"Shopping",
            "subcategory":"Luggage & Leather Goods",
            "type":"Retail Goods"
        }
    ],
    "sg:phone":"+1 919 929 2620",
    "sg:postcode":"27514",
    "sg:province":"NC",
    "wof:name":"Florenza Leathergoods & Luggage",
    "wof:placetype":"venue"
},
  "geometry": {"coordinates":[-79.0382,35.924702],"type":"Point"}
}