{
  "type": "Feature",
  "properties": {
    "addr:full":"2319 Statesville Hwy Mooresville NC 28115",
    "addr:housenumber":"2319",
    "addr:postcode":"28115",
    "addr:street":"Statesville Hwy",
    "iso:country":"US",
    "sg:address":"2319 Statesville Hwy",
    "sg:city":"Mooresville",
    "sg:classifiers":[
        {
            "category":"Shopping",
            "subcategory":"Bicycles & Sporting Goods",
            "type":"Retail Goods"
        }
    ],
    "sg:phone":"+1 704 658 9355",
    "sg:postcode":"28115",
    "sg:province":"NC",
    "sg:tags":[
        "gun",
        "gunsmith"
    ],
    "wof:name":"Set Your Sights Gunsmithing",
    "wof:placetype":"venue"
},
  "geometry": {"coordinates":[-80.815991,35.607628],"type":"Point"}
}