{
  "type": "Feature",
  "properties": {
    "addr:full":"600 Alligator Rd Vanceboro NC 28586",
    "addr:housenumber":"600",
    "addr:postcode":"28586",
    "addr:street":"Alligator Rd",
    "iso:country":"US",
    "sg:address":"600 Alligator Rd",
    "sg:city":"Vanceboro",
    "sg:classifiers":[
        {
            "category":"Government",
            "subcategory":"Office",
            "type":"Public Place"
        }
    ],
    "sg:phone":"+1 252 244 3337",
    "sg:postcode":"28586",
    "sg:province":"NC",
    "sg:website":"www.doc.state.nc.us",
    "wof:name":"Correction Dept",
    "wof:placetype":"venue"
},
  "geometry": {"coordinates":[-77.124832,35.318892],"type":"Point"}
}