{
  "type": "Feature",
  "properties": {
    "iso:country":"US",
    "sg:address":"104 Arbor Dr",
    "sg:city":"Elon College",
    "sg:classifiers":[
        {
            "category":"Wholesale",
            "subcategory":"Motor Vehicles",
            "type":"Manufacturing & Wholesale Goods"
        }
    ],
    "sg:phone":"+1 336 446 0636",
    "sg:postcode":"27244",
    "sg:province":"NC",
    "wof:name":"Transam",
    "wof:placetype":"venue"
},
  "geometry": {"coordinates":[-79.53426899999999,36.087927],"type":"Point"}
}