{
  "type": "Feature",
  "properties": {
    "addr:full":"3500 Borum Dr Winston Salem NC 27107",
    "addr:postcode":"3500;27107",
    "addr:street":"Borum Dr",
    "iso:country":"US",
    "sg:address":"3500 Borum Dr",
    "sg:city":"Winston Salem",
    "sg:classifiers":[
        {
            "category":"Building & Trades",
            "subcategory":"Cleaning & Sanitation",
            "type":"Services"
        }
    ],
    "sg:phone":"+1   ",
    "sg:postcode":"27107",
    "sg:province":"NC",
    "sg:tags":[
        "maintenance"
    ],
    "wof:name":"Two Girls & A Mop Inc",
    "wof:placetype":"venue"
},
  "geometry": {"coordinates":[-80.162194,36.05053],"type":"Point"}
}