{
  "type": "Feature",
  "properties": {
    "addr:full":"80 East Rd Pittsboro NC 27312",
    "addr:housenumber":"80",
    "addr:postcode":"27312",
    "addr:street":"East Rd",
    "iso:country":"US",
    "sg:address":"80 East Rd",
    "sg:city":"Pittsboro",
    "sg:classifiers":[
        {
            "category":"Government",
            "subcategory":"Office",
            "type":"Public Place"
        }
    ],
    "sg:phone":"+1 919 542 8220",
    "sg:postcode":"27312",
    "sg:province":"NC",
    "sg:tags":[
        "county",
        "administrative",
        "program",
        "health"
    ],
    "wof:name":"Chatham County Health Clinic",
    "wof:placetype":"venue"
},
  "geometry": {"coordinates":[-79.182427,35.773165],"type":"Point"}
}