{
  "type": "Feature",
  "properties": {
    "iso:country":"US",
    "sg:address":"136 Wind Chime Ct",
    "sg:city":"Raleigh",
    "sg:classifiers":[
        {
            "category":"Wholesale",
            "subcategory":"Durable Goods & Equipment",
            "type":"Manufacturing & Wholesale Goods"
        }
    ],
    "sg:phone":"+1 919 847 4002",
    "sg:postcode":"27615",
    "sg:province":"NC",
    "sg:tags":[
        "representative",
        "manufacturer"
    ],
    "wof:name":"Allstate Lighting",
    "wof:placetype":"venue"
},
  "geometry": {"coordinates":[-78.64254800000001,35.874813],"type":"Point"}
}