{
  "type": "Feature",
  "properties": {
    "iso:country":"US",
    "sg:address":"535 Sanders Dr",
    "sg:city":"Wilmington",
    "sg:classifiers":[
        {
            "category":"Building & Trades",
            "subcategory":"Construction",
            "type":"Services"
        }
    ],
    "sg:phone":"+1 910 792 7666",
    "sg:postcode":"28412",
    "sg:province":"NC",
    "sg:tags":[
        "residential",
        "general",
        "contractor"
    ],
    "wof:name":"No Limit Framing",
    "wof:placetype":"venue"
},
  "geometry": {"coordinates":[-77.914975,34.123679],"type":"Point"}
}