{
  "type": "Feature",
  "properties": {
    "addr:full":"4013 George V Strong Wynd Raleigh NC 27612",
    "addr:housenumber":"4013",
    "addr:postcode":"27612",
    "addr:street":"George V Strong Wynd",
    "iso:country":"US",
    "sg:address":"4013 George V Strong Wynd",
    "sg:city":"Raleigh",
    "sg:classifiers":[
        {
            "category":"Professional",
            "subcategory":"Management & Consulting",
            "type":"Services"
        }
    ],
    "sg:phone":"+1   ",
    "sg:postcode":"27612",
    "sg:province":"NC",
    "sg:tags":[
        "business"
    ],
    "wof:name":"Retail Technology Intl",
    "wof:placetype":"venue"
},
  "geometry": {"coordinates":[-78.71133500000001,35.834224],"type":"Point"}
}