{
  "type": "Feature",
  "properties": {
    "iso:country":"US",
    "sg:address":"104 E Main St",
    "sg:city":"Stoneville",
    "sg:classifiers":[
        {
            "category":"Manufacturing",
            "subcategory":"Printing",
            "type":"Manufacturing & Wholesale Goods"
        }
    ],
    "sg:phone":"+1 336 573 1300",
    "sg:postcode":"27048",
    "sg:province":"NC",
    "sg:tags":[
        "screen"
    ],
    "wof:name":"Designed Image",
    "wof:placetype":"venue"
},
  "geometry": {"coordinates":[-79.903339,36.466432],"type":"Point"}
}