{
  "type": "Feature",
  "properties": {
    "iso:country":"US",
    "sg:address":"112 Ridge Way Ln",
    "sg:city":"Clayton",
    "sg:classifiers":[
        {
            "category":"Banks & Credit Unions",
            "subcategory":"Investment Brokerage",
            "type":"Services"
        }
    ],
    "sg:phone":"+1 919 989 8390",
    "sg:postcode":"27520",
    "sg:province":"NC",
    "sg:tags":[
        "security"
    ],
    "wof:name":"Alliance Capital Inc",
    "wof:placetype":"venue"
},
  "geometry": {"coordinates":[-78.542025,35.568223],"type":"Point"}
}