{
  "type": "Feature",
  "properties": {
    "iso:country":"US",
    "sg:address":"1368 Dellwood Rd",
    "sg:city":"Waynesville",
    "sg:classifiers":[
        {
            "category":"Home & Garden",
            "subcategory":"Garden Supply",
            "type":"Retail Goods"
        },
        {
            "category":"Building & Trades",
            "subcategory":"Landscaping Services",
            "type":"Services"
        }
    ],
    "sg:phone":"+1 828 926 0925",
    "sg:postcode":"28786",
    "sg:province":"NC",
    "sg:tags":[
        "nurseryman"
    ],
    "wof:name":"Grass Root Gardens Inc",
    "wof:placetype":"venue"
},
  "geometry": {"coordinates":[-82.98863299999999,35.526155],"type":"Point"}
}