{
  "type": "Feature",
  "properties": {
    "addr:full":"1342 Rutledge Ave Charlotte NC 28211",
    "addr:housenumber":"1342",
    "addr:postcode":"28211",
    "addr:street":"Rutledge Ave",
    "iso:country":"US",
    "sg:address":"1342 Rutledge Ave",
    "sg:city":"Charlotte",
    "sg:classifiers":[
        {
            "category":"Manufacturing",
            "subcategory":"Tools & Machinery",
            "type":"Manufacturing & Wholesale Goods"
        }
    ],
    "sg:phone":"+1 704 364 9108",
    "sg:postcode":"28211",
    "sg:province":"NC",
    "sg:tags":[
        "equipment",
        "industrial",
        "mfg"
    ],
    "wof:name":"Torque Assembly Systems Corp",
    "wof:placetype":"venue"
},
  "geometry": {"coordinates":[-80.799634,35.168949],"type":"Point"}
}