{
  "type": "Feature",
  "properties": {
    "addr:full":"1021 Plantation Dr Cary NC 27511",
    "addr:housenumber":"1021",
    "addr:postcode":"27511",
    "addr:street":"Plantation Dr",
    "iso:country":"US",
    "sg:address":"1021 Plantation Dr",
    "sg:city":"Cary",
    "sg:classifiers":[
        {
            "category":"Building & Trades",
            "subcategory":"Construction",
            "type":"Services"
        }
    ],
    "sg:phone":"+1 919 266 6633",
    "sg:postcode":"27511",
    "sg:province":"NC",
    "sg:tags":[
        "house"
    ],
    "wof:name":"Dreamquest Inc",
    "wof:placetype":"venue"
},
  "geometry": {"coordinates":[-78.795407,35.769931],"type":"Point"}
}