{
  "type": "Feature",
  "properties": {
    "iso:country":"US",
    "sg:address":"100 S Water St",
    "sg:city":"Elizabeth City",
    "sg:classifiers":[
        {
            "category":"Retail",
            "subcategory":"Laundry & Dry Cleaning",
            "type":"Services"
        }
    ],
    "sg:phone":"+1 252 338 6196",
    "sg:postcode":"27909",
    "sg:province":"NC",
    "sg:tags":[
        "cleaner"
    ],
    "wof:name":"Rochelle Cleaners Inc",
    "wof:placetype":"venue"
},
  "geometry": {"coordinates":[-76.21876399999999,36.299636],"type":"Point"}
}