{
  "type": "Feature",
  "properties": {
    "addr:full":"1538 Ridge St South Boston NC 24592",
    "addr:housenumber":"1538",
    "addr:postcode":"24592",
    "addr:street":"Ridge St",
    "iso:country":"US",
    "sg:address":"1538 Ridge St",
    "sg:city":"South Boston",
    "sg:classifiers":[
        {
            "category":"Organizations",
            "subcategory":"Religious Organization",
            "type":"Services"
        }
    ],
    "sg:phone":"+1 434 572 8454",
    "sg:postcode":"24592",
    "sg:province":"NC",
    "wof:name":"United Temple of God",
    "wof:placetype":"venue"
},
  "geometry": {"coordinates":[-78.899895,36.714761],"type":"Point"}
}