{
  "type": "Feature",
  "properties": {
    "addr:full":"435 Woodington Rd Kinston NC 28504",
    "addr:housenumber":"435",
    "addr:postcode":"28504",
    "addr:street":"Woodington Rd",
    "iso:country":"US",
    "sg:address":"435 Woodington Rd",
    "sg:city":"Kinston",
    "sg:classifiers":[
        {
            "category":"Freight",
            "type":"Transportation"
        }
    ],
    "sg:phone":"+1 252 527 3376",
    "sg:postcode":"28504",
    "sg:province":"NC",
    "sg:tags":[
        "operator",
        "local",
        "trucking"
    ],
    "wof:name":"Sk Riggsbee Trucking Inc",
    "wof:placetype":"venue"
},
  "geometry": {"coordinates":[-77.61890099999999,35.182479],"type":"Point"}
}