{
  "type": "Feature",
  "properties": {
    "iso:country":"US",
    "sg:address":"1414 Ellen St",
    "sg:city":"Monroe",
    "sg:classifiers":[
        {
            "category":"Health Services",
            "subcategory":"Doctor",
            "type":"Services"
        }
    ],
    "sg:phone":"+1 704 283 8811",
    "sg:postcode":"28112",
    "sg:province":"NC",
    "sg:tags":[
        "physician",
        "surgeon"
    ],
    "wof:name":"Neurology EMG & Pain Clinic",
    "wof:placetype":"venue"
},
  "geometry": {"coordinates":[-80.521997,34.972757],"type":"Point"}
}