{
  "type": "Feature",
  "properties": {
    "iso:country":"US",
    "sg:address":"108 Eastview Dr",
    "sg:city":"Lexington",
    "sg:classifiers":[
        {
            "category":"Utilities",
            "subcategory":"Fuel Oil & Lpg",
            "type":"Services"
        }
    ],
    "sg:phone":"+1 336 249 2276",
    "sg:postcode":"27292",
    "sg:province":"NC",
    "sg:tags":[
        "dealer"
    ],
    "wof:name":"Lindsay Younts",
    "wof:placetype":"venue"
},
  "geometry": {"coordinates":[-80.210689,35.793364],"type":"Point"}
}