{
  "type": "Feature",
  "properties": {
    "iso:country":"US",
    "sg:address":"2950 S Memorial Dr",
    "sg:city":"Greenville",
    "sg:classifiers":[
        {
            "category":"Organizations",
            "subcategory":"Religious Organization",
            "type":"Services"
        }
    ],
    "sg:phone":"+1 252 757 3033",
    "sg:postcode":"27834",
    "sg:province":"NC",
    "sg:tags":[
        "church"
    ],
    "wof:name":"United Pentecostal Church",
    "wof:placetype":"venue"
},
  "geometry": {"coordinates":[-77.396911,35.580983],"type":"Point"}
}