{
  "type": "Feature",
  "properties": {
    "iso:country":"US",
    "sg:address":"1014 Roanoke Ave",
    "sg:city":"Roanoke Rapids",
    "sg:classifiers":[
        {
            "category":"Real Estate",
            "subcategory":"Real Estate Agent",
            "type":"Services"
        }
    ],
    "sg:phone":"+1 252 537 8919",
    "sg:postcode":"27870",
    "sg:province":"NC",
    "sg:tags":[
        "management"
    ],
    "wof:name":"Dixon Realty",
    "wof:placetype":"venue"
},
  "geometry": {"coordinates":[-77.657191,36.455823],"type":"Point"}
}