{
  "type": "Feature",
  "properties": {
    "iso:country":"US",
    "sg:address":"2207 Lancey Dr",
    "sg:city":"Thomasville",
    "sg:classifiers":[
        {
            "category":"Retail",
            "subcategory":"Repair Shop",
            "type":"Services"
        }
    ],
    "sg:phone":"+1 336 882 3902",
    "sg:postcode":"27360",
    "sg:province":"NC",
    "sg:tags":[
        "welding"
    ],
    "wof:name":"Triad Welding Contractors",
    "wof:placetype":"venue"
},
  "geometry": {"coordinates":[-80.050679,35.940895],"type":"Point"}
}