{
  "type": "Feature",
  "properties": {
    "addr:full":"110 Marin Dr Chapel Hill NC 27516",
    "addr:housenumber":"110",
    "addr:postcode":"27516",
    "addr:street":"Marin Dr",
    "iso:country":"US",
    "sg:address":"110 Marin Dr",
    "sg:city":"Chapel Hill",
    "sg:classifiers":[
        {
            "category":"Professional",
            "subcategory":"Management & Consulting",
            "type":"Services"
        }
    ],
    "sg:phone":"+1   ",
    "sg:postcode":"27516",
    "sg:province":"NC",
    "sg:tags":[
        "business"
    ],
    "wof:name":"Ambrosia International Corp",
    "wof:placetype":"venue"
},
  "geometry": {"coordinates":[-79.070054,35.893529],"type":"Point"}
}