{
  "type": "Feature",
  "properties": {
    "addr:full":"122 E Main St Durham NC 27701",
    "addr:housenumber":"122",
    "addr:postcode":"27701",
    "addr:street":"E Main St",
    "iso:country":"US",
    "sg:address":"122 E Main St",
    "sg:city":"Durham",
    "sg:classifiers":[
        {
            "category":"Professional",
            "subcategory":"Lawyer & Legal Services",
            "type":"Services"
        }
    ],
    "sg:phone":"+1 919 683 6229",
    "sg:postcode":"27701",
    "sg:province":"NC",
    "sg:tags":[
        "attorney"
    ],
    "wof:name":"Zabrina White Dempson Law Ofc",
    "wof:placetype":"venue"
},
  "geometry": {"coordinates":[-78.899767,35.994475],"type":"Point"}
}