{
  "type": "Feature",
  "properties": {
    "iso:country":"US",
    "sg:address":"608 Holly Springs Rd",
    "sg:city":"Holly Springs",
    "sg:classifiers":[
        {
            "category":"Health Services",
            "subcategory":"Optometrist",
            "type":"Services"
        }
    ],
    "sg:phone":"+1 919 577 3937",
    "sg:postcode":"27540",
    "sg:province":"NC",
    "wof:name":"Holly Springs Eye Assoc",
    "wof:placetype":"venue"
},
  "geometry": {"coordinates":[-78.82655200000001,35.654709],"type":"Point"}
}