{
  "type": "Feature",
  "properties": {
    "iso:country":"US",
    "sg:address":"584 Talbott Rd",
    "sg:city":"Blanch",
    "sg:classifiers":[
        {
            "category":"Organizations",
            "subcategory":"Membership Organization",
            "type":"Services"
        }
    ],
    "sg:phone":"+1   ",
    "sg:postcode":"27212",
    "sg:province":"NC",
    "wof:name":"Star Hoopers of Tomorrow",
    "wof:placetype":"venue"
},
  "geometry": {"coordinates":[-79.331879,36.493411],"type":"Point"}
}