{
  "type": "Feature",
  "properties": {
    "iso:country":"US",
    "sg:address":"6409 Rutherglen Dr",
    "sg:city":"Fayetteville",
    "sg:classifiers":[
        {
            "category":"Professional",
            "subcategory":"Business Services",
            "type":"Services"
        }
    ],
    "sg:phone":"+1   ",
    "sg:postcode":"28304",
    "sg:province":"NC",
    "wof:name":"L & M Group Homes Inc",
    "wof:placetype":"venue"
},
  "geometry": {"coordinates":[-78.992597,35.028511],"type":"Point"}
}