{
  "type": "Feature",
  "properties": {
    "addr:full":"792 N Luther Rd Candler NC 28715",
    "addr:housenumber":"792",
    "addr:postcode":"28715",
    "addr:street":"N Luther Rd",
    "iso:country":"US",
    "sg:address":"792 N Luther Rd",
    "sg:city":"Candler",
    "sg:classifiers":[
        {
            "category":"Personal",
            "subcategory":"Beauty Salon",
            "type":"Services"
        }
    ],
    "sg:phone":"+1 828 667 8579",
    "sg:postcode":"28715",
    "sg:province":"NC",
    "wof:name":"Charlie's Family Hair & Nail",
    "wof:placetype":"venue"
},
  "geometry": {"coordinates":[-82.749151,35.548662],"type":"Point"}
}