{
  "type": "Feature",
  "properties": {
    "addr:full":"119 Abron Ct Kitty Hawk NC 27949",
    "addr:housenumber":"119",
    "addr:postcode":"27949",
    "addr:street":"Abron Ct",
    "iso:country":"US",
    "sg:address":"119 Abron Ct",
    "sg:city":"Kitty Hawk",
    "sg:classifiers":[
        {
            "category":"Real Estate",
            "subcategory":"Architect",
            "type":"Services"
        }
    ],
    "sg:phone":"+1 252 255 1093",
    "sg:postcode":"27949",
    "sg:province":"NC",
    "wof:name":"Morrisette Architecture",
    "wof:placetype":"venue"
},
  "geometry": {"coordinates":[-75.745779,36.152922],"type":"Point"}
}