{
  "type": "Feature",
  "properties": {
    "iso:country":"US",
    "sg:address":"5920 Wrightsville Ave",
    "sg:city":"Wilmington",
    "sg:classifiers":[
        {
            "category":"Bars & Pubs",
            "type":"Food & Drink"
        }
    ],
    "sg:phone":"+1 910 799 6253",
    "sg:postcode":"28403",
    "sg:province":"NC",
    "sg:tags":[
        "drinking"
    ],
    "wof:name":"Triangle Lounge",
    "wof:placetype":"venue"
},
  "geometry": {"coordinates":[-77.849011,34.216844],"type":"Point"}
}