{
  "type": "Feature",
  "properties": {
    "addr:full":"7804 Alison Ct Raleigh NC 27615",
    "addr:housenumber":"7804",
    "addr:postcode":"27615",
    "addr:street":"Alison Ct",
    "iso:country":"US",
    "sg:address":"7804 Alison Ct",
    "sg:city":"Raleigh",
    "sg:classifiers":[
        {
            "category":"Social Services",
            "subcategory":"Child Care",
            "type":"Services"
        }
    ],
    "sg:phone":"+1   ",
    "sg:postcode":"27615",
    "sg:province":"NC",
    "sg:tags":[
        "day"
    ],
    "wof:name":"Buzzy Bee Pre School",
    "wof:placetype":"venue"
},
  "geometry": {"coordinates":[-78.643123,35.884266],"type":"Point"}
}