{
  "type": "Feature",
  "properties": {
    "addr:full":"895 Joe Hege Rd Clemmons NC 27012",
    "addr:housenumber":"895",
    "addr:postcode":"27012",
    "addr:street":"Joe Hege Rd",
    "iso:country":"US",
    "sg:address":"895 Joe Hege Rd",
    "sg:city":"Clemmons",
    "sg:classifiers":[
        {
            "category":"Building & Trades",
            "subcategory":"Construction",
            "type":"Services"
        }
    ],
    "sg:phone":"+1 336 775 5315",
    "sg:postcode":"27012",
    "sg:province":"NC",
    "sg:tags":[
        "house"
    ],
    "wof:name":"J & L Builders",
    "wof:placetype":"venue"
},
  "geometry": {"coordinates":[-80.336575,35.941437],"type":"Point"}
}