{
  "type": "Feature",
  "properties": {
    "iso:country":"US",
    "sg:address":"7835 N Point Blvd",
    "sg:city":"Winston Salem",
    "sg:classifiers":[
        {
            "category":"Real Estate",
            "subcategory":"Real Estate Operator",
            "type":"Services"
        }
    ],
    "sg:phone":"+1 336 759 0777",
    "sg:postcode":"27106",
    "sg:province":"NC",
    "sg:tags":[
        "owner",
        "manager",
        "property"
    ],
    "wof:name":"Residence Inn By Marriott",
    "wof:placetype":"venue"
},
  "geometry": {"coordinates":[-80.277959,36.150742],"type":"Point"}
}