{
  "type": "Feature",
  "properties": {
    "addr:full":"2101 Old State Hwy 98 Wake Forest NC 27587",
    "addr:housenumber":"2101",
    "addr:postcode":"27587",
    "addr:street":"Old State Hwy 98",
    "iso:country":"US",
    "sg:address":"2101 Old State Hwy 98",
    "sg:city":"Wake Forest",
    "sg:classifiers":[
        {
            "category":"Communications",
            "subcategory":"Film & Video Production",
            "type":"Services"
        }
    ],
    "sg:phone":"+1 919 562 7052",
    "sg:postcode":"27587",
    "sg:province":"NC",
    "sg:tags":[
        "development",
        "multimedia",
        "interactive"
    ],
    "wof:name":"Insight Studios",
    "wof:placetype":"venue"
},
  "geometry": {"coordinates":[-78.57899500000001,35.966112],"type":"Point"}
}