{
  "type": "Feature",
  "properties": {
    "iso:country":"US",
    "sg:address":"2010 Hamby Mountain Rd",
    "sg:city":"Purlear",
    "sg:classifiers":[
        {
            "category":"Restaurant",
            "type":"Food & Drink"
        }
    ],
    "sg:phone":"+1 336 973 7059",
    "sg:postcode":"28665",
    "sg:province":"NC",
    "sg:tags":[
        "eating"
    ],
    "wof:name":"Savory Affair Catering",
    "wof:placetype":"venue"
},
  "geometry": {"coordinates":[-81.276658,36.159682],"type":"Point"}
}