{
  "type": "Feature",
  "properties": {
    "iso:country":"US",
    "sg:address":"1600 W Roosevelt Blvd",
    "sg:city":"Monroe",
    "sg:classifiers":[
        {
            "category":"Autos & Motor Vehicles",
            "subcategory":"Motorcycle Sales",
            "type":"Retail Goods"
        }
    ],
    "sg:phone":"+1 704 283 9467",
    "sg:postcode":"28110",
    "sg:province":"NC",
    "sg:website":"www.ironhorsemc.com",
    "wof:name":"Iron Horse Motorcycles",
    "wof:placetype":"venue"
},
  "geometry": {"coordinates":[-80.54239099999999,34.99531],"type":"Point"}
}