{
  "type": "Feature",
  "properties": {
    "addr:full":"107 Front St Swansboro NC 28584",
    "addr:housenumber":"107",
    "addr:postcode":"28584",
    "addr:street":"Front St",
    "iso:country":"US",
    "sg:address":"107 Front St",
    "sg:city":"Swansboro",
    "sg:classifiers":[
        {
            "category":"Professional",
            "subcategory":"Lawyer & Legal Services",
            "type":"Services"
        }
    ],
    "sg:phone":"+1 910 326 2020",
    "sg:postcode":"28584",
    "sg:province":"NC",
    "sg:tags":[
        "attorney"
    ],
    "wof:name":"C Jason Humphrey Pa",
    "wof:placetype":"venue"
},
  "geometry": {"coordinates":[-77.11803399999999,34.687569],"type":"Point"}
}