{
  "type": "Feature",
  "properties": {
    "addr:full":"4324 Barringer Dr Charlotte NC 28217",
    "addr:housenumber":"4324",
    "addr:postcode":"28217",
    "addr:street":"Barringer Dr",
    "iso:country":"US",
    "sg:address":"4324 Barringer Dr",
    "sg:city":"Charlotte",
    "sg:classifiers":[
        {
            "category":"Freight",
            "type":"Transportation"
        }
    ],
    "sg:phone":"+1 704 527 6770",
    "sg:postcode":"28217",
    "sg:province":"NC",
    "sg:tags":[
        "broker",
        "trucking"
    ],
    "wof:name":"Registered Transportation Syst",
    "wof:placetype":"venue"
},
  "geometry": {"coordinates":[-80.891609,35.193374],"type":"Point"}
}