{
  "type": "Feature",
  "properties": {
    "iso:country":"US",
    "sg:address":"6309 Bragg Blvd",
    "sg:city":"Fayetteville",
    "sg:classifiers":[
        {
            "category":"Retail",
            "subcategory":"Auto Repair",
            "type":"Services"
        }
    ],
    "sg:phone":"+1   ",
    "sg:postcode":"28303",
    "sg:province":"NC",
    "sg:tags":[
        "general"
    ],
    "wof:name":"F & S Automotive Services",
    "wof:placetype":"venue"
},
  "geometry": {"coordinates":[-78.959327,35.104062],"type":"Point"}
}