{
  "type": "Feature",
  "properties": {
    "iso:country":"US",
    "sg:address":"2601 Appliance Ct",
    "sg:city":"Raleigh",
    "sg:classifiers":[
        {
            "category":"Travel",
            "subcategory":"Hotels & Motels",
            "type":"Entertainment"
        }
    ],
    "sg:phone":"+1 919 807 9970",
    "sg:postcode":"27604",
    "sg:province":"NC",
    "sg:website":"www.extendedstayhotels.com",
    "wof:name":"Homestead Studio Suites Hotel",
    "wof:placetype":"venue"
},
  "geometry": {"coordinates":[-78.59996099999999,35.811038],"type":"Point"}
}