{
  "type": "Feature",
  "properties": {
    "addr:full":"1060 Industrial Park Dr Kernersville NC 27284",
    "addr:housenumber":"1060",
    "addr:postcode":"27284",
    "addr:street":"Industrial Park Dr",
    "iso:country":"US",
    "sg:address":"1060 Industrial Park Dr",
    "sg:city":"Kernersville",
    "sg:classifiers":[
        {
            "category":"Professional",
            "type":"Services"
        }
    ],
    "sg:phone":"+1 336 993 1000",
    "sg:postcode":"27284",
    "sg:province":"NC",
    "sg:tags":[
        "establishment"
    ],
    "wof:name":"Artistry",
    "wof:placetype":"venue"
},
  "geometry": {"coordinates":[-80.048524,36.104463],"type":"Point"}
}