{
  "type": "Feature",
  "properties": {
    "addr:full":"125 Tynch Town Rd Edenton NC 27932",
    "addr:housenumber":"125",
    "addr:postcode":"27932",
    "addr:street":"Tynch Town Rd",
    "iso:country":"US",
    "sg:address":"125 Tynch Town Rd",
    "sg:city":"Edenton",
    "sg:classifiers":[
        {
            "category":"Building & Trades",
            "subcategory":"Landscaping Services",
            "type":"Services"
        }
    ],
    "sg:phone":"+1 252 482 1100",
    "sg:postcode":"27932",
    "sg:province":"NC",
    "sg:tags":[
        "landscape"
    ],
    "wof:name":"DNE Landscaping",
    "wof:placetype":"venue"
},
  "geometry": {"coordinates":[-76.706523,36.14963],"type":"Point"}
}