{
  "type": "Feature",
  "properties": {
    "addr:full":"905 N State St Raleigh NC 27604",
    "addr:housenumber":"905",
    "addr:postcode":"27604",
    "addr:street":"N State St",
    "iso:country":"US",
    "sg:address":"905 N State St",
    "sg:city":"Raleigh",
    "sg:classifiers":[
        {
            "category":"Building & Trades",
            "subcategory":"Plumbing",
            "type":"Services"
        }
    ],
    "sg:phone":"+1 919 832 7067",
    "sg:postcode":"27604",
    "sg:province":"NC",
    "sg:tags":[
        "contractor"
    ],
    "wof:name":"Hopkins Plumbing & Repair",
    "wof:placetype":"venue"
},
  "geometry": {"coordinates":[-78.62054500000001,35.791772],"type":"Point"}
}