{
  "type": "Feature",
  "properties": {
    "addr:full":"2304 Beechridge Rd Raleigh NC 27608",
    "addr:housenumber":"2304",
    "addr:postcode":"27608",
    "addr:street":"Beechridge Rd",
    "iso:country":"US",
    "sg:address":"2304 Beechridge Rd",
    "sg:city":"Raleigh",
    "sg:classifiers":[
        {
            "category":"Shopping",
            "subcategory":"Clothing, Apparel, & Fashions",
            "type":"Retail Goods"
        }
    ],
    "sg:phone":"+1 919 787 8170",
    "sg:postcode":"27608",
    "sg:province":"NC",
    "wof:name":"Smith Lefort Collections",
    "wof:placetype":"venue"
},
  "geometry": {"coordinates":[-78.644763,35.811303],"type":"Point"}
}