{
  "type": "Feature",
  "properties": {
    "addr:full":"401 E Broad St Dunn NC 28334",
    "addr:housenumber":"401",
    "addr:postcode":"28334",
    "addr:street":"E Broad St",
    "iso:country":"US",
    "sg:address":"401 E Broad St",
    "sg:city":"Dunn",
    "sg:classifiers":[
        {
            "category":"Social Services",
            "type":"Services"
        }
    ],
    "sg:phone":"+1 910 892 7246",
    "sg:postcode":"28334",
    "sg:province":"NC",
    "sg:tags":[
        "probation"
    ],
    "wof:name":"Probation Dept",
    "wof:placetype":"venue"
},
  "geometry": {"coordinates":[-78.60687,35.3063],"type":"Point"}
}