{
  "type": "Feature",
  "properties": {
    "addr:full":"338 S Main St Fuquay Varina NC 27526",
    "addr:housenumber":"338",
    "addr:postcode":"27526",
    "addr:street":"S Main St",
    "iso:country":"US",
    "sg:address":"338 S Main St",
    "sg:city":"Fuquay Varina",
    "sg:classifiers":[
        {
            "category":"Organizations",
            "subcategory":"Community Association",
            "type":"Services"
        }
    ],
    "sg:phone":"+1 919 577 0050",
    "sg:postcode":"27526",
    "sg:province":"NC",
    "sg:tags":[
        "sorority",
        "fraternity"
    ],
    "wof:name":"Fuquay Masonic Lodge",
    "wof:placetype":"venue"
},
  "geometry": {"coordinates":[-78.799817,35.581892],"type":"Point"}
}