{
  "type": "Feature",
  "properties": {
    "addr:full":"163 Bill Beard Ln Chadbourn NC 28431",
    "addr:housenumber":"163",
    "addr:postcode":"28431",
    "addr:street":"Bill Beard Ln",
    "iso:country":"US",
    "sg:address":"163 Bill Beard Ln",
    "sg:city":"Chadbourn",
    "sg:classifiers":[
        {
            "category":"Professional",
            "type":"Services"
        }
    ],
    "sg:phone":"+1 910 642 5301",
    "sg:postcode":"28431",
    "sg:province":"NC",
    "wof:name":"Bertha M Ward",
    "wof:placetype":"venue"
},
  "geometry": {"coordinates":[-78.78557000000001,34.352193],"type":"Point"}
}