{
  "type": "Feature",
  "properties": {
    "iso:country":"US",
    "sg:address":"3548 Lynhaven Dr",
    "sg:city":"Greensboro",
    "sg:classifiers":[
        {
            "category":"Communications",
            "subcategory":"Film & Video Production",
            "type":"Services"
        }
    ],
    "sg:phone":"+1   ",
    "sg:postcode":"27406",
    "sg:province":"NC",
    "sg:tags":[
        "motion"
    ],
    "wof:name":"Image Ink Productions",
    "wof:placetype":"venue"
},
  "geometry": {"coordinates":[-79.809226,36.025161],"type":"Point"}
}