{
  "type": "Feature",
  "properties": {
    "iso:country":"US",
    "sg:address":"506 W Beaufort Rd",
    "sg:city":"Beaufort",
    "sg:classifiers":[
        {
            "category":"Freight",
            "type":"Transportation"
        }
    ],
    "sg:phone":"+1 252 728 6789",
    "sg:postcode":"28516",
    "sg:province":"NC",
    "sg:tags":[
        "commercial",
        "storage"
    ],
    "wof:name":"Stor-It",
    "wof:placetype":"venue"
},
  "geometry": {"coordinates":[-76.656519,34.726136],"type":"Point"}
}