{
  "type": "Feature",
  "properties": {
    "iso:country":"US",
    "sg:address":"1203 N Main St",
    "sg:city":"Roxboro",
    "sg:classifiers":[
        {
            "category":"Autos & Motor Vehicles",
            "subcategory":"Automobile Sales",
            "type":"Retail Goods"
        }
    ],
    "sg:phone":"+1 336 597 4388",
    "sg:postcode":"27573",
    "sg:province":"NC",
    "sg:tags":[
        "car",
        "dealer"
    ],
    "wof:name":"R & D Auto Sales",
    "wof:placetype":"venue"
},
  "geometry": {"coordinates":[-78.969202,36.418425],"type":"Point"}
}