{
  "type": "Feature",
  "properties": {
    "iso:country":"US",
    "sg:address":"299 Baynes Rd",
    "sg:city":"Reidsville",
    "sg:classifiers":[
        {
            "category":"Building & Trades",
            "subcategory":"Construction",
            "type":"Services"
        }
    ],
    "sg:phone":"+1 336 951 2894",
    "sg:postcode":"27320",
    "sg:province":"NC",
    "sg:tags":[
        "grading",
        "contractor"
    ],
    "wof:name":"Walter Baynes Grading",
    "wof:placetype":"venue"
},
  "geometry": {"coordinates":[-79.834827,36.310918],"type":"Point"}
}