{
  "type": "Feature",
  "properties": {
    "iso:country":"US",
    "sg:address":"6481 Keeneland Trl",
    "sg:city":"Vale",
    "sg:classifiers":[
        {
            "category":"Building & Trades",
            "subcategory":"Construction",
            "type":"Services"
        }
    ],
    "sg:phone":"+1 704 462 0074",
    "sg:postcode":"28168",
    "sg:province":"NC",
    "sg:tags":[
        "tile",
        "dealer"
    ],
    "wof:name":"Fox Custom Tile LLC",
    "wof:placetype":"venue"
},
  "geometry": {"coordinates":[-81.406991,35.584855],"type":"Point"}
}