{
  "type": "Feature",
  "properties": {
    "iso:country":"US",
    "sg:address":"7925 Baux Mountain Rd",
    "sg:city":"Germanton",
    "sg:classifiers":[
        {
            "category":"Building & Trades",
            "subcategory":"Construction",
            "type":"Services"
        }
    ],
    "sg:phone":"+1 336 767 7102",
    "sg:postcode":"27019",
    "sg:province":"NC",
    "sg:tags":[
        "commercial",
        "contractor"
    ],
    "wof:name":"Rd Contractors Inc",
    "wof:placetype":"venue"
},
  "geometry": {"coordinates":[-80.200441,36.231649],"type":"Point"}
}