{
  "type": "Feature",
  "properties": {
    "iso:country":"US",
    "sg:address":"1209 Linwood Ave",
    "sg:city":"Durham",
    "sg:classifiers":[
        {
            "category":"Organizations",
            "subcategory":"Religious Organization",
            "type":"Services"
        }
    ],
    "sg:phone":"+1 252 635 4854",
    "sg:postcode":"27701",
    "sg:province":"NC",
    "sg:tags":[
        "church"
    ],
    "wof:name":"Housing For New Hope",
    "wof:placetype":"venue"
},
  "geometry": {"coordinates":[-78.89072400000001,35.979169],"type":"Point"}
}