{
  "type": "Feature",
  "properties": {
    "iso:country":"US",
    "sg:address":"2301 Westinghouse Blvd",
    "sg:city":"Charlotte",
    "sg:classifiers":[
        {
            "category":"Personal",
            "subcategory":"Barber",
            "type":"Services"
        }
    ],
    "sg:phone":"+1 704 588 9784",
    "sg:postcode":"28273",
    "sg:province":"NC",
    "wof:name":"Sharp Cut",
    "wof:placetype":"venue"
},
  "geometry": {"coordinates":[-80.943009,35.129881],"type":"Point"}
}