{
  "type": "Feature",
  "properties": {
    "iso:country":"US",
    "sg:address":"4029 Wild Nursery Ct",
    "sg:city":"Charlotte",
    "sg:classifiers":[
        {
            "category":"Professional",
            "subcategory":"Management & Consulting",
            "type":"Services"
        }
    ],
    "sg:phone":"+1   ",
    "sg:postcode":"28215",
    "sg:province":"NC",
    "wof:name":"Professional Consultants NC",
    "wof:placetype":"venue"
},
  "geometry": {"coordinates":[-80.688256,35.27488],"type":"Point"}
}