{
  "type": "Feature",
  "properties": {
    "addr:full":"896 Concord Pkwy N Concord NC 28027",
    "addr:housenumber":"896",
    "addr:postcode":"28027",
    "addr:street":"Concord Pkwy N",
    "iso:country":"US",
    "sg:address":"896 Concord Pkwy N",
    "sg:city":"Concord",
    "sg:classifiers":[
        {
            "category":"Restaurant",
            "type":"Food & Drink"
        }
    ],
    "sg:phone":"+1 704 782 1220",
    "sg:postcode":"28027",
    "sg:province":"NC",
    "sg:tags":[
        "eating"
    ],
    "wof:name":"Steak & Hoagie Shop",
    "wof:placetype":"venue"
},
  "geometry": {"coordinates":[-80.61545,35.424712],"type":"Point"}
}