{
  "type": "Feature",
  "properties": {
    "iso:country":"US",
    "sg:address":"8400 Header Stone Dr",
    "sg:city":"Raleigh",
    "sg:classifiers":[
        {
            "category":"Building & Trades",
            "subcategory":"Construction",
            "type":"Services"
        }
    ],
    "sg:phone":"+1 919 793 0018",
    "sg:postcode":"27613",
    "sg:province":"NC",
    "sg:tags":[
        "home",
        "builder"
    ],
    "wof:name":"Centex Homes",
    "wof:placetype":"venue"
},
  "geometry": {"coordinates":[-78.73759699999999,35.890675],"type":"Point"}
}