{
  "type": "Feature",
  "properties": {
    "iso:country":"US",
    "sg:address":"200 E 1st St",
    "sg:city":"Greenville",
    "sg:classifiers":[
        {
            "category":"Organizations",
            "subcategory":"Professional Association",
            "type":"Services"
        }
    ],
    "sg:phone":"+1   ",
    "sg:postcode":"27858",
    "sg:province":"NC",
    "wof:name":"Ecu Foundation Inc",
    "wof:placetype":"venue"
},
  "geometry": {"coordinates":[-77.37093299999999,35.61508],"type":"Point"}
}