{
  "type": "Feature",
  "properties": {
    "iso:country":"US",
    "sg:address":"349 Green Acres Dr",
    "sg:city":"East Bend",
    "sg:classifiers":[
        {
            "category":"Freight",
            "type":"Transportation"
        }
    ],
    "sg:phone":"+1 336 699 2835",
    "sg:postcode":"27018",
    "sg:province":"NC",
    "wof:name":"Handy Help Moving LLC",
    "wof:placetype":"venue"
},
  "geometry": {"coordinates":[-80.50555799999999,36.218452],"type":"Point"}
}