{
  "type": "Feature",
  "properties": {
    "addr:full":"1999 McEachern Farm Rd Red Springs NC 28377",
    "addr:housenumber":"1999",
    "addr:postcode":"28377",
    "addr:street":"Mceachern Farm Rd",
    "iso:country":"US",
    "sg:address":"1999 McEachern Farm Rd",
    "sg:city":"Red Springs",
    "sg:classifiers":[
        {
            "category":"Retail",
            "subcategory":"Animal Services",
            "type":"Services"
        }
    ],
    "sg:phone":"+1 910 843 9210",
    "sg:postcode":"28377",
    "sg:province":"NC",
    "wof:name":"Nunns Creek Kennels",
    "wof:placetype":"venue"
},
  "geometry": {"coordinates":[-79.26699499999999,34.896352],"type":"Point"}
}