{
  "type": "Feature",
  "properties": {
    "iso:country":"US",
    "sg:address":"2825 Rice Rd",
    "sg:city":"Matthews",
    "sg:classifiers":[
        {
            "category":"Professional",
            "subcategory":"Employment Agencies",
            "type":"Services"
        }
    ],
    "sg:phone":"+1   ",
    "sg:postcode":"28105",
    "sg:province":"NC",
    "sg:tags":[
        "help",
        "supply"
    ],
    "wof:name":"Curtis A Seagle",
    "wof:placetype":"venue"
},
  "geometry": {"coordinates":[-80.70148399999999,35.140845],"type":"Point"}
}