{
  "type": "Feature",
  "properties": {
    "addr:full":"308 Merrimon Ave Asheville NC 28801",
    "addr:housenumber":"308",
    "addr:postcode":"28801",
    "addr:street":"Merrimon Ave",
    "iso:country":"US",
    "sg:address":"308 Merrimon Ave",
    "sg:city":"Asheville",
    "sg:classifiers":[
        {
            "category":"Organizations",
            "subcategory":"Religious Organization",
            "type":"Services"
        }
    ],
    "sg:phone":"+1 828 252 8729",
    "sg:postcode":"28801",
    "sg:province":"NC",
    "sg:tags":[
        "church"
    ],
    "wof:name":"First Congregational Church",
    "wof:placetype":"venue"
},
  "geometry": {"coordinates":[-82.554389,35.60897],"type":"Point"}
}