{
  "type": "Feature",
  "properties": {
    "addr:full":"1148 Fleming Rd Creedmoor NC 27522",
    "addr:housenumber":"1148",
    "addr:postcode":"27522",
    "addr:street":"Fleming Rd",
    "iso:country":"US",
    "sg:address":"1148 Fleming Rd",
    "sg:city":"Creedmoor",
    "sg:classifiers":[
        {
            "category":"Health Services",
            "subcategory":"Doctor",
            "type":"Services"
        }
    ],
    "sg:phone":"+1 919 529 0607",
    "sg:postcode":"27522",
    "sg:province":"NC",
    "sg:tags":[
        "physician",
        "surgeon"
    ],
    "wof:name":"Amilda K Horne MD",
    "wof:placetype":"venue"
},
  "geometry": {"coordinates":[-78.747443,36.082482],"type":"Point"}
}