{
  "type": "Feature",
  "properties": {
    "addr:full":"3470 Kildaire Farm Rd Cary NC 27518",
    "addr:housenumber":"3470",
    "addr:postcode":"27518",
    "addr:street":"Kildaire Farm Rd",
    "iso:country":"US",
    "sg:address":"3470 Kildaire Farm Rd",
    "sg:city":"Cary",
    "sg:classifiers":[
        {
            "category":"Professional",
            "subcategory":"Business Services",
            "type":"Services"
        }
    ],
    "sg:phone":"+1 919 363 4848",
    "sg:postcode":"27518",
    "sg:province":"NC",
    "sg:tags":[
        "interior",
        "consultant",
        "design",
        "decorator"
    ],
    "wof:name":"Nettle Creek Decorating Inc",
    "wof:placetype":"venue"
},
  "geometry": {"coordinates":[-78.79456399999999,35.704274],"type":"Point"}
}