{
  "type": "Feature",
  "properties": {
    "iso:country":"US",
    "sg:address":"25 Mount Bolus Rd",
    "sg:city":"Chapel Hill",
    "sg:classifiers":[
        {
            "category":"Real Estate",
            "subcategory":"Architect",
            "type":"Services"
        },
        {
            "category":"Health Services",
            "subcategory":"Health Practitioner",
            "type":"Services"
        }
    ],
    "sg:phone":"+1 919 967 1291",
    "sg:postcode":"27514",
    "sg:province":"NC",
    "sg:tags":[
        "psychotherapist",
        "architectural"
    ],
    "wof:name":"Annette L Kahn",
    "wof:placetype":"venue"
},
  "geometry": {"coordinates":[-79.046392,35.927959],"type":"Point"}
}