{
  "type": "Feature",
  "properties": {
    "iso:country":"US",
    "sg:address":"4904 Crystal Lake Dr",
    "sg:city":"Greensboro",
    "sg:classifiers":[
        {
            "category":"Professional",
            "subcategory":"Management & Consulting",
            "type":"Services"
        }
    ],
    "sg:phone":"+1   ",
    "sg:postcode":"27410",
    "sg:province":"NC",
    "wof:name":"Cmj Consulting",
    "wof:placetype":"venue"
},
  "geometry": {"coordinates":[-79.922105,36.144794],"type":"Point"}
}