{
  "type": "Feature",
  "properties": {
    "addr:full":"101 Maple St Salisbury NC 28146",
    "addr:housenumber":"101",
    "addr:postcode":"28146",
    "addr:street":"Maple St",
    "iso:country":"US",
    "sg:address":"101 Maple St",
    "sg:city":"Salisbury",
    "sg:classifiers":[
        {
            "category":"Organizations",
            "subcategory":"Religious Organization",
            "type":"Services"
        }
    ],
    "sg:phone":"+1 704 278 4552",
    "sg:postcode":"28146",
    "sg:province":"NC",
    "sg:tags":[
        "church"
    ],
    "wof:name":"Cleveland Presbyterian Church",
    "wof:placetype":"venue"
},
  "geometry": {"coordinates":[-80.48597599999999,35.582387],"type":"Point"}
}