{
  "type": "Feature",
  "properties": {
    "iso:country":"US",
    "sg:address":"1330 Eldorado St",
    "sg:city":"Troy",
    "sg:classifiers":[
        {
            "category":"Food & Beverages",
            "subcategory":"Groceries & Convenience Stores",
            "type":"Retail Goods"
        }
    ],
    "sg:phone":"+1 910 576 0096",
    "sg:postcode":"27371",
    "sg:province":"NC",
    "wof:name":"Jake's KWIK Stop",
    "wof:placetype":"venue"
},
  "geometry": {"coordinates":[-79.913439,35.369185],"type":"Point"}
}