{
  "type": "Feature",
  "properties": {
    "addr:full":"4861 New Walkertown Rd NE Walkertown NC 27051",
    "addr:housenumber":"4861",
    "addr:postcode":"27051",
    "addr:street":"New Walkertown Rd Ne",
    "iso:country":"US",
    "sg:address":"4861 New Walkertown Rd NE",
    "sg:city":"Walkertown",
    "sg:classifiers":[
        {
            "category":"Retail",
            "subcategory":"Auto Repair",
            "type":"Services"
        }
    ],
    "sg:phone":"+1 336 595 2473",
    "sg:postcode":"27051",
    "sg:province":"NC",
    "sg:tags":[
        "repairing",
        "automobile"
    ],
    "wof:name":"Stoltz Automotive",
    "wof:placetype":"venue"
},
  "geometry": {"coordinates":[-80.15818,36.172827],"type":"Point"}
}