{
  "type": "Feature",
  "properties": {
    "iso:country":"US",
    "sg:address":"800 Brevard Rd",
    "sg:city":"Asheville",
    "sg:classifiers":[
        {
            "category":"Shopping",
            "subcategory":"Hobbies, Toys, & Games",
            "type":"Retail Goods"
        }
    ],
    "sg:phone":"+1 828 667 1732",
    "sg:postcode":"28806",
    "sg:province":"NC",
    "sg:tags":[
        "craft"
    ],
    "wof:name":"Craft Tee's",
    "wof:placetype":"venue"
},
  "geometry": {"coordinates":[-82.60579,35.529739],"type":"Point"}
}