{
  "type": "Feature",
  "properties": {
    "iso:country":"US",
    "sg:address":"11 S College Ave",
    "sg:city":"Newton",
    "sg:classifiers":[
        {
            "category":"Wholesale",
            "subcategory":"Durable Goods & Equipment",
            "type":"Manufacturing & Wholesale Goods"
        }
    ],
    "sg:phone":"+1 828 465 6036",
    "sg:postcode":"28658",
    "sg:province":"NC",
    "sg:tags":[
        "representative",
        "manufacturer"
    ],
    "wof:name":"Jamesco Inc",
    "wof:placetype":"venue"
},
  "geometry": {"coordinates":[-81.221797,35.661851],"type":"Point"}
}