{
  "type": "Feature",
  "properties": {
    "addr:full":"713 Hope Mills Rd Fayetteville NC 28304",
    "addr:housenumber":"713",
    "addr:postcode":"28304",
    "addr:street":"Hope Mills Rd",
    "iso:country":"US",
    "sg:address":"713 Hope Mills Rd",
    "sg:city":"Fayetteville",
    "sg:classifiers":[
        {
            "category":"Building & Trades",
            "subcategory":"Construction",
            "type":"Services"
        }
    ],
    "sg:phone":"+1 910 483 7801",
    "sg:postcode":"28304",
    "sg:province":"NC",
    "sg:tags":[
        "concrete",
        "contractor"
    ],
    "wof:name":"Murphys Concrete & Finishing",
    "wof:placetype":"venue"
},
  "geometry": {"coordinates":[-78.960902,35.035243],"type":"Point"}
}