{
  "type": "Feature",
  "properties": {
    "addr:full":"315 Barringer Rd Salisbury NC 28147",
    "addr:housenumber":"315",
    "addr:postcode":"28147",
    "addr:street":"Barringer Rd",
    "iso:country":"US",
    "sg:address":"315 Barringer Rd",
    "sg:city":"Salisbury",
    "sg:classifiers":[
        {
            "category":"Social Services",
            "subcategory":"Child Care",
            "type":"Services"
        }
    ],
    "sg:phone":"+1   ",
    "sg:postcode":"28147",
    "sg:province":"NC",
    "sg:tags":[
        "day"
    ],
    "wof:name":"Childs Play Daycare",
    "wof:placetype":"venue"
},
  "geometry": {"coordinates":[-80.583777,35.712427],"type":"Point"}
}