{
  "type": "Feature",
  "properties": {
    "iso:country":"US",
    "sg:address":"12929 Ballantyne Corporate Pl",
    "sg:city":"Charlotte",
    "sg:classifiers":[
        {
            "category":"Professional",
            "type":"Services"
        }
    ],
    "sg:phone":"+1 704 752 3778",
    "sg:postcode":"28277",
    "sg:province":"NC",
    "wof:name":"Bill Wentz",
    "wof:placetype":"venue"
},
  "geometry": {"coordinates":[-80.84358899999999,35.054342],"type":"Point"}
}