{
  "type": "Feature",
  "properties": {
    "addr:full":"13415 Kintyre Ct Matthews NC 28105",
    "addr:housenumber":"13415",
    "addr:postcode":"28105",
    "addr:street":"Kintyre Ct",
    "iso:country":"US",
    "sg:address":"13415 Kintyre Ct",
    "sg:city":"Matthews",
    "sg:classifiers":[
        {
            "category":"Professional",
            "subcategory":"Computer Services",
            "type":"Services"
        }
    ],
    "sg:phone":"+1 704 321 9298",
    "sg:postcode":"28105",
    "sg:province":"NC",
    "sg:tags":[
        "web",
        "design",
        "hosting",
        "site"
    ],
    "wof:name":"Leverage Point Interactive Inc",
    "wof:placetype":"venue"
},
  "geometry": {"coordinates":[-80.681285,35.118149],"type":"Point"}
}