{
  "type": "Feature",
  "properties": {
    "iso:country":"US",
    "sg:address":"3302 Mulberry Ln",
    "sg:city":"Greenville",
    "sg:classifiers":[
        {
            "category":"Home & Garden",
            "subcategory":"Furniture",
            "type":"Retail Goods"
        }
    ],
    "sg:phone":"+1 252 353 1619",
    "sg:postcode":"27858",
    "sg:province":"NC",
    "wof:name":"Direct In Greenville Furniture",
    "wof:placetype":"venue"
},
  "geometry": {"coordinates":[-77.35853400000001,35.57456],"type":"Point"}
}