{
  "type": "Feature",
  "properties": {
    "addr:full":"5216 Brevard Rd Horse Shoe NC 28742",
    "addr:housenumber":"5216",
    "addr:postcode":"28742",
    "addr:street":"Brevard Rd",
    "iso:country":"US",
    "sg:address":"5216 Brevard Rd",
    "sg:city":"Horse Shoe",
    "sg:classifiers":[
        {
            "category":"Building & Trades",
            "subcategory":"Construction",
            "type":"Services"
        }
    ],
    "sg:phone":"+1 828 890 3685",
    "sg:postcode":"28742",
    "sg:province":"NC",
    "sg:tags":[
        "tile",
        "dealer"
    ],
    "wof:name":"Terry's Tile Works",
    "wof:placetype":"venue"
},
  "geometry": {"coordinates":[-82.566895,35.336204],"type":"Point"}
}