{
  "type": "Feature",
  "properties": {
    "addr:full":"1304 Annapolis Dr Raleigh NC 27608",
    "addr:housenumber":"1304",
    "addr:postcode":"27608",
    "addr:street":"Annapolis Dr",
    "iso:country":"US",
    "sg:address":"1304 Annapolis Dr",
    "sg:city":"Raleigh",
    "sg:classifiers":[
        {
            "category":"Real Estate",
            "subcategory":"Real Estate Agent",
            "type":"Services"
        }
    ],
    "sg:phone":"+1 919 821 2125",
    "sg:postcode":"27608",
    "sg:province":"NC",
    "wof:name":"J Mark Properties Inc",
    "wof:placetype":"venue"
},
  "geometry": {"coordinates":[-78.658041,35.799109],"type":"Point"}
}