{
  "type": "Feature",
  "properties": {
    "iso:country":"US",
    "sg:address":"319 Merrimon Ave",
    "sg:city":"Asheville",
    "sg:classifiers":[
        {
            "category":"Shopping",
            "subcategory":"Musical Instruments",
            "type":"Retail Goods"
        }
    ],
    "sg:phone":"+1 828 252 1249",
    "sg:postcode":"28801",
    "sg:province":"NC",
    "sg:website":"www.musiciansworkshop.com",
    "wof:name":"Musician's Workshop",
    "wof:placetype":"venue"
},
  "geometry": {"coordinates":[-82.554131,35.608654],"type":"Point"}
}