{
  "type": "Feature",
  "properties": {
    "addr:full":"1215 W New Bern Rd Kinston NC 28504",
    "addr:housenumber":"1215",
    "addr:postcode":"28504",
    "addr:street":"W New Bern Rd",
    "iso:country":"US",
    "sg:address":"1215 W New Bern Rd",
    "sg:city":"Kinston",
    "sg:classifiers":[
        {
            "category":"Retail",
            "subcategory":"Repair Shop",
            "type":"Services"
        }
    ],
    "sg:phone":"+1   ",
    "sg:postcode":"28504",
    "sg:province":"NC",
    "sg:tags":[
        "auto",
        "reupholstery",
        "furniture"
    ],
    "wof:name":"Spence Upholstery",
    "wof:placetype":"venue"
},
  "geometry": {"coordinates":[-77.610626,35.258477],"type":"Point"}
}