{
  "type": "Feature",
  "properties": {
    "iso:country":"US",
    "sg:address":"3181 George II Hwy",
    "sg:city":"Southport",
    "sg:classifiers":[
        {
            "category":"Health Services",
            "subcategory":"Doctor",
            "type":"Services"
        }
    ],
    "sg:phone":"+1 910 845 3244",
    "sg:postcode":"28461",
    "sg:province":"NC",
    "sg:tags":[
        "physician",
        "surgeon"
    ],
    "wof:name":"Boiling Spring Lakes",
    "wof:placetype":"venue"
},
  "geometry": {"coordinates":[-78.04055700000001,33.993567],"type":"Point"}
}