{
  "type": "Feature",
  "properties": {
    "iso:country":"US",
    "sg:address":"1404 River St",
    "sg:city":"Wilkesboro",
    "sg:classifiers":[
        {
            "category":"Wholesale",
            "subcategory":"Non-durable Goods",
            "type":"Manufacturing & Wholesale Goods"
        }
    ],
    "sg:phone":"+1 336 667 3487",
    "sg:postcode":"28697",
    "sg:province":"NC",
    "sg:tags":[
        "merchandise",
        "general"
    ],
    "wof:name":"Lucky Dollar Stores Inc",
    "wof:placetype":"venue"
},
  "geometry": {"coordinates":[-81.180835,36.141334],"type":"Point"}
}