{
  "type": "Feature",
  "properties": {
    "addr:full":"42 Cannon Woods Dr Marion NC 28752",
    "addr:housenumber":"42",
    "addr:postcode":"28752",
    "addr:street":"Cannon Woods",
    "iso:country":"US",
    "sg:address":"42 Cannon Woods Dr",
    "sg:city":"Marion",
    "sg:classifiers":[
        {
            "category":"Shopping",
            "type":"Retail Goods"
        }
    ],
    "sg:phone":"+1 828 659 7611",
    "sg:postcode":"28752",
    "sg:province":"NC",
    "sg:tags":[
        "merchandise"
    ],
    "wof:name":"Quality Stone LLC",
    "wof:placetype":"venue"
},
  "geometry": {"coordinates":[-82.014793,35.738522],"type":"Point"}
}