{
  "type": "Feature",
  "properties": {
    "iso:country":"US",
    "sg:address":"109 W 8th Ave",
    "sg:city":"Gastonia",
    "sg:classifiers":[
        {
            "category":"Health Services",
            "subcategory":"Clinic",
            "type":"Services"
        }
    ],
    "sg:phone":"+1 704 853 5358",
    "sg:postcode":"28054",
    "sg:province":"NC",
    "sg:tags":[
        "information",
        "alcoholism",
        "treatment"
    ],
    "sg:website":"http://www.ncatp.org",
    "wof:name":"Vocational Rehabilation Svc",
    "wof:placetype":"venue"
},
  "geometry": {"coordinates":[-81.18147999999999,35.251456],"type":"Point"}
}