{
  "type": "Feature",
  "properties": {
    "iso:country":"US",
    "sg:address":"315 Julian Ave",
    "sg:city":"Thomasville",
    "sg:classifiers":[
        {
            "category":"Freight",
            "type":"Transportation"
        }
    ],
    "sg:phone":"+1 336 475 1600",
    "sg:postcode":"27360",
    "sg:province":"NC",
    "sg:tags":[
        "special"
    ],
    "wof:name":"Community Self Storage",
    "wof:placetype":"venue"
},
  "geometry": {"coordinates":[-80.071744,35.879673],"type":"Point"}
}