{
  "type": "Feature",
  "properties": {
    "iso:country":"US",
    "sg:address":"201 S Green St",
    "sg:city":"Morganton",
    "sg:classifiers":[
        {
            "category":"Government",
            "subcategory":"Office",
            "type":"Public Place"
        }
    ],
    "sg:phone":"+1 828 438 6288",
    "sg:postcode":"28655",
    "sg:province":"NC",
    "sg:tags":[
        "state",
        "resource"
    ],
    "wof:name":"Community Service",
    "wof:placetype":"venue"
},
  "geometry": {"coordinates":[-81.68633199999999,35.745419],"type":"Point"}
}