{
  "type": "Feature",
  "properties": {
    "iso:country":"US",
    "sg:address":"228 Willow",
    "sg:city":"Hudson",
    "sg:classifiers":[
        {
            "category":"Building & Trades",
            "subcategory":"Electrical",
            "type":"Services"
        }
    ],
    "sg:phone":"+1 828 612 2750",
    "sg:postcode":"28638",
    "sg:province":"NC",
    "sg:tags":[
        "electric",
        "contractor"
    ],
    "wof:name":"B H Electric",
    "wof:placetype":"venue"
},
  "geometry": {"coordinates":[-81.50391399999999,35.838761],"type":"Point"}
}