{
  "type": "Feature",
  "properties": {
    "addr:full":"715 Cypress Creek Rd Richlands NC 28574",
    "addr:housenumber":"715",
    "addr:postcode":"28574",
    "addr:street":"Cypress Creek Rd",
    "iso:country":"US",
    "sg:address":"715 Cypress Creek Rd",
    "sg:city":"Richlands",
    "sg:classifiers":[
        {
            "category":"Food & Beverages",
            "subcategory":"Groceries & Convenience Stores",
            "type":"Retail Goods"
        }
    ],
    "sg:phone":"+1 910 324 4881",
    "sg:postcode":"28574",
    "sg:province":"NC",
    "sg:tags":[
        "grocer"
    ],
    "wof:name":"Craft's Country Store",
    "wof:placetype":"venue"
},
  "geometry": {"coordinates":[-77.667243,34.804319],"type":"Point"}
}