{
  "type": "Feature",
  "properties": {
    "iso:country":"US",
    "sg:address":"4915 High Point Rd",
    "sg:city":"Greensboro",
    "sg:classifiers":[
        {
            "category":"Personal",
            "subcategory":"Beauty Salon",
            "type":"Services"
        }
    ],
    "sg:phone":"+1   ",
    "sg:postcode":"27407",
    "sg:province":"NC",
    "sg:tags":[
        "shop"
    ],
    "wof:name":"Talking Heads Salon",
    "wof:placetype":"venue"
},
  "geometry": {"coordinates":[-79.87606700000001,36.024643],"type":"Point"}
}