{
  "type": "Feature",
  "properties": {
    "addr:full":"8913 Oneal Rd Raleigh NC 27613",
    "addr:housenumber":"8913",
    "addr:postcode":"27613",
    "addr:street":"Oneal Rd",
    "iso:country":"US",
    "sg:address":"8913 Oneal Rd",
    "sg:city":"Raleigh",
    "sg:classifiers":[
        {
            "category":"Professional",
            "subcategory":"Research",
            "type":"Services"
        }
    ],
    "sg:phone":"+1 919 848 6981",
    "sg:postcode":"27613",
    "sg:province":"NC",
    "sg:tags":[
        "plasma",
        "technology",
        "heating"
    ],
    "wof:name":"Plasma Technology Corporation",
    "wof:placetype":"venue"
},
  "geometry": {"coordinates":[-78.71726099999999,35.898405],"type":"Point"}
}