{
  "type": "Feature",
  "properties": {
    "iso:country":"US",
    "sg:address":"5218 State Rd 150",
    "sg:city":"Lincolnton",
    "sg:classifiers":[
        {
            "category":"Shopping",
            "subcategory":"Computers & Home Electronics",
            "type":"Retail Goods"
        }
    ],
    "sg:phone":"+1 704 732 8176",
    "sg:postcode":"28092",
    "sg:province":"NC",
    "sg:tags":[
        "television",
        "radio"
    ],
    "wof:name":"Amateur Radio",
    "wof:placetype":"venue"
},
  "geometry": {"coordinates":[-81.130234,35.532676],"type":"Point"}
}