{
  "type": "Feature",
  "properties": {
    "addr:full":"1313 Three Oaks Rd Hamptonville NC 27020",
    "addr:housenumber":"1313",
    "addr:postcode":"27020",
    "addr:street":"Three Oaks Rd",
    "iso:country":"US",
    "sg:address":"1313 Three Oaks Rd",
    "sg:city":"Hamptonville",
    "sg:classifiers":[
        {
            "category":"Retail",
            "subcategory":"Auto Repair",
            "type":"Services"
        }
    ],
    "sg:phone":"+1   ",
    "sg:postcode":"27020",
    "sg:province":"NC",
    "sg:tags":[
        "general"
    ],
    "wof:name":"Gilliam Son Diesl Repr & Trckg",
    "wof:placetype":"venue"
},
  "geometry": {"coordinates":[-80.788048,36.145724],"type":"Point"}
}