{
  "type": "Feature",
  "properties": {
    "addr:full":"5137 Snow White Ln Charlotte NC 28213",
    "addr:housenumber":"5137",
    "addr:postcode":"28213",
    "addr:street":"Snow White Ln",
    "iso:country":"US",
    "sg:address":"5137 Snow White Ln",
    "sg:city":"Charlotte",
    "sg:classifiers":[
        {
            "category":"Freight",
            "type":"Transportation"
        }
    ],
    "sg:phone":"+1 704 597 8734",
    "sg:postcode":"28213",
    "sg:province":"NC",
    "sg:tags":[
        "courier"
    ],
    "wof:name":"Brewer Courier Inc",
    "wof:placetype":"venue"
},
  "geometry": {"coordinates":[-80.784125,35.269189],"type":"Point"}
}