{
  "type": "Feature",
  "properties": {
    "iso:country":"US",
    "sg:address":"100 Young Rider Ln",
    "sg:city":"Grandy",
    "sg:classifiers":[
        {
            "category":"Building & Trades",
            "subcategory":"Construction",
            "type":"Services"
        }
    ],
    "sg:phone":"+1 252 491 8727",
    "sg:postcode":"27939",
    "sg:province":"NC",
    "sg:tags":[
        "general",
        "contractor"
    ],
    "wof:name":"Dirt Pushers",
    "wof:placetype":"venue"
},
  "geometry": {"coordinates":[-75.868768,36.214318],"type":"Point"}
}