{
  "type": "Feature",
  "properties": {
    "addr:full":"521 Suwanee Dr Black Mountain NC 28711",
    "addr:housenumber":"521",
    "addr:postcode":"28711",
    "addr:street":"Suwanee Dr",
    "iso:country":"US",
    "sg:address":"521 Suwanee Dr",
    "sg:city":"Black Mountain",
    "sg:classifiers":[
        {
            "category":"Building & Trades",
            "subcategory":"Construction",
            "type":"Services"
        }
    ],
    "sg:phone":"+1 828 669 4337",
    "sg:postcode":"28711",
    "sg:province":"NC",
    "sg:tags":[
        "general",
        "contractor"
    ],
    "wof:name":"Ewing Construction",
    "wof:placetype":"venue"
},
  "geometry": {"coordinates":[-82.299004,35.656288],"type":"Point"}
}