{
  "type": "Feature",
  "properties": {
    "addr:full":"1072 N Main St Walnut Cove NC 27052",
    "addr:housenumber":"1072",
    "addr:postcode":"27052",
    "addr:street":"N Main St",
    "iso:country":"US",
    "sg:address":"1072 N Main St",
    "sg:city":"Walnut Cove",
    "sg:classifiers":[
        {
            "category":"Food & Beverages",
            "subcategory":"Groceries & Convenience Stores",
            "type":"Retail Goods"
        }
    ],
    "sg:phone":"+1 336 591 3375",
    "sg:postcode":"27052",
    "sg:province":"NC",
    "sg:tags":[
        "grocer"
    ],
    "wof:name":"Food Lion",
    "wof:placetype":"venue"
},
  "geometry": {"coordinates":[-80.140682,36.309251],"type":"Point"}
}