{
  "type": "Feature",
  "properties": {
    "addr:full":"1015 S Grove St Exd Lincolnton NC 28092",
    "addr:housenumber":"1015",
    "addr:postcode":"28092",
    "addr:street":"S Grove St Exd",
    "iso:country":"US",
    "sg:address":"1015 S Grove St Exd",
    "sg:city":"Lincolnton",
    "sg:classifiers":[
        {
            "category":"Freight",
            "type":"Transportation"
        },
        {
            "category":"Retail",
            "subcategory":"Auto Repair",
            "type":"Services"
        }
    ],
    "sg:phone":"+1 704 736 0376",
    "sg:postcode":"28092",
    "sg:province":"NC",
    "sg:tags":[
        "operator",
        "local",
        "trucking",
        "truck",
        "general"
    ],
    "wof:name":"M & M Truck Center",
    "wof:placetype":"venue"
},
  "geometry": {"coordinates":[-81.268575,35.446595],"type":"Point"}
}