{
  "type": "Feature",
  "properties": {
    "iso:country":"US",
    "sg:address":"4001 Meriwether Dr",
    "sg:city":"Durham",
    "sg:classifiers":[
        {
            "category":"Real Estate",
            "subcategory":"Real Estate Agent",
            "type":"Services"
        },
        {
            "category":"Real Estate",
            "subcategory":"Real Estate Operator",
            "type":"Services"
        }
    ],
    "sg:phone":"+1 919 220 8466",
    "sg:postcode":"27704",
    "sg:province":"NC",
    "sg:tags":[
        "apartment"
    ],
    "wof:name":"Carver Pond Apartments",
    "wof:placetype":"venue"
},
  "geometry": {"coordinates":[-78.89015499999999,36.042201],"type":"Point"}
}