{
  "type": "Feature",
  "properties": {
    "addr:full":"202 N Broad St Edenton NC 27932",
    "addr:housenumber":"202",
    "addr:postcode":"27932",
    "addr:street":"N Broad St",
    "iso:country":"US",
    "sg:address":"202 N Broad St",
    "sg:city":"Edenton",
    "sg:classifiers":[
        {
            "category":"Shopping",
            "subcategory":"Catalog Store",
            "type":"Retail Goods"
        }
    ],
    "sg:phone":"+1 252 482 3244",
    "sg:postcode":"27932",
    "sg:province":"NC",
    "sg:tags":[
        "mail",
        "electronic",
        "house"
    ],
    "wof:name":"Colonial Communications",
    "wof:placetype":"venue"
},
  "geometry": {"coordinates":[-76.576168,36.085826],"type":"Point"}
}