{
  "type": "Feature",
  "properties": {
    "addr:full":"1070 Tunnel Rd Asheville NC 28805",
    "addr:housenumber":"1070",
    "addr:postcode":"28805",
    "addr:street":"Tunnel Rd",
    "iso:country":"US",
    "sg:address":"1070 Tunnel Rd",
    "sg:city":"Asheville",
    "sg:classifiers":[
        {
            "category":"Personal",
            "subcategory":"Beauty Salon",
            "type":"Services"
        }
    ],
    "sg:phone":"+1   ",
    "sg:postcode":"28805",
    "sg:province":"NC",
    "sg:tags":[
        "shop"
    ],
    "wof:name":"Custom Cuts & Color",
    "wof:placetype":"venue"
},
  "geometry": {"coordinates":[-82.494967,35.588555],"type":"Point"}
}