{
  "type": "Feature",
  "properties": {
    "iso:country":"US",
    "sg:address":"9431 Bonnie Briar Cir",
    "sg:city":"Charlotte",
    "sg:classifiers":[
        {
            "category":"Banks & Credit Unions",
            "subcategory":"Bank",
            "type":"Services"
        }
    ],
    "sg:phone":"+1 704 540 4244",
    "sg:postcode":"28277",
    "sg:province":"NC",
    "wof:name":"Hsbc Bank USA",
    "wof:placetype":"venue"
},
  "geometry": {"coordinates":[-80.82328099999999,35.08329],"type":"Point"}
}