{
  "type": "Feature",
  "properties": {
    "addr:full":"5500 Executive Center Dr # 102 Charlotte NC 28212",
    "addr:housenumber":"5500",
    "addr:postcode":"28212",
    "addr:street":"Executive Center Dr # 102",
    "iso:country":"US",
    "sg:address":"5500 Executive Center Dr # 102",
    "sg:city":"Charlotte",
    "sg:classifiers":[
        {
            "category":"Professional",
            "subcategory":"Management & Consulting",
            "type":"Services"
        },
        {
            "category":"Insurance",
            "subcategory":"Hazard Insurance",
            "type":"Services"
        },
        {
            "category":"Banks & Credit Unions",
            "subcategory":"Financial Services",
            "type":"Services"
        },
        {
            "category":"Professional",
            "subcategory":"Business Services",
            "type":"Services"
        }
    ],
    "sg:phone":"+1 704 531 9999",
    "sg:postcode":"28212",
    "sg:province":"NC",
    "sg:tags":[
        "planning",
        "financing",
        "coach",
        "annuity",
        "commercial",
        "retirement",
        "plan",
        "consultant"
    ],
    "wof:name":"U S Financial Services",
    "wof:placetype":"venue"
},
  "geometry": {"coordinates":[-80.744148,35.20314],"type":"Point"}
}