{
  "type": "Feature",
  "properties": {
    "addr:full":"103 Kilmayne Dr Cary NC 27511",
    "addr:housenumber":"103",
    "addr:postcode":"27511",
    "addr:street":"Kilmayne Dr",
    "iso:country":"US",
    "sg:address":"103 Kilmayne Dr",
    "sg:city":"Cary",
    "sg:classifiers":[
        {
            "category":"Insurance",
            "subcategory":"Insurance Agent",
            "type":"Services"
        }
    ],
    "sg:phone":"+1 919 467 6339",
    "sg:postcode":"27511",
    "sg:province":"NC",
    "sg:tags":[
        "agency"
    ],
    "wof:name":"Ed Moore & Associates Inc",
    "wof:placetype":"venue"
},
  "geometry": {"coordinates":[-78.78187800000001,35.769324],"type":"Point"}
}