{
  "type": "Feature",
  "properties": {
    "addr:full":"3220 Wilkinson Blvd #A 5 Charlotte NC 28208",
    "addr:housenumber":"3220;5",
    "addr:postcode":"28208",
    "addr:street":"Wilkinson Blvd # A",
    "iso:country":"US",
    "sg:address":"3220 Wilkinson Blvd #A 5",
    "sg:city":"Charlotte",
    "sg:classifiers":[
        {
            "category":"Shopping",
            "subcategory":"Beauty & Cosmetics",
            "type":"Retail Goods"
        },
        {
            "category":"Personal",
            "subcategory":"Beauty Salon",
            "type":"Services"
        }
    ],
    "sg:phone":"+1 704 392 2353",
    "sg:postcode":"28208",
    "sg:province":"NC",
    "sg:tags":[
        "supply",
        "perfume",
        "hair",
        "equipment",
        "salons-equipment",
        "accessory"
    ],
    "sg:website":"http://www.sallybeauty.com/",
    "wof:name":"Sally Beauty Supply",
    "wof:placetype":"venue"
},
  "geometry": {"coordinates":[-80.892636,35.224407],"type":"Point"}
}