{
  "type": "Feature",
  "properties": {
    "iso:country":"US",
    "sg:address":"4616 Bryan Hardy Rd",
    "sg:city":"La Grange",
    "sg:classifiers":[
        {
            "category":"Farming",
            "subcategory":"Farm",
            "type":"Manufacturing & Wholesale Goods"
        }
    ],
    "sg:phone":"+1 252 566 9897",
    "sg:postcode":"28551",
    "sg:province":"NC",
    "sg:tags":[
        "crop",
        "general"
    ],
    "wof:name":"Hope Farms",
    "wof:placetype":"venue"
},
  "geometry": {"coordinates":[-77.71253,35.351676],"type":"Point"}
}