{
  "type": "Feature",
  "properties": {
    "iso:country":"US",
    "sg:address":"109 N Deerfield Cir",
    "sg:city":"Salisbury",
    "sg:classifiers":[
        {
            "category":"Professional",
            "subcategory":"Management & Consulting",
            "type":"Services"
        }
    ],
    "sg:phone":"+1   ",
    "sg:postcode":"28147",
    "sg:province":"NC",
    "wof:name":"Milton Mull Marketing Inc",
    "wof:placetype":"venue"
},
  "geometry": {"coordinates":[-80.510272,35.750658],"type":"Point"}
}