{
  "type": "Feature",
  "properties": {
    "iso:country":"US",
    "sg:address":"814 Ward Blvd",
    "sg:city":"Wilson",
    "sg:classifiers":[
        {
            "category":"Autos & Motor Vehicles",
            "subcategory":"Auto Supplies",
            "type":"Retail Goods"
        }
    ],
    "sg:phone":"+1 252 243 2169",
    "sg:postcode":"27893",
    "sg:province":"NC",
    "sg:tags":[
        "automobile",
        "parts"
    ],
    "sg:website":"www.advancedauto.com",
    "wof:name":"Advance Auto Parts Inc",
    "wof:placetype":"venue"
},
  "geometry": {"coordinates":[-77.93350599999999,35.716684],"type":"Point"}
}