{
  "type": "Feature",
  "properties": {
    "addr:full":"16014 Marvin Rd Charlotte NC 28277",
    "addr:housenumber":"16014",
    "addr:postcode":"28277",
    "addr:street":"Marvin Rd",
    "iso:country":"US",
    "sg:address":"16014 Marvin Rd",
    "sg:city":"Charlotte",
    "sg:classifiers":[
        {
            "category":"Arts & Performance",
            "subcategory":"Theater",
            "type":"Entertainment"
        },
        {
            "category":"Recreation",
            "type":"Entertainment"
        }
    ],
    "sg:phone":"+1 704 542 1046",
    "sg:postcode":"28277",
    "sg:province":"NC",
    "sg:tags":[
        "group",
        "stable"
    ],
    "wof:name":"Mary-Go Round Pony Parties",
    "wof:placetype":"venue"
},
  "geometry": {"coordinates":[-80.84616,35.033658],"type":"Point"}
}