{
  "type": "Feature",
  "properties": {
    "iso:country":"US",
    "sg:address":"2222 Chapel Hill Rd",
    "sg:city":"Durham",
    "sg:classifiers":[
        {
            "category":"Professional",
            "subcategory":"Computer Services",
            "type":"Services"
        }
    ],
    "sg:phone":"+1 919 572 2750",
    "sg:postcode":"27707",
    "sg:province":"NC",
    "sg:tags":[
        "consulting",
        "management",
        "related"
    ],
    "wof:name":"Ajilon J T S Srvs",
    "wof:placetype":"venue"
},
  "geometry": {"coordinates":[-78.930733,35.983296],"type":"Point"}
}