{
  "type": "Feature",
  "properties": {
    "addr:full":"2035 Propst Rd Morganton NC 28655",
    "addr:housenumber":"2035",
    "addr:postcode":"28655",
    "addr:street":"Propst Rd",
    "iso:country":"US",
    "sg:address":"2035 Propst Rd",
    "sg:city":"Morganton",
    "sg:classifiers":[
        {
            "category":"Autos & Motor Vehicles",
            "subcategory":"Auto Supplies",
            "type":"Retail Goods"
        }
    ],
    "sg:phone":"+1 828 433 8801",
    "sg:postcode":"28655",
    "sg:province":"NC",
    "wof:name":"Rectors Truck & Car ACC",
    "wof:placetype":"venue"
},
  "geometry": {"coordinates":[-81.728847,35.701755],"type":"Point"}
}