{
  "type": "Feature",
  "properties": {
    "addr:full":"255 Knoxview Ln Mooresville NC 28117",
    "addr:housenumber":"255",
    "addr:postcode":"28117",
    "addr:street":"Knoxview Ln",
    "iso:country":"US",
    "sg:address":"255 Knoxview Ln",
    "sg:city":"Mooresville",
    "sg:classifiers":[
        {
            "category":"Home & Garden",
            "subcategory":"Home Furnishings",
            "type":"Retail Goods"
        }
    ],
    "sg:phone":"+1 704 896 7173",
    "sg:postcode":"28117",
    "sg:province":"NC",
    "wof:name":"Davidson Bunkhouse",
    "wof:placetype":"venue"
},
  "geometry": {"coordinates":[-80.88394599999999,35.522991],"type":"Point"}
}