{
  "type": "Feature",
  "properties": {
    "iso:country":"US",
    "sg:address":"135 Center St",
    "sg:city":"Jacksonville",
    "sg:classifiers":[
        {
            "category":"Freight",
            "type":"Transportation"
        }
    ],
    "sg:phone":"+1 910 577 4117",
    "sg:postcode":"28546",
    "sg:province":"NC",
    "sg:tags":[
        "commercial",
        "storage"
    ],
    "wof:name":"Uncle Bob's Self-Storage",
    "wof:placetype":"venue"
},
  "geometry": {"coordinates":[-77.382085,34.747484],"type":"Point"}
}