{
  "type": "Feature",
  "properties": {
    "iso:country":"US",
    "sg:address":"2831 Henslowe Ln",
    "sg:city":"Charlotte",
    "sg:classifiers":[
        {
            "category":"Professional",
            "type":"Services"
        }
    ],
    "sg:phone":"+1 704 547 9577",
    "sg:postcode":"28262",
    "sg:province":"NC",
    "wof:name":"Stairchek",
    "wof:placetype":"venue"
},
  "geometry": {"coordinates":[-80.695516,35.325938],"type":"Point"}
}