{
  "type": "Feature",
  "properties": {
    "addr:full":"621 Madison Ave Kinston NC 28501",
    "addr:housenumber":"621",
    "addr:postcode":"28501",
    "addr:street":"Madison Ave",
    "iso:country":"US",
    "sg:address":"621 Madison Ave",
    "sg:city":"Kinston",
    "sg:classifiers":[
        {
            "category":"Organizations",
            "subcategory":"Community Association",
            "type":"Services"
        }
    ],
    "sg:phone":"+1   ",
    "sg:postcode":"28501",
    "sg:province":"NC",
    "wof:name":"Association of Self Advocates",
    "wof:placetype":"venue"
},
  "geometry": {"coordinates":[-77.584993,35.281573],"type":"Point"}
}