{
  "type": "Feature",
  "properties": {
    "iso:country":"US",
    "sg:address":"660 Westinghouse Blvd",
    "sg:city":"Charlotte",
    "sg:classifiers":[
        {
            "category":"Home & Garden",
            "subcategory":"Garden Supply",
            "type":"Retail Goods"
        }
    ],
    "sg:phone":"+1 704 504 3358",
    "sg:postcode":"28273",
    "sg:province":"NC",
    "sg:tags":[
        "landscaping",
        "equipment"
    ],
    "wof:name":"Ridge Rock Retaining Walls",
    "wof:placetype":"venue"
},
  "geometry": {"coordinates":[-80.924603,35.115145],"type":"Point"}
}