{
  "type": "Feature",
  "properties": {
    "addr:full":"299 N Haywood St Waynesville NC 28786",
    "addr:housenumber":"299",
    "addr:postcode":"28786",
    "addr:street":"N Haywood St",
    "iso:country":"US",
    "sg:address":"299 N Haywood St",
    "sg:city":"Waynesville",
    "sg:classifiers":[
        {
            "category":"Organizations",
            "subcategory":"Non-profit Organization",
            "type":"Services"
        }
    ],
    "sg:phone":"+1 828 452 9456",
    "sg:postcode":"28786",
    "sg:province":"NC",
    "sg:tags":[
        "information",
        "alcoholism",
        "treatment"
    ],
    "wof:name":"New Beginnings",
    "wof:placetype":"venue"
},
  "geometry": {"coordinates":[-82.988941,35.491599],"type":"Point"}
}