{
  "type": "Feature",
  "properties": {
    "iso:country":"US",
    "sg:address":"5725 Concord Pkwy S",
    "sg:city":"Concord",
    "sg:classifiers":[
        {
            "category":"Restaurant",
            "type":"Food & Drink"
        }
    ],
    "sg:phone":"+1 704 455 4340",
    "sg:postcode":"28027",
    "sg:province":"NC",
    "sg:tags":[
        "catering"
    ],
    "sg:website":"www.levyrestaurants.com",
    "wof:name":"Levy Restaurants",
    "wof:placetype":"venue"
},
  "geometry": {"coordinates":[-80.690161,35.349977],"type":"Point"}
}