{
  "type": "Feature",
  "properties": {
    "iso:country":"US",
    "sg:address":"5335 US Hwy 70 Bus W",
    "sg:city":"Clayton",
    "sg:classifiers":[
        {
            "category":"Manufacturing",
            "subcategory":"Retail Goods",
            "type":"Manufacturing & Wholesale Goods"
        }
    ],
    "sg:phone":"+1 919 553 2202",
    "sg:postcode":"27520",
    "sg:province":"NC",
    "sg:tags":[
        "manufacturer"
    ],
    "wof:name":"Magnevolt Inc",
    "wof:placetype":"venue"
},
  "geometry": {"coordinates":[-78.405756,35.587434],"type":"Point"}
}