{
  "type": "Feature",
  "properties": {
    "iso:country":"US",
    "sg:address":"3300 Kellystone Dr",
    "sg:city":"Monroe",
    "sg:classifiers":[
        {
            "category":"Building & Trades",
            "subcategory":"Electrical",
            "type":"Services"
        }
    ],
    "sg:phone":"+1 704 289 9999",
    "sg:postcode":"28110",
    "sg:province":"NC",
    "sg:tags":[
        "electrical",
        "electric",
        "contractor"
    ],
    "wof:name":"No Shorts Electric Inc",
    "wof:placetype":"venue"
},
  "geometry": {"coordinates":[-80.522109,35.028892],"type":"Point"}
}