{
  "type": "Feature",
  "properties": {
    "addr:full":"104 Leah Dr Clayton NC 27520",
    "addr:housenumber":"104",
    "addr:postcode":"27520",
    "addr:street":"Leah Dr",
    "iso:country":"US",
    "sg:address":"104 Leah Dr",
    "sg:city":"Clayton",
    "sg:classifiers":[
        {
            "category":"Professional",
            "type":"Services"
        }
    ],
    "sg:phone":"+1 919 934 1752",
    "sg:postcode":"27520",
    "sg:province":"NC",
    "wof:name":"No Hassle Grass LLC",
    "wof:placetype":"venue"
},
  "geometry": {"coordinates":[-78.50797300000001,35.541821],"type":"Point"}
}