{
  "type": "Feature",
  "properties": {
    "addr:full":"1255 Shady Grove Church Rd Winston Salem NC 27107",
    "addr:housenumber":"1255",
    "addr:postcode":"27107",
    "addr:street":"Shady Grove Church Rd",
    "iso:country":"US",
    "sg:address":"1255 Shady Grove Church Rd",
    "sg:city":"Winston Salem",
    "sg:classifiers":[
        {
            "category":"Retail",
            "subcategory":"Auto Repair",
            "type":"Services"
        }
    ],
    "sg:phone":"+1   ",
    "sg:postcode":"27107",
    "sg:province":"NC",
    "wof:name":"Youngs Tire & Service Inc",
    "wof:placetype":"venue"
},
  "geometry": {"coordinates":[-80.148574,35.975643],"type":"Point"}
}