{
  "type": "Feature",
  "properties": {
    "addr:full":"37 Haywood St Asheville NC 28801",
    "addr:housenumber":"37",
    "addr:postcode":"28801",
    "addr:street":"Haywood St",
    "iso:country":"US",
    "sg:address":"37 Haywood St",
    "sg:city":"Asheville",
    "sg:classifiers":[
        {
            "category":"Social Services",
            "type":"Services"
        }
    ],
    "sg:phone":"+1   ",
    "sg:postcode":"28801",
    "sg:province":"NC",
    "sg:website":"www.steamteam.org",
    "wof:name":"Project STEAM",
    "wof:placetype":"venue"
},
  "geometry": {"coordinates":[-82.55459500000001,35.595609],"type":"Point"}
}