{
  "type": "Feature",
  "properties": {
    "iso:country":"US",
    "sg:address":"504 W Charlotte Ave",
    "sg:city":"Mount Holly",
    "sg:classifiers":[
        {
            "category":"Social Services",
            "subcategory":"Child Care",
            "type":"Services"
        }
    ],
    "sg:phone":"+1 704 827 0700",
    "sg:postcode":"28120",
    "sg:province":"NC",
    "sg:tags":[
        "day",
        "provider"
    ],
    "wof:name":"Mini Academy Day Care Center",
    "wof:placetype":"venue"
},
  "geometry": {"coordinates":[-81.024641,35.301721],"type":"Point"}
}