{
  "type": "Feature",
  "properties": {
    "addr:full":"400 E Franklin St Monroe NC 28112",
    "addr:housenumber":"400",
    "addr:postcode":"28112",
    "addr:street":"E Franklin St",
    "iso:country":"US",
    "sg:address":"400 E Franklin St",
    "sg:city":"Monroe",
    "sg:classifiers":[
        {
            "category":"Professional",
            "subcategory":"Accounting & Tax Preparation",
            "type":"Services"
        }
    ],
    "sg:phone":"+1 704 283 5935",
    "sg:postcode":"28112",
    "sg:province":"NC",
    "sg:tags":[
        "accountant"
    ],
    "wof:name":"Parker Accounting Tax Svcs LLC",
    "wof:placetype":"venue"
},
  "geometry": {"coordinates":[-80.542571,34.981204],"type":"Point"}
}