{
  "type": "Feature",
  "properties": {
    "addr:full":"8950 US Hwy 25 Marshall NC 28753",
    "addr:housenumber":"8950",
    "addr:postcode":"28753",
    "addr:street":"Us Hwy 25",
    "iso:country":"US",
    "sg:address":"8950 US Hwy 25",
    "sg:city":"Marshall",
    "sg:classifiers":[
        {
            "category":"Manufacturing",
            "subcategory":"Lumber",
            "type":"Manufacturing & Wholesale Goods"
        }
    ],
    "sg:phone":"+1 828 649 3821",
    "sg:postcode":"28753",
    "sg:province":"NC",
    "sg:tags":[
        "government"
    ],
    "wof:name":"Forestry Dept",
    "wof:placetype":"venue"
},
  "geometry": {"coordinates":[-82.70656,35.8315],"type":"Point"}
}