{
  "type": "Feature",
  "properties": {
    "iso:country":"US",
    "sg:address":"1916 Cloister Dr",
    "sg:city":"Charlotte",
    "sg:classifiers":[
        {
            "category":"Professional",
            "type":"Services"
        }
    ],
    "sg:phone":"+1 704 364 8052",
    "sg:postcode":"28211",
    "sg:province":"NC",
    "wof:name":"Halsey Hill Inc",
    "wof:placetype":"venue"
},
  "geometry": {"coordinates":[-80.80138700000001,35.159648],"type":"Point"}
}