{
  "type": "Feature",
  "properties": {
    "iso:country":"US",
    "sg:address":"2976 Kedron Ct",
    "sg:city":"Winston Salem",
    "sg:classifiers":[
        {
            "category":"Real Estate",
            "subcategory":"Real Estate Agent",
            "type":"Services"
        }
    ],
    "sg:phone":"+1 336 722 3456",
    "sg:postcode":"27106",
    "sg:province":"NC",
    "sg:tags":[
        "information"
    ],
    "wof:name":"Listingbook Services",
    "wof:placetype":"venue"
},
  "geometry": {"coordinates":[-80.295543,36.12555],"type":"Point"}
}