{
  "type": "Feature",
  "properties": {
    "iso:country":"US",
    "sg:address":"1009 Brook St",
    "sg:city":"Fayetteville",
    "sg:classifiers":[
        {
            "category":"Real Estate",
            "subcategory":"Real Estate Agent",
            "type":"Services"
        }
    ],
    "sg:phone":"+1 910 678 0692",
    "sg:postcode":"28305",
    "sg:province":"NC",
    "sg:tags":[
        "appraiser"
    ],
    "wof:name":"W F Brewer & Assoc",
    "wof:placetype":"venue"
},
  "geometry": {"coordinates":[-78.897828,35.058264],"type":"Point"}
}