{
  "type": "Feature",
  "properties": {
    "addr:full":"1530 Ashley Rd Charlotte NC 28208",
    "addr:housenumber":"1530",
    "addr:postcode":"28208",
    "addr:street":"Ashley Rd",
    "iso:country":"US",
    "sg:address":"1530 Ashley Rd",
    "sg:city":"Charlotte",
    "sg:classifiers":[
        {
            "category":"Retail",
            "subcategory":"Auto Rental",
            "type":"Services"
        }
    ],
    "sg:phone":"+1 704 399 2528",
    "sg:postcode":"28208",
    "sg:province":"NC",
    "sg:tags":[
        "renting",
        "leasing",
        "trailer"
    ],
    "wof:name":"U Haul 780 59",
    "wof:placetype":"venue"
},
  "geometry": {"coordinates":[-80.89711,35.24184],"type":"Point"}
}