{
  "type": "Feature",
  "properties": {
    "addr:full":"5533 State Hwy 42 W Garner NC 27529",
    "addr:housenumber":"5533",
    "addr:postcode":"27529",
    "addr:street":"State Hwy 42 W",
    "iso:country":"US",
    "sg:address":"5533 State Hwy 42 W",
    "sg:city":"Garner",
    "sg:classifiers":[
        {
            "category":"Manufacturing",
            "subcategory":"Signs",
            "type":"Manufacturing & Wholesale Goods"
        },
        {
            "category":"Professional",
            "subcategory":"Art Services",
            "type":"Services"
        }
    ],
    "sg:phone":"+1 919 662 7446",
    "sg:postcode":"27529",
    "sg:province":"NC",
    "sg:tags":[
        "graphic",
        "design"
    ],
    "wof:name":"Image Makers",
    "wof:placetype":"venue"
},
  "geometry": {"coordinates":[-78.567655,35.604902],"type":"Point"}
}