{
  "type": "Feature",
  "properties": {
    "addr:full":"6960 Flower Hill Rd Middlesex NC 27557",
    "addr:housenumber":"6960",
    "addr:postcode":"27557",
    "addr:street":"Flower Hill Rd",
    "iso:country":"US",
    "sg:address":"6960 Flower Hill Rd",
    "sg:city":"Middlesex",
    "sg:classifiers":[
        {
            "category":"Building & Trades",
            "subcategory":"Construction",
            "type":"Services"
        }
    ],
    "sg:phone":"+1 919 284 4310",
    "sg:postcode":"27557",
    "sg:province":"NC",
    "wof:name":"BRS Construction",
    "wof:placetype":"venue"
},
  "geometry": {"coordinates":[-78.18563899999999,35.704393],"type":"Point"}
}