{
  "type": "Feature",
  "properties": {
    "addr:full":"1155 N Main St Marion NC 28752",
    "addr:housenumber":"1155",
    "addr:postcode":"28752",
    "addr:street":"N Main St",
    "iso:country":"US",
    "sg:address":"1155 N Main St",
    "sg:city":"Marion",
    "sg:classifiers":[
        {
            "category":"Food & Beverages",
            "subcategory":"Groceries & Convenience Stores",
            "type":"Retail Goods"
        }
    ],
    "sg:phone":"+1 828 659 0318",
    "sg:postcode":"28752",
    "sg:province":"NC",
    "sg:tags":[
        "grocer"
    ],
    "wof:name":"Grocery Outlet",
    "wof:placetype":"venue"
},
  "geometry": {"coordinates":[-82.023906,35.695514],"type":"Point"}
}