{
  "type": "Feature",
  "properties": {
    "iso:country":"US",
    "sg:address":"4329 Canipe Dr",
    "sg:city":"Charlotte",
    "sg:classifiers":[
        {
            "category":"Real Estate",
            "subcategory":"Real Estate Agent",
            "type":"Services"
        }
    ],
    "sg:phone":"+1 704 597 5040",
    "sg:postcode":"28269",
    "sg:province":"NC",
    "wof:name":"Davis Ridge",
    "wof:placetype":"venue"
},
  "geometry": {"coordinates":[-80.81383599999999,35.349326],"type":"Point"}
}