{
  "type": "Feature",
  "properties": {
    "iso:country":"US",
    "sg:address":"505 S Jones St",
    "sg:city":"Pembroke",
    "sg:classifiers":[
        {
            "category":"Education",
            "subcategory":"School",
            "type":"Public Place"
        }
    ],
    "sg:phone":"+1 910 521 4204",
    "sg:postcode":"28372",
    "sg:province":"NC",
    "wof:name":"Pembroke Elementary School",
    "wof:placetype":"venue"
},
  "geometry": {"coordinates":[-79.194258,34.676727],"type":"Point"}
}