{
  "type": "Feature",
  "properties": {
    "addr:full":"5402 Shady Crest Dr Raleigh NC 27613",
    "addr:housenumber":"5402",
    "addr:postcode":"27613",
    "addr:street":"Shady Crest Dr",
    "iso:country":"US",
    "sg:address":"5402 Shady Crest Dr",
    "sg:city":"Raleigh",
    "sg:classifiers":[
        {
            "category":"Professional",
            "type":"Services"
        }
    ],
    "sg:phone":"+1 919 788 8259",
    "sg:postcode":"27613",
    "sg:province":"NC",
    "wof:name":"Digital Instruments",
    "wof:placetype":"venue"
},
  "geometry": {"coordinates":[-78.72568,35.876012],"type":"Point"}
}