{
  "type": "Feature",
  "properties": {
    "iso:country":"US",
    "sg:address":"1077 Sonoma Rd",
    "sg:city":"Canton",
    "sg:classifiers":[
        {
            "category":"Building & Trades",
            "subcategory":"Construction",
            "type":"Services"
        }
    ],
    "sg:phone":"+1 828 648 3993",
    "sg:postcode":"28716",
    "sg:province":"NC",
    "sg:tags":[
        "hanging",
        "contractor"
    ],
    "wof:name":"Triple H Contracting",
    "wof:placetype":"venue"
},
  "geometry": {"coordinates":[-82.88932200000001,35.476307],"type":"Point"}
}