{
  "type": "Feature",
  "properties": {
    "addr:full":"5415 W Friendly Ave Greensboro NC 27410",
    "addr:housenumber":"5415",
    "addr:postcode":"27410",
    "addr:street":"W Friendly Ave",
    "iso:country":"US",
    "sg:address":"5415 W Friendly Ave",
    "sg:city":"Greensboro",
    "sg:classifiers":[
        {
            "category":"Health Services",
            "subcategory":"Health Practitioner",
            "type":"Services"
        }
    ],
    "sg:phone":"+1   ",
    "sg:postcode":"27410",
    "sg:province":"NC",
    "wof:name":"Novacare Pa Inc",
    "wof:placetype":"venue"
},
  "geometry": {"coordinates":[-79.88426800000001,36.089061],"type":"Point"}
}