{
  "type": "Feature",
  "properties": {
    "addr:full":"7957 Market St Wilmington NC 28411",
    "addr:housenumber":"7957",
    "addr:postcode":"28411",
    "addr:street":"Market St",
    "iso:country":"US",
    "sg:address":"7957 Market St",
    "sg:city":"Wilmington",
    "sg:classifiers":[
        {
            "category":"Organizations",
            "subcategory":"Religious Organization",
            "type":"Services"
        }
    ],
    "sg:phone":"+1 910 686 0176",
    "sg:postcode":"28411",
    "sg:province":"NC",
    "sg:website":"www.thereisliberty.org",
    "wof:name":"Liberty Ministries",
    "wof:placetype":"venue"
},
  "geometry": {"coordinates":[-77.804001,34.287498],"type":"Point"}
}