{
  "type": "Feature",
  "properties": {
    "addr:full":"136 Hall Ave Burlington NC 27215",
    "addr:housenumber":"136",
    "addr:postcode":"27215",
    "addr:street":"Hall Ave",
    "iso:country":"US",
    "sg:address":"136 Hall Ave",
    "sg:city":"Burlington",
    "sg:classifiers":[
        {
            "category":"Health Services",
            "subcategory":"Hospital",
            "type":"Services"
        }
    ],
    "sg:phone":"+1 336 227 7417",
    "sg:postcode":"27215",
    "sg:province":"NC",
    "sg:tags":[
        "mental"
    ],
    "wof:name":"Residential Treatment Svc",
    "wof:placetype":"venue"
},
  "geometry": {"coordinates":[-79.43816099999999,36.099526],"type":"Point"}
}