{
  "type": "Feature",
  "properties": {
    "iso:country":"US",
    "sg:address":"321 W B McLean Dr",
    "sg:city":"Swansboro",
    "sg:classifiers":[
        {
            "category":"Food & Beverages",
            "subcategory":"Groceries & Convenience Stores",
            "type":"Retail Goods"
        }
    ],
    "sg:phone":"+1 252 393 1602",
    "sg:postcode":"28584",
    "sg:province":"NC",
    "wof:name":"Lowes Food Stores Inc",
    "wof:placetype":"venue"
},
  "geometry": {"coordinates":[-77.06576699999999,34.69031],"type":"Point"}
}