{
  "type": "Feature",
  "properties": {
    "iso:country":"US",
    "sg:address":"163 Jackson Store Rd",
    "sg:city":"Beulaville",
    "sg:classifiers":[
        {
            "category":"Professional",
            "subcategory":"Testing Lab",
            "type":"Services"
        }
    ],
    "sg:phone":"+1 910 298 3847",
    "sg:postcode":"28518",
    "sg:province":"NC",
    "sg:tags":[
        "laboratory",
        "management"
    ],
    "wof:name":"Millers Utility Manageme",
    "wof:placetype":"venue"
},
  "geometry": {"coordinates":[-77.829887,34.904576],"type":"Point"}
}