{
  "type": "Feature",
  "properties": {
    "addr:full":"125 W High Ave High Point NC 27260",
    "addr:housenumber":"125",
    "addr:postcode":"27260",
    "addr:street":"W High Ave",
    "iso:country":"US",
    "sg:address":"125 W High Ave",
    "sg:city":"High Point",
    "sg:classifiers":[
        {
            "category":"Building & Trades",
            "subcategory":"Equipment Rental",
            "type":"Services"
        }
    ],
    "sg:phone":"+1   ",
    "sg:postcode":"27260",
    "sg:province":"NC",
    "wof:name":"Happy Rentz Inc",
    "wof:placetype":"venue"
},
  "geometry": {"coordinates":[-80.00765,35.956391],"type":"Point"}
}