{
  "type": "Feature",
  "properties": {
    "iso:country":"US",
    "sg:address":"19382 Riverton Rd",
    "sg:city":"Wagram",
    "sg:classifiers":[
        {
            "category":"Professional",
            "type":"Services"
        }
    ],
    "sg:phone":"+1 910 369 0260",
    "sg:postcode":"28396",
    "sg:province":"NC",
    "wof:name":"Brian Taylor Walls LLC",
    "wof:placetype":"venue"
},
  "geometry": {"coordinates":[-79.354096,34.830487],"type":"Point"}
}