{
  "type": "Feature",
  "properties": {
    "iso:country":"US",
    "sg:address":"103 Crestview Dr",
    "sg:city":"Belmont",
    "sg:classifiers":[
        {
            "category":"Shopping",
            "subcategory":"Discount & Variety Stores",
            "type":"Retail Goods"
        }
    ],
    "sg:phone":"+1 704 825 1639",
    "sg:postcode":"28012",
    "sg:province":"NC",
    "sg:tags":[
        "merchandise",
        "general"
    ],
    "wof:name":"Nualpha Inc",
    "wof:placetype":"venue"
},
  "geometry": {"coordinates":[-81.052943,35.233755],"type":"Point"}
}