{
  "type": "Feature",
  "properties": {
    "iso:country":"US",
    "sg:address":"2432 Harrison Dr",
    "sg:city":"Burlington",
    "sg:classifiers":[
        {
            "category":"Building & Trades",
            "subcategory":"Construction",
            "type":"Services"
        }
    ],
    "sg:phone":"+1 336 229 5235",
    "sg:postcode":"27215",
    "sg:province":"NC",
    "sg:tags":[
        "builder",
        "operative"
    ],
    "wof:name":"ARB Enterprises Inc",
    "wof:placetype":"venue"
},
  "geometry": {"coordinates":[-79.47771,36.055277],"type":"Point"}
}