{
  "type": "Feature",
  "properties": {
    "addr:full":"220 S South St Gastonia NC 28052",
    "addr:housenumber":"220",
    "addr:postcode":"28052",
    "addr:street":"S South St",
    "iso:country":"US",
    "sg:address":"220 S South St",
    "sg:city":"Gastonia",
    "sg:classifiers":[
        {
            "category":"Professional",
            "type":"Services"
        }
    ],
    "sg:phone":"+1 704 861 1302",
    "sg:postcode":"28052",
    "sg:province":"NC",
    "sg:tags":[
        "establishment"
    ],
    "wof:name":"Bst",
    "wof:placetype":"venue"
},
  "geometry": {"coordinates":[-81.183734,35.26097],"type":"Point"}
}