{
  "type": "Feature",
  "properties": {
    "iso:country":"US",
    "sg:address":"121 E Morgan St",
    "sg:city":"Raleigh",
    "sg:classifiers":[
        {
            "category":"Professional",
            "subcategory":"Management & Consulting",
            "type":"Services"
        }
    ],
    "sg:phone":"+1 919 755 1762",
    "sg:postcode":"27601",
    "sg:province":"NC",
    "sg:tags":[
        "consultant",
        "business"
    ],
    "wof:name":"Robert Noell & Assoc",
    "wof:placetype":"venue"
},
  "geometry": {"coordinates":[-78.636827,35.779575],"type":"Point"}
}