{
  "type": "Feature",
  "properties": {
    "addr:full":"100 E Britania Ave Durham NC 27704",
    "addr:housenumber":"100",
    "addr:postcode":"27704",
    "addr:street":"E Britania Ave",
    "iso:country":"US",
    "sg:address":"100 E Britania Ave",
    "sg:city":"Durham",
    "sg:classifiers":[
        {
            "category":"Building & Trades",
            "subcategory":"Construction",
            "type":"Services"
        }
    ],
    "sg:phone":"+1 919 220 1141",
    "sg:postcode":"27704",
    "sg:province":"NC",
    "sg:tags":[
        "general",
        "contractor"
    ],
    "wof:name":"Bordeaux Construction Co Inc",
    "wof:placetype":"venue"
},
  "geometry": {"coordinates":[-78.891031,36.032848],"type":"Point"}
}