{
  "type": "Feature",
  "properties": {
    "iso:country":"US",
    "sg:address":"3938 Bethel Rd",
    "sg:city":"Jonesville",
    "sg:classifiers":[
        {
            "category":"Farming",
            "subcategory":"Dairy Farm",
            "type":"Manufacturing & Wholesale Goods"
        }
    ],
    "sg:phone":"+1 336 835 1048",
    "sg:postcode":"28642",
    "sg:province":"NC",
    "wof:name":"Myers Dairy Inc",
    "wof:placetype":"venue"
},
  "geometry": {"coordinates":[-80.884214,36.219315],"type":"Point"}
}