{
  "type": "Feature",
  "properties": {
    "iso:country":"US",
    "sg:address":"812 Vestavia Woods Dr",
    "sg:city":"Raleigh",
    "sg:classifiers":[
        {
            "category":"Building & Trades",
            "subcategory":"Construction",
            "type":"Services"
        }
    ],
    "sg:phone":"+1 919 846 1341",
    "sg:postcode":"27615",
    "sg:province":"NC",
    "sg:tags":[
        "house"
    ],
    "wof:name":"Baker Development Co Inc",
    "wof:placetype":"venue"
},
  "geometry": {"coordinates":[-78.664993,35.890724],"type":"Point"}
}