{
  "type": "Feature",
  "properties": {
    "iso:country":"US",
    "sg:address":"3032 State Hwy 18 S",
    "sg:city":"Morganton",
    "sg:classifiers":[
        {
            "category":"Retail",
            "subcategory":"Repair Shop",
            "type":"Services"
        }
    ],
    "sg:phone":"+1 828 430 3040",
    "sg:postcode":"28655",
    "sg:province":"NC",
    "sg:tags":[
        "upholsterer"
    ],
    "wof:name":"Bollinger Upholsterers",
    "wof:placetype":"venue"
},
  "geometry": {"coordinates":[-81.640837,35.709864],"type":"Point"}
}