{
  "type": "Feature",
  "properties": {
    "addr:full":"30 E 1st St Lexington NC 27292",
    "addr:housenumber":"30",
    "addr:postcode":"27292",
    "addr:street":"E 1St St",
    "iso:country":"US",
    "sg:address":"30 E 1st St",
    "sg:city":"Lexington",
    "sg:classifiers":[
        {
            "category":"Wholesale",
            "subcategory":"Farm Supplies",
            "type":"Manufacturing & Wholesale Goods"
        }
    ],
    "sg:phone":"+1 336 248 2173",
    "sg:postcode":"27292",
    "sg:province":"NC",
    "sg:tags":[
        "feed"
    ],
    "wof:name":"Davidson Farmers Co-Op",
    "wof:placetype":"venue"
},
  "geometry": {"coordinates":[-80.25189399999999,35.824124],"type":"Point"}
}