{
  "type": "Feature",
  "properties": {
    "addr:full":"3126 Starlight Dr Winston Salem NC 27107",
    "addr:housenumber":"3126",
    "addr:postcode":"27107",
    "addr:street":"Starlight Dr",
    "iso:country":"US",
    "sg:address":"3126 Starlight Dr",
    "sg:city":"Winston Salem",
    "sg:classifiers":[
        {
            "category":"Manufacturing",
            "subcategory":"Petroleum Products",
            "type":"Manufacturing & Wholesale Goods"
        }
    ],
    "sg:phone":"+1 336 788 0432",
    "sg:postcode":"27107",
    "sg:province":"NC",
    "sg:tags":[
        "oil"
    ],
    "wof:name":"Routh Oil Co",
    "wof:placetype":"venue"
},
  "geometry": {"coordinates":[-80.232021,36.055473],"type":"Point"}
}