{
  "type": "Feature",
  "properties": {
    "iso:country":"US",
    "sg:address":"222 S Main St",
    "sg:city":"Star",
    "sg:classifiers":[
        {
            "category":"Education",
            "subcategory":"Library",
            "type":"Public Place"
        }
    ],
    "sg:phone":"+1 910 428 2338",
    "sg:postcode":"27356",
    "sg:province":"NC",
    "wof:name":"Star Public Library",
    "wof:placetype":"venue"
},
  "geometry": {"coordinates":[-79.78404500000001,35.400334],"type":"Point"}
}