{
  "type": "Feature",
  "properties": {
    "iso:country":"US",
    "sg:address":"3729 Yorktown Pl",
    "sg:city":"Raleigh",
    "sg:classifiers":[
        {
            "category":"Building & Trades",
            "subcategory":"Construction",
            "type":"Services"
        }
    ],
    "sg:phone":"+1 919 571 0508",
    "sg:postcode":"27609",
    "sg:province":"NC",
    "sg:tags":[
        "designer",
        "dealer",
        "pool",
        "swimming"
    ],
    "wof:name":"Georgetown North Pool",
    "wof:placetype":"venue"
},
  "geometry": {"coordinates":[-78.63340100000001,35.831288],"type":"Point"}
}