{
  "type": "Feature",
  "properties": {
    "addr:full":"1352 Matthews Township Pkwy Matthews NC 28105",
    "addr:housenumber":"1352",
    "addr:postcode":"28105",
    "addr:street":"Matthews Township Pkwy",
    "iso:country":"US",
    "sg:address":"1352 Matthews Township Pkwy",
    "sg:city":"Matthews",
    "sg:classifiers":[
        {
            "category":"Health Services",
            "subcategory":"Clinic",
            "type":"Services"
        }
    ],
    "sg:phone":"+1   ",
    "sg:postcode":"28105",
    "sg:province":"NC",
    "sg:tags":[
        "care",
        "center",
        "prosthetic"
    ],
    "wof:name":"Prosthetic-Orthotics Care Ctrs",
    "wof:placetype":"venue"
},
  "geometry": {"coordinates":[-80.713623,35.121863],"type":"Point"}
}