{
  "type": "Feature",
  "properties": {
    "addr:full":"3921 High Point Rd Greensboro NC 27407",
    "addr:housenumber":"3921",
    "addr:postcode":"27407",
    "addr:street":"High Point Rd",
    "iso:country":"US",
    "sg:address":"3921 High Point Rd",
    "sg:city":"Greensboro",
    "sg:classifiers":[
        {
            "category":"Personal",
            "subcategory":"Beauty Salon",
            "type":"Services"
        }
    ],
    "sg:phone":"+1 336 299 9955",
    "sg:postcode":"27407",
    "sg:province":"NC",
    "wof:name":"Toms International Salon",
    "wof:placetype":"venue"
},
  "geometry": {"coordinates":[-79.86376199999999,36.035717],"type":"Point"}
}