{
  "type": "Feature",
  "properties": {
    "iso:country":"US",
    "sg:address":"1140 Swains Ln",
    "sg:city":"Harrellsville",
    "sg:phone":"+1 252 356 2418",
    "sg:postcode":"27917",
    "sg:province":"NC",
    "sg:tags":[
        "farm",
        "tobacco"
    ],
    "wof:name":"Brett Holloman",
    "wof:placetype":"venue"
},
  "geometry": {"coordinates":[-75.98194700000001,36.38101],"type":"Point"}
}