{
  "type": "Feature",
  "properties": {
    "addr:full":"136 Elwood Rd Jacksonville NC 28546",
    "addr:housenumber":"136",
    "addr:postcode":"28546",
    "addr:street":"Elwood Rd",
    "iso:country":"US",
    "sg:address":"136 Elwood Rd",
    "sg:city":"Jacksonville",
    "sg:classifiers":[
        {
            "category":"Shopping",
            "type":"Retail Goods"
        }
    ],
    "sg:phone":"+1 910 347 7559",
    "sg:postcode":"28546",
    "sg:province":"NC",
    "sg:tags":[
        "automotive",
        "upholstery"
    ],
    "wof:name":"Carolina Auto Upholstery",
    "wof:placetype":"venue"
},
  "geometry": {"coordinates":[-77.373839,34.79466],"type":"Point"}
}