{
  "type": "Feature",
  "properties": {
    "iso:country":"US",
    "sg:address":"1031 W Williams St",
    "sg:city":"Apex",
    "sg:classifiers":[
        {
            "category":"Health Services",
            "subcategory":"Health Practitioner",
            "type":"Services"
        }
    ],
    "sg:phone":"+1 919 249 4040",
    "sg:postcode":"27502",
    "sg:province":"NC",
    "sg:tags":[
        "therapy",
        "physical"
    ],
    "wof:name":"Excel Physical Therapy",
    "wof:placetype":"venue"
},
  "geometry": {"coordinates":[-78.870199,35.74302],"type":"Point"}
}