{
  "type": "Feature",
  "properties": {
    "addr:full":"235 S Cobb Ave Burlington NC 27217",
    "addr:housenumber":"235",
    "addr:postcode":"27217",
    "addr:street":"S Cobb Ave",
    "iso:country":"US",
    "sg:address":"235 S Cobb Ave",
    "sg:city":"Burlington",
    "sg:classifiers":[
        {
            "category":"Building & Trades",
            "subcategory":"Landscaping Services",
            "type":"Services"
        }
    ],
    "sg:phone":"+1 336 584 1336",
    "sg:postcode":"27217",
    "sg:province":"NC",
    "sg:tags":[
        "lawn",
        "maintenance",
        "grounds"
    ],
    "wof:name":"Kenny & Kevin Lawn Svc Inc",
    "wof:placetype":"venue"
},
  "geometry": {"coordinates":[-79.410962,36.094314],"type":"Point"}
}