{
  "type": "Feature",
  "properties": {
    "addr:full":"828 Hendersonville Rd Asheville NC 28803",
    "addr:housenumber":"828",
    "addr:postcode":"28803",
    "addr:street":"Hendersonville Rd",
    "iso:country":"US",
    "sg:address":"828 Hendersonville Rd",
    "sg:city":"Asheville",
    "sg:classifiers":[
        {
            "category":"Manufacturing",
            "subcategory":"Musical Instruments",
            "type":"Manufacturing & Wholesale Goods"
        },
        {
            "category":"Shopping",
            "subcategory":"Music",
            "type":"Retail Goods"
        }
    ],
    "sg:phone":"+1 828 277 5588",
    "sg:postcode":"28803",
    "sg:province":"NC",
    "sg:tags":[
        "compact",
        "record",
        "disc",
        "tape",
        "mfg"
    ],
    "wof:name":"Blue Ridge Music",
    "wof:placetype":"venue"
},
  "geometry": {"coordinates":[-82.533092,35.543611],"type":"Point"}
}