{
  "type": "Feature",
  "properties": {
    "iso:country":"US",
    "sg:address":"11833 Mourning Dove Ln",
    "sg:city":"Charlotte",
    "sg:classifiers":[
        {
            "category":"Professional",
            "subcategory":"Business Services",
            "type":"Services"
        }
    ],
    "sg:phone":"+1 704 549 1366",
    "sg:postcode":"28269",
    "sg:province":"NC",
    "wof:name":"Apex Business Solutions LLC",
    "wof:placetype":"venue"
},
  "geometry": {"coordinates":[-80.757012,35.360624],"type":"Point"}
}