{
  "type": "Feature",
  "properties": {
    "addr:full":"994 Charlotte Hwy Fairview NC 28730",
    "addr:housenumber":"994",
    "addr:postcode":"28730",
    "addr:street":"Charlotte Hwy",
    "iso:country":"US",
    "sg:address":"994 Charlotte Hwy",
    "sg:city":"Fairview",
    "sg:classifiers":[
        {
            "category":"Building & Trades",
            "subcategory":"Equipment Rental",
            "type":"Services"
        }
    ],
    "sg:phone":"+1 828 628 3004",
    "sg:postcode":"28730",
    "sg:province":"NC",
    "sg:tags":[
        "contractor"
    ],
    "wof:name":"Carolina Equipment",
    "wof:placetype":"venue"
},
  "geometry": {"coordinates":[-82.43768799999999,35.538919],"type":"Point"}
}