{
  "type": "Feature",
  "properties": {
    "iso:country":"US",
    "sg:address":"2328 Declaration Dr",
    "sg:city":"Raleigh",
    "sg:classifiers":[
        {
            "category":"Professional",
            "subcategory":"Business Services",
            "type":"Services"
        }
    ],
    "sg:phone":"+1   ",
    "sg:postcode":"27615",
    "sg:province":"NC",
    "wof:name":"Unicorn Express Inc",
    "wof:placetype":"venue"
},
  "geometry": {"coordinates":[-78.59499599999999,35.880787],"type":"Point"}
}