{
  "type": "Feature",
  "properties": {
    "addr:full":"3647 Sunset Ave Rocky Mount NC 27804",
    "addr:housenumber":"3647",
    "addr:postcode":"27804",
    "addr:street":"Sunset Ave",
    "iso:country":"US",
    "sg:address":"3647 Sunset Ave",
    "sg:city":"Rocky Mount",
    "sg:classifiers":[
        {
            "category":"Professional",
            "subcategory":"Advertising",
            "type":"Services"
        }
    ],
    "sg:phone":"+1 252 443 7700",
    "sg:postcode":"27804",
    "sg:province":"NC",
    "sg:tags":[
        "mailing",
        "shipping"
    ],
    "wof:name":"Mail Boxes Etc",
    "wof:placetype":"venue"
},
  "geometry": {"coordinates":[-77.85367100000001,35.963777],"type":"Point"}
}