{
  "type": "Feature",
  "properties": {
    "addr:full":"537 N Church St Burlington NC 27217",
    "addr:housenumber":"537",
    "addr:postcode":"27217",
    "addr:street":"N Church St",
    "iso:country":"US",
    "sg:address":"537 N Church St",
    "sg:city":"Burlington",
    "sg:classifiers":[
        {
            "category":"Personal",
            "subcategory":"Barber",
            "type":"Services"
        }
    ],
    "sg:phone":"+1   ",
    "sg:postcode":"27217",
    "sg:province":"NC",
    "sg:tags":[
        "shop",
        "beauty"
    ],
    "wof:name":"Headhunters Barber Shop",
    "wof:placetype":"venue"
},
  "geometry": {"coordinates":[-79.430975,36.100405],"type":"Point"}
}