{
  "type": "Feature",
  "properties": {
    "addr:full":"8048 Witty Rd Summerfield NC 27358",
    "addr:postcode":"8048;27358",
    "addr:street":"Witty Rd",
    "iso:country":"US",
    "sg:address":"8048 Witty Rd",
    "sg:city":"Summerfield",
    "sg:classifiers":[
        {
            "category":"Banks & Credit Unions",
            "subcategory":"Financial Services",
            "type":"Services"
        }
    ],
    "sg:phone":"+1 336 644 8652",
    "sg:postcode":"27358",
    "sg:province":"NC",
    "sg:tags":[
        "investor"
    ],
    "wof:name":"Wsg Investment Group LLC",
    "wof:placetype":"venue"
},
  "geometry": {"coordinates":[-79.841809,36.220172],"type":"Point"}
}