{
  "type": "Feature",
  "properties": {
    "addr:full":"225 White St Jacksonville NC 28546",
    "addr:housenumber":"225",
    "addr:postcode":"28546",
    "addr:street":"White St",
    "iso:country":"US",
    "sg:address":"225 White St",
    "sg:city":"Jacksonville",
    "sg:classifiers":[
        {
            "category":"Health Services",
            "subcategory":"Nursing And Care Facility",
            "type":"Services"
        }
    ],
    "sg:phone":"+1 910 353 7222",
    "sg:postcode":"28546",
    "sg:province":"NC",
    "sg:tags":[
        "skilled"
    ],
    "wof:name":"Britthaven",
    "wof:placetype":"venue"
},
  "geometry": {"coordinates":[-77.38575,34.760708],"type":"Point"}
}