{
  "type": "Feature",
  "properties": {
    "addr:full":"71 N Spring St Hot Springs NC 28743",
    "addr:housenumber":"71",
    "addr:postcode":"28743",
    "addr:street":"N Spring St",
    "iso:country":"US",
    "sg:address":"71 N Spring St",
    "sg:city":"Hot Springs",
    "sg:classifiers":[
        {
            "category":"Personal",
            "subcategory":"Beauty Salon",
            "type":"Services"
        }
    ],
    "sg:phone":"+1 828 622 7268",
    "sg:postcode":"28743",
    "sg:province":"NC",
    "wof:name":"Village Hair Styling Salon",
    "wof:placetype":"venue"
},
  "geometry": {"coordinates":[-82.827804,35.893016],"type":"Point"}
}