{
  "type": "Feature",
  "properties": {
    "addr:full":"8415 Maeve Ct Clemmons NC 27012",
    "addr:postcode":"8415;27012",
    "addr:street":"Maeve Ct",
    "iso:country":"US",
    "sg:address":"8415 Maeve Ct",
    "sg:city":"Clemmons",
    "sg:classifiers":[
        {
            "category":"Professional",
            "subcategory":"Business Services",
            "type":"Services"
        }
    ],
    "sg:phone":"+1   ",
    "sg:postcode":"27012",
    "sg:province":"NC",
    "wof:name":"John F Coyne",
    "wof:placetype":"venue"
},
  "geometry": {"coordinates":[-80.410721,36.043084],"type":"Point"}
}