{
  "type": "Feature",
  "properties": {
    "addr:full":"5201 Oak Park Rd Raleigh NC 27612",
    "addr:housenumber":"5201",
    "addr:postcode":"27612",
    "addr:street":"Oak Park Rd",
    "iso:country":"US",
    "sg:address":"5201 Oak Park Rd",
    "sg:city":"Raleigh",
    "sg:classifiers":[
        {
            "category":"Shopping",
            "subcategory":"Hobbies, Toys, & Games",
            "type":"Retail Goods"
        }
    ],
    "sg:phone":"+1 919 881 1010",
    "sg:postcode":"27612",
    "sg:province":"NC",
    "sg:tags":[
        "model",
        "toy",
        "store",
        "supply"
    ],
    "wof:name":"Nick's Trains Inc",
    "wof:placetype":"venue"
},
  "geometry": {"coordinates":[-78.70272,35.854341],"type":"Point"}
}