{
  "type": "Feature",
  "properties": {
    "iso:country":"US",
    "sg:address":"113 Parmele Blvd",
    "sg:city":"Wrightsville Bch",
    "sg:classifiers":[
        {
            "category":"Marine",
            "type":"Transportation"
        }
    ],
    "sg:phone":"+1 910 232 3692",
    "sg:postcode":"28480",
    "sg:province":"NC",
    "sg:tags":[
        "cleaning",
        "boat"
    ],
    "wof:name":"Custom Boat Detailing",
    "wof:placetype":"venue"
},
  "geometry": {"coordinates":[-77.789675,34.22355],"type":"Point"}
}