{
  "type": "Feature",
  "properties": {
    "addr:full":"6933 E W T Harris Blvd Charlotte NC 28215",
    "addr:housenumber":"6933",
    "addr:postcode":"28215",
    "addr:street":"E W T Harris Blvd",
    "iso:country":"US",
    "sg:address":"6933 E W T Harris Blvd",
    "sg:city":"Charlotte",
    "sg:classifiers":[
        {
            "category":"Manufacturing",
            "subcategory":"Printing",
            "type":"Manufacturing & Wholesale Goods"
        }
    ],
    "sg:phone":"+1 704 537 1919",
    "sg:postcode":"28215",
    "sg:province":"NC",
    "sg:tags":[
        "printer"
    ],
    "wof:name":"International Minute Press",
    "wof:placetype":"venue"
},
  "geometry": {"coordinates":[-80.72585599999999,35.225513],"type":"Point"}
}