{
  "type": "Feature",
  "properties": {
    "iso:country":"US",
    "sg:address":"971 W Wards Bridge Rd",
    "sg:city":"Warsaw",
    "sg:classifiers":[
        {
            "category":"Building & Trades",
            "subcategory":"Landscaping Services",
            "type":"Services"
        }
    ],
    "sg:phone":"+1 910 293 7478",
    "sg:postcode":"28398",
    "sg:province":"NC",
    "sg:tags":[
        "lawn",
        "maintenance",
        "grounds"
    ],
    "wof:name":"Wallace Lawn Maint & Tree Svc",
    "wof:placetype":"venue"
},
  "geometry": {"coordinates":[-78.062595,35.007072],"type":"Point"}
}