{
  "type": "Feature",
  "properties": {
    "iso:country":"US",
    "sg:address":"144 Hickory Grove Rd",
    "sg:city":"Mc Adenville",
    "sg:classifiers":[
        {
            "category":"Autos & Motor Vehicles",
            "subcategory":"Automobile Sales",
            "type":"Retail Goods"
        }
    ],
    "sg:phone":"+1 704 827 8484",
    "sg:postcode":"28101",
    "sg:province":"NC",
    "sg:tags":[
        "car",
        "dealer"
    ],
    "wof:name":"Advantage Auto Truck Sales",
    "wof:placetype":"venue"
},
  "geometry": {"coordinates":[-81.07146,35.261729],"type":"Point"}
}