{
  "type": "Feature",
  "properties": {
    "addr:full":"14529 S Brent Dr Huntersville NC 28078",
    "addr:housenumber":"14529",
    "addr:postcode":"28078",
    "addr:street":"S Brent Dr",
    "iso:country":"US",
    "sg:address":"14529 S Brent Dr",
    "sg:city":"Huntersville",
    "sg:classifiers":[
        {
            "category":"Shopping",
            "subcategory":"Computers & Home Electronics",
            "type":"Retail Goods"
        }
    ],
    "sg:phone":"+1 704 948 6038",
    "sg:postcode":"28078",
    "sg:province":"NC",
    "sg:tags":[
        "equipment",
        "dealer"
    ],
    "wof:name":"Compu Com Systems Inc",
    "wof:placetype":"venue"
},
  "geometry": {"coordinates":[-80.878584,35.408666],"type":"Point"}
}