{
  "type": "Feature",
  "properties": {
    "iso:country":"US",
    "sg:address":"214 S 3rd St",
    "sg:city":"Highlands",
    "sg:classifiers":[
        {
            "category":"Professional",
            "subcategory":"Business Services",
            "type":"Services"
        }
    ],
    "sg:phone":"+1   ",
    "sg:postcode":"28741",
    "sg:province":"NC",
    "wof:name":"Jean Macrea Interiors Inc",
    "wof:placetype":"venue"
},
  "geometry": {"coordinates":[-83.199488,35.052742],"type":"Point"}
}