{
  "type": "Feature",
  "properties": {
    "iso:country":"US",
    "sg:address":"684 E Arlington Blvd",
    "sg:city":"Greenville",
    "sg:classifiers":[
        {
            "category":"Shopping",
            "subcategory":"Florist",
            "type":"Retail Goods"
        }
    ],
    "sg:phone":"+1 252 439 0550",
    "sg:postcode":"27858",
    "sg:province":"NC",
    "sg:tags":[
        "gift"
    ],
    "wof:name":"Emerald City Flower Company",
    "wof:placetype":"venue"
},
  "geometry": {"coordinates":[-77.366467,35.582558],"type":"Point"}
}