{
  "type": "Feature",
  "properties": {
    "iso:country":"US",
    "sg:address":"4150 Shattalon Dr",
    "sg:city":"Winston Salem",
    "sg:classifiers":[
        {
            "category":"Professional",
            "subcategory":"Secretarial Services",
            "type":"Services"
        }
    ],
    "sg:phone":"+1 336 924 0389",
    "sg:postcode":"27106",
    "sg:province":"NC",
    "sg:tags":[
        "convention",
        "court",
        "reporter"
    ],
    "wof:name":"Graham Erlacher & Assoc",
    "wof:placetype":"venue"
},
  "geometry": {"coordinates":[-80.344134,36.135981],"type":"Point"}
}