{
  "type": "Feature",
  "properties": {
    "iso:country":"US",
    "sg:address":"2126 Haven Cir",
    "sg:city":"Lenoir",
    "sg:classifiers":[
        {
            "category":"Social Services",
            "subcategory":"Child Care",
            "type":"Services"
        }
    ],
    "sg:phone":"+1   ",
    "sg:postcode":"28645",
    "sg:province":"NC",
    "sg:tags":[
        "day"
    ],
    "wof:name":"Little Ones Child Development",
    "wof:placetype":"venue"
},
  "geometry": {"coordinates":[-81.512936,35.876447],"type":"Point"}
}