{
  "type": "Feature",
  "properties": {
    "addr:full":"511 Lama St Greensboro NC 27406",
    "addr:housenumber":"511",
    "addr:postcode":"27406",
    "addr:street":"Lama St",
    "iso:country":"US",
    "sg:address":"511 Lama St",
    "sg:city":"Greensboro",
    "sg:classifiers":[
        {
            "category":"Social Services",
            "subcategory":"Child Care",
            "type":"Services"
        }
    ],
    "sg:phone":"+1   ",
    "sg:postcode":"27406",
    "sg:province":"NC",
    "sg:tags":[
        "day"
    ],
    "wof:name":"Lama Street Academy",
    "wof:placetype":"venue"
},
  "geometry": {"coordinates":[-79.798407,36.054934],"type":"Point"}
}