{
  "type": "Feature",
  "properties": {
    "iso:country":"US",
    "sg:address":"260 Erwin Rd",
    "sg:city":"Chapel Hill",
    "sg:classifiers":[
        {
            "category":"Organizations",
            "subcategory":"Religious Organization",
            "type":"Services"
        }
    ],
    "sg:phone":"+1 919 408 0310",
    "sg:postcode":"27514",
    "sg:province":"NC",
    "sg:tags":[
        "church"
    ],
    "sg:website":"www.biblechurch.org",
    "wof:name":"Chapel Hill Bible Church",
    "wof:placetype":"venue"
},
  "geometry": {"coordinates":[-79.015428,35.953329],"type":"Point"}
}