{
  "type": "Feature",
  "properties": {
    "iso:country":"US",
    "sg:address":"955 N Wesleyan Blvd",
    "sg:city":"Rocky Mount",
    "sg:classifiers":[
        {
            "category":"Shopping",
            "subcategory":"Crafts & Fabrics",
            "type":"Retail Goods"
        }
    ],
    "sg:phone":"+1 252 972 2444",
    "sg:postcode":"27804",
    "sg:province":"NC",
    "sg:tags":[
        "shop",
        "notion"
    ],
    "sg:website":"www.hancockfabrics.com",
    "wof:name":"Hancock Fabrics 469",
    "wof:placetype":"venue"
},
  "geometry": {"coordinates":[-77.81442699999999,35.968321],"type":"Point"}
}