{
  "type": "Feature",
  "properties": {
    "iso:country":"US",
    "sg:address":"11635 State Hwy 150",
    "sg:city":"Winston Salem",
    "sg:classifiers":[
        {
            "category":"Building & Trades",
            "subcategory":"Construction",
            "type":"Services"
        }
    ],
    "sg:phone":"+1 336 764 1341",
    "sg:postcode":"27127",
    "sg:province":"NC",
    "wof:name":"T F Scott Construction Company",
    "wof:placetype":"venue"
},
  "geometry": {"coordinates":[-80.27504500000001,35.987638],"type":"Point"}
}