{
  "type": "Feature",
  "properties": {
    "addr:full":"5726 Fayetteville Rd Durham NC 27713",
    "addr:housenumber":"5726",
    "addr:postcode":"27713",
    "addr:street":"Fayetteville Rd",
    "iso:country":"US",
    "sg:address":"5726 Fayetteville Rd",
    "sg:city":"Durham",
    "sg:classifiers":[
        {
            "category":"Banks & Credit Unions",
            "subcategory":"Bank",
            "type":"Services"
        }
    ],
    "sg:phone":"+1 919 206 4187",
    "sg:postcode":"27713",
    "sg:province":"NC",
    "sg:tags":[
        "loan",
        "real estate"
    ],
    "wof:name":"Alpha Home Mortgage Inc",
    "wof:placetype":"venue"
},
  "geometry": {"coordinates":[-78.928015,35.921929],"type":"Point"}
}