{
  "type": "Feature",
  "properties": {
    "addr:full":"630 Lance Rd Fletcher NC 28732",
    "addr:housenumber":"630",
    "addr:postcode":"28732",
    "addr:street":"Lance Rd",
    "iso:country":"US",
    "sg:address":"630 Lance Rd",
    "sg:city":"Fletcher",
    "sg:classifiers":[
        {
            "category":"Building & Trades",
            "subcategory":"Construction",
            "type":"Services"
        }
    ],
    "sg:phone":"+1 828 891 8998",
    "sg:postcode":"28732",
    "sg:province":"NC",
    "sg:tags":[
        "carpentry",
        "contractor"
    ],
    "wof:name":"Stangel Carpentry",
    "wof:placetype":"venue"
},
  "geometry": {"coordinates":[-82.568417,35.416447],"type":"Point"}
}