{
  "type": "Feature",
  "properties": {
    "iso:country":"US",
    "sg:address":"1205 Paddock Dr",
    "sg:city":"Raleigh",
    "sg:classifiers":[
        {
            "category":"Organizations",
            "subcategory":"Religious Organization",
            "type":"Services"
        }
    ],
    "sg:phone":"+1   ",
    "sg:postcode":"27609",
    "sg:province":"NC",
    "wof:name":"Southeast Christian Ministries",
    "wof:placetype":"venue"
},
  "geometry": {"coordinates":[-78.616445,35.851884],"type":"Point"}
}