{
  "type": "Feature",
  "properties": {
    "addr:full":"400 Four Seasons Town Center Greensboro NC 27407",
    "addr:housenumber":"400",
    "addr:postcode":"27407",
    "addr:street":"Four Seasons",
    "iso:country":"US",
    "sg:address":"400 Four Seasons Town Center",
    "sg:city":"Greensboro",
    "sg:classifiers":[
        {
            "category":"Shopping",
            "subcategory":"Gifts & Souvenirs",
            "type":"Retail Goods"
        }
    ],
    "sg:phone":"+1 336 854 8887",
    "sg:postcode":"27407",
    "sg:province":"NC",
    "sg:tags":[
        "shop"
    ],
    "wof:name":"Nautical Hangups",
    "wof:placetype":"venue"
},
  "geometry": {"coordinates":[-79.840008,36.038607],"type":"Point"}
}