{
  "type": "Feature",
  "properties": {
    "iso:country":"US",
    "sg:address":"108 Hamilton Rd",
    "sg:city":"Lexington",
    "sg:classifiers":[
        {
            "category":"Retail",
            "subcategory":"Veterinary Services",
            "type":"Services"
        }
    ],
    "sg:phone":"+1 336 249 1211",
    "sg:postcode":"27295",
    "sg:province":"NC",
    "sg:tags":[
        "hospital",
        "animal"
    ],
    "wof:name":"Animal Center Of Davidson Cnty",
    "wof:placetype":"venue"
},
  "geometry": {"coordinates":[-80.243257,35.836627],"type":"Point"}
}