{
  "type": "Feature",
  "properties": {
    "iso:country":"US",
    "sg:address":"100 Arendell St",
    "sg:city":"Morehead City",
    "sg:classifiers":[
        {
            "category":"Organizations",
            "subcategory":"Labor Organization",
            "type":"Services"
        }
    ],
    "sg:phone":"+1 252 726 3275",
    "sg:postcode":"28557",
    "sg:province":"NC",
    "wof:name":"ILA",
    "wof:placetype":"venue"
},
  "geometry": {"coordinates":[-76.696168,34.720767],"type":"Point"}
}