{
  "type": "Feature",
  "properties": {
    "addr:full":"1420 National Hwy Thomasville NC 27360",
    "addr:housenumber":"1420",
    "addr:postcode":"27360",
    "addr:street":"National Hwy",
    "iso:country":"US",
    "sg:address":"1420 National Hwy",
    "sg:city":"Thomasville",
    "sg:classifiers":[
        {
            "category":"Banks & Credit Unions",
            "subcategory":"Bank",
            "type":"Services"
        }
    ],
    "sg:phone":"+1 336 887 2511",
    "sg:postcode":"27360",
    "sg:province":"NC",
    "sg:tags":[
        "cashing",
        "check"
    ],
    "wof:name":"Check 'n Go",
    "wof:placetype":"venue"
},
  "geometry": {"coordinates":[-80.06278500000001,35.906094],"type":"Point"}
}