{
  "type": "Feature",
  "properties": {
    "iso:country":"US",
    "sg:address":"6401 Carmel Rd",
    "sg:city":"Charlotte",
    "sg:classifiers":[
        {
            "category":"Real Estate",
            "subcategory":"Real Estate Services",
            "type":"Services"
        },
        {
            "category":"Real Estate",
            "subcategory":"Real Estate Agent",
            "type":"Services"
        }
    ],
    "sg:phone":"+1 704 714 1141",
    "sg:postcode":"28226",
    "sg:province":"NC",
    "sg:tags":[
        "buyer",
        "broker"
    ],
    "wof:name":"Carolina Real Estate Advisors",
    "wof:placetype":"venue"
},
  "geometry": {"coordinates":[-80.844416,35.090695],"type":"Point"}
}