{
  "type": "Feature",
  "properties": {
    "iso:country":"US",
    "sg:address":"130 Lewisville Clemmons Rd",
    "sg:city":"Lewisville",
    "sg:phone":"+1 336 945 2061",
    "sg:postcode":"27023",
    "sg:province":"NC",
    "sg:tags":[
        "oil"
    ],
    "wof:name":"G & B Oil Co",
    "wof:placetype":"venue"
},
  "geometry": {"coordinates":[-80.418414,36.096022],"type":"Point"}
}