{
  "type": "Feature",
  "properties": {
    "addr:full":"320 Nash St E Wilson NC 27893",
    "addr:housenumber":"320",
    "addr:postcode":"27893",
    "addr:street":"Nash St E",
    "iso:country":"US",
    "sg:address":"320 Nash St E",
    "sg:city":"Wilson",
    "sg:classifiers":[
        {
            "category":"Restaurant",
            "type":"Food & Drink"
        }
    ],
    "sg:phone":"+1 252 237 0157",
    "sg:postcode":"27893",
    "sg:province":"NC",
    "wof:name":"Bus Stop Grill",
    "wof:placetype":"venue"
},
  "geometry": {"coordinates":[-77.909288,35.723891],"type":"Point"}
}