{
  "type": "Feature",
  "properties": {
    "addr:full":"920 Wagstaff Rd Fuquay Varina NC 27526",
    "addr:housenumber":"920",
    "addr:postcode":"27526",
    "addr:street":"Wagstaff Rd",
    "iso:country":"US",
    "sg:address":"920 Wagstaff Rd",
    "sg:city":"Fuquay Varina",
    "sg:classifiers":[
        {
            "category":"Building & Trades",
            "subcategory":"Construction",
            "type":"Services"
        }
    ],
    "sg:phone":"+1 919 557 7671",
    "sg:postcode":"27526",
    "sg:province":"NC",
    "sg:tags":[
        "carpentry",
        "contractor"
    ],
    "wof:name":"Graham Building Co Inc",
    "wof:placetype":"venue"
},
  "geometry": {"coordinates":[-78.82356799999999,35.562914],"type":"Point"}
}