{
  "type": "Feature",
  "properties": {
    "addr:full":"6001 Glenwood Ave Raleigh NC 27612",
    "addr:housenumber":"6001",
    "addr:postcode":"27612",
    "addr:street":"Glenwood Ave",
    "iso:country":"US",
    "sg:address":"6001 Glenwood Ave",
    "sg:city":"Raleigh",
    "sg:classifiers":[
        {
            "category":"Real Estate",
            "subcategory":"Real Estate Services",
            "type":"Services"
        }
    ],
    "sg:phone":"+1 919 787 0181",
    "sg:postcode":"27612",
    "sg:province":"NC",
    "wof:name":"Connell John M Rl Est",
    "wof:placetype":"venue"
},
  "geometry": {"coordinates":[-78.70059999999999,35.854599],"type":"Point"}
}