{
  "type": "Feature",
  "properties": {
    "iso:country":"US",
    "sg:address":"110 Sheraton Ct",
    "sg:city":"King",
    "sg:classifiers":[
        {
            "category":"Freight",
            "type":"Transportation"
        }
    ],
    "sg:phone":"+1 336 983 9857",
    "sg:postcode":"27021",
    "sg:province":"NC",
    "sg:tags":[
        "distance",
        "long",
        "trucking"
    ],
    "wof:name":"K&L Trucking",
    "wof:placetype":"venue"
},
  "geometry": {"coordinates":[-80.37946100000001,36.263744],"type":"Point"}
}