{
  "type": "Feature",
  "properties": {
    "iso:country":"US",
    "sg:address":"6319 Cook Ave",
    "sg:city":"Clemmons",
    "sg:classifiers":[
        {
            "category":"Insurance",
            "subcategory":"Insurance Agent",
            "type":"Services"
        }
    ],
    "sg:phone":"+1 336 778 2278",
    "sg:postcode":"27012",
    "sg:province":"NC",
    "wof:name":"Carolina Commercial Insurance",
    "wof:placetype":"venue"
},
  "geometry": {"coordinates":[-80.37917899999999,36.027662],"type":"Point"}
}