{
  "type": "Feature",
  "properties": {
    "iso:country":"US",
    "sg:address":"111 W Broad St",
    "sg:city":"Statesville",
    "sg:classifiers":[
        {
            "category":"Professional",
            "subcategory":"Lawyer & Legal Services",
            "type":"Services"
        }
    ],
    "sg:phone":"+1 704 878 2365",
    "sg:postcode":"28677",
    "sg:province":"NC",
    "sg:tags":[
        "attorney"
    ],
    "wof:name":"Judith M Daly Law Office",
    "wof:placetype":"venue"
},
  "geometry": {"coordinates":[-80.888401,35.784509],"type":"Point"}
}