{
  "type": "Feature",
  "properties": {
    "addr:full":"1036 Beecher Rd Winston Salem NC 27104",
    "addr:housenumber":"1036",
    "addr:postcode":"27104",
    "addr:street":"Beecher Rd",
    "iso:country":"US",
    "sg:address":"1036 Beecher Rd",
    "sg:city":"Winston Salem",
    "sg:classifiers":[
        {
            "category":"Professional",
            "subcategory":"Management & Consulting",
            "type":"Services"
        }
    ],
    "sg:phone":"+1   ",
    "sg:postcode":"27104",
    "sg:province":"NC",
    "wof:name":"Windward Direct Mktg Group",
    "wof:placetype":"venue"
},
  "geometry": {"coordinates":[-80.332155,36.108678],"type":"Point"}
}