{
  "type": "Feature",
  "properties": {
    "addr:full":"112 Banterling Ct Mooresville NC 28115",
    "addr:housenumber":"112",
    "addr:postcode":"28115",
    "addr:street":"Banterling Ct",
    "iso:country":"US",
    "sg:address":"112 Banterling Ct",
    "sg:city":"Mooresville",
    "sg:classifiers":[
        {
            "category":"Restaurant",
            "type":"Food & Drink"
        }
    ],
    "sg:phone":"+1 704 799 6405",
    "sg:postcode":"28115",
    "sg:province":"NC",
    "sg:tags":[
        "eating"
    ],
    "wof:name":"Cjs Home Inspection",
    "wof:placetype":"venue"
},
  "geometry": {"coordinates":[-80.82024,35.621236],"type":"Point"}
}