{
  "type": "Feature",
  "properties": {
    "iso:country":"US",
    "sg:address":"125 E Franklin St",
    "sg:city":"Chapel Hill",
    "sg:classifiers":[
        {
            "category":"Food & Beverages",
            "subcategory":"Bakery",
            "type":"Retail Goods"
        }
    ],
    "sg:phone":"+1 919 929 3639",
    "sg:postcode":"27514",
    "sg:province":"NC",
    "wof:name":"Katies Soft Pretzels",
    "wof:placetype":"venue"
},
  "geometry": {"coordinates":[-79.05494400000001,35.913516],"type":"Point"}
}