{
  "type": "Feature",
  "properties": {
    "addr:full":"1516 Ford Rd Chapel Hill NC 27516",
    "addr:housenumber":"1516",
    "addr:postcode":"27516",
    "addr:street":"Ford Rd",
    "iso:country":"US",
    "sg:address":"1516 Ford Rd",
    "sg:city":"Chapel Hill",
    "sg:classifiers":[
        {
            "category":"Freight",
            "type":"Transportation"
        }
    ],
    "sg:phone":"+1 919 967 4313",
    "sg:postcode":"27516",
    "sg:province":"NC",
    "sg:tags":[
        "operator",
        "local",
        "trucking"
    ],
    "wof:name":"Joe Harris Trucking",
    "wof:placetype":"venue"
},
  "geometry": {"coordinates":[-79.16919799999999,35.893791],"type":"Point"}
}