{
  "type": "Feature",
  "properties": {
    "iso:country":"US",
    "sg:address":"330 Jake Alexander Blvd W",
    "sg:city":"Salisbury",
    "sg:classifiers":[
        {
            "category":"Health Services",
            "subcategory":"Clinic",
            "type":"Services"
        }
    ],
    "sg:phone":"+1 704 637 0292",
    "sg:postcode":"28147",
    "sg:province":"NC",
    "wof:name":"Health Mgmt Resources Inc",
    "wof:placetype":"venue"
},
  "geometry": {"coordinates":[-80.49890000000001,35.651915],"type":"Point"}
}