{
  "type": "Feature",
  "properties": {
    "iso:country":"US",
    "sg:address":"1809 Elkhart Dr",
    "sg:city":"Greensboro",
    "sg:classifiers":[
        {
            "category":"Building & Trades",
            "subcategory":"Landscaping Services",
            "type":"Services"
        }
    ],
    "sg:phone":"+1 336 340 3000",
    "sg:postcode":"27408",
    "sg:province":"NC",
    "sg:tags":[
        "business"
    ],
    "wof:name":"Grassroots Lawn Care",
    "wof:placetype":"venue"
},
  "geometry": {"coordinates":[-79.814645,36.10854],"type":"Point"}
}