{
  "type": "Feature",
  "properties": {
    "iso:country":"US",
    "sg:address":"3621 Bastion Ln",
    "sg:city":"Raleigh",
    "sg:classifiers":[
        {
            "category":"Retail",
            "subcategory":"Laundry & Dry Cleaning",
            "type":"Services"
        }
    ],
    "sg:phone":"+1 919 231 9797",
    "sg:postcode":"27604",
    "sg:province":"NC",
    "wof:name":"After Disaster",
    "wof:placetype":"venue"
},
  "geometry": {"coordinates":[-78.58397600000001,35.798187],"type":"Point"}
}