{
  "type": "Feature",
  "properties": {
    "iso:country":"US",
    "sg:address":"1249 Thelma Rd",
    "sg:city":"Roanoke Rapids",
    "sg:classifiers":[
        {
            "category":"Building & Trades",
            "subcategory":"Equipment Rental",
            "type":"Services"
        }
    ],
    "sg:phone":"+1   ",
    "sg:postcode":"27870",
    "sg:province":"NC",
    "wof:name":"Rapid Portable Toilets",
    "wof:placetype":"venue"
},
  "geometry": {"coordinates":[-77.696389,36.465516],"type":"Point"}
}