{
  "type": "Feature",
  "properties": {
    "addr:full":"307 S Salem St Ste 100 Apex NC 27502",
    "addr:housenumber":"307",
    "addr:postcode":"27502",
    "addr:street":"S Salem St Ste 100",
    "iso:country":"US",
    "sg:address":"307 S Salem St Ste 100",
    "sg:city":"Apex",
    "sg:classifiers":[
        {
            "category":"Health Services",
            "subcategory":"Clinic",
            "type":"Services"
        }
    ],
    "sg:phone":"+1 919 434 6398",
    "sg:postcode":"27502",
    "sg:province":"NC",
    "sg:tags":[
        "medical"
    ],
    "wof:name":"Stonebridge Counseling",
    "wof:placetype":"venue"
},
  "geometry": {"coordinates":[-78.853257,35.727878],"type":"Point"}
}