{
  "type": "Feature",
  "properties": {
    "addr:full":"606 Peanut Plant Rd Elizabethtown NC 28337",
    "addr:housenumber":"606",
    "addr:postcode":"28337",
    "addr:street":"Peanut Plant Rd",
    "iso:country":"US",
    "sg:address":"606 Peanut Plant Rd",
    "sg:city":"Elizabethtown",
    "sg:classifiers":[
        {
            "category":"Retail",
            "subcategory":"Veterinary Services",
            "type":"Services"
        }
    ],
    "sg:phone":"+1 910 862 3960",
    "sg:postcode":"28337",
    "sg:province":"NC",
    "sg:tags":[
        "veterinarian"
    ],
    "wof:name":"Bladen Animal Hospital",
    "wof:placetype":"venue"
},
  "geometry": {"coordinates":[-78.623676,34.625138],"type":"Point"}
}