{
  "type": "Feature",
  "properties": {
    "iso:country":"US",
    "sg:address":"3379 Nc 69",
    "sg:city":"Hayesville",
    "sg:classifiers":[
        {
            "category":"Autos & Motor Vehicles",
            "subcategory":"Auto Supplies",
            "type":"Retail Goods"
        }
    ],
    "sg:phone":"+1 828 389 0100",
    "sg:postcode":"28904",
    "sg:province":"NC",
    "sg:tags":[
        "tire"
    ],
    "wof:name":"Thomas Sean Tire & Service",
    "wof:placetype":"venue"
},
  "geometry": {"coordinates":[-83.824066,34.995857],"type":"Point"}
}