{
  "type": "Feature",
  "properties": {
    "addr:full":"259 Creek Water Farm Rd State Road NC 28676",
    "addr:housenumber":"259",
    "addr:postcode":"28676",
    "addr:street":"Creek Water Farm Rd",
    "iso:country":"US",
    "sg:address":"259 Creek Water Farm Rd",
    "sg:city":"State Road",
    "sg:classifiers":[
        {
            "category":"Farming",
            "subcategory":"Livestock Farm",
            "type":"Manufacturing & Wholesale Goods"
        }
    ],
    "sg:phone":"+1 336 874 2170",
    "sg:postcode":"28676",
    "sg:province":"NC",
    "sg:tags":[
        "animal",
        "general"
    ],
    "wof:name":"Creekwater Farm",
    "wof:placetype":"venue"
},
  "geometry": {"coordinates":[-80.862861,36.338302],"type":"Point"}
}