{
  "type": "Feature",
  "properties": {
    "iso:country":"US",
    "sg:address":"440 Cricket Creek Ln",
    "sg:city":"Kittrell",
    "sg:classifiers":[
        {
            "category":"Building & Trades",
            "subcategory":"Plumbing",
            "type":"Services"
        }
    ],
    "sg:phone":"+1 252 438 6023",
    "sg:postcode":"27544",
    "sg:province":"NC",
    "sg:tags":[
        "plumber",
        "drain",
        "tank",
        "septic",
        "consultant",
        "system",
        "sewer"
    ],
    "wof:name":"Moore K T Septic Tank Service",
    "wof:placetype":"venue"
},
  "geometry": {"coordinates":[-78.42559900000001,36.17048],"type":"Point"}
}