{
  "type": "Feature",
  "properties": {
    "addr:full":"3151 Gordonton Rd Hurdle Mills NC 27541",
    "addr:housenumber":"3151",
    "addr:postcode":"27541",
    "addr:street":"Gordonton Rd",
    "iso:country":"US",
    "sg:address":"3151 Gordonton Rd",
    "sg:city":"Hurdle Mills",
    "sg:phone":"+1 336 599 0643",
    "sg:postcode":"27541",
    "sg:province":"NC",
    "sg:tags":[
        "farm",
        "tobacco"
    ],
    "wof:name":"Donald Hester Farm",
    "wof:placetype":"venue"
},
  "geometry": {"coordinates":[-79.13732299999999,36.343769],"type":"Point"}
}