{
  "type": "Feature",
  "properties": {
    "iso:country":"US",
    "sg:address":"2463 Green Swamp Rd",
    "sg:city":"Bolton",
    "sg:classifiers":[
        {
            "category":"Building & Trades",
            "subcategory":"Construction",
            "type":"Services"
        }
    ],
    "sg:phone":"+1 910 655 8790",
    "sg:postcode":"28423",
    "sg:province":"NC",
    "sg:tags":[
        "water",
        "sewer",
        "utility"
    ],
    "wof:name":"Southern Environmental Company",
    "wof:placetype":"venue"
},
  "geometry": {"coordinates":[-78.441271,34.356781],"type":"Point"}
}