{
  "type": "Feature",
  "properties": {
    "addr:full":"104 Corbett St Snow Hill NC 28580",
    "addr:housenumber":"104",
    "addr:postcode":"28580",
    "addr:street":"Corbett St",
    "iso:country":"US",
    "sg:address":"104 Corbett St",
    "sg:city":"Snow Hill",
    "sg:classifiers":[
        {
            "category":"Real Estate",
            "subcategory":"Real Estate Operator",
            "type":"Services"
        }
    ],
    "sg:phone":"+1 252 747 3853",
    "sg:postcode":"28580",
    "sg:province":"NC",
    "sg:tags":[
        "property",
        "lessor"
    ],
    "wof:name":"Joshua Mewborn Farm Inc",
    "wof:placetype":"venue"
},
  "geometry": {"coordinates":[-77.673636,35.455303],"type":"Point"}
}