{
  "type": "Feature",
  "properties": {
    "addr:full":"402 Higgins Rd Ennice NC 28623",
    "addr:housenumber":"402",
    "addr:postcode":"28623",
    "addr:street":"Higgins Rd",
    "iso:country":"US",
    "sg:address":"402 Higgins Rd",
    "sg:city":"Ennice",
    "sg:classifiers":[
        {
            "category":"Home & Garden",
            "subcategory":"Garden Supply",
            "type":"Retail Goods"
        }
    ],
    "sg:phone":"+1 336 657 8276",
    "sg:postcode":"28623",
    "sg:province":"NC",
    "sg:tags":[
        "tree",
        "christmas"
    ],
    "wof:name":"Edward's Evergreens",
    "wof:placetype":"venue"
},
  "geometry": {"coordinates":[-80.974754,36.499887],"type":"Point"}
}