{
  "type": "Feature",
  "properties": {
    "addr:full":"7229 George Hildebran Rd Hickory NC 28602",
    "addr:housenumber":"7229",
    "addr:postcode":"28602",
    "addr:street":"George Hildebran Rd",
    "iso:country":"US",
    "sg:address":"7229 George Hildebran Rd",
    "sg:city":"Hickory",
    "sg:classifiers":[
        {
            "category":"Building & Trades",
            "subcategory":"Plumbing",
            "type":"Services"
        }
    ],
    "sg:phone":"+1 828 304 8285",
    "sg:postcode":"28602",
    "sg:province":"NC",
    "sg:tags":[
        "conditioning",
        "air",
        "system",
        "contractor"
    ],
    "wof:name":"Mc Kinney's Heating & Air",
    "wof:placetype":"venue"
},
  "geometry": {"coordinates":[-81.43047300000001,35.666123],"type":"Point"}
}