{
  "type": "Feature",
  "properties": {
    "addr:full":"4336 Indiana Ave Winston Salem NC 27105",
    "addr:housenumber":"4336",
    "addr:postcode":"27105",
    "addr:street":"Indiana Ave",
    "iso:country":"US",
    "sg:address":"4336 Indiana Ave",
    "sg:city":"Winston Salem",
    "sg:classifiers":[
        {
            "category":"Building & Trades",
            "subcategory":"Construction",
            "type":"Services"
        }
    ],
    "sg:phone":"+1 336 661 0208",
    "sg:postcode":"27105",
    "sg:province":"NC",
    "sg:tags":[
        "contractor"
    ],
    "wof:name":"C S M Welding",
    "wof:placetype":"venue"
},
  "geometry": {"coordinates":[-80.26105200000001,36.147063],"type":"Point"}
}