{
  "type": "Feature",
  "properties": {
    "iso:country":"US",
    "sg:address":"937 US Hwy 13 Bus",
    "sg:city":"Windsor",
    "sg:classifiers":[
        {
            "category":"Organizations",
            "subcategory":"Religious Organization",
            "type":"Services"
        }
    ],
    "sg:phone":"+1 252 794 9453",
    "sg:postcode":"27983",
    "sg:province":"NC",
    "sg:tags":[
        "church"
    ],
    "wof:name":"Free Temple Revival Ctr",
    "wof:placetype":"venue"
},
  "geometry": {"coordinates":[-76.95231800000001,36.005903],"type":"Point"}
}