{
  "type": "Feature",
  "properties": {
    "iso:country":"US",
    "sg:address":"8700 Pineville-Matthews Rd",
    "sg:city":"Charlotte",
    "sg:classifiers":[
        {
            "category":"Health Services",
            "subcategory":"Optometrist",
            "type":"Services"
        }
    ],
    "sg:phone":"+1 704 541 8448",
    "sg:postcode":"28226",
    "sg:province":"NC",
    "wof:name":"Doctors Vision Ctr",
    "wof:placetype":"venue"
},
  "geometry": {"coordinates":[-80.86993699999999,35.089256],"type":"Point"}
}