{
  "type": "Feature",
  "properties": {
    "addr:full":"568 Hillview Dr Lexington NC 27292",
    "addr:housenumber":"568",
    "addr:postcode":"27292",
    "addr:street":"Hillview Dr",
    "iso:country":"US",
    "sg:address":"568 Hillview Dr",
    "sg:city":"Lexington",
    "sg:classifiers":[
        {
            "category":"Retail",
            "subcategory":"Repair Shop",
            "type":"Services"
        }
    ],
    "sg:phone":"+1   ",
    "sg:postcode":"27292",
    "sg:province":"NC",
    "wof:name":"Vickers Wildlife Studio",
    "wof:placetype":"venue"
},
  "geometry": {"coordinates":[-80.252116,35.712359],"type":"Point"}
}