{
  "type": "Feature",
  "properties": {
    "iso:country":"US",
    "sg:address":"10417 Balmoral Cir",
    "sg:city":"Charlotte",
    "sg:classifiers":[
        {
            "category":"Professional",
            "subcategory":"Management & Consulting",
            "type":"Services"
        }
    ],
    "sg:phone":"+1   ",
    "sg:postcode":"28210",
    "sg:province":"NC",
    "wof:name":"Joes Marketing Inc",
    "wof:placetype":"venue"
},
  "geometry": {"coordinates":[-80.871105,35.103605],"type":"Point"}
}