{
  "type": "Feature",
  "properties": {
    "iso:country":"US",
    "sg:address":"107 N Main St",
    "sg:city":"Randleman",
    "sg:classifiers":[
        {
            "category":"Manufacturing",
            "subcategory":"Printing",
            "type":"Manufacturing & Wholesale Goods"
        }
    ],
    "sg:phone":"+1 336 495 3076",
    "sg:postcode":"27317",
    "sg:province":"NC",
    "sg:tags":[
        "screen",
        "printer",
        "commercial"
    ],
    "wof:name":"Trogdon Printing Co",
    "wof:placetype":"venue"
},
  "geometry": {"coordinates":[-79.803161,35.817936],"type":"Point"}
}