{
  "type": "Feature",
  "properties": {
    "addr:full":"7216 E Marshville Blvd Marshville NC 28103",
    "addr:housenumber":"7216",
    "addr:postcode":"28103",
    "addr:street":"E Marshville Blvd",
    "iso:country":"US",
    "sg:address":"7216 E Marshville Blvd",
    "sg:city":"Marshville",
    "sg:classifiers":[
        {
            "category":"Restaurant",
            "type":"Food & Drink"
        }
    ],
    "sg:menulink":"http://www.allmenus.com/nc/marshville/236853-top-china/menu/",
    "sg:phone":"+1 704 624 3836",
    "sg:postcode":"28103",
    "sg:province":"NC",
    "sg:tags":[
        "asian",
        "chinese"
    ],
    "wof:name":"Top China",
    "wof:placetype":"venue"
},
  "geometry": {"coordinates":[-80.35342300000001,34.987188],"type":"Point"}
}