{
  "type": "Feature",
  "properties": {
    "addr:full":"1794 Red Hill Rd Mount Olive NC 28365",
    "addr:housenumber":"1794",
    "addr:postcode":"28365",
    "addr:street":"Red Hill Rd",
    "iso:country":"US",
    "sg:address":"1794 Red Hill Rd",
    "sg:city":"Mount Olive",
    "sg:classifiers":[
        {
            "category":"Government",
            "subcategory":"Fire Station",
            "type":"Public Place"
        }
    ],
    "sg:phone":"+1 919 658 5793",
    "sg:postcode":"28365",
    "sg:province":"NC",
    "sg:tags":[
        "protection"
    ],
    "wof:name":"Pleasant Grove Vol Fire Dept",
    "wof:placetype":"venue"
},
  "geometry": {"coordinates":[-77.87364700000001,35.113382],"type":"Point"}
}