{
  "type": "Feature",
  "properties": {
    "iso:country":"US",
    "sg:address":"1000 Cape Hickory Rd",
    "sg:city":"Hickory",
    "sg:classifiers":[
        {
            "category":"Building & Trades",
            "subcategory":"Cleaning & Sanitation",
            "type":"Services"
        }
    ],
    "sg:phone":"+1 828 325 0072",
    "sg:postcode":"28601",
    "sg:province":"NC",
    "sg:tags":[
        "ventilating",
        "system"
    ],
    "wof:name":"72 Degrees Of Hickory",
    "wof:placetype":"venue"
},
  "geometry": {"coordinates":[-81.421853,35.748377],"type":"Point"}
}