{
  "type": "Feature",
  "properties": {
    "iso:country":"US",
    "sg:address":"3100 Jefferson Davis Hwy",
    "sg:city":"Sanford",
    "sg:classifiers":[
        {
            "category":"Home & Garden",
            "subcategory":"Furniture",
            "type":"Retail Goods"
        }
    ],
    "sg:phone":"+1 919 708 6880",
    "sg:postcode":"27332",
    "sg:province":"NC",
    "wof:name":"What Not Shops",
    "wof:placetype":"venue"
},
  "geometry": {"coordinates":[-79.230328,35.413796],"type":"Point"}
}