{
  "type": "Feature",
  "properties": {
    "addr:full":"4018 US Hwy 74 Monroe NC 28110",
    "addr:housenumber":"4018",
    "addr:postcode":"28110",
    "addr:street":"Us Hwy 74",
    "iso:country":"US",
    "sg:address":"4018 US Hwy 74",
    "sg:city":"Monroe",
    "sg:classifiers":[
        {
            "category":"Building & Trades",
            "subcategory":"Construction",
            "type":"Services"
        }
    ],
    "sg:phone":"+1 704 283 1561",
    "sg:postcode":"28110",
    "sg:province":"NC",
    "sg:tags":[
        "mobile",
        "home"
    ],
    "wof:name":"Jim Quick Homes",
    "wof:placetype":"venue"
},
  "geometry": {"coordinates":[-80.596807,35.03428],"type":"Point"}
}