{
  "type": "Feature",
  "properties": {
    "addr:full":"432 N Broad St Mooresville NC 28115",
    "addr:housenumber":"432",
    "addr:postcode":"28115",
    "addr:street":"N Broad St",
    "iso:country":"US",
    "sg:address":"432 N Broad St",
    "sg:city":"Mooresville",
    "sg:classifiers":[
        {
            "category":"Building & Trades",
            "subcategory":"Construction",
            "type":"Services"
        }
    ],
    "sg:phone":"+1 704 664 5252",
    "sg:postcode":"28115",
    "sg:province":"NC",
    "sg:tags":[
        "general",
        "contractor"
    ],
    "wof:name":"Mooresville Roofing & Heating",
    "wof:placetype":"venue"
},
  "geometry": {"coordinates":[-80.80819700000001,35.589513],"type":"Point"}
}