{
  "type": "Feature",
  "properties": {
    "addr:full":"354 Sawdust Rd Rocky Point NC 28457",
    "addr:housenumber":"354",
    "addr:postcode":"28457",
    "addr:street":"Sawdust Rd",
    "iso:country":"US",
    "sg:address":"354 Sawdust Rd",
    "sg:city":"Rocky Point",
    "sg:classifiers":[
        {
            "category":"Manufacturing",
            "subcategory":"Tools & Machinery",
            "type":"Manufacturing & Wholesale Goods"
        }
    ],
    "sg:phone":"+1 910 675 1336",
    "sg:postcode":"28457",
    "sg:province":"NC",
    "sg:tags":[
        "machine",
        "shop"
    ],
    "wof:name":"Superior Machine Shop Inc",
    "wof:placetype":"venue"
},
  "geometry": {"coordinates":[-77.88456499999999,34.4318],"type":"Point"}
}