{
  "type": "Feature",
  "properties": {
    "iso:country":"US",
    "sg:address":"P.O Box 542",
    "sg:city":"Paw Creek",
    "sg:classifiers":[
        {
            "category":"Professional",
            "subcategory":"Advertising",
            "type":"Services"
        }
    ],
    "sg:postcode":"28130",
    "sg:province":"NC",
    "sg:website":"http://www.moolpit.com",
    "wof:name":"moolpit",
    "wof:placetype":"venue"
},
  "geometry": {"coordinates":[-80.804151,35.26002],"type":"Point"}
}