{
  "type": "Feature",
  "properties": {
    "iso:country":"US",
    "sg:address":"1317 Earl Cir",
    "sg:city":"Greenville",
    "sg:classifiers":[
        {
            "category":"Building & Trades",
            "subcategory":"Construction",
            "type":"Services"
        }
    ],
    "sg:phone":"+1 252 756 9936",
    "sg:postcode":"27858",
    "sg:province":"NC",
    "sg:tags":[
        "painter"
    ],
    "wof:name":"R T Home Improvements",
    "wof:placetype":"venue"
},
  "geometry": {"coordinates":[-77.30834299999999,35.547399],"type":"Point"}
}