{
  "type": "Feature",
  "properties": {
    "iso:country":"US",
    "sg:address":"2060 Carolina Beach Rd",
    "sg:city":"Wilmington",
    "sg:classifiers":[
        {
            "category":"Personal",
            "subcategory":"Beauty Salon",
            "type":"Services"
        }
    ],
    "sg:phone":"+1 910 343 0008",
    "sg:postcode":"28401",
    "sg:province":"NC",
    "wof:name":"Legend Beauty Salon",
    "wof:placetype":"venue"
},
  "geometry": {"coordinates":[-77.941299,34.203495],"type":"Point"}
}