{
  "type": "Feature",
  "properties": {
    "addr:full":"4301 Flake Rd Hamptonville NC 27020",
    "addr:housenumber":"4301",
    "addr:postcode":"27020",
    "addr:street":"Flake Rd",
    "iso:country":"US",
    "sg:address":"4301 Flake Rd",
    "sg:city":"Hamptonville",
    "sg:classifiers":[
        {
            "category":"Professional",
            "subcategory":"Management & Consulting",
            "type":"Services"
        }
    ],
    "sg:phone":"+1 336 468 6075",
    "sg:postcode":"27020",
    "sg:province":"NC",
    "sg:tags":[
        "consultant",
        "safety"
    ],
    "wof:name":"Safety Tech Consultants",
    "wof:placetype":"venue"
},
  "geometry": {"coordinates":[-80.809122,36.173499],"type":"Point"}
}