{
  "type": "Feature",
  "properties": {
    "iso:country":"US",
    "sg:address":"216 Clay Hill Rd",
    "sg:city":"Sneads Ferry",
    "sg:classifiers":[
        {
            "category":"Home & Garden",
            "subcategory":"Garden Supply",
            "type":"Retail Goods"
        }
    ],
    "sg:phone":"+1 910 327 0568",
    "sg:postcode":"28460",
    "sg:province":"NC",
    "sg:tags":[
        "lawn",
        "mower"
    ],
    "wof:name":"Smith Small Eng & Jet Ski Rpr",
    "wof:placetype":"venue"
},
  "geometry": {"coordinates":[-77.394864,34.544642],"type":"Point"}
}