{
  "type": "Feature",
  "properties": {
    "iso:country":"US",
    "sg:address":"129 W Center St",
    "sg:city":"Lexington",
    "sg:classifiers":[
        {
            "category":"Professional",
            "subcategory":"Lawyer & Legal Services",
            "type":"Services"
        }
    ],
    "sg:phone":"+1   ",
    "sg:postcode":"27292",
    "sg:province":"NC",
    "wof:name":"James A Gleason Atty",
    "wof:placetype":"venue"
},
  "geometry": {"coordinates":[-80.255098,35.825364],"type":"Point"}
}