{
  "type": "Feature",
  "properties": {
    "iso:country":"US",
    "sg:address":"121 Boone Square St",
    "sg:city":"Hillsborough",
    "sg:classifiers":[
        {
            "category":"Personal",
            "type":"Services"
        }
    ],
    "sg:phone":"+1 919 732 9197",
    "sg:postcode":"27278",
    "sg:province":"NC",
    "sg:tags":[
        "therapist",
        "massage"
    ],
    "wof:name":"Kirk Lila",
    "wof:placetype":"venue"
},
  "geometry": {"coordinates":[-79.100044,36.06331],"type":"Point"}
}