{
  "type": "Feature",
  "properties": {
    "addr:full":"1240 25th St SE Hickory NC 28602",
    "addr:housenumber":"1240",
    "addr:postcode":"28602",
    "addr:street":"25Th St Se",
    "iso:country":"US",
    "sg:address":"1240 25th St SE",
    "sg:city":"Hickory",
    "sg:classifiers":[
        {
            "category":"Manufacturing",
            "subcategory":"Lumber",
            "type":"Manufacturing & Wholesale Goods"
        }
    ],
    "sg:phone":"+1 828 322 7457",
    "sg:postcode":"28602",
    "sg:province":"NC",
    "sg:tags":[
        "hardwood",
        "mill"
    ],
    "wof:name":"Hester Enterprises Inc",
    "wof:placetype":"venue"
},
  "geometry": {"coordinates":[-81.289475,35.709973],"type":"Point"}
}