{
  "type": "Feature",
  "properties": {
    "addr:full":"3436 Redbud Ln Raleigh NC 27607",
    "addr:housenumber":"3436",
    "addr:postcode":"27607",
    "addr:street":"Redbud Ln",
    "iso:country":"US",
    "sg:address":"3436 Redbud Ln",
    "sg:city":"Raleigh",
    "sg:classifiers":[
        {
            "category":"Professional",
            "subcategory":"Art Services",
            "type":"Services"
        }
    ],
    "sg:phone":"+1 919 881 9848",
    "sg:postcode":"27607",
    "sg:province":"NC",
    "sg:tags":[
        "graphic",
        "designer"
    ],
    "wof:name":"Vicky Earp Design",
    "wof:placetype":"venue"
},
  "geometry": {"coordinates":[-78.68373200000001,35.802481],"type":"Point"}
}