{
  "type": "Feature",
  "properties": {
    "iso:country":"US",
    "sg:address":"4220 State Hwy 55",
    "sg:city":"Durham",
    "sg:classifiers":[
        {
            "category":"Professional",
            "type":"Services"
        }
    ],
    "sg:phone":"+1 919 484 2442",
    "sg:postcode":"27713",
    "sg:province":"NC",
    "sg:tags":[
        "establishment"
    ],
    "wof:name":"Rate Integration",
    "wof:placetype":"venue"
},
  "geometry": {"coordinates":[-78.891738,35.914836],"type":"Point"}
}