{
  "type": "Feature",
  "properties": {
    "addr:full":"399 W Spring St Seven Springs NC 28578",
    "addr:housenumber":"399",
    "addr:postcode":"28578",
    "addr:street":"W Spring St",
    "iso:country":"US",
    "sg:address":"399 W Spring St",
    "sg:city":"Seven Springs",
    "sg:classifiers":[
        {
            "category":"Retail",
            "subcategory":"Auto Repair",
            "type":"Services"
        }
    ],
    "sg:phone":"+1   ",
    "sg:postcode":"28578",
    "sg:province":"NC",
    "sg:tags":[
        "automotive"
    ],
    "wof:name":"Mark Williams-Electrical Contr",
    "wof:placetype":"venue"
},
  "geometry": {"coordinates":[-77.85512199999999,35.227535],"type":"Point"}
}