{
  "type": "Feature",
  "properties": {
    "iso:country":"US",
    "sg:address":"443 Woltz Atkins Rd",
    "sg:city":"Mount Airy",
    "sg:phone":"+1 336 352 4856",
    "sg:postcode":"27030",
    "sg:province":"NC",
    "sg:tags":[
        "farm",
        "tobacco"
    ],
    "wof:name":"Ivylyn Swift",
    "wof:placetype":"venue"
},
  "geometry": {"coordinates":[-80.7948,36.470713],"type":"Point"}
}