{
  "type": "Feature",
  "properties": {
    "addr:full":"806 State Hwy 66 Kernersville NC 27284",
    "addr:housenumber":"806",
    "addr:postcode":"27284",
    "addr:street":"State Hwy 66",
    "iso:country":"US",
    "sg:address":"806 State Hwy 66",
    "sg:city":"Kernersville",
    "sg:classifiers":[
        {
            "category":"Sports & Exercise",
            "subcategory":"Gym",
            "type":"Entertainment"
        }
    ],
    "sg:phone":"+1 336 996 0303",
    "sg:postcode":"27284",
    "sg:province":"NC",
    "sg:tags":[
        "club",
        "health",
        "studio",
        "gymnasium"
    ],
    "wof:name":"Boomer's & Beyond",
    "wof:placetype":"venue"
},
  "geometry": {"coordinates":[-80.062372,36.108468],"type":"Point"}
}