{
  "type": "Feature",
  "properties": {
    "addr:full":"2161 Hawkins St Charlotte NC 28203",
    "addr:housenumber":"2161",
    "addr:postcode":"28203",
    "addr:street":"Hawkins St",
    "iso:country":"US",
    "sg:address":"2161 Hawkins St",
    "sg:city":"Charlotte",
    "sg:classifiers":[
        {
            "category":"Manufacturing",
            "subcategory":"Printing",
            "type":"Manufacturing & Wholesale Goods"
        }
    ],
    "sg:phone":"+1 704 332 4658",
    "sg:postcode":"28203",
    "sg:province":"NC",
    "sg:tags":[
        "multimedia"
    ],
    "wof:name":"Undergroud Exchange Media",
    "wof:placetype":"venue"
},
  "geometry": {"coordinates":[-80.86316100000001,35.208804],"type":"Point"}
}