{
  "type": "Feature",
  "properties": {
    "addr:full":"3115 Coley Rd Durham NC 27703",
    "addr:housenumber":"3115",
    "addr:postcode":"27703",
    "addr:street":"Coley Rd",
    "iso:country":"US",
    "sg:address":"3115 Coley Rd",
    "sg:city":"Durham",
    "sg:classifiers":[
        {
            "category":"Building & Trades",
            "subcategory":"Electrical",
            "type":"Services"
        }
    ],
    "sg:phone":"+1 919 598 5323",
    "sg:postcode":"27703",
    "sg:province":"NC",
    "sg:tags":[
        "electrical",
        "contractor"
    ],
    "wof:name":"Timothy Earl McCowan Electrica",
    "wof:placetype":"venue"
},
  "geometry": {"coordinates":[-78.747067,35.946473],"type":"Point"}
}