{
  "type": "Feature",
  "properties": {
    "addr:full":"164 Hickman Ave Hudson NC 28638",
    "addr:housenumber":"164",
    "addr:postcode":"28638",
    "addr:street":"Hickman Ave",
    "iso:country":"US",
    "sg:address":"164 Hickman Ave",
    "sg:city":"Hudson",
    "sg:classifiers":[
        {
            "category":"Banks & Credit Unions",
            "subcategory":"Bank",
            "type":"Services"
        }
    ],
    "sg:phone":"+1 828 757 2666",
    "sg:postcode":"28638",
    "sg:province":"NC",
    "wof:name":"Sun Trust Bank",
    "wof:placetype":"venue"
},
  "geometry": {"coordinates":[-81.49676100000001,35.84538],"type":"Point"}
}