{
  "type": "Feature",
  "properties": {
    "iso:country":"US",
    "sg:address":"400 Central Ave",
    "sg:city":"Butner",
    "sg:classifiers":[
        {
            "category":"Personal",
            "subcategory":"Shoe Repair & Shine",
            "type":"Services"
        },
        {
            "category":"Shopping",
            "subcategory":"Shoes",
            "type":"Retail Goods"
        }
    ],
    "sg:phone":"+1 919 575 9408",
    "sg:postcode":"27509",
    "sg:province":"NC",
    "sg:tags":[
        "store"
    ],
    "wof:name":"Field's Shoe Shop",
    "wof:placetype":"venue"
},
  "geometry": {"coordinates":[-78.75990299999999,36.1357],"type":"Point"}
}