{
  "type": "Feature",
  "properties": {
    "addr:full":"1030 Lake Royale Louisburg NC 27549",
    "addr:housenumber":"1030",
    "addr:postcode":"27549",
    "addr:street":"Lake Royale",
    "iso:country":"US",
    "sg:address":"1030 Lake Royale",
    "sg:city":"Louisburg",
    "sg:classifiers":[
        {
            "category":"Professional",
            "subcategory":"Engineering",
            "type":"Services"
        }
    ],
    "sg:phone":"+1 919 570 0942",
    "sg:postcode":"27549",
    "sg:province":"NC",
    "sg:tags":[
        "engineer"
    ],
    "wof:name":"Aseco Integrated System Inc",
    "wof:placetype":"venue"
},
  "geometry": {"coordinates":[-78.185593,35.95989],"type":"Point"}
}