{
  "type": "Feature",
  "properties": {
    "addr:full":"3410 S Buccaneer Dr Nags Head NC 27959",
    "addr:housenumber":"3410",
    "addr:postcode":"27959",
    "addr:street":"S Buccaneer Dr",
    "iso:country":"US",
    "sg:address":"3410 S Buccaneer Dr",
    "sg:city":"Nags Head",
    "sg:classifiers":[
        {
            "category":"Bars & Pubs",
            "type":"Food & Drink"
        }
    ],
    "sg:phone":"+1 252 441 0293",
    "sg:postcode":"27959",
    "sg:province":"NC",
    "sg:tags":[
        "drinking"
    ],
    "wof:name":"Comedy Club Inc",
    "wof:placetype":"venue"
},
  "geometry": {"coordinates":[-75.636701,35.968842],"type":"Point"}
}