{
  "type": "Feature",
  "properties": {
    "addr:full":"539 Manning Dr Charlotte NC 28209",
    "addr:housenumber":"539",
    "addr:postcode":"28209",
    "addr:street":"Manning Dr",
    "iso:country":"US",
    "sg:address":"539 Manning Dr",
    "sg:city":"Charlotte",
    "sg:classifiers":[
        {
            "category":"Professional",
            "subcategory":"Computer Services",
            "type":"Services"
        }
    ],
    "sg:phone":"+1 704 521 9600",
    "sg:postcode":"28209",
    "sg:province":"NC",
    "sg:tags":[
        "processing",
        "datum"
    ],
    "sg:website":"www.denton-assoc.com",
    "wof:name":"Denton Associates",
    "wof:placetype":"venue"
},
  "geometry": {"coordinates":[-80.8421,35.160949],"type":"Point"}
}