{
  "type": "Feature",
  "properties": {
    "addr:full":"1835 Newell St Asheboro NC 27203",
    "addr:housenumber":"1835",
    "addr:postcode":"27203",
    "addr:street":"Newell St",
    "iso:country":"US",
    "sg:address":"1835 Newell St",
    "sg:city":"Asheboro",
    "sg:classifiers":[
        {
            "category":"Personal",
            "type":"Services"
        },
        {
            "category":"Professional",
            "subcategory":"Management & Consulting",
            "type":"Services"
        }
    ],
    "sg:phone":"+1 336 629 9005",
    "sg:postcode":"27203",
    "sg:province":"NC",
    "sg:tags":[
        "party",
        "planning"
    ],
    "wof:name":"Lucky's Entertainment",
    "wof:placetype":"venue"
},
  "geometry": {"coordinates":[-79.800375,35.746303],"type":"Point"}
}