{
  "type": "Feature",
  "properties": {
    "addr:full":"3187 New Bern Hwy Jacksonville NC 28546",
    "addr:housenumber":"3187",
    "addr:postcode":"28546",
    "addr:street":"New Bern Hwy",
    "iso:country":"US",
    "sg:address":"3187 New Bern Hwy",
    "sg:city":"Jacksonville",
    "sg:classifiers":[
        {
            "category":"Autos & Motor Vehicles",
            "subcategory":"Automobile Sales",
            "type":"Retail Goods"
        }
    ],
    "sg:phone":"+1 910 577 4313",
    "sg:postcode":"28546",
    "sg:province":"NC",
    "sg:tags":[
        "car",
        "dealer"
    ],
    "wof:name":"Northside Auto Sales",
    "wof:placetype":"venue"
},
  "geometry": {"coordinates":[-77.375883,34.78945],"type":"Point"}
}