{
  "type": "Feature",
  "properties": {
    "iso:country":"US",
    "sg:address":"1237 Beaverton Trl",
    "sg:city":"Winston Salem",
    "sg:classifiers":[
        {
            "category":"Shopping",
            "subcategory":"Clothing, Apparel, & Fashions",
            "type":"Retail Goods"
        }
    ],
    "sg:phone":"+1 336 794 0062",
    "sg:postcode":"27103",
    "sg:province":"NC",
    "sg:tags":[
        "alteration"
    ],
    "wof:name":"Moment By Moment Alterations",
    "wof:placetype":"venue"
},
  "geometry": {"coordinates":[-80.348315,36.049309],"type":"Point"}
}