{
  "type": "Feature",
  "properties": {
    "addr:full":"1035 Carriage Loop Burlington NC 27217",
    "addr:housenumber":"1035",
    "addr:postcode":"27217",
    "addr:street":"Carriage Loop",
    "iso:country":"US",
    "sg:address":"1035 Carriage Loop",
    "sg:city":"Burlington",
    "sg:classifiers":[
        {
            "category":"Retail",
            "subcategory":"Repair Shop",
            "type":"Services"
        }
    ],
    "sg:phone":"+1   ",
    "sg:postcode":"27217",
    "sg:province":"NC",
    "wof:name":"S Noble Cleaning",
    "wof:placetype":"venue"
},
  "geometry": {"coordinates":[-79.424419,36.125006],"type":"Point"}
}