{
  "type": "Feature",
  "properties": {
    "iso:country":"US",
    "sg:address":"407 Penrose Ct",
    "sg:city":"Greensboro",
    "sg:classifiers":[
        {
            "category":"Building & Trades",
            "subcategory":"Landscaping Services",
            "type":"Services"
        }
    ],
    "sg:phone":"+1 336 282 3665",
    "sg:postcode":"27410",
    "sg:province":"NC",
    "sg:tags":[
        "landscape",
        "contractor"
    ],
    "wof:name":"Greeny's Landscaping",
    "wof:placetype":"venue"
},
  "geometry": {"coordinates":[-79.90644899999999,36.0939],"type":"Point"}
}