{
  "type": "Feature",
  "properties": {
    "addr:full":"3900 Stallings Rd Harrisburg NC 28075",
    "addr:housenumber":"3900",
    "addr:postcode":"28075",
    "addr:street":"Stallings Rd",
    "iso:country":"US",
    "sg:address":"3900 Stallings Rd",
    "sg:city":"Harrisburg",
    "sg:classifiers":[
        {
            "category":"Education",
            "subcategory":"School",
            "type":"Public Place"
        }
    ],
    "sg:phone":"+1 704 455 5118",
    "sg:postcode":"28075",
    "sg:province":"NC",
    "sg:website":"www.cabarrus.k12.nc.us",
    "wof:name":"Harrisburg Elementary School",
    "wof:placetype":"venue"
},
  "geometry": {"coordinates":[-80.646023,35.315728],"type":"Point"}
}