{
  "type": "Feature",
  "properties": {
    "addr:full":"800 Moye Blvd Greenville NC 27834",
    "addr:housenumber":"800",
    "addr:postcode":"27834",
    "addr:street":"Moye Blvd",
    "iso:country":"US",
    "sg:address":"800 Moye Blvd",
    "sg:city":"Greenville",
    "sg:classifiers":[
        {
            "category":"Health Services",
            "subcategory":"Doctor",
            "type":"Services"
        }
    ],
    "sg:phone":"+1 252 830 1680",
    "sg:postcode":"27834",
    "sg:province":"NC",
    "sg:tags":[
        "physician",
        "surgeon"
    ],
    "wof:name":"Greenville Internal Medicine",
    "wof:placetype":"venue"
},
  "geometry": {"coordinates":[-77.39931799999999,35.603161],"type":"Point"}
}