{
  "type": "Feature",
  "properties": {
    "addr:full":"823 Hamilton St Charlotte NC 28206",
    "addr:housenumber":"823",
    "addr:postcode":"28206",
    "addr:street":"Hamilton St",
    "iso:country":"US",
    "sg:address":"823 Hamilton St",
    "sg:city":"Charlotte",
    "sg:phone":"+1 704 916 8970",
    "sg:postcode":"28206",
    "sg:province":"NC",
    "wof:name":"Uptown Charlotte Jazz at Uptown Amphitheatre at the Music Factory",
    "wof:placetype":"venue"
},
  "geometry": {"coordinates":[-80.84642100000001,35.239131],"type":"Point"}
}