{
  "type": "Feature",
  "properties": {
    "iso:country":"US",
    "sg:address":"3127 Kalynne St",
    "sg:city":"Charlotte",
    "sg:classifiers":[
        {
            "category":"Social Services",
            "subcategory":"Adult Care",
            "type":"Services"
        }
    ],
    "sg:phone":"+1 704 393 5916",
    "sg:postcode":"28208",
    "sg:province":"NC",
    "sg:tags":[
        "centers-adult",
        "day"
    ],
    "wof:name":"Lifespan Lakeview",
    "wof:placetype":"venue"
},
  "geometry": {"coordinates":[-80.877015,35.252191],"type":"Point"}
}