{
  "type": "Feature",
  "properties": {
    "addr:full":"5419 Pecanbluff Ct Charlotte NC 28216",
    "addr:housenumber":"5419",
    "addr:postcode":"28216",
    "addr:street":"Pecanbluff Ct",
    "iso:country":"US",
    "sg:address":"5419 Pecanbluff Ct",
    "sg:city":"Charlotte",
    "sg:classifiers":[
        {
            "category":"Sports & Exercise",
            "subcategory":"Bowling",
            "type":"Entertainment"
        }
    ],
    "sg:phone":"+1 704 399 2441",
    "sg:postcode":"28216",
    "sg:province":"NC",
    "sg:tags":[
        "center"
    ],
    "wof:name":"Cinema Lanes",
    "wof:placetype":"venue"
},
  "geometry": {"coordinates":[-80.888628,35.294745],"type":"Point"}
}