{
  "type": "Feature",
  "properties": {
    "addr:full":"2500 Wilco Blvd Wilson NC 27893",
    "addr:postcode":"2500;27893",
    "addr:street":"Wilco Blvd",
    "iso:country":"US",
    "sg:address":"2500 Wilco Blvd",
    "sg:city":"Wilson",
    "sg:classifiers":[
        {
            "category":"Wholesale",
            "subcategory":"Farm Supplies",
            "type":"Manufacturing & Wholesale Goods"
        }
    ],
    "sg:phone":"+1 252 243 4167",
    "sg:postcode":"27893",
    "sg:province":"NC",
    "sg:tags":[
        "feed"
    ],
    "sg:website":"www.cargill.com",
    "wof:name":"Cargill Inc",
    "wof:placetype":"venue"
},
  "geometry": {"coordinates":[-77.917686,35.691852],"type":"Point"}
}