{
  "type": "Feature",
  "properties": {
    "addr:full":"7573 Watkins Ford Rd Kernersville NC 27284",
    "addr:housenumber":"7573",
    "addr:postcode":"27284",
    "addr:street":"Watkins Ford Rd",
    "iso:country":"US",
    "sg:address":"7573 Watkins Ford Rd",
    "sg:city":"Kernersville",
    "sg:classifiers":[
        {
            "category":"Manufacturing",
            "subcategory":"Metals",
            "type":"Manufacturing & Wholesale Goods"
        }
    ],
    "sg:phone":"+1 336 869 6256",
    "sg:postcode":"27284",
    "sg:province":"NC",
    "sg:tags":[
        "fabrication",
        "structural"
    ],
    "wof:name":"Dons Welding Service",
    "wof:placetype":"venue"
},
  "geometry": {"coordinates":[-80.07555499999999,36.04558],"type":"Point"}
}