{
  "type": "Feature",
  "properties": {
    "iso:country":"US",
    "sg:address":"51 Carpenter Ct NW",
    "sg:city":"Concord",
    "sg:classifiers":[
        {
            "category":"Manufacturing",
            "subcategory":"Retail Goods",
            "type":"Manufacturing & Wholesale Goods"
        }
    ],
    "sg:phone":"+1 704 262 3711",
    "sg:postcode":"28027",
    "sg:province":"NC",
    "sg:tags":[
        "product",
        "mfg"
    ],
    "wof:name":"Extreme Industries",
    "wof:placetype":"venue"
},
  "geometry": {"coordinates":[-80.671747,35.366644],"type":"Point"}
}