{
  "type": "Feature",
  "properties": {
    "addr:full":"4805 Old Randleman Rd Greensboro NC 27406",
    "addr:housenumber":"4805",
    "addr:postcode":"27406",
    "addr:street":"Old Randleman Rd",
    "iso:country":"US",
    "sg:address":"4805 Old Randleman Rd",
    "sg:city":"Greensboro",
    "sg:classifiers":[
        {
            "category":"Manufacturing",
            "subcategory":"Motor Vehicles & Parts",
            "type":"Manufacturing & Wholesale Goods"
        }
    ],
    "sg:phone":"+1 336 292 3169",
    "sg:postcode":"27406",
    "sg:province":"NC",
    "sg:tags":[
        "mfg"
    ],
    "wof:name":"Glass Tek Inc",
    "wof:placetype":"venue"
},
  "geometry": {"coordinates":[-79.823171,35.989837],"type":"Point"}
}