{
  "type": "Feature",
  "properties": {
    "addr:full":"532 Grove St Fayetteville NC 28301",
    "addr:housenumber":"532",
    "addr:postcode":"28301",
    "addr:street":"Grove St",
    "iso:country":"US",
    "sg:address":"532 Grove St",
    "sg:city":"Fayetteville",
    "sg:classifiers":[
        {
            "category":"Restaurant",
            "type":"Food & Drink"
        }
    ],
    "sg:menulink":"http://www.allmenus.com/nc/cross-creek/182501-wendys/menu/",
    "sg:phone":"+1 910 323 4532",
    "sg:postcode":"28301",
    "sg:province":"NC",
    "sg:tags":[
        "burger",
        "american",
        "soup"
    ],
    "wof:name":"Wendy's",
    "wof:placetype":"venue"
},
  "geometry": {"coordinates":[-78.86616100000001,35.053138],"type":"Point"}
}