{
  "type": "Feature",
  "properties": {
    "addr:full":"915 Washington St Eden NC 27288",
    "addr:housenumber":"915",
    "addr:postcode":"27288",
    "addr:street":"Washington St",
    "iso:country":"US",
    "sg:address":"915 Washington St",
    "sg:city":"Eden",
    "sg:classifiers":[
        {
            "category":"Autos & Motor Vehicles",
            "subcategory":"Automobile Sales",
            "type":"Retail Goods"
        }
    ],
    "sg:phone":"+1 336 623 6273",
    "sg:postcode":"27288",
    "sg:province":"NC",
    "sg:tags":[
        "used"
    ],
    "wof:name":"Ore Auto Sales",
    "wof:placetype":"venue"
},
  "geometry": {"coordinates":[-79.768654,36.488022],"type":"Point"}
}