{
  "type": "Feature",
  "properties": {
    "addr:full":"3118 US Hwy 13 N Ahoskie NC 27910",
    "addr:housenumber":"3118",
    "addr:postcode":"27910",
    "addr:street":"Us Hwy 13 N",
    "iso:country":"US",
    "sg:address":"3118 US Hwy 13 N",
    "sg:city":"Ahoskie",
    "sg:phone":"+1 252 332 3105",
    "sg:postcode":"27910",
    "sg:province":"NC",
    "sg:tags":[
        "farm",
        "field",
        "crop",
        "tobacco"
    ],
    "wof:name":"Kcw Farms Inc",
    "wof:placetype":"venue"
},
  "geometry": {"coordinates":[-76.93839199999999,36.221592],"type":"Point"}
}