{
  "type": "Feature",
  "properties": {
    "iso:country":"US",
    "sg:address":"421 N Fork Rd",
    "sg:city":"Black Mountain",
    "sg:classifiers":[
        {
            "category":"Building & Trades",
            "subcategory":"Construction",
            "type":"Services"
        }
    ],
    "sg:phone":"+1 828 669 2764",
    "sg:postcode":"28711",
    "sg:province":"NC",
    "sg:tags":[
        "contractor"
    ],
    "wof:name":"Harold Melton Masonry",
    "wof:placetype":"venue"
},
  "geometry": {"coordinates":[-82.339354,35.636679],"type":"Point"}
}