{
  "type": "Feature",
  "properties": {
    "addr:full":"153 Tifton Dr Ellenboro NC 28040",
    "addr:housenumber":"153",
    "addr:postcode":"28040",
    "addr:street":"Tifton Dr",
    "iso:country":"US",
    "sg:address":"153 Tifton Dr",
    "sg:city":"Ellenboro",
    "sg:classifiers":[
        {
            "category":"Building & Trades",
            "subcategory":"Construction",
            "type":"Services"
        }
    ],
    "sg:phone":"+1 828 248 1108",
    "sg:postcode":"28040",
    "sg:province":"NC",
    "sg:tags":[
        "house",
        "business"
    ],
    "wof:name":"Hightower Enterprises Inc",
    "wof:placetype":"venue"
},
  "geometry": {"coordinates":[-81.79440200000001,35.335105],"type":"Point"}
}