{
  "type": "Feature",
  "properties": {
    "iso:country":"US",
    "sg:address":"800 W Haggard Ave",
    "sg:city":"Elon College",
    "sg:classifiers":[
        {
            "category":"Freight",
            "type":"Transportation"
        }
    ],
    "sg:phone":"+1 336 449 4473",
    "sg:postcode":"27244",
    "sg:province":"NC",
    "sg:tags":[
        "special"
    ],
    "wof:name":"800 West Mini Storage",
    "wof:placetype":"venue"
},
  "geometry": {"coordinates":[-79.521897,36.103234],"type":"Point"}
}