{
  "type": "Feature",
  "properties": {
    "iso:country":"US",
    "sg:address":"2205 Godwin Ave",
    "sg:city":"Lumberton",
    "sg:classifiers":[
        {
            "category":"Sports & Exercise",
            "subcategory":"Bowling",
            "type":"Entertainment"
        }
    ],
    "sg:phone":"+1 910 739 4499",
    "sg:postcode":"28358",
    "sg:province":"NC",
    "sg:tags":[
        "center"
    ],
    "wof:name":"Lumberton Bowling Center",
    "wof:placetype":"venue"
},
  "geometry": {"coordinates":[-79.00191700000001,34.633545],"type":"Point"}
}