{
  "type": "Feature",
  "properties": {
    "addr:full":"2660 Zion Church Rd Concord NC 28025",
    "addr:housenumber":"2660",
    "addr:postcode":"28025",
    "addr:street":"Zion Church Rd",
    "iso:country":"US",
    "sg:address":"2660 Zion Church Rd",
    "sg:city":"Concord",
    "sg:classifiers":[
        {
            "category":"Wholesale",
            "subcategory":"Chemicals & Plastics",
            "type":"Manufacturing & Wholesale Goods"
        }
    ],
    "sg:phone":"+1 704 793 1799",
    "sg:postcode":"28025",
    "sg:province":"NC",
    "sg:tags":[
        "textile",
        "dyer"
    ],
    "wof:name":"Custom Colours Inc",
    "wof:placetype":"venue"
},
  "geometry": {"coordinates":[-80.58201200000001,35.379446],"type":"Point"}
}