{
  "type": "Feature",
  "properties": {
    "addr:full":"207 1st St SW Hildebran NC 28637",
    "addr:housenumber":"207",
    "addr:postcode":"28637",
    "addr:street":"1St St Sw",
    "iso:country":"US",
    "sg:address":"207 1st St SW",
    "sg:city":"Hildebran",
    "sg:classifiers":[
        {
            "category":"Social Services",
            "type":"Services"
        }
    ],
    "sg:phone":"+1 828 397 7062",
    "sg:postcode":"28637",
    "sg:province":"NC",
    "sg:tags":[
        "youth",
        "organization",
        "center"
    ],
    "wof:name":"Hildebran-Icard Little League",
    "wof:placetype":"venue"
},
  "geometry": {"coordinates":[-81.424711,35.715045],"type":"Point"}
}