{
  "type": "Feature",
  "properties": {
    "addr:full":"13010 Eastfield Rd Huntersville NC 28078",
    "addr:housenumber":"13010",
    "addr:postcode":"28078",
    "addr:street":"Eastfield Rd",
    "iso:country":"US",
    "sg:address":"13010 Eastfield Rd",
    "sg:city":"Huntersville",
    "sg:classifiers":[
        {
            "category":"Professional",
            "subcategory":"Accounting & Tax Preparation",
            "type":"Services"
        }
    ],
    "sg:phone":"+1 704 875 3153",
    "sg:postcode":"28078",
    "sg:province":"NC",
    "sg:tags":[
        "return",
        "filing"
    ],
    "sg:website":"www.hhrb.com",
    "wof:name":"H & R Block Tax Svc",
    "wof:placetype":"venue"
},
  "geometry": {"coordinates":[-80.784747,35.386153],"type":"Point"}
}