{
  "type": "Feature",
  "properties": {
    "addr:full":"109 Kilmayne Dr Ste B Cary NC 27511",
    "addr:housenumber":"109",
    "addr:postcode":"27511",
    "addr:street":"Kilmayne Dr Ste B",
    "iso:country":"US",
    "sg:address":"109 Kilmayne Dr Ste B",
    "sg:city":"Cary",
    "sg:classifiers":[
        {
            "category":"Health Services",
            "subcategory":"Clinic",
            "type":"Services"
        },
        {
            "category":"Personal",
            "subcategory":"Skin Care",
            "type":"Services"
        }
    ],
    "sg:phone":"+1 919 783 4188",
    "sg:postcode":"27511",
    "sg:province":"NC",
    "sg:tags":[
        "medical"
    ],
    "sg:website":"www.caryskincare.com",
    "wof:name":"Cary Skin Care",
    "wof:placetype":"venue"
},
  "geometry": {"coordinates":[-78.78309299999999,35.769414],"type":"Point"}
}