{
  "type": "Feature",
  "properties": {
    "iso:country":"US",
    "sg:address":"515 W 5th Ave",
    "sg:city":"Lexington",
    "sg:classifiers":[
        {
            "category":"Wholesale",
            "subcategory":"Auto Parts",
            "type":"Manufacturing & Wholesale Goods"
        }
    ],
    "sg:phone":"+1 336 249 7987",
    "sg:postcode":"27292",
    "sg:province":"NC",
    "sg:tags":[
        "automobile",
        "rebuilt",
        "used"
    ],
    "wof:name":"Just Camaro's",
    "wof:placetype":"venue"
},
  "geometry": {"coordinates":[-80.26425999999999,35.823582],"type":"Point"}
}