{
  "type": "Feature",
  "properties": {
    "iso:country":"US",
    "sg:address":"302 E Broad St",
    "sg:city":"St Pauls",
    "sg:classifiers":[
        {
            "category":"Autos & Motor Vehicles",
            "subcategory":"Auto Supplies",
            "type":"Retail Goods"
        }
    ],
    "sg:phone":"+1 910 865 5135",
    "sg:postcode":"28384",
    "sg:province":"NC",
    "sg:tags":[
        "automobile",
        "parts"
    ],
    "wof:name":"Western Auto",
    "wof:placetype":"venue"
},
  "geometry": {"coordinates":[-78.96851700000001,34.806193],"type":"Point"}
}