{
  "type": "Feature",
  "properties": {
    "iso:country":"US",
    "sg:address":"5650 Albemarle Rd",
    "sg:city":"Charlotte",
    "sg:classifiers":[
        {
            "category":"Food & Beverages",
            "subcategory":"Groceries & Convenience Stores",
            "type":"Retail Goods"
        }
    ],
    "sg:phone":"+1 704 568 3045",
    "sg:postcode":"28212",
    "sg:province":"NC",
    "wof:name":"Neo Silver Express",
    "wof:placetype":"venue"
},
  "geometry": {"coordinates":[-80.753755,35.203788],"type":"Point"}
}