{
  "type": "Feature",
  "properties": {
    "addr:full":"249 Coke Ave Edenton NC 27932",
    "addr:housenumber":"249",
    "addr:postcode":"27932",
    "addr:street":"Coke Ave",
    "iso:country":"US",
    "sg:address":"249 Coke Ave",
    "sg:city":"Edenton",
    "sg:classifiers":[
        {
            "category":"Social Services",
            "subcategory":"Adult Care",
            "type":"Services"
        }
    ],
    "sg:phone":"+1 252 482 5456",
    "sg:postcode":"27932",
    "sg:province":"NC",
    "sg:tags":[
        "home",
        "group"
    ],
    "wof:name":"Life Inc",
    "wof:placetype":"venue"
},
  "geometry": {"coordinates":[-76.59760199999999,36.068692],"type":"Point"}
}