{
  "type": "Feature",
  "properties": {
    "iso:country":"US",
    "sg:address":"1233 Cobb Corners Dr",
    "sg:city":"Rocky Mount",
    "sg:classifiers":[
        {
            "category":"Professional",
            "subcategory":"Accounting & Tax Preparation",
            "type":"Services"
        }
    ],
    "sg:phone":"+1 252 442 3136",
    "sg:postcode":"27804",
    "sg:province":"NC",
    "sg:tags":[
        "return",
        "filing"
    ],
    "wof:name":"Liberty Tax Svc",
    "wof:placetype":"venue"
},
  "geometry": {"coordinates":[-77.810033,35.9774],"type":"Point"}
}