{
  "type": "Feature",
  "properties": {
    "addr:full":"8909 J W Clay Blvd Charlotte NC 28262",
    "addr:housenumber":"8909",
    "addr:postcode":"28262",
    "addr:street":"J W Clay Blvd",
    "iso:country":"US",
    "sg:address":"8909 J W Clay Blvd",
    "sg:city":"Charlotte",
    "sg:classifiers":[
        {
            "category":"Shopping",
            "subcategory":"Department Store",
            "type":"Retail Goods"
        }
    ],
    "sg:phone":"+1 704 531 6588",
    "sg:postcode":"28262",
    "sg:province":"NC",
    "sg:tags":[
        "club",
        "wholesale"
    ],
    "sg:website":"www.samsclub.com",
    "wof:name":"Sam's Club",
    "wof:placetype":"venue"
},
  "geometry": {"coordinates":[-80.752797,35.31301],"type":"Point"}
}