{
  "type": "Feature",
  "properties": {
    "addr:full":"28 Crest Ave Asheville NC 28803",
    "addr:housenumber":"28",
    "addr:postcode":"28803",
    "addr:street":"Crest Ave",
    "iso:country":"US",
    "sg:address":"28 Crest Ave",
    "sg:city":"Asheville",
    "sg:classifiers":[
        {
            "category":"Health Services",
            "subcategory":"Nursing And Care Facility",
            "type":"Services"
        }
    ],
    "sg:phone":"+1   ",
    "sg:postcode":"28803",
    "sg:province":"NC",
    "wof:name":"Holmes Family Care Home",
    "wof:placetype":"venue"
},
  "geometry": {"coordinates":[-82.523976,35.549989],"type":"Point"}
}