{
  "type": "Feature",
  "properties": {
    "iso:country":"US",
    "sg:address":"136 Towerview Ct",
    "sg:city":"Cary",
    "sg:classifiers":[
        {
            "category":"Professional",
            "subcategory":"Business Services",
            "type":"Services"
        }
    ],
    "sg:phone":"+1   ",
    "sg:postcode":"27513",
    "sg:province":"NC",
    "sg:website":"www.isrsolutions.com",
    "wof:name":"ISR Solutions",
    "wof:placetype":"venue"
},
  "geometry": {"coordinates":[-78.81072,35.801844],"type":"Point"}
}