{
  "type": "Feature",
  "properties": {
    "addr:full":"2369 Bagley Springs Rd Ronda NC 28670",
    "addr:housenumber":"2369",
    "addr:postcode":"28670",
    "addr:street":"Bagley Springs Rd",
    "iso:country":"US",
    "sg:address":"2369 Bagley Springs Rd",
    "sg:city":"Ronda",
    "sg:classifiers":[
        {
            "category":"Farming",
            "subcategory":"Livestock Farm",
            "type":"Manufacturing & Wholesale Goods"
        }
    ],
    "sg:phone":"+1 336 835 6316",
    "sg:postcode":"28670",
    "sg:province":"NC",
    "sg:tags":[
        "chicken",
        "egg",
        "animal",
        "general"
    ],
    "wof:name":"Bagley Spring Farm",
    "wof:placetype":"venue"
},
  "geometry": {"coordinates":[-80.903192,36.207781],"type":"Point"}
}