{
  "type": "Feature",
  "properties": {
    "addr:full":"320 Cumberland St Greensboro NC 27401",
    "addr:housenumber":"320",
    "addr:postcode":"27401",
    "addr:street":"Cumberland St",
    "iso:country":"US",
    "sg:address":"320 Cumberland St",
    "sg:city":"Greensboro",
    "sg:classifiers":[
        {
            "category":"Professional",
            "subcategory":"Business Services",
            "type":"Services"
        }
    ],
    "sg:phone":"+1   ",
    "sg:postcode":"27401",
    "sg:province":"NC",
    "wof:name":"Personal Shredding Co",
    "wof:placetype":"venue"
},
  "geometry": {"coordinates":[-79.781785,36.073744],"type":"Point"}
}