{
  "type": "Feature",
  "properties": {
    "addr:full":"304 S Morgan St Roxboro NC 27573",
    "addr:housenumber":"304",
    "addr:postcode":"27573",
    "addr:street":"S Morgan St",
    "iso:country":"US",
    "sg:address":"304 S Morgan St",
    "sg:city":"Roxboro",
    "sg:classifiers":[
        {
            "category":"Education",
            "subcategory":"School",
            "type":"Public Place"
        }
    ],
    "sg:phone":"+1 336 599 2191",
    "sg:postcode":"27573",
    "sg:province":"NC",
    "wof:name":"Person County Public Schools",
    "wof:placetype":"venue"
},
  "geometry": {"coordinates":[-78.99143599999999,36.395711],"type":"Point"}
}