{
  "type": "Feature",
  "properties": {
    "addr:full":"5041 Styers Ferry Rd Lewisville NC 27023",
    "addr:housenumber":"5041",
    "addr:postcode":"27023",
    "addr:street":"Styers Ferry Rd",
    "iso:country":"US",
    "sg:address":"5041 Styers Ferry Rd",
    "sg:city":"Lewisville",
    "sg:classifiers":[
        {
            "category":"Organizations",
            "subcategory":"Religious Organization",
            "type":"Services"
        }
    ],
    "sg:phone":"+1   ",
    "sg:postcode":"27023",
    "sg:province":"NC",
    "wof:name":"Harmony Grv Untd Mthdst Chrch",
    "wof:placetype":"venue"
},
  "geometry": {"coordinates":[-80.387761,36.078711],"type":"Point"}
}