{
  "type": "Feature",
  "properties": {
    "addr:full":"306 Jefferson St Wilmington NC 28472",
    "addr:housenumber":"306",
    "addr:postcode":"28472",
    "addr:street":"Jefferson St",
    "iso:country":"US",
    "sg:address":"306 Jefferson St",
    "sg:city":"Wilmington",
    "sg:classifiers":[
        {
            "category":"Professional",
            "subcategory":"Management & Consulting",
            "type":"Services"
        }
    ],
    "sg:phone":"+1   ",
    "sg:postcode":"28472",
    "sg:province":"NC",
    "wof:name":"Columbus County Heath Dept",
    "wof:placetype":"venue"
},
  "geometry": {"coordinates":[-78.697126,34.338332],"type":"Point"}
}