{
  "type": "Feature",
  "properties": {
    "addr:full":"2924 Battleground Ave Greensboro NC 27408",
    "addr:housenumber":"2924",
    "addr:postcode":"27408",
    "addr:street":"Battleground Ave",
    "iso:country":"US",
    "sg:address":"2924 Battleground Ave",
    "sg:city":"Greensboro",
    "sg:classifiers":[
        {
            "category":"Restaurant",
            "type":"Food & Drink"
        }
    ],
    "sg:menulink":"http://www.allmenus.com/nc/greensboro/91269-melting-pot/menu/",
    "sg:phone":"+1 336 545 6233",
    "sg:postcode":"27408",
    "sg:province":"NC",
    "sg:tags":[
        "new",
        "american"
    ],
    "wof:name":"Melting Pot",
    "wof:placetype":"venue"
},
  "geometry": {"coordinates":[-79.833534,36.1138],"type":"Point"}
}