{
  "type": "Feature",
  "properties": {
    "iso:country":"US",
    "sg:address":"209 Cellas Ln",
    "sg:city":"Sanford",
    "sg:classifiers":[
        {
            "category":"Wholesale",
            "subcategory":"Auto Parts",
            "type":"Manufacturing & Wholesale Goods"
        }
    ],
    "sg:phone":"+1 919 708 3783",
    "sg:postcode":"27332",
    "sg:province":"NC",
    "wof:name":"Billy Slater Tools",
    "wof:placetype":"venue"
},
  "geometry": {"coordinates":[-79.212721,35.437231],"type":"Point"}
}