{
  "type": "Feature",
  "properties": {
    "addr:full":"1703 Brookcliff Dr Greensboro NC 27408",
    "addr:housenumber":"1703",
    "addr:postcode":"27408",
    "addr:street":"Brookcliff Dr",
    "iso:country":"US",
    "sg:address":"1703 Brookcliff Dr",
    "sg:city":"Greensboro",
    "sg:classifiers":[
        {
            "category":"Professional",
            "subcategory":"Management & Consulting",
            "type":"Services"
        }
    ],
    "sg:phone":"+1   ",
    "sg:postcode":"27408",
    "sg:province":"NC",
    "sg:tags":[
        "business"
    ],
    "wof:name":"Atlas Computing Inc",
    "wof:placetype":"venue"
},
  "geometry": {"coordinates":[-79.843981,36.113239],"type":"Point"}
}