{
  "type": "Feature",
  "properties": {
    "addr:full":"6113 Yadkin Rd Fayetteville NC 28303",
    "addr:housenumber":"6113",
    "addr:postcode":"28303",
    "addr:street":"Yadkin Rd",
    "iso:country":"US",
    "sg:address":"6113 Yadkin Rd",
    "sg:city":"Fayetteville",
    "sg:classifiers":[
        {
            "category":"Recreation",
            "type":"Entertainment"
        }
    ],
    "sg:phone":"+1 910 487 0026",
    "sg:postcode":"28303",
    "sg:province":"NC",
    "sg:tags":[
        "bingo",
        "game"
    ],
    "wof:name":"SPCA Of Cumberland Co Bingo",
    "wof:placetype":"venue"
},
  "geometry": {"coordinates":[-78.99099099999999,35.10134],"type":"Point"}
}