{
  "type": "Feature",
  "properties": {
    "iso:country":"US",
    "sg:address":"4549 Raeford Rd",
    "sg:city":"Fayetteville",
    "sg:classifiers":[
        {
            "category":"Recreation",
            "subcategory":"Amusement Park",
            "type":"Entertainment"
        }
    ],
    "sg:phone":"+1 910 424 8541",
    "sg:postcode":"28304",
    "sg:province":"NC",
    "wof:name":"Lucky 7 Bingo",
    "wof:placetype":"venue"
},
  "geometry": {"coordinates":[-78.956723,35.043112],"type":"Point"}
}