{
  "type": "Feature",
  "properties": {
    "iso:country":"US",
    "sg:address":"1506 E Franklin St Ste 102",
    "sg:city":"Chapel Hill",
    "sg:classifiers":[
        {
            "category":"Building & Trades",
            "subcategory":"Construction",
            "type":"Services"
        }
    ],
    "sg:phone":"+1 919 942 9006",
    "sg:postcode":"27514",
    "sg:province":"NC",
    "sg:tags":[
        "contractor"
    ],
    "wof:name":"Village Building Co Inc",
    "wof:placetype":"venue"
},
  "geometry": {"coordinates":[-79.03138800000001,35.933016],"type":"Point"}
}