{
  "type": "Feature",
  "properties": {
    "iso:country":"US",
    "sg:address":"2821 Edgewood Ave",
    "sg:city":"Burlington",
    "sg:classifiers":[
        {
            "category":"Freight",
            "type":"Transportation"
        }
    ],
    "sg:phone":"+1 336 584 3057",
    "sg:postcode":"27215",
    "sg:province":"NC",
    "sg:tags":[
        "arrangement"
    ],
    "wof:name":"Harris Transportation Svcs I",
    "wof:placetype":"venue"
},
  "geometry": {"coordinates":[-79.49081200000001,36.081739],"type":"Point"}
}