{
  "type": "Feature",
  "properties": {
    "addr:full":"310 Reger Ave Swannanoa NC 28778",
    "addr:housenumber":"310",
    "addr:postcode":"28778",
    "addr:street":"Reger Ave",
    "iso:country":"US",
    "sg:address":"310 Reger Ave",
    "sg:city":"Swannanoa",
    "sg:classifiers":[
        {
            "category":"Building & Trades",
            "subcategory":"Cleaning & Sanitation",
            "type":"Services"
        }
    ],
    "sg:phone":"+1   ",
    "sg:postcode":"28778",
    "sg:province":"NC",
    "sg:tags":[
        "maintenance"
    ],
    "wof:name":"Reeces Clean Sweep",
    "wof:placetype":"venue"
},
  "geometry": {"coordinates":[-82.42952200000001,35.59733],"type":"Point"}
}