{
  "type": "Feature",
  "properties": {
    "iso:country":"US",
    "sg:address":"188 N Main St",
    "sg:city":"Mooresville",
    "sg:classifiers":[
        {
            "category":"Food & Beverages",
            "subcategory":"Bakery",
            "type":"Retail Goods"
        }
    ],
    "sg:phone":"+1 704 799 1633",
    "sg:postcode":"28115",
    "sg:province":"NC",
    "sg:tags":[
        "wholesale"
    ],
    "wof:name":"LA Patisserie",
    "wof:placetype":"venue"
},
  "geometry": {"coordinates":[-80.81085299999999,35.58391],"type":"Point"}
}