{
  "type": "Feature",
  "properties": {
    "addr:full":"8319 Providence North Dr Stokesdale NC 27357",
    "addr:housenumber":"8319",
    "addr:postcode":"27357",
    "addr:street":"Providence North Dr",
    "iso:country":"US",
    "sg:address":"8319 Providence North Dr",
    "sg:city":"Stokesdale",
    "sg:classifiers":[
        {
            "category":"Food & Beverages",
            "subcategory":"Specialty",
            "type":"Retail Goods"
        }
    ],
    "sg:phone":"+1 336 644 7852",
    "sg:postcode":"27357",
    "sg:province":"NC",
    "wof:name":"Therapy 4 ME Inc",
    "wof:placetype":"venue"
},
  "geometry": {"coordinates":[-79.943596,36.243817],"type":"Point"}
}