{
  "type": "Feature",
  "properties": {
    "iso:country":"US",
    "sg:address":"332 Dusty Hollow Rd",
    "sg:city":"Bostic",
    "sg:classifiers":[
        {
            "category":"Building & Trades",
            "subcategory":"Construction",
            "type":"Services"
        }
    ],
    "sg:phone":"+1 828 248 2165",
    "sg:postcode":"28018",
    "sg:province":"NC",
    "sg:tags":[
        "hanging",
        "contractor"
    ],
    "wof:name":"Freeman Painting Sean",
    "wof:placetype":"venue"
},
  "geometry": {"coordinates":[-81.812365,35.413962],"type":"Point"}
}