{
  "type": "Feature",
  "properties": {
    "addr:full":"150 Edward Jarman Ln Jacksonville NC 28540",
    "addr:housenumber":"150",
    "addr:postcode":"28540",
    "addr:street":"Edward Jarman Ln",
    "iso:country":"US",
    "sg:address":"150 Edward Jarman Ln",
    "sg:city":"Jacksonville",
    "sg:classifiers":[
        {
            "category":"Building & Trades",
            "subcategory":"Construction",
            "type":"Services"
        }
    ],
    "sg:phone":"+1 910 938 1255",
    "sg:postcode":"28540",
    "sg:province":"NC",
    "sg:tags":[
        "painter"
    ],
    "wof:name":"Sydes Professionalcoating",
    "wof:placetype":"venue"
},
  "geometry": {"coordinates":[-77.52745899999999,34.749496],"type":"Point"}
}