{
  "type": "Feature",
  "properties": {
    "addr:full":"191 Sterling St NW Valdese NC 28690",
    "addr:housenumber":"191",
    "addr:postcode":"28690",
    "addr:street":"Sterling St Nw",
    "iso:country":"US",
    "sg:address":"191 Sterling St NW",
    "sg:city":"Valdese",
    "sg:classifiers":[
        {
            "category":"Manufacturing",
            "subcategory":"Textiles",
            "type":"Manufacturing & Wholesale Goods"
        }
    ],
    "sg:phone":"+1 828 874 6341",
    "sg:postcode":"28690",
    "sg:province":"NC",
    "sg:tags":[
        "mills",
        "yarn"
    ],
    "sg:website":"www.burkemills.com",
    "wof:name":"Burke Mills Inc",
    "wof:placetype":"venue"
},
  "geometry": {"coordinates":[-81.577749,35.750092],"type":"Point"}
}