{
  "type": "Feature",
  "properties": {
    "addr:full":"31 Pinnacle Park Rd Weaverville NC 28787",
    "addr:housenumber":"31",
    "addr:postcode":"28787",
    "addr:street":"Pinnacle Park Rd",
    "iso:country":"US",
    "sg:address":"31 Pinnacle Park Rd",
    "sg:city":"Weaverville",
    "sg:classifiers":[
        {
            "category":"Professional",
            "subcategory":"Computer Services",
            "type":"Services"
        }
    ],
    "sg:phone":"+1   ",
    "sg:postcode":"28787",
    "sg:province":"NC",
    "sg:tags":[
        "datum"
    ],
    "wof:name":"Appalachian Animations",
    "wof:placetype":"venue"
},
  "geometry": {"coordinates":[-82.55697499999999,35.68339],"type":"Point"}
}