{
  "type": "Feature",
  "properties": {
    "iso:country":"US",
    "sg:address":"217 N George St",
    "sg:city":"Goldsboro",
    "sg:classifiers":[
        {
            "category":"Shopping",
            "subcategory":"Clothing, Apparel, & Fashions",
            "type":"Retail Goods"
        }
    ],
    "sg:phone":"+1 919 734 2020",
    "sg:postcode":"27530",
    "sg:province":"NC",
    "sg:tags":[
        "family"
    ],
    "wof:name":"CRC Enterprises",
    "wof:placetype":"venue"
},
  "geometry": {"coordinates":[-77.999234,35.386405],"type":"Point"}
}