{
  "type": "Feature",
  "properties": {
    "addr:full":"105 E Virginia Ave Bessemer City NC 28016",
    "addr:housenumber":"105",
    "addr:postcode":"28016",
    "addr:street":"E Virginia Ave",
    "iso:country":"US",
    "sg:address":"105 E Virginia Ave",
    "sg:city":"Bessemer City",
    "sg:classifiers":[
        {
            "category":"Shopping",
            "subcategory":"Clothing, Apparel, & Fashions",
            "type":"Retail Goods"
        }
    ],
    "sg:phone":"+1 704 629 6299",
    "sg:postcode":"28016",
    "sg:province":"NC",
    "sg:tags":[
        "dancing",
        "supply"
    ],
    "wof:name":"Broadway Bound",
    "wof:placetype":"venue"
},
  "geometry": {"coordinates":[-81.283818,35.284789],"type":"Point"}
}