{
  "type": "Feature",
  "properties": {
    "addr:full":"1707 Delaware Ave Durham NC 27705",
    "addr:housenumber":"1707",
    "addr:postcode":"27705",
    "addr:street":"Delaware Ave",
    "iso:country":"US",
    "sg:address":"1707 Delaware Ave",
    "sg:city":"Durham",
    "sg:classifiers":[
        {
            "category":"Education",
            "subcategory":"School",
            "type":"Public Place"
        }
    ],
    "sg:phone":"+1   ",
    "sg:postcode":"27705",
    "sg:province":"NC",
    "wof:name":"Montessori Morning Program",
    "wof:placetype":"venue"
},
  "geometry": {"coordinates":[-78.921356,36.024644],"type":"Point"}
}