{
  "type": "Feature",
  "properties": {
    "iso:country":"US",
    "sg:address":"897 Londonderry Dr",
    "sg:city":"High Point",
    "sg:classifiers":[
        {
            "category":"Health Services",
            "subcategory":"Chiropractor",
            "type":"Services"
        }
    ],
    "sg:phone":"+1 336 869 7417",
    "sg:postcode":"27265",
    "sg:province":"NC",
    "wof:name":"Wall Chiropractic",
    "wof:placetype":"venue"
},
  "geometry": {"coordinates":[-80.048196,35.988464],"type":"Point"}
}