{
  "type": "Feature",
  "properties": {
    "addr:full":"531 W Meadowview Rd Greensboro NC 27406",
    "addr:housenumber":"531",
    "addr:postcode":"27406",
    "addr:street":"W Meadowview Rd",
    "iso:country":"US",
    "sg:address":"531 W Meadowview Rd",
    "sg:city":"Greensboro",
    "sg:classifiers":[
        {
            "category":"Shopping",
            "subcategory":"Department Store",
            "type":"Retail Goods"
        }
    ],
    "sg:phone":"+1 336 274 3010",
    "sg:postcode":"27406",
    "sg:province":"NC",
    "sg:tags":[
        "shop"
    ],
    "wof:name":"Maxway",
    "wof:placetype":"venue"
},
  "geometry": {"coordinates":[-79.804106,36.037335],"type":"Point"}
}