{
  "type": "Feature",
  "properties": {
    "addr:full":"2406 Bel Aire Ave SE Wilson NC 27893",
    "addr:postcode":"2406;27893",
    "addr:street":"Bel Aire Ave Se",
    "iso:country":"US",
    "sg:address":"2406 Bel Aire Ave SE",
    "sg:city":"Wilson",
    "sg:classifiers":[
        {
            "category":"Real Estate",
            "subcategory":"Real Estate Operator",
            "type":"Services"
        }
    ],
    "sg:phone":"+1 252 237 3284",
    "sg:postcode":"27893",
    "sg:province":"NC",
    "sg:tags":[
        "building",
        "nonresidential"
    ],
    "wof:name":"C&C Properties of Wilson Inc",
    "wof:placetype":"venue"
},
  "geometry": {"coordinates":[-77.88123,35.703686],"type":"Point"}
}