{
  "type": "Feature",
  "properties": {
    "addr:full":"729 Creek Ridge Rd Greensboro NC 27406",
    "addr:housenumber":"729",
    "addr:postcode":"27406",
    "addr:street":"Creek Ridge Rd",
    "iso:country":"US",
    "sg:address":"729 Creek Ridge Rd",
    "sg:city":"Greensboro",
    "sg:classifiers":[
        {
            "category":"Organizations",
            "subcategory":"Membership Organization",
            "type":"Services"
        }
    ],
    "sg:phone":"+1   ",
    "sg:postcode":"27406",
    "sg:province":"NC",
    "wof:name":"Disabled American Veterans",
    "wof:placetype":"venue"
},
  "geometry": {"coordinates":[-79.814303,36.027571],"type":"Point"}
}