{
  "type": "Feature",
  "properties": {
    "iso:country":"US",
    "sg:address":"12271 Capital Blvd",
    "sg:city":"Wake Forest",
    "sg:classifiers":[
        {
            "category":"Ice Cream",
            "type":"Food & Drink"
        }
    ],
    "sg:menulink":"http://www.allmenus.com/nc/wake-forest/167675-dairy-queen/menu/",
    "sg:phone":"+1 919 554 2564",
    "sg:postcode":"27587",
    "sg:province":"NC",
    "sg:tags":[
        "burger",
        "american"
    ],
    "wof:name":"Dairy Queen",
    "wof:placetype":"venue"
},
  "geometry": {"coordinates":[-78.538093,35.983533],"type":"Point"}
}