{
  "type": "Feature",
  "properties": {
    "iso:country":"US",
    "sg:address":"1433 Scout Rd",
    "sg:city":"Four Oaks",
    "sg:classifiers":[
        {
            "category":"Professional",
            "type":"Services"
        }
    ],
    "sg:phone":"+1 919 938 2203",
    "sg:postcode":"27524",
    "sg:province":"NC",
    "wof:name":"Boyscout of America",
    "wof:placetype":"venue"
},
  "geometry": {"coordinates":[-78.258363,35.337749],"type":"Point"}
}