{
  "type": "Feature",
  "properties": {
    "addr:full":"2823 Saint James Church Rd Denver NC 28037",
    "addr:housenumber":"2823",
    "addr:postcode":"28037",
    "addr:street":"Saint James Church Rd",
    "iso:country":"US",
    "sg:address":"2823 Saint James Church Rd",
    "sg:city":"Denver",
    "sg:classifiers":[
        {
            "category":"Building & Trades",
            "subcategory":"Construction",
            "type":"Services"
        }
    ],
    "sg:phone":"+1 704 483 0701",
    "sg:postcode":"28037",
    "sg:province":"NC",
    "sg:tags":[
        "nonresidential"
    ],
    "wof:name":"G Lilly Construction Services",
    "wof:placetype":"venue"
},
  "geometry": {"coordinates":[-81.02551099999999,35.511652],"type":"Point"}
}