{
  "type": "Feature",
  "properties": {
    "addr:full":"104 Nash St NE Wilson NC 27893",
    "addr:housenumber":"104",
    "addr:postcode":"27893",
    "addr:street":"Nash St Ne",
    "iso:country":"US",
    "sg:address":"104 Nash St NE",
    "sg:city":"Wilson",
    "sg:classifiers":[
        {
            "category":"Professional",
            "subcategory":"Lawyer & Legal Services",
            "type":"Services"
        }
    ],
    "sg:phone":"+1 252 243 3000",
    "sg:postcode":"27893",
    "sg:province":"NC",
    "sg:tags":[
        "attorney"
    ],
    "wof:name":"Thomas & Farris Pa",
    "wof:placetype":"venue"
},
  "geometry": {"coordinates":[-77.91186,35.726689],"type":"Point"}
}