{
  "type": "Feature",
  "properties": {
    "iso:country":"US",
    "sg:address":"2300 Westover Dr",
    "sg:city":"Winston Salem",
    "sg:classifiers":[
        {
            "category":"Travel",
            "subcategory":"Travel Agent",
            "type":"Entertainment"
        }
    ],
    "sg:phone":"+1 336 725 1624",
    "sg:postcode":"27103",
    "sg:province":"NC",
    "sg:tags":[
        "agency",
        "bureau"
    ],
    "sg:website":"www.jeanwellstravel.com",
    "wof:name":"Jean Wells Travel",
    "wof:placetype":"venue"
},
  "geometry": {"coordinates":[-80.27937799999999,36.083528],"type":"Point"}
}