{
  "type": "Feature",
  "properties": {
    "addr:full":"1845 Robinwood Village Dr Gastonia NC 28054",
    "addr:housenumber":"1845",
    "addr:postcode":"28054",
    "addr:street":"Robinwood Village Dr",
    "iso:country":"US",
    "sg:address":"1845 Robinwood Village Dr",
    "sg:city":"Gastonia",
    "sg:classifiers":[
        {
            "category":"Professional",
            "subcategory":"Management & Consulting",
            "type":"Services"
        }
    ],
    "sg:phone":"+1   ",
    "sg:postcode":"28054",
    "sg:province":"NC",
    "sg:tags":[
        "export"
    ],
    "wof:name":"Spektrumn Corporation",
    "wof:placetype":"venue"
},
  "geometry": {"coordinates":[-81.14877799999999,35.241582],"type":"Point"}
}