{
  "type": "Feature",
  "properties": {
    "addr:full":"1380 Fairgrove Church Rd SE Conover NC 28613",
    "addr:housenumber":"1380",
    "addr:postcode":"28613",
    "addr:street":"Fairgrove Church Rd Se",
    "iso:country":"US",
    "sg:address":"1380 Fairgrove Church Rd SE",
    "sg:city":"Conover",
    "sg:classifiers":[
        {
            "category":"Restaurant",
            "type":"Food & Drink"
        }
    ],
    "sg:menulink":"http://www.allmenus.com/nc/hickory/211932-mcdonalds/menu/",
    "sg:phone":"+1 828 464 8551",
    "sg:postcode":"28613",
    "sg:province":"NC",
    "sg:tags":[
        "burger",
        "american"
    ],
    "wof:name":"McDonald's",
    "wof:placetype":"venue"
},
  "geometry": {"coordinates":[-81.262989,35.705504],"type":"Point"}
}