{
  "type": "Feature",
  "properties": {
    "addr:full":"7123 Raymond Rd Lucama NC 27851",
    "addr:housenumber":"7123",
    "addr:postcode":"27851",
    "addr:street":"Raymond Rd",
    "iso:country":"US",
    "sg:address":"7123 Raymond Rd",
    "sg:city":"Lucama",
    "sg:classifiers":[
        {
            "category":"Building & Trades",
            "subcategory":"Construction",
            "type":"Services"
        }
    ],
    "sg:phone":"+1 252 239 0765",
    "sg:postcode":"27851",
    "sg:province":"NC",
    "sg:tags":[
        "contractor"
    ],
    "wof:name":"Bass Welding Service",
    "wof:placetype":"venue"
},
  "geometry": {"coordinates":[-78.040977,35.625871],"type":"Point"}
}