{
  "type": "Feature",
  "properties": {
    "addr:full":"141 Old Spring Rd Belmont NC 28012",
    "addr:housenumber":"141",
    "addr:postcode":"28012",
    "addr:street":"Old Spring Rd",
    "iso:country":"US",
    "sg:address":"141 Old Spring Rd",
    "sg:city":"Belmont",
    "sg:classifiers":[
        {
            "category":"Building & Trades",
            "subcategory":"Landscaping Services",
            "type":"Services"
        }
    ],
    "sg:phone":"+1 704 825 2818",
    "sg:postcode":"28012",
    "sg:province":"NC",
    "wof:name":"JDM Seeding Inc",
    "wof:placetype":"venue"
},
  "geometry": {"coordinates":[-81.03079200000001,35.17829],"type":"Point"}
}