{
  "type": "Feature",
  "properties": {
    "addr:full":"4208 New Bern Ave Raleigh NC 27610",
    "addr:housenumber":"4208",
    "addr:postcode":"27610",
    "addr:street":"New Bern Ave",
    "iso:country":"US",
    "sg:address":"4208 New Bern Ave",
    "sg:city":"Raleigh",
    "sg:classifiers":[
        {
            "category":"Autos & Motor Vehicles",
            "subcategory":"Recreational Vehicle Sales",
            "type":"Retail Goods"
        }
    ],
    "sg:phone":"+1 919 231 8710",
    "sg:postcode":"27610",
    "sg:province":"NC",
    "sg:tags":[
        "recreation",
        "truck"
    ],
    "wof:name":"College Park",
    "wof:placetype":"venue"
},
  "geometry": {"coordinates":[-78.56554199999999,35.798604],"type":"Point"}
}