{
  "type": "Feature",
  "properties": {
    "addr:full":"415 Springtime Dr Greensboro NC 27409",
    "addr:housenumber":"415",
    "addr:postcode":"27409",
    "addr:street":"Springtime Dr",
    "iso:country":"US",
    "sg:address":"415 Springtime Dr",
    "sg:city":"Greensboro",
    "sg:classifiers":[
        {
            "category":"Insurance",
            "subcategory":"Insurance Agent",
            "type":"Services"
        }
    ],
    "sg:phone":"+1 336 852 9151",
    "sg:postcode":"27409",
    "sg:province":"NC",
    "sg:tags":[
        "consultant"
    ],
    "wof:name":"Insurance Brokerage Consulting",
    "wof:placetype":"venue"
},
  "geometry": {"coordinates":[-79.898563,36.067368],"type":"Point"}
}