{
  "type": "Feature",
  "properties": {
    "addr:full":"1463 Pleasant Union Rd Trinity NC 27370",
    "addr:housenumber":"1463",
    "addr:postcode":"27370",
    "addr:street":"Pleasant Union Rd",
    "iso:country":"US",
    "sg:address":"1463 Pleasant Union Rd",
    "sg:city":"Trinity",
    "sg:classifiers":[
        {
            "category":"Education",
            "subcategory":"School",
            "type":"Public Place"
        }
    ],
    "sg:phone":"+1 336 241 3900",
    "sg:postcode":"27370",
    "sg:province":"NC",
    "wof:name":"Uwharrie Middle School",
    "wof:placetype":"venue"
},
  "geometry": {"coordinates":[-79.992007,35.716717],"type":"Point"}
}