{
  "type": "Feature",
  "properties": {
    "iso:country":"US",
    "sg:address":"2728 Kilmarnock Ct",
    "sg:city":"Matthews",
    "sg:classifiers":[
        {
            "category":"Shopping",
            "type":"Retail Goods"
        }
    ],
    "sg:phone":"+1 704 846 0477",
    "sg:postcode":"28105",
    "sg:province":"NC",
    "sg:tags":[
        "equipment",
        "pool",
        "swimming"
    ],
    "wof:name":"Polar Pools",
    "wof:placetype":"venue"
},
  "geometry": {"coordinates":[-80.681997,35.123139],"type":"Point"}
}