{
  "type": "Feature",
  "properties": {
    "iso:country":"US",
    "sg:address":"5936 Market St",
    "sg:city":"Wilmington",
    "sg:classifiers":[
        {
            "category":"Retail",
            "subcategory":"Repair Shop",
            "type":"Services"
        }
    ],
    "sg:phone":"+1 910 799 8222",
    "sg:postcode":"28405",
    "sg:province":"NC",
    "sg:tags":[
        "equipment",
        "conditioning",
        "air"
    ],
    "wof:name":"Hollingsworth Heating & AC",
    "wof:placetype":"venue"
},
  "geometry": {"coordinates":[-77.854922,34.251171],"type":"Point"}
}