{
  "type": "Feature",
  "properties": {
    "addr:full":"1213 Newsome St Tarboro NC 27886",
    "addr:housenumber":"1213",
    "addr:postcode":"27886",
    "addr:street":"Newsome St",
    "iso:country":"US",
    "sg:address":"1213 Newsome St",
    "sg:city":"Tarboro",
    "sg:classifiers":[
        {
            "category":"Organizations",
            "subcategory":"Religious Organization",
            "type":"Services"
        }
    ],
    "sg:phone":"+1 252 641 1093",
    "sg:postcode":"27886",
    "sg:province":"NC",
    "sg:tags":[
        "church"
    ],
    "wof:name":"Grace Baptist Church",
    "wof:placetype":"venue"
},
  "geometry": {"coordinates":[-77.528558,35.927393],"type":"Point"}
}