{
  "type": "Feature",
  "properties": {
    "addr:full":"1238 Moss Rd Rutherfordton NC 28139",
    "addr:housenumber":"1238",
    "addr:postcode":"28139",
    "addr:street":"Moss Rd",
    "iso:country":"US",
    "sg:address":"1238 Moss Rd",
    "sg:city":"Rutherfordton",
    "sg:classifiers":[
        {
            "category":"Building & Trades",
            "subcategory":"Construction",
            "type":"Services"
        }
    ],
    "sg:phone":"+1 828 287 0362",
    "sg:postcode":"28139",
    "sg:province":"NC",
    "sg:tags":[
        "contractor"
    ],
    "wof:name":"Pope Roofing",
    "wof:placetype":"venue"
},
  "geometry": {"coordinates":[-82.038116,35.382557],"type":"Point"}
}