{
  "type": "Feature",
  "properties": {
    "iso:country":"US",
    "sg:address":"4004 State Hwy 205",
    "sg:city":"Marshville",
    "sg:classifiers":[
        {
            "category":"Freight",
            "type":"Transportation"
        }
    ],
    "sg:phone":"+1 704 385 9888",
    "sg:postcode":"28103",
    "sg:province":"NC",
    "wof:name":"Becks Transport Inc",
    "wof:placetype":"venue"
},
  "geometry": {"coordinates":[-80.382171,35.092221],"type":"Point"}
}