{
  "type": "Feature",
  "properties": {
    "addr:full":"5400 Olde South Rd Raleigh NC 27606",
    "addr:housenumber":"5400",
    "addr:postcode":"27606",
    "addr:street":"Olde South Rd",
    "iso:country":"US",
    "sg:address":"5400 Olde South Rd",
    "sg:city":"Raleigh",
    "sg:classifiers":[
        {
            "category":"Social Services",
            "subcategory":"Child Care",
            "type":"Services"
        }
    ],
    "sg:phone":"+1   ",
    "sg:postcode":"27606",
    "sg:province":"NC",
    "sg:tags":[
        "day"
    ],
    "wof:name":"Child Development Centre",
    "wof:placetype":"venue"
},
  "geometry": {"coordinates":[-78.710414,35.713287],"type":"Point"}
}