{
  "type": "Feature",
  "properties": {
    "iso:country":"US",
    "sg:address":"602 S Main St",
    "sg:city":"Salisbury",
    "sg:classifiers":[
        {
            "category":"Autos & Motor Vehicles",
            "subcategory":"Automobile Sales",
            "type":"Retail Goods"
        }
    ],
    "sg:phone":"+1 704 647 0220",
    "sg:postcode":"28144",
    "sg:province":"NC",
    "sg:tags":[
        "car",
        "dealer"
    ],
    "wof:name":"Edna's Auto Store",
    "wof:placetype":"venue"
},
  "geometry": {"coordinates":[-80.476525,35.662323],"type":"Point"}
}