{
  "type": "Feature",
  "properties": {
    "iso:country":"US",
    "sg:address":"2015 Ellisboro Rd",
    "sg:city":"Stokesdale",
    "sg:classifiers":[
        {
            "category":"Food & Beverages",
            "subcategory":"Groceries & Convenience Stores",
            "type":"Retail Goods"
        }
    ],
    "sg:phone":"+1 336 427 5023",
    "sg:postcode":"27357",
    "sg:province":"NC",
    "sg:tags":[
        "grocer"
    ],
    "wof:name":"Rocky's Grocery",
    "wof:placetype":"venue"
},
  "geometry": {"coordinates":[-79.978717,36.331241],"type":"Point"}
}