{
  "type": "Feature",
  "properties": {
    "iso:country":"US",
    "sg:address":"35 Chatuge Woods Dr",
    "sg:city":"Hayesville",
    "sg:classifiers":[
        {
            "category":"Building & Trades",
            "subcategory":"Construction",
            "type":"Services"
        }
    ],
    "sg:phone":"+1 828 389 0120",
    "sg:postcode":"28904",
    "sg:province":"NC",
    "sg:tags":[
        "contractor"
    ],
    "wof:name":"Cotton Builders",
    "wof:placetype":"venue"
},
  "geometry": {"coordinates":[-83.761403,35.04347],"type":"Point"}
}