{
  "type": "Feature",
  "properties": {
    "iso:country":"US",
    "sg:address":"608 W King St",
    "sg:city":"Kings Mountain",
    "sg:classifiers":[
        {
            "category":"Health Services",
            "subcategory":"Chiropractor",
            "type":"Services"
        }
    ],
    "sg:phone":"+1   ",
    "sg:postcode":"28086",
    "sg:province":"NC",
    "wof:name":"Advanced Care Clinics",
    "wof:placetype":"venue"
},
  "geometry": {"coordinates":[-81.354871,35.241032],"type":"Point"}
}