{
  "type": "Feature",
  "properties": {
    "addr:full":"510 W Main St Beulaville NC 28518",
    "addr:housenumber":"510",
    "addr:postcode":"28518",
    "addr:street":"W Main St",
    "iso:country":"US",
    "sg:address":"510 W Main St",
    "sg:city":"Beulaville",
    "sg:classifiers":[
        {
            "category":"Personal",
            "subcategory":"Barber",
            "type":"Services"
        }
    ],
    "sg:phone":"+1 910 298 4711",
    "sg:postcode":"28518",
    "sg:province":"NC",
    "wof:name":"Deno's Barber Style",
    "wof:placetype":"venue"
},
  "geometry": {"coordinates":[-77.77879799999999,34.924778],"type":"Point"}
}