{
  "type": "Feature",
  "properties": {
    "addr:full":"216 Academy St Ahoskie NC 27910",
    "addr:housenumber":"216",
    "addr:postcode":"27910",
    "addr:street":"Academy St",
    "iso:country":"US",
    "sg:address":"216 Academy St",
    "sg:city":"Ahoskie",
    "sg:classifiers":[
        {
            "category":"Health Services",
            "subcategory":"Chiropractor",
            "type":"Services"
        }
    ],
    "sg:phone":"+1 252 332 1990",
    "sg:postcode":"27910",
    "sg:province":"NC",
    "wof:name":"Cagle Chiropractic",
    "wof:placetype":"venue"
},
  "geometry": {"coordinates":[-76.989559,36.289748],"type":"Point"}
}