{
  "type": "Feature",
  "properties": {
    "addr:full":"95 Highland Center Blvd Asheville NC 28806",
    "addr:housenumber":"95",
    "addr:postcode":"28806",
    "addr:street":"Highland Center Blvd",
    "iso:country":"US",
    "sg:address":"95 Highland Center Blvd",
    "sg:city":"Asheville",
    "sg:classifiers":[
        {
            "category":"Freight",
            "type":"Transportation"
        }
    ],
    "sg:phone":"+1 828 667 3204",
    "sg:postcode":"28806",
    "sg:province":"NC",
    "sg:tags":[
        "distance",
        "long",
        "trucking"
    ],
    "wof:name":"Silvers Brothers Inc",
    "wof:placetype":"venue"
},
  "geometry": {"coordinates":[-82.635077,35.557395],"type":"Point"}
}