{
  "type": "Feature",
  "properties": {
    "iso:country":"US",
    "sg:address":"83 Rivercrest Ct",
    "sg:city":"Canton",
    "sg:classifiers":[
        {
            "category":"Professional",
            "type":"Services"
        }
    ],
    "sg:phone":"+1 828 235 8123",
    "sg:postcode":"28716",
    "sg:province":"NC",
    "wof:name":"Joyce E Clark",
    "wof:placetype":"venue"
},
  "geometry": {"coordinates":[-82.853731,35.512156],"type":"Point"}
}