{
  "type": "Feature",
  "properties": {
    "iso:country":"US",
    "sg:address":"800 Carolina Ave",
    "sg:city":"Washington",
    "sg:classifiers":[
        {
            "category":"Food & Beverages",
            "subcategory":"Groceries & Convenience Stores",
            "type":"Retail Goods"
        }
    ],
    "sg:phone":"+1 252 940 1746",
    "sg:postcode":"27889",
    "sg:province":"NC",
    "wof:name":"S & K",
    "wof:placetype":"venue"
},
  "geometry": {"coordinates":[-77.05859,35.553034],"type":"Point"}
}