{
  "type": "Feature",
  "properties": {
    "iso:country":"US",
    "sg:address":"7720 Bud Morris Rd",
    "sg:city":"Wake Forest",
    "sg:classifiers":[
        {
            "category":"Personal",
            "type":"Services"
        }
    ],
    "sg:phone":"+1 919 556 0339",
    "sg:postcode":"27587",
    "sg:province":"NC",
    "wof:name":"Newborn Home Care Inc",
    "wof:placetype":"venue"
},
  "geometry": {"coordinates":[-78.609168,35.997272],"type":"Point"}
}