{
  "type": "Feature",
  "properties": {
    "addr:full":"151 Main St Canton NC 28716",
    "addr:housenumber":"151",
    "addr:postcode":"28716",
    "addr:street":"Main St",
    "iso:country":"US",
    "sg:address":"151 Main St",
    "sg:city":"Canton",
    "sg:classifiers":[
        {
            "category":"Recreation",
            "type":"Entertainment"
        }
    ],
    "sg:phone":"+1   ",
    "sg:postcode":"28716",
    "sg:province":"NC",
    "wof:name":"Riley Academy of Martial Arts",
    "wof:placetype":"venue"
},
  "geometry": {"coordinates":[-82.837603,35.533332],"type":"Point"}
}