{
  "type": "Feature",
  "properties": {
    "iso:country":"US",
    "sg:address":"230 Greasy Creek Rd",
    "sg:city":"Marion",
    "sg:classifiers":[
        {
            "category":"Building & Trades",
            "subcategory":"Construction",
            "type":"Services"
        }
    ],
    "sg:phone":"+1 828 738 0518",
    "sg:postcode":"28752",
    "sg:province":"NC",
    "sg:tags":[
        "restoration",
        "cleaning",
        "patio",
        "deck"
    ],
    "wof:name":"Bill's Pressure Washing",
    "wof:placetype":"venue"
},
  "geometry": {"coordinates":[-82.08051500000001,35.543813],"type":"Point"}
}