{
  "type": "Feature",
  "properties": {
    "addr:full":"321 7th Ave E Hendersonville NC 28792",
    "addr:housenumber":"321",
    "addr:postcode":"28792",
    "addr:street":"7Th Ave E",
    "iso:country":"US",
    "sg:address":"321 7th Ave E",
    "sg:city":"Hendersonville",
    "sg:classifiers":[
        {
            "category":"Wholesale",
            "subcategory":"Meat",
            "type":"Manufacturing & Wholesale Goods"
        }
    ],
    "sg:phone":"+1 828 692 3558",
    "sg:postcode":"28792",
    "sg:province":"NC",
    "sg:tags":[
        "plant",
        "packing"
    ],
    "wof:name":"M & M Freezer Locker Plant",
    "wof:placetype":"venue"
},
  "geometry": {"coordinates":[-82.457868,35.320814],"type":"Point"}
}