{
  "type": "Feature",
  "properties": {
    "addr:full":"4415 Celia Creek Rd Lenoir NC 28645",
    "addr:housenumber":"4415",
    "addr:postcode":"28645",
    "addr:street":"Celia Creek Rd",
    "iso:country":"US",
    "sg:address":"4415 Celia Creek Rd",
    "sg:city":"Lenoir",
    "sg:classifiers":[
        {
            "category":"Farming",
            "subcategory":"Dairy Farm",
            "type":"Manufacturing & Wholesale Goods"
        }
    ],
    "sg:phone":"+1 828 754 5731",
    "sg:postcode":"28645",
    "sg:province":"NC",
    "wof:name":"Clay S Dairy",
    "wof:placetype":"venue"
},
  "geometry": {"coordinates":[-81.637201,35.8619],"type":"Point"}
}