{
  "type": "Feature",
  "properties": {
    "addr:full":"449 Cox Rd Gastonia NC 28054",
    "addr:housenumber":"449",
    "addr:postcode":"28054",
    "addr:street":"Cox Rd",
    "iso:country":"US",
    "sg:address":"449 Cox Rd",
    "sg:city":"Gastonia",
    "sg:classifiers":[
        {
            "category":"Travel",
            "subcategory":"Travel Agent",
            "type":"Entertainment"
        }
    ],
    "sg:phone":"+1 704 868 5372",
    "sg:postcode":"28054",
    "sg:province":"NC",
    "wof:name":"American Express",
    "wof:placetype":"venue"
},
  "geometry": {"coordinates":[-81.13361999999999,35.262522],"type":"Point"}
}