{
  "type": "Feature",
  "properties": {
    "iso:country":"US",
    "sg:address":"8208 US Highway 117 S",
    "sg:city":"Rocky Point",
    "sg:classifiers":[
        {
            "category":"Retail",
            "subcategory":"Auto Repair",
            "type":"Services"
        }
    ],
    "sg:phone":"+1 910 675 3776",
    "sg:postcode":"28457",
    "sg:province":"NC",
    "wof:name":"Don's Tire & Automotive Repair",
    "wof:placetype":"venue"
},
  "geometry": {"coordinates":[-77.87951700000001,34.439369],"type":"Point"}
}