{
  "type": "Feature",
  "properties": {
    "iso:country":"US",
    "sg:address":"3746 Clemmons Rd",
    "sg:city":"Clemmons",
    "sg:classifiers":[
        {
            "category":"Health Services",
            "subcategory":"Chiropractor",
            "type":"Services"
        }
    ],
    "sg:phone":"+1   ",
    "sg:postcode":"27012",
    "sg:province":"NC",
    "wof:name":"Foster Chiropractic Clinic PC",
    "wof:placetype":"venue"
},
  "geometry": {"coordinates":[-80.384666,36.020869],"type":"Point"}
}