{
  "type": "Feature",
  "properties": {
    "iso:country":"US",
    "sg:address":"5011 Mackay Rd",
    "sg:city":"Jamestown",
    "sg:classifiers":[
        {
            "category":"Retail",
            "subcategory":"Laundry & Dry Cleaning",
            "type":"Services"
        }
    ],
    "sg:phone":"+1   ",
    "sg:postcode":"27282",
    "sg:province":"NC",
    "sg:tags":[
        "drycleaning",
        "plant"
    ],
    "wof:name":"Hangers Dry Cleaners",
    "wof:placetype":"venue"
},
  "geometry": {"coordinates":[-79.898867,36.016075],"type":"Point"}
}