{
  "type": "Feature",
  "properties": {
    "iso:country":"US",
    "sg:address":"7700 Falls of Neuse Rd",
    "sg:city":"Raleigh",
    "sg:classifiers":[
        {
            "category":"Health Services",
            "subcategory":"Doctor",
            "type":"Services"
        }
    ],
    "sg:phone":"+1 919 676 0541",
    "sg:postcode":"27615",
    "sg:province":"NC",
    "sg:tags":[
        "dentist"
    ],
    "wof:name":"William B Brunk DDS",
    "wof:placetype":"venue"
},
  "geometry": {"coordinates":[-78.627394,35.890364],"type":"Point"}
}