{
  "type": "Feature",
  "properties": {
    "addr:full":"123 McKendree Rd Mooresville NC 28117",
    "addr:housenumber":"123",
    "addr:postcode":"28117",
    "addr:street":"Mckendree Rd",
    "iso:country":"US",
    "sg:address":"123 McKendree Rd",
    "sg:city":"Mooresville",
    "sg:classifiers":[
        {
            "category":"Shopping",
            "type":"Retail Goods"
        },
        {
            "category":"Wholesale",
            "subcategory":"Sporting Goods",
            "type":"Manufacturing & Wholesale Goods"
        }
    ],
    "sg:phone":"+1 704 663 6264",
    "sg:postcode":"28117",
    "sg:province":"NC",
    "sg:tags":[
        "canvas",
        "m",
        "product",
        "merchandise"
    ],
    "wof:name":"Carolina Custom Canvas Inc",
    "wof:placetype":"venue"
},
  "geometry": {"coordinates":[-80.92434299999999,35.563406],"type":"Point"}
}