{
  "type": "Feature",
  "properties": {
    "iso:country":"US",
    "sg:address":"4008 Bass Mountain Rd",
    "sg:city":"Snow Camp",
    "sg:classifiers":[
        {
            "category":"Building & Trades",
            "subcategory":"Construction",
            "type":"Services"
        }
    ],
    "sg:phone":"+1 336 376 0624",
    "sg:postcode":"27349",
    "sg:province":"NC",
    "sg:tags":[
        "house"
    ],
    "wof:name":"Southern Builders of Alamance",
    "wof:placetype":"venue"
},
  "geometry": {"coordinates":[-79.402824,35.981668],"type":"Point"}
}