{
  "type": "Feature",
  "properties": {
    "iso:country":"US",
    "sg:address":"4632 Delrae Cir",
    "sg:city":"Concord",
    "sg:classifiers":[
        {
            "category":"Professional",
            "type":"Services"
        }
    ],
    "sg:phone":"+1 704 455 9282",
    "sg:postcode":"28027",
    "sg:province":"NC",
    "sg:tags":[
        "campground",
        "recreational",
        "park",
        "vehicle"
    ],
    "wof:name":"Glen-Wood Acres",
    "wof:placetype":"venue"
},
  "geometry": {"coordinates":[-80.69238300000001,35.351749],"type":"Point"}
}