{
  "type": "Feature",
  "properties": {
    "addr:full":"232 Causeway Dr Wrightsville Bch NC 28480",
    "addr:housenumber":"232",
    "addr:postcode":"28480",
    "addr:street":"Causeway Dr",
    "iso:country":"US",
    "sg:address":"232 Causeway Dr",
    "sg:city":"Wrightsville Bch",
    "sg:classifiers":[
        {
            "category":"Professional",
            "subcategory":"Lawyer & Legal Services",
            "type":"Services"
        }
    ],
    "sg:phone":"+1 910 256 6896",
    "sg:postcode":"28480",
    "sg:province":"NC",
    "sg:tags":[
        "attorney"
    ],
    "wof:name":"Anderson Daniel & Coxe",
    "wof:placetype":"venue"
},
  "geometry": {"coordinates":[-77.809697,34.216656],"type":"Point"}
}