{
  "type": "Feature",
  "properties": {
    "iso:country":"US",
    "sg:address":"416 S Main St",
    "sg:city":"Davidson",
    "sg:classifiers":[
        {
            "category":"Cafe",
            "type":"Food & Drink"
        }
    ],
    "sg:menulink":"http://www.allmenus.com/nc/deweese/282706-campania-cafe/menu/",
    "sg:phone":"+1 704 987 5111",
    "sg:postcode":"28036",
    "sg:province":"NC",
    "sg:tags":[
        "italian"
    ],
    "wof:name":"Campania Cafe",
    "wof:placetype":"venue"
},
  "geometry": {"coordinates":[-80.853177,35.496082],"type":"Point"}
}