{
  "type": "Feature",
  "properties": {
    "iso:country":"US",
    "sg:address":"311 Central Ave",
    "sg:city":"Butner",
    "sg:classifiers":[
        {
            "category":"Home & Garden",
            "subcategory":"Hardware",
            "type":"Retail Goods"
        }
    ],
    "sg:phone":"+1 919 575 4262",
    "sg:postcode":"27509",
    "sg:province":"NC",
    "sg:tags":[
        "store"
    ],
    "wof:name":"Butner Hardware & Paint",
    "wof:placetype":"venue"
},
  "geometry": {"coordinates":[-78.758698,36.134201],"type":"Point"}
}