{
  "type": "Feature",
  "properties": {
    "addr:full":"119 Kristens Court Dr Mooresville NC 28115",
    "addr:housenumber":"119",
    "addr:postcode":"28115",
    "addr:street":"Kristens Court Dr",
    "iso:country":"US",
    "sg:address":"119 Kristens Court Dr",
    "sg:city":"Mooresville",
    "sg:classifiers":[
        {
            "category":"Freight",
            "type":"Transportation"
        }
    ],
    "sg:phone":"+1 704 664 9830",
    "sg:postcode":"28115",
    "sg:province":"NC",
    "sg:tags":[
        "trucking"
    ],
    "wof:name":"Albert Transport Inc",
    "wof:placetype":"venue"
},
  "geometry": {"coordinates":[-80.797713,35.606457],"type":"Point"}
}