{
  "type": "Feature",
  "properties": {
    "addr:full":"2050 Catawba Valley Blvd SE Hickory NC 28602",
    "addr:housenumber":"2050",
    "addr:postcode":"28602",
    "addr:street":"Catawba Valley Blvd Se",
    "iso:country":"US",
    "sg:address":"2050 Catawba Valley Blvd SE",
    "sg:city":"Hickory",
    "sg:classifiers":[
        {
            "category":"Building & Trades",
            "subcategory":"Construction",
            "type":"Services"
        }
    ],
    "sg:phone":"+1 828 624 4010",
    "sg:postcode":"28602",
    "sg:province":"NC",
    "sg:tags":[
        "contractor"
    ],
    "wof:name":"Colson Park Construction Inc",
    "wof:placetype":"venue"
},
  "geometry": {"coordinates":[-81.303832,35.700895],"type":"Point"}
}