{
  "type": "Feature",
  "properties": {
    "iso:country":"US",
    "sg:address":"969 N Main St",
    "sg:city":"Mooresville",
    "sg:classifiers":[
        {
            "category":"Restaurant",
            "type":"Food & Drink"
        }
    ],
    "sg:menulink":"http://www.allmenus.com/nc/coddle-creek/229292-little-spaghetti/menu/",
    "sg:phone":"+1 704 663 1510",
    "sg:postcode":"28115",
    "sg:province":"NC",
    "sg:tags":[
        "american"
    ],
    "wof:name":"Little Spaghetti",
    "wof:placetype":"venue"
},
  "geometry": {"coordinates":[-80.798042,35.587932],"type":"Point"}
}