{
  "type": "Feature",
  "properties": {
    "addr:full":"207 S Poindexter St Elizabeth City NC 27909",
    "addr:housenumber":"207",
    "addr:postcode":"27909",
    "addr:street":"S Poindexter St",
    "iso:country":"US",
    "sg:address":"207 S Poindexter St",
    "sg:city":"Elizabeth City",
    "sg:classifiers":[
        {
            "category":"Shopping",
            "subcategory":"Pharmacy",
            "type":"Retail Goods"
        }
    ],
    "sg:phone":"+1 252 335 2901",
    "sg:postcode":"27909",
    "sg:province":"NC",
    "wof:name":"Todd's Pharmacy Inc",
    "wof:placetype":"venue"
},
  "geometry": {"coordinates":[-76.219863,36.29902],"type":"Point"}
}