{
  "type": "Feature",
  "properties": {
    "addr:full":"15400 Cabarrus Rd Charlotte NC 28227",
    "addr:postcode":"15400;28227",
    "addr:street":"Cabarrus Rd",
    "iso:country":"US",
    "sg:address":"15400 Cabarrus Rd",
    "sg:city":"Charlotte",
    "sg:classifiers":[
        {
            "category":"Shopping",
            "subcategory":"Computers & Home Electronics",
            "type":"Retail Goods"
        }
    ],
    "sg:phone":"+1 704 545 5444",
    "sg:postcode":"28227",
    "sg:province":"NC",
    "sg:tags":[
        "equipment",
        "dealer"
    ],
    "wof:name":"Gemini Purchasing Inc",
    "wof:placetype":"venue"
},
  "geometry": {"coordinates":[-80.601821,35.214818],"type":"Point"}
}