{
  "type": "Feature",
  "properties": {
    "addr:full":"620 Hanes Mall Blvd Winston Salem NC 27103",
    "addr:housenumber":"620",
    "addr:postcode":"27103",
    "addr:street":"Hanes Mall Blvd",
    "iso:country":"US",
    "sg:address":"620 Hanes Mall Blvd",
    "sg:city":"Winston Salem",
    "sg:classifiers":[
        {
            "category":"Restaurant",
            "type":"Food & Drink"
        }
    ],
    "sg:menulink":"http://www.allmenus.com/nc/winston/64366-chuck-e-cheeses/menu/",
    "sg:phone":"+1 336 774 0690",
    "sg:postcode":"27103",
    "sg:province":"NC",
    "sg:tags":[
        "american",
        "pizza"
    ],
    "wof:name":"Chuck E. Cheese's",
    "wof:placetype":"venue"
},
  "geometry": {"coordinates":[-80.302111,36.062795],"type":"Point"}
}