{
  "type": "Feature",
  "properties": {
    "addr:full":"701 S Sharon Amity Rd Charlotte NC 28211",
    "addr:housenumber":"701",
    "addr:postcode":"28211",
    "addr:street":"S Sharon Amity Rd",
    "iso:country":"US",
    "sg:address":"701 S Sharon Amity Rd",
    "sg:city":"Charlotte",
    "sg:classifiers":[
        {
            "category":"Personal",
            "subcategory":"Beauty Salon",
            "type":"Services"
        }
    ],
    "sg:phone":"+1 704 366 3662",
    "sg:postcode":"28211",
    "sg:province":"NC",
    "sg:tags":[
        "barber"
    ],
    "sg:website":"http://www.greatclips.com/",
    "wof:name":"Great Clips",
    "wof:placetype":"venue"
},
  "geometry": {"coordinates":[-80.80746000000001,35.171841],"type":"Point"}
}