{
  "type": "Feature",
  "properties": {
    "addr:full":"4512 S Shiner Dr Nags Head NC 27959",
    "addr:housenumber":"4512",
    "addr:postcode":"27959",
    "addr:street":"S Shiner Dr",
    "iso:country":"US",
    "sg:address":"4512 S Shiner Dr",
    "sg:city":"Nags Head",
    "sg:classifiers":[
        {
            "category":"Building & Trades",
            "subcategory":"Construction",
            "type":"Services"
        }
    ],
    "sg:phone":"+1 252 449 8681",
    "sg:postcode":"27959",
    "sg:province":"NC",
    "sg:tags":[
        "house"
    ],
    "wof:name":"Lowes Construction",
    "wof:placetype":"venue"
},
  "geometry": {"coordinates":[-75.624307,35.944297],"type":"Point"}
}