{
  "type": "Feature",
  "properties": {
    "iso:country":"US",
    "sg:address":"640 Spring Branch Rd",
    "sg:city":"Wilmington",
    "sg:classifiers":[
        {
            "category":"Real Estate",
            "subcategory":"Real Estate Agent",
            "type":"Services"
        }
    ],
    "sg:phone":"+1 910 392 1102",
    "sg:postcode":"28405",
    "sg:province":"NC",
    "wof:name":"Benton Associates",
    "wof:placetype":"venue"
},
  "geometry": {"coordinates":[-77.872123,34.257632],"type":"Point"}
}