{
  "type": "Feature",
  "properties": {
    "addr:full":"326 W 10th St Charlotte NC 28202",
    "addr:housenumber":"326",
    "addr:postcode":"28202",
    "addr:street":"W 10Th St",
    "iso:country":"US",
    "sg:address":"326 W 10th St",
    "sg:city":"Charlotte",
    "sg:classifiers":[
        {
            "category":"Professional",
            "subcategory":"Management & Consulting",
            "type":"Services"
        },
        {
            "category":"Professional",
            "subcategory":"Employment Agencies",
            "type":"Services"
        }
    ],
    "sg:phone":"+1 704 377 0362",
    "sg:postcode":"28202",
    "sg:province":"NC",
    "sg:tags":[
        "consultant",
        "search",
        "executive",
        "opportunity"
    ],
    "sg:website":"http://www.colemanlew.com",
    "wof:name":"Coleman Lew & Associates",
    "wof:placetype":"venue"
},
  "geometry": {"coordinates":[-80.838725,35.233873],"type":"Point"}
}