{
  "type": "Feature",
  "properties": {
    "iso:country":"US",
    "sg:address":"4775 Yadkin Rd",
    "sg:city":"Fayetteville",
    "sg:classifiers":[
        {
            "category":"Autos & Motor Vehicles",
            "subcategory":"Auto Supplies",
            "type":"Retail Goods"
        },
        {
            "category":"Retail",
            "subcategory":"Auto Repair",
            "type":"Services"
        }
    ],
    "sg:phone":"+1 910 864 0775",
    "sg:postcode":"28303",
    "sg:province":"NC",
    "sg:tags":[
        "automotive",
        "tire"
    ],
    "wof:name":"Ed's Tire & Auto Shop",
    "wof:placetype":"venue"
},
  "geometry": {"coordinates":[-78.961659,35.080689],"type":"Point"}
}