{
  "type": "Feature",
  "properties": {
    "addr:full":"110 Valley River Ave Murphy NC 28906",
    "addr:housenumber":"110",
    "addr:postcode":"28906",
    "addr:street":"Valley River Ave",
    "iso:country":"US",
    "sg:address":"110 Valley River Ave",
    "sg:city":"Murphy",
    "sg:classifiers":[
        {
            "category":"Retail",
            "subcategory":"Laundry & Dry Cleaning",
            "type":"Services"
        }
    ],
    "sg:phone":"+1 828 837 8220",
    "sg:postcode":"28906",
    "sg:province":"NC",
    "sg:tags":[
        "cleaners",
        "plant",
        "coin",
        "drycleaning"
    ],
    "wof:name":"Palmer's Cleaners Inc",
    "wof:placetype":"venue"
},
  "geometry": {"coordinates":[-84.030188,35.088454],"type":"Point"}
}