{
  "type": "Feature",
  "properties": {
    "addr:full":"4201 Thompson Mill Rd Graham NC 27253",
    "addr:housenumber":"4201",
    "addr:postcode":"27253",
    "addr:street":"Thompson Mill Rd",
    "iso:country":"US",
    "sg:address":"4201 Thompson Mill Rd",
    "sg:city":"Graham",
    "sg:classifiers":[
        {
            "category":"Shopping",
            "type":"Retail Goods"
        }
    ],
    "sg:phone":"+1 336 376 5147",
    "sg:postcode":"27253",
    "sg:province":"NC",
    "sg:tags":[
        "wedding",
        "supply"
    ],
    "wof:name":"Wedding Creations",
    "wof:placetype":"venue"
},
  "geometry": {"coordinates":[-79.39865899999999,35.970809],"type":"Point"}
}