{
  "type": "Feature",
  "properties": {
    "iso:country":"US",
    "sg:address":"1503 Sutton Dr",
    "sg:city":"Kinston",
    "sg:classifiers":[
        {
            "category":"Professional",
            "subcategory":"Computer Services",
            "type":"Services"
        }
    ],
    "sg:phone":"+1   ",
    "sg:postcode":"28501",
    "sg:province":"NC",
    "sg:tags":[
        "datum"
    ],
    "wof:name":"Phil H Crawford III",
    "wof:placetype":"venue"
},
  "geometry": {"coordinates":[-77.597236,35.27942],"type":"Point"}
}