{
  "type": "Feature",
  "properties": {
    "addr:full":"3406 Dunn Rd Fayetteville NC 28312",
    "addr:housenumber":"3406",
    "addr:postcode":"28312",
    "addr:street":"Dunn Rd",
    "iso:country":"US",
    "sg:address":"3406 Dunn Rd",
    "sg:city":"Fayetteville",
    "sg:classifiers":[
        {
            "category":"Utilities",
            "subcategory":"Mobile Phone",
            "type":"Services"
        }
    ],
    "sg:phone":"+1 910 323 9203",
    "sg:postcode":"28312",
    "sg:province":"NC",
    "sg:tags":[
        "telephone",
        "cellular"
    ],
    "wof:name":"Verizon Wireless",
    "wof:placetype":"venue"
},
  "geometry": {"coordinates":[-78.788764,35.089798],"type":"Point"}
}