{
  "type": "Feature",
  "properties": {
    "iso:country":"US",
    "sg:address":"104 Markham Dr",
    "sg:city":"Chapel Hill",
    "sg:classifiers":[
        {
            "category":"Restaurant",
            "type":"Food & Drink"
        }
    ],
    "sg:phone":"+1 919 403 2456",
    "sg:postcode":"27514",
    "sg:province":"NC",
    "wof:name":"Bayou Bistro Inc",
    "wof:placetype":"venue"
},
  "geometry": {"coordinates":[-79.029813,35.944065],"type":"Point"}
}