{
  "type": "Feature",
  "properties": {
    "addr:full":"165 Blue Hollow Rd Mount Airy NC 27030",
    "addr:housenumber":"165",
    "addr:postcode":"27030",
    "addr:street":"Blue Hollow Rd",
    "iso:country":"US",
    "sg:address":"165 Blue Hollow Rd",
    "sg:city":"Mount Airy",
    "sg:classifiers":[
        {
            "category":"Real Estate",
            "subcategory":"Real Estate Operator",
            "type":"Services"
        }
    ],
    "sg:phone":"+1 336 789 2214",
    "sg:postcode":"27030",
    "sg:province":"NC",
    "sg:tags":[
        "building",
        "nonresidential"
    ],
    "wof:name":"Treva J Kirkman Properties LLC",
    "wof:placetype":"venue"
},
  "geometry": {"coordinates":[-80.540766,36.497314],"type":"Point"}
}