{
  "type": "Feature",
  "properties": {
    "iso:country":"US",
    "sg:address":"2123 Floral Ave",
    "sg:city":"Charlotte",
    "sg:classifiers":[
        {
            "category":"Recreation",
            "type":"Entertainment"
        }
    ],
    "sg:phone":"+1   ",
    "sg:postcode":"28203",
    "sg:province":"NC",
    "wof:name":"Time 2 Tri LLC",
    "wof:placetype":"venue"
},
  "geometry": {"coordinates":[-80.84518199999999,35.198633],"type":"Point"}
}