{
  "type": "Feature",
  "properties": {
    "iso:country":"US",
    "sg:address":"2480 Raintree St",
    "sg:city":"Connellys Spgs",
    "sg:classifiers":[
        {
            "category":"Retail",
            "subcategory":"Laundry & Dry Cleaning",
            "type":"Services"
        }
    ],
    "sg:phone":"+1 828 397 7054",
    "sg:postcode":"28612",
    "sg:province":"NC",
    "sg:tags":[
        "cleaners",
        "rug",
        "carpet"
    ],
    "wof:name":"Brown's Cleaning Svc",
    "wof:placetype":"venue"
},
  "geometry": {"coordinates":[-81.453761,35.745652],"type":"Point"}
}