{
  "type": "Feature",
  "properties": {
    "addr:full":"1501 Wellington Ave Wilmington NC 28401",
    "addr:housenumber":"1501",
    "addr:postcode":"28401",
    "addr:street":"Wellington Ave",
    "iso:country":"US",
    "sg:address":"1501 Wellington Ave",
    "sg:city":"Wilmington",
    "sg:classifiers":[
        {
            "category":"Banks & Credit Unions",
            "subcategory":"Investment Brokerage",
            "type":"Services"
        }
    ],
    "sg:phone":"+1 910 799 4490",
    "sg:postcode":"28401",
    "sg:province":"NC",
    "wof:name":"James A Wolfe",
    "wof:placetype":"venue"
},
  "geometry": {"coordinates":[-77.926519,34.197362],"type":"Point"}
}