{
  "type": "Feature",
  "properties": {
    "iso:country":"US",
    "sg:address":"439 Martin Luther King Jr Blvd",
    "sg:city":"Siler City",
    "sg:classifiers":[
        {
            "category":"Education",
            "subcategory":"School",
            "type":"Public Place"
        }
    ],
    "sg:phone":"+1 919 663 5899",
    "sg:postcode":"27344",
    "sg:province":"NC",
    "wof:name":"Sage Academy",
    "wof:placetype":"venue"
},
  "geometry": {"coordinates":[-79.45997800000001,35.72922],"type":"Point"}
}