{
  "type": "Feature",
  "properties": {
    "addr:full":"5439 Central Ave Charlotte NC 28212",
    "addr:housenumber":"5439",
    "addr:postcode":"28212",
    "addr:street":"Central Ave",
    "iso:country":"US",
    "sg:address":"5439 Central Ave",
    "sg:city":"Charlotte",
    "sg:classifiers":[
        {
            "category":"Shopping",
            "subcategory":"Clothing, Apparel, & Fashions",
            "type":"Retail Goods"
        }
    ],
    "sg:phone":"+1 704 535 7333",
    "sg:postcode":"28212",
    "sg:province":"NC",
    "sg:website":"www.bodyc.com",
    "wof:name":"Body Shop",
    "wof:placetype":"venue"
},
  "geometry": {"coordinates":[-80.753308,35.207607],"type":"Point"}
}