{
  "type": "Feature",
  "properties": {
    "iso:country":"US",
    "sg:address":"7585 Sherrills Ford Rd",
    "sg:city":"Salisbury",
    "sg:classifiers":[
        {
            "category":"Wholesale",
            "subcategory":"Metals & Minerals",
            "type":"Manufacturing & Wholesale Goods"
        }
    ],
    "sg:phone":"+1 704 636 9821",
    "sg:postcode":"28147",
    "sg:province":"NC",
    "sg:tags":[
        "steel",
        "warehouse"
    ],
    "wof:name":"Davis Enterprises Inc",
    "wof:placetype":"venue"
},
  "geometry": {"coordinates":[-80.610225,35.695947],"type":"Point"}
}