{
  "type": "Feature",
  "properties": {
    "addr:full":"1812 W Morehead St Charlotte NC 28208",
    "addr:housenumber":"1812",
    "addr:postcode":"28208",
    "addr:street":"W Morehead St",
    "iso:country":"US",
    "sg:address":"1812 W Morehead St",
    "sg:city":"Charlotte",
    "sg:classifiers":[
        {
            "category":"Wholesale",
            "subcategory":"Construction Materials",
            "type":"Manufacturing & Wholesale Goods"
        }
    ],
    "sg:phone":"+1 704 379 7900",
    "sg:postcode":"28208",
    "sg:province":"NC",
    "sg:tags":[
        "product",
        "masonry",
        "brick",
        "related"
    ],
    "sg:website":"www.brickandstone.com",
    "wof:name":"Brick Yard LTD",
    "wof:placetype":"venue"
},
  "geometry": {"coordinates":[-80.87334799999999,35.227988],"type":"Point"}
}