{
  "type": "Feature",
  "properties": {
    "iso:country":"US",
    "sg:address":"312 Commerce Ave",
    "sg:city":"Morehead City",
    "sg:classifiers":[
        {
            "category":"Professional",
            "subcategory":"Accounting & Tax Preparation",
            "type":"Services"
        }
    ],
    "sg:phone":"+1 252 727 5600",
    "sg:postcode":"28557",
    "sg:province":"NC",
    "sg:tags":[
        "accountant"
    ],
    "wof:name":"Chused & Assoc",
    "wof:placetype":"venue"
},
  "geometry": {"coordinates":[-76.74802800000001,34.728312],"type":"Point"}
}