{
  "type": "Feature",
  "properties": {
    "iso:country":"US",
    "sg:address":"64 Coggins Rd",
    "sg:city":"Walstonburg",
    "sg:classifiers":[
        {
            "category":"Building & Trades",
            "subcategory":"Construction",
            "type":"Services"
        }
    ],
    "sg:phone":"+1 252 747 5373",
    "sg:postcode":"27888",
    "sg:province":"NC",
    "sg:tags":[
        "house"
    ],
    "wof:name":"Ashley Jones",
    "wof:placetype":"venue"
},
  "geometry": {"coordinates":[-77.721548,35.538127],"type":"Point"}
}