{
  "type": "Feature",
  "properties": {
    "iso:country":"US",
    "sg:address":"6657 Beach Dr SW",
    "sg:city":"Ocean Isle Beach",
    "sg:classifiers":[
        {
            "category":"Health Services",
            "subcategory":"Chiropractor",
            "type":"Services"
        }
    ],
    "sg:phone":"+1 910 579 3502",
    "sg:postcode":"28469",
    "sg:province":"NC",
    "wof:name":"Chiropractic Center-Shallotte",
    "wof:placetype":"venue"
},
  "geometry": {"coordinates":[-78.45793399999999,33.900273],"type":"Point"}
}