{
  "type": "Feature",
  "properties": {
    "iso:country":"US",
    "sg:address":"240 Dixie Blvd",
    "sg:city":"Morganton",
    "sg:classifiers":[
        {
            "category":"Wholesale",
            "subcategory":"Machinery & Supplies",
            "type":"Manufacturing & Wholesale Goods"
        }
    ],
    "sg:phone":"+1 828 584 4990",
    "sg:postcode":"28655",
    "sg:province":"NC",
    "sg:tags":[
        "equipment",
        "industrial"
    ],
    "wof:name":"Burke Industrial Supply Inc",
    "wof:placetype":"venue"
},
  "geometry": {"coordinates":[-81.753811,35.723243],"type":"Point"}
}