{
  "type": "Feature",
  "properties": {
    "iso:country":"US",
    "sg:address":"116 Wedgewood Dr",
    "sg:city":"Roanoke Rapids",
    "sg:classifiers":[
        {
            "category":"Professional",
            "subcategory":"Detective & Security Services",
            "type":"Services"
        }
    ],
    "sg:phone":"+1   ",
    "sg:postcode":"27870",
    "sg:province":"NC",
    "sg:tags":[
        "system"
    ],
    "wof:name":"Secure Solutions Inc",
    "wof:placetype":"venue"
},
  "geometry": {"coordinates":[-77.685361,36.464232],"type":"Point"}
}