{
  "type": "Feature",
  "properties": {
    "addr:full":"265 Charlotte St Asheville NC 28801",
    "addr:housenumber":"265",
    "addr:postcode":"28801",
    "addr:street":"Charlotte St",
    "iso:country":"US",
    "sg:address":"265 Charlotte St",
    "sg:city":"Asheville",
    "sg:classifiers":[
        {
            "category":"Professional",
            "subcategory":"Business Services",
            "type":"Services"
        }
    ],
    "sg:phone":"+1 828 253 2880",
    "sg:postcode":"28801",
    "sg:province":"NC",
    "sg:tags":[
        "association"
    ],
    "wof:name":"Ashevillecom",
    "wof:placetype":"venue"
},
  "geometry": {"coordinates":[-82.546029,35.608526],"type":"Point"}
}