{
  "type": "Feature",
  "properties": {
    "iso:country":"US",
    "sg:address":"5826 South Blvd",
    "sg:city":"Charlotte",
    "sg:classifiers":[
        {
            "category":"Retail",
            "subcategory":"Auto Repair",
            "type":"Services"
        }
    ],
    "sg:phone":"+1   ",
    "sg:postcode":"28217",
    "sg:province":"NC",
    "sg:tags":[
        "general"
    ],
    "wof:name":"Hondashop",
    "wof:placetype":"venue"
},
  "geometry": {"coordinates":[-80.87638800000001,35.153057],"type":"Point"}
}