{
  "type": "Feature",
  "properties": {
    "addr:full":"1022 Hipp Rd Charlotte NC 28216",
    "addr:housenumber":"1022",
    "addr:postcode":"28216",
    "addr:street":"Hipp Rd",
    "iso:country":"US",
    "sg:address":"1022 Hipp Rd",
    "sg:city":"Charlotte",
    "sg:classifiers":[
        {
            "category":"Professional",
            "subcategory":"Management & Consulting",
            "type":"Services"
        },
        {
            "category":"Professional",
            "subcategory":"Advertising",
            "type":"Services"
        }
    ],
    "sg:phone":"+1 704 208 7088",
    "sg:postcode":"28216",
    "sg:province":"NC",
    "sg:tags":[
        "marketing",
        "program",
        "consultant"
    ],
    "wof:name":"Ross Marketing",
    "wof:placetype":"venue"
},
  "geometry": {"coordinates":[-80.90319700000001,35.29999],"type":"Point"}
}