{
  "type": "Feature",
  "properties": {
    "iso:country":"US",
    "sg:address":"1108 Union Rd",
    "sg:city":"Gastonia",
    "sg:classifiers":[
        {
            "category":"Food & Beverages",
            "subcategory":"Groceries & Convenience Stores",
            "type":"Retail Goods"
        }
    ],
    "sg:phone":"+1 704 866 0464",
    "sg:postcode":"28054",
    "sg:province":"NC",
    "wof:name":"Pattys Service",
    "wof:placetype":"venue"
},
  "geometry": {"coordinates":[-81.174482,35.248529],"type":"Point"}
}