{
  "type": "Feature",
  "properties": {
    "iso:country":"US",
    "sg:address":"133 Clear Vista Ln",
    "sg:city":"Asheville",
    "sg:classifiers":[
        {
            "category":"Professional",
            "subcategory":"Management & Consulting",
            "type":"Services"
        }
    ],
    "sg:phone":"+1   ",
    "sg:postcode":"28805",
    "sg:province":"NC",
    "sg:tags":[
        "business"
    ],
    "wof:name":"Counsell Consulting Corp",
    "wof:placetype":"venue"
},
  "geometry": {"coordinates":[-82.483535,35.60281],"type":"Point"}
}