{
  "type": "Feature",
  "properties": {
    "iso:country":"US",
    "sg:address":"2420 Davis Dr",
    "sg:city":"Cary",
    "sg:classifiers":[
        {
            "category":"Autos & Motor Vehicles",
            "subcategory":"Automobile Sales",
            "type":"Retail Goods"
        },
        {
            "category":"Autos & Motor Vehicles",
            "subcategory":"Auto Supplies",
            "type":"Retail Goods"
        },
        {
            "category":"Retail",
            "subcategory":"Auto Repair",
            "type":"Services"
        }
    ],
    "sg:phone":"+1 919 467 4872",
    "sg:postcode":"27519",
    "sg:province":"NC",
    "sg:tags":[
        "body",
        "repairing",
        "tire",
        "accessory",
        "equipment",
        "part",
        "truck",
        "electrical",
        "painting"
    ],
    "wof:name":"Council & Son Repair Service",
    "wof:placetype":"venue"
},
  "geometry": {"coordinates":[-78.84703399999999,35.792885],"type":"Point"}
}