{
  "type": "Feature",
  "properties": {
    "iso:country":"US",
    "sg:address":"2302 Mc Knight Mill Rd",
    "sg:city":"Greensboro",
    "sg:classifiers":[
        {
            "category":"Building & Trades",
            "subcategory":"Landscaping Services",
            "type":"Services"
        }
    ],
    "sg:phone":"+1 336 375 0910",
    "sg:postcode":"27405",
    "sg:province":"NC",
    "sg:tags":[
        "landscape"
    ],
    "wof:name":"Marks John Ldscpg Prprty Maint",
    "wof:placetype":"venue"
},
  "geometry": {"coordinates":[-79.734939,36.124766],"type":"Point"}
}