{
  "type": "Feature",
  "properties": {
    "addr:full":"108 McWalker Rd Reidsville NC 27320",
    "addr:housenumber":"108",
    "addr:postcode":"27320",
    "addr:street":"Mcwalker Rd",
    "iso:country":"US",
    "sg:address":"108 McWalker Rd",
    "sg:city":"Reidsville",
    "sg:classifiers":[
        {
            "category":"Building & Trades",
            "subcategory":"Construction",
            "type":"Services"
        },
        {
            "category":"Real Estate",
            "subcategory":"Real Estate Operator",
            "type":"Services"
        }
    ],
    "sg:phone":"+1 336 349 5033",
    "sg:postcode":"27320",
    "sg:province":"NC",
    "sg:tags":[
        "house",
        "parks"
    ],
    "wof:name":"Hudson Bay Buildings",
    "wof:placetype":"venue"
},
  "geometry": {"coordinates":[-79.65961799999999,36.254723],"type":"Point"}
}