{
  "type": "Feature",
  "properties": {
    "iso:country":"US",
    "sg:address":"553 Fork Rd",
    "sg:city":"Norwood",
    "sg:classifiers":[
        {
            "category":"Organizations",
            "subcategory":"Religious Organization",
            "type":"Services"
        }
    ],
    "sg:phone":"+1 704 474 3634",
    "sg:postcode":"28128",
    "sg:province":"NC",
    "sg:tags":[
        "church"
    ],
    "wof:name":"Barringer Chapel Baptist",
    "wof:placetype":"venue"
},
  "geometry": {"coordinates":[-80.111951,35.21818],"type":"Point"}
}