{
  "type": "Feature",
  "properties": {
    "iso:country":"US",
    "sg:address":"1228 Eastchester Dr",
    "sg:city":"High Point",
    "sg:classifiers":[
        {
            "category":"Shopping",
            "type":"Retail Goods"
        },
        {
            "category":"Shopping",
            "subcategory":"Florist",
            "type":"Retail Goods"
        }
    ],
    "sg:phone":"+1 336 883 6868",
    "sg:postcode":"27265",
    "sg:province":"NC",
    "sg:tags":[
        "merchandise"
    ],
    "wof:name":"Flowers & Gifts By U Inc",
    "wof:placetype":"venue"
},
  "geometry": {"coordinates":[-79.998121,35.992791],"type":"Point"}
}