{
  "type": "Feature",
  "properties": {
    "iso:country":"US",
    "sg:address":"824 W 4th St",
    "sg:city":"Winston Salem",
    "sg:classifiers":[
        {
            "category":"Professional",
            "subcategory":"Computer Services",
            "type":"Services"
        }
    ],
    "sg:phone":"+1   ",
    "sg:postcode":"27101",
    "sg:province":"NC",
    "sg:tags":[
        "related"
    ],
    "wof:name":"C Tek",
    "wof:placetype":"venue"
},
  "geometry": {"coordinates":[-80.25552999999999,36.097121],"type":"Point"}
}