{
  "type": "Feature",
  "properties": {
    "addr:full":"3790 Guess Rd Durham NC 27705",
    "addr:housenumber":"3790",
    "addr:postcode":"27705",
    "addr:street":"Guess Rd",
    "iso:country":"US",
    "sg:address":"3790 Guess Rd",
    "sg:city":"Durham",
    "sg:classifiers":[
        {
            "category":"Personal",
            "type":"Services"
        }
    ],
    "sg:phone":"+1 919 477 3224",
    "sg:postcode":"27705",
    "sg:province":"NC",
    "sg:tags":[
        "therapist",
        "massage"
    ],
    "sg:website":"www.bodyworkscenter.com",
    "wof:name":"Bodyworks Treatment & Prvntn",
    "wof:placetype":"venue"
},
  "geometry": {"coordinates":[-78.929085,36.057234],"type":"Point"}
}