{
  "type": "Feature",
  "properties": {
    "iso:country":"US",
    "sg:address":"1209 Congressional Ln",
    "sg:city":"Wilmington",
    "sg:classifiers":[
        {
            "category":"Professional",
            "subcategory":"Management & Consulting",
            "type":"Services"
        }
    ],
    "sg:phone":"+1 910 686 9321",
    "sg:postcode":"28411",
    "sg:province":"NC",
    "sg:tags":[
        "consultant"
    ],
    "wof:name":"Henriksen Consulting",
    "wof:placetype":"venue"
},
  "geometry": {"coordinates":[-77.75906500000001,34.299799],"type":"Point"}
}