{
  "type": "Feature",
  "properties": {
    "iso:country":"US",
    "sg:address":"107 Market St",
    "sg:city":"Wilmington",
    "sg:classifiers":[
        {
            "category":"Shopping",
            "subcategory":"Tobacco",
            "type":"Retail Goods"
        }
    ],
    "sg:phone":"+1 910 251 5015",
    "sg:postcode":"28401",
    "sg:province":"NC",
    "sg:tags":[
        "product"
    ],
    "wof:name":"Cigar Exchange",
    "wof:placetype":"venue"
},
  "geometry": {"coordinates":[-77.947489,34.235438],"type":"Point"}
}