{
  "type": "Feature",
  "properties": {
    "iso:country":"US",
    "sg:address":"122 Hickory Hills Rd",
    "sg:city":"Swansboro",
    "sg:classifiers":[
        {
            "category":"Building & Trades",
            "subcategory":"Electrical",
            "type":"Services"
        }
    ],
    "sg:phone":"+1 252 393 7519",
    "sg:postcode":"28584",
    "sg:province":"NC",
    "sg:tags":[
        "electrical",
        "contractor"
    ],
    "wof:name":"Renards Electrical",
    "wof:placetype":"venue"
},
  "geometry": {"coordinates":[-77.068662,34.704948],"type":"Point"}
}