{
  "type": "Feature",
  "properties": {
    "iso:country":"US",
    "sg:address":"859 New Leicester Hwy",
    "sg:city":"Asheville",
    "sg:classifiers":[
        {
            "category":"Autos & Motor Vehicles",
            "subcategory":"Automobile Sales",
            "type":"Retail Goods"
        }
    ],
    "sg:phone":"+1 828 683 7700",
    "sg:postcode":"28806",
    "sg:province":"NC",
    "sg:tags":[
        "car",
        "dealer"
    ],
    "wof:name":"S & R Auto Sales",
    "wof:placetype":"venue"
},
  "geometry": {"coordinates":[-82.64694,35.614197],"type":"Point"}
}