{
  "type": "Feature",
  "properties": {
    "iso:country":"US",
    "sg:address":"1421 Elizabeth Ave",
    "sg:city":"Charlotte",
    "sg:classifiers":[
        {
            "category":"Deli",
            "type":"Food & Drink"
        }
    ],
    "sg:menulink":"http://www.allmenus.com/nc/charlotte/46963-leos-deli/menu/",
    "sg:phone":"+1 704 375 2400",
    "sg:postcode":"28204",
    "sg:province":"NC",
    "sg:tags":[
        "american"
    ],
    "wof:name":"Leo's Deli",
    "wof:placetype":"venue"
},
  "geometry": {"coordinates":[-80.82817900000001,35.215218],"type":"Point"}
}