{
  "type": "Feature",
  "properties": {
    "addr:full":"2652 Hester Rd Oxford NC 27522",
    "addr:housenumber":"2652",
    "addr:postcode":"27522",
    "addr:street":"Hester Rd",
    "iso:country":"US",
    "sg:address":"2652 Hester Rd",
    "sg:city":"Oxford",
    "sg:classifiers":[
        {
            "category":"Manufacturing",
            "subcategory":"Tools & Machinery",
            "type":"Manufacturing & Wholesale Goods"
        }
    ],
    "sg:phone":"+1 919 528 3877",
    "sg:postcode":"27522",
    "sg:province":"NC",
    "sg:tags":[
        "engine",
        "equipment",
        "electrical",
        "mfg"
    ],
    "wof:name":"Tooters Scooters LLC",
    "wof:placetype":"venue"
},
  "geometry": {"coordinates":[-78.64373999999999,36.167883],"type":"Point"}
}