{
  "type": "Feature",
  "properties": {
    "addr:full":"2321 Evans St SW Lenoir NC 28645",
    "addr:housenumber":"2321",
    "addr:postcode":"28645",
    "addr:street":"Evans St Sw",
    "iso:country":"US",
    "sg:address":"2321 Evans St SW",
    "sg:city":"Lenoir",
    "sg:classifiers":[
        {
            "category":"Social Services",
            "subcategory":"Child Care",
            "type":"Services"
        }
    ],
    "sg:phone":"+1   ",
    "sg:postcode":"28645",
    "sg:province":"NC",
    "sg:tags":[
        "day"
    ],
    "wof:name":"Lindas Daycare",
    "wof:placetype":"venue"
},
  "geometry": {"coordinates":[-81.514781,35.871064],"type":"Point"}
}