{
  "type": "Feature",
  "properties": {
    "iso:country":"US",
    "sg:address":"3501 Huffine Mill Rd",
    "sg:city":"Gibsonville",
    "sg:classifiers":[
        {
            "category":"Building & Trades",
            "subcategory":"Landscaping Services",
            "type":"Services"
        }
    ],
    "sg:phone":"+1 336 621 0453",
    "sg:postcode":"27249",
    "sg:province":"NC",
    "sg:tags":[
        "machinery"
    ],
    "wof:name":"Blooming Valley Nursery",
    "wof:placetype":"venue"
},
  "geometry": {"coordinates":[-79.608574,36.162792],"type":"Point"}
}