{
  "type": "Feature",
  "properties": {
    "addr:full":"12168 Falls of Neuse Rd Wake Forest NC 27587",
    "addr:housenumber":"12168",
    "addr:postcode":"27587",
    "addr:street":"Falls Of Neuse Rd",
    "iso:country":"US",
    "sg:address":"12168 Falls of Neuse Rd",
    "sg:city":"Wake Forest",
    "sg:classifiers":[
        {
            "category":"Organizations",
            "subcategory":"Religious Organization",
            "type":"Services"
        }
    ],
    "sg:phone":"+1   ",
    "sg:postcode":"27587",
    "sg:province":"NC",
    "wof:name":"Falls of Neuse",
    "wof:placetype":"venue"
},
  "geometry": {"coordinates":[-78.578918,35.944275],"type":"Point"}
}