{
  "type": "Feature",
  "properties": {
    "iso:country":"US",
    "sg:address":"627 State Hwy 16",
    "sg:city":"Taylorsville",
    "sg:classifiers":[
        {
            "category":"Building & Trades",
            "subcategory":"Construction",
            "type":"Services"
        }
    ],
    "sg:phone":"+1 828 632 7212",
    "sg:postcode":"28681",
    "sg:province":"NC",
    "sg:tags":[
        "siding",
        "contractor"
    ],
    "wof:name":"Northwoods Home Svc",
    "wof:placetype":"venue"
},
  "geometry": {"coordinates":[-81.18250500000001,35.921571],"type":"Point"}
}