{
  "type": "Feature",
  "properties": {
    "iso:country":"US",
    "sg:address":"2328 Davie Ave",
    "sg:city":"Statesville",
    "sg:classifiers":[
        {
            "category":"Shopping",
            "subcategory":"Department Store",
            "type":"Retail Goods"
        }
    ],
    "sg:phone":"+1 704 924 8200",
    "sg:postcode":"28625",
    "sg:province":"NC",
    "sg:tags":[
        "shop"
    ],
    "wof:name":"Country Cabin Discount Market",
    "wof:placetype":"venue"
},
  "geometry": {"coordinates":[-80.857534,35.803859],"type":"Point"}
}