{
  "type": "Feature",
  "properties": {
    "addr:full":"314 Bay City Rd Aurora NC 27806",
    "addr:housenumber":"314",
    "addr:postcode":"27806",
    "addr:street":"Bay City Rd",
    "iso:country":"US",
    "sg:address":"314 Bay City Rd",
    "sg:city":"Aurora",
    "sg:phone":"+1 252 322 5329",
    "sg:postcode":"27806",
    "sg:province":"NC",
    "sg:tags":[
        "farm",
        "corn"
    ],
    "wof:name":"Lloyd Hollowell",
    "wof:placetype":"venue"
},
  "geometry": {"coordinates":[-76.76910700000001,35.299406],"type":"Point"}
}