{
  "type": "Feature",
  "properties": {
    "addr:full":"2516 Hillsborough St Raleigh NC 27607",
    "addr:housenumber":"2516",
    "addr:postcode":"27607",
    "addr:street":"Hillsborough St",
    "iso:country":"US",
    "sg:address":"2516 Hillsborough St",
    "sg:city":"Raleigh",
    "sg:classifiers":[
        {
            "category":"Shopping",
            "subcategory":"Clothing, Apparel, & Fashions",
            "type":"Retail Goods"
        }
    ],
    "sg:phone":"+1 919 834 7420",
    "sg:postcode":"27607",
    "sg:province":"NC",
    "wof:name":"Detour",
    "wof:placetype":"venue"
},
  "geometry": {"coordinates":[-78.66943999999999,35.788147],"type":"Point"}
}