{
  "type": "Feature",
  "properties": {
    "addr:full":"4125 Ben Franklin Blvd Durham NC 27704",
    "addr:housenumber":"4125",
    "addr:postcode":"27704",
    "addr:street":"Ben Franklin Blvd",
    "iso:country":"US",
    "sg:address":"4125 Ben Franklin Blvd",
    "sg:city":"Durham",
    "sg:classifiers":[
        {
            "category":"Health Services",
            "subcategory":"Doctor",
            "type":"Services"
        }
    ],
    "sg:phone":"+1   ",
    "sg:postcode":"27704",
    "sg:province":"NC",
    "sg:tags":[
        "physician"
    ],
    "wof:name":"Durham Orthopedic Clinic",
    "wof:placetype":"venue"
},
  "geometry": {"coordinates":[-78.898132,36.044722],"type":"Point"}
}