{
  "type": "Feature",
  "properties": {
    "addr:full":"808 Crawley Gin Rd Shelby NC 28150",
    "addr:housenumber":"808",
    "addr:postcode":"28150",
    "addr:street":"Crawley Gin Rd",
    "iso:country":"US",
    "sg:address":"808 Crawley Gin Rd",
    "sg:city":"Shelby",
    "sg:classifiers":[
        {
            "category":"Wholesale",
            "subcategory":"Auto Parts",
            "type":"Manufacturing & Wholesale Goods"
        }
    ],
    "sg:phone":"+1 704 434 7872",
    "sg:postcode":"28150",
    "sg:province":"NC",
    "wof:name":"Mike Harrill",
    "wof:placetype":"venue"
},
  "geometry": {"coordinates":[-81.69305900000001,35.334957],"type":"Point"}
}