{
  "type": "Feature",
  "properties": {
    "addr:full":"3224 Cricketeer Dr Charlotte NC 28216",
    "addr:housenumber":"3224",
    "addr:postcode":"28216",
    "addr:street":"Cricketeer Dr",
    "iso:country":"US",
    "sg:address":"3224 Cricketeer Dr",
    "sg:city":"Charlotte",
    "sg:classifiers":[
        {
            "category":"Professional",
            "subcategory":"Management & Consulting",
            "type":"Services"
        }
    ],
    "sg:phone":"+1   ",
    "sg:postcode":"28216",
    "sg:province":"NC",
    "sg:tags":[
        "marketing",
        "consultant"
    ],
    "wof:name":"Little & Associates Marketing",
    "wof:placetype":"venue"
},
  "geometry": {"coordinates":[-80.86395899999999,35.279246],"type":"Point"}
}