{
  "type": "Feature",
  "properties": {
    "addr:full":"915 Magnolia Ave Charlotte NC 28203",
    "addr:housenumber":"915",
    "addr:postcode":"28203",
    "addr:street":"Magnolia Ave",
    "iso:country":"US",
    "sg:address":"915 Magnolia Ave",
    "sg:city":"Charlotte",
    "sg:classifiers":[
        {
            "category":"Wholesale",
            "subcategory":"Non-durable Goods",
            "type":"Manufacturing & Wholesale Goods"
        }
    ],
    "sg:phone":"+1 704 344 1176",
    "sg:postcode":"28203",
    "sg:province":"NC",
    "sg:website":"www.stlicensed.com",
    "wof:name":"Slavic Treasures",
    "wof:placetype":"venue"
},
  "geometry": {"coordinates":[-80.850584,35.202839],"type":"Point"}
}