{
  "type": "Feature",
  "properties": {
    "addr:full":"2710 Chamber Dr Monroe NC 28110",
    "addr:housenumber":"2710",
    "addr:postcode":"28110",
    "addr:street":"Chamber Dr",
    "iso:country":"US",
    "sg:address":"2710 Chamber Dr",
    "sg:city":"Monroe",
    "sg:classifiers":[
        {
            "category":"Freight",
            "type":"Transportation"
        }
    ],
    "sg:phone":"+1 704 238 8224",
    "sg:postcode":"28110",
    "sg:province":"NC",
    "wof:name":"JRC Transportation",
    "wof:placetype":"venue"
},
  "geometry": {"coordinates":[-80.617893,35.052691],"type":"Point"}
}