{
  "type": "Feature",
  "properties": {
    "iso:country":"US",
    "sg:address":"2738 State Hwy 62",
    "sg:city":"Blanch",
    "sg:classifiers":[
        {
            "category":"Education",
            "subcategory":"Special Training",
            "type":"Public Place"
        }
    ],
    "sg:phone":"+1   ",
    "sg:postcode":"27212",
    "sg:province":"NC",
    "wof:name":"Yanceyville Brotherhood",
    "wof:placetype":"venue"
},
  "geometry": {"coordinates":[-79.27726,36.447305],"type":"Point"}
}