{
  "type": "Feature",
  "properties": {
    "iso:country":"US",
    "sg:address":"2913 Country Club Rd",
    "sg:city":"Jacksonville",
    "sg:classifiers":[
        {
            "category":"Retail",
            "subcategory":"Auto Repair",
            "type":"Services"
        }
    ],
    "sg:phone":"+1 910 938 2500",
    "sg:postcode":"28546",
    "sg:province":"NC",
    "sg:tags":[
        "repairing",
        "automobile"
    ],
    "wof:name":"B J's Garage",
    "wof:placetype":"venue"
},
  "geometry": {"coordinates":[-77.360497,34.783727],"type":"Point"}
}