{
  "type": "Feature",
  "properties": {
    "iso:country":"US",
    "sg:address":"4224 Six Forks Rd",
    "sg:city":"Raleigh",
    "sg:classifiers":[
        {
            "category":"Utilities",
            "subcategory":"Telephone",
            "type":"Services"
        },
        {
            "category":"Shopping",
            "type":"Retail Goods"
        },
        {
            "category":"Wholesale",
            "subcategory":"Electrical",
            "type":"Manufacturing & Wholesale Goods"
        }
    ],
    "sg:phone":"+1 919 784 0021",
    "sg:postcode":"27609",
    "sg:province":"NC",
    "sg:tags":[
        "equipment",
        "company",
        "electronic",
        "supply"
    ],
    "wof:name":"Longleaf Communications LLC",
    "wof:placetype":"venue"
},
  "geometry": {"coordinates":[-78.641279,35.837796],"type":"Point"}
}