{
  "type": "Feature",
  "properties": {
    "addr:full":"618 Tobacco Rd Fairmont NC 28340",
    "addr:housenumber":"618",
    "addr:postcode":"28340",
    "addr:street":"Tobacco Rd",
    "iso:country":"US",
    "sg:address":"618 Tobacco Rd",
    "sg:city":"Fairmont",
    "sg:classifiers":[
        {
            "category":"Building & Trades",
            "subcategory":"Construction",
            "type":"Services"
        }
    ],
    "sg:phone":"+1 910 628 7605",
    "sg:postcode":"28340",
    "sg:province":"NC",
    "wof:name":"Callahan Builders Inc",
    "wof:placetype":"venue"
},
  "geometry": {"coordinates":[-79.06869,34.460491],"type":"Point"}
}