{
  "type": "Feature",
  "properties": {
    "addr:full":"172 Otis Johnson Rd Pittsboro NC 27312",
    "addr:housenumber":"172",
    "addr:postcode":"27312",
    "addr:street":"Otis Johnson Rd",
    "iso:country":"US",
    "sg:address":"172 Otis Johnson Rd",
    "sg:city":"Pittsboro",
    "sg:classifiers":[
        {
            "category":"Wholesale",
            "subcategory":"Groceries",
            "type":"Manufacturing & Wholesale Goods"
        }
    ],
    "sg:phone":"+1 919 545 9401",
    "sg:postcode":"27312",
    "sg:province":"NC",
    "sg:tags":[
        "food",
        "product"
    ],
    "wof:name":"Rolls Enterprises Inc",
    "wof:placetype":"venue"
},
  "geometry": {"coordinates":[-79.28957800000001,35.837189],"type":"Point"}
}