{
  "type": "Feature",
  "properties": {
    "iso:country":"US",
    "sg:address":"3041 Zebulon Rd",
    "sg:city":"Rocky Mount",
    "sg:classifiers":[
        {
            "category":"Insurance",
            "subcategory":"Insurance Agent",
            "type":"Services"
        }
    ],
    "sg:phone":"+1 252 451 2600",
    "sg:postcode":"27804",
    "sg:province":"NC",
    "sg:tags":[
        "adjuster"
    ],
    "wof:name":"Gmac Insurance",
    "wof:placetype":"venue"
},
  "geometry": {"coordinates":[-77.83595200000001,35.965299],"type":"Point"}
}