{
  "type": "Feature",
  "properties": {
    "addr:full":"12517 Twisted Hickory Rd Bladenboro NC 28320",
    "addr:housenumber":"12517",
    "addr:postcode":"28320",
    "addr:street":"Twisted Hickory Rd",
    "iso:country":"US",
    "sg:address":"12517 Twisted Hickory Rd",
    "sg:city":"Bladenboro",
    "sg:classifiers":[
        {
            "category":"Professional",
            "subcategory":"Business Services",
            "type":"Services"
        }
    ],
    "sg:phone":"+1   ",
    "sg:postcode":"28320",
    "sg:province":"NC",
    "wof:name":"Helms Business Service",
    "wof:placetype":"venue"
},
  "geometry": {"coordinates":[-78.71168400000001,34.528068],"type":"Point"}
}