{
  "type": "Feature",
  "properties": {
    "iso:country":"US",
    "sg:address":"7315 Captain Neal Ln",
    "sg:city":"Charlotte",
    "sg:classifiers":[
        {
            "category":"Freight",
            "type":"Transportation"
        }
    ],
    "sg:phone":"+1 704 366 6200",
    "sg:postcode":"28273",
    "sg:province":"NC",
    "sg:tags":[
        "mover"
    ],
    "sg:website":"www.easymovers.com",
    "wof:name":"Easy Movers Inc",
    "wof:placetype":"venue"
},
  "geometry": {"coordinates":[-80.93007299999999,35.157261],"type":"Point"}
}