{
  "type": "Feature",
  "properties": {
    "addr:full":"2003 Chapel Hill Rd Durham NC 27707",
    "addr:housenumber":"2003",
    "addr:postcode":"27707",
    "addr:street":"Chapel Hill Rd",
    "iso:country":"US",
    "sg:address":"2003 Chapel Hill Rd",
    "sg:city":"Durham",
    "sg:classifiers":[
        {
            "category":"Professional",
            "subcategory":"Lawyer & Legal Services",
            "type":"Services"
        }
    ],
    "sg:phone":"+1   ",
    "sg:postcode":"27707",
    "sg:province":"NC",
    "wof:name":"Michael E Mauney Atty",
    "wof:placetype":"venue"
},
  "geometry": {"coordinates":[-78.926591,35.987212],"type":"Point"}
}