{
  "type": "Feature",
  "properties": {
    "addr:full":"116 Morgan Rd Weaverville NC 28787",
    "addr:housenumber":"116",
    "addr:postcode":"28787",
    "addr:street":"Morgan Rd",
    "iso:country":"US",
    "sg:address":"116 Morgan Rd",
    "sg:city":"Weaverville",
    "sg:classifiers":[
        {
            "category":"Building & Trades",
            "subcategory":"Plumbing",
            "type":"Services"
        }
    ],
    "sg:phone":"+1 828 645 7463",
    "sg:postcode":"28787",
    "sg:province":"NC",
    "sg:tags":[
        "contractor"
    ],
    "wof:name":"Maxwell Heating & Cooling",
    "wof:placetype":"venue"
},
  "geometry": {"coordinates":[-82.502273,35.767346],"type":"Point"}
}