{
  "type": "Feature",
  "properties": {
    "iso:country":"US",
    "sg:address":"202 Bob Cat Spur Ln",
    "sg:city":"Hendersonville",
    "sg:classifiers":[
        {
            "category":"Personal",
            "subcategory":"Beauty Salon",
            "type":"Services"
        }
    ],
    "sg:phone":"+1   ",
    "sg:postcode":"28792",
    "sg:province":"NC",
    "sg:tags":[
        "shop"
    ],
    "wof:name":"Chadwicks Full Service Salon",
    "wof:placetype":"venue"
},
  "geometry": {"coordinates":[-82.274709,35.384005],"type":"Point"}
}