{
  "type": "Feature",
  "properties": {
    "addr:full":"5521 Farmbrook Dr Charlotte NC 28210",
    "addr:housenumber":"5521",
    "addr:postcode":"28210",
    "addr:street":"Farmbrook Dr",
    "iso:country":"US",
    "sg:address":"5521 Farmbrook Dr",
    "sg:city":"Charlotte",
    "sg:classifiers":[
        {
            "category":"Building & Trades",
            "subcategory":"Cleaning & Sanitation",
            "type":"Services"
        }
    ],
    "sg:phone":"+1 704 529 1145",
    "sg:postcode":"28210",
    "sg:province":"NC",
    "sg:tags":[
        "downspout",
        "gutter"
    ],
    "wof:name":"A-1 Gutter Cleaning",
    "wof:placetype":"venue"
},
  "geometry": {"coordinates":[-80.86508499999999,35.155444],"type":"Point"}
}