{
  "type": "Feature",
  "properties": {
    "addr:full":"100 Industrial Park Rd Mountain Home NC 28734",
    "addr:housenumber":"100",
    "addr:postcode":"28734",
    "addr:street":"Industrial Park Rd",
    "iso:country":"US",
    "sg:address":"100 Industrial Park Rd",
    "sg:city":"Mountain Home",
    "sg:classifiers":[
        {
            "category":"Manufacturing",
            "subcategory":"Glass & Minerals",
            "type":"Manufacturing & Wholesale Goods"
        }
    ],
    "sg:phone":"+1 828 693 6596",
    "sg:postcode":"28734",
    "sg:province":"NC",
    "sg:tags":[
        "product",
        "ceramic"
    ],
    "wof:name":"Ceratip Cutting Tool Svc",
    "wof:placetype":"venue"
},
  "geometry": {"coordinates":[-83.434703,35.163387],"type":"Point"}
}