{
  "type": "Feature",
  "properties": {
    "iso:country":"US",
    "sg:address":"1007 Johnson St",
    "sg:city":"High Point",
    "sg:classifiers":[
        {
            "category":"Manufacturing",
            "subcategory":"Textiles",
            "type":"Manufacturing & Wholesale Goods"
        }
    ],
    "sg:phone":"+1 336 472 9178",
    "sg:postcode":"27262",
    "sg:province":"NC",
    "sg:tags":[
        "athletic",
        "sock",
        "manufacturer"
    ],
    "wof:name":"Sockware Manufacturing Co",
    "wof:placetype":"venue"
},
  "geometry": {"coordinates":[-80.014399,35.97026],"type":"Point"}
}