{
  "type": "Feature",
  "properties": {
    "iso:country":"US",
    "sg:address":"312 Pritchard St",
    "sg:city":"Elizabeth City",
    "sg:classifiers":[
        {
            "category":"Government",
            "subcategory":"Office",
            "type":"Public Place"
        }
    ],
    "sg:phone":"+1 252 335 4306",
    "sg:postcode":"27909",
    "sg:province":"NC",
    "sg:tags":[
        "city"
    ],
    "sg:website":"www.ecpps.k12.nc.us",
    "wof:name":"Elizabeth City Pasquotank",
    "wof:placetype":"venue"
},
  "geometry": {"coordinates":[-76.237163,36.298569],"type":"Point"}
}