{
  "type": "Feature",
  "properties": {
    "addr:full":"213 W Littleton Rd Roanoke Rapids NC 27870",
    "addr:housenumber":"213",
    "addr:postcode":"27870",
    "addr:street":"W Littleton Rd",
    "iso:country":"US",
    "sg:address":"213 W Littleton Rd",
    "sg:city":"Roanoke Rapids",
    "sg:classifiers":[
        {
            "category":"Organizations",
            "subcategory":"Religious Organization",
            "type":"Services"
        }
    ],
    "sg:phone":"+1   ",
    "sg:postcode":"27870",
    "sg:province":"NC",
    "wof:name":"South Rsmary Untd Mthdst Chrch",
    "wof:placetype":"venue"
},
  "geometry": {"coordinates":[-77.671183,36.442432],"type":"Point"}
}