{
  "type": "Feature",
  "properties": {
    "addr:full":"113 Kingold Blvd Snow Hill NC 28580",
    "addr:housenumber":"113",
    "addr:postcode":"28580",
    "addr:street":"Kingold Blvd",
    "iso:country":"US",
    "sg:address":"113 Kingold Blvd",
    "sg:city":"Snow Hill",
    "sg:classifiers":[
        {
            "category":"Personal",
            "subcategory":"Barber",
            "type":"Services"
        }
    ],
    "sg:phone":"+1 252 747 2942",
    "sg:postcode":"28580",
    "sg:province":"NC",
    "sg:tags":[
        "shop"
    ],
    "wof:name":"Jeanette's Barber Shop",
    "wof:placetype":"venue"
},
  "geometry": {"coordinates":[-77.68075399999999,35.450213],"type":"Point"}
}