{
  "type": "Feature",
  "properties": {
    "addr:full":"150 Weaverville Hwy Asheville NC 28804",
    "addr:housenumber":"150",
    "addr:postcode":"28804",
    "addr:street":"Weaverville Hwy",
    "iso:country":"US",
    "sg:address":"150 Weaverville Hwy",
    "sg:city":"Asheville",
    "sg:classifiers":[
        {
            "category":"Restaurant",
            "type":"Food & Drink"
        }
    ],
    "sg:phone":"+1 828 645 4517",
    "sg:postcode":"28804",
    "sg:province":"NC",
    "sg:tags":[
        "eating"
    ],
    "wof:name":"Ilenes Cafe",
    "wof:placetype":"venue"
},
  "geometry": {"coordinates":[-82.58107699999999,35.647756],"type":"Point"}
}