{
  "type": "Feature",
  "properties": {
    "addr:full":"301 N Mcdowell St Charlotte NC 28204",
    "addr:housenumber":"301",
    "addr:postcode":"28204",
    "addr:street":"N Mcdowell St",
    "iso:country":"US",
    "sg:address":"301 N Mcdowell St",
    "sg:city":"Charlotte",
    "sg:classifiers":[
        {
            "category":"Professional",
            "subcategory":"Lawyer & Legal Services",
            "type":"Services"
        }
    ],
    "sg:phone":"+1 704 372 2770",
    "sg:postcode":"28204",
    "sg:province":"NC",
    "sg:tags":[
        "attorney"
    ],
    "wof:name":"Carr, Michael P",
    "wof:placetype":"venue"
},
  "geometry": {"coordinates":[-80.832787,35.22192],"type":"Point"}
}