{
  "type": "Feature",
  "properties": {
    "iso:country":"US",
    "sg:address":"1896 Goat Rd",
    "sg:city":"Catawba",
    "sg:classifiers":[
        {
            "category":"Professional",
            "subcategory":"Business Services",
            "type":"Services"
        }
    ],
    "sg:phone":"+1   ",
    "sg:postcode":"28609",
    "sg:province":"NC",
    "wof:name":"Lpd Sales LLC",
    "wof:placetype":"venue"
},
  "geometry": {"coordinates":[-80.992046,35.690569],"type":"Point"}
}