{
  "type": "Feature",
  "properties": {
    "addr:full":"6635 Ramsey St Fayetteville NC 28311",
    "addr:housenumber":"6635",
    "addr:postcode":"28311",
    "addr:street":"Ramsey St",
    "iso:country":"US",
    "sg:address":"6635 Ramsey St",
    "sg:city":"Fayetteville",
    "sg:classifiers":[
        {
            "category":"Professional",
            "subcategory":"Management & Consulting",
            "type":"Services"
        }
    ],
    "sg:phone":"+1   ",
    "sg:postcode":"28311",
    "sg:province":"NC",
    "sg:tags":[
        "development",
        "business"
    ],
    "wof:name":"818 Group Inc",
    "wof:placetype":"venue"
},
  "geometry": {"coordinates":[-78.859554,35.173935],"type":"Point"}
}