{
  "type": "Feature",
  "properties": {
    "addr:full":"2915 Providence Rd Charlotte NC 28211",
    "addr:housenumber":"2915",
    "addr:postcode":"28211",
    "addr:street":"Providence Rd",
    "iso:country":"US",
    "sg:address":"2915 Providence Rd",
    "sg:city":"Charlotte",
    "sg:classifiers":[
        {
            "category":"Professional",
            "type":"Services"
        }
    ],
    "sg:phone":"+1 704 366 1226",
    "sg:postcode":"28211",
    "sg:province":"NC",
    "sg:tags":[
        "establishment"
    ],
    "wof:name":"B Mountjoy Sorkin Dcgn",
    "wof:placetype":"venue"
},
  "geometry": {"coordinates":[-80.80584,35.169411],"type":"Point"}
}