{
  "type": "Feature",
  "properties": {
    "iso:country":"US",
    "sg:address":"1234 Gillespie St",
    "sg:city":"Fayetteville",
    "sg:classifiers":[
        {
            "category":"Shopping",
            "subcategory":"Pharmacy",
            "type":"Retail Goods"
        }
    ],
    "sg:phone":"+1 910 323 9559",
    "sg:postcode":"28306",
    "sg:province":"NC",
    "sg:tags":[
        "aid",
        "first",
        "supply"
    ],
    "wof:name":"Mobile Med",
    "wof:placetype":"venue"
},
  "geometry": {"coordinates":[-78.885661,35.0336],"type":"Point"}
}