{
  "type": "Feature",
  "properties": {
    "addr:full":"1212 Kenilworth Ave Charlotte NC 28204",
    "addr:housenumber":"1212",
    "addr:postcode":"28204",
    "addr:street":"Kenilworth Ave",
    "iso:country":"US",
    "sg:address":"1212 Kenilworth Ave",
    "sg:city":"Charlotte",
    "sg:classifiers":[
        {
            "category":"Science Facility",
            "type":"Public Place"
        }
    ],
    "sg:phone":"+1 704 953 6421",
    "sg:postcode":"28204",
    "sg:province":"NC",
    "sg:tags":[
        "development",
        "laboratories-research"
    ],
    "wof:name":"Carolina Yachting Concepts",
    "wof:placetype":"venue"
},
  "geometry": {"coordinates":[-80.840424,35.206466],"type":"Point"}
}