{
  "type": "Feature",
  "properties": {
    "iso:country":"US",
    "sg:address":"9523 Charolais Ln",
    "sg:city":"Charlotte",
    "sg:classifiers":[
        {
            "category":"Professional",
            "subcategory":"Management & Consulting",
            "type":"Services"
        }
    ],
    "sg:phone":"+1   ",
    "sg:postcode":"28213",
    "sg:province":"NC",
    "wof:name":"Maxima II",
    "wof:placetype":"venue"
},
  "geometry": {"coordinates":[-80.720371,35.292012],"type":"Point"}
}