{
  "type": "Feature",
  "properties": {
    "addr:full":"4064 Lost Creek Ct Hickory NC 28602",
    "addr:housenumber":"4064",
    "addr:postcode":"28602",
    "addr:street":"Lost Creek Ct",
    "iso:country":"US",
    "sg:address":"4064 Lost Creek Ct",
    "sg:city":"Hickory",
    "sg:classifiers":[
        {
            "category":"Restaurant",
            "type":"Food & Drink"
        }
    ],
    "sg:phone":"+1 828 294 1461",
    "sg:postcode":"28602",
    "sg:province":"NC",
    "sg:tags":[
        "eating"
    ],
    "wof:name":"Steel Horses Pizza Grill & Bar",
    "wof:placetype":"venue"
},
  "geometry": {"coordinates":[-81.325687,35.667685],"type":"Point"}
}