{
  "type": "Feature",
  "properties": {
    "iso:country":"US",
    "sg:address":"304 W Union St",
    "sg:city":"Morganton",
    "sg:classifiers":[
        {
            "category":"Government",
            "subcategory":"Jail",
            "type":"Public Place"
        }
    ],
    "sg:phone":"+1 828 438 6004",
    "sg:postcode":"28655",
    "sg:province":"NC",
    "sg:tags":[
        "probation",
        "parole",
        "adult"
    ],
    "wof:name":"Judicial District 25a",
    "wof:placetype":"venue"
},
  "geometry": {"coordinates":[-81.690512,35.741984],"type":"Point"}
}