{
  "type": "Feature",
  "properties": {
    "addr:full":"731 Keck Rd Haw River NC 27258",
    "addr:housenumber":"731",
    "addr:postcode":"27258",
    "addr:street":"Keck Rd",
    "iso:country":"US",
    "sg:address":"731 Keck Rd",
    "sg:city":"Haw River",
    "sg:classifiers":[
        {
            "category":"Organizations",
            "subcategory":"Community Association",
            "type":"Services"
        }
    ],
    "sg:phone":"+1   ",
    "sg:postcode":"27258",
    "sg:province":"NC",
    "wof:name":"American Legion Post 427 Dani",
    "wof:placetype":"venue"
},
  "geometry": {"coordinates":[-79.35527999999999,36.10736],"type":"Point"}
}