{
  "type": "Feature",
  "properties": {
    "addr:full":"101 Queens Rd Charlotte NC 28204",
    "addr:housenumber":"101",
    "addr:postcode":"28204",
    "addr:street":"Queens Rd",
    "iso:country":"US",
    "sg:address":"101 Queens Rd",
    "sg:city":"Charlotte",
    "sg:classifiers":[
        {
            "category":"Banks & Credit Unions",
            "subcategory":"Bank",
            "type":"Services"
        }
    ],
    "sg:phone":"+1 704 954 2005",
    "sg:postcode":"28204",
    "sg:province":"NC",
    "wof:name":"B B & T",
    "wof:placetype":"venue"
},
  "geometry": {"coordinates":[-80.82761600000001,35.210843],"type":"Point"}
}