{
  "type": "Feature",
  "properties": {
    "addr:full":"103 N Main St Colerain NC 27924",
    "addr:housenumber":"103",
    "addr:postcode":"27924",
    "addr:street":"N Main St",
    "iso:country":"US",
    "sg:address":"103 N Main St",
    "sg:city":"Colerain",
    "sg:classifiers":[
        {
            "category":"Food & Beverages",
            "subcategory":"Groceries & Convenience Stores",
            "type":"Retail Goods"
        }
    ],
    "sg:phone":"+1 252 356 4546",
    "sg:postcode":"27924",
    "sg:province":"NC",
    "wof:name":"Country Market Inc",
    "wof:placetype":"venue"
},
  "geometry": {"coordinates":[-76.76776099999999,36.20246],"type":"Point"}
}