{
  "type": "Feature",
  "properties": {
    "iso:country":"US",
    "sg:address":"230 E Independence Blvd",
    "sg:city":"Charlotte",
    "sg:phone":"+1 919 877 1288",
    "sg:postcode":"28204",
    "sg:province":"NC",
    "wof:name":"Emsi Oneill Enterprises",
    "wof:placetype":"venue"
},
  "geometry": {"coordinates":[-80.82032,35.218739],"type":"Point"}
}