{
  "type": "Feature",
  "properties": {
    "addr:full":"209 Burbank Rd Wilmington NC 28412",
    "addr:housenumber":"209",
    "addr:postcode":"28412",
    "addr:street":"Burbank Rd",
    "iso:country":"US",
    "sg:address":"209 Burbank Rd",
    "sg:city":"Wilmington",
    "sg:classifiers":[
        {
            "category":"Retail",
            "subcategory":"Repair Shop",
            "type":"Services"
        }
    ],
    "sg:phone":"+1 910 792 0637",
    "sg:postcode":"28412",
    "sg:province":"NC",
    "sg:tags":[
        "lock",
        "locksmith"
    ],
    "wof:name":"Cape Fear Lock and Key",
    "wof:placetype":"venue"
},
  "geometry": {"coordinates":[-77.903002,34.109509],"type":"Point"}
}