{
  "type": "Feature",
  "properties": {
    "addr:full":"3263 S Church St Burlington NC 27215",
    "addr:housenumber":"3263",
    "addr:postcode":"27215",
    "addr:street":"S Church St",
    "iso:country":"US",
    "sg:address":"3263 S Church St",
    "sg:city":"Burlington",
    "sg:classifiers":[
        {
            "category":"Restaurant",
            "type":"Food & Drink"
        }
    ],
    "sg:phone":"+1 336 584 4197",
    "sg:postcode":"27215",
    "sg:province":"NC",
    "wof:name":"Kachi Japanese Steakhouse & Sushi",
    "wof:placetype":"venue"
},
  "geometry": {"coordinates":[-79.503069,36.080937],"type":"Point"}
}