{
  "type": "Feature",
  "properties": {
    "iso:country":"US",
    "sg:address":"4106 Puetts Chapel Rd",
    "sg:city":"Dallas",
    "sg:classifiers":[
        {
            "category":"Building & Trades",
            "subcategory":"Construction",
            "type":"Services"
        }
    ],
    "sg:phone":"+1 704 922 3588",
    "sg:postcode":"28034",
    "sg:province":"NC",
    "sg:tags":[
        "house"
    ],
    "wof:name":"Dream Builders",
    "wof:placetype":"venue"
},
  "geometry": {"coordinates":[-81.222956,35.38118],"type":"Point"}
}