{
  "type": "Feature",
  "properties": {
    "addr:full":"308 Crutchfield St Durham NC 27704",
    "addr:housenumber":"308",
    "addr:postcode":"27704",
    "addr:street":"Crutchfield St",
    "iso:country":"US",
    "sg:address":"308 Crutchfield St",
    "sg:city":"Durham",
    "sg:classifiers":[
        {
            "category":"Health Services",
            "subcategory":"Doctor",
            "type":"Services"
        }
    ],
    "sg:phone":"+1 919 479 5757",
    "sg:postcode":"27704",
    "sg:province":"NC",
    "sg:tags":[
        "dentist"
    ],
    "wof:name":"E Zambrana Jr DDS",
    "wof:placetype":"venue"
},
  "geometry": {"coordinates":[-78.903966,36.038964],"type":"Point"}
}