{
  "type": "Feature",
  "properties": {
    "iso:country":"US",
    "sg:address":"9 Bent Twig Dr",
    "sg:city":"Old Fort",
    "sg:classifiers":[
        {
            "category":"Building & Trades",
            "subcategory":"Construction",
            "type":"Services"
        }
    ],
    "sg:phone":"+1 828 668 4800",
    "sg:postcode":"28762",
    "sg:province":"NC",
    "sg:tags":[
        "downspouts",
        "gutter"
    ],
    "wof:name":"James Norton Seemless Gutter",
    "wof:placetype":"venue"
},
  "geometry": {"coordinates":[-82.146494,35.663632],"type":"Point"}
}