{
  "type": "Feature",
  "properties": {
    "iso:country":"US",
    "sg:address":"92 George Dr",
    "sg:city":"Whiteville",
    "sg:classifiers":[
        {
            "category":"Professional",
            "type":"Services"
        }
    ],
    "sg:phone":"+1 910 648 6332",
    "sg:postcode":"28472",
    "sg:province":"NC",
    "wof:name":"Ann Pittman",
    "wof:placetype":"venue"
},
  "geometry": {"coordinates":[-78.711083,34.355272],"type":"Point"}
}