{
  "type": "Feature",
  "properties": {
    "iso:country":"US",
    "sg:address":"200 Washington St",
    "sg:city":"Seaboard",
    "sg:classifiers":[
        {
            "category":"Freight",
            "type":"Transportation"
        }
    ],
    "sg:phone":"+1 252 589 3781",
    "sg:postcode":"27876",
    "sg:province":"NC",
    "sg:tags":[
        "local",
        "trucking"
    ],
    "wof:name":"Anderson M Davis Trucking Inc",
    "wof:placetype":"venue"
},
  "geometry": {"coordinates":[-77.44508399999999,36.48827],"type":"Point"}
}