{
  "type": "Feature",
  "properties": {
    "addr:full":"139 W Main St Everetts NC 27825",
    "addr:housenumber":"139",
    "addr:postcode":"27825",
    "addr:street":"W Main St",
    "iso:country":"US",
    "sg:address":"139 W Main St",
    "sg:city":"Everetts",
    "sg:classifiers":[
        {
            "category":"Professional",
            "type":"Services"
        }
    ],
    "sg:phone":"+1 252 792 7499",
    "sg:postcode":"27825",
    "sg:province":"NC",
    "sg:tags":[
        "establishment"
    ],
    "wof:name":"New Life Women's Leadership",
    "wof:placetype":"venue"
},
  "geometry": {"coordinates":[-77.171879,35.834099],"type":"Point"}
}