{
  "type": "Feature",
  "properties": {
    "addr:full":"6204 Lydden Rd Wilmington NC 28409",
    "addr:housenumber":"6204",
    "addr:postcode":"28409",
    "addr:street":"Lydden Rd",
    "iso:country":"US",
    "sg:address":"6204 Lydden Rd",
    "sg:city":"Wilmington",
    "sg:classifiers":[
        {
            "category":"Building & Trades",
            "subcategory":"Construction",
            "type":"Services"
        }
    ],
    "sg:phone":"+1 910 794 4168",
    "sg:postcode":"28409",
    "sg:province":"NC",
    "sg:tags":[
        "house",
        "nonresidential"
    ],
    "wof:name":"Risley Padula Construction",
    "wof:placetype":"venue"
},
  "geometry": {"coordinates":[-77.887563,34.126264],"type":"Point"}
}