{
  "type": "Feature",
  "properties": {
    "iso:country":"US",
    "sg:address":"67 Penny Tew Mill Rd",
    "sg:city":"Roseboro",
    "sg:classifiers":[
        {
            "category":"Shopping",
            "subcategory":"Hobbies, Toys, & Games",
            "type":"Retail Goods"
        }
    ],
    "sg:phone":"+1 910 564 4618",
    "sg:postcode":"28382",
    "sg:province":"NC",
    "wof:name":"Royal Gladys Ceramics",
    "wof:placetype":"venue"
},
  "geometry": {"coordinates":[-78.479085,35.106261],"type":"Point"}
}