{
  "type": "Feature",
  "properties": {
    "addr:full":"2102 Cambridge Beltway Dr Charlotte NC 28273",
    "addr:housenumber":"2102",
    "addr:postcode":"28273",
    "addr:street":"Cambridge Beltway Dr",
    "iso:country":"US",
    "sg:address":"2102 Cambridge Beltway Dr",
    "sg:city":"Charlotte",
    "sg:classifiers":[
        {
            "category":"Real Estate",
            "subcategory":"Developer",
            "type":"Services"
        },
        {
            "category":"Real Estate",
            "subcategory":"Real Estate Agent",
            "type":"Services"
        }
    ],
    "sg:phone":"+1 704 583 2115",
    "sg:postcode":"28273",
    "sg:province":"NC",
    "wof:name":"Cambridge Partners LLC",
    "wof:placetype":"venue"
},
  "geometry": {"coordinates":[-80.93589299999999,35.136907],"type":"Point"}
}