{
  "type": "Feature",
  "properties": {
    "iso:country":"US",
    "sg:address":"360 Milling Rd",
    "sg:city":"Mocksville",
    "sg:classifiers":[
        {
            "category":"Shopping",
            "subcategory":"Hobbies, Toys, & Games",
            "type":"Retail Goods"
        }
    ],
    "sg:phone":"+1 336 751 7655",
    "sg:postcode":"27028",
    "sg:province":"NC",
    "sg:tags":[
        "equipment",
        "ceramic",
        "supply"
    ],
    "wof:name":"Mad Ceramics Jr's Slip",
    "wof:placetype":"venue"
},
  "geometry": {"coordinates":[-80.54141199999999,35.90327],"type":"Point"}
}