{
  "type": "Feature",
  "properties": {
    "iso:country":"US",
    "sg:address":"5427 Watering Pond Rd",
    "sg:city":"Pink Hill",
    "sg:classifiers":[
        {
            "category":"Shopping",
            "subcategory":"Luggage & Leather Goods",
            "type":"Retail Goods"
        }
    ],
    "sg:phone":"+1 910 298 6240",
    "sg:postcode":"28572",
    "sg:province":"NC",
    "wof:name":"Fast Lane Leathers",
    "wof:placetype":"venue"
},
  "geometry": {"coordinates":[-77.68445699999999,35.049926],"type":"Point"}
}