{
  "type": "Feature",
  "properties": {
    "addr:full":"19901 W Catawba Ave Cornelius NC 28031",
    "addr:housenumber":"19901",
    "addr:postcode":"28031",
    "addr:street":"W Catawba Ave",
    "iso:country":"US",
    "sg:address":"19901 W Catawba Ave",
    "sg:city":"Cornelius",
    "sg:classifiers":[
        {
            "category":"Health Services",
            "subcategory":"Dentist",
            "type":"Services"
        }
    ],
    "sg:phone":"+1 704 896 9798",
    "sg:postcode":"28031",
    "sg:province":"NC",
    "sg:tags":[
        "laboratories-medical",
        "dental",
        "x-ray"
    ],
    "wof:name":"Lake Norman 3-D Imaging",
    "wof:placetype":"venue"
},
  "geometry": {"coordinates":[-80.884612,35.48164],"type":"Point"}
}