{
  "type": "Feature",
  "properties": {
    "addr:full":"722 S Hughes St Apex NC 27502",
    "addr:housenumber":"722",
    "addr:postcode":"27502",
    "addr:street":"S Hughes St",
    "iso:country":"US",
    "sg:address":"722 S Hughes St",
    "sg:city":"Apex",
    "sg:classifiers":[
        {
            "category":"Building & Trades",
            "subcategory":"Cleaning & Sanitation",
            "type":"Services"
        }
    ],
    "sg:phone":"+1 919 387 9800",
    "sg:postcode":"27502",
    "sg:province":"NC",
    "sg:tags":[
        "home",
        "janitor"
    ],
    "wof:name":"Klean For You",
    "wof:placetype":"venue"
},
  "geometry": {"coordinates":[-78.850864,35.721537],"type":"Point"}
}