{
  "type": "Feature",
  "properties": {
    "iso:country":"US",
    "sg:address":"626 Dogwood Rd",
    "sg:city":"Statesville",
    "sg:classifiers":[
        {
            "category":"Communications",
            "subcategory":"Film & Video Production",
            "type":"Services"
        }
    ],
    "sg:phone":"+1 704 883 7556",
    "sg:postcode":"28677",
    "sg:province":"NC",
    "sg:tags":[
        "motion",
        "taping"
    ],
    "wof:name":"Stonemark Production & Posts",
    "wof:placetype":"venue"
},
  "geometry": {"coordinates":[-80.874589,35.803569],"type":"Point"}
}