{
  "type": "Feature",
  "properties": {
    "addr:full":"3363 US Hwy 301 Wilson NC 27893",
    "addr:housenumber":"3363",
    "addr:postcode":"27893",
    "addr:street":"Us Hwy 301",
    "iso:country":"US",
    "sg:address":"3363 US Hwy 301",
    "sg:city":"Wilson",
    "sg:classifiers":[
        {
            "category":"Manufacturing",
            "subcategory":"Apparel",
            "type":"Manufacturing & Wholesale Goods"
        }
    ],
    "sg:phone":"+1 252 237 6101",
    "sg:postcode":"27893",
    "sg:province":"NC",
    "sg:tags":[
        "jean"
    ],
    "wof:name":"VF Jeanswear",
    "wof:placetype":"venue"
},
  "geometry": {"coordinates":[-77.87324,35.743151],"type":"Point"}
}