{
  "type": "Feature",
  "properties": {
    "addr:full":"13777 Ballantyne Corporate Pl Charlotte NC 28277",
    "addr:housenumber":"13777",
    "addr:postcode":"28277",
    "addr:street":"Ballantyne Corporate Pl",
    "iso:country":"US",
    "sg:address":"13777 Ballantyne Corporate Pl",
    "sg:city":"Charlotte",
    "sg:classifiers":[
        {
            "category":"Professional",
            "subcategory":"Computer Services",
            "type":"Services"
        }
    ],
    "sg:phone":"+1 704 540 5800",
    "sg:postcode":"28277",
    "sg:province":"NC",
    "sg:tags":[
        "consultant",
        "designer"
    ],
    "wof:name":"Internetwork Engineering",
    "wof:placetype":"venue"
},
  "geometry": {"coordinates":[-80.852464,35.061783],"type":"Point"}
}