{
  "type": "Feature",
  "properties": {
    "addr:full":"2550 W Tyvola Rd Charlotte NC 28217",
    "addr:housenumber":"2550",
    "addr:postcode":"28217",
    "addr:street":"W Tyvola Rd",
    "iso:country":"US",
    "sg:address":"2550 W Tyvola Rd",
    "sg:city":"Charlotte",
    "sg:classifiers":[
        {
            "category":"Utilities",
            "subcategory":"Mobile Phone",
            "type":"Services"
        },
        {
            "category":"Utilities",
            "subcategory":"Telephone",
            "type":"Services"
        }
    ],
    "sg:phone":"+1 704 423 5000",
    "sg:postcode":"28217",
    "sg:province":"NC",
    "sg:tags":[
        "communications",
        "radiotelephone",
        "cellular",
        "communication"
    ],
    "wof:name":"Cingular Wireless",
    "wof:placetype":"venue"
},
  "geometry": {"coordinates":[-80.920511,35.185165],"type":"Point"}
}