{
  "type": "Feature",
  "properties": {
    "iso:country":"US",
    "sg:address":"1129 Flowe Dr",
    "sg:city":"Matthews",
    "sg:classifiers":[
        {
            "category":"Real Estate",
            "subcategory":"Real Estate Agent",
            "type":"Services"
        }
    ],
    "sg:phone":"+1 704 821 1946",
    "sg:postcode":"28104",
    "sg:province":"NC",
    "wof:name":"Guion Family LP",
    "wof:placetype":"venue"
},
  "geometry": {"coordinates":[-80.68231900000001,35.092128],"type":"Point"}
}