{
  "type": "Feature",
  "properties": {
    "addr:full":"1321 Lake Cole Rd Midway Park NC 28544",
    "addr:housenumber":"1321",
    "addr:postcode":"28544",
    "addr:street":"Lake Cole Rd",
    "iso:country":"US",
    "sg:address":"1321 Lake Cole Rd",
    "sg:city":"Midway Park",
    "sg:classifiers":[
        {
            "category":"Building & Trades",
            "subcategory":"Landscaping Services",
            "type":"Services"
        }
    ],
    "sg:phone":"+1 910 353 0818",
    "sg:postcode":"28544",
    "sg:province":"NC",
    "sg:tags":[
        "tree"
    ],
    "wof:name":"Fletcher's Tree & Stump Rmvl",
    "wof:placetype":"venue"
},
  "geometry": {"coordinates":[-77.31368500000001,34.738384],"type":"Point"}
}