{
  "type": "Feature",
  "properties": {
    "addr:full":"7642 US Hwy 29 Browns Summit NC 27214",
    "addr:housenumber":"7642",
    "addr:postcode":"27214",
    "addr:street":"Us Hwy 29",
    "iso:country":"US",
    "sg:address":"7642 US Hwy 29",
    "sg:city":"Browns Summit",
    "sg:classifiers":[
        {
            "category":"Professional",
            "subcategory":"Testing Lab",
            "type":"Services"
        }
    ],
    "sg:phone":"+1 336 656 9944",
    "sg:postcode":"27214",
    "sg:province":"NC",
    "sg:tags":[
        "laboratory"
    ],
    "wof:name":"NDE Svc",
    "wof:placetype":"venue"
},
  "geometry": {"coordinates":[-79.67288600000001,36.235862],"type":"Point"}
}