{
  "type": "Feature",
  "properties": {
    "addr:full":"860 Old Leicester Hwy Asheville NC 28806",
    "addr:housenumber":"860",
    "addr:postcode":"28806",
    "addr:street":"Old Leicester Hwy",
    "iso:country":"US",
    "sg:address":"860 Old Leicester Hwy",
    "sg:city":"Asheville",
    "sg:classifiers":[
        {
            "category":"Autos & Motor Vehicles",
            "subcategory":"Auto Supplies",
            "type":"Retail Goods"
        }
    ],
    "sg:phone":"+1 828 683 3934",
    "sg:postcode":"28806",
    "sg:province":"NC",
    "sg:tags":[
        "tire"
    ],
    "wof:name":"Juno Tire & Svc Ctr Inc",
    "wof:placetype":"venue"
},
  "geometry": {"coordinates":[-82.644362,35.638933],"type":"Point"}
}