{
  "type": "Feature",
  "properties": {
    "iso:country":"US",
    "sg:address":"11213 New Britton Hwy E",
    "sg:city":"Whiteville",
    "sg:classifiers":[
        {
            "category":"Autos & Motor Vehicles",
            "subcategory":"Automobile Sales",
            "type":"Retail Goods"
        }
    ],
    "sg:phone":"+1 910 642 3437",
    "sg:postcode":"28472",
    "sg:province":"NC",
    "sg:tags":[
        "car",
        "dealer"
    ],
    "wof:name":"Ward's Used Cars",
    "wof:placetype":"venue"
},
  "geometry": {"coordinates":[-78.599954,34.183206],"type":"Point"}
}