{
  "type": "Feature",
  "properties": {
    "iso:country":"US",
    "sg:address":"6900 Kenbridge Dr",
    "sg:city":"Clemmons",
    "sg:classifiers":[
        {
            "category":"Professional",
            "subcategory":"Advertising",
            "type":"Services"
        }
    ],
    "sg:phone":"+1   ",
    "sg:postcode":"27012",
    "sg:province":"NC",
    "sg:website":"www.advinadv.com",
    "wof:name":"Adventures In Advertising",
    "wof:placetype":"venue"
},
  "geometry": {"coordinates":[-80.38975499999999,36.066524],"type":"Point"}
}