{
  "type": "Feature",
  "properties": {
    "addr:full":"618 W Center St Lexington NC 27292",
    "addr:housenumber":"618",
    "addr:postcode":"27292",
    "addr:street":"W Center St",
    "iso:country":"US",
    "sg:address":"618 W Center St",
    "sg:city":"Lexington",
    "sg:classifiers":[
        {
            "category":"Real Estate",
            "subcategory":"Surveying",
            "type":"Services"
        }
    ],
    "sg:phone":"+1 336 238 2398",
    "sg:postcode":"27292",
    "sg:province":"NC",
    "sg:tags":[
        "surveyor"
    ],
    "wof:name":"Everhart Surveying & Mapping",
    "wof:placetype":"venue"
},
  "geometry": {"coordinates":[-80.26195199999999,35.831006],"type":"Point"}
}