{
  "type": "Feature",
  "properties": {
    "iso:country":"US",
    "sg:address":"295 Juanita Ln",
    "sg:city":"New Bern",
    "sg:classifiers":[
        {
            "category":"Wholesale",
            "subcategory":"Auto Parts",
            "type":"Manufacturing & Wholesale Goods"
        }
    ],
    "sg:phone":"+1 252 636 1776",
    "sg:postcode":"28560",
    "sg:province":"NC",
    "sg:tags":[
        "automobile",
        "rebuilt"
    ],
    "wof:name":"S T Corvettes",
    "wof:placetype":"venue"
},
  "geometry": {"coordinates":[-76.99685100000001,35.03908],"type":"Point"}
}