{
  "type": "Feature",
  "properties": {
    "iso:country":"US",
    "sg:address":"104 New Edition Ct",
    "sg:city":"Cary",
    "sg:classifiers":[
        {
            "category":"Professional",
            "type":"Services"
        }
    ],
    "sg:phone":"+1 919 481 0181",
    "sg:postcode":"27511",
    "sg:province":"NC",
    "wof:name":"Celebration Cottage Inc",
    "wof:placetype":"venue"
},
  "geometry": {"coordinates":[-78.78422,35.767809],"type":"Point"}
}