{
  "type": "Feature",
  "properties": {
    "iso:country":"US",
    "sg:address":"1651 US Hwy 17 N",
    "sg:city":"Merry Hill",
    "sg:classifiers":[
        {
            "category":"Social Services",
            "subcategory":"Child Care",
            "type":"Services"
        }
    ],
    "sg:phone":"+1 252 482 8101",
    "sg:postcode":"27957",
    "sg:province":"NC",
    "wof:name":"Jumpin' Jacks Child Care Ctr",
    "wof:placetype":"venue"
},
  "geometry": {"coordinates":[-76.796295,36.03106],"type":"Point"}
}