{
  "type": "Feature",
  "properties": {
    "iso:country":"US",
    "sg:address":"2821 Rosemont St",
    "sg:city":"Charlotte",
    "sg:classifiers":[
        {
            "category":"Home & Garden",
            "subcategory":"Building Materials",
            "type":"Retail Goods"
        },
        {
            "category":"Manufacturing",
            "subcategory":"Glass & Minerals",
            "type":"Manufacturing & Wholesale Goods"
        },
        {
            "category":"Manufacturing",
            "subcategory":"Building Materials",
            "type":"Manufacturing & Wholesale Goods"
        }
    ],
    "sg:phone":"+1 704 399 4244",
    "sg:postcode":"28208",
    "sg:province":"NC",
    "sg:tags":[
        "door",
        "doors-glass",
        "window",
        "storm",
        "awning",
        "canopy"
    ],
    "sg:website":"http://www.allseasonswindow.com",
    "wof:name":"All Seasons Window & Door Company",
    "wof:placetype":"venue"
},
  "geometry": {"coordinates":[-80.906994,35.224756],"type":"Point"}
}