{
  "type": "Feature",
  "properties": {
    "addr:full":"6718 River Hills Dr Greensboro NC 27410",
    "addr:housenumber":"6718",
    "addr:postcode":"27410",
    "addr:street":"River Hills Dr",
    "iso:country":"US",
    "sg:address":"6718 River Hills Dr",
    "sg:city":"Greensboro",
    "sg:classifiers":[
        {
            "category":"Manufacturing",
            "subcategory":"Tools & Machinery",
            "type":"Manufacturing & Wholesale Goods"
        }
    ],
    "sg:phone":"+1 336 668 2299",
    "sg:postcode":"27410",
    "sg:province":"NC",
    "sg:tags":[
        "textile",
        "mfg"
    ],
    "wof:name":"Nova Tech International",
    "wof:placetype":"venue"
},
  "geometry": {"coordinates":[-79.932321,36.13477],"type":"Point"}
}