{
  "type": "Feature",
  "properties": {
    "iso:country":"US",
    "sg:address":"3192 US Hwy 70 E",
    "sg:city":"Smithfield",
    "sg:classifiers":[
        {
            "category":"Autos & Motor Vehicles",
            "subcategory":"Auto Supplies",
            "type":"Retail Goods"
        }
    ],
    "sg:phone":"+1 919 989 7772",
    "sg:postcode":"27577",
    "sg:province":"NC",
    "sg:tags":[
        "tire"
    ],
    "wof:name":"Tires R Us",
    "wof:placetype":"venue"
},
  "geometry": {"coordinates":[-78.259535,35.486569],"type":"Point"}
}