{
  "type": "Feature",
  "properties": {
    "addr:full":"40 Mountain Vista Dr Asheville NC 28804",
    "addr:housenumber":"40",
    "addr:postcode":"28804",
    "addr:street":"Mountain Vista Dr",
    "iso:country":"US",
    "sg:address":"40 Mountain Vista Dr",
    "sg:city":"Asheville",
    "sg:classifiers":[
        {
            "category":"Professional",
            "subcategory":"Management & Consulting",
            "type":"Services"
        }
    ],
    "sg:phone":"+1 828 285 0236",
    "sg:postcode":"28804",
    "sg:province":"NC",
    "sg:tags":[
        "consultant",
        "resource",
        "human"
    ],
    "sg:website":"www.buildingbridgesinc.com",
    "wof:name":"Building Bridges Inc",
    "wof:placetype":"venue"
},
  "geometry": {"coordinates":[-82.51708499999999,35.628429],"type":"Point"}
}