{
  "type": "Feature",
  "properties": {
    "addr:full":"131 S Park Dr Mooresville NC 28117",
    "addr:housenumber":"131",
    "addr:postcode":"28117",
    "addr:street":"S Park Dr",
    "iso:country":"US",
    "sg:address":"131 S Park Dr",
    "sg:city":"Mooresville",
    "sg:classifiers":[
        {
            "category":"Health Services",
            "subcategory":"Doctor",
            "type":"Services"
        }
    ],
    "sg:phone":"+1 704 662 0877",
    "sg:postcode":"28117",
    "sg:province":"NC",
    "sg:tags":[
        "physician",
        "surgeon"
    ],
    "wof:name":"Lake Norman Anesthesia Assoc",
    "wof:placetype":"venue"
},
  "geometry": {"coordinates":[-80.873214,35.580924],"type":"Point"}
}