{
  "type": "Feature",
  "properties": {
    "addr:full":"101 Innovation Ave Morrisville NC 27560",
    "addr:housenumber":"101",
    "addr:postcode":"27560",
    "addr:street":"Innovation Ave",
    "iso:country":"US",
    "sg:address":"101 Innovation Ave",
    "sg:city":"Morrisville",
    "sg:classifiers":[
        {
            "category":"Arena",
            "subcategory":"Sports Club",
            "type":"Entertainment"
        }
    ],
    "sg:phone":"+1   ",
    "sg:postcode":"27560",
    "sg:province":"NC",
    "sg:tags":[
        "membership"
    ],
    "wof:name":"Carolina Courage",
    "wof:placetype":"venue"
},
  "geometry": {"coordinates":[-78.81882899999999,35.871984],"type":"Point"}
}