{
  "type": "Feature",
  "properties": {
    "addr:full":"6209 Poole Rd Raleigh NC 27610",
    "addr:housenumber":"6209",
    "addr:postcode":"27610",
    "addr:street":"Poole Rd",
    "iso:country":"US",
    "sg:address":"6209 Poole Rd",
    "sg:city":"Raleigh",
    "sg:classifiers":[
        {
            "category":"Professional",
            "subcategory":"Business Services",
            "type":"Services"
        }
    ],
    "sg:phone":"+1   ",
    "sg:postcode":"27610",
    "sg:province":"NC",
    "wof:name":"On-Site Media Solutions",
    "wof:placetype":"venue"
},
  "geometry": {"coordinates":[-78.536824,35.754983],"type":"Point"}
}