{
  "type": "Feature",
  "properties": {
    "iso:country":"US",
    "sg:address":"102 Sequoyah Cir",
    "sg:city":"Morganton",
    "sg:classifiers":[
        {
            "category":"Professional",
            "subcategory":"Advertising",
            "type":"Services"
        }
    ],
    "sg:phone":"+1   ",
    "sg:postcode":"28655",
    "sg:province":"NC",
    "sg:tags":[
        "agency"
    ],
    "wof:name":"Landers Assoc",
    "wof:placetype":"venue"
},
  "geometry": {"coordinates":[-81.64708400000001,35.75316],"type":"Point"}
}