{
  "type": "Feature",
  "properties": {
    "addr:full":"10813 Wilmore Dr Raleigh NC 27614",
    "addr:housenumber":"10813",
    "addr:postcode":"27614",
    "addr:street":"Wilmore Dr",
    "iso:country":"US",
    "sg:address":"10813 Wilmore Dr",
    "sg:city":"Raleigh",
    "sg:classifiers":[
        {
            "category":"Building & Trades",
            "subcategory":"Construction",
            "type":"Services"
        }
    ],
    "sg:phone":"+1 919 489 4899",
    "sg:postcode":"27614",
    "sg:province":"NC",
    "sg:tags":[
        "house"
    ],
    "wof:name":"Trg Construction Services",
    "wof:placetype":"venue"
},
  "geometry": {"coordinates":[-78.65804900000001,35.935706],"type":"Point"}
}