{
  "type": "Feature",
  "properties": {
    "addr:full":"420 E Plaza Dr Mooresville NC 28115",
    "addr:housenumber":"420",
    "addr:postcode":"28115",
    "addr:street":"E Plaza Dr",
    "iso:country":"US",
    "sg:address":"420 E Plaza Dr",
    "sg:city":"Mooresville",
    "sg:classifiers":[
        {
            "category":"Insurance",
            "subcategory":"Insurance Agent",
            "type":"Services"
        }
    ],
    "sg:phone":"+1 704 664 7990",
    "sg:postcode":"28115",
    "sg:province":"NC",
    "wof:name":"Triangle Insur Agcy Moresville",
    "wof:placetype":"venue"
},
  "geometry": {"coordinates":[-80.82016900000001,35.592518],"type":"Point"}
}