{
  "type": "Feature",
  "properties": {
    "addr:full":"700 Peter Gill Rd Henderson NC 27537",
    "addr:housenumber":"700",
    "addr:postcode":"27537",
    "addr:street":"Peter Gill Rd",
    "iso:country":"US",
    "sg:address":"700 Peter Gill Rd",
    "sg:city":"Henderson",
    "sg:classifiers":[
        {
            "category":"Professional",
            "subcategory":"Business Services",
            "type":"Services"
        }
    ],
    "sg:phone":"+1 252 438 8479",
    "sg:postcode":"27537",
    "sg:province":"NC",
    "wof:name":"D & J Express Inc",
    "wof:placetype":"venue"
},
  "geometry": {"coordinates":[-78.392207,36.264521],"type":"Point"}
}