{
  "type": "Feature",
  "properties": {
    "addr:full":"34 Wall St Asheville NC 28801",
    "addr:housenumber":"34",
    "addr:postcode":"28801",
    "addr:street":"Wall St",
    "iso:country":"US",
    "sg:address":"34 Wall St",
    "sg:city":"Asheville",
    "sg:classifiers":[
        {
            "category":"Organizations",
            "subcategory":"Community Association",
            "type":"Services"
        }
    ],
    "sg:phone":"+1 828 251 0606",
    "sg:postcode":"28801",
    "sg:province":"NC",
    "wof:name":"Sigma Alpha Iotainternational",
    "wof:placetype":"venue"
},
  "geometry": {"coordinates":[-82.55623799999999,35.594502],"type":"Point"}
}