{
  "type": "Feature",
  "properties": {
    "iso:country":"US",
    "sg:address":"3655 Reynolda Rd",
    "sg:city":"Winston Salem",
    "sg:classifiers":[
        {
            "category":"Home & Garden",
            "subcategory":"Building Materials",
            "type":"Retail Goods"
        }
    ],
    "sg:phone":"+1 336 924 0948",
    "sg:postcode":"27106",
    "sg:province":"NC",
    "sg:tags":[
        "paint"
    ],
    "wof:name":"Sherwin-Williams Paints",
    "wof:placetype":"venue"
},
  "geometry": {"coordinates":[-80.32066399999999,36.159341],"type":"Point"}
}