{
  "type": "Feature",
  "properties": {
    "addr:full":"400 S Main St Laurinburg NC 28352",
    "addr:housenumber":"400",
    "addr:postcode":"28352",
    "addr:street":"S Main St",
    "iso:country":"US",
    "sg:address":"400 S Main St",
    "sg:city":"Laurinburg",
    "sg:classifiers":[
        {
            "category":"Banks & Credit Unions",
            "subcategory":"Bank",
            "type":"Services"
        }
    ],
    "sg:phone":"+1 910 276 2775",
    "sg:postcode":"28352",
    "sg:province":"NC",
    "wof:name":"B B & T",
    "wof:placetype":"venue"
},
  "geometry": {"coordinates":[-79.46280299999999,34.774161],"type":"Point"}
}