{
  "type": "Feature",
  "properties": {
    "addr:full":"1320 Wagram Ct Raleigh NC 27615",
    "addr:housenumber":"1320",
    "addr:postcode":"27615",
    "addr:street":"Wagram Ct",
    "iso:country":"US",
    "sg:address":"1320 Wagram Ct",
    "sg:city":"Raleigh",
    "sg:classifiers":[
        {
            "category":"Building & Trades",
            "subcategory":"Construction",
            "type":"Services"
        }
    ],
    "sg:phone":"+1 919 846 2874",
    "sg:postcode":"27615",
    "sg:province":"NC",
    "sg:tags":[
        "house",
        "industrial",
        "co"
    ],
    "wof:name":"European Concepts Inc",
    "wof:placetype":"venue"
},
  "geometry": {"coordinates":[-78.617051,35.891817],"type":"Point"}
}