{
  "type": "Feature",
  "properties": {
    "iso:country":"US",
    "sg:address":"1887 Long Mill Rd",
    "sg:city":"Youngsville",
    "sg:classifiers":[
        {
            "category":"Retail",
            "subcategory":"Repair Shop",
            "type":"Services"
        },
        {
            "category":"Home & Garden",
            "subcategory":"Garden Supply",
            "type":"Retail Goods"
        }
    ],
    "sg:phone":"+1 919 556 2887",
    "sg:postcode":"27596",
    "sg:province":"NC",
    "sg:tags":[
        "engine"
    ],
    "wof:name":"Henry's Small Engines Repair",
    "wof:placetype":"venue"
},
  "geometry": {"coordinates":[-78.50180400000001,36.048106],"type":"Point"}
}