{
  "type": "Feature",
  "properties": {
    "addr:full":"6203 Murchison Rd Fayetteville NC 28311",
    "addr:housenumber":"6203",
    "addr:postcode":"28311",
    "addr:street":"Murchison Rd",
    "iso:country":"US",
    "sg:address":"6203 Murchison Rd",
    "sg:city":"Fayetteville",
    "sg:classifiers":[
        {
            "category":"Retail",
            "subcategory":"Auto Repair",
            "type":"Services"
        }
    ],
    "sg:phone":"+1   ",
    "sg:postcode":"28311",
    "sg:province":"NC",
    "sg:tags":[
        "general"
    ],
    "wof:name":"Universal Auto Body Repair",
    "wof:placetype":"venue"
},
  "geometry": {"coordinates":[-78.937985,35.122924],"type":"Point"}
}