{
  "type": "Feature",
  "properties": {
    "iso:country":"US",
    "sg:address":"199 W Salisbury St",
    "sg:city":"Pittsboro",
    "sg:classifiers":[
        {
            "category":"Health Services",
            "subcategory":"Clinic",
            "type":"Services"
        }
    ],
    "sg:phone":"+1   ",
    "sg:postcode":"27312",
    "sg:province":"NC",
    "wof:name":"Chatham Wellness Assoc LL",
    "wof:placetype":"venue"
},
  "geometry": {"coordinates":[-79.179704,35.721684],"type":"Point"}
}