{
  "type": "Feature",
  "properties": {
    "addr:full":"830 N State St Yadkinville NC 27055",
    "addr:housenumber":"830",
    "addr:postcode":"27055",
    "addr:street":"N State St",
    "iso:country":"US",
    "sg:address":"830 N State St",
    "sg:city":"Yadkinville",
    "sg:classifiers":[
        {
            "category":"Food & Beverages",
            "subcategory":"Groceries & Convenience Stores",
            "type":"Retail Goods"
        }
    ],
    "sg:phone":"+1 336 677 6564",
    "sg:postcode":"27055",
    "sg:province":"NC",
    "sg:tags":[
        "grocer"
    ],
    "wof:name":"Hop In Grocery",
    "wof:placetype":"venue"
},
  "geometry": {"coordinates":[-80.665205,36.142254],"type":"Point"}
}