{
  "type": "Feature",
  "properties": {
    "iso:country":"US",
    "sg:address":"4419 Tuckaseegee Rd",
    "sg:city":"Charlotte",
    "sg:classifiers":[
        {
            "category":"Restaurant",
            "type":"Food & Drink"
        }
    ],
    "sg:phone":"+1 704 392 8308",
    "sg:postcode":"28208",
    "sg:province":"NC",
    "sg:tags":[
        "eating"
    ],
    "wof:name":"Daves Grill",
    "wof:placetype":"venue"
},
  "geometry": {"coordinates":[-80.899348,35.246158],"type":"Point"}
}