{
  "type": "Feature",
  "properties": {
    "addr:full":"402 Halstead Blvd Elizabeth City NC 27909",
    "addr:housenumber":"402",
    "addr:postcode":"27909",
    "addr:street":"Halstead Blvd",
    "iso:country":"US",
    "sg:address":"402 Halstead Blvd",
    "sg:city":"Elizabeth City",
    "sg:classifiers":[
        {
            "category":"Travel",
            "subcategory":"Hotels & Motels",
            "type":"Entertainment"
        }
    ],
    "sg:phone":"+1 252 333 1800",
    "sg:postcode":"27909",
    "sg:province":"NC",
    "sg:tags":[
        "operation"
    ],
    "wof:name":"Hampton Inn",
    "wof:placetype":"venue"
},
  "geometry": {"coordinates":[-76.247,36.294897],"type":"Point"}
}