{
  "type": "Feature",
  "properties": {
    "iso:country":"US",
    "sg:address":"210 S Main St",
    "sg:city":"Stanley",
    "sg:classifiers":[
        {
            "category":"Restaurant",
            "type":"Food & Drink"
        }
    ],
    "sg:phone":"+1 704 263 1030",
    "sg:postcode":"28164",
    "sg:province":"NC",
    "wof:name":"Woodshed Restaurant",
    "wof:placetype":"venue"
},
  "geometry": {"coordinates":[-81.095247,35.358321],"type":"Point"}
}