{
  "type": "Feature",
  "properties": {
    "addr:full":"1523 Starlite Dr Lumberton NC 28358",
    "addr:housenumber":"1523",
    "addr:postcode":"28358",
    "addr:street":"Starlite Dr",
    "iso:country":"US",
    "sg:address":"1523 Starlite Dr",
    "sg:city":"Lumberton",
    "sg:classifiers":[
        {
            "category":"Building & Trades",
            "subcategory":"Construction",
            "type":"Services"
        }
    ],
    "sg:phone":"+1 910 608 0336",
    "sg:postcode":"28358",
    "sg:province":"NC",
    "sg:tags":[
        "steel",
        "erectors"
    ],
    "wof:name":"OSE Construction Co Inc",
    "wof:placetype":"venue"
},
  "geometry": {"coordinates":[-79.05286599999999,34.62098],"type":"Point"}
}