{
  "type": "Feature",
  "properties": {
    "iso:country":"US",
    "sg:address":"7221 Belmont Dr",
    "sg:city":"Trinity",
    "sg:classifiers":[
        {
            "category":"Building & Trades",
            "subcategory":"Construction",
            "type":"Services"
        }
    ],
    "sg:phone":"+1 336 475 1359",
    "sg:postcode":"27370",
    "sg:province":"NC",
    "sg:tags":[
        "house"
    ],
    "wof:name":"Carolina Custom Home Craft",
    "wof:placetype":"venue"
},
  "geometry": {"coordinates":[-80.046978,35.855267],"type":"Point"}
}