{
  "type": "Feature",
  "properties": {
    "iso:country":"US",
    "sg:address":"124 Gilliland Rd",
    "sg:city":"Siler City",
    "sg:classifiers":[
        {
            "category":"Wholesale",
            "subcategory":"Vending Machines",
            "type":"Manufacturing & Wholesale Goods"
        }
    ],
    "sg:phone":"+1 919 663 0964",
    "sg:postcode":"27344",
    "sg:province":"NC",
    "sg:tags":[
        "operator"
    ],
    "wof:name":"Variety Vending Service",
    "wof:placetype":"venue"
},
  "geometry": {"coordinates":[-79.514207,35.691969],"type":"Point"}
}