{
  "type": "Feature",
  "properties": {
    "addr:full":"3824 N Elm St Greensboro NC 27455",
    "addr:housenumber":"3824",
    "addr:postcode":"27455",
    "addr:street":"N Elm St",
    "iso:country":"US",
    "sg:address":"3824 N Elm St",
    "sg:city":"Greensboro",
    "sg:classifiers":[
        {
            "category":"Health Services",
            "subcategory":"Doctor",
            "type":"Services"
        }
    ],
    "sg:phone":"+1 336 373 1996",
    "sg:postcode":"27455",
    "sg:province":"NC",
    "sg:tags":[
        "physician",
        "surgeon"
    ],
    "sg:website":"www.eaglemds.com",
    "wof:name":"Eagle Physicians",
    "wof:placetype":"venue"
},
  "geometry": {"coordinates":[-79.799116,36.143315],"type":"Point"}
}