{
  "type": "Feature",
  "properties": {
    "addr:full":"6809 Phillips Place Ct Charlotte NC 28210",
    "addr:housenumber":"6809",
    "addr:postcode":"28210",
    "addr:street":"Phillips Place Ct",
    "iso:country":"US",
    "sg:address":"6809 Phillips Place Ct",
    "sg:city":"Charlotte",
    "sg:classifiers":[
        {
            "category":"Restaurant",
            "type":"Food & Drink"
        }
    ],
    "sg:menulink":"http://www.allmenus.com/nc/charlotte/6827-pf-changs/menu/",
    "sg:phone":"+1 704 552 6644",
    "sg:postcode":"28210",
    "sg:province":"NC",
    "sg:tags":[
        "japanese",
        "chinese",
        "asian"
    ],
    "wof:name":"P.F. Chang's",
    "wof:placetype":"venue"
},
  "geometry": {"coordinates":[-80.82531400000001,35.145815],"type":"Point"}
}