{
  "type": "Feature",
  "properties": {
    "iso:country":"US",
    "sg:address":"223 Hearthside Dr",
    "sg:city":"Winston Salem",
    "sg:classifiers":[
        {
            "category":"Shopping",
            "subcategory":"Stationery & Office Supplies",
            "type":"Retail Goods"
        }
    ],
    "sg:phone":"+1 336 703 0430",
    "sg:postcode":"27104",
    "sg:province":"NC",
    "sg:tags":[
        "educational",
        "material"
    ],
    "wof:name":"Unlimited Learning Resources",
    "wof:placetype":"venue"
},
  "geometry": {"coordinates":[-80.33180900000001,36.094056],"type":"Point"}
}