{
  "type": "Feature",
  "properties": {
    "iso:country":"US",
    "sg:address":"3700 Cottonwood Dr",
    "sg:city":"Durham",
    "sg:classifiers":[
        {
            "category":"Building & Trades",
            "subcategory":"Construction",
            "type":"Services"
        }
    ],
    "sg:phone":"+1 919 490 6880",
    "sg:postcode":"27707",
    "sg:province":"NC",
    "sg:tags":[
        "house"
    ],
    "wof:name":"Copeland Renovations",
    "wof:placetype":"venue"
},
  "geometry": {"coordinates":[-78.98290299999999,35.969817],"type":"Point"}
}