{
  "type": "Feature",
  "properties": {
    "iso:country":"US",
    "sg:address":"3519 Mallory Taylor Ln",
    "sg:city":"Charlotte",
    "sg:classifiers":[
        {
            "category":"Building & Trades",
            "subcategory":"Construction",
            "type":"Services"
        }
    ],
    "sg:phone":"+1 704 634 0713",
    "sg:postcode":"28216",
    "sg:province":"NC",
    "sg:tags":[
        "concrete",
        "stamped"
    ],
    "wof:name":"Decorative Concrete F/X Inc",
    "wof:placetype":"venue"
},
  "geometry": {"coordinates":[-80.86735899999999,35.307893],"type":"Point"}
}