{
  "type": "Feature",
  "properties": {
    "addr:full":"1469 River Ridge Rd Clemmons NC 27012",
    "addr:housenumber":"1469",
    "addr:postcode":"27012",
    "addr:street":"River Ridge Rd",
    "iso:country":"US",
    "sg:address":"1469 River Ridge Rd",
    "sg:city":"Clemmons",
    "sg:classifiers":[
        {
            "category":"Restaurant",
            "type":"Food & Drink"
        }
    ],
    "sg:menulink":"http://www.allmenus.com/nc/hampton/140776-marios-pizza/menu/",
    "sg:phone":"+1 336 778 2002",
    "sg:postcode":"27012",
    "sg:province":"NC",
    "sg:tags":[
        "american",
        "pizza"
    ],
    "wof:name":"Mario's Pizza",
    "wof:placetype":"venue"
},
  "geometry": {"coordinates":[-80.375075,35.961101],"type":"Point"}
}