{
  "type": "Feature",
  "properties": {
    "addr:full":"1801 Claude Austin Rd Monroe NC 28112",
    "addr:housenumber":"1801",
    "addr:postcode":"28112",
    "addr:street":"Claude Austin Rd",
    "iso:country":"US",
    "sg:address":"1801 Claude Austin Rd",
    "sg:city":"Monroe",
    "sg:classifiers":[
        {
            "category":"Professional",
            "subcategory":"Business Services",
            "type":"Services"
        }
    ],
    "sg:phone":"+1   ",
    "sg:postcode":"28112",
    "sg:province":"NC",
    "wof:name":"Country Living Inc",
    "wof:placetype":"venue"
},
  "geometry": {"coordinates":[-80.47314,34.910534],"type":"Point"}
}