{
  "type": "Feature",
  "properties": {
    "addr:full":"3101 S Evans St Greenville NC 27834",
    "addr:housenumber":"3101",
    "addr:postcode":"27834",
    "addr:street":"S Evans St",
    "iso:country":"US",
    "sg:address":"3101 S Evans St",
    "sg:city":"Greenville",
    "sg:classifiers":[
        {
            "category":"Retail",
            "subcategory":"Photofinishing",
            "type":"Services"
        }
    ],
    "sg:phone":"+1 252 355 5118",
    "sg:postcode":"27834",
    "sg:province":"NC",
    "sg:tags":[
        "photo",
        "finishing"
    ],
    "wof:name":"Half Hour Photo Inc",
    "wof:placetype":"venue"
},
  "geometry": {"coordinates":[-77.38173399999999,35.577279],"type":"Point"}
}