{
  "type": "Feature",
  "properties": {
    "addr:full":"129 Pine Grove Church Rd Concord NC 28025",
    "addr:housenumber":"129",
    "addr:postcode":"28025",
    "addr:street":"Pine Grove Church Rd",
    "iso:country":"US",
    "sg:address":"129 Pine Grove Church Rd",
    "sg:city":"Concord",
    "sg:classifiers":[
        {
            "category":"Building & Trades",
            "subcategory":"Plumbing",
            "type":"Services"
        }
    ],
    "sg:phone":"+1 704 531 1922",
    "sg:postcode":"28025",
    "sg:province":"NC",
    "sg:tags":[
        "plumbing",
        "contractor"
    ],
    "wof:name":"Alex's Plumbing Repair",
    "wof:placetype":"venue"
},
  "geometry": {"coordinates":[-80.56981500000001,35.29219],"type":"Point"}
}