{
  "type": "Feature",
  "properties": {
    "iso:country":"US",
    "sg:address":"250 Pungo View Rd",
    "sg:city":"Belhaven",
    "sg:classifiers":[
        {
            "category":"Wholesale",
            "subcategory":"Machinery & Supplies",
            "type":"Manufacturing & Wholesale Goods"
        }
    ],
    "sg:phone":"+1 252 964 6190",
    "sg:postcode":"27810",
    "sg:province":"NC",
    "sg:tags":[
        "equipment",
        "transportation"
    ],
    "wof:name":"Pungo Marine",
    "wof:placetype":"venue"
},
  "geometry": {"coordinates":[-76.655748,35.510998],"type":"Point"}
}