{
  "type": "Feature",
  "properties": {
    "iso:country":"US",
    "sg:address":"9102 Sasspan Lndg SW",
    "sg:city":"Calabash",
    "sg:classifiers":[
        {
            "category":"Building & Trades",
            "subcategory":"Construction",
            "type":"Services"
        }
    ],
    "sg:phone":"+1 910 575 2443",
    "sg:postcode":"28467",
    "sg:province":"NC",
    "sg:tags":[
        "contractor"
    ],
    "wof:name":"Empire Builders",
    "wof:placetype":"venue"
},
  "geometry": {"coordinates":[-78.55054,33.881702],"type":"Point"}
}