{
  "type": "Feature",
  "properties": {
    "iso:country":"US",
    "sg:address":"1519 Morrisville Pkwy",
    "sg:city":"Morrisville",
    "sg:classifiers":[
        {
            "category":"Education",
            "subcategory":"School",
            "type":"Public Place"
        }
    ],
    "sg:phone":"+1 919 460 3400",
    "sg:postcode":"27560",
    "sg:province":"NC",
    "sg:website":"morrisvillees.wcpss.net",
    "wof:name":"Wake County Public School System",
    "wof:placetype":"venue"
},
  "geometry": {"coordinates":[-78.845257,35.811867],"type":"Point"}
}