{
  "type": "Feature",
  "properties": {
    "addr:full":"5821 Fairview Rd Charlotte NC 28209",
    "addr:housenumber":"5821",
    "addr:postcode":"28209",
    "addr:street":"Fairview Rd",
    "iso:country":"US",
    "sg:address":"5821 Fairview Rd",
    "sg:city":"Charlotte",
    "sg:classifiers":[
        {
            "category":"Insurance",
            "subcategory":"Insurance Agent",
            "type":"Services"
        }
    ],
    "sg:phone":"+1 704 552 4774",
    "sg:postcode":"28209",
    "sg:province":"NC",
    "wof:name":"E L Johnson Insurance",
    "wof:placetype":"venue"
},
  "geometry": {"coordinates":[-80.841959,35.151747],"type":"Point"}
}