{
  "type": "Feature",
  "properties": {
    "iso:country":"US",
    "sg:address":"1100 Martin Luther King Jr Blvd",
    "sg:city":"Siler City",
    "sg:classifiers":[
        {
            "category":"Government",
            "subcategory":"Office",
            "type":"Public Place"
        }
    ],
    "sg:phone":"+1 919 560 1200",
    "sg:postcode":"27344",
    "sg:province":"NC",
    "sg:tags":[
        "village"
    ],
    "wof:name":"Division - Water Management",
    "wof:placetype":"venue"
},
  "geometry": {"coordinates":[-79.45761400000001,35.733562],"type":"Point"}
}