{
  "type": "Feature",
  "properties": {
    "iso:country":"US",
    "sg:address":"914 Ash St",
    "sg:city":"Albemarle",
    "sg:classifiers":[
        {
            "category":"Wholesale",
            "subcategory":"Machinery & Supplies",
            "type":"Manufacturing & Wholesale Goods"
        }
    ],
    "sg:phone":"+1 704 983 3130",
    "sg:postcode":"28001",
    "sg:province":"NC",
    "sg:tags":[
        "salon",
        "beauty"
    ],
    "wof:name":"Jerbe' Cosmetics & Beauty Supl",
    "wof:placetype":"venue"
},
  "geometry": {"coordinates":[-80.203649,35.363628],"type":"Point"}
}