{
  "type": "Feature",
  "properties": {
    "addr:full":"4140 Mendenhall Oaks Pkwy High Point NC 27265",
    "addr:housenumber":"4140",
    "addr:postcode":"27265",
    "addr:street":"Mendenhall Oaks Pkwy",
    "iso:country":"US",
    "sg:address":"4140 Mendenhall Oaks Pkwy",
    "sg:city":"High Point",
    "sg:classifiers":[
        {
            "category":"Building & Trades",
            "subcategory":"Construction",
            "type":"Services"
        }
    ],
    "sg:phone":"+1 336 454 6131",
    "sg:postcode":"27265",
    "sg:province":"NC",
    "sg:tags":[
        "general",
        "contractor"
    ],
    "wof:name":"Milton Kirkland Inc",
    "wof:placetype":"venue"
},
  "geometry": {"coordinates":[-79.95755,36.047084],"type":"Point"}
}