{
  "type": "Feature",
  "properties": {
    "addr:full":"417 N Boylan Ave Raleigh NC 27603",
    "addr:housenumber":"417",
    "addr:postcode":"27603",
    "addr:street":"N Boylan Ave",
    "iso:country":"US",
    "sg:address":"417 N Boylan Ave",
    "sg:city":"Raleigh",
    "sg:classifiers":[
        {
            "category":"Professional",
            "subcategory":"Engineering",
            "type":"Services"
        }
    ],
    "sg:phone":"+1   ",
    "sg:postcode":"27603",
    "sg:province":"NC",
    "wof:name":"Infratrek Consultants PC",
    "wof:placetype":"venue"
},
  "geometry": {"coordinates":[-78.648988,35.786241],"type":"Point"}
}