{
  "type": "Feature",
  "properties": {
    "iso:country":"US",
    "sg:address":"209 Ruth Dial St",
    "sg:city":"Pembroke",
    "sg:classifiers":[
        {
            "category":"Real Estate",
            "subcategory":"Real Estate Operator",
            "type":"Services"
        }
    ],
    "sg:phone":"+1 910 521 3388",
    "sg:postcode":"28372",
    "sg:province":"NC",
    "sg:tags":[
        "apartment"
    ],
    "wof:name":"Cedar Wood Apartments",
    "wof:placetype":"venue"
},
  "geometry": {"coordinates":[-79.19193199999999,34.675436],"type":"Point"}
}