{
  "type": "Feature",
  "properties": {
    "addr:full":"1022 Anderson St Durham NC 27705",
    "addr:housenumber":"1022",
    "addr:postcode":"27705",
    "addr:street":"Anderson St",
    "iso:country":"US",
    "sg:address":"1022 Anderson St",
    "sg:city":"Durham",
    "sg:classifiers":[
        {
            "category":"Banks & Credit Unions",
            "subcategory":"Bank",
            "type":"Services"
        }
    ],
    "sg:phone":"+1 877 535 2066",
    "sg:postcode":"27705",
    "sg:province":"NC",
    "sg:tags":[
        "broker",
        "mortgage"
    ],
    "wof:name":"Sovereign Financial Svcs LLC",
    "wof:placetype":"venue"
},
  "geometry": {"coordinates":[-78.933072,35.990709],"type":"Point"}
}