{
  "type": "Feature",
  "properties": {
    "iso:country":"US",
    "sg:address":"106 W 5th St",
    "sg:city":"Lumberton",
    "sg:classifiers":[
        {
            "category":"Professional",
            "subcategory":"Lawyer & Legal Services",
            "type":"Services"
        }
    ],
    "sg:phone":"+1 910 739 7141",
    "sg:postcode":"28358",
    "sg:province":"NC",
    "sg:tags":[
        "attorney"
    ],
    "wof:name":"Britt William S Law Offices",
    "wof:placetype":"venue"
},
  "geometry": {"coordinates":[-79.008673,34.620066],"type":"Point"}
}