{
  "type": "Feature",
  "properties": {
    "iso:country":"US",
    "sg:address":"2860 Nathan St",
    "sg:city":"Hickory",
    "sg:classifiers":[
        {
            "category":"Manufacturing",
            "subcategory":"Furniture",
            "type":"Manufacturing & Wholesale Goods"
        }
    ],
    "sg:phone":"+1 828 465 1776",
    "sg:postcode":"28658",
    "sg:province":"NC",
    "sg:tags":[
        "upholstered",
        "wood"
    ],
    "sg:website":"www.southwoodfurn.com",
    "wof:name":"Southwood Furniture Corp",
    "wof:placetype":"venue"
},
  "geometry": {"coordinates":[-81.252307,35.694947],"type":"Point"}
}