{
  "type": "Feature",
  "properties": {
    "addr:full":"5496 Davis Ln Spring Hope NC 27882",
    "addr:housenumber":"5496",
    "addr:postcode":"27882",
    "addr:street":"Davis Ln",
    "iso:country":"US",
    "sg:address":"5496 Davis Ln",
    "sg:city":"Spring Hope",
    "sg:classifiers":[
        {
            "category":"Shopping",
            "subcategory":"Catalog Store",
            "type":"Retail Goods"
        }
    ],
    "sg:phone":"+1 252 478 3804",
    "sg:postcode":"27882",
    "sg:province":"NC",
    "sg:tags":[
        "mail",
        "house"
    ],
    "wof:name":"Dis Heavenly Treasures",
    "wof:placetype":"venue"
},
  "geometry": {"coordinates":[-78.03166400000001,35.886377],"type":"Point"}
}