{
  "type": "Feature",
  "properties": {
    "addr:full":"1644 Union Cross Church Rd Yadkinville NC 27055",
    "addr:housenumber":"1644",
    "addr:postcode":"27055",
    "addr:street":"Union Cross Church Rd",
    "iso:country":"US",
    "sg:address":"1644 Union Cross Church Rd",
    "sg:city":"Yadkinville",
    "sg:classifiers":[
        {
            "category":"Shopping",
            "subcategory":"Computers & Home Electronics",
            "type":"Retail Goods"
        }
    ],
    "sg:phone":"+1 336 961 6483",
    "sg:postcode":"27055",
    "sg:province":"NC",
    "sg:tags":[
        "equipment",
        "dealer"
    ],
    "wof:name":"Paladin Computer Systems",
    "wof:placetype":"venue"
},
  "geometry": {"coordinates":[-80.61677,36.158862],"type":"Point"}
}