{
  "type": "Feature",
  "properties": {
    "addr:full":"301 S Caledonia Rd Laurinburg NC 28352",
    "addr:housenumber":"301",
    "addr:postcode":"28352",
    "addr:street":"S Caledonia Rd",
    "iso:country":"US",
    "sg:address":"301 S Caledonia Rd",
    "sg:city":"Laurinburg",
    "sg:classifiers":[
        {
            "category":"Health Services",
            "subcategory":"Nursing And Care Facility",
            "type":"Services"
        }
    ],
    "sg:phone":"+1   ",
    "sg:postcode":"28352",
    "sg:province":"NC",
    "wof:name":"United Families",
    "wof:placetype":"venue"
},
  "geometry": {"coordinates":[-79.457086,34.773253],"type":"Point"}
}