{
  "type": "Feature",
  "properties": {
    "iso:country":"US",
    "sg:address":"324 S Washington St",
    "sg:city":"Hendersonville",
    "sg:classifiers":[
        {
            "category":"Food & Beverages",
            "subcategory":"Groceries & Convenience Stores",
            "type":"Retail Goods"
        }
    ],
    "sg:phone":"+1 828 692 8701",
    "sg:postcode":"28739",
    "sg:province":"NC",
    "wof:name":"Fast Lane",
    "wof:placetype":"venue"
},
  "geometry": {"coordinates":[-82.461586,35.311871],"type":"Point"}
}