{
  "type": "Feature",
  "properties": {
    "addr:full":"2104 Nixonton Rd Elizabeth City NC 27909",
    "addr:housenumber":"2104",
    "addr:postcode":"27909",
    "addr:street":"Nixonton Rd",
    "iso:country":"US",
    "sg:address":"2104 Nixonton Rd",
    "sg:city":"Elizabeth City",
    "sg:classifiers":[
        {
            "category":"Wholesale",
            "subcategory":"Fruits & Vegetables",
            "type":"Manufacturing & Wholesale Goods"
        }
    ],
    "sg:phone":"+1 252 330 4661",
    "sg:postcode":"27909",
    "sg:province":"NC",
    "wof:name":"Arelion M Berry & Son",
    "wof:placetype":"venue"
},
  "geometry": {"coordinates":[-76.20176499999999,36.196762],"type":"Point"}
}