{
  "type": "Feature",
  "properties": {
    "addr:full":"1493 Main St Yanceyville NC 27379",
    "addr:housenumber":"1493",
    "addr:postcode":"27379",
    "addr:street":"Main St",
    "iso:country":"US",
    "sg:address":"1493 Main St",
    "sg:city":"Yanceyville",
    "sg:classifiers":[
        {
            "category":"Shopping",
            "subcategory":"Pharmacy",
            "type":"Retail Goods"
        }
    ],
    "sg:phone":"+1 336 694 4104",
    "sg:postcode":"27379",
    "sg:province":"NC",
    "wof:name":"North Village Pharmacy",
    "wof:placetype":"venue"
},
  "geometry": {"coordinates":[-79.351482,36.415819],"type":"Point"}
}