{
  "type": "Feature",
  "properties": {
    "addr:full":"518 US Hwy 70 E Hildebran NC 28637",
    "addr:housenumber":"518",
    "addr:postcode":"28637",
    "addr:street":"Us Hwy 70 E",
    "iso:country":"US",
    "sg:address":"518 US Hwy 70 E",
    "sg:city":"Hildebran",
    "sg:classifiers":[
        {
            "category":"Shopping",
            "subcategory":"Clothing, Apparel, & Fashions",
            "type":"Retail Goods"
        }
    ],
    "sg:phone":"+1 828 397 5051",
    "sg:postcode":"28637",
    "sg:province":"NC",
    "sg:tags":[
        "wear"
    ],
    "wof:name":"Baby Goo Round",
    "wof:placetype":"venue"
},
  "geometry": {"coordinates":[-81.424786,35.715344],"type":"Point"}
}