{
  "type": "Feature",
  "properties": {
    "iso:country":"US",
    "sg:address":"127 Grandy Rd",
    "sg:city":"Grandy",
    "sg:classifiers":[
        {
            "category":"Sports & Exercise",
            "subcategory":"Golf",
            "type":"Entertainment"
        }
    ],
    "sg:phone":"+1 252 453 3588",
    "sg:postcode":"27939",
    "sg:province":"NC",
    "sg:tags":[
        "course"
    ],
    "sg:website":"www.thecarolinaclub.com",
    "wof:name":"Carolina Club",
    "wof:placetype":"venue"
},
  "geometry": {"coordinates":[-75.879356,36.217501],"type":"Point"}
}