{
  "type": "Feature",
  "properties": {
    "iso:country":"US",
    "sg:address":"107 Luxury Ln",
    "sg:city":"Knightdale",
    "sg:classifiers":[
        {
            "category":"Building & Trades",
            "subcategory":"Construction",
            "type":"Services"
        },
        {
            "category":"Real Estate",
            "subcategory":"Real Estate Operator",
            "type":"Services"
        }
    ],
    "sg:phone":"+1 919 266 1323",
    "sg:postcode":"27545",
    "sg:province":"NC",
    "sg:tags":[
        "apartment",
        "nonresidential"
    ],
    "wof:name":"Park Place Apartments",
    "wof:placetype":"venue"
},
  "geometry": {"coordinates":[-78.488572,35.792875],"type":"Point"}
}