{
  "type": "Feature",
  "properties": {
    "iso:country":"US",
    "sg:address":"8315 Byrum Dr",
    "sg:city":"Charlotte",
    "sg:classifiers":[
        {
            "category":"Government",
            "subcategory":"Office",
            "type":"Public Place"
        }
    ],
    "sg:phone":"+1 704 336 7600",
    "sg:postcode":"28217",
    "sg:province":"NC",
    "sg:tags":[
        "parish",
        "government-county"
    ],
    "wof:name":"City Cnty Govt Anml Care & Cntrl Bureau; City Cnty I",
    "wof:placetype":"venue"
},
  "geometry": {"coordinates":[-80.947462,35.192503],"type":"Point"}
}