{
  "type": "Feature",
  "properties": {
    "iso:country":"US",
    "sg:address":"8810 Blakeney Dr",
    "sg:city":"Charlotte",
    "sg:classifiers":[
        {
            "category":"Professional",
            "subcategory":"Management & Consulting",
            "type":"Services"
        }
    ],
    "sg:phone":"+1   ",
    "sg:postcode":"28277",
    "sg:province":"NC",
    "sg:tags":[
        "business"
    ],
    "wof:name":"Kumon",
    "wof:placetype":"venue"
},
  "geometry": {"coordinates":[-80.815442,35.037779],"type":"Point"}
}