{
  "type": "Feature",
  "properties": {
    "iso:country":"US",
    "sg:address":"7316 Bassett Hall Ct",
    "sg:city":"Raleigh",
    "sg:classifiers":[
        {
            "category":"Restaurant",
            "type":"Food & Drink"
        }
    ],
    "sg:phone":"+1 919 872 5527",
    "sg:postcode":"27616",
    "sg:province":"NC",
    "sg:tags":[
        "eating"
    ],
    "wof:name":"Cater To You Inc",
    "wof:placetype":"venue"
},
  "geometry": {"coordinates":[-78.567938,35.882704],"type":"Point"}
}