{
  "type": "Feature",
  "properties": {
    "addr:full":"4423 S Browntown Rd Rocky Mount NC 27804",
    "addr:housenumber":"4423",
    "addr:postcode":"27804",
    "addr:street":"S Browntown Rd",
    "iso:country":"US",
    "sg:address":"4423 S Browntown Rd",
    "sg:city":"Rocky Mount",
    "sg:classifiers":[
        {
            "category":"Manufacturing",
            "subcategory":"Apparel",
            "type":"Manufacturing & Wholesale Goods"
        },
        {
            "category":"Shopping",
            "subcategory":"Gifts & Souvenirs",
            "type":"Retail Goods"
        }
    ],
    "sg:phone":"+1 252 443 4321",
    "sg:postcode":"27804",
    "sg:province":"NC",
    "sg:tags":[
        "shop",
        "bedspread"
    ],
    "wof:name":"Corries Creations",
    "wof:placetype":"venue"
},
  "geometry": {"coordinates":[-77.83810200000001,36.02323],"type":"Point"}
}