{
  "type": "Feature",
  "properties": {
    "addr:full":"19400 W Catawba Ave Cornelius NC 28031",
    "addr:housenumber":"19400",
    "addr:postcode":"28031",
    "addr:street":"W Catawba Ave",
    "iso:country":"US",
    "sg:address":"19400 W Catawba Ave",
    "sg:city":"Cornelius",
    "sg:classifiers":[
        {
            "category":"Wholesale",
            "subcategory":"Medical Equipment & Supplies",
            "type":"Manufacturing & Wholesale Goods"
        },
        {
            "category":"Shopping",
            "subcategory":"Beauty & Cosmetics",
            "type":"Retail Goods"
        },
        {
            "category":"Food & Beverages",
            "subcategory":"Specialty",
            "type":"Retail Goods"
        },
        {
            "category":"Shopping",
            "subcategory":"Gifts & Souvenirs",
            "type":"Retail Goods"
        },
        {
            "category":"Retail",
            "subcategory":"Photofinishing",
            "type":"Services"
        },
        {
            "category":"Shopping",
            "subcategory":"Pharmacy",
            "type":"Retail Goods"
        }
    ],
    "sg:phone":"+1 704 892 9540",
    "sg:postcode":"28031",
    "sg:province":"NC",
    "sg:tags":[
        "product",
        "photo",
        "vitamin",
        "perfume",
        "supplement",
        "health",
        "wellness",
        "aid",
        "finishing",
        "first",
        "card",
        "greeting"
    ],
    "sg:website":"http://www.riteaid.com",
    "wof:name":"Rite Aid",
    "wof:placetype":"venue"
},
  "geometry": {"coordinates":[-80.89144899999999,35.476761],"type":"Point"}
}