{
  "type": "Feature",
  "properties": {
    "addr:full":"9625 Old Mill Rd NE Leland NC 28451",
    "addr:housenumber":"9625",
    "addr:postcode":"28451",
    "addr:street":"Old Mill Rd Ne",
    "iso:country":"US",
    "sg:address":"9625 Old Mill Rd NE",
    "sg:city":"Leland",
    "sg:classifiers":[
        {
            "category":"Food & Beverages",
            "subcategory":"Groceries & Convenience Stores",
            "type":"Retail Goods"
        }
    ],
    "sg:phone":"+1 910 371 2797",
    "sg:postcode":"28451",
    "sg:province":"NC",
    "wof:name":"Stop & Save Mini Mart",
    "wof:placetype":"venue"
},
  "geometry": {"coordinates":[-78.023567,34.257673],"type":"Point"}
}