{
  "type": "Feature",
  "properties": {
    "addr:full":"209 Candlewood Rd Rocky Mount NC 27804",
    "addr:housenumber":"209",
    "addr:postcode":"27804",
    "addr:street":"Candlewood Rd",
    "iso:country":"US",
    "sg:address":"209 Candlewood Rd",
    "sg:city":"Rocky Mount",
    "sg:classifiers":[
        {
            "category":"Professional",
            "subcategory":"Computer Services",
            "type":"Services"
        }
    ],
    "sg:phone":"+1 252 443 2079",
    "sg:postcode":"27804",
    "sg:province":"NC",
    "wof:name":"Enterprize Networks Inc",
    "wof:placetype":"venue"
},
  "geometry": {"coordinates":[-77.861707,35.974681],"type":"Point"}
}