{
  "type": "Feature",
  "properties": {
    "iso:country":"US",
    "sg:address":"2401 Dr M L King Jr Blvd",
    "sg:city":"New Bern",
    "sg:classifiers":[
        {
            "category":"Ice Cream",
            "type":"Food & Drink"
        }
    ],
    "sg:menulink":"http://www.allmenus.com/nc/new-bern/167614-dairy-queen-store/menu/",
    "sg:phone":"+1 252 637 6457",
    "sg:postcode":"28562",
    "sg:province":"NC",
    "sg:tags":[
        "burger",
        "american"
    ],
    "wof:name":"Dairy Queen Store",
    "wof:placetype":"venue"
},
  "geometry": {"coordinates":[-77.078245,35.10603],"type":"Point"}
}