{
  "type": "Feature",
  "properties": {
    "addr:full":"300 Bellemeade St Greensboro NC 27401",
    "addr:housenumber":"300",
    "addr:postcode":"27401",
    "addr:street":"Bellemeade St",
    "iso:country":"US",
    "sg:address":"300 Bellemeade St",
    "sg:city":"Greensboro",
    "sg:classifiers":[
        {
            "category":"Shopping",
            "subcategory":"Discount & Variety Stores",
            "type":"Retail Goods"
        }
    ],
    "sg:phone":"+1 336 389 9118",
    "sg:postcode":"27401",
    "sg:province":"NC",
    "sg:tags":[
        "merchandise",
        "general"
    ],
    "wof:name":"ASG",
    "wof:placetype":"venue"
},
  "geometry": {"coordinates":[-79.791439,36.075264],"type":"Point"}
}