{
  "type": "Feature",
  "properties": {
    "addr:full":"413 Earl Rd Shelby NC 28150",
    "addr:housenumber":"413",
    "addr:postcode":"28150",
    "addr:street":"Earl Rd",
    "iso:country":"US",
    "sg:address":"413 Earl Rd",
    "sg:city":"Shelby",
    "sg:classifiers":[
        {
            "category":"Food & Beverages",
            "subcategory":"Groceries & Convenience Stores",
            "type":"Retail Goods"
        }
    ],
    "sg:phone":"+1 704 000 1111",
    "sg:postcode":"28150",
    "sg:province":"NC",
    "sg:tags":[
        "grocer"
    ],
    "wof:name":"Aldi",
    "wof:placetype":"venue"
},
  "geometry": {"coordinates":[-81.534813,35.276934],"type":"Point"}
}