{
  "type": "Feature",
  "properties": {
    "iso:country":"US",
    "sg:address":"1300 Goodview Ave",
    "sg:city":"Fayetteville",
    "sg:classifiers":[
        {
            "category":"Real Estate",
            "subcategory":"Real Estate Agent",
            "type":"Services"
        }
    ],
    "sg:phone":"+1 910 323 1622",
    "sg:postcode":"28305",
    "sg:province":"NC",
    "wof:name":"Anderson Real Estate",
    "wof:placetype":"venue"
},
  "geometry": {"coordinates":[-78.902299,35.060859],"type":"Point"}
}