{
  "type": "Feature",
  "properties": {
    "iso:country":"US",
    "sg:address":"4529 Sharon Rd",
    "sg:city":"Charlotte",
    "sg:classifiers":[
        {
            "category":"Real Estate",
            "subcategory":"Real Estate Agent",
            "type":"Services"
        }
    ],
    "sg:phone":"+1 704 365 8781",
    "sg:postcode":"28211",
    "sg:province":"NC",
    "sg:tags":[
        "finding",
        "apartment",
        "rental"
    ],
    "wof:name":"Preduntial Carolina Rl Est",
    "wof:placetype":"venue"
},
  "geometry": {"coordinates":[-80.830764,35.148527],"type":"Point"}
}