{
  "type": "Feature",
  "properties": {
    "addr:full":"500 Fisher St Fayetteville NC 28301",
    "addr:housenumber":"500",
    "addr:postcode":"28301",
    "addr:street":"Fisher St",
    "iso:country":"US",
    "sg:address":"500 Fisher St",
    "sg:city":"Fayetteville",
    "sg:classifiers":[
        {
            "category":"Recreation",
            "type":"Entertainment"
        }
    ],
    "sg:phone":"+1 910 433 1572",
    "sg:postcode":"28301",
    "sg:province":"NC",
    "sg:tags":[
        "parks"
    ],
    "wof:name":"Christina S Smith Park",
    "wof:placetype":"venue"
},
  "geometry": {"coordinates":[-78.870167,35.039273],"type":"Point"}
}