{
  "type": "Feature",
  "properties": {
    "iso:country":"US",
    "sg:address":"1734 State Rd 39",
    "sg:city":"Louisburg",
    "sg:classifiers":[
        {
            "category":"Autos & Motor Vehicles",
            "subcategory":"Auto Supplies",
            "type":"Retail Goods"
        },
        {
            "category":"Retail",
            "subcategory":"Auto Repair",
            "type":"Services"
        }
    ],
    "sg:phone":"+1 919 496 1792",
    "sg:postcode":"27549",
    "sg:province":"NC",
    "sg:tags":[
        "tire",
        "general"
    ],
    "wof:name":"Jimmy's Tire & Auto Repair",
    "wof:placetype":"venue"
},
  "geometry": {"coordinates":[-78.299397,36.052793],"type":"Point"}
}