{
  "type": "Feature",
  "properties": {
    "addr:full":"3946 Westpoint Blvd Winston Salem NC 27103",
    "addr:housenumber":"3946",
    "addr:postcode":"27103",
    "addr:street":"Westpoint Blvd",
    "iso:country":"US",
    "sg:address":"3946 Westpoint Blvd",
    "sg:city":"Winston Salem",
    "sg:classifiers":[
        {
            "category":"Freight",
            "type":"Transportation"
        }
    ],
    "sg:phone":"+1 336 659 4356",
    "sg:postcode":"27103",
    "sg:province":"NC",
    "sg:tags":[
        "operator",
        "local",
        "trucking"
    ],
    "wof:name":"Fedex",
    "wof:placetype":"venue"
},
  "geometry": {"coordinates":[-80.318425,36.038276],"type":"Point"}
}