{
  "type": "Feature",
  "properties": {
    "iso:country":"US",
    "sg:address":"502 N Broad St",
    "sg:city":"Winston Salem",
    "sg:classifiers":[
        {
            "category":"Social Services",
            "subcategory":"Child Care",
            "type":"Services"
        }
    ],
    "sg:phone":"+1 336 723 7416",
    "sg:postcode":"27101",
    "sg:province":"NC",
    "sg:tags":[
        "school",
        "day"
    ],
    "wof:name":"Assoction For Beneft Child Dev",
    "wof:placetype":"venue"
},
  "geometry": {"coordinates":[-80.254283,36.100142],"type":"Point"}
}