{
  "type": "Feature",
  "properties": {
    "addr:full":"124 W Kapp St Dobson NC 27017",
    "addr:housenumber":"124",
    "addr:postcode":"27017",
    "addr:street":"W Kapp St",
    "iso:country":"US",
    "sg:address":"124 W Kapp St",
    "sg:city":"Dobson",
    "sg:classifiers":[
        {
            "category":"Real Estate",
            "subcategory":"Real Estate Agent",
            "type":"Services"
        }
    ],
    "sg:phone":"+1 336 386 9900",
    "sg:postcode":"27017",
    "sg:province":"NC",
    "wof:name":"Dobson Realty & Auction",
    "wof:placetype":"venue"
},
  "geometry": {"coordinates":[-80.72327900000001,36.396561],"type":"Point"}
}