{
  "type": "Feature",
  "properties": {
    "addr:full":"1952 Lynnwood Dr Charlotte NC 28209",
    "addr:housenumber":"1952",
    "addr:postcode":"28209",
    "addr:street":"Lynnwood Dr",
    "iso:country":"US",
    "sg:address":"1952 Lynnwood Dr",
    "sg:city":"Charlotte",
    "sg:classifiers":[
        {
            "category":"Wholesale",
            "subcategory":"Apparel",
            "type":"Manufacturing & Wholesale Goods"
        }
    ],
    "sg:phone":"+1 704 372 7511",
    "sg:postcode":"28209",
    "sg:province":"NC",
    "sg:tags":[
        "piece"
    ],
    "wof:name":"ARC Co Fabrics Inc",
    "wof:placetype":"venue"
},
  "geometry": {"coordinates":[-80.844342,35.181377],"type":"Point"}
}