{
  "type": "Feature",
  "properties": {
    "addr:full":"5 Blue Briar Rd Asheville NC 28804",
    "addr:housenumber":"5",
    "addr:postcode":"28804",
    "addr:street":"Blue Briar Rd",
    "iso:country":"US",
    "sg:address":"5 Blue Briar Rd",
    "sg:city":"Asheville",
    "sg:classifiers":[
        {
            "category":"Professional",
            "subcategory":"Lawyer & Legal Services",
            "type":"Services"
        }
    ],
    "sg:phone":"+1 828 658 0077",
    "sg:postcode":"28804",
    "sg:province":"NC",
    "sg:tags":[
        "attorney"
    ],
    "wof:name":"Norman C Riddle Law Firm PA",
    "wof:placetype":"venue"
},
  "geometry": {"coordinates":[-82.537301,35.616658],"type":"Point"}
}