{
  "type": "Feature",
  "properties": {
    "addr:full":"100 Pocosin Rd Washington NC 27889",
    "addr:housenumber":"100",
    "addr:postcode":"27889",
    "addr:street":"Pocosin Rd",
    "iso:country":"US",
    "sg:address":"100 Pocosin Rd",
    "sg:city":"Washington",
    "sg:classifiers":[
        {
            "category":"Building & Trades",
            "subcategory":"Landscaping Services",
            "type":"Services"
        }
    ],
    "sg:phone":"+1 252 927 1998",
    "sg:postcode":"27889",
    "sg:province":"NC",
    "wof:name":"Uninversal Landscape",
    "wof:placetype":"venue"
},
  "geometry": {"coordinates":[-76.89478200000001,35.556097],"type":"Point"}
}