{
  "type": "Feature",
  "properties": {
    "iso:country":"US",
    "sg:address":"2417 Lake Wheeler Rd",
    "sg:city":"Raleigh",
    "sg:classifiers":[
        {
            "category":"Manufacturing",
            "subcategory":"Lumber",
            "type":"Manufacturing & Wholesale Goods"
        }
    ],
    "sg:phone":"+1 919 836 8435",
    "sg:postcode":"27603",
    "sg:province":"NC",
    "sg:tags":[
        "hardwood",
        "mill"
    ],
    "wof:name":"Ocampo Enterprises",
    "wof:placetype":"venue"
},
  "geometry": {"coordinates":[-78.674335,35.747396],"type":"Point"}
}