{
  "type": "Feature",
  "properties": {
    "addr:full":"456 US Hwy 70 Havelock NC 28532",
    "addr:housenumber":"456",
    "addr:postcode":"28532",
    "addr:street":"Us Hwy 70",
    "iso:country":"US",
    "sg:address":"456 US Hwy 70",
    "sg:city":"Havelock",
    "sg:classifiers":[
        {
            "category":"Communications",
            "subcategory":"Radio Station",
            "type":"Services"
        }
    ],
    "sg:phone":"+1 252 444 0788",
    "sg:postcode":"28532",
    "sg:province":"NC",
    "sg:tags":[
        "company",
        "broadcasting"
    ],
    "wof:name":"WNBR Bear 94.1 FM",
    "wof:placetype":"venue"
},
  "geometry": {"coordinates":[-76.921074,34.889932],"type":"Point"}
}