{
  "type": "Feature",
  "properties": {
    "iso:country":"US",
    "sg:address":"3627 New Bern Ave",
    "sg:city":"Raleigh",
    "sg:classifiers":[
        {
            "category":"Food & Beverages",
            "subcategory":"Dairy",
            "type":"Retail Goods"
        },
        {
            "category":"Restaurant",
            "type":"Food & Drink"
        }
    ],
    "sg:phone":"+1 919 250 9595",
    "sg:postcode":"27610",
    "sg:province":"NC",
    "sg:tags":[
        "product",
        "parlor",
        "ice",
        "cream"
    ],
    "sg:website":"www.icecreamclub.com",
    "wof:name":"Ice Cream Club",
    "wof:placetype":"venue"
},
  "geometry": {"coordinates":[-78.580011,35.796063],"type":"Point"}
}