{
  "type": "Feature",
  "properties": {
    "addr:full":"110 E Oak St Goldsboro NC 27530",
    "addr:housenumber":"110",
    "addr:postcode":"27530",
    "addr:street":"E Oak St",
    "iso:country":"US",
    "sg:address":"110 E Oak St",
    "sg:city":"Goldsboro",
    "sg:classifiers":[
        {
            "category":"Health Services",
            "subcategory":"Nursing And Care Facility",
            "type":"Services"
        }
    ],
    "sg:phone":"+1 919 583 9006",
    "sg:postcode":"27530",
    "sg:province":"NC",
    "sg:tags":[
        "home",
        "rest"
    ],
    "wof:name":"White Oak Homes II Inc",
    "wof:placetype":"venue"
},
  "geometry": {"coordinates":[-77.99394100000001,35.386556],"type":"Point"}
}