{
  "type": "Feature",
  "properties": {
    "addr:full":"3310 Redgate Dr Durham NC 27703",
    "addr:housenumber":"3310",
    "addr:postcode":"27703",
    "addr:street":"Redgate Dr",
    "iso:country":"US",
    "sg:address":"3310 Redgate Dr",
    "sg:city":"Durham",
    "sg:classifiers":[
        {
            "category":"Autos & Motor Vehicles",
            "subcategory":"Automobile Sales",
            "type":"Retail Goods"
        }
    ],
    "sg:phone":"+1 919 598 1321",
    "sg:postcode":"27703",
    "sg:province":"NC",
    "sg:tags":[
        "used"
    ],
    "wof:name":"Premiere Bus Services",
    "wof:placetype":"venue"
},
  "geometry": {"coordinates":[-78.83861899999999,35.974893],"type":"Point"}
}