{
  "type": "Feature",
  "properties": {
    "addr:full":"1012 3rd Ave NW Hickory NC 28601",
    "addr:housenumber":"1012",
    "addr:postcode":"28601",
    "addr:street":"3Rd Ave Nw",
    "iso:country":"US",
    "sg:address":"1012 3rd Ave NW",
    "sg:city":"Hickory",
    "sg:classifiers":[
        {
            "category":"Shopping",
            "type":"Retail Goods"
        }
    ],
    "sg:phone":"+1 828 324 4000",
    "sg:postcode":"28601",
    "sg:province":"NC",
    "sg:tags":[
        "equipment",
        "telephone",
        "supply"
    ],
    "wof:name":"Uni-Com Systems",
    "wof:placetype":"venue"
},
  "geometry": {"coordinates":[-81.357145,35.735808],"type":"Point"}
}