{
  "type": "Feature",
  "properties": {
    "addr:full":"608 E E St Butner NC 27509",
    "addr:housenumber":"608",
    "addr:postcode":"27509",
    "addr:street":"E E St",
    "iso:country":"US",
    "sg:address":"608 E E St",
    "sg:city":"Butner",
    "sg:classifiers":[
        {
            "category":"Organizations",
            "subcategory":"Membership Organization",
            "type":"Services"
        }
    ],
    "sg:phone":"+1   ",
    "sg:postcode":"27509",
    "sg:province":"NC",
    "wof:name":"Zone Zlous Orgnzed Nat Educatn",
    "wof:placetype":"venue"
},
  "geometry": {"coordinates":[-78.75415099999999,36.143885],"type":"Point"}
}