{
  "type": "Feature",
  "properties": {
    "iso:country":"US",
    "sg:address":"1114 Instrument Dr",
    "sg:city":"Rocky Mount",
    "sg:classifiers":[
        {
            "category":"Communications",
            "subcategory":"Film & Video Production",
            "type":"Services"
        }
    ],
    "sg:phone":"+1   ",
    "sg:postcode":"27804",
    "sg:province":"NC",
    "sg:tags":[
        "motion"
    ],
    "wof:name":"Greiner Specialty Products LLC",
    "wof:placetype":"venue"
},
  "geometry": {"coordinates":[-77.787933,36.00693],"type":"Point"}
}