{
  "type": "Feature",
  "properties": {
    "iso:country":"US",
    "sg:address":"117 Gaines St",
    "sg:city":"Aberdeen",
    "sg:classifiers":[
        {
            "category":"Home & Garden",
            "subcategory":"Home Furnishings",
            "type":"Retail Goods"
        }
    ],
    "sg:phone":"+1 910 215 0538",
    "sg:postcode":"28374",
    "sg:province":"NC",
    "sg:tags":[
        "curtain",
        "made",
        "drapery"
    ],
    "wof:name":"Sewing By Faith Designer",
    "wof:placetype":"venue"
},
  "geometry": {"coordinates":[-79.471593,35.167667],"type":"Point"}
}