{
  "type": "Feature",
  "properties": {
    "iso:country":"US",
    "sg:address":"8244 Deverow Ct",
    "sg:city":"Lewisville",
    "sg:classifiers":[
        {
            "category":"Professional",
            "subcategory":"Management & Consulting",
            "type":"Services"
        }
    ],
    "sg:phone":"+1   ",
    "sg:postcode":"27023",
    "sg:province":"NC",
    "sg:tags":[
        "agency",
        "advertising"
    ],
    "wof:name":"Marketing Impact Inc",
    "wof:placetype":"venue"
},
  "geometry": {"coordinates":[-80.425889,36.109689],"type":"Point"}
}