{
  "type": "Feature",
  "properties": {
    "addr:full":"9709 Waterwood Ct Wake Forest NC 27587",
    "addr:housenumber":"9709",
    "addr:postcode":"27587",
    "addr:street":"Waterwood Ct",
    "iso:country":"US",
    "sg:address":"9709 Waterwood Ct",
    "sg:city":"Wake Forest",
    "sg:classifiers":[
        {
            "category":"Retail",
            "subcategory":"Repair Shop",
            "type":"Services"
        },
        {
            "category":"Shopping",
            "subcategory":"Crafts & Fabrics",
            "type":"Retail Goods"
        }
    ],
    "sg:phone":"+1 919 870 7207",
    "sg:postcode":"27587",
    "sg:province":"NC",
    "sg:tags":[
        "sewing",
        "cushion"
    ],
    "wof:name":"Francines Pillows & Upholstery",
    "wof:placetype":"venue"
},
  "geometry": {"coordinates":[-78.580974,35.936511],"type":"Point"}
}