{
  "type": "Feature",
  "properties": {
    "addr:full":"15 Loop Rd Arden NC 28715",
    "addr:housenumber":"15",
    "addr:postcode":"28715",
    "addr:street":"Loop Rd",
    "iso:country":"US",
    "sg:address":"15 Loop Rd",
    "sg:city":"Arden",
    "sg:classifiers":[
        {
            "category":"Building & Trades",
            "subcategory":"Plumbing",
            "type":"Services"
        }
    ],
    "sg:phone":"+1 828 681 8801",
    "sg:postcode":"28715",
    "sg:province":"NC",
    "sg:tags":[
        "contractor",
        "mechanical"
    ],
    "wof:name":"Predictive Maintenance Technol",
    "wof:placetype":"venue"
},
  "geometry": {"coordinates":[-82.746776,35.549808],"type":"Point"}
}