{
  "type": "Feature",
  "properties": {
    "addr:full":"133 39th Avenue Dr NW Hickory NC 28601",
    "addr:housenumber":"133",
    "addr:postcode":"28601",
    "addr:street":"39Th Avenue Dr Nw",
    "iso:country":"US",
    "sg:address":"133 39th Avenue Dr NW",
    "sg:city":"Hickory",
    "sg:classifiers":[
        {
            "category":"Shopping",
            "subcategory":"Florist",
            "type":"Retail Goods"
        }
    ],
    "sg:phone":"+1 828 324 0897",
    "sg:postcode":"28601",
    "sg:province":"NC",
    "wof:name":"Raby's Florist & Greenhouses",
    "wof:placetype":"venue"
},
  "geometry": {"coordinates":[-81.327409,35.788057],"type":"Point"}
}