{
  "type": "Feature",
  "properties": {
    "iso:country":"US",
    "sg:address":"200 Mill Creek Rd",
    "sg:city":"Franklin",
    "sg:classifiers":[
        {
            "category":"Retail",
            "subcategory":"Laundry & Dry Cleaning",
            "type":"Services"
        },
        {
            "category":"Building & Trades",
            "subcategory":"Cleaning & Sanitation",
            "type":"Services"
        }
    ],
    "sg:phone":"+1 828 524 6902",
    "sg:postcode":"28734",
    "sg:province":"NC",
    "sg:tags":[
        "cleaner",
        "upholstery",
        "rug",
        "carpet"
    ],
    "sg:website":"http://www.chemdry.com",
    "wof:name":"Chem-Dry",
    "wof:placetype":"venue"
},
  "geometry": {"coordinates":[-83.454292,35.165046],"type":"Point"}
}