{
  "type": "Feature",
  "properties": {
    "addr:full":"2724 Spring Garden Rd Winston Salem NC 27106",
    "addr:housenumber":"2724",
    "addr:postcode":"27106",
    "addr:street":"Spring Garden Rd",
    "iso:country":"US",
    "sg:address":"2724 Spring Garden Rd",
    "sg:city":"Winston Salem",
    "sg:classifiers":[
        {
            "category":"Professional",
            "subcategory":"Business Services",
            "type":"Services"
        }
    ],
    "sg:phone":"+1   ",
    "sg:postcode":"27106",
    "sg:province":"NC",
    "wof:name":"MB & Assoc",
    "wof:placetype":"venue"
},
  "geometry": {"coordinates":[-80.28944300000001,36.111401],"type":"Point"}
}