{
  "type": "Feature",
  "properties": {
    "iso:country":"US",
    "sg:address":"674 Radio Dr",
    "sg:city":"Lexington",
    "sg:classifiers":[
        {
            "category":"Food & Beverages",
            "subcategory":"Specialty",
            "type":"Retail Goods"
        }
    ],
    "sg:phone":"+1 336 249 6603",
    "sg:postcode":"27292",
    "sg:province":"NC",
    "sg:tags":[
        "health",
        "diet"
    ],
    "wof:name":"Lexington Health Foods Shoppe",
    "wof:placetype":"venue"
},
  "geometry": {"coordinates":[-80.226596,35.837996],"type":"Point"}
}