{
  "type": "Feature",
  "properties": {
    "iso:country":"US",
    "sg:address":"2332 N Liberty St",
    "sg:city":"Winston Salem",
    "sg:classifiers":[
        {
            "category":"Organizations",
            "subcategory":"Community Association",
            "type":"Services"
        }
    ],
    "sg:phone":"+1 336 724 0040",
    "sg:postcode":"27105",
    "sg:province":"NC",
    "sg:tags":[
        "military"
    ],
    "wof:name":"American Legion",
    "wof:placetype":"venue"
},
  "geometry": {"coordinates":[-80.233762,36.120218],"type":"Point"}
}