{
  "type": "Feature",
  "properties": {
    "addr:full":"98 Shop Dr Marion NC 28752",
    "addr:housenumber":"98",
    "addr:postcode":"28752",
    "addr:street":"Shop Dr",
    "iso:country":"US",
    "sg:address":"98 Shop Dr",
    "sg:city":"Marion",
    "sg:classifiers":[
        {
            "category":"Government",
            "subcategory":"Office",
            "type":"Public Place"
        }
    ],
    "sg:phone":"+1 828 659 7733",
    "sg:postcode":"28752",
    "sg:province":"NC",
    "sg:tags":[
        "village"
    ],
    "wof:name":"City Of Marion Project Manager",
    "wof:placetype":"venue"
},
  "geometry": {"coordinates":[-81.99679500000001,35.675082],"type":"Point"}
}