{
  "type": "Feature",
  "properties": {
    "addr:full":"9413 Bells Valley Dr Raleigh NC 27617",
    "addr:housenumber":"9413",
    "addr:postcode":"27617",
    "addr:street":"Bells Valley Dr",
    "iso:country":"US",
    "sg:address":"9413 Bells Valley Dr",
    "sg:city":"Raleigh",
    "sg:classifiers":[
        {
            "category":"Banks & Credit Unions",
            "subcategory":"Bank",
            "type":"Services"
        }
    ],
    "sg:phone":"+1 919 676 3771",
    "sg:postcode":"27617",
    "sg:province":"NC",
    "sg:tags":[
        "short",
        "institution",
        "business"
    ],
    "wof:name":"Triangle College Funding Inc",
    "wof:placetype":"venue"
},
  "geometry": {"coordinates":[-78.73903799999999,35.912089],"type":"Point"}
}