{
  "type": "Feature",
  "properties": {
    "addr:full":"105 Pineywood St Thomasville NC 27360",
    "addr:housenumber":"105",
    "addr:postcode":"27360",
    "addr:street":"Pineywood St",
    "iso:country":"US",
    "sg:address":"105 Pineywood St",
    "sg:city":"Thomasville",
    "sg:classifiers":[
        {
            "category":"Health Services",
            "subcategory":"Medical Lab",
            "type":"Services"
        }
    ],
    "sg:phone":"+1 336 472 3600",
    "sg:postcode":"27360",
    "sg:province":"NC",
    "sg:tags":[
        "laboratory"
    ],
    "wof:name":"Laboratory Corp Of America",
    "wof:placetype":"venue"
},
  "geometry": {"coordinates":[-80.10586600000001,35.879517],"type":"Point"}
}