{
  "type": "Feature",
  "properties": {
    "addr:full":"111 S College St Boiling Springs NC 28034",
    "addr:housenumber":"111",
    "addr:postcode":"28034",
    "addr:street":"S College St",
    "iso:country":"US",
    "sg:address":"111 S College St",
    "sg:city":"Boiling Springs",
    "sg:classifiers":[
        {
            "category":"Building & Trades",
            "subcategory":"Construction",
            "type":"Services"
        }
    ],
    "sg:phone":"+1 704 434 6090",
    "sg:postcode":"28034",
    "sg:province":"NC",
    "sg:tags":[
        "tile",
        "dealer"
    ],
    "wof:name":"Artisan Tile & Granite",
    "wof:placetype":"venue"
},
  "geometry": {"coordinates":[-81.17461299999999,35.315267],"type":"Point"}
}