{
  "type": "Feature",
  "properties": {
    "iso:country":"US",
    "sg:address":"745 N Main St",
    "sg:city":"Troy",
    "sg:classifiers":[
        {
            "category":"Autos & Motor Vehicles",
            "subcategory":"Auto Supplies",
            "type":"Retail Goods"
        }
    ],
    "sg:phone":"+1 910 576 6951",
    "sg:postcode":"27371",
    "sg:province":"NC",
    "sg:tags":[
        "automobile",
        "parts"
    ],
    "wof:name":"Deaton's Auto Supply",
    "wof:placetype":"venue"
},
  "geometry": {"coordinates":[-79.89506,35.366083],"type":"Point"}
}