{
  "type": "Feature",
  "properties": {
    "addr:full":"1521 Huffman Mill Rd Burlington NC 27215",
    "addr:housenumber":"1521",
    "addr:postcode":"27215",
    "addr:street":"Huffman Mill Rd",
    "iso:country":"US",
    "sg:address":"1521 Huffman Mill Rd",
    "sg:city":"Burlington",
    "sg:classifiers":[
        {
            "category":"Building & Trades",
            "subcategory":"Construction",
            "type":"Services"
        }
    ],
    "sg:phone":"+1 336 584 1359",
    "sg:postcode":"27215",
    "sg:province":"NC",
    "sg:tags":[
        "contractor"
    ],
    "wof:name":"Indeco Properties",
    "wof:placetype":"venue"
},
  "geometry": {"coordinates":[-79.50711200000001,36.05625],"type":"Point"}
}