{
  "type": "Feature",
  "properties": {
    "iso:country":"US",
    "sg:address":"PO BOX 1007 3280 Hwy 69, Suite 11",
    "sg:city":"Hayesville",
    "sg:classifiers":[
        {
            "category":"Professional",
            "subcategory":"Computer Services",
            "type":"Services"
        }
    ],
    "sg:phone":"+1 888 777 3203",
    "sg:postcode":"28904",
    "sg:province":"NC",
    "sg:tags":[
        "diabetic-supplies",
        "diabetes-services"
    ],
    "sg:website":"http://4leafcloverdiabetics.net",
    "wof:name":"Four Leaf Clover Diabetic Supplies",
    "wof:placetype":"venue"
},
  "geometry": {"coordinates":[-83.77830899999999,35.071416],"type":"Point"}
}