{
  "type": "Feature",
  "properties": {
    "addr:full":"114 W Main St West Jefferson NC 28640",
    "addr:housenumber":"114",
    "addr:postcode":"28640",
    "addr:street":"W Main St",
    "iso:country":"US",
    "sg:address":"114 W Main St",
    "sg:city":"West Jefferson",
    "sg:classifiers":[
        {
            "category":"Retail",
            "subcategory":"Car Wash",
            "type":"Services"
        }
    ],
    "sg:phone":"+1 336 219 0200",
    "sg:postcode":"28640",
    "sg:province":"NC",
    "sg:tags":[
        "carwash",
        "polishing",
        "washing"
    ],
    "wof:name":"Jefferson Car Wash & Detail Sh",
    "wof:placetype":"venue"
},
  "geometry": {"coordinates":[-81.47653099999999,36.420607],"type":"Point"}
}