{
  "type": "Feature",
  "properties": {
    "iso:country":"US",
    "sg:address":"156 Wind Chime Ct",
    "sg:city":"Raleigh",
    "sg:classifiers":[
        {
            "category":"Restaurant",
            "type":"Food & Drink"
        }
    ],
    "sg:phone":"+1 919 383 1053",
    "sg:postcode":"27615",
    "sg:province":"NC",
    "wof:name":"Pelican Bay Restaurant",
    "wof:placetype":"venue"
},
  "geometry": {"coordinates":[-78.64277300000001,35.874435],"type":"Point"}
}