{
  "type": "Feature",
  "properties": {
    "addr:full":"1877 Cabot Cove Ct Denver NC 28037",
    "addr:housenumber":"1877",
    "addr:postcode":"28037",
    "addr:street":"Cabot Cove Ct",
    "iso:country":"US",
    "sg:address":"1877 Cabot Cove Ct",
    "sg:city":"Denver",
    "sg:classifiers":[
        {
            "category":"Shopping",
            "subcategory":"Used Merchandise",
            "type":"Retail Goods"
        }
    ],
    "sg:phone":"+1 704 483 8633",
    "sg:postcode":"28037",
    "sg:province":"NC",
    "wof:name":"Cara Seoe",
    "wof:placetype":"venue"
},
  "geometry": {"coordinates":[-80.97572099999999,35.47132],"type":"Point"}
}