{
  "type": "Feature",
  "properties": {
    "iso:country":"US",
    "sg:address":"3820 Crow Rd",
    "sg:city":"Monroe",
    "sg:classifiers":[
        {
            "category":"Professional",
            "subcategory":"Business Services",
            "type":"Services"
        }
    ],
    "sg:phone":"+1   ",
    "sg:postcode":"28112",
    "sg:province":"NC",
    "wof:name":"Otterstadt Enterprises Inc",
    "wof:placetype":"venue"
},
  "geometry": {"coordinates":[-80.637935,34.915252],"type":"Point"}
}