{
  "type": "Feature",
  "properties": {
    "addr:full":"2607 Oberlin Rd Raleigh NC 27608",
    "addr:housenumber":"2607",
    "addr:postcode":"27608",
    "addr:street":"Oberlin Rd",
    "iso:country":"US",
    "sg:address":"2607 Oberlin Rd",
    "sg:city":"Raleigh",
    "sg:classifiers":[
        {
            "category":"Professional",
            "subcategory":"Lawyer & Legal Services",
            "type":"Services"
        }
    ],
    "sg:phone":"+1 919 510 8585",
    "sg:postcode":"27608",
    "sg:province":"NC",
    "sg:tags":[
        "attorney"
    ],
    "wof:name":"Nan E Hannah",
    "wof:placetype":"venue"
},
  "geometry": {"coordinates":[-78.65603900000001,35.810106],"type":"Point"}
}