{
  "type": "Feature",
  "properties": {
    "iso:country":"US",
    "sg:address":"6223 State Hwy 62",
    "sg:city":"Trinity",
    "sg:classifiers":[
        {
            "category":"Autos & Motor Vehicles",
            "subcategory":"Auto Supplies",
            "type":"Retail Goods"
        }
    ],
    "sg:phone":"+1 336 434 1990",
    "sg:postcode":"27370",
    "sg:province":"NC",
    "sg:tags":[
        "automobile",
        "parts"
    ],
    "wof:name":"Crossen Racing Products",
    "wof:placetype":"venue"
},
  "geometry": {"coordinates":[-80.003658,35.881386],"type":"Point"}
}