{
  "type": "Feature",
  "properties": {
    "iso:country":"US",
    "sg:address":"109 Carolina Pines Blvd",
    "sg:city":"New Bern",
    "sg:classifiers":[
        {
            "category":"Government",
            "subcategory":"Fire Station",
            "type":"Public Place"
        }
    ],
    "sg:phone":"+1 252 447 2700",
    "sg:postcode":"28560",
    "sg:province":"NC",
    "sg:tags":[
        "department",
        "protection"
    ],
    "wof:name":"Township Six Fire Department",
    "wof:placetype":"venue"
},
  "geometry": {"coordinates":[-76.94662,34.957592],"type":"Point"}
}