{
  "type": "Feature",
  "properties": {
    "addr:full":"119 N Washington St Wadesboro NC 28170",
    "addr:housenumber":"119",
    "addr:postcode":"28170",
    "addr:street":"N Washington St",
    "iso:country":"US",
    "sg:address":"119 N Washington St",
    "sg:city":"Wadesboro",
    "sg:classifiers":[
        {
            "category":"Professional",
            "subcategory":"Lawyer & Legal Services",
            "type":"Services"
        }
    ],
    "sg:phone":"+1 704 694 2304",
    "sg:postcode":"28170",
    "sg:province":"NC",
    "wof:name":"Criminal Justice Partnership",
    "wof:placetype":"venue"
},
  "geometry": {"coordinates":[-80.075537,34.967115],"type":"Point"}
}