{
  "type": "Feature",
  "properties": {
    "addr:full":"668 Blowing Rock Rd Boone NC 28607",
    "addr:housenumber":"668",
    "addr:postcode":"28607",
    "addr:street":"Blowing Rock Rd",
    "iso:country":"US",
    "sg:address":"668 Blowing Rock Rd",
    "sg:city":"Boone",
    "sg:classifiers":[
        {
            "category":"Restaurant",
            "type":"Food & Drink"
        }
    ],
    "sg:menulink":"http://www.allmenus.com/nc/boone/115728-quiznos-sub/menu/",
    "sg:phone":"+1 828 264 5444",
    "sg:postcode":"28607",
    "sg:province":"NC",
    "sg:tags":[
        "wrap",
        "american",
        "sandwich"
    ],
    "wof:name":"Quiznos Sub",
    "wof:placetype":"venue"
},
  "geometry": {"coordinates":[-81.671605,36.207045],"type":"Point"}
}