{
  "type": "Feature",
  "properties": {
    "addr:full":"55 Altapass Hwy Spruce Pine NC 28777",
    "addr:housenumber":"55",
    "addr:postcode":"28777",
    "addr:street":"Altapass Hwy",
    "iso:country":"US",
    "sg:address":"55 Altapass Hwy",
    "sg:city":"Spruce Pine",
    "sg:classifiers":[
        {
            "category":"Manufacturing",
            "subcategory":"Lumber",
            "type":"Manufacturing & Wholesale Goods"
        }
    ],
    "sg:phone":"+1 828 765 2732",
    "sg:postcode":"28777",
    "sg:province":"NC",
    "sg:tags":[
        "hardwood",
        "mill"
    ],
    "wof:name":"Mitchell Lumber Inc",
    "wof:placetype":"venue"
},
  "geometry": {"coordinates":[-82.064198,35.914237],"type":"Point"}
}