{
  "type": "Feature",
  "properties": {
    "addr:full":"1616 E Bessemer Ave Greensboro NC 27405",
    "addr:housenumber":"1616",
    "addr:postcode":"27405",
    "addr:street":"E Bessemer Ave",
    "iso:country":"US",
    "sg:address":"1616 E Bessemer Ave",
    "sg:city":"Greensboro",
    "sg:classifiers":[
        {
            "category":"Banks & Credit Unions",
            "subcategory":"Bank",
            "type":"Services"
        }
    ],
    "sg:phone":"+1 336 370 3050",
    "sg:postcode":"27405",
    "sg:province":"NC",
    "sg:tags":[
        "national",
        "commercial"
    ],
    "wof:name":"Bank Of America",
    "wof:placetype":"venue"
},
  "geometry": {"coordinates":[-79.76487899999999,36.084745],"type":"Point"}
}