{
  "type": "Feature",
  "properties": {
    "addr:full":"1222 Hillsborough Rd Chapel Hill NC 27516",
    "addr:housenumber":"1222",
    "addr:postcode":"27516",
    "addr:street":"Hillsborough Rd",
    "iso:country":"US",
    "sg:address":"1222 Hillsborough Rd",
    "sg:city":"Chapel Hill",
    "sg:classifiers":[
        {
            "category":"Communications",
            "subcategory":"Film & Video Production",
            "type":"Services"
        }
    ],
    "sg:phone":"+1   ",
    "sg:postcode":"27516",
    "sg:province":"NC",
    "sg:tags":[
        "motion"
    ],
    "wof:name":"Ballistic Productions",
    "wof:placetype":"venue"
},
  "geometry": {"coordinates":[-79.095141,35.92872],"type":"Point"}
}