{
  "type": "Feature",
  "properties": {
    "iso:country":"US",
    "sg:address":"7709 University City Blvd",
    "sg:city":"Charlotte",
    "sg:classifiers":[
        {
            "category":"Autos & Motor Vehicles",
            "subcategory":"Auto Supplies",
            "type":"Retail Goods"
        }
    ],
    "sg:phone":"+1 704 599 6603",
    "sg:postcode":"28213",
    "sg:province":"NC",
    "sg:tags":[
        "repair",
        "brake",
        "tire"
    ],
    "sg:website":"http://www.tirekingdom.com",
    "wof:name":"Tire Kingdom",
    "wof:placetype":"venue"
},
  "geometry": {"coordinates":[-80.753692,35.291607],"type":"Point"}
}