{
  "type": "Feature",
  "properties": {
    "addr:full":"933 Gurley Dairy Rd Pikeville NC 27863",
    "addr:housenumber":"933",
    "addr:postcode":"27863",
    "addr:street":"Gurley Dairy Rd",
    "iso:country":"US",
    "sg:address":"933 Gurley Dairy Rd",
    "sg:city":"Pikeville",
    "sg:classifiers":[
        {
            "category":"Professional",
            "type":"Services"
        }
    ],
    "sg:phone":"+1 919 734 5358",
    "sg:postcode":"27863",
    "sg:province":"NC",
    "wof:name":"Edgerton Corp",
    "wof:placetype":"venue"
},
  "geometry": {"coordinates":[-78.073049,35.469241],"type":"Point"}
}