{
  "type": "Feature",
  "properties": {
    "addr:full":"20 Redbud Ln Bakersville NC 28705",
    "addr:housenumber":"20",
    "addr:postcode":"28705",
    "addr:street":"Redbud Ln",
    "iso:country":"US",
    "sg:address":"20 Redbud Ln",
    "sg:city":"Bakersville",
    "sg:classifiers":[
        {
            "category":"Professional",
            "subcategory":"Management & Consulting",
            "type":"Services"
        }
    ],
    "sg:phone":"+1   ",
    "sg:postcode":"28705",
    "sg:province":"NC",
    "sg:tags":[
        "business"
    ],
    "wof:name":"Myvendicom",
    "wof:placetype":"venue"
},
  "geometry": {"coordinates":[-82.11701100000001,36.04164],"type":"Point"}
}