{
  "type": "Feature",
  "properties": {
    "iso:country":"US",
    "sg:address":"14971 Scothurst Ln",
    "sg:city":"Charlotte",
    "sg:classifiers":[
        {
            "category":"Professional",
            "subcategory":"Advertising",
            "type":"Services"
        }
    ],
    "sg:phone":"+1 704 544 7829",
    "sg:postcode":"28277",
    "sg:province":"NC",
    "sg:tags":[
        "picture"
    ],
    "wof:name":"National Cine Media",
    "wof:placetype":"venue"
},
  "geometry": {"coordinates":[-80.850779,35.041972],"type":"Point"}
}