{
  "type": "Feature",
  "properties": {
    "addr:full":"3701 National Dr Raleigh NC 27612",
    "addr:housenumber":"3701",
    "addr:postcode":"27612",
    "addr:street":"National Dr",
    "iso:country":"US",
    "sg:address":"3701 National Dr",
    "sg:city":"Raleigh",
    "sg:classifiers":[
        {
            "category":"Professional",
            "subcategory":"Business Services",
            "type":"Services"
        }
    ],
    "sg:phone":"+1 919 782 1110",
    "sg:postcode":"27612",
    "sg:province":"NC",
    "sg:tags":[
        "brokerage",
        "commercial",
        "real estate"
    ],
    "wof:name":"Kimball & Company Rest Svcs",
    "wof:placetype":"venue"
},
  "geometry": {"coordinates":[-78.665983,35.831897],"type":"Point"}
}