{
  "type": "Feature",
  "properties": {
    "iso:country":"US",
    "sg:address":"2307 Deep Creek Church Rd",
    "sg:city":"Burlington",
    "sg:classifiers":[
        {
            "category":"Building & Trades",
            "subcategory":"Construction",
            "type":"Services"
        }
    ],
    "sg:phone":"+1 336 578 2931",
    "sg:postcode":"27217",
    "sg:province":"NC",
    "sg:tags":[
        "water",
        "line",
        "sewer"
    ],
    "wof:name":"C & J Utilities Inc",
    "wof:placetype":"venue"
},
  "geometry": {"coordinates":[-79.369786,36.144545],"type":"Point"}
}