{
  "type": "Feature",
  "properties": {
    "iso:country":"US",
    "sg:address":"6701 N Tryon St Ste U",
    "sg:city":"Charlotte",
    "sg:classifiers":[
        {
            "category":"Insurance",
            "subcategory":"Hazard Insurance",
            "type":"Services"
        }
    ],
    "sg:phone":"+1 704 596 9991",
    "sg:postcode":"28213",
    "sg:province":"NC",
    "sg:website":"http://mitchellinsurancesvcs.com",
    "wof:name":"Mitchell Insurance Services",
    "wof:placetype":"venue"
},
  "geometry": {"coordinates":[-80.765871,35.279777],"type":"Point"}
}