{
  "type": "Feature",
  "properties": {
    "addr:full":"2700 Mount Olivet Rd Zirconia NC 28790",
    "addr:housenumber":"2700",
    "addr:postcode":"28790",
    "addr:street":"Mount Olivet Rd",
    "iso:country":"US",
    "sg:address":"2700 Mount Olivet Rd",
    "sg:city":"Zirconia",
    "sg:classifiers":[
        {
            "category":"Professional",
            "subcategory":"Management & Consulting",
            "type":"Services"
        }
    ],
    "sg:phone":"+1   ",
    "sg:postcode":"28790",
    "sg:province":"NC",
    "sg:tags":[
        "business"
    ],
    "wof:name":"Thomas Hill-Consultg",
    "wof:placetype":"venue"
},
  "geometry": {"coordinates":[-82.468653,35.234766],"type":"Point"}
}