{
  "type": "Feature",
  "properties": {
    "addr:full":"1840 W Deep Creek Rd Bryson City NC 28713",
    "addr:housenumber":"1840",
    "addr:postcode":"28713",
    "addr:street":"W Deep Creek Rd",
    "iso:country":"US",
    "sg:address":"1840 W Deep Creek Rd",
    "sg:city":"Bryson City",
    "sg:classifiers":[
        {
            "category":"Travel",
            "subcategory":"Campground",
            "type":"Entertainment"
        }
    ],
    "sg:phone":"+1 828 488 3302",
    "sg:postcode":"28713",
    "sg:province":"NC",
    "sg:tags":[
        "camp"
    ],
    "sg:website":"www.smokymtncampground.com",
    "wof:name":"Smokey Mountain Campground",
    "wof:placetype":"venue"
},
  "geometry": {"coordinates":[-83.438305,35.457775],"type":"Point"}
}