{
  "type": "Feature",
  "properties": {
    "addr:full":"6105 Oleander Dr Wilmington NC 28403",
    "addr:housenumber":"6105",
    "addr:postcode":"28403",
    "addr:street":"Oleander Dr",
    "iso:country":"US",
    "sg:address":"6105 Oleander Dr",
    "sg:city":"Wilmington",
    "sg:classifiers":[
        {
            "category":"Banks & Credit Unions",
            "subcategory":"Bank",
            "type":"Services"
        }
    ],
    "sg:phone":"+1 910 452 1774",
    "sg:postcode":"28403",
    "sg:province":"NC",
    "wof:name":"East Carolina Bank",
    "wof:placetype":"venue"
},
  "geometry": {"coordinates":[-77.837012,34.210319],"type":"Point"}
}