{
  "type": "Feature",
  "properties": {
    "addr:full":"2425 Park Rd Charlotte NC 28203",
    "addr:housenumber":"2425",
    "addr:postcode":"28203",
    "addr:street":"Park Rd",
    "iso:country":"US",
    "sg:address":"2425 Park Rd",
    "sg:city":"Charlotte",
    "sg:classifiers":[
        {
            "category":"Recreation",
            "type":"Entertainment"
        }
    ],
    "sg:phone":"+1 704 334 3900",
    "sg:postcode":"28203",
    "sg:province":"NC",
    "sg:tags":[
        "club",
        "membership"
    ],
    "wof:name":"Mecklenbrg Amtur Radio Scty",
    "wof:placetype":"venue"
},
  "geometry": {"coordinates":[-80.851545,35.197082],"type":"Point"}
}