{
  "type": "Feature",
  "properties": {
    "iso:country":"US",
    "sg:address":"215 W Ketchie St",
    "sg:city":"China Grove",
    "sg:classifiers":[
        {
            "category":"Professional",
            "type":"Services"
        }
    ],
    "sg:phone":"+1 704 857 3219",
    "sg:postcode":"28023",
    "sg:province":"NC",
    "wof:name":"Doug McDonald",
    "wof:placetype":"venue"
},
  "geometry": {"coordinates":[-80.577816,35.572966],"type":"Point"}
}