{
  "type": "Feature",
  "properties": {
    "iso:country":"US",
    "sg:address":"110 N Bridge St",
    "sg:city":"Elkin",
    "sg:classifiers":[
        {
            "category":"Real Estate",
            "subcategory":"Real Estate Agent",
            "type":"Services"
        }
    ],
    "sg:phone":"+1 336 527 1718",
    "sg:postcode":"28621",
    "sg:province":"NC",
    "wof:name":"Golden Key Realty",
    "wof:placetype":"venue"
},
  "geometry": {"coordinates":[-80.850842,36.244796],"type":"Point"}
}