{
  "type": "Feature",
  "properties": {
    "addr:full":"6120 River Run Dr Marshville NC 28103",
    "addr:housenumber":"6120",
    "addr:postcode":"28103",
    "addr:street":"River Run Dr",
    "iso:country":"US",
    "sg:address":"6120 River Run Dr",
    "sg:city":"Marshville",
    "sg:classifiers":[
        {
            "category":"Professional",
            "subcategory":"Business Services",
            "type":"Services"
        }
    ],
    "sg:phone":"+1   ",
    "sg:postcode":"28103",
    "sg:province":"NC",
    "wof:name":"Danco Interior Syste",
    "wof:placetype":"venue"
},
  "geometry": {"coordinates":[-80.332111,35.166297],"type":"Point"}
}