{
  "type": "Feature",
  "properties": {
    "addr:full":"8802 Reed Dr Emerald Isle NC 28594",
    "addr:housenumber":"8802",
    "addr:postcode":"28594",
    "addr:street":"Reed Dr",
    "iso:country":"US",
    "sg:address":"8802 Reed Dr",
    "sg:city":"Emerald Isle",
    "sg:classifiers":[
        {
            "category":"Restaurant",
            "type":"Food & Drink"
        }
    ],
    "sg:phone":"+1 252 354 8721",
    "sg:postcode":"28594",
    "sg:province":"NC",
    "wof:name":"Royale Gargoyle Pub & Rstrnt",
    "wof:placetype":"venue"
},
  "geometry": {"coordinates":[-77.050551,34.660651],"type":"Point"}
}