{
  "type": "Feature",
  "properties": {
    "iso:country":"US",
    "sg:address":"1685 Wendell Griffin Rd",
    "sg:city":"Williamston",
    "sg:classifiers":[
        {
            "category":"Building & Trades",
            "subcategory":"Construction",
            "type":"Services"
        }
    ],
    "sg:phone":"+1 252 792 8531",
    "sg:postcode":"27892",
    "sg:province":"NC",
    "sg:tags":[
        "house"
    ],
    "wof:name":"Griffin Islands Cnstr Co",
    "wof:placetype":"venue"
},
  "geometry": {"coordinates":[-76.956109,35.826935],"type":"Point"}
}