{
  "type": "Feature",
  "properties": {
    "iso:country":"US",
    "sg:address":"300 W Parkway Ave",
    "sg:city":"High Point",
    "sg:classifiers":[
        {
            "category":"Professional",
            "subcategory":"Management & Consulting",
            "type":"Services"
        }
    ],
    "sg:phone":"+1   ",
    "sg:postcode":"27262",
    "sg:province":"NC",
    "sg:tags":[
        "business"
    ],
    "wof:name":"Deering Service",
    "wof:placetype":"venue"
},
  "geometry": {"coordinates":[-80.01703500000001,35.967248],"type":"Point"}
}