{
  "type": "Feature",
  "properties": {
    "addr:full":"3975 Market St Wilmington NC 28403",
    "addr:housenumber":"3975",
    "addr:postcode":"28403",
    "addr:street":"Market St",
    "iso:country":"US",
    "sg:address":"3975 Market St",
    "sg:city":"Wilmington",
    "sg:classifiers":[
        {
            "category":"Health Services",
            "subcategory":"Clinic",
            "type":"Services"
        }
    ],
    "sg:phone":"+1 910 342 9200",
    "sg:postcode":"28403",
    "sg:province":"NC",
    "sg:tags":[
        "home"
    ],
    "sg:website":"www.comfortkeepers.com",
    "wof:name":"Comfort Keepers",
    "wof:placetype":"venue"
},
  "geometry": {"coordinates":[-77.897317,34.241503],"type":"Point"}
}