{
  "type": "Feature",
  "properties": {
    "iso:country":"US",
    "sg:address":"2201 New Hope Church Rd",
    "sg:city":"Raleigh",
    "sg:classifiers":[
        {
            "category":"Food & Beverages",
            "subcategory":"Groceries & Convenience Stores",
            "type":"Retail Goods"
        },
        {
            "category":"Autos & Motor Vehicles",
            "subcategory":"Fuel & Gas Station",
            "type":"Retail Goods"
        }
    ],
    "sg:phone":"+1 919 876 3895",
    "sg:postcode":"27604",
    "sg:province":"NC",
    "sg:tags":[
        "grocer",
        "station",
        "gasoline"
    ],
    "wof:name":"Grocery Boy Junior",
    "wof:placetype":"venue"
},
  "geometry": {"coordinates":[-78.599125,35.835049],"type":"Point"}
}