{
  "type": "Feature",
  "properties": {
    "addr:full":"5009 Coburn Ct Charlotte NC 28277",
    "addr:housenumber":"5009",
    "addr:postcode":"28277",
    "addr:street":"Coburn Ct",
    "iso:country":"US",
    "sg:address":"5009 Coburn Ct",
    "sg:city":"Charlotte",
    "sg:classifiers":[
        {
            "category":"Organizations",
            "subcategory":"Membership Organization",
            "type":"Services"
        }
    ],
    "sg:phone":"+1   ",
    "sg:postcode":"28277",
    "sg:province":"NC",
    "wof:name":"Amigo A Amigo",
    "wof:placetype":"venue"
},
  "geometry": {"coordinates":[-80.808892,35.084077],"type":"Point"}
}