{
  "type": "Feature",
  "properties": {
    "addr:full":"4010 Shinnecock Dr New Bern NC 28562",
    "addr:postcode":"4010;28562",
    "addr:street":"Shinnecock Dr",
    "iso:country":"US",
    "sg:address":"4010 Shinnecock Dr",
    "sg:city":"New Bern",
    "sg:classifiers":[
        {
            "category":"Banks & Credit Unions",
            "subcategory":"Investment Brokerage",
            "type":"Services"
        }
    ],
    "sg:phone":"+1 252 633 5419",
    "sg:postcode":"28562",
    "sg:province":"NC",
    "sg:tags":[
        "advisory"
    ],
    "wof:name":"Jordan Associates",
    "wof:placetype":"venue"
},
  "geometry": {"coordinates":[-77.11374000000001,35.108924],"type":"Point"}
}