{
  "type": "Feature",
  "properties": {
    "addr:full":"104 Pinewood Cir Belmont NC 28012",
    "addr:housenumber":"104",
    "addr:postcode":"28012",
    "addr:street":"Pinewood Cir",
    "iso:country":"US",
    "sg:address":"104 Pinewood Cir",
    "sg:city":"Belmont",
    "sg:classifiers":[
        {
            "category":"Building & Trades",
            "subcategory":"Plumbing",
            "type":"Services"
        }
    ],
    "sg:phone":"+1 704 827 9903",
    "sg:postcode":"28012",
    "sg:province":"NC",
    "sg:tags":[
        "contractor"
    ],
    "wof:name":"Cauthens Backhoe Service",
    "wof:placetype":"venue"
},
  "geometry": {"coordinates":[-81.05510200000001,35.276191],"type":"Point"}
}