{
  "type": "Feature",
  "properties": {
    "iso:country":"US",
    "sg:address":"36414 Millingport Rd",
    "sg:city":"New London",
    "sg:classifiers":[
        {
            "category":"Professional",
            "subcategory":"Management & Consulting",
            "type":"Services"
        }
    ],
    "sg:phone":"+1   ",
    "sg:postcode":"28127",
    "sg:province":"NC",
    "wof:name":"Innovative Communications Svcs",
    "wof:placetype":"venue"
},
  "geometry": {"coordinates":[-80.299177,35.406504],"type":"Point"}
}