{
  "type": "Feature",
  "properties": {
    "addr:full":"828 Salisbury Rd Statesville NC 28677",
    "addr:housenumber":"828",
    "addr:postcode":"28677",
    "addr:street":"Salisbury Rd",
    "iso:country":"US",
    "sg:address":"828 Salisbury Rd",
    "sg:city":"Statesville",
    "sg:classifiers":[
        {
            "category":"Mining & Drilling",
            "type":"Manufacturing & Wholesale Goods"
        }
    ],
    "sg:phone":"+1 704 873 8151",
    "sg:postcode":"28677",
    "sg:province":"NC",
    "sg:tags":[
        "oil",
        "gas",
        "producer"
    ],
    "wof:name":"Quality Oil Co",
    "wof:placetype":"venue"
},
  "geometry": {"coordinates":[-80.871737,35.776175],"type":"Point"}
}