{
  "type": "Feature",
  "properties": {
    "addr:full":"3930 Mount Carmel Rd Carthage NC 28327",
    "addr:housenumber":"3930",
    "addr:postcode":"28327",
    "addr:street":"Mount Carmel Rd",
    "iso:country":"US",
    "sg:address":"3930 Mount Carmel Rd",
    "sg:city":"Carthage",
    "sg:phone":"+1 910 947 2293",
    "sg:postcode":"28327",
    "sg:province":"NC",
    "sg:tags":[
        "farm",
        "tobacco"
    ],
    "wof:name":"Harris Farms",
    "wof:placetype":"venue"
},
  "geometry": {"coordinates":[-79.53605,35.304967],"type":"Point"}
}