{
  "type": "Feature",
  "properties": {
    "iso:country":"US",
    "sg:address":"143 Gasper Ct",
    "sg:city":"Clayton",
    "sg:classifiers":[
        {
            "category":"Building & Trades",
            "subcategory":"Construction",
            "type":"Services"
        }
    ],
    "sg:phone":"+1 919 553 0513",
    "sg:postcode":"27527",
    "sg:province":"NC",
    "sg:tags":[
        "house"
    ],
    "wof:name":"Jarman Homes Inc",
    "wof:placetype":"venue"
},
  "geometry": {"coordinates":[-76.614114,36.320433],"type":"Point"}
}