{
  "type": "Feature",
  "properties": {
    "iso:country":"US",
    "sg:address":"1307 Glenwood Ave",
    "sg:city":"Raleigh",
    "sg:classifiers":[
        {
            "category":"Professional",
            "subcategory":"Art Services",
            "type":"Services"
        },
        {
            "category":"Manufacturing",
            "subcategory":"Printing",
            "type":"Manufacturing & Wholesale Goods"
        }
    ],
    "sg:phone":"+1 919 832 9311",
    "sg:postcode":"27605",
    "sg:province":"NC",
    "sg:tags":[
        "graphic",
        "production",
        "design",
        "designer",
        "typesetting"
    ],
    "wof:name":"Publications Unlimited",
    "wof:placetype":"venue"
},
  "geometry": {"coordinates":[-78.646348,35.796515],"type":"Point"}
}