{
  "type": "Feature",
  "properties": {
    "addr:full":"809 Georgetown Dr Charlotte NC 28213",
    "addr:housenumber":"809",
    "addr:postcode":"28213",
    "addr:street":"Georgetown Dr",
    "iso:country":"US",
    "sg:address":"809 Georgetown Dr",
    "sg:city":"Charlotte",
    "sg:classifiers":[
        {
            "category":"Shopping",
            "type":"Retail Goods"
        }
    ],
    "sg:phone":"+1 704 596 8207",
    "sg:postcode":"28213",
    "sg:province":"NC",
    "sg:tags":[
        "merchandise"
    ],
    "wof:name":"Bradford Thrift Shop",
    "wof:placetype":"venue"
},
  "geometry": {"coordinates":[-80.776308,35.273076],"type":"Point"}
}