{
  "type": "Feature",
  "properties": {
    "addr:full":"105 Riverbirch Pt Carrboro NC 27510",
    "addr:housenumber":"105",
    "addr:postcode":"27510",
    "addr:street":"Riverbirch Pt",
    "iso:country":"US",
    "sg:address":"105 Riverbirch Pt",
    "sg:city":"Carrboro",
    "sg:classifiers":[
        {
            "category":"Restaurant",
            "type":"Food & Drink"
        }
    ],
    "sg:phone":"+1 919 929 2288",
    "sg:postcode":"27510",
    "sg:province":"NC",
    "sg:tags":[
        "eating"
    ],
    "wof:name":"Carrboro Subway Inc",
    "wof:placetype":"venue"
},
  "geometry": {"coordinates":[-79.08223599999999,35.900035],"type":"Point"}
}