{
  "type": "Feature",
  "properties": {
    "addr:full":"210 E Trade St Charlotte NC 28202",
    "addr:housenumber":"210",
    "addr:postcode":"28202",
    "addr:street":"E Trade St",
    "iso:country":"US",
    "sg:address":"210 E Trade St",
    "sg:city":"Charlotte",
    "sg:classifiers":[
        {
            "category":"Utilities",
            "subcategory":"Mobile Phone",
            "type":"Services"
        },
        {
            "category":"Shopping",
            "subcategory":"Mobile Phones",
            "type":"Retail Goods"
        },
        {
            "category":"Communications",
            "type":"Services"
        },
        {
            "category":"Internet Cafe",
            "subcategory":"None",
            "type":"Food & Drink"
        }
    ],
    "sg:phone":"+1 704 971 2637",
    "sg:postcode":"28202",
    "sg:province":"NC",
    "sg:tags":[
        "supply",
        "telephone",
        "wireless",
        "equipment",
        "paging",
        "signaling",
        "cellular",
        "provider"
    ],
    "sg:website":"http://www.att.com",
    "wof:name":"AT&T",
    "wof:placetype":"venue"
},
  "geometry": {"coordinates":[-80.84186099999999,35.226163],"type":"Point"}
}