{
  "type": "Feature",
  "properties": {
    "iso:country":"US",
    "sg:address":"310 Clayton Dr",
    "sg:city":"Mocksville",
    "sg:classifiers":[
        {
            "category":"Health Services",
            "subcategory":"Doctor",
            "type":"Services"
        }
    ],
    "sg:phone":"+1   ",
    "sg:postcode":"27028",
    "sg:province":"NC",
    "wof:name":"James B West DDS Inc",
    "wof:placetype":"venue"
},
  "geometry": {"coordinates":[-80.559393,35.985768],"type":"Point"}
}