{
  "type": "Feature",
  "properties": {
    "addr:full":"611 Batchelor Rd Sharpsburg NC 27878",
    "addr:housenumber":"611",
    "addr:postcode":"27878",
    "addr:street":"Batchelor Rd",
    "iso:country":"US",
    "sg:address":"611 Batchelor Rd",
    "sg:city":"Sharpsburg",
    "sg:classifiers":[
        {
            "category":"Wholesale",
            "subcategory":"Chemicals & Plastics",
            "type":"Manufacturing & Wholesale Goods"
        }
    ],
    "sg:phone":"+1 252 446 9591",
    "sg:postcode":"27878",
    "sg:province":"NC",
    "sg:tags":[
        "cleaning",
        "compound"
    ],
    "wof:name":"Stanley Home Products",
    "wof:placetype":"venue"
},
  "geometry": {"coordinates":[-77.82388899999999,35.868728],"type":"Point"}
}