{
  "type": "Feature",
  "properties": {
    "iso:country":"US",
    "sg:address":"7057 Beach Dr SW",
    "sg:city":"Ocean Isle Beach",
    "sg:classifiers":[
        {
            "category":"Building & Trades",
            "subcategory":"Construction",
            "type":"Services"
        }
    ],
    "sg:phone":"+1 910 579 0283",
    "sg:postcode":"28469",
    "sg:province":"NC",
    "sg:tags":[
        "home",
        "builder"
    ],
    "wof:name":"Elite Homes-Forrest Taylor Inc",
    "wof:placetype":"venue"
},
  "geometry": {"coordinates":[-78.476733,33.898537],"type":"Point"}
}