{
  "type": "Feature",
  "properties": {
    "addr:full":"3033 Slocomb Rd Linden NC 28356",
    "addr:housenumber":"3033",
    "addr:postcode":"28356",
    "addr:street":"Slocomb Rd",
    "iso:country":"US",
    "sg:address":"3033 Slocomb Rd",
    "sg:city":"Linden",
    "sg:classifiers":[
        {
            "category":"Building & Trades",
            "subcategory":"Cleaning & Sanitation",
            "type":"Services"
        }
    ],
    "sg:phone":"+1 910 980 0879",
    "sg:postcode":"28356",
    "sg:province":"NC",
    "sg:tags":[
        "commercial"
    ],
    "wof:name":"Jani-King",
    "wof:placetype":"venue"
},
  "geometry": {"coordinates":[-78.781699,35.187847],"type":"Point"}
}