{
  "type": "Feature",
  "properties": {
    "addr:full":"2630 Vega Ct Raleigh NC 27614",
    "addr:housenumber":"2630",
    "addr:postcode":"27614",
    "addr:street":"Vega Ct",
    "iso:country":"US",
    "sg:address":"2630 Vega Ct",
    "sg:city":"Raleigh",
    "sg:classifiers":[
        {
            "category":"Home & Garden",
            "subcategory":"Furniture",
            "type":"Retail Goods"
        }
    ],
    "sg:phone":"+1 919 601 5677",
    "sg:postcode":"27614",
    "sg:province":"NC",
    "sg:tags":[
        "cabinet"
    ],
    "wof:name":"Wayne's Repair World",
    "wof:placetype":"venue"
},
  "geometry": {"coordinates":[-78.560631,35.937189],"type":"Point"}
}