{
  "type": "Feature",
  "properties": {
    "addr:full":"1925 Aiken Ave Durham NC 27704",
    "addr:housenumber":"1925",
    "addr:postcode":"27704",
    "addr:street":"Aiken Ave",
    "iso:country":"US",
    "sg:address":"1925 Aiken Ave",
    "sg:city":"Durham",
    "sg:classifiers":[
        {
            "category":"Professional",
            "subcategory":"Business Services",
            "type":"Services"
        }
    ],
    "sg:phone":"+1   ",
    "sg:postcode":"27704",
    "sg:province":"NC",
    "wof:name":"Midgette Enterprises",
    "wof:placetype":"venue"
},
  "geometry": {"coordinates":[-78.864513,36.00982],"type":"Point"}
}