{
  "type": "Feature",
  "properties": {
    "addr:full":"3442 Crowder Ridge Rd Shelby NC 28150",
    "addr:housenumber":"3442",
    "addr:postcode":"28150",
    "addr:street":"Crowder Ridge Rd",
    "iso:country":"US",
    "sg:address":"3442 Crowder Ridge Rd",
    "sg:city":"Shelby",
    "sg:classifiers":[
        {
            "category":"Professional",
            "subcategory":"Business Services",
            "type":"Services"
        },
        {
            "category":"Manufacturing",
            "subcategory":"Printing",
            "type":"Manufacturing & Wholesale Goods"
        }
    ],
    "sg:phone":"+1 704 538 3019",
    "sg:postcode":"28150",
    "sg:province":"NC",
    "sg:tags":[
        "commercial",
        "embroidery"
    ],
    "wof:name":"Cal Dan Promotional Products",
    "wof:placetype":"venue"
},
  "geometry": {"coordinates":[-81.66712699999999,35.397433],"type":"Point"}
}