{
  "type": "Feature",
  "properties": {
    "iso:country":"US",
    "sg:address":"8540 University City Blvd",
    "sg:city":"Charlotte",
    "sg:classifiers":[
        {
            "category":"Personal",
            "subcategory":"Beauty Salon",
            "type":"Services"
        }
    ],
    "sg:phone":"+1 704 503 5600",
    "sg:postcode":"28213",
    "sg:province":"NC",
    "sg:tags":[
        "shop"
    ],
    "sg:website":"http://www.saloncharlottehaircare.com",
    "wof:name":"Salon Charlotte",
    "wof:placetype":"venue"
},
  "geometry": {"coordinates":[-80.740489,35.296992],"type":"Point"}
}