{
  "type": "Feature",
  "properties": {
    "iso:country":"US",
    "sg:address":"1363 Oquinn Rd",
    "sg:city":"Sanford",
    "sg:classifiers":[
        {
            "category":"Professional",
            "subcategory":"Management & Consulting",
            "type":"Services"
        }
    ],
    "sg:phone":"+1 919 774 7874",
    "sg:postcode":"27330",
    "sg:province":"NC",
    "sg:tags":[
        "party",
        "planning"
    ],
    "wof:name":"S & T Concession Stand",
    "wof:placetype":"venue"
},
  "geometry": {"coordinates":[-79.12231199999999,35.469446],"type":"Point"}
}