{
  "type": "Feature",
  "properties": {
    "iso:country":"US",
    "sg:address":"122 Gradys Farm Dr",
    "sg:city":"Mooresville",
    "sg:classifiers":[
        {
            "category":"Building & Trades",
            "subcategory":"Landscaping Services",
            "type":"Services"
        }
    ],
    "sg:phone":"+1 704 896 2108",
    "sg:postcode":"28115",
    "sg:province":"NC",
    "wof:name":"Carolina Aboriculture",
    "wof:placetype":"venue"
},
  "geometry": {"coordinates":[-80.824895,35.527432],"type":"Point"}
}