{
  "type": "Feature",
  "properties": {
    "addr:full":"343 New Leicester Hwy Asheville NC 28806",
    "addr:housenumber":"343",
    "addr:postcode":"28806",
    "addr:street":"New Leicester Hwy",
    "iso:country":"US",
    "sg:address":"343 New Leicester Hwy",
    "sg:city":"Asheville",
    "sg:classifiers":[
        {
            "category":"Restaurant",
            "type":"Food & Drink"
        }
    ],
    "sg:phone":"+1 828 285 8929",
    "sg:postcode":"28806",
    "sg:province":"NC",
    "sg:website":"www.mcdonalds.com",
    "wof:name":"Mc Donald's",
    "wof:placetype":"venue"
},
  "geometry": {"coordinates":[-82.62336500000001,35.601555],"type":"Point"}
}