{
  "type": "Feature",
  "properties": {
    "addr:full":"50 Main St Bryson City NC 28713",
    "addr:housenumber":"50",
    "addr:postcode":"28713",
    "addr:street":"Main St",
    "iso:country":"US",
    "sg:address":"50 Main St",
    "sg:city":"Bryson City",
    "sg:classifiers":[
        {
            "category":"Social Services",
            "subcategory":"Adult Care",
            "type":"Services"
        }
    ],
    "sg:phone":"+1 828 488 9211",
    "sg:postcode":"28713",
    "sg:province":"NC",
    "sg:tags":[
        "organization",
        "senior",
        "citizen"
    ],
    "wof:name":"Area Agency On Aging",
    "wof:placetype":"venue"
},
  "geometry": {"coordinates":[-83.447185,35.426151],"type":"Point"}
}