{
  "type": "Feature",
  "properties": {
    "addr:full":"1426 Green Lake Rd Ellerbe NC 28338",
    "addr:housenumber":"1426",
    "addr:postcode":"28338",
    "addr:street":"Green Lake Rd",
    "iso:country":"US",
    "sg:address":"1426 Green Lake Rd",
    "sg:city":"Ellerbe",
    "sg:classifiers":[
        {
            "category":"Education",
            "subcategory":"School",
            "type":"Public Place"
        }
    ],
    "sg:phone":"+1 910 652 2931",
    "sg:postcode":"28338",
    "sg:province":"NC",
    "sg:website":"www.richmond.k12.nc.us",
    "wof:name":"Mineral Springs Middle School",
    "wof:placetype":"venue"
},
  "geometry": {"coordinates":[-79.753676,35.060813],"type":"Point"}
}