{
  "type": "Feature",
  "properties": {
    "iso:country":"US",
    "sg:address":"280 Green Ave",
    "sg:city":"New Bern",
    "sg:classifiers":[
        {
            "category":"Organizations",
            "subcategory":"Religious Organization",
            "type":"Services"
        }
    ],
    "sg:phone":"+1   ",
    "sg:postcode":"28562",
    "sg:province":"NC",
    "wof:name":"Clarence Rice Rev",
    "wof:placetype":"venue"
},
  "geometry": {"coordinates":[-76.984235,34.992421],"type":"Point"}
}