{
  "type": "Feature",
  "properties": {
    "addr:full":"4723 Ansonville Rd Marshville NC 28103",
    "addr:housenumber":"4723",
    "addr:postcode":"28103",
    "addr:street":"Ansonville Rd",
    "iso:country":"US",
    "sg:address":"4723 Ansonville Rd",
    "sg:city":"Marshville",
    "sg:phone":"+1 704 624 5644",
    "sg:postcode":"28103",
    "sg:province":"NC",
    "sg:tags":[
        "farm",
        "soybean"
    ],
    "wof:name":"Lynn Thomas",
    "wof:placetype":"venue"
},
  "geometry": {"coordinates":[-80.33462900000001,35.056144],"type":"Point"}
}