{
  "type": "Feature",
  "properties": {
    "iso:country":"US",
    "sg:address":"3635 Big Oak Rd",
    "sg:city":"Kinston",
    "sg:classifiers":[
        {
            "category":"Farming",
            "subcategory":"Livestock Farm",
            "type":"Manufacturing & Wholesale Goods"
        }
    ],
    "sg:phone":"+1 252 522 5880",
    "sg:postcode":"28504",
    "sg:province":"NC",
    "sg:tags":[
        "animal",
        "general"
    ],
    "wof:name":"Circle W Longhorns",
    "wof:placetype":"venue"
},
  "geometry": {"coordinates":[-77.655278,35.145054],"type":"Point"}
}