{
  "type": "Feature",
  "properties": {
    "iso:country":"US",
    "sg:address":"130 W Worthington Ave",
    "sg:city":"Charlotte",
    "sg:classifiers":[
        {
            "category":"Professional",
            "subcategory":"Advertising",
            "type":"Services"
        }
    ],
    "sg:phone":"+1 704 339 0099",
    "sg:postcode":"28203",
    "sg:province":"NC",
    "sg:tags":[
        "counselor"
    ],
    "wof:name":"Maxim Agency",
    "wof:placetype":"venue"
},
  "geometry": {"coordinates":[-80.860524,35.212063],"type":"Point"}
}