{
  "type": "Feature",
  "properties": {
    "addr:full":"1425 Neal Hawkins Rd Gastonia NC 28056",
    "addr:housenumber":"1425",
    "addr:postcode":"28056",
    "addr:street":"Neal Hawkins Rd",
    "iso:country":"US",
    "sg:address":"1425 Neal Hawkins Rd",
    "sg:city":"Gastonia",
    "sg:classifiers":[
        {
            "category":"Organizations",
            "subcategory":"Religious Organization",
            "type":"Services"
        }
    ],
    "sg:phone":"+1 704 867 7766",
    "sg:postcode":"28056",
    "sg:province":"NC",
    "sg:tags":[
        "church"
    ],
    "wof:name":"Riverwood Worship Center",
    "wof:placetype":"venue"
},
  "geometry": {"coordinates":[-81.17505199999999,35.22051],"type":"Point"}
}