{
  "type": "Feature",
  "properties": {
    "iso:country":"US",
    "sg:address":"1241 Hardin Rd",
    "sg:city":"Dallas",
    "sg:classifiers":[
        {
            "category":"Professional",
            "type":"Services"
        }
    ],
    "sg:phone":"+1 704 922 8814",
    "sg:postcode":"28034",
    "sg:province":"NC",
    "wof:name":"Gmr Self Inc",
    "wof:placetype":"venue"
},
  "geometry": {"coordinates":[-81.184473,35.39839],"type":"Point"}
}