{
  "type": "Feature",
  "properties": {
    "iso:country":"US",
    "sg:address":"6104 Pintail Ct",
    "sg:city":"Oak Ridge",
    "sg:classifiers":[
        {
            "category":"Building & Trades",
            "subcategory":"Construction",
            "type":"Services"
        }
    ],
    "sg:phone":"+1 336 643 8747",
    "sg:postcode":"27310",
    "sg:province":"NC",
    "sg:tags":[
        "general",
        "contractor"
    ],
    "wof:name":"M K Peeples Inc",
    "wof:placetype":"venue"
},
  "geometry": {"coordinates":[-80.01255500000001,36.16978],"type":"Point"}
}