{
  "type": "Feature",
  "properties": {
    "iso:country":"US",
    "sg:address":"605 South St",
    "sg:city":"Davidson",
    "sg:classifiers":[
        {
            "category":"Organizations",
            "subcategory":"Religious Organization",
            "type":"Services"
        }
    ],
    "sg:phone":"+1 704 895 0059",
    "sg:postcode":"28036",
    "sg:province":"NC",
    "sg:tags":[
        "church"
    ],
    "wof:name":"Church Of The Good Shepherd",
    "wof:placetype":"venue"
},
  "geometry": {"coordinates":[-80.849163,35.491746],"type":"Point"}
}