{
  "type": "Feature",
  "properties": {
    "addr:full":"847 N Main St Waynesville NC 28786",
    "addr:housenumber":"847",
    "addr:postcode":"28786",
    "addr:street":"N Main St",
    "iso:country":"US",
    "sg:address":"847 N Main St",
    "sg:city":"Waynesville",
    "sg:classifiers":[
        {
            "category":"Health Services",
            "subcategory":"Hospital",
            "type":"Services"
        },
        {
            "category":"Building & Trades",
            "subcategory":"Plumbing",
            "type":"Services"
        }
    ],
    "sg:phone":"+1 828 454 0163",
    "sg:postcode":"28786",
    "sg:province":"NC",
    "sg:tags":[
        "mental",
        "contractor"
    ],
    "wof:name":"Smoky Mountain Area Mental Hea",
    "wof:placetype":"venue"
},
  "geometry": {"coordinates":[-82.97994799999999,35.496953],"type":"Point"}
}