{
  "type": "Feature",
  "properties": {
    "addr:full":"1180 State Rd 111 Beulaville NC 28518",
    "addr:housenumber":"1180",
    "addr:postcode":"28518",
    "addr:street":"State Rd 111",
    "iso:country":"US",
    "sg:address":"1180 State Rd 111",
    "sg:city":"Beulaville",
    "sg:classifiers":[
        {
            "category":"Retail",
            "subcategory":"Auto Repair",
            "type":"Services"
        }
    ],
    "sg:phone":"+1 910 298 6270",
    "sg:postcode":"28518",
    "sg:province":"NC",
    "sg:tags":[
        "repairing",
        "automobile"
    ],
    "wof:name":"Thompson Service Ctr",
    "wof:placetype":"venue"
},
  "geometry": {"coordinates":[-77.775767,34.915959],"type":"Point"}
}