{
  "type": "Feature",
  "properties": {
    "iso:country":"US",
    "sg:address":"8713 Pierce Olive Rd",
    "sg:city":"Apex",
    "sg:classifiers":[
        {
            "category":"Professional",
            "subcategory":"Business Services",
            "type":"Services"
        }
    ],
    "sg:phone":"+1   ",
    "sg:postcode":"27539",
    "sg:province":"NC",
    "wof:name":"Airington Enterprise LLC",
    "wof:placetype":"venue"
},
  "geometry": {"coordinates":[-78.781267,35.679255],"type":"Point"}
}