{
  "type": "Feature",
  "properties": {
    "addr:full":"301 Yadkin St Albemarle NC 28001",
    "addr:housenumber":"301",
    "addr:postcode":"28001",
    "addr:street":"Yadkin St",
    "iso:country":"US",
    "sg:address":"301 Yadkin St",
    "sg:city":"Albemarle",
    "sg:classifiers":[
        {
            "category":"Health Services",
            "subcategory":"Doctor",
            "type":"Services"
        }
    ],
    "sg:phone":"+1   ",
    "sg:postcode":"28001",
    "sg:province":"NC",
    "sg:tags":[
        "medical"
    ],
    "wof:name":"Cardinal Anesthesia",
    "wof:placetype":"venue"
},
  "geometry": {"coordinates":[-80.19428000000001,35.362604],"type":"Point"}
}