{
  "type": "Feature",
  "properties": {
    "addr:full":"124 S Post Rd Shelby NC 28152",
    "addr:housenumber":"124",
    "addr:postcode":"28152",
    "addr:street":"S Post Rd",
    "iso:country":"US",
    "sg:address":"124 S Post Rd",
    "sg:city":"Shelby",
    "sg:classifiers":[
        {
            "category":"Social Services",
            "subcategory":"Job Training",
            "type":"Services"
        }
    ],
    "sg:phone":"+1 704 480 6641",
    "sg:postcode":"28152",
    "sg:province":"NC",
    "sg:tags":[
        "retardation",
        "disabled",
        "mental",
        "dev"
    ],
    "sg:website":"www.pathmhddsa.org",
    "wof:name":"Footprints Carolina Inc",
    "wof:placetype":"venue"
},
  "geometry": {"coordinates":[-81.492081,35.282915],"type":"Point"}
}