{
  "type": "Feature",
  "properties": {
    "addr:full":"1284 Buck Jones Rd Raleigh NC 27606",
    "addr:housenumber":"1284",
    "addr:postcode":"27606",
    "addr:street":"Buck Jones Rd",
    "iso:country":"US",
    "sg:address":"1284 Buck Jones Rd",
    "sg:city":"Raleigh",
    "sg:classifiers":[
        {
            "category":"Cafe",
            "type":"Food & Drink"
        },
        {
            "category":"Restaurant",
            "type":"Food & Drink"
        }
    ],
    "sg:menulink":"http://www.allmenus.com/nc/cary/28347-hot-point-cafe/menu/",
    "sg:phone":"+1 919 460 6299",
    "sg:postcode":"27606",
    "sg:province":"NC",
    "sg:tags":[
        "wrap",
        "american",
        "sandwich"
    ],
    "wof:name":"Hot Point Cafe",
    "wof:placetype":"venue"
},
  "geometry": {"coordinates":[-78.742165,35.766339],"type":"Point"}
}