{
  "type": "Feature",
  "properties": {
    "iso:country":"US",
    "sg:address":"2125 Commonwealth Ave",
    "sg:city":"Charlotte",
    "sg:classifiers":[
        {
            "category":"Personal",
            "subcategory":"Beauty Salon",
            "type":"Services"
        }
    ],
    "sg:phone":"+1 704 377 1400",
    "sg:postcode":"28205",
    "sg:province":"NC",
    "wof:name":"Walston & Co",
    "wof:placetype":"venue"
},
  "geometry": {"coordinates":[-80.809697,35.217661],"type":"Point"}
}