{
  "type": "Feature",
  "properties": {
    "iso:country":"US",
    "sg:address":"4909 Green Rd",
    "sg:city":"Raleigh",
    "sg:classifiers":[
        {
            "category":"Health Services",
            "subcategory":"Doctor",
            "type":"Services"
        }
    ],
    "sg:phone":"+1 919 790 0288",
    "sg:postcode":"27616",
    "sg:province":"NC",
    "sg:tags":[
        "physician",
        "medical",
        "surgeon",
        "center"
    ],
    "sg:website":"www.concentramedical.com",
    "wof:name":"Concentra Medical Center",
    "wof:placetype":"venue"
},
  "geometry": {"coordinates":[-78.586512,35.849447],"type":"Point"}
}