{
  "type": "Feature",
  "properties": {
    "iso:country":"US",
    "sg:address":"1507 Carolina Ave",
    "sg:city":"Washington",
    "sg:classifiers":[
        {
            "category":"Restaurant",
            "type":"Food & Drink"
        }
    ],
    "sg:phone":"+1 252 946 4663",
    "sg:postcode":"27889",
    "sg:province":"NC",
    "wof:name":"Dragon Garden Buffet",
    "wof:placetype":"venue"
},
  "geometry": {"coordinates":[-77.06187799999999,35.562816],"type":"Point"}
}