{
  "type": "Feature",
  "properties": {
    "addr:full":"301 Alice Dr Greenville NC 27834",
    "addr:housenumber":"301",
    "addr:postcode":"27834",
    "addr:street":"Alice Dr",
    "iso:country":"US",
    "sg:address":"301 Alice Dr",
    "sg:city":"Greenville",
    "sg:classifiers":[
        {
            "category":"Social Services",
            "subcategory":"Child Care",
            "type":"Services"
        }
    ],
    "sg:phone":"+1   ",
    "sg:postcode":"27834",
    "sg:province":"NC",
    "sg:tags":[
        "day"
    ],
    "wof:name":"Take A Break Childcare",
    "wof:placetype":"venue"
},
  "geometry": {"coordinates":[-77.410826,35.577282],"type":"Point"}
}