{
  "type": "Feature",
  "properties": {
    "addr:full":"720 Governor Morrison St Charlotte NC 28211",
    "addr:housenumber":"720",
    "addr:postcode":"28211",
    "addr:street":"Governor Morrison St",
    "iso:country":"US",
    "sg:address":"720 Governor Morrison St",
    "sg:city":"Charlotte",
    "sg:classifiers":[
        {
            "category":"Personal",
            "subcategory":"Beauty Salon",
            "type":"Services"
        },
        {
            "category":"Personal",
            "subcategory":"Day Spa",
            "type":"Services"
        },
        {
            "category":"Personal",
            "subcategory":"Skin Care",
            "type":"Services"
        },
        {
            "category":"Personal",
            "subcategory":"Nail Salon",
            "type":"Services"
        }
    ],
    "sg:phone":"+1 704 366 7366",
    "sg:postcode":"28211",
    "sg:province":"NC",
    "sg:tags":[
        "hair",
        "stylist"
    ],
    "sg:website":"http://www.varji.com",
    "wof:name":"Varji & Varji Salon",
    "wof:placetype":"venue"
},
  "geometry": {"coordinates":[-80.82467,35.156585],"type":"Point"}
}