{
  "type": "Feature",
  "properties": {
    "iso:country":"US",
    "sg:address":"2 W Edenton St",
    "sg:city":"Raleigh",
    "sg:classifiers":[
        {
            "category":"Government",
            "subcategory":"Office",
            "type":"Public Place"
        }
    ],
    "sg:phone":"+1 919 733 6100",
    "sg:postcode":"27601",
    "sg:province":"NC",
    "wof:name":"Nc State Structural Pest",
    "wof:placetype":"venue"
},
  "geometry": {"coordinates":[-78.640022,35.781244],"type":"Point"}
}