{
  "type": "Feature",
  "properties": {
    "addr:full":"211 N Queen St Kinston NC 28501",
    "addr:housenumber":"211",
    "addr:postcode":"28501",
    "addr:street":"N Queen St",
    "iso:country":"US",
    "sg:address":"211 N Queen St",
    "sg:city":"Kinston",
    "sg:classifiers":[
        {
            "category":"Professional",
            "type":"Services"
        }
    ],
    "sg:phone":"+1 252 522 2757",
    "sg:postcode":"28501",
    "sg:province":"NC",
    "wof:name":"Annie De Lo Ro",
    "wof:placetype":"venue"
},
  "geometry": {"coordinates":[-77.58103199999999,35.262315],"type":"Point"}
}