{
  "type": "Feature",
  "properties": {
    "addr:full":"1618 Royal Red Trl Apex NC 27502",
    "addr:housenumber":"1618",
    "addr:postcode":"27502",
    "addr:street":"Royal Red Trl",
    "iso:country":"US",
    "sg:address":"1618 Royal Red Trl",
    "sg:city":"Apex",
    "sg:classifiers":[
        {
            "category":"Professional",
            "subcategory":"Computer Services",
            "type":"Services"
        }
    ],
    "sg:phone":"+1 919 303 2976",
    "sg:postcode":"27502",
    "sg:province":"NC",
    "sg:tags":[
        "consultant",
        "designer"
    ],
    "wof:name":"Electronics Design",
    "wof:placetype":"venue"
},
  "geometry": {"coordinates":[-78.87618999999999,35.729361],"type":"Point"}
}