{
  "type": "Feature",
  "properties": {
    "iso:country":"US",
    "sg:address":"5547 Central Ave",
    "sg:city":"Charlotte",
    "sg:classifiers":[
        {
            "category":"Food & Beverages",
            "subcategory":"Specialty",
            "type":"Retail Goods"
        }
    ],
    "sg:phone":"+1 704 563 5839",
    "sg:postcode":"28212",
    "sg:province":"NC",
    "wof:name":"Vitamin World 2710",
    "wof:placetype":"venue"
},
  "geometry": {"coordinates":[-80.754778,35.208631],"type":"Point"}
}