{
  "type": "Feature",
  "properties": {
    "addr:full":"2045 Cedar Meadows Ct Pleasant Garden NC 27313",
    "addr:housenumber":"2045",
    "addr:postcode":"27313",
    "addr:street":"Cedar Meadows Ct Pleasant",
    "iso:country":"US",
    "sg:address":"2045 Cedar Meadows Ct",
    "sg:city":"Pleasant Garden",
    "sg:classifiers":[
        {
            "category":"Building & Trades",
            "subcategory":"Landscaping Services",
            "type":"Services"
        }
    ],
    "sg:phone":"+1 336 685 0401",
    "sg:postcode":"27313",
    "sg:province":"NC",
    "sg:tags":[
        "landscape",
        "contractor"
    ],
    "wof:name":"Weed Warriors",
    "wof:placetype":"venue"
},
  "geometry": {"coordinates":[-79.740334,35.906307],"type":"Point"}
}