{
  "type": "Feature",
  "properties": {
    "iso:country":"US",
    "sg:address":"140 Brevard Ct",
    "sg:city":"Charlotte",
    "sg:classifiers":[
        {
            "category":"Restaurant",
            "type":"Food & Drink"
        }
    ],
    "sg:phone":"+1 704 333 7229",
    "sg:postcode":"28202",
    "sg:province":"NC",
    "sg:tags":[
        "eating"
    ],
    "wof:name":"Mel's Submarines",
    "wof:placetype":"venue"
},
  "geometry": {"coordinates":[-80.846566,35.225985],"type":"Point"}
}