{
  "type": "Feature",
  "properties": {
    "addr:full":"511 Shepherd St Winston Salem NC 27103",
    "addr:housenumber":"511",
    "addr:postcode":"27103",
    "addr:street":"Shepherd St",
    "iso:country":"US",
    "sg:address":"511 Shepherd St",
    "sg:city":"Winston Salem",
    "sg:classifiers":[
        {
            "category":"Real Estate",
            "subcategory":"Real Estate Agent",
            "type":"Services"
        }
    ],
    "sg:phone":"+1 336 774 9160",
    "sg:postcode":"27103",
    "sg:province":"NC",
    "sg:tags":[
        "management"
    ],
    "wof:name":"J G Messick & Sons Inc",
    "wof:placetype":"venue"
},
  "geometry": {"coordinates":[-80.302205,36.083608],"type":"Point"}
}