{
  "type": "Feature",
  "properties": {
    "iso:country":"US",
    "sg:address":"960 S Hancock St",
    "sg:city":"Rockingham",
    "sg:classifiers":[
        {
            "category":"Building & Trades",
            "subcategory":"Construction",
            "type":"Services"
        }
    ],
    "sg:phone":"+1 910 895 1572",
    "sg:postcode":"28379",
    "sg:province":"NC",
    "sg:tags":[
        "house"
    ],
    "wof:name":"JMC Disastor Restoration",
    "wof:placetype":"venue"
},
  "geometry": {"coordinates":[-79.783075,34.920621],"type":"Point"}
}