{
  "type": "Feature",
  "properties": {
    "addr:full":"1103 E US Hwy 74 Bus Ellenboro NC 28040",
    "addr:housenumber":"1103",
    "addr:postcode":"28040",
    "addr:street":"E Us Hwy 74 Bus",
    "iso:country":"US",
    "sg:address":"1103 E US Hwy 74 Bus",
    "sg:city":"Ellenboro",
    "sg:classifiers":[
        {
            "category":"Building & Trades",
            "subcategory":"Equipment Rental",
            "type":"Services"
        }
    ],
    "sg:phone":"+1 828 453 0548",
    "sg:postcode":"28040",
    "sg:province":"NC",
    "sg:tags":[
        "toilet"
    ],
    "wof:name":"Triple H Rent-A-Toilet",
    "wof:placetype":"venue"
},
  "geometry": {"coordinates":[-81.726994,35.306003],"type":"Point"}
}