{
  "type": "Feature",
  "properties": {
    "iso:country":"US",
    "sg:address":"308 E Leonard St",
    "sg:city":"Southport",
    "sg:classifiers":[
        {
            "category":"Manufacturing",
            "subcategory":"Metals",
            "type":"Manufacturing & Wholesale Goods"
        }
    ],
    "sg:phone":"+1 910 457 5672",
    "sg:postcode":"28461",
    "sg:province":"NC",
    "sg:tags":[
        "product",
        "fabricated",
        "mfg"
    ],
    "wof:name":"Cape Fear Coppershop",
    "wof:placetype":"venue"
},
  "geometry": {"coordinates":[-78.017156,33.926509],"type":"Point"}
}