{
  "type": "Feature",
  "properties": {
    "addr:full":"716 Benjamin Pkwy Greensboro NC 27408",
    "addr:housenumber":"716",
    "addr:postcode":"27408",
    "addr:street":"Benjamin Pkwy",
    "iso:country":"US",
    "sg:address":"716 Benjamin Pkwy",
    "sg:city":"Greensboro",
    "sg:classifiers":[
        {
            "category":"Education",
            "subcategory":"School",
            "type":"Public Place"
        }
    ],
    "sg:phone":"+1 336 370 8240",
    "sg:postcode":"27408",
    "sg:province":"NC",
    "sg:website":"www.guilford.k12.nc.us",
    "wof:name":"Kiser Middle School",
    "wof:placetype":"venue"
},
  "geometry": {"coordinates":[-79.818727,36.083418],"type":"Point"}
}