{
  "type": "Feature",
  "properties": {
    "addr:full":"2002 N Elm St Greensboro NC 27408",
    "addr:housenumber":"2002",
    "addr:postcode":"27408",
    "addr:street":"N Elm St",
    "iso:country":"US",
    "sg:address":"2002 N Elm St",
    "sg:city":"Greensboro",
    "sg:classifiers":[
        {
            "category":"Personal",
            "subcategory":"Beauty Salon",
            "type":"Services"
        },
        {
            "category":"Personal",
            "subcategory":"Barber",
            "type":"Services"
        }
    ],
    "sg:phone":"+1 336 274 6060",
    "sg:postcode":"27408",
    "sg:province":"NC",
    "sg:tags":[
        "shop"
    ],
    "wof:name":"Elm Street Hair Co Barber",
    "wof:placetype":"venue"
},
  "geometry": {"coordinates":[-79.78794600000001,36.101594],"type":"Point"}
}