{
  "type": "Feature",
  "properties": {
    "iso:country":"US",
    "sg:address":"3318 Hampton Rd",
    "sg:city":"Raleigh",
    "sg:classifiers":[
        {
            "category":"Professional",
            "type":"Services"
        }
    ],
    "sg:phone":"+1   ",
    "sg:postcode":"27607",
    "sg:province":"NC",
    "wof:name":"Mhi Property Services Inc",
    "wof:placetype":"venue"
},
  "geometry": {"coordinates":[-78.683854,35.818996],"type":"Point"}
}