{
  "type": "Feature",
  "properties": {
    "iso:country":"US",
    "sg:address":"3850 Legion Rd",
    "sg:city":"Hope Mills",
    "sg:classifiers":[
        {
            "category":"Retail",
            "subcategory":"Auto Repair",
            "type":"Services"
        }
    ],
    "sg:phone":"+1 910 624 1200",
    "sg:postcode":"28348",
    "sg:province":"NC",
    "sg:tags":[
        "wrecker"
    ],
    "wof:name":"Legion Road Wrecker Svc",
    "wof:placetype":"venue"
},
  "geometry": {"coordinates":[-78.925074,34.988874],"type":"Point"}
}