{
  "type": "Feature",
  "properties": {
    "addr:full":"107 School Dr Murphy NC 28904",
    "addr:housenumber":"107",
    "addr:postcode":"28904",
    "addr:street":"School Dr",
    "iso:country":"US",
    "sg:address":"107 School Dr",
    "sg:city":"Murphy",
    "sg:classifiers":[
        {
            "category":"Education",
            "subcategory":"School",
            "type":"Public Place"
        }
    ],
    "sg:phone":"+1 828 837 9371",
    "sg:postcode":"28904",
    "sg:province":"NC",
    "sg:tags":[
        "middle"
    ],
    "wof:name":"Murphy Middle School",
    "wof:placetype":"venue"
},
  "geometry": {"coordinates":[-83.817521,35.040896],"type":"Point"}
}