{
  "type": "Feature",
  "properties": {
    "addr:full":"5441 Basking Ridge Dr Fayetteville NC 28314",
    "addr:housenumber":"5441",
    "addr:postcode":"28314",
    "addr:street":"Basking Ridge Dr",
    "iso:country":"US",
    "sg:address":"5441 Basking Ridge Dr",
    "sg:city":"Fayetteville",
    "sg:classifiers":[
        {
            "category":"Real Estate",
            "subcategory":"Real Estate Agent",
            "type":"Services"
        }
    ],
    "sg:phone":"+1 910 864 2273",
    "sg:postcode":"28314",
    "sg:province":"NC",
    "wof:name":"Stoney Ridge",
    "wof:placetype":"venue"
},
  "geometry": {"coordinates":[-78.97421300000001,35.073628],"type":"Point"}
}