{
  "type": "Feature",
  "properties": {
    "addr:full":"212 Vinwood Ave Goldsboro NC 27534",
    "addr:housenumber":"212",
    "addr:postcode":"27534",
    "addr:street":"Vinwood Ave",
    "iso:country":"US",
    "sg:address":"212 Vinwood Ave",
    "sg:city":"Goldsboro",
    "sg:classifiers":[
        {
            "category":"Organizations",
            "subcategory":"Religious Organization",
            "type":"Services"
        }
    ],
    "sg:phone":"+1   ",
    "sg:postcode":"27534",
    "sg:province":"NC",
    "wof:name":"Abundant Grace Holiness Church",
    "wof:placetype":"venue"
},
  "geometry": {"coordinates":[-77.88848900000001,35.385501],"type":"Point"}
}