{
  "type": "Feature",
  "properties": {
    "addr:full":"1301 Beverly Dr Raleigh NC 27610",
    "addr:housenumber":"1301",
    "addr:postcode":"27610",
    "addr:street":"Beverly Dr",
    "iso:country":"US",
    "sg:address":"1301 Beverly Dr",
    "sg:city":"Raleigh",
    "sg:classifiers":[
        {
            "category":"Retail",
            "subcategory":"Repair Shop",
            "type":"Services"
        }
    ],
    "sg:phone":"+1   ",
    "sg:postcode":"27610",
    "sg:province":"NC",
    "sg:tags":[
        "electrical"
    ],
    "wof:name":"Precision Communication",
    "wof:placetype":"venue"
},
  "geometry": {"coordinates":[-78.591464,35.760422],"type":"Point"}
}