{
  "type": "Feature",
  "properties": {
    "iso:country":"US",
    "sg:address":"3190 W 5th St",
    "sg:city":"Lumberton",
    "sg:classifiers":[
        {
            "category":"Retail",
            "subcategory":"Auto Repair",
            "type":"Services"
        }
    ],
    "sg:phone":"+1 910 671 9111",
    "sg:postcode":"28358",
    "sg:province":"NC",
    "sg:tags":[
        "parts",
        "truck"
    ],
    "wof:name":"Smith International Truck Ctr",
    "wof:placetype":"venue"
},
  "geometry": {"coordinates":[-79.051354,34.621533],"type":"Point"}
}