{
  "type": "Feature",
  "properties": {
    "addr:full":"1319 Woodbriar Ave Greensboro NC 27405",
    "addr:housenumber":"1319",
    "addr:postcode":"27405",
    "addr:street":"Woodbriar Ave",
    "iso:country":"US",
    "sg:address":"1319 Woodbriar Ave",
    "sg:city":"Greensboro",
    "sg:classifiers":[
        {
            "category":"Health Services",
            "subcategory":"Nursing And Care Facility",
            "type":"Services"
        }
    ],
    "sg:phone":"+1 336 273 0017",
    "sg:postcode":"27405",
    "sg:province":"NC",
    "sg:tags":[
        "home",
        "rest"
    ],
    "wof:name":"Lawson Adult Enrichment Ctr",
    "wof:placetype":"venue"
},
  "geometry": {"coordinates":[-79.744849,36.099322],"type":"Point"}
}