{
  "type": "Feature",
  "properties": {
    "addr:full":"2190 Sanders Rd Stem NC 27581",
    "addr:housenumber":"2190",
    "addr:postcode":"27581",
    "addr:street":"Sanders Rd",
    "iso:country":"US",
    "sg:address":"2190 Sanders Rd",
    "sg:city":"Stem",
    "sg:classifiers":[
        {
            "category":"Freight",
            "type":"Transportation"
        }
    ],
    "sg:phone":"+1 919 528 1554",
    "sg:postcode":"27581",
    "sg:province":"NC",
    "wof:name":"Jj Transportation Inc",
    "wof:placetype":"venue"
},
  "geometry": {"coordinates":[-78.672303,36.200209],"type":"Point"}
}