{
  "type": "Feature",
  "properties": {
    "iso:country":"US",
    "sg:address":"807 S Duke St",
    "sg:city":"Durham",
    "sg:classifiers":[
        {
            "category":"Real Estate",
            "subcategory":"Real Estate Agent",
            "type":"Services"
        }
    ],
    "sg:phone":"+1 919 682 4221",
    "sg:postcode":"27701",
    "sg:province":"NC",
    "wof:name":"Housing Auth/Cty/Drhm",
    "wof:placetype":"venue"
},
  "geometry": {"coordinates":[-78.908833,35.991156],"type":"Point"}
}