{
  "type": "Feature",
  "properties": {
    "iso:country":"US",
    "sg:address":"4908 Harri Ann Dr",
    "sg:city":"Charlotte",
    "sg:classifiers":[
        {
            "category":"Shopping",
            "subcategory":"Clothing, Apparel, & Fashions",
            "type":"Retail Goods"
        },
        {
            "category":"Manufacturing",
            "subcategory":"Toys & Sporting Goods",
            "type":"Manufacturing & Wholesale Goods"
        }
    ],
    "sg:phone":"+1 704 449 9268",
    "sg:postcode":"28227",
    "sg:province":"NC",
    "sg:tags":[
        "girdle",
        "manufacturer",
        "corset",
        "underwear-wholesale"
    ],
    "wof:name":"Just Bras Co",
    "wof:placetype":"venue"
},
  "geometry": {"coordinates":[-80.70802,35.193653],"type":"Point"}
}