{
  "type": "Feature",
  "properties": {
    "addr:full":"3235 Dearborn Dr Durham NC 27704",
    "addr:housenumber":"3235",
    "addr:postcode":"27704",
    "addr:street":"Dearborn Dr",
    "iso:country":"US",
    "sg:address":"3235 Dearborn Dr",
    "sg:city":"Durham",
    "sg:classifiers":[
        {
            "category":"Shopping",
            "subcategory":"Discount & Variety Stores",
            "type":"Retail Goods"
        }
    ],
    "sg:phone":"+1 919 220 0377",
    "sg:postcode":"27704",
    "sg:province":"NC",
    "wof:name":"Allens Variety Shop",
    "wof:placetype":"venue"
},
  "geometry": {"coordinates":[-78.874319,36.037593],"type":"Point"}
}