{
  "type": "Feature",
  "properties": {
    "addr:full":"320 Quail Dr Raleigh NC 27604",
    "addr:housenumber":"320",
    "addr:postcode":"27604",
    "addr:street":"Quail Dr",
    "iso:country":"US",
    "sg:address":"320 Quail Dr",
    "sg:city":"Raleigh",
    "sg:classifiers":[
        {
            "category":"Building & Trades",
            "subcategory":"Construction",
            "type":"Services"
        }
    ],
    "sg:phone":"+1 919 833 9847",
    "sg:postcode":"27604",
    "sg:province":"NC",
    "sg:tags":[
        "wallpaper"
    ],
    "wof:name":"Hankins & Hankins Wall Pprng",
    "wof:placetype":"venue"
},
  "geometry": {"coordinates":[-78.61533900000001,35.80238],"type":"Point"}
}