{
  "type": "Feature",
  "properties": {
    "addr:full":"550 Swannanoa River Rd Asheville NC 28805",
    "addr:housenumber":"550",
    "addr:postcode":"28805",
    "addr:street":"Swannanoa River Rd",
    "iso:country":"US",
    "sg:address":"550 Swannanoa River Rd",
    "sg:city":"Asheville",
    "sg:classifiers":[
        {
            "category":"Freight",
            "type":"Transportation"
        }
    ],
    "sg:phone":"+1 828 298 4644",
    "sg:postcode":"28805",
    "sg:province":"NC",
    "sg:tags":[
        "commercial",
        "storage"
    ],
    "wof:name":"George's Stor-Mor",
    "wof:placetype":"venue"
},
  "geometry": {"coordinates":[-82.508844,35.575666],"type":"Point"}
}