{
  "type": "Feature",
  "properties": {
    "iso:country":"US",
    "sg:address":"4712 Prosperity Church Rd",
    "sg:city":"Charlotte",
    "sg:classifiers":[
        {
            "category":"Professional",
            "subcategory":"Engineering",
            "type":"Services"
        }
    ],
    "sg:phone":"+1   ",
    "sg:postcode":"28269",
    "sg:province":"NC",
    "sg:tags":[
        "consulting"
    ],
    "wof:name":"Langley Engineering PC",
    "wof:placetype":"venue"
},
  "geometry": {"coordinates":[-80.782302,35.35945],"type":"Point"}
}