{
  "type": "Feature",
  "properties": {
    "iso:country":"US",
    "sg:address":"2310 Asheville Hwy",
    "sg:city":"Hendersonville",
    "sg:classifiers":[
        {
            "category":"Organizations",
            "subcategory":"Religious Organization",
            "type":"Services"
        }
    ],
    "sg:phone":"+1 828 698 1060",
    "sg:postcode":"28791",
    "sg:province":"NC",
    "sg:tags":[
        "church"
    ],
    "wof:name":"Hendersonville Seventh Day",
    "wof:placetype":"venue"
},
  "geometry": {"coordinates":[-82.474245,35.343285],"type":"Point"}
}