{
  "type": "Feature",
  "properties": {
    "addr:full":"1606 Kilmer Ter Durham NC 27703",
    "addr:housenumber":"1606",
    "addr:postcode":"27703",
    "addr:street":"Kilmer Ter",
    "iso:country":"US",
    "sg:address":"1606 Kilmer Ter",
    "sg:city":"Durham",
    "sg:classifiers":[
        {
            "category":"Social Services",
            "subcategory":"Child Care",
            "type":"Services"
        }
    ],
    "sg:phone":"+1 919 956 7540",
    "sg:postcode":"27703",
    "sg:province":"NC",
    "sg:tags":[
        "day"
    ],
    "wof:name":"Noah's Ark Day Care",
    "wof:placetype":"venue"
},
  "geometry": {"coordinates":[-78.873519,36.000133],"type":"Point"}
}