{
  "type": "Feature",
  "properties": {
    "addr:full":"305 Winterberry Ridge Dr Durham NC 27713",
    "addr:housenumber":"305",
    "addr:postcode":"27713",
    "addr:street":"Winterberry Ridge Dr",
    "iso:country":"US",
    "sg:address":"305 Winterberry Ridge Dr",
    "sg:city":"Durham",
    "sg:classifiers":[
        {
            "category":"Local Transit",
            "type":"Transportation"
        }
    ],
    "sg:phone":"+1 919 493 5890",
    "sg:postcode":"27713",
    "sg:province":"NC",
    "sg:tags":[
        "passenger",
        "transport"
    ],
    "wof:name":"Brads Shuttle & Courier",
    "wof:placetype":"venue"
},
  "geometry": {"coordinates":[-78.948774,35.921566],"type":"Point"}
}