{
  "type": "Feature",
  "properties": {
    "addr:full":"3609 Robin Ln Charlotte NC 28269",
    "addr:housenumber":"3609",
    "addr:postcode":"28269",
    "addr:street":"Robin Ln",
    "iso:country":"US",
    "sg:address":"3609 Robin Ln",
    "sg:city":"Charlotte",
    "sg:classifiers":[
        {
            "category":"Building & Trades",
            "subcategory":"Construction",
            "type":"Services"
        }
    ],
    "sg:phone":"+1 704 598 7853",
    "sg:postcode":"28269",
    "sg:province":"NC",
    "sg:tags":[
        "house",
        "nonresidential"
    ],
    "wof:name":"Alan Melhiser Custom Builder",
    "wof:placetype":"venue"
},
  "geometry": {"coordinates":[-80.78669600000001,35.342105],"type":"Point"}
}