{
  "type": "Feature",
  "properties": {
    "iso:country":"US",
    "sg:address":"302 Rodoret St S",
    "sg:city":"Valdese",
    "sg:classifiers":[
        {
            "category":"Insurance",
            "subcategory":"Insurance Agent",
            "type":"Services"
        }
    ],
    "sg:phone":"+1 828 874 2186",
    "sg:postcode":"28690",
    "sg:province":"NC",
    "wof:name":"Paul D Mears Insurance",
    "wof:placetype":"venue"
},
  "geometry": {"coordinates":[-81.56308199999999,35.742193],"type":"Point"}
}