{
  "type": "Feature",
  "properties": {
    "iso:country":"US",
    "sg:address":"4255 Glenn High Rd",
    "sg:city":"Winston Salem",
    "sg:classifiers":[
        {
            "category":"Home & Garden",
            "subcategory":"Building Materials",
            "type":"Retail Goods"
        }
    ],
    "sg:phone":"+1 336 788 6621",
    "sg:postcode":"27107",
    "sg:province":"NC",
    "sg:tags":[
        "sell",
        "garage",
        "door",
        "install"
    ],
    "wof:name":"Craft Garage Door Co",
    "wof:placetype":"venue"
},
  "geometry": {"coordinates":[-80.132538,36.069739],"type":"Point"}
}