{
  "type": "Feature",
  "properties": {
    "addr:full":"120 Wade St Jamestown NC 27282",
    "addr:housenumber":"120",
    "addr:postcode":"27282",
    "addr:street":"Wade St",
    "iso:country":"US",
    "sg:address":"120 Wade St",
    "sg:city":"Jamestown",
    "sg:classifiers":[
        {
            "category":"Communications",
            "subcategory":"Film & Video Production",
            "type":"Services"
        }
    ],
    "sg:phone":"+1 336 883 8107",
    "sg:postcode":"27282",
    "sg:province":"NC",
    "sg:tags":[
        "taping"
    ],
    "wof:name":"Bradleigh Productions",
    "wof:placetype":"venue"
},
  "geometry": {"coordinates":[-79.943217,35.990435],"type":"Point"}
}