{
  "type": "Feature",
  "properties": {
    "addr:full":"1503 Buck Jones Rd Raleigh NC 27606",
    "addr:housenumber":"1503",
    "addr:postcode":"27606",
    "addr:street":"Buck Jones Rd",
    "iso:country":"US",
    "sg:address":"1503 Buck Jones Rd",
    "sg:city":"Raleigh",
    "sg:classifiers":[
        {
            "category":"Restaurant",
            "type":"Food & Drink"
        }
    ],
    "sg:phone":"+1 919 469 8877",
    "sg:postcode":"27606",
    "sg:province":"NC",
    "sg:tags":[
        "eating"
    ],
    "wof:name":"Guarino's Italian Restaurant",
    "wof:placetype":"venue"
},
  "geometry": {"coordinates":[-78.744316,35.763805],"type":"Point"}
}