{
  "type": "Feature",
  "properties": {
    "addr:full":"2812 Patrie Pl Raleigh NC 27613",
    "addr:housenumber":"2812",
    "addr:postcode":"27613",
    "addr:street":"Patrie Pl",
    "iso:country":"US",
    "sg:address":"2812 Patrie Pl",
    "sg:city":"Raleigh",
    "sg:classifiers":[
        {
            "category":"Real Estate",
            "subcategory":"Real Estate Agent",
            "type":"Services"
        }
    ],
    "sg:phone":"+1 919 846 0924",
    "sg:postcode":"27613",
    "sg:province":"NC",
    "wof:name":"Mommies Quilts Crafts LP",
    "wof:placetype":"venue"
},
  "geometry": {"coordinates":[-78.689943,35.930048],"type":"Point"}
}