{
  "type": "Feature",
  "properties": {
    "iso:country":"US",
    "sg:address":"102 Peckskill Ct",
    "sg:city":"Cary",
    "sg:classifiers":[
        {
            "category":"Banks & Credit Unions",
            "subcategory":"Financial Services",
            "type":"Services"
        }
    ],
    "sg:phone":"+1 919 460 3306",
    "sg:postcode":"27519",
    "sg:province":"NC",
    "sg:tags":[
        "investor"
    ],
    "wof:name":"Bdm Investments LLC",
    "wof:placetype":"venue"
},
  "geometry": {"coordinates":[-78.853757,35.8112],"type":"Point"}
}