{
  "type": "Feature",
  "properties": {
    "iso:country":"US",
    "sg:address":"4749 South Blvd Ste A",
    "sg:city":"Charlotte",
    "sg:classifiers":[
        {
            "category":"Banks & Credit Unions",
            "subcategory":"Financial Services",
            "type":"Services"
        }
    ],
    "sg:phone":"+1 704 716 1002",
    "sg:postcode":"28217",
    "sg:province":"NC",
    "sg:tags":[
        "cashing",
        "check"
    ],
    "wof:name":"Charlotte Check Cashiers 8",
    "wof:placetype":"venue"
},
  "geometry": {"coordinates":[-80.875918,35.175436],"type":"Point"}
}