{
  "type": "Feature",
  "properties": {
    "addr:full":"252 Booker Lennon Rd S Bladenboro NC 28320",
    "addr:housenumber":"252",
    "addr:postcode":"28320",
    "addr:street":"Booker Lennon Rd S",
    "iso:country":"US",
    "sg:address":"252 Booker Lennon Rd S",
    "sg:city":"Bladenboro",
    "sg:classifiers":[
        {
            "category":"Freight",
            "type":"Transportation"
        }
    ],
    "sg:phone":"+1 910 648 2079",
    "sg:postcode":"28320",
    "sg:province":"NC",
    "sg:tags":[
        "operator",
        "hauling",
        "trucking"
    ],
    "wof:name":"Pridgen Trucking Co Inc",
    "wof:placetype":"venue"
},
  "geometry": {"coordinates":[-78.830264,34.463186],"type":"Point"}
}