{
  "type": "Feature",
  "properties": {
    "addr:full":"6200 Milford Rd Fayetteville NC 28303",
    "addr:housenumber":"6200",
    "addr:postcode":"28303",
    "addr:street":"Milford Rd",
    "iso:country":"US",
    "sg:address":"6200 Milford Rd",
    "sg:city":"Fayetteville",
    "sg:classifiers":[
        {
            "category":"Personal",
            "subcategory":"Beauty Salon",
            "type":"Services"
        }
    ],
    "sg:phone":"+1 910 826 8002",
    "sg:postcode":"28303",
    "sg:province":"NC",
    "sg:tags":[
        "shop"
    ],
    "wof:name":"Cottondale Hair Salon",
    "wof:placetype":"venue"
},
  "geometry": {"coordinates":[-78.98703999999999,35.098773],"type":"Point"}
}