{
  "type": "Feature",
  "properties": {
    "addr:full":"5945 Harris Technology Blvd Charlotte NC 28269",
    "addr:housenumber":"5945",
    "addr:postcode":"28269",
    "addr:street":"Harris Technology Blvd",
    "iso:country":"US",
    "sg:address":"5945 Harris Technology Blvd",
    "sg:city":"Charlotte",
    "sg:classifiers":[
        {
            "category":"Wholesale",
            "subcategory":"Construction Materials",
            "type":"Manufacturing & Wholesale Goods"
        }
    ],
    "sg:phone":"+1 704 596 8866",
    "sg:postcode":"28269",
    "sg:province":"NC",
    "sg:tags":[
        "siding"
    ],
    "wof:name":"Best Distributing Co Inc",
    "wof:placetype":"venue"
},
  "geometry": {"coordinates":[-80.83793300000001,35.337232],"type":"Point"}
}