{
  "type": "Feature",
  "properties": {
    "addr:full":"3300 Westgate Dr Durham NC 27707",
    "addr:housenumber":"3300",
    "addr:postcode":"27707",
    "addr:street":"Westgate Dr",
    "iso:country":"US",
    "sg:address":"3300 Westgate Dr",
    "sg:city":"Durham",
    "sg:classifiers":[
        {
            "category":"Shopping",
            "subcategory":"Hobbies, Toys, & Games",
            "type":"Retail Goods"
        }
    ],
    "sg:phone":"+1 919 493 4603",
    "sg:postcode":"27707",
    "sg:province":"NC",
    "wof:name":"Toys R Us",
    "wof:placetype":"venue"
},
  "geometry": {"coordinates":[-78.95941500000001,35.963744],"type":"Point"}
}