{
  "type": "Feature",
  "properties": {
    "addr:full":"345 Goodwin Mill Rd Hertford NC 27944",
    "addr:housenumber":"345",
    "addr:postcode":"27944",
    "addr:street":"Goodwin Mill Rd",
    "iso:country":"US",
    "sg:address":"345 Goodwin Mill Rd",
    "sg:city":"Hertford",
    "sg:phone":"+1 252 297 2543",
    "sg:postcode":"27944",
    "sg:province":"NC",
    "sg:tags":[
        "farm",
        "soybean"
    ],
    "wof:name":"Paul Byrum",
    "wof:placetype":"venue"
},
  "geometry": {"coordinates":[-76.549869,36.264326],"type":"Point"}
}