{
  "type": "Feature",
  "properties": {
    "iso:country":"US",
    "sg:address":"4903 South Blvd Ste B",
    "sg:city":"Charlotte",
    "sg:classifiers":[
        {
            "category":"Shopping",
            "subcategory":"Clothing, Apparel, & Fashions",
            "type":"Retail Goods"
        }
    ],
    "sg:phone":"+1 704 679 9604",
    "sg:postcode":"28217",
    "sg:province":"NC",
    "sg:tags":[
        "apparel",
        "lingerie",
        "women's"
    ],
    "wof:name":"Priscilla McCall's",
    "wof:placetype":"venue"
},
  "geometry": {"coordinates":[-80.875991,35.170568],"type":"Point"}
}