{
  "type": "Feature",
  "properties": {
    "addr:full":"1011 Fuller St Raleigh NC 27603",
    "addr:housenumber":"1011",
    "addr:postcode":"27603",
    "addr:street":"Fuller St",
    "iso:country":"US",
    "sg:address":"1011 Fuller St",
    "sg:city":"Raleigh",
    "sg:classifiers":[
        {
            "category":"Building & Trades",
            "subcategory":"Cleaning & Sanitation",
            "type":"Services"
        }
    ],
    "sg:phone":"+1   ",
    "sg:postcode":"27603",
    "sg:province":"NC",
    "sg:tags":[
        "maintenance"
    ],
    "wof:name":"Right Touch Cleaning Service",
    "wof:placetype":"venue"
},
  "geometry": {"coordinates":[-78.651336,35.766353],"type":"Point"}
}