{
  "type": "Feature",
  "properties": {
    "addr:full":"12116 Old Creedmoor Rd Raleigh NC 27613",
    "addr:housenumber":"12116",
    "addr:postcode":"27613",
    "addr:street":"Old Creedmoor Rd",
    "iso:country":"US",
    "sg:address":"12116 Old Creedmoor Rd",
    "sg:city":"Raleigh",
    "sg:classifiers":[
        {
            "category":"Building & Trades",
            "subcategory":"Construction",
            "type":"Services"
        }
    ],
    "sg:phone":"+1 919 870 6900",
    "sg:postcode":"27613",
    "sg:province":"NC",
    "sg:tags":[
        "contractor"
    ],
    "wof:name":"J Satterwhite Builder Inc",
    "wof:placetype":"venue"
},
  "geometry": {"coordinates":[-78.706272,35.964176],"type":"Point"}
}