{
  "type": "Feature",
  "properties": {
    "iso:country":"US",
    "sg:address":"5874 Farringdon Pl",
    "sg:city":"Raleigh",
    "sg:classifiers":[
        {
            "category":"Real Estate",
            "subcategory":"Real Estate Agent",
            "type":"Services"
        }
    ],
    "sg:phone":"+1 919 872 6343",
    "sg:postcode":"27609",
    "sg:province":"NC",
    "wof:name":"Doreen Silber & Co",
    "wof:placetype":"venue"
},
  "geometry": {"coordinates":[-78.621658,35.861351],"type":"Point"}
}