{
  "type": "Feature",
  "properties": {
    "iso:country":"US",
    "sg:address":"9934 Rose Commons Dr",
    "sg:city":"Huntersville",
    "sg:classifiers":[
        {
            "category":"Personal",
            "subcategory":"Beauty Salon",
            "type":"Services"
        }
    ],
    "sg:phone":"+1 704 947 3292",
    "sg:postcode":"28078",
    "sg:province":"NC",
    "sg:tags":[
        "shop"
    ],
    "wof:name":"New Age Hair Design",
    "wof:placetype":"venue"
},
  "geometry": {"coordinates":[-80.86168000000001,35.408764],"type":"Point"}
}