{
  "type": "Feature",
  "properties": {
    "addr:full":"4206 Lipton Ct High Point NC 27262",
    "addr:housenumber":"4206",
    "addr:postcode":"27262",
    "addr:street":"Lipton Ct",
    "iso:country":"US",
    "sg:address":"4206 Lipton Ct",
    "sg:city":"High Point",
    "sg:classifiers":[
        {
            "category":"Banks & Credit Unions",
            "subcategory":"Financial Services",
            "type":"Services"
        }
    ],
    "sg:phone":"+1 336 882 5303",
    "sg:postcode":"27262",
    "sg:province":"NC",
    "sg:tags":[
        "investor"
    ],
    "wof:name":"Rihp LLC",
    "wof:placetype":"venue"
},
  "geometry": {"coordinates":[-80.06249699999999,35.970358],"type":"Point"}
}