{
  "type": "Feature",
  "properties": {
    "addr:full":"1028 W Northwest Blvd Winston Salem NC 27101",
    "addr:housenumber":"1028",
    "addr:postcode":"27101",
    "addr:street":"W Northwest Blvd",
    "iso:country":"US",
    "sg:address":"1028 W Northwest Blvd",
    "sg:city":"Winston Salem",
    "sg:classifiers":[
        {
            "category":"Building & Trades",
            "subcategory":"Plumbing",
            "type":"Services"
        }
    ],
    "sg:phone":"+1 336 748 1727",
    "sg:postcode":"27101",
    "sg:province":"NC",
    "sg:tags":[
        "conditioning",
        "air",
        "system",
        "contractor"
    ],
    "wof:name":"Heat & Cool Shop",
    "wof:placetype":"venue"
},
  "geometry": {"coordinates":[-80.26097900000001,36.103358],"type":"Point"}
}