{
  "type": "Feature",
  "properties": {
    "addr:full":"7708 Burwell St Raleigh NC 27615",
    "addr:housenumber":"7708",
    "addr:postcode":"27615",
    "addr:street":"Burwell St",
    "iso:country":"US",
    "sg:address":"7708 Burwell St",
    "sg:city":"Raleigh",
    "sg:classifiers":[
        {
            "category":"Manufacturing",
            "subcategory":"Building Materials",
            "type":"Manufacturing & Wholesale Goods"
        }
    ],
    "sg:phone":"+1 919 850 8250",
    "sg:postcode":"27615",
    "sg:province":"NC",
    "sg:tags":[
        "member",
        "mfg",
        "wood",
        "structural"
    ],
    "wof:name":"Panel Plant",
    "wof:placetype":"venue"
},
  "geometry": {"coordinates":[-78.57677,35.889041],"type":"Point"}
}