{
  "type": "Feature",
  "properties": {
    "addr:full":"128 S Main St Laurinburg NC 28352",
    "addr:housenumber":"128",
    "addr:postcode":"28352",
    "addr:street":"S Main St",
    "iso:country":"US",
    "sg:address":"128 S Main St",
    "sg:city":"Laurinburg",
    "sg:classifiers":[
        {
            "category":"Shopping",
            "subcategory":"Used Merchandise",
            "type":"Retail Goods"
        }
    ],
    "sg:phone":"+1 910 276 3111",
    "sg:postcode":"28352",
    "sg:province":"NC",
    "wof:name":"Fairy Wings Consignment Boutiq",
    "wof:placetype":"venue"
},
  "geometry": {"coordinates":[-79.461398,34.776459],"type":"Point"}
}