{
  "type": "Feature",
  "properties": {
    "iso:country":"US",
    "sg:address":"318 Forester Ave",
    "sg:city":"North Wilkesboro",
    "sg:classifiers":[
        {
            "category":"Professional",
            "subcategory":"Credit Reporting & Collection",
            "type":"Services"
        }
    ],
    "sg:phone":"+1 336 667 7400",
    "sg:postcode":"28659",
    "sg:province":"NC",
    "sg:tags":[
        "agency"
    ],
    "wof:name":"Allied Recovery",
    "wof:placetype":"venue"
},
  "geometry": {"coordinates":[-81.149192,36.159936],"type":"Point"}
}