{
  "type": "Feature",
  "properties": {
    "iso:country":"US",
    "sg:address":"145 Madison Rd",
    "sg:city":"Mocksville",
    "sg:classifiers":[
        {
            "category":"Freight",
            "type":"Transportation"
        }
    ],
    "sg:phone":"+1 336 751 1102",
    "sg:postcode":"27028",
    "sg:province":"NC",
    "sg:tags":[
        "operator",
        "local",
        "trucking"
    ],
    "wof:name":"Greg Butcher Trucking Inc",
    "wof:placetype":"venue"
},
  "geometry": {"coordinates":[-80.59589099999999,35.905099],"type":"Point"}
}