{
  "type": "Feature",
  "properties": {
    "addr:full":"312 W Palmer St Raeford NC 28376",
    "addr:housenumber":"312",
    "addr:postcode":"28376",
    "addr:street":"W Palmer St",
    "iso:country":"US",
    "sg:address":"312 W Palmer St",
    "sg:city":"Raeford",
    "sg:classifiers":[
        {
            "category":"Organizations",
            "subcategory":"Religious Organization",
            "type":"Services"
        }
    ],
    "sg:phone":"+1   ",
    "sg:postcode":"28376",
    "sg:province":"NC",
    "wof:name":"Kingdom Hall Jhovahs Witnesses",
    "wof:placetype":"venue"
},
  "geometry": {"coordinates":[-79.244941,34.976556],"type":"Point"}
}