{
  "type": "Feature",
  "properties": {
    "addr:full":"1017 E Main St Lincolnton NC 28092",
    "addr:housenumber":"1017",
    "addr:postcode":"28092",
    "addr:street":"E Main St",
    "iso:country":"US",
    "sg:address":"1017 E Main St",
    "sg:city":"Lincolnton",
    "sg:classifiers":[
        {
            "category":"Autos & Motor Vehicles",
            "subcategory":"Auto Supplies",
            "type":"Retail Goods"
        }
    ],
    "sg:phone":"+1 704 732 2223",
    "sg:postcode":"28092",
    "sg:province":"NC",
    "sg:tags":[
        "equipment",
        "parts",
        "electrical",
        "automobile"
    ],
    "sg:website":"www.advanceautoparts.com",
    "wof:name":"Advance Auto Parts Inc",
    "wof:placetype":"venue"
},
  "geometry": {"coordinates":[-81.245442,35.475074],"type":"Point"}
}