{
  "type": "Feature",
  "properties": {
    "iso:country":"US",
    "sg:address":"1230 Spring Ave",
    "sg:city":"Spring Lake",
    "sg:classifiers":[
        {
            "category":"Organizations",
            "subcategory":"Religious Organization",
            "type":"Services"
        }
    ],
    "sg:phone":"+1   ",
    "sg:postcode":"28390",
    "sg:province":"NC",
    "wof:name":"William Chapel",
    "wof:placetype":"venue"
},
  "geometry": {"coordinates":[-78.961648,35.170575],"type":"Point"}
}