{
  "type": "Feature",
  "properties": {
    "iso:country":"US",
    "sg:address":"1458 Ellisboro Rd",
    "sg:city":"Madison",
    "sg:classifiers":[
        {
            "category":"Organizations",
            "subcategory":"Community Association",
            "type":"Services"
        }
    ],
    "sg:phone":"+1 336 427 4844",
    "sg:postcode":"27025",
    "sg:province":"NC",
    "wof:name":"Huntsville Community Club Inc",
    "wof:placetype":"venue"
},
  "geometry": {"coordinates":[-79.967167,36.351158],"type":"Point"}
}