{
  "type": "Feature",
  "properties": {
    "iso:country":"US",
    "sg:address":"3012 Mason St",
    "sg:city":"Monroe",
    "sg:classifiers":[
        {
            "category":"Professional",
            "type":"Services"
        }
    ],
    "sg:phone":"+1 704 289 4646",
    "sg:postcode":"28110",
    "sg:province":"NC",
    "sg:tags":[
        "establishment"
    ],
    "wof:name":"Cooper Group",
    "wof:placetype":"venue"
},
  "geometry": {"coordinates":[-80.491028,34.991425],"type":"Point"}
}