{
  "type": "Feature",
  "properties": {
    "iso:country":"US",
    "sg:address":"85 Lanvale Ave",
    "sg:city":"Asheville",
    "sg:classifiers":[
        {
            "category":"Professional",
            "subcategory":"Management & Consulting",
            "type":"Services"
        }
    ],
    "sg:phone":"+1   ",
    "sg:postcode":"28806",
    "sg:province":"NC",
    "sg:tags":[
        "business"
    ],
    "wof:name":"Final Mile Inc",
    "wof:placetype":"venue"
},
  "geometry": {"coordinates":[-82.598491,35.577551],"type":"Point"}
}