{
  "type": "Feature",
  "properties": {
    "iso:country":"US",
    "sg:address":"7548 McEwen Lake Ln",
    "sg:city":"Charlotte",
    "sg:classifiers":[
        {
            "category":"Building & Trades",
            "subcategory":"Construction",
            "type":"Services"
        }
    ],
    "sg:phone":"+1 704 545 8126",
    "sg:postcode":"28227",
    "sg:province":"NC",
    "sg:tags":[
        "gen",
        "contractor"
    ],
    "wof:name":"Dick Lamb Builder",
    "wof:placetype":"venue"
},
  "geometry": {"coordinates":[-80.65416,35.178972],"type":"Point"}
}