{
  "type": "Feature",
  "properties": {
    "addr:full":"9408 S Mere Ct Raleigh NC 27615",
    "addr:housenumber":"9408",
    "addr:postcode":"27615",
    "addr:street":"S Mere Ct",
    "iso:country":"US",
    "sg:address":"9408 S Mere Ct",
    "sg:city":"Raleigh",
    "sg:classifiers":[
        {
            "category":"Building & Trades",
            "subcategory":"Construction",
            "type":"Services"
        }
    ],
    "sg:phone":"+1 919 676 8565",
    "sg:postcode":"27615",
    "sg:province":"NC",
    "sg:tags":[
        "house"
    ],
    "wof:name":"Wagoners Home Improvements",
    "wof:placetype":"venue"
},
  "geometry": {"coordinates":[-78.604632,35.903625],"type":"Point"}
}