{
  "type": "Feature",
  "properties": {
    "iso:country":"US",
    "sg:address":"87 McCachern Blvd SE",
    "sg:city":"Concord",
    "sg:classifiers":[
        {
            "category":"Shopping",
            "subcategory":"Used Merchandise",
            "type":"Retail Goods"
        }
    ],
    "sg:phone":"+1 704 782 7797",
    "sg:postcode":"28025",
    "sg:province":"NC",
    "sg:tags":[
        "shop",
        "consignment"
    ],
    "wof:name":"Open Door General Store Inc",
    "wof:placetype":"venue"
},
  "geometry": {"coordinates":[-80.57770600000001,35.411098],"type":"Point"}
}