{
  "type": "Feature",
  "properties": {
    "iso:country":"US",
    "sg:address":"11 James Tart Rd",
    "sg:city":"Lillington",
    "sg:classifiers":[
        {
            "category":"Restaurant",
            "type":"Food & Drink"
        }
    ],
    "sg:phone":"+1 910 893 6418",
    "sg:postcode":"27546",
    "sg:province":"NC",
    "sg:tags":[
        "eating"
    ],
    "wof:name":"B JS Diner",
    "wof:placetype":"venue"
},
  "geometry": {"coordinates":[-78.76828500000001,35.344351],"type":"Point"}
}