{
  "type": "Feature",
  "properties": {
    "addr:full":"390 White Plains Rd Hiddenite NC 28636",
    "addr:housenumber":"390",
    "addr:postcode":"28636",
    "addr:street":"White Plains Rd",
    "iso:country":"US",
    "sg:address":"390 White Plains Rd",
    "sg:city":"Hiddenite",
    "sg:classifiers":[
        {
            "category":"Building & Trades",
            "subcategory":"Equipment Rental",
            "type":"Services"
        }
    ],
    "sg:phone":"+1 828 632 9810",
    "sg:postcode":"28636",
    "sg:province":"NC",
    "sg:tags":[
        "aircraft",
        "leasing",
        "charter"
    ],
    "wof:name":"Gryder Aviation",
    "wof:placetype":"venue"
},
  "geometry": {"coordinates":[-81.121393,35.924154],"type":"Point"}
}