{
  "type": "Feature",
  "properties": {
    "iso:country":"US",
    "sg:address":"1508 Rector St",
    "sg:city":"Granite Falls",
    "sg:classifiers":[
        {
            "category":"Wholesale",
            "subcategory":"Groceries",
            "type":"Manufacturing & Wholesale Goods"
        }
    ],
    "sg:phone":"+1 828 728 6221",
    "sg:postcode":"28630",
    "sg:province":"NC",
    "sg:tags":[
        "grocer"
    ],
    "wof:name":"Odum's Salvage",
    "wof:placetype":"venue"
},
  "geometry": {"coordinates":[-81.541214,35.810807],"type":"Point"}
}