{
  "type": "Feature",
  "properties": {
    "addr:full":"2681 Lewisville Clemmons Rd Clemmons NC 27012",
    "addr:housenumber":"2681",
    "addr:postcode":"27012",
    "addr:street":"Lewisville Clemmons Rd",
    "iso:country":"US",
    "sg:address":"2681 Lewisville Clemmons Rd",
    "sg:city":"Clemmons",
    "sg:classifiers":[
        {
            "category":"Shopping",
            "type":"Retail Goods"
        }
    ],
    "sg:phone":"+1 336 766 5742",
    "sg:postcode":"27012",
    "sg:province":"NC",
    "sg:tags":[
        "picture",
        "frame"
    ],
    "wof:name":"Frameshop",
    "wof:placetype":"venue"
},
  "geometry": {"coordinates":[-80.38201599999999,36.024393],"type":"Point"}
}