{
  "type": "Feature",
  "properties": {
    "addr:full":"502 Cross Creek Mall Fayetteville NC 28303",
    "addr:housenumber":"502",
    "addr:postcode":"28303",
    "addr:street":"Cross Creek Mall",
    "iso:country":"US",
    "sg:address":"502 Cross Creek Mall",
    "sg:city":"Fayetteville",
    "sg:classifiers":[
        {
            "category":"Restaurant",
            "type":"Food & Drink"
        }
    ],
    "sg:menulink":"http://www.allmenus.com/nc/seventy-first/8741-red-robin/menu/",
    "sg:phone":"+1 910 864 4550",
    "sg:postcode":"28303",
    "sg:province":"NC",
    "sg:tags":[
        "american"
    ],
    "wof:name":"Red Robin",
    "wof:placetype":"venue"
},
  "geometry": {"coordinates":[-78.959788,35.082686],"type":"Point"}
}