{
  "type": "Feature",
  "properties": {
    "iso:country":"US",
    "sg:address":"8713 Cinnabay Dr",
    "sg:city":"Charlotte",
    "sg:classifiers":[
        {
            "category":"Professional",
            "subcategory":"Advertising",
            "type":"Services"
        }
    ],
    "sg:phone":"+1   ",
    "sg:postcode":"28216",
    "sg:province":"NC",
    "sg:tags":[
        "agency"
    ],
    "wof:name":"Stargayzer Inc",
    "wof:placetype":"venue"
},
  "geometry": {"coordinates":[-80.87252700000001,35.344455],"type":"Point"}
}