{
  "type": "Feature",
  "properties": {
    "iso:country":"US",
    "sg:address":"436 Rodney Orr Byp",
    "sg:city":"Robbinsville",
    "sg:classifiers":[
        {
            "category":"Sports & Exercise",
            "subcategory":"Gym",
            "type":"Entertainment"
        }
    ],
    "sg:phone":"+1   ",
    "sg:postcode":"28771",
    "sg:province":"NC",
    "sg:tags":[
        "physical",
        "center",
        "fitness"
    ],
    "wof:name":"Curves",
    "wof:placetype":"venue"
},
  "geometry": {"coordinates":[-83.804322,35.326487],"type":"Point"}
}