{
  "type": "Feature",
  "properties": {
    "addr:full":"303 W King St La Grange NC 28551",
    "addr:housenumber":"303",
    "addr:postcode":"28551",
    "addr:street":"W King St",
    "iso:country":"US",
    "sg:address":"303 W King St",
    "sg:city":"La Grange",
    "sg:classifiers":[
        {
            "category":"Personal",
            "subcategory":"Barber",
            "type":"Services"
        }
    ],
    "sg:phone":"+1   ",
    "sg:postcode":"28551",
    "sg:province":"NC",
    "sg:tags":[
        "shop"
    ],
    "wof:name":"Garden Spot Barber Shop",
    "wof:placetype":"venue"
},
  "geometry": {"coordinates":[-77.791983,35.311206],"type":"Point"}
}