{
  "type": "Feature",
  "properties": {
    "addr:full":"801 Ward Blvd Wilson NC 27893",
    "addr:housenumber":"801",
    "addr:postcode":"27893",
    "addr:street":"Ward Blvd",
    "iso:country":"US",
    "sg:address":"801 Ward Blvd",
    "sg:city":"Wilson",
    "sg:classifiers":[
        {
            "category":"Shopping",
            "subcategory":"Clothing, Apparel, & Fashions",
            "type":"Retail Goods"
        }
    ],
    "sg:phone":"+1 252 243 3401",
    "sg:postcode":"27893",
    "sg:province":"NC",
    "sg:tags":[
        "shop",
        "bridal"
    ],
    "wof:name":"Lucielle's Bridals & Formals",
    "wof:placetype":"venue"
},
  "geometry": {"coordinates":[-77.933621,35.716791],"type":"Point"}
}