{
  "type": "Feature",
  "properties": {
    "addr:full":"934 Cambridge St Fayetteville NC 28303",
    "addr:housenumber":"934",
    "addr:postcode":"28303",
    "addr:street":"Cambridge St",
    "iso:country":"US",
    "sg:address":"934 Cambridge St",
    "sg:city":"Fayetteville",
    "sg:classifiers":[
        {
            "category":"Arts & Performance",
            "subcategory":"Theater",
            "type":"Entertainment"
        }
    ],
    "sg:phone":"+1   ",
    "sg:postcode":"28303",
    "sg:province":"NC",
    "sg:tags":[
        "theatrical"
    ],
    "wof:name":"Stage Door Theatr",
    "wof:placetype":"venue"
},
  "geometry": {"coordinates":[-78.932761,35.044831],"type":"Point"}
}