{
  "type": "Feature",
  "properties": {
    "iso:country":"US",
    "sg:address":"3935 Statesville Ave",
    "sg:city":"Charlotte",
    "sg:classifiers":[
        {
            "category":"Arts & Performance",
            "subcategory":"Theater",
            "type":"Entertainment"
        }
    ],
    "sg:phone":"+1 704 373 1404",
    "sg:postcode":"28206",
    "sg:province":"NC",
    "sg:tags":[
        "entertainer"
    ],
    "wof:name":"Peaches N Cream Cabaret",
    "wof:placetype":"venue"
},
  "geometry": {"coordinates":[-80.837529,35.270416],"type":"Point"}
}