{
  "type": "Feature",
  "properties": {
    "iso:country":"US",
    "sg:address":"1367 E Garrison Blvd",
    "sg:city":"Gastonia",
    "sg:classifiers":[
        {
            "category":"Health Services",
            "subcategory":"Doctor",
            "type":"Services"
        }
    ],
    "sg:phone":"+1 704 864 8393",
    "sg:postcode":"28054",
    "sg:province":"NC",
    "sg:tags":[
        "dentist"
    ],
    "wof:name":"Stover & Stover",
    "wof:placetype":"venue"
},
  "geometry": {"coordinates":[-81.162413,35.25269],"type":"Point"}
}