{
  "type": "Feature",
  "properties": {
    "addr:full":"3921 Highway 74 E Wingate NC 28174",
    "addr:housenumber":"3921",
    "addr:postcode":"28174",
    "addr:street":"Highway 74 E Wingate",
    "iso:country":"US",
    "sg:address":"3921 Highway 74 E",
    "sg:city":"Wingate",
    "sg:classifiers":[
        {
            "category":"Restaurant",
            "type":"Food & Drink"
        }
    ],
    "sg:menulink":"http://www.allmenus.com/nc/monroe/236855-tokyo-bistro/menu/",
    "sg:phone":"+1 704 233 0378",
    "sg:postcode":"28174",
    "sg:province":"NC",
    "sg:tags":[
        "japanese",
        "asian"
    ],
    "wof:name":"Tokyo Bistro",
    "wof:placetype":"venue"
},
  "geometry": {"coordinates":[-80.45038599999999,34.982704],"type":"Point"}
}