{
  "type": "Feature",
  "properties": {
    "iso:country":"US",
    "sg:address":"1074 Ridge Rd",
    "sg:city":"Mocksville",
    "sg:classifiers":[
        {
            "category":"Building & Trades",
            "subcategory":"Construction",
            "type":"Services"
        }
    ],
    "sg:phone":"+1 336 492 7260",
    "sg:postcode":"27028",
    "sg:province":"NC",
    "sg:tags":[
        "house"
    ],
    "wof:name":"Tutterow Remodeling",
    "wof:placetype":"venue"
},
  "geometry": {"coordinates":[-80.671688,35.870067],"type":"Point"}
}