{
  "type": "Feature",
  "properties": {
    "addr:full":"313 SE Maynard Rd Cary NC 27511",
    "addr:housenumber":"313",
    "addr:postcode":"27511",
    "addr:street":"Se Maynard Rd",
    "iso:country":"US",
    "sg:address":"313 SE Maynard Rd",
    "sg:city":"Cary",
    "sg:classifiers":[
        {
            "category":"Social Services",
            "subcategory":"Child Care",
            "type":"Services"
        }
    ],
    "sg:phone":"+1 919 469 2217",
    "sg:postcode":"27511",
    "sg:province":"NC",
    "sg:tags":[
        "day"
    ],
    "sg:website":"www.wpcckids.org",
    "wof:name":"White Plains Children's Center",
    "wof:placetype":"venue"
},
  "geometry": {"coordinates":[-78.77419999999999,35.767399],"type":"Point"}
}