{
  "type": "Feature",
  "properties": {
    "addr:full":"4130 River Rd Midland NC 28107",
    "addr:housenumber":"4130",
    "addr:postcode":"28107",
    "addr:street":"River Rd",
    "iso:country":"US",
    "sg:address":"4130 River Rd",
    "sg:city":"Midland",
    "sg:classifiers":[
        {
            "category":"Professional",
            "type":"Services"
        }
    ],
    "sg:phone":"+1 704 888 3030",
    "sg:postcode":"28107",
    "sg:province":"NC",
    "wof:name":"Conklin",
    "wof:placetype":"venue"
},
  "geometry": {"coordinates":[-80.460229,35.224574],"type":"Point"}
}