{
  "type": "Feature",
  "properties": {
    "iso:country":"US",
    "sg:address":"112 Kimberly Ave",
    "sg:city":"Asheville",
    "sg:classifiers":[
        {
            "category":"Building & Trades",
            "subcategory":"Plumbing",
            "type":"Services"
        }
    ],
    "sg:phone":"+1 828 252 0807",
    "sg:postcode":"28804",
    "sg:province":"NC",
    "sg:tags":[
        "contractor"
    ],
    "wof:name":"Carolina Moutain Cooling",
    "wof:placetype":"venue"
},
  "geometry": {"coordinates":[-82.549784,35.617629],"type":"Point"}
}