{
  "type": "Feature",
  "properties": {
    "iso:country":"US",
    "sg:address":"146 Wiggins Rd",
    "sg:city":"Candler",
    "sg:classifiers":[
        {
            "category":"Food & Beverages",
            "subcategory":"Groceries & Convenience Stores",
            "type":"Retail Goods"
        }
    ],
    "sg:phone":"+1 828 667 5092",
    "sg:postcode":"28715",
    "sg:province":"NC",
    "wof:name":"One Stop #15",
    "wof:placetype":"venue"
},
  "geometry": {"coordinates":[-82.75331199999999,35.543427],"type":"Point"}
}