{
  "type": "Feature",
  "properties": {
    "iso:country":"US",
    "sg:address":"6240 Old Davis Rd",
    "sg:city":"Sims",
    "sg:classifiers":[
        {
            "category":"Home & Garden",
            "subcategory":"Carpets & Floor Coverings",
            "type":"Retail Goods"
        }
    ],
    "sg:phone":"+1 252 314 4216",
    "sg:postcode":"27880",
    "sg:province":"NC",
    "wof:name":"Langleys Carpet Service Inc",
    "wof:placetype":"venue"
},
  "geometry": {"coordinates":[-78.045601,35.742201],"type":"Point"}
}