{
  "type": "Feature",
  "properties": {
    "iso:country":"US",
    "sg:address":"311B Alpha Mill Ln",
    "sg:city":"Charlotte",
    "sg:classifiers":[
        {
            "category":"Building & Trades",
            "subcategory":"Construction",
            "type":"Services"
        }
    ],
    "sg:phone":"+1 336 926 0258",
    "sg:postcode":"28206",
    "sg:province":"NC",
    "sg:tags":[
        "contractor"
    ],
    "wof:name":"Lyme Light Enterprises",
    "wof:placetype":"venue"
},
  "geometry": {"coordinates":[-80.830752,35.232558],"type":"Point"}
}