{
  "type": "Feature",
  "properties": {
    "iso:country":"US",
    "sg:address":"1957 Peace Haven Rd N",
    "sg:city":"Winston Salem",
    "sg:classifiers":[
        {
            "category":"Banks & Credit Unions",
            "subcategory":"Investment Brokerage",
            "type":"Services"
        }
    ],
    "sg:phone":"+1 336 768 1566",
    "sg:postcode":"27106",
    "sg:province":"NC",
    "sg:tags":[
        "stock",
        "bond"
    ],
    "wof:name":"Edward Jones Investments",
    "wof:placetype":"venue"
},
  "geometry": {"coordinates":[-80.31368000000001,36.117532],"type":"Point"}
}