{
  "type": "Feature",
  "properties": {
    "iso:country":"US",
    "sg:address":"3100 E Independence Blvd",
    "sg:city":"Charlotte",
    "sg:classifiers":[
        {
            "category":"Retail",
            "subcategory":"Auto Repair",
            "type":"Services"
        }
    ],
    "sg:phone":"+1   ",
    "sg:postcode":"28205",
    "sg:province":"NC",
    "sg:tags":[
        "general"
    ],
    "wof:name":"Latino Auto Repair",
    "wof:placetype":"venue"
},
  "geometry": {"coordinates":[-80.79042200000001,35.202816],"type":"Point"}
}