{
  "type": "Feature",
  "properties": {
    "iso:country":"US",
    "sg:address":"1801 Seabrook Rd",
    "sg:city":"Fayetteville",
    "sg:classifiers":[
        {
            "category":"Organizations",
            "subcategory":"Religious Organization",
            "type":"Services"
        },
        {
            "category":"Education",
            "subcategory":"School",
            "type":"Public Place"
        }
    ],
    "sg:phone":"+1 910 323 4828",
    "sg:postcode":"28301",
    "sg:province":"NC",
    "sg:tags":[
        "church"
    ],
    "wof:name":"College Heights Presbyterian",
    "wof:placetype":"venue"
},
  "geometry": {"coordinates":[-78.89850199999999,35.086721],"type":"Point"}
}