{
  "type": "Feature",
  "properties": {
    "iso:country":"US",
    "sg:address":"131 E Parris Ave",
    "sg:city":"High Point",
    "sg:classifiers":[
        {
            "category":"Food & Beverages",
            "subcategory":"Groceries & Convenience Stores",
            "type":"Retail Goods"
        }
    ],
    "sg:phone":"+1 336 886 2003",
    "sg:postcode":"27262",
    "sg:province":"NC",
    "sg:tags":[
        "market"
    ],
    "wof:name":"Market Direction",
    "wof:placetype":"venue"
},
  "geometry": {"coordinates":[-80.021844,35.984844],"type":"Point"}
}