{
  "type": "Feature",
  "properties": {
    "iso:country":"US",
    "sg:address":"403 Lorraine St",
    "sg:city":"Carrboro",
    "sg:classifiers":[
        {
            "category":"Professional",
            "subcategory":"Business Services",
            "type":"Services"
        }
    ],
    "sg:phone":"+1   ",
    "sg:postcode":"27510",
    "sg:province":"NC",
    "wof:name":"Vanfleet John & Paige",
    "wof:placetype":"venue"
},
  "geometry": {"coordinates":[-79.091667,35.919934],"type":"Point"}
}