{
  "type": "Feature",
  "properties": {
    "addr:full":"976 Airport Rd Ste 100 Chapel Hill NC 27514",
    "addr:housenumber":"976",
    "addr:postcode":"27514",
    "addr:street":"Airport Rd Ste 100",
    "iso:country":"US",
    "sg:address":"976 Airport Rd Ste 100",
    "sg:city":"Chapel Hill",
    "sg:classifiers":[
        {
            "category":"Health Services",
            "subcategory":"Clinic",
            "type":"Services"
        }
    ],
    "sg:phone":"+1 919 933 6500",
    "sg:postcode":"27514",
    "sg:province":"NC",
    "sg:tags":[
        "counseling",
        "mental"
    ],
    "wof:name":"Smith Peter J Dr Psycholgst",
    "wof:placetype":"venue"
},
  "geometry": {"coordinates":[-79.05529799999999,35.9319],"type":"Point"}
}