{
  "type": "Feature",
  "properties": {
    "addr:full":"3601 Carpenter Pond Rd Durham NC 27703",
    "addr:housenumber":"3601",
    "addr:postcode":"27703",
    "addr:street":"Carpenter Pond Rd",
    "iso:country":"US",
    "sg:address":"3601 Carpenter Pond Rd",
    "sg:city":"Durham",
    "sg:classifiers":[
        {
            "category":"Retail",
            "subcategory":"Repair Shop",
            "type":"Services"
        }
    ],
    "sg:phone":"+1   ",
    "sg:postcode":"27703",
    "sg:province":"NC",
    "sg:tags":[
        "armature",
        "rewinding"
    ],
    "wof:name":"Jims Electric Motor Repair",
    "wof:placetype":"venue"
},
  "geometry": {"coordinates":[-78.75312700000001,35.933972],"type":"Point"}
}