{
  "type": "Feature",
  "properties": {
    "addr:full":"1628 Highwoods Blvd Greensboro NC 27410",
    "addr:housenumber":"1628",
    "addr:postcode":"27410",
    "addr:street":"Highwoods Blvd",
    "iso:country":"US",
    "sg:address":"1628 Highwoods Blvd",
    "sg:city":"Greensboro",
    "sg:classifiers":[
        {
            "category":"Professional",
            "type":"Services"
        }
    ],
    "sg:phone":"+1 336 294 0155",
    "sg:postcode":"27410",
    "sg:province":"NC",
    "sg:tags":[
        "establishment"
    ],
    "wof:name":"John S Clark Co",
    "wof:placetype":"venue"
},
  "geometry": {"coordinates":[-79.87789600000001,36.113758],"type":"Point"}
}