{
  "type": "Feature",
  "properties": {
    "iso:country":"US",
    "sg:address":"347 Merrimon Ave",
    "sg:city":"Asheville",
    "sg:classifiers":[
        {
            "category":"Professional",
            "type":"Services"
        }
    ],
    "sg:phone":"+1 828 232 0208",
    "sg:postcode":"28801",
    "sg:province":"NC",
    "sg:tags":[
        "establishment"
    ],
    "wof:name":"STS Technologies",
    "wof:placetype":"venue"
},
  "geometry": {"coordinates":[-82.555097,35.612407],"type":"Point"}
}