{
  "type": "Feature",
  "properties": {
    "iso:country":"US",
    "sg:address":"202 Westwood Dr",
    "sg:city":"Lexington",
    "sg:classifiers":[
        {
            "category":"Building & Trades",
            "subcategory":"Electrical",
            "type":"Services"
        }
    ],
    "sg:phone":"+1 336 853 1052",
    "sg:postcode":"27295",
    "sg:province":"NC",
    "sg:tags":[
        "electric",
        "contractor"
    ],
    "wof:name":"Mccormick Electric",
    "wof:placetype":"venue"
},
  "geometry": {"coordinates":[-80.28230600000001,35.820474],"type":"Point"}
}