{
  "type": "Feature",
  "properties": {
    "iso:country":"US",
    "sg:address":"411 Andrews Rd",
    "sg:city":"Durham",
    "sg:classifiers":[
        {
            "category":"Professional",
            "subcategory":"Management & Consulting",
            "type":"Services"
        }
    ],
    "sg:phone":"+1 919 384 8180",
    "sg:postcode":"27705",
    "sg:province":"NC",
    "sg:tags":[
        "construction"
    ],
    "wof:name":"CPMFGO12",
    "wof:placetype":"venue"
},
  "geometry": {"coordinates":[-78.953585,36.015497],"type":"Point"}
}