{
  "type": "Feature",
  "properties": {
    "addr:full":"808 Rock Quarry Rd Raleigh NC 27610",
    "addr:housenumber":"808",
    "addr:postcode":"27610",
    "addr:street":"Rock Quarry Rd",
    "iso:country":"US",
    "sg:address":"808 Rock Quarry Rd",
    "sg:city":"Raleigh",
    "sg:classifiers":[
        {
            "category":"Shopping",
            "subcategory":"Shoes",
            "type":"Retail Goods"
        }
    ],
    "sg:phone":"+1 919 821 2038",
    "sg:postcode":"27610",
    "sg:province":"NC",
    "wof:name":"Shoe Diva's",
    "wof:placetype":"venue"
},
  "geometry": {"coordinates":[-78.61909900000001,35.769808],"type":"Point"}
}