{
  "type": "Feature",
  "properties": {
    "addr:full":"814 Kanuga Rd Hendersonville NC 28739",
    "addr:housenumber":"814",
    "addr:postcode":"28739",
    "addr:street":"Kanuga Rd",
    "iso:country":"US",
    "sg:address":"814 Kanuga Rd",
    "sg:city":"Hendersonville",
    "sg:classifiers":[
        {
            "category":"Professional",
            "subcategory":"Business Services",
            "type":"Services"
        }
    ],
    "sg:phone":"+1 828 697 0063",
    "sg:postcode":"28739",
    "sg:province":"NC",
    "sg:tags":[
        "water",
        "treatment"
    ],
    "wof:name":"James & James Environmental",
    "wof:placetype":"venue"
},
  "geometry": {"coordinates":[-82.462684,35.306033],"type":"Point"}
}