{
  "type": "Feature",
  "properties": {
    "iso:country":"US",
    "sg:address":"37335 Barnhardt Rd",
    "sg:city":"Albemarle",
    "sg:classifiers":[
        {
            "category":"Building & Trades",
            "subcategory":"Plumbing",
            "type":"Services"
        }
    ],
    "sg:phone":"+1 704 982 0176",
    "sg:postcode":"28001",
    "sg:province":"NC",
    "sg:tags":[
        "plumbing",
        "contractor"
    ],
    "wof:name":"Bill's Plumbing Co",
    "wof:placetype":"venue"
},
  "geometry": {"coordinates":[-80.164446,35.404152],"type":"Point"}
}