{
  "type": "Feature",
  "properties": {
    "iso:country":"US",
    "sg:address":"2813 W Sugar Creek Rd",
    "sg:city":"Charlotte",
    "sg:classifiers":[
        {
            "category":"Recreation",
            "type":"Entertainment"
        }
    ],
    "sg:phone":"+1   ",
    "sg:postcode":"28262",
    "sg:province":"NC",
    "wof:name":"American Martial Arts",
    "wof:placetype":"venue"
},
  "geometry": {"coordinates":[-80.80183,35.300588],"type":"Point"}
}