{
  "type": "Feature",
  "properties": {
    "iso:country":"US",
    "sg:address":"1005 Meadowlark Ln",
    "sg:city":"Waxhaw",
    "sg:classifiers":[
        {
            "category":"Professional",
            "subcategory":"Advertising",
            "type":"Services"
        }
    ],
    "sg:phone":"+1   ",
    "sg:postcode":"28173",
    "sg:province":"NC",
    "sg:tags":[
        "agency"
    ],
    "wof:name":"Scott E Lett Associates",
    "wof:placetype":"venue"
},
  "geometry": {"coordinates":[-80.820877,34.994599],"type":"Point"}
}