{
  "type": "Feature",
  "properties": {
    "addr:full":"700 Beverly Hanks Center Hendersonville NC 28792",
    "addr:housenumber":"700",
    "addr:postcode":"28792",
    "addr:street":"Beverly Hanks Center",
    "iso:country":"US",
    "sg:address":"700 Beverly Hanks Center",
    "sg:city":"Hendersonville",
    "sg:classifiers":[
        {
            "category":"Health Services",
            "subcategory":"Doctor",
            "type":"Services"
        }
    ],
    "sg:phone":"+1 828 692 0488",
    "sg:postcode":"28792",
    "sg:province":"NC",
    "sg:tags":[
        "physician",
        "surgeon"
    ],
    "wof:name":"Mountain Allergy & Asthma",
    "wof:placetype":"venue"
},
  "geometry": {"coordinates":[-82.467111,35.331083],"type":"Point"}
}