{
  "type": "Feature",
  "properties": {
    "iso:country":"US",
    "sg:address":"700 Sunset Ave",
    "sg:city":"Asheboro",
    "sg:classifiers":[
        {
            "category":"Health Services",
            "subcategory":"Doctor",
            "type":"Services"
        }
    ],
    "sg:phone":"+1 336 625 0305",
    "sg:postcode":"27203",
    "sg:province":"NC",
    "sg:tags":[
        "physician",
        "surgeon"
    ],
    "wof:name":"Bennett I Fein MD",
    "wof:placetype":"venue"
},
  "geometry": {"coordinates":[-79.82263,35.706156],"type":"Point"}
}