{
  "type": "Feature",
  "properties": {
    "addr:full":"5171 Davis Rd Winston Salem NC 27105",
    "addr:housenumber":"5171",
    "addr:postcode":"27105",
    "addr:street":"Davis Rd",
    "iso:country":"US",
    "sg:address":"5171 Davis Rd",
    "sg:city":"Winston Salem",
    "sg:classifiers":[
        {
            "category":"Building & Trades",
            "subcategory":"Construction",
            "type":"Services"
        }
    ],
    "sg:phone":"+1 336 767 9769",
    "sg:postcode":"27105",
    "sg:province":"NC",
    "sg:tags":[
        "residential",
        "contractor",
        "commercial",
        "new"
    ],
    "wof:name":"Autry Construction Inc",
    "wof:placetype":"venue"
},
  "geometry": {"coordinates":[-80.205038,36.174554],"type":"Point"}
}