{
  "type": "Feature",
  "properties": {
    "addr:full":"901 Hargett St Jacksonville NC 28540",
    "addr:housenumber":"901",
    "addr:postcode":"28540",
    "addr:street":"Hargett St",
    "iso:country":"US",
    "sg:address":"901 Hargett St",
    "sg:city":"Jacksonville",
    "sg:classifiers":[
        {
            "category":"Banks & Credit Unions",
            "subcategory":"Bank",
            "type":"Services"
        }
    ],
    "sg:phone":"+1 910 346 7200",
    "sg:postcode":"28540",
    "sg:province":"NC",
    "sg:tags":[
        "national",
        "commercial"
    ],
    "wof:name":"Wachovia Bank",
    "wof:placetype":"venue"
},
  "geometry": {"coordinates":[-77.415353,34.749877],"type":"Point"}
}