{
  "type": "Feature",
  "properties": {
    "iso:country":"US",
    "sg:address":"612 E Iowa Ave",
    "sg:city":"Bessemer City",
    "sg:classifiers":[
        {
            "category":"Retail",
            "subcategory":"Repair Shop",
            "type":"Services"
        }
    ],
    "sg:phone":"+1   ",
    "sg:postcode":"28016",
    "sg:province":"NC",
    "wof:name":"Sidney Hamilton Piano Tuning",
    "wof:placetype":"venue"
},
  "geometry": {"coordinates":[-81.27095199999999,35.289747],"type":"Point"}
}