{
  "type": "Feature",
  "properties": {
    "iso:country":"US",
    "sg:address":"102 Industrial Dr",
    "sg:city":"Nashville",
    "sg:classifiers":[
        {
            "category":"Health Services",
            "subcategory":"Doctor",
            "type":"Services"
        }
    ],
    "sg:phone":"+1 252 459 6600",
    "sg:postcode":"27839",
    "sg:province":"NC",
    "sg:tags":[
        "physician",
        "surgeon"
    ],
    "wof:name":"Yasmin Heater Internal",
    "wof:placetype":"venue"
},
  "geometry": {"coordinates":[-77.66809000000001,36.363496],"type":"Point"}
}