{
  "type": "Feature",
  "properties": {
    "iso:country":"US",
    "sg:address":"12 E Henderson St",
    "sg:city":"Marion",
    "sg:classifiers":[
        {
            "category":"Shopping",
            "subcategory":"Used Merchandise",
            "type":"Retail Goods"
        }
    ],
    "sg:phone":"+1 828 659 1474",
    "sg:postcode":"28752",
    "sg:province":"NC",
    "sg:tags":[
        "shop",
        "thrift"
    ],
    "wof:name":"Helping Hands Thrift Shop",
    "wof:placetype":"venue"
},
  "geometry": {"coordinates":[-82.007262,35.683249],"type":"Point"}
}