{
  "type": "Feature",
  "properties": {
    "iso:country":"US",
    "sg:address":"219 Franklin St",
    "sg:city":"Albemarle",
    "sg:classifiers":[
        {
            "category":"Building & Trades",
            "subcategory":"Cleaning & Sanitation",
            "type":"Services"
        }
    ],
    "sg:phone":"+1 704 982 2907",
    "sg:postcode":"28001",
    "sg:province":"NC",
    "sg:tags":[
        "maintenance"
    ],
    "wof:name":"Whitley Maintenance Services",
    "wof:placetype":"venue"
},
  "geometry": {"coordinates":[-80.200867,35.356424],"type":"Point"}
}