{
  "type": "Feature",
  "properties": {
    "addr:full":"1410 Airlie Rd Wilmington NC 28403",
    "addr:housenumber":"1410",
    "addr:postcode":"28403",
    "addr:street":"Airlie Rd",
    "iso:country":"US",
    "sg:address":"1410 Airlie Rd",
    "sg:city":"Wilmington",
    "sg:classifiers":[
        {
            "category":"Recreation",
            "type":"Entertainment"
        }
    ],
    "sg:phone":"+1 910 791 0555",
    "sg:postcode":"28403",
    "sg:province":"NC",
    "sg:tags":[
        "guide"
    ],
    "wof:name":"Whipsaw Charter Boat",
    "wof:placetype":"venue"
},
  "geometry": {"coordinates":[-77.815108,34.217126],"type":"Point"}
}