{
  "type": "Feature",
  "properties": {
    "addr:full":"3832 Harden Rd Hope Mills NC 28348",
    "addr:housenumber":"3832",
    "addr:postcode":"28348",
    "addr:street":"Harden Rd",
    "iso:country":"US",
    "sg:address":"3832 Harden Rd",
    "sg:city":"Hope Mills",
    "sg:classifiers":[
        {
            "category":"Personal",
            "type":"Services"
        }
    ],
    "sg:phone":"+1 910 424 1884",
    "sg:postcode":"28348",
    "sg:province":"NC",
    "sg:tags":[
        "miscellaneous"
    ],
    "wof:name":"Psalms Of Praise Ministries",
    "wof:placetype":"venue"
},
  "geometry": {"coordinates":[-78.92715699999999,34.995277],"type":"Point"}
}