{
  "type": "Feature",
  "properties": {
    "addr:full":"246 N New Hope Rd Gastonia NC 28054",
    "addr:housenumber":"246",
    "addr:postcode":"28054",
    "addr:street":"N New Hope Rd",
    "iso:country":"US",
    "sg:address":"246 N New Hope Rd",
    "sg:city":"Gastonia",
    "sg:classifiers":[
        {
            "category":"Shopping",
            "subcategory":"Clothing, Apparel, & Fashions",
            "type":"Retail Goods"
        }
    ],
    "sg:phone":"+1 704 861 8808",
    "sg:postcode":"28054",
    "sg:province":"NC",
    "wof:name":"Afterthoughts",
    "wof:placetype":"venue"
},
  "geometry": {"coordinates":[-81.151724,35.264114],"type":"Point"}
}