{
  "type": "Feature",
  "properties": {
    "iso:country":"US",
    "sg:address":"1244 N Main St",
    "sg:city":"Lillington",
    "sg:classifiers":[
        {
            "category":"Retail",
            "subcategory":"Animal Services",
            "type":"Services"
        }
    ],
    "sg:phone":"+1 910 893 8080",
    "sg:postcode":"27546",
    "sg:province":"NC",
    "wof:name":"Pet Grooming By Debbie",
    "wof:placetype":"venue"
},
  "geometry": {"coordinates":[-78.805182,35.415805],"type":"Point"}
}