{
  "type": "Feature",
  "properties": {
    "addr:full":"1648 Mount Carmel Rd Carthage NC 28327",
    "addr:housenumber":"1648",
    "addr:postcode":"28327",
    "addr:street":"Mount Carmel Rd",
    "iso:country":"US",
    "sg:address":"1648 Mount Carmel Rd",
    "sg:city":"Carthage",
    "sg:classifiers":[
        {
            "category":"Professional",
            "type":"Services"
        }
    ],
    "sg:phone":"+1 910 948 3111",
    "sg:postcode":"28327",
    "sg:province":"NC",
    "wof:name":"James C Allred",
    "wof:placetype":"venue"
},
  "geometry": {"coordinates":[-79.550681,35.361586],"type":"Point"}
}