{
  "type": "Feature",
  "properties": {
    "addr:full":"4850 State Hwy 49 S Harrisburg NC 28075",
    "addr:housenumber":"4850",
    "addr:postcode":"28075",
    "addr:street":"State Hwy 49 S",
    "iso:country":"US",
    "sg:address":"4850 State Hwy 49 S",
    "sg:city":"Harrisburg",
    "sg:classifiers":[
        {
            "category":"Restaurant",
            "type":"Food & Drink"
        }
    ],
    "sg:phone":"+1 704 455 1987",
    "sg:postcode":"28075",
    "sg:province":"NC",
    "wof:name":"Bojangles' Famous Chicken",
    "wof:placetype":"venue"
},
  "geometry": {"coordinates":[-80.656272,35.321646],"type":"Point"}
}