{
  "type": "Feature",
  "properties": {
    "addr:full":"1419 East Blvd Ste F Charlotte NC 28203",
    "addr:housenumber":"1419",
    "addr:postcode":"28203",
    "addr:street":"East Blvd Ste F",
    "iso:country":"US",
    "sg:address":"1419 East Blvd Ste F",
    "sg:city":"Charlotte",
    "sg:classifiers":[
        {
            "category":"Shopping",
            "subcategory":"Clothing, Apparel, & Fashions",
            "type":"Retail Goods"
        },
        {
            "category":"Shopping",
            "subcategory":"Adult",
            "type":"Retail Goods"
        }
    ],
    "sg:phone":"+1 704 377 7955",
    "sg:postcode":"28203",
    "sg:province":"NC",
    "sg:tags":[
        "corset",
        "girdle",
        "women's",
        "lingerie",
        "apparel",
        "bra"
    ],
    "wof:name":"Ic London Office",
    "wof:placetype":"venue"
},
  "geometry": {"coordinates":[-80.842888,35.20068],"type":"Point"}
}