{
  "type": "Feature",
  "properties": {
    "iso:country":"US",
    "sg:address":"503 Bowman Gray Dr",
    "sg:city":"Greenville",
    "sg:classifiers":[
        {
            "category":"Health Services",
            "subcategory":"Clinic",
            "type":"Services"
        }
    ],
    "sg:phone":"+1 252 758 8212",
    "sg:postcode":"27834",
    "sg:province":"NC",
    "sg:tags":[
        "home",
        "care"
    ],
    "wof:name":"Home Habitat Care",
    "wof:placetype":"venue"
},
  "geometry": {"coordinates":[-77.416259,35.604769],"type":"Point"}
}