{
  "type": "Feature",
  "properties": {
    "iso:country":"US",
    "sg:address":"826 Sunset Dr",
    "sg:city":"Pilot Mountain",
    "sg:classifiers":[
        {
            "category":"Professional",
            "type":"Services"
        }
    ],
    "sg:phone":"+1 336 368 2811",
    "sg:postcode":"27041",
    "sg:province":"NC",
    "sg:tags":[
        "establishment"
    ],
    "wof:name":"CRS Inc",
    "wof:placetype":"venue"
},
  "geometry": {"coordinates":[-80.47780899999999,36.391111],"type":"Point"}
}