{
  "type": "Feature",
  "properties": {
    "addr:full":"121 Washington St Yadkinville NC 27055",
    "addr:housenumber":"121",
    "addr:postcode":"27055",
    "addr:street":"Washington St",
    "iso:country":"US",
    "sg:address":"121 Washington St",
    "sg:city":"Yadkinville",
    "sg:classifiers":[
        {
            "category":"Education",
            "subcategory":"School",
            "type":"Public Place"
        }
    ],
    "sg:phone":"+1 336 679 2051",
    "sg:postcode":"27055",
    "sg:province":"NC",
    "sg:tags":[
        "district"
    ],
    "wof:name":"Yadkin County School District",
    "wof:placetype":"venue"
},
  "geometry": {"coordinates":[-80.66904,36.135829],"type":"Point"}
}