{
  "type": "Feature",
  "properties": {
    "iso:country":"US",
    "sg:address":"1031 River St",
    "sg:city":"Wilkesboro",
    "sg:classifiers":[
        {
            "category":"Autos & Motor Vehicles",
            "subcategory":"Automobile Sales",
            "type":"Retail Goods"
        }
    ],
    "sg:phone":"+1 336 838 1951",
    "sg:postcode":"28697",
    "sg:province":"NC",
    "sg:tags":[
        "car",
        "dealer"
    ],
    "wof:name":"Dwight Phillips Auto Sales Inc",
    "wof:placetype":"venue"
},
  "geometry": {"coordinates":[-81.17095500000001,36.141201],"type":"Point"}
}