{
  "type": "Feature",
  "properties": {
    "addr:full":"4133 Tyng Way Charlotte NC 28211",
    "addr:postcode":"4133;28211",
    "addr:street":"Tyng Way",
    "iso:country":"US",
    "sg:address":"4133 Tyng Way",
    "sg:city":"Charlotte",
    "sg:classifiers":[
        {
            "category":"Insurance",
            "subcategory":"Hazard Insurance",
            "type":"Services"
        }
    ],
    "sg:phone":"+1 704 362 5600",
    "sg:postcode":"28211",
    "sg:province":"NC",
    "sg:tags":[
        "fidelity",
        "carrier",
        "surety",
        "bond"
    ],
    "wof:name":"A-1",
    "wof:placetype":"venue"
},
  "geometry": {"coordinates":[-80.804616,35.179208],"type":"Point"}
}