{
  "type": "Feature",
  "properties": {
    "iso:country":"US",
    "sg:address":"6555 Comm Scope Rd",
    "sg:city":"Catawba",
    "sg:classifiers":[
        {
            "category":"Wholesale",
            "subcategory":"Metals & Minerals",
            "type":"Manufacturing & Wholesale Goods"
        }
    ],
    "sg:phone":"+1 828 241 3301",
    "sg:postcode":"28609",
    "sg:province":"NC",
    "sg:tags":[
        "aluminum"
    ],
    "sg:website":"www.alcoa.com",
    "wof:name":"Alcoa Engineered Products",
    "wof:placetype":"venue"
},
  "geometry": {"coordinates":[-81.032264,35.653686],"type":"Point"}
}