{
  "type": "Feature",
  "properties": {
    "iso:country":"US",
    "sg:address":"1134 Barkley Rd",
    "sg:city":"Statesville",
    "sg:classifiers":[
        {
            "category":"Recreation",
            "type":"Entertainment"
        }
    ],
    "sg:phone":"+1 704 873 0452",
    "sg:postcode":"28677",
    "sg:province":"NC",
    "sg:tags":[
        "bingo",
        "game"
    ],
    "wof:name":"Friendly Folks Beach Bingo",
    "wof:placetype":"venue"
},
  "geometry": {"coordinates":[-80.860671,35.758794],"type":"Point"}
}