{
  "type": "Feature",
  "properties": {
    "iso:country":"US",
    "sg:address":"6016 Stone Bluff Dr",
    "sg:city":"Clemmons",
    "sg:classifiers":[
        {
            "category":"Retail",
            "subcategory":"Repair Shop",
            "type":"Services"
        }
    ],
    "sg:phone":"+1 336 766 7128",
    "sg:postcode":"27012",
    "sg:province":"NC",
    "sg:tags":[
        "plumbing",
        "drain",
        "work",
        "cleaning"
    ],
    "wof:name":"Triad Rooter Service",
    "wof:placetype":"venue"
},
  "geometry": {"coordinates":[-80.354236,35.990936],"type":"Point"}
}