{
  "type": "Feature",
  "properties": {
    "iso:country":"US",
    "sg:address":"1101 W Main St",
    "sg:city":"Yadkinville",
    "sg:classifiers":[
        {
            "category":"Professional",
            "subcategory":"Business Services",
            "type":"Services"
        }
    ],
    "sg:phone":"+1   ",
    "sg:postcode":"27055",
    "sg:province":"NC",
    "wof:name":"Ausley Appraisal Service",
    "wof:placetype":"venue"
},
  "geometry": {"coordinates":[-80.678331,36.13565],"type":"Point"}
}