{
  "type": "Feature",
  "properties": {
    "addr:full":"1800 E Franklin St Chapel Hill NC 27514",
    "addr:housenumber":"1800",
    "addr:postcode":"27514",
    "addr:street":"E Franklin St",
    "iso:country":"US",
    "sg:address":"1800 E Franklin St",
    "sg:city":"Chapel Hill",
    "sg:classifiers":[
        {
            "category":"Food & Beverages",
            "subcategory":"Specialty",
            "type":"Retail Goods"
        }
    ],
    "sg:phone":"+1 919 442 1223",
    "sg:postcode":"27514",
    "sg:province":"NC",
    "sg:tags":[
        "health",
        "diet"
    ],
    "wof:name":"Earth Fare",
    "wof:placetype":"venue"
},
  "geometry": {"coordinates":[-79.02353100000001,35.938357],"type":"Point"}
}