{
  "type": "Feature",
  "properties": {
    "iso:country":"US",
    "sg:address":"31 Nelson St",
    "sg:city":"Clyde",
    "sg:classifiers":[
        {
            "category":"Health Services",
            "subcategory":"Clinic",
            "type":"Services"
        }
    ],
    "sg:phone":"+1 828 627 3499",
    "sg:postcode":"28721",
    "sg:province":"NC",
    "sg:tags":[
        "home",
        "care"
    ],
    "wof:name":"Grandview Assisted Living Serv",
    "wof:placetype":"venue"
},
  "geometry": {"coordinates":[-82.91768999999999,35.530899],"type":"Point"}
}