{
  "type": "Feature",
  "properties": {
    "addr:full":"450 Mc Koy St Clinton NC 28328",
    "addr:housenumber":"450",
    "addr:postcode":"28328",
    "addr:street":"Mc Koy St",
    "iso:country":"US",
    "sg:address":"450 Mc Koy St",
    "sg:city":"Clinton",
    "sg:classifiers":[
        {
            "category":"Organizations",
            "subcategory":"Professional Association",
            "type":"Services"
        }
    ],
    "sg:phone":"+1 910 592 2488",
    "sg:postcode":"28328",
    "sg:province":"NC",
    "wof:name":"H S Sampson Alumni Assn",
    "wof:placetype":"venue"
},
  "geometry": {"coordinates":[-78.329294,35.001944],"type":"Point"}
}