{
  "type": "Feature",
  "properties": {
    "iso:country":"US",
    "sg:address":"16405 Northcross Dr",
    "sg:city":"Huntersville",
    "sg:classifiers":[
        {
            "category":"Health Services",
            "subcategory":"Doctor",
            "type":"Services"
        }
    ],
    "sg:phone":"+1 704 892 6160",
    "sg:postcode":"28078",
    "sg:province":"NC",
    "sg:tags":[
        "medical"
    ],
    "wof:name":"Totalcare",
    "wof:placetype":"venue"
},
  "geometry": {"coordinates":[-80.87002200000001,35.435173],"type":"Point"}
}