{
  "type": "Feature",
  "properties": {
    "addr:full":"8318 Pineville Matthews Rd Charlotte NC 28226",
    "addr:housenumber":"8318",
    "addr:postcode":"28226",
    "addr:street":"Matthews Rd",
    "iso:country":"US",
    "sg:address":"8318 Pineville Matthews Rd",
    "sg:city":"Charlotte",
    "sg:classifiers":[
        {
            "category":"Restaurant",
            "type":"Food & Drink"
        }
    ],
    "sg:menulink":"http://www.allmenus.com/nc/pineville/137202-subway/menu/",
    "sg:phone":"+1 704 541 5309",
    "sg:postcode":"28226",
    "sg:province":"NC",
    "sg:tags":[
        "american",
        "sandwich"
    ],
    "wof:name":"Subway",
    "wof:placetype":"venue"
},
  "geometry": {"coordinates":[-80.859697,35.087589],"type":"Point"}
}