{
  "type": "Feature",
  "properties": {
    "iso:country":"US",
    "sg:address":"29 N Market St",
    "sg:city":"Asheville",
    "sg:classifiers":[
        {
            "category":"Professional",
            "subcategory":"Business Services",
            "type":"Services"
        }
    ],
    "sg:phone":"+1   ",
    "sg:postcode":"28801",
    "sg:province":"NC",
    "wof:name":"Kc Bonding",
    "wof:placetype":"venue"
},
  "geometry": {"coordinates":[-82.551143,35.596455],"type":"Point"}
}