{
  "type": "Feature",
  "properties": {
    "addr:full":"3249 Blue Ridge Rd Raleigh NC 27612",
    "addr:housenumber":"3249",
    "addr:postcode":"27612",
    "addr:street":"Blue Ridge Rd",
    "iso:country":"US",
    "sg:address":"3249 Blue Ridge Rd",
    "sg:city":"Raleigh",
    "sg:classifiers":[
        {
            "category":"Organizations",
            "subcategory":"Professional Association",
            "type":"Services"
        }
    ],
    "sg:phone":"+1   ",
    "sg:postcode":"27612",
    "sg:province":"NC",
    "sg:tags":[
        "community"
    ],
    "wof:name":"Blue Ridge Community Services",
    "wof:placetype":"venue"
},
  "geometry": {"coordinates":[-78.69837099999999,35.824605],"type":"Point"}
}