{
  "type": "Feature",
  "properties": {
    "iso:country":"US",
    "sg:address":"3865 Reynolda Rd",
    "sg:city":"Winston Salem",
    "sg:classifiers":[
        {
            "category":"Home & Garden",
            "subcategory":"Carpets & Floor Coverings",
            "type":"Retail Goods"
        }
    ],
    "sg:phone":"+1 336 922 2740",
    "sg:postcode":"27106",
    "sg:province":"NC",
    "sg:tags":[
        "dealer",
        "rug"
    ],
    "wof:name":"Faulkner Flooring Inc",
    "wof:placetype":"venue"
},
  "geometry": {"coordinates":[-80.32905100000001,36.164093],"type":"Point"}
}