{
  "type": "Feature",
  "properties": {
    "iso:country":"US",
    "sg:address":"211 E Main St",
    "sg:city":"Albemarle",
    "sg:classifiers":[
        {
            "category":"Wholesale",
            "subcategory":"Stationery",
            "type":"Manufacturing & Wholesale Goods"
        }
    ],
    "sg:phone":"+1 704 983 3488",
    "sg:postcode":"28001",
    "sg:province":"NC",
    "sg:tags":[
        "business",
        "form",
        "system"
    ],
    "wof:name":"First Graphics Inc",
    "wof:placetype":"venue"
},
  "geometry": {"coordinates":[-80.19623,35.350355],"type":"Point"}
}