{
  "type": "Feature",
  "properties": {
    "iso:country":"US",
    "sg:address":"445 S 1st St",
    "sg:city":"Albemarle",
    "sg:classifiers":[
        {
            "category":"Retail",
            "subcategory":"Laundry & Dry Cleaning",
            "type":"Services"
        }
    ],
    "sg:phone":"+1 704 982 6627",
    "sg:postcode":"28001",
    "sg:province":"NC",
    "sg:tags":[
        "cleaners",
        "plant"
    ],
    "wof:name":"Almo Cleaners Inc",
    "wof:placetype":"venue"
},
  "geometry": {"coordinates":[-80.19925000000001,35.345782],"type":"Point"}
}