{
  "type": "Feature",
  "properties": {
    "iso:country":"US",
    "sg:address":"123 S 3rd St",
    "sg:city":"Smithfield",
    "sg:classifiers":[
        {
            "category":"Real Estate",
            "subcategory":"Real Estate Services",
            "type":"Services"
        }
    ],
    "sg:phone":"+1 919 989 6339",
    "sg:postcode":"27577",
    "sg:province":"NC",
    "sg:tags":[
        "company",
        "title"
    ],
    "wof:name":"Investors Title Insurance Co",
    "wof:placetype":"venue"
},
  "geometry": {"coordinates":[-78.34610600000001,35.510903],"type":"Point"}
}