{
  "type": "Feature",
  "properties": {
    "iso:country":"US",
    "sg:address":"928 Carolina St",
    "sg:city":"Roanoke Rapids",
    "sg:classifiers":[
        {
            "category":"Building & Trades",
            "subcategory":"Landscaping Services",
            "type":"Services"
        }
    ],
    "sg:phone":"+1 252 537 3843",
    "sg:postcode":"27870",
    "sg:province":"NC",
    "sg:tags":[
        "ornamental",
        "scrub",
        "tree",
        "removal"
    ],
    "wof:name":"Stumper",
    "wof:placetype":"venue"
},
  "geometry": {"coordinates":[-77.64849100000001,36.454614],"type":"Point"}
}