{
  "type": "Feature",
  "properties": {
    "iso:country":"US",
    "sg:address":"840 Kemp Rd",
    "sg:city":"Mooresville",
    "sg:classifiers":[
        {
            "category":"Professional",
            "subcategory":"Art Services",
            "type":"Services"
        }
    ],
    "sg:phone":"+1 704 660 1495",
    "sg:postcode":"28117",
    "sg:province":"NC",
    "sg:tags":[
        "graphic",
        "designer"
    ],
    "wof:name":"Graphic Design Etc",
    "wof:placetype":"venue"
},
  "geometry": {"coordinates":[-80.94789900000001,35.5608],"type":"Point"}
}