{
  "type": "Feature",
  "properties": {
    "iso:country":"US",
    "sg:address":"1330 N Wesleyan Blvd",
    "sg:city":"Rocky Mount",
    "sg:classifiers":[
        {
            "category":"Restaurant",
            "type":"Food & Drink"
        }
    ],
    "sg:phone":"+1 252 977 0877",
    "sg:postcode":"27804",
    "sg:province":"NC",
    "wof:name":"Peking Palace",
    "wof:placetype":"venue"
},
  "geometry": {"coordinates":[-77.798359,35.975458],"type":"Point"}
}