{
  "type": "Feature",
  "properties": {
    "iso:country":"US",
    "sg:address":"4512 Groometown Rd",
    "sg:city":"Greensboro",
    "sg:classifiers":[
        {
            "category":"Building & Trades",
            "subcategory":"Electrical",
            "type":"Services"
        }
    ],
    "sg:phone":"+1 336 292 9467",
    "sg:postcode":"27407",
    "sg:province":"NC",
    "sg:tags":[
        "electrical",
        "contractor"
    ],
    "wof:name":"All Seasons Electric Co",
    "wof:placetype":"venue"
},
  "geometry": {"coordinates":[-79.867333,35.991266],"type":"Point"}
}