{
  "type": "Feature",
  "properties": {
    "iso:country":"US",
    "sg:address":"10700 Sikes Pl",
    "sg:city":"Charlotte",
    "sg:classifiers":[
        {
            "category":"Insurance",
            "subcategory":"Hazard Insurance",
            "type":"Services"
        }
    ],
    "sg:phone":"+1 704 846 0258",
    "sg:postcode":"28277",
    "sg:province":"NC",
    "sg:tags":[
        "fidelity",
        "surety",
        "bond"
    ],
    "wof:name":"First Sealord Surety Inc",
    "wof:placetype":"venue"
},
  "geometry": {"coordinates":[-80.76847600000001,35.062022],"type":"Point"}
}