{
  "type": "Feature",
  "properties": {
    "addr:full":"5607 Clayton Ct Granite Falls NC 28630",
    "addr:housenumber":"5607",
    "addr:postcode":"28630",
    "addr:street":"Clayton Ct",
    "iso:country":"US",
    "sg:address":"5607 Clayton Ct",
    "sg:city":"Granite Falls",
    "sg:classifiers":[
        {
            "category":"Manufacturing",
            "subcategory":"Toys & Sporting Goods",
            "type":"Manufacturing & Wholesale Goods"
        }
    ],
    "sg:phone":"+1 828 313 0756",
    "sg:postcode":"28630",
    "sg:province":"NC",
    "sg:tags":[
        "mfg"
    ],
    "wof:name":"Day Florists",
    "wof:placetype":"venue"
},
  "geometry": {"coordinates":[-81.365087,35.794425],"type":"Point"}
}