{
  "type": "Feature",
  "properties": {
    "addr:full":"1037 Old Forest Ct Asheboro NC 27205",
    "addr:housenumber":"1037",
    "addr:postcode":"27205",
    "addr:street":"Old Forest Ct",
    "iso:country":"US",
    "sg:address":"1037 Old Forest Ct",
    "sg:city":"Asheboro",
    "sg:classifiers":[
        {
            "category":"Building & Trades",
            "subcategory":"Landscaping Services",
            "type":"Services"
        }
    ],
    "sg:phone":"+1 336 625 1480",
    "sg:postcode":"27205",
    "sg:province":"NC",
    "sg:tags":[
        "lawn",
        "maintenance",
        "grounds"
    ],
    "wof:name":"Mc Kee's Diamond Cut Lawn Svc",
    "wof:placetype":"venue"
},
  "geometry": {"coordinates":[-79.883235,35.678152],"type":"Point"}
}