{
  "type": "Feature",
  "properties": {
    "iso:country":"US",
    "sg:address":"248 Murdock C Rd",
    "sg:city":"Cameron",
    "sg:classifiers":[
        {
            "category":"Building & Trades",
            "subcategory":"Construction",
            "type":"Services"
        }
    ],
    "sg:phone":"+1 910 245 2100",
    "sg:postcode":"28326",
    "sg:province":"NC",
    "sg:tags":[
        "residential"
    ],
    "wof:name":"Softwalk Construction Co Inc",
    "wof:placetype":"venue"
},
  "geometry": {"coordinates":[-79.205996,35.250114],"type":"Point"}
}