{
  "type": "Feature",
  "properties": {
    "iso:country":"US",
    "sg:address":"2007 Hobbton Hwy",
    "sg:city":"Clinton",
    "sg:classifiers":[
        {
            "category":"Professional",
            "subcategory":"Business Services",
            "type":"Services"
        }
    ],
    "sg:phone":"+1   ",
    "sg:postcode":"28328",
    "sg:province":"NC",
    "wof:name":"Jds Advertisting",
    "wof:placetype":"venue"
},
  "geometry": {"coordinates":[-78.32731099999999,35.030222],"type":"Point"}
}