{
  "type": "Feature",
  "properties": {
    "addr:full":"75 Troxler Cir NW Concord NC 28027",
    "addr:housenumber":"75",
    "addr:postcode":"28027",
    "addr:street":"Troxler Cir Nw",
    "iso:country":"US",
    "sg:address":"75 Troxler Cir NW",
    "sg:city":"Concord",
    "sg:classifiers":[
        {
            "category":"Retail",
            "subcategory":"Auto Repair",
            "type":"Services"
        }
    ],
    "sg:phone":"+1 704 788 1230",
    "sg:postcode":"28027",
    "sg:province":"NC",
    "sg:tags":[
        "repairing",
        "automobile"
    ],
    "wof:name":"Frankie's Alignment Svc",
    "wof:placetype":"venue"
},
  "geometry": {"coordinates":[-80.619398,35.418172],"type":"Point"}
}