{
  "type": "Feature",
  "properties": {
    "addr:full":"19000 Jetton Rd Cornelius NC 28031",
    "addr:housenumber":"19000",
    "addr:postcode":"28031",
    "addr:street":"Jetton Rd",
    "iso:country":"US",
    "sg:address":"19000 Jetton Rd",
    "sg:city":"Cornelius",
    "sg:classifiers":[
        {
            "category":"Professional",
            "type":"Services"
        }
    ],
    "sg:phone":"+1 704 896 9808",
    "sg:postcode":"28031",
    "sg:province":"NC",
    "sg:tags":[
        "establishment"
    ],
    "wof:name":"Jetton Park",
    "wof:placetype":"venue"
},
  "geometry": {"coordinates":[-80.897075,35.476363],"type":"Point"}
}