{
  "type": "Feature",
  "properties": {
    "addr:full":"1200 E Caswell St Wadesboro NC 28170",
    "addr:housenumber":"1200",
    "addr:postcode":"28170",
    "addr:street":"E Caswell St",
    "iso:country":"US",
    "sg:address":"1200 E Caswell St",
    "sg:city":"Wadesboro",
    "sg:classifiers":[
        {
            "category":"Restaurant",
            "type":"Food & Drink"
        }
    ],
    "sg:menulink":"http://www.allmenus.com/nc/wadesboro/153329-bojangles/menu/",
    "sg:phone":"+1 704 694 9007",
    "sg:postcode":"28170",
    "sg:province":"NC",
    "sg:tags":[
        "chicken",
        "sandwich",
        "american"
    ],
    "wof:name":"Bojangle's",
    "wof:placetype":"venue"
},
  "geometry": {"coordinates":[-80.0565,34.963465],"type":"Point"}
}