{
  "type": "Feature",
  "properties": {
    "iso:country":"US",
    "sg:address":"5311 Dodsons Cross Rd",
    "sg:city":"Hillsborough",
    "sg:classifiers":[
        {
            "category":"Professional",
            "type":"Services"
        }
    ],
    "sg:phone":"+1   ",
    "sg:postcode":"27278",
    "sg:province":"NC",
    "wof:name":"Dolly A Hunter",
    "wof:placetype":"venue"
},
  "geometry": {"coordinates":[-79.163082,36.00191],"type":"Point"}
}