{
  "type": "Feature",
  "properties": {
    "iso:country":"US",
    "sg:address":"825 Brett Ct",
    "sg:city":"Kernersville",
    "sg:classifiers":[
        {
            "category":"Insurance",
            "subcategory":"Insurance Agent",
            "type":"Services"
        }
    ],
    "sg:phone":"+1 336 993 1515",
    "sg:postcode":"27284",
    "sg:province":"NC",
    "sg:tags":[
        "adjuster"
    ],
    "wof:name":"Carolina Independent Adjusters",
    "wof:placetype":"venue"
},
  "geometry": {"coordinates":[-80.09378,36.121378],"type":"Point"}
}