{
  "type": "Feature",
  "properties": {
    "iso:country":"US",
    "sg:address":"9201 S Tryon St",
    "sg:city":"Charlotte",
    "sg:classifiers":[
        {
            "category":"Health Services",
            "subcategory":"Doctor",
            "type":"Services"
        }
    ],
    "sg:phone":"+1 704 588 1627",
    "sg:postcode":"28273",
    "sg:province":"NC",
    "sg:tags":[
        "dentist"
    ],
    "wof:name":"Joseph O Newell DDS",
    "wof:placetype":"venue"
},
  "geometry": {"coordinates":[-80.939953,35.13331],"type":"Point"}
}