{
  "type": "Feature",
  "properties": {
    "iso:country":"US",
    "sg:address":"1250 Beagle Club Rd",
    "sg:city":"Salisbury",
    "sg:classifiers":[
        {
            "category":"Building & Trades",
            "subcategory":"Landscaping Services",
            "type":"Services"
        }
    ],
    "sg:phone":"+1 704 636 4522",
    "sg:postcode":"28146",
    "sg:province":"NC",
    "sg:tags":[
        "landscape"
    ],
    "wof:name":"Stephen G Brown Ldscp Architec",
    "wof:placetype":"venue"
},
  "geometry": {"coordinates":[-80.374982,35.620659],"type":"Point"}
}