{
  "type": "Feature",
  "properties": {
    "iso:country":"US",
    "sg:address":"179 Casstevens Rd",
    "sg:city":"Mount Airy",
    "sg:classifiers":[
        {
            "category":"Freight",
            "type":"Transportation"
        }
    ],
    "sg:phone":"+1 336 352 3082",
    "sg:postcode":"27030",
    "sg:province":"NC",
    "sg:tags":[
        "operator",
        "local",
        "trucking"
    ],
    "wof:name":"Casstevens Trucking",
    "wof:placetype":"venue"
},
  "geometry": {"coordinates":[-80.772841,36.455345],"type":"Point"}
}