{
  "type": "Feature",
  "properties": {
    "addr:full":"684 Pleasant Hill Rd Rutherfordton NC 28139",
    "addr:housenumber":"684",
    "addr:postcode":"28139",
    "addr:street":"Pleasant Hill Rd",
    "iso:country":"US",
    "sg:address":"684 Pleasant Hill Rd",
    "sg:city":"Rutherfordton",
    "sg:classifiers":[
        {
            "category":"Wholesale",
            "subcategory":"Groceries",
            "type":"Manufacturing & Wholesale Goods"
        }
    ],
    "sg:phone":"+1 828 286 4164",
    "sg:postcode":"28139",
    "sg:province":"NC",
    "wof:name":"Total Living Connection",
    "wof:placetype":"venue"
},
  "geometry": {"coordinates":[-81.99861,35.317001],"type":"Point"}
}