{
  "type": "Feature",
  "properties": {
    "addr:full":"195 Hodges Rd Chocowinity NC 27817",
    "addr:housenumber":"195",
    "addr:postcode":"27817",
    "addr:street":"Hodges Rd",
    "iso:country":"US",
    "sg:address":"195 Hodges Rd",
    "sg:city":"Chocowinity",
    "sg:classifiers":[
        {
            "category":"Wholesale",
            "subcategory":"Construction Materials",
            "type":"Manufacturing & Wholesale Goods"
        }
    ],
    "sg:phone":"+1 252 946 8385",
    "sg:postcode":"27817",
    "sg:province":"NC",
    "sg:tags":[
        "fence"
    ],
    "wof:name":"Clark & Son Fence Co",
    "wof:placetype":"venue"
},
  "geometry": {"coordinates":[-77.163725,35.520338],"type":"Point"}
}