{
  "type": "Feature",
  "properties": {
    "addr:full":"3808 Guess Rd Durham NC 27705",
    "addr:housenumber":"3808",
    "addr:postcode":"27705",
    "addr:street":"Guess Rd",
    "iso:country":"US",
    "sg:address":"3808 Guess Rd",
    "sg:city":"Durham",
    "sg:classifiers":[
        {
            "category":"Restaurant",
            "type":"Food & Drink"
        }
    ],
    "sg:phone":"+1 919 620 7771",
    "sg:postcode":"27705",
    "sg:province":"NC",
    "sg:tags":[
        "eating"
    ],
    "wof:name":"China House Restaurant",
    "wof:placetype":"venue"
},
  "geometry": {"coordinates":[-78.928917,36.05928],"type":"Point"}
}