{
  "type": "Feature",
  "properties": {
    "addr:full":"104 Main St E Valdese NC 28690",
    "addr:housenumber":"104",
    "addr:postcode":"28690",
    "addr:street":"Main St E",
    "iso:country":"US",
    "sg:address":"104 Main St E",
    "sg:city":"Valdese",
    "sg:classifiers":[
        {
            "category":"Personal",
            "type":"Services"
        }
    ],
    "sg:phone":"+1 828 879 9711",
    "sg:postcode":"28690",
    "sg:province":"NC",
    "sg:tags":[
        "wear",
        "formal"
    ],
    "wof:name":"Your Floral Bouquet Florist",
    "wof:placetype":"venue"
},
  "geometry": {"coordinates":[-81.56256999999999,35.743452],"type":"Point"}
}