{
  "type": "Feature",
  "properties": {
    "iso:country":"US",
    "sg:address":"226 Linden Ave",
    "sg:city":"Sanford",
    "sg:classifiers":[
        {
            "category":"Education",
            "subcategory":"School",
            "type":"Public Place"
        }
    ],
    "sg:phone":"+1 919 776 6831",
    "sg:postcode":"27330",
    "sg:province":"NC",
    "wof:name":"Johnstn-Lee Head Start Program",
    "wof:placetype":"venue"
},
  "geometry": {"coordinates":[-79.173891,35.487112],"type":"Point"}
}