{
  "type": "Feature",
  "properties": {
    "iso:country":"US",
    "sg:address":"4757 Main St",
    "sg:city":"South Brunswick",
    "sg:classifiers":[
        {
            "category":"Retail",
            "subcategory":"Auto Repair",
            "type":"Services"
        }
    ],
    "sg:phone":"+1 910 754 3820",
    "sg:postcode":"28470",
    "sg:province":"NC",
    "sg:tags":[
        "body",
        "automobile",
        "painting"
    ],
    "wof:name":"Southern Coast Collision",
    "wof:placetype":"venue"
},
  "geometry": {"coordinates":[-78.38517,33.973326],"type":"Point"}
}