{
  "type": "Feature",
  "properties": {
    "iso:country":"US",
    "sg:address":"2616 Knob Mountain Dr",
    "sg:city":"Connellys Springs",
    "sg:classifiers":[
        {
            "category":"Wholesale",
            "subcategory":"Groceries",
            "type":"Manufacturing & Wholesale Goods"
        }
    ],
    "sg:phone":"+1 828 879 1953",
    "sg:postcode":"28612",
    "sg:province":"NC",
    "sg:tags":[
        "general"
    ],
    "wof:name":"Federated Group Inc",
    "wof:placetype":"venue"
},
  "geometry": {"coordinates":[-81.484115,35.736469],"type":"Point"}
}