{
  "type": "Feature",
  "properties": {
    "addr:full":"830 Hanes Mall Blvd Winston Salem NC 27103",
    "addr:housenumber":"830",
    "addr:postcode":"27103",
    "addr:street":"Hanes Mall Blvd",
    "iso:country":"US",
    "sg:address":"830 Hanes Mall Blvd",
    "sg:city":"Winston Salem",
    "sg:classifiers":[
        {
            "category":"Shopping",
            "subcategory":"Clothing, Apparel, & Fashions",
            "type":"Retail Goods"
        }
    ],
    "sg:phone":"+1 336 760 3799",
    "sg:postcode":"27103",
    "sg:province":"NC",
    "sg:website":"www.gap.com",
    "wof:name":"Gap",
    "wof:placetype":"venue"
},
  "geometry": {"coordinates":[-80.30846699999999,36.062657],"type":"Point"}
}