{
  "type": "Feature",
  "properties": {
    "iso:country":"US",
    "sg:address":"130 Boone Farm Rd",
    "sg:city":"Mocksville",
    "sg:classifiers":[
        {
            "category":"Retail",
            "subcategory":"Auto Repair",
            "type":"Services"
        }
    ],
    "sg:phone":"+1 336 492 2375",
    "sg:postcode":"27028",
    "sg:province":"NC",
    "sg:tags":[
        "automobile",
        "inspection"
    ],
    "wof:name":"Bob's Auto Svc",
    "wof:placetype":"venue"
},
  "geometry": {"coordinates":[-80.615769,35.907146],"type":"Point"}
}