{
  "type": "Feature",
  "properties": {
    "iso:country":"US",
    "sg:address":"1072 Perth Rd",
    "sg:city":"Troutman",
    "sg:classifiers":[
        {
            "category":"Wholesale",
            "subcategory":"Machinery & Supplies",
            "type":"Manufacturing & Wholesale Goods"
        }
    ],
    "sg:phone":"+1 704 528 0431",
    "sg:postcode":"28166",
    "sg:province":"NC",
    "sg:tags":[
        "equipment"
    ],
    "wof:name":"Mitchell Distributing Company",
    "wof:placetype":"venue"
},
  "geometry": {"coordinates":[-80.89644699999999,35.670981],"type":"Point"}
}