{
  "type": "Feature",
  "properties": {
    "iso:country":"US",
    "sg:address":"207 Coventry Ln",
    "sg:city":"Cary",
    "sg:classifiers":[
        {
            "category":"Home & Garden",
            "subcategory":"Garden Supply",
            "type":"Retail Goods"
        }
    ],
    "sg:phone":"+1 919 467 4245",
    "sg:postcode":"27511",
    "sg:province":"NC",
    "wof:name":"Bens Creek Nursery",
    "wof:placetype":"venue"
},
  "geometry": {"coordinates":[-78.78218200000001,35.752877],"type":"Point"}
}