{
  "type": "Feature",
  "properties": {
    "iso:country":"US",
    "sg:address":"388 Merrimon Ave",
    "sg:city":"Asheville",
    "sg:classifiers":[
        {
            "category":"Health Services",
            "subcategory":"Chiropractor",
            "type":"Services"
        }
    ],
    "sg:phone":"+1 828 236 2200",
    "sg:postcode":"28801",
    "sg:province":"NC",
    "wof:name":"Doster Chiropractic PC",
    "wof:placetype":"venue"
},
  "geometry": {"coordinates":[-82.554976,35.610852],"type":"Point"}
}