{
  "type": "Feature",
  "properties": {
    "iso:country":"US",
    "sg:address":"4848 State Hwy 54",
    "sg:city":"Graham",
    "sg:classifiers":[
        {
            "category":"Retail",
            "subcategory":"Auto Repair",
            "type":"Services"
        }
    ],
    "sg:phone":"+1 336 376 1611",
    "sg:postcode":"27253",
    "sg:province":"NC",
    "sg:tags":[
        "repairing",
        "automobile"
    ],
    "wof:name":"Bud's Automotive",
    "wof:placetype":"venue"
},
  "geometry": {"coordinates":[-79.29276900000001,35.992494],"type":"Point"}
}