{
  "type": "Feature",
  "properties": {
    "addr:full":"2324 Shore Rd Yadkinville NC 27055",
    "addr:housenumber":"2324",
    "addr:postcode":"27055",
    "addr:street":"Shore Rd",
    "iso:country":"US",
    "sg:address":"2324 Shore Rd",
    "sg:city":"Yadkinville",
    "sg:classifiers":[
        {
            "category":"Professional",
            "type":"Services"
        }
    ],
    "sg:phone":"+1 336 679 8466",
    "sg:postcode":"27055",
    "sg:province":"NC",
    "wof:name":"Matthews & Williams Cemet",
    "wof:placetype":"venue"
},
  "geometry": {"coordinates":[-80.672664,36.173741],"type":"Point"}
}