{
  "type": "Feature",
  "properties": {
    "addr:full":"110 Pineridge Dr Greenville NC 27858",
    "addr:housenumber":"110",
    "addr:postcode":"27858",
    "addr:street":"Pineridge Dr",
    "iso:country":"US",
    "sg:address":"110 Pineridge Dr",
    "sg:city":"Greenville",
    "sg:classifiers":[
        {
            "category":"Professional",
            "type":"Services"
        }
    ],
    "sg:phone":"+1   ",
    "sg:postcode":"27858",
    "sg:province":"NC",
    "wof:name":"Betsy Reid Arts",
    "wof:placetype":"venue"
},
  "geometry": {"coordinates":[-77.30797200000001,35.574191],"type":"Point"}
}