{
  "type": "Feature",
  "properties": {
    "iso:country":"US",
    "sg:address":"722 Durham Rd",
    "sg:city":"Roxboro",
    "sg:classifiers":[
        {
            "category":"Personal",
            "subcategory":"Beauty Salon",
            "type":"Services"
        }
    ],
    "sg:phone":"+1 336 598 5644",
    "sg:postcode":"27573",
    "sg:province":"NC",
    "wof:name":"Special K's Hairstyling",
    "wof:placetype":"venue"
},
  "geometry": {"coordinates":[-78.986715,36.383632],"type":"Point"}
}