{
  "type": "Feature",
  "properties": {
    "iso:country":"US",
    "sg:address":"107 Indian Trail Rd",
    "sg:city":"Edenton",
    "sg:classifiers":[
        {
            "category":"Building & Trades",
            "subcategory":"Electrical",
            "type":"Services"
        }
    ],
    "sg:phone":"+1 252 482 0290",
    "sg:postcode":"27932",
    "sg:province":"NC",
    "sg:tags":[
        "electrical",
        "contractor"
    ],
    "wof:name":"Lee Electrical Construction",
    "wof:placetype":"venue"
},
  "geometry": {"coordinates":[-76.488552,36.03957],"type":"Point"}
}