{
  "type": "Feature",
  "properties": {
    "iso:country":"US",
    "sg:address":"101 Olive Ln",
    "sg:city":"Mt Olive",
    "sg:classifiers":[
        {
            "category":"Real Estate",
            "subcategory":"Real Estate Agent",
            "type":"Services"
        }
    ],
    "sg:phone":"+1 919 778 6889",
    "sg:postcode":"28365",
    "sg:province":"NC",
    "wof:name":"Whitfield Construction Realty",
    "wof:placetype":"venue"
},
  "geometry": {"coordinates":[-78.04601599999999,35.206298],"type":"Point"}
}