{
  "type": "Feature",
  "properties": {
    "iso:country":"US",
    "sg:address":"5058 US Hwy 70",
    "sg:city":"Morehead City",
    "sg:classifiers":[
        {
            "category":"Shopping",
            "type":"Retail Goods"
        }
    ],
    "sg:phone":"+1 252 247 7782",
    "sg:postcode":"28557",
    "sg:province":"NC",
    "sg:tags":[
        "hearing",
        "equipment",
        "supply",
        "impaired"
    ],
    "wof:name":"Coastal Hearing Care Ctr",
    "wof:placetype":"venue"
},
  "geometry": {"coordinates":[-76.799792,34.736728],"type":"Point"}
}