{
  "type": "Feature",
  "properties": {
    "iso:country":"US",
    "sg:address":"326 E Main St",
    "sg:city":"Lincolnton",
    "sg:classifiers":[
        {
            "category":"Organizations",
            "subcategory":"Non-profit Organization",
            "type":"Services"
        }
    ],
    "sg:phone":"+1 704 735 3507",
    "sg:postcode":"28092",
    "sg:province":"NC",
    "sg:tags":[
        "information",
        "alcoholism",
        "treatment"
    ],
    "wof:name":"Acts In Recovery",
    "wof:placetype":"venue"
},
  "geometry": {"coordinates":[-81.25242,35.472744],"type":"Point"}
}