{
  "type": "Feature",
  "properties": {
    "iso:country":"US",
    "sg:address":"53 N Market St",
    "sg:city":"Asheville",
    "sg:classifiers":[
        {
            "category":"Health Services",
            "subcategory":"Doctor",
            "type":"Services"
        }
    ],
    "sg:phone":"+1   ",
    "sg:postcode":"28801",
    "sg:province":"NC",
    "wof:name":"Bonner Leslie Clement N D Lmt",
    "wof:placetype":"venue"
},
  "geometry": {"coordinates":[-82.55188699999999,35.598344],"type":"Point"}
}