{
  "type": "Feature",
  "properties": {
    "addr:full":"1370 N Church St Burlington NC 27217",
    "addr:housenumber":"1370",
    "addr:postcode":"27217",
    "addr:street":"N Church St",
    "iso:country":"US",
    "sg:address":"1370 N Church St",
    "sg:city":"Burlington",
    "sg:classifiers":[
        {
            "category":"Bars & Pubs",
            "type":"Food & Drink"
        }
    ],
    "sg:phone":"+1 336 228 9336",
    "sg:postcode":"27217",
    "sg:province":"NC",
    "sg:tags":[
        "lounge",
        "drinking",
        "cocktail"
    ],
    "wof:name":"Idlehour Lounge Inc",
    "wof:placetype":"venue"
},
  "geometry": {"coordinates":[-79.41482499999999,36.097262],"type":"Point"}
}