{
  "type": "Feature",
  "properties": {
    "iso:country":"US",
    "sg:address":"6830 Willmatt Dr",
    "sg:city":"Browns Summit",
    "sg:classifiers":[
        {
            "category":"Building & Trades",
            "subcategory":"Construction",
            "type":"Services"
        }
    ],
    "sg:phone":"+1 336 288 1596",
    "sg:postcode":"27214",
    "sg:province":"NC",
    "sg:tags":[
        "resurfacing",
        "floor",
        "laying",
        "refinishing",
        "contractor"
    ],
    "wof:name":"Conklin Flooring Inc",
    "wof:placetype":"venue"
},
  "geometry": {"coordinates":[-79.775457,36.185602],"type":"Point"}
}