{
  "type": "Feature",
  "properties": {
    "addr:full":"635 4th St E Winston Salem NC 27101",
    "addr:housenumber":"635",
    "addr:postcode":"27101",
    "addr:street":"4Th St E",
    "iso:country":"US",
    "sg:address":"635 4th St E",
    "sg:city":"Winston Salem",
    "sg:classifiers":[
        {
            "category":"Shopping",
            "subcategory":"Computers & Home Electronics",
            "type":"Retail Goods"
        }
    ],
    "sg:phone":"+1 336 723 1450",
    "sg:postcode":"27101",
    "sg:province":"NC",
    "sg:tags":[
        "software"
    ],
    "wof:name":"Point Dx Inc",
    "wof:placetype":"venue"
},
  "geometry": {"coordinates":[-80.236952,36.099375],"type":"Point"}
}