{
  "type": "Feature",
  "properties": {
    "addr:full":"5309 Germaine Ter Charlotte NC 28226",
    "addr:housenumber":"5309",
    "addr:postcode":"28226",
    "addr:street":"Germaine Ter",
    "iso:country":"US",
    "sg:address":"5309 Germaine Ter",
    "sg:city":"Charlotte",
    "sg:classifiers":[
        {
            "category":"Banks & Credit Unions",
            "subcategory":"Financial Services",
            "type":"Services"
        }
    ],
    "sg:phone":"+1 704 362 3600",
    "sg:postcode":"28226",
    "sg:province":"NC",
    "sg:tags":[
        "investor"
    ],
    "wof:name":"Perennial Investments",
    "wof:placetype":"venue"
},
  "geometry": {"coordinates":[-80.81469,35.134794],"type":"Point"}
}