{
  "type": "Feature",
  "properties": {
    "addr:full":"198 Creekside Ln Boone NC 28607",
    "addr:housenumber":"198",
    "addr:postcode":"28607",
    "addr:street":"Creekside Ln",
    "iso:country":"US",
    "sg:address":"198 Creekside Ln",
    "sg:city":"Boone",
    "sg:classifiers":[
        {
            "category":"Travel",
            "subcategory":"Travel Agent",
            "type":"Entertainment"
        }
    ],
    "sg:phone":"+1 828 264 8747",
    "sg:postcode":"28607",
    "sg:province":"NC",
    "sg:tags":[
        "agency",
        "bureau"
    ],
    "wof:name":"Appalachian Travel Inc",
    "wof:placetype":"venue"
},
  "geometry": {"coordinates":[-81.639122,36.193559],"type":"Point"}
}