{
  "type": "Feature",
  "properties": {
    "addr:full":"6820 Dodsons Cross Rd Hillsborough NC 27278",
    "addr:housenumber":"6820",
    "addr:postcode":"27278",
    "addr:street":"Dodsons Cross Rd",
    "iso:country":"US",
    "sg:address":"6820 Dodsons Cross Rd",
    "sg:city":"Hillsborough",
    "sg:classifiers":[
        {
            "category":"Real Estate",
            "subcategory":"Real Estate Agent",
            "type":"Services"
        }
    ],
    "sg:phone":"+1 919 967 3833",
    "sg:postcode":"27278",
    "sg:province":"NC",
    "sg:tags":[
        "management"
    ],
    "wof:name":"Moore Management Inc",
    "wof:placetype":"venue"
},
  "geometry": {"coordinates":[-79.15944500000001,35.977668],"type":"Point"}
}