{
  "type": "Feature",
  "properties": {
    "iso:country":"US",
    "sg:address":"1550 US Hwy 29 Bus",
    "sg:city":"Reidsville",
    "sg:classifiers":[
        {
            "category":"Real Estate",
            "subcategory":"Real Estate Operator",
            "type":"Services"
        }
    ],
    "sg:phone":"+1 336 342 1053",
    "sg:postcode":"27320",
    "sg:province":"NC",
    "sg:tags":[
        "building",
        "apartment"
    ],
    "wof:name":"Bullock Mobile Homes",
    "wof:placetype":"venue"
},
  "geometry": {"coordinates":[-79.662963,36.297965],"type":"Point"}
}