{
  "type": "Feature",
  "properties": {
    "addr:full":"4808 Chesapeake Dr Charlotte NC 28216",
    "addr:housenumber":"4808",
    "addr:postcode":"28216",
    "addr:street":"Chesapeake Dr",
    "iso:country":"US",
    "sg:address":"4808 Chesapeake Dr",
    "sg:city":"Charlotte",
    "sg:classifiers":[
        {
            "category":"Restaurant",
            "type":"Food & Drink"
        }
    ],
    "sg:menulink":"http://www.allmenus.com/nc/paw-creek/72578-sbarro/menu/",
    "sg:phone":"+1 704 597 3933",
    "sg:postcode":"28216",
    "sg:province":"NC",
    "sg:tags":[
        "american",
        "pizza"
    ],
    "wof:name":"Sbarro",
    "wof:placetype":"venue"
},
  "geometry": {"coordinates":[-80.879526,35.287004],"type":"Point"}
}