{
  "type": "Feature",
  "properties": {
    "iso:country":"US",
    "sg:address":"7013 Three Bridges Cir",
    "sg:city":"Raleigh",
    "sg:classifiers":[
        {
            "category":"Real Estate",
            "subcategory":"Real Estate Agent",
            "type":"Services"
        }
    ],
    "sg:phone":"+1 919 870 7653",
    "sg:postcode":"27613",
    "sg:province":"NC",
    "wof:name":"Advantage Realty Inc",
    "wof:placetype":"venue"
},
  "geometry": {"coordinates":[-78.688993,35.875691],"type":"Point"}
}