{
  "type": "Feature",
  "properties": {
    "iso:country":"US",
    "sg:address":"1711 E Ash St",
    "sg:city":"Goldsboro",
    "sg:classifiers":[
        {
            "category":"Shopping",
            "subcategory":"Musical Instruments",
            "type":"Retail Goods"
        }
    ],
    "sg:phone":"+1 919 735 4481",
    "sg:postcode":"27530",
    "sg:province":"NC",
    "wof:name":"Frederick's Music Inc",
    "wof:placetype":"venue"
},
  "geometry": {"coordinates":[-77.968994,35.378147],"type":"Point"}
}