{
  "type": "Feature",
  "properties": {
    "addr:full":"6633 Siler City Snow Camp Rd Siler City NC 27344",
    "addr:housenumber":"6633",
    "addr:postcode":"27344",
    "addr:street":"Snow Camp Rd",
    "iso:country":"US",
    "sg:address":"6633 Siler City Snow Camp Rd",
    "sg:city":"Siler City",
    "sg:classifiers":[
        {
            "category":"Professional",
            "subcategory":"Management & Consulting",
            "type":"Services"
        }
    ],
    "sg:phone":"+1   ",
    "sg:postcode":"27344",
    "sg:province":"NC",
    "wof:name":"David Seagrove",
    "wof:placetype":"venue"
},
  "geometry": {"coordinates":[-79.433137,35.806898],"type":"Point"}
}