{
  "type": "Feature",
  "properties": {
    "iso:country":"US",
    "sg:address":"404 Shadowbrook Dr",
    "sg:city":"Burlington",
    "sg:classifiers":[
        {
            "category":"Professional",
            "subcategory":"Engineering",
            "type":"Services"
        }
    ],
    "sg:phone":"+1   ",
    "sg:postcode":"27215",
    "sg:province":"NC",
    "sg:tags":[
        "machine",
        "designing"
    ],
    "wof:name":"Ibis Machine Design Inc",
    "wof:placetype":"venue"
},
  "geometry": {"coordinates":[-79.480189,36.087778],"type":"Point"}
}