{
  "type": "Feature",
  "properties": {
    "iso:country":"US",
    "sg:address":"705 Magnolia St",
    "sg:city":"Greensboro",
    "sg:classifiers":[
        {
            "category":"Professional",
            "subcategory":"Business Services",
            "type":"Services"
        }
    ],
    "sg:phone":"+1   ",
    "sg:postcode":"27401",
    "sg:province":"NC",
    "wof:name":"Nancy Caldwell Interiors",
    "wof:placetype":"venue"
},
  "geometry": {"coordinates":[-79.78843000000001,36.081571],"type":"Point"}
}