{
  "type": "Feature",
  "properties": {
    "iso:country":"US",
    "sg:address":"105 Sunset Dr",
    "sg:city":"Greensboro",
    "sg:classifiers":[
        {
            "category":"Manufacturing",
            "subcategory":"Toys & Sporting Goods",
            "type":"Manufacturing & Wholesale Goods"
        }
    ],
    "sg:phone":"+1 336 574 2464",
    "sg:postcode":"27408",
    "sg:province":"NC",
    "sg:tags":[
        "mfg"
    ],
    "wof:name":"Southeast Sports Sales",
    "wof:placetype":"venue"
},
  "geometry": {"coordinates":[-79.789884,36.09672],"type":"Point"}
}