{
  "type": "Feature",
  "properties": {
    "iso:country":"US",
    "sg:address":"139 Mina Dr",
    "sg:city":"Kinston",
    "sg:classifiers":[
        {
            "category":"Retail",
            "subcategory":"Portrait Studio",
            "type":"Services"
        }
    ],
    "sg:phone":"+1 252 523 0986",
    "sg:postcode":"28504",
    "sg:province":"NC",
    "sg:tags":[
        "photographer"
    ],
    "wof:name":"Williamson's Photography",
    "wof:placetype":"venue"
},
  "geometry": {"coordinates":[-77.621461,35.184899],"type":"Point"}
}