{
  "type": "Feature",
  "properties": {
    "iso:country":"US",
    "sg:address":"2009 Woodland Ave",
    "sg:city":"Burlington",
    "sg:classifiers":[
        {
            "category":"Health Services",
            "subcategory":"Clinic",
            "type":"Services"
        }
    ],
    "sg:phone":"+1 336 226 3359",
    "sg:postcode":"27215",
    "sg:province":"NC",
    "sg:tags":[
        "information",
        "program",
        "referral"
    ],
    "wof:name":"Registry Partners",
    "wof:placetype":"venue"
},
  "geometry": {"coordinates":[-79.47196099999999,36.096291],"type":"Point"}
}