{
  "type": "Feature",
  "properties": {
    "addr:full":"122 Gladiolus Ln Kittrell NC 27544",
    "addr:housenumber":"122",
    "addr:postcode":"27544",
    "addr:street":"Gladiolus Ln",
    "iso:country":"US",
    "sg:address":"122 Gladiolus Ln",
    "sg:city":"Kittrell",
    "sg:classifiers":[
        {
            "category":"Personal",
            "subcategory":"Beauty Salon",
            "type":"Services"
        }
    ],
    "sg:phone":"+1 252 492 1883",
    "sg:postcode":"27544",
    "sg:province":"NC",
    "sg:tags":[
        "shop"
    ],
    "wof:name":"Pat's Beauty Shop",
    "wof:placetype":"venue"
},
  "geometry": {"coordinates":[-78.442916,36.191759],"type":"Point"}
}