{
  "type": "Feature",
  "properties": {
    "iso:country":"US",
    "sg:address":"2665 Reynolds Dr",
    "sg:city":"Winston Salem",
    "sg:classifiers":[
        {
            "category":"Banks & Credit Unions",
            "subcategory":"Financial Services",
            "type":"Services"
        }
    ],
    "sg:phone":"+1 336 727 9251",
    "sg:postcode":"27104",
    "sg:province":"NC",
    "sg:tags":[
        "investor"
    ],
    "wof:name":"Gritches Investment Club LLP",
    "wof:placetype":"venue"
},
  "geometry": {"coordinates":[-80.289423,36.101518],"type":"Point"}
}