{
  "type": "Feature",
  "properties": {
    "addr:full":"584 Conley Rd Morganton NC 28655",
    "addr:housenumber":"584",
    "addr:postcode":"28655",
    "addr:street":"Conley Rd",
    "iso:country":"US",
    "sg:address":"584 Conley Rd",
    "sg:city":"Morganton",
    "sg:classifiers":[
        {
            "category":"Restaurant",
            "type":"Food & Drink"
        }
    ],
    "sg:phone":"+1 828 438 8682",
    "sg:postcode":"28655",
    "sg:province":"NC",
    "sg:tags":[
        "eating"
    ],
    "wof:name":"G R China",
    "wof:placetype":"venue"
},
  "geometry": {"coordinates":[-81.760983,35.703506],"type":"Point"}
}