{
  "type": "Feature",
  "properties": {
    "iso:country":"US",
    "sg:address":"14435 Pommel Ln",
    "sg:city":"Matthews",
    "sg:classifiers":[
        {
            "category":"Retail",
            "subcategory":"Repair Shop",
            "type":"Services"
        }
    ],
    "sg:phone":"+1 704 847 6639",
    "sg:postcode":"28105",
    "sg:province":"NC",
    "sg:tags":[
        "equipment",
        "telephone",
        "system"
    ],
    "sg:website":"www.nortelworks.com",
    "wof:name":"Nortel Network",
    "wof:placetype":"venue"
},
  "geometry": {"coordinates":[-80.66702600000001,35.123415],"type":"Point"}
}