{
  "type": "Feature",
  "properties": {
    "iso:country":"US",
    "sg:address":"320 Will Isaacs Rd",
    "sg:city":"Zionville",
    "sg:classifiers":[
        {
            "category":"Travel",
            "subcategory":"Hotels & Motels",
            "type":"Entertainment"
        }
    ],
    "sg:phone":"+1   ",
    "sg:postcode":"28698",
    "sg:province":"NC",
    "sg:tags":[
        "operation"
    ],
    "wof:name":"Hoot Owl Hollow Cabin Rentals",
    "wof:placetype":"venue"
},
  "geometry": {"coordinates":[-81.74256200000001,36.294202],"type":"Point"}
}