{
  "type": "Feature",
  "properties": {
    "iso:country":"US",
    "sg:address":"2001 S Main St",
    "sg:city":"Salisbury",
    "sg:classifiers":[
        {
            "category":"Professional",
            "subcategory":"Management & Consulting",
            "type":"Services"
        }
    ],
    "sg:phone":"+1 704 637 7110",
    "sg:postcode":"28144",
    "sg:province":"NC",
    "sg:tags":[
        "consultant",
        "business"
    ],
    "wof:name":"Custom Design",
    "wof:placetype":"venue"
},
  "geometry": {"coordinates":[-80.49683,35.652886],"type":"Point"}
}