{
  "type": "Feature",
  "properties": {
    "addr:full":"809 Morven Rd Wadesboro NC 28170",
    "addr:housenumber":"809",
    "addr:postcode":"28170",
    "addr:street":"Morven Rd",
    "iso:country":"US",
    "sg:address":"809 Morven Rd",
    "sg:city":"Wadesboro",
    "sg:classifiers":[
        {
            "category":"Building & Trades",
            "subcategory":"Construction",
            "type":"Services"
        }
    ],
    "sg:phone":"+1 704 694 6751",
    "sg:postcode":"28170",
    "sg:province":"NC",
    "sg:tags":[
        "house"
    ],
    "wof:name":"Kent J Thompson",
    "wof:placetype":"venue"
},
  "geometry": {"coordinates":[-80.073278,34.958514],"type":"Point"}
}