{
  "type": "Feature",
  "properties": {
    "addr:full":"4233 Morton-Pulliam Rd Roxboro NC 27574",
    "addr:housenumber":"4233",
    "addr:postcode":"27574",
    "addr:street":"Morton-Pulliam Rd",
    "iso:country":"US",
    "sg:address":"4233 Morton-Pulliam Rd",
    "sg:city":"Roxboro",
    "sg:classifiers":[
        {
            "category":"Organizations",
            "subcategory":"Religious Organization",
            "type":"Services"
        }
    ],
    "sg:phone":"+1   ",
    "sg:postcode":"27574",
    "sg:province":"NC",
    "wof:name":"Oak Grove Untd Methdst Church",
    "wof:placetype":"venue"
},
  "geometry": {"coordinates":[-79.042214,36.446013],"type":"Point"}
}