{
  "type": "Feature",
  "properties": {
    "addr:full":"10224 Baileywick Rd Raleigh NC 27613",
    "addr:housenumber":"10224",
    "addr:postcode":"27613",
    "addr:street":"Baileywick Rd",
    "iso:country":"US",
    "sg:address":"10224 Baileywick Rd",
    "sg:city":"Raleigh",
    "sg:classifiers":[
        {
            "category":"Education",
            "subcategory":"School",
            "type":"Public Place"
        }
    ],
    "sg:phone":"+1 919 786 0114",
    "sg:postcode":"27613",
    "sg:province":"NC",
    "sg:tags":[
        "religious"
    ],
    "sg:website":"www.trinityacademy.com",
    "wof:name":"Trinity Academy Of Raleigh",
    "wof:placetype":"venue"
},
  "geometry": {"coordinates":[-78.702167,35.906561],"type":"Point"}
}