{
  "type": "Feature",
  "properties": {
    "iso:country":"US",
    "sg:address":"23 Daniel Rd",
    "sg:city":"Asheville",
    "sg:classifiers":[
        {
            "category":"Real Estate",
            "subcategory":"Real Estate Agent",
            "type":"Services"
        }
    ],
    "sg:phone":"+1 828 667 5498",
    "sg:postcode":"28806",
    "sg:province":"NC",
    "wof:name":"Peek Investment RE LLC",
    "wof:placetype":"venue"
},
  "geometry": {"coordinates":[-82.639582,35.571396],"type":"Point"}
}