{
  "type": "Feature",
  "properties": {
    "iso:country":"US",
    "sg:address":"113 Teakwood Dr",
    "sg:city":"Greensboro",
    "sg:classifiers":[
        {
            "category":"Building & Trades",
            "subcategory":"Cleaning & Sanitation",
            "type":"Services"
        }
    ],
    "sg:phone":"+1   ",
    "sg:postcode":"27406",
    "sg:province":"NC",
    "sg:tags":[
        "maintenance"
    ],
    "wof:name":"3 Sisters Cleaning Service",
    "wof:placetype":"venue"
},
  "geometry": {"coordinates":[-79.801457,36.004273],"type":"Point"}
}