{
  "type": "Feature",
  "properties": {
    "iso:country":"US",
    "sg:address":"281 Washboard Ave",
    "sg:city":"Mount Olive",
    "sg:classifiers":[
        {
            "category":"Personal",
            "subcategory":"Beauty Salon",
            "type":"Services"
        }
    ],
    "sg:phone":"+1   ",
    "sg:postcode":"28365",
    "sg:province":"NC",
    "sg:tags":[
        "shop"
    ],
    "wof:name":"Doris Beauty Shop",
    "wof:placetype":"venue"
},
  "geometry": {"coordinates":[-77.899984,35.12006],"type":"Point"}
}