{
  "type": "Feature",
  "properties": {
    "addr:full":"221 S Selma Rd Wendell NC 27591",
    "addr:housenumber":"221",
    "addr:postcode":"27591",
    "addr:street":"S Selma Rd",
    "iso:country":"US",
    "sg:address":"221 S Selma Rd",
    "sg:city":"Wendell",
    "sg:classifiers":[
        {
            "category":"Building & Trades",
            "subcategory":"Cleaning & Sanitation",
            "type":"Services"
        }
    ],
    "sg:phone":"+1   ",
    "sg:postcode":"27591",
    "sg:province":"NC",
    "sg:tags":[
        "maintenance"
    ],
    "wof:name":"Jani-King",
    "wof:placetype":"venue"
},
  "geometry": {"coordinates":[-78.36185399999999,35.777513],"type":"Point"}
}