{
  "type": "Feature",
  "properties": {
    "addr:full":"2008 Cotton Grove Rd Lexington NC 27292",
    "addr:housenumber":"2008",
    "addr:postcode":"27292",
    "addr:street":"Cotton Grove Rd",
    "iso:country":"US",
    "sg:address":"2008 Cotton Grove Rd",
    "sg:city":"Lexington",
    "sg:classifiers":[
        {
            "category":"Utilities",
            "subcategory":"Fuel Oil & Lpg",
            "type":"Services"
        }
    ],
    "sg:phone":"+1 704 352 5700",
    "sg:postcode":"27292",
    "sg:province":"NC",
    "wof:name":"Snellings Oil Co",
    "wof:placetype":"venue"
},
  "geometry": {"coordinates":[-80.25921,35.770271],"type":"Point"}
}