{
  "type": "Feature",
  "properties": {
    "addr:full":"2216 Hawkins St Charlotte NC 28203",
    "addr:housenumber":"2216",
    "addr:postcode":"28203",
    "addr:street":"Hawkins St",
    "iso:country":"US",
    "sg:address":"2216 Hawkins St",
    "sg:city":"Charlotte",
    "sg:classifiers":[
        {
            "category":"Professional",
            "type":"Services"
        }
    ],
    "sg:phone":"+1 704 375 0082",
    "sg:postcode":"28203",
    "sg:province":"NC",
    "wof:name":"Ladonnas Finds & Designs",
    "wof:placetype":"venue"
},
  "geometry": {"coordinates":[-80.865218,35.207338],"type":"Point"}
}