{
  "type": "Feature",
  "properties": {
    "addr:full":"2111 S Elm Eugene St Greensboro NC 27406",
    "addr:housenumber":"2111",
    "addr:postcode":"27406",
    "addr:street":"S Elm Eugene St",
    "iso:country":"US",
    "sg:address":"2111 S Elm Eugene St",
    "sg:city":"Greensboro",
    "sg:classifiers":[
        {
            "category":"Manufacturing",
            "subcategory":"Metals",
            "type":"Manufacturing & Wholesale Goods"
        }
    ],
    "sg:phone":"+1 336 274 3731",
    "sg:postcode":"27406",
    "sg:province":"NC",
    "sg:tags":[
        "nut",
        "bolt"
    ],
    "sg:website":"www.automotivefasteners.com",
    "wof:name":"Automotive Fasteners Inc",
    "wof:placetype":"venue"
},
  "geometry": {"coordinates":[-79.791481,36.046014],"type":"Point"}
}