{
  "type": "Feature",
  "properties": {
    "addr:full":"55 Bennett Dr Maggie Valley NC 28751",
    "addr:housenumber":"55",
    "addr:postcode":"28751",
    "addr:street":"Bennett Dr Maggie",
    "iso:country":"US",
    "sg:address":"55 Bennett Dr",
    "sg:city":"Maggie Valley",
    "sg:classifiers":[
        {
            "category":"Building & Trades",
            "subcategory":"Construction",
            "type":"Services"
        }
    ],
    "sg:phone":"+1 828 926 3396",
    "sg:postcode":"28751",
    "sg:province":"NC",
    "sg:tags":[
        "residential",
        "nonresidential"
    ],
    "wof:name":"J Ring General Contractor",
    "wof:placetype":"venue"
},
  "geometry": {"coordinates":[-83.070662,35.511685],"type":"Point"}
}