{
  "type": "Feature",
  "properties": {
    "iso:country":"US",
    "sg:address":"1050 N May St",
    "sg:city":"Southern Pines",
    "sg:classifiers":[
        {
            "category":"Personal",
            "subcategory":"Beauty Salon",
            "type":"Services"
        }
    ],
    "sg:phone":"+1   ",
    "sg:postcode":"28387",
    "sg:province":"NC",
    "sg:tags":[
        "shop"
    ],
    "wof:name":"Ambiance Salon",
    "wof:placetype":"venue"
},
  "geometry": {"coordinates":[-79.378063,35.178929],"type":"Point"}
}