{
  "type": "Feature",
  "properties": {
    "iso:country":"US",
    "sg:address":"4551 Beatties Ford Rd",
    "sg:city":"Charlotte",
    "sg:classifiers":[
        {
            "category":"Manufacturing",
            "subcategory":"Glass & Minerals",
            "type":"Manufacturing & Wholesale Goods"
        }
    ],
    "sg:phone":"+1 704 392 1333",
    "sg:postcode":"28216",
    "sg:province":"NC",
    "sg:website":"http://www.martinmarietta.com",
    "wof:name":"Martin Marietta Aggregates",
    "wof:placetype":"venue"
},
  "geometry": {"coordinates":[-80.855997,35.296681],"type":"Point"}
}