{
  "type": "Feature",
  "properties": {
    "addr:full":"4803 S Tryon St Charlotte NC 28217",
    "addr:housenumber":"4803",
    "addr:postcode":"28217",
    "addr:street":"S Tryon St",
    "iso:country":"US",
    "sg:address":"4803 S Tryon St",
    "sg:city":"Charlotte",
    "sg:classifiers":[
        {
            "category":"Shopping",
            "subcategory":"Florist",
            "type":"Retail Goods"
        }
    ],
    "sg:phone":"+1 704 521 9080",
    "sg:postcode":"28217",
    "sg:province":"NC",
    "wof:name":"Kelly's Flowers",
    "wof:placetype":"venue"
},
  "geometry": {"coordinates":[-80.890882,35.178936],"type":"Point"}
}