{
  "type": "Feature",
  "properties": {
    "addr:full":"361 Holland Dr Statesville NC 28677",
    "addr:housenumber":"361",
    "addr:postcode":"28677",
    "addr:street":"Holland Dr",
    "iso:country":"US",
    "sg:address":"361 Holland Dr",
    "sg:city":"Statesville",
    "sg:classifiers":[
        {
            "category":"Real Estate",
            "subcategory":"Real Estate Agent",
            "type":"Services"
        }
    ],
    "sg:phone":"+1 704 872 2265",
    "sg:postcode":"28677",
    "sg:province":"NC",
    "wof:name":"Miller Realty Services In",
    "wof:placetype":"venue"
},
  "geometry": {"coordinates":[-80.883833,35.791982],"type":"Point"}
}