{
  "type": "Feature",
  "properties": {
    "iso:country":"US",
    "sg:address":"17 Foggy Mountain Rd",
    "sg:city":"Leicester",
    "sg:classifiers":[
        {
            "category":"Retail",
            "subcategory":"Repair Shop",
            "type":"Services"
        }
    ],
    "sg:phone":"+1   ",
    "sg:postcode":"28742",
    "sg:province":"NC",
    "wof:name":"K & M Small Engine Sls & Svcs",
    "wof:placetype":"venue"
},
  "geometry": {"coordinates":[-82.62723800000001,35.314346],"type":"Point"}
}