{
  "type": "Feature",
  "properties": {
    "addr:full":"3301 Robinson Cir Charlotte NC 28206",
    "addr:housenumber":"3301",
    "addr:postcode":"28206",
    "addr:street":"Robinson Cir",
    "iso:country":"US",
    "sg:address":"3301 Robinson Cir",
    "sg:city":"Charlotte",
    "sg:classifiers":[
        {
            "category":"Freight",
            "type":"Transportation"
        }
    ],
    "sg:phone":"+1 704 858 0051",
    "sg:postcode":"28206",
    "sg:province":"NC",
    "wof:name":"Export Import Us",
    "wof:placetype":"venue"
},
  "geometry": {"coordinates":[-80.81156799999999,35.255781],"type":"Point"}
}