{
  "type": "Feature",
  "properties": {
    "addr:full":"9380 Falls Of Neuse Rd Ste 101 Raleigh NC 27615",
    "addr:housenumber":"9380",
    "addr:postcode":"27615",
    "addr:street":"Falls Of Neuse Rd Ste 101",
    "iso:country":"US",
    "sg:address":"9380 Falls Of Neuse Rd Ste 101",
    "sg:city":"Raleigh",
    "sg:classifiers":[
        {
            "category":"Health Services",
            "subcategory":"Chiropractor",
            "type":"Services"
        }
    ],
    "sg:phone":"+1 919 870 9500",
    "sg:postcode":"27615",
    "sg:province":"NC",
    "sg:tags":[
        "chiropractic"
    ],
    "wof:name":"Swindler, Barry P, Dc - Carolina Chiropractic",
    "wof:placetype":"venue"
},
  "geometry": {"coordinates":[-78.60417700000001,35.902671],"type":"Point"}
}