{
  "type": "Feature",
  "properties": {
    "addr:full":"549 Trolling Ln Corolla NC 27927",
    "addr:housenumber":"549",
    "addr:postcode":"27927",
    "addr:street":"Trolling Ln",
    "iso:country":"US",
    "sg:address":"549 Trolling Ln",
    "sg:city":"Corolla",
    "sg:classifiers":[
        {
            "category":"Real Estate",
            "subcategory":"Architect",
            "type":"Services"
        }
    ],
    "sg:phone":"+1 252 453 4335",
    "sg:postcode":"27927",
    "sg:province":"NC",
    "sg:tags":[
        "architectural"
    ],
    "wof:name":"Jeffrey A Lees AIA",
    "wof:placetype":"venue"
},
  "geometry": {"coordinates":[-75.80282699999999,36.298687],"type":"Point"}
}