{
  "type": "Feature",
  "properties": {
    "iso:country":"US",
    "sg:address":"2601 Iron Gate Dr",
    "sg:city":"Wilmington",
    "sg:classifiers":[
        {
            "category":"Real Estate",
            "subcategory":"Real Estate Operator",
            "type":"Services"
        }
    ],
    "sg:phone":"+1 910 395 0984",
    "sg:postcode":"28412",
    "sg:province":"NC",
    "sg:tags":[
        "building",
        "nonresidential"
    ],
    "wof:name":"Cameron Properties LP",
    "wof:placetype":"venue"
},
  "geometry": {"coordinates":[-77.912312,34.192203],"type":"Point"}
}