{
  "type": "Feature",
  "properties": {
    "iso:country":"US",
    "sg:address":"115 E 3rd St",
    "sg:city":"Ayden",
    "sg:classifiers":[
        {
            "category":"Restaurant",
            "type":"Food & Drink"
        }
    ],
    "sg:phone":"+1 252 746 6880",
    "sg:postcode":"28513",
    "sg:province":"NC",
    "sg:tags":[
        "eating"
    ],
    "wof:name":"Bums Restaurant",
    "wof:placetype":"venue"
},
  "geometry": {"coordinates":[-77.417434,35.471029],"type":"Point"}
}