{
  "type": "Feature",
  "properties": {
    "addr:full":"11181 US Hwy 70 W Clayton NC 27520",
    "addr:housenumber":"11181",
    "addr:postcode":"27520",
    "addr:street":"Us Hwy 70 W",
    "iso:country":"US",
    "sg:address":"11181 US Hwy 70 W",
    "sg:city":"Clayton",
    "sg:classifiers":[
        {
            "category":"Professional",
            "subcategory":"Lawyer & Legal Services",
            "type":"Services"
        }
    ],
    "sg:phone":"+1 919 553 2121",
    "sg:postcode":"27520",
    "sg:province":"NC",
    "sg:tags":[
        "attorney"
    ],
    "wof:name":"Richard M Price",
    "wof:placetype":"venue"
},
  "geometry": {"coordinates":[-78.467297,35.647925],"type":"Point"}
}