{
  "type": "Feature",
  "properties": {
    "addr:full":"1520 Sunday Dr Raleigh NC 27607",
    "addr:housenumber":"1520",
    "addr:postcode":"27607",
    "addr:street":"Sunday Dr",
    "iso:country":"US",
    "sg:address":"1520 Sunday Dr",
    "sg:city":"Raleigh",
    "sg:classifiers":[
        {
            "category":"Health Services",
            "subcategory":"Doctor",
            "type":"Services"
        }
    ],
    "sg:phone":"+1 919 782 3456",
    "sg:postcode":"27607",
    "sg:province":"NC",
    "sg:website":"www.raleighneurology.com",
    "wof:name":"Syndee J Givre MD",
    "wof:placetype":"venue"
},
  "geometry": {"coordinates":[-78.730524,35.800332],"type":"Point"}
}