{
  "type": "Feature",
  "properties": {
    "iso:country":"US",
    "sg:address":"5107 Southpark Dr",
    "sg:city":"Durham",
    "sg:classifiers":[
        {
            "category":"Health Services",
            "subcategory":"Doctor",
            "type":"Services"
        }
    ],
    "sg:phone":"+1   ",
    "sg:postcode":"27713",
    "sg:province":"NC",
    "sg:tags":[
        "medical"
    ],
    "wof:name":"Durham Obstetrics & Gynecology",
    "wof:placetype":"venue"
},
  "geometry": {"coordinates":[-78.9434,35.910799],"type":"Point"}
}