{
  "type": "Feature",
  "properties": {
    "iso:country":"US",
    "sg:address":"5108 US Hwy 601",
    "sg:city":"Yadkinville",
    "sg:classifiers":[
        {
            "category":"Retail",
            "subcategory":"Funeral Services",
            "type":"Services"
        }
    ],
    "sg:phone":"+1 336 679 7111",
    "sg:postcode":"27055",
    "sg:province":"NC",
    "sg:tags":[
        "director",
        "insurance"
    ],
    "wof:name":"Gentry Family Funeral Service",
    "wof:placetype":"venue"
},
  "geometry": {"coordinates":[-80.677701,36.163523],"type":"Point"}
}