{
  "type": "Feature",
  "properties": {
    "addr:full":"1090 Connelly Springs Rd SW Lenoir NC 28645",
    "addr:housenumber":"1090",
    "addr:postcode":"28645",
    "addr:street":"Connelly Springs Rd Sw",
    "iso:country":"US",
    "sg:address":"1090 Connelly Springs Rd SW",
    "sg:city":"Lenoir",
    "sg:classifiers":[
        {
            "category":"Restaurant",
            "type":"Food & Drink"
        }
    ],
    "sg:phone":"+1 828 728 1484",
    "sg:postcode":"28645",
    "sg:province":"NC",
    "wof:name":"Chubby's Of Cajah's Mountain",
    "wof:placetype":"venue"
},
  "geometry": {"coordinates":[-81.53637500000001,35.878121],"type":"Point"}
}