{
  "type": "Feature",
  "properties": {
    "iso:country":"US",
    "sg:address":"909 Colington Dr",
    "sg:city":"Kill Devil Hills",
    "sg:classifiers":[
        {
            "category":"Shopping",
            "subcategory":"Gifts & Souvenirs",
            "type":"Retail Goods"
        }
    ],
    "sg:phone":"+1 252 449 4352",
    "sg:postcode":"27948",
    "sg:province":"NC",
    "sg:tags":[
        "basket",
        "parcel"
    ],
    "wof:name":"Outer Banks Specialty Baskets",
    "wof:placetype":"venue"
},
  "geometry": {"coordinates":[-75.725326,36.020443],"type":"Point"}
}