{
  "type": "Feature",
  "properties": {
    "addr:full":"8820 Aberdeen Rd Aberdeen NC 28315",
    "addr:housenumber":"8820",
    "addr:postcode":"28315",
    "addr:street":"Aberdeen Rd",
    "iso:country":"US",
    "sg:address":"8820 Aberdeen Rd",
    "sg:city":"Aberdeen",
    "sg:classifiers":[
        {
            "category":"Shopping",
            "subcategory":"Used Merchandise",
            "type":"Retail Goods"
        }
    ],
    "sg:phone":"+1 910 944 3177",
    "sg:postcode":"28315",
    "sg:province":"NC",
    "wof:name":"C & C Thrift Mart",
    "wof:placetype":"venue"
},
  "geometry": {"coordinates":[-79.357816,35.074554],"type":"Point"}
}