{
  "type": "Feature",
  "properties": {
    "addr:full":"609 S New Hope Rd Gastonia NC 28054",
    "addr:housenumber":"609",
    "addr:postcode":"28054",
    "addr:street":"S New Hope Rd",
    "iso:country":"US",
    "sg:address":"609 S New Hope Rd",
    "sg:city":"Gastonia",
    "sg:classifiers":[
        {
            "category":"Health Services",
            "subcategory":"Clinic",
            "type":"Services"
        },
        {
            "category":"Professional",
            "subcategory":"Employment Agencies",
            "type":"Services"
        }
    ],
    "sg:phone":"+1 704 833 0042",
    "sg:postcode":"28054",
    "sg:province":"NC",
    "sg:tags":[
        "opportunity",
        "staffing"
    ],
    "wof:name":"Wesley Medical Staffing Inc",
    "wof:placetype":"venue"
},
  "geometry": {"coordinates":[-81.148679,35.256429],"type":"Point"}
}