{
  "type": "Feature",
  "properties": {
    "addr:full":"244 Country Club Rd Camden NC 27921",
    "addr:housenumber":"244",
    "addr:postcode":"27921",
    "addr:street":"Country Club Rd",
    "iso:country":"US",
    "sg:address":"244 Country Club Rd",
    "sg:city":"Camden",
    "sg:classifiers":[
        {
            "category":"Building & Trades",
            "subcategory":"Construction",
            "type":"Services"
        }
    ],
    "sg:phone":"+1 252 335 2657",
    "sg:postcode":"27921",
    "sg:province":"NC",
    "sg:tags":[
        "roofing",
        "contractor"
    ],
    "wof:name":"G A Staples Roofing",
    "wof:placetype":"venue"
},
  "geometry": {"coordinates":[-76.163312,36.306292],"type":"Point"}
}