{
  "type": "Feature",
  "properties": {
    "iso:country":"US",
    "sg:address":"1100 Lisbon St",
    "sg:city":"Clinton",
    "sg:classifiers":[
        {
            "category":"Wholesale",
            "subcategory":"Electrical",
            "type":"Manufacturing & Wholesale Goods"
        }
    ],
    "sg:phone":"+1 910 592 1858",
    "sg:postcode":"28328",
    "sg:province":"NC",
    "sg:tags":[
        "equipment",
        "pole",
        "line"
    ],
    "wof:name":"BVJ Co",
    "wof:placetype":"venue"
},
  "geometry": {"coordinates":[-78.314601,34.98974],"type":"Point"}
}