{
  "type": "Feature",
  "properties": {
    "iso:country":"US",
    "sg:address":"2702 Silk Hope Rd",
    "sg:city":"Siler City",
    "sg:classifiers":[
        {
            "category":"Building & Trades",
            "subcategory":"Electrical",
            "type":"Services"
        }
    ],
    "sg:phone":"+1 919 742 5711",
    "sg:postcode":"27344",
    "sg:province":"NC",
    "sg:tags":[
        "electrical",
        "contractor"
    ],
    "wof:name":"Ed Smith Electric",
    "wof:placetype":"venue"
},
  "geometry": {"coordinates":[-79.403729,35.757487],"type":"Point"}
}