{
  "type": "Feature",
  "properties": {
    "addr:full":"2500 Old Lexington Rd Winston Salem NC 27107",
    "addr:housenumber":"2500",
    "addr:postcode":"27107",
    "addr:street":"Old Lexington Rd",
    "iso:country":"US",
    "sg:address":"2500 Old Lexington Rd",
    "sg:city":"Winston Salem",
    "sg:classifiers":[
        {
            "category":"Manufacturing",
            "subcategory":"Paper Products",
            "type":"Manufacturing & Wholesale Goods"
        }
    ],
    "sg:phone":"+1 336 784 5887",
    "sg:postcode":"27107",
    "sg:province":"NC",
    "wof:name":"T S Paper",
    "wof:placetype":"venue"
},
  "geometry": {"coordinates":[-80.226721,36.06602],"type":"Point"}
}