{
  "type": "Feature",
  "properties": {
    "iso:country":"US",
    "sg:address":"1837 Martin Luther King Jr Pkwy",
    "sg:city":"Durham",
    "sg:classifiers":[
        {
            "category":"Utilities",
            "subcategory":"Mobile Phone",
            "type":"Services"
        },
        {
            "category":"Shopping",
            "type":"Retail Goods"
        }
    ],
    "sg:phone":"+1 919 403 2590",
    "sg:postcode":"27707",
    "sg:province":"NC",
    "sg:tags":[
        "sell",
        "equipment",
        "telephone",
        "cellular"
    ],
    "wof:name":"Cingular Wireless",
    "wof:placetype":"venue"
},
  "geometry": {"coordinates":[-78.95898200000001,35.960845],"type":"Point"}
}