{
  "type": "Feature",
  "properties": {
    "iso:country":"US",
    "sg:address":"270 Sunset Rd",
    "sg:city":"Lumberton",
    "sg:classifiers":[
        {
            "category":"Professional",
            "type":"Services"
        }
    ],
    "sg:phone":"+1 910 738 3294",
    "sg:postcode":"28360",
    "sg:province":"NC",
    "wof:name":"Vernon L Kirby",
    "wof:placetype":"venue"
},
  "geometry": {"coordinates":[-79.026059,34.678017],"type":"Point"}
}