{
  "type": "Feature",
  "properties": {
    "addr:full":"1464 Garner Station Blvd Raleigh NC 27603",
    "addr:housenumber":"1464",
    "addr:postcode":"27603",
    "addr:street":"Garner Station Blvd",
    "iso:country":"US",
    "sg:address":"1464 Garner Station Blvd",
    "sg:city":"Raleigh",
    "sg:classifiers":[
        {
            "category":"Building & Trades",
            "subcategory":"Construction",
            "type":"Services"
        }
    ],
    "sg:phone":"+1 919 639 9400",
    "sg:postcode":"27603",
    "sg:province":"NC",
    "sg:tags":[
        "repairing",
        "remodeling",
        "contractor"
    ],
    "wof:name":"Morrow Enterprises",
    "wof:placetype":"venue"
},
  "geometry": {"coordinates":[-78.657478,35.724917],"type":"Point"}
}