{
  "type": "Feature",
  "properties": {
    "addr:full":"919 Norland Rd Charlotte NC 28205",
    "addr:housenumber":"919",
    "addr:postcode":"28205",
    "addr:street":"Norland Rd",
    "iso:country":"US",
    "sg:address":"919 Norland Rd",
    "sg:city":"Charlotte",
    "sg:classifiers":[
        {
            "category":"Real Estate",
            "subcategory":"Real Estate Services",
            "type":"Services"
        }
    ],
    "sg:phone":"+1 704 535 1122",
    "sg:postcode":"28205",
    "sg:province":"NC",
    "sg:tags":[
        "management",
        "rental"
    ],
    "sg:website":"http://www.hendersonproperties.com",
    "wof:name":"Henderson Properties",
    "wof:placetype":"venue"
},
  "geometry": {"coordinates":[-80.782601,35.202414],"type":"Point"}
}