{
  "type": "Feature",
  "properties": {
    "iso:country":"US",
    "sg:address":"400 Sardis Grove Ln",
    "sg:city":"Matthews",
    "sg:classifiers":[
        {
            "category":"Shopping",
            "subcategory":"Beauty & Cosmetics",
            "type":"Retail Goods"
        },
        {
            "category":"Shopping",
            "subcategory":"Catalog Store",
            "type":"Retail Goods"
        }
    ],
    "sg:phone":"+1 704 841 8453",
    "sg:postcode":"28105",
    "sg:province":"NC",
    "sg:tags":[
        "mail",
        "online",
        "order",
        "perfume"
    ],
    "wof:name":"Beauticontrol",
    "wof:placetype":"venue"
},
  "geometry": {"coordinates":[-80.739098,35.12174],"type":"Point"}
}