{
  "type": "Feature",
  "properties": {
    "iso:country":"US",
    "sg:address":"106 Staton Ct",
    "sg:city":"Greenville",
    "sg:classifiers":[
        {
            "category":"Professional",
            "type":"Services"
        }
    ],
    "sg:phone":"+1 252 353 0800",
    "sg:postcode":"27834",
    "sg:province":"NC",
    "wof:name":"Tia & Sons Co",
    "wof:placetype":"venue"
},
  "geometry": {"coordinates":[-77.356567,35.648342],"type":"Point"}
}