{
  "type": "Feature",
  "properties": {
    "addr:full":"220 Blowing Rock Blvd Lenoir NC 28645",
    "addr:housenumber":"220",
    "addr:postcode":"28645",
    "addr:street":"Blowing Rock Blvd",
    "iso:country":"US",
    "sg:address":"220 Blowing Rock Blvd",
    "sg:city":"Lenoir",
    "sg:classifiers":[
        {
            "category":"Restaurant",
            "type":"Food & Drink"
        }
    ],
    "sg:phone":"+1 828 754 3716",
    "sg:postcode":"28645",
    "sg:province":"NC",
    "wof:name":"Fuji Express",
    "wof:placetype":"venue"
},
  "geometry": {"coordinates":[-81.524869,35.914726],"type":"Point"}
}