{
  "type": "Feature",
  "properties": {
    "iso:country":"US",
    "sg:address":"1101 S Elm St",
    "sg:city":"Greenville",
    "sg:classifiers":[
        {
            "category":"Organizations",
            "subcategory":"Religious Organization",
            "type":"Services"
        }
    ],
    "sg:phone":"+1 252 758 1240",
    "sg:postcode":"27858",
    "sg:province":"NC",
    "sg:website":"www.ibcg.org",
    "wof:name":"Immanuel Baptist Church",
    "wof:placetype":"venue"
},
  "geometry": {"coordinates":[-77.359363,35.600131],"type":"Point"}
}