{
  "type": "Feature",
  "properties": {
    "addr:full":"425 S Beaumont Ave Burlington NC 27217",
    "addr:housenumber":"425",
    "addr:postcode":"27217",
    "addr:street":"S Beaumont Ave",
    "iso:country":"US",
    "sg:address":"425 S Beaumont Ave",
    "sg:city":"Burlington",
    "sg:classifiers":[
        {
            "category":"Personal",
            "subcategory":"Beauty Salon",
            "type":"Services"
        }
    ],
    "sg:phone":"+1 336 437 1300",
    "sg:postcode":"27217",
    "sg:province":"NC",
    "wof:name":"Unlimited Designs Hair & Nail",
    "wof:placetype":"venue"
},
  "geometry": {"coordinates":[-79.41388999999999,36.09368],"type":"Point"}
}