{
  "type": "Feature",
  "properties": {
    "iso:country":"US",
    "sg:address":"1101 N Green St",
    "sg:city":"Morganton",
    "sg:classifiers":[
        {
            "category":"Restaurant",
            "type":"Food & Drink"
        }
    ],
    "sg:phone":"+1 828 433 6747",
    "sg:postcode":"28655",
    "sg:province":"NC",
    "sg:tags":[
        "thai",
        "asian",
        "pan"
    ],
    "wof:name":"Pancho Villa",
    "wof:placetype":"venue"
},
  "geometry": {"coordinates":[-81.721069,35.755379],"type":"Point"}
}