{
  "type": "Feature",
  "properties": {
    "iso:country":"US",
    "sg:address":"315 N 17th St",
    "sg:city":"Wilmington",
    "sg:classifiers":[
        {
            "category":"Wholesale",
            "subcategory":"Machinery & Supplies",
            "type":"Manufacturing & Wholesale Goods"
        }
    ],
    "sg:phone":"+1 910 762 6334",
    "sg:postcode":"28401",
    "sg:province":"NC",
    "sg:tags":[
        "tool"
    ],
    "sg:website":"www.porta-nails.com",
    "wof:name":"Porta-Nails Inc",
    "wof:placetype":"venue"
},
  "geometry": {"coordinates":[-77.928141,34.240825],"type":"Point"}
}