{
  "type": "Feature",
  "properties": {
    "iso:country":"US",
    "sg:address":"4800 Silabert Ave",
    "sg:city":"Charlotte",
    "sg:classifiers":[
        {
            "category":"Wholesale",
            "subcategory":"Medical Equipment & Supplies",
            "type":"Manufacturing & Wholesale Goods"
        },
        {
            "category":"Manufacturing",
            "subcategory":"Tools & Machinery",
            "type":"Manufacturing & Wholesale Goods"
        }
    ],
    "sg:phone":"+1 704 537 3232",
    "sg:postcode":"28205",
    "sg:province":"NC",
    "sg:tags":[
        "mfr",
        "optical",
        "rep"
    ],
    "wof:name":"Sentilles Optical Service",
    "wof:placetype":"venue"
},
  "geometry": {"coordinates":[-80.783151,35.190188],"type":"Point"}
}