{
  "type": "Feature",
  "properties": {
    "addr:full":"212 N Cumberland St Wallace NC 28466",
    "addr:housenumber":"212",
    "addr:postcode":"28466",
    "addr:street":"N Cumberland St",
    "iso:country":"US",
    "sg:address":"212 N Cumberland St",
    "sg:city":"Wallace",
    "sg:classifiers":[
        {
            "category":"Personal",
            "subcategory":"Beauty Salon",
            "type":"Services"
        }
    ],
    "sg:phone":"+1 910 285 1133",
    "sg:postcode":"28466",
    "sg:province":"NC",
    "wof:name":"Miz Donna's",
    "wof:placetype":"venue"
},
  "geometry": {"coordinates":[-78.00009,34.736424],"type":"Point"}
}