{
  "type": "Feature",
  "properties": {
    "iso:country":"US",
    "sg:address":"1437 E Franklin Blvd",
    "sg:city":"Gastonia",
    "sg:classifiers":[
        {
            "category":"Professional",
            "subcategory":"Business Services",
            "type":"Services"
        }
    ],
    "sg:phone":"+1 704 460 4045",
    "sg:postcode":"28054",
    "sg:province":"NC",
    "wof:name":"Design Tech",
    "wof:placetype":"venue"
},
  "geometry": {"coordinates":[-81.154076,35.262126],"type":"Point"}
}