{
  "type": "Feature",
  "properties": {
    "addr:full":"1863 W Ehringhaus St Elizabeth City NC 27909",
    "addr:housenumber":"1863",
    "addr:postcode":"27909",
    "addr:street":"W Ehringhaus St",
    "iso:country":"US",
    "sg:address":"1863 W Ehringhaus St",
    "sg:city":"Elizabeth City",
    "sg:classifiers":[
        {
            "category":"Home & Garden",
            "subcategory":"Furniture",
            "type":"Retail Goods"
        }
    ],
    "sg:phone":"+1 252 331 1003",
    "sg:postcode":"27909",
    "sg:province":"NC",
    "sg:website":"www.mattressdiscounters.com",
    "wof:name":"Mattress Discounters",
    "wof:placetype":"venue"
},
  "geometry": {"coordinates":[-76.251182,36.289742],"type":"Point"}
}