{
  "type": "Feature",
  "properties": {
    "addr:full":"20 Pine St E Lillington NC 27546",
    "addr:housenumber":"20",
    "addr:postcode":"27546",
    "addr:street":"Pine St E",
    "iso:country":"US",
    "sg:address":"20 Pine St E",
    "sg:city":"Lillington",
    "sg:classifiers":[
        {
            "category":"Banks & Credit Unions",
            "subcategory":"Bank",
            "type":"Services"
        }
    ],
    "sg:phone":"+1 910 814 1164",
    "sg:postcode":"27546",
    "sg:province":"NC",
    "wof:name":"Fidelity Bank",
    "wof:placetype":"venue"
},
  "geometry": {"coordinates":[-78.839381,35.405938],"type":"Point"}
}