{
  "type": "Feature",
  "properties": {
    "addr:full":"1510 Burgaw Hwy Jacksonville NC 28540",
    "addr:housenumber":"1510",
    "addr:postcode":"28540",
    "addr:street":"Burgaw Hwy",
    "iso:country":"US",
    "sg:address":"1510 Burgaw Hwy",
    "sg:city":"Jacksonville",
    "sg:classifiers":[
        {
            "category":"Utilities",
            "subcategory":"Refuse",
            "type":"Services"
        }
    ],
    "sg:phone":"+1 910 347 9033",
    "sg:postcode":"28540",
    "sg:province":"NC",
    "sg:tags":[
        "garbage",
        "system",
        "collection"
    ],
    "wof:name":"A-1 Marine Sanitation",
    "wof:placetype":"venue"
},
  "geometry": {"coordinates":[-77.483724,34.746413],"type":"Point"}
}