{
  "type": "Feature",
  "properties": {
    "iso:country":"US",
    "sg:address":"2996 Institute Rd",
    "sg:city":"La Grange",
    "sg:classifiers":[
        {
            "category":"Retail",
            "subcategory":"Animal Services",
            "type":"Services"
        }
    ],
    "sg:phone":"+1 252 566 3355",
    "sg:postcode":"28551",
    "sg:province":"NC",
    "sg:tags":[
        "pet",
        "grooming",
        "washing"
    ],
    "wof:name":"Poodle Spa",
    "wof:placetype":"venue"
},
  "geometry": {"coordinates":[-77.685337,35.341251],"type":"Point"}
}