{
  "type": "Feature",
  "properties": {
    "addr:full":"6260 Meadowview Dr Davidson NC 28036",
    "addr:housenumber":"6260",
    "addr:postcode":"28036",
    "addr:street":"Meadowview Dr",
    "iso:country":"US",
    "sg:address":"6260 Meadowview Dr",
    "sg:city":"Davidson",
    "sg:classifiers":[
        {
            "category":"Professional",
            "type":"Services"
        }
    ],
    "sg:phone":"+1 704 933 8151",
    "sg:postcode":"28036",
    "sg:province":"NC",
    "wof:name":"Robert Bruce Baker",
    "wof:placetype":"venue"
},
  "geometry": {"coordinates":[-80.733936,35.497015],"type":"Point"}
}