{
  "type": "Feature",
  "properties": {
    "addr:full":"1938 N Roberts Ave Lumberton NC 28358",
    "addr:housenumber":"1938",
    "addr:postcode":"28358",
    "addr:street":"N Roberts Ave",
    "iso:country":"US",
    "sg:address":"1938 N Roberts Ave",
    "sg:city":"Lumberton",
    "sg:classifiers":[
        {
            "category":"Retail",
            "subcategory":"Self-service Laundry",
            "type":"Services"
        }
    ],
    "sg:phone":"+1 910 735 0030",
    "sg:postcode":"28358",
    "sg:province":"NC",
    "wof:name":"Jt's Laundry Ctr",
    "wof:placetype":"venue"
},
  "geometry": {"coordinates":[-78.993785,34.633573],"type":"Point"}
}