{
  "type": "Feature",
  "properties": {
    "addr:full":"22 S Main Ave Newton NC 28658",
    "addr:housenumber":"22",
    "addr:postcode":"28658",
    "addr:street":"S Main Ave",
    "iso:country":"US",
    "sg:address":"22 S Main Ave",
    "sg:city":"Newton",
    "sg:classifiers":[
        {
            "category":"Real Estate",
            "subcategory":"Real Estate Agent",
            "type":"Services"
        }
    ],
    "sg:phone":"+1 828 466 2575",
    "sg:postcode":"28658",
    "sg:province":"NC",
    "sg:tags":[
        "appraiser"
    ],
    "wof:name":"NC Realty & Appraisal Inc",
    "wof:placetype":"venue"
},
  "geometry": {"coordinates":[-81.222858,35.662208],"type":"Point"}
}