{
  "type": "Feature",
  "properties": {
    "addr:full":"10750 State Hwy 53 Burgaw NC 28425",
    "addr:housenumber":"10750",
    "addr:postcode":"28425",
    "addr:street":"State Hwy 53",
    "iso:country":"US",
    "sg:address":"10750 State Hwy 53",
    "sg:city":"Burgaw",
    "sg:classifiers":[
        {
            "category":"Education",
            "subcategory":"School",
            "type":"Public Place"
        }
    ],
    "sg:phone":"+1 910 283 5626",
    "sg:postcode":"28425",
    "sg:province":"NC",
    "sg:website":"www.pendercountyschools.net",
    "wof:name":"West Pender Middle School",
    "wof:placetype":"venue"
},
  "geometry": {"coordinates":[-78.110603,34.526726],"type":"Point"}
}