{
  "type": "Feature",
  "properties": {
    "addr:full":"112 E Dixon Blvd Shelby NC 28152",
    "addr:housenumber":"112",
    "addr:postcode":"28152",
    "addr:street":"E Dixon Blvd",
    "iso:country":"US",
    "sg:address":"112 E Dixon Blvd",
    "sg:city":"Shelby",
    "sg:classifiers":[
        {
            "category":"Social Services",
            "type":"Services"
        }
    ],
    "sg:phone":"+1 704 487 9780",
    "sg:postcode":"28152",
    "sg:province":"NC",
    "sg:tags":[
        "organization",
        "welfare"
    ],
    "wof:name":"Comserv",
    "wof:placetype":"venue"
},
  "geometry": {"coordinates":[-81.54207599999999,35.278684],"type":"Point"}
}