{
  "type": "Feature",
  "properties": {
    "iso:country":"US",
    "sg:address":"8801 Forest Shadow Cir",
    "sg:city":"Cornelius",
    "sg:classifiers":[
        {
            "category":"Professional",
            "subcategory":"Management & Consulting",
            "type":"Services"
        }
    ],
    "sg:phone":"+1   ",
    "sg:postcode":"28031",
    "sg:province":"NC",
    "sg:tags":[
        "business"
    ],
    "wof:name":"Strafford Forest Cabana",
    "wof:placetype":"venue"
},
  "geometry": {"coordinates":[-80.87403399999999,35.449366],"type":"Point"}
}