{
  "type": "Feature",
  "properties": {
    "addr:full":"746 Crabtree Rd Carthage NC 28327",
    "addr:housenumber":"746",
    "addr:postcode":"28327",
    "addr:street":"Crabtree Rd",
    "iso:country":"US",
    "sg:address":"746 Crabtree Rd",
    "sg:city":"Carthage",
    "sg:classifiers":[
        {
            "category":"Farming",
            "subcategory":"Poultry Farm",
            "type":"Manufacturing & Wholesale Goods"
        }
    ],
    "sg:phone":"+1 910 948 2300",
    "sg:postcode":"28327",
    "sg:province":"NC",
    "sg:tags":[
        "chicken",
        "egg"
    ],
    "wof:name":"Flinchum Jack Chicken Egg Farm",
    "wof:placetype":"venue"
},
  "geometry": {"coordinates":[-79.50231700000001,35.399252],"type":"Point"}
}