{
  "type": "Feature",
  "properties": {
    "iso:country":"US",
    "sg:address":"4912 Hoover Hill Rd",
    "sg:city":"Trinity",
    "sg:classifiers":[
        {
            "category":"Recreation",
            "subcategory":"Marina",
            "type":"Entertainment"
        }
    ],
    "sg:phone":"+1 336 431 9500",
    "sg:postcode":"27370",
    "sg:province":"NC",
    "sg:tags":[
        "repairing",
        "boat"
    ],
    "wof:name":"South Main Automotive & Marine",
    "wof:placetype":"venue"
},
  "geometry": {"coordinates":[-79.94799999999999,35.825842],"type":"Point"}
}