{
  "type": "Feature",
  "properties": {
    "addr:full":"136 Ostwalt Amity Rd Troutman NC 28166",
    "addr:housenumber":"136",
    "addr:postcode":"28166",
    "addr:street":"Ostwalt Amity Rd",
    "iso:country":"US",
    "sg:address":"136 Ostwalt Amity Rd",
    "sg:city":"Troutman",
    "sg:classifiers":[
        {
            "category":"Professional",
            "subcategory":"Engineering",
            "type":"Services"
        }
    ],
    "sg:phone":"+1   ",
    "sg:postcode":"28166",
    "sg:province":"NC",
    "wof:name":"Baker Testing Services",
    "wof:placetype":"venue"
},
  "geometry": {"coordinates":[-80.858869,35.682582],"type":"Point"}
}