{
  "type": "Feature",
  "properties": {
    "iso:country":"US",
    "sg:address":"884 Rosewood Rd",
    "sg:city":"Goldsboro",
    "sg:classifiers":[
        {
            "category":"Government",
            "subcategory":"Fire Station",
            "type":"Public Place"
        }
    ],
    "sg:phone":"+1 919 735 5066",
    "sg:postcode":"27530",
    "sg:province":"NC",
    "sg:tags":[
        "protection"
    ],
    "wof:name":"Fork Township Fire Dept",
    "wof:placetype":"venue"
},
  "geometry": {"coordinates":[-78.081295,35.416174],"type":"Point"}
}