{
  "type": "Feature",
  "properties": {
    "addr:full":"129 Cedar Hill Ln Henrico NC 27842",
    "addr:housenumber":"129",
    "addr:postcode":"27842",
    "addr:street":"Cedar Hill Ln",
    "iso:country":"US",
    "sg:address":"129 Cedar Hill Ln",
    "sg:city":"Henrico",
    "sg:classifiers":[
        {
            "category":"Social Services",
            "subcategory":"Child Care",
            "type":"Services"
        }
    ],
    "sg:phone":"+1 252 537 4414",
    "sg:postcode":"27842",
    "sg:province":"NC",
    "wof:name":"Academy Of Little Lambs",
    "wof:placetype":"venue"
},
  "geometry": {"coordinates":[-77.876137,36.521399],"type":"Point"}
}