{
  "type": "Feature",
  "properties": {
    "addr:full":"527 Keisler Dr Cary NC 27518",
    "addr:housenumber":"527",
    "addr:postcode":"27518",
    "addr:street":"Keisler Dr",
    "iso:country":"US",
    "sg:address":"527 Keisler Dr",
    "sg:city":"Cary",
    "sg:classifiers":[
        {
            "category":"Health Services",
            "subcategory":"Health Practitioner",
            "type":"Services"
        }
    ],
    "sg:phone":"+1 919 233 0075",
    "sg:postcode":"27518",
    "sg:province":"NC",
    "sg:tags":[
        "gambling",
        "addiction-information",
        "treatment"
    ],
    "wof:name":"Gecko Hospitality",
    "wof:placetype":"venue"
},
  "geometry": {"coordinates":[-78.776911,35.742134],"type":"Point"}
}