{
  "type": "Feature",
  "properties": {
    "addr:full":"290 US Hwy 158 Yanceyville NC 27379",
    "addr:housenumber":"290",
    "addr:postcode":"27379",
    "addr:street":"Us Hwy 158",
    "iso:country":"US",
    "sg:address":"290 US Hwy 158",
    "sg:city":"Yanceyville",
    "sg:classifiers":[
        {
            "category":"Shopping",
            "subcategory":"Computers & Home Electronics",
            "type":"Retail Goods"
        },
        {
            "category":"Shopping",
            "subcategory":"Music",
            "type":"Retail Goods"
        }
    ],
    "sg:phone":"+1 336 694 5505",
    "sg:postcode":"27379",
    "sg:province":"NC",
    "sg:tags":[
        "video",
        "disc",
        "tape",
        "cassette"
    ],
    "wof:name":"Tatums Video Rentals Inc",
    "wof:placetype":"venue"
},
  "geometry": {"coordinates":[-79.270968,36.388614],"type":"Point"}
}