{
  "type": "Feature",
  "properties": {
    "iso:country":"US",
    "sg:address":"13 Governors Rd SE",
    "sg:city":"Winnabow",
    "sg:classifiers":[
        {
            "category":"Autos & Motor Vehicles",
            "subcategory":"Automobile Sales",
            "type":"Retail Goods"
        }
    ],
    "sg:phone":"+1 910 253 9940",
    "sg:postcode":"28479",
    "sg:province":"NC",
    "sg:tags":[
        "car",
        "dealer"
    ],
    "wof:name":"Winnabow Auto Sales",
    "wof:placetype":"venue"
},
  "geometry": {"coordinates":[-78.080968,34.150544],"type":"Point"}
}