{
  "type": "Feature",
  "properties": {
    "iso:country":"US",
    "sg:address":"499 Griffith Rd",
    "sg:city":"Advance",
    "sg:classifiers":[
        {
            "category":"Building & Trades",
            "subcategory":"Construction",
            "type":"Services"
        }
    ],
    "sg:phone":"+1 336 998 8287",
    "sg:postcode":"27006",
    "sg:province":"NC",
    "sg:tags":[
        "contractor"
    ],
    "wof:name":"Kountry Korner Day Care",
    "wof:placetype":"venue"
},
  "geometry": {"coordinates":[-80.46597300000001,36.056971],"type":"Point"}
}