{
  "type": "Feature",
  "properties": {
    "addr:full":"502 Whitaker St Chapel Hill NC 27516",
    "addr:housenumber":"502",
    "addr:postcode":"27516",
    "addr:street":"Whitaker St",
    "iso:country":"US",
    "sg:address":"502 Whitaker St",
    "sg:city":"Chapel Hill",
    "sg:classifiers":[
        {
            "category":"Arts & Performance",
            "subcategory":"Theater",
            "type":"Entertainment"
        }
    ],
    "sg:phone":"+1   ",
    "sg:postcode":"27516",
    "sg:province":"NC",
    "sg:tags":[
        "group"
    ],
    "wof:name":"Gray Rolly & Sunfire",
    "wof:placetype":"venue"
},
  "geometry": {"coordinates":[-79.064172,35.913852],"type":"Point"}
}