{
  "type": "Feature",
  "properties": {
    "addr:full":"100 Center Ln Huntersville NC 28078",
    "addr:housenumber":"100",
    "addr:postcode":"28078",
    "addr:street":"Center Ln",
    "iso:country":"US",
    "sg:address":"100 Center Ln",
    "sg:city":"Huntersville",
    "sg:classifiers":[
        {
            "category":"Wholesale",
            "subcategory":"Sporting Goods",
            "type":"Manufacturing & Wholesale Goods"
        }
    ],
    "sg:phone":"+1 704 948 8754",
    "sg:postcode":"28078",
    "sg:province":"NC",
    "wof:name":"Integra Motor Sports",
    "wof:placetype":"venue"
},
  "geometry": {"coordinates":[-80.851433,35.397962],"type":"Point"}
}