{
  "type": "Feature",
  "properties": {
    "addr:full":"1301 Cotanche St Greenville NC 27858",
    "addr:housenumber":"1301",
    "addr:postcode":"27858",
    "addr:street":"Cotanche St",
    "iso:country":"US",
    "sg:address":"1301 Cotanche St",
    "sg:city":"Greenville",
    "sg:classifiers":[
        {
            "category":"Organizations",
            "subcategory":"Religious Organization",
            "type":"Services"
        }
    ],
    "sg:phone":"+1 252 754 2222",
    "sg:postcode":"27858",
    "sg:province":"NC",
    "sg:tags":[
        "church"
    ],
    "wof:name":"South Greenville Chr Of Christ",
    "wof:placetype":"venue"
},
  "geometry": {"coordinates":[-77.37299899999999,35.602409],"type":"Point"}
}