{
  "type": "Feature",
  "properties": {
    "addr:full":"996 N Hill Rd Fayetteville NC 28303",
    "addr:housenumber":"996",
    "addr:postcode":"28303",
    "addr:street":"N Hill Rd",
    "iso:country":"US",
    "sg:address":"996 N Hill Rd",
    "sg:city":"Fayetteville",
    "sg:classifiers":[
        {
            "category":"Professional",
            "subcategory":"Business Services",
            "type":"Services"
        }
    ],
    "sg:phone":"+1   ",
    "sg:postcode":"28303",
    "sg:province":"NC",
    "wof:name":"Digitizing 4u",
    "wof:placetype":"venue"
},
  "geometry": {"coordinates":[-78.94068799999999,35.081291],"type":"Point"}
}