{
  "type": "Feature",
  "properties": {
    "iso:country":"US",
    "sg:address":"712 Torrence Dr",
    "sg:city":"Gastonia",
    "sg:classifiers":[
        {
            "category":"Professional",
            "type":"Services"
        }
    ],
    "sg:phone":"+1   ",
    "sg:postcode":"28054",
    "sg:province":"NC",
    "wof:name":"Cds Services",
    "wof:placetype":"venue"
},
  "geometry": {"coordinates":[-81.15135100000001,35.253224],"type":"Point"}
}