{
  "type": "Feature",
  "properties": {
    "addr:full":"400 East St Pittsboro NC 27312",
    "addr:housenumber":"400",
    "addr:postcode":"27312",
    "addr:street":"East St",
    "iso:country":"US",
    "sg:address":"400 East St",
    "sg:city":"Pittsboro",
    "sg:classifiers":[
        {
            "category":"Shopping",
            "subcategory":"Department Store",
            "type":"Retail Goods"
        }
    ],
    "sg:phone":"+1 919 542 6442",
    "sg:postcode":"27312",
    "sg:province":"NC",
    "wof:name":"Sears Roebuck & Co",
    "wof:placetype":"venue"
},
  "geometry": {"coordinates":[-79.17058,35.719972],"type":"Point"}
}