{
  "type": "Feature",
  "properties": {
    "addr:full":"509 Atkinson St Laurinburg NC 28352",
    "addr:housenumber":"509",
    "addr:postcode":"28352",
    "addr:street":"Atkinson St",
    "iso:country":"US",
    "sg:address":"509 Atkinson St",
    "sg:city":"Laurinburg",
    "sg:classifiers":[
        {
            "category":"Professional",
            "subcategory":"Employment Agencies",
            "type":"Services"
        }
    ],
    "sg:phone":"+1   ",
    "sg:postcode":"28352",
    "sg:province":"NC",
    "sg:tags":[
        "help",
        "supply"
    ],
    "wof:name":"Adecco Staffing",
    "wof:placetype":"venue"
},
  "geometry": {"coordinates":[-79.46482,34.772922],"type":"Point"}
}