{
  "type": "Feature",
  "properties": {
    "addr:full":"1100 N John St Goldsboro NC 27530",
    "addr:housenumber":"1100",
    "addr:postcode":"27530",
    "addr:street":"N John St",
    "iso:country":"US",
    "sg:address":"1100 N John St",
    "sg:city":"Goldsboro",
    "sg:classifiers":[
        {
            "category":"Organizations",
            "subcategory":"Religious Organization",
            "type":"Services"
        }
    ],
    "sg:phone":"+1 919 734 6304",
    "sg:postcode":"27530",
    "sg:province":"NC",
    "sg:tags":[
        "church"
    ],
    "wof:name":"Praise Prayer Worship Ctr",
    "wof:placetype":"venue"
},
  "geometry": {"coordinates":[-77.98904400000001,35.398075],"type":"Point"}
}