{
  "type": "Feature",
  "properties": {
    "addr:full":"4545 S Halifax Rd Rocky Mount NC 27803",
    "addr:housenumber":"4545",
    "addr:postcode":"27803",
    "addr:street":"S Halifax Rd",
    "iso:country":"US",
    "sg:address":"4545 S Halifax Rd",
    "sg:city":"Rocky Mount",
    "sg:classifiers":[
        {
            "category":"Professional",
            "subcategory":"Business Services",
            "type":"Services"
        }
    ],
    "sg:phone":"+1   ",
    "sg:postcode":"27803",
    "sg:province":"NC",
    "wof:name":"Dhr Sales & Marketing Inc",
    "wof:placetype":"venue"
},
  "geometry": {"coordinates":[-77.86613199999999,35.903145],"type":"Point"}
}