{
  "type": "Feature",
  "properties": {
    "iso:country":"US",
    "sg:address":"209 Pender St E",
    "sg:city":"Wilson",
    "sg:classifiers":[
        {
            "category":"Organizations",
            "subcategory":"Religious Organization",
            "type":"Services"
        }
    ],
    "sg:phone":"+1   ",
    "sg:postcode":"27893",
    "sg:province":"NC",
    "wof:name":"Calvary Presbyterian Church",
    "wof:placetype":"venue"
},
  "geometry": {"coordinates":[-77.904442,35.723003],"type":"Point"}
}