{
  "type": "Feature",
  "properties": {
    "addr:full":"1504 Greenville Blvd SW Greenville NC 27834",
    "addr:housenumber":"1504",
    "addr:postcode":"27834",
    "addr:street":"Greenville Blvd Sw",
    "iso:country":"US",
    "sg:address":"1504 Greenville Blvd SW",
    "sg:city":"Greenville",
    "sg:classifiers":[
        {
            "category":"Personal",
            "subcategory":"Beauty Salon",
            "type":"Services"
        }
    ],
    "sg:phone":"+1 252 355 0003",
    "sg:postcode":"27834",
    "sg:province":"NC",
    "wof:name":"Nu Look",
    "wof:placetype":"venue"
},
  "geometry": {"coordinates":[-77.42312099999999,35.5756],"type":"Point"}
}