{
  "type": "Feature",
  "properties": {
    "iso:country":"US",
    "sg:address":"730 Union Rd",
    "sg:city":"Gastonia",
    "sg:classifiers":[
        {
            "category":"Wholesale",
            "subcategory":"Stationery",
            "type":"Manufacturing & Wholesale Goods"
        }
    ],
    "sg:phone":"+1 704 866 7776",
    "sg:postcode":"28054",
    "sg:province":"NC",
    "sg:tags":[
        "school",
        "supply"
    ],
    "wof:name":"Union Road Learning Station",
    "wof:placetype":"venue"
},
  "geometry": {"coordinates":[-81.17642600000001,35.253691],"type":"Point"}
}