{
  "type": "Feature",
  "properties": {
    "iso:country":"US",
    "sg:address":"106 Laurel Falls Rd",
    "sg:city":"Franklin",
    "sg:classifiers":[
        {
            "category":"Professional",
            "subcategory":"Business Services",
            "type":"Services"
        }
    ],
    "sg:phone":"+1   ",
    "sg:postcode":"28734",
    "sg:province":"NC",
    "wof:name":"Rustic Sign Co",
    "wof:placetype":"venue"
},
  "geometry": {"coordinates":[-83.28149999999999,35.192968],"type":"Point"}
}