{
  "type": "Feature",
  "properties": {
    "iso:country":"US",
    "sg:address":"2921 Jennings Rd",
    "sg:city":"Olin",
    "sg:classifiers":[
        {
            "category":"Building & Trades",
            "subcategory":"Plumbing",
            "type":"Services"
        }
    ],
    "sg:phone":"+1 704 539 5611",
    "sg:postcode":"28660",
    "sg:province":"NC",
    "sg:tags":[
        "contractor"
    ],
    "wof:name":"H Team V A C Inc",
    "wof:placetype":"venue"
},
  "geometry": {"coordinates":[-80.87548099999999,35.991716],"type":"Point"}
}