{
  "type": "Feature",
  "properties": {
    "addr:full":"513 Barnes St S Wilson NC 27893",
    "addr:housenumber":"513",
    "addr:postcode":"27893",
    "addr:street":"Barnes St S",
    "iso:country":"US",
    "sg:address":"513 Barnes St S",
    "sg:city":"Wilson",
    "sg:classifiers":[
        {
            "category":"Organizations",
            "subcategory":"Religious Organization",
            "type":"Services"
        }
    ],
    "sg:phone":"+1 252 291 2047",
    "sg:postcode":"27893",
    "sg:province":"NC",
    "sg:tags":[
        "church"
    ],
    "wof:name":"Wilson Chapel Free Will Bapt",
    "wof:placetype":"venue"
},
  "geometry": {"coordinates":[-77.906781,35.720258],"type":"Point"}
}