{
  "type": "Feature",
  "properties": {
    "iso:country":"US",
    "sg:address":"2113 Big Daddy's Rd",
    "sg:city":"Pikeville",
    "sg:classifiers":[
        {
            "category":"Building & Trades",
            "subcategory":"Electrical",
            "type":"Services"
        }
    ],
    "sg:phone":"+1 919 242 6865",
    "sg:postcode":"27863",
    "sg:province":"NC",
    "sg:tags":[
        "electrical",
        "contractor"
    ],
    "wof:name":"Stacey Electrical Contracting",
    "wof:placetype":"venue"
},
  "geometry": {"coordinates":[-77.887973,35.484354],"type":"Point"}
}