{
  "type": "Feature",
  "properties": {
    "iso:country":"US",
    "sg:address":"215 E Main St",
    "sg:city":"Hamlet",
    "sg:classifiers":[
        {
            "category":"Health Services",
            "subcategory":"Doctor",
            "type":"Services"
        }
    ],
    "sg:phone":"+1 910 582 5707",
    "sg:postcode":"28345",
    "sg:province":"NC",
    "sg:tags":[
        "dentist"
    ],
    "wof:name":"Marshall Brown DDS",
    "wof:placetype":"venue"
},
  "geometry": {"coordinates":[-79.69556300000001,34.880435],"type":"Point"}
}