{
  "type": "Feature",
  "properties": {
    "iso:country":"US",
    "sg:address":"200 N Greensboro St Carr Mill Mall",
    "sg:city":"Carrboro",
    "sg:classifiers":[
        {
            "category":"Shopping",
            "subcategory":"Hobbies, Toys, & Games",
            "type":"Retail Goods"
        }
    ],
    "sg:phone":"+1 919 932 3954",
    "sg:postcode":"27510",
    "sg:province":"NC",
    "sg:tags":[
        "toy",
        "store"
    ],
    "wof:name":"Ali Cat",
    "wof:placetype":"venue"
},
  "geometry": {"coordinates":[-79.072272,35.911602],"type":"Point"}
}