{
  "type": "Feature",
  "properties": {
    "addr:full":"5630 Old US Hwy 52 Lexington NC 27295",
    "addr:housenumber":"5630",
    "addr:postcode":"27295",
    "addr:street":"Old Us Hwy 52",
    "iso:country":"US",
    "sg:address":"5630 Old US Hwy 52",
    "sg:city":"Lexington",
    "sg:classifiers":[
        {
            "category":"Autos & Motor Vehicles",
            "subcategory":"Automobile Sales",
            "type":"Retail Goods"
        }
    ],
    "sg:phone":"+1 336 731 1399",
    "sg:postcode":"27295",
    "sg:province":"NC",
    "sg:tags":[
        "car",
        "dealer"
    ],
    "wof:name":"Lex-Car Motors",
    "wof:placetype":"venue"
},
  "geometry": {"coordinates":[-80.25732499999999,35.901724],"type":"Point"}
}