{
  "type": "Feature",
  "properties": {
    "iso:country":"US",
    "sg:address":"822 Herman Ct",
    "sg:city":"High Point",
    "sg:classifiers":[
        {
            "category":"Manufacturing",
            "subcategory":"Building Materials",
            "type":"Manufacturing & Wholesale Goods"
        }
    ],
    "sg:phone":"+1 336 434 2158",
    "sg:postcode":"27263",
    "sg:province":"NC",
    "sg:tags":[
        "plywood",
        "veneer"
    ],
    "wof:name":"Craftwood Inc",
    "wof:placetype":"venue"
},
  "geometry": {"coordinates":[-79.972601,35.931534],"type":"Point"}
}