{
  "type": "Feature",
  "properties": {
    "iso:country":"US",
    "sg:address":"106 W Main St",
    "sg:city":"Burnsville",
    "sg:classifiers":[
        {
            "category":"Government",
            "subcategory":"Office",
            "type":"Public Place"
        }
    ],
    "sg:phone":"+1 828 682 7722",
    "sg:postcode":"28714",
    "sg:province":"NC",
    "sg:tags":[
        "county",
        "program",
        "adm"
    ],
    "sg:website":"www.yanceyedc.org",
    "wof:name":"Yancey Economic Devlpmnt Comm",
    "wof:placetype":"venue"
},
  "geometry": {"coordinates":[-82.299097,35.917172],"type":"Point"}
}