{
  "type": "Feature",
  "properties": {
    "iso:country":"US",
    "sg:address":"2421 Lassiter Mill Rd",
    "sg:city":"Asheboro",
    "sg:classifiers":[
        {
            "category":"Organizations",
            "subcategory":"Religious Organization",
            "type":"Services"
        }
    ],
    "sg:phone":"+1 336 857 3360",
    "sg:postcode":"27205",
    "sg:province":"NC",
    "sg:tags":[
        "church"
    ],
    "wof:name":"Science Hill Friends Church",
    "wof:placetype":"venue"
},
  "geometry": {"coordinates":[-79.932472,35.655831],"type":"Point"}
}