{
  "type": "Feature",
  "properties": {
    "addr:full":"2015 Randolph Rd Charlotte NC 28207",
    "addr:housenumber":"2015",
    "addr:postcode":"28207",
    "addr:street":"Randolph Rd",
    "iso:country":"US",
    "sg:address":"2015 Randolph Rd",
    "sg:city":"Charlotte",
    "sg:classifiers":[
        {
            "category":"Health Services",
            "subcategory":"Doctor",
            "type":"Services"
        }
    ],
    "sg:phone":"+1 704 334 2020",
    "sg:postcode":"28207",
    "sg:province":"NC",
    "sg:tags":[
        "physician",
        "good",
        "optician",
        "medical",
        "surgeons",
        "ophthalmology",
        "optical",
        "surgeon"
    ],
    "sg:website":"http://www.meckeye.com/",
    "wof:name":"Mecklenburg Eye Associates",
    "wof:placetype":"venue"
},
  "geometry": {"coordinates":[-80.822288,35.208411],"type":"Point"}
}