{
  "type": "Feature",
  "properties": {
    "addr:full":"3705 Battleground Ave Greensboro NC 27410",
    "addr:housenumber":"3705",
    "addr:postcode":"27410",
    "addr:street":"Battleground Ave",
    "iso:country":"US",
    "sg:address":"3705 Battleground Ave",
    "sg:city":"Greensboro",
    "sg:classifiers":[
        {
            "category":"Banks & Credit Unions",
            "subcategory":"Bank",
            "type":"Services"
        }
    ],
    "sg:phone":"+1 336 282 0378",
    "sg:postcode":"27410",
    "sg:province":"NC",
    "sg:tags":[
        "national",
        "commercial"
    ],
    "wof:name":"Wachovia Bank National Assn",
    "wof:placetype":"venue"
},
  "geometry": {"coordinates":[-79.854933,36.13058],"type":"Point"}
}