{
  "type": "Feature",
  "properties": {
    "iso:country":"US",
    "sg:address":"6208 Cedar Croft Dr",
    "sg:city":"Charlotte",
    "sg:classifiers":[
        {
            "category":"Professional",
            "subcategory":"Management & Consulting",
            "type":"Services"
        }
    ],
    "sg:phone":"+1   ",
    "sg:postcode":"28226",
    "sg:province":"NC",
    "wof:name":"Downey Management Service Inc",
    "wof:placetype":"venue"
},
  "geometry": {"coordinates":[-80.781533,35.113879],"type":"Point"}
}