{
  "type": "Feature",
  "properties": {
    "iso:country":"US",
    "sg:address":"1185 Charlotte Hwy",
    "sg:city":"Fairview",
    "sg:classifiers":[
        {
            "category":"Sports & Exercise",
            "subcategory":"Gym",
            "type":"Entertainment"
        }
    ],
    "sg:phone":"+1 828 628 6005",
    "sg:postcode":"28730",
    "sg:province":"NC",
    "sg:tags":[
        "club",
        "health",
        "studio",
        "gymnasium"
    ],
    "wof:name":"Curves For Women",
    "wof:placetype":"venue"
},
  "geometry": {"coordinates":[-82.42245699999999,35.524489],"type":"Point"}
}