{
  "type": "Feature",
  "properties": {
    "addr:full":"4537 Hillsborough Rd Durham NC 27705",
    "addr:housenumber":"4537",
    "addr:postcode":"27705",
    "addr:street":"Hillsborough Rd",
    "iso:country":"US",
    "sg:address":"4537 Hillsborough Rd",
    "sg:city":"Durham",
    "sg:classifiers":[
        {
            "category":"Wholesale",
            "subcategory":"Plants",
            "type":"Manufacturing & Wholesale Goods"
        }
    ],
    "sg:phone":"+1 919 383 1450",
    "sg:postcode":"27705",
    "sg:province":"NC",
    "sg:tags":[
        "supply"
    ],
    "wof:name":"Spell Wholesale Florist",
    "wof:placetype":"venue"
},
  "geometry": {"coordinates":[-78.97630700000001,36.03314],"type":"Point"}
}