{
  "type": "Feature",
  "properties": {
    "addr:full":"2709 Blue Ridge Rd Raleigh NC 27607",
    "addr:housenumber":"2709",
    "addr:postcode":"27607",
    "addr:street":"Blue Ridge Rd",
    "iso:country":"US",
    "sg:address":"2709 Blue Ridge Rd",
    "sg:city":"Raleigh",
    "sg:classifiers":[
        {
            "category":"Social Services",
            "type":"Services"
        }
    ],
    "sg:phone":"+1 919 349 2146",
    "sg:postcode":"27607",
    "sg:province":"NC",
    "sg:tags":[
        "professional",
        "counselor",
        "marriage",
        "family"
    ],
    "wof:name":"Cynthia Dowdy PHD",
    "wof:placetype":"venue"
},
  "geometry": {"coordinates":[-78.70498499999999,35.818825],"type":"Point"}
}