{
  "type": "Feature",
  "properties": {
    "addr:full":"3920 Cotswold Ave Greensboro NC 27410",
    "addr:housenumber":"3920",
    "addr:postcode":"27410",
    "addr:street":"Cotswold Ave",
    "iso:country":"US",
    "sg:address":"3920 Cotswold Ave",
    "sg:city":"Greensboro",
    "sg:classifiers":[
        {
            "category":"Restaurant",
            "type":"Food & Drink"
        }
    ],
    "sg:phone":"+1 336 288 6782",
    "sg:postcode":"27410",
    "sg:province":"NC",
    "sg:website":"www.libbyhill.com",
    "wof:name":"Libby Hill Seafood Restaurant",
    "wof:placetype":"venue"
},
  "geometry": {"coordinates":[-79.85955199999999,36.136113],"type":"Point"}
}