{
  "type": "Feature",
  "properties": {
    "iso:country":"US",
    "sg:address":"300 Treybrooke Cir",
    "sg:city":"Greenville",
    "sg:classifiers":[
        {
            "category":"Restaurant",
            "type":"Food & Drink"
        }
    ],
    "sg:phone":"+1 252 757 1716",
    "sg:postcode":"27834",
    "sg:province":"NC",
    "wof:name":"Courtside Cafe",
    "wof:placetype":"venue"
},
  "geometry": {"coordinates":[-77.403724,35.614891],"type":"Point"}
}