{
  "type": "Feature",
  "properties": {
    "iso:country":"US",
    "sg:address":"1451 14th Ave NE",
    "sg:city":"Hickory",
    "sg:classifiers":[
        {
            "category":"Manufacturing",
            "subcategory":"Textiles",
            "type":"Manufacturing & Wholesale Goods"
        }
    ],
    "sg:phone":"+1 828 322 6841",
    "sg:postcode":"28601",
    "sg:province":"NC",
    "sg:tags":[
        "hosiery"
    ],
    "wof:name":"Madaris Hosiery Mill",
    "wof:placetype":"venue"
},
  "geometry": {"coordinates":[-81.30861,35.747243],"type":"Point"}
}