{
  "type": "Feature",
  "properties": {
    "iso:country":"US",
    "sg:address":"3779 Barber Mill Rd",
    "sg:city":"Clayton",
    "sg:classifiers":[
        {
            "category":"Building & Trades",
            "subcategory":"Construction",
            "type":"Services"
        }
    ],
    "sg:phone":"+1 919 553 3652",
    "sg:postcode":"27520",
    "sg:province":"NC",
    "sg:tags":[
        "house"
    ],
    "wof:name":"Lonnie W Jones Builders",
    "wof:placetype":"venue"
},
  "geometry": {"coordinates":[-78.48295400000001,35.619862],"type":"Point"}
}