{
  "type": "Feature",
  "properties": {
    "addr:full":"207 Medcon Ct Cary NC 27511",
    "addr:housenumber":"207",
    "addr:postcode":"27511",
    "addr:street":"Medcon Ct",
    "iso:country":"US",
    "sg:address":"207 Medcon Ct",
    "sg:city":"Cary",
    "sg:classifiers":[
        {
            "category":"Professional",
            "subcategory":"Business Services",
            "type":"Services"
        }
    ],
    "sg:phone":"+1   ",
    "sg:postcode":"27511",
    "sg:province":"NC",
    "wof:name":"Concoxtions",
    "wof:placetype":"venue"
},
  "geometry": {"coordinates":[-78.77865199999999,35.773183],"type":"Point"}
}