{
  "type": "Feature",
  "properties": {
    "addr:full":"138 S Steele St Sanford NC 27330",
    "addr:housenumber":"138",
    "addr:postcode":"27330",
    "addr:street":"S Steele St",
    "iso:country":"US",
    "sg:address":"138 S Steele St",
    "sg:city":"Sanford",
    "sg:classifiers":[
        {
            "category":"Banks & Credit Unions",
            "subcategory":"Investment Brokerage",
            "type":"Services"
        }
    ],
    "sg:phone":"+1 919 774 4011",
    "sg:postcode":"27330",
    "sg:province":"NC",
    "sg:tags":[
        "advisory",
        "consulting",
        "management"
    ],
    "wof:name":"American Express",
    "wof:placetype":"venue"
},
  "geometry": {"coordinates":[-79.178926,35.480201],"type":"Point"}
}