{
  "type": "Feature",
  "properties": {
    "iso:country":"US",
    "sg:address":"206 Henderson Dr",
    "sg:city":"Jacksonville",
    "sg:classifiers":[
        {
            "category":"Shopping",
            "subcategory":"Clothing, Apparel, & Fashions",
            "type":"Retail Goods"
        }
    ],
    "sg:phone":"+1 910 455 3100",
    "sg:postcode":"28540",
    "sg:province":"NC",
    "sg:tags":[
        "garment"
    ],
    "wof:name":"Vilma Apparel & Accessories",
    "wof:placetype":"venue"
},
  "geometry": {"coordinates":[-77.42018,34.763499],"type":"Point"}
}