{
  "type": "Feature",
  "properties": {
    "addr:full":"129 Dove Meadows Dr Archdale NC 27263",
    "addr:housenumber":"129",
    "addr:postcode":"27263",
    "addr:street":"Dove Meadows Dr",
    "iso:country":"US",
    "sg:address":"129 Dove Meadows Dr",
    "sg:city":"Archdale",
    "sg:classifiers":[
        {
            "category":"Building & Trades",
            "subcategory":"Electrical",
            "type":"Services"
        }
    ],
    "sg:phone":"+1 336 434 0131",
    "sg:postcode":"27263",
    "sg:province":"NC",
    "sg:tags":[
        "electric",
        "contractor"
    ],
    "wof:name":"G S Electric",
    "wof:placetype":"venue"
},
  "geometry": {"coordinates":[-79.94384700000001,35.905461],"type":"Point"}
}