{
  "type": "Feature",
  "properties": {
    "iso:country":"US",
    "sg:address":"148 Burchette Chapel Rd",
    "sg:city":"Manson",
    "sg:classifiers":[
        {
            "category":"Organizations",
            "subcategory":"Religious Organization",
            "type":"Services"
        }
    ],
    "sg:phone":"+1 252 456 2545",
    "sg:postcode":"27553",
    "sg:province":"NC",
    "sg:tags":[
        "church"
    ],
    "wof:name":"Burchette Chapel United Church",
    "wof:placetype":"venue"
},
  "geometry": {"coordinates":[-78.28487199999999,36.482705],"type":"Point"}
}