{
  "type": "Feature",
  "properties": {
    "addr:full":"1225 Crescent Green Cary NC 27518",
    "addr:housenumber":"1225",
    "addr:postcode":"27518",
    "addr:street":"Crescent Green",
    "iso:country":"US",
    "sg:address":"1225 Crescent Green",
    "sg:city":"Cary",
    "sg:classifiers":[
        {
            "category":"Banks & Credit Unions",
            "subcategory":"Financial Services",
            "type":"Services"
        }
    ],
    "sg:phone":"+1 919 816 1190",
    "sg:postcode":"27518",
    "sg:province":"NC",
    "sg:tags":[
        "broker",
        "mortgage"
    ],
    "wof:name":"Pulte Mortgage Corp",
    "wof:placetype":"venue"
},
  "geometry": {"coordinates":[-78.783703,35.732055],"type":"Point"}
}