{
  "type": "Feature",
  "properties": {
    "iso:country":"US",
    "sg:address":"3206 Hickory Blvd",
    "sg:city":"Hudson",
    "sg:classifiers":[
        {
            "category":"Professional",
            "subcategory":"Art Services",
            "type":"Services"
        }
    ],
    "sg:phone":"+1   ",
    "sg:postcode":"28638",
    "sg:province":"NC",
    "sg:tags":[
        "photo",
        "photography",
        "commercial",
        "studio",
        "portrait"
    ],
    "wof:name":"Lail Photography",
    "wof:placetype":"venue"
},
  "geometry": {"coordinates":[-81.467337,35.841106],"type":"Point"}
}