{
  "type": "Feature",
  "properties": {
    "addr:full":"2235 Cessna Dr Burlington NC 27215",
    "addr:housenumber":"2235",
    "addr:postcode":"27215",
    "addr:street":"Cessna Dr",
    "iso:country":"US",
    "sg:address":"2235 Cessna Dr",
    "sg:city":"Burlington",
    "sg:classifiers":[
        {
            "category":"Wholesale",
            "subcategory":"Scrap",
            "type":"Manufacturing & Wholesale Goods"
        }
    ],
    "sg:phone":"+1 336 222 6979",
    "sg:postcode":"27215",
    "sg:province":"NC",
    "sg:tags":[
        "recycling",
        "center"
    ],
    "wof:name":"Duffy Box & Recycling Inc",
    "wof:placetype":"venue"
},
  "geometry": {"coordinates":[-79.46267899999999,36.047678],"type":"Point"}
}