{
  "type": "Feature",
  "properties": {
    "addr:full":"909 Witherbee Ln Raleigh NC 27603",
    "addr:housenumber":"909",
    "addr:postcode":"27603",
    "addr:street":"Witherbee Ln",
    "iso:country":"US",
    "sg:address":"909 Witherbee Ln",
    "sg:city":"Raleigh",
    "sg:classifiers":[
        {
            "category":"Building & Trades",
            "subcategory":"Construction",
            "type":"Services"
        }
    ],
    "sg:phone":"+1 919 779 4030",
    "sg:postcode":"27603",
    "sg:province":"NC",
    "sg:tags":[
        "roofing",
        "contractor"
    ],
    "wof:name":"Area Roofing & Home Imprvmnt",
    "wof:placetype":"venue"
},
  "geometry": {"coordinates":[-78.635048,35.620424],"type":"Point"}
}