{
  "type": "Feature",
  "properties": {
    "iso:country":"US",
    "sg:address":"12305 Canolder St",
    "sg:city":"Raleigh",
    "sg:classifiers":[
        {
            "category":"Communications",
            "type":"Services"
        }
    ],
    "sg:phone":"+1 919 488 4471",
    "sg:postcode":"27614",
    "sg:province":"NC",
    "wof:name":"Mc Keeman Communications Group",
    "wof:placetype":"venue"
},
  "geometry": {"coordinates":[-78.564751,35.946256],"type":"Point"}
}