{
  "type": "Feature",
  "properties": {
    "addr:full":"106 Allen Pl Jacksonville NC 28546",
    "addr:housenumber":"106",
    "addr:postcode":"28546",
    "addr:street":"Allen Pl",
    "iso:country":"US",
    "sg:address":"106 Allen Pl",
    "sg:city":"Jacksonville",
    "sg:classifiers":[
        {
            "category":"Professional",
            "subcategory":"Business Services",
            "type":"Services"
        }
    ],
    "sg:phone":"+1   ",
    "sg:postcode":"28546",
    "sg:province":"NC",
    "wof:name":"Brinkley Enterprises Inc",
    "wof:placetype":"venue"
},
  "geometry": {"coordinates":[-77.37869499999999,34.753201],"type":"Point"}
}