{
  "type": "Feature",
  "properties": {
    "addr:full":"90 Palmer Rd Hayesville NC 28904",
    "addr:housenumber":"90",
    "addr:postcode":"28904",
    "addr:street":"Palmer Rd",
    "iso:country":"US",
    "sg:address":"90 Palmer Rd",
    "sg:city":"Hayesville",
    "sg:classifiers":[
        {
            "category":"Insurance",
            "subcategory":"Insurance Agent",
            "type":"Services"
        }
    ],
    "sg:phone":"+1 828 389 8063",
    "sg:postcode":"28904",
    "sg:province":"NC",
    "wof:name":"Clay County Farm Bureau",
    "wof:placetype":"venue"
},
  "geometry": {"coordinates":[-83.818539,35.038691],"type":"Point"}
}