{
  "type": "Feature",
  "properties": {
    "addr:full":"280 W Main Ave Gastonia NC 28052",
    "addr:housenumber":"280",
    "addr:postcode":"28052",
    "addr:street":"W Main Ave",
    "iso:country":"US",
    "sg:address":"280 W Main Ave",
    "sg:city":"Gastonia",
    "sg:classifiers":[
        {
            "category":"Home & Garden",
            "subcategory":"Furniture",
            "type":"Retail Goods"
        }
    ],
    "sg:phone":"+1 704 867 5313",
    "sg:postcode":"28052",
    "sg:province":"NC",
    "wof:name":"Luxury Interiors & Furniture",
    "wof:placetype":"venue"
},
  "geometry": {"coordinates":[-81.184471,35.26386],"type":"Point"}
}