{
  "type": "Feature",
  "properties": {
    "addr:full":"1050 W Noble St Selma NC 27576",
    "addr:housenumber":"1050",
    "addr:postcode":"27576",
    "addr:street":"W Noble St",
    "iso:country":"US",
    "sg:address":"1050 W Noble St",
    "sg:city":"Selma",
    "sg:classifiers":[
        {
            "category":"Local Transit",
            "type":"Transportation"
        }
    ],
    "sg:phone":"+1 919 202 5030",
    "sg:postcode":"27576",
    "sg:province":"NC",
    "sg:tags":[
        "line"
    ],
    "wof:name":"Jcats",
    "wof:placetype":"venue"
},
  "geometry": {"coordinates":[-78.296297,35.540105],"type":"Point"}
}