{
  "type": "Feature",
  "properties": {
    "addr:full":"3605 Middle Sound Loop Rd Wilmington NC 28411",
    "addr:housenumber":"3605",
    "addr:postcode":"28411",
    "addr:street":"Middle Sound Loop Rd",
    "iso:country":"US",
    "sg:address":"3605 Middle Sound Loop Rd",
    "sg:city":"Wilmington",
    "sg:classifiers":[
        {
            "category":"Building & Trades",
            "subcategory":"Construction",
            "type":"Services"
        }
    ],
    "sg:phone":"+1 910 686 8282",
    "sg:postcode":"28411",
    "sg:province":"NC",
    "sg:tags":[
        "concrete",
        "contractor"
    ],
    "wof:name":"Casarez Concrete Inc",
    "wof:placetype":"venue"
},
  "geometry": {"coordinates":[-77.80670000000001,34.265437],"type":"Point"}
}