{
  "type": "Feature",
  "properties": {
    "iso:country":"US",
    "sg:address":"48 College St",
    "sg:city":"Asheville",
    "sg:classifiers":[
        {
            "category":"Restaurant",
            "type":"Food & Drink"
        }
    ],
    "sg:menulink":"http://www.allmenus.com/nc/asheville/268254-table/menu/",
    "sg:phone":"+1 828 254 8980",
    "sg:postcode":"28801",
    "sg:province":"NC",
    "wof:name":"Table",
    "wof:placetype":"venue"
},
  "geometry": {"coordinates":[-82.55310900000001,35.595274],"type":"Point"}
}