{
  "type": "Feature",
  "properties": {
    "addr:full":"6360 State Rd 150 Maiden NC 28650",
    "addr:housenumber":"6360;150",
    "addr:postcode":"28650",
    "addr:street":"State Rd",
    "iso:country":"US",
    "sg:address":"6360 State Rd 150",
    "sg:city":"Maiden",
    "sg:classifiers":[
        {
            "category":"Wholesale",
            "subcategory":"Medical Equipment & Supplies",
            "type":"Manufacturing & Wholesale Goods"
        }
    ],
    "sg:phone":"+1 704 483 9150",
    "sg:postcode":"28650",
    "sg:province":"NC",
    "sg:tags":[
        "physician",
        "surgeon"
    ],
    "wof:name":"Paul Taylor Inc",
    "wof:placetype":"venue"
},
  "geometry": {"coordinates":[-81.095699,35.545868],"type":"Point"}
}