{
  "type": "Feature",
  "properties": {
    "iso:country":"US",
    "sg:address":"1100 Bodenheimer Dr",
    "sg:city":"Boone",
    "sg:classifiers":[
        {
            "category":"Travel",
            "subcategory":"Travel Agent",
            "type":"Entertainment"
        }
    ],
    "sg:phone":"+1 828 265 2263",
    "sg:postcode":"28607",
    "sg:province":"NC",
    "sg:tags":[
        "tours",
        "promoter"
    ],
    "wof:name":"Experiences International Inc",
    "wof:placetype":"venue"
},
  "geometry": {"coordinates":[-81.69416,36.210471],"type":"Point"}
}