{
  "type": "Feature",
  "properties": {
    "addr:full":"2032 White Rd Wilmington NC 28411",
    "addr:housenumber":"2032",
    "addr:postcode":"28411",
    "addr:street":"White Rd",
    "iso:country":"US",
    "sg:address":"2032 White Rd",
    "sg:city":"Wilmington",
    "sg:classifiers":[
        {
            "category":"Real Estate",
            "subcategory":"Real Estate Agent",
            "type":"Services"
        }
    ],
    "sg:phone":"+1 910 794 9186",
    "sg:postcode":"28411",
    "sg:province":"NC",
    "wof:name":"Ocean Realty",
    "wof:placetype":"venue"
},
  "geometry": {"coordinates":[-77.84764300000001,34.274011],"type":"Point"}
}