{
  "type": "Feature",
  "properties": {
    "addr:full":"6505 Kilberry Ln Charlotte NC 28277",
    "addr:housenumber":"6505",
    "addr:postcode":"28277",
    "addr:street":"Kilberry Ln",
    "iso:country":"US",
    "sg:address":"6505 Kilberry Ln",
    "sg:city":"Charlotte",
    "sg:classifiers":[
        {
            "category":"Professional",
            "type":"Services"
        }
    ],
    "sg:phone":"+1 704 847 9494",
    "sg:postcode":"28277",
    "sg:province":"NC",
    "sg:tags":[
        "establishment"
    ],
    "wof:name":"Time Out Inc",
    "wof:placetype":"venue"
},
  "geometry": {"coordinates":[-80.81029100000001,35.075725],"type":"Point"}
}