{
  "type": "Feature",
  "properties": {
    "addr:full":"112 W Church St Williamston NC 27892",
    "addr:housenumber":"112",
    "addr:postcode":"27892",
    "addr:street":"W Church St",
    "iso:country":"US",
    "sg:address":"112 W Church St",
    "sg:city":"Williamston",
    "sg:classifiers":[
        {
            "category":"Organizations",
            "subcategory":"Religious Organization",
            "type":"Services"
        }
    ],
    "sg:phone":"+1 252 792 2244",
    "sg:postcode":"27892",
    "sg:province":"NC",
    "sg:tags":[
        "church"
    ],
    "wof:name":"Church Of The Advent",
    "wof:placetype":"venue"
},
  "geometry": {"coordinates":[-77.056048,35.856162],"type":"Point"}
}