{
  "type": "Feature",
  "properties": {
    "addr:full":"820 Planters St Rocky Mount NC 27801",
    "addr:housenumber":"820",
    "addr:postcode":"27801",
    "addr:street":"Planters St",
    "iso:country":"US",
    "sg:address":"820 Planters St",
    "sg:city":"Rocky Mount",
    "sg:classifiers":[
        {
            "category":"Personal",
            "subcategory":"Beauty Salon",
            "type":"Services"
        }
    ],
    "sg:phone":"+1 252 977 7781",
    "sg:postcode":"27801",
    "sg:province":"NC",
    "wof:name":"Vision Of Beauty",
    "wof:placetype":"venue"
},
  "geometry": {"coordinates":[-77.786563,35.92867],"type":"Point"}
}