{
  "type": "Feature",
  "properties": {
    "iso:country":"US",
    "sg:address":"15 Laura Ln",
    "sg:city":"Thomasville",
    "sg:classifiers":[
        {
            "category":"Restaurant",
            "type":"Food & Drink"
        }
    ],
    "sg:phone":"+1 336 472 3274",
    "sg:postcode":"27360",
    "sg:province":"NC",
    "sg:tags":[
        "eating"
    ],
    "wof:name":"Big Game Safari Steakhouse",
    "wof:placetype":"venue"
},
  "geometry": {"coordinates":[-80.06717399999999,35.862385],"type":"Point"}
}