{
  "type": "Feature",
  "properties": {
    "addr:full":"11121 Timber Hill Ct Charlotte NC 28226",
    "addr:housenumber":"11121",
    "addr:postcode":"28226",
    "addr:street":"Timber Hill Ct",
    "iso:country":"US",
    "sg:address":"11121 Timber Hill Ct",
    "sg:city":"Charlotte",
    "sg:classifiers":[
        {
            "category":"Building & Trades",
            "subcategory":"Landscaping Services",
            "type":"Services"
        }
    ],
    "sg:phone":"+1 704 543 1898",
    "sg:postcode":"28226",
    "sg:province":"NC",
    "wof:name":"Timber Hill Service",
    "wof:placetype":"venue"
},
  "geometry": {"coordinates":[-80.857795,35.075753],"type":"Point"}
}