{
  "type": "Feature",
  "properties": {
    "iso:country":"US",
    "sg:address":"330 S Evans St",
    "sg:city":"Greenville",
    "sg:classifiers":[
        {
            "category":"Food & Beverages",
            "subcategory":"Liquor & Beverages",
            "type":"Retail Goods"
        }
    ],
    "sg:phone":"+1 252 758 6900",
    "sg:postcode":"27858",
    "sg:province":"NC",
    "sg:tags":[
        "wine"
    ],
    "wof:name":"4th Street Wine Shop",
    "wof:placetype":"venue"
},
  "geometry": {"coordinates":[-77.37277,35.612527],"type":"Point"}
}