{
  "type": "Feature",
  "properties": {
    "iso:country":"US",
    "sg:address":"406 N Main St",
    "sg:city":"Creedmoor",
    "sg:classifiers":[
        {
            "category":"Restaurant",
            "type":"Food & Drink"
        }
    ],
    "sg:phone":"+1 919 528 7777",
    "sg:postcode":"27522",
    "sg:province":"NC",
    "wof:name":"Jon's Main Street Bar & Grill",
    "wof:placetype":"venue"
},
  "geometry": {"coordinates":[-78.68319700000001,36.1255],"type":"Point"}
}