{
  "type": "Feature",
  "properties": {
    "addr:full":"17201 Old Lumberton Rd Laurinburg NC 28352",
    "addr:housenumber":"17201",
    "addr:postcode":"28352",
    "addr:street":"Old Lumberton Rd",
    "iso:country":"US",
    "sg:address":"17201 Old Lumberton Rd",
    "sg:city":"Laurinburg",
    "sg:classifiers":[
        {
            "category":"Social Services",
            "subcategory":"Child Care",
            "type":"Services"
        }
    ],
    "sg:phone":"+1 910 276 3933",
    "sg:postcode":"28352",
    "sg:province":"NC",
    "wof:name":"Little Butterfly Day Care",
    "wof:placetype":"venue"
},
  "geometry": {"coordinates":[-79.440113,34.775386],"type":"Point"}
}