{
  "type": "Feature",
  "properties": {
    "addr:full":"827 Wiley Brown Rd Franklin NC 28734",
    "addr:housenumber":"827",
    "addr:postcode":"nc 28734",
    "addr:street":"Wiley Brown Rd",
    "iso:country":"US",
    "sg:address":"827 Wiley Brown Rd",
    "sg:city":"Franklin",
    "sg:classifiers":[
        {
            "category":"Social Services",
            "type":"Services"
        }
    ],
    "sg:phone":"+1 828 349 0345",
    "sg:postcode":"28734",
    "sg:province":"NC",
    "sg:tags":[
        "counselor",
        "marriage",
        "family"
    ],
    "sg:website":"www.tchome.org",
    "wof:name":"Family Restoration Program",
    "wof:placetype":"venue"
},
  "geometry": {"coordinates":[-83.372623,35.156716],"type":"Point"}
}