{
  "type": "Feature",
  "properties": {
    "iso:country":"US",
    "sg:address":"383 Suitt Rd",
    "sg:city":"Franklinton",
    "sg:classifiers":[
        {
            "category":"Building & Trades",
            "subcategory":"Electrical",
            "type":"Services"
        }
    ],
    "sg:phone":"+1 919 494 5457",
    "sg:postcode":"27525",
    "sg:province":"NC",
    "sg:tags":[
        "electrical",
        "contractor"
    ],
    "wof:name":"Caleb Hill Electrical Service",
    "wof:placetype":"venue"
},
  "geometry": {"coordinates":[-78.533872,36.094612],"type":"Point"}
}