{
  "type": "Feature",
  "properties": {
    "addr:full":"301 S College St Charlotte NC 28202",
    "addr:housenumber":"301",
    "addr:postcode":"28202",
    "addr:street":"S College St",
    "iso:country":"US",
    "sg:address":"301 S College St",
    "sg:city":"Charlotte",
    "sg:classifiers":[
        {
            "category":"Real Estate",
            "subcategory":"Developer",
            "type":"Services"
        }
    ],
    "sg:phone":"+1 704 374 6490",
    "sg:postcode":"28202",
    "sg:province":"NC",
    "sg:tags":[
        "development",
        "residential",
        "property"
    ],
    "wof:name":"Wachovia",
    "wof:placetype":"venue"
},
  "geometry": {"coordinates":[-80.845254,35.223974],"type":"Point"}
}