{
  "type": "Feature",
  "properties": {
    "iso:country":"US",
    "sg:address":"54 Hill St",
    "sg:city":"Spruce Pine",
    "sg:classifiers":[
        {
            "category":"Health Services",
            "subcategory":"Optometrist",
            "type":"Services"
        }
    ],
    "sg:phone":"+1 828 765 2020",
    "sg:postcode":"28777",
    "sg:province":"NC",
    "wof:name":"Appalachian Eye Assoc",
    "wof:placetype":"venue"
},
  "geometry": {"coordinates":[-82.065551,35.910367],"type":"Point"}
}