{
  "type": "Feature",
  "properties": {
    "iso:country":"US",
    "sg:address":"121 Peoria Ln",
    "sg:city":"Kings Mountain",
    "sg:classifiers":[
        {
            "category":"Food & Beverages",
            "subcategory":"Groceries & Convenience Stores",
            "type":"Retail Goods"
        }
    ],
    "sg:phone":"+1 704 739 0790",
    "sg:postcode":"28086",
    "sg:province":"NC",
    "wof:name":"A JS Quick Stop",
    "wof:placetype":"venue"
},
  "geometry": {"coordinates":[-81.454657,35.241641],"type":"Point"}
}