{
  "type": "Feature",
  "properties": {
    "iso:country":"US",
    "sg:address":"708 Southeast Blvd",
    "sg:city":"Clinton",
    "sg:classifiers":[
        {
            "category":"Organizations",
            "subcategory":"Community Association",
            "type":"Services"
        }
    ],
    "sg:phone":"+1 910 592 6096",
    "sg:postcode":"28328",
    "sg:province":"NC",
    "sg:tags":[
        "club"
    ],
    "wof:name":"Club Bahia",
    "wof:placetype":"venue"
},
  "geometry": {"coordinates":[-78.308286,34.991643],"type":"Point"}
}