{
  "type": "Feature",
  "properties": {
    "iso:country":"US",
    "sg:address":"513 Pershing Rd",
    "sg:city":"Raleigh",
    "sg:classifiers":[
        {
            "category":"Manufacturing",
            "subcategory":"Building Materials",
            "type":"Manufacturing & Wholesale Goods"
        }
    ],
    "sg:phone":"+1 919 832 4554",
    "sg:postcode":"27608",
    "sg:province":"NC",
    "wof:name":"Great Escape Millwork",
    "wof:placetype":"venue"
},
  "geometry": {"coordinates":[-78.631169,35.804231],"type":"Point"}
}