{
  "type": "Feature",
  "properties": {
    "iso:country":"US",
    "sg:address":"220 18th Street Cir SE",
    "sg:city":"Hickory",
    "sg:classifiers":[
        {
            "category":"Health Services",
            "subcategory":"Doctor",
            "type":"Services"
        }
    ],
    "sg:phone":"+1   ",
    "sg:postcode":"28602",
    "sg:province":"NC",
    "sg:tags":[
        "medical"
    ],
    "wof:name":"David E Tart MD",
    "wof:placetype":"venue"
},
  "geometry": {"coordinates":[-81.306498,35.730289],"type":"Point"}
}