{
  "type": "Feature",
  "properties": {
    "addr:full":"1331 N Brightleaf Blvd Smithfield NC 27577",
    "addr:housenumber":"1331",
    "addr:postcode":"27577",
    "addr:street":"N Brightleaf Blvd",
    "iso:country":"US",
    "sg:address":"1331 N Brightleaf Blvd",
    "sg:city":"Smithfield",
    "sg:classifiers":[
        {
            "category":"Autos & Motor Vehicles",
            "subcategory":"Fuel & Gas Station",
            "type":"Retail Goods"
        }
    ],
    "sg:phone":"+1 919 934 6055",
    "sg:postcode":"27577",
    "sg:province":"NC",
    "sg:tags":[
        "convenience",
        "station",
        "gasoline",
        "store"
    ],
    "wof:name":"Etna",
    "wof:placetype":"venue"
},
  "geometry": {"coordinates":[-78.305159,35.522103],"type":"Point"}
}