{
  "type": "Feature",
  "properties": {
    "addr:full":"1506 Wayne Memorial Dr Goldsboro NC 27534",
    "addr:housenumber":"1506",
    "addr:postcode":"27534",
    "addr:street":"Wayne Memorial Dr",
    "iso:country":"US",
    "sg:address":"1506 Wayne Memorial Dr",
    "sg:city":"Goldsboro",
    "sg:classifiers":[
        {
            "category":"Insurance",
            "subcategory":"Insurance Agent",
            "type":"Services"
        }
    ],
    "sg:phone":"+1 919 580 0243",
    "sg:postcode":"27534",
    "sg:province":"NC",
    "wof:name":"Monumental Life Insurance Co",
    "wof:placetype":"venue"
},
  "geometry": {"coordinates":[-77.97384099999999,35.393237],"type":"Point"}
}