{
  "type": "Feature",
  "properties": {
    "addr:full":"626 Greenville Hwy Hendersonville NC 28792",
    "addr:housenumber":"626",
    "addr:postcode":"28792",
    "addr:street":"Greenville Hwy",
    "iso:country":"US",
    "sg:address":"626 Greenville Hwy",
    "sg:city":"Hendersonville",
    "sg:classifiers":[
        {
            "category":"Real Estate",
            "subcategory":"Real Estate Agent",
            "type":"Services"
        }
    ],
    "sg:phone":"+1 828 692 9394",
    "sg:postcode":"28792",
    "sg:province":"NC",
    "wof:name":"Landmark Properties",
    "wof:placetype":"venue"
},
  "geometry": {"coordinates":[-82.458292,35.306055],"type":"Point"}
}