{
  "type": "Feature",
  "properties": {
    "addr:full":"1300 Yadkinville Rd Mocksville NC 27028",
    "addr:housenumber":"1300",
    "addr:postcode":"27028",
    "addr:street":"Yadkinville Rd",
    "iso:country":"US",
    "sg:address":"1300 Yadkinville Rd",
    "sg:city":"Mocksville",
    "sg:classifiers":[
        {
            "category":"Personal",
            "subcategory":"Beauty Salon",
            "type":"Services"
        }
    ],
    "sg:phone":"+1   ",
    "sg:postcode":"27028",
    "sg:province":"NC",
    "sg:tags":[
        "shop"
    ],
    "wof:name":"Phase II Hair Design & Beyond",
    "wof:placetype":"venue"
},
  "geometry": {"coordinates":[-80.583338,35.916807],"type":"Point"}
}