{
  "type": "Feature",
  "properties": {
    "iso:country":"US",
    "sg:address":"3713 White Chapel Way",
    "sg:city":"Raleigh",
    "sg:classifiers":[
        {
            "category":"Professional",
            "subcategory":"Business Services",
            "type":"Services"
        }
    ],
    "sg:phone":"+1   ",
    "sg:postcode":"27615",
    "sg:province":"NC",
    "wof:name":"Monique S Interiors Pia",
    "wof:placetype":"venue"
},
  "geometry": {"coordinates":[-78.63151000000001,35.908343],"type":"Point"}
}