{
  "type": "Feature",
  "properties": {
    "addr:full":"5086 Ritchie Rd Lincolnton NC 28092",
    "addr:housenumber":"5086",
    "addr:postcode":"28092",
    "addr:street":"Ritchie Rd",
    "iso:country":"US",
    "sg:address":"5086 Ritchie Rd",
    "sg:city":"Lincolnton",
    "sg:classifiers":[
        {
            "category":"Building & Trades",
            "subcategory":"Plumbing",
            "type":"Services"
        }
    ],
    "sg:phone":"+1 704 732 4525",
    "sg:postcode":"28092",
    "sg:province":"NC",
    "sg:tags":[
        "plumbing",
        "contractor"
    ],
    "wof:name":"Plumbing Shoppe",
    "wof:placetype":"venue"
},
  "geometry": {"coordinates":[-81.271647,35.55572],"type":"Point"}
}