{
  "type": "Feature",
  "properties": {
    "iso:country":"US",
    "sg:address":"10502 Park Rd",
    "sg:city":"Charlotte",
    "sg:classifiers":[
        {
            "category":"Health Services",
            "subcategory":"Doctor",
            "type":"Services"
        }
    ],
    "sg:phone":"+1 704 341 1122",
    "sg:postcode":"28210",
    "sg:province":"NC",
    "sg:tags":[
        "physician",
        "surgeon",
        "medical"
    ],
    "wof:name":"Vein Clinic of Charlotte",
    "wof:placetype":"venue"
},
  "geometry": {"coordinates":[-80.870671,35.089379],"type":"Point"}
}