{
  "type": "Feature",
  "properties": {
    "iso:country":"US",
    "sg:address":"709 McLeod Dr",
    "sg:city":"Sanford",
    "sg:classifiers":[
        {
            "category":"Shopping",
            "subcategory":"Computers & Home Electronics",
            "type":"Retail Goods"
        }
    ],
    "sg:phone":"+1 919 774 1950",
    "sg:postcode":"27330",
    "sg:province":"NC",
    "sg:tags":[
        "high",
        "fidelity",
        "stereophonic"
    ],
    "wof:name":"Westpoint Products",
    "wof:placetype":"venue"
},
  "geometry": {"coordinates":[-79.207076,35.476854],"type":"Point"}
}