{
  "type": "Feature",
  "properties": {
    "addr:full":"12478 Old Bailey Hwy Wilson NC 27896",
    "addr:housenumber":"12478",
    "addr:postcode":"27896",
    "addr:street":"Old Bailey Hwy",
    "iso:country":"US",
    "sg:address":"12478 Old Bailey Hwy",
    "sg:city":"Wilson",
    "sg:classifiers":[
        {
            "category":"Building & Trades",
            "subcategory":"Construction",
            "type":"Services"
        }
    ],
    "sg:phone":"+1 252 243 2587",
    "sg:postcode":"27896",
    "sg:province":"NC",
    "sg:tags":[
        "excavation",
        "contractor"
    ],
    "wof:name":"Jack B Smith Backhoe Serv",
    "wof:placetype":"venue"
},
  "geometry": {"coordinates":[-78.001273,35.811128],"type":"Point"}
}