{
  "type": "Feature",
  "properties": {
    "iso:country":"US",
    "sg:address":"2302 US Hwy 301 S",
    "sg:city":"Dunn",
    "sg:classifiers":[
        {
            "category":"Manufacturing",
            "subcategory":"Food",
            "type":"Manufacturing & Wholesale Goods"
        }
    ],
    "sg:phone":"+1 910 892 8751",
    "sg:postcode":"28334",
    "sg:province":"NC",
    "sg:tags":[
        "frozen",
        "canned",
        "specialty",
        "mfg"
    ],
    "sg:website":"www.alphinbros.com",
    "wof:name":"Alphin Brothers Inc",
    "wof:placetype":"venue"
},
  "geometry": {"coordinates":[-78.62893200000001,35.277084],"type":"Point"}
}