{
  "type": "Feature",
  "properties": {
    "iso:country":"US",
    "sg:address":"2233 Old New Bern Rd",
    "sg:city":"Chocowinity",
    "sg:classifiers":[
        {
            "category":"Professional",
            "type":"Services"
        }
    ],
    "sg:phone":"+1 252 946 5431",
    "sg:postcode":"27817",
    "sg:province":"NC",
    "wof:name":"Louise Harris",
    "wof:placetype":"venue"
},
  "geometry": {"coordinates":[-77.118871,35.459704],"type":"Point"}
}