{
  "type": "Feature",
  "properties": {
    "iso:country":"US",
    "sg:address":"180 E Main St",
    "sg:city":"Forest City",
    "sg:classifiers":[
        {
            "category":"Autos & Motor Vehicles",
            "subcategory":"Auto Supplies",
            "type":"Retail Goods"
        }
    ],
    "sg:phone":"+1 828 245 4297",
    "sg:postcode":"28043",
    "sg:province":"NC",
    "sg:tags":[
        "automotive",
        "appliance",
        "l",
        "related",
        "item",
        "parts"
    ],
    "wof:name":"Marchman J F",
    "wof:placetype":"venue"
},
  "geometry": {"coordinates":[-81.86266999999999,35.333097],"type":"Point"}
}