{
  "type": "Feature",
  "properties": {
    "addr:full":"1009 Andiron Ln Raleigh NC 27614",
    "addr:housenumber":"1009",
    "addr:postcode":"27614",
    "addr:street":"Andiron Ln",
    "iso:country":"US",
    "sg:address":"1009 Andiron Ln",
    "sg:city":"Raleigh",
    "sg:classifiers":[
        {
            "category":"Food & Beverages",
            "subcategory":"Specialty",
            "type":"Retail Goods"
        }
    ],
    "sg:phone":"+1 919 870 0090",
    "sg:postcode":"27614",
    "sg:province":"NC",
    "wof:name":"Healthy Living Concepts",
    "wof:placetype":"venue"
},
  "geometry": {"coordinates":[-78.644091,35.94218],"type":"Point"}
}