{
  "type": "Feature",
  "properties": {
    "addr:full":"452 Butler Bridge Rd Fletcher NC 28732",
    "addr:housenumber":"452",
    "addr:postcode":"28732",
    "addr:street":"Butler Bridge Rd",
    "iso:country":"US",
    "sg:address":"452 Butler Bridge Rd",
    "sg:city":"Fletcher",
    "sg:classifiers":[
        {
            "category":"Wholesale",
            "subcategory":"Durable Goods & Equipment",
            "type":"Manufacturing & Wholesale Goods"
        }
    ],
    "sg:phone":"+1 828 651 8606",
    "sg:postcode":"28732",
    "sg:province":"NC",
    "sg:tags":[
        "exporter"
    ],
    "wof:name":"Big Frog Construction",
    "wof:placetype":"venue"
},
  "geometry": {"coordinates":[-82.52010300000001,35.406946],"type":"Point"}
}