{
  "type": "Feature",
  "properties": {
    "iso:country":"US",
    "sg:address":"3849 Murchison Rd",
    "sg:city":"Fayetteville",
    "sg:classifiers":[
        {
            "category":"Home & Garden",
            "subcategory":"Furniture",
            "type":"Retail Goods"
        }
    ],
    "sg:phone":"+1 910 488 9393",
    "sg:postcode":"28311",
    "sg:province":"NC",
    "sg:tags":[
        "mattress"
    ],
    "wof:name":"A & A Adjustable Beds",
    "wof:placetype":"venue"
},
  "geometry": {"coordinates":[-78.918418,35.100113],"type":"Point"}
}