{
  "type": "Feature",
  "properties": {
    "addr:full":"300 Craven St Beaufort NC 28516",
    "addr:housenumber":"300",
    "addr:postcode":"28516",
    "addr:street":"Craven St",
    "iso:country":"US",
    "sg:address":"300 Craven St",
    "sg:city":"Beaufort",
    "sg:classifiers":[
        {
            "category":"Professional",
            "subcategory":"Management & Consulting",
            "type":"Services"
        }
    ],
    "sg:phone":"+1 252 728 3709",
    "sg:postcode":"28516",
    "sg:province":"NC",
    "sg:tags":[
        "fuel"
    ],
    "wof:name":"ABL Management",
    "wof:placetype":"venue"
},
  "geometry": {"coordinates":[-76.661728,34.720064],"type":"Point"}
}