{
  "type": "Feature",
  "properties": {
    "iso:country":"US",
    "sg:address":"1104 Maplewood Ave",
    "sg:city":"High Point",
    "sg:classifiers":[
        {
            "category":"Building & Trades",
            "subcategory":"Construction",
            "type":"Services"
        }
    ],
    "sg:phone":"+1 336 887 3050",
    "sg:postcode":"27265",
    "sg:province":"NC",
    "sg:tags":[
        "floor",
        "laying",
        "contractor"
    ],
    "wof:name":"Larry Shepherd Flooring",
    "wof:placetype":"venue"
},
  "geometry": {"coordinates":[-80.016429,36.031721],"type":"Point"}
}