{
  "type": "Feature",
  "properties": {
    "iso:country":"US",
    "sg:address":"1507 Skyway Dr",
    "sg:city":"Monroe",
    "sg:classifiers":[
        {
            "category":"Building & Trades",
            "subcategory":"Construction",
            "type":"Services"
        }
    ],
    "sg:phone":"+1 704 291 7468",
    "sg:postcode":"28110",
    "sg:province":"NC",
    "sg:tags":[
        "industrial",
        "commercial",
        "contractor"
    ],
    "wof:name":"Consolidated Construction Svcs",
    "wof:placetype":"venue"
},
  "geometry": {"coordinates":[-80.548965,34.997133],"type":"Point"}
}