{
  "type": "Feature",
  "properties": {
    "addr:full":"144 Terry Dr Siler City NC 27360",
    "addr:housenumber":"144",
    "addr:postcode":"27360",
    "addr:street":"Terry Dr",
    "iso:country":"US",
    "sg:address":"144 Terry Dr",
    "sg:city":"Siler City",
    "sg:classifiers":[
        {
            "category":"Travel",
            "subcategory":"Hotels & Motels",
            "type":"Entertainment"
        }
    ],
    "sg:phone":"+1 919 742 5176",
    "sg:postcode":"27360",
    "sg:province":"NC",
    "sg:tags":[
        "breakfast",
        "accommodation",
        "bed"
    ],
    "wof:name":"Inn At Celebrity Dairy",
    "wof:placetype":"venue"
},
  "geometry": {"coordinates":[-80.054266,35.898282],"type":"Point"}
}