{
  "type": "Feature",
  "properties": {
    "addr:full":"102 Friendway Rd Greensboro NC 27409",
    "addr:housenumber":"102",
    "addr:postcode":"27409",
    "addr:street":"Friendway Rd",
    "iso:country":"US",
    "sg:address":"102 Friendway Rd",
    "sg:city":"Greensboro",
    "sg:classifiers":[
        {
            "category":"Retail",
            "subcategory":"Auto Repair",
            "type":"Services"
        }
    ],
    "sg:phone":"+1 336 299 5341",
    "sg:postcode":"27409",
    "sg:province":"NC",
    "sg:tags":[
        "repairing",
        "automobile",
        "general"
    ],
    "wof:name":"Bondurant's Garage",
    "wof:placetype":"venue"
},
  "geometry": {"coordinates":[-79.902638,36.077741],"type":"Point"}
}