{
  "type": "Feature",
  "properties": {
    "addr:full":"4201 Congress St Charlotte NC 28209",
    "addr:housenumber":"4201",
    "addr:postcode":"28209",
    "addr:street":"Congress St",
    "iso:country":"US",
    "sg:address":"4201 Congress St",
    "sg:city":"Charlotte",
    "sg:classifiers":[
        {
            "category":"Professional",
            "type":"Services"
        }
    ],
    "sg:phone":"+1 704 554 8150",
    "sg:postcode":"28209",
    "sg:province":"NC",
    "sg:tags":[
        "establishment"
    ],
    "wof:name":"Bridgestone Partners LLC",
    "wof:placetype":"venue"
},
  "geometry": {"coordinates":[-80.83749299999999,35.153738],"type":"Point"}
}