{
  "type": "Feature",
  "properties": {
    "addr:full":"7101 Creedmoor Rd Raleigh NC 27613",
    "addr:housenumber":"7101",
    "addr:postcode":"27613",
    "addr:street":"Creedmoor Rd",
    "iso:country":"US",
    "sg:address":"7101 Creedmoor Rd",
    "sg:city":"Raleigh",
    "sg:phone":"+1 919 845 6688",
    "sg:postcode":"27613",
    "sg:province":"NC",
    "sg:website":"http://www.sffcriminallaw.com",
    "wof:name":"Sandman Finn & Fitzhugh Attorneys At Law",
    "wof:placetype":"venue"
},
  "geometry": {"coordinates":[-78.679199,35.88295],"type":"Point"}
}