{
  "type": "Feature",
  "properties": {
    "addr:full":"1624 Jordan Dr Winston Salem NC 27105",
    "addr:housenumber":"1624",
    "addr:postcode":"27105",
    "addr:street":"Jordan Dr",
    "iso:country":"US",
    "sg:address":"1624 Jordan Dr",
    "sg:city":"Winston Salem",
    "sg:classifiers":[
        {
            "category":"Real Estate",
            "subcategory":"Real Estate Agent",
            "type":"Services"
        }
    ],
    "sg:phone":"+1 336 376 0250",
    "sg:postcode":"27105",
    "sg:province":"NC",
    "sg:website":"www.jordanproperties.com",
    "wof:name":"Jordan Properties",
    "wof:placetype":"venue"
},
  "geometry": {"coordinates":[-80.21061400000001,36.164939],"type":"Point"}
}