{
  "type": "Feature",
  "properties": {
    "iso:country":"US",
    "sg:address":"2114 Carlisle Way",
    "sg:city":"High Point",
    "sg:classifiers":[
        {
            "category":"Professional",
            "type":"Services"
        }
    ],
    "sg:phone":"+1 336 883 7830",
    "sg:postcode":"27265",
    "sg:province":"NC",
    "wof:name":"Triad Family Svc",
    "wof:placetype":"venue"
},
  "geometry": {"coordinates":[-79.987515,35.987345],"type":"Point"}
}