{
  "type": "Feature",
  "properties": {
    "addr:full":"1225 Prabhupada Rd Sandy Ridge NC 27046",
    "addr:housenumber":"1225",
    "addr:postcode":"27046",
    "addr:street":"Prabhupada Rd",
    "iso:country":"US",
    "sg:address":"1225 Prabhupada Rd",
    "sg:city":"Sandy Ridge",
    "sg:classifiers":[
        {
            "category":"Wholesale",
            "subcategory":"Farm Supplies",
            "type":"Manufacturing & Wholesale Goods"
        }
    ],
    "sg:phone":"+1 336 593 3277",
    "sg:postcode":"27046",
    "sg:province":"NC",
    "wof:name":"In God We Trust",
    "wof:placetype":"venue"
},
  "geometry": {"coordinates":[-80.142511,36.453152],"type":"Point"}
}