{
  "type": "Feature",
  "properties": {
    "iso:country":"US",
    "sg:address":"4802 Acreland Dr",
    "sg:city":"Claremont",
    "sg:classifiers":[
        {
            "category":"Building & Trades",
            "subcategory":"Cleaning & Sanitation",
            "type":"Services"
        }
    ],
    "sg:phone":"+1 828 459 9111",
    "sg:postcode":"28610",
    "sg:province":"NC",
    "sg:tags":[
        "janitor"
    ],
    "wof:name":"A & C Cleaning Svc Inc",
    "wof:placetype":"venue"
},
  "geometry": {"coordinates":[-81.13796000000001,35.76959],"type":"Point"}
}