{
  "type": "Feature",
  "properties": {
    "addr:full":"3560 Rockfish Rd Raeford NC 28376",
    "addr:postcode":"3560;28376",
    "addr:street":"Rockfish Rd",
    "iso:country":"US",
    "sg:address":"3560 Rockfish Rd",
    "sg:city":"Raeford",
    "sg:classifiers":[
        {
            "category":"Building & Trades",
            "subcategory":"Plumbing",
            "type":"Services"
        }
    ],
    "sg:phone":"+1 910 904 5544",
    "sg:postcode":"28376",
    "sg:province":"NC",
    "sg:tags":[
        "plumbing",
        "contractor"
    ],
    "wof:name":"Raymes Plumbing",
    "wof:placetype":"venue"
},
  "geometry": {"coordinates":[-79.137862,34.991742],"type":"Point"}
}