{
  "type": "Feature",
  "properties": {
    "iso:country":"US",
    "sg:address":"265 Charlotte St",
    "sg:city":"Asheville",
    "sg:classifiers":[
        {
            "category":"Real Estate",
            "subcategory":"Real Estate Agent",
            "type":"Services"
        }
    ],
    "sg:phone":"+1 828 258 2348",
    "sg:postcode":"28801",
    "sg:province":"NC",
    "wof:name":"W C Johnson Realty",
    "wof:placetype":"venue"
},
  "geometry": {"coordinates":[-82.546029,35.608526],"type":"Point"}
}