{
  "type": "Feature",
  "properties": {
    "addr:full":"2620 Hydrangea Pl Wilmington NC 28403",
    "addr:housenumber":"2620",
    "addr:postcode":"28403",
    "addr:street":"Hydrangea Pl",
    "iso:country":"US",
    "sg:address":"2620 Hydrangea Pl",
    "sg:city":"Wilmington",
    "sg:classifiers":[
        {
            "category":"Professional",
            "subcategory":"Business Services",
            "type":"Services"
        }
    ],
    "sg:phone":"+1 910 620 9419",
    "sg:postcode":"28403",
    "sg:province":"NC",
    "wof:name":"Onsite Mobile Document",
    "wof:placetype":"venue"
},
  "geometry": {"coordinates":[-77.911295,34.220338],"type":"Point"}
}