{
  "type": "Feature",
  "properties": {
    "addr:full":"426 E Arlington Blvd Greenville NC 27858",
    "addr:housenumber":"426",
    "addr:postcode":"27858",
    "addr:street":"E Arlington Blvd",
    "iso:country":"US",
    "sg:address":"426 E Arlington Blvd",
    "sg:city":"Greenville",
    "sg:classifiers":[
        {
            "category":"Personal",
            "subcategory":"Beauty Salon",
            "type":"Services"
        }
    ],
    "sg:phone":"+1 252 756 3050",
    "sg:postcode":"27858",
    "sg:province":"NC",
    "sg:tags":[
        "shop"
    ],
    "wof:name":"Mitchells Hair Styling Inc",
    "wof:placetype":"venue"
},
  "geometry": {"coordinates":[-77.370301,35.585345],"type":"Point"}
}