{
  "type": "Feature",
  "properties": {
    "iso:country":"US",
    "sg:address":"10840 Rio Springs Dr",
    "sg:city":"Raleigh",
    "sg:classifiers":[
        {
            "category":"Professional",
            "type":"Services"
        }
    ],
    "sg:phone":"+1 919 676 8282",
    "sg:postcode":"27614",
    "sg:province":"NC",
    "wof:name":"Minimed James Stroup",
    "wof:placetype":"venue"
},
  "geometry": {"coordinates":[-78.59253099999999,35.909978],"type":"Point"}
}