{
  "type": "Feature",
  "properties": {
    "addr:full":"90 McCollum Dr Franklin NC 28734",
    "addr:housenumber":"90",
    "addr:postcode":"nc 28734",
    "addr:street":"Mccollum Dr",
    "iso:country":"US",
    "sg:address":"90 McCollum Dr",
    "sg:city":"Franklin",
    "sg:classifiers":[
        {
            "category":"Organizations",
            "subcategory":"Religious Organization",
            "type":"Services"
        }
    ],
    "sg:phone":"+1 828 524 9921",
    "sg:postcode":"28734",
    "sg:province":"NC",
    "sg:tags":[
        "church"
    ],
    "wof:name":"Church Of Christ",
    "wof:placetype":"venue"
},
  "geometry": {"coordinates":[-83.379932,35.176929],"type":"Point"}
}