{
  "type": "Feature",
  "properties": {
    "addr:full":"1112 S Pollock St Selma NC 27576",
    "addr:housenumber":"1112",
    "addr:postcode":"27576",
    "addr:street":"S Pollock St",
    "iso:country":"US",
    "sg:address":"1112 S Pollock St",
    "sg:city":"Selma",
    "sg:classifiers":[
        {
            "category":"Shopping",
            "subcategory":"Jewelry",
            "type":"Retail Goods"
        }
    ],
    "sg:phone":"+1 919 965 3344",
    "sg:postcode":"27576",
    "sg:province":"NC",
    "wof:name":"Gold Mine Jewelry",
    "wof:placetype":"venue"
},
  "geometry": {"coordinates":[-78.294065,35.527636],"type":"Point"}
}