{
  "type": "Feature",
  "properties": {
    "addr:full":"832 Ridgeway Ave Durham NC 27701",
    "addr:housenumber":"832",
    "addr:postcode":"27701",
    "addr:street":"Ridgeway Ave",
    "iso:country":"US",
    "sg:address":"832 Ridgeway Ave",
    "sg:city":"Durham",
    "sg:classifiers":[
        {
            "category":"Food & Beverages",
            "subcategory":"Groceries & Convenience Stores",
            "type":"Retail Goods"
        }
    ],
    "sg:phone":"+1 919 688 9182",
    "sg:postcode":"27701",
    "sg:province":"NC",
    "sg:tags":[
        "grocer",
        "alcoholic"
    ],
    "wof:name":"McDougald Terrace Super Market",
    "wof:placetype":"venue"
},
  "geometry": {"coordinates":[-78.890456,35.97717],"type":"Point"}
}