{
  "type": "Feature",
  "properties": {
    "iso:country":"US",
    "sg:address":"5330 Wilkinson Blvd",
    "sg:city":"Charlotte",
    "sg:classifiers":[
        {
            "category":"Building & Trades",
            "subcategory":"Construction",
            "type":"Services"
        }
    ],
    "sg:phone":"+1 704 391 0060",
    "sg:postcode":"28208",
    "sg:province":"NC",
    "sg:tags":[
        "stucco",
        "contractor"
    ],
    "wof:name":"Carolina Design Team Inc",
    "wof:placetype":"venue"
},
  "geometry": {"coordinates":[-80.92849,35.233188],"type":"Point"}
}