{
  "type": "Feature",
  "properties": {
    "addr:full":"1836 Hunters Forest Dr Winston Salem NC 27103",
    "addr:housenumber":"1836",
    "addr:postcode":"27103",
    "addr:street":"Hunters Forest Dr",
    "iso:country":"US",
    "sg:address":"1836 Hunters Forest Dr",
    "sg:city":"Winston Salem",
    "sg:classifiers":[
        {
            "category":"Professional",
            "subcategory":"Employment Agencies",
            "type":"Services"
        }
    ],
    "sg:phone":"+1   ",
    "sg:postcode":"27103",
    "sg:province":"NC",
    "wof:name":"Assoc of Operating Room Nurses",
    "wof:placetype":"venue"
},
  "geometry": {"coordinates":[-80.33307499999999,36.041524],"type":"Point"}
}