{
  "type": "Feature",
  "properties": {
    "addr:full":"118 Wisteria Dr Chapel Hill NC 27514",
    "addr:housenumber":"118",
    "addr:postcode":"27514",
    "addr:street":"Wisteria Dr",
    "iso:country":"US",
    "sg:address":"118 Wisteria Dr",
    "sg:city":"Chapel Hill",
    "sg:classifiers":[
        {
            "category":"Arena",
            "subcategory":"Sports Club",
            "type":"Entertainment"
        }
    ],
    "sg:phone":"+1   ",
    "sg:postcode":"27514",
    "sg:province":"NC",
    "wof:name":"Durham Strikers Club Inc",
    "wof:placetype":"venue"
},
  "geometry": {"coordinates":[-79.022042,35.977038],"type":"Point"}
}