{
  "type": "Feature",
  "properties": {
    "iso:country":"US",
    "sg:address":"468 Cedar Ln",
    "sg:city":"Mebane",
    "sg:classifiers":[
        {
            "category":"Restaurant",
            "type":"Food & Drink"
        }
    ],
    "sg:phone":"+1 919 563 2164",
    "sg:postcode":"27302",
    "sg:province":"NC",
    "sg:tags":[
        "eating"
    ],
    "wof:name":"Daniel Bryant",
    "wof:placetype":"venue"
},
  "geometry": {"coordinates":[-79.264082,36.08558],"type":"Point"}
}