{
  "type": "Feature",
  "properties": {
    "iso:country":"US",
    "sg:address":"107 Windel Dr",
    "sg:city":"Raleigh",
    "sg:classifiers":[
        {
            "category":"Health Services",
            "subcategory":"Doctor",
            "type":"Services"
        }
    ],
    "sg:phone":"+1 919 235 3440",
    "sg:postcode":"27609",
    "sg:province":"NC",
    "sg:tags":[
        "physician",
        "surgeon"
    ],
    "wof:name":"Triangle Physicians Assistants",
    "wof:placetype":"venue"
},
  "geometry": {"coordinates":[-78.637181,35.852883],"type":"Point"}
}