{
  "type": "Feature",
  "properties": {
    "addr:full":"110 Heathcliff Rd Wilmington NC 28409",
    "addr:housenumber":"110",
    "addr:postcode":"28409",
    "addr:street":"Heathcliff Rd",
    "iso:country":"US",
    "sg:address":"110 Heathcliff Rd",
    "sg:city":"Wilmington",
    "sg:classifiers":[
        {
            "category":"Building & Trades",
            "subcategory":"Construction",
            "type":"Services"
        }
    ],
    "sg:phone":"+1 910 452 1636",
    "sg:postcode":"28409",
    "sg:province":"NC",
    "sg:tags":[
        "hanging",
        "contractor"
    ],
    "wof:name":"Seashore Professional Coating",
    "wof:placetype":"venue"
},
  "geometry": {"coordinates":[-77.897582,34.102225],"type":"Point"}
}