{
  "type": "Feature",
  "properties": {
    "iso:country":"US",
    "sg:address":"5500 McNeely Dr Ste 103",
    "sg:city":"Raleigh",
    "sg:classifiers":[
        {
            "category":"Health Services",
            "subcategory":"Chiropractor",
            "type":"Services"
        }
    ],
    "sg:phone":"+1 919 781 0304",
    "sg:postcode":"27612",
    "sg:province":"NC",
    "sg:tags":[
        "chiropractic"
    ],
    "wof:name":"Duraleigh Chiropractic",
    "wof:placetype":"venue"
},
  "geometry": {"coordinates":[-78.711403,35.853699],"type":"Point"}
}