{
  "type": "Feature",
  "properties": {
    "iso:country":"US",
    "sg:address":"424 9th St Exd",
    "sg:city":"Lexington",
    "sg:classifiers":[
        {
            "category":"Organizations",
            "subcategory":"Religious Organization",
            "type":"Services"
        }
    ],
    "sg:phone":"+1 336 249 4493",
    "sg:postcode":"27295",
    "sg:province":"NC",
    "sg:tags":[
        "church"
    ],
    "wof:name":"First Alliance Church",
    "wof:placetype":"venue"
},
  "geometry": {"coordinates":[-80.24462,35.836822],"type":"Point"}
}