{
  "type": "Feature",
  "properties": {
    "addr:full":"109 Roberts St Asheville NC 28801",
    "addr:housenumber":"109",
    "addr:postcode":"28801",
    "addr:street":"Roberts St",
    "iso:country":"US",
    "sg:address":"109 Roberts St",
    "sg:city":"Asheville",
    "sg:classifiers":[
        {
            "category":"Building & Trades",
            "subcategory":"Construction",
            "type":"Services"
        }
    ],
    "sg:phone":"+1 828 253 6147",
    "sg:postcode":"28801",
    "sg:province":"NC",
    "sg:tags":[
        "general",
        "contractor"
    ],
    "wof:name":"Placeways",
    "wof:placetype":"venue"
},
  "geometry": {"coordinates":[-82.56774799999999,35.588252],"type":"Point"}
}