{
  "type": "Feature",
  "properties": {
    "addr:full":"1036 S College Rd Wilmington NC 28403",
    "addr:housenumber":"1036",
    "addr:postcode":"28403",
    "addr:street":"S College Rd",
    "iso:country":"US",
    "sg:address":"1036 S College Rd",
    "sg:city":"Wilmington",
    "sg:classifiers":[
        {
            "category":"Retail",
            "subcategory":"Auto Repair",
            "type":"Services"
        }
    ],
    "sg:phone":"+1 910 790 5533",
    "sg:postcode":"28403",
    "sg:province":"NC",
    "sg:tags":[
        "automobile",
        "lubrication",
        "automotive"
    ],
    "wof:name":"Prolube Inc 2",
    "wof:placetype":"venue"
},
  "geometry": {"coordinates":[-77.885953,34.21591],"type":"Point"}
}