{
  "type": "Feature",
  "properties": {
    "iso:country":"US",
    "sg:address":"1485 US Hwy 70 W",
    "sg:city":"Valdese",
    "sg:classifiers":[
        {
            "category":"Shopping",
            "subcategory":"Hobbies, Toys, & Games",
            "type":"Retail Goods"
        }
    ],
    "sg:phone":"+1 828 874 3536",
    "sg:postcode":"28690",
    "sg:province":"NC",
    "sg:tags":[
        "model",
        "supply"
    ],
    "wof:name":"Pearson's Toy Trains",
    "wof:placetype":"venue"
},
  "geometry": {"coordinates":[-81.596358,35.748473],"type":"Point"}
}