{
  "type": "Feature",
  "properties": {
    "iso:country":"US",
    "sg:address":"5100 Hutchins St",
    "sg:city":"Winston Salem",
    "sg:classifiers":[
        {
            "category":"Building & Trades",
            "subcategory":"Landscaping Services",
            "type":"Services"
        }
    ],
    "sg:phone":"+1 336 922 4617",
    "sg:postcode":"27106",
    "sg:province":"NC",
    "sg:tags":[
        "tree"
    ],
    "wof:name":"Barrows Tree Svc",
    "wof:placetype":"venue"
},
  "geometry": {"coordinates":[-80.307086,36.168753],"type":"Point"}
}