{
  "type": "Feature",
  "properties": {
    "iso:country":"US",
    "sg:address":"258 State Hwy 801",
    "sg:city":"Advance",
    "sg:classifiers":[
        {
            "category":"Food & Beverages",
            "subcategory":"Groceries & Convenience Stores",
            "type":"Retail Goods"
        }
    ],
    "sg:phone":"+1 336 940 4103",
    "sg:postcode":"27006",
    "sg:province":"NC",
    "sg:tags":[
        "grocer"
    ],
    "sg:website":"www.lowesfoods.com",
    "wof:name":"Lowes Foods",
    "wof:placetype":"venue"
},
  "geometry": {"coordinates":[-80.436393,35.999994],"type":"Point"}
}