{
  "type": "Feature",
  "properties": {
    "addr:full":"301 W 10th St Apt 501 Charlotte NC 28202",
    "addr:housenumber":"301;501",
    "addr:postcode":"28202",
    "addr:street":"W 10Th St Apt",
    "iso:country":"US",
    "sg:address":"301 W 10th St Apt 501",
    "sg:city":"Charlotte",
    "sg:classifiers":[
        {
            "category":"Personal",
            "subcategory":"Massage",
            "type":"Services"
        }
    ],
    "sg:phone":"+1 704 347 0733",
    "sg:postcode":"28202",
    "sg:province":"NC",
    "wof:name":"Centercity Massage",
    "wof:placetype":"venue"
},
  "geometry": {"coordinates":[-80.838593,35.23357],"type":"Point"}
}