{
  "type": "Feature",
  "properties": {
    "addr:full":"801 W Grover St Shelby NC 28150",
    "addr:housenumber":"801",
    "addr:postcode":"28150",
    "addr:street":"W Grover St",
    "iso:country":"US",
    "sg:address":"801 W Grover St",
    "sg:city":"Shelby",
    "sg:classifiers":[
        {
            "category":"Government",
            "subcategory":"Office",
            "type":"Public Place"
        }
    ],
    "sg:phone":"+1 704 484 6885",
    "sg:postcode":"28150",
    "sg:province":"NC",
    "sg:tags":[
        "village"
    ],
    "wof:name":"Shelby Water Filtration Plant",
    "wof:placetype":"venue"
},
  "geometry": {"coordinates":[-81.555594,35.303625],"type":"Point"}
}