{
  "type": "Feature",
  "properties": {
    "iso:country":"US",
    "sg:address":"315 Martin Luther King Jr Dr",
    "sg:city":"Greensboro",
    "sg:classifiers":[
        {
            "category":"Building & Trades",
            "subcategory":"Construction",
            "type":"Services"
        }
    ],
    "sg:phone":"+1 336 230 2279",
    "sg:postcode":"27406",
    "sg:province":"NC",
    "sg:tags":[
        "general",
        "contractor"
    ],
    "wof:name":"Greensboro Contracting Corp",
    "wof:placetype":"venue"
},
  "geometry": {"coordinates":[-79.787565,36.06616],"type":"Point"}
}