{
  "type": "Feature",
  "properties": {
    "addr:full":"344 Main St Highlands NC 28741",
    "addr:housenumber":"344",
    "addr:postcode":"28741",
    "addr:street":"Main St",
    "iso:country":"US",
    "sg:address":"344 Main St",
    "sg:city":"Highlands",
    "sg:classifiers":[
        {
            "category":"Home & Garden",
            "subcategory":"Home Furnishings",
            "type":"Retail Goods"
        }
    ],
    "sg:phone":"+1 828 526 8280",
    "sg:postcode":"28741",
    "sg:province":"NC",
    "sg:tags":[
        "blanket"
    ],
    "wof:name":"Azure Rose Quilts & Gifts",
    "wof:placetype":"venue"
},
  "geometry": {"coordinates":[-83.19837,35.053131],"type":"Point"}
}