{
  "type": "Feature",
  "properties": {
    "addr:full":"6701 Morrison Blvd Charlotte NC 28211",
    "addr:housenumber":"6701",
    "addr:postcode":"28211",
    "addr:street":"Morrison Blvd",
    "iso:country":"US",
    "sg:address":"6701 Morrison Blvd",
    "sg:city":"Charlotte",
    "sg:classifiers":[
        {
            "category":"Banks & Credit Unions",
            "subcategory":"Bank",
            "type":"Services"
        }
    ],
    "sg:phone":"+1 704 442 7012",
    "sg:postcode":"28211",
    "sg:province":"NC",
    "wof:name":"Bank Of America",
    "wof:placetype":"venue"
},
  "geometry": {"coordinates":[-80.824118,35.150881],"type":"Point"}
}