{
  "type": "Feature",
  "properties": {
    "addr:full":"707 Westchester Dr High Point NC 27262",
    "addr:housenumber":"707",
    "addr:postcode":"27262",
    "addr:street":"Westchester Dr",
    "iso:country":"US",
    "sg:address":"707 Westchester Dr",
    "sg:city":"High Point",
    "sg:classifiers":[
        {
            "category":"Shopping",
            "subcategory":"Pharmacy",
            "type":"Retail Goods"
        }
    ],
    "sg:phone":"+1 336 882 3316",
    "sg:postcode":"27262",
    "sg:province":"NC",
    "wof:name":"Advent Pharmacy",
    "wof:placetype":"venue"
},
  "geometry": {"coordinates":[-80.032967,35.976287],"type":"Point"}
}