{
  "type": "Feature",
  "properties": {
    "addr:full":"1841 Hoots Rd Yadkinville NC 27055",
    "addr:housenumber":"1841",
    "addr:postcode":"27055",
    "addr:street":"Hoots Rd",
    "iso:country":"US",
    "sg:address":"1841 Hoots Rd",
    "sg:city":"Yadkinville",
    "sg:classifiers":[
        {
            "category":"Manufacturing",
            "subcategory":"Signs",
            "type":"Manufacturing & Wholesale Goods"
        }
    ],
    "sg:phone":"+1 336 463 5998",
    "sg:postcode":"27055",
    "sg:province":"NC",
    "sg:tags":[
        "specialty",
        "mfg"
    ],
    "wof:name":"Valley Custom Vinyl",
    "wof:placetype":"venue"
},
  "geometry": {"coordinates":[-80.68546600000001,36.111629],"type":"Point"}
}