{
  "type": "Feature",
  "properties": {
    "iso:country":"US",
    "sg:address":"8514 McAlpine Park Dr",
    "sg:city":"Charlotte",
    "sg:classifiers":[
        {
            "category":"Manufacturing",
            "subcategory":"Tools & Machinery",
            "type":"Manufacturing & Wholesale Goods"
        },
        {
            "category":"Wholesale",
            "subcategory":"Electrical",
            "type":"Manufacturing & Wholesale Goods"
        }
    ],
    "sg:phone":"+1 704 362 2445",
    "sg:postcode":"28211",
    "sg:province":"NC",
    "sg:tags":[
        "equipment",
        "electric"
    ],
    "wof:name":"Thomas & Betts Corporation",
    "wof:placetype":"venue"
},
  "geometry": {"coordinates":[-80.74995199999999,35.152486],"type":"Point"}
}