{
  "type": "Feature",
  "properties": {
    "addr:full":"801 Biggs St Laurinburg NC 28352",
    "addr:housenumber":"801",
    "addr:postcode":"28352",
    "addr:street":"Biggs St",
    "iso:country":"US",
    "sg:address":"801 Biggs St",
    "sg:city":"Laurinburg",
    "sg:classifiers":[
        {
            "category":"Organizations",
            "subcategory":"Religious Organization",
            "type":"Services"
        }
    ],
    "sg:phone":"+1 910 276 1478",
    "sg:postcode":"28352",
    "sg:province":"NC",
    "sg:tags":[
        "clergy"
    ],
    "wof:name":"Catholic Rectory",
    "wof:placetype":"venue"
},
  "geometry": {"coordinates":[-79.464648,34.767925],"type":"Point"}
}