{
  "type": "Feature",
  "properties": {
    "iso:country":"US",
    "sg:address":"902 Lakeside Ave",
    "sg:city":"Burlington",
    "sg:classifiers":[
        {
            "category":"Social Services",
            "subcategory":"Adult Care",
            "type":"Services"
        }
    ],
    "sg:phone":"+1 336 229 1132",
    "sg:postcode":"27217",
    "sg:province":"NC",
    "sg:tags":[
        "home",
        "group"
    ],
    "wof:name":"Another Chance Group Home",
    "wof:placetype":"venue"
},
  "geometry": {"coordinates":[-79.443316,36.115907],"type":"Point"}
}