{
  "type": "Feature",
  "properties": {
    "iso:country":"US",
    "sg:address":"742 Latimer St",
    "sg:city":"Hillsborough",
    "sg:classifiers":[
        {
            "category":"Building & Trades",
            "subcategory":"Cleaning & Sanitation",
            "type":"Services"
        }
    ],
    "sg:phone":"+1 919 732 9446",
    "sg:postcode":"27278",
    "sg:province":"NC",
    "sg:tags":[
        "house"
    ],
    "wof:name":"Carpenter House Cleaning",
    "wof:placetype":"venue"
},
  "geometry": {"coordinates":[-79.12218,36.077096],"type":"Point"}
}