{
  "type": "Feature",
  "properties": {
    "addr:full":"262 Drumgold Rd Littleton NC 27850",
    "addr:housenumber":"262",
    "addr:postcode":"27850",
    "addr:street":"Drumgold Rd",
    "iso:country":"US",
    "sg:address":"262 Drumgold Rd",
    "sg:city":"Littleton",
    "sg:classifiers":[
        {
            "category":"Recreation",
            "type":"Entertainment"
        }
    ],
    "sg:phone":"+1 252 586 4557",
    "sg:postcode":"27850",
    "sg:province":"NC",
    "sg:tags":[
        "club",
        "membership"
    ],
    "wof:name":"Alligator Club",
    "wof:placetype":"venue"
},
  "geometry": {"coordinates":[-77.837965,36.49673],"type":"Point"}
}