{
  "type": "Feature",
  "properties": {
    "iso:country":"US",
    "sg:address":"373 W Main St",
    "sg:city":"Franklin",
    "sg:classifiers":[
        {
            "category":"Personal",
            "subcategory":"Beauty Salon",
            "type":"Services"
        }
    ],
    "sg:phone":"+1 828 524 5525",
    "sg:postcode":"28734",
    "sg:province":"NC",
    "wof:name":"First Impressions Salon",
    "wof:placetype":"venue"
},
  "geometry": {"coordinates":[-83.38642299999999,35.180417],"type":"Point"}
}