{
  "type": "Feature",
  "properties": {
    "iso:country":"US",
    "sg:address":"600 E 4th St",
    "sg:city":"Charlotte",
    "sg:classifiers":[
        {
            "category":"Government",
            "subcategory":"Office",
            "type":"Public Place"
        }
    ],
    "sg:phone":"+1 704 344 8686",
    "sg:postcode":"28202",
    "sg:province":"NC",
    "sg:tags":[
        "government-state"
    ],
    "sg:website":"http://www.charlottecdc.com",
    "wof:name":"Emergency Management",
    "wof:placetype":"venue"
},
  "geometry": {"coordinates":[-80.839172,35.22208],"type":"Point"}
}