{
  "type": "Feature",
  "properties": {
    "iso:country":"US",
    "sg:address":"1405 Auman Rd",
    "sg:city":"Raleigh",
    "sg:classifiers":[
        {
            "category":"Retail",
            "subcategory":"Animal Services",
            "type":"Services"
        }
    ],
    "sg:phone":"+1 919 779 5315",
    "sg:postcode":"27603",
    "sg:province":"NC",
    "sg:tags":[
        "merchandise"
    ],
    "wof:name":"Personal Pet",
    "wof:placetype":"venue"
},
  "geometry": {"coordinates":[-78.661934,35.690647],"type":"Point"}
}