{
  "type": "Feature",
  "properties": {
    "addr:full":"7413 Rollingdale Ct Raleigh NC 27615",
    "addr:housenumber":"7413",
    "addr:postcode":"27615",
    "addr:street":"Rollingdale Ct",
    "iso:country":"US",
    "sg:address":"7413 Rollingdale Ct",
    "sg:city":"Raleigh",
    "sg:classifiers":[
        {
            "category":"Professional",
            "subcategory":"Management & Consulting",
            "type":"Services"
        }
    ],
    "sg:phone":"+1 919 846 9429",
    "sg:postcode":"27615",
    "sg:province":"NC",
    "sg:tags":[
        "marketing",
        "program"
    ],
    "wof:name":"Carolina Canners",
    "wof:placetype":"venue"
},
  "geometry": {"coordinates":[-78.66381699999999,35.881492],"type":"Point"}
}