{
  "type": "Feature",
  "properties": {
    "addr:full":"1023 S Hawthorne Rd Winston Salem NC 27103",
    "addr:housenumber":"1023",
    "addr:postcode":"27103",
    "addr:street":"S Hawthorne Rd",
    "iso:country":"US",
    "sg:address":"1023 S Hawthorne Rd",
    "sg:city":"Winston Salem",
    "sg:classifiers":[
        {
            "category":"Professional",
            "subcategory":"Business Services",
            "type":"Services"
        }
    ],
    "sg:phone":"+1   ",
    "sg:postcode":"27103",
    "sg:province":"NC",
    "wof:name":"D S L Global Event Marketing",
    "wof:placetype":"venue"
},
  "geometry": {"coordinates":[-80.276201,36.079669],"type":"Point"}
}