{
  "type": "Feature",
  "properties": {
    "addr:full":"6659 Wilkinson Blvd Belmont NC 28012",
    "addr:housenumber":"6659",
    "addr:postcode":"28012",
    "addr:street":"Wilkinson Blvd",
    "iso:country":"US",
    "sg:address":"6659 Wilkinson Blvd",
    "sg:city":"Belmont",
    "sg:classifiers":[
        {
            "category":"Professional",
            "subcategory":"Accounting & Tax Preparation",
            "type":"Services"
        }
    ],
    "sg:phone":"+1 704 825 3146",
    "sg:postcode":"28012",
    "sg:province":"NC",
    "sg:tags":[
        "return",
        "filing"
    ],
    "wof:name":"Flong Income Tax & Bookkeeping",
    "wof:placetype":"venue"
},
  "geometry": {"coordinates":[-81.03571700000001,35.252497],"type":"Point"}
}