{
  "type": "Feature",
  "properties": {
    "iso:country":"US",
    "sg:address":"615 Oakridge Farm Hwy",
    "sg:city":"Mooresville",
    "sg:classifiers":[
        {
            "category":"Retail",
            "subcategory":"Car Wash",
            "type":"Services"
        }
    ],
    "sg:phone":"+1   ",
    "sg:postcode":"28115",
    "sg:province":"NC",
    "sg:tags":[
        "carwash"
    ],
    "wof:name":"Street Trendz",
    "wof:placetype":"venue"
},
  "geometry": {"coordinates":[-80.808939,35.603821],"type":"Point"}
}