{
  "type": "Feature",
  "properties": {
    "iso:country":"US",
    "sg:address":"1914 Mary Ann Dr",
    "sg:city":"Charlotte",
    "sg:classifiers":[
        {
            "category":"Professional",
            "type":"Services"
        }
    ],
    "sg:phone":"+1 704 399 5434",
    "sg:postcode":"28214",
    "sg:province":"NC",
    "wof:name":"Queen White",
    "wof:placetype":"venue"
},
  "geometry": {"coordinates":[-80.93361299999999,35.254248],"type":"Point"}
}