{
  "type": "Feature",
  "properties": {
    "addr:full":"374 Blume Rd Mooresville NC 28117",
    "addr:housenumber":"374",
    "addr:postcode":"28117",
    "addr:street":"Blume Rd",
    "iso:country":"US",
    "sg:address":"374 Blume Rd",
    "sg:city":"Mooresville",
    "sg:classifiers":[
        {
            "category":"Professional",
            "subcategory":"Management & Consulting",
            "type":"Services"
        }
    ],
    "sg:phone":"+1   ",
    "sg:postcode":"28117",
    "sg:province":"NC",
    "wof:name":"Natural Senses Inc",
    "wof:placetype":"venue"
},
  "geometry": {"coordinates":[-80.911343,35.581514],"type":"Point"}
}