{
  "type": "Feature",
  "properties": {
    "iso:country":"US",
    "sg:address":"1515 Mockingbird Ln",
    "sg:city":"Charlotte",
    "sg:classifiers":[
        {
            "category":"Professional",
            "subcategory":"Employment Agencies",
            "type":"Services"
        }
    ],
    "sg:phone":"+1   ",
    "sg:postcode":"28209",
    "sg:province":"NC",
    "wof:name":"Mann Staffing",
    "wof:placetype":"venue"
},
  "geometry": {"coordinates":[-80.847692,35.16678],"type":"Point"}
}