{
  "type": "Feature",
  "properties": {
    "addr:full":"105 Hilliard Dr Plymouth NC 27962",
    "addr:housenumber":"105",
    "addr:postcode":"27962",
    "addr:street":"Hilliard Dr",
    "iso:country":"US",
    "sg:address":"105 Hilliard Dr",
    "sg:city":"Plymouth",
    "sg:classifiers":[
        {
            "category":"Real Estate",
            "subcategory":"Surveying",
            "type":"Services"
        }
    ],
    "sg:phone":"+1   ",
    "sg:postcode":"27962",
    "sg:province":"NC",
    "wof:name":"Timothy J Esolen",
    "wof:placetype":"venue"
},
  "geometry": {"coordinates":[-76.736317,35.853845],"type":"Point"}
}