{
  "type": "Feature",
  "properties": {
    "addr:full":"213 N 7th St Smithfield NC 27577",
    "addr:housenumber":"213",
    "addr:postcode":"27577",
    "addr:street":"N 7Th St",
    "iso:country":"US",
    "sg:address":"213 N 7th St",
    "sg:city":"Smithfield",
    "sg:classifiers":[
        {
            "category":"Organizations",
            "subcategory":"Community Association",
            "type":"Services"
        }
    ],
    "sg:phone":"+1 919 989 7177",
    "sg:postcode":"27577",
    "sg:province":"NC",
    "sg:tags":[
        "military"
    ],
    "wof:name":"Disabled America Veterans",
    "wof:placetype":"venue"
},
  "geometry": {"coordinates":[-78.339896,35.511507],"type":"Point"}
}