{
  "type": "Feature",
  "properties": {
    "iso:country":"US",
    "sg:address":"1203 Buckhorn Ct",
    "sg:city":"Wilmington",
    "sg:classifiers":[
        {
            "category":"Professional",
            "subcategory":"Business Services",
            "type":"Services"
        }
    ],
    "sg:phone":"+1   ",
    "sg:postcode":"28411",
    "sg:province":"NC",
    "wof:name":"Shawn Breedlove",
    "wof:placetype":"venue"
},
  "geometry": {"coordinates":[-77.83175199999999,34.292525],"type":"Point"}
}