{
  "type": "Feature",
  "properties": {
    "addr:full":"107 Budleigh St Manteo NC 27954",
    "addr:housenumber":"107",
    "addr:postcode":"27954",
    "addr:street":"Budleigh St",
    "iso:country":"US",
    "sg:address":"107 Budleigh St",
    "sg:city":"Manteo",
    "sg:classifiers":[
        {
            "category":"Home & Garden",
            "subcategory":"Home Furnishings",
            "type":"Retail Goods"
        }
    ],
    "sg:phone":"+1 252 475 1594",
    "sg:postcode":"27954",
    "sg:province":"NC",
    "sg:tags":[
        "housewares"
    ],
    "wof:name":"Something Special",
    "wof:placetype":"venue"
},
  "geometry": {"coordinates":[-75.670491,35.909858],"type":"Point"}
}