{
  "type": "Feature",
  "properties": {
    "addr:full":"3546 Dewing Dr Raleigh NC 27616",
    "addr:housenumber":"3546",
    "addr:postcode":"27616",
    "addr:street":"Dewing Dr",
    "iso:country":"US",
    "sg:address":"3546 Dewing Dr",
    "sg:city":"Raleigh",
    "sg:classifiers":[
        {
            "category":"Building & Trades",
            "subcategory":"Cleaning & Sanitation",
            "type":"Services"
        }
    ],
    "sg:phone":"+1 919 217 4677",
    "sg:postcode":"27616",
    "sg:province":"NC",
    "sg:tags":[
        "maintenance"
    ],
    "wof:name":"Miracle Air Duct",
    "wof:placetype":"venue"
},
  "geometry": {"coordinates":[-78.51403000000001,35.875623],"type":"Point"}
}