{
  "type": "Feature",
  "properties": {
    "addr:full":"6105 US Hwy 13 Farmville NC 27828",
    "addr:housenumber":"6105",
    "addr:postcode":"27828",
    "addr:street":"Us Hwy 13",
    "iso:country":"US",
    "sg:address":"6105 US Hwy 13",
    "sg:city":"Farmville",
    "sg:classifiers":[
        {
            "category":"Autos & Motor Vehicles",
            "subcategory":"Automobile Sales",
            "type":"Retail Goods"
        }
    ],
    "sg:phone":"+1 252 756 2501",
    "sg:postcode":"27828",
    "sg:province":"NC",
    "sg:tags":[
        "wholesale"
    ],
    "wof:name":"TV Sales Center",
    "wof:placetype":"venue"
},
  "geometry": {"coordinates":[-77.523021,35.542505],"type":"Point"}
}