{
  "type": "Feature",
  "properties": {
    "addr:full":"919 Rauhut St Burlington NC 27217",
    "addr:housenumber":"919",
    "addr:postcode":"27217",
    "addr:street":"Rauhut St",
    "iso:country":"US",
    "sg:address":"919 Rauhut St",
    "sg:city":"Burlington",
    "sg:classifiers":[
        {
            "category":"Personal",
            "subcategory":"Barber",
            "type":"Services"
        }
    ],
    "sg:phone":"+1   ",
    "sg:postcode":"27217",
    "sg:province":"NC",
    "sg:tags":[
        "shop"
    ],
    "wof:name":"Palace Barber Shop",
    "wof:placetype":"venue"
},
  "geometry": {"coordinates":[-79.434005,36.107825],"type":"Point"}
}