{
  "type": "Feature",
  "properties": {
    "iso:country":"US",
    "sg:address":"500 E Chatham St",
    "sg:city":"Newport",
    "sg:classifiers":[
        {
            "category":"Education",
            "subcategory":"School",
            "type":"Public Place"
        }
    ],
    "sg:phone":"+1 252 223 3482",
    "sg:postcode":"28570",
    "sg:province":"NC",
    "wof:name":"Newport Middle School",
    "wof:placetype":"venue"
},
  "geometry": {"coordinates":[-76.859313,34.772029],"type":"Point"}
}