{
  "type": "Feature",
  "properties": {
    "iso:country":"US",
    "sg:address":"3755 Kings Cross Rd",
    "sg:city":"Lumberton",
    "sg:classifiers":[
        {
            "category":"Shopping",
            "subcategory":"Beauty & Cosmetics",
            "type":"Retail Goods"
        }
    ],
    "sg:phone":"+1 910 738 5512",
    "sg:postcode":"28360",
    "sg:province":"NC",
    "sg:tags":[
        "merchandise"
    ],
    "wof:name":"Audrey Price",
    "wof:placetype":"venue"
},
  "geometry": {"coordinates":[-79.01612900000001,34.653647],"type":"Point"}
}