{
  "type": "Feature",
  "properties": {
    "addr:full":"8401 Medical Plaza Dr Charlotte NC 28262",
    "addr:housenumber":"8401",
    "addr:postcode":"28262",
    "addr:street":"Medical Plaza Dr",
    "iso:country":"US",
    "sg:address":"8401 Medical Plaza Dr",
    "sg:city":"Charlotte",
    "sg:classifiers":[
        {
            "category":"Health Services",
            "subcategory":"Doctor",
            "type":"Services"
        }
    ],
    "sg:phone":"+1 704 593 1090",
    "sg:postcode":"28262",
    "sg:province":"NC",
    "sg:tags":[
        "dentist"
    ],
    "sg:website":"www.olsen2.com",
    "wof:name":"Olsen & Olsen",
    "wof:placetype":"venue"
},
  "geometry": {"coordinates":[-80.775594,35.321016],"type":"Point"}
}