{
  "type": "Feature",
  "properties": {
    "addr:full":"441 McLin Creek Rd N Conover NC 28613",
    "addr:housenumber":"441",
    "addr:postcode":"28613",
    "addr:street":"Mclin Creek Rd N",
    "iso:country":"US",
    "sg:address":"441 McLin Creek Rd N",
    "sg:city":"Conover",
    "sg:classifiers":[
        {
            "category":"Wholesale",
            "subcategory":"Furniture",
            "type":"Manufacturing & Wholesale Goods"
        }
    ],
    "sg:phone":"+1 828 465 2393",
    "sg:postcode":"28613",
    "sg:province":"NC",
    "wof:name":"Allen Lee Furniture",
    "wof:placetype":"venue"
},
  "geometry": {"coordinates":[-81.186618,35.70259],"type":"Point"}
}