{
  "type": "Feature",
  "properties": {
    "addr:full":"205 Preston Ave Fayetteville NC 28301",
    "addr:housenumber":"205",
    "addr:postcode":"28301",
    "addr:street":"Preston Ave",
    "iso:country":"US",
    "sg:address":"205 Preston Ave",
    "sg:city":"Fayetteville",
    "sg:classifiers":[
        {
            "category":"Social Services",
            "subcategory":"Adult Care",
            "type":"Services"
        }
    ],
    "sg:phone":"+1 910 480 0695",
    "sg:postcode":"28301",
    "sg:province":"NC",
    "sg:tags":[
        "home"
    ],
    "wof:name":"Magby & Assoc",
    "wof:placetype":"venue"
},
  "geometry": {"coordinates":[-78.91310199999999,35.092357],"type":"Point"}
}