{
  "type": "Feature",
  "properties": {
    "iso:country":"US",
    "sg:address":"2802 Hermitage Ave",
    "sg:city":"Fayetteville",
    "sg:classifiers":[
        {
            "category":"Professional",
            "subcategory":"Business Services",
            "type":"Services"
        }
    ],
    "sg:phone":"+1   ",
    "sg:postcode":"28304",
    "sg:province":"NC",
    "wof:name":"Custom Interior Creations",
    "wof:placetype":"venue"
},
  "geometry": {"coordinates":[-78.928557,35.039148],"type":"Point"}
}