{
  "type": "Feature",
  "properties": {
    "addr:full":"302 Interstate Dr Archdale NC 27263",
    "addr:housenumber":"302",
    "addr:postcode":"27263",
    "addr:street":"Interstate Dr",
    "iso:country":"US",
    "sg:address":"302 Interstate Dr",
    "sg:city":"Archdale",
    "sg:classifiers":[
        {
            "category":"Wholesale",
            "subcategory":"Apparel",
            "type":"Manufacturing & Wholesale Goods"
        }
    ],
    "sg:phone":"+1 336 434 4542",
    "sg:postcode":"27263",
    "sg:province":"NC",
    "wof:name":"Soft-Wear",
    "wof:placetype":"venue"
},
  "geometry": {"coordinates":[-79.957008,35.899099],"type":"Point"}
}