{
  "type": "Feature",
  "properties": {
    "iso:country":"US",
    "sg:address":"3030 S Park Dr",
    "sg:city":"Reidsville",
    "sg:classifiers":[
        {
            "category":"Professional",
            "subcategory":"Lawyer & Legal Services",
            "type":"Services"
        }
    ],
    "sg:phone":"+1 336 342 6050",
    "sg:postcode":"27320",
    "sg:province":"NC",
    "sg:tags":[
        "attorney"
    ],
    "wof:name":"Eunice Jones-Obeng",
    "wof:placetype":"venue"
},
  "geometry": {"coordinates":[-79.684251,36.327546],"type":"Point"}
}