{
  "type": "Feature",
  "properties": {
    "iso:country":"US",
    "sg:address":"2010 Stonebridge Ln",
    "sg:city":"Charlotte",
    "sg:classifiers":[
        {
            "category":"Wholesale",
            "subcategory":"Drugs",
            "type":"Manufacturing & Wholesale Goods"
        }
    ],
    "sg:phone":"+1 704 364 1958",
    "sg:postcode":"28211",
    "sg:province":"NC",
    "sg:tags":[
        "cosmetics-wholesale",
        "cosmetic",
        "fragrance",
        "manufacturer"
    ],
    "wof:name":"S Berlin Inc",
    "wof:placetype":"venue"
},
  "geometry": {"coordinates":[-80.81804700000001,35.182621],"type":"Point"}
}