{
  "type": "Feature",
  "properties": {
    "addr:full":"1 Vanderbilt Rd Asheville NC 28803",
    "addr:housenumber":"1",
    "addr:postcode":"28803",
    "addr:street":"Vanderbilt Rd",
    "iso:country":"US",
    "sg:address":"1 Vanderbilt Rd",
    "sg:city":"Asheville",
    "sg:classifiers":[
        {
            "category":"Health Services",
            "subcategory":"Health Practitioner",
            "type":"Services"
        }
    ],
    "sg:phone":"+1 828 277 6957",
    "sg:postcode":"28803",
    "sg:province":"NC",
    "sg:tags":[
        "therapist",
        "physical"
    ],
    "wof:name":"Combine Therapy Specialties",
    "wof:placetype":"venue"
},
  "geometry": {"coordinates":[-82.543133,35.564377],"type":"Point"}
}