{
  "type": "Feature",
  "properties": {
    "addr:full":"5425 Styers Ferry Rd Clemmons NC 27012",
    "addr:housenumber":"5425",
    "addr:postcode":"27012",
    "addr:street":"Styers Ferry Rd",
    "iso:country":"US",
    "sg:address":"5425 Styers Ferry Rd",
    "sg:city":"Clemmons",
    "sg:classifiers":[
        {
            "category":"Professional",
            "subcategory":"Business Services",
            "type":"Services"
        }
    ],
    "sg:phone":"+1   ",
    "sg:postcode":"27012",
    "sg:province":"NC",
    "wof:name":"Soper",
    "wof:placetype":"venue"
},
  "geometry": {"coordinates":[-80.39593600000001,36.072353],"type":"Point"}
}