{
  "type": "Feature",
  "properties": {
    "addr:full":"224 Happy Hollow Rd Marshall NC 28753",
    "addr:housenumber":"224",
    "addr:postcode":"28753",
    "addr:street":"Happy Hollow Rd",
    "iso:country":"US",
    "sg:address":"224 Happy Hollow Rd",
    "sg:city":"Marshall",
    "sg:classifiers":[
        {
            "category":"Building & Trades",
            "subcategory":"Construction",
            "type":"Services"
        }
    ],
    "sg:phone":"+1 828 649 3017",
    "sg:postcode":"28753",
    "sg:province":"NC",
    "wof:name":"Happy Hollow Enterprises",
    "wof:placetype":"venue"
},
  "geometry": {"coordinates":[-82.634865,35.811169],"type":"Point"}
}