{
  "type": "Feature",
  "properties": {
    "addr:full":"411 Grande Heights Dr Cary NC 27513",
    "addr:housenumber":"411",
    "addr:postcode":"27513",
    "addr:street":"Grande Heights Dr",
    "iso:country":"US",
    "sg:address":"411 Grande Heights Dr",
    "sg:city":"Cary",
    "sg:classifiers":[
        {
            "category":"Professional",
            "type":"Services"
        }
    ],
    "sg:phone":"+1 919 463 9554",
    "sg:postcode":"27513",
    "sg:province":"NC",
    "wof:name":"Family Run & Walk Inc",
    "wof:placetype":"venue"
},
  "geometry": {"coordinates":[-78.784705,35.804931],"type":"Point"}
}