{
  "type": "Feature",
  "properties": {
    "addr:full":"1027 Fleming St Hendersonville NC 28791",
    "addr:housenumber":"1027",
    "addr:postcode":"28791",
    "addr:street":"Fleming St",
    "iso:country":"US",
    "sg:address":"1027 Fleming St",
    "sg:city":"Hendersonville",
    "sg:classifiers":[
        {
            "category":"Health Services",
            "subcategory":"Doctor",
            "type":"Services"
        }
    ],
    "sg:phone":"+1 828 692 5781",
    "sg:postcode":"28791",
    "sg:province":"NC",
    "sg:tags":[
        "physician",
        "surgeon"
    ],
    "wof:name":"Hendersonville Orthapedics",
    "wof:placetype":"venue"
},
  "geometry": {"coordinates":[-82.466052,35.323833],"type":"Point"}
}