{
  "type": "Feature",
  "properties": {
    "iso:country":"US",
    "sg:address":"547 Champion Dr",
    "sg:city":"Canton",
    "sg:classifiers":[
        {
            "category":"Shopping",
            "subcategory":"Bicycles & Sporting Goods",
            "type":"Retail Goods"
        }
    ],
    "sg:phone":"+1 828 648 4447",
    "sg:postcode":"28716",
    "sg:province":"NC",
    "wof:name":"Carolina Pawn & Gun Shop",
    "wof:placetype":"venue"
},
  "geometry": {"coordinates":[-82.850183,35.549194],"type":"Point"}
}