{
  "type": "Feature",
  "properties": {
    "addr:full":"304 Old Hargrave Rd Lexington NC 27295",
    "addr:housenumber":"304",
    "addr:postcode":"27295",
    "addr:street":"Old Hargrave Rd",
    "iso:country":"US",
    "sg:address":"304 Old Hargrave Rd",
    "sg:city":"Lexington",
    "sg:classifiers":[
        {
            "category":"Manufacturing",
            "subcategory":"Lumber",
            "type":"Manufacturing & Wholesale Goods"
        }
    ],
    "sg:phone":"+1 336 956 2112",
    "sg:postcode":"27295",
    "sg:province":"NC",
    "sg:tags":[
        "government"
    ],
    "wof:name":"Forestry Dept",
    "wof:placetype":"venue"
},
  "geometry": {"coordinates":[-80.31044,35.792576],"type":"Point"}
}