{
  "type": "Feature",
  "properties": {
    "iso:country":"US",
    "sg:address":"2831 Wendell Blvd",
    "sg:city":"Wendell",
    "sg:classifiers":[
        {
            "category":"Restaurant",
            "type":"Food & Drink"
        }
    ],
    "sg:phone":"+1 919 365 4005",
    "sg:postcode":"27591",
    "sg:province":"NC",
    "wof:name":"Subway Sandwiches & Salads",
    "wof:placetype":"venue"
},
  "geometry": {"coordinates":[-78.399885,35.802317],"type":"Point"}
}