{
  "type": "Feature",
  "properties": {
    "addr:full":"1057 Colington Rd Kill Devil Hills NC 27948",
    "addr:housenumber":"1057",
    "addr:postcode":"27948",
    "addr:street":"Colington Rd",
    "iso:country":"US",
    "sg:address":"1057 Colington Rd",
    "sg:city":"Kill Devil Hills",
    "sg:classifiers":[
        {
            "category":"Travel",
            "subcategory":"Hotels & Motels",
            "type":"Entertainment"
        }
    ],
    "sg:phone":"+1   ",
    "sg:postcode":"27948",
    "sg:province":"NC",
    "sg:tags":[
        "operation"
    ],
    "wof:name":"White Egret Bed & Breakfast",
    "wof:placetype":"venue"
},
  "geometry": {"coordinates":[-75.68301700000001,36.015021],"type":"Point"}
}