{
  "type": "Feature",
  "properties": {
    "addr:full":"1168 Kellum Loop Rd Jacksonville NC 28546",
    "addr:housenumber":"1168",
    "addr:postcode":"28546",
    "addr:street":"Kellum Loop Rd",
    "iso:country":"US",
    "sg:address":"1168 Kellum Loop Rd",
    "sg:city":"Jacksonville",
    "sg:classifiers":[
        {
            "category":"Retail",
            "subcategory":"Laundry & Dry Cleaning",
            "type":"Services"
        }
    ],
    "sg:phone":"+1   ",
    "sg:postcode":"28546",
    "sg:province":"NC",
    "sg:tags":[
        "upholstery",
        "carpet"
    ],
    "wof:name":"Carolina Clean Care",
    "wof:placetype":"venue"
},
  "geometry": {"coordinates":[-77.35477899999999,34.814189],"type":"Point"}
}