{
  "type": "Feature",
  "properties": {
    "addr:full":"105 W Meadowview Rd Greensboro NC 27406",
    "addr:housenumber":"105",
    "addr:postcode":"27406",
    "addr:street":"W Meadowview Rd",
    "iso:country":"US",
    "sg:address":"105 W Meadowview Rd",
    "sg:city":"Greensboro",
    "sg:classifiers":[
        {
            "category":"Retail",
            "subcategory":"Auto Repair",
            "type":"Services"
        }
    ],
    "sg:phone":"+1 336 274 7265",
    "sg:postcode":"27406",
    "sg:province":"NC",
    "sg:tags":[
        "repairing",
        "automobile"
    ],
    "wof:name":"Casey's Tire & Automotive Inc",
    "wof:placetype":"venue"
},
  "geometry": {"coordinates":[-79.796795,36.039366],"type":"Point"}
}