{
  "type": "Feature",
  "properties": {
    "addr:full":"2215 Dogwood Ln Kinston NC 28504",
    "addr:housenumber":"2215",
    "addr:postcode":"28504",
    "addr:street":"Dogwood Ln",
    "iso:country":"US",
    "sg:address":"2215 Dogwood Ln",
    "sg:city":"Kinston",
    "sg:classifiers":[
        {
            "category":"Building & Trades",
            "subcategory":"Construction",
            "type":"Services"
        }
    ],
    "sg:phone":"+1 252 560 8868",
    "sg:postcode":"28504",
    "sg:province":"NC",
    "sg:tags":[
        "residential"
    ],
    "wof:name":"Michael R Burke",
    "wof:placetype":"venue"
},
  "geometry": {"coordinates":[-77.662482,35.286934],"type":"Point"}
}