{
  "type": "Feature",
  "properties": {
    "iso:country":"US",
    "sg:address":"120 College St",
    "sg:city":"Asheville",
    "sg:classifiers":[
        {
            "category":"Professional",
            "subcategory":"Lawyer & Legal Services",
            "type":"Services"
        }
    ],
    "sg:phone":"+1 828 258 1501",
    "sg:postcode":"28801",
    "sg:province":"NC",
    "sg:tags":[
        "attorney"
    ],
    "wof:name":"Marsha Stone",
    "wof:placetype":"venue"
},
  "geometry": {"coordinates":[-82.550377,35.595896],"type":"Point"}
}