{
  "type": "Feature",
  "properties": {
    "iso:country":"US",
    "sg:address":"1718 Blanche St",
    "sg:city":"Albemarle",
    "sg:classifiers":[
        {
            "category":"Manufacturing",
            "subcategory":"Printing",
            "type":"Manufacturing & Wholesale Goods"
        }
    ],
    "sg:phone":"+1 704 985 1315",
    "sg:postcode":"28001",
    "sg:province":"NC",
    "sg:tags":[
        "reporting",
        "typesetting"
    ],
    "wof:name":"Typeset Plus",
    "wof:placetype":"venue"
},
  "geometry": {"coordinates":[-80.18946099999999,35.385092],"type":"Point"}
}