{
  "type": "Feature",
  "properties": {
    "iso:country":"US",
    "sg:address":"1318 S Person St",
    "sg:city":"Raleigh",
    "sg:classifiers":[
        {
            "category":"Wholesale",
            "subcategory":"Apparel",
            "type":"Manufacturing & Wholesale Goods"
        }
    ],
    "sg:phone":"+1 919 828 7807",
    "sg:postcode":"27601",
    "sg:province":"NC",
    "sg:tags":[
        "shoes"
    ],
    "wof:name":"Mak Associates",
    "wof:placetype":"venue"
},
  "geometry": {"coordinates":[-78.63576999999999,35.763641],"type":"Point"}
}