{
  "type": "Feature",
  "properties": {
    "addr:full":"203 W Weaver St Carrboro NC 27510",
    "addr:housenumber":"203",
    "addr:postcode":"27510",
    "addr:street":"W Weaver St",
    "iso:country":"US",
    "sg:address":"203 W Weaver St",
    "sg:city":"Carrboro",
    "sg:classifiers":[
        {
            "category":"Restaurant",
            "type":"Food & Drink"
        }
    ],
    "sg:phone":"+1 919 967 5008",
    "sg:postcode":"27510",
    "sg:province":"NC",
    "sg:tags":[
        "eating",
        "french"
    ],
    "wof:name":"Provence",
    "wof:placetype":"venue"
},
  "geometry": {"coordinates":[-79.073303,35.911098],"type":"Point"}
}