{
  "type": "Feature",
  "properties": {
    "addr:full":"4216 Kildare Dr Greensboro NC 27405",
    "addr:housenumber":"4216",
    "addr:postcode":"27405",
    "addr:street":"Kildare Dr",
    "iso:country":"US",
    "sg:address":"4216 Kildare Dr",
    "sg:city":"Greensboro",
    "sg:classifiers":[
        {
            "category":"Organizations",
            "subcategory":"Religious Organization",
            "type":"Services"
        }
    ],
    "sg:phone":"+1   ",
    "sg:postcode":"27405",
    "sg:province":"NC",
    "wof:name":"Community United Church C",
    "wof:placetype":"venue"
},
  "geometry": {"coordinates":[-79.733412,36.090703],"type":"Point"}
}