{
  "type": "Feature",
  "properties": {
    "iso:country":"US",
    "sg:address":"201 Hay St",
    "sg:city":"Fayetteville",
    "sg:classifiers":[
        {
            "category":"Professional",
            "type":"Services"
        }
    ],
    "sg:phone":"+1 910 483 2576",
    "sg:postcode":"28301",
    "sg:province":"NC",
    "wof:name":"J Smith Lanier",
    "wof:placetype":"venue"
},
  "geometry": {"coordinates":[-78.880877,35.053461],"type":"Point"}
}