{
  "type": "Feature",
  "properties": {
    "addr:full":"304 Depot St Franklin NC 28734",
    "addr:housenumber":"304",
    "addr:postcode":"nc 28734",
    "addr:street":"Depot St",
    "iso:country":"US",
    "sg:address":"304 Depot St",
    "sg:city":"Franklin",
    "sg:classifiers":[
        {
            "category":"Shopping",
            "subcategory":"Used Merchandise",
            "type":"Retail Goods"
        }
    ],
    "sg:phone":"+1 828 524 3395",
    "sg:postcode":"28734",
    "sg:province":"NC",
    "wof:name":"Back On Rack",
    "wof:placetype":"venue"
},
  "geometry": {"coordinates":[-83.373418,35.176557],"type":"Point"}
}