{
  "type": "Feature",
  "properties": {
    "iso:country":"US",
    "sg:address":"1058 W Club Blvd",
    "sg:city":"Durham",
    "sg:classifiers":[
        {
            "category":"Shopping",
            "subcategory":"Clothing, Apparel, & Fashions",
            "type":"Retail Goods"
        }
    ],
    "sg:phone":"+1 919 286 0067",
    "sg:postcode":"27701",
    "sg:province":"NC",
    "sg:tags":[
        "family"
    ],
    "wof:name":"Gap",
    "wof:placetype":"venue"
},
  "geometry": {"coordinates":[-78.908835,36.016983],"type":"Point"}
}