{
  "type": "Feature",
  "properties": {
    "addr:full":"12412 Landing Green Dr Charlotte NC 28277",
    "addr:housenumber":"12412",
    "addr:postcode":"28277",
    "addr:street":"Landing Green Dr",
    "iso:country":"US",
    "sg:address":"12412 Landing Green Dr",
    "sg:city":"Charlotte",
    "sg:classifiers":[
        {
            "category":"Banks & Credit Unions",
            "subcategory":"Bank",
            "type":"Services"
        }
    ],
    "sg:phone":"+1 704 841 0613",
    "sg:postcode":"28277",
    "sg:province":"NC",
    "sg:tags":[
        "broker",
        "mortgage"
    ],
    "wof:name":"MBA Mortgage Inc",
    "wof:placetype":"venue"
},
  "geometry": {"coordinates":[-80.79703600000001,35.033841],"type":"Point"}
}