{
  "type": "Feature",
  "properties": {
    "addr:full":"10901 University City Blvd Charlotte NC 28213",
    "addr:housenumber":"10901",
    "addr:postcode":"28213",
    "addr:street":"University City Blvd",
    "iso:country":"US",
    "sg:address":"10901 University City Blvd",
    "sg:city":"Charlotte",
    "sg:classifiers":[
        {
            "category":"Shopping",
            "type":"Retail Goods"
        }
    ],
    "sg:phone":"+1 704 548 9411",
    "sg:postcode":"28213",
    "sg:province":"NC",
    "sg:tags":[
        "trophy",
        "medal",
        "award"
    ],
    "wof:name":"Walker Trophies & Awards Inc",
    "wof:placetype":"venue"
},
  "geometry": {"coordinates":[-80.700791,35.313942],"type":"Point"}
}