{
  "type": "Feature",
  "properties": {
    "iso:country":"US",
    "sg:address":"104 Jones Franklin Rd",
    "sg:city":"Raleigh",
    "sg:classifiers":[
        {
            "category":"Taxi",
            "type":"Transportation"
        }
    ],
    "sg:phone":"+1 919 233 6798",
    "sg:postcode":"27606",
    "sg:province":"NC",
    "sg:tags":[
        "taxicab"
    ],
    "wof:name":"Limited The",
    "wof:placetype":"venue"
},
  "geometry": {"coordinates":[-78.72199500000001,35.785195],"type":"Point"}
}