{
  "type": "Feature",
  "properties": {
    "iso:country":"US",
    "sg:address":"308 S Walton Dr",
    "sg:city":"Benson",
    "sg:classifiers":[
        {
            "category":"Retail",
            "subcategory":"Auto Repair",
            "type":"Services"
        }
    ],
    "sg:phone":"+1 919 207 0781",
    "sg:postcode":"27504",
    "sg:province":"NC",
    "sg:tags":[
        "repairing",
        "automobile"
    ],
    "wof:name":"Mr C's Bar & Restaurant",
    "wof:placetype":"venue"
},
  "geometry": {"coordinates":[-78.541096,35.373851],"type":"Point"}
}