{
  "type": "Feature",
  "properties": {
    "addr:full":"4705 Dwight Evans Rd Charlotte NC 28217",
    "addr:housenumber":"4705",
    "addr:postcode":"28217",
    "addr:street":"Dwight Evans Rd",
    "iso:country":"US",
    "sg:address":"4705 Dwight Evans Rd",
    "sg:city":"Charlotte",
    "sg:classifiers":[
        {
            "category":"Freight",
            "type":"Transportation"
        }
    ],
    "sg:phone":"+1 704 525 9384",
    "sg:postcode":"28217",
    "sg:province":"NC",
    "sg:tags":[
        "warehouse"
    ],
    "wof:name":"Nabisco",
    "wof:placetype":"venue"
},
  "geometry": {"coordinates":[-80.899564,35.1899],"type":"Point"}
}