{
  "type": "Feature",
  "properties": {
    "iso:country":"US",
    "sg:address":"1120 Gurganus Rd",
    "sg:city":"Richlands",
    "sg:phone":"+1 910 455 3143",
    "sg:postcode":"28574",
    "sg:province":"NC",
    "sg:tags":[
        "farm",
        "soybean"
    ],
    "wof:name":"Johnnie Gurganus",
    "wof:placetype":"venue"
},
  "geometry": {"coordinates":[-77.674049,34.760505],"type":"Point"}
}