{
  "type": "Feature",
  "properties": {
    "iso:country":"US",
    "sg:address":"114 Silver Creek Rd",
    "sg:city":"Morganton",
    "sg:classifiers":[
        {
            "category":"Organizations",
            "subcategory":"Religious Organization",
            "type":"Services"
        }
    ],
    "sg:phone":"+1 828 438 4217",
    "sg:postcode":"28655",
    "sg:province":"NC",
    "sg:tags":[
        "church"
    ],
    "sg:website":"www.presbyterywnc.org",
    "wof:name":"Presbytery Of Western Nc",
    "wof:placetype":"venue"
},
  "geometry": {"coordinates":[-81.702702,35.738275],"type":"Point"}
}