{
  "type": "Feature",
  "properties": {
    "iso:country":"US",
    "sg:address":"6225 Stanleyville Dr",
    "sg:city":"Rural Hall",
    "sg:classifiers":[
        {
            "category":"Building & Trades",
            "subcategory":"Construction",
            "type":"Services"
        }
    ],
    "sg:phone":"+1 336 377 2778",
    "sg:postcode":"27045",
    "sg:province":"NC",
    "sg:tags":[
        "house",
        "nonresidential",
        "general",
        "contractor"
    ],
    "wof:name":"Jim Lineback Construction",
    "wof:placetype":"venue"
},
  "geometry": {"coordinates":[-80.25448,36.224731],"type":"Point"}
}