{
  "type": "Feature",
  "properties": {
    "iso:country":"US",
    "sg:address":"204 S 4th St",
    "sg:city":"Spring Lake",
    "sg:classifiers":[
        {
            "category":"Social Services",
            "type":"Services"
        }
    ],
    "sg:phone":"+1 910 497 7700",
    "sg:postcode":"28390",
    "sg:province":"NC",
    "sg:tags":[
        "senior",
        "citizen"
    ],
    "wof:name":"Spring Lake Senior Citizens",
    "wof:placetype":"venue"
},
  "geometry": {"coordinates":[-78.969855,35.165798],"type":"Point"}
}