{
  "type": "Feature",
  "properties": {
    "addr:full":"240 N Bethesda Rd Southern Pines NC 28387",
    "addr:housenumber":"240",
    "addr:postcode":"28387",
    "addr:street":"N Bethesda Rd",
    "iso:country":"US",
    "sg:address":"240 N Bethesda Rd",
    "sg:city":"Southern Pines",
    "sg:classifiers":[
        {
            "category":"Real Estate",
            "subcategory":"Real Estate Operator",
            "type":"Services"
        }
    ],
    "sg:phone":"+1 910 692 6942",
    "sg:postcode":"28387",
    "sg:province":"NC",
    "sg:tags":[
        "building",
        "nonresidential"
    ],
    "wof:name":"Spc Building Partnership",
    "wof:placetype":"venue"
},
  "geometry": {"coordinates":[-79.383241,35.154439],"type":"Point"}
}