{
  "type": "Feature",
  "properties": {
    "addr:full":"273 Beverly Dr NE Concord NC 28025",
    "addr:housenumber":"273",
    "addr:postcode":"28025",
    "addr:street":"Beverly Dr Ne",
    "iso:country":"US",
    "sg:address":"273 Beverly Dr NE",
    "sg:city":"Concord",
    "sg:classifiers":[
        {
            "category":"Banks & Credit Unions",
            "subcategory":"Financial Services",
            "type":"Services"
        }
    ],
    "sg:phone":"+1 704 782 3647",
    "sg:postcode":"28025",
    "sg:province":"NC",
    "sg:tags":[
        "investor"
    ],
    "wof:name":"Early Investments LLC",
    "wof:placetype":"venue"
},
  "geometry": {"coordinates":[-80.593217,35.439876],"type":"Point"}
}