{
  "type": "Feature",
  "properties": {
    "iso:country":"US",
    "sg:address":"2534 Reepsville Rd",
    "sg:city":"Lincolnton",
    "sg:classifiers":[
        {
            "category":"Retail",
            "subcategory":"Auto Repair",
            "type":"Services"
        }
    ],
    "sg:phone":"+1 704 735 2930",
    "sg:postcode":"28092",
    "sg:province":"NC",
    "sg:tags":[
        "automotive",
        "grocery",
        "gasoline",
        "stat"
    ],
    "wof:name":"Hamptons Sunoco Service",
    "wof:placetype":"venue"
},
  "geometry": {"coordinates":[-81.298205,35.508074],"type":"Point"}
}