{
  "type": "Feature",
  "properties": {
    "iso:country":"US",
    "sg:address":"104 Ararat Longhill Rd",
    "sg:city":"Pilot Mountain",
    "sg:classifiers":[
        {
            "category":"Health Services",
            "subcategory":"Doctor",
            "type":"Services"
        }
    ],
    "sg:phone":"+1 336 786 7966",
    "sg:postcode":"27041",
    "sg:province":"NC",
    "sg:tags":[
        "physician",
        "surgeon"
    ],
    "wof:name":"Holly Springs Family Practice",
    "wof:placetype":"venue"
},
  "geometry": {"coordinates":[-80.552121,36.441819],"type":"Point"}
}