{
  "type": "Feature",
  "properties": {
    "addr:full":"2901 Hiking Trl Raleigh NC 27615",
    "addr:housenumber":"2901",
    "addr:postcode":"27615",
    "addr:street":"Hiking Trl",
    "iso:country":"US",
    "sg:address":"2901 Hiking Trl",
    "sg:city":"Raleigh",
    "sg:classifiers":[
        {
            "category":"Professional",
            "subcategory":"Management & Consulting",
            "type":"Services"
        }
    ],
    "sg:phone":"+1   ",
    "sg:postcode":"27615",
    "sg:province":"NC",
    "wof:name":"Coggins Sales and Mktg Inc",
    "wof:placetype":"venue"
},
  "geometry": {"coordinates":[-78.591375,35.899043],"type":"Point"}
}