{
  "type": "Feature",
  "properties": {
    "iso:country":"US",
    "sg:address":"204 Ernest Lambeth Rd",
    "sg:city":"Winston Salem",
    "sg:classifiers":[
        {
            "category":"Freight",
            "type":"Transportation"
        }
    ],
    "sg:phone":"+1 336 784 0408",
    "sg:postcode":"27107",
    "sg:province":"NC",
    "sg:tags":[
        "operator",
        "local",
        "trucking"
    ],
    "wof:name":"Gene S Hauling Landscaping",
    "wof:placetype":"venue"
},
  "geometry": {"coordinates":[-80.20788,36.019248],"type":"Point"}
}