{
  "type": "Feature",
  "properties": {
    "iso:country":"US",
    "sg:address":"606 E 11th St",
    "sg:city":"Greenville",
    "sg:classifiers":[
        {
            "category":"Shopping",
            "subcategory":"Music",
            "type":"Retail Goods"
        }
    ],
    "sg:phone":"+1 252 695 0409",
    "sg:postcode":"27858",
    "sg:province":"NC",
    "wof:name":"Ultramod Records",
    "wof:placetype":"venue"
},
  "geometry": {"coordinates":[-77.368084,35.603777],"type":"Point"}
}