{
  "type": "Feature",
  "properties": {
    "addr:full":"222 Barber St Asheboro NC 27203",
    "addr:housenumber":"222",
    "addr:postcode":"27203",
    "addr:street":"Barber St",
    "iso:country":"US",
    "sg:address":"222 Barber St",
    "sg:city":"Asheboro",
    "sg:classifiers":[
        {
            "category":"Building & Trades",
            "subcategory":"Construction",
            "type":"Services"
        }
    ],
    "sg:phone":"+1 336 672 3030",
    "sg:postcode":"27203",
    "sg:province":"NC",
    "sg:tags":[
        "general",
        "contractor"
    ],
    "wof:name":"Carolina Insulation",
    "wof:placetype":"venue"
},
  "geometry": {"coordinates":[-79.81242,35.738927],"type":"Point"}
}