{
  "type": "Feature",
  "properties": {
    "iso:country":"US",
    "sg:address":"6920 N Tryon St",
    "sg:city":"Charlotte",
    "sg:classifiers":[
        {
            "category":"Professional",
            "subcategory":"Business Services",
            "type":"Services"
        }
    ],
    "sg:phone":"+1 704 596 3979",
    "sg:postcode":"28213",
    "sg:province":"NC",
    "sg:tags":[
        "inventory",
        "computing"
    ],
    "wof:name":"Washington Inventory Service",
    "wof:placetype":"venue"
},
  "geometry": {"coordinates":[-80.76494700000001,35.281688],"type":"Point"}
}