{
  "type": "Feature",
  "properties": {
    "addr:full":"105 Lee St E Wilson NC 27893",
    "addr:housenumber":"105",
    "addr:postcode":"27893",
    "addr:street":"Lee St E",
    "iso:country":"US",
    "sg:address":"105 Lee St E",
    "sg:city":"Wilson",
    "sg:classifiers":[
        {
            "category":"Professional",
            "type":"Services"
        }
    ],
    "sg:phone":"+1 252 291 2502",
    "sg:postcode":"27893",
    "sg:province":"NC",
    "wof:name":"Masheadys",
    "wof:placetype":"venue"
},
  "geometry": {"coordinates":[-77.907185,35.728385],"type":"Point"}
}