{
  "type": "Feature",
  "properties": {
    "addr:full":"109 Head Rd Hendersonville NC 28786",
    "addr:housenumber":"109",
    "addr:postcode":"28786",
    "addr:street":"Head Rd",
    "iso:country":"US",
    "sg:address":"109 Head Rd",
    "sg:city":"Hendersonville",
    "sg:classifiers":[
        {
            "category":"Building & Trades",
            "subcategory":"Construction",
            "type":"Services"
        }
    ],
    "sg:phone":"+1 828 692 8669",
    "sg:postcode":"28786",
    "sg:province":"NC",
    "sg:tags":[
        "residential"
    ],
    "wof:name":"Terry Gibbs Construction",
    "wof:placetype":"venue"
},
  "geometry": {"coordinates":[-82.96213899999999,35.47504],"type":"Point"}
}