{
  "type": "Feature",
  "properties": {
    "iso:country":"US",
    "sg:address":"1110 E Salisbury St",
    "sg:city":"Asheboro",
    "sg:classifiers":[
        {
            "category":"Food & Beverages",
            "subcategory":"Groceries & Convenience Stores",
            "type":"Retail Goods"
        }
    ],
    "sg:phone":"+1 336 328 0333",
    "sg:postcode":"27203",
    "sg:province":"NC",
    "sg:tags":[
        "grocer"
    ],
    "wof:name":"El Cordero",
    "wof:placetype":"venue"
},
  "geometry": {"coordinates":[-79.79531,35.704767],"type":"Point"}
}