{
  "type": "Feature",
  "properties": {
    "iso:country":"US",
    "sg:address":"20488 Chartwell Center Dr",
    "sg:city":"Cornelius",
    "sg:classifiers":[
        {
            "category":"Wholesale",
            "subcategory":"Medical Equipment & Supplies",
            "type":"Manufacturing & Wholesale Goods"
        },
        {
            "category":"Retail",
            "subcategory":"Repair Shop",
            "type":"Services"
        }
    ],
    "sg:phone":"+1 704 896 0305",
    "sg:postcode":"28031",
    "sg:province":"NC",
    "sg:website":"www.gilloolyinc.com",
    "wof:name":"Gillooly Ultrasound Inc",
    "wof:placetype":"venue"
},
  "geometry": {"coordinates":[-80.87849900000001,35.480308],"type":"Point"}
}