{
  "type": "Feature",
  "properties": {
    "iso:country":"US",
    "sg:address":"1802 S Horner Blvd",
    "sg:city":"Sanford",
    "sg:classifiers":[
        {
            "category":"Shopping",
            "subcategory":"Pharmacy",
            "type":"Retail Goods"
        }
    ],
    "sg:phone":"+1 919 776 4574",
    "sg:postcode":"27330",
    "sg:province":"NC",
    "wof:name":"CVS Pharmacy",
    "wof:placetype":"venue"
},
  "geometry": {"coordinates":[-79.15816599999999,35.465687],"type":"Point"}
}