{
  "type": "Feature",
  "properties": {
    "iso:country":"US",
    "sg:address":"106 Oak Ridge Ln",
    "sg:city":"Wilmington",
    "sg:classifiers":[
        {
            "category":"Building & Trades",
            "subcategory":"Landscaping Services",
            "type":"Services"
        }
    ],
    "sg:phone":"+1 910 686 4984",
    "sg:postcode":"28411",
    "sg:province":"NC",
    "sg:tags":[
        "nursery",
        "landscape",
        "contractor"
    ],
    "wof:name":"Lloyds Nursery",
    "wof:placetype":"venue"
},
  "geometry": {"coordinates":[-77.81534499999999,34.284283],"type":"Point"}
}