{
  "type": "Feature",
  "properties": {
    "addr:full":"111 Creek Ridge Rd Greensboro NC 27406",
    "addr:housenumber":"111",
    "addr:postcode":"27406",
    "addr:street":"Creek Ridge Rd",
    "iso:country":"US",
    "sg:address":"111 Creek Ridge Rd",
    "sg:city":"Greensboro",
    "sg:classifiers":[
        {
            "category":"Manufacturing",
            "subcategory":"Signs",
            "type":"Manufacturing & Wholesale Goods"
        }
    ],
    "sg:phone":"+1 336 274 1388",
    "sg:postcode":"27406",
    "sg:province":"NC",
    "sg:tags":[
        "specialty",
        "mfg"
    ],
    "wof:name":"Mitchell Signs",
    "wof:placetype":"venue"
},
  "geometry": {"coordinates":[-79.793672,36.029162],"type":"Point"}
}