{
  "type": "Feature",
  "properties": {
    "iso:country":"US",
    "sg:address":"3590 Yadkinville Rd",
    "sg:city":"Winston Salem",
    "sg:classifiers":[
        {
            "category":"Freight",
            "type":"Transportation"
        }
    ],
    "sg:phone":"+1 336 922 2244",
    "sg:postcode":"27106",
    "sg:province":"NC",
    "sg:tags":[
        "commercial",
        "storage"
    ],
    "wof:name":"Reynolda Storage Ctr",
    "wof:placetype":"venue"
},
  "geometry": {"coordinates":[-80.317407,36.153745],"type":"Point"}
}