{
  "type": "Feature",
  "properties": {
    "iso:country":"US",
    "sg:address":"14203 Eastfield Rd",
    "sg:city":"Huntersville",
    "sg:classifiers":[
        {
            "category":"Personal",
            "subcategory":"Beauty Salon",
            "type":"Services"
        }
    ],
    "sg:phone":"+1   ",
    "sg:postcode":"28078",
    "sg:province":"NC",
    "sg:tags":[
        "shop"
    ],
    "wof:name":"Country Salon Of Beauty",
    "wof:placetype":"venue"
},
  "geometry": {"coordinates":[-80.770393,35.39642],"type":"Point"}
}