{
  "type": "Feature",
  "properties": {
    "iso:country":"US",
    "sg:address":"125 W Main St",
    "sg:city":"Garner",
    "sg:classifiers":[
        {
            "category":"Building & Trades",
            "subcategory":"Electrical",
            "type":"Services"
        }
    ],
    "sg:phone":"+1 919 662 9600",
    "sg:postcode":"27529",
    "sg:province":"NC",
    "sg:tags":[
        "electric",
        "contractor"
    ],
    "wof:name":"Delta Electrical Corp",
    "wof:placetype":"venue"
},
  "geometry": {"coordinates":[-78.606177,35.707088],"type":"Point"}
}