{
  "type": "Feature",
  "properties": {
    "iso:country":"US",
    "sg:address":"721 Dobson St",
    "sg:city":"Kernersville",
    "sg:classifiers":[
        {
            "category":"Building & Trades",
            "subcategory":"Plumbing",
            "type":"Services"
        }
    ],
    "sg:phone":"+1 336 993 5744",
    "sg:postcode":"27284",
    "sg:province":"NC",
    "sg:tags":[
        "contractor"
    ],
    "wof:name":"J Letchworth Plumbing",
    "wof:placetype":"venue"
},
  "geometry": {"coordinates":[-80.080816,36.135711],"type":"Point"}
}