{
  "type": "Feature",
  "properties": {
    "iso:country":"US",
    "sg:address":"121 Sherron Rd",
    "sg:city":"Durham",
    "sg:classifiers":[
        {
            "category":"Personal",
            "subcategory":"Beauty Salon",
            "type":"Services"
        }
    ],
    "sg:phone":"+1 919 596 9388",
    "sg:postcode":"27703",
    "sg:province":"NC",
    "sg:tags":[
        "manicuring"
    ],
    "wof:name":"Nail Time",
    "wof:placetype":"venue"
},
  "geometry": {"coordinates":[-78.793882,35.975662],"type":"Point"}
}