{
  "type": "Feature",
  "properties": {
    "addr:full":"100 Whisperwood Dr Cary NC 27518",
    "addr:housenumber":"100",
    "addr:postcode":"27518",
    "addr:street":"Whisperwood Dr",
    "iso:country":"US",
    "sg:address":"100 Whisperwood Dr",
    "sg:city":"Cary",
    "sg:classifiers":[
        {
            "category":"Real Estate",
            "subcategory":"Real Estate Operator",
            "type":"Services"
        }
    ],
    "sg:phone":"+1 919 859 3119",
    "sg:postcode":"27518",
    "sg:province":"NC",
    "sg:tags":[
        "building",
        "nonresidential"
    ],
    "wof:name":"Cumberland Street Properties",
    "wof:placetype":"venue"
},
  "geometry": {"coordinates":[-78.760921,35.725207],"type":"Point"}
}