{
  "type": "Feature",
  "properties": {
    "addr:full":"924 Ashley Glen Ln Winston Salem NC 27104",
    "addr:housenumber":"924",
    "addr:postcode":"27104",
    "addr:street":"Ashley Glen Ln",
    "iso:country":"US",
    "sg:address":"924 Ashley Glen Ln",
    "sg:city":"Winston Salem",
    "sg:classifiers":[
        {
            "category":"Real Estate",
            "subcategory":"Real Estate Agent",
            "type":"Services"
        }
    ],
    "sg:phone":"+1 336 760 2966",
    "sg:postcode":"27104",
    "sg:province":"NC",
    "wof:name":"Land Allan Certif Appraiser",
    "wof:placetype":"venue"
},
  "geometry": {"coordinates":[-80.32517300000001,36.110989],"type":"Point"}
}