{
  "type": "Feature",
  "properties": {
    "iso:country":"US",
    "sg:address":"12524 Hennigan Place Ln",
    "sg:city":"Charlotte",
    "sg:classifiers":[
        {
            "category":"Wholesale",
            "subcategory":"Construction Materials",
            "type":"Manufacturing & Wholesale Goods"
        }
    ],
    "sg:phone":"+1 704 392 9392",
    "sg:postcode":"28214",
    "sg:province":"NC",
    "sg:tags":[
        "pallet",
        "skid"
    ],
    "wof:name":"Pallet Lady Inc",
    "wof:placetype":"venue"
},
  "geometry": {"coordinates":[-80.966735,35.335833],"type":"Point"}
}