{
  "type": "Feature",
  "properties": {
    "addr:full":"520 Country Club Rd Brevard SC 28712",
    "addr:housenumber":"520",
    "addr:postcode":"28712",
    "addr:street":"Country Club Rd",
    "iso:country":"US",
    "sg:address":"520 Country Club Rd",
    "sg:city":"Brevard",
    "sg:classifiers":[
        {
            "category":"Building & Trades",
            "subcategory":"Construction",
            "type":"Services"
        }
    ],
    "sg:phone":"+1 828 884 4466",
    "sg:postcode":"28712",
    "sg:province":"SC",
    "sg:tags":[
        "house"
    ],
    "wof:name":"Grohne Construction Co",
    "wof:placetype":"venue"
},
  "geometry": {"coordinates":[-82.73750699999999,35.226186],"type":"Point"}
}