{
  "type": "Feature",
  "properties": {
    "iso:country":"US",
    "sg:address":"108 S Market St",
    "sg:city":"Madison",
    "sg:classifiers":[
        {
            "category":"Shopping",
            "type":"Retail Goods"
        }
    ],
    "sg:phone":"+1 336 427 4044",
    "sg:postcode":"27025",
    "sg:province":"NC",
    "sg:tags":[
        "merchandise"
    ],
    "wof:name":"Joys Pollution Solutions Inc",
    "wof:placetype":"venue"
},
  "geometry": {"coordinates":[-79.959701,36.387438],"type":"Point"}
}