{
  "type": "Feature",
  "properties": {
    "iso:country":"US",
    "sg:address":"124 Avalon Dr",
    "sg:city":"Salisbury",
    "sg:classifiers":[
        {
            "category":"Retail",
            "subcategory":"Self-service Laundry",
            "type":"Services"
        }
    ],
    "sg:phone":"+1 704 637 3969",
    "sg:postcode":"28146",
    "sg:province":"NC",
    "sg:tags":[
        "full",
        "coin"
    ],
    "wof:name":"Super Speed Wash",
    "wof:placetype":"venue"
},
  "geometry": {"coordinates":[-80.45798499999999,35.650128],"type":"Point"}
}