{
  "type": "Feature",
  "properties": {
    "addr:full":"1208 Casey Rd Faison NC 28341",
    "addr:housenumber":"1208",
    "addr:postcode":"28341",
    "addr:street":"Casey Rd",
    "iso:country":"US",
    "sg:address":"1208 Casey Rd",
    "sg:city":"Faison",
    "sg:classifiers":[
        {
            "category":"Farming",
            "subcategory":"Farm & Veterinary Services",
            "type":"Manufacturing & Wholesale Goods"
        }
    ],
    "sg:phone":"+1 910 594 0220",
    "sg:postcode":"28341",
    "sg:province":"NC",
    "sg:tags":[
        "breeder",
        "livestock"
    ],
    "wof:name":"Carolina Packers & Bode Assoc",
    "wof:placetype":"venue"
},
  "geometry": {"coordinates":[-78.269902,35.161908],"type":"Point"}
}