{
  "type": "Feature",
  "properties": {
    "addr:full":"700 Biltmore Ave Asheville NC 28803",
    "addr:housenumber":"700",
    "addr:postcode":"28803",
    "addr:street":"Biltmore Ave",
    "iso:country":"US",
    "sg:address":"700 Biltmore Ave",
    "sg:city":"Asheville",
    "sg:classifiers":[
        {
            "category":"Real Estate",
            "subcategory":"Real Estate Operator",
            "type":"Services"
        }
    ],
    "sg:phone":"+1 828 252 6158",
    "sg:postcode":"28803",
    "sg:province":"NC",
    "sg:tags":[
        "apartment",
        "complex"
    ],
    "wof:name":"Biltmore Garden Apartments",
    "wof:placetype":"venue"
},
  "geometry": {"coordinates":[-82.545101,35.571931],"type":"Point"}
}