{
  "type": "Feature",
  "properties": {
    "addr:full":"991 Lake Forest Ct Eden NC 27288",
    "addr:housenumber":"991",
    "addr:postcode":"27288",
    "addr:street":"Lake Forest Ct",
    "iso:country":"US",
    "sg:address":"991 Lake Forest Ct",
    "sg:city":"Eden",
    "sg:classifiers":[
        {
            "category":"Banks & Credit Unions",
            "subcategory":"Financial Services",
            "type":"Services"
        }
    ],
    "sg:phone":"+1 336 627 9403",
    "sg:postcode":"27288",
    "sg:province":"NC",
    "sg:tags":[
        "trust",
        "management"
    ],
    "wof:name":"Bennett Family Partnership",
    "wof:placetype":"venue"
},
  "geometry": {"coordinates":[-79.736182,36.477838],"type":"Point"}
}