{
  "type": "Feature",
  "properties": {
    "addr:full":"5500 McNeely Dr Raleigh NC 27612",
    "addr:housenumber":"5500",
    "addr:postcode":"27612",
    "addr:street":"Mcneely Dr",
    "iso:country":"US",
    "sg:address":"5500 McNeely Dr",
    "sg:city":"Raleigh",
    "sg:classifiers":[
        {
            "category":"Professional",
            "type":"Services"
        }
    ],
    "sg:phone":"+1   ",
    "sg:postcode":"27612",
    "sg:province":"NC",
    "wof:name":"Cityscape Consultants Inc",
    "wof:placetype":"venue"
},
  "geometry": {"coordinates":[-78.71168,35.853702],"type":"Point"}
}