{
  "type": "Feature",
  "properties": {
    "iso:country":"US",
    "sg:address":"1035 Simpson Ditch Rd",
    "sg:city":"Elizabeth City",
    "sg:classifiers":[
        {
            "category":"Personal",
            "subcategory":"Barber",
            "type":"Services"
        }
    ],
    "sg:phone":"+1   ",
    "sg:postcode":"27909",
    "sg:province":"NC",
    "sg:tags":[
        "shop"
    ],
    "wof:name":"Jones Barber Shop",
    "wof:placetype":"venue"
},
  "geometry": {"coordinates":[-76.260819,36.252642],"type":"Point"}
}