{
  "type": "Feature",
  "properties": {
    "iso:country":"US",
    "sg:address":"3516 Carolina Beach Rd",
    "sg:city":"Wilmington",
    "sg:classifiers":[
        {
            "category":"Shopping",
            "subcategory":"Bicycles & Sporting Goods",
            "type":"Retail Goods"
        }
    ],
    "sg:phone":"+1 910 799 5992",
    "sg:postcode":"28412",
    "sg:province":"NC",
    "sg:tags":[
        "surfboard"
    ],
    "wof:name":"Havoc Surf Co",
    "wof:placetype":"venue"
},
  "geometry": {"coordinates":[-77.929987,34.183884],"type":"Point"}
}