{
  "type": "Feature",
  "properties": {
    "addr:full":"174 E Main St Franklin NC 28734",
    "addr:housenumber":"174",
    "addr:postcode":"nc 28734",
    "addr:street":"E Main St",
    "iso:country":"US",
    "sg:address":"174 E Main St",
    "sg:city":"Franklin",
    "sg:classifiers":[
        {
            "category":"Personal",
            "subcategory":"Beauty Salon",
            "type":"Services"
        }
    ],
    "sg:phone":"+1 828 524 5297",
    "sg:postcode":"28734",
    "sg:province":"NC",
    "wof:name":"Stella Anne's Nailz & Tan",
    "wof:placetype":"venue"
},
  "geometry": {"coordinates":[-83.37785100000001,35.182887],"type":"Point"}
}