{
  "type": "Feature",
  "properties": {
    "addr:full":"515 Murchison Rd Fayetteville NC 28301",
    "addr:housenumber":"515",
    "addr:postcode":"28301",
    "addr:street":"Murchison Rd",
    "iso:country":"US",
    "sg:address":"515 Murchison Rd",
    "sg:city":"Fayetteville",
    "sg:classifiers":[
        {
            "category":"Retail",
            "subcategory":"Funeral Services",
            "type":"Services"
        }
    ],
    "sg:phone":"+1 910 483 4290",
    "sg:postcode":"28301",
    "sg:province":"NC",
    "sg:tags":[
        "director"
    ],
    "wof:name":"Paye Funeral Homes & Memorial",
    "wof:placetype":"venue"
},
  "geometry": {"coordinates":[-78.88896099999999,35.063945],"type":"Point"}
}