{
  "type": "Feature",
  "properties": {
    "iso:country":"US",
    "sg:address":"3543 Robinhood Rd",
    "sg:city":"Winston Salem",
    "sg:classifiers":[
        {
            "category":"Organizations",
            "subcategory":"Religious Organization",
            "type":"Services"
        }
    ],
    "sg:phone":"+1   ",
    "sg:postcode":"27106",
    "sg:province":"NC",
    "wof:name":"Dial-A-Devotion",
    "wof:placetype":"venue"
},
  "geometry": {"coordinates":[-80.320892,36.120383],"type":"Point"}
}