{
  "type": "Feature",
  "properties": {
    "addr:full":"671 Brevard Rd Asheville NC 28806",
    "addr:housenumber":"671",
    "addr:postcode":"28806",
    "addr:street":"Brevard Rd",
    "iso:country":"US",
    "sg:address":"671 Brevard Rd",
    "sg:city":"Asheville",
    "sg:classifiers":[
        {
            "category":"Health Services",
            "subcategory":"Clinic",
            "type":"Services"
        }
    ],
    "sg:phone":"+1 828 665 3944",
    "sg:postcode":"28806",
    "sg:province":"NC",
    "sg:tags":[
        "home"
    ],
    "wof:name":"Visiting Angels-Western Nc",
    "wof:placetype":"venue"
},
  "geometry": {"coordinates":[-82.597393,35.544255],"type":"Point"}
}