{
  "type": "Feature",
  "properties": {
    "iso:country":"US",
    "sg:address":"1001 W Innes St",
    "sg:city":"Salisbury",
    "sg:classifiers":[
        {
            "category":"Real Estate",
            "subcategory":"Real Estate Agent",
            "type":"Services"
        }
    ],
    "sg:phone":"+1 704 633 3098",
    "sg:postcode":"28144",
    "sg:province":"NC",
    "wof:name":"Sellers & Buyers Realty Inc",
    "wof:placetype":"venue"
},
  "geometry": {"coordinates":[-80.478094,35.673879],"type":"Point"}
}