{
  "type": "Feature",
  "properties": {
    "addr:full":"4608 Pearl Rd Raleigh NC 27610",
    "addr:housenumber":"4608",
    "addr:postcode":"27610",
    "addr:street":"Pearl Rd",
    "iso:country":"US",
    "sg:address":"4608 Pearl Rd",
    "sg:city":"Raleigh",
    "sg:classifiers":[
        {
            "category":"Organizations",
            "subcategory":"Religious Organization",
            "type":"Services"
        }
    ],
    "sg:phone":"+1   ",
    "sg:postcode":"27610",
    "sg:province":"NC",
    "wof:name":"Solid Rock Baptist Church",
    "wof:placetype":"venue"
},
  "geometry": {"coordinates":[-78.561701,35.72592],"type":"Point"}
}