{
  "type": "Feature",
  "properties": {
    "addr:full":"894 Elm St Fayetteville NC 28303",
    "addr:housenumber":"894",
    "addr:postcode":"28303",
    "addr:street":"Elm St",
    "iso:country":"US",
    "sg:address":"894 Elm St",
    "sg:city":"Fayetteville",
    "sg:classifiers":[
        {
            "category":"Professional",
            "subcategory":"Employment Agencies",
            "type":"Services"
        }
    ],
    "sg:phone":"+1 910 437 5959",
    "sg:postcode":"28303",
    "sg:province":"NC",
    "sg:tags":[
        "temp"
    ],
    "wof:name":"Loase Enterprises Inc",
    "wof:placetype":"venue"
},
  "geometry": {"coordinates":[-78.925957,35.074576],"type":"Point"}
}