{
  "type": "Feature",
  "properties": {
    "iso:country":"US",
    "sg:address":"161 Indian Springs Trl",
    "sg:city":"Hendersonville",
    "sg:classifiers":[
        {
            "category":"Real Estate",
            "subcategory":"Real Estate Operator",
            "type":"Services"
        }
    ],
    "sg:phone":"+1 828 685 9755",
    "sg:postcode":"28792",
    "sg:province":"NC",
    "sg:tags":[
        "mobile",
        "home",
        "site"
    ],
    "wof:name":"Indian Springs Park",
    "wof:placetype":"venue"
},
  "geometry": {"coordinates":[-82.374584,35.37466],"type":"Point"}
}