{
  "type": "Feature",
  "properties": {
    "addr:full":"506 Bainbridge Rd Stedman NC 28391",
    "addr:housenumber":"506",
    "addr:postcode":"28391",
    "addr:street":"Bainbridge Rd",
    "iso:country":"US",
    "sg:address":"506 Bainbridge Rd",
    "sg:city":"Stedman",
    "sg:classifiers":[
        {
            "category":"Restaurant",
            "type":"Food & Drink"
        }
    ],
    "sg:phone":"+1 910 223 0796",
    "sg:postcode":"28391",
    "sg:province":"NC",
    "sg:tags":[
        "eating"
    ],
    "wof:name":"China Grove Disciple Church",
    "wof:placetype":"venue"
},
  "geometry": {"coordinates":[-78.69185299999999,35.018778],"type":"Point"}
}