{
  "type": "Feature",
  "properties": {
    "iso:country":"US",
    "sg:address":"935 Abington Rd",
    "sg:city":"Lenoir",
    "sg:classifiers":[
        {
            "category":"Wholesale",
            "subcategory":"Sporting Goods",
            "type":"Manufacturing & Wholesale Goods"
        }
    ],
    "sg:phone":"+1 828 758 8337",
    "sg:postcode":"28645",
    "sg:province":"NC",
    "sg:tags":[
        "equipment",
        "billiard",
        "supply"
    ],
    "wof:name":"Dixie Novelty & Billiards",
    "wof:placetype":"venue"
},
  "geometry": {"coordinates":[-81.602626,35.916593],"type":"Point"}
}