{
  "type": "Feature",
  "properties": {
    "addr:full":"811 W Main St Beulaville NC 28518",
    "addr:housenumber":"811",
    "addr:postcode":"28518",
    "addr:street":"W Main St",
    "iso:country":"US",
    "sg:address":"811 W Main St",
    "sg:city":"Beulaville",
    "sg:classifiers":[
        {
            "category":"Restaurant",
            "type":"Food & Drink"
        }
    ],
    "sg:phone":"+1 910 298 3346",
    "sg:postcode":"28518",
    "sg:province":"NC",
    "wof:name":"Pizza Village Of Beulaville",
    "wof:placetype":"venue"
},
  "geometry": {"coordinates":[-77.78291299999999,34.925344],"type":"Point"}
}