{
  "type": "Feature",
  "properties": {
    "addr:full":"2125 N Church St Burlington NC 27217",
    "addr:housenumber":"2125",
    "addr:postcode":"27217",
    "addr:street":"N Church St",
    "iso:country":"US",
    "sg:address":"2125 N Church St",
    "sg:city":"Burlington",
    "sg:classifiers":[
        {
            "category":"Shopping",
            "subcategory":"Discount & Variety Stores",
            "type":"Retail Goods"
        }
    ],
    "sg:phone":"+1 336 229 1360",
    "sg:postcode":"27217",
    "sg:province":"NC",
    "wof:name":"Dollar General",
    "wof:placetype":"venue"
},
  "geometry": {"coordinates":[-79.39956599999999,36.093862],"type":"Point"}
}