{
  "type": "Feature",
  "properties": {
    "addr:full":"716 W Haven Blvd Rocky Mount NC 27803",
    "addr:housenumber":"716",
    "addr:postcode":"27803",
    "addr:street":"W Haven Blvd",
    "iso:country":"US",
    "sg:address":"716 W Haven Blvd",
    "sg:city":"Rocky Mount",
    "sg:classifiers":[
        {
            "category":"Retail",
            "subcategory":"Laundry & Dry Cleaning",
            "type":"Services"
        }
    ],
    "sg:phone":"+1   ",
    "sg:postcode":"27803",
    "sg:province":"NC",
    "wof:name":"Rocky Mount Carpet Cleaners",
    "wof:placetype":"venue"
},
  "geometry": {"coordinates":[-77.810993,35.935621],"type":"Point"}
}