{
  "type": "Feature",
  "properties": {
    "addr:full":"3145 S Tryon St Charlotte NC 28217",
    "addr:housenumber":"3145",
    "addr:postcode":"28217",
    "addr:street":"S Tryon St",
    "iso:country":"US",
    "sg:address":"3145 S Tryon St",
    "sg:city":"Charlotte",
    "sg:classifiers":[
        {
            "category":"Local Transit",
            "type":"Transportation"
        },
        {
            "category":"Government",
            "subcategory":"Office",
            "type":"Public Place"
        }
    ],
    "sg:phone":"+1 704 336 3366",
    "sg:postcode":"28217",
    "sg:province":"NC",
    "sg:tags":[
        "city",
        "line",
        "program"
    ],
    "sg:website":"www.charmeck.org",
    "wof:name":"Charlotte Area Transit Systems",
    "wof:placetype":"venue"
},
  "geometry": {"coordinates":[-80.874426,35.199441],"type":"Point"}
}