{
  "type": "Feature",
  "properties": {
    "iso:country":"US",
    "sg:address":"523 Green Willow Cir",
    "sg:city":"Wendell",
    "sg:classifiers":[
        {
            "category":"Professional",
            "type":"Services"
        }
    ],
    "sg:phone":"+1 919 365 3441",
    "sg:postcode":"27591",
    "sg:province":"NC",
    "sg:tags":[
        "establishment"
    ],
    "wof:name":"Greenwillow Lift Station",
    "wof:placetype":"venue"
},
  "geometry": {"coordinates":[-78.36918799999999,35.788886],"type":"Point"}
}