{
  "type": "Feature",
  "properties": {
    "addr:full":"508 E Chatham St Cary NC 27511",
    "addr:housenumber":"508",
    "addr:postcode":"27511",
    "addr:street":"E Chatham St",
    "iso:country":"US",
    "sg:address":"508 E Chatham St",
    "sg:city":"Cary",
    "sg:classifiers":[
        {
            "category":"Retail",
            "subcategory":"Auto Repair",
            "type":"Services"
        },
        {
            "category":"Government",
            "subcategory":"Office",
            "type":"Public Place"
        }
    ],
    "sg:phone":"+1 919 469 8665",
    "sg:postcode":"27511",
    "sg:province":"NC",
    "sg:tags":[
        "smog",
        "oil",
        "check",
        "change"
    ],
    "sg:website":"caryautoinspectionandrepair.net",
    "wof:name":"Cary Auto Inspection and Repair",
    "wof:placetype":"venue"
},
  "geometry": {"coordinates":[-78.77089100000001,35.79014],"type":"Point"}
}