{
  "type": "Feature",
  "properties": {
    "addr:full":"1003 Hemlock Dr Shelby NC 28150",
    "addr:housenumber":"1003",
    "addr:postcode":"28150",
    "addr:street":"Hemlock Dr",
    "iso:country":"US",
    "sg:address":"1003 Hemlock Dr",
    "sg:city":"Shelby",
    "sg:classifiers":[
        {
            "category":"Shopping",
            "subcategory":"Clothing, Apparel, & Fashions",
            "type":"Retail Goods"
        }
    ],
    "sg:phone":"+1 704 482 1065",
    "sg:postcode":"28150",
    "sg:province":"NC",
    "wof:name":"Lessies Fashions",
    "wof:placetype":"venue"
},
  "geometry": {"coordinates":[-81.526,35.308665],"type":"Point"}
}