{
  "type": "Feature",
  "properties": {
    "addr:full":"112 Underwood St Clinton NC 28328",
    "addr:housenumber":"112",
    "addr:postcode":"28328",
    "addr:street":"Underwood St",
    "iso:country":"US",
    "sg:address":"112 Underwood St",
    "sg:city":"Clinton",
    "sg:classifiers":[
        {
            "category":"Personal",
            "subcategory":"Beauty Salon",
            "type":"Services"
        }
    ],
    "sg:phone":"+1 910 592 3131",
    "sg:postcode":"28328",
    "sg:province":"NC",
    "wof:name":"Vicki's Beauty Salon",
    "wof:placetype":"venue"
},
  "geometry": {"coordinates":[-78.313587,35.007283],"type":"Point"}
}