{
  "type": "Feature",
  "properties": {
    "addr:full":"1057 Yadkinville Rd Mocksville NC 27028",
    "addr:housenumber":"1057",
    "addr:postcode":"27028",
    "addr:street":"Yadkinville Rd",
    "iso:country":"US",
    "sg:address":"1057 Yadkinville Rd",
    "sg:city":"Mocksville",
    "sg:classifiers":[
        {
            "category":"Wholesale",
            "subcategory":"Electrical",
            "type":"Manufacturing & Wholesale Goods"
        }
    ],
    "sg:phone":"+1 336 751 0528",
    "sg:postcode":"27028",
    "sg:province":"NC",
    "sg:tags":[
        "mobile",
        "telephone"
    ],
    "wof:name":"Yadkin Valley Telecom",
    "wof:placetype":"venue"
},
  "geometry": {"coordinates":[-80.579859,35.91126],"type":"Point"}
}