{
  "type": "Feature",
  "properties": {
    "addr:full":"4083 Westfield Rd Mount Airy NC 27030",
    "addr:housenumber":"4083",
    "addr:postcode":"27030",
    "addr:street":"Westfield Rd",
    "iso:country":"US",
    "sg:address":"4083 Westfield Rd",
    "sg:city":"Mount Airy",
    "sg:classifiers":[
        {
            "category":"Building & Trades",
            "subcategory":"Electrical",
            "type":"Services"
        }
    ],
    "sg:phone":"+1 336 351 3524",
    "sg:postcode":"27030",
    "sg:province":"NC",
    "sg:tags":[
        "electrical",
        "contractor"
    ],
    "wof:name":"Cooke Electric Inc",
    "wof:placetype":"venue"
},
  "geometry": {"coordinates":[-80.51615,36.506456],"type":"Point"}
}