{
  "type": "Feature",
  "properties": {
    "iso:country":"US",
    "sg:address":"2749 Hickory Blvd",
    "sg:city":"Hudson",
    "sg:classifiers":[
        {
            "category":"Shopping",
            "subcategory":"Gifts & Souvenirs",
            "type":"Retail Goods"
        }
    ],
    "sg:phone":"+1 828 728 4735",
    "sg:postcode":"28638",
    "sg:province":"NC",
    "sg:tags":[
        "collectible"
    ],
    "wof:name":"B & L Collectables",
    "wof:placetype":"venue"
},
  "geometry": {"coordinates":[-81.487165,35.859036],"type":"Point"}
}