{
  "type": "Feature",
  "properties": {
    "addr:full":"8891 State Hwy 11 Willard NC 28478",
    "addr:housenumber":"8891",
    "addr:postcode":"28478",
    "addr:street":"State Hwy 11",
    "iso:country":"US",
    "sg:address":"8891 State Hwy 11",
    "sg:city":"Willard",
    "sg:classifiers":[
        {
            "category":"Building & Trades",
            "subcategory":"Construction",
            "type":"Services"
        }
    ],
    "sg:phone":"+1 910 285 6560",
    "sg:postcode":"28478",
    "sg:province":"NC",
    "sg:tags":[
        "contractor"
    ],
    "wof:name":"Cages Gutter Specialist",
    "wof:placetype":"venue"
},
  "geometry": {"coordinates":[-77.976713,34.691379],"type":"Point"}
}