{
  "type": "Feature",
  "properties": {
    "addr:full":"2459 US Hwy 258 Kinston NC 28504",
    "addr:housenumber":"2459",
    "addr:postcode":"28504",
    "addr:street":"Us Hwy 258",
    "iso:country":"US",
    "sg:address":"2459 US Hwy 258",
    "sg:city":"Kinston",
    "sg:classifiers":[
        {
            "category":"Restaurant",
            "type":"Food & Drink"
        }
    ],
    "sg:phone":"+1 252 520 0025",
    "sg:postcode":"28504",
    "sg:province":"NC",
    "wof:name":"Little J's Pizza & Subs",
    "wof:placetype":"venue"
},
  "geometry": {"coordinates":[-77.647223,35.3027],"type":"Point"}
}