{
  "type": "Feature",
  "properties": {
    "iso:country":"US",
    "sg:address":"242 Burton Rd",
    "sg:city":"Reidsville",
    "sg:classifiers":[
        {
            "category":"Building & Trades",
            "subcategory":"Construction",
            "type":"Services"
        }
    ],
    "sg:phone":"+1 336 349 4761",
    "sg:postcode":"27320",
    "sg:province":"NC",
    "sg:tags":[
        "house"
    ],
    "wof:name":"Bratton Bobby L Const Co",
    "wof:placetype":"venue"
},
  "geometry": {"coordinates":[-79.581738,36.428763],"type":"Point"}
}