{
  "type": "Feature",
  "properties": {
    "iso:country":"US",
    "sg:address":"15105 John J Delaney Dr",
    "sg:city":"Charlotte",
    "sg:classifiers":[
        {
            "category":"Organizations",
            "subcategory":"Professional Association",
            "type":"Services"
        }
    ],
    "sg:phone":"+1 704 542 4121",
    "sg:postcode":"28277",
    "sg:province":"NC",
    "sg:tags":[
        "business",
        "trade"
    ],
    "wof:name":"Paramount Building Co",
    "wof:placetype":"venue"
},
  "geometry": {"coordinates":[-80.84825600000001,35.05237],"type":"Point"}
}