{
  "type": "Feature",
  "properties": {
    "addr:full":"500 Carolina Ave Thomasville NC 27360",
    "addr:housenumber":"500",
    "addr:postcode":"27360",
    "addr:street":"Carolina Ave",
    "iso:country":"US",
    "sg:address":"500 Carolina Ave",
    "sg:city":"Thomasville",
    "sg:classifiers":[
        {
            "category":"Manufacturing",
            "subcategory":"Furniture",
            "type":"Manufacturing & Wholesale Goods"
        }
    ],
    "sg:phone":"+1 336 472 7700",
    "sg:postcode":"27360",
    "sg:province":"NC",
    "sg:tags":[
        "household"
    ],
    "wof:name":"Classics By Casa Bique",
    "wof:placetype":"venue"
},
  "geometry": {"coordinates":[-80.06768700000001,35.880742],"type":"Point"}
}