{
  "type": "Feature",
  "properties": {
    "iso:country":"US",
    "sg:address":"821 Tomlin Mill Rd",
    "sg:city":"Statesville",
    "sg:classifiers":[
        {
            "category":"Organizations",
            "subcategory":"Religious Organization",
            "type":"Services"
        }
    ],
    "sg:phone":"+1   ",
    "sg:postcode":"28625",
    "sg:province":"NC",
    "wof:name":"Northside Baptist Church",
    "wof:placetype":"venue"
},
  "geometry": {"coordinates":[-80.839401,35.915065],"type":"Point"}
}