{
  "type": "Feature",
  "properties": {
    "iso:country":"US",
    "sg:address":"412 W 3rd St",
    "sg:city":"Princeton",
    "sg:classifiers":[
        {
            "category":"Social Services",
            "type":"Services"
        }
    ],
    "sg:phone":"+1 919 936 2184",
    "sg:postcode":"27569",
    "sg:province":"NC",
    "sg:tags":[
        "senior",
        "citizen"
    ],
    "wof:name":"Princeton Senior Center",
    "wof:placetype":"venue"
},
  "geometry": {"coordinates":[-78.166315,35.465689],"type":"Point"}
}