{
  "type": "Feature",
  "properties": {
    "iso:country":"US",
    "sg:address":"916 Benfield Dr",
    "sg:city":"Greensboro",
    "sg:classifiers":[
        {
            "category":"Home & Garden",
            "subcategory":"Home Furnishings",
            "type":"Retail Goods"
        }
    ],
    "sg:phone":"+1 336 316 0557",
    "sg:postcode":"27410",
    "sg:province":"NC",
    "wof:name":"Blind Ambition",
    "wof:placetype":"venue"
},
  "geometry": {"coordinates":[-79.844937,36.090693],"type":"Point"}
}