{
  "type": "Feature",
  "properties": {
    "addr:full":"3040 University Pkwy Winston Salem NC 27105",
    "addr:housenumber":"3040",
    "addr:postcode":"27105",
    "addr:street":"University Pkwy",
    "iso:country":"US",
    "sg:address":"3040 University Pkwy",
    "sg:city":"Winston Salem",
    "sg:classifiers":[
        {
            "category":"Restaurant",
            "type":"Food & Drink"
        }
    ],
    "sg:menulink":"http://www.allmenus.com/nc/winston/73408-pizza-hut/menu/",
    "sg:phone":"+1 336 724 0494",
    "sg:postcode":"27105",
    "sg:province":"NC",
    "sg:tags":[
        "american",
        "pizza"
    ],
    "wof:name":"Pizza Hut",
    "wof:placetype":"venue"
},
  "geometry": {"coordinates":[-80.26238600000001,36.130069],"type":"Point"}
}