{
  "type": "Feature",
  "properties": {
    "addr:full":"229 Trade Ave NW Hickory NC 28601",
    "addr:housenumber":"229",
    "addr:postcode":"28601",
    "addr:street":"Trade Ave Nw",
    "iso:country":"US",
    "sg:address":"229 Trade Ave NW",
    "sg:city":"Hickory",
    "sg:classifiers":[
        {
            "category":"Real Estate",
            "subcategory":"Architect",
            "type":"Services"
        }
    ],
    "sg:phone":"+1 828 322 3529",
    "sg:postcode":"28601",
    "sg:province":"NC",
    "wof:name":"J Michael Robbins",
    "wof:placetype":"venue"
},
  "geometry": {"coordinates":[-81.340703,35.732679],"type":"Point"}
}