{
  "type": "Feature",
  "properties": {
    "addr:full":"5613 US Hwy 70 Durham NC 27705",
    "addr:housenumber":"5613",
    "addr:postcode":"27705",
    "addr:street":"Us Hwy 70",
    "iso:country":"US",
    "sg:address":"5613 US Hwy 70",
    "sg:city":"Durham",
    "sg:classifiers":[
        {
            "category":"Retail",
            "subcategory":"Repair Shop",
            "type":"Services"
        }
    ],
    "sg:phone":"+1 919 383 1497",
    "sg:postcode":"27705",
    "sg:province":"NC",
    "sg:tags":[
        "hardware"
    ],
    "wof:name":"Ragan Saw & Mower Service",
    "wof:placetype":"venue"
},
  "geometry": {"coordinates":[-79.003012,36.034932],"type":"Point"}
}