{
  "type": "Feature",
  "properties": {
    "iso:country":"US",
    "sg:address":"1528 N Green St",
    "sg:city":"Morganton",
    "sg:classifiers":[
        {
            "category":"Autos & Motor Vehicles",
            "subcategory":"Auto Supplies",
            "type":"Retail Goods"
        }
    ],
    "sg:phone":"+1 828 433 6050",
    "sg:postcode":"28655",
    "sg:province":"NC",
    "sg:tags":[
        "automotive",
        "accessory"
    ],
    "wof:name":"Go Fast Engrg & Off Rd Ctr",
    "wof:placetype":"venue"
},
  "geometry": {"coordinates":[-81.734225,35.76042],"type":"Point"}
}