{
  "type": "Feature",
  "properties": {
    "addr:full":"2005 Beatties Ford Rd Charlotte NC 28216",
    "addr:housenumber":"2005",
    "addr:postcode":"28216",
    "addr:street":"Beatties Ford Rd",
    "iso:country":"US",
    "sg:address":"2005 Beatties Ford Rd",
    "sg:city":"Charlotte",
    "sg:classifiers":[
        {
            "category":"Organizations",
            "subcategory":"Religious Organization",
            "type":"Services"
        }
    ],
    "sg:phone":"+1   ",
    "sg:postcode":"28216",
    "sg:province":"NC",
    "wof:name":"Grace Tabernacle Of Prayer",
    "wof:placetype":"venue"
},
  "geometry": {"coordinates":[-80.854989,35.26185],"type":"Point"}
}