{
  "type": "Feature",
  "properties": {
    "addr:full":"237 White Oak Ln Plymouth NC 27962",
    "addr:housenumber":"237",
    "addr:postcode":"27962",
    "addr:street":"White Oak Ln",
    "iso:country":"US",
    "sg:address":"237 White Oak Ln",
    "sg:city":"Plymouth",
    "sg:classifiers":[
        {
            "category":"Building & Trades",
            "subcategory":"Landscaping Services",
            "type":"Services"
        }
    ],
    "sg:phone":"+1 252 793 5242",
    "sg:postcode":"27962",
    "sg:province":"NC",
    "sg:tags":[
        "landscape"
    ],
    "wof:name":"Ange E  Burton Jr",
    "wof:placetype":"venue"
},
  "geometry": {"coordinates":[-76.716401,35.833906],"type":"Point"}
}