{
  "type": "Feature",
  "properties": {
    "addr:full":"8220 University Executive Park Dr Charlotte NC 28262",
    "addr:housenumber":"8220",
    "addr:postcode":"28262",
    "addr:street":"University Executive Park Dr",
    "iso:country":"US",
    "sg:address":"8220 University Executive Park Dr",
    "sg:city":"Charlotte",
    "sg:classifiers":[
        {
            "category":"Social Services",
            "subcategory":"Job Training",
            "type":"Services"
        }
    ],
    "sg:phone":"+1 704 547 1129",
    "sg:postcode":"28262",
    "sg:province":"NC",
    "sg:tags":[
        "rehabilitation"
    ],
    "sg:website":"www.novacare.com",
    "wof:name":"Nova Care",
    "wof:placetype":"venue"
},
  "geometry": {"coordinates":[-80.75492199999999,35.298809],"type":"Point"}
}