{
  "type": "Feature",
  "properties": {
    "iso:country":"US",
    "sg:address":"1475 N Bridge St",
    "sg:city":"Elkin",
    "sg:classifiers":[
        {
            "category":"Shopping",
            "subcategory":"Pharmacy",
            "type":"Retail Goods"
        }
    ],
    "sg:phone":"+1 336 526 6102",
    "sg:postcode":"28621",
    "sg:province":"NC",
    "wof:name":"Eckerd Drugs",
    "wof:placetype":"venue"
},
  "geometry": {"coordinates":[-80.853624,36.270711],"type":"Point"}
}