{
  "type": "Feature",
  "properties": {
    "addr:full":"457 Baywood Rd Fayetteville NC 28312",
    "addr:housenumber":"457",
    "addr:postcode":"28312",
    "addr:street":"Baywood Rd",
    "iso:country":"US",
    "sg:address":"457 Baywood Rd",
    "sg:city":"Fayetteville",
    "sg:classifiers":[
        {
            "category":"Building & Trades",
            "subcategory":"Construction",
            "type":"Services"
        }
    ],
    "sg:phone":"+1 910 485 0925",
    "sg:postcode":"28312",
    "sg:province":"NC",
    "sg:tags":[
        "builder",
        "operative"
    ],
    "wof:name":"Landry Loyd A",
    "wof:placetype":"venue"
},
  "geometry": {"coordinates":[-78.772515,35.046105],"type":"Point"}
}