{
  "type": "Feature",
  "properties": {
    "addr:full":"803 W Salisbury St Asheboro NC 27203",
    "addr:housenumber":"803",
    "addr:postcode":"27203",
    "addr:street":"W Salisbury St",
    "iso:country":"US",
    "sg:address":"803 W Salisbury St",
    "sg:city":"Asheboro",
    "sg:classifiers":[
        {
            "category":"Personal",
            "subcategory":"Beauty Salon",
            "type":"Services"
        }
    ],
    "sg:phone":"+1   ",
    "sg:postcode":"27203",
    "sg:province":"NC",
    "sg:tags":[
        "shop"
    ],
    "wof:name":"Styles of Essence",
    "wof:placetype":"venue"
},
  "geometry": {"coordinates":[-79.826843,35.70855],"type":"Point"}
}