{
  "type": "Feature",
  "properties": {
    "iso:country":"US",
    "sg:address":"251 Ross St",
    "sg:city":"Asheboro",
    "sg:classifiers":[
        {
            "category":"Manufacturing",
            "subcategory":"Lumber",
            "type":"Manufacturing & Wholesale Goods"
        }
    ],
    "sg:phone":"+1 336 625 2195",
    "sg:postcode":"27203",
    "sg:province":"NC",
    "sg:tags":[
        "planing",
        "mills",
        "sawmill"
    ],
    "wof:name":"Hedgecock Builders Supply Co",
    "wof:placetype":"venue"
},
  "geometry": {"coordinates":[-79.81874500000001,35.710103],"type":"Point"}
}