{
  "type": "Feature",
  "properties": {
    "iso:country":"US",
    "sg:address":"385 Knotts Island Rd",
    "sg:city":"Knotts Island",
    "sg:classifiers":[
        {
            "category":"Government",
            "subcategory":"Post Office",
            "type":"Public Place"
        }
    ],
    "sg:phone":"+1 252 429 3252",
    "sg:postcode":"27950",
    "sg:province":"NC",
    "wof:name":"US Post Office",
    "wof:placetype":"venue"
},
  "geometry": {"coordinates":[-75.92756,36.537172],"type":"Point"}
}