{
  "type": "Feature",
  "properties": {
    "iso:country":"US",
    "sg:address":"500 N 35th St",
    "sg:city":"Morehead City",
    "sg:classifiers":[
        {
            "category":"Health Services",
            "subcategory":"Doctor",
            "type":"Services"
        }
    ],
    "sg:phone":"+1   ",
    "sg:postcode":"28557",
    "sg:province":"NC",
    "sg:tags":[
        "medical"
    ],
    "wof:name":"Broad Street Clinic Foundation",
    "wof:placetype":"venue"
},
  "geometry": {"coordinates":[-76.754127,34.73075],"type":"Point"}
}