{
  "type": "Feature",
  "properties": {
    "addr:full":"106 Anna Lake Ln Cary NC 27513",
    "addr:housenumber":"106",
    "addr:postcode":"27513",
    "addr:street":"Anna Lake Ln",
    "iso:country":"US",
    "sg:address":"106 Anna Lake Ln",
    "sg:city":"Cary",
    "sg:classifiers":[
        {
            "category":"Professional",
            "subcategory":"Management & Consulting",
            "type":"Services"
        }
    ],
    "sg:phone":"+1   ",
    "sg:postcode":"27513",
    "sg:province":"NC",
    "sg:tags":[
        "thermal",
        "storage",
        "engineering"
    ],
    "wof:name":"Peter Carr",
    "wof:placetype":"venue"
},
  "geometry": {"coordinates":[-78.798063,35.80542],"type":"Point"}
}