{
  "type": "Feature",
  "properties": {
    "iso:country":"US",
    "sg:address":"251 Fairway Dr",
    "sg:city":"Asheville",
    "sg:classifiers":[
        {
            "category":"Shopping",
            "type":"Retail Goods"
        }
    ],
    "sg:phone":"+1 828 299 0596",
    "sg:postcode":"28805",
    "sg:province":"NC",
    "sg:tags":[
        "art",
        "gallery",
        "dealer"
    ],
    "wof:name":"Art Atelier",
    "wof:placetype":"venue"
},
  "geometry": {"coordinates":[-82.50424700000001,35.577024],"type":"Point"}
}