{
  "type": "Feature",
  "properties": {
    "iso:country":"US",
    "sg:address":"1129 N Fayetteville St",
    "sg:city":"Asheboro",
    "sg:classifiers":[
        {
            "category":"Professional",
            "subcategory":"Business Services",
            "type":"Services"
        }
    ],
    "sg:phone":"+1 336 683 9446",
    "sg:postcode":"27203",
    "sg:province":"NC",
    "sg:tags":[
        "merchandising"
    ],
    "wof:name":"Novedades El Surtidor",
    "wof:placetype":"venue"
},
  "geometry": {"coordinates":[-79.808913,35.726511],"type":"Point"}
}