{
  "type": "Feature",
  "properties": {
    "iso:country":"US",
    "sg:address":"125 S John St",
    "sg:city":"Goldsboro",
    "sg:classifiers":[
        {
            "category":"Social Services",
            "subcategory":"Child Care",
            "type":"Services"
        }
    ],
    "sg:phone":"+1 919 735 8879",
    "sg:postcode":"28530",
    "sg:province":"NC",
    "wof:name":"First Baptist Church Camp",
    "wof:placetype":"venue"
},
  "geometry": {"coordinates":[-77.995969,35.381646],"type":"Point"}
}