{
  "type": "Feature",
  "properties": {
    "iso:country":"US",
    "sg:address":"1640 S Main St",
    "sg:city":"Laurinburg",
    "sg:classifiers":[
        {
            "category":"Cinema",
            "subcategory":"Movie Rental",
            "type":"Entertainment"
        }
    ],
    "sg:phone":"+1 910 610 4235",
    "sg:postcode":"28352",
    "sg:province":"NC",
    "sg:tags":[
        "leasing",
        "video",
        "disc",
        "tape"
    ],
    "sg:website":"www.moviegallery.com",
    "wof:name":"Movie Gallery",
    "wof:placetype":"venue"
},
  "geometry": {"coordinates":[-79.474806,34.755765],"type":"Point"}
}