{
  "type": "Feature",
  "properties": {
    "iso:country":"US",
    "sg:address":"101 Chadwick Square Ct",
    "sg:city":"Hendersonville",
    "sg:classifiers":[
        {
            "category":"Building & Trades",
            "subcategory":"Construction",
            "type":"Services"
        }
    ],
    "sg:phone":"+1 828 692 6102",
    "sg:postcode":"28739",
    "sg:province":"NC",
    "sg:tags":[
        "house"
    ],
    "wof:name":"Woodridge View Homes",
    "wof:placetype":"venue"
},
  "geometry": {"coordinates":[-82.456723,35.302546],"type":"Point"}
}