{
  "type": "Feature",
  "properties": {
    "addr:full":"1626 N Main St Salisbury NC 28144",
    "addr:housenumber":"1626",
    "addr:postcode":"28144",
    "addr:street":"N Main St",
    "iso:country":"US",
    "sg:address":"1626 N Main St",
    "sg:city":"Salisbury",
    "sg:classifiers":[
        {
            "category":"Retail",
            "subcategory":"Portrait Studio",
            "type":"Services"
        }
    ],
    "sg:phone":"+1   ",
    "sg:postcode":"28144",
    "sg:province":"NC",
    "sg:tags":[
        "photo"
    ],
    "wof:name":"Sean Meyers Photography",
    "wof:placetype":"venue"
},
  "geometry": {"coordinates":[-80.45061699999999,35.680377],"type":"Point"}
}