{
  "type": "Feature",
  "properties": {
    "iso:country":"US",
    "sg:address":"3717 National Dr",
    "sg:city":"Raleigh",
    "sg:classifiers":[
        {
            "category":"Insurance",
            "subcategory":"Insurance Agent",
            "type":"Services"
        }
    ],
    "sg:phone":"+1 919 571 2984",
    "sg:postcode":"27612",
    "sg:province":"NC",
    "wof:name":"Richard H Mason Jr",
    "wof:placetype":"venue"
},
  "geometry": {"coordinates":[-78.66582699999999,35.83167],"type":"Point"}
}