{
  "type": "Feature",
  "properties": {
    "addr:full":"1067 Trollingwood Hawfields Rd Mebane NC 27302",
    "addr:housenumber":"1067",
    "addr:postcode":"27302",
    "addr:street":"Trollingwood Hawfields Rd",
    "iso:country":"US",
    "sg:address":"1067 Trollingwood Hawfields Rd",
    "sg:city":"Mebane",
    "sg:classifiers":[
        {
            "category":"Professional",
            "subcategory":"Employment Agencies",
            "type":"Services"
        }
    ],
    "sg:phone":"+1 919 304 6011",
    "sg:postcode":"27302",
    "sg:province":"NC",
    "sg:tags":[
        "co",
        "fraternal"
    ],
    "wof:name":"Adecco-026205",
    "wof:placetype":"venue"
},
  "geometry": {"coordinates":[-79.316354,36.070608],"type":"Point"}
}