{
  "type": "Feature",
  "properties": {
    "addr:full":"452 Madison Rd Mocksville NC 27028",
    "addr:housenumber":"452",
    "addr:postcode":"27028",
    "addr:street":"Madison Rd",
    "iso:country":"US",
    "sg:address":"452 Madison Rd",
    "sg:city":"Mocksville",
    "sg:classifiers":[
        {
            "category":"Building & Trades",
            "subcategory":"Construction",
            "type":"Services"
        }
    ],
    "sg:phone":"+1 336 751 4726",
    "sg:postcode":"27028",
    "sg:province":"NC",
    "sg:tags":[
        "concrete",
        "contractor"
    ],
    "wof:name":"Angell Paving",
    "wof:placetype":"venue"
},
  "geometry": {"coordinates":[-80.59461400000001,35.915936],"type":"Point"}
}