{
  "type": "Feature",
  "properties": {
    "iso:country":"US",
    "sg:address":"6220 Shallowford Rd",
    "sg:city":"Lewisville",
    "sg:classifiers":[
        {
            "category":"Personal",
            "type":"Services"
        }
    ],
    "sg:phone":"+1 336 945 6187",
    "sg:postcode":"27023",
    "sg:province":"NC",
    "sg:tags":[
        "consultant",
        "wedding"
    ],
    "wof:name":"Promed Assistance Group",
    "wof:placetype":"venue"
},
  "geometry": {"coordinates":[-80.41247199999999,36.100374],"type":"Point"}
}