{
  "type": "Feature",
  "properties": {
    "iso:country":"US",
    "sg:address":"1222 Holloway St",
    "sg:city":"Durham",
    "sg:classifiers":[
        {
            "category":"Social Services",
            "subcategory":"Child Care",
            "type":"Services"
        }
    ],
    "sg:phone":"+1 919 687 0862",
    "sg:postcode":"27701",
    "sg:province":"NC",
    "sg:tags":[
        "day"
    ],
    "wof:name":"Academy Of Stars",
    "wof:placetype":"venue"
},
  "geometry": {"coordinates":[-78.878433,35.994361],"type":"Point"}
}