{
  "type": "Feature",
  "properties": {
    "iso:country":"US",
    "sg:address":"504 W 25th St",
    "sg:city":"Newton",
    "sg:classifiers":[
        {
            "category":"Manufacturing",
            "subcategory":"Metals",
            "type":"Manufacturing & Wholesale Goods"
        }
    ],
    "sg:phone":"+1 828 695 9994",
    "sg:postcode":"28658",
    "sg:province":"NC",
    "sg:tags":[
        "coating"
    ],
    "wof:name":"PCT Coating",
    "wof:placetype":"venue"
},
  "geometry": {"coordinates":[-81.225852,35.687402],"type":"Point"}
}