{
  "type": "Feature",
  "properties": {
    "iso:country":"US",
    "sg:address":"4067 Angel Ln",
    "sg:city":"Maiden",
    "sg:classifiers":[
        {
            "category":"Building & Trades",
            "subcategory":"Construction",
            "type":"Services"
        }
    ],
    "sg:phone":"+1 704 489 9285",
    "sg:postcode":"28650",
    "sg:province":"NC",
    "sg:tags":[
        "hanging",
        "contractor"
    ],
    "wof:name":"Rjk Painting Inc",
    "wof:placetype":"venue"
},
  "geometry": {"coordinates":[-81.07938,35.543248],"type":"Point"}
}