{
  "type": "Feature",
  "properties": {
    "addr:full":"109 N Main St Faith NC 28081",
    "addr:housenumber":"109",
    "addr:postcode":"28081",
    "addr:street":"N Main St",
    "iso:country":"US",
    "sg:address":"109 N Main St",
    "sg:city":"Faith",
    "sg:classifiers":[
        {
            "category":"Personal",
            "subcategory":"Beauty Salon",
            "type":"Services"
        }
    ],
    "sg:phone":"+1 704 279 2161",
    "sg:postcode":"28081",
    "sg:province":"NC",
    "wof:name":"Faith Beauty Shop",
    "wof:placetype":"venue"
},
  "geometry": {"coordinates":[-80.622496,35.500001],"type":"Point"}
}