{
  "type": "Feature",
  "properties": {
    "iso:country":"US",
    "sg:address":"5408 Dowgate Dr",
    "sg:city":"Charlotte",
    "sg:classifiers":[
        {
            "category":"Building & Trades",
            "subcategory":"Cleaning & Sanitation",
            "type":"Services"
        }
    ],
    "sg:phone":"+1   ",
    "sg:postcode":"28208",
    "sg:province":"NC",
    "sg:tags":[
        "maintenance"
    ],
    "wof:name":"Siffords Cleaning",
    "wof:placetype":"venue"
},
  "geometry": {"coordinates":[-80.919596,35.252679],"type":"Point"}
}