{
  "type": "Feature",
  "properties": {
    "addr:full":"3604 Southern Dr Efland NC 27243",
    "addr:housenumber":"3604",
    "addr:postcode":"27243",
    "addr:street":"Southern Dr",
    "iso:country":"US",
    "sg:address":"3604 Southern Dr",
    "sg:city":"Efland",
    "sg:classifiers":[
        {
            "category":"Manufacturing",
            "subcategory":"Metals",
            "type":"Manufacturing & Wholesale Goods"
        }
    ],
    "sg:phone":"+1 919 732 6956",
    "sg:postcode":"27243",
    "sg:province":"NC",
    "sg:tags":[
        "fabricator",
        "sheet"
    ],
    "wof:name":"USA Dutch Inc",
    "wof:placetype":"venue"
},
  "geometry": {"coordinates":[-79.172043,36.079161],"type":"Point"}
}