{
  "type": "Feature",
  "properties": {
    "addr:full":"111 13th St Southport NC 28461",
    "addr:housenumber":"111",
    "addr:postcode":"28461",
    "addr:street":"13Th St",
    "iso:country":"US",
    "sg:address":"111 13th St",
    "sg:city":"Southport",
    "sg:classifiers":[
        {
            "category":"Building & Trades",
            "subcategory":"Construction",
            "type":"Services"
        }
    ],
    "sg:phone":"+1 910 457 7150",
    "sg:postcode":"28461",
    "sg:province":"NC",
    "sg:tags":[
        "general",
        "contractor"
    ],
    "wof:name":"Inuit Services",
    "wof:placetype":"venue"
},
  "geometry": {"coordinates":[-78.02409299999999,33.934606],"type":"Point"}
}