{
  "type": "Feature",
  "properties": {
    "iso:country":"US",
    "sg:address":"774 Dupont Rd",
    "sg:city":"Hendersonville",
    "sg:classifiers":[
        {
            "category":"Building & Trades",
            "subcategory":"Plumbing",
            "type":"Services"
        }
    ],
    "sg:phone":"+1 828 693 9697",
    "sg:postcode":"28739",
    "sg:province":"NC",
    "sg:tags":[
        "plumbing",
        "contractor"
    ],
    "wof:name":"Appalachian Plumbing & Gas",
    "wof:placetype":"venue"
},
  "geometry": {"coordinates":[-82.596577,35.228461],"type":"Point"}
}