{
  "type": "Feature",
  "properties": {
    "addr:full":"5412 W Market St Greensboro NC 27409",
    "addr:housenumber":"5412",
    "addr:postcode":"27409",
    "addr:street":"W Market St",
    "iso:country":"US",
    "sg:address":"5412 W Market St",
    "sg:city":"Greensboro",
    "sg:classifiers":[
        {
            "category":"Restaurant",
            "type":"Food & Drink"
        }
    ],
    "sg:menulink":"http://www.allmenus.com/nc/greensboro/87083-little-caesars-pizza/menu/",
    "sg:phone":"+1 336 377 2226",
    "sg:postcode":"27409",
    "sg:province":"NC",
    "sg:tags":[
        "american",
        "pizza"
    ],
    "wof:name":"Little Caesar's Pizza",
    "wof:placetype":"venue"
},
  "geometry": {"coordinates":[-79.886888,36.074131],"type":"Point"}
}