{
  "type": "Feature",
  "properties": {
    "iso:country":"US",
    "sg:address":"211 N Fayetteville Ave",
    "sg:city":"Dunn",
    "sg:classifiers":[
        {
            "category":"Personal",
            "subcategory":"Beauty Salon",
            "type":"Services"
        }
    ],
    "sg:phone":"+1 910 892 1236",
    "sg:postcode":"28334",
    "sg:province":"NC",
    "wof:name":"Hair Fashions By Denise",
    "wof:placetype":"venue"
},
  "geometry": {"coordinates":[-78.610255,35.310598],"type":"Point"}
}