{
  "type": "Feature",
  "properties": {
    "iso:country":"US",
    "sg:address":"3815 Tinsley Dr",
    "sg:city":"High Point",
    "sg:classifiers":[
        {
            "category":"Real Estate",
            "subcategory":"Real Estate Agent",
            "type":"Services"
        }
    ],
    "sg:phone":"+1 336 883 6052",
    "sg:postcode":"27265",
    "sg:province":"NC",
    "sg:tags":[
        "agency"
    ],
    "wof:name":"Re/Max",
    "wof:placetype":"venue"
},
  "geometry": {"coordinates":[-79.969776,36.027212],"type":"Point"}
}