{
  "type": "Feature",
  "properties": {
    "iso:country":"US",
    "sg:address":"351 Summit Ave",
    "sg:city":"Greensboro",
    "sg:classifiers":[
        {
            "category":"Autos & Motor Vehicles",
            "subcategory":"Automobile Sales",
            "type":"Retail Goods"
        }
    ],
    "sg:phone":"+1 336 370 1208",
    "sg:postcode":"27405",
    "sg:province":"NC",
    "sg:tags":[
        "used"
    ],
    "wof:name":"Royal Auto Sales",
    "wof:placetype":"venue"
},
  "geometry": {"coordinates":[-79.78372899999999,36.078584],"type":"Point"}
}