{
  "type": "Feature",
  "properties": {
    "addr:full":"584 Wildlife Club Rd Graham NC 27253",
    "addr:housenumber":"584",
    "addr:postcode":"27253",
    "addr:street":"Wildlife Club Rd",
    "iso:country":"US",
    "sg:address":"584 Wildlife Club Rd",
    "sg:city":"Graham",
    "sg:classifiers":[
        {
            "category":"Recreation",
            "type":"Entertainment"
        }
    ],
    "sg:phone":"+1   ",
    "sg:postcode":"27253",
    "sg:province":"NC",
    "sg:tags":[
        "club",
        "membership"
    ],
    "wof:name":"Alamance Wildlife Club",
    "wof:placetype":"venue"
},
  "geometry": {"coordinates":[-79.38374399999999,35.955892],"type":"Point"}
}