{
  "type": "Feature",
  "properties": {
    "iso:country":"US",
    "sg:address":"114 W Medical Park Dr",
    "sg:city":"Lexington",
    "sg:classifiers":[
        {
            "category":"Health Services",
            "subcategory":"Doctor",
            "type":"Services"
        }
    ],
    "sg:phone":"+1 336 249 8760",
    "sg:postcode":"27292",
    "sg:province":"NC",
    "sg:tags":[
        "physician",
        "surgeon"
    ],
    "wof:name":"James R Long MD",
    "wof:placetype":"venue"
},
  "geometry": {"coordinates":[-80.289458,35.803794],"type":"Point"}
}