{
  "type": "Feature",
  "properties": {
    "iso:country":"US",
    "sg:address":"609 Whitsett Ave",
    "sg:city":"Gibsonville",
    "sg:classifiers":[
        {
            "category":"Professional",
            "type":"Services"
        }
    ],
    "sg:phone":"+1 336 449 4510",
    "sg:postcode":"27249",
    "sg:province":"NC",
    "sg:tags":[
        "establishment"
    ],
    "wof:name":"Bennett Corp",
    "wof:placetype":"venue"
},
  "geometry": {"coordinates":[-79.54821800000001,36.102924],"type":"Point"}
}