{
  "type": "Feature",
  "properties": {
    "iso:country":"US",
    "sg:address":"5424 Royal Troon Dr",
    "sg:city":"Raleigh",
    "sg:classifiers":[
        {
            "category":"Retail",
            "subcategory":"Animal Services",
            "type":"Services"
        }
    ],
    "sg:phone":"+1 919 231 3598",
    "sg:postcode":"27604",
    "sg:province":"NC",
    "sg:tags":[
        "cat",
        "dog",
        "kennel"
    ],
    "wof:name":"TLC Pet Sitting Svc",
    "wof:placetype":"venue"
},
  "geometry": {"coordinates":[-78.543291,35.805104],"type":"Point"}
}