{
  "type": "Feature",
  "properties": {
    "iso:country":"US",
    "sg:address":"126 Thomas St",
    "sg:city":"Rutherfordton",
    "sg:classifiers":[
        {
            "category":"Real Estate",
            "subcategory":"Real Estate Agent",
            "type":"Services"
        }
    ],
    "sg:phone":"+1 828 286 2340",
    "sg:postcode":"28139",
    "sg:province":"NC",
    "wof:name":"Properities Unlimited Inc",
    "wof:placetype":"venue"
},
  "geometry": {"coordinates":[-81.975589,35.358518],"type":"Point"}
}