{
  "type": "Feature",
  "properties": {
    "addr:full":"103 Yates Hill Rd Rockingham NC 28379",
    "addr:housenumber":"103",
    "addr:postcode":"28379",
    "addr:street":"Yates Hill Rd",
    "iso:country":"US",
    "sg:address":"103 Yates Hill Rd",
    "sg:city":"Rockingham",
    "sg:classifiers":[
        {
            "category":"Utilities",
            "subcategory":"Telephone",
            "type":"Services"
        }
    ],
    "sg:phone":"+1 910 419 9365",
    "sg:postcode":"28379",
    "sg:province":"NC",
    "sg:tags":[
        "telecommunication"
    ],
    "sg:website":"www.mastec.com",
    "wof:name":"Mas Tec",
    "wof:placetype":"venue"
},
  "geometry": {"coordinates":[-79.785554,34.94039],"type":"Point"}
}