{
  "type": "Feature",
  "properties": {
    "iso:country":"US",
    "sg:address":"422 E Grand Ave",
    "sg:city":"Rocky Mount",
    "sg:classifiers":[
        {
            "category":"Food & Beverages",
            "subcategory":"Groceries & Convenience Stores",
            "type":"Retail Goods"
        }
    ],
    "sg:phone":"+1 252 442 8940",
    "sg:postcode":"27801",
    "sg:province":"NC",
    "sg:tags":[
        "grocer"
    ],
    "wof:name":"Grand Food Market",
    "wof:placetype":"venue"
},
  "geometry": {"coordinates":[-77.78801,35.949318],"type":"Point"}
}