{
  "type": "Feature",
  "properties": {
    "iso:country":"US",
    "sg:address":"115 Bonview Ave",
    "sg:city":"Lincolnton",
    "sg:classifiers":[
        {
            "category":"Organizations",
            "subcategory":"Religious Organization",
            "type":"Services"
        }
    ],
    "sg:phone":"+1 704 735 4956",
    "sg:postcode":"28092",
    "sg:province":"NC",
    "sg:tags":[
        "church"
    ],
    "wof:name":"First Wesleyan Church",
    "wof:placetype":"venue"
},
  "geometry": {"coordinates":[-81.258788,35.474861],"type":"Point"}
}