{
  "type": "Feature",
  "properties": {
    "iso:country":"US",
    "sg:address":"214 Roymac Dr",
    "sg:city":"Wilmington",
    "sg:classifiers":[
        {
            "category":"Utilities",
            "subcategory":"Fuel Oil & Lpg",
            "type":"Services"
        }
    ],
    "sg:phone":"+1 910 762 5484",
    "sg:postcode":"28401",
    "sg:province":"NC",
    "sg:tags":[
        "propane",
        "gas"
    ],
    "wof:name":"Ameri Gas Propane LP",
    "wof:placetype":"venue"
},
  "geometry": {"coordinates":[-77.97179300000001,34.287856],"type":"Point"}
}