{
  "type": "Feature",
  "properties": {
    "addr:full":"201 Ruritan Park Rd Stony Point NC 28678",
    "addr:housenumber":"201",
    "addr:postcode":"28678",
    "addr:street":"Ruritan Park Rd",
    "iso:country":"US",
    "sg:address":"201 Ruritan Park Rd",
    "sg:city":"Stony Point",
    "sg:classifiers":[
        {
            "category":"Government",
            "subcategory":"Fire Station",
            "type":"Public Place"
        }
    ],
    "sg:phone":"+1 704 585 2519",
    "sg:postcode":"28678",
    "sg:province":"NC",
    "sg:tags":[
        "department"
    ],
    "wof:name":"Stony Point Fire Dept",
    "wof:placetype":"venue"
},
  "geometry": {"coordinates":[-81.048678,35.864244],"type":"Point"}
}