{
  "type": "Feature",
  "properties": {
    "iso:country":"US",
    "sg:address":"1060 Gunter Lake Rd",
    "sg:city":"Sanford",
    "sg:classifiers":[
        {
            "category":"Communications",
            "subcategory":"Film & Video Production",
            "type":"Services"
        }
    ],
    "sg:phone":"+1 919 498 6694",
    "sg:postcode":"27332",
    "sg:province":"NC",
    "sg:tags":[
        "motion",
        "picture",
        "taping"
    ],
    "wof:name":"George Denson's Video Quest",
    "wof:placetype":"venue"
},
  "geometry": {"coordinates":[-79.18514999999999,35.339968],"type":"Point"}
}