{
  "type": "Feature",
  "properties": {
    "iso:country":"US",
    "sg:address":"2010 State Hwy 231",
    "sg:city":"Wendell",
    "sg:classifiers":[
        {
            "category":"Retail",
            "subcategory":"Repair Shop",
            "type":"Services"
        }
    ],
    "sg:phone":"+1 919 365 9860",
    "sg:postcode":"27591",
    "sg:province":"NC",
    "sg:tags":[
        "machine",
        "copying"
    ],
    "wof:name":"Carolina Copier",
    "wof:placetype":"venue"
},
  "geometry": {"coordinates":[-78.32555600000001,35.74947],"type":"Point"}
}