{
  "type": "Feature",
  "properties": {
    "iso:country":"US",
    "sg:address":"1011 Arnold St",
    "sg:city":"Greensboro",
    "sg:classifiers":[
        {
            "category":"Bars & Pubs",
            "type":"Food & Drink"
        }
    ],
    "sg:phone":"+1 336 333 9333",
    "sg:postcode":"27405",
    "sg:province":"NC",
    "sg:tags":[
        "drinking"
    ],
    "wof:name":"Warehouse 29",
    "wof:placetype":"venue"
},
  "geometry": {"coordinates":[-79.76818,36.087471],"type":"Point"}
}