{
  "type": "Feature",
  "properties": {
    "addr:full":"4604 Poole Rd Raleigh NC 27610",
    "addr:housenumber":"4604",
    "addr:postcode":"27610",
    "addr:street":"Poole Rd",
    "iso:country":"US",
    "sg:address":"4604 Poole Rd",
    "sg:city":"Raleigh",
    "sg:classifiers":[
        {
            "category":"Manufacturing",
            "subcategory":"Tools & Machinery",
            "type":"Manufacturing & Wholesale Goods"
        }
    ],
    "sg:phone":"+1 919 212 0555",
    "sg:postcode":"27610",
    "sg:province":"NC",
    "sg:tags":[
        "control",
        "environmental",
        "co",
        "mfg"
    ],
    "wof:name":"Yamas Controls Carolinas Inc",
    "wof:placetype":"venue"
},
  "geometry": {"coordinates":[-78.556299,35.763111],"type":"Point"}
}