{
  "type": "Feature",
  "properties": {
    "iso:country":"US",
    "sg:address":"3048 Prosperity Church Rd",
    "sg:city":"Charlotte",
    "sg:classifiers":[
        {
            "category":"Restaurant",
            "type":"Food & Drink"
        }
    ],
    "sg:menulink":"http://www.allmenus.com/nc/charlotte/89198-subway/menu/",
    "sg:phone":"+1 704 547 1912",
    "sg:postcode":"28269",
    "sg:province":"NC",
    "sg:tags":[
        "american",
        "sandwich"
    ],
    "wof:name":"Subway",
    "wof:placetype":"venue"
},
  "geometry": {"coordinates":[-80.76941600000001,35.342418],"type":"Point"}
}