{
  "type": "Feature",
  "properties": {
    "iso:country":"US",
    "sg:address":"993 Brompton Ln",
    "sg:city":"Greenville",
    "sg:classifiers":[
        {
            "category":"Freight",
            "type":"Transportation"
        }
    ],
    "sg:phone":"+1 252 321 2689",
    "sg:postcode":"27834",
    "sg:province":"NC",
    "sg:tags":[
        "courier"
    ],
    "wof:name":"Dhl",
    "wof:placetype":"venue"
},
  "geometry": {"coordinates":[-77.44280500000001,35.575608],"type":"Point"}
}