{
  "type": "Feature",
  "properties": {
    "addr:full":"180 Smokey Park Hwy Asheville NC 28806",
    "addr:housenumber":"180",
    "addr:postcode":"28806",
    "addr:street":"Smokey Park Hwy",
    "iso:country":"US",
    "sg:address":"180 Smokey Park Hwy",
    "sg:city":"Asheville",
    "sg:classifiers":[
        {
            "category":"Retail",
            "subcategory":"Auto Rental",
            "type":"Services"
        }
    ],
    "sg:phone":"+1 828 665 1511",
    "sg:postcode":"28806",
    "sg:province":"NC",
    "sg:tags":[
        "renting",
        "truck",
        "leasing"
    ],
    "wof:name":"U-Haul Co",
    "wof:placetype":"venue"
},
  "geometry": {"coordinates":[-82.63011400000001,35.562504],"type":"Point"}
}