{
  "type": "Feature",
  "properties": {
    "addr:full":"1 Mountain Heritage Pl Candler NC 28715",
    "addr:housenumber":"1",
    "addr:postcode":"28715",
    "addr:street":"Mountain Heritage Pl",
    "iso:country":"US",
    "sg:address":"1 Mountain Heritage Pl",
    "sg:city":"Candler",
    "sg:classifiers":[
        {
            "category":"Professional",
            "subcategory":"Business Services",
            "type":"Services"
        }
    ],
    "sg:phone":"+1   ",
    "sg:postcode":"28715",
    "sg:province":"NC",
    "wof:name":"Bob Jones Fund Raising Inc",
    "wof:placetype":"venue"
},
  "geometry": {"coordinates":[-82.67966,35.52354],"type":"Point"}
}