{
  "type": "Feature",
  "properties": {
    "addr:full":"1755 Carson Rd Shelby NC 28150",
    "addr:housenumber":"1755",
    "addr:postcode":"28150",
    "addr:street":"Carson Rd",
    "iso:country":"US",
    "sg:address":"1755 Carson Rd",
    "sg:city":"Shelby",
    "sg:classifiers":[
        {
            "category":"Building & Trades",
            "subcategory":"Construction",
            "type":"Services"
        }
    ],
    "sg:phone":"+1 704 482 4882",
    "sg:postcode":"28150",
    "sg:province":"NC",
    "sg:tags":[
        "concrete",
        "contractor"
    ],
    "wof:name":"Concrete Kid Concrete Finshg",
    "wof:placetype":"venue"
},
  "geometry": {"coordinates":[-81.483018,35.339294],"type":"Point"}
}