{
  "type": "Feature",
  "properties": {
    "addr:full":"139 SE Railroad St Enfield NC 27823",
    "addr:housenumber":"139",
    "addr:postcode":"27823",
    "addr:street":"Se Railroad St",
    "iso:country":"US",
    "sg:address":"139 SE Railroad St",
    "sg:city":"Enfield",
    "sg:classifiers":[
        {
            "category":"Social Services",
            "subcategory":"Child Care",
            "type":"Services"
        }
    ],
    "sg:phone":"+1   ",
    "sg:postcode":"27823",
    "sg:province":"NC",
    "sg:tags":[
        "day"
    ],
    "wof:name":"J & J Child Care Center 2",
    "wof:placetype":"venue"
},
  "geometry": {"coordinates":[-77.666709,36.180187],"type":"Point"}
}