{
  "type": "Feature",
  "properties": {
    "addr:full":"3901 Aster Dr Charlotte NC 28227",
    "addr:housenumber":"3901",
    "addr:postcode":"28227",
    "addr:street":"Aster Dr",
    "iso:country":"US",
    "sg:address":"3901 Aster Dr",
    "sg:city":"Charlotte",
    "sg:classifiers":[
        {
            "category":"Building & Trades",
            "subcategory":"Construction",
            "type":"Services"
        }
    ],
    "sg:phone":"+1 704 545 2256",
    "sg:postcode":"28227",
    "sg:province":"NC",
    "sg:tags":[
        "house"
    ],
    "wof:name":"Cracker Boy Construction LLC",
    "wof:placetype":"venue"
},
  "geometry": {"coordinates":[-80.716402,35.17874],"type":"Point"}
}