{
  "type": "Feature",
  "properties": {
    "addr:full":"209 Magnolia Bloom Ct Cary NC 27519",
    "addr:housenumber":"209",
    "addr:postcode":"27519",
    "addr:street":"Magnolia Bloom Ct",
    "iso:country":"US",
    "sg:address":"209 Magnolia Bloom Ct",
    "sg:city":"Cary",
    "sg:classifiers":[
        {
            "category":"Professional",
            "subcategory":"Computer Services",
            "type":"Services"
        }
    ],
    "sg:phone":"+1   ",
    "sg:postcode":"27519",
    "sg:province":"NC",
    "sg:tags":[
        "prepackaged",
        "software"
    ],
    "wof:name":"Oracle",
    "wof:placetype":"venue"
},
  "geometry": {"coordinates":[-78.851657,35.819343],"type":"Point"}
}