{
  "type": "Feature",
  "properties": {
    "iso:country":"US",
    "sg:address":"3610 State Hwy 24",
    "sg:city":"Newport",
    "sg:classifiers":[
        {
            "category":"Retail",
            "subcategory":"Auto Repair",
            "type":"Services"
        }
    ],
    "sg:phone":"+1 252 393 2121",
    "sg:postcode":"28570",
    "sg:province":"NC",
    "sg:tags":[
        "repairing",
        "automobile"
    ],
    "wof:name":"Absolute Auto Care Inc",
    "wof:placetype":"venue"
},
  "geometry": {"coordinates":[-76.963717,34.718765],"type":"Point"}
}