{
  "type": "Feature",
  "properties": {
    "iso:country":"US",
    "sg:address":"5620 Bragg Blvd",
    "sg:city":"Fayetteville",
    "sg:classifiers":[
        {
            "category":"Personal",
            "subcategory":"Barber",
            "type":"Services"
        }
    ],
    "sg:phone":"+1   ",
    "sg:postcode":"28303",
    "sg:province":"NC",
    "sg:tags":[
        "shop"
    ],
    "wof:name":"Mr B Barbour Shop",
    "wof:placetype":"venue"
},
  "geometry": {"coordinates":[-78.95858,35.102486],"type":"Point"}
}