{
  "type": "Feature",
  "properties": {
    "iso:country":"US",
    "sg:address":"1516 Lake Branch Dr",
    "sg:city":"Wilmington",
    "sg:classifiers":[
        {
            "category":"Shopping",
            "subcategory":"Gifts & Souvenirs",
            "type":"Retail Goods"
        }
    ],
    "sg:phone":"+1 910 762 7221",
    "sg:postcode":"28401",
    "sg:province":"NC",
    "sg:tags":[
        "shop"
    ],
    "wof:name":"Nature's Comfort",
    "wof:placetype":"venue"
},
  "geometry": {"coordinates":[-77.93593300000001,34.214533],"type":"Point"}
}