{
  "type": "Feature",
  "properties": {
    "iso:country":"US",
    "sg:address":"108 N Sutherland Ave",
    "sg:city":"Monroe",
    "sg:classifiers":[
        {
            "category":"Wholesale",
            "subcategory":"Electrical",
            "type":"Manufacturing & Wholesale Goods"
        }
    ],
    "sg:phone":"+1 704 283 8106",
    "sg:postcode":"28110",
    "sg:province":"NC",
    "sg:tags":[
        "equipment",
        "electric",
        "supply"
    ],
    "sg:website":"www.graybar.com",
    "wof:name":"Graybar Electric Co",
    "wof:placetype":"venue"
},
  "geometry": {"coordinates":[-80.52323699999999,34.983982],"type":"Point"}
}