{
  "type": "Feature",
  "properties": {
    "iso:country":"US",
    "sg:address":"807 Aspen St",
    "sg:city":"Aberdeen",
    "sg:classifiers":[
        {
            "category":"Freight",
            "type":"Transportation"
        }
    ],
    "sg:phone":"+1 910 944 3562",
    "sg:postcode":"28315",
    "sg:province":"NC",
    "sg:tags":[
        "operator",
        "trucking"
    ],
    "wof:name":"Martin T Wells",
    "wof:placetype":"venue"
},
  "geometry": {"coordinates":[-79.420436,35.140928],"type":"Point"}
}