{
  "type": "Feature",
  "properties": {
    "addr:full":"3060 S Church St Burlington NC 27215",
    "addr:housenumber":"3060",
    "addr:postcode":"27215",
    "addr:street":"S Church St",
    "iso:country":"US",
    "sg:address":"3060 S Church St",
    "sg:city":"Burlington",
    "sg:classifiers":[
        {
            "category":"Insurance",
            "subcategory":"Insurance Agent",
            "type":"Services"
        }
    ],
    "sg:phone":"+1 336 538 4000",
    "sg:postcode":"27215",
    "sg:province":"NC",
    "wof:name":"Gmac Insurance",
    "wof:placetype":"venue"
},
  "geometry": {"coordinates":[-79.493602,36.080284],"type":"Point"}
}