{
  "type": "Feature",
  "properties": {
    "addr:full":"10948 N Main St Archdale NC 27263",
    "addr:housenumber":"10948",
    "addr:postcode":"27263",
    "addr:street":"N Main St",
    "iso:country":"US",
    "sg:address":"10948 N Main St",
    "sg:city":"Archdale",
    "sg:classifiers":[
        {
            "category":"Shopping",
            "subcategory":"Hobbies, Toys, & Games",
            "type":"Retail Goods"
        }
    ],
    "sg:phone":"+1 336 434 3482",
    "sg:postcode":"27263",
    "sg:province":"NC",
    "sg:tags":[
        "model",
        "supply"
    ],
    "wof:name":"K C Hobby",
    "wof:placetype":"venue"
},
  "geometry": {"coordinates":[-79.969618,35.911068],"type":"Point"}
}