{
  "type": "Feature",
  "properties": {
    "addr:full":"2165 Rains Crossroads Rd Selma NC 27576",
    "addr:housenumber":"2165",
    "addr:postcode":"27576",
    "addr:street":"Rains Crossroads Rd",
    "iso:country":"US",
    "sg:address":"2165 Rains Crossroads Rd",
    "sg:city":"Selma",
    "sg:phone":"+1 919 965 8106",
    "sg:postcode":"27576",
    "sg:province":"NC",
    "sg:tags":[
        "farm",
        "grain",
        "cash"
    ],
    "wof:name":"Holloman Farms",
    "wof:placetype":"venue"
},
  "geometry": {"coordinates":[-78.20013400000001,35.518152],"type":"Point"}
}