{
  "type": "Feature",
  "properties": {
    "addr:full":"113 Ervin St Belmont NC 28012",
    "addr:housenumber":"113",
    "addr:postcode":"28012",
    "addr:street":"Ervin St",
    "iso:country":"US",
    "sg:address":"113 Ervin St",
    "sg:city":"Belmont",
    "sg:classifiers":[
        {
            "category":"Professional",
            "subcategory":"Computer Services",
            "type":"Services"
        }
    ],
    "sg:phone":"+1   ",
    "sg:postcode":"28012",
    "sg:province":"NC",
    "sg:tags":[
        "prepackaged",
        "software"
    ],
    "wof:name":"Midatlantic Tech",
    "wof:placetype":"venue"
},
  "geometry": {"coordinates":[-81.03228300000001,35.244856],"type":"Point"}
}