{
  "type": "Feature",
  "properties": {
    "iso:country":"US",
    "sg:address":"244 Roope Ridge Rd",
    "sg:city":"Hays",
    "sg:classifiers":[
        {
            "category":"Professional",
            "subcategory":"Business Services",
            "type":"Services"
        }
    ],
    "sg:phone":"+1 336 957 8991",
    "sg:postcode":"28635",
    "sg:province":"NC",
    "wof:name":"A & J Construction Co Inc",
    "wof:placetype":"venue"
},
  "geometry": {"coordinates":[-81.08737600000001,36.260685],"type":"Point"}
}