{
  "type": "Feature",
  "properties": {
    "iso:country":"US",
    "sg:address":"1380 Faison Hwy",
    "sg:city":"Clinton",
    "sg:classifiers":[
        {
            "category":"Building & Trades",
            "subcategory":"Construction",
            "type":"Services"
        }
    ],
    "sg:phone":"+1 910 592 6060",
    "sg:postcode":"28328",
    "sg:province":"NC",
    "sg:tags":[
        "residential"
    ],
    "wof:name":"W L Faison Company Inc",
    "wof:placetype":"venue"
},
  "geometry": {"coordinates":[-78.289328,35.014636],"type":"Point"}
}