{
  "type": "Feature",
  "properties": {
    "iso:country":"US",
    "sg:address":"25313 State Hwy 12",
    "sg:city":"Waves",
    "sg:classifiers":[
        {
            "category":"Travel",
            "subcategory":"Campground",
            "type":"Entertainment"
        }
    ],
    "sg:phone":"+1 252 987 2556",
    "sg:postcode":"27982",
    "sg:province":"NC",
    "wof:name":"Ocean Waves Campground",
    "wof:placetype":"venue"
},
  "geometry": {"coordinates":[-75.47112799999999,35.544982],"type":"Point"}
}