{
  "type": "Feature",
  "properties": {
    "iso:country":"US",
    "sg:address":"962 S Talbert Blvd",
    "sg:city":"Lexington",
    "sg:classifiers":[
        {
            "category":"Social Services",
            "subcategory":"Child Care",
            "type":"Services"
        }
    ],
    "sg:phone":"+1 336 249 2704",
    "sg:postcode":"27292",
    "sg:province":"NC",
    "sg:tags":[
        "kindergarten",
        "academic",
        "school"
    ],
    "wof:name":"Davidson County Headstart",
    "wof:placetype":"venue"
},
  "geometry": {"coordinates":[-80.26057299999999,35.813373],"type":"Point"}
}