{
  "type": "Feature",
  "properties": {
    "addr:full":"189 Meadow Mountain Est Rd Franklin NC 28734",
    "addr:housenumber":"189",
    "addr:postcode":"nc 28734",
    "addr:street":"Meadow Mountain Est Rd",
    "iso:country":"US",
    "sg:address":"189 Meadow Mountain Est Rd",
    "sg:city":"Franklin",
    "sg:classifiers":[
        {
            "category":"Retail",
            "subcategory":"Animal Services",
            "type":"Services"
        }
    ],
    "sg:phone":"+1 828 524 8868",
    "sg:postcode":"28734",
    "sg:province":"NC",
    "sg:tags":[
        "pet"
    ],
    "wof:name":"Mountain Pets Sitting Svc",
    "wof:placetype":"venue"
},
  "geometry": {"coordinates":[-83.479696,35.12455],"type":"Point"}
}