{
  "type": "Feature",
  "properties": {
    "addr:full":"3105 Nash St NW Wilson NC 27896",
    "addr:housenumber":"3105",
    "addr:postcode":"27896",
    "addr:street":"Nash St Nw",
    "iso:country":"US",
    "sg:address":"3105 Nash St NW",
    "sg:city":"Wilson",
    "sg:classifiers":[
        {
            "category":"Health Services",
            "subcategory":"Doctor",
            "type":"Services"
        }
    ],
    "sg:phone":"+1 252 243 5376",
    "sg:postcode":"27896",
    "sg:province":"NC",
    "sg:tags":[
        "physician",
        "medical",
        "surgeon"
    ],
    "wof:name":"Celso B Lobao MD",
    "wof:placetype":"venue"
},
  "geometry": {"coordinates":[-77.93719,35.765345],"type":"Point"}
}