{
  "type": "Feature",
  "properties": {
    "addr:full":"231 N Church St Rocky Mount NC 27804",
    "addr:housenumber":"231",
    "addr:postcode":"27804",
    "addr:street":"N Church St",
    "iso:country":"US",
    "sg:address":"231 N Church St",
    "sg:city":"Rocky Mount",
    "sg:classifiers":[
        {
            "category":"Social Services",
            "subcategory":"Child Care",
            "type":"Services"
        }
    ],
    "sg:phone":"+1 252 442 1092",
    "sg:postcode":"27804",
    "sg:province":"NC",
    "wof:name":"Church-Good Shepherd Day Care",
    "wof:placetype":"venue"
},
  "geometry": {"coordinates":[-77.795742,35.945499],"type":"Point"}
}