{
  "type": "Feature",
  "properties": {
    "iso:country":"US",
    "sg:address":"152 Ledger School Rd",
    "sg:city":"Bakersville",
    "sg:classifiers":[
        {
            "category":"Social Services",
            "type":"Services"
        }
    ],
    "sg:phone":"+1 828 688 3019",
    "sg:postcode":"28705",
    "sg:province":"NC",
    "wof:name":"Mitchell Senior Citizens Ctr",
    "wof:placetype":"venue"
},
  "geometry": {"coordinates":[-82.11587400000001,35.966466],"type":"Point"}
}