{
  "type": "Feature",
  "properties": {
    "iso:country":"US",
    "sg:address":"3621 Camden Rd",
    "sg:city":"Fayetteville",
    "sg:classifiers":[
        {
            "category":"Building & Trades",
            "subcategory":"Cleaning & Sanitation",
            "type":"Services"
        }
    ],
    "sg:phone":"+1   ",
    "sg:postcode":"28306",
    "sg:province":"NC",
    "sg:tags":[
        "maintenance"
    ],
    "wof:name":"Southview Residential",
    "wof:placetype":"venue"
},
  "geometry": {"coordinates":[-78.9177,35.008481],"type":"Point"}
}