{
  "type": "Feature",
  "properties": {
    "iso:country":"US",
    "sg:address":"221 Commonwealth Ct",
    "sg:city":"Cary",
    "sg:classifiers":[
        {
            "category":"Restaurant",
            "type":"Food & Drink"
        }
    ],
    "sg:phone":"+1 919 465 0120",
    "sg:postcode":"27511",
    "sg:province":"NC",
    "wof:name":"Out Of The Box Developers",
    "wof:placetype":"venue"
},
  "geometry": {"coordinates":[-78.78475299999999,35.766885],"type":"Point"}
}