{
  "type": "Feature",
  "properties": {
    "addr:full":"102 S Kerr Ave Wilmington NC 28403",
    "addr:housenumber":"102",
    "addr:postcode":"28403",
    "addr:street":"S Kerr Ave",
    "iso:country":"US",
    "sg:address":"102 S Kerr Ave",
    "sg:city":"Wilmington",
    "sg:classifiers":[
        {
            "category":"Wholesale",
            "subcategory":"Groceries",
            "type":"Manufacturing & Wholesale Goods"
        }
    ],
    "sg:phone":"+1 910 392 2297",
    "sg:postcode":"28403",
    "sg:province":"NC",
    "sg:tags":[
        "baker"
    ],
    "wof:name":"Merita Bakeries",
    "wof:placetype":"venue"
},
  "geometry": {"coordinates":[-77.88904599999999,34.238336],"type":"Point"}
}