{
  "type": "Feature",
  "properties": {
    "iso:country":"US",
    "sg:address":"3107 Valleywood Pl",
    "sg:city":"Charlotte",
    "sg:classifiers":[
        {
            "category":"Professional",
            "type":"Services"
        }
    ],
    "sg:phone":"+1 704 392 5528",
    "sg:postcode":"28216",
    "sg:province":"NC",
    "wof:name":"Betty C Montgomery",
    "wof:placetype":"venue"
},
  "geometry": {"coordinates":[-80.86154000000001,35.277523],"type":"Point"}
}