{
  "type": "Feature",
  "properties": {
    "iso:country":"US",
    "sg:address":"111 James Jackson Ave",
    "sg:city":"Cary",
    "sg:classifiers":[
        {
            "category":"Travel",
            "subcategory":"Travel Agent",
            "type":"Entertainment"
        }
    ],
    "sg:phone":"+1 919 466 9994",
    "sg:postcode":"27513",
    "sg:province":"NC",
    "sg:tags":[
        "tour",
        "agency",
        "bureau"
    ],
    "wof:name":"Music Adventures Travel & Tours Inc",
    "wof:placetype":"venue"
},
  "geometry": {"coordinates":[-78.801498,35.796001],"type":"Point"}
}