{
  "type": "Feature",
  "properties": {
    "addr:full":"1320 Ridge Rd Raleigh NC 27607",
    "addr:housenumber":"1320",
    "addr:postcode":"27607",
    "addr:street":"Ridge Rd",
    "iso:country":"US",
    "sg:address":"1320 Ridge Rd",
    "sg:city":"Raleigh",
    "sg:classifiers":[
        {
            "category":"Health Services",
            "subcategory":"Nursing And Care Facility",
            "type":"Services"
        },
        {
            "category":"Social Services",
            "subcategory":"Adult Care",
            "type":"Services"
        }
    ],
    "sg:phone":"+1 919 270 4100",
    "sg:postcode":"27607",
    "sg:province":"NC",
    "sg:tags":[
        "home",
        "living",
        "assisted",
        "rest",
        "elder"
    ],
    "wof:name":"Steve Gaitos North Carolina Trust Retirement Manager",
    "wof:placetype":"venue"
},
  "geometry": {"coordinates":[-78.68729999999999,35.804191],"type":"Point"}
}