{
  "type": "Feature",
  "properties": {
    "addr:full":"8422 Brentfield Rd Huntersville NC 28078",
    "addr:postcode":"8422;28078",
    "addr:street":"Brentfield Rd",
    "iso:country":"US",
    "sg:address":"8422 Brentfield Rd",
    "sg:city":"Huntersville",
    "sg:classifiers":[
        {
            "category":"Professional",
            "subcategory":"Computer Services",
            "type":"Services"
        }
    ],
    "sg:phone":"+1   ",
    "sg:postcode":"28078",
    "sg:province":"NC",
    "sg:tags":[
        "information",
        "retrieval"
    ],
    "wof:name":"Youngblood Services",
    "wof:placetype":"venue"
},
  "geometry": {"coordinates":[-80.894713,35.437634],"type":"Point"}
}