{
  "type": "Feature",
  "properties": {
    "iso:country":"US",
    "sg:address":"1668 Brown Ave",
    "sg:city":"Waynesville",
    "sg:classifiers":[
        {
            "category":"Social Services",
            "type":"Services"
        }
    ],
    "sg:phone":"+1   ",
    "sg:postcode":"28786",
    "sg:province":"NC",
    "sg:tags":[
        "profit",
        "aid"
    ],
    "wof:name":"Red Cross",
    "wof:placetype":"venue"
},
  "geometry": {"coordinates":[-83.004267,35.470214],"type":"Point"}
}