{
  "type": "Feature",
  "properties": {
    "iso:country":"US",
    "sg:address":"601 Providence Rd",
    "sg:city":"Charlotte",
    "sg:classifiers":[
        {
            "category":"Shopping",
            "type":"Retail Goods"
        }
    ],
    "sg:phone":"+1 704 334 7744",
    "sg:postcode":"28207",
    "sg:province":"NC",
    "sg:tags":[
        "art",
        "gallery",
        "dealer"
    ],
    "sg:website":"www.shaingallery.com",
    "wof:name":"Shain Gallery",
    "wof:placetype":"venue"
},
  "geometry": {"coordinates":[-80.82516699999999,35.200964],"type":"Point"}
}