{
  "type": "Feature",
  "properties": {
    "addr:full":"55 Four and One Half St Highlands NC 28741",
    "addr:housenumber":"55",
    "addr:postcode":"28741",
    "addr:street":"Four;St",
    "iso:country":"US",
    "sg:address":"55 Four and One Half St",
    "sg:city":"Highlands",
    "sg:classifiers":[
        {
            "category":"Bars & Pubs",
            "type":"Food & Drink"
        }
    ],
    "sg:phone":"+1 828 526 4464",
    "sg:postcode":"28741",
    "sg:province":"NC",
    "sg:tags":[
        "drinking"
    ],
    "wof:name":"412 Street Inn",
    "wof:placetype":"venue"
},
  "geometry": {"coordinates":[-83.194912,35.057814],"type":"Point"}
}