{
  "type": "Feature",
  "properties": {
    "addr:full":"1707 Sardis Rd N Charlotte NC 28270",
    "addr:housenumber":"1707",
    "addr:postcode":"28270",
    "addr:street":"Sardis Rd N",
    "iso:country":"US",
    "sg:address":"1707 Sardis Rd N",
    "sg:city":"Charlotte",
    "sg:classifiers":[
        {
            "category":"Retail",
            "subcategory":"Photofinishing",
            "type":"Services"
        }
    ],
    "sg:phone":"+1   ",
    "sg:postcode":"28270",
    "sg:province":"NC",
    "sg:tags":[
        "processing",
        "photo",
        "photography",
        "work",
        "commercial",
        "lab",
        "studio"
    ],
    "wof:name":"Gem Photo/Studio Inc",
    "wof:placetype":"venue"
},
  "geometry": {"coordinates":[-80.73506399999999,35.14082],"type":"Point"}
}