{
  "type": "Feature",
  "properties": {
    "addr:full":"105 Duncan Ct Southern Pines NC 28387",
    "addr:housenumber":"105",
    "addr:postcode":"28387",
    "addr:street":"Duncan Ct",
    "iso:country":"US",
    "sg:address":"105 Duncan Ct",
    "sg:city":"Southern Pines",
    "sg:classifiers":[
        {
            "category":"Professional",
            "subcategory":"Computer Services",
            "type":"Services"
        }
    ],
    "sg:phone":"+1 919 776 9311",
    "sg:postcode":"28387",
    "sg:province":"NC",
    "sg:tags":[
        "consultant",
        "consulting",
        "management",
        "related",
        "designer"
    ],
    "sg:website":"www.strategiclinks.com",
    "wof:name":"Strategic Links Inc",
    "wof:placetype":"venue"
},
  "geometry": {"coordinates":[-79.372382,35.129245],"type":"Point"}
}