{
  "type": "Feature",
  "properties": {
    "addr:full":"7052 Sherrills Ford Rd Sherrills Ford NC 28673",
    "addr:housenumber":"7052",
    "addr:postcode":"28673",
    "addr:street":"Sherrills Ford Rd",
    "iso:country":"US",
    "sg:address":"7052 Sherrills Ford Rd",
    "sg:city":"Sherrills Ford",
    "sg:classifiers":[
        {
            "category":"Arts & Performance",
            "subcategory":"Theater",
            "type":"Entertainment"
        }
    ],
    "sg:phone":"+1 828 478 4306",
    "sg:postcode":"28673",
    "sg:province":"NC",
    "sg:tags":[
        "group"
    ],
    "wof:name":"Cockman Family Music",
    "wof:placetype":"venue"
},
  "geometry": {"coordinates":[-81.018002,35.636167],"type":"Point"}
}