{
  "type": "Feature",
  "properties": {
    "iso:country":"US",
    "sg:address":"312 N Church St",
    "sg:city":"Monroe",
    "sg:classifiers":[
        {
            "category":"Insurance",
            "subcategory":"Insurance Agent",
            "type":"Services"
        }
    ],
    "sg:phone":"+1 704 292 2920",
    "sg:postcode":"28112",
    "sg:province":"NC",
    "wof:name":"Pinnacle Financial Group LLC",
    "wof:placetype":"venue"
},
  "geometry": {"coordinates":[-80.547952,34.983979],"type":"Point"}
}