{
  "type": "Feature",
  "properties": {
    "addr:full":"5238 South Blvd Charlotte NC 28217",
    "addr:housenumber":"5238",
    "addr:postcode":"28217",
    "addr:street":"South Blvd",
    "iso:country":"US",
    "sg:address":"5238 South Blvd",
    "sg:city":"Charlotte",
    "sg:classifiers":[
        {
            "category":"Autos & Motor Vehicles",
            "subcategory":"Automobile Sales",
            "type":"Retail Goods"
        },
        {
            "category":"Autos & Motor Vehicles",
            "subcategory":"Fuel & Gas Station",
            "type":"Retail Goods"
        },
        {
            "category":"Autos & Motor Vehicles",
            "subcategory":"Auto Supplies",
            "type":"Retail Goods"
        },
        {
            "category":"Retail",
            "subcategory":"Auto Repair",
            "type":"Services"
        }
    ],
    "sg:phone":"+1 980 229 4879",
    "sg:postcode":"28217",
    "sg:province":"NC",
    "sg:tags":[
        "wheel",
        "exhaust",
        "oil",
        "muffler",
        "balancing",
        "wheels-aligning",
        "servicing-automotive",
        "system",
        "accessory",
        "equipment",
        "lube",
        "electrical",
        "axle",
        "equipment-service",
        "alignment-frame",
        "brake",
        "inspection",
        "air conditioning"
    ],
    "sg:website":"http://www.tomtracker.com/redirect.cfm?bID=4837&hID=111353",
    "wof:name":"Meineke Car Care Center",
    "wof:placetype":"venue"
},
  "geometry": {"coordinates":[-80.876059,35.165318],"type":"Point"}
}