{
  "type": "Feature",
  "properties": {
    "addr:full":"910 Tim Currin Rd Lillington NC 27546",
    "addr:housenumber":"910",
    "addr:postcode":"27546",
    "addr:street":"Tim Currin Rd",
    "iso:country":"US",
    "sg:address":"910 Tim Currin Rd",
    "sg:city":"Lillington",
    "sg:classifiers":[
        {
            "category":"Building & Trades",
            "subcategory":"Construction",
            "type":"Services"
        }
    ],
    "sg:phone":"+1 910 814 0398",
    "sg:postcode":"27546",
    "sg:province":"NC",
    "sg:tags":[
        "residential"
    ],
    "wof:name":"Porrazzo Construction",
    "wof:placetype":"venue"
},
  "geometry": {"coordinates":[-78.91861900000001,35.369466],"type":"Point"}
}