{
  "type": "Feature",
  "properties": {
    "addr:full":"1 Centerview Dr Greensboro NC 27407",
    "addr:housenumber":"1",
    "addr:postcode":"27407",
    "addr:street":"Centerview Dr",
    "iso:country":"US",
    "sg:address":"1 Centerview Dr",
    "sg:city":"Greensboro",
    "sg:classifiers":[
        {
            "category":"Banks & Credit Unions",
            "subcategory":"Bank",
            "type":"Services"
        }
    ],
    "sg:phone":"+1 336 855 3448",
    "sg:postcode":"27407",
    "sg:province":"NC",
    "sg:tags":[
        "banking",
        "mortgage"
    ],
    "wof:name":"Rbmg-Greensboro",
    "wof:placetype":"venue"
},
  "geometry": {"coordinates":[-79.840276,36.050517],"type":"Point"}
}