{
  "type": "Feature",
  "properties": {
    "iso:country":"US",
    "sg:address":"129 Murfield Dr",
    "sg:city":"Kings Mountain",
    "sg:classifiers":[
        {
            "category":"Building & Trades",
            "subcategory":"Construction",
            "type":"Services"
        }
    ],
    "sg:phone":"+1 704 392 1548",
    "sg:postcode":"28086",
    "sg:province":"NC",
    "sg:tags":[
        "commercial",
        "drywall"
    ],
    "wof:name":"Milligan Construction Company",
    "wof:placetype":"venue"
},
  "geometry": {"coordinates":[-81.44044599999999,35.29355],"type":"Point"}
}