{
  "type": "Feature",
  "properties": {
    "addr:full":"347 Mockingbird Ln Wake Forest NC 27587",
    "addr:housenumber":"347",
    "addr:postcode":"27587",
    "addr:street":"Mockingbird Ln",
    "iso:country":"US",
    "sg:address":"347 Mockingbird Ln",
    "sg:city":"Wake Forest",
    "sg:classifiers":[
        {
            "category":"Banks & Credit Unions",
            "subcategory":"Financial Services",
            "type":"Services"
        }
    ],
    "sg:phone":"+1 919 570 9450",
    "sg:postcode":"27587",
    "sg:province":"NC",
    "sg:tags":[
        "company",
        "holding"
    ],
    "wof:name":"Roni Holdings LLC",
    "wof:placetype":"venue"
},
  "geometry": {"coordinates":[-78.50067799999999,35.970291],"type":"Point"}
}