{
  "type": "Feature",
  "properties": {
    "addr:full":"2422 US Hwy 70 Durham NC 27703",
    "addr:housenumber":"2422",
    "addr:postcode":"27703",
    "addr:street":"Us Hwy 70",
    "iso:country":"US",
    "sg:address":"2422 US Hwy 70",
    "sg:city":"Durham",
    "sg:classifiers":[
        {
            "category":"Autos & Motor Vehicles",
            "subcategory":"Boat Sales",
            "type":"Retail Goods"
        },
        {
            "category":"Autos & Motor Vehicles",
            "subcategory":"Motorcycle Sales",
            "type":"Retail Goods"
        }
    ],
    "sg:phone":"+1 919 688 7999",
    "sg:postcode":"27703",
    "sg:province":"NC",
    "sg:tags":[
        "personal",
        "watercraft",
        "sales",
        "dealer"
    ],
    "sg:website":"www.kawasakisuzukidurham.com",
    "wof:name":"Kawasaki-Suzuki of Durham",
    "wof:placetype":"venue"
},
  "geometry": {"coordinates":[-78.82333300000001,35.941303],"type":"Point"}
}