{
  "type": "Feature",
  "properties": {
    "iso:country":"US",
    "sg:address":"402 W Patterson Pl",
    "sg:city":"Chapel Hill",
    "sg:classifiers":[
        {
            "category":"Education",
            "subcategory":"Special Training",
            "type":"Public Place"
        }
    ],
    "sg:phone":"+1   ",
    "sg:postcode":"27516",
    "sg:province":"NC",
    "wof:name":"Michael Sharp",
    "wof:placetype":"venue"
},
  "geometry": {"coordinates":[-79.05878300000001,35.907974],"type":"Point"}
}