{
  "type": "Feature",
  "properties": {
    "iso:country":"US",
    "sg:address":"800 Cricket Knoll Rd",
    "sg:city":"Fuquay Varina",
    "sg:classifiers":[
        {
            "category":"Professional",
            "subcategory":"Art Services",
            "type":"Services"
        }
    ],
    "sg:phone":"+1   ",
    "sg:postcode":"27526",
    "sg:province":"NC",
    "sg:tags":[
        "oil",
        "analysis",
        "vibration"
    ],
    "wof:name":"CMI Performance Diagnostics",
    "wof:placetype":"venue"
},
  "geometry": {"coordinates":[-78.81895799999999,35.56531],"type":"Point"}
}