{
  "type": "Feature",
  "properties": {
    "addr:full":"329 Haywood Rd Asheville NC 28806",
    "addr:housenumber":"329",
    "addr:postcode":"28806",
    "addr:street":"Haywood Rd",
    "iso:country":"US",
    "sg:address":"329 Haywood Rd",
    "sg:city":"Asheville",
    "sg:classifiers":[
        {
            "category":"Real Estate",
            "subcategory":"Real Estate Agent",
            "type":"Services"
        }
    ],
    "sg:phone":"+1 828 216 5425",
    "sg:postcode":"28806",
    "sg:province":"NC",
    "wof:name":"I Buy Homes",
    "wof:placetype":"venue"
},
  "geometry": {"coordinates":[-82.5789,35.577961],"type":"Point"}
}