{
  "type": "Feature",
  "properties": {
    "iso:country":"US",
    "sg:address":"1111 Ocean Blvd W",
    "sg:city":"Supply",
    "sg:classifiers":[
        {
            "category":"Real Estate",
            "subcategory":"Real Estate Agent",
            "type":"Services"
        }
    ],
    "sg:phone":"+1 910 842 3330",
    "sg:postcode":"28462",
    "sg:province":"NC",
    "wof:name":"Alan Holden Realty",
    "wof:placetype":"venue"
},
  "geometry": {"coordinates":[-78.35317999999999,33.905929],"type":"Point"}
}