{
  "type": "Feature",
  "properties": {
    "iso:country":"US",
    "sg:address":"2832 Lester Mills Rd",
    "sg:city":"Greenville",
    "sg:classifiers":[
        {
            "category":"Utilities",
            "subcategory":"Telephone",
            "type":"Services"
        }
    ],
    "sg:phone":"+1 252 746 6305",
    "sg:postcode":"27858",
    "sg:province":"NC",
    "sg:tags":[
        "telecommunication"
    ],
    "wof:name":"Crown Castle USA",
    "wof:placetype":"venue"
},
  "geometry": {"coordinates":[-77.30162199999999,35.494858],"type":"Point"}
}