{
  "type": "Feature",
  "properties": {
    "iso:country":"US",
    "sg:address":"1034 Greenville Hwy",
    "sg:city":"Hendersonville",
    "sg:classifiers":[
        {
            "category":"Shopping",
            "type":"Retail Goods"
        }
    ],
    "sg:phone":"+1 828 698 7877",
    "sg:postcode":"28792",
    "sg:province":"NC",
    "sg:tags":[
        "art",
        "gallery",
        "dealer"
    ],
    "wof:name":"Oliver's Folk Art",
    "wof:placetype":"venue"
},
  "geometry": {"coordinates":[-82.453515,35.298956],"type":"Point"}
}