{
  "type": "Feature",
  "properties": {
    "addr:full":"1774 E Dixon Blvd Shelby NC 28152",
    "addr:housenumber":"1774",
    "addr:postcode":"28152",
    "addr:street":"E Dixon Blvd",
    "iso:country":"US",
    "sg:address":"1774 E Dixon Blvd",
    "sg:city":"Shelby",
    "sg:classifiers":[
        {
            "category":"Banks & Credit Unions",
            "subcategory":"Bank",
            "type":"Services"
        }
    ],
    "sg:phone":"+1 704 487 2940",
    "sg:postcode":"28152",
    "sg:province":"NC",
    "sg:tags":[
        "state"
    ],
    "wof:name":"BB&T",
    "wof:placetype":"venue"
},
  "geometry": {"coordinates":[-81.499047,35.272417],"type":"Point"}
}