{
  "type": "Feature",
  "properties": {
    "iso:country":"US",
    "sg:address":"3722 Shipyard Blvd",
    "sg:city":"Wilmington",
    "sg:classifiers":[
        {
            "category":"Banks & Credit Unions",
            "subcategory":"Investment Brokerage",
            "type":"Services"
        }
    ],
    "sg:phone":"+1 910 452 4066",
    "sg:postcode":"28403",
    "sg:province":"NC",
    "sg:tags":[
        "security"
    ],
    "wof:name":"Edward Jones 14921",
    "wof:placetype":"venue"
},
  "geometry": {"coordinates":[-77.904974,34.196182],"type":"Point"}
}