{
  "type": "Feature",
  "properties": {
    "addr:full":"130 N Fort Fisher Blvd Kure Beach NC 28449",
    "addr:housenumber":"130",
    "addr:postcode":"28449",
    "addr:street":"N Fort Fisher Blvd",
    "iso:country":"US",
    "sg:address":"130 N Fort Fisher Blvd",
    "sg:city":"Kure Beach",
    "sg:classifiers":[
        {
            "category":"Travel",
            "subcategory":"Hotels & Motels",
            "type":"Entertainment"
        }
    ],
    "sg:phone":"+1 910 458 8122",
    "sg:postcode":"28449",
    "sg:province":"NC",
    "sg:website":"www.sevenseasinn.com",
    "wof:name":"Seven Seas Inn",
    "wof:placetype":"venue"
},
  "geometry": {"coordinates":[-77.90584699999999,33.999404],"type":"Point"}
}