{
  "type": "Feature",
  "properties": {
    "iso:country":"US",
    "sg:address":"11103 Stonepath Ln",
    "sg:city":"Charlotte",
    "sg:classifiers":[
        {
            "category":"Wholesale",
            "subcategory":"Groceries",
            "type":"Manufacturing & Wholesale Goods"
        }
    ],
    "sg:phone":"+1 704 752 0805",
    "sg:postcode":"28277",
    "sg:province":"NC",
    "sg:tags":[
        "food",
        "broker"
    ],
    "wof:name":"Perimeter Marketing Inc",
    "wof:placetype":"venue"
},
  "geometry": {"coordinates":[-80.821716,35.058264],"type":"Point"}
}