{
  "type": "Feature",
  "properties": {
    "iso:country":"US",
    "sg:address":"311 S. Polk St",
    "sg:city":"Pineville",
    "sg:classifiers":[
        {
            "category":"Utilities",
            "subcategory":"Electric",
            "type":"Services"
        }
    ],
    "sg:phone":"+1 704 831 8313",
    "sg:postcode":"28134",
    "sg:province":"NC",
    "sg:tags":[
        "equipment-repair"
    ],
    "sg:website":"http://www.cpr-charlotte.com",
    "wof:name":"Charlotte-Cell Phone Repair",
    "wof:placetype":"venue"
},
  "geometry": {"coordinates":[-80.886195,35.082845],"type":"Point"}
}