{
  "type": "Feature",
  "properties": {
    "iso:country":"US",
    "sg:address":"8595 Belews Creek Rd",
    "sg:city":"Stokesdale",
    "sg:classifiers":[
        {
            "category":"Building & Trades",
            "subcategory":"Electrical",
            "type":"Services"
        }
    ],
    "sg:phone":"+1 336 643 4305",
    "sg:postcode":"27357",
    "sg:province":"NC",
    "sg:tags":[
        "electrical",
        "contractor"
    ],
    "wof:name":"Northwest Electric",
    "wof:placetype":"venue"
},
  "geometry": {"coordinates":[-80.006908,36.245445],"type":"Point"}
}