{
  "type": "Feature",
  "properties": {
    "addr:full":"123 State Hwy 801 Advance NC 27006",
    "addr:housenumber":"123",
    "addr:postcode":"27006",
    "addr:street":"State Hwy 801",
    "iso:country":"US",
    "sg:address":"123 State Hwy 801",
    "sg:city":"Advance",
    "sg:classifiers":[
        {
            "category":"Health Services",
            "subcategory":"Doctor",
            "type":"Services"
        }
    ],
    "sg:phone":"+1 336 940 2342",
    "sg:postcode":"27006",
    "sg:province":"NC",
    "sg:tags":[
        "dentist"
    ],
    "wof:name":"Todd H Carter DDS",
    "wof:placetype":"venue"
},
  "geometry": {"coordinates":[-80.438435,36.004394],"type":"Point"}
}