{
  "type": "Feature",
  "properties": {
    "iso:country":"US",
    "sg:address":"3643 Sugarcane Cir",
    "sg:city":"Fayetteville",
    "sg:classifiers":[
        {
            "category":"Health Services",
            "subcategory":"Doctor",
            "type":"Services"
        }
    ],
    "sg:phone":"+1   ",
    "sg:postcode":"28303",
    "sg:province":"NC",
    "sg:tags":[
        "medical"
    ],
    "wof:name":"Hines Radiology PA",
    "wof:placetype":"venue"
},
  "geometry": {"coordinates":[-78.94300800000001,35.071045],"type":"Point"}
}