{
  "type": "Feature",
  "properties": {
    "addr:full":"545 Trade St Winston Salem NC 27101",
    "addr:housenumber":"545",
    "addr:postcode":"27101",
    "addr:street":"Trade St",
    "iso:country":"US",
    "sg:address":"545 Trade St",
    "sg:city":"Winston Salem",
    "sg:classifiers":[
        {
            "category":"Personal",
            "subcategory":"Beauty Salon",
            "type":"Services"
        }
    ],
    "sg:phone":"+1   ",
    "sg:postcode":"27101",
    "sg:province":"NC",
    "sg:tags":[
        "shop"
    ],
    "wof:name":"Hair Pizazz",
    "wof:placetype":"venue"
},
  "geometry": {"coordinates":[-80.246073,36.100676],"type":"Point"}
}