{
  "type": "Feature",
  "properties": {
    "iso:country":"US",
    "sg:address":"505 Mendenhall Dr",
    "sg:city":"Winston Salem",
    "sg:classifiers":[
        {
            "category":"Social Services",
            "subcategory":"Child Care",
            "type":"Services"
        }
    ],
    "sg:phone":"+1   ",
    "sg:postcode":"27127",
    "sg:province":"NC",
    "sg:tags":[
        "day"
    ],
    "wof:name":"Village Child Developement",
    "wof:placetype":"venue"
},
  "geometry": {"coordinates":[-80.26079799999999,35.988395],"type":"Point"}
}