{
  "type": "Feature",
  "properties": {
    "addr:full":"2304 W Cumberland St Dunn NC 28334",
    "addr:housenumber":"2304",
    "addr:postcode":"28334",
    "addr:street":"W Cumberland St",
    "iso:country":"US",
    "sg:address":"2304 W Cumberland St",
    "sg:city":"Dunn",
    "sg:classifiers":[
        {
            "category":"Restaurant",
            "type":"Food & Drink"
        }
    ],
    "sg:menulink":"http://www.allmenus.com/nc/averasboro/137233-subway/menu/",
    "sg:phone":"+1 910 892 0840",
    "sg:postcode":"28334",
    "sg:province":"NC",
    "sg:tags":[
        "american",
        "sandwich"
    ],
    "wof:name":"Subway",
    "wof:placetype":"venue"
},
  "geometry": {"coordinates":[-78.637613,35.321608],"type":"Point"}
}