{
  "type": "Feature",
  "properties": {
    "iso:country":"US",
    "sg:address":"524 S Hoskins Rd",
    "sg:city":"Charlotte",
    "sg:classifiers":[
        {
            "category":"Real Estate",
            "subcategory":"Real Estate Operator",
            "type":"Services"
        }
    ],
    "sg:phone":"+1 704 392 5817",
    "sg:postcode":"28208",
    "sg:province":"NC",
    "sg:tags":[
        "building",
        "apartment",
        "mobile",
        "site",
        "n",
        "home"
    ],
    "wof:name":"Village Properties",
    "wof:placetype":"venue"
},
  "geometry": {"coordinates":[-80.889307,35.26254],"type":"Point"}
}