{
  "type": "Feature",
  "properties": {
    "iso:country":"US",
    "sg:address":"108 Stockbridge Cir",
    "sg:city":"Rocky Mount",
    "sg:classifiers":[
        {
            "category":"Professional",
            "subcategory":"Management & Consulting",
            "type":"Services"
        }
    ],
    "sg:phone":"+1   ",
    "sg:postcode":"27804",
    "sg:province":"NC",
    "sg:tags":[
        "marketing",
        "research"
    ],
    "wof:name":"Marketing Strategy & Planning",
    "wof:placetype":"venue"
},
  "geometry": {"coordinates":[-77.86637899999999,35.972593],"type":"Point"}
}