{
  "type": "Feature",
  "properties": {
    "addr:full":"1012 Panseyhill Ln Willow Spring NC 27592",
    "addr:housenumber":"1012",
    "addr:postcode":"27592",
    "addr:street":"Panseyhill Ln",
    "iso:country":"US",
    "sg:address":"1012 Panseyhill Ln",
    "sg:city":"Willow Spring",
    "sg:classifiers":[
        {
            "category":"Building & Trades",
            "subcategory":"Plumbing",
            "type":"Services"
        }
    ],
    "sg:phone":"+1 919 567 2273",
    "sg:postcode":"27592",
    "sg:province":"NC",
    "sg:tags":[
        "contractor"
    ],
    "wof:name":"Mark Hughes Plumbing Specialst",
    "wof:placetype":"venue"
},
  "geometry": {"coordinates":[-78.659614,35.562397],"type":"Point"}
}