{
  "type": "Feature",
  "properties": {
    "addr:full":"313 Walnut St Wilmington NC 28401",
    "addr:housenumber":"313",
    "addr:postcode":"28401",
    "addr:street":"Walnut St",
    "iso:country":"US",
    "sg:address":"313 Walnut St",
    "sg:city":"Wilmington",
    "sg:classifiers":[
        {
            "category":"Wholesale",
            "subcategory":"Construction Materials",
            "type":"Manufacturing & Wholesale Goods"
        }
    ],
    "sg:phone":"+1 910 762 0072",
    "sg:postcode":"28401",
    "sg:province":"NC",
    "sg:tags":[
        "sand",
        "gravel"
    ],
    "wof:name":"Sitemasters",
    "wof:placetype":"venue"
},
  "geometry": {"coordinates":[-77.946055,34.240227],"type":"Point"}
}