{
  "type": "Feature",
  "properties": {
    "addr:full":"470 Spence Dr Salisbury NC 28144",
    "addr:housenumber":"470",
    "addr:postcode":"28144",
    "addr:street":"Spence Dr",
    "iso:country":"US",
    "sg:address":"470 Spence Dr",
    "sg:city":"Salisbury",
    "sg:classifiers":[
        {
            "category":"Real Estate",
            "subcategory":"Real Estate Operator",
            "type":"Services"
        }
    ],
    "sg:phone":"+1 704 642 1282",
    "sg:postcode":"28144",
    "sg:province":"NC",
    "sg:tags":[
        "building",
        "nonresidential"
    ],
    "wof:name":"Jeter Properties",
    "wof:placetype":"venue"
},
  "geometry": {"coordinates":[-80.470935,35.714807],"type":"Point"}
}