{
  "type": "Feature",
  "properties": {
    "addr:full":"545 Concord Pkwy N Concord NC 28027",
    "addr:housenumber":"545",
    "addr:postcode":"28027",
    "addr:street":"Concord Pkwy N",
    "iso:country":"US",
    "sg:address":"545 Concord Pkwy N",
    "sg:city":"Concord",
    "sg:classifiers":[
        {
            "category":"Restaurant",
            "type":"Food & Drink"
        }
    ],
    "sg:menulink":"http://www.allmenus.com/nc/poplar-tent/87072-little-caesars-pizza/menu/",
    "sg:phone":"+1 704 792 9333",
    "sg:postcode":"28027",
    "sg:province":"NC",
    "sg:tags":[
        "american",
        "pizza"
    ],
    "wof:name":"Little Caesar's Pizza",
    "wof:placetype":"venue"
},
  "geometry": {"coordinates":[-80.615587,35.411669],"type":"Point"}
}