{
  "type": "Feature",
  "properties": {
    "iso:country":"US",
    "sg:address":"14891 State Hwy 72 W",
    "sg:city":"Red Springs",
    "sg:classifiers":[
        {
            "category":"Farming",
            "subcategory":"Farm",
            "type":"Manufacturing & Wholesale Goods"
        }
    ],
    "sg:phone":"+1 910 843 9377",
    "sg:postcode":"28377",
    "sg:province":"NC",
    "wof:name":"Buie Farms",
    "wof:placetype":"venue"
},
  "geometry": {"coordinates":[-79.190556,34.789705],"type":"Point"}
}