{
  "type": "Feature",
  "properties": {
    "addr:full":"201 Oakwood Dr Belmont NC 28012",
    "addr:housenumber":"201",
    "addr:postcode":"28012",
    "addr:street":"Oakwood Dr",
    "iso:country":"US",
    "sg:address":"201 Oakwood Dr",
    "sg:city":"Belmont",
    "sg:classifiers":[
        {
            "category":"Real Estate",
            "subcategory":"Real Estate Operator",
            "type":"Services"
        }
    ],
    "sg:phone":"+1 704 827 4915",
    "sg:postcode":"28012",
    "sg:province":"NC",
    "sg:tags":[
        "building",
        "apartment"
    ],
    "wof:name":"Rein Apts Inc",
    "wof:placetype":"venue"
},
  "geometry": {"coordinates":[-81.057845,35.273734],"type":"Point"}
}