{
  "type": "Feature",
  "properties": {
    "addr:full":"1029 E Broad St Fuquay Varina NC 27526",
    "addr:housenumber":"1029",
    "addr:postcode":"27526",
    "addr:street":"E Broad St",
    "iso:country":"US",
    "sg:address":"1029 E Broad St",
    "sg:city":"Fuquay Varina",
    "sg:classifiers":[
        {
            "category":"Restaurant",
            "type":"Food & Drink"
        }
    ],
    "sg:menulink":"http://www.allmenus.com/nc/middle-creek/65479-cicis-pizza-buffet/menu/",
    "sg:phone":"+1 919 557 4929",
    "sg:postcode":"27526",
    "sg:province":"NC",
    "sg:tags":[
        "american",
        "pizza"
    ],
    "wof:name":"CiCi's Pizza Buffet",
    "wof:placetype":"venue"
},
  "geometry": {"coordinates":[-78.78183300000001,35.592472],"type":"Point"}
}