{
  "type": "Feature",
  "properties": {
    "addr:full":"8 Sandon Cir Asheville NC 28804",
    "addr:housenumber":"8",
    "addr:postcode":"28804",
    "addr:street":"Sandon Cir",
    "iso:country":"US",
    "sg:address":"8 Sandon Cir",
    "sg:city":"Asheville",
    "sg:classifiers":[
        {
            "category":"Building & Trades",
            "subcategory":"Construction",
            "type":"Services"
        }
    ],
    "sg:phone":"+1 828 252 3739",
    "sg:postcode":"28804",
    "sg:province":"NC",
    "sg:tags":[
        "contractor"
    ],
    "wof:name":"Harmony Builders Inc",
    "wof:placetype":"venue"
},
  "geometry": {"coordinates":[-82.557652,35.624425],"type":"Point"}
}