{
  "type": "Feature",
  "properties": {
    "addr:full":"249 Cedar Lake Farm Rd Cherryville NC 28021",
    "addr:housenumber":"249",
    "addr:postcode":"28021",
    "addr:street":"Cedar Lake Farm Rd",
    "iso:country":"US",
    "sg:address":"249 Cedar Lake Farm Rd",
    "sg:city":"Cherryville",
    "sg:classifiers":[
        {
            "category":"Freight",
            "type":"Transportation"
        }
    ],
    "sg:phone":"+1 704 739 4884",
    "sg:postcode":"28021",
    "sg:province":"NC",
    "sg:tags":[
        "operator",
        "local",
        "trucking"
    ],
    "wof:name":"B & C Equipment Inc",
    "wof:placetype":"venue"
},
  "geometry": {"coordinates":[-81.44954,35.406206],"type":"Point"}
}