{
  "type": "Feature",
  "properties": {
    "addr:full":"5905 Fayetteville Rd Raleigh NC 27603",
    "addr:housenumber":"5905",
    "addr:postcode":"27603",
    "addr:street":"Fayetteville Rd",
    "iso:country":"US",
    "sg:address":"5905 Fayetteville Rd",
    "sg:city":"Raleigh",
    "sg:classifiers":[
        {
            "category":"Home & Garden",
            "subcategory":"Furniture",
            "type":"Retail Goods"
        }
    ],
    "sg:phone":"+1 919 329 7944",
    "sg:postcode":"27603",
    "sg:province":"NC",
    "wof:name":"Furniture House Of Values",
    "wof:placetype":"venue"
},
  "geometry": {"coordinates":[-78.67182200000001,35.698075],"type":"Point"}
}