{
  "type": "Feature",
  "properties": {
    "iso:country":"US",
    "sg:address":"2883 Grainger Station Rd",
    "sg:city":"Kinston",
    "sg:classifiers":[
        {
            "category":"Farming",
            "subcategory":"Farm",
            "type":"Manufacturing & Wholesale Goods"
        }
    ],
    "sg:phone":"+1 252 523 1954",
    "sg:postcode":"28501",
    "sg:province":"NC",
    "sg:tags":[
        "crop",
        "general"
    ],
    "wof:name":"Broadway Farms",
    "wof:placetype":"venue"
},
  "geometry": {"coordinates":[-77.511815,35.317571],"type":"Point"}
}