{
  "type": "Feature",
  "properties": {
    "addr:full":"2012 Azalea Dr Goldsboro NC 27530",
    "addr:housenumber":"2012",
    "addr:postcode":"27530",
    "addr:street":"Azalea Dr",
    "iso:country":"US",
    "sg:address":"2012 Azalea Dr",
    "sg:city":"Goldsboro",
    "sg:classifiers":[
        {
            "category":"Professional",
            "subcategory":"Advertising",
            "type":"Services"
        }
    ],
    "sg:phone":"+1 919 759 0000",
    "sg:postcode":"27530",
    "sg:province":"NC",
    "sg:tags":[
        "representative"
    ],
    "wof:name":"Time Warner",
    "wof:placetype":"venue"
},
  "geometry": {"coordinates":[-77.99575900000001,35.410982],"type":"Point"}
}