{
  "type": "Feature",
  "properties": {
    "iso:country":"US",
    "sg:address":"1106 Chalmers St",
    "sg:city":"Durham",
    "sg:classifiers":[
        {
            "category":"Utilities",
            "subcategory":"Cable",
            "type":"Services"
        }
    ],
    "sg:phone":"+1 919 688 9416",
    "sg:postcode":"27707",
    "sg:province":"NC",
    "sg:tags":[
        "television"
    ],
    "wof:name":"Evans Satellite Systems",
    "wof:placetype":"venue"
},
  "geometry": {"coordinates":[-78.894375,35.957584],"type":"Point"}
}