{
  "type": "Feature",
  "properties": {
    "addr:full":"1511 Benvenue Rd Rocky Mount NC 27804",
    "addr:housenumber":"1511",
    "addr:postcode":"27804",
    "addr:street":"Benvenue Rd",
    "iso:country":"US",
    "sg:address":"1511 Benvenue Rd",
    "sg:city":"Rocky Mount",
    "sg:classifiers":[
        {
            "category":"Professional",
            "subcategory":"Accounting & Tax Preparation",
            "type":"Services"
        }
    ],
    "sg:phone":"+1 252 442 3959",
    "sg:postcode":"27804",
    "sg:province":"NC",
    "sg:tags":[
        "return",
        "filing"
    ],
    "sg:website":"www.jacksonhewitt.com",
    "wof:name":"Jackson Hewitt Tax Svc",
    "wof:placetype":"venue"
},
  "geometry": {"coordinates":[-77.808419,35.980048],"type":"Point"}
}