{
  "type": "Feature",
  "properties": {
    "addr:full":"4336 Roxboro Rd Durham NC 27704",
    "addr:housenumber":"4336",
    "addr:postcode":"27704",
    "addr:street":"Roxboro Rd",
    "iso:country":"US",
    "sg:address":"4336 Roxboro Rd",
    "sg:city":"Durham",
    "sg:classifiers":[
        {
            "category":"Autos & Motor Vehicles",
            "subcategory":"Automobile Sales",
            "type":"Retail Goods"
        }
    ],
    "sg:phone":"+1 919 471 6000",
    "sg:postcode":"27704",
    "sg:province":"NC",
    "sg:tags":[
        "used",
        "truck"
    ],
    "wof:name":"CBS Quality Cars Inc",
    "wof:placetype":"venue"
},
  "geometry": {"coordinates":[-78.90331500000001,36.05305],"type":"Point"}
}