{
  "type": "Feature",
  "properties": {
    "iso:country":"US",
    "sg:address":"562 Barrus Construction Rd",
    "sg:city":"Greenville",
    "sg:classifiers":[
        {
            "category":"Building & Trades",
            "subcategory":"Construction",
            "type":"Services"
        }
    ],
    "sg:phone":"+1 252 752 2587",
    "sg:postcode":"27834",
    "sg:province":"NC",
    "sg:tags":[
        "general",
        "contractor"
    ],
    "wof:name":"DPD Team Concrete",
    "wof:placetype":"venue"
},
  "geometry": {"coordinates":[-77.442122,35.671815],"type":"Point"}
}