{
  "type": "Feature",
  "properties": {
    "iso:country":"US",
    "sg:address":"4 Indian Trl",
    "sg:city":"Weaverville",
    "sg:classifiers":[
        {
            "category":"Building & Trades",
            "subcategory":"Construction",
            "type":"Services"
        }
    ],
    "sg:phone":"+1 828 645 3332",
    "sg:postcode":"28787",
    "sg:province":"NC",
    "sg:tags":[
        "house"
    ],
    "wof:name":"Trantham Const Co Inc",
    "wof:placetype":"venue"
},
  "geometry": {"coordinates":[-82.607876,35.740635],"type":"Point"}
}