{
  "type": "Feature",
  "properties": {
    "iso:country":"US",
    "sg:address":"155 E Pennsylvania Ave",
    "sg:city":"Southern Pines",
    "sg:classifiers":[
        {
            "category":"Insurance",
            "subcategory":"Life Insurance",
            "type":"Services"
        }
    ],
    "sg:phone":"+1 910 692 2126",
    "sg:postcode":"28387",
    "sg:province":"NC",
    "sg:tags":[
        "carrier"
    ],
    "wof:name":"MetLife",
    "wof:placetype":"venue"
},
  "geometry": {"coordinates":[-79.391278,35.173176],"type":"Point"}
}