{
  "type": "Feature",
  "properties": {
    "iso:country":"US",
    "sg:address":"122 E Saint James St",
    "sg:city":"Tarboro",
    "sg:classifiers":[
        {
            "category":"Utilities",
            "subcategory":"Mobile Phone",
            "type":"Services"
        }
    ],
    "sg:phone":"+1 252 823 9900",
    "sg:postcode":"27886",
    "sg:province":"NC",
    "sg:tags":[
        "telephone",
        "cellular"
    ],
    "wof:name":"Sprint Wireless Ctr",
    "wof:placetype":"venue"
},
  "geometry": {"coordinates":[-77.533815,35.897827],"type":"Point"}
}