{
  "type": "Feature",
  "properties": {
    "iso:country":"US",
    "sg:address":"112 Scarboro St",
    "sg:city":"Asheboro",
    "sg:classifiers":[
        {
            "category":"Insurance",
            "subcategory":"Insurance Agent",
            "type":"Services"
        }
    ],
    "sg:phone":"+1 336 626 7264",
    "sg:postcode":"27203",
    "sg:province":"NC",
    "wof:name":"Stan Beck",
    "wof:placetype":"venue"
},
  "geometry": {"coordinates":[-79.81394400000001,35.704894],"type":"Point"}
}