{
  "type": "Feature",
  "properties": {
    "iso:country":"US",
    "sg:address":"373 Barrington Ridge",
    "sg:city":"Newport",
    "sg:classifiers":[
        {
            "category":"Personal",
            "type":"Services"
        }
    ],
    "sg:phone":"+1   ",
    "sg:postcode":"28570",
    "sg:province":"NC",
    "sg:tags":[
        "contracting",
        "general"
    ],
    "wof:name":"Trademark Homes",
    "wof:placetype":"venue"
},
  "geometry": {"coordinates":[-77.032895,34.706598],"type":"Point"}
}