{
  "type": "Feature",
  "properties": {
    "addr:full":"81 Broadway St Asheville NC 28801",
    "addr:housenumber":"81",
    "addr:postcode":"28801",
    "addr:street":"Broadway St",
    "iso:country":"US",
    "sg:address":"81 Broadway St",
    "sg:city":"Asheville",
    "sg:classifiers":[
        {
            "category":"Bars & Pubs",
            "type":"Food & Drink"
        }
    ],
    "sg:phone":"+1 828 251 8280",
    "sg:postcode":"28801",
    "sg:province":"NC",
    "wof:name":"Whiskey Tavern",
    "wof:placetype":"venue"
},
  "geometry": {"coordinates":[-82.55221899999999,35.596645],"type":"Point"}
}