{
  "type": "Feature",
  "properties": {
    "iso:country":"US",
    "sg:address":"1241 S Main St",
    "sg:city":"Wake Forest",
    "sg:classifiers":[
        {
            "category":"Professional",
            "subcategory":"Accounting & Tax Preparation",
            "type":"Services"
        }
    ],
    "sg:phone":"+1 919 554 6537",
    "sg:postcode":"27587",
    "sg:province":"NC",
    "sg:tags":[
        "return",
        "filing"
    ],
    "wof:name":"Alliance Tax Svc",
    "wof:placetype":"venue"
},
  "geometry": {"coordinates":[-78.518113,35.962499],"type":"Point"}
}