{
  "type": "Feature",
  "properties": {
    "iso:country":"US",
    "sg:address":"2322 US Hwy 52",
    "sg:city":"Albemarle",
    "sg:classifiers":[
        {
            "category":"Restaurant",
            "type":"Food & Drink"
        }
    ],
    "sg:phone":"+1 704 982 5257",
    "sg:postcode":"28001",
    "sg:province":"NC",
    "sg:tags":[
        "eating"
    ],
    "wof:name":"Log Cabin Bar B Que",
    "wof:placetype":"venue"
},
  "geometry": {"coordinates":[-80.19923900000001,35.395094],"type":"Point"}
}