{
  "type": "Feature",
  "properties": {
    "iso:country":"US",
    "sg:address":"1318 Central Ave Ste A10",
    "sg:city":"Charlotte",
    "sg:classifiers":[
        {
            "category":"Professional",
            "subcategory":"Management & Consulting",
            "type":"Services"
        },
        {
            "category":"Professional",
            "subcategory":"Advertising",
            "type":"Services"
        }
    ],
    "sg:phone":"+1 704 375 9350",
    "sg:postcode":"28205",
    "sg:province":"NC",
    "sg:tags":[
        "marketing",
        "program",
        "consultant"
    ],
    "wof:name":"Greenspon Ritz Marketing Group",
    "wof:placetype":"venue"
},
  "geometry": {"coordinates":[-80.816377,35.220865],"type":"Point"}
}