{
  "type": "Feature",
  "properties": {
    "addr:full":"2759 S Church St Burlington NC 27215",
    "addr:housenumber":"2759",
    "addr:postcode":"27215",
    "addr:street":"S Church St",
    "iso:country":"US",
    "sg:address":"2759 S Church St",
    "sg:city":"Burlington",
    "sg:classifiers":[
        {
            "category":"Professional",
            "subcategory":"Business Services",
            "type":"Services"
        }
    ],
    "sg:phone":"+1 336 538 0801",
    "sg:postcode":"27215",
    "sg:province":"NC",
    "sg:tags":[
        "packaging"
    ],
    "wof:name":"Pak Mail Ctr",
    "wof:placetype":"venue"
},
  "geometry": {"coordinates":[-79.489874,36.0807],"type":"Point"}
}