{
  "type": "Feature",
  "properties": {
    "addr:full":"405 S Main St Lexington NC 27292",
    "addr:housenumber":"405",
    "addr:postcode":"27292",
    "addr:street":"S Main St",
    "iso:country":"US",
    "sg:address":"405 S Main St",
    "sg:city":"Lexington",
    "sg:classifiers":[
        {
            "category":"Retail",
            "subcategory":"Funeral Services",
            "type":"Services"
        }
    ],
    "sg:phone":"+1 336 248 2366",
    "sg:postcode":"27292",
    "sg:province":"NC",
    "sg:tags":[
        "director"
    ],
    "wof:name":"Piedmont Funeral Home",
    "wof:placetype":"venue"
},
  "geometry": {"coordinates":[-80.256576,35.821042],"type":"Point"}
}