{
  "type": "Feature",
  "properties": {
    "addr:full":"6521 Wynbrook Way Raleigh NC 27612",
    "addr:housenumber":"6521",
    "addr:postcode":"27612",
    "addr:street":"Wynbrook Way",
    "iso:country":"US",
    "sg:address":"6521 Wynbrook Way",
    "sg:city":"Raleigh",
    "sg:classifiers":[
        {
            "category":"Professional",
            "subcategory":"Detective & Security Services",
            "type":"Services"
        }
    ],
    "sg:phone":"+1 919 844 1483",
    "sg:postcode":"27612",
    "sg:province":"NC",
    "wof:name":"Pickett Macks Investigative",
    "wof:placetype":"venue"
},
  "geometry": {"coordinates":[-78.67115699999999,35.869552],"type":"Point"}
}