{
  "type": "Feature",
  "properties": {
    "iso:country":"US",
    "sg:address":"2 Clubhouse Dr SW",
    "sg:city":"Supply",
    "sg:classifiers":[
        {
            "category":"Organizations",
            "subcategory":"Community Association",
            "type":"Services"
        }
    ],
    "sg:phone":"+1   ",
    "sg:postcode":"28462",
    "sg:province":"NC",
    "wof:name":"Links Homeowners Assn Inc",
    "wof:placetype":"venue"
},
  "geometry": {"coordinates":[-78.236178,33.936164],"type":"Point"}
}