{
  "type": "Feature",
  "properties": {
    "addr:full":"106 City Hall Plz Durham NC 27701",
    "addr:housenumber":"106",
    "addr:postcode":"27701",
    "addr:street":"City Hall Plz",
    "iso:country":"US",
    "sg:address":"106 City Hall Plz",
    "sg:city":"Durham",
    "sg:classifiers":[
        {
            "category":"Organizations",
            "subcategory":"Non-profit Organization",
            "type":"Services"
        }
    ],
    "sg:phone":"+1 919 680 6500",
    "sg:postcode":"27701",
    "sg:province":"NC",
    "sg:tags":[
        "information",
        "alcoholism",
        "treatment"
    ],
    "wof:name":"Alcohol 24 Hour Abuse A & A",
    "wof:placetype":"venue"
},
  "geometry": {"coordinates":[-78.898087,35.995807],"type":"Point"}
}