{
  "type": "Feature",
  "properties": {
    "iso:country":"US",
    "sg:address":"11828 Planters Estates Dr",
    "sg:city":"Charlotte",
    "sg:classifiers":[
        {
            "category":"Retail",
            "subcategory":"Repair Shop",
            "type":"Services"
        }
    ],
    "sg:phone":"+1   ",
    "sg:postcode":"28278",
    "sg:province":"NC",
    "sg:tags":[
        "aircraft",
        "maintenance"
    ],
    "wof:name":"Sutton Aviation Services",
    "wof:placetype":"venue"
},
  "geometry": {"coordinates":[-80.993151,35.123697],"type":"Point"}
}