{
  "type": "Feature",
  "properties": {
    "addr:full":"60 Dorchester Ave Asheville NC 28806",
    "addr:housenumber":"60",
    "addr:postcode":"28806",
    "addr:street":"Dorchester Ave",
    "iso:country":"US",
    "sg:address":"60 Dorchester Ave",
    "sg:city":"Asheville",
    "sg:classifiers":[
        {
            "category":"Building & Trades",
            "subcategory":"Plumbing",
            "type":"Services"
        }
    ],
    "sg:phone":"+1 828 252 5606",
    "sg:postcode":"28806",
    "sg:province":"NC",
    "sg:tags":[
        "plumbing",
        "contractor"
    ],
    "wof:name":"Harwood Plumbing",
    "wof:placetype":"venue"
},
  "geometry": {"coordinates":[-82.588764,35.580331],"type":"Point"}
}