{
  "type": "Feature",
  "properties": {
    "addr:full":"3701 Barclay Downs Dr Charlotte NC 28209",
    "addr:housenumber":"3701",
    "addr:postcode":"28209",
    "addr:street":"Barclay Downs Dr",
    "iso:country":"US",
    "sg:address":"3701 Barclay Downs Dr",
    "sg:city":"Charlotte",
    "sg:classifiers":[
        {
            "category":"Sports & Exercise",
            "subcategory":"Golf",
            "type":"Entertainment"
        }
    ],
    "sg:phone":"+1   ",
    "sg:postcode":"28209",
    "sg:province":"NC",
    "sg:tags":[
        "course",
        "public"
    ],
    "wof:name":"Augusta Golf Inc",
    "wof:placetype":"venue"
},
  "geometry": {"coordinates":[-80.837476,35.161954],"type":"Point"}
}