{
  "type": "Feature",
  "properties": {
    "iso:country":"US",
    "sg:address":"214 S Rutherford St",
    "sg:city":"Wadesboro",
    "sg:classifiers":[
        {
            "category":"Shopping",
            "subcategory":"Gifts & Souvenirs",
            "type":"Retail Goods"
        }
    ],
    "sg:phone":"+1 704 695 1370",
    "sg:postcode":"28170",
    "sg:province":"NC",
    "sg:tags":[
        "party",
        "supply"
    ],
    "wof:name":"Anson Democratic Party",
    "wof:placetype":"venue"
},
  "geometry": {"coordinates":[-80.078434,34.964058],"type":"Point"}
}