{
  "type": "Feature",
  "properties": {
    "iso:country":"US",
    "sg:address":"5071 Pisgah Covered Bridge Rd",
    "sg:city":"Asheboro",
    "sg:classifiers":[
        {
            "category":"Building & Trades",
            "subcategory":"Construction",
            "type":"Services"
        }
    ],
    "sg:phone":"+1 336 381 3443",
    "sg:postcode":"27205",
    "sg:province":"NC",
    "sg:tags":[
        "concrete",
        "contractor"
    ],
    "wof:name":"Luther Wlter Cnter Tops Floors",
    "wof:placetype":"venue"
},
  "geometry": {"coordinates":[-79.87238600000001,35.572413],"type":"Point"}
}