{
  "type": "Feature",
  "properties": {
    "iso:country":"US",
    "sg:address":"112 Stratford Dr",
    "sg:city":"Louisburg",
    "sg:classifiers":[
        {
            "category":"Wholesale",
            "subcategory":"Poultry",
            "type":"Manufacturing & Wholesale Goods"
        }
    ],
    "sg:phone":"+1 919 496 4817",
    "sg:postcode":"27549",
    "sg:province":"NC",
    "sg:tags":[
        "seafood"
    ],
    "wof:name":"Dean Farms Inc",
    "wof:placetype":"venue"
},
  "geometry": {"coordinates":[-78.28699899999999,36.112857],"type":"Point"}
}