{
  "type": "Feature",
  "properties": {
    "iso:country":"US",
    "sg:address":"2505 Neuse Blvd",
    "sg:city":"New Bern",
    "sg:classifiers":[
        {
            "category":"Professional",
            "subcategory":"Engineering",
            "type":"Services"
        }
    ],
    "sg:phone":"+1   ",
    "sg:postcode":"28562",
    "sg:province":"NC",
    "wof:name":"Brinkley Construction",
    "wof:placetype":"venue"
},
  "geometry": {"coordinates":[-77.07673200000001,35.117702],"type":"Point"}
}