{
  "type": "Feature",
  "properties": {
    "iso:country":"US",
    "sg:address":"105 Hospital Dr",
    "sg:city":"Lexington",
    "sg:classifiers":[
        {
            "category":"Health Services",
            "subcategory":"Doctor",
            "type":"Services"
        }
    ],
    "sg:phone":"+1 336 236 4568",
    "sg:postcode":"27292",
    "sg:province":"NC",
    "sg:tags":[
        "medical"
    ],
    "wof:name":"Davidson Internists",
    "wof:placetype":"venue"
},
  "geometry": {"coordinates":[-80.287899,35.803303],"type":"Point"}
}