{
  "type": "Feature",
  "properties": {
    "addr:full":"809 Cedar Dr Kill Devil Hills NC 27948",
    "addr:housenumber":"809",
    "addr:postcode":"27948",
    "addr:street":"Cedar Dr",
    "iso:country":"US",
    "sg:address":"809 Cedar Dr",
    "sg:city":"Kill Devil Hills",
    "sg:classifiers":[
        {
            "category":"Bars & Pubs",
            "type":"Food & Drink"
        }
    ],
    "sg:phone":"+1 252 441 8530",
    "sg:postcode":"27948",
    "sg:province":"NC",
    "sg:tags":[
        "drinking"
    ],
    "wof:name":"Tap Agency LLC",
    "wof:placetype":"venue"
},
  "geometry": {"coordinates":[-75.68022499999999,36.021531],"type":"Point"}
}