{
  "type": "Feature",
  "properties": {
    "iso:country":"US",
    "sg:address":"2729 Ring Rd",
    "sg:city":"Greensboro",
    "sg:classifiers":[
        {
            "category":"Bus Charters",
            "type":"Transportation"
        }
    ],
    "sg:phone":"+1 336 375 7748",
    "sg:postcode":"27405",
    "sg:province":"NC",
    "wof:name":"Sho Tranz Executive LLC",
    "wof:placetype":"venue"
},
  "geometry": {"coordinates":[-79.757295,36.108103],"type":"Point"}
}