{
  "type": "Feature",
  "properties": {
    "addr:full":"271 Cow Horn Rd Richlands NC 28574",
    "addr:housenumber":"271",
    "addr:postcode":"28574",
    "addr:street":"Cow Horn Rd",
    "iso:country":"US",
    "sg:address":"271 Cow Horn Rd",
    "sg:city":"Richlands",
    "sg:classifiers":[
        {
            "category":"Professional",
            "subcategory":"Business Services",
            "type":"Services"
        }
    ],
    "sg:phone":"+1 910 324 7093",
    "sg:postcode":"28574",
    "sg:province":"NC",
    "sg:tags":[
        "website",
        "design",
        "hosting"
    ],
    "wof:name":"Washington Enterprises",
    "wof:placetype":"venue"
},
  "geometry": {"coordinates":[-77.50841,34.884626],"type":"Point"}
}