{
  "type": "Feature",
  "properties": {
    "addr:full":"1338 Balls Creek Rd Claremont NC 28610",
    "addr:housenumber":"1338",
    "addr:postcode":"28610",
    "addr:street":"Balls Creek Rd",
    "iso:country":"US",
    "sg:address":"1338 Balls Creek Rd",
    "sg:city":"Claremont",
    "sg:classifiers":[
        {
            "category":"Professional",
            "subcategory":"Business Services",
            "type":"Services"
        }
    ],
    "sg:phone":"+1 828 241 2088",
    "sg:postcode":"28610",
    "sg:province":"NC",
    "wof:name":"Sipe Landscape & Design",
    "wof:placetype":"venue"
},
  "geometry": {"coordinates":[-81.113226,35.667329],"type":"Point"}
}