{
  "type": "Feature",
  "properties": {
    "iso:country":"US",
    "sg:address":"832 S Fifth St",
    "sg:city":"Mebane",
    "sg:classifiers":[
        {
            "category":"Restaurant",
            "type":"Food & Drink"
        }
    ],
    "sg:menulink":"http://www.allmenus.com/nc/melville/214550-biscuitville/menu/",
    "sg:phone":"+1 919 563 8498",
    "sg:postcode":"27302",
    "sg:province":"NC",
    "sg:tags":[
        "american"
    ],
    "wof:name":"Biscuitville",
    "wof:placetype":"venue"
},
  "geometry": {"coordinates":[-79.273909,36.080149],"type":"Point"}
}