{
  "type": "Feature",
  "properties": {
    "addr:full":"7570 State Rd 700 Ruffin NC 27288",
    "addr:housenumber":"7570;700",
    "addr:postcode":"27288",
    "addr:street":"State Rd",
    "iso:country":"US",
    "sg:address":"7570 State Rd 700",
    "sg:city":"Ruffin",
    "sg:classifiers":[
        {
            "category":"Professional",
            "subcategory":"Management & Consulting",
            "type":"Services"
        }
    ],
    "sg:phone":"+1 336 939 9158",
    "sg:postcode":"27288",
    "sg:province":"NC",
    "sg:tags":[
        "consultant",
        "business"
    ],
    "wof:name":"Hutson Clinical Lab Consultant",
    "wof:placetype":"venue"
},
  "geometry": {"coordinates":[-79.589179,36.508018],"type":"Point"}
}