{
  "type": "Feature",
  "properties": {
    "addr:full":"719 Farmhurst Dr Charlotte NC 28217",
    "addr:housenumber":"719",
    "addr:postcode":"28217",
    "addr:street":"Farmhurst Dr",
    "iso:country":"US",
    "sg:address":"719 Farmhurst Dr",
    "sg:city":"Charlotte",
    "sg:classifiers":[
        {
            "category":"Social Services",
            "type":"Services"
        }
    ],
    "sg:phone":"+1 704 561 9543",
    "sg:postcode":"28217",
    "sg:province":"NC",
    "sg:tags":[
        "referral"
    ],
    "wof:name":"Ellerbe & Assoc LLC",
    "wof:placetype":"venue"
},
  "geometry": {"coordinates":[-80.891582,35.146949],"type":"Point"}
}