{
  "type": "Feature",
  "properties": {
    "iso:country":"US",
    "sg:address":"202 W Queen St",
    "sg:city":"Hillsborough",
    "sg:classifiers":[
        {
            "category":"Building & Trades",
            "subcategory":"Construction",
            "type":"Services"
        }
    ],
    "sg:phone":"+1 919 563 2005",
    "sg:postcode":"27278",
    "sg:province":"NC",
    "sg:tags":[
        "home",
        "builder"
    ],
    "wof:name":"Stonewall Custom Homes Inc",
    "wof:placetype":"venue"
},
  "geometry": {"coordinates":[-79.102591,36.078759],"type":"Point"}
}