{
  "type": "Feature",
  "properties": {
    "addr:full":"353 Oak Grove Church Rd Mocksville NC 27028",
    "addr:housenumber":"353",
    "addr:postcode":"27028",
    "addr:street":"Oak Grove Church Rd",
    "iso:country":"US",
    "sg:address":"353 Oak Grove Church Rd",
    "sg:city":"Mocksville",
    "sg:classifiers":[
        {
            "category":"Building & Trades",
            "subcategory":"Construction",
            "type":"Services"
        }
    ],
    "sg:phone":"+1 336 972 2402",
    "sg:postcode":"27028",
    "sg:province":"NC",
    "sg:tags":[
        "painter"
    ],
    "wof:name":"Andy's First Choice Painting",
    "wof:placetype":"venue"
},
  "geometry": {"coordinates":[-80.539452,35.928783],"type":"Point"}
}