{
  "type": "Feature",
  "properties": {
    "addr:full":"331 1st Ave E Hendersonville NC 28792",
    "addr:housenumber":"331",
    "addr:postcode":"28792",
    "addr:street":"1St Ave E",
    "iso:country":"US",
    "sg:address":"331 1st Ave E",
    "sg:city":"Hendersonville",
    "sg:classifiers":[
        {
            "category":"Government",
            "subcategory":"Office",
            "type":"Public Place"
        }
    ],
    "sg:phone":"+1 828 697 4817",
    "sg:postcode":"28792",
    "sg:province":"NC",
    "sg:tags":[
        "affairs",
        "administrative"
    ],
    "wof:name":"Henderson County Veterans Svc",
    "wof:placetype":"venue"
},
  "geometry": {"coordinates":[-82.456305,35.314876],"type":"Point"}
}