{
  "type": "Feature",
  "properties": {
    "addr:full":"26 Mo's Way Candler NC 28715",
    "addr:housenumber":"26",
    "addr:postcode":"28715",
    "addr:street":"Mo'S Way",
    "iso:country":"US",
    "sg:address":"26 Mo's Way",
    "sg:city":"Candler",
    "sg:classifiers":[
        {
            "category":"Retail",
            "subcategory":"Repair Shop",
            "type":"Services"
        }
    ],
    "sg:phone":"+1   ",
    "sg:postcode":"28715",
    "sg:province":"NC",
    "wof:name":"Keymasters Safe & Lock",
    "wof:placetype":"venue"
},
  "geometry": {"coordinates":[-82.653038,35.512487],"type":"Point"}
}