{
  "type": "Feature",
  "properties": {
    "iso:country":"US",
    "sg:address":"6130 Andrew Thomas Dr",
    "sg:city":"Charlotte",
    "sg:classifiers":[
        {
            "category":"Freight",
            "type":"Transportation"
        }
    ],
    "sg:phone":"+1 704 363 3640",
    "sg:postcode":"28269",
    "sg:province":"NC",
    "sg:tags":[
        "delivery"
    ],
    "wof:name":"C & C Logistics Inc",
    "wof:placetype":"venue"
},
  "geometry": {"coordinates":[-80.800138,35.332059],"type":"Point"}
}