{
  "type": "Feature",
  "properties": {
    "iso:country":"US",
    "sg:address":"6112 Old Pineville Rd",
    "sg:city":"Charlotte",
    "sg:classifiers":[
        {
            "category":"Building & Trades",
            "subcategory":"Electrical",
            "type":"Services"
        }
    ],
    "sg:phone":"+1 704 527 4646",
    "sg:postcode":"28217",
    "sg:province":"NC",
    "sg:tags":[
        "industrial",
        "electrician",
        "contractors-commercial",
        "electric"
    ],
    "wof:name":"Vision Electric Inc",
    "wof:placetype":"venue"
},
  "geometry": {"coordinates":[-80.877177,35.157307],"type":"Point"}
}