{
  "type": "Feature",
  "properties": {
    "iso:country":"US",
    "sg:address":"10101 Beach Dr SW",
    "sg:city":"Calabash",
    "sg:classifiers":[
        {
            "category":"Restaurant",
            "type":"Food & Drink"
        }
    ],
    "sg:phone":"+1 910 579 6228",
    "sg:postcode":"28467",
    "sg:province":"NC",
    "wof:name":"Derbster's",
    "wof:placetype":"venue"
},
  "geometry": {"coordinates":[-78.572936,33.89079],"type":"Point"}
}