{
  "type": "Feature",
  "properties": {
    "addr:full":"133 S Powell St Forest City NC 28043",
    "addr:housenumber":"133",
    "addr:postcode":"28043",
    "addr:street":"S Powell St",
    "iso:country":"US",
    "sg:address":"133 S Powell St",
    "sg:city":"Forest City",
    "sg:classifiers":[
        {
            "category":"Government",
            "subcategory":"Post Office",
            "type":"Public Place"
        }
    ],
    "sg:phone":"+1 828 245 2815",
    "sg:postcode":"28043",
    "sg:province":"NC",
    "wof:name":"US Post Office",
    "wof:placetype":"venue"
},
  "geometry": {"coordinates":[-81.863435,35.332611],"type":"Point"}
}