{
  "type": "Feature",
  "properties": {
    "addr:full":"3492 Buffalo Shoals Rd Newton NC 28658",
    "addr:housenumber":"3492",
    "addr:postcode":"28658",
    "addr:street":"Buffalo Shoals Rd",
    "iso:country":"US",
    "sg:address":"3492 Buffalo Shoals Rd",
    "sg:city":"Newton",
    "sg:classifiers":[
        {
            "category":"Building & Trades",
            "subcategory":"Equipment Rental",
            "type":"Services"
        }
    ],
    "sg:phone":"+1 828 428 0444",
    "sg:postcode":"28658",
    "sg:province":"NC",
    "sg:tags":[
        "toilet"
    ],
    "wof:name":"Cst Portable Sanitation",
    "wof:placetype":"venue"
},
  "geometry": {"coordinates":[-81.12379,35.588511],"type":"Point"}
}