{
  "type": "Feature",
  "properties": {
    "iso:country":"US",
    "sg:address":"410 Painted Spindle Ct",
    "sg:city":"Wilmington",
    "sg:classifiers":[
        {
            "category":"Building & Trades",
            "subcategory":"Landscaping Services",
            "type":"Services"
        }
    ],
    "sg:phone":"+1 910 796 3292",
    "sg:postcode":"28405",
    "sg:province":"NC",
    "wof:name":"Passionate Garden",
    "wof:placetype":"venue"
},
  "geometry": {"coordinates":[-77.832489,34.252944],"type":"Point"}
}