{
  "type": "Feature",
  "properties": {
    "addr:full":"1397 Charlotte Hwy Fairview NC 28730",
    "addr:housenumber":"1397",
    "addr:postcode":"28730",
    "addr:street":"Charlotte Hwy",
    "iso:country":"US",
    "sg:address":"1397 Charlotte Hwy",
    "sg:city":"Fairview",
    "sg:classifiers":[
        {
            "category":"Restaurant",
            "type":"Food & Drink"
        }
    ],
    "sg:phone":"+1 828 628 3080",
    "sg:postcode":"28730",
    "sg:province":"NC",
    "sg:tags":[
        "eating"
    ],
    "wof:name":"Subway",
    "wof:placetype":"venue"
},
  "geometry": {"coordinates":[-82.411776,35.524033],"type":"Point"}
}