{
  "type": "Feature",
  "properties": {
    "addr:full":"3801 Wake Forest Rd Raleigh NC 27609",
    "addr:housenumber":"3801",
    "addr:postcode":"27609",
    "addr:street":"Wake Forest Rd",
    "iso:country":"US",
    "sg:address":"3801 Wake Forest Rd",
    "sg:city":"Raleigh",
    "sg:classifiers":[
        {
            "category":"Manufacturing",
            "subcategory":"Printing",
            "type":"Manufacturing & Wholesale Goods"
        }
    ],
    "sg:phone":"+1 919 872 7077",
    "sg:postcode":"27609",
    "sg:province":"NC",
    "sg:tags":[
        "periodical"
    ],
    "wof:name":"Business Leader",
    "wof:placetype":"venue"
},
  "geometry": {"coordinates":[-78.61606399999999,35.834139],"type":"Point"}
}