{
  "type": "Feature",
  "properties": {
    "addr:full":"2500 State Hwy 87 S Cameron NC 28326",
    "addr:housenumber":"2500",
    "addr:postcode":"28326",
    "addr:street":"State Hwy 87 S",
    "iso:country":"US",
    "sg:address":"2500 State Hwy 87 S",
    "sg:city":"Cameron",
    "sg:classifiers":[
        {
            "category":"Building & Trades",
            "subcategory":"Electrical",
            "type":"Services"
        }
    ],
    "sg:phone":"+1 919 499 4274",
    "sg:postcode":"28326",
    "sg:province":"NC",
    "sg:tags":[
        "electrical",
        "contractor"
    ],
    "wof:name":"Cook Buel Electric",
    "wof:placetype":"venue"
},
  "geometry": {"coordinates":[-79.069093,35.27515],"type":"Point"}
}