{
  "type": "Feature",
  "properties": {
    "iso:country":"US",
    "sg:address":"512 Caratoke Hwy",
    "sg:city":"Moyock",
    "sg:classifiers":[
        {
            "category":"Restaurant",
            "type":"Food & Drink"
        }
    ],
    "sg:menulink":"http://www.allmenus.com/nc/moyock/85440-dominos-pizza/menu/",
    "sg:phone":"+1 252 435 2500",
    "sg:postcode":"27958",
    "sg:province":"NC",
    "sg:tags":[
        "american",
        "wing",
        "pizza"
    ],
    "wof:name":"Domino's Pizza",
    "wof:placetype":"venue"
},
  "geometry": {"coordinates":[-76.17898700000001,36.525153],"type":"Point"}
}