{
  "type": "Feature",
  "properties": {
    "addr:full":"1522 Providence Rd Charlotte NC 28207",
    "addr:housenumber":"1522",
    "addr:postcode":"28207",
    "addr:street":"Providence Rd",
    "iso:country":"US",
    "sg:address":"1522 Providence Rd",
    "sg:city":"Charlotte",
    "sg:classifiers":[
        {
            "category":"Bars & Pubs",
            "type":"Food & Drink"
        }
    ],
    "sg:phone":"+1 704 366 4467",
    "sg:postcode":"28207",
    "sg:province":"NC",
    "sg:tags":[
        "drinking",
        "eating"
    ],
    "wof:name":"Man Inc",
    "wof:placetype":"venue"
},
  "geometry": {"coordinates":[-80.82090100000001,35.184596],"type":"Point"}
}