{
  "type": "Feature",
  "properties": {
    "addr:full":"111 Jordan Blvd Holden Beach NC 28462",
    "addr:housenumber":"111",
    "addr:postcode":"28462",
    "addr:street":"Jordan Blvd",
    "iso:country":"US",
    "sg:address":"111 Jordan Blvd",
    "sg:city":"Holden Beach",
    "sg:classifiers":[
        {
            "category":"Building & Trades",
            "subcategory":"Plumbing",
            "type":"Services"
        }
    ],
    "sg:phone":"+1 910 842 2771",
    "sg:postcode":"28462",
    "sg:province":"NC",
    "sg:tags":[
        "plumbing",
        "contractor"
    ],
    "wof:name":"P J & A Plumbing Contractors",
    "wof:placetype":"venue"
},
  "geometry": {"coordinates":[-78.267083,33.9141],"type":"Point"}
}