{
  "type": "Feature",
  "properties": {
    "iso:country":"US",
    "sg:address":"303 Riverby Farm Rd",
    "sg:city":"Edenton",
    "sg:classifiers":[
        {
            "category":"Building & Trades",
            "subcategory":"Construction",
            "type":"Services"
        }
    ],
    "sg:phone":"+1 252 482 0778",
    "sg:postcode":"27932",
    "sg:province":"NC",
    "wof:name":"Hassell Construction",
    "wof:placetype":"venue"
},
  "geometry": {"coordinates":[-76.697771,36.140876],"type":"Point"}
}