{
  "type": "Feature",
  "properties": {
    "addr:full":"999 Jennings Rd Statesville NC 28625",
    "addr:housenumber":"999",
    "addr:postcode":"28625",
    "addr:street":"Jennings Rd",
    "iso:country":"US",
    "sg:address":"999 Jennings Rd",
    "sg:city":"Statesville",
    "sg:classifiers":[
        {
            "category":"Shopping",
            "type":"Retail Goods"
        },
        {
            "category":"Professional",
            "subcategory":"Management & Consulting",
            "type":"Services"
        }
    ],
    "sg:phone":"+1 704 876 3324",
    "sg:postcode":"28625",
    "sg:province":"NC",
    "sg:tags":[
        "fire",
        "consultant",
        "protection",
        "merchandise"
    ],
    "wof:name":"Melco Firestopping Fsc C",
    "wof:placetype":"venue"
},
  "geometry": {"coordinates":[-80.87431100000001,35.904413],"type":"Point"}
}