{
  "type": "Feature",
  "properties": {
    "iso:country":"US",
    "sg:address":"30 W A St",
    "sg:city":"Newton",
    "sg:classifiers":[
        {
            "category":"Professional",
            "subcategory":"Lawyer & Legal Services",
            "type":"Services"
        }
    ],
    "sg:phone":"+1 828 464 3117",
    "sg:postcode":"28658",
    "sg:province":"NC",
    "sg:tags":[
        "attorney",
        "practice"
    ],
    "wof:name":"David R Moose",
    "wof:placetype":"venue"
},
  "geometry": {"coordinates":[-81.22283299999999,35.662928],"type":"Point"}
}