{
  "type": "Feature",
  "properties": {
    "addr:full":"801 W Innes St Salisbury NC 28144",
    "addr:housenumber":"801",
    "addr:postcode":"28144",
    "addr:street":"W Innes St",
    "iso:country":"US",
    "sg:address":"801 W Innes St",
    "sg:city":"Salisbury",
    "sg:classifiers":[
        {
            "category":"Manufacturing",
            "subcategory":"Printing",
            "type":"Manufacturing & Wholesale Goods"
        }
    ],
    "sg:phone":"+1 704 633 4974",
    "sg:postcode":"28144",
    "sg:province":"NC",
    "sg:tags":[
        "foil",
        "printer"
    ],
    "wof:name":"Dunham Packaging Co Inc",
    "wof:placetype":"venue"
},
  "geometry": {"coordinates":[-80.47967800000001,35.675053],"type":"Point"}
}