{
  "type": "Feature",
  "properties": {
    "iso:country":"US",
    "sg:address":"75 W Zeb Vance St",
    "sg:city":"Marion",
    "sg:classifiers":[
        {
            "category":"Real Estate",
            "subcategory":"Real Estate Operator",
            "type":"Services"
        }
    ],
    "sg:phone":"+1 828 652 0059",
    "sg:postcode":"28752",
    "sg:province":"NC",
    "sg:tags":[
        "building",
        "apartment"
    ],
    "wof:name":"Woodland Court",
    "wof:placetype":"venue"
},
  "geometry": {"coordinates":[-82.001097,35.683778],"type":"Point"}
}