{
  "type": "Feature",
  "properties": {
    "addr:full":"10473 State Hwy 268 Elkin NC 28621",
    "addr:housenumber":"10473",
    "addr:postcode":"28621",
    "addr:street":"State Hwy 268",
    "iso:country":"US",
    "sg:address":"10473 State Hwy 268",
    "sg:city":"Elkin",
    "sg:classifiers":[
        {
            "category":"Organizations",
            "subcategory":"Religious Organization",
            "type":"Services"
        }
    ],
    "sg:phone":"+1 336 366 4389",
    "sg:postcode":"28621",
    "sg:province":"NC",
    "sg:tags":[
        "church"
    ],
    "wof:name":"Shiloh Primitive Baptist Chr",
    "wof:placetype":"venue"
},
  "geometry": {"coordinates":[-80.76888599999999,36.276506],"type":"Point"}
}