{
  "type": "Feature",
  "properties": {
    "addr:full":"1012 Spainhour Mill Rd Pinnacle NC 27043",
    "addr:housenumber":"1012",
    "addr:postcode":"27043",
    "addr:street":"Spainhour Mill Rd",
    "iso:country":"US",
    "sg:address":"1012 Spainhour Mill Rd",
    "sg:city":"Pinnacle",
    "sg:classifiers":[
        {
            "category":"Personal",
            "subcategory":"Beauty Salon",
            "type":"Services"
        }
    ],
    "sg:phone":"+1 336 325 2763",
    "sg:postcode":"27043",
    "sg:province":"NC",
    "sg:tags":[
        "shop"
    ],
    "wof:name":"Donna's Place",
    "wof:placetype":"venue"
},
  "geometry": {"coordinates":[-80.450423,36.281125],"type":"Point"}
}