{
  "type": "Feature",
  "properties": {
    "iso:country":"US",
    "sg:address":"4 Feeney Ct",
    "sg:city":"Clayton",
    "sg:classifiers":[
        {
            "category":"Wholesale",
            "subcategory":"Non-durable Goods",
            "type":"Manufacturing & Wholesale Goods"
        }
    ],
    "sg:phone":"+1 919 247 0180",
    "sg:postcode":"27520",
    "sg:province":"NC",
    "wof:name":"Juarez Import",
    "wof:placetype":"venue"
},
  "geometry": {"coordinates":[-78.482006,35.649738],"type":"Point"}
}