{
  "type": "Feature",
  "properties": {
    "iso:country":"US",
    "sg:address":"119 Cambridge Dr",
    "sg:city":"Henderson",
    "sg:classifiers":[
        {
            "category":"Insurance",
            "subcategory":"Hazard Insurance",
            "type":"Services"
        }
    ],
    "sg:phone":"+1 252 433 9361",
    "sg:postcode":"27530",
    "sg:province":"NC",
    "sg:tags":[
        "bond"
    ],
    "wof:name":"Bullock Bail Bonds Inc",
    "wof:placetype":"venue"
},
  "geometry": {"coordinates":[-78.008898,35.44612],"type":"Point"}
}