{
  "type": "Feature",
  "properties": {
    "iso:country":"US",
    "sg:address":"811 Stanfield Dr",
    "sg:city":"Charlotte",
    "sg:classifiers":[
        {
            "category":"Home & Garden",
            "subcategory":"Home Furnishings",
            "type":"Retail Goods"
        },
        {
            "category":"Manufacturing",
            "subcategory":"Textiles",
            "type":"Manufacturing & Wholesale Goods"
        }
    ],
    "sg:phone":"+1 704 586 0412",
    "sg:postcode":"28210",
    "sg:province":"NC",
    "sg:tags":[
        "linen",
        "towels-cloth-wholesale",
        "manufacturer"
    ],
    "wof:name":"The Reusable Paper Towel Co",
    "wof:placetype":"venue"
},
  "geometry": {"coordinates":[-80.86448300000001,35.163639],"type":"Point"}
}