{
  "type": "Feature",
  "properties": {
    "addr:full":"211 W Queen St Grifton NC 28530",
    "addr:housenumber":"211",
    "addr:postcode":"28530",
    "addr:street":"W Queen St",
    "iso:country":"US",
    "sg:address":"211 W Queen St",
    "sg:city":"Grifton",
    "sg:classifiers":[
        {
            "category":"Retail",
            "subcategory":"Auto Repair",
            "type":"Services"
        }
    ],
    "sg:phone":"+1 252 524 4733",
    "sg:postcode":"28530",
    "sg:province":"NC",
    "sg:tags":[
        "repairing",
        "automobile"
    ],
    "wof:name":"Grifton Auto Parts",
    "wof:placetype":"venue"
},
  "geometry": {"coordinates":[-77.43557699999999,35.372963],"type":"Point"}
}