{
  "type": "Feature",
  "properties": {
    "iso:country":"US",
    "sg:address":"730 Highland Oaks Dr",
    "sg:city":"Winston Salem",
    "sg:classifiers":[
        {
            "category":"Health Services",
            "subcategory":"Doctor",
            "type":"Services"
        }
    ],
    "sg:phone":"+1 336 765 6312",
    "sg:postcode":"27103",
    "sg:province":"NC",
    "sg:tags":[
        "medical"
    ],
    "wof:name":"Radiological Forsyth Assoc PA",
    "wof:placetype":"venue"
},
  "geometry": {"coordinates":[-80.302707,36.059744],"type":"Point"}
}