{
  "type": "Feature",
  "properties": {
    "iso:country":"US",
    "sg:address":"2614 W Florida St",
    "sg:city":"Greensboro",
    "sg:classifiers":[
        {
            "category":"Building & Trades",
            "subcategory":"Cleaning & Sanitation",
            "type":"Services"
        }
    ],
    "sg:phone":"+1 336 333 9012",
    "sg:postcode":"27407",
    "sg:province":"NC",
    "sg:tags":[
        "janitor"
    ],
    "wof:name":"G & G Cleaning Svc",
    "wof:placetype":"venue"
},
  "geometry": {"coordinates":[-79.836298,36.052977],"type":"Point"}
}