{
  "type": "Feature",
  "properties": {
    "iso:country":"US",
    "sg:address":"828 Old Boiling Springs Rd",
    "sg:city":"Shelby",
    "sg:classifiers":[
        {
            "category":"Retail",
            "subcategory":"Repair Shop",
            "type":"Services"
        }
    ],
    "sg:phone":"+1 704 487 0591",
    "sg:postcode":"28152",
    "sg:province":"NC",
    "sg:tags":[
        "antique",
        "restoring"
    ],
    "wof:name":"Gary Reynolds Ltd",
    "wof:placetype":"venue"
},
  "geometry": {"coordinates":[-81.60991799999999,35.269815],"type":"Point"}
}