{
  "type": "Feature",
  "properties": {
    "addr:full":"598 Oak Ave Spruce Pine NC 28777",
    "addr:housenumber":"598",
    "addr:postcode":"28777",
    "addr:street":"Oak Ave",
    "iso:country":"US",
    "sg:address":"598 Oak Ave",
    "sg:city":"Spruce Pine",
    "sg:classifiers":[
        {
            "category":"Health Services",
            "subcategory":"Doctor",
            "type":"Services"
        }
    ],
    "sg:phone":"+1 828 765 9002",
    "sg:postcode":"28777",
    "sg:province":"NC",
    "sg:tags":[
        "dentist"
    ],
    "wof:name":"James S Thompson Pa",
    "wof:placetype":"venue"
},
  "geometry": {"coordinates":[-82.062184,35.915669],"type":"Point"}
}