{
  "type": "Feature",
  "properties": {
    "addr:full":"360 Hopkins Rd Kernersville NC 27284",
    "addr:housenumber":"360",
    "addr:postcode":"27284",
    "addr:street":"Hopkins Rd",
    "iso:country":"US",
    "sg:address":"360 Hopkins Rd",
    "sg:city":"Kernersville",
    "sg:classifiers":[
        {
            "category":"Organizations",
            "subcategory":"Religious Organization",
            "type":"Services"
        }
    ],
    "sg:phone":"+1   ",
    "sg:postcode":"27284",
    "sg:province":"NC",
    "sg:website":"www.gracekernersville.org",
    "wof:name":"Grace Presbyterian Church",
    "wof:placetype":"venue"
},
  "geometry": {"coordinates":[-80.10324199999999,36.120235],"type":"Point"}
}