{
  "type": "Feature",
  "properties": {
    "addr:full":"309 S Sharon Amity Rd Charlotte NC 28211",
    "addr:housenumber":"309",
    "addr:postcode":"28211",
    "addr:street":"S Sharon Amity Rd",
    "iso:country":"US",
    "sg:address":"309 S Sharon Amity Rd",
    "sg:city":"Charlotte",
    "sg:classifiers":[
        {
            "category":"Professional",
            "type":"Services"
        }
    ],
    "sg:phone":"+1 704 366 7586",
    "sg:postcode":"28211",
    "sg:province":"NC",
    "sg:tags":[
        "establishment"
    ],
    "wof:name":"Cotswold Family Medicine",
    "wof:placetype":"venue"
},
  "geometry": {"coordinates":[-80.79978699999999,35.175471],"type":"Point"}
}