{
  "type": "Feature",
  "properties": {
    "iso:country":"US",
    "sg:address":"152 Water St",
    "sg:city":"Belhaven",
    "sg:classifiers":[
        {
            "category":"Local Transit",
            "type":"Transportation"
        }
    ],
    "sg:phone":"+1 252 943 3775",
    "sg:postcode":"27810",
    "sg:province":"NC",
    "sg:tags":[
        "ambulance"
    ],
    "wof:name":"Bertie Ambulance Svc",
    "wof:placetype":"venue"
},
  "geometry": {"coordinates":[-76.62293,35.538083],"type":"Point"}
}