{
  "type": "Feature",
  "properties": {
    "addr:full":"26 Technology Dr Garner NC 27529",
    "addr:housenumber":"26",
    "addr:postcode":"27529",
    "addr:street":"Technology Dr",
    "iso:country":"US",
    "sg:address":"26 Technology Dr",
    "sg:city":"Garner",
    "sg:classifiers":[
        {
            "category":"Shopping",
            "subcategory":"Music",
            "type":"Retail Goods"
        }
    ],
    "sg:phone":"+1 919 661 1555",
    "sg:postcode":"27529",
    "sg:province":"NC",
    "sg:tags":[
        "video",
        "disc",
        "tape",
        "cassette"
    ],
    "wof:name":"A-1 Video",
    "wof:placetype":"venue"
},
  "geometry": {"coordinates":[-78.569064,35.606344],"type":"Point"}
}