{
  "type": "Feature",
  "properties": {
    "iso:country":"US",
    "sg:address":"201 Dalrymple St",
    "sg:city":"Kannapolis",
    "sg:classifiers":[
        {
            "category":"Wholesale",
            "subcategory":"Auto Parts",
            "type":"Manufacturing & Wholesale Goods"
        }
    ],
    "sg:phone":"+1 704 933 9024",
    "sg:postcode":"28083",
    "sg:province":"NC",
    "sg:tags":[
        "supply"
    ],
    "wof:name":"Hartsoe Battery Inc",
    "wof:placetype":"venue"
},
  "geometry": {"coordinates":[-80.612105,35.528628],"type":"Point"}
}