{
  "type": "Feature",
  "properties": {
    "addr:full":"762 Collier Rd Woodland NC 27897",
    "addr:housenumber":"762",
    "addr:postcode":"27897",
    "addr:street":"Collier Rd",
    "iso:country":"US",
    "sg:address":"762 Collier Rd",
    "sg:city":"Woodland",
    "sg:phone":"+1 252 539 2521",
    "sg:postcode":"27897",
    "sg:province":"NC",
    "sg:tags":[
        "farm",
        "cotton"
    ],
    "wof:name":"Jimmy Collier",
    "wof:placetype":"venue"
},
  "geometry": {"coordinates":[-77.277013,36.350738],"type":"Point"}
}