{
  "type": "Feature",
  "properties": {
    "iso:country":"US",
    "sg:address":"911 Linden Ave",
    "sg:city":"Oxford",
    "sg:classifiers":[
        {
            "category":"Shopping",
            "subcategory":"Clothing, Apparel, & Fashions",
            "type":"Retail Goods"
        }
    ],
    "sg:phone":"+1 919 693 9321",
    "sg:postcode":"27565",
    "sg:province":"NC",
    "wof:name":"In Style Urban Wear",
    "wof:placetype":"venue"
},
  "geometry": {"coordinates":[-78.58120599999999,36.29755],"type":"Point"}
}