{
  "type": "Feature",
  "properties": {
    "iso:country":"US",
    "sg:address":"7412 Beaverwood Dr",
    "sg:city":"Raleigh",
    "sg:classifiers":[
        {
            "category":"Freight",
            "type":"Transportation"
        }
    ],
    "sg:phone":"+1 919 876 2297",
    "sg:postcode":"27616",
    "sg:province":"NC",
    "sg:tags":[
        "operator",
        "local",
        "trucking"
    ],
    "wof:name":"Elite Courier Service LLC",
    "wof:placetype":"venue"
},
  "geometry": {"coordinates":[-78.544928,35.876429],"type":"Point"}
}