{
  "type": "Feature",
  "properties": {
    "addr:full":"9650 Neils Branch Rd Raleigh NC 27529",
    "addr:housenumber":"9650",
    "addr:postcode":"27529",
    "addr:street":"Neils Branch Rd",
    "iso:country":"US",
    "sg:address":"9650 Neils Branch Rd",
    "sg:city":"Raleigh",
    "sg:classifiers":[
        {
            "category":"Manufacturing",
            "subcategory":"Lumber",
            "type":"Manufacturing & Wholesale Goods"
        }
    ],
    "sg:phone":"+1 919 369 8027",
    "sg:postcode":"27529",
    "sg:province":"NC",
    "sg:tags":[
        "hardwood",
        "floor"
    ],
    "wof:name":"Mr Hardwood Floors Inc",
    "wof:placetype":"venue"
},
  "geometry": {"coordinates":[-78.62351700000001,35.637829],"type":"Point"}
}