{
  "type": "Feature",
  "properties": {
    "addr:full":"1434 N Main St Fuquay Varina NC 27526",
    "addr:housenumber":"1434",
    "addr:postcode":"27526",
    "addr:street":"N Main St",
    "iso:country":"US",
    "sg:address":"1434 N Main St",
    "sg:city":"Fuquay Varina",
    "sg:classifiers":[
        {
            "category":"Restaurant",
            "type":"Food & Drink"
        }
    ],
    "sg:menulink":"http://www.allmenus.com/nc/middle-creek/84413-the-original-italian-pie/menu/",
    "sg:phone":"+1 919 577 0500",
    "sg:postcode":"27526",
    "sg:province":"NC",
    "sg:tags":[
        "american",
        "pizza"
    ],
    "wof:name":"The Original Italian Pie",
    "wof:placetype":"venue"
},
  "geometry": {"coordinates":[-78.770279,35.593543],"type":"Point"}
}