{
  "type": "Feature",
  "properties": {
    "addr:full":"193 Mundy Cove Rd Weaverville NC 28787",
    "addr:housenumber":"193",
    "addr:postcode":"28787",
    "addr:street":"Mundy Cove Rd",
    "iso:country":"US",
    "sg:address":"193 Mundy Cove Rd",
    "sg:city":"Weaverville",
    "sg:classifiers":[
        {
            "category":"Manufacturing",
            "subcategory":"Lumber",
            "type":"Manufacturing & Wholesale Goods"
        }
    ],
    "sg:phone":"+1 828 658 0848",
    "sg:postcode":"28787",
    "sg:province":"NC",
    "sg:tags":[
        "forestry"
    ],
    "wof:name":"Lloyd Fordner",
    "wof:placetype":"venue"
},
  "geometry": {"coordinates":[-82.50286199999999,35.686855],"type":"Point"}
}