{
  "type": "Feature",
  "properties": {
    "iso:country":"US",
    "sg:address":"124 Parker Rd",
    "sg:city":"Eden",
    "sg:classifiers":[
        {
            "category":"Professional",
            "subcategory":"Management & Consulting",
            "type":"Services"
        }
    ],
    "sg:phone":"+1   ",
    "sg:postcode":"27288",
    "sg:province":"NC",
    "sg:tags":[
        "business"
    ],
    "wof:name":"Consulidating Freight",
    "wof:placetype":"venue"
},
  "geometry": {"coordinates":[-79.76140100000001,36.47926],"type":"Point"}
}