{
  "type": "Feature",
  "properties": {
    "addr:full":"2600 Randleman Rd Greensboro NC 27406",
    "addr:housenumber":"2600",
    "addr:postcode":"27406",
    "addr:street":"Randleman Rd",
    "iso:country":"US",
    "sg:address":"2600 Randleman Rd",
    "sg:city":"Greensboro",
    "sg:classifiers":[
        {
            "category":"Autos & Motor Vehicles",
            "subcategory":"Fuel & Gas Station",
            "type":"Retail Goods"
        }
    ],
    "sg:phone":"+1 336 271 6900",
    "sg:postcode":"27406",
    "sg:province":"NC",
    "sg:tags":[
        "grocery",
        "station",
        "gasoline"
    ],
    "wof:name":"BP",
    "wof:placetype":"venue"
},
  "geometry": {"coordinates":[-79.801761,36.029278],"type":"Point"}
}