{
  "type": "Feature",
  "properties": {
    "addr:full":"13502 S Ridge Dr Charlotte NC 28273",
    "addr:housenumber":"13502",
    "addr:postcode":"28273",
    "addr:street":"S Ridge Dr",
    "iso:country":"US",
    "sg:address":"13502 S Ridge Dr",
    "sg:city":"Charlotte",
    "sg:classifiers":[
        {
            "category":"Manufacturing",
            "subcategory":"Motor Vehicles & Parts",
            "type":"Manufacturing & Wholesale Goods"
        },
        {
            "category":"Autos & Motor Vehicles",
            "subcategory":"Motorcycle Sales",
            "type":"Retail Goods"
        }
    ],
    "sg:phone":"+1 704 588 1111",
    "sg:postcode":"28273",
    "sg:province":"NC",
    "sg:tags":[
        "control",
        "manufacturer",
        "electric",
        "controls-wholesale"
    ],
    "wof:name":"Moore R A Associates",
    "wof:placetype":"venue"
},
  "geometry": {"coordinates":[-80.96058600000001,35.113128],"type":"Point"}
}