{
  "type": "Feature",
  "properties": {
    "iso:country":"US",
    "sg:address":"2805 Spring Forest Rd",
    "sg:city":"Raleigh",
    "sg:classifiers":[
        {
            "category":"Manufacturing",
            "subcategory":"Printing",
            "type":"Manufacturing & Wholesale Goods"
        }
    ],
    "sg:phone":"+1 919 862 0551",
    "sg:postcode":"27616",
    "sg:province":"NC",
    "sg:tags":[
        "publisher"
    ],
    "wof:name":"Jarrett Press & Publications",
    "wof:placetype":"venue"
},
  "geometry": {"coordinates":[-78.594199,35.857594],"type":"Point"}
}