{
  "type": "Feature",
  "properties": {
    "iso:country":"US",
    "sg:address":"100 Regency Pl",
    "sg:city":"Cary",
    "sg:classifiers":[
        {
            "category":"Professional",
            "subcategory":"Management & Consulting",
            "type":"Services"
        }
    ],
    "sg:phone":"+1   ",
    "sg:postcode":"27511",
    "sg:province":"NC",
    "wof:name":"Atstake",
    "wof:placetype":"venue"
},
  "geometry": {"coordinates":[-78.77840999999999,35.764047],"type":"Point"}
}