{
  "type": "Feature",
  "properties": {
    "addr:full":"101 Manatee St Cape Carteret NC 28584",
    "addr:housenumber":"101",
    "addr:postcode":"28584",
    "addr:street":"Manatee St",
    "iso:country":"US",
    "sg:address":"101 Manatee St",
    "sg:city":"Cape Carteret",
    "sg:classifiers":[
        {
            "category":"Personal",
            "subcategory":"Beauty Salon",
            "type":"Services"
        }
    ],
    "sg:phone":"+1 252 393 3433",
    "sg:postcode":"28584",
    "sg:province":"NC",
    "wof:name":"Salon 101",
    "wof:placetype":"venue"
},
  "geometry": {"coordinates":[-77.067211,34.686485],"type":"Point"}
}