{
  "type": "Feature",
  "properties": {
    "iso:country":"US",
    "sg:address":"4722 Pleasant Garden Rd",
    "sg:city":"Pleasant Garden",
    "sg:classifiers":[
        {
            "category":"Professional",
            "subcategory":"Accounting & Tax Preparation",
            "type":"Services"
        }
    ],
    "sg:phone":"+1 336 674 7152",
    "sg:postcode":"27313",
    "sg:province":"NC",
    "sg:tags":[
        "accountant"
    ],
    "wof:name":"Amy R Parsons CPA",
    "wof:placetype":"venue"
},
  "geometry": {"coordinates":[-79.764197,35.967705],"type":"Point"}
}