{
  "type": "Feature",
  "properties": {
    "iso:country":"US",
    "sg:address":"420 Dinkins Creek Rd",
    "sg:city":"Murphy",
    "sg:classifiers":[
        {
            "category":"Building & Trades",
            "subcategory":"Landscaping Services",
            "type":"Services"
        }
    ],
    "sg:phone":"+1 828 837 6422",
    "sg:postcode":"28906",
    "sg:province":"NC",
    "wof:name":"Spring Meadows Property MGT",
    "wof:placetype":"venue"
},
  "geometry": {"coordinates":[-84.012016,35.176498],"type":"Point"}
}