{
  "type": "Feature",
  "properties": {
    "iso:country":"US",
    "sg:address":"1110 Glynwater Ln",
    "sg:city":"Waxhaw",
    "sg:classifiers":[
        {
            "category":"Building & Trades",
            "subcategory":"Equipment Rental",
            "type":"Services"
        }
    ],
    "sg:phone":"+1 704 846 5438",
    "sg:postcode":"28173",
    "sg:province":"NC",
    "sg:tags":[
        "crane"
    ],
    "wof:name":"Wilkinson Crane",
    "wof:placetype":"venue"
},
  "geometry": {"coordinates":[-80.78608800000001,35.012757],"type":"Point"}
}