{
  "type": "Feature",
  "properties": {
    "addr:full":"20 Westside Dr Asheville NC 28806",
    "addr:housenumber":"20",
    "addr:postcode":"28806",
    "addr:street":"Westside Dr",
    "iso:country":"US",
    "sg:address":"20 Westside Dr",
    "sg:city":"Asheville",
    "sg:classifiers":[
        {
            "category":"Restaurant",
            "type":"Food & Drink"
        }
    ],
    "sg:phone":"+1 828 258 2685",
    "sg:postcode":"28806",
    "sg:province":"NC",
    "sg:tags":[
        "shop",
        "coffee"
    ],
    "sg:website":"www.sndcoffee.com",
    "wof:name":"S & D Coffee Inc",
    "wof:placetype":"venue"
},
  "geometry": {"coordinates":[-82.59991100000001,35.599482],"type":"Point"}
}