{
  "type": "Feature",
  "properties": {
    "iso:country":"US",
    "sg:address":"6709 David Moore Rd",
    "sg:city":"Elon College",
    "sg:classifiers":[
        {
            "category":"Shopping",
            "subcategory":"Used Merchandise",
            "type":"Retail Goods"
        }
    ],
    "sg:phone":"+1 336 584 2638",
    "sg:postcode":"27244",
    "sg:province":"NC",
    "wof:name":"Little Red Barn",
    "wof:placetype":"venue"
},
  "geometry": {"coordinates":[-79.47333999999999,36.226877],"type":"Point"}
}