{
  "type": "Feature",
  "properties": {
    "iso:country":"US",
    "sg:address":"180 Imperial Hts",
    "sg:city":"Statesville",
    "sg:classifiers":[
        {
            "category":"Professional",
            "type":"Services"
        }
    ],
    "sg:phone":"+1   ",
    "sg:postcode":"28625",
    "sg:province":"NC",
    "wof:name":"Systems Media Service",
    "wof:placetype":"venue"
},
  "geometry": {"coordinates":[-80.89758,35.54155],"type":"Point"}
}