{
  "type": "Feature",
  "properties": {
    "addr:full":"28 NW Court Sq Graham NC 27253",
    "addr:housenumber":"28",
    "addr:postcode":"27253",
    "addr:street":"Nw Court Sq",
    "iso:country":"US",
    "sg:address":"28 NW Court Sq",
    "sg:city":"Graham",
    "sg:classifiers":[
        {
            "category":"Restaurant",
            "type":"Food & Drink"
        }
    ],
    "sg:phone":"+1 336 221 1112",
    "sg:postcode":"27253",
    "sg:province":"NC",
    "sg:tags":[
        "eating"
    ],
    "wof:name":"Barristers Cafe Inc",
    "wof:placetype":"venue"
},
  "geometry": {"coordinates":[-79.40049500000001,36.069545],"type":"Point"}
}