{
  "type": "Feature",
  "properties": {
    "iso:country":"US",
    "sg:address":"4832 Noras Path Rd",
    "sg:city":"Charlotte",
    "sg:classifiers":[
        {
            "category":"Retail",
            "subcategory":"Repair Shop",
            "type":"Services"
        }
    ],
    "sg:phone":"+1 704 759 3053",
    "sg:postcode":"28226",
    "sg:province":"NC",
    "sg:tags":[
        "refinishing",
        "furniture"
    ],
    "wof:name":"De Castro Furniture Repair",
    "wof:placetype":"venue"
},
  "geometry": {"coordinates":[-80.806921,35.089804],"type":"Point"}
}