{
  "type": "Feature",
  "properties": {
    "iso:country":"US",
    "sg:address":"14901 Black Farms Rd",
    "sg:city":"Huntersville",
    "sg:classifiers":[
        {
            "category":"Manufacturing",
            "subcategory":"Tools & Machinery",
            "type":"Manufacturing & Wholesale Goods"
        }
    ],
    "sg:phone":"+1 704 895 3886",
    "sg:postcode":"28078",
    "sg:province":"NC",
    "sg:tags":[
        "machine",
        "shop"
    ],
    "wof:name":"Precision Tek",
    "wof:placetype":"venue"
},
  "geometry": {"coordinates":[-80.808409,35.449107],"type":"Point"}
}