{
  "type": "Feature",
  "properties": {
    "iso:country":"US",
    "sg:address":"1105 S George St",
    "sg:city":"Goldsboro",
    "sg:classifiers":[
        {
            "category":"Recreation",
            "type":"Entertainment"
        }
    ],
    "sg:phone":"+1   ",
    "sg:postcode":"27530",
    "sg:province":"NC",
    "sg:tags":[
        "club",
        "membership"
    ],
    "wof:name":"Daryles",
    "wof:placetype":"venue"
},
  "geometry": {"coordinates":[-78.008252,35.366589],"type":"Point"}
}