{
  "type": "Feature",
  "properties": {
    "iso:country":"US",
    "sg:address":"981 Wolf Island Rd",
    "sg:city":"Reidsville",
    "sg:classifiers":[
        {
            "category":"Farming",
            "subcategory":"Farm",
            "type":"Manufacturing & Wholesale Goods"
        }
    ],
    "sg:phone":"+1 336 342 0373",
    "sg:postcode":"27320",
    "sg:province":"NC",
    "sg:tags":[
        "crop",
        "general"
    ],
    "wof:name":"Mike Bray",
    "wof:placetype":"venue"
},
  "geometry": {"coordinates":[-79.65952900000001,36.397577],"type":"Point"}
}