{
  "type": "Feature",
  "properties": {
    "addr:full":"8601 Ebenezer Church Rd Raleigh NC 27617",
    "addr:housenumber":"8601",
    "addr:postcode":"27617",
    "addr:street":"Ebenezer Church Rd",
    "iso:country":"US",
    "sg:address":"8601 Ebenezer Church Rd",
    "sg:city":"Raleigh",
    "sg:classifiers":[
        {
            "category":"Manufacturing",
            "subcategory":"Building Materials",
            "type":"Manufacturing & Wholesale Goods"
        }
    ],
    "sg:phone":"+1 919 782 8917",
    "sg:postcode":"27617",
    "sg:province":"NC",
    "sg:tags":[
        "molding",
        "mfg",
        "custom",
        "wood",
        "teller",
        "line",
        "bank"
    ],
    "wof:name":"Triangle Fixtures & Millwork",
    "wof:placetype":"venue"
},
  "geometry": {"coordinates":[-78.739728,35.897076],"type":"Point"}
}