{
  "type": "Feature",
  "properties": {
    "addr:full":"803 W Pine St Mount Airy NC 27030",
    "addr:housenumber":"803",
    "addr:postcode":"27030",
    "addr:street":"W Pine St",
    "iso:country":"US",
    "sg:address":"803 W Pine St",
    "sg:city":"Mount Airy",
    "sg:classifiers":[
        {
            "category":"Building & Trades",
            "subcategory":"Construction",
            "type":"Services"
        }
    ],
    "sg:phone":"+1 336 789 0102",
    "sg:postcode":"27030",
    "sg:province":"NC",
    "sg:tags":[
        "hanging",
        "contractor"
    ],
    "wof:name":"Davis Sandblasting & Painting",
    "wof:placetype":"venue"
},
  "geometry": {"coordinates":[-80.62619599999999,36.500068],"type":"Point"}
}