{
  "type": "Feature",
  "properties": {
    "iso:country":"US",
    "sg:address":"401 Finley Ave NW",
    "sg:city":"Lenoir",
    "sg:classifiers":[
        {
            "category":"Personal",
            "subcategory":"Barber",
            "type":"Services"
        }
    ],
    "sg:phone":"+1 828 759 1214",
    "sg:postcode":"28645",
    "sg:province":"NC",
    "wof:name":"Best Cuts Barber & Beauty Sln",
    "wof:placetype":"venue"
},
  "geometry": {"coordinates":[-81.53490600000001,35.921735],"type":"Point"}
}