{
  "type": "Feature",
  "properties": {
    "iso:country":"US",
    "sg:address":"818 Corporate Cir",
    "sg:city":"Salisbury",
    "sg:classifiers":[
        {
            "category":"Professional",
            "subcategory":"Management & Consulting",
            "type":"Services"
        },
        {
            "category":"Education",
            "subcategory":"Special Training",
            "type":"Public Place"
        }
    ],
    "sg:phone":"+1 704 633 8207",
    "sg:postcode":"28147",
    "sg:province":"NC",
    "sg:tags":[
        "consultant",
        "educational",
        "tutoring",
        "school"
    ],
    "wof:name":"Salisbury Tutoring Academy Ltd",
    "wof:placetype":"venue"
},
  "geometry": {"coordinates":[-80.49180699999999,35.639797],"type":"Point"}
}