{
  "type": "Feature",
  "properties": {
    "iso:country":"US",
    "sg:address":"2350 Hoey Church Rd",
    "sg:city":"Shelby",
    "sg:classifiers":[
        {
            "category":"Organizations",
            "subcategory":"Religious Organization",
            "type":"Services"
        }
    ],
    "sg:phone":"+1 704 482 9188",
    "sg:postcode":"28152",
    "sg:province":"NC",
    "sg:tags":[
        "church"
    ],
    "wof:name":"Shelby Seventh Day Adventist",
    "wof:placetype":"venue"
},
  "geometry": {"coordinates":[-81.462307,35.259343],"type":"Point"}
}