{
  "type": "Feature",
  "properties": {
    "iso:country":"US",
    "sg:address":"6563 Suits Rd",
    "sg:city":"Archdale",
    "sg:classifiers":[
        {
            "category":"Retail",
            "subcategory":"Repair Shop",
            "type":"Services"
        }
    ],
    "sg:phone":"+1 336 434 3624",
    "sg:postcode":"27263",
    "sg:province":"NC",
    "sg:tags":[
        "taxidermist"
    ],
    "wof:name":"Carlson Wildlife Art",
    "wof:placetype":"venue"
},
  "geometry": {"coordinates":[-79.919411,35.896721],"type":"Point"}
}