{
  "type": "Feature",
  "properties": {
    "addr:full":"403 Shoals Rd Pinnacle NC 27043",
    "addr:housenumber":"403",
    "addr:postcode":"27043",
    "addr:street":"Shoals Rd",
    "iso:country":"US",
    "sg:address":"403 Shoals Rd",
    "sg:city":"Pinnacle",
    "sg:classifiers":[
        {
            "category":"Shopping",
            "subcategory":"Hobbies, Toys, & Games",
            "type":"Retail Goods"
        }
    ],
    "sg:phone":"+1 336 325 2691",
    "sg:postcode":"27043",
    "sg:province":"NC",
    "sg:tags":[
        "craft",
        "supply"
    ],
    "wof:name":"Studio Art Supply",
    "wof:placetype":"venue"
},
  "geometry": {"coordinates":[-80.495285,36.366741],"type":"Point"}
}