{
  "type": "Feature",
  "properties": {
    "addr:full":"113 Collingwood Dr Pikeville NC 27863",
    "addr:housenumber":"113",
    "addr:postcode":"27863",
    "addr:street":"Collingwood Dr",
    "iso:country":"US",
    "sg:address":"113 Collingwood Dr",
    "sg:city":"Pikeville",
    "sg:classifiers":[
        {
            "category":"Retail",
            "subcategory":"Repair Shop",
            "type":"Services"
        }
    ],
    "sg:phone":"+1 919 242 6658",
    "sg:postcode":"27863",
    "sg:province":"NC",
    "sg:tags":[
        "appliance",
        "electrical"
    ],
    "wof:name":"Atlantic Appliance Repair",
    "wof:placetype":"venue"
},
  "geometry": {"coordinates":[-77.99158199999999,35.501951],"type":"Point"}
}