{
  "type": "Feature",
  "properties": {
    "addr:full":"2310 Stinson Dr Raleigh NC 27607",
    "addr:housenumber":"2310",
    "addr:postcode":"27607",
    "addr:street":"Stinson Dr",
    "iso:country":"US",
    "sg:address":"2310 Stinson Dr",
    "sg:city":"Raleigh",
    "sg:classifiers":[
        {
            "category":"Education",
            "subcategory":"University",
            "type":"Public Place"
        }
    ],
    "sg:phone":"+1 919 515 2253",
    "sg:postcode":"27607",
    "sg:province":"NC",
    "sg:tags":[
        "college"
    ],
    "sg:website":"http://www.ncsu.edu",
    "wof:name":"North Carolina State University",
    "wof:placetype":"venue"
},
  "geometry": {"coordinates":[-78.665672,35.785099],"type":"Point"}
}