{
  "type": "Feature",
  "properties": {
    "addr:full":"616 Bayberry Dr Chapel Hill NC 27517",
    "addr:housenumber":"616",
    "addr:postcode":"27517",
    "addr:street":"Bayberry Dr",
    "iso:country":"US",
    "sg:address":"616 Bayberry Dr",
    "sg:city":"Chapel Hill",
    "sg:classifiers":[
        {
            "category":"Arts & Performance",
            "subcategory":"Theater",
            "type":"Entertainment"
        }
    ],
    "sg:phone":"+1   ",
    "sg:postcode":"27517",
    "sg:province":"NC",
    "sg:tags":[
        "theatrical"
    ],
    "wof:name":"Thats Entertainment",
    "wof:placetype":"venue"
},
  "geometry": {"coordinates":[-79.041241,35.888809],"type":"Point"}
}