{
  "type": "Feature",
  "properties": {
    "iso:country":"US",
    "sg:address":"6005 Spartan Dr",
    "sg:city":"Hudson",
    "sg:classifiers":[
        {
            "category":"Professional",
            "type":"Services"
        }
    ],
    "sg:phone":"+1 828 496 2361",
    "sg:postcode":"28638",
    "sg:province":"NC",
    "sg:tags":[
        "establishment"
    ],
    "wof:name":"Thermwood",
    "wof:placetype":"venue"
},
  "geometry": {"coordinates":[-81.454339,35.828076],"type":"Point"}
}