{
  "type": "Feature",
  "properties": {
    "iso:country":"US",
    "sg:address":"631 Washington St",
    "sg:city":"Washington",
    "sg:classifiers":[
        {
            "category":"Retail",
            "subcategory":"Laundry & Dry Cleaning",
            "type":"Services"
        }
    ],
    "sg:phone":"+1 252 946 5211",
    "sg:postcode":"27889",
    "sg:province":"NC",
    "wof:name":"Wash House",
    "wof:placetype":"venue"
},
  "geometry": {"coordinates":[-77.058862,35.552452],"type":"Point"}
}