{
  "type": "Feature",
  "properties": {
    "addr:full":"13756 State Hwy 125 Oak City NC 27857",
    "addr:housenumber":"13756",
    "addr:postcode":"27857",
    "addr:street":"State Hwy 125",
    "iso:country":"US",
    "sg:address":"13756 State Hwy 125",
    "sg:city":"Oak City",
    "sg:classifiers":[
        {
            "category":"Organizations",
            "subcategory":"Religious Organization",
            "type":"Services"
        }
    ],
    "sg:phone":"+1 252 798 3942",
    "sg:postcode":"27857",
    "sg:province":"NC",
    "sg:tags":[
        "church"
    ],
    "wof:name":"Hamilton Pentecostal Holiness",
    "wof:placetype":"venue"
},
  "geometry": {"coordinates":[-77.203917,35.932544],"type":"Point"}
}