{
  "type": "Feature",
  "properties": {
    "addr:full":"301 E Renovah Cir Wilmington NC 28403",
    "addr:housenumber":"301",
    "addr:postcode":"28403",
    "addr:street":"E Renovah Cir",
    "iso:country":"US",
    "sg:address":"301 E Renovah Cir",
    "sg:city":"Wilmington",
    "sg:classifiers":[
        {
            "category":"Organizations",
            "subcategory":"Non-profit Organization",
            "type":"Services"
        }
    ],
    "sg:phone":"+1 910 791 8788",
    "sg:postcode":"28403",
    "sg:province":"NC",
    "sg:tags":[
        "social"
    ],
    "wof:name":"Ricky Fountain Educationa",
    "wof:placetype":"venue"
},
  "geometry": {"coordinates":[-77.90961299999999,34.232389],"type":"Point"}
}