{
  "type": "Feature",
  "properties": {
    "addr:full":"125 Pirate Ln Rockingham NC 28379",
    "addr:housenumber":"125",
    "addr:postcode":"28379",
    "addr:street":"Pirate Ln",
    "iso:country":"US",
    "sg:address":"125 Pirate Ln",
    "sg:city":"Rockingham",
    "sg:classifiers":[
        {
            "category":"Building & Trades",
            "subcategory":"Electrical",
            "type":"Services"
        }
    ],
    "sg:phone":"+1 910 895 5300",
    "sg:postcode":"28379",
    "sg:province":"NC",
    "sg:tags":[
        "electric",
        "contractor"
    ],
    "wof:name":"M & N Electrical Svc",
    "wof:placetype":"venue"
},
  "geometry": {"coordinates":[-79.716499,34.943987],"type":"Point"}
}