{
  "type": "Feature",
  "properties": {
    "addr:full":"145 Main St W Banner Elk NC 28604",
    "addr:housenumber":"145",
    "addr:postcode":"28604",
    "addr:street":"Main St W Banner",
    "iso:country":"US",
    "sg:address":"145 Main St W",
    "sg:city":"Banner Elk",
    "sg:classifiers":[
        {
            "category":"Professional",
            "subcategory":"Business Services",
            "type":"Services"
        }
    ],
    "sg:phone":"+1 828 898 3197",
    "sg:postcode":"28604",
    "sg:province":"NC",
    "sg:tags":[
        "interior",
        "consultant",
        "design",
        "decorator"
    ],
    "wof:name":"British Colonial Style",
    "wof:placetype":"venue"
},
  "geometry": {"coordinates":[-81.871818,36.163219],"type":"Point"}
}