{
  "type": "Feature",
  "properties": {
    "addr:full":"3703 Tryon Rd Raleigh NC 27606",
    "addr:housenumber":"3703",
    "addr:postcode":"27606",
    "addr:street":"Tryon Rd",
    "iso:country":"US",
    "sg:address":"3703 Tryon Rd",
    "sg:city":"Raleigh",
    "sg:classifiers":[
        {
            "category":"Organizations",
            "subcategory":"Religious Organization",
            "type":"Services"
        }
    ],
    "sg:phone":"+1 919 828 7348",
    "sg:postcode":"27606",
    "sg:province":"NC",
    "wof:name":"Watts Chapel Baptist Church",
    "wof:placetype":"venue"
},
  "geometry": {"coordinates":[-78.69754500000001,35.74723],"type":"Point"}
}