{
  "type": "Feature",
  "properties": {
    "addr:full":"7919 Vermilion Dr Charlotte NC 28215",
    "addr:housenumber":"7919",
    "addr:postcode":"28215",
    "addr:street":"Vermilion Dr",
    "iso:country":"US",
    "sg:address":"7919 Vermilion Dr",
    "sg:city":"Charlotte",
    "sg:classifiers":[
        {
            "category":"Professional",
            "subcategory":"Management & Consulting",
            "type":"Services"
        }
    ],
    "sg:phone":"+1   ",
    "sg:postcode":"28215",
    "sg:province":"NC",
    "sg:tags":[
        "business"
    ],
    "wof:name":"Graham Enterprises",
    "wof:placetype":"venue"
},
  "geometry": {"coordinates":[-80.71460500000001,35.249462],"type":"Point"}
}