{
  "type": "Feature",
  "properties": {
    "addr:full":"3765 E Brocktown Rd Moravian Falls NC 28654",
    "addr:housenumber":"3765",
    "addr:postcode":"28654",
    "addr:street":"E Brocktown Rd",
    "iso:country":"US",
    "sg:address":"3765 E Brocktown Rd",
    "sg:city":"Moravian Falls",
    "sg:classifiers":[
        {
            "category":"Farming",
            "subcategory":"Orchard",
            "type":"Manufacturing & Wholesale Goods"
        }
    ],
    "sg:phone":"+1 336 921 4036",
    "sg:postcode":"28654",
    "sg:province":"NC",
    "sg:tags":[
        "fruit",
        "tree"
    ],
    "wof:name":"McKinney Orchard",
    "wof:placetype":"venue"
},
  "geometry": {"coordinates":[-81.138257,36.057224],"type":"Point"}
}