{
  "type": "Feature",
  "properties": {
    "iso:country":"US",
    "sg:address":"106 Elm St",
    "sg:city":"Aberdeen",
    "sg:classifiers":[
        {
            "category":"Building & Trades",
            "subcategory":"Landscaping Services",
            "type":"Services"
        }
    ],
    "sg:phone":"+1 910 944 1744",
    "sg:postcode":"28315",
    "sg:province":"NC",
    "wof:name":"Lawn Smart",
    "wof:placetype":"venue"
},
  "geometry": {"coordinates":[-79.42451,35.137587],"type":"Point"}
}