{
  "type": "Feature",
  "properties": {
    "iso:country":"US",
    "sg:address":"2804 US Hwy 220",
    "sg:city":"Madison",
    "sg:classifiers":[
        {
            "category":"Building & Trades",
            "subcategory":"Construction",
            "type":"Services"
        }
    ],
    "sg:phone":"+1 336 616 6701",
    "sg:postcode":"27025",
    "sg:province":"NC",
    "sg:tags":[
        "excavation",
        "contractor"
    ],
    "wof:name":"CA Woods Grading & Hauling",
    "wof:placetype":"venue"
},
  "geometry": {"coordinates":[-79.945553,36.322576],"type":"Point"}
}