{
  "type": "Feature",
  "properties": {
    "iso:country":"US",
    "sg:address":"6706 Amberley Ln",
    "sg:city":"Clemmons",
    "sg:classifiers":[
        {
            "category":"Personal",
            "subcategory":"Beauty Salon",
            "type":"Services"
        }
    ],
    "sg:phone":"+1   ",
    "sg:postcode":"27012",
    "sg:province":"NC",
    "sg:tags":[
        "shop"
    ],
    "wof:name":"Stanley C Davis",
    "wof:placetype":"venue"
},
  "geometry": {"coordinates":[-80.38296800000001,36.011892],"type":"Point"}
}