{
  "type": "Feature",
  "properties": {
    "addr:full":"279 Stanaford Rd Winston Salem NC 27104",
    "addr:housenumber":"279",
    "addr:postcode":"27104",
    "addr:street":"Stanaford Rd",
    "iso:country":"US",
    "sg:address":"279 Stanaford Rd",
    "sg:city":"Winston Salem",
    "sg:classifiers":[
        {
            "category":"Health Services",
            "subcategory":"Doctor",
            "type":"Services"
        }
    ],
    "sg:phone":"+1   ",
    "sg:postcode":"27104",
    "sg:province":"NC",
    "sg:tags":[
        "medical"
    ],
    "wof:name":"David H Allen MD",
    "wof:placetype":"venue"
},
  "geometry": {"coordinates":[-80.32987799999999,36.092335],"type":"Point"}
}