{
  "type": "Feature",
  "properties": {
    "addr:full":"310 Grabtown Rd Windsor NC 27983",
    "addr:housenumber":"310",
    "addr:postcode":"27983",
    "addr:street":"Grabtown Rd",
    "iso:country":"US",
    "sg:address":"310 Grabtown Rd",
    "sg:city":"Windsor",
    "sg:classifiers":[
        {
            "category":"Farming",
            "subcategory":"Livestock Farm",
            "type":"Manufacturing & Wholesale Goods"
        }
    ],
    "sg:phone":"+1 252 794 1718",
    "sg:postcode":"27983",
    "sg:province":"NC",
    "sg:tags":[
        "animal",
        "general"
    ],
    "wof:name":"Heckstall Farms",
    "wof:placetype":"venue"
},
  "geometry": {"coordinates":[-76.985344,35.99152],"type":"Point"}
}