{
  "type": "Feature",
  "properties": {
    "iso:country":"US",
    "sg:address":"104 Quail Run",
    "sg:city":"Goldsboro",
    "sg:classifiers":[
        {
            "category":"Building & Trades",
            "subcategory":"Electrical",
            "type":"Services"
        }
    ],
    "sg:phone":"+1 919 735 9030",
    "sg:postcode":"27530",
    "sg:province":"NC",
    "sg:tags":[
        "electric",
        "contractor"
    ],
    "wof:name":"Culbreth Electrical Svc",
    "wof:placetype":"venue"
},
  "geometry": {"coordinates":[-78.073657,35.310742],"type":"Point"}
}