{
  "type": "Feature",
  "properties": {
    "addr:full":"6496 Shallowford Rd Lewisville NC 27023",
    "addr:housenumber":"6496",
    "addr:postcode":"27023",
    "addr:street":"Shallowford Rd",
    "iso:country":"US",
    "sg:address":"6496 Shallowford Rd",
    "sg:city":"Lewisville",
    "sg:classifiers":[
        {
            "category":"Organizations",
            "subcategory":"Membership Organization",
            "type":"Services"
        }
    ],
    "sg:phone":"+1   ",
    "sg:postcode":"27023",
    "sg:province":"NC",
    "wof:name":"Lewisville Area Arts Council",
    "wof:placetype":"venue"
},
  "geometry": {"coordinates":[-80.42012699999999,36.096847],"type":"Point"}
}