{
  "type": "Feature",
  "properties": {
    "iso:country":"US",
    "sg:address":"101 S 3rd St",
    "sg:city":"Smithfield",
    "sg:classifiers":[
        {
            "category":"Personal",
            "type":"Services"
        }
    ],
    "sg:phone":"+1 919 934 4943",
    "sg:postcode":"27577",
    "sg:province":"NC",
    "sg:tags":[
        "wear",
        "formal"
    ],
    "wof:name":"Jewel's Formals",
    "wof:placetype":"venue"
},
  "geometry": {"coordinates":[-78.346007,35.511209],"type":"Point"}
}