{
  "type": "Feature",
  "properties": {
    "addr:full":"385 Lloyd Murphy Rd Thomasville NC 27360",
    "addr:housenumber":"385",
    "addr:postcode":"27360",
    "addr:street":"Lloyd Murphy Rd",
    "iso:country":"US",
    "sg:address":"385 Lloyd Murphy Rd",
    "sg:city":"Thomasville",
    "sg:classifiers":[
        {
            "category":"Manufacturing",
            "subcategory":"Tools & Machinery",
            "type":"Manufacturing & Wholesale Goods"
        }
    ],
    "sg:phone":"+1 336 475 2268",
    "sg:postcode":"27360",
    "sg:province":"NC",
    "sg:tags":[
        "machine",
        "shop"
    ],
    "wof:name":"Woempner Machine Co",
    "wof:placetype":"venue"
},
  "geometry": {"coordinates":[-80.141358,35.92688],"type":"Point"}
}