{
  "type": "Feature",
  "properties": {
    "addr:full":"732 Topeka St Fayetteville NC 28301",
    "addr:housenumber":"732",
    "addr:postcode":"28301",
    "addr:street":"Topeka St",
    "iso:country":"US",
    "sg:address":"732 Topeka St",
    "sg:city":"Fayetteville",
    "sg:classifiers":[
        {
            "category":"Professional",
            "type":"Services"
        }
    ],
    "sg:phone":"+1 910 488 9903",
    "sg:postcode":"28301",
    "sg:province":"NC",
    "wof:name":"Reliable Nannies",
    "wof:placetype":"venue"
},
  "geometry": {"coordinates":[-78.897313,35.089251],"type":"Point"}
}