{
  "type": "Feature",
  "properties": {
    "iso:country":"US",
    "sg:address":"207 State Hwy 200",
    "sg:city":"Stanfield",
    "sg:classifiers":[
        {
            "category":"Building & Trades",
            "subcategory":"Construction",
            "type":"Services"
        }
    ],
    "sg:phone":"+1 704 888 0891",
    "sg:postcode":"28163",
    "sg:province":"NC",
    "sg:tags":[
        "general",
        "contractor"
    ],
    "wof:name":"David A Ross Construction",
    "wof:placetype":"venue"
},
  "geometry": {"coordinates":[-80.42470299999999,35.236418],"type":"Point"}
}