{
  "type": "Feature",
  "properties": {
    "iso:country":"US",
    "sg:address":"6004 Racers Aly",
    "sg:city":"Concord",
    "sg:classifiers":[
        {
            "category":"Restaurant",
            "type":"Food & Drink"
        }
    ],
    "sg:phone":"+1 704 785 2101",
    "sg:postcode":"28027",
    "sg:province":"NC",
    "sg:tags":[
        "pizza"
    ],
    "wof:name":"Buck's Pizza",
    "wof:placetype":"venue"
},
  "geometry": {"coordinates":[-80.67843000000001,35.34435],"type":"Point"}
}