{
  "type": "Feature",
  "properties": {
    "addr:full":"712 Enon Rd Oxford NC 27565",
    "addr:housenumber":"712",
    "addr:postcode":"27565",
    "addr:street":"Enon Rd",
    "iso:country":"US",
    "sg:address":"712 Enon Rd",
    "sg:city":"Oxford",
    "sg:classifiers":[
        {
            "category":"Building & Trades",
            "subcategory":"Landscaping Services",
            "type":"Services"
        }
    ],
    "sg:phone":"+1 919 693 2927",
    "sg:postcode":"27565",
    "sg:province":"NC",
    "sg:tags":[
        "designer",
        "landscape"
    ],
    "wof:name":"Site Technology Inc",
    "wof:placetype":"venue"
},
  "geometry": {"coordinates":[-78.779279,36.245087],"type":"Point"}
}