{
  "type": "Feature",
  "properties": {
    "iso:country":"US",
    "sg:address":"5315 Highgate Dr",
    "sg:city":"Durham",
    "sg:classifiers":[
        {
            "category":"Professional",
            "subcategory":"Advertising",
            "type":"Services"
        }
    ],
    "sg:phone":"+1 919 544 2150",
    "sg:postcode":"27713",
    "sg:province":"NC",
    "sg:tags":[
        "counselor"
    ],
    "wof:name":"Octagon",
    "wof:placetype":"venue"
},
  "geometry": {"coordinates":[-78.942758,35.910751],"type":"Point"}
}