{
  "type": "Feature",
  "properties": {
    "iso:country":"US",
    "sg:address":"5593 Tabbs Creek Rd",
    "sg:city":"Oxford",
    "sg:classifiers":[
        {
            "category":"Professional",
            "type":"Services"
        }
    ],
    "sg:phone":"+1 919 693 0808",
    "sg:postcode":"27565",
    "sg:province":"NC",
    "sg:tags":[
        "establishment"
    ],
    "wof:name":"Tony's Country Cottage",
    "wof:placetype":"venue"
},
  "geometry": {"coordinates":[-78.549179,36.321999],"type":"Point"}
}