{
  "type": "Feature",
  "properties": {
    "addr:full":"801 Huffine Mill Rd Greensboro NC 27405",
    "addr:housenumber":"801",
    "addr:postcode":"27405",
    "addr:street":"Huffine Mill Rd",
    "iso:country":"US",
    "sg:address":"801 Huffine Mill Rd",
    "sg:city":"Greensboro",
    "sg:classifiers":[
        {
            "category":"Building & Trades",
            "subcategory":"Cleaning & Sanitation",
            "type":"Services"
        }
    ],
    "sg:phone":"+1   ",
    "sg:postcode":"27405",
    "sg:province":"NC",
    "sg:tags":[
        "maintenance"
    ],
    "wof:name":"Rubys Cleaning Service",
    "wof:placetype":"venue"
},
  "geometry": {"coordinates":[-79.740488,36.087481],"type":"Point"}
}