{
  "type": "Feature",
  "properties": {
    "iso:country":"US",
    "sg:address":"5432 Coburg Ave",
    "sg:city":"Charlotte",
    "sg:classifiers":[
        {
            "category":"Shopping",
            "subcategory":"Clothing, Apparel, & Fashions",
            "type":"Retail Goods"
        }
    ],
    "sg:phone":"+1 704 563 5066",
    "sg:postcode":"28215",
    "sg:province":"NC",
    "sg:tags":[
        "baby",
        "accessory"
    ],
    "wof:name":"Lady Lullaby",
    "wof:placetype":"venue"
},
  "geometry": {"coordinates":[-80.759388,35.244034],"type":"Point"}
}