{
  "type": "Feature",
  "properties": {
    "addr:full":"5210 Stokes Ferry Rd Salisbury NC 28146",
    "addr:housenumber":"5210",
    "addr:postcode":"28146",
    "addr:street":"Stokes Ferry Rd",
    "iso:country":"US",
    "sg:address":"5210 Stokes Ferry Rd",
    "sg:city":"Salisbury",
    "sg:classifiers":[
        {
            "category":"Home & Garden",
            "subcategory":"Garden Supply",
            "type":"Retail Goods"
        }
    ],
    "sg:phone":"+1 704 636 5384",
    "sg:postcode":"28146",
    "sg:province":"NC",
    "sg:tags":[
        "nurseryman"
    ],
    "wof:name":"Lester J Brown & Son Nursery",
    "wof:placetype":"venue"
},
  "geometry": {"coordinates":[-80.401594,35.620855],"type":"Point"}
}