{
  "type": "Feature",
  "properties": {
    "addr:full":"8108 Running Cedar Trl Raleigh NC 27615",
    "addr:housenumber":"8108",
    "addr:postcode":"27615",
    "addr:street":"Running Cedar Trl",
    "iso:country":"US",
    "sg:address":"8108 Running Cedar Trl",
    "sg:city":"Raleigh",
    "sg:classifiers":[
        {
            "category":"Professional",
            "subcategory":"Management & Consulting",
            "type":"Services"
        }
    ],
    "sg:phone":"+1 919 870 1051",
    "sg:postcode":"27615",
    "sg:province":"NC",
    "sg:tags":[
        "consultant",
        "business"
    ],
    "wof:name":"Straight Line Solutions",
    "wof:placetype":"venue"
},
  "geometry": {"coordinates":[-78.63761100000001,35.889492],"type":"Point"}
}