{
  "type": "Feature",
  "properties": {
    "addr:full":"220 W Murray St Wallace NC 28466",
    "addr:housenumber":"220",
    "addr:postcode":"28466",
    "addr:street":"W Murray St",
    "iso:country":"US",
    "sg:address":"220 W Murray St",
    "sg:city":"Wallace",
    "sg:classifiers":[
        {
            "category":"Professional",
            "subcategory":"Advertising",
            "type":"Services"
        }
    ],
    "sg:phone":"+1   ",
    "sg:postcode":"28466",
    "sg:province":"NC",
    "wof:name":"McKenzie Professional Services",
    "wof:placetype":"venue"
},
  "geometry": {"coordinates":[-77.998952,34.736917],"type":"Point"}
}