{
  "type": "Feature",
  "properties": {
    "addr:full":"606 E Lee St Smithfield NC 27577",
    "addr:housenumber":"606",
    "addr:postcode":"27577",
    "addr:street":"E Lee St",
    "iso:country":"US",
    "sg:address":"606 E Lee St",
    "sg:city":"Smithfield",
    "sg:classifiers":[
        {
            "category":"Insurance",
            "subcategory":"Insurance Agent",
            "type":"Services"
        }
    ],
    "sg:phone":"+1 919 934 5131",
    "sg:postcode":"27577",
    "sg:province":"NC",
    "wof:name":"Bigham & Parrish",
    "wof:placetype":"venue"
},
  "geometry": {"coordinates":[-78.344847,35.503538],"type":"Point"}
}