{
  "type": "Feature",
  "properties": {
    "addr:full":"1401 E 11th St Siler City NC 27344",
    "addr:housenumber":"1401",
    "addr:postcode":"27344",
    "addr:street":"E 11Th St",
    "iso:country":"US",
    "sg:address":"1401 E 11th St",
    "sg:city":"Siler City",
    "sg:classifiers":[
        {
            "category":"Autos & Motor Vehicles",
            "subcategory":"Auto Supplies",
            "type":"Retail Goods"
        }
    ],
    "sg:phone":"+1 919 742 3200",
    "sg:postcode":"27344",
    "sg:province":"NC",
    "sg:tags":[
        "automobile",
        "parts"
    ],
    "wof:name":"Advance Auto Parts Inc",
    "wof:placetype":"venue"
},
  "geometry": {"coordinates":[-79.444003,35.733005],"type":"Point"}
}