{
  "type": "Feature",
  "properties": {
    "addr:full":"922 Castle Rock Farm Rd Pittsboro NC 27312",
    "addr:housenumber":"922",
    "addr:postcode":"27312",
    "addr:street":"Castle;Farm Rd",
    "iso:country":"US",
    "sg:address":"922 Castle Rock Farm Rd",
    "sg:city":"Pittsboro",
    "sg:classifiers":[
        {
            "category":"Building & Trades",
            "subcategory":"Landscaping Services",
            "type":"Services"
        }
    ],
    "sg:phone":"+1 919 545 0274",
    "sg:postcode":"27312",
    "sg:province":"NC",
    "sg:tags":[
        "ground"
    ],
    "wof:name":"Kings Ldscpg & Ground Maint",
    "wof:placetype":"venue"
},
  "geometry": {"coordinates":[-79.263958,35.804741],"type":"Point"}
}