{
  "type": "Feature",
  "properties": {
    "addr:full":"7111 Busick Quarry Rd Elon College NC 27244",
    "addr:housenumber":"7111",
    "addr:postcode":"27244",
    "addr:street":"Busick Quarry Rd",
    "iso:country":"US",
    "sg:address":"7111 Busick Quarry Rd",
    "sg:city":"Elon College",
    "sg:phone":"+1 336 584 9508",
    "sg:postcode":"27244",
    "sg:province":"NC",
    "sg:tags":[
        "farm",
        "tobacco"
    ],
    "wof:name":"Scott Landscaping and Lawn Svc",
    "wof:placetype":"venue"
},
  "geometry": {"coordinates":[-79.562957,36.190139],"type":"Point"}
}