{
  "type": "Feature",
  "properties": {
    "addr:full":"2914 Sandy Ridge Rd Colfax NC 27235",
    "addr:housenumber":"2914",
    "addr:postcode":"27235",
    "addr:street":"Sandy Ridge Rd",
    "iso:country":"US",
    "sg:address":"2914 Sandy Ridge Rd",
    "sg:city":"Colfax",
    "sg:classifiers":[
        {
            "category":"Home & Garden",
            "subcategory":"Garden Supply",
            "type":"Retail Goods"
        }
    ],
    "sg:phone":"+1 336 393 0214",
    "sg:postcode":"27235",
    "sg:province":"NC",
    "sg:tags":[
        "own"
    ],
    "wof:name":"AB Seed & Company",
    "wof:placetype":"venue"
},
  "geometry": {"coordinates":[-79.99388999999999,36.086498],"type":"Point"}
}