{
  "type": "Feature",
  "properties": {
    "iso:country":"US",
    "sg:address":"968 Cedar Fork Rd",
    "sg:city":"Beulaville",
    "sg:classifiers":[
        {
            "category":"Wholesale",
            "subcategory":"Electrical",
            "type":"Manufacturing & Wholesale Goods"
        }
    ],
    "sg:phone":"+1 910 298 4522",
    "sg:postcode":"28518",
    "sg:province":"NC",
    "sg:tags":[
        "equipment"
    ],
    "wof:name":"Stand By Generators",
    "wof:placetype":"venue"
},
  "geometry": {"coordinates":[-77.680649,34.875318],"type":"Point"}
}