{
  "type": "Feature",
  "properties": {
    "iso:country":"US",
    "sg:address":"694 N Main St",
    "sg:city":"Troutman",
    "sg:classifiers":[
        {
            "category":"Manufacturing",
            "subcategory":"Furniture",
            "type":"Manufacturing & Wholesale Goods"
        }
    ],
    "sg:phone":"+1 704 528 4506",
    "sg:postcode":"28166",
    "sg:province":"NC",
    "wof:name":"Blanton & Moore Co",
    "wof:placetype":"venue"
},
  "geometry": {"coordinates":[-80.896666,35.714582],"type":"Point"}
}