{
  "type": "Feature",
  "properties": {
    "addr:full":"544 Seastone St Raleigh NC 27603",
    "addr:housenumber":"544",
    "addr:postcode":"27603",
    "addr:street":"Seastone St",
    "iso:country":"US",
    "sg:address":"544 Seastone St",
    "sg:city":"Raleigh",
    "sg:classifiers":[
        {
            "category":"Personal",
            "subcategory":"Tanning Parlor",
            "type":"Services"
        }
    ],
    "sg:phone":"+1 919 876 4855",
    "sg:postcode":"27603",
    "sg:province":"NC",
    "sg:tags":[
        "salon"
    ],
    "wof:name":"Bronze Bodies Inc",
    "wof:placetype":"venue"
},
  "geometry": {"coordinates":[-78.668915,35.663726],"type":"Point"}
}