{
  "type": "Feature",
  "properties": {
    "addr:full":"5917 Deep Spring Cir Wake Forest NC 27587",
    "addr:housenumber":"5917",
    "addr:postcode":"27587",
    "addr:street":"Deep Spring Cir",
    "iso:country":"US",
    "sg:address":"5917 Deep Spring Cir",
    "sg:city":"Wake Forest",
    "sg:classifiers":[
        {
            "category":"Utilities",
            "subcategory":"Fuel Oil & Lpg",
            "type":"Services"
        }
    ],
    "sg:phone":"+1 919 562 3735",
    "sg:postcode":"27587",
    "sg:province":"NC",
    "sg:tags":[
        "liquefied",
        "gas",
        "petroleum"
    ],
    "wof:name":"Professional Propane Services",
    "wof:placetype":"venue"
},
  "geometry": {"coordinates":[-78.486276,35.945849],"type":"Point"}
}