{
  "type": "Feature",
  "properties": {
    "iso:country":"US",
    "sg:address":"4324 Kennedy Home Rd",
    "sg:city":"La Grange",
    "sg:classifiers":[
        {
            "category":"Organizations",
            "subcategory":"Religious Organization",
            "type":"Services"
        }
    ],
    "sg:phone":"+1   ",
    "sg:postcode":"28551",
    "sg:province":"NC",
    "wof:name":"Rockford Chapel Fwb Churc",
    "wof:placetype":"venue"
},
  "geometry": {"coordinates":[-77.7573,35.245444],"type":"Point"}
}