{
  "type": "Feature",
  "properties": {
    "addr:full":"162 Great Point Dr Mooresville NC 28117",
    "addr:housenumber":"162",
    "addr:postcode":"28117",
    "addr:street":"Great Point Dr",
    "iso:country":"US",
    "sg:address":"162 Great Point Dr",
    "sg:city":"Mooresville",
    "sg:classifiers":[
        {
            "category":"Insurance",
            "subcategory":"Insurance Agent",
            "type":"Services"
        }
    ],
    "sg:phone":"+1 704 660 6568",
    "sg:postcode":"28117",
    "sg:province":"NC",
    "wof:name":"Colonial Life & Accident Of Nc",
    "wof:placetype":"venue"
},
  "geometry": {"coordinates":[-80.918753,35.548899],"type":"Point"}
}