{
  "type": "Feature",
  "properties": {
    "addr:full":"1075 W King St Boone NC 28607",
    "addr:housenumber":"1075",
    "addr:postcode":"28607",
    "addr:street":"W King St",
    "iso:country":"US",
    "sg:address":"1075 W King St",
    "sg:city":"Boone",
    "sg:classifiers":[
        {
            "category":"Retail",
            "subcategory":"Laundry & Dry Cleaning",
            "type":"Services"
        }
    ],
    "sg:phone":"+1   ",
    "sg:postcode":"28607",
    "sg:province":"NC",
    "wof:name":"Alpine Disaster Cleanup",
    "wof:placetype":"venue"
},
  "geometry": {"coordinates":[-81.69150999999999,36.2209],"type":"Point"}
}