{
  "type": "Feature",
  "properties": {
    "addr:full":"915 Galloway Rd Grimesland NC 27837",
    "addr:housenumber":"915",
    "addr:postcode":"27837",
    "addr:street":"Galloway Rd",
    "iso:country":"US",
    "sg:address":"915 Galloway Rd",
    "sg:city":"Grimesland",
    "sg:classifiers":[
        {
            "category":"Autos & Motor Vehicles",
            "subcategory":"Automobile Sales",
            "type":"Retail Goods"
        }
    ],
    "sg:phone":"+1 252 752 8161",
    "sg:postcode":"27837",
    "sg:province":"NC",
    "wof:name":"Hodges Used Cars and Body Shop",
    "wof:placetype":"venue"
},
  "geometry": {"coordinates":[-77.212486,35.559814],"type":"Point"}
}