{
  "type": "Feature",
  "properties": {
    "iso:country":"US",
    "sg:address":"4720 Mitchell Mill Rd",
    "sg:city":"Wake Forest",
    "sg:classifiers":[
        {
            "category":"Building & Trades",
            "subcategory":"Landscaping Services",
            "type":"Services"
        }
    ],
    "sg:phone":"+1 919 261 0099",
    "sg:postcode":"27587",
    "sg:province":"NC",
    "sg:tags":[
        "lawn",
        "maintenance",
        "grounds"
    ],
    "wof:name":"MDH Lawn Svc",
    "wof:placetype":"venue"
},
  "geometry": {"coordinates":[-78.486621,35.878915],"type":"Point"}
}