{
  "type": "Feature",
  "properties": {
    "iso:country":"US",
    "sg:address":"7300 Swansea Ln",
    "sg:city":"Cornelius",
    "sg:classifiers":[
        {
            "category":"Building & Trades",
            "subcategory":"Equipment Rental",
            "type":"Services"
        }
    ],
    "sg:phone":"+1 704 892 6300",
    "sg:postcode":"28031",
    "sg:province":"NC",
    "wof:name":"Netjets Inc",
    "wof:placetype":"venue"
},
  "geometry": {"coordinates":[-80.900341,35.445454],"type":"Point"}
}