{
  "type": "Feature",
  "properties": {
    "iso:country":"US",
    "sg:address":"7196 Beach Dr SW",
    "sg:city":"Ocean Isle Beach",
    "sg:classifiers":[
        {
            "category":"Retail",
            "subcategory":"Laundry & Dry Cleaning",
            "type":"Services"
        }
    ],
    "sg:phone":"+1   ",
    "sg:postcode":"28469",
    "sg:province":"NC",
    "wof:name":"Williams Carpet",
    "wof:placetype":"venue"
},
  "geometry": {"coordinates":[-78.47693099999999,33.898518],"type":"Point"}
}