{
  "type": "Feature",
  "properties": {
    "addr:full":"4899 Antioch Church Rd Middlesex NC 27557",
    "addr:housenumber":"4899",
    "addr:postcode":"27557",
    "addr:street":"Antioch Church Rd",
    "iso:country":"US",
    "sg:address":"4899 Antioch Church Rd",
    "sg:city":"Middlesex",
    "sg:classifiers":[
        {
            "category":"Building & Trades",
            "subcategory":"Construction",
            "type":"Services"
        }
    ],
    "sg:phone":"+1 919 284 1593",
    "sg:postcode":"27557",
    "sg:province":"NC",
    "sg:tags":[
        "concrete",
        "contractor"
    ],
    "wof:name":"Narron Concrete & Construction",
    "wof:placetype":"venue"
},
  "geometry": {"coordinates":[-78.23625800000001,35.696792],"type":"Point"}
}