{
  "type": "Feature",
  "properties": {
    "addr:full":"303 N Madison Blvd Roxboro NC 27573",
    "addr:housenumber":"303",
    "addr:postcode":"27573",
    "addr:street":"N Madison Blvd",
    "iso:country":"US",
    "sg:address":"303 N Madison Blvd",
    "sg:city":"Roxboro",
    "sg:classifiers":[
        {
            "category":"Restaurant",
            "type":"Food & Drink"
        }
    ],
    "sg:menulink":"http://www.allmenus.com/nc/roxboro/154618-hardees/menu/",
    "sg:phone":"+1 336 599 2942",
    "sg:postcode":"27573",
    "sg:province":"NC",
    "sg:tags":[
        "burger",
        "american"
    ],
    "wof:name":"Hardee's",
    "wof:placetype":"venue"
},
  "geometry": {"coordinates":[-78.98332499999999,36.397277],"type":"Point"}
}