{
  "type": "Feature",
  "properties": {
    "iso:country":"US",
    "sg:address":"8700 US Hwy 117",
    "sg:city":"Rocky Point",
    "sg:classifiers":[
        {
            "category":"Shopping",
            "type":"Retail Goods"
        }
    ],
    "sg:phone":"+1 910 675 3886",
    "sg:postcode":"28457",
    "sg:province":"NC",
    "sg:tags":[
        "graduation",
        "supply"
    ],
    "wof:name":"Jostens-Overby School Svc",
    "wof:placetype":"venue"
},
  "geometry": {"coordinates":[-77.881044,34.43237],"type":"Point"}
}