{
  "type": "Feature",
  "properties": {
    "addr:full":"816 S Chapman St Greensboro NC 27403",
    "addr:housenumber":"816",
    "addr:postcode":"27403",
    "addr:street":"S Chapman St",
    "iso:country":"US",
    "sg:address":"816 S Chapman St",
    "sg:city":"Greensboro",
    "sg:classifiers":[
        {
            "category":"Shopping",
            "subcategory":"Used Merchandise",
            "type":"Retail Goods"
        }
    ],
    "sg:phone":"+1 336 272 2999",
    "sg:postcode":"27403",
    "sg:province":"NC",
    "wof:name":"Computer Consignment Shop",
    "wof:placetype":"venue"
},
  "geometry": {"coordinates":[-79.82390700000001,36.063819],"type":"Point"}
}