{
  "type": "Feature",
  "properties": {
    "addr:full":"5200 N Croatan Hwy Kitty Hawk NC 27949",
    "addr:housenumber":"5200",
    "addr:postcode":"27949",
    "addr:street":"N Croatan Hwy",
    "iso:country":"US",
    "sg:address":"5200 N Croatan Hwy",
    "sg:city":"Kitty Hawk",
    "sg:classifiers":[
        {
            "category":"Health Services",
            "subcategory":"Doctor",
            "type":"Services"
        }
    ],
    "sg:phone":"+1 252 261 4311",
    "sg:postcode":"27949",
    "sg:province":"NC",
    "sg:tags":[
        "physician",
        "surgeon"
    ],
    "wof:name":"Outer Banks Radiology",
    "wof:placetype":"venue"
},
  "geometry": {"coordinates":[-75.712361,36.097173],"type":"Point"}
}