{
  "type": "Feature",
  "properties": {
    "addr:full":"801 Pamlico Dr Greensboro NC 27408",
    "addr:housenumber":"801",
    "addr:postcode":"27408",
    "addr:street":"Pamlico Dr",
    "iso:country":"US",
    "sg:address":"801 Pamlico Dr",
    "sg:city":"Greensboro",
    "sg:classifiers":[
        {
            "category":"Professional",
            "subcategory":"Art Services",
            "type":"Services"
        }
    ],
    "sg:phone":"+1 336 272 0914",
    "sg:postcode":"27408",
    "sg:province":"NC",
    "sg:tags":[
        "photographer",
        "photography",
        "commercial"
    ],
    "wof:name":"Howard Bemus Photography",
    "wof:placetype":"venue"
},
  "geometry": {"coordinates":[-79.811386,36.08282],"type":"Point"}
}