{
  "type": "Feature",
  "properties": {
    "iso:country":"US",
    "sg:address":"3292 Edwards Rd",
    "sg:city":"Sanford",
    "sg:classifiers":[
        {
            "category":"Organizations",
            "subcategory":"Religious Organization",
            "type":"Services"
        }
    ],
    "sg:phone":"+1   ",
    "sg:postcode":"27332",
    "sg:province":"NC",
    "wof:name":"Mount Nebo FWB Church",
    "wof:placetype":"venue"
},
  "geometry": {"coordinates":[-79.18162,35.361716],"type":"Point"}
}