{
  "type": "Feature",
  "properties": {
    "iso:country":"US",
    "sg:address":"11919 Austin Traphill Rd",
    "sg:city":"Traphill",
    "sg:classifiers":[
        {
            "category":"Personal",
            "subcategory":"Beauty Salon",
            "type":"Services"
        }
    ],
    "sg:phone":"+1 336 957 3093",
    "sg:postcode":"28685",
    "sg:province":"NC",
    "wof:name":"Shirley's Stylin' Salon",
    "wof:placetype":"venue"
},
  "geometry": {"coordinates":[-81.022761,36.340832],"type":"Point"}
}