{
  "type": "Feature",
  "properties": {
    "addr:full":"5407 Frieden Church Rd Mc Leansville NC 27301",
    "addr:housenumber":"5407",
    "addr:postcode":"27301",
    "addr:street":"Frieden Church Rd",
    "iso:country":"US",
    "sg:address":"5407 Frieden Church Rd",
    "sg:city":"Mc Leansville",
    "sg:classifiers":[
        {
            "category":"Retail",
            "subcategory":"Car Wash",
            "type":"Services"
        }
    ],
    "sg:phone":"+1 336 697 0511",
    "sg:postcode":"27301",
    "sg:province":"NC",
    "sg:tags":[
        "polishing",
        "washing"
    ],
    "wof:name":"New Glo Car Wash",
    "wof:placetype":"venue"
},
  "geometry": {"coordinates":[-79.658007,36.10768],"type":"Point"}
}