{
  "type": "Feature",
  "properties": {
    "addr:full":"311 E Cedar St Cary NC 27511",
    "addr:housenumber":"311",
    "addr:postcode":"27511",
    "addr:street":"E Cedar St",
    "iso:country":"US",
    "sg:address":"311 E Cedar St",
    "sg:city":"Cary",
    "sg:classifiers":[
        {
            "category":"Retail",
            "subcategory":"Auto Repair",
            "type":"Services"
        }
    ],
    "sg:phone":"+1 919 467 2639",
    "sg:postcode":"27511",
    "sg:province":"NC",
    "sg:tags":[
        "body",
        "shop"
    ],
    "sg:website":"www.caryautobody.com",
    "wof:name":"Cary Auto Body Specialists",
    "wof:placetype":"venue"
},
  "geometry": {"coordinates":[-78.77629899999999,35.789299],"type":"Point"}
}