{
  "type": "Feature",
  "properties": {
    "iso:country":"US",
    "sg:address":"1260 US Hwy 64 W",
    "sg:city":"Plymouth",
    "sg:classifiers":[
        {
            "category":"Building & Trades",
            "subcategory":"Construction",
            "type":"Services"
        }
    ],
    "sg:phone":"+1 252 793 1342",
    "sg:postcode":"27962",
    "sg:province":"NC",
    "sg:tags":[
        "earth",
        "moving",
        "contractor"
    ],
    "wof:name":"B & S Equipment Inc",
    "wof:placetype":"venue"
},
  "geometry": {"coordinates":[-76.757755,35.844035],"type":"Point"}
}