{
  "type": "Feature",
  "properties": {
    "addr:full":"605 Stratford Dr Zebulon NC 27597",
    "addr:housenumber":"605",
    "addr:postcode":"27597",
    "addr:street":"Stratford Dr",
    "iso:country":"US",
    "sg:address":"605 Stratford Dr",
    "sg:city":"Zebulon",
    "sg:classifiers":[
        {
            "category":"Real Estate",
            "subcategory":"Real Estate Agent",
            "type":"Services"
        }
    ],
    "sg:phone":"+1 919 269 9300",
    "sg:postcode":"27597",
    "sg:province":"NC",
    "sg:tags":[
        "appraiser"
    ],
    "wof:name":"Beck Appraisal Svc",
    "wof:placetype":"venue"
},
  "geometry": {"coordinates":[-78.325654,35.824523],"type":"Point"}
}