{
  "type": "Feature",
  "properties": {
    "iso:country":"US",
    "sg:address":"1901 W Park Dr",
    "sg:city":"North Wilkesboro",
    "sg:classifiers":[
        {
            "category":"Wholesale",
            "subcategory":"Medical Equipment & Supplies",
            "type":"Manufacturing & Wholesale Goods"
        },
        {
            "category":"Health Services",
            "subcategory":"Clinic",
            "type":"Services"
        }
    ],
    "sg:phone":"+1 336 667 0922",
    "sg:postcode":"28659",
    "sg:province":"NC",
    "sg:tags":[
        "home",
        "hospital",
        "care"
    ],
    "wof:name":"Medi Home Care",
    "wof:placetype":"venue"
},
  "geometry": {"coordinates":[-81.163113,36.155553],"type":"Point"}
}