{
  "type": "Feature",
  "properties": {
    "iso:country":"US",
    "sg:address":"403 W 15th St",
    "sg:city":"Washington",
    "sg:classifiers":[
        {
            "category":"Health Services",
            "subcategory":"Podiatrist",
            "type":"Services"
        }
    ],
    "sg:phone":"+1 252 946 0324",
    "sg:postcode":"27889",
    "sg:province":"NC",
    "wof:name":"Pamlico Podiatry Assoc",
    "wof:placetype":"venue"
},
  "geometry": {"coordinates":[-77.051794,35.55788],"type":"Point"}
}