{
  "type": "Feature",
  "properties": {
    "iso:country":"US",
    "sg:address":"400 Queens Rd",
    "sg:city":"Charlotte",
    "sg:classifiers":[
        {
            "category":"Professional",
            "subcategory":"Detective & Security Services",
            "type":"Services"
        }
    ],
    "sg:phone":"+1   ",
    "sg:postcode":"28207",
    "sg:province":"NC",
    "sg:tags":[
        "car"
    ],
    "wof:name":"Luther & Associates",
    "wof:placetype":"venue"
},
  "geometry": {"coordinates":[-80.827387,35.208172],"type":"Point"}
}