{
  "type": "Feature",
  "properties": {
    "addr:full":"4552 Yank Rd Wilson NC 27893",
    "addr:housenumber":"4552",
    "addr:postcode":"27893",
    "addr:street":"Yank Rd",
    "iso:country":"US",
    "sg:address":"4552 Yank Rd",
    "sg:city":"Wilson",
    "sg:classifiers":[
        {
            "category":"Professional",
            "subcategory":"Employment Agencies",
            "type":"Services"
        }
    ],
    "sg:phone":"+1   ",
    "sg:postcode":"27893",
    "sg:province":"NC",
    "wof:name":"Sandra Smith Recruiting",
    "wof:placetype":"venue"
},
  "geometry": {"coordinates":[-77.94231600000001,35.658531],"type":"Point"}
}