{
  "type": "Feature",
  "properties": {
    "iso:country":"US",
    "sg:address":"728 E Franklin Blvd",
    "sg:city":"Gastonia",
    "sg:classifiers":[
        {
            "category":"Retail",
            "subcategory":"Veterinary Services",
            "type":"Services"
        }
    ],
    "sg:phone":"+1 704 866 7918",
    "sg:postcode":"28054",
    "sg:province":"NC",
    "sg:tags":[
        "veterinarian",
        "emergency"
    ],
    "wof:name":"Veterinarian Emergency Clinic",
    "wof:placetype":"venue"
},
  "geometry": {"coordinates":[-81.170599,35.262412],"type":"Point"}
}