{
  "type": "Feature",
  "properties": {
    "iso:country":"US",
    "sg:address":"1921 Carolina Beach Rd",
    "sg:city":"Wilmington",
    "sg:classifiers":[
        {
            "category":"Food & Beverages",
            "subcategory":"Bakery",
            "type":"Retail Goods"
        }
    ],
    "sg:phone":"+1 910 251 8886",
    "sg:postcode":"28401",
    "sg:province":"NC",
    "sg:tags":[
        "baker"
    ],
    "wof:name":"Danny's Pastry Shoppe Inc",
    "wof:placetype":"venue"
},
  "geometry": {"coordinates":[-77.94381799999999,34.208301],"type":"Point"}
}