{
  "type": "Feature",
  "properties": {
    "iso:country":"US",
    "sg:address":"26 W Walnut St",
    "sg:city":"Asheville",
    "sg:classifiers":[
        {
            "category":"Restaurant",
            "type":"Food & Drink"
        }
    ],
    "sg:phone":"+1 828 251 5211",
    "sg:postcode":"28801",
    "sg:province":"NC",
    "wof:name":"Magnolia's Raw Bar & Grille",
    "wof:placetype":"venue"
},
  "geometry": {"coordinates":[-82.55253999999999,35.596493],"type":"Point"}
}