{
  "type": "Feature",
  "properties": {
    "iso:country":"US",
    "sg:address":"3500 Oleander Dr",
    "sg:city":"Wilmington",
    "sg:classifiers":[
        {
            "category":"Restaurant",
            "type":"Food & Drink"
        }
    ],
    "sg:menulink":"http://www.allmenus.com/nc/wilmington/72579-sbarro/menu/",
    "sg:phone":"+1 910 313 6900",
    "sg:postcode":"28403",
    "sg:province":"NC",
    "sg:tags":[
        "american",
        "pizza"
    ],
    "wof:name":"Sbarro",
    "wof:placetype":"venue"
},
  "geometry": {"coordinates":[-77.907135,34.217336],"type":"Point"}
}