{
  "type": "Feature",
  "properties": {
    "iso:country":"US",
    "sg:address":"1088 Harbor Dr SW",
    "sg:city":"Calabash",
    "sg:classifiers":[
        {
            "category":"Professional",
            "type":"Services"
        }
    ],
    "sg:phone":"+1 910 579 6518",
    "sg:postcode":"28467",
    "sg:province":"NC",
    "wof:name":"Harriett Norris",
    "wof:placetype":"venue"
},
  "geometry": {"coordinates":[-78.566596,33.900284],"type":"Point"}
}