{
  "type": "Feature",
  "properties": {
    "addr:full":"30 Briarwood Ct Durham NC 27713",
    "addr:housenumber":"30",
    "addr:postcode":"27713",
    "addr:street":"Briarwood Ct",
    "iso:country":"US",
    "sg:address":"30 Briarwood Ct",
    "sg:city":"Durham",
    "sg:classifiers":[
        {
            "category":"Building & Trades",
            "subcategory":"Construction",
            "type":"Services"
        }
    ],
    "sg:phone":"+1 919 544 4900",
    "sg:postcode":"27713",
    "sg:province":"NC",
    "sg:tags":[
        "floor",
        "laying",
        "contractor"
    ],
    "wof:name":"Off The Wall Carpet",
    "wof:placetype":"venue"
},
  "geometry": {"coordinates":[-78.908052,35.926002],"type":"Point"}
}