{
  "type": "Feature",
  "properties": {
    "iso:country":"US",
    "sg:address":"3647 Abernathy Dr",
    "sg:city":"Fayetteville",
    "sg:classifiers":[
        {
            "category":"Social Services",
            "subcategory":"Child Care",
            "type":"Services"
        }
    ],
    "sg:phone":"+1   ",
    "sg:postcode":"28311",
    "sg:province":"NC",
    "sg:tags":[
        "day"
    ],
    "wof:name":"Watch Over ME Childcare Center",
    "wof:placetype":"venue"
},
  "geometry": {"coordinates":[-78.88722,35.111655],"type":"Point"}
}