{
  "type": "Feature",
  "properties": {
    "addr:full":"113 Pebble Loch Ln Cary NC 27518",
    "addr:housenumber":"113",
    "addr:postcode":"27518",
    "addr:street":"Pebble Loch Ln",
    "iso:country":"US",
    "sg:address":"113 Pebble Loch Ln",
    "sg:city":"Cary",
    "sg:classifiers":[
        {
            "category":"Shopping",
            "subcategory":"Jewelry",
            "type":"Retail Goods"
        }
    ],
    "sg:phone":"+1 919 854 2001",
    "sg:postcode":"27518",
    "sg:province":"NC",
    "sg:tags":[
        "furniture"
    ],
    "wof:name":"Sweet Deal of Cary LLC",
    "wof:placetype":"venue"
},
  "geometry": {"coordinates":[-78.776415,35.73141],"type":"Point"}
}