{
  "type": "Feature",
  "properties": {
    "iso:country":"US",
    "sg:address":"308 Tarboro St",
    "sg:city":"Rocky Mount",
    "sg:classifiers":[
        {
            "category":"Taxi",
            "type":"Transportation"
        }
    ],
    "sg:phone":"+1 252 985 1200",
    "sg:postcode":"27801",
    "sg:province":"NC",
    "sg:tags":[
        "taxicab"
    ],
    "wof:name":"Rocky Mount Cab Co",
    "wof:placetype":"venue"
},
  "geometry": {"coordinates":[-77.792174,35.940459],"type":"Point"}
}