{
  "type": "Feature",
  "properties": {
    "addr:full":"1002 Trogdon Ave North Wilkesboro NC 28659",
    "addr:housenumber":"1002",
    "addr:postcode":"28659",
    "addr:street":"Trogdon Ave",
    "iso:country":"US",
    "sg:address":"1002 Trogdon Ave",
    "sg:city":"North Wilkesboro",
    "sg:classifiers":[
        {
            "category":"Building & Trades",
            "subcategory":"Cleaning & Sanitation",
            "type":"Services"
        }
    ],
    "sg:phone":"+1 336 667 4899",
    "sg:postcode":"28659",
    "sg:province":"NC",
    "sg:tags":[
        "janitor"
    ],
    "wof:name":"An Extra Pair Of Hands",
    "wof:placetype":"venue"
},
  "geometry": {"coordinates":[-81.151242,36.169245],"type":"Point"}
}