{
  "type": "Feature",
  "properties": {
    "iso:country":"US",
    "sg:address":"20480 Chartwell Center Dr",
    "sg:city":"Cornelius",
    "sg:classifiers":[
        {
            "category":"Health Services",
            "subcategory":"Chiropractor",
            "type":"Services"
        }
    ],
    "sg:phone":"+1 704 895 8117",
    "sg:postcode":"28031",
    "sg:province":"NC",
    "wof:name":"Chiropractic Network-Carolinas",
    "wof:placetype":"venue"
},
  "geometry": {"coordinates":[-80.878461,35.48024],"type":"Point"}
}