{
  "type": "Feature",
  "properties": {
    "addr:full":"809 E Arrowood Rd Charlotte NC 28217",
    "addr:housenumber":"809",
    "addr:postcode":"28217",
    "addr:street":"E Arrowood Rd",
    "iso:country":"US",
    "sg:address":"809 E Arrowood Rd",
    "sg:city":"Charlotte",
    "sg:classifiers":[
        {
            "category":"Restaurant",
            "type":"Food & Drink"
        }
    ],
    "sg:menulink":"http://www.allmenus.com/nc/charlotte/57893-la-providencia/menu/",
    "sg:phone":"+1 704 522 8581",
    "sg:postcode":"28217",
    "sg:province":"NC",
    "sg:tags":[
        "mexican"
    ],
    "wof:name":"La Providencia",
    "wof:placetype":"venue"
},
  "geometry": {"coordinates":[-80.879149,35.13781],"type":"Point"}
}