{
  "type": "Feature",
  "properties": {
    "iso:country":"US",
    "sg:address":"5710 US Hwy 74",
    "sg:city":"Indian Trail",
    "sg:classifiers":[
        {
            "category":"Autos & Motor Vehicles",
            "subcategory":"Automobile Sales",
            "type":"Retail Goods"
        }
    ],
    "sg:phone":"+1 704 821 9099",
    "sg:postcode":"28079",
    "sg:province":"NC",
    "sg:tags":[
        "used"
    ],
    "wof:name":"Autoselect Brokers Investments",
    "wof:placetype":"venue"
},
  "geometry": {"coordinates":[-80.63588900000001,35.062997],"type":"Point"}
}