{
  "type": "Feature",
  "properties": {
    "addr:full":"238 Clay St Gastonia NC 28052",
    "addr:housenumber":"238",
    "addr:postcode":"28052",
    "addr:street":"Clay St",
    "iso:country":"US",
    "sg:address":"238 Clay St",
    "sg:city":"Gastonia",
    "sg:classifiers":[
        {
            "category":"Arts & Performance",
            "subcategory":"Theater",
            "type":"Entertainment"
        }
    ],
    "sg:phone":"+1 704 865 0160",
    "sg:postcode":"28052",
    "sg:province":"NC",
    "wof:name":"Gastonia Little Theatre Inc",
    "wof:placetype":"venue"
},
  "geometry": {"coordinates":[-81.191614,35.261106],"type":"Point"}
}