{
  "type": "Feature",
  "properties": {
    "iso:country":"US",
    "sg:address":"601 E Salisbury St",
    "sg:city":"Asheboro",
    "sg:classifiers":[
        {
            "category":"Building & Trades",
            "subcategory":"Construction",
            "type":"Services"
        }
    ],
    "sg:phone":"+1 336 629 7600",
    "sg:postcode":"27203",
    "sg:province":"NC",
    "sg:tags":[
        "general",
        "contractor"
    ],
    "wof:name":"Isley Construction",
    "wof:placetype":"venue"
},
  "geometry": {"coordinates":[-79.804039,35.706323],"type":"Point"}
}