{
  "type": "Feature",
  "properties": {
    "iso:country":"US",
    "sg:address":"8101 South Blvd",
    "sg:city":"Charlotte",
    "sg:classifiers":[
        {
            "category":"Retail",
            "subcategory":"Auto Repair",
            "type":"Services"
        }
    ],
    "sg:phone":"+1 704 556 0271",
    "sg:postcode":"28273",
    "sg:province":"NC",
    "sg:tags":[
        "body"
    ],
    "sg:website":"www.dentwizard.com",
    "wof:name":"Dent Wizard",
    "wof:placetype":"venue"
},
  "geometry": {"coordinates":[-80.877387,35.127089],"type":"Point"}
}