{
  "type": "Feature",
  "properties": {
    "iso:country":"US",
    "sg:address":"2377 Corporation Pkwy",
    "sg:city":"Burlington",
    "sg:classifiers":[
        {
            "category":"Shopping",
            "subcategory":"Gifts & Souvenirs",
            "type":"Retail Goods"
        }
    ],
    "sg:phone":"+1 336 222 0776",
    "sg:postcode":"27215",
    "sg:province":"NC",
    "wof:name":"Paper Factory The",
    "wof:placetype":"venue"
},
  "geometry": {"coordinates":[-79.43588,36.066281],"type":"Point"}
}