{
  "type": "Feature",
  "properties": {
    "addr:full":"323 S Arlington St Salisbury NC 28144",
    "addr:housenumber":"323",
    "addr:postcode":"28144",
    "addr:street":"S Arlington St",
    "iso:country":"US",
    "sg:address":"323 S Arlington St",
    "sg:city":"Salisbury",
    "sg:classifiers":[
        {
            "category":"Restaurant",
            "type":"Food & Drink"
        }
    ],
    "sg:menulink":"http://www.allmenus.com/nc/salisbury/137603-subway/menu/",
    "sg:phone":"+1 704 633 3803",
    "sg:postcode":"28144",
    "sg:province":"NC",
    "sg:tags":[
        "american",
        "sandwich"
    ],
    "wof:name":"Subway",
    "wof:placetype":"venue"
},
  "geometry": {"coordinates":[-80.468645,35.655918],"type":"Point"}
}