{
  "type": "Feature",
  "properties": {
    "iso:country":"US",
    "sg:address":"400 Princess St",
    "sg:city":"Wilmington",
    "sg:classifiers":[
        {
            "category":"Government",
            "subcategory":"Police Station",
            "type":"Public Place"
        }
    ],
    "sg:phone":"+1 910 000 1111",
    "sg:postcode":"28401",
    "sg:province":"NC",
    "sg:tags":[
        "sheriff"
    ],
    "wof:name":"New Hanover County Sheriff",
    "wof:placetype":"venue"
},
  "geometry": {"coordinates":[-77.94352000000001,34.236891],"type":"Point"}
}