{
  "type": "Feature",
  "properties": {
    "addr:full":"720 N Grove St Hendersonville NC 28792",
    "addr:housenumber":"720",
    "addr:postcode":"28792",
    "addr:street":"N Grove St",
    "iso:country":"US",
    "sg:address":"720 N Grove St",
    "sg:city":"Hendersonville",
    "sg:classifiers":[
        {
            "category":"Building & Trades",
            "subcategory":"Construction",
            "type":"Services"
        }
    ],
    "sg:phone":"+1 828 697 9598",
    "sg:postcode":"28792",
    "sg:province":"NC",
    "sg:tags":[
        "contractor"
    ],
    "wof:name":"Dunlap Construction",
    "wof:placetype":"venue"
},
  "geometry": {"coordinates":[-82.459502,35.321146],"type":"Point"}
}