{
  "type": "Feature",
  "properties": {
    "addr:full":"323 Bendix Dr Salisbury NC 28146",
    "addr:housenumber":"323",
    "addr:postcode":"28146",
    "addr:street":"Bendix Dr",
    "iso:country":"US",
    "sg:address":"323 Bendix Dr",
    "sg:city":"Salisbury",
    "sg:classifiers":[
        {
            "category":"Travel",
            "subcategory":"Hotels & Motels",
            "type":"Entertainment"
        }
    ],
    "sg:phone":"+1 704 633 5961",
    "sg:postcode":"28146",
    "sg:province":"NC",
    "wof:name":"Days Inn",
    "wof:placetype":"venue"
},
  "geometry": {"coordinates":[-80.468461,35.651053],"type":"Point"}
}