{
  "type": "Feature",
  "properties": {
    "iso:country":"US",
    "sg:address":"1554 Clayton Dr",
    "sg:city":"Charlotte",
    "sg:classifiers":[
        {
            "category":"Building & Trades",
            "subcategory":"Construction",
            "type":"Services"
        }
    ],
    "sg:phone":"+1 704 333 4243",
    "sg:postcode":"28203",
    "sg:province":"NC",
    "sg:tags":[
        "roofing",
        "contractor"
    ],
    "wof:name":"Griffin Construction Co",
    "wof:placetype":"venue"
},
  "geometry": {"coordinates":[-80.847883,35.19574],"type":"Point"}
}