{
  "type": "Feature",
  "properties": {
    "addr:full":"1101 Charter Pl Charlotte NC 28211",
    "addr:housenumber":"1101",
    "addr:postcode":"28211",
    "addr:street":"Charter Pl",
    "iso:country":"US",
    "sg:address":"1101 Charter Pl",
    "sg:city":"Charlotte",
    "sg:classifiers":[
        {
            "category":"Professional",
            "subcategory":"Management & Consulting",
            "type":"Services"
        }
    ],
    "sg:phone":"+1   ",
    "sg:postcode":"28211",
    "sg:province":"NC",
    "wof:name":"Calbert & Associates",
    "wof:placetype":"venue"
},
  "geometry": {"coordinates":[-80.76658500000001,35.161003],"type":"Point"}
}