{
  "type": "Feature",
  "properties": {
    "addr:full":"209 N 35th St New Bern NC 28557",
    "addr:housenumber":"209",
    "addr:postcode":"28557",
    "addr:street":"N 35Th St",
    "iso:country":"US",
    "sg:address":"209 N 35th St",
    "sg:city":"New Bern",
    "sg:classifiers":[
        {
            "category":"Social Services",
            "type":"Services"
        }
    ],
    "sg:phone":"+1 252 240 0380",
    "sg:postcode":"28557",
    "sg:province":"NC",
    "sg:tags":[
        "counseling"
    ],
    "wof:name":"Advance Counseling",
    "wof:placetype":"venue"
},
  "geometry": {"coordinates":[-76.753547,34.727928],"type":"Point"}
}