{
  "type": "Feature",
  "properties": {
    "iso:country":"US",
    "sg:address":"113 E Main St",
    "sg:city":"Beulaville",
    "sg:phone":"+1 910 298 4118",
    "sg:postcode":"28518",
    "sg:province":"NC",
    "sg:tags":[
        "oil"
    ],
    "wof:name":"Thomas & Horne Tire & Oil Co",
    "wof:placetype":"venue"
},
  "geometry": {"coordinates":[-77.77346300000001,34.923794],"type":"Point"}
}