{
  "type": "Feature",
  "properties": {
    "iso:country":"US",
    "sg:address":"5001 Randolph Rd",
    "sg:city":"Charlotte",
    "sg:classifiers":[
        {
            "category":"Health Services",
            "subcategory":"Doctor",
            "type":"Services"
        }
    ],
    "sg:phone":"+1 704 536 1336",
    "sg:postcode":"28211",
    "sg:province":"NC",
    "sg:tags":[
        "dentist"
    ],
    "wof:name":"Charles F Robinson DDS",
    "wof:placetype":"venue"
},
  "geometry": {"coordinates":[-80.794815,35.167159],"type":"Point"}
}