{
  "type": "Feature",
  "properties": {
    "addr:full":"304 High Hill Rd Jacksonville NC 28540",
    "addr:housenumber":"304",
    "addr:postcode":"28540",
    "addr:street":"High Hill Rd",
    "iso:country":"US",
    "sg:address":"304 High Hill Rd",
    "sg:city":"Jacksonville",
    "sg:classifiers":[
        {
            "category":"Retail",
            "subcategory":"Auto Repair",
            "type":"Services"
        }
    ],
    "sg:phone":"+1   ",
    "sg:postcode":"28540",
    "sg:province":"NC",
    "sg:tags":[
        "automotive"
    ],
    "wof:name":"Mc Coys Garage",
    "wof:placetype":"venue"
},
  "geometry": {"coordinates":[-77.486501,34.663],"type":"Point"}
}