{
  "type": "Feature",
  "properties": {
    "addr:full":"609 Lakeshore Dr Goldsboro NC 27534",
    "addr:housenumber":"609",
    "addr:postcode":"27534",
    "addr:street":"Lakeshore Dr",
    "iso:country":"US",
    "sg:address":"609 Lakeshore Dr",
    "sg:city":"Goldsboro",
    "sg:classifiers":[
        {
            "category":"Building & Trades",
            "subcategory":"Construction",
            "type":"Services"
        }
    ],
    "sg:phone":"+1 919 751 5402",
    "sg:postcode":"27534",
    "sg:province":"NC",
    "sg:tags":[
        "house"
    ],
    "wof:name":"Graham Home Repair",
    "wof:placetype":"venue"
},
  "geometry": {"coordinates":[-77.871951,35.303619],"type":"Point"}
}