{
  "type": "Feature",
  "properties": {
    "addr:full":"5141 Beulah Church Rd Lumberton NC 28358",
    "addr:housenumber":"5141",
    "addr:postcode":"28358",
    "addr:street":"Beulah Church Rd",
    "iso:country":"US",
    "sg:address":"5141 Beulah Church Rd",
    "sg:city":"Lumberton",
    "sg:classifiers":[
        {
            "category":"Building & Trades",
            "subcategory":"Plumbing",
            "type":"Services"
        }
    ],
    "sg:phone":"+1 910 738 7952",
    "sg:postcode":"28358",
    "sg:province":"NC",
    "sg:tags":[
        "contractor"
    ],
    "wof:name":"Jesse Fisher Ace Plumbing",
    "wof:placetype":"venue"
},
  "geometry": {"coordinates":[-78.91564700000001,34.531037],"type":"Point"}
}