{
  "type": "Feature",
  "properties": {
    "addr:full":"109 E Innes St Salisbury NC 28144",
    "addr:housenumber":"109",
    "addr:postcode":"28144",
    "addr:street":"E Innes St",
    "iso:country":"US",
    "sg:address":"109 E Innes St",
    "sg:city":"Salisbury",
    "sg:classifiers":[
        {
            "category":"Shopping",
            "subcategory":"Gifts & Souvenirs",
            "type":"Retail Goods"
        }
    ],
    "sg:phone":"+1 704 636 2726",
    "sg:postcode":"28144",
    "sg:province":"NC",
    "wof:name":"Carolina Cards",
    "wof:placetype":"venue"
},
  "geometry": {"coordinates":[-80.468917,35.666469],"type":"Point"}
}