{
  "type": "Feature",
  "properties": {
    "addr:full":"785 Peach Orchard Ln Salisbury NC 28147",
    "addr:housenumber":"785",
    "addr:postcode":"28147",
    "addr:street":"Peach Orchard Ln",
    "iso:country":"US",
    "sg:address":"785 Peach Orchard Ln",
    "sg:city":"Salisbury",
    "sg:classifiers":[
        {
            "category":"Retail",
            "subcategory":"Repair Shop",
            "type":"Services"
        }
    ],
    "sg:phone":"+1   ",
    "sg:postcode":"28147",
    "sg:province":"NC",
    "sg:tags":[
        "sewing",
        "mach"
    ],
    "wof:name":"Basinger Sewing Machine",
    "wof:placetype":"venue"
},
  "geometry": {"coordinates":[-80.525826,35.624968],"type":"Point"}
}