{
  "type": "Feature",
  "properties": {
    "addr:full":"112 Deerwood Ct Chapel Hill NC 27517",
    "addr:housenumber":"112",
    "addr:postcode":"27517",
    "addr:street":"Deerwood Ct",
    "iso:country":"US",
    "sg:address":"112 Deerwood Ct",
    "sg:city":"Chapel Hill",
    "sg:classifiers":[
        {
            "category":"Professional",
            "type":"Services"
        }
    ],
    "sg:phone":"+1 919 967 1542",
    "sg:postcode":"27517",
    "sg:province":"NC",
    "wof:name":"Thomas & Samantha Maynard",
    "wof:placetype":"venue"
},
  "geometry": {"coordinates":[-79.017562,35.924444],"type":"Point"}
}