{
  "type": "Feature",
  "properties": {
    "iso:country":"US",
    "sg:address":"1320 Industrial Dr",
    "sg:city":"Matthews",
    "sg:classifiers":[
        {
            "category":"Manufacturing",
            "subcategory":"Tools & Machinery",
            "type":"Manufacturing & Wholesale Goods"
        }
    ],
    "sg:phone":"+1 704 845 2785",
    "sg:postcode":"28105",
    "sg:province":"NC",
    "sg:tags":[
        "equipment",
        "woodworking",
        "mfg"
    ],
    "sg:website":"www.ogdeninc.com",
    "wof:name":"Ogden Enterprises Inc",
    "wof:placetype":"venue"
},
  "geometry": {"coordinates":[-80.727969,35.129837],"type":"Point"}
}