{
  "type": "Feature",
  "properties": {
    "iso:country":"US",
    "sg:address":"917 Charlotte Hwy",
    "sg:city":"Fairview",
    "sg:classifiers":[
        {
            "category":"Retail",
            "subcategory":"Car Wash",
            "type":"Services"
        }
    ],
    "sg:phone":"+1   ",
    "sg:postcode":"28730",
    "sg:province":"NC",
    "sg:tags":[
        "carwash"
    ],
    "wof:name":"Detail Time",
    "wof:placetype":"venue"
},
  "geometry": {"coordinates":[-82.439097,35.54031],"type":"Point"}
}