{
  "type": "Feature",
  "properties": {
    "addr:full":"120 Henry St Henderson NC 27536",
    "addr:housenumber":"120",
    "addr:postcode":"27536",
    "addr:street":"Henry St",
    "iso:country":"US",
    "sg:address":"120 Henry St",
    "sg:city":"Henderson",
    "sg:classifiers":[
        {
            "category":"Professional",
            "type":"Services"
        }
    ],
    "sg:phone":"+1 252 431 1868",
    "sg:postcode":"27536",
    "sg:province":"NC",
    "sg:tags":[
        "establishment"
    ],
    "wof:name":"T &N T Boxing",
    "wof:placetype":"venue"
},
  "geometry": {"coordinates":[-78.39311600000001,36.340095],"type":"Point"}
}