{
  "type": "Feature",
  "properties": {
    "addr:full":"142 Claire Dr Clayton NC 27520",
    "addr:housenumber":"142",
    "addr:postcode":"27520",
    "addr:street":"Claire Dr",
    "iso:country":"US",
    "sg:address":"142 Claire Dr",
    "sg:city":"Clayton",
    "sg:classifiers":[
        {
            "category":"Professional",
            "subcategory":"Management & Consulting",
            "type":"Services"
        }
    ],
    "sg:phone":"+1   ",
    "sg:postcode":"27520",
    "sg:province":"NC",
    "sg:tags":[
        "public",
        "relations"
    ],
    "wof:name":"Harvey Inc",
    "wof:placetype":"venue"
},
  "geometry": {"coordinates":[-78.447237,35.68825],"type":"Point"}
}