{
  "type": "Feature",
  "properties": {
    "addr:full":"37 US Hwy 221 Bus Marion NC 28752",
    "addr:housenumber":"37",
    "addr:postcode":"28752",
    "addr:street":"Us Hwy 221 Bus",
    "iso:country":"US",
    "sg:address":"37 US Hwy 221 Bus",
    "sg:city":"Marion",
    "sg:classifiers":[
        {
            "category":"Home & Garden",
            "subcategory":"Garden Supply",
            "type":"Retail Goods"
        }
    ],
    "sg:phone":"+1 828 652 5399",
    "sg:postcode":"28752",
    "sg:province":"NC",
    "sg:tags":[
        "lawn",
        "mower"
    ],
    "wof:name":"Rhinehardts Saw & Lawn Equip",
    "wof:placetype":"venue"
},
  "geometry": {"coordinates":[-82.009681,35.685245],"type":"Point"}
}