{
  "type": "Feature",
  "properties": {
    "addr:full":"1425 Whittington Dr Raleigh NC 27614",
    "addr:housenumber":"1425",
    "addr:postcode":"27614",
    "addr:street":"Whittington Dr",
    "iso:country":"US",
    "sg:address":"1425 Whittington Dr",
    "sg:city":"Raleigh",
    "sg:classifiers":[
        {
            "category":"Real Estate",
            "subcategory":"Real Estate Agent",
            "type":"Services"
        }
    ],
    "sg:phone":"+1 919 847 7214",
    "sg:postcode":"27614",
    "sg:province":"NC",
    "wof:name":"Equity Appraisal Services Inc",
    "wof:placetype":"venue"
},
  "geometry": {"coordinates":[-78.584563,35.92342],"type":"Point"}
}