{
  "type": "Feature",
  "properties": {
    "addr:full":"3701 Clayburn Rd Greensboro NC 27406",
    "addr:housenumber":"3701",
    "addr:postcode":"27406",
    "addr:street":"Clayburn Rd",
    "iso:country":"US",
    "sg:address":"3701 Clayburn Rd",
    "sg:city":"Greensboro",
    "sg:classifiers":[
        {
            "category":"Professional",
            "subcategory":"Business Services",
            "type":"Services"
        }
    ],
    "sg:phone":"+1   ",
    "sg:postcode":"27406",
    "sg:province":"NC",
    "wof:name":"Katco Design Inc",
    "wof:placetype":"venue"
},
  "geometry": {"coordinates":[-79.686753,36.018421],"type":"Point"}
}