{
  "type": "Feature",
  "properties": {
    "iso:country":"US",
    "sg:address":"210 Oak Ave",
    "sg:city":"Kannapolis",
    "sg:classifiers":[
        {
            "category":"Real Estate",
            "subcategory":"Real Estate Agent",
            "type":"Services"
        }
    ],
    "sg:phone":"+1 704 932 0141",
    "sg:postcode":"28081",
    "sg:province":"NC",
    "sg:tags":[
        "management"
    ],
    "wof:name":"Atlantic American Properties",
    "wof:placetype":"venue"
},
  "geometry": {"coordinates":[-80.627543,35.496931],"type":"Point"}
}