{
  "type": "Feature",
  "properties": {
    "addr:full":"901 S Brightleaf Blvd Smithfield NC 27577",
    "addr:housenumber":"901",
    "addr:postcode":"27577",
    "addr:street":"S Brightleaf Blvd",
    "iso:country":"US",
    "sg:address":"901 S Brightleaf Blvd",
    "sg:city":"Smithfield",
    "sg:classifiers":[
        {
            "category":"Food & Beverages",
            "subcategory":"Groceries & Convenience Stores",
            "type":"Retail Goods"
        }
    ],
    "sg:phone":"+1 919 209 0782",
    "sg:postcode":"27577",
    "sg:province":"NC",
    "sg:tags":[
        "grocer"
    ],
    "sg:website":"www.foodlion.com",
    "wof:name":"Food Lion",
    "wof:placetype":"venue"
},
  "geometry": {"coordinates":[-78.3526,35.499102],"type":"Point"}
}