{
  "type": "Feature",
  "properties": {
    "addr:full":"961 N Main St Mooresville NC 28115",
    "addr:housenumber":"961",
    "addr:postcode":"28115",
    "addr:street":"N Main St",
    "iso:country":"US",
    "sg:address":"961 N Main St",
    "sg:city":"Mooresville",
    "sg:classifiers":[
        {
            "category":"Insurance",
            "subcategory":"Insurance Agent",
            "type":"Services"
        },
        {
            "category":"Insurance",
            "subcategory":"Hazard Insurance",
            "type":"Services"
        },
        {
            "category":"Insurance",
            "subcategory":"Title Insurance",
            "type":"Services"
        },
        {
            "category":"Insurance",
            "subcategory":"Life Insurance",
            "type":"Services"
        }
    ],
    "sg:phone":"+1 704 663 1230",
    "sg:postcode":"28115",
    "sg:province":"NC",
    "sg:tags":[
        "business",
        "auto",
        "commercial",
        "homeowner",
        "motorcycle",
        "renter"
    ],
    "wof:name":"Allstate Insurance Company - James Mccall",
    "wof:placetype":"venue"
},
  "geometry": {"coordinates":[-80.796126,35.588925],"type":"Point"}
}