{
  "type": "Feature",
  "properties": {
    "addr:full":"1103 Watson Way Knightdale NC 27545",
    "addr:housenumber":"1103",
    "addr:postcode":"27545",
    "addr:street":"Watson Way",
    "iso:country":"US",
    "sg:address":"1103 Watson Way",
    "sg:city":"Knightdale",
    "sg:classifiers":[
        {
            "category":"Real Estate",
            "subcategory":"Real Estate Agent",
            "type":"Services"
        }
    ],
    "sg:phone":"+1 919 217 2647",
    "sg:postcode":"27545",
    "sg:province":"NC",
    "wof:name":"Costal Consulting Co",
    "wof:placetype":"venue"
},
  "geometry": {"coordinates":[-78.518154,35.785468],"type":"Point"}
}