{
  "type": "Feature",
  "properties": {
    "addr:full":"361 Stanford Church Rd Siloam NC 27047",
    "addr:housenumber":"361",
    "addr:postcode":"27047",
    "addr:street":"Stanford Church Rd",
    "iso:country":"US",
    "sg:address":"361 Stanford Church Rd",
    "sg:city":"Siloam",
    "sg:classifiers":[
        {
            "category":"Real Estate",
            "subcategory":"Real Estate Operator",
            "type":"Services"
        }
    ],
    "sg:phone":"+1 336 374 5553",
    "sg:postcode":"27047",
    "sg:province":"NC",
    "sg:tags":[
        "property",
        "lessor"
    ],
    "wof:name":"Ronald F Rumberger",
    "wof:placetype":"venue"
},
  "geometry": {"coordinates":[-80.57799,36.345936],"type":"Point"}
}