{
  "type": "Feature",
  "properties": {
    "iso:country":"US",
    "sg:address":"357 N Railroad St",
    "sg:city":"Old Fort",
    "sg:classifiers":[
        {
            "category":"Social Services",
            "subcategory":"Child Care",
            "type":"Services"
        }
    ],
    "sg:phone":"+1 828 668 7766",
    "sg:postcode":"28762",
    "sg:province":"NC",
    "wof:name":"Little World Day Care",
    "wof:placetype":"venue"
},
  "geometry": {"coordinates":[-82.17569899999999,35.630944],"type":"Point"}
}