{
  "type": "Feature",
  "properties": {
    "iso:country":"US",
    "sg:address":"6339 Crabtree Rd",
    "sg:city":"Clyde",
    "sg:classifiers":[
        {
            "category":"Manufacturing",
            "subcategory":"Lumber",
            "type":"Manufacturing & Wholesale Goods"
        }
    ],
    "sg:phone":"+1 828 627 8010",
    "sg:postcode":"28721",
    "sg:province":"NC",
    "sg:tags":[
        "mill"
    ],
    "wof:name":"Sims Lumber Co",
    "wof:placetype":"venue"
},
  "geometry": {"coordinates":[-82.93839199999999,35.604556],"type":"Point"}
}