{
  "type": "Feature",
  "properties": {
    "iso:country":"US",
    "sg:address":"2008 W Cumberland St",
    "sg:city":"Dunn",
    "sg:classifiers":[
        {
            "category":"Food & Beverages",
            "subcategory":"Fruits & Vegetables",
            "type":"Retail Goods"
        }
    ],
    "sg:phone":"+1 910 892 1324",
    "sg:postcode":"28334",
    "sg:province":"NC",
    "sg:tags":[
        "produce"
    ],
    "wof:name":"T & L Strawberry Produce",
    "wof:placetype":"venue"
},
  "geometry": {"coordinates":[-78.63199899999999,35.319234],"type":"Point"}
}