{
  "type": "Feature",
  "properties": {
    "iso:country":"US",
    "sg:address":"40 Blake St",
    "sg:city":"Asheville",
    "sg:classifiers":[
        {
            "category":"Real Estate",
            "subcategory":"Developer",
            "type":"Services"
        }
    ],
    "sg:phone":"+1 828 684 9227",
    "sg:postcode":"28801",
    "sg:province":"NC",
    "wof:name":"Graham Development Group",
    "wof:placetype":"venue"
},
  "geometry": {"coordinates":[-82.561074,35.600185],"type":"Point"}
}