{
  "type": "Feature",
  "properties": {
    "addr:full":"1327 Tot Dellinger Rd Cherryville NC 28021",
    "addr:housenumber":"1327",
    "addr:postcode":"28021",
    "addr:street":"Tot Dellinger Rd",
    "iso:country":"US",
    "sg:address":"1327 Tot Dellinger Rd",
    "sg:city":"Cherryville",
    "sg:classifiers":[
        {
            "category":"Building & Trades",
            "subcategory":"Construction",
            "type":"Services"
        }
    ],
    "sg:phone":"+1 704 435 8553",
    "sg:postcode":"28021",
    "sg:province":"NC",
    "sg:tags":[
        "heavy"
    ],
    "wof:name":"A & B Trenching Company",
    "wof:placetype":"venue"
},
  "geometry": {"coordinates":[-81.393011,35.415019],"type":"Point"}
}