{
  "type": "Feature",
  "properties": {
    "iso:country":"US",
    "sg:address":"5106 Roxboro Rd",
    "sg:city":"Durham",
    "sg:classifiers":[
        {
            "category":"Wholesale",
            "subcategory":"Machinery & Supplies",
            "type":"Manufacturing & Wholesale Goods"
        }
    ],
    "sg:phone":"+1 919 477 4014",
    "sg:postcode":"27704",
    "sg:province":"NC",
    "sg:tags":[
        "equipment",
        "establishment"
    ],
    "wof:name":"Carolina Beauty College",
    "wof:placetype":"venue"
},
  "geometry": {"coordinates":[-78.908159,36.070549],"type":"Point"}
}