{
  "type": "Feature",
  "properties": {
    "iso:country":"US",
    "sg:address":"40655 Snuggs Rd",
    "sg:city":"Norwood",
    "sg:classifiers":[
        {
            "category":"Farming",
            "subcategory":"Farm & Veterinary Services",
            "type":"Manufacturing & Wholesale Goods"
        }
    ],
    "sg:phone":"+1 704 982 8301",
    "sg:postcode":"28128",
    "sg:province":"NC",
    "sg:tags":[
        "livestock"
    ],
    "wof:name":"Smith Farms",
    "wof:placetype":"venue"
},
  "geometry": {"coordinates":[-80.154051,35.270237],"type":"Point"}
}