{
  "type": "Feature",
  "properties": {
    "iso:country":"US",
    "sg:address":"1821 Ashley Loop",
    "sg:city":"Reidsville",
    "sg:classifiers":[
        {
            "category":"Real Estate",
            "subcategory":"Developer",
            "type":"Services"
        }
    ],
    "sg:phone":"+1 336 342 3441",
    "sg:postcode":"27320",
    "sg:province":"NC",
    "sg:tags":[
        "cemetery"
    ],
    "wof:name":"Roselawn Memorial Gardens",
    "wof:placetype":"venue"
},
  "geometry": {"coordinates":[-79.724822,36.426914],"type":"Point"}
}