{
  "type": "Feature",
  "properties": {
    "addr:full":"2568 E Main St Lincolnton NC 28092",
    "addr:housenumber":"2568",
    "addr:postcode":"28092",
    "addr:street":"E Main St",
    "iso:country":"US",
    "sg:address":"2568 E Main St",
    "sg:city":"Lincolnton",
    "sg:classifiers":[
        {
            "category":"Retail",
            "subcategory":"Auto Repair",
            "type":"Services"
        }
    ],
    "sg:phone":"+1 704 735 9140",
    "sg:postcode":"28092",
    "sg:province":"NC",
    "sg:tags":[
        "repairing",
        "automobile"
    ],
    "wof:name":"Richards Automotive",
    "wof:placetype":"venue"
},
  "geometry": {"coordinates":[-81.208108,35.481196],"type":"Point"}
}