{
  "type": "Feature",
  "properties": {
    "iso:country":"US",
    "sg:address":"18627 Northline Dr",
    "sg:city":"Cornelius",
    "sg:classifiers":[
        {
            "category":"Manufacturing",
            "subcategory":"Building Materials",
            "type":"Manufacturing & Wholesale Goods"
        }
    ],
    "sg:phone":"+1 704 895 5780",
    "sg:postcode":"28031",
    "sg:province":"NC",
    "sg:tags":[
        "mfg"
    ],
    "wof:name":"Shutters International",
    "wof:placetype":"venue"
},
  "geometry": {"coordinates":[-80.85449199999999,35.45945],"type":"Point"}
}