{
  "type": "Feature",
  "properties": {
    "addr:full":"220 Nash St E Wilson NC 27893",
    "addr:housenumber":"220",
    "addr:postcode":"27893",
    "addr:street":"Nash St E",
    "iso:country":"US",
    "sg:address":"220 Nash St E",
    "sg:city":"Wilson",
    "sg:classifiers":[
        {
            "category":"Professional",
            "subcategory":"Accounting & Tax Preparation",
            "type":"Services"
        }
    ],
    "sg:phone":"+1 252 206 1468",
    "sg:postcode":"27893",
    "sg:province":"NC",
    "sg:tags":[
        "return",
        "filing"
    ],
    "wof:name":"T & K Income Tax Svc",
    "wof:placetype":"venue"
},
  "geometry": {"coordinates":[-77.91017100000001,35.724778],"type":"Point"}
}