{
  "type": "Feature",
  "properties": {
    "iso:country":"US",
    "sg:address":"1322 E Millbrook Rd",
    "sg:city":"Raleigh",
    "sg:classifiers":[
        {
            "category":"Utilities",
            "subcategory":"Mobile Phone",
            "type":"Services"
        },
        {
            "category":"Shopping",
            "type":"Retail Goods"
        }
    ],
    "sg:phone":"+1 919 850 1389",
    "sg:postcode":"27609",
    "sg:province":"NC",
    "sg:tags":[
        "cellular",
        "telephone",
        "merchandise"
    ],
    "wof:name":"Planet Wireless",
    "wof:placetype":"venue"
},
  "geometry": {"coordinates":[-78.615048,35.850522],"type":"Point"}
}