{
  "type": "Feature",
  "properties": {
    "iso:country":"US",
    "sg:address":"152 Northcutt Rd",
    "sg:city":"Robbins",
    "sg:classifiers":[
        {
            "category":"Professional",
            "subcategory":"Computer Services",
            "type":"Services"
        }
    ],
    "sg:phone":"+1   ",
    "sg:postcode":"27325",
    "sg:province":"NC",
    "sg:tags":[
        "datum"
    ],
    "wof:name":"Raymond F Hutchins",
    "wof:placetype":"venue"
},
  "geometry": {"coordinates":[-79.665986,35.474652],"type":"Point"}
}