{
  "type": "Feature",
  "properties": {
    "addr:full":"2513 E Main St Lincolnton NC 28092",
    "addr:housenumber":"2513",
    "addr:postcode":"28092",
    "addr:street":"E Main St",
    "iso:country":"US",
    "sg:address":"2513 E Main St",
    "sg:city":"Lincolnton",
    "sg:classifiers":[
        {
            "category":"Professional",
            "subcategory":"Business Services",
            "type":"Services"
        }
    ],
    "sg:phone":"+1 704 732 2169",
    "sg:postcode":"28092",
    "sg:province":"NC",
    "sg:tags":[
        "embroidery"
    ],
    "wof:name":"Carolina Custom Embroidery",
    "wof:placetype":"venue"
},
  "geometry": {"coordinates":[-81.210616,35.480398],"type":"Point"}
}