{
  "type": "Feature",
  "properties": {
    "iso:country":"US",
    "sg:address":"900 The Cape Blvd",
    "sg:city":"Wilmington",
    "sg:classifiers":[
        {
            "category":"Utilities",
            "subcategory":"Water",
            "type":"Services"
        }
    ],
    "sg:phone":"+1 910 791 4404",
    "sg:postcode":"28412",
    "sg:province":"NC",
    "sg:tags":[
        "company",
        "sewage"
    ],
    "wof:name":"Aqua North Carolina",
    "wof:placetype":"venue"
},
  "geometry": {"coordinates":[-77.90035,34.075026],"type":"Point"}
}