{
  "type": "Feature",
  "properties": {
    "iso:country":"US",
    "sg:address":"294 S 4th St",
    "sg:city":"Highlands",
    "sg:classifiers":[
        {
            "category":"Home & Garden",
            "subcategory":"Furniture",
            "type":"Retail Goods"
        }
    ],
    "sg:phone":"+1 828 526 8364",
    "sg:postcode":"28741",
    "sg:province":"NC",
    "sg:tags":[
        "cabinet"
    ],
    "wof:name":"Highlands Cabinet Co",
    "wof:placetype":"venue"
},
  "geometry": {"coordinates":[-83.197441,35.051318],"type":"Point"}
}