{
  "type": "Feature",
  "properties": {
    "iso:country":"US",
    "sg:address":"5306 High St",
    "sg:city":"Morehead City",
    "sg:classifiers":[
        {
            "category":"Shopping",
            "type":"Retail Goods"
        }
    ],
    "sg:phone":"+1 252 222 0707",
    "sg:postcode":"28557",
    "sg:province":"NC",
    "sg:tags":[
        "awning",
        "canopy"
    ],
    "wof:name":"Coastal Awnings",
    "wof:placetype":"venue"
},
  "geometry": {"coordinates":[-76.818544,34.738475],"type":"Point"}
}