{
  "type": "Feature",
  "properties": {
    "addr:full":"2706 Byerly Dr Wilson NC 27896",
    "addr:housenumber":"2706",
    "addr:postcode":"27896",
    "addr:street":"Byerly Dr",
    "iso:country":"US",
    "sg:address":"2706 Byerly Dr",
    "sg:city":"Wilson",
    "sg:classifiers":[
        {
            "category":"Retail",
            "subcategory":"Laundry & Dry Cleaning",
            "type":"Services"
        }
    ],
    "sg:phone":"+1 252 289 7505",
    "sg:postcode":"27896",
    "sg:province":"NC",
    "sg:tags":[
        "cleaners",
        "rug",
        "carpet"
    ],
    "wof:name":"Carpet Cleaner",
    "wof:placetype":"venue"
},
  "geometry": {"coordinates":[-77.928218,35.760978],"type":"Point"}
}