{
  "type": "Feature",
  "properties": {
    "iso:country":"US",
    "sg:address":"2 Princess St",
    "sg:city":"Wilmington",
    "sg:classifiers":[
        {
            "category":"Government",
            "subcategory":"Office",
            "type":"Public Place"
        }
    ],
    "sg:phone":"+1 910 343 4876",
    "sg:postcode":"28401",
    "sg:province":"NC",
    "sg:tags":[
        "international",
        "affairs"
    ],
    "wof:name":"Port of Entry",
    "wof:placetype":"venue"
},
  "geometry": {"coordinates":[-77.948847,34.236456],"type":"Point"}
}