{
  "type": "Feature",
  "properties": {
    "addr:full":"1029 Breezewood Rd Greensboro NC 27410",
    "addr:housenumber":"1029",
    "addr:postcode":"27410",
    "addr:street":"Breezewood Rd",
    "iso:country":"US",
    "sg:address":"1029 Breezewood Rd",
    "sg:city":"Greensboro",
    "sg:classifiers":[
        {
            "category":"Recreation",
            "type":"Entertainment"
        }
    ],
    "sg:phone":"+1 336 299 9702",
    "sg:postcode":"27410",
    "sg:province":"NC",
    "sg:tags":[
        "drinking",
        "practice",
        "golf",
        "range"
    ],
    "wof:name":"Longview Practice Center",
    "wof:placetype":"venue"
},
  "geometry": {"coordinates":[-79.917255,36.103737],"type":"Point"}
}