{
  "type": "Feature",
  "properties": {
    "iso:country":"US",
    "sg:address":"2504 Whitney Hill Rd",
    "sg:city":"Charlotte",
    "sg:classifiers":[
        {
            "category":"Professional",
            "subcategory":"Engineering",
            "type":"Services"
        }
    ],
    "sg:phone":"+1   ",
    "sg:postcode":"28226",
    "sg:province":"NC",
    "wof:name":"Maloney & Associates Inc",
    "wof:placetype":"venue"
},
  "geometry": {"coordinates":[-80.80121800000001,35.123116],"type":"Point"}
}