{
  "type": "Feature",
  "properties": {
    "addr:full":"575 N Main St Granite Falls NC 28630",
    "addr:housenumber":"575",
    "addr:postcode":"28630",
    "addr:street":"N Main St",
    "iso:country":"US",
    "sg:address":"575 N Main St",
    "sg:city":"Granite Falls",
    "sg:classifiers":[
        {
            "category":"Wholesale",
            "subcategory":"Machinery & Supplies",
            "type":"Manufacturing & Wholesale Goods"
        }
    ],
    "sg:phone":"+1 828 396 3391",
    "sg:postcode":"28630",
    "sg:province":"NC",
    "sg:tags":[
        "tractor"
    ],
    "wof:name":"Granite Machinery & Equipment",
    "wof:placetype":"venue"
},
  "geometry": {"coordinates":[-81.450436,35.809223],"type":"Point"}
}