{
  "type": "Feature",
  "properties": {
    "addr:full":"6028 Old Mount Holly Rd Charlotte NC 28208",
    "addr:housenumber":"6028",
    "addr:postcode":"28208",
    "addr:street":"Old Mount Holly Rd",
    "iso:country":"US",
    "sg:address":"6028 Old Mount Holly Rd",
    "sg:city":"Charlotte",
    "sg:classifiers":[
        {
            "category":"Freight",
            "type":"Transportation"
        }
    ],
    "sg:phone":"+1 704 398 1542",
    "sg:postcode":"28208",
    "sg:province":"NC",
    "sg:tags":[
        "dry",
        "bulk",
        "trucking"
    ],
    "sg:website":"www.superior-carriers.com",
    "wof:name":"Superior Carriers Inc",
    "wof:placetype":"venue"
},
  "geometry": {"coordinates":[-80.90580199999999,35.281046],"type":"Point"}
}