{
  "type": "Feature",
  "properties": {
    "iso:country":"US",
    "sg:address":"2519 Washburn Rd",
    "sg:city":"Shelby",
    "sg:classifiers":[
        {
            "category":"Building & Trades",
            "subcategory":"Construction",
            "type":"Services"
        }
    ],
    "sg:phone":"+1 704 434 7045",
    "sg:postcode":"28150",
    "sg:province":"NC",
    "sg:tags":[
        "company"
    ],
    "wof:name":"Washburn Construction",
    "wof:placetype":"venue"
},
  "geometry": {"coordinates":[-81.644744,35.321771],"type":"Point"}
}