{
  "type": "Feature",
  "properties": {
    "addr:full":"10 Laboratory Dr Durham NC 27703",
    "addr:postcode":"27703",
    "addr:street":"Laboratory Dr",
    "iso:country":"US",
    "sg:address":"10 Laboratory Dr",
    "sg:city":"Durham",
    "sg:classifiers":[
        {
            "category":"Professional",
            "subcategory":"Art Services",
            "type":"Services"
        }
    ],
    "sg:phone":"+1 919 544 2193",
    "sg:postcode":"27703",
    "sg:province":"NC",
    "sg:tags":[
        "graphic",
        "designer"
    ],
    "sg:website":"www.cleandata.com",
    "wof:name":"Clean Design Inc",
    "wof:placetype":"venue"
},
  "geometry": {"coordinates":[-78.858475,35.901046],"type":"Point"}
}