{
  "type": "Feature",
  "properties": {
    "addr:full":"6708 Westborough Dr Raleigh NC 27612",
    "addr:housenumber":"6708",
    "addr:postcode":"27612",
    "addr:street":"Westborough Dr",
    "iso:country":"US",
    "sg:address":"6708 Westborough Dr",
    "sg:city":"Raleigh",
    "sg:classifiers":[
        {
            "category":"Wholesale",
            "subcategory":"Construction Materials",
            "type":"Manufacturing & Wholesale Goods"
        }
    ],
    "sg:phone":"+1 919 782 1333",
    "sg:postcode":"27612",
    "sg:province":"NC",
    "sg:tags":[
        "laminate"
    ],
    "wof:name":"Meyer Laminates (se) Inc",
    "wof:placetype":"venue"
},
  "geometry": {"coordinates":[-78.72887,35.872203],"type":"Point"}
}