{
  "type": "Feature",
  "properties": {
    "iso:country":"US",
    "sg:address":"103 Eastbrook Dr",
    "sg:city":"Greenville",
    "sg:classifiers":[
        {
            "category":"Restaurant",
            "type":"Food & Drink"
        }
    ],
    "sg:phone":"+1 252 551 3190",
    "sg:postcode":"27858",
    "sg:province":"NC",
    "sg:tags":[
        "mexican"
    ],
    "wof:name":"Mazatlan Mexican Restaurant",
    "wof:placetype":"venue"
},
  "geometry": {"coordinates":[-77.33743800000001,35.597044],"type":"Point"}
}