{
  "type": "Feature",
  "properties": {
    "iso:country":"US",
    "sg:address":"9 Island Dr",
    "sg:city":"Wrightsville Bch",
    "sg:classifiers":[
        {
            "category":"Professional",
            "subcategory":"Research",
            "type":"Services"
        },
        {
            "category":"Professional",
            "subcategory":"Management & Consulting",
            "type":"Services"
        }
    ],
    "sg:phone":"+1 910 509 1805",
    "sg:postcode":"28480",
    "sg:province":"NC",
    "sg:tags":[
        "economic",
        "analysis",
        "business"
    ],
    "wof:name":"Greenfield Development Co",
    "wof:placetype":"venue"
},
  "geometry": {"coordinates":[-77.802194,34.211051],"type":"Point"}
}