{
  "type": "Feature",
  "properties": {
    "addr:full":"115 Willow Run Dr Morganton NC 28655",
    "addr:housenumber":"115",
    "addr:postcode":"28655",
    "addr:street":"Willow Run Dr",
    "iso:country":"US",
    "sg:address":"115 Willow Run Dr",
    "sg:city":"Morganton",
    "sg:classifiers":[
        {
            "category":"Real Estate",
            "subcategory":"Real Estate Operator",
            "type":"Services"
        }
    ],
    "sg:phone":"+1 828 438 8825",
    "sg:postcode":"28655",
    "sg:province":"NC",
    "sg:tags":[
        "building",
        "apartment"
    ],
    "wof:name":"Willow Run",
    "wof:placetype":"venue"
},
  "geometry": {"coordinates":[-81.66917100000001,35.724367],"type":"Point"}
}