{
  "type": "Feature",
  "properties": {
    "iso:country":"US",
    "sg:address":"417 Kingswood Dr",
    "sg:city":"Cary",
    "sg:classifiers":[
        {
            "category":"Health Services",
            "subcategory":"Clinic",
            "type":"Services"
        }
    ],
    "sg:phone":"+1 919 780 6250",
    "sg:postcode":"27513",
    "sg:province":"NC",
    "sg:tags":[
        "medical"
    ],
    "wof:name":"Tele-Nurse On Call",
    "wof:placetype":"venue"
},
  "geometry": {"coordinates":[-78.777036,35.795496],"type":"Point"}
}