{
  "type": "Feature",
  "properties": {
    "iso:country":"US",
    "sg:address":"361 Falls Rd",
    "sg:city":"Arden",
    "sg:classifiers":[
        {
            "category":"Professional",
            "subcategory":"Management & Consulting",
            "type":"Services"
        }
    ],
    "sg:phone":"+1 828 329 4661",
    "sg:postcode":"28751",
    "sg:province":"NC",
    "wof:name":"Housing Marketplace Inc",
    "wof:placetype":"venue"
},
  "geometry": {"coordinates":[-83.08855200000001,35.547825],"type":"Point"}
}