{
  "type": "Feature",
  "properties": {
    "addr:full":"1646 S Main St Laurinburg NC 28352",
    "addr:housenumber":"1646",
    "addr:postcode":"28352",
    "addr:street":"S Main St",
    "iso:country":"US",
    "sg:address":"1646 S Main St",
    "sg:city":"Laurinburg",
    "sg:classifiers":[
        {
            "category":"Building & Trades",
            "subcategory":"Equipment Rental",
            "type":"Services"
        }
    ],
    "sg:phone":"+1 910 291 1600",
    "sg:postcode":"28352",
    "sg:province":"NC",
    "sg:tags":[
        "leasing",
        "furniture"
    ],
    "sg:website":"www.rentway.com",
    "wof:name":"Rent Way",
    "wof:placetype":"venue"
},
  "geometry": {"coordinates":[-79.475267,34.755479],"type":"Point"}
}