{
  "type": "Feature",
  "properties": {
    "addr:full":"1928 Snow Hill Rd Durham NC 27712",
    "addr:housenumber":"1928",
    "addr:postcode":"27712",
    "addr:street":"Snow Hill Rd",
    "iso:country":"US",
    "sg:address":"1928 Snow Hill Rd",
    "sg:city":"Durham",
    "sg:classifiers":[
        {
            "category":"Shopping",
            "subcategory":"Discount & Variety Stores",
            "type":"Retail Goods"
        }
    ],
    "sg:phone":"+1 919 471 5350",
    "sg:postcode":"27712",
    "sg:province":"NC",
    "sg:tags":[
        "merchandise",
        "general"
    ],
    "wof:name":"L & M Websites Inc",
    "wof:placetype":"venue"
},
  "geometry": {"coordinates":[-78.86884000000001,36.103673],"type":"Point"}
}