{
  "type": "Feature",
  "properties": {
    "iso:country":"US",
    "sg:address":"507 N Main St",
    "sg:city":"Staley",
    "sg:classifiers":[
        {
            "category":"Freight",
            "type":"Transportation"
        }
    ],
    "sg:phone":"+1 336 622 7128",
    "sg:postcode":"27355",
    "sg:province":"NC",
    "sg:tags":[
        "operator",
        "trucking"
    ],
    "wof:name":"T & J Transport Inc",
    "wof:placetype":"venue"
},
  "geometry": {"coordinates":[-79.56284599999999,35.803803],"type":"Point"}
}