{
  "type": "Feature",
  "properties": {
    "iso:country":"US",
    "sg:address":"8912 Leinster Dr",
    "sg:city":"Charlotte",
    "sg:classifiers":[
        {
            "category":"Professional",
            "subcategory":"Business Services",
            "type":"Services"
        }
    ],
    "sg:phone":"+1 704 759 3899",
    "sg:postcode":"28277",
    "sg:province":"NC",
    "sg:tags":[
        "interior",
        "consultant",
        "design",
        "decorator"
    ],
    "wof:name":"Drake Interior Design",
    "wof:placetype":"venue"
},
  "geometry": {"coordinates":[-80.820137,35.049214],"type":"Point"}
}