{
  "type": "Feature",
  "properties": {
    "iso:country":"US",
    "sg:address":"2736 S Browntown Rd",
    "sg:city":"Rocky Mount",
    "sg:classifiers":[
        {
            "category":"Restaurant",
            "type":"Food & Drink"
        }
    ],
    "sg:phone":"+1 252 937 4176",
    "sg:postcode":"27804",
    "sg:province":"NC",
    "sg:tags":[
        "caterer"
    ],
    "wof:name":"Khayruh Enterprises",
    "wof:placetype":"venue"
},
  "geometry": {"coordinates":[-77.835511,36.000117],"type":"Point"}
}