{
  "type": "Feature",
  "properties": {
    "addr:full":"609 Woodcrest Dr Gastonia NC 28052",
    "addr:housenumber":"609",
    "addr:postcode":"28052",
    "addr:street":"Woodcrest Dr",
    "iso:country":"US",
    "sg:address":"609 Woodcrest Dr",
    "sg:city":"Gastonia",
    "sg:classifiers":[
        {
            "category":"Building & Trades",
            "subcategory":"Landscaping Services",
            "type":"Services"
        },
        {
            "category":"Home & Garden",
            "subcategory":"Garden Supply",
            "type":"Retail Goods"
        }
    ],
    "sg:phone":"+1 704 865 2004",
    "sg:postcode":"28052",
    "sg:province":"NC",
    "sg:tags":[
        "consultant",
        "lawn",
        "designer",
        "landscape"
    ],
    "wof:name":"Baker Landscaping & Nursery",
    "wof:placetype":"venue"
},
  "geometry": {"coordinates":[-81.219708,35.19478],"type":"Point"}
}