{
  "type": "Feature",
  "properties": {
    "addr:full":"921 Falls Church Rd Charlotte NC 28270",
    "addr:housenumber":"921",
    "addr:postcode":"28270",
    "addr:street":"Falls Church Rd",
    "iso:country":"US",
    "sg:address":"921 Falls Church Rd",
    "sg:city":"Charlotte",
    "sg:phone":"+1 704 814 8899",
    "sg:postcode":"28270",
    "sg:province":"NC",
    "sg:website":"http://www.apollovideoclt.com",
    "wof:name":"Apollo Video Productions",
    "wof:placetype":"venue"
},
  "geometry": {"coordinates":[-80.749201,35.140602],"type":"Point"}
}