{
  "type": "Feature",
  "properties": {
    "iso:country":"US",
    "sg:address":"8128 Providence Rd",
    "sg:city":"Charlotte",
    "sg:classifiers":[
        {
            "category":"Food & Beverages",
            "subcategory":"Liquor & Beverages",
            "type":"Retail Goods"
        }
    ],
    "sg:phone":"+1 704 543 9909",
    "sg:postcode":"28277",
    "sg:province":"NC",
    "sg:tags":[
        "wine"
    ],
    "wof:name":"Vintner Wine Market",
    "wof:placetype":"venue"
},
  "geometry": {"coordinates":[-80.777344,35.0954],"type":"Point"}
}