{
  "type": "Feature",
  "properties": {
    "addr:full":"3005 Long Wood Dr Shelby NC 28152",
    "addr:housenumber":"3005",
    "addr:postcode":"28152",
    "addr:street":"Long Wood Dr",
    "iso:country":"US",
    "sg:address":"3005 Long Wood Dr",
    "sg:city":"Shelby",
    "sg:classifiers":[
        {
            "category":"Professional",
            "type":"Services"
        }
    ],
    "sg:phone":"+1 704 481 9819",
    "sg:postcode":"28152",
    "sg:province":"NC",
    "sg:tags":[
        "establishment"
    ],
    "wof:name":"Porter Corp",
    "wof:placetype":"venue"
},
  "geometry": {"coordinates":[-81.588926,35.249714],"type":"Point"}
}