{
  "type": "Feature",
  "properties": {
    "iso:country":"US",
    "sg:address":"4037 Stone Summit Ln",
    "sg:city":"Raleigh",
    "sg:classifiers":[
        {
            "category":"Professional",
            "subcategory":"Management & Consulting",
            "type":"Services"
        }
    ],
    "sg:phone":"+1 919 773 0396",
    "sg:postcode":"27603",
    "sg:province":"NC",
    "sg:tags":[
        "installs",
        "environmental",
        "consultant",
        "design",
        "pollution"
    ],
    "wof:name":"Awt",
    "wof:placetype":"venue"
},
  "geometry": {"coordinates":[-78.656555,35.665895],"type":"Point"}
}