{
  "type": "Feature",
  "properties": {
    "iso:country":"US",
    "sg:address":"546 S Stratford Rd",
    "sg:city":"Winston Salem",
    "sg:classifiers":[
        {
            "category":"Shopping",
            "subcategory":"Florist",
            "type":"Retail Goods"
        }
    ],
    "sg:phone":"+1 336 722 7673",
    "sg:postcode":"27103",
    "sg:province":"NC",
    "wof:name":"George K Walker Florist Inc",
    "wof:placetype":"venue"
},
  "geometry": {"coordinates":[-80.28945400000001,36.087134],"type":"Point"}
}