{
  "type": "Feature",
  "properties": {
    "addr:full":"4220 Highway 49 S Harrisburg NC 28075",
    "addr:housenumber":"4220",
    "addr:postcode":"28075",
    "addr:street":"Highway 49 S",
    "iso:country":"US",
    "sg:address":"4220 Highway 49 S",
    "sg:city":"Harrisburg",
    "sg:classifiers":[
        {
            "category":"Shopping",
            "subcategory":"Department Store",
            "type":"Retail Goods"
        },
        {
            "category":"Shopping",
            "type":"Retail Goods"
        },
        {
            "category":"Shopping",
            "subcategory":"Discount & Variety Stores",
            "type":"Retail Goods"
        }
    ],
    "sg:phone":"+1 704 455 2181",
    "sg:postcode":"28075",
    "sg:province":"NC",
    "sg:tags":[
        "merchandise"
    ],
    "sg:website":"http://www.dollartree.com/",
    "wof:name":"Dollar Tree",
    "wof:placetype":"venue"
},
  "geometry": {"coordinates":[-80.654286,35.321674],"type":"Point"}
}