{
  "type": "Feature",
  "properties": {
    "iso:country":"US",
    "sg:address":"606 E Morris Ave",
    "sg:city":"Benson",
    "sg:classifiers":[
        {
            "category":"Health Services",
            "subcategory":"Nursing And Care Facility",
            "type":"Services"
        }
    ],
    "sg:phone":"+1 919 894 2567",
    "sg:postcode":"27504",
    "sg:province":"NC",
    "sg:tags":[
        "home",
        "rest"
    ],
    "wof:name":"Oasis",
    "wof:placetype":"venue"
},
  "geometry": {"coordinates":[-78.538697,35.380879],"type":"Point"}
}