{
  "type": "Feature",
  "properties": {
    "addr:full":"8 Hasting Cir Greensboro NC 27406",
    "addr:housenumber":"8",
    "addr:postcode":"27406",
    "addr:street":"Hasting Cir",
    "iso:country":"US",
    "sg:address":"8 Hasting Cir",
    "sg:city":"Greensboro",
    "sg:classifiers":[
        {
            "category":"Professional",
            "subcategory":"Engineering",
            "type":"Services"
        }
    ],
    "sg:phone":"+1   ",
    "sg:postcode":"27406",
    "sg:province":"NC",
    "wof:name":"Willard C Grayson Pe",
    "wof:placetype":"venue"
},
  "geometry": {"coordinates":[-79.713238,35.990705],"type":"Point"}
}