{
  "type": "Feature",
  "properties": {
    "addr:full":"157 Webber Ln Dudley NC 28333",
    "addr:housenumber":"157",
    "addr:postcode":"28333",
    "addr:street":"Webber Ln",
    "iso:country":"US",
    "sg:address":"157 Webber Ln",
    "sg:city":"Dudley",
    "sg:classifiers":[
        {
            "category":"Building & Trades",
            "subcategory":"Construction",
            "type":"Services"
        }
    ],
    "sg:phone":"+1 919 731 3808",
    "sg:postcode":"28333",
    "sg:province":"NC",
    "sg:tags":[
        "carpentry",
        "contractor"
    ],
    "wof:name":"Carpentry A 1 Top Quality",
    "wof:placetype":"venue"
},
  "geometry": {"coordinates":[-77.97894700000001,35.311182],"type":"Point"}
}