{
  "type": "Feature",
  "properties": {
    "iso:country":"US",
    "sg:address":"236 Brinkley Rd",
    "sg:city":"Ahoskie",
    "sg:classifiers":[
        {
            "category":"Freight",
            "type":"Transportation"
        }
    ],
    "sg:phone":"+1 252 332 5292",
    "sg:postcode":"27926",
    "sg:province":"NC",
    "sg:tags":[
        "operator",
        "trucking"
    ],
    "wof:name":"Billy S Mulder Jr",
    "wof:placetype":"venue"
},
  "geometry": {"coordinates":[-76.63354200000001,36.544348],"type":"Point"}
}