{
  "type": "Feature",
  "properties": {
    "iso:country":"US",
    "sg:address":"2219 Mecklenburg Ave",
    "sg:city":"Charlotte",
    "sg:classifiers":[
        {
            "category":"Professional",
            "subcategory":"Business Services",
            "type":"Services"
        }
    ],
    "sg:phone":"+1 704 347 2900",
    "sg:postcode":"28205",
    "sg:province":"NC",
    "sg:tags":[
        "event"
    ],
    "sg:website":"www.carolinaweddingsandevents.com",
    "wof:name":"Carolina Weddings & Events",
    "wof:placetype":"venue"
},
  "geometry": {"coordinates":[-80.798604,35.229224],"type":"Point"}
}