{
  "type": "Feature",
  "properties": {
    "addr:full":"363 Graphite Rd Old Fort NC 28762",
    "addr:housenumber":"363",
    "addr:postcode":"28762",
    "addr:street":"Graphite Rd",
    "iso:country":"US",
    "sg:address":"363 Graphite Rd",
    "sg:city":"Old Fort",
    "sg:classifiers":[
        {
            "category":"Social Services",
            "type":"Services"
        }
    ],
    "sg:phone":"+1 828 668 7590",
    "sg:postcode":"28762",
    "sg:province":"NC",
    "wof:name":"Talisman",
    "wof:placetype":"venue"
},
  "geometry": {"coordinates":[-82.251953,35.660397],"type":"Point"}
}