{
  "type": "Feature",
  "properties": {
    "iso:country":"US",
    "sg:address":"376 Shepard Rd",
    "sg:city":"Council",
    "sg:classifiers":[
        {
            "category":"Farming",
            "subcategory":"Livestock Farm",
            "type":"Manufacturing & Wholesale Goods"
        }
    ],
    "sg:phone":"+1 910 645 6072",
    "sg:postcode":"28434",
    "sg:province":"NC",
    "sg:tags":[
        "producer"
    ],
    "wof:name":"Murphy-Brown",
    "wof:placetype":"venue"
},
  "geometry": {"coordinates":[-78.546988,34.490643],"type":"Point"}
}