{
  "type": "Feature",
  "properties": {
    "addr:full":"5715 Rowan Way Charlotte NC 28214",
    "addr:housenumber":"5715",
    "addr:postcode":"28214",
    "addr:street":"Rowan Way",
    "iso:country":"US",
    "sg:address":"5715 Rowan Way",
    "sg:city":"Charlotte",
    "sg:classifiers":[
        {
            "category":"Utilities",
            "subcategory":"Refuse",
            "type":"Services"
        }
    ],
    "sg:phone":"+1 704 394 1042",
    "sg:postcode":"28214",
    "sg:province":"NC",
    "sg:tags":[
        "truck",
        "dump"
    ],
    "wof:name":"Owen Hauling Inc",
    "wof:placetype":"venue"
},
  "geometry": {"coordinates":[-80.92965700000001,35.260579],"type":"Point"}
}