{
  "type": "Feature",
  "properties": {
    "iso:country":"US",
    "sg:address":"270 Industrial Park Dr",
    "sg:city":"Smithfield",
    "sg:classifiers":[
        {
            "category":"Shopping",
            "subcategory":"Books",
            "type":"Retail Goods"
        }
    ],
    "sg:phone":"+1 919 934 6250",
    "sg:postcode":"27577",
    "sg:province":"NC",
    "wof:name":"Book Warehouse",
    "wof:placetype":"venue"
},
  "geometry": {"coordinates":[-78.322855,35.50561],"type":"Point"}
}