{
  "type": "Feature",
  "properties": {
    "addr:full":"6103 Honeysuckle Ln Charlotte NC 28212",
    "addr:housenumber":"6103",
    "addr:postcode":"28212",
    "addr:street":"Honeysuckle Ln",
    "iso:country":"US",
    "sg:address":"6103 Honeysuckle Ln",
    "sg:city":"Charlotte",
    "sg:classifiers":[
        {
            "category":"Real Estate",
            "subcategory":"Real Estate Agent",
            "type":"Services"
        }
    ],
    "sg:phone":"+1 704 573 2589",
    "sg:postcode":"28212",
    "sg:province":"NC",
    "wof:name":"All-Metro Realty",
    "wof:placetype":"venue"
},
  "geometry": {"coordinates":[-80.73744000000001,35.20713],"type":"Point"}
}