{
  "type": "Feature",
  "properties": {
    "addr:full":"204 Eastchester Dr High Point NC 27262",
    "addr:housenumber":"204",
    "addr:postcode":"27262",
    "addr:street":"Eastchester Dr",
    "iso:country":"US",
    "sg:address":"204 Eastchester Dr",
    "sg:city":"High Point",
    "sg:classifiers":[
        {
            "category":"Personal",
            "subcategory":"Beauty Salon",
            "type":"Services"
        }
    ],
    "sg:phone":"+1   ",
    "sg:postcode":"27262",
    "sg:province":"NC",
    "sg:tags":[
        "shop"
    ],
    "wof:name":"Shelton Lori G Hairstylist",
    "wof:placetype":"venue"
},
  "geometry": {"coordinates":[-80.017949,35.983159],"type":"Point"}
}