{
  "type": "Feature",
  "properties": {
    "addr:full":"200 E Main St Durham NC 27701",
    "addr:housenumber":"200",
    "addr:postcode":"27701",
    "addr:street":"E Main St",
    "iso:country":"US",
    "sg:address":"200 E Main St",
    "sg:city":"Durham",
    "sg:classifiers":[
        {
            "category":"Government",
            "subcategory":"Office",
            "type":"Public Place"
        }
    ],
    "sg:phone":"+1 919 560 0035",
    "sg:postcode":"27701",
    "sg:province":"NC",
    "sg:tags":[
        "county",
        "taxation"
    ],
    "sg:website":"www.co.durham.nc.us",
    "wof:name":"Durham County Finance Dept",
    "wof:placetype":"venue"
},
  "geometry": {"coordinates":[-78.898399,35.993745],"type":"Point"}
}