{
  "type": "Feature",
  "properties": {
    "iso:country":"US",
    "sg:address":"2081 Oklahoma Ct",
    "sg:city":"Lincolnton",
    "sg:classifiers":[
        {
            "category":"Building & Trades",
            "subcategory":"Construction",
            "type":"Services"
        }
    ],
    "sg:phone":"+1 704 736 0872",
    "sg:postcode":"28092",
    "sg:province":"NC",
    "sg:tags":[
        "nonresidential"
    ],
    "wof:name":"Roger Dale Gold",
    "wof:placetype":"venue"
},
  "geometry": {"coordinates":[-81.30089099999999,35.503621],"type":"Point"}
}