{
  "type": "Feature",
  "properties": {
    "iso:country":"US",
    "sg:address":"14 Oak Branch Dr",
    "sg:city":"Greensboro",
    "sg:classifiers":[
        {
            "category":"Professional",
            "subcategory":"Employment Agencies",
            "type":"Services"
        }
    ],
    "sg:phone":"+1 336 855 4945",
    "sg:postcode":"27407",
    "sg:province":"NC",
    "sg:tags":[
        "opportunity"
    ],
    "sg:website":"www.ablest.com",
    "wof:name":"Ablest Staffing Svc",
    "wof:placetype":"venue"
},
  "geometry": {"coordinates":[-79.861135,36.059549],"type":"Point"}
}