{
  "type": "Feature",
  "properties": {
    "addr:full":"1109 Goldsboro St S Wilson NC 27893",
    "addr:housenumber":"1109",
    "addr:postcode":"27893",
    "addr:street":"Goldsboro St S",
    "iso:country":"US",
    "sg:address":"1109 Goldsboro St S",
    "sg:city":"Wilson",
    "sg:classifiers":[
        {
            "category":"Wholesale",
            "subcategory":"Jewelry",
            "type":"Manufacturing & Wholesale Goods"
        }
    ],
    "sg:phone":"+1 252 237 3297",
    "sg:postcode":"27893",
    "sg:province":"NC",
    "sg:tags":[
        "ribbon"
    ],
    "wof:name":"Don's Wholesale",
    "wof:placetype":"venue"
},
  "geometry": {"coordinates":[-77.924132,35.715148],"type":"Point"}
}