{
  "type": "Feature",
  "properties": {
    "addr:full":"1824 Kathryn Ln Greenville NC 27834",
    "addr:housenumber":"1824",
    "addr:postcode":"27834",
    "addr:street":"Kathryn Ln",
    "iso:country":"US",
    "sg:address":"1824 Kathryn Ln",
    "sg:city":"Greenville",
    "sg:classifiers":[
        {
            "category":"Health Services",
            "subcategory":"Nursing And Care Facility",
            "type":"Services"
        }
    ],
    "sg:phone":"+1 252 695 0180",
    "sg:postcode":"27834",
    "sg:province":"NC",
    "sg:tags":[
        "home",
        "institution"
    ],
    "wof:name":"Hamilton Group Home",
    "wof:placetype":"venue"
},
  "geometry": {"coordinates":[-77.492423,35.600268],"type":"Point"}
}