{
  "type": "Feature",
  "properties": {
    "addr:full":"4717 Worchester Pl Raleigh NC 27604",
    "addr:housenumber":"4717",
    "addr:postcode":"27604",
    "addr:street":"Worchester Pl",
    "iso:country":"US",
    "sg:address":"4717 Worchester Pl",
    "sg:city":"Raleigh",
    "sg:classifiers":[
        {
            "category":"Professional",
            "subcategory":"Business Services",
            "type":"Services"
        }
    ],
    "sg:phone":"+1 919 523 6467",
    "sg:postcode":"27604",
    "sg:province":"NC",
    "sg:tags":[
        "interior",
        "consultant",
        "design",
        "decorator"
    ],
    "wof:name":"Kid's Rooms Inc",
    "wof:placetype":"venue"
},
  "geometry": {"coordinates":[-78.55718899999999,35.808554],"type":"Point"}
}