{
  "type": "Feature",
  "properties": {
    "addr:full":"400 E Cornwallis Dr Greensboro NC 27408",
    "addr:housenumber":"400",
    "addr:postcode":"27408",
    "addr:street":"E Cornwallis Dr",
    "iso:country":"US",
    "sg:address":"400 E Cornwallis Dr",
    "sg:city":"Greensboro",
    "sg:classifiers":[
        {
            "category":"Restaurant",
            "type":"Food & Drink"
        }
    ],
    "sg:phone":"+1 336 378 1000",
    "sg:postcode":"27408",
    "sg:province":"NC",
    "sg:tags":[
        "eating"
    ],
    "wof:name":"Ghassans Restaurant",
    "wof:placetype":"venue"
},
  "geometry": {"coordinates":[-79.781149,36.102064],"type":"Point"}
}