{
  "type": "Feature",
  "properties": {
    "iso:country":"US",
    "sg:address":"507 Kornegay St",
    "sg:city":"Dover",
    "sg:classifiers":[
        {
            "category":"Building & Trades",
            "subcategory":"Construction",
            "type":"Services"
        }
    ],
    "sg:phone":"+1 252 527 2998",
    "sg:postcode":"28526",
    "sg:province":"NC",
    "sg:tags":[
        "water",
        "line",
        "sewer",
        "contractor"
    ],
    "wof:name":"Arnette Pipe Laying Co Inc",
    "wof:placetype":"venue"
},
  "geometry": {"coordinates":[-77.425641,35.213431],"type":"Point"}
}