{
  "type": "Feature",
  "properties": {
    "iso:country":"US",
    "sg:address":"3832 Elijah Baum Rd",
    "sg:city":"Kitty Hawk",
    "sg:classifiers":[
        {
            "category":"Building & Trades",
            "subcategory":"Construction",
            "type":"Services"
        }
    ],
    "sg:phone":"+1 252 449 2843",
    "sg:postcode":"27949",
    "sg:province":"NC",
    "sg:tags":[
        "residential",
        "designer"
    ],
    "wof:name":"Coastal Cottages",
    "wof:placetype":"venue"
},
  "geometry": {"coordinates":[-75.702764,36.059174],"type":"Point"}
}