{
  "type": "Feature",
  "properties": {
    "iso:country":"US",
    "sg:address":"1700 Campbell Rd",
    "sg:city":"Woodleaf",
    "sg:classifiers":[
        {
            "category":"Wholesale",
            "subcategory":"Groceries",
            "type":"Manufacturing & Wholesale Goods"
        }
    ],
    "sg:phone":"+1 704 278 0408",
    "sg:postcode":"27054",
    "sg:province":"NC",
    "sg:tags":[
        "food",
        "product"
    ],
    "wof:name":"Velazquez Inc",
    "wof:placetype":"venue"
},
  "geometry": {"coordinates":[-80.549295,35.766722],"type":"Point"}
}