{
  "type": "Feature",
  "properties": {
    "addr:full":"3040 Ormond Dr Winston Salem NC 27106",
    "addr:housenumber":"3040",
    "addr:postcode":"27106",
    "addr:street":"Ormond Dr",
    "iso:country":"US",
    "sg:address":"3040 Ormond Dr",
    "sg:city":"Winston Salem",
    "sg:classifiers":[
        {
            "category":"Arena",
            "subcategory":"Sports Club",
            "type":"Entertainment"
        }
    ],
    "sg:phone":"+1 336 768 9400",
    "sg:postcode":"27106",
    "sg:province":"NC",
    "sg:tags":[
        "course",
        "golf",
        "dev"
    ],
    "wof:name":"Elite Sport Management Group",
    "wof:placetype":"venue"
},
  "geometry": {"coordinates":[-80.29540799999999,36.129069],"type":"Point"}
}