{
  "type": "Feature",
  "properties": {
    "iso:country":"US",
    "sg:address":"1389 Ray Loop Rd",
    "sg:city":"Westfield",
    "sg:phone":"+1 336 593 8630",
    "sg:postcode":"27053",
    "sg:province":"NC",
    "sg:tags":[
        "farm",
        "tobacco"
    ],
    "wof:name":"Donnies Farm",
    "wof:placetype":"venue"
},
  "geometry": {"coordinates":[-80.30524699999999,36.498765],"type":"Point"}
}