{
  "type": "Feature",
  "properties": {
    "iso:country":"US",
    "sg:address":"1824 Toddville Rd",
    "sg:city":"Charlotte",
    "sg:classifiers":[
        {
            "category":"Organizations",
            "subcategory":"Religious Organization",
            "type":"Services"
        }
    ],
    "sg:phone":"+1   ",
    "sg:postcode":"28214",
    "sg:province":"NC",
    "wof:name":"Laotian Culture Center",
    "wof:placetype":"venue"
},
  "geometry": {"coordinates":[-80.92581,35.259918],"type":"Point"}
}