{
  "type": "Feature",
  "properties": {
    "addr:full":"102 Dundee St Windsor NC 27983",
    "addr:housenumber":"102",
    "addr:postcode":"27983",
    "addr:street":"Dundee St",
    "iso:country":"US",
    "sg:address":"102 Dundee St",
    "sg:city":"Windsor",
    "sg:classifiers":[
        {
            "category":"Government",
            "subcategory":"Police Station",
            "type":"Public Place"
        }
    ],
    "sg:phone":"+1 252 794 5445",
    "sg:postcode":"27983",
    "sg:province":"NC",
    "sg:tags":[
        "protection"
    ],
    "wof:name":"Community Service Work Program",
    "wof:placetype":"venue"
},
  "geometry": {"coordinates":[-76.945572,35.997309],"type":"Point"}
}