{
  "type": "Feature",
  "properties": {
    "addr:full":"857 Salem Church Rd Lincolnton NC 28092",
    "addr:housenumber":"857",
    "addr:postcode":"28092",
    "addr:street":"Salem Church Rd",
    "iso:country":"US",
    "sg:address":"857 Salem Church Rd",
    "sg:city":"Lincolnton",
    "sg:classifiers":[
        {
            "category":"Personal",
            "type":"Services"
        }
    ],
    "sg:phone":"+1   ",
    "sg:postcode":"28092",
    "sg:province":"NC",
    "sg:tags":[
        "repair",
        "computer",
        "sales"
    ],
    "wof:name":"Southpaw Technology",
    "wof:placetype":"venue"
},
  "geometry": {"coordinates":[-81.207106,35.460751],"type":"Point"}
}