{
  "type": "Feature",
  "properties": {
    "iso:country":"US",
    "sg:address":"28 Briarwood Rd",
    "sg:city":"Asheville",
    "sg:classifiers":[
        {
            "category":"Wholesale",
            "subcategory":"Non-durable Goods",
            "type":"Manufacturing & Wholesale Goods"
        }
    ],
    "sg:phone":"+1 828 645 8484",
    "sg:postcode":"28804",
    "sg:province":"NC",
    "sg:tags":[
        "fund",
        "raising",
        "merchandise"
    ],
    "wof:name":"Mountain Marketing Inc",
    "wof:placetype":"venue"
},
  "geometry": {"coordinates":[-82.58477600000001,35.676575],"type":"Point"}
}