{
  "type": "Feature",
  "properties": {
    "iso:country":"US",
    "sg:address":"510 Walnut St",
    "sg:city":"Cary",
    "sg:classifiers":[
        {
            "category":"Building & Trades",
            "subcategory":"Cleaning & Sanitation",
            "type":"Services"
        }
    ],
    "sg:phone":"+1   ",
    "sg:postcode":"27511",
    "sg:province":"NC",
    "sg:tags":[
        "maintenance"
    ],
    "wof:name":"F Cary Procare",
    "wof:placetype":"venue"
},
  "geometry": {"coordinates":[-78.76893099999999,35.775945],"type":"Point"}
}