{
  "type": "Feature",
  "properties": {
    "iso:country":"US",
    "sg:address":"1556 Mount Carmel Church Rd",
    "sg:city":"Pikeville",
    "sg:classifiers":[
        {
            "category":"Building & Trades",
            "subcategory":"Construction",
            "type":"Services"
        }
    ],
    "sg:phone":"+1 919 736 3949",
    "sg:postcode":"27863",
    "sg:province":"NC",
    "sg:tags":[
        "carpentry",
        "contractor"
    ],
    "wof:name":"Lucas Construction",
    "wof:placetype":"venue"
},
  "geometry": {"coordinates":[-77.95223900000001,35.457988],"type":"Point"}
}