{
  "type": "Feature",
  "properties": {
    "iso:country":"US",
    "sg:address":"1235 W Acres Ln",
    "sg:city":"Greenville",
    "sg:classifiers":[
        {
            "category":"Shopping",
            "subcategory":"Shoes",
            "type":"Retail Goods"
        }
    ],
    "sg:phone":"+1 252 355 0869",
    "sg:postcode":"27834",
    "sg:province":"NC",
    "wof:name":"Shoe Outlet",
    "wof:placetype":"venue"
},
  "geometry": {"coordinates":[-77.456396,35.556902],"type":"Point"}
}