{
  "type": "Feature",
  "properties": {
    "addr:full":"4124 Cobblestone Pl Durham NC 27707",
    "addr:housenumber":"4124",
    "addr:postcode":"27707",
    "addr:street":"Cobblestone Pl",
    "iso:country":"US",
    "sg:address":"4124 Cobblestone Pl",
    "sg:city":"Durham",
    "sg:classifiers":[
        {
            "category":"Shopping",
            "subcategory":"Clothing, Apparel, & Fashions",
            "type":"Retail Goods"
        }
    ],
    "sg:phone":"+1 919 493 0301",
    "sg:postcode":"27707",
    "sg:province":"NC",
    "sg:tags":[
        "alteration"
    ],
    "wof:name":"Tina's Custom Monogramming",
    "wof:placetype":"venue"
},
  "geometry": {"coordinates":[-78.96553,35.929347],"type":"Point"}
}