{
  "type": "Feature",
  "properties": {
    "addr:full":"4333 Perkins Rd Charlotte NC 28269",
    "addr:housenumber":"4333",
    "addr:postcode":"28269",
    "addr:street":"Perkins Rd",
    "iso:country":"US",
    "sg:address":"4333 Perkins Rd",
    "sg:city":"Charlotte",
    "sg:classifiers":[
        {
            "category":"Organizations",
            "subcategory":"Religious Organization",
            "type":"Services"
        }
    ],
    "sg:phone":"+1 704 599 1630",
    "sg:postcode":"28269",
    "sg:province":"NC",
    "sg:tags":[
        "church"
    ],
    "wof:name":"New Creation Missionary Baptis",
    "wof:placetype":"venue"
},
  "geometry": {"coordinates":[-80.824088,35.301207],"type":"Point"}
}