{
  "type": "Feature",
  "properties": {
    "addr:full":"1500 Lamont Ct Chapel Hill NC 27517",
    "addr:housenumber":"1500",
    "addr:postcode":"27517",
    "addr:street":"Lamont Ct",
    "iso:country":"US",
    "sg:address":"1500 Lamont Ct",
    "sg:city":"Chapel Hill",
    "sg:classifiers":[
        {
            "category":"Professional",
            "subcategory":"Management & Consulting",
            "type":"Services"
        }
    ],
    "sg:phone":"+1 919 967 7171",
    "sg:postcode":"27517",
    "sg:province":"NC",
    "sg:tags":[
        "roofing",
        "consultant"
    ],
    "wof:name":"Cold Process Roofing Co",
    "wof:placetype":"venue"
},
  "geometry": {"coordinates":[-79.013516,35.931455],"type":"Point"}
}