{
  "type": "Feature",
  "properties": {
    "iso:country":"US",
    "sg:address":"14900 Rothwell Dr",
    "sg:city":"Charlotte",
    "sg:classifiers":[
        {
            "category":"Professional",
            "type":"Services"
        }
    ],
    "sg:phone":"+1 704 573 3094",
    "sg:postcode":"28227",
    "sg:province":"NC",
    "sg:tags":[
        "establishment"
    ],
    "wof:name":"PUR Rfect Palace",
    "wof:placetype":"venue"
},
  "geometry": {"coordinates":[-80.65635399999999,35.143187],"type":"Point"}
}