{
  "type": "Feature",
  "properties": {
    "iso:country":"US",
    "sg:address":"3221 Wellington Ct",
    "sg:city":"Raleigh",
    "sg:classifiers":[
        {
            "category":"Building & Trades",
            "subcategory":"Construction",
            "type":"Services"
        },
        {
            "category":"Professional",
            "subcategory":"Management & Consulting",
            "type":"Services"
        }
    ],
    "sg:phone":"+1 919 845 1025",
    "sg:postcode":"27615",
    "sg:province":"NC",
    "sg:tags":[
        "steel",
        "consultant",
        "industry",
        "manufacture"
    ],
    "sg:website":"www.steelnetwork.com",
    "wof:name":"Steel Network Inc",
    "wof:placetype":"venue"
},
  "geometry": {"coordinates":[-78.581503,35.88712],"type":"Point"}
}