{
  "type": "Feature",
  "properties": {
    "addr:full":"5741 Spence Farm Rd Holly Springs NC 27540",
    "addr:housenumber":"5741",
    "addr:postcode":"27540",
    "addr:street":"Spence Farm Rd",
    "iso:country":"US",
    "sg:address":"5741 Spence Farm Rd",
    "sg:city":"Holly Springs",
    "sg:classifiers":[
        {
            "category":"Building & Trades",
            "subcategory":"Construction",
            "type":"Services"
        }
    ],
    "sg:phone":"+1 919 669 8773",
    "sg:postcode":"27540",
    "sg:province":"NC",
    "sg:tags":[
        "house"
    ],
    "wof:name":"Scott C Wood Builders",
    "wof:placetype":"venue"
},
  "geometry": {"coordinates":[-78.829252,35.607377],"type":"Point"}
}