{
  "type": "Feature",
  "properties": {
    "iso:country":"US",
    "sg:address":"4321 Jenkins Rd",
    "sg:city":"Marshville",
    "sg:classifiers":[
        {
            "category":"Building & Trades",
            "subcategory":"Construction",
            "type":"Services"
        }
    ],
    "sg:phone":"+1 704 624 2861",
    "sg:postcode":"28103",
    "sg:province":"NC",
    "sg:tags":[
        "house"
    ],
    "wof:name":"Jenkin Jenkins Cnstr Comp",
    "wof:placetype":"venue"
},
  "geometry": {"coordinates":[-80.35704200000001,34.874886],"type":"Point"}
}