{
  "type": "Feature",
  "properties": {
    "iso:country":"US",
    "sg:address":"156 Worth Money Ln",
    "sg:city":"Elkin",
    "sg:classifiers":[
        {
            "category":"Wholesale",
            "subcategory":"Construction Materials",
            "type":"Manufacturing & Wholesale Goods"
        },
        {
            "category":"Building & Trades",
            "subcategory":"Construction",
            "type":"Services"
        }
    ],
    "sg:phone":"+1 336 835 9999",
    "sg:postcode":"28621",
    "sg:province":"NC",
    "sg:tags":[
        "contractor",
        "fence",
        "supply"
    ],
    "wof:name":"67 Yard & Garden Center",
    "wof:placetype":"venue"
},
  "geometry": {"coordinates":[-80.794742,36.260314],"type":"Point"}
}