{
  "type": "Feature",
  "properties": {
    "addr:full":"201 Cricket Hollow Run Clayton NC 27520",
    "addr:housenumber":"201",
    "addr:postcode":"27520",
    "addr:street":"Cricket Hollow Run",
    "iso:country":"US",
    "sg:address":"201 Cricket Hollow Run",
    "sg:city":"Clayton",
    "sg:classifiers":[
        {
            "category":"Professional",
            "type":"Services"
        }
    ],
    "sg:phone":"+1 919 553 5555",
    "sg:postcode":"27520",
    "sg:province":"NC",
    "sg:tags":[
        "establishment"
    ],
    "wof:name":"Bagley & Assoc",
    "wof:placetype":"venue"
},
  "geometry": {"coordinates":[-78.47414999999999,35.644128],"type":"Point"}
}