{
  "type": "Feature",
  "properties": {
    "iso:country":"US",
    "sg:address":"16600 State Hwy 73",
    "sg:city":"Huntersville",
    "sg:classifiers":[
        {
            "category":"Food & Beverages",
            "subcategory":"Groceries & Convenience Stores",
            "type":"Retail Goods"
        },
        {
            "category":"Autos & Motor Vehicles",
            "subcategory":"Fuel & Gas Station",
            "type":"Retail Goods"
        }
    ],
    "sg:phone":"+1 704 892 7998",
    "sg:postcode":"28078",
    "sg:province":"NC",
    "sg:tags":[
        "oil"
    ],
    "wof:name":"Cashions Quik Stop 5",
    "wof:placetype":"venue"
},
  "geometry": {"coordinates":[-80.89442699999999,35.444616],"type":"Point"}
}