{
  "type": "Feature",
  "properties": {
    "addr:full":"5201 Bentgrass Dr Raleigh NC 27610",
    "addr:housenumber":"5201",
    "addr:postcode":"27610",
    "addr:street":"Bentgrass Dr",
    "iso:country":"US",
    "sg:address":"5201 Bentgrass Dr",
    "sg:city":"Raleigh",
    "sg:classifiers":[
        {
            "category":"Communications",
            "subcategory":"Film & Video Production",
            "type":"Services"
        }
    ],
    "sg:phone":"+1   ",
    "sg:postcode":"27610",
    "sg:province":"NC",
    "sg:tags":[
        "motion"
    ],
    "wof:name":"Willis Production",
    "wof:placetype":"venue"
},
  "geometry": {"coordinates":[-78.544321,35.781674],"type":"Point"}
}