{
  "type": "Feature",
  "properties": {
    "iso:country":"US",
    "sg:address":"6604 Six Forks Rd",
    "sg:city":"Raleigh",
    "sg:classifiers":[
        {
            "category":"Professional",
            "type":"Services"
        }
    ],
    "sg:phone":"+1 919 870 9148",
    "sg:postcode":"27615",
    "sg:province":"NC",
    "sg:tags":[
        "establishment"
    ],
    "wof:name":"Alvarez Enterprises",
    "wof:placetype":"venue"
},
  "geometry": {"coordinates":[-78.64151699999999,35.871409],"type":"Point"}
}