{
  "type": "Feature",
  "properties": {
    "addr:full":"611 N Smithwick St Williamston NC 27892",
    "addr:housenumber":"611",
    "addr:postcode":"27892",
    "addr:street":"N Smithwick St",
    "iso:country":"US",
    "sg:address":"611 N Smithwick St",
    "sg:city":"Williamston",
    "sg:phone":"+1 252 792 2691",
    "sg:postcode":"27892",
    "sg:province":"NC",
    "sg:tags":[
        "farm",
        "corn",
        "soybean"
    ],
    "wof:name":"Whitley John",
    "wof:placetype":"venue"
},
  "geometry": {"coordinates":[-77.05966600000001,35.860552],"type":"Point"}
}