{
  "type": "Feature",
  "properties": {
    "addr:full":"132 Collins Mountain Rd Chapel Hill NC 27516",
    "addr:housenumber":"132",
    "addr:postcode":"27516",
    "addr:street":"Collins Mountain Rd",
    "iso:country":"US",
    "sg:address":"132 Collins Mountain Rd",
    "sg:city":"Chapel Hill",
    "sg:classifiers":[
        {
            "category":"Home & Garden",
            "subcategory":"Home Furnishings",
            "type":"Retail Goods"
        }
    ],
    "sg:phone":"+1 919 929 3324",
    "sg:postcode":"27516",
    "sg:province":"NC",
    "wof:name":"Janet Resnik Pottery",
    "wof:placetype":"venue"
},
  "geometry": {"coordinates":[-79.22797199999999,35.855044],"type":"Point"}
}