{
  "type": "Feature",
  "properties": {
    "iso:country":"US",
    "sg:address":"5202 Carolina Beach Rd",
    "sg:city":"Wilmington",
    "sg:classifiers":[
        {
            "category":"Banks & Credit Unions",
            "subcategory":"Bank",
            "type":"Services"
        }
    ],
    "sg:phone":"+1 910 794 2349",
    "sg:postcode":"28412",
    "sg:province":"NC",
    "sg:tags":[
        "mortgage",
        "loan",
        "broker",
        "real estate"
    ],
    "wof:name":"Affordable Mortgage Company",
    "wof:placetype":"venue"
},
  "geometry": {"coordinates":[-77.897015,34.143417],"type":"Point"}
}