{
  "type": "Feature",
  "properties": {
    "addr:full":"101 Country Club Dr Henderson NC 27536",
    "addr:housenumber":"101",
    "addr:postcode":"27536",
    "addr:street":"Country Club Dr",
    "iso:country":"US",
    "sg:address":"101 Country Club Dr",
    "sg:city":"Henderson",
    "sg:classifiers":[
        {
            "category":"Wholesale",
            "subcategory":"Machinery & Supplies",
            "type":"Manufacturing & Wholesale Goods"
        }
    ],
    "sg:phone":"+1 252 438 5080",
    "sg:postcode":"27536",
    "sg:province":"NC",
    "sg:tags":[
        "janitor"
    ],
    "wof:name":"Chemical Sales Co",
    "wof:placetype":"venue"
},
  "geometry": {"coordinates":[-78.433374,36.313478],"type":"Point"}
}