{
  "type": "Feature",
  "properties": {
    "addr:full":"223 S Kerr Ave Wilmington NC 28403",
    "addr:housenumber":"223",
    "addr:postcode":"28403",
    "addr:street":"S Kerr Ave",
    "iso:country":"US",
    "sg:address":"223 S Kerr Ave",
    "sg:city":"Wilmington",
    "sg:classifiers":[
        {
            "category":"Retail",
            "subcategory":"Auto Repair",
            "type":"Services"
        }
    ],
    "sg:phone":"+1 910 791 7050",
    "sg:postcode":"28403",
    "sg:province":"NC",
    "sg:tags":[
        "repairing",
        "automobile"
    ],
    "wof:name":"Complete Car Care",
    "wof:placetype":"venue"
},
  "geometry": {"coordinates":[-77.88842699999999,34.235836],"type":"Point"}
}