{
  "type": "Feature",
  "properties": {
    "iso:country":"US",
    "sg:address":"2450 Crestwood Dr",
    "sg:city":"Conover",
    "sg:classifiers":[
        {
            "category":"Restaurant",
            "type":"Food & Drink"
        }
    ],
    "sg:phone":"+1 828 464 2055",
    "sg:postcode":"28613",
    "sg:province":"NC",
    "sg:tags":[
        "eating"
    ],
    "wof:name":"Pineola Cafe Inc",
    "wof:placetype":"venue"
},
  "geometry": {"coordinates":[-81.175329,35.695068],"type":"Point"}
}