{
  "type": "Feature",
  "properties": {
    "addr:full":"410 Blackwell St Durham NC 27701",
    "addr:housenumber":"410",
    "addr:postcode":"27701",
    "addr:street":"Blackwell St",
    "iso:country":"US",
    "sg:address":"410 Blackwell St",
    "sg:city":"Durham",
    "sg:classifiers":[
        {
            "category":"Professional",
            "subcategory":"Computer Services",
            "type":"Services"
        }
    ],
    "sg:phone":"+1 919 858 8158",
    "sg:postcode":"27701",
    "sg:province":"NC",
    "sg:tags":[
        "consultant",
        "designer"
    ],
    "sg:website":"www.compuware.com",
    "wof:name":"Compuware Corp",
    "wof:placetype":"venue"
},
  "geometry": {"coordinates":[-78.90556599999999,35.991521],"type":"Point"}
}