{
  "type": "Feature",
  "properties": {
    "iso:country":"US",
    "sg:address":"106 E Queen St",
    "sg:city":"Edenton",
    "sg:classifiers":[
        {
            "category":"Professional",
            "subcategory":"Lawyer & Legal Services",
            "type":"Services"
        }
    ],
    "sg:phone":"+1 252 482 2175",
    "sg:postcode":"27932",
    "sg:province":"NC",
    "sg:tags":[
        "attorney"
    ],
    "wof:name":"W T Culpepper III Law Firm",
    "wof:placetype":"venue"
},
  "geometry": {"coordinates":[-76.608509,36.059812],"type":"Point"}
}