{
  "type": "Feature",
  "properties": {
    "addr:full":"1033 Landsford Rd Marshville NC 28103",
    "addr:housenumber":"1033",
    "addr:postcode":"28103",
    "addr:street":"Landsford Rd",
    "iso:country":"US",
    "sg:address":"1033 Landsford Rd",
    "sg:city":"Marshville",
    "sg:classifiers":[
        {
            "category":"Farming",
            "subcategory":"Farm & Veterinary Services",
            "type":"Manufacturing & Wholesale Goods"
        }
    ],
    "sg:phone":"+1 704 624 5947",
    "sg:postcode":"28103",
    "sg:province":"NC",
    "sg:tags":[
        "livestock"
    ],
    "wof:name":"Jerry W Marsh",
    "wof:placetype":"venue"
},
  "geometry": {"coordinates":[-80.352161,34.967878],"type":"Point"}
}