{
  "type": "Feature",
  "properties": {
    "addr:full":"108 Rowan St Fayetteville NC 28301",
    "addr:housenumber":"108",
    "addr:postcode":"28301",
    "addr:street":"Rowan St",
    "iso:country":"US",
    "sg:address":"108 Rowan St",
    "sg:city":"Fayetteville",
    "sg:classifiers":[
        {
            "category":"Shopping",
            "subcategory":"Pharmacy",
            "type":"Retail Goods"
        }
    ],
    "sg:phone":"+1 910 307 0342",
    "sg:postcode":"28301",
    "sg:province":"NC",
    "wof:name":"Eckerd",
    "wof:placetype":"venue"
},
  "geometry": {"coordinates":[-78.877432,35.05748],"type":"Point"}
}