{
  "type": "Feature",
  "properties": {
    "addr:full":"595 Porterville School Rd Clarkton NC 28433",
    "addr:housenumber":"595",
    "addr:postcode":"28433",
    "addr:street":"Porterville School Rd",
    "iso:country":"US",
    "sg:address":"595 Porterville School Rd",
    "sg:city":"Clarkton",
    "sg:classifiers":[
        {
            "category":"Organizations",
            "subcategory":"Religious Organization",
            "type":"Services"
        }
    ],
    "sg:phone":"+1 910 645 6292",
    "sg:postcode":"28433",
    "sg:province":"NC",
    "sg:tags":[
        "church"
    ],
    "wof:name":"Pierce's Chapel AME Zion Churc",
    "wof:placetype":"venue"
},
  "geometry": {"coordinates":[-78.57624,34.450051],"type":"Point"}
}