{
  "type": "Feature",
  "properties": {
    "addr:full":"4828 Fayetteville Rd Lumberton NC 28358",
    "addr:housenumber":"4828",
    "addr:postcode":"28358",
    "addr:street":"Fayetteville Rd",
    "iso:country":"US",
    "sg:address":"4828 Fayetteville Rd",
    "sg:city":"Lumberton",
    "sg:classifiers":[
        {
            "category":"Real Estate",
            "subcategory":"Real Estate Agent",
            "type":"Services"
        }
    ],
    "sg:phone":"+1 910 738 3731",
    "sg:postcode":"28358",
    "sg:province":"NC",
    "sg:tags":[
        "business"
    ],
    "wof:name":"Heritage Realty",
    "wof:placetype":"venue"
},
  "geometry": {"coordinates":[-79.000032,34.661186],"type":"Point"}
}