{
  "type": "Feature",
  "properties": {
    "iso:country":"US",
    "sg:address":"204 Spyglass Dr",
    "sg:city":"Advance",
    "sg:classifiers":[
        {
            "category":"Autos & Motor Vehicles",
            "subcategory":"Automobile Sales",
            "type":"Retail Goods"
        }
    ],
    "sg:phone":"+1 336 998 6239",
    "sg:postcode":"27006",
    "sg:province":"NC",
    "sg:tags":[
        "aircraft"
    ],
    "wof:name":"Aircraft Equipment Corp",
    "wof:placetype":"venue"
},
  "geometry": {"coordinates":[-80.42450599999999,35.997705],"type":"Point"}
}