{
  "type": "Feature",
  "properties": {
    "iso:country":"US",
    "sg:address":"831 E Morehead St",
    "sg:city":"Charlotte",
    "sg:classifiers":[
        {
            "category":"Professional",
            "subcategory":"Lawyer & Legal Services",
            "type":"Services"
        }
    ],
    "sg:phone":"+1 704 372 6541",
    "sg:postcode":"28202",
    "sg:province":"NC",
    "sg:tags":[
        "attorney"
    ],
    "wof:name":"Jones Hewson & Woolard",
    "wof:placetype":"venue"
},
  "geometry": {"coordinates":[-80.84504099999999,35.214381],"type":"Point"}
}