{
  "type": "Feature",
  "properties": {
    "iso:country":"US",
    "sg:address":"1572 Everett Rd",
    "sg:city":"Robersonville",
    "sg:classifiers":[
        {
            "category":"Organizations",
            "subcategory":"Religious Organization",
            "type":"Services"
        }
    ],
    "sg:phone":"+1 252 795 3818",
    "sg:postcode":"27871",
    "sg:province":"NC",
    "sg:tags":[
        "church"
    ],
    "wof:name":"Lloyd's Chapel Church",
    "wof:placetype":"venue"
},
  "geometry": {"coordinates":[-77.23079,35.81829],"type":"Point"}
}