{
  "type": "Feature",
  "properties": {
    "iso:country":"US",
    "sg:address":"1 Battery Park Ave",
    "sg:city":"Asheville",
    "sg:classifiers":[
        {
            "category":"Shopping",
            "type":"Retail Goods"
        }
    ],
    "sg:phone":"+1 828 254 7959",
    "sg:postcode":"28801",
    "sg:province":"NC",
    "sg:tags":[
        "art",
        "gallery",
        "dealer"
    ],
    "wof:name":"Vadim Bora Studio-Gallery",
    "wof:placetype":"venue"
},
  "geometry": {"coordinates":[-82.55486399999999,35.595242],"type":"Point"}
}