{
  "type": "Feature",
  "properties": {
    "addr:full":"124 W Peeler St Mooresville NC 28146",
    "addr:housenumber":"124",
    "addr:postcode":"28146",
    "addr:street":"W Peeler St",
    "iso:country":"US",
    "sg:address":"124 W Peeler St",
    "sg:city":"Mooresville",
    "sg:classifiers":[
        {
            "category":"Wholesale",
            "subcategory":"Machinery & Supplies",
            "type":"Manufacturing & Wholesale Goods"
        }
    ],
    "sg:phone":"+1 704 799 6850",
    "sg:postcode":"28146",
    "sg:province":"NC",
    "sg:tags":[
        "industrial"
    ],
    "wof:name":"Process Media & Equipment",
    "wof:placetype":"venue"
},
  "geometry": {"coordinates":[-80.448899,35.614316],"type":"Point"}
}