{
  "type": "Feature",
  "properties": {
    "addr:full":"1123 Montreat Rd Black Mountain NC 28711",
    "addr:housenumber":"1123",
    "addr:postcode":"28711",
    "addr:street":"Montreat Rd",
    "iso:country":"US",
    "sg:address":"1123 Montreat Rd",
    "sg:city":"Black Mountain",
    "sg:classifiers":[
        {
            "category":"Travel",
            "subcategory":"Campground",
            "type":"Entertainment"
        }
    ],
    "sg:phone":"+1 828 669 8766",
    "sg:postcode":"28711",
    "sg:province":"NC",
    "sg:tags":[
        "organization",
        "camp",
        "religious"
    ],
    "wof:name":"Camp Timberlake",
    "wof:placetype":"venue"
},
  "geometry": {"coordinates":[-82.316833,35.633061],"type":"Point"}
}