{
  "type": "Feature",
  "properties": {
    "iso:country":"US",
    "sg:address":"1760 Brevard Rd",
    "sg:city":"Arden",
    "sg:classifiers":[
        {
            "category":"Building & Trades",
            "subcategory":"Plumbing",
            "type":"Services"
        }
    ],
    "sg:phone":"+1 828 684 5661",
    "sg:postcode":"28704",
    "sg:province":"NC",
    "sg:tags":[
        "conditioning",
        "air",
        "system",
        "contractor"
    ],
    "wof:name":"Dixon Air Conditioning",
    "wof:placetype":"venue"
},
  "geometry": {"coordinates":[-82.58153900000001,35.479442],"type":"Point"}
}