{
  "type": "Feature",
  "properties": {
    "iso:country":"US",
    "sg:address":"2301 Schieffelin Rd",
    "sg:city":"Apex",
    "sg:classifiers":[
        {
            "category":"Government",
            "subcategory":"Jail",
            "type":"Public Place"
        }
    ],
    "sg:phone":"+1 919 387 1000",
    "sg:postcode":"27502",
    "sg:province":"NC",
    "sg:tags":[
        "correctional",
        "institution"
    ],
    "wof:name":"Correction North Carolina Dept",
    "wof:placetype":"venue"
},
  "geometry": {"coordinates":[-78.838075,35.719093],"type":"Point"}
}