{
  "type": "Feature",
  "properties": {
    "addr:full":"891 Willow Dr Chapel Hill NC 27514",
    "addr:housenumber":"891",
    "addr:postcode":"27514",
    "addr:street":"Willow Dr",
    "iso:country":"US",
    "sg:address":"891 Willow Dr",
    "sg:city":"Chapel Hill",
    "sg:classifiers":[
        {
            "category":"Real Estate",
            "subcategory":"Real Estate Agent",
            "type":"Services"
        }
    ],
    "sg:phone":"+1 919 933 9910",
    "sg:postcode":"27514",
    "sg:province":"NC",
    "wof:name":"Clayton Commercial Realty",
    "wof:placetype":"venue"
},
  "geometry": {"coordinates":[-79.029732,35.928536],"type":"Point"}
}