{
  "type": "Feature",
  "properties": {
    "iso:country":"US",
    "sg:address":"5913 Surrie Trl",
    "sg:city":"Pleasant Garden",
    "sg:classifiers":[
        {
            "category":"Manufacturing",
            "subcategory":"Building Materials",
            "type":"Manufacturing & Wholesale Goods"
        }
    ],
    "sg:phone":"+1 336 685 9862",
    "sg:postcode":"27313",
    "sg:province":"NC",
    "sg:tags":[
        "mfg"
    ],
    "wof:name":"Ilderton Woodworks",
    "wof:placetype":"venue"
},
  "geometry": {"coordinates":[-79.745812,35.886936],"type":"Point"}
}