{
  "type": "Feature",
  "properties": {
    "addr:full":"1000 Revolution Mill Dr Greensboro NC 27405",
    "addr:housenumber":"1000",
    "addr:postcode":"27405",
    "addr:street":"Revolution Mill Dr",
    "iso:country":"US",
    "sg:address":"1000 Revolution Mill Dr",
    "sg:city":"Greensboro",
    "sg:classifiers":[
        {
            "category":"Real Estate",
            "subcategory":"Real Estate Operator",
            "type":"Services"
        }
    ],
    "sg:phone":"+1 336 235 2393",
    "sg:postcode":"27405",
    "sg:province":"NC",
    "sg:tags":[
        "building",
        "parks"
    ],
    "wof:name":"Revolution Mill Studios",
    "wof:placetype":"venue"
},
  "geometry": {"coordinates":[-79.77787600000001,36.099911],"type":"Point"}
}