{
  "type": "Feature",
  "properties": {
    "addr:full":"5311 Sterling Forest Dr Clemmons NC 27012",
    "addr:housenumber":"5311",
    "addr:postcode":"27012",
    "addr:street":"Sterling Forest Dr",
    "iso:country":"US",
    "sg:address":"5311 Sterling Forest Dr",
    "sg:city":"Clemmons",
    "sg:classifiers":[
        {
            "category":"Building & Trades",
            "subcategory":"Construction",
            "type":"Services"
        }
    ],
    "sg:phone":"+1 336 766 3447",
    "sg:postcode":"27012",
    "sg:province":"NC",
    "sg:tags":[
        "house",
        "contractor"
    ],
    "wof:name":"Robbins Construction Co Inc",
    "wof:placetype":"venue"
},
  "geometry": {"coordinates":[-80.357787,35.992122],"type":"Point"}
}