{
  "type": "Feature",
  "properties": {
    "addr:full":"99 Franklin St Roanoke Rapids NC 27870",
    "addr:housenumber":"99",
    "addr:postcode":"27870",
    "addr:street":"Franklin St",
    "iso:country":"US",
    "sg:address":"99 Franklin St",
    "sg:city":"Roanoke Rapids",
    "sg:classifiers":[
        {
            "category":"Building & Trades",
            "subcategory":"Construction",
            "type":"Services"
        }
    ],
    "sg:phone":"+1 252 537 5976",
    "sg:postcode":"27870",
    "sg:province":"NC",
    "sg:tags":[
        "contractor"
    ],
    "wof:name":"Moncure Home Service Inc",
    "wof:placetype":"venue"
},
  "geometry": {"coordinates":[-77.655248,36.473064],"type":"Point"}
}