{
  "type": "Feature",
  "properties": {
    "iso:country":"US",
    "sg:address":"2700 High Point Rd ",
    "sg:city":"Greensboro",
    "sg:classifiers":[
        {
            "category":"Restaurant",
            "type":"Food & Drink"
        }
    ],
    "sg:menulink":"http://www.allmenus.com/nc/greensboro/279658-titos/menu/",
    "sg:phone":"+1 336 299 8486",
    "sg:postcode":"27403",
    "sg:province":"NC",
    "sg:tags":[
        "calzones",
        "american",
        "sandwich",
        "wing",
        "pizza"
    ],
    "wof:name":"Tito's Pizza & Subs",
    "wof:placetype":"venue"
},
  "geometry": {"coordinates":[-79.833558,36.052542],"type":"Point"}
}