{
  "type": "Feature",
  "properties": {
    "iso:country":"US",
    "sg:address":"621 Hania Dr SW",
    "sg:city":"Concord",
    "sg:classifiers":[
        {
            "category":"Professional",
            "subcategory":"Computer Services",
            "type":"Services"
        }
    ],
    "sg:phone":"+1 704 795 1942",
    "sg:postcode":"28027",
    "sg:province":"NC",
    "sg:tags":[
        "repair"
    ],
    "wof:name":"CNT",
    "wof:placetype":"venue"
},
  "geometry": {"coordinates":[-80.636825,35.361184],"type":"Point"}
}