{
  "type": "Feature",
  "properties": {
    "addr:full":"127 1st Ave NE Hickory NC 28601",
    "addr:housenumber":"127",
    "addr:postcode":"28601",
    "addr:street":"1St Ave Ne",
    "iso:country":"US",
    "sg:address":"127 1st Ave NE",
    "sg:city":"Hickory",
    "sg:classifiers":[
        {
            "category":"Professional",
            "type":"Services"
        }
    ],
    "sg:phone":"+1 828 327 4509",
    "sg:postcode":"28601",
    "sg:province":"NC",
    "wof:name":"Cbbh LLC",
    "wof:placetype":"venue"
},
  "geometry": {"coordinates":[-81.33568099999999,35.733349],"type":"Point"}
}