{
  "type": "Feature",
  "properties": {
    "iso:country":"US",
    "sg:address":"1418 Country Club Rd",
    "sg:city":"Wilmington",
    "sg:classifiers":[
        {
            "category":"Restaurant",
            "type":"Food & Drink"
        }
    ],
    "sg:phone":"+1 910 763 5179",
    "sg:postcode":"28403",
    "sg:province":"NC",
    "sg:tags":[
        "eating"
    ],
    "wof:name":"China Main Source LLC",
    "wof:placetype":"venue"
},
  "geometry": {"coordinates":[-77.915415,34.221557],"type":"Point"}
}