{
  "type": "Feature",
  "properties": {
    "iso:country":"US",
    "sg:address":"508 Jenkins Rd",
    "sg:city":"Canton",
    "sg:classifiers":[
        {
            "category":"Professional",
            "type":"Services"
        }
    ],
    "sg:phone":"+1 828 646 0306",
    "sg:postcode":"28716",
    "sg:province":"NC",
    "sg:tags":[
        "establishment"
    ],
    "wof:name":"Tower Place",
    "wof:placetype":"venue"
},
  "geometry": {"coordinates":[-82.80923,35.518438],"type":"Point"}
}