{
  "type": "Feature",
  "properties": {
    "iso:country":"US",
    "sg:address":"9 Mollie Rd",
    "sg:city":"Maple Hill",
    "sg:classifiers":[
        {
            "category":"Professional",
            "type":"Services"
        }
    ],
    "sg:phone":"+1 910 455 4682",
    "sg:postcode":"28472",
    "sg:province":"NC",
    "wof:name":"Blue Mrcle Snitizer Deodorizer",
    "wof:placetype":"venue"
},
  "geometry": {"coordinates":[-78.76264999999999,34.204355],"type":"Point"}
}