{
  "type": "Feature",
  "properties": {
    "addr:full":"1984 Remount Rd Gastonia NC 28054",
    "addr:housenumber":"1984",
    "addr:postcode":"28054",
    "addr:street":"Remount Rd",
    "iso:country":"US",
    "sg:address":"1984 Remount Rd",
    "sg:city":"Gastonia",
    "sg:classifiers":[
        {
            "category":"Retail",
            "subcategory":"Auto Rental",
            "type":"Services"
        }
    ],
    "sg:phone":"+1 704 868 2100",
    "sg:postcode":"28054",
    "sg:province":"NC",
    "sg:tags":[
        "passenger",
        "car"
    ],
    "wof:name":"Alamo Rent-A-Car LLC",
    "wof:placetype":"venue"
},
  "geometry": {"coordinates":[-81.141989,35.268162],"type":"Point"}
}