{
  "type": "Feature",
  "properties": {
    "iso:country":"US",
    "sg:address":"3240 Norman Blalock Rd",
    "sg:city":"Willow Spring",
    "sg:classifiers":[
        {
            "category":"Building & Trades",
            "subcategory":"Cleaning & Sanitation",
            "type":"Services"
        }
    ],
    "sg:phone":"+1 919 557 3105",
    "sg:postcode":"27592",
    "sg:province":"NC",
    "sg:tags":[
        "maintenance"
    ],
    "wof:name":"Final Concepts Enterprises Inc",
    "wof:placetype":"venue"
},
  "geometry": {"coordinates":[-78.692142,35.601659],"type":"Point"}
}