{
  "type": "Feature",
  "properties": {
    "addr:full":"1234 S J K Powell Blvd Whiteville NC 28472",
    "addr:housenumber":"1234",
    "addr:postcode":"28472",
    "addr:street":"S J K Powell Blvd",
    "iso:country":"US",
    "sg:address":"1234 S J K Powell Blvd",
    "sg:city":"Whiteville",
    "sg:classifiers":[
        {
            "category":"Shopping",
            "subcategory":"Discount & Variety Stores",
            "type":"Retail Goods"
        }
    ],
    "sg:phone":"+1 910 642 9264",
    "sg:postcode":"28472",
    "sg:province":"NC",
    "wof:name":"Via Mexico",
    "wof:placetype":"venue"
},
  "geometry": {"coordinates":[-78.71225,34.313484],"type":"Point"}
}