{
  "type": "Feature",
  "properties": {
    "iso:country":"US",
    "sg:address":"2817 Durham Rd",
    "sg:city":"Wake Forest",
    "sg:classifiers":[
        {
            "category":"Organizations",
            "subcategory":"Religious Organization",
            "type":"Services"
        }
    ],
    "sg:phone":"+1   ",
    "sg:postcode":"27587",
    "sg:province":"NC",
    "wof:name":"Ridgecrest Baptist Church",
    "wof:placetype":"venue"
},
  "geometry": {"coordinates":[-78.61331,35.981386],"type":"Point"}
}