{
  "type": "Feature",
  "properties": {
    "addr:full":"3380 Wilfong Rd Newton NC 28658",
    "addr:housenumber":"3380",
    "addr:postcode":"28658",
    "addr:street":"Wilfong Rd",
    "iso:country":"US",
    "sg:address":"3380 Wilfong Rd",
    "sg:city":"Newton",
    "sg:classifiers":[
        {
            "category":"Building & Trades",
            "subcategory":"Construction",
            "type":"Services"
        }
    ],
    "sg:phone":"+1 828 313 0956",
    "sg:postcode":"28658",
    "sg:province":"NC",
    "sg:tags":[
        "concrete",
        "contractor"
    ],
    "wof:name":"Carl Concrete Construction",
    "wof:placetype":"venue"
},
  "geometry": {"coordinates":[-81.298756,35.596447],"type":"Point"}
}