{
  "type": "Feature",
  "properties": {
    "addr:full":"616 Branch St Rocky Mount NC 27801",
    "addr:housenumber":"616",
    "addr:postcode":"27801",
    "addr:street":"Branch St",
    "iso:country":"US",
    "sg:address":"616 Branch St",
    "sg:city":"Rocky Mount",
    "sg:classifiers":[
        {
            "category":"Freight",
            "type":"Transportation"
        }
    ],
    "sg:phone":"+1 252 977 3585",
    "sg:postcode":"27801",
    "sg:province":"NC",
    "sg:tags":[
        "operator",
        "local",
        "trucking"
    ],
    "wof:name":"Parker Jl Inc",
    "wof:placetype":"venue"
},
  "geometry": {"coordinates":[-77.792548,35.934876],"type":"Point"}
}