{
  "type": "Feature",
  "properties": {
    "addr:full":"312 Birmingham Ave Carolina Beach NC 28428",
    "addr:housenumber":"312",
    "addr:postcode":"28428",
    "addr:street":"Birmingham Ave",
    "iso:country":"US",
    "sg:address":"312 Birmingham Ave",
    "sg:city":"Carolina Beach",
    "sg:classifiers":[
        {
            "category":"Food & Beverages",
            "subcategory":"Groceries & Convenience Stores",
            "type":"Retail Goods"
        }
    ],
    "sg:phone":"+1 910 458 0106",
    "sg:postcode":"28428",
    "sg:province":"NC",
    "sg:tags":[
        "product"
    ],
    "wof:name":"Food Science Corp",
    "wof:placetype":"venue"
},
  "geometry": {"coordinates":[-77.899818,34.028846],"type":"Point"}
}