{
  "type": "Feature",
  "properties": {
    "addr:full":"125 S Main St Hendersonville NC 28792",
    "addr:housenumber":"125",
    "addr:postcode":"28792",
    "addr:street":"S Main St",
    "iso:country":"US",
    "sg:address":"125 S Main St",
    "sg:city":"Hendersonville",
    "sg:classifiers":[
        {
            "category":"Social Services",
            "type":"Services"
        }
    ],
    "sg:phone":"+1 828 693 3840",
    "sg:postcode":"28792",
    "sg:province":"NC",
    "wof:name":"Main Stay",
    "wof:placetype":"venue"
},
  "geometry": {"coordinates":[-82.459727,35.314077],"type":"Point"}
}