{
  "type": "Feature",
  "properties": {
    "addr:full":"9 Stirling St Granite Falls NC 28630",
    "addr:housenumber":"9",
    "addr:postcode":"28630",
    "addr:street":"Stirling St",
    "iso:country":"US",
    "sg:address":"9 Stirling St",
    "sg:city":"Granite Falls",
    "sg:classifiers":[
        {
            "category":"Wholesale",
            "subcategory":"Construction Materials",
            "type":"Manufacturing & Wholesale Goods"
        }
    ],
    "sg:phone":"+1 828 396 6719",
    "sg:postcode":"28630",
    "sg:province":"NC",
    "sg:tags":[
        "lumber"
    ],
    "wof:name":"Cronland Lumber Co",
    "wof:placetype":"venue"
},
  "geometry": {"coordinates":[-81.426963,35.796034],"type":"Point"}
}