{
  "type": "Feature",
  "properties": {
    "iso:country":"US",
    "sg:address":"5820 E W T Harris Blvd",
    "sg:city":"Charlotte",
    "sg:classifiers":[
        {
            "category":"Professional",
            "subcategory":"Computer Services",
            "type":"Services"
        }
    ],
    "sg:phone":"+1   ",
    "sg:postcode":"28215",
    "sg:province":"NC",
    "sg:tags":[
        "prepackaged",
        "software"
    ],
    "wof:name":"Trucksoft",
    "wof:placetype":"venue"
},
  "geometry": {"coordinates":[-80.735636,35.236502],"type":"Point"}
}