{
  "type": "Feature",
  "properties": {
    "iso:country":"US",
    "sg:address":"1611 Colonial Ave",
    "sg:city":"Greensboro",
    "sg:classifiers":[
        {
            "category":"Professional",
            "subcategory":"Business Services",
            "type":"Services"
        }
    ],
    "sg:phone":"+1   ",
    "sg:postcode":"27408",
    "sg:province":"NC",
    "wof:name":"Optimus Solutions",
    "wof:placetype":"venue"
},
  "geometry": {"coordinates":[-79.81020599999999,36.105955],"type":"Point"}
}