{
  "type": "Feature",
  "properties": {
    "addr:full":"120 W Broad St Elizabethtown NC 28337",
    "addr:housenumber":"120",
    "addr:postcode":"28337",
    "addr:street":"W Broad St",
    "iso:country":"US",
    "sg:address":"120 W Broad St",
    "sg:city":"Elizabethtown",
    "sg:classifiers":[
        {
            "category":"Shopping",
            "subcategory":"Florist",
            "type":"Retail Goods"
        }
    ],
    "sg:phone":"+1 910 862 4369",
    "sg:postcode":"28337",
    "sg:province":"NC",
    "wof:name":"Elizabethtown Florist",
    "wof:placetype":"venue"
},
  "geometry": {"coordinates":[-78.607005,34.629342],"type":"Point"}
}