{
  "type": "Feature",
  "properties": {
    "addr:full":"561 N Polk St Pineville NC 28134",
    "addr:housenumber":"561",
    "addr:postcode":"28134",
    "addr:street":"N Polk St",
    "iso:country":"US",
    "sg:address":"561 N Polk St",
    "sg:city":"Pineville",
    "sg:classifiers":[
        {
            "category":"Professional",
            "type":"Services"
        },
        {
            "category":"Health Services",
            "subcategory":"Health Practitioner",
            "type":"Services"
        }
    ],
    "sg:phone":"+1 704 889 7828",
    "sg:postcode":"28134",
    "sg:province":"NC",
    "sg:tags":[
        "occupational",
        "therapist",
        "physical"
    ],
    "wof:name":"Touchstone Therapy Inc",
    "wof:placetype":"venue"
},
  "geometry": {"coordinates":[-80.885411,35.091337],"type":"Point"}
}