{
  "type": "Feature",
  "properties": {
    "addr:full":"4995 State Hwy 101 Newport NC 28570",
    "addr:housenumber":"4995",
    "addr:postcode":"28570",
    "addr:street":"State Hwy 101",
    "iso:country":"US",
    "sg:address":"4995 State Hwy 101",
    "sg:city":"Newport",
    "sg:classifiers":[
        {
            "category":"Farming",
            "subcategory":"Farm",
            "type":"Manufacturing & Wholesale Goods"
        },
        {
            "category":"Farming",
            "subcategory":"Farm & Veterinary Services",
            "type":"Manufacturing & Wholesale Goods"
        }
    ],
    "sg:phone":"+1 252 447 4813",
    "sg:postcode":"28570",
    "sg:province":"NC",
    "sg:tags":[
        "tree",
        "crop"
    ],
    "wof:name":"Temple Farms Inc",
    "wof:placetype":"venue"
},
  "geometry": {"coordinates":[-76.752179,34.834891],"type":"Point"}
}