{
  "type": "Feature",
  "properties": {
    "addr:full":"274 Jet St Hendersonville NC 28792",
    "addr:housenumber":"274",
    "addr:postcode":"28792",
    "addr:street":"Jet St",
    "iso:country":"US",
    "sg:address":"274 Jet St",
    "sg:city":"Hendersonville",
    "sg:classifiers":[
        {
            "category":"Wholesale",
            "subcategory":"Fruits & Vegetables",
            "type":"Manufacturing & Wholesale Goods"
        }
    ],
    "sg:phone":"+1 828 685 3447",
    "sg:postcode":"28792",
    "sg:province":"NC",
    "wof:name":"Riverwood Produce Sales Inc",
    "wof:placetype":"venue"
},
  "geometry": {"coordinates":[-82.402922,35.345416],"type":"Point"}
}