{
  "type": "Feature",
  "properties": {
    "iso:country":"US",
    "sg:address":"97 Anna Pl",
    "sg:city":"Clayton",
    "sg:classifiers":[
        {
            "category":"Wholesale",
            "subcategory":"Electrical",
            "type":"Manufacturing & Wholesale Goods"
        }
    ],
    "sg:phone":"+1 919 359 0081",
    "sg:postcode":"27520",
    "sg:province":"NC",
    "sg:tags":[
        "sound",
        "equipment",
        "system"
    ],
    "wof:name":"North Carolina Sound Contrs",
    "wof:placetype":"venue"
},
  "geometry": {"coordinates":[-78.52703,35.617305],"type":"Point"}
}