{
  "type": "Feature",
  "properties": {
    "iso:country":"US",
    "sg:address":"801 Stadium Dr",
    "sg:city":"Durham",
    "sg:classifiers":[
        {
            "category":"Government",
            "subcategory":"Office",
            "type":"Public Place"
        }
    ],
    "sg:phone":"+1 919 220 7510",
    "sg:postcode":"27704",
    "sg:province":"NC",
    "sg:tags":[
        "national",
        "security"
    ],
    "wof:name":"National Guard North Carolina",
    "wof:placetype":"venue"
},
  "geometry": {"coordinates":[-78.89957,36.03358],"type":"Point"}
}