{
  "type": "Feature",
  "properties": {
    "iso:country":"US",
    "sg:address":"4751 Dusty Ln",
    "sg:city":"Marshville",
    "sg:classifiers":[
        {
            "category":"Professional",
            "type":"Services"
        }
    ],
    "sg:phone":"+1 704 385 9048",
    "sg:postcode":"28103",
    "sg:province":"NC",
    "wof:name":"Little Rock Grading Inc",
    "wof:placetype":"venue"
},
  "geometry": {"coordinates":[-80.362658,35.126616],"type":"Point"}
}