{
  "type": "Feature",
  "properties": {
    "iso:country":"US",
    "sg:address":"307 Simmons St",
    "sg:city":"New Bern",
    "sg:classifiers":[
        {
            "category":"Real Estate",
            "subcategory":"Real Estate Operator",
            "type":"Services"
        }
    ],
    "sg:phone":"+1 252 633 3357",
    "sg:postcode":"28560",
    "sg:province":"NC",
    "sg:tags":[
        "apartment"
    ],
    "wof:name":"Carolina Club",
    "wof:placetype":"venue"
},
  "geometry": {"coordinates":[-77.076041,35.104285],"type":"Point"}
}