{
  "type": "Feature",
  "properties": {
    "iso:country":"US",
    "sg:address":"10401 Old Stage Rd",
    "sg:city":"Raleigh",
    "sg:classifiers":[
        {
            "category":"Social Services",
            "subcategory":"Adult Care",
            "type":"Services"
        }
    ],
    "sg:phone":"+1 919 771 1052",
    "sg:postcode":"27603",
    "sg:province":"NC",
    "sg:tags":[
        "home",
        "residential"
    ],
    "wof:name":"Morgan Family Care Home",
    "wof:placetype":"venue"
},
  "geometry": {"coordinates":[-78.674695,35.631204],"type":"Point"}
}