{
  "type": "Feature",
  "properties": {
    "addr:full":"138 Marshall Chapel Rd Jacksonville NC 28546",
    "addr:housenumber":"138",
    "addr:postcode":"28546",
    "addr:street":"Marshall Chapel Rd",
    "iso:country":"US",
    "sg:address":"138 Marshall Chapel Rd",
    "sg:city":"Jacksonville",
    "sg:classifiers":[
        {
            "category":"Building & Trades",
            "subcategory":"Plumbing",
            "type":"Services"
        }
    ],
    "sg:phone":"+1 910 330 8078",
    "sg:postcode":"28546",
    "sg:province":"NC",
    "sg:tags":[
        "contractor"
    ],
    "wof:name":"Rj Plumbing Co",
    "wof:placetype":"venue"
},
  "geometry": {"coordinates":[-77.32673699999999,34.740193],"type":"Point"}
}