{
  "type": "Feature",
  "properties": {
    "iso:country":"US",
    "sg:address":"120 Turner St",
    "sg:city":"Beaufort",
    "sg:classifiers":[
        {
            "category":"Professional",
            "subcategory":"Research",
            "type":"Services"
        }
    ],
    "sg:phone":"+1 252 728 2109",
    "sg:postcode":"28516",
    "sg:province":"NC",
    "sg:tags":[
        "organization",
        "noncommercial"
    ],
    "wof:name":"Alderon Corp",
    "wof:placetype":"venue"
},
  "geometry": {"coordinates":[-76.66475,34.71839],"type":"Point"}
}