{
  "type": "Feature",
  "properties": {
    "addr:full":"1508 Beaucrest Ave High Point NC 27265",
    "addr:housenumber":"1508",
    "addr:postcode":"27265",
    "addr:street":"Beaucrest Ave",
    "iso:country":"US",
    "sg:address":"1508 Beaucrest Ave",
    "sg:city":"High Point",
    "sg:classifiers":[
        {
            "category":"Organizations",
            "subcategory":"Religious Organization",
            "type":"Services"
        }
    ],
    "sg:phone":"+1 336 885 6837",
    "sg:postcode":"27265",
    "sg:province":"NC",
    "sg:tags":[
        "church"
    ],
    "wof:name":"Conrad Memorial Bapt Chr Prsng",
    "wof:placetype":"venue"
},
  "geometry": {"coordinates":[-79.996888,35.988103],"type":"Point"}
}