{
  "type": "Feature",
  "properties": {
    "addr:full":"211 Main St Pineville NC 28134",
    "addr:housenumber":"211",
    "addr:postcode":"28134",
    "addr:street":"Main St",
    "iso:country":"US",
    "sg:address":"211 Main St",
    "sg:city":"Pineville",
    "sg:classifiers":[
        {
            "category":"Building & Trades",
            "subcategory":"Plumbing",
            "type":"Services"
        }
    ],
    "sg:phone":"+1 704 547 0071",
    "sg:postcode":"28134",
    "sg:province":"NC",
    "sg:tags":[
        "plumbing",
        "contractor"
    ],
    "wof:name":"U S Plumbing Heating & Air Inc",
    "wof:placetype":"venue"
},
  "geometry": {"coordinates":[-80.888655,35.085203],"type":"Point"}
}