{
  "type": "Feature",
  "properties": {
    "addr:full":"4530 S Ridge Dr Fuquay Varina NC 27526",
    "addr:housenumber":"4530",
    "addr:postcode":"27526",
    "addr:street":"S Ridge Dr",
    "iso:country":"US",
    "sg:address":"4530 S Ridge Dr",
    "sg:city":"Fuquay Varina",
    "sg:classifiers":[
        {
            "category":"Home & Garden",
            "subcategory":"Building Materials",
            "type":"Retail Goods"
        }
    ],
    "sg:phone":"+1 919 557 3700",
    "sg:postcode":"27526",
    "sg:province":"NC",
    "sg:tags":[
        "glass",
        "leaded"
    ],
    "wof:name":"Not Afraid-Color Stained Glass",
    "wof:placetype":"venue"
},
  "geometry": {"coordinates":[-78.73555500000001,35.624356],"type":"Point"}
}