{
  "type": "Feature",
  "properties": {
    "addr:full":"2548 Gumtree Rd Winston Salem NC 27107",
    "addr:housenumber":"2548",
    "addr:postcode":"27107",
    "addr:street":"Gumtree Rd",
    "iso:country":"US",
    "sg:address":"2548 Gumtree Rd",
    "sg:city":"Winston Salem",
    "sg:classifiers":[
        {
            "category":"Home & Garden",
            "subcategory":"Furniture",
            "type":"Retail Goods"
        }
    ],
    "sg:phone":"+1 336 784 7648",
    "sg:postcode":"27107",
    "sg:province":"NC",
    "wof:name":"Triad Home Furnishing",
    "wof:placetype":"venue"
},
  "geometry": {"coordinates":[-80.198311,35.996784],"type":"Point"}
}