{
  "type": "Feature",
  "properties": {
    "iso:country":"US",
    "sg:address":"6801 Northlake Mall Dr",
    "sg:city":"Charlotte",
    "sg:classifiers":[
        {
            "category":"Shopping",
            "subcategory":"Hobbies, Toys, & Games",
            "type":"Retail Goods"
        }
    ],
    "sg:phone":"+1 704 494 4403",
    "sg:postcode":"28216",
    "sg:province":"NC",
    "sg:tags":[
        "toy",
        "store"
    ],
    "sg:website":"http://www.buildabear.com",
    "wof:name":"Build-A-Bear Workshop",
    "wof:placetype":"venue"
},
  "geometry": {"coordinates":[-80.85015799999999,35.349814],"type":"Point"}
}