{
  "type": "Feature",
  "properties": {
    "addr:full":"107 E Walker St East Flat Rock NC 28726",
    "addr:housenumber":"107",
    "addr:postcode":"28726",
    "addr:street":"E Walker St",
    "iso:country":"US",
    "sg:address":"107 E Walker St",
    "sg:city":"East Flat Rock",
    "sg:classifiers":[
        {
            "category":"Shopping",
            "type":"Retail Goods"
        }
    ],
    "sg:phone":"+1 828 697 0048",
    "sg:postcode":"28726",
    "sg:province":"NC",
    "sg:tags":[
        "orthopedic",
        "appliance"
    ],
    "wof:name":"Footlogic Inc",
    "wof:placetype":"venue"
},
  "geometry": {"coordinates":[-82.423194,35.284504],"type":"Point"}
}