{
  "type": "Feature",
  "properties": {
    "iso:country":"US",
    "sg:address":"3411 Integrity Dr",
    "sg:city":"Garner",
    "sg:classifiers":[
        {
            "category":"Building & Trades",
            "subcategory":"Cleaning & Sanitation",
            "type":"Services"
        }
    ],
    "sg:phone":"+1 919 773 3522",
    "sg:postcode":"27529",
    "sg:province":"NC",
    "sg:tags":[
        "maintenance"
    ],
    "wof:name":"IMC",
    "wof:placetype":"venue"
},
  "geometry": {"coordinates":[-78.583122,35.727452],"type":"Point"}
}