{
  "type": "Feature",
  "properties": {
    "addr:full":"1205 E Main St Haw River NC 27258",
    "addr:housenumber":"1205",
    "addr:postcode":"27258",
    "addr:street":"E Main St",
    "iso:country":"US",
    "sg:address":"1205 E Main St",
    "sg:city":"Haw River",
    "sg:classifiers":[
        {
            "category":"Autos & Motor Vehicles",
            "subcategory":"Automobile Sales",
            "type":"Retail Goods"
        }
    ],
    "sg:phone":"+1 336 578 1600",
    "sg:postcode":"27258",
    "sg:province":"NC",
    "sg:tags":[
        "car",
        "dealer"
    ],
    "wof:name":"D & T Auto Sales",
    "wof:placetype":"venue"
},
  "geometry": {"coordinates":[-79.349474,36.093508],"type":"Point"}
}