{
  "type": "Feature",
  "properties": {
    "iso:country":"US",
    "sg:address":"426 E Donaldson Ave",
    "sg:city":"Raeford",
    "sg:classifiers":[
        {
            "category":"Social Services",
            "subcategory":"Adult Care",
            "type":"Services"
        }
    ],
    "sg:phone":"+1 910 904 0009",
    "sg:postcode":"28376",
    "sg:province":"NC",
    "sg:tags":[
        "home",
        "group"
    ],
    "wof:name":"Concordia Group Home",
    "wof:placetype":"venue"
},
  "geometry": {"coordinates":[-79.219154,34.982829],"type":"Point"}
}