{
  "type": "Feature",
  "properties": {
    "iso:country":"US",
    "sg:address":"1200 Corporation Dr",
    "sg:city":"Archdale",
    "sg:classifiers":[
        {
            "category":"Manufacturing",
            "subcategory":"Chemicals & Compounds",
            "type":"Manufacturing & Wholesale Goods"
        }
    ],
    "sg:phone":"+1 336 431 1157",
    "sg:postcode":"27263",
    "sg:province":"NC",
    "sg:tags":[
        "finishing",
        "material",
        "furniture"
    ],
    "wof:name":"Renner Sayerlack USA Inc",
    "wof:placetype":"venue"
},
  "geometry": {"coordinates":[-80.00551299999999,35.916215],"type":"Point"}
}