{
  "type": "Feature",
  "properties": {
    "iso:country":"US",
    "sg:address":"4205 Old US Hwy 29",
    "sg:city":"Thomasville",
    "sg:classifiers":[
        {
            "category":"Government",
            "subcategory":"Fire Station",
            "type":"Public Place"
        }
    ],
    "sg:phone":"+1 336 475 6152",
    "sg:postcode":"27360",
    "sg:province":"NC",
    "sg:tags":[
        "department"
    ],
    "wof:name":"Pilot Fire Dept",
    "wof:placetype":"venue"
},
  "geometry": {"coordinates":[-80.135863,35.878849],"type":"Point"}
}