{
  "type": "Feature",
  "properties": {
    "iso:country":"US",
    "sg:address":"137 Fleming Farm Dr",
    "sg:city":"Youngsville",
    "sg:classifiers":[
        {
            "category":"Wholesale",
            "subcategory":"Construction Materials",
            "type":"Manufacturing & Wholesale Goods"
        },
        {
            "category":"Manufacturing",
            "subcategory":"Lumber",
            "type":"Manufacturing & Wholesale Goods"
        }
    ],
    "sg:phone":"+1 919 554 4597",
    "sg:postcode":"27596",
    "sg:province":"NC",
    "sg:tags":[
        "timberland",
        "operation",
        "timber",
        "company",
        "tract"
    ],
    "wof:name":"A & P Timber Co Inc",
    "wof:placetype":"venue"
},
  "geometry": {"coordinates":[-78.472842,36.041774],"type":"Point"}
}