{
  "type": "Feature",
  "properties": {
    "iso:country":"US",
    "sg:address":"116 E Market St",
    "sg:city":"Greensboro",
    "sg:classifiers":[
        {
            "category":"Shopping",
            "subcategory":"Clothing, Apparel, & Fashions",
            "type":"Retail Goods"
        }
    ],
    "sg:phone":"+1 336 272 7040",
    "sg:postcode":"27401",
    "sg:province":"NC",
    "sg:tags":[
        "uniform"
    ],
    "wof:name":"Showfety's Uniforms Inc",
    "wof:placetype":"venue"
},
  "geometry": {"coordinates":[-79.789226,36.072365],"type":"Point"}
}