{
  "type": "Feature",
  "properties": {
    "iso:country":"US",
    "sg:address":"3001 Spring Forest Rd",
    "sg:city":"Raleigh",
    "sg:classifiers":[
        {
            "category":"Health Services",
            "subcategory":"Clinic",
            "type":"Services"
        }
    ],
    "sg:phone":"+1 919 424 5080",
    "sg:postcode":"27616",
    "sg:province":"NC",
    "sg:website":"www.legacyhealthcare.net",
    "wof:name":"Legacy Healthcare Svc Inc",
    "wof:placetype":"venue"
},
  "geometry": {"coordinates":[-78.59168099999999,35.855561],"type":"Point"}
}