{
  "type": "Feature",
  "properties": {
    "iso:country":"US",
    "sg:address":"4415 Matthews Weddington Rd",
    "sg:city":"Matthews",
    "sg:classifiers":[
        {
            "category":"Professional",
            "subcategory":"Management & Consulting",
            "type":"Services"
        }
    ],
    "sg:phone":"+1   ",
    "sg:postcode":"28104",
    "sg:province":"NC",
    "wof:name":"Ciminelli & Associates",
    "wof:placetype":"venue"
},
  "geometry": {"coordinates":[-80.737776,35.051381],"type":"Point"}
}