{
  "type": "Feature",
  "properties": {
    "iso:country":"US",
    "sg:address":"106 Brook Hollow Dr",
    "sg:city":"Flat Rock",
    "sg:classifiers":[
        {
            "category":"Mining & Drilling",
            "type":"Manufacturing & Wholesale Goods"
        }
    ],
    "sg:phone":"+1 828 697 1425",
    "sg:postcode":"28731",
    "sg:province":"NC",
    "sg:tags":[
        "exploration"
    ],
    "wof:name":"Dandelion Enterprises Inc",
    "wof:placetype":"venue"
},
  "geometry": {"coordinates":[-82.464268,35.249058],"type":"Point"}
}