{
  "type": "Feature",
  "properties": {
    "addr:full":"632 Telephone Exchange Rd Hickory NC 28601",
    "addr:housenumber":"632",
    "addr:postcode":"28601",
    "addr:street":"Exchange Rd",
    "iso:country":"US",
    "sg:address":"632 Telephone Exchange Rd",
    "sg:city":"Hickory",
    "sg:classifiers":[
        {
            "category":"Retail",
            "subcategory":"Auto Rental",
            "type":"Services"
        }
    ],
    "sg:phone":"+1   ",
    "sg:postcode":"28601",
    "sg:province":"NC",
    "sg:tags":[
        "trailer",
        "utility"
    ],
    "wof:name":"Lane Rentals",
    "wof:placetype":"venue"
},
  "geometry": {"coordinates":[-81.298817,35.827809],"type":"Point"}
}