{
  "type": "Feature",
  "properties": {
    "addr:full":"7301 Caldwell Rd Harrisburg NC 28075",
    "addr:housenumber":"7301",
    "addr:postcode":"28075",
    "addr:street":"Caldwell Rd",
    "iso:country":"US",
    "sg:address":"7301 Caldwell Rd",
    "sg:city":"Harrisburg",
    "sg:classifiers":[
        {
            "category":"Manufacturing",
            "subcategory":"Chemicals & Compounds",
            "type":"Manufacturing & Wholesale Goods"
        }
    ],
    "sg:phone":"+1 704 455 5191",
    "sg:postcode":"28075",
    "sg:province":"NC",
    "sg:tags":[
        "material",
        "plastic"
    ],
    "wof:name":"Morton Custom Plastics",
    "wof:placetype":"venue"
},
  "geometry": {"coordinates":[-80.673365,35.315924],"type":"Point"}
}