{
  "type": "Feature",
  "properties": {
    "iso:country":"US",
    "sg:address":"4909 Olde Millcrest Ct",
    "sg:city":"Raleigh",
    "sg:classifiers":[
        {
            "category":"Real Estate",
            "subcategory":"Real Estate Operator",
            "type":"Services"
        }
    ],
    "sg:phone":"+1 919 881 2031",
    "sg:postcode":"27609",
    "sg:province":"NC",
    "sg:tags":[
        "building",
        "nonresidential"
    ],
    "wof:name":"Jjsb Properties LLC",
    "wof:placetype":"venue"
},
  "geometry": {"coordinates":[-78.62525599999999,35.850972],"type":"Point"}
}