{
  "type": "Feature",
  "properties": {
    "iso:country":"US",
    "sg:address":"1704 Leggett Rd",
    "sg:city":"Rocky Mount",
    "sg:classifiers":[
        {
            "category":"Professional",
            "type":"Services"
        }
    ],
    "sg:phone":"+1 252 985 1376",
    "sg:postcode":"27801",
    "sg:province":"NC",
    "wof:name":"Phillips Son",
    "wof:placetype":"venue"
},
  "geometry": {"coordinates":[-77.75981899999999,35.963057],"type":"Point"}
}