{
  "type": "Feature",
  "properties": {
    "iso:country":"US",
    "sg:address":"135 Old Mill Rd",
    "sg:city":"Mars Hill",
    "sg:classifiers":[
        {
            "category":"Food & Beverages",
            "subcategory":"Groceries & Convenience Stores",
            "type":"Retail Goods"
        }
    ],
    "sg:phone":"+1 828 689 4073",
    "sg:postcode":"28754",
    "sg:province":"NC",
    "wof:name":"Curb Company",
    "wof:placetype":"venue"
},
  "geometry": {"coordinates":[-82.49550600000001,35.844721],"type":"Point"}
}