{
  "type": "Feature",
  "properties": {
    "iso:country":"US",
    "sg:address":"219 N Hayne St",
    "sg:city":"Monroe",
    "sg:classifiers":[
        {
            "category":"Professional",
            "subcategory":"Accounting & Tax Preparation",
            "type":"Services"
        }
    ],
    "sg:phone":"+1   ",
    "sg:postcode":"28112",
    "sg:province":"NC",
    "sg:tags":[
        "firm"
    ],
    "wof:name":"Jimmy R Williams",
    "wof:placetype":"venue"
},
  "geometry": {"coordinates":[-80.549561,34.982507],"type":"Point"}
}