{
  "type": "Feature",
  "properties": {
    "addr:full":"700 Old Zebulon Rd Wendell NC 27591",
    "addr:housenumber":"700",
    "addr:postcode":"27591",
    "addr:street":"Old Zebulon Rd",
    "iso:country":"US",
    "sg:address":"700 Old Zebulon Rd",
    "sg:city":"Wendell",
    "sg:classifiers":[
        {
            "category":"Retail",
            "subcategory":"Repair Shop",
            "type":"Services"
        }
    ],
    "sg:phone":"+1   ",
    "sg:postcode":"27591",
    "sg:province":"NC",
    "wof:name":"Jj Lawn Mower Repairs",
    "wof:placetype":"venue"
},
  "geometry": {"coordinates":[-78.358519,35.794221],"type":"Point"}
}