{
  "type": "Feature",
  "properties": {
    "iso:country":"US",
    "sg:address":"207 Queen St",
    "sg:city":"Morganton",
    "sg:classifiers":[
        {
            "category":"Health Services",
            "subcategory":"Doctor",
            "type":"Services"
        }
    ],
    "sg:phone":"+1 828 438 1010",
    "sg:postcode":"28655",
    "sg:province":"NC",
    "sg:tags":[
        "physician",
        "surgeon"
    ],
    "wof:name":"Amy Brooks DDS",
    "wof:placetype":"venue"
},
  "geometry": {"coordinates":[-81.690699,35.743886],"type":"Point"}
}