{
  "type": "Feature",
  "properties": {
    "addr:full":"1811 State Hwy 172 Sneads Ferry NC 28460",
    "addr:housenumber":"1811",
    "addr:postcode":"28460",
    "addr:street":"State Hwy 172",
    "iso:country":"US",
    "sg:address":"1811 State Hwy 172",
    "sg:city":"Sneads Ferry",
    "sg:classifiers":[
        {
            "category":"Building & Trades",
            "subcategory":"Equipment Rental",
            "type":"Services"
        }
    ],
    "sg:phone":"+1 910 327 2381",
    "sg:postcode":"28460",
    "sg:province":"NC",
    "sg:tags":[
        "toilet"
    ],
    "wof:name":"TNT Porta Potty",
    "wof:placetype":"venue"
},
  "geometry": {"coordinates":[-77.44998099999999,34.547228],"type":"Point"}
}