{
  "type": "Feature",
  "properties": {
    "iso:country":"US",
    "sg:address":"200 Sanford Rd",
    "sg:city":"Pittsboro",
    "sg:classifiers":[
        {
            "category":"Organizations",
            "subcategory":"Non-profit Organization",
            "type":"Services"
        }
    ],
    "sg:phone":"+1 919 542 1593",
    "sg:postcode":"27312",
    "sg:province":"NC",
    "sg:tags":[
        "human"
    ],
    "wof:name":"Salvation Army",
    "wof:placetype":"venue"
},
  "geometry": {"coordinates":[-79.178938,35.717563],"type":"Point"}
}