{
  "type": "Feature",
  "properties": {
    "iso:country":"US",
    "sg:address":"2112 Sloan Dr",
    "sg:city":"Charlotte",
    "sg:classifiers":[
        {
            "category":"Social Services",
            "subcategory":"Child Care",
            "type":"Services"
        }
    ],
    "sg:phone":"+1 704 392 7113",
    "sg:postcode":"28208",
    "sg:province":"NC",
    "sg:tags":[
        "day"
    ],
    "wof:name":"Precious Gifts Child Care",
    "wof:placetype":"venue"
},
  "geometry": {"coordinates":[-80.92404999999999,35.250438],"type":"Point"}
}