{
  "type": "Feature",
  "properties": {
    "iso:country":"US",
    "sg:address":"2205 Westinghouse Blvd",
    "sg:city":"Raleigh",
    "sg:classifiers":[
        {
            "category":"Retail",
            "subcategory":"Laundry & Dry Cleaning",
            "type":"Services"
        }
    ],
    "sg:phone":"+1 919 872 6775",
    "sg:postcode":"27604",
    "sg:province":"NC",
    "sg:tags":[
        "uniform",
        "supply"
    ],
    "wof:name":"Cintas The Uniform People",
    "wof:placetype":"venue"
},
  "geometry": {"coordinates":[-78.596206,35.809053],"type":"Point"}
}