{
  "type": "Feature",
  "properties": {
    "addr:full":"131 Edwin Pl Asheville NC 28801",
    "addr:housenumber":"131",
    "addr:postcode":"28801",
    "addr:street":"Edwin Pl",
    "iso:country":"US",
    "sg:address":"131 Edwin Pl",
    "sg:city":"Asheville",
    "sg:classifiers":[
        {
            "category":"Professional",
            "subcategory":"Management & Consulting",
            "type":"Services"
        }
    ],
    "sg:phone":"+1   ",
    "sg:postcode":"28801",
    "sg:province":"NC",
    "wof:name":"F C Foods Inc",
    "wof:placetype":"venue"
},
  "geometry": {"coordinates":[-82.550174,35.612007],"type":"Point"}
}