{
  "type": "Feature",
  "properties": {
    "iso:country":"US",
    "sg:address":"1113 Bridges St",
    "sg:city":"Morehead City",
    "sg:classifiers":[
        {
            "category":"Shopping",
            "subcategory":"Used Merchandise",
            "type":"Retail Goods"
        }
    ],
    "sg:phone":"+1 252 726 1399",
    "sg:postcode":"28557",
    "sg:province":"NC",
    "sg:tags":[
        "shop",
        "thrift"
    ],
    "wof:name":"Carteret County Humane Shelter",
    "wof:placetype":"venue"
},
  "geometry": {"coordinates":[-76.718069,34.722613],"type":"Point"}
}