{
  "type": "Feature",
  "properties": {
    "iso:country":"US",
    "sg:address":"253 Duncan Ln",
    "sg:city":"Winston Salem",
    "sg:classifiers":[
        {
            "category":"Recreation",
            "type":"Entertainment"
        }
    ],
    "sg:phone":"+1 336 764 3308",
    "sg:postcode":"27127",
    "sg:province":"NC",
    "sg:tags":[
        "stable"
    ],
    "wof:name":"Pony Tales Children Entrtnmnt",
    "wof:placetype":"venue"
},
  "geometry": {"coordinates":[-80.312288,35.991461],"type":"Point"}
}