{
  "type": "Feature",
  "properties": {
    "addr:full":"2806 Virginia Rd Tyner NC 27980",
    "addr:housenumber":"2806",
    "addr:postcode":"27980",
    "addr:street":"Virginia Rd",
    "iso:country":"US",
    "sg:address":"2806 Virginia Rd",
    "sg:city":"Tyner",
    "sg:classifiers":[
        {
            "category":"Restaurant",
            "type":"Food & Drink"
        }
    ],
    "sg:phone":"+1 252 221 2036",
    "sg:postcode":"27980",
    "sg:province":"NC",
    "sg:tags":[
        "caterer"
    ],
    "wof:name":"Leon Nixon Catering Svc",
    "wof:placetype":"venue"
},
  "geometry": {"coordinates":[-76.654141,36.234352],"type":"Point"}
}