{
  "type": "Feature",
  "properties": {
    "iso:country":"US",
    "sg:address":"6619 Somersworth Dr",
    "sg:city":"Charlotte",
    "sg:classifiers":[
        {
            "category":"Building & Trades",
            "subcategory":"Cleaning & Sanitation",
            "type":"Services"
        }
    ],
    "sg:phone":"+1   ",
    "sg:postcode":"28215",
    "sg:province":"NC",
    "sg:tags":[
        "maintenance"
    ],
    "wof:name":"Norfleet Car Cleaning Service",
    "wof:placetype":"venue"
},
  "geometry": {"coordinates":[-80.748565,35.257472],"type":"Point"}
}