{
  "type": "Feature",
  "properties": {
    "addr:full":"6416 Rea Rd Charlotte NC 28277",
    "addr:housenumber":"6416",
    "addr:postcode":"28277",
    "addr:street":"Rea Rd",
    "iso:country":"US",
    "sg:address":"6416 Rea Rd",
    "sg:city":"Charlotte",
    "sg:classifiers":[
        {
            "category":"Shopping",
            "subcategory":"Discount & Variety Stores",
            "type":"Retail Goods"
        }
    ],
    "sg:phone":"+1 704 542 5804",
    "sg:postcode":"28277",
    "sg:province":"NC",
    "sg:tags":[
        "merchandise",
        "general"
    ],
    "wof:name":"CVS Pharmacy",
    "wof:placetype":"venue"
},
  "geometry": {"coordinates":[-80.816647,35.079089],"type":"Point"}
}