{
  "type": "Feature",
  "properties": {
    "iso:country":"US",
    "sg:address":"300 Sir Walter Raleigh St",
    "sg:city":"Manteo",
    "sg:classifiers":[
        {
            "category":"Utilities",
            "subcategory":"Refuse",
            "type":"Services"
        }
    ],
    "sg:phone":"+1 252 473 2309",
    "sg:postcode":"27954",
    "sg:province":"NC",
    "sg:tags":[
        "garbage",
        "collection"
    ],
    "wof:name":"Pick Up Man",
    "wof:placetype":"venue"
},
  "geometry": {"coordinates":[-75.673199,35.907484],"type":"Point"}
}