{
  "type": "Feature",
  "properties": {
    "iso:country":"US",
    "sg:address":"3169 State Hwy 8 S",
    "sg:city":"Walnut Cove",
    "sg:classifiers":[
        {
            "category":"Building & Trades",
            "subcategory":"Construction",
            "type":"Services"
        }
    ],
    "sg:phone":"+1 336 593 2104",
    "sg:postcode":"27052",
    "sg:province":"NC",
    "sg:tags":[
        "water",
        "well",
        "drilling"
    ],
    "wof:name":"Venable Brothers Well Constr",
    "wof:placetype":"venue"
},
  "geometry": {"coordinates":[-80.199011,36.365295],"type":"Point"}
}