{
  "type": "Feature",
  "properties": {
    "addr:full":"133 4th Ave W Hendersonville NC 28792",
    "addr:housenumber":"133",
    "addr:postcode":"28792",
    "addr:street":"4Th Ave W",
    "iso:country":"US",
    "sg:address":"133 4th Ave W",
    "sg:city":"Hendersonville",
    "sg:classifiers":[
        {
            "category":"Shopping",
            "subcategory":"Florist",
            "type":"Retail Goods"
        }
    ],
    "sg:phone":"+1 828 693 9998",
    "sg:postcode":"28792",
    "sg:province":"NC",
    "sg:tags":[
        "funeral",
        "supply"
    ],
    "sg:website":"http://www.choysikebana.com",
    "wof:name":"Choy's Flowers & Ikebana",
    "wof:placetype":"venue"
},
  "geometry": {"coordinates":[-82.461021,35.316677],"type":"Point"}
}