{
  "type": "Feature",
  "properties": {
    "addr:full":"401 Lakeside Dr Lumberton NC 28360",
    "addr:housenumber":"401",
    "addr:postcode":"28360",
    "addr:street":"Lakeside Dr",
    "iso:country":"US",
    "sg:address":"401 Lakeside Dr",
    "sg:city":"Lumberton",
    "sg:classifiers":[
        {
            "category":"Building & Trades",
            "subcategory":"Construction",
            "type":"Services"
        }
    ],
    "sg:phone":"+1 910 739 4546",
    "sg:postcode":"28360",
    "sg:province":"NC",
    "sg:tags":[
        "home",
        "siding",
        "improvement",
        "contractor",
        "roofing"
    ],
    "wof:name":"Pait's Home Improvements Inc",
    "wof:placetype":"venue"
},
  "geometry": {"coordinates":[-79.009647,34.686517],"type":"Point"}
}