{
  "type": "Feature",
  "properties": {
    "iso:country":"US",
    "sg:address":"142 Sound Dr",
    "sg:city":"Atlantic Beach",
    "sg:classifiers":[
        {
            "category":"Shopping",
            "subcategory":"Gifts & Souvenirs",
            "type":"Retail Goods"
        }
    ],
    "sg:phone":"+1 252 726 9040",
    "sg:postcode":"28512",
    "sg:province":"NC",
    "sg:tags":[
        "shop"
    ],
    "wof:name":"Harbor House",
    "wof:placetype":"venue"
},
  "geometry": {"coordinates":[-76.740803,34.703058],"type":"Point"}
}