{
  "type": "Feature",
  "properties": {
    "addr:full":"103 Cape Fear Blvd Carolina Beach NC 28428",
    "addr:housenumber":"103",
    "addr:postcode":"28428",
    "addr:street":"Cape Fear Blvd",
    "iso:country":"US",
    "sg:address":"103 Cape Fear Blvd",
    "sg:city":"Carolina Beach",
    "sg:classifiers":[
        {
            "category":"Restaurant",
            "type":"Food & Drink"
        }
    ],
    "sg:phone":"+1 910 458 7557",
    "sg:postcode":"28428",
    "sg:province":"NC",
    "wof:name":"Trolly Stop Hot Dogs",
    "wof:placetype":"venue"
},
  "geometry": {"coordinates":[-77.893204,34.0331],"type":"Point"}
}