{
  "type": "Feature",
  "properties": {
    "addr:full":"5725 N Sharon Dr Raleigh NC 27603",
    "addr:housenumber":"5725",
    "addr:postcode":"27603",
    "addr:street":"N Sharon Dr",
    "iso:country":"US",
    "sg:address":"5725 N Sharon Dr",
    "sg:city":"Raleigh",
    "sg:classifiers":[
        {
            "category":"Professional",
            "subcategory":"Business Services",
            "type":"Services"
        }
    ],
    "sg:phone":"+1   ",
    "sg:postcode":"27603",
    "sg:province":"NC",
    "wof:name":"Eb Rental Properties LLC",
    "wof:placetype":"venue"
},
  "geometry": {"coordinates":[-78.663641,35.699616],"type":"Point"}
}