{
  "type": "Feature",
  "properties": {
    "iso:country":"US",
    "sg:address":"233 Allen St",
    "sg:city":"Belhaven",
    "sg:classifiers":[
        {
            "category":"Health Services",
            "subcategory":"Doctor",
            "type":"Services"
        }
    ],
    "sg:phone":"+1 252 943 6262",
    "sg:postcode":"27810",
    "sg:province":"NC",
    "sg:tags":[
        "dentist"
    ],
    "wof:name":"David H Elliott II DDS",
    "wof:placetype":"venue"
},
  "geometry": {"coordinates":[-76.620908,35.539962],"type":"Point"}
}