{
  "type": "Feature",
  "properties": {
    "addr:full":"551 Ryan Ave Sanford NC 27330",
    "addr:housenumber":"551",
    "addr:postcode":"27330",
    "addr:street":"Ryan Ave",
    "iso:country":"US",
    "sg:address":"551 Ryan Ave",
    "sg:city":"Sanford",
    "sg:classifiers":[
        {
            "category":"Wholesale",
            "subcategory":"Electrical",
            "type":"Manufacturing & Wholesale Goods"
        }
    ],
    "sg:phone":"+1 919 775 5112",
    "sg:postcode":"27330",
    "sg:province":"NC",
    "sg:tags":[
        "operated",
        "telephone",
        "card"
    ],
    "wof:name":"Telaleasing Enterprises Inc",
    "wof:placetype":"venue"
},
  "geometry": {"coordinates":[-79.16230299999999,35.479222],"type":"Point"}
}