{
  "type": "Feature",
  "properties": {
    "iso:country":"US",
    "sg:address":"11 Carolina Ave",
    "sg:city":"Maiden",
    "sg:classifiers":[
        {
            "category":"Restaurant",
            "type":"Food & Drink"
        }
    ],
    "sg:phone":"+1 828 428 3500",
    "sg:postcode":"28646",
    "sg:province":"NC",
    "sg:tags":[
        "eating"
    ],
    "wof:name":"KFC",
    "wof:placetype":"venue"
},
  "geometry": {"coordinates":[-81.869106,36.067634],"type":"Point"}
}