{
  "type": "Feature",
  "properties": {
    "addr:full":"2612 Hidden Pointe Dr Wilmington NC 28411",
    "addr:housenumber":"2612",
    "addr:postcode":"28411",
    "addr:street":"Hidden Pointe Dr",
    "iso:country":"US",
    "sg:address":"2612 Hidden Pointe Dr",
    "sg:city":"Wilmington",
    "sg:classifiers":[
        {
            "category":"Professional",
            "type":"Services"
        }
    ],
    "sg:phone":"+1 910 790 0115",
    "sg:postcode":"28411",
    "sg:province":"NC",
    "sg:tags":[
        "establishment"
    ],
    "wof:name":"W L Gore & Assoc",
    "wof:placetype":"venue"
},
  "geometry": {"coordinates":[-77.854736,34.287635],"type":"Point"}
}