{
  "type": "Feature",
  "properties": {
    "iso:country":"US",
    "sg:address":"1111 Hawthorne Ln",
    "sg:city":"Charlotte",
    "sg:classifiers":[
        {
            "category":"Wholesale",
            "subcategory":"Electrical",
            "type":"Manufacturing & Wholesale Goods"
        }
    ],
    "sg:phone":"+1 704 333 7191",
    "sg:postcode":"28205",
    "sg:province":"NC",
    "sg:tags":[
        "supply",
        "sign"
    ],
    "wof:name":"Mayberry Sign Supplies",
    "wof:placetype":"venue"
},
  "geometry": {"coordinates":[-80.8175,35.223752],"type":"Point"}
}