{
  "type": "Feature",
  "properties": {
    "addr:full":"4031 Dearborn Pl NW Concord NC 28027",
    "addr:housenumber":"4031",
    "addr:postcode":"28027",
    "addr:street":"Dearborn Pl Nw",
    "iso:country":"US",
    "sg:address":"4031 Dearborn Pl NW",
    "sg:city":"Concord",
    "sg:classifiers":[
        {
            "category":"Manufacturing",
            "subcategory":"Textiles",
            "type":"Manufacturing & Wholesale Goods"
        }
    ],
    "sg:phone":"+1 704 782 4800",
    "sg:postcode":"28027",
    "sg:province":"NC",
    "sg:tags":[
        "manufacturer",
        "hat",
        "shirt",
        "market",
        "tee"
    ],
    "wof:name":"Performance 1 Mktg & Mdse LLC",
    "wof:placetype":"venue"
},
  "geometry": {"coordinates":[-80.670311,35.367952],"type":"Point"}
}