{
  "type": "Feature",
  "properties": {
    "iso:country":"US",
    "sg:address":"120 Pat Ct",
    "sg:city":"Kings Mountain",
    "sg:classifiers":[
        {
            "category":"Retail",
            "subcategory":"Auto Repair",
            "type":"Services"
        }
    ],
    "sg:phone":"+1 704 739 6488",
    "sg:postcode":"28086",
    "sg:province":"NC",
    "sg:tags":[
        "transmission"
    ],
    "wof:name":"Curry's Trans-Research & Dev",
    "wof:placetype":"venue"
},
  "geometry": {"coordinates":[-81.324242,35.215667],"type":"Point"}
}