{
  "type": "Feature",
  "properties": {
    "addr:full":"1102 W Colonial Ave Elizabeth City NC 27909",
    "addr:housenumber":"1102",
    "addr:postcode":"27909",
    "addr:street":"W Colonial Ave",
    "iso:country":"US",
    "sg:address":"1102 W Colonial Ave",
    "sg:city":"Elizabeth City",
    "sg:classifiers":[
        {
            "category":"Home & Garden",
            "subcategory":"Carpets & Floor Coverings",
            "type":"Retail Goods"
        }
    ],
    "sg:phone":"+1 252 338 0261",
    "sg:postcode":"27909",
    "sg:province":"NC",
    "wof:name":"Final Touches Carpet & Vinyl",
    "wof:placetype":"venue"
},
  "geometry": {"coordinates":[-76.236709,36.303768],"type":"Point"}
}