{
  "type": "Feature",
  "properties": {
    "addr:full":"299 White Pine Dr Asheville NC 28805",
    "addr:housenumber":"299",
    "addr:postcode":"28805",
    "addr:street":"White Pine Dr",
    "iso:country":"US",
    "sg:address":"299 White Pine Dr",
    "sg:city":"Asheville",
    "sg:classifiers":[
        {
            "category":"Wholesale",
            "subcategory":"Machinery & Supplies",
            "type":"Manufacturing & Wholesale Goods"
        }
    ],
    "sg:phone":"+1 828 253 8079",
    "sg:postcode":"28805",
    "sg:province":"NC",
    "sg:tags":[
        "equipment",
        "industrial"
    ],
    "wof:name":"Clipper Ship Inc",
    "wof:placetype":"venue"
},
  "geometry": {"coordinates":[-82.52724600000001,35.576586],"type":"Point"}
}