{
  "type": "Feature",
  "properties": {
    "iso:country":"US",
    "sg:address":"9332 Lake Wheeler Rd",
    "sg:city":"Fuquay Varina",
    "sg:classifiers":[
        {
            "category":"Communications",
            "type":"Services"
        }
    ],
    "sg:phone":"+1 919 567 2002",
    "sg:postcode":"27526",
    "sg:province":"NC",
    "sg:website":"www.gsignal.com",
    "wof:name":"Global Signal Inc",
    "wof:placetype":"venue"
},
  "geometry": {"coordinates":[-78.723341,35.644622],"type":"Point"}
}