{
  "type": "Feature",
  "properties": {
    "iso:country":"US",
    "sg:address":"2032 Cameron St",
    "sg:city":"Raleigh",
    "sg:classifiers":[
        {
            "category":"Shopping",
            "subcategory":"Shoes",
            "type":"Retail Goods"
        }
    ],
    "sg:phone":"+1 919 828 9567",
    "sg:postcode":"27605",
    "sg:province":"NC",
    "wof:name":"Birkenstock Comfortable Soles",
    "wof:placetype":"venue"
},
  "geometry": {"coordinates":[-78.66059799999999,35.790979],"type":"Point"}
}