{
  "type": "Feature",
  "properties": {
    "addr:full":"2316 Lowell Rd Gastonia NC 28054",
    "addr:housenumber":"2316",
    "addr:postcode":"28054",
    "addr:street":"Lowell Rd",
    "iso:country":"US",
    "sg:address":"2316 Lowell Rd",
    "sg:city":"Gastonia",
    "sg:classifiers":[
        {
            "category":"Personal",
            "subcategory":"Beauty Salon",
            "type":"Services"
        }
    ],
    "sg:phone":"+1 704 824 5724",
    "sg:postcode":"28054",
    "sg:province":"NC",
    "sg:tags":[
        "shop"
    ],
    "wof:name":"Blondie's Hair Designs",
    "wof:placetype":"venue"
},
  "geometry": {"coordinates":[-81.13351900000001,35.279313],"type":"Point"}
}