{
  "type": "Feature",
  "properties": {
    "addr:full":"3516 Green Park Cir Charlotte NC 28217",
    "addr:housenumber":"3516",
    "addr:postcode":"28217",
    "addr:street":"Green Park Cir",
    "iso:country":"US",
    "sg:address":"3516 Green Park Cir",
    "sg:city":"Charlotte",
    "sg:classifiers":[
        {
            "category":"Wholesale",
            "subcategory":"Seafood",
            "type":"Manufacturing & Wholesale Goods"
        }
    ],
    "sg:phone":"+1 704 944 1160",
    "sg:postcode":"28217",
    "sg:province":"NC",
    "sg:website":"www.poseidonseafood.com",
    "wof:name":"Poseidon Enterprises Inc",
    "wof:placetype":"venue"
},
  "geometry": {"coordinates":[-80.931865,35.171784],"type":"Point"}
}