{
  "type": "Feature",
  "properties": {
    "iso:country":"US",
    "sg:address":"711 Fairview St",
    "sg:city":"Fayetteville",
    "sg:classifiers":[
        {
            "category":"Organizations",
            "subcategory":"Religious Organization",
            "type":"Services"
        }
    ],
    "sg:phone":"+1 910 323 4882",
    "sg:postcode":"28312",
    "sg:province":"NC",
    "sg:website":"www.gideons.org",
    "wof:name":"Gideons International",
    "wof:placetype":"venue"
},
  "geometry": {"coordinates":[-78.84188899999999,35.035497],"type":"Point"}
}