{
  "type": "Feature",
  "properties": {
    "addr:full":"1427 Westover Ter Greensboro NC 27408",
    "addr:housenumber":"1427",
    "addr:postcode":"27408",
    "addr:street":"Westover Ter",
    "iso:country":"US",
    "sg:address":"1427 Westover Ter",
    "sg:city":"Greensboro",
    "sg:classifiers":[
        {
            "category":"Manufacturing",
            "subcategory":"Apparel",
            "type":"Manufacturing & Wholesale Goods"
        }
    ],
    "sg:phone":"+1 336 272 8527",
    "sg:postcode":"27408",
    "sg:province":"NC",
    "sg:tags":[
        "fur"
    ],
    "sg:website":"www.jonesf.com",
    "wof:name":"Jones Fabricare Inc",
    "wof:placetype":"venue"
},
  "geometry": {"coordinates":[-79.81481100000001,36.091473],"type":"Point"}
}