{
  "type": "Feature",
  "properties": {
    "addr:full":"1874 Stone Rose Ave Rocky Mount NC 27804",
    "addr:housenumber":"1874",
    "addr:postcode":"27804",
    "addr:street":"Stone Rose Ave",
    "iso:country":"US",
    "sg:address":"1874 Stone Rose Ave",
    "sg:city":"Rocky Mount",
    "sg:classifiers":[
        {
            "category":"Restaurant",
            "type":"Food & Drink"
        }
    ],
    "sg:phone":"+1 252 443 2133",
    "sg:postcode":"27804",
    "sg:province":"NC",
    "sg:tags":[
        "pizza"
    ],
    "wof:name":"Italian Pizzeria",
    "wof:placetype":"venue"
},
  "geometry": {"coordinates":[-77.82096799999999,35.955442],"type":"Point"}
}