{
  "type": "Feature",
  "properties": {
    "iso:country":"US",
    "sg:address":"10837 Wilklee Dr",
    "sg:city":"Charlotte",
    "sg:classifiers":[
        {
            "category":"Building & Trades",
            "subcategory":"Construction",
            "type":"Services"
        }
    ],
    "sg:phone":"+1 704 540 6306",
    "sg:postcode":"28277",
    "sg:province":"NC",
    "sg:tags":[
        "hanging",
        "contractor"
    ],
    "wof:name":"Mj Painting Co",
    "wof:placetype":"venue"
},
  "geometry": {"coordinates":[-80.84205300000001,35.033192],"type":"Point"}
}