{
  "type": "Feature",
  "properties": {
    "addr:full":"7583 State Hwy 50 N Angier NC 27501",
    "addr:housenumber":"7583",
    "addr:postcode":"27501",
    "addr:street":"State Hwy 50 N",
    "iso:country":"US",
    "sg:address":"7583 State Hwy 50 N",
    "sg:city":"Angier",
    "sg:phone":"+1 919 894 4729",
    "sg:postcode":"27501",
    "sg:province":"NC",
    "sg:tags":[
        "tobacco",
        "farm",
        "crop",
        "field",
        "soybean",
        "cotton"
    ],
    "wof:name":"Benson Randal",
    "wof:placetype":"venue"
},
  "geometry": {"coordinates":[-78.557356,35.473883],"type":"Point"}
}