{
  "type": "Feature",
  "properties": {
    "addr:full":"2881 Shady Lane Ave Concord NC 28027",
    "addr:housenumber":"2881",
    "addr:postcode":"28027",
    "addr:street":"Shady Lane Ave",
    "iso:country":"US",
    "sg:address":"2881 Shady Lane Ave",
    "sg:city":"Concord",
    "sg:classifiers":[
        {
            "category":"Building & Trades",
            "subcategory":"Construction",
            "type":"Services"
        }
    ],
    "sg:phone":"+1 704 788 9725",
    "sg:postcode":"28027",
    "sg:province":"NC",
    "sg:tags":[
        "house"
    ],
    "wof:name":"Work Wright Construction",
    "wof:placetype":"venue"
},
  "geometry": {"coordinates":[-80.62134500000001,35.44924],"type":"Point"}
}