{
  "type": "Feature",
  "properties": {
    "iso:country":"US",
    "sg:address":"107 Kenmore Dr",
    "sg:city":"Pineville",
    "sg:classifiers":[
        {
            "category":"Professional",
            "subcategory":"Accounting & Tax Preparation",
            "type":"Services"
        }
    ],
    "sg:phone":"+1 704 889 4166",
    "sg:postcode":"28134",
    "sg:province":"NC",
    "sg:tags":[
        "accountant"
    ],
    "wof:name":"J B White",
    "wof:placetype":"venue"
},
  "geometry": {"coordinates":[-80.88952399999999,35.078883],"type":"Point"}
}