{
  "type": "Feature",
  "properties": {
    "addr:full":"209 E Main St Carrboro NC 27510",
    "addr:housenumber":"209",
    "addr:postcode":"27510",
    "addr:street":"E Main St",
    "iso:country":"US",
    "sg:address":"209 E Main St",
    "sg:city":"Carrboro",
    "sg:classifiers":[
        {
            "category":"Utilities",
            "type":"Services"
        }
    ],
    "sg:phone":"+1 919 932 1590",
    "sg:postcode":"27510",
    "sg:province":"NC",
    "sg:tags":[
        "cleanup"
    ],
    "wof:name":"Terraquest Envmtl Cons PC",
    "wof:placetype":"venue"
},
  "geometry": {"coordinates":[-79.069678,35.910529],"type":"Point"}
}