{
  "type": "Feature",
  "properties": {
    "addr:full":"6614 Wanderview Ln Charlotte NC 28214",
    "addr:housenumber":"6614",
    "addr:postcode":"28214",
    "addr:street":"Wanderview Ln",
    "iso:country":"US",
    "sg:address":"6614 Wanderview Ln",
    "sg:city":"Charlotte",
    "sg:classifiers":[
        {
            "category":"Retail",
            "subcategory":"Auto Repair",
            "type":"Services"
        }
    ],
    "sg:phone":"+1   ",
    "sg:postcode":"28214",
    "sg:province":"NC",
    "sg:tags":[
        "mobile",
        "automotive",
        "glass",
        "replacement"
    ],
    "wof:name":"Brads Auto Glass",
    "wof:placetype":"venue"
},
  "geometry": {"coordinates":[-80.94293999999999,35.267894],"type":"Point"}
}