{
  "type": "Feature",
  "properties": {
    "addr:full":"9229 Lawyers Rd Charlotte NC 28227",
    "addr:housenumber":"9229",
    "addr:postcode":"28227",
    "addr:street":"Lawyers Rd",
    "iso:country":"US",
    "sg:address":"9229 Lawyers Rd",
    "sg:city":"Charlotte",
    "sg:classifiers":[
        {
            "category":"Personal",
            "subcategory":"Beauty Salon",
            "type":"Services"
        }
    ],
    "sg:phone":"+1 704 573 1450",
    "sg:postcode":"28227",
    "sg:province":"NC",
    "sg:tags":[
        "manicuring"
    ],
    "wof:name":"Jazzy Nails",
    "wof:placetype":"venue"
},
  "geometry": {"coordinates":[-80.686881,35.185482],"type":"Point"}
}