{
  "type": "Feature",
  "properties": {
    "iso:country":"US",
    "sg:address":"23 W 2nd St",
    "sg:city":"Lexington",
    "sg:classifiers":[
        {
            "category":"Professional",
            "subcategory":"Lawyer & Legal Services",
            "type":"Services"
        }
    ],
    "sg:phone":"+1   ",
    "sg:postcode":"27292",
    "sg:province":"NC",
    "wof:name":"Benjamin G Philpott",
    "wof:placetype":"venue"
},
  "geometry": {"coordinates":[-80.253221,35.826005],"type":"Point"}
}