{
  "type": "Feature",
  "properties": {
    "addr:full":"408 Gresham Ave Durham NC 27704",
    "addr:housenumber":"408",
    "addr:postcode":"27704",
    "addr:street":"Gresham Ave",
    "iso:country":"US",
    "sg:address":"408 Gresham Ave",
    "sg:city":"Durham",
    "sg:classifiers":[
        {
            "category":"Building & Trades",
            "subcategory":"Plumbing",
            "type":"Services"
        }
    ],
    "sg:phone":"+1 919 933 4665",
    "sg:postcode":"27704",
    "sg:province":"NC",
    "sg:tags":[
        "conditioning",
        "air",
        "system",
        "contractor"
    ],
    "wof:name":"Sparrow Heating & Air Conditio",
    "wof:placetype":"venue"
},
  "geometry": {"coordinates":[-78.896308,36.025157],"type":"Point"}
}