{
  "type": "Feature",
  "properties": {
    "addr:full":"4321 Christian Light Rd Fuquay Varina NC 27526",
    "addr:housenumber":"4321",
    "addr:postcode":"27526",
    "addr:street":"Christian Light Rd",
    "iso:country":"US",
    "sg:address":"4321 Christian Light Rd",
    "sg:city":"Fuquay Varina",
    "sg:classifiers":[
        {
            "category":"Building & Trades",
            "subcategory":"Construction",
            "type":"Services"
        }
    ],
    "sg:phone":"+1 919 552 3124",
    "sg:postcode":"27526",
    "sg:province":"NC",
    "sg:tags":[
        "insulation",
        "heat",
        "contractor"
    ],
    "wof:name":"Dean's Insulation Co",
    "wof:placetype":"venue"
},
  "geometry": {"coordinates":[-78.87976500000001,35.493322],"type":"Point"}
}