{
  "type": "Feature",
  "properties": {
    "iso:country":"US",
    "sg:address":"1004 Antler Ct",
    "sg:city":"Apex",
    "sg:classifiers":[
        {
            "category":"Professional",
            "subcategory":"Computer Services",
            "type":"Services"
        }
    ],
    "sg:phone":"+1   ",
    "sg:postcode":"27502",
    "sg:province":"NC",
    "sg:tags":[
        "datum"
    ],
    "wof:name":"Web Structures Inc",
    "wof:placetype":"venue"
},
  "geometry": {"coordinates":[-78.888513,35.733885],"type":"Point"}
}