{
  "type": "Feature",
  "properties": {
    "iso:country":"US",
    "sg:address":"4519 Hartland Rd",
    "sg:city":"Lenoir",
    "sg:classifiers":[
        {
            "category":"Manufacturing",
            "subcategory":"Furniture",
            "type":"Manufacturing & Wholesale Goods"
        }
    ],
    "sg:phone":"+1 828 754 0081",
    "sg:postcode":"28645",
    "sg:province":"NC",
    "wof:name":"Mc Creary Woodworking",
    "wof:placetype":"venue"
},
  "geometry": {"coordinates":[-81.607812,35.866207],"type":"Point"}
}