{
  "type": "Feature",
  "properties": {
    "iso:country":"US",
    "sg:address":"628 Confederate Rd",
    "sg:city":"Sneads Ferry",
    "sg:classifiers":[
        {
            "category":"Building & Trades",
            "subcategory":"Landscaping Services",
            "type":"Services"
        }
    ],
    "sg:phone":"+1 910 327 2006",
    "sg:postcode":"28460",
    "sg:province":"NC",
    "sg:tags":[
        "lawn",
        "maintenance",
        "grounds"
    ],
    "wof:name":"Sneads Ferry Bushhog Svc",
    "wof:placetype":"venue"
},
  "geometry": {"coordinates":[-77.362801,34.550187],"type":"Point"}
}