{
  "type": "Feature",
  "properties": {
    "addr:full":"112 Meadowbrook Dr King NC 27021",
    "addr:housenumber":"112",
    "addr:postcode":"27021",
    "addr:street":"Meadowbrook Dr",
    "iso:country":"US",
    "sg:address":"112 Meadowbrook Dr",
    "sg:city":"King",
    "sg:classifiers":[
        {
            "category":"Building & Trades",
            "subcategory":"Plumbing",
            "type":"Services"
        }
    ],
    "sg:phone":"+1 336 983 5976",
    "sg:postcode":"27021",
    "sg:province":"NC",
    "sg:tags":[
        "plumbing",
        "contractor"
    ],
    "wof:name":"Clayton's Plumbing",
    "wof:placetype":"venue"
},
  "geometry": {"coordinates":[-80.36245,36.275807],"type":"Point"}
}