{
  "type": "Feature",
  "properties": {
    "addr:full":"117 Union St S Concord NC 28025",
    "addr:housenumber":"117",
    "addr:postcode":"28025",
    "addr:street":"Union St S",
    "iso:country":"US",
    "sg:address":"117 Union St S",
    "sg:city":"Concord",
    "sg:classifiers":[
        {
            "category":"Food & Beverages",
            "subcategory":"Specialty",
            "type":"Retail Goods"
        }
    ],
    "sg:phone":"+1 704 786 3559",
    "sg:postcode":"28025",
    "sg:province":"NC",
    "sg:tags":[
        "tea",
        "coffee"
    ],
    "wof:name":"Java Hutt",
    "wof:placetype":"venue"
},
  "geometry": {"coordinates":[-80.57875799999999,35.408446],"type":"Point"}
}