{
  "type": "Feature",
  "properties": {
    "addr:full":"6317 Lisbon Rd Clarkton NC 28433",
    "addr:housenumber":"6317",
    "addr:postcode":"28433",
    "addr:street":"Lisbon Rd",
    "iso:country":"US",
    "sg:address":"6317 Lisbon Rd",
    "sg:city":"Clarkton",
    "sg:classifiers":[
        {
            "category":"Government",
            "subcategory":"Fire Station",
            "type":"Public Place"
        }
    ],
    "sg:phone":"+1 910 645 6360",
    "sg:postcode":"28433",
    "sg:province":"NC",
    "sg:tags":[
        "department"
    ],
    "wof:name":"Lisbon Fire Dept",
    "wof:placetype":"venue"
},
  "geometry": {"coordinates":[-78.55761200000001,34.520117],"type":"Point"}
}