{
  "type": "Feature",
  "properties": {
    "addr:full":"3590 Georgia Rd Franklin NC 28734",
    "addr:housenumber":"3590",
    "addr:postcode":"nc 28734",
    "addr:street":"Georgia Rd",
    "iso:country":"US",
    "sg:address":"3590 Georgia Rd",
    "sg:city":"Franklin",
    "sg:classifiers":[
        {
            "category":"Retail",
            "subcategory":"Repair Shop",
            "type":"Services"
        }
    ],
    "sg:phone":"+1 828 369 7100",
    "sg:postcode":"28734",
    "sg:province":"NC",
    "sg:tags":[
        "scooter",
        "motorcycle",
        "motor"
    ],
    "wof:name":"Smith Power Sports",
    "wof:placetype":"venue"
},
  "geometry": {"coordinates":[-83.382085,35.023091],"type":"Point"}
}