{
  "type": "Feature",
  "properties": {
    "addr:full":"401 S Main St China Grove NC 28023",
    "addr:housenumber":"401",
    "addr:postcode":"28023",
    "addr:street":"S Main St",
    "iso:country":"US",
    "sg:address":"401 S Main St",
    "sg:city":"China Grove",
    "sg:classifiers":[
        {
            "category":"Real Estate",
            "subcategory":"Real Estate Agent",
            "type":"Services"
        }
    ],
    "sg:phone":"+1 704 857 7570",
    "sg:postcode":"28023",
    "sg:province":"NC",
    "wof:name":"Option B Inc",
    "wof:placetype":"venue"
},
  "geometry": {"coordinates":[-80.58236100000001,35.56813],"type":"Point"}
}