{
  "type": "Feature",
  "properties": {
    "addr:full":"1568 Baton School Rd Granite Falls NC 28630",
    "addr:housenumber":"1568",
    "addr:postcode":"28630",
    "addr:street":"Baton School Rd",
    "iso:country":"US",
    "sg:address":"1568 Baton School Rd",
    "sg:city":"Granite Falls",
    "sg:classifiers":[
        {
            "category":"Freight",
            "type":"Transportation"
        }
    ],
    "sg:phone":"+1 828 728 8537",
    "sg:postcode":"28630",
    "sg:province":"NC",
    "sg:tags":[
        "operator",
        "trucking"
    ],
    "wof:name":"Walkers Back Hoe and Tranching",
    "wof:placetype":"venue"
},
  "geometry": {"coordinates":[-81.547558,35.8024],"type":"Point"}
}