{
  "type": "Feature",
  "properties": {
    "addr:full":"2507 Beechridge Rd Raleigh NC 27608",
    "addr:housenumber":"2507",
    "addr:postcode":"27608",
    "addr:street":"Beechridge Rd",
    "iso:country":"US",
    "sg:address":"2507 Beechridge Rd",
    "sg:city":"Raleigh",
    "sg:classifiers":[
        {
            "category":"Building & Trades",
            "subcategory":"Construction",
            "type":"Services"
        }
    ],
    "sg:phone":"+1 919 787 7889",
    "sg:postcode":"27608",
    "sg:province":"NC",
    "sg:tags":[
        "house",
        "equipment"
    ],
    "wof:name":"Matthews Home Repair & SE",
    "wof:placetype":"venue"
},
  "geometry": {"coordinates":[-78.640494,35.812067],"type":"Point"}
}