{
  "type": "Feature",
  "properties": {
    "addr:full":"6701 Pargo Rd Charlotte NC 28216",
    "addr:housenumber":"6701",
    "addr:postcode":"28216",
    "addr:street":"Pargo Rd",
    "iso:country":"US",
    "sg:address":"6701 Pargo Rd",
    "sg:city":"Charlotte",
    "sg:classifiers":[
        {
            "category":"Wholesale",
            "subcategory":"Medical Equipment & Supplies",
            "type":"Manufacturing & Wholesale Goods"
        }
    ],
    "sg:phone":"+1 704 372 2240",
    "sg:postcode":"28216",
    "sg:province":"NC",
    "wof:name":"Pss Winchester",
    "wof:placetype":"venue"
},
  "geometry": {"coordinates":[-80.904005,35.323472],"type":"Point"}
}