{
  "type": "Feature",
  "properties": {
    "addr:full":"401 Hope Mills Rd Fayetteville NC 28304",
    "addr:housenumber":"401",
    "addr:postcode":"28304",
    "addr:street":"Hope Mills Rd",
    "iso:country":"US",
    "sg:address":"401 Hope Mills Rd",
    "sg:city":"Fayetteville",
    "sg:classifiers":[
        {
            "category":"Retail",
            "subcategory":"Laundry & Dry Cleaning",
            "type":"Services"
        }
    ],
    "sg:phone":"+1   ",
    "sg:postcode":"28304",
    "sg:province":"NC",
    "sg:tags":[
        "drycleaning",
        "plant"
    ],
    "wof:name":"Al Glamorama",
    "wof:placetype":"venue"
},
  "geometry": {"coordinates":[-78.96096799999999,35.038042],"type":"Point"}
}