{
  "type": "Feature",
  "properties": {
    "addr:full":"142 Joel Wright Dr Hendersonville NC 28792",
    "addr:housenumber":"142",
    "addr:postcode":"28792",
    "addr:street":"Joel Wright Dr",
    "iso:country":"US",
    "sg:address":"142 Joel Wright Dr",
    "sg:city":"Hendersonville",
    "sg:classifiers":[
        {
            "category":"Home & Garden",
            "subcategory":"Household Appliances",
            "type":"Retail Goods"
        }
    ],
    "sg:phone":"+1 828 692 8870",
    "sg:postcode":"28792",
    "sg:province":"NC",
    "sg:tags":[
        "machine",
        "sewing"
    ],
    "wof:name":"My Quilt Shoppe Inc",
    "wof:placetype":"venue"
},
  "geometry": {"coordinates":[-82.45682600000001,35.306108],"type":"Point"}
}