{
  "type": "Feature",
  "properties": {
    "iso:country":"US",
    "sg:address":"104 Frontier Ct",
    "sg:city":"Cary",
    "sg:classifiers":[
        {
            "category":"Professional",
            "subcategory":"Computer Services",
            "type":"Services"
        }
    ],
    "sg:phone":"+1   ",
    "sg:postcode":"27513",
    "sg:province":"NC",
    "sg:tags":[
        "prepackaged",
        "software"
    ],
    "wof:name":"Guzinta Software Inc",
    "wof:placetype":"venue"
},
  "geometry": {"coordinates":[-78.833251,35.781301],"type":"Point"}
}