{
  "type": "Feature",
  "properties": {
    "addr:full":"5930 S Rocky River Rd Monroe NC 28112",
    "addr:housenumber":"5930",
    "addr:postcode":"28112",
    "addr:street":"S Rocky River Rd",
    "iso:country":"US",
    "sg:address":"5930 S Rocky River Rd",
    "sg:city":"Monroe",
    "sg:classifiers":[
        {
            "category":"Retail",
            "subcategory":"Repair Shop",
            "type":"Services"
        }
    ],
    "sg:phone":"+1   ",
    "sg:postcode":"28112",
    "sg:province":"NC",
    "wof:name":"Xtreme Cycles",
    "wof:placetype":"venue"
},
  "geometry": {"coordinates":[-80.618179,34.861268],"type":"Point"}
}