{
  "type": "Feature",
  "properties": {
    "iso:country":"US",
    "sg:address":"1033 E 10th St",
    "sg:city":"Roanoke Rapids",
    "sg:classifiers":[
        {
            "category":"Personal",
            "subcategory":"Beauty Salon",
            "type":"Services"
        }
    ],
    "sg:phone":"+1   ",
    "sg:postcode":"27870",
    "sg:province":"NC",
    "sg:tags":[
        "shop"
    ],
    "wof:name":"Essential Beauty Salon",
    "wof:placetype":"venue"
},
  "geometry": {"coordinates":[-77.648113,36.452408],"type":"Point"}
}