{
  "type": "Feature",
  "properties": {
    "iso:country":"US",
    "sg:address":"108 Moose Dr",
    "sg:city":"Shelby",
    "sg:classifiers":[
        {
            "category":"Real Estate",
            "subcategory":"Real Estate Operator",
            "type":"Services"
        }
    ],
    "sg:phone":"+1 704 480 1793",
    "sg:postcode":"28150",
    "sg:province":"NC",
    "sg:tags":[
        "mobile",
        "home",
        "site"
    ],
    "wof:name":"Lakeside Mobile Pk",
    "wof:placetype":"venue"
},
  "geometry": {"coordinates":[-81.46325400000001,35.280498],"type":"Point"}
}