{
  "type": "Feature",
  "properties": {
    "iso:country":"US",
    "sg:address":"918 West Ave NW",
    "sg:city":"Lenoir",
    "sg:classifiers":[
        {
            "category":"Professional",
            "subcategory":"Management & Consulting",
            "type":"Services"
        }
    ],
    "sg:phone":"+1 828 758 2005",
    "sg:postcode":"28645",
    "sg:province":"NC",
    "sg:tags":[
        "marketing",
        "consultant"
    ],
    "wof:name":"Mulberry Group Inc",
    "wof:placetype":"venue"
},
  "geometry": {"coordinates":[-81.54069800000001,35.91454],"type":"Point"}
}