{
  "type": "Feature",
  "properties": {
    "addr:full":"1009 S Columbia St Chapel Hill NC 27514",
    "addr:housenumber":"1009",
    "addr:postcode":"27514",
    "addr:street":"S Columbia St",
    "iso:country":"US",
    "sg:address":"1009 S Columbia St",
    "sg:city":"Chapel Hill",
    "sg:classifiers":[
        {
            "category":"Food & Beverages",
            "subcategory":"Liquor & Beverages",
            "type":"Retail Goods"
        },
        {
            "category":"Food & Beverages",
            "subcategory":"Bakery",
            "type":"Retail Goods"
        },
        {
            "category":"Food & Beverages",
            "subcategory":"Groceries & Convenience Stores",
            "type":"Retail Goods"
        }
    ],
    "sg:phone":"+1 919 942 4897",
    "sg:postcode":"27514",
    "sg:province":"NC",
    "sg:tags":[
        "beer",
        "sandwich",
        "spirit",
        "wine"
    ],
    "sg:website":"merrittsstoreandgrill.com",
    "wof:name":"Merritt's Store & Grill",
    "wof:placetype":"venue"
},
  "geometry": {"coordinates":[-79.05819700000001,35.896702],"type":"Point"}
}