{
  "type": "Feature",
  "properties": {
    "iso:country":"US",
    "sg:address":"6005 Bridgersville Rd",
    "sg:city":"Elm City",
    "sg:classifiers":[
        {
            "category":"Personal",
            "subcategory":"Beauty Salon",
            "type":"Services"
        }
    ],
    "sg:phone":"+1   ",
    "sg:postcode":"27822",
    "sg:province":"NC",
    "sg:tags":[
        "shop"
    ],
    "wof:name":"Anns Unique Hair Fashions",
    "wof:placetype":"venue"
},
  "geometry": {"coordinates":[-77.81174799999999,35.790293],"type":"Point"}
}