{
  "type": "Feature",
  "properties": {
    "iso:country":"US",
    "sg:address":"5900 Turkey Hwy",
    "sg:city":"Turkey",
    "sg:classifiers":[
        {
            "category":"Manufacturing",
            "subcategory":"Food",
            "type":"Manufacturing & Wholesale Goods"
        },
        {
            "category":"Manufacturing",
            "subcategory":"Tools & Machinery",
            "type":"Manufacturing & Wholesale Goods"
        }
    ],
    "sg:phone":"+1 910 596 0028",
    "sg:postcode":"28393",
    "sg:province":"NC",
    "sg:tags":[
        "packaging",
        "canned",
        "canning",
        "mfg"
    ],
    "sg:website":"www.allencanning.com",
    "wof:name":"Allen Canning Company",
    "wof:placetype":"venue"
},
  "geometry": {"coordinates":[-78.21829700000001,34.985523],"type":"Point"}
}