{
  "type": "Feature",
  "properties": {
    "iso:country":"US",
    "sg:address":"211 Sycamore St",
    "sg:city":"Oxford",
    "sg:classifiers":[
        {
            "category":"Social Services",
            "subcategory":"Child Care",
            "type":"Services"
        }
    ],
    "sg:phone":"+1   ",
    "sg:postcode":"27565",
    "sg:province":"NC",
    "sg:tags":[
        "day"
    ],
    "wof:name":"Mother Goose Kindergarten",
    "wof:placetype":"venue"
},
  "geometry": {"coordinates":[-78.588824,36.3074],"type":"Point"}
}