{
  "type": "Feature",
  "properties": {
    "iso:country":"US",
    "sg:address":"500 Shore Acres Rd",
    "sg:city":"Salisbury",
    "sg:classifiers":[
        {
            "category":"Freight",
            "type":"Transportation"
        }
    ],
    "sg:phone":"+1 704 637 3566",
    "sg:postcode":"28146",
    "sg:province":"NC",
    "sg:tags":[
        "operator",
        "trucking"
    ],
    "wof:name":"James Hodgson",
    "wof:placetype":"venue"
},
  "geometry": {"coordinates":[-80.336027,35.603128],"type":"Point"}
}