{
  "type": "Feature",
  "properties": {
    "addr:full":"652 N Main St Sparta NC 28675",
    "addr:housenumber":"652",
    "addr:postcode":"28675",
    "addr:street":"N Main St",
    "iso:country":"US",
    "sg:address":"652 N Main St",
    "sg:city":"Sparta",
    "sg:classifiers":[
        {
            "category":"Home & Garden",
            "subcategory":"Building Materials",
            "type":"Retail Goods"
        }
    ],
    "sg:phone":"+1 336 372 4000",
    "sg:postcode":"28675",
    "sg:province":"NC",
    "wof:name":"Blevins Building Supply",
    "wof:placetype":"venue"
},
  "geometry": {"coordinates":[-81.128328,36.50976],"type":"Point"}
}