{
  "type": "Feature",
  "properties": {
    "iso:country":"US",
    "sg:address":"614 Old Hwy 601",
    "sg:city":"Mount Airy",
    "sg:classifiers":[
        {
            "category":"Organizations",
            "subcategory":"Religious Organization",
            "type":"Services"
        }
    ],
    "sg:phone":"+1 336 786 6310",
    "sg:postcode":"27030",
    "sg:province":"NC",
    "sg:tags":[
        "baptist",
        "christian",
        "school",
        "church"
    ],
    "wof:name":"White Plains Christian School",
    "wof:placetype":"venue"
},
  "geometry": {"coordinates":[-80.62839099999999,36.453711],"type":"Point"}
}