{
  "type": "Feature",
  "properties": {
    "iso:country":"US",
    "sg:address":"4724 Stantonsburg Rd",
    "sg:city":"Greenville",
    "sg:classifiers":[
        {
            "category":"Food & Beverages",
            "subcategory":"Groceries & Convenience Stores",
            "type":"Retail Goods"
        }
    ],
    "sg:phone":"+1 252 830 0800",
    "sg:postcode":"27834",
    "sg:province":"NC",
    "wof:name":"GSG Quick Stop Inc",
    "wof:placetype":"venue"
},
  "geometry": {"coordinates":[-77.48332000000001,35.604828],"type":"Point"}
}