{
  "type": "Feature",
  "properties": {
    "iso:country":"US",
    "sg:address":"321 E Hargett St",
    "sg:city":"Raleigh",
    "sg:classifiers":[
        {
            "category":"Social Services",
            "subcategory":"Job Training",
            "type":"Services"
        }
    ],
    "sg:phone":"+1 919 834 0504",
    "sg:postcode":"27601",
    "sg:province":"NC",
    "sg:tags":[
        "used",
        "merchandise",
        "rehabilitation",
        "store"
    ],
    "wof:name":"Goodwill Industries",
    "wof:placetype":"venue"
},
  "geometry": {"coordinates":[-78.63360299999999,35.778136],"type":"Point"}
}