{
  "type": "Feature",
  "properties": {
    "iso:country":"US",
    "sg:address":"1108B Nowell Rd",
    "sg:city":"Raleigh",
    "sg:classifiers":[
        {
            "category":"Building & Trades",
            "subcategory":"Landscaping Services",
            "type":"Services"
        },
        {
            "category":"Building & Trades",
            "subcategory":"Pest Control",
            "type":"Services"
        }
    ],
    "sg:phone":"+1 919 851 5135",
    "sg:postcode":"27607",
    "sg:province":"NC",
    "sg:tags":[
        "gardener"
    ],
    "sg:website":"raleigh-durham.mosquitosquad.com/",
    "wof:name":"Mosquito Squad of Raleigh-Durham",
    "wof:placetype":"venue"
},
  "geometry": {"coordinates":[-78.734996,35.795623],"type":"Point"}
}