{
  "type": "Feature",
  "properties": {
    "iso:country":"US",
    "sg:address":"482 Esclip Rd",
    "sg:city":"Elizabeth City",
    "sg:classifiers":[
        {
            "category":"Retail",
            "subcategory":"Auto Repair",
            "type":"Services"
        }
    ],
    "sg:phone":"+1   ",
    "sg:postcode":"27909",
    "sg:province":"NC",
    "sg:tags":[
        "general"
    ],
    "wof:name":"Murray S Auto & Truck Service",
    "wof:placetype":"venue"
},
  "geometry": {"coordinates":[-76.16182499999999,36.170407],"type":"Point"}
}