{
  "type": "Feature",
  "properties": {
    "iso:country":"US",
    "sg:address":"1807 Garner Rd",
    "sg:city":"Raleigh",
    "sg:classifiers":[
        {
            "category":"Shopping",
            "subcategory":"Clothing, Apparel, & Fashions",
            "type":"Retail Goods"
        }
    ],
    "sg:phone":"+1 919 828 1373",
    "sg:postcode":"27610",
    "sg:province":"NC",
    "wof:name":"E Z Jeans & Urban Fashions",
    "wof:placetype":"venue"
},
  "geometry": {"coordinates":[-78.631221,35.756125],"type":"Point"}
}