{
  "type": "Feature",
  "properties": {
    "addr:full":"221 S West Ave Ayden NC 28513",
    "addr:housenumber":"221",
    "addr:postcode":"28513",
    "addr:street":"S West Ave",
    "iso:country":"US",
    "sg:address":"221 S West Ave",
    "sg:city":"Ayden",
    "sg:classifiers":[
        {
            "category":"Social Services",
            "type":"Services"
        }
    ],
    "sg:phone":"+1   ",
    "sg:postcode":"28513",
    "sg:province":"NC",
    "wof:name":"North Carolina Probation Off",
    "wof:placetype":"venue"
},
  "geometry": {"coordinates":[-77.416358,35.471865],"type":"Point"}
}