{
  "type": "Feature",
  "properties": {
    "addr:full":"1224 N Norwood St Wallace NC 28466",
    "addr:housenumber":"1224",
    "addr:postcode":"28466",
    "addr:street":"N Norwood St",
    "iso:country":"US",
    "sg:address":"1224 N Norwood St",
    "sg:city":"Wallace",
    "sg:classifiers":[
        {
            "category":"Shopping",
            "subcategory":"Discount & Variety Stores",
            "type":"Retail Goods"
        }
    ],
    "sg:phone":"+1 910 285 9334",
    "sg:postcode":"28466",
    "sg:province":"NC",
    "wof:name":"Dollar General",
    "wof:placetype":"venue"
},
  "geometry": {"coordinates":[-77.99763900000001,34.748896],"type":"Point"}
}