{
  "type": "Feature",
  "properties": {
    "iso:country":"US",
    "sg:address":"3704 Alliance Dr",
    "sg:city":"Greensboro",
    "sg:classifiers":[
        {
            "category":"Manufacturing",
            "subcategory":"Furniture",
            "type":"Manufacturing & Wholesale Goods"
        },
        {
            "category":"Wholesale",
            "subcategory":"Chemicals & Plastics",
            "type":"Manufacturing & Wholesale Goods"
        }
    ],
    "sg:phone":"+1 336 346 1839",
    "sg:postcode":"27407",
    "sg:province":"NC",
    "sg:tags":[
        "specialty",
        "mfg"
    ],
    "wof:name":"Endless Plastics LLC",
    "wof:placetype":"venue"
},
  "geometry": {"coordinates":[-79.87285799999999,36.055583],"type":"Point"}
}