{
  "type": "Feature",
  "properties": {
    "iso:country":"US",
    "sg:address":"900 Aviation Parkway",
    "sg:city":"Morrisville",
    "sg:classifiers":[
        {
            "category":"Autos & Motor Vehicles",
            "subcategory":"Automobile Sales",
            "type":"Retail Goods"
        },
        {
            "category":"Airline",
            "type":"Transportation"
        },
        {
            "category":"Travel",
            "subcategory":"Travel Agent",
            "type":"Entertainment"
        }
    ],
    "sg:phone":"+1 919 244 1608",
    "sg:postcode":"27560",
    "sg:province":"NC",
    "sg:tags":[
        "shuttle",
        "airport",
        "limo"
    ],
    "sg:website":"www.limousineraleigh.com",
    "wof:name":"Airport Transportation Raleigh",
    "wof:placetype":"venue"
},
  "geometry": {"coordinates":[-78.80892799999999,35.837429],"type":"Point"}
}