{
  "type": "Feature",
  "properties": {
    "addr:full":"258 Boundary St Waynesville NC 28786",
    "addr:housenumber":"258",
    "addr:postcode":"28786",
    "addr:street":"Boundary St",
    "iso:country":"US",
    "sg:address":"258 Boundary St",
    "sg:city":"Waynesville",
    "sg:classifiers":[
        {
            "category":"Professional",
            "subcategory":"Accounting & Tax Preparation",
            "type":"Services"
        }
    ],
    "sg:phone":"+1 828 456 3190",
    "sg:postcode":"28786",
    "sg:province":"NC",
    "sg:tags":[
        "accountant",
        "auditing",
        "bookkeeping"
    ],
    "wof:name":"Independent Accountign Svcs",
    "wof:placetype":"venue"
},
  "geometry": {"coordinates":[-82.98621,35.495289],"type":"Point"}
}