{
  "type": "Feature",
  "properties": {
    "iso:country":"US",
    "sg:address":"120 N Main Ave",
    "sg:city":"Newton",
    "sg:classifiers":[
        {
            "category":"Shopping",
            "subcategory":"Computers & Home Electronics",
            "type":"Retail Goods"
        }
    ],
    "sg:phone":"+1 828 466 3648",
    "sg:postcode":"28658",
    "sg:province":"NC",
    "sg:tags":[
        "equipment",
        "satellite",
        "system"
    ],
    "wof:name":"White's Satellite Svc",
    "wof:placetype":"venue"
},
  "geometry": {"coordinates":[-81.222078,35.664259],"type":"Point"}
}