{
  "type": "Feature",
  "properties": {
    "addr:full":"617 N Center St Hickory NC 28601",
    "addr:housenumber":"617",
    "addr:postcode":"28601",
    "addr:street":"N Center St",
    "iso:country":"US",
    "sg:address":"617 N Center St",
    "sg:city":"Hickory",
    "sg:classifiers":[
        {
            "category":"Professional",
            "subcategory":"Computer Services",
            "type":"Services"
        }
    ],
    "sg:phone":"+1   ",
    "sg:postcode":"28601",
    "sg:province":"NC",
    "sg:tags":[
        "datum"
    ],
    "wof:name":"P Edwards Leslie",
    "wof:placetype":"venue"
},
  "geometry": {"coordinates":[-81.337692,35.741171],"type":"Point"}
}