{
  "type": "Feature",
  "properties": {
    "iso:country":"US",
    "sg:address":"6932 Market St",
    "sg:city":"Wilmington",
    "sg:classifiers":[
        {
            "category":"Restaurant",
            "type":"Food & Drink"
        }
    ],
    "sg:phone":"+1 910 794 9013",
    "sg:postcode":"28411",
    "sg:province":"NC",
    "sg:tags":[
        "parlor",
        "ice",
        "cream"
    ],
    "wof:name":"Carvel Ice Cream & Bakery",
    "wof:placetype":"venue"
},
  "geometry": {"coordinates":[-77.82911199999999,34.262329],"type":"Point"}
}