{
  "type": "Feature",
  "properties": {
    "iso:country":"US",
    "sg:address":"5552 US Hwy 70",
    "sg:city":"Goldsboro",
    "sg:classifiers":[
        {
            "category":"Professional",
            "subcategory":"Business Services",
            "type":"Services"
        }
    ],
    "sg:phone":"+1   ",
    "sg:postcode":"27534",
    "sg:province":"NC",
    "wof:name":"Olde Country Store",
    "wof:placetype":"venue"
},
  "geometry": {"coordinates":[-77.894991,35.337316],"type":"Point"}
}