{
  "type": "Feature",
  "properties": {
    "addr:full":"605 Sugar Hill Rd Lawndale NC 28090",
    "addr:housenumber":"605",
    "addr:postcode":"28090",
    "addr:street":"Sugar Hill Rd",
    "iso:country":"US",
    "sg:address":"605 Sugar Hill Rd",
    "sg:city":"Lawndale",
    "sg:classifiers":[
        {
            "category":"Health Services",
            "subcategory":"Nursing And Care Facility",
            "type":"Services"
        }
    ],
    "sg:phone":"+1 704 538 0526",
    "sg:postcode":"28090",
    "sg:province":"NC",
    "wof:name":"Paula S Family Carehome",
    "wof:placetype":"venue"
},
  "geometry": {"coordinates":[-81.466567,35.437422],"type":"Point"}
}