{
  "type": "Feature",
  "properties": {
    "addr:full":"409 4th St SW Hickory NC 28602",
    "addr:housenumber":"409",
    "addr:postcode":"28602",
    "addr:street":"4Th St Sw",
    "iso:country":"US",
    "sg:address":"409 4th St SW",
    "sg:city":"Hickory",
    "sg:classifiers":[
        {
            "category":"Insurance",
            "subcategory":"Insurance Agent",
            "type":"Services"
        }
    ],
    "sg:phone":"+1 828 322 4010",
    "sg:postcode":"28602",
    "sg:province":"NC",
    "wof:name":"Tri County Insurance",
    "wof:placetype":"venue"
},
  "geometry": {"coordinates":[-81.344796,35.725323],"type":"Point"}
}