{
  "type": "Feature",
  "properties": {
    "iso:country":"US",
    "sg:address":"30 Brookside Dr",
    "sg:city":"Hendersonville",
    "sg:classifiers":[
        {
            "category":"Building & Trades",
            "subcategory":"Construction",
            "type":"Services"
        }
    ],
    "sg:phone":"+1 828 693 0439",
    "sg:postcode":"28792",
    "sg:province":"NC",
    "sg:tags":[
        "roofing",
        "contractor"
    ],
    "wof:name":"Doug Limeberry Roofing Co",
    "wof:placetype":"venue"
},
  "geometry": {"coordinates":[-82.469148,35.380677],"type":"Point"}
}