{
  "type": "Feature",
  "properties": {
    "addr:full":"1012 Henderson Dr Jacksonville NC 28540",
    "addr:housenumber":"1012",
    "addr:postcode":"28540",
    "addr:street":"Henderson Dr",
    "iso:country":"US",
    "sg:address":"1012 Henderson Dr",
    "sg:city":"Jacksonville",
    "sg:classifiers":[
        {
            "category":"Real Estate",
            "subcategory":"Real Estate Agent",
            "type":"Services"
        }
    ],
    "sg:phone":"+1 910 355 2500",
    "sg:postcode":"28540",
    "sg:province":"NC",
    "wof:name":"Carol Jamison",
    "wof:placetype":"venue"
},
  "geometry": {"coordinates":[-77.425284,34.781812],"type":"Point"}
}