{
  "type": "Feature",
  "properties": {
    "addr:full":"127 Williamsboro St Oxford NC 27565",
    "addr:housenumber":"127",
    "addr:postcode":"27565",
    "addr:street":"Williamsboro St",
    "iso:country":"US",
    "sg:address":"127 Williamsboro St",
    "sg:city":"Oxford",
    "sg:classifiers":[
        {
            "category":"Restaurant",
            "type":"Food & Drink"
        }
    ],
    "sg:phone":"+1 919 693 6444",
    "sg:postcode":"27565",
    "sg:province":"NC",
    "sg:tags":[
        "eating"
    ],
    "wof:name":"Milanos of Oxford Inc",
    "wof:placetype":"venue"
},
  "geometry": {"coordinates":[-78.588994,36.31168],"type":"Point"}
}