{
  "type": "Feature",
  "properties": {
    "addr:full":"79 Morton Ave NW Concord NC 28025",
    "addr:housenumber":"79",
    "addr:postcode":"28025",
    "addr:street":"Morton Ave Nw",
    "iso:country":"US",
    "sg:address":"79 Morton Ave NW",
    "sg:city":"Concord",
    "sg:classifiers":[
        {
            "category":"Retail",
            "subcategory":"Auto Repair",
            "type":"Services"
        }
    ],
    "sg:phone":"+1 704 788 3710",
    "sg:postcode":"28025",
    "sg:province":"NC",
    "sg:tags":[
        "body",
        "automobile",
        "painting"
    ],
    "wof:name":"Baker Body & Glass",
    "wof:placetype":"venue"
},
  "geometry": {"coordinates":[-80.60371000000001,35.430531],"type":"Point"}
}