{
  "type": "Feature",
  "properties": {
    "iso:country":"US",
    "sg:address":"2039 N Center St",
    "sg:city":"Hickory",
    "sg:classifiers":[
        {
            "category":"Restaurant",
            "type":"Food & Drink"
        }
    ],
    "sg:phone":"+1 828 322 9111",
    "sg:postcode":"28601",
    "sg:province":"NC",
    "sg:tags":[
        "banquet",
        "rooms"
    ],
    "wof:name":"Godfrey's Steak Seafood",
    "wof:placetype":"venue"
},
  "geometry": {"coordinates":[-81.33456,35.759742],"type":"Point"}
}