{
  "type": "Feature",
  "properties": {
    "addr:full":"4114 Scottsdale Dr SW Shallotte NC 28470",
    "addr:housenumber":"4114",
    "addr:postcode":"28470",
    "addr:street":"Scottsdale Dr Sw",
    "iso:country":"US",
    "sg:address":"4114 Scottsdale Dr SW",
    "sg:city":"Shallotte",
    "sg:classifiers":[
        {
            "category":"Insurance",
            "subcategory":"Insurance Agent",
            "type":"Services"
        }
    ],
    "sg:phone":"+1 910 754 5454",
    "sg:postcode":"28470",
    "sg:province":"NC",
    "wof:name":"Modern Woodmen of America",
    "wof:placetype":"venue"
},
  "geometry": {"coordinates":[-78.389088,33.947044],"type":"Point"}
}