{
  "type": "Feature",
  "properties": {
    "iso:country":"US",
    "sg:address":"900 W 12th St",
    "sg:city":"Charlotte",
    "sg:classifiers":[
        {
            "category":"Government",
            "subcategory":"Office",
            "type":"Public Place"
        }
    ],
    "sg:phone":"+1 704 336 3226",
    "sg:postcode":"28206",
    "sg:province":"NC",
    "wof:name":"Mecklenburg County Security",
    "wof:placetype":"venue"
},
  "geometry": {"coordinates":[-80.84472599999999,35.239613],"type":"Point"}
}