{
  "type": "Feature",
  "properties": {
    "addr:full":"764 Old Vander Rd Fayetteville NC 28312",
    "addr:housenumber":"764",
    "addr:postcode":"28312",
    "addr:street":"Old Vander Rd",
    "iso:country":"US",
    "sg:address":"764 Old Vander Rd",
    "sg:city":"Fayetteville",
    "sg:classifiers":[
        {
            "category":"Retail",
            "subcategory":"Repair Shop",
            "type":"Services"
        }
    ],
    "sg:phone":"+1 910 483 5675",
    "sg:postcode":"28312",
    "sg:province":"NC",
    "sg:tags":[
        "upholsterer"
    ],
    "wof:name":"Beard's Quality Upholstery",
    "wof:placetype":"venue"
},
  "geometry": {"coordinates":[-78.76625,35.021529],"type":"Point"}
}