{
  "type": "Feature",
  "properties": {
    "addr:full":"2201 Wakefield Pines Dr Raleigh NC 27614",
    "addr:housenumber":"2201",
    "addr:postcode":"27614",
    "addr:street":"Wakefield Pines Dr",
    "iso:country":"US",
    "sg:address":"2201 Wakefield Pines Dr",
    "sg:city":"Raleigh",
    "sg:classifiers":[
        {
            "category":"Recreation",
            "type":"Entertainment"
        }
    ],
    "sg:phone":"+1 919 562 7909",
    "sg:postcode":"27614",
    "sg:province":"NC",
    "sg:tags":[
        "club",
        "membership",
        "physical",
        "fitness"
    ],
    "wof:name":"Pga Tour Golf Course Prpts",
    "wof:placetype":"venue"
},
  "geometry": {"coordinates":[-78.564386,35.945191],"type":"Point"}
}