{
  "type": "Feature",
  "properties": {
    "addr:full":"8817 Old Potters Rd Charlotte NC 28269",
    "addr:housenumber":"8817",
    "addr:postcode":"28269",
    "addr:street":"Old Potters Rd",
    "iso:country":"US",
    "sg:address":"8817 Old Potters Rd",
    "sg:city":"Charlotte",
    "sg:classifiers":[
        {
            "category":"Retail",
            "subcategory":"Repair Shop",
            "type":"Services"
        }
    ],
    "sg:phone":"+1 704 597 8723",
    "sg:postcode":"28269",
    "sg:province":"NC",
    "sg:tags":[
        "upholsterer"
    ],
    "wof:name":"Larry Cline Upholstery",
    "wof:placetype":"venue"
},
  "geometry": {"coordinates":[-80.811927,35.320056],"type":"Point"}
}