{
  "type": "Feature",
  "properties": {
    "addr:full":"3060 S Evans St Greenville NC 27834",
    "addr:housenumber":"3060",
    "addr:postcode":"27834",
    "addr:street":"S Evans St",
    "iso:country":"US",
    "sg:address":"3060 S Evans St",
    "sg:city":"Greenville",
    "sg:classifiers":[
        {
            "category":"Shopping",
            "subcategory":"Computers & Home Electronics",
            "type":"Retail Goods"
        }
    ],
    "sg:phone":"+1 252 321 8011",
    "sg:postcode":"27834",
    "sg:province":"NC",
    "sg:tags":[
        "equipment",
        "electronic",
        "supply"
    ],
    "wof:name":"Circuit City",
    "wof:placetype":"venue"
},
  "geometry": {"coordinates":[-77.381421,35.578747],"type":"Point"}
}