{
  "type": "Feature",
  "properties": {
    "addr:full":"200 N Harbor Pl Davidson NC 28036",
    "addr:housenumber":"200",
    "addr:postcode":"28036",
    "addr:street":"N Harbor Pl",
    "iso:country":"US",
    "sg:address":"200 N Harbor Pl",
    "sg:city":"Davidson",
    "sg:classifiers":[
        {
            "category":"Banks & Credit Unions",
            "subcategory":"Bank",
            "type":"Services"
        }
    ],
    "sg:phone":"+1 704 987 2700",
    "sg:postcode":"28036",
    "sg:province":"NC",
    "sg:tags":[
        "loan",
        "real estate"
    ],
    "wof:name":"Full Spectrum Lending",
    "wof:placetype":"venue"
},
  "geometry": {"coordinates":[-80.868235,35.505585],"type":"Point"}
}