{
  "type": "Feature",
  "properties": {
    "addr:full":"104 N West St Wilkesboro NC 28697",
    "addr:housenumber":"104",
    "addr:postcode":"28697",
    "addr:street":"N West St",
    "iso:country":"US",
    "sg:address":"104 N West St",
    "sg:city":"Wilkesboro",
    "sg:classifiers":[
        {
            "category":"Social Services",
            "type":"Services"
        }
    ],
    "sg:phone":"+1 336 838 4563",
    "sg:postcode":"28697",
    "sg:province":"NC",
    "sg:tags":[
        "organization",
        "welfare"
    ],
    "sg:website":"www.redcross.org",
    "wof:name":"American Red Cross",
    "wof:placetype":"venue"
},
  "geometry": {"coordinates":[-81.153862,36.148707],"type":"Point"}
}