{
  "type": "Feature",
  "properties": {
    "iso:country":"US",
    "sg:address":"1322 Airlie Rd",
    "sg:city":"Wilmington",
    "sg:classifiers":[
        {
            "category":"Autos & Motor Vehicles",
            "subcategory":"Boat Sales",
            "type":"Retail Goods"
        }
    ],
    "sg:phone":"+1 910 256 9779",
    "sg:postcode":"28403",
    "sg:province":"NC",
    "sg:tags":[
        "equipment",
        "rebuilt",
        "marine"
    ],
    "wof:name":"Castaways Nautica Consignments",
    "wof:placetype":"venue"
},
  "geometry": {"coordinates":[-77.81527199999999,34.216867],"type":"Point"}
}