{
  "type": "Feature",
  "properties": {
    "addr:full":"5517 Goldcrest Dr Indian Trail NC 28079",
    "addr:housenumber":"5517",
    "addr:postcode":"28079",
    "addr:street":"Goldcrest Dr",
    "iso:country":"US",
    "sg:address":"5517 Goldcrest Dr",
    "sg:city":"Indian Trail",
    "sg:classifiers":[
        {
            "category":"Professional",
            "subcategory":"Lawyer & Legal Services",
            "type":"Services"
        }
    ],
    "sg:phone":"+1 704 882 2863",
    "sg:postcode":"28079",
    "sg:province":"NC",
    "sg:tags":[
        "right",
        "way",
        "acquisition",
        "contractor"
    ],
    "wof:name":"Kenneth J Frank & Assoc",
    "wof:placetype":"venue"
},
  "geometry": {"coordinates":[-80.613923,35.125278],"type":"Point"}
}