{
  "type": "Feature",
  "properties": {
    "addr:full":"2590 Hope Mills Rd Fayetteville NC 28306",
    "addr:housenumber":"2590",
    "addr:postcode":"28306",
    "addr:street":"Hope Mills Rd",
    "iso:country":"US",
    "sg:address":"2590 Hope Mills Rd",
    "sg:city":"Fayetteville",
    "sg:classifiers":[
        {
            "category":"Autos & Motor Vehicles",
            "subcategory":"Automobile Sales",
            "type":"Retail Goods"
        }
    ],
    "sg:phone":"+1 910 425 6200",
    "sg:postcode":"28306",
    "sg:province":"NC",
    "sg:tags":[
        "car",
        "dealer"
    ],
    "wof:name":"P G's Cars Inc",
    "wof:placetype":"venue"
},
  "geometry": {"coordinates":[-78.96746400000001,34.999987],"type":"Point"}
}