{
  "type": "Feature",
  "properties": {
    "addr:full":"8009 Ivory Ct Charlotte NC 28215",
    "addr:housenumber":"8009",
    "addr:postcode":"28215",
    "addr:street":"Ivory Ct",
    "iso:country":"US",
    "sg:address":"8009 Ivory Ct",
    "sg:city":"Charlotte",
    "sg:classifiers":[
        {
            "category":"Manufacturing",
            "subcategory":"Tools & Machinery",
            "type":"Manufacturing & Wholesale Goods"
        }
    ],
    "sg:phone":"+1 704 567 1057",
    "sg:postcode":"28215",
    "sg:province":"NC",
    "sg:tags":[
        "computer",
        "electronic",
        "mfg"
    ],
    "wof:name":"Gill V Sabrena",
    "wof:placetype":"venue"
},
  "geometry": {"coordinates":[-80.717074,35.248994],"type":"Point"}
}