{
  "type": "Feature",
  "properties": {
    "iso:country":"US",
    "sg:address":"1185 W Pennsylvania Ave",
    "sg:city":"Southern Pines",
    "sg:classifiers":[
        {
            "category":"Government",
            "subcategory":"Office",
            "type":"Public Place"
        },
        {
            "category":"Recreation",
            "type":"Entertainment"
        }
    ],
    "sg:phone":"+1 910 692 7376",
    "sg:postcode":"28387",
    "sg:province":"NC",
    "sg:tags":[
        "a",
        "city",
        "operates",
        "as",
        "hall",
        "auditorium"
    ],
    "wof:name":"Douglass Community Center",
    "wof:placetype":"venue"
},
  "geometry": {"coordinates":[-79.402005,35.184795],"type":"Point"}
}