{
  "type": "Feature",
  "properties": {
    "addr:full":"5008 White Flag Way Wake Forest NC 27587",
    "addr:housenumber":"5008",
    "addr:postcode":"27587",
    "addr:street":"White Flag Way",
    "iso:country":"US",
    "sg:address":"5008 White Flag Way",
    "sg:city":"Wake Forest",
    "sg:classifiers":[
        {
            "category":"Professional",
            "subcategory":"Business Services",
            "type":"Services"
        }
    ],
    "sg:phone":"+1   ",
    "sg:postcode":"27587",
    "sg:province":"NC",
    "wof:name":"By Special Arrangements",
    "wof:placetype":"venue"
},
  "geometry": {"coordinates":[-78.513993,35.916799],"type":"Point"}
}