{
  "type": "Feature",
  "properties": {
    "addr:full":"1716 Virginia St Monroe NC 28110",
    "addr:housenumber":"1716",
    "addr:postcode":"28110",
    "addr:street":"Virginia St",
    "iso:country":"US",
    "sg:address":"1716 Virginia St",
    "sg:city":"Monroe",
    "sg:classifiers":[
        {
            "category":"Communications",
            "subcategory":"Film & Video Production",
            "type":"Services"
        }
    ],
    "sg:phone":"+1 704 320 7792",
    "sg:postcode":"28110",
    "sg:province":"NC",
    "sg:tags":[
        "editing",
        "tape"
    ],
    "wof:name":"Custom Photo & Video",
    "wof:placetype":"venue"
},
  "geometry": {"coordinates":[-80.59433799999999,35.011945],"type":"Point"}
}