{
  "type": "Feature",
  "properties": {
    "addr:full":"416 S King St Laurinburg NC 28352",
    "addr:housenumber":"416",
    "addr:postcode":"28352",
    "addr:street":"S King St",
    "iso:country":"US",
    "sg:address":"416 S King St",
    "sg:city":"Laurinburg",
    "sg:classifiers":[
        {
            "category":"Personal",
            "subcategory":"Beauty Salon",
            "type":"Services"
        }
    ],
    "sg:phone":"+1 910 276 5130",
    "sg:postcode":"28352",
    "sg:province":"NC",
    "sg:tags":[
        "shop"
    ],
    "wof:name":"Mary's Beauty Salon",
    "wof:placetype":"venue"
},
  "geometry": {"coordinates":[-79.468165,34.775728],"type":"Point"}
}