{
  "type": "Feature",
  "properties": {
    "addr:full":"613 S Green St Morganton NC 28655",
    "addr:housenumber":"613",
    "addr:postcode":"28655",
    "addr:street":"S Green St",
    "iso:country":"US",
    "sg:address":"613 S Green St",
    "sg:city":"Morganton",
    "sg:classifiers":[
        {
            "category":"Shopping",
            "subcategory":"Clothing, Apparel, & Fashions",
            "type":"Retail Goods"
        }
    ],
    "sg:phone":"+1 828 430 7073",
    "sg:postcode":"28655",
    "sg:province":"NC",
    "sg:tags":[
        "item",
        "boutique"
    ],
    "wof:name":"Hot Pink Boutique",
    "wof:placetype":"venue"
},
  "geometry": {"coordinates":[-81.68222,35.741595],"type":"Point"}
}