{
  "type": "Feature",
  "properties": {
    "addr:full":"4582 Cumberland Rd Fayetteville NC 28306",
    "addr:housenumber":"4582",
    "addr:postcode":"28306",
    "addr:street":"Cumberland Rd",
    "iso:country":"US",
    "sg:address":"4582 Cumberland Rd",
    "sg:city":"Fayetteville",
    "sg:classifiers":[
        {
            "category":"Shopping",
            "subcategory":"Discount & Variety Stores",
            "type":"Retail Goods"
        }
    ],
    "sg:phone":"+1 910 426 4500",
    "sg:postcode":"28306",
    "sg:province":"NC",
    "wof:name":"Unique Dollar",
    "wof:placetype":"venue"
},
  "geometry": {"coordinates":[-78.961234,35.00835],"type":"Point"}
}