{
  "type": "Feature",
  "properties": {
    "iso:country":"US",
    "sg:address":"6 E Thompson St",
    "sg:city":"Jacksonville",
    "sg:classifiers":[
        {
            "category":"Organizations",
            "subcategory":"Community Association",
            "type":"Services"
        }
    ],
    "sg:phone":"+1 910 346 9482",
    "sg:postcode":"28540",
    "sg:province":"NC",
    "sg:tags":[
        "fraternal"
    ],
    "wof:name":"Shriners",
    "wof:placetype":"venue"
},
  "geometry": {"coordinates":[-77.40883100000001,34.764297],"type":"Point"}
}