{
  "type": "Feature",
  "properties": {
    "addr:full":"1985 Tate Blvd SE Hickory NC 28602",
    "addr:housenumber":"1985",
    "addr:postcode":"28602",
    "addr:street":"Tate Blvd Se",
    "iso:country":"US",
    "sg:address":"1985 Tate Blvd SE",
    "sg:city":"Hickory",
    "sg:classifiers":[
        {
            "category":"Insurance",
            "subcategory":"Hazard Insurance",
            "type":"Services"
        }
    ],
    "sg:phone":"+1 828 345 1341",
    "sg:postcode":"28602",
    "sg:province":"NC",
    "sg:tags":[
        "warranty",
        "program"
    ],
    "wof:name":"Television & Appliance Wrnty",
    "wof:placetype":"venue"
},
  "geometry": {"coordinates":[-81.302632,35.728246],"type":"Point"}
}