{
  "type": "Feature",
  "properties": {
    "iso:country":"US",
    "sg:address":"3614 Providence Rd",
    "sg:city":"Charlotte",
    "sg:classifiers":[
        {
            "category":"Health Services",
            "subcategory":"Doctor",
            "type":"Services"
        },
        {
            "category":"Wholesale",
            "subcategory":"Medical Equipment & Supplies",
            "type":"Manufacturing & Wholesale Goods"
        }
    ],
    "sg:phone":"+1 704 544 6533",
    "sg:postcode":"28211",
    "sg:province":"NC",
    "sg:tags":[
        "physician",
        "immunology",
        "pediatrics-otorhinolaryngology",
        "allergy",
        "surgeons",
        "hearing",
        "otorhinolaryngology",
        "throat",
        "device",
        "treatment",
        "assistive",
        "aid",
        "ear",
        "nose"
    ],
    "sg:website":"http://www.entaac.org",
    "wof:name":"Ear Nose Throat And Audiology Associates Of The Carolinas",
    "wof:placetype":"venue"
},
  "geometry": {"coordinates":[-80.80137499999999,35.162667],"type":"Point"}
}