{
  "type": "Feature",
  "properties": {
    "iso:country":"US",
    "sg:address":"2311 Dawson Cabin Rd",
    "sg:city":"Jacksonville",
    "sg:classifiers":[
        {
            "category":"Organizations",
            "subcategory":"Religious Organization",
            "type":"Services"
        }
    ],
    "sg:phone":"+1   ",
    "sg:postcode":"28540",
    "sg:province":"NC",
    "wof:name":"First Church Of God",
    "wof:placetype":"venue"
},
  "geometry": {"coordinates":[-77.50295199999999,34.687264],"type":"Point"}
}