{
  "type": "Feature",
  "properties": {
    "iso:country":"US",
    "sg:address":"4052 W State Hwy 97",
    "sg:city":"Spring Hope",
    "sg:classifiers":[
        {
            "category":"Building & Trades",
            "subcategory":"Construction",
            "type":"Services"
        }
    ],
    "sg:phone":"+1 919 783 0066",
    "sg:postcode":"27882",
    "sg:province":"NC",
    "sg:tags":[
        "tile",
        "dealer"
    ],
    "wof:name":"Lee's Tile",
    "wof:placetype":"venue"
},
  "geometry": {"coordinates":[-78.078703,35.865518],"type":"Point"}
}