{
  "type": "Feature",
  "properties": {
    "iso:country":"US",
    "sg:address":"5908 E Oak Island Dr",
    "sg:city":"Oak Island",
    "sg:classifiers":[
        {
            "category":"Restaurant",
            "type":"Food & Drink"
        }
    ],
    "sg:phone":"+1 910 278 4400",
    "sg:postcode":"28465",
    "sg:province":"NC",
    "wof:name":"Bogey's",
    "wof:placetype":"venue"
},
  "geometry": {"coordinates":[-78.104586,33.912163],"type":"Point"}
}