{
  "type": "Feature",
  "properties": {
    "iso:country":"US",
    "sg:address":"515 Barnett Ln",
    "sg:city":"Kinston",
    "sg:classifiers":[
        {
            "category":"Freight",
            "type":"Transportation"
        }
    ],
    "sg:phone":"+1 252 527 5241",
    "sg:postcode":"28504",
    "sg:province":"NC",
    "sg:tags":[
        "local",
        "storage",
        "trucking"
    ],
    "wof:name":"Dempsey Transportation Service",
    "wof:placetype":"venue"
},
  "geometry": {"coordinates":[-77.627798,35.220811],"type":"Point"}
}