{
  "type": "Feature",
  "properties": {
    "iso:country":"US",
    "sg:address":"2850 US Hwy 301 S",
    "sg:city":"Smithfield",
    "sg:classifiers":[
        {
            "category":"Manufacturing",
            "subcategory":"Tools & Machinery",
            "type":"Manufacturing & Wholesale Goods"
        }
    ],
    "sg:phone":"+1 919 934 3300",
    "sg:postcode":"27577",
    "sg:province":"NC",
    "sg:tags":[
        "machine",
        "shop"
    ],
    "wof:name":"Barbour Machine Works",
    "wof:placetype":"venue"
},
  "geometry": {"coordinates":[-78.37204300000001,35.480122],"type":"Point"}
}