{
  "type": "Feature",
  "properties": {
    "iso:country":"US",
    "sg:address":"515 Lauchwood Dr",
    "sg:city":"Laurinburg",
    "sg:classifiers":[
        {
            "category":"Health Services",
            "subcategory":"Doctor",
            "type":"Services"
        }
    ],
    "sg:phone":"+1 910 277 6221",
    "sg:postcode":"28352",
    "sg:province":"NC",
    "sg:tags":[
        "physician",
        "surgeon"
    ],
    "wof:name":"Scotland Family Practice",
    "wof:placetype":"venue"
},
  "geometry": {"coordinates":[-79.468244,34.750905],"type":"Point"}
}