{
  "type": "Feature",
  "properties": {
    "iso:country":"US",
    "sg:address":"394 Merrimon Ave",
    "sg:city":"Asheville",
    "sg:classifiers":[
        {
            "category":"Insurance",
            "subcategory":"Insurance Agent",
            "type":"Services"
        }
    ],
    "sg:phone":"+1 828 285 9590",
    "sg:postcode":"28801",
    "sg:province":"NC",
    "wof:name":"W N C Insurance Agency LLC",
    "wof:placetype":"venue"
},
  "geometry": {"coordinates":[-82.554896,35.610626],"type":"Point"}
}