{
  "type": "Feature",
  "properties": {
    "addr:full":"1012 Patton Avenue Asheville NC 28806",
    "addr:housenumber":"1012",
    "addr:postcode":"28806",
    "addr:street":"Patton Avenue",
    "iso:country":"US",
    "sg:address":"1012 Patton Avenue",
    "sg:city":"Asheville",
    "sg:classifiers":[
        {
            "category":"Banks & Credit Unions",
            "subcategory":"Bank",
            "type":"Services"
        }
    ],
    "sg:phone":"+1 828 254 1778",
    "sg:postcode":"28806",
    "sg:province":"NC",
    "sg:website":"www.ashevillesavings.com/",
    "wof:name":"Asheville Savings Bank",
    "wof:placetype":"venue"
},
  "geometry": {"coordinates":[-82.591224,35.586689],"type":"Point"}
}