{
  "type": "Feature",
  "properties": {
    "iso:country":"US",
    "sg:address":"4425 Randolph Rd",
    "sg:city":"Charlotte",
    "sg:classifiers":[
        {
            "category":"Wholesale",
            "subcategory":"Non-durable Goods",
            "type":"Manufacturing & Wholesale Goods"
        }
    ],
    "sg:phone":"+1 704 365 5016",
    "sg:postcode":"28211",
    "sg:province":"NC",
    "sg:tags":[
        "yarn"
    ],
    "wof:name":"Gilbert Sidney & Company Inc",
    "wof:placetype":"venue"
},
  "geometry": {"coordinates":[-80.7987,35.176589],"type":"Point"}
}