{
  "type": "Feature",
  "properties": {
    "addr:full":"16130 Amber Field Dr Huntersville NC 28078",
    "addr:housenumber":"16130",
    "addr:postcode":"28078",
    "addr:street":"Amber Field Dr",
    "iso:country":"US",
    "sg:address":"16130 Amber Field Dr",
    "sg:city":"Huntersville",
    "sg:classifiers":[
        {
            "category":"Professional",
            "subcategory":"Employment Agencies",
            "type":"Services"
        }
    ],
    "sg:phone":"+1 704 992 1080",
    "sg:postcode":"28078",
    "sg:province":"NC",
    "sg:tags":[
        "help",
        "contractor"
    ],
    "wof:name":"Keeg Del Radiology Staffing",
    "wof:placetype":"venue"
},
  "geometry": {"coordinates":[-80.846819,35.431239],"type":"Point"}
}