{
  "type": "Feature",
  "properties": {
    "iso:country":"US",
    "sg:address":"4100 Nick Dr",
    "sg:city":"Morganton",
    "sg:classifiers":[
        {
            "category":"Retail",
            "subcategory":"Repair Shop",
            "type":"Services"
        }
    ],
    "sg:phone":"+1   ",
    "sg:postcode":"28655",
    "sg:province":"NC",
    "wof:name":"J & J Upholstery Inc",
    "wof:placetype":"venue"
},
  "geometry": {"coordinates":[-81.61552,35.699701],"type":"Point"}
}