{
  "type": "Feature",
  "properties": {
    "addr:full":"2411 Jackson Springs Rd Jackson Springs NC 27281",
    "addr:housenumber":"2411",
    "addr:postcode":"27281",
    "addr:street":"Jackson Springs Rd",
    "iso:country":"US",
    "sg:address":"2411 Jackson Springs Rd",
    "sg:city":"Jackson Springs",
    "sg:classifiers":[
        {
            "category":"Government",
            "subcategory":"Post Office",
            "type":"Public Place"
        }
    ],
    "sg:phone":"+1 910 673 3251",
    "sg:postcode":"27281",
    "sg:province":"NC",
    "wof:name":"US Post Office",
    "wof:placetype":"venue"
},
  "geometry": {"coordinates":[-79.62616800000001,35.206852],"type":"Point"}
}