{
  "type": "Feature",
  "properties": {
    "addr:full":"101 W Railroad St La Grange NC 28551",
    "addr:housenumber":"101",
    "addr:postcode":"28551",
    "addr:street":"W Railroad St",
    "iso:country":"US",
    "sg:address":"101 W Railroad St",
    "sg:city":"La Grange",
    "sg:classifiers":[
        {
            "category":"Professional",
            "subcategory":"Accounting & Tax Preparation",
            "type":"Services"
        }
    ],
    "sg:phone":"+1 252 566 5500",
    "sg:postcode":"28551",
    "sg:province":"NC",
    "sg:tags":[
        "return",
        "filing"
    ],
    "wof:name":"Fastax Of LA Grange",
    "wof:placetype":"venue"
},
  "geometry": {"coordinates":[-77.79072499999999,35.307789],"type":"Point"}
}