{
  "type": "Feature",
  "properties": {
    "addr:full":"352 Etowah School Rd Hendersonville NC 28739",
    "addr:housenumber":"352",
    "addr:postcode":"28739",
    "addr:street":"Etowah School Rd",
    "iso:country":"US",
    "sg:address":"352 Etowah School Rd",
    "sg:city":"Hendersonville",
    "sg:classifiers":[
        {
            "category":"Professional",
            "subcategory":"Business Services",
            "type":"Services"
        }
    ],
    "sg:phone":"+1   ",
    "sg:postcode":"28739",
    "sg:province":"NC",
    "wof:name":"Casa Moreno",
    "wof:placetype":"venue"
},
  "geometry": {"coordinates":[-82.588232,35.313863],"type":"Point"}
}