{
  "type": "Feature",
  "properties": {
    "iso:country":"US",
    "sg:address":"1717 Kirkwood Dr",
    "sg:city":"Durham",
    "sg:classifiers":[
        {
            "category":"Building & Trades",
            "subcategory":"Construction",
            "type":"Services"
        }
    ],
    "sg:phone":"+1 919 477 4636",
    "sg:postcode":"27705",
    "sg:province":"NC",
    "sg:tags":[
        "covering",
        "mfg",
        "hard",
        "laying",
        "contractor",
        "floor"
    ],
    "wof:name":"Quality and Dependable Flrg",
    "wof:placetype":"venue"
},
  "geometry": {"coordinates":[-78.923877,36.042861],"type":"Point"}
}