{
  "type": "Feature",
  "properties": {
    "iso:country":"US",
    "sg:address":"1081 W Chapel Rd",
    "sg:city":"Asheville",
    "sg:classifiers":[
        {
            "category":"Building & Trades",
            "subcategory":"Landscaping Services",
            "type":"Services"
        }
    ],
    "sg:phone":"+1 828 274 4229",
    "sg:postcode":"28803",
    "sg:province":"NC",
    "wof:name":"M & J Lawn & Landscaping Servi",
    "wof:placetype":"venue"
},
  "geometry": {"coordinates":[-82.52248299999999,35.548559],"type":"Point"}
}