{
  "type": "Feature",
  "properties": {
    "addr:full":"410 New Bridge St Jacksonville NC 28540",
    "addr:housenumber":"410",
    "addr:postcode":"28540",
    "addr:street":"New;St",
    "iso:country":"US",
    "sg:address":"410 New Bridge St",
    "sg:city":"Jacksonville",
    "sg:classifiers":[
        {
            "category":"Health Services",
            "subcategory":"Health Practitioner",
            "type":"Services"
        }
    ],
    "sg:phone":"+1 910 347 2212",
    "sg:postcode":"28540",
    "sg:province":"NC",
    "sg:tags":[
        "occupational",
        "therapist",
        "therapy",
        "physical"
    ],
    "wof:name":"J Z Mann Pdtric Physcl Therapy",
    "wof:placetype":"venue"
},
  "geometry": {"coordinates":[-77.42568199999999,34.749969],"type":"Point"}
}