{
  "type": "Feature",
  "properties": {
    "iso:country":"US",
    "sg:address":"1311 Burtonwood Cir",
    "sg:city":"Charlotte",
    "sg:classifiers":[
        {
            "category":"Manufacturing",
            "subcategory":"Toys & Sporting Goods",
            "type":"Manufacturing & Wholesale Goods"
        }
    ],
    "sg:phone":"+1 704 567 2472",
    "sg:postcode":"28212",
    "sg:province":"NC",
    "sg:tags":[
        "mfg"
    ],
    "wof:name":"Yard Golfers Association",
    "wof:placetype":"venue"
},
  "geometry": {"coordinates":[-80.761261,35.16856],"type":"Point"}
}