{
  "type": "Feature",
  "properties": {
    "addr:full":"180 Webster Rd Sylva NC 28779",
    "addr:housenumber":"180",
    "addr:postcode":"28779",
    "addr:street":"Webster Rd",
    "iso:country":"US",
    "sg:address":"180 Webster Rd",
    "sg:city":"Sylva",
    "sg:classifiers":[
        {
            "category":"Insurance",
            "subcategory":"Insurance Agent",
            "type":"Services"
        }
    ],
    "sg:phone":"+1 828 586 4026",
    "sg:postcode":"28779",
    "sg:province":"NC",
    "wof:name":"State Farm Insurance",
    "wof:placetype":"venue"
},
  "geometry": {"coordinates":[-83.212599,35.345713],"type":"Point"}
}