{
  "type": "Feature",
  "properties": {
    "addr:full":"4100 Shannamara Dr Matthews NC 28104",
    "addr:housenumber":"4100",
    "addr:postcode":"28104",
    "addr:street":"Shannamara Dr",
    "iso:country":"US",
    "sg:address":"4100 Shannamara Dr",
    "sg:city":"Matthews",
    "sg:classifiers":[
        {
            "category":"Professional",
            "subcategory":"Detective & Security Services",
            "type":"Services"
        }
    ],
    "sg:phone":"+1   ",
    "sg:postcode":"28104",
    "sg:province":"NC",
    "sg:tags":[
        "car"
    ],
    "wof:name":"Db Investigations Inc",
    "wof:placetype":"venue"
},
  "geometry": {"coordinates":[-80.64195599999999,35.123542],"type":"Point"}
}