{
  "type": "Feature",
  "properties": {
    "addr:full":"408 Plaza Dr Harrisburg NC 28075",
    "addr:housenumber":"408",
    "addr:postcode":"28075",
    "addr:street":"Plaza Dr",
    "iso:country":"US",
    "sg:address":"408 Plaza Dr",
    "sg:city":"Harrisburg",
    "sg:classifiers":[
        {
            "category":"Autos & Motor Vehicles",
            "subcategory":"Motorcycle Sales",
            "type":"Retail Goods"
        }
    ],
    "sg:phone":"+1 704 455 2434",
    "sg:postcode":"28075",
    "sg:province":"NC",
    "sg:tags":[
        "scooter"
    ],
    "wof:name":"SMC Inc",
    "wof:placetype":"venue"
},
  "geometry": {"coordinates":[-80.65527299999999,35.323729],"type":"Point"}
}