{
  "type": "Feature",
  "properties": {
    "addr:full":"11030 Golf Links Dr Charlotte NC 28277",
    "addr:housenumber":"11030",
    "addr:postcode":"28277",
    "addr:street":"Golf Links Dr",
    "iso:country":"US",
    "sg:address":"11030 Golf Links Dr",
    "sg:city":"Charlotte",
    "sg:classifiers":[
        {
            "category":"Health Services",
            "subcategory":"Doctor",
            "type":"Services"
        }
    ],
    "sg:phone":"+1 704 321 0414",
    "sg:postcode":"28277",
    "sg:province":"NC",
    "sg:tags":[
        "dentist"
    ],
    "wof:name":"Brady Family & Cosmetic",
    "wof:placetype":"venue"
},
  "geometry": {"coordinates":[-80.771345,35.054329],"type":"Point"}
}