{
  "type": "Feature",
  "properties": {
    "iso:country":"US",
    "sg:address":"334 E Meadow Rd",
    "sg:city":"Eden",
    "sg:classifiers":[
        {
            "category":"Personal",
            "subcategory":"Beauty Salon",
            "type":"Services"
        }
    ],
    "sg:phone":"+1 336 623 3232",
    "sg:postcode":"27288",
    "sg:province":"NC",
    "wof:name":"Techniques By Carlea Inc",
    "wof:placetype":"venue"
},
  "geometry": {"coordinates":[-79.735116,36.509295],"type":"Point"}
}