{
  "type": "Feature",
  "properties": {
    "addr:full":"3512 Tunas St Raleigh NC 27616",
    "addr:postcode":"3512;27616",
    "addr:street":"Tunas St",
    "iso:country":"US",
    "sg:address":"3512 Tunas St",
    "sg:city":"Raleigh",
    "sg:classifiers":[
        {
            "category":"Professional",
            "subcategory":"Computer Services",
            "type":"Services"
        }
    ],
    "sg:phone":"+1 919 217 5277",
    "sg:postcode":"27616",
    "sg:province":"NC",
    "sg:tags":[
        "datum"
    ],
    "wof:name":"Media Guru Communications",
    "wof:placetype":"venue"
},
  "geometry": {"coordinates":[-78.521462,35.881129],"type":"Point"}
}