{
  "type": "Feature",
  "properties": {
    "iso:country":"US",
    "sg:address":"1251 Arrow Pine Dr",
    "sg:city":"Charlotte",
    "sg:classifiers":[
        {
            "category":"Banks & Credit Unions",
            "subcategory":"Investment Brokerage",
            "type":"Services"
        }
    ],
    "sg:phone":"+1 704 525 0649",
    "sg:postcode":"28273",
    "sg:province":"NC",
    "sg:tags":[
        "stock",
        "bond"
    ],
    "wof:name":"Scott & Stringfellow Inc",
    "wof:placetype":"venue"
},
  "geometry": {"coordinates":[-80.911935,35.137014],"type":"Point"}
}