{
  "type": "Feature",
  "properties": {
    "iso:country":"US",
    "sg:address":"651 Truitt Rd",
    "sg:city":"New Bern",
    "sg:classifiers":[
        {
            "category":"Government",
            "subcategory":"Office",
            "type":"Public Place"
        }
    ],
    "sg:phone":"+1 252 637 2733",
    "sg:postcode":"28560",
    "sg:province":"NC",
    "sg:tags":[
        "executive"
    ],
    "wof:name":"Tri Community Vol Fire Dept",
    "wof:placetype":"venue"
},
  "geometry": {"coordinates":[-76.98676500000001,35.199603],"type":"Point"}
}