{
  "type": "Feature",
  "properties": {
    "iso:country":"US",
    "sg:address":"22791 State Hwy 87",
    "sg:city":"Riegelwood",
    "sg:classifiers":[
        {
            "category":"Building & Trades",
            "subcategory":"Construction",
            "type":"Services"
        }
    ],
    "sg:phone":"+1 910 669 2722",
    "sg:postcode":"28456",
    "sg:province":"NC",
    "sg:tags":[
        "industrial"
    ],
    "wof:name":"G&M Leasing Co of NC LLC",
    "wof:placetype":"venue"
},
  "geometry": {"coordinates":[-78.317915,34.401414],"type":"Point"}
}