{
  "type": "Feature",
  "properties": {
    "addr:full":"126 Brockton Ln Mooresville NC 28117",
    "addr:housenumber":"126",
    "addr:postcode":"28117",
    "addr:street":"Brockton Ln",
    "iso:country":"US",
    "sg:address":"126 Brockton Ln",
    "sg:city":"Mooresville",
    "sg:classifiers":[
        {
            "category":"Banks & Credit Unions",
            "subcategory":"Investment Brokerage",
            "type":"Services"
        }
    ],
    "sg:phone":"+1 704 658 9190",
    "sg:postcode":"28117",
    "sg:province":"NC",
    "sg:tags":[
        "consultant",
        "planning",
        "financial"
    ],
    "wof:name":"Linsco Private Ledger Fncl Svc",
    "wof:placetype":"venue"
},
  "geometry": {"coordinates":[-80.940146,35.51556],"type":"Point"}
}