{
  "type": "Feature",
  "properties": {
    "addr:full":"2828 Gilmer Ave Winston Salem NC 27105",
    "addr:housenumber":"2828",
    "addr:postcode":"27105",
    "addr:street":"Gilmer Ave",
    "iso:country":"US",
    "sg:address":"2828 Gilmer Ave",
    "sg:city":"Winston Salem",
    "sg:classifiers":[
        {
            "category":"Wholesale",
            "subcategory":"Groceries",
            "type":"Manufacturing & Wholesale Goods"
        }
    ],
    "sg:phone":"+1 336 722 0635",
    "sg:postcode":"27105",
    "sg:province":"NC",
    "sg:tags":[
        "bakery"
    ],
    "wof:name":"Plott Bakery Products",
    "wof:placetype":"venue"
},
  "geometry": {"coordinates":[-80.244426,36.126101],"type":"Point"}
}