{
  "type": "Feature",
  "properties": {
    "addr:full":"101 Hickory St North Wilkesboro NC 28659",
    "addr:housenumber":"101",
    "addr:postcode":"28659",
    "addr:street":"Hickory St",
    "iso:country":"US",
    "sg:address":"101 Hickory St",
    "sg:city":"North Wilkesboro",
    "sg:classifiers":[
        {
            "category":"Government",
            "subcategory":"Office",
            "type":"Public Place"
        }
    ],
    "sg:phone":"+1 336 667 3203",
    "sg:postcode":"28659",
    "sg:province":"NC",
    "sg:tags":[
        "village"
    ],
    "wof:name":"North Wilkesboro Housing",
    "wof:placetype":"venue"
},
  "geometry": {"coordinates":[-81.16324299999999,36.158259],"type":"Point"}
}