{
  "type": "Feature",
  "properties": {
    "iso:country":"US",
    "sg:address":"286 Little Creek Church Rd",
    "sg:city":"Clayton",
    "sg:classifiers":[
        {
            "category":"Retail",
            "subcategory":"Auto Repair",
            "type":"Services"
        }
    ],
    "sg:phone":"+1 919 938 3424",
    "sg:postcode":"27520",
    "sg:province":"NC",
    "sg:tags":[
        "repairing",
        "automobile"
    ],
    "wof:name":"OVI Era Auto Svc",
    "wof:placetype":"venue"
},
  "geometry": {"coordinates":[-78.398405,35.559241],"type":"Point"}
}