{
  "type": "Feature",
  "properties": {
    "iso:country":"US",
    "sg:address":"1659 Saint Pauls Rd",
    "sg:city":"Hendersonville",
    "sg:classifiers":[
        {
            "category":"Organizations",
            "subcategory":"Religious Organization",
            "type":"Services"
        }
    ],
    "sg:phone":"+1 828 685 3644",
    "sg:postcode":"28792",
    "sg:province":"NC",
    "sg:tags":[
        "church"
    ],
    "wof:name":"St Paul's Episcopal Church",
    "wof:placetype":"venue"
},
  "geometry": {"coordinates":[-82.33855200000001,35.411929],"type":"Point"}
}