{
  "type": "Feature",
  "properties": {
    "addr:full":"8539 Chapel Hill Rd Cary NC 27513",
    "addr:housenumber":"8539",
    "addr:postcode":"27513",
    "addr:street":"Chapel Hill Rd",
    "iso:country":"US",
    "sg:address":"8539 Chapel Hill Rd",
    "sg:city":"Cary",
    "sg:classifiers":[
        {
            "category":"Professional",
            "type":"Services"
        }
    ],
    "sg:phone":"+1 919 380 1401",
    "sg:postcode":"27513",
    "sg:province":"NC",
    "sg:tags":[
        "establishment"
    ],
    "wof:name":"Disaster One Inc",
    "wof:placetype":"venue"
},
  "geometry": {"coordinates":[-78.78113500000001,35.791465],"type":"Point"}
}