{
  "type": "Feature",
  "properties": {
    "addr:full":"6901 Running Brook Ter Wilmington NC 28411",
    "addr:housenumber":"6901",
    "addr:postcode":"28411",
    "addr:street":"Running Brook Ter",
    "iso:country":"US",
    "sg:address":"6901 Running Brook Ter",
    "sg:city":"Wilmington",
    "sg:classifiers":[
        {
            "category":"Professional",
            "type":"Services"
        }
    ],
    "sg:phone":"+1 910 681 0830",
    "sg:postcode":"28411",
    "sg:province":"NC",
    "sg:tags":[
        "establishment"
    ],
    "wof:name":"Collins & Collins",
    "wof:placetype":"venue"
},
  "geometry": {"coordinates":[-77.79771100000001,34.257035],"type":"Point"}
}