{
  "type": "Feature",
  "properties": {
    "addr:full":"4000 Dickinson Ave Greenville NC 27834",
    "addr:housenumber":"4000",
    "addr:postcode":"27834",
    "addr:street":"Dickinson Ave",
    "iso:country":"US",
    "sg:address":"4000 Dickinson Ave",
    "sg:city":"Greenville",
    "sg:classifiers":[
        {
            "category":"Food & Beverages",
            "subcategory":"Groceries & Convenience Stores",
            "type":"Retail Goods"
        }
    ],
    "sg:phone":"+1 252 321 9263",
    "sg:postcode":"27834",
    "sg:province":"NC",
    "wof:name":"Trade Mart No",
    "wof:placetype":"venue"
},
  "geometry": {"coordinates":[-77.43119,35.577002],"type":"Point"}
}