{
  "type": "Feature",
  "properties": {
    "iso:country":"US",
    "sg:address":"4114 Kestrel Ct",
    "sg:city":"Lenoir",
    "sg:classifiers":[
        {
            "category":"Autos & Motor Vehicles",
            "subcategory":"Automobile Sales",
            "type":"Retail Goods"
        }
    ],
    "sg:phone":"+1 828 757 9919",
    "sg:postcode":"28645",
    "sg:province":"NC",
    "wof:name":"Cadillac Lasalle Club Inc",
    "wof:placetype":"venue"
},
  "geometry": {"coordinates":[-81.423615,35.974764],"type":"Point"}
}