{
  "type": "Feature",
  "properties": {
    "iso:country":"US",
    "sg:address":"104 Pinecrest Pkwy",
    "sg:city":"Wilmington",
    "sg:classifiers":[
        {
            "category":"Arts & Performance",
            "subcategory":"Theater",
            "type":"Entertainment"
        }
    ],
    "sg:phone":"+1   ",
    "sg:postcode":"28401",
    "sg:province":"NC",
    "sg:tags":[
        "theatrical"
    ],
    "wof:name":"Sunshine Management Group Inc",
    "wof:placetype":"venue"
},
  "geometry": {"coordinates":[-77.939734,34.214115],"type":"Point"}
}