{
  "type": "Feature",
  "properties": {
    "addr:full":"2850 Village Dr Fayetteville NC 28304",
    "addr:housenumber":"2850",
    "addr:postcode":"28304",
    "addr:street":"Village Dr",
    "iso:country":"US",
    "sg:address":"2850 Village Dr",
    "sg:city":"Fayetteville",
    "sg:classifiers":[
        {
            "category":"Professional",
            "subcategory":"Lawyer & Legal Services",
            "type":"Services"
        }
    ],
    "sg:phone":"+1   ",
    "sg:postcode":"28304",
    "sg:province":"NC",
    "wof:name":"Orion Construction",
    "wof:placetype":"venue"
},
  "geometry": {"coordinates":[-78.923316,35.032497],"type":"Point"}
}