{
  "type": "Feature",
  "properties": {
    "addr:full":"1829 Hullwood Dr Kinston NC 28504",
    "addr:housenumber":"1829",
    "addr:postcode":"28504",
    "addr:street":"Hullwood Dr",
    "iso:country":"US",
    "sg:address":"1829 Hullwood Dr",
    "sg:city":"Kinston",
    "sg:classifiers":[
        {
            "category":"Professional",
            "subcategory":"Computer Services",
            "type":"Services"
        }
    ],
    "sg:phone":"+1 252 939 3919",
    "sg:postcode":"28504",
    "sg:province":"NC",
    "sg:tags":[
        "datum"
    ],
    "wof:name":"Horizon Technologies",
    "wof:placetype":"venue"
},
  "geometry": {"coordinates":[-77.642302,35.308168],"type":"Point"}
}