{
  "type": "Feature",
  "properties": {
    "addr:full":"813 Smoke Tree Cir Lewisville NC 27023",
    "addr:housenumber":"813",
    "addr:postcode":"27023",
    "addr:street":"Smoke Tree Cir",
    "iso:country":"US",
    "sg:address":"813 Smoke Tree Cir",
    "sg:city":"Lewisville",
    "sg:classifiers":[
        {
            "category":"Retail",
            "subcategory":"Repair Shop",
            "type":"Services"
        }
    ],
    "sg:phone":"+1   ",
    "sg:postcode":"27023",
    "sg:province":"NC",
    "wof:name":"Pt Sharpening Inc",
    "wof:placetype":"venue"
},
  "geometry": {"coordinates":[-80.40293200000001,36.089517],"type":"Point"}
}