{
  "type": "Feature",
  "properties": {
    "iso:country":"US",
    "sg:address":"109 S Brightleaf Blvd",
    "sg:city":"Smithfield",
    "sg:classifiers":[
        {
            "category":"Restaurant",
            "type":"Food & Drink"
        }
    ],
    "sg:phone":"+1 919 989 7863",
    "sg:postcode":"27577",
    "sg:province":"NC",
    "sg:tags":[
        "eating"
    ],
    "wof:name":"Millie's Hot Dogs",
    "wof:placetype":"venue"
},
  "geometry": {"coordinates":[-78.339479,35.508387],"type":"Point"}
}