{
  "type": "Feature",
  "properties": {
    "iso:country":"US",
    "sg:address":"116 Walnut St",
    "sg:city":"Burnsville",
    "sg:classifiers":[
        {
            "category":"Home & Garden",
            "subcategory":"Building Materials",
            "type":"Retail Goods"
        }
    ],
    "sg:phone":"+1 828 682 3403",
    "sg:postcode":"28714",
    "sg:province":"NC",
    "wof:name":"Archer Glass",
    "wof:placetype":"venue"
},
  "geometry": {"coordinates":[-82.30145400000001,35.918142],"type":"Point"}
}