{
  "type": "Feature",
  "properties": {
    "iso:country":"US",
    "sg:address":"7440 Apple Murray Rd",
    "sg:city":"Gibsonville",
    "sg:classifiers":[
        {
            "category":"Professional",
            "subcategory":"Business Services",
            "type":"Services"
        }
    ],
    "sg:phone":"+1   ",
    "sg:postcode":"27249",
    "sg:province":"NC",
    "wof:name":"Creekside Auction Service",
    "wof:placetype":"venue"
},
  "geometry": {"coordinates":[-79.552297,36.208028],"type":"Point"}
}