{
  "type": "Feature",
  "properties": {
    "iso:country":"US",
    "sg:address":"1095 Damascus Rd",
    "sg:city":"Danbury",
    "sg:classifiers":[
        {
            "category":"Education",
            "subcategory":"School",
            "type":"Public Place"
        }
    ],
    "sg:phone":"+1 336 593 8635",
    "sg:postcode":"27016",
    "sg:province":"NC",
    "sg:tags":[
        "private"
    ],
    "wof:name":"King Family Ministries School",
    "wof:placetype":"venue"
},
  "geometry": {"coordinates":[-80.195751,36.441406],"type":"Point"}
}