{
  "type": "Feature",
  "properties": {
    "iso:country":"US",
    "sg:address":"111 Gardner Point Cir",
    "sg:city":"Littleton",
    "sg:classifiers":[
        {
            "category":"Professional",
            "type":"Services"
        }
    ],
    "sg:phone":"+1 252 586 6907",
    "sg:postcode":"27850",
    "sg:province":"NC",
    "wof:name":"Ron Nida Rev",
    "wof:placetype":"venue"
},
  "geometry": {"coordinates":[-77.967692,36.533693],"type":"Point"}
}