{
  "type": "Feature",
  "properties": {
    "addr:full":"826 State Hwy 27 Albemarle NC 28001",
    "addr:housenumber":"826",
    "addr:postcode":"28001",
    "addr:street":"State Hwy 27",
    "iso:country":"US",
    "sg:address":"826 State Hwy 27",
    "sg:city":"Albemarle",
    "sg:classifiers":[
        {
            "category":"Restaurant",
            "type":"Food & Drink"
        }
    ],
    "sg:phone":"+1 704 982 6394",
    "sg:postcode":"28001",
    "sg:province":"NC",
    "sg:tags":[
        "eating"
    ],
    "wof:name":"Taco Bell",
    "wof:placetype":"venue"
},
  "geometry": {"coordinates":[-80.204925,35.338706],"type":"Point"}
}