{
  "type": "Feature",
  "properties": {
    "iso:country":"US",
    "sg:address":"125 E Plaza Dr",
    "sg:city":"Mooresville",
    "sg:classifiers":[
        {
            "category":"Real Estate",
            "subcategory":"Real Estate Agent",
            "type":"Services"
        }
    ],
    "sg:phone":"+1 704 660 7529",
    "sg:postcode":"28115",
    "sg:province":"NC",
    "wof:name":"Front Porch Properties",
    "wof:placetype":"venue"
},
  "geometry": {"coordinates":[-80.8275,35.588426],"type":"Point"}
}