{
  "type": "Feature",
  "properties": {
    "addr:full":"1303 Gateshead Ln Matthews NC 28105",
    "addr:housenumber":"1303",
    "addr:postcode":"28105",
    "addr:street":"Gateshead Ln",
    "iso:country":"US",
    "sg:address":"1303 Gateshead Ln",
    "sg:city":"Matthews",
    "sg:classifiers":[
        {
            "category":"Home & Garden",
            "subcategory":"Building Materials",
            "type":"Retail Goods"
        }
    ],
    "sg:phone":"+1 704 321 1543",
    "sg:postcode":"28105",
    "sg:province":"NC",
    "wof:name":"Charlotte Brick Company LLC",
    "wof:placetype":"venue"
},
  "geometry": {"coordinates":[-80.735596,35.104967],"type":"Point"}
}