{
  "type": "Feature",
  "properties": {
    "addr:full":"497 N McPherson Church Rd Fayetteville NC 28303",
    "addr:housenumber":"497",
    "addr:postcode":"28303",
    "addr:street":"N Mcpherson Church Rd",
    "iso:country":"US",
    "sg:address":"497 N McPherson Church Rd",
    "sg:city":"Fayetteville",
    "sg:classifiers":[
        {
            "category":"Autos & Motor Vehicles",
            "subcategory":"Automobile Sales",
            "type":"Retail Goods"
        }
    ],
    "sg:phone":"+1 910 864 5240",
    "sg:postcode":"28303",
    "sg:province":"NC",
    "sg:tags":[
        "car",
        "dealer"
    ],
    "sg:website":"www.crosscreekcars.com",
    "wof:name":"Cross Creek Lincoln-Mercury",
    "wof:placetype":"venue"
},
  "geometry": {"coordinates":[-78.952635,35.072669],"type":"Point"}
}