{
  "type": "Feature",
  "properties": {
    "iso:country":"US",
    "sg:address":"8708 Green Apple Ct",
    "sg:city":"Wake Forest",
    "sg:classifiers":[
        {
            "category":"Real Estate",
            "subcategory":"Real Estate Agent",
            "type":"Services"
        },
        {
            "category":"Professional",
            "subcategory":"Business Services",
            "type":"Services"
        }
    ],
    "sg:phone":"+1 919 805 2153",
    "sg:postcode":"27587",
    "sg:province":"NC",
    "sg:tags":[
        "inspection"
    ],
    "wof:name":"Raleigh Residential Svcs LLC",
    "wof:placetype":"venue"
},
  "geometry": {"coordinates":[-78.52575,35.917001],"type":"Point"}
}