{
  "type": "Feature",
  "properties": {
    "iso:country":"US",
    "sg:address":"301 E Main St",
    "sg:city":"Carrboro",
    "sg:classifiers":[
        {
            "category":"Restaurant",
            "type":"Food & Drink"
        }
    ],
    "sg:phone":"+1 919 932 7222",
    "sg:postcode":"27510",
    "sg:province":"NC",
    "sg:tags":[
        "chinese"
    ],
    "sg:website":"www.thegourmetkingdom.com/",
    "wof:name":"Gourmet Kingdom",
    "wof:placetype":"venue"
},
  "geometry": {"coordinates":[-79.069016,35.910721],"type":"Point"}
}