{
  "type": "Feature",
  "properties": {
    "addr:full":"406 S Elliott Rd Chapel Hill NC 27514",
    "addr:housenumber":"406",
    "addr:postcode":"27514",
    "addr:street":"S Elliott Rd",
    "iso:country":"US",
    "sg:address":"406 S Elliott Rd",
    "sg:city":"Chapel Hill",
    "sg:classifiers":[
        {
            "category":"Education",
            "subcategory":"College",
            "type":"Public Place"
        }
    ],
    "sg:phone":"+1 919 962 4124",
    "sg:postcode":"27514",
    "sg:province":"NC",
    "wof:name":"University NC At Chapel Hl",
    "wof:placetype":"venue"
},
  "geometry": {"coordinates":[-79.024565,35.932464],"type":"Point"}
}