{
  "type": "Feature",
  "properties": {
    "iso:country":"US",
    "sg:address":"306 N Main St",
    "sg:city":"Sparta",
    "sg:classifiers":[
        {
            "category":"Food & Beverages",
            "subcategory":"Groceries & Convenience Stores",
            "type":"Retail Goods"
        }
    ],
    "sg:phone":"+1 336 372 8787",
    "sg:postcode":"28675",
    "sg:province":"NC",
    "wof:name":"Sparta Wilco",
    "wof:placetype":"venue"
},
  "geometry": {"coordinates":[-81.12217099999999,36.506803],"type":"Point"}
}