{
  "type": "Feature",
  "properties": {
    "iso:country":"US",
    "sg:address":"1501 Capps Hill Mine Rd",
    "sg:city":"Charlotte",
    "sg:classifiers":[
        {
            "category":"Building & Trades",
            "subcategory":"Cleaning & Sanitation",
            "type":"Services"
        }
    ],
    "sg:phone":"+1   ",
    "sg:postcode":"28216",
    "sg:province":"NC",
    "sg:tags":[
        "maintenance"
    ],
    "wof:name":"G and G Janitorial",
    "wof:placetype":"venue"
},
  "geometry": {"coordinates":[-80.864423,35.289486],"type":"Point"}
}