{
  "type": "Feature",
  "properties": {
    "addr:full":"10741 Forest Pines Dr Raleigh NC 27614",
    "addr:housenumber":"10741",
    "addr:postcode":"27614",
    "addr:street":"Forest Pines Dr",
    "iso:country":"US",
    "sg:address":"10741 Forest Pines Dr",
    "sg:city":"Raleigh",
    "sg:classifiers":[
        {
            "category":"Social Services",
            "subcategory":"Child Care",
            "type":"Services"
        },
        {
            "category":"Education",
            "subcategory":"Preschool",
            "type":"Public Place"
        }
    ],
    "sg:phone":"+1 919 570 3401",
    "sg:postcode":"27614",
    "sg:province":"NC",
    "sg:tags":[
        "kindergarten",
        "nursery",
        "day"
    ],
    "sg:website":"http://www.kindercare.com/our-centers/center-details/075302/?cid=YP_KB075302",
    "wof:name":"Knowledge Beginnings",
    "wof:placetype":"venue"
},
  "geometry": {"coordinates":[-78.544721,35.941968],"type":"Point"}
}