{
  "type": "Feature",
  "properties": {
    "addr:full":"121 E Morgan St Raleigh NC 27601",
    "addr:housenumber":"121",
    "addr:postcode":"27601",
    "addr:street":"E Morgan St",
    "iso:country":"US",
    "sg:address":"121 E Morgan St",
    "sg:city":"Raleigh",
    "sg:classifiers":[
        {
            "category":"Utilities",
            "subcategory":"Telephone",
            "type":"Services"
        }
    ],
    "sg:phone":"+1 919 821 6004",
    "sg:postcode":"27601",
    "sg:province":"NC",
    "sg:tags":[
        "communications",
        "company"
    ],
    "wof:name":"Bell South",
    "wof:placetype":"venue"
},
  "geometry": {"coordinates":[-78.636827,35.779575],"type":"Point"}
}