{
  "type": "Feature",
  "properties": {
    "iso:country":"US",
    "sg:address":"6320 Owenby Ct",
    "sg:city":"Charlotte",
    "sg:classifiers":[
        {
            "category":"Mining & Drilling",
            "type":"Manufacturing & Wholesale Goods"
        }
    ],
    "sg:phone":"+1 704 365 0085",
    "sg:postcode":"28270",
    "sg:province":"NC",
    "sg:tags":[
        "oil",
        "gas"
    ],
    "wof:name":"Status Oilwells Inc",
    "wof:placetype":"venue"
},
  "geometry": {"coordinates":[-80.78357200000001,35.141593],"type":"Point"}
}