{
  "type": "Feature",
  "properties": {
    "iso:country":"US",
    "sg:address":"3020 Montclair Dr",
    "sg:city":"Claremont",
    "sg:classifiers":[
        {
            "category":"Organizations",
            "subcategory":"Religious Organization",
            "type":"Services"
        }
    ],
    "sg:phone":"+1 828 459 2245",
    "sg:postcode":"28610",
    "sg:province":"NC",
    "wof:name":"United Chrstn Fllowship Church",
    "wof:placetype":"venue"
},
  "geometry": {"coordinates":[-81.155258,35.72679],"type":"Point"}
}