{
  "type": "Feature",
  "properties": {
    "iso:country":"US",
    "sg:address":"3339 Quarry Dr",
    "sg:city":"Fayetteville",
    "sg:classifiers":[
        {
            "category":"Building & Trades",
            "subcategory":"Equipment Rental",
            "type":"Services"
        }
    ],
    "sg:phone":"+1   ",
    "sg:postcode":"28303",
    "sg:province":"NC",
    "sg:tags":[
        "truck"
    ],
    "wof:name":"Dogwood Leasing Inc",
    "wof:placetype":"venue"
},
  "geometry": {"coordinates":[-78.94101000000001,35.070623],"type":"Point"}
}