{
  "type": "Feature",
  "properties": {
    "iso:country":"US",
    "sg:address":"614 Fort Fisher Blvd S",
    "sg:city":"Kure Beach",
    "sg:classifiers":[
        {
            "category":"Travel",
            "subcategory":"Hotels & Motels",
            "type":"Entertainment"
        }
    ],
    "sg:phone":"+1   ",
    "sg:postcode":"28449",
    "sg:province":"NC",
    "sg:tags":[
        "operation"
    ],
    "wof:name":"C and C Coastal",
    "wof:placetype":"venue"
},
  "geometry": {"coordinates":[-77.909716,33.989248],"type":"Point"}
}