{
  "type": "Feature",
  "properties": {
    "iso:country":"US",
    "sg:address":"1074 Crossroads Dr",
    "sg:city":"Statesville",
    "sg:classifiers":[
        {
            "category":"Shopping",
            "subcategory":"Shoes",
            "type":"Retail Goods"
        }
    ],
    "sg:phone":"+1 704 871 0227",
    "sg:postcode":"28625",
    "sg:province":"NC",
    "wof:name":"Shoe Department",
    "wof:placetype":"venue"
},
  "geometry": {"coordinates":[-80.87102899999999,35.810243],"type":"Point"}
}