{
  "type": "Feature",
  "properties": {
    "iso:country":"US",
    "sg:address":"1631 Cotton Grove Rd",
    "sg:city":"Lexington",
    "sg:classifiers":[
        {
            "category":"Travel",
            "subcategory":"Hotels & Motels",
            "type":"Entertainment"
        }
    ],
    "sg:phone":"+1 336 357 6444",
    "sg:postcode":"27292",
    "sg:province":"NC",
    "wof:name":"Super 8 Motel",
    "wof:placetype":"venue"
},
  "geometry": {"coordinates":[-80.259939,35.779913],"type":"Point"}
}