{
  "type": "Feature",
  "properties": {
    "iso:country":"US",
    "sg:address":"2515 Westerly Hills Dr",
    "sg:city":"Charlotte",
    "sg:classifiers":[
        {
            "category":"Insurance",
            "subcategory":"Insurance Agent",
            "type":"Services"
        }
    ],
    "sg:phone":"+1 704 393 0050",
    "sg:postcode":"28208",
    "sg:province":"NC",
    "wof:name":"Cpn Centralina Insurance & Inv",
    "wof:placetype":"venue"
},
  "geometry": {"coordinates":[-80.897668,35.225634],"type":"Point"}
}