{
  "type": "Feature",
  "properties": {
    "addr:full":"3107 Nc 410 Hwy Bladenboro NC 28320",
    "addr:housenumber":"3107",
    "addr:postcode":"28320",
    "addr:street":"Nc 410 Hwy",
    "iso:country":"US",
    "sg:address":"3107 Nc 410 Hwy",
    "sg:city":"Bladenboro",
    "sg:classifiers":[
        {
            "category":"Organizations",
            "subcategory":"Religious Organization",
            "type":"Services"
        }
    ],
    "sg:phone":"+1 910 863 4320",
    "sg:postcode":"28320",
    "sg:province":"NC",
    "wof:name":"Community Baptist Church",
    "wof:placetype":"venue"
},
  "geometry": {"coordinates":[-78.75040199999999,34.618579],"type":"Point"}
}