{
  "type": "Feature",
  "properties": {
    "iso:country":"US",
    "sg:address":"162 Manor Ave SW",
    "sg:city":"Concord",
    "sg:classifiers":[
        {
            "category":"Building & Trades",
            "subcategory":"Construction",
            "type":"Services"
        }
    ],
    "sg:phone":"+1 704 782 6128",
    "sg:postcode":"28025",
    "sg:province":"NC",
    "sg:tags":[
        "roofing",
        "contractor"
    ],
    "wof:name":"D R Huneycutt Enterprises Inc",
    "wof:placetype":"venue"
},
  "geometry": {"coordinates":[-80.56836699999999,35.384348],"type":"Point"}
}