{
  "type": "Feature",
  "properties": {
    "addr:full":"45 Church St SE Concord NC 28025",
    "addr:housenumber":"45",
    "addr:postcode":"28025",
    "addr:street":"Church St Se",
    "iso:country":"US",
    "sg:address":"45 Church St SE",
    "sg:city":"Concord",
    "sg:classifiers":[
        {
            "category":"Professional",
            "subcategory":"Lawyer & Legal Services",
            "type":"Services"
        }
    ],
    "sg:phone":"+1   ",
    "sg:postcode":"28025",
    "sg:province":"NC",
    "wof:name":"Mills William 3 Law Offices",
    "wof:placetype":"venue"
},
  "geometry": {"coordinates":[-80.57952,35.410945],"type":"Point"}
}