{
  "type": "Feature",
  "properties": {
    "addr:full":"3521 Haworth Dr Raleigh NC 27609",
    "addr:housenumber":"3521",
    "addr:postcode":"27609",
    "addr:street":"Haworth Dr",
    "iso:country":"US",
    "sg:address":"3521 Haworth Dr",
    "sg:city":"Raleigh",
    "sg:classifiers":[
        {
            "category":"Health Services",
            "subcategory":"Doctor",
            "type":"Services"
        }
    ],
    "sg:phone":"+1 919 782 1806",
    "sg:postcode":"27609",
    "sg:province":"NC",
    "sg:tags":[
        "physician",
        "surgeon"
    ],
    "sg:website":"www.raleighmedicalgroup.com",
    "wof:name":"Raleigh Medical Group",
    "wof:placetype":"venue"
},
  "geometry": {"coordinates":[-78.633746,35.829165],"type":"Point"}
}