{
  "type": "Feature",
  "properties": {
    "iso:country":"US",
    "sg:address":"314 W Broad St",
    "sg:city":"St Pauls",
    "sg:classifiers":[
        {
            "category":"Shopping",
            "subcategory":"Florist",
            "type":"Retail Goods"
        }
    ],
    "sg:phone":"+1 910 865 3336",
    "sg:postcode":"28384",
    "sg:province":"NC",
    "wof:name":"Flower Market",
    "wof:placetype":"venue"
},
  "geometry": {"coordinates":[-78.97474099999999,34.807146],"type":"Point"}
}