{
  "type": "Feature",
  "properties": {
    "addr:full":"120 Costen Rd Sunbury NC 27979",
    "addr:housenumber":"120",
    "addr:postcode":"27979",
    "addr:street":"Costen Rd",
    "iso:country":"US",
    "sg:address":"120 Costen Rd",
    "sg:city":"Sunbury",
    "sg:classifiers":[
        {
            "category":"Freight",
            "type":"Transportation"
        }
    ],
    "sg:phone":"+1 252 465 2025",
    "sg:postcode":"27979",
    "sg:province":"NC",
    "sg:tags":[
        "operator",
        "local",
        "trucking"
    ],
    "wof:name":"Easons Trucking",
    "wof:placetype":"venue"
},
  "geometry": {"coordinates":[-76.61261500000001,36.428119],"type":"Point"}
}