{
  "type": "Feature",
  "properties": {
    "addr:full":"210 S Lafayette St Shelby NC 28150",
    "addr:housenumber":"210",
    "addr:postcode":"28150",
    "addr:street":"S Lafayette St",
    "iso:country":"US",
    "sg:address":"210 S Lafayette St",
    "sg:city":"Shelby",
    "sg:classifiers":[
        {
            "category":"Restaurant",
            "type":"Food & Drink"
        }
    ],
    "sg:phone":"+1 704 482 6755",
    "sg:postcode":"28150",
    "sg:province":"NC",
    "sg:tags":[
        "eating"
    ],
    "wof:name":"Bellatoni's",
    "wof:placetype":"venue"
},
  "geometry": {"coordinates":[-81.54033800000001,35.290473],"type":"Point"}
}