{
  "type": "Feature",
  "properties": {
    "iso:country":"US",
    "sg:address":"1928 South Blvd",
    "sg:city":"Charlotte",
    "sg:classifiers":[
        {
            "category":"Real Estate",
            "subcategory":"Architect",
            "type":"Services"
        }
    ],
    "sg:phone":"+1 704 333 5931",
    "sg:postcode":"28203",
    "sg:province":"NC",
    "sg:tags":[
        "specification",
        "construction",
        "architectural",
        "engineer"
    ],
    "wof:name":"Bartlett Associates Mgstrtgs",
    "wof:placetype":"venue"
},
  "geometry": {"coordinates":[-80.859521,35.210082],"type":"Point"}
}