{
  "type": "Feature",
  "properties": {
    "addr:full":"722 Robinson St Lowell NC 28098",
    "addr:housenumber":"722",
    "addr:postcode":"28098",
    "addr:street":"Robinson St",
    "iso:country":"US",
    "sg:address":"722 Robinson St",
    "sg:city":"Lowell",
    "sg:classifiers":[
        {
            "category":"Retail",
            "subcategory":"Auto Repair",
            "type":"Services"
        }
    ],
    "sg:phone":"+1 704 824 9566",
    "sg:postcode":"28098",
    "sg:province":"NC",
    "sg:tags":[
        "truck"
    ],
    "wof:name":"H & J Truck Repair",
    "wof:placetype":"venue"
},
  "geometry": {"coordinates":[-81.10185300000001,35.257666],"type":"Point"}
}