{
  "type": "Feature",
  "properties": {
    "iso:country":"US",
    "sg:address":"1414 E Andrews Ave",
    "sg:city":"Henderson",
    "sg:classifiers":[
        {
            "category":"Shopping",
            "subcategory":"Clothing, Apparel, & Fashions",
            "type":"Retail Goods"
        }
    ],
    "sg:phone":"+1 252 738 9705",
    "sg:postcode":"27536",
    "sg:province":"NC",
    "wof:name":"Royal Home Fashions",
    "wof:placetype":"venue"
},
  "geometry": {"coordinates":[-78.382501,36.318614],"type":"Point"}
}