{
  "type": "Feature",
  "properties": {
    "addr:full":"829 Campanella Ln Raleigh NC 27610",
    "addr:housenumber":"829",
    "addr:postcode":"27610",
    "addr:street":"Campanella Ln",
    "iso:country":"US",
    "sg:address":"829 Campanella Ln",
    "sg:city":"Raleigh",
    "sg:classifiers":[
        {
            "category":"Professional",
            "type":"Services"
        }
    ],
    "sg:phone":"+1 919 839 0566",
    "sg:postcode":"27610",
    "sg:province":"NC",
    "wof:name":"M J Svc",
    "wof:placetype":"venue"
},
  "geometry": {"coordinates":[-78.624593,35.748856],"type":"Point"}
}