{
  "type": "Feature",
  "properties": {
    "addr:full":"101 S Main St Creedmoor NC 27522",
    "addr:housenumber":"101",
    "addr:postcode":"27522",
    "addr:street":"S Main St",
    "iso:country":"US",
    "sg:address":"101 S Main St",
    "sg:city":"Creedmoor",
    "sg:classifiers":[
        {
            "category":"Autos & Motor Vehicles",
            "subcategory":"Fuel & Gas Station",
            "type":"Retail Goods"
        }
    ],
    "sg:phone":"+1 919 528 0505",
    "sg:postcode":"27522",
    "sg:province":"NC",
    "wof:name":"Boyd's Service Center",
    "wof:placetype":"venue"
},
  "geometry": {"coordinates":[-78.68559999999999,36.122398],"type":"Point"}
}