{
  "type": "Feature",
  "properties": {
    "addr:full":"727 W Hargett St Raleigh NC 27603",
    "addr:housenumber":"727",
    "addr:postcode":"27603",
    "addr:street":"W Hargett St",
    "iso:country":"US",
    "sg:address":"727 W Hargett St",
    "sg:city":"Raleigh",
    "sg:classifiers":[
        {
            "category":"Shopping",
            "type":"Retail Goods"
        }
    ],
    "sg:phone":"+1 919 833 6561",
    "sg:postcode":"27603",
    "sg:province":"NC",
    "sg:tags":[
        "product",
        "for",
        "create",
        "base",
        "tech",
        "child"
    ],
    "wof:name":"Do2learn Foundation",
    "wof:placetype":"venue"
},
  "geometry": {"coordinates":[-78.65046599999999,35.778663],"type":"Point"}
}