{
  "type": "Feature",
  "properties": {
    "iso:country":"US",
    "sg:address":"413 Chesham Dr",
    "sg:city":"Kernersville",
    "sg:classifiers":[
        {
            "category":"Professional",
            "subcategory":"Computer Services",
            "type":"Services"
        }
    ],
    "sg:phone":"+1   ",
    "sg:postcode":"27284",
    "sg:province":"NC",
    "sg:tags":[
        "prepackaged",
        "software"
    ],
    "wof:name":"Norris Software Development",
    "wof:placetype":"venue"
},
  "geometry": {"coordinates":[-80.119519,36.12132],"type":"Point"}
}