{
  "type": "Feature",
  "properties": {
    "addr:full":"6720 Constitution Ln Charlotte NC 28210",
    "addr:housenumber":"6720",
    "addr:postcode":"28210",
    "addr:street":"Constitution Ln",
    "iso:country":"US",
    "sg:address":"6720 Constitution Ln",
    "sg:city":"Charlotte",
    "sg:classifiers":[
        {
            "category":"Professional",
            "subcategory":"Business Services",
            "type":"Services"
        }
    ],
    "sg:phone":"+1   ",
    "sg:postcode":"28210",
    "sg:province":"NC",
    "wof:name":"San Miguel Imports",
    "wof:placetype":"venue"
},
  "geometry": {"coordinates":[-80.846659,35.123242],"type":"Point"}
}