{
  "type": "Feature",
  "properties": {
    "addr:full":"8129 Riley Hill Rd Zebulon NC 27597",
    "addr:housenumber":"8129",
    "addr:postcode":"27597",
    "addr:street":"Riley Hill Rd",
    "iso:country":"US",
    "sg:address":"8129 Riley Hill Rd",
    "sg:city":"Zebulon",
    "sg:classifiers":[
        {
            "category":"Retail",
            "subcategory":"Repair Shop",
            "type":"Services"
        }
    ],
    "sg:phone":"+1 919 404 0931",
    "sg:postcode":"27597",
    "sg:province":"NC",
    "sg:tags":[
        "installs",
        "communication",
        "voice",
        "datum",
        "system"
    ],
    "wof:name":"Triangle Tel-Com Inc",
    "wof:placetype":"venue"
},
  "geometry": {"coordinates":[-78.35284,35.84102],"type":"Point"}
}