{
  "type": "Feature",
  "properties": {
    "iso:country":"US",
    "sg:address":"5360 Hendersonville Rd",
    "sg:city":"Fletcher",
    "sg:classifiers":[
        {
            "category":"Shopping",
            "subcategory":"Jewelry",
            "type":"Retail Goods"
        }
    ],
    "sg:phone":"+1 828 684 7744",
    "sg:postcode":"28732",
    "sg:province":"NC",
    "sg:tags":[
        "jeweler"
    ],
    "wof:name":"Princess Body Jewelry",
    "wof:placetype":"venue"
},
  "geometry": {"coordinates":[-82.512551,35.410326],"type":"Point"}
}