{
  "type": "Feature",
  "properties": {
    "iso:country":"US",
    "sg:address":"1094 Turnersburg Hwy",
    "sg:city":"Statesville",
    "sg:classifiers":[
        {
            "category":"Building & Trades",
            "subcategory":"Construction",
            "type":"Services"
        }
    ],
    "sg:phone":"+1 704 876 8765",
    "sg:postcode":"28625",
    "sg:province":"NC",
    "sg:tags":[
        "contractor"
    ],
    "wof:name":"High Country Fireplaces",
    "wof:placetype":"venue"
},
  "geometry": {"coordinates":[-80.846763,35.858955],"type":"Point"}
}