{
  "type": "Feature",
  "properties": {
    "iso:country":"US",
    "sg:address":"6102 Oleander Dr",
    "sg:city":"Wilmington",
    "sg:classifiers":[
        {
            "category":"Government",
            "subcategory":"Fire Station",
            "type":"Public Place"
        }
    ],
    "sg:phone":"+1 910 791 8745",
    "sg:postcode":"28403",
    "sg:province":"NC",
    "sg:tags":[
        "protection"
    ],
    "wof:name":"Seagate Volunteer Fire Dept",
    "wof:placetype":"venue"
},
  "geometry": {"coordinates":[-77.836878,34.210224],"type":"Point"}
}