{
  "type": "Feature",
  "properties": {
    "iso:country":"US",
    "sg:address":"4929 Monroe Rd",
    "sg:city":"Charlotte",
    "sg:classifiers":[
        {
            "category":"Professional",
            "subcategory":"Lawyer & Legal Services",
            "type":"Services"
        }
    ],
    "sg:phone":"+1 704 567 9751",
    "sg:postcode":"28205",
    "sg:province":"NC",
    "sg:tags":[
        "attorney",
        "practice",
        "plan"
    ],
    "wof:name":"Mcnary Law Firm Pa",
    "wof:placetype":"venue"
},
  "geometry": {"coordinates":[-80.778592,35.192118],"type":"Point"}
}