{
  "type": "Feature",
  "properties": {
    "addr:full":"2871 Old US Hwy 29 Thomasville NC 27360",
    "addr:housenumber":"2871",
    "addr:postcode":"27360",
    "addr:street":"Old Us Hwy 29",
    "iso:country":"US",
    "sg:address":"2871 Old US Hwy 29",
    "sg:city":"Thomasville",
    "sg:classifiers":[
        {
            "category":"Retail",
            "subcategory":"Repair Shop",
            "type":"Services"
        }
    ],
    "sg:phone":"+1 336 472 5804",
    "sg:postcode":"27360",
    "sg:province":"NC",
    "sg:tags":[
        "welding"
    ],
    "wof:name":"Mike's Welding & Fabricating",
    "wof:placetype":"venue"
},
  "geometry": {"coordinates":[-80.15659100000001,35.864624],"type":"Point"}
}