{
  "type": "Feature",
  "properties": {
    "addr:full":"10911 Fountaingrove Dr Charlotte NC 28262",
    "addr:housenumber":"10911",
    "addr:postcode":"28262",
    "addr:street":"Fountaingrove Dr",
    "iso:country":"US",
    "sg:address":"10911 Fountaingrove Dr",
    "sg:city":"Charlotte",
    "sg:classifiers":[
        {
            "category":"Building & Trades",
            "subcategory":"Construction",
            "type":"Services"
        }
    ],
    "sg:phone":"+1 704 549 0376",
    "sg:postcode":"28262",
    "sg:province":"NC",
    "sg:tags":[
        "house"
    ],
    "wof:name":"Shea Homes",
    "wof:placetype":"venue"
},
  "geometry": {"coordinates":[-80.75419599999999,35.342277],"type":"Point"}
}