{
  "type": "Feature",
  "properties": {
    "addr:full":"7305 Fisherman Creek Dr Wilmington NC 28405",
    "addr:housenumber":"7305",
    "addr:postcode":"28405",
    "addr:street":"Fisherman Creek Dr",
    "iso:country":"US",
    "sg:address":"7305 Fisherman Creek Dr",
    "sg:city":"Wilmington",
    "sg:classifiers":[
        {
            "category":"Building & Trades",
            "subcategory":"Construction",
            "type":"Services"
        }
    ],
    "sg:phone":"+1 910 794 3935",
    "sg:postcode":"28405",
    "sg:province":"NC",
    "sg:tags":[
        "contractor"
    ],
    "wof:name":"A D Coke Msnry Rstrtion Wtrpro",
    "wof:placetype":"venue"
},
  "geometry": {"coordinates":[-77.817275,34.25763],"type":"Point"}
}