{
  "type": "Feature",
  "properties": {
    "addr:full":"2511 Lane St Durham NC 27707",
    "addr:housenumber":"2511",
    "addr:postcode":"27707",
    "addr:street":"Lane St",
    "iso:country":"US",
    "sg:address":"2511 Lane St",
    "sg:city":"Durham",
    "sg:classifiers":[
        {
            "category":"Shopping",
            "subcategory":"Beauty & Cosmetics",
            "type":"Retail Goods"
        }
    ],
    "sg:phone":"+1 919 682 4673",
    "sg:postcode":"27707",
    "sg:province":"NC",
    "sg:tags":[
        "merchandise"
    ],
    "wof:name":"Anns Mary Kay",
    "wof:placetype":"venue"
},
  "geometry": {"coordinates":[-78.902503,35.965721],"type":"Point"}
}