{
  "type": "Feature",
  "properties": {
    "iso:country":"US",
    "sg:address":"1498 Bland Howell Rd",
    "sg:city":"Kinston",
    "sg:classifiers":[
        {
            "category":"Freight",
            "type":"Transportation"
        }
    ],
    "sg:phone":"+1 252 527 5071",
    "sg:postcode":"28504",
    "sg:province":"NC",
    "sg:tags":[
        "commercial",
        "storage"
    ],
    "wof:name":"Economy Mini Storage",
    "wof:placetype":"venue"
},
  "geometry": {"coordinates":[-77.69525400000001,35.172677],"type":"Point"}
}