{
  "type": "Feature",
  "properties": {
    "iso:country":"US",
    "sg:address":"3306 Jupiter St",
    "sg:city":"Raleigh",
    "sg:classifiers":[
        {
            "category":"Building & Trades",
            "subcategory":"Construction",
            "type":"Services"
        }
    ],
    "sg:phone":"+1 919 255 6160",
    "sg:postcode":"27604",
    "sg:province":"NC",
    "sg:tags":[
        "painter"
    ],
    "wof:name":"Leonard Lavoie Painting",
    "wof:placetype":"venue"
},
  "geometry": {"coordinates":[-78.578148,35.824928],"type":"Point"}
}