{
  "type": "Feature",
  "properties": {
    "iso:country":"US",
    "sg:address":"3473 Thorndike Dr",
    "sg:city":"Fayetteville",
    "sg:classifiers":[
        {
            "category":"Wholesale",
            "subcategory":"Electrical",
            "type":"Manufacturing & Wholesale Goods"
        }
    ],
    "sg:phone":"+1 910 826 1234",
    "sg:postcode":"28311",
    "sg:province":"NC",
    "sg:tags":[
        "control",
        "security",
        "system"
    ],
    "wof:name":"Enterprise Security",
    "wof:placetype":"venue"
},
  "geometry": {"coordinates":[-78.89876700000001,35.105915],"type":"Point"}
}