{
  "type": "Feature",
  "properties": {
    "iso:country":"US",
    "sg:address":"309 W Weaver St",
    "sg:city":"Carrboro",
    "sg:classifiers":[
        {
            "category":"Insurance",
            "subcategory":"Insurance Agent",
            "type":"Services"
        }
    ],
    "sg:phone":"+1 919 932 9990",
    "sg:postcode":"27510",
    "sg:province":"NC",
    "wof:name":"Alex Maiolo Lee-Moore Ins Svc",
    "wof:placetype":"venue"
},
  "geometry": {"coordinates":[-79.075096,35.911106],"type":"Point"}
}