{
  "type": "Feature",
  "properties": {
    "iso:country":"US",
    "sg:address":"401 E Broad St",
    "sg:city":"Dunn",
    "sg:classifiers":[
        {
            "category":"Government",
            "subcategory":"Police Station",
            "type":"Public Place"
        }
    ],
    "sg:phone":"+1 910 892 2716",
    "sg:postcode":"28334",
    "sg:province":"NC",
    "sg:tags":[
        "department"
    ],
    "wof:name":"Dunn City Police Criminal",
    "wof:placetype":"venue"
},
  "geometry": {"coordinates":[-78.60687,35.3063],"type":"Point"}
}