{
  "type": "Feature",
  "properties": {
    "addr:full":"1222 NW Maynard Rd Cary NC 27513",
    "addr:housenumber":"1222",
    "addr:postcode":"27513",
    "addr:street":"Nw Maynard Rd",
    "iso:country":"US",
    "sg:address":"1222 NW Maynard Rd",
    "sg:city":"Cary",
    "sg:classifiers":[
        {
            "category":"Home & Garden",
            "subcategory":"Building Materials",
            "type":"Retail Goods"
        }
    ],
    "sg:phone":"+1 919 468 3685",
    "sg:postcode":"27513",
    "sg:province":"NC",
    "wof:name":"Pittsburgh Paint & Wlpr Cary",
    "wof:placetype":"venue"
},
  "geometry": {"coordinates":[-78.80988600000001,35.784046],"type":"Point"}
}