{
  "type": "Feature",
  "properties": {
    "addr:full":"1808 White Lake Dr Elizabethtown NC 28337",
    "addr:housenumber":"1808",
    "addr:postcode":"28337",
    "addr:street":"White Lake Dr",
    "iso:country":"US",
    "sg:address":"1808 White Lake Dr",
    "sg:city":"Elizabethtown",
    "sg:classifiers":[
        {
            "category":"Real Estate",
            "subcategory":"Real Estate Operator",
            "type":"Services"
        }
    ],
    "sg:phone":"+1 910 862 4030",
    "sg:postcode":"28337",
    "sg:province":"NC",
    "sg:tags":[
        "apartment"
    ],
    "wof:name":"Isley's Apartments",
    "wof:placetype":"venue"
},
  "geometry": {"coordinates":[-78.48604,34.633289],"type":"Point"}
}