{
  "type": "Feature",
  "properties": {
    "iso:country":"US",
    "sg:address":"805 Ayersville Rd",
    "sg:city":"Madison",
    "sg:classifiers":[
        {
            "category":"Building & Trades",
            "subcategory":"Construction",
            "type":"Services"
        }
    ],
    "sg:phone":"+1 336 427 5949",
    "sg:postcode":"27025",
    "sg:province":"NC",
    "sg:tags":[
        "carpentry",
        "contractor"
    ],
    "wof:name":"Heritage Cabinets & Woodwork",
    "wof:placetype":"venue"
},
  "geometry": {"coordinates":[-79.977583,36.403299],"type":"Point"}
}