{
  "type": "Feature",
  "properties": {
    "iso:country":"US",
    "sg:address":"6315 Fayetteville Rd",
    "sg:city":"Durham",
    "sg:classifiers":[
        {
            "category":"Shopping",
            "subcategory":"Clothing, Apparel, & Fashions",
            "type":"Retail Goods"
        }
    ],
    "sg:phone":"+1 919 806 5300",
    "sg:postcode":"27713",
    "sg:province":"NC",
    "sg:tags":[
        "infant",
        "wear"
    ],
    "wof:name":"Chickadees A Children's Btq",
    "wof:placetype":"venue"
},
  "geometry": {"coordinates":[-78.933493,35.912942],"type":"Point"}
}