{
  "type": "Feature",
  "properties": {
    "iso:country":"US",
    "sg:address":"404 E Harnett St",
    "sg:city":"Benson",
    "sg:classifiers":[
        {
            "category":"Shopping",
            "type":"Retail Goods"
        }
    ],
    "sg:phone":"+1 919 894 4200",
    "sg:postcode":"27504",
    "sg:province":"NC",
    "sg:tags":[
        "pet",
        "food",
        "supply"
    ],
    "wof:name":"Deana's Dog House",
    "wof:placetype":"venue"
},
  "geometry": {"coordinates":[-78.54487,35.377096],"type":"Point"}
}