{
  "type": "Feature",
  "properties": {
    "addr:full":"1291 Merrimon Ave Asheville NC 28804",
    "addr:housenumber":"1291",
    "addr:postcode":"28804",
    "addr:street":"Merrimon Ave",
    "iso:country":"US",
    "sg:address":"1291 Merrimon Ave",
    "sg:city":"Asheville",
    "sg:classifiers":[
        {
            "category":"Real Estate",
            "subcategory":"Developer",
            "type":"Services"
        }
    ],
    "sg:phone":"+1 828 253 5580",
    "sg:postcode":"28804",
    "sg:province":"NC",
    "sg:tags":[
        "cemetery"
    ],
    "wof:name":"Absalom Dillingham Cemete",
    "wof:placetype":"venue"
},
  "geometry": {"coordinates":[-82.565713,35.636114],"type":"Point"}
}