{
  "type": "Feature",
  "properties": {
    "addr:full":"7500 Market St Wilmington NC 28411",
    "addr:housenumber":"7500",
    "addr:postcode":"28411",
    "addr:street":"Market St",
    "iso:country":"US",
    "sg:address":"7500 Market St",
    "sg:city":"Wilmington",
    "sg:classifiers":[
        {
            "category":"Social Services",
            "subcategory":"Child Care",
            "type":"Services"
        }
    ],
    "sg:phone":"+1 910 686 4742",
    "sg:postcode":"28411",
    "sg:province":"NC",
    "sg:tags":[
        "day"
    ],
    "wof:name":"Lutheran Church of Reconciliation Elca",
    "wof:placetype":"venue"
},
  "geometry": {"coordinates":[-77.81210299999999,34.279999],"type":"Point"}
}