{
  "type": "Feature",
  "properties": {
    "iso:country":"US",
    "sg:address":"1726 E Maple St",
    "sg:city":"Goldsboro",
    "sg:classifiers":[
        {
            "category":"Building & Trades",
            "subcategory":"Cleaning & Sanitation",
            "type":"Services"
        }
    ],
    "sg:phone":"+1   ",
    "sg:postcode":"27530",
    "sg:province":"NC",
    "sg:tags":[
        "maintenance"
    ],
    "wof:name":"Underwood Cleaning Services",
    "wof:placetype":"venue"
},
  "geometry": {"coordinates":[-77.965107,35.383935],"type":"Point"}
}