{
  "type": "Feature",
  "properties": {
    "addr:full":"559 N Raleigh St Angier NC 27501",
    "addr:housenumber":"559",
    "addr:postcode":"27501",
    "addr:street":"N Raleigh St",
    "iso:country":"US",
    "sg:address":"559 N Raleigh St",
    "sg:city":"Angier",
    "sg:classifiers":[
        {
            "category":"Food & Beverages",
            "subcategory":"Meat & Fish",
            "type":"Retail Goods"
        }
    ],
    "sg:phone":"+1 919 639 2301",
    "sg:postcode":"27501",
    "sg:province":"NC",
    "sg:tags":[
        "seafood"
    ],
    "wof:name":"J & K Seafood Market",
    "wof:placetype":"venue"
},
  "geometry": {"coordinates":[-78.740838,35.513433],"type":"Point"}
}