{
  "type": "Feature",
  "properties": {
    "addr:full":"220 Hopkins Rd Kernersville NC 27284",
    "addr:housenumber":"220",
    "addr:postcode":"27284",
    "addr:street":"Hopkins Rd",
    "iso:country":"US",
    "sg:address":"220 Hopkins Rd",
    "sg:city":"Kernersville",
    "sg:classifiers":[
        {
            "category":"Recreation",
            "type":"Entertainment"
        }
    ],
    "sg:phone":"+1 336 992 2658",
    "sg:postcode":"27284",
    "sg:province":"NC",
    "sg:tags":[
        "instruction",
        "gymnastic"
    ],
    "wof:name":"Cheer Extreme Allstars",
    "wof:placetype":"venue"
},
  "geometry": {"coordinates":[-80.096519,36.113163],"type":"Point"}
}