{
  "type": "Feature",
  "properties": {
    "iso:country":"US",
    "sg:address":"345 Hasty School Rd",
    "sg:city":"Thomasville",
    "sg:classifiers":[
        {
            "category":"Retail",
            "subcategory":"Repair Shop",
            "type":"Services"
        }
    ],
    "sg:phone":"+1 336 472 7952",
    "sg:postcode":"27360",
    "sg:province":"NC",
    "sg:tags":[
        "appliance"
    ],
    "wof:name":"Mahan Appliance Co",
    "wof:placetype":"venue"
},
  "geometry": {"coordinates":[-80.082942,35.921397],"type":"Point"}
}