{
  "type": "Feature",
  "properties": {
    "iso:country":"US",
    "sg:address":"204 Granville St",
    "sg:city":"Oxford",
    "sg:classifiers":[
        {
            "category":"Retail",
            "subcategory":"Laundry & Dry Cleaning",
            "type":"Services"
        }
    ],
    "sg:phone":"+1   ",
    "sg:postcode":"27565",
    "sg:province":"NC",
    "sg:tags":[
        "drycleaning",
        "plant"
    ],
    "wof:name":"Best Cleaners",
    "wof:placetype":"venue"
},
  "geometry": {"coordinates":[-78.59123099999999,36.308556],"type":"Point"}
}