{
  "type": "Feature",
  "properties": {
    "iso:country":"US",
    "sg:address":"9924 Industrial Dr",
    "sg:city":"Pineville",
    "sg:classifiers":[
        {
            "category":"Freight",
            "type":"Transportation"
        }
    ],
    "sg:phone":"+1 704 554 6260",
    "sg:postcode":"28134",
    "sg:province":"NC",
    "sg:tags":[
        "commercial",
        "storage"
    ],
    "wof:name":"Southland Mini Storage",
    "wof:placetype":"venue"
},
  "geometry": {"coordinates":[-80.890443,35.100992],"type":"Point"}
}