{
  "type": "Feature",
  "properties": {
    "addr:full":"7092 State Hwy 43 S Greenville NC 27858",
    "addr:housenumber":"7092",
    "addr:postcode":"27858",
    "addr:street":"State Hwy 43 S",
    "iso:country":"US",
    "sg:address":"7092 State Hwy 43 S",
    "sg:city":"Greenville",
    "sg:classifiers":[
        {
            "category":"Retail",
            "subcategory":"Repair Shop",
            "type":"Services"
        }
    ],
    "sg:phone":"+1 252 717 9075",
    "sg:postcode":"27858",
    "sg:province":"NC",
    "sg:tags":[
        "welding"
    ],
    "wof:name":"Ferrell's Welding",
    "wof:placetype":"venue"
},
  "geometry": {"coordinates":[-77.290622,35.473129],"type":"Point"}
}