{
  "type": "Feature",
  "properties": {
    "addr:full":"701 Merrimon Ave Asheville NC 28804",
    "addr:housenumber":"701",
    "addr:postcode":"28804",
    "addr:street":"Merrimon Ave",
    "iso:country":"US",
    "sg:address":"701 Merrimon Ave",
    "sg:city":"Asheville",
    "sg:classifiers":[
        {
            "category":"Shopping",
            "subcategory":"Used Merchandise",
            "type":"Retail Goods"
        }
    ],
    "sg:phone":"+1 828 253 2244",
    "sg:postcode":"28804",
    "sg:province":"NC",
    "sg:tags":[
        "antique"
    ],
    "wof:name":"Arlene's Antiques",
    "wof:placetype":"venue"
},
  "geometry": {"coordinates":[-82.554405,35.621322],"type":"Point"}
}