{
  "type": "Feature",
  "properties": {
    "addr:full":"5201 Holly Ct Clayton NC 27520",
    "addr:housenumber":"5201",
    "addr:postcode":"27520",
    "addr:street":"Holly Ct",
    "iso:country":"US",
    "sg:address":"5201 Holly Ct",
    "sg:city":"Clayton",
    "sg:classifiers":[
        {
            "category":"Building & Trades",
            "subcategory":"Construction",
            "type":"Services"
        }
    ],
    "sg:phone":"+1 919 550 0145",
    "sg:postcode":"27520",
    "sg:province":"NC",
    "sg:tags":[
        "hanging",
        "contractor"
    ],
    "wof:name":"Pollard Ventures Inc",
    "wof:placetype":"venue"
},
  "geometry": {"coordinates":[-78.49860700000001,35.681302],"type":"Point"}
}