{
  "type": "Feature",
  "properties": {
    "iso:country":"US",
    "sg:address":"2535 Providence Rd",
    "sg:city":"Charlotte",
    "sg:classifiers":[
        {
            "category":"Professional",
            "subcategory":"Business Services",
            "type":"Services"
        }
    ],
    "sg:phone":"+1   ",
    "sg:postcode":"28211",
    "sg:province":"NC",
    "wof:name":"Novus Solutions LLC",
    "wof:placetype":"venue"
},
  "geometry": {"coordinates":[-80.811487,35.173525],"type":"Point"}
}