{
  "type": "Feature",
  "properties": {
    "iso:country":"US",
    "sg:address":"107 Longs Trl",
    "sg:city":"Hampstead",
    "sg:classifiers":[
        {
            "category":"Restaurant",
            "type":"Food & Drink"
        }
    ],
    "sg:phone":"+1 910 270 1097",
    "sg:postcode":"28455",
    "sg:province":"NC",
    "wof:name":"King's Table",
    "wof:placetype":"venue"
},
  "geometry": {"coordinates":[-78.654055,34.114569],"type":"Point"}
}