{
  "type": "Feature",
  "properties": {
    "iso:country":"US",
    "sg:address":"102 E 2nd St",
    "sg:city":"Washington",
    "sg:classifiers":[
        {
            "category":"Government",
            "subcategory":"Office",
            "type":"Public Place"
        }
    ],
    "sg:phone":"+1 252 975 9306",
    "sg:postcode":"27889",
    "sg:province":"NC",
    "sg:tags":[
        "village"
    ],
    "wof:name":"Washington Electric-Water-Swr",
    "wof:placetype":"venue"
},
  "geometry": {"coordinates":[-77.054247,35.543283],"type":"Point"}
}