{
  "type": "Feature",
  "properties": {
    "addr:full":"3948 Hodges Chapel Rd Dunn NC 28334",
    "addr:housenumber":"3948",
    "addr:postcode":"28334",
    "addr:street":"Hodges Chapel Rd",
    "iso:country":"US",
    "sg:address":"3948 Hodges Chapel Rd",
    "sg:city":"Dunn",
    "sg:classifiers":[
        {
            "category":"Restaurant",
            "type":"Food & Drink"
        }
    ],
    "sg:menulink":"http://www.allmenus.com/nc/averasboro/137234-subway/menu/",
    "sg:phone":"+1 910 892 0216",
    "sg:postcode":"28334",
    "sg:province":"NC",
    "sg:tags":[
        "american",
        "sandwich"
    ],
    "wof:name":"Subway",
    "wof:placetype":"venue"
},
  "geometry": {"coordinates":[-78.554547,35.33533],"type":"Point"}
}