{
  "type": "Feature",
  "properties": {
    "iso:country":"US",
    "sg:address":"1131 Linda Ln",
    "sg:city":"Charlotte",
    "sg:classifiers":[
        {
            "category":"Professional",
            "type":"Services"
        }
    ],
    "sg:phone":"+1 704 366 8514",
    "sg:postcode":"28211",
    "sg:province":"NC",
    "wof:name":"Nin Shelia Prince El",
    "wof:placetype":"venue"
},
  "geometry": {"coordinates":[-80.787807,35.183279],"type":"Point"}
}