{
  "type": "Feature",
  "properties": {
    "addr:full":"100 Sas Campus Dr Cary NC 27513",
    "addr:housenumber":"100",
    "addr:postcode":"27513",
    "addr:street":"Campus Dr",
    "iso:country":"US",
    "sg:address":"100 Sas Campus Dr",
    "sg:city":"Cary",
    "sg:classifiers":[
        {
            "category":"Restaurant",
            "type":"Food & Drink"
        }
    ],
    "sg:phone":"+1 919 677 8000",
    "sg:postcode":"27513",
    "sg:province":"NC",
    "sg:tags":[
        "traditional",
        "american"
    ],
    "sg:website":"www.sas.com",
    "wof:name":"SAS",
    "wof:placetype":"venue"
},
  "geometry": {"coordinates":[-78.765681,35.829346],"type":"Point"}
}