{
  "type": "Feature",
  "properties": {
    "addr:full":"4107 Chevington Rd Charlotte NC 28226",
    "addr:housenumber":"4107",
    "addr:postcode":"28226",
    "addr:street":"Chevington Rd",
    "iso:country":"US",
    "sg:address":"4107 Chevington Rd",
    "sg:city":"Charlotte",
    "sg:classifiers":[
        {
            "category":"Professional",
            "subcategory":"Management & Consulting",
            "type":"Services"
        }
    ],
    "sg:phone":"+1   ",
    "sg:postcode":"28226",
    "sg:province":"NC",
    "wof:name":"Pettit Asset Planning Inc",
    "wof:placetype":"venue"
},
  "geometry": {"coordinates":[-80.815281,35.14404],"type":"Point"}
}