{
  "type": "Feature",
  "properties": {
    "addr:full":"1428 Ridgecrest Dr Hendersonville NC 28792",
    "addr:housenumber":"1428",
    "addr:postcode":"28792",
    "addr:street":"Ridgecrest Dr",
    "iso:country":"US",
    "sg:address":"1428 Ridgecrest Dr",
    "sg:city":"Hendersonville",
    "sg:classifiers":[
        {
            "category":"Professional",
            "subcategory":"Business Services",
            "type":"Services"
        }
    ],
    "sg:phone":"+1   ",
    "sg:postcode":"28792",
    "sg:province":"NC",
    "sg:tags":[
        "interior",
        "design"
    ],
    "wof:name":"Jean Bailey Interiors",
    "wof:placetype":"venue"
},
  "geometry": {"coordinates":[-82.46666999999999,35.328596],"type":"Point"}
}