{
  "type": "Feature",
  "properties": {
    "addr:full":"59 Upper Roberts Branch Rd Weaverville NC 28787",
    "addr:housenumber":"59",
    "addr:postcode":"28787",
    "addr:street":"Upper Roberts Branch Rd",
    "iso:country":"US",
    "sg:address":"59 Upper Roberts Branch Rd",
    "sg:city":"Weaverville",
    "sg:classifiers":[
        {
            "category":"Personal",
            "subcategory":"Beauty Salon",
            "type":"Services"
        }
    ],
    "sg:phone":"+1   ",
    "sg:postcode":"28787",
    "sg:province":"NC",
    "sg:tags":[
        "shop"
    ],
    "wof:name":"Styles Clarence P Styles",
    "wof:placetype":"venue"
},
  "geometry": {"coordinates":[-82.537412,35.760806],"type":"Point"}
}