{
  "type": "Feature",
  "properties": {
    "iso:country":"US",
    "sg:address":"374 Hidden Pond Rd",
    "sg:city":"Boone",
    "sg:classifiers":[
        {
            "category":"Insurance",
            "subcategory":"Insurance Agent",
            "type":"Services"
        }
    ],
    "sg:phone":"+1 828 264 2555",
    "sg:postcode":"28607",
    "sg:province":"NC",
    "wof:name":"Don Butler & Assoc",
    "wof:placetype":"venue"
},
  "geometry": {"coordinates":[-81.610382,36.219961],"type":"Point"}
}