{
  "type": "Feature",
  "properties": {
    "iso:country":"US",
    "sg:address":"250 White Oak St",
    "sg:city":"Franklin",
    "sg:classifiers":[
        {
            "category":"Health Services",
            "subcategory":"Doctor",
            "type":"Services"
        }
    ],
    "sg:phone":"+1 828 524 7477",
    "sg:postcode":"28734",
    "sg:province":"NC",
    "sg:tags":[
        "dentist"
    ],
    "wof:name":"Ralph S Kurti DDS",
    "wof:placetype":"venue"
},
  "geometry": {"coordinates":[-83.37819,35.185469],"type":"Point"}
}