{
  "type": "Feature",
  "properties": {
    "addr:full":"1633 Old Milburnie Rd Raleigh NC 27604",
    "addr:housenumber":"1633",
    "addr:postcode":"27604",
    "addr:street":"Old Milburnie Rd",
    "iso:country":"US",
    "sg:address":"1633 Old Milburnie Rd",
    "sg:city":"Raleigh",
    "sg:classifiers":[
        {
            "category":"Building & Trades",
            "subcategory":"Construction",
            "type":"Services"
        }
    ],
    "sg:phone":"+1 919 266 0557",
    "sg:postcode":"27604",
    "sg:province":"NC",
    "sg:tags":[
        "contractor",
        "grading"
    ],
    "wof:name":"Adcock Contracting",
    "wof:placetype":"venue"
},
  "geometry": {"coordinates":[-78.52723,35.809449],"type":"Point"}
}