{
  "type": "Feature",
  "properties": {
    "iso:country":"US",
    "sg:address":"4203 Hewitt St",
    "sg:city":"Greensboro",
    "sg:classifiers":[
        {
            "category":"Health Services",
            "subcategory":"Medical Lab",
            "type":"Services"
        }
    ],
    "sg:phone":"+1 336 315 9765",
    "sg:postcode":"27407",
    "sg:province":"NC",
    "sg:tags":[
        "laboratory"
    ],
    "wof:name":"Fairfax Identiy Lab",
    "wof:placetype":"venue"
},
  "geometry": {"coordinates":[-79.866422,36.056482],"type":"Point"}
}