{
  "type": "Feature",
  "properties": {
    "addr:full":"3201 1st Ave SW Hickory NC 28602",
    "addr:housenumber":"3201",
    "addr:postcode":"28602",
    "addr:street":"1St Ave Sw",
    "iso:country":"US",
    "sg:address":"3201 1st Ave SW",
    "sg:city":"Hickory",
    "sg:classifiers":[
        {
            "category":"Banks & Credit Unions",
            "subcategory":"Bank",
            "type":"Services"
        }
    ],
    "sg:phone":"+1 828 326 6880",
    "sg:postcode":"28602",
    "sg:province":"NC",
    "wof:name":"B B & T",
    "wof:placetype":"venue"
},
  "geometry": {"coordinates":[-81.39292399999999,35.728428],"type":"Point"}
}