{
  "type": "Feature",
  "properties": {
    "addr:full":"1332 W Ehringhaus St Elizabeth City NC 27909",
    "addr:housenumber":"1332",
    "addr:postcode":"27909",
    "addr:street":"W Ehringhaus St",
    "iso:country":"US",
    "sg:address":"1332 W Ehringhaus St",
    "sg:city":"Elizabeth City",
    "sg:classifiers":[
        {
            "category":"Autos & Motor Vehicles",
            "subcategory":"Auto Supplies",
            "type":"Retail Goods"
        }
    ],
    "sg:phone":"+1 252 335 5421",
    "sg:postcode":"27909",
    "sg:province":"NC",
    "sg:tags":[
        "automobile",
        "parts"
    ],
    "wof:name":"Mc Pherson Auto Supply",
    "wof:placetype":"venue"
},
  "geometry": {"coordinates":[-76.23937599999999,36.294976],"type":"Point"}
}