{
  "type": "Feature",
  "properties": {
    "iso:country":"US",
    "sg:address":"4324 Republic Ct NW",
    "sg:city":"Concord",
    "sg:classifiers":[
        {
            "category":"Autos & Motor Vehicles",
            "subcategory":"Automobile Sales",
            "type":"Retail Goods"
        }
    ],
    "sg:phone":"+1 704 788 8225",
    "sg:postcode":"28027",
    "sg:province":"NC",
    "sg:tags":[
        "dealers-used",
        "car",
        "used",
        "cars-wholesale"
    ],
    "wof:name":"Quality Auto Sales",
    "wof:placetype":"venue"
},
  "geometry": {"coordinates":[-80.652158,35.421017],"type":"Point"}
}