{
  "type": "Feature",
  "properties": {
    "addr:full":"3650 Mount Zion Church Rd Maxton NC 28364",
    "addr:housenumber":"3650",
    "addr:postcode":"28364",
    "addr:street":"Mount Zion Church Rd",
    "iso:country":"US",
    "sg:address":"3650 Mount Zion Church Rd",
    "sg:city":"Maxton",
    "sg:classifiers":[
        {
            "category":"Organizations",
            "subcategory":"Religious Organization",
            "type":"Services"
        }
    ],
    "sg:phone":"+1   ",
    "sg:postcode":"28364",
    "sg:province":"NC",
    "wof:name":"Mt Zion United Methodist Churc",
    "wof:placetype":"venue"
},
  "geometry": {"coordinates":[-79.238586,34.812315],"type":"Point"}
}