{
  "type": "Feature",
  "properties": {
    "addr:full":"115 Oakridge Ave Fayetteville NC 28305",
    "addr:housenumber":"115",
    "addr:postcode":"28305",
    "addr:street":"Oakridge Ave",
    "iso:country":"US",
    "sg:address":"115 Oakridge Ave",
    "sg:city":"Fayetteville",
    "sg:classifiers":[
        {
            "category":"Restaurant",
            "type":"Food & Drink"
        }
    ],
    "sg:phone":"+1 910 483 2777",
    "sg:postcode":"28305",
    "sg:province":"NC",
    "sg:tags":[
        "caterer"
    ],
    "wof:name":"Cooking Connection",
    "wof:placetype":"venue"
},
  "geometry": {"coordinates":[-78.899325,35.057255],"type":"Point"}
}