{
  "type": "Feature",
  "properties": {
    "addr:full":"5106 S College Rd Wilmington NC 28412",
    "addr:housenumber":"5106",
    "addr:postcode":"28412",
    "addr:street":"S College Rd",
    "iso:country":"US",
    "sg:address":"5106 S College Rd",
    "sg:city":"Wilmington",
    "sg:classifiers":[
        {
            "category":"Professional",
            "type":"Services"
        }
    ],
    "sg:phone":"+1 910 796 6760",
    "sg:postcode":"28412",
    "sg:province":"NC",
    "wof:name":"Megapath Networks",
    "wof:placetype":"venue"
},
  "geometry": {"coordinates":[-77.892537,34.147327],"type":"Point"}
}