{
  "type": "Feature",
  "properties": {
    "addr:full":"5400 Statesville Rd Charlotte NC 28269",
    "addr:postcode":"5400;28269",
    "addr:street":"Statesville Rd",
    "iso:country":"US",
    "sg:address":"5400 Statesville Rd",
    "sg:city":"Charlotte",
    "sg:classifiers":[
        {
            "category":"Professional",
            "type":"Services"
        }
    ],
    "sg:phone":"+1 704 494 3533",
    "sg:postcode":"28269",
    "sg:province":"NC",
    "wof:name":"Georgias Toufekoulas",
    "wof:placetype":"venue"
},
  "geometry": {"coordinates":[-80.838961,35.29455],"type":"Point"}
}