{
  "type": "Feature",
  "properties": {
    "iso:country":"US",
    "sg:address":"5643 Creedmoor Rd",
    "sg:city":"Raleigh",
    "sg:classifiers":[
        {
            "category":"Retail",
            "subcategory":"Photofinishing",
            "type":"Services"
        }
    ],
    "sg:phone":"+1   ",
    "sg:postcode":"27612",
    "sg:province":"NC",
    "wof:name":"Foto 40",
    "wof:placetype":"venue"
},
  "geometry": {"coordinates":[-78.68062,35.858791],"type":"Point"}
}