{
  "type": "Feature",
  "properties": {
    "iso:country":"US",
    "sg:address":"1111 Louise Rd",
    "sg:city":"Winston Salem",
    "sg:classifiers":[
        {
            "category":"Building & Trades",
            "subcategory":"Construction",
            "type":"Services"
        }
    ],
    "sg:phone":"+1 336 788 4982",
    "sg:postcode":"27107",
    "sg:province":"NC",
    "wof:name":"Luther N Leak Construction Co",
    "wof:placetype":"venue"
},
  "geometry": {"coordinates":[-80.210015,36.056123],"type":"Point"}
}