{
  "type": "Feature",
  "properties": {
    "iso:country":"US",
    "sg:address":"1589 Zoo Pkwy",
    "sg:city":"Asheboro",
    "sg:classifiers":[
        {
            "category":"Shopping",
            "subcategory":"Books",
            "type":"Retail Goods"
        }
    ],
    "sg:phone":"+1 336 626 6594",
    "sg:postcode":"27205",
    "sg:province":"NC",
    "sg:tags":[
        "dealer"
    ],
    "wof:name":"Daniels Read-A-Lot",
    "wof:placetype":"venue"
},
  "geometry": {"coordinates":[-79.80902,35.685815],"type":"Point"}
}