{
  "type": "Feature",
  "properties": {
    "iso:country":"US",
    "sg:address":"1143 Marlowe Rd",
    "sg:city":"Tabor City",
    "sg:classifiers":[
        {
            "category":"Professional",
            "subcategory":"Business Services",
            "type":"Services"
        }
    ],
    "sg:phone":"+1   ",
    "sg:postcode":"28463",
    "sg:province":"NC",
    "wof:name":"Lap 3 Enterprises Inc",
    "wof:placetype":"venue"
},
  "geometry": {"coordinates":[-78.736217,34.023958],"type":"Point"}
}