{
  "type": "Feature",
  "properties": {
    "iso:country":"US",
    "sg:address":"3741b Battleground Ave",
    "sg:city":"Greensboro",
    "sg:classifiers":[
        {
            "category":"Restaurant",
            "type":"Food & Drink"
        }
    ],
    "sg:menulink":"http://www.allmenus.com/nc/greensboro/115784-quiznos-sub/menu/",
    "sg:phone":"+1 336 545 5535",
    "sg:postcode":"27410",
    "sg:province":"NC",
    "sg:tags":[
        "wrap",
        "american",
        "sandwich"
    ],
    "wof:name":"Quiznos Sub",
    "wof:placetype":"venue"
},
  "geometry": {"coordinates":[-79.85763300000001,36.133369],"type":"Point"}
}