{
  "type": "Feature",
  "properties": {
    "addr:full":"38 Donna Ln Alexander NC 28701",
    "addr:housenumber":"38",
    "addr:postcode":"28701",
    "addr:street":"Donna Ln",
    "iso:country":"US",
    "sg:address":"38 Donna Ln",
    "sg:city":"Alexander",
    "sg:classifiers":[
        {
            "category":"Health Services",
            "subcategory":"Doctor",
            "type":"Services"
        }
    ],
    "sg:phone":"+1   ",
    "sg:postcode":"28701",
    "sg:province":"NC",
    "wof:name":"Cuento Oblendo PA",
    "wof:placetype":"venue"
},
  "geometry": {"coordinates":[-82.62636999999999,35.73976],"type":"Point"}
}