{
  "type": "Feature",
  "properties": {
    "iso:country":"US",
    "sg:address":"4614 Wilgrove Mint Hill Rd",
    "sg:city":"Charlotte",
    "sg:classifiers":[
        {
            "category":"Home & Garden",
            "subcategory":"Building Materials",
            "type":"Retail Goods"
        },
        {
            "category":"Retail",
            "subcategory":"Repair Shop",
            "type":"Services"
        }
    ],
    "sg:phone":"+1 704 573 0420",
    "sg:postcode":"28227",
    "sg:province":"NC",
    "sg:tags":[
        "equipment",
        "electrical",
        "electric",
        "supply"
    ],
    "wof:name":"Power Products & Solutions",
    "wof:placetype":"venue"
},
  "geometry": {"coordinates":[-80.648121,35.181027],"type":"Point"}
}