{
  "type": "Feature",
  "properties": {
    "iso:country":"US",
    "sg:address":"2802 Lee Ave",
    "sg:city":"Sanford",
    "sg:classifiers":[
        {
            "category":"Autos & Motor Vehicles",
            "subcategory":"Auto Supplies",
            "type":"Retail Goods"
        }
    ],
    "sg:phone":"+1 919 777 2947",
    "sg:postcode":"27332",
    "sg:province":"NC",
    "sg:tags":[
        "automobile",
        "accessory"
    ],
    "wof:name":"K & J Auto Accessories",
    "wof:placetype":"venue"
},
  "geometry": {"coordinates":[-79.14769,35.452454],"type":"Point"}
}