{
  "type": "Feature",
  "properties": {
    "addr:full":"5861 Albemarle Rd Charlotte NC 28212",
    "addr:housenumber":"5861",
    "addr:postcode":"28212",
    "addr:street":"Albemarle Rd",
    "iso:country":"US",
    "sg:address":"5861 Albemarle Rd",
    "sg:city":"Charlotte",
    "sg:classifiers":[
        {
            "category":"Food & Beverages",
            "subcategory":"Groceries & Convenience Stores",
            "type":"Retail Goods"
        }
    ],
    "sg:phone":"+1 704 532 0322",
    "sg:postcode":"28212",
    "sg:province":"NC",
    "sg:tags":[
        "japanese"
    ],
    "wof:name":"Island Grocery",
    "wof:placetype":"venue"
},
  "geometry": {"coordinates":[-80.745903,35.203398],"type":"Point"}
}