{
  "type": "Feature",
  "properties": {
    "addr:full":"225 N Salem St Ste 101 Apex NC 27502",
    "addr:housenumber":"225",
    "addr:postcode":"27502",
    "addr:street":"N Salem St Ste 101",
    "iso:country":"US",
    "sg:address":"225 N Salem St Ste 101",
    "sg:city":"Apex",
    "sg:classifiers":[
        {
            "category":"Personal",
            "subcategory":"Day Spa",
            "type":"Services"
        }
    ],
    "sg:phone":"+1 919 387 4166",
    "sg:postcode":"27502",
    "sg:province":"NC",
    "wof:name":"Syeni Llc",
    "wof:placetype":"venue"
},
  "geometry": {"coordinates":[-78.850706,35.73223],"type":"Point"}
}