{
  "type": "Feature",
  "properties": {
    "addr:full":"523 N Aspen St Lincolnton NC 28092",
    "addr:housenumber":"523 n",
    "addr:postcode":"28092",
    "addr:street":"Aspen St",
    "iso:country":"US",
    "sg:address":"523 N Aspen St",
    "sg:city":"Lincolnton",
    "sg:classifiers":[
        {
            "category":"Manufacturing",
            "subcategory":"Printing",
            "type":"Manufacturing & Wholesale Goods"
        }
    ],
    "sg:phone":"+1 704 735 6831",
    "sg:postcode":"28092",
    "sg:province":"NC",
    "sg:tags":[
        "commercial"
    ],
    "wof:name":"Commercial Printing Co",
    "wof:placetype":"venue"
},
  "geometry": {"coordinates":[-81.25896899999999,35.476287],"type":"Point"}
}