{
  "type": "Feature",
  "properties": {
    "addr:full":"9608 University City Blvd Charlotte NC 28213",
    "addr:housenumber":"9608",
    "addr:postcode":"28213",
    "addr:street":"University City Blvd",
    "iso:country":"US",
    "sg:address":"9608 University City Blvd",
    "sg:city":"Charlotte",
    "sg:classifiers":[
        {
            "category":"Food & Beverages",
            "subcategory":"Groceries & Convenience Stores",
            "type":"Retail Goods"
        }
    ],
    "sg:phone":"+1 704 503 6200",
    "sg:postcode":"28213",
    "sg:province":"NC",
    "wof:name":"Sam's Mart",
    "wof:placetype":"venue"
},
  "geometry": {"coordinates":[-80.721575,35.307529],"type":"Point"}
}