{
  "type": "Feature",
  "properties": {
    "iso:country":"US",
    "sg:address":"180 Providence Rd",
    "sg:city":"Chapel Hill",
    "sg:classifiers":[
        {
            "category":"Health Services",
            "subcategory":"Doctor",
            "type":"Services"
        }
    ],
    "sg:phone":"+1 919 493 2895",
    "sg:postcode":"27514",
    "sg:province":"NC",
    "sg:tags":[
        "physician",
        "surgeon"
    ],
    "wof:name":"Lucile D Clotfelter MD",
    "wof:placetype":"venue"
},
  "geometry": {"coordinates":[-79.007507,35.95177],"type":"Point"}
}