{
  "type": "Feature",
  "properties": {
    "iso:country":"US",
    "sg:address":"1917 S Fayetteville St",
    "sg:city":"Asheboro",
    "sg:classifiers":[
        {
            "category":"Retail",
            "subcategory":"Auto Repair",
            "type":"Services"
        }
    ],
    "sg:phone":"+1 336 625 5531",
    "sg:postcode":"27205",
    "sg:province":"NC",
    "sg:tags":[
        "automobile",
        "electric"
    ],
    "wof:name":"Eubanks Generator & Starter",
    "wof:placetype":"venue"
},
  "geometry": {"coordinates":[-79.81795700000001,35.679717],"type":"Point"}
}