{
  "type": "Feature",
  "properties": {
    "addr:full":"896 Hwy 258 N Snow Hill NC 28580",
    "addr:housenumber":"896",
    "addr:postcode":"28580",
    "addr:street":"Hwy 258 N",
    "iso:country":"US",
    "sg:address":"896 Hwy 258 N",
    "sg:city":"Snow Hill",
    "sg:classifiers":[
        {
            "category":"Social Services",
            "subcategory":"Child Care",
            "type":"Services"
        }
    ],
    "sg:phone":"+1   ",
    "sg:postcode":"28580",
    "sg:province":"NC",
    "sg:tags":[
        "day"
    ],
    "wof:name":"Tender Love Child Care Inc",
    "wof:placetype":"venue"
},
  "geometry": {"coordinates":[-77.665031,35.466298],"type":"Point"}
}