{
  "type": "Feature",
  "properties": {
    "addr:full":"307 W Tremont Ave Charlotte NC 28203",
    "addr:housenumber":"307",
    "addr:postcode":"28203",
    "addr:street":"W Tremont Ave",
    "iso:country":"US",
    "sg:address":"307 W Tremont Ave",
    "sg:city":"Charlotte",
    "sg:classifiers":[
        {
            "category":"Home & Garden",
            "subcategory":"Household Appliances",
            "type":"Retail Goods"
        }
    ],
    "sg:phone":"+1 704 332 8301",
    "sg:postcode":"28203",
    "sg:province":"NC",
    "wof:name":"Dj Distributing",
    "wof:placetype":"venue"
},
  "geometry": {"coordinates":[-80.864118,35.210824],"type":"Point"}
}