{
  "type": "Feature",
  "properties": {
    "addr:full":"3000 Capital Blvd Raleigh NC 27604",
    "addr:postcode":"3000;27604",
    "addr:street":"Capital Blvd",
    "iso:country":"US",
    "sg:address":"3000 Capital Blvd",
    "sg:city":"Raleigh",
    "sg:classifiers":[
        {
            "category":"Restaurant",
            "type":"Food & Drink"
        }
    ],
    "sg:menulink":"http://www.allmenus.com/nc/st-matthews/191115-burger-king/menu/",
    "sg:phone":"+1 919 872 2070",
    "sg:postcode":"27604",
    "sg:province":"NC",
    "sg:tags":[
        "burger",
        "american"
    ],
    "wof:name":"Burger King",
    "wof:placetype":"venue"
},
  "geometry": {"coordinates":[-78.592029,35.820225],"type":"Point"}
}