{
  "type": "Feature",
  "properties": {
    "addr:full":"427 29th Avenue Dr NW Hickory NC 28601",
    "addr:housenumber":"427",
    "addr:postcode":"28601",
    "addr:street":"29Th Avenue Dr Nw",
    "iso:country":"US",
    "sg:address":"427 29th Avenue Dr NW",
    "sg:city":"Hickory",
    "sg:classifiers":[
        {
            "category":"Health Services",
            "subcategory":"Clinic",
            "type":"Services"
        }
    ],
    "sg:phone":"+1 828 304 0808",
    "sg:postcode":"28601",
    "sg:province":"NC",
    "sg:tags":[
        "home"
    ],
    "wof:name":"VOCA Corp",
    "wof:placetype":"venue"
},
  "geometry": {"coordinates":[-81.336461,35.773453],"type":"Point"}
}