{
  "type": "Feature",
  "properties": {
    "addr:full":"3215 Pinecroft Rd Greensboro NC 27407",
    "addr:housenumber":"3215",
    "addr:postcode":"27407",
    "addr:street":"Pinecroft Rd",
    "iso:country":"US",
    "sg:address":"3215 Pinecroft Rd",
    "sg:city":"Greensboro",
    "sg:classifiers":[
        {
            "category":"Home & Garden",
            "subcategory":"Building Materials",
            "type":"Retail Goods"
        }
    ],
    "sg:phone":"+1 336 852 6999",
    "sg:postcode":"27407",
    "sg:province":"NC",
    "wof:name":"Innovative Building Solutions",
    "wof:placetype":"venue"
},
  "geometry": {"coordinates":[-79.842011,36.014122],"type":"Point"}
}