{
  "type": "Feature",
  "properties": {
    "addr:full":"1530 Smith Level Rd Chapel Hill NC 27516",
    "addr:housenumber":"1530",
    "addr:postcode":"27516",
    "addr:street":"Smith Level Rd",
    "iso:country":"US",
    "sg:address":"1530 Smith Level Rd",
    "sg:city":"Chapel Hill",
    "sg:classifiers":[
        {
            "category":"Personal",
            "type":"Services"
        }
    ],
    "sg:phone":"+1   ",
    "sg:postcode":"27516",
    "sg:province":"NC",
    "wof:name":"Brighter Living Massage",
    "wof:placetype":"venue"
},
  "geometry": {"coordinates":[-79.080719,35.868559],"type":"Point"}
}