{
  "type": "Feature",
  "properties": {
    "iso:country":"US",
    "sg:address":"100 Dominion Dr",
    "sg:city":"Morrisville",
    "sg:classifiers":[
        {
            "category":"Food & Beverages",
            "subcategory":"Meat & Fish",
            "type":"Retail Goods"
        }
    ],
    "sg:phone":"+1 919 463 7900",
    "sg:postcode":"27560",
    "sg:province":"NC",
    "sg:tags":[
        "shop"
    ],
    "sg:website":"www.horizonfoods.com/",
    "wof:name":"Horizon Foods",
    "wof:placetype":"venue"
},
  "geometry": {"coordinates":[-78.808998,35.840302],"type":"Point"}
}