{
  "type": "Feature",
  "properties": {
    "iso:country":"US",
    "sg:address":"4036 Ridgebrook Bluffs Dr",
    "sg:city":"Raleigh",
    "sg:classifiers":[
        {
            "category":"Manufacturing",
            "subcategory":"Chemicals & Compounds",
            "type":"Manufacturing & Wholesale Goods"
        }
    ],
    "sg:phone":"+1 919 662 0288",
    "sg:postcode":"27603",
    "sg:province":"NC",
    "sg:tags":[
        "gas"
    ],
    "wof:name":"Air Products & Chemicals Inc",
    "wof:placetype":"venue"
},
  "geometry": {"coordinates":[-78.711528,35.663623],"type":"Point"}
}