{
  "type": "Feature",
  "properties": {
    "addr:full":"1204 Gaston Way Dallas NC 28034",
    "addr:housenumber":"1204",
    "addr:postcode":"28034",
    "addr:street":"Gaston Way",
    "iso:country":"US",
    "sg:address":"1204 Gaston Way",
    "sg:city":"Dallas",
    "sg:classifiers":[
        {
            "category":"Professional",
            "type":"Services"
        }
    ],
    "sg:phone":"+1 704 922 5987",
    "sg:postcode":"28034",
    "sg:province":"NC",
    "wof:name":"PBL Assessor",
    "wof:placetype":"venue"
},
  "geometry": {"coordinates":[-81.19488200000001,35.323741],"type":"Point"}
}