{
  "type": "Feature",
  "properties": {
    "iso:country":"US",
    "sg:address":"9040 Nations Ford Rd",
    "sg:city":"Charlotte",
    "sg:classifiers":[
        {
            "category":"Health Services",
            "subcategory":"Doctor",
            "type":"Services"
        }
    ],
    "sg:phone":"+1 704 527 0282",
    "sg:postcode":"28273",
    "sg:province":"NC",
    "sg:tags":[
        "clinic"
    ],
    "wof:name":"First Care Medical Clinic",
    "wof:placetype":"venue"
},
  "geometry": {"coordinates":[-80.891819,35.132088],"type":"Point"}
}