{
  "type": "Feature",
  "properties": {
    "iso:country":"US",
    "sg:address":"2005 Glenwood Ave",
    "sg:city":"Raleigh",
    "sg:classifiers":[
        {
            "category":"Real Estate",
            "subcategory":"Real Estate Agent",
            "type":"Services"
        }
    ],
    "sg:phone":"+1 919 832 3184",
    "sg:postcode":"27608",
    "sg:province":"NC",
    "wof:name":"Jim Stephenson Realtor",
    "wof:placetype":"venue"
},
  "geometry": {"coordinates":[-78.64875000000001,35.808821],"type":"Point"}
}