{
  "type": "Feature",
  "properties": {
    "addr:full":"University Square 123 W Franklin St Chapel Hill NC 27516",
    "addr:housenumber":"123",
    "addr:postcode":"27516",
    "addr:street":"W Franklin St",
    "iso:country":"US",
    "sg:address":"University Square 123 W Franklin St",
    "sg:city":"Chapel Hill",
    "sg:classifiers":[
        {
            "category":"Sports & Exercise",
            "subcategory":"Gym",
            "type":"Entertainment"
        }
    ],
    "sg:phone":"+1 919 929 0414",
    "sg:postcode":"27516",
    "sg:province":"NC",
    "sg:tags":[
        "yoga"
    ],
    "sg:website":"www.franklinstyoga.com",
    "wof:name":"Franklin Street Yoga Center",
    "wof:placetype":"venue"
},
  "geometry": {"coordinates":[-79.05682899999999,35.912735],"type":"Point"}
}