{
  "type": "Feature",
  "properties": {
    "addr:full":"3015 Cardigan Ct Matthews NC 28104",
    "addr:housenumber":"3015",
    "addr:postcode":"28104",
    "addr:street":"Cardigan Ct",
    "iso:country":"US",
    "sg:address":"3015 Cardigan Ct",
    "sg:city":"Matthews",
    "sg:classifiers":[
        {
            "category":"Professional",
            "type":"Services"
        }
    ],
    "sg:phone":"+1 704 882 9331",
    "sg:postcode":"28104",
    "sg:province":"NC",
    "sg:tags":[
        "establishment"
    ],
    "wof:name":"Compsee Inc Matthews",
    "wof:placetype":"venue"
},
  "geometry": {"coordinates":[-80.63629400000001,35.128713],"type":"Point"}
}