{
  "type": "Feature",
  "properties": {
    "iso:country":"US",
    "sg:address":"3048 Elk Ridge Rd",
    "sg:city":"Ferguson",
    "sg:classifiers":[
        {
            "category":"Building & Trades",
            "subcategory":"Construction",
            "type":"Services"
        }
    ],
    "sg:phone":"+1 336 973 3105",
    "sg:postcode":"28624",
    "sg:province":"NC",
    "sg:tags":[
        "general",
        "contractor"
    ],
    "wof:name":"DKA Construction",
    "wof:placetype":"venue"
},
  "geometry": {"coordinates":[-81.453245,36.137055],"type":"Point"}
}