{
  "type": "Feature",
  "properties": {
    "iso:country":"US",
    "sg:address":"425 Cherryville Rd",
    "sg:city":"Shelby",
    "sg:classifiers":[
        {
            "category":"Health Services",
            "subcategory":"Clinic",
            "type":"Services"
        }
    ],
    "sg:phone":"+1 704 484 3294",
    "sg:postcode":"28150",
    "sg:province":"NC",
    "sg:tags":[
        "home"
    ],
    "sg:website":"www.totalcareinc.com",
    "wof:name":"Total Care",
    "wof:placetype":"venue"
},
  "geometry": {"coordinates":[-81.505788,35.302893],"type":"Point"}
}