{
  "type": "Feature",
  "properties": {
    "addr:full":"2800 Watkins Town Rd Raleigh NC 27616",
    "addr:housenumber":"2800",
    "addr:postcode":"27616",
    "addr:street":"Watkins Town Rd",
    "iso:country":"US",
    "sg:address":"2800 Watkins Town Rd",
    "sg:city":"Raleigh",
    "sg:classifiers":[
        {
            "category":"Professional",
            "subcategory":"Advertising",
            "type":"Services"
        }
    ],
    "sg:phone":"+1 919 266 4132",
    "sg:postcode":"27616",
    "sg:province":"NC",
    "sg:tags":[
        "demonstration"
    ],
    "wof:name":"Brenda's Demo Svc",
    "wof:placetype":"venue"
},
  "geometry": {"coordinates":[-78.50010899999999,35.861405],"type":"Point"}
}