{
  "type": "Feature",
  "properties": {
    "iso:country":"US",
    "sg:address":"2429 Bill Tuttle Rd",
    "sg:city":"Lenoir",
    "sg:classifiers":[
        {
            "category":"Manufacturing",
            "subcategory":"Glass & Minerals",
            "type":"Manufacturing & Wholesale Goods"
        }
    ],
    "sg:phone":"+1 828 758 5614",
    "sg:postcode":"28645",
    "sg:province":"NC",
    "sg:tags":[
        "hardware",
        "cut",
        "mfg"
    ],
    "wof:name":"Brakefields Cabinet & Stone",
    "wof:placetype":"venue"
},
  "geometry": {"coordinates":[-81.54818299999999,35.95385],"type":"Point"}
}