{
  "type": "Feature",
  "properties": {
    "addr:full":"1015 Stokes St Burlington NC 27215",
    "addr:housenumber":"1015",
    "addr:postcode":"27215",
    "addr:street":"Stokes St",
    "iso:country":"US",
    "sg:address":"1015 Stokes St",
    "sg:city":"Burlington",
    "sg:classifiers":[
        {
            "category":"Wholesale",
            "subcategory":"Machinery & Supplies",
            "type":"Manufacturing & Wholesale Goods"
        }
    ],
    "sg:phone":"+1 336 227 2723",
    "sg:postcode":"27215",
    "sg:province":"NC",
    "sg:tags":[
        "equipment",
        "industrial"
    ],
    "sg:website":"www.sykessupply.com",
    "wof:name":"Sykes Supply Co",
    "wof:placetype":"venue"
},
  "geometry": {"coordinates":[-79.431217,36.079688],"type":"Point"}
}