{
  "type": "Feature",
  "properties": {
    "iso:country":"US",
    "sg:address":"202 Treva Dr",
    "sg:city":"Greensboro",
    "sg:classifiers":[
        {
            "category":"Wholesale",
            "subcategory":"Motor Vehicles",
            "type":"Manufacturing & Wholesale Goods"
        }
    ],
    "sg:phone":"+1 336 218 8319",
    "sg:postcode":"27409",
    "sg:province":"NC",
    "wof:name":"Filterhaus",
    "wof:placetype":"venue"
},
  "geometry": {"coordinates":[-79.88597,36.062262],"type":"Point"}
}