{
  "type": "Feature",
  "properties": {
    "iso:country":"US",
    "sg:address":"104 30th Ave NW",
    "sg:city":"Hickory",
    "sg:classifiers":[
        {
            "category":"Shopping",
            "subcategory":"Florist",
            "type":"Retail Goods"
        }
    ],
    "sg:phone":"+1 828 328 2939",
    "sg:postcode":"28601",
    "sg:province":"NC",
    "wof:name":"Viewmont Florist & Gifts",
    "wof:placetype":"venue"
},
  "geometry": {"coordinates":[-81.331444,35.773109],"type":"Point"}
}