{
  "type": "Feature",
  "properties": {
    "iso:country":"US",
    "sg:address":"1504 Raleigh Rd",
    "sg:city":"Henderson",
    "sg:classifiers":[
        {
            "category":"Retail",
            "subcategory":"Auto Repair",
            "type":"Services"
        }
    ],
    "sg:phone":"+1 252 438 2279",
    "sg:postcode":"27536",
    "sg:province":"NC",
    "sg:tags":[
        "repairing",
        "automobile"
    ],
    "wof:name":"Hope's Automotive Svc",
    "wof:placetype":"venue"
},
  "geometry": {"coordinates":[-78.40884,36.307007],"type":"Point"}
}