{
  "type": "Feature",
  "properties": {
    "addr:full":"1515 W CORNWALLIS DR GREENSBORO NC 27408",
    "addr:housenumber":"1515",
    "addr:postcode":"27408",
    "addr:street":"W Cornwallis Dr",
    "iso:country":"US",
    "sg:address":"1515 W CORNWALLIS DR",
    "sg:city":"GREENSBORO",
    "sg:classifiers":[
        {
            "category":"Health Services",
            "subcategory":"Dentist",
            "type":"Services"
        }
    ],
    "sg:phone":"+1 336 379 1207",
    "sg:postcode":"27408",
    "sg:province":"NC",
    "sg:tags":[
        "dentists-cosmetic",
        "dentistry"
    ],
    "sg:website":"http://www.sandrafullerdds.com",
    "wof:name":"Fuller, Sandra L DDS PA",
    "wof:placetype":"venue"
},
  "geometry": {"coordinates":[-79.814499,36.097843],"type":"Point"}
}