{
  "type": "Feature",
  "properties": {
    "iso:country":"US",
    "sg:address":"214 Brynn Marr Rd",
    "sg:city":"Jacksonville",
    "sg:classifiers":[
        {
            "category":"Banks & Credit Unions",
            "subcategory":"Bank",
            "type":"Services"
        }
    ],
    "sg:phone":"+1 910 355 7000",
    "sg:postcode":"28546",
    "sg:province":"NC",
    "sg:tags":[
        "loan"
    ],
    "wof:name":"Equity One",
    "wof:placetype":"venue"
},
  "geometry": {"coordinates":[-77.380228,34.749035],"type":"Point"}
}