{
  "type": "Feature",
  "properties": {
    "iso:country":"US",
    "sg:address":"1226 E Garrison Blvd",
    "sg:city":"Gastonia",
    "sg:classifiers":[
        {
            "category":"Organizations",
            "subcategory":"Religious Organization",
            "type":"Services"
        }
    ],
    "sg:phone":"+1   ",
    "sg:postcode":"28054",
    "sg:province":"NC",
    "wof:name":"East Garrison Baptist Church",
    "wof:placetype":"venue"
},
  "geometry": {"coordinates":[-81.163203,35.252806],"type":"Point"}
}