{
  "type": "Feature",
  "properties": {
    "addr:full":"4869 Greystone Ln Maiden NC 28650",
    "addr:housenumber":"4869",
    "addr:postcode":"28650",
    "addr:street":"Greystone Ln",
    "iso:country":"US",
    "sg:address":"4869 Greystone Ln",
    "sg:city":"Maiden",
    "sg:classifiers":[
        {
            "category":"Building & Trades",
            "subcategory":"Construction",
            "type":"Services"
        }
    ],
    "sg:phone":"+1 828 695 9811",
    "sg:postcode":"28650",
    "sg:province":"NC",
    "sg:tags":[
        "house"
    ],
    "wof:name":"Sutton Construction",
    "wof:placetype":"venue"
},
  "geometry": {"coordinates":[-81.089924,35.59367],"type":"Point"}
}