{
  "type": "Feature",
  "properties": {
    "addr:full":"3015 Hammerfest Cir Fayetteville NC 28306",
    "addr:postcode":"3015;28306",
    "addr:street":"Hammerfest Cir",
    "iso:country":"US",
    "sg:address":"3015 Hammerfest Cir",
    "sg:city":"Fayetteville",
    "sg:classifiers":[
        {
            "category":"Professional",
            "type":"Services"
        }
    ],
    "sg:phone":"+1 910 425 8991",
    "sg:postcode":"28306",
    "sg:province":"NC",
    "wof:name":"Joan C Cummings Studio",
    "wof:placetype":"venue"
},
  "geometry": {"coordinates":[-79.00838299999999,34.989093],"type":"Point"}
}