{
  "type": "Feature",
  "properties": {
    "addr:full":"6613 Bentwinds Ln Fuquay Varina NC 27526",
    "addr:housenumber":"6613",
    "addr:postcode":"27526",
    "addr:street":"Bentwinds Ln",
    "iso:country":"US",
    "sg:address":"6613 Bentwinds Ln",
    "sg:city":"Fuquay Varina",
    "sg:classifiers":[
        {
            "category":"Wholesale",
            "subcategory":"Stationery",
            "type":"Manufacturing & Wholesale Goods"
        }
    ],
    "sg:phone":"+1 919 577 2212",
    "sg:postcode":"27526",
    "sg:province":"NC",
    "sg:tags":[
        "business",
        "form",
        "system"
    ],
    "wof:name":"Willamette Industries",
    "wof:placetype":"venue"
},
  "geometry": {"coordinates":[-78.772323,35.624966],"type":"Point"}
}