{
  "type": "Feature",
  "properties": {
    "iso:country":"US",
    "sg:address":"6008 Quiet Cove Ct",
    "sg:city":"Charlotte",
    "sg:classifiers":[
        {
            "category":"Organizations",
            "subcategory":"Non-profit Organization",
            "type":"Services"
        }
    ],
    "sg:phone":"+1 704 567 1756",
    "sg:postcode":"28215",
    "sg:province":"NC",
    "wof:name":"Eastside Community Economic",
    "wof:placetype":"venue"
},
  "geometry": {"coordinates":[-80.741488,35.255204],"type":"Point"}
}