{
  "type": "Feature",
  "properties": {
    "addr:full":"125 Plaza Ln Mount Airy NC 27030",
    "addr:housenumber":"125",
    "addr:postcode":"27030",
    "addr:street":"Plaza Ln",
    "iso:country":"US",
    "sg:address":"125 Plaza Ln",
    "sg:city":"Mount Airy",
    "sg:classifiers":[
        {
            "category":"Travel",
            "subcategory":"Hotels & Motels",
            "type":"Entertainment"
        }
    ],
    "sg:phone":"+1 336 352 3400",
    "sg:postcode":"27030",
    "sg:province":"NC",
    "sg:tags":[
        "operation"
    ],
    "wof:name":"Best Western",
    "wof:placetype":"venue"
},
  "geometry": {"coordinates":[-80.74658100000001,36.487413],"type":"Point"}
}