{
  "type": "Feature",
  "properties": {
    "addr:full":"285 W Morganton Rd Southern Pines NC 28387",
    "addr:housenumber":"285",
    "addr:postcode":"28387",
    "addr:street":"W Morganton Rd",
    "iso:country":"US",
    "sg:address":"285 W Morganton Rd",
    "sg:city":"Southern Pines",
    "sg:classifiers":[
        {
            "category":"Shopping",
            "subcategory":"Clothing, Apparel, & Fashions",
            "type":"Retail Goods"
        }
    ],
    "sg:phone":"+1 910 695 2621",
    "sg:postcode":"28387",
    "sg:province":"NC",
    "sg:tags":[
        "family"
    ],
    "wof:name":"Flowland Inc",
    "wof:placetype":"venue"
},
  "geometry": {"coordinates":[-79.405046,35.169792],"type":"Point"}
}