{
  "type": "Feature",
  "properties": {
    "iso:country":"US",
    "sg:address":"5030 State Hwy 152 E",
    "sg:city":"Rockwell",
    "sg:classifiers":[
        {
            "category":"Real Estate",
            "subcategory":"Real Estate Agent",
            "type":"Services"
        }
    ],
    "sg:phone":"+1 704 279 8750",
    "sg:postcode":"28138",
    "sg:province":"NC",
    "sg:website":"www.foreclosed-homes.net",
    "wof:name":"Genesis Realty Co",
    "wof:placetype":"venue"
},
  "geometry": {"coordinates":[-80.475695,35.550148],"type":"Point"}
}