{
  "type": "Feature",
  "properties": {
    "iso:country":"US",
    "sg:address":"1040 Dick Smith Rd",
    "sg:city":"Kittrell",
    "sg:classifiers":[
        {
            "category":"Home & Garden",
            "subcategory":"Building Materials",
            "type":"Retail Goods"
        }
    ],
    "sg:phone":"+1 252 430 0211",
    "sg:postcode":"27544",
    "sg:province":"NC",
    "sg:tags":[
        "glass",
        "window",
        "plate"
    ],
    "wof:name":"P & P Auto Glass",
    "wof:placetype":"venue"
},
  "geometry": {"coordinates":[-78.41004,36.199203],"type":"Point"}
}