{
  "type": "Feature",
  "properties": {
    "iso:country":"US",
    "sg:address":"9103 W Marlboro Rd",
    "sg:city":"Farmville",
    "sg:classifiers":[
        {
            "category":"Building & Trades",
            "subcategory":"Construction",
            "type":"Services"
        }
    ],
    "sg:phone":"+1 252 753 5408",
    "sg:postcode":"27828",
    "sg:province":"NC",
    "sg:tags":[
        "house",
        "improvement",
        "home"
    ],
    "wof:name":"Hampton's Home Improvements",
    "wof:placetype":"venue"
},
  "geometry": {"coordinates":[-77.622778,35.592637],"type":"Point"}
}