{
  "type": "Feature",
  "properties": {
    "iso:country":"US",
    "sg:address":"2233 Edgemont Rd",
    "sg:city":"Wendell",
    "sg:classifiers":[
        {
            "category":"Food & Beverages",
            "subcategory":"Groceries & Convenience Stores",
            "type":"Retail Goods"
        }
    ],
    "sg:phone":"+1 919 366 9009",
    "sg:postcode":"27591",
    "sg:province":"NC",
    "sg:tags":[
        "product"
    ],
    "wof:name":"Military Food & Beverage Spec",
    "wof:placetype":"venue"
},
  "geometry": {"coordinates":[-78.39890699999999,35.81921],"type":"Point"}
}