{
  "type": "Feature",
  "properties": {
    "addr:full":"315 Fulton St Kings Mountain NC 28086",
    "addr:housenumber":"315",
    "addr:postcode":"28086",
    "addr:street":"Fulton St",
    "iso:country":"US",
    "sg:address":"315 Fulton St",
    "sg:city":"Kings Mountain",
    "sg:classifiers":[
        {
            "category":"Retail",
            "subcategory":"Repair Shop",
            "type":"Services"
        }
    ],
    "sg:phone":"+1   ",
    "sg:postcode":"28086",
    "sg:province":"NC",
    "wof:name":"T S Trolling Motor Service",
    "wof:placetype":"venue"
},
  "geometry": {"coordinates":[-81.35046699999999,35.250404],"type":"Point"}
}