{
  "type": "Feature",
  "properties": {
    "addr:full":"1231 Cathey Rd Charlotte NC 28214",
    "addr:housenumber":"1231",
    "addr:postcode":"28214",
    "addr:street":"Cathey Rd",
    "iso:country":"US",
    "sg:address":"1231 Cathey Rd",
    "sg:city":"Charlotte",
    "sg:classifiers":[
        {
            "category":"Arts & Performance",
            "subcategory":"Theater",
            "type":"Entertainment"
        }
    ],
    "sg:phone":"+1 704 393 1241",
    "sg:postcode":"28214",
    "sg:province":"NC",
    "sg:tags":[
        "live",
        "music"
    ],
    "wof:name":"D J Express",
    "wof:placetype":"venue"
},
  "geometry": {"coordinates":[-80.945826,35.29093],"type":"Point"}
}