{
  "type": "Feature",
  "properties": {
    "addr:full":"802 Cedar Falls Rd Chapel Hill NC 27514",
    "addr:housenumber":"802",
    "addr:postcode":"27514",
    "addr:street":"Cedar Falls Rd",
    "iso:country":"US",
    "sg:address":"802 Cedar Falls Rd",
    "sg:city":"Chapel Hill",
    "sg:classifiers":[
        {
            "category":"Health Services",
            "subcategory":"Doctor",
            "type":"Services"
        }
    ],
    "sg:phone":"+1 919 929 3933",
    "sg:postcode":"27514",
    "sg:province":"NC",
    "sg:tags":[
        "physician",
        "surgeon"
    ],
    "wof:name":"James H Hilkey PHD",
    "wof:placetype":"venue"
},
  "geometry": {"coordinates":[-79.034932,35.952771],"type":"Point"}
}