{
  "type": "Feature",
  "properties": {
    "iso:country":"US",
    "sg:address":"307 W 3rd Ave",
    "sg:city":"Lexington",
    "sg:classifiers":[
        {
            "category":"Shopping",
            "subcategory":"Florist",
            "type":"Retail Goods"
        }
    ],
    "sg:phone":"+1 336 236 1234",
    "sg:postcode":"27292",
    "sg:province":"NC",
    "wof:name":"Precious Treasured Memories",
    "wof:placetype":"venue"
},
  "geometry": {"coordinates":[-80.260099,35.825289],"type":"Point"}
}