{
  "type": "Feature",
  "properties": {
    "iso:country":"US",
    "sg:address":"1265 Allred St",
    "sg:city":"Asheboro",
    "sg:classifiers":[
        {
            "category":"Professional",
            "subcategory":"Computer Services",
            "type":"Services"
        }
    ],
    "sg:phone":"+1 336 672 2929",
    "sg:postcode":"27203",
    "sg:province":"NC",
    "sg:tags":[
        "repair"
    ],
    "wof:name":"Hi Tech Svc",
    "wof:placetype":"venue"
},
  "geometry": {"coordinates":[-79.790943,35.7342],"type":"Point"}
}