{
  "type": "Feature",
  "properties": {
    "addr:full":"4007 White Level Rd Mebane NC 27302",
    "addr:housenumber":"4007",
    "addr:postcode":"27302",
    "addr:street":"White Level Rd",
    "iso:country":"US",
    "sg:address":"4007 White Level Rd",
    "sg:city":"Mebane",
    "sg:classifiers":[
        {
            "category":"Professional",
            "type":"Services"
        }
    ],
    "sg:phone":"+1 919 304 5431",
    "sg:postcode":"27302",
    "sg:province":"NC",
    "sg:tags":[
        "establishment"
    ],
    "wof:name":"TACSI Assisitve Systems",
    "wof:placetype":"venue"
},
  "geometry": {"coordinates":[-79.29803800000001,36.122324],"type":"Point"}
}