{
  "type": "Feature",
  "properties": {
    "iso:country":"US",
    "sg:address":"229 1st Ave SE",
    "sg:city":"Hickory",
    "sg:classifiers":[
        {
            "category":"Personal",
            "subcategory":"Beauty Salon",
            "type":"Services"
        }
    ],
    "sg:phone":"+1 828 327 3846",
    "sg:postcode":"28602",
    "sg:province":"NC",
    "sg:tags":[
        "school"
    ],
    "wof:name":"Catawba Hair Styling Academy",
    "wof:placetype":"venue"
},
  "geometry": {"coordinates":[-81.334339,35.730556],"type":"Point"}
}