{
  "type": "Feature",
  "properties": {
    "iso:country":"US",
    "sg:address":"1226 Conover Blvd W",
    "sg:city":"Conover",
    "sg:classifiers":[
        {
            "category":"Restaurant",
            "type":"Food & Drink"
        }
    ],
    "sg:menulink":"http://www.allmenus.com/nc/newton/238978-nagano/menu/",
    "sg:phone":"+1 828 466 7770",
    "sg:postcode":"28613",
    "sg:province":"NC",
    "sg:tags":[
        "japanese",
        "asian"
    ],
    "wof:name":"Nagano",
    "wof:placetype":"venue"
},
  "geometry": {"coordinates":[-81.255207,35.696374],"type":"Point"}
}