{
  "type": "Feature",
  "properties": {
    "iso:country":"US",
    "sg:address":"1128 Nottingham Dr",
    "sg:city":"Gastonia",
    "sg:classifiers":[
        {
            "category":"Shopping",
            "type":"Retail Goods"
        }
    ],
    "sg:phone":"+1 704 867 3730",
    "sg:postcode":"28054",
    "sg:province":"NC",
    "sg:tags":[
        "merchandise"
    ],
    "wof:name":"Systems 2 Corp",
    "wof:placetype":"venue"
},
  "geometry": {"coordinates":[-81.162605,35.247245],"type":"Point"}
}