{
  "type": "Feature",
  "properties": {
    "iso:country":"US",
    "sg:address":"4309 Fireside Ct",
    "sg:city":"Wilmington",
    "sg:classifiers":[
        {
            "category":"Real Estate",
            "subcategory":"Real Estate Agent",
            "type":"Services"
        }
    ],
    "sg:phone":"+1 910 793 8796",
    "sg:postcode":"28412",
    "sg:province":"NC",
    "sg:tags":[
        "mail",
        "order"
    ],
    "wof:name":"John Henry Miller Pharmacy",
    "wof:placetype":"venue"
},
  "geometry": {"coordinates":[-77.901427,34.167897],"type":"Point"}
}