{
  "type": "Feature",
  "properties": {
    "iso:country":"US",
    "sg:address":"9430 Guernsey Ct",
    "sg:city":"Charlotte",
    "sg:classifiers":[
        {
            "category":"Professional",
            "subcategory":"Lawyer & Legal Services",
            "type":"Services"
        }
    ],
    "sg:phone":"+1   ",
    "sg:postcode":"28213",
    "sg:province":"NC",
    "wof:name":"Stacy D Fulcher",
    "wof:placetype":"venue"
},
  "geometry": {"coordinates":[-80.713042,35.295077],"type":"Point"}
}