{
  "type": "Feature",
  "properties": {
    "iso:country":"US",
    "sg:address":"626 State Hwy 105 Byp",
    "sg:city":"Boone",
    "sg:classifiers":[
        {
            "category":"Shopping",
            "subcategory":"Beauty & Cosmetics",
            "type":"Retail Goods"
        }
    ],
    "sg:phone":"+1   ",
    "sg:postcode":"28607",
    "sg:province":"NC",
    "sg:tags":[
        "personal",
        "merchandise"
    ],
    "wof:name":"Mary Kay Cosmetics",
    "wof:placetype":"venue"
},
  "geometry": {"coordinates":[-81.718042,36.220925],"type":"Point"}
}