{
  "type": "Feature",
  "properties": {
    "iso:country":"US",
    "sg:address":"107 S Lincoln Dr",
    "sg:city":"Dudley",
    "sg:classifiers":[
        {
            "category":"Education",
            "subcategory":"Dance Studio",
            "type":"Public Place"
        }
    ],
    "sg:phone":"+1 919 580 9329",
    "sg:postcode":"28333",
    "sg:province":"NC",
    "sg:tags":[
        "instruction",
        "dancing"
    ],
    "wof:name":"Mystic Dance Productions",
    "wof:placetype":"venue"
},
  "geometry": {"coordinates":[-78.029411,35.303998],"type":"Point"}
}