{
  "type": "Feature",
  "properties": {
    "iso:country":"US",
    "sg:address":"710 Cromwell Dr",
    "sg:city":"Greenville",
    "sg:classifiers":[
        {
            "category":"Social Services",
            "type":"Services"
        }
    ],
    "sg:phone":"+1 252 756 8549",
    "sg:postcode":"27858",
    "sg:province":"NC",
    "sg:tags":[
        "community"
    ],
    "wof:name":"Greater Greenville Foundation",
    "wof:placetype":"venue"
},
  "geometry": {"coordinates":[-77.370327,35.576841],"type":"Point"}
}