{
  "type": "Feature",
  "properties": {
    "iso:country":"US",
    "sg:address":"3118 Bridges St",
    "sg:city":"Morehead City",
    "sg:classifiers":[
        {
            "category":"Building & Trades",
            "subcategory":"Plumbing",
            "type":"Services"
        }
    ],
    "sg:phone":"+1 252 726 4833",
    "sg:postcode":"28557",
    "sg:province":"NC",
    "sg:tags":[
        "tank",
        "septic"
    ],
    "wof:name":"Carteret Septic Tank & Constr",
    "wof:placetype":"venue"
},
  "geometry": {"coordinates":[-76.74652399999999,34.727334],"type":"Point"}
}