{
  "type": "Feature",
  "properties": {
    "iso:country":"US",
    "sg:address":"102 Stone Point Ct",
    "sg:city":"Mooresville",
    "sg:classifiers":[
        {
            "category":"Professional",
            "subcategory":"Management & Consulting",
            "type":"Services"
        }
    ],
    "sg:phone":"+1   ",
    "sg:postcode":"28117",
    "sg:province":"NC",
    "wof:name":"J M Rafols",
    "wof:placetype":"venue"
},
  "geometry": {"coordinates":[-80.952944,35.527763],"type":"Point"}
}