{
  "type": "Feature",
  "properties": {
    "iso:country":"US",
    "sg:address":"518 Ridge Dr",
    "sg:city":"Winterville",
    "sg:classifiers":[
        {
            "category":"Professional",
            "subcategory":"Employment Agencies",
            "type":"Services"
        }
    ],
    "sg:phone":"+1 252 756 1325",
    "sg:postcode":"28590",
    "sg:province":"NC",
    "wof:name":"H&H Concrete Placement",
    "wof:placetype":"venue"
},
  "geometry": {"coordinates":[-77.425758,35.545683],"type":"Point"}
}