{
  "type": "Feature",
  "properties": {
    "addr:full":"1304 Patton Ave Asheville NC 28806",
    "addr:housenumber":"1304",
    "addr:postcode":"28806",
    "addr:street":"Patton Ave",
    "iso:country":"US",
    "sg:address":"1304 Patton Ave",
    "sg:city":"Asheville",
    "sg:classifiers":[
        {
            "category":"Insurance",
            "subcategory":"Insurance Agent",
            "type":"Services"
        }
    ],
    "sg:phone":"+1 828 252 5661",
    "sg:postcode":"28806",
    "sg:province":"NC",
    "sg:tags":[
        "agency"
    ],
    "wof:name":"Allstate",
    "wof:placetype":"venue"
},
  "geometry": {"coordinates":[-82.601162,35.585773],"type":"Point"}
}