{
  "type": "Feature",
  "properties": {
    "addr:full":"451 Howard Blvd Newport NC 28570",
    "addr:housenumber":"451",
    "addr:postcode":"28570",
    "addr:street":"Howard Blvd",
    "iso:country":"US",
    "sg:address":"451 Howard Blvd",
    "sg:city":"Newport",
    "sg:classifiers":[
        {
            "category":"Government",
            "subcategory":"Office",
            "type":"Public Place"
        }
    ],
    "sg:phone":"+1 252 223 4272",
    "sg:postcode":"28570",
    "sg:province":"NC",
    "sg:tags":[
        "federal",
        "program"
    ],
    "sg:website":"www.usda.gov",
    "wof:name":"US Agricultural Dept",
    "wof:placetype":"venue"
},
  "geometry": {"coordinates":[-76.875781,34.789249],"type":"Point"}
}