{
  "type": "Feature",
  "properties": {
    "iso:country":"US",
    "sg:address":"2101 Gateway Centre Blvd",
    "sg:city":"Morrisville",
    "sg:classifiers":[
        {
            "category":"Health Services",
            "subcategory":"Doctor",
            "type":"Services"
        }
    ],
    "sg:phone":"+1 919 734 9888",
    "sg:postcode":"27560",
    "sg:province":"NC",
    "sg:tags":[
        "physician",
        "surgeon"
    ],
    "wof:name":"Nc Neurology Ctr",
    "wof:placetype":"venue"
},
  "geometry": {"coordinates":[-78.80191499999999,35.845912],"type":"Point"}
}