{
  "type": "Feature",
  "properties": {
    "addr:full":"145 Old US Hwy 70 E Black Mountain NC 28711",
    "addr:housenumber":"145",
    "addr:postcode":"28711",
    "addr:street":"Old Us Hwy 70 E",
    "iso:country":"US",
    "sg:address":"145 Old US Hwy 70 E",
    "sg:city":"Black Mountain",
    "sg:classifiers":[
        {
            "category":"Shopping",
            "subcategory":"Optical Goods",
            "type":"Retail Goods"
        }
    ],
    "sg:phone":"+1 828 669 6024",
    "sg:postcode":"28711",
    "sg:province":"NC",
    "wof:name":"A Better View Family Eye Care",
    "wof:placetype":"venue"
},
  "geometry": {"coordinates":[-82.282065,35.618087],"type":"Point"}
}