{
  "type": "Feature",
  "properties": {
    "addr:full":"5058 US Hwy 70 Morehead City NC 28557",
    "addr:housenumber":"5058",
    "addr:postcode":"28557",
    "addr:street":"Us Hwy 70",
    "iso:country":"US",
    "sg:address":"5058 US Hwy 70",
    "sg:city":"Morehead City",
    "sg:classifiers":[
        {
            "category":"Building & Trades",
            "subcategory":"Construction",
            "type":"Services"
        }
    ],
    "sg:phone":"+1 252 727 5418",
    "sg:postcode":"28557",
    "sg:province":"NC",
    "sg:tags":[
        "concrete",
        "contractor"
    ],
    "wof:name":"Royal Coat Decorative Concrete",
    "wof:placetype":"venue"
},
  "geometry": {"coordinates":[-76.799792,34.736728],"type":"Point"}
}