{
  "type": "Feature",
  "properties": {
    "addr:full":"112 Linwood Dr Albemarle NC 28001",
    "addr:housenumber":"112",
    "addr:postcode":"28001",
    "addr:street":"Linwood Dr",
    "iso:country":"US",
    "sg:address":"112 Linwood Dr",
    "sg:city":"Albemarle",
    "sg:classifiers":[
        {
            "category":"Social Services",
            "subcategory":"Adult Care",
            "type":"Services"
        }
    ],
    "sg:phone":"+1 704 983 4806",
    "sg:postcode":"28001",
    "sg:province":"NC",
    "sg:tags":[
        "home",
        "group"
    ],
    "wof:name":"Group Homes For The Autistic",
    "wof:placetype":"venue"
},
  "geometry": {"coordinates":[-80.192629,35.370069],"type":"Point"}
}