{
  "type": "Feature",
  "properties": {
    "iso:country":"US",
    "sg:address":"517 West St",
    "sg:city":"Pittsboro",
    "sg:classifiers":[
        {
            "category":"Professional",
            "type":"Services"
        }
    ],
    "sg:phone":"+1 919 545 9831",
    "sg:postcode":"27312",
    "sg:province":"NC",
    "wof:name":"Circle City Java",
    "wof:placetype":"venue"
},
  "geometry": {"coordinates":[-79.188807,35.720828],"type":"Point"}
}