{
  "type": "Feature",
  "properties": {
    "iso:country":"US",
    "sg:address":"207 Oak Grove Ave",
    "sg:city":"Greenville",
    "sg:classifiers":[
        {
            "category":"Freight",
            "type":"Transportation"
        }
    ],
    "sg:phone":"+1 252 830 1018",
    "sg:postcode":"27834",
    "sg:province":"NC",
    "sg:tags":[
        "operator",
        "local",
        "trucking"
    ],
    "wof:name":"Daniels Trucking",
    "wof:placetype":"venue"
},
  "geometry": {"coordinates":[-77.384675,35.656013],"type":"Point"}
}