{
  "type": "Feature",
  "properties": {
    "iso:country":"US",
    "sg:address":"115 Potters Ln",
    "sg:city":"Mocksville",
    "sg:classifiers":[
        {
            "category":"Freight",
            "type":"Transportation"
        }
    ],
    "sg:phone":"+1 336 998 3748",
    "sg:postcode":"27028",
    "sg:province":"NC",
    "sg:tags":[
        "operator",
        "local",
        "trucking"
    ],
    "wof:name":"J Rod Trucking",
    "wof:placetype":"venue"
},
  "geometry": {"coordinates":[-80.582573,35.965772],"type":"Point"}
}