{
  "type": "Feature",
  "properties": {
    "addr:full":"3924 S Holden Rd Greensboro NC 27406",
    "addr:housenumber":"3924",
    "addr:postcode":"27406",
    "addr:street":"S Holden Rd",
    "iso:country":"US",
    "sg:address":"3924 S Holden Rd",
    "sg:city":"Greensboro",
    "sg:classifiers":[
        {
            "category":"Professional",
            "subcategory":"Accounting & Tax Preparation",
            "type":"Services"
        }
    ],
    "sg:phone":"+1 336 854 4006",
    "sg:postcode":"27406",
    "sg:province":"NC",
    "sg:tags":[
        "accountant"
    ],
    "wof:name":"Kenneth H Hopkins",
    "wof:placetype":"venue"
},
  "geometry": {"coordinates":[-79.83587300000001,36.007966],"type":"Point"}
}