{
  "type": "Feature",
  "properties": {
    "iso:country":"US",
    "sg:address":"6705 Folinsbee Ct",
    "sg:city":"Raleigh",
    "sg:classifiers":[
        {
            "category":"Social Services",
            "subcategory":"Child Care",
            "type":"Services"
        },
        {
            "category":"Shopping",
            "subcategory":"Gifts & Souvenirs",
            "type":"Retail Goods"
        }
    ],
    "sg:phone":"+1 919 266 7704",
    "sg:postcode":"27616",
    "sg:province":"NC",
    "sg:tags":[
        "basket",
        "parcel",
        "day"
    ],
    "wof:name":"A Day Off Private Spa Baskets",
    "wof:placetype":"venue"
},
  "geometry": {"coordinates":[-78.521838,35.878468],"type":"Point"}
}