{
  "type": "Feature",
  "properties": {
    "iso:country":"US",
    "sg:address":"215 Alamance Rd",
    "sg:city":"Burlington",
    "sg:classifiers":[
        {
            "category":"Professional",
            "subcategory":"Business Services",
            "type":"Services"
        }
    ],
    "sg:phone":"+1   ",
    "sg:postcode":"27215",
    "sg:province":"NC",
    "wof:name":"Lowman Burgess & Associates",
    "wof:placetype":"venue"
},
  "geometry": {"coordinates":[-79.464173,36.07929],"type":"Point"}
}