{
  "type": "Feature",
  "properties": {
    "addr:full":"2210 Cokey Rd Rocky Mount NC 27801",
    "addr:housenumber":"2210",
    "addr:postcode":"27801",
    "addr:street":"Cokey Rd",
    "iso:country":"US",
    "sg:address":"2210 Cokey Rd",
    "sg:city":"Rocky Mount",
    "sg:classifiers":[
        {
            "category":"Professional",
            "subcategory":"Engineering",
            "type":"Services"
        }
    ],
    "sg:phone":"+1   ",
    "sg:postcode":"27801",
    "sg:province":"NC",
    "wof:name":"Lang Technical Resources LLC",
    "wof:placetype":"venue"
},
  "geometry": {"coordinates":[-77.768885,35.91927],"type":"Point"}
}