{
  "type": "Feature",
  "properties": {
    "addr:full":"1401 S Ridge Ave Kannapolis NC 28083",
    "addr:housenumber":"1401",
    "addr:postcode":"28083",
    "addr:street":"S Ridge Ave",
    "iso:country":"US",
    "sg:address":"1401 S Ridge Ave",
    "sg:city":"Kannapolis",
    "sg:classifiers":[
        {
            "category":"Wholesale",
            "subcategory":"Electrical",
            "type":"Manufacturing & Wholesale Goods"
        }
    ],
    "sg:phone":"+1 704 934 2122",
    "sg:postcode":"28083",
    "sg:province":"NC",
    "sg:tags":[
        "electric",
        "motor"
    ],
    "wof:name":"Fisherman's Friend Too",
    "wof:placetype":"venue"
},
  "geometry": {"coordinates":[-80.62250299999999,35.473912],"type":"Point"}
}