{
  "type": "Feature",
  "properties": {
    "addr:full":"5309 Carolina Beach Rd Wilmington NC 28412",
    "addr:housenumber":"5309",
    "addr:postcode":"28412",
    "addr:street":"Carolina Beach Rd",
    "iso:country":"US",
    "sg:address":"5309 Carolina Beach Rd",
    "sg:city":"Wilmington",
    "sg:classifiers":[
        {
            "category":"Home & Garden",
            "subcategory":"Furniture",
            "type":"Retail Goods"
        }
    ],
    "sg:phone":"+1 910 799 5559",
    "sg:postcode":"28412",
    "sg:province":"NC",
    "sg:tags":[
        "bedding"
    ],
    "wof:name":"Beds Plus",
    "wof:placetype":"venue"
},
  "geometry": {"coordinates":[-77.895495,34.141819],"type":"Point"}
}