{
  "type": "Feature",
  "properties": {
    "addr:full":"132 Green Acres Ct Mount Airy NC 27030",
    "addr:housenumber":"132",
    "addr:postcode":"27030",
    "addr:street":"Green Acres Ct",
    "iso:country":"US",
    "sg:address":"132 Green Acres Ct",
    "sg:city":"Mount Airy",
    "sg:classifiers":[
        {
            "category":"Building & Trades",
            "subcategory":"Construction",
            "type":"Services"
        }
    ],
    "sg:phone":"+1 336 351 4345",
    "sg:postcode":"27030",
    "sg:province":"NC",
    "sg:tags":[
        "contractor"
    ],
    "wof:name":"Gwyn Brothers Masonry",
    "wof:placetype":"venue"
},
  "geometry": {"coordinates":[-80.488809,36.493826],"type":"Point"}
}