{
  "type": "Feature",
  "properties": {
    "iso:country":"US",
    "sg:address":"1007 S Lafayette St",
    "sg:city":"Shelby",
    "sg:classifiers":[
        {
            "category":"Personal",
            "type":"Services"
        }
    ],
    "sg:phone":"+1   ",
    "sg:postcode":"28152",
    "sg:province":"NC",
    "wof:name":"Everlasting Tattoo",
    "wof:placetype":"venue"
},
  "geometry": {"coordinates":[-81.54374300000001,35.277498],"type":"Point"}
}