{
  "type": "Feature",
  "properties": {
    "addr:full":"901 Matthews-Mint Hill Rd Matthews NC 28105",
    "addr:housenumber":"901",
    "addr:postcode":"28105",
    "addr:street":"Matthews-Mint Hill Rd",
    "iso:country":"US",
    "sg:address":"901 Matthews-Mint Hill Rd",
    "sg:city":"Matthews",
    "sg:classifiers":[
        {
            "category":"Home & Garden",
            "subcategory":"Household Appliances",
            "type":"Retail Goods"
        }
    ],
    "sg:phone":"+1 704 814 6164",
    "sg:postcode":"28105",
    "sg:province":"NC",
    "sg:tags":[
        "pump"
    ],
    "wof:name":"KRAL USA Inc",
    "wof:placetype":"venue"
},
  "geometry": {"coordinates":[-80.70891,35.117829],"type":"Point"}
}