{
  "type": "Feature",
  "properties": {
    "iso:country":"US",
    "sg:address":"165 Robin Ln",
    "sg:city":"Boone",
    "sg:classifiers":[
        {
            "category":"Real Estate",
            "subcategory":"Real Estate Operator",
            "type":"Services"
        }
    ],
    "sg:phone":"+1 828 264 4804",
    "sg:postcode":"28607",
    "sg:province":"NC",
    "sg:tags":[
        "apartment"
    ],
    "wof:name":"Watauga Village Apartments",
    "wof:placetype":"venue"
},
  "geometry": {"coordinates":[-81.665588,36.213236],"type":"Point"}
}