{
  "type": "Feature",
  "properties": {
    "iso:country":"US",
    "sg:address":"14 W Main St",
    "sg:city":"Brevard",
    "sg:classifiers":[
        {
            "category":"Shopping",
            "subcategory":"Clothing, Apparel, & Fashions",
            "type":"Retail Goods"
        }
    ],
    "sg:phone":"+1 828 884 3444",
    "sg:postcode":"28712",
    "sg:province":"SC",
    "wof:name":"Lilly T's",
    "wof:placetype":"venue"
},
  "geometry": {"coordinates":[-82.734802,35.234045],"type":"Point"}
}