{
  "type": "Feature",
  "properties": {
    "addr:full":"5725 Laurium Rd Charlotte NC 28226",
    "addr:postcode":"5725;28226",
    "addr:street":"Laurium Rd",
    "iso:country":"US",
    "sg:address":"5725 Laurium Rd",
    "sg:city":"Charlotte",
    "sg:classifiers":[
        {
            "category":"Real Estate",
            "subcategory":"Real Estate Agent",
            "type":"Services"
        }
    ],
    "sg:phone":"+1 704 343 9800",
    "sg:postcode":"28226",
    "sg:province":"NC",
    "sg:tags":[
        "property",
        "rental"
    ],
    "wof:name":"Monark Properties LLC",
    "wof:placetype":"venue"
},
  "geometry": {"coordinates":[-80.79525599999999,35.12151],"type":"Point"}
}