{
  "type": "Feature",
  "properties": {
    "addr:full":"300 S Brevard St Charlotte NC 28202",
    "addr:housenumber":"300",
    "addr:postcode":"28202",
    "addr:street":"S Brevard St",
    "iso:country":"US",
    "sg:address":"300 S Brevard St",
    "sg:city":"Charlotte",
    "sg:classifiers":[
        {
            "category":"Utilities",
            "subcategory":"Mobile Phone",
            "type":"Services"
        }
    ],
    "sg:phone":"+1 704 347 0796",
    "sg:postcode":"28202",
    "sg:province":"NC",
    "sg:tags":[
        "communication",
        "radiotelephone"
    ],
    "wof:name":"Cingular Wireless",
    "wof:placetype":"venue"
},
  "geometry": {"coordinates":[-80.843363,35.222249],"type":"Point"}
}