{
  "type": "Feature",
  "properties": {
    "addr:full":"7446 Bowers Rd Littleton NC 27850",
    "addr:housenumber":"7446",
    "addr:postcode":"27850",
    "addr:street":"Bowers Rd",
    "iso:country":"US",
    "sg:address":"7446 Bowers Rd",
    "sg:city":"Littleton",
    "sg:classifiers":[
        {
            "category":"Freight",
            "type":"Transportation"
        }
    ],
    "sg:phone":"+1 252 586 0280",
    "sg:postcode":"27850",
    "sg:province":"NC",
    "sg:tags":[
        "operator",
        "trucking"
    ],
    "wof:name":"H & T Transport Inc",
    "wof:placetype":"venue"
},
  "geometry": {"coordinates":[-77.855721,36.33091],"type":"Point"}
}