{
  "type": "Feature",
  "properties": {
    "iso:country":"US",
    "sg:address":"410 Glenwood Ave Ste 150",
    "sg:city":"Raleigh",
    "sg:phone":"+1 919 832 1212",
    "sg:postcode":"27603",
    "sg:province":"NC",
    "wof:name":"Playspace",
    "wof:placetype":"venue"
},
  "geometry": {"coordinates":[-78.647308,35.785457],"type":"Point"}
}