{
  "type": "Feature",
  "properties": {
    "addr:full":"5071 Follansbee Rd Winston Salem NC 27127",
    "addr:postcode":"5071;27127",
    "addr:street":"Follansbee Rd",
    "iso:country":"US",
    "sg:address":"5071 Follansbee Rd",
    "sg:city":"Winston Salem",
    "sg:classifiers":[
        {
            "category":"Building & Trades",
            "subcategory":"Plumbing",
            "type":"Services"
        }
    ],
    "sg:phone":"+1 336 416 8007",
    "sg:postcode":"27127",
    "sg:province":"NC",
    "sg:tags":[
        "mechanical",
        "contractor"
    ],
    "wof:name":"B & B Mechanical Inc",
    "wof:placetype":"venue"
},
  "geometry": {"coordinates":[-80.24120499999999,36.001277],"type":"Point"}
}