{
  "type": "Feature",
  "properties": {
    "addr:full":"1006 Monroe St Carthage NC 28327",
    "addr:housenumber":"1006",
    "addr:postcode":"28327",
    "addr:street":"Monroe St",
    "iso:country":"US",
    "sg:address":"1006 Monroe St",
    "sg:city":"Carthage",
    "sg:classifiers":[
        {
            "category":"Shopping",
            "subcategory":"Pharmacy",
            "type":"Retail Goods"
        }
    ],
    "sg:phone":"+1 910 947 2690",
    "sg:postcode":"28327",
    "sg:province":"NC",
    "sg:website":"www.kerrdrug.com",
    "wof:name":"KERR Drug",
    "wof:placetype":"venue"
},
  "geometry": {"coordinates":[-79.401613,35.340947],"type":"Point"}
}