{
  "type": "Feature",
  "properties": {
    "iso:country":"US",
    "sg:address":"14301 Wynfield Creek Pkwy",
    "sg:city":"Huntersville",
    "sg:classifiers":[
        {
            "category":"Organizations",
            "subcategory":"Community Association",
            "type":"Services"
        }
    ],
    "sg:phone":"+1 704 875 6627",
    "sg:postcode":"28078",
    "sg:province":"NC",
    "sg:tags":[
        "club"
    ],
    "wof:name":"Wynfield Property Owners Club",
    "wof:placetype":"venue"
},
  "geometry": {"coordinates":[-80.877818,35.406421],"type":"Point"}
}