{
  "type": "Feature",
  "properties": {
    "iso:country":"US",
    "sg:address":"517 Fenton Pl",
    "sg:city":"Charlotte",
    "sg:classifiers":[
        {
            "category":"Professional",
            "subcategory":"Business Services",
            "type":"Services"
        }
    ],
    "sg:phone":"+1 704 333 5668",
    "sg:postcode":"28207",
    "sg:province":"NC",
    "sg:tags":[
        "interior",
        "consultant",
        "design",
        "decorator"
    ],
    "wof:name":"Walker Gray Interiors ASID",
    "wof:placetype":"venue"
},
  "geometry": {"coordinates":[-80.82304499999999,35.200749],"type":"Point"}
}