{
  "type": "Feature",
  "properties": {
    "addr:full":"6010 McDaniel Ln Charlotte NC 28213",
    "addr:housenumber":"6010",
    "addr:postcode":"28213",
    "addr:street":"Mcdaniel Ln",
    "iso:country":"US",
    "sg:address":"6010 McDaniel Ln",
    "sg:city":"Charlotte",
    "sg:classifiers":[
        {
            "category":"Retail",
            "subcategory":"Auto Repair",
            "type":"Services"
        }
    ],
    "sg:phone":"+1   ",
    "sg:postcode":"28213",
    "sg:province":"NC",
    "sg:tags":[
        "general"
    ],
    "wof:name":"Latinos Auto Service",
    "wof:placetype":"venue"
},
  "geometry": {"coordinates":[-80.76025799999999,35.263455],"type":"Point"}
}