{
  "type": "Feature",
  "properties": {
    "iso:country":"US",
    "sg:address":"2433 Burch Bridge Rd",
    "sg:city":"Burlington",
    "sg:classifiers":[
        {
            "category":"Professional",
            "subcategory":"Accounting & Tax Preparation",
            "type":"Services"
        }
    ],
    "sg:phone":"+1 336 226 8812",
    "sg:postcode":"27217",
    "sg:province":"NC",
    "sg:tags":[
        "return",
        "filing"
    ],
    "wof:name":"Thompson Tax & Accounting Svc",
    "wof:placetype":"venue"
},
  "geometry": {"coordinates":[-79.464933,36.129333],"type":"Point"}
}