{
  "type": "Feature",
  "properties": {
    "addr:full":"214 Hay St Fayetteville NC 28301",
    "addr:housenumber":"214",
    "addr:postcode":"28301",
    "addr:street":"Hay St",
    "iso:country":"US",
    "sg:address":"214 Hay St",
    "sg:city":"Fayetteville",
    "sg:classifiers":[
        {
            "category":"Utilities",
            "subcategory":"Mobile Phone",
            "type":"Services"
        }
    ],
    "sg:phone":"+1 910 323 2291",
    "sg:postcode":"28301",
    "sg:province":"NC",
    "sg:tags":[
        "telephone",
        "cellular"
    ],
    "wof:name":"All Access Wireless",
    "wof:placetype":"venue"
},
  "geometry": {"coordinates":[-78.880709,35.053475],"type":"Point"}
}