{
  "type": "Feature",
  "properties": {
    "iso:country":"US",
    "sg:address":"201 E Judd St",
    "sg:city":"Zebulon",
    "sg:classifiers":[
        {
            "category":"Professional",
            "type":"Services"
        }
    ],
    "sg:phone":"+1 919 269 6380",
    "sg:postcode":"27597",
    "sg:province":"NC",
    "sg:tags":[
        "establishment"
    ],
    "wof:name":"Digital Call Ctr Inc",
    "wof:placetype":"venue"
},
  "geometry": {"coordinates":[-78.313721,35.831575],"type":"Point"}
}