{
  "type": "Feature",
  "properties": {
    "addr:full":"3260 Ray Rd Spring Lake NC 28390",
    "addr:housenumber":"3260",
    "addr:postcode":"28390",
    "addr:street":"Ray Rd",
    "iso:country":"US",
    "sg:address":"3260 Ray Rd",
    "sg:city":"Spring Lake",
    "sg:classifiers":[
        {
            "category":"Personal",
            "subcategory":"Beauty Salon",
            "type":"Services"
        }
    ],
    "sg:phone":"+1 910 497 2300",
    "sg:postcode":"28390",
    "sg:province":"NC",
    "wof:name":"California Stylin",
    "wof:placetype":"venue"
},
  "geometry": {"coordinates":[-78.967721,35.255948],"type":"Point"}
}