{
  "type": "Feature",
  "properties": {
    "addr:full":"4927 Barrett Rd Kings Mountain NC 28086",
    "addr:housenumber":"4927",
    "addr:postcode":"28086",
    "addr:street":"Barrett Rd",
    "iso:country":"US",
    "sg:address":"4927 Barrett Rd",
    "sg:city":"Kings Mountain",
    "sg:classifiers":[
        {
            "category":"Insurance",
            "subcategory":"Insurance Agent",
            "type":"Services"
        }
    ],
    "sg:phone":"+1 704 739 9585",
    "sg:postcode":"28086",
    "sg:province":"NC",
    "wof:name":"All American Insurance Assoc",
    "wof:placetype":"venue"
},
  "geometry": {"coordinates":[-81.443783,35.240877],"type":"Point"}
}