{
  "type": "Feature",
  "properties": {
    "iso:country":"US",
    "sg:address":"2031 E Roosevelt Blvd",
    "sg:city":"Monroe",
    "sg:classifiers":[
        {
            "category":"Manufacturing",
            "subcategory":"Chemicals & Compounds",
            "type":"Manufacturing & Wholesale Goods"
        },
        {
            "category":"Wholesale",
            "subcategory":"Chemicals & Plastics",
            "type":"Manufacturing & Wholesale Goods"
        }
    ],
    "sg:phone":"+1 704 289 4551",
    "sg:postcode":"28112",
    "sg:province":"NC",
    "sg:tags":[
        "adhesive",
        "glue",
        "mfg"
    ],
    "sg:website":"www.lddavis.com",
    "wof:name":"L D Davis Industries Inc",
    "wof:placetype":"venue"
},
  "geometry": {"coordinates":[-80.488185,34.979769],"type":"Point"}
}