{
  "type": "Feature",
  "properties": {
    "iso:country":"US",
    "sg:address":"1433 Aversboro Rd",
    "sg:city":"Garner",
    "sg:classifiers":[
        {
            "category":"Organizations",
            "subcategory":"Religious Organization",
            "type":"Services"
        }
    ],
    "sg:phone":"+1 919 779 7244",
    "sg:postcode":"27529",
    "sg:province":"NC",
    "sg:tags":[
        "church"
    ],
    "wof:name":"Church Of Jesus Christ Of Lds",
    "wof:placetype":"venue"
},
  "geometry": {"coordinates":[-78.616585,35.694436],"type":"Point"}
}