{
  "type": "Feature",
  "properties": {
    "iso:country":"US",
    "sg:address":"7211 Mason Rd",
    "sg:city":"Climax",
    "sg:classifiers":[
        {
            "category":"Professional",
            "type":"Services"
        }
    ],
    "sg:phone":"+1 336 674 5677",
    "sg:postcode":"27233",
    "sg:province":"NC",
    "wof:name":"Impact Steel Erections LLC",
    "wof:placetype":"venue"
},
  "geometry": {"coordinates":[-79.72341,35.914802],"type":"Point"}
}