{
  "type": "Feature",
  "properties": {
    "iso:country":"US",
    "sg:address":"204 E Country Day Rd",
    "sg:city":"Goldsboro",
    "sg:classifiers":[
        {
            "category":"Organizations",
            "subcategory":"Religious Organization",
            "type":"Services"
        }
    ],
    "sg:phone":"+1   ",
    "sg:postcode":"27530",
    "sg:province":"NC",
    "wof:name":"Liberty Pntcstal Hlness Church",
    "wof:placetype":"venue"
},
  "geometry": {"coordinates":[-77.96169399999999,35.405104],"type":"Point"}
}