{
  "type": "Feature",
  "properties": {
    "iso:country":"US",
    "sg:address":"601 Ridge Rd",
    "sg:city":"Roxboro",
    "sg:classifiers":[
        {
            "category":"Health Services",
            "subcategory":"Doctor",
            "type":"Services"
        }
    ],
    "sg:phone":"+1 336 597 3865",
    "sg:postcode":"27573",
    "sg:province":"NC",
    "sg:tags":[
        "medical"
    ],
    "wof:name":"Duke Orthopedics Person County",
    "wof:placetype":"venue"
},
  "geometry": {"coordinates":[-78.98575099999999,36.406496],"type":"Point"}
}