{
  "type": "Feature",
  "properties": {
    "addr:full":"175 Furr Ave NW Concord NC 28027",
    "addr:housenumber":"175",
    "addr:postcode":"28027",
    "addr:street":"Furr Ave Nw",
    "iso:country":"US",
    "sg:address":"175 Furr Ave NW",
    "sg:city":"Concord",
    "sg:classifiers":[
        {
            "category":"Personal",
            "type":"Services"
        },
        {
            "category":"Recreation",
            "type":"Entertainment"
        }
    ],
    "sg:phone":"+1 704 795 7478",
    "sg:postcode":"28027",
    "sg:province":"NC",
    "sg:tags":[
        "therapist",
        "instruction",
        "massage"
    ],
    "sg:website":"www.blueridgemassage.com",
    "wof:name":"Blue Rdge Healing Arts Academy",
    "wof:placetype":"venue"
},
  "geometry": {"coordinates":[-80.608363,35.428546],"type":"Point"}
}