{
  "type": "Feature",
  "properties": {
    "addr:full":"7595 Broad St Rural Hall NC 27045",
    "addr:housenumber":"7595",
    "addr:postcode":"27045",
    "addr:street":"Broad St",
    "iso:country":"US",
    "sg:address":"7595 Broad St",
    "sg:city":"Rural Hall",
    "sg:classifiers":[
        {
            "category":"Professional",
            "subcategory":"Management & Consulting",
            "type":"Services"
        }
    ],
    "sg:phone":"+1 336 969 5711",
    "sg:postcode":"27045",
    "sg:province":"NC",
    "wof:name":"Federal Financial Services",
    "wof:placetype":"venue"
},
  "geometry": {"coordinates":[-80.29013500000001,36.233536],"type":"Point"}
}