{
  "type": "Feature",
  "properties": {
    "addr:full":"1431 Lynn Rd Raleigh NC 27612",
    "addr:housenumber":"1431",
    "addr:postcode":"27612",
    "addr:street":"Lynn Rd",
    "iso:country":"US",
    "sg:address":"1431 Lynn Rd",
    "sg:city":"Raleigh",
    "sg:classifiers":[
        {
            "category":"Local Transit",
            "type":"Transportation"
        }
    ],
    "sg:phone":"+1 919 848 0021",
    "sg:postcode":"27612",
    "sg:province":"NC",
    "sg:tags":[
        "passenger"
    ],
    "wof:name":"Six Forks",
    "wof:placetype":"venue"
},
  "geometry": {"coordinates":[-78.660032,35.872133],"type":"Point"}
}