{
  "type": "Feature",
  "properties": {
    "iso:country":"US",
    "sg:address":"308 E Main St",
    "sg:city":"Dallas",
    "sg:classifiers":[
        {
            "category":"Building & Trades",
            "subcategory":"Plumbing",
            "type":"Services"
        }
    ],
    "sg:phone":"+1 704 922 4151",
    "sg:postcode":"28034",
    "sg:province":"NC",
    "sg:tags":[
        "air",
        "heating",
        "conditioning",
        "contractor"
    ],
    "wof:name":"Rudisill Brothers Co Inc",
    "wof:placetype":"venue"
},
  "geometry": {"coordinates":[-81.172811,35.315357],"type":"Point"}
}