{
  "type": "Feature",
  "properties": {
    "addr:full":"4400 Sharon Rd Charlotte NC 28211",
    "addr:housenumber":"4400",
    "addr:postcode":"28211",
    "addr:street":"Sharon Rd",
    "iso:country":"US",
    "sg:address":"4400 Sharon Rd",
    "sg:city":"Charlotte",
    "sg:classifiers":[
        {
            "category":"Restaurant",
            "type":"Food & Drink"
        }
    ],
    "sg:menulink":"http://www.allmenus.com/nc/charlotte/180151-chick-fil-a/menu/",
    "sg:phone":"+1 704 364 5770",
    "sg:postcode":"28211",
    "sg:province":"NC",
    "sg:tags":[
        "wrap",
        "soup",
        "american",
        "sandwich",
        "salad"
    ],
    "wof:name":"Chick-fil-A",
    "wof:placetype":"venue"
},
  "geometry": {"coordinates":[-80.827788,35.151948],"type":"Point"}
}