{
  "type": "Feature",
  "properties": {
    "addr:full":"141 Sheep Hill Rd Pikeville NC 27863",
    "addr:housenumber":"141",
    "addr:postcode":"27863",
    "addr:street":"Sheep Hill Rd",
    "iso:country":"US",
    "sg:address":"141 Sheep Hill Rd",
    "sg:city":"Pikeville",
    "sg:classifiers":[
        {
            "category":"Building & Trades",
            "subcategory":"Construction",
            "type":"Services"
        }
    ],
    "sg:phone":"+1 919 920 0678",
    "sg:postcode":"27863",
    "sg:province":"NC",
    "sg:tags":[
        "contractor"
    ],
    "wof:name":"Custom Vinyl Exteriors",
    "wof:placetype":"venue"
},
  "geometry": {"coordinates":[-78.06567200000001,35.466627],"type":"Point"}
}