{
  "type": "Feature",
  "properties": {
    "addr:full":"318 N Center St Statesville NC 28677",
    "addr:housenumber":"318",
    "addr:postcode":"28677",
    "addr:street":"N Center St",
    "iso:country":"US",
    "sg:address":"318 N Center St",
    "sg:city":"Statesville",
    "sg:classifiers":[
        {
            "category":"Professional",
            "subcategory":"Accounting & Tax Preparation",
            "type":"Services"
        }
    ],
    "sg:phone":"+1   ",
    "sg:postcode":"28677",
    "sg:province":"NC",
    "wof:name":"Dorothy Reep Accounting Svc",
    "wof:placetype":"venue"
},
  "geometry": {"coordinates":[-80.891537,35.790448],"type":"Point"}
}