{
  "type": "Feature",
  "properties": {
    "iso:country":"US",
    "sg:address":"435 Hunter Ln",
    "sg:city":"Charlotte",
    "sg:classifiers":[
        {
            "category":"Shopping",
            "type":"Retail Goods"
        }
    ],
    "sg:phone":"+1 704 365 4059",
    "sg:postcode":"28211",
    "sg:province":"NC",
    "sg:tags":[
        "picture",
        "frame"
    ],
    "wof:name":"Castro Ventures Inc",
    "wof:placetype":"venue"
},
  "geometry": {"coordinates":[-80.78928000000001,35.171847],"type":"Point"}
}