{
  "type": "Feature",
  "properties": {
    "iso:country":"US",
    "sg:address":"3200 Kenly Ct",
    "sg:city":"Raleigh",
    "sg:classifiers":[
        {
            "category":"Professional",
            "subcategory":"Accounting & Tax Preparation",
            "type":"Services"
        }
    ],
    "sg:phone":"+1 919 783 0911",
    "sg:postcode":"27607",
    "sg:province":"NC",
    "sg:tags":[
        "accountant"
    ],
    "wof:name":"Perkins Michael F CPA",
    "wof:placetype":"venue"
},
  "geometry": {"coordinates":[-78.67849699999999,35.817299],"type":"Point"}
}