{
  "type": "Feature",
  "properties": {
    "addr:full":"939 4th St SW Conover NC 28613",
    "addr:housenumber":"939",
    "addr:postcode":"28613",
    "addr:street":"4Th St Sw",
    "iso:country":"US",
    "sg:address":"939 4th St SW",
    "sg:city":"Conover",
    "sg:classifiers":[
        {
            "category":"Building & Trades",
            "subcategory":"Construction",
            "type":"Services"
        }
    ],
    "sg:phone":"+1 828 464 4808",
    "sg:postcode":"28613",
    "sg:province":"NC",
    "sg:tags":[
        "marking",
        "maintenance",
        "parking"
    ],
    "wof:name":"Conover Public Works",
    "wof:placetype":"venue"
},
  "geometry": {"coordinates":[-81.233024,35.703472],"type":"Point"}
}