{
  "type": "Feature",
  "properties": {
    "iso:country":"US",
    "sg:address":"1200 National Dr",
    "sg:city":"Winston Salem",
    "sg:classifiers":[
        {
            "category":"Freight",
            "type":"Transportation"
        }
    ],
    "sg:phone":"+1 336 722 2744",
    "sg:postcode":"27103",
    "sg:province":"NC",
    "sg:tags":[
        "commercial",
        "storage",
        "general"
    ],
    "wof:name":"Piedmont Self-Storage Inc",
    "wof:placetype":"venue"
},
  "geometry": {"coordinates":[-80.258284,36.07338],"type":"Point"}
}