{
  "type": "Feature",
  "properties": {
    "addr:full":"147 Union St S Concord NC 28025",
    "addr:housenumber":"147",
    "addr:postcode":"28025",
    "addr:street":"Union St S",
    "iso:country":"US",
    "sg:address":"147 Union St S",
    "sg:city":"Concord",
    "sg:classifiers":[
        {
            "category":"Manufacturing",
            "subcategory":"Printing",
            "type":"Manufacturing & Wholesale Goods"
        }
    ],
    "sg:phone":"+1 704 795 2002",
    "sg:postcode":"28025",
    "sg:province":"NC",
    "sg:tags":[
        "publishing"
    ],
    "wof:name":"Motorsports Publishing Group",
    "wof:placetype":"venue"
},
  "geometry": {"coordinates":[-80.577817,35.407597],"type":"Point"}
}