{
  "type": "Feature",
  "properties": {
    "iso:country":"US",
    "sg:address":"1219 Goose Creek Rd",
    "sg:city":"Marion",
    "sg:classifiers":[
        {
            "category":"Manufacturing",
            "subcategory":"Tools & Machinery",
            "type":"Manufacturing & Wholesale Goods"
        }
    ],
    "sg:phone":"+1 828 738 3778",
    "sg:postcode":"28752",
    "sg:province":"NC",
    "sg:tags":[
        "machine",
        "shop",
        "industrial",
        "mfg"
    ],
    "wof:name":"Goose Creek Machine & Tools",
    "wof:placetype":"venue"
},
  "geometry": {"coordinates":[-82.033779,35.6292],"type":"Point"}
}