{
  "type": "Feature",
  "properties": {
    "addr:full":"2005 E Market St Greensboro NC 27401",
    "addr:housenumber":"2005",
    "addr:postcode":"27401",
    "addr:street":"E Market St",
    "iso:country":"US",
    "sg:address":"2005 E Market St",
    "sg:city":"Greensboro",
    "sg:classifiers":[
        {
            "category":"Personal",
            "subcategory":"Beauty Salon",
            "type":"Services"
        }
    ],
    "sg:phone":"+1   ",
    "sg:postcode":"27401",
    "sg:province":"NC",
    "sg:tags":[
        "shop"
    ],
    "wof:name":"Shear Essnce Hair Dsign Studio",
    "wof:placetype":"venue"
},
  "geometry": {"coordinates":[-79.76508699999999,36.073731],"type":"Point"}
}