{
  "type": "Feature",
  "properties": {
    "iso:country":"US",
    "sg:address":"2237 Pauls Path Rd",
    "sg:city":"Kinston",
    "sg:classifiers":[
        {
            "category":"Personal",
            "subcategory":"Hair Removal",
            "type":"Services"
        }
    ],
    "sg:phone":"+1   ",
    "sg:postcode":"28504",
    "sg:province":"NC",
    "wof:name":"TNT",
    "wof:placetype":"venue"
},
  "geometry": {"coordinates":[-77.666275,35.305082],"type":"Point"}
}