{
  "type": "Feature",
  "properties": {
    "addr:full":"11921 Tanton Ln Charlotte NC 28273",
    "addr:housenumber":"11921",
    "addr:postcode":"28273",
    "addr:street":"Tanton Ln",
    "iso:country":"US",
    "sg:address":"11921 Tanton Ln",
    "sg:city":"Charlotte",
    "sg:classifiers":[
        {
            "category":"Shopping",
            "subcategory":"Stationery & Office Supplies",
            "type":"Retail Goods"
        }
    ],
    "sg:phone":"+1 704 588 6268",
    "sg:postcode":"28273",
    "sg:province":"NC",
    "wof:name":"Typeffects",
    "wof:placetype":"venue"
},
  "geometry": {"coordinates":[-80.967634,35.10534],"type":"Point"}
}