{
  "type": "Feature",
  "properties": {
    "iso:country":"US",
    "sg:address":"7111 US Hwy 70",
    "sg:city":"Newport",
    "sg:classifiers":[
        {
            "category":"Shopping",
            "subcategory":"Discount & Variety Stores",
            "type":"Retail Goods"
        }
    ],
    "sg:phone":"+1 252 223 2582",
    "sg:postcode":"28570",
    "sg:province":"NC",
    "wof:name":"Dollar General",
    "wof:placetype":"venue"
},
  "geometry": {"coordinates":[-76.876025,34.789594],"type":"Point"}
}