{
  "type": "Feature",
  "properties": {
    "iso:country":"US",
    "sg:address":"2424 S Wrightsville Ave",
    "sg:city":"Nags Head",
    "sg:classifiers":[
        {
            "category":"Communications",
            "subcategory":"Radio Station",
            "type":"Services"
        }
    ],
    "sg:phone":"+1 252 449 8331",
    "sg:postcode":"27959",
    "sg:province":"NC",
    "wof:name":"Werx FM",
    "wof:placetype":"venue"
},
  "geometry": {"coordinates":[-75.638645,35.978348],"type":"Point"}
}