{
  "type": "Feature",
  "properties": {
    "iso:country":"US",
    "sg:address":"935 3rd Ave SE",
    "sg:city":"Hickory",
    "sg:classifiers":[
        {
            "category":"Professional",
            "subcategory":"Detective & Security Services",
            "type":"Services"
        }
    ],
    "sg:phone":"+1 828 328 4036",
    "sg:postcode":"28602",
    "sg:province":"NC",
    "sg:tags":[
        "agency"
    ],
    "wof:name":"August Investigations",
    "wof:placetype":"venue"
},
  "geometry": {"coordinates":[-81.320125,35.728397],"type":"Point"}
}