{
  "type": "Feature",
  "properties": {
    "addr:full":"609 E Brown St Randleman NC 27317",
    "addr:housenumber":"609",
    "addr:postcode":"27317",
    "addr:street":"E Brown St",
    "iso:country":"US",
    "sg:address":"609 E Brown St",
    "sg:city":"Randleman",
    "sg:classifiers":[
        {
            "category":"Building & Trades",
            "subcategory":"Construction",
            "type":"Services"
        }
    ],
    "sg:phone":"+1 336 498 3359",
    "sg:postcode":"27317",
    "sg:province":"NC",
    "sg:tags":[
        "contractor"
    ],
    "wof:name":"King Masonry",
    "wof:placetype":"venue"
},
  "geometry": {"coordinates":[-79.794854,35.813292],"type":"Point"}
}