{
  "type": "Feature",
  "properties": {
    "addr:full":"280 Franklin Church Dr Salisbury NC 28147",
    "addr:housenumber":"280",
    "addr:postcode":"28147",
    "addr:street":"Franklin Church Dr",
    "iso:country":"US",
    "sg:address":"280 Franklin Church Dr",
    "sg:city":"Salisbury",
    "sg:classifiers":[
        {
            "category":"Organizations",
            "subcategory":"Religious Organization",
            "type":"Services"
        }
    ],
    "sg:phone":"+1   ",
    "sg:postcode":"28147",
    "sg:province":"NC",
    "wof:name":"Franklin Presbyterian Church",
    "wof:placetype":"venue"
},
  "geometry": {"coordinates":[-80.501903,35.723318],"type":"Point"}
}