{
  "type": "Feature",
  "properties": {
    "iso:country":"US",
    "sg:address":"3708 Westwood Rd",
    "sg:city":"Hamptonville",
    "sg:classifiers":[
        {
            "category":"Personal",
            "type":"Services"
        }
    ],
    "sg:phone":"+1   ",
    "sg:postcode":"27020",
    "sg:province":"NC",
    "wof:name":"Bill Brown",
    "wof:placetype":"venue"
},
  "geometry": {"coordinates":[-80.78432100000001,36.126684],"type":"Point"}
}