{
  "type": "Feature",
  "properties": {
    "addr:full":"11707 Windy Mist Way Huntersville NC 28078",
    "addr:housenumber":"11707",
    "addr:postcode":"28078",
    "addr:street":"Windy Mist Way",
    "iso:country":"US",
    "sg:address":"11707 Windy Mist Way",
    "sg:city":"Huntersville",
    "sg:classifiers":[
        {
            "category":"Building & Trades",
            "subcategory":"Construction",
            "type":"Services"
        }
    ],
    "sg:phone":"+1 704 875 1903",
    "sg:postcode":"28078",
    "sg:province":"NC",
    "sg:tags":[
        "home",
        "builder"
    ],
    "wof:name":"D R Horton Inc",
    "wof:placetype":"venue"
},
  "geometry": {"coordinates":[-80.91432500000001,35.378651],"type":"Point"}
}