{
  "type": "Feature",
  "properties": {
    "iso:country":"US",
    "sg:address":"2119 Hubbard St",
    "sg:city":"Greensboro",
    "sg:classifiers":[
        {
            "category":"Building & Trades",
            "subcategory":"Electrical",
            "type":"Services"
        },
        {
            "category":"Professional",
            "type":"Services"
        }
    ],
    "sg:phone":"+1 336 275 1147",
    "sg:postcode":"27405",
    "sg:province":"NC",
    "sg:tags":[
        "electrical",
        "contractor"
    ],
    "wof:name":"Trauma Services",
    "wof:placetype":"venue"
},
  "geometry": {"coordinates":[-79.779053,36.101618],"type":"Point"}
}