{
  "type": "Feature",
  "properties": {
    "iso:country":"US",
    "sg:address":"901 W Chapel Hill St",
    "sg:city":"Durham",
    "sg:classifiers":[
        {
            "category":"Professional",
            "subcategory":"Accounting & Tax Preparation",
            "type":"Services"
        }
    ],
    "sg:phone":"+1 919 683 2614",
    "sg:postcode":"27701",
    "sg:province":"NC",
    "sg:tags":[
        "accountant"
    ],
    "wof:name":"Pless Pless & Stephens",
    "wof:placetype":"venue"
},
  "geometry": {"coordinates":[-78.91503299999999,35.996845],"type":"Point"}
}