{
  "type": "Feature",
  "properties": {
    "addr:full":"101 Dairy Rd Reidsville NC 27320",
    "addr:housenumber":"101",
    "addr:postcode":"27320",
    "addr:street":"Dairy Rd",
    "iso:country":"US",
    "sg:address":"101 Dairy Rd",
    "sg:city":"Reidsville",
    "sg:classifiers":[
        {
            "category":"Travel",
            "subcategory":"Hotels & Motels",
            "type":"Entertainment"
        }
    ],
    "sg:phone":"+1 336 361 4000",
    "sg:postcode":"27320",
    "sg:province":"NC",
    "wof:name":"Holiday Inn Express Reidsville",
    "wof:placetype":"venue"
},
  "geometry": {"coordinates":[-79.73554799999999,36.368176],"type":"Point"}
}