{
  "type": "Feature",
  "properties": {
    "addr:full":"1619 Carolina Beach Ave N Carolina Beach NC 28428",
    "addr:housenumber":"1619",
    "addr:postcode":"28428",
    "addr:street":"Carolina Beach Ave N Carolina Beach",
    "iso:country":"US",
    "sg:address":"1619 Carolina Beach Ave N",
    "sg:city":"Carolina Beach",
    "sg:classifiers":[
        {
            "category":"Sports & Exercise",
            "subcategory":"Swimming Pool",
            "type":"Entertainment"
        }
    ],
    "sg:phone":"+1 910 458 6489",
    "sg:postcode":"28428",
    "sg:province":"NC",
    "wof:name":"Seascape Homeowners Assoc Swimming Pool",
    "wof:placetype":"venue"
},
  "geometry": {"coordinates":[-77.88300700000001,34.054366],"type":"Point"}
}