{
  "type": "Feature",
  "properties": {
    "iso:country":"US",
    "sg:address":"221 N 1st Ave",
    "sg:city":"Knightdale",
    "sg:classifiers":[
        {
            "category":"Home & Garden",
            "subcategory":"Building Materials",
            "type":"Retail Goods"
        }
    ],
    "sg:phone":"+1 919 266 2493",
    "sg:postcode":"27545",
    "sg:province":"NC",
    "sg:tags":[
        "glass",
        "leaded"
    ],
    "wof:name":"Stained Glass Assoc",
    "wof:placetype":"venue"
},
  "geometry": {"coordinates":[-78.47953,35.789078],"type":"Point"}
}