{
  "type": "Feature",
  "properties": {
    "iso:country":"US",
    "sg:address":"115 E Lewis St",
    "sg:city":"Greensboro",
    "sg:classifiers":[
        {
            "category":"Retail",
            "subcategory":"Auto Repair",
            "type":"Services"
        }
    ],
    "sg:phone":"+1   ",
    "sg:postcode":"27406",
    "sg:province":"NC",
    "sg:tags":[
        "automotive",
        "general"
    ],
    "wof:name":"Bellamys Auto Service",
    "wof:placetype":"venue"
},
  "geometry": {"coordinates":[-79.78940299999999,36.065967],"type":"Point"}
}