{
  "type": "Feature",
  "properties": {
    "addr:full":"207 Premier Ln Pilot Mountain NC 27041",
    "addr:housenumber":"207",
    "addr:postcode":"27041",
    "addr:street":"Premier Ln",
    "iso:country":"US",
    "sg:address":"207 Premier Ln",
    "sg:city":"Pilot Mountain",
    "sg:classifiers":[
        {
            "category":"Manufacturing",
            "subcategory":"Metals",
            "type":"Manufacturing & Wholesale Goods"
        }
    ],
    "sg:phone":"+1 336 368 1302",
    "sg:postcode":"27041",
    "sg:province":"NC",
    "sg:tags":[
        "fab",
        "steel",
        "mfg",
        "wire",
        "fa"
    ],
    "wof:name":"Rack Works Inc",
    "wof:placetype":"venue"
},
  "geometry": {"coordinates":[-80.55701500000001,36.43246],"type":"Point"}
}