{
  "type": "Feature",
  "properties": {
    "addr:full":"145 N Center St Goldsboro NC 27530",
    "addr:housenumber":"145",
    "addr:postcode":"27530",
    "addr:street":"N Center St",
    "iso:country":"US",
    "sg:address":"145 N Center St",
    "sg:city":"Goldsboro",
    "sg:classifiers":[
        {
            "category":"Shopping",
            "type":"Retail Goods"
        }
    ],
    "sg:phone":"+1 919 580 9944",
    "sg:postcode":"27530",
    "sg:province":"NC",
    "sg:tags":[
        "merchandise"
    ],
    "wof:name":"La Paws Grooming Parlor",
    "wof:placetype":"venue"
},
  "geometry": {"coordinates":[-77.996937,35.38385],"type":"Point"}
}