{
  "type": "Feature",
  "properties": {
    "addr:full":"894 S Kerr Ave Wilmington NC 28403",
    "addr:housenumber":"894",
    "addr:postcode":"28403",
    "addr:street":"S Kerr Ave",
    "iso:country":"US",
    "sg:address":"894 S Kerr Ave",
    "sg:city":"Wilmington",
    "sg:classifiers":[
        {
            "category":"Banks & Credit Unions",
            "subcategory":"Investment Brokerage",
            "type":"Services"
        }
    ],
    "sg:phone":"+1 910 452 6432",
    "sg:postcode":"28403",
    "sg:province":"NC",
    "sg:tags":[
        "security"
    ],
    "wof:name":"Edward Jones Co",
    "wof:placetype":"venue"
},
  "geometry": {"coordinates":[-77.88622599999999,34.222735],"type":"Point"}
}