{
  "type": "Feature",
  "properties": {
    "iso:country":"US",
    "sg:address":"4246 Asherton Dr",
    "sg:city":"Charlotte",
    "sg:classifiers":[
        {
            "category":"Professional",
            "subcategory":"Business Services",
            "type":"Services"
        }
    ],
    "sg:phone":"+1   ",
    "sg:postcode":"28226",
    "sg:province":"NC",
    "wof:name":"Associated Packaging Inc",
    "wof:placetype":"venue"
},
  "geometry": {"coordinates":[-80.840975,35.101471],"type":"Point"}
}