{
  "type": "Feature",
  "properties": {
    "addr:full":"1101 N Turkey Creek Rd Leicester NC 28748",
    "addr:housenumber":"1101",
    "addr:postcode":"28748",
    "addr:street":"N Turkey Creek Rd",
    "iso:country":"US",
    "sg:address":"1101 N Turkey Creek Rd",
    "sg:city":"Leicester",
    "sg:classifiers":[
        {
            "category":"Freight",
            "type":"Transportation"
        }
    ],
    "sg:phone":"+1 828 683 6035",
    "sg:postcode":"28748",
    "sg:province":"NC",
    "sg:tags":[
        "packing",
        "crating"
    ],
    "wof:name":"Clarks Tomato Packing House",
    "wof:placetype":"venue"
},
  "geometry": {"coordinates":[-82.77000700000001,35.656574],"type":"Point"}
}