{
  "type": "Feature",
  "properties": {
    "iso:country":"US",
    "sg:address":"2808 Brewton Pl",
    "sg:city":"Raleigh",
    "sg:classifiers":[
        {
            "category":"Taxi",
            "type":"Transportation"
        }
    ],
    "sg:phone":"+1 919 790 1488",
    "sg:postcode":"27604",
    "sg:province":"NC",
    "sg:tags":[
        "taxicab"
    ],
    "wof:name":"Cardinal Transit Inc",
    "wof:placetype":"venue"
},
  "geometry": {"coordinates":[-78.592778,35.820026],"type":"Point"}
}