{
  "type": "Feature",
  "properties": {
    "addr:full":"4862 Range Ridge Rd Claremont NC 28610",
    "addr:housenumber":"4862",
    "addr:postcode":"28610",
    "addr:street":"Range Ridge Rd",
    "iso:country":"US",
    "sg:address":"4862 Range Ridge Rd",
    "sg:city":"Claremont",
    "sg:classifiers":[
        {
            "category":"Farming",
            "subcategory":"Poultry Farm",
            "type":"Manufacturing & Wholesale Goods"
        }
    ],
    "sg:phone":"+1 828 241 5959",
    "sg:postcode":"28610",
    "sg:province":"NC",
    "sg:tags":[
        "egg"
    ],
    "wof:name":"Elmore Poultry Farm",
    "wof:placetype":"venue"
},
  "geometry": {"coordinates":[-81.091719,35.651166],"type":"Point"}
}