{
  "type": "Feature",
  "properties": {
    "addr:full":"5622 E Independence Blvd Charlotte NC 28212",
    "addr:housenumber":"5622",
    "addr:postcode":"28212",
    "addr:street":"E Independence Blvd",
    "iso:country":"US",
    "sg:address":"5622 E Independence Blvd",
    "sg:city":"Charlotte",
    "sg:classifiers":[
        {
            "category":"Personal",
            "subcategory":"Beauty Salon",
            "type":"Services"
        }
    ],
    "sg:phone":"+1 704 535 1104",
    "sg:postcode":"28212",
    "sg:province":"NC",
    "sg:tags":[
        "unisex",
        "hair"
    ],
    "wof:name":"Supercuts",
    "wof:placetype":"venue"
},
  "geometry": {"coordinates":[-80.754435,35.181427],"type":"Point"}
}