{
  "type": "Feature",
  "properties": {
    "addr:full":"760 Hadrian Dr Garner NC 27529",
    "addr:housenumber":"760",
    "addr:postcode":"27529",
    "addr:street":"Hadrian Dr",
    "iso:country":"US",
    "sg:address":"760 Hadrian Dr",
    "sg:city":"Garner",
    "sg:classifiers":[
        {
            "category":"Retail",
            "subcategory":"Animal Services",
            "type":"Services"
        }
    ],
    "sg:phone":"+1 919 772 5861",
    "sg:postcode":"27529",
    "sg:province":"NC",
    "wof:name":"Claws & Paws Inc",
    "wof:placetype":"venue"
},
  "geometry": {"coordinates":[-78.61567599999999,35.677744],"type":"Point"}
}