{
  "type": "Feature",
  "properties": {
    "addr:full":"5030 Southport-Supply Rd SE Southport NC 28461",
    "addr:housenumber":"5030",
    "addr:postcode":"28461",
    "addr:street":"Southport-Supply Rd Se",
    "iso:country":"US",
    "sg:address":"5030 Southport-Supply Rd SE",
    "sg:city":"Southport",
    "sg:classifiers":[
        {
            "category":"Home & Garden",
            "subcategory":"Carpets & Floor Coverings",
            "type":"Retail Goods"
        }
    ],
    "sg:phone":"+1 910 454 4020",
    "sg:postcode":"28461",
    "sg:province":"NC",
    "sg:tags":[
        "material"
    ],
    "wof:name":"D's Hardwood Floors",
    "wof:placetype":"venue"
},
  "geometry": {"coordinates":[-78.048474,33.952443],"type":"Point"}
}