{
  "type": "Feature",
  "properties": {
    "iso:country":"US",
    "sg:address":"6923 US Hwy 70",
    "sg:city":"Newport",
    "sg:classifiers":[
        {
            "category":"Shopping",
            "type":"Retail Goods"
        }
    ],
    "sg:phone":"+1 252 223 4700",
    "sg:postcode":"28570",
    "sg:province":"NC",
    "sg:tags":[
        "c",
        "supply",
        "above",
        "ground",
        "pool",
        "swimming"
    ],
    "wof:name":"Atlantic Breeze Pools Hot Tubs",
    "wof:placetype":"venue"
},
  "geometry": {"coordinates":[-76.876064,34.78849],"type":"Point"}
}