{
  "type": "Feature",
  "properties": {
    "addr:full":"403 E Jefferson St Monroe NC 28112",
    "addr:housenumber":"403",
    "addr:postcode":"28112",
    "addr:street":"E Jefferson St",
    "iso:country":"US",
    "sg:address":"403 E Jefferson St",
    "sg:city":"Monroe",
    "sg:classifiers":[
        {
            "category":"Manufacturing",
            "subcategory":"Signs",
            "type":"Manufacturing & Wholesale Goods"
        },
        {
            "category":"Professional",
            "subcategory":"Business Services",
            "type":"Services"
        }
    ],
    "sg:phone":"+1 704 225 0673",
    "sg:postcode":"28112",
    "sg:province":"NC",
    "sg:tags":[
        "specialty",
        "painter",
        "mfg"
    ],
    "wof:name":"Sign Masters",
    "wof:placetype":"venue"
},
  "geometry": {"coordinates":[-80.545869,34.982922],"type":"Point"}
}