{
  "type": "Feature",
  "properties": {
    "iso:country":"US",
    "sg:address":"709 Long Meadows Rd",
    "sg:city":"Chapel Hill",
    "sg:classifiers":[
        {
            "category":"Building & Trades",
            "subcategory":"Construction",
            "type":"Services"
        }
    ],
    "sg:phone":"+1 919 967 2079",
    "sg:postcode":"27516",
    "sg:province":"NC",
    "sg:tags":[
        "contractor"
    ],
    "sg:website":"www.davidweekleyhomes.com",
    "wof:name":"David Weekley Homes Llc",
    "wof:placetype":"venue"
},
  "geometry": {"coordinates":[-79.104389,35.954397],"type":"Point"}
}