{
  "type": "Feature",
  "properties": {
    "iso:country":"US",
    "sg:address":"313 W Martin St",
    "sg:city":"Raleigh",
    "sg:classifiers":[
        {
            "category":"Professional",
            "type":"Services"
        }
    ],
    "sg:phone":"+1 919 834 1665",
    "sg:postcode":"27601",
    "sg:province":"NC",
    "sg:tags":[
        "establishment"
    ],
    "wof:name":"Sutherland Welles LTD",
    "wof:placetype":"venue"
},
  "geometry": {"coordinates":[-78.643519,35.777066],"type":"Point"}
}