{
  "type": "Feature",
  "properties": {
    "iso:country":"US",
    "sg:address":"113 W 10th St",
    "sg:city":"Roanoke Rapids",
    "sg:classifiers":[
        {
            "category":"Professional",
            "subcategory":"Lawyer & Legal Services",
            "type":"Services"
        }
    ],
    "sg:phone":"+1 252 535 2266",
    "sg:postcode":"27870",
    "sg:province":"NC",
    "sg:tags":[
        "attorney"
    ],
    "wof:name":"Monique Skinner Dixon",
    "wof:placetype":"venue"
},
  "geometry": {"coordinates":[-77.65759199999999,36.456254],"type":"Point"}
}