{
  "type": "Feature",
  "properties": {
    "iso:country":"US",
    "sg:address":"1071 Beaver Creek Commons Dr",
    "sg:city":"Apex",
    "sg:classifiers":[
        {
            "category":"Health Services",
            "subcategory":"Health Practitioner",
            "type":"Services"
        }
    ],
    "sg:phone":"+1 919 290 2780",
    "sg:postcode":"27502",
    "sg:province":"NC",
    "sg:tags":[
        "nutritionist"
    ],
    "wof:name":"Peak Nutrition Inc",
    "wof:placetype":"venue"
},
  "geometry": {"coordinates":[-78.87441200000001,35.745326],"type":"Point"}
}