{
  "type": "Feature",
  "properties": {
    "iso:country":"US",
    "sg:address":"105 Salter Path Rd",
    "sg:city":"Atlantic Beach",
    "sg:classifiers":[
        {
            "category":"Travel",
            "subcategory":"Hotels & Motels",
            "type":"Entertainment"
        }
    ],
    "sg:phone":"+1 252 726 4146",
    "sg:postcode":"28512",
    "sg:province":"NC",
    "wof:name":"Seahawk Motor Lodge",
    "wof:placetype":"venue"
},
  "geometry": {"coordinates":[-76.78315000000001,34.697887],"type":"Point"}
}