{
  "type": "Feature",
  "properties": {
    "iso:country":"US",
    "sg:address":"2705 Van Dyke Ave",
    "sg:city":"Raleigh",
    "sg:classifiers":[
        {
            "category":"Communications",
            "subcategory":"Film & Video Production",
            "type":"Services"
        }
    ],
    "sg:phone":"+1 919 833 4160",
    "sg:postcode":"27607",
    "sg:province":"NC",
    "sg:tags":[
        "motion",
        "taping"
    ],
    "wof:name":"Words & Pictures Inc",
    "wof:placetype":"venue"
},
  "geometry": {"coordinates":[-78.67279499999999,35.795085],"type":"Point"}
}