{
  "type": "Feature",
  "properties": {
    "iso:country":"US",
    "sg:address":"12393 State Hwy 210",
    "sg:city":"Rocky Point",
    "sg:classifiers":[
        {
            "category":"Freight",
            "type":"Transportation"
        }
    ],
    "sg:phone":"+1 910 675 8309",
    "sg:postcode":"28457",
    "sg:province":"NC",
    "sg:tags":[
        "operator",
        "local",
        "trucking"
    ],
    "wof:name":"Malloy Trucking Inc",
    "wof:placetype":"venue"
},
  "geometry": {"coordinates":[-77.85733999999999,34.440112],"type":"Point"}
}