{
  "type": "Feature",
  "properties": {
    "addr:full":"1514 Jake Alexander Blvd W Salisbury NC 28147",
    "addr:housenumber":"1514",
    "addr:postcode":"28147",
    "addr:street":"Jake Alexander Blvd W",
    "iso:country":"US",
    "sg:address":"1514 Jake Alexander Blvd W",
    "sg:city":"Salisbury",
    "sg:classifiers":[
        {
            "category":"Freight",
            "type":"Transportation"
        }
    ],
    "sg:phone":"+1 704 637 3456",
    "sg:postcode":"28147",
    "sg:province":"NC",
    "sg:tags":[
        "warehouse",
        "apparel",
        "for"
    ],
    "wof:name":"Robert Alan Sales Inc",
    "wof:placetype":"venue"
},
  "geometry": {"coordinates":[-80.50666699999999,35.681414],"type":"Point"}
}