{
  "type": "Feature",
  "properties": {
    "iso:country":"US",
    "sg:address":"524 Cox Rd",
    "sg:city":"Gastonia",
    "sg:classifiers":[
        {
            "category":"Restaurant",
            "type":"Food & Drink"
        }
    ],
    "sg:menulink":"http://www.allmenus.com/nc/gastonia/158813-arbys/menu/",
    "sg:phone":"+1 704 869 9871",
    "sg:postcode":"28054",
    "sg:province":"NC",
    "sg:tags":[
        "burger",
        "american"
    ],
    "wof:name":"Arby's",
    "wof:placetype":"venue"
},
  "geometry": {"coordinates":[-81.13382900000001,35.266952],"type":"Point"}
}