{
  "type": "Feature",
  "properties": {
    "iso:country":"US",
    "sg:address":"260 Town Hall Dr Ste A",
    "sg:city":"Morrisville",
    "sg:classifiers":[
        {
            "category":"Organizations",
            "subcategory":"Non-profit Organization",
            "type":"Services"
        }
    ],
    "sg:phone":"+1 919 319 0014",
    "sg:postcode":"27560",
    "sg:province":"NC",
    "sg:tags":[
        "service/non-profit",
        "community"
    ],
    "sg:website":"www.hemophilia-nc.org",
    "wof:name":"Hemophilia of North Carolina",
    "wof:placetype":"venue"
},
  "geometry": {"coordinates":[-78.830415,35.823159],"type":"Point"}
}