{
  "type": "Feature",
  "properties": {
    "iso:country":"US",
    "sg:address":"4298 Pleasant Valley Rd",
    "sg:city":"Greensboro",
    "sg:classifiers":[
        {
            "category":"Social Services",
            "type":"Services"
        }
    ],
    "sg:phone":"+1   ",
    "sg:postcode":"27406",
    "sg:province":"NC",
    "wof:name":"B T C Services",
    "wof:placetype":"venue"
},
  "geometry": {"coordinates":[-79.806839,35.995928],"type":"Point"}
}