{
  "type": "Feature",
  "properties": {
    "addr:full":"28 N Lexington Ave Asheville NC 28801",
    "addr:housenumber":"28",
    "addr:postcode":"28801",
    "addr:street":"N Lexington Ave",
    "iso:country":"US",
    "sg:address":"28 N Lexington Ave",
    "sg:city":"Asheville",
    "sg:classifiers":[
        {
            "category":"Shopping",
            "subcategory":"Crafts & Fabrics",
            "type":"Retail Goods"
        }
    ],
    "sg:phone":"+1 828 254 3116",
    "sg:postcode":"28801",
    "sg:province":"NC",
    "sg:tags":[
        "material",
        "quilting",
        "supply"
    ],
    "wof:name":"Piece Gardens",
    "wof:placetype":"venue"
},
  "geometry": {"coordinates":[-82.55293,35.595902],"type":"Point"}
}