{
  "type": "Feature",
  "properties": {
    "iso:country":"US",
    "sg:address":"141 S Main St",
    "sg:city":"Stanley",
    "sg:classifiers":[
        {
            "category":"Professional",
            "subcategory":"Accounting & Tax Preparation",
            "type":"Services"
        }
    ],
    "sg:phone":"+1   ",
    "sg:postcode":"28164",
    "sg:province":"NC",
    "wof:name":"Alexander-Pace Tax Accounting",
    "wof:placetype":"venue"
},
  "geometry": {"coordinates":[-81.094989,35.358928],"type":"Point"}
}