{
  "type": "Feature",
  "properties": {
    "addr:full":"12208 Mapleton Rd Charlotte NC 28273",
    "addr:housenumber":"12208",
    "addr:postcode":"28273",
    "addr:street":"Mapleton Rd",
    "iso:country":"US",
    "sg:address":"12208 Mapleton Rd",
    "sg:city":"Charlotte",
    "sg:classifiers":[
        {
            "category":"Home & Garden",
            "subcategory":"Home Furnishings",
            "type":"Retail Goods"
        }
    ],
    "sg:phone":"+1 704 451 1351",
    "sg:postcode":"28273",
    "sg:province":"NC",
    "sg:tags":[
        "venetian",
        "blind"
    ],
    "wof:name":"A Blind & More",
    "wof:placetype":"venue"
},
  "geometry": {"coordinates":[-80.953969,35.147147],"type":"Point"}
}