{
  "type": "Feature",
  "properties": {
    "addr:full":"6140 Jonquil Dr Greensboro NC 27407",
    "addr:housenumber":"6140",
    "addr:postcode":"27407",
    "addr:street":"Jonquil Dr",
    "iso:country":"US",
    "sg:address":"6140 Jonquil Dr",
    "sg:city":"Greensboro",
    "sg:classifiers":[
        {
            "category":"Restaurant",
            "type":"Food & Drink"
        }
    ],
    "sg:phone":"+1 336 299 8621",
    "sg:postcode":"27407",
    "sg:province":"NC",
    "sg:tags":[
        "farm",
        "eating",
        "specialty",
        "animal"
    ],
    "wof:name":"Dr KS Cattle Dogs",
    "wof:placetype":"venue"
},
  "geometry": {"coordinates":[-79.878433,35.956716],"type":"Point"}
}