{
  "type": "Feature",
  "properties": {
    "iso:country":"US",
    "sg:address":"4805 Calder Ct",
    "sg:city":"Wilmington",
    "sg:classifiers":[
        {
            "category":"Insurance",
            "subcategory":"Hazard Insurance",
            "type":"Services"
        }
    ],
    "sg:phone":"+1 910 452 4233",
    "sg:postcode":"28405",
    "sg:province":"NC",
    "sg:tags":[
        "bond"
    ],
    "wof:name":"Freedom Bail Bond",
    "wof:placetype":"venue"
},
  "geometry": {"coordinates":[-77.868612,34.26477],"type":"Point"}
}