{
  "type": "Feature",
  "properties": {
    "addr:full":"1859 Evans Rd Cary NC 27513",
    "addr:housenumber":"1859",
    "addr:postcode":"27513",
    "addr:street":"Evans Rd",
    "iso:country":"US",
    "sg:address":"1859 Evans Rd",
    "sg:city":"Cary",
    "sg:classifiers":[
        {
            "category":"Professional",
            "subcategory":"Business Services",
            "type":"Services"
        }
    ],
    "sg:phone":"+1 919 297 0004",
    "sg:postcode":"27513",
    "sg:province":"NC",
    "sg:tags":[
        "fund",
        "promotion",
        "raising"
    ],
    "wof:name":"Bluegrass Promotional Mktng",
    "wof:placetype":"venue"
},
  "geometry": {"coordinates":[-78.802634,35.818431],"type":"Point"}
}