{
  "type": "Feature",
  "properties": {
    "iso:country":"US",
    "sg:address":"202 N Van Buren Rd",
    "sg:city":"Eden",
    "sg:classifiers":[
        {
            "category":"Banks & Credit Unions",
            "subcategory":"Investment Brokerage",
            "type":"Services"
        }
    ],
    "sg:phone":"+1 336 627 5363",
    "sg:postcode":"27288",
    "sg:province":"NC",
    "sg:tags":[
        "advisory",
        "financial"
    ],
    "wof:name":"Integrity Financial Svc",
    "wof:placetype":"venue"
},
  "geometry": {"coordinates":[-79.744243,36.505248],"type":"Point"}
}