{
  "type": "Feature",
  "properties": {
    "addr:full":"2525 Meridian Pkwy Durham NC 27713",
    "addr:housenumber":"2525",
    "addr:postcode":"27713",
    "addr:street":"Meridian Pkwy",
    "iso:country":"US",
    "sg:address":"2525 Meridian Pkwy",
    "sg:city":"Durham",
    "sg:classifiers":[
        {
            "category":"Professional",
            "subcategory":"Management & Consulting",
            "type":"Services"
        }
    ],
    "sg:phone":"+1 919 833 1766",
    "sg:postcode":"27713",
    "sg:province":"NC",
    "sg:tags":[
        "information",
        "business"
    ],
    "wof:name":"Filefrenzycom Inc",
    "wof:placetype":"venue"
},
  "geometry": {"coordinates":[-78.90254400000001,35.911868],"type":"Point"}
}