{
  "type": "Feature",
  "properties": {
    "iso:country":"US",
    "sg:address":"407 Lightwood Ln SW",
    "sg:city":"South Brunswick",
    "sg:classifiers":[
        {
            "category":"Arts & Performance",
            "subcategory":"Theater",
            "type":"Entertainment"
        }
    ],
    "sg:phone":"+1 910 754 6856",
    "sg:postcode":"28470",
    "sg:province":"NC",
    "sg:tags":[
        "musician"
    ],
    "wof:name":"Kindermusik Of Brunswick",
    "wof:placetype":"venue"
},
  "geometry": {"coordinates":[-78.374634,33.966859],"type":"Point"}
}