{
  "type": "Feature",
  "properties": {
    "iso:country":"US",
    "sg:address":"1827 Martin Luther King Jr Pkwy",
    "sg:city":"Durham",
    "sg:classifiers":[
        {
            "category":"Personal",
            "subcategory":"Beauty Salon",
            "type":"Services"
        }
    ],
    "sg:phone":"+1 919 403 1500",
    "sg:postcode":"27707",
    "sg:province":"NC",
    "sg:tags":[
        "shop"
    ],
    "sg:website":"www.greatclips.com",
    "wof:name":"Great Clips",
    "wof:placetype":"venue"
},
  "geometry": {"coordinates":[-78.95926799999999,35.960891],"type":"Point"}
}