{
  "type": "Feature",
  "properties": {
    "iso:country":"US",
    "sg:address":"2227 Inverness Rd",
    "sg:city":"Charlotte",
    "sg:classifiers":[
        {
            "category":"Professional",
            "subcategory":"Management & Consulting",
            "type":"Services"
        }
    ],
    "sg:phone":"+1   ",
    "sg:postcode":"28209",
    "sg:province":"NC",
    "sg:tags":[
        "planner",
        "financial"
    ],
    "wof:name":"C P A Club of Charlotte",
    "wof:placetype":"venue"
},
  "geometry": {"coordinates":[-80.840968,35.162729],"type":"Point"}
}