{
  "type": "Feature",
  "properties": {
    "iso:country":"US",
    "sg:address":"109 Brentwood Center Ln",
    "sg:city":"Wilson",
    "sg:classifiers":[
        {
            "category":"Health Services",
            "subcategory":"Doctor",
            "type":"Services"
        }
    ],
    "sg:phone":"+1 252 291 2892",
    "sg:postcode":"27896",
    "sg:province":"NC",
    "sg:tags":[
        "dentist"
    ],
    "wof:name":"Boles Ham Dixon & Boles",
    "wof:placetype":"venue"
},
  "geometry": {"coordinates":[-77.93057899999999,35.755047],"type":"Point"}
}