{
  "type": "Feature",
  "properties": {
    "addr:full":"5471 University Pkwy Winston Salem NC 27105",
    "addr:housenumber":"5471",
    "addr:postcode":"27105",
    "addr:street":"University Pkwy",
    "iso:country":"US",
    "sg:address":"5471 University Pkwy",
    "sg:city":"Winston Salem",
    "sg:classifiers":[
        {
            "category":"Shopping",
            "subcategory":"Pharmacy",
            "type":"Retail Goods"
        }
    ],
    "sg:phone":"+1 336 744 2321",
    "sg:postcode":"27105",
    "sg:province":"NC",
    "wof:name":"CVS Pharmacy",
    "wof:placetype":"venue"
},
  "geometry": {"coordinates":[-80.277205,36.170383],"type":"Point"}
}