{
  "type": "Feature",
  "properties": {
    "iso:country":"US",
    "sg:address":"14341 New Falls of Neuse Rd",
    "sg:city":"Raleigh",
    "sg:classifiers":[
        {
            "category":"Health Services",
            "subcategory":"Doctor",
            "type":"Services"
        }
    ],
    "sg:phone":"+1 919 861 6881",
    "sg:postcode":"27614",
    "sg:province":"NC",
    "sg:tags":[
        "physician",
        "surgeon"
    ],
    "wof:name":"Wakefield Internal Medicine",
    "wof:placetype":"venue"
},
  "geometry": {"coordinates":[-78.54492999999999,35.945785],"type":"Point"}
}