{
  "type": "Feature",
  "properties": {
    "iso:country":"US",
    "sg:address":"1686 Castle Rock Farm Rd",
    "sg:city":"Pittsboro",
    "sg:classifiers":[
        {
            "category":"Building & Trades",
            "subcategory":"Construction",
            "type":"Services"
        }
    ],
    "sg:phone":"+1 919 542 4335",
    "sg:postcode":"27312",
    "sg:province":"NC",
    "sg:tags":[
        "house"
    ],
    "wof:name":"Webster Construction Company",
    "wof:placetype":"venue"
},
  "geometry": {"coordinates":[-79.279453,35.80552],"type":"Point"}
}