{
  "type": "Feature",
  "properties": {
    "addr:full":"7904 River Ridge Rd Wake Forest NC 27587",
    "addr:housenumber":"7904",
    "addr:postcode":"27587",
    "addr:street":"River Ridge Rd",
    "iso:country":"US",
    "sg:address":"7904 River Ridge Rd",
    "sg:city":"Wake Forest",
    "sg:classifiers":[
        {
            "category":"Retail",
            "subcategory":"Repair Shop",
            "type":"Services"
        }
    ],
    "sg:phone":"+1   ",
    "sg:postcode":"27587",
    "sg:province":"NC",
    "wof:name":"Finishing Touches",
    "wof:placetype":"venue"
},
  "geometry": {"coordinates":[-78.528204,35.887148],"type":"Point"}
}