{
  "type": "Feature",
  "properties": {
    "addr:full":"329 Madison Beach Rd Madison NC 27025",
    "addr:housenumber":"329",
    "addr:postcode":"27025",
    "addr:street":"Beach Rd",
    "iso:country":"US",
    "sg:address":"329 Madison Beach Rd",
    "sg:city":"Madison",
    "sg:classifiers":[
        {
            "category":"Building & Trades",
            "subcategory":"Landscaping Services",
            "type":"Services"
        }
    ],
    "sg:phone":"+1 336 548 1545",
    "sg:postcode":"27025",
    "sg:province":"NC",
    "wof:name":"Carolina Custom Tree Inc",
    "wof:placetype":"venue"
},
  "geometry": {"coordinates":[-80.00903700000001,36.39472],"type":"Point"}
}