{
  "type": "Feature",
  "properties": {
    "iso:country":"US",
    "sg:address":"6309 Boathouse Rd",
    "sg:city":"Wilmington",
    "sg:classifiers":[
        {
            "category":"Professional",
            "subcategory":"Business Services",
            "type":"Services"
        }
    ],
    "sg:phone":"+1 910 395 5516",
    "sg:postcode":"28403",
    "sg:province":"NC",
    "wof:name":"Port City Group Inc",
    "wof:placetype":"venue"
},
  "geometry": {"coordinates":[-77.834367,34.212059],"type":"Point"}
}