{
  "type": "Feature",
  "properties": {
    "addr:full":"3702 Willow Run Dr Greenville NC 27858",
    "addr:housenumber":"3702",
    "addr:postcode":"27858",
    "addr:street":"Willow Run Dr",
    "iso:country":"US",
    "sg:address":"3702 Willow Run Dr",
    "sg:city":"Greenville",
    "sg:classifiers":[
        {
            "category":"Shopping",
            "subcategory":"Used Merchandise",
            "type":"Retail Goods"
        }
    ],
    "sg:phone":"+1 252 522 5593",
    "sg:postcode":"27858",
    "sg:province":"NC",
    "wof:name":"Radcliff & Associates",
    "wof:placetype":"venue"
},
  "geometry": {"coordinates":[-77.31948300000001,35.576562],"type":"Point"}
}