{
  "type": "Feature",
  "properties": {
    "addr:full":"1146 Twin Branch Dr Lexington NC 27295",
    "addr:housenumber":"1146",
    "addr:postcode":"27295",
    "addr:street":"Twin Branch Dr",
    "iso:country":"US",
    "sg:address":"1146 Twin Branch Dr",
    "sg:city":"Lexington",
    "sg:classifiers":[
        {
            "category":"Professional",
            "subcategory":"Computer Services",
            "type":"Services"
        }
    ],
    "sg:phone":"+1   ",
    "sg:postcode":"27295",
    "sg:province":"NC",
    "sg:tags":[
        "related"
    ],
    "wof:name":"T J B Consulting Inc",
    "wof:placetype":"venue"
},
  "geometry": {"coordinates":[-80.26472699999999,35.957144],"type":"Point"}
}