{
  "type": "Feature",
  "properties": {
    "addr:full":"644 W Pine St Mount Airy NC 27030",
    "addr:housenumber":"644",
    "addr:postcode":"27030",
    "addr:street":"W Pine St",
    "iso:country":"US",
    "sg:address":"644 W Pine St",
    "sg:city":"Mount Airy",
    "sg:classifiers":[
        {
            "category":"Retail",
            "subcategory":"Auto Repair",
            "type":"Services"
        }
    ],
    "sg:phone":"+1   ",
    "sg:postcode":"27030",
    "sg:province":"NC",
    "sg:tags":[
        "general"
    ],
    "wof:name":"Kings Garage II",
    "wof:placetype":"venue"
},
  "geometry": {"coordinates":[-80.61621599999999,36.498292],"type":"Point"}
}