{
  "type": "Feature",
  "properties": {
    "iso:country":"US",
    "sg:address":"144 Klutz Rd",
    "sg:city":"Mooresville",
    "sg:classifiers":[
        {
            "category":"Building & Trades",
            "subcategory":"Landscaping Services",
            "type":"Services"
        }
    ],
    "sg:phone":"+1 704 663 4211",
    "sg:postcode":"28115",
    "sg:province":"NC",
    "sg:tags":[
        "landscape"
    ],
    "wof:name":"Quliaty Fine Grading",
    "wof:placetype":"venue"
},
  "geometry": {"coordinates":[-80.831199,35.560228],"type":"Point"}
}