{
  "type": "Feature",
  "properties": {
    "iso:country":"US",
    "sg:address":"1609 Burke Rd",
    "sg:city":"Shelby",
    "sg:classifiers":[
        {
            "category":"Professional",
            "type":"Services"
        }
    ],
    "sg:phone":"+1 704 487 6712",
    "sg:postcode":"28152",
    "sg:province":"NC",
    "wof:name":"James F Queen",
    "wof:placetype":"venue"
},
  "geometry": {"coordinates":[-81.614608,35.234749],"type":"Point"}
}