{
  "type": "Feature",
  "properties": {
    "addr:full":"8325 Prince Edward Rd Oak Ridge NC 27357",
    "addr:housenumber":"8325",
    "addr:postcode":"27357",
    "addr:street":"Prince Edward Rd",
    "iso:country":"US",
    "sg:address":"8325 Prince Edward Rd",
    "sg:city":"Oak Ridge",
    "sg:classifiers":[
        {
            "category":"Building & Trades",
            "subcategory":"Construction",
            "type":"Services"
        },
        {
            "category":"Home & Garden",
            "subcategory":"Furniture",
            "type":"Retail Goods"
        }
    ],
    "sg:phone":"+1 336 644 0675",
    "sg:postcode":"27357",
    "sg:province":"NC",
    "sg:tags":[
        "cabinet",
        "carpentry",
        "contractor"
    ],
    "wof:name":"Norman A Daniel & Son Inc",
    "wof:placetype":"venue"
},
  "geometry": {"coordinates":[-79.988737,36.229129],"type":"Point"}
}