{
  "type": "Feature",
  "properties": {
    "addr:full":"506 Mare Ct Bahama NC 27503",
    "addr:housenumber":"506",
    "addr:postcode":"27503",
    "addr:street":"Mare Ct",
    "iso:country":"US",
    "sg:address":"506 Mare Ct",
    "sg:city":"Bahama",
    "sg:classifiers":[
        {
            "category":"Real Estate",
            "subcategory":"Real Estate Operator",
            "type":"Services"
        }
    ],
    "sg:phone":"+1 919 479 0223",
    "sg:postcode":"27503",
    "sg:province":"NC",
    "sg:tags":[
        "building",
        "nonresidential"
    ],
    "wof:name":"Dmg Properties LLC",
    "wof:placetype":"venue"
},
  "geometry": {"coordinates":[-78.892718,36.179364],"type":"Point"}
}