{
  "type": "Feature",
  "properties": {
    "iso:country":"US",
    "sg:address":"2810 Bragg Blvd",
    "sg:city":"Fayetteville",
    "sg:classifiers":[
        {
            "category":"Banks & Credit Unions",
            "subcategory":"Bank",
            "type":"Services"
        }
    ],
    "sg:phone":"+1 910 487 2254",
    "sg:postcode":"28303",
    "sg:province":"NC",
    "sg:tags":[
        "state",
        "commercial"
    ],
    "wof:name":"Bank Of America",
    "wof:placetype":"venue"
},
  "geometry": {"coordinates":[-78.923405,35.072319],"type":"Point"}
}