{
  "type": "Feature",
  "properties": {
    "addr:full":"7605 Rainwater Rd Raleigh NC 27615",
    "addr:housenumber":"7605",
    "addr:postcode":"27615",
    "addr:street":"Rainwater Rd",
    "iso:country":"US",
    "sg:address":"7605 Rainwater Rd",
    "sg:city":"Raleigh",
    "sg:classifiers":[
        {
            "category":"Professional",
            "subcategory":"Lawyer & Legal Services",
            "type":"Services"
        }
    ],
    "sg:phone":"+1 919 981 4468",
    "sg:postcode":"27615",
    "sg:province":"NC",
    "sg:tags":[
        "attorney"
    ],
    "wof:name":"Resnick Abraham & Schwartzman",
    "wof:placetype":"venue"
},
  "geometry": {"coordinates":[-78.604944,35.889209],"type":"Point"}
}