{
  "type": "Feature",
  "properties": {
    "iso:country":"US",
    "sg:address":"1118 W Chapel Hill St",
    "sg:city":"Durham",
    "sg:classifiers":[
        {
            "category":"Autos & Motor Vehicles",
            "subcategory":"Auto Supplies",
            "type":"Retail Goods"
        }
    ],
    "sg:phone":"+1 919 419 0339",
    "sg:postcode":"27701",
    "sg:province":"NC",
    "sg:tags":[
        "automobile",
        "stereo",
        "radio"
    ],
    "wof:name":"Affordable Auto Svc",
    "wof:placetype":"venue"
},
  "geometry": {"coordinates":[-78.917193,35.996812],"type":"Point"}
}