{
  "type": "Feature",
  "properties": {
    "addr:full":"915 Kimberly Rd Burlington NC 27215",
    "addr:housenumber":"915",
    "addr:postcode":"27215",
    "addr:street":"Kimberly Rd",
    "iso:country":"US",
    "sg:address":"915 Kimberly Rd",
    "sg:city":"Burlington",
    "sg:classifiers":[
        {
            "category":"Real Estate",
            "subcategory":"Real Estate Agent",
            "type":"Services"
        }
    ],
    "sg:phone":"+1 336 584 6146",
    "sg:postcode":"27215",
    "sg:province":"NC",
    "wof:name":"Little Bay Corporation",
    "wof:placetype":"venue"
},
  "geometry": {"coordinates":[-79.47522600000001,36.093224],"type":"Point"}
}