{
  "type": "Feature",
  "properties": {
    "iso:country":"US",
    "sg:address":"131 Dublin Square Rd",
    "sg:city":"Asheboro",
    "sg:classifiers":[
        {
            "category":"Education",
            "subcategory":"Special Training",
            "type":"Public Place"
        }
    ],
    "sg:phone":"+1 336 629 7868",
    "sg:postcode":"27203",
    "sg:province":"NC",
    "sg:tags":[
        "tutoring"
    ],
    "wof:name":"Brooks Tutoring Center",
    "wof:placetype":"venue"
},
  "geometry": {"coordinates":[-79.795374,35.704445],"type":"Point"}
}