{
  "type": "Feature",
  "properties": {
    "addr:full":"227 Market St Mount Airy NC 27030",
    "addr:housenumber":"227",
    "addr:postcode":"27030",
    "addr:street":"Market St",
    "iso:country":"US",
    "sg:address":"227 Market St",
    "sg:city":"Mount Airy",
    "sg:classifiers":[
        {
            "category":"Taxi",
            "type":"Transportation"
        }
    ],
    "sg:phone":"+1 336 786 6964",
    "sg:postcode":"27030",
    "sg:province":"NC",
    "sg:tags":[
        "taxicab"
    ],
    "wof:name":"Granite City Cab Co",
    "wof:placetype":"venue"
},
  "geometry": {"coordinates":[-80.609161,36.501068],"type":"Point"}
}