{
  "type": "Feature",
  "properties": {
    "addr:full":"3466 Hoover Hill Rd Trinity NC 27370",
    "addr:housenumber":"3466",
    "addr:postcode":"27370",
    "addr:street":"Hoover Hill Rd",
    "iso:country":"US",
    "sg:address":"3466 Hoover Hill Rd",
    "sg:city":"Trinity",
    "sg:classifiers":[
        {
            "category":"Retail",
            "subcategory":"Repair Shop",
            "type":"Services"
        }
    ],
    "sg:phone":"+1 336 861 6793",
    "sg:postcode":"27370",
    "sg:province":"NC",
    "sg:tags":[
        "scooter",
        "motorcycle",
        "motor"
    ],
    "wof:name":"D K Cycles",
    "wof:placetype":"venue"
},
  "geometry": {"coordinates":[-79.962529,35.800288],"type":"Point"}
}