{
  "type": "Feature",
  "properties": {
    "addr:full":"3017 Dixon Rd Durham NC 27707",
    "addr:housenumber":"3017",
    "addr:postcode":"27707",
    "addr:street":"Dixon Rd",
    "iso:country":"US",
    "sg:address":"3017 Dixon Rd",
    "sg:city":"Durham",
    "sg:classifiers":[
        {
            "category":"Education",
            "subcategory":"School",
            "type":"Public Place"
        }
    ],
    "sg:phone":"+1 919 493 0197",
    "sg:postcode":"27707",
    "sg:province":"NC",
    "wof:name":"Keys Learning Ctr",
    "wof:placetype":"venue"
},
  "geometry": {"coordinates":[-78.939879,35.966873],"type":"Point"}
}