{
  "type": "Feature",
  "properties": {
    "addr:full":"109 Sanderling Ct Hampstead NC 28443",
    "addr:housenumber":"109",
    "addr:postcode":"28443",
    "addr:street":"Sanderling Ct",
    "iso:country":"US",
    "sg:address":"109 Sanderling Ct",
    "sg:city":"Hampstead",
    "sg:classifiers":[
        {
            "category":"Professional",
            "subcategory":"Business Services",
            "type":"Services"
        }
    ],
    "sg:phone":"+1   ",
    "sg:postcode":"28443",
    "sg:province":"NC",
    "wof:name":"Obannon Enterprises Ltd",
    "wof:placetype":"venue"
},
  "geometry": {"coordinates":[-77.609897,34.426876],"type":"Point"}
}