{
  "type": "Feature",
  "properties": {
    "addr:full":"1417 Market St Wilmington NC 28401",
    "addr:housenumber":"1417",
    "addr:postcode":"28401",
    "addr:street":"Market St",
    "iso:country":"US",
    "sg:address":"1417 Market St",
    "sg:city":"Wilmington",
    "sg:classifiers":[
        {
            "category":"Travel",
            "subcategory":"Hotels & Motels",
            "type":"Entertainment"
        }
    ],
    "sg:phone":"+1   ",
    "sg:postcode":"28401",
    "sg:province":"NC",
    "sg:tags":[
        "operation"
    ],
    "wof:name":"Bellamy Bed & Breakfast",
    "wof:placetype":"venue"
},
  "geometry": {"coordinates":[-77.93041700000001,34.23695],"type":"Point"}
}