{
  "type": "Feature",
  "properties": {
    "addr:full":"217 Sawmill Rd Raleigh NC 27615",
    "addr:housenumber":"217",
    "addr:postcode":"27615",
    "addr:street":"Sawmill Rd",
    "iso:country":"US",
    "sg:address":"217 Sawmill Rd",
    "sg:city":"Raleigh",
    "sg:classifiers":[
        {
            "category":"Arts & Performance",
            "subcategory":"Theater",
            "type":"Entertainment"
        }
    ],
    "sg:phone":"+1   ",
    "sg:postcode":"27615",
    "sg:province":"NC",
    "sg:tags":[
        "company"
    ],
    "wof:name":"Infinyte Entertainment",
    "wof:placetype":"venue"
},
  "geometry": {"coordinates":[-78.649365,35.881925],"type":"Point"}
}