{
  "type": "Feature",
  "properties": {
    "iso:country":"US",
    "sg:address":"117 Newbern Rd",
    "sg:city":"Jarvisburg",
    "sg:classifiers":[
        {
            "category":"Building & Trades",
            "subcategory":"Landscaping Services",
            "type":"Services"
        }
    ],
    "sg:phone":"+1 252 491 4200",
    "sg:postcode":"27947",
    "sg:province":"NC",
    "sg:tags":[
        "tree"
    ],
    "wof:name":"Starchers Tree & Svc Co",
    "wof:placetype":"venue"
},
  "geometry": {"coordinates":[-75.83985300000001,36.168508],"type":"Point"}
}