{
  "type": "Feature",
  "properties": {
    "addr:full":"1111 Churchill Dr Gastonia NC 28054",
    "addr:housenumber":"1111",
    "addr:postcode":"28054",
    "addr:street":"Churchill Dr",
    "iso:country":"US",
    "sg:address":"1111 Churchill Dr",
    "sg:city":"Gastonia",
    "sg:classifiers":[
        {
            "category":"Shopping",
            "subcategory":"Music",
            "type":"Retail Goods"
        }
    ],
    "sg:phone":"+1 704 864 0909",
    "sg:postcode":"28054",
    "sg:province":"NC",
    "wof:name":"T&T Records Inc",
    "wof:placetype":"venue"
},
  "geometry": {"coordinates":[-81.15853300000001,35.24806],"type":"Point"}
}