{
  "type": "Feature",
  "properties": {
    "addr:full":"701 W Grantham St Goldsboro NC 27530",
    "addr:housenumber":"701",
    "addr:postcode":"27530",
    "addr:street":"W Grantham St",
    "iso:country":"US",
    "sg:address":"701 W Grantham St",
    "sg:city":"Goldsboro",
    "sg:classifiers":[
        {
            "category":"Government",
            "subcategory":"Office",
            "type":"Public Place"
        }
    ],
    "sg:phone":"+1 919 731 7964",
    "sg:postcode":"27530",
    "sg:province":"NC",
    "sg:tags":[
        "state",
        "program"
    ],
    "wof:name":"Motor Vehicles Dept Office",
    "wof:placetype":"venue"
},
  "geometry": {"coordinates":[-78.000651,35.398564],"type":"Point"}
}