{
  "type": "Feature",
  "properties": {
    "iso:country":"US",
    "sg:address":"2225 Township Rd",
    "sg:city":"Charlotte",
    "sg:classifiers":[
        {
            "category":"Retail",
            "subcategory":"Veterinary Services",
            "type":"Services"
        }
    ],
    "sg:phone":"+1 704 588 7015",
    "sg:postcode":"28273",
    "sg:province":"NC",
    "sg:tags":[
        "veterinarian",
        "specialty",
        "emergency"
    ],
    "sg:website":"http://www.carolinavet.com",
    "wof:name":"Carolina Veterinary Specialists",
    "wof:placetype":"venue"
},
  "geometry": {"coordinates":[-80.940669,35.132291],"type":"Point"}
}