{
  "type": "Feature",
  "properties": {
    "iso:country":"US",
    "sg:address":"100 Timber Hollow Ct",
    "sg:city":"Chapel Hill",
    "sg:classifiers":[
        {
            "category":"Building & Trades",
            "subcategory":"Construction",
            "type":"Services"
        }
    ],
    "sg:phone":"+1 919 933 7618",
    "sg:postcode":"27514",
    "sg:province":"NC",
    "sg:tags":[
        "residential"
    ],
    "wof:name":"David Griffin Construction",
    "wof:placetype":"venue"
},
  "geometry": {"coordinates":[-79.057406,35.941606],"type":"Point"}
}