{
  "type": "Feature",
  "properties": {
    "addr:full":"269 Gospel Cir Hayesville NC 28904",
    "addr:housenumber":"269",
    "addr:postcode":"28904",
    "addr:street":"Gospel Cir",
    "iso:country":"US",
    "sg:address":"269 Gospel Cir",
    "sg:city":"Hayesville",
    "sg:classifiers":[
        {
            "category":"Building & Trades",
            "subcategory":"Landscaping Services",
            "type":"Services"
        }
    ],
    "sg:phone":"+1 828 389 6455",
    "sg:postcode":"28904",
    "sg:province":"NC",
    "sg:tags":[
        "tree"
    ],
    "wof:name":"Pierce's Tree Svc",
    "wof:placetype":"venue"
},
  "geometry": {"coordinates":[-83.823475,35.020237],"type":"Point"}
}