{
  "type": "Feature",
  "properties": {
    "iso:country":"US",
    "sg:address":"995 Old Tomotla Rd",
    "sg:city":"Marble",
    "sg:classifiers":[
        {
            "category":"Organizations",
            "subcategory":"Labor Organization",
            "type":"Services"
        }
    ],
    "sg:phone":"+1 828 837 8934",
    "sg:postcode":"28905",
    "sg:province":"NC",
    "wof:name":"US Dept of Transportation",
    "wof:placetype":"venue"
},
  "geometry": {"coordinates":[-83.991203,35.13169],"type":"Point"}
}