{
  "type": "Feature",
  "properties": {
    "iso:country":"US",
    "sg:address":"11401 Turn Stone Ct",
    "sg:city":"Charlotte",
    "sg:classifiers":[
        {
            "category":"Real Estate",
            "subcategory":"Real Estate Operator",
            "type":"Services"
        }
    ],
    "sg:phone":"+1 704 542 8231",
    "sg:postcode":"28226",
    "sg:province":"NC",
    "sg:tags":[
        "condominium"
    ],
    "wof:name":"Carmel Chace Condo",
    "wof:placetype":"venue"
},
  "geometry": {"coordinates":[-80.84695000000001,35.07995],"type":"Point"}
}