{
  "type": "Feature",
  "properties": {
    "iso:country":"US",
    "sg:address":"1215 Hillsborough St",
    "sg:city":"Raleigh",
    "sg:classifiers":[
        {
            "category":"Shopping",
            "type":"Retail Goods"
        }
    ],
    "sg:phone":"+1 919 834 8055",
    "sg:postcode":"27603",
    "sg:province":"NC",
    "sg:tags":[
        "art",
        "gallery",
        "dealer"
    ],
    "wof:name":"Tattoo Devil Studios",
    "wof:placetype":"venue"
},
  "geometry": {"coordinates":[-78.655688,35.782877],"type":"Point"}
}