{
  "type": "Feature",
  "properties": {
    "iso:country":"US",
    "sg:address":"3376 Zacks Mill Rd",
    "sg:city":"Angier",
    "sg:classifiers":[
        {
            "category":"Building & Trades",
            "subcategory":"Electrical",
            "type":"Services"
        }
    ],
    "sg:phone":"+1 919 894 3907",
    "sg:postcode":"27501",
    "sg:province":"NC",
    "sg:tags":[
        "electrical",
        "contractor"
    ],
    "wof:name":"RST Electric",
    "wof:placetype":"venue"
},
  "geometry": {"coordinates":[-78.58402100000001,35.475946],"type":"Point"}
}