{
  "type": "Feature",
  "properties": {
    "addr:full":"4202 Barringer Dr Charlotte NC 28217",
    "addr:housenumber":"4202",
    "addr:postcode":"28217",
    "addr:street":"Barringer Dr",
    "iso:country":"US",
    "sg:address":"4202 Barringer Dr",
    "sg:city":"Charlotte",
    "sg:classifiers":[
        {
            "category":"Arts & Performance",
            "subcategory":"Theater",
            "type":"Entertainment"
        }
    ],
    "sg:phone":"+1 704 676 4995",
    "sg:postcode":"28217",
    "sg:province":"NC",
    "sg:tags":[
        "television",
        "program",
        "producer"
    ],
    "wof:name":"Maverick Entertainment",
    "wof:placetype":"venue"
},
  "geometry": {"coordinates":[-80.89312700000001,35.192857],"type":"Point"}
}