{
  "type": "Feature",
  "properties": {
    "iso:country":"US",
    "sg:address":"407 Woodland Blvd",
    "sg:city":"Wilkesboro",
    "sg:classifiers":[
        {
            "category":"Travel",
            "subcategory":"Hotels & Motels",
            "type":"Entertainment"
        },
        {
            "category":"Travel",
            "subcategory":"Bed & Breakfast",
            "type":"Entertainment"
        }
    ],
    "sg:phone":"+1 336 667 7282",
    "sg:postcode":"28697",
    "sg:province":"NC",
    "sg:tags":[
        "inn",
        "lodging"
    ],
    "sg:website":"http://www.graystonemanorbandb.com",
    "wof:name":"Graystone Manor B & B",
    "wof:placetype":"venue"
},
  "geometry": {"coordinates":[-81.158699,36.148571],"type":"Point"}
}