{
  "type": "Feature",
  "properties": {
    "iso:country":"US",
    "sg:address":"13895 State Hwy 96",
    "sg:city":"Zebulon",
    "sg:classifiers":[
        {
            "category":"Building & Trades",
            "subcategory":"Landscaping Services",
            "type":"Services"
        }
    ],
    "sg:phone":"+1 919 366 0195",
    "sg:postcode":"27597",
    "sg:province":"NC",
    "wof:name":"Hoods Lawn Care & Landscaping",
    "wof:placetype":"venue"
},
  "geometry": {"coordinates":[-78.295922,35.737443],"type":"Point"}
}