{
  "type": "Feature",
  "properties": {
    "iso:country":"US",
    "sg:address":"4304 Market St",
    "sg:city":"Wilmington",
    "sg:classifiers":[
        {
            "category":"Wholesale",
            "subcategory":"Computers",
            "type":"Manufacturing & Wholesale Goods"
        }
    ],
    "sg:phone":"+1 910 763 8400",
    "sg:postcode":"28403",
    "sg:province":"NC",
    "sg:tags":[
        "peripheral"
    ],
    "sg:website":"www.wiltec.com",
    "wof:name":"Wiltec Inc",
    "wof:placetype":"venue"
},
  "geometry": {"coordinates":[-77.89087600000001,34.242488],"type":"Point"}
}