{
  "type": "Feature",
  "properties": {
    "addr:full":"1350 S Main St Wake Forest NC 27587",
    "addr:housenumber":"1350",
    "addr:postcode":"27587",
    "addr:street":"S Main St",
    "iso:country":"US",
    "sg:address":"1350 S Main St",
    "sg:city":"Wake Forest",
    "sg:classifiers":[
        {
            "category":"Organizations",
            "subcategory":"Religious Organization",
            "type":"Services"
        }
    ],
    "sg:phone":"+1 919 556 2067",
    "sg:postcode":"27587",
    "sg:province":"NC",
    "sg:tags":[
        "church"
    ],
    "wof:name":"Forestville Baptist Church",
    "wof:placetype":"venue"
},
  "geometry": {"coordinates":[-78.520143,35.959882],"type":"Point"}
}