{
  "type": "Feature",
  "properties": {
    "iso:country":"US",
    "sg:address":"4709 Tuckaseegee Rd",
    "sg:city":"Charlotte",
    "sg:classifiers":[
        {
            "category":"Food & Beverages",
            "subcategory":"Groceries & Convenience Stores",
            "type":"Retail Goods"
        }
    ],
    "sg:phone":"+1 704 393 1293",
    "sg:postcode":"28208",
    "sg:province":"NC",
    "sg:tags":[
        "grocer"
    ],
    "wof:name":"LA Acapulquena",
    "wof:placetype":"venue"
},
  "geometry": {"coordinates":[-80.901931,35.246642],"type":"Point"}
}