{
  "type": "Feature",
  "properties": {
    "iso:country":"US",
    "sg:address":"622 Clyde St",
    "sg:city":"Gastonia",
    "sg:classifiers":[
        {
            "category":"Professional",
            "subcategory":"Business Services",
            "type":"Services"
        }
    ],
    "sg:phone":"+1 704 865 4498",
    "sg:postcode":"28052",
    "sg:province":"NC",
    "sg:tags":[
        "mfg"
    ],
    "wof:name":"Masons Bar Turning Machine Sp",
    "wof:placetype":"venue"
},
  "geometry": {"coordinates":[-81.200362,35.235026],"type":"Point"}
}