{
  "type": "Feature",
  "properties": {
    "iso:country":"US",
    "sg:address":"315 Vinson Blvd",
    "sg:city":"Whiteville",
    "sg:classifiers":[
        {
            "category":"Shopping",
            "subcategory":"Used Merchandise",
            "type":"Retail Goods"
        }
    ],
    "sg:phone":"+1 910 640 2213",
    "sg:postcode":"28472",
    "sg:province":"NC",
    "sg:tags":[
        "shop",
        "thrift"
    ],
    "wof:name":"130 Thrift Shop",
    "wof:placetype":"venue"
},
  "geometry": {"coordinates":[-78.70722600000001,34.295166],"type":"Point"}
}