{
  "type": "Feature",
  "properties": {
    "iso:country":"US",
    "sg:address":"8536 Plimoth Hill Dr",
    "sg:city":"Wake Forest",
    "sg:classifiers":[
        {
            "category":"Building & Trades",
            "subcategory":"Construction",
            "type":"Services"
        }
    ],
    "sg:phone":"+1 919 556 9901",
    "sg:postcode":"27587",
    "sg:province":"NC",
    "sg:tags":[
        "roofing",
        "contractor"
    ],
    "wof:name":"State Roofing & Repair Contr",
    "wof:placetype":"venue"
},
  "geometry": {"coordinates":[-78.531408,35.912322],"type":"Point"}
}