{
  "type": "Feature",
  "properties": {
    "iso:country":"US",
    "sg:address":"100 Pub Works Dr",
    "sg:city":"Carrboro",
    "sg:classifiers":[
        {
            "category":"Government",
            "subcategory":"Office",
            "type":"Public Place"
        }
    ],
    "sg:phone":"+1 919 918 7431",
    "sg:postcode":"27516",
    "sg:province":"NC",
    "sg:tags":[
        "village"
    ],
    "wof:name":"Carrboro Landscaping & Grounds",
    "wof:placetype":"venue"
},
  "geometry": {"coordinates":[-79.07441300000001,35.900503],"type":"Point"}
}