{
  "type": "Feature",
  "properties": {
    "addr:full":"96 Green Dr Waynesville NC 28785",
    "addr:housenumber":"96",
    "addr:postcode":"28785",
    "addr:street":"Green Dr",
    "iso:country":"US",
    "sg:address":"96 Green Dr",
    "sg:city":"Waynesville",
    "sg:classifiers":[
        {
            "category":"Building & Trades",
            "subcategory":"Construction",
            "type":"Services"
        }
    ],
    "sg:phone":"+1 828 926 6325",
    "sg:postcode":"28785",
    "sg:province":"NC",
    "sg:tags":[
        "excavation",
        "contractor"
    ],
    "wof:name":"Jerry Trull Excavating & Pav",
    "wof:placetype":"venue"
},
  "geometry": {"coordinates":[-82.996934,35.531257],"type":"Point"}
}