{
  "type": "Feature",
  "properties": {
    "iso:country":"US",
    "sg:address":"4823 Old Rural Hall Rd",
    "sg:city":"Winston Salem",
    "sg:classifiers":[
        {
            "category":"Organizations",
            "subcategory":"Religious Organization",
            "type":"Services"
        }
    ],
    "sg:phone":"+1 336 767 6576",
    "sg:postcode":"27105",
    "sg:province":"NC",
    "sg:tags":[
        "church"
    ],
    "wof:name":"Joy Temple Holiness Apostle",
    "wof:placetype":"venue"
},
  "geometry": {"coordinates":[-80.22681799999999,36.156048],"type":"Point"}
}