{
  "type": "Feature",
  "properties": {
    "addr:full":"10033 Brief Rd Charlotte NC 28227",
    "addr:postcode":"10033;28227",
    "addr:street":"Brief Rd",
    "iso:country":"US",
    "sg:address":"10033 Brief Rd",
    "sg:city":"Charlotte",
    "sg:classifiers":[
        {
            "category":"Professional",
            "subcategory":"Business Services",
            "type":"Services"
        }
    ],
    "sg:phone":"+1   ",
    "sg:postcode":"28227",
    "sg:province":"NC",
    "wof:name":"Tri-County Inspection",
    "wof:placetype":"venue"
},
  "geometry": {"coordinates":[-80.595473,35.188924],"type":"Point"}
}