{
  "type": "Feature",
  "properties": {
    "iso:country":"US",
    "sg:address":"7717 Elevation Rd",
    "sg:city":"Benson",
    "sg:classifiers":[
        {
            "category":"Building & Trades",
            "subcategory":"Construction",
            "type":"Services"
        }
    ],
    "sg:phone":"+1 919 894 4491",
    "sg:postcode":"27504",
    "sg:province":"NC",
    "sg:tags":[
        "resurfacing",
        "laying",
        "refinishing",
        "floor"
    ],
    "wof:name":"Mc Lamb's Flooring Co",
    "wof:placetype":"venue"
},
  "geometry": {"coordinates":[-78.585723,35.456188],"type":"Point"}
}