{
  "type": "Feature",
  "properties": {
    "iso:country":"US",
    "sg:address":"595 W 5th St",
    "sg:city":"Lumberton",
    "sg:classifiers":[
        {
            "category":"Retail",
            "subcategory":"Car Wash",
            "type":"Services"
        }
    ],
    "sg:phone":"+1 910 738 2288",
    "sg:postcode":"28358",
    "sg:province":"NC",
    "sg:tags":[
        "polishing",
        "washing"
    ],
    "wof:name":"On Point Car Wash",
    "wof:placetype":"venue"
},
  "geometry": {"coordinates":[-79.01606200000001,34.620842],"type":"Point"}
}