{
  "type": "Feature",
  "properties": {
    "iso:country":"US",
    "sg:address":"249 Holden Rd",
    "sg:city":"Youngsville",
    "sg:classifiers":[
        {
            "category":"Organizations",
            "subcategory":"Religious Organization",
            "type":"Services"
        }
    ],
    "sg:phone":"+1 919 556 3420",
    "sg:postcode":"27596",
    "sg:province":"NC",
    "sg:tags":[
        "church"
    ],
    "wof:name":"Faith Baptist Church Inc",
    "wof:placetype":"venue"
},
  "geometry": {"coordinates":[-78.50652100000001,36.025414],"type":"Point"}
}