{
  "type": "Feature",
  "properties": {
    "addr:full":"10 Catalpa Ln N Pinehurst NC 28374",
    "addr:housenumber":"10",
    "addr:postcode":"28374",
    "addr:street":"Catalpa Ln N",
    "iso:country":"US",
    "sg:address":"10 Catalpa Ln N",
    "sg:city":"Pinehurst",
    "sg:classifiers":[
        {
            "category":"Wholesale",
            "subcategory":"Sporting Goods",
            "type":"Manufacturing & Wholesale Goods"
        }
    ],
    "sg:phone":"+1 910 295 6533",
    "sg:postcode":"28374",
    "sg:province":"NC",
    "wof:name":"R E B Golf",
    "wof:placetype":"venue"
},
  "geometry": {"coordinates":[-79.49381099999999,35.182354],"type":"Point"}
}