{
  "type": "Feature",
  "properties": {
    "iso:country":"US",
    "sg:address":"115 ABC Ct NE",
    "sg:city":"Lenoir",
    "sg:classifiers":[
        {
            "category":"Food & Beverages",
            "subcategory":"Liquor & Beverages",
            "type":"Retail Goods"
        }
    ],
    "sg:phone":"+1 828 754 6820",
    "sg:postcode":"28645",
    "sg:province":"NC",
    "wof:name":"Lenoir ABC Store",
    "wof:placetype":"venue"
},
  "geometry": {"coordinates":[-81.52328300000001,35.915544],"type":"Point"}
}