{
  "type": "Feature",
  "properties": {
    "iso:country":"US",
    "sg:address":"2948 Carolyn Dr",
    "sg:city":"Durham",
    "sg:classifiers":[
        {
            "category":"Building & Trades",
            "subcategory":"Construction",
            "type":"Services"
        }
    ],
    "sg:phone":"+1 919 596 6800",
    "sg:postcode":"27703",
    "sg:province":"NC",
    "sg:tags":[
        "hanging",
        "painter",
        "contractor"
    ],
    "wof:name":"Moore's Paint & Decorating",
    "wof:placetype":"venue"
},
  "geometry": {"coordinates":[-78.84925699999999,35.978526],"type":"Point"}
}