{
  "type": "Feature",
  "properties": {
    "addr:full":"112 Butler St Morganton NC 28655",
    "addr:housenumber":"112",
    "addr:postcode":"28655",
    "addr:street":"Butler St",
    "iso:country":"US",
    "sg:address":"112 Butler St",
    "sg:city":"Morganton",
    "sg:classifiers":[
        {
            "category":"Shopping",
            "subcategory":"Florist",
            "type":"Retail Goods"
        }
    ],
    "sg:phone":"+1 828 438 3633",
    "sg:postcode":"28655",
    "sg:province":"NC",
    "wof:name":"Jimis Creations",
    "wof:placetype":"venue"
},
  "geometry": {"coordinates":[-81.673708,35.755583],"type":"Point"}
}