{
  "type": "Feature",
  "properties": {
    "iso:country":"US",
    "sg:address":"750 Haywood Road",
    "sg:city":"Asheville",
    "sg:classifiers":[
        {
            "category":"Social Services",
            "subcategory":"Child Care",
            "type":"Services"
        }
    ],
    "sg:phone":"+1 828 255 0266",
    "sg:postcode":"28806",
    "sg:province":"NC",
    "sg:tags":[
        "day"
    ],
    "sg:website":"www.bgca.org",
    "wof:name":"Salvation Army Boys & Girls Club",
    "wof:placetype":"venue"
},
  "geometry": {"coordinates":[-82.593407,35.577977],"type":"Point"}
}