{
  "type": "Feature",
  "properties": {
    "iso:country":"US",
    "sg:address":"7619 Old Statesville Rd",
    "sg:city":"Charlotte",
    "sg:classifiers":[
        {
            "category":"Retail",
            "subcategory":"Auto Repair",
            "type":"Services"
        }
    ],
    "sg:phone":"+1 704 596 6394",
    "sg:postcode":"28269",
    "sg:province":"NC",
    "sg:tags":[
        "repairing",
        "automobile"
    ],
    "wof:name":"DLB Transmissions & Auto",
    "wof:placetype":"venue"
},
  "geometry": {"coordinates":[-80.826786,35.325882],"type":"Point"}
}