{
  "type": "Feature",
  "properties": {
    "iso:country":"US",
    "sg:address":"106 Ballatore Ct",
    "sg:city":"Cary",
    "sg:classifiers":[
        {
            "category":"Professional",
            "subcategory":"Management & Consulting",
            "type":"Services"
        }
    ],
    "sg:phone":"+1 919 460 6938",
    "sg:postcode":"27519",
    "sg:province":"NC",
    "sg:tags":[
        "marketing",
        "consultant"
    ],
    "wof:name":"Strategic Guru",
    "wof:placetype":"venue"
},
  "geometry": {"coordinates":[-78.880966,35.798],"type":"Point"}
}