{
  "type": "Feature",
  "properties": {
    "addr:full":"602 S Garnett St Henderson NC 27536",
    "addr:housenumber":"602",
    "addr:postcode":"27536",
    "addr:street":"S Garnett St",
    "iso:country":"US",
    "sg:address":"602 S Garnett St",
    "sg:city":"Henderson",
    "sg:classifiers":[
        {
            "category":"Social Services",
            "subcategory":"Adult Care",
            "type":"Services"
        }
    ],
    "sg:phone":"+1 252 492 9555",
    "sg:postcode":"27536",
    "sg:province":"NC",
    "sg:tags":[
        "residential",
        "job",
        "t"
    ],
    "wof:name":"Area Mental Health Program Inc",
    "wof:placetype":"venue"
},
  "geometry": {"coordinates":[-78.407144,36.32427],"type":"Point"}
}