{
  "type": "Feature",
  "properties": {
    "addr:full":"127 Church Cir Haw River NC 27258",
    "addr:housenumber":"127",
    "addr:postcode":"27258",
    "addr:street":"Church Cir",
    "iso:country":"US",
    "sg:address":"127 Church Cir",
    "sg:city":"Haw River",
    "sg:classifiers":[
        {
            "category":"Organizations",
            "subcategory":"Religious Organization",
            "type":"Services"
        }
    ],
    "sg:phone":"+1 336 578 0611",
    "sg:postcode":"27258",
    "sg:province":"NC",
    "sg:tags":[
        "church"
    ],
    "sg:website":"www.hawriverunitedmeth.ypgs.net",
    "wof:name":"Haw River United Methodist Chr",
    "wof:placetype":"venue"
},
  "geometry": {"coordinates":[-79.37288599999999,36.088542],"type":"Point"}
}