{
  "type": "Feature",
  "properties": {
    "iso:country":"US",
    "sg:address":"211 Elwood Ln",
    "sg:city":"Wallace",
    "sg:classifiers":[
        {
            "category":"Farming",
            "subcategory":"Livestock Farm",
            "type":"Manufacturing & Wholesale Goods"
        }
    ],
    "sg:phone":"+1 910 285 3946",
    "sg:postcode":"28466",
    "sg:province":"NC",
    "sg:tags":[
        "feedlot",
        "cattle",
        "crop",
        "beef",
        "general"
    ],
    "wof:name":"Elwood Casteen",
    "wof:placetype":"venue"
},
  "geometry": {"coordinates":[-77.76561,34.730496],"type":"Point"}
}