{
  "type": "Feature",
  "properties": {
    "iso:country":"US",
    "sg:address":"337 Airport Rd",
    "sg:city":"Wadesboro",
    "sg:classifiers":[
        {
            "category":"Social Services",
            "subcategory":"Child Care",
            "type":"Services"
        }
    ],
    "sg:phone":"+1   ",
    "sg:postcode":"28147",
    "sg:province":"NC",
    "sg:tags":[
        "day"
    ],
    "wof:name":"Kids World Day Care",
    "wof:placetype":"venue"
},
  "geometry": {"coordinates":[-80.563677,35.654134],"type":"Point"}
}