{
  "type": "Feature",
  "properties": {
    "addr:full":"6132 Carolina Beach Rd Wilmington NC 28412",
    "addr:housenumber":"6132",
    "addr:postcode":"28412",
    "addr:street":"Carolina Beach Rd",
    "iso:country":"US",
    "sg:address":"6132 Carolina Beach Rd",
    "sg:city":"Wilmington",
    "sg:classifiers":[
        {
            "category":"Building & Trades",
            "subcategory":"Construction",
            "type":"Services"
        },
        {
            "category":"Home & Garden",
            "subcategory":"Carpets & Floor Coverings",
            "type":"Retail Goods"
        }
    ],
    "sg:phone":"+1 910 799 9949",
    "sg:postcode":"28412",
    "sg:province":"NC",
    "sg:tags":[
        "dealer",
        "installation",
        "rug",
        "sales"
    ],
    "wof:name":"Coastline Carpets Inc",
    "wof:placetype":"venue"
},
  "geometry": {"coordinates":[-77.900841,34.115885],"type":"Point"}
}