{
  "type": "Feature",
  "properties": {
    "iso:country":"US",
    "sg:address":"3210 State Hwy 87",
    "sg:city":"Sanford",
    "sg:classifiers":[
        {
            "category":"Restaurant",
            "type":"Food & Drink"
        }
    ],
    "sg:phone":"+1 919 776 0292",
    "sg:postcode":"27330",
    "sg:province":"NC",
    "sg:website":"www.rubytuesday.com",
    "wof:name":"Ruby Tuesday",
    "wof:placetype":"venue"
},
  "geometry": {"coordinates":[-79.185968,35.52979],"type":"Point"}
}