{
  "type": "Feature",
  "properties": {
    "addr:full":"205 Pats Rd Vass NC 28394",
    "addr:housenumber":"205",
    "addr:postcode":"28394",
    "addr:street":"Pats Rd",
    "iso:country":"US",
    "sg:address":"205 Pats Rd",
    "sg:city":"Vass",
    "sg:classifiers":[
        {
            "category":"Retail",
            "subcategory":"Repair Shop",
            "type":"Services"
        }
    ],
    "sg:phone":"+1 910 245 4883",
    "sg:postcode":"28394",
    "sg:province":"NC",
    "sg:tags":[
        "repairing",
        "lawn",
        "mower"
    ],
    "wof:name":"Kelly's Small Engine Repair",
    "wof:placetype":"venue"
},
  "geometry": {"coordinates":[-79.235748,35.237579],"type":"Point"}
}