{
  "type": "Feature",
  "properties": {
    "addr:full":"125 State Hwy 102 W Ayden NC 28513",
    "addr:housenumber":"125",
    "addr:postcode":"28513",
    "addr:street":"State Hwy 102 W",
    "iso:country":"US",
    "sg:address":"125 State Hwy 102 W",
    "sg:city":"Ayden",
    "sg:classifiers":[
        {
            "category":"Food & Beverages",
            "subcategory":"Groceries & Convenience Stores",
            "type":"Retail Goods"
        }
    ],
    "sg:phone":"+1 252 746 9144",
    "sg:postcode":"28513",
    "sg:province":"NC",
    "wof:name":"Handy Mart",
    "wof:placetype":"venue"
},
  "geometry": {"coordinates":[-77.43580799999999,35.475607],"type":"Point"}
}