{
  "type": "Feature",
  "properties": {
    "addr:full":"110 W Academy St Madison NC 27025",
    "addr:housenumber":"110",
    "addr:postcode":"27025",
    "addr:street":"W Academy St",
    "iso:country":"US",
    "sg:address":"110 W Academy St",
    "sg:city":"Madison",
    "sg:classifiers":[
        {
            "category":"Organizations",
            "subcategory":"Religious Organization",
            "type":"Services"
        }
    ],
    "sg:phone":"+1 336 548 6658",
    "sg:postcode":"27025",
    "sg:province":"NC",
    "sg:tags":[
        "church"
    ],
    "wof:name":"Madison United Methodist Chr",
    "wof:placetype":"venue"
},
  "geometry": {"coordinates":[-79.96163,36.385329],"type":"Point"}
}