{
  "type": "Feature",
  "properties": {
    "iso:country":"US",
    "sg:address":"1202 Chestnut St",
    "sg:city":"Wilmington",
    "sg:classifiers":[
        {
            "category":"Food & Beverages",
            "subcategory":"Groceries & Convenience Stores",
            "type":"Retail Goods"
        }
    ],
    "sg:phone":"+1 910 762 8718",
    "sg:postcode":"28401",
    "sg:province":"NC",
    "sg:tags":[
        "grocer"
    ],
    "wof:name":"Chestnut Food Market",
    "wof:placetype":"venue"
},
  "geometry": {"coordinates":[-77.933756,34.238706],"type":"Point"}
}