{
  "type": "Feature",
  "properties": {
    "addr:full":"211 N Road St Elizabeth City NC 27909",
    "addr:housenumber":"211",
    "addr:postcode":"27909",
    "addr:street":"N Road St",
    "iso:country":"US",
    "sg:address":"211 N Road St",
    "sg:city":"Elizabeth City",
    "sg:classifiers":[
        {
            "category":"Real Estate",
            "subcategory":"Real Estate Agent",
            "type":"Services"
        }
    ],
    "sg:phone":"+1 252 338 5459",
    "sg:postcode":"27909",
    "sg:province":"NC",
    "wof:name":"First Choice Real Estate",
    "wof:placetype":"venue"
},
  "geometry": {"coordinates":[-76.22336900000001,36.302053],"type":"Point"}
}