{
  "type": "Feature",
  "properties": {
    "iso:country":"US",
    "sg:address":"503 Quail Ln",
    "sg:city":"Kill Devil Hills",
    "sg:classifiers":[
        {
            "category":"Real Estate",
            "subcategory":"Real Estate Agent",
            "type":"Services"
        }
    ],
    "sg:phone":"+1 252 441 9007",
    "sg:postcode":"27948",
    "sg:province":"NC",
    "wof:name":"Doug Duval Real Estate Svc",
    "wof:placetype":"venue"
},
  "geometry": {"coordinates":[-75.661237,35.99421],"type":"Point"}
}