{
  "type": "Feature",
  "properties": {
    "iso:country":"US",
    "sg:address":"13382 Cleveland Rd",
    "sg:city":"Garner",
    "sg:classifiers":[
        {
            "category":"Building & Trades",
            "subcategory":"Construction",
            "type":"Services"
        }
    ],
    "sg:phone":"+1 919 772 3218",
    "sg:postcode":"27529",
    "sg:province":"NC",
    "sg:tags":[
        "house"
    ],
    "wof:name":"Down Home Construction LLC",
    "wof:placetype":"venue"
},
  "geometry": {"coordinates":[-78.584749,35.611185],"type":"Point"}
}