{
  "type": "Feature",
  "properties": {
    "addr:full":"28 Katherine Pl Asheville NC 28801",
    "addr:housenumber":"28",
    "addr:postcode":"28801",
    "addr:street":"Katherine Pl",
    "iso:country":"US",
    "sg:address":"28 Katherine Pl",
    "sg:city":"Asheville",
    "sg:classifiers":[
        {
            "category":"Home & Garden",
            "subcategory":"Carpets & Floor Coverings",
            "type":"Retail Goods"
        }
    ],
    "sg:phone":"+1 828 255 9753",
    "sg:postcode":"28801",
    "sg:province":"NC",
    "wof:name":"Natural Floor",
    "wof:placetype":"venue"
},
  "geometry": {"coordinates":[-82.54886500000001,35.6121],"type":"Point"}
}