{
  "type": "Feature",
  "properties": {
    "iso:country":"US",
    "sg:address":"3200 Atlantic Ave",
    "sg:city":"Raleigh",
    "sg:classifiers":[
        {
            "category":"Wholesale",
            "subcategory":"Stationery",
            "type":"Manufacturing & Wholesale Goods"
        }
    ],
    "sg:phone":"+1 919 876 0343",
    "sg:postcode":"27604",
    "sg:province":"NC",
    "sg:tags":[
        "business",
        "form",
        "system"
    ],
    "sg:website":"www.rrdonnelley.com",
    "wof:name":"Moore Wallace Inc",
    "wof:placetype":"venue"
},
  "geometry": {"coordinates":[-78.603548,35.829157],"type":"Point"}
}