{
  "type": "Feature",
  "properties": {
    "iso:country":"US",
    "sg:address":"324 Ridgefield Ct",
    "sg:city":"Asheville",
    "sg:classifiers":[
        {
            "category":"Education",
            "subcategory":"Vocational School",
            "type":"Public Place"
        }
    ],
    "sg:phone":"+1 828 252 8888",
    "sg:postcode":"28806",
    "sg:province":"NC",
    "sg:tags":[
        "training",
        "computer"
    ],
    "sg:website":"www.softraininc.com",
    "wof:name":"Softrain",
    "wof:placetype":"venue"
},
  "geometry": {"coordinates":[-82.599013,35.524108],"type":"Point"}
}