{
  "type": "Feature",
  "properties": {
    "addr:full":"7837 Fairfield Forest Rd Denver NC 28037",
    "addr:housenumber":"7837",
    "addr:postcode":"28037",
    "addr:street":"Fairfield Forest Rd",
    "iso:country":"US",
    "sg:address":"7837 Fairfield Forest Rd",
    "sg:city":"Denver",
    "sg:classifiers":[
        {
            "category":"Education",
            "subcategory":"Library",
            "type":"Public Place"
        }
    ],
    "sg:phone":"+1   ",
    "sg:postcode":"28037",
    "sg:province":"NC",
    "wof:name":"Gaston Lncoln Regional Lib Sys",
    "wof:placetype":"venue"
},
  "geometry": {"coordinates":[-80.989913,35.506103],"type":"Point"}
}