{
  "type": "Feature",
  "properties": {
    "addr:full":"2451 N Wesleyan Blvd Rocky Mount NC 27804",
    "addr:housenumber":"2451",
    "addr:postcode":"27804",
    "addr:street":"N Wesleyan Blvd",
    "iso:country":"US",
    "sg:address":"2451 N Wesleyan Blvd",
    "sg:city":"Rocky Mount",
    "sg:classifiers":[
        {
            "category":"Shopping",
            "subcategory":"Hobbies, Toys, & Games",
            "type":"Retail Goods"
        }
    ],
    "sg:phone":"+1 252 442 3340",
    "sg:postcode":"27804",
    "sg:province":"NC",
    "sg:tags":[
        "equipment",
        "video",
        "rental"
    ],
    "wof:name":"Bailey Music Co",
    "wof:placetype":"venue"
},
  "geometry": {"coordinates":[-77.77775,35.996532],"type":"Point"}
}