{
  "type": "Feature",
  "properties": {
    "iso:country":"US",
    "sg:address":"104 Goldsboro St SW",
    "sg:city":"Wilson",
    "sg:classifiers":[
        {
            "category":"Government",
            "subcategory":"Office",
            "type":"Public Place"
        }
    ],
    "sg:phone":"+1 252 399 2308",
    "sg:postcode":"27893",
    "sg:province":"NC",
    "sg:tags":[
        "village"
    ],
    "wof:name":"Human Relations Dept",
    "wof:placetype":"venue"
},
  "geometry": {"coordinates":[-77.910346,35.725024],"type":"Point"}
}