{
  "type": "Feature",
  "properties": {
    "iso:country":"US",
    "sg:address":"3806 Langdon Dr",
    "sg:city":"Greensboro",
    "sg:classifiers":[
        {
            "category":"Building & Trades",
            "subcategory":"Construction",
            "type":"Services"
        }
    ],
    "sg:phone":"+1 336 218 1120",
    "sg:postcode":"27410",
    "sg:province":"NC",
    "sg:tags":[
        "contractor"
    ],
    "wof:name":"Deckades",
    "wof:placetype":"venue"
},
  "geometry": {"coordinates":[-79.87491799999999,36.121358],"type":"Point"}
}