{
  "type": "Feature",
  "properties": {
    "addr:full":"1315 East Blvd Charlotte NC 28203",
    "addr:housenumber":"1315",
    "addr:postcode":"28203",
    "addr:street":"East Blvd",
    "iso:country":"US",
    "sg:address":"1315 East Blvd",
    "sg:city":"Charlotte",
    "sg:classifiers":[
        {
            "category":"Shopping",
            "subcategory":"Clothing, Apparel, & Fashions",
            "type":"Retail Goods"
        }
    ],
    "sg:phone":"+1 704 333 9655",
    "sg:postcode":"28203",
    "sg:province":"NC",
    "sg:tags":[
        "item",
        "boutique"
    ],
    "wof:name":"Di Fonseca",
    "wof:placetype":"venue"
},
  "geometry": {"coordinates":[-80.84377600000001,35.2014],"type":"Point"}
}