{
  "type": "Feature",
  "properties": {
    "addr:full":"614 Daniel St Tarboro NC 27886",
    "addr:housenumber":"614",
    "addr:postcode":"27886",
    "addr:street":"Daniel St",
    "iso:country":"US",
    "sg:address":"614 Daniel St",
    "sg:city":"Tarboro",
    "sg:classifiers":[
        {
            "category":"Utilities",
            "subcategory":"Refuse",
            "type":"Services"
        }
    ],
    "sg:phone":"+1 252 641 4111",
    "sg:postcode":"27886",
    "sg:province":"NC",
    "sg:tags":[
        "system"
    ],
    "wof:name":"Seaboard Container Service",
    "wof:placetype":"venue"
},
  "geometry": {"coordinates":[-77.53246900000001,35.917268],"type":"Point"}
}