{
  "type": "Feature",
  "properties": {
    "iso:country":"US",
    "sg:address":"3356 S Church St",
    "sg:city":"Burlington",
    "sg:classifiers":[
        {
            "category":"Restaurant",
            "type":"Food & Drink"
        }
    ],
    "sg:menulink":"http://www.allmenus.com/nc/boone-station/65470-cicis-pizza-buffet/menu/",
    "sg:phone":"+1 336 584 9596",
    "sg:postcode":"27215",
    "sg:province":"NC",
    "sg:tags":[
        "american",
        "pizza"
    ],
    "wof:name":"CiCi's Pizza Buffet",
    "wof:placetype":"venue"
},
  "geometry": {"coordinates":[-79.507169,36.08075],"type":"Point"}
}