{
  "type": "Feature",
  "properties": {
    "addr:full":"6709 Candlewood Dr Raleigh NC 27612",
    "addr:housenumber":"6709",
    "addr:postcode":"27612",
    "addr:street":"Candlewood Dr",
    "iso:country":"US",
    "sg:address":"6709 Candlewood Dr",
    "sg:city":"Raleigh",
    "sg:classifiers":[
        {
            "category":"Insurance",
            "subcategory":"Insurance Agent",
            "type":"Services"
        }
    ],
    "sg:phone":"+1 919 848 0499",
    "sg:postcode":"27612",
    "sg:province":"NC",
    "wof:name":"Union Central Life Insurance",
    "wof:placetype":"venue"
},
  "geometry": {"coordinates":[-78.663738,35.873631],"type":"Point"}
}