{
  "type": "Feature",
  "properties": {
    "iso:country":"US",
    "sg:address":"1308 Hobbton Hwy",
    "sg:city":"Clinton",
    "sg:classifiers":[
        {
            "category":"Autos & Motor Vehicles",
            "subcategory":"Auto Supplies",
            "type":"Retail Goods"
        }
    ],
    "sg:phone":"+1 910 592 3808",
    "sg:postcode":"28328",
    "sg:province":"NC",
    "sg:tags":[
        "tire"
    ],
    "wof:name":"S & S Tire Company Inc",
    "wof:placetype":"venue"
},
  "geometry": {"coordinates":[-78.326908,35.019895],"type":"Point"}
}