{
  "type": "Feature",
  "properties": {
    "addr:full":"10208 Mountain Apple Dr Charlotte NC 28227",
    "addr:housenumber":"10208",
    "addr:postcode":"28227",
    "addr:street":"Mountain Apple Dr",
    "iso:country":"US",
    "sg:address":"10208 Mountain Apple Dr",
    "sg:city":"Charlotte",
    "sg:classifiers":[
        {
            "category":"Professional",
            "subcategory":"Lawyer & Legal Services",
            "type":"Services"
        }
    ],
    "sg:phone":"+1   ",
    "sg:postcode":"28227",
    "sg:province":"NC",
    "wof:name":"Charles L Davis",
    "wof:placetype":"venue"
},
  "geometry": {"coordinates":[-80.673343,35.176296],"type":"Point"}
}