{
  "type": "Feature",
  "properties": {
    "iso:country":"US",
    "sg:address":"1651 Seaside Rd SW",
    "sg:city":"Ocean Isle Beach",
    "sg:classifiers":[
        {
            "category":"Restaurant",
            "type":"Food & Drink"
        }
    ],
    "sg:menulink":"http://www.allmenus.com/nc/shallotte/156291-hardees/menu/",
    "sg:phone":"+1 910 579 0808",
    "sg:postcode":"28469",
    "sg:province":"NC",
    "sg:tags":[
        "burger",
        "american"
    ],
    "wof:name":"Hardee's",
    "wof:placetype":"venue"
},
  "geometry": {"coordinates":[-78.487782,33.898797],"type":"Point"}
}