{
  "type": "Feature",
  "properties": {
    "addr:full":"5990 Beach Dr SW South Brunswick NC 28470",
    "addr:housenumber":"5990",
    "addr:postcode":"28470",
    "addr:street":"Beach Dr Sw",
    "iso:country":"US",
    "sg:address":"5990 Beach Dr SW",
    "sg:city":"South Brunswick",
    "sg:classifiers":[
        {
            "category":"Home & Garden",
            "subcategory":"Home Furnishings",
            "type":"Retail Goods"
        }
    ],
    "sg:phone":"+1 910 579 5033",
    "sg:postcode":"28470",
    "sg:province":"NC",
    "sg:tags":[
        "mirror"
    ],
    "wof:name":"Mirror Image Maintenance",
    "wof:placetype":"venue"
},
  "geometry": {"coordinates":[-78.436606,33.906889],"type":"Point"}
}