{
  "type": "Feature",
  "properties": {
    "addr:full":"517 Becks Church Rd Lexington NC 27292",
    "addr:housenumber":"517",
    "addr:postcode":"27292",
    "addr:street":"Becks Church Rd",
    "iso:country":"US",
    "sg:address":"517 Becks Church Rd",
    "sg:city":"Lexington",
    "sg:classifiers":[
        {
            "category":"Building & Trades",
            "subcategory":"Construction",
            "type":"Services"
        }
    ],
    "sg:phone":"+1 336 470 3389",
    "sg:postcode":"27292",
    "sg:province":"NC",
    "sg:tags":[
        "carpenter"
    ],
    "wof:name":"Burkhart By Design",
    "wof:placetype":"venue"
},
  "geometry": {"coordinates":[-80.218132,35.787359],"type":"Point"}
}