{
  "type": "Feature",
  "properties": {
    "addr:full":"46 Denning Rd Benson NC 27504",
    "addr:housenumber":"46",
    "addr:postcode":"27504",
    "addr:street":"Denning Rd",
    "iso:country":"US",
    "sg:address":"46 Denning Rd",
    "sg:city":"Benson",
    "sg:classifiers":[
        {
            "category":"Insurance",
            "subcategory":"Insurance Agent",
            "type":"Services"
        }
    ],
    "sg:phone":"+1 919 894 3291",
    "sg:postcode":"27504",
    "sg:province":"NC",
    "sg:tags":[
        "preparation",
        "tax"
    ],
    "wof:name":"Leonard C Honeycutt Accounting",
    "wof:placetype":"venue"
},
  "geometry": {"coordinates":[-78.56456799999999,35.429574],"type":"Point"}
}