{
  "type": "Feature",
  "properties": {
    "addr:full":"115 Fuchia Ln Lincolnton NC 28092",
    "addr:housenumber":"115",
    "addr:postcode":"28092",
    "addr:street":"Fuchia Ln",
    "iso:country":"US",
    "sg:address":"115 Fuchia Ln",
    "sg:city":"Lincolnton",
    "sg:classifiers":[
        {
            "category":"Personal",
            "subcategory":"Beauty Salon",
            "type":"Services"
        }
    ],
    "sg:phone":"+1 704 735 3334",
    "sg:postcode":"28092",
    "sg:province":"NC",
    "wof:name":"3 Amigas Salon",
    "wof:placetype":"venue"
},
  "geometry": {"coordinates":[-81.209503,35.481366],"type":"Point"}
}