{
  "type": "Feature",
  "properties": {
    "addr:full":"2626 Lewisville Clemmons Rd Clemmons NC 27012",
    "addr:housenumber":"2626",
    "addr:postcode":"27012",
    "addr:street":"Lewisville Clemmons Rd",
    "iso:country":"US",
    "sg:address":"2626 Lewisville Clemmons Rd",
    "sg:city":"Clemmons",
    "sg:classifiers":[
        {
            "category":"Shopping",
            "subcategory":"Clothing, Apparel, & Fashions",
            "type":"Retail Goods"
        }
    ],
    "sg:phone":"+1 336 766 7440",
    "sg:postcode":"27012",
    "sg:province":"NC",
    "wof:name":"Fraleigh's",
    "wof:placetype":"venue"
},
  "geometry": {"coordinates":[-80.382182,36.026313],"type":"Point"}
}