{
  "type": "Feature",
  "properties": {
    "iso:country":"US",
    "sg:address":"4235 Colebrook Rd",
    "sg:city":"Charlotte",
    "sg:classifiers":[
        {
            "category":"Professional",
            "type":"Services"
        }
    ],
    "sg:phone":"+1 704 535 9774",
    "sg:postcode":"28215",
    "sg:province":"NC",
    "wof:name":"World Prophecys Inc",
    "wof:placetype":"venue"
},
  "geometry": {"coordinates":[-80.748878,35.239596],"type":"Point"}
}