{
  "type": "Feature",
  "properties": {
    "iso:country":"US",
    "sg:address":"3557 High Point Rd",
    "sg:city":"Winston Salem",
    "sg:classifiers":[
        {
            "category":"Wholesale",
            "subcategory":"Electrical",
            "type":"Manufacturing & Wholesale Goods"
        }
    ],
    "sg:phone":"+1 336 788 2484",
    "sg:postcode":"27107",
    "sg:province":"NC",
    "sg:tags":[
        "equipment"
    ],
    "wof:name":"Farmalarm Systems Inc",
    "wof:placetype":"venue"
},
  "geometry": {"coordinates":[-80.16810700000001,36.073741],"type":"Point"}
}