{
  "type": "Feature",
  "properties": {
    "iso:country":"US",
    "sg:address":"4901 Holder Rd",
    "sg:city":"Durham",
    "sg:classifiers":[
        {
            "category":"Building & Trades",
            "subcategory":"Construction",
            "type":"Services"
        }
    ],
    "sg:phone":"+1 919 596 5838",
    "sg:postcode":"27703",
    "sg:province":"NC",
    "sg:tags":[
        "excavating",
        "contractor"
    ],
    "wof:name":"Barnett Backhoe Svc",
    "wof:placetype":"venue"
},
  "geometry": {"coordinates":[-78.80511799999999,35.966736],"type":"Point"}
}