{
  "type": "Feature",
  "properties": {
    "addr:full":"278 N Hummingbird Ln Rocky Point NC 28457",
    "addr:housenumber":"278",
    "addr:postcode":"28457",
    "addr:street":"N Hummingbird Ln",
    "iso:country":"US",
    "sg:address":"278 N Hummingbird Ln",
    "sg:city":"Rocky Point",
    "sg:classifiers":[
        {
            "category":"Professional",
            "subcategory":"Business Services",
            "type":"Services"
        }
    ],
    "sg:phone":"+1   ",
    "sg:postcode":"28457",
    "sg:province":"NC",
    "wof:name":"Wicks Enterprises LLC",
    "wof:placetype":"venue"
},
  "geometry": {"coordinates":[-77.973212,34.487683],"type":"Point"}
}