{
  "type": "Feature",
  "properties": {
    "addr:full":"376 Big Hungry Rd Flat Rock NC 28731",
    "addr:housenumber":"376",
    "addr:postcode":"28731",
    "addr:street":"Big Hungry Rd",
    "iso:country":"US",
    "sg:address":"376 Big Hungry Rd",
    "sg:city":"Flat Rock",
    "sg:classifiers":[
        {
            "category":"Autos & Motor Vehicles",
            "subcategory":"Fuel & Gas Station",
            "type":"Retail Goods"
        },
        {
            "category":"Retail",
            "subcategory":"Auto Repair",
            "type":"Services"
        }
    ],
    "sg:phone":"+1 828 692 3207",
    "sg:postcode":"28731",
    "sg:province":"NC",
    "sg:tags":[
        "automotive",
        "station",
        "gasoline",
        "wrecker",
        "general"
    ],
    "wof:name":"Hill's Garage & Wrecker Svc",
    "wof:placetype":"venue"
},
  "geometry": {"coordinates":[-82.37409100000001,35.299486],"type":"Point"}
}