{
  "type": "Feature",
  "properties": {
    "iso:country":"US",
    "sg:address":"901 Willow Dr",
    "sg:city":"Chapel Hill",
    "sg:classifiers":[
        {
            "category":"Food & Beverages",
            "subcategory":"Groceries & Convenience Stores",
            "type":"Retail Goods"
        },
        {
            "category":"Autos & Motor Vehicles",
            "subcategory":"Fuel & Gas Station",
            "type":"Retail Goods"
        }
    ],
    "sg:phone":"+1 919 942 6080",
    "sg:postcode":"27514",
    "sg:province":"NC",
    "sg:tags":[
        "gasoline"
    ],
    "wof:name":"Tops Petroleum Corp",
    "wof:placetype":"venue"
},
  "geometry": {"coordinates":[-79.02990800000001,35.928367],"type":"Point"}
}