{
  "type": "Feature",
  "properties": {
    "addr:full":"2321 High Ridge Church Rd Marshville NC 28103",
    "addr:housenumber":"2321",
    "addr:postcode":"28103",
    "addr:street":"High Ridge Church Rd",
    "iso:country":"US",
    "sg:address":"2321 High Ridge Church Rd",
    "sg:city":"Marshville",
    "sg:classifiers":[
        {
            "category":"Building & Trades",
            "subcategory":"Plumbing",
            "type":"Services"
        }
    ],
    "sg:phone":"+1 704 624 6292",
    "sg:postcode":"28103",
    "sg:province":"NC",
    "sg:tags":[
        "repair",
        "boiler"
    ],
    "wof:name":"Custom Iron Works Inc",
    "wof:placetype":"venue"
},
  "geometry": {"coordinates":[-80.311791,34.926331],"type":"Point"}
}