{
  "type": "Feature",
  "properties": {
    "addr:full":"1170 S Main St Waynesville NC 28786",
    "addr:housenumber":"1170",
    "addr:postcode":"28786",
    "addr:street":"S Main St",
    "iso:country":"US",
    "sg:address":"1170 S Main St",
    "sg:city":"Waynesville",
    "sg:classifiers":[
        {
            "category":"Real Estate",
            "subcategory":"Real Estate Agent",
            "type":"Services"
        }
    ],
    "sg:phone":"+1 828 452 7931",
    "sg:postcode":"28786",
    "sg:province":"NC",
    "wof:name":"Highland Homes",
    "wof:placetype":"venue"
},
  "geometry": {"coordinates":[-82.99710899999999,35.475713],"type":"Point"}
}