{
  "type": "Feature",
  "properties": {
    "iso:country":"US",
    "sg:address":"4725 N Croatan Hwy",
    "sg:city":"Kitty Hawk",
    "sg:classifiers":[
        {
            "category":"Building & Trades",
            "subcategory":"Construction",
            "type":"Services"
        }
    ],
    "sg:phone":"+1 252 261 6010",
    "sg:postcode":"27949",
    "sg:province":"NC",
    "sg:tags":[
        "insulation",
        "heat",
        "contractor"
    ],
    "wof:name":"All Star Insulation",
    "wof:placetype":"venue"
},
  "geometry": {"coordinates":[-75.709892,36.092938],"type":"Point"}
}