{
  "type": "Feature",
  "properties": {
    "addr:full":"2580 Hayes Chapel Rd Rose Hill NC 28458",
    "addr:housenumber":"2580",
    "addr:postcode":"28458",
    "addr:street":"Hayes Chapel Rd",
    "iso:country":"US",
    "sg:address":"2580 Hayes Chapel Rd",
    "sg:city":"Rose Hill",
    "sg:classifiers":[
        {
            "category":"Organizations",
            "subcategory":"Religious Organization",
            "type":"Services"
        }
    ],
    "sg:phone":"+1 910 532 2372",
    "sg:postcode":"28458",
    "sg:province":"NC",
    "sg:tags":[
        "church"
    ],
    "wof:name":"Hayes' Chapel Church",
    "wof:placetype":"venue"
},
  "geometry": {"coordinates":[-78.28816,34.815528],"type":"Point"}
}