{
  "type": "Feature",
  "properties": {
    "iso:country":"US",
    "sg:address":"231 Newstock Rd",
    "sg:city":"Asheville",
    "sg:classifiers":[
        {
            "category":"Building & Trades",
            "subcategory":"Construction",
            "type":"Services"
        }
    ],
    "sg:phone":"+1 828 658 8541",
    "sg:postcode":"28804",
    "sg:province":"NC",
    "sg:tags":[
        "carpentry",
        "contractor"
    ],
    "wof:name":"North Star Construction",
    "wof:placetype":"venue"
},
  "geometry": {"coordinates":[-82.589422,35.681956],"type":"Point"}
}