{
  "type": "Feature",
  "properties": {
    "addr:full":"3701 Thomasville Rd Winston Salem NC 27107",
    "addr:housenumber":"3701",
    "addr:postcode":"27107",
    "addr:street":"Thomasville Rd",
    "iso:country":"US",
    "sg:address":"3701 Thomasville Rd",
    "sg:city":"Winston Salem",
    "sg:classifiers":[
        {
            "category":"Building & Trades",
            "subcategory":"Construction",
            "type":"Services"
        }
    ],
    "sg:phone":"+1 336 784 9387",
    "sg:postcode":"27107",
    "sg:province":"NC",
    "sg:tags":[
        "roofing",
        "contractor"
    ],
    "wof:name":"Winston Roofing Co Inc",
    "wof:placetype":"venue"
},
  "geometry": {"coordinates":[-80.199899,36.047703],"type":"Point"}
}