{
  "type": "Feature",
  "properties": {
    "addr:full":"401 N Norwood St Wallace NC 28466",
    "addr:housenumber":"401",
    "addr:postcode":"28466",
    "addr:street":"N Norwood St",
    "iso:country":"US",
    "sg:address":"401 N Norwood St",
    "sg:city":"Wallace",
    "sg:classifiers":[
        {
            "category":"Sports & Exercise",
            "subcategory":"Gym",
            "type":"Entertainment"
        }
    ],
    "sg:phone":"+1 910 285 6768",
    "sg:postcode":"28466",
    "sg:province":"NC",
    "sg:tags":[
        "facility",
        "club",
        "gymnasium",
        "health",
        "fitness",
        "studio",
        "physical"
    ],
    "wof:name":"Curves For Womens",
    "wof:placetype":"venue"
},
  "geometry": {"coordinates":[-77.99473999999999,34.740635],"type":"Point"}
}