{
  "type": "Feature",
  "properties": {
    "iso:country":"US",
    "sg:address":"903 Willow Ridge Dr",
    "sg:city":"Knightdale",
    "sg:classifiers":[
        {
            "category":"Professional",
            "subcategory":"Computer Services",
            "type":"Services"
        }
    ],
    "sg:phone":"+1   ",
    "sg:postcode":"27545",
    "sg:province":"NC",
    "sg:tags":[
        "development",
        "provides",
        "software"
    ],
    "wof:name":"Software Pro Inc",
    "wof:placetype":"venue"
},
  "geometry": {"coordinates":[-78.520081,35.782105],"type":"Point"}
}