{
  "type": "Feature",
  "properties": {
    "addr:full":"1415 W New Bern Rd Kinston NC 28504",
    "addr:housenumber":"1415",
    "addr:postcode":"28504",
    "addr:street":"W New Bern Rd",
    "iso:country":"US",
    "sg:address":"1415 W New Bern Rd",
    "sg:city":"Kinston",
    "sg:classifiers":[
        {
            "category":"Retail",
            "subcategory":"Repair Shop",
            "type":"Services"
        }
    ],
    "sg:phone":"+1 252 522 4005",
    "sg:postcode":"28504",
    "sg:province":"NC",
    "sg:tags":[
        "welding"
    ],
    "wof:name":"Villabona Iron Works",
    "wof:placetype":"venue"
},
  "geometry": {"coordinates":[-77.60877000000001,35.257852],"type":"Point"}
}