{
  "type": "Feature",
  "properties": {
    "addr:full":"213 Lilliput Ln Wake Forest NC 27587",
    "addr:housenumber":"213",
    "addr:postcode":"27587",
    "addr:street":"Lilliput Ln",
    "iso:country":"US",
    "sg:address":"213 Lilliput Ln",
    "sg:city":"Wake Forest",
    "sg:classifiers":[
        {
            "category":"Wholesale",
            "subcategory":"Machinery & Supplies",
            "type":"Manufacturing & Wholesale Goods"
        }
    ],
    "sg:phone":"+1 919 562 8034",
    "sg:postcode":"27587",
    "sg:province":"NC",
    "sg:tags":[
        "equipment",
        "industrial"
    ],
    "wof:name":"Woodhead Connectivity",
    "wof:placetype":"venue"
},
  "geometry": {"coordinates":[-78.503343,35.997722],"type":"Point"}
}