{
  "type": "Feature",
  "properties": {
    "iso:country":"US",
    "sg:address":"1313 S Dekalb St",
    "sg:city":"Shelby",
    "sg:classifiers":[
        {
            "category":"Shopping",
            "type":"Retail Goods"
        }
    ],
    "sg:phone":"+1 704 487 6215",
    "sg:postcode":"28152",
    "sg:province":"NC",
    "sg:tags":[
        "merchandise",
        "furniture"
    ],
    "wof:name":"McAllster Mcllster Frame Wodwo",
    "wof:placetype":"venue"
},
  "geometry": {"coordinates":[-81.54244300000001,35.267452],"type":"Point"}
}