{
  "type": "Feature",
  "properties": {
    "iso:country":"US",
    "sg:address":"2603 Glenwood Ave",
    "sg:city":"Raleigh",
    "sg:classifiers":[
        {
            "category":"Shopping",
            "subcategory":"Stationery & Office Supplies",
            "type":"Retail Goods"
        },
        {
            "category":"Shopping",
            "subcategory":"Gifts & Souvenirs",
            "type":"Retail Goods"
        }
    ],
    "sg:phone":"+1 919 787 1246",
    "sg:postcode":"27608",
    "sg:province":"NC",
    "sg:tags":[
        "shop",
        "item"
    ],
    "wof:name":"Taylors of Raleigh",
    "wof:placetype":"venue"
},
  "geometry": {"coordinates":[-78.66213,35.817495],"type":"Point"}
}