{
  "type": "Feature",
  "properties": {
    "addr:full":"1329 Beaman Pl Greensboro NC 27408",
    "addr:housenumber":"1329",
    "addr:postcode":"27408",
    "addr:street":"Beaman Pl",
    "iso:country":"US",
    "sg:address":"1329 Beaman Pl",
    "sg:city":"Greensboro",
    "sg:classifiers":[
        {
            "category":"Building & Trades",
            "subcategory":"Construction",
            "type":"Services"
        }
    ],
    "sg:phone":"+1 336 272 7201",
    "sg:postcode":"27408",
    "sg:province":"NC",
    "sg:tags":[
        "masonry",
        "contractor"
    ],
    "wof:name":"Dillingham Stone Masonry & Sls",
    "wof:placetype":"venue"
},
  "geometry": {"coordinates":[-79.803736,36.084711],"type":"Point"}
}