{
  "type": "Feature",
  "properties": {
    "addr:full":"390 McCrae St Grifton NC 28530",
    "addr:housenumber":"390",
    "addr:postcode":"28530",
    "addr:street":"Mccrae St",
    "iso:country":"US",
    "sg:address":"390 McCrae St",
    "sg:city":"Grifton",
    "sg:classifiers":[
        {
            "category":"Professional",
            "subcategory":"Lawyer & Legal Services",
            "type":"Services"
        }
    ],
    "sg:phone":"+1 252 524 4521",
    "sg:postcode":"28530",
    "sg:province":"NC",
    "sg:tags":[
        "attorney"
    ],
    "wof:name":"Russell Houston III PC",
    "wof:placetype":"venue"
},
  "geometry": {"coordinates":[-77.434933,35.373697],"type":"Point"}
}