{
  "type": "Feature",
  "properties": {
    "iso:country":"US",
    "sg:address":"106 N Ridge Dr",
    "sg:city":"Asheville",
    "sg:classifiers":[
        {
            "category":"Professional",
            "type":"Services"
        }
    ],
    "sg:phone":"+1   ",
    "sg:postcode":"28804",
    "sg:province":"NC",
    "wof:name":"Faith Dort Services",
    "wof:placetype":"venue"
},
  "geometry": {"coordinates":[-82.576722,35.635272],"type":"Point"}
}