{
  "type": "Feature",
  "properties": {
    "iso:country":"US",
    "sg:address":"141 Rand St",
    "sg:city":"Sanford",
    "sg:classifiers":[
        {
            "category":"Retail",
            "subcategory":"Laundry & Dry Cleaning",
            "type":"Services"
        }
    ],
    "sg:phone":"+1 919 776 8826",
    "sg:postcode":"27332",
    "sg:province":"NC",
    "sg:tags":[
        "uniform",
        "supply"
    ],
    "wof:name":"J & E Uniforms Inc",
    "wof:placetype":"venue"
},
  "geometry": {"coordinates":[-79.14639099999999,35.450683],"type":"Point"}
}