{
  "type": "Feature",
  "properties": {
    "iso:country":"US",
    "sg:address":"202 Thames Dr",
    "sg:city":"Jacksonville",
    "sg:classifiers":[
        {
            "category":"Organizations",
            "subcategory":"Religious Organization",
            "type":"Services"
        }
    ],
    "sg:phone":"+1   ",
    "sg:postcode":"28546",
    "sg:province":"NC",
    "wof:name":"Rock Truth Deliverance Chur",
    "wof:placetype":"venue"
},
  "geometry": {"coordinates":[-77.362742,34.782205],"type":"Point"}
}