{
  "type": "Feature",
  "properties": {
    "addr:full":"102 N Railroad St Benson NC 27504",
    "addr:housenumber":"102",
    "addr:postcode":"27504",
    "addr:street":"N Railroad St",
    "iso:country":"US",
    "sg:address":"102 N Railroad St",
    "sg:city":"Benson",
    "sg:classifiers":[
        {
            "category":"Personal",
            "subcategory":"Beauty Salon",
            "type":"Services"
        }
    ],
    "sg:phone":"+1   ",
    "sg:postcode":"27504",
    "sg:province":"NC",
    "sg:tags":[
        "shop"
    ],
    "wof:name":"Diana Salon",
    "wof:placetype":"venue"
},
  "geometry": {"coordinates":[-78.546932,35.382044],"type":"Point"}
}