{
  "type": "Feature",
  "properties": {
    "addr:full":"104 W Carr St Carrboro NC 27510",
    "addr:housenumber":"104",
    "addr:postcode":"27510",
    "addr:street":"W Carr St",
    "iso:country":"US",
    "sg:address":"104 W Carr St",
    "sg:city":"Carrboro",
    "sg:classifiers":[
        {
            "category":"Insurance",
            "subcategory":"Insurance Agent",
            "type":"Services"
        }
    ],
    "sg:phone":"+1 919 929 6900",
    "sg:postcode":"27510",
    "sg:province":"NC",
    "sg:tags":[
        "company",
        "general"
    ],
    "wof:name":"Allstate",
    "wof:placetype":"venue"
},
  "geometry": {"coordinates":[-79.074448,35.908911],"type":"Point"}
}