{
  "type": "Feature",
  "properties": {
    "addr:full":"1010 Clyde Edgerton Dr Kernersville NC 27284",
    "addr:housenumber":"1010",
    "addr:postcode":"27284",
    "addr:street":"Clyde Edgerton Dr",
    "iso:country":"US",
    "sg:address":"1010 Clyde Edgerton Dr",
    "sg:city":"Kernersville",
    "sg:classifiers":[
        {
            "category":"Personal",
            "subcategory":"Beauty Salon",
            "type":"Services"
        }
    ],
    "sg:phone":"+1   ",
    "sg:postcode":"27284",
    "sg:province":"NC",
    "sg:tags":[
        "shop"
    ],
    "wof:name":"NJ Bourn Inc",
    "wof:placetype":"venue"
},
  "geometry": {"coordinates":[-80.09462600000001,36.088293],"type":"Point"}
}