{
  "type": "Feature",
  "properties": {
    "iso:country":"US",
    "sg:address":"659 Cary Towne Blvd",
    "sg:city":"Cary",
    "sg:classifiers":[
        {
            "category":"Arts & Performance",
            "subcategory":"Theater",
            "type":"Entertainment"
        }
    ],
    "sg:phone":"+1 919 272 1652",
    "sg:postcode":"27511",
    "sg:province":"NC",
    "sg:tags":[
        "group",
        "live",
        "music"
    ],
    "wof:name":"Karaoke Entertainment Group",
    "wof:placetype":"venue"
},
  "geometry": {"coordinates":[-78.768338,35.775741],"type":"Point"}
}