{
  "type": "Feature",
  "properties": {
    "iso:country":"US",
    "sg:address":"431 W Franklin St",
    "sg:city":"Chapel Hill",
    "sg:classifiers":[
        {
            "category":"Restaurant",
            "type":"Food & Drink"
        }
    ],
    "sg:postcode":"27514",
    "sg:province":"NC",
    "sg:tags":[
        "middle",
        "eastern"
    ],
    "wof:name":"Baba Ghannoush",
    "wof:placetype":"venue"
},
  "geometry": {"coordinates":[-79.048863,35.915846],"type":"Point"}
}