{
  "type": "Feature",
  "properties": {
    "iso:country":"US",
    "sg:address":"2409 Houston Branch Rd",
    "sg:city":"Charlotte",
    "sg:classifiers":[
        {
            "category":"Manufacturing",
            "subcategory":"Metals",
            "type":"Manufacturing & Wholesale Goods"
        }
    ],
    "sg:phone":"+1 704 847 1133",
    "sg:postcode":"28270",
    "sg:province":"NC",
    "sg:tags":[
        "engraver"
    ],
    "wof:name":"Edward's Engraving",
    "wof:placetype":"venue"
},
  "geometry": {"coordinates":[-80.745434,35.089931],"type":"Point"}
}