{
  "type": "Feature",
  "properties": {
    "addr:full":"300 S Poplar St Elizabethtown NC 28337",
    "addr:housenumber":"300",
    "addr:postcode":"28337",
    "addr:street":"S Poplar St",
    "iso:country":"US",
    "sg:address":"300 S Poplar St",
    "sg:city":"Elizabethtown",
    "sg:classifiers":[
        {
            "category":"Cinema",
            "subcategory":"Movie Rental",
            "type":"Entertainment"
        }
    ],
    "sg:phone":"+1 910 872 0005",
    "sg:postcode":"28337",
    "sg:province":"NC",
    "sg:tags":[
        "leasing",
        "video",
        "disc",
        "tape"
    ],
    "sg:website":"www.moviegallery.com",
    "wof:name":"Movie Gallery",
    "wof:placetype":"venue"
},
  "geometry": {"coordinates":[-78.606754,34.626249],"type":"Point"}
}