{
  "type": "Feature",
  "properties": {
    "addr:full":"2112 Dayton Ave S Wilson NC 27893",
    "addr:housenumber":"2112",
    "addr:postcode":"27893",
    "addr:street":"Dayton Ave S",
    "iso:country":"US",
    "sg:address":"2112 Dayton Ave S",
    "sg:city":"Wilson",
    "sg:classifiers":[
        {
            "category":"Building & Trades",
            "subcategory":"Construction",
            "type":"Services"
        }
    ],
    "sg:phone":"+1 252 291 0338",
    "sg:postcode":"27893",
    "sg:province":"NC",
    "sg:tags":[
        "carpentry",
        "contractor"
    ],
    "wof:name":"Erdmann Construction",
    "wof:placetype":"venue"
},
  "geometry": {"coordinates":[-77.93554,35.682443],"type":"Point"}
}