{
  "type": "Feature",
  "properties": {
    "iso:country":"US",
    "sg:address":"2339 E Franklin Blvd",
    "sg:city":"Gastonia",
    "sg:classifiers":[
        {
            "category":"Autos & Motor Vehicles",
            "subcategory":"Automobile Sales",
            "type":"Retail Goods"
        }
    ],
    "sg:phone":"+1 704 824 3500",
    "sg:postcode":"28054",
    "sg:province":"NC",
    "wof:name":"Sonny Hancock Mazda",
    "wof:placetype":"venue"
},
  "geometry": {"coordinates":[-81.135356,35.261152],"type":"Point"}
}