{
  "type": "Feature",
  "properties": {
    "addr:full":"147 Knoxview Ln Mooresville NC 28117",
    "addr:housenumber":"147",
    "addr:postcode":"28117",
    "addr:street":"Knoxview Ln",
    "iso:country":"US",
    "sg:address":"147 Knoxview Ln",
    "sg:city":"Mooresville",
    "sg:classifiers":[
        {
            "category":"Insurance",
            "subcategory":"Life Insurance",
            "type":"Services"
        }
    ],
    "sg:phone":"+1 704 895 2365",
    "sg:postcode":"28117",
    "sg:province":"NC",
    "sg:tags":[
        "carrier"
    ],
    "wof:name":"Maccabees LLC",
    "wof:placetype":"venue"
},
  "geometry": {"coordinates":[-80.88394599999999,35.522991],"type":"Point"}
}