{
  "type": "Feature",
  "properties": {
    "addr:full":"300 Perimeter Park Drive Morrisville NC 27560",
    "addr:housenumber":"300",
    "addr:postcode":"27560",
    "addr:street":"Perimeter Park Drive",
    "iso:country":"US",
    "sg:address":"300 Perimeter Park Drive",
    "sg:city":"Morrisville",
    "sg:classifiers":[
        {
            "category":"Shopping",
            "subcategory":"Jewelry",
            "type":"Retail Goods"
        }
    ],
    "sg:phone":"+1 888 345 8725",
    "sg:postcode":"27560",
    "sg:province":"NC",
    "sg:website":"www.moissanitefinejewelry.com/",
    "wof:name":"Moissanite Fine Jewelry",
    "wof:placetype":"venue"
},
  "geometry": {"coordinates":[-78.820339,35.853564],"type":"Point"}
}