{
  "type": "Feature",
  "properties": {
    "iso:country":"US",
    "sg:address":"2319 Beechridge Rd",
    "sg:city":"Raleigh",
    "sg:classifiers":[
        {
            "category":"Professional",
            "subcategory":"Employment Agencies",
            "type":"Services"
        }
    ],
    "sg:phone":"+1   ",
    "sg:postcode":"27608",
    "sg:province":"NC",
    "wof:name":"Softrol Systems Inc",
    "wof:placetype":"venue"
},
  "geometry": {"coordinates":[-78.645191,35.811434],"type":"Point"}
}