{
  "type": "Feature",
  "properties": {
    "addr:full":"1712 Sherman Ave Durham NC 27707",
    "addr:housenumber":"1712",
    "addr:postcode":"27707",
    "addr:street":"Sherman Ave",
    "iso:country":"US",
    "sg:address":"1712 Sherman Ave",
    "sg:city":"Durham",
    "sg:classifiers":[
        {
            "category":"Health Services",
            "subcategory":"Nursing And Care Facility",
            "type":"Services"
        }
    ],
    "sg:phone":"+1 919 688 6454",
    "sg:postcode":"27707",
    "sg:province":"NC",
    "sg:tags":[
        "skilled"
    ],
    "wof:name":"Php of NC Inc",
    "wof:placetype":"venue"
},
  "geometry": {"coordinates":[-78.888746,35.963898],"type":"Point"}
}