{
  "type": "Feature",
  "properties": {
    "addr:full":"757 Catheys Creek Church Rd Brevard SC 28712",
    "addr:housenumber":"757",
    "addr:postcode":"28712",
    "addr:street":"Catheys Creek Church Rd",
    "iso:country":"US",
    "sg:address":"757 Catheys Creek Church Rd",
    "sg:city":"Brevard",
    "sg:classifiers":[
        {
            "category":"Building & Trades",
            "subcategory":"Construction",
            "type":"Services"
        }
    ],
    "sg:phone":"+1 828 883 3867",
    "sg:postcode":"28712",
    "sg:province":"SC",
    "sg:tags":[
        "preparation",
        "land"
    ],
    "wof:name":"Whitmire Jerry T Grading Inc",
    "wof:placetype":"venue"
},
  "geometry": {"coordinates":[-82.78717899999999,35.192676],"type":"Point"}
}