{
  "type": "Feature",
  "properties": {
    "addr:full":"3897 Old US Hwy 1 Moncure NC 27559",
    "addr:housenumber":"3897",
    "addr:postcode":"27559",
    "addr:street":"Old Us Hwy 1",
    "iso:country":"US",
    "sg:address":"3897 Old US Hwy 1",
    "sg:city":"Moncure",
    "sg:classifiers":[
        {
            "category":"Freight",
            "type":"Transportation"
        }
    ],
    "sg:phone":"+1 919 362 6715",
    "sg:postcode":"27559",
    "sg:province":"NC",
    "sg:tags":[
        "operator",
        "local",
        "trucking"
    ],
    "wof:name":"Ellis JD Trucking LLC",
    "wof:placetype":"venue"
},
  "geometry": {"coordinates":[-79.02929899999999,35.625664],"type":"Point"}
}