{
  "type": "Feature",
  "properties": {
    "iso:country":"US",
    "sg:address":"3000 Aerial Center Pkwy",
    "sg:city":"Morrisville",
    "sg:classifiers":[
        {
            "category":"Professional",
            "subcategory":"Computer Services",
            "type":"Services"
        }
    ],
    "sg:phone":"+1 919 467 2080",
    "sg:postcode":"27560",
    "sg:province":"NC",
    "sg:tags":[
        "consultant",
        "designer"
    ],
    "wof:name":"Hifen Inc",
    "wof:placetype":"venue"
},
  "geometry": {"coordinates":[-78.813299,35.855101],"type":"Point"}
}