{
  "type": "Feature",
  "properties": {
    "addr:full":"303 N Sterling St Morganton NC 28655",
    "addr:housenumber":"303",
    "addr:postcode":"28655",
    "addr:street":"N Sterling St",
    "iso:country":"US",
    "sg:address":"303 N Sterling St",
    "sg:city":"Morganton",
    "sg:classifiers":[
        {
            "category":"Professional",
            "subcategory":"Business Services",
            "type":"Services"
        }
    ],
    "sg:phone":"+1 828 430 7473",
    "sg:postcode":"28655",
    "sg:province":"NC",
    "sg:tags":[
        "interior",
        "consultant",
        "design",
        "decorator"
    ],
    "wof:name":"Tiffany Poteat Interior Design",
    "wof:placetype":"venue"
},
  "geometry": {"coordinates":[-81.68965,35.746697],"type":"Point"}
}