{
  "type": "Feature",
  "properties": {
    "addr:full":"9390 Glen Cross Dr Kernersville NC 27284",
    "addr:housenumber":"9390",
    "addr:postcode":"27284",
    "addr:street":"Glen Cross Dr",
    "iso:country":"US",
    "sg:address":"9390 Glen Cross Dr",
    "sg:city":"Kernersville",
    "sg:classifiers":[
        {
            "category":"Freight",
            "type":"Transportation"
        }
    ],
    "sg:phone":"+1 336 996 2094",
    "sg:postcode":"27284",
    "sg:province":"NC",
    "sg:tags":[
        "hauling",
        "trucking"
    ],
    "wof:name":"J D Porterfield Recycler",
    "wof:placetype":"venue"
},
  "geometry": {"coordinates":[-80.042986,36.16043],"type":"Point"}
}