{
  "type": "Feature",
  "properties": {
    "addr:full":"204 E Virginia Ave Bessemer City NC 28016",
    "addr:housenumber":"204",
    "addr:postcode":"28016",
    "addr:street":"E Virginia Ave",
    "iso:country":"US",
    "sg:address":"204 E Virginia Ave",
    "sg:city":"Bessemer City",
    "sg:classifiers":[
        {
            "category":"Organizations",
            "subcategory":"Religious Organization",
            "type":"Services"
        }
    ],
    "sg:phone":"+1 704 629 5971",
    "sg:postcode":"28016",
    "sg:province":"NC",
    "sg:tags":[
        "church"
    ],
    "wof:name":"Heavenbound Baptist Church",
    "wof:placetype":"venue"
},
  "geometry": {"coordinates":[-81.281705,35.284255],"type":"Point"}
}