{
  "type": "Feature",
  "properties": {
    "iso:country":"US",
    "sg:address":"148 Tarheel Ln",
    "sg:city":"Boone",
    "sg:classifiers":[
        {
            "category":"Wholesale",
            "subcategory":"Machinery & Supplies",
            "type":"Manufacturing & Wholesale Goods"
        },
        {
            "category":"Freight",
            "type":"Transportation"
        }
    ],
    "sg:phone":"+1 828 264 6336",
    "sg:postcode":"28677",
    "sg:province":"NC",
    "sg:tags":[
        "building",
        "material",
        "hauling",
        "contract",
        "mason",
        "contractor",
        "local"
    ],
    "wof:name":"Greene's Masonry Supplies",
    "wof:placetype":"venue"
},
  "geometry": {"coordinates":[-80.92859199999999,35.692256],"type":"Point"}
}