{
  "type": "Feature",
  "properties": {
    "iso:country":"US",
    "sg:address":"100 Ocean Bay Blvd",
    "sg:city":"Kill Devil Hills",
    "sg:classifiers":[
        {
            "category":"Food & Beverages",
            "subcategory":"Groceries & Convenience Stores",
            "type":"Retail Goods"
        }
    ],
    "sg:phone":"+1 252 441 7188",
    "sg:postcode":"27948",
    "sg:province":"NC",
    "sg:tags":[
        "grocer"
    ],
    "sg:website":"www.redapplemarkets.com",
    "wof:name":"Red Apple Market",
    "wof:placetype":"venue"
},
  "geometry": {"coordinates":[-75.658862,36.014187],"type":"Point"}
}