{
  "type": "Feature",
  "properties": {
    "iso:country":"US",
    "sg:address":"11229 E Independence Blvd",
    "sg:city":"Matthews",
    "sg:classifiers":[
        {
            "category":"Banks & Credit Unions",
            "subcategory":"Bank",
            "type":"Services"
        }
    ],
    "sg:phone":"+1 704 846 7422",
    "sg:postcode":"28105",
    "sg:province":"NC",
    "sg:tags":[
        "cashing",
        "check"
    ],
    "wof:name":"Check 'n Go",
    "wof:placetype":"venue"
},
  "geometry": {"coordinates":[-80.694006,35.115353],"type":"Point"}
}