{
  "type": "Feature",
  "properties": {
    "iso:country":"US",
    "sg:address":"914 White Plains Rd",
    "sg:city":"Charlotte",
    "sg:classifiers":[
        {
            "category":"Building & Trades",
            "subcategory":"Construction",
            "type":"Services"
        }
    ],
    "sg:phone":"+1 704 596 4647",
    "sg:postcode":"28213",
    "sg:province":"NC",
    "sg:tags":[
        "floor",
        "laying",
        "contractor"
    ],
    "wof:name":"Houpe Services",
    "wof:placetype":"venue"
},
  "geometry": {"coordinates":[-80.790752,35.272655],"type":"Point"}
}