{
  "type": "Feature",
  "properties": {
    "addr:full":"6210 Ginkgo Ln Charlotte NC 28215",
    "addr:housenumber":"6210",
    "addr:postcode":"28215",
    "addr:street":"Ginkgo Ln",
    "iso:country":"US",
    "sg:address":"6210 Ginkgo Ln",
    "sg:city":"Charlotte",
    "sg:classifiers":[
        {
            "category":"Professional",
            "type":"Services"
        }
    ],
    "sg:phone":"+1 704 532 6485",
    "sg:postcode":"28215",
    "sg:province":"NC",
    "wof:name":"Champsolutions",
    "wof:placetype":"venue"
},
  "geometry": {"coordinates":[-80.685064,35.231943],"type":"Point"}
}