{
  "type": "Feature",
  "properties": {
    "addr:full":"306 S Evans St Greenville NC 27858",
    "addr:housenumber":"306",
    "addr:postcode":"27858",
    "addr:street":"S Evans St",
    "iso:country":"US",
    "sg:address":"306 S Evans St",
    "sg:city":"Greenville",
    "sg:classifiers":[
        {
            "category":"Government",
            "subcategory":"Office",
            "type":"Public Place"
        }
    ],
    "sg:phone":"+1 252 329 1093",
    "sg:postcode":"27858",
    "sg:province":"NC",
    "wof:name":"Senator Elizabeth Dole",
    "wof:placetype":"venue"
},
  "geometry": {"coordinates":[-77.372832,35.612284],"type":"Point"}
}