{
  "type": "Feature",
  "properties": {
    "iso:country":"US",
    "sg:address":"2734 Mansfield Ave",
    "sg:city":"Durham",
    "sg:classifiers":[
        {
            "category":"Retail",
            "subcategory":"Laundry & Dry Cleaning",
            "type":"Services"
        }
    ],
    "sg:phone":"+1 919 596 5059",
    "sg:postcode":"27703",
    "sg:province":"NC",
    "sg:tags":[
        "cleaners",
        "rug",
        "carpet"
    ],
    "wof:name":"Snipes Carpet Cleaning",
    "wof:placetype":"venue"
},
  "geometry": {"coordinates":[-78.849847,35.997871],"type":"Point"}
}