{
  "type": "Feature",
  "properties": {
    "iso:country":"US",
    "sg:address":"5813 Oleander Dr",
    "sg:city":"Wilmington",
    "sg:classifiers":[
        {
            "category":"Retail",
            "subcategory":"Repair Shop",
            "type":"Services"
        }
    ],
    "sg:phone":"+1   ",
    "sg:postcode":"28403",
    "sg:province":"NC",
    "wof:name":"Heritage Furniture Restoration",
    "wof:placetype":"venue"
},
  "geometry": {"coordinates":[-77.843542,34.209491],"type":"Point"}
}