{
  "type": "Feature",
  "properties": {
    "iso:country":"US",
    "sg:address":"935 Phils Creek Rd",
    "sg:city":"Chapel Hill",
    "sg:classifiers":[
        {
            "category":"Real Estate",
            "subcategory":"Real Estate Services",
            "type":"Services"
        }
    ],
    "sg:phone":"+1 919 968 0177",
    "sg:postcode":"27516",
    "sg:province":"NC",
    "sg:tags":[
        "management",
        "property"
    ],
    "wof:name":"Hco Properties",
    "wof:placetype":"venue"
},
  "geometry": {"coordinates":[-79.11676900000001,35.900009],"type":"Point"}
}