{
  "type": "Feature",
  "properties": {
    "iso:country":"US",
    "sg:address":"530 Ocean Trl",
    "sg:city":"Corolla",
    "sg:classifiers":[
        {
            "category":"Building & Trades",
            "subcategory":"Equipment Rental",
            "type":"Services"
        }
    ],
    "sg:phone":"+1 252 457 0072",
    "sg:postcode":"27927",
    "sg:province":"NC",
    "sg:tags":[
        "yard"
    ],
    "wof:name":"Lighthouse Resort Svc",
    "wof:placetype":"venue"
},
  "geometry": {"coordinates":[-75.80441,36.301446],"type":"Point"}
}