{
  "type": "Feature",
  "properties": {
    "iso:country":"US",
    "sg:address":"135 McArthur St",
    "sg:city":"Asheboro",
    "sg:classifiers":[
        {
            "category":"Health Services",
            "subcategory":"Doctor",
            "type":"Services"
        }
    ],
    "sg:phone":"+1   ",
    "sg:postcode":"27203",
    "sg:province":"NC",
    "wof:name":"Killiam Harry W Dr",
    "wof:placetype":"venue"
},
  "geometry": {"coordinates":[-79.814288,35.710783],"type":"Point"}
}