{
  "type": "Feature",
  "properties": {
    "addr:full":"1188 McNeill Farm Rd Raeford NC 28376",
    "addr:housenumber":"1188",
    "addr:postcode":"28376",
    "addr:street":"Mcneill Farm Rd",
    "iso:country":"US",
    "sg:address":"1188 McNeill Farm Rd",
    "sg:city":"Raeford",
    "sg:classifiers":[
        {
            "category":"Professional",
            "type":"Services"
        }
    ],
    "sg:phone":"+1 910 848 1464",
    "sg:postcode":"28376",
    "sg:province":"NC",
    "wof:name":"Community Residential Svc",
    "wof:placetype":"venue"
},
  "geometry": {"coordinates":[-79.292334,34.952303],"type":"Point"}
}