{
  "type": "Feature",
  "properties": {
    "addr:full":"301 Hunters Ridge Rd Sanford NC 27332",
    "addr:housenumber":"301",
    "addr:postcode":"27332",
    "addr:street":"Hunters Ridge Rd",
    "iso:country":"US",
    "sg:address":"301 Hunters Ridge Rd",
    "sg:city":"Sanford",
    "sg:classifiers":[
        {
            "category":"Freight",
            "type":"Transportation"
        }
    ],
    "sg:phone":"+1 919 499 1407",
    "sg:postcode":"27332",
    "sg:province":"NC",
    "sg:tags":[
        "operator",
        "local",
        "trucking"
    ],
    "wof:name":"K&M Trucking",
    "wof:placetype":"venue"
},
  "geometry": {"coordinates":[-79.178382,35.327939],"type":"Point"}
}