{
  "type": "Feature",
  "properties": {
    "iso:country":"US",
    "sg:address":"600 E Henry St",
    "sg:city":"Belmont",
    "sg:classifiers":[
        {
            "category":"Building & Trades",
            "subcategory":"Construction",
            "type":"Services"
        }
    ],
    "sg:phone":"+1 704 869 9952",
    "sg:postcode":"28012",
    "sg:province":"NC",
    "sg:tags":[
        "house"
    ],
    "wof:name":"E & M Wallace Construction",
    "wof:placetype":"venue"
},
  "geometry": {"coordinates":[-81.02480199999999,35.271114],"type":"Point"}
}