{
  "type": "Feature",
  "properties": {
    "iso:country":"US",
    "sg:address":"531 Old US Hwy 70",
    "sg:city":"Swannanoa",
    "sg:classifiers":[
        {
            "category":"Food & Beverages",
            "subcategory":"Groceries & Convenience Stores",
            "type":"Retail Goods"
        }
    ],
    "sg:phone":"+1 828 686 8888",
    "sg:postcode":"28778",
    "sg:province":"NC",
    "wof:name":"Lee's Food Stores",
    "wof:placetype":"venue"
},
  "geometry": {"coordinates":[-82.389426,35.604249],"type":"Point"}
}