{
  "type": "Feature",
  "properties": {
    "iso:country":"US",
    "sg:address":"1226 Yorkshire Dr",
    "sg:city":"High Point",
    "sg:classifiers":[
        {
            "category":"Wholesale",
            "subcategory":"Furniture",
            "type":"Manufacturing & Wholesale Goods"
        }
    ],
    "sg:phone":"+1 336 882 4880",
    "sg:postcode":"27262",
    "sg:province":"NC",
    "wof:name":"K R Owens Associates",
    "wof:placetype":"venue"
},
  "geometry": {"coordinates":[-80.039962,35.966153],"type":"Point"}
}