{
  "type": "Feature",
  "properties": {
    "iso:country":"US",
    "sg:address":"803 High Meadow Ln",
    "sg:city":"Charlotte",
    "sg:classifiers":[
        {
            "category":"Professional",
            "subcategory":"Computer Services",
            "type":"Services"
        }
    ],
    "sg:phone":"+1 704 527 8272",
    "sg:postcode":"28217",
    "sg:province":"NC",
    "sg:tags":[
        "internet"
    ],
    "wof:name":"Vivid Effects",
    "wof:placetype":"venue"
},
  "geometry": {"coordinates":[-80.89179900000001,35.147047],"type":"Point"}
}