{
  "type": "Feature",
  "properties": {
    "iso:country":"US",
    "sg:address":"154 Bass Lake Rd",
    "sg:city":"South Mills",
    "sg:classifiers":[
        {
            "category":"Farming",
            "subcategory":"Farm",
            "type":"Manufacturing & Wholesale Goods"
        }
    ],
    "sg:phone":"+1 252 771 5759",
    "sg:postcode":"27976",
    "sg:province":"NC",
    "sg:tags":[
        "crop",
        "general"
    ],
    "wof:name":"Judy B Old",
    "wof:placetype":"venue"
},
  "geometry": {"coordinates":[-76.283636,36.435534],"type":"Point"}
}