{
  "type": "Feature",
  "properties": {
    "iso:country":"US",
    "sg:address":"330 Kennen Krest Rd",
    "sg:city":"Mocksville",
    "sg:classifiers":[
        {
            "category":"Professional",
            "type":"Services"
        }
    ],
    "sg:phone":"+1 336 998 9391",
    "sg:postcode":"27028",
    "sg:province":"NC",
    "sg:tags":[
        "establishment"
    ],
    "wof:name":"Carter Tennyson Dean",
    "wof:placetype":"venue"
},
  "geometry": {"coordinates":[-80.526293,36.002057],"type":"Point"}
}