{
  "type": "Feature",
  "properties": {
    "iso:country":"US",
    "sg:address":"4909 Bartlett St",
    "sg:city":"Greensboro",
    "sg:classifiers":[
        {
            "category":"Building & Trades",
            "subcategory":"Equipment Rental",
            "type":"Services"
        }
    ],
    "sg:phone":"+1 336 294 8887",
    "sg:postcode":"27409",
    "sg:province":"NC",
    "wof:name":"Associated Scaffolding Co Inc",
    "wof:placetype":"venue"
},
  "geometry": {"coordinates":[-79.88080100000001,36.062551],"type":"Point"}
}