{
  "type": "Feature",
  "properties": {
    "addr:full":"829 Shoreland Rd Winston Salem NC 27106",
    "addr:housenumber":"829",
    "addr:postcode":"27106",
    "addr:street":"Shoreland Rd",
    "iso:country":"US",
    "sg:address":"829 Shoreland Rd",
    "sg:city":"Winston Salem",
    "sg:classifiers":[
        {
            "category":"Wholesale",
            "subcategory":"Construction Materials",
            "type":"Manufacturing & Wholesale Goods"
        }
    ],
    "sg:phone":"+1 336 748 1493",
    "sg:postcode":"27106",
    "sg:province":"NC",
    "sg:tags":[
        "broker",
        "drawers",
        "wood",
        "plywood",
        "dimension",
        "block"
    ],
    "wof:name":"Reco Sales",
    "wof:placetype":"venue"
},
  "geometry": {"coordinates":[-80.299684,36.111918],"type":"Point"}
}