{
  "type": "Feature",
  "properties": {
    "addr:full":"800 Briar Creek Rd Charlotte NC 28205",
    "addr:housenumber":"800",
    "addr:postcode":"28205",
    "addr:street":"Briar Creek Rd",
    "iso:country":"US",
    "sg:address":"800 Briar Creek Rd",
    "sg:city":"Charlotte",
    "sg:classifiers":[
        {
            "category":"Professional",
            "subcategory":"Art Services",
            "type":"Services"
        }
    ],
    "sg:phone":"+1 704 377 8550",
    "sg:postcode":"28205",
    "sg:province":"NC",
    "sg:tags":[
        "commercial",
        "graphic",
        "design"
    ],
    "wof:name":"Darling Dsign Illustration LLC",
    "wof:placetype":"venue"
},
  "geometry": {"coordinates":[-80.799409,35.207096],"type":"Point"}
}