{
  "type": "Feature",
  "properties": {
    "iso:country":"US",
    "sg:address":"1402 Dellwood Rd",
    "sg:city":"Waynesville",
    "sg:classifiers":[
        {
            "category":"Building & Trades",
            "subcategory":"Construction",
            "type":"Services"
        }
    ],
    "sg:phone":"+1 828 926 9669",
    "sg:postcode":"28786",
    "sg:province":"NC",
    "sg:tags":[
        "contractor"
    ],
    "wof:name":"Structures Inc Nc",
    "wof:placetype":"venue"
},
  "geometry": {"coordinates":[-82.989188,35.526176],"type":"Point"}
}