{
  "type": "Feature",
  "properties": {
    "iso:country":"US",
    "sg:address":"3503 Wedgewood Dr",
    "sg:city":"Trent Woods",
    "sg:classifiers":[
        {
            "category":"Wholesale",
            "subcategory":"Medical Equipment & Supplies",
            "type":"Manufacturing & Wholesale Goods"
        }
    ],
    "sg:phone":"+1 252 636 2992",
    "sg:postcode":"28562",
    "sg:province":"NC",
    "sg:tags":[
        "therapy",
        "physical"
    ],
    "wof:name":"Spectrum Therapy",
    "wof:placetype":"venue"
},
  "geometry": {"coordinates":[-77.07748100000001,35.078059],"type":"Point"}
}