{
  "type": "Feature",
  "properties": {
    "iso:country":"US",
    "sg:address":"601 E New Bern Rd",
    "sg:city":"Kinston",
    "sg:classifiers":[
        {
            "category":"Restaurant",
            "type":"Food & Drink"
        }
    ],
    "sg:menulink":"http://www.allmenus.com/nc/neuse/191165-burger-king/menu/",
    "sg:phone":"+1 252 523 6490",
    "sg:postcode":"28504",
    "sg:province":"NC",
    "sg:tags":[
        "burger",
        "american"
    ],
    "wof:name":"Burger King",
    "wof:placetype":"venue"
},
  "geometry": {"coordinates":[-77.575738,35.239005],"type":"Point"}
}