{
  "type": "Feature",
  "properties": {
    "addr:full":"431 Mine Branch Rd Blowing Rock NC 28605",
    "addr:housenumber":"431",
    "addr:postcode":"28605",
    "addr:street":"Mine Branch Rd",
    "iso:country":"US",
    "sg:address":"431 Mine Branch Rd",
    "sg:city":"Blowing Rock",
    "sg:classifiers":[
        {
            "category":"Wholesale",
            "subcategory":"Office Equipment",
            "type":"Manufacturing & Wholesale Goods"
        }
    ],
    "sg:phone":"+1 828 268 0097",
    "sg:postcode":"28605",
    "sg:province":"NC",
    "sg:tags":[
        "dictating",
        "machine",
        "supply"
    ],
    "sg:website":"www.dictaphone.com",
    "wof:name":"Dictaphone Corp",
    "wof:placetype":"venue"
},
  "geometry": {"coordinates":[-81.6412,36.182671],"type":"Point"}
}