{
  "type": "Feature",
  "properties": {
    "iso:country":"US",
    "sg:address":"402 E Russell St",
    "sg:city":"Fayetteville",
    "sg:classifiers":[
        {
            "category":"Wholesale",
            "subcategory":"Electrical",
            "type":"Manufacturing & Wholesale Goods"
        }
    ],
    "sg:phone":"+1 910 483 9119",
    "sg:postcode":"28301",
    "sg:province":"NC",
    "sg:tags":[
        "communication",
        "radio",
        "system"
    ],
    "wof:name":"Piedmont Communications Co",
    "wof:placetype":"venue"
},
  "geometry": {"coordinates":[-78.872186,35.048123],"type":"Point"}
}