{
  "type": "Feature",
  "properties": {
    "iso:country":"US",
    "sg:address":"3900 Westinghouse Blvd",
    "sg:city":"Charlotte",
    "sg:classifiers":[
        {
            "category":"Professional",
            "type":"Services"
        }
    ],
    "sg:phone":"+1 704 588 9477",
    "sg:postcode":"28273",
    "sg:province":"NC",
    "sg:tags":[
        "establishment"
    ],
    "wof:name":"Boston Gear",
    "wof:placetype":"venue"
},
  "geometry": {"coordinates":[-80.971182,35.133848],"type":"Point"}
}