{
  "type": "Feature",
  "properties": {
    "addr:full":"1330 Ashleybrook Ln Winston Salem NC 27103",
    "addr:housenumber":"1330",
    "addr:postcode":"27103",
    "addr:street":"Ashleybrook Ln",
    "iso:country":"US",
    "sg:address":"1330 Ashleybrook Ln",
    "sg:city":"Winston Salem",
    "sg:classifiers":[
        {
            "category":"Health Services",
            "subcategory":"Optometrist",
            "type":"Services"
        }
    ],
    "sg:phone":"+1 336 774 1770",
    "sg:postcode":"27103",
    "sg:province":"NC",
    "wof:name":"Sports Performance Center",
    "wof:placetype":"venue"
},
  "geometry": {"coordinates":[-80.311769,36.074794],"type":"Point"}
}