{
  "type": "Feature",
  "properties": {
    "addr:full":"8442 Buffalo Rd Selma NC 27576",
    "addr:housenumber":"8442",
    "addr:postcode":"27576",
    "addr:street":"Buffalo Rd",
    "iso:country":"US",
    "sg:address":"8442 Buffalo Rd",
    "sg:city":"Selma",
    "sg:classifiers":[
        {
            "category":"Wholesale",
            "subcategory":"Farm Supplies",
            "type":"Manufacturing & Wholesale Goods"
        }
    ],
    "sg:phone":"+1 919 965 6511",
    "sg:postcode":"27576",
    "sg:province":"NC",
    "sg:tags":[
        "livestock"
    ],
    "wof:name":"Twin Pines Farms",
    "wof:placetype":"venue"
},
  "geometry": {"coordinates":[-78.317374,35.609095],"type":"Point"}
}