{
  "type": "Feature",
  "properties": {
    "addr:full":"260 Avery Rd New Bern NC 28560",
    "addr:housenumber":"260",
    "addr:postcode":"28560",
    "addr:street":"Avery Rd",
    "iso:country":"US",
    "sg:address":"260 Avery Rd",
    "sg:city":"New Bern",
    "sg:classifiers":[
        {
            "category":"Building & Trades",
            "subcategory":"Plumbing",
            "type":"Services"
        }
    ],
    "sg:phone":"+1 252 633 2186",
    "sg:postcode":"28560",
    "sg:province":"NC",
    "sg:tags":[
        "conditioning",
        "air",
        "system",
        "contractor"
    ],
    "wof:name":"Hardison Heating & Air Cond Co",
    "wof:placetype":"venue"
},
  "geometry": {"coordinates":[-77.042463,35.151438],"type":"Point"}
}