{
  "type": "Feature",
  "properties": {
    "iso:country":"US",
    "sg:address":"103 W 5th St",
    "sg:city":"Tabor City",
    "sg:classifiers":[
        {
            "category":"Personal",
            "subcategory":"Beauty Salon",
            "type":"Services"
        }
    ],
    "sg:phone":"+1 910 653 2355",
    "sg:postcode":"28463",
    "sg:province":"NC",
    "wof:name":"Fifth & Main",
    "wof:placetype":"venue"
},
  "geometry": {"coordinates":[-78.879189,34.14859],"type":"Point"}
}