{
  "type": "Feature",
  "properties": {
    "iso:country":"US",
    "sg:address":"702 Bat Cave Rd",
    "sg:city":"Old Fort",
    "sg:classifiers":[
        {
            "category":"Food & Beverages",
            "subcategory":"Groceries & Convenience Stores",
            "type":"Retail Goods"
        }
    ],
    "sg:phone":"+1 828 668 0452",
    "sg:postcode":"28762",
    "sg:province":"NC",
    "wof:name":"K Max Grocery",
    "wof:placetype":"venue"
},
  "geometry": {"coordinates":[-82.178302,35.619847],"type":"Point"}
}