{
  "type": "Feature",
  "properties": {
    "iso:country":"US",
    "sg:address":"11911 US Hwy 70 W",
    "sg:city":"Clayton",
    "sg:classifiers":[
        {
            "category":"Shopping",
            "subcategory":"Pharmacy",
            "type":"Retail Goods"
        }
    ],
    "sg:phone":"+1 919 359 2900",
    "sg:postcode":"27520",
    "sg:province":"NC",
    "wof:name":"CVS",
    "wof:placetype":"venue"
},
  "geometry": {"coordinates":[-78.479536,35.657122],"type":"Point"}
}