{
  "type": "Feature",
  "properties": {
    "addr:full":"601 S Meadow Rd Raleigh NC 27603",
    "addr:housenumber":"601",
    "addr:postcode":"27603",
    "addr:street":"S Meadow Rd",
    "iso:country":"US",
    "sg:address":"601 S Meadow Rd",
    "sg:city":"Raleigh",
    "sg:classifiers":[
        {
            "category":"Bars & Pubs",
            "type":"Food & Drink"
        }
    ],
    "sg:phone":"+1 919 773 8324",
    "sg:postcode":"27603",
    "sg:province":"NC",
    "sg:tags":[
        "drinking"
    ],
    "wof:name":"Noel Chase",
    "wof:placetype":"venue"
},
  "geometry": {"coordinates":[-78.639031,35.623905],"type":"Point"}
}