{
  "type": "Feature",
  "properties": {
    "iso:country":"US",
    "sg:address":"105 Blackford Ct",
    "sg:city":"Durham",
    "sg:classifiers":[
        {
            "category":"Building & Trades",
            "subcategory":"Construction",
            "type":"Services"
        }
    ],
    "sg:phone":"+1 919 620 0299",
    "sg:postcode":"27712",
    "sg:province":"NC",
    "sg:tags":[
        "house",
        "contractor"
    ],
    "wof:name":"Ken Huff Builders Inc",
    "wof:placetype":"venue"
},
  "geometry": {"coordinates":[-78.859056,36.129216],"type":"Point"}
}