{
  "type": "Feature",
  "properties": {
    "addr:full":"411 Hardy Ave New Bern NC 28560",
    "addr:housenumber":"411",
    "addr:postcode":"28560",
    "addr:street":"Hardy Ave",
    "iso:country":"US",
    "sg:address":"411 Hardy Ave",
    "sg:city":"New Bern",
    "sg:classifiers":[
        {
            "category":"Retail",
            "subcategory":"Auto Repair",
            "type":"Services"
        }
    ],
    "sg:phone":"+1 252 638 1731",
    "sg:postcode":"28560",
    "sg:province":"NC",
    "sg:tags":[
        "repairing",
        "automobile"
    ],
    "wof:name":"Jimmy's Auto & Truck Repair",
    "wof:placetype":"venue"
},
  "geometry": {"coordinates":[-77.014753,35.055637],"type":"Point"}
}