{
  "type": "Feature",
  "properties": {
    "addr:full":"3718 Selwyn Ave Charlotte NC 28209",
    "addr:housenumber":"3718",
    "addr:postcode":"28209",
    "addr:street":"Selwyn Ave",
    "iso:country":"US",
    "sg:address":"3718 Selwyn Ave",
    "sg:city":"Charlotte",
    "sg:classifiers":[
        {
            "category":"Building & Trades",
            "subcategory":"Construction",
            "type":"Services"
        }
    ],
    "sg:phone":"+1 704 523 6521",
    "sg:postcode":"28209",
    "sg:province":"NC",
    "sg:tags":[
        "contractor"
    ],
    "wof:name":"David Tyson & Associates Inc",
    "wof:placetype":"venue"
},
  "geometry": {"coordinates":[-80.848488,35.159432],"type":"Point"}
}