{
  "type": "Feature",
  "properties": {
    "iso:country":"US",
    "sg:address":"1670 Lemuel Black Rd",
    "sg:city":"Bunnlevel",
    "sg:classifiers":[
        {
            "category":"Building & Trades",
            "subcategory":"Landscaping Services",
            "type":"Services"
        }
    ],
    "sg:phone":"+1 910 893 2746",
    "sg:postcode":"28323",
    "sg:province":"NC",
    "wof:name":"B & M Backhoe and Landscaping",
    "wof:placetype":"venue"
},
  "geometry": {"coordinates":[-78.941463,35.286609],"type":"Point"}
}