{
  "type": "Feature",
  "properties": {
    "addr:full":"2315 Mountain Laurel Trl Morganton NC 28655",
    "addr:housenumber":"2315",
    "addr:postcode":"28655",
    "addr:street":"Mountain Laurel Trl",
    "iso:country":"US",
    "sg:address":"2315 Mountain Laurel Trl",
    "sg:city":"Morganton",
    "sg:classifiers":[
        {
            "category":"Manufacturing",
            "subcategory":"Lumber",
            "type":"Manufacturing & Wholesale Goods"
        }
    ],
    "sg:phone":"+1 828 437 2310",
    "sg:postcode":"28655",
    "sg:province":"NC",
    "sg:tags":[
        "forestry",
        "forester",
        "surveying"
    ],
    "wof:name":"Saunders C J Land Timber & Sur",
    "wof:placetype":"venue"
},
  "geometry": {"coordinates":[-81.80256199999999,35.815197],"type":"Point"}
}