{
  "type": "Feature",
  "properties": {
    "iso:country":"US",
    "sg:address":"407 W Main St",
    "sg:city":"Magnolia",
    "sg:classifiers":[
        {
            "category":"Organizations",
            "subcategory":"Religious Organization",
            "type":"Services"
        }
    ],
    "sg:phone":"+1 910 289 9425",
    "sg:postcode":"28453",
    "sg:province":"NC",
    "sg:tags":[
        "church"
    ],
    "wof:name":"Magnolia United Methodist Chr",
    "wof:placetype":"venue"
},
  "geometry": {"coordinates":[-78.059119,34.895244],"type":"Point"}
}