{
  "type": "Feature",
  "properties": {
    "iso:country":"US",
    "sg:address":"236 Charlotte Rd",
    "sg:city":"Rutherfordton",
    "sg:classifiers":[
        {
            "category":"Health Services",
            "subcategory":"Doctor",
            "type":"Services"
        }
    ],
    "sg:phone":"+1 828 287 8861",
    "sg:postcode":"28139",
    "sg:province":"NC",
    "sg:tags":[
        "physician",
        "surgeon"
    ],
    "wof:name":"Raintree Clinic",
    "wof:placetype":"venue"
},
  "geometry": {"coordinates":[-81.95211,35.364574],"type":"Point"}
}