{
  "type": "Feature",
  "properties": {
    "iso:country":"US",
    "sg:address":"133 Person St",
    "sg:city":"Fayetteville",
    "sg:classifiers":[
        {
            "category":"Home & Garden",
            "subcategory":"Carpets & Floor Coverings",
            "type":"Retail Goods"
        },
        {
            "category":"Building & Trades",
            "subcategory":"Construction",
            "type":"Services"
        }
    ],
    "sg:phone":"+1 910 484 7680",
    "sg:postcode":"28301",
    "sg:province":"NC",
    "sg:tags":[
        "dealer",
        "laying",
        "rug",
        "contractor"
    ],
    "wof:name":"E & M Carpet Vinyl Service",
    "wof:placetype":"venue"
},
  "geometry": {"coordinates":[-78.87670199999999,35.052118],"type":"Point"}
}