{
  "type": "Feature",
  "properties": {
    "iso:country":"US",
    "sg:address":"916 E Webb Ave",
    "sg:city":"Burlington",
    "sg:classifiers":[
        {
            "category":"Autos & Motor Vehicles",
            "subcategory":"Automobile Sales",
            "type":"Retail Goods"
        }
    ],
    "sg:phone":"+1 336 229 0200",
    "sg:postcode":"27217",
    "sg:province":"NC",
    "sg:tags":[
        "car",
        "used",
        "dealer"
    ],
    "wof:name":"Midway Auto Sales",
    "wof:placetype":"venue"
},
  "geometry": {"coordinates":[-79.426619,36.084953],"type":"Point"}
}