{
  "type": "Feature",
  "properties": {
    "addr:full":"1013 Parkwood Dr Siler City NC 27344",
    "addr:housenumber":"1013",
    "addr:postcode":"27344",
    "addr:street":"Parkwood Dr",
    "iso:country":"US",
    "sg:address":"1013 Parkwood Dr",
    "sg:city":"Siler City",
    "sg:classifiers":[
        {
            "category":"Building & Trades",
            "subcategory":"Construction",
            "type":"Services"
        }
    ],
    "sg:phone":"+1 919 663 3156",
    "sg:postcode":"27344",
    "sg:province":"NC",
    "sg:tags":[
        "residential"
    ],
    "wof:name":"Ls Construction",
    "wof:placetype":"venue"
},
  "geometry": {"coordinates":[-79.484374,35.728643],"type":"Point"}
}