{
  "type": "Feature",
  "properties": {
    "iso:country":"US",
    "sg:address":"513 E Main St",
    "sg:city":"Havelock",
    "sg:classifiers":[
        {
            "category":"Shopping",
            "subcategory":"Tobacco",
            "type":"Retail Goods"
        }
    ],
    "sg:phone":"+1 252 447 8646",
    "sg:postcode":"28532",
    "sg:province":"NC",
    "sg:tags":[
        "product"
    ],
    "wof:name":"Express Way",
    "wof:placetype":"venue"
},
  "geometry": {"coordinates":[-76.901093,34.870395],"type":"Point"}
}