{
  "type": "Feature",
  "properties": {
    "addr:full":"5601 Spring Pines Way Raleigh NC 27616",
    "addr:housenumber":"5601",
    "addr:postcode":"27616",
    "addr:street":"Spring Pines Way",
    "iso:country":"US",
    "sg:address":"5601 Spring Pines Way",
    "sg:city":"Raleigh",
    "sg:classifiers":[
        {
            "category":"Building & Trades",
            "subcategory":"Construction",
            "type":"Services"
        }
    ],
    "sg:phone":"+1 919 855 9922",
    "sg:postcode":"27616",
    "sg:province":"NC",
    "sg:tags":[
        "designer",
        "dealer",
        "pool",
        "swimming"
    ],
    "wof:name":"Springs Pines Hoa Pool",
    "wof:placetype":"venue"
},
  "geometry": {"coordinates":[-78.565067,35.854406],"type":"Point"}
}