{
  "type": "Feature",
  "properties": {
    "iso:country":"US",
    "sg:address":"133 W Franklin St Ste B",
    "sg:city":"Chapel Hill",
    "sg:classifiers":[
        {
            "category":"Shopping",
            "subcategory":"Clothing, Apparel, & Fashions",
            "type":"Retail Goods"
        }
    ],
    "sg:phone":"+1 919 932 9280",
    "sg:postcode":"27516",
    "sg:province":"NC",
    "sg:tags":[
        "clothing",
        "women's"
    ],
    "sg:website":"www.appleboutique.com",
    "wof:name":"Apple Boutique",
    "wof:placetype":"venue"
},
  "geometry": {"coordinates":[-79.05744900000001,35.912505],"type":"Point"}
}