{
  "type": "Feature",
  "properties": {
    "addr:full":"548 State Hwy 801 Advance NC 27006",
    "addr:housenumber":"548",
    "addr:postcode":"27006",
    "addr:street":"State Hwy 801",
    "iso:country":"US",
    "sg:address":"548 State Hwy 801",
    "sg:city":"Advance",
    "sg:classifiers":[
        {
            "category":"Wholesale",
            "subcategory":"Groceries",
            "type":"Manufacturing & Wholesale Goods"
        }
    ],
    "sg:phone":"+1 336 998 0277",
    "sg:postcode":"27006",
    "sg:province":"NC",
    "sg:tags":[
        "baker"
    ],
    "wof:name":"Sara Lee Knit Products",
    "wof:placetype":"venue"
},
  "geometry": {"coordinates":[-80.433897,35.989652],"type":"Point"}
}