{
  "type": "Feature",
  "properties": {
    "addr:full":"6300 Countryside Dr Apt 7 Charlotte NC 28213",
    "addr:housenumber":"6300;7",
    "addr:postcode":"28213",
    "addr:street":"Countryside Dr Apt",
    "iso:country":"US",
    "sg:address":"6300 Countryside Dr Apt 7",
    "sg:city":"Charlotte",
    "sg:classifiers":[
        {
            "category":"Home & Garden",
            "subcategory":"Building Materials",
            "type":"Retail Goods"
        },
        {
            "category":"Building & Trades",
            "subcategory":"Construction",
            "type":"Services"
        }
    ],
    "sg:phone":"+1 704 281 7603",
    "sg:postcode":"28213",
    "sg:province":"NC",
    "sg:tags":[
        "concrete",
        "staining",
        "contractor"
    ],
    "wof:name":"Mnm Stucco & Concrete Co",
    "wof:placetype":"venue"
},
  "geometry": {"coordinates":[-80.76966899999999,35.27335],"type":"Point"}
}