{
  "type": "Feature",
  "properties": {
    "addr:full":"2720 Voncannon Farm Rd Asheboro NC 27205",
    "addr:housenumber":"2720",
    "addr:postcode":"27205",
    "addr:street":"Voncannon Farm Rd",
    "iso:country":"US",
    "sg:address":"2720 Voncannon Farm Rd",
    "sg:city":"Asheboro",
    "sg:classifiers":[
        {
            "category":"Building & Trades",
            "subcategory":"Construction",
            "type":"Services"
        }
    ],
    "sg:phone":"+1 336 381 3875",
    "sg:postcode":"27205",
    "sg:province":"NC",
    "sg:tags":[
        "residential",
        "general",
        "contractor"
    ],
    "wof:name":"William L Moffitt Jr Gen Contr",
    "wof:placetype":"venue"
},
  "geometry": {"coordinates":[-79.90975899999999,35.579967],"type":"Point"}
}