{
  "type": "Feature",
  "properties": {
    "addr:full":"7208 Vixen Ct Raleigh NC 27616",
    "addr:housenumber":"7208",
    "addr:postcode":"27616",
    "addr:street":"Vixen Ct",
    "iso:country":"US",
    "sg:address":"7208 Vixen Ct",
    "sg:city":"Raleigh",
    "sg:classifiers":[
        {
            "category":"Health Services",
            "subcategory":"Clinic",
            "type":"Services"
        }
    ],
    "sg:phone":"+1 919 872 5999",
    "sg:postcode":"27616",
    "sg:province":"NC",
    "sg:tags":[
        "home"
    ],
    "wof:name":"Agape Health Care Svc",
    "wof:placetype":"venue"
},
  "geometry": {"coordinates":[-78.552256,35.875349],"type":"Point"}
}