{
  "type": "Feature",
  "properties": {
    "iso:country":"US",
    "sg:address":"4330 Arendell St",
    "sg:city":"Morehead City",
    "sg:classifiers":[
        {
            "category":"Utilities",
            "subcategory":"Mobile Phone",
            "type":"Services"
        }
    ],
    "sg:phone":"+1 252 726 8035",
    "sg:postcode":"28557",
    "sg:province":"NC",
    "sg:tags":[
        "telephone",
        "cellular"
    ],
    "wof:name":"Wireless Co",
    "wof:placetype":"venue"
},
  "geometry": {"coordinates":[-76.77451000000001,34.728979],"type":"Point"}
}