{
  "type": "Feature",
  "properties": {
    "iso:country":"US",
    "sg:address":"653 Old Market Rd",
    "sg:city":"Seaboard",
    "sg:classifiers":[
        {
            "category":"Organizations",
            "subcategory":"Community Association",
            "type":"Services"
        }
    ],
    "sg:phone":"+1 252 589 2005",
    "sg:postcode":"27829",
    "sg:province":"NC",
    "sg:tags":[
        "club"
    ],
    "wof:name":"Seaboard Lions Club",
    "wof:placetype":"venue"
},
  "geometry": {"coordinates":[-77.661677,35.704625],"type":"Point"}
}