{
  "type": "Feature",
  "properties": {
    "addr:full":"11016 Nc Highway 210 Rocky Point NC 28457",
    "addr:housenumber":"11016",
    "addr:postcode":"28457",
    "addr:street":"Nc Highway 210",
    "iso:country":"US",
    "sg:address":"11016 Nc Highway 210",
    "sg:city":"Rocky Point",
    "sg:classifiers":[
        {
            "category":"Restaurant",
            "type":"Food & Drink"
        }
    ],
    "sg:phone":"+1 910 675 3751",
    "sg:postcode":"28457",
    "sg:province":"NC",
    "wof:name":"Lanes Ferry Bait Tackle & Grill",
    "wof:placetype":"venue"
},
  "geometry": {"coordinates":[-77.845001,34.439301],"type":"Point"}
}