{
  "type": "Feature",
  "properties": {
    "addr:full":"34 Pine Crest Ln Southern Pines NC 28445",
    "addr:housenumber":"34",
    "addr:postcode":"28445",
    "addr:street":"Pine Crest Ln",
    "iso:country":"US",
    "sg:address":"34 Pine Crest Ln",
    "sg:city":"Southern Pines",
    "sg:classifiers":[
        {
            "category":"Restaurant",
            "type":"Food & Drink"
        }
    ],
    "sg:phone":"+1 910 692 6787",
    "sg:postcode":"28445",
    "sg:province":"NC",
    "sg:tags":[
        "chinese"
    ],
    "wof:name":"Peking Wok",
    "wof:placetype":"venue"
},
  "geometry": {"coordinates":[-78.49633799999999,34.977457],"type":"Point"}
}