{
  "type": "Feature",
  "properties": {
    "addr:full":"1564 Flowerfield Dr Concord NC 28025",
    "addr:housenumber":"1564",
    "addr:postcode":"28025",
    "addr:street":"Flowerfield Dr",
    "iso:country":"US",
    "sg:address":"1564 Flowerfield Dr",
    "sg:city":"Concord",
    "sg:classifiers":[
        {
            "category":"Retail",
            "subcategory":"Car Wash",
            "type":"Services"
        }
    ],
    "sg:phone":"+1 704 788 7678",
    "sg:postcode":"28025",
    "sg:province":"NC",
    "sg:tags":[
        "carwash",
        "industry",
        "machinery",
        "mfg"
    ],
    "wof:name":"Concord Mobile Wash",
    "wof:placetype":"venue"
},
  "geometry": {"coordinates":[-80.55367099999999,35.448366],"type":"Point"}
}