{
  "type": "Feature",
  "properties": {
    "addr:full":"241 Camelot Dr Morganton NC 28655",
    "addr:housenumber":"241",
    "addr:postcode":"28655",
    "addr:street":"Camelot Dr",
    "iso:country":"US",
    "sg:address":"241 Camelot Dr",
    "sg:city":"Morganton",
    "sg:classifiers":[
        {
            "category":"Real Estate",
            "subcategory":"Real Estate Operator",
            "type":"Services"
        }
    ],
    "sg:phone":"+1 828 437 6597",
    "sg:postcode":"28655",
    "sg:province":"NC",
    "sg:tags":[
        "property",
        "lessor"
    ],
    "wof:name":"Redman Enterprises LLC",
    "wof:placetype":"venue"
},
  "geometry": {"coordinates":[-81.719491,35.765196],"type":"Point"}
}