{
  "type": "Feature",
  "properties": {
    "addr:full":"862 Chatuge Village Cir Hayesville NC 28904",
    "addr:housenumber":"862",
    "addr:postcode":"28904",
    "addr:street":"Chatuge Village Cir",
    "iso:country":"US",
    "sg:address":"862 Chatuge Village Cir",
    "sg:city":"Hayesville",
    "sg:classifiers":[
        {
            "category":"Real Estate",
            "subcategory":"Real Estate Services",
            "type":"Services"
        },
        {
            "category":"Real Estate",
            "subcategory":"Real Estate Agent",
            "type":"Services"
        }
    ],
    "sg:phone":"+1 828 389 2369",
    "sg:postcode":"28904",
    "sg:province":"NC",
    "sg:tags":[
        "buyer",
        "broker"
    ],
    "wof:name":"Appalachian Lakes Realty",
    "wof:placetype":"venue"
},
  "geometry": {"coordinates":[-83.748395,35.030172],"type":"Point"}
}