{
  "type": "Feature",
  "properties": {
    "addr:full":"3413 N Main St Hope Mills NC 28348",
    "addr:housenumber":"3413",
    "addr:postcode":"28348",
    "addr:street":"N Main St",
    "iso:country":"US",
    "sg:address":"3413 N Main St",
    "sg:city":"Hope Mills",
    "sg:classifiers":[
        {
            "category":"Real Estate",
            "subcategory":"Real Estate Agent",
            "type":"Services"
        }
    ],
    "sg:phone":"+1 910 429 2626",
    "sg:postcode":"28348",
    "sg:province":"NC",
    "sg:website":"www.bearcreekonline.com",
    "wof:name":"Bear Creek Realty Inc",
    "wof:placetype":"venue"
},
  "geometry": {"coordinates":[-78.95415199999999,34.977615],"type":"Point"}
}