{
  "type": "Feature",
  "properties": {
    "addr:full":"125 Person St Fayetteville NC 28301",
    "addr:housenumber":"125",
    "addr:postcode":"28301",
    "addr:street":"Person St",
    "iso:country":"US",
    "sg:address":"125 Person St",
    "sg:city":"Fayetteville",
    "sg:classifiers":[
        {
            "category":"Professional",
            "subcategory":"Lawyer & Legal Services",
            "type":"Services"
        }
    ],
    "sg:phone":"+1 910 483 3509",
    "sg:postcode":"28301",
    "sg:province":"NC",
    "sg:tags":[
        "attorney"
    ],
    "wof:name":"Marion C George Jr Atty",
    "wof:placetype":"venue"
},
  "geometry": {"coordinates":[-78.87647800000001,35.052063],"type":"Point"}
}