{
  "type": "Feature",
  "properties": {
    "addr:full":"241 Springs Rd Dallas NC 28034",
    "addr:housenumber":"241",
    "addr:postcode":"28034",
    "addr:street":"Springs Rd",
    "iso:country":"US",
    "sg:address":"241 Springs Rd",
    "sg:city":"Dallas",
    "sg:classifiers":[
        {
            "category":"Wholesale",
            "subcategory":"Machinery & Supplies",
            "type":"Manufacturing & Wholesale Goods"
        }
    ],
    "sg:phone":"+1 704 922 4594",
    "sg:postcode":"28034",
    "sg:province":"NC",
    "sg:tags":[
        "textile",
        "parts"
    ],
    "wof:name":"Ravaco Cam Co",
    "wof:placetype":"venue"
},
  "geometry": {"coordinates":[-81.19838300000001,35.356191],"type":"Point"}
}