{
  "type": "Feature",
  "properties": {
    "iso:country":"US",
    "sg:address":"1101 N William St",
    "sg:city":"Goldsboro",
    "sg:classifiers":[
        {
            "category":"Organizations",
            "subcategory":"Religious Organization",
            "type":"Services"
        }
    ],
    "sg:phone":"+1 919 734 7255",
    "sg:postcode":"27530",
    "sg:province":"NC",
    "sg:tags":[
        "church"
    ],
    "wof:name":"Higher Elevation Ministries",
    "wof:placetype":"venue"
},
  "geometry": {"coordinates":[-77.987194,35.397446],"type":"Point"}
}