{
  "type": "Feature",
  "properties": {
    "addr:full":"171 Sand Hill School Rd Candler NC 28715",
    "addr:housenumber":"171",
    "addr:postcode":"28715",
    "addr:street":"Sand Hill School Rd",
    "iso:country":"US",
    "sg:address":"171 Sand Hill School Rd",
    "sg:city":"Candler",
    "sg:classifiers":[
        {
            "category":"Education",
            "subcategory":"Preschool",
            "type":"Public Place"
        },
        {
            "category":"Education",
            "subcategory":"School",
            "type":"Public Place"
        }
    ],
    "sg:phone":"+1 828 665 4302",
    "sg:postcode":"28715",
    "sg:province":"NC",
    "sg:tags":[
        "elementary"
    ],
    "wof:name":"Church Acton United Methodist",
    "wof:placetype":"venue"
},
  "geometry": {"coordinates":[-82.647102,35.557999],"type":"Point"}
}