{
  "type": "Feature",
  "properties": {
    "iso:country":"US",
    "sg:address":"4235 Princess Place Dr",
    "sg:city":"Wilmington",
    "sg:classifiers":[
        {
            "category":"Retail",
            "subcategory":"Auto Repair",
            "type":"Services"
        }
    ],
    "sg:phone":"+1 910 762 7721",
    "sg:postcode":"28405",
    "sg:province":"NC",
    "sg:tags":[
        "muffler",
        "exhaust",
        "system"
    ],
    "wof:name":"Midas Auto Svc Experts",
    "wof:placetype":"venue"
},
  "geometry": {"coordinates":[-77.89228300000001,34.242621],"type":"Point"}
}