{
  "type": "Feature",
  "properties": {
    "addr:full":"5900 Timber Creek Ln Raleigh NC 27612",
    "addr:housenumber":"5900",
    "addr:postcode":"27612",
    "addr:street":"Timber Creek Ln",
    "iso:country":"US",
    "sg:address":"5900 Timber Creek Ln",
    "sg:city":"Raleigh",
    "sg:classifiers":[
        {
            "category":"Professional",
            "subcategory":"Business Services",
            "type":"Services"
        }
    ],
    "sg:phone":"+1 919 940 0744",
    "sg:postcode":"27612",
    "sg:province":"NC",
    "sg:tags":[
        "music"
    ],
    "wof:name":"RG Records",
    "wof:placetype":"venue"
},
  "geometry": {"coordinates":[-78.695864,35.862342],"type":"Point"}
}