{
  "type": "Feature",
  "properties": {
    "iso:country":"US",
    "sg:address":"3110 Raeford Rd",
    "sg:city":"Fayetteville",
    "sg:classifiers":[
        {
            "category":"Restaurant",
            "type":"Food & Drink"
        }
    ],
    "sg:phone":"+1 910 485 3777",
    "sg:postcode":"28303",
    "sg:province":"NC",
    "sg:tags":[
        "eating"
    ],
    "wof:name":"Hardees",
    "wof:placetype":"venue"
},
  "geometry": {"coordinates":[-78.932885,35.044663],"type":"Point"}
}