{
  "type": "Feature",
  "properties": {
    "addr:full":"414 S Jefferson Ave West Jefferson NC 28694",
    "addr:housenumber":"414",
    "addr:postcode":"28694",
    "addr:street":"S Jefferson Ave",
    "iso:country":"US",
    "sg:address":"414 S Jefferson Ave",
    "sg:city":"West Jefferson",
    "sg:classifiers":[
        {
            "category":"Autos & Motor Vehicles",
            "subcategory":"Automobile Sales",
            "type":"Retail Goods"
        }
    ],
    "sg:phone":"+1 336 846 3166",
    "sg:postcode":"28694",
    "sg:province":"NC",
    "sg:tags":[
        "car",
        "dealer"
    ],
    "wof:name":"Paisleys Auto Sales",
    "wof:placetype":"venue"
},
  "geometry": {"coordinates":[-81.491038,36.39873],"type":"Point"}
}