{
  "type": "Feature",
  "properties": {
    "addr:full":"3041 Spoons Chapel Rd Asheboro NC 27205",
    "addr:postcode":"3041;27205",
    "addr:street":"Chapel Rd",
    "iso:country":"US",
    "sg:address":"3041 Spoons Chapel Rd",
    "sg:city":"Asheboro",
    "sg:classifiers":[
        {
            "category":"Freight",
            "type":"Transportation"
        }
    ],
    "sg:phone":"+1 336 629 8297",
    "sg:postcode":"27205",
    "sg:province":"NC",
    "sg:tags":[
        "operator",
        "local",
        "trucking"
    ],
    "wof:name":"Queens Hauling",
    "wof:placetype":"venue"
},
  "geometry": {"coordinates":[-79.721885,35.670398],"type":"Point"}
}