{
  "type": "Feature",
  "properties": {
    "addr:full":"139 Tunnel Rd Asheville NC 28805",
    "addr:housenumber":"139",
    "addr:postcode":"28805",
    "addr:street":"Tunnel Rd",
    "iso:country":"US",
    "sg:address":"139 Tunnel Rd",
    "sg:city":"Asheville",
    "sg:classifiers":[
        {
            "category":"Restaurant",
            "type":"Food & Drink"
        }
    ],
    "sg:menulink":"http://www.allmenus.com/nc/asheville/127870-red-lobster/menu/",
    "sg:phone":"+1 828 350 7773",
    "sg:postcode":"28805",
    "sg:province":"NC",
    "sg:tags":[
        "seafood",
        "american"
    ],
    "wof:name":"Red Lobster",
    "wof:placetype":"venue"
},
  "geometry": {"coordinates":[-82.530418,35.590999],"type":"Point"}
}