{
  "type": "Feature",
  "properties": {
    "addr:full":"215 Oak Ave Spruce Pine NC 28777",
    "addr:housenumber":"215",
    "addr:postcode":"28777",
    "addr:street":"Oak Ave",
    "iso:country":"US",
    "sg:address":"215 Oak Ave",
    "sg:city":"Spruce Pine",
    "sg:classifiers":[
        {
            "category":"Social Services",
            "type":"Services"
        }
    ],
    "sg:phone":"+1 828 765 9980",
    "sg:postcode":"28777",
    "sg:province":"NC",
    "sg:tags":[
        "organization",
        "welfare"
    ],
    "wof:name":"Service Center For Latinos",
    "wof:placetype":"venue"
},
  "geometry": {"coordinates":[-82.069667,35.916673],"type":"Point"}
}