{
  "type": "Feature",
  "properties": {
    "addr:full":"3842 US Hwy 74 Monroe NC 28110",
    "addr:housenumber":"3842",
    "addr:postcode":"28110",
    "addr:street":"Us Hwy 74",
    "iso:country":"US",
    "sg:address":"3842 US Hwy 74",
    "sg:city":"Monroe",
    "sg:classifiers":[
        {
            "category":"Autos & Motor Vehicles",
            "subcategory":"Automobile Sales",
            "type":"Retail Goods"
        }
    ],
    "sg:phone":"+1 704 261 0080",
    "sg:postcode":"28110",
    "sg:province":"NC",
    "sg:tags":[
        "car",
        "dealer"
    ],
    "sg:website":"www.autopalace.com",
    "wof:name":"AUTOPALACE.COM",
    "wof:placetype":"venue"
},
  "geometry": {"coordinates":[-80.593941,35.032298],"type":"Point"}
}