{
  "type": "Feature",
  "properties": {
    "addr:full":"8301 Knights Bridge Rd Charlotte NC 28210",
    "addr:housenumber":"8301",
    "addr:postcode":"28210",
    "addr:street":"Knights Bridge Rd",
    "iso:country":"US",
    "sg:address":"8301 Knights Bridge Rd",
    "sg:city":"Charlotte",
    "sg:classifiers":[
        {
            "category":"Professional",
            "subcategory":"Business Services",
            "type":"Services"
        }
    ],
    "sg:phone":"+1   ",
    "sg:postcode":"28210",
    "sg:province":"NC",
    "wof:name":"Fire and Dom Backflow Svcs",
    "wof:placetype":"venue"
},
  "geometry": {"coordinates":[-80.87187299999999,35.115068],"type":"Point"}
}