{
  "type": "Feature",
  "properties": {
    "addr:full":"2203 Hope Mills Rd Fayetteville NC 28304",
    "addr:housenumber":"2203",
    "addr:postcode":"28304",
    "addr:street":"Hope Mills Rd",
    "iso:country":"US",
    "sg:address":"2203 Hope Mills Rd",
    "sg:city":"Fayetteville",
    "sg:classifiers":[
        {
            "category":"Wholesale",
            "subcategory":"Auto Parts",
            "type":"Manufacturing & Wholesale Goods"
        }
    ],
    "sg:phone":"+1 910 429 0300",
    "sg:postcode":"28304",
    "sg:province":"NC",
    "sg:tags":[
        "tire"
    ],
    "wof:name":"Class A Tires",
    "wof:placetype":"venue"
},
  "geometry": {"coordinates":[-78.963674,35.017422],"type":"Point"}
}