{
  "type": "Feature",
  "properties": {
    "iso:country":"US",
    "sg:address":"8254 Galwood Dr",
    "sg:city":"Linden",
    "sg:classifiers":[
        {
            "category":"Building & Trades",
            "subcategory":"Construction",
            "type":"Services"
        }
    ],
    "sg:phone":"+1 910 488 6941",
    "sg:postcode":"28356",
    "sg:province":"NC",
    "sg:tags":[
        "residential"
    ],
    "wof:name":"John Muth Custom Homes",
    "wof:placetype":"venue"
},
  "geometry": {"coordinates":[-78.844814,35.216964],"type":"Point"}
}