{
  "type": "Feature",
  "properties": {
    "addr:full":"835 Abington Rd Lenoir NC 28645",
    "addr:housenumber":"835",
    "addr:postcode":"28645",
    "addr:street":"Abington Rd",
    "iso:country":"US",
    "sg:address":"835 Abington Rd",
    "sg:city":"Lenoir",
    "sg:classifiers":[
        {
            "category":"Recreation",
            "type":"Entertainment"
        }
    ],
    "sg:phone":"+1 828 758 9098",
    "sg:postcode":"28645",
    "sg:province":"NC",
    "sg:tags":[
        "skating",
        "rink"
    ],
    "wof:name":"Roller Palace",
    "wof:placetype":"venue"
},
  "geometry": {"coordinates":[-81.59392800000001,35.908094],"type":"Point"}
}