{
  "type": "Feature",
  "properties": {
    "iso:country":"US",
    "sg:address":"244 Slocomb Rd",
    "sg:city":"Fayetteville",
    "sg:classifiers":[
        {
            "category":"Organizations",
            "subcategory":"Religious Organization",
            "type":"Services"
        }
    ],
    "sg:phone":"+1   ",
    "sg:postcode":"28311",
    "sg:province":"NC",
    "wof:name":"Piney Grove Frwill Bptst Chrch",
    "wof:placetype":"venue"
},
  "geometry": {"coordinates":[-78.853689,35.178808],"type":"Point"}
}