{
  "type": "Feature",
  "properties": {
    "iso:country":"US",
    "sg:address":"1315 Redmon Rd",
    "sg:city":"Cleveland",
    "sg:classifiers":[
        {
            "category":"Retail",
            "subcategory":"Auto Repair",
            "type":"Services"
        }
    ],
    "sg:phone":"+1 704 278 9621",
    "sg:postcode":"27013",
    "sg:province":"NC",
    "sg:tags":[
        "repairing",
        "tire"
    ],
    "wof:name":"RDH Tire & Retreading Co",
    "wof:placetype":"venue"
},
  "geometry": {"coordinates":[-80.667095,35.713321],"type":"Point"}
}