{
  "type": "Feature",
  "properties": {
    "addr:full":"416 Providence Rd Charlotte NC 28207",
    "addr:housenumber":"416",
    "addr:postcode":"28207",
    "addr:street":"Providence Rd",
    "iso:country":"US",
    "sg:address":"416 Providence Rd",
    "sg:city":"Charlotte",
    "sg:classifiers":[
        {
            "category":"Personal",
            "subcategory":"Beauty Salon",
            "type":"Services"
        }
    ],
    "sg:phone":"+1 704 334 5661",
    "sg:postcode":"28207",
    "sg:province":"NC",
    "wof:name":"Studio 416",
    "wof:placetype":"venue"
},
  "geometry": {"coordinates":[-80.824624,35.203951],"type":"Point"}
}