{
  "type": "Feature",
  "properties": {
    "addr:full":"6205 Creek Breeze Rd Charlotte NC 28269",
    "addr:housenumber":"6205",
    "addr:postcode":"28269",
    "addr:street":"Creek Breeze Rd",
    "iso:country":"US",
    "sg:address":"6205 Creek Breeze Rd",
    "sg:city":"Charlotte",
    "sg:classifiers":[
        {
            "category":"Personal",
            "type":"Services"
        }
    ],
    "sg:phone":"+1 704 948 4311",
    "sg:postcode":"28269",
    "sg:province":"NC",
    "sg:tags":[
        "consultant",
        "wedding"
    ],
    "wof:name":"Graceful Creations",
    "wof:placetype":"venue"
},
  "geometry": {"coordinates":[-80.76516599999999,35.373615],"type":"Point"}
}