{
  "type": "Feature",
  "properties": {
    "addr:full":"1441 Morganton Blvd SW Newton NC 28645",
    "addr:housenumber":"1441",
    "addr:postcode":"28645",
    "addr:street":"Morganton Blvd Sw",
    "iso:country":"US",
    "sg:address":"1441 Morganton Blvd SW",
    "sg:city":"Newton",
    "sg:classifiers":[
        {
            "category":"Retail",
            "subcategory":"Auto Repair",
            "type":"Services"
        }
    ],
    "sg:phone":"+1 828 754 8208",
    "sg:postcode":"28645",
    "sg:province":"NC",
    "sg:tags":[
        "repairing",
        "automobile",
        "generator",
        "alternator"
    ],
    "wof:name":"Alternator & Starter Re Bldrs",
    "wof:placetype":"venue"
},
  "geometry": {"coordinates":[-81.547567,35.901059],"type":"Point"}
}