{
  "type": "Feature",
  "properties": {
    "addr:full":"318 Oaklawn Rd Winston Salem NC 27107",
    "addr:housenumber":"318",
    "addr:postcode":"27107",
    "addr:street":"Oaklawn Rd",
    "iso:country":"US",
    "sg:address":"318 Oaklawn Rd",
    "sg:city":"Winston Salem",
    "sg:classifiers":[
        {
            "category":"Professional",
            "subcategory":"Business Services",
            "type":"Services"
        }
    ],
    "sg:phone":"+1   ",
    "sg:postcode":"27107",
    "sg:province":"NC",
    "sg:tags":[
        "transportation",
        "freight"
    ],
    "wof:name":"Johnny Bush Enterprises",
    "wof:placetype":"venue"
},
  "geometry": {"coordinates":[-80.168588,36.009499],"type":"Point"}
}