{
  "type": "Feature",
  "properties": {
    "addr:full":"3000 Arendell St Morehead City NC 28557",
    "addr:postcode":"3000;28557",
    "addr:street":"Arendell St",
    "iso:country":"US",
    "sg:address":"3000 Arendell St",
    "sg:city":"Morehead City",
    "sg:classifiers":[
        {
            "category":"Personal",
            "subcategory":"Beauty Salon",
            "type":"Services"
        }
    ],
    "sg:phone":"+1   ",
    "sg:postcode":"28557",
    "sg:province":"NC",
    "sg:tags":[
        "shop"
    ],
    "wof:name":"Crystal Nails",
    "wof:placetype":"venue"
},
  "geometry": {"coordinates":[-76.74483499999999,34.723949],"type":"Point"}
}