{
  "type": "Feature",
  "properties": {
    "addr:full":"2211 Russell Pope Rd Wingate NC 28174",
    "addr:housenumber":"2211",
    "addr:postcode":"28174",
    "addr:street":"Russell Pope Rd",
    "iso:country":"US",
    "sg:address":"2211 Russell Pope Rd",
    "sg:city":"Wingate",
    "sg:classifiers":[
        {
            "category":"Retail",
            "subcategory":"Auto Repair",
            "type":"Services"
        }
    ],
    "sg:phone":"+1   ",
    "sg:postcode":"28174",
    "sg:province":"NC",
    "sg:tags":[
        "automotive"
    ],
    "wof:name":"Gordons Towing Service",
    "wof:placetype":"venue"
},
  "geometry": {"coordinates":[-80.413765,34.924955],"type":"Point"}
}