{
  "type": "Feature",
  "properties": {
    "iso:country":"US",
    "sg:address":"811 Carrick St",
    "sg:city":"High Point",
    "sg:classifiers":[
        {
            "category":"Shopping",
            "subcategory":"Catalog Store",
            "type":"Retail Goods"
        }
    ],
    "sg:phone":"+1 336 885 3346",
    "sg:postcode":"27262",
    "sg:province":"NC",
    "sg:tags":[
        "internet"
    ],
    "wof:name":"Cat's Cradle Books",
    "wof:placetype":"venue"
},
  "geometry": {"coordinates":[-80.016475,35.966085],"type":"Point"}
}