{
  "type": "Feature",
  "properties": {
    "addr:full":"2409 Farlow Gap Ln Raleigh NC 27603",
    "addr:housenumber":"2409",
    "addr:postcode":"27603",
    "addr:street":"Farlow Gap Ln",
    "iso:country":"US",
    "sg:address":"2409 Farlow Gap Ln",
    "sg:city":"Raleigh",
    "sg:classifiers":[
        {
            "category":"Building & Trades",
            "subcategory":"Construction",
            "type":"Services"
        }
    ],
    "sg:phone":"+1 919 272 0050",
    "sg:postcode":"27603",
    "sg:province":"NC",
    "sg:tags":[
        "builder",
        "patio",
        "deck"
    ],
    "wof:name":"Setting Sun Patios & Decks",
    "wof:placetype":"venue"
},
  "geometry": {"coordinates":[-78.68158699999999,35.749386],"type":"Point"}
}