{
  "type": "Feature",
  "properties": {
    "iso:country":"US",
    "sg:address":"1717 Windmill Dr",
    "sg:city":"Sanford",
    "sg:classifiers":[
        {
            "category":"Professional",
            "type":"Services"
        }
    ],
    "sg:phone":"+1 919 776 5371",
    "sg:postcode":"27330",
    "sg:province":"NC",
    "wof:name":"Woodell Childrens Phone",
    "wof:placetype":"venue"
},
  "geometry": {"coordinates":[-79.212388,35.491413],"type":"Point"}
}