{
  "type": "Feature",
  "properties": {
    "iso:country":"US",
    "sg:address":"6401 Carmel Rd",
    "sg:city":"Charlotte",
    "sg:classifiers":[
        {
            "category":"Manufacturing",
            "subcategory":"Tobacco Products",
            "type":"Manufacturing & Wholesale Goods"
        },
        {
            "category":"Shopping",
            "subcategory":"Tobacco",
            "type":"Retail Goods"
        }
    ],
    "sg:phone":"+1 704 341 5969",
    "sg:postcode":"28226",
    "sg:province":"NC",
    "sg:tags":[
        "cigarette",
        "cigar",
        "manufacturer",
        "tobacco-wholesale"
    ],
    "wof:name":"Tobacco Outlet Business",
    "wof:placetype":"venue"
},
  "geometry": {"coordinates":[-80.844416,35.090695],"type":"Point"}
}