{
  "type": "Feature",
  "properties": {
    "iso:country":"US",
    "sg:address":"2 E South St",
    "sg:city":"Raleigh",
    "sg:classifiers":[
        {
            "category":"Restaurant",
            "type":"Food & Drink"
        }
    ],
    "sg:phone":"+1 919 831 6200",
    "sg:postcode":"27601",
    "sg:province":"NC",
    "sg:tags":[
        "caterer"
    ],
    "sg:website":"www.centerplate.com",
    "wof:name":"Centerplate",
    "wof:placetype":"venue"
},
  "geometry": {"coordinates":[-78.63854499999999,35.772138],"type":"Point"}
}