{
  "type": "Feature",
  "properties": {
    "addr:full":"965 Meadow Ln Henderson NC 27536",
    "addr:housenumber":"965",
    "addr:postcode":"27536",
    "addr:street":"Meadow Ln",
    "iso:country":"US",
    "sg:address":"965 Meadow Ln",
    "sg:city":"Henderson",
    "sg:classifiers":[
        {
            "category":"Building & Trades",
            "subcategory":"Equipment Rental",
            "type":"Services"
        }
    ],
    "sg:phone":"+1   ",
    "sg:postcode":"27536",
    "sg:province":"NC",
    "wof:name":"Bd Leasing Inc",
    "wof:placetype":"venue"
},
  "geometry": {"coordinates":[-78.431444,36.321607],"type":"Point"}
}