{
  "type": "Feature",
  "properties": {
    "iso:country":"US",
    "sg:address":"418 S King St",
    "sg:city":"Laurinburg",
    "sg:classifiers":[
        {
            "category":"Health Services",
            "subcategory":"Doctor",
            "type":"Services"
        }
    ],
    "sg:phone":"+1   ",
    "sg:postcode":"28352",
    "sg:province":"NC",
    "sg:tags":[
        "medical"
    ],
    "wof:name":"Parcelle Clinic",
    "wof:placetype":"venue"
},
  "geometry": {"coordinates":[-79.468205,34.775698],"type":"Point"}
}