{
  "type": "Feature",
  "properties": {
    "iso:country":"US",
    "sg:address":"1409 W Corbett Ave",
    "sg:city":"Swansboro",
    "sg:classifiers":[
        {
            "category":"Banks & Credit Unions",
            "subcategory":"Bank",
            "type":"Services"
        }
    ],
    "sg:phone":"+1 910 326 0134",
    "sg:postcode":"28584",
    "sg:province":"NC",
    "sg:tags":[
        "cashing",
        "check"
    ],
    "wof:name":"Nationwide Money Svc",
    "wof:placetype":"venue"
},
  "geometry": {"coordinates":[-77.15641100000001,34.704707],"type":"Point"}
}