{
  "type": "Feature",
  "properties": {
    "iso:country":"US",
    "sg:address":"110 N Randolph Ave",
    "sg:city":"Asheboro",
    "sg:classifiers":[
        {
            "category":"Shopping",
            "subcategory":"Shoes",
            "type":"Retail Goods"
        }
    ],
    "sg:phone":"+1 336 629 4922",
    "sg:postcode":"27203",
    "sg:province":"NC",
    "wof:name":"Shoe Dept",
    "wof:placetype":"venue"
},
  "geometry": {"coordinates":[-79.805179,35.706115],"type":"Point"}
}