{
  "type": "Feature",
  "properties": {
    "iso:country":"US",
    "sg:address":"641 Wait Ave",
    "sg:city":"Wake Forest",
    "sg:classifiers":[
        {
            "category":"Real Estate",
            "subcategory":"Real Estate Agent",
            "type":"Services"
        }
    ],
    "sg:phone":"+1 919 556 0835",
    "sg:postcode":"27587",
    "sg:province":"NC",
    "wof:name":"Ingram Realty & Appraisal",
    "wof:placetype":"venue"
},
  "geometry": {"coordinates":[-78.502786,35.976569],"type":"Point"}
}