{
  "type": "Feature",
  "properties": {
    "addr:full":"813 Brookfield Rd Raleigh NC 27615",
    "addr:housenumber":"813",
    "addr:postcode":"27615",
    "addr:street":"Brookfield Rd",
    "iso:country":"US",
    "sg:address":"813 Brookfield Rd",
    "sg:city":"Raleigh",
    "sg:classifiers":[
        {
            "category":"Professional",
            "subcategory":"Management & Consulting",
            "type":"Services"
        }
    ],
    "sg:phone":"+1   ",
    "sg:postcode":"27615",
    "sg:province":"NC",
    "sg:tags":[
        "business"
    ],
    "wof:name":"Mancini Retail Consulting",
    "wof:placetype":"venue"
},
  "geometry": {"coordinates":[-78.66936800000001,35.919208],"type":"Point"}
}