{
  "type": "Feature",
  "properties": {
    "addr:full":"310 Neuse Harbor Blvd New Bern NC 28560",
    "addr:housenumber":"310",
    "addr:postcode":"28560",
    "addr:street":"Neuse Harbor Blvd",
    "iso:country":"US",
    "sg:address":"310 Neuse Harbor Blvd",
    "sg:city":"New Bern",
    "sg:classifiers":[
        {
            "category":"Recreation",
            "type":"Entertainment"
        }
    ],
    "sg:phone":"+1   ",
    "sg:postcode":"28560",
    "sg:province":"NC",
    "wof:name":"Swing Zone Inc",
    "wof:placetype":"venue"
},
  "geometry": {"coordinates":[-76.96546600000001,34.992598],"type":"Point"}
}