{
  "type": "Feature",
  "properties": {
    "iso:country":"US",
    "sg:address":"901 Reid St E",
    "sg:city":"Wilson",
    "sg:classifiers":[
        {
            "category":"Recreation",
            "type":"Entertainment"
        }
    ],
    "sg:phone":"+1 252 399 2288",
    "sg:postcode":"27893",
    "sg:province":"NC",
    "sg:tags":[
        "pool",
        "swimming"
    ],
    "wof:name":"Reid Street Pool",
    "wof:placetype":"venue"
},
  "geometry": {"coordinates":[-77.896709,35.724838],"type":"Point"}
}