{
  "type": "Feature",
  "properties": {
    "iso:country":"US",
    "sg:address":"4225 Tudor Ln",
    "sg:city":"Greensboro",
    "sg:classifiers":[
        {
            "category":"Food & Beverages",
            "subcategory":"Specialty",
            "type":"Retail Goods"
        }
    ],
    "sg:phone":"+1 336 294 1919",
    "sg:postcode":"27410",
    "sg:province":"NC",
    "sg:tags":[
        "water",
        "bulk",
        "company"
    ],
    "sg:website":"www.lebleu.com",
    "wof:name":"Le Bleu Of Greensboro",
    "wof:placetype":"venue"
},
  "geometry": {"coordinates":[-79.948374,36.059368],"type":"Point"}
}