{
  "type": "Feature",
  "properties": {
    "iso:country":"US",
    "sg:address":"440 Ryland Rd",
    "sg:city":"Tyner",
    "sg:classifiers":[
        {
            "category":"Farming",
            "subcategory":"Poultry Farm",
            "type":"Manufacturing & Wholesale Goods"
        }
    ],
    "sg:phone":"+1 252 221 8151",
    "sg:postcode":"27980",
    "sg:province":"NC",
    "sg:tags":[
        "chicken",
        "cotton"
    ],
    "wof:name":"Bradley Ward",
    "wof:placetype":"venue"
},
  "geometry": {"coordinates":[-76.631524,36.27507],"type":"Point"}
}