{
  "type": "Feature",
  "properties": {
    "iso:country":"US",
    "sg:address":"2736 E Ozark Ave",
    "sg:city":"Gastonia",
    "sg:classifiers":[
        {
            "category":"Food & Beverages",
            "subcategory":"Groceries & Convenience Stores",
            "type":"Retail Goods"
        }
    ],
    "sg:phone":"+1 704 824 0349",
    "sg:postcode":"28054",
    "sg:province":"NC",
    "wof:name":"Jack's Grocery & Package Store",
    "wof:placetype":"venue"
},
  "geometry": {"coordinates":[-81.136455,35.279494],"type":"Point"}
}