{
  "type": "Feature",
  "properties": {
    "iso:country":"US",
    "sg:address":"436 Riverglen Dr NW",
    "sg:city":"Concord",
    "sg:classifiers":[
        {
            "category":"Professional",
            "subcategory":"Accounting & Tax Preparation",
            "type":"Services"
        }
    ],
    "sg:phone":"+1   ",
    "sg:postcode":"28027",
    "sg:province":"NC",
    "sg:tags":[
        "return"
    ],
    "wof:name":"Bradford Income Tax Services",
    "wof:placetype":"venue"
},
  "geometry": {"coordinates":[-80.68887599999999,35.378112],"type":"Point"}
}