{
  "type": "Feature",
  "properties": {
    "iso:country":"US",
    "sg:address":"4227 Braddock Rd",
    "sg:city":"High Point",
    "sg:classifiers":[
        {
            "category":"Shopping",
            "subcategory":"Catalog Store",
            "type":"Retail Goods"
        }
    ],
    "sg:phone":"+1 336 869 0008",
    "sg:postcode":"27265",
    "sg:province":"NC",
    "sg:tags":[
        "house",
        "mail"
    ],
    "wof:name":"P K Enterprise",
    "wof:placetype":"venue"
},
  "geometry": {"coordinates":[-79.984956,36.035826],"type":"Point"}
}