{
  "type": "Feature",
  "properties": {
    "iso:country":"US",
    "sg:address":"3217 Apex Hwy",
    "sg:city":"Durham",
    "sg:classifiers":[
        {
            "category":"Shopping",
            "subcategory":"Catalog Store",
            "type":"Retail Goods"
        }
    ],
    "sg:phone":"+1 919 544 1263",
    "sg:postcode":"27713",
    "sg:province":"NC",
    "sg:tags":[
        "mail",
        "order"
    ],
    "wof:name":"Sherrie & Sonya Inc",
    "wof:placetype":"venue"
},
  "geometry": {"coordinates":[-78.887863,35.934742],"type":"Point"}
}