{
  "type": "Feature",
  "properties": {
    "iso:country":"US",
    "sg:address":"108 Stone Lake Ct",
    "sg:city":"Raleigh",
    "sg:classifiers":[
        {
            "category":"Building & Trades",
            "subcategory":"Cleaning & Sanitation",
            "type":"Services"
        }
    ],
    "sg:phone":"+1 919 231 0444",
    "sg:postcode":"27610",
    "sg:province":"NC",
    "sg:tags":[
        "janitor"
    ],
    "wof:name":"R & M Janitorial Svc",
    "wof:placetype":"venue"
},
  "geometry": {"coordinates":[-78.59880800000001,35.781428],"type":"Point"}
}