{
  "type": "Feature",
  "properties": {
    "addr:full":"125 W 9th St Roanoke Rapids NC 27870",
    "addr:housenumber":"125",
    "addr:postcode":"27870",
    "addr:street":"W 9Th St",
    "iso:country":"US",
    "sg:address":"125 W 9th St",
    "sg:city":"Roanoke Rapids",
    "sg:classifiers":[
        {
            "category":"Shopping",
            "subcategory":"Used Merchandise",
            "type":"Retail Goods"
        }
    ],
    "sg:phone":"+1 252 537 5843",
    "sg:postcode":"27870",
    "sg:province":"NC",
    "sg:tags":[
        "antique"
    ],
    "wof:name":"Past & Present Shop",
    "wof:placetype":"venue"
},
  "geometry": {"coordinates":[-77.658376,36.458499],"type":"Point"}
}