{
  "type": "Feature",
  "properties": {
    "iso:country":"US",
    "sg:address":"3126 Sussex Rd",
    "sg:city":"Raleigh",
    "sg:classifiers":[
        {
            "category":"Real Estate",
            "subcategory":"Real Estate Agent",
            "type":"Services"
        }
    ],
    "sg:phone":"+1 919 785 1445",
    "sg:postcode":"27607",
    "sg:province":"NC",
    "wof:name":"Beacon Street Development Co",
    "wof:placetype":"venue"
},
  "geometry": {"coordinates":[-78.668584,35.817867],"type":"Point"}
}