{
  "type": "Feature",
  "properties": {
    "addr:full":"404 Hickory Dr Elizabeth City NC 27909",
    "addr:housenumber":"404",
    "addr:postcode":"27909",
    "addr:street":"Hickory Dr",
    "iso:country":"US",
    "sg:address":"404 Hickory Dr",
    "sg:city":"Elizabeth City",
    "sg:classifiers":[
        {
            "category":"Professional",
            "subcategory":"Management & Consulting",
            "type":"Services"
        }
    ],
    "sg:phone":"+1   ",
    "sg:postcode":"27909",
    "sg:province":"NC",
    "sg:tags":[
        "business"
    ],
    "wof:name":"Dierview Performance Inc",
    "wof:placetype":"venue"
},
  "geometry": {"coordinates":[-76.25369999999999,36.316567],"type":"Point"}
}