{
  "type": "Feature",
  "properties": {
    "addr:full":"516 E Springhill Ter Jacksonville NC 28546",
    "addr:housenumber":"516",
    "addr:postcode":"28546",
    "addr:street":"E Springhill Ter",
    "iso:country":"US",
    "sg:address":"516 E Springhill Ter",
    "sg:city":"Jacksonville",
    "sg:classifiers":[
        {
            "category":"Health Services",
            "subcategory":"Nursing And Care Facility",
            "type":"Services"
        }
    ],
    "sg:phone":"+1 910 219 4371",
    "sg:postcode":"28546",
    "sg:province":"NC",
    "sg:tags":[
        "home",
        "institution"
    ],
    "wof:name":"Brymarr House",
    "wof:placetype":"venue"
},
  "geometry": {"coordinates":[-77.371031,34.753666],"type":"Point"}
}