{
  "type": "Feature",
  "properties": {
    "addr:full":"764 US Hwy 64 Cashiers NC 28717",
    "addr:housenumber":"764",
    "addr:postcode":"28717",
    "addr:street":"Us Hwy 64",
    "iso:country":"US",
    "sg:address":"764 US Hwy 64",
    "sg:city":"Cashiers",
    "sg:classifiers":[
        {
            "category":"Insurance",
            "subcategory":"Insurance Agent",
            "type":"Services"
        }
    ],
    "sg:phone":"+1 828 743 0990",
    "sg:postcode":"28717",
    "sg:province":"NC",
    "wof:name":"Black Bear Insurance Svc",
    "wof:placetype":"venue"
},
  "geometry": {"coordinates":[-83.082081,35.122682],"type":"Point"}
}