{
  "type": "Feature",
  "properties": {
    "iso:country":"US",
    "sg:address":"403 S Long Dr",
    "sg:city":"Rockingham",
    "sg:classifiers":[
        {
            "category":"Shopping",
            "subcategory":"Jewelry",
            "type":"Retail Goods"
        }
    ],
    "sg:phone":"+1 910 997 7327",
    "sg:postcode":"28379",
    "sg:province":"NC",
    "sg:tags":[
        "jeweler"
    ],
    "wof:name":"Jennifer's Jewelry & Gifts",
    "wof:placetype":"venue"
},
  "geometry": {"coordinates":[-79.753102,34.935656],"type":"Point"}
}