{
  "type": "Feature",
  "properties": {
    "iso:country":"US",
    "sg:address":"120 Healthplex Way",
    "sg:city":"Apex",
    "sg:classifiers":[
        {
            "category":"Health Services",
            "subcategory":"Hospital",
            "type":"Services"
        }
    ],
    "sg:phone":"+1 919 387 0228",
    "sg:postcode":"27502",
    "sg:province":"NC",
    "sg:website":"www.wakemed.org/landing.cfm?id=759",
    "wof:name":"Wakemed Apex Healthplex",
    "wof:placetype":"venue"
},
  "geometry": {"coordinates":[-78.86758,35.739232],"type":"Point"}
}