{
  "type": "Feature",
  "properties": {
    "addr:full":"1794 Greenlee Dr Morganton NC 28655",
    "addr:postcode":"1794;28655",
    "addr:street":"Greenlee Dr",
    "iso:country":"US",
    "sg:address":"1794 Greenlee Dr",
    "sg:city":"Morganton",
    "sg:classifiers":[
        {
            "category":"Shopping",
            "type":"Retail Goods"
        }
    ],
    "sg:phone":"+1 828 430 7449",
    "sg:postcode":"28655",
    "sg:province":"NC",
    "sg:tags":[
        "merchandise"
    ],
    "wof:name":"Creasys Flower Shop",
    "wof:placetype":"venue"
},
  "geometry": {"coordinates":[-81.67280100000001,35.858295],"type":"Point"}
}