{
  "type": "Feature",
  "properties": {
    "iso:country":"US",
    "sg:address":"866 Poplar Springs Church Rd",
    "sg:city":"Shelby",
    "sg:classifiers":[
        {
            "category":"Building & Trades",
            "subcategory":"Cleaning & Sanitation",
            "type":"Services"
        }
    ],
    "sg:phone":"+1 704 487 9087",
    "sg:postcode":"28152",
    "sg:province":"NC",
    "sg:tags":[
        "maintenance"
    ],
    "wof:name":"Cleveland Cnty Schl Plant Oper",
    "wof:placetype":"venue"
},
  "geometry": {"coordinates":[-81.599643,35.264849],"type":"Point"}
}