{
  "type": "Feature",
  "properties": {
    "addr:full":"304 N Beaverdam Rd Candler NC 28715",
    "addr:housenumber":"304",
    "addr:postcode":"28715",
    "addr:street":"N Beaverdam Rd",
    "iso:country":"US",
    "sg:address":"304 N Beaverdam Rd",
    "sg:city":"Candler",
    "sg:classifiers":[
        {
            "category":"Farming",
            "subcategory":"Farm",
            "type":"Manufacturing & Wholesale Goods"
        }
    ],
    "sg:phone":"+1 828 667 0875",
    "sg:postcode":"28715",
    "sg:province":"NC",
    "wof:name":"R & V Warren Farms",
    "wof:placetype":"venue"
},
  "geometry": {"coordinates":[-82.686329,35.49765],"type":"Point"}
}