{
  "type": "Feature",
  "properties": {
    "addr:full":"84 Cornerstone Dr Cary NC 27519",
    "addr:housenumber":"84",
    "addr:postcode":"27519",
    "addr:street":"Cornerstone Dr",
    "iso:country":"US",
    "sg:address":"84 Cornerstone Dr",
    "sg:city":"Cary",
    "sg:classifiers":[
        {
            "category":"Retail",
            "subcategory":"Laundry & Dry Cleaning",
            "type":"Services"
        }
    ],
    "sg:phone":"+1 919 460 8185",
    "sg:postcode":"27519",
    "sg:province":"NC",
    "wof:name":"Pristine Cleaners",
    "wof:placetype":"venue"
},
  "geometry": {"coordinates":[-78.85199,35.791479],"type":"Point"}
}