{
  "type": "Feature",
  "properties": {
    "addr:full":"140 S Hamilton St Eden NC 27288",
    "addr:housenumber":"140",
    "addr:postcode":"27288",
    "addr:street":"S Hamilton St",
    "iso:country":"US",
    "sg:address":"140 S Hamilton St",
    "sg:city":"Eden",
    "sg:classifiers":[
        {
            "category":"Restaurant",
            "type":"Food & Drink"
        }
    ],
    "sg:phone":"+1 336 627 9800",
    "sg:postcode":"27288",
    "sg:province":"NC",
    "sg:website":"www.subway.com",
    "wof:name":"Subway Sandwiches & Salads",
    "wof:placetype":"venue"
},
  "geometry": {"coordinates":[-79.772741,36.50204],"type":"Point"}
}