{
  "type": "Feature",
  "properties": {
    "addr:full":"120 Coop Ln Garysburg NC 27831",
    "addr:housenumber":"120",
    "addr:postcode":"27831",
    "addr:street":"Coop Ln",
    "iso:country":"US",
    "sg:address":"120 Coop Ln",
    "sg:city":"Garysburg",
    "sg:classifiers":[
        {
            "category":"Banks & Credit Unions",
            "subcategory":"Financial Services",
            "type":"Services"
        },
        {
            "category":"Manufacturing",
            "subcategory":"Textiles",
            "type":"Manufacturing & Wholesale Goods"
        }
    ],
    "sg:phone":"+1 252 537 1272",
    "sg:postcode":"27831",
    "sg:province":"NC",
    "sg:tags":[
        "gin",
        "purchasing",
        "cotton"
    ],
    "wof:name":"Gaston Co-Operative",
    "wof:placetype":"venue"
},
  "geometry": {"coordinates":[-77.619995,36.485907],"type":"Point"}
}