{
  "type": "Feature",
  "properties": {
    "iso:country":"US",
    "sg:address":"1801 Old Stage Rd",
    "sg:city":"Yadkinville",
    "sg:classifiers":[
        {
            "category":"Restaurant",
            "type":"Food & Drink"
        }
    ],
    "sg:phone":"+1 336 463 2825",
    "sg:postcode":"27055",
    "sg:province":"NC",
    "sg:tags":[
        "eating"
    ],
    "wof:name":"Walkers Grill",
    "wof:placetype":"venue"
},
  "geometry": {"coordinates":[-80.633009,36.097124],"type":"Point"}
}