{
  "type": "Feature",
  "properties": {
    "addr:full":"313 E 24th St Kannapolis NC 28083",
    "addr:housenumber":"313",
    "addr:postcode":"28083",
    "addr:street":"E 24Th St",
    "iso:country":"US",
    "sg:address":"313 E 24th St",
    "sg:city":"Kannapolis",
    "sg:classifiers":[
        {
            "category":"Organizations",
            "subcategory":"Religious Organization",
            "type":"Services"
        }
    ],
    "sg:phone":"+1 704 933 5736",
    "sg:postcode":"28083",
    "sg:province":"NC",
    "sg:tags":[
        "clergy"
    ],
    "wof:name":"H D Faulkenberry",
    "wof:placetype":"venue"
},
  "geometry": {"coordinates":[-80.60854,35.525445],"type":"Point"}
}