{
  "type": "Feature",
  "properties": {
    "addr:full":"148 S Washington St Rocky Mount NC 27801",
    "addr:housenumber":"148",
    "addr:postcode":"27801",
    "addr:street":"S Washington St",
    "iso:country":"US",
    "sg:address":"148 S Washington St",
    "sg:city":"Rocky Mount",
    "sg:classifiers":[
        {
            "category":"Professional",
            "subcategory":"Lawyer & Legal Services",
            "type":"Services"
        }
    ],
    "sg:phone":"+1   ",
    "sg:postcode":"27801",
    "sg:province":"NC",
    "wof:name":"North Crlina Assn Black Lwyers",
    "wof:placetype":"venue"
},
  "geometry": {"coordinates":[-77.794618,35.941491],"type":"Point"}
}