{
  "type": "Feature",
  "properties": {
    "iso:country":"US",
    "sg:address":"701 Hillsborough St",
    "sg:city":"Raleigh",
    "sg:classifiers":[
        {
            "category":"Autos & Motor Vehicles",
            "subcategory":"Fuel & Gas Station",
            "type":"Retail Goods"
        },
        {
            "category":"Autos & Motor Vehicles",
            "subcategory":"Auto Supplies",
            "type":"Retail Goods"
        },
        {
            "category":"Manufacturing",
            "subcategory":"Motor Vehicles & Parts",
            "type":"Manufacturing & Wholesale Goods"
        },
        {
            "category":"Retail",
            "subcategory":"Auto Repair",
            "type":"Services"
        }
    ],
    "sg:phone":"+1 919 834 9190",
    "sg:postcode":"27603",
    "sg:province":"NC",
    "sg:tags":[
        "wheel",
        "engines-diesel",
        "oil",
        "automotive",
        "radiator",
        "transmission",
        "spring",
        "equipment-service",
        "servicing-automotive",
        "sale",
        "lube",
        "brake",
        "axle",
        "automobile",
        "alignment-frame",
        "suspension",
        "tire",
        "air conditioning"
    ],
    "sg:website":"http://www.allensautonc.com",
    "wof:name":"Allen's Automotive",
    "wof:placetype":"venue"
},
  "geometry": {"coordinates":[-78.64917800000001,35.780811],"type":"Point"}
}