{
  "type": "Feature",
  "properties": {
    "iso:country":"US",
    "sg:address":"209 E Mill St",
    "sg:city":"Landis",
    "sg:classifiers":[
        {
            "category":"Organizations",
            "subcategory":"Religious Organization",
            "type":"Services"
        }
    ],
    "sg:phone":"+1 704 857 5041",
    "sg:postcode":"28088",
    "sg:province":"NC",
    "sg:tags":[
        "church"
    ],
    "wof:name":"First United Methodist Church",
    "wof:placetype":"venue"
},
  "geometry": {"coordinates":[-80.60966500000001,35.544876],"type":"Point"}
}