{
  "type": "Feature",
  "properties": {
    "iso:country":"US",
    "sg:address":"5647 Mountain Terrace Dr",
    "sg:city":"Hickory",
    "sg:classifiers":[
        {
            "category":"Utilities",
            "subcategory":"Telephone",
            "type":"Services"
        }
    ],
    "sg:phone":"+1 828 294 0037",
    "sg:postcode":"28602",
    "sg:province":"NC",
    "sg:tags":[
        "telecommunication"
    ],
    "wof:name":"Killian's",
    "wof:placetype":"venue"
},
  "geometry": {"coordinates":[-81.37953899999999,35.670699],"type":"Point"}
}