{
  "type": "Feature",
  "properties": {
    "addr:full":"1403 Buckingham Rd Garner NC 27529",
    "addr:housenumber":"1403",
    "addr:postcode":"27529",
    "addr:street":"Buckingham Rd",
    "iso:country":"US",
    "sg:address":"1403 Buckingham Rd",
    "sg:city":"Garner",
    "sg:classifiers":[
        {
            "category":"Insurance",
            "subcategory":"Insurance Agent",
            "type":"Services"
        }
    ],
    "sg:phone":"+1 919 662 2169",
    "sg:postcode":"27529",
    "sg:province":"NC",
    "wof:name":"Imperial Insurance Group",
    "wof:placetype":"venue"
},
  "geometry": {"coordinates":[-78.625236,35.687012],"type":"Point"}
}