{
  "type": "Feature",
  "properties": {
    "iso:country":"US",
    "sg:address":"6029 Walker Mill Rd",
    "sg:city":"Randleman",
    "sg:classifiers":[
        {
            "category":"Farming",
            "subcategory":"Dairy Farm",
            "type":"Manufacturing & Wholesale Goods"
        }
    ],
    "sg:phone":"+1 336 495 4172",
    "sg:postcode":"27317",
    "sg:province":"NC",
    "wof:name":"Buttke Dairy Enterprises",
    "wof:placetype":"venue"
},
  "geometry": {"coordinates":[-79.841075,35.845063],"type":"Point"}
}