{
  "type": "Feature",
  "properties": {
    "iso:country":"US",
    "sg:address":"610 Spring St",
    "sg:city":"Mount Holly",
    "sg:classifiers":[
        {
            "category":"Manufacturing",
            "subcategory":"Tools & Machinery",
            "type":"Manufacturing & Wholesale Goods"
        }
    ],
    "sg:phone":"+1 704 827 3287",
    "sg:postcode":"28120",
    "sg:province":"NC",
    "sg:tags":[
        "machine",
        "shop"
    ],
    "wof:name":"Diversified Insta Parts Inc",
    "wof:placetype":"venue"
},
  "geometry": {"coordinates":[-81.010464,35.304599],"type":"Point"}
}