{
  "type": "Feature",
  "properties": {
    "addr:full":"218 E Peedin Rd Smithfield NC 27577",
    "addr:housenumber":"218",
    "addr:postcode":"27577",
    "addr:street":"E Peedin Rd",
    "iso:country":"US",
    "sg:address":"218 E Peedin Rd",
    "sg:city":"Smithfield",
    "sg:classifiers":[
        {
            "category":"Social Services",
            "type":"Services"
        }
    ],
    "sg:phone":"+1 919 989 6304",
    "sg:postcode":"27577",
    "sg:province":"NC",
    "sg:tags":[
        "organization",
        "welfare"
    ],
    "wof:name":"Easter Seals North Carolina",
    "wof:placetype":"venue"
},
  "geometry": {"coordinates":[-78.31669599999999,35.512637],"type":"Point"}
}