{
  "type": "Feature",
  "properties": {
    "iso:country":"US",
    "sg:address":"9257 Miranda Dr",
    "sg:city":"Raleigh",
    "sg:classifiers":[
        {
            "category":"Professional",
            "subcategory":"Advertising",
            "type":"Services"
        }
    ],
    "sg:phone":"+1 919 676 8788",
    "sg:postcode":"27617",
    "sg:province":"NC",
    "sg:website":"www.criminalrecordcheck.com",
    "wof:name":"CRIMINALRECORDCHECK.COM",
    "wof:placetype":"venue"
},
  "geometry": {"coordinates":[-78.74538200000001,35.910121],"type":"Point"}
}