{
  "type": "Feature",
  "properties": {
    "addr:full":"9623 E Independence Blvd Matthews NC 28105",
    "addr:housenumber":"9623",
    "addr:postcode":"28105",
    "addr:street":"E Independence Blvd",
    "iso:country":"US",
    "sg:address":"9623 E Independence Blvd",
    "sg:city":"Matthews",
    "sg:classifiers":[
        {
            "category":"Personal",
            "subcategory":"Beauty Salon",
            "type":"Services"
        }
    ],
    "sg:phone":"+1 704 708 6969",
    "sg:postcode":"28105",
    "sg:province":"NC",
    "sg:tags":[
        "spa",
        "day"
    ],
    "sg:website":"http://hairspakdsorganics.vpweb.com",
    "wof:name":"Hair Spa",
    "wof:placetype":"venue"
},
  "geometry": {"coordinates":[-80.714534,35.136159],"type":"Point"}
}