{
  "type": "Feature",
  "properties": {
    "iso:country":"US",
    "sg:address":"1355 Shearers Rd Suite A",
    "sg:city":"Mooresville",
    "sg:classifiers":[
        {
            "category":"Banks & Credit Unions",
            "subcategory":"Investment Brokerage",
            "type":"Services"
        },
        {
            "category":"Banks & Credit Unions",
            "subcategory":"Bank",
            "type":"Services"
        },
        {
            "category":"Banks & Credit Unions",
            "subcategory":"Financial Services",
            "type":"Services"
        }
    ],
    "sg:phone":"+1 704 746 9479",
    "sg:postcode":"28115",
    "sg:province":"NC",
    "sg:tags":[
        "advisory",
        "mutual",
        "retirement",
        "annuity",
        "broker",
        "fund",
        "planning",
        "plan",
        "consultant",
        "security",
        "bond",
        "insurance",
        "stock"
    ],
    "sg:website":"http://national.citysearch.com/profile/external/648066710/mooresville_nc/edward_jones_brenda_g_lutz_kiser.html?publisher=yellowpages&reference_id=1&placement=ypwebsitemip",
    "wof:name":"Edward Jones - BRENDA G LUTZ-KISER",
    "wof:placetype":"venue"
},
  "geometry": {"coordinates":[-80.799806,35.533098],"type":"Point"}
}