{
  "type": "Feature",
  "properties": {
    "iso:country":"US",
    "sg:address":"191 Thomas Heights Rd",
    "sg:city":"Franklin",
    "sg:classifiers":[
        {
            "category":"Government",
            "subcategory":"Office",
            "type":"Public Place"
        }
    ],
    "sg:phone":"+1 828 524 3311",
    "sg:postcode":"28734",
    "sg:province":"NC",
    "wof:name":"Macon County Soil-Water Cnsvtn",
    "wof:placetype":"venue"
},
  "geometry": {"coordinates":[-83.367008,35.179225],"type":"Point"}
}