{
  "type": "Feature",
  "properties": {
    "iso:country":"US",
    "sg:address":"158 Sugar Maple Dr",
    "sg:city":"Browns Summit",
    "sg:classifiers":[
        {
            "category":"Shopping",
            "subcategory":"Catalog Store",
            "type":"Retail Goods"
        }
    ],
    "sg:phone":"+1 336 358 0979",
    "sg:postcode":"27214",
    "sg:province":"NC",
    "sg:tags":[
        "direct",
        "order"
    ],
    "wof:name":"Outlook Unlimited",
    "wof:placetype":"venue"
},
  "geometry": {"coordinates":[-79.721232,36.202416],"type":"Point"}
}