{
  "type": "Feature",
  "properties": {
    "addr:full":"3125 Poplarwood Ct Raleigh NC 27604",
    "addr:housenumber":"3125",
    "addr:postcode":"27604",
    "addr:street":"Poplarwood Ct",
    "iso:country":"US",
    "sg:address":"3125 Poplarwood Ct",
    "sg:city":"Raleigh",
    "sg:classifiers":[
        {
            "category":"Professional",
            "subcategory":"Research",
            "type":"Services"
        }
    ],
    "sg:phone":"+1 919 431 0020",
    "sg:postcode":"27604",
    "sg:province":"NC",
    "sg:tags":[
        "assistance",
        "program",
        "technology"
    ],
    "wof:name":"Modern Tech",
    "wof:placetype":"venue"
},
  "geometry": {"coordinates":[-78.60371000000001,35.819183],"type":"Point"}
}