{
  "type": "Feature",
  "properties": {
    "iso:country":"US",
    "sg:address":"110 Wilkesboro Ave",
    "sg:city":"North Wilkesboro",
    "sg:classifiers":[
        {
            "category":"Shopping",
            "subcategory":"Pharmacy",
            "type":"Retail Goods"
        }
    ],
    "sg:phone":"+1 336 667 3259",
    "sg:postcode":"28659",
    "sg:province":"NC",
    "wof:name":"Care Connection Pharmacy",
    "wof:placetype":"venue"
},
  "geometry": {"coordinates":[-81.142816,36.159345],"type":"Point"}
}