{
  "type": "Feature",
  "properties": {
    "addr:full":"1018 Lillington Hwy Spring Lake NC 28390",
    "addr:housenumber":"1018",
    "addr:postcode":"28390",
    "addr:street":"Lillington Hwy",
    "iso:country":"US",
    "sg:address":"1018 Lillington Hwy",
    "sg:city":"Spring Lake",
    "sg:classifiers":[
        {
            "category":"Professional",
            "subcategory":"Engineering",
            "type":"Services"
        }
    ],
    "sg:phone":"+1 910 960 1050",
    "sg:postcode":"28390",
    "sg:province":"NC",
    "sg:tags":[
        "consulting"
    ],
    "wof:name":"Bae Systems North America",
    "wof:placetype":"venue"
},
  "geometry": {"coordinates":[-78.964485,35.182518],"type":"Point"}
}