{
  "type": "Feature",
  "properties": {
    "iso:country":"US",
    "sg:address":"1935 Hilco St",
    "sg:city":"Albemarle",
    "sg:classifiers":[
        {
            "category":"Wholesale",
            "subcategory":"Electrical",
            "type":"Manufacturing & Wholesale Goods"
        }
    ],
    "sg:phone":"+1 704 983 5392",
    "sg:postcode":"28001",
    "sg:province":"NC",
    "sg:tags":[
        "equipment",
        "electronic"
    ],
    "sg:website":"www.descoinc.com",
    "wof:name":"Desco Inc",
    "wof:placetype":"venue"
},
  "geometry": {"coordinates":[-80.16131,35.349918],"type":"Point"}
}