{
  "type": "Feature",
  "properties": {
    "iso:country":"US",
    "sg:address":"2110 Baywater Dr",
    "sg:city":"Fayetteville",
    "sg:classifiers":[
        {
            "category":"Social Services",
            "subcategory":"Child Care",
            "type":"Services"
        }
    ],
    "sg:phone":"+1   ",
    "sg:postcode":"28304",
    "sg:province":"NC",
    "sg:tags":[
        "day"
    ],
    "wof:name":"Little Blessings From He",
    "wof:placetype":"venue"
},
  "geometry": {"coordinates":[-78.998321,35.013836],"type":"Point"}
}