{
  "type": "Feature",
  "properties": {
    "addr:full":"1004 W 3rd Ave Red Springs NC 28377",
    "addr:housenumber":"1004",
    "addr:postcode":"28377",
    "addr:street":"W 3Rd Ave",
    "iso:country":"US",
    "sg:address":"1004 W 3rd Ave",
    "sg:city":"Red Springs",
    "sg:classifiers":[
        {
            "category":"Wholesale",
            "subcategory":"Hardware",
            "type":"Manufacturing & Wholesale Goods"
        },
        {
            "category":"Food & Beverages",
            "subcategory":"Meat & Fish",
            "type":"Retail Goods"
        }
    ],
    "sg:phone":"+1 910 843 3412",
    "sg:postcode":"28377",
    "sg:province":"NC",
    "sg:tags":[
        "plumbing"
    ],
    "wof:name":"Ferguson Enterprises Inc",
    "wof:placetype":"venue"
},
  "geometry": {"coordinates":[-79.19893399999999,34.812226],"type":"Point"}
}