{
  "type": "Feature",
  "properties": {
    "iso:country":"US",
    "sg:address":"3760 Fraternity Church Rd",
    "sg:city":"Winston Salem",
    "sg:classifiers":[
        {
            "category":"Organizations",
            "subcategory":"Religious Organization",
            "type":"Services"
        }
    ],
    "sg:phone":"+1 336 765 0610",
    "sg:postcode":"27127",
    "sg:province":"NC",
    "sg:tags":[
        "church"
    ],
    "wof:name":"Fraternity Church-The Brethren",
    "wof:placetype":"venue"
},
  "geometry": {"coordinates":[-80.342894,36.025113],"type":"Point"}
}