{
  "type": "Feature",
  "properties": {
    "iso:country":"US",
    "sg:address":"355 Ollis Rd",
    "sg:city":"Spruce Pine",
    "sg:classifiers":[
        {
            "category":"Retail",
            "subcategory":"Auto Repair",
            "type":"Services"
        }
    ],
    "sg:phone":"+1 828 765 0975",
    "sg:postcode":"28777",
    "sg:province":"NC",
    "sg:tags":[
        "automotive",
        "wrecker",
        "general"
    ],
    "wof:name":"Dean's Garage & Wrecker Svc",
    "wof:placetype":"venue"
},
  "geometry": {"coordinates":[-82.070967,35.929536],"type":"Point"}
}