{
  "type": "Feature",
  "properties": {
    "addr:full":"11464 Old US Hwy 52 Winston Salem NC 27107",
    "addr:housenumber":"11464",
    "addr:postcode":"27107",
    "addr:street":"Old Us Hwy 52",
    "iso:country":"US",
    "sg:address":"11464 Old US Hwy 52",
    "sg:city":"Winston Salem",
    "sg:classifiers":[
        {
            "category":"Restaurant",
            "type":"Food & Drink"
        }
    ],
    "sg:phone":"+1 336 764 1480",
    "sg:postcode":"27107",
    "sg:province":"NC",
    "sg:tags":[
        "eating"
    ],
    "wof:name":"Country Kitchen",
    "wof:placetype":"venue"
},
  "geometry": {"coordinates":[-80.224678,35.973768],"type":"Point"}
}