{
  "type": "Feature",
  "properties": {
    "iso:country":"US",
    "sg:address":"750 Weaver Dairy Rd",
    "sg:city":"Chapel Hill",
    "sg:classifiers":[
        {
            "category":"Health Services",
            "subcategory":"Nursing And Care Facility",
            "type":"Services"
        }
    ],
    "sg:phone":"+1 919 968 4511",
    "sg:postcode":"27514",
    "sg:province":"NC",
    "sg:tags":[
        "home",
        "retirement",
        "community"
    ],
    "wof:name":"Carol Woods Retirement Cmnty",
    "wof:placetype":"venue"
},
  "geometry": {"coordinates":[-79.040345,35.96382],"type":"Point"}
}