{
  "type": "Feature",
  "properties": {
    "addr:full":"1900 E Firetower Rd Greenville NC 27858",
    "addr:housenumber":"1900",
    "addr:postcode":"27858",
    "addr:street":"E Firetower Rd",
    "iso:country":"US",
    "sg:address":"1900 E Firetower Rd",
    "sg:city":"Greenville",
    "sg:classifiers":[
        {
            "category":"Food & Beverages",
            "subcategory":"Groceries & Convenience Stores",
            "type":"Retail Goods"
        }
    ],
    "sg:phone":"+1 252 353 0547",
    "sg:postcode":"27858",
    "sg:province":"NC",
    "wof:name":"Smokers Express",
    "wof:placetype":"venue"
},
  "geometry": {"coordinates":[-77.352053,35.566455],"type":"Point"}
}