{
  "type": "Feature",
  "properties": {
    "iso:country":"US",
    "sg:address":"211 Broad St",
    "sg:city":"Kernersville",
    "sg:classifiers":[
        {
            "category":"Banks & Credit Unions",
            "subcategory":"Bank",
            "type":"Services"
        }
    ],
    "sg:phone":"+1 336 996 1776",
    "sg:postcode":"27284",
    "sg:province":"NC",
    "sg:website":"www.bankofnc.com",
    "wof:name":"Bank Of North Carolina",
    "wof:placetype":"venue"
},
  "geometry": {"coordinates":[-80.07129999999999,36.116038],"type":"Point"}
}