{
  "type": "Feature",
  "properties": {
    "addr:full":"130 Windham Farm Ln Lewisville NC 27023",
    "addr:housenumber":"130",
    "addr:postcode":"27023",
    "addr:street":"Windham Farm Ln",
    "iso:country":"US",
    "sg:address":"130 Windham Farm Ln",
    "sg:city":"Lewisville",
    "sg:classifiers":[
        {
            "category":"Professional",
            "subcategory":"Management & Consulting",
            "type":"Services"
        }
    ],
    "sg:phone":"+1 336 946 2096",
    "sg:postcode":"27023",
    "sg:province":"NC",
    "sg:tags":[
        "consultant",
        "business"
    ],
    "wof:name":"Irvin Goforth & Irvin LLC",
    "wof:placetype":"venue"
},
  "geometry": {"coordinates":[-80.40158700000001,36.110411],"type":"Point"}
}