{
  "type": "Feature",
  "properties": {
    "iso:country":"US",
    "sg:address":"101 Center St",
    "sg:city":"Cramerton",
    "sg:classifiers":[
        {
            "category":"Shopping",
            "subcategory":"Florist",
            "type":"Retail Goods"
        }
    ],
    "sg:phone":"+1 704 824 1924",
    "sg:postcode":"28032",
    "sg:province":"NC",
    "wof:name":"Queen's Florist & Gift Shop",
    "wof:placetype":"venue"
},
  "geometry": {"coordinates":[-81.071625,35.235374],"type":"Point"}
}