{
  "type": "Feature",
  "properties": {
    "iso:country":"US",
    "sg:address":"4101 West Blvd",
    "sg:city":"Charlotte",
    "sg:classifiers":[
        {
            "category":"Manufacturing",
            "subcategory":"Tools & Machinery",
            "type":"Manufacturing & Wholesale Goods"
        }
    ],
    "sg:phone":"+1 704 424 9599",
    "sg:postcode":"28208",
    "sg:province":"NC",
    "wof:name":"Hunter Lab Southeast Ctr",
    "wof:placetype":"venue"
},
  "geometry": {"coordinates":[-80.927222,35.20351],"type":"Point"}
}