{
  "type": "Feature",
  "properties": {
    "iso:country":"US",
    "sg:address":"2912 New Hall Ct",
    "sg:city":"Raleigh",
    "sg:classifiers":[
        {
            "category":"Real Estate",
            "subcategory":"Real Estate Agent",
            "type":"Services"
        }
    ],
    "sg:phone":"+1 919 844 0440",
    "sg:postcode":"27615",
    "sg:province":"NC",
    "wof:name":"Anderson & Associates Realty",
    "wof:placetype":"venue"
},
  "geometry": {"coordinates":[-78.58978,35.899642],"type":"Point"}
}