{
  "type": "Feature",
  "properties": {
    "addr:full":"819 Franklin Blvd Greensboro NC 27401",
    "addr:housenumber":"819",
    "addr:postcode":"27401",
    "addr:street":"Franklin Blvd",
    "iso:country":"US",
    "sg:address":"819 Franklin Blvd",
    "sg:city":"Greensboro",
    "sg:classifiers":[
        {
            "category":"Building & Trades",
            "subcategory":"Construction",
            "type":"Services"
        }
    ],
    "sg:phone":"+1 336 987 1632",
    "sg:postcode":"27401",
    "sg:province":"NC",
    "sg:tags":[
        "contractor"
    ],
    "wof:name":"Install Right",
    "wof:placetype":"venue"
},
  "geometry": {"coordinates":[-79.741275,36.063989],"type":"Point"}
}