{
  "type": "Feature",
  "properties": {
    "addr:full":"130 Ridge Cir Gastonia NC 28052",
    "addr:housenumber":"130",
    "addr:postcode":"28052",
    "addr:street":"Ridge Cir",
    "iso:country":"US",
    "sg:address":"130 Ridge Cir",
    "sg:city":"Gastonia",
    "sg:classifiers":[
        {
            "category":"Shopping",
            "subcategory":"Clothing, Apparel, & Fashions",
            "type":"Retail Goods"
        }
    ],
    "sg:phone":"+1 704 865 2654",
    "sg:postcode":"28052",
    "sg:province":"NC",
    "wof:name":"Lerner New York",
    "wof:placetype":"venue"
},
  "geometry": {"coordinates":[-81.201082,35.213682],"type":"Point"}
}