{
  "type": "Feature",
  "properties": {
    "iso:country":"US",
    "sg:address":"7228 Davis Rd",
    "sg:city":"Charlotte",
    "sg:classifiers":[
        {
            "category":"Building & Trades",
            "subcategory":"Landscaping Services",
            "type":"Services"
        }
    ],
    "sg:phone":"+1 704 573 8162",
    "sg:postcode":"28227",
    "sg:province":"NC",
    "sg:tags":[
        "lawn",
        "maintenance",
        "grounds"
    ],
    "wof:name":"Richies Lawn Svc",
    "wof:placetype":"venue"
},
  "geometry": {"coordinates":[-80.675387,35.192963],"type":"Point"}
}