{
  "type": "Feature",
  "properties": {
    "iso:country":"US",
    "sg:address":"4803 W US Hwy 421",
    "sg:city":"Wilkesboro",
    "sg:classifiers":[
        {
            "category":"Professional",
            "type":"Services"
        }
    ],
    "sg:phone":"+1 336 973 4098",
    "sg:postcode":"28697",
    "sg:province":"NC",
    "wof:name":"Meadowlark Landing",
    "wof:placetype":"venue"
},
  "geometry": {"coordinates":[-81.333663,36.152483],"type":"Point"}
}