{
  "type": "Feature",
  "properties": {
    "addr:full":"411 W 5th St Siler City NC 27344",
    "addr:housenumber":"411",
    "addr:postcode":"27344",
    "addr:street":"W 5Th St",
    "iso:country":"US",
    "sg:address":"411 W 5th St",
    "sg:city":"Siler City",
    "sg:classifiers":[
        {
            "category":"Farming",
            "subcategory":"Poultry Farm",
            "type":"Manufacturing & Wholesale Goods"
        }
    ],
    "sg:phone":"+1 919 742 2714",
    "sg:postcode":"27344",
    "sg:province":"NC",
    "sg:tags":[
        "hatchery"
    ],
    "wof:name":"Ellington Terrill Farms",
    "wof:placetype":"venue"
},
  "geometry": {"coordinates":[-79.469375,35.725143],"type":"Point"}
}