{
  "type": "Feature",
  "properties": {
    "iso:country":"US",
    "sg:address":"2170 Plain View Hwy",
    "sg:city":"Dunn",
    "sg:classifiers":[
        {
            "category":"Manufacturing",
            "subcategory":"Wood Products",
            "type":"Manufacturing & Wholesale Goods"
        }
    ],
    "sg:phone":"+1 910 892 7841",
    "sg:postcode":"28334",
    "sg:province":"NC",
    "sg:tags":[
        "mfg"
    ],
    "wof:name":"Georges Pallets",
    "wof:placetype":"venue"
},
  "geometry": {"coordinates":[-78.504937,35.214293],"type":"Point"}
}