{
  "type": "Feature",
  "properties": {
    "addr:full":"504 S 6th St Bessemer City NC 28016",
    "addr:housenumber":"504",
    "addr:postcode":"28016",
    "addr:street":"S 6Th St",
    "iso:country":"US",
    "sg:address":"504 S 6th St",
    "sg:city":"Bessemer City",
    "sg:classifiers":[
        {
            "category":"Building & Trades",
            "subcategory":"Construction",
            "type":"Services"
        }
    ],
    "sg:phone":"+1 704 629 6490",
    "sg:postcode":"28016",
    "sg:province":"NC",
    "sg:tags":[
        "concrete",
        "contractor"
    ],
    "wof:name":"Terrell K Wilson Construction",
    "wof:placetype":"venue"
},
  "geometry": {"coordinates":[-81.272096,35.278534],"type":"Point"}
}