{
  "type": "Feature",
  "properties": {
    "addr:full":"8312 Fayetteville Rd Raleigh NC 27603",
    "addr:housenumber":"8312",
    "addr:postcode":"27603",
    "addr:street":"Fayetteville Rd",
    "iso:country":"US",
    "sg:address":"8312 Fayetteville Rd",
    "sg:city":"Raleigh",
    "sg:classifiers":[
        {
            "category":"Professional",
            "type":"Services"
        }
    ],
    "sg:phone":"+1 919 832 5590",
    "sg:postcode":"27603",
    "sg:province":"NC",
    "wof:name":"Hammerhead Grading Company",
    "wof:placetype":"venue"
},
  "geometry": {"coordinates":[-78.702703,35.661901],"type":"Point"}
}