{
  "type": "Feature",
  "properties": {
    "iso:country":"US",
    "sg:address":"5728 Reams Rd",
    "sg:city":"Spring Hope",
    "sg:classifiers":[
        {
            "category":"Wholesale",
            "subcategory":"Poultry",
            "type":"Manufacturing & Wholesale Goods"
        }
    ],
    "sg:phone":"+1 252 478 5650",
    "sg:postcode":"27882",
    "sg:province":"NC",
    "wof:name":"Gary Manning Poultry Inc",
    "wof:placetype":"venue"
},
  "geometry": {"coordinates":[-78.07731200000001,35.939373],"type":"Point"}
}