{
  "type": "Feature",
  "properties": {
    "iso:country":"US",
    "sg:address":"232 W Main St",
    "sg:city":"Washington",
    "sg:classifiers":[
        {
            "category":"Personal",
            "subcategory":"Beauty Salon",
            "type":"Services"
        }
    ],
    "sg:phone":"+1 252 975 2277",
    "sg:postcode":"27889",
    "sg:province":"NC",
    "sg:tags":[
        "shop"
    ],
    "wof:name":"T-Lanee's Beauty Palace",
    "wof:placetype":"venue"
},
  "geometry": {"coordinates":[-77.057885,35.543411],"type":"Point"}
}