{
  "type": "Feature",
  "properties": {
    "iso:country":"US",
    "sg:address":"714 Richardson St",
    "sg:city":"Elizabeth City",
    "sg:classifiers":[
        {
            "category":"Organizations",
            "subcategory":"Religious Organization",
            "type":"Services"
        }
    ],
    "sg:phone":"+1 252 331 2884",
    "sg:postcode":"27909",
    "sg:province":"NC",
    "sg:tags":[
        "church"
    ],
    "wof:name":"Word Of Reconciliation Church",
    "wof:placetype":"venue"
},
  "geometry": {"coordinates":[-76.22674000000001,36.307081],"type":"Point"}
}