{
  "type": "Feature",
  "properties": {
    "iso:country":"US",
    "sg:address":"221 Crousetown Rd",
    "sg:city":"Lexington",
    "sg:classifiers":[
        {
            "category":"Manufacturing",
            "subcategory":"Lumber",
            "type":"Manufacturing & Wholesale Goods"
        }
    ],
    "sg:phone":"+1 336 859 4814",
    "sg:postcode":"27292",
    "sg:province":"NC",
    "sg:tags":[
        "logging",
        "contractor"
    ],
    "wof:name":"Edward Grubb Logging",
    "wof:placetype":"venue"
},
  "geometry": {"coordinates":[-80.077928,35.698287],"type":"Point"}
}