{
  "type": "Feature",
  "properties": {
    "iso:country":"US",
    "sg:address":"407 E College Ave",
    "sg:city":"Shelby",
    "sg:classifiers":[
        {
            "category":"Wholesale",
            "subcategory":"Construction Materials",
            "type":"Manufacturing & Wholesale Goods"
        }
    ],
    "sg:phone":"+1 704 434 5011",
    "sg:postcode":"28152",
    "sg:province":"NC",
    "sg:tags":[
        "fence"
    ],
    "wof:name":"Hamrick Fence Co",
    "wof:placetype":"venue"
},
  "geometry": {"coordinates":[-81.65418,35.249549],"type":"Point"}
}