{
  "type": "Feature",
  "properties": {
    "iso:country":"US",
    "sg:address":"215 Cedarwood Dr",
    "sg:city":"Jamestown",
    "sg:classifiers":[
        {
            "category":"Home & Garden",
            "subcategory":"Furniture",
            "type":"Retail Goods"
        }
    ],
    "sg:phone":"+1 336 847 1902",
    "sg:postcode":"27282",
    "sg:province":"NC",
    "wof:name":"Office Furniture Consultants",
    "wof:placetype":"venue"
},
  "geometry": {"coordinates":[-79.933263,36.017559],"type":"Point"}
}