{
  "type": "Feature",
  "properties": {
    "iso:country":"US",
    "sg:address":"4224 Saxonbury Way",
    "sg:city":"Charlotte",
    "sg:classifiers":[
        {
            "category":"Professional",
            "subcategory":"Business Services",
            "type":"Services"
        }
    ],
    "sg:phone":"+1   ",
    "sg:postcode":"28269",
    "sg:province":"NC",
    "wof:name":"Dorais Enterprises",
    "wof:placetype":"venue"
},
  "geometry": {"coordinates":[-80.78182700000001,35.347512],"type":"Point"}
}