{
  "type": "Feature",
  "properties": {
    "addr:full":"703 Greenwood Cir Cary NC 27511",
    "addr:housenumber":"703",
    "addr:postcode":"27511",
    "addr:street":"Greenwood Cir",
    "iso:country":"US",
    "sg:address":"703 Greenwood Cir",
    "sg:city":"Cary",
    "sg:classifiers":[
        {
            "category":"Professional",
            "type":"Services"
        }
    ],
    "sg:phone":"+1 919 462 8074",
    "sg:postcode":"27511",
    "sg:province":"NC",
    "sg:tags":[
        "establishment"
    ],
    "wof:name":"William H Towe Inc",
    "wof:placetype":"venue"
},
  "geometry": {"coordinates":[-78.763035,35.762767],"type":"Point"}
}