{
  "type": "Feature",
  "properties": {
    "addr:full":"44118 State Hwy 740 New London NC 28127",
    "addr:housenumber":"44118",
    "addr:postcode":"28127",
    "addr:street":"State Hwy 740",
    "iso:country":"US",
    "sg:address":"44118 State Hwy 740",
    "sg:city":"New London",
    "sg:classifiers":[
        {
            "category":"Organizations",
            "subcategory":"Religious Organization",
            "type":"Services"
        }
    ],
    "sg:phone":"+1 704 463 5209",
    "sg:postcode":"28127",
    "sg:province":"NC",
    "sg:tags":[
        "church"
    ],
    "wof:name":"Bethel United Methodist Church",
    "wof:placetype":"venue"
},
  "geometry": {"coordinates":[-80.17953199999999,35.448273],"type":"Point"}
}