{
  "type": "Feature",
  "properties": {
    "iso:country":"US",
    "sg:address":"403 Kyloe Rd",
    "sg:city":"Southern Pines",
    "sg:classifiers":[
        {
            "category":"Building & Trades",
            "subcategory":"Cleaning & Sanitation",
            "type":"Services"
        }
    ],
    "sg:phone":"+1   ",
    "sg:postcode":"28387",
    "sg:province":"NC",
    "sg:tags":[
        "maintenance"
    ],
    "wof:name":"Arthur Joseph Birner",
    "wof:placetype":"venue"
},
  "geometry": {"coordinates":[-79.369815,35.138342],"type":"Point"}
}