{
  "type": "Feature",
  "properties": {
    "iso:country":"US",
    "sg:address":"8625 Crown Crescent Ct",
    "sg:city":"Charlotte",
    "sg:classifiers":[
        {
            "category":"Professional",
            "subcategory":"Credit Reporting & Collection",
            "type":"Services"
        }
    ],
    "sg:phone":"+1 704 841 2424",
    "sg:postcode":"28227",
    "sg:province":"NC",
    "sg:tags":[
        "agency"
    ],
    "sg:website":"www.princeparker.com",
    "wof:name":"Prince Parker & Assoc",
    "wof:placetype":"venue"
},
  "geometry": {"coordinates":[-80.72913,35.142064],"type":"Point"}
}