{
  "type": "Feature",
  "properties": {
    "iso:country":"US",
    "sg:address":"645 Stallings Rd",
    "sg:city":"Matthews",
    "sg:classifiers":[
        {
            "category":"Shopping",
            "type":"Retail Goods"
        },
        {
            "category":"Retail",
            "subcategory":"Auto Repair",
            "type":"Services"
        }
    ],
    "sg:phone":"+1 704 821 6459",
    "sg:postcode":"28104",
    "sg:province":"NC",
    "sg:tags":[
        "importer",
        "general"
    ],
    "wof:name":"Matthews Imports Inc",
    "wof:placetype":"venue"
},
  "geometry": {"coordinates":[-80.68761499999999,35.089574],"type":"Point"}
}