{
  "type": "Feature",
  "properties": {
    "iso:country":"US",
    "sg:address":"6626 Courtland St",
    "sg:city":"Indian Trail",
    "sg:classifiers":[
        {
            "category":"Government",
            "subcategory":"Court House",
            "type":"Public Place"
        }
    ],
    "sg:phone":"+1 704 893 0873",
    "sg:postcode":"28079",
    "sg:province":"NC",
    "sg:tags":[
        "legal"
    ],
    "wof:name":"Prepaid Legal",
    "wof:placetype":"venue"
},
  "geometry": {"coordinates":[-80.63711000000001,35.092449],"type":"Point"}
}