{
  "type": "Feature",
  "properties": {
    "addr:full":"1812 House Ave Durham NC 27707",
    "addr:housenumber":"1812",
    "addr:postcode":"27707",
    "addr:street":"House Ave",
    "iso:country":"US",
    "sg:address":"1812 House Ave",
    "sg:city":"Durham",
    "sg:classifiers":[
        {
            "category":"Manufacturing",
            "subcategory":"Printing",
            "type":"Manufacturing & Wholesale Goods"
        }
    ],
    "sg:phone":"+1 919 490 6578",
    "sg:postcode":"27707",
    "sg:province":"NC",
    "sg:tags":[
        "publisher"
    ],
    "wof:name":"Alice Leyland Publishing",
    "wof:placetype":"venue"
},
  "geometry": {"coordinates":[-78.92484,35.991395],"type":"Point"}
}