{
  "type": "Feature",
  "properties": {
    "iso:country":"US",
    "sg:address":"5101 Sellers St",
    "sg:city":"South Brunswick",
    "sg:classifiers":[
        {
            "category":"Real Estate",
            "subcategory":"Real Estate Agent",
            "type":"Services"
        }
    ],
    "sg:phone":"+1 910 755 7190",
    "sg:postcode":"28470",
    "sg:province":"NC",
    "wof:name":"Jeffrey Milliken Real Estate",
    "wof:placetype":"venue"
},
  "geometry": {"coordinates":[-78.39389199999999,33.963238],"type":"Point"}
}