{
  "type": "Feature",
  "properties": {
    "iso:country":"US",
    "sg:address":"8704 Wellsley Way",
    "sg:city":"Raleigh",
    "sg:classifiers":[
        {
            "category":"Education",
            "subcategory":"Vocational School",
            "type":"Public Place"
        },
        {
            "category":"Shopping",
            "subcategory":"Computers & Home Electronics",
            "type":"Retail Goods"
        },
        {
            "category":"Wholesale",
            "subcategory":"Computers",
            "type":"Manufacturing & Wholesale Goods"
        }
    ],
    "sg:phone":"+1 919 845 0321",
    "sg:postcode":"27613",
    "sg:province":"NC",
    "sg:tags":[
        "hardware",
        "equipment",
        "business",
        "supply"
    ],
    "wof:name":"Tripp Lite",
    "wof:placetype":"venue"
},
  "geometry": {"coordinates":[-78.693139,35.898124],"type":"Point"}
}