{
  "type": "Feature",
  "properties": {
    "iso:country":"US",
    "sg:address":"5134 Sharon Church Rd",
    "sg:city":"Kinston",
    "sg:classifiers":[
        {
            "category":"Freight",
            "type":"Transportation"
        }
    ],
    "sg:phone":"+1 252 523 2279",
    "sg:postcode":"28501",
    "sg:province":"NC",
    "sg:tags":[
        "operator",
        "local",
        "trucking"
    ],
    "wof:name":"Abbott Trucking",
    "wof:placetype":"venue"
},
  "geometry": {"coordinates":[-77.51045499999999,35.3699],"type":"Point"}
}