{
  "type": "Feature",
  "properties": {
    "addr:full":"113 James J Freeland Memorial Dr Hillsborough NC 27278",
    "addr:housenumber":"113",
    "addr:postcode":"27278",
    "addr:street":"James J Freeland Memorial Dr",
    "iso:country":"US",
    "sg:address":"113 James J Freeland Memorial Dr",
    "sg:city":"Hillsborough",
    "sg:classifiers":[
        {
            "category":"Shopping",
            "subcategory":"Used Merchandise",
            "type":"Retail Goods"
        }
    ],
    "sg:phone":"+1 919 732 5081",
    "sg:postcode":"27278",
    "sg:province":"NC",
    "wof:name":"Gatewood Antiques",
    "wof:placetype":"venue"
},
  "geometry": {"coordinates":[-79.103419,36.059617],"type":"Point"}
}