{
  "type": "Feature",
  "properties": {
    "iso:country":"US",
    "sg:address":"624 9th St",
    "sg:city":"Durham",
    "sg:classifiers":[
        {
            "category":"Retail",
            "subcategory":"Photofinishing",
            "type":"Services"
        }
    ],
    "sg:phone":"+1 919 286 7655",
    "sg:postcode":"27705",
    "sg:province":"NC",
    "sg:tags":[
        "laboratory"
    ],
    "wof:name":"CCI Photographics",
    "wof:placetype":"venue"
},
  "geometry": {"coordinates":[-78.922118,36.007393],"type":"Point"}
}