{
  "type": "Feature",
  "properties": {
    "iso:country":"US",
    "sg:address":"34 Yellow Jacket Dr",
    "sg:city":"Hayesville",
    "sg:classifiers":[
        {
            "category":"Shopping",
            "subcategory":"Used Merchandise",
            "type":"Retail Goods"
        }
    ],
    "sg:phone":"+1 828 389 0164",
    "sg:postcode":"28904",
    "sg:province":"NC",
    "sg:tags":[
        "flea",
        "market"
    ],
    "wof:name":"Best Little Antique House",
    "wof:placetype":"venue"
},
  "geometry": {"coordinates":[-83.81725299999999,35.039398],"type":"Point"}
}