{
  "type": "Feature",
  "properties": {
    "addr:full":"1745 Kehukee Church Rd Scotland Neck NC 27874",
    "addr:housenumber":"1745",
    "addr:postcode":"27874",
    "addr:street":"Kehukee Church Rd",
    "iso:country":"US",
    "sg:address":"1745 Kehukee Church Rd",
    "sg:city":"Scotland Neck",
    "sg:phone":"+1 252 826 3578",
    "sg:postcode":"27874",
    "sg:province":"NC",
    "sg:tags":[
        "farm",
        "tobacco"
    ],
    "wof:name":"James Davis",
    "wof:placetype":"venue"
},
  "geometry": {"coordinates":[-77.391137,36.09123],"type":"Point"}
}