{
  "type": "Feature",
  "properties": {
    "iso:country":"US",
    "sg:address":"1004 Camden Ln",
    "sg:city":"Chapel Hill",
    "sg:classifiers":[
        {
            "category":"Professional",
            "subcategory":"Computer Services",
            "type":"Services"
        }
    ],
    "sg:phone":"+1   ",
    "sg:postcode":"27516",
    "sg:province":"NC",
    "sg:tags":[
        "related"
    ],
    "wof:name":"Callimanis",
    "wof:placetype":"venue"
},
  "geometry": {"coordinates":[-79.08561899999999,35.948079],"type":"Point"}
}