{
  "type": "Feature",
  "properties": {
    "addr:full":"225 Summit Ave Greensboro NC 27401",
    "addr:housenumber":"225",
    "addr:postcode":"27401",
    "addr:street":"Summit Ave",
    "iso:country":"US",
    "sg:address":"225 Summit Ave",
    "sg:city":"Greensboro",
    "sg:classifiers":[
        {
            "category":"Retail",
            "subcategory":"Repair Shop",
            "type":"Services"
        }
    ],
    "sg:phone":"+1 336 333 0040",
    "sg:postcode":"27401",
    "sg:province":"NC",
    "sg:tags":[
        "upholsterer"
    ],
    "wof:name":"Harvey's Upholstery",
    "wof:placetype":"venue"
},
  "geometry": {"coordinates":[-79.787418,36.076317],"type":"Point"}
}