{
  "type": "Feature",
  "properties": {
    "iso:country":"US",
    "sg:address":"338 Pine Ridge Rd",
    "sg:city":"Windsor",
    "sg:phone":"+1 252 794 2852",
    "sg:postcode":"27983",
    "sg:province":"NC",
    "sg:tags":[
        "farm",
        "tobacco"
    ],
    "wof:name":"Herbert Askew Farm",
    "wof:placetype":"venue"
},
  "geometry": {"coordinates":[-76.86550699999999,36.089031],"type":"Point"}
}