{
  "type": "Feature",
  "properties": {
    "addr:full":"1 Indigo Lake Ter Greensboro NC 27455",
    "addr:housenumber":"1",
    "addr:postcode":"27455",
    "addr:street":"Indigo Lake Ter",
    "iso:country":"US",
    "sg:address":"1 Indigo Lake Ter",
    "sg:city":"Greensboro",
    "sg:classifiers":[
        {
            "category":"Professional",
            "subcategory":"Management & Consulting",
            "type":"Services"
        }
    ],
    "sg:phone":"+1   ",
    "sg:postcode":"27455",
    "sg:province":"NC",
    "sg:tags":[
        "public",
        "relations"
    ],
    "wof:name":"Capital City Promotions LLC",
    "wof:placetype":"venue"
},
  "geometry": {"coordinates":[-79.805961,36.147583],"type":"Point"}
}