{
  "type": "Feature",
  "properties": {
    "addr:full":"6400 Shallowford Rd Lewisville NC 27023",
    "addr:housenumber":"6400",
    "addr:postcode":"27023",
    "addr:street":"Shallowford Rd",
    "iso:country":"US",
    "sg:address":"6400 Shallowford Rd",
    "sg:city":"Lewisville",
    "sg:classifiers":[
        {
            "category":"Wholesale",
            "subcategory":"Electrical",
            "type":"Manufacturing & Wholesale Goods"
        }
    ],
    "sg:phone":"+1 336 945 3755",
    "sg:postcode":"27023",
    "sg:province":"NC",
    "sg:tags":[
        "alarm",
        "burglar",
        "system"
    ],
    "wof:name":"Dynamark Security Ctr",
    "wof:placetype":"venue"
},
  "geometry": {"coordinates":[-80.416763,36.098313],"type":"Point"}
}