{
  "type": "Feature",
  "properties": {
    "addr:full":"822 E Main St Jefferson NC 28640",
    "addr:housenumber":"822",
    "addr:postcode":"28640",
    "addr:street":"E Main St",
    "iso:country":"US",
    "sg:address":"822 E Main St",
    "sg:city":"Jefferson",
    "sg:classifiers":[
        {
            "category":"Shopping",
            "subcategory":"Department Store",
            "type":"Retail Goods"
        }
    ],
    "sg:phone":"+1 336 246 4552",
    "sg:postcode":"28640",
    "sg:province":"NC",
    "wof:name":"Rose's Stores",
    "wof:placetype":"venue"
},
  "geometry": {"coordinates":[-81.455493,36.41991],"type":"Point"}
}