{
  "type": "Feature",
  "properties": {
    "iso:country":"US",
    "sg:address":"1641 New Garden Rd",
    "sg:city":"Greensboro",
    "sg:classifiers":[
        {
            "category":"Restaurant",
            "type":"Food & Drink"
        }
    ],
    "sg:phone":"+1 336 855 5158",
    "sg:postcode":"27410",
    "sg:province":"NC",
    "wof:name":"Phoenix Asian Cuisine",
    "wof:placetype":"venue"
},
  "geometry": {"coordinates":[-79.876097,36.116762],"type":"Point"}
}