{
  "type": "Feature",
  "properties": {
    "addr:full":"7876 Sedgebrook Dr E Stanley NC 28164",
    "addr:housenumber":"7876",
    "addr:postcode":"28164",
    "addr:street":"Sedgebrook Dr E",
    "iso:country":"US",
    "sg:address":"7876 Sedgebrook Dr E",
    "sg:city":"Stanley",
    "sg:classifiers":[
        {
            "category":"Manufacturing",
            "subcategory":"Printing",
            "type":"Manufacturing & Wholesale Goods"
        }
    ],
    "sg:phone":"+1 704 827 2557",
    "sg:postcode":"28164",
    "sg:province":"NC",
    "sg:tags":[
        "printer"
    ],
    "wof:name":"Heritage Printing & Graphics",
    "wof:placetype":"venue"
},
  "geometry": {"coordinates":[-80.992192,35.438308],"type":"Point"}
}