{
  "type": "Feature",
  "properties": {
    "iso:country":"US",
    "sg:address":"604 N Main St",
    "sg:city":"Fuquay Varina",
    "sg:classifiers":[
        {
            "category":"Retail",
            "subcategory":"Funeral Services",
            "type":"Services"
        }
    ],
    "sg:phone":"+1   ",
    "sg:postcode":"27526",
    "sg:province":"NC",
    "wof:name":"Greenlawn Memorial Gardens",
    "wof:placetype":"venue"
},
  "geometry": {"coordinates":[-78.794177,35.591384],"type":"Point"}
}