{
  "type": "Feature",
  "properties": {
    "addr:full":"2557 Ravenhill Dr Fayetteville NC 28303",
    "addr:housenumber":"2557",
    "addr:postcode":"28303",
    "addr:street":"Ravenhill Dr",
    "iso:country":"US",
    "sg:address":"2557 Ravenhill Dr",
    "sg:city":"Fayetteville",
    "sg:classifiers":[
        {
            "category":"Banks & Credit Unions",
            "subcategory":"Bank",
            "type":"Services"
        }
    ],
    "sg:phone":"+1 910 485 1104",
    "sg:postcode":"28303",
    "sg:province":"NC",
    "sg:tags":[
        "mortgage"
    ],
    "wof:name":"Charter One",
    "wof:placetype":"venue"
},
  "geometry": {"coordinates":[-78.92596,35.046444],"type":"Point"}
}