{
  "type": "Feature",
  "properties": {
    "iso:country":"US",
    "sg:address":"42 Concord Rd",
    "sg:city":"Asheville",
    "sg:classifiers":[
        {
            "category":"Manufacturing",
            "subcategory":"Printing",
            "type":"Manufacturing & Wholesale Goods"
        }
    ],
    "sg:phone":"+1 828 650 9784",
    "sg:postcode":"28803",
    "sg:province":"NC",
    "sg:tags":[
        "publishing"
    ],
    "wof:name":"Bigdog Publishing LLC",
    "wof:placetype":"venue"
},
  "geometry": {"coordinates":[-82.498575,35.491426],"type":"Point"}
}