{
  "type": "Feature",
  "properties": {
    "addr:full":"828 Kenwood Rd Cherryville NC 28021",
    "addr:housenumber":"828",
    "addr:postcode":"28021",
    "addr:street":"Kenwood Rd",
    "iso:country":"US",
    "sg:address":"828 Kenwood Rd",
    "sg:city":"Cherryville",
    "sg:classifiers":[
        {
            "category":"Building & Trades",
            "subcategory":"Construction",
            "type":"Services"
        }
    ],
    "sg:phone":"+1 704 435 6744",
    "sg:postcode":"28021",
    "sg:province":"NC",
    "sg:tags":[
        "concrete",
        "contractor"
    ],
    "wof:name":"Wilson Concrete Contractors",
    "wof:placetype":"venue"
},
  "geometry": {"coordinates":[-81.34888599999999,35.370619],"type":"Point"}
}