{
  "type": "Feature",
  "properties": {
    "addr:full":"3806 Degrasse Dr Charlotte NC 28269",
    "addr:housenumber":"3806",
    "addr:postcode":"28269",
    "addr:street":"Degrasse Dr",
    "iso:country":"US",
    "sg:address":"3806 Degrasse Dr",
    "sg:city":"Charlotte",
    "sg:classifiers":[
        {
            "category":"Professional",
            "subcategory":"Business Services",
            "type":"Services"
        }
    ],
    "sg:phone":"+1   ",
    "sg:postcode":"28269",
    "sg:province":"NC",
    "wof:name":"Pacifica Communications",
    "wof:placetype":"venue"
},
  "geometry": {"coordinates":[-80.78322799999999,35.337308],"type":"Point"}
}