{
  "type": "Feature",
  "properties": {
    "addr:full":"1723 E Cone Blvd Greensboro NC 27405",
    "addr:housenumber":"1723",
    "addr:postcode":"27405",
    "addr:street":"E Cone Blvd",
    "iso:country":"US",
    "sg:address":"1723 E Cone Blvd",
    "sg:city":"Greensboro",
    "sg:classifiers":[
        {
            "category":"Professional",
            "subcategory":"Computer Services",
            "type":"Services"
        }
    ],
    "sg:phone":"+1   ",
    "sg:postcode":"27405",
    "sg:province":"NC",
    "wof:name":"Team Rampant Gecko",
    "wof:placetype":"venue"
},
  "geometry": {"coordinates":[-79.757279,36.112899],"type":"Point"}
}