{
  "type": "Feature",
  "properties": {
    "addr:full":"202 Burler St Lexington NC 27292",
    "addr:housenumber":"202",
    "addr:postcode":"27292",
    "addr:street":"Burler St",
    "iso:country":"US",
    "sg:address":"202 Burler St",
    "sg:city":"Lexington",
    "sg:classifiers":[
        {
            "category":"Building & Trades",
            "subcategory":"Construction",
            "type":"Services"
        }
    ],
    "sg:phone":"+1 336 236 6381",
    "sg:postcode":"27292",
    "sg:province":"NC",
    "sg:tags":[
        "hanging",
        "contractor"
    ],
    "wof:name":"Storys Painting & Wall Co",
    "wof:placetype":"venue"
},
  "geometry": {"coordinates":[-80.266988,35.830257],"type":"Point"}
}