{
  "type": "Feature",
  "properties": {
    "addr:full":"723 Fleming St NE Wilson NC 27893",
    "addr:housenumber":"723",
    "addr:postcode":"27893",
    "addr:street":"Fleming St Ne",
    "iso:country":"US",
    "sg:address":"723 Fleming St NE",
    "sg:city":"Wilson",
    "sg:classifiers":[
        {
            "category":"Social Services",
            "subcategory":"Adult Care",
            "type":"Services"
        }
    ],
    "sg:phone":"+1 252 234 9996",
    "sg:postcode":"27893",
    "sg:province":"NC",
    "sg:tags":[
        "residential"
    ],
    "wof:name":"Loises House",
    "wof:placetype":"venue"
},
  "geometry": {"coordinates":[-77.91067,35.741001],"type":"Point"}
}