{
  "type": "Feature",
  "properties": {
    "iso:country":"US",
    "sg:address":"2115 W Front St",
    "sg:city":"Statesville",
    "sg:classifiers":[
        {
            "category":"Wholesale",
            "subcategory":"Electrical",
            "type":"Manufacturing & Wholesale Goods"
        }
    ],
    "sg:phone":"+1 704 873 1006",
    "sg:postcode":"28677",
    "sg:province":"NC",
    "sg:tags":[
        "equipment"
    ],
    "wof:name":"Rexel Inc",
    "wof:placetype":"venue"
},
  "geometry": {"coordinates":[-80.923097,35.788736],"type":"Point"}
}