{
  "type": "Feature",
  "properties": {
    "addr:full":"1013 Toms St Shelby NC 28150",
    "addr:housenumber":"1013",
    "addr:postcode":"28150",
    "addr:street":"Toms St",
    "iso:country":"US",
    "sg:address":"1013 Toms St",
    "sg:city":"Shelby",
    "sg:classifiers":[
        {
            "category":"Social Services",
            "type":"Services"
        }
    ],
    "sg:phone":"+1   ",
    "sg:postcode":"28150",
    "sg:province":"NC",
    "wof:name":"Wilson Respite Services",
    "wof:placetype":"venue"
},
  "geometry": {"coordinates":[-81.52412699999999,35.302121],"type":"Point"}
}