{
  "type": "Feature",
  "properties": {
    "iso:country":"US",
    "sg:address":"300 Ross Grove Rd E",
    "sg:city":"Shelby",
    "sg:classifiers":[
        {
            "category":"Organizations",
            "subcategory":"Religious Organization",
            "type":"Services"
        }
    ],
    "sg:phone":"+1 704 480 0906",
    "sg:postcode":"28150",
    "sg:province":"NC",
    "sg:tags":[
        "church"
    ],
    "wof:name":"Solid Rock Independent Mission",
    "wof:placetype":"venue"
},
  "geometry": {"coordinates":[-81.53126899999999,35.316874],"type":"Point"}
}