{
  "type": "Feature",
  "properties": {
    "addr:full":"5756 Casar Rd Casar NC 28020",
    "addr:housenumber":"5756",
    "addr:postcode":"28020",
    "addr:street":"Casar Rd",
    "iso:country":"US",
    "sg:address":"5756 Casar Rd",
    "sg:city":"Casar",
    "sg:classifiers":[
        {
            "category":"Food & Beverages",
            "subcategory":"Groceries & Convenience Stores",
            "type":"Retail Goods"
        }
    ],
    "sg:phone":"+1 704 538 8020",
    "sg:postcode":"28020",
    "sg:province":"NC",
    "sg:tags":[
        "grocer"
    ],
    "wof:name":"Mountain View Grocery",
    "wof:placetype":"venue"
},
  "geometry": {"coordinates":[-81.622384,35.508252],"type":"Point"}
}