{
  "type": "Feature",
  "properties": {
    "addr:full":"3553 N Sharon Amity Rd Charlotte NC 28205",
    "addr:housenumber":"3553",
    "addr:postcode":"28205",
    "addr:street":"N Sharon Amity Rd",
    "iso:country":"US",
    "sg:address":"3553 N Sharon Amity Rd",
    "sg:city":"Charlotte",
    "sg:classifiers":[
        {
            "category":"Personal",
            "subcategory":"Beauty Salon",
            "type":"Services"
        }
    ],
    "sg:phone":"+1 704 566 9382",
    "sg:postcode":"28205",
    "sg:province":"NC",
    "wof:name":"G Q Hair Clinic",
    "wof:placetype":"venue"
},
  "geometry": {"coordinates":[-80.757318,35.209547],"type":"Point"}
}