{
  "type": "Feature",
  "properties": {
    "addr:full":"181 Edgewater Rd Hickory NC 28601",
    "addr:housenumber":"181",
    "addr:postcode":"28601",
    "addr:street":"Edgewater Rd",
    "iso:country":"US",
    "sg:address":"181 Edgewater Rd",
    "sg:city":"Hickory",
    "sg:classifiers":[
        {
            "category":"Wholesale",
            "subcategory":"Toys & Hobbies",
            "type":"Manufacturing & Wholesale Goods"
        }
    ],
    "sg:phone":"+1 828 495 2012",
    "sg:postcode":"28601",
    "sg:province":"NC",
    "sg:tags":[
        "wholesaler"
    ],
    "wof:name":"Manufactured Housing Equipment",
    "wof:placetype":"venue"
},
  "geometry": {"coordinates":[-81.329988,35.80703],"type":"Point"}
}