{
  "type": "Feature",
  "properties": {
    "addr:full":"124 College St Asheville NC 28801",
    "addr:housenumber":"124",
    "addr:postcode":"28801",
    "addr:street":"College St",
    "iso:country":"US",
    "sg:address":"124 College St",
    "sg:city":"Asheville",
    "sg:classifiers":[
        {
            "category":"Real Estate",
            "subcategory":"Real Estate Agent",
            "type":"Services"
        }
    ],
    "sg:phone":"+1 828 255 8330",
    "sg:postcode":"28801",
    "sg:province":"NC",
    "wof:name":"Nichols Realty",
    "wof:placetype":"venue"
},
  "geometry": {"coordinates":[-82.550577,35.595859],"type":"Point"}
}