{
  "type": "Feature",
  "properties": {
    "iso:country":"US",
    "sg:address":"2137 Spring Branch Rd",
    "sg:city":"Tar Heel",
    "sg:classifiers":[
        {
            "category":"Health Services",
            "subcategory":"Nursing And Care Facility",
            "type":"Services"
        }
    ],
    "sg:phone":"+1 910 862 2696",
    "sg:postcode":"28392",
    "sg:province":"NC",
    "sg:tags":[
        "home",
        "rest"
    ],
    "wof:name":"Eastland Home",
    "wof:placetype":"venue"
},
  "geometry": {"coordinates":[-78.833636,34.762291],"type":"Point"}
}