{
  "type": "Feature",
  "properties": {
    "addr:full":"3684 Eaton Rd Kittrell NC 27544",
    "addr:housenumber":"3684",
    "addr:postcode":"27544",
    "addr:street":"Eaton Rd",
    "iso:country":"US",
    "sg:address":"3684 Eaton Rd",
    "sg:city":"Kittrell",
    "sg:classifiers":[
        {
            "category":"Building & Trades",
            "subcategory":"Construction",
            "type":"Services"
        }
    ],
    "sg:phone":"+1 919 693 8149",
    "sg:postcode":"27544",
    "sg:province":"NC",
    "sg:tags":[
        "contractor"
    ],
    "wof:name":"TCM Construction",
    "wof:placetype":"venue"
},
  "geometry": {"coordinates":[-78.574709,36.22323],"type":"Point"}
}