{
  "type": "Feature",
  "properties": {
    "addr:full":"222 S French Broad Ave Asheville NC 28801",
    "addr:housenumber":"222",
    "addr:postcode":"28801",
    "addr:street":"S French Broad Ave",
    "iso:country":"US",
    "sg:address":"222 S French Broad Ave",
    "sg:city":"Asheville",
    "sg:classifiers":[
        {
            "category":"Social Services",
            "type":"Services"
        }
    ],
    "sg:phone":"+1   ",
    "sg:postcode":"28801",
    "sg:province":"NC",
    "wof:name":"Hospitality House",
    "wof:placetype":"venue"
},
  "geometry": {"coordinates":[-82.559359,35.58626],"type":"Point"}
}