{
  "type": "Feature",
  "properties": {
    "iso:country":"US",
    "sg:address":"209 S Wilson Ave",
    "sg:city":"Dunn",
    "sg:classifiers":[
        {
            "category":"Professional",
            "subcategory":"Lawyer & Legal Services",
            "type":"Services"
        }
    ],
    "sg:phone":"+1 910 892 6136",
    "sg:postcode":"28334",
    "sg:province":"NC",
    "sg:tags":[
        "attorney"
    ],
    "wof:name":"Mc Leod & Harrop",
    "wof:placetype":"venue"
},
  "geometry": {"coordinates":[-78.610029,35.306738],"type":"Point"}
}