{
  "type": "Feature",
  "properties": {
    "iso:country":"US",
    "sg:address":"1412 S Main St",
    "sg:city":"Laurinburg",
    "sg:classifiers":[
        {
            "category":"Personal",
            "subcategory":"Tattoo Parlor",
            "type":"Services"
        }
    ],
    "sg:phone":"+1 910 276 1122",
    "sg:postcode":"28352",
    "sg:province":"NC",
    "sg:tags":[
        "tattooing"
    ],
    "wof:name":"Illusion Dermagraphics",
    "wof:placetype":"venue"
},
  "geometry": {"coordinates":[-79.47003599999999,34.759908],"type":"Point"}
}