{
  "type": "Feature",
  "properties": {
    "iso:country":"US",
    "sg:address":"3504 N Kerr Ave",
    "sg:city":"Wilmington",
    "sg:classifiers":[
        {
            "category":"Social Services",
            "subcategory":"Child Care",
            "type":"Services"
        }
    ],
    "sg:phone":"+1 910 675 8682",
    "sg:postcode":"28405",
    "sg:province":"NC",
    "wof:name":"Nancy's After School Care",
    "wof:placetype":"venue"
},
  "geometry": {"coordinates":[-77.91442499999999,34.288948],"type":"Point"}
}