{
  "type": "Feature",
  "properties": {
    "iso:country":"US",
    "sg:address":"213 River St",
    "sg:city":"High Shoals",
    "sg:classifiers":[
        {
            "category":"Professional",
            "subcategory":"Business Services",
            "type":"Services"
        }
    ],
    "sg:phone":"+1   ",
    "sg:postcode":"28077",
    "sg:province":"NC",
    "wof:name":"Weekley Enterprise LLC",
    "wof:placetype":"venue"
},
  "geometry": {"coordinates":[-81.20311,35.402032],"type":"Point"}
}