{
  "type": "Feature",
  "properties": {
    "addr:full":"1940 Carolina Beach Rd Wilmington NC 28401",
    "addr:housenumber":"1940",
    "addr:postcode":"28401",
    "addr:street":"Carolina Beach Rd",
    "iso:country":"US",
    "sg:address":"1940 Carolina Beach Rd",
    "sg:city":"Wilmington",
    "sg:classifiers":[
        {
            "category":"Shopping",
            "subcategory":"Used Merchandise",
            "type":"Retail Goods"
        }
    ],
    "sg:phone":"+1 910 343 8327",
    "sg:postcode":"28401",
    "sg:province":"NC",
    "sg:tags":[
        "shop",
        "thrift"
    ],
    "wof:name":"Open Arms 101",
    "wof:placetype":"venue"
},
  "geometry": {"coordinates":[-77.943217,34.206879],"type":"Point"}
}