{
  "type": "Feature",
  "properties": {
    "iso:country":"US",
    "sg:address":"925 Reedy Creek Rd",
    "sg:city":"Lexington",
    "sg:classifiers":[
        {
            "category":"Retail",
            "subcategory":"Auto Repair",
            "type":"Services"
        }
    ],
    "sg:phone":"+1 336 731 4640",
    "sg:postcode":"27295",
    "sg:province":"NC",
    "sg:tags":[
        "body",
        "automobile",
        "painting"
    ],
    "wof:name":"Byerly Brothers Used Cars",
    "wof:placetype":"venue"
},
  "geometry": {"coordinates":[-80.31991499999999,35.918874],"type":"Point"}
}