{
  "type": "Feature",
  "properties": {
    "iso:country":"US",
    "sg:address":"617 Laurel Lake Dr",
    "sg:city":"Columbus",
    "sg:classifiers":[
        {
            "category":"Real Estate",
            "subcategory":"Real Estate Operator",
            "type":"Services"
        }
    ],
    "sg:phone":"+1 828 894 3000",
    "sg:postcode":"28722",
    "sg:province":"NC",
    "sg:tags":[
        "building",
        "apartment",
        "skilled",
        "nursing",
        "care"
    ],
    "wof:name":"Acts",
    "wof:placetype":"venue"
},
  "geometry": {"coordinates":[-82.193493,35.23833],"type":"Point"}
}