{
  "type": "Feature",
  "properties": {
    "iso:country":"US",
    "sg:address":"6002 Embassy Ct",
    "sg:city":"Monroe",
    "sg:classifiers":[
        {
            "category":"Insurance",
            "subcategory":"Insurance Agent",
            "type":"Services"
        }
    ],
    "sg:phone":"+1 704 821 4544",
    "sg:postcode":"28110",
    "sg:province":"NC",
    "wof:name":"Allstate Insurance",
    "wof:placetype":"venue"
},
  "geometry": {"coordinates":[-80.669389,34.999169],"type":"Point"}
}