{
  "type": "Feature",
  "properties": {
    "addr:full":"584 Dragstrip Rd Benson NC 27504",
    "addr:housenumber":"584",
    "addr:postcode":"27504",
    "addr:street":"Dragstrip Rd",
    "iso:country":"US",
    "sg:address":"584 Dragstrip Rd",
    "sg:city":"Benson",
    "sg:classifiers":[
        {
            "category":"Freight",
            "type":"Transportation"
        }
    ],
    "sg:phone":"+1 919 894 1803",
    "sg:postcode":"27504",
    "sg:province":"NC",
    "sg:tags":[
        "operator",
        "local",
        "trucking"
    ],
    "wof:name":"Mule City Trucking Inc",
    "wof:placetype":"venue"
},
  "geometry": {"coordinates":[-78.49893899999999,35.324639],"type":"Point"}
}