{
  "type": "Feature",
  "properties": {
    "addr:full":"7422 Carmel Executive Park Dr Charlotte NC 28226",
    "addr:housenumber":"7422",
    "addr:postcode":"28226",
    "addr:street":"Carmel Executive Park Dr",
    "iso:country":"US",
    "sg:address":"7422 Carmel Executive Park Dr",
    "sg:city":"Charlotte",
    "sg:classifiers":[
        {
            "category":"Banks & Credit Unions",
            "subcategory":"Bank",
            "type":"Services"
        }
    ],
    "sg:phone":"+1 704 752 1810",
    "sg:postcode":"28226",
    "sg:province":"NC",
    "sg:tags":[
        "loan",
        "real estate"
    ],
    "wof:name":"Atlantis Mortgage Co Inc",
    "wof:placetype":"venue"
},
  "geometry": {"coordinates":[-80.84466,35.089034],"type":"Point"}
}