{
  "type": "Feature",
  "properties": {
    "addr:full":"238 E Russell St Fayetteville NC 28301",
    "addr:housenumber":"238",
    "addr:postcode":"28301",
    "addr:street":"E Russell St",
    "iso:country":"US",
    "sg:address":"238 E Russell St",
    "sg:city":"Fayetteville",
    "sg:classifiers":[
        {
            "category":"Autos & Motor Vehicles",
            "subcategory":"Auto Supplies",
            "type":"Retail Goods"
        },
        {
            "category":"Wholesale",
            "subcategory":"Auto Parts",
            "type":"Manufacturing & Wholesale Goods"
        }
    ],
    "sg:phone":"+1 910 483 1433",
    "sg:postcode":"28301",
    "sg:province":"NC",
    "sg:tags":[
        "automobile"
    ],
    "wof:name":"Ideal Auto Supply Co Inc",
    "wof:placetype":"venue"
},
  "geometry": {"coordinates":[-78.875502,35.049255],"type":"Point"}
}