{
  "type": "Feature",
  "properties": {
    "iso:country":"US",
    "sg:address":"6982 US Hwy 158",
    "sg:city":"Leasburg",
    "sg:classifiers":[
        {
            "category":"Building & Trades",
            "subcategory":"Construction",
            "type":"Services"
        }
    ],
    "sg:phone":"+1 336 599 1961",
    "sg:postcode":"27291",
    "sg:province":"NC",
    "sg:tags":[
        "contractor"
    ],
    "wof:name":"Quality Masonry",
    "wof:placetype":"venue"
},
  "geometry": {"coordinates":[-79.176441,36.397003],"type":"Point"}
}