{
  "type": "Feature",
  "properties": {
    "addr:full":"814 State Hwy 27 Albemarle NC 28001",
    "addr:housenumber":"814",
    "addr:postcode":"28001",
    "addr:street":"State Hwy 27",
    "iso:country":"US",
    "sg:address":"814 State Hwy 27",
    "sg:city":"Albemarle",
    "sg:classifiers":[
        {
            "category":"Shopping",
            "subcategory":"Department Store",
            "type":"Retail Goods"
        }
    ],
    "sg:phone":"+1 704 983 1178",
    "sg:postcode":"28001",
    "sg:province":"NC",
    "sg:website":"www.belk.com",
    "wof:name":"Belk",
    "wof:placetype":"venue"
},
  "geometry": {"coordinates":[-80.205043,35.338717],"type":"Point"}
}