{
  "type": "Feature",
  "properties": {
    "iso:country":"US",
    "sg:address":"311 Southfork Dr",
    "sg:city":"Belmont",
    "sg:classifiers":[
        {
            "category":"Professional",
            "subcategory":"Management & Consulting",
            "type":"Services"
        }
    ],
    "sg:phone":"+1   ",
    "sg:postcode":"28012",
    "sg:province":"NC",
    "sg:tags":[
        "business"
    ],
    "wof:name":"Christeph Consulting LLC",
    "wof:placetype":"venue"
},
  "geometry": {"coordinates":[-81.053928,35.226104],"type":"Point"}
}