{
  "type": "Feature",
  "properties": {
    "iso:country":"US",
    "sg:address":"111 E Church St",
    "sg:city":"Nashville",
    "sg:classifiers":[
        {
            "category":"Manufacturing",
            "subcategory":"Signs",
            "type":"Manufacturing & Wholesale Goods"
        }
    ],
    "sg:phone":"+1 252 567 1451",
    "sg:postcode":"27856",
    "sg:province":"NC",
    "sg:tags":[
        "advertising",
        "specialty"
    ],
    "wof:name":"Brent Gray Signs & Graphics",
    "wof:placetype":"venue"
},
  "geometry": {"coordinates":[-77.966166,35.973063],"type":"Point"}
}