{
  "type": "Feature",
  "properties": {
    "addr:full":"149 Charley's Knob Rd Pisgah Forest NC 28768",
    "addr:housenumber":"149",
    "addr:postcode":"28768",
    "addr:street":"Charley'S Knob Rd",
    "iso:country":"US",
    "sg:address":"149 Charley's Knob Rd",
    "sg:city":"Pisgah Forest",
    "sg:classifiers":[
        {
            "category":"Building & Trades",
            "subcategory":"Construction",
            "type":"Services"
        }
    ],
    "sg:phone":"+1 828 877 4775",
    "sg:postcode":"28768",
    "sg:province":"NC",
    "sg:tags":[
        "house"
    ],
    "wof:name":"Donald E Singleton Const",
    "wof:placetype":"venue"
},
  "geometry": {"coordinates":[-82.671088,35.275705],"type":"Point"}
}