{
  "type": "Feature",
  "properties": {
    "addr:full":"502 Windstream Way Cary NC 27518",
    "addr:housenumber":"502",
    "addr:postcode":"27518",
    "addr:street":"Windstream Way",
    "iso:country":"US",
    "sg:address":"502 Windstream Way",
    "sg:city":"Cary",
    "sg:classifiers":[
        {
            "category":"Insurance",
            "subcategory":"Insurance Agent",
            "type":"Services"
        }
    ],
    "sg:phone":"+1 919 851 0029",
    "sg:postcode":"27518",
    "sg:province":"NC",
    "wof:name":"Ais Insurance",
    "wof:placetype":"venue"
},
  "geometry": {"coordinates":[-78.750744,35.735582],"type":"Point"}
}