{
  "type": "Feature",
  "properties": {
    "iso:country":"US",
    "sg:address":"4903 South Blvd",
    "sg:city":"Charlotte",
    "sg:classifiers":[
        {
            "category":"Shopping",
            "subcategory":"Jewelry",
            "type":"Retail Goods"
        }
    ],
    "sg:phone":"+1 704 523 3688",
    "sg:postcode":"28217",
    "sg:province":"NC",
    "sg:tags":[
        "jeweler"
    ],
    "wof:name":"Kim Sen Jewelry",
    "wof:placetype":"venue"
},
  "geometry": {"coordinates":[-80.875934,35.169405],"type":"Point"}
}