{
  "type": "Feature",
  "properties": {
    "addr:full":"4811 Pagetown Rd Burlington NC 27217",
    "addr:housenumber":"4811",
    "addr:postcode":"27217",
    "addr:street":"Pagetown Rd",
    "iso:country":"US",
    "sg:address":"4811 Pagetown Rd",
    "sg:city":"Burlington",
    "sg:classifiers":[
        {
            "category":"Social Services",
            "subcategory":"Child Care",
            "type":"Services"
        }
    ],
    "sg:phone":"+1 336 584 5850",
    "sg:postcode":"27217",
    "sg:province":"NC",
    "sg:tags":[
        "day"
    ],
    "wof:name":"Step By Step Child Care Center",
    "wof:placetype":"venue"
},
  "geometry": {"coordinates":[-79.454554,36.201734],"type":"Point"}
}