{
  "type": "Feature",
  "properties": {
    "iso:country":"US",
    "sg:address":"276 Sunset Dr",
    "sg:city":"Blowing Rock",
    "sg:classifiers":[
        {
            "category":"Real Estate",
            "subcategory":"Real Estate Agent",
            "type":"Services"
        }
    ],
    "sg:phone":"+1 828 295 7602",
    "sg:postcode":"28605",
    "sg:province":"NC",
    "wof:name":"Tellekamp/Campbell Real Estate",
    "wof:placetype":"venue"
},
  "geometry": {"coordinates":[-81.674959,36.132825],"type":"Point"}
}