{
  "type": "Feature",
  "properties": {
    "iso:country":"US",
    "sg:address":"1810 Planters Walk",
    "sg:city":"Greenville",
    "sg:classifiers":[
        {
            "category":"Wholesale",
            "subcategory":"Stationery",
            "type":"Manufacturing & Wholesale Goods"
        }
    ],
    "sg:phone":"+1 252 756 5445",
    "sg:postcode":"27858",
    "sg:province":"NC",
    "sg:tags":[
        "business",
        "form",
        "system"
    ],
    "sg:website":"www.relizon.com",
    "wof:name":"Relizon",
    "wof:placetype":"venue"
},
  "geometry": {"coordinates":[-77.34036399999999,35.574157],"type":"Point"}
}