{
  "type": "Feature",
  "properties": {
    "addr:full":"9547 James B White Hwy S Whiteville NC 28472",
    "addr:housenumber":"9547",
    "addr:postcode":"28472",
    "addr:street":"James B White Hwy S",
    "iso:country":"US",
    "sg:address":"9547 James B White Hwy S",
    "sg:city":"Whiteville",
    "sg:classifiers":[
        {
            "category":"Autos & Motor Vehicles",
            "subcategory":"Auto Supplies",
            "type":"Retail Goods"
        }
    ],
    "sg:phone":"+1 910 653 2459",
    "sg:postcode":"28472",
    "sg:province":"NC",
    "sg:tags":[
        "tire"
    ],
    "wof:name":"Burroughs Tire Svc",
    "wof:placetype":"venue"
},
  "geometry": {"coordinates":[-78.756946,34.215371],"type":"Point"}
}