{
  "type": "Feature",
  "properties": {
    "addr:full":"312 W 3rd Ave Gastonia NC 28052",
    "addr:housenumber":"312",
    "addr:postcode":"28052",
    "addr:street":"W 3Rd Ave",
    "iso:country":"US",
    "sg:address":"312 W 3rd Ave",
    "sg:city":"Gastonia",
    "sg:classifiers":[
        {
            "category":"Organizations",
            "subcategory":"Political Organization",
            "type":"Services"
        }
    ],
    "sg:phone":"+1 704 868 3330",
    "sg:postcode":"28052",
    "sg:province":"NC",
    "wof:name":"Gaston County Republican Party",
    "wof:placetype":"venue"
},
  "geometry": {"coordinates":[-81.187307,35.259178],"type":"Point"}
}