{
  "type": "Feature",
  "properties": {
    "addr:full":"2800 Asphalt Dr Winston Salem NC 27105",
    "addr:postcode":"2800;27105",
    "addr:street":"Asphalt Dr",
    "iso:country":"US",
    "sg:address":"2800 Asphalt Dr",
    "sg:city":"Winston Salem",
    "sg:classifiers":[
        {
            "category":"Manufacturing",
            "subcategory":"Petroleum Products",
            "type":"Manufacturing & Wholesale Goods"
        }
    ],
    "sg:phone":"+1 336 759 7802",
    "sg:postcode":"27105",
    "sg:province":"NC",
    "sg:tags":[
        "asphalt"
    ],
    "wof:name":"Thompson-Arthur Paving Co",
    "wof:placetype":"venue"
},
  "geometry": {"coordinates":[-80.26082100000001,36.146392],"type":"Point"}
}