{
  "type": "Feature",
  "properties": {
    "addr:full":"1660 Clark Rd Lillington NC 27546",
    "addr:housenumber":"1660",
    "addr:postcode":"27546",
    "addr:street":"Clark Rd",
    "iso:country":"US",
    "sg:address":"1660 Clark Rd",
    "sg:city":"Lillington",
    "sg:classifiers":[
        {
            "category":"Professional",
            "type":"Services"
        }
    ],
    "sg:phone":"+1 910 893 4245",
    "sg:postcode":"27546",
    "sg:province":"NC",
    "wof:name":"Rodney W Bennett",
    "wof:placetype":"venue"
},
  "geometry": {"coordinates":[-78.90993400000001,35.3382],"type":"Point"}
}