{
  "type": "Feature",
  "properties": {
    "iso:country":"US",
    "sg:address":"1816 Gum St",
    "sg:city":"Gastonia",
    "sg:classifiers":[
        {
            "category":"Organizations",
            "subcategory":"Religious Organization",
            "type":"Services"
        }
    ],
    "sg:phone":"+1   ",
    "sg:postcode":"28054",
    "sg:province":"NC",
    "wof:name":"Jesus Way Tabernacle Inc",
    "wof:placetype":"venue"
},
  "geometry": {"coordinates":[-81.155115,35.279472],"type":"Point"}
}