{
  "type": "Feature",
  "properties": {
    "addr:full":"826 Chapel Hill Rd Burlington NC 27215",
    "addr:housenumber":"826",
    "addr:postcode":"27215",
    "addr:street":"Chapel Hill Rd",
    "iso:country":"US",
    "sg:address":"826 Chapel Hill Rd",
    "sg:city":"Burlington",
    "sg:classifiers":[
        {
            "category":"Retail",
            "subcategory":"Repair Shop",
            "type":"Services"
        }
    ],
    "sg:phone":"+1 336 226 1637",
    "sg:postcode":"27215",
    "sg:province":"NC",
    "sg:tags":[
        "lock",
        "locksmith"
    ],
    "wof:name":"Coble Locksmith Co",
    "wof:placetype":"venue"
},
  "geometry": {"coordinates":[-79.43861,36.072735],"type":"Point"}
}