{
  "type": "Feature",
  "properties": {
    "addr:full":"1204 Grove St Greensboro NC 27403",
    "addr:housenumber":"1204",
    "addr:postcode":"27403",
    "addr:street":"Grove St",
    "iso:country":"US",
    "sg:address":"1204 Grove St",
    "sg:city":"Greensboro",
    "sg:classifiers":[
        {
            "category":"Building & Trades",
            "subcategory":"Plumbing",
            "type":"Services"
        }
    ],
    "sg:phone":"+1 336 379 7367",
    "sg:postcode":"27403",
    "sg:province":"NC",
    "sg:tags":[
        "mechanical",
        "contractor"
    ],
    "wof:name":"T R Svc Co",
    "wof:placetype":"venue"
},
  "geometry": {"coordinates":[-79.812304,36.053492],"type":"Point"}
}