{
  "type": "Feature",
  "properties": {
    "iso:country":"US",
    "sg:address":"3552 Ridgewood Ct",
    "sg:city":"Winston Salem",
    "sg:classifiers":[
        {
            "category":"Building & Trades",
            "subcategory":"Landscaping Services",
            "type":"Services"
        }
    ],
    "sg:phone":"+1 336 785 9489",
    "sg:postcode":"27107",
    "sg:province":"NC",
    "sg:tags":[
        "tree"
    ],
    "wof:name":"Carolina Hoist Professionals",
    "wof:placetype":"venue"
},
  "geometry": {"coordinates":[-80.158621,36.054661],"type":"Point"}
}