{
  "type": "Feature",
  "properties": {
    "iso:country":"US",
    "sg:address":"4200 Barrier Store Rd",
    "sg:city":"Mount Pleasant",
    "sg:classifiers":[
        {
            "category":"Professional",
            "type":"Services"
        }
    ],
    "sg:phone":"+1 704 436 6960",
    "sg:postcode":"28124",
    "sg:province":"NC",
    "wof:name":"Payroll Lease Plans",
    "wof:placetype":"venue"
},
  "geometry": {"coordinates":[-80.438204,35.362309],"type":"Point"}
}