{
  "type": "Feature",
  "properties": {
    "addr:full":"1312 Holt Rd Apex NC 27523",
    "addr:housenumber":"1312",
    "addr:postcode":"27523",
    "addr:street":"Holt Rd",
    "iso:country":"US",
    "sg:address":"1312 Holt Rd",
    "sg:city":"Apex",
    "sg:classifiers":[
        {
            "category":"Building & Trades",
            "subcategory":"Construction",
            "type":"Services"
        }
    ],
    "sg:phone":"+1 919 363 1969",
    "sg:postcode":"27523",
    "sg:province":"NC",
    "sg:tags":[
        "home",
        "builder"
    ],
    "wof:name":"Cattano Construction Inc",
    "wof:placetype":"venue"
},
  "geometry": {"coordinates":[-78.854039,35.764996],"type":"Point"}
}