{
  "type": "Feature",
  "properties": {
    "iso:country":"US",
    "sg:address":"1001 Marshall St N",
    "sg:city":"Winston Salem",
    "sg:classifiers":[
        {
            "category":"Education",
            "subcategory":"Vocational School",
            "type":"Public Place"
        }
    ],
    "sg:phone":"+1 336 724 1551",
    "sg:postcode":"27101",
    "sg:province":"NC",
    "sg:tags":[
        "training",
        "computer"
    ],
    "wof:name":"First Technology",
    "wof:placetype":"venue"
},
  "geometry": {"coordinates":[-80.25214200000001,36.107613],"type":"Point"}
}