{
  "type": "Feature",
  "properties": {
    "addr:full":"2350 Cragmore Rd SE Winston Salem NC 27107",
    "addr:postcode":"2350;27107",
    "addr:street":"Cragmore Rd Se",
    "iso:country":"US",
    "sg:address":"2350 Cragmore Rd SE",
    "sg:city":"Winston Salem",
    "sg:classifiers":[
        {
            "category":"Building & Trades",
            "subcategory":"Electrical",
            "type":"Services"
        }
    ],
    "sg:phone":"+1 336 650 0945",
    "sg:postcode":"27107",
    "sg:province":"NC",
    "sg:tags":[
        "electric",
        "contractor"
    ],
    "wof:name":"It's Electric",
    "wof:placetype":"venue"
},
  "geometry": {"coordinates":[-80.186735,36.069025],"type":"Point"}
}