{
  "type": "Feature",
  "properties": {
    "iso:country":"US",
    "sg:address":"425 Marshall Rd",
    "sg:city":"Hendersonville",
    "sg:classifiers":[
        {
            "category":"Building & Trades",
            "subcategory":"Construction",
            "type":"Services"
        }
    ],
    "sg:phone":"+1 828 685 3802",
    "sg:postcode":"28792",
    "sg:province":"NC",
    "sg:tags":[
        "residential"
    ],
    "wof:name":"Mc Crain Brothers Builders",
    "wof:placetype":"venue"
},
  "geometry": {"coordinates":[-82.32956900000001,35.368195],"type":"Point"}
}