{
  "type": "Feature",
  "properties": {
    "iso:country":"US",
    "sg:address":"11039 Painted Tree Rd",
    "sg:city":"Charlotte",
    "sg:phone":"+1 704 544 2103",
    "sg:postcode":"28226",
    "sg:province":"NC",
    "sg:tags":[
        "video",
        "conferencing"
    ],
    "wof:name":"Pena Enterprises Tortilleria",
    "wof:placetype":"venue"
},
  "geometry": {"coordinates":[-80.852988,35.078764],"type":"Point"}
}