{
  "type": "Feature",
  "properties": {
    "iso:country":"US",
    "sg:address":"3626 Westfield St",
    "sg:city":"High Point",
    "sg:classifiers":[
        {
            "category":"Professional",
            "type":"Services"
        }
    ],
    "sg:phone":"+1 336 869 0550",
    "sg:postcode":"27265",
    "sg:province":"NC",
    "wof:name":"Soto Corporation",
    "wof:placetype":"venue"
},
  "geometry": {"coordinates":[-80.01248099999999,36.008316],"type":"Point"}
}