{
  "type": "Feature",
  "properties": {
    "addr:full":"5928 Newman Smith Rd NW Ash NC 28459",
    "addr:housenumber":"5928",
    "addr:postcode":"28459",
    "addr:street":"Newman Smith Rd Nw",
    "iso:country":"US",
    "sg:address":"5928 Newman Smith Rd NW",
    "sg:city":"Ash",
    "sg:classifiers":[
        {
            "category":"Retail",
            "subcategory":"Auto Repair",
            "type":"Services"
        }
    ],
    "sg:phone":"+1 910 754 5640",
    "sg:postcode":"28459",
    "sg:province":"NC",
    "sg:tags":[
        "repairing",
        "automobile"
    ],
    "wof:name":"Smith's Automotive Repair Ctr",
    "wof:placetype":"venue"
},
  "geometry": {"coordinates":[-78.490832,34.013464],"type":"Point"}
}