{
  "type": "Feature",
  "properties": {
    "iso:country":"US",
    "sg:address":"800 Moultrie Ct",
    "sg:city":"Greensboro",
    "sg:classifiers":[
        {
            "category":"Social Services",
            "subcategory":"Child Care",
            "type":"Services"
        }
    ],
    "sg:phone":"+1 336 908 0405",
    "sg:postcode":"27409",
    "sg:province":"NC",
    "wof:name":"Academy Of Little Wonders",
    "wof:placetype":"venue"
},
  "geometry": {"coordinates":[-79.91618,36.056325],"type":"Point"}
}