{
  "type": "Feature",
  "properties": {
    "iso:country":"US",
    "sg:address":"420 W 4th St",
    "sg:city":"Winston Salem",
    "sg:classifiers":[
        {
            "category":"Professional",
            "type":"Services"
        }
    ],
    "sg:phone":"+1 336 761 0570",
    "sg:postcode":"27101",
    "sg:province":"NC",
    "wof:name":"Philip Hanes Ofc",
    "wof:placetype":"venue"
},
  "geometry": {"coordinates":[-80.24861300000001,36.097915],"type":"Point"}
}