{
  "type": "Feature",
  "properties": {
    "addr:full":"1028 E 22nd St Kannapolis NC 28083",
    "addr:housenumber":"1028",
    "addr:postcode":"28083",
    "addr:street":"E 22Nd St",
    "iso:country":"US",
    "sg:address":"1028 E 22nd St",
    "sg:city":"Kannapolis",
    "sg:classifiers":[
        {
            "category":"Organizations",
            "subcategory":"Membership Organization",
            "type":"Services"
        }
    ],
    "sg:phone":"+1   ",
    "sg:postcode":"28083",
    "sg:province":"NC",
    "wof:name":"Richard Petty Fan Club",
    "wof:placetype":"venue"
},
  "geometry": {"coordinates":[-80.59494599999999,35.523459],"type":"Point"}
}