{
  "type": "Feature",
  "properties": {
    "addr:full":"1242 Eps Rd Hickory NC 28602",
    "addr:housenumber":"1242",
    "addr:postcode":"28602",
    "addr:street":"Eps Rd",
    "iso:country":"US",
    "sg:address":"1242 Eps Rd",
    "sg:city":"Hickory",
    "sg:classifiers":[
        {
            "category":"Manufacturing",
            "subcategory":"Textiles",
            "type":"Manufacturing & Wholesale Goods"
        }
    ],
    "sg:phone":"+1 828 294 0715",
    "sg:postcode":"28602",
    "sg:province":"NC",
    "sg:tags":[
        "sock",
        "seam"
    ],
    "wof:name":"T T S Textile Seaming",
    "wof:placetype":"venue"
},
  "geometry": {"coordinates":[-81.398084,35.666078],"type":"Point"}
}