{
  "type": "Feature",
  "properties": {
    "addr:full":"2198 Hwy 903 S Snow Hill NC 28580",
    "addr:housenumber":"2198",
    "addr:postcode":"28580",
    "addr:street":"Hwy 903 S",
    "iso:country":"US",
    "sg:address":"2198 Hwy 903 S",
    "sg:city":"Snow Hill",
    "sg:classifiers":[
        {
            "category":"Building & Trades",
            "subcategory":"Construction",
            "type":"Services"
        }
    ],
    "sg:phone":"+1 252 747 5696",
    "sg:postcode":"28580",
    "sg:province":"NC",
    "sg:tags":[
        "contractor"
    ],
    "wof:name":"Sauls Insulation",
    "wof:placetype":"venue"
},
  "geometry": {"coordinates":[-77.71025,35.430609],"type":"Point"}
}