{
  "type": "Feature",
  "properties": {
    "iso:country":"US",
    "sg:address":"6209 Oleander Dr",
    "sg:city":"Wilmington",
    "sg:classifiers":[
        {
            "category":"Professional",
            "subcategory":"Employment Agencies",
            "type":"Services"
        }
    ],
    "sg:phone":"+1 910 799 5944",
    "sg:postcode":"28403",
    "sg:province":"NC",
    "sg:tags":[
        "opportunity"
    ],
    "wof:name":"Harper Hunter LLC",
    "wof:placetype":"venue"
},
  "geometry": {"coordinates":[-77.836195,34.21106],"type":"Point"}
}