{
  "type": "Feature",
  "properties": {
    "iso:country":"US",
    "sg:address":"4858 Sierra Dr",
    "sg:city":"Maiden",
    "sg:classifiers":[
        {
            "category":"Building & Trades",
            "subcategory":"Construction",
            "type":"Services"
        }
    ],
    "sg:phone":"+1 704 483 9051",
    "sg:postcode":"28650",
    "sg:province":"NC",
    "sg:tags":[
        "contractor"
    ],
    "wof:name":"Jr Sparrow Masonry",
    "wof:placetype":"venue"
},
  "geometry": {"coordinates":[-81.090279,35.575804],"type":"Point"}
}