{
  "type": "Feature",
  "properties": {
    "iso:country":"US",
    "sg:address":"156 Rudd Trl",
    "sg:city":"Hollister",
    "sg:classifiers":[
        {
            "category":"Banks & Credit Unions",
            "subcategory":"Bank",
            "type":"Services"
        }
    ],
    "sg:phone":"+1 252 586 2270",
    "sg:postcode":"27844",
    "sg:province":"NC",
    "sg:tags":[
        "loan",
        "real estate"
    ],
    "wof:name":"Leader Mortgage",
    "wof:placetype":"venue"
},
  "geometry": {"coordinates":[-77.950332,36.290719],"type":"Point"}
}