{
  "type": "Feature",
  "properties": {
    "iso:country":"US",
    "sg:address":"9579 South Blvd",
    "sg:city":"Charlotte",
    "sg:classifiers":[
        {
            "category":"Shopping",
            "subcategory":"Department Store",
            "type":"Retail Goods"
        }
    ],
    "sg:phone":"+1 704 643 1070",
    "sg:postcode":"28273",
    "sg:province":"NC",
    "sg:website":"http://www.kohls.com",
    "wof:name":"Kohl's",
    "wof:placetype":"venue"
},
  "geometry": {"coordinates":[-80.88088399999999,35.106034],"type":"Point"}
}