{
  "type": "Feature",
  "properties": {
    "iso:country":"US",
    "sg:address":"504 Vance St NW",
    "sg:city":"Lenoir",
    "sg:classifiers":[
        {
            "category":"Social Services",
            "subcategory":"Child Care",
            "type":"Services"
        }
    ],
    "sg:phone":"+1 828 754 3511",
    "sg:postcode":"28645",
    "sg:province":"NC",
    "wof:name":"First Step",
    "wof:placetype":"venue"
},
  "geometry": {"coordinates":[-81.543026,35.919548],"type":"Point"}
}