{
  "type": "Feature",
  "properties": {
    "iso:country":"US",
    "sg:address":"100 Village St",
    "sg:city":"Bladenboro",
    "sg:classifiers":[
        {
            "category":"Health Services",
            "subcategory":"Health Practitioner",
            "type":"Services"
        }
    ],
    "sg:phone":"+1 910 863 4850",
    "sg:postcode":"28320",
    "sg:province":"NC",
    "sg:tags":[
        "paramedic"
    ],
    "wof:name":"Simmons Paramedical Svc",
    "wof:placetype":"venue"
},
  "geometry": {"coordinates":[-78.799447,34.544672],"type":"Point"}
}