{
  "type": "Feature",
  "properties": {
    "iso:country":"US",
    "sg:address":"151 Jordan Rd",
    "sg:city":"Ramseur",
    "sg:classifiers":[
        {
            "category":"Restaurant",
            "type":"Food & Drink"
        }
    ],
    "sg:phone":"+1 336 824 1188",
    "sg:postcode":"27316",
    "sg:province":"NC",
    "sg:tags":[
        "eating"
    ],
    "wof:name":"BJs Biscuit Company",
    "wof:placetype":"venue"
},
  "geometry": {"coordinates":[-79.652754,35.738382],"type":"Point"}
}