{
  "type": "Feature",
  "properties": {
    "addr:full":"1304 W Pine St Mount Airy NC 27030",
    "addr:housenumber":"1304",
    "addr:postcode":"27030",
    "addr:street":"W Pine St",
    "iso:country":"US",
    "sg:address":"1304 W Pine St",
    "sg:city":"Mount Airy",
    "sg:classifiers":[
        {
            "category":"Food & Beverages",
            "subcategory":"Groceries & Convenience Stores",
            "type":"Retail Goods"
        }
    ],
    "sg:phone":"+1 336 786 2283",
    "sg:postcode":"27030",
    "sg:province":"NC",
    "sg:tags":[
        "alcoholic"
    ],
    "wof:name":"Texaco Food Mart",
    "wof:placetype":"venue"
},
  "geometry": {"coordinates":[-80.635317,36.501464],"type":"Point"}
}