{
  "type": "Feature",
  "properties": {
    "iso:country":"US",
    "sg:address":"1178 Hallberry Dr",
    "sg:city":"Fayetteville",
    "sg:classifiers":[
        {
            "category":"Real Estate",
            "subcategory":"Real Estate Agent",
            "type":"Services"
        }
    ],
    "sg:phone":"+1 910 609 1778",
    "sg:postcode":"28314",
    "sg:province":"NC",
    "wof:name":"First Carolina Real Estate",
    "wof:placetype":"venue"
},
  "geometry": {"coordinates":[-79.013113,35.045665],"type":"Point"}
}