{
  "type": "Feature",
  "properties": {
    "iso:country":"US",
    "sg:address":"143 Gray Mill Rd",
    "sg:city":"Lexington",
    "sg:classifiers":[
        {
            "category":"Building & Trades",
            "subcategory":"Construction",
            "type":"Services"
        }
    ],
    "sg:phone":"+1 336 357 2859",
    "sg:postcode":"27292",
    "sg:province":"NC",
    "sg:tags":[
        "house",
        "nonresidential"
    ],
    "wof:name":"Jeff Nichols Properties",
    "wof:placetype":"venue"
},
  "geometry": {"coordinates":[-80.24095199999999,35.777289],"type":"Point"}
}