{
  "type": "Feature",
  "properties": {
    "addr:full":"365 S Oak St Spindale NC 28160",
    "addr:housenumber":"365",
    "addr:postcode":"28160",
    "addr:street":"S Oak St",
    "iso:country":"US",
    "sg:address":"365 S Oak St",
    "sg:city":"Spindale",
    "sg:classifiers":[
        {
            "category":"Recreation",
            "type":"Entertainment"
        }
    ],
    "sg:phone":"+1 828 286 0006",
    "sg:postcode":"28160",
    "sg:province":"NC",
    "sg:tags":[
        "amusement"
    ],
    "wof:name":"Rutherford Cheer Academy",
    "wof:placetype":"venue"
},
  "geometry": {"coordinates":[-81.93596599999999,35.35154],"type":"Point"}
}