{
  "type": "Feature",
  "properties": {
    "iso:country":"US",
    "sg:address":"1205 Shelby Hwy",
    "sg:city":"Cherryville",
    "sg:classifiers":[
        {
            "category":"Restaurant",
            "type":"Food & Drink"
        }
    ],
    "sg:menulink":"http://www.allmenus.com/nc/cherryville/229379-no-1/menu/",
    "sg:phone":"+1 704 445 0608",
    "sg:postcode":"28021",
    "sg:province":"NC",
    "sg:tags":[
        "asian",
        "chinese"
    ],
    "wof:name":"No. 1",
    "wof:placetype":"venue"
},
  "geometry": {"coordinates":[-81.394277,35.376987],"type":"Point"}
}