{
  "type": "Feature",
  "properties": {
    "iso:country":"US",
    "sg:address":"2738 Ward Blvd",
    "sg:city":"Wilson",
    "sg:classifiers":[
        {
            "category":"Restaurant",
            "type":"Food & Drink"
        }
    ],
    "sg:phone":"+1 252 237 3878",
    "sg:postcode":"27893",
    "sg:province":"NC",
    "sg:tags":[
        "eating"
    ],
    "wof:name":"Tonys Pizza",
    "wof:placetype":"venue"
},
  "geometry": {"coordinates":[-77.929496,35.753328],"type":"Point"}
}