{
  "type": "Feature",
  "properties": {
    "addr:full":"722 S Sellars Mill Rd Burlington NC 27217",
    "addr:housenumber":"722",
    "addr:postcode":"27217",
    "addr:street":"S Sellars Mill Rd",
    "iso:country":"US",
    "sg:address":"722 S Sellars Mill Rd",
    "sg:city":"Burlington",
    "sg:classifiers":[
        {
            "category":"Building & Trades",
            "subcategory":"Landscaping Services",
            "type":"Services"
        }
    ],
    "sg:phone":"+1 336 222 8555",
    "sg:postcode":"27217",
    "sg:province":"NC",
    "wof:name":"Overman Lawn Landscaping",
    "wof:placetype":"venue"
},
  "geometry": {"coordinates":[-79.399421,36.087293],"type":"Point"}
}