{
  "type": "Feature",
  "properties": {
    "addr:full":"4928 Linksland Dr Holly Springs NC 27540",
    "addr:housenumber":"4928",
    "addr:postcode":"27540",
    "addr:street":"Linksland Dr",
    "iso:country":"US",
    "sg:address":"4928 Linksland Dr",
    "sg:city":"Holly Springs",
    "sg:classifiers":[
        {
            "category":"Insurance",
            "subcategory":"Insurance Agent",
            "type":"Services"
        }
    ],
    "sg:phone":"+1 919 577 0501",
    "sg:postcode":"27540",
    "sg:province":"NC",
    "wof:name":"State Farm Insurance",
    "wof:placetype":"venue"
},
  "geometry": {"coordinates":[-78.81009,35.658018],"type":"Point"}
}