{
  "type": "Feature",
  "properties": {
    "iso:country":"US",
    "sg:address":"202 W Noble St",
    "sg:city":"Selma",
    "sg:classifiers":[
        {
            "category":"Personal",
            "subcategory":"Beauty Salon",
            "type":"Services"
        }
    ],
    "sg:phone":"+1 919 965 5657",
    "sg:postcode":"27576",
    "sg:province":"NC",
    "sg:tags":[
        "shop"
    ],
    "wof:name":"More Hair",
    "wof:placetype":"venue"
},
  "geometry": {"coordinates":[-78.287023,35.534962],"type":"Point"}
}