{
  "type": "Feature",
  "properties": {
    "addr:full":"52 Ray Wood Dr Waynesville NC 28786",
    "addr:housenumber":"52",
    "addr:postcode":"28786",
    "addr:street":"Ray Wood Dr",
    "iso:country":"US",
    "sg:address":"52 Ray Wood Dr",
    "sg:city":"Waynesville",
    "sg:classifiers":[
        {
            "category":"Building & Trades",
            "subcategory":"Plumbing",
            "type":"Services"
        }
    ],
    "sg:phone":"+1 828 648 4450",
    "sg:postcode":"28786",
    "sg:province":"NC",
    "sg:tags":[
        "heating",
        "contractor"
    ],
    "wof:name":"Third Tradition Heating & Cool",
    "wof:placetype":"venue"
},
  "geometry": {"coordinates":[-82.89982999999999,35.473489],"type":"Point"}
}