{
  "type": "Feature",
  "properties": {
    "addr:full":"1428 River Rd Selma NC 27576",
    "addr:housenumber":"1428",
    "addr:postcode":"27576",
    "addr:street":"River Rd",
    "iso:country":"US",
    "sg:address":"1428 River Rd",
    "sg:city":"Selma",
    "sg:classifiers":[
        {
            "category":"Retail",
            "subcategory":"Auto Repair",
            "type":"Services"
        }
    ],
    "sg:phone":"+1 919 965 3411",
    "sg:postcode":"27576",
    "sg:province":"NC",
    "sg:tags":[
        "repairing",
        "automobile",
        "general"
    ],
    "wof:name":"Continental Auto Repair",
    "wof:placetype":"venue"
},
  "geometry": {"coordinates":[-78.297123,35.551509],"type":"Point"}
}