{
  "type": "Feature",
  "properties": {
    "addr:full":"943 Pulliam-Tingen Mine Rd Roxboro NC 27574",
    "addr:housenumber":"943",
    "addr:postcode":"27574",
    "addr:street":"Pulliam-Tingen Mine Rd",
    "iso:country":"US",
    "sg:address":"943 Pulliam-Tingen Mine Rd",
    "sg:city":"Roxboro",
    "sg:classifiers":[
        {
            "category":"Personal",
            "subcategory":"Beauty Salon",
            "type":"Services"
        }
    ],
    "sg:phone":"+1 336 599 7130",
    "sg:postcode":"27574",
    "sg:province":"NC",
    "sg:tags":[
        "shop"
    ],
    "wof:name":"Carolyn & Daughter Hair Design",
    "wof:placetype":"venue"
},
  "geometry": {"coordinates":[-78.893135,36.368618],"type":"Point"}
}