{
  "type": "Feature",
  "properties": {
    "iso:country":"US",
    "sg:address":"626 Medlin Rd",
    "sg:city":"Franklin",
    "sg:classifiers":[
        {
            "category":"Organizations",
            "subcategory":"Religious Organization",
            "type":"Services"
        }
    ],
    "sg:phone":"+1 828 524 2357",
    "sg:postcode":"28734",
    "sg:province":"NC",
    "sg:tags":[
        "church"
    ],
    "wof:name":"Clark's Chapel Methodist",
    "wof:placetype":"venue"
},
  "geometry": {"coordinates":[-83.369457,35.140776],"type":"Point"}
}