{
  "type": "Feature",
  "properties": {
    "addr:full":"12999 E Independence Blvd Matthews NC 28105",
    "addr:housenumber":"12999",
    "addr:postcode":"28105",
    "addr:street":"E Independence Blvd",
    "iso:country":"US",
    "sg:address":"12999 E Independence Blvd",
    "sg:city":"Matthews",
    "sg:classifiers":[
        {
            "category":"Autos & Motor Vehicles",
            "subcategory":"Automobile Sales",
            "type":"Retail Goods"
        },
        {
            "category":"Shopping",
            "subcategory":"Clothing, Apparel, & Fashions",
            "type":"Retail Goods"
        },
        {
            "category":"Retail",
            "subcategory":"Driving School",
            "type":"Services"
        },
        {
            "category":"Autos & Motor Vehicles",
            "subcategory":"Motorcycle Sales",
            "type":"Retail Goods"
        },
        {
            "category":"Retail",
            "subcategory":"Auto Repair",
            "type":"Services"
        }
    ],
    "sg:phone":"+1 704 882 6106",
    "sg:postcode":"28105",
    "sg:province":"NC",
    "sg:tags":[
        "scooters-parts",
        "leasing",
        "motorcycles-customizing",
        "supply",
        "scooters-renting",
        "instruction",
        "scooters-repairing",
        "sportswear"
    ],
    "sg:website":"http://www.bmw-ducati.com",
    "wof:name":"BMW - Ducati - Triumph - MV Agusta Motorcycles Of Charlotte",
    "wof:placetype":"venue"
},
  "geometry": {"coordinates":[-80.676401,35.098813],"type":"Point"}
}