{
  "type": "Feature",
  "properties": {
    "addr:full":"446 Tyvola Rd Charlotte NC 28217",
    "addr:housenumber":"446",
    "addr:postcode":"28217",
    "addr:street":"Tyvola Rd",
    "iso:country":"US",
    "sg:address":"446 Tyvola Rd",
    "sg:city":"Charlotte",
    "sg:classifiers":[
        {
            "category":"Restaurant",
            "type":"Food & Drink"
        }
    ],
    "sg:menulink":"http://www.allmenus.com/nc/charlotte/46989-kabuto/menu/",
    "sg:phone":"+1 704 529 0659",
    "sg:postcode":"28217",
    "sg:province":"NC",
    "sg:tags":[
        "sushi",
        "japanese",
        "asian"
    ],
    "wof:name":"Kabuto",
    "wof:placetype":"venue"
},
  "geometry": {"coordinates":[-80.886706,35.163283],"type":"Point"}
}