{
  "type": "Feature",
  "properties": {
    "addr:full":"3115 Friendship Rd Apex NC 27502",
    "addr:housenumber":"3115",
    "addr:postcode":"27502",
    "addr:street":"Friendship Rd",
    "iso:country":"US",
    "sg:address":"3115 Friendship Rd",
    "sg:city":"Apex",
    "sg:classifiers":[
        {
            "category":"Building & Trades",
            "subcategory":"Landscaping Services",
            "type":"Services"
        }
    ],
    "sg:phone":"+1 919 387 6348",
    "sg:postcode":"27502",
    "sg:province":"NC",
    "wof:name":"Dream Scapes Unlimited",
    "wof:placetype":"venue"
},
  "geometry": {"coordinates":[-78.894066,35.695573],"type":"Point"}
}