{
  "type": "Feature",
  "properties": {
    "iso:country":"US",
    "sg:address":"6458 Tryon Rd",
    "sg:city":"Cary",
    "sg:classifiers":[
        {
            "category":"Restaurant",
            "type":"Food & Drink"
        }
    ],
    "sg:phone":"+1 919 852 2242",
    "sg:postcode":"27511",
    "sg:province":"NC",
    "sg:tags":[
        "italian",
        "pizza"
    ],
    "sg:website":"www.theoriginalnypizza.com",
    "wof:name":"N.Y. Pizza",
    "wof:placetype":"venue"
},
  "geometry": {"coordinates":[-78.761251,35.743888],"type":"Point"}
}