{
  "type": "Feature",
  "properties": {
    "iso:country":"US",
    "sg:address":"8130 Wilkinson Blvd",
    "sg:city":"Charlotte",
    "sg:classifiers":[
        {
            "category":"Autos & Motor Vehicles",
            "subcategory":"Automobile Sales",
            "type":"Retail Goods"
        }
    ],
    "sg:phone":"+1 704 392 4071",
    "sg:postcode":"28214",
    "sg:province":"NC",
    "sg:tags":[
        "car",
        "dealer"
    ],
    "sg:website":"www.littlerockautosales.com",
    "wof:name":"Little Rock Auto Sales",
    "wof:placetype":"venue"
},
  "geometry": {"coordinates":[-80.978246,35.240894],"type":"Point"}
}