{
  "type": "Feature",
  "properties": {
    "iso:country":"US",
    "sg:address":"1202 Curtis Bridge Rd",
    "sg:city":"Wilkesboro",
    "sg:classifiers":[
        {
            "category":"Travel",
            "subcategory":"Travel Agent",
            "type":"Entertainment"
        }
    ],
    "sg:phone":"+1 336 903 0072",
    "sg:postcode":"28697",
    "sg:province":"NC",
    "sg:tags":[
        "agency",
        "bureau"
    ],
    "wof:name":"Electric Rays Travel Agency",
    "wof:placetype":"venue"
},
  "geometry": {"coordinates":[-81.172685,36.147869],"type":"Point"}
}