{
  "type": "Feature",
  "properties": {
    "addr:full":"191 Park Plaza Dr Winston Salem NC 27105",
    "addr:housenumber":"191",
    "addr:postcode":"27105",
    "addr:street":"Park Plaza Dr",
    "iso:country":"US",
    "sg:address":"191 Park Plaza Dr",
    "sg:city":"Winston Salem",
    "sg:classifiers":[
        {
            "category":"Building & Trades",
            "subcategory":"Equipment Rental",
            "type":"Services"
        }
    ],
    "sg:phone":"+1 336 661 3195",
    "sg:postcode":"27105",
    "sg:province":"NC",
    "sg:tags":[
        "leasing"
    ],
    "sg:website":"www.salemleasing.com",
    "wof:name":"Salem Leasing Corp",
    "wof:placetype":"venue"
},
  "geometry": {"coordinates":[-80.24753699999999,36.154643],"type":"Point"}
}