{
  "type": "Feature",
  "properties": {
    "iso:country":"US",
    "sg:address":"111 W Central Ave",
    "sg:city":"Mount Holly",
    "sg:classifiers":[
        {
            "category":"Personal",
            "type":"Services"
        }
    ],
    "sg:phone":"+1 704 827 3509",
    "sg:postcode":"28120",
    "sg:province":"NC",
    "sg:tags":[
        "leather",
        "d"
    ],
    "wof:name":"Sun Tanz",
    "wof:placetype":"venue"
},
  "geometry": {"coordinates":[-81.016317,35.297574],"type":"Point"}
}