{
  "type": "Feature",
  "properties": {
    "addr:full":"2456 Milburnie Rd Raleigh NC 27610",
    "addr:housenumber":"2456",
    "addr:postcode":"27610",
    "addr:street":"Milburnie Rd",
    "iso:country":"US",
    "sg:address":"2456 Milburnie Rd",
    "sg:city":"Raleigh",
    "sg:classifiers":[
        {
            "category":"Mining & Drilling",
            "type":"Manufacturing & Wholesale Goods"
        }
    ],
    "sg:phone":"+1 919 201 5274",
    "sg:postcode":"27610",
    "sg:province":"NC",
    "sg:tags":[
        "repair",
        "dismantling"
    ],
    "wof:name":"R & D Contracting Inc",
    "wof:placetype":"venue"
},
  "geometry": {"coordinates":[-78.600189,35.788429],"type":"Point"}
}