{
  "type": "Feature",
  "properties": {
    "iso:country":"US",
    "sg:address":"8712 Cinnabay Dr",
    "sg:city":"Charlotte",
    "sg:classifiers":[
        {
            "category":"Food & Beverages",
            "subcategory":"Bakery",
            "type":"Retail Goods"
        }
    ],
    "sg:phone":"+1 704 399 3214",
    "sg:postcode":"28216",
    "sg:province":"NC",
    "wof:name":"Colombian House Bakery",
    "wof:placetype":"venue"
},
  "geometry": {"coordinates":[-80.872379,35.344432],"type":"Point"}
}