{
  "type": "Feature",
  "properties": {
    "iso:country":"US",
    "sg:address":"6505 Northridge Village Dr",
    "sg:city":"Charlotte",
    "sg:classifiers":[
        {
            "category":"Social Services",
            "subcategory":"Child Care",
            "type":"Services"
        }
    ],
    "sg:phone":"+1   ",
    "sg:postcode":"28213",
    "sg:province":"NC",
    "sg:tags":[
        "day"
    ],
    "wof:name":"All In Family Home Daycare",
    "wof:placetype":"venue"
},
  "geometry": {"coordinates":[-80.767854,35.280196],"type":"Point"}
}