{
  "type": "Feature",
  "properties": {
    "iso:country":"US",
    "sg:address":"1050 13th St SE",
    "sg:city":"Hickory",
    "sg:classifiers":[
        {
            "category":"Real Estate",
            "subcategory":"Real Estate Services",
            "type":"Services"
        }
    ],
    "sg:phone":"+1 828 345 1140",
    "sg:postcode":"28602",
    "sg:province":"NC",
    "sg:tags":[
        "company",
        "title"
    ],
    "wof:name":"Elite Title Co Inc",
    "wof:placetype":"venue"
},
  "geometry": {"coordinates":[-81.31303200000001,35.719325],"type":"Point"}
}