{
  "type": "Feature",
  "properties": {
    "addr:full":"133 E Main St Albemarle NC 28001",
    "addr:housenumber":"133",
    "addr:postcode":"28001",
    "addr:street":"E Main St",
    "iso:country":"US",
    "sg:address":"133 E Main St",
    "sg:city":"Albemarle",
    "sg:classifiers":[
        {
            "category":"Education",
            "subcategory":"Library",
            "type":"Public Place"
        }
    ],
    "sg:phone":"+1 704 986 3755",
    "sg:postcode":"28001",
    "sg:province":"NC",
    "sg:website":"www.stanlylib.org",
    "wof:name":"Stanly Co Public Library",
    "wof:placetype":"venue"
},
  "geometry": {"coordinates":[-80.197637,35.350396],"type":"Point"}
}