{
  "type": "Feature",
  "properties": {
    "addr:full":"105 Wind Chime Ct Raleigh NC 27615",
    "addr:housenumber":"105",
    "addr:postcode":"27615",
    "addr:street":"Wind Chime Ct",
    "iso:country":"US",
    "sg:address":"105 Wind Chime Ct",
    "sg:city":"Raleigh",
    "sg:classifiers":[
        {
            "category":"Health Services",
            "subcategory":"Doctor",
            "type":"Services"
        }
    ],
    "sg:phone":"+1 919 870 7645",
    "sg:postcode":"27615",
    "sg:province":"NC",
    "sg:tags":[
        "dentist"
    ],
    "wof:name":"Philip W Shoemaker DDS",
    "wof:placetype":"venue"
},
  "geometry": {"coordinates":[-78.642264,35.875496],"type":"Point"}
}