{
  "type": "Feature",
  "properties": {
    "iso:country":"US",
    "sg:address":"189 Pine Mountain Rd",
    "sg:city":"Jefferson",
    "sg:classifiers":[
        {
            "category":"Banks & Credit Unions",
            "subcategory":"Investment Brokerage",
            "type":"Services"
        }
    ],
    "sg:phone":"+1 336 385 1224",
    "sg:postcode":"28615",
    "sg:province":"NC",
    "sg:tags":[
        "security"
    ],
    "wof:name":"Edward Jones 17959",
    "wof:placetype":"venue"
},
  "geometry": {"coordinates":[-81.70038,36.417325],"type":"Point"}
}