{
  "type": "Feature",
  "properties": {
    "addr:full":"2059 Dallas Stanley Hwy Stanley NC 28164",
    "addr:housenumber":"2059",
    "addr:postcode":"28164",
    "addr:street":"Dallas Stanley Hwy",
    "iso:country":"US",
    "sg:address":"2059 Dallas Stanley Hwy",
    "sg:city":"Stanley",
    "sg:classifiers":[
        {
            "category":"Professional",
            "type":"Services"
        }
    ],
    "sg:phone":"+1 704 263 9207",
    "sg:postcode":"28164",
    "sg:province":"NC",
    "wof:name":"Kristie Gardner",
    "wof:placetype":"venue"
},
  "geometry": {"coordinates":[-81.10926000000001,35.340158],"type":"Point"}
}