{
  "type": "Feature",
  "properties": {
    "addr:full":"106 Smith St Thomasville NC 27360",
    "addr:housenumber":"106",
    "addr:postcode":"27360",
    "addr:street":"Smith St",
    "iso:country":"US",
    "sg:address":"106 Smith St",
    "sg:city":"Thomasville",
    "sg:classifiers":[
        {
            "category":"Organizations",
            "subcategory":"Religious Organization",
            "type":"Services"
        }
    ],
    "sg:phone":"+1 336 472 3052",
    "sg:postcode":"27360",
    "sg:province":"NC",
    "sg:tags":[
        "church"
    ],
    "wof:name":"Friendship Baptist Church",
    "wof:placetype":"venue"
},
  "geometry": {"coordinates":[-80.06873400000001,35.890669],"type":"Point"}
}