{
  "type": "Feature",
  "properties": {
    "iso:country":"US",
    "sg:address":"2520 Avent Ferry Rd",
    "sg:city":"Holly Springs",
    "sg:classifiers":[
        {
            "category":"Building & Trades",
            "subcategory":"Construction",
            "type":"Services"
        }
    ],
    "sg:phone":"+1 919 552 6360",
    "sg:postcode":"27540",
    "sg:province":"NC",
    "sg:tags":[
        "contractor"
    ],
    "wof:name":"Donny Johnson Drywall",
    "wof:placetype":"venue"
},
  "geometry": {"coordinates":[-78.8835,35.625275],"type":"Point"}
}