{
  "type": "Feature",
  "properties": {
    "addr:full":"800 W Williams St Suite 100 Apex NC 27502",
    "addr:housenumber":"800",
    "addr:postcode":"27502",
    "addr:street":"W Williams St Suite 100",
    "iso:country":"US",
    "sg:address":"800 W Williams St Suite 100",
    "sg:city":"Apex",
    "sg:classifiers":[
        {
            "category":"Restaurant",
            "type":"Food & Drink"
        }
    ],
    "sg:phone":"+1 919 363 5288",
    "sg:postcode":"27502",
    "sg:province":"NC",
    "sg:tags":[
        "style",
        "family",
        "lunch",
        "mediterranean",
        "greek",
        "brunch",
        "breakfast"
    ],
    "wof:name":"XIOS Authentic Greek Cuisine",
    "wof:placetype":"venue"
},
  "geometry": {"coordinates":[-78.865219,35.738548],"type":"Point"}
}