{
  "type": "Feature",
  "properties": {
    "iso:country":"US",
    "sg:address":"311 Abington Rd NW",
    "sg:city":"Lenoir",
    "sg:classifiers":[
        {
            "category":"Organizations",
            "subcategory":"Religious Organization",
            "type":"Services"
        }
    ],
    "sg:phone":"+1 828 758 2818",
    "sg:postcode":"28645",
    "sg:province":"NC",
    "sg:website":"www.westlenoirbc.org",
    "wof:name":"West Lenoir Baptist Church",
    "wof:placetype":"venue"
},
  "geometry": {"coordinates":[-81.560289,35.903938],"type":"Point"}
}