{
  "type": "Feature",
  "properties": {
    "iso:country":"US",
    "sg:address":"801 US Hwy 52",
    "sg:city":"Albemarle",
    "sg:classifiers":[
        {
            "category":"Food & Beverages",
            "subcategory":"Groceries & Convenience Stores",
            "type":"Retail Goods"
        }
    ],
    "sg:phone":"+1 704 982 8803",
    "sg:postcode":"28001",
    "sg:province":"NC",
    "wof:name":"Express Mart Stores",
    "wof:placetype":"venue"
},
  "geometry": {"coordinates":[-80.20355000000001,35.362218],"type":"Point"}
}