{
  "type": "Feature",
  "properties": {
    "addr:full":"1195 Daisy Trail Rd Germanton NC 27019",
    "addr:housenumber":"1195",
    "addr:postcode":"27019",
    "addr:street":"Daisy Trail Rd",
    "iso:country":"US",
    "sg:address":"1195 Daisy Trail Rd",
    "sg:city":"Germanton",
    "sg:classifiers":[
        {
            "category":"Farming",
            "subcategory":"Farm",
            "type":"Manufacturing & Wholesale Goods"
        }
    ],
    "sg:phone":"+1 336 591 7102",
    "sg:postcode":"27019",
    "sg:province":"NC",
    "sg:tags":[
        "crop",
        "general"
    ],
    "wof:name":"Richard Oehmen",
    "wof:placetype":"venue"
},
  "geometry": {"coordinates":[-80.262083,36.273983],"type":"Point"}
}