{
  "type": "Feature",
  "properties": {
    "addr:full":"247 E Plaza Dr Mooresville NC 28115",
    "addr:housenumber":"247",
    "addr:postcode":"28115",
    "addr:street":"E Plaza Dr",
    "iso:country":"US",
    "sg:address":"247 E Plaza Dr",
    "sg:city":"Mooresville",
    "sg:classifiers":[
        {
            "category":"Restaurant",
            "type":"Food & Drink"
        }
    ],
    "sg:menulink":"http://www.allmenus.com/nc/coddle-creek/229302-js/menu/",
    "sg:phone":"+1 704 662 3088",
    "sg:postcode":"28115",
    "sg:province":"NC",
    "sg:tags":[
        "asian",
        "chinese"
    ],
    "wof:name":"J's",
    "wof:placetype":"venue"
},
  "geometry": {"coordinates":[-80.830911,35.588399],"type":"Point"}
}