{
  "type": "Feature",
  "properties": {
    "iso:country":"US",
    "sg:address":"1322 N Road St",
    "sg:city":"Elizabeth City",
    "sg:classifiers":[
        {
            "category":"Autos & Motor Vehicles",
            "subcategory":"Automobile Sales",
            "type":"Retail Goods"
        }
    ],
    "sg:phone":"+1 252 331 1101",
    "sg:postcode":"27909",
    "sg:province":"NC",
    "sg:tags":[
        "used"
    ],
    "wof:name":"E City Motors Inc",
    "wof:placetype":"venue"
},
  "geometry": {"coordinates":[-76.226733,36.331068],"type":"Point"}
}