{
  "type": "Feature",
  "properties": {
    "addr:full":"2304 Wesvill Ct Raleigh NC 27607",
    "addr:housenumber":"2304",
    "addr:postcode":"27607",
    "addr:street":"Wesvill Ct",
    "iso:country":"US",
    "sg:address":"2304 Wesvill Ct",
    "sg:city":"Raleigh",
    "sg:classifiers":[
        {
            "category":"Professional",
            "subcategory":"Management & Consulting",
            "type":"Services"
        }
    ],
    "sg:phone":"+1   ",
    "sg:postcode":"27607",
    "sg:province":"NC",
    "sg:tags":[
        "architectural"
    ],
    "wof:name":"Rla",
    "wof:placetype":"venue"
},
  "geometry": {"coordinates":[-78.69606899999999,35.814776],"type":"Point"}
}