{
  "type": "Feature",
  "properties": {
    "iso:country":"US",
    "sg:address":"1430 Derby Dr",
    "sg:city":"Shelby",
    "sg:classifiers":[
        {
            "category":"Farming",
            "subcategory":"Livestock Farm",
            "type":"Manufacturing & Wholesale Goods"
        }
    ],
    "sg:phone":"+1 704 434 0770",
    "sg:postcode":"28150",
    "sg:province":"NC",
    "sg:tags":[
        "hog",
        "or",
        "feedlot"
    ],
    "wof:name":"Abrahams Cove Farms",
    "wof:placetype":"venue"
},
  "geometry": {"coordinates":[-81.630573,35.355804],"type":"Point"}
}