{
  "type": "Feature",
  "properties": {
    "addr:full":"1009 Flintwood Ct High Point NC 27265",
    "addr:housenumber":"1009",
    "addr:postcode":"27265",
    "addr:street":"Flintwood Ct",
    "iso:country":"US",
    "sg:address":"1009 Flintwood Ct",
    "sg:city":"High Point",
    "sg:classifiers":[
        {
            "category":"Manufacturing",
            "subcategory":"Printing",
            "type":"Manufacturing & Wholesale Goods"
        }
    ],
    "sg:phone":"+1 336 454 2648",
    "sg:postcode":"27265",
    "sg:province":"NC",
    "sg:tags":[
        "book"
    ],
    "wof:name":"Alligator Creek Genealogy",
    "wof:placetype":"venue"
},
  "geometry": {"coordinates":[-80.02717699999999,36.036959],"type":"Point"}
}