{
  "type": "Feature",
  "properties": {
    "addr:full":"10030 Gilead Rd Huntersville NC 28078",
    "addr:housenumber":"10030",
    "addr:postcode":"28078",
    "addr:street":"Gilead Rd",
    "iso:country":"US",
    "sg:address":"10030 Gilead Rd",
    "sg:city":"Huntersville",
    "sg:classifiers":[
        {
            "category":"Organizations",
            "subcategory":"Non-profit Organization",
            "type":"Services"
        }
    ],
    "sg:phone":"+1 704 316 5580",
    "sg:postcode":"28078",
    "sg:province":"NC",
    "sg:tags":[
        "breastfeeding",
        "information",
        "supply"
    ],
    "wof:name":"Nursing Mothers Place",
    "wof:placetype":"venue"
},
  "geometry": {"coordinates":[-80.862191,35.407288],"type":"Point"}
}