{
  "type": "Feature",
  "properties": {
    "iso:country":"US",
    "sg:address":"6625 Denver Industrial Park Rd",
    "sg:city":"Denver",
    "sg:classifiers":[
        {
            "category":"Retail",
            "subcategory":"Repair Shop",
            "type":"Services"
        }
    ],
    "sg:phone":"+1 704 489 9989",
    "sg:postcode":"28037",
    "sg:province":"NC",
    "sg:tags":[
        "valve"
    ],
    "wof:name":"International Pump & Valve",
    "wof:placetype":"venue"
},
  "geometry": {"coordinates":[-81.03826100000001,35.539351],"type":"Point"}
}