{
  "type": "Feature",
  "properties": {
    "iso:country":"US",
    "sg:address":"853 Cid Rd",
    "sg:city":"Lexington",
    "sg:classifiers":[
        {
            "category":"Manufacturing",
            "subcategory":"Metals",
            "type":"Manufacturing & Wholesale Goods"
        }
    ],
    "sg:phone":"+1 336 859 2002",
    "sg:postcode":"27292",
    "sg:province":"NC",
    "sg:tags":[
        "stamping"
    ],
    "wof:name":"CID Metal Works",
    "wof:placetype":"venue"
},
  "geometry": {"coordinates":[-80.09355499999999,35.710216],"type":"Point"}
}