{
  "type": "Feature",
  "properties": {
    "iso:country":"US",
    "sg:address":"1777 S Main St",
    "sg:city":"Laurinburg",
    "sg:classifiers":[
        {
            "category":"Health Services",
            "subcategory":"Chiropractor",
            "type":"Services"
        }
    ],
    "sg:phone":"+1 910 276 0303",
    "sg:postcode":"28352",
    "sg:province":"NC",
    "wof:name":"Raby Chiropractic Ctr",
    "wof:placetype":"venue"
},
  "geometry": {"coordinates":[-79.48284200000001,34.750107],"type":"Point"}
}