{
  "type": "Feature",
  "properties": {
    "iso:country":"US",
    "sg:address":"148 S Main St",
    "sg:city":"Laurinburg",
    "sg:classifiers":[
        {
            "category":"Food & Beverages",
            "subcategory":"Groceries & Convenience Stores",
            "type":"Retail Goods"
        }
    ],
    "sg:phone":"+1 910 276 7277",
    "sg:postcode":"28352",
    "sg:province":"NC",
    "wof:name":"Swift Mart",
    "wof:placetype":"venue"
},
  "geometry": {"coordinates":[-79.461539,34.776339],"type":"Point"}
}