{
  "type": "Feature",
  "properties": {
    "addr:full":"1155 N Clodfelter Rd High Point NC 27265",
    "addr:housenumber":"1155",
    "addr:postcode":"27265",
    "addr:street":"N Clodfelter Rd",
    "iso:country":"US",
    "sg:address":"1155 N Clodfelter Rd",
    "sg:city":"High Point",
    "sg:classifiers":[
        {
            "category":"Professional",
            "type":"Services"
        }
    ],
    "sg:phone":"+1 336 887 8426",
    "sg:postcode":"27265",
    "sg:province":"NC",
    "wof:name":"Tonya C Clodfelter",
    "wof:placetype":"venue"
},
  "geometry": {"coordinates":[-80.11253499999999,35.984201],"type":"Point"}
}