{
  "type": "Feature",
  "properties": {
    "addr:full":"116 Main St NW Lenoir NC 28645",
    "addr:housenumber":"116",
    "addr:postcode":"28645",
    "addr:street":"Main St Nw",
    "iso:country":"US",
    "sg:address":"116 Main St NW",
    "sg:city":"Lenoir",
    "sg:classifiers":[
        {
            "category":"Real Estate",
            "subcategory":"Real Estate Agent",
            "type":"Services"
        }
    ],
    "sg:phone":"+1 828 754 8611",
    "sg:postcode":"28645",
    "sg:province":"NC",
    "wof:name":"Nrh Real Estate LLC",
    "wof:placetype":"venue"
},
  "geometry": {"coordinates":[-81.53967,35.914778],"type":"Point"}
}