{
  "type": "Feature",
  "properties": {
    "addr:full":"1011 E Morehead St Charlotte NC 28204",
    "addr:housenumber":"1011",
    "addr:postcode":"28204",
    "addr:street":"E Morehead St",
    "iso:country":"US",
    "sg:address":"1011 E Morehead St",
    "sg:city":"Charlotte",
    "sg:classifiers":[
        {
            "category":"Government",
            "subcategory":"Police Station",
            "type":"Public Place"
        },
        {
            "category":"Professional",
            "subcategory":"Lawyer & Legal Services",
            "type":"Services"
        }
    ],
    "sg:phone":"+1 704 347 1809",
    "sg:postcode":"28204",
    "sg:province":"NC",
    "sg:tags":[
        "attorney",
        "dwi",
        "duo",
        "drug",
        "charge",
        "traffic",
        "criminal",
        "law"
    ],
    "sg:website":"http://www.realpagessites.com/gronqlaw",
    "wof:name":"Foster, Mark",
    "wof:placetype":"venue"
},
  "geometry": {"coordinates":[-80.843683,35.212808],"type":"Point"}
}