{
  "type": "Feature",
  "properties": {
    "addr:full":"111 Annandale Dr Cary NC 27511",
    "addr:housenumber":"111",
    "addr:postcode":"27511",
    "addr:street":"Annandale Dr",
    "iso:country":"US",
    "sg:address":"111 Annandale Dr",
    "sg:city":"Cary",
    "sg:classifiers":[
        {
            "category":"Professional",
            "type":"Services"
        }
    ],
    "sg:phone":"+1 919 467 6824",
    "sg:postcode":"27511",
    "sg:province":"NC",
    "wof:name":"Donald E Boesch",
    "wof:placetype":"venue"
},
  "geometry": {"coordinates":[-78.792661,35.751345],"type":"Point"}
}