{
  "type": "Feature",
  "properties": {
    "addr:full":"2110 Angier Ave Durham NC 27703",
    "addr:housenumber":"2110",
    "addr:postcode":"27703",
    "addr:street":"Angier Ave",
    "iso:country":"US",
    "sg:address":"2110 Angier Ave",
    "sg:city":"Durham",
    "sg:classifiers":[
        {
            "category":"Personal",
            "subcategory":"Barber",
            "type":"Services"
        }
    ],
    "sg:phone":"+1 919 596 1294",
    "sg:postcode":"27703",
    "sg:province":"NC",
    "wof:name":"Samuel & Sons",
    "wof:placetype":"venue"
},
  "geometry": {"coordinates":[-78.877645,35.981953],"type":"Point"}
}