{
  "type": "Feature",
  "properties": {
    "iso:country":"US",
    "sg:address":"1839 Onslow Dr",
    "sg:city":"Jacksonville",
    "sg:classifiers":[
        {
            "category":"Health Services",
            "subcategory":"Nursing And Care Facility",
            "type":"Services"
        }
    ],
    "sg:phone":"+1 910 455 3610",
    "sg:postcode":"28540",
    "sg:province":"NC",
    "sg:tags":[
        "skilled"
    ],
    "wof:name":"Britthaven",
    "wof:placetype":"venue"
},
  "geometry": {"coordinates":[-77.409147,34.74987],"type":"Point"}
}