{
  "type": "Feature",
  "properties": {
    "iso:country":"US",
    "sg:address":"16 Ponderosa Ct",
    "sg:city":"Greensboro",
    "sg:classifiers":[
        {
            "category":"Arts & Performance",
            "subcategory":"Theater",
            "type":"Entertainment"
        }
    ],
    "sg:phone":"+1 336 681 2330",
    "sg:postcode":"27406",
    "sg:province":"NC",
    "sg:tags":[
        "bureau"
    ],
    "wof:name":"Next Level Entertainment",
    "wof:placetype":"venue"
},
  "geometry": {"coordinates":[-79.76365300000001,36.028172],"type":"Point"}
}