{
  "type": "Feature",
  "properties": {
    "addr:full":"187 Oak Ridge Pl Mount Airy NC 27030",
    "addr:housenumber":"187",
    "addr:postcode":"27030",
    "addr:street":"Oak Ridge Pl",
    "iso:country":"US",
    "sg:address":"187 Oak Ridge Pl",
    "sg:city":"Mount Airy",
    "sg:classifiers":[
        {
            "category":"Building & Trades",
            "subcategory":"Construction",
            "type":"Services"
        }
    ],
    "sg:phone":"+1 336 789 4282",
    "sg:postcode":"27030",
    "sg:province":"NC",
    "sg:tags":[
        "contractor"
    ],
    "wof:name":"McMillian Construction & Repr",
    "wof:placetype":"venue"
},
  "geometry": {"coordinates":[-80.685131,36.498019],"type":"Point"}
}