{
  "type": "Feature",
  "properties": {
    "addr:full":"1691 Barber Mill Rd Clayton NC 27520",
    "addr:housenumber":"1691",
    "addr:postcode":"27520",
    "addr:street":"Barber Mill Rd",
    "iso:country":"US",
    "sg:address":"1691 Barber Mill Rd",
    "sg:city":"Clayton",
    "sg:classifiers":[
        {
            "category":"Organizations",
            "subcategory":"Religious Organization",
            "type":"Services"
        }
    ],
    "sg:phone":"+1 919 553 5056",
    "sg:postcode":"27520",
    "sg:province":"NC",
    "sg:tags":[
        "church"
    ],
    "wof:name":"Johnston Piney Grove Bapt Chr",
    "wof:placetype":"venue"
},
  "geometry": {"coordinates":[-78.48536300000001,35.585048],"type":"Point"}
}