{
  "type": "Feature",
  "properties": {
    "iso:country":"US",
    "sg:address":"4105 Scott Futrell Dr",
    "sg:city":"Charlotte",
    "sg:classifiers":[
        {
            "category":"Wholesale",
            "subcategory":"Machinery & Supplies",
            "type":"Manufacturing & Wholesale Goods"
        },
        {
            "category":"Wholesale",
            "subcategory":"Construction Materials",
            "type":"Manufacturing & Wholesale Goods"
        },
        {
            "category":"Building & Trades",
            "subcategory":"Construction",
            "type":"Services"
        }
    ],
    "sg:phone":"+1 704 391 2227",
    "sg:postcode":"28208",
    "sg:province":"NC",
    "sg:tags":[
        "handling",
        "rack",
        "pallet",
        "equipment",
        "skid"
    ],
    "sg:website":"http://www.ifco-us.com/america/na/en/biz_pallet/index.php",
    "wof:name":"IFCO SYSTEMS",
    "wof:placetype":"venue"
},
  "geometry": {"coordinates":[-80.937789,35.238796],"type":"Point"}
}