{
  "type": "Feature",
  "properties": {
    "iso:country":"US",
    "sg:address":"155 Parkway Office Ct",
    "sg:city":"Cary",
    "sg:classifiers":[
        {
            "category":"Building & Trades",
            "subcategory":"Construction",
            "type":"Services"
        }
    ],
    "sg:phone":"+1 919 854 4830",
    "sg:postcode":"27518",
    "sg:province":"NC",
    "sg:tags":[
        "contractor"
    ],
    "wof:name":"Horizon Five General Contractors",
    "wof:placetype":"venue"
},
  "geometry": {"coordinates":[-78.76608,35.744878],"type":"Point"}
}