{
  "type": "Feature",
  "properties": {
    "iso:country":"US",
    "sg:address":"108 W Innes St",
    "sg:city":"Salisbury",
    "sg:classifiers":[
        {
            "category":"Personal",
            "subcategory":"Beauty Salon",
            "type":"Services"
        }
    ],
    "sg:phone":"+1   ",
    "sg:postcode":"28144",
    "sg:province":"NC",
    "sg:tags":[
        "shop"
    ],
    "wof:name":"Sandi Summers Hair Services",
    "wof:placetype":"venue"
},
  "geometry": {"coordinates":[-80.470866,35.668302],"type":"Point"}
}