{
  "type": "Feature",
  "properties": {
    "iso:country":"US",
    "sg:address":"1405 E Franklin Blvd",
    "sg:city":"Gastonia",
    "sg:classifiers":[
        {
            "category":"Manufacturing",
            "subcategory":"Electronics",
            "type":"Manufacturing & Wholesale Goods"
        }
    ],
    "sg:phone":"+1 704 867 3371",
    "sg:postcode":"28054",
    "sg:province":"NC",
    "sg:tags":[
        "prerecorded",
        "mfg"
    ],
    "wof:name":"Joyful Noise",
    "wof:placetype":"venue"
},
  "geometry": {"coordinates":[-81.15613399999999,35.262221],"type":"Point"}
}