{
  "type": "Feature",
  "properties": {
    "iso:country":"US",
    "sg:address":"101 Freeland Ln",
    "sg:city":"Charlotte",
    "sg:classifiers":[
        {
            "category":"Building & Trades",
            "subcategory":"Equipment Rental",
            "type":"Services"
        }
    ],
    "sg:phone":"+1 704 525 7400",
    "sg:postcode":"28217",
    "sg:province":"NC",
    "sg:tags":[
        "party",
        "supply"
    ],
    "wof:name":"Ace Party Rentals Inc",
    "wof:placetype":"venue"
},
  "geometry": {"coordinates":[-80.87549,35.189851],"type":"Point"}
}