{
  "type": "Feature",
  "properties": {
    "addr:full":"430 Enoch Rd Benson NC 27504",
    "addr:housenumber":"430",
    "addr:postcode":"27504",
    "addr:street":"Enoch Rd",
    "iso:country":"US",
    "sg:address":"430 Enoch Rd",
    "sg:city":"Benson",
    "sg:classifiers":[
        {
            "category":"Farming",
            "subcategory":"Farm",
            "type":"Manufacturing & Wholesale Goods"
        }
    ],
    "sg:phone":"+1 919 894 7539",
    "sg:postcode":"27504",
    "sg:province":"NC",
    "wof:name":"Coharie Farms",
    "wof:placetype":"venue"
},
  "geometry": {"coordinates":[-78.42075,35.322433],"type":"Point"}
}