{
  "type": "Feature",
  "properties": {
    "iso:country":"US",
    "sg:address":"241 Sunset Ave",
    "sg:city":"Asheboro",
    "sg:classifiers":[
        {
            "category":"Government",
            "subcategory":"Office",
            "type":"Public Place"
        }
    ],
    "sg:phone":"+1 336 318 6490",
    "sg:postcode":"27203",
    "sg:province":"NC",
    "wof:name":"Randolph County Soil & Water",
    "wof:placetype":"venue"
},
  "geometry": {"coordinates":[-79.816788,35.705721],"type":"Point"}
}