{
  "type": "Feature",
  "properties": {
    "iso:country":"US",
    "sg:address":"3024 New Bern Ave",
    "sg:city":"Raleigh",
    "sg:classifiers":[
        {
            "category":"Health Services",
            "subcategory":"Doctor",
            "type":"Services"
        }
    ],
    "sg:phone":"+1 919 350 7844",
    "sg:postcode":"27610",
    "sg:province":"NC",
    "sg:tags":[
        "physician",
        "surgeon"
    ],
    "wof:name":"Wake Medical Ctr",
    "wof:placetype":"venue"
},
  "geometry": {"coordinates":[-78.58778,35.787507],"type":"Point"}
}