{
  "type": "Feature",
  "properties": {
    "iso:country":"US",
    "sg:address":"835 Kentwood Dr",
    "sg:city":"Statesville",
    "sg:classifiers":[
        {
            "category":"Building & Trades",
            "subcategory":"Construction",
            "type":"Services"
        }
    ],
    "sg:phone":"+1 704 881 0535",
    "sg:postcode":"28677",
    "sg:province":"NC",
    "sg:tags":[
        "contractor"
    ],
    "wof:name":"Iredell County Home Builders",
    "wof:placetype":"venue"
},
  "geometry": {"coordinates":[-80.939059,35.778426],"type":"Point"}
}