{
  "type": "Feature",
  "properties": {
    "addr:full":"2855 Jones Franklin Rd Raleigh NC 27606",
    "addr:housenumber":"2855",
    "addr:postcode":"27606",
    "addr:street":"Jones Franklin Rd",
    "iso:country":"US",
    "sg:address":"2855 Jones Franklin Rd",
    "sg:city":"Raleigh",
    "sg:classifiers":[
        {
            "category":"Personal",
            "subcategory":"Beauty Salon",
            "type":"Services"
        },
        {
            "category":"Personal",
            "subcategory":"Barber",
            "type":"Services"
        }
    ],
    "sg:phone":"+1 919 465 9565",
    "sg:postcode":"27606",
    "sg:province":"NC",
    "wof:name":"Shear Elegance",
    "wof:placetype":"venue"
},
  "geometry": {"coordinates":[-78.739463,35.744429],"type":"Point"}
}