{
  "type": "Feature",
  "properties": {
    "addr:full":"612 N Main St Mooresville NC 28115",
    "addr:housenumber":"612",
    "addr:postcode":"28115",
    "addr:street":"N Main St",
    "iso:country":"US",
    "sg:address":"612 N Main St",
    "sg:city":"Mooresville",
    "sg:classifiers":[
        {
            "category":"Health Services",
            "subcategory":"Chiropractor",
            "type":"Services"
        }
    ],
    "sg:phone":"+1 704 664 3455",
    "sg:postcode":"28115",
    "sg:province":"NC",
    "wof:name":"Lake Norman Chiropractic",
    "wof:placetype":"venue"
},
  "geometry": {"coordinates":[-80.802206,35.586767],"type":"Point"}
}