{
  "type": "Feature",
  "properties": {
    "iso:country":"US",
    "sg:address":"8316 Heel Stone Ct",
    "sg:city":"Raleigh",
    "sg:classifiers":[
        {
            "category":"Banks & Credit Unions",
            "subcategory":"Investment Brokerage",
            "type":"Services"
        }
    ],
    "sg:phone":"+1 919 846 8644",
    "sg:postcode":"27613",
    "sg:province":"NC",
    "sg:tags":[
        "advisory"
    ],
    "wof:name":"Schoonderwoerd Financial Group",
    "wof:placetype":"venue"
},
  "geometry": {"coordinates":[-78.69394800000001,35.893085],"type":"Point"}
}