{
  "type": "Feature",
  "properties": {
    "iso:country":"US",
    "sg:address":"1805 E Millbrook Rd",
    "sg:city":"Raleigh",
    "sg:classifiers":[
        {
            "category":"Autos & Motor Vehicles",
            "subcategory":"Auto Supplies",
            "type":"Retail Goods"
        },
        {
            "category":"Retail",
            "subcategory":"Auto Repair",
            "type":"Services"
        }
    ],
    "sg:phone":"+1 919 790 9049",
    "sg:postcode":"27609",
    "sg:province":"NC",
    "sg:tags":[
        "oil",
        "tire",
        "retread",
        "lube",
        "balancing",
        "wheels-aligning",
        "recap"
    ],
    "sg:website":"http://www.justtires.com",
    "wof:name":"Just Tires",
    "wof:placetype":"venue"
},
  "geometry": {"coordinates":[-78.605234,35.850101],"type":"Point"}
}