{
  "type": "Feature",
  "properties": {
    "addr:full":"414 Village Rd NE Leland NC 28451",
    "addr:housenumber":"414",
    "addr:postcode":"28451",
    "addr:street":"Village Rd Ne",
    "iso:country":"US",
    "sg:address":"414 Village Rd NE",
    "sg:city":"Leland",
    "sg:classifiers":[
        {
            "category":"Restaurant",
            "type":"Food & Drink"
        }
    ],
    "sg:phone":"+1 910 383 3222",
    "sg:postcode":"28451",
    "sg:province":"NC",
    "wof:name":"Seguins Courtyard Cafe",
    "wof:placetype":"venue"
},
  "geometry": {"coordinates":[-78.00917,34.239663],"type":"Point"}
}