{
  "type": "Feature",
  "properties": {
    "iso:country":"US",
    "sg:address":"5200 New Centre Dr",
    "sg:city":"Wilmington",
    "sg:classifiers":[
        {
            "category":"Real Estate",
            "subcategory":"Real Estate Operator",
            "type":"Services"
        }
    ],
    "sg:phone":"+1 910 395 5678",
    "sg:postcode":"28403",
    "sg:province":"NC",
    "sg:tags":[
        "building",
        "apartment"
    ],
    "wof:name":"Clear Run Apartments",
    "wof:placetype":"venue"
},
  "geometry": {"coordinates":[-77.871836,34.236145],"type":"Point"}
}