{
  "type": "Feature",
  "properties": {
    "addr:full":"1003 E Webb Ave Burlington NC 27217",
    "addr:housenumber":"1003",
    "addr:postcode":"27217",
    "addr:street":"E Webb Ave",
    "iso:country":"US",
    "sg:address":"1003 E Webb Ave",
    "sg:city":"Burlington",
    "sg:classifiers":[
        {
            "category":"Retail",
            "subcategory":"Auto Repair",
            "type":"Services"
        }
    ],
    "sg:phone":"+1 336 570 2141",
    "sg:postcode":"27217",
    "sg:province":"NC",
    "sg:tags":[
        "repairing",
        "automobile"
    ],
    "wof:name":"El Escondido Auto Repair",
    "wof:placetype":"venue"
},
  "geometry": {"coordinates":[-79.425405,36.083513],"type":"Point"}
}