{
  "type": "Feature",
  "properties": {
    "addr:full":"707 Mistique Ct New Bern NC 28560",
    "addr:housenumber":"707",
    "addr:postcode":"28560",
    "addr:street":"Mistique Ct",
    "iso:country":"US",
    "sg:address":"707 Mistique Ct",
    "sg:city":"New Bern",
    "sg:classifiers":[
        {
            "category":"Health Services",
            "subcategory":"Medical Lab",
            "type":"Services"
        }
    ],
    "sg:phone":"+1   ",
    "sg:postcode":"28560",
    "sg:province":"NC",
    "sg:tags":[
        "laboratory"
    ],
    "wof:name":"Complete Clinical Research",
    "wof:placetype":"venue"
},
  "geometry": {"coordinates":[-76.98045500000001,35.080107],"type":"Point"}
}