{
  "type": "Feature",
  "properties": {
    "iso:country":"US",
    "sg:address":"1331 Golden Hill Rd",
    "sg:city":"Matthews",
    "sg:classifiers":[
        {
            "category":"Shopping",
            "subcategory":"Pets & Pet Supplies",
            "type":"Retail Goods"
        }
    ],
    "sg:phone":"+1 704 996 9011",
    "sg:postcode":"28105",
    "sg:province":"NC",
    "sg:tags":[
        "furnishing",
        "dog",
        "store",
        "cat"
    ],
    "wof:name":"Whisker Watchers Pet Sitting Se",
    "wof:placetype":"venue"
},
  "geometry": {"coordinates":[-80.710047,35.098118],"type":"Point"}
}