{
  "type": "Feature",
  "properties": {
    "addr:full":"126 Bb Dr Belmont NC 28012",
    "addr:housenumber":"126",
    "addr:postcode":"28012",
    "addr:street":"Bb Dr",
    "iso:country":"US",
    "sg:address":"126 Bb Dr",
    "sg:city":"Belmont",
    "sg:classifiers":[
        {
            "category":"Retail",
            "subcategory":"Auto Repair",
            "type":"Services"
        }
    ],
    "sg:phone":"+1   ",
    "sg:postcode":"28012",
    "sg:province":"NC",
    "sg:tags":[
        "automotive"
    ],
    "wof:name":"Lemleys Towing",
    "wof:placetype":"venue"
},
  "geometry": {"coordinates":[-81.034271,35.213685],"type":"Point"}
}