{
  "type": "Feature",
  "properties": {
    "iso:country":"US",
    "sg:address":"599 Vail Rd",
    "sg:city":"Pikeville",
    "sg:classifiers":[
        {
            "category":"Freight",
            "type":"Transportation"
        }
    ],
    "sg:phone":"+1 919 734 3612",
    "sg:postcode":"27863",
    "sg:province":"NC",
    "sg:tags":[
        "commercial",
        "storage",
        "special"
    ],
    "wof:name":"Sallie's Mini Storage",
    "wof:placetype":"venue"
},
  "geometry": {"coordinates":[-78.022819,35.469696],"type":"Point"}
}