{
  "type": "Feature",
  "properties": {
    "addr:full":"2121 Commonwealth Ave Charlotte NC 28205",
    "addr:housenumber":"2121",
    "addr:postcode":"28205",
    "addr:street":"Commonwealth Ave",
    "iso:country":"US",
    "sg:address":"2121 Commonwealth Ave",
    "sg:city":"Charlotte",
    "sg:classifiers":[
        {
            "category":"Organizations",
            "subcategory":"Professional Association",
            "type":"Services"
        }
    ],
    "sg:phone":"+1 704 334 2667",
    "sg:postcode":"28205",
    "sg:province":"NC",
    "wof:name":"Comp Program",
    "wof:placetype":"venue"
},
  "geometry": {"coordinates":[-80.809639,35.217624],"type":"Point"}
}