{
  "type": "Feature",
  "properties": {
    "addr:full":"602 Fairview St Kernersville NC 27284",
    "addr:housenumber":"602",
    "addr:postcode":"27284",
    "addr:street":"Fairview St",
    "iso:country":"US",
    "sg:address":"602 Fairview St",
    "sg:city":"Kernersville",
    "sg:classifiers":[
        {
            "category":"Retail",
            "subcategory":"Repair Shop",
            "type":"Services"
        }
    ],
    "sg:phone":"+1 336 993 5683",
    "sg:postcode":"27284",
    "sg:province":"NC",
    "sg:tags":[
        "ironwork"
    ],
    "wof:name":"Gibson Welding & Iron Works",
    "wof:placetype":"venue"
},
  "geometry": {"coordinates":[-80.076415,36.113125],"type":"Point"}
}