{
  "type": "Feature",
  "properties": {
    "iso:country":"US",
    "sg:address":"107 N Main St",
    "sg:city":"Kannapolis",
    "sg:classifiers":[
        {
            "category":"Manufacturing",
            "subcategory":"Printing",
            "type":"Manufacturing & Wholesale Goods"
        }
    ],
    "sg:phone":"+1 704 932 8415",
    "sg:postcode":"28081",
    "sg:province":"NC",
    "sg:tags":[
        "lithographic",
        "commercial"
    ],
    "wof:name":"J & B Printing Co",
    "wof:placetype":"venue"
},
  "geometry": {"coordinates":[-80.622471,35.500047],"type":"Point"}
}