{
  "type": "Feature",
  "properties": {
    "iso:country":"US",
    "sg:address":"7404 State Hwy 194 S",
    "sg:city":"Todd",
    "sg:classifiers":[
        {
            "category":"Building & Trades",
            "subcategory":"Landscaping Services",
            "type":"Services"
        }
    ],
    "sg:phone":"+1 336 877 8733",
    "sg:postcode":"28684",
    "sg:province":"NC",
    "sg:tags":[
        "tree"
    ],
    "wof:name":"High County Tree Svc",
    "wof:placetype":"venue"
},
  "geometry": {"coordinates":[-81.591244,36.314068],"type":"Point"}
}