{
  "type": "Feature",
  "properties": {
    "addr:full":"1281 Georgia Rd Franklin NC 28734",
    "addr:housenumber":"1281",
    "addr:postcode":"nc 28734",
    "addr:street":"Georgia Rd",
    "iso:country":"US",
    "sg:address":"1281 Georgia Rd",
    "sg:city":"Franklin",
    "sg:classifiers":[
        {
            "category":"Restaurant",
            "type":"Food & Drink"
        }
    ],
    "sg:phone":"+1 828 524 4800",
    "sg:postcode":"28734",
    "sg:province":"NC",
    "wof:name":"Lighthouse",
    "wof:placetype":"venue"
},
  "geometry": {"coordinates":[-83.383758,35.093981],"type":"Point"}
}