{
  "type": "Feature",
  "properties": {
    "addr:full":"205 Lloyd St Ste 101 Carrboro NC 27510",
    "addr:housenumber":"205",
    "addr:postcode":"27510",
    "addr:street":"Lloyd St Ste 101",
    "iso:country":"US",
    "sg:address":"205 Lloyd St Ste 101",
    "sg:city":"Carrboro",
    "sg:classifiers":[
        {
            "category":"Health Services",
            "subcategory":"Doctor",
            "type":"Services"
        }
    ],
    "sg:phone":"+1 919 933 8381",
    "sg:postcode":"27510",
    "sg:province":"NC",
    "wof:name":"Annis Cory L MD",
    "wof:placetype":"venue"
},
  "geometry": {"coordinates":[-79.069199,35.911499],"type":"Point"}
}