{
  "type": "Feature",
  "properties": {
    "addr:full":"6544 Lake Brandt Rd Summerfield NC 27358",
    "addr:housenumber":"6544",
    "addr:postcode":"27358",
    "addr:street":"Lake Brandt Rd",
    "iso:country":"US",
    "sg:address":"6544 Lake Brandt Rd",
    "sg:city":"Summerfield",
    "sg:classifiers":[
        {
            "category":"Place Of Worship",
            "subcategory":"Church",
            "type":"Public Place"
        },
        {
            "category":"Place Of Worship",
            "type":"Public Place"
        }
    ],
    "sg:phone":"+1 336 643 4225",
    "sg:postcode":"27358",
    "sg:province":"NC",
    "sg:tags":[
        "churches-baptist-general",
        "churches-baptist"
    ],
    "wof:name":"Lawsonville Road Baptist Ch",
    "wof:placetype":"venue"
},
  "geometry": {"coordinates":[-79.864198,36.229677],"type":"Point"}
}