{
  "type": "Feature",
  "properties": {
    "iso:country":"US",
    "sg:address":"235 N McPherson Church Rd",
    "sg:city":"Fayetteville",
    "sg:classifiers":[
        {
            "category":"Health Services",
            "subcategory":"Clinic",
            "type":"Services"
        }
    ],
    "sg:phone":"+1 910 860 0383",
    "sg:postcode":"28303",
    "sg:province":"NC",
    "wof:name":"Health Services-Cumberland",
    "wof:placetype":"venue"
},
  "geometry": {"coordinates":[-78.952167,35.07188],"type":"Point"}
}