{
  "type": "Feature",
  "properties": {
    "addr:full":"12121 S State Hwy 226 Spruce Pine NC 28777",
    "addr:housenumber":"12121",
    "addr:postcode":"28777",
    "addr:street":"S State Hwy 226",
    "iso:country":"US",
    "sg:address":"12121 S State Hwy 226",
    "sg:city":"Spruce Pine",
    "sg:classifiers":[
        {
            "category":"Shopping",
            "subcategory":"Pharmacy",
            "type":"Retail Goods"
        }
    ],
    "sg:phone":"+1 828 765 7076",
    "sg:postcode":"28777",
    "sg:province":"NC",
    "sg:website":"www.cvs.com",
    "wof:name":"CVS Pharmacy",
    "wof:placetype":"venue"
},
  "geometry": {"coordinates":[-82.06701700000001,35.890193],"type":"Point"}
}