{
  "type": "Feature",
  "properties": {
    "iso:country":"US",
    "sg:address":"228 Goldsboro St SW",
    "sg:city":"Wilson",
    "sg:classifiers":[
        {
            "category":"Farming",
            "subcategory":"Farm",
            "type":"Manufacturing & Wholesale Goods"
        }
    ],
    "sg:phone":"+1 252 291 3171",
    "sg:postcode":"27893",
    "sg:province":"NC",
    "wof:name":"Cozart Farms",
    "wof:placetype":"venue"
},
  "geometry": {"coordinates":[-77.91288900000001,35.723313],"type":"Point"}
}