{
  "type": "Feature",
  "properties": {
    "iso:country":"US",
    "sg:address":"704 Cherry Ln",
    "sg:city":"Shelby",
    "sg:classifiers":[
        {
            "category":"Retail",
            "subcategory":"Portrait Studio",
            "type":"Services"
        }
    ],
    "sg:phone":"+1   ",
    "sg:postcode":"28150",
    "sg:province":"NC",
    "sg:tags":[
        "photo"
    ],
    "wof:name":"Digital Dreams Photography",
    "wof:placetype":"venue"
},
  "geometry": {"coordinates":[-81.62745200000001,35.314903],"type":"Point"}
}