{
  "type": "Feature",
  "properties": {
    "addr:full":"3002 River Hill Ln Burlington NC 27217",
    "addr:housenumber":"3002",
    "addr:postcode":"27217",
    "addr:street":"River Hill Ln",
    "iso:country":"US",
    "sg:address":"3002 River Hill Ln",
    "sg:city":"Burlington",
    "sg:classifiers":[
        {
            "category":"Building & Trades",
            "subcategory":"Construction",
            "type":"Services"
        }
    ],
    "sg:phone":"+1 336 570 1896",
    "sg:postcode":"27217",
    "sg:province":"NC",
    "sg:tags":[
        "hanging",
        "contractor"
    ],
    "wof:name":"Jeff Russell Painting",
    "wof:placetype":"venue"
},
  "geometry": {"coordinates":[-79.482418,36.138069],"type":"Point"}
}