{
  "type": "Feature",
  "properties": {
    "iso:country":"US",
    "sg:address":"1005 Edwards Rd",
    "sg:city":"Sanford",
    "sg:classifiers":[
        {
            "category":"Government",
            "subcategory":"Office",
            "type":"Public Place"
        }
    ],
    "sg:phone":"+1 919 776 6644",
    "sg:postcode":"27332",
    "sg:province":"NC",
    "sg:tags":[
        "county"
    ],
    "sg:website":"www.harnettsheriff.com",
    "wof:name":"Harnett County Sheriff's Dept",
    "wof:placetype":"venue"
},
  "geometry": {"coordinates":[-79.17682600000001,35.393404],"type":"Point"}
}