{
  "type": "Feature",
  "properties": {
    "iso:country":"US",
    "sg:address":"1720 Braswell Rd",
    "sg:city":"Smithfield",
    "sg:classifiers":[
        {
            "category":"Building & Trades",
            "subcategory":"Plumbing",
            "type":"Services"
        }
    ],
    "sg:phone":"+1 919 965 8679",
    "sg:postcode":"27577",
    "sg:province":"NC",
    "sg:tags":[
        "contractor"
    ],
    "wof:name":"Sassers Plumbing",
    "wof:placetype":"venue"
},
  "geometry": {"coordinates":[-78.22056000000001,35.443801],"type":"Point"}
}