{
  "type": "Feature",
  "properties": {
    "iso:country":"US",
    "sg:address":"40 Windswept Dr",
    "sg:city":"Asheville",
    "sg:classifiers":[
        {
            "category":"Professional",
            "subcategory":"Secretarial Services",
            "type":"Services"
        }
    ],
    "sg:phone":"+1 828 273 6107",
    "sg:postcode":"28801",
    "sg:province":"NC",
    "sg:tags":[
        "reporting",
        "court"
    ],
    "wof:name":"Mailscribe Inc",
    "wof:placetype":"venue"
},
  "geometry": {"coordinates":[-82.542019,35.586],"type":"Point"}
}