{
  "type": "Feature",
  "properties": {
    "addr:full":"7328 Aragorn Ln Charlotte NC 28212",
    "addr:housenumber":"7328",
    "addr:postcode":"28212",
    "addr:street":"Aragorn Ln",
    "iso:country":"US",
    "sg:address":"7328 Aragorn Ln",
    "sg:city":"Charlotte",
    "sg:classifiers":[
        {
            "category":"Professional",
            "subcategory":"Printing & Photocopies",
            "type":"Services"
        }
    ],
    "sg:phone":"+1 704 532 4377",
    "sg:postcode":"28212",
    "sg:province":"NC",
    "sg:tags":[
        "services-commercial"
    ],
    "wof:name":"Deleon Printing",
    "wof:placetype":"venue"
},
  "geometry": {"coordinates":[-80.726292,35.16978],"type":"Point"}
}