{
  "type": "Feature",
  "properties": {
    "addr:full":"32 Oshea Ln Waynesville NC 28786",
    "addr:housenumber":"32",
    "addr:postcode":"28786",
    "addr:street":"Oshea Ln",
    "iso:country":"US",
    "sg:address":"32 Oshea Ln",
    "sg:city":"Waynesville",
    "sg:classifiers":[
        {
            "category":"Building & Trades",
            "subcategory":"Equipment Rental",
            "type":"Services"
        }
    ],
    "sg:phone":"+1   ",
    "sg:postcode":"28786",
    "sg:province":"NC",
    "wof:name":"Birchfeld Bros Port A John Svc",
    "wof:placetype":"venue"
},
  "geometry": {"coordinates":[-83.010418,35.480536],"type":"Point"}
}