{
  "type": "Feature",
  "properties": {
    "iso:country":"US",
    "sg:address":"704 Carolina Ave",
    "sg:city":"Ahoskie",
    "sg:classifiers":[
        {
            "category":"Social Services",
            "subcategory":"Adult Care",
            "type":"Services"
        }
    ],
    "sg:phone":"+1 252 209 0111",
    "sg:postcode":"27910",
    "sg:province":"NC",
    "sg:tags":[
        "home",
        "group"
    ],
    "wof:name":"Roanoke Place",
    "wof:placetype":"venue"
},
  "geometry": {"coordinates":[-76.985518,36.293059],"type":"Point"}
}