{
  "type": "Feature",
  "properties": {
    "iso:country":"US",
    "sg:address":"1038 Homeland Ave",
    "sg:city":"Greensboro",
    "sg:classifiers":[
        {
            "category":"Manufacturing",
            "subcategory":"Metals",
            "type":"Manufacturing & Wholesale Goods"
        }
    ],
    "sg:phone":"+1 336 272 5255",
    "sg:postcode":"27405",
    "sg:province":"NC",
    "sg:tags":[
        "shutter"
    ],
    "wof:name":"Custom Blinds-Blandwood Intrs",
    "wof:placetype":"venue"
},
  "geometry": {"coordinates":[-79.772335,36.086422],"type":"Point"}
}