{
  "type": "Feature",
  "properties": {
    "addr:full":"100 Price St Williamston NC 27892",
    "addr:housenumber":"100",
    "addr:postcode":"27892",
    "addr:street":"Price St",
    "iso:country":"US",
    "sg:address":"100 Price St",
    "sg:city":"Williamston",
    "sg:classifiers":[
        {
            "category":"Social Services",
            "subcategory":"Child Care",
            "type":"Services"
        }
    ],
    "sg:phone":"+1   ",
    "sg:postcode":"27892",
    "sg:province":"NC",
    "sg:tags":[
        "day"
    ],
    "wof:name":"Tender Care Daycare",
    "wof:placetype":"venue"
},
  "geometry": {"coordinates":[-77.06807999999999,35.849312],"type":"Point"}
}