{
  "type": "Feature",
  "properties": {
    "addr:full":"5747 State Hwy 58 Elm City NC 27822",
    "addr:housenumber":"5747",
    "addr:postcode":"27822",
    "addr:street":"State Hwy 58 Elm",
    "iso:country":"US",
    "sg:address":"5747 State Hwy 58",
    "sg:city":"Elm City",
    "sg:classifiers":[
        {
            "category":"Home & Garden",
            "subcategory":"Furniture",
            "type":"Retail Goods"
        }
    ],
    "sg:phone":"+1 252 237 0313",
    "sg:postcode":"27822",
    "sg:province":"NC",
    "sg:tags":[
        "builder",
        "custom"
    ],
    "wof:name":"Hart T Wiggins Custom Furn",
    "wof:placetype":"venue"
},
  "geometry": {"coordinates":[-77.94679499999999,35.808636],"type":"Point"}
}