{
  "type": "Feature",
  "properties": {
    "addr:full":"600 W Main St Sylva NC 28779",
    "addr:housenumber":"600",
    "addr:postcode":"28779",
    "addr:street":"W Main St",
    "iso:country":"US",
    "sg:address":"600 W Main St",
    "sg:city":"Sylva",
    "sg:classifiers":[
        {
            "category":"Shopping",
            "subcategory":"Jewelry",
            "type":"Retail Goods"
        }
    ],
    "sg:phone":"+1 828 586 4274",
    "sg:postcode":"28779",
    "sg:province":"NC",
    "sg:tags":[
        "jeweler"
    ],
    "wof:name":"Hollifield Jewelers",
    "wof:placetype":"venue"
},
  "geometry": {"coordinates":[-83.22472399999999,35.373644],"type":"Point"}
}