{
  "type": "Feature",
  "properties": {
    "iso:country":"US",
    "sg:address":"1550 Buck Jones Rd",
    "sg:city":"Raleigh",
    "sg:classifiers":[
        {
            "category":"Restaurant",
            "type":"Food & Drink"
        }
    ],
    "sg:phone":"+1 919 469 3663",
    "sg:postcode":"27606",
    "sg:province":"NC",
    "sg:tags":[
        "diner"
    ],
    "sg:website":"www.gypsysshinydiner.com/",
    "wof:name":"Gypsy's Shiny Diner",
    "wof:placetype":"venue"
},
  "geometry": {"coordinates":[-78.74539900000001,35.763199],"type":"Point"}
}