{
  "type": "Feature",
  "properties": {
    "addr:full":"900 West Blvd Laurinburg NC 28352",
    "addr:housenumber":"900",
    "addr:postcode":"28352",
    "addr:street":"West Blvd",
    "iso:country":"US",
    "sg:address":"900 West Blvd",
    "sg:city":"Laurinburg",
    "sg:classifiers":[
        {
            "category":"Food & Beverages",
            "subcategory":"Groceries & Convenience Stores",
            "type":"Retail Goods"
        }
    ],
    "sg:phone":"+1 910 276 1311",
    "sg:postcode":"28352",
    "sg:province":"NC",
    "wof:name":"Winn-Dixie",
    "wof:placetype":"venue"
},
  "geometry": {"coordinates":[-79.476871,34.76582],"type":"Point"}
}