{
  "type": "Feature",
  "properties": {
    "iso:country":"US",
    "sg:address":"686 Sunderland Rd SW",
    "sg:city":"Concord",
    "sg:phone":"+1 704 792 1816",
    "sg:postcode":"28027",
    "sg:province":"NC",
    "sg:tags":[
        "farm",
        "tobacco"
    ],
    "wof:name":"Delmar L Triplett",
    "wof:placetype":"venue"
},
  "geometry": {"coordinates":[-80.600391,35.392123],"type":"Point"}
}