{
  "type": "Feature",
  "properties": {
    "addr:full":"241 Butterball Rd Teachey NC 28464",
    "addr:housenumber":"241",
    "addr:postcode":"28464",
    "addr:street":"Butterball Rd",
    "iso:country":"US",
    "sg:address":"241 Butterball Rd",
    "sg:city":"Teachey",
    "sg:classifiers":[
        {
            "category":"Food & Beverages",
            "subcategory":"Groceries & Convenience Stores",
            "type":"Retail Goods"
        }
    ],
    "sg:phone":"+1 910 285 6145",
    "sg:postcode":"28464",
    "sg:province":"NC",
    "sg:tags":[
        "product"
    ],
    "wof:name":"Con Agra Foods",
    "wof:placetype":"venue"
},
  "geometry": {"coordinates":[-78.051579,34.75691],"type":"Point"}
}