{
  "type": "Feature",
  "properties": {
    "iso:country":"US",
    "sg:address":"203 E Morgan St",
    "sg:city":"Brevard",
    "sg:classifiers":[
        {
            "category":"Education",
            "subcategory":"Special Training",
            "type":"Public Place"
        }
    ],
    "sg:phone":"+1 828 884 3109",
    "sg:postcode":"28712",
    "sg:province":"NC",
    "wof:name":"Cooperative Extension Service",
    "wof:placetype":"venue"
},
  "geometry": {"coordinates":[-82.734973,35.231991],"type":"Point"}
}