{
  "type": "Feature",
  "properties": {
    "addr:full":"310 Grace St Wilmington NC 28401",
    "addr:housenumber":"310",
    "addr:postcode":"28401",
    "addr:street":"Grace St",
    "iso:country":"US",
    "sg:address":"310 Grace St",
    "sg:city":"Wilmington",
    "sg:classifiers":[
        {
            "category":"Personal",
            "subcategory":"Beauty Salon",
            "type":"Services"
        }
    ],
    "sg:phone":"+1 910 343 9919",
    "sg:postcode":"28401",
    "sg:province":"NC",
    "wof:name":"Renaissance Salon & Spa",
    "wof:placetype":"venue"
},
  "geometry": {"coordinates":[-77.94521899999999,34.239052],"type":"Point"}
}