{
  "type": "Feature",
  "properties": {
    "iso:country":"US",
    "sg:address":"2080 State Hwy 217",
    "sg:city":"Erwin",
    "sg:classifiers":[
        {
            "category":"Manufacturing",
            "subcategory":"Textiles",
            "type":"Manufacturing & Wholesale Goods"
        }
    ],
    "sg:phone":"+1 910 897 4854",
    "sg:postcode":"28339",
    "sg:province":"NC",
    "wof:name":"Swift Textiles Inc",
    "wof:placetype":"venue"
},
  "geometry": {"coordinates":[-78.69053099999999,35.312425],"type":"Point"}
}