{
  "type": "Feature",
  "properties": {
    "iso:country":"US",
    "sg:address":"1131 E Webb Ave",
    "sg:city":"Burlington",
    "sg:classifiers":[
        {
            "category":"Home & Garden",
            "subcategory":"Home Furnishings",
            "type":"Retail Goods"
        }
    ],
    "sg:phone":"+1 336 226 8429",
    "sg:postcode":"27217",
    "sg:province":"NC",
    "sg:tags":[
        "bathroom",
        "fixture",
        "accessory"
    ],
    "wof:name":"Bennett-Hockett Supply Co",
    "wof:placetype":"venue"
},
  "geometry": {"coordinates":[-79.42418000000001,36.08256],"type":"Point"}
}