{
  "type": "Feature",
  "properties": {
    "addr:full":"316 W Mountain St Kernersville NC 27284",
    "addr:housenumber":"316",
    "addr:postcode":"27284",
    "addr:street":"W Mountain St",
    "iso:country":"US",
    "sg:address":"316 W Mountain St",
    "sg:city":"Kernersville",
    "sg:classifiers":[
        {
            "category":"Retail",
            "subcategory":"Auto Repair",
            "type":"Services"
        }
    ],
    "sg:phone":"+1 336 992 2555",
    "sg:postcode":"27284",
    "sg:province":"NC",
    "sg:tags":[
        "repairing",
        "automobile"
    ],
    "wof:name":"C & H Discount Auto",
    "wof:placetype":"venue"
},
  "geometry": {"coordinates":[-80.076142,36.122713],"type":"Point"}
}