{
  "type": "Feature",
  "properties": {
    "addr:full":"2004 Bancroft St Charlotte NC 28206",
    "addr:housenumber":"2004",
    "addr:postcode":"28206",
    "addr:street":"Bancroft St",
    "iso:country":"US",
    "sg:address":"2004 Bancroft St",
    "sg:city":"Charlotte",
    "sg:classifiers":[
        {
            "category":"Manufacturing",
            "subcategory":"Glass & Minerals",
            "type":"Manufacturing & Wholesale Goods"
        }
    ],
    "sg:phone":"+1 704 887 7924",
    "sg:postcode":"28206",
    "sg:province":"NC",
    "sg:website":"http://www.caesarstoneus.com",
    "wof:name":"U.S. Quartz Products, Inc.",
    "wof:placetype":"venue"
},
  "geometry": {"coordinates":[-80.829055,35.244881],"type":"Point"}
}