{
  "type": "Feature",
  "properties": {
    "iso:country":"US",
    "sg:address":"215 Trindale Rd",
    "sg:city":"Archdale",
    "sg:classifiers":[
        {
            "category":"Shopping",
            "subcategory":"Used Merchandise",
            "type":"Retail Goods"
        }
    ],
    "sg:phone":"+1 336 434 7491",
    "sg:postcode":"27263",
    "sg:province":"NC",
    "sg:tags":[
        "shop",
        "consignment"
    ],
    "wof:name":"Decorator's Domain",
    "wof:placetype":"venue"
},
  "geometry": {"coordinates":[-79.976296,35.913237],"type":"Point"}
}