{
  "type": "Feature",
  "properties": {
    "iso:country":"US",
    "sg:address":"2093 Highlands Rd",
    "sg:city":"Franklin",
    "sg:classifiers":[
        {
            "category":"Shopping",
            "type":"Retail Goods"
        }
    ],
    "sg:phone":"+1 828 369 3810",
    "sg:postcode":"28734",
    "sg:province":"NC",
    "sg:tags":[
        "merchandise",
        "animal"
    ],
    "wof:name":"Puttin On Dog Inc",
    "wof:placetype":"venue"
},
  "geometry": {"coordinates":[-83.353801,35.176474],"type":"Point"}
}