{
  "type": "Feature",
  "properties": {
    "iso:country":"US",
    "sg:address":"170 Old Tram Rd",
    "sg:city":"Whiteville",
    "sg:classifiers":[
        {
            "category":"Organizations",
            "subcategory":"Religious Organization",
            "type":"Services"
        }
    ],
    "sg:phone":"+1   ",
    "sg:postcode":"28472",
    "sg:province":"NC",
    "wof:name":"Antioch Baptist Church",
    "wof:placetype":"venue"
},
  "geometry": {"coordinates":[-78.71795899999999,34.223167],"type":"Point"}
}