{
  "type": "Feature",
  "properties": {
    "iso:country":"US",
    "sg:address":"268 Russells Creek Rd",
    "sg:city":"Beaufort",
    "sg:classifiers":[
        {
            "category":"Building & Trades",
            "subcategory":"Landscaping Services",
            "type":"Services"
        }
    ],
    "sg:phone":"+1 252 728 7369",
    "sg:postcode":"28516",
    "sg:province":"NC",
    "wof:name":"Adams Lawn & Maintenance",
    "wof:placetype":"venue"
},
  "geometry": {"coordinates":[-76.664362,34.764983],"type":"Point"}
}