{
  "type": "Feature",
  "properties": {
    "iso:country":"US",
    "sg:address":"500 W High Ave",
    "sg:city":"High Point",
    "sg:classifiers":[
        {
            "category":"Home & Garden",
            "subcategory":"Carpets & Floor Coverings",
            "type":"Retail Goods"
        }
    ],
    "sg:phone":"+1 336 886 3164",
    "sg:postcode":"27260",
    "sg:province":"NC",
    "sg:tags":[
        "dealer",
        "rug"
    ],
    "wof:name":"Tamarian Carpets Inc",
    "wof:placetype":"venue"
},
  "geometry": {"coordinates":[-80.012795,35.953133],"type":"Point"}
}