{
  "type": "Feature",
  "properties": {
    "iso:country":"US",
    "sg:address":"1351 Asheville Hwy",
    "sg:city":"Hendersonville",
    "sg:classifiers":[
        {
            "category":"Travel",
            "subcategory":"Hotels & Motels",
            "type":"Entertainment"
        }
    ],
    "sg:phone":"+1 828 692 9173",
    "sg:postcode":"28791",
    "sg:province":"NC",
    "wof:name":"Mountain Aire Cottages",
    "wof:placetype":"venue"
},
  "geometry": {"coordinates":[-82.46762200000001,35.327533],"type":"Point"}
}