{
  "type": "Feature",
  "properties": {
    "addr:full":"5223 Revere Rd Durham NC 27713",
    "addr:housenumber":"5223",
    "addr:postcode":"27713",
    "addr:street":"Revere Rd",
    "iso:country":"US",
    "sg:address":"5223 Revere Rd",
    "sg:city":"Durham",
    "sg:classifiers":[
        {
            "category":"Professional",
            "subcategory":"Management & Consulting",
            "type":"Services"
        }
    ],
    "sg:phone":"+1 919 544 2370",
    "sg:postcode":"27713",
    "sg:province":"NC",
    "sg:tags":[
        "theatrical"
    ],
    "wof:name":"Carolina Ha Ha",
    "wof:placetype":"venue"
},
  "geometry": {"coordinates":[-78.907222,35.890105],"type":"Point"}
}