{
  "type": "Feature",
  "properties": {
    "iso:country":"US",
    "sg:address":"1033 E King St",
    "sg:city":"Boone",
    "sg:classifiers":[
        {
            "category":"Food & Beverages",
            "subcategory":"Groceries & Convenience Stores",
            "type":"Retail Goods"
        }
    ],
    "sg:phone":"+1 828 264 2285",
    "sg:postcode":"28607",
    "sg:province":"NC",
    "wof:name":"Wilcohess",
    "wof:placetype":"venue"
},
  "geometry": {"coordinates":[-81.668325,36.21642],"type":"Point"}
}