{
  "type": "Feature",
  "properties": {
    "iso:country":"US",
    "sg:address":"9801 Mallard Creek Rd",
    "sg:city":"Charlotte",
    "sg:classifiers":[
        {
            "category":"Education",
            "subcategory":"School",
            "type":"Public Place"
        }
    ],
    "sg:phone":"+1 980 343 3980",
    "sg:postcode":"28262",
    "sg:province":"NC",
    "wof:name":"Mallard Creek Elementary Schl",
    "wof:placetype":"venue"
},
  "geometry": {"coordinates":[-80.773224,35.332071],"type":"Point"}
}