{
  "type": "Feature",
  "properties": {
    "addr:full":"701 Plantation Estates Dr Matthews NC 28105",
    "addr:housenumber":"701",
    "addr:postcode":"28105",
    "addr:street":"Plantation Estates Dr",
    "iso:country":"US",
    "sg:address":"701 Plantation Estates Dr",
    "sg:city":"Matthews",
    "sg:classifiers":[
        {
            "category":"Health Services",
            "subcategory":"Nursing And Care Facility",
            "type":"Services"
        }
    ],
    "sg:phone":"+1   ",
    "sg:postcode":"28105",
    "sg:province":"NC",
    "sg:tags":[
        "skilled",
        "center"
    ],
    "wof:name":"Genesis",
    "wof:placetype":"venue"
},
  "geometry": {"coordinates":[-80.73454,35.112296],"type":"Point"}
}