{
  "type": "Feature",
  "properties": {
    "addr:full":"5420 Amsterdam Pl Raleigh NC 27606",
    "addr:housenumber":"5420",
    "addr:postcode":"27606",
    "addr:street":"Amsterdam Pl",
    "iso:country":"US",
    "sg:address":"5420 Amsterdam Pl",
    "sg:city":"Raleigh",
    "sg:classifiers":[
        {
            "category":"Building & Trades",
            "subcategory":"Electrical",
            "type":"Services"
        }
    ],
    "sg:phone":"+1 919 362 7000",
    "sg:postcode":"27606",
    "sg:province":"NC",
    "sg:tags":[
        "electric",
        "contractor"
    ],
    "wof:name":"Ogilvie Electric",
    "wof:placetype":"venue"
},
  "geometry": {"coordinates":[-78.776687,35.705627],"type":"Point"}
}