{
  "type": "Feature",
  "properties": {
    "addr:full":"139 S College St Boiling Springs NC 28034",
    "addr:housenumber":"139",
    "addr:postcode":"28034",
    "addr:street":"S College St",
    "iso:country":"US",
    "sg:address":"139 S College St",
    "sg:city":"Boiling Springs",
    "sg:classifiers":[
        {
            "category":"Personal",
            "subcategory":"Beauty Salon",
            "type":"Services"
        }
    ],
    "sg:phone":"+1   ",
    "sg:postcode":"28034",
    "sg:province":"NC",
    "sg:tags":[
        "shop"
    ],
    "wof:name":"Wagon Wheel Beauty Salon",
    "wof:placetype":"venue"
},
  "geometry": {"coordinates":[-81.174632,35.314948],"type":"Point"}
}