{
  "type": "Feature",
  "properties": {
    "iso:country":"US",
    "sg:address":"2210 E Millbrook Rd",
    "sg:city":"Raleigh",
    "sg:classifiers":[
        {
            "category":"Personal",
            "subcategory":"Beauty Salon",
            "type":"Services"
        }
    ],
    "sg:phone":"+1 919 981 6521",
    "sg:postcode":"27604",
    "sg:province":"NC",
    "wof:name":"Bebe Hair Braiding",
    "wof:placetype":"venue"
},
  "geometry": {"coordinates":[-78.59913299999999,35.848462],"type":"Point"}
}