{
  "type": "Feature",
  "properties": {
    "addr:full":"3401 Bon-Rea Dr Charlotte NC 28226",
    "addr:housenumber":"3401",
    "addr:postcode":"28226",
    "addr:street":"Bon-Rea Dr",
    "iso:country":"US",
    "sg:address":"3401 Bon-Rea Dr",
    "sg:city":"Charlotte",
    "sg:classifiers":[
        {
            "category":"Restaurant",
            "type":"Food & Drink"
        }
    ],
    "sg:phone":"+1 704 543 8759",
    "sg:postcode":"28226",
    "sg:province":"NC",
    "sg:tags":[
        "eating"
    ],
    "wof:name":"Bayou Smokehouse Inc",
    "wof:placetype":"venue"
},
  "geometry": {"coordinates":[-80.791169,35.101821],"type":"Point"}
}