{
  "type": "Feature",
  "properties": {
    "iso:country":"US",
    "sg:address":"4603 Oakhill School Rd",
    "sg:city":"Lenoir",
    "sg:classifiers":[
        {
            "category":"Education",
            "subcategory":"School",
            "type":"Public Place"
        }
    ],
    "sg:phone":"+1 828 754 6128",
    "sg:postcode":"28645",
    "sg:province":"NC",
    "sg:tags":[
        "elementary"
    ],
    "wof:name":"Oak Hill Elementary School",
    "wof:placetype":"venue"
},
  "geometry": {"coordinates":[-81.414935,35.903496],"type":"Point"}
}