{
  "type": "Feature",
  "properties": {
    "addr:full":"335 Lariat Cir Salisbury NC 28144",
    "addr:housenumber":"335",
    "addr:postcode":"28144",
    "addr:street":"Lariat Cir",
    "iso:country":"US",
    "sg:address":"335 Lariat Cir",
    "sg:city":"Salisbury",
    "sg:classifiers":[
        {
            "category":"Professional",
            "subcategory":"Detective & Security Services",
            "type":"Services"
        }
    ],
    "sg:phone":"+1 704 636 9594",
    "sg:postcode":"28144",
    "sg:province":"NC",
    "sg:tags":[
        "guard",
        "patrol"
    ],
    "wof:name":"Piedmont Security Patrol",
    "wof:placetype":"venue"
},
  "geometry": {"coordinates":[-80.483751,35.715815],"type":"Point"}
}