{
  "type": "Feature",
  "properties": {
    "addr:full":"1002 E Garrison Blvd Gastonia NC 28054",
    "addr:housenumber":"1002",
    "addr:postcode":"28054",
    "addr:street":"E Garrison Blvd",
    "iso:country":"US",
    "sg:address":"1002 E Garrison Blvd",
    "sg:city":"Gastonia",
    "sg:classifiers":[
        {
            "category":"Personal",
            "subcategory":"Beauty Salon",
            "type":"Services"
        }
    ],
    "sg:phone":"+1   ",
    "sg:postcode":"28054",
    "sg:province":"NC",
    "sg:tags":[
        "shop"
    ],
    "wof:name":"Cutting Edge Hair Salon",
    "wof:placetype":"venue"
},
  "geometry": {"coordinates":[-81.165859,35.253244],"type":"Point"}
}