{
  "type": "Feature",
  "properties": {
    "addr:full":"1802 Britton St Greensboro NC 27406",
    "addr:housenumber":"1802",
    "addr:postcode":"27406",
    "addr:street":"Britton St",
    "iso:country":"US",
    "sg:address":"1802 Britton St",
    "sg:city":"Greensboro",
    "sg:classifiers":[
        {
            "category":"Organizations",
            "subcategory":"Religious Organization",
            "type":"Services"
        }
    ],
    "sg:phone":"+1 336 273 4732",
    "sg:postcode":"27406",
    "sg:province":"NC",
    "sg:tags":[
        "church"
    ],
    "wof:name":"Godly Love Baptist Church",
    "wof:placetype":"venue"
},
  "geometry": {"coordinates":[-79.777202,36.05063],"type":"Point"}
}