{
  "type": "Feature",
  "properties": {
    "iso:country":"US",
    "sg:address":"901 N Winstead Ave",
    "sg:city":"Rocky Mount",
    "sg:classifiers":[
        {
            "category":"Health Services",
            "subcategory":"Doctor",
            "type":"Services"
        }
    ],
    "sg:phone":"+1 252 443 7331",
    "sg:postcode":"27804",
    "sg:province":"NC",
    "sg:tags":[
        "dentist"
    ],
    "wof:name":"Winslow Brrnger Crsttto Drs PA",
    "wof:placetype":"venue"
},
  "geometry": {"coordinates":[-77.84011099999999,35.981924],"type":"Point"}
}