{
  "type": "Feature",
  "properties": {
    "addr:full":"12888 State Hwy 48 Littleton NC 27850",
    "addr:housenumber":"12888",
    "addr:postcode":"27850",
    "addr:street":"State Hwy 48",
    "iso:country":"US",
    "sg:address":"12888 State Hwy 48",
    "sg:city":"Littleton",
    "sg:classifiers":[
        {
            "category":"Manufacturing",
            "subcategory":"Lumber",
            "type":"Manufacturing & Wholesale Goods"
        }
    ],
    "sg:phone":"+1 252 586 4692",
    "sg:postcode":"27850",
    "sg:province":"NC",
    "sg:tags":[
        "logging"
    ],
    "wof:name":"Crawley Logging",
    "wof:placetype":"venue"
},
  "geometry": {"coordinates":[-77.80932300000001,36.33091],"type":"Point"}
}