{
  "type": "Feature",
  "properties": {
    "iso:country":"US",
    "sg:address":"188 Corbett Hill Rd",
    "sg:city":"Mount Olive",
    "sg:classifiers":[
        {
            "category":"Farming",
            "subcategory":"Farm",
            "type":"Manufacturing & Wholesale Goods"
        }
    ],
    "sg:phone":"+1 919 689 9739",
    "sg:postcode":"28365",
    "sg:province":"NC",
    "sg:tags":[
        "crop",
        "general"
    ],
    "wof:name":"Thornton Ammie",
    "wof:placetype":"venue"
},
  "geometry": {"coordinates":[-78.20784399999999,35.269855],"type":"Point"}
}