{
  "type": "Feature",
  "properties": {
    "addr:full":"4900 Raeford Rd Fayetteville NC 28304",
    "addr:housenumber":"4900",
    "addr:postcode":"28304",
    "addr:street":"Raeford Rd",
    "iso:country":"US",
    "sg:address":"4900 Raeford Rd",
    "sg:city":"Fayetteville",
    "sg:classifiers":[
        {
            "category":"Autos & Motor Vehicles",
            "subcategory":"Automobile Sales",
            "type":"Retail Goods"
        }
    ],
    "sg:phone":"+1 910 423 6981",
    "sg:postcode":"28304",
    "sg:province":"NC",
    "sg:tags":[
        "car",
        "dealer"
    ],
    "wof:name":"MWS Inc",
    "wof:placetype":"venue"
},
  "geometry": {"coordinates":[-78.96098499999999,35.042868],"type":"Point"}
}