{
  "type": "Feature",
  "properties": {
    "addr:full":"275 River Rd Rockingham NC 28379",
    "addr:housenumber":"275",
    "addr:postcode":"28379",
    "addr:street":"River Rd",
    "iso:country":"US",
    "sg:address":"275 River Rd",
    "sg:city":"Rockingham",
    "sg:classifiers":[
        {
            "category":"Communications",
            "subcategory":"Radio Station",
            "type":"Services"
        }
    ],
    "sg:phone":"+1 910 997 2526",
    "sg:postcode":"28379",
    "sg:province":"NC",
    "sg:tags":[
        "company",
        "broadcasting"
    ],
    "wof:name":"WLWL",
    "wof:placetype":"venue"
},
  "geometry": {"coordinates":[-79.78622799999999,34.926213],"type":"Point"}
}