{
  "type": "Feature",
  "properties": {
    "addr:full":"402 Park Ave Salisbury NC 28144",
    "addr:housenumber":"402",
    "addr:postcode":"28144",
    "addr:street":"Park Ave",
    "iso:country":"US",
    "sg:address":"402 Park Ave",
    "sg:city":"Salisbury",
    "sg:classifiers":[
        {
            "category":"Food & Beverages",
            "subcategory":"Groceries & Convenience Stores",
            "type":"Retail Goods"
        }
    ],
    "sg:phone":"+1 704 637 0641",
    "sg:postcode":"28144",
    "sg:province":"NC",
    "wof:name":"Spee-Dee Mart Inc",
    "wof:placetype":"venue"
},
  "geometry": {"coordinates":[-80.46227399999999,35.66642],"type":"Point"}
}