{
  "type": "Feature",
  "properties": {
    "iso:country":"US",
    "sg:address":"3519 Bragg Blvd",
    "sg:city":"Fayetteville",
    "sg:classifiers":[
        {
            "category":"Autos & Motor Vehicles",
            "subcategory":"Automobile Sales",
            "type":"Retail Goods"
        }
    ],
    "sg:phone":"+1 910 826 7100",
    "sg:postcode":"28303",
    "sg:province":"NC",
    "sg:tags":[
        "car",
        "dealer"
    ],
    "wof:name":"5 Points Automax",
    "wof:placetype":"venue"
},
  "geometry": {"coordinates":[-78.93803200000001,35.077563],"type":"Point"}
}