{
  "type": "Feature",
  "properties": {
    "addr:full":"4100 Well Spring Dr Greensboro NC 27410",
    "addr:housenumber":"4100",
    "addr:postcode":"27410",
    "addr:street":"Well Spring Dr",
    "iso:country":"US",
    "sg:address":"4100 Well Spring Dr",
    "sg:city":"Greensboro",
    "sg:classifiers":[
        {
            "category":"Health Services",
            "subcategory":"Nursing And Care Facility",
            "type":"Services"
        },
        {
            "category":"Real Estate",
            "subcategory":"Real Estate Operator",
            "type":"Services"
        }
    ],
    "sg:phone":"+1 336 545 5400",
    "sg:postcode":"27410",
    "sg:province":"NC",
    "sg:tags":[
        "home",
        "life",
        "retirement",
        "community"
    ],
    "sg:website":"www.well-spring.org",
    "wof:name":"Well Spring",
    "wof:placetype":"venue"
},
  "geometry": {"coordinates":[-79.87503599999999,36.132509],"type":"Point"}
}