{
  "type": "Feature",
  "properties": {
    "iso:country":"US",
    "sg:address":"914 Dickerson Rd",
    "sg:city":"Ruffin",
    "sg:classifiers":[
        {
            "category":"Farming",
            "subcategory":"Farm",
            "type":"Manufacturing & Wholesale Goods"
        }
    ],
    "sg:phone":"+1 336 939 7164",
    "sg:postcode":"27326",
    "sg:province":"NC",
    "sg:tags":[
        "crop",
        "general"
    ],
    "wof:name":"Strader Farm",
    "wof:placetype":"venue"
},
  "geometry": {"coordinates":[-79.59307800000001,36.484448],"type":"Point"}
}