{
  "type": "Feature",
  "properties": {
    "iso:country":"US",
    "sg:address":"9154 Clervie Dr",
    "sg:city":"Linden",
    "sg:classifiers":[
        {
            "category":"Building & Trades",
            "subcategory":"Landscaping Services",
            "type":"Services"
        }
    ],
    "sg:phone":"+1 910 822 5800",
    "sg:postcode":"28356",
    "sg:province":"NC",
    "sg:tags":[
        "landscape"
    ],
    "wof:name":"Grounds Pro",
    "wof:placetype":"venue"
},
  "geometry": {"coordinates":[-78.736204,35.250501],"type":"Point"}
}