{
  "type": "Feature",
  "properties": {
    "addr:full":"10404 Granite St Charlotte NC 28273",
    "addr:housenumber":"10404",
    "addr:postcode":"28273",
    "addr:street":"Granite St",
    "iso:country":"US",
    "sg:address":"10404 Granite St",
    "sg:city":"Charlotte",
    "sg:classifiers":[
        {
            "category":"Wholesale",
            "subcategory":"Metals & Minerals",
            "type":"Manufacturing & Wholesale Goods"
        }
    ],
    "sg:phone":"+1 704 588 4111",
    "sg:postcode":"28273",
    "sg:province":"NC",
    "sg:tags":[
        "specialty"
    ],
    "sg:website":"www.twmetals.com",
    "wof:name":"T W Metals Co",
    "wof:placetype":"venue"
},
  "geometry": {"coordinates":[-80.92348200000001,35.126235],"type":"Point"}
}