{
  "type": "Feature",
  "properties": {
    "addr:full":"1117 South Blvd Charlotte NC 28203",
    "addr:housenumber":"1117",
    "addr:postcode":"28203",
    "addr:street":"South Blvd",
    "iso:country":"US",
    "sg:address":"1117 South Blvd",
    "sg:city":"Charlotte",
    "sg:classifiers":[
        {
            "category":"Organizations",
            "subcategory":"Religious Organization",
            "type":"Services"
        }
    ],
    "sg:phone":"+1   ",
    "sg:postcode":"28203",
    "sg:province":"NC",
    "sg:tags":[
        "business"
    ],
    "wof:name":"Dial-A-Prayer",
    "wof:placetype":"venue"
},
  "geometry": {"coordinates":[-80.851162,35.217049],"type":"Point"}
}