{
  "type": "Feature",
  "properties": {
    "iso:country":"US",
    "sg:address":"533 E Martin St",
    "sg:city":"Raleigh",
    "sg:classifiers":[
        {
            "category":"Professional",
            "subcategory":"Detective & Security Services",
            "type":"Services"
        }
    ],
    "sg:phone":"+1 919 829 9447",
    "sg:postcode":"27601",
    "sg:province":"NC",
    "sg:tags":[
        "investigator"
    ],
    "wof:name":"Rogers Worldwide Investigation",
    "wof:placetype":"venue"
},
  "geometry": {"coordinates":[-78.629302,35.776645],"type":"Point"}
}