{
  "type": "Feature",
  "properties": {
    "addr:full":"624 Holly Springs Rd Holly Springs NC 27540",
    "addr:housenumber":"624",
    "addr:postcode":"27540",
    "addr:street":"Holly Springs Rd",
    "iso:country":"US",
    "sg:address":"624 Holly Springs Rd",
    "sg:city":"Holly Springs",
    "sg:classifiers":[
        {
            "category":"Professional",
            "subcategory":"Advertising",
            "type":"Services"
        }
    ],
    "sg:phone":"+1   ",
    "sg:postcode":"27540",
    "sg:province":"NC",
    "sg:tags":[
        "mail",
        "direct"
    ],
    "wof:name":"UPS",
    "wof:placetype":"venue"
},
  "geometry": {"coordinates":[-78.826081,35.654718],"type":"Point"}
}