{
  "type": "Feature",
  "properties": {
    "addr:full":"701 Peregrine Ct Gastonia NC 28056",
    "addr:housenumber":"701",
    "addr:postcode":"28056",
    "addr:street":"Peregrine Ct",
    "iso:country":"US",
    "sg:address":"701 Peregrine Ct",
    "sg:city":"Gastonia",
    "sg:classifiers":[
        {
            "category":"Banks & Credit Unions",
            "subcategory":"Financial Services",
            "type":"Services"
        }
    ],
    "sg:phone":"+1 704 868 3849",
    "sg:postcode":"28056",
    "sg:province":"NC",
    "sg:tags":[
        "investor"
    ],
    "wof:name":"Prime Real Estate Investments",
    "wof:placetype":"venue"
},
  "geometry": {"coordinates":[-81.182558,35.228148],"type":"Point"}
}