{
  "type": "Feature",
  "properties": {
    "iso:country":"US",
    "sg:address":"435 Lansing St",
    "sg:city":"Raleigh",
    "sg:classifiers":[
        {
            "category":"Organizations",
            "subcategory":"Religious Organization",
            "type":"Services"
        }
    ],
    "sg:phone":"+1 919 848 8598",
    "sg:postcode":"27610",
    "sg:province":"NC",
    "sg:tags":[
        "church"
    ],
    "wof:name":"Hickory Grove United Ch Christ",
    "wof:placetype":"venue"
},
  "geometry": {"coordinates":[-78.610415,35.773167],"type":"Point"}
}