{
  "type": "Feature",
  "properties": {
    "addr:full":"2538 Olivet Church Rd Winston Salem NC 27106",
    "addr:housenumber":"2538",
    "addr:postcode":"27106",
    "addr:street":"Olivet Church Rd",
    "iso:country":"US",
    "sg:address":"2538 Olivet Church Rd",
    "sg:city":"Winston Salem",
    "sg:classifiers":[
        {
            "category":"Building & Trades",
            "subcategory":"Construction",
            "type":"Services"
        }
    ],
    "sg:phone":"+1 336 924 6009",
    "sg:postcode":"27106",
    "sg:province":"NC",
    "sg:tags":[
        "carpentry",
        "contractor"
    ],
    "wof:name":"Star Interior Carpentry",
    "wof:placetype":"venue"
},
  "geometry": {"coordinates":[-80.37793499999999,36.14122],"type":"Point"}
}