{
  "type": "Feature",
  "properties": {
    "iso:country":"US",
    "sg:address":"1813 Eastchester Dr",
    "sg:city":"High Point",
    "sg:classifiers":[
        {
            "category":"Health Services",
            "subcategory":"Doctor",
            "type":"Services"
        }
    ],
    "sg:phone":"+1 336 885 5500",
    "sg:postcode":"27265",
    "sg:province":"NC",
    "sg:tags":[
        "dentist"
    ],
    "wof:name":"Stephanie P Lindsay Pa",
    "wof:placetype":"venue"
},
  "geometry": {"coordinates":[-79.985316,36.009587],"type":"Point"}
}