{
  "type": "Feature",
  "properties": {
    "iso:country":"US",
    "sg:address":"8139 Brooks Lake Rd",
    "sg:city":"Browns Summit",
    "sg:classifiers":[
        {
            "category":"Retail",
            "subcategory":"Repair Shop",
            "type":"Services"
        }
    ],
    "sg:phone":"+1   ",
    "sg:postcode":"27214",
    "sg:province":"NC",
    "wof:name":"Dustbusters",
    "wof:placetype":"venue"
},
  "geometry": {"coordinates":[-79.721959,36.248176],"type":"Point"}
}