{
  "type": "Feature",
  "properties": {
    "iso:country":"US",
    "sg:address":"215 Doctors St",
    "sg:city":"Boone",
    "sg:classifiers":[
        {
            "category":"Health Services",
            "subcategory":"Health Practitioner",
            "type":"Services"
        }
    ],
    "sg:phone":"+1 828 268 9043",
    "sg:postcode":"28675",
    "sg:province":"NC",
    "sg:tags":[
        "therapist",
        "physical"
    ],
    "wof:name":"Blue Ridge Physical Therapy",
    "wof:placetype":"venue"
},
  "geometry": {"coordinates":[-81.115657,36.508851],"type":"Point"}
}