{
  "type": "Feature",
  "properties": {
    "addr:full":"705 Princess St Wilmington NC 28401",
    "addr:housenumber":"705",
    "addr:postcode":"28401",
    "addr:street":"Princess St",
    "iso:country":"US",
    "sg:address":"705 Princess St",
    "sg:city":"Wilmington",
    "sg:classifiers":[
        {
            "category":"Professional",
            "subcategory":"Lawyer & Legal Services",
            "type":"Services"
        }
    ],
    "sg:phone":"+1   ",
    "sg:postcode":"28401",
    "sg:province":"NC",
    "wof:name":"Baker & Slaughter Law Firm",
    "wof:placetype":"venue"
},
  "geometry": {"coordinates":[-77.93955099999999,34.237291],"type":"Point"}
}