{
  "type": "Feature",
  "properties": {
    "iso:country":"US",
    "sg:address":"1221 Diana Lee Ln",
    "sg:city":"Monroe",
    "sg:classifiers":[
        {
            "category":"Utilities",
            "subcategory":"Cable",
            "type":"Services"
        }
    ],
    "sg:phone":"+1 704 283 8778",
    "sg:postcode":"28112",
    "sg:province":"NC",
    "sg:tags":[
        "television"
    ],
    "wof:name":"Union Cable Inc",
    "wof:placetype":"venue"
},
  "geometry": {"coordinates":[-80.57328099999999,34.922816],"type":"Point"}
}