{
  "type": "Feature",
  "properties": {
    "iso:country":"US",
    "sg:address":"1671 Huffman Mill Rd",
    "sg:city":"Burlington",
    "sg:classifiers":[
        {
            "category":"Mining & Drilling",
            "type":"Manufacturing & Wholesale Goods"
        }
    ],
    "sg:phone":"+1 336 584 8875",
    "sg:postcode":"27215",
    "sg:province":"NC",
    "sg:tags":[
        "stone"
    ],
    "wof:name":"Martin Marietta Aggregates",
    "wof:placetype":"venue"
},
  "geometry": {"coordinates":[-79.50744299999999,36.055454],"type":"Point"}
}