{
  "type": "Feature",
  "properties": {
    "iso:country":"US",
    "sg:address":"2250 Hatchery Rd",
    "sg:city":"Burlington",
    "sg:classifiers":[
        {
            "category":"Home & Garden",
            "subcategory":"Building Materials",
            "type":"Retail Goods"
        }
    ],
    "sg:phone":"+1 336 226 2507",
    "sg:postcode":"27215",
    "sg:province":"NC",
    "sg:tags":[
        "mixed",
        "concrete"
    ],
    "wof:name":"Rmc Cemex",
    "wof:placetype":"venue"
},
  "geometry": {"coordinates":[-79.467247,36.062416],"type":"Point"}
}