{
  "type": "Feature",
  "properties": {
    "iso:country":"US",
    "sg:address":"370 Elm Bend Rd",
    "sg:city":"Brevard",
    "sg:classifiers":[
        {
            "category":"Building & Trades",
            "subcategory":"Construction",
            "type":"Services"
        }
    ],
    "sg:phone":"+1 828 883 8245",
    "sg:postcode":"28712",
    "sg:province":"SC",
    "sg:tags":[
        "house"
    ],
    "wof:name":"Charles M Morgan & Co",
    "wof:placetype":"venue"
},
  "geometry": {"coordinates":[-82.71433,35.224463],"type":"Point"}
}