{
  "type": "Feature",
  "properties": {
    "addr:full":"219 Poplar Dr Clyde NC 28721",
    "addr:housenumber":"219",
    "addr:postcode":"28721",
    "addr:street":"Poplar Dr",
    "iso:country":"US",
    "sg:address":"219 Poplar Dr",
    "sg:city":"Clyde",
    "sg:classifiers":[
        {
            "category":"Banks & Credit Unions",
            "subcategory":"Financial Services",
            "type":"Services"
        }
    ],
    "sg:phone":"+1 828 627 6103",
    "sg:postcode":"28721",
    "sg:province":"NC",
    "sg:tags":[
        "investor"
    ],
    "wof:name":"L2 Investments Inc",
    "wof:placetype":"venue"
},
  "geometry": {"coordinates":[-82.943026,35.541753],"type":"Point"}
}