{
  "type": "Feature",
  "properties": {
    "addr:full":"3613 Antionette Ln Raleigh NC 27616",
    "addr:housenumber":"3613",
    "addr:postcode":"27616",
    "addr:street":"Antionette Ln",
    "iso:country":"US",
    "sg:address":"3613 Antionette Ln",
    "sg:city":"Raleigh",
    "sg:classifiers":[
        {
            "category":"Retail",
            "subcategory":"Repair Shop",
            "type":"Services"
        }
    ],
    "sg:phone":"+1 919 969 2997",
    "sg:postcode":"27616",
    "sg:province":"NC",
    "sg:tags":[
        "appliance"
    ],
    "wof:name":"D & C Home Appliance Svc",
    "wof:placetype":"venue"
},
  "geometry": {"coordinates":[-78.513364,35.866965],"type":"Point"}
}