{
  "type": "Feature",
  "properties": {
    "iso:country":"US",
    "sg:address":"4900 Shady Pine Dr",
    "sg:city":"Greensboro",
    "sg:classifiers":[
        {
            "category":"Health Services",
            "subcategory":"Hospital",
            "type":"Services"
        }
    ],
    "sg:phone":"+1 336 286 0025",
    "sg:postcode":"27455",
    "sg:province":"NC",
    "sg:tags":[
        "mental"
    ],
    "wof:name":"United Youth Care Svc",
    "wof:placetype":"venue"
},
  "geometry": {"coordinates":[-79.78483300000001,36.145576],"type":"Point"}
}