{
  "type": "Feature",
  "properties": {
    "addr:full":"118 N Green St Winston Salem NC 27101",
    "addr:housenumber":"118",
    "addr:postcode":"27101",
    "addr:street":"N Green St",
    "iso:country":"US",
    "sg:address":"118 N Green St",
    "sg:city":"Winston Salem",
    "sg:classifiers":[
        {
            "category":"Building & Trades",
            "subcategory":"Construction",
            "type":"Services"
        }
    ],
    "sg:phone":"+1 336 777 3441",
    "sg:postcode":"27101",
    "sg:province":"NC",
    "sg:tags":[
        "home",
        "general",
        "family",
        "contractor"
    ],
    "wof:name":"J H Johnson Construction",
    "wof:placetype":"venue"
},
  "geometry": {"coordinates":[-80.25397100000001,36.093742],"type":"Point"}
}