{
  "type": "Feature",
  "properties": {
    "iso:country":"US",
    "sg:address":"423 S South St",
    "sg:city":"Mt Airy",
    "sg:classifiers":[
        {
            "category":"Shopping",
            "type":"Retail Goods"
        },
        {
            "category":"Health Services",
            "subcategory":"Doctor",
            "type":"Services"
        }
    ],
    "sg:phone":"+1 336 786 7366",
    "sg:postcode":"27030",
    "sg:province":"NC",
    "sg:tags":[
        "physician",
        "medical",
        "surgeon",
        "merchandise"
    ],
    "sg:website":"www.piedmontent.com",
    "wof:name":"Piedmont Ear Nose Throat Assn",
    "wof:placetype":"venue"
},
  "geometry": {"coordinates":[-80.614328,36.495226],"type":"Point"}
}