{
  "type": "Feature",
  "properties": {
    "addr:full":"2310 State Hwy 801 Mocksville NC 27028",
    "addr:housenumber":"2310",
    "addr:postcode":"27028",
    "addr:street":"State Hwy 801",
    "iso:country":"US",
    "sg:address":"2310 State Hwy 801",
    "sg:city":"Mocksville",
    "sg:classifiers":[
        {
            "category":"Wholesale",
            "subcategory":"Machinery & Supplies",
            "type":"Manufacturing & Wholesale Goods"
        }
    ],
    "sg:phone":"+1 336 998 3232",
    "sg:postcode":"27028",
    "sg:province":"NC",
    "sg:tags":[
        "equipment",
        "irrigation",
        "system"
    ],
    "wof:name":"GRA-Mac Distr",
    "wof:placetype":"venue"
},
  "geometry": {"coordinates":[-80.531508,36.015792],"type":"Point"}
}