{
  "type": "Feature",
  "properties": {
    "iso:country":"US",
    "sg:address":"103 US Hwy 158",
    "sg:city":"Camden",
    "sg:classifiers":[
        {
            "category":"Wholesale",
            "subcategory":"Petroleum",
            "type":"Manufacturing & Wholesale Goods"
        }
    ],
    "sg:phone":"+1 252 335 9155",
    "sg:postcode":"27921",
    "sg:province":"NC",
    "sg:tags":[
        "fuel",
        "product",
        "oil",
        "retail"
    ],
    "wof:name":"Duck Thru",
    "wof:placetype":"venue"
},
  "geometry": {"coordinates":[-76.17188299999999,36.327834],"type":"Point"}
}