{
  "type": "Feature",
  "properties": {
    "iso:country":"US",
    "sg:address":"93 Bridlewood Pl NE",
    "sg:city":"Concord",
    "sg:classifiers":[
        {
            "category":"Building & Trades",
            "subcategory":"Construction",
            "type":"Services"
        }
    ],
    "sg:phone":"+1 704 786 9544",
    "sg:postcode":"28025",
    "sg:province":"NC",
    "wof:name":"Gregory Minor Haile",
    "wof:placetype":"venue"
},
  "geometry": {"coordinates":[-80.582859,35.456287],"type":"Point"}
}