{
  "type": "Feature",
  "properties": {
    "addr:full":"3004 Guess Rd Durham NC 27705",
    "addr:housenumber":"3004",
    "addr:postcode":"27705",
    "addr:street":"Guess Rd",
    "iso:country":"US",
    "sg:address":"3004 Guess Rd",
    "sg:city":"Durham",
    "sg:classifiers":[
        {
            "category":"Wholesale",
            "subcategory":"Medical Equipment & Supplies",
            "type":"Manufacturing & Wholesale Goods"
        },
        {
            "category":"Professional",
            "subcategory":"Business Services",
            "type":"Services"
        }
    ],
    "sg:phone":"+1 919 479 4840",
    "sg:postcode":"27705",
    "sg:province":"NC",
    "sg:tags":[
        "physician",
        "surgeon"
    ],
    "wof:name":"Rose Rich Group",
    "wof:placetype":"venue"
},
  "geometry": {"coordinates":[-78.928788,36.031847],"type":"Point"}
}