{
  "type": "Feature",
  "properties": {
    "addr:full":"421 Perth St Fayetteville NC 28314",
    "addr:housenumber":"421",
    "addr:postcode":"28314",
    "addr:street":"Perth St",
    "iso:country":"US",
    "sg:address":"421 Perth St",
    "sg:city":"Fayetteville",
    "sg:classifiers":[
        {
            "category":"Personal",
            "subcategory":"Adult",
            "type":"Services"
        }
    ],
    "sg:phone":"+1 910 826 7455",
    "sg:postcode":"28314",
    "sg:province":"NC",
    "sg:tags":[
        "escort"
    ],
    "wof:name":"Pure Silk",
    "wof:placetype":"venue"
},
  "geometry": {"coordinates":[-79.00633999999999,35.068587],"type":"Point"}
}