{
  "type": "Feature",
  "properties": {
    "addr:full":"709 9th St North Wilkesboro NC 28659",
    "addr:housenumber":"709",
    "addr:postcode":"28659",
    "addr:street":"9Th St",
    "iso:country":"US",
    "sg:address":"709 9th St",
    "sg:city":"North Wilkesboro",
    "sg:classifiers":[
        {
            "category":"Government",
            "subcategory":"Fire Station",
            "type":"Public Place"
        }
    ],
    "sg:phone":"+1 336 838 2552",
    "sg:postcode":"28659",
    "sg:province":"NC",
    "sg:tags":[
        "department",
        "protection"
    ],
    "wof:name":"North Wilkesboro Fire Dept",
    "wof:placetype":"venue"
},
  "geometry": {"coordinates":[-81.148797,36.163062],"type":"Point"}
}