{
  "type": "Feature",
  "properties": {
    "iso:country":"US",
    "sg:address":"2388 US Hwy 70",
    "sg:city":"Kinston",
    "sg:classifiers":[
        {
            "category":"Building & Trades",
            "subcategory":"Electrical",
            "type":"Services"
        }
    ],
    "sg:phone":"+1 252 523 5463",
    "sg:postcode":"28501",
    "sg:province":"NC",
    "sg:tags":[
        "electrical",
        "electric",
        "contractor"
    ],
    "wof:name":"Let's Electric",
    "wof:placetype":"venue"
},
  "geometry": {"coordinates":[-77.52338,35.221073],"type":"Point"}
}