{
  "type": "Feature",
  "properties": {
    "addr:full":"405 W Main St Havelock NC 28532",
    "addr:housenumber":"405",
    "addr:postcode":"28532",
    "addr:street":"W Main St",
    "iso:country":"US",
    "sg:address":"405 W Main St",
    "sg:city":"Havelock",
    "sg:classifiers":[
        {
            "category":"Restaurant",
            "type":"Food & Drink"
        }
    ],
    "sg:phone":"+1 252 444 1121",
    "sg:postcode":"28532",
    "sg:province":"NC",
    "sg:tags":[
        "eating"
    ],
    "wof:name":"LA Rosa Italian Restaurant",
    "wof:placetype":"venue"
},
  "geometry": {"coordinates":[-76.92035799999999,34.889221],"type":"Point"}
}