{
  "type": "Feature",
  "properties": {
    "iso:country":"US",
    "sg:address":"548 Winfield Blvd SE",
    "sg:city":"Concord",
    "sg:classifiers":[
        {
            "category":"Building & Trades",
            "subcategory":"Construction",
            "type":"Services"
        }
    ],
    "sg:phone":"+1 704 721 5709",
    "sg:postcode":"28025",
    "sg:province":"NC",
    "sg:tags":[
        "house"
    ],
    "wof:name":"Gulledge Classic Homes Inc",
    "wof:placetype":"venue"
},
  "geometry": {"coordinates":[-80.562353,35.400745],"type":"Point"}
}