{
  "type": "Feature",
  "properties": {
    "iso:country":"US",
    "sg:address":"2904 Hackney Way",
    "sg:city":"Jamestown",
    "sg:classifiers":[
        {
            "category":"Real Estate",
            "subcategory":"Real Estate Agent",
            "type":"Services"
        }
    ],
    "sg:phone":"+1 336 218 1140",
    "sg:postcode":"27282",
    "sg:province":"NC",
    "wof:name":"CB Commerical Koll Managment",
    "wof:placetype":"venue"
},
  "geometry": {"coordinates":[-79.933976,36.03282],"type":"Point"}
}