{
  "type": "Feature",
  "properties": {
    "addr:full":"6053 Martins Point Rd Kitty Hawk NC 27949",
    "addr:housenumber":"6053",
    "addr:postcode":"27949",
    "addr:street":"Martins Point Rd",
    "iso:country":"US",
    "sg:address":"6053 Martins Point Rd",
    "sg:city":"Kitty Hawk",
    "sg:classifiers":[
        {
            "category":"Building & Trades",
            "subcategory":"Construction",
            "type":"Services"
        }
    ],
    "sg:phone":"+1 252 261 0164",
    "sg:postcode":"27949",
    "sg:province":"NC",
    "sg:tags":[
        "residential",
        "commercial",
        "light"
    ],
    "wof:name":"Fishin Frenzy",
    "wof:placetype":"venue"
},
  "geometry": {"coordinates":[-75.746938,36.11567],"type":"Point"}
}