{
  "type": "Feature",
  "properties": {
    "addr:full":"121 Bayleaf Dr Raleigh NC 27615",
    "addr:housenumber":"121",
    "addr:postcode":"27615",
    "addr:street":"Bayleaf Dr",
    "iso:country":"US",
    "sg:address":"121 Bayleaf Dr",
    "sg:city":"Raleigh",
    "sg:classifiers":[
        {
            "category":"Shopping",
            "subcategory":"Books",
            "type":"Retail Goods"
        }
    ],
    "sg:phone":"+1 919 870 1749",
    "sg:postcode":"27615",
    "sg:province":"NC",
    "sg:tags":[
        "gift"
    ],
    "wof:name":"Books Are Fun",
    "wof:placetype":"venue"
},
  "geometry": {"coordinates":[-78.64260899999999,35.918491],"type":"Point"}
}