{
  "type": "Feature",
  "properties": {
    "iso:country":"US",
    "sg:address":"1636 N Church St",
    "sg:city":"Burlington",
    "sg:classifiers":[
        {
            "category":"Social Services",
            "type":"Services"
        }
    ],
    "sg:phone":"+1   ",
    "sg:postcode":"27217",
    "sg:province":"NC",
    "wof:name":"Alamance Pregnancy Services",
    "wof:placetype":"venue"
},
  "geometry": {"coordinates":[-79.4101,36.096277],"type":"Point"}
}