{
  "type": "Feature",
  "properties": {
    "iso:country":"US",
    "sg:address":"3501 Oleander Dr",
    "sg:city":"Wilmington",
    "sg:classifiers":[
        {
            "category":"Shopping",
            "subcategory":"Pharmacy",
            "type":"Retail Goods"
        }
    ],
    "sg:phone":"+1 910 763 3367",
    "sg:postcode":"28403",
    "sg:province":"NC",
    "sg:tags":[
        "drug",
        "store"
    ],
    "wof:name":"Eckerd",
    "wof:placetype":"venue"
},
  "geometry": {"coordinates":[-77.90497499999999,34.216607],"type":"Point"}
}