{
  "type": "Feature",
  "properties": {
    "addr:full":"1609 Temple St SW Valdese NC 28690",
    "addr:housenumber":"1609",
    "addr:postcode":"28690",
    "addr:street":"Temple St Sw",
    "iso:country":"US",
    "sg:address":"1609 Temple St SW",
    "sg:city":"Valdese",
    "sg:classifiers":[
        {
            "category":"Farming",
            "subcategory":"Nursery",
            "type":"Manufacturing & Wholesale Goods"
        }
    ],
    "sg:phone":"+1 828 433 7780",
    "sg:postcode":"28690",
    "sg:province":"NC",
    "sg:tags":[
        "greenhouse"
    ],
    "wof:name":"Rain House",
    "wof:placetype":"venue"
},
  "geometry": {"coordinates":[-81.56905999999999,35.733675],"type":"Point"}
}