{
  "type": "Feature",
  "properties": {
    "addr:full":"711 E Cherry St Salisbury NC 28144",
    "addr:housenumber":"711",
    "addr:postcode":"28144",
    "addr:street":"E Cherry St",
    "iso:country":"US",
    "sg:address":"711 E Cherry St",
    "sg:city":"Salisbury",
    "sg:classifiers":[
        {
            "category":"Professional",
            "type":"Services"
        }
    ],
    "sg:phone":"+1 704 622 0972",
    "sg:postcode":"28144",
    "sg:province":"NC",
    "wof:name":"New Beginnings Community Chris",
    "wof:placetype":"venue"
},
  "geometry": {"coordinates":[-80.47381,35.657041],"type":"Point"}
}