{
  "type": "Feature",
  "properties": {
    "iso:country":"US",
    "sg:address":"10009 Plum Creek Ln Apt B",
    "sg:city":"Charlotte",
    "sg:classifiers":[
        {
            "category":"Shopping",
            "subcategory":"Department Store",
            "type":"Retail Goods"
        }
    ],
    "sg:phone":"+1 704 661 5635",
    "sg:postcode":"28210",
    "sg:province":"NC",
    "wof:name":"Carolina Belk Place Mall",
    "wof:placetype":"venue"
},
  "geometry": {"coordinates":[-80.86138,35.095182],"type":"Point"}
}