{
  "type": "Feature",
  "properties": {
    "addr:full":"711 S Memorial Dr Greenville NC 27834",
    "addr:housenumber":"711",
    "addr:postcode":"27834",
    "addr:street":"S Memorial Dr",
    "iso:country":"US",
    "sg:address":"711 S Memorial Dr",
    "sg:city":"Greenville",
    "sg:classifiers":[
        {
            "category":"Restaurant",
            "type":"Food & Drink"
        }
    ],
    "sg:phone":"+1 252 757 3046",
    "sg:postcode":"27834",
    "sg:province":"NC",
    "sg:tags":[
        "eating"
    ],
    "wof:name":"BJs Chicken-Bbq-Seafood",
    "wof:placetype":"venue"
},
  "geometry": {"coordinates":[-77.394785,35.607903],"type":"Point"}
}