{
  "type": "Feature",
  "properties": {
    "addr:full":"3716 High Point Rd Greensboro NC 27407",
    "addr:housenumber":"3716",
    "addr:postcode":"27407",
    "addr:street":"High Point Rd",
    "iso:country":"US",
    "sg:address":"3716 High Point Rd",
    "sg:city":"Greensboro",
    "sg:classifiers":[
        {
            "category":"Autos & Motor Vehicles",
            "subcategory":"Auto Supplies",
            "type":"Retail Goods"
        }
    ],
    "sg:phone":"+1 336 547 9039",
    "sg:postcode":"27407",
    "sg:province":"NC",
    "sg:tags":[
        "customer",
        "wheel",
        "retailer"
    ],
    "wof:name":"G P Tire & Wheel",
    "wof:placetype":"venue"
},
  "geometry": {"coordinates":[-79.85443100000001,36.038636],"type":"Point"}
}