{
  "type": "Feature",
  "properties": {
    "addr:full":"401 Hawthorne Ln 110-189 Charlotte NC 28204",
    "addr:housenumber":"401;110-189",
    "addr:postcode":"28204",
    "addr:street":"Hawthorne Ln",
    "iso:country":"US",
    "sg:address":"401 Hawthorne Ln 110-189",
    "sg:city":"Charlotte",
    "sg:classifiers":[
        {
            "category":"Shopping",
            "subcategory":"Bicycles & Sporting Goods",
            "type":"Retail Goods"
        }
    ],
    "sg:phone":"+1 704 819 1755",
    "sg:postcode":"28204",
    "sg:province":"NC",
    "sg:tags":[
        "equipment",
        "golf",
        "supply"
    ],
    "wof:name":"Corporate Golf Enterprises",
    "wof:placetype":"venue"
},
  "geometry": {"coordinates":[-80.822113,35.215778],"type":"Point"}
}