{
  "type": "Feature",
  "properties": {
    "addr:full":"612 Vallie Ln Wilmington NC 28412",
    "addr:housenumber":"612",
    "addr:postcode":"28412",
    "addr:street":"Vallie Ln",
    "iso:country":"US",
    "sg:address":"612 Vallie Ln",
    "sg:city":"Wilmington",
    "sg:classifiers":[
        {
            "category":"Retail",
            "subcategory":"Animal Services",
            "type":"Services"
        }
    ],
    "sg:phone":"+1 910 793 5550",
    "sg:postcode":"28412",
    "sg:province":"NC",
    "sg:tags":[
        "farm",
        "equine"
    ],
    "wof:name":"Circle K Tack & Feed",
    "wof:placetype":"venue"
},
  "geometry": {"coordinates":[-77.89714499999999,34.133849],"type":"Point"}
}