{
  "type": "Feature",
  "properties": {
    "addr:full":"10404 E Independence Blvd Matthews NC 28105",
    "addr:housenumber":"10404",
    "addr:postcode":"28105",
    "addr:street":"E Independence Blvd",
    "iso:country":"US",
    "sg:address":"10404 E Independence Blvd",
    "sg:city":"Matthews",
    "sg:classifiers":[
        {
            "category":"Recreation",
            "type":"Entertainment"
        }
    ],
    "sg:phone":"+1 704 841 7555",
    "sg:postcode":"28105",
    "sg:province":"NC",
    "sg:tags":[
        "martial",
        "arts",
        "instruction"
    ],
    "wof:name":"Taekwondo",
    "wof:placetype":"venue"
},
  "geometry": {"coordinates":[-80.706718,35.126958],"type":"Point"}
}