{
  "type": "Feature",
  "properties": {
    "iso:country":"US",
    "sg:address":"1806 W Innes St",
    "sg:city":"Salisbury",
    "sg:classifiers":[
        {
            "category":"Shopping",
            "subcategory":"Stationery & Office Supplies",
            "type":"Retail Goods"
        }
    ],
    "sg:phone":"+1 704 633 6095",
    "sg:postcode":"28144",
    "sg:province":"NC",
    "sg:tags":[
        "book"
    ],
    "wof:name":"Bookmaster",
    "wof:placetype":"venue"
},
  "geometry": {"coordinates":[-80.483234,35.686296],"type":"Point"}
}