{
  "type": "Feature",
  "properties": {
    "iso:country":"US",
    "sg:address":"2575 State Hwy 105",
    "sg:city":"Boone",
    "sg:classifiers":[
        {
            "category":"Restaurant",
            "type":"Food & Drink"
        }
    ],
    "sg:phone":"+1 828 265 2222",
    "sg:postcode":"28607",
    "sg:province":"NC",
    "sg:tags":[
        "shop",
        "coffee"
    ],
    "wof:name":"Conrad's Coffee Co",
    "wof:placetype":"venue"
},
  "geometry": {"coordinates":[-81.693611,36.204946],"type":"Point"}
}