{
  "type": "Feature",
  "properties": {
    "iso:country":"US",
    "sg:address":"8 Hillview Cir",
    "sg:city":"Asheville",
    "sg:classifiers":[
        {
            "category":"Professional",
            "subcategory":"Business Services",
            "type":"Services"
        }
    ],
    "sg:phone":"+1   ",
    "sg:postcode":"28805",
    "sg:province":"NC",
    "wof:name":"Rock For Life of Asheville",
    "wof:placetype":"venue"
},
  "geometry": {"coordinates":[-82.507597,35.610951],"type":"Point"}
}