{
  "type": "Feature",
  "properties": {
    "iso:country":"US",
    "sg:address":"2605 State Hwy 130",
    "sg:city":"Rowland",
    "sg:classifiers":[
        {
            "category":"Food & Beverages",
            "subcategory":"Groceries & Convenience Stores",
            "type":"Retail Goods"
        }
    ],
    "sg:phone":"+1 910 422 0032",
    "sg:postcode":"28383",
    "sg:province":"NC",
    "wof:name":"KWIK Stop",
    "wof:placetype":"venue"
},
  "geometry": {"coordinates":[-79.31540699999999,34.568744],"type":"Point"}
}