{
  "type": "Feature",
  "properties": {
    "iso:country":"US",
    "sg:address":"2606 Phoenix Dr",
    "sg:city":"Greensboro",
    "sg:classifiers":[
        {
            "category":"Wholesale",
            "subcategory":"Vending Machines",
            "type":"Manufacturing & Wholesale Goods"
        },
        {
            "category":"Building & Trades",
            "subcategory":"Equipment Rental",
            "type":"Services"
        }
    ],
    "sg:phone":"+1 336 851 0090",
    "sg:postcode":"27406",
    "sg:province":"NC",
    "wof:name":"C & G Products Inc",
    "wof:placetype":"venue"
},
  "geometry": {"coordinates":[-79.833428,36.010905],"type":"Point"}
}