{
  "type": "Feature",
  "properties": {
    "iso:country":"US",
    "sg:address":"912 Shady Retreat Ln",
    "sg:city":"Iron Station",
    "sg:classifiers":[
        {
            "category":"Organizations",
            "subcategory":"Religious Organization",
            "type":"Services"
        }
    ],
    "sg:phone":"+1 704 735 2261",
    "sg:postcode":"28080",
    "sg:province":"NC",
    "sg:tags":[
        "church"
    ],
    "wof:name":"Manantial Devida Church God",
    "wof:placetype":"venue"
},
  "geometry": {"coordinates":[-81.173885,35.454411],"type":"Point"}
}