{
  "type": "Feature",
  "properties": {
    "addr:full":"2608 Crest St Durham NC 27705",
    "addr:housenumber":"2608",
    "addr:postcode":"27705",
    "addr:street":"Crest St",
    "iso:country":"US",
    "sg:address":"2608 Crest St",
    "sg:city":"Durham",
    "sg:classifiers":[
        {
            "category":"Professional",
            "type":"Services"
        }
    ],
    "sg:phone":"+1   ",
    "sg:postcode":"27705",
    "sg:province":"NC",
    "wof:name":"Superb Home Care Services",
    "wof:placetype":"venue"
},
  "geometry": {"coordinates":[-78.939734,36.012826],"type":"Point"}
}