{
  "type": "Feature",
  "properties": {
    "iso:country":"US",
    "sg:address":"2417 Neuse Blvd",
    "sg:city":"New Bern",
    "sg:classifiers":[
        {
            "category":"Health Services",
            "subcategory":"Doctor",
            "type":"Services"
        }
    ],
    "sg:phone":"+1   ",
    "sg:postcode":"28562",
    "sg:province":"NC",
    "sg:tags":[
        "medical"
    ],
    "wof:name":"Allergy Asthma Clinic New Bern",
    "wof:placetype":"venue"
},
  "geometry": {"coordinates":[-77.07602799999999,35.11718],"type":"Point"}
}