{
  "type": "Feature",
  "properties": {
    "addr:full":"2635 Alderney Ln SW Winston Salem NC 27103",
    "addr:housenumber":"2635",
    "addr:postcode":"27103",
    "addr:street":"Alderney Ln Sw",
    "iso:country":"US",
    "sg:address":"2635 Alderney Ln SW",
    "sg:city":"Winston Salem",
    "sg:classifiers":[
        {
            "category":"Retail",
            "subcategory":"Portrait Studio",
            "type":"Services"
        }
    ],
    "sg:phone":"+1   ",
    "sg:postcode":"27103",
    "sg:province":"NC",
    "sg:tags":[
        "photo"
    ],
    "wof:name":"Photography By Carole",
    "wof:placetype":"venue"
},
  "geometry": {"coordinates":[-80.288954,36.065608],"type":"Point"}
}