{
  "type": "Feature",
  "properties": {
    "iso:country":"US",
    "sg:address":"600 Ardsley Rd",
    "sg:city":"Charlotte",
    "sg:classifiers":[
        {
            "category":"Organizations",
            "subcategory":"Membership Organization",
            "type":"Services"
        }
    ],
    "sg:phone":"+1 704 375 4400",
    "sg:postcode":"28207",
    "sg:province":"NC",
    "sg:website":"www.lynnwoodfoundation.com",
    "wof:name":"Lynnwood Foundation",
    "wof:placetype":"venue"
},
  "geometry": {"coordinates":[-80.82651199999999,35.201347],"type":"Point"}
}