{
  "type": "Feature",
  "properties": {
    "iso:country":"US",
    "sg:address":"3140 State Rd 16",
    "sg:city":"Denver",
    "sg:classifiers":[
        {
            "category":"Building & Trades",
            "subcategory":"Electrical",
            "type":"Services"
        }
    ],
    "sg:phone":"+1 704 489 1119",
    "sg:postcode":"28037",
    "sg:province":"NC",
    "sg:tags":[
        "electrical",
        "contractor"
    ],
    "wof:name":"Todays Audio Video Inc",
    "wof:placetype":"venue"
},
  "geometry": {"coordinates":[-81.011859,35.52308],"type":"Point"}
}