{
  "type": "Feature",
  "properties": {
    "iso:country":"US",
    "sg:address":"7210 Beach Dr SW",
    "sg:city":"Ocean Isle Beach",
    "sg:classifiers":[
        {
            "category":"Food & Beverages",
            "subcategory":"Bakery",
            "type":"Retail Goods"
        }
    ],
    "sg:phone":"+1 910 579 9866",
    "sg:postcode":"28469",
    "sg:province":"NC",
    "sg:tags":[
        "baker"
    ],
    "wof:name":"Taste Of Heaven Dessert Bakery",
    "wof:placetype":"venue"
},
  "geometry": {"coordinates":[-78.476951,33.898516],"type":"Point"}
}