{
  "type": "Feature",
  "properties": {
    "addr:full":"822 Odell-Arcola Rd Littleton NC 27850",
    "addr:housenumber":"822",
    "addr:postcode":"27850",
    "addr:street":"Odell-Arcola Rd",
    "iso:country":"US",
    "sg:address":"822 Odell-Arcola Rd",
    "sg:city":"Littleton",
    "sg:classifiers":[
        {
            "category":"Building & Trades",
            "subcategory":"Construction",
            "type":"Services"
        }
    ],
    "sg:phone":"+1 252 586 6141",
    "sg:postcode":"27850",
    "sg:province":"NC",
    "sg:tags":[
        "masonry",
        "contractor"
    ],
    "wof:name":"P & R Masonry",
    "wof:placetype":"venue"
},
  "geometry": {"coordinates":[-77.948319,36.324146],"type":"Point"}
}