{
  "type": "Feature",
  "properties": {
    "iso:country":"US",
    "sg:address":"165 Newman Ln",
    "sg:city":"Iron Station",
    "sg:classifiers":[
        {
            "category":"Professional",
            "subcategory":"Advertising",
            "type":"Services"
        }
    ],
    "sg:phone":"+1   ",
    "sg:postcode":"28080",
    "sg:province":"NC",
    "sg:tags":[
        "outdoor"
    ],
    "wof:name":"Charles E Newman",
    "wof:placetype":"venue"
},
  "geometry": {"coordinates":[-81.08017,35.459417],"type":"Point"}
}