{
  "type": "Feature",
  "properties": {
    "addr:full":"1410 Skyway Dr Ste B Monroe NC 28110",
    "addr:housenumber":"1410",
    "addr:postcode":"28110",
    "addr:street":"Skyway Dr Ste B",
    "iso:country":"US",
    "sg:address":"1410 Skyway Dr Ste B",
    "sg:city":"Monroe",
    "sg:classifiers":[
        {
            "category":"Retail",
            "subcategory":"Animal Services",
            "type":"Services"
        }
    ],
    "sg:phone":"+1 704 225 8390",
    "sg:postcode":"28110",
    "sg:province":"NC",
    "sg:tags":[
        "pet",
        "grooming"
    ],
    "wof:name":"Animal Trax Inc.",
    "wof:placetype":"venue"
},
  "geometry": {"coordinates":[-80.548861,34.995417],"type":"Point"}
}