{
  "type": "Feature",
  "properties": {
    "addr:full":"2815 Caraway Ln Winston Salem NC 27103",
    "addr:housenumber":"2815",
    "addr:postcode":"27103",
    "addr:street":"Caraway Ln",
    "iso:country":"US",
    "sg:address":"2815 Caraway Ln",
    "sg:city":"Winston Salem",
    "sg:classifiers":[
        {
            "category":"Freight",
            "type":"Transportation"
        }
    ],
    "sg:phone":"+1 336 794 0046",
    "sg:postcode":"27103",
    "sg:province":"NC",
    "sg:tags":[
        "trucking"
    ],
    "wof:name":"Carl A Cash Trucking Co Inc",
    "wof:placetype":"venue"
},
  "geometry": {"coordinates":[-80.341785,36.042235],"type":"Point"}
}