{
  "type": "Feature",
  "properties": {
    "iso:country":"US",
    "sg:address":"100 Davis Rd",
    "sg:city":"Mt Olive",
    "sg:classifiers":[
        {
            "category":"Real Estate",
            "subcategory":"Real Estate Operator",
            "type":"Services"
        }
    ],
    "sg:phone":"+1 919 658 5842",
    "sg:postcode":"28365",
    "sg:province":"NC",
    "sg:tags":[
        "building",
        "apartment"
    ],
    "wof:name":"Mount Olive Village Apartments",
    "wof:placetype":"venue"
},
  "geometry": {"coordinates":[-78.06006499999999,35.214132],"type":"Point"}
}