{
  "type": "Feature",
  "properties": {
    "iso:country":"US",
    "sg:address":"317 W Main St",
    "sg:city":"Spindale",
    "sg:classifiers":[
        {
            "category":"Manufacturing",
            "subcategory":"Printing",
            "type":"Manufacturing & Wholesale Goods"
        }
    ],
    "sg:phone":"+1 828 287 8870",
    "sg:postcode":"28160",
    "sg:province":"NC",
    "sg:tags":[
        "commercial"
    ],
    "wof:name":"Artcrafters Screen Printing",
    "wof:placetype":"venue"
},
  "geometry": {"coordinates":[-81.933567,35.358365],"type":"Point"}
}