{
  "type": "Feature",
  "properties": {
    "iso:country":"US",
    "sg:address":"2112 W Vandalia Rd",
    "sg:city":"Greensboro",
    "sg:classifiers":[
        {
            "category":"Social Services",
            "type":"Services"
        }
    ],
    "sg:phone":"+1 336 299 5884",
    "sg:postcode":"27407",
    "sg:province":"NC",
    "wof:name":"John W Mitchell",
    "wof:placetype":"venue"
},
  "geometry": {"coordinates":[-79.846014,36.020272],"type":"Point"}
}