{
  "type": "Feature",
  "properties": {
    "iso:country":"US",
    "sg:address":"3101 E Independence Blvd",
    "sg:city":"Charlotte",
    "sg:classifiers":[
        {
            "category":"Restaurant",
            "type":"Food & Drink"
        }
    ],
    "sg:menulink":"http://www.allmenus.com/nc/charlotte/39235-south-21-curb-service/menu/",
    "sg:phone":"+1 704 377 4509",
    "sg:postcode":"28205",
    "sg:province":"NC",
    "sg:tags":[
        "american"
    ],
    "wof:name":"South 21 Curb Service",
    "wof:placetype":"venue"
},
  "geometry": {"coordinates":[-80.79196399999999,35.203789],"type":"Point"}
}