{
  "type": "Feature",
  "properties": {
    "addr:full":"8774 Harlow Rd Archdale NC 27263",
    "addr:housenumber":"8774",
    "addr:postcode":"27263",
    "addr:street":"Harlow Rd",
    "iso:country":"US",
    "sg:address":"8774 Harlow Rd",
    "sg:city":"Archdale",
    "sg:classifiers":[
        {
            "category":"Retail",
            "subcategory":"Auto Repair",
            "type":"Services"
        }
    ],
    "sg:phone":"+1 336 431 8700",
    "sg:postcode":"27263",
    "sg:province":"NC",
    "sg:tags":[
        "body",
        "automobile",
        "painting"
    ],
    "wof:name":"Blue Ribbon Body Shop",
    "wof:placetype":"venue"
},
  "geometry": {"coordinates":[-79.888274,35.906984],"type":"Point"}
}