{
  "type": "Feature",
  "properties": {
    "addr:full":"2729 Bartram Rd Winston Salem NC 27106",
    "addr:housenumber":"2729",
    "addr:postcode":"27106",
    "addr:street":"Bartram Rd",
    "iso:country":"US",
    "sg:address":"2729 Bartram Rd",
    "sg:city":"Winston Salem",
    "sg:classifiers":[
        {
            "category":"Professional",
            "subcategory":"Business Services",
            "type":"Services"
        }
    ],
    "sg:phone":"+1   ",
    "sg:postcode":"27106",
    "sg:province":"NC",
    "wof:name":"Whitaker Design",
    "wof:placetype":"venue"
},
  "geometry": {"coordinates":[-80.275176,36.122016],"type":"Point"}
}