{
  "type": "Feature",
  "properties": {
    "iso:country":"US",
    "sg:address":"3600 Fayetteville Rd",
    "sg:city":"Durham",
    "sg:classifiers":[
        {
            "category":"Real Estate",
            "subcategory":"Developer",
            "type":"Services"
        }
    ],
    "sg:phone":"+1 919 560 4154",
    "sg:postcode":"27707",
    "sg:province":"NC",
    "sg:tags":[
        "cemetery"
    ],
    "wof:name":"Beechwood Cemetery",
    "wof:placetype":"venue"
},
  "geometry": {"coordinates":[-78.90534599999999,35.952627],"type":"Point"}
}