{
  "type": "Feature",
  "properties": {
    "iso:country":"US",
    "sg:address":"1311 Wakefield Pl",
    "sg:city":"Greensboro",
    "sg:classifiers":[
        {
            "category":"Wholesale",
            "subcategory":"Groceries",
            "type":"Manufacturing & Wholesale Goods"
        }
    ],
    "sg:phone":"+1 336 323 0909",
    "sg:postcode":"27410",
    "sg:province":"NC",
    "wof:name":"Blue Mountain Coffee Inc",
    "wof:placetype":"venue"
},
  "geometry": {"coordinates":[-79.904922,36.1007],"type":"Point"}
}