{
  "type": "Feature",
  "properties": {
    "iso:country":"US",
    "sg:address":"6816 Morrison Blvd",
    "sg:city":"Charlotte",
    "sg:classifiers":[
        {
            "category":"Professional",
            "subcategory":"Management & Consulting",
            "type":"Services"
        }
    ],
    "sg:phone":"+1 704 362 5202",
    "sg:postcode":"28211",
    "sg:province":"NC",
    "sg:tags":[
        "consultant",
        "business"
    ],
    "wof:name":"Taylor Group",
    "wof:placetype":"venue"
},
  "geometry": {"coordinates":[-80.825931,35.151734],"type":"Point"}
}