{
  "type": "Feature",
  "properties": {
    "addr:full":"53 Kinglet Cir Greensboro NC 27455",
    "addr:housenumber":"53",
    "addr:postcode":"27455",
    "addr:street":"Kinglet Cir",
    "iso:country":"US",
    "sg:address":"53 Kinglet Cir",
    "sg:city":"Greensboro",
    "sg:classifiers":[
        {
            "category":"Wholesale",
            "subcategory":"Plants",
            "type":"Manufacturing & Wholesale Goods"
        }
    ],
    "sg:phone":"+1 336 282 1274",
    "sg:postcode":"27455",
    "sg:province":"NC",
    "sg:tags":[
        "nursery",
        "tree"
    ],
    "wof:name":"Rock Ridge Nursery Inc",
    "wof:placetype":"venue"
},
  "geometry": {"coordinates":[-79.799511,36.149188],"type":"Point"}
}