{
  "type": "Feature",
  "properties": {
    "addr:full":"7336 Connan Ln Charlotte NC 28226",
    "addr:housenumber":"7336",
    "addr:postcode":"28226",
    "addr:street":"Connan Ln",
    "iso:country":"US",
    "sg:address":"7336 Connan Ln",
    "sg:city":"Charlotte",
    "sg:classifiers":[
        {
            "category":"Professional",
            "subcategory":"Advertising",
            "type":"Services"
        }
    ],
    "sg:phone":"+1   ",
    "sg:postcode":"28226",
    "sg:province":"NC",
    "wof:name":"Extremechefscom",
    "wof:placetype":"venue"
},
  "geometry": {"coordinates":[-80.840604,35.092199],"type":"Point"}
}