{
  "type": "Feature",
  "properties": {
    "iso:country":"US",
    "sg:address":"835 Armstrong Park Rd",
    "sg:city":"Gastonia",
    "sg:classifiers":[
        {
            "category":"Real Estate",
            "subcategory":"Real Estate Operator",
            "type":"Services"
        }
    ],
    "sg:phone":"+1 704 866 0275",
    "sg:postcode":"28054",
    "sg:province":"NC",
    "sg:tags":[
        "apartment"
    ],
    "wof:name":"Azalea Apartments",
    "wof:placetype":"venue"
},
  "geometry": {"coordinates":[-81.135671,35.24731],"type":"Point"}
}