{
  "type": "Feature",
  "properties": {
    "iso:country":"US",
    "sg:address":"5600 Executive Center Dr",
    "sg:city":"Charlotte",
    "sg:classifiers":[
        {
            "category":"Professional",
            "subcategory":"Accounting & Tax Preparation",
            "type":"Services"
        }
    ],
    "sg:phone":"+1 704 566 6399",
    "sg:postcode":"28212",
    "sg:province":"NC",
    "sg:tags":[
        "bookkeeping",
        "general"
    ],
    "wof:name":"Lechleider Tax & Accounting",
    "wof:placetype":"venue"
},
  "geometry": {"coordinates":[-80.74403700000001,35.200568],"type":"Point"}
}