{
  "type": "Feature",
  "properties": {
    "iso:country":"US",
    "sg:address":"401 Mocksville Ave",
    "sg:city":"Salisbury",
    "sg:classifiers":[
        {
            "category":"Health Services",
            "subcategory":"Doctor",
            "type":"Services"
        }
    ],
    "sg:phone":"+1 704 647 9913",
    "sg:postcode":"28144",
    "sg:province":"NC",
    "sg:tags":[
        "clinic"
    ],
    "wof:name":"Crescent Medical Research",
    "wof:placetype":"venue"
},
  "geometry": {"coordinates":[-80.471503,35.68046],"type":"Point"}
}