{
  "type": "Feature",
  "properties": {
    "iso:country":"US",
    "sg:address":"3877 Hendersonville Rd",
    "sg:city":"Fletcher",
    "sg:classifiers":[
        {
            "category":"Shopping",
            "subcategory":"Used Merchandise",
            "type":"Retail Goods"
        }
    ],
    "sg:phone":"+1 828 684 7906",
    "sg:postcode":"28732",
    "sg:province":"NC",
    "sg:tags":[
        "book",
        "rare",
        "dealer"
    ],
    "wof:name":"Jenny's Book Exchange",
    "wof:placetype":"venue"
},
  "geometry": {"coordinates":[-82.50149999999999,35.428689],"type":"Point"}
}