{
  "type": "Feature",
  "properties": {
    "addr:full":"728 S Fayetteville St Asheboro NC 27203",
    "addr:housenumber":"728",
    "addr:postcode":"27203",
    "addr:street":"S Fayetteville St",
    "iso:country":"US",
    "sg:address":"728 S Fayetteville St",
    "sg:city":"Asheboro",
    "sg:classifiers":[
        {
            "category":"Manufacturing",
            "subcategory":"Furniture",
            "type":"Manufacturing & Wholesale Goods"
        }
    ],
    "sg:phone":"+1 336 625 0195",
    "sg:postcode":"27203",
    "sg:province":"NC",
    "sg:website":"www.chairsmfg.com",
    "wof:name":"Chairs Manufacturing Co Inc",
    "wof:placetype":"venue"
},
  "geometry": {"coordinates":[-79.815102,35.698237],"type":"Point"}
}