{
  "type": "Feature",
  "properties": {
    "iso:country":"US",
    "sg:address":"714 N Norwood St",
    "sg:city":"Wallace",
    "sg:classifiers":[
        {
            "category":"Personal",
            "subcategory":"Beauty Salon",
            "type":"Services"
        }
    ],
    "sg:phone":"+1 910 285 8335",
    "sg:postcode":"28466",
    "sg:province":"NC",
    "sg:tags":[
        "manicuring"
    ],
    "wof:name":"Le Nails",
    "wof:placetype":"venue"
},
  "geometry": {"coordinates":[-77.99560700000001,34.743235],"type":"Point"}
}