{
  "type": "Feature",
  "properties": {
    "iso:country":"US",
    "sg:address":"1527 Bairds Creek Rd",
    "sg:city":"Vilas",
    "sg:classifiers":[
        {
            "category":"Building & Trades",
            "subcategory":"Construction",
            "type":"Services"
        }
    ],
    "sg:phone":"+1 828 963 7292",
    "sg:postcode":"28692",
    "sg:province":"NC",
    "sg:tags":[
        "home",
        "builder"
    ],
    "wof:name":"High South Builders",
    "wof:placetype":"venue"
},
  "geometry": {"coordinates":[-81.763761,36.219476],"type":"Point"}
}