{
  "type": "Feature",
  "properties": {
    "addr:full":"1833 Anthony Rd Burlington NC 27215",
    "addr:housenumber":"1833",
    "addr:postcode":"27215",
    "addr:street":"Anthony Rd",
    "iso:country":"US",
    "sg:address":"1833 Anthony Rd",
    "sg:city":"Burlington",
    "sg:classifiers":[
        {
            "category":"Building & Trades",
            "subcategory":"Plumbing",
            "type":"Services"
        }
    ],
    "sg:phone":"+1 336 227 5222",
    "sg:postcode":"27215",
    "sg:province":"NC",
    "sg:tags":[
        "conditioning",
        "air",
        "system",
        "contractor"
    ],
    "wof:name":"Comfort Consultants Of Nc",
    "wof:placetype":"venue"
},
  "geometry": {"coordinates":[-79.453372,36.049302],"type":"Point"}
}