{
  "type": "Feature",
  "properties": {
    "addr:full":"1819 Madison Ave Greensboro NC 27403",
    "addr:housenumber":"1819",
    "addr:postcode":"27403",
    "addr:street":"Madison Ave",
    "iso:country":"US",
    "sg:address":"1819 Madison Ave",
    "sg:city":"Greensboro",
    "sg:classifiers":[
        {
            "category":"Health Services",
            "subcategory":"Health Practitioner",
            "type":"Services"
        }
    ],
    "sg:phone":"+1   ",
    "sg:postcode":"27403",
    "sg:province":"NC",
    "wof:name":"E Elaine Talbert PHD",
    "wof:placetype":"venue"
},
  "geometry": {"coordinates":[-79.82037,36.075149],"type":"Point"}
}