{
  "type": "Feature",
  "properties": {
    "addr:full":"2930 Randleman Rd Greensboro NC 27406",
    "addr:postcode":"2930;27406",
    "addr:street":"Randleman Rd",
    "iso:country":"US",
    "sg:address":"2930 Randleman Rd",
    "sg:city":"Greensboro",
    "sg:classifiers":[
        {
            "category":"Restaurant",
            "type":"Food & Drink"
        }
    ],
    "sg:menulink":"http://www.allmenus.com/nc/greensboro/281823-romos-pizza-and-subs/menu/",
    "sg:phone":"+1 336 275 7303",
    "sg:postcode":"27406",
    "sg:province":"NC",
    "sg:tags":[
        "american",
        "sandwich",
        "pizza"
    ],
    "wof:name":"Romo's Pizza and Subs",
    "wof:placetype":"venue"
},
  "geometry": {"coordinates":[-79.80431900000001,36.01623],"type":"Point"}
}