{
  "type": "Feature",
  "properties": {
    "addr:full":"120 James St Laurinburg NC 28352",
    "addr:housenumber":"120",
    "addr:postcode":"28352",
    "addr:street":"James St",
    "iso:country":"US",
    "sg:address":"120 James St",
    "sg:city":"Laurinburg",
    "sg:classifiers":[
        {
            "category":"Education",
            "subcategory":"Dance Studio",
            "type":"Public Place"
        }
    ],
    "sg:phone":"+1   ",
    "sg:postcode":"28352",
    "sg:province":"NC",
    "wof:name":"Karen Gibson School Of Dance",
    "wof:placetype":"venue"
},
  "geometry": {"coordinates":[-79.458794,34.775243],"type":"Point"}
}