{
  "type": "Feature",
  "properties": {
    "addr:full":"34 2nd St NW Hickory NC 28601",
    "addr:housenumber":"34",
    "addr:postcode":"28601",
    "addr:street":"2Nd St Nw",
    "iso:country":"US",
    "sg:address":"34 2nd St NW",
    "sg:city":"Hickory",
    "sg:classifiers":[
        {
            "category":"Social Services",
            "type":"Services"
        }
    ],
    "sg:phone":"+1 828 328 2966",
    "sg:postcode":"28601",
    "sg:province":"NC",
    "sg:tags":[
        "counseling"
    ],
    "wof:name":"Trinity Counseling",
    "wof:placetype":"venue"
},
  "geometry": {"coordinates":[-81.339573,35.732288],"type":"Point"}
}