{
  "type": "Feature",
  "properties": {
    "iso:country":"US",
    "sg:address":"129 Central Blvd",
    "sg:city":"Wilmington",
    "sg:classifiers":[
        {
            "category":"Professional",
            "type":"Services"
        }
    ],
    "sg:phone":"+1 910 762 9521",
    "sg:postcode":"28401",
    "sg:province":"NC",
    "wof:name":"Billy Gurganious",
    "wof:placetype":"venue"
},
  "geometry": {"coordinates":[-77.946544,34.20065],"type":"Point"}
}