{
  "type": "Feature",
  "properties": {
    "iso:country":"US",
    "sg:address":"3001 Wood Rd",
    "sg:city":"Mooresboro",
    "sg:classifiers":[
        {
            "category":"Building & Trades",
            "subcategory":"Landscaping Services",
            "type":"Services"
        }
    ],
    "sg:phone":"+1 828 657 5552",
    "sg:postcode":"28114",
    "sg:province":"SC",
    "sg:tags":[
        "landscape",
        "contractor"
    ],
    "wof:name":"Prospect Landscaping",
    "wof:placetype":"venue"
},
  "geometry": {"coordinates":[-81.752989,35.203602],"type":"Point"}
}