{
  "type": "Feature",
  "properties": {
    "iso:country":"US",
    "sg:address":"909 Tarpon Dr",
    "sg:city":"Wilmington",
    "sg:classifiers":[
        {
            "category":"Home & Garden",
            "subcategory":"Garden Supply",
            "type":"Retail Goods"
        }
    ],
    "sg:phone":"+1 910 799 0595",
    "sg:postcode":"28409",
    "sg:province":"NC",
    "sg:tags":[
        "lawn",
        "mower"
    ],
    "wof:name":"TURFMACHINES.COM",
    "wof:placetype":"venue"
},
  "geometry": {"coordinates":[-77.892293,34.068571],"type":"Point"}
}