{
  "type": "Feature",
  "properties": {
    "iso:country":"US",
    "sg:address":"5747 Wisteria Ln",
    "sg:city":"Wilmington",
    "sg:classifiers":[
        {
            "category":"Organizations",
            "subcategory":"Religious Organization",
            "type":"Services"
        }
    ],
    "sg:phone":"+1   ",
    "sg:postcode":"28409",
    "sg:province":"NC",
    "wof:name":"Cornerstone Church",
    "wof:placetype":"venue"
},
  "geometry": {"coordinates":[-77.850683,34.205812],"type":"Point"}
}