{
  "type": "Feature",
  "properties": {
    "iso:country":"US",
    "sg:address":"412 Front St",
    "sg:city":"Beaufort",
    "sg:classifiers":[
        {
            "category":"Professional",
            "subcategory":"Lawyer & Legal Services",
            "type":"Services"
        }
    ],
    "sg:phone":"+1 252 728 4080",
    "sg:postcode":"28516",
    "sg:province":"NC",
    "sg:tags":[
        "attorney"
    ],
    "wof:name":"Davis Murrelle & Lyles",
    "wof:placetype":"venue"
},
  "geometry": {"coordinates":[-76.66331700000001,34.715476],"type":"Point"}
}