{
  "type": "Feature",
  "properties": {
    "addr:full":"605 W Chapel Hill St Durham NC 27701",
    "addr:housenumber":"605",
    "addr:postcode":"27701",
    "addr:street":"W Chapel Hill St",
    "iso:country":"US",
    "sg:address":"605 W Chapel Hill St",
    "sg:city":"Durham",
    "sg:classifiers":[
        {
            "category":"Shopping",
            "subcategory":"Used Merchandise",
            "type":"Retail Goods"
        },
        {
            "category":"Travel",
            "subcategory":"Hotels & Motels",
            "type":"Entertainment"
        }
    ],
    "sg:phone":"+1 919 688 6059",
    "sg:postcode":"27701",
    "sg:province":"NC",
    "sg:tags":[
        "flea",
        "operation",
        "market"
    ],
    "wof:name":"Urban Merchant Center",
    "wof:placetype":"venue"
},
  "geometry": {"coordinates":[-78.91050199999999,35.996898],"type":"Point"}
}