{
  "type": "Feature",
  "properties": {
    "iso:country":"US",
    "sg:address":"266 Old Coats Rd",
    "sg:city":"Lillington",
    "sg:classifiers":[
        {
            "category":"Professional",
            "subcategory":"Testing Lab",
            "type":"Services"
        }
    ],
    "sg:phone":"+1 910 893 8743",
    "sg:postcode":"27546",
    "sg:province":"NC",
    "sg:tags":[
        "soil"
    ],
    "wof:name":"Hal Owen & Assoc Inc",
    "wof:placetype":"venue"
},
  "geometry": {"coordinates":[-78.791376,35.424848],"type":"Point"}
}