{
  "type": "Feature",
  "properties": {
    "addr:full":"1506 Union Rd Gastonia NC 28054",
    "addr:housenumber":"1506",
    "addr:postcode":"28054",
    "addr:street":"Union Rd",
    "iso:country":"US",
    "sg:address":"1506 Union Rd",
    "sg:city":"Gastonia",
    "sg:classifiers":[
        {
            "category":"Social Services",
            "type":"Services"
        },
        {
            "category":"Place Of Worship",
            "subcategory":"Church",
            "type":"Public Place"
        },
        {
            "category":"Place Of Worship",
            "type":"Public Place"
        },
        {
            "category":"Shopping",
            "subcategory":"Thrift Store",
            "type":"Retail Goods"
        }
    ],
    "sg:phone":"+1 704 867 6910",
    "sg:postcode":"28054",
    "sg:province":"NC",
    "sg:tags":[
        "shop",
        "churches-salvation",
        "army"
    ],
    "sg:website":"http://www.salvationarmyusa.org/",
    "wof:name":"Salvation Army Family Store",
    "wof:placetype":"venue"
},
  "geometry": {"coordinates":[-81.1713,35.244169],"type":"Point"}
}