{
  "type": "Feature",
  "properties": {
    "iso:country":"US",
    "sg:address":"5607 Wispy Willow Ln",
    "sg:city":"Raleigh",
    "sg:classifiers":[
        {
            "category":"Building & Trades",
            "subcategory":"Construction",
            "type":"Services"
        }
    ],
    "sg:phone":"+1 919 676 3337",
    "sg:postcode":"27609",
    "sg:province":"NC",
    "sg:tags":[
        "house"
    ],
    "wof:name":"Quality Home Repair",
    "wof:placetype":"venue"
},
  "geometry": {"coordinates":[-78.602884,35.85562],"type":"Point"}
}