{
  "type": "Feature",
  "properties": {
    "addr:full":"1220 Lochcarron Ln Cary NC 27511",
    "addr:housenumber":"1220",
    "addr:postcode":"27511",
    "addr:street":"Lochcarron Ln",
    "iso:country":"US",
    "sg:address":"1220 Lochcarron Ln",
    "sg:city":"Cary",
    "sg:classifiers":[
        {
            "category":"Real Estate",
            "subcategory":"Real Estate Agent",
            "type":"Services"
        }
    ],
    "sg:phone":"+1 919 469 2056",
    "sg:postcode":"27511",
    "sg:province":"NC",
    "wof:name":"John P Healey",
    "wof:placetype":"venue"
},
  "geometry": {"coordinates":[-78.807108,35.765091],"type":"Point"}
}