{
  "type": "Feature",
  "properties": {
    "addr:full":"1401 Buffalo Shoals Rd Catawba NC 28609",
    "addr:housenumber":"1401",
    "addr:postcode":"28609",
    "addr:street":"Buffalo Shoals Rd",
    "iso:country":"US",
    "sg:address":"1401 Buffalo Shoals Rd",
    "sg:city":"Catawba",
    "sg:classifiers":[
        {
            "category":"Manufacturing",
            "subcategory":"Printing",
            "type":"Manufacturing & Wholesale Goods"
        }
    ],
    "sg:phone":"+1 828 241 2342",
    "sg:postcode":"28609",
    "sg:province":"NC",
    "sg:tags":[
        "book",
        "transportation",
        "freight"
    ],
    "wof:name":"D & V Enterprises",
    "wof:placetype":"venue"
},
  "geometry": {"coordinates":[-81.085819,35.651529],"type":"Point"}
}