{
  "type": "Feature",
  "properties": {
    "iso:country":"US",
    "sg:address":"620 S Trade St",
    "sg:city":"Tryon",
    "sg:classifiers":[
        {
            "category":"Shopping",
            "subcategory":"Pharmacy",
            "type":"Retail Goods"
        }
    ],
    "sg:phone":"+1 828 859 6615",
    "sg:postcode":"28782",
    "sg:province":"NC",
    "sg:tags":[
        "drug",
        "store"
    ],
    "wof:name":"Tryon Pharmacy",
    "wof:placetype":"venue"
},
  "geometry": {"coordinates":[-82.23585300000001,35.200599],"type":"Point"}
}