{
  "type": "Feature",
  "properties": {
    "addr:full":"10720 S Tryon St Charlotte NC 28273",
    "addr:housenumber":"10720",
    "addr:postcode":"28273",
    "addr:street":"S Tryon St",
    "iso:country":"US",
    "sg:address":"10720 S Tryon St",
    "sg:city":"Charlotte",
    "sg:classifiers":[
        {
            "category":"Shopping",
            "subcategory":"Discount & Variety Stores",
            "type":"Retail Goods"
        }
    ],
    "sg:phone":"+1 704 583 9202",
    "sg:postcode":"28273",
    "sg:province":"NC",
    "wof:name":"Golden Dollar",
    "wof:placetype":"venue"
},
  "geometry": {"coordinates":[-80.954646,35.118936],"type":"Point"}
}