{
  "type": "Feature",
  "properties": {
    "iso:country":"US",
    "sg:address":"317 S Chester St",
    "sg:city":"Gastonia",
    "sg:classifiers":[
        {
            "category":"Organizations",
            "subcategory":"Religious Organization",
            "type":"Services"
        }
    ],
    "sg:phone":"+1 704 864 3468",
    "sg:postcode":"28052",
    "sg:province":"NC",
    "sg:tags":[
        "church"
    ],
    "wof:name":"First Arp Church",
    "wof:placetype":"venue"
},
  "geometry": {"coordinates":[-81.187478,35.259373],"type":"Point"}
}