{
  "type": "Feature",
  "properties": {
    "iso:country":"US",
    "sg:address":"3924 Chesapeake Dr",
    "sg:city":"Charlotte",
    "sg:classifiers":[
        {
            "category":"Shopping",
            "subcategory":"Computers & Home Electronics",
            "type":"Retail Goods"
        }
    ],
    "sg:phone":"+1 704 398 0777",
    "sg:postcode":"28216",
    "sg:province":"NC",
    "sg:website":"www.smartsystems2000.com",
    "wof:name":"Smart Systems",
    "wof:placetype":"venue"
},
  "geometry": {"coordinates":[-80.869989,35.272988],"type":"Point"}
}