{
  "type": "Feature",
  "properties": {
    "addr:full":"6017 Cedar Square Rd Archdale NC 27263",
    "addr:housenumber":"6017",
    "addr:postcode":"27263",
    "addr:street":"Cedar Square Rd",
    "iso:country":"US",
    "sg:address":"6017 Cedar Square Rd",
    "sg:city":"Archdale",
    "sg:classifiers":[
        {
            "category":"Wholesale",
            "subcategory":"Machinery & Supplies",
            "type":"Manufacturing & Wholesale Goods"
        }
    ],
    "sg:phone":"+1 336 434 3848",
    "sg:postcode":"27263",
    "sg:province":"NC",
    "sg:tags":[
        "equipment",
        "material",
        "handling"
    ],
    "wof:name":"Dan Ellington Co",
    "wof:placetype":"venue"
},
  "geometry": {"coordinates":[-79.88273599999999,35.874568],"type":"Point"}
}