{
  "type": "Feature",
  "properties": {
    "addr:full":"4431 Angier Ave Durham NC 27703",
    "addr:housenumber":"4431",
    "addr:postcode":"27703",
    "addr:street":"Angier Ave",
    "iso:country":"US",
    "sg:address":"4431 Angier Ave",
    "sg:city":"Durham",
    "sg:classifiers":[
        {
            "category":"Social Services",
            "subcategory":"Child Care",
            "type":"Services"
        }
    ],
    "sg:phone":"+1 919 596 3446",
    "sg:postcode":"27703",
    "sg:province":"NC",
    "wof:name":"Jean Jewels Family Chldcr Home",
    "wof:placetype":"venue"
},
  "geometry": {"coordinates":[-78.830313,35.941226],"type":"Point"}
}