{
  "type": "Feature",
  "properties": {
    "iso:country":"US",
    "sg:address":"106 High Bluff Trl",
    "sg:city":"Hubert",
    "sg:classifiers":[
        {
            "category":"Building & Trades",
            "subcategory":"Landscaping Services",
            "type":"Services"
        }
    ],
    "sg:phone":"+1 910 326 6949",
    "sg:postcode":"28539",
    "sg:province":"NC",
    "sg:tags":[
        "lawn",
        "maintenance",
        "grounds"
    ],
    "wof:name":"Elite Lawn Care",
    "wof:placetype":"venue"
},
  "geometry": {"coordinates":[-77.171628,34.716064],"type":"Point"}
}