{
  "type": "Feature",
  "properties": {
    "iso:country":"US",
    "sg:address":"2180 State Hwy 101",
    "sg:city":"Havelock",
    "sg:classifiers":[
        {
            "category":"Organizations",
            "subcategory":"Religious Organization",
            "type":"Services"
        }
    ],
    "sg:phone":"+1   ",
    "sg:postcode":"28532",
    "sg:province":"NC",
    "wof:name":"Hyman Chapel",
    "wof:placetype":"venue"
},
  "geometry": {"coordinates":[-76.83505700000001,34.871653],"type":"Point"}
}