{
  "type": "Feature",
  "properties": {
    "addr:full":"2443 Green Cove Rd Brasstown NC 28902",
    "addr:housenumber":"2443",
    "addr:postcode":"28902",
    "addr:street":"Green Cove Rd",
    "iso:country":"US",
    "sg:address":"2443 Green Cove Rd",
    "sg:city":"Brasstown",
    "sg:classifiers":[
        {
            "category":"Shopping",
            "subcategory":"Musical Instruments",
            "type":"Retail Goods"
        }
    ],
    "sg:phone":"+1 828 837 3524",
    "sg:postcode":"28902",
    "sg:province":"NC",
    "sg:tags":[
        "repair"
    ],
    "wof:name":"Somervell Guitars",
    "wof:placetype":"venue"
},
  "geometry": {"coordinates":[-83.928513,35.039307],"type":"Point"}
}