{
  "type": "Feature",
  "properties": {
    "addr:full":"207 Westcroft Dr Garner NC 27529",
    "addr:housenumber":"207",
    "addr:postcode":"27529",
    "addr:street":"Westcroft Dr",
    "iso:country":"US",
    "sg:address":"207 Westcroft Dr",
    "sg:city":"Garner",
    "sg:classifiers":[
        {
            "category":"Real Estate",
            "subcategory":"Real Estate Operator",
            "type":"Services"
        }
    ],
    "sg:phone":"+1 919 661 4244",
    "sg:postcode":"27529",
    "sg:province":"NC",
    "sg:tags":[
        "building",
        "apartment"
    ],
    "wof:name":"Weston Trace Apartments",
    "wof:placetype":"venue"
},
  "geometry": {"coordinates":[-78.61601400000001,35.71923],"type":"Point"}
}