{
  "type": "Feature",
  "properties": {
    "addr:full":"3202 Old Oak Walk Greenville NC 27858",
    "addr:housenumber":"3202",
    "addr:postcode":"27858",
    "addr:street":"Old Oak Walk",
    "iso:country":"US",
    "sg:address":"3202 Old Oak Walk",
    "sg:city":"Greenville",
    "sg:classifiers":[
        {
            "category":"Manufacturing",
            "subcategory":"Tools & Machinery",
            "type":"Manufacturing & Wholesale Goods"
        }
    ],
    "sg:phone":"+1 252 355 6107",
    "sg:postcode":"27858",
    "sg:province":"NC",
    "sg:tags":[
        "filter",
        "dental",
        "for"
    ],
    "wof:name":"Miracle Filter Inc",
    "wof:placetype":"venue"
},
  "geometry": {"coordinates":[-77.336974,35.577274],"type":"Point"}
}