{
  "type": "Feature",
  "properties": {
    "addr:full":"1009 N Madison Blvd Roxboro NC 27573",
    "addr:housenumber":"1009",
    "addr:postcode":"27573",
    "addr:street":"N Madison Blvd",
    "iso:country":"US",
    "sg:address":"1009 N Madison Blvd",
    "sg:city":"Roxboro",
    "sg:classifiers":[
        {
            "category":"Personal",
            "subcategory":"Tanning Parlor",
            "type":"Services"
        }
    ],
    "sg:phone":"+1 336 599 1983",
    "sg:postcode":"27573",
    "sg:province":"NC",
    "sg:tags":[
        "salon"
    ],
    "wof:name":"Endless Summer Tanning",
    "wof:placetype":"venue"
},
  "geometry": {"coordinates":[-78.974487,36.409475],"type":"Point"}
}