{
  "type": "Feature",
  "properties": {
    "addr:full":"2445 Carolina Beach Rd Wilmington NC 28401",
    "addr:housenumber":"2445",
    "addr:postcode":"28401",
    "addr:street":"Carolina Beach Rd",
    "iso:country":"US",
    "sg:address":"2445 Carolina Beach Rd",
    "sg:city":"Wilmington",
    "sg:classifiers":[
        {
            "category":"Shopping",
            "subcategory":"Used Merchandise",
            "type":"Retail Goods"
        }
    ],
    "sg:phone":"+1 910 815 1014",
    "sg:postcode":"28401",
    "sg:province":"NC",
    "sg:tags":[
        "shop",
        "thrift"
    ],
    "wof:name":"Salvation Army",
    "wof:placetype":"venue"
},
  "geometry": {"coordinates":[-77.935987,34.194517],"type":"Point"}
}