{
  "type": "Feature",
  "properties": {
    "iso:country":"US",
    "sg:address":"100 Jerusalem Drive",
    "sg:city":"Morrisville",
    "sg:classifiers":[
        {
            "category":"Bars & Pubs",
            "subcategory":"Sports Bar",
            "type":"Food & Drink"
        }
    ],
    "sg:phone":"+1 919 465 1900",
    "sg:postcode":"27560",
    "sg:province":"NC",
    "sg:website":"www.ohmulligans.com",
    "wof:name":"Oh Mulligan's",
    "wof:placetype":"venue"
},
  "geometry": {"coordinates":[-78.82703100000001,35.850681],"type":"Point"}
}