{
  "type": "Feature",
  "properties": {
    "iso:country":"US",
    "sg:address":"17 Lady Bug Ln",
    "sg:city":"Leicester",
    "sg:classifiers":[
        {
            "category":"Professional",
            "type":"Services"
        }
    ],
    "sg:phone":"+1 828 683 8003",
    "sg:postcode":"28748",
    "sg:province":"NC",
    "wof:name":"Glaz Inc",
    "wof:placetype":"venue"
},
  "geometry": {"coordinates":[-82.707695,35.634016],"type":"Point"}
}