{
  "type": "Feature",
  "properties": {
    "iso:country":"US",
    "sg:address":"3525 Old Whiteville Rd",
    "sg:city":"Lumberton",
    "sg:classifiers":[
        {
            "category":"Wholesale",
            "subcategory":"Hardware",
            "type":"Manufacturing & Wholesale Goods"
        }
    ],
    "sg:phone":"+1 910 739 0496",
    "sg:postcode":"28358",
    "sg:province":"NC",
    "sg:tags":[
        "equipment",
        "heating",
        "system"
    ],
    "wof:name":"Ben Troy Heating & Air",
    "wof:placetype":"venue"
},
  "geometry": {"coordinates":[-78.944153,34.585097],"type":"Point"}
}