{
  "type": "Feature",
  "properties": {
    "addr:full":"109 Keller St Morganton NC 28655",
    "addr:housenumber":"109",
    "addr:postcode":"28655",
    "addr:street":"Keller St",
    "iso:country":"US",
    "sg:address":"109 Keller St",
    "sg:city":"Morganton",
    "sg:classifiers":[
        {
            "category":"Building & Trades",
            "subcategory":"Construction",
            "type":"Services"
        }
    ],
    "sg:phone":"+1 828 584 2495",
    "sg:postcode":"28655",
    "sg:province":"NC",
    "sg:tags":[
        "heavy"
    ],
    "wof:name":"Kellers Stump Grinding Service",
    "wof:placetype":"venue"
},
  "geometry": {"coordinates":[-81.770458,35.724739],"type":"Point"}
}