{
  "type": "Feature",
  "properties": {
    "addr:full":"3867 Taylorsville Hwy Statesville NC 28625",
    "addr:housenumber":"3867",
    "addr:postcode":"28625",
    "addr:street":"Taylorsville Hwy",
    "iso:country":"US",
    "sg:address":"3867 Taylorsville Hwy",
    "sg:city":"Statesville",
    "sg:classifiers":[
        {
            "category":"Organizations",
            "subcategory":"Religious Organization",
            "type":"Services"
        }
    ],
    "sg:phone":"+1 704 872 7344",
    "sg:postcode":"28625",
    "sg:province":"NC",
    "sg:website":"www.concordpreschurch.com",
    "wof:name":"Concord Presbyterian Church",
    "wof:placetype":"venue"
},
  "geometry": {"coordinates":[-80.972877,35.816875],"type":"Point"}
}