{
  "type": "Feature",
  "properties": {
    "addr:full":"209 York Rd Kings Mountain NC 28086",
    "addr:housenumber":"209",
    "addr:postcode":"28086",
    "addr:street":"York Rd",
    "iso:country":"US",
    "sg:address":"209 York Rd",
    "sg:city":"Kings Mountain",
    "sg:classifiers":[
        {
            "category":"Wholesale",
            "subcategory":"Auto Parts",
            "type":"Manufacturing & Wholesale Goods"
        }
    ],
    "sg:phone":"+1 704 739 4783",
    "sg:postcode":"28086",
    "sg:province":"NC",
    "wof:name":"City Auto & Truck Parts Inc",
    "wof:placetype":"venue"
},
  "geometry": {"coordinates":[-81.333011,35.239052],"type":"Point"}
}