{
  "type": "Feature",
  "properties": {
    "iso:country":"US",
    "sg:address":"146 Locust Ct",
    "sg:city":"Jacksonville",
    "sg:classifiers":[
        {
            "category":"Retail",
            "subcategory":"Auto Repair",
            "type":"Services"
        }
    ],
    "sg:phone":"+1   ",
    "sg:postcode":"28546",
    "sg:province":"NC",
    "sg:tags":[
        "general"
    ],
    "wof:name":"Dingus Mobile Auto Repair",
    "wof:placetype":"venue"
},
  "geometry": {"coordinates":[-77.352,34.761672],"type":"Point"}
}