{
  "type": "Feature",
  "properties": {
    "iso:country":"US",
    "sg:address":"4904 Larchmont St",
    "sg:city":"Raleigh",
    "sg:classifiers":[
        {
            "category":"Farming",
            "subcategory":"Farm",
            "type":"Manufacturing & Wholesale Goods"
        }
    ],
    "sg:phone":"+1 919 782 9596",
    "sg:postcode":"27612",
    "sg:province":"NC",
    "sg:tags":[
        "crop",
        "general"
    ],
    "wof:name":"Worsley Properties LLC",
    "wof:placetype":"venue"
},
  "geometry": {"coordinates":[-78.691879,35.860855],"type":"Point"}
}