{
  "type": "Feature",
  "properties": {
    "addr:full":"3299 Starmount Dr Greensboro NC 27403",
    "addr:housenumber":"3299",
    "addr:postcode":"27403",
    "addr:street":"Starmount Dr",
    "iso:country":"US",
    "sg:address":"3299 Starmount Dr",
    "sg:city":"Greensboro",
    "sg:classifiers":[
        {
            "category":"Government",
            "subcategory":"Office",
            "type":"Public Place"
        }
    ],
    "sg:phone":"+1 336 297 5036",
    "sg:postcode":"27403",
    "sg:province":"NC",
    "sg:tags":[
        "village"
    ],
    "wof:name":"W Market Ballfield",
    "wof:placetype":"venue"
},
  "geometry": {"coordinates":[-79.833319,36.074202],"type":"Point"}
}