{
  "type": "Feature",
  "properties": {
    "iso:country":"US",
    "sg:address":"347 Deatherage Rd",
    "sg:city":"Mount Airy",
    "sg:classifiers":[
        {
            "category":"Organizations",
            "subcategory":"Religious Organization",
            "type":"Services"
        }
    ],
    "sg:phone":"+1   ",
    "sg:postcode":"27030",
    "sg:province":"NC",
    "wof:name":"Church of God of Prophecy",
    "wof:placetype":"venue"
},
  "geometry": {"coordinates":[-80.565737,36.506769],"type":"Point"}
}