{
  "type": "Feature",
  "properties": {
    "addr:full":"4200 Ferriday Ct Raleigh NC 27616",
    "addr:housenumber":"4200",
    "addr:postcode":"27616",
    "addr:street":"Ferriday Ct",
    "iso:country":"US",
    "sg:address":"4200 Ferriday Ct",
    "sg:city":"Raleigh",
    "sg:classifiers":[
        {
            "category":"Freight",
            "type":"Transportation"
        }
    ],
    "sg:phone":"+1 919 217 3311",
    "sg:postcode":"27616",
    "sg:province":"NC",
    "sg:tags":[
        "trucking"
    ],
    "wof:name":"Hi Way Trucking",
    "wof:placetype":"venue"
},
  "geometry": {"coordinates":[-78.50352599999999,35.879042],"type":"Point"}
}