{
  "type": "Feature",
  "properties": {
    "addr:full":"274 Pittsboro Elem School Rd Pittsboro NC 27312",
    "addr:housenumber":"274",
    "addr:postcode":"27312",
    "addr:street":"School Rd",
    "iso:country":"US",
    "sg:address":"274 Pittsboro Elem School Rd",
    "sg:city":"Pittsboro",
    "sg:classifiers":[
        {
            "category":"Professional",
            "subcategory":"Research",
            "type":"Services"
        }
    ],
    "sg:phone":"+1 919 545 9050",
    "sg:postcode":"27312",
    "sg:province":"NC",
    "sg:tags":[
        "consultant",
        "recycling"
    ],
    "wof:name":"Carolina Recycling Assn",
    "wof:placetype":"venue"
},
  "geometry": {"coordinates":[-79.181079,35.717538],"type":"Point"}
}