{
  "type": "Feature",
  "properties": {
    "addr:full":"306 N Main St Burlington NC 27215",
    "addr:housenumber":"306",
    "addr:postcode":"27215",
    "addr:street":"N Main St",
    "iso:country":"US",
    "sg:address":"306 N Main St",
    "sg:city":"Burlington",
    "sg:classifiers":[
        {
            "category":"Retail",
            "subcategory":"Laundry & Dry Cleaning",
            "type":"Services"
        }
    ],
    "sg:phone":"+1 336 226 6226",
    "sg:postcode":"27215",
    "sg:province":"NC",
    "sg:tags":[
        "drycleaning",
        "plant",
        "coin",
        "power"
    ],
    "wof:name":"R E Boone Cleaners",
    "wof:placetype":"venue"
},
  "geometry": {"coordinates":[-79.431178,36.096925],"type":"Point"}
}