{
  "type": "Feature",
  "properties": {
    "iso:country":"US",
    "sg:address":"1422 Highland Dr",
    "sg:city":"Washington",
    "sg:classifiers":[
        {
            "category":"Education",
            "subcategory":"School",
            "type":"Public Place"
        }
    ],
    "sg:phone":"+1 252 946 5032",
    "sg:postcode":"27889",
    "sg:province":"NC",
    "sg:tags":[
        "resource",
        "center",
        "learning"
    ],
    "wof:name":"Bcs Learning Resource Center",
    "wof:placetype":"venue"
},
  "geometry": {"coordinates":[-77.03249099999999,35.551907],"type":"Point"}
}