{
  "type": "Feature",
  "properties": {
    "addr:full":"523 Country Club Dr Fayetteville NC 28301",
    "addr:housenumber":"523",
    "addr:postcode":"28301",
    "addr:street":"Country Club Dr",
    "iso:country":"US",
    "sg:address":"523 Country Club Dr",
    "sg:city":"Fayetteville",
    "sg:classifiers":[
        {
            "category":"Health Services",
            "subcategory":"Nursing And Care Facility",
            "type":"Services"
        }
    ],
    "sg:phone":"+1 910 488 0711",
    "sg:postcode":"28301",
    "sg:province":"NC",
    "sg:tags":[
        "skilled",
        "home",
        "intermediate"
    ],
    "wof:name":"Whispering Pines Nursing Home",
    "wof:placetype":"venue"
},
  "geometry": {"coordinates":[-78.888772,35.104146],"type":"Point"}
}