{
  "type": "Feature",
  "properties": {
    "iso:country":"US",
    "sg:address":"3396 Six Forks Rd",
    "sg:city":"Raleigh",
    "sg:classifiers":[
        {
            "category":"Health Services",
            "subcategory":"Doctor",
            "type":"Services"
        }
    ],
    "sg:phone":"+1 919 571 9494",
    "sg:postcode":"27609",
    "sg:province":"NC",
    "sg:tags":[
        "medical"
    ],
    "wof:name":"Carolina Surgical Assoc PA",
    "wof:placetype":"venue"
},
  "geometry": {"coordinates":[-78.634077,35.827058],"type":"Point"}
}