{
  "type": "Feature",
  "properties": {
    "iso:country":"US",
    "sg:address":"6612 E W T Harris Blvd",
    "sg:city":"Charlotte",
    "sg:classifiers":[
        {
            "category":"Building & Trades",
            "subcategory":"Cleaning & Sanitation",
            "type":"Services"
        }
    ],
    "sg:phone":"+1 704 537 9644",
    "sg:postcode":"28215",
    "sg:province":"NC",
    "sg:tags":[
        "janitor"
    ],
    "wof:name":"Smith Janitorial Svc",
    "wof:placetype":"venue"
},
  "geometry": {"coordinates":[-80.72841699999999,35.229956],"type":"Point"}
}