{
  "type": "Feature",
  "properties": {
    "iso:country":"US",
    "sg:address":"1014 Canyon Rd",
    "sg:city":"Marble",
    "sg:classifiers":[
        {
            "category":"Building & Trades",
            "subcategory":"Construction",
            "type":"Services"
        }
    ],
    "sg:phone":"+1 828 837 7045",
    "sg:postcode":"28905",
    "sg:province":"NC",
    "sg:tags":[
        "grading",
        "contractor"
    ],
    "wof:name":"Triple M Construction",
    "wof:placetype":"venue"
},
  "geometry": {"coordinates":[-83.93041100000001,35.129616],"type":"Point"}
}