{
  "type": "Feature",
  "properties": {
    "iso:country":"US",
    "sg:address":"5594 Friendship Glen Dr",
    "sg:city":"Browns Summit",
    "sg:classifiers":[
        {
            "category":"Building & Trades",
            "subcategory":"Landscaping Services",
            "type":"Services"
        }
    ],
    "sg:phone":"+1 336 656 5219",
    "sg:postcode":"27214",
    "sg:province":"NC",
    "sg:tags":[
        "lawn",
        "maintenance",
        "grounds"
    ],
    "wof:name":"Southern Lawn Care",
    "wof:placetype":"venue"
},
  "geometry": {"coordinates":[-79.650794,36.208528],"type":"Point"}
}