{
  "type": "Feature",
  "properties": {
    "iso:country":"US",
    "sg:address":"189 Nahunta Farm Rd",
    "sg:city":"Pikeville",
    "sg:classifiers":[
        {
            "category":"Wholesale",
            "subcategory":"Meat",
            "type":"Manufacturing & Wholesale Goods"
        }
    ],
    "sg:phone":"+1 919 242 4852",
    "sg:postcode":"27863",
    "sg:province":"NC",
    "sg:tags":[
        "pork",
        "mfg",
        "product",
        "prepared"
    ],
    "wof:name":"Nahunta Farm Sausage Co Inc",
    "wof:placetype":"venue"
},
  "geometry": {"coordinates":[-78.066228,35.498023],"type":"Point"}
}