{
  "type": "Feature",
  "properties": {
    "addr:full":"119 Cross Center Rd Denver NC 28037",
    "addr:housenumber":"119",
    "addr:postcode":"28037",
    "addr:street":"Cross Center Rd",
    "iso:country":"US",
    "sg:address":"119 Cross Center Rd",
    "sg:city":"Denver",
    "sg:classifiers":[
        {
            "category":"Banks & Credit Unions",
            "subcategory":"Bank",
            "type":"Services"
        }
    ],
    "sg:phone":"+1 704 399 6595",
    "sg:postcode":"28037",
    "sg:province":"NC",
    "wof:name":"Bank Of America",
    "wof:placetype":"venue"
},
  "geometry": {"coordinates":[-80.99621399999999,35.445187],"type":"Point"}
}