{
  "type": "Feature",
  "properties": {
    "iso:country":"US",
    "sg:address":"2604 Hargate Ct",
    "sg:city":"Wilmington",
    "sg:classifiers":[
        {
            "category":"Real Estate",
            "subcategory":"Real Estate Agent",
            "type":"Services"
        }
    ],
    "sg:phone":"+1 910 395 5345",
    "sg:postcode":"28405",
    "sg:province":"NC",
    "wof:name":"Emily Mathews Real Estate",
    "wof:placetype":"venue"
},
  "geometry": {"coordinates":[-77.877127,34.296028],"type":"Point"}
}