{
  "type": "Feature",
  "properties": {
    "addr:full":"2501 Junaluska Rd Boone NC 28607",
    "addr:housenumber":"2501",
    "addr:postcode":"28607",
    "addr:street":"Junaluska Rd",
    "iso:country":"US",
    "sg:address":"2501 Junaluska Rd",
    "sg:city":"Boone",
    "sg:classifiers":[
        {
            "category":"Arts & Performance",
            "subcategory":"Theater",
            "type":"Entertainment"
        }
    ],
    "sg:phone":"+1 828 264 8118",
    "sg:postcode":"28607",
    "sg:province":"NC",
    "sg:tags":[
        "theatrical",
        "bureau"
    ],
    "wof:name":"Mountain Home Music Inc",
    "wof:placetype":"venue"
},
  "geometry": {"coordinates":[-81.710617,36.245613],"type":"Point"}
}