{
  "type": "Feature",
  "properties": {
    "iso:country":"US",
    "sg:address":"3400 Westgate Dr",
    "sg:city":"Durham",
    "sg:classifiers":[
        {
            "category":"Home & Garden",
            "subcategory":"Home Furnishings",
            "type":"Retail Goods"
        }
    ],
    "sg:phone":"+1 919 403 9133",
    "sg:postcode":"27707",
    "sg:province":"NC",
    "sg:tags":[
        "fireplace"
    ],
    "wof:name":"Just Fireplaces",
    "wof:placetype":"venue"
},
  "geometry": {"coordinates":[-78.96069199999999,35.964923],"type":"Point"}
}