{
  "type": "Feature",
  "properties": {
    "addr:full":"601 E Trade St Charlotte NC 28202",
    "addr:housenumber":"601",
    "addr:postcode":"28202",
    "addr:street":"E Trade St",
    "iso:country":"US",
    "sg:address":"601 E Trade St",
    "sg:city":"Charlotte",
    "sg:classifiers":[
        {
            "category":"Government",
            "subcategory":"Police Station",
            "type":"Public Place"
        }
    ],
    "sg:phone":"+1 704 336 8301",
    "sg:postcode":"28202",
    "sg:province":"NC",
    "sg:tags":[
        "department"
    ],
    "wof:name":"Charlotte Police Dept",
    "wof:placetype":"venue"
},
  "geometry": {"coordinates":[-80.83707,35.222097],"type":"Point"}
}