{
  "type": "Feature",
  "properties": {
    "addr:full":"215 Guffey St Salisbury NC 28147",
    "addr:housenumber":"215",
    "addr:postcode":"28147",
    "addr:street":"Guffey St",
    "iso:country":"US",
    "sg:address":"215 Guffey St",
    "sg:city":"Salisbury",
    "sg:classifiers":[
        {
            "category":"Social Services",
            "type":"Services"
        }
    ],
    "sg:phone":"+1 704 633 7370",
    "sg:postcode":"28147",
    "sg:province":"NC",
    "sg:tags":[
        "organization",
        "welfare"
    ],
    "wof:name":"Rowan Homes Inc",
    "wof:placetype":"venue"
},
  "geometry": {"coordinates":[-80.508385,35.645491],"type":"Point"}
}