{
  "type": "Feature",
  "properties": {
    "addr:full":"105 W Main St Faison NC 28341",
    "addr:housenumber":"105",
    "addr:postcode":"28341",
    "addr:street":"W Main St",
    "iso:country":"US",
    "sg:address":"105 W Main St",
    "sg:city":"Faison",
    "sg:classifiers":[
        {
            "category":"Freight",
            "type":"Transportation"
        }
    ],
    "sg:phone":"+1 910 267 0555",
    "sg:postcode":"28341",
    "sg:province":"NC",
    "sg:tags":[
        "trucking"
    ],
    "wof:name":"Eugene's Trucking",
    "wof:placetype":"venue"
},
  "geometry": {"coordinates":[-78.137139,35.116329],"type":"Point"}
}