{
  "type": "Feature",
  "properties": {
    "iso:country":"US",
    "sg:address":"1711 Castle St",
    "sg:city":"Wilmington",
    "sg:classifiers":[
        {
            "category":"Professional",
            "subcategory":"Research",
            "type":"Services"
        }
    ],
    "sg:phone":"+1 910 762 7082",
    "sg:postcode":"28403",
    "sg:province":"NC",
    "sg:tags":[
        "environmental",
        "ecological"
    ],
    "wof:name":"Law & Co Of Wilmington Inc",
    "wof:placetype":"venue"
},
  "geometry": {"coordinates":[-77.92544700000001,34.229695],"type":"Point"}
}