{
  "type": "Feature",
  "properties": {
    "addr:full":"2100 Faculty Dr Winston Salem NC 27106",
    "addr:housenumber":"2100",
    "addr:postcode":"27106",
    "addr:street":"Faculty Dr",
    "iso:country":"US",
    "sg:address":"2100 Faculty Dr",
    "sg:city":"Winston Salem",
    "sg:classifiers":[
        {
            "category":"Utilities",
            "subcategory":"Telephone",
            "type":"Services"
        }
    ],
    "sg:phone":"+1 336 896 1834",
    "sg:postcode":"27106",
    "sg:province":"NC",
    "sg:tags":[
        "communications"
    ],
    "wof:name":"Gw Technoligies",
    "wof:placetype":"venue"
},
  "geometry": {"coordinates":[-80.276504,36.130252],"type":"Point"}
}