{
  "type": "Feature",
  "properties": {
    "iso:country":"US",
    "sg:address":"101 N Tamilynn Cir",
    "sg:city":"Cary",
    "sg:classifiers":[
        {
            "category":"Professional",
            "subcategory":"Lawyer & Legal Services",
            "type":"Services"
        }
    ],
    "sg:phone":"+1   ",
    "sg:postcode":"27513",
    "sg:province":"NC",
    "wof:name":"James B Stephenson II",
    "wof:placetype":"venue"
},
  "geometry": {"coordinates":[-78.785685,35.797689],"type":"Point"}
}