{
  "type": "Feature",
  "properties": {
    "addr:full":"50 State St Marion NC 28752",
    "addr:housenumber":"50",
    "addr:postcode":"28752",
    "addr:street":"State St",
    "iso:country":"US",
    "sg:address":"50 State St",
    "sg:city":"Marion",
    "sg:classifiers":[
        {
            "category":"Organizations",
            "subcategory":"Religious Organization",
            "type":"Services"
        }
    ],
    "sg:phone":"+1 828 652 5532",
    "sg:postcode":"28752",
    "sg:province":"NC",
    "sg:tags":[
        "church"
    ],
    "wof:name":"Marion United Meth Dist Office",
    "wof:placetype":"venue"
},
  "geometry": {"coordinates":[-82.007541,35.682063],"type":"Point"}
}