{
  "type": "Feature",
  "properties": {
    "iso:country":"US",
    "sg:address":"2711 Princess Place Dr",
    "sg:city":"Wilmington",
    "sg:classifiers":[
        {
            "category":"Education",
            "subcategory":"Special Training",
            "type":"Public Place"
        }
    ],
    "sg:phone":"+1 910 343 4177",
    "sg:postcode":"28405",
    "sg:province":"NC",
    "sg:tags":[
        "youth",
        "school",
        "after",
        "at"
    ],
    "wof:name":"Yesic",
    "wof:placetype":"venue"
},
  "geometry": {"coordinates":[-77.90939400000001,34.243921],"type":"Point"}
}