{
  "type": "Feature",
  "properties": {
    "iso:country":"US",
    "sg:address":"2500 Blue Ridge Rd Ste 421",
    "sg:city":"Raleigh",
    "sg:classifiers":[
        {
            "category":"Health Services",
            "subcategory":"Doctor",
            "type":"Services"
        }
    ],
    "sg:phone":"+1 919 787 1772",
    "sg:postcode":"27607",
    "sg:province":"NC",
    "sg:tags":[
        "cardiologist"
    ],
    "wof:name":"Capital Cardiovascular Surgery PA",
    "wof:placetype":"venue"
},
  "geometry": {"coordinates":[-78.7052,35.8144],"type":"Point"}
}