{
  "type": "Feature",
  "properties": {
    "addr:full":"501 Warren C Coleman Blvd Concord NC 28025",
    "addr:housenumber":"501;c",
    "addr:postcode":"28025",
    "addr:street":"Warren;Coleman Blvd",
    "iso:country":"US",
    "sg:address":"501 Warren C Coleman Blvd",
    "sg:city":"Concord",
    "sg:classifiers":[
        {
            "category":"Shopping",
            "subcategory":"Discount & Variety Stores",
            "type":"Retail Goods"
        }
    ],
    "sg:phone":"+1 704 262 7692",
    "sg:postcode":"28025",
    "sg:province":"NC",
    "wof:name":"Dollar General",
    "wof:placetype":"venue"
},
  "geometry": {"coordinates":[-80.580517,35.381639],"type":"Point"}
}