{
  "type": "Feature",
  "properties": {
    "iso:country":"US",
    "sg:address":"2233 Piney Grove-Wilbon Rd",
    "sg:city":"Holly Springs",
    "sg:phone":"+1 919 552 9479",
    "sg:postcode":"27540",
    "sg:province":"NC",
    "sg:tags":[
        "farm",
        "soybean"
    ],
    "wof:name":"Joe Callis",
    "wof:placetype":"venue"
},
  "geometry": {"coordinates":[-78.83823,35.600133],"type":"Point"}
}