{
  "type": "Feature",
  "properties": {
    "iso:country":"US",
    "sg:address":"115 Atwood St",
    "sg:city":"Sparta",
    "sg:classifiers":[
        {
            "category":"Professional",
            "subcategory":"Management & Consulting",
            "type":"Services"
        }
    ],
    "sg:phone":"+1 336 372 1525",
    "sg:postcode":"28675",
    "sg:province":"NC",
    "sg:tags":[
        "consultant",
        "business"
    ],
    "wof:name":"Blue Ridge Business Dev Ctr",
    "wof:placetype":"venue"
},
  "geometry": {"coordinates":[-81.119091,36.512372],"type":"Point"}
}