{
  "type": "Feature",
  "properties": {
    "addr:full":"339 Harrison St Charlotte NC 28208",
    "addr:housenumber":"339",
    "addr:postcode":"28208",
    "addr:street":"Harrison St",
    "iso:country":"US",
    "sg:address":"339 Harrison St",
    "sg:city":"Charlotte",
    "sg:classifiers":[
        {
            "category":"Social Services",
            "subcategory":"Child Care",
            "type":"Services"
        }
    ],
    "sg:phone":"+1   ",
    "sg:postcode":"28208",
    "sg:province":"NC",
    "sg:tags":[
        "day"
    ],
    "wof:name":"Davis Home Daycare",
    "wof:placetype":"venue"
},
  "geometry": {"coordinates":[-80.87708499999999,35.252889],"type":"Point"}
}