{
  "type": "Feature",
  "properties": {
    "addr:full":"435 Bear Rd Madison NC 27025",
    "addr:housenumber":"435",
    "addr:postcode":"27025",
    "addr:street":"Bear Rd",
    "iso:country":"US",
    "sg:address":"435 Bear Rd",
    "sg:city":"Madison",
    "sg:classifiers":[
        {
            "category":"Building & Trades",
            "subcategory":"Construction",
            "type":"Services"
        }
    ],
    "sg:phone":"+1 336 427 9919",
    "sg:postcode":"27025",
    "sg:province":"NC",
    "sg:tags":[
        "resurfacing",
        "laying",
        "refinishing",
        "floor"
    ],
    "wof:name":"Oak Finishing & Hardwood Flrng",
    "wof:placetype":"venue"
},
  "geometry": {"coordinates":[-79.879688,36.371405],"type":"Point"}
}