{
  "type": "Feature",
  "properties": {
    "addr:full":"1 E Hargett St Raleigh NC 27601",
    "addr:housenumber":"1",
    "addr:postcode":"27601",
    "addr:street":"E Hargett St",
    "iso:country":"US",
    "sg:address":"1 E Hargett St",
    "sg:city":"Raleigh",
    "sg:classifiers":[
        {
            "category":"Professional",
            "subcategory":"Lawyer & Legal Services",
            "type":"Services"
        }
    ],
    "sg:phone":"+1 919 834 8877",
    "sg:postcode":"27601",
    "sg:province":"NC",
    "sg:tags":[
        "attorney"
    ],
    "wof:name":"Hilliard & Jones",
    "wof:placetype":"venue"
},
  "geometry": {"coordinates":[-78.63821299999999,35.778228],"type":"Point"}
}