{
  "type": "Feature",
  "properties": {
    "iso:country":"US",
    "sg:address":"211 E Center St",
    "sg:city":"Mebane",
    "sg:classifiers":[
        {
            "category":"Building & Trades",
            "subcategory":"Electrical",
            "type":"Services"
        }
    ],
    "sg:phone":"+1 919 304 3643",
    "sg:postcode":"27302",
    "sg:province":"NC",
    "sg:tags":[
        "electric",
        "contractor"
    ],
    "wof:name":"TARCO Electrical",
    "wof:placetype":"venue"
},
  "geometry": {"coordinates":[-79.266265,36.095887],"type":"Point"}
}