{
  "type": "Feature",
  "properties": {
    "iso:country":"US",
    "sg:address":"1902 Old Haywood Rd",
    "sg:city":"Asheville",
    "sg:classifiers":[
        {
            "category":"Food & Beverages",
            "subcategory":"Groceries & Convenience Stores",
            "type":"Retail Goods"
        }
    ],
    "sg:phone":"+1 828 670 0000",
    "sg:postcode":"28806",
    "sg:province":"NC",
    "wof:name":"M & J Food Stores Inc",
    "wof:placetype":"venue"
},
  "geometry": {"coordinates":[-82.632999,35.564867],"type":"Point"}
}