{
  "type": "Feature",
  "properties": {
    "iso:country":"US",
    "sg:address":"43 Substation Rd",
    "sg:city":"Canton",
    "sg:classifiers":[
        {
            "category":"Building & Trades",
            "subcategory":"Electrical",
            "type":"Services"
        }
    ],
    "sg:phone":"+1 828 648 6588",
    "sg:postcode":"28716",
    "sg:province":"NC",
    "sg:tags":[
        "electrical",
        "contractor"
    ],
    "wof:name":"Jennings Sizemore Electric",
    "wof:placetype":"venue"
},
  "geometry": {"coordinates":[-82.84042700000001,35.523076],"type":"Point"}
}