{
  "type": "Feature",
  "properties": {
    "iso:country":"US",
    "sg:address":"90 Green Ridge Rd",
    "sg:city":"Weaverville",
    "sg:classifiers":[
        {
            "category":"Professional",
            "type":"Services"
        }
    ],
    "sg:phone":"+1 828 658 1327",
    "sg:postcode":"28787",
    "sg:province":"NC",
    "wof:name":"John M Zeigler IV Inc",
    "wof:placetype":"venue"
},
  "geometry": {"coordinates":[-82.58050299999999,35.722616],"type":"Point"}
}