{
  "type": "Feature",
  "properties": {
    "addr:full":"1610 Vaughn Rd Burlington NC 27217",
    "addr:housenumber":"1610",
    "addr:postcode":"27217",
    "addr:street":"Vaughn Rd",
    "iso:country":"US",
    "sg:address":"1610 Vaughn Rd",
    "sg:city":"Burlington",
    "sg:classifiers":[
        {
            "category":"Personal",
            "subcategory":"Barber",
            "type":"Services"
        }
    ],
    "sg:phone":"+1 336 570 1117",
    "sg:postcode":"27217",
    "sg:province":"NC",
    "wof:name":"Carl Siler Barber Shop",
    "wof:placetype":"venue"
},
  "geometry": {"coordinates":[-79.40943900000001,36.101213],"type":"Point"}
}