{
  "type": "Feature",
  "properties": {
    "iso:country":"US",
    "sg:address":"320 Melody Cir",
    "sg:city":"Swannanoa",
    "sg:classifiers":[
        {
            "category":"Shopping",
            "subcategory":"Catalog Store",
            "type":"Retail Goods"
        }
    ],
    "sg:phone":"+1 828 298 5819",
    "sg:postcode":"28778",
    "sg:province":"NC",
    "sg:tags":[
        "mail",
        "house"
    ],
    "wof:name":"Ardeekaye Photography",
    "wof:placetype":"venue"
},
  "geometry": {"coordinates":[-82.423666,35.599587],"type":"Point"}
}