{
  "type": "Feature",
  "properties": {
    "addr:full":"13111 Ambrosia St Charlotte NC 28278",
    "addr:housenumber":"13111",
    "addr:postcode":"28278",
    "addr:street":"Ambrosia St",
    "iso:country":"US",
    "sg:address":"13111 Ambrosia St",
    "sg:city":"Charlotte",
    "sg:classifiers":[
        {
            "category":"Professional",
            "subcategory":"Accounting & Tax Preparation",
            "type":"Services"
        }
    ],
    "sg:phone":"+1 704 588 7711",
    "sg:postcode":"28278",
    "sg:province":"NC",
    "sg:tags":[
        "bookkeeping",
        "general"
    ],
    "wof:name":"HMA Business Svc",
    "wof:placetype":"venue"
},
  "geometry": {"coordinates":[-80.992867,35.132225],"type":"Point"}
}