{
  "type": "Feature",
  "properties": {
    "iso:country":"US",
    "sg:address":"28 Tunnel Rd",
    "sg:city":"Asheville",
    "sg:classifiers":[
        {
            "category":"Restaurant",
            "type":"Food & Drink"
        }
    ],
    "sg:phone":"+1 828 253 4900",
    "sg:postcode":"28805",
    "sg:province":"NC",
    "sg:tags":[
        "eating"
    ],
    "sg:website":"www.joescrabshack.com",
    "wof:name":"Joe's Crab Shack",
    "wof:placetype":"venue"
},
  "geometry": {"coordinates":[-82.532788,35.595514],"type":"Point"}
}