{
  "type": "Feature",
  "properties": {
    "addr:full":"2221 Bayview Rd Bath NC 27808",
    "addr:housenumber":"2221",
    "addr:postcode":"27808",
    "addr:street":"Bayview Rd",
    "iso:country":"US",
    "sg:address":"2221 Bayview Rd",
    "sg:city":"Bath",
    "sg:classifiers":[
        {
            "category":"Professional",
            "subcategory":"Business Services",
            "type":"Services"
        }
    ],
    "sg:phone":"+1   ",
    "sg:postcode":"27808",
    "sg:province":"NC",
    "wof:name":"Candy Man",
    "wof:placetype":"venue"
},
  "geometry": {"coordinates":[-76.80325000000001,35.439378],"type":"Point"}
}