{
  "type": "Feature",
  "properties": {
    "iso:country":"US",
    "sg:address":"1205 Floral Pkwy",
    "sg:city":"Wilmington",
    "sg:classifiers":[
        {
            "category":"Shopping",
            "subcategory":"Optical Goods",
            "type":"Retail Goods"
        }
    ],
    "sg:phone":"+1 910 452 7331",
    "sg:postcode":"28403",
    "sg:province":"NC",
    "wof:name":"Floral Parkway Opticians",
    "wof:placetype":"venue"
},
  "geometry": {"coordinates":[-77.899619,34.217433],"type":"Point"}
}