{
  "type": "Feature",
  "properties": {
    "iso:country":"US",
    "sg:address":"140 S Main St",
    "sg:city":"Laurinburg",
    "sg:classifiers":[
        {
            "category":"Shopping",
            "subcategory":"Pharmacy",
            "type":"Retail Goods"
        }
    ],
    "sg:phone":"+1 910 276 3001",
    "sg:postcode":"28352",
    "sg:province":"NC",
    "wof:name":"Scotland Drug",
    "wof:placetype":"venue"
},
  "geometry": {"coordinates":[-79.46152600000001,34.776368],"type":"Point"}
}