{
  "type": "Feature",
  "properties": {
    "addr:full":"3608 Oleander Dr Wilmington NC 28403",
    "addr:housenumber":"3608",
    "addr:postcode":"28403",
    "addr:street":"Oleander Dr",
    "iso:country":"US",
    "sg:address":"3608 Oleander Dr",
    "sg:city":"Wilmington",
    "sg:classifiers":[
        {
            "category":"Shopping",
            "subcategory":"Clothing, Apparel, & Fashions",
            "type":"Retail Goods"
        }
    ],
    "sg:phone":"+1 910 799 4822",
    "sg:postcode":"28403",
    "sg:province":"NC",
    "sg:tags":[
        "furnishing"
    ],
    "wof:name":"S & K Famous Brands Menswear",
    "wof:placetype":"venue"
},
  "geometry": {"coordinates":[-77.90346700000001,34.215537],"type":"Point"}
}