{
  "type": "Feature",
  "properties": {
    "addr:full":"321 N Front St Wilmington NC 28401",
    "addr:housenumber":"321",
    "addr:postcode":"28401",
    "addr:street":"N Front St",
    "iso:country":"US",
    "sg:address":"321 N Front St",
    "sg:city":"Wilmington",
    "sg:classifiers":[
        {
            "category":"Personal",
            "type":"Services"
        }
    ],
    "sg:phone":"+1 910 762 4893",
    "sg:postcode":"28401",
    "sg:province":"NC",
    "sg:tags":[
        "therapist",
        "massage"
    ],
    "wof:name":"Wilmington Center-Therapeutic",
    "wof:placetype":"venue"
},
  "geometry": {"coordinates":[-77.94932300000001,34.239661],"type":"Point"}
}