{
  "type": "Feature",
  "properties": {
    "addr:full":"4014 US Hwy 64 Robersonville NC 27871",
    "addr:housenumber":"4014",
    "addr:postcode":"27871",
    "addr:street":"Us Hwy 64",
    "iso:country":"US",
    "sg:address":"4014 US Hwy 64",
    "sg:city":"Robersonville",
    "sg:classifiers":[
        {
            "category":"Organizations",
            "subcategory":"Religious Organization",
            "type":"Services"
        }
    ],
    "sg:phone":"+1   ",
    "sg:postcode":"27871",
    "sg:province":"NC",
    "wof:name":"Roberson Chapel Church",
    "wof:placetype":"venue"
},
  "geometry": {"coordinates":[-77.30306899999999,35.822029],"type":"Point"}
}