{
  "type": "Feature",
  "properties": {
    "iso:country":"US",
    "sg:address":"21 Falls Ave",
    "sg:city":"Granite Falls",
    "sg:classifiers":[
        {
            "category":"Shopping",
            "subcategory":"Pharmacy",
            "type":"Retail Goods"
        }
    ],
    "sg:phone":"+1 828 396 2144",
    "sg:postcode":"28630",
    "sg:province":"NC",
    "wof:name":"Granite Drug Ctr",
    "wof:placetype":"venue"
},
  "geometry": {"coordinates":[-81.428608,35.798065],"type":"Point"}
}