{
  "type": "Feature",
  "properties": {
    "addr:full":"3631 Croft Haven Dr Charlotte NC 28269",
    "addr:housenumber":"3631",
    "addr:postcode":"28269",
    "addr:street":"Croft Haven Dr",
    "iso:country":"US",
    "sg:address":"3631 Croft Haven Dr",
    "sg:city":"Charlotte",
    "sg:classifiers":[
        {
            "category":"Manufacturing",
            "subcategory":"Building Materials",
            "type":"Manufacturing & Wholesale Goods"
        }
    ],
    "sg:phone":"+1 704 509 5788",
    "sg:postcode":"28269",
    "sg:province":"NC",
    "sg:tags":[
        "millwork",
        "mfg"
    ],
    "wof:name":"Woodworking Jackson & Design",
    "wof:placetype":"venue"
},
  "geometry": {"coordinates":[-80.813734,35.351373],"type":"Point"}
}