{
  "type": "Feature",
  "properties": {
    "iso:country":"US",
    "sg:address":"1300 S Church St",
    "sg:city":"Charlotte",
    "sg:classifiers":[
        {
            "category":"Building & Trades",
            "subcategory":"Construction",
            "type":"Services"
        }
    ],
    "sg:phone":"+1 704 375 3197",
    "sg:postcode":"28203",
    "sg:province":"NC",
    "sg:tags":[
        "painter"
    ],
    "wof:name":"Painting Specialties Inc",
    "wof:placetype":"venue"
},
  "geometry": {"coordinates":[-80.85659699999999,35.219972],"type":"Point"}
}