{
  "type": "Feature",
  "properties": {
    "addr:full":"1232 Essex Ave Gastonia NC 28052",
    "addr:housenumber":"1232",
    "addr:postcode":"28052",
    "addr:street":"Essex Ave",
    "iso:country":"US",
    "sg:address":"1232 Essex Ave",
    "sg:city":"Gastonia",
    "sg:classifiers":[
        {
            "category":"Professional",
            "subcategory":"Advertising",
            "type":"Services"
        }
    ],
    "sg:phone":"+1 704 868 8424",
    "sg:postcode":"28052",
    "sg:province":"NC",
    "sg:tags":[
        "counselor"
    ],
    "wof:name":"Nirvana Management Inc",
    "wof:placetype":"venue"
},
  "geometry": {"coordinates":[-81.20847999999999,35.270032],"type":"Point"}
}