{
  "type": "Feature",
  "properties": {
    "iso:country":"US",
    "sg:address":"141 N Oakland St",
    "sg:city":"Gastonia",
    "sg:classifiers":[
        {
            "category":"Government",
            "subcategory":"Office",
            "type":"Public Place"
        }
    ],
    "sg:phone":"+1 704 866 6056",
    "sg:postcode":"28052",
    "sg:province":"NC",
    "sg:tags":[
        "city",
        "program"
    ],
    "wof:name":"Gastonia Transit ADA Van Svc",
    "wof:placetype":"venue"
},
  "geometry": {"coordinates":[-81.18006699999999,35.26381],"type":"Point"}
}