{
  "type": "Feature",
  "properties": {
    "addr:full":"401 Chestnut St Wilmington NC 28401",
    "addr:housenumber":"401",
    "addr:postcode":"28401",
    "addr:street":"Chestnut St",
    "iso:country":"US",
    "sg:address":"401 Chestnut St",
    "sg:city":"Wilmington",
    "sg:classifiers":[
        {
            "category":"Professional",
            "subcategory":"Lawyer & Legal Services",
            "type":"Services"
        }
    ],
    "sg:phone":"+1 910 763 6020",
    "sg:postcode":"28401",
    "sg:province":"NC",
    "sg:tags":[
        "attorney"
    ],
    "wof:name":"Monica J Rathke",
    "wof:placetype":"venue"
},
  "geometry": {"coordinates":[-77.94364899999999,34.23797],"type":"Point"}
}