{
  "type": "Feature",
  "properties": {
    "iso:country":"US",
    "sg:address":"1015 Montgomery St SW",
    "sg:city":"Winston Salem",
    "sg:classifiers":[
        {
            "category":"Manufacturing",
            "subcategory":"Printing",
            "type":"Manufacturing & Wholesale Goods"
        }
    ],
    "sg:phone":"+1 336 724 0812",
    "sg:postcode":"27101",
    "sg:province":"NC",
    "sg:tags":[
        "work"
    ],
    "wof:name":"Boxwood Bindery",
    "wof:placetype":"venue"
},
  "geometry": {"coordinates":[-80.251859,36.083305],"type":"Point"}
}