{
  "type": "Feature",
  "properties": {
    "iso:country":"US",
    "sg:address":"374 Lucinda Ln",
    "sg:city":"Kernersville",
    "sg:classifiers":[
        {
            "category":"Building & Trades",
            "subcategory":"Construction",
            "type":"Services"
        }
    ],
    "sg:phone":"+1 336 788 3893",
    "sg:postcode":"27284",
    "sg:province":"NC",
    "sg:tags":[
        "carpentry",
        "contractor"
    ],
    "wof:name":"Hiatt Custom Framing",
    "wof:placetype":"venue"
},
  "geometry": {"coordinates":[-80.156648,36.102931],"type":"Point"}
}