{
  "type": "Feature",
  "properties": {
    "addr:full":"101 Manning Dr Chapel Hill NC 27514",
    "addr:housenumber":"101",
    "addr:postcode":"27514",
    "addr:street":"Manning Dr",
    "iso:country":"US",
    "sg:address":"101 Manning Dr",
    "sg:city":"Chapel Hill",
    "sg:classifiers":[
        {
            "category":"Health Services",
            "subcategory":"Hospital",
            "type":"Services"
        }
    ],
    "sg:phone":"+1 919 966 2453",
    "sg:postcode":"27514",
    "sg:province":"NC",
    "wof:name":"Unc Hospitals",
    "wof:placetype":"venue"
},
  "geometry": {"coordinates":[-79.051598,35.903301],"type":"Point"}
}