{
  "type": "Feature",
  "properties": {
    "iso:country":"US",
    "sg:address":"925 Emerald Bay Dr",
    "sg:city":"Salisbury",
    "sg:classifiers":[
        {
            "category":"Professional",
            "subcategory":"Computer Services",
            "type":"Services"
        }
    ],
    "sg:phone":"+1 704 630 6914",
    "sg:postcode":"28146",
    "sg:province":"NC",
    "sg:tags":[
        "consultant"
    ],
    "wof:name":"Leland Group LLC",
    "wof:placetype":"venue"
},
  "geometry": {"coordinates":[-80.262173,35.600759],"type":"Point"}
}