{
  "type": "Feature",
  "properties": {
    "iso:country":"US",
    "sg:address":"1 Edgedale Dr",
    "sg:city":"Asheville",
    "sg:classifiers":[
        {
            "category":"Professional",
            "type":"Services"
        }
    ],
    "sg:phone":"+1 828 250 0482",
    "sg:postcode":"28804",
    "sg:province":"NC",
    "wof:name":"In Mountain Childrens Therapy",
    "wof:placetype":"venue"
},
  "geometry": {"coordinates":[-82.54730499999999,35.637842],"type":"Point"}
}