{
  "type": "Feature",
  "properties": {
    "iso:country":"US",
    "sg:address":"534 Canvasback Rd",
    "sg:city":"Mooresville",
    "sg:classifiers":[
        {
            "category":"Professional",
            "type":"Services"
        }
    ],
    "sg:phone":"+1 704 799 9791",
    "sg:postcode":"28117",
    "sg:province":"NC",
    "wof:name":"Rondal F Eller",
    "wof:placetype":"venue"
},
  "geometry": {"coordinates":[-80.886572,35.555963],"type":"Point"}
}