{
  "type": "Feature",
  "properties": {
    "iso:country":"US",
    "sg:address":"3391 Dellwood Rd",
    "sg:city":"Waynesville",
    "sg:classifiers":[
        {
            "category":"Professional",
            "subcategory":"Business Services",
            "type":"Services"
        }
    ],
    "sg:phone":"+1   ",
    "sg:postcode":"28786",
    "sg:province":"NC",
    "wof:name":"Ffs Enterprises LLC",
    "wof:placetype":"venue"
},
  "geometry": {"coordinates":[-83.02255599999999,35.522363],"type":"Point"}
}