{
  "type": "Feature",
  "properties": {
    "iso:country":"US",
    "sg:address":"1410 US Hwy 70 E",
    "sg:city":"Connellys Spgs",
    "sg:classifiers":[
        {
            "category":"Shopping",
            "subcategory":"Used Merchandise",
            "type":"Retail Goods"
        }
    ],
    "sg:phone":"+1 828 879 8845",
    "sg:postcode":"28612",
    "sg:province":"NC",
    "sg:tags":[
        "pawnbroker"
    ],
    "wof:name":"Danny's Buy Sell & Trades",
    "wof:placetype":"venue"
},
  "geometry": {"coordinates":[-81.485187,35.729415],"type":"Point"}
}