{
  "type": "Feature",
  "properties": {
    "addr:full":"110 Kathyrn Ct Elizabeth City NC 27909",
    "addr:housenumber":"110",
    "addr:postcode":"27909",
    "addr:street":"Kathyrn Ct",
    "iso:country":"US",
    "sg:address":"110 Kathyrn Ct",
    "sg:city":"Elizabeth City",
    "sg:classifiers":[
        {
            "category":"Shopping",
            "type":"Retail Goods"
        }
    ],
    "sg:phone":"+1 252 338 5718",
    "sg:postcode":"27909",
    "sg:province":"NC",
    "sg:tags":[
        "equipment",
        "paging",
        "telephone",
        "cellular"
    ],
    "wof:name":"Beepers Plus",
    "wof:placetype":"venue"
},
  "geometry": {"coordinates":[-76.23958,36.286678],"type":"Point"}
}