{
  "type": "Feature",
  "properties": {
    "addr:full":"172 Turnersburg Hwy Statesville NC 28625",
    "addr:housenumber":"172",
    "addr:postcode":"28625",
    "addr:street":"Turnersburg Hwy",
    "iso:country":"US",
    "sg:address":"172 Turnersburg Hwy",
    "sg:city":"Statesville",
    "sg:classifiers":[
        {
            "category":"Restaurant",
            "type":"Food & Drink"
        }
    ],
    "sg:phone":"+1 704 872 9560",
    "sg:postcode":"28625",
    "sg:province":"NC",
    "wof:name":"Taco Bell",
    "wof:placetype":"venue"
},
  "geometry": {"coordinates":[-80.87624,35.813265],"type":"Point"}
}