{
  "type": "Feature",
  "properties": {
    "iso:country":"US",
    "sg:address":"120 W Washington St",
    "sg:city":"Nashville",
    "sg:classifiers":[
        {
            "category":"Government",
            "subcategory":"Office",
            "type":"Public Place"
        }
    ],
    "sg:phone":"+1 252 459 7376",
    "sg:postcode":"27856",
    "sg:province":"NC",
    "sg:tags":[
        "county"
    ],
    "wof:name":"Nash County Fire",
    "wof:placetype":"venue"
},
  "geometry": {"coordinates":[-77.967088,35.975011],"type":"Point"}
}