{
  "type": "Feature",
  "properties": {
    "iso:country":"US",
    "sg:address":"120 Corporate Dr",
    "sg:city":"Troutman",
    "sg:classifiers":[
        {
            "category":"Wholesale",
            "subcategory":"Durable Goods & Equipment",
            "type":"Manufacturing & Wholesale Goods"
        }
    ],
    "sg:phone":"+1 704 528 3005",
    "sg:postcode":"28166",
    "sg:province":"NC",
    "sg:tags":[
        "representative",
        "manufacturer"
    ],
    "wof:name":"M James Bezanson & Assoc Inc",
    "wof:placetype":"venue"
},
  "geometry": {"coordinates":[-80.862334,35.681726],"type":"Point"}
}