{
  "type": "Feature",
  "properties": {
    "iso:country":"US",
    "sg:address":"528 Park Ln",
    "sg:city":"Albemarle",
    "sg:classifiers":[
        {
            "category":"Real Estate",
            "subcategory":"Real Estate Agent",
            "type":"Services"
        }
    ],
    "sg:phone":"+1 704 982 7270",
    "sg:postcode":"28001",
    "sg:province":"NC",
    "wof:name":"West Properties",
    "wof:placetype":"venue"
},
  "geometry": {"coordinates":[-80.18893199999999,35.358506],"type":"Point"}
}