{
  "type": "Feature",
  "properties": {
    "addr:full":"1084 Wells Rd Jacksonville NC 28540",
    "addr:housenumber":"1084",
    "addr:postcode":"28540",
    "addr:street":"Wells Rd",
    "iso:country":"US",
    "sg:address":"1084 Wells Rd",
    "sg:city":"Jacksonville",
    "sg:classifiers":[
        {
            "category":"Home & Garden",
            "subcategory":"Home Furnishings",
            "type":"Retail Goods"
        }
    ],
    "sg:phone":"+1 910 347 3958",
    "sg:postcode":"28540",
    "sg:province":"NC",
    "sg:tags":[
        "building",
        "maintenance"
    ],
    "wof:name":"Jacksonville Chimney Sweeps",
    "wof:placetype":"venue"
},
  "geometry": {"coordinates":[-77.495355,34.799928],"type":"Point"}
}