{
  "type": "Feature",
  "properties": {
    "addr:full":"1213 Marlwood Cir Charlotte NC 28227",
    "addr:housenumber":"1213",
    "addr:postcode":"28227",
    "addr:street":"Marlwood Cir",
    "iso:country":"US",
    "sg:address":"1213 Marlwood Cir",
    "sg:city":"Charlotte",
    "sg:classifiers":[
        {
            "category":"Building & Trades",
            "subcategory":"Construction",
            "type":"Services"
        }
    ],
    "sg:phone":"+1 704 536 7858",
    "sg:postcode":"28227",
    "sg:province":"NC",
    "sg:tags":[
        "home",
        "improvement"
    ],
    "wof:name":"M & R Home Maintenance Svc",
    "wof:placetype":"venue"
},
  "geometry": {"coordinates":[-80.706152,35.19961],"type":"Point"}
}