{
  "type": "Feature",
  "properties": {
    "iso:country":"US",
    "sg:address":"122 Sanford Rd",
    "sg:city":"Pittsboro",
    "sg:classifiers":[
        {
            "category":"Restaurant",
            "type":"Food & Drink"
        }
    ],
    "sg:phone":"+1 919 542 7460",
    "sg:postcode":"27312",
    "sg:province":"NC",
    "wof:name":"Mexico Lindo",
    "wof:placetype":"venue"
},
  "geometry": {"coordinates":[-79.178479,35.718623],"type":"Point"}
}