{
  "type": "Feature",
  "properties": {
    "iso:country":"US",
    "sg:address":"71 Ottinger Hts",
    "sg:city":"Waynesville",
    "sg:classifiers":[
        {
            "category":"Professional",
            "type":"Services"
        }
    ],
    "sg:phone":"+1   ",
    "sg:postcode":"28786",
    "sg:province":"NC",
    "wof:name":"Global Environmental Services",
    "wof:placetype":"venue"
},
  "geometry": {"coordinates":[-83.044968,35.463415],"type":"Point"}
}