{
  "type": "Feature",
  "properties": {
    "addr:full":"221 N 5th St Wilmington NC 28401",
    "addr:housenumber":"221",
    "addr:postcode":"28401",
    "addr:street":"N 5Th St",
    "iso:country":"US",
    "sg:address":"221 N 5th St",
    "sg:city":"Wilmington",
    "sg:classifiers":[
        {
            "category":"Social Services",
            "type":"Services"
        }
    ],
    "sg:phone":"+1 910 251 6590",
    "sg:postcode":"28401",
    "sg:province":"NC",
    "wof:name":"Oceanhouse",
    "wof:placetype":"venue"
},
  "geometry": {"coordinates":[-77.943849,34.238981],"type":"Point"}
}