{
  "type": "Feature",
  "properties": {
    "addr:full":"334 Milburn Dr Fayetteville NC 28314",
    "addr:housenumber":"334",
    "addr:postcode":"28314",
    "addr:street":"Milburn Dr",
    "iso:country":"US",
    "sg:address":"334 Milburn Dr",
    "sg:city":"Fayetteville",
    "sg:classifiers":[
        {
            "category":"Shopping",
            "subcategory":"Beauty & Cosmetics",
            "type":"Retail Goods"
        },
        {
            "category":"Personal",
            "subcategory":"Beauty Salon",
            "type":"Services"
        }
    ],
    "sg:phone":"+1 910 867 0635",
    "sg:postcode":"28314",
    "sg:province":"NC",
    "sg:tags":[
        "merchandise"
    ],
    "wof:name":"Shirley's Beauty Mart",
    "wof:placetype":"venue"
},
  "geometry": {"coordinates":[-79.005424,35.068956],"type":"Point"}
}