{
  "type": "Feature",
  "properties": {
    "iso:country":"US",
    "sg:address":"225 Village Rd",
    "sg:city":"South Brunswick",
    "sg:classifiers":[
        {
            "category":"Education",
            "subcategory":"School",
            "type":"Public Place"
        }
    ],
    "sg:phone":"+1 910 754 8218",
    "sg:postcode":"28470",
    "sg:province":"NC",
    "wof:name":"Shallotte Middle School",
    "wof:placetype":"venue"
},
  "geometry": {"coordinates":[-78.38989599999999,33.966692],"type":"Point"}
}