{
  "type": "Feature",
  "properties": {
    "addr:full":"3888 W Franklin Blvd Gastonia NC 28052",
    "addr:housenumber":"3888",
    "addr:postcode":"28052",
    "addr:street":"W Franklin Blvd",
    "iso:country":"US",
    "sg:address":"3888 W Franklin Blvd",
    "sg:city":"Gastonia",
    "sg:classifiers":[
        {
            "category":"Personal",
            "subcategory":"Beauty Salon",
            "type":"Services"
        }
    ],
    "sg:phone":"+1   ",
    "sg:postcode":"28052",
    "sg:province":"NC",
    "sg:tags":[
        "shop"
    ],
    "wof:name":"Number One Hair Connection",
    "wof:placetype":"venue"
},
  "geometry": {"coordinates":[-81.255771,35.257364],"type":"Point"}
}