{
  "type": "Feature",
  "properties": {
    "addr:full":"4220 Old Cherry Point Rd New Bern NC 28560",
    "addr:housenumber":"4220",
    "addr:postcode":"28560",
    "addr:street":"Old Cherry Point Rd",
    "iso:country":"US",
    "sg:address":"4220 Old Cherry Point Rd",
    "sg:city":"New Bern",
    "sg:classifiers":[
        {
            "category":"Organizations",
            "subcategory":"Religious Organization",
            "type":"Services"
        }
    ],
    "sg:phone":"+1 252 514 6897",
    "sg:postcode":"28560",
    "sg:province":"NC",
    "sg:tags":[
        "church"
    ],
    "wof:name":"Riverside United Methodist Chr",
    "wof:placetype":"venue"
},
  "geometry": {"coordinates":[-76.998407,35.033113],"type":"Point"}
}