{
  "type": "Feature",
  "properties": {
    "addr:full":"5405 Hilltop Cir Charlotte NC 28269",
    "addr:housenumber":"5405",
    "addr:postcode":"28269",
    "addr:street":"Hilltop Cir",
    "iso:country":"US",
    "sg:address":"5405 Hilltop Cir",
    "sg:city":"Charlotte",
    "sg:classifiers":[
        {
            "category":"Professional",
            "subcategory":"Business Services",
            "type":"Services"
        }
    ],
    "sg:phone":"+1   ",
    "sg:postcode":"28269",
    "sg:province":"NC",
    "sg:tags":[
        "promotional"
    ],
    "wof:name":"Dr Morheads Hunted Ware House",
    "wof:placetype":"venue"
},
  "geometry": {"coordinates":[-80.805785,35.2894],"type":"Point"}
}