{
  "type": "Feature",
  "properties": {
    "iso:country":"US",
    "sg:address":"7317 Edgefield Ct",
    "sg:city":"Matthews",
    "sg:classifiers":[
        {
            "category":"Professional",
            "subcategory":"Computer Services",
            "type":"Services"
        }
    ],
    "sg:phone":"+1   ",
    "sg:postcode":"28104",
    "sg:province":"NC",
    "sg:tags":[
        "datum"
    ],
    "wof:name":"Framing South",
    "wof:placetype":"venue"
},
  "geometry": {"coordinates":[-80.62483,35.131523],"type":"Point"}
}