{
  "type": "Feature",
  "properties": {
    "addr:full":"304 Wilmington Ave Surf City NC 28445",
    "addr:housenumber":"304",
    "addr:postcode":"28445",
    "addr:street":"Wilmington Ave",
    "iso:country":"US",
    "sg:address":"304 Wilmington Ave",
    "sg:city":"Surf City",
    "sg:classifiers":[
        {
            "category":"Organizations",
            "subcategory":"Religious Organization",
            "type":"Services"
        }
    ],
    "sg:phone":"+1 910 328 2831",
    "sg:postcode":"28445",
    "sg:province":"NC",
    "sg:tags":[
        "church"
    ],
    "wof:name":"Surf City Baptist Church",
    "wof:placetype":"venue"
},
  "geometry": {"coordinates":[-77.538085,34.430925],"type":"Point"}
}