{
  "type": "Feature",
  "properties": {
    "addr:full":"101 N Dougherty St Black Mountain NC 28711",
    "addr:housenumber":"101",
    "addr:postcode":"28711",
    "addr:street":"N Dougherty St",
    "iso:country":"US",
    "sg:address":"101 N Dougherty St",
    "sg:city":"Black Mountain",
    "sg:classifiers":[
        {
            "category":"Shopping",
            "subcategory":"Used Merchandise",
            "type":"Retail Goods"
        }
    ],
    "sg:phone":"+1 828 669 1966",
    "sg:postcode":"28711",
    "sg:province":"NC",
    "wof:name":"Reunions",
    "wof:placetype":"venue"
},
  "geometry": {"coordinates":[-82.32303899999999,35.616881],"type":"Point"}
}