{
  "type": "Feature",
  "properties": {
    "addr:full":"2514 Walkup Ave Monroe NC 28110",
    "addr:housenumber":"2514",
    "addr:postcode":"28110",
    "addr:street":"Walkup Ave",
    "iso:country":"US",
    "sg:address":"2514 Walkup Ave",
    "sg:city":"Monroe",
    "sg:classifiers":[
        {
            "category":"Retail",
            "subcategory":"Repair Shop",
            "type":"Services"
        }
    ],
    "sg:phone":"+1 704 289 3107",
    "sg:postcode":"28110",
    "sg:province":"NC",
    "sg:tags":[
        "textile"
    ],
    "wof:name":"Pine Island Sportswear",
    "wof:placetype":"venue"
},
  "geometry": {"coordinates":[-80.50614400000001,34.989333],"type":"Point"}
}