{
  "type": "Feature",
  "properties": {
    "addr:full":"4001 City of Oaks Wynd Raleigh NC 27612",
    "addr:housenumber":"4001",
    "addr:postcode":"27612",
    "addr:street":"Wynd",
    "iso:country":"US",
    "sg:address":"4001 City of Oaks Wynd",
    "sg:city":"Raleigh",
    "sg:classifiers":[
        {
            "category":"Real Estate",
            "subcategory":"Real Estate Agent",
            "type":"Services"
        }
    ],
    "sg:phone":"+1 919 787 9975",
    "sg:postcode":"27612",
    "sg:province":"NC",
    "wof:name":"P R Commercial Properties Inc",
    "wof:placetype":"venue"
},
  "geometry": {"coordinates":[-78.707493,35.831661],"type":"Point"}
}