{
  "type": "Feature",
  "properties": {
    "iso:country":"US",
    "sg:address":"3509 Asheville Hwy",
    "sg:city":"Hendersonville",
    "sg:classifiers":[
        {
            "category":"Retail",
            "subcategory":"Auto Repair",
            "type":"Services"
        }
    ],
    "sg:phone":"+1 828 692 5922",
    "sg:postcode":"28791",
    "sg:province":"NC",
    "sg:tags":[
        "repairing",
        "automobile"
    ],
    "wof:name":"Windy Hill Auto Ctr",
    "wof:placetype":"venue"
},
  "geometry": {"coordinates":[-82.486969,35.366508],"type":"Point"}
}