{
  "type": "Feature",
  "properties": {
    "iso:country":"US",
    "sg:address":"108 Forest Green Dr",
    "sg:city":"Cary",
    "sg:classifiers":[
        {
            "category":"Professional",
            "subcategory":"Management & Consulting",
            "type":"Services"
        }
    ],
    "sg:phone":"+1 919 363 4050",
    "sg:postcode":"27511",
    "sg:province":"NC",
    "sg:tags":[
        "party",
        "planning"
    ],
    "wof:name":"All-In Entertainment",
    "wof:placetype":"venue"
},
  "geometry": {"coordinates":[-78.77646,35.780816],"type":"Point"}
}