{
  "type": "Feature",
  "properties": {
    "iso:country":"US",
    "sg:address":"1930 N Poplar St",
    "sg:city":"Southern Pines",
    "sg:classifiers":[
        {
            "category":"Banks & Credit Unions",
            "subcategory":"Investment Brokerage",
            "type":"Services"
        }
    ],
    "sg:phone":"+1 910 692 1849",
    "sg:postcode":"28387",
    "sg:province":"NC",
    "sg:tags":[
        "security"
    ],
    "wof:name":"Edward Jones 17477",
    "wof:placetype":"venue"
},
  "geometry": {"coordinates":[-79.412462,35.158453],"type":"Point"}
}