{
  "type": "Feature",
  "properties": {
    "addr:full":"519 Keisler Dr Cary NC 27518",
    "addr:housenumber":"519",
    "addr:postcode":"27518",
    "addr:street":"Keisler Dr",
    "iso:country":"US",
    "sg:address":"519 Keisler Dr",
    "sg:city":"Cary",
    "sg:classifiers":[
        {
            "category":"Professional",
            "subcategory":"Testing Lab",
            "type":"Services"
        }
    ],
    "sg:phone":"+1 919 851 3505",
    "sg:postcode":"27518",
    "sg:province":"NC",
    "sg:tags":[
        "laboratory"
    ],
    "wof:name":"Analytics Corporation",
    "wof:placetype":"venue"
},
  "geometry": {"coordinates":[-78.779994,35.740672],"type":"Point"}
}