{
  "type": "Feature",
  "properties": {
    "addr:full":"703 Greenville Blvd SE Greenville NC 27858",
    "addr:housenumber":"703",
    "addr:postcode":"27858",
    "addr:street":"Greenville Blvd Se",
    "iso:country":"US",
    "sg:address":"703 Greenville Blvd SE",
    "sg:city":"Greenville",
    "sg:classifiers":[
        {
            "category":"Ice Cream",
            "type":"Food & Drink"
        }
    ],
    "sg:menulink":"http://www.allmenus.com/nc/greenville/243347-baskin-robbins/menu/",
    "sg:phone":"+1 252 756 4477",
    "sg:postcode":"27858",
    "sg:province":"NC",
    "sg:tags":[
        "american"
    ],
    "wof:name":"Baskin-Robbins",
    "wof:placetype":"venue"
},
  "geometry": {"coordinates":[-77.369343,35.587571],"type":"Point"}
}