{
  "type": "Feature",
  "properties": {
    "addr:full":"6605 Falls of Neuse Rd Raleigh NC 27615",
    "addr:housenumber":"6605",
    "addr:postcode":"27615",
    "addr:street":"Falls Of Neuse Rd",
    "iso:country":"US",
    "sg:address":"6605 Falls of Neuse Rd",
    "sg:city":"Raleigh",
    "sg:classifiers":[
        {
            "category":"Restaurant",
            "type":"Food & Drink"
        }
    ],
    "sg:menulink":"http://www.allmenus.com/nc/neuse/115818-quiznos-sub/menu/",
    "sg:phone":"+1 919 676 1909",
    "sg:postcode":"27615",
    "sg:province":"NC",
    "sg:tags":[
        "wrap",
        "american",
        "sandwich"
    ],
    "wof:name":"Quiznos Sub",
    "wof:placetype":"venue"
},
  "geometry": {"coordinates":[-78.62235699999999,35.873278],"type":"Point"}
}