{
  "type": "Feature",
  "properties": {
    "iso:country":"US",
    "sg:address":"6602 Grist Mill Rd",
    "sg:city":"Fayetteville",
    "sg:classifiers":[
        {
            "category":"Government",
            "subcategory":"Office",
            "type":"Public Place"
        }
    ],
    "sg:phone":"+1 910 864 6698",
    "sg:postcode":"28314",
    "sg:province":"NC",
    "sg:tags":[
        "administrative",
        "program",
        "economic",
        "general"
    ],
    "wof:name":"Cleo R Greene",
    "wof:placetype":"venue"
},
  "geometry": {"coordinates":[-79.014816,35.083043],"type":"Point"}
}