{
  "type": "Feature",
  "properties": {
    "addr:full":"401 Hawthorne Ln Ste 110 Charlotte NC 28204",
    "addr:housenumber":"401",
    "addr:postcode":"28204",
    "addr:street":"Hawthorne Ln Ste 110",
    "iso:country":"US",
    "sg:address":"401 Hawthorne Ln Ste 110",
    "sg:city":"Charlotte",
    "sg:classifiers":[
        {
            "category":"Communications",
            "subcategory":"News Services",
            "type":"Services"
        },
        {
            "category":"Transit Center",
            "subcategory":"Freight",
            "type":"Transportation"
        },
        {
            "category":"Professional",
            "subcategory":"Business Services",
            "type":"Services"
        },
        {
            "category":"Professional",
            "subcategory":"Printing & Photocopies",
            "type":"Services"
        },
        {
            "category":"Government",
            "subcategory":"Post Office",
            "type":"Public Place"
        }
    ],
    "sg:phone":"+1 704 370 6030",
    "sg:postcode":"28204",
    "sg:province":"NC",
    "sg:tags":[
        "cargo",
        "fax",
        "transparency",
        "package",
        "color",
        "express",
        "duplicating",
        "shipping",
        "mailbox-rental",
        "air",
        "copying",
        "mail",
        "print",
        "notary",
        "receiving",
        "photographic"
    ],
    "sg:website":"http://www.upsstore.com",
    "wof:name":"The UPS Store",
    "wof:placetype":"venue"
},
  "geometry": {"coordinates":[-80.822113,35.215778],"type":"Point"}
}