{
  "type": "Feature",
  "properties": {
    "addr:full":"8504 Ledger Ct Charlotte NC 28277",
    "addr:housenumber":"8504",
    "addr:postcode":"28277",
    "addr:street":"Ledger Ct",
    "iso:country":"US",
    "sg:address":"8504 Ledger Ct",
    "sg:city":"Charlotte",
    "sg:classifiers":[
        {
            "category":"Restaurant",
            "type":"Food & Drink"
        }
    ],
    "sg:phone":"+1 704 752 8169",
    "sg:postcode":"28277",
    "sg:province":"NC",
    "sg:tags":[
        "fast"
    ],
    "wof:name":"Jemcam Inc",
    "wof:placetype":"venue"
},
  "geometry": {"coordinates":[-80.81430899999999,35.025724],"type":"Point"}
}