{
  "type": "Feature",
  "properties": {
    "iso:country":"US",
    "sg:address":"600 Reedy Creek Baptist Church Rd",
    "sg:city":"Lexington",
    "sg:classifiers":[
        {
            "category":"Organizations",
            "subcategory":"Religious Organization",
            "type":"Services"
        }
    ],
    "sg:phone":"+1 336 764 3620",
    "sg:postcode":"27295",
    "sg:province":"NC",
    "sg:tags":[
        "church"
    ],
    "wof:name":"Reedy Creek Baptist Church",
    "wof:placetype":"venue"
},
  "geometry": {"coordinates":[-80.348969,35.922275],"type":"Point"}
}