{
  "type": "Feature",
  "properties": {
    "addr:full":"10422 Earnhardt Lake Rd Davidson NC 28036",
    "addr:housenumber":"10422",
    "addr:postcode":"28036",
    "addr:street":"Earnhardt Lake Rd",
    "iso:country":"US",
    "sg:address":"10422 Earnhardt Lake Rd",
    "sg:city":"Davidson",
    "sg:classifiers":[
        {
            "category":"Personal",
            "subcategory":"Beauty Salon",
            "type":"Services"
        }
    ],
    "sg:phone":"+1 704 938 2756",
    "sg:postcode":"28036",
    "sg:province":"NC",
    "sg:tags":[
        "shop"
    ],
    "wof:name":"Jean's Cuts & Curls",
    "wof:placetype":"venue"
},
  "geometry": {"coordinates":[-80.75989800000001,35.501056],"type":"Point"}
}