{
  "type": "Feature",
  "properties": {
    "addr:full":"154 N Allen Rd Wake Forest NC 27587",
    "addr:housenumber":"154",
    "addr:postcode":"27587",
    "addr:street":"N Allen Rd",
    "iso:country":"US",
    "sg:address":"154 N Allen Rd",
    "sg:city":"Wake Forest",
    "sg:classifiers":[
        {
            "category":"Real Estate",
            "subcategory":"Real Estate Agent",
            "type":"Services"
        }
    ],
    "sg:phone":"+1 919 556 5903",
    "sg:postcode":"27587",
    "sg:province":"NC",
    "sg:tags":[
        "authorities",
        "housing"
    ],
    "wof:name":"Debois Center Counseling Svc",
    "wof:placetype":"venue"
},
  "geometry": {"coordinates":[-78.50079700000001,35.977641],"type":"Point"}
}