{
  "type": "Feature",
  "properties": {
    "addr:full":"1092 Pearsall Rd Red Springs NC 28377",
    "addr:housenumber":"1092",
    "addr:postcode":"28377",
    "addr:street":"Pearsall Rd",
    "iso:country":"US",
    "sg:address":"1092 Pearsall Rd",
    "sg:city":"Red Springs",
    "sg:classifiers":[
        {
            "category":"Building & Trades",
            "subcategory":"Construction",
            "type":"Services"
        }
    ],
    "sg:phone":"+1 910 843 1666",
    "sg:postcode":"28377",
    "sg:province":"NC",
    "sg:tags":[
        "house"
    ],
    "wof:name":"Jr Willie Wynn",
    "wof:placetype":"venue"
},
  "geometry": {"coordinates":[-79.169235,34.824998],"type":"Point"}
}