{
  "type": "Feature",
  "properties": {
    "iso:country":"US",
    "sg:address":"5318 Valley Forge Rd",
    "sg:city":"Charlotte",
    "sg:classifiers":[
        {
            "category":"Mining & Drilling",
            "type":"Manufacturing & Wholesale Goods"
        }
    ],
    "sg:phone":"+1 704 525 8485",
    "sg:postcode":"28210",
    "sg:province":"NC",
    "sg:tags":[
        "exploration"
    ],
    "wof:name":"Steel Tape Measuring",
    "wof:placetype":"venue"
},
  "geometry": {"coordinates":[-80.86613699999999,35.159606],"type":"Point"}
}