{
  "type": "Feature",
  "properties": {
    "iso:country":"US",
    "sg:address":"500 Weaver Dairy Rd.",
    "sg:city":"Chapel Hill",
    "sg:classifiers":[
        {
            "category":"Arts & Performance",
            "subcategory":"Festival",
            "type":"Entertainment"
        }
    ],
    "sg:postcode":"27514",
    "sg:province":"NC",
    "sg:website":"stbarbaranc-greekfestival.org/In...",
    "wof:name":"St. Barbara's Greek Festival",
    "wof:placetype":"venue"
},
  "geometry": {"coordinates":[-79.030444,35.959491],"type":"Point"}
}