{
  "type": "Feature",
  "properties": {
    "iso:country":"US",
    "sg:address":"3518 Westgate Dr",
    "sg:city":"Durham",
    "sg:classifiers":[
        {
            "category":"Banks & Credit Unions",
            "subcategory":"Bank",
            "type":"Services"
        }
    ],
    "sg:phone":"+1 919 493 5099",
    "sg:postcode":"27707",
    "sg:province":"NC",
    "sg:tags":[
        "financing"
    ],
    "wof:name":"First Merchants Acceptance",
    "wof:placetype":"venue"
},
  "geometry": {"coordinates":[-78.961135,35.966773],"type":"Point"}
}