{
  "type": "Feature",
  "properties": {
    "iso:country":"US",
    "sg:address":"55 Pine Meadows Pl",
    "sg:city":"Pinehurst",
    "sg:classifiers":[
        {
            "category":"Professional",
            "subcategory":"Art Services",
            "type":"Services"
        }
    ],
    "sg:phone":"+1   ",
    "sg:postcode":"28374",
    "sg:province":"NC",
    "sg:tags":[
        "photography",
        "commercial"
    ],
    "wof:name":"Nielsen Creative Enterpri",
    "wof:placetype":"venue"
},
  "geometry": {"coordinates":[-79.483424,35.184683],"type":"Point"}
}