{
  "type": "Feature",
  "properties": {
    "iso:country":"US",
    "sg:address":"367 Academy Dr",
    "sg:city":"Thomasville",
    "sg:classifiers":[
        {
            "category":"Education",
            "subcategory":"School",
            "type":"Public Place"
        }
    ],
    "sg:phone":"+1 336 472 8950",
    "sg:postcode":"27360",
    "sg:province":"NC",
    "wof:name":"Carolina Christian Academy",
    "wof:placetype":"venue"
},
  "geometry": {"coordinates":[-80.119553,35.817228],"type":"Point"}
}