{
  "type": "Feature",
  "properties": {
    "iso:country":"US",
    "sg:address":"10451 N College St",
    "sg:city":"Clarkton",
    "sg:classifiers":[
        {
            "category":"Shopping",
            "subcategory":"Florist",
            "type":"Retail Goods"
        }
    ],
    "sg:phone":"+1 910 647 0007",
    "sg:postcode":"28433",
    "sg:province":"NC",
    "wof:name":"Dianne S Floral Designs",
    "wof:placetype":"venue"
},
  "geometry": {"coordinates":[-78.655593,34.488096],"type":"Point"}
}