{
  "type": "Feature",
  "properties": {
    "addr:full":"7862 Idlewild Rd Indian Trail NC 28079",
    "addr:housenumber":"7862",
    "addr:postcode":"28079",
    "addr:street":"Idlewild Rd",
    "iso:country":"US",
    "sg:address":"7862 Idlewild Rd",
    "sg:city":"Indian Trail",
    "sg:classifiers":[
        {
            "category":"Shopping",
            "subcategory":"Department Store",
            "type":"Retail Goods"
        }
    ],
    "sg:phone":"+1 704 882 9029",
    "sg:postcode":"28079",
    "sg:province":"NC",
    "wof:name":"Family Dollar Store",
    "wof:placetype":"venue"
},
  "geometry": {"coordinates":[-80.63319300000001,35.105821],"type":"Point"}
}