{
  "type": "Feature",
  "properties": {
    "addr:full":"200 E Northwood St Greensboro NC 27401",
    "addr:housenumber":"200",
    "addr:postcode":"27401",
    "addr:street":"E;St",
    "iso:country":"US",
    "sg:address":"200 E Northwood St",
    "sg:city":"Greensboro",
    "sg:classifiers":[
        {
            "category":"Health Services",
            "subcategory":"Doctor",
            "type":"Services"
        }
    ],
    "sg:phone":"+1 336 379 7711",
    "sg:postcode":"27401",
    "sg:province":"NC",
    "sg:tags":[
        "medical"
    ],
    "wof:name":"Brenner Sub Specialist",
    "wof:placetype":"venue"
},
  "geometry": {"coordinates":[-79.78645400000001,36.089631],"type":"Point"}
}