{
  "type": "Feature",
  "properties": {
    "addr:full":"280 Lewis Iley Tew Rd Dunn NC 28334",
    "addr:housenumber":"280",
    "addr:postcode":"28334",
    "addr:street":"Lewis Iley Tew Rd",
    "iso:country":"US",
    "sg:address":"280 Lewis Iley Tew Rd",
    "sg:city":"Dunn",
    "sg:classifiers":[
        {
            "category":"Restaurant",
            "type":"Food & Drink"
        }
    ],
    "sg:phone":"+1 910 892 6536",
    "sg:postcode":"28334",
    "sg:province":"NC",
    "sg:tags":[
        "caterer"
    ],
    "wof:name":"Elegant Party Rentals-Catering",
    "wof:placetype":"venue"
},
  "geometry": {"coordinates":[-78.55269,35.25191],"type":"Point"}
}