{
  "type": "Feature",
  "properties": {
    "addr:full":"321 N Graham St Charlotte NC 28202",
    "addr:housenumber":"321",
    "addr:postcode":"28202",
    "addr:street":"N Graham St",
    "iso:country":"US",
    "sg:address":"321 N Graham St",
    "sg:city":"Charlotte",
    "sg:classifiers":[
        {
            "category":"Real Estate",
            "subcategory":"Real Estate Agent",
            "type":"Services"
        }
    ],
    "sg:phone":"+1 704 568 4848",
    "sg:postcode":"28202",
    "sg:province":"NC",
    "sg:website":"www.oldecharlotterealty.com",
    "wof:name":"Charlotte Olde Realty",
    "wof:placetype":"venue"
},
  "geometry": {"coordinates":[-80.843929,35.232888],"type":"Point"}
}