{
  "type": "Feature",
  "properties": {
    "addr:full":"217 S Jefferson Ave West Jefferson NC 28694",
    "addr:housenumber":"217",
    "addr:postcode":"28694",
    "addr:street":"S Jefferson Ave",
    "iso:country":"US",
    "sg:address":"217 S Jefferson Ave",
    "sg:city":"West Jefferson",
    "sg:classifiers":[
        {
            "category":"Shopping",
            "subcategory":"Used Merchandise",
            "type":"Retail Goods"
        }
    ],
    "sg:phone":"+1 336 846 1110",
    "sg:postcode":"28694",
    "sg:province":"NC",
    "sg:tags":[
        "antique"
    ],
    "wof:name":"Beaver Creek Antiques",
    "wof:placetype":"venue"
},
  "geometry": {"coordinates":[-81.491699,36.40032],"type":"Point"}
}