{
  "type": "Feature",
  "properties": {
    "addr:full":"1800 W 5th St Greenville NC 27834",
    "addr:housenumber":"1800",
    "addr:postcode":"27834",
    "addr:street":"W 5Th St",
    "iso:country":"US",
    "sg:address":"1800 W 5th St",
    "sg:city":"Greenville",
    "sg:classifiers":[
        {
            "category":"Health Services",
            "subcategory":"Doctor",
            "type":"Services"
        }
    ],
    "sg:phone":"+1 252 744 1959",
    "sg:postcode":"27834",
    "sg:province":"NC",
    "sg:tags":[
        "physician",
        "surgeon"
    ],
    "wof:name":"Bone Denistometry",
    "wof:placetype":"venue"
},
  "geometry": {"coordinates":[-77.395031,35.613116],"type":"Point"}
}