{
  "type": "Feature",
  "properties": {
    "addr:full":"800 Beaty St Davidson NC 28036",
    "addr:housenumber":"800",
    "addr:postcode":"28036",
    "addr:street":"Beaty St",
    "iso:country":"US",
    "sg:address":"800 Beaty St",
    "sg:city":"Davidson",
    "sg:classifiers":[
        {
            "category":"Restaurant",
            "type":"Food & Drink"
        }
    ],
    "sg:phone":"+1 704 896 4455",
    "sg:postcode":"28036",
    "sg:province":"NC",
    "sg:tags":[
        "eating"
    ],
    "wof:name":"Ingersollrand",
    "wof:placetype":"venue"
},
  "geometry": {"coordinates":[-80.84200199999999,35.508652],"type":"Point"}
}