{
  "type": "Feature",
  "properties": {
    "addr:full":"216 W 3rd St Washington NC 27889",
    "addr:housenumber":"216",
    "addr:postcode":"27889",
    "addr:street":"W 3Rd St",
    "iso:country":"US",
    "sg:address":"216 W 3rd St",
    "sg:city":"Washington",
    "sg:classifiers":[
        {
            "category":"Building & Trades",
            "subcategory":"Construction",
            "type":"Services"
        }
    ],
    "sg:phone":"+1 252 946 8866",
    "sg:postcode":"27889",
    "sg:province":"NC",
    "sg:tags":[
        "home",
        "contractor"
    ],
    "wof:name":"Gillko Incorporated",
    "wof:placetype":"venue"
},
  "geometry": {"coordinates":[-77.056521,35.545757],"type":"Point"}
}