{
  "type": "Feature",
  "properties": {
    "iso:country":"US",
    "sg:address":"8431 Old Statesville Rd",
    "sg:city":"Charlotte",
    "sg:classifiers":[
        {
            "category":"Manufacturing",
            "subcategory":"Rubber & Plastics",
            "type":"Manufacturing & Wholesale Goods"
        }
    ],
    "sg:phone":"+1 704 921 9898",
    "sg:postcode":"28269",
    "sg:province":"NC",
    "sg:tags":[
        "polyethylene",
        "material",
        "prod"
    ],
    "wof:name":"Xtreme Custom Surfaces",
    "wof:placetype":"venue"
},
  "geometry": {"coordinates":[-80.824589,35.337342],"type":"Point"}
}