{
  "type": "Feature",
  "properties": {
    "iso:country":"US",
    "sg:address":"5022 Rehobeth Rd",
    "sg:city":"Waxhaw",
    "sg:classifiers":[
        {
            "category":"Building & Trades",
            "subcategory":"Construction",
            "type":"Services"
        }
    ],
    "sg:phone":"+1 704 243 0858",
    "sg:postcode":"28173",
    "sg:province":"NC",
    "sg:tags":[
        "excavation",
        "contractor"
    ],
    "wof:name":"Stoyko Construction",
    "wof:placetype":"venue"
},
  "geometry": {"coordinates":[-80.75676300000001,34.911313],"type":"Point"}
}