{
  "type": "Feature",
  "properties": {
    "iso:country":"US",
    "sg:address":"270 Hogans Rd",
    "sg:city":"Hubert",
    "sg:classifiers":[
        {
            "category":"Manufacturing",
            "subcategory":"Watercraft",
            "type":"Manufacturing & Wholesale Goods"
        }
    ],
    "sg:phone":"+1 910 326 1705",
    "sg:postcode":"28539",
    "sg:province":"NC",
    "sg:tags":[
        "fiberglass",
        "powerboat",
        "mfg"
    ],
    "sg:website":"www.s2yachts.com",
    "wof:name":"Tiara Yachts",
    "wof:placetype":"venue"
},
  "geometry": {"coordinates":[-77.177196,34.647932],"type":"Point"}
}