{
  "type": "Feature",
  "properties": {
    "iso:country":"US",
    "sg:address":"4813 Oberwald Pl",
    "sg:city":"Charlotte",
    "sg:classifiers":[
        {
            "category":"Shopping",
            "subcategory":"Stationery & Office Supplies",
            "type":"Retail Goods"
        }
    ],
    "sg:phone":"+1 704 888 1329",
    "sg:postcode":"28227",
    "sg:province":"NC",
    "sg:tags":[
        "equipment"
    ],
    "wof:name":"Reliable Service",
    "wof:placetype":"venue"
},
  "geometry": {"coordinates":[-80.707678,35.17617],"type":"Point"}
}