{
  "type": "Feature",
  "properties": {
    "addr:full":"1019 Crane Creek Rd Salisbury NC 28146",
    "addr:housenumber":"1019",
    "addr:postcode":"28146",
    "addr:street":"Crane Creek Rd",
    "iso:country":"US",
    "sg:address":"1019 Crane Creek Rd",
    "sg:city":"Salisbury",
    "sg:classifiers":[
        {
            "category":"Building & Trades",
            "subcategory":"Plumbing",
            "type":"Services"
        }
    ],
    "sg:phone":"+1 704 636 4674",
    "sg:postcode":"28146",
    "sg:province":"NC",
    "sg:tags":[
        "contractor"
    ],
    "wof:name":"Christian Ronnie L",
    "wof:placetype":"venue"
},
  "geometry": {"coordinates":[-80.44298000000001,35.659133],"type":"Point"}
}