{
  "type": "Feature",
  "properties": {
    "addr:full":"2211 N Wesleyan Blvd Rocky Mount NC 27804",
    "addr:housenumber":"2211",
    "addr:postcode":"27804",
    "addr:street":"N Wesleyan Blvd",
    "iso:country":"US",
    "sg:address":"2211 N Wesleyan Blvd",
    "sg:city":"Rocky Mount",
    "sg:classifiers":[
        {
            "category":"Wholesale",
            "subcategory":"Machinery & Supplies",
            "type":"Manufacturing & Wholesale Goods"
        }
    ],
    "sg:phone":"+1 252 985 3411",
    "sg:postcode":"27804",
    "sg:province":"NC",
    "sg:tags":[
        "equipment",
        "industrial"
    ],
    "wof:name":"National Welders Supply Co",
    "wof:placetype":"venue"
},
  "geometry": {"coordinates":[-77.778599,35.995098],"type":"Point"}
}