{
  "type": "Feature",
  "properties": {
    "addr:full":"805 Patton Ave Asheville NC 28806",
    "addr:housenumber":"805",
    "addr:postcode":"28806",
    "addr:street":"Patton Ave",
    "iso:country":"US",
    "sg:address":"805 Patton Ave",
    "sg:city":"Asheville",
    "sg:classifiers":[
        {
            "category":"Cinema",
            "subcategory":"Movie Rental",
            "type":"Entertainment"
        }
    ],
    "sg:phone":"+1 828 252 6874",
    "sg:postcode":"28806",
    "sg:province":"NC",
    "sg:tags":[
        "leasing",
        "video",
        "disc",
        "tape"
    ],
    "wof:name":"Blockbuster Video",
    "wof:placetype":"venue"
},
  "geometry": {"coordinates":[-82.58668400000001,35.587633],"type":"Point"}
}