{
  "type": "Feature",
  "properties": {
    "addr:full":"420 S Ashe St Southern Pines NC 28387",
    "addr:housenumber":"420",
    "addr:postcode":"28387",
    "addr:street":"S Ashe St",
    "iso:country":"US",
    "sg:address":"420 S Ashe St",
    "sg:city":"Southern Pines",
    "sg:classifiers":[
        {
            "category":"Social Services",
            "type":"Services"
        }
    ],
    "sg:phone":"+1 910 692 2608",
    "sg:postcode":"28387",
    "sg:province":"NC",
    "sg:tags":[
        "counselor",
        "marriage",
        "family"
    ],
    "wof:name":"Robert L Katrin",
    "wof:placetype":"venue"
},
  "geometry": {"coordinates":[-79.39502,35.170173],"type":"Point"}
}