{
  "type": "Feature",
  "properties": {
    "iso:country":"US",
    "sg:address":"805 W Railroad St",
    "sg:city":"Selma",
    "sg:classifiers":[
        {
            "category":"Shopping",
            "type":"Retail Goods"
        }
    ],
    "sg:phone":"+1 919 975 0096",
    "sg:postcode":"27576",
    "sg:province":"NC",
    "sg:tags":[
        "chemical"
    ],
    "wof:name":"Tomlinson Enterprises",
    "wof:placetype":"venue"
},
  "geometry": {"coordinates":[-78.29356900000001,35.539392],"type":"Point"}
}