{
  "type": "Feature",
  "properties": {
    "addr:full":"9706 Hollystone Ln Charlotte NC 28215",
    "addr:housenumber":"9706",
    "addr:postcode":"28215",
    "addr:street":"Hollystone Ln",
    "iso:country":"US",
    "sg:address":"9706 Hollystone Ln",
    "sg:city":"Charlotte",
    "sg:classifiers":[
        {
            "category":"Retail",
            "subcategory":"Laundry & Dry Cleaning",
            "type":"Services"
        },
        {
            "category":"Building & Trades",
            "subcategory":"Cleaning & Sanitation",
            "type":"Services"
        }
    ],
    "sg:phone":"+1 704 540 4666",
    "sg:postcode":"28215",
    "sg:province":"NC",
    "sg:tags":[
        "cleaner",
        "carpet",
        "rug",
        "house"
    ],
    "wof:name":"My Carpet Cleaner",
    "wof:placetype":"venue"
},
  "geometry": {"coordinates":[-80.712934,35.276904],"type":"Point"}
}