{
  "type": "Feature",
  "properties": {
    "addr:full":"900 W Warren St Shelby NC 28150",
    "addr:housenumber":"900",
    "addr:postcode":"28150",
    "addr:street":"W Warren St",
    "iso:country":"US",
    "sg:address":"900 W Warren St",
    "sg:city":"Shelby",
    "sg:classifiers":[
        {
            "category":"Building & Trades",
            "subcategory":"Equipment Rental",
            "type":"Services"
        }
    ],
    "sg:phone":"+1   ",
    "sg:postcode":"28150",
    "sg:province":"NC",
    "sg:tags":[
        "company",
        "holding",
        "vehicle"
    ],
    "wof:name":"Causby Enterprises",
    "wof:placetype":"venue"
},
  "geometry": {"coordinates":[-81.55929399999999,35.289834],"type":"Point"}
}