{
  "type": "Feature",
  "properties": {
    "addr:full":"300 Copperfield Blvd NE Concord NC 28025",
    "addr:housenumber":"300",
    "addr:postcode":"28025",
    "addr:street":"Copperfield Blvd Ne",
    "iso:country":"US",
    "sg:address":"300 Copperfield Blvd NE",
    "sg:city":"Concord",
    "sg:classifiers":[
        {
            "category":"Organizations",
            "subcategory":"Non-profit Organization",
            "type":"Services"
        },
        {
            "category":"Health Services",
            "subcategory":"Hospital",
            "type":"Services"
        }
    ],
    "sg:phone":"+1 704 782 3131",
    "sg:postcode":"28025",
    "sg:province":"NC",
    "sg:tags":[
        "information",
        "treatment",
        "alcoholism",
        "specialty"
    ],
    "sg:website":"www.mcleodcenter.com",
    "wof:name":"Mc Leod Addictive Disease Ctr",
    "wof:placetype":"venue"
},
  "geometry": {"coordinates":[-80.596886,35.447713],"type":"Point"}
}