{
  "type": "Feature",
  "properties": {
    "addr:full":"1041 Alexwood Dr Hope Mills NC 28348",
    "addr:housenumber":"1041",
    "addr:postcode":"28348",
    "addr:street":"Alexwood Dr",
    "iso:country":"US",
    "sg:address":"1041 Alexwood Dr",
    "sg:city":"Hope Mills",
    "sg:classifiers":[
        {
            "category":"Food & Beverages",
            "subcategory":"Groceries & Convenience Stores",
            "type":"Retail Goods"
        }
    ],
    "sg:phone":"+1 910 423 4556",
    "sg:postcode":"28348",
    "sg:province":"NC",
    "wof:name":"Thrifty Mart",
    "wof:placetype":"venue"
},
  "geometry": {"coordinates":[-78.920086,34.982848],"type":"Point"}
}