{
  "type": "Feature",
  "properties": {
    "addr:full":"4611 Western Blvd Raleigh NC 27606",
    "addr:housenumber":"4611",
    "addr:postcode":"27606",
    "addr:street":"Western Blvd",
    "iso:country":"US",
    "sg:address":"4611 Western Blvd",
    "sg:city":"Raleigh",
    "sg:classifiers":[
        {
            "category":"Social Services",
            "type":"Services"
        }
    ],
    "sg:phone":"+1   ",
    "sg:postcode":"27606",
    "sg:province":"NC",
    "wof:name":"Care Psychthrapy Cnseling Svcs",
    "wof:placetype":"venue"
},
  "geometry": {"coordinates":[-78.702771,35.784709],"type":"Point"}
}