{
  "type": "Feature",
  "properties": {
    "addr:full":"525 Donna Dr Dallas NC 28034",
    "addr:housenumber":"525",
    "addr:postcode":"28034",
    "addr:street":"Donna Dr",
    "iso:country":"US",
    "sg:address":"525 Donna Dr",
    "sg:city":"Dallas",
    "sg:classifiers":[
        {
            "category":"Building & Trades",
            "subcategory":"Construction",
            "type":"Services"
        }
    ],
    "sg:phone":"+1 704 922 9131",
    "sg:postcode":"28034",
    "sg:province":"NC",
    "sg:tags":[
        "house"
    ],
    "wof:name":"Tj Construction of Dallas Inc",
    "wof:placetype":"venue"
},
  "geometry": {"coordinates":[-81.20394400000001,35.369172],"type":"Point"}
}