{
  "type": "Feature",
  "properties": {
    "addr:full":"113 Howard Rd Jacksonville NC 28540",
    "addr:housenumber":"113",
    "addr:postcode":"28540",
    "addr:street":"Howard Rd",
    "iso:country":"US",
    "sg:address":"113 Howard Rd",
    "sg:city":"Jacksonville",
    "sg:classifiers":[
        {
            "category":"Social Services",
            "type":"Services"
        }
    ],
    "sg:phone":"+1 910 554 0321",
    "sg:postcode":"28540",
    "sg:province":"NC",
    "sg:tags":[
        "counseling"
    ],
    "wof:name":"Christopher Hunt Counseling",
    "wof:placetype":"venue"
},
  "geometry": {"coordinates":[-77.48061199999999,34.847002],"type":"Point"}
}