{
  "type": "Feature",
  "properties": {
    "iso:country":"US",
    "sg:address":"405 N Bragg Blvd",
    "sg:city":"Spring Lake",
    "sg:classifiers":[
        {
            "category":"Food & Beverages",
            "subcategory":"Groceries & Convenience Stores",
            "type":"Retail Goods"
        }
    ],
    "sg:phone":"+1 910 436 4638",
    "sg:postcode":"28390",
    "sg:province":"NC",
    "sg:tags":[
        "station",
        "gasoline"
    ],
    "wof:name":"Kangaroo Express",
    "wof:placetype":"venue"
},
  "geometry": {"coordinates":[-78.97483099999999,35.171085],"type":"Point"}
}