{
  "type": "Feature",
  "properties": {
    "addr:full":"2524 Reliance Ave Apex NC 27539",
    "addr:housenumber":"2524",
    "addr:postcode":"27539",
    "addr:street":"Reliance Ave",
    "iso:country":"US",
    "sg:address":"2524 Reliance Ave",
    "sg:city":"Apex",
    "sg:classifiers":[
        {
            "category":"Insurance",
            "subcategory":"Health Insurance",
            "type":"Services"
        }
    ],
    "sg:phone":"+1 919 462 7055",
    "sg:postcode":"27539",
    "sg:province":"NC",
    "sg:tags":[
        "surgical",
        "hospitalization",
        "plan"
    ],
    "wof:name":"Visiontech Partners",
    "wof:placetype":"venue"
},
  "geometry": {"coordinates":[-78.822688,35.714903],"type":"Point"}
}