{
  "type": "Feature",
  "properties": {
    "addr:full":"2227 Cloverdale Ave Winston Salem NC 27103",
    "addr:housenumber":"2227",
    "addr:postcode":"27103",
    "addr:street":"Cloverdale Ave",
    "iso:country":"US",
    "sg:address":"2227 Cloverdale Ave",
    "sg:city":"Winston Salem",
    "sg:classifiers":[
        {
            "category":"Shopping",
            "subcategory":"Clothing, Apparel, & Fashions",
            "type":"Retail Goods"
        }
    ],
    "sg:phone":"+1 336 748 1681",
    "sg:postcode":"27103",
    "sg:province":"NC",
    "sg:tags":[
        "ready"
    ],
    "wof:name":"Mel Brooks Fashions",
    "wof:placetype":"venue"
},
  "geometry": {"coordinates":[-80.27509999999999,36.090197],"type":"Point"}
}