{
  "type": "Feature",
  "properties": {
    "iso:country":"US",
    "sg:address":"2100 Mount Pleasant Rd W",
    "sg:city":"Mt Pleasant",
    "sg:classifiers":[
        {
            "category":"Recreation",
            "type":"Entertainment"
        }
    ],
    "sg:phone":"+1 704 436 2529",
    "sg:postcode":"28124",
    "sg:province":"NC",
    "sg:tags":[
        "amusement"
    ],
    "wof:name":"Clay Hair Motorsports",
    "wof:placetype":"venue"
},
  "geometry": {"coordinates":[-80.465541,35.389016],"type":"Point"}
}