{
  "type": "Feature",
  "properties": {
    "addr:full":"2605 William Allen Rd Burlington NC 27217",
    "addr:housenumber":"2605",
    "addr:postcode":"27217",
    "addr:street":"William Allen Rd",
    "iso:country":"US",
    "sg:address":"2605 William Allen Rd",
    "sg:city":"Burlington",
    "sg:classifiers":[
        {
            "category":"Social Services",
            "subcategory":"Child Care",
            "type":"Services"
        }
    ],
    "sg:phone":"+1   ",
    "sg:postcode":"27217",
    "sg:province":"NC",
    "sg:tags":[
        "day"
    ],
    "wof:name":"Marie S In Home Daycare",
    "wof:placetype":"venue"
},
  "geometry": {"coordinates":[-79.340326,36.153727],"type":"Point"}
}