{
  "type": "Feature",
  "properties": {
    "iso:country":"US",
    "sg:address":"1401 Hoffman Rd",
    "sg:city":"Gastonia",
    "sg:classifiers":[
        {
            "category":"Organizations",
            "subcategory":"Religious Organization",
            "type":"Services"
        }
    ],
    "sg:phone":"+1 704 868 3638",
    "sg:postcode":"28054",
    "sg:province":"NC",
    "sg:tags":[
        "church"
    ],
    "wof:name":"Southminister Weekday School",
    "wof:placetype":"venue"
},
  "geometry": {"coordinates":[-81.14653,35.222229],"type":"Point"}
}