{
  "type": "Feature",
  "properties": {
    "iso:country":"US",
    "sg:address":"145 Berrymore Rd",
    "sg:city":"Reidsville",
    "sg:classifiers":[
        {
            "category":"Building & Trades",
            "subcategory":"Landscaping Services",
            "type":"Services"
        }
    ],
    "sg:phone":"+1 336 342 6596",
    "sg:postcode":"27320",
    "sg:province":"NC",
    "sg:tags":[
        "landscape",
        "contractor"
    ],
    "wof:name":"Kenneth Stone Landscape Cntrct",
    "wof:placetype":"venue"
},
  "geometry": {"coordinates":[-79.686654,36.422239],"type":"Point"}
}