{
  "type": "Feature",
  "properties": {
    "addr:full":"3541 Surveyor St Fayetteville NC 28308",
    "addr:housenumber":"3541",
    "addr:postcode":"28308",
    "addr:street":"Surveyor St",
    "iso:country":"US",
    "sg:address":"3541 Surveyor St",
    "sg:city":"Fayetteville",
    "sg:classifiers":[
        {
            "category":"Government",
            "subcategory":"Office",
            "type":"Public Place"
        }
    ],
    "sg:phone":"+1 910 394 6945",
    "sg:postcode":"28308",
    "sg:province":"NC",
    "sg:tags":[
        "national",
        "security"
    ],
    "wof:name":"41st Airlift Squadron",
    "wof:placetype":"venue"
},
  "geometry": {"coordinates":[-79.024182,35.172368],"type":"Point"}
}