{
  "type": "Feature",
  "properties": {
    "iso:country":"US",
    "sg:address":"611 Martin Luther King Jr Dr",
    "sg:city":"Greensboro",
    "sg:classifiers":[
        {
            "category":"Restaurant",
            "type":"Food & Drink"
        }
    ],
    "sg:phone":"+1 336 274 0456",
    "sg:postcode":"27406",
    "sg:province":"NC",
    "sg:tags":[
        "eating"
    ],
    "sg:website":"www.churchs.com",
    "wof:name":"Church's Chicken",
    "wof:placetype":"venue"
},
  "geometry": {"coordinates":[-79.785186,36.060497],"type":"Point"}
}