{
  "type": "Feature",
  "properties": {
    "iso:country":"US",
    "sg:address":"1720 Westchester Dr",
    "sg:city":"High Point",
    "sg:classifiers":[
        {
            "category":"Health Services",
            "subcategory":"Doctor",
            "type":"Services"
        }
    ],
    "sg:phone":"+1   ",
    "sg:postcode":"27262",
    "sg:province":"NC",
    "sg:tags":[
        "clinic",
        "medical",
        "outpatient",
        "specialty"
    ],
    "wof:name":"High Point Regional Health Sys",
    "wof:placetype":"venue"
},
  "geometry": {"coordinates":[-80.033779,35.947544],"type":"Point"}
}