{
  "type": "Feature",
  "properties": {
    "addr:full":"5447 Brokaw Dr Trinity NC 27370",
    "addr:housenumber":"5447",
    "addr:postcode":"27370",
    "addr:street":"Brokaw Dr",
    "iso:country":"US",
    "sg:address":"5447 Brokaw Dr",
    "sg:city":"Trinity",
    "sg:classifiers":[
        {
            "category":"Organizations",
            "subcategory":"Religious Organization",
            "type":"Services"
        }
    ],
    "sg:phone":"+1 336 431 1539",
    "sg:postcode":"27370",
    "sg:province":"NC",
    "sg:tags":[
        "clergy"
    ],
    "wof:name":"Hearth Kennedy",
    "wof:placetype":"venue"
},
  "geometry": {"coordinates":[-79.98397900000001,35.85541],"type":"Point"}
}