{
  "type": "Feature",
  "properties": {
    "addr:full":"13 Winterberry Way Chapel Hill NC 27516",
    "addr:housenumber":"13",
    "addr:postcode":"27516",
    "addr:street":"Winterberry Way",
    "iso:country":"US",
    "sg:address":"13 Winterberry Way",
    "sg:city":"Chapel Hill",
    "sg:classifiers":[
        {
            "category":"Professional",
            "subcategory":"Computer Services",
            "type":"Services"
        }
    ],
    "sg:phone":"+1   ",
    "sg:postcode":"27516",
    "sg:province":"NC",
    "sg:tags":[
        "business"
    ],
    "wof:name":"Austin Enterprises",
    "wof:placetype":"venue"
},
  "geometry": {"coordinates":[-79.119197,35.84568],"type":"Point"}
}