{
  "type": "Feature",
  "properties": {
    "iso:country":"US",
    "sg:address":"5447 Brantley Gordon Rd",
    "sg:city":"Denton",
    "sg:classifiers":[
        {
            "category":"Building & Trades",
            "subcategory":"Construction",
            "type":"Services"
        }
    ],
    "sg:phone":"+1 336 857 2446",
    "sg:postcode":"27239",
    "sg:province":"NC",
    "sg:tags":[
        "excavating",
        "contractor"
    ],
    "wof:name":"S-R Construction",
    "wof:placetype":"venue"
},
  "geometry": {"coordinates":[-80.00313,35.636814],"type":"Point"}
}