{
  "type": "Feature",
  "properties": {
    "iso:country":"US",
    "sg:address":"4704 South Blvd",
    "sg:city":"Charlotte",
    "sg:classifiers":[
        {
            "category":"Shopping",
            "subcategory":"Computers & Home Electronics",
            "type":"Retail Goods"
        }
    ],
    "sg:phone":"+1 704 529 1548",
    "sg:postcode":"28217",
    "sg:province":"NC",
    "sg:tags":[
        "comp",
        "software"
    ],
    "wof:name":"Electronic Boutique Inc",
    "wof:placetype":"venue"
},
  "geometry": {"coordinates":[-80.876025,35.173885],"type":"Point"}
}