{
  "type": "Feature",
  "properties": {
    "iso:country":"US",
    "sg:address":"200 Farrar Rd",
    "sg:city":"Lillington",
    "sg:phone":"+1 910 893 8214",
    "sg:postcode":"27546",
    "sg:province":"NC",
    "sg:tags":[
        "farm",
        "tobacco",
        "soybean"
    ],
    "wof:name":"Gilbert McPhail",
    "wof:placetype":"venue"
},
  "geometry": {"coordinates":[-78.956114,35.365773],"type":"Point"}
}