{
  "type": "Feature",
  "properties": {
    "iso:country":"US",
    "sg:address":"8605 Stanton Pl",
    "sg:city":"Raleigh",
    "sg:classifiers":[
        {
            "category":"Insurance",
            "subcategory":"Insurance Agent",
            "type":"Services"
        }
    ],
    "sg:phone":"+1 919 676 1008",
    "sg:postcode":"27615",
    "sg:province":"NC",
    "wof:name":"Donnelly Joseph J CLU & Assoc",
    "wof:placetype":"venue"
},
  "geometry": {"coordinates":[-78.66872499999999,35.902839],"type":"Point"}
}