{
  "type": "Feature",
  "properties": {
    "iso:country":"US",
    "sg:address":"730 Lewis St",
    "sg:city":"Oxford",
    "sg:classifiers":[
        {
            "category":"Freight",
            "type":"Transportation"
        }
    ],
    "sg:phone":"+1 919 693 7371",
    "sg:postcode":"27565",
    "sg:province":"NC",
    "sg:tags":[
        "trucking"
    ],
    "wof:name":"Sherman & Boddie Inc",
    "wof:placetype":"venue"
},
  "geometry": {"coordinates":[-78.603925,36.291874],"type":"Point"}
}