{
  "type": "Feature",
  "properties": {
    "addr:full":"147 W Main St Washington NC 27889",
    "addr:housenumber":"147",
    "addr:postcode":"27889",
    "addr:street":"W Main St",
    "iso:country":"US",
    "sg:address":"147 W Main St",
    "sg:city":"Washington",
    "sg:classifiers":[
        {
            "category":"Manufacturing",
            "subcategory":"Printing",
            "type":"Manufacturing & Wholesale Goods"
        }
    ],
    "sg:phone":"+1 252 946 2640",
    "sg:postcode":"27889",
    "sg:province":"NC",
    "sg:tags":[
        "commercial"
    ],
    "wof:name":"Litho Graphix Offset Printing",
    "wof:placetype":"venue"
},
  "geometry": {"coordinates":[-77.055711,35.542222],"type":"Point"}
}