{
  "type": "Feature",
  "properties": {
    "iso:country":"US",
    "sg:address":"5110 S College Rd",
    "sg:city":"Wilmington",
    "sg:classifiers":[
        {
            "category":"Home & Garden",
            "subcategory":"Building Materials",
            "type":"Retail Goods"
        }
    ],
    "sg:phone":"+1 910 397 0137",
    "sg:postcode":"28412",
    "sg:province":"NC",
    "sg:tags":[
        "center"
    ],
    "wof:name":"Lowe's",
    "wof:placetype":"venue"
},
  "geometry": {"coordinates":[-77.892535,34.14737],"type":"Point"}
}