{
  "type": "Feature",
  "properties": {
    "addr:full":"626 Guilford College Rd Greensboro NC 27409",
    "addr:housenumber":"626",
    "addr:postcode":"27409",
    "addr:street":"Guilford College Rd",
    "iso:country":"US",
    "sg:address":"626 Guilford College Rd",
    "sg:city":"Greensboro",
    "sg:classifiers":[
        {
            "category":"Retail",
            "subcategory":"Car Wash",
            "type":"Services"
        }
    ],
    "sg:phone":"+1 336 854 0660",
    "sg:postcode":"27409",
    "sg:province":"NC",
    "sg:tags":[
        "carwash"
    ],
    "wof:name":"Harpers II Exotic Carwash",
    "wof:placetype":"venue"
},
  "geometry": {"coordinates":[-79.906762,36.063883],"type":"Point"}
}