{
  "type": "Feature",
  "properties": {
    "addr:full":"1607 Rankin Lake Rd Gastonia NC 28052",
    "addr:housenumber":"1607",
    "addr:postcode":"28052",
    "addr:street":"Rankin Lake Rd",
    "iso:country":"US",
    "sg:address":"1607 Rankin Lake Rd",
    "sg:city":"Gastonia",
    "sg:classifiers":[
        {
            "category":"Organizations",
            "subcategory":"Religious Organization",
            "type":"Services"
        }
    ],
    "sg:phone":"+1   ",
    "sg:postcode":"28052",
    "sg:province":"NC",
    "wof:name":"Baptist Social Ministries",
    "wof:placetype":"venue"
},
  "geometry": {"coordinates":[-81.19073,35.289546],"type":"Point"}
}