{
  "type": "Feature",
  "properties": {
    "addr:full":"622 S Memorial Dr Greenville NC 27834",
    "addr:housenumber":"622",
    "addr:postcode":"27834",
    "addr:street":"S Memorial Dr",
    "iso:country":"US",
    "sg:address":"622 S Memorial Dr",
    "sg:city":"Greenville",
    "sg:classifiers":[
        {
            "category":"Health Services",
            "subcategory":"Clinic",
            "type":"Services"
        },
        {
            "category":"Health Services",
            "subcategory":"Health Practitioner",
            "type":"Services"
        }
    ],
    "sg:phone":"+1 252 353 4250",
    "sg:postcode":"27834",
    "sg:province":"NC",
    "sg:tags":[
        "psychotherapist"
    ],
    "wof:name":"Cambridge Behavioral Health",
    "wof:placetype":"venue"
},
  "geometry": {"coordinates":[-77.39427499999999,35.609598],"type":"Point"}
}