{
  "type": "Feature",
  "properties": {
    "addr:full":"1204 Clifton St Raleigh NC 27604",
    "addr:housenumber":"1204",
    "addr:postcode":"27604",
    "addr:street":"Clifton St",
    "iso:country":"US",
    "sg:address":"1204 Clifton St",
    "sg:city":"Raleigh",
    "sg:classifiers":[
        {
            "category":"Professional",
            "type":"Services"
        }
    ],
    "sg:phone":"+1   ",
    "sg:postcode":"27604",
    "sg:province":"NC",
    "sg:tags":[
        "writer"
    ],
    "wof:name":"Carla Burgess",
    "wof:placetype":"venue"
},
  "geometry": {"coordinates":[-78.62685,35.794931],"type":"Point"}
}