{
  "type": "Feature",
  "properties": {
    "iso:country":"US",
    "sg:address":"4820 Thacker Dairy Rd",
    "sg:city":"Greensboro",
    "sg:classifiers":[
        {
            "category":"Recreation",
            "type":"Entertainment"
        }
    ],
    "sg:phone":"+1 336 697 0605",
    "sg:postcode":"27406",
    "sg:province":"NC",
    "sg:tags":[
        "riding",
        "horse",
        "instruction",
        "boards"
    ],
    "wof:name":"Fellowship Farm",
    "wof:placetype":"venue"
},
  "geometry": {"coordinates":[-79.693617,36.023974],"type":"Point"}
}