{
  "type": "Feature",
  "properties": {
    "iso:country":"US",
    "sg:address":"5766 Rockfish Rd",
    "sg:city":"Hope Mills",
    "sg:classifiers":[
        {
            "category":"Building & Trades",
            "subcategory":"Construction",
            "type":"Services"
        }
    ],
    "sg:phone":"+1 910 425 4560",
    "sg:postcode":"28348",
    "sg:province":"NC",
    "sg:tags":[
        "contractor"
    ],
    "wof:name":"M & E Contracting Co",
    "wof:placetype":"venue"
},
  "geometry": {"coordinates":[-78.957204,34.97266],"type":"Point"}
}