{
  "type": "Feature",
  "properties": {
    "addr:full":"8523 Woodhill Manor Ct Charlotte NC 28215",
    "addr:housenumber":"8523",
    "addr:postcode":"28215",
    "addr:street":"Woodhill Manor Ct",
    "iso:country":"US",
    "sg:address":"8523 Woodhill Manor Ct",
    "sg:city":"Charlotte",
    "sg:classifiers":[
        {
            "category":"Professional",
            "subcategory":"Business Services",
            "type":"Services"
        }
    ],
    "sg:phone":"+1   ",
    "sg:postcode":"28215",
    "sg:province":"NC",
    "wof:name":"Impact Finish Group",
    "wof:placetype":"venue"
},
  "geometry": {"coordinates":[-80.668188,35.251957],"type":"Point"}
}