{
  "type": "Feature",
  "properties": {
    "addr:full":"843 Foreman Bundy Rd Elizabeth City NC 27909",
    "addr:housenumber":"843",
    "addr:postcode":"27909",
    "addr:street":"Foreman Bundy Rd",
    "iso:country":"US",
    "sg:address":"843 Foreman Bundy Rd",
    "sg:city":"Elizabeth City",
    "sg:classifiers":[
        {
            "category":"Wholesale",
            "subcategory":"Farm Supplies",
            "type":"Manufacturing & Wholesale Goods"
        }
    ],
    "sg:phone":"+1 252 426 5224",
    "sg:postcode":"27909",
    "sg:province":"NC",
    "wof:name":"Royster-Clark",
    "wof:placetype":"venue"
},
  "geometry": {"coordinates":[-76.32052899999999,36.272365],"type":"Point"}
}