{
  "type": "Feature",
  "properties": {
    "iso:country":"US",
    "sg:address":"5681 Hull Rd",
    "sg:city":"La Grange",
    "sg:classifiers":[
        {
            "category":"Building & Trades",
            "subcategory":"Construction",
            "type":"Services"
        }
    ],
    "sg:phone":"+1 252 747 5320",
    "sg:postcode":"28551",
    "sg:province":"NC",
    "sg:tags":[
        "water",
        "well",
        "drilling"
    ],
    "wof:name":"Cunningham Well Drilling",
    "wof:placetype":"venue"
},
  "geometry": {"coordinates":[-77.713112,35.380949],"type":"Point"}
}