{
  "type": "Feature",
  "properties": {
    "iso:country":"US",
    "sg:address":"575 Dogwood St SE",
    "sg:city":"Concord",
    "sg:classifiers":[
        {
            "category":"Professional",
            "type":"Services"
        }
    ],
    "sg:phone":"+1 704 784 5527",
    "sg:postcode":"28025",
    "sg:province":"NC",
    "wof:name":"Jim Rothwell",
    "wof:placetype":"venue"
},
  "geometry": {"coordinates":[-80.556192,35.404149],"type":"Point"}
}