{
  "type": "Feature",
  "properties": {
    "iso:country":"US",
    "sg:address":"709 Catawba St",
    "sg:city":"Belmont",
    "sg:classifiers":[
        {
            "category":"Retail",
            "subcategory":"Self-service Laundry",
            "type":"Services"
        }
    ],
    "sg:phone":"+1   ",
    "sg:postcode":"28012",
    "sg:province":"NC",
    "sg:tags":[
        "coin"
    ],
    "wof:name":"A & M Laundry",
    "wof:placetype":"venue"
},
  "geometry": {"coordinates":[-81.022212,35.241181],"type":"Point"}
}