{
  "type": "Feature",
  "properties": {
    "addr:full":"1774 Saint James Church Rd Denver NC 28037",
    "addr:housenumber":"1774",
    "addr:postcode":"28037",
    "addr:street":"Saint James Church Rd",
    "iso:country":"US",
    "sg:address":"1774 Saint James Church Rd",
    "sg:city":"Denver",
    "sg:classifiers":[
        {
            "category":"Education",
            "subcategory":"School",
            "type":"Public Place"
        }
    ],
    "sg:phone":"+1 704 736 1958",
    "sg:postcode":"28037",
    "sg:province":"NC",
    "sg:website":"www.lincoln.k12.nc.us",
    "wof:name":"St James Elementary School",
    "wof:placetype":"venue"
},
  "geometry": {"coordinates":[-81.019509,35.486481],"type":"Point"}
}