{
  "type": "Feature",
  "properties": {
    "iso:country":"US",
    "sg:address":"107 S Bladen Ave",
    "sg:city":"Garland",
    "sg:classifiers":[
        {
            "category":"Government",
            "subcategory":"Post Office",
            "type":"Public Place"
        }
    ],
    "sg:phone":"+1 910 529 4961",
    "sg:postcode":"28441",
    "sg:province":"NC",
    "wof:name":"US Post Office",
    "wof:placetype":"venue"
},
  "geometry": {"coordinates":[-78.39410700000001,34.784506],"type":"Point"}
}