{
  "type": "Feature",
  "properties": {
    "iso:country":"US",
    "sg:address":"5101 Bass Chapel Rd",
    "sg:city":"Greensboro",
    "sg:classifiers":[
        {
            "category":"Professional",
            "type":"Services"
        }
    ],
    "sg:phone":"+1 336 288 3551",
    "sg:postcode":"27455",
    "sg:province":"NC",
    "wof:name":"Rev Willie Napper",
    "wof:placetype":"venue"
},
  "geometry": {"coordinates":[-79.824156,36.159955],"type":"Point"}
}