{
  "type": "Feature",
  "properties": {
    "iso:country":"US",
    "sg:address":"4131 E 10th St",
    "sg:city":"Greenville",
    "sg:classifiers":[
        {
            "category":"Building & Trades",
            "subcategory":"Construction",
            "type":"Services"
        }
    ],
    "sg:phone":"+1 252 754 2368",
    "sg:postcode":"27858",
    "sg:province":"NC",
    "sg:tags":[
        "home",
        "improvement"
    ],
    "wof:name":"Affordable Improvements",
    "wof:placetype":"venue"
},
  "geometry": {"coordinates":[-77.313993,35.585688],"type":"Point"}
}