{
  "type": "Feature",
  "properties": {
    "iso:country":"US",
    "sg:address":"104 Leonard Dr",
    "sg:city":"Greensboro",
    "sg:classifiers":[
        {
            "category":"Home & Garden",
            "subcategory":"Home Furnishings",
            "type":"Retail Goods"
        }
    ],
    "sg:phone":"+1 336 299 0421",
    "sg:postcode":"27410",
    "sg:province":"NC",
    "sg:tags":[
        "housewares"
    ],
    "wof:name":"Ibolili",
    "wof:placetype":"venue"
},
  "geometry": {"coordinates":[-79.869863,36.085676],"type":"Point"}
}