{
  "type": "Feature",
  "properties": {
    "addr:full":"31 Allen St Sylva NC 28779",
    "addr:housenumber":"31",
    "addr:postcode":"28779",
    "addr:street":"Allen St",
    "iso:country":"US",
    "sg:address":"31 Allen St",
    "sg:city":"Sylva",
    "sg:classifiers":[
        {
            "category":"Organizations",
            "subcategory":"Religious Organization",
            "type":"Services"
        }
    ],
    "sg:phone":"+1 828 631 9322",
    "sg:postcode":"28779",
    "sg:province":"NC",
    "sg:tags":[
        "church"
    ],
    "sg:website":"www.lifewaycommunitychurch.com",
    "wof:name":"Lifeway Community Church",
    "wof:placetype":"venue"
},
  "geometry": {"coordinates":[-83.222695,35.375437],"type":"Point"}
}