{
  "type": "Feature",
  "properties": {
    "iso:country":"US",
    "sg:address":"111 W 10th St",
    "sg:city":"Roanoke Rapids",
    "sg:classifiers":[
        {
            "category":"Organizations",
            "subcategory":"Non-profit Organization",
            "type":"Services"
        },
        {
            "category":"Organizations",
            "subcategory":"Membership Organization",
            "type":"Services"
        }
    ],
    "sg:phone":"+1 252 519 4357",
    "sg:postcode":"27870",
    "sg:province":"NC",
    "sg:tags":[
        "alternative",
        "abortion"
    ],
    "wof:name":"Pregnancy Support Center",
    "wof:placetype":"venue"
},
  "geometry": {"coordinates":[-77.657708,36.4563],"type":"Point"}
}