{
  "type": "Feature",
  "properties": {
    "iso:country":"US",
    "sg:address":"2305 Wellington Dr SW",
    "sg:city":"Wilson",
    "sg:classifiers":[
        {
            "category":"Local Transit",
            "type":"Transportation"
        }
    ],
    "sg:phone":"+1 252 246 9222",
    "sg:postcode":"27893",
    "sg:province":"NC",
    "sg:website":"www.callcpc.com",
    "wof:name":"CPC Logistics",
    "wof:placetype":"venue"
},
  "geometry": {"coordinates":[-77.947391,35.719543],"type":"Point"}
}