{
  "type": "Feature",
  "properties": {
    "iso:country":"US",
    "sg:address":"104 Lakeshore Dr",
    "sg:city":"Asheville",
    "sg:classifiers":[
        {
            "category":"Wholesale",
            "subcategory":"Computers",
            "type":"Manufacturing & Wholesale Goods"
        }
    ],
    "sg:phone":"+1 828 251 1500",
    "sg:postcode":"28804",
    "sg:province":"NC",
    "wof:name":"Seneca Data Corp",
    "wof:placetype":"venue"
},
  "geometry": {"coordinates":[-82.55588400000001,35.629481],"type":"Point"}
}