{
  "type": "Feature",
  "properties": {
    "addr:full":"106 Wakefield St Raleigh NC 27603",
    "addr:housenumber":"106",
    "addr:postcode":"27603",
    "addr:street":"Wakefield St",
    "iso:country":"US",
    "sg:address":"106 Wakefield St",
    "sg:city":"Raleigh",
    "sg:classifiers":[
        {
            "category":"Manufacturing",
            "subcategory":"Metals",
            "type":"Manufacturing & Wholesale Goods"
        }
    ],
    "sg:phone":"+1 919 828 9396",
    "sg:postcode":"27603",
    "sg:province":"NC",
    "wof:name":"Webco Inc",
    "wof:placetype":"venue"
},
  "geometry": {"coordinates":[-78.657347,35.781543],"type":"Point"}
}