{
  "type": "Feature",
  "properties": {
    "addr:full":"135 Industrial Ave Greensboro NC 27406",
    "addr:housenumber":"135",
    "addr:postcode":"27406",
    "addr:street":"Industrial Ave",
    "iso:country":"US",
    "sg:address":"135 Industrial Ave",
    "sg:city":"Greensboro",
    "sg:classifiers":[
        {
            "category":"Organizations",
            "subcategory":"Religious Organization",
            "type":"Services"
        }
    ],
    "sg:phone":"+1 336 333 9367",
    "sg:postcode":"27406",
    "sg:province":"NC",
    "sg:tags":[
        "church"
    ],
    "wof:name":"Ambassador For Christ",
    "wof:placetype":"venue"
},
  "geometry": {"coordinates":[-79.787018,36.029125],"type":"Point"}
}