{
  "type": "Feature",
  "properties": {
    "iso:country":"US",
    "sg:address":"860 Aviation Pkwy",
    "sg:city":"Morrisville",
    "sg:classifiers":[
        {
            "category":"Professional",
            "subcategory":"Business Services",
            "type":"Services"
        }
    ],
    "sg:phone":"+1 919 459 5858",
    "sg:postcode":"27560",
    "sg:province":"NC",
    "sg:tags":[
        "conference",
        "coordinator",
        "seminar"
    ],
    "wof:name":"Lulu Technology Circus",
    "wof:placetype":"venue"
},
  "geometry": {"coordinates":[-78.813006,35.835162],"type":"Point"}
}