{
  "type": "Feature",
  "properties": {
    "iso:country":"US",
    "sg:address":"1927 Bragg St",
    "sg:city":"Sanford",
    "sg:classifiers":[
        {
            "category":"Shopping",
            "subcategory":"Tobacco",
            "type":"Retail Goods"
        }
    ],
    "sg:phone":"+1 919 775 2085",
    "sg:postcode":"27330",
    "sg:province":"NC",
    "sg:tags":[
        "cigarette",
        "cigar",
        "dealer"
    ],
    "sg:website":"www.cheapcig.com",
    "wof:name":"Tobacco Road Outlet",
    "wof:placetype":"venue"
},
  "geometry": {"coordinates":[-79.151961,35.467397],"type":"Point"}
}