{
  "type": "Feature",
  "properties": {
    "addr:full":"19 Whitaker Pl Thomasville NC 27360",
    "addr:housenumber":"19",
    "addr:postcode":"27360",
    "addr:street":"Whitaker Pl",
    "iso:country":"US",
    "sg:address":"19 Whitaker Pl",
    "sg:city":"Thomasville",
    "sg:classifiers":[
        {
            "category":"Building & Trades",
            "subcategory":"Electrical",
            "type":"Services"
        }
    ],
    "sg:phone":"+1 336 884 7298",
    "sg:postcode":"27360",
    "sg:province":"NC",
    "sg:tags":[
        "electrical",
        "contractor"
    ],
    "wof:name":"Barry Marsh Electrical Works",
    "wof:placetype":"venue"
},
  "geometry": {"coordinates":[-80.071899,35.925879],"type":"Point"}
}