{
  "type": "Feature",
  "properties": {
    "addr:full":"3415 Cottage Pl Greensboro NC 27455",
    "addr:housenumber":"3415",
    "addr:postcode":"27455",
    "addr:street":"Cottage Pl",
    "iso:country":"US",
    "sg:address":"3415 Cottage Pl",
    "sg:city":"Greensboro",
    "sg:classifiers":[
        {
            "category":"Social Services",
            "type":"Services"
        }
    ],
    "sg:phone":"+1 336 288 7685",
    "sg:postcode":"27455",
    "sg:province":"NC",
    "wof:name":"Vision Youth Group Home Inc",
    "wof:placetype":"venue"
},
  "geometry": {"coordinates":[-79.842517,36.136449],"type":"Point"}
}