{
  "type": "Feature",
  "properties": {
    "addr:full":"4600 Swan Meadow Ln Charlotte NC 28226",
    "addr:housenumber":"4600",
    "addr:postcode":"28226",
    "addr:street":"Swan Meadow Ln",
    "iso:country":"US",
    "sg:address":"4600 Swan Meadow Ln",
    "sg:city":"Charlotte",
    "sg:classifiers":[
        {
            "category":"Real Estate",
            "subcategory":"Real Estate Operator",
            "type":"Services"
        }
    ],
    "sg:phone":"+1 704 542 2200",
    "sg:postcode":"28226",
    "sg:province":"NC",
    "sg:tags":[
        "apartment"
    ],
    "wof:name":"Swan Run Duplexes & Apartments",
    "wof:placetype":"venue"
},
  "geometry": {"coordinates":[-80.788746,35.10473],"type":"Point"}
}