{
  "type": "Feature",
  "properties": {
    "addr:full":"8816 Running Oak Dr Raleigh NC 27617",
    "addr:housenumber":"8816",
    "addr:postcode":"27617",
    "addr:street":"Running Oak Dr",
    "iso:country":"US",
    "sg:address":"8816 Running Oak Dr",
    "sg:city":"Raleigh",
    "sg:classifiers":[
        {
            "category":"Autos & Motor Vehicles",
            "subcategory":"Boat Sales",
            "type":"Retail Goods"
        },
        {
            "category":"Professional",
            "type":"Services"
        }
    ],
    "sg:phone":"+1 919 861 6550",
    "sg:postcode":"27617",
    "sg:province":"NC",
    "sg:tags":[
        "dealer",
        "sales"
    ],
    "wof:name":"D C One Marine & Motorsports",
    "wof:placetype":"venue"
},
  "geometry": {"coordinates":[-78.759337,35.904821],"type":"Point"}
}