{
  "type": "Feature",
  "properties": {
    "addr:full":"1641 Rayland Dr Hickory NC 28601",
    "addr:housenumber":"1641",
    "addr:postcode":"28601",
    "addr:street":"Rayland Dr",
    "iso:country":"US",
    "sg:address":"1641 Rayland Dr",
    "sg:city":"Hickory",
    "sg:classifiers":[
        {
            "category":"Food & Beverages",
            "subcategory":"Groceries & Convenience Stores",
            "type":"Retail Goods"
        }
    ],
    "sg:phone":"+1 828 327 4353",
    "sg:postcode":"28601",
    "sg:province":"NC",
    "sg:tags":[
        "grocer"
    ],
    "wof:name":"Sweetwater Curb Market",
    "wof:placetype":"venue"
},
  "geometry": {"coordinates":[-81.245317,35.731409],"type":"Point"}
}