{
  "type": "Feature",
  "properties": {
    "addr:full":"2358 Springs Rd NE Hickory NC 28601",
    "addr:housenumber":"2358",
    "addr:postcode":"28601",
    "addr:street":"Springs Rd Ne",
    "iso:country":"US",
    "sg:address":"2358 Springs Rd NE",
    "sg:city":"Hickory",
    "sg:classifiers":[
        {
            "category":"Restaurant",
            "type":"Food & Drink"
        }
    ],
    "sg:phone":"+1 828 256 9822",
    "sg:postcode":"28601",
    "sg:province":"NC",
    "sg:tags":[
        "eating"
    ],
    "wof:name":"Pizza Hut",
    "wof:placetype":"venue"
},
  "geometry": {"coordinates":[-81.290944,35.746816],"type":"Point"}
}