{
  "type": "Feature",
  "properties": {
    "addr:full":"5655 Mineral Springs Mountain Rd Connellys Springs NC 28612",
    "addr:housenumber":"5655",
    "addr:postcode":"28612",
    "addr:street":"Mineral Springs Mountain Rd Connellys Springs",
    "iso:country":"US",
    "sg:address":"5655 Mineral Springs Mountain Rd",
    "sg:city":"Connellys Springs",
    "sg:classifiers":[
        {
            "category":"Autos & Motor Vehicles",
            "subcategory":"Auto Supplies",
            "type":"Retail Goods"
        }
    ],
    "sg:phone":"+1 828 879 8595",
    "sg:postcode":"28612",
    "sg:province":"NC",
    "wof:name":"Lowmans Service Station & Gar",
    "wof:placetype":"venue"
},
  "geometry": {"coordinates":[-81.526628,35.667406],"type":"Point"}
}