{
  "type": "Feature",
  "properties": {
    "iso:country":"US",
    "sg:address":"3205 State Hwy 62",
    "sg:city":"Burlington",
    "sg:classifiers":[
        {
            "category":"Professional",
            "type":"Services"
        }
    ],
    "sg:phone":"+1 919 437 8858",
    "sg:postcode":"27217",
    "sg:province":"NC",
    "sg:tags":[
        "establishment"
    ],
    "wof:name":"Dancer's Dressing Room",
    "wof:placetype":"venue"
},
  "geometry": {"coordinates":[-79.40692,36.153847],"type":"Point"}
}