{
  "type": "Feature",
  "properties": {
    "addr:full":"827 E Sugar Creek Rd Charlotte NC 28205",
    "addr:housenumber":"827",
    "addr:postcode":"28205",
    "addr:street":"E Sugar Creek Rd",
    "iso:country":"US",
    "sg:address":"827 E Sugar Creek Rd",
    "sg:city":"Charlotte",
    "sg:classifiers":[
        {
            "category":"Organizations",
            "subcategory":"Religious Organization",
            "type":"Services"
        }
    ],
    "sg:phone":"+1   ",
    "sg:postcode":"28205",
    "sg:province":"NC",
    "wof:name":"Zion Primitive Baptist Church",
    "wof:placetype":"venue"
},
  "geometry": {"coordinates":[-80.790132,35.249997],"type":"Point"}
}