{
  "type": "Feature",
  "properties": {
    "iso:country":"US",
    "sg:address":"28 New Castle Pl",
    "sg:city":"Pinehurst",
    "sg:classifiers":[
        {
            "category":"Insurance",
            "subcategory":"Insurance Agent",
            "type":"Services"
        }
    ],
    "sg:phone":"+1 910 215 6180",
    "sg:postcode":"28374",
    "sg:province":"NC",
    "wof:name":"Teri Elmore",
    "wof:placetype":"venue"
},
  "geometry": {"coordinates":[-79.506021,35.204156],"type":"Point"}
}