{
  "type": "Feature",
  "properties": {
    "addr:full":"6731 Johnson Mill Rd Durham NC 27712",
    "addr:housenumber":"6731",
    "addr:postcode":"27712",
    "addr:street":"Johnson Mill Rd",
    "iso:country":"US",
    "sg:address":"6731 Johnson Mill Rd",
    "sg:city":"Durham",
    "sg:classifiers":[
        {
            "category":"Professional",
            "subcategory":"Accounting & Tax Preparation",
            "type":"Services"
        }
    ],
    "sg:phone":"+1 919 471 2621",
    "sg:postcode":"27712",
    "sg:province":"NC",
    "sg:tags":[
        "accountant"
    ],
    "wof:name":"Barefoot Art CPA",
    "wof:placetype":"venue"
},
  "geometry": {"coordinates":[-78.91734099999999,36.126792],"type":"Point"}
}