{
  "type": "Feature",
  "properties": {
    "iso:country":"US",
    "sg:address":"204 N McDaniel St",
    "sg:city":"Enfield",
    "sg:classifiers":[
        {
            "category":"Retail",
            "subcategory":"Auto Repair",
            "type":"Services"
        }
    ],
    "sg:phone":"+1 252 445 1600",
    "sg:postcode":"27823",
    "sg:province":"NC",
    "sg:tags":[
        "alternator",
        "generator"
    ],
    "wof:name":"Mc Daniel's Alternator",
    "wof:placetype":"venue"
},
  "geometry": {"coordinates":[-77.66235399999999,36.181319],"type":"Point"}
}