{
  "type": "Feature",
  "properties": {
    "iso:country":"US",
    "sg:address":"1121 E Whitaker Mill Rd",
    "sg:city":"Raleigh",
    "sg:classifiers":[
        {
            "category":"Professional",
            "subcategory":"Employment Agencies",
            "type":"Services"
        }
    ],
    "sg:phone":"+1 919 835 1701",
    "sg:postcode":"27604",
    "sg:province":"NC",
    "sg:tags":[
        "opportunity"
    ],
    "wof:name":"Elite Staffing",
    "wof:placetype":"venue"
},
  "geometry": {"coordinates":[-78.620867,35.807269],"type":"Point"}
}