{
  "type": "Feature",
  "properties": {
    "addr:full":"112 N Old Statesville Rd Huntersville NC 28078",
    "addr:housenumber":"112",
    "addr:postcode":"28078",
    "addr:street":"N Old Statesville Rd",
    "iso:country":"US",
    "sg:address":"112 N Old Statesville Rd",
    "sg:city":"Huntersville",
    "sg:classifiers":[
        {
            "category":"Real Estate",
            "subcategory":"Real Estate Agent",
            "type":"Services"
        }
    ],
    "sg:phone":"+1 704 948 9869",
    "sg:postcode":"28078",
    "sg:province":"NC",
    "wof:name":"Home Ventures Realty",
    "wof:placetype":"venue"
},
  "geometry": {"coordinates":[-80.84312199999999,35.413856],"type":"Point"}
}