{
  "type": "Feature",
  "properties": {
    "iso:country":"US",
    "sg:address":"439 W Kings Hwy",
    "sg:city":"Eden",
    "sg:classifiers":[
        {
            "category":"Social Services",
            "type":"Services"
        }
    ],
    "sg:phone":"+1 336 623 1800",
    "sg:postcode":"27288",
    "sg:province":"NC",
    "sg:tags":[
        "counselor",
        "marriage",
        "family"
    ],
    "wof:name":"Center For Counseling",
    "wof:placetype":"venue"
},
  "geometry": {"coordinates":[-79.75674600000001,36.490595],"type":"Point"}
}