{
  "type": "Feature",
  "properties": {
    "iso:country":"US",
    "sg:address":"1615 Fairway Dr",
    "sg:city":"Newton",
    "sg:classifiers":[
        {
            "category":"Building & Trades",
            "subcategory":"Construction",
            "type":"Services"
        }
    ],
    "sg:phone":"+1 828 464 2345",
    "sg:postcode":"28658",
    "sg:province":"NC",
    "sg:tags":[
        "house"
    ],
    "wof:name":"Buchanan Construction & Design",
    "wof:placetype":"venue"
},
  "geometry": {"coordinates":[-81.28540700000001,35.656858],"type":"Point"}
}