{
  "type": "Feature",
  "properties": {
    "addr:full":"1829 E Franklin St Ste 700A Chapel Hill NC 27514",
    "addr:housenumber":"1829;700a",
    "addr:postcode":"27514",
    "addr:street":"E Franklin St Ste",
    "iso:country":"US",
    "sg:address":"1829 E Franklin St Ste 700A",
    "sg:city":"Chapel Hill",
    "sg:classifiers":[
        {
            "category":"Health Services",
            "subcategory":"Clinic",
            "type":"Services"
        }
    ],
    "sg:phone":"+1 919 942 8097",
    "sg:postcode":"27514",
    "sg:province":"NC",
    "sg:tags":[
        "counseling",
        "mental"
    ],
    "sg:website":"www.StephenHawthorneLCSW.com",
    "wof:name":"Hawthorne Stephen, LCSW",
    "wof:placetype":"venue"
},
  "geometry": {"coordinates":[-79.024744,35.938614],"type":"Point"}
}