{
  "type": "Feature",
  "properties": {
    "addr:full":"1002 N Pitt St Greenville NC 27834",
    "addr:housenumber":"1002",
    "addr:postcode":"27834",
    "addr:street":"N Pitt St",
    "iso:country":"US",
    "sg:address":"1002 N Pitt St",
    "sg:city":"Greenville",
    "sg:classifiers":[
        {
            "category":"Wholesale",
            "subcategory":"Groceries",
            "type":"Manufacturing & Wholesale Goods"
        }
    ],
    "sg:phone":"+1 252 695 6291",
    "sg:postcode":"27834",
    "sg:province":"NC",
    "sg:tags":[
        "beverage"
    ],
    "wof:name":"Carolina Beverage Co",
    "wof:placetype":"venue"
},
  "geometry": {"coordinates":[-77.372254,35.627819],"type":"Point"}
}