{
  "type": "Feature",
  "properties": {
    "iso:country":"US",
    "sg:address":"4323 Ben Franklin Blvd",
    "sg:city":"Durham",
    "sg:classifiers":[
        {
            "category":"Health Services",
            "subcategory":"Doctor",
            "type":"Services"
        }
    ],
    "sg:phone":"+1   ",
    "sg:postcode":"27704",
    "sg:province":"NC",
    "sg:tags":[
        "medical"
    ],
    "wof:name":"Regional Hematology Oncol",
    "wof:placetype":"venue"
},
  "geometry": {"coordinates":[-78.892456,36.047807],"type":"Point"}
}