{
  "type": "Feature",
  "properties": {
    "iso:country":"US",
    "sg:address":"3502 Wrightsville Ave",
    "sg:city":"Wilmington",
    "sg:classifiers":[
        {
            "category":"Insurance",
            "subcategory":"Insurance Agent",
            "type":"Services"
        }
    ],
    "sg:phone":"+1 910 452 9877",
    "sg:postcode":"28403",
    "sg:province":"NC",
    "wof:name":"Ronald G Phelps",
    "wof:placetype":"venue"
},
  "geometry": {"coordinates":[-77.899907,34.221733],"type":"Point"}
}