{
  "type": "Feature",
  "properties": {
    "addr:full":"5823 Nello Dr Hickory NC 28602",
    "addr:housenumber":"5823",
    "addr:postcode":"28602",
    "addr:street":"Nello Dr",
    "iso:country":"US",
    "sg:address":"5823 Nello Dr",
    "sg:city":"Hickory",
    "sg:classifiers":[
        {
            "category":"Freight",
            "type":"Transportation"
        }
    ],
    "sg:phone":"+1 828 294 0888",
    "sg:postcode":"28602",
    "sg:province":"NC",
    "sg:tags":[
        "operator",
        "local",
        "trucking"
    ],
    "wof:name":"Jerry Whitner Inc",
    "wof:placetype":"venue"
},
  "geometry": {"coordinates":[-81.381647,35.682167],"type":"Point"}
}