{
  "type": "Feature",
  "properties": {
    "addr:full":"2110 Cokey Rd Rocky Mount NC 27801",
    "addr:housenumber":"2110",
    "addr:postcode":"27801",
    "addr:street":"Cokey Rd",
    "iso:country":"US",
    "sg:address":"2110 Cokey Rd",
    "sg:city":"Rocky Mount",
    "sg:classifiers":[
        {
            "category":"Professional",
            "subcategory":"Business Services",
            "type":"Services"
        }
    ],
    "sg:phone":"+1 252 446 1533",
    "sg:postcode":"27801",
    "sg:province":"NC",
    "sg:tags":[
        "interior",
        "consultant",
        "design",
        "decorator"
    ],
    "wof:name":"Bill Thomas Assoc Inc",
    "wof:placetype":"venue"
},
  "geometry": {"coordinates":[-77.772688,35.92012],"type":"Point"}
}