{
  "type": "Feature",
  "properties": {
    "addr:full":"9851 Corrystone Dr Charlotte NC 28277",
    "addr:housenumber":"9851",
    "addr:postcode":"28277",
    "addr:street":"Corrystone Dr",
    "iso:country":"US",
    "sg:address":"9851 Corrystone Dr",
    "sg:city":"Charlotte",
    "sg:classifiers":[
        {
            "category":"Manufacturing",
            "subcategory":"Building Materials",
            "type":"Manufacturing & Wholesale Goods"
        }
    ],
    "sg:phone":"+1 704 752 7600",
    "sg:postcode":"28277",
    "sg:province":"NC",
    "sg:tags":[
        "mfg",
        "wood",
        "kitchen",
        "cabinet"
    ],
    "wof:name":"Artistic Cabinet Design Co",
    "wof:placetype":"venue"
},
  "geometry": {"coordinates":[-80.832696,35.040038],"type":"Point"}
}