{
  "type": "Feature",
  "properties": {
    "iso:country":"US",
    "sg:address":"2505 N Main St",
    "sg:city":"High Point",
    "sg:classifiers":[
        {
            "category":"Restaurant",
            "type":"Food & Drink"
        }
    ],
    "sg:phone":"+1 336 884 0822",
    "sg:postcode":"27262",
    "sg:province":"NC",
    "sg:tags":[
        "parlor",
        "ice",
        "cream"
    ],
    "wof:name":"Sno Biz Treats",
    "wof:placetype":"venue"
},
  "geometry": {"coordinates":[-80.02833699999999,35.990719],"type":"Point"}
}