{
  "type": "Feature",
  "properties": {
    "iso:country":"US",
    "sg:address":"404 W Fleming Dr",
    "sg:city":"Morganton",
    "sg:classifiers":[
        {
            "category":"Shopping",
            "subcategory":"Clothing, Apparel, & Fashions",
            "type":"Retail Goods"
        }
    ],
    "sg:phone":"+1 828 430 9900",
    "sg:postcode":"28655",
    "sg:province":"NC",
    "sg:tags":[
        "uniform"
    ],
    "wof:name":"Debi's Uniforms",
    "wof:placetype":"venue"
},
  "geometry": {"coordinates":[-81.684586,35.734596],"type":"Point"}
}