{
  "type": "Feature",
  "properties": {
    "addr:full":"101 Village Walk W Lumberton NC 28358",
    "addr:housenumber":"101",
    "addr:postcode":"28358",
    "addr:street":"Village Walk W",
    "iso:country":"US",
    "sg:address":"101 Village Walk W",
    "sg:city":"Lumberton",
    "sg:classifiers":[
        {
            "category":"Personal",
            "subcategory":"Tanning Parlor",
            "type":"Services"
        }
    ],
    "sg:phone":"+1 910 739 1130",
    "sg:postcode":"28358",
    "sg:province":"NC",
    "sg:tags":[
        "salon"
    ],
    "wof:name":"Stubbo's Tanning",
    "wof:placetype":"venue"
},
  "geometry": {"coordinates":[-78.99696299999999,34.662333],"type":"Point"}
}