{
  "type": "Feature",
  "properties": {
    "addr:full":"909 Martin Ave Graham NC 27253",
    "addr:housenumber":"909",
    "addr:postcode":"27253",
    "addr:street":"Martin Ave",
    "iso:country":"US",
    "sg:address":"909 Martin Ave",
    "sg:city":"Graham",
    "sg:classifiers":[
        {
            "category":"Organizations",
            "subcategory":"Religious Organization",
            "type":"Services"
        }
    ],
    "sg:phone":"+1   ",
    "sg:postcode":"27253",
    "sg:province":"NC",
    "wof:name":"Efland Community Church",
    "wof:placetype":"venue"
},
  "geometry": {"coordinates":[-79.376704,36.037692],"type":"Point"}
}