{
  "type": "Feature",
  "properties": {
    "iso:country":"US",
    "sg:address":"1505 Broad St",
    "sg:city":"Durham",
    "sg:classifiers":[
        {
            "category":"Shopping",
            "subcategory":"Pharmacy",
            "type":"Retail Goods"
        }
    ],
    "sg:phone":"+1 919 286 4431",
    "sg:postcode":"27705",
    "sg:province":"NC",
    "sg:tags":[
        "drug",
        "store"
    ],
    "wof:name":"Eckerd",
    "wof:placetype":"venue"
},
  "geometry": {"coordinates":[-78.918055,36.02415],"type":"Point"}
}