{
  "type": "Feature",
  "properties": {
    "addr:full":"403 Smith Rd Mt Holly NC 28120",
    "addr:housenumber":"403",
    "addr:postcode":"28120",
    "addr:street":"Smith Rd",
    "iso:country":"US",
    "sg:address":"403 Smith Rd",
    "sg:city":"Mt Holly",
    "sg:classifiers":[
        {
            "category":"Building & Trades",
            "subcategory":"Cleaning & Sanitation",
            "type":"Services"
        }
    ],
    "sg:phone":"+1 704 827 0147",
    "sg:postcode":"28120",
    "sg:province":"NC",
    "sg:tags":[
        "fireplace",
        "chimney"
    ],
    "wof:name":"Mr Clean's Pressure Wash",
    "wof:placetype":"venue"
},
  "geometry": {"coordinates":[-81.06133800000001,35.303826],"type":"Point"}
}