{
  "type": "Feature",
  "properties": {
    "iso:country":"US",
    "sg:address":"10300 Chapel Hill Rd Ste 500",
    "sg:city":"Morrisville",
    "sg:classifiers":[
        {
            "category":"Health Services",
            "subcategory":"Doctor",
            "type":"Services"
        }
    ],
    "sg:phone":"+1 919 468 0911",
    "sg:postcode":"27560",
    "sg:province":"NC",
    "sg:tags":[
        "practice",
        "family"
    ],
    "wof:name":"West Cary Medicine",
    "wof:placetype":"venue"
},
  "geometry": {"coordinates":[-78.82688899999999,35.830761],"type":"Point"}
}