{
  "type": "Feature",
  "properties": {
    "iso:country":"US",
    "sg:address":"1502 Sherwood Dr",
    "sg:city":"Reidsville",
    "sg:classifiers":[
        {
            "category":"Building & Trades",
            "subcategory":"Landscaping Services",
            "type":"Services"
        }
    ],
    "sg:phone":"+1 336 342 1139",
    "sg:postcode":"27320",
    "sg:province":"NC",
    "wof:name":"Brays Tree & Landscaping",
    "wof:placetype":"venue"
},
  "geometry": {"coordinates":[-79.687777,36.352373],"type":"Point"}
}