{
  "type": "Feature",
  "properties": {
    "addr:full":"1015 S Horner Blvd Sanford NC 27330",
    "addr:housenumber":"1015",
    "addr:postcode":"27330",
    "addr:street":"S Horner Blvd",
    "iso:country":"US",
    "sg:address":"1015 S Horner Blvd",
    "sg:city":"Sanford",
    "sg:classifiers":[
        {
            "category":"Health Services",
            "subcategory":"Medical Lab",
            "type":"Services"
        }
    ],
    "sg:phone":"+1 919 774 1438",
    "sg:postcode":"27330",
    "sg:province":"NC",
    "sg:tags":[
        "detection",
        "equipment",
        "drug"
    ],
    "wof:name":"A1 Laboratories",
    "wof:placetype":"venue"
},
  "geometry": {"coordinates":[-79.167744,35.47049],"type":"Point"}
}