{
  "type": "Feature",
  "properties": {
    "iso:country":"US",
    "sg:address":"425 E Main St",
    "sg:city":"Lincolnton",
    "sg:classifiers":[
        {
            "category":"Banks & Credit Unions",
            "subcategory":"Bank",
            "type":"Services"
        }
    ],
    "sg:phone":"+1 704 742 7000",
    "sg:postcode":"28092",
    "sg:province":"NC",
    "wof:name":"First-Citizens Bank & Trust Co",
    "wof:placetype":"venue"
},
  "geometry": {"coordinates":[-81.251212,35.473279],"type":"Point"}
}