{
  "type": "Feature",
  "properties": {
    "iso:country":"US",
    "sg:address":"3754 Cardinal Downs Dr",
    "sg:city":"Greensboro",
    "sg:classifiers":[
        {
            "category":"Professional",
            "subcategory":"Management & Consulting",
            "type":"Services"
        }
    ],
    "sg:phone":"+1 336 665 1641",
    "sg:postcode":"27410",
    "sg:province":"NC",
    "sg:tags":[
        "consultant",
        "business"
    ],
    "wof:name":"Keep Inc",
    "wof:placetype":"venue"
},
  "geometry": {"coordinates":[-79.914057,36.133303],"type":"Point"}
}