{
  "type": "Feature",
  "properties": {
    "iso:country":"US",
    "sg:address":"3575 US Hwy 70 Bus W",
    "sg:city":"Clayton",
    "sg:classifiers":[
        {
            "category":"Organizations",
            "subcategory":"Religious Organization",
            "type":"Services"
        }
    ],
    "sg:phone":"+1 919 934 3428",
    "sg:postcode":"27520",
    "sg:province":"NC",
    "sg:tags":[
        "church"
    ],
    "wof:name":"Johnston Union Free Will Bapt",
    "wof:placetype":"venue"
},
  "geometry": {"coordinates":[-78.38926600000001,35.557842],"type":"Point"}
}