{
  "type": "Feature",
  "properties": {
    "iso:country":"US",
    "sg:address":"329 Salt Market St",
    "sg:city":"Dunn",
    "sg:classifiers":[
        {
            "category":"Building & Trades",
            "subcategory":"Construction",
            "type":"Services"
        }
    ],
    "sg:phone":"+1 910 897 5715",
    "sg:postcode":"28334",
    "sg:province":"NC",
    "sg:tags":[
        "concrete",
        "contractor",
        "installation",
        "equipment"
    ],
    "wof:name":"Debreaux Site Work",
    "wof:placetype":"venue"
},
  "geometry": {"coordinates":[-78.68435700000001,35.305725],"type":"Point"}
}