{
  "type": "Feature",
  "properties": {
    "iso:country":"US",
    "sg:address":"504 Hough St",
    "sg:city":"Monroe",
    "sg:classifiers":[
        {
            "category":"Government",
            "subcategory":"Office",
            "type":"Public Place"
        }
    ],
    "sg:phone":"+1 704 289 2514",
    "sg:postcode":"28112",
    "sg:province":"NC",
    "sg:tags":[
        "housing",
        "program"
    ],
    "wof:name":"Monroe Housing Authority",
    "wof:placetype":"venue"
},
  "geometry": {"coordinates":[-80.539693,34.977374],"type":"Point"}
}