{
  "type": "Feature",
  "properties": {
    "iso:country":"US",
    "sg:address":"126 Old Hwy 74",
    "sg:city":"Lake Waccamaw",
    "sg:classifiers":[
        {
            "category":"Food & Beverages",
            "subcategory":"Groceries & Convenience Stores",
            "type":"Retail Goods"
        }
    ],
    "sg:phone":"+1 910 646 7196",
    "sg:postcode":"28431",
    "sg:province":"NC",
    "sg:tags":[
        "grocer"
    ],
    "wof:name":"Hills Food Stores",
    "wof:placetype":"venue"
},
  "geometry": {"coordinates":[-78.82830800000001,34.333404],"type":"Point"}
}