{
  "type": "Feature",
  "properties": {
    "addr:full":"409 Kent St Andrews NC 28901",
    "addr:housenumber":"409",
    "addr:postcode":"28901",
    "addr:street":"Kent",
    "iso:country":"US",
    "sg:address":"409 Kent St",
    "sg:city":"Andrews",
    "sg:classifiers":[
        {
            "category":"Retail",
            "subcategory":"Funeral Services",
            "type":"Services"
        }
    ],
    "sg:phone":"+1 828 321 4409",
    "sg:postcode":"28901",
    "sg:province":"NC",
    "sg:tags":[
        "director",
        "crematory"
    ],
    "wof:name":"Townson Rose Funeral Home",
    "wof:placetype":"venue"
},
  "geometry": {"coordinates":[-83.83873199999999,35.195814],"type":"Point"}
}