{
  "type": "Feature",
  "properties": {
    "iso:country":"US",
    "sg:address":"1000 Mount Vernon Ave",
    "sg:city":"Charlotte",
    "sg:classifiers":[
        {
            "category":"Shopping",
            "subcategory":"Used Merchandise",
            "type":"Retail Goods"
        }
    ],
    "sg:phone":"+1 704 334 0077",
    "sg:postcode":"28203",
    "sg:province":"NC",
    "wof:name":"Serendipity Antiques",
    "wof:placetype":"venue"
},
  "geometry": {"coordinates":[-80.84469,35.211417],"type":"Point"}
}