{
  "type": "Feature",
  "properties": {
    "iso:country":"US",
    "sg:address":"505 W High Ave",
    "sg:city":"High Point",
    "sg:classifiers":[
        {
            "category":"Government",
            "subcategory":"Jail",
            "type":"Public Place"
        }
    ],
    "sg:phone":"+1 336 882 1915",
    "sg:postcode":"27260",
    "sg:province":"NC",
    "sg:tags":[
        "correctional",
        "institution"
    ],
    "wof:name":"Correction North Carolina Dept",
    "wof:placetype":"venue"
},
  "geometry": {"coordinates":[-80.012715,35.953102],"type":"Point"}
}