{
  "type": "Feature",
  "properties": {
    "iso:country":"US",
    "sg:address":"100 Yaupon Dr",
    "sg:city":"Oak Island",
    "sg:classifiers":[
        {
            "category":"Food & Beverages",
            "subcategory":"Groceries & Convenience Stores",
            "type":"Retail Goods"
        }
    ],
    "sg:phone":"+1 910 278 5749",
    "sg:postcode":"28465",
    "sg:province":"NC",
    "wof:name":"Express Stop 5",
    "wof:placetype":"venue"
},
  "geometry": {"coordinates":[-78.075311,33.90875],"type":"Point"}
}