{
  "type": "Feature",
  "properties": {
    "addr:full":"11 Salem St Thomasville NC 27360",
    "addr:housenumber":"11",
    "addr:postcode":"27360",
    "addr:street":"Salem St",
    "iso:country":"US",
    "sg:address":"11 Salem St",
    "sg:city":"Thomasville",
    "sg:classifiers":[
        {
            "category":"Shopping",
            "type":"Retail Goods"
        }
    ],
    "sg:phone":"+1 336 476 4256",
    "sg:postcode":"27360",
    "sg:province":"NC",
    "sg:tags":[
        "cosmetic",
        "perfume"
    ],
    "wof:name":"Avon Center",
    "wof:placetype":"venue"
},
  "geometry": {"coordinates":[-80.08224300000001,35.884021],"type":"Point"}
}