{
  "type": "Feature",
  "properties": {
    "iso:country":"US",
    "sg:address":"548 Ocean Blvd W",
    "sg:city":"Holden Beach",
    "sg:classifiers":[
        {
            "category":"Professional",
            "type":"Services"
        }
    ],
    "sg:phone":"+1 910 842 3838",
    "sg:postcode":"28462",
    "sg:province":"NC",
    "sg:tags":[
        "establishment"
    ],
    "wof:name":"Pearl LTD",
    "wof:placetype":"venue"
},
  "geometry": {"coordinates":[-78.305408,33.910927],"type":"Point"}
}