{
  "type": "Feature",
  "properties": {
    "iso:country":"US",
    "sg:address":"4202 Driftwood Rd",
    "sg:city":"Greensboro",
    "sg:classifiers":[
        {
            "category":"Autos & Motor Vehicles",
            "subcategory":"Fuel & Gas Station",
            "type":"Retail Goods"
        }
    ],
    "sg:phone":"+1 336 545 6979",
    "sg:postcode":"27455",
    "sg:province":"NC",
    "sg:tags":[
        "station",
        "gasoline"
    ],
    "wof:name":"Mark Viii Enterprises Inc",
    "wof:placetype":"venue"
},
  "geometry": {"coordinates":[-79.821257,36.127607],"type":"Point"}
}