{
  "type": "Feature",
  "properties": {
    "iso:country":"US",
    "sg:address":"9144 Sylvan Rd",
    "sg:city":"Liberty",
    "sg:classifiers":[
        {
            "category":"Farming",
            "subcategory":"Dairy Farm",
            "type":"Manufacturing & Wholesale Goods"
        }
    ],
    "sg:phone":"+1 336 376 3970",
    "sg:postcode":"27298",
    "sg:province":"NC",
    "wof:name":"Fogleman Dairy",
    "wof:placetype":"venue"
},
  "geometry": {"coordinates":[-79.46022000000001,35.847448],"type":"Point"}
}