{
  "type": "Feature",
  "properties": {
    "addr:full":"2185 Chestnut Grove Rd King NC 27021",
    "addr:housenumber":"2185",
    "addr:postcode":"27021",
    "addr:street":"Chestnut Grove Rd",
    "iso:country":"US",
    "sg:address":"2185 Chestnut Grove Rd",
    "sg:city":"King",
    "sg:classifiers":[
        {
            "category":"Education",
            "subcategory":"School",
            "type":"Public Place"
        }
    ],
    "sg:phone":"+1 336 983 2106",
    "sg:postcode":"27021",
    "sg:province":"NC",
    "sg:tags":[
        "combined"
    ],
    "sg:website":"www.chestnutgrove.stokes.k12.nc.us",
    "wof:name":"Chestnut Grove Middle School",
    "wof:placetype":"venue"
},
  "geometry": {"coordinates":[-80.374528,36.320995],"type":"Point"}
}