{
  "type": "Feature",
  "properties": {
    "addr:full":"279 Crestoak Dr Wilkesboro NC 28697",
    "addr:housenumber":"279",
    "addr:postcode":"28697",
    "addr:street":"Crestoak Dr",
    "iso:country":"US",
    "sg:address":"279 Crestoak Dr",
    "sg:city":"Wilkesboro",
    "sg:classifiers":[
        {
            "category":"Organizations",
            "subcategory":"Religious Organization",
            "type":"Services"
        }
    ],
    "sg:phone":"+1 336 973 3657",
    "sg:postcode":"28697",
    "sg:province":"NC",
    "sg:website":"www.gideons.org",
    "wof:name":"Gideons International",
    "wof:placetype":"venue"
},
  "geometry": {"coordinates":[-81.24389600000001,36.152343],"type":"Point"}
}