{
  "type": "Feature",
  "properties": {
    "addr:full":"2500 Gateway Center Blvd Cary NC 27511",
    "addr:housenumber":"2500",
    "addr:postcode":"27511",
    "addr:street":"Gateway Center Blvd",
    "iso:country":"US",
    "sg:address":"2500 Gateway Center Blvd",
    "sg:city":"Cary",
    "sg:classifiers":[
        {
            "category":"Building & Trades",
            "subcategory":"Construction",
            "type":"Services"
        }
    ],
    "sg:phone":"+1 919 388 9937",
    "sg:postcode":"27511",
    "sg:province":"NC",
    "sg:tags":[
        "contractor"
    ],
    "wof:name":"Diamond Touch",
    "wof:placetype":"venue"
},
  "geometry": {"coordinates":[-78.80471300000001,35.846869],"type":"Point"}
}