{
  "type": "Feature",
  "properties": {
    "iso:country":"US",
    "sg:address":"803 Meridon St",
    "sg:city":"Fayetteville",
    "sg:classifiers":[
        {
            "category":"Shopping",
            "type":"Retail Goods"
        }
    ],
    "sg:phone":"+1 910 826 7007",
    "sg:postcode":"28314",
    "sg:province":"NC",
    "sg:tags":[
        "wedding",
        "supply"
    ],
    "wof:name":"Princess Veils",
    "wof:placetype":"venue"
},
  "geometry": {"coordinates":[-79.00206300000001,35.049986],"type":"Point"}
}