{
  "type": "Feature",
  "properties": {
    "addr:full":"2401 Wentworth St Raleigh NC 27612",
    "addr:housenumber":"2401",
    "addr:postcode":"27612",
    "addr:street":"Wentworth St",
    "iso:country":"US",
    "sg:address":"2401 Wentworth St",
    "sg:city":"Raleigh",
    "sg:classifiers":[
        {
            "category":"Building & Trades",
            "subcategory":"Construction",
            "type":"Services"
        }
    ],
    "sg:phone":"+1 919 788 2080",
    "sg:postcode":"27612",
    "sg:province":"NC",
    "sg:tags":[
        "contractor"
    ],
    "wof:name":"Ed's Custom Contracting",
    "wof:placetype":"venue"
},
  "geometry": {"coordinates":[-78.67995500000001,35.826329],"type":"Point"}
}