{
  "type": "Feature",
  "properties": {
    "iso:country":"US",
    "sg:address":"101 S Tryon St",
    "sg:city":"Charlotte",
    "sg:classifiers":[
        {
            "category":"Manufacturing",
            "subcategory":"Printing",
            "type":"Manufacturing & Wholesale Goods"
        }
    ],
    "sg:phone":"+1 704 339 0000",
    "sg:postcode":"28202",
    "sg:province":"NC",
    "sg:tags":[
        "commercial"
    ],
    "wof:name":"Bowne of Charlotte",
    "wof:placetype":"venue"
},
  "geometry": {"coordinates":[-80.844207,35.226414],"type":"Point"}
}