{
  "type": "Feature",
  "properties": {
    "iso:country":"US",
    "sg:address":"5806 Prosperity Church Rd",
    "sg:city":"Charlotte",
    "sg:classifiers":[
        {
            "category":"Personal",
            "subcategory":"Beauty Salon",
            "type":"Services"
        }
    ],
    "sg:phone":"+1   ",
    "sg:postcode":"28269",
    "sg:province":"NC",
    "sg:tags":[
        "shop"
    ],
    "sg:website":"www.greatclips.com",
    "wof:name":"Great Clips",
    "wof:placetype":"venue"
},
  "geometry": {"coordinates":[-80.785042,35.370467],"type":"Point"}
}