{
  "type": "Feature",
  "properties": {
    "iso:country":"US",
    "sg:address":"655 Pitts School Rd NW",
    "sg:city":"Concord",
    "sg:phone":"+1 704 782 5000",
    "sg:postcode":"28027",
    "sg:province":"NC",
    "sg:tags":[
        "farm",
        "soybean"
    ],
    "wof:name":"Ralph Bonds",
    "wof:placetype":"venue"
},
  "geometry": {"coordinates":[-80.696665,35.400006],"type":"Point"}
}