{
  "type": "Feature",
  "properties": {
    "iso:country":"US",
    "sg:address":"578 W Northwest Blvd",
    "sg:city":"Winston Salem",
    "sg:classifiers":[
        {
            "category":"Autos & Motor Vehicles",
            "subcategory":"Fuel & Gas Station",
            "type":"Retail Goods"
        }
    ],
    "sg:phone":"+1 336 723 9906",
    "sg:postcode":"27105",
    "sg:province":"NC",
    "sg:tags":[
        "station",
        "gasoline"
    ],
    "wof:name":"Fairway One Stop Citgo",
    "wof:placetype":"venue"
},
  "geometry": {"coordinates":[-80.250185,36.109545],"type":"Point"}
}