{
  "type": "Feature",
  "properties": {
    "iso:country":"US",
    "sg:address":"6298 McLeansville Rd",
    "sg:city":"Mc Leansville",
    "sg:classifiers":[
        {
            "category":"Building & Trades",
            "subcategory":"Landscaping Services",
            "type":"Services"
        }
    ],
    "sg:phone":"+1 336 621 1341",
    "sg:postcode":"27301",
    "sg:province":"NC",
    "sg:tags":[
        "sodding",
        "machinery",
        "landscape",
        "sod"
    ],
    "wof:name":"Turf's Up Sod Farm",
    "wof:placetype":"venue"
},
  "geometry": {"coordinates":[-79.66284,36.133134],"type":"Point"}
}