{
  "type": "Feature",
  "properties": {
    "iso:country":"US",
    "sg:address":"6614 McCain Blvd",
    "sg:city":"Waxhaw",
    "sg:classifiers":[
        {
            "category":"Professional",
            "subcategory":"Business Services",
            "type":"Services"
        },
        {
            "category":"Professional",
            "subcategory":"Management & Consulting",
            "type":"Services"
        }
    ],
    "sg:phone":"+1 704 254 5405",
    "sg:postcode":"28173",
    "sg:province":"NC",
    "sg:tags":[
        "consultant",
        "resource",
        "human"
    ],
    "wof:name":"Barclay Resource Group Inc",
    "wof:placetype":"venue"
},
  "geometry": {"coordinates":[-80.691768,34.857217],"type":"Point"}
}