{
  "type": "Feature",
  "properties": {
    "iso:country":"US",
    "sg:address":"4399 Ritchie Rd",
    "sg:city":"Lincolnton",
    "sg:classifiers":[
        {
            "category":"Farming",
            "subcategory":"Dairy Farm",
            "type":"Manufacturing & Wholesale Goods"
        }
    ],
    "sg:phone":"+1 704 735 1222",
    "sg:postcode":"28092",
    "sg:province":"NC",
    "wof:name":"Piedmont Jersey",
    "wof:placetype":"venue"
},
  "geometry": {"coordinates":[-81.287868,35.544264],"type":"Point"}
}