{
  "type": "Feature",
  "properties": {
    "iso:country":"US",
    "sg:address":"120 E 10th St",
    "sg:city":"Roanoke Rapids",
    "sg:classifiers":[
        {
            "category":"Restaurant",
            "type":"Food & Drink"
        }
    ],
    "sg:menulink":"http://www.allmenus.com/nc/roanoke-rapids/156314-hardees/menu/",
    "sg:phone":"+1 252 537 3619",
    "sg:postcode":"27870",
    "sg:province":"NC",
    "sg:tags":[
        "burger",
        "american"
    ],
    "wof:name":"Hardee's",
    "wof:placetype":"venue"
},
  "geometry": {"coordinates":[-77.655826,36.455587],"type":"Point"}
}