{
  "type": "Feature",
  "properties": {
    "addr:full":"108 W Jefferson St Jackson NC 27845",
    "addr:housenumber":"108",
    "addr:postcode":"27845",
    "addr:street":"W Jefferson St",
    "iso:country":"US",
    "sg:address":"108 W Jefferson St",
    "sg:city":"Jackson",
    "sg:classifiers":[
        {
            "category":"Government",
            "subcategory":"Office",
            "type":"Public Place"
        }
    ],
    "sg:phone":"+1 252 534 1228",
    "sg:postcode":"27845",
    "sg:province":"NC",
    "wof:name":"Northampton Count Custody",
    "wof:placetype":"venue"
},
  "geometry": {"coordinates":[-77.419459,36.389725],"type":"Point"}
}