{
  "type": "Feature",
  "properties": {
    "addr:full":"1920 Smythwyck Dr Greenville NC 27858",
    "addr:housenumber":"1920",
    "addr:postcode":"27858",
    "addr:street":"Smythwyck Dr",
    "iso:country":"US",
    "sg:address":"1920 Smythwyck Dr",
    "sg:city":"Greenville",
    "sg:classifiers":[
        {
            "category":"Wholesale",
            "subcategory":"Machinery & Supplies",
            "type":"Manufacturing & Wholesale Goods"
        }
    ],
    "sg:phone":"+1 252 321 4779",
    "sg:postcode":"27858",
    "sg:province":"NC",
    "sg:tags":[
        "beauty"
    ],
    "wof:name":"Davidson Beauty Supply",
    "wof:placetype":"venue"
},
  "geometry": {"coordinates":[-77.353419,35.567672],"type":"Point"}
}