{
  "type": "Feature",
  "properties": {
    "iso:country":"US",
    "sg:address":"615 US Hwy 52",
    "sg:city":"Albemarle",
    "sg:classifiers":[
        {
            "category":"Personal",
            "subcategory":"Barber",
            "type":"Services"
        }
    ],
    "sg:phone":"+1 704 982 7815",
    "sg:postcode":"28001",
    "sg:province":"NC",
    "wof:name":"New Images Hair Care",
    "wof:placetype":"venue"
},
  "geometry": {"coordinates":[-80.207103,35.358413],"type":"Point"}
}