{
  "type": "Feature",
  "properties": {
    "iso:country":"US",
    "sg:address":"211 S 4th St",
    "sg:city":"Highlands",
    "sg:classifiers":[
        {
            "category":"Shopping",
            "subcategory":"Gifts & Souvenirs",
            "type":"Retail Goods"
        }
    ],
    "sg:phone":"+1 828 526 1924",
    "sg:postcode":"28741",
    "sg:province":"NC",
    "sg:tags":[
        "shop"
    ],
    "wof:name":"Mamma Ro'",
    "wof:placetype":"venue"
},
  "geometry": {"coordinates":[-83.19744,35.051925],"type":"Point"}
}