{
  "type": "Feature",
  "properties": {
    "addr:full":"1007 Balsam Ter Charlotte NC 28214",
    "addr:housenumber":"1007",
    "addr:postcode":"28214",
    "addr:street":"Balsam Ter",
    "iso:country":"US",
    "sg:address":"1007 Balsam Ter",
    "sg:city":"Charlotte",
    "sg:classifiers":[
        {
            "category":"Professional",
            "subcategory":"Computer Services",
            "type":"Services"
        }
    ],
    "sg:phone":"+1 704 609 1341",
    "sg:postcode":"28214",
    "sg:province":"NC",
    "sg:tags":[
        "repair"
    ],
    "wof:name":"A Plus Computer Svc",
    "wof:placetype":"venue"
},
  "geometry": {"coordinates":[-80.941498,35.289349],"type":"Point"}
}