{
  "type": "Feature",
  "properties": {
    "iso:country":"US",
    "sg:address":"217 1st St SW",
    "sg:city":"Taylorsville",
    "sg:classifiers":[
        {
            "category":"Insurance",
            "subcategory":"Insurance Agent",
            "type":"Services"
        }
    ],
    "sg:phone":"+1 828 632 6458",
    "sg:postcode":"28681",
    "sg:province":"NC",
    "wof:name":"Benfield Insurance",
    "wof:placetype":"venue"
},
  "geometry": {"coordinates":[-81.175686,35.921056],"type":"Point"}
}