{
  "type": "Feature",
  "properties": {
    "addr:full":"5931 Yadkin Rd Fayetteville NC 28303",
    "addr:housenumber":"5931",
    "addr:postcode":"28303",
    "addr:street":"Yadkin Rd",
    "iso:country":"US",
    "sg:address":"5931 Yadkin Rd",
    "sg:city":"Fayetteville",
    "sg:classifiers":[
        {
            "category":"Restaurant",
            "type":"Food & Drink"
        }
    ],
    "sg:phone":"+1 910 864 5100",
    "sg:postcode":"28303",
    "sg:province":"NC",
    "sg:tags":[
        "seafood"
    ],
    "wof:name":"Fish and Chips",
    "wof:placetype":"venue"
},
  "geometry": {"coordinates":[-78.98631399999999,35.094044],"type":"Point"}
}