{
  "type": "Feature",
  "properties": {
    "iso:country":"US",
    "sg:address":"520 Hart Rd",
    "sg:city":"Woodleaf",
    "sg:classifiers":[
        {
            "category":"Organizations",
            "subcategory":"Religious Organization",
            "type":"Services"
        }
    ],
    "sg:phone":"+1 704 278 9633",
    "sg:postcode":"27054",
    "sg:province":"NC",
    "sg:tags":[
        "church"
    ],
    "wof:name":"Emanuel Pentecostal Church",
    "wof:placetype":"venue"
},
  "geometry": {"coordinates":[-80.60291700000001,35.796689],"type":"Point"}
}