{
  "type": "Feature",
  "properties": {
    "addr:full":"2510 Siler City Snow Camp Rd Siler City NC 27344",
    "addr:housenumber":"2510",
    "addr:postcode":"27344",
    "addr:street":"Snow Camp Rd",
    "iso:country":"US",
    "sg:address":"2510 Siler City Snow Camp Rd",
    "sg:city":"Siler City",
    "sg:classifiers":[
        {
            "category":"Retail",
            "subcategory":"Animal Services",
            "type":"Services"
        }
    ],
    "sg:phone":"+1 919 742 4808",
    "sg:postcode":"27344",
    "sg:province":"NC",
    "wof:name":"Groomin Plus",
    "wof:placetype":"venue"
},
  "geometry": {"coordinates":[-79.446434,35.748354],"type":"Point"}
}