{
  "type": "Feature",
  "properties": {
    "iso:country":"US",
    "sg:address":"204 Wilmington Hwy",
    "sg:city":"Jacksonville",
    "sg:classifiers":[
        {
            "category":"Cinema",
            "subcategory":"Movie Rental",
            "type":"Entertainment"
        }
    ],
    "sg:phone":"+1 910 346 0934",
    "sg:postcode":"28540",
    "sg:province":"NC",
    "sg:tags":[
        "leasing",
        "video",
        "disc",
        "tape"
    ],
    "wof:name":"Video Update",
    "wof:placetype":"venue"
},
  "geometry": {"coordinates":[-77.452466,34.750978],"type":"Point"}
}