{
  "type": "Feature",
  "properties": {
    "addr:full":"104 1st St Erwin NC 28339",
    "addr:housenumber":"104",
    "addr:postcode":"28339",
    "addr:street":"1St St",
    "iso:country":"US",
    "sg:address":"104 1st St",
    "sg:city":"Erwin",
    "sg:classifiers":[
        {
            "category":"Wholesale",
            "subcategory":"Non-durable Goods",
            "type":"Manufacturing & Wholesale Goods"
        }
    ],
    "sg:phone":"+1 910 891 4776",
    "sg:postcode":"28339",
    "sg:province":"NC",
    "wof:name":"Beitar Speciality Imports",
    "wof:placetype":"venue"
},
  "geometry": {"coordinates":[-78.657365,35.32353],"type":"Point"}
}