{
  "type": "Feature",
  "properties": {
    "iso:country":"US",
    "sg:address":"4642 Creekview Rd",
    "sg:city":"Mc Leansville",
    "sg:classifiers":[
        {
            "category":"Travel",
            "subcategory":"Travel Agent",
            "type":"Entertainment"
        }
    ],
    "sg:phone":"+1 336 954 7700",
    "sg:postcode":"27301",
    "sg:province":"NC",
    "sg:tags":[
        "agency"
    ],
    "wof:name":"Classic World Travel",
    "wof:placetype":"venue"
},
  "geometry": {"coordinates":[-79.68687199999999,36.127691],"type":"Point"}
}