{
  "type": "Feature",
  "properties": {
    "iso:country":"US",
    "sg:address":"5 Cedar Ridge Dr",
    "sg:city":"Asheville",
    "sg:classifiers":[
        {
            "category":"Shopping",
            "subcategory":"Computers & Home Electronics",
            "type":"Retail Goods"
        }
    ],
    "sg:phone":"+1 828 253 0643",
    "sg:postcode":"28806",
    "sg:province":"NC",
    "sg:tags":[
        "store",
        "software"
    ],
    "wof:name":"Compuclaims Plus",
    "wof:placetype":"venue"
},
  "geometry": {"coordinates":[-82.62277400000001,35.629891],"type":"Point"}
}