{
  "type": "Feature",
  "properties": {
    "addr:full":"410 21st St SE Hickory NC 28602",
    "addr:housenumber":"410",
    "addr:postcode":"28602",
    "addr:street":"21St St Se",
    "iso:country":"US",
    "sg:address":"410 21st St SE",
    "sg:city":"Hickory",
    "sg:classifiers":[
        {
            "category":"Social Services",
            "subcategory":"Child Care",
            "type":"Services"
        }
    ],
    "sg:phone":"+1 828 327 9983",
    "sg:postcode":"28602",
    "sg:province":"NC",
    "wof:name":"Little Folks School-East",
    "wof:placetype":"venue"
},
  "geometry": {"coordinates":[-81.29690100000001,35.725628],"type":"Point"}
}