{
  "type": "Feature",
  "properties": {
    "iso:country":"US",
    "sg:address":"7200 Albemarle Rd",
    "sg:city":"Charlotte",
    "sg:classifiers":[
        {
            "category":"Professional",
            "subcategory":"Accounting & Tax Preparation",
            "type":"Services"
        }
    ],
    "sg:phone":"+1 704 535 7487",
    "sg:postcode":"28227",
    "sg:province":"NC",
    "sg:tags":[
        "return"
    ],
    "wof:name":"H & R Block",
    "wof:placetype":"venue"
},
  "geometry": {"coordinates":[-80.71925400000001,35.204691],"type":"Point"}
}