{
  "type": "Feature",
  "properties": {
    "addr:full":"107 E Edgerton St Kenly NC 27542",
    "addr:housenumber":"107",
    "addr:postcode":"27542",
    "addr:street":"E Edgerton St",
    "iso:country":"US",
    "sg:address":"107 E Edgerton St",
    "sg:city":"Kenly",
    "sg:classifiers":[
        {
            "category":"Organizations",
            "subcategory":"Religious Organization",
            "type":"Services"
        }
    ],
    "sg:phone":"+1 919 284 3504",
    "sg:postcode":"27542",
    "sg:province":"NC",
    "sg:tags":[
        "church"
    ],
    "wof:name":"Kenly Free Will Baptist Chr",
    "wof:placetype":"venue"
},
  "geometry": {"coordinates":[-78.124995,35.593122],"type":"Point"}
}