{
  "type": "Feature",
  "properties": {
    "addr:full":"1082 Burning Tree Dr Chapel Hill NC 27517",
    "addr:housenumber":"1082",
    "addr:postcode":"27517",
    "addr:street":"Burning Tree Dr",
    "iso:country":"US",
    "sg:address":"1082 Burning Tree Dr",
    "sg:city":"Chapel Hill",
    "sg:classifiers":[
        {
            "category":"Banks & Credit Unions",
            "subcategory":"Financial Services",
            "type":"Services"
        }
    ],
    "sg:phone":"+1 919 932 3230",
    "sg:postcode":"27517",
    "sg:province":"NC",
    "sg:tags":[
        "company",
        "holding"
    ],
    "wof:name":"Lamont Properties LLC",
    "wof:placetype":"venue"
},
  "geometry": {"coordinates":[-79.01886,35.913591],"type":"Point"}
}