{
  "type": "Feature",
  "properties": {
    "iso:country":"US",
    "sg:address":"1137 N Fayetteville St",
    "sg:city":"Asheboro",
    "sg:classifiers":[
        {
            "category":"Shopping",
            "subcategory":"Discount & Variety Stores",
            "type":"Retail Goods"
        }
    ],
    "sg:phone":"+1 336 629 1442",
    "sg:postcode":"27203",
    "sg:province":"NC",
    "sg:tags":[
        "merchandise",
        "general"
    ],
    "wof:name":"Coneccion Latino Americana",
    "wof:placetype":"venue"
},
  "geometry": {"coordinates":[-79.80897,35.726276],"type":"Point"}
}