{
  "type": "Feature",
  "properties": {
    "addr:full":"118 E Jones St Fuquay Varina NC 27526",
    "addr:housenumber":"118",
    "addr:postcode":"27526",
    "addr:street":"E Jones St",
    "iso:country":"US",
    "sg:address":"118 E Jones St",
    "sg:city":"Fuquay Varina",
    "sg:classifiers":[
        {
            "category":"Building & Trades",
            "subcategory":"Construction",
            "type":"Services"
        }
    ],
    "sg:phone":"+1 919 567 9400",
    "sg:postcode":"27526",
    "sg:province":"NC",
    "sg:tags":[
        "maker",
        "cabinet"
    ],
    "wof:name":"Olive Branch Cabinets & Furn",
    "wof:placetype":"venue"
},
  "geometry": {"coordinates":[-78.799651,35.586722],"type":"Point"}
}