{
  "type": "Feature",
  "properties": {
    "addr:full":"20823 N Main St Cornelius NC 28031",
    "addr:housenumber":"20823",
    "addr:postcode":"28031",
    "addr:street":"N Main St",
    "iso:country":"US",
    "sg:address":"20823 N Main St",
    "sg:city":"Cornelius",
    "sg:classifiers":[
        {
            "category":"Building & Trades",
            "subcategory":"Construction",
            "type":"Services"
        }
    ],
    "sg:phone":"+1 704 896 6379",
    "sg:postcode":"28031",
    "sg:province":"NC",
    "sg:tags":[
        "handyman"
    ],
    "wof:name":"Hands4hire",
    "wof:placetype":"venue"
},
  "geometry": {"coordinates":[-80.85760000000001,35.491625],"type":"Point"}
}