{
  "type": "Feature",
  "properties": {
    "addr:full":"121 Memorial Dr Jacksonville NC 28546",
    "addr:housenumber":"121",
    "addr:postcode":"28546",
    "addr:street":"Memorial Dr",
    "iso:country":"US",
    "sg:address":"121 Memorial Dr",
    "sg:city":"Jacksonville",
    "sg:classifiers":[
        {
            "category":"Health Services",
            "subcategory":"Doctor",
            "type":"Services"
        }
    ],
    "sg:phone":"+1 910 577 0267",
    "sg:postcode":"28546",
    "sg:province":"NC",
    "sg:tags":[
        "clinic"
    ],
    "wof:name":"Urgent Care Of Jacksonville",
    "wof:placetype":"venue"
},
  "geometry": {"coordinates":[-77.38547699999999,34.764341],"type":"Point"}
}