{
  "type": "Feature",
  "properties": {
    "addr:full":"118 Grady W Ln Carthage NC 28327",
    "addr:housenumber":"118",
    "addr:postcode":"28327",
    "addr:street":"Grady W Ln",
    "iso:country":"US",
    "sg:address":"118 Grady W Ln",
    "sg:city":"Carthage",
    "sg:classifiers":[
        {
            "category":"Retail",
            "subcategory":"Auto Repair",
            "type":"Services"
        }
    ],
    "sg:phone":"+1 910 947 5577",
    "sg:postcode":"28327",
    "sg:province":"NC",
    "sg:tags":[
        "repairing",
        "automobile",
        "general"
    ],
    "wof:name":"Collier's Garage",
    "wof:placetype":"venue"
},
  "geometry": {"coordinates":[-79.37115900000001,35.307384],"type":"Point"}
}