{
  "type": "Feature",
  "properties": {
    "addr:full":"907 Fields Dr Sanford NC 27330",
    "addr:housenumber":"907",
    "addr:postcode":"27330",
    "addr:street":"Fields Dr",
    "iso:country":"US",
    "sg:address":"907 Fields Dr",
    "sg:city":"Sanford",
    "sg:classifiers":[
        {
            "category":"Manufacturing",
            "subcategory":"Printing",
            "type":"Manufacturing & Wholesale Goods"
        }
    ],
    "sg:phone":"+1 919 776 0055",
    "sg:postcode":"27330",
    "sg:province":"NC",
    "sg:tags":[
        "commercial"
    ],
    "wof:name":"Vlo Designs & Graphics",
    "wof:placetype":"venue"
},
  "geometry": {"coordinates":[-79.17624499999999,35.468556],"type":"Point"}
}