{
  "type": "Feature",
  "properties": {
    "addr:full":"3164 Morningside Dr Raleigh NC 27607",
    "addr:housenumber":"3164",
    "addr:postcode":"27607",
    "addr:street":"Morningside Dr",
    "iso:country":"US",
    "sg:address":"3164 Morningside Dr",
    "sg:city":"Raleigh",
    "sg:classifiers":[
        {
            "category":"Insurance",
            "subcategory":"Insurance Agent",
            "type":"Services"
        }
    ],
    "sg:phone":"+1 919 787 1239",
    "sg:postcode":"27607",
    "sg:province":"NC",
    "wof:name":"Insurance Planning Assoc",
    "wof:placetype":"venue"
},
  "geometry": {"coordinates":[-78.690175,35.824986],"type":"Point"}
}