{
  "type": "Feature",
  "properties": {
    "iso:country":"US",
    "sg:address":"3739 Nash St NW",
    "sg:city":"Wilson",
    "sg:classifiers":[
        {
            "category":"Shopping",
            "subcategory":"Pharmacy",
            "type":"Retail Goods"
        }
    ],
    "sg:phone":"+1 252 293 4175",
    "sg:postcode":"27896",
    "sg:province":"NC",
    "wof:name":"CVS Pharmacy",
    "wof:placetype":"venue"
},
  "geometry": {"coordinates":[-77.94076800000001,35.770325],"type":"Point"}
}