{
  "type": "Feature",
  "properties": {
    "addr:full":"801 Fairview Rd Asheville NC 28803",
    "addr:housenumber":"801",
    "addr:postcode":"28803",
    "addr:street":"Fairview Rd",
    "iso:country":"US",
    "sg:address":"801 Fairview Rd",
    "sg:city":"Asheville",
    "sg:classifiers":[
        {
            "category":"Restaurant",
            "type":"Food & Drink"
        }
    ],
    "sg:menulink":"http://www.allmenus.com/nc/asheville/191192-burger-king/menu/",
    "sg:phone":"+1 828 299 8447",
    "sg:postcode":"28803",
    "sg:province":"NC",
    "sg:tags":[
        "burger",
        "american"
    ],
    "wof:name":"Burger King",
    "wof:placetype":"venue"
},
  "geometry": {"coordinates":[-82.50503999999999,35.56956],"type":"Point"}
}