{
  "type": "Feature",
  "properties": {
    "iso:country":"US",
    "sg:address":"125 W Gum Rd",
    "sg:city":"Greenville",
    "sg:classifiers":[
        {
            "category":"Building & Trades",
            "subcategory":"Plumbing",
            "type":"Services"
        }
    ],
    "sg:phone":"+1 252 752 1779",
    "sg:postcode":"27834",
    "sg:province":"NC",
    "sg:tags":[
        "conditioning",
        "air",
        "system",
        "contractor"
    ],
    "wof:name":"Comfortmaster Mechanical Assoc",
    "wof:placetype":"venue"
},
  "geometry": {"coordinates":[-77.37588599999999,35.635197],"type":"Point"}
}