{
  "type": "Feature",
  "properties": {
    "iso:country":"US",
    "sg:address":"111 Kitty Hawk Ln",
    "sg:city":"Elizabeth City",
    "sg:classifiers":[
        {
            "category":"Manufacturing",
            "subcategory":"Tools & Machinery",
            "type":"Manufacturing & Wholesale Goods"
        }
    ],
    "sg:phone":"+1 252 338 3200",
    "sg:postcode":"27909",
    "sg:province":"NC",
    "sg:tags":[
        "construction",
        "mfg"
    ],
    "wof:name":"Tcom Ground Systems LP",
    "wof:placetype":"venue"
},
  "geometry": {"coordinates":[-76.213312,36.2735],"type":"Point"}
}