{
  "type": "Feature",
  "properties": {
    "iso:country":"US",
    "sg:address":"321 S York St",
    "sg:city":"Gastonia",
    "sg:classifiers":[
        {
            "category":"Government",
            "subcategory":"Office",
            "type":"Public Place"
        }
    ],
    "sg:phone":"+1 704 854 6657",
    "sg:postcode":"28052",
    "sg:province":"NC",
    "sg:tags":[
        "village"
    ],
    "wof:name":"Crowders Creek Wastewater",
    "wof:placetype":"venue"
},
  "geometry": {"coordinates":[-81.185749,35.259409],"type":"Point"}
}