{
  "type": "Feature",
  "properties": {
    "addr:full":"100 Endeavor Way Cary NC 27513",
    "addr:housenumber":"100",
    "addr:postcode":"27513",
    "addr:street":"Endeavor Way",
    "iso:country":"US",
    "sg:address":"100 Endeavor Way",
    "sg:city":"Cary",
    "sg:classifiers":[
        {
            "category":"Education",
            "subcategory":"Preschool",
            "type":"Public Place"
        },
        {
            "category":"Education",
            "subcategory":"School",
            "type":"Public Place"
        }
    ],
    "sg:phone":"+1 919 677 7114",
    "sg:postcode":"27513",
    "sg:province":"NC",
    "sg:tags":[
        "elementary"
    ],
    "wof:name":"Spanish For Fun",
    "wof:placetype":"venue"
},
  "geometry": {"coordinates":[-78.773481,35.831461],"type":"Point"}
}