{
  "type": "Feature",
  "properties": {
    "addr:full":"6137 Princeton Kenly Rd Princeton NC 27569",
    "addr:housenumber":"6137",
    "addr:postcode":"27569",
    "addr:street":"Princeton Kenly Rd",
    "iso:country":"US",
    "sg:address":"6137 Princeton Kenly Rd",
    "sg:city":"Princeton",
    "sg:classifiers":[
        {
            "category":"Manufacturing",
            "subcategory":"Tools & Machinery",
            "type":"Manufacturing & Wholesale Goods"
        }
    ],
    "sg:phone":"+1 919 818 8700",
    "sg:postcode":"27569",
    "sg:province":"NC",
    "sg:tags":[
        "mfg"
    ],
    "wof:name":"Powersecure Inc",
    "wof:placetype":"venue"
},
  "geometry": {"coordinates":[-78.136026,35.504605],"type":"Point"}
}