{
  "type": "Feature",
  "properties": {
    "iso:country":"US",
    "sg:address":"2513 Mahala Dr",
    "sg:city":"Durham",
    "sg:classifiers":[
        {
            "category":"Personal",
            "subcategory":"Barber",
            "type":"Services"
        }
    ],
    "sg:phone":"+1   ",
    "sg:postcode":"27704",
    "sg:province":"NC",
    "sg:tags":[
        "shop"
    ],
    "wof:name":"Just For His Glory",
    "wof:placetype":"venue"
},
  "geometry": {"coordinates":[-78.869253,36.030263],"type":"Point"}
}