{
  "type": "Feature",
  "properties": {
    "addr:full":"2033 Cowpen Landing Rd Wilmington NC 28401",
    "addr:housenumber":"2033",
    "addr:postcode":"28401",
    "addr:street":"Cowpen Landing Rd",
    "iso:country":"US",
    "sg:address":"2033 Cowpen Landing Rd",
    "sg:city":"Wilmington",
    "sg:classifiers":[
        {
            "category":"Retail",
            "subcategory":"Auto Repair",
            "type":"Services"
        }
    ],
    "sg:phone":"+1 910 763 4134",
    "sg:postcode":"28401",
    "sg:province":"NC",
    "sg:tags":[
        "general"
    ],
    "wof:name":"Chris Pepper",
    "wof:placetype":"venue"
},
  "geometry": {"coordinates":[-77.99549,34.36968],"type":"Point"}
}