{
  "type": "Feature",
  "properties": {
    "addr:full":"4801 Ola Ln Walkertown NC 27051",
    "addr:housenumber":"4801",
    "addr:postcode":"27051",
    "addr:street":"Ola Ln",
    "iso:country":"US",
    "sg:address":"4801 Ola Ln",
    "sg:city":"Walkertown",
    "sg:classifiers":[
        {
            "category":"Personal",
            "subcategory":"Beauty Salon",
            "type":"Services"
        }
    ],
    "sg:phone":"+1   ",
    "sg:postcode":"27051",
    "sg:province":"NC",
    "sg:tags":[
        "shop"
    ],
    "wof:name":"Shear Art Salon LLC",
    "wof:placetype":"venue"
},
  "geometry": {"coordinates":[-80.156471,36.151061],"type":"Point"}
}