{
  "type": "Feature",
  "properties": {
    "addr:full":"635 Armfield St Statesville NC 28677",
    "addr:housenumber":"635",
    "addr:postcode":"28677",
    "addr:street":"Armfield St",
    "iso:country":"US",
    "sg:address":"635 Armfield St",
    "sg:city":"Statesville",
    "sg:classifiers":[
        {
            "category":"Autos & Motor Vehicles",
            "subcategory":"Auto Supplies",
            "type":"Retail Goods"
        }
    ],
    "sg:phone":"+1 704 838 0068",
    "sg:postcode":"28677",
    "sg:province":"NC",
    "wof:name":"Custom Creations",
    "wof:placetype":"venue"
},
  "geometry": {"coordinates":[-80.89360600000001,35.77632],"type":"Point"}
}