{
  "type": "Feature",
  "properties": {
    "iso:country":"US",
    "sg:address":"3792 Kelford Dr",
    "sg:city":"Greensboro",
    "sg:classifiers":[
        {
            "category":"Professional",
            "subcategory":"Business Services",
            "type":"Services"
        }
    ],
    "sg:phone":"+1   ",
    "sg:postcode":"27406",
    "sg:province":"NC",
    "wof:name":"Dominion Group",
    "wof:placetype":"venue"
},
  "geometry": {"coordinates":[-79.696243,36.013677],"type":"Point"}
}