{
  "type": "Feature",
  "properties": {
    "addr:full":"5057 Lowder Rd Burlington NC 27217",
    "addr:postcode":"5057;27217",
    "addr:street":"Lowder Rd",
    "iso:country":"US",
    "sg:address":"5057 Lowder Rd",
    "sg:city":"Burlington",
    "sg:classifiers":[
        {
            "category":"Building & Trades",
            "subcategory":"Construction",
            "type":"Services"
        }
    ],
    "sg:phone":"+1 336 421 1520",
    "sg:postcode":"27217",
    "sg:province":"NC",
    "sg:tags":[
        "contractor"
    ],
    "wof:name":"David T Wilkinson",
    "wof:placetype":"venue"
},
  "geometry": {"coordinates":[-79.365534,36.215666],"type":"Point"}
}