{
  "type": "Feature",
  "properties": {
    "addr:full":"7000 Old Mount Holly Rd Charlotte NC 28214",
    "addr:housenumber":"7000",
    "addr:postcode":"28214",
    "addr:street":"Old Mount Holly Rd",
    "iso:country":"US",
    "sg:address":"7000 Old Mount Holly Rd",
    "sg:city":"Charlotte",
    "sg:classifiers":[
        {
            "category":"Wholesale",
            "subcategory":"Construction Materials",
            "type":"Manufacturing & Wholesale Goods"
        }
    ],
    "sg:phone":"+1 704 392 8813",
    "sg:postcode":"28214",
    "sg:province":"NC",
    "sg:tags":[
        "concrete",
        "product"
    ],
    "wof:name":"Precast Construction Products",
    "wof:placetype":"venue"
},
  "geometry": {"coordinates":[-80.922996,35.280942],"type":"Point"}
}