{
  "type": "Feature",
  "properties": {
    "addr:full":"7836 Caratoke Hwy Powells Point NC 27966",
    "addr:housenumber":"7836",
    "addr:postcode":"27966",
    "addr:street":"Caratoke Hwy",
    "iso:country":"US",
    "sg:address":"7836 Caratoke Hwy",
    "sg:city":"Powells Point",
    "sg:classifiers":[
        {
            "category":"Shopping",
            "type":"Retail Goods"
        },
        {
            "category":"Mining & Drilling",
            "type":"Manufacturing & Wholesale Goods"
        }
    ],
    "sg:phone":"+1 252 491 2300",
    "sg:postcode":"27966",
    "sg:province":"NC",
    "sg:tags":[
        "stone"
    ],
    "wof:name":"Currituck Stone Inc",
    "wof:placetype":"venue"
},
  "geometry": {"coordinates":[-75.859241,36.159699],"type":"Point"}
}