{
  "type": "Feature",
  "properties": {
    "iso:country":"US",
    "sg:address":"527 Rainbow Mountain Rd",
    "sg:city":"Boone",
    "sg:classifiers":[
        {
            "category":"Shopping",
            "type":"Retail Goods"
        }
    ],
    "sg:phone":"+1 828 355 9514",
    "sg:postcode":"28607",
    "sg:province":"NC",
    "sg:tags":[
        "merchandise"
    ],
    "wof:name":"3791 Warehouse Inc",
    "wof:placetype":"venue"
},
  "geometry": {"coordinates":[-81.683373,36.18356],"type":"Point"}
}