{
  "type": "Feature",
  "properties": {
    "iso:country":"US",
    "sg:address":"410 Oak St Exd",
    "sg:city":"Forest City",
    "sg:classifiers":[
        {
            "category":"Food & Beverages",
            "subcategory":"Groceries & Convenience Stores",
            "type":"Retail Goods"
        }
    ],
    "sg:phone":"+1 828 287 0017",
    "sg:postcode":"28043",
    "sg:province":"NC",
    "wof:name":"J's General Store",
    "wof:placetype":"venue"
},
  "geometry": {"coordinates":[-81.900553,35.331326],"type":"Point"}
}