{
  "type": "Feature",
  "properties": {
    "addr:full":"1005 S Main St China Grove NC 28023",
    "addr:housenumber":"1005",
    "addr:postcode":"28023",
    "addr:street":"S Main St",
    "iso:country":"US",
    "sg:address":"1005 S Main St",
    "sg:city":"China Grove",
    "sg:classifiers":[
        {
            "category":"Building & Trades",
            "subcategory":"Plumbing",
            "type":"Services"
        }
    ],
    "sg:phone":"+1 704 857 1186",
    "sg:postcode":"28023",
    "sg:province":"NC",
    "sg:tags":[
        "system",
        "heating",
        "air",
        "electrical",
        "conditioning",
        "contractor"
    ],
    "wof:name":"C E Howard Electric Inc",
    "wof:placetype":"venue"
},
  "geometry": {"coordinates":[-80.58602999999999,35.562017],"type":"Point"}
}