{
  "type": "Feature",
  "properties": {
    "iso:country":"US",
    "sg:address":"587 Harrison Ave",
    "sg:city":"Franklin",
    "sg:classifiers":[
        {
            "category":"Autos & Motor Vehicles",
            "subcategory":"Fuel & Gas Station",
            "type":"Retail Goods"
        }
    ],
    "sg:phone":"+1 828 369 8088",
    "sg:postcode":"28734",
    "sg:province":"NC",
    "sg:tags":[
        "station",
        "gasoline"
    ],
    "wof:name":"First Stop Affrdbl Gas & Beer",
    "wof:placetype":"venue"
},
  "geometry": {"coordinates":[-83.389618,35.187439],"type":"Point"}
}