{
  "type": "Feature",
  "properties": {
    "addr:full":"1302 Camden Ave Durham NC 27701",
    "addr:housenumber":"1302",
    "addr:postcode":"27701",
    "addr:street":"Camden Ave",
    "iso:country":"US",
    "sg:address":"1302 Camden Ave",
    "sg:city":"Durham",
    "sg:classifiers":[
        {
            "category":"Retail",
            "subcategory":"Auto Repair",
            "type":"Services"
        }
    ],
    "sg:phone":"+1   ",
    "sg:postcode":"27701",
    "sg:province":"NC",
    "sg:tags":[
        "consulting",
        "management",
        "general"
    ],
    "wof:name":"Durhams Best Cab",
    "wof:placetype":"venue"
},
  "geometry": {"coordinates":[-78.878878,36.01273],"type":"Point"}
}