{
  "type": "Feature",
  "properties": {
    "iso:country":"US",
    "sg:address":"1414 Charles Blvd",
    "sg:city":"Greenville",
    "sg:classifiers":[
        {
            "category":"Personal",
            "subcategory":"Tanning Parlor",
            "type":"Services"
        }
    ],
    "sg:phone":"+1 252 754 2300",
    "sg:postcode":"27858",
    "sg:province":"NC",
    "sg:tags":[
        "salon"
    ],
    "wof:name":"Sunset Professional Tanning",
    "wof:placetype":"venue"
},
  "geometry": {"coordinates":[-77.370732,35.599794],"type":"Point"}
}