{
  "type": "Feature",
  "properties": {
    "addr:full":"8216 US Hwy 158 Stokesdale NC 27357",
    "addr:housenumber":"8216",
    "addr:postcode":"27357",
    "addr:street":"Us Hwy 158",
    "iso:country":"US",
    "sg:address":"8216 US Hwy 158",
    "sg:city":"Stokesdale",
    "sg:classifiers":[
        {
            "category":"Restaurant",
            "type":"Food & Drink"
        }
    ],
    "sg:phone":"+1 336 643 9366",
    "sg:postcode":"27357",
    "sg:province":"NC",
    "sg:tags":[
        "eating",
        "pizza"
    ],
    "wof:name":"Stokey's Pizza",
    "wof:placetype":"venue"
},
  "geometry": {"coordinates":[-79.98034800000001,36.23809],"type":"Point"}
}