{
  "type": "Feature",
  "properties": {
    "iso:country":"US",
    "sg:address":"627 Summit Ave",
    "sg:city":"Greensboro",
    "sg:classifiers":[
        {
            "category":"Health Services",
            "subcategory":"Doctor",
            "type":"Services"
        }
    ],
    "sg:phone":"+1 336 272 3955",
    "sg:postcode":"27405",
    "sg:province":"NC",
    "sg:tags":[
        "physician",
        "surgeon"
    ],
    "wof:name":"Circulation & Chest Clinic",
    "wof:placetype":"venue"
},
  "geometry": {"coordinates":[-79.78063400000001,36.080565],"type":"Point"}
}