{
  "type": "Feature",
  "properties": {
    "addr:full":"2302a Arendell St Morehead City NC 28557",
    "addr:housenumber":"2302a",
    "addr:postcode":"28557",
    "addr:street":"Arendell St",
    "iso:country":"US",
    "sg:address":"2302a Arendell St",
    "sg:city":"Morehead City",
    "sg:classifiers":[
        {
            "category":"Ice Cream",
            "type":"Food & Drink"
        }
    ],
    "sg:menulink":"http://www.allmenus.com/nc/morehead/167637-dairy-queen/menu/",
    "sg:phone":"+1 252 726 5647",
    "sg:postcode":"28557",
    "sg:province":"NC",
    "sg:tags":[
        "burger",
        "american"
    ],
    "wof:name":"Dairy Queen",
    "wof:placetype":"venue"
},
  "geometry": {"coordinates":[-76.734038,34.723087],"type":"Point"}
}