{
  "type": "Feature",
  "properties": {
    "addr:full":"216 Whitson Ave Swannanoa NC 28778",
    "addr:housenumber":"216",
    "addr:postcode":"28778",
    "addr:street":"Whitson Ave",
    "iso:country":"US",
    "sg:address":"216 Whitson Ave",
    "sg:city":"Swannanoa",
    "sg:classifiers":[
        {
            "category":"Organizations",
            "subcategory":"Religious Organization",
            "type":"Services"
        }
    ],
    "sg:phone":"+1   ",
    "sg:postcode":"28778",
    "sg:province":"NC",
    "wof:name":"Swannanoa Untd Methdst Church",
    "wof:placetype":"venue"
},
  "geometry": {"coordinates":[-82.39717,35.600509],"type":"Point"}
}