{
  "type": "Feature",
  "properties": {
    "addr:full":"3016 Pearces Rd Zebulon NC 27597",
    "addr:housenumber":"3016",
    "addr:postcode":"27597",
    "addr:street":"Pearces Rd",
    "iso:country":"US",
    "sg:address":"3016 Pearces Rd",
    "sg:city":"Zebulon",
    "sg:classifiers":[
        {
            "category":"Building & Trades",
            "subcategory":"Landscaping Services",
            "type":"Services"
        }
    ],
    "sg:phone":"+1 919 269 9348",
    "sg:postcode":"27597",
    "sg:province":"NC",
    "sg:tags":[
        "landscape"
    ],
    "wof:name":"Bills Landscaping",
    "wof:placetype":"venue"
},
  "geometry": {"coordinates":[-78.31258800000001,35.891826],"type":"Point"}
}