{
  "type": "Feature",
  "properties": {
    "iso:country":"US",
    "sg:address":"406 N Bridge St",
    "sg:city":"Eden",
    "sg:classifiers":[
        {
            "category":"Retail",
            "subcategory":"Auto Rental",
            "type":"Services"
        }
    ],
    "sg:phone":"+1 336 623 7680",
    "sg:postcode":"27288",
    "sg:province":"NC",
    "sg:tags":[
        "renting",
        "truck",
        "leasing"
    ],
    "wof:name":"Budget Truck Rental",
    "wof:placetype":"venue"
},
  "geometry": {"coordinates":[-79.768922,36.497758],"type":"Point"}
}