{
  "type": "Feature",
  "properties": {
    "iso:country":"US",
    "sg:address":"417 Sunny Dr",
    "sg:city":"Waynesville",
    "sg:classifiers":[
        {
            "category":"Retail",
            "subcategory":"Repair Shop",
            "type":"Services"
        }
    ],
    "sg:phone":"+1 828 648 2111",
    "sg:postcode":"28786",
    "sg:province":"NC",
    "sg:tags":[
        "welding"
    ],
    "wof:name":"Tim's Welding & Fabrication",
    "wof:placetype":"venue"
},
  "geometry": {"coordinates":[-82.89622900000001,35.482207],"type":"Point"}
}