{
  "type": "Feature",
  "properties": {
    "iso:country":"US",
    "sg:address":"839 Rauhut St",
    "sg:city":"Burlington",
    "sg:classifiers":[
        {
            "category":"Food & Beverages",
            "subcategory":"Groceries & Convenience Stores",
            "type":"Retail Goods"
        }
    ],
    "sg:phone":"+1 336 227 7519",
    "sg:postcode":"27217",
    "sg:province":"NC",
    "wof:name":"D P Mini Mart",
    "wof:placetype":"venue"
},
  "geometry": {"coordinates":[-79.43407500000001,36.106251],"type":"Point"}
}