{
  "type": "Feature",
  "properties": {
    "iso:country":"US",
    "sg:address":"4679 Yadkinville Rd",
    "sg:city":"Pfafftown",
    "sg:classifiers":[
        {
            "category":"Building & Trades",
            "subcategory":"Construction",
            "type":"Services"
        }
    ],
    "sg:phone":"+1 336 922 2264",
    "sg:postcode":"27040",
    "sg:province":"NC",
    "sg:tags":[
        "stone",
        "setting",
        "contractor"
    ],
    "wof:name":"Grandview Rock Yard",
    "wof:placetype":"venue"
},
  "geometry": {"coordinates":[-80.35995699999999,36.153158],"type":"Point"}
}