{
  "type": "Feature",
  "properties": {
    "addr:full":"129 Victory Grove Church Rd Lincolnton NC 28092",
    "addr:housenumber":"129",
    "addr:postcode":"28092",
    "addr:street":"Victory Grove Church Rd",
    "iso:country":"US",
    "sg:address":"129 Victory Grove Church Rd",
    "sg:city":"Lincolnton",
    "sg:classifiers":[
        {
            "category":"Wholesale",
            "subcategory":"Machinery & Supplies",
            "type":"Manufacturing & Wholesale Goods"
        }
    ],
    "sg:phone":"+1 704 732 7000",
    "sg:postcode":"28092",
    "sg:province":"NC",
    "wof:name":"Mid-South Machinery Sales",
    "wof:placetype":"venue"
},
  "geometry": {"coordinates":[-81.239425,35.451655],"type":"Point"}
}