{
  "type": "Feature",
  "properties": {
    "iso:country":"US",
    "sg:address":"228 Eastwood Rd",
    "sg:city":"Wilmington",
    "sg:classifiers":[
        {
            "category":"Restaurant",
            "type":"Food & Drink"
        }
    ],
    "sg:menulink":"http://www.allmenus.com/nc/wilmington/140795-michaelangelos-pizza--subs/menu/",
    "sg:phone":"+1 910 790 3163",
    "sg:postcode":"28403",
    "sg:province":"NC",
    "sg:tags":[
        "american",
        "pizza"
    ],
    "wof:name":"Michaelangelos Pizza & Subs",
    "wof:placetype":"venue"
},
  "geometry": {"coordinates":[-77.86272,34.245001],"type":"Point"}
}