{
  "type": "Feature",
  "properties": {
    "addr:full":"809 Wittenburg Rd Taylorsville NC 28681",
    "addr:housenumber":"809",
    "addr:postcode":"28681",
    "addr:street":"Wittenburg Rd",
    "iso:country":"US",
    "sg:address":"809 Wittenburg Rd",
    "sg:city":"Taylorsville",
    "sg:classifiers":[
        {
            "category":"Recreation",
            "type":"Entertainment"
        }
    ],
    "sg:phone":"+1 828 632 1104",
    "sg:postcode":"28681",
    "sg:province":"NC",
    "sg:tags":[
        "parks"
    ],
    "wof:name":"Alexander County Recreation",
    "wof:placetype":"venue"
},
  "geometry": {"coordinates":[-81.173096,35.837438],"type":"Point"}
}