{
  "type": "Feature",
  "properties": {
    "iso:country":"US",
    "sg:address":"5134 Revere Rd",
    "sg:city":"Durham",
    "sg:classifiers":[
        {
            "category":"Building & Trades",
            "subcategory":"Construction",
            "type":"Services"
        }
    ],
    "sg:phone":"+1 919 544 3104",
    "sg:postcode":"27713",
    "sg:province":"NC",
    "sg:tags":[
        "contractor"
    ],
    "wof:name":"Yg Contractors",
    "wof:placetype":"venue"
},
  "geometry": {"coordinates":[-78.90916900000001,35.892936],"type":"Point"}
}