{
  "type": "Feature",
  "properties": {
    "addr:full":"300 N Broad St Edenton NC 27932",
    "addr:housenumber":"300",
    "addr:postcode":"27932",
    "addr:street":"N Broad St",
    "iso:country":"US",
    "sg:address":"300 N Broad St",
    "sg:city":"Edenton",
    "sg:classifiers":[
        {
            "category":"Real Estate",
            "subcategory":"Real Estate Operator",
            "type":"Services"
        }
    ],
    "sg:phone":"+1 252 482 7771",
    "sg:postcode":"27932",
    "sg:province":"NC",
    "sg:tags":[
        "building",
        "apartment"
    ],
    "wof:name":"B Edwards Arch Co",
    "wof:placetype":"venue"
},
  "geometry": {"coordinates":[-76.6073,36.063948],"type":"Point"}
}