{
  "type": "Feature",
  "properties": {
    "addr:full":"113 Vaughan Ln Currituck NC 27929",
    "addr:housenumber":"113",
    "addr:postcode":"27929",
    "addr:street":"Vaughan Ln",
    "iso:country":"US",
    "sg:address":"113 Vaughan Ln",
    "sg:city":"Currituck",
    "sg:classifiers":[
        {
            "category":"Retail",
            "subcategory":"Repair Shop",
            "type":"Services"
        }
    ],
    "sg:phone":"+1   ",
    "sg:postcode":"27929",
    "sg:province":"NC",
    "wof:name":"Dd Duct Cleaning LLC",
    "wof:placetype":"venue"
},
  "geometry": {"coordinates":[-76.00142099999999,36.434751],"type":"Point"}
}