{
  "type": "Feature",
  "properties": {
    "addr:full":"1737 S Scales St Reidsville NC 27320",
    "addr:housenumber":"1737",
    "addr:postcode":"27320",
    "addr:street":"S Scales St",
    "iso:country":"US",
    "sg:address":"1737 S Scales St",
    "sg:city":"Reidsville",
    "sg:classifiers":[
        {
            "category":"Real Estate",
            "subcategory":"Real Estate Operator",
            "type":"Services"
        }
    ],
    "sg:phone":"+1 336 342 6913",
    "sg:postcode":"27320",
    "sg:province":"NC",
    "sg:tags":[
        "building",
        "apartment"
    ],
    "wof:name":"Jackson Hobart Apartments",
    "wof:placetype":"venue"
},
  "geometry": {"coordinates":[-79.6634,36.337375],"type":"Point"}
}