{
  "type": "Feature",
  "properties": {
    "iso:country":"US",
    "sg:address":"1325 W Pine St",
    "sg:city":"Mount Airy",
    "sg:classifiers":[
        {
            "category":"Retail",
            "subcategory":"Repair Shop",
            "type":"Services"
        }
    ],
    "sg:phone":"+1   ",
    "sg:postcode":"27030",
    "sg:province":"NC",
    "wof:name":"Shelton Key & Lock",
    "wof:placetype":"venue"
},
  "geometry": {"coordinates":[-80.636252,36.501237],"type":"Point"}
}