{
  "type": "Feature",
  "properties": {
    "iso:country":"US",
    "sg:address":"1901 Landon Farms Ln",
    "sg:city":"Durham",
    "sg:classifiers":[
        {
            "category":"Building & Trades",
            "subcategory":"Construction",
            "type":"Services"
        }
    ],
    "sg:phone":"+1 919 956 2700",
    "sg:postcode":"27704",
    "sg:province":"NC",
    "sg:tags":[
        "home",
        "builder"
    ],
    "wof:name":"Anderson Homes Inc",
    "wof:placetype":"venue"
},
  "geometry": {"coordinates":[-78.84771499999999,36.01958],"type":"Point"}
}