{
  "type": "Feature",
  "properties": {
    "iso:country":"US",
    "sg:address":"1004 Parkview Dr",
    "sg:city":"Elizabeth City",
    "sg:classifiers":[
        {
            "category":"Education",
            "subcategory":"School",
            "type":"Public Place"
        }
    ],
    "sg:phone":"+1 252 335 1765",
    "sg:postcode":"27909",
    "sg:province":"NC",
    "sg:website":"www.ecpps.k12.nc.us",
    "wof:name":"H L Trigg Elementary School",
    "wof:placetype":"venue"
},
  "geometry": {"coordinates":[-76.21289299999999,36.285291],"type":"Point"}
}