{
  "type": "Feature",
  "properties": {
    "addr:full":"702 E 4th Ave Red Springs NC 28377",
    "addr:housenumber":"702",
    "addr:postcode":"28377",
    "addr:street":"E 4Th Ave",
    "iso:country":"US",
    "sg:address":"702 E 4th Ave",
    "sg:city":"Red Springs",
    "sg:classifiers":[
        {
            "category":"Insurance",
            "subcategory":"Insurance Agent",
            "type":"Services"
        }
    ],
    "sg:phone":"+1 910 843 2125",
    "sg:postcode":"28377",
    "sg:province":"NC",
    "wof:name":"G & M Insurance Agency Inc",
    "wof:placetype":"venue"
},
  "geometry": {"coordinates":[-79.17542,34.811495],"type":"Point"}
}