{
  "type": "Feature",
  "properties": {
    "iso:country":"US",
    "sg:address":"3242 Commonwealth Ave",
    "sg:city":"Charlotte",
    "sg:classifiers":[
        {
            "category":"Professional",
            "subcategory":"Business Services",
            "type":"Services"
        }
    ],
    "sg:phone":"+1 704 347 0347",
    "sg:postcode":"28205",
    "sg:province":"NC",
    "sg:website":"www.carolinabusiness.com",
    "wof:name":"Carolina Business Review",
    "wof:placetype":"venue"
},
  "geometry": {"coordinates":[-80.79192399999999,35.20844],"type":"Point"}
}