{
  "type": "Feature",
  "properties": {
    "iso:country":"US",
    "sg:address":"140 Corporate Blvd",
    "sg:city":"Indian Trail",
    "sg:classifiers":[
        {
            "category":"Manufacturing",
            "subcategory":"Building Materials",
            "type":"Manufacturing & Wholesale Goods"
        }
    ],
    "sg:phone":"+1 704 821 8799",
    "sg:postcode":"28079",
    "sg:province":"NC",
    "wof:name":"Carolina Trim Specialties",
    "wof:placetype":"venue"
},
  "geometry": {"coordinates":[-80.65685499999999,35.080228],"type":"Point"}
}