{
  "type": "Feature",
  "properties": {
    "iso:country":"US",
    "sg:address":"394 Bear Creek Rd",
    "sg:city":"Hubert",
    "sg:classifiers":[
        {
            "category":"Organizations",
            "subcategory":"Religious Organization",
            "type":"Services"
        }
    ],
    "sg:phone":"+1 910 326 3454",
    "sg:postcode":"28539",
    "sg:province":"NC",
    "sg:tags":[
        "church"
    ],
    "wof:name":"Oak Grove United Methodist Chr",
    "wof:placetype":"venue"
},
  "geometry": {"coordinates":[-77.208533,34.658967],"type":"Point"}
}