{
  "type": "Feature",
  "properties": {
    "addr:full":"125 Old Wilkesboro Rd Exd Taylorsville NC 28681",
    "addr:housenumber":"125",
    "addr:postcode":"28681",
    "addr:street":"Old Wilkesboro Rd Exd",
    "iso:country":"US",
    "sg:address":"125 Old Wilkesboro Rd Exd",
    "sg:city":"Taylorsville",
    "sg:classifiers":[
        {
            "category":"Social Services",
            "type":"Services"
        }
    ],
    "sg:phone":"+1 828 635 8500",
    "sg:postcode":"28681",
    "sg:province":"NC",
    "sg:tags":[
        "professional",
        "counselor"
    ],
    "wof:name":"Alexander Counseling",
    "wof:placetype":"venue"
},
  "geometry": {"coordinates":[-81.196258,35.957122],"type":"Point"}
}