{
  "type": "Feature",
  "properties": {
    "addr:full":"1607 Fairgrove Church Rd SE Conover NC 28613",
    "addr:housenumber":"1607",
    "addr:postcode":"28613",
    "addr:street":"Fairgrove Church Rd Se",
    "iso:country":"US",
    "sg:address":"1607 Fairgrove Church Rd SE",
    "sg:city":"Conover",
    "sg:classifiers":[
        {
            "category":"Restaurant",
            "type":"Food & Drink"
        }
    ],
    "sg:menulink":"http://www.allmenus.com/nc/newton/238983-harbor-inn/menu/",
    "sg:phone":"+1 828 465 6641",
    "sg:postcode":"28613",
    "sg:province":"NC",
    "sg:tags":[
        "seafood",
        "american"
    ],
    "wof:name":"Harbor Inn",
    "wof:placetype":"venue"
},
  "geometry": {"coordinates":[-81.261889,35.699652],"type":"Point"}
}