{
  "type": "Feature",
  "properties": {
    "addr:full":"2195 Civietown Rd SW Supply NC 28462",
    "addr:housenumber":"2195",
    "addr:postcode":"28462",
    "addr:street":"Civietown Rd Sw",
    "iso:country":"US",
    "sg:address":"2195 Civietown Rd SW",
    "sg:city":"Supply",
    "sg:classifiers":[
        {
            "category":"Building & Trades",
            "subcategory":"Construction",
            "type":"Services"
        }
    ],
    "sg:phone":"+1 910 754 4765",
    "sg:postcode":"28462",
    "sg:province":"NC",
    "sg:tags":[
        "house"
    ],
    "wof:name":"Robert Hewett Construction",
    "wof:placetype":"venue"
},
  "geometry": {"coordinates":[-78.328592,33.96786],"type":"Point"}
}