{
  "type": "Feature",
  "properties": {
    "addr:full":"1135 N Bragg Blvd Spring Lake NC 28390",
    "addr:housenumber":"1135",
    "addr:postcode":"28390",
    "addr:street":"N Bragg Blvd",
    "iso:country":"US",
    "sg:address":"1135 N Bragg Blvd",
    "sg:city":"Spring Lake",
    "sg:classifiers":[
        {
            "category":"Shopping",
            "subcategory":"Clothing, Apparel, & Fashions",
            "type":"Retail Goods"
        }
    ],
    "sg:phone":"+1 910 436 3755",
    "sg:postcode":"28390",
    "sg:province":"NC",
    "wof:name":"Kahn Fashions",
    "wof:placetype":"venue"
},
  "geometry": {"coordinates":[-78.98161500000001,35.18058],"type":"Point"}
}