{
  "type": "Feature",
  "properties": {
    "addr:full":"1517 Industrial Dr Matthews NC 28105",
    "addr:housenumber":"1517",
    "addr:postcode":"28105",
    "addr:street":"Industrial Dr",
    "iso:country":"US",
    "sg:address":"1517 Industrial Dr",
    "sg:city":"Matthews",
    "sg:classifiers":[
        {
            "category":"Retail",
            "subcategory":"Repair Shop",
            "type":"Services"
        },
        {
            "category":"Professional",
            "subcategory":"Art Services",
            "type":"Services"
        },
        {
            "category":"Shopping",
            "subcategory":"Antiques",
            "type":"Retail Goods"
        },
        {
            "category":"Manufacturing",
            "subcategory":"Furniture",
            "type":"Manufacturing & Wholesale Goods"
        }
    ],
    "sg:phone":"+1 704 845 0550",
    "sg:postcode":"28105",
    "sg:province":"NC",
    "sg:tags":[
        "designer",
        "refinish",
        "custom",
        "refacing",
        "resurfacing",
        "restoration",
        "builder",
        "cabinets-refinishing"
    ],
    "sg:website":"http://www.gravesfurnitureshop.com",
    "wof:name":"Graves Furniture Shop",
    "wof:placetype":"venue"
},
  "geometry": {"coordinates":[-80.728629,35.131772],"type":"Point"}
}