{
  "type": "Feature",
  "properties": {
    "iso:country":"US",
    "sg:address":"3200 Rotary Dr",
    "sg:city":"Charlotte",
    "sg:classifiers":[
        {
            "category":"Travel",
            "subcategory":"Hotels & Motels",
            "type":"Entertainment"
        }
    ],
    "sg:phone":"+1 704 398 3144",
    "sg:postcode":"28269",
    "sg:province":"NC",
    "sg:tags":[
        "lodging"
    ],
    "wof:name":"Americas Best Value Inn & Suites Charlotte",
    "wof:placetype":"venue"
},
  "geometry": {"coordinates":[-80.825958,35.274731],"type":"Point"}
}