{
  "type": "Feature",
  "properties": {
    "addr:full":"1130 Old Greensboro Rd Kernersville NC 27284",
    "addr:housenumber":"1130",
    "addr:postcode":"27284",
    "addr:street":"Old Greensboro Rd",
    "iso:country":"US",
    "sg:address":"1130 Old Greensboro Rd",
    "sg:city":"Kernersville",
    "sg:classifiers":[
        {
            "category":"Professional",
            "type":"Services"
        }
    ],
    "sg:phone":"+1 336 993 1499",
    "sg:postcode":"27284",
    "sg:province":"NC",
    "wof:name":"Inphaze LLC",
    "wof:placetype":"venue"
},
  "geometry": {"coordinates":[-80.048023,36.108776],"type":"Point"}
}