{
  "type": "Feature",
  "properties": {
    "addr:full":"1418 Dellwood Rd Waynesville NC 28786",
    "addr:housenumber":"1418",
    "addr:postcode":"28786",
    "addr:street":"Dellwood Rd",
    "iso:country":"US",
    "sg:address":"1418 Dellwood Rd",
    "sg:city":"Waynesville",
    "sg:classifiers":[
        {
            "category":"Professional",
            "subcategory":"Computer Services",
            "type":"Services"
        }
    ],
    "sg:phone":"+1 828 926 8252",
    "sg:postcode":"28786",
    "sg:province":"NC",
    "sg:tags":[
        "programming",
        "custom"
    ],
    "wof:name":"E-Quest Software Corporation",
    "wof:placetype":"venue"
},
  "geometry": {"coordinates":[-82.98896000000001,35.526166],"type":"Point"}
}