{
  "type": "Feature",
  "properties": {
    "addr:full":"2023 Mallard Woods Pl Charlotte NC 28262",
    "addr:housenumber":"2023",
    "addr:postcode":"28262",
    "addr:street":"Mallard Woods Pl",
    "iso:country":"US",
    "sg:address":"2023 Mallard Woods Pl",
    "sg:city":"Charlotte",
    "sg:classifiers":[
        {
            "category":"Professional",
            "subcategory":"Computer Services",
            "type":"Services"
        }
    ],
    "sg:phone":"+1 704 549 8152",
    "sg:postcode":"28262",
    "sg:province":"NC",
    "sg:tags":[
        "publisher",
        "software",
        "developer",
        "services-wholesale"
    ],
    "wof:name":"Kristin Stewart",
    "wof:placetype":"venue"
},
  "geometry": {"coordinates":[-80.745981,35.358356],"type":"Point"}
}