{
  "type": "Feature",
  "properties": {
    "addr:full":"1015 S Main St Laurinburg NC 28352",
    "addr:housenumber":"1015",
    "addr:postcode":"28352",
    "addr:street":"S Main St",
    "iso:country":"US",
    "sg:address":"1015 S Main St",
    "sg:city":"Laurinburg",
    "sg:classifiers":[
        {
            "category":"Shopping",
            "subcategory":"Tobacco",
            "type":"Retail Goods"
        }
    ],
    "sg:phone":"+1 910 276 2322",
    "sg:postcode":"28352",
    "sg:province":"NC",
    "sg:tags":[
        "cigarette",
        "cigar",
        "dealer"
    ],
    "wof:name":"Easy Bass Tobacco Outlet",
    "wof:placetype":"venue"
},
  "geometry": {"coordinates":[-79.467862,34.764433],"type":"Point"}
}