{
  "type": "Feature",
  "properties": {
    "addr:full":"119 S Fayetteville St Liberty NC 27298",
    "addr:housenumber":"119",
    "addr:postcode":"27298",
    "addr:street":"S Fayetteville St",
    "iso:country":"US",
    "sg:address":"119 S Fayetteville St",
    "sg:city":"Liberty",
    "sg:classifiers":[
        {
            "category":"Restaurant",
            "type":"Food & Drink"
        }
    ],
    "sg:phone":"+1 336 622 2984",
    "sg:postcode":"27298",
    "sg:province":"NC",
    "wof:name":"Marco Polo's",
    "wof:placetype":"venue"
},
  "geometry": {"coordinates":[-79.57046200000001,35.853117],"type":"Point"}
}