{
  "type": "Feature",
  "properties": {
    "iso:country":"US",
    "sg:address":"4446 US Hwy 220",
    "sg:city":"Summerfield",
    "sg:classifiers":[
        {
            "category":"Shopping",
            "subcategory":"Pharmacy",
            "type":"Retail Goods"
        }
    ],
    "sg:phone":"+1 336 644 7058",
    "sg:postcode":"27358",
    "sg:province":"NC",
    "wof:name":"Summerfield Pharmacy",
    "wof:placetype":"venue"
},
  "geometry": {"coordinates":[-79.888317,36.184003],"type":"Point"}
}