{
  "type": "Feature",
  "properties": {
    "addr:full":"7975 Old Beatty Ford Rd Rockwell NC 28138",
    "addr:housenumber":"7975",
    "addr:postcode":"28138",
    "addr:street":"Old Beatty Ford Rd",
    "iso:country":"US",
    "sg:address":"7975 Old Beatty Ford Rd",
    "sg:city":"Rockwell",
    "sg:classifiers":[
        {
            "category":"Building & Trades",
            "subcategory":"Landscaping Services",
            "type":"Services"
        }
    ],
    "sg:phone":"+1 704 279 3521",
    "sg:postcode":"28138",
    "sg:province":"NC",
    "sg:tags":[
        "ways",
        "tree",
        "drive",
        "construct"
    ],
    "wof:name":"Joe Moore's Tree & Yard Work",
    "wof:placetype":"venue"
},
  "geometry": {"coordinates":[-80.48365699999999,35.521647],"type":"Point"}
}