{
  "type": "Feature",
  "properties": {
    "addr:full":"14425 Adair Manor Ct Charlotte NC 28277",
    "addr:housenumber":"14425",
    "addr:postcode":"28277",
    "addr:street":"Adair Manor Ct",
    "iso:country":"US",
    "sg:address":"14425 Adair Manor Ct",
    "sg:city":"Charlotte",
    "sg:classifiers":[
        {
            "category":"Recreation",
            "type":"Entertainment"
        }
    ],
    "sg:phone":"+1 704 544 0419",
    "sg:postcode":"28277",
    "sg:province":"NC",
    "sg:tags":[
        "club",
        "membership"
    ],
    "wof:name":"Eastway Beach Bingo",
    "wof:placetype":"venue"
},
  "geometry": {"coordinates":[-80.866727,35.049238],"type":"Point"}
}