{
  "type": "Feature",
  "properties": {
    "addr:full":"2100 Crescent Ave Charlotte NC 28207",
    "addr:housenumber":"2100",
    "addr:postcode":"28207",
    "addr:street":"Crescent Ave",
    "iso:country":"US",
    "sg:address":"2100 Crescent Ave",
    "sg:city":"Charlotte",
    "sg:classifiers":[
        {
            "category":"Professional",
            "subcategory":"Lawyer & Legal Services",
            "type":"Services"
        }
    ],
    "sg:phone":"+1   ",
    "sg:postcode":"28207",
    "sg:province":"NC",
    "wof:name":"Attorney At Law",
    "wof:placetype":"venue"
},
  "geometry": {"coordinates":[-80.82102399999999,35.205427],"type":"Point"}
}