{
  "type": "Feature",
  "properties": {
    "iso:country":"US",
    "sg:address":"3204 Selwyn Ave",
    "sg:city":"Charlotte",
    "sg:classifiers":[
        {
            "category":"Professional",
            "subcategory":"Computer Services",
            "type":"Services"
        }
    ],
    "sg:phone":"+1 704 523 9493",
    "sg:postcode":"28209",
    "sg:province":"NC",
    "sg:tags":[
        "development",
        "system",
        "software"
    ],
    "wof:name":"Multimedia Design Corporation",
    "wof:placetype":"venue"
},
  "geometry": {"coordinates":[-80.84129299999999,35.170904],"type":"Point"}
}