{
  "type": "Feature",
  "properties": {
    "iso:country":"US",
    "sg:address":"5115 Raeford Rd",
    "sg:city":"Fayetteville",
    "sg:classifiers":[
        {
            "category":"Manufacturing",
            "subcategory":"Apparel",
            "type":"Manufacturing & Wholesale Goods"
        }
    ],
    "sg:phone":"+1 910 423 0270",
    "sg:postcode":"28304",
    "sg:province":"NC",
    "sg:tags":[
        "clothing",
        "mfg"
    ],
    "wof:name":"NYC Mensware",
    "wof:placetype":"venue"
},
  "geometry": {"coordinates":[-78.964085,35.042563],"type":"Point"}
}