{
  "type": "Feature",
  "properties": {
    "addr:full":"406 Deep Creek Rd Fayetteville NC 28312",
    "addr:housenumber":"406",
    "addr:postcode":"28312",
    "addr:street":"Deep Creek Rd",
    "iso:country":"US",
    "sg:address":"406 Deep Creek Rd",
    "sg:city":"Fayetteville",
    "sg:classifiers":[
        {
            "category":"Social Services",
            "type":"Services"
        }
    ],
    "sg:phone":"+1 910 485 8809",
    "sg:postcode":"28312",
    "sg:province":"NC",
    "sg:tags":[
        "food",
        "banks",
        "organization",
        "welfare"
    ],
    "wof:name":"Second Harvest Food Bank",
    "wof:placetype":"venue"
},
  "geometry": {"coordinates":[-78.854381,35.040516],"type":"Point"}
}