{
  "type": "Feature",
  "properties": {
    "iso:country":"US",
    "sg:address":"135 Scaleybark Rd",
    "sg:city":"Charlotte",
    "sg:classifiers":[
        {
            "category":"Real Estate",
            "subcategory":"Real Estate Agent",
            "type":"Services"
        }
    ],
    "sg:phone":"+1 704 529 6098",
    "sg:postcode":"28209",
    "sg:province":"NC",
    "sg:website":"www.croslandgroup.com",
    "wof:name":"Crosland Group Inc",
    "wof:placetype":"venue"
},
  "geometry": {"coordinates":[-80.87335,35.187905],"type":"Point"}
}