{
  "type": "Feature",
  "properties": {
    "addr:full":"100 US Hwy 52 Albemarle NC 28001",
    "addr:housenumber":"100",
    "addr:postcode":"28001",
    "addr:street":"Us Hwy 52",
    "iso:country":"US",
    "sg:address":"100 US Hwy 52",
    "sg:city":"Albemarle",
    "sg:classifiers":[
        {
            "category":"Food & Beverages",
            "subcategory":"Groceries & Convenience Stores",
            "type":"Retail Goods"
        },
        {
            "category":"Mining & Drilling",
            "type":"Manufacturing & Wholesale Goods"
        }
    ],
    "sg:phone":"+1 704 983 2270",
    "sg:postcode":"28001",
    "sg:province":"NC",
    "sg:tags":[
        "crude",
        "production",
        "gas"
    ],
    "wof:name":"Quick Check 18",
    "wof:placetype":"venue"
},
  "geometry": {"coordinates":[-80.206299,35.354642],"type":"Point"}
}