{
  "type": "Feature",
  "properties": {
    "iso:country":"US",
    "sg:address":"1482 Furr Rd",
    "sg:city":"Vass",
    "sg:classifiers":[
        {
            "category":"Retail",
            "subcategory":"Auto Repair",
            "type":"Services"
        }
    ],
    "sg:phone":"+1   ",
    "sg:postcode":"28394",
    "sg:province":"NC",
    "sg:tags":[
        "general"
    ],
    "wof:name":"Hoovers U Cars Pattersons Gar",
    "wof:placetype":"venue"
},
  "geometry": {"coordinates":[-79.31716400000001,35.208998],"type":"Point"}
}