{
  "type": "Feature",
  "properties": {
    "iso:country":"US",
    "sg:address":"1106 Turnpike Rd",
    "sg:city":"Fayetteville",
    "sg:classifiers":[
        {
            "category":"Government",
            "subcategory":"Fire Station",
            "type":"Public Place"
        }
    ],
    "sg:phone":"+1 910 875 4256",
    "sg:postcode":"28305",
    "sg:province":"NC",
    "sg:tags":[
        "department"
    ],
    "wof:name":"North Raeford Fire Dept",
    "wof:placetype":"venue"
},
  "geometry": {"coordinates":[-78.898219,35.050624],"type":"Point"}
}