{
  "type": "Feature",
  "properties": {
    "addr:full":"615 N Salisbury Ave Spencer NC 28159",
    "addr:housenumber":"615",
    "addr:postcode":"28159",
    "addr:street":"N Salisbury Ave",
    "iso:country":"US",
    "sg:address":"615 N Salisbury Ave",
    "sg:city":"Spencer",
    "sg:classifiers":[
        {
            "category":"Restaurant",
            "type":"Food & Drink"
        }
    ],
    "sg:phone":"+1 704 633 1094",
    "sg:postcode":"28159",
    "sg:province":"NC",
    "sg:tags":[
        "barbecue"
    ],
    "wof:name":"Jim's Bar-B-Q",
    "wof:placetype":"venue"
},
  "geometry": {"coordinates":[-80.421976,35.694617],"type":"Point"}
}