{
  "type": "Feature",
  "properties": {
    "iso:country":"US",
    "sg:address":"259 Goose Creek Rd",
    "sg:city":"Washington",
    "sg:classifiers":[
        {
            "category":"Building & Trades",
            "subcategory":"Construction",
            "type":"Services"
        }
    ],
    "sg:phone":"+1 252 975 3215",
    "sg:postcode":"27889",
    "sg:province":"NC",
    "sg:tags":[
        "house",
        "general",
        "contractor"
    ],
    "wof:name":"Goose Creek Construction Inc",
    "wof:placetype":"venue"
},
  "geometry": {"coordinates":[-76.926501,35.511968],"type":"Point"}
}