{
  "type": "Feature",
  "properties": {
    "addr:full":"2721 Guess Rd Durham NC 27705",
    "addr:housenumber":"2721",
    "addr:postcode":"27705",
    "addr:street":"Guess Rd",
    "iso:country":"US",
    "sg:address":"2721 Guess Rd",
    "sg:city":"Durham",
    "sg:classifiers":[
        {
            "category":"Restaurant",
            "type":"Food & Drink"
        }
    ],
    "sg:phone":"+1 919 479 2134",
    "sg:postcode":"27705",
    "sg:province":"NC",
    "wof:name":"Puobla Express",
    "wof:placetype":"venue"
},
  "geometry": {"coordinates":[-78.92564,36.028652],"type":"Point"}
}