{
  "type": "Feature",
  "properties": {
    "addr:full":"103 E Broad St Statesville NC 28677",
    "addr:housenumber":"103",
    "addr:postcode":"28677",
    "addr:street":"E Broad St",
    "iso:country":"US",
    "sg:address":"103 E Broad St",
    "sg:city":"Statesville",
    "sg:classifiers":[
        {
            "category":"Shopping",
            "subcategory":"Clothing, Apparel, & Fashions",
            "type":"Retail Goods"
        }
    ],
    "sg:phone":"+1 704 873 1900",
    "sg:postcode":"28677",
    "sg:province":"NC",
    "sg:tags":[
        "boy",
        "man"
    ],
    "wof:name":"Styles New York",
    "wof:placetype":"venue"
},
  "geometry": {"coordinates":[-80.88606299999999,35.785414],"type":"Point"}
}