{
  "type": "Feature",
  "properties": {
    "addr:full":"3120 Garden Rd Burlington NC 27215",
    "addr:housenumber":"3120",
    "addr:postcode":"27215",
    "addr:street":"Garden Rd",
    "iso:country":"US",
    "sg:address":"3120 Garden Rd",
    "sg:city":"Burlington",
    "sg:classifiers":[
        {
            "category":"Restaurant",
            "type":"Food & Drink"
        },
        {
            "category":"Ice Cream",
            "type":"Food & Drink"
        }
    ],
    "sg:menulink":"http://www.allmenus.com/nc/boone-station/92659-steak-n-shake/menu/",
    "sg:phone":"+1 336 585 1222",
    "sg:postcode":"27215",
    "sg:province":"NC",
    "sg:tags":[
        "american",
        "ice",
        "cream"
    ],
    "wof:name":"Steak 'n Shake",
    "wof:placetype":"venue"
},
  "geometry": {"coordinates":[-79.49935000000001,36.069006],"type":"Point"}
}