{
  "type": "Feature",
  "properties": {
    "iso:country":"US",
    "sg:address":"2333 Pax Hill Rd",
    "sg:city":"Morganton",
    "sg:classifiers":[
        {
            "category":"Professional",
            "subcategory":"Management & Consulting",
            "type":"Services"
        }
    ],
    "sg:phone":"+1   ",
    "sg:postcode":"28655",
    "sg:province":"NC",
    "sg:tags":[
        "business"
    ],
    "wof:name":"Rosenberger Ent Inc",
    "wof:placetype":"venue"
},
  "geometry": {"coordinates":[-81.661372,35.811175],"type":"Point"}
}