{
  "type": "Feature",
  "properties": {
    "addr:full":"1940 State Hwy 172 Sneads Ferry NC 28460",
    "addr:housenumber":"1940",
    "addr:postcode":"28460",
    "addr:street":"State Hwy 172",
    "iso:country":"US",
    "sg:address":"1940 State Hwy 172",
    "sg:city":"Sneads Ferry",
    "sg:classifiers":[
        {
            "category":"Banks & Credit Unions",
            "subcategory":"Bank",
            "type":"Services"
        }
    ],
    "sg:phone":"+1 910 327 0364",
    "sg:postcode":"28460",
    "sg:province":"NC",
    "sg:tags":[
        "loan",
        "broker"
    ],
    "wof:name":"All Fund",
    "wof:placetype":"venue"
},
  "geometry": {"coordinates":[-77.451537,34.547018],"type":"Point"}
}