{
  "type": "Feature",
  "properties": {
    "iso:country":"US",
    "sg:address":"2714 Union Church Rd",
    "sg:city":"Lincolnton",
    "sg:classifiers":[
        {
            "category":"Wholesale",
            "subcategory":"Non-durable Goods",
            "type":"Manufacturing & Wholesale Goods"
        }
    ],
    "sg:phone":"+1 704 633 1317",
    "sg:postcode":"28092",
    "sg:province":"NC",
    "sg:tags":[
        "advertising",
        "specialty"
    ],
    "wof:name":"Hank Palmer & Associates Inc",
    "wof:placetype":"venue"
},
  "geometry": {"coordinates":[-81.16259100000001,35.534996],"type":"Point"}
}