{
  "type": "Feature",
  "properties": {
    "addr:full":"2661 W Roosevelt Blvd Monroe NC 28110",
    "addr:housenumber":"2661",
    "addr:postcode":"28110",
    "addr:street":"W Roosevelt Blvd",
    "iso:country":"US",
    "sg:address":"2661 W Roosevelt Blvd",
    "sg:city":"Monroe",
    "sg:classifiers":[
        {
            "category":"Shopping",
            "type":"Retail Goods"
        }
    ],
    "sg:phone":"+1 704 604 2720",
    "sg:postcode":"28110",
    "sg:province":"NC",
    "sg:tags":[
        "merchandise"
    ],
    "wof:name":"Medlink",
    "wof:placetype":"venue"
},
  "geometry": {"coordinates":[-80.57454300000001,35.017967],"type":"Point"}
}