{
  "type": "Feature",
  "properties": {
    "addr:full":"5360 Barrier Store Rd Mount Pleasant NC 28124",
    "addr:housenumber":"5360",
    "addr:postcode":"28124",
    "addr:street":"Barrier Store Rd",
    "iso:country":"US",
    "sg:address":"5360 Barrier Store Rd",
    "sg:city":"Mount Pleasant",
    "sg:classifiers":[
        {
            "category":"Farming",
            "subcategory":"Farm",
            "type":"Manufacturing & Wholesale Goods"
        }
    ],
    "sg:phone":"+1 704 436 2454",
    "sg:postcode":"28124",
    "sg:province":"NC",
    "sg:tags":[
        "crop",
        "general"
    ],
    "wof:name":"Landon Barrier",
    "wof:placetype":"venue"
},
  "geometry": {"coordinates":[-80.420796,35.353536],"type":"Point"}
}