{
  "type": "Feature",
  "properties": {
    "addr:full":"37775 US Hwy 52 New London NC 28127",
    "addr:postcode":"37775;28127",
    "addr:street":"Us Hwy 52",
    "iso:country":"US",
    "sg:address":"37775 US Hwy 52",
    "sg:city":"New London",
    "sg:classifiers":[
        {
            "category":"Autos & Motor Vehicles",
            "subcategory":"Automobile Sales",
            "type":"Retail Goods"
        }
    ],
    "sg:phone":"+1 704 463 4400",
    "sg:postcode":"28127",
    "sg:province":"NC",
    "sg:tags":[
        "used"
    ],
    "wof:name":"City Motors",
    "wof:placetype":"venue"
},
  "geometry": {"coordinates":[-80.20396599999999,35.411156],"type":"Point"}
}