{
  "type": "Feature",
  "properties": {
    "iso:country":"US",
    "sg:address":"615 W Friendly Ave",
    "sg:city":"Greensboro",
    "sg:classifiers":[
        {
            "category":"Professional",
            "subcategory":"Computer Services",
            "type":"Services"
        }
    ],
    "sg:phone":"+1 336 379 9029",
    "sg:postcode":"27401",
    "sg:province":"NC",
    "sg:tags":[
        "datum"
    ],
    "wof:name":"Fiserv",
    "wof:placetype":"venue"
},
  "geometry": {"coordinates":[-79.79942800000001,36.073853],"type":"Point"}
}