{
  "type": "Feature",
  "properties": {
    "addr:full":"202 US Hwy 264 Manteo NC 27954",
    "addr:housenumber":"202",
    "addr:postcode":"27954",
    "addr:street":"Us Hwy 264",
    "iso:country":"US",
    "sg:address":"202 US Hwy 264",
    "sg:city":"Manteo",
    "sg:classifiers":[
        {
            "category":"Food & Beverages",
            "subcategory":"Groceries & Convenience Stores",
            "type":"Retail Goods"
        }
    ],
    "sg:phone":"+1 252 475 1095",
    "sg:postcode":"27954",
    "sg:province":"NC",
    "wof:name":"Trade Mart",
    "wof:placetype":"venue"
},
  "geometry": {"coordinates":[-75.674256,35.90593],"type":"Point"}
}