{
  "type": "Feature",
  "properties": {
    "iso:country":"US",
    "sg:address":"701 E Salem Ave",
    "sg:city":"Winston Salem",
    "sg:classifiers":[
        {
            "category":"Wholesale",
            "subcategory":"Machinery & Supplies",
            "type":"Manufacturing & Wholesale Goods"
        }
    ],
    "sg:phone":"+1 336 722 2470",
    "sg:postcode":"27101",
    "sg:province":"NC",
    "sg:tags":[
        "equipment",
        "layer",
        "carpet"
    ],
    "wof:name":"Kimco Distributors Inc",
    "wof:placetype":"venue"
},
  "geometry": {"coordinates":[-80.237061,36.087652],"type":"Point"}
}