{
  "type": "Feature",
  "properties": {
    "iso:country":"US",
    "sg:address":"108 Newberry St",
    "sg:city":"Jamestown",
    "sg:classifiers":[
        {
            "category":"Manufacturing",
            "subcategory":"Furniture",
            "type":"Manufacturing & Wholesale Goods"
        }
    ],
    "sg:phone":"+1 336 886 1699",
    "sg:postcode":"27282",
    "sg:province":"NC",
    "wof:name":"Kimberly Gale Furniture Co",
    "wof:placetype":"venue"
},
  "geometry": {"coordinates":[-79.936455,36.004259],"type":"Point"}
}