{
  "type": "Feature",
  "properties": {
    "addr:full":"115 Commerce Centre Dr Huntersville NC 28078",
    "addr:housenumber":"115",
    "addr:postcode":"28078",
    "addr:street":"Commerce Centre Dr",
    "iso:country":"US",
    "sg:address":"115 Commerce Centre Dr",
    "sg:city":"Huntersville",
    "sg:classifiers":[
        {
            "category":"Organizations",
            "subcategory":"Religious Organization",
            "type":"Services"
        }
    ],
    "sg:phone":"+1 704 948 5900",
    "sg:postcode":"28078",
    "sg:province":"NC",
    "sg:tags":[
        "church"
    ],
    "wof:name":"Faith Life Church",
    "wof:placetype":"venue"
},
  "geometry": {"coordinates":[-80.851759,35.412392],"type":"Point"}
}