{
  "type": "Feature",
  "properties": {
    "iso:country":"US",
    "sg:address":"235 Pigeon St",
    "sg:city":"Waynesville",
    "sg:classifiers":[
        {
            "category":"Food & Beverages",
            "subcategory":"Candy",
            "type":"Retail Goods"
        }
    ],
    "sg:phone":"+1 828 456 4416",
    "sg:postcode":"28786",
    "sg:province":"NC",
    "sg:tags":[
        "confectionery"
    ],
    "sg:website":"www.steeplechasetoffee.com",
    "wof:name":"Steeplechase Olde English Tffe",
    "wof:placetype":"venue"
},
  "geometry": {"coordinates":[-82.985573,35.486252],"type":"Point"}
}