{
  "type": "Feature",
  "properties": {
    "addr:full":"1501 Swainey Ave Fayetteville NC 28303",
    "addr:housenumber":"1501",
    "addr:postcode":"28303",
    "addr:street":"Swainey Ave",
    "iso:country":"US",
    "sg:address":"1501 Swainey Ave",
    "sg:city":"Fayetteville",
    "sg:classifiers":[
        {
            "category":"Professional",
            "type":"Services"
        }
    ],
    "sg:phone":"+1 910 907 2137",
    "sg:postcode":"28303",
    "sg:province":"NC",
    "wof:name":"Rupert D Williams Jr",
    "wof:placetype":"venue"
},
  "geometry": {"coordinates":[-78.937349,35.101287],"type":"Point"}
}