{
  "type": "Feature",
  "properties": {
    "addr:full":"1084 Fuller Rd Louisburg NC 27549",
    "addr:housenumber":"1084",
    "addr:postcode":"27549",
    "addr:street":"Fuller Rd",
    "iso:country":"US",
    "sg:address":"1084 Fuller Rd",
    "sg:city":"Louisburg",
    "sg:classifiers":[
        {
            "category":"Professional",
            "subcategory":"Management & Consulting",
            "type":"Services"
        }
    ],
    "sg:phone":"+1   ",
    "sg:postcode":"27549",
    "sg:province":"NC",
    "wof:name":"Extended Care Service",
    "wof:placetype":"venue"
},
  "geometry": {"coordinates":[-78.240414,36.206942],"type":"Point"}
}