{
  "type": "Feature",
  "properties": {
    "addr:full":"117 Breeze Hill Ln Dobson NC 27017",
    "addr:housenumber":"117",
    "addr:postcode":"27017",
    "addr:street":"Breeze Hill Ln",
    "iso:country":"US",
    "sg:address":"117 Breeze Hill Ln",
    "sg:city":"Dobson",
    "sg:classifiers":[
        {
            "category":"Banks & Credit Unions",
            "subcategory":"Investment Brokerage",
            "type":"Services"
        }
    ],
    "sg:phone":"+1 336 374 4836",
    "sg:postcode":"27017",
    "sg:province":"NC",
    "sg:tags":[
        "stock",
        "bond"
    ],
    "wof:name":"AAC Brokerage Svc",
    "wof:placetype":"venue"
},
  "geometry": {"coordinates":[-80.69433600000001,36.355522],"type":"Point"}
}