{
  "type": "Feature",
  "properties": {
    "iso:country":"US",
    "sg:address":"1088 US Hwy 64 Bus",
    "sg:city":"Hayesville",
    "sg:classifiers":[
        {
            "category":"Autos & Motor Vehicles",
            "subcategory":"Boat Sales",
            "type":"Retail Goods"
        }
    ],
    "sg:phone":"+1 828 389 6353",
    "sg:postcode":"28904",
    "sg:province":"NC",
    "sg:tags":[
        "dealer",
        "sales"
    ],
    "wof:name":"B & T Marine",
    "wof:placetype":"venue"
},
  "geometry": {"coordinates":[-83.82083299999999,35.046519],"type":"Point"}
}