{
  "type": "Feature",
  "properties": {
    "iso:country":"US",
    "sg:address":"1027 W Lee St",
    "sg:city":"Greensboro",
    "sg:classifiers":[
        {
            "category":"Wholesale",
            "subcategory":"Machinery & Supplies",
            "type":"Manufacturing & Wholesale Goods"
        }
    ],
    "sg:phone":"+1 336 275 9274",
    "sg:postcode":"27403",
    "sg:province":"NC",
    "sg:tags":[
        "industrial"
    ],
    "wof:name":"Ramset-Ammo Fastening Systems",
    "wof:placetype":"venue"
},
  "geometry": {"coordinates":[-79.808755,36.063125],"type":"Point"}
}