{
  "type": "Feature",
  "properties": {
    "addr:full":"11137 Amberglades Ln Charlotte NC 28215",
    "addr:housenumber":"11137",
    "addr:postcode":"28215",
    "addr:street":"Amberglades Ln",
    "iso:country":"US",
    "sg:address":"11137 Amberglades Ln",
    "sg:city":"Charlotte",
    "sg:classifiers":[
        {
            "category":"Social Services",
            "subcategory":"Child Care",
            "type":"Services"
        }
    ],
    "sg:phone":"+1   ",
    "sg:postcode":"28215",
    "sg:province":"NC",
    "sg:tags":[
        "day"
    ],
    "wof:name":"Building Blocks Investments LL",
    "wof:placetype":"venue"
},
  "geometry": {"coordinates":[-80.679917,35.256457],"type":"Point"}
}