{
  "type": "Feature",
  "properties": {
    "addr:full":"415 Air Harbor Rd Greensboro NC 27455",
    "addr:housenumber":"415",
    "addr:postcode":"27455",
    "addr:street":"Air Harbor Rd",
    "iso:country":"US",
    "sg:address":"415 Air Harbor Rd",
    "sg:city":"Greensboro",
    "sg:classifiers":[
        {
            "category":"Building & Trades",
            "subcategory":"Landscaping Services",
            "type":"Services"
        }
    ],
    "sg:phone":"+1 336 545 5561",
    "sg:postcode":"27455",
    "sg:province":"NC",
    "sg:tags":[
        "designer",
        "landscape"
    ],
    "wof:name":"Floyd's Landscaping & Lawn",
    "wof:placetype":"venue"
},
  "geometry": {"coordinates":[-79.822183,36.162074],"type":"Point"}
}