{
  "type": "Feature",
  "properties": {
    "iso:country":"US",
    "sg:address":"727 W Hargett St",
    "sg:city":"Raleigh",
    "sg:classifiers":[
        {
            "category":"Professional",
            "subcategory":"Art Services",
            "type":"Services"
        }
    ],
    "sg:phone":"+1 919 829 0970",
    "sg:postcode":"27603",
    "sg:province":"NC",
    "sg:tags":[
        "graphic",
        "designer"
    ],
    "wof:name":"Fuel Design Group",
    "wof:placetype":"venue"
},
  "geometry": {"coordinates":[-78.65046599999999,35.778663],"type":"Point"}
}