{
  "type": "Feature",
  "properties": {
    "addr:full":"826 Dillard St Greensboro NC 27403",
    "addr:housenumber":"826",
    "addr:postcode":"27403",
    "addr:street":"Dillard St",
    "iso:country":"US",
    "sg:address":"826 Dillard St",
    "sg:city":"Greensboro",
    "sg:classifiers":[
        {
            "category":"Utilities",
            "subcategory":"Telephone",
            "type":"Services"
        }
    ],
    "sg:phone":"+1 336 273 1542",
    "sg:postcode":"27403",
    "sg:province":"NC",
    "sg:tags":[
        "company"
    ],
    "wof:name":"Alexander Telephone Svc",
    "wof:placetype":"venue"
},
  "geometry": {"coordinates":[-79.803416,36.061063],"type":"Point"}
}