{
  "type": "Feature",
  "properties": {
    "addr:full":"3915 Burlington Rd Greensboro NC 27405",
    "addr:housenumber":"3915",
    "addr:postcode":"27405",
    "addr:street":"Burlington Rd",
    "iso:country":"US",
    "sg:address":"3915 Burlington Rd",
    "sg:city":"Greensboro",
    "sg:classifiers":[
        {
            "category":"Building & Trades",
            "subcategory":"Construction",
            "type":"Services"
        }
    ],
    "sg:phone":"+1 336 382 9331",
    "sg:postcode":"27405",
    "sg:province":"NC",
    "sg:tags":[
        "general",
        "contractor"
    ],
    "wof:name":"Bryant Construction",
    "wof:placetype":"venue"
},
  "geometry": {"coordinates":[-79.716548,36.086489],"type":"Point"}
}