{
  "type": "Feature",
  "properties": {
    "addr:full":"2820 Half Hitch Trl Raleigh NC 27615",
    "addr:housenumber":"2820",
    "addr:postcode":"27615",
    "addr:street":"Half Hitch Trl",
    "iso:country":"US",
    "sg:address":"2820 Half Hitch Trl",
    "sg:city":"Raleigh",
    "sg:classifiers":[
        {
            "category":"Health Services",
            "subcategory":"Doctor",
            "type":"Services"
        }
    ],
    "sg:phone":"+1   ",
    "sg:postcode":"27615",
    "sg:province":"NC",
    "sg:tags":[
        "medical"
    ],
    "wof:name":"Reigel Haidee MD",
    "wof:placetype":"venue"
},
  "geometry": {"coordinates":[-78.59287500000001,35.896974],"type":"Point"}
}