{
  "type": "Feature",
  "properties": {
    "addr:full":"812 Spring Ln Sanford NC 27330",
    "addr:housenumber":"812",
    "addr:postcode":"27330",
    "addr:street":"Spring Ln",
    "iso:country":"US",
    "sg:address":"812 Spring Ln",
    "sg:city":"Sanford",
    "sg:classifiers":[
        {
            "category":"Personal",
            "subcategory":"Beauty Salon",
            "type":"Services"
        }
    ],
    "sg:phone":"+1 919 775 4939",
    "sg:postcode":"27330",
    "sg:province":"NC",
    "sg:tags":[
        "shop"
    ],
    "sg:website":"www.greatclips.com",
    "wof:name":"Great Clips",
    "wof:placetype":"venue"
},
  "geometry": {"coordinates":[-79.194299,35.487337],"type":"Point"}
}