{
  "type": "Feature",
  "properties": {
    "iso:country":"US",
    "sg:address":"3041 W Cornwallis Rd",
    "sg:city":"Resrch Trngle Pk",
    "sg:classifiers":[
        {
            "category":"Government",
            "subcategory":"Office",
            "type":"Public Place"
        }
    ],
    "sg:phone":"+1 919 549 4000",
    "sg:postcode":"27705",
    "sg:province":"NC",
    "wof:name":"US Forestry Science Lab",
    "wof:placetype":"venue"
},
  "geometry": {"coordinates":[-78.97293500000001,35.99311],"type":"Point"}
}