{
  "type": "Feature",
  "properties": {
    "addr:full":"1614 E Millbrook Rd Raleigh NC 27609",
    "addr:housenumber":"1614",
    "addr:postcode":"27609",
    "addr:street":"E Millbrook Rd",
    "iso:country":"US",
    "sg:address":"1614 E Millbrook Rd",
    "sg:city":"Raleigh",
    "sg:classifiers":[
        {
            "category":"Real Estate",
            "subcategory":"Real Estate Agent",
            "type":"Services"
        }
    ],
    "sg:phone":"+1 919 862 9202",
    "sg:postcode":"27609",
    "sg:province":"NC",
    "wof:name":"Duke Weeks Realty Ref Brookfor",
    "wof:placetype":"venue"
},
  "geometry": {"coordinates":[-78.60794300000001,35.850075],"type":"Point"}
}