{
  "type": "Feature",
  "properties": {
    "iso:country":"US",
    "sg:address":"800 Hallsville Rd",
    "sg:city":"Beulaville",
    "sg:classifiers":[
        {
            "category":"Social Services",
            "subcategory":"Child Care",
            "type":"Services"
        }
    ],
    "sg:phone":"+1 910 298 6510",
    "sg:postcode":"28518",
    "sg:province":"NC",
    "wof:name":"Tiny Tots Fun Time Learning",
    "wof:placetype":"venue"
},
  "geometry": {"coordinates":[-77.802699,34.915719],"type":"Point"}
}