{
  "type": "Feature",
  "properties": {
    "iso:country":"US",
    "sg:address":"635 Smokey Park Hwy",
    "sg:city":"Candler",
    "sg:classifiers":[
        {
            "category":"Wholesale",
            "subcategory":"Stationery",
            "type":"Manufacturing & Wholesale Goods"
        }
    ],
    "sg:phone":"+1 828 667 3892",
    "sg:postcode":"28715",
    "sg:province":"NC",
    "sg:tags":[
        "food",
        "institutional",
        "product",
        "paper",
        "coffee"
    ],
    "wof:name":"Msi Cash and Carry",
    "wof:placetype":"venue"
},
  "geometry": {"coordinates":[-82.6437,35.5522],"type":"Point"}
}