{
  "type": "Feature",
  "properties": {
    "iso:country":"US",
    "sg:address":"111 Huffstetler Rd",
    "sg:city":"Gastonia",
    "sg:classifiers":[
        {
            "category":"Retail",
            "subcategory":"Auto Repair",
            "type":"Services"
        }
    ],
    "sg:phone":"+1 704 824 2174",
    "sg:postcode":"28056",
    "sg:province":"NC",
    "sg:tags":[
        "repairing",
        "automobile"
    ],
    "wof:name":"Featherstone Garage & Svc",
    "wof:placetype":"venue"
},
  "geometry": {"coordinates":[-81.09472,35.218688],"type":"Point"}
}