{
  "type": "Feature",
  "properties": {
    "addr:full":"3100 Sam Wilson Rd Charlotte NC 28214",
    "addr:housenumber":"3100",
    "addr:postcode":"28214",
    "addr:street":"Sam Wilson Rd",
    "iso:country":"US",
    "sg:address":"3100 Sam Wilson Rd",
    "sg:city":"Charlotte",
    "sg:classifiers":[
        {
            "category":"Building & Trades",
            "subcategory":"Construction",
            "type":"Services"
        }
    ],
    "sg:phone":"+1 704 391 3371",
    "sg:postcode":"28214",
    "sg:province":"NC",
    "sg:tags":[
        "contractor"
    ],
    "wof:name":"REA Contracting",
    "wof:placetype":"venue"
},
  "geometry": {"coordinates":[-80.98382599999999,35.251673],"type":"Point"}
}