{
  "type": "Feature",
  "properties": {
    "addr:full":"979 Concord Pkwy N Concord NC 28027",
    "addr:housenumber":"979",
    "addr:postcode":"28027",
    "addr:street":"Concord Pkwy N",
    "iso:country":"US",
    "sg:address":"979 Concord Pkwy N",
    "sg:city":"Concord",
    "sg:classifiers":[
        {
            "category":"Utilities",
            "subcategory":"Mobile Phone",
            "type":"Services"
        }
    ],
    "sg:phone":"+1 704 788 4444",
    "sg:postcode":"28027",
    "sg:province":"NC",
    "sg:tags":[
        "telephone",
        "cellular"
    ],
    "wof:name":"Future Cellular Communications",
    "wof:placetype":"venue"
},
  "geometry": {"coordinates":[-80.614502,35.426605],"type":"Point"}
}