{
  "type": "Feature",
  "properties": {
    "iso:country":"US",
    "sg:address":"33 N Oak Ter",
    "sg:city":"Arden",
    "sg:classifiers":[
        {
            "category":"Professional",
            "type":"Services"
        }
    ],
    "sg:phone":"+1 828 681 0979",
    "sg:postcode":"28704",
    "sg:province":"NC",
    "wof:name":"Gerald L Stewart",
    "wof:placetype":"venue"
},
  "geometry": {"coordinates":[-82.50249700000001,35.479694],"type":"Point"}
}