{
  "type": "Feature",
  "properties": {
    "iso:country":"US",
    "sg:address":"700 Leesville St",
    "sg:city":"Fairmont",
    "sg:classifiers":[
        {
            "category":"Organizations",
            "subcategory":"Religious Organization",
            "type":"Services"
        }
    ],
    "sg:phone":"+1 910 628 9539",
    "sg:postcode":"28340",
    "sg:province":"NC",
    "sg:tags":[
        "church"
    ],
    "wof:name":"St Johns AME Church",
    "wof:placetype":"venue"
},
  "geometry": {"coordinates":[-79.10973799999999,34.498008],"type":"Point"}
}