{
  "type": "Feature",
  "properties": {
    "addr:full":"6926 Hwy 64 W Brasstown NC 28902",
    "addr:housenumber":"6926",
    "addr:postcode":"28902",
    "addr:street":"Hwy 64 W Brasstown",
    "iso:country":"US",
    "sg:address":"6926 Hwy 64 W",
    "sg:city":"Brasstown",
    "sg:classifiers":[
        {
            "category":"Manufacturing",
            "subcategory":"Lumber",
            "type":"Manufacturing & Wholesale Goods"
        }
    ],
    "sg:phone":"+1 828 837 0118",
    "sg:postcode":"28902",
    "sg:province":"NC",
    "sg:tags":[
        "sawmill"
    ],
    "wof:name":"Buckhorn Lumber & Wood",
    "wof:placetype":"venue"
},
  "geometry": {"coordinates":[-83.924583,35.05665],"type":"Point"}
}