{
  "type": "Feature",
  "properties": {
    "iso:country":"US",
    "sg:address":"6609 Hunters Ln",
    "sg:city":"Durham",
    "sg:classifiers":[
        {
            "category":"Professional",
            "subcategory":"Management & Consulting",
            "type":"Services"
        }
    ],
    "sg:phone":"+1   ",
    "sg:postcode":"27713",
    "sg:province":"NC",
    "sg:tags":[
        "business"
    ],
    "wof:name":"Vista Comm",
    "wof:placetype":"venue"
},
  "geometry": {"coordinates":[-78.920636,35.901577],"type":"Point"}
}