{
  "type": "Feature",
  "properties": {
    "iso:country":"US",
    "sg:address":"1200 Chestnut Ln",
    "sg:city":"Matthews",
    "sg:classifiers":[
        {
            "category":"Wholesale",
            "subcategory":"Fruits & Vegetables",
            "type":"Manufacturing & Wholesale Goods"
        }
    ],
    "sg:phone":"+1 704 821 7116",
    "sg:postcode":"28104",
    "sg:province":"NC",
    "wof:name":"Austin Produce Inc",
    "wof:placetype":"venue"
},
  "geometry": {"coordinates":[-80.699314,35.070239],"type":"Point"}
}