{
  "type": "Feature",
  "properties": {
    "addr:full":"4312 Seth Dr Holly Springs NC 27540",
    "addr:housenumber":"4312",
    "addr:postcode":"27540",
    "addr:street":"Seth Dr",
    "iso:country":"US",
    "sg:address":"4312 Seth Dr",
    "sg:city":"Holly Springs",
    "sg:classifiers":[
        {
            "category":"Freight",
            "type":"Transportation"
        }
    ],
    "sg:phone":"+1 919 552 0583",
    "sg:postcode":"27540",
    "sg:province":"NC",
    "sg:tags":[
        "operator",
        "local",
        "trucking"
    ],
    "wof:name":"Spainhours Hauling Inc",
    "wof:placetype":"venue"
},
  "geometry": {"coordinates":[-78.793228,35.633855],"type":"Point"}
}