{
  "type": "Feature",
  "properties": {
    "iso:country":"US",
    "sg:address":"100 Briggs Rd",
    "sg:city":"Asheville",
    "sg:classifiers":[
        {
            "category":"Building & Trades",
            "subcategory":"Construction",
            "type":"Services"
        }
    ],
    "sg:phone":"+1 828 298 2469",
    "sg:postcode":"28805",
    "sg:province":"NC",
    "sg:tags":[
        "contractor"
    ],
    "wof:name":"Wilson Drywall",
    "wof:placetype":"venue"
},
  "geometry": {"coordinates":[-82.459743,35.586535],"type":"Point"}
}