{
  "type": "Feature",
  "properties": {
    "addr:full":"1809 Hickory Grove Rd Gastonia NC 28056",
    "addr:housenumber":"1809",
    "addr:postcode":"28056",
    "addr:street":"Hickory Grove Rd",
    "iso:country":"US",
    "sg:address":"1809 Hickory Grove Rd",
    "sg:city":"Gastonia",
    "sg:classifiers":[
        {
            "category":"Shopping",
            "subcategory":"Music",
            "type":"Retail Goods"
        }
    ],
    "sg:phone":"+1 704 827 5222",
    "sg:postcode":"28056",
    "sg:province":"NC",
    "sg:tags":[
        "video",
        "disc",
        "tape",
        "cassette"
    ],
    "wof:name":"Videos For Less Inc",
    "wof:placetype":"venue"
},
  "geometry": {"coordinates":[-81.058768,35.279303],"type":"Point"}
}