{
  "type": "Feature",
  "properties": {
    "iso:country":"US",
    "sg:address":"409 W Fisher Ave",
    "sg:city":"Greensboro",
    "sg:classifiers":[
        {
            "category":"Professional",
            "subcategory":"Business Services",
            "type":"Services"
        }
    ],
    "sg:phone":"+1 336 274 7533",
    "sg:postcode":"27401",
    "sg:province":"NC",
    "sg:tags":[
        "interior",
        "consultant",
        "designer",
        "design",
        "decorator"
    ],
    "wof:name":"Design Collection Ltd",
    "wof:placetype":"venue"
},
  "geometry": {"coordinates":[-79.79471599999999,36.080003],"type":"Point"}
}