{
  "type": "Feature",
  "properties": {
    "addr:full":"2710 Lance Dr Winston Salem NC 27103",
    "addr:housenumber":"2710",
    "addr:postcode":"27103",
    "addr:street":"Lance Dr",
    "iso:country":"US",
    "sg:address":"2710 Lance Dr",
    "sg:city":"Winston Salem",
    "sg:classifiers":[
        {
            "category":"Manufacturing",
            "subcategory":"Metals",
            "type":"Manufacturing & Wholesale Goods"
        }
    ],
    "sg:phone":"+1 336 765 5411",
    "sg:postcode":"27103",
    "sg:province":"NC",
    "sg:tags":[
        "ornamental",
        "work"
    ],
    "wof:name":"Envision Products",
    "wof:placetype":"venue"
},
  "geometry": {"coordinates":[-80.342843,36.035669],"type":"Point"}
}