{
  "type": "Feature",
  "properties": {
    "addr:full":"1667 Charlotte Hwy Fairview NC 28730",
    "addr:housenumber":"1667",
    "addr:postcode":"28730",
    "addr:street":"Charlotte Hwy",
    "iso:country":"US",
    "sg:address":"1667 Charlotte Hwy",
    "sg:city":"Fairview",
    "sg:classifiers":[
        {
            "category":"Building & Trades",
            "subcategory":"Cleaning & Sanitation",
            "type":"Services"
        },
        {
            "category":"Building & Trades",
            "subcategory":"Construction",
            "type":"Services"
        }
    ],
    "sg:phone":"+1 828 628 0104",
    "sg:postcode":"28730",
    "sg:province":"NC",
    "sg:tags":[
        "product",
        "mfg",
        "contractor",
        "clay",
        "fireplace",
        "chimney",
        "structural"
    ],
    "wof:name":"Environmental Chimney Sweep",
    "wof:placetype":"venue"
},
  "geometry": {"coordinates":[-82.397325,35.514756],"type":"Point"}
}