{
  "type": "Feature",
  "properties": {
    "addr:full":"5505 Thornton Rd Raleigh NC 27616",
    "addr:housenumber":"5505",
    "addr:postcode":"27616",
    "addr:street":"Thornton Rd",
    "iso:country":"US",
    "sg:address":"5505 Thornton Rd",
    "sg:city":"Raleigh",
    "sg:classifiers":[
        {
            "category":"Wholesale",
            "subcategory":"Auto Parts",
            "type":"Manufacturing & Wholesale Goods"
        }
    ],
    "sg:phone":"+1 919 876 1331",
    "sg:postcode":"27616",
    "sg:province":"NC",
    "sg:tags":[
        "used",
        "salvage",
        "surplus",
        "merchandise"
    ],
    "wof:name":"T & T Salvage And Wrecker",
    "wof:placetype":"venue"
},
  "geometry": {"coordinates":[-78.546255,35.898273],"type":"Point"}
}