{
  "type": "Feature",
  "properties": {
    "iso:country":"US",
    "sg:address":"949 Saint Marys St",
    "sg:city":"Raleigh",
    "sg:classifiers":[
        {
            "category":"Building & Trades",
            "subcategory":"Construction",
            "type":"Services"
        }
    ],
    "sg:phone":"+1 919 754 8102",
    "sg:postcode":"27605",
    "sg:province":"NC",
    "sg:tags":[
        "general",
        "contractor"
    ],
    "wof:name":"John C Sanders & Co",
    "wof:placetype":"venue"
},
  "geometry": {"coordinates":[-78.652856,35.792554],"type":"Point"}
}