{
  "type": "Feature",
  "properties": {
    "addr:full":"3301 Teversham Ln Charlotte NC 28210",
    "addr:housenumber":"3301",
    "addr:postcode":"28210",
    "addr:street":"Teversham Ln",
    "iso:country":"US",
    "sg:address":"3301 Teversham Ln",
    "sg:city":"Charlotte",
    "sg:classifiers":[
        {
            "category":"Shopping",
            "subcategory":"Beauty & Cosmetics",
            "type":"Retail Goods"
        }
    ],
    "sg:phone":"+1 704 552 6692",
    "sg:postcode":"28210",
    "sg:province":"NC",
    "sg:tags":[
        "merchandise"
    ],
    "wof:name":"Gail F Weston",
    "wof:placetype":"venue"
},
  "geometry": {"coordinates":[-80.849406,35.142922],"type":"Point"}
}