{
  "type": "Feature",
  "properties": {
    "iso:country":"US",
    "sg:address":"1234 Ivey Dr",
    "sg:city":"Charlotte",
    "sg:classifiers":[
        {
            "category":"Professional",
            "type":"Services"
        }
    ],
    "sg:phone":"+1   ",
    "sg:postcode":"28205",
    "sg:province":"NC",
    "wof:name":"Fun Services North Carolina",
    "wof:placetype":"venue"
},
  "geometry": {"coordinates":[-80.798209,35.216192],"type":"Point"}
}