{
  "type": "Feature",
  "properties": {
    "iso:country":"US",
    "sg:address":"803 Moye Blvd",
    "sg:city":"Greenville",
    "sg:classifiers":[
        {
            "category":"Personal",
            "subcategory":"Beauty Salon",
            "type":"Services"
        }
    ],
    "sg:phone":"+1 252 758 5782",
    "sg:postcode":"27834",
    "sg:province":"NC",
    "wof:name":"Beauty At Its Best",
    "wof:placetype":"venue"
},
  "geometry": {"coordinates":[-77.39928500000001,35.603235],"type":"Point"}
}