{
  "type": "Feature",
  "properties": {
    "iso:country":"US",
    "sg:address":"4435 Rankin Rd",
    "sg:city":"Concord",
    "sg:classifiers":[
        {
            "category":"Farming",
            "subcategory":"Livestock Farm",
            "type":"Manufacturing & Wholesale Goods"
        }
    ],
    "sg:phone":"+1 704 782 0206",
    "sg:postcode":"28027",
    "sg:province":"NC",
    "sg:tags":[
        "beef",
        "feedlot",
        "cattle"
    ],
    "wof:name":"Jack Rankin",
    "wof:placetype":"venue"
},
  "geometry": {"coordinates":[-80.708848,35.482651],"type":"Point"}
}