{
  "type": "Feature",
  "properties": {
    "iso:country":"US",
    "sg:address":"3006 Hickory Blvd",
    "sg:city":"Hudson",
    "sg:classifiers":[
        {
            "category":"Health Services",
            "subcategory":"Hospital",
            "type":"Services"
        }
    ],
    "sg:phone":"+1 828 728 9700",
    "sg:postcode":"28638",
    "sg:province":"NC",
    "sg:tags":[
        "mental"
    ],
    "wof:name":"Skill Creations Inc",
    "wof:placetype":"venue"
},
  "geometry": {"coordinates":[-81.476799,35.848766],"type":"Point"}
}