{
  "type": "Feature",
  "properties": {
    "addr:full":"6017 Riley Hill Rd Wendell NC 27591",
    "addr:housenumber":"6017",
    "addr:postcode":"27591",
    "addr:street":"Riley Hill Rd",
    "iso:country":"US",
    "sg:address":"6017 Riley Hill Rd",
    "sg:city":"Wendell",
    "sg:classifiers":[
        {
            "category":"Building & Trades",
            "subcategory":"Construction",
            "type":"Services"
        }
    ],
    "sg:phone":"+1 919 365 4573",
    "sg:postcode":"27591",
    "sg:province":"NC",
    "sg:tags":[
        "house",
        "contractor",
        "roofing"
    ],
    "wof:name":"J D's Roofing Co Inc",
    "wof:placetype":"venue"
},
  "geometry": {"coordinates":[-78.416276,35.857197],"type":"Point"}
}