{
  "type": "Feature",
  "properties": {
    "iso:country":"US",
    "sg:address":"8498 State Hwy 150",
    "sg:city":"Terrell",
    "sg:classifiers":[
        {
            "category":"Professional",
            "subcategory":"Business Services",
            "type":"Services"
        }
    ],
    "sg:phone":"+1   ",
    "sg:postcode":"28682",
    "sg:province":"NC",
    "wof:name":"Common Wealth Constructors",
    "wof:placetype":"venue"
},
  "geometry": {"coordinates":[-80.970331,35.59188],"type":"Point"}
}