{
  "type": "Feature",
  "properties": {
    "iso:country":"US",
    "sg:address":"339 N Front St",
    "sg:city":"Wilmington",
    "sg:classifiers":[
        {
            "category":"Shopping",
            "subcategory":"Gifts & Souvenirs",
            "type":"Retail Goods"
        }
    ],
    "sg:phone":"+1 910 251 2566",
    "sg:postcode":"28401",
    "sg:province":"NC",
    "sg:tags":[
        "shop"
    ],
    "wof:name":"Hummingbird Station",
    "wof:placetype":"venue"
},
  "geometry": {"coordinates":[-77.94930600000001,34.239465],"type":"Point"}
}