{
  "type": "Feature",
  "properties": {
    "iso:country":"US",
    "sg:address":"175 Freedom Way",
    "sg:city":"Midway Park",
    "sg:classifiers":[
        {
            "category":"Restaurant",
            "type":"Food & Drink"
        }
    ],
    "sg:phone":"+1 910 219 0898",
    "sg:postcode":"28539",
    "sg:province":"NC",
    "sg:tags":[
        "eating"
    ],
    "wof:name":"China King",
    "wof:placetype":"venue"
},
  "geometry": {"coordinates":[-77.320464,34.715931],"type":"Point"}
}