{
  "type": "Feature",
  "properties": {
    "addr:full":"819 W King St Boone NC 28607",
    "addr:housenumber":"819",
    "addr:postcode":"28607",
    "addr:street":"W King St",
    "iso:country":"US",
    "sg:address":"819 W King St",
    "sg:city":"Boone",
    "sg:classifiers":[
        {
            "category":"Real Estate",
            "subcategory":"Surveying",
            "type":"Services"
        }
    ],
    "sg:phone":"+1 828 262 3353",
    "sg:postcode":"28607",
    "sg:province":"NC",
    "wof:name":"Skyline Surveyors PA",
    "wof:placetype":"venue"
},
  "geometry": {"coordinates":[-81.68731099999999,36.22045],"type":"Point"}
}