{
  "type": "Feature",
  "properties": {
    "addr:full":"504 N Main St Robersonville NC 27871",
    "addr:housenumber":"504",
    "addr:postcode":"27871",
    "addr:street":"N Main St",
    "iso:country":"US",
    "sg:address":"504 N Main St",
    "sg:city":"Robersonville",
    "sg:classifiers":[
        {
            "category":"Health Services",
            "subcategory":"Doctor",
            "type":"Services"
        }
    ],
    "sg:phone":"+1 252 795 5555",
    "sg:postcode":"27871",
    "sg:province":"NC",
    "sg:tags":[
        "physician",
        "surgeon"
    ],
    "wof:name":"Robersonville Physicians",
    "wof:placetype":"venue"
},
  "geometry": {"coordinates":[-77.254558,35.829956],"type":"Point"}
}