{
  "type": "Feature",
  "properties": {
    "iso:country":"US",
    "sg:address":"160 Royal Pines Dr",
    "sg:city":"Arden",
    "sg:phone":"+1 828 684 3110",
    "sg:postcode":"28704",
    "sg:province":"NC",
    "sg:tags":[
        "oil"
    ],
    "wof:name":"Western Carolina Oil Co",
    "wof:placetype":"venue"
},
  "geometry": {"coordinates":[-82.517223,35.474686],"type":"Point"}
}