{
  "type": "Feature",
  "properties": {
    "addr:full":"2340 Tynecastle Hwy Banner Elk NC 28604",
    "addr:housenumber":"2340",
    "addr:postcode":"28604",
    "addr:street":"Tynecastle Hwy",
    "iso:country":"US",
    "sg:address":"2340 Tynecastle Hwy",
    "sg:city":"Banner Elk",
    "sg:classifiers":[
        {
            "category":"Wholesale",
            "subcategory":"Farm Supplies",
            "type":"Manufacturing & Wholesale Goods"
        }
    ],
    "sg:phone":"+1 828 898 5660",
    "sg:postcode":"28604",
    "sg:province":"NC",
    "sg:tags":[
        "feed"
    ],
    "wof:name":"New River Building Supply",
    "wof:placetype":"venue"
},
  "geometry": {"coordinates":[-81.847043,36.126718],"type":"Point"}
}