{
  "type": "Feature",
  "properties": {
    "addr:full":"1009 Shelby Rd Kings Mountain NC 28086",
    "addr:housenumber":"1009",
    "addr:postcode":"28086",
    "addr:street":"Shelby Rd",
    "iso:country":"US",
    "sg:address":"1009 Shelby Rd",
    "sg:city":"Kings Mountain",
    "sg:classifiers":[
        {
            "category":"Restaurant",
            "type":"Food & Drink"
        }
    ],
    "sg:phone":"+1 704 739 7691",
    "sg:postcode":"28086",
    "sg:province":"NC",
    "wof:name":"Wiener Works",
    "wof:placetype":"venue"
},
  "geometry": {"coordinates":[-81.365212,35.239542],"type":"Point"}
}