{
  "type": "Feature",
  "properties": {
    "addr:full":"5813 Stone Bridge Ln Waxhaw NC 28173",
    "addr:housenumber":"5813",
    "addr:postcode":"28173",
    "addr:street":"Stone Bridge Ln",
    "iso:country":"US",
    "sg:address":"5813 Stone Bridge Ln",
    "sg:city":"Waxhaw",
    "sg:classifiers":[
        {
            "category":"Insurance",
            "subcategory":"Insurance Agent",
            "type":"Services"
        }
    ],
    "sg:phone":"+1 704 873 8002",
    "sg:postcode":"28173",
    "sg:province":"NC",
    "wof:name":"Gingerich Insurance Agency",
    "wof:placetype":"venue"
},
  "geometry": {"coordinates":[-80.744119,34.879287],"type":"Point"}
}