{
  "type": "Feature",
  "properties": {
    "iso:country":"US",
    "sg:address":"173 Jonestown Rd",
    "sg:city":"Winston Salem",
    "sg:classifiers":[
        {
            "category":"Health Services",
            "subcategory":"Chiropractor",
            "type":"Services"
        }
    ],
    "sg:phone":"+1   ",
    "sg:postcode":"27103",
    "sg:province":"NC",
    "wof:name":"Simmer Chiropractic",
    "wof:placetype":"venue"
},
  "geometry": {"coordinates":[-80.335052,36.079425],"type":"Point"}
}