{
  "type": "Feature",
  "properties": {
    "addr:full":"201 Wayne St Badin NC 28009",
    "addr:housenumber":"201",
    "addr:postcode":"28009",
    "addr:street":"Wayne St",
    "iso:country":"US",
    "sg:address":"201 Wayne St",
    "sg:city":"Badin",
    "sg:classifiers":[
        {
            "category":"Organizations",
            "subcategory":"Religious Organization",
            "type":"Services"
        }
    ],
    "sg:phone":"+1   ",
    "sg:postcode":"28009",
    "sg:province":"NC",
    "wof:name":"First Baptist Church",
    "wof:placetype":"venue"
},
  "geometry": {"coordinates":[-80.123982,35.412624],"type":"Point"}
}