{
  "type": "Feature",
  "properties": {
    "iso:country":"US",
    "sg:address":"3700 Mckee Rd",
    "sg:city":"Charlotte",
    "sg:classifiers":[
        {
            "category":"Professional",
            "subcategory":"Lawyer & Legal Services",
            "type":"Services"
        }
    ],
    "sg:phone":"+1 704 814 6079",
    "sg:postcode":"28270",
    "sg:province":"NC",
    "sg:tags":[
        "plan"
    ],
    "wof:name":"Fayer Netcoms International",
    "wof:placetype":"venue"
},
  "geometry": {"coordinates":[-80.74968699999999,35.072472],"type":"Point"}
}