{
  "type": "Feature",
  "properties": {
    "addr:full":"11240 N Tryon St Charlotte NC 28262",
    "addr:housenumber":"11240",
    "addr:postcode":"28262",
    "addr:street":"N Tryon St",
    "iso:country":"US",
    "sg:address":"11240 N Tryon St",
    "sg:city":"Charlotte",
    "sg:phone":"+1 704 503 0070",
    "sg:postcode":"28262",
    "sg:province":"NC",
    "wof:name":"Starlight Stadium 14",
    "wof:placetype":"venue"
},
  "geometry": {"coordinates":[-80.71728299999999,35.33478],"type":"Point"}
}