{
  "type": "Feature",
  "properties": {
    "iso:country":"US",
    "sg:address":"145 Fox Hunter Rd",
    "sg:city":"Harmony",
    "sg:classifiers":[
        {
            "category":"Organizations",
            "subcategory":"Religious Organization",
            "type":"Services"
        }
    ],
    "sg:phone":"+1 704 546 2799",
    "sg:postcode":"28634",
    "sg:province":"NC",
    "sg:tags":[
        "church"
    ],
    "wof:name":"Piney Grove Methodist Church",
    "wof:placetype":"venue"
},
  "geometry": {"coordinates":[-80.714938,35.9449],"type":"Point"}
}