{
  "type": "Feature",
  "properties": {
    "iso:country":"US",
    "sg:address":"613 Crabtree Crossing Pkwy",
    "sg:city":"Cary",
    "sg:classifiers":[
        {
            "category":"Building & Trades",
            "subcategory":"Construction",
            "type":"Services"
        }
    ],
    "sg:phone":"+1 919 460 1192",
    "sg:postcode":"27513",
    "sg:province":"NC",
    "sg:tags":[
        "home",
        "builder"
    ],
    "wof:name":"Hurst Built Inc",
    "wof:placetype":"venue"
},
  "geometry": {"coordinates":[-78.830242,35.795815],"type":"Point"}
}