{
  "type": "Feature",
  "properties": {
    "iso:country":"US",
    "sg:address":"4727 Arbor Rd",
    "sg:city":"Fayetteville",
    "sg:classifiers":[
        {
            "category":"Building & Trades",
            "subcategory":"Construction",
            "type":"Services"
        }
    ],
    "sg:phone":"+1 910 488 8665",
    "sg:postcode":"28311",
    "sg:province":"NC",
    "sg:tags":[
        "painter"
    ],
    "wof:name":"Salvador Ortiz",
    "wof:placetype":"venue"
},
  "geometry": {"coordinates":[-78.881608,35.128254],"type":"Point"}
}