{
  "type": "Feature",
  "properties": {
    "iso:country":"US",
    "sg:address":"205 Wild Oak Dr",
    "sg:city":"Swansboro",
    "sg:classifiers":[
        {
            "category":"Building & Trades",
            "subcategory":"Plumbing",
            "type":"Services"
        }
    ],
    "sg:phone":"+1 910 326 3861",
    "sg:postcode":"28584",
    "sg:province":"NC",
    "sg:tags":[
        "plumbing",
        "contractor"
    ],
    "wof:name":"Intown Plumbing",
    "wof:placetype":"venue"
},
  "geometry": {"coordinates":[-77.16021000000001,34.682772],"type":"Point"}
}