{
  "type": "Feature",
  "properties": {
    "iso:country":"US",
    "sg:address":"6119 Creedmoor Rd",
    "sg:city":"Raleigh",
    "sg:classifiers":[
        {
            "category":"Education",
            "subcategory":"School",
            "type":"Public Place"
        }
    ],
    "sg:phone":"+1 919 881 4910",
    "sg:postcode":"27612",
    "sg:province":"NC",
    "sg:website":"schools.wcpss.net/jeffreys-grove",
    "wof:name":"Wake County Public School System",
    "wof:placetype":"venue"
},
  "geometry": {"coordinates":[-78.680266,35.869157],"type":"Point"}
}