{
  "type": "Feature",
  "properties": {
    "iso:country":"US",
    "sg:address":"1116 Jefferson Rd",
    "sg:city":"Greensboro",
    "sg:classifiers":[
        {
            "category":"Manufacturing",
            "subcategory":"Food",
            "type":"Manufacturing & Wholesale Goods"
        }
    ],
    "sg:phone":"+1 336 294 5509",
    "sg:postcode":"27410",
    "sg:province":"NC",
    "sg:tags":[
        "mfg"
    ],
    "wof:name":"Boar Castle Co",
    "wof:placetype":"venue"
},
  "geometry": {"coordinates":[-79.870819,36.103818],"type":"Point"}
}