{
  "type": "Feature",
  "properties": {
    "addr:full":"320 Avon Lake Dr Durham NC 27713",
    "addr:housenumber":"320",
    "addr:postcode":"27713",
    "addr:street":"Avon Lake Dr",
    "iso:country":"US",
    "sg:address":"320 Avon Lake Dr",
    "sg:city":"Durham",
    "sg:classifiers":[
        {
            "category":"Building & Trades",
            "subcategory":"Cleaning & Sanitation",
            "type":"Services"
        }
    ],
    "sg:phone":"+1   ",
    "sg:postcode":"27713",
    "sg:province":"NC",
    "sg:tags":[
        "maintenance"
    ],
    "wof:name":"Francis Cleaning Service",
    "wof:placetype":"venue"
},
  "geometry": {"coordinates":[-78.918305,35.943327],"type":"Point"}
}