{
  "type": "Feature",
  "properties": {
    "addr:full":"4095 Deep River Church Rd Coleridge NC 27316",
    "addr:housenumber":"4095",
    "addr:postcode":"27316",
    "addr:street":"Deep River Church Rd",
    "iso:country":"US",
    "sg:address":"4095 Deep River Church Rd",
    "sg:city":"Coleridge",
    "sg:classifiers":[
        {
            "category":"Organizations",
            "subcategory":"Religious Organization",
            "type":"Services"
        }
    ],
    "sg:phone":"+1 336 879 5246",
    "sg:postcode":"27316",
    "sg:province":"NC",
    "sg:tags":[
        "church"
    ],
    "wof:name":"Deep River Baptist Church",
    "wof:placetype":"venue"
},
  "geometry": {"coordinates":[-79.62679799999999,35.639235],"type":"Point"}
}