{
  "type": "Feature",
  "properties": {
    "addr:full":"212 Biggs St Laurinburg NC 28352",
    "addr:housenumber":"212",
    "addr:postcode":"28352",
    "addr:street":"Biggs St",
    "iso:country":"US",
    "sg:address":"212 Biggs St",
    "sg:city":"Laurinburg",
    "sg:classifiers":[
        {
            "category":"Government",
            "subcategory":"Police Station",
            "type":"Public Place"
        }
    ],
    "sg:phone":"+1 910 277 3250",
    "sg:postcode":"28352",
    "sg:province":"NC",
    "sg:tags":[
        "sheriff"
    ],
    "wof:name":"Criminal Clerk Of Court",
    "wof:placetype":"venue"
},
  "geometry": {"coordinates":[-79.460566,34.775985],"type":"Point"}
}