{
  "type": "Feature",
  "properties": {
    "iso:country":"US",
    "sg:address":"811 N Clear Creek Rd",
    "sg:city":"Hendersonville",
    "sg:phone":"+1 828 694 1372",
    "sg:postcode":"28792",
    "sg:province":"NC",
    "sg:tags":[
        "video",
        "conferencing"
    ],
    "wof:name":"DMA Video Data Networks Inc",
    "wof:placetype":"venue"
},
  "geometry": {"coordinates":[-82.440713,35.371416],"type":"Point"}
}