{
  "type": "Feature",
  "properties": {
    "iso:country":"US",
    "sg:address":"143 N Main St",
    "sg:city":"Kernersville",
    "sg:classifiers":[
        {
            "category":"Banks & Credit Unions",
            "subcategory":"Investment Brokerage",
            "type":"Services"
        }
    ],
    "sg:phone":"+1 336 996 2121",
    "sg:postcode":"27284",
    "sg:province":"NC",
    "sg:tags":[
        "advisory",
        "financial"
    ],
    "wof:name":"Reliant Financial Group",
    "wof:placetype":"venue"
},
  "geometry": {"coordinates":[-80.072453,36.12096],"type":"Point"}
}