{
  "type": "Feature",
  "properties": {
    "addr:full":"6332 Ellesmere Ct Charlotte NC 28227",
    "addr:housenumber":"6332",
    "addr:postcode":"28227",
    "addr:street":"Ellesmere Ct",
    "iso:country":"US",
    "sg:address":"6332 Ellesmere Ct",
    "sg:city":"Charlotte",
    "sg:classifiers":[
        {
            "category":"Freight",
            "type":"Transportation"
        }
    ],
    "sg:phone":"+1 704 545 8153",
    "sg:postcode":"28227",
    "sg:province":"NC",
    "wof:name":"Keats Transportation LLC",
    "wof:placetype":"venue"
},
  "geometry": {"coordinates":[-80.682371,35.187601],"type":"Point"}
}