{
  "type": "Feature",
  "properties": {
    "iso:country":"US",
    "sg:address":"1630 Military Cutoff Rd # 108",
    "sg:city":"Wilmington",
    "sg:classifiers":[
        {
            "category":"Health Services",
            "subcategory":"Doctor",
            "type":"Services"
        }
    ],
    "sg:phone":"+1 910 256 8087",
    "sg:postcode":"28403",
    "sg:province":"NC",
    "sg:tags":[
        "physician",
        "pediatrics-emergency",
        "pediatrics",
        "surgeons",
        "medicine",
        "surgeon"
    ],
    "wof:name":"Ambulatory Pediatric Clinic",
    "wof:placetype":"venue"
},
  "geometry": {"coordinates":[-77.83171,34.22105],"type":"Point"}
}