{
  "type": "Feature",
  "properties": {
    "iso:country":"US",
    "sg:address":"3825 Morgan Mill Rd",
    "sg:city":"Monroe",
    "sg:classifiers":[
        {
            "category":"Food & Beverages",
            "subcategory":"Groceries & Convenience Stores",
            "type":"Retail Goods"
        }
    ],
    "sg:phone":"+1 704 289 3651",
    "sg:postcode":"28110",
    "sg:province":"NC",
    "sg:tags":[
        "grocer"
    ],
    "wof:name":"Shop N Go",
    "wof:placetype":"venue"
},
  "geometry": {"coordinates":[-80.503001,35.04246],"type":"Point"}
}