{
  "type": "Feature",
  "properties": {
    "iso:country":"US",
    "sg:address":"2407 N Elm St",
    "sg:city":"Lumberton",
    "sg:classifiers":[
        {
            "category":"Shopping",
            "type":"Retail Goods"
        }
    ],
    "sg:phone":"+1 910 618 1935",
    "sg:postcode":"28358",
    "sg:province":"NC",
    "sg:tags":[
        "limb",
        "artificial"
    ],
    "wof:name":"Total Rehab Orthotic & Prsthtc",
    "wof:placetype":"venue"
},
  "geometry": {"coordinates":[-79.008143,34.635419],"type":"Point"}
}