{
  "type": "Feature",
  "properties": {
    "iso:country":"US",
    "sg:address":"350 Peace St",
    "sg:city":"North Wilkesboro",
    "sg:classifiers":[
        {
            "category":"Real Estate",
            "subcategory":"Real Estate Operator",
            "type":"Services"
        }
    ],
    "sg:phone":"+1 336 838 0511",
    "sg:postcode":"28659",
    "sg:province":"NC",
    "sg:tags":[
        "apartment"
    ],
    "wof:name":"Community Apartments CORP-Wc",
    "wof:placetype":"venue"
},
  "geometry": {"coordinates":[-81.129586,36.156931],"type":"Point"}
}