{
  "type": "Feature",
  "properties": {
    "iso:country":"US",
    "sg:address":"200 N Water St",
    "sg:city":"Elizabeth City",
    "sg:classifiers":[
        {
            "category":"Health Services",
            "subcategory":"Doctor",
            "type":"Services"
        }
    ],
    "sg:phone":"+1 252 335 0431",
    "sg:postcode":"27909",
    "sg:province":"NC",
    "sg:tags":[
        "clinic"
    ],
    "wof:name":"Albemarle Mental Health Ctr",
    "wof:placetype":"venue"
},
  "geometry": {"coordinates":[-76.218425,36.301355],"type":"Point"}
}