{
  "type": "Feature",
  "properties": {
    "iso:country":"US",
    "sg:address":"10100 Fayetteville Rd",
    "sg:city":"Fuquay Varina",
    "sg:classifiers":[
        {
            "category":"Food & Beverages",
            "subcategory":"Groceries & Convenience Stores",
            "type":"Retail Goods"
        }
    ],
    "sg:phone":"+1 919 567 0885",
    "sg:postcode":"27526",
    "sg:province":"NC",
    "wof:name":"Village Convenient Food Mart",
    "wof:placetype":"venue"
},
  "geometry": {"coordinates":[-78.718288,35.628395],"type":"Point"}
}