{
  "type": "Feature",
  "properties": {
    "iso:country":"US",
    "sg:address":"550 New Waverly Pl Ste 120",
    "sg:city":"Cary",
    "sg:classifiers":[
        {
            "category":"Health Services",
            "subcategory":"Doctor",
            "type":"Services"
        }
    ],
    "sg:phone":"+1 919 233 6615",
    "sg:postcode":"27518",
    "sg:province":"NC",
    "sg:tags":[
        "medicine",
        "internal"
    ],
    "wof:name":"Prime Internal Medicine",
    "wof:placetype":"venue"
},
  "geometry": {"coordinates":[-78.775831,35.739699],"type":"Point"}
}