{
  "type": "Feature",
  "properties": {
    "iso:country":"US",
    "sg:address":"6065 Faith Rd",
    "sg:city":"Salisbury",
    "sg:classifiers":[
        {
            "category":"Restaurant",
            "type":"Food & Drink"
        }
    ],
    "sg:phone":"+1 704 933 3373",
    "sg:postcode":"28146",
    "sg:province":"NC",
    "sg:tags":[
        "eating"
    ],
    "wof:name":"Grub Shack",
    "wof:placetype":"venue"
},
  "geometry": {"coordinates":[-80.459092,35.565498],"type":"Point"}
}