{
  "type": "Feature",
  "properties": {
    "iso:country":"US",
    "sg:address":"825 Purser Dr",
    "sg:city":"Raleigh",
    "sg:phone":"+1 919 772 1316",
    "sg:postcode":"27603",
    "sg:province":"NC",
    "wof:name":"Republic Waste Svc Inc",
    "wof:placetype":"venue"
},
  "geometry": {"coordinates":[-78.65759300000001,35.717546],"type":"Point"}
}