{
  "type": "Feature",
  "properties": {
    "addr:full":"301 N Eugene St Greensboro NC 27401",
    "addr:housenumber":"301",
    "addr:postcode":"27401",
    "addr:street":"N Eugene St",
    "iso:country":"US",
    "sg:address":"301 N Eugene St",
    "sg:city":"Greensboro",
    "sg:classifiers":[
        {
            "category":"Government",
            "subcategory":"Office",
            "type":"Public Place"
        }
    ],
    "sg:phone":"+1 336 373 3815",
    "sg:postcode":"27401",
    "sg:province":"NC",
    "wof:name":"Guilford County Data Proc",
    "wof:placetype":"venue"
},
  "geometry": {"coordinates":[-79.793836,36.076758],"type":"Point"}
}