{
  "type": "Feature",
  "properties": {
    "iso:country":"US",
    "sg:address":"5131 US Hwy 74",
    "sg:city":"Monroe",
    "sg:classifiers":[
        {
            "category":"Building & Trades",
            "subcategory":"Landscaping Services",
            "type":"Services"
        }
    ],
    "sg:phone":"+1 704 225 0334",
    "sg:postcode":"28110",
    "sg:province":"NC",
    "wof:name":"Michael T Long",
    "wof:placetype":"venue"
},
  "geometry": {"coordinates":[-80.62622,35.055553],"type":"Point"}
}