{
  "type": "Feature",
  "properties": {
    "iso:country":"US",
    "sg:address":"2411 Schirra Pl",
    "sg:city":"High Point",
    "sg:classifiers":[
        {
            "category":"Professional",
            "type":"Services"
        }
    ],
    "sg:phone":"+1 336 869 2397",
    "sg:postcode":"27263",
    "sg:province":"NC",
    "sg:tags":[
        "establishment"
    ],
    "wof:name":"Sunrooms Plus Inc",
    "wof:placetype":"venue"
},
  "geometry": {"coordinates":[-79.994916,35.92733],"type":"Point"}
}