{
  "type": "Feature",
  "properties": {
    "addr:full":"117 E Kings Hwy Eden NC 27288",
    "addr:housenumber":"117",
    "addr:postcode":"27288",
    "addr:street":"E Kings Hwy",
    "iso:country":"US",
    "sg:address":"117 E Kings Hwy",
    "sg:city":"Eden",
    "sg:classifiers":[
        {
            "category":"Professional",
            "subcategory":"Business Services",
            "type":"Services"
        }
    ],
    "sg:phone":"+1 336 627 6334",
    "sg:postcode":"27288",
    "sg:province":"NC",
    "sg:tags":[
        "affiliate"
    ],
    "wof:name":"Morehead Mem Hosp Foundation",
    "wof:placetype":"venue"
},
  "geometry": {"coordinates":[-79.73697900000001,36.493989],"type":"Point"}
}