{
  "type": "Feature",
  "properties": {
    "addr:full":"1200 SE Maynard Rd Cary NC 27511",
    "addr:housenumber":"1200",
    "addr:postcode":"27511",
    "addr:street":"Se Maynard Rd",
    "iso:country":"US",
    "sg:address":"1200 SE Maynard Rd",
    "sg:city":"Cary",
    "sg:classifiers":[
        {
            "category":"Building & Trades",
            "subcategory":"Landscaping Services",
            "type":"Services"
        }
    ],
    "sg:phone":"+1 919 389 2229",
    "sg:postcode":"27511",
    "sg:province":"NC",
    "sg:tags":[
        "lawn",
        "maintenance",
        "grounds"
    ],
    "wof:name":"Duff's Design & Landscaping",
    "wof:placetype":"venue"
},
  "geometry": {"coordinates":[-78.76419,35.784998],"type":"Point"}
}