{
  "type": "Feature",
  "properties": {
    "addr:full":"1698 Old Cox Rd Asheboro NC 27205",
    "addr:housenumber":"1698",
    "addr:postcode":"27205",
    "addr:street":"Old Cox Rd",
    "iso:country":"US",
    "sg:address":"1698 Old Cox Rd",
    "sg:city":"Asheboro",
    "sg:classifiers":[
        {
            "category":"Insurance",
            "subcategory":"Insurance Agent",
            "type":"Services"
        }
    ],
    "sg:phone":"+1 336 629 4490",
    "sg:postcode":"27205",
    "sg:province":"NC",
    "wof:name":"Tom Frazier Insurance Svc",
    "wof:placetype":"venue"
},
  "geometry": {"coordinates":[-79.78077,35.656857],"type":"Point"}
}