{
  "type": "Feature",
  "properties": {
    "iso:country":"US",
    "sg:address":"627 Davis Dr",
    "sg:city":"Morrisville",
    "sg:classifiers":[
        {
            "category":"Insurance",
            "subcategory":"Insurance Agent",
            "type":"Services"
        }
    ],
    "sg:phone":"+1 919 281 7100",
    "sg:postcode":"27560",
    "sg:province":"NC",
    "wof:name":"MAMSI Health Plans",
    "wof:placetype":"venue"
},
  "geometry": {"coordinates":[-78.86438200000001,35.871103],"type":"Point"}
}