{
  "type": "Feature",
  "properties": {
    "iso:country":"US",
    "sg:address":"2016 Englewood Dr",
    "sg:city":"Apex",
    "sg:classifiers":[
        {
            "category":"Professional",
            "subcategory":"Computer Services",
            "type":"Services"
        }
    ],
    "sg:phone":"+1   ",
    "sg:postcode":"27520",
    "sg:province":"NC",
    "sg:tags":[
        "design",
        "system"
    ],
    "wof:name":"Manrton Corp",
    "wof:placetype":"venue"
},
  "geometry": {"coordinates":[-78.50336799999999,35.655985],"type":"Point"}
}