{
  "type": "Feature",
  "properties": {
    "iso:country":"US",
    "sg:address":"413 Chestnut St",
    "sg:city":"Weldon",
    "sg:classifiers":[
        {
            "category":"Professional",
            "subcategory":"Business Services",
            "type":"Services"
        }
    ],
    "sg:phone":"+1   ",
    "sg:postcode":"27890",
    "sg:province":"NC",
    "wof:name":"National Assoc of Univers",
    "wof:placetype":"venue"
},
  "geometry": {"coordinates":[-77.60188599999999,36.427433],"type":"Point"}
}