{
  "type": "Feature",
  "properties": {
    "iso:country":"US",
    "sg:address":"396 State Rd 903",
    "sg:city":"Kenansville",
    "sg:classifiers":[
        {
            "category":"Building & Trades",
            "subcategory":"Construction",
            "type":"Services"
        }
    ],
    "sg:phone":"+1 910 296 1235",
    "sg:postcode":"28349",
    "sg:province":"NC",
    "sg:tags":[
        "contractor"
    ],
    "wof:name":"United Contractors Inc",
    "wof:placetype":"venue"
},
  "geometry": {"coordinates":[-77.960463,34.964437],"type":"Point"}
}