{
  "type": "Feature",
  "properties": {
    "iso:country":"US",
    "sg:address":"1569 Jim Johnson Rd",
    "sg:city":"Fayetteville",
    "sg:classifiers":[
        {
            "category":"Travel",
            "subcategory":"Hotels & Motels",
            "type":"Entertainment"
        }
    ],
    "sg:phone":"+1 910 321 1460",
    "sg:postcode":"28312",
    "sg:province":"NC",
    "sg:tags":[
        "operation"
    ],
    "sg:website":"www.redroof.com",
    "wof:name":"Red Roof Inn",
    "wof:placetype":"venue"
},
  "geometry": {"coordinates":[-78.819582,35.015565],"type":"Point"}
}