{
  "type": "Feature",
  "properties": {
    "iso:country":"US",
    "sg:address":"564 State Hwy 46",
    "sg:city":"Gaston",
    "sg:classifiers":[
        {
            "category":"Recreation",
            "type":"Entertainment"
        }
    ],
    "sg:phone":"+1 252 535 5092",
    "sg:postcode":"27832",
    "sg:province":"NC",
    "sg:tags":[
        "center"
    ],
    "wof:name":"Old Gaston Community Ctr",
    "wof:placetype":"venue"
},
  "geometry": {"coordinates":[-77.79117599999999,36.535678],"type":"Point"}
}