{
  "type": "Feature",
  "properties": {
    "iso:country":"US",
    "sg:address":"9101 Southern Pine Blvd",
    "sg:city":"Charlotte",
    "sg:classifiers":[
        {
            "category":"Utilities",
            "subcategory":"Telephone",
            "type":"Services"
        }
    ],
    "sg:phone":"+1 704 529 5953",
    "sg:postcode":"28273",
    "sg:province":"NC",
    "sg:tags":[
        "company"
    ],
    "sg:website":"www.birch.com",
    "wof:name":"Birch Telecom",
    "wof:placetype":"venue"
},
  "geometry": {"coordinates":[-80.911734,35.135913],"type":"Point"}
}