{
  "type": "Feature",
  "properties": {
    "iso:country":"US",
    "sg:address":"2075 Bear Creek Rd",
    "sg:city":"Leicester",
    "sg:classifiers":[
        {
            "category":"Farming",
            "subcategory":"Farm",
            "type":"Manufacturing & Wholesale Goods"
        }
    ],
    "sg:phone":"+1 828 683 3340",
    "sg:postcode":"28748",
    "sg:province":"NC",
    "sg:tags":[
        "crop",
        "general"
    ],
    "wof:name":"Everette C Ponder",
    "wof:placetype":"venue"
},
  "geometry": {"coordinates":[-82.683115,35.675642],"type":"Point"}
}