{
  "type": "Feature",
  "properties": {
    "iso:country":"US",
    "sg:address":"80 Hoover Rd",
    "sg:city":"White Oak",
    "sg:classifiers":[
        {
            "category":"Sports & Exercise",
            "subcategory":"Golf",
            "type":"Entertainment"
        }
    ],
    "sg:phone":"+1 910 866 4463",
    "sg:postcode":"28399",
    "sg:province":"NC",
    "sg:tags":[
        "course",
        "public"
    ],
    "wof:name":"White Oak Greens Golf Course",
    "wof:placetype":"venue"
},
  "geometry": {"coordinates":[-78.70861499999999,34.735738],"type":"Point"}
}