{
  "type": "Feature",
  "properties": {
    "iso:country":"US",
    "sg:address":"2686 Riverview Rd",
    "sg:city":"Lexington",
    "sg:classifiers":[
        {
            "category":"Professional",
            "subcategory":"Business Services",
            "type":"Services"
        }
    ],
    "sg:phone":"+1   ",
    "sg:postcode":"27292",
    "sg:province":"NC",
    "wof:name":"Enhancements Unlimited",
    "wof:placetype":"venue"
},
  "geometry": {"coordinates":[-80.30713900000001,35.674606],"type":"Point"}
}