{
  "type": "Feature",
  "properties": {
    "addr:full":"7828 Arboretum Dr Charlotte NC 28270",
    "addr:housenumber":"7828",
    "addr:postcode":"28270",
    "addr:street":"Arboretum Dr",
    "iso:country":"US",
    "sg:address":"7828 Arboretum Dr",
    "sg:city":"Charlotte",
    "sg:classifiers":[
        {
            "category":"Building & Trades",
            "subcategory":"Cleaning & Sanitation",
            "type":"Services"
        }
    ],
    "sg:phone":"+1 704 341 3087",
    "sg:postcode":"28270",
    "sg:province":"NC",
    "sg:tags":[
        "janitor"
    ],
    "wof:name":"Cleaning By Andrea",
    "wof:placetype":"venue"
},
  "geometry": {"coordinates":[-80.77676599999999,35.101286],"type":"Point"}
}