{
  "type": "Feature",
  "properties": {
    "iso:country":"US",
    "sg:address":"735 W Dixie Dr",
    "sg:city":"Asheboro",
    "sg:classifiers":[
        {
            "category":"Shopping",
            "subcategory":"Music",
            "type":"Retail Goods"
        }
    ],
    "sg:phone":"+1 336 626 4492",
    "sg:postcode":"27205",
    "sg:province":"NC",
    "sg:tags":[
        "video",
        "disc",
        "tape",
        "cassette"
    ],
    "wof:name":"Video Tek Inc",
    "wof:placetype":"venue"
},
  "geometry": {"coordinates":[-79.82455,35.687404],"type":"Point"}
}