{
  "type": "Feature",
  "properties": {
    "addr:full":"4622 Manchester Dr Wilmington NC 28405",
    "addr:housenumber":"4622",
    "addr:postcode":"28405",
    "addr:street":"Manchester Dr",
    "iso:country":"US",
    "sg:address":"4622 Manchester Dr",
    "sg:city":"Wilmington",
    "sg:classifiers":[
        {
            "category":"Retail",
            "subcategory":"Auto Repair",
            "type":"Services"
        }
    ],
    "sg:phone":"+1 910 675 3232",
    "sg:postcode":"28405",
    "sg:province":"NC",
    "sg:tags":[
        "automotive",
        "consultant"
    ],
    "wof:name":"American Automotive",
    "wof:placetype":"venue"
},
  "geometry": {"coordinates":[-77.872758,34.260852],"type":"Point"}
}