{
  "type": "Feature",
  "properties": {
    "iso:country":"US",
    "sg:address":"2134 Empire Rd SW",
    "sg:city":"Supply",
    "sg:classifiers":[
        {
            "category":"Building & Trades",
            "subcategory":"Plumbing",
            "type":"Services"
        }
    ],
    "sg:phone":"+1 910 842 6903",
    "sg:postcode":"28462",
    "sg:province":"NC",
    "sg:tags":[
        "plumbing",
        "contractor"
    ],
    "wof:name":"Clemmon's Plumbing Inc",
    "wof:placetype":"venue"
},
  "geometry": {"coordinates":[-78.323829,33.963165],"type":"Point"}
}