{
  "type": "Feature",
  "properties": {
    "addr:full":"510 D St North Wilkesboro NC 28659",
    "addr:housenumber":"510",
    "addr:postcode":"28659",
    "addr:street":"D St",
    "iso:country":"US",
    "sg:address":"510 D St",
    "sg:city":"North Wilkesboro",
    "sg:classifiers":[
        {
            "category":"Organizations",
            "subcategory":"Religious Organization",
            "type":"Services"
        }
    ],
    "sg:phone":"+1 336 838 5197",
    "sg:postcode":"28659",
    "sg:province":"NC",
    "sg:tags":[
        "church"
    ],
    "sg:website":"www.fbcnw.org",
    "wof:name":"First Baptist Church",
    "wof:placetype":"venue"
},
  "geometry": {"coordinates":[-81.14194999999999,36.163708],"type":"Point"}
}