{
  "type": "Feature",
  "properties": {
    "iso:country":"US",
    "sg:address":"787 Trinity Church Rd",
    "sg:city":"Louisburg",
    "sg:classifiers":[
        {
            "category":"Utilities",
            "subcategory":"Refuse",
            "type":"Services"
        }
    ],
    "sg:phone":"+1 919 496 3004",
    "sg:postcode":"27549",
    "sg:province":"NC",
    "sg:tags":[
        "garbage",
        "collection"
    ],
    "wof:name":"Waste Industries Inc",
    "wof:placetype":"venue"
},
  "geometry": {"coordinates":[-78.259996,36.177995],"type":"Point"}
}