{
  "type": "Feature",
  "properties": {
    "addr:full":"1017 Carolina St Greensboro NC 27401",
    "addr:housenumber":"1017",
    "addr:postcode":"27401",
    "addr:street":"Carolina St",
    "iso:country":"US",
    "sg:address":"1017 Carolina St",
    "sg:city":"Greensboro",
    "sg:classifiers":[
        {
            "category":"Recreation",
            "type":"Entertainment"
        }
    ],
    "sg:phone":"+1   ",
    "sg:postcode":"27401",
    "sg:province":"NC",
    "wof:name":"Readings By Doreen",
    "wof:placetype":"venue"
},
  "geometry": {"coordinates":[-79.790323,36.087959],"type":"Point"}
}