{
  "type": "Feature",
  "properties": {
    "addr:full":"801 Pamlico Dr Cary NC 27511",
    "addr:housenumber":"801",
    "addr:postcode":"27511",
    "addr:street":"Pamlico Dr",
    "iso:country":"US",
    "sg:address":"801 Pamlico Dr",
    "sg:city":"Cary",
    "sg:classifiers":[
        {
            "category":"Building & Trades",
            "subcategory":"Electrical",
            "type":"Services"
        }
    ],
    "sg:phone":"+1 919 460 6866",
    "sg:postcode":"27511",
    "sg:province":"NC",
    "sg:tags":[
        "electrical",
        "contractor"
    ],
    "wof:name":"Teasley Dl Electrical Contr",
    "wof:placetype":"venue"
},
  "geometry": {"coordinates":[-78.794923,35.777863],"type":"Point"}
}