{
  "type": "Feature",
  "properties": {
    "addr:full":"100 N Main St Winston Salem NC 27101",
    "addr:housenumber":"100",
    "addr:postcode":"27101",
    "addr:street":"N Main St",
    "iso:country":"US",
    "sg:address":"100 N Main St",
    "sg:city":"Winston Salem",
    "sg:classifiers":[
        {
            "category":"Real Estate",
            "subcategory":"Real Estate Agent",
            "type":"Services"
        }
    ],
    "sg:phone":"+1 336 201 0372",
    "sg:postcode":"27101",
    "sg:province":"NC",
    "sg:tags":[
        "management"
    ],
    "wof:name":"Cushman & Wakefield",
    "wof:placetype":"venue"
},
  "geometry": {"coordinates":[-80.243635,36.096281],"type":"Point"}
}