{
  "type": "Feature",
  "properties": {
    "iso:country":"US",
    "sg:address":"3720 Freeman Rd",
    "sg:city":"Durham",
    "sg:classifiers":[
        {
            "category":"Retail",
            "subcategory":"Repair Shop",
            "type":"Services"
        },
        {
            "category":"Building & Trades",
            "subcategory":"Construction",
            "type":"Services"
        }
    ],
    "sg:phone":"+1 919 598 9066",
    "sg:postcode":"27703",
    "sg:province":"NC",
    "sg:tags":[
        "welding",
        "contractor"
    ],
    "wof:name":"Affordable Welding & Fabricati",
    "wof:placetype":"venue"
},
  "geometry": {"coordinates":[-78.824055,35.996377],"type":"Point"}
}