{
  "type": "Feature",
  "properties": {
    "addr:full":"7920 Oakbark Ln Charlotte NC 28226",
    "addr:housenumber":"7920",
    "addr:postcode":"28226",
    "addr:street":"Oakbark Ln",
    "iso:country":"US",
    "sg:address":"7920 Oakbark Ln",
    "sg:city":"Charlotte",
    "sg:classifiers":[
        {
            "category":"Professional",
            "subcategory":"Management & Consulting",
            "type":"Services"
        }
    ],
    "sg:phone":"+1 704 542 7417",
    "sg:postcode":"28226",
    "sg:province":"NC",
    "sg:tags":[
        "marketing",
        "consultant"
    ],
    "wof:name":"Durration Sales & Distribution",
    "wof:placetype":"venue"
},
  "geometry": {"coordinates":[-80.85800500000001,35.073315],"type":"Point"}
}