{
  "type": "Feature",
  "properties": {
    "iso:country":"US",
    "sg:address":"1707 Rice Planters Rd",
    "sg:city":"Charlotte",
    "sg:classifiers":[
        {
            "category":"Professional",
            "type":"Services"
        }
    ],
    "sg:phone":"+1 704 583 6343",
    "sg:postcode":"28273",
    "sg:province":"NC",
    "wof:name":"North Carolina Round Up",
    "wof:placetype":"venue"
},
  "geometry": {"coordinates":[-80.958196,35.145342],"type":"Point"}
}