{
  "type": "Feature",
  "properties": {
    "iso:country":"US",
    "sg:address":"17 Devon Dr",
    "sg:city":"Pinehurst",
    "sg:classifiers":[
        {
            "category":"Insurance",
            "subcategory":"Insurance Agent",
            "type":"Services"
        }
    ],
    "sg:phone":"+1 910 295 2022",
    "sg:postcode":"28374",
    "sg:province":"NC",
    "wof:name":"PLS Of The Carolinas LLC",
    "wof:placetype":"venue"
},
  "geometry": {"coordinates":[-79.50094799999999,35.193933],"type":"Point"}
}