{
  "type": "Feature",
  "properties": {
    "iso:country":"US",
    "sg:address":"3039 South Blvd",
    "sg:city":"Charlotte",
    "sg:classifiers":[
        {
            "category":"Utilities",
            "subcategory":"Mobile Phone",
            "type":"Services"
        }
    ],
    "sg:phone":"+1 704 559 8100",
    "sg:postcode":"28209",
    "sg:province":"NC",
    "sg:tags":[
        "telephone",
        "cellular"
    ],
    "wof:name":"Hispanos Unidos",
    "wof:placetype":"venue"
},
  "geometry": {"coordinates":[-80.86944,35.197378],"type":"Point"}
}