{
  "type": "Feature",
  "properties": {
    "addr:full":"305 E Main St Williamston NC 27892",
    "addr:housenumber":"305",
    "addr:postcode":"27892",
    "addr:street":"E Main St",
    "iso:country":"US",
    "sg:address":"305 E Main St",
    "sg:city":"Williamston",
    "sg:classifiers":[
        {
            "category":"Government",
            "subcategory":"Office",
            "type":"Public Place"
        }
    ],
    "sg:phone":"+1 252 792 7016",
    "sg:postcode":"27892",
    "sg:province":"NC",
    "sg:tags":[
        "county",
        "resource"
    ],
    "wof:name":"Martin County Food Stamp Unit",
    "wof:placetype":"venue"
},
  "geometry": {"coordinates":[-77.051643,35.856848],"type":"Point"}
}