{
  "type": "Feature",
  "properties": {
    "addr:full":"7400 Antioch Church Rd Seagrove NC 27341",
    "addr:housenumber":"7400",
    "addr:postcode":"27341",
    "addr:street":"Antioch Church Rd",
    "iso:country":"US",
    "sg:address":"7400 Antioch Church Rd",
    "sg:city":"Seagrove",
    "sg:classifiers":[
        {
            "category":"Organizations",
            "subcategory":"Religious Organization",
            "type":"Services"
        }
    ],
    "sg:phone":"+1 336 879 5992",
    "sg:postcode":"27341",
    "sg:province":"NC",
    "sg:tags":[
        "church"
    ],
    "wof:name":"Mt Zion Pleasant Hl Methodist",
    "wof:placetype":"venue"
},
  "geometry": {"coordinates":[-79.615076,35.553282],"type":"Point"}
}