{
  "type": "Feature",
  "properties": {
    "addr:full":"2129 S Main St Winston Salem NC 27127",
    "addr:housenumber":"2129",
    "addr:postcode":"27127",
    "addr:street":"S Main St",
    "iso:country":"US",
    "sg:address":"2129 S Main St",
    "sg:city":"Winston Salem",
    "sg:classifiers":[
        {
            "category":"Retail",
            "subcategory":"Laundry & Dry Cleaning",
            "type":"Services"
        }
    ],
    "sg:phone":"+1 336 777 8109",
    "sg:postcode":"27127",
    "sg:province":"NC",
    "sg:tags":[
        "cleaners"
    ],
    "wof:name":"Craft Cleaners",
    "wof:placetype":"venue"
},
  "geometry": {"coordinates":[-80.23914499999999,36.071309],"type":"Point"}
}