{
  "type": "Feature",
  "properties": {
    "addr:full":"236 Riverbend Rd Graham NC 27253",
    "addr:housenumber":"236",
    "addr:postcode":"27253",
    "addr:street":"Riverbend Rd",
    "iso:country":"US",
    "sg:address":"236 Riverbend Rd",
    "sg:city":"Graham",
    "sg:classifiers":[
        {
            "category":"Health Services",
            "subcategory":"Doctor",
            "type":"Services"
        }
    ],
    "sg:phone":"+1   ",
    "sg:postcode":"27253",
    "sg:province":"NC",
    "sg:tags":[
        "medical"
    ],
    "wof:name":"Jack H Wolf MD",
    "wof:placetype":"venue"
},
  "geometry": {"coordinates":[-79.384669,36.06542],"type":"Point"}
}