{
  "type": "Feature",
  "properties": {
    "iso:country":"US",
    "sg:address":"1900 W Wilson St",
    "sg:city":"Tarboro",
    "sg:classifiers":[
        {
            "category":"Retail",
            "subcategory":"Portrait Studio",
            "type":"Services"
        }
    ],
    "sg:phone":"+1   ",
    "sg:postcode":"27886",
    "sg:province":"NC",
    "sg:tags":[
        "photo"
    ],
    "wof:name":"Brown Video & Photography",
    "wof:placetype":"venue"
},
  "geometry": {"coordinates":[-77.56612800000001,35.885881],"type":"Point"}
}