{
  "type": "Feature",
  "properties": {
    "iso:country":"US",
    "sg:address":"3033 Marlborough Rd",
    "sg:city":"Burlington",
    "sg:classifiers":[
        {
            "category":"Building & Trades",
            "subcategory":"Construction",
            "type":"Services"
        }
    ],
    "sg:phone":"+1 336 584 9800",
    "sg:postcode":"27215",
    "sg:province":"NC",
    "sg:tags":[
        "home",
        "improvement"
    ],
    "wof:name":"B F Construction",
    "wof:placetype":"venue"
},
  "geometry": {"coordinates":[-79.482936,36.066379],"type":"Point"}
}