{
  "type": "Feature",
  "properties": {
    "addr:full":"3501 Associate Dr Greensboro NC 27405",
    "addr:housenumber":"3501",
    "addr:postcode":"27405",
    "addr:street":"Associate Dr",
    "iso:country":"US",
    "sg:address":"3501 Associate Dr",
    "sg:city":"Greensboro",
    "sg:classifiers":[
        {
            "category":"Home & Garden",
            "subcategory":"Carpets & Floor Coverings",
            "type":"Retail Goods"
        }
    ],
    "sg:phone":"+1 336 854 4001",
    "sg:postcode":"27405",
    "sg:province":"NC",
    "sg:website":"www.imperialcarpetinc.com",
    "wof:name":"Imperial Carpet Inc",
    "wof:placetype":"venue"
},
  "geometry": {"coordinates":[-79.748566,36.128533],"type":"Point"}
}