{
  "type": "Feature",
  "properties": {
    "addr:full":"103 E Horton St Zebulon NC 27597",
    "addr:housenumber":"103",
    "addr:postcode":"27597",
    "addr:street":"E Horton St",
    "iso:country":"US",
    "sg:address":"103 E Horton St",
    "sg:city":"Zebulon",
    "sg:classifiers":[
        {
            "category":"Real Estate",
            "subcategory":"Surveying",
            "type":"Services"
        }
    ],
    "sg:phone":"+1 919 269 5700",
    "sg:postcode":"27597",
    "sg:province":"NC",
    "sg:tags":[
        "surveyor"
    ],
    "wof:name":"Robert G Williams",
    "wof:placetype":"venue"
},
  "geometry": {"coordinates":[-78.31133800000001,35.823065],"type":"Point"}
}