{
  "type": "Feature",
  "properties": {
    "addr:full":"8202 Joe Brown Hwy S Clarendon NC 28432",
    "addr:housenumber":"8202",
    "addr:postcode":"28432",
    "addr:street":"Joe Brown Hwy S",
    "iso:country":"US",
    "sg:address":"8202 Joe Brown Hwy S",
    "sg:city":"Clarendon",
    "sg:phone":"+1 910 653 4959",
    "sg:postcode":"28432",
    "sg:province":"NC",
    "sg:tags":[
        "farm"
    ],
    "wof:name":"Harold Williams",
    "wof:placetype":"venue"
},
  "geometry": {"coordinates":[-78.82402,34.217289],"type":"Point"}
}