{
  "type": "Feature",
  "properties": {
    "iso:country":"US",
    "sg:address":"2395 Baynes Rd",
    "sg:city":"Burlington",
    "sg:classifiers":[
        {
            "category":"Food & Beverages",
            "subcategory":"Groceries & Convenience Stores",
            "type":"Retail Goods"
        }
    ],
    "sg:phone":"+1 336 421 9088",
    "sg:postcode":"27217",
    "sg:province":"NC",
    "wof:name":"Baynes Store",
    "wof:placetype":"venue"
},
  "geometry": {"coordinates":[-79.32128299999999,36.269568],"type":"Point"}
}