{
  "type": "Feature",
  "properties": {
    "addr:full":"336 Deerfield Rd Boone NC 28607",
    "addr:housenumber":"336",
    "addr:postcode":"28607",
    "addr:street":"Deerfield Rd",
    "iso:country":"US",
    "sg:address":"336 Deerfield Rd",
    "sg:city":"Boone",
    "sg:classifiers":[
        {
            "category":"Health Services",
            "subcategory":"Doctor",
            "type":"Services"
        }
    ],
    "sg:phone":"+1   ",
    "sg:postcode":"28607",
    "sg:province":"NC",
    "sg:tags":[
        "medical"
    ],
    "wof:name":"Appalchian Rgonal Pain MGT Cen",
    "wof:placetype":"venue"
},
  "geometry": {"coordinates":[-81.650397,36.200895],"type":"Point"}
}