{
  "type": "Feature",
  "properties": {
    "iso:country":"US",
    "sg:address":"1985 Tate Blvd SE",
    "sg:city":"Hickory",
    "sg:classifiers":[
        {
            "category":"Health Services",
            "subcategory":"Hospital",
            "type":"Services"
        }
    ],
    "sg:phone":"+1 828 327 2595",
    "sg:postcode":"28602",
    "sg:province":"NC",
    "sg:tags":[
        "mental"
    ],
    "sg:website":"www.co.catawba.nc.us",
    "wof:name":"Mental Health Svc-Catawba Cnty",
    "wof:placetype":"venue"
},
  "geometry": {"coordinates":[-81.302632,35.728246],"type":"Point"}
}