{
  "type": "Feature",
  "properties": {
    "iso:country":"US",
    "sg:address":"177 Persimmon Ln",
    "sg:city":"Littleton",
    "sg:classifiers":[
        {
            "category":"Railroad",
            "type":"Transportation"
        }
    ],
    "sg:phone":"+1 252 586 6303",
    "sg:postcode":"27850",
    "sg:province":"NC",
    "sg:tags":[
        "operator",
        "line"
    ],
    "wof:name":"RR Inspections Inc",
    "wof:placetype":"venue"
},
  "geometry": {"coordinates":[-77.907882,36.497472],"type":"Point"}
}