{
  "type": "Feature",
  "properties": {
    "iso:country":"US",
    "sg:address":"12116 Betts Ln",
    "sg:city":"Raleigh",
    "sg:classifiers":[
        {
            "category":"Professional",
            "subcategory":"Engineering",
            "type":"Services"
        }
    ],
    "sg:phone":"+1   ",
    "sg:postcode":"27614",
    "sg:province":"NC",
    "wof:name":"Robert J Owens & Associates",
    "wof:placetype":"venue"
},
  "geometry": {"coordinates":[-78.625975,35.947825],"type":"Point"}
}