{
  "type": "Feature",
  "properties": {
    "addr:full":"2201 Trent Blvd New Bern NC 28560",
    "addr:housenumber":"2201",
    "addr:postcode":"28560",
    "addr:street":"Trent Blvd",
    "iso:country":"US",
    "sg:address":"2201 Trent Blvd",
    "sg:city":"New Bern",
    "sg:classifiers":[
        {
            "category":"Wholesale",
            "subcategory":"Auto Parts",
            "type":"Manufacturing & Wholesale Goods"
        }
    ],
    "sg:phone":"+1 252 638 6016",
    "sg:postcode":"28560",
    "sg:province":"NC",
    "wof:name":"Carquest Auto Parts",
    "wof:placetype":"venue"
},
  "geometry": {"coordinates":[-77.07396199999999,35.103486],"type":"Point"}
}