{
  "type": "Feature",
  "properties": {
    "addr:full":"1 Pine Top Ct Jackson Springs NC 27281",
    "addr:housenumber":"1",
    "addr:postcode":"27281",
    "addr:street":"Pine Top Ct Jackson",
    "iso:country":"US",
    "sg:address":"1 Pine Top Ct",
    "sg:city":"Jackson Springs",
    "sg:classifiers":[
        {
            "category":"Professional",
            "type":"Services"
        }
    ],
    "sg:phone":"+1 910 295 1002",
    "sg:postcode":"27281",
    "sg:province":"NC",
    "wof:name":"Dreammaker Bath Kitchen B",
    "wof:placetype":"venue"
},
  "geometry": {"coordinates":[-79.564088,35.176494],"type":"Point"}
}