{
  "type": "Feature",
  "properties": {
    "addr:full":"2926 Fox Run Cir Kinston NC 28504",
    "addr:housenumber":"2926",
    "addr:postcode":"28504",
    "addr:street":"Fox Run Cir",
    "iso:country":"US",
    "sg:address":"2926 Fox Run Cir",
    "sg:city":"Kinston",
    "sg:classifiers":[
        {
            "category":"Real Estate",
            "subcategory":"Real Estate Operator",
            "type":"Services"
        }
    ],
    "sg:phone":"+1 252 527 0123",
    "sg:postcode":"28504",
    "sg:province":"NC",
    "sg:tags":[
        "building",
        "nonresidential"
    ],
    "wof:name":"Q&L Properties LLC",
    "wof:placetype":"venue"
},
  "geometry": {"coordinates":[-77.67703400000001,35.302728],"type":"Point"}
}