{
  "type": "Feature",
  "properties": {
    "iso:country":"US",
    "sg:address":"8817 Ray Rd",
    "sg:city":"Raleigh",
    "sg:classifiers":[
        {
            "category":"Professional",
            "type":"Services"
        }
    ],
    "sg:phone":"+1   ",
    "sg:postcode":"27613",
    "sg:province":"NC",
    "wof:name":"E&T Truck Service Inc",
    "wof:placetype":"venue"
},
  "geometry": {"coordinates":[-78.703271,35.904199],"type":"Point"}
}