{
  "type": "Feature",
  "properties": {
    "addr:full":"715 E Geer St Durham NC 27701",
    "addr:housenumber":"715",
    "addr:postcode":"27701",
    "addr:street":"E Geer St",
    "iso:country":"US",
    "sg:address":"715 E Geer St",
    "sg:city":"Durham",
    "sg:classifiers":[
        {
            "category":"Organizations",
            "subcategory":"Religious Organization",
            "type":"Services"
        }
    ],
    "sg:phone":"+1 919 688 3564",
    "sg:postcode":"27701",
    "sg:province":"NC",
    "sg:tags":[
        "church"
    ],
    "wof:name":"Father Son Holiness Church",
    "wof:placetype":"venue"
},
  "geometry": {"coordinates":[-78.88151999999999,36.00373],"type":"Point"}
}