{
  "type": "Feature",
  "properties": {
    "addr:full":"8046 N Hebron Church Rd Vale NC 28168",
    "addr:housenumber":"8046",
    "addr:postcode":"28168",
    "addr:street":"N Hebron Church Rd",
    "iso:country":"US",
    "sg:address":"8046 N Hebron Church Rd",
    "sg:city":"Vale",
    "sg:classifiers":[
        {
            "category":"Organizations",
            "subcategory":"Religious Organization",
            "type":"Services"
        }
    ],
    "sg:phone":"+1 704 276 1744",
    "sg:postcode":"28168",
    "sg:province":"NC",
    "sg:tags":[
        "church"
    ],
    "wof:name":"Mt Vernon Baptist Church",
    "wof:placetype":"venue"
},
  "geometry": {"coordinates":[-81.482097,35.531921],"type":"Point"}
}