{
  "type": "Feature",
  "properties": {
    "iso:country":"US",
    "sg:address":"504 Green St E",
    "sg:city":"Wilson",
    "sg:classifiers":[
        {
            "category":"Real Estate",
            "subcategory":"Developer",
            "type":"Services"
        }
    ],
    "sg:phone":"+1 252 243 4855",
    "sg:postcode":"27893",
    "sg:province":"NC",
    "wof:name":"Wilson Community Improvement",
    "wof:placetype":"venue"
},
  "geometry": {"coordinates":[-77.905432,35.723296],"type":"Point"}
}