{
  "type": "Feature",
  "properties": {
    "addr:full":"2008 Redding Ln Durham NC 27712",
    "addr:housenumber":"2008",
    "addr:postcode":"27712",
    "addr:street":"Redding Ln",
    "iso:country":"US",
    "sg:address":"2008 Redding Ln",
    "sg:city":"Durham",
    "sg:classifiers":[
        {
            "category":"Building & Trades",
            "subcategory":"Landscaping Services",
            "type":"Services"
        }
    ],
    "sg:phone":"+1 919 471 1264",
    "sg:postcode":"27712",
    "sg:province":"NC",
    "wof:name":"Westbrook Lawn Maintenance",
    "wof:placetype":"venue"
},
  "geometry": {"coordinates":[-78.94739199999999,36.08244],"type":"Point"}
}