{
  "type": "Feature",
  "properties": {
    "addr:full":"509 Longleaf Dr New Bern NC 28560",
    "addr:housenumber":"509",
    "addr:postcode":"28560",
    "addr:street":"Longleaf Dr",
    "iso:country":"US",
    "sg:address":"509 Longleaf Dr",
    "sg:city":"New Bern",
    "sg:classifiers":[
        {
            "category":"Food & Beverages",
            "subcategory":"Specialty",
            "type":"Retail Goods"
        }
    ],
    "sg:phone":"+1 252 745 5464",
    "sg:postcode":"28560",
    "sg:province":"NC",
    "wof:name":"Next To Nature 2",
    "wof:placetype":"venue"
},
  "geometry": {"coordinates":[-76.91560699999999,35.121234],"type":"Point"}
}