{
  "type": "Feature",
  "properties": {
    "addr:full":"10311 Lady Grace Ln Charlotte NC 28270",
    "addr:housenumber":"10311",
    "addr:postcode":"28270",
    "addr:street":"Lady Grace Ln",
    "iso:country":"US",
    "sg:address":"10311 Lady Grace Ln",
    "sg:city":"Charlotte",
    "sg:classifiers":[
        {
            "category":"Professional",
            "subcategory":"Detective & Security Services",
            "type":"Services"
        }
    ],
    "sg:phone":"+1   ",
    "sg:postcode":"28270",
    "sg:province":"NC",
    "sg:tags":[
        "system"
    ],
    "wof:name":"Ed Waylock Security Consulting",
    "wof:placetype":"venue"
},
  "geometry": {"coordinates":[-80.766971,35.070261],"type":"Point"}
}