{
  "type": "Feature",
  "properties": {
    "addr:full":"4304 Wilkinson Blvd Gastonia NC 28056",
    "addr:housenumber":"4304",
    "addr:postcode":"28056",
    "addr:street":"Wilkinson Blvd",
    "iso:country":"US",
    "sg:address":"4304 Wilkinson Blvd",
    "sg:city":"Gastonia",
    "sg:classifiers":[
        {
            "category":"Autos & Motor Vehicles",
            "subcategory":"Automobile Sales",
            "type":"Retail Goods"
        }
    ],
    "sg:phone":"+1 704 824 9451",
    "sg:postcode":"28056",
    "sg:province":"NC",
    "sg:tags":[
        "car",
        "used",
        "dealer"
    ],
    "wof:name":"Village Auto Sales Inc",
    "wof:placetype":"venue"
},
  "geometry": {"coordinates":[-81.10390099999999,35.25614],"type":"Point"}
}