{
  "type": "Feature",
  "properties": {
    "iso:country":"US",
    "sg:address":"118 Flowers-Pridgen Dr",
    "sg:city":"Whiteville",
    "sg:classifiers":[
        {
            "category":"Professional",
            "type":"Services"
        }
    ],
    "sg:phone":"+1 910 640 3003",
    "sg:postcode":"28472",
    "sg:province":"NC",
    "sg:tags":[
        "establishment"
    ],
    "wof:name":"Swing Away",
    "wof:placetype":"venue"
},
  "geometry": {"coordinates":[-78.702692,34.348401],"type":"Point"}
}