{
  "type": "Feature",
  "properties": {
    "iso:country":"US",
    "sg:address":"9504 Gooden Dr",
    "sg:city":"Fayetteville",
    "sg:classifiers":[
        {
            "category":"Arts & Performance",
            "subcategory":"Theater",
            "type":"Entertainment"
        }
    ],
    "sg:phone":"+1   ",
    "sg:postcode":"28314",
    "sg:province":"NC",
    "sg:tags":[
        "pianist"
    ],
    "wof:name":"Jeannette Hollins",
    "wof:placetype":"venue"
},
  "geometry": {"coordinates":[-79.03997200000001,35.044699],"type":"Point"}
}