{
  "type": "Feature",
  "properties": {
    "iso:country":"US",
    "sg:address":"103 Clark St",
    "sg:city":"Morganton",
    "sg:classifiers":[
        {
            "category":"Wholesale",
            "subcategory":"Hardware",
            "type":"Manufacturing & Wholesale Goods"
        },
        {
            "category":"Building & Trades",
            "subcategory":"Plumbing",
            "type":"Services"
        }
    ],
    "sg:phone":"+1 828 433 9808",
    "sg:postcode":"28655",
    "sg:province":"NC",
    "sg:tags":[
        "furnace",
        "contractor"
    ],
    "wof:name":"Alan's Furnace Repair",
    "wof:placetype":"venue"
},
  "geometry": {"coordinates":[-81.690721,35.758448],"type":"Point"}
}