{
  "type": "Feature",
  "properties": {
    "iso:country":"US",
    "sg:address":"122 Park Dr",
    "sg:city":"Shiloh",
    "sg:classifiers":[
        {
            "category":"Retail",
            "subcategory":"Repair Shop",
            "type":"Services"
        }
    ],
    "sg:phone":"+1   ",
    "sg:postcode":"27974",
    "sg:province":"NC",
    "sg:tags":[
        "picture",
        "framing",
        "custom"
    ],
    "wof:name":"Shamrock Studio",
    "wof:placetype":"venue"
},
  "geometry": {"coordinates":[-76.094943,36.255989],"type":"Point"}
}