{
  "type": "Feature",
  "properties": {
    "addr:full":"223 US Hwy 70 E Garner NC 27529",
    "addr:housenumber":"223",
    "addr:postcode":"27529",
    "addr:street":"Us Hwy 70 E",
    "iso:country":"US",
    "sg:address":"223 US Hwy 70 E",
    "sg:city":"Garner",
    "sg:classifiers":[
        {
            "category":"Organizations",
            "subcategory":"Religious Organization",
            "type":"Services"
        }
    ],
    "sg:phone":"+1 919 661 9466",
    "sg:postcode":"27529",
    "sg:province":"NC",
    "sg:tags":[
        "church"
    ],
    "wof:name":"Sovereign King Church",
    "wof:placetype":"venue"
},
  "geometry": {"coordinates":[-78.601173,35.70207],"type":"Point"}
}