{
  "type": "Feature",
  "properties": {
    "addr:full":"1798 S Ridge Ave Kannapolis NC 28083",
    "addr:housenumber":"1798",
    "addr:postcode":"28083",
    "addr:street":"S Ridge Ave",
    "iso:country":"US",
    "sg:address":"1798 S Ridge Ave",
    "sg:city":"Kannapolis",
    "sg:classifiers":[
        {
            "category":"Retail",
            "subcategory":"Portrait Studio",
            "type":"Services"
        }
    ],
    "sg:phone":"+1 704 932 5555",
    "sg:postcode":"28083",
    "sg:province":"NC",
    "sg:tags":[
        "photographer"
    ],
    "wof:name":"Envisions By Jennifer",
    "wof:placetype":"venue"
},
  "geometry": {"coordinates":[-80.621804,35.47183],"type":"Point"}
}