{
  "type": "Feature",
  "properties": {
    "addr:full":"5613 Duraleigh Rd Raleigh NC 27612",
    "addr:housenumber":"5613",
    "addr:postcode":"27612",
    "addr:street":"Duraleigh Rd",
    "iso:country":"US",
    "sg:address":"5613 Duraleigh Rd",
    "sg:city":"Raleigh",
    "sg:classifiers":[
        {
            "category":"Health Services",
            "subcategory":"Health Practitioner",
            "type":"Services"
        }
    ],
    "sg:phone":"+1 919 599 0536",
    "sg:postcode":"27612",
    "sg:province":"NC",
    "sg:tags":[
        "psychologist"
    ],
    "wof:name":"David G Kravetz PHD",
    "wof:placetype":"venue"
},
  "geometry": {"coordinates":[-78.711494,35.854491],"type":"Point"}
}