{
  "type": "Feature",
  "properties": {
    "addr:full":"3120 New Hope Rd Raleigh NC 27604",
    "addr:housenumber":"3120",
    "addr:postcode":"27604",
    "addr:street":"New Hope Rd",
    "iso:country":"US",
    "sg:address":"3120 New Hope Rd",
    "sg:city":"Raleigh",
    "sg:classifiers":[
        {
            "category":"Organizations",
            "subcategory":"Religious Organization",
            "type":"Services"
        }
    ],
    "sg:phone":"+1   ",
    "sg:postcode":"27604",
    "sg:province":"NC",
    "sg:website":"www.trinitypresbyterianchurch.net",
    "wof:name":"Trinity Presbyterian Church",
    "wof:placetype":"venue"
},
  "geometry": {"coordinates":[-78.569137,35.824101],"type":"Point"}
}