{
  "type": "Feature",
  "properties": {
    "addr:full":"32 W 1st St Lexington NC 27292",
    "addr:housenumber":"32",
    "addr:postcode":"27292",
    "addr:street":"W 1St St",
    "iso:country":"US",
    "sg:address":"32 W 1st St",
    "sg:city":"Lexington",
    "sg:classifiers":[
        {
            "category":"Personal",
            "subcategory":"Beauty Salon",
            "type":"Services"
        }
    ],
    "sg:phone":"+1   ",
    "sg:postcode":"27292",
    "sg:province":"NC",
    "sg:tags":[
        "shop"
    ],
    "wof:name":"Ivorys House of Styles",
    "wof:placetype":"venue"
},
  "geometry": {"coordinates":[-80.25370700000001,35.825573],"type":"Point"}
}