{
  "type": "Feature",
  "properties": {
    "iso:country":"US",
    "sg:address":"2111 W Club Blvd",
    "sg:city":"Durham",
    "sg:classifiers":[
        {
            "category":"Retail",
            "subcategory":"Self-service Laundry",
            "type":"Services"
        }
    ],
    "sg:phone":"+1   ",
    "sg:postcode":"27705",
    "sg:province":"NC",
    "sg:tags":[
        "coin"
    ],
    "wof:name":"Page Coin",
    "wof:placetype":"venue"
},
  "geometry": {"coordinates":[-78.926599,36.017387],"type":"Point"}
}