{
  "type": "Feature",
  "properties": {
    "iso:country":"US",
    "sg:address":"4715 Brompton Dr",
    "sg:city":"Greensboro",
    "sg:classifiers":[
        {
            "category":"Manufacturing",
            "subcategory":"Printing",
            "type":"Manufacturing & Wholesale Goods"
        }
    ],
    "sg:phone":"+1 336 854 8825",
    "sg:postcode":"27407",
    "sg:province":"NC",
    "sg:tags":[
        "publishing",
        "periodical"
    ],
    "wof:name":"Your Voice",
    "wof:placetype":"venue"
},
  "geometry": {"coordinates":[-79.862658,36.072799],"type":"Point"}
}