{
  "type": "Feature",
  "properties": {
    "iso:country":"US",
    "sg:address":"101 E 5th St",
    "sg:city":"Washington",
    "sg:classifiers":[
        {
            "category":"Banks & Credit Unions",
            "subcategory":"Bank",
            "type":"Services"
        }
    ],
    "sg:phone":"+1 252 940 0036",
    "sg:postcode":"27889",
    "sg:province":"NC",
    "sg:tags":[
        "depository",
        "banking"
    ],
    "sg:website":"www.acecashexpress.com",
    "wof:name":"ACE Cash Express",
    "wof:placetype":"venue"
},
  "geometry": {"coordinates":[-77.05202,35.546576],"type":"Point"}
}