{
  "type": "Feature",
  "properties": {
    "iso:country":"US",
    "sg:address":"6750 Shallowford Rd",
    "sg:city":"Lewisville",
    "sg:classifiers":[
        {
            "category":"Personal",
            "subcategory":"Beauty Salon",
            "type":"Services"
        }
    ],
    "sg:phone":"+1 336 945 3345",
    "sg:postcode":"27023",
    "sg:province":"NC",
    "sg:tags":[
        "manicuring"
    ],
    "wof:name":"Eastcoast Tans",
    "wof:placetype":"venue"
},
  "geometry": {"coordinates":[-80.425827,36.094518],"type":"Point"}
}