{
  "type": "Feature",
  "properties": {
    "iso:country":"US",
    "sg:address":"3332 3rd Street Dr NW",
    "sg:city":"Hickory",
    "sg:classifiers":[
        {
            "category":"Professional",
            "type":"Services"
        }
    ],
    "sg:phone":"+1 828 461 1999",
    "sg:postcode":"28601",
    "sg:province":"NC",
    "wof:name":"Cobb & Lester Inc",
    "wof:placetype":"venue"
},
  "geometry": {"coordinates":[-81.33553000000001,35.778981],"type":"Point"}
}