{
  "type": "Feature",
  "properties": {
    "iso:country":"US",
    "sg:address":"1218 Raleigh Rd",
    "sg:city":"Chapel Hill",
    "sg:classifiers":[
        {
            "category":"Shopping",
            "subcategory":"Pharmacy",
            "type":"Retail Goods"
        }
    ],
    "sg:phone":"+1 919 968 3777",
    "sg:postcode":"27517",
    "sg:province":"NC",
    "sg:tags":[
        "photofinishing",
        "laboratory"
    ],
    "wof:name":"Eckerd",
    "wof:placetype":"venue"
},
  "geometry": {"coordinates":[-79.02870299999999,35.90899],"type":"Point"}
}