{
  "type": "Feature",
  "properties": {
    "addr:full":"201 Oakdale Ave Clayton NC 27520",
    "addr:housenumber":"201",
    "addr:postcode":"27520",
    "addr:street":"Oakdale Ave",
    "iso:country":"US",
    "sg:address":"201 Oakdale Ave",
    "sg:city":"Clayton",
    "sg:classifiers":[
        {
            "category":"Insurance",
            "subcategory":"Hazard Insurance",
            "type":"Services"
        }
    ],
    "sg:phone":"+1 919 553 5527",
    "sg:postcode":"27520",
    "sg:province":"NC",
    "sg:tags":[
        "carrier",
        "surety"
    ],
    "wof:name":"Racron Financial Service",
    "wof:placetype":"venue"
},
  "geometry": {"coordinates":[-78.44798299999999,35.658798],"type":"Point"}
}