{
  "type": "Feature",
  "properties": {
    "addr:full":"1628 State Hwy 22 S Ramseur NC 27316",
    "addr:housenumber":"1628",
    "addr:postcode":"27316",
    "addr:street":"State Hwy 22 S",
    "iso:country":"US",
    "sg:address":"1628 State Hwy 22 S",
    "sg:city":"Ramseur",
    "sg:classifiers":[
        {
            "category":"Retail",
            "subcategory":"Auto Repair",
            "type":"Services"
        }
    ],
    "sg:phone":"+1 336 824 2000",
    "sg:postcode":"27316",
    "sg:province":"NC",
    "sg:tags":[
        "repairing",
        "automobile",
        "general"
    ],
    "wof:name":"Mitchell's Auto Repair",
    "wof:placetype":"venue"
},
  "geometry": {"coordinates":[-79.629564,35.713887],"type":"Point"}
}