{
  "type": "Feature",
  "properties": {
    "iso:country":"US",
    "sg:address":"101 N McDowell St",
    "sg:city":"Charlotte",
    "sg:classifiers":[
        {
            "category":"Real Estate",
            "subcategory":"Real Estate Agent",
            "type":"Services"
        },
        {
            "category":"Real Estate",
            "subcategory":"Real Estate Operator",
            "type":"Services"
        }
    ],
    "sg:phone":"+1 704 333 0333",
    "sg:postcode":"28204",
    "sg:province":"NC",
    "sg:tags":[
        "building",
        "nonresidential"
    ],
    "wof:name":"S & E Properties",
    "wof:placetype":"venue"
},
  "geometry": {"coordinates":[-80.83391399999999,35.221154],"type":"Point"}
}