{
  "type": "Feature",
  "properties": {
    "iso:country":"US",
    "sg:address":"2708 Smokey Ridge Rd",
    "sg:city":"Raleigh",
    "sg:classifiers":[
        {
            "category":"Wholesale",
            "subcategory":"Auto Parts",
            "type":"Manufacturing & Wholesale Goods"
        }
    ],
    "sg:phone":"+1 919 848 1971",
    "sg:postcode":"27613",
    "sg:province":"NC",
    "wof:name":"B & S Equipment Co",
    "wof:placetype":"venue"
},
  "geometry": {"coordinates":[-78.68911199999999,35.894412],"type":"Point"}
}