{
  "type": "Feature",
  "properties": {
    "addr:full":"1414 Setter Ct Wilmington NC 28411",
    "addr:housenumber":"1414",
    "addr:postcode":"28411",
    "addr:street":"Setter Ct",
    "iso:country":"US",
    "sg:address":"1414 Setter Ct",
    "sg:city":"Wilmington",
    "sg:classifiers":[
        {
            "category":"Home & Garden",
            "subcategory":"Garden Supply",
            "type":"Retail Goods"
        }
    ],
    "sg:phone":"+1 910 791 1500",
    "sg:postcode":"28411",
    "sg:province":"NC",
    "sg:tags":[
        "sprinkler"
    ],
    "wof:name":"Star Lawn Svc",
    "wof:placetype":"venue"
},
  "geometry": {"coordinates":[-77.83407800000001,34.294852],"type":"Point"}
}