{
  "type": "Feature",
  "properties": {
    "iso:country":"US",
    "sg:address":"4807 Olympic Ln N",
    "sg:city":"Wilson",
    "sg:classifiers":[
        {
            "category":"Professional",
            "subcategory":"Business Services",
            "type":"Services"
        }
    ],
    "sg:phone":"+1 252 243 4183",
    "sg:postcode":"27893",
    "sg:province":"NC",
    "wof:name":"Mark A Driver",
    "wof:placetype":"venue"
},
  "geometry": {"coordinates":[-77.948532,35.782666],"type":"Point"}
}