{
  "type": "Feature",
  "properties": {
    "addr:full":"807 N Queen St Kinston NC 28501",
    "addr:housenumber":"807",
    "addr:postcode":"28501",
    "addr:street":"N Queen St",
    "iso:country":"US",
    "sg:address":"807 N Queen St",
    "sg:city":"Kinston",
    "sg:classifiers":[
        {
            "category":"Professional",
            "subcategory":"Lawyer & Legal Services",
            "type":"Services"
        }
    ],
    "sg:phone":"+1 252 523 3100",
    "sg:postcode":"28501",
    "sg:province":"NC",
    "sg:tags":[
        "attorney"
    ],
    "wof:name":"Nicholas E Harvey",
    "wof:placetype":"venue"
},
  "geometry": {"coordinates":[-77.580816,35.269501],"type":"Point"}
}