{
  "type": "Feature",
  "properties": {
    "addr:full":"2965 Little Kelly Rd Rocky Point NC 28457",
    "addr:housenumber":"2965",
    "addr:postcode":"28457",
    "addr:street":"Little Kelly Rd",
    "iso:country":"US",
    "sg:address":"2965 Little Kelly Rd",
    "sg:city":"Rocky Point",
    "sg:classifiers":[
        {
            "category":"Organizations",
            "subcategory":"Religious Organization",
            "type":"Services"
        }
    ],
    "sg:phone":"+1 910 259 7747",
    "sg:postcode":"28457",
    "sg:province":"NC",
    "sg:tags":[
        "church"
    ],
    "wof:name":"Antioch United Holy Church",
    "wof:placetype":"venue"
},
  "geometry": {"coordinates":[-77.952088,34.459968],"type":"Point"}
}