{
  "type": "Feature",
  "properties": {
    "addr:full":"1461 Country Meadow Ln Kernersville NC 27284",
    "addr:housenumber":"1461",
    "addr:postcode":"27284",
    "addr:street":"Country Meadow Ln",
    "iso:country":"US",
    "sg:address":"1461 Country Meadow Ln",
    "sg:city":"Kernersville",
    "sg:classifiers":[
        {
            "category":"Museum",
            "type":"Entertainment"
        }
    ],
    "sg:phone":"+1   ",
    "sg:postcode":"27284",
    "sg:province":"NC",
    "sg:tags":[
        "gallery"
    ],
    "wof:name":"Golden Lace",
    "wof:placetype":"venue"
},
  "geometry": {"coordinates":[-80.111366,36.091541],"type":"Point"}
}