{
  "type": "Feature",
  "properties": {
    "addr:full":"223 Gilbert Rd Mocksville NC 27028",
    "addr:housenumber":"223",
    "addr:postcode":"27028",
    "addr:street":"Gilbert Rd",
    "iso:country":"US",
    "sg:address":"223 Gilbert Rd",
    "sg:city":"Mocksville",
    "sg:classifiers":[
        {
            "category":"Food & Beverages",
            "subcategory":"Specialty",
            "type":"Retail Goods"
        }
    ],
    "sg:phone":"+1 336 940 5210",
    "sg:postcode":"27028",
    "sg:province":"NC",
    "sg:tags":[
        "health",
        "diet"
    ],
    "wof:name":"Shaklee Products Distrubtor",
    "wof:placetype":"venue"
},
  "geometry": {"coordinates":[-80.514017,35.985399],"type":"Point"}
}