{
  "type": "Feature",
  "properties": {
    "addr:full":"1420 Athens Dr Raleigh NC 27606",
    "addr:housenumber":"1420",
    "addr:postcode":"27606",
    "addr:street":"Athens Dr",
    "iso:country":"US",
    "sg:address":"1420 Athens Dr",
    "sg:city":"Raleigh",
    "sg:classifiers":[
        {
            "category":"Education",
            "subcategory":"School",
            "type":"Public Place"
        }
    ],
    "sg:phone":"+1 919 233 4050",
    "sg:postcode":"27606",
    "sg:province":"NC",
    "sg:tags":[
        "high",
        "middle"
    ],
    "sg:website":"schools.wcpss.net/athensdrive-hs",
    "wof:name":"Wake County Public School System",
    "wof:placetype":"venue"
},
  "geometry": {"coordinates":[-78.710999,35.769901],"type":"Point"}
}