{
  "type": "Feature",
  "properties": {
    "iso:country":"US",
    "sg:address":"128 8th Ave",
    "sg:city":"Cramerton",
    "sg:classifiers":[
        {
            "category":"Retail",
            "subcategory":"Repair Shop",
            "type":"Services"
        }
    ],
    "sg:phone":"+1 704 824 2131",
    "sg:postcode":"28032",
    "sg:province":"NC",
    "sg:tags":[
        "appliance"
    ],
    "wof:name":"Tim's Appliance Svc",
    "wof:placetype":"venue"
},
  "geometry": {"coordinates":[-81.073318,35.23399],"type":"Point"}
}