{
  "type": "Feature",
  "properties": {
    "addr:full":"8 Sandpiper St Wrightsville Beach NC 28480",
    "addr:housenumber":"8",
    "addr:postcode":"28480",
    "addr:street":"Sandpiper St",
    "iso:country":"US",
    "sg:address":"8 Sandpiper St",
    "sg:city":"Wrightsville Beach",
    "sg:classifiers":[
        {
            "category":"Professional",
            "type":"Services"
        }
    ],
    "sg:phone":"+1   ",
    "sg:postcode":"28480",
    "sg:province":"NC",
    "wof:name":"Professional Corporate Service",
    "wof:placetype":"venue"
},
  "geometry": {"coordinates":[-77.787851,34.216318],"type":"Point"}
}