{
  "type": "Feature",
  "properties": {
    "addr:full":"511 Piedmont Ave Shelby NC 28150",
    "addr:housenumber":"511",
    "addr:postcode":"28150",
    "addr:street":"Piedmont Ave",
    "iso:country":"US",
    "sg:address":"511 Piedmont Ave",
    "sg:city":"Shelby",
    "sg:classifiers":[
        {
            "category":"Building & Trades",
            "subcategory":"Construction",
            "type":"Services"
        }
    ],
    "sg:phone":"+1 704 482 4569",
    "sg:postcode":"28150",
    "sg:province":"NC",
    "wof:name":"Ceramic Tile & Marble",
    "wof:placetype":"venue"
},
  "geometry": {"coordinates":[-81.52961500000001,35.31008],"type":"Point"}
}