{
  "type": "Feature",
  "properties": {
    "addr:full":"706 S Main St King NC 27021",
    "addr:housenumber":"706",
    "addr:postcode":"27021",
    "addr:street":"S Main St",
    "iso:country":"US",
    "sg:address":"706 S Main St",
    "sg:city":"King",
    "sg:classifiers":[
        {
            "category":"Restaurant",
            "type":"Food & Drink"
        }
    ],
    "sg:menulink":"http://www.allmenus.com/nc/yadkin/183376-kfc---kentucky-fried-chicken/menu/",
    "sg:phone":"+1 336 983 6706",
    "sg:postcode":"27021",
    "sg:province":"NC",
    "sg:tags":[
        "american",
        "chicken"
    ],
    "wof:name":"KFC - Kentucky Fried Chicken",
    "wof:placetype":"venue"
},
  "geometry": {"coordinates":[-80.361126,36.265345],"type":"Point"}
}