{
  "type": "Feature",
  "properties": {
    "addr:full":"46 Commons Way Cashiers NC 28786",
    "addr:housenumber":"46",
    "addr:postcode":"28786",
    "addr:street":"Commons Way",
    "iso:country":"US",
    "sg:address":"46 Commons Way",
    "sg:city":"Cashiers",
    "sg:classifiers":[
        {
            "category":"Shopping",
            "subcategory":"Used Merchandise",
            "type":"Retail Goods"
        }
    ],
    "sg:phone":"+1 828 743 6728",
    "sg:postcode":"28786",
    "sg:province":"NC",
    "sg:tags":[
        "antique"
    ],
    "sg:website":"www.cottagewalk.com",
    "wof:name":"Cottage Walk",
    "wof:placetype":"venue"
},
  "geometry": {"coordinates":[-82.95426500000001,35.519787],"type":"Point"}
}