{
  "type": "Feature",
  "properties": {
    "addr:full":"3007 Mills Harris Rd Marshville NC 28103",
    "addr:housenumber":"3007",
    "addr:postcode":"28103",
    "addr:street":"Mills Harris Rd",
    "iso:country":"US",
    "sg:address":"3007 Mills Harris Rd",
    "sg:city":"Marshville",
    "sg:classifiers":[
        {
            "category":"Farming",
            "subcategory":"Livestock Farm",
            "type":"Manufacturing & Wholesale Goods"
        }
    ],
    "sg:phone":"+1 704 233 4651",
    "sg:postcode":"28103",
    "sg:province":"NC",
    "sg:tags":[
        "chicken",
        "beef",
        "feedlot",
        "cattle"
    ],
    "wof:name":"Broome Olin",
    "wof:placetype":"venue"
},
  "geometry": {"coordinates":[-80.412082,35.062203],"type":"Point"}
}