{
  "type": "Feature",
  "properties": {
    "addr:full":"610 Rockingham Sq Madison NC 27025",
    "addr:housenumber":"610",
    "addr:postcode":"27025",
    "addr:street":"Rockingham Sq",
    "iso:country":"US",
    "sg:address":"610 Rockingham Sq",
    "sg:city":"Madison",
    "sg:classifiers":[
        {
            "category":"Shopping",
            "subcategory":"Department Store",
            "type":"Retail Goods"
        }
    ],
    "sg:phone":"+1 336 427 4966",
    "sg:postcode":"27025",
    "sg:province":"NC",
    "wof:name":"Sears Roebuck & Co Lawn & Gdn",
    "wof:placetype":"venue"
},
  "geometry": {"coordinates":[-79.972719,36.39463],"type":"Point"}
}