{
  "type": "Feature",
  "properties": {
    "addr:full":"1455 Hoke Loop Rd Fayetteville NC 28314",
    "addr:housenumber":"1455",
    "addr:postcode":"28314",
    "addr:street":"Hoke Loop Rd",
    "iso:country":"US",
    "sg:address":"1455 Hoke Loop Rd",
    "sg:city":"Fayetteville",
    "sg:classifiers":[
        {
            "category":"Recreation",
            "type":"Entertainment"
        }
    ],
    "sg:phone":"+1 910 867 1147",
    "sg:postcode":"28314",
    "sg:province":"NC",
    "sg:tags":[
        "center"
    ],
    "wof:name":"Cumberland Cnty Lake Rim Rec",
    "wof:placetype":"venue"
},
  "geometry": {"coordinates":[-79.076403,35.050763],"type":"Point"}
}