{
  "type": "Feature",
  "properties": {
    "addr:full":"239 Armory Rd North Wilkesboro NC 28659",
    "addr:housenumber":"239",
    "addr:postcode":"28659",
    "addr:street":"Armory Rd",
    "iso:country":"US",
    "sg:address":"239 Armory Rd",
    "sg:city":"North Wilkesboro",
    "sg:classifiers":[
        {
            "category":"Freight",
            "type":"Transportation"
        }
    ],
    "sg:phone":"+1 336 667 6240",
    "sg:postcode":"28659",
    "sg:province":"NC",
    "sg:tags":[
        "delivery"
    ],
    "wof:name":"Beavex USA",
    "wof:placetype":"venue"
},
  "geometry": {"coordinates":[-81.124343,36.165169],"type":"Point"}
}