{
  "type": "Feature",
  "properties": {
    "iso:country":"US",
    "sg:address":"131 Windy Hills Dr",
    "sg:city":"Wilmington",
    "sg:classifiers":[
        {
            "category":"Professional",
            "type":"Services"
        }
    ],
    "sg:phone":"+1 910 791 0067",
    "sg:postcode":"28409",
    "sg:province":"NC",
    "wof:name":"Caap LLC",
    "wof:placetype":"venue"
},
  "geometry": {"coordinates":[-77.877802,34.122208],"type":"Point"}
}