{
  "type": "Feature",
  "properties": {
    "addr:full":"100 Latta Rd Durham NC 27712",
    "addr:housenumber":"100",
    "addr:postcode":"27712",
    "addr:street":"Latta Rd",
    "iso:country":"US",
    "sg:address":"100 Latta Rd",
    "sg:city":"Durham",
    "sg:classifiers":[
        {
            "category":"Autos & Motor Vehicles",
            "subcategory":"Fuel & Gas Station",
            "type":"Retail Goods"
        }
    ],
    "sg:phone":"+1 919 477 0666",
    "sg:postcode":"27712",
    "sg:province":"NC",
    "sg:tags":[
        "station",
        "gasoline"
    ],
    "wof:name":"Cruisers",
    "wof:placetype":"venue"
},
  "geometry": {"coordinates":[-78.91620399999999,36.077704],"type":"Point"}
}