{
  "type": "Feature",
  "properties": {
    "iso:country":"US",
    "sg:address":"208 W Salisbury St",
    "sg:city":"Asheboro",
    "sg:classifiers":[
        {
            "category":"Personal",
            "subcategory":"Beauty Salon",
            "type":"Services"
        }
    ],
    "sg:phone":"+1 336 626 5092",
    "sg:postcode":"27203",
    "sg:province":"NC",
    "wof:name":"1212 Salon",
    "wof:placetype":"venue"
},
  "geometry": {"coordinates":[-79.81628499999999,35.708193],"type":"Point"}
}