{
  "type": "Feature",
  "properties": {
    "iso:country":"US",
    "sg:address":"1247 N Brightleaf Blvd",
    "sg:city":"Smithfield",
    "sg:classifiers":[
        {
            "category":"Building & Trades",
            "subcategory":"Plumbing",
            "type":"Services"
        }
    ],
    "sg:phone":"+1 919 989 8898",
    "sg:postcode":"27577",
    "sg:province":"NC",
    "sg:tags":[
        "conditioning",
        "air",
        "system",
        "contractor"
    ],
    "wof:name":"Partners In Comfort",
    "wof:placetype":"venue"
},
  "geometry": {"coordinates":[-78.314015,35.519148],"type":"Point"}
}