{
  "type": "Feature",
  "properties": {
    "iso:country":"US",
    "sg:address":"1225 Streets Ferry Rd",
    "sg:city":"Vanceboro",
    "sg:classifiers":[
        {
            "category":"Building & Trades",
            "subcategory":"Landscaping Services",
            "type":"Services"
        }
    ],
    "sg:phone":"+1 252 244 0367",
    "sg:postcode":"28586",
    "sg:province":"NC",
    "sg:tags":[
        "landscape"
    ],
    "wof:name":"Floyd A Smith Trucking",
    "wof:placetype":"venue"
},
  "geometry": {"coordinates":[-77.15102,35.271217],"type":"Point"}
}