{
  "type": "Feature",
  "properties": {
    "addr:full":"3910 Providance Rd Charlotte NC 28211",
    "addr:housenumber":"3910",
    "addr:postcode":"28211",
    "addr:street":"Providance Rd",
    "iso:country":"US",
    "sg:address":"3910 Providance Rd",
    "sg:city":"Charlotte",
    "sg:phone":"+1 704 907 3995",
    "sg:postcode":"28211",
    "sg:province":"NC",
    "sg:website":"http://www.allcitytransportation.com",
    "wof:name":"taxi service charlotte",
    "wof:placetype":"venue"
},
  "geometry": {"coordinates":[-80.79910099999999,35.158826],"type":"Point"}
}