{
  "type": "Feature",
  "properties": {
    "iso:country":"US",
    "sg:address":"4602 Odessa Pl",
    "sg:city":"Monroe",
    "sg:classifiers":[
        {
            "category":"Building & Trades",
            "subcategory":"Construction",
            "type":"Services"
        }
    ],
    "sg:phone":"+1 704 283 0056",
    "sg:postcode":"28110",
    "sg:province":"NC",
    "sg:tags":[
        "contractor"
    ],
    "wof:name":"Meade Custom Contracting",
    "wof:placetype":"venue"
},
  "geometry": {"coordinates":[-80.643432,35.0279],"type":"Point"}
}