{
  "type": "Feature",
  "properties": {
    "addr:full":"518 Pleasant Dr Durham NC 27703",
    "addr:housenumber":"518",
    "addr:postcode":"27703",
    "addr:street":"Pleasant Dr",
    "iso:country":"US",
    "sg:address":"518 Pleasant Dr",
    "sg:city":"Durham",
    "sg:classifiers":[
        {
            "category":"Professional",
            "subcategory":"Employment Agencies",
            "type":"Services"
        }
    ],
    "sg:phone":"+1   ",
    "sg:postcode":"27703",
    "sg:province":"NC",
    "wof:name":"Carolina Healthcare Network",
    "wof:placetype":"venue"
},
  "geometry": {"coordinates":[-78.849513,35.965669],"type":"Point"}
}