{
  "type": "Feature",
  "properties": {
    "addr:full":"19 Trinity Dr Lumberton NC 28358",
    "addr:housenumber":"19",
    "addr:postcode":"28358",
    "addr:street":"Trinity Dr",
    "iso:country":"US",
    "sg:address":"19 Trinity Dr",
    "sg:city":"Lumberton",
    "sg:classifiers":[
        {
            "category":"Professional",
            "subcategory":"Management & Consulting",
            "type":"Services"
        }
    ],
    "sg:phone":"+1   ",
    "sg:postcode":"28358",
    "sg:province":"NC",
    "sg:tags":[
        "business"
    ],
    "wof:name":"Red Drum Operations LLC",
    "wof:placetype":"venue"
},
  "geometry": {"coordinates":[-78.994545,34.667859],"type":"Point"}
}