{
  "type": "Feature",
  "properties": {
    "iso:country":"US",
    "sg:address":"30 Princess St",
    "sg:city":"Wilmington",
    "sg:classifiers":[
        {
            "category":"Arts & Performance",
            "subcategory":"Theater",
            "type":"Entertainment"
        }
    ],
    "sg:phone":"+1 910 254 2072",
    "sg:postcode":"28401",
    "sg:province":"NC",
    "sg:tags":[
        "entertainer"
    ],
    "wof:name":"Cape Fear Entertainers",
    "wof:placetype":"venue"
},
  "geometry": {"coordinates":[-77.949135,34.236352],"type":"Point"}
}