{
  "type": "Feature",
  "properties": {
    "iso:country":"US",
    "sg:address":"183 Branch Rd",
    "sg:city":"Leicester",
    "sg:classifiers":[
        {
            "category":"Professional",
            "type":"Services"
        }
    ],
    "sg:phone":"+1 828 683 4817",
    "sg:postcode":"28777",
    "sg:province":"NC",
    "wof:name":"Annies Place LLC",
    "wof:placetype":"venue"
},
  "geometry": {"coordinates":[-82.03512499999999,35.876151],"type":"Point"}
}