{
  "type": "Feature",
  "properties": {
    "addr:full":"12205 Longmont Dr Charlotte NC 28277",
    "addr:housenumber":"12205",
    "addr:postcode":"28277",
    "addr:street":"Longmont Dr",
    "iso:country":"US",
    "sg:address":"12205 Longmont Dr",
    "sg:city":"Charlotte",
    "sg:classifiers":[
        {
            "category":"Professional",
            "subcategory":"Employment Agencies",
            "type":"Services"
        }
    ],
    "sg:phone":"+1   ",
    "sg:postcode":"28277",
    "sg:province":"NC",
    "wof:name":"Southeast Search Consultants",
    "wof:placetype":"venue"
},
  "geometry": {"coordinates":[-80.799167,35.037188],"type":"Point"}
}