{
  "type": "Feature",
  "properties": {
    "iso:country":"US",
    "sg:address":"1976 Old Plank Rd",
    "sg:city":"Sophia",
    "sg:classifiers":[
        {
            "category":"Wholesale",
            "subcategory":"Construction Materials",
            "type":"Manufacturing & Wholesale Goods"
        }
    ],
    "sg:phone":"+1 336 498 1250",
    "sg:postcode":"27350",
    "sg:province":"NC",
    "sg:tags":[
        "lumber"
    ],
    "wof:name":"Raymond Wall Lumber Co",
    "wof:placetype":"venue"
},
  "geometry": {"coordinates":[-79.860592,35.827057],"type":"Point"}
}