{
  "type": "Feature",
  "properties": {
    "iso:country":"US",
    "sg:address":"45 Monroe Ln",
    "sg:city":"White Oak",
    "sg:classifiers":[
        {
            "category":"Autos & Motor Vehicles",
            "subcategory":"Automobile Sales",
            "type":"Retail Goods"
        }
    ],
    "sg:phone":"+1 910 866 4219",
    "sg:postcode":"28374",
    "sg:province":"NC",
    "sg:tags":[
        "car",
        "dealer"
    ],
    "wof:name":"Pleasant Oaks Auto Sales",
    "wof:placetype":"venue"
},
  "geometry": {"coordinates":[-79.457465,35.218155],"type":"Point"}
}