{
  "type": "Feature",
  "properties": {
    "addr:full":"4114 Ashmore Dr Greensboro NC 27405",
    "addr:housenumber":"4114",
    "addr:postcode":"27405",
    "addr:street":"Ashmore Dr",
    "iso:country":"US",
    "sg:address":"4114 Ashmore Dr",
    "sg:city":"Greensboro",
    "sg:classifiers":[
        {
            "category":"Personal",
            "subcategory":"Beauty Salon",
            "type":"Services"
        }
    ],
    "sg:phone":"+1   ",
    "sg:postcode":"27405",
    "sg:province":"NC",
    "sg:tags":[
        "shop"
    ],
    "wof:name":"Barbaras Hair Designs",
    "wof:placetype":"venue"
},
  "geometry": {"coordinates":[-79.73628100000001,36.097957],"type":"Point"}
}