{
  "type": "Feature",
  "properties": {
    "iso:country":"US",
    "sg:address":"2826 Kendale Dr",
    "sg:city":"Sanford",
    "sg:classifiers":[
        {
            "category":"Arena",
            "subcategory":"Sports Club",
            "type":"Entertainment"
        }
    ],
    "sg:phone":"+1   ",
    "sg:postcode":"27332",
    "sg:province":"NC",
    "wof:name":"Juventud Soccer Team",
    "wof:placetype":"venue"
},
  "geometry": {"coordinates":[-79.158328,35.445815],"type":"Point"}
}