{
  "type": "Feature",
  "properties": {
    "iso:country":"US",
    "sg:address":"1 Dundee St",
    "sg:city":"Asheville",
    "sg:classifiers":[
        {
            "category":"Organizations",
            "subcategory":"Religious Organization",
            "type":"Services"
        }
    ],
    "sg:phone":"+1 828 254 4884",
    "sg:postcode":"28801",
    "sg:province":"NC",
    "wof:name":"Christians For A United Comm",
    "wof:placetype":"venue"
},
  "geometry": {"coordinates":[-82.54733299999999,35.591236],"type":"Point"}
}