{
  "type": "Feature",
  "properties": {
    "addr:full":"4234 Providence Rd Charlotte NC 28211",
    "addr:housenumber":"4234",
    "addr:postcode":"28211",
    "addr:street":"Providence Rd",
    "iso:country":"US",
    "sg:address":"4234 Providence Rd",
    "sg:city":"Charlotte",
    "sg:classifiers":[
        {
            "category":"Food & Beverages",
            "subcategory":"Groceries & Convenience Stores",
            "type":"Retail Goods"
        }
    ],
    "sg:phone":"+1 704 366 4776",
    "sg:postcode":"28211",
    "sg:province":"NC",
    "wof:name":"Circle K Store",
    "wof:placetype":"venue"
},
  "geometry": {"coordinates":[-80.79652400000001,35.1563],"type":"Point"}
}