{
  "type": "Feature",
  "properties": {
    "addr:full":"7158 Free Union Church Rd Pinetown NC 27808",
    "addr:housenumber":"7158",
    "addr:postcode":"27808",
    "addr:street":"Free Union Church Rd",
    "iso:country":"US",
    "sg:address":"7158 Free Union Church Rd",
    "sg:city":"Pinetown",
    "sg:classifiers":[
        {
            "category":"Building & Trades",
            "subcategory":"Construction",
            "type":"Services"
        }
    ],
    "sg:phone":"+1 252 943 3700",
    "sg:postcode":"27808",
    "sg:province":"NC",
    "sg:tags":[
        "house"
    ],
    "wof:name":"Keechs Construction Inc",
    "wof:placetype":"venue"
},
  "geometry": {"coordinates":[-76.75730900000001,35.541276],"type":"Point"}
}