{
  "type": "Feature",
  "properties": {
    "addr:full":"131 Lattner Ct Morrisville NC 27560",
    "addr:housenumber":"131",
    "addr:postcode":"27560",
    "addr:street":"Lattner Ct",
    "iso:country":"US",
    "sg:address":"131 Lattner Ct",
    "sg:city":"Morrisville",
    "sg:classifiers":[
        {
            "category":"Social Services",
            "subcategory":"Child Care",
            "type":"Services"
        }
    ],
    "sg:phone":"+1 919 468 8880",
    "sg:postcode":"27560",
    "sg:province":"NC",
    "sg:tags":[
        "elementary",
        "kindergarten",
        "school",
        "academic"
    ],
    "wof:name":"Primrose Schools",
    "wof:placetype":"venue"
},
  "geometry": {"coordinates":[-78.852699,35.831001],"type":"Point"}
}