{
  "type": "Feature",
  "properties": {
    "addr:full":"317 S Church St Charlotte NC 28202",
    "addr:housenumber":"317",
    "addr:postcode":"28202",
    "addr:street":"S Church St",
    "iso:country":"US",
    "sg:address":"317 S Church St",
    "sg:city":"Charlotte",
    "sg:classifiers":[
        {
            "category":"Restaurant",
            "type":"Food & Drink"
        }
    ],
    "sg:phone":"+1 704 332 6375",
    "sg:postcode":"28202",
    "sg:province":"NC",
    "sg:tags":[
        "delicatessen"
    ],
    "wof:name":"Roly Poly Uptown Charlotte",
    "wof:placetype":"venue"
},
  "geometry": {"coordinates":[-80.846807,35.226209],"type":"Point"}
}