{
  "type": "Feature",
  "properties": {
    "addr:full":"226 N Main St Hendersonville NC 28792",
    "addr:housenumber":"226",
    "addr:postcode":"28792",
    "addr:street":"N Main St",
    "iso:country":"US",
    "sg:address":"226 N Main St",
    "sg:city":"Hendersonville",
    "sg:classifiers":[
        {
            "category":"Home & Garden",
            "subcategory":"Furniture",
            "type":"Retail Goods"
        }
    ],
    "sg:phone":"+1 828 693 5463",
    "sg:postcode":"28792",
    "sg:province":"NC",
    "sg:tags":[
        "used",
        "merchandise"
    ],
    "wof:name":"Kalins Furniture Inc",
    "wof:placetype":"venue"
},
  "geometry": {"coordinates":[-82.459914,35.315612],"type":"Point"}
}