{
  "type": "Feature",
  "properties": {
    "addr:full":"2421 South Blvd Charlotte NC 28203",
    "addr:housenumber":"2421",
    "addr:postcode":"28203",
    "addr:street":"South Blvd",
    "iso:country":"US",
    "sg:address":"2421 South Blvd",
    "sg:city":"Charlotte",
    "sg:classifiers":[
        {
            "category":"Retail",
            "subcategory":"Veterinary Services",
            "type":"Services"
        }
    ],
    "sg:phone":"+1 704 523 2996",
    "sg:postcode":"28203",
    "sg:province":"NC",
    "wof:name":"Long Animal Hospital",
    "wof:placetype":"venue"
},
  "geometry": {"coordinates":[-80.865081,35.202605],"type":"Point"}
}