{
  "type": "Feature",
  "properties": {
    "addr:full":"102 Ridgecreek Cir Trinity NC 27370",
    "addr:housenumber":"102",
    "addr:postcode":"27370",
    "addr:street":"Ridgecreek Cir",
    "iso:country":"US",
    "sg:address":"102 Ridgecreek Cir",
    "sg:city":"Trinity",
    "sg:classifiers":[
        {
            "category":"Insurance",
            "subcategory":"Insurance Agent",
            "type":"Services"
        }
    ],
    "sg:phone":"+1 336 431 1032",
    "sg:postcode":"27370",
    "sg:province":"NC",
    "wof:name":"Carter Insurance",
    "wof:placetype":"venue"
},
  "geometry": {"coordinates":[-79.940985,35.882257],"type":"Point"}
}