{
  "type": "Feature",
  "properties": {
    "addr:full":"4273 Long Beach Rd SE Southport NC 28461",
    "addr:housenumber":"4273",
    "addr:postcode":"28461",
    "addr:street":"Long Beach Rd Se",
    "iso:country":"US",
    "sg:address":"4273 Long Beach Rd SE",
    "sg:city":"Southport",
    "sg:classifiers":[
        {
            "category":"Home & Garden",
            "subcategory":"Building Materials",
            "type":"Retail Goods"
        }
    ],
    "sg:phone":"+1 910 457 1877",
    "sg:postcode":"28461",
    "sg:province":"NC",
    "sg:tags":[
        "lumber"
    ],
    "wof:name":"T Square Lumber Inc",
    "wof:placetype":"venue"
},
  "geometry": {"coordinates":[-78.06623,33.934544],"type":"Point"}
}