{
  "type": "Feature",
  "properties": {
    "addr:full":"108 S Commerce St Aulander NC 27805",
    "addr:housenumber":"108",
    "addr:postcode":"27805",
    "addr:street":"S Commerce St",
    "iso:country":"US",
    "sg:address":"108 S Commerce St",
    "sg:city":"Aulander",
    "sg:classifiers":[
        {
            "category":"Health Services",
            "subcategory":"Doctor",
            "type":"Services"
        }
    ],
    "sg:phone":"+1 252 345 3791",
    "sg:postcode":"27805",
    "sg:province":"NC",
    "sg:tags":[
        "physician",
        "surgeon"
    ],
    "wof:name":"Aulander Medical Practice",
    "wof:placetype":"venue"
},
  "geometry": {"coordinates":[-77.114177,36.229447],"type":"Point"}
}