{
  "type": "Feature",
  "properties": {
    "iso:country":"US",
    "sg:address":"2012 Foxbrook Dr",
    "sg:city":"Raleigh",
    "sg:classifiers":[
        {
            "category":"Professional",
            "type":"Services"
        }
    ],
    "sg:phone":"+1 919 773 9101",
    "sg:postcode":"27603",
    "sg:province":"NC",
    "wof:name":"Fluid Energy",
    "wof:placetype":"venue"
},
  "geometry": {"coordinates":[-78.710588,35.677927],"type":"Point"}
}