{
  "type": "Feature",
  "properties": {
    "iso:country":"US",
    "sg:address":"7343 W Friendly Ave",
    "sg:city":"Greensboro",
    "sg:classifiers":[
        {
            "category":"Professional",
            "subcategory":"Advertising",
            "type":"Services"
        }
    ],
    "sg:phone":"+1 336 299 3111",
    "sg:postcode":"27410",
    "sg:province":"NC",
    "sg:tags":[
        "mailing",
        "shipping"
    ],
    "wof:name":"Mail By Vera",
    "wof:placetype":"venue"
},
  "geometry": {"coordinates":[-79.922484,36.088393],"type":"Point"}
}