{
  "type": "Feature",
  "properties": {
    "iso:country":"US",
    "sg:address":"294 W Plaza Dr",
    "sg:city":"Mooresville",
    "sg:classifiers":[
        {
            "category":"Personal",
            "subcategory":"Beauty Salon",
            "type":"Services"
        }
    ],
    "sg:phone":"+1   ",
    "sg:postcode":"28117",
    "sg:province":"NC",
    "sg:tags":[
        "shop"
    ],
    "wof:name":"Pretty Nail",
    "wof:placetype":"venue"
},
  "geometry": {"coordinates":[-80.85029299999999,35.592138],"type":"Point"}
}