{
  "type": "Feature",
  "properties": {
    "iso:country":"US",
    "sg:address":"425 John M Ward Rd",
    "sg:city":"Lexington",
    "sg:classifiers":[
        {
            "category":"Manufacturing",
            "subcategory":"Furniture",
            "type":"Manufacturing & Wholesale Goods"
        }
    ],
    "sg:phone":"+1 336 249 4931",
    "sg:postcode":"27295",
    "sg:province":"NC",
    "sg:website":"www.wellingtonhalldesigns.com",
    "wof:name":"Wellington Hall Designs LLC",
    "wof:placetype":"venue"
},
  "geometry": {"coordinates":[-80.40027499999999,35.806428],"type":"Point"}
}