{
  "type": "Feature",
  "properties": {
    "iso:country":"US",
    "sg:address":"8009 Oak Arbor Rd",
    "sg:city":"Greensboro",
    "sg:classifiers":[
        {
            "category":"Retail",
            "subcategory":"Repair Shop",
            "type":"Services"
        }
    ],
    "sg:phone":"+1   ",
    "sg:postcode":"27455",
    "sg:province":"NC",
    "wof:name":"Copy Shop of Greensboro",
    "wof:placetype":"venue"
},
  "geometry": {"coordinates":[-79.774272,36.225644],"type":"Point"}
}