{
  "type": "Feature",
  "properties": {
    "iso:country":"US",
    "sg:address":"3020 Shangri la Dr",
    "sg:city":"Conover",
    "sg:classifiers":[
        {
            "category":"Building & Trades",
            "subcategory":"Construction",
            "type":"Services"
        }
    ],
    "sg:phone":"+1 828 464 6886",
    "sg:postcode":"28613",
    "sg:province":"NC",
    "sg:tags":[
        "contractor"
    ],
    "wof:name":"Elswick Waterproofing",
    "wof:placetype":"venue"
},
  "geometry": {"coordinates":[-81.15364599999999,35.688828],"type":"Point"}
}