{
  "type": "Feature",
  "properties": {
    "addr:full":"200 Lander St Charlotte NC 28208",
    "addr:housenumber":"200",
    "addr:postcode":"28208",
    "addr:street":"Lander St",
    "iso:country":"US",
    "sg:address":"200 Lander St",
    "sg:city":"Charlotte",
    "sg:classifiers":[
        {
            "category":"Organizations",
            "subcategory":"Religious Organization",
            "type":"Services"
        }
    ],
    "sg:phone":"+1 704 391 9956",
    "sg:postcode":"28208",
    "sg:province":"NC",
    "sg:tags":[
        "church"
    ],
    "wof:name":"Greater Deliverance",
    "wof:placetype":"venue"
},
  "geometry": {"coordinates":[-80.880106,35.256792],"type":"Point"}
}