{
  "type": "Feature",
  "properties": {
    "addr:full":"3800 Opportunity Ln Raleigh NC 27603",
    "addr:housenumber":"3800",
    "addr:postcode":"27603",
    "addr:street":"Opportunity Ln",
    "iso:country":"US",
    "sg:address":"3800 Opportunity Ln",
    "sg:city":"Raleigh",
    "sg:classifiers":[
        {
            "category":"Wholesale",
            "subcategory":"Machinery & Supplies",
            "type":"Manufacturing & Wholesale Goods"
        }
    ],
    "sg:phone":"+1 919 662 9886",
    "sg:postcode":"27603",
    "sg:province":"NC",
    "sg:tags":[
        "fire",
        "department",
        "equipment"
    ],
    "wof:name":"Lee Fire Equipment & Supplies",
    "wof:placetype":"venue"
},
  "geometry": {"coordinates":[-78.70723599999999,35.660671],"type":"Point"}
}