{
  "type": "Feature",
  "properties": {
    "iso:country":"US",
    "sg:address":"30 All Souls Cres",
    "sg:city":"Asheville",
    "sg:classifiers":[
        {
            "category":"Shopping",
            "subcategory":"Jewelry",
            "type":"Retail Goods"
        }
    ],
    "sg:phone":"+1 828 274 7007",
    "sg:postcode":"28803",
    "sg:province":"NC",
    "sg:tags":[
        "jeweler"
    ],
    "wof:name":"Estate Jewelry LTD",
    "wof:placetype":"venue"
},
  "geometry": {"coordinates":[-82.54322500000001,35.56506],"type":"Point"}
}