{
  "type": "Feature",
  "properties": {
    "addr:full":"44 Village Way Cashiers NC 28711",
    "addr:housenumber":"44",
    "addr:postcode":"28711",
    "addr:street":"Village Way",
    "iso:country":"US",
    "sg:address":"44 Village Way",
    "sg:city":"Cashiers",
    "sg:classifiers":[
        {
            "category":"Shopping",
            "subcategory":"Hobbies, Toys, & Games",
            "type":"Retail Goods"
        }
    ],
    "sg:phone":"+1 828 743 6267",
    "sg:postcode":"28711",
    "sg:province":"NC",
    "wof:name":"Corner Store",
    "wof:placetype":"venue"
},
  "geometry": {"coordinates":[-82.316198,35.621485],"type":"Point"}
}