{
  "type": "Feature",
  "properties": {
    "addr:full":"113 W Union St Morganton NC 28655",
    "addr:housenumber":"113",
    "addr:postcode":"28655",
    "addr:street":"W Union St",
    "iso:country":"US",
    "sg:address":"113 W Union St",
    "sg:city":"Morganton",
    "sg:classifiers":[
        {
            "category":"Organizations",
            "subcategory":"Religious Organization",
            "type":"Services"
        }
    ],
    "sg:phone":"+1 828 438 4673",
    "sg:postcode":"28655",
    "sg:province":"NC",
    "wof:name":"Nathan's Hope Ministries",
    "wof:placetype":"venue"
},
  "geometry": {"coordinates":[-81.68813,35.745428],"type":"Point"}
}