{
  "type": "Feature",
  "properties": {
    "iso:country":"US",
    "sg:address":"901 Smokey Park Hwy",
    "sg:city":"Candler",
    "sg:classifiers":[
        {
            "category":"Shopping",
            "subcategory":"Pharmacy",
            "type":"Retail Goods"
        }
    ],
    "sg:phone":"+1 828 667 0851",
    "sg:postcode":"28715",
    "sg:province":"NC",
    "wof:name":"Eckerd",
    "wof:placetype":"venue"
},
  "geometry": {"coordinates":[-82.65274599999999,35.5478],"type":"Point"}
}