{
  "type": "Feature",
  "properties": {
    "addr:full":"103 Lanier Valley Dr Durham NC 27703",
    "addr:housenumber":"103",
    "addr:postcode":"27703",
    "addr:street":"Lanier Valley Dr",
    "iso:country":"US",
    "sg:address":"103 Lanier Valley Dr",
    "sg:city":"Durham",
    "sg:classifiers":[
        {
            "category":"Travel",
            "subcategory":"Travel Agent",
            "type":"Entertainment"
        }
    ],
    "sg:phone":"+1 919 957 7538",
    "sg:postcode":"27703",
    "sg:province":"NC",
    "sg:tags":[
        "agency"
    ],
    "wof:name":"Kaieteur Travel",
    "wof:placetype":"venue"
},
  "geometry": {"coordinates":[-78.807829,35.984611],"type":"Point"}
}