{
  "type": "Feature",
  "properties": {
    "addr:full":"199 Forum Pkwy Rural Hall NC 27045",
    "addr:housenumber":"199",
    "addr:postcode":"27045",
    "addr:street":"Forum Pkwy Rural Hall",
    "iso:country":"US",
    "sg:address":"199 Forum Pkwy",
    "sg:city":"Rural Hall",
    "sg:classifiers":[
        {
            "category":"Building & Trades",
            "subcategory":"Electrical",
            "type":"Services"
        }
    ],
    "sg:phone":"+1 336 969 5122",
    "sg:postcode":"27045",
    "sg:province":"NC",
    "sg:tags":[
        "electric",
        "contractor"
    ],
    "wof:name":"L E Myers Co",
    "wof:placetype":"venue"
},
  "geometry": {"coordinates":[-80.290161,36.209839],"type":"Point"}
}