{
  "type": "Feature",
  "properties": {
    "addr:full":"204 Livengood Rd Advance NC 27006",
    "addr:housenumber":"204",
    "addr:postcode":"27006",
    "addr:street":"Livengood Rd",
    "iso:country":"US",
    "sg:address":"204 Livengood Rd",
    "sg:city":"Advance",
    "sg:classifiers":[
        {
            "category":"Building & Trades",
            "subcategory":"Construction",
            "type":"Services"
        }
    ],
    "sg:phone":"+1 336 998 5510",
    "sg:postcode":"27006",
    "sg:province":"NC",
    "sg:tags":[
        "water",
        "well",
        "drilling"
    ],
    "wof:name":"WEBB Well Drilling Inc",
    "wof:placetype":"venue"
},
  "geometry": {"coordinates":[-80.43704099999999,35.904442],"type":"Point"}
}