{
  "type": "Feature",
  "properties": {
    "iso:country":"US",
    "sg:address":"2250 Asheville Hwy",
    "sg:city":"Hendersonville",
    "sg:classifiers":[
        {
            "category":"Building & Trades",
            "subcategory":"Construction",
            "type":"Services"
        },
        {
            "category":"Retail",
            "subcategory":"Auto Repair",
            "type":"Services"
        }
    ],
    "sg:phone":"+1 828 232 0500",
    "sg:postcode":"28791",
    "sg:province":"NC",
    "sg:tags":[
        "glass",
        "coating",
        "tinting",
        "contractor"
    ],
    "wof:name":"Hendersonville Window Tinting",
    "wof:placetype":"venue"
},
  "geometry": {"coordinates":[-82.47462899999999,35.341707],"type":"Point"}
}