{
  "type": "Feature",
  "properties": {
    "addr:full":"701 Princess St Wilmington NC 28401",
    "addr:housenumber":"701",
    "addr:postcode":"28401",
    "addr:street":"Princess St",
    "iso:country":"US",
    "sg:address":"701 Princess St",
    "sg:city":"Wilmington",
    "sg:classifiers":[
        {
            "category":"Professional",
            "subcategory":"Lawyer & Legal Services",
            "type":"Services"
        }
    ],
    "sg:phone":"+1 910 343 1022",
    "sg:postcode":"28401",
    "sg:province":"NC",
    "sg:tags":[
        "attorney"
    ],
    "wof:name":"H Kenneth Stephens II",
    "wof:placetype":"venue"
},
  "geometry": {"coordinates":[-77.9395,34.237221],"type":"Point"}
}