{
  "type": "Feature",
  "properties": {
    "iso:country":"US",
    "sg:address":"4411 W Market St",
    "sg:city":"Greensboro",
    "sg:classifiers":[
        {
            "category":"Government",
            "subcategory":"Office",
            "type":"Public Place"
        }
    ],
    "sg:phone":"+1 336 854 9180",
    "sg:postcode":"27407",
    "sg:province":"NC",
    "sg:tags":[
        "housing",
        "program"
    ],
    "wof:name":"Mfg Housing Services LLC",
    "wof:placetype":"venue"
},
  "geometry": {"coordinates":[-79.85687,36.06911],"type":"Point"}
}