{
  "type": "Feature",
  "properties": {
    "addr:full":"5068 Main St South Brunswick NC 28470",
    "addr:housenumber":"5068",
    "addr:postcode":"28470",
    "addr:street":"Main St",
    "iso:country":"US",
    "sg:address":"5068 Main St",
    "sg:city":"South Brunswick",
    "sg:classifiers":[
        {
            "category":"Education",
            "subcategory":"Library",
            "type":"Public Place"
        }
    ],
    "sg:phone":"+1 910 754 6578",
    "sg:postcode":"28470",
    "sg:province":"NC",
    "wof:name":"Rourk Branch Library",
    "wof:placetype":"venue"
},
  "geometry": {"coordinates":[-78.392629,33.967654],"type":"Point"}
}