{
  "type": "Feature",
  "properties": {
    "iso:country":"US",
    "sg:address":"3922 Miami Church Rd",
    "sg:city":"Concord",
    "sg:classifiers":[
        {
            "category":"Retail",
            "subcategory":"Auto Repair",
            "type":"Services"
        }
    ],
    "sg:phone":"+1   ",
    "sg:postcode":"28025",
    "sg:province":"NC",
    "sg:tags":[
        "general"
    ],
    "wof:name":"Joyners Garage Door",
    "wof:placetype":"venue"
},
  "geometry": {"coordinates":[-80.50958,35.360133],"type":"Point"}
}