{
  "type": "Feature",
  "properties": {
    "iso:country":"US",
    "sg:address":"5309 Monroe Rd",
    "sg:city":"Charlotte",
    "sg:classifiers":[
        {
            "category":"Professional",
            "subcategory":"Accounting & Tax Preparation",
            "type":"Services"
        }
    ],
    "sg:phone":"+1 704 375 2715",
    "sg:postcode":"28205",
    "sg:province":"NC",
    "sg:tags":[
        "accountant"
    ],
    "sg:website":"www.carolinaaccounting.com",
    "wof:name":"Carolina Accounting & Tax Svc",
    "wof:placetype":"venue"
},
  "geometry": {"coordinates":[-80.77257400000001,35.189601],"type":"Point"}
}