{
  "type": "Feature",
  "properties": {
    "iso:country":"US",
    "sg:address":"234 Mount Gould River Rd",
    "sg:city":"Merry Hill",
    "sg:phone":"+1 252 356 2585",
    "sg:postcode":"27957",
    "sg:province":"NC",
    "sg:tags":[
        "farm",
        "peanut",
        "corn",
        "tobacco"
    ],
    "wof:name":"Richard Harrell",
    "wof:placetype":"venue"
},
  "geometry": {"coordinates":[-76.74525199999999,36.124233],"type":"Point"}
}