{
  "type": "Feature",
  "properties": {
    "iso:country":"US",
    "sg:address":"230 N 2nd Ave",
    "sg:city":"Siler City",
    "sg:classifiers":[
        {
            "category":"Retail",
            "subcategory":"Funeral Services",
            "type":"Services"
        }
    ],
    "sg:phone":"+1   ",
    "sg:postcode":"27344",
    "sg:province":"NC",
    "wof:name":"Smith & Buckner Funeral Home",
    "wof:placetype":"venue"
},
  "geometry": {"coordinates":[-79.46319,35.724996],"type":"Point"}
}