{
  "type": "Feature",
  "properties": {
    "addr:full":"5454 Roxboro Rd Durham NC 27712",
    "addr:housenumber":"5454",
    "addr:postcode":"27712",
    "addr:street":"Roxboro Rd",
    "iso:country":"US",
    "sg:address":"5454 Roxboro Rd",
    "sg:city":"Durham",
    "sg:classifiers":[
        {
            "category":"Building & Trades",
            "subcategory":"Construction",
            "type":"Services"
        }
    ],
    "sg:phone":"+1 919 477 9595",
    "sg:postcode":"27712",
    "sg:province":"NC",
    "sg:tags":[
        "heavy",
        "clearing",
        "land",
        "leveling"
    ],
    "wof:name":"Specialized Land Clearing LLC",
    "wof:placetype":"venue"
},
  "geometry": {"coordinates":[-78.91073299999999,36.088788],"type":"Point"}
}