{
  "type": "Feature",
  "properties": {
    "iso:country":"US",
    "sg:address":"100 Brewster Blvd",
    "sg:city":"Camp Lejeune",
    "sg:classifiers":[
        {
            "category":"Health Services",
            "subcategory":"Hospital",
            "type":"Services"
        }
    ],
    "sg:phone":"+1 910 451 1113",
    "sg:postcode":"28547",
    "sg:province":"NC",
    "sg:tags":[
        "hosp",
        "ex",
        "psychiatric",
        "government"
    ],
    "wof:name":"Naval Hospital",
    "wof:placetype":"venue"
},
  "geometry": {"coordinates":[-77.342568,34.717963],"type":"Point"}
}