{
  "type": "Feature",
  "properties": {
    "addr:full":"5623 Gallagher Dr Gastonia NC 28052",
    "addr:housenumber":"5623",
    "addr:postcode":"28052",
    "addr:street":"Gallagher Dr",
    "iso:country":"US",
    "sg:address":"5623 Gallagher Dr",
    "sg:city":"Gastonia",
    "sg:classifiers":[
        {
            "category":"Manufacturing",
            "subcategory":"Tools & Machinery",
            "type":"Manufacturing & Wholesale Goods"
        }
    ],
    "sg:phone":"+1 704 867 5880",
    "sg:postcode":"28052",
    "sg:province":"NC",
    "sg:tags":[
        "machine",
        "shop"
    ],
    "wof:name":"K B Parets Inc",
    "wof:placetype":"venue"
},
  "geometry": {"coordinates":[-81.212159,35.192587],"type":"Point"}
}