{
  "type": "Feature",
  "properties": {
    "iso:country":"US",
    "sg:address":"1312 Longleaf Dr",
    "sg:city":"Fayetteville",
    "sg:classifiers":[
        {
            "category":"Recreation",
            "type":"Entertainment"
        }
    ],
    "sg:phone":"+1   ",
    "sg:postcode":"28305",
    "sg:province":"NC",
    "wof:name":"Putt Putt Golf Courses",
    "wof:placetype":"venue"
},
  "geometry": {"coordinates":[-78.903637,35.041441],"type":"Point"}
}