{
  "type": "Feature",
  "properties": {
    "iso:country":"US",
    "sg:address":"789 Moye St",
    "sg:city":"Fremont",
    "sg:classifiers":[
        {
            "category":"Organizations",
            "subcategory":"Religious Organization",
            "type":"Services"
        }
    ],
    "sg:phone":"+1   ",
    "sg:postcode":"27830",
    "sg:province":"NC",
    "wof:name":"New Daniel Chapel",
    "wof:placetype":"venue"
},
  "geometry": {"coordinates":[-77.961423,35.552314],"type":"Point"}
}