{
  "type": "Feature",
  "properties": {
    "iso:country":"US",
    "sg:address":"300 S Salisbury Ave",
    "sg:city":"Spencer",
    "sg:classifiers":[
        {
            "category":"Food & Beverages",
            "subcategory":"Groceries & Convenience Stores",
            "type":"Retail Goods"
        }
    ],
    "sg:phone":"+1 704 637 5708",
    "sg:postcode":"28159",
    "sg:province":"NC",
    "wof:name":"Pantry Inc",
    "wof:placetype":"venue"
},
  "geometry": {"coordinates":[-80.433325,35.688894],"type":"Point"}
}