{
  "type": "Feature",
  "properties": {
    "iso:country":"US",
    "sg:address":"200 N Main St",
    "sg:city":"Holly Springs",
    "sg:classifiers":[
        {
            "category":"Shopping",
            "subcategory":"Gifts & Souvenirs",
            "type":"Retail Goods"
        }
    ],
    "sg:phone":"+1 919 577 1945",
    "sg:postcode":"27540",
    "sg:province":"NC",
    "wof:name":"Things Of Joy",
    "wof:placetype":"venue"
},
  "geometry": {"coordinates":[-78.83400899999999,35.654128],"type":"Point"}
}