{
  "type": "Feature",
  "properties": {
    "addr:full":"604 Willow Rd Hendersonville NC 28739",
    "addr:housenumber":"604",
    "addr:postcode":"28739",
    "addr:street":"Willow Rd",
    "iso:country":"US",
    "sg:address":"604 Willow Rd",
    "sg:city":"Hendersonville",
    "sg:classifiers":[
        {
            "category":"Retail",
            "subcategory":"Auto Repair",
            "type":"Services"
        }
    ],
    "sg:phone":"+1 828 696 0711",
    "sg:postcode":"28739",
    "sg:province":"NC",
    "sg:tags":[
        "truck"
    ],
    "wof:name":"T M Truck Repair & Maintenance",
    "wof:placetype":"venue"
},
  "geometry": {"coordinates":[-82.46376600000001,35.308568],"type":"Point"}
}