{
  "type": "Feature",
  "properties": {
    "iso:country":"US",
    "sg:address":"807 Jamestown Rd",
    "sg:city":"Morganton",
    "sg:classifiers":[
        {
            "category":"Freight",
            "type":"Transportation"
        }
    ],
    "sg:phone":"+1 828 584 6995",
    "sg:postcode":"28655",
    "sg:province":"NC",
    "sg:tags":[
        "operator",
        "local",
        "trucking"
    ],
    "wof:name":"Chatman Five Inc",
    "wof:placetype":"venue"
},
  "geometry": {"coordinates":[-81.741354,35.725513],"type":"Point"}
}