{
  "type": "Feature",
  "properties": {
    "addr:full":"235 Fulcher Landing Rd Sneads Ferry NC 28460",
    "addr:housenumber":"235",
    "addr:postcode":"28460",
    "addr:street":"Fulcher Landing Rd",
    "iso:country":"US",
    "sg:address":"235 Fulcher Landing Rd",
    "sg:city":"Sneads Ferry",
    "sg:classifiers":[
        {
            "category":"Personal",
            "subcategory":"Beauty Salon",
            "type":"Services"
        }
    ],
    "sg:phone":"+1 910 327 0039",
    "sg:postcode":"28460",
    "sg:province":"NC",
    "wof:name":"Creative Touch",
    "wof:placetype":"venue"
},
  "geometry": {"coordinates":[-77.38555599999999,34.5611],"type":"Point"}
}