{
  "type": "Feature",
  "properties": {
    "addr:full":"6326 Seton House Ln Charlotte NC 28277",
    "addr:housenumber":"6326",
    "addr:postcode":"28277",
    "addr:street":"Seton House Ln",
    "iso:country":"US",
    "sg:address":"6326 Seton House Ln",
    "sg:city":"Charlotte",
    "sg:classifiers":[
        {
            "category":"Professional",
            "type":"Services"
        }
    ],
    "sg:phone":"+1 704 844 2915",
    "sg:postcode":"28277",
    "sg:province":"NC",
    "wof:name":"Ingention Inc",
    "wof:placetype":"venue"
},
  "geometry": {"coordinates":[-80.806625,35.075074],"type":"Point"}
}