{
  "type": "Feature",
  "properties": {
    "iso:country":"US",
    "sg:address":"6908 State Hwy 305",
    "sg:city":"Jackson",
    "sg:classifiers":[
        {
            "category":"Farming",
            "subcategory":"Nursery",
            "type":"Manufacturing & Wholesale Goods"
        }
    ],
    "sg:phone":"+1 252 534 4141",
    "sg:postcode":"27845",
    "sg:province":"NC",
    "sg:tags":[
        "box",
        "american",
        "wood",
        "english",
        "root",
        "grow"
    ],
    "wof:name":"Kathryn Shrubs",
    "wof:placetype":"venue"
},
  "geometry": {"coordinates":[-77.364709,36.374818],"type":"Point"}
}