{
  "type": "Feature",
  "properties": {
    "iso:country":"US",
    "sg:address":"1129 Western Blvd",
    "sg:city":"Jacksonville",
    "sg:classifiers":[
        {
            "category":"Retail",
            "subcategory":"Auto Repair",
            "type":"Services"
        }
    ],
    "sg:phone":"+1 910 346 1582",
    "sg:postcode":"28546",
    "sg:province":"NC",
    "sg:tags":[
        "body",
        "automobile",
        "painting"
    ],
    "wof:name":"Dents Away Of Jacksonville Inc",
    "wof:placetype":"venue"
},
  "geometry": {"coordinates":[-77.395062,34.779509],"type":"Point"}
}