{
  "type": "Feature",
  "properties": {
    "addr:full":"1008 Mount Pleasant Church Rd Mooresboro SC 28114",
    "addr:housenumber":"1008",
    "addr:postcode":"28114",
    "addr:street":"Mount Pleasant Church Rd",
    "iso:country":"US",
    "sg:address":"1008 Mount Pleasant Church Rd",
    "sg:city":"Mooresboro",
    "sg:classifiers":[
        {
            "category":"Building & Trades",
            "subcategory":"Landscaping Services",
            "type":"Services"
        }
    ],
    "sg:phone":"+1 704 434 9096",
    "sg:postcode":"28114",
    "sg:province":"SC",
    "sg:tags":[
        "landscape"
    ],
    "wof:name":"GG Designs",
    "wof:placetype":"venue"
},
  "geometry": {"coordinates":[-81.716729,35.24602],"type":"Point"}
}