{
  "type": "Feature",
  "properties": {
    "iso:country":"US",
    "sg:address":"11611 Bain School Rd",
    "sg:city":"Mint Hill",
    "sg:classifiers":[
        {
            "category":"Building & Trades",
            "subcategory":"Construction",
            "type":"Services"
        }
    ],
    "sg:phone":"+1 704 545 1291",
    "sg:postcode":"28227",
    "sg:province":"NC",
    "sg:tags":[
        "tile",
        "dealer"
    ],
    "wof:name":"Acme Tile Co",
    "wof:placetype":"venue"
},
  "geometry": {"coordinates":[-80.64273300000001,35.168065],"type":"Point"}
}