{
  "type": "Feature",
  "properties": {
    "addr:full":"6412 Gumwood Rd Oak Ridge NC 27310",
    "addr:housenumber":"6412",
    "addr:postcode":"27310",
    "addr:street":"Gumwood Rd",
    "iso:country":"US",
    "sg:address":"6412 Gumwood Rd",
    "sg:city":"Oak Ridge",
    "sg:classifiers":[
        {
            "category":"Retail",
            "subcategory":"Repair Shop",
            "type":"Services"
        }
    ],
    "sg:phone":"+1   ",
    "sg:postcode":"27310",
    "sg:province":"NC",
    "wof:name":"Steve Varga Furniture Repari",
    "wof:placetype":"venue"
},
  "geometry": {"coordinates":[-79.958855,36.171261],"type":"Point"}
}