{
  "type": "Feature",
  "properties": {
    "addr:full":"3001 Barnsley Trl Raleigh NC 27604",
    "addr:housenumber":"3001",
    "addr:postcode":"27604",
    "addr:street":"Barnsley Trl",
    "iso:country":"US",
    "sg:address":"3001 Barnsley Trl",
    "sg:city":"Raleigh",
    "sg:classifiers":[
        {
            "category":"Wholesale",
            "subcategory":"Fruits & Vegetables",
            "type":"Manufacturing & Wholesale Goods"
        }
    ],
    "sg:phone":"+1 919 231 7546",
    "sg:postcode":"27604",
    "sg:province":"NC",
    "sg:tags":[
        "fresh"
    ],
    "wof:name":"Etheridge Gordon S",
    "wof:placetype":"venue"
},
  "geometry": {"coordinates":[-78.55052999999999,35.822434],"type":"Point"}
}