{
  "type": "Feature",
  "properties": {
    "iso:country":"US",
    "sg:address":"10320 Globe Rd",
    "sg:city":"Morrisville",
    "sg:classifiers":[
        {
            "category":"Freight",
            "type":"Transportation"
        }
    ],
    "sg:phone":"+1 919 821 1370",
    "sg:postcode":"27560",
    "sg:province":"NC",
    "sg:tags":[
        "mover"
    ],
    "sg:website":"www.lawrencetransportation.com",
    "wof:name":"Lawrence Transportation Systs",
    "wof:placetype":"venue"
},
  "geometry": {"coordinates":[-78.80059799999999,35.88961],"type":"Point"}
}