{
  "type": "Feature",
  "properties": {
    "addr:full":"4387 Baylor St Greensboro NC 27455",
    "addr:housenumber":"4387",
    "addr:postcode":"27455",
    "addr:street":"Baylor St",
    "iso:country":"US",
    "sg:address":"4387 Baylor St",
    "sg:city":"Greensboro",
    "sg:classifiers":[
        {
            "category":"Restaurant",
            "type":"Food & Drink"
        }
    ],
    "sg:phone":"+1 336 282 0774",
    "sg:postcode":"27455",
    "sg:province":"NC",
    "sg:tags":[
        "eating"
    ],
    "wof:name":"200 North Bistro",
    "wof:placetype":"venue"
},
  "geometry": {"coordinates":[-79.808217,36.135039],"type":"Point"}
}