{
  "type": "Feature",
  "properties": {
    "addr:full":"18 Brook St Asheville NC 28803",
    "addr:housenumber":"18",
    "addr:postcode":"28803",
    "addr:street":"Brook St",
    "iso:country":"US",
    "sg:address":"18 Brook St",
    "sg:city":"Asheville",
    "sg:classifiers":[
        {
            "category":"Shopping",
            "subcategory":"Pharmacy",
            "type":"Retail Goods"
        }
    ],
    "sg:phone":"+1 828 277 1205",
    "sg:postcode":"28803",
    "sg:province":"NC",
    "wof:name":"Turner & Co Apothecary",
    "wof:placetype":"venue"
},
  "geometry": {"coordinates":[-82.540829,35.566563],"type":"Point"}
}