{
  "type": "Feature",
  "properties": {
    "iso:country":"US",
    "sg:address":"3996 Williams Loop",
    "sg:city":"Drexel",
    "sg:classifiers":[
        {
            "category":"Real Estate",
            "subcategory":"Real Estate Operator",
            "type":"Services"
        }
    ],
    "sg:phone":"+1 828 433 6972",
    "sg:postcode":"28619",
    "sg:province":"NC",
    "sg:tags":[
        "mobile",
        "home",
        "community"
    ],
    "wof:name":"Ray C Anthony's Mobile Home",
    "wof:placetype":"venue"
},
  "geometry": {"coordinates":[-81.59195800000001,35.759792],"type":"Point"}
}