{
  "type": "Feature",
  "properties": {
    "iso:country":"US",
    "sg:address":"1610 Jordan Narron Rd",
    "sg:city":"Selma",
    "sg:classifiers":[
        {
            "category":"Farming",
            "subcategory":"Farm",
            "type":"Manufacturing & Wholesale Goods"
        }
    ],
    "sg:phone":"+1 919 965 4669",
    "sg:postcode":"27576",
    "sg:province":"NC",
    "sg:tags":[
        "crop",
        "general"
    ],
    "wof:name":"Maple Leaf Farm",
    "wof:placetype":"venue"
},
  "geometry": {"coordinates":[-78.330506,35.665766],"type":"Point"}
}