{
  "type": "Feature",
  "properties": {
    "iso:country":"US",
    "sg:address":"44 Bishop Ridge Rd",
    "sg:city":"Fairview",
    "sg:classifiers":[
        {
            "category":"Insurance",
            "subcategory":"Insurance Agent",
            "type":"Services"
        }
    ],
    "sg:phone":"+1 828 628 1394",
    "sg:postcode":"28730",
    "sg:province":"NC",
    "sg:website":"www.nase.org",
    "wof:name":"National Assn Of Self Employed",
    "wof:placetype":"venue"
},
  "geometry": {"coordinates":[-82.43180599999999,35.531621],"type":"Point"}
}