{
  "type": "Feature",
  "properties": {
    "iso:country":"US",
    "sg:address":"3493 S Evans St",
    "sg:city":"Greenville",
    "sg:classifiers":[
        {
            "category":"Professional",
            "subcategory":"Lawyer & Legal Services",
            "type":"Services"
        }
    ],
    "sg:phone":"+1 252 752 0952",
    "sg:postcode":"27834",
    "sg:province":"NC",
    "sg:tags":[
        "attorney"
    ],
    "wof:name":"Brown & Brown",
    "wof:placetype":"venue"
},
  "geometry": {"coordinates":[-77.384107,35.565342],"type":"Point"}
}