{
  "type": "Feature",
  "properties": {
    "iso:country":"US",
    "sg:address":"1103 Arendell St",
    "sg:city":"Morehead City",
    "sg:classifiers":[
        {
            "category":"Real Estate",
            "subcategory":"Developer",
            "type":"Services"
        }
    ],
    "sg:phone":"+1 252 808 0220",
    "sg:postcode":"28557",
    "sg:province":"NC",
    "wof:name":"Britt Development Co",
    "wof:placetype":"venue"
},
  "geometry": {"coordinates":[-76.71822899999999,34.721579],"type":"Point"}
}