{
  "type": "Feature",
  "properties": {
    "addr:full":"1423 Smokey Park Hwy Candler NC 28715",
    "addr:housenumber":"1423",
    "addr:postcode":"28715",
    "addr:street":"Smokey Park Hwy",
    "iso:country":"US",
    "sg:address":"1423 Smokey Park Hwy",
    "sg:city":"Candler",
    "sg:classifiers":[
        {
            "category":"Personal",
            "subcategory":"Beauty Salon",
            "type":"Services"
        }
    ],
    "sg:phone":"+1 828 667 8870",
    "sg:postcode":"28715",
    "sg:province":"NC",
    "wof:name":"Teazers",
    "wof:placetype":"venue"
},
  "geometry": {"coordinates":[-82.67870600000001,35.54523],"type":"Point"}
}