{
  "type": "Feature",
  "properties": {
    "addr:full":"14736 Youngblood Rd Charlotte NC 28278",
    "addr:postcode":"14736;28278",
    "addr:street":"Youngblood Rd",
    "iso:country":"US",
    "sg:address":"14736 Youngblood Rd",
    "sg:city":"Charlotte",
    "sg:classifiers":[
        {
            "category":"Wholesale",
            "subcategory":"Vending Machines",
            "type":"Manufacturing & Wholesale Goods"
        }
    ],
    "sg:phone":"+1 704 504 0022",
    "sg:postcode":"28278",
    "sg:province":"NC",
    "sg:tags":[
        "operator"
    ],
    "wof:name":"American Vending Vendng Machs",
    "wof:placetype":"venue"
},
  "geometry": {"coordinates":[-81.00644800000001,35.08686],"type":"Point"}
}