{
  "type": "Feature",
  "properties": {
    "iso:country":"US",
    "sg:address":"1277 Freedom Way",
    "sg:city":"Hubert",
    "sg:classifiers":[
        {
            "category":"Wholesale",
            "subcategory":"Plants",
            "type":"Manufacturing & Wholesale Goods"
        },
        {
            "category":"Personal",
            "type":"Services"
        }
    ],
    "sg:phone":"+1 910 353 3000",
    "sg:postcode":"28539",
    "sg:province":"NC",
    "sg:tags":[
        "therapist",
        "massage",
        "supply"
    ],
    "wof:name":"Massage and Flower Gallery",
    "wof:placetype":"venue"
},
  "geometry": {"coordinates":[-77.281109,34.706815],"type":"Point"}
}