{
  "type": "Feature",
  "properties": {
    "addr:full":"1789 Woodglo Dr Asheboro NC 27205",
    "addr:housenumber":"1789",
    "addr:postcode":"27205",
    "addr:street":"Woodglo Dr",
    "iso:country":"US",
    "sg:address":"1789 Woodglo Dr",
    "sg:city":"Asheboro",
    "sg:classifiers":[
        {
            "category":"Freight",
            "type":"Transportation"
        }
    ],
    "sg:phone":"+1 336 302 6466",
    "sg:postcode":"27205",
    "sg:province":"NC",
    "sg:tags":[
        "operator",
        "local",
        "trucking"
    ],
    "wof:name":"Tarheel Transfer",
    "wof:placetype":"venue"
},
  "geometry": {"coordinates":[-79.703575,35.678245],"type":"Point"}
}