{
  "type": "Feature",
  "properties": {
    "addr:full":"218 S Railroad Ave Kings Mountain NC 28086",
    "addr:housenumber":"218",
    "addr:postcode":"28086",
    "addr:street":"S Railroad Ave",
    "iso:country":"US",
    "sg:address":"218 S Railroad Ave",
    "sg:city":"Kings Mountain",
    "sg:classifiers":[
        {
            "category":"Shopping",
            "subcategory":"Used Merchandise",
            "type":"Retail Goods"
        }
    ],
    "sg:phone":"+1 704 739 3005",
    "sg:postcode":"28086",
    "sg:province":"NC",
    "wof:name":"This & That Novelty Shoppe",
    "wof:placetype":"venue"
},
  "geometry": {"coordinates":[-81.344972,35.239034],"type":"Point"}
}