{
  "type": "Feature",
  "properties": {
    "iso:country":"US",
    "sg:address":"816 Main St",
    "sg:city":"North Wilkesboro",
    "sg:classifiers":[
        {
            "category":"Cinema",
            "subcategory":"Movie Theater",
            "type":"Entertainment"
        }
    ],
    "sg:phone":"+1 336 838 4561",
    "sg:postcode":"28659",
    "sg:province":"NC",
    "wof:name":"Liberty Theatre",
    "wof:placetype":"venue"
},
  "geometry": {"coordinates":[-81.145483,36.159939],"type":"Point"}
}