{
  "type": "Feature",
  "properties": {
    "iso:country":"US",
    "sg:address":"1509 State Hwy 49",
    "sg:city":"Burlington",
    "sg:classifiers":[
        {
            "category":"Organizations",
            "subcategory":"Religious Organization",
            "type":"Services"
        }
    ],
    "sg:phone":"+1 336 567 0050",
    "sg:postcode":"27217",
    "sg:province":"NC",
    "sg:tags":[
        "church"
    ],
    "wof:name":"Higher Praise Ministries",
    "wof:placetype":"venue"
},
  "geometry": {"coordinates":[-79.34961800000001,36.122178],"type":"Point"}
}