{
  "type": "Feature",
  "properties": {
    "addr:full":"4058 Matthews-Indian Trail Rd Matthews NC 28104",
    "addr:housenumber":"4058",
    "addr:postcode":"28104",
    "addr:street":"Matthews-Indian Trail Rd",
    "iso:country":"US",
    "sg:address":"4058 Matthews-Indian Trail Rd",
    "sg:city":"Matthews",
    "sg:classifiers":[
        {
            "category":"Retail",
            "subcategory":"Auto Repair",
            "type":"Services"
        }
    ],
    "sg:phone":"+1 704 821 4494",
    "sg:postcode":"28104",
    "sg:province":"NC",
    "sg:tags":[
        "muffler",
        "exhaust",
        "system"
    ],
    "wof:name":"Elston Exhaust",
    "wof:placetype":"venue"
},
  "geometry": {"coordinates":[-80.67252000000001,35.089453],"type":"Point"}
}