{
  "type": "Feature",
  "properties": {
    "addr:full":"1449 Old Liberty Rd Asheboro NC 27203",
    "addr:housenumber":"1449",
    "addr:postcode":"27203",
    "addr:street":"Old Liberty Rd",
    "iso:country":"US",
    "sg:address":"1449 Old Liberty Rd",
    "sg:city":"Asheboro",
    "sg:classifiers":[
        {
            "category":"Retail",
            "subcategory":"Repair Shop",
            "type":"Services"
        }
    ],
    "sg:phone":"+1   ",
    "sg:postcode":"27203",
    "sg:province":"NC",
    "wof:name":"Hughes Boat & Motor Repair",
    "wof:placetype":"venue"
},
  "geometry": {"coordinates":[-79.774075,35.762588],"type":"Point"}
}