{
  "type": "Feature",
  "properties": {
    "addr:full":"23 Spring Mountain Rd Fairview NC 28730",
    "addr:housenumber":"23",
    "addr:postcode":"28730",
    "addr:street":"Spring Mountain Rd",
    "iso:country":"US",
    "sg:address":"23 Spring Mountain Rd",
    "sg:city":"Fairview",
    "sg:classifiers":[
        {
            "category":"Building & Trades",
            "subcategory":"Construction",
            "type":"Services"
        }
    ],
    "sg:phone":"+1 828 628 9438",
    "sg:postcode":"28730",
    "sg:province":"NC",
    "sg:tags":[
        "house"
    ],
    "wof:name":"Wilson Construction Company",
    "wof:placetype":"venue"
},
  "geometry": {"coordinates":[-82.35047900000001,35.561195],"type":"Point"}
}