{
  "type": "Feature",
  "properties": {
    "addr:full":"1002 Kenan Dr Hope Mills NC 28348",
    "addr:housenumber":"1002",
    "addr:postcode":"28348",
    "addr:street":"Kenan Dr",
    "iso:country":"US",
    "sg:address":"1002 Kenan Dr",
    "sg:city":"Hope Mills",
    "sg:classifiers":[
        {
            "category":"Professional",
            "type":"Services"
        }
    ],
    "sg:phone":"+1 910 480 0417",
    "sg:postcode":"28348",
    "sg:province":"NC",
    "wof:name":"Hayden R Jones",
    "wof:placetype":"venue"
},
  "geometry": {"coordinates":[-78.911523,34.922931],"type":"Point"}
}