{
  "type": "Feature",
  "properties": {
    "addr:full":"222 Edinboro Dr Southern Pines NC 28387",
    "addr:housenumber":"222",
    "addr:postcode":"28387",
    "addr:street":"Edinboro Dr",
    "iso:country":"US",
    "sg:address":"222 Edinboro Dr",
    "sg:city":"Southern Pines",
    "sg:classifiers":[
        {
            "category":"Professional",
            "subcategory":"Management & Consulting",
            "type":"Services"
        }
    ],
    "sg:phone":"+1   ",
    "sg:postcode":"28387",
    "sg:province":"NC",
    "wof:name":"Andrew Gager Inc",
    "wof:placetype":"venue"
},
  "geometry": {"coordinates":[-79.37427599999999,35.128836],"type":"Point"}
}