{
  "type": "Feature",
  "properties": {
    "addr:full":"9817 Bayview Pkwy Charlotte NC 28216",
    "addr:housenumber":"9817",
    "addr:postcode":"28216",
    "addr:street":"Bayview Pkwy",
    "iso:country":"US",
    "sg:address":"9817 Bayview Pkwy",
    "sg:city":"Charlotte",
    "sg:classifiers":[
        {
            "category":"Education",
            "subcategory":"Special Training",
            "type":"Public Place"
        }
    ],
    "sg:phone":"+1 704 509 1544",
    "sg:postcode":"28216",
    "sg:province":"NC",
    "sg:tags":[
        "center"
    ],
    "wof:name":"Unique Learning Concepts",
    "wof:placetype":"venue"
},
  "geometry": {"coordinates":[-80.86724700000001,35.341678],"type":"Point"}
}