{
  "type": "Feature",
  "properties": {
    "iso:country":"US",
    "sg:address":"235 Ward Rd",
    "sg:city":"Greensboro",
    "sg:classifiers":[
        {
            "category":"Organizations",
            "subcategory":"Religious Organization",
            "type":"Services"
        }
    ],
    "sg:phone":"+1 336 275 8929",
    "sg:postcode":"27405",
    "sg:province":"NC",
    "sg:tags":[
        "church"
    ],
    "wof:name":"Believers Missionary Baptist",
    "wof:placetype":"venue"
},
  "geometry": {"coordinates":[-79.72933399999999,36.071957],"type":"Point"}
}