{
  "type": "Feature",
  "properties": {
    "addr:full":"302 Pomona Dr Greensboro NC 27407",
    "addr:housenumber":"302",
    "addr:postcode":"27407",
    "addr:street":"Pomona Dr",
    "iso:country":"US",
    "sg:address":"302 Pomona Dr",
    "sg:city":"Greensboro",
    "sg:classifiers":[
        {
            "category":"Real Estate",
            "subcategory":"Real Estate Agent",
            "type":"Services"
        }
    ],
    "sg:phone":"+1 336 852 2600",
    "sg:postcode":"27407",
    "sg:province":"NC",
    "wof:name":"Winstead & True Realty",
    "wof:placetype":"venue"
},
  "geometry": {"coordinates":[-79.866981,36.065991],"type":"Point"}
}