{
  "type": "Feature",
  "properties": {
    "iso:country":"US",
    "sg:address":"1983 Quail Ridge Rd",
    "sg:city":"Greenville",
    "sg:classifiers":[
        {
            "category":"Professional",
            "subcategory":"Engineering",
            "type":"Services"
        }
    ],
    "sg:phone":"+1 252 355 5244",
    "sg:postcode":"27858",
    "sg:province":"NC",
    "sg:tags":[
        "engineer"
    ],
    "wof:name":"Compass Training & Consulting",
    "wof:placetype":"venue"
},
  "geometry": {"coordinates":[-77.338908,35.579723],"type":"Point"}
}