{
  "type": "Feature",
  "properties": {
    "iso:country":"US",
    "sg:address":"111 W Pennsylvania Ave",
    "sg:city":"Bessemer City",
    "sg:classifiers":[
        {
            "category":"Professional",
            "type":"Services"
        }
    ],
    "sg:phone":"+1 704 629 1111",
    "sg:postcode":"28016",
    "sg:province":"NC",
    "sg:tags":[
        "establishment"
    ],
    "wof:name":"Divas On The Go",
    "wof:placetype":"venue"
},
  "geometry": {"coordinates":[-81.28610399999999,35.284274],"type":"Point"}
}