{
  "type": "Feature",
  "properties": {
    "addr:full":"6421 Medlin Rd Monroe NC 28112",
    "addr:postcode":"6421;28112",
    "addr:street":"Medlin Rd",
    "iso:country":"US",
    "sg:address":"6421 Medlin Rd",
    "sg:city":"Monroe",
    "sg:classifiers":[
        {
            "category":"Retail",
            "subcategory":"Auto Repair",
            "type":"Services"
        }
    ],
    "sg:phone":"+1 704 577 6777",
    "sg:postcode":"28112",
    "sg:province":"NC",
    "sg:tags":[
        "wheel",
        "automobile",
        "reconditioning",
        "reconditions",
        "sale"
    ],
    "wof:name":"Prince Reconditioning Services",
    "wof:placetype":"venue"
},
  "geometry": {"coordinates":[-80.451369,34.848476],"type":"Point"}
}