{
  "type": "Feature",
  "properties": {
    "addr:full":"5631 Creedmoor Rd Raleigh NC 27612",
    "addr:housenumber":"5631",
    "addr:postcode":"27612",
    "addr:street":"Creedmoor Rd",
    "iso:country":"US",
    "sg:address":"5631 Creedmoor Rd",
    "sg:city":"Raleigh",
    "sg:classifiers":[
        {
            "category":"Shopping",
            "subcategory":"Pharmacy",
            "type":"Retail Goods"
        }
    ],
    "sg:phone":"+1 919 782 7330",
    "sg:postcode":"27612",
    "sg:province":"NC",
    "sg:tags":[
        "drugstore"
    ],
    "wof:name":"Rite Aid Pharmacies",
    "wof:placetype":"venue"
},
  "geometry": {"coordinates":[-78.68086,35.85836],"type":"Point"}
}