{
  "type": "Feature",
  "properties": {
    "iso:country":"US",
    "sg:address":"117 Vance St",
    "sg:city":"Clinton",
    "sg:classifiers":[
        {
            "category":"Social Services",
            "type":"Services"
        }
    ],
    "sg:phone":"+1 910 592 4209",
    "sg:postcode":"28328",
    "sg:province":"NC",
    "sg:tags":[
        "probation"
    ],
    "wof:name":"Probation Dept Intensive",
    "wof:placetype":"venue"
},
  "geometry": {"coordinates":[-78.32394499999999,34.998337],"type":"Point"}
}