{
  "type": "Feature",
  "properties": {
    "iso:country":"US",
    "sg:address":"1735 E Dixon Blvd",
    "sg:city":"Shelby",
    "sg:classifiers":[
        {
            "category":"Autos & Motor Vehicles",
            "subcategory":"Motorcycle Sales",
            "type":"Retail Goods"
        }
    ],
    "sg:phone":"+1 704 482 5946",
    "sg:postcode":"28152",
    "sg:province":"NC",
    "sg:tags":[
        "scooter"
    ],
    "wof:name":"Shelby Motorsports",
    "wof:placetype":"venue"
},
  "geometry": {"coordinates":[-81.502132,35.273398],"type":"Point"}
}