{
  "type": "Feature",
  "properties": {
    "iso:country":"US",
    "sg:address":"1803 N Brevard St",
    "sg:city":"Charlotte",
    "sg:classifiers":[
        {
            "category":"Professional",
            "type":"Services"
        }
    ],
    "sg:phone":"+1 704 358 0941",
    "sg:postcode":"28206",
    "sg:province":"NC",
    "sg:tags":[
        "transportation"
    ],
    "wof:name":"H & M International",
    "wof:placetype":"venue"
},
  "geometry": {"coordinates":[-80.821809,35.237848],"type":"Point"}
}