{
  "type": "Feature",
  "properties": {
    "iso:country":"US",
    "sg:address":"617 W North St",
    "sg:city":"Raleigh",
    "sg:classifiers":[
        {
            "category":"Professional",
            "type":"Services"
        }
    ],
    "sg:phone":"+1 919 264 5299",
    "sg:postcode":"27603",
    "sg:province":"NC",
    "wof:name":"Durzt Inc",
    "wof:placetype":"venue"
},
  "geometry": {"coordinates":[-78.648762,35.784891],"type":"Point"}
}