{
  "type": "Feature",
  "properties": {
    "iso:country":"US",
    "sg:address":"205 Cowan St",
    "sg:city":"Lilesville",
    "sg:classifiers":[
        {
            "category":"Personal",
            "subcategory":"Beauty Salon",
            "type":"Services"
        }
    ],
    "sg:phone":"+1 704 848 4387",
    "sg:postcode":"28091",
    "sg:province":"NC",
    "wof:name":"Shonda Beauty Parlor",
    "wof:placetype":"venue"
},
  "geometry": {"coordinates":[-79.984703,34.969911],"type":"Point"}
}