{
  "type": "Feature",
  "properties": {
    "addr:full":"29 N College Ave Newton NC 28658",
    "addr:housenumber":"29",
    "addr:postcode":"28658",
    "addr:street":"N College Ave",
    "iso:country":"US",
    "sg:address":"29 N College Ave",
    "sg:city":"Newton",
    "sg:classifiers":[
        {
            "category":"Shopping",
            "subcategory":"Clothing, Apparel, & Fashions",
            "type":"Retail Goods"
        }
    ],
    "sg:phone":"+1 828 465 0854",
    "sg:postcode":"28658",
    "sg:province":"NC",
    "sg:tags":[
        "woman"
    ],
    "wof:name":"Sonny & Thelmas Fashions",
    "wof:placetype":"venue"
},
  "geometry": {"coordinates":[-81.22133599999999,35.663123],"type":"Point"}
}