{
  "type": "Feature",
  "properties": {
    "iso:country":"US",
    "sg:address":"54 W Main St",
    "sg:city":"Thomasville",
    "sg:classifiers":[
        {
            "category":"Personal",
            "subcategory":"Beauty Salon",
            "type":"Services"
        }
    ],
    "sg:phone":"+1 336 472 7254",
    "sg:postcode":"27360",
    "sg:province":"NC",
    "wof:name":"Vogue Beauty Salon",
    "wof:placetype":"venue"
},
  "geometry": {"coordinates":[-80.083935,35.882503],"type":"Point"}
}