{
  "type": "Feature",
  "properties": {
    "addr:full":"1717 S York Rd Gastonia NC 28052",
    "addr:housenumber":"1717",
    "addr:postcode":"28052",
    "addr:street":"S York Rd",
    "iso:country":"US",
    "sg:address":"1717 S York Rd",
    "sg:city":"Gastonia",
    "sg:classifiers":[
        {
            "category":"Retail",
            "subcategory":"Repair Shop",
            "type":"Services"
        }
    ],
    "sg:phone":"+1   ",
    "sg:postcode":"28052",
    "sg:province":"NC",
    "wof:name":"Pruitts Television Service",
    "wof:placetype":"venue"
},
  "geometry": {"coordinates":[-81.195033,35.239792],"type":"Point"}
}