{
  "type": "Feature",
  "properties": {
    "iso:country":"US",
    "sg:address":"604 8th St",
    "sg:city":"Black Mountain",
    "sg:classifiers":[
        {
            "category":"Shopping",
            "subcategory":"Hobbies, Toys, & Games",
            "type":"Retail Goods"
        }
    ],
    "sg:phone":"+1 828 669 5299",
    "sg:postcode":"28711",
    "sg:province":"NC",
    "wof:name":"Catawba Sunrise Gallery",
    "wof:placetype":"venue"
},
  "geometry": {"coordinates":[-82.32826300000001,35.622581],"type":"Point"}
}