{
  "type": "Feature",
  "properties": {
    "iso:country":"US",
    "sg:address":"1240 Briarcreek Rd",
    "sg:city":"King",
    "sg:classifiers":[
        {
            "category":"Retail",
            "subcategory":"Animal Services",
            "type":"Services"
        }
    ],
    "sg:phone":"+1 336 983 5687",
    "sg:postcode":"27021",
    "sg:province":"NC",
    "wof:name":"Briarcreek Grooming By Sandy",
    "wof:placetype":"venue"
},
  "geometry": {"coordinates":[-80.36379599999999,36.326858],"type":"Point"}
}