{
  "type": "Feature",
  "properties": {
    "iso:country":"US",
    "sg:address":"626 S Magnolia St",
    "sg:city":"Lincolnton",
    "sg:classifiers":[
        {
            "category":"Wholesale",
            "subcategory":"Hardware",
            "type":"Manufacturing & Wholesale Goods"
        }
    ],
    "sg:phone":"+1 704 732 4057",
    "sg:postcode":"28092",
    "sg:province":"NC",
    "sg:tags":[
        "tool"
    ],
    "wof:name":"Jim Lail & Assoc",
    "wof:placetype":"venue"
},
  "geometry": {"coordinates":[-81.242305,35.469458],"type":"Point"}
}