{
  "type": "Feature",
  "properties": {
    "addr:full":"3172 Morningside Dr Raleigh NC 27607",
    "addr:housenumber":"3172",
    "addr:postcode":"27607",
    "addr:street":"Morningside Dr",
    "iso:country":"US",
    "sg:address":"3172 Morningside Dr",
    "sg:city":"Raleigh",
    "sg:classifiers":[
        {
            "category":"Manufacturing",
            "subcategory":"Printing",
            "type":"Manufacturing & Wholesale Goods"
        }
    ],
    "sg:phone":"+1 919 782 7492",
    "sg:postcode":"27607",
    "sg:province":"NC",
    "sg:tags":[
        "agency",
        "advertising"
    ],
    "wof:name":"Satori Publishing",
    "wof:placetype":"venue"
},
  "geometry": {"coordinates":[-78.690777,35.824192],"type":"Point"}
}