{
  "type": "Feature",
  "properties": {
    "addr:full":"2086 State Hwy 24 27 E Biscoe NC 27209",
    "addr:housenumber":"2086;27 e",
    "addr:postcode":"27209",
    "addr:street":"State Hwy 24;Biscoe",
    "iso:country":"US",
    "sg:address":"2086 State Hwy 24 27 E",
    "sg:city":"Biscoe",
    "sg:classifiers":[
        {
            "category":"Government",
            "subcategory":"Office",
            "type":"Public Place"
        }
    ],
    "sg:phone":"+1 910 428 4325",
    "sg:postcode":"27209",
    "sg:province":"NC",
    "sg:tags":[
        "city"
    ],
    "wof:name":"Home City LTD",
    "wof:placetype":"venue"
},
  "geometry": {"coordinates":[-79.80583799999999,35.356895],"type":"Point"}
}