{
  "type": "Feature",
  "properties": {
    "iso:country":"US",
    "sg:address":"104 Gloria Pl",
    "sg:city":"Jacksonville",
    "sg:classifiers":[
        {
            "category":"Professional",
            "subcategory":"Business Services",
            "type":"Services"
        }
    ],
    "sg:phone":"+1   ",
    "sg:postcode":"28540",
    "sg:province":"NC",
    "wof:name":"Lecher Enterprises Inc",
    "wof:placetype":"venue"
},
  "geometry": {"coordinates":[-77.43037,34.786186],"type":"Point"}
}