{
  "type": "Feature",
  "properties": {
    "addr:full":"140 S Main St Mocksville NC 27028",
    "addr:housenumber":"140",
    "addr:postcode":"27028",
    "addr:street":"S Main St",
    "iso:country":"US",
    "sg:address":"140 S Main St",
    "sg:city":"Mocksville",
    "sg:classifiers":[
        {
            "category":"Government",
            "subcategory":"Police Station",
            "type":"Public Place"
        }
    ],
    "sg:phone":"+1 336 751 6238",
    "sg:postcode":"27028",
    "sg:province":"NC",
    "sg:tags":[
        "department"
    ],
    "wof:name":"Sheriffs Department",
    "wof:placetype":"venue"
},
  "geometry": {"coordinates":[-80.56180000000001,35.893461],"type":"Point"}
}