{
  "type": "Feature",
  "properties": {
    "addr:full":"1207 Cherry Ln New Bern NC 28562",
    "addr:housenumber":"1207",
    "addr:postcode":"28562",
    "addr:street":"Cherry Ln",
    "iso:country":"US",
    "sg:address":"1207 Cherry Ln",
    "sg:city":"New Bern",
    "sg:classifiers":[
        {
            "category":"Freight",
            "type":"Transportation"
        }
    ],
    "sg:phone":"+1 252 638 4926",
    "sg:postcode":"28562",
    "sg:province":"NC",
    "sg:tags":[
        "operator",
        "mover",
        "local",
        "trucking"
    ],
    "wof:name":"Mitchell Movers",
    "wof:placetype":"venue"
},
  "geometry": {"coordinates":[-77.076548,35.116152],"type":"Point"}
}