{
  "type": "Feature",
  "properties": {
    "iso:country":"US",
    "sg:address":"5913 Countryview Ln",
    "sg:city":"Raleigh",
    "sg:classifiers":[
        {
            "category":"Building & Trades",
            "subcategory":"Construction",
            "type":"Services"
        }
    ],
    "sg:phone":"+1 919 851 0027",
    "sg:postcode":"27606",
    "sg:province":"NC",
    "sg:tags":[
        "acoustical",
        "contractor"
    ],
    "wof:name":"Duke Acoustical",
    "wof:placetype":"venue"
},
  "geometry": {"coordinates":[-78.707238,35.713773],"type":"Point"}
}