{
  "type": "Feature",
  "properties": {
    "addr:full":"6404 Berridge Dr Wilmington NC 28412",
    "addr:housenumber":"6404",
    "addr:postcode":"28412",
    "addr:street":"Berridge Dr",
    "iso:country":"US",
    "sg:address":"6404 Berridge Dr",
    "sg:city":"Wilmington",
    "sg:classifiers":[
        {
            "category":"Professional",
            "subcategory":"Business Services",
            "type":"Services"
        }
    ],
    "sg:phone":"+1   ",
    "sg:postcode":"28412",
    "sg:province":"NC",
    "wof:name":"EZ Rider Motorworks Inc",
    "wof:placetype":"venue"
},
  "geometry": {"coordinates":[-77.900953,34.102925],"type":"Point"}
}