{
  "type": "Feature",
  "properties": {
    "iso:country":"US",
    "sg:address":"6613 Battleford Dr",
    "sg:city":"Raleigh",
    "sg:classifiers":[
        {
            "category":"Building & Trades",
            "subcategory":"Plumbing",
            "type":"Services"
        }
    ],
    "sg:phone":"+1 919 676 2900",
    "sg:postcode":"27613",
    "sg:province":"NC",
    "sg:tags":[
        "contractor"
    ],
    "wof:name":"Simply Refrigeration",
    "wof:placetype":"venue"
},
  "geometry": {"coordinates":[-78.68059,35.876282],"type":"Point"}
}