{
  "type": "Feature",
  "properties": {
    "addr:full":"2209 Cloverdale Ave Winston Salem NC 27103",
    "addr:housenumber":"2209",
    "addr:postcode":"27103",
    "addr:street":"Cloverdale Ave",
    "iso:country":"US",
    "sg:address":"2209 Cloverdale Ave",
    "sg:city":"Winston Salem",
    "sg:classifiers":[
        {
            "category":"Bakery",
            "type":"Food & Drink"
        }
    ],
    "sg:menulink":"http://www.allmenus.com/nc/winston/106005-panera-bread/menu/",
    "sg:phone":"+1 336 722 0900",
    "sg:postcode":"27103",
    "sg:province":"NC",
    "sg:tags":[
        "american",
        "sandwich",
        "pastry"
    ],
    "wof:name":"Panera Bread",
    "wof:placetype":"venue"
},
  "geometry": {"coordinates":[-80.274348,36.090146],"type":"Point"}
}