{
  "type": "Feature",
  "properties": {
    "addr:full":"128 W Elizabeth St Clinton NC 28328",
    "addr:housenumber":"128",
    "addr:postcode":"28328",
    "addr:street":"W Elizabeth St",
    "iso:country":"US",
    "sg:address":"128 W Elizabeth St",
    "sg:city":"Clinton",
    "sg:classifiers":[
        {
            "category":"Government",
            "subcategory":"Police Station",
            "type":"Public Place"
        }
    ],
    "sg:phone":"+1 910 592 4141",
    "sg:postcode":"28328",
    "sg:province":"NC",
    "sg:tags":[
        "sheriff"
    ],
    "wof:name":"Sampson County Sheriff's Dept",
    "wof:placetype":"venue"
},
  "geometry": {"coordinates":[-78.322928,34.997417],"type":"Point"}
}