{
  "type": "Feature",
  "properties": {
    "addr:full":"9935 Ballantyne Commons Pkwy Charlotte NC 28277",
    "addr:housenumber":"9935",
    "addr:postcode":"28277",
    "addr:street":"Ballantyne Commons Pkwy",
    "iso:country":"US",
    "sg:address":"9935 Ballantyne Commons Pkwy",
    "sg:city":"Charlotte",
    "sg:classifiers":[
        {
            "category":"Autos & Motor Vehicles",
            "subcategory":"Fuel & Gas Station",
            "type":"Retail Goods"
        }
    ],
    "sg:phone":"+1 704 752 8518",
    "sg:postcode":"28277",
    "sg:province":"NC",
    "sg:tags":[
        "oil"
    ],
    "wof:name":"Ballantyne Amoco",
    "wof:placetype":"venue"
},
  "geometry": {"coordinates":[-80.846907,35.054999],"type":"Point"}
}