{
  "type": "Feature",
  "properties": {
    "iso:country":"US",
    "sg:address":"19141 State Hwy 73",
    "sg:city":"Cornelius",
    "sg:classifiers":[
        {
            "category":"Wholesale",
            "subcategory":"Electrical",
            "type":"Manufacturing & Wholesale Goods"
        }
    ],
    "sg:phone":"+1 704 896 8473",
    "sg:postcode":"28001",
    "sg:province":"NC",
    "sg:tags":[
        "repair",
        "electronic"
    ],
    "wof:name":"GCI",
    "wof:placetype":"venue"
},
  "geometry": {"coordinates":[-80.343538,35.38254],"type":"Point"}
}