{
  "type": "Feature",
  "properties": {
    "iso:country":"US",
    "sg:address":"2051 Carriage Way",
    "sg:city":"Chapel Hill",
    "sg:classifiers":[
        {
            "category":"Professional",
            "type":"Services"
        }
    ],
    "sg:phone":"+1 919 918 4170",
    "sg:postcode":"27517",
    "sg:province":"NC",
    "sg:tags":[
        "establishment"
    ],
    "wof:name":"Beaconrock Application Systems",
    "wof:placetype":"venue"
},
  "geometry": {"coordinates":[-78.99880899999999,35.895348],"type":"Point"}
}