{
  "type": "Feature",
  "properties": {
    "addr:full":"120 Randolph St Randleman NC 27317",
    "addr:housenumber":"120",
    "addr:postcode":"27317",
    "addr:street":"Randolph St",
    "iso:country":"US",
    "sg:address":"120 Randolph St",
    "sg:city":"Randleman",
    "sg:classifiers":[
        {
            "category":"Social Services",
            "subcategory":"Job Training",
            "type":"Services"
        }
    ],
    "sg:phone":"+1 336 495 8966",
    "sg:postcode":"27317",
    "sg:province":"NC",
    "sg:tags":[
        "rehabilitation"
    ],
    "wof:name":"Rehab Builders Inc",
    "wof:placetype":"venue"
},
  "geometry": {"coordinates":[-79.806826,35.818425],"type":"Point"}
}