{
  "type": "Feature",
  "properties": {
    "iso:country":"US",
    "sg:address":"3525 Haystack Rd",
    "sg:city":"Mount Airy",
    "sg:phone":"+1 336 352 4233",
    "sg:postcode":"27030",
    "sg:province":"NC",
    "sg:tags":[
        "farm",
        "tobacco"
    ],
    "wof:name":"Robert Brindle",
    "wof:placetype":"venue"
},
  "geometry": {"coordinates":[-80.801484,36.46003],"type":"Point"}
}