{
  "type": "Feature",
  "properties": {
    "iso:country":"US",
    "sg:address":"786 State Hwy 268",
    "sg:city":"Elkin",
    "sg:classifiers":[
        {
            "category":"Retail",
            "subcategory":"Veterinary Services",
            "type":"Services"
        }
    ],
    "sg:phone":"+1 336 835 1853",
    "sg:postcode":"28621",
    "sg:province":"NC",
    "sg:tags":[
        "hospital",
        "animal"
    ],
    "wof:name":"Elkin Veterinary Clinic",
    "wof:placetype":"venue"
},
  "geometry": {"coordinates":[-80.835404,36.249064],"type":"Point"}
}