{
  "type": "Feature",
  "properties": {
    "iso:country":"US",
    "sg:address":"509 Sturbridge Dr",
    "sg:city":"Snow Hill",
    "sg:classifiers":[
        {
            "category":"Manufacturing",
            "subcategory":"Tools & Machinery",
            "type":"Manufacturing & Wholesale Goods"
        }
    ],
    "sg:phone":"+1 252 747 9994",
    "sg:postcode":"28580",
    "sg:province":"NC",
    "sg:tags":[
        "mfg"
    ],
    "wof:name":"Worth Products",
    "wof:placetype":"venue"
},
  "geometry": {"coordinates":[-77.67792900000001,35.440489],"type":"Point"}
}