{
  "type": "Feature",
  "properties": {
    "addr:full":"9822 Albemarle Rd Charlotte NC 28227",
    "addr:housenumber":"9822",
    "addr:postcode":"28227",
    "addr:street":"Albemarle Rd",
    "iso:country":"US",
    "sg:address":"9822 Albemarle Rd",
    "sg:city":"Charlotte",
    "sg:classifiers":[
        {
            "category":"Building & Trades",
            "subcategory":"Plumbing",
            "type":"Services"
        }
    ],
    "sg:phone":"+1 704 545 0050",
    "sg:postcode":"28227",
    "sg:province":"NC",
    "sg:tags":[
        "conditioning",
        "air",
        "system",
        "contractor"
    ],
    "wof:name":"Hackney Air Conditioning & Htg",
    "wof:placetype":"venue"
},
  "geometry": {"coordinates":[-80.67573299999999,35.209466],"type":"Point"}
}