{
  "type": "Feature",
  "properties": {
    "addr:full":"709 S Kerr Ave Wilmington NC 28403",
    "addr:housenumber":"709",
    "addr:postcode":"28403",
    "addr:street":"S Kerr Ave",
    "iso:country":"US",
    "sg:address":"709 S Kerr Ave",
    "sg:city":"Wilmington",
    "sg:classifiers":[
        {
            "category":"Shopping",
            "subcategory":"Used Merchandise",
            "type":"Retail Goods"
        }
    ],
    "sg:phone":"+1 910 791 2764",
    "sg:postcode":"28403",
    "sg:province":"NC",
    "sg:tags":[
        "shop",
        "thrift"
    ],
    "sg:website":"www.gcfcommunityfoundation.org",
    "wof:name":"Goodwill Industries",
    "wof:placetype":"venue"
},
  "geometry": {"coordinates":[-77.885729,34.224976],"type":"Point"}
}