{
  "type": "Feature",
  "properties": {
    "iso:country":"US",
    "sg:address":"1402 Eastchester Dr",
    "sg:city":"High Point",
    "sg:classifiers":[
        {
            "category":"Health Services",
            "subcategory":"Optometrist",
            "type":"Services"
        }
    ],
    "sg:phone":"+1 336 886 8400",
    "sg:postcode":"27265",
    "sg:province":"NC",
    "wof:name":"Doctors Vision Ctr",
    "wof:placetype":"venue"
},
  "geometry": {"coordinates":[-79.99479100000001,35.997192],"type":"Point"}
}