{
  "type": "Feature",
  "properties": {
    "addr:full":"424 Airport Blvd Morrisville NC 27560",
    "addr:housenumber":"424",
    "addr:postcode":"27560",
    "addr:street":"Airport Blvd",
    "iso:country":"US",
    "sg:address":"424 Airport Blvd",
    "sg:city":"Morrisville",
    "sg:classifiers":[
        {
            "category":"Wholesale",
            "subcategory":"Machinery & Supplies",
            "type":"Manufacturing & Wholesale Goods"
        }
    ],
    "sg:phone":"+1 919 465 2399",
    "sg:postcode":"27560",
    "sg:province":"NC",
    "sg:tags":[
        "equipment",
        "industrial"
    ],
    "sg:website":"www.fastenal.com",
    "wof:name":"Fastenal Co",
    "wof:placetype":"venue"
},
  "geometry": {"coordinates":[-78.82729500000001,35.846705],"type":"Point"}
}