{
  "type": "Feature",
  "properties": {
    "addr:full":"7830 N Point Blvd Winston Salem NC 27106",
    "addr:housenumber":"7830",
    "addr:postcode":"27106",
    "addr:street":"N Point Blvd",
    "iso:country":"US",
    "sg:address":"7830 N Point Blvd",
    "sg:city":"Winston Salem",
    "sg:classifiers":[
        {
            "category":"Shopping",
            "subcategory":"Computers & Home Electronics",
            "type":"Retail Goods"
        }
    ],
    "sg:phone":"+1 336 659 0815",
    "sg:postcode":"27106",
    "sg:province":"NC",
    "sg:tags":[
        "software"
    ],
    "sg:website":"www.mtihorizon.com",
    "wof:name":"MTI",
    "wof:placetype":"venue"
},
  "geometry": {"coordinates":[-80.27808899999999,36.150914],"type":"Point"}
}