{
  "type": "Feature",
  "properties": {
    "iso:country":"US",
    "sg:address":"112 Carmalt St",
    "sg:city":"Thomasville",
    "sg:classifiers":[
        {
            "category":"Social Services",
            "subcategory":"Child Care",
            "type":"Services"
        }
    ],
    "sg:phone":"+1 336 475 6482",
    "sg:postcode":"27360",
    "sg:province":"NC",
    "wof:name":"Nanny's Daycare",
    "wof:placetype":"venue"
},
  "geometry": {"coordinates":[-80.088812,35.87851],"type":"Point"}
}