{
  "type": "Feature",
  "properties": {
    "iso:country":"US",
    "sg:address":"319 Reeves Ridge Rd",
    "sg:city":"Sparta",
    "sg:classifiers":[
        {
            "category":"Manufacturing",
            "subcategory":"Buildings",
            "type":"Manufacturing & Wholesale Goods"
        },
        {
            "category":"Building & Trades",
            "subcategory":"Construction",
            "type":"Services"
        }
    ],
    "sg:phone":"+1 336 372 6467",
    "sg:postcode":"28675",
    "sg:province":"NC",
    "sg:tags":[
        "home",
        "builder",
        "contractor"
    ],
    "wof:name":"Lemasters Construction",
    "wof:placetype":"venue"
},
  "geometry": {"coordinates":[-81.201797,36.53772],"type":"Point"}
}