{
  "type": "Feature",
  "properties": {
    "iso:country":"US",
    "sg:address":"538 Lake Concord Rd NE",
    "sg:city":"Concord",
    "sg:classifiers":[
        {
            "category":"Banks & Credit Unions",
            "subcategory":"Bank",
            "type":"Services"
        }
    ],
    "sg:phone":"+1 704 788 4174",
    "sg:postcode":"28025",
    "sg:province":"NC",
    "sg:website":"http://www.secuga.org",
    "wof:name":"State Employees Credit Union Inc",
    "wof:placetype":"venue"
},
  "geometry": {"coordinates":[-80.600202,35.444325],"type":"Point"}
}