{
  "type": "Feature",
  "properties": {
    "iso:country":"US",
    "sg:address":"7313 Mallard Creek Rd",
    "sg:city":"Charlotte",
    "sg:classifiers":[
        {
            "category":"Home & Garden",
            "subcategory":"Carpets & Floor Coverings",
            "type":"Retail Goods"
        }
    ],
    "sg:phone":"+1 704 599 4797",
    "sg:postcode":"28262",
    "sg:province":"NC",
    "wof:name":"Two Friends Floor Covering",
    "wof:placetype":"venue"
},
  "geometry": {"coordinates":[-80.78839499999999,35.312687],"type":"Point"}
}