{
  "type": "Feature",
  "properties": {
    "iso:country":"US",
    "sg:address":"225 Green St",
    "sg:city":"Fayetteville",
    "sg:classifiers":[
        {
            "category":"Government",
            "subcategory":"Office",
            "type":"Public Place"
        }
    ],
    "sg:phone":"+1 910 486 1554",
    "sg:postcode":"28301",
    "sg:province":"NC",
    "sg:tags":[
        "state",
        "program"
    ],
    "wof:name":"Transportation Dept",
    "wof:placetype":"venue"
},
  "geometry": {"coordinates":[-78.877441,35.055185],"type":"Point"}
}