{
  "type": "Feature",
  "properties": {
    "iso:country":"US",
    "sg:address":"2601 Wheeler Ridge Ln",
    "sg:city":"Raleigh",
    "sg:classifiers":[
        {
            "category":"Professional",
            "subcategory":"Computer Services",
            "type":"Services"
        }
    ],
    "sg:phone":"+1   ",
    "sg:postcode":"27606",
    "sg:province":"NC",
    "sg:tags":[
        "related"
    ],
    "wof:name":"Marc Silverman",
    "wof:placetype":"venue"
},
  "geometry": {"coordinates":[-78.71142399999999,35.705701],"type":"Point"}
}