{
  "type": "Feature",
  "properties": {
    "addr:full":"9414 Stonegate Dr Charlotte NC 28216",
    "addr:housenumber":"9414",
    "addr:postcode":"28216",
    "addr:street":"Stonegate Dr",
    "iso:country":"US",
    "sg:address":"9414 Stonegate Dr",
    "sg:city":"Charlotte",
    "sg:classifiers":[
        {
            "category":"Retail",
            "subcategory":"Repair Shop",
            "type":"Services"
        }
    ],
    "sg:phone":"+1 704 392 3435",
    "sg:postcode":"28216",
    "sg:province":"NC",
    "sg:tags":[
        "cleaners",
        "parts",
        "vacuum"
    ],
    "wof:name":"Central Vac Of The Carolinas",
    "wof:placetype":"venue"
},
  "geometry": {"coordinates":[-80.90708100000001,35.31757],"type":"Point"}
}