{
  "type": "Feature",
  "properties": {
    "iso:country":"US",
    "sg:address":"874 W Main St",
    "sg:city":"Forest City",
    "sg:classifiers":[
        {
            "category":"Autos & Motor Vehicles",
            "subcategory":"Automobile Sales",
            "type":"Retail Goods"
        }
    ],
    "sg:phone":"+1 828 245 5899",
    "sg:postcode":"28043",
    "sg:province":"NC",
    "sg:tags":[
        "car",
        "dealer"
    ],
    "wof:name":"Car City Inc",
    "wof:placetype":"venue"
},
  "geometry": {"coordinates":[-81.885054,35.346095],"type":"Point"}
}