{
  "type": "Feature",
  "properties": {
    "addr:full":"4469 Paysour Pond Rd Iron Station NC 28080",
    "addr:housenumber":"4469",
    "addr:postcode":"28080",
    "addr:street":"Paysour Pond Rd",
    "iso:country":"US",
    "sg:address":"4469 Paysour Pond Rd",
    "sg:city":"Iron Station",
    "sg:classifiers":[
        {
            "category":"Farming",
            "subcategory":"Livestock Farm",
            "type":"Manufacturing & Wholesale Goods"
        }
    ],
    "sg:phone":"+1 704 735 7701",
    "sg:postcode":"28080",
    "sg:province":"NC",
    "sg:tags":[
        "beef",
        "feedlot",
        "cattle"
    ],
    "wof:name":"Frank E Grigg",
    "wof:placetype":"venue"
},
  "geometry": {"coordinates":[-81.10135,35.425055],"type":"Point"}
}