{
  "type": "Feature",
  "properties": {
    "iso:country":"US",
    "sg:address":"332 Slatestone Rd",
    "sg:city":"Washington",
    "sg:classifiers":[
        {
            "category":"Health Services",
            "subcategory":"Nursing And Care Facility",
            "type":"Services"
        }
    ],
    "sg:phone":"+1 252 946 9055",
    "sg:postcode":"27889",
    "sg:province":"NC",
    "sg:tags":[
        "residential"
    ],
    "wof:name":"Slatestone Road Group Home Lf",
    "wof:placetype":"venue"
},
  "geometry": {"coordinates":[-77.014966,35.554535],"type":"Point"}
}