{
  "type": "Feature",
  "properties": {
    "iso:country":"US",
    "sg:address":"4031 Davis Dr",
    "sg:city":"Charlotte",
    "sg:classifiers":[
        {
            "category":"Cinema",
            "subcategory":"Movie Rental",
            "type":"Entertainment"
        }
    ],
    "sg:phone":"+1 919 466 9133",
    "sg:postcode":"28270",
    "sg:province":"NC",
    "sg:tags":[
        "leasing",
        "video",
        "disc",
        "tape"
    ],
    "wof:name":"Hollywood Video",
    "wof:placetype":"venue"
},
  "geometry": {"coordinates":[-80.73842,35.071798],"type":"Point"}
}