{
  "type": "Feature",
  "properties": {
    "iso:country":"US",
    "sg:address":"2644 Kivett Dr",
    "sg:city":"Greensboro",
    "sg:classifiers":[
        {
            "category":"Organizations",
            "subcategory":"Community Association",
            "type":"Services"
        }
    ],
    "sg:phone":"+1 336 852 3992",
    "sg:postcode":"27407",
    "sg:province":"NC",
    "sg:tags":[
        "military"
    ],
    "sg:website":"www.dav.org",
    "wof:name":"Disabled American Veterans",
    "wof:placetype":"venue"
},
  "geometry": {"coordinates":[-79.878136,35.968283],"type":"Point"}
}