{
  "type": "Feature",
  "properties": {
    "iso:country":"US",
    "sg:address":"8235 Thornhaven Ct",
    "sg:city":"Charlotte",
    "sg:classifiers":[
        {
            "category":"Real Estate",
            "subcategory":"Real Estate Services",
            "type":"Services"
        },
        {
            "category":"Real Estate",
            "subcategory":"Real Estate Agent",
            "type":"Services"
        }
    ],
    "sg:phone":"+1 704 537 9091",
    "sg:postcode":"28212",
    "sg:province":"NC",
    "sg:tags":[
        "buyer",
        "broker"
    ],
    "wof:name":"Blackberry Realty & Associates",
    "wof:placetype":"venue"
},
  "geometry": {"coordinates":[-80.730745,35.210087],"type":"Point"}
}