{
  "type": "Feature",
  "properties": {
    "iso:country":"US",
    "sg:address":"9105 Sulkirk Dr",
    "sg:city":"Raleigh",
    "sg:classifiers":[
        {
            "category":"Travel",
            "subcategory":"Hotels & Motels",
            "type":"Entertainment"
        }
    ],
    "sg:phone":"+1 919 215 7829",
    "sg:postcode":"27617",
    "sg:province":"NC",
    "sg:tags":[
        "hotels-apartment"
    ],
    "sg:website":"http://www.extendedstayamerica.com",
    "wof:name":"Extended Stay America",
    "wof:placetype":"venue"
},
  "geometry": {"coordinates":[-78.74776199999999,35.910583],"type":"Point"}
}