{
  "type": "Feature",
  "properties": {
    "iso:country":"US",
    "sg:address":"704 E 10th St",
    "sg:city":"Charlotte",
    "sg:classifiers":[
        {
            "category":"Retail",
            "subcategory":"Self-service Laundry",
            "type":"Services"
        }
    ],
    "sg:phone":"+1   ",
    "sg:postcode":"28202",
    "sg:province":"NC",
    "sg:tags":[
        "coin"
    ],
    "wof:name":"Gary Adcock Laundry Service",
    "wof:placetype":"venue"
},
  "geometry": {"coordinates":[-80.829431,35.225624],"type":"Point"}
}