{
  "type": "Feature",
  "properties": {
    "addr:full":"2027 Gateway Blvd Charlotte NC 28208",
    "addr:housenumber":"2027",
    "addr:postcode":"28208",
    "addr:street":"Gateway Blvd",
    "iso:country":"US",
    "sg:address":"2027 Gateway Blvd",
    "sg:city":"Charlotte",
    "sg:classifiers":[
        {
            "category":"Wholesale",
            "subcategory":"Metals & Minerals",
            "type":"Manufacturing & Wholesale Goods"
        }
    ],
    "sg:phone":"+1 704 394 3341",
    "sg:postcode":"28208",
    "sg:province":"NC",
    "sg:tags":[
        "steel",
        "center"
    ],
    "wof:name":"Precision Steel Wrhs Inc-Chrlt",
    "wof:placetype":"venue"
},
  "geometry": {"coordinates":[-80.906886,35.24087],"type":"Point"}
}