{
  "type": "Feature",
  "properties": {
    "iso:country":"US",
    "sg:address":"2215 Wyngate Dr",
    "sg:city":"Hillsborough",
    "sg:classifiers":[
        {
            "category":"Professional",
            "type":"Services"
        }
    ],
    "sg:phone":"+1 919 644 1789",
    "sg:postcode":"27278",
    "sg:province":"NC",
    "wof:name":"Jeffrey Evarts",
    "wof:placetype":"venue"
},
  "geometry": {"coordinates":[-79.069345,36.051277],"type":"Point"}
}