{
  "type": "Feature",
  "properties": {
    "iso:country":"US",
    "sg:address":"3300 Cessna Rd",
    "sg:city":"Charlotte",
    "sg:classifiers":[
        {
            "category":"Shopping",
            "subcategory":"Crafts & Fabrics",
            "type":"Retail Goods"
        }
    ],
    "sg:phone":"+1 704 423 9471",
    "sg:postcode":"28208",
    "sg:province":"NC",
    "sg:tags":[
        "sewing"
    ],
    "wof:name":"Novelty Yarn Inc",
    "wof:placetype":"venue"
},
  "geometry": {"coordinates":[-80.932496,35.195504],"type":"Point"}
}