{
  "type": "Feature",
  "properties": {
    "addr:full":"3314 State Hwy 42 Bus Wilson NC 27893",
    "addr:housenumber":"3314",
    "addr:postcode":"27893",
    "addr:street":"State Hwy 42 Bus",
    "iso:country":"US",
    "sg:address":"3314 State Hwy 42 Bus",
    "sg:city":"Wilson",
    "sg:classifiers":[
        {
            "category":"Building & Trades",
            "subcategory":"Equipment Rental",
            "type":"Services"
        }
    ],
    "sg:phone":"+1   ",
    "sg:postcode":"27893",
    "sg:province":"NC",
    "wof:name":"Fortson John",
    "wof:placetype":"venue"
},
  "geometry": {"coordinates":[-77.91439099999999,35.753497],"type":"Point"}
}