{
  "type": "Feature",
  "properties": {
    "addr:full":"601 Canal Dr Carolina Beach NC 28428",
    "addr:housenumber":"601",
    "addr:postcode":"28428",
    "addr:street":"Canal Dr",
    "iso:country":"US",
    "sg:address":"601 Canal Dr",
    "sg:city":"Carolina Beach",
    "sg:classifiers":[
        {
            "category":"Building & Trades",
            "subcategory":"Construction",
            "type":"Services"
        }
    ],
    "sg:phone":"+1 910 458 5376",
    "sg:postcode":"28428",
    "sg:province":"NC",
    "sg:tags":[
        "house"
    ],
    "wof:name":"Jimmy W Coble",
    "wof:placetype":"venue"
},
  "geometry": {"coordinates":[-77.889853,34.042162],"type":"Point"}
}