{
  "type": "Feature",
  "properties": {
    "iso:country":"US",
    "sg:address":"9004 Brimberry Ct",
    "sg:city":"Charlotte",
    "sg:classifiers":[
        {
            "category":"Professional",
            "subcategory":"Art Services",
            "type":"Services"
        }
    ],
    "sg:phone":"+1 704 399 0383",
    "sg:postcode":"28216",
    "sg:province":"NC",
    "sg:tags":[
        "commercial",
        "graphic",
        "design",
        "designer"
    ],
    "wof:name":"N Motion Graphic Design Inc",
    "wof:placetype":"venue"
},
  "geometry": {"coordinates":[-80.86827099999999,35.346648],"type":"Point"}
}