{
  "type": "Feature",
  "properties": {
    "iso:country":"US",
    "sg:address":"310 Ricks Rd",
    "sg:city":"Selma",
    "sg:classifiers":[
        {
            "category":"Freight",
            "type":"Transportation"
        }
    ],
    "sg:phone":"+1 919 965 4636",
    "sg:postcode":"27576",
    "sg:province":"NC",
    "sg:tags":[
        "operator",
        "trucking"
    ],
    "wof:name":"Kelly Mobile Home Moving",
    "wof:placetype":"venue"
},
  "geometry": {"coordinates":[-78.29116399999999,35.524831],"type":"Point"}
}