{
  "type": "Feature",
  "properties": {
    "addr:full":"2057 Newton Dr Statesville NC 28677",
    "addr:housenumber":"2057",
    "addr:postcode":"28677",
    "addr:street":"Newton Dr",
    "iso:country":"US",
    "sg:address":"2057 Newton Dr",
    "sg:city":"Statesville",
    "sg:classifiers":[
        {
            "category":"Manufacturing",
            "subcategory":"Retail Goods",
            "type":"Manufacturing & Wholesale Goods"
        }
    ],
    "sg:phone":"+1 704 883 8484",
    "sg:postcode":"28677",
    "sg:province":"NC",
    "sg:tags":[
        "assembly",
        "fabricating"
    ],
    "wof:name":"Quality Assemblers & Prdctn",
    "wof:placetype":"venue"
},
  "geometry": {"coordinates":[-80.92051600000001,35.782202],"type":"Point"}
}