{
  "type": "Feature",
  "properties": {
    "addr:full":"835 Highland Ave SE Hickory NC 28602",
    "addr:housenumber":"835",
    "addr:postcode":"28602",
    "addr:street":"Highland Ave Se",
    "iso:country":"US",
    "sg:address":"835 Highland Ave SE",
    "sg:city":"Hickory",
    "sg:classifiers":[
        {
            "category":"Professional",
            "subcategory":"Employment Agencies",
            "type":"Services"
        }
    ],
    "sg:phone":"+1 828 324 2020",
    "sg:postcode":"28602",
    "sg:province":"NC",
    "sg:tags":[
        "help",
        "contractor"
    ],
    "sg:website":"www.mrihky.com",
    "wof:name":"Management Recruiters Intl",
    "wof:placetype":"venue"
},
  "geometry": {"coordinates":[-81.327175,35.734452],"type":"Point"}
}