{
  "type": "Feature",
  "properties": {
    "iso:country":"US",
    "sg:address":"1235 Old Ranger Rd",
    "sg:city":"Murphy",
    "sg:classifiers":[
        {
            "category":"Wholesale",
            "subcategory":"Groceries",
            "type":"Manufacturing & Wholesale Goods"
        }
    ],
    "sg:phone":"+1 828 837 2126",
    "sg:postcode":"28906",
    "sg:province":"NC",
    "sg:tags":[
        "grocer"
    ],
    "wof:name":"H T Hackney Co",
    "wof:placetype":"venue"
},
  "geometry": {"coordinates":[-84.054897,35.072495],"type":"Point"}
}