{
  "type": "Feature",
  "properties": {
    "addr:full":"2409 Guess Rd Durham NC 27705",
    "addr:housenumber":"2409",
    "addr:postcode":"27705",
    "addr:street":"Guess Rd",
    "iso:country":"US",
    "sg:address":"2409 Guess Rd",
    "sg:city":"Durham",
    "sg:classifiers":[
        {
            "category":"Education",
            "subcategory":"Dance Studio",
            "type":"Public Place"
        }
    ],
    "sg:phone":"+1 919 539 7513",
    "sg:postcode":"27705",
    "sg:province":"NC",
    "sg:tags":[
        "instruction",
        "dancing"
    ],
    "wof:name":"Carolina Dancesport Inc",
    "wof:placetype":"venue"
},
  "geometry": {"coordinates":[-78.92324499999999,36.026797],"type":"Point"}
}