{
  "type": "Feature",
  "properties": {
    "iso:country":"US",
    "sg:address":"293 Stanford Church Rd",
    "sg:city":"Siloam",
    "sg:classifiers":[
        {
            "category":"Building & Trades",
            "subcategory":"Electrical",
            "type":"Services"
        }
    ],
    "sg:phone":"+1 336 374 2979",
    "sg:postcode":"27047",
    "sg:province":"NC",
    "sg:tags":[
        "electrical",
        "contractor"
    ],
    "wof:name":"Hfj Electrical Services",
    "wof:placetype":"venue"
},
  "geometry": {"coordinates":[-80.57835,36.347856],"type":"Point"}
}