{
  "type": "Feature",
  "properties": {
    "iso:country":"US",
    "sg:address":"130 Glory Dr",
    "sg:city":"Kings Mountain",
    "sg:classifiers":[
        {
            "category":"Organizations",
            "subcategory":"Religious Organization",
            "type":"Services"
        }
    ],
    "sg:phone":"+1   ",
    "sg:postcode":"28086",
    "sg:province":"NC",
    "wof:name":"Bostic Berry D",
    "wof:placetype":"venue"
},
  "geometry": {"coordinates":[-81.39037500000001,35.17066],"type":"Point"}
}