{
  "type": "Feature",
  "properties": {
    "addr:full":"9122 Magnolia Estates Dr Cornelius NC 28031",
    "addr:housenumber":"9122",
    "addr:postcode":"28031",
    "addr:street":"Magnolia Estates Dr",
    "iso:country":"US",
    "sg:address":"9122 Magnolia Estates Dr",
    "sg:city":"Cornelius",
    "sg:classifiers":[
        {
            "category":"Organizations",
            "subcategory":"Non-profit Organization",
            "type":"Services"
        }
    ],
    "sg:phone":"+1 704 892 3415",
    "sg:postcode":"28031",
    "sg:province":"NC",
    "sg:tags":[
        "fund",
        "counselor",
        "raising"
    ],
    "wof:name":"KBCG",
    "wof:placetype":"venue"
},
  "geometry": {"coordinates":[-80.887006,35.474113],"type":"Point"}
}