{
  "type": "Feature",
  "properties": {
    "iso:country":"US",
    "sg:address":"1605 W Ehringhaus St",
    "sg:city":"Elizabeth City",
    "sg:classifiers":[
        {
            "category":"Home & Garden",
            "subcategory":"Building Materials",
            "type":"Retail Goods"
        }
    ],
    "sg:phone":"+1 252 331 6160",
    "sg:postcode":"27909",
    "sg:province":"NC",
    "wof:name":"Lowes",
    "wof:placetype":"venue"
},
  "geometry": {"coordinates":[-76.245603,36.292725],"type":"Point"}
}