{
  "type": "Feature",
  "properties": {
    "addr:full":"1571 US Hwy 70 W Garner NC 27529",
    "addr:housenumber":"1571",
    "addr:postcode":"27529",
    "addr:street":"Us Hwy 70 W",
    "iso:country":"US",
    "sg:address":"1571 US Hwy 70 W",
    "sg:city":"Garner",
    "sg:classifiers":[
        {
            "category":"Shopping",
            "subcategory":"Pharmacy",
            "type":"Retail Goods"
        }
    ],
    "sg:phone":"+1 919 772 3167",
    "sg:postcode":"27529",
    "sg:province":"NC",
    "sg:website":"www.cvs.com",
    "wof:name":"CVS Pharmacy",
    "wof:placetype":"venue"
},
  "geometry": {"coordinates":[-78.644614,35.722103],"type":"Point"}
}