{
  "type": "Feature",
  "properties": {
    "iso:country":"US",
    "sg:address":"202 Savanna Ct",
    "sg:city":"Hubert",
    "sg:classifiers":[
        {
            "category":"Education",
            "subcategory":"School",
            "type":"Public Place"
        }
    ],
    "sg:phone":"+1 910 326 9047",
    "sg:postcode":"28539",
    "sg:province":"NC",
    "wof:name":"St Andrews Presbt College",
    "wof:placetype":"venue"
},
  "geometry": {"coordinates":[-77.214883,34.68733],"type":"Point"}
}