{
  "type": "Feature",
  "properties": {
    "iso:country":"US",
    "sg:address":"42 Professional Dr",
    "sg:city":"Havelock",
    "sg:classifiers":[
        {
            "category":"Health Services",
            "subcategory":"Health Practitioner",
            "type":"Services"
        }
    ],
    "sg:phone":"+1 252 444 4022",
    "sg:postcode":"28580",
    "sg:province":"NC",
    "sg:tags":[
        "dietitian"
    ],
    "wof:name":"Contemporary Nutrition",
    "wof:placetype":"venue"
},
  "geometry": {"coordinates":[-77.680896,35.454171],"type":"Point"}
}