{
  "type": "Feature",
  "properties": {
    "iso:country":"US",
    "sg:address":"4625 Hillsborough Rd",
    "sg:city":"Durham",
    "sg:classifiers":[
        {
            "category":"Bars & Pubs",
            "type":"Food & Drink"
        }
    ],
    "sg:menulink":"http://www.allmenus.com/nc/durham/140794-bennett-pointe-grill--bar/menu/",
    "sg:phone":"+1 919 382 9341",
    "sg:postcode":"27705",
    "sg:province":"NC",
    "sg:tags":[
        "afghan"
    ],
    "wof:name":"Bennett Pointe Grill & Bar",
    "wof:placetype":"venue"
},
  "geometry": {"coordinates":[-78.97857999999999,36.033003],"type":"Point"}
}