{
  "type": "Feature",
  "properties": {
    "iso:country":"US",
    "sg:address":"261 Rolling Hill Rd",
    "sg:city":"Mooresville",
    "sg:classifiers":[
        {
            "category":"Autos & Motor Vehicles",
            "subcategory":"Automobile Sales",
            "type":"Retail Goods"
        },
        {
            "category":"Manufacturing",
            "subcategory":"Motor Vehicles & Parts",
            "type":"Manufacturing & Wholesale Goods"
        }
    ],
    "sg:phone":"+1 704 660 9566",
    "sg:postcode":"28117",
    "sg:province":"NC",
    "sg:tags":[
        "body",
        "performance",
        "race",
        "dealer",
        "mfg"
    ],
    "wof:name":"Hutcherson Pagan Enterprises",
    "wof:placetype":"venue"
},
  "geometry": {"coordinates":[-80.860699,35.585618],"type":"Point"}
}