{
  "type": "Feature",
  "properties": {
    "iso:country":"US",
    "sg:address":"204 S Main St",
    "sg:city":"Dobson",
    "sg:classifiers":[
        {
            "category":"Organizations",
            "subcategory":"Religious Organization",
            "type":"Services"
        }
    ],
    "sg:phone":"+1 336 356 8621",
    "sg:postcode":"27017",
    "sg:province":"NC",
    "sg:tags":[
        "church"
    ],
    "wof:name":"Dobson United Methodist Chr",
    "wof:placetype":"venue"
},
  "geometry": {"coordinates":[-80.722115,36.394739],"type":"Point"}
}