{
  "type": "Feature",
  "properties": {
    "iso:country":"US",
    "sg:address":"2 Country Spring Dr",
    "sg:city":"Asheville",
    "sg:classifiers":[
        {
            "category":"Professional",
            "type":"Services"
        }
    ],
    "sg:phone":"+1 828 645 8846",
    "sg:postcode":"28804",
    "sg:province":"NC",
    "sg:tags":[
        "establishment"
    ],
    "wof:name":"Hyder Way Concrete",
    "wof:placetype":"venue"
},
  "geometry": {"coordinates":[-82.62025800000001,35.633302],"type":"Point"}
}