{
  "type": "Feature",
  "properties": {
    "iso:country":"US",
    "sg:address":"2560 Onslow Dr",
    "sg:city":"Jacksonville",
    "sg:classifiers":[
        {
            "category":"Shopping",
            "subcategory":"Used Merchandise",
            "type":"Retail Goods"
        }
    ],
    "sg:phone":"+1 910 938 1505",
    "sg:postcode":"28540",
    "sg:province":"NC",
    "sg:tags":[
        "pawnbroker"
    ],
    "wof:name":"Mr B's Jewelry & Pawn",
    "wof:placetype":"venue"
},
  "geometry": {"coordinates":[-77.419096,34.764371],"type":"Point"}
}