{
  "type": "Feature",
  "properties": {
    "iso:country":"US",
    "sg:address":"5389 State Hwy 33 W",
    "sg:city":"Tarboro",
    "sg:classifiers":[
        {
            "category":"Farming",
            "subcategory":"Farm",
            "type":"Manufacturing & Wholesale Goods"
        }
    ],
    "sg:phone":"+1 252 758 1962",
    "sg:postcode":"27886",
    "sg:province":"NC",
    "sg:tags":[
        "crop",
        "general"
    ],
    "wof:name":"Tucker Farms",
    "wof:placetype":"venue"
},
  "geometry": {"coordinates":[-77.502972,35.737406],"type":"Point"}
}