{
  "type": "Feature",
  "properties": {
    "iso:country":"US",
    "sg:address":"7319 Windaliere Dr",
    "sg:city":"Cornelius",
    "sg:classifiers":[
        {
            "category":"Real Estate",
            "subcategory":"Developer",
            "type":"Services"
        }
    ],
    "sg:phone":"+1 704 895 9850",
    "sg:postcode":"28031",
    "sg:province":"NC",
    "wof:name":"Signature Development LLC",
    "wof:placetype":"venue"
},
  "geometry": {"coordinates":[-80.903313,35.44186],"type":"Point"}
}