{
  "type": "Feature",
  "properties": {
    "addr:full":"957 S Salisbury St Lexington NC 27292",
    "addr:housenumber":"957",
    "addr:postcode":"27292",
    "addr:street":"S Salisbury St",
    "iso:country":"US",
    "sg:address":"957 S Salisbury St",
    "sg:city":"Lexington",
    "sg:classifiers":[
        {
            "category":"Health Services",
            "subcategory":"Clinic",
            "type":"Services"
        }
    ],
    "sg:phone":"+1 336 249 7813",
    "sg:postcode":"27292",
    "sg:province":"NC",
    "sg:tags":[
        "home"
    ],
    "wof:name":"Care South Homecare Pros",
    "wof:placetype":"venue"
},
  "geometry": {"coordinates":[-80.26265600000001,35.813968],"type":"Point"}
}