{
  "type": "Feature",
  "properties": {
    "addr:full":"617 Flynn St Eden NC 27288",
    "addr:housenumber":"617",
    "addr:postcode":"27288",
    "addr:street":"Flynn St",
    "iso:country":"US",
    "sg:address":"617 Flynn St",
    "sg:city":"Eden",
    "sg:classifiers":[
        {
            "category":"Real Estate",
            "subcategory":"Real Estate Agent",
            "type":"Services"
        }
    ],
    "sg:phone":"+1 336 623 3475",
    "sg:postcode":"27288",
    "sg:province":"NC",
    "wof:name":"Janice Bickford Realty Inc",
    "wof:placetype":"venue"
},
  "geometry": {"coordinates":[-79.76083800000001,36.512405],"type":"Point"}
}