{
  "type": "Feature",
  "properties": {
    "iso:country":"US",
    "sg:address":"9440 John White Rd",
    "sg:city":"Midland",
    "sg:classifiers":[
        {
            "category":"Building & Trades",
            "subcategory":"Plumbing",
            "type":"Services"
        }
    ],
    "sg:phone":"+1 704 782 0176",
    "sg:postcode":"28107",
    "sg:province":"NC",
    "sg:tags":[
        "contractor"
    ],
    "wof:name":"Brindle Plumbing Co",
    "wof:placetype":"venue"
},
  "geometry": {"coordinates":[-80.529618,35.288171],"type":"Point"}
}