{
  "type": "Feature",
  "properties": {
    "addr:full":"146 Ridgeford Dr Broadway NC 27505",
    "addr:housenumber":"146",
    "addr:postcode":"27505",
    "addr:street":"Ridgeford Dr",
    "iso:country":"US",
    "sg:address":"146 Ridgeford Dr",
    "sg:city":"Broadway",
    "sg:classifiers":[
        {
            "category":"Manufacturing",
            "subcategory":"Metals",
            "type":"Manufacturing & Wholesale Goods"
        }
    ],
    "sg:phone":"+1 919 258 6918",
    "sg:postcode":"27505",
    "sg:province":"NC",
    "sg:tags":[
        "cutlery",
        "mfg"
    ],
    "wof:name":"Celtic Trader",
    "wof:placetype":"venue"
},
  "geometry": {"coordinates":[-79.011743,35.444119],"type":"Point"}
}