{
  "type": "Feature",
  "properties": {
    "iso:country":"US",
    "sg:address":"1724 Mount Olive Church Rd",
    "sg:city":"Gastonia",
    "sg:classifiers":[
        {
            "category":"Manufacturing",
            "subcategory":"Textiles",
            "type":"Manufacturing & Wholesale Goods"
        }
    ],
    "sg:phone":"+1 704 854 9187",
    "sg:postcode":"28052",
    "sg:province":"NC",
    "sg:tags":[
        "mill",
        "supply"
    ],
    "wof:name":"Consolidated Textile Svc Inc",
    "wof:placetype":"venue"
},
  "geometry": {"coordinates":[-81.227816,35.284865],"type":"Point"}
}