{
  "type": "Feature",
  "properties": {
    "addr:full":"5565 W Market St Greensboro NC 27409",
    "addr:housenumber":"5565",
    "addr:postcode":"27409",
    "addr:street":"W Market St",
    "iso:country":"US",
    "sg:address":"5565 W Market St",
    "sg:city":"Greensboro",
    "sg:classifiers":[
        {
            "category":"Personal",
            "type":"Services"
        }
    ],
    "sg:phone":"+1   ",
    "sg:postcode":"27409",
    "sg:province":"NC",
    "wof:name":"Redis Media Group",
    "wof:placetype":"venue"
},
  "geometry": {"coordinates":[-79.888581,36.074346],"type":"Point"}
}