{
  "type": "Feature",
  "properties": {
    "iso:country":"US",
    "sg:address":"119 Pigeon St",
    "sg:city":"Waynesville",
    "sg:classifiers":[
        {
            "category":"Health Services",
            "subcategory":"Chiropractor",
            "type":"Services"
        }
    ],
    "sg:phone":"+1   ",
    "sg:postcode":"28786",
    "sg:province":"NC",
    "wof:name":"Baroody Chiropractic Care",
    "wof:placetype":"venue"
},
  "geometry": {"coordinates":[-82.98707400000001,35.487447],"type":"Point"}
}