{
  "type": "Feature",
  "properties": {
    "addr:full":"675 Fern Trl Waynesville NC 28786",
    "addr:housenumber":"675",
    "addr:postcode":"28786",
    "addr:street":"Fern Trl",
    "iso:country":"US",
    "sg:address":"675 Fern Trl",
    "sg:city":"Waynesville",
    "sg:classifiers":[
        {
            "category":"Professional",
            "type":"Services"
        }
    ],
    "sg:phone":"+1   ",
    "sg:postcode":"28786",
    "sg:province":"NC",
    "wof:name":"Angels Decorator Service",
    "wof:placetype":"venue"
},
  "geometry": {"coordinates":[-83.07325,35.443645],"type":"Point"}
}