{
  "type": "Feature",
  "properties": {
    "addr:full":"6315 Old Mendenhall Rd Archdale NC 27263",
    "addr:housenumber":"6315",
    "addr:postcode":"27263",
    "addr:street":"Old Mendenhall Rd",
    "iso:country":"US",
    "sg:address":"6315 Old Mendenhall Rd",
    "sg:city":"Archdale",
    "sg:classifiers":[
        {
            "category":"Organizations",
            "subcategory":"Religious Organization",
            "type":"Services"
        }
    ],
    "sg:phone":"+1 336 431 3296",
    "sg:postcode":"27263",
    "sg:province":"NC",
    "sg:tags":[
        "church"
    ],
    "wof:name":"Church Of Jesus",
    "wof:placetype":"venue"
},
  "geometry": {"coordinates":[-80.01473,35.91718],"type":"Point"}
}