{
  "type": "Feature",
  "properties": {
    "addr:full":"1500 Garner Rd Raleigh NC 27610",
    "addr:housenumber":"1500",
    "addr:postcode":"27610",
    "addr:street":"Garner Rd",
    "iso:country":"US",
    "sg:address":"1500 Garner Rd",
    "sg:city":"Raleigh",
    "sg:classifiers":[
        {
            "category":"Food & Beverages",
            "subcategory":"Meat & Fish",
            "type":"Retail Goods"
        },
        {
            "category":"Wholesale",
            "subcategory":"Groceries",
            "type":"Manufacturing & Wholesale Goods"
        },
        {
            "category":"Wholesale",
            "subcategory":"Meat",
            "type":"Manufacturing & Wholesale Goods"
        }
    ],
    "sg:phone":"+1 919 755 2262",
    "sg:postcode":"27610",
    "sg:province":"NC",
    "sg:tags":[
        "product"
    ],
    "wof:name":"Faal Specialty Food Dist Co",
    "wof:placetype":"venue"
},
  "geometry": {"coordinates":[-78.631416,35.76045],"type":"Point"}
}