{
  "type": "Feature",
  "properties": {
    "addr:full":"5950 US Hwy 29 Bus Reidsville NC 27320",
    "addr:housenumber":"5950",
    "addr:postcode":"27320",
    "addr:street":"Us Hwy 29 Bus",
    "iso:country":"US",
    "sg:address":"5950 US Hwy 29 Bus",
    "sg:city":"Reidsville",
    "sg:classifiers":[
        {
            "category":"Shopping",
            "subcategory":"Computers & Home Electronics",
            "type":"Retail Goods"
        }
    ],
    "sg:phone":"+1 336 349 3969",
    "sg:postcode":"27320",
    "sg:province":"NC",
    "sg:tags":[
        "repair"
    ],
    "wof:name":"Johnson TV Service",
    "wof:placetype":"venue"
},
  "geometry": {"coordinates":[-79.64507399999999,36.389909],"type":"Point"}
}