{
  "type": "Feature",
  "properties": {
    "addr:full":"9939 Lee St Pineville NC 28134",
    "addr:housenumber":"9939",
    "addr:postcode":"28134",
    "addr:street":"Lee St",
    "iso:country":"US",
    "sg:address":"9939 Lee St",
    "sg:city":"Pineville",
    "sg:classifiers":[
        {
            "category":"Shopping",
            "subcategory":"Tobacco",
            "type":"Retail Goods"
        }
    ],
    "sg:phone":"+1 704 889 0161",
    "sg:postcode":"28134",
    "sg:province":"NC",
    "sg:tags":[
        "cigarette",
        "product",
        "cigar",
        "dealer"
    ],
    "wof:name":"Smokers Depot",
    "wof:placetype":"venue"
},
  "geometry": {"coordinates":[-80.88449900000001,35.084662],"type":"Point"}
}