{
  "type": "Feature",
  "properties": {
    "iso:country":"US",
    "sg:address":"513 Faith Chapel Rd",
    "sg:city":"Thomasville",
    "sg:classifiers":[
        {
            "category":"Organizations",
            "subcategory":"Religious Organization",
            "type":"Services"
        }
    ],
    "sg:phone":"+1   ",
    "sg:postcode":"27360",
    "sg:province":"NC",
    "wof:name":"Allegheny Wslyan Mthdst Connec",
    "wof:placetype":"venue"
},
  "geometry": {"coordinates":[-80.118233,35.816359],"type":"Point"}
}