{
  "type": "Feature",
  "properties": {
    "addr:full":"1207 Hazel St Durham NC 27701",
    "addr:housenumber":"1207",
    "addr:postcode":"27701",
    "addr:street":"Hazel St",
    "iso:country":"US",
    "sg:address":"1207 Hazel St",
    "sg:city":"Durham",
    "sg:classifiers":[
        {
            "category":"Professional",
            "subcategory":"Management & Consulting",
            "type":"Services"
        }
    ],
    "sg:phone":"+1   ",
    "sg:postcode":"27701",
    "sg:province":"NC",
    "sg:tags":[
        "business"
    ],
    "wof:name":"Edwards & Associates",
    "wof:placetype":"venue"
},
  "geometry": {"coordinates":[-78.888868,36.000317],"type":"Point"}
}