{
  "type": "Feature",
  "properties": {
    "iso:country":"US",
    "sg:address":"1415 Cedar Branch Ct",
    "sg:city":"Wake Forest",
    "sg:classifiers":[
        {
            "category":"Retail",
            "subcategory":"Animal Services",
            "type":"Services"
        }
    ],
    "sg:phone":"+1 919 570 0330",
    "sg:postcode":"27587",
    "sg:province":"NC",
    "sg:tags":[
        "shelter"
    ],
    "wof:name":"Pawsitive Touch Pet Sitting",
    "wof:placetype":"venue"
},
  "geometry": {"coordinates":[-78.52477500000001,35.959717],"type":"Point"}
}