{
  "type": "Feature",
  "properties": {
    "addr:full":"219 S Wilmington St Raleigh NC 27601",
    "addr:housenumber":"219",
    "addr:postcode":"27601",
    "addr:street":"S Wilmington St",
    "iso:country":"US",
    "sg:address":"219 S Wilmington St",
    "sg:city":"Raleigh",
    "sg:classifiers":[
        {
            "category":"Professional",
            "subcategory":"Management & Consulting",
            "type":"Services"
        }
    ],
    "sg:phone":"+1 919 828 4110",
    "sg:postcode":"27601",
    "sg:province":"NC",
    "sg:tags":[
        "personnel",
        "consultant"
    ],
    "wof:name":"Power Personnel",
    "wof:placetype":"venue"
},
  "geometry": {"coordinates":[-78.638143,35.778128],"type":"Point"}
}