{
  "type": "Feature",
  "properties": {
    "iso:country":"US",
    "sg:address":"2822 Little Windfall Rd",
    "sg:city":"Lansing",
    "sg:classifiers":[
        {
            "category":"Building & Trades",
            "subcategory":"Construction",
            "type":"Services"
        }
    ],
    "sg:phone":"+1 336 384 4590",
    "sg:postcode":"28643",
    "sg:province":"NC",
    "sg:tags":[
        "contractor"
    ],
    "wof:name":"High Country Contractors LLC",
    "wof:placetype":"venue"
},
  "geometry": {"coordinates":[-81.576044,36.561764],"type":"Point"}
}