{
  "type": "Feature",
  "properties": {
    "addr:full":"411 Pitts School Rd SW Concord NC 28027",
    "addr:housenumber":"411",
    "addr:postcode":"28027",
    "addr:street":"Pitts School Rd Sw",
    "iso:country":"US",
    "sg:address":"411 Pitts School Rd SW",
    "sg:city":"Concord",
    "sg:classifiers":[
        {
            "category":"Organizations",
            "subcategory":"Community Association",
            "type":"Services"
        }
    ],
    "sg:phone":"+1   ",
    "sg:postcode":"28027",
    "sg:province":"NC",
    "sg:tags":[
        "profit"
    ],
    "wof:name":"Cannon Memorial YMCA Inc",
    "wof:placetype":"venue"
},
  "geometry": {"coordinates":[-80.65896600000001,35.35413],"type":"Point"}
}