{
  "type": "Feature",
  "properties": {
    "iso:country":"US",
    "sg:address":"27 Blake St",
    "sg:city":"Asheville",
    "sg:classifiers":[
        {
            "category":"Professional",
            "type":"Services"
        },
        {
            "category":"Retail",
            "subcategory":"Repair Shop",
            "type":"Services"
        }
    ],
    "sg:phone":"+1 828 254 0549",
    "sg:postcode":"28801",
    "sg:province":"NC",
    "sg:tags":[
        "ironwork"
    ],
    "wof:name":"Sculptures By Berry Bate",
    "wof:placetype":"venue"
},
  "geometry": {"coordinates":[-82.560987,35.600434],"type":"Point"}
}