{
  "type": "Feature",
  "properties": {
    "addr:full":"3216 Valencia Ter Charlotte NC 28211",
    "addr:housenumber":"3216",
    "addr:postcode":"28211",
    "addr:street":"Valencia Ter",
    "iso:country":"US",
    "sg:address":"3216 Valencia Ter",
    "sg:city":"Charlotte",
    "sg:classifiers":[
        {
            "category":"Social Services",
            "type":"Services"
        },
        {
            "category":"Personal",
            "type":"Services"
        }
    ],
    "sg:phone":"+1 704 560 2911",
    "sg:postcode":"28211",
    "sg:province":"NC",
    "sg:tags":[
        "family",
        "individual",
        "marriage",
        "child",
        "counseling",
        "counselor"
    ],
    "sg:website":"http://www.karenfpierce.com",
    "wof:name":"Integrative Heart Healing Center",
    "wof:placetype":"venue"
},
  "geometry": {"coordinates":[-80.80754899999999,35.149918],"type":"Point"}
}