{
  "type": "Feature",
  "properties": {
    "addr:full":"128 Pet Burwell Rd Warrenton NC 27589",
    "addr:postcode":"27589",
    "addr:street":"Burwell Rd",
    "iso:country":"US",
    "sg:address":"128 Pet Burwell Rd",
    "sg:city":"Warrenton",
    "sg:classifiers":[
        {
            "category":"Travel",
            "subcategory":"Hotels & Motels",
            "type":"Entertainment"
        }
    ],
    "sg:phone":"+1 252 257 6055",
    "sg:postcode":"27589",
    "sg:province":"NC",
    "sg:tags":[
        "breakfast",
        "accommodation",
        "bed"
    ],
    "wof:name":"Magnolia Manor Plantation Bed",
    "wof:placetype":"venue"
},
  "geometry": {"coordinates":[-78.18206600000001,36.36359],"type":"Point"}
}