{
  "type": "Feature",
  "properties": {
    "addr:full":"10129 Mount Holly Rd Charlotte NC 28214",
    "addr:housenumber":"10129",
    "addr:postcode":"28214",
    "addr:street":"Mount Holly Rd",
    "iso:country":"US",
    "sg:address":"10129 Mount Holly Rd",
    "sg:city":"Charlotte",
    "sg:classifiers":[
        {
            "category":"Wholesale",
            "subcategory":"Durable Goods & Equipment",
            "type":"Manufacturing & Wholesale Goods"
        }
    ],
    "sg:phone":"+1 704 393 1474",
    "sg:postcode":"28214",
    "sg:province":"NC",
    "sg:tags":[
        "representative",
        "manufacturer"
    ],
    "sg:website":"www.eysco.com",
    "wof:name":"Ed Young Sales Co",
    "wof:placetype":"venue"
},
  "geometry": {"coordinates":[-80.97380800000001,35.293698],"type":"Point"}
}