{
  "type": "Feature",
  "properties": {
    "iso:country":"US",
    "sg:address":"20 Oakleaf Ln",
    "sg:city":"Arden",
    "sg:classifiers":[
        {
            "category":"Food & Beverages",
            "subcategory":"Bakery",
            "type":"Retail Goods"
        }
    ],
    "sg:phone":"+1 828 684 4770",
    "sg:postcode":"28704",
    "sg:province":"NC",
    "wof:name":"No Nuts Bakery",
    "wof:placetype":"venue"
},
  "geometry": {"coordinates":[-82.500997,35.473376],"type":"Point"}
}