{
  "type": "Feature",
  "properties": {
    "iso:country":"US",
    "sg:address":"1 Queensland Ct",
    "sg:city":"Durham",
    "sg:classifiers":[
        {
            "category":"Building & Trades",
            "subcategory":"Construction",
            "type":"Services"
        }
    ],
    "sg:phone":"+1 919 477 9985",
    "sg:postcode":"27712",
    "sg:province":"NC",
    "sg:tags":[
        "house",
        "builder",
        "home"
    ],
    "wof:name":"Saint Lawrence Homes Inc",
    "wof:placetype":"venue"
},
  "geometry": {"coordinates":[-78.935847,36.084303],"type":"Point"}
}