{
  "type": "Feature",
  "properties": {
    "addr:full":"1505 S Blount St Raleigh NC 27601",
    "addr:housenumber":"1505",
    "addr:postcode":"27601",
    "addr:street":"S Blount St",
    "iso:country":"US",
    "sg:address":"1505 S Blount St",
    "sg:city":"Raleigh",
    "sg:classifiers":[
        {
            "category":"Wholesale",
            "subcategory":"Construction Materials",
            "type":"Manufacturing & Wholesale Goods"
        }
    ],
    "sg:phone":"+1 919 833 0911",
    "sg:postcode":"27601",
    "sg:province":"NC",
    "sg:tags":[
        "concrete",
        "form"
    ],
    "wof:name":"Form Tech Concrete Forms Inc",
    "wof:placetype":"venue"
},
  "geometry": {"coordinates":[-78.637321,35.762396],"type":"Point"}
}