{
  "type": "Feature",
  "properties": {
    "iso:country":"US",
    "sg:address":"2316 Commonwealth Ave",
    "sg:city":"Charlotte",
    "sg:classifiers":[
        {
            "category":"Retail",
            "subcategory":"Auto Repair",
            "type":"Services"
        }
    ],
    "sg:phone":"+1 704 724 0712",
    "sg:postcode":"28205",
    "sg:province":"NC",
    "sg:tags":[
        "repairing",
        "automobile"
    ],
    "wof:name":"Star Automotive",
    "wof:placetype":"venue"
},
  "geometry": {"coordinates":[-80.80627200000001,35.215677],"type":"Point"}
}