{
  "type": "Feature",
  "properties": {
    "iso:country":"US",
    "sg:address":"5568 US Hwy 70",
    "sg:city":"Morehead City",
    "sg:classifiers":[
        {
            "category":"Home & Garden",
            "subcategory":"Carpets & Floor Coverings",
            "type":"Retail Goods"
        }
    ],
    "sg:phone":"+1 252 726 2023",
    "sg:postcode":"28557",
    "sg:province":"NC",
    "sg:tags":[
        "dealer",
        "rug"
    ],
    "wof:name":"Larry's Carpet One",
    "wof:placetype":"venue"
},
  "geometry": {"coordinates":[-76.83886699999999,34.749865],"type":"Point"}
}