{
  "type": "Feature",
  "properties": {
    "iso:country":"US",
    "sg:address":"1447 York Pl",
    "sg:city":"Burlington",
    "sg:classifiers":[
        {
            "category":"Manufacturing",
            "subcategory":"Tools & Machinery",
            "type":"Manufacturing & Wholesale Goods"
        }
    ],
    "sg:phone":"+1 336 584 5171",
    "sg:postcode":"27215",
    "sg:province":"NC",
    "sg:tags":[
        "physician",
        "surgeon"
    ],
    "wof:name":"Laboratory Corp-Amer Holdings",
    "wof:placetype":"venue"
},
  "geometry": {"coordinates":[-79.47978000000001,36.102441],"type":"Point"}
}