{
  "type": "Feature",
  "properties": {
    "addr:full":"2323 Hopecrest Dr Charlotte NC 28210",
    "addr:postcode":"2323;28210",
    "addr:street":"Hopecrest Dr",
    "iso:country":"US",
    "sg:address":"2323 Hopecrest Dr",
    "sg:city":"Charlotte",
    "sg:classifiers":[
        {
            "category":"Professional",
            "subcategory":"Management & Consulting",
            "type":"Services"
        }
    ],
    "sg:phone":"+1   ",
    "sg:postcode":"28210",
    "sg:province":"NC",
    "sg:tags":[
        "environmental"
    ],
    "wof:name":"Carolina Environmental Svcs",
    "wof:placetype":"venue"
},
  "geometry": {"coordinates":[-80.861254,35.1256],"type":"Point"}
}