{
  "type": "Feature",
  "properties": {
    "addr:full":"1780 Hobbton Hwy Clinton NC 28328",
    "addr:housenumber":"1780",
    "addr:postcode":"28328",
    "addr:street":"Hobbton Hwy",
    "iso:country":"US",
    "sg:address":"1780 Hobbton Hwy",
    "sg:city":"Clinton",
    "sg:classifiers":[
        {
            "category":"Autos & Motor Vehicles",
            "subcategory":"Automobile Sales",
            "type":"Retail Goods"
        }
    ],
    "sg:phone":"+1 910 590 2400",
    "sg:postcode":"28328",
    "sg:province":"NC",
    "wof:name":"S & S Auto Sales",
    "wof:placetype":"venue"
},
  "geometry": {"coordinates":[-78.327006,35.023493],"type":"Point"}
}