{
  "type": "Feature",
  "properties": {
    "addr:full":"401 Old Spartanburg Rd Hendersonville NC 28792",
    "addr:housenumber":"401",
    "addr:postcode":"28792",
    "addr:street":"Old Spartanburg Rd",
    "iso:country":"US",
    "sg:address":"401 Old Spartanburg Rd",
    "sg:city":"Hendersonville",
    "sg:classifiers":[
        {
            "category":"Manufacturing",
            "subcategory":"Tools & Machinery",
            "type":"Manufacturing & Wholesale Goods"
        }
    ],
    "sg:phone":"+1 828 698 8804",
    "sg:postcode":"28792",
    "sg:province":"NC",
    "sg:tags":[
        "machine",
        "shop"
    ],
    "wof:name":"Michael Merker Co",
    "wof:placetype":"venue"
},
  "geometry": {"coordinates":[-82.45727599999999,35.312723],"type":"Point"}
}