{
  "type": "Feature",
  "properties": {
    "addr:full":"3232 Kentland Ln Fuquay Varina NC 27526",
    "addr:housenumber":"3232",
    "addr:postcode":"27526",
    "addr:street":"Kentland Ln",
    "iso:country":"US",
    "sg:address":"3232 Kentland Ln",
    "sg:city":"Fuquay Varina",
    "sg:classifiers":[
        {
            "category":"Building & Trades",
            "subcategory":"Plumbing",
            "type":"Services"
        }
    ],
    "sg:phone":"+1 919 552 8495",
    "sg:postcode":"27526",
    "sg:province":"NC",
    "sg:tags":[
        "contractor"
    ],
    "wof:name":"USDA Aphis Code AC",
    "wof:placetype":"venue"
},
  "geometry": {"coordinates":[-78.748806,35.637579],"type":"Point"}
}