{
  "type": "Feature",
  "properties": {
    "addr:full":"7008 W Wt Harris Blvd Charlotte NC 28269",
    "addr:housenumber":"7008",
    "addr:postcode":"28269",
    "addr:street":"W Wt Harris Blvd",
    "iso:country":"US",
    "sg:address":"7008 W Wt Harris Blvd",
    "sg:city":"Charlotte",
    "sg:classifiers":[
        {
            "category":"Restaurant",
            "type":"Food & Drink"
        }
    ],
    "sg:menulink":"http://www.allmenus.com/nc/charlotte/158789-arbys/menu/",
    "sg:phone":"+1 704 599 8109",
    "sg:postcode":"28269",
    "sg:province":"NC",
    "sg:tags":[
        "burger",
        "american"
    ],
    "wof:name":"Arby's",
    "wof:placetype":"venue"
},
  "geometry": {"coordinates":[-80.844233,35.348357],"type":"Point"}
}