{
  "type": "Feature",
  "properties": {
    "iso:country":"US",
    "sg:address":"512 N Johnson St",
    "sg:city":"Monroe",
    "sg:classifiers":[
        {
            "category":"Wholesale",
            "subcategory":"Machinery & Supplies",
            "type":"Manufacturing & Wholesale Goods"
        }
    ],
    "sg:phone":"+1 704 289 8471",
    "sg:postcode":"28112",
    "sg:province":"NC",
    "sg:tags":[
        "equipment",
        "industrial"
    ],
    "sg:website":"www.priceequipment.com",
    "wof:name":"Price Equipment Co",
    "wof:placetype":"venue"
},
  "geometry": {"coordinates":[-80.558177,34.984465],"type":"Point"}
}