{
  "type": "Feature",
  "properties": {
    "addr:full":"200 W Hamlet St Pinetops NC 27864",
    "addr:housenumber":"200",
    "addr:postcode":"27864",
    "addr:street":"W Hamlet St",
    "iso:country":"US",
    "sg:address":"200 W Hamlet St",
    "sg:city":"Pinetops",
    "sg:classifiers":[
        {
            "category":"Restaurant",
            "type":"Food & Drink"
        }
    ],
    "sg:phone":"+1 252 827 2645",
    "sg:postcode":"27864",
    "sg:province":"NC",
    "wof:name":"Millies's Cafe",
    "wof:placetype":"venue"
},
  "geometry": {"coordinates":[-77.639939,35.792076],"type":"Point"}
}