{
  "type": "Feature",
  "properties": {
    "addr:full":"1109 Oakside Ct Raleigh NC 27609",
    "addr:housenumber":"1109",
    "addr:postcode":"27609",
    "addr:street":"Oakside Ct",
    "iso:country":"US",
    "sg:address":"1109 Oakside Ct",
    "sg:city":"Raleigh",
    "sg:classifiers":[
        {
            "category":"Personal",
            "subcategory":"Barber",
            "type":"Services"
        }
    ],
    "sg:phone":"+1 919 871 6363",
    "sg:postcode":"27609",
    "sg:province":"NC",
    "wof:name":"Barber Tammy",
    "wof:placetype":"venue"
},
  "geometry": {"coordinates":[-78.618028,35.868255],"type":"Point"}
}