{
  "type": "Feature",
  "properties": {
    "addr:full":"351 Summit Ct SE Concord NC 28025",
    "addr:housenumber":"351",
    "addr:postcode":"28025",
    "addr:street":"Summit Ct Se",
    "iso:country":"US",
    "sg:address":"351 Summit Ct SE",
    "sg:city":"Concord",
    "sg:classifiers":[
        {
            "category":"Wholesale",
            "subcategory":"Stationery",
            "type":"Manufacturing & Wholesale Goods"
        }
    ],
    "sg:phone":"+1 704 782 4553",
    "sg:postcode":"28025",
    "sg:province":"NC",
    "sg:tags":[
        "paper"
    ],
    "wof:name":"Hoyco",
    "wof:placetype":"venue"
},
  "geometry": {"coordinates":[-80.56236,35.409958],"type":"Point"}
}