{
  "type": "Feature",
  "properties": {
    "iso:country":"US",
    "sg:address":"400 Royster Ave",
    "sg:city":"Shelby",
    "sg:classifiers":[
        {
            "category":"Social Services",
            "subcategory":"Child Care",
            "type":"Services"
        }
    ],
    "sg:phone":"+1 704 471 2128",
    "sg:postcode":"28150",
    "sg:province":"NC",
    "wof:name":"Cleveland Family Svc",
    "wof:placetype":"venue"
},
  "geometry": {"coordinates":[-81.54915699999999,35.282294],"type":"Point"}
}