{
  "type": "Feature",
  "properties": {
    "addr:full":"3935 Brian Jordan Pl High Point NC 27265",
    "addr:housenumber":"3935",
    "addr:postcode":"27265",
    "addr:street":"Brian Jordan Pl",
    "iso:country":"US",
    "sg:address":"3935 Brian Jordan Pl",
    "sg:city":"High Point",
    "sg:classifiers":[
        {
            "category":"Professional",
            "subcategory":"Engineering",
            "type":"Services"
        }
    ],
    "sg:phone":"+1 336 812 8800",
    "sg:postcode":"27265",
    "sg:province":"NC",
    "sg:tags":[
        "engineer"
    ],
    "sg:website":"www.cptengineering.com",
    "wof:name":"CPT Engineering & Surveying",
    "wof:placetype":"venue"
},
  "geometry": {"coordinates":[-79.959835,36.032938],"type":"Point"}
}