{
  "type": "Feature",
  "properties": {
    "addr:full":"722 Warsaw Rd Clinton NC 28328",
    "addr:housenumber":"722",
    "addr:postcode":"28328",
    "addr:street":"Warsaw Rd",
    "iso:country":"US",
    "sg:address":"722 Warsaw Rd",
    "sg:city":"Clinton",
    "sg:classifiers":[
        {
            "category":"Freight",
            "type":"Transportation"
        }
    ],
    "sg:phone":"+1 910 299 0002",
    "sg:postcode":"28328",
    "sg:province":"NC",
    "sg:tags":[
        "warehouse",
        "public"
    ],
    "wof:name":"K & W Real Estate LLC",
    "wof:placetype":"venue"
},
  "geometry": {"coordinates":[-78.304822,34.996925],"type":"Point"}
}