{
  "type": "Feature",
  "properties": {
    "addr:full":"13020 Angel Oak Dr Huntersville NC 28078",
    "addr:housenumber":"13020",
    "addr:postcode":"28078",
    "addr:street":"Angel Oak Dr",
    "iso:country":"US",
    "sg:address":"13020 Angel Oak Dr",
    "sg:city":"Huntersville",
    "sg:classifiers":[
        {
            "category":"Professional",
            "type":"Services"
        }
    ],
    "sg:phone":"+1 704 875 6574",
    "sg:postcode":"28078",
    "sg:province":"NC",
    "wof:name":"Valparaiso University Guild",
    "wof:placetype":"venue"
},
  "geometry": {"coordinates":[-80.890528,35.400052],"type":"Point"}
}