{
  "type": "Feature",
  "properties": {
    "iso:country":"US",
    "sg:address":"53 Carolina Lakes Rd",
    "sg:city":"Sanford",
    "sg:classifiers":[
        {
            "category":"Freight",
            "type":"Transportation"
        }
    ],
    "sg:phone":"+1 919 499 0785",
    "sg:postcode":"27332",
    "sg:province":"NC",
    "sg:tags":[
        "hauling",
        "trucking"
    ],
    "wof:name":"Divots Inc",
    "wof:placetype":"venue"
},
  "geometry": {"coordinates":[-79.05833699999999,35.287604],"type":"Point"}
}