{
  "type": "Feature",
  "properties": {
    "iso:country":"US",
    "sg:address":"1347 Catawba Ter",
    "sg:city":"Lenoir",
    "sg:classifiers":[
        {
            "category":"Building & Trades",
            "subcategory":"Construction",
            "type":"Services"
        }
    ],
    "sg:phone":"+1 828 726 1960",
    "sg:postcode":"28645",
    "sg:province":"NC",
    "sg:tags":[
        "excavation",
        "work"
    ],
    "wof:name":"Williams Brothers Grading Inc",
    "wof:placetype":"venue"
},
  "geometry": {"coordinates":[-81.539998,35.843871],"type":"Point"}
}