{
  "type": "Feature",
  "properties": {
    "addr:full":"930 W Wilson Ave Mooresville NC 28117",
    "addr:housenumber":"930",
    "addr:postcode":"28117",
    "addr:street":"W Wilson Ave",
    "iso:country":"US",
    "sg:address":"930 W Wilson Ave",
    "sg:city":"Mooresville",
    "sg:classifiers":[
        {
            "category":"Personal",
            "type":"Services"
        }
    ],
    "sg:phone":"+1 704 664 4480",
    "sg:postcode":"28117",
    "sg:province":"NC",
    "sg:tags":[
        "control",
        "weight"
    ],
    "wof:name":"Northlake Weight Mgmt Ctr",
    "wof:placetype":"venue"
},
  "geometry": {"coordinates":[-80.83551199999999,35.579627],"type":"Point"}
}