{
  "type": "Feature",
  "properties": {
    "iso:country":"US",
    "sg:address":"3520 Spring Forest Rd",
    "sg:city":"Raleigh",
    "sg:classifiers":[
        {
            "category":"Home & Garden",
            "subcategory":"Furniture",
            "type":"Retail Goods"
        }
    ],
    "sg:phone":"+1 919 878 0110",
    "sg:postcode":"27616",
    "sg:province":"NC",
    "sg:tags":[
        "decorative",
        "household",
        "furnishing",
        "accessory"
    ],
    "sg:website":"www.westsidefurnishings.com",
    "wof:name":"West Side Furnishings L L C",
    "wof:placetype":"venue"
},
  "geometry": {"coordinates":[-78.58321100000001,35.854996],"type":"Point"}
}