{
  "type": "Feature",
  "properties": {
    "addr:full":"5528 Pepperdine Dr Charlotte NC 28226",
    "addr:housenumber":"5528",
    "addr:postcode":"28226",
    "addr:street":"Pepperdine Dr",
    "iso:country":"US",
    "sg:address":"5528 Pepperdine Dr",
    "sg:city":"Charlotte",
    "sg:classifiers":[
        {
            "category":"Banks & Credit Unions",
            "subcategory":"Financial Services",
            "type":"Services"
        }
    ],
    "sg:phone":"+1 704 367 1575",
    "sg:postcode":"28226",
    "sg:province":"NC",
    "sg:tags":[
        "investment",
        "closed"
    ],
    "wof:name":"Chapcell Incorporated",
    "wof:placetype":"venue"
},
  "geometry": {"coordinates":[-80.80215,35.124007],"type":"Point"}
}