{
  "type": "Feature",
  "properties": {
    "addr:full":"6252 Weeping Willow Ct Pleasant Garden NC 27313",
    "addr:housenumber":"6252",
    "addr:postcode":"27313",
    "addr:street":"Weeping Willow Ct Pleasant",
    "iso:country":"US",
    "sg:address":"6252 Weeping Willow Ct",
    "sg:city":"Pleasant Garden",
    "sg:classifiers":[
        {
            "category":"Freight",
            "type":"Transportation"
        }
    ],
    "sg:phone":"+1 336 685 5705",
    "sg:postcode":"27313",
    "sg:province":"NC",
    "sg:tags":[
        "truck",
        "company",
        "leasing"
    ],
    "wof:name":"JM Caviness Inc",
    "wof:placetype":"venue"
},
  "geometry": {"coordinates":[-79.730585,35.894262],"type":"Point"}
}