{
  "type": "Feature",
  "properties": {
    "iso:country":"US",
    "sg:address":"1611 Way St",
    "sg:city":"Reidsville",
    "sg:classifiers":[
        {
            "category":"Shopping",
            "subcategory":"Jewelry",
            "type":"Retail Goods"
        }
    ],
    "sg:phone":"+1 336 342 3508",
    "sg:postcode":"27320",
    "sg:province":"NC",
    "wof:name":"Arthurs Jewelry Inc",
    "wof:placetype":"venue"
},
  "geometry": {"coordinates":[-79.658661,36.340224],"type":"Point"}
}