{
  "type": "Feature",
  "properties": {
    "addr:full":"122 Cedar Creek Rd Biscoe NC 27209",
    "addr:housenumber":"122",
    "addr:postcode":"27209",
    "addr:street":"Cedar Creek Rd",
    "iso:country":"US",
    "sg:address":"122 Cedar Creek Rd",
    "sg:city":"Biscoe",
    "sg:classifiers":[
        {
            "category":"Autos & Motor Vehicles",
            "subcategory":"Automobile Sales",
            "type":"Retail Goods"
        }
    ],
    "sg:phone":"+1 910 428 9238",
    "sg:postcode":"27209",
    "sg:province":"NC",
    "sg:tags":[
        "cart"
    ],
    "wof:name":"Eddie's Kart Shop",
    "wof:placetype":"venue"
},
  "geometry": {"coordinates":[-79.780843,35.345092],"type":"Point"}
}