{
  "type": "Feature",
  "properties": {
    "addr:full":"2815 Carolina Beach Rd Wilmington NC 28412",
    "addr:housenumber":"2815",
    "addr:postcode":"28412",
    "addr:street":"Carolina Beach Rd",
    "iso:country":"US",
    "sg:address":"2815 Carolina Beach Rd",
    "sg:city":"Wilmington",
    "sg:classifiers":[
        {
            "category":"Freight",
            "type":"Transportation"
        }
    ],
    "sg:phone":"+1 910 791 6921",
    "sg:postcode":"28412",
    "sg:province":"NC",
    "sg:tags":[
        "trucking"
    ],
    "sg:website":"www.overnite.com",
    "wof:name":"UPS Freight",
    "wof:placetype":"venue"
},
  "geometry": {"coordinates":[-77.931894,34.18745],"type":"Point"}
}