{
  "type": "Feature",
  "properties": {
    "iso:country":"US",
    "sg:address":"1903 Bragg Blvd",
    "sg:city":"Fayetteville",
    "sg:classifiers":[
        {
            "category":"Real Estate",
            "subcategory":"Real Estate Agent",
            "type":"Services"
        }
    ],
    "sg:phone":"+1 910 323 5535",
    "sg:postcode":"28303",
    "sg:province":"NC",
    "wof:name":"William Shrman In Lfyette Rlty",
    "wof:placetype":"venue"
},
  "geometry": {"coordinates":[-78.91152700000001,35.069092],"type":"Point"}
}