{
  "type": "Feature",
  "properties": {
    "iso:country":"US",
    "sg:address":"471 Center Church Rd",
    "sg:city":"Pittsboro",
    "sg:classifiers":[
        {
            "category":"Organizations",
            "subcategory":"Religious Organization",
            "type":"Services"
        }
    ],
    "sg:phone":"+1   ",
    "sg:postcode":"27312",
    "sg:province":"NC",
    "wof:name":"Bible Baptist Church",
    "wof:placetype":"venue"
},
  "geometry": {"coordinates":[-79.33085699999999,35.842905],"type":"Point"}
}