{
  "type": "Feature",
  "properties": {
    "addr:full":"1758 S Fayetteville St Asheboro NC 27205",
    "addr:housenumber":"1758",
    "addr:postcode":"27205",
    "addr:street":"S Fayetteville St",
    "iso:country":"US",
    "sg:address":"1758 S Fayetteville St",
    "sg:city":"Asheboro",
    "sg:classifiers":[
        {
            "category":"Autos & Motor Vehicles",
            "subcategory":"Auto Supplies",
            "type":"Retail Goods"
        }
    ],
    "sg:phone":"+1 336 328 1366",
    "sg:postcode":"27205",
    "sg:province":"NC",
    "sg:tags":[
        "tire"
    ],
    "sg:website":"www.coopertire.com",
    "wof:name":"Cooper Tire & Rubber Co",
    "wof:placetype":"venue"
},
  "geometry": {"coordinates":[-79.81702900000001,35.682625],"type":"Point"}
}