{
  "type": "Feature",
  "properties": {
    "addr:full":"1240 Old Farmer Rd Asheboro NC 27205",
    "addr:housenumber":"1240",
    "addr:postcode":"27205",
    "addr:street":"Old Farmer Rd",
    "iso:country":"US",
    "sg:address":"1240 Old Farmer Rd",
    "sg:city":"Asheboro",
    "sg:classifiers":[
        {
            "category":"Retail",
            "subcategory":"Repair Shop",
            "type":"Services"
        }
    ],
    "sg:phone":"+1 336 629 0428",
    "sg:postcode":"27205",
    "sg:province":"NC",
    "sg:tags":[
        "operator",
        "tour"
    ],
    "wof:name":"Williamson Tours",
    "wof:placetype":"venue"
},
  "geometry": {"coordinates":[-79.83293399999999,35.700957],"type":"Point"}
}