{
  "type": "Feature",
  "properties": {
    "iso:country":"US",
    "sg:address":"333 E Main St",
    "sg:city":"Clayton",
    "sg:classifiers":[
        {
            "category":"Travel",
            "subcategory":"Travel Agent",
            "type":"Entertainment"
        }
    ],
    "sg:phone":"+1 919 550 8030",
    "sg:postcode":"27520",
    "sg:province":"NC",
    "sg:tags":[
        "agency",
        "bureau"
    ],
    "sg:website":"www.truelovetravel.com",
    "wof:name":"Truelove Travel",
    "wof:placetype":"venue"
},
  "geometry": {"coordinates":[-78.457449,35.651117],"type":"Point"}
}