{
  "type": "Feature",
  "properties": {
    "addr:full":"203 Onyx Ln Knightdale NC 27545",
    "addr:housenumber":"203",
    "addr:postcode":"27545",
    "addr:street":"Onyx Ln",
    "iso:country":"US",
    "sg:address":"203 Onyx Ln",
    "sg:city":"Knightdale",
    "sg:classifiers":[
        {
            "category":"Building & Trades",
            "subcategory":"Electrical",
            "type":"Services"
        }
    ],
    "sg:phone":"+1 919 266 0691",
    "sg:postcode":"27545",
    "sg:province":"NC",
    "sg:tags":[
        "electrical",
        "contractor"
    ],
    "wof:name":"Dunston & Sons Electrical Cont",
    "wof:placetype":"venue"
},
  "geometry": {"coordinates":[-78.46584199999999,35.814663],"type":"Point"}
}