{
  "type": "Feature",
  "properties": {
    "addr:full":"411 Friendway Rd Greensboro NC 27410",
    "addr:housenumber":"411",
    "addr:postcode":"27410",
    "addr:street":"Friendway Rd",
    "iso:country":"US",
    "sg:address":"411 Friendway Rd",
    "sg:city":"Greensboro",
    "sg:classifiers":[
        {
            "category":"Education",
            "subcategory":"School",
            "type":"Public Place"
        }
    ],
    "sg:phone":"+1 336 316 5844",
    "sg:postcode":"27410",
    "sg:province":"NC",
    "sg:tags":[
        "elementary"
    ],
    "wof:name":"Guilford Primary School",
    "wof:placetype":"venue"
},
  "geometry": {"coordinates":[-79.90464299999999,36.084291],"type":"Point"}
}