{
  "type": "Feature",
  "properties": {
    "addr:full":"1216 Falls Creek Ln Charlotte NC 28209",
    "addr:housenumber":"1216",
    "addr:postcode":"28209",
    "addr:street":"Falls Creek Ln",
    "iso:country":"US",
    "sg:address":"1216 Falls Creek Ln",
    "sg:city":"Charlotte",
    "sg:classifiers":[
        {
            "category":"Banks & Credit Unions",
            "subcategory":"Bank",
            "type":"Services"
        }
    ],
    "sg:phone":"+1 704 386 1014",
    "sg:postcode":"28209",
    "sg:province":"NC",
    "sg:tags":[
        "commercial"
    ],
    "wof:name":"Bank of America",
    "wof:placetype":"venue"
},
  "geometry": {"coordinates":[-80.863945,35.17782],"type":"Point"}
}