{
  "type": "Feature",
  "properties": {
    "iso:country":"US",
    "sg:address":"603 E Lake Ridge Rd",
    "sg:city":"Raeford",
    "sg:classifiers":[
        {
            "category":"Banks & Credit Unions",
            "subcategory":"Investment Brokerage",
            "type":"Services"
        }
    ],
    "sg:phone":"+1 910 321 0520",
    "sg:postcode":"28376",
    "sg:province":"NC",
    "sg:tags":[
        "advisory"
    ],
    "wof:name":"Benjamin Bernard Financial Ser",
    "wof:placetype":"venue"
},
  "geometry": {"coordinates":[-79.04213799999999,34.962729],"type":"Point"}
}