{
  "type": "Feature",
  "properties": {
    "iso:country":"US",
    "sg:address":"5175 Pine Hall Rd",
    "sg:city":"Walnut Cove",
    "sg:classifiers":[
        {
            "category":"Retail",
            "subcategory":"Repair Shop",
            "type":"Services"
        }
    ],
    "sg:phone":"+1   ",
    "sg:postcode":"27052",
    "sg:province":"NC",
    "sg:tags":[
        "welding"
    ],
    "wof:name":"R & R Precision Fabrication",
    "wof:placetype":"venue"
},
  "geometry": {"coordinates":[-80.134434,36.209787],"type":"Point"}
}