{
  "type": "Feature",
  "properties": {
    "addr:full":"5220 Sugar and Wine Rd Monroe NC 28110",
    "addr:housenumber":"5220",
    "addr:postcode":"28110",
    "addr:street":"Sugar And Wine Rd",
    "iso:country":"US",
    "sg:address":"5220 Sugar and Wine Rd",
    "sg:city":"Monroe",
    "sg:classifiers":[
        {
            "category":"Farming",
            "subcategory":"Farm & Veterinary Services",
            "type":"Manufacturing & Wholesale Goods"
        }
    ],
    "sg:phone":"+1 704 385 9144",
    "sg:postcode":"28110",
    "sg:province":"NC",
    "sg:tags":[
        "livestock"
    ],
    "wof:name":"Troy L Purser",
    "wof:placetype":"venue"
},
  "geometry": {"coordinates":[-80.417355,35.107238],"type":"Point"}
}