{
  "type": "Feature",
  "properties": {
    "addr:full":"118 W T Weaver Blvd Asheville NC 28804",
    "addr:housenumber":"118",
    "addr:postcode":"28804",
    "addr:street":"W T Weaver Blvd",
    "iso:country":"US",
    "sg:address":"118 W T Weaver Blvd",
    "sg:city":"Asheville",
    "sg:classifiers":[
        {
            "category":"Health Services",
            "subcategory":"Doctor",
            "type":"Services"
        }
    ],
    "sg:phone":"+1 828 257 4730",
    "sg:postcode":"28804",
    "sg:province":"NC",
    "sg:tags":[
        "physician",
        "surgeon"
    ],
    "wof:name":"MAHEC Family Health Ctr",
    "wof:placetype":"venue"
},
  "geometry": {"coordinates":[-82.558629,35.614208],"type":"Point"}
}