{
  "type": "Feature",
  "properties": {
    "addr:full":"2649 Union Ridge Rd Burlington NC 27217",
    "addr:housenumber":"2649",
    "addr:postcode":"27217",
    "addr:street":"Union Ridge Rd",
    "iso:country":"US",
    "sg:address":"2649 Union Ridge Rd",
    "sg:city":"Burlington",
    "sg:classifiers":[
        {
            "category":"Shopping",
            "subcategory":"Discount & Variety Stores",
            "type":"Retail Goods"
        }
    ],
    "sg:phone":"+1 336 229 5232",
    "sg:postcode":"27217",
    "sg:province":"NC",
    "sg:tags":[
        "merchandise",
        "general"
    ],
    "wof:name":"Garland Simmons Upholstry",
    "wof:placetype":"venue"
},
  "geometry": {"coordinates":[-79.42330699999999,36.144988],"type":"Point"}
}