{
  "type": "Feature",
  "properties": {
    "addr:full":"2201 Brentwood Rd Raleigh NC 27604",
    "addr:housenumber":"2201",
    "addr:postcode":"27604",
    "addr:street":"Brentwood Rd",
    "iso:country":"US",
    "sg:address":"2201 Brentwood Rd",
    "sg:city":"Raleigh",
    "sg:classifiers":[
        {
            "category":"Professional",
            "type":"Services"
        }
    ],
    "sg:phone":"+1 919 719 2010",
    "sg:postcode":"27604",
    "sg:province":"NC",
    "sg:tags":[
        "establishment"
    ],
    "wof:name":"Digital Horizon",
    "wof:placetype":"venue"
},
  "geometry": {"coordinates":[-78.59459200000001,35.807312],"type":"Point"}
}