{
  "type": "Feature",
  "properties": {
    "iso:country":"US",
    "sg:address":"101 Mill St",
    "sg:city":"Rockingham",
    "sg:classifiers":[
        {
            "category":"Real Estate",
            "subcategory":"Real Estate Operator",
            "type":"Services"
        }
    ],
    "sg:phone":"+1 910 997 2155",
    "sg:postcode":"28379",
    "sg:province":"NC",
    "sg:tags":[
        "condominium"
    ],
    "wof:name":"Carolyn's Mill Condominiums",
    "wof:placetype":"venue"
},
  "geometry": {"coordinates":[-79.76875699999999,34.924918],"type":"Point"}
}