{
  "type": "Feature",
  "properties": {
    "iso:country":"US",
    "sg:address":"4718 Antioch Church Rd",
    "sg:city":"Middlesex",
    "sg:classifiers":[
        {
            "category":"Professional",
            "subcategory":"Business Services",
            "type":"Services"
        }
    ],
    "sg:phone":"+1 919 975 0612",
    "sg:postcode":"27557",
    "sg:province":"NC",
    "sg:tags":[
        "appraiser"
    ],
    "wof:name":"Sunrise Appraisal",
    "wof:placetype":"venue"
},
  "geometry": {"coordinates":[-78.23830599999999,35.695348],"type":"Point"}
}