{
  "type": "Feature",
  "properties": {
    "addr:full":"4218 Poplar Grove Dr Charlotte NC 28269",
    "addr:housenumber":"4218",
    "addr:postcode":"28269",
    "addr:street":"Poplar Grove Dr",
    "iso:country":"US",
    "sg:address":"4218 Poplar Grove Dr",
    "sg:city":"Charlotte",
    "sg:classifiers":[
        {
            "category":"Professional",
            "subcategory":"Business Services",
            "type":"Services"
        }
    ],
    "sg:phone":"+1   ",
    "sg:postcode":"28269",
    "sg:province":"NC",
    "wof:name":"Kasahara Kazuhtio",
    "wof:placetype":"venue"
},
  "geometry": {"coordinates":[-80.818815,35.345105],"type":"Point"}
}