{
  "type": "Feature",
  "properties": {
    "iso:country":"US",
    "sg:address":"350 State Hwy 118",
    "sg:city":"Vanceboro",
    "sg:classifiers":[
        {
            "category":"Organizations",
            "subcategory":"Religious Organization",
            "type":"Services"
        }
    ],
    "sg:phone":"+1 252 244 1888",
    "sg:postcode":"28586",
    "sg:province":"NC",
    "sg:tags":[
        "church"
    ],
    "wof:name":"St James Church Of Christ",
    "wof:placetype":"venue"
},
  "geometry": {"coordinates":[-77.166471,35.312292],"type":"Point"}
}