{
  "type": "Feature",
  "properties": {
    "iso:country":"US",
    "sg:address":"3011 Falstaff Rd",
    "sg:city":"Raleigh",
    "sg:classifiers":[
        {
            "category":"Organizations",
            "subcategory":"Non-profit Organization",
            "type":"Services"
        }
    ],
    "sg:phone":"+1 919 231 3325",
    "sg:postcode":"27610",
    "sg:province":"NC",
    "sg:website":"www.raleighvocational.com",
    "wof:name":"Raleigh Vocational Ctr",
    "wof:placetype":"venue"
},
  "geometry": {"coordinates":[-78.58863599999999,35.781769],"type":"Point"}
}