{
  "type": "Feature",
  "properties": {
    "iso:country":"US",
    "sg:address":"1100 Greenvale Rd",
    "sg:city":"Raleigh",
    "sg:classifiers":[
        {
            "category":"Real Estate",
            "subcategory":"Real Estate Operator",
            "type":"Services"
        }
    ],
    "sg:phone":"+1 919 772 6405",
    "sg:postcode":"27603",
    "sg:province":"NC",
    "sg:tags":[
        "mobile",
        "home",
        "site"
    ],
    "wof:name":"George McGeeney",
    "wof:placetype":"venue"
},
  "geometry": {"coordinates":[-78.663669,35.675384],"type":"Point"}
}