{
  "type": "Feature",
  "properties": {
    "iso:country":"US",
    "sg:address":"3705 Chetola Dr",
    "sg:city":"Lenoir",
    "sg:classifiers":[
        {
            "category":"Food & Beverages",
            "subcategory":"Bakery",
            "type":"Retail Goods"
        }
    ],
    "sg:phone":"+1 828 757 3126",
    "sg:postcode":"28645",
    "sg:province":"NC",
    "sg:tags":[
        "baker"
    ],
    "wof:name":"Joan's Sourdough Bread",
    "wof:placetype":"venue"
},
  "geometry": {"coordinates":[-81.52484,35.98935],"type":"Point"}
}