{
  "type": "Feature",
  "properties": {
    "addr:full":"2518 Plantation Center Dr Matthews NC 28105",
    "addr:housenumber":"2518",
    "addr:postcode":"28105",
    "addr:street":"Plantation Center Dr",
    "iso:country":"US",
    "sg:address":"2518 Plantation Center Dr",
    "sg:city":"Matthews",
    "sg:classifiers":[
        {
            "category":"Insurance",
            "subcategory":"Insurance Agent",
            "type":"Services"
        }
    ],
    "sg:phone":"+1 704 844 1200",
    "sg:postcode":"28105",
    "sg:province":"NC",
    "wof:name":"M R Bare & Assoc",
    "wof:placetype":"venue"
},
  "geometry": {"coordinates":[-80.732803,35.085649],"type":"Point"}
}