{
  "type": "Feature",
  "properties": {
    "addr:full":"3908 Patriot Dr.  Suite 140 Durham NC 27703-8031",
    "addr:housenumber":"3908",
    "addr:postcode":"27703-8031",
    "addr:street":"Patriot Dr. Suite 140",
    "iso:country":"US",
    "sg:address":"3908 Patriot Dr.  Suite 140",
    "sg:city":"Durham",
    "sg:classifiers":[
        {
            "category":"Manufacturing",
            "subcategory":"Electronics",
            "type":"Manufacturing & Wholesale Goods"
        }
    ],
    "sg:phone":"+1 919 597 7300",
    "sg:postcode":"27703-8031",
    "sg:province":"NC",
    "sg:website":"http://www.nextremethermal.com",
    "wof:name":"Nextreme Thermal Solutions",
    "wof:placetype":"venue"
},
  "geometry": {"coordinates":[-78.850022,35.911835],"type":"Point"}
}