{
  "type": "Feature",
  "properties": {
    "addr:full":"403 Early Morning Trl Fuquay Varina NC 27526",
    "addr:housenumber":"403",
    "addr:postcode":"27526",
    "addr:street":"Early Morning Trl",
    "iso:country":"US",
    "sg:address":"403 Early Morning Trl",
    "sg:city":"Fuquay Varina",
    "sg:classifiers":[
        {
            "category":"Professional",
            "subcategory":"Advertising",
            "type":"Services"
        }
    ],
    "sg:phone":"+1   ",
    "sg:postcode":"27526",
    "sg:province":"NC",
    "sg:tags":[
        "mail",
        "direct"
    ],
    "wof:name":"Carolina Clipper",
    "wof:placetype":"venue"
},
  "geometry": {"coordinates":[-78.814075,35.556855],"type":"Point"}
}