{
  "type": "Feature",
  "properties": {
    "addr:full":"200 Hyde Park Ct Cary NC 27513",
    "addr:housenumber":"200",
    "addr:postcode":"27513",
    "addr:street":"Hyde Park Ct",
    "iso:country":"US",
    "sg:address":"200 Hyde Park Ct",
    "sg:city":"Cary",
    "sg:classifiers":[
        {
            "category":"Real Estate",
            "subcategory":"Real Estate Operator",
            "type":"Services"
        }
    ],
    "sg:phone":"+1 919 467 0303",
    "sg:postcode":"27513",
    "sg:province":"NC",
    "sg:tags":[
        "apartment"
    ],
    "wof:name":"Hyde Park Apartments",
    "wof:placetype":"venue"
},
  "geometry": {"coordinates":[-78.77570299999999,35.8055],"type":"Point"}
}