{
  "type": "Feature",
  "properties": {
    "iso:country":"US",
    "sg:address":"220 Dalton Ave",
    "sg:city":"Charlotte",
    "sg:classifiers":[
        {
            "category":"Travel",
            "subcategory":"Travel Agent",
            "type":"Entertainment"
        }
    ],
    "sg:phone":"+1 704 201 4420",
    "sg:postcode":"28206",
    "sg:province":"NC",
    "sg:tags":[
        "agency",
        "services-commercial"
    ],
    "wof:name":"Charles Travel Co.",
    "wof:placetype":"venue"
},
  "geometry": {"coordinates":[-80.831198,35.239544],"type":"Point"}
}