{
  "type": "Feature",
  "properties": {
    "addr:full":"3709 University Dr Durham NC 27707",
    "addr:housenumber":"3709",
    "addr:postcode":"27707",
    "addr:street":"University Dr",
    "iso:country":"US",
    "sg:address":"3709 University Dr",
    "sg:city":"Durham",
    "sg:classifiers":[
        {
            "category":"Real Estate",
            "subcategory":"Real Estate Agent",
            "type":"Services"
        }
    ],
    "sg:phone":"+1 919 419 1200",
    "sg:postcode":"27707",
    "sg:province":"NC",
    "wof:name":"Southeast Cmb",
    "wof:placetype":"venue"
},
  "geometry": {"coordinates":[-78.950214,35.966749],"type":"Point"}
}