{
  "type": "Feature",
  "properties": {
    "iso:country":"US",
    "sg:address":"1903 Anaconda Rd",
    "sg:city":"Tarboro",
    "sg:classifiers":[
        {
            "category":"Insurance",
            "subcategory":"Life Insurance",
            "type":"Services"
        }
    ],
    "sg:phone":"+1 252 823 1432",
    "sg:postcode":"27886",
    "sg:province":"NC",
    "sg:tags":[
        "carrier"
    ],
    "wof:name":"Woodmen Tarboro Lodge 115",
    "wof:placetype":"venue"
},
  "geometry": {"coordinates":[-77.56878399999999,35.909818],"type":"Point"}
}