{
  "type": "Feature",
  "properties": {
    "iso:country":"US",
    "sg:address":"534 Lake Ledford Rd",
    "sg:city":"Franklin",
    "sg:classifiers":[
        {
            "category":"Building & Trades",
            "subcategory":"Construction",
            "type":"Services"
        }
    ],
    "sg:phone":"+1 828 369 8710",
    "sg:postcode":"28734",
    "sg:province":"NC",
    "sg:tags":[
        "house"
    ],
    "wof:name":"Davids Remodeling",
    "wof:placetype":"venue"
},
  "geometry": {"coordinates":[-83.41542200000001,35.13197],"type":"Point"}
}