{
  "type": "Feature",
  "properties": {
    "iso:country":"US",
    "sg:address":"1310 Simmons St",
    "sg:city":"New Bern",
    "sg:classifiers":[
        {
            "category":"Personal",
            "subcategory":"Beauty Salon",
            "type":"Services"
        }
    ],
    "sg:phone":"+1 252 638 5854",
    "sg:postcode":"28560",
    "sg:province":"NC",
    "wof:name":"Cut Above",
    "wof:placetype":"venue"
},
  "geometry": {"coordinates":[-77.073605,35.115971],"type":"Point"}
}