{
  "type": "Feature",
  "properties": {
    "addr:full":"706 Money Ct Knightdale NC 27545",
    "addr:housenumber":"706",
    "addr:postcode":"27545",
    "addr:street":"Money Ct",
    "iso:country":"US",
    "sg:address":"706 Money Ct",
    "sg:city":"Knightdale",
    "sg:classifiers":[
        {
            "category":"Restaurant",
            "type":"Food & Drink"
        }
    ],
    "sg:phone":"+1 919 266 4447",
    "sg:postcode":"27545",
    "sg:province":"NC",
    "sg:tags":[
        "eating"
    ],
    "wof:name":"Knightdale Seafood & Barbecue",
    "wof:placetype":"venue"
},
  "geometry": {"coordinates":[-78.473602,35.798203],"type":"Point"}
}