{
  "type": "Feature",
  "properties": {
    "addr:full":"5741 Erect Rd Ramseur NC 27316",
    "addr:housenumber":"5741",
    "addr:postcode":"27316",
    "addr:street":"Erect Rd",
    "iso:country":"US",
    "sg:address":"5741 Erect Rd",
    "sg:city":"Ramseur",
    "sg:classifiers":[
        {
            "category":"Home & Garden",
            "subcategory":"Home Furnishings",
            "type":"Retail Goods"
        }
    ],
    "sg:phone":"+1 336 879 4200",
    "sg:postcode":"27316",
    "sg:province":"NC",
    "sg:tags":[
        "pottery"
    ],
    "wof:name":"LDDK Studio",
    "wof:placetype":"venue"
},
  "geometry": {"coordinates":[-79.64799499999999,35.609228],"type":"Point"}
}