{
  "type": "Feature",
  "properties": {
    "iso:country":"US",
    "sg:address":"102 Wicker St",
    "sg:city":"Sanford",
    "sg:classifiers":[
        {
            "category":"Communications",
            "type":"Services"
        }
    ],
    "sg:phone":"+1 919 775 1515",
    "sg:postcode":"27330",
    "sg:province":"NC",
    "wof:name":"Sandhills Communications",
    "wof:placetype":"venue"
},
  "geometry": {"coordinates":[-79.17713500000001,35.480114],"type":"Point"}
}