{
  "type": "Feature",
  "properties": {
    "iso:country":"US",
    "sg:address":"1611 Ellis Belk Rd",
    "sg:city":"Monroe",
    "sg:classifiers":[
        {
            "category":"Autos & Motor Vehicles",
            "subcategory":"Automobile Sales",
            "type":"Retail Goods"
        }
    ],
    "sg:phone":"+1 704 764 7292",
    "sg:postcode":"28112",
    "sg:province":"NC",
    "sg:tags":[
        "used"
    ],
    "wof:name":"Ricks Auto Sales",
    "wof:placetype":"venue"
},
  "geometry": {"coordinates":[-80.568775,34.820597],"type":"Point"}
}