{
  "type": "Feature",
  "properties": {
    "iso:country":"US",
    "sg:address":"2308 E Bessemer Ave",
    "sg:city":"Greensboro",
    "sg:classifiers":[
        {
            "category":"Personal",
            "subcategory":"Barber",
            "type":"Services"
        }
    ],
    "sg:phone":"+1 336 275 1288",
    "sg:postcode":"27405",
    "sg:province":"NC",
    "wof:name":"Motivations Barber Shop III",
    "wof:placetype":"venue"
},
  "geometry": {"coordinates":[-79.755809,36.085096],"type":"Point"}
}