{
  "type": "Feature",
  "properties": {
    "iso:country":"US",
    "sg:address":"110 Maypatch Rd",
    "sg:city":"Jacksonville",
    "sg:classifiers":[
        {
            "category":"Local Transit",
            "type":"Transportation"
        }
    ],
    "sg:phone":"+1 910 353 8004",
    "sg:postcode":"28546",
    "sg:province":"NC",
    "wof:name":"T & W Transportation Inc",
    "wof:placetype":"venue"
},
  "geometry": {"coordinates":[-77.38638899999999,34.746365],"type":"Point"}
}