{
  "type": "Feature",
  "properties": {
    "addr:full":"205 E 25th St Winston Salem NC 27105",
    "addr:housenumber":"205",
    "addr:postcode":"27105",
    "addr:street":"E 25Th St",
    "iso:country":"US",
    "sg:address":"205 E 25th St",
    "sg:city":"Winston Salem",
    "sg:classifiers":[
        {
            "category":"Organizations",
            "subcategory":"Religious Organization",
            "type":"Services"
        }
    ],
    "sg:phone":"+1   ",
    "sg:postcode":"27105",
    "sg:province":"NC",
    "wof:name":"Mount Nebo Holiness Church",
    "wof:placetype":"venue"
},
  "geometry": {"coordinates":[-80.241984,36.122136],"type":"Point"}
}