{
  "type": "Feature",
  "properties": {
    "addr:full":"203 Hillcrest Dr Madison NC 27025",
    "addr:housenumber":"203",
    "addr:postcode":"27025",
    "addr:street":"Hillcrest Dr",
    "iso:country":"US",
    "sg:address":"203 Hillcrest Dr",
    "sg:city":"Madison",
    "sg:classifiers":[
        {
            "category":"Organizations",
            "subcategory":"Community Association",
            "type":"Services"
        }
    ],
    "sg:phone":"+1 336 548 9241",
    "sg:postcode":"27025",
    "sg:province":"NC",
    "wof:name":"Madison VFW Post 5684",
    "wof:placetype":"venue"
},
  "geometry": {"coordinates":[-79.975021,36.384371],"type":"Point"}
}