{
  "type": "Feature",
  "properties": {
    "addr:full":"948 Redfield Dr Clyde NC 28721",
    "addr:housenumber":"948",
    "addr:postcode":"28721",
    "addr:street":"Redfield Dr",
    "iso:country":"US",
    "sg:address":"948 Redfield Dr",
    "sg:city":"Clyde",
    "sg:classifiers":[
        {
            "category":"Utilities",
            "subcategory":"Mobile Phone",
            "type":"Services"
        }
    ],
    "sg:phone":"+1 828 627 6634",
    "sg:postcode":"28721",
    "sg:province":"NC",
    "sg:tags":[
        "communication",
        "radiotelephone"
    ],
    "wof:name":"US Bell Telecomm Consultants I",
    "wof:placetype":"venue"
},
  "geometry": {"coordinates":[-82.92040900000001,35.52044],"type":"Point"}
}