{
  "type": "Feature",
  "properties": {
    "iso:country":"US",
    "sg:address":"104 Transit Ave",
    "sg:city":"Thomasville",
    "sg:classifiers":[
        {
            "category":"Retail",
            "subcategory":"Repair Shop",
            "type":"Services"
        }
    ],
    "sg:phone":"+1   ",
    "sg:postcode":"27360",
    "sg:province":"NC",
    "wof:name":"H & H Fiberglass Repair",
    "wof:placetype":"venue"
},
  "geometry": {"coordinates":[-80.05436899999999,35.9181],"type":"Point"}
}