{
  "type": "Feature",
  "properties": {
    "iso:country":"US",
    "sg:address":"4735 Reedy Branch Rd",
    "sg:city":"Winterville",
    "sg:classifiers":[
        {
            "category":"Shopping",
            "subcategory":"Bicycles & Sporting Goods",
            "type":"Retail Goods"
        }
    ],
    "sg:phone":"+1 252 353 9035",
    "sg:postcode":"28590",
    "sg:province":"NC",
    "wof:name":"Hooked Up Tackle",
    "wof:placetype":"venue"
},
  "geometry": {"coordinates":[-77.415076,35.536027],"type":"Point"}
}