{
  "type": "Feature",
  "properties": {
    "addr:full":"201 N Green St Morganton NC 28655",
    "addr:housenumber":"201",
    "addr:postcode":"28655",
    "addr:street":"N Green St",
    "iso:country":"US",
    "sg:address":"201 N Green St",
    "sg:city":"Morganton",
    "sg:classifiers":[
        {
            "category":"Government",
            "subcategory":"Office",
            "type":"Public Place"
        }
    ],
    "sg:phone":"+1 828 439 4373",
    "sg:postcode":"28655",
    "sg:province":"NC",
    "wof:name":"Veterans Service",
    "wof:placetype":"venue"
},
  "geometry": {"coordinates":[-81.689555,35.74746],"type":"Point"}
}