{
  "type": "Feature",
  "properties": {
    "iso:country":"US",
    "sg:address":"105 N Gooden St",
    "sg:city":"Clarkton",
    "sg:classifiers":[
        {
            "category":"Wholesale",
            "subcategory":"Meat",
            "type":"Manufacturing & Wholesale Goods"
        }
    ],
    "sg:phone":"+1 910 647 8191",
    "sg:postcode":"28433",
    "sg:province":"NC",
    "sg:tags":[
        "butchering"
    ],
    "wof:name":"Clarkton Processing Co",
    "wof:placetype":"venue"
},
  "geometry": {"coordinates":[-78.659386,34.490679],"type":"Point"}
}