{
  "type": "Feature",
  "properties": {
    "addr:full":"3220 N Ohenry Blvd Greensboro NC 27405",
    "addr:housenumber":"3220",
    "addr:postcode":"27405",
    "addr:street":"N Ohenry Blvd",
    "iso:country":"US",
    "sg:address":"3220 N Ohenry Blvd",
    "sg:city":"Greensboro",
    "sg:classifiers":[
        {
            "category":"Shopping",
            "subcategory":"Clothing, Apparel, & Fashions",
            "type":"Retail Goods"
        }
    ],
    "sg:phone":"+1 336 475 2415",
    "sg:postcode":"27405",
    "sg:province":"NC",
    "wof:name":"Lindas Accessories",
    "wof:placetype":"venue"
},
  "geometry": {"coordinates":[-79.749606,36.122514],"type":"Point"}
}