{
  "type": "Feature",
  "properties": {
    "iso:country":"US",
    "sg:address":"111 Electra Dr",
    "sg:city":"Cary",
    "sg:classifiers":[
        {
            "category":"Professional",
            "type":"Services"
        }
    ],
    "sg:phone":"+1 919 469 0278",
    "sg:postcode":"27513",
    "sg:province":"NC",
    "wof:name":"Brandy Farrar",
    "wof:placetype":"venue"
},
  "geometry": {"coordinates":[-78.769201,35.808981],"type":"Point"}
}