{
  "type": "Feature",
  "properties": {
    "addr:full":"6399 Weston Pkwy Cary NC 27513",
    "addr:housenumber":"6399",
    "addr:postcode":"27513",
    "addr:street":"Weston Pkwy",
    "iso:country":"US",
    "sg:address":"6399 Weston Pkwy",
    "sg:city":"Cary",
    "sg:classifiers":[
        {
            "category":"Wholesale",
            "subcategory":"Durable Goods & Equipment",
            "type":"Manufacturing & Wholesale Goods"
        }
    ],
    "sg:phone":"+1 919 678 2220",
    "sg:postcode":"27513",
    "sg:province":"NC",
    "sg:tags":[
        "importer"
    ],
    "sg:website":"www.cottoninc.com",
    "wof:name":"Cotton Inc",
    "wof:placetype":"venue"
},
  "geometry": {"coordinates":[-78.782614,35.831243],"type":"Point"}
}