{
  "type": "Feature",
  "properties": {
    "iso:country":"US",
    "sg:address":"2304 Waughtown St",
    "sg:city":"Winston Salem",
    "sg:classifiers":[
        {
            "category":"Personal",
            "subcategory":"Barber",
            "type":"Services"
        }
    ],
    "sg:phone":"+1 336 785 4440",
    "sg:postcode":"27107",
    "sg:province":"NC",
    "wof:name":"Doug'e Fresh Cuts",
    "wof:placetype":"venue"
},
  "geometry": {"coordinates":[-80.19325499999999,36.073991],"type":"Point"}
}