{
  "type": "Feature",
  "properties": {
    "iso:country":"US",
    "sg:address":"102 Washington Ave",
    "sg:city":"Weldon",
    "sg:classifiers":[
        {
            "category":"Personal",
            "subcategory":"Beauty Salon",
            "type":"Services"
        }
    ],
    "sg:phone":"+1 252 536 3322",
    "sg:postcode":"27890",
    "sg:province":"NC",
    "sg:tags":[
        "shop"
    ],
    "wof:name":"Sheila's Hair Care",
    "wof:placetype":"venue"
},
  "geometry": {"coordinates":[-77.596011,36.428344],"type":"Point"}
}