{
  "type": "Feature",
  "properties": {
    "iso:country":"US",
    "sg:address":"136 Hickorynut Ln",
    "sg:city":"Mount Holly",
    "sg:classifiers":[
        {
            "category":"Building & Trades",
            "subcategory":"Construction",
            "type":"Services"
        }
    ],
    "sg:phone":"+1 704 827 2684",
    "sg:postcode":"28120",
    "sg:province":"NC",
    "sg:tags":[
        "house"
    ],
    "wof:name":"Zapsas Construction",
    "wof:placetype":"venue"
},
  "geometry": {"coordinates":[-81.070753,35.316514],"type":"Point"}
}