{
  "type": "Feature",
  "properties": {
    "addr:full":"660 Overman Rd Goldsboro NC 27530",
    "addr:housenumber":"660",
    "addr:postcode":"27530",
    "addr:street":"Overman Rd",
    "iso:country":"US",
    "sg:address":"660 Overman Rd",
    "sg:city":"Goldsboro",
    "sg:classifiers":[
        {
            "category":"Social Services",
            "subcategory":"Child Care",
            "type":"Services"
        }
    ],
    "sg:phone":"+1 919 689 2697",
    "sg:postcode":"27530",
    "sg:province":"NC",
    "sg:tags":[
        "day"
    ],
    "wof:name":"Happy Days Nursery",
    "wof:placetype":"venue"
},
  "geometry": {"coordinates":[-78.105626,35.312552],"type":"Point"}
}