{
  "type": "Feature",
  "properties": {
    "iso:country":"US",
    "sg:address":"228 Kanuga Rd",
    "sg:city":"Hendersonville",
    "sg:classifiers":[
        {
            "category":"Personal",
            "subcategory":"Beauty Salon",
            "type":"Services"
        }
    ],
    "sg:phone":"+1   ",
    "sg:postcode":"28739",
    "sg:province":"NC",
    "sg:tags":[
        "shop"
    ],
    "wof:name":"Profiles Hair Salon",
    "wof:placetype":"venue"
},
  "geometry": {"coordinates":[-82.46057999999999,35.311178],"type":"Point"}
}