{
  "type": "Feature",
  "properties": {
    "iso:country":"US",
    "sg:address":"812 E Guilford St",
    "sg:city":"Thomasville",
    "sg:classifiers":[
        {
            "category":"Personal",
            "subcategory":"Barber",
            "type":"Services"
        }
    ],
    "sg:phone":"+1   ",
    "sg:postcode":"27360",
    "sg:province":"NC",
    "sg:tags":[
        "shop"
    ],
    "wof:name":"East End Barber Shop",
    "wof:placetype":"venue"
},
  "geometry": {"coordinates":[-80.07158099999999,35.888766],"type":"Point"}
}