{
  "type": "Feature",
  "properties": {
    "iso:country":"US",
    "sg:address":"199 Spruce St",
    "sg:city":"Boone",
    "sg:classifiers":[
        {
            "category":"Professional",
            "subcategory":"Computer Services",
            "type":"Services"
        }
    ],
    "sg:phone":"+1 828 265 2254",
    "sg:postcode":"28607",
    "sg:province":"NC",
    "wof:name":"Appalachian Computer Svc",
    "wof:placetype":"venue"
},
  "geometry": {"coordinates":[-81.653887,36.218649],"type":"Point"}
}