{
  "type": "Feature",
  "properties": {
    "iso:country":"US",
    "sg:address":"460 College St",
    "sg:city":"Mooresville",
    "sg:classifiers":[
        {
            "category":"Building & Trades",
            "subcategory":"Construction",
            "type":"Services"
        }
    ],
    "sg:phone":"+1 704 799 7611",
    "sg:postcode":"28115",
    "sg:province":"NC",
    "sg:tags":[
        "engineering",
        "contractor"
    ],
    "wof:name":"Jim Hobby Construction",
    "wof:placetype":"venue"
},
  "geometry": {"coordinates":[-80.81753500000001,35.572922],"type":"Point"}
}