{
  "type": "Feature",
  "properties": {
    "iso:country":"US",
    "sg:address":"1214 Reynolda Rd",
    "sg:city":"Winston Salem",
    "sg:classifiers":[
        {
            "category":"Personal",
            "subcategory":"Beauty Salon",
            "type":"Services"
        }
    ],
    "sg:phone":"+1   ",
    "sg:postcode":"27104",
    "sg:province":"NC",
    "sg:tags":[
        "shop"
    ],
    "wof:name":"Ball Keely",
    "wof:placetype":"venue"
},
  "geometry": {"coordinates":[-80.267522,36.10845],"type":"Point"}
}