{
  "type": "Feature",
  "properties": {
    "addr:full":"310 NE 52nd St Oak Island NC 28465",
    "addr:housenumber":"310",
    "addr:postcode":"28465",
    "addr:street":"Ne 52Nd St",
    "iso:country":"US",
    "sg:address":"310 NE 52nd St",
    "sg:city":"Oak Island",
    "sg:classifiers":[
        {
            "category":"Building & Trades",
            "subcategory":"Construction",
            "type":"Services"
        }
    ],
    "sg:phone":"+1 910 278 7630",
    "sg:postcode":"28465",
    "sg:province":"NC",
    "sg:tags":[
        "tree"
    ],
    "wof:name":"Mark E Bulich",
    "wof:placetype":"venue"
},
  "geometry": {"coordinates":[-78.10945100000001,33.918909],"type":"Point"}
}