{
  "type": "Feature",
  "properties": {
    "addr:full":"7 W Yacht Dr Oak Island NC 28465",
    "addr:housenumber":"7",
    "addr:postcode":"28465",
    "addr:street":"W Yacht Dr",
    "iso:country":"US",
    "sg:address":"7 W Yacht Dr",
    "sg:city":"Oak Island",
    "sg:classifiers":[
        {
            "category":"Building & Trades",
            "subcategory":"Electrical",
            "type":"Services"
        }
    ],
    "sg:phone":"+1 910 278 5934",
    "sg:postcode":"28465",
    "sg:province":"NC",
    "sg:tags":[
        "electric",
        "contractor"
    ],
    "wof:name":"Randy's Electrical Svc",
    "wof:placetype":"venue"
},
  "geometry": {"coordinates":[-78.16054099999999,33.926538],"type":"Point"}
}