{
  "type": "Feature",
  "properties": {
    "addr:full":"1253 Buck Jones Rd Cary NC 27519",
    "addr:housenumber":"1253",
    "addr:postcode":"27519",
    "addr:street":"Buck Jones Rd",
    "iso:country":"US",
    "sg:address":"1253 Buck Jones Rd",
    "sg:city":"Cary",
    "sg:classifiers":[
        {
            "category":"Restaurant",
            "type":"Food & Drink"
        },
        {
            "category":"Bakery",
            "type":"Food & Drink"
        },
        {
            "category":"Food & Beverages",
            "subcategory":"Groceries & Convenience Stores",
            "type":"Retail Goods"
        }
    ],
    "sg:phone":"+1 919 468 2988",
    "sg:postcode":"27519",
    "sg:province":"NC",
    "sg:tags":[
        "chinese"
    ],
    "sg:website":"www.grandasiamarket.com",
    "wof:name":"Grand Asia Market",
    "wof:placetype":"venue"
},
  "geometry": {"coordinates":[-78.739571,35.770686],"type":"Point"}
}