{
  "type": "Feature",
  "properties": {
    "addr:full":"4317 Pleasant Valley Rd Raleigh NC 27612",
    "addr:housenumber":"4317",
    "addr:postcode":"27612",
    "addr:street":"Pleasant Valley Rd",
    "iso:country":"US",
    "sg:address":"4317 Pleasant Valley Rd",
    "sg:city":"Raleigh",
    "sg:classifiers":[
        {
            "category":"Professional",
            "subcategory":"Business Services",
            "type":"Services"
        }
    ],
    "sg:phone":"+1 919 787 4418",
    "sg:postcode":"27612",
    "sg:province":"NC",
    "wof:name":"Lason Inc",
    "wof:placetype":"venue"
},
  "geometry": {"coordinates":[-78.711068,35.859712],"type":"Point"}
}