{
  "type": "Feature",
  "properties": {
    "iso:country":"US",
    "sg:address":"132 N 1st St",
    "sg:city":"Albemarle",
    "sg:classifiers":[
        {
            "category":"Banks & Credit Unions",
            "subcategory":"Financial Services",
            "type":"Services"
        }
    ],
    "sg:phone":"+1 704 982 4415",
    "sg:postcode":"28001",
    "sg:province":"NC",
    "sg:tags":[
        "company",
        "holding"
    ],
    "sg:website":"www.ansonbank.com",
    "wof:name":"Uwharrie Capital Corp",
    "wof:placetype":"venue"
},
  "geometry": {"coordinates":[-80.199427,35.351675],"type":"Point"}
}