{
  "type": "Feature",
  "properties": {
    "addr:full":"8363 State Hwy 109 Winston Salem NC 27107",
    "addr:housenumber":"8363",
    "addr:postcode":"27107",
    "addr:street":"State Hwy 109",
    "iso:country":"US",
    "sg:address":"8363 State Hwy 109",
    "sg:city":"Winston Salem",
    "sg:classifiers":[
        {
            "category":"Personal",
            "type":"Services"
        }
    ],
    "sg:phone":"+1   ",
    "sg:postcode":"27107",
    "sg:province":"NC",
    "wof:name":"All About You Salon & Day Spa",
    "wof:placetype":"venue"
},
  "geometry": {"coordinates":[-80.13557,36.007733],"type":"Point"}
}