{
  "type": "Feature",
  "properties": {
    "addr:full":"204 N Buchanan Blvd Durham NC 27701",
    "addr:housenumber":"204",
    "addr:postcode":"27701",
    "addr:street":"N Buchanan Blvd",
    "iso:country":"US",
    "sg:address":"204 N Buchanan Blvd",
    "sg:city":"Durham",
    "sg:classifiers":[
        {
            "category":"Organizations",
            "subcategory":"Professional Association",
            "type":"Services"
        }
    ],
    "sg:phone":"+1 919 688 4040",
    "sg:postcode":"27701",
    "sg:province":"NC",
    "wof:name":"Kings Daughters Home",
    "wof:placetype":"venue"
},
  "geometry": {"coordinates":[-78.91238800000001,36.003912],"type":"Point"}
}