{
  "type": "Feature",
  "properties": {
    "iso:country":"US",
    "sg:address":"952 US Hwy 64 W",
    "sg:city":"Apex",
    "sg:classifiers":[
        {
            "category":"Personal",
            "subcategory":"Beauty Salon",
            "type":"Services"
        }
    ],
    "sg:phone":"+1 919 233 9960",
    "sg:postcode":"27523",
    "sg:province":"NC",
    "sg:tags":[
        "health"
    ],
    "wof:name":"Dermatek LP",
    "wof:placetype":"venue"
},
  "geometry": {"coordinates":[-78.82546000000001,35.74467],"type":"Point"}
}