{
  "type": "Feature",
  "properties": {
    "iso:country":"US",
    "sg:address":"320 Nottingham Dr",
    "sg:city":"Linwood",
    "sg:classifiers":[
        {
            "category":"Building & Trades",
            "subcategory":"Construction",
            "type":"Services"
        }
    ],
    "sg:phone":"+1 336 853 8494",
    "sg:postcode":"27299",
    "sg:province":"NC",
    "sg:tags":[
        "residential"
    ],
    "wof:name":"Brock Construction Co",
    "wof:placetype":"venue"
},
  "geometry": {"coordinates":[-80.38419,35.762004],"type":"Point"}
}