{
  "type": "Feature",
  "properties": {
    "iso:country":"US",
    "sg:address":"341 Tenney Cir",
    "sg:city":"Chapel Hill",
    "sg:classifiers":[
        {
            "category":"Banks & Credit Unions",
            "subcategory":"Investment Brokerage",
            "type":"Services"
        }
    ],
    "sg:phone":"+1 919 286 0721",
    "sg:postcode":"27514",
    "sg:province":"NC",
    "sg:tags":[
        "consultant",
        "financing"
    ],
    "sg:website":"www.rjkinc.com",
    "wof:name":"Ross Johnston & Kersting Inc",
    "wof:placetype":"venue"
},
  "geometry": {"coordinates":[-79.043559,35.920441],"type":"Point"}
}