{
  "type": "Feature",
  "properties": {
    "addr:full":"1101 S Main St Laurinburg NC 28352",
    "addr:housenumber":"1101",
    "addr:postcode":"28352",
    "addr:street":"S Main St",
    "iso:country":"US",
    "sg:address":"1101 S Main St",
    "sg:city":"Laurinburg",
    "sg:classifiers":[
        {
            "category":"Retail",
            "subcategory":"Repair Shop",
            "type":"Services"
        }
    ],
    "sg:phone":"+1 910 276 6401",
    "sg:postcode":"28352",
    "sg:province":"NC",
    "sg:tags":[
        "appliance"
    ],
    "wof:name":"Carolina Home Appliance",
    "wof:placetype":"venue"
},
  "geometry": {"coordinates":[-79.46791899999999,34.76416],"type":"Point"}
}