{
  "type": "Feature",
  "properties": {
    "addr:full":"4927 Silabert Ave Charlotte NC 28205",
    "addr:housenumber":"4927",
    "addr:postcode":"28205",
    "addr:street":"Silabert Ave",
    "iso:country":"US",
    "sg:address":"4927 Silabert Ave",
    "sg:city":"Charlotte",
    "sg:classifiers":[
        {
            "category":"Wholesale",
            "subcategory":"Auto Parts",
            "type":"Manufacturing & Wholesale Goods"
        }
    ],
    "sg:phone":"+1 704 537 1924",
    "sg:postcode":"28205",
    "sg:province":"NC",
    "sg:tags":[
        "supply"
    ],
    "wof:name":"Apx Management  Inc",
    "wof:placetype":"venue"
},
  "geometry": {"coordinates":[-80.780681,35.189232],"type":"Point"}
}