{
  "type": "Feature",
  "properties": {
    "iso:country":"US",
    "sg:address":"5201 Linwick Dr",
    "sg:city":"Fuquay Varina",
    "sg:classifiers":[
        {
            "category":"Recreation",
            "type":"Entertainment"
        }
    ],
    "sg:phone":"+1 919 552 1006",
    "sg:postcode":"27526",
    "sg:province":"NC",
    "sg:tags":[
        "club",
        "membership"
    ],
    "wof:name":"Fuquay Varina Jr Womens Club",
    "wof:placetype":"venue"
},
  "geometry": {"coordinates":[-78.7709,35.638371],"type":"Point"}
}