{
  "type": "Feature",
  "properties": {
    "iso:country":"US",
    "sg:address":"1320 Airlie Rd",
    "sg:city":"Wilmington",
    "sg:classifiers":[
        {
            "category":"Wholesale",
            "subcategory":"Sporting Goods",
            "type":"Manufacturing & Wholesale Goods"
        }
    ],
    "sg:phone":"+1 910 256 6800",
    "sg:postcode":"28403",
    "sg:province":"NC",
    "sg:website":"www.alphamarinecorp.com",
    "wof:name":"Alpha Marine Contractors",
    "wof:placetype":"venue"
},
  "geometry": {"coordinates":[-77.81527199999999,34.216867],"type":"Point"}
}