{
  "type": "Feature",
  "properties": {
    "iso:country":"US",
    "sg:address":"1800 E Franklin St",
    "sg:city":"Chapel Hill",
    "sg:classifiers":[
        {
            "category":"Ice Cream",
            "type":"Food & Drink"
        }
    ],
    "sg:menulink":"http://www.allmenus.com/nc/chapel-hill/209191-tcby/menu/",
    "sg:phone":"+1 919 967 0629",
    "sg:postcode":"27514",
    "sg:province":"NC",
    "sg:tags":[
        "smoothy",
        "juice",
        "american"
    ],
    "wof:name":"TCBY",
    "wof:placetype":"venue"
},
  "geometry": {"coordinates":[-79.02593299999999,35.936915],"type":"Point"}
}