{
  "type": "Feature",
  "properties": {
    "addr:full":"1813 Watlington Dr Charlotte NC 28270",
    "addr:housenumber":"1813",
    "addr:postcode":"28270",
    "addr:street":"Watlington Dr",
    "iso:country":"US",
    "sg:address":"1813 Watlington Dr",
    "sg:city":"Charlotte",
    "sg:classifiers":[
        {
            "category":"Insurance",
            "subcategory":"Insurance Agent",
            "type":"Services"
        }
    ],
    "sg:phone":"+1 704 847 5179",
    "sg:postcode":"28270",
    "sg:province":"NC",
    "wof:name":"Sutton Insurance Services",
    "wof:placetype":"venue"
},
  "geometry": {"coordinates":[-80.738315,35.100725],"type":"Point"}
}