{
  "type": "Feature",
  "properties": {
    "addr:full":"4318 Market St Wilmington NC 28403",
    "addr:housenumber":"4318",
    "addr:postcode":"28403",
    "addr:street":"Market St",
    "iso:country":"US",
    "sg:address":"4318 Market St",
    "sg:city":"Wilmington",
    "sg:classifiers":[
        {
            "category":"Personal",
            "subcategory":"Beauty Salon",
            "type":"Services"
        }
    ],
    "sg:phone":"+1 910 763 0891",
    "sg:postcode":"28403",
    "sg:province":"NC",
    "wof:name":"Us Nail",
    "wof:placetype":"venue"
},
  "geometry": {"coordinates":[-77.890987,34.242464],"type":"Point"}
}