{
  "type": "Feature",
  "properties": {
    "iso:country":"US",
    "sg:address":"3002 Bridges St",
    "sg:city":"Morehead City",
    "sg:classifiers":[
        {
            "category":"Restaurant",
            "type":"Food & Drink"
        }
    ],
    "sg:phone":"+1 252 247 2838",
    "sg:postcode":"28557",
    "sg:province":"NC",
    "wof:name":"Mrs Willis's Too",
    "wof:placetype":"venue"
},
  "geometry": {"coordinates":[-76.74296200000001,34.72733],"type":"Point"}
}