{
  "type": "Feature",
  "properties": {
    "addr:full":"1001 Marshall St S Winston Salem NC 27101",
    "addr:housenumber":"1001",
    "addr:postcode":"27101",
    "addr:street":"Marshall St S",
    "iso:country":"US",
    "sg:address":"1001 Marshall St S",
    "sg:city":"Winston Salem",
    "sg:classifiers":[
        {
            "category":"Organizations",
            "subcategory":"Religious Organization",
            "type":"Services"
        }
    ],
    "sg:phone":"+1 336 722 3773",
    "sg:postcode":"27101",
    "sg:province":"NC",
    "sg:tags":[
        "church"
    ],
    "wof:name":"Marcus Barr Ministries Inc",
    "wof:placetype":"venue"
},
  "geometry": {"coordinates":[-80.243439,36.083366],"type":"Point"}
}