{
  "type": "Feature",
  "properties": {
    "addr:full":"300 The Cape Blvd Wilmington NC 28412",
    "addr:housenumber":"300",
    "addr:postcode":"28412",
    "addr:street":"The Cape Blvd",
    "iso:country":"US",
    "sg:address":"300 The Cape Blvd",
    "sg:city":"Wilmington",
    "sg:classifiers":[
        {
            "category":"Social Services",
            "subcategory":"Child Care",
            "type":"Services"
        }
    ],
    "sg:phone":"+1 910 392 1560",
    "sg:postcode":"28412",
    "sg:province":"NC",
    "wof:name":"Carolina Preschool",
    "wof:placetype":"venue"
},
  "geometry": {"coordinates":[-77.916584,34.075708],"type":"Point"}
}