{
  "type": "Feature",
  "properties": {
    "addr:full":"2627 Rockford Rd Shelby NC 28152",
    "addr:housenumber":"2627",
    "addr:postcode":"28152",
    "addr:street":"Rockford Rd",
    "iso:country":"US",
    "sg:address":"2627 Rockford Rd",
    "sg:city":"Shelby",
    "sg:classifiers":[
        {
            "category":"Manufacturing",
            "subcategory":"Textiles",
            "type":"Manufacturing & Wholesale Goods"
        }
    ],
    "sg:phone":"+1 704 434 5098",
    "sg:postcode":"28152",
    "sg:province":"NC",
    "sg:tags":[
        "rug",
        "carpet"
    ],
    "wof:name":"Stroud Braided Rug Co",
    "wof:placetype":"venue"
},
  "geometry": {"coordinates":[-81.700033,35.244444],"type":"Point"}
}