{
  "type": "Feature",
  "properties": {
    "iso:country":"US",
    "sg:address":"106 Chapman Dr",
    "sg:city":"Asheville",
    "sg:classifiers":[
        {
            "category":"Professional",
            "subcategory":"Research",
            "type":"Services"
        }
    ],
    "sg:phone":"+1 828 299 7118",
    "sg:postcode":"28805",
    "sg:province":"NC",
    "sg:tags":[
        "environmental",
        "ecological"
    ],
    "wof:name":"Blue Ridge Environmental Svc",
    "wof:placetype":"venue"
},
  "geometry": {"coordinates":[-82.45862,35.624753],"type":"Point"}
}