{
  "type": "Feature",
  "properties": {
    "addr:full":"7445 Dallas Cherryville Hwy Cherryville NC 28021",
    "addr:housenumber":"7445",
    "addr:postcode":"28021",
    "addr:street":"Dallas Cherryville Hwy",
    "iso:country":"US",
    "sg:address":"7445 Dallas Cherryville Hwy",
    "sg:city":"Cherryville",
    "sg:classifiers":[
        {
            "category":"Retail",
            "subcategory":"Auto Repair",
            "type":"Services"
        }
    ],
    "sg:phone":"+1 704 435 9241",
    "sg:postcode":"28021",
    "sg:province":"NC",
    "sg:tags":[
        "body",
        "automobile",
        "painting"
    ],
    "wof:name":"Cherry Auto Paint",
    "wof:placetype":"venue"
},
  "geometry": {"coordinates":[-81.344551,35.384024],"type":"Point"}
}