{
  "type": "Feature",
  "properties": {
    "iso:country":"US",
    "sg:address":"2817 Buckboard Ln",
    "sg:city":"Raleigh",
    "sg:classifiers":[
        {
            "category":"Building & Trades",
            "subcategory":"Plumbing",
            "type":"Services"
        }
    ],
    "sg:phone":"+1 919 779 2736",
    "sg:postcode":"27603",
    "sg:province":"NC",
    "sg:tags":[
        "conditioning",
        "air",
        "system",
        "contractor"
    ],
    "wof:name":"A C Heating Experts",
    "wof:placetype":"venue"
},
  "geometry": {"coordinates":[-78.67887899999999,35.627129],"type":"Point"}
}