{
  "type": "Feature",
  "properties": {
    "addr:full":"1710 N Center St Hickory NC 28601",
    "addr:housenumber":"1710",
    "addr:postcode":"28601",
    "addr:street":"N Center St",
    "iso:country":"US",
    "sg:address":"1710 N Center St",
    "sg:city":"Hickory",
    "sg:classifiers":[
        {
            "category":"Restaurant",
            "type":"Food & Drink"
        }
    ],
    "sg:phone":"+1 828 322 2630",
    "sg:postcode":"28601",
    "sg:province":"NC",
    "sg:tags":[
        "eating",
        "product",
        "dairy"
    ],
    "wof:name":"Circus Hall Of Cream",
    "wof:placetype":"venue"
},
  "geometry": {"coordinates":[-81.336189,35.755314],"type":"Point"}
}