{
  "type": "Feature",
  "properties": {
    "iso:country":"US",
    "sg:address":"1141 N Horner Blvd",
    "sg:city":"Sanford",
    "sg:classifiers":[
        {
            "category":"Food & Beverages",
            "subcategory":"Groceries & Convenience Stores",
            "type":"Retail Goods"
        }
    ],
    "sg:phone":"+1 919 774 4422",
    "sg:postcode":"27330",
    "sg:province":"NC",
    "sg:tags":[
        "grocer"
    ],
    "wof:name":"Scotchman Food",
    "wof:placetype":"venue"
},
  "geometry": {"coordinates":[-79.197868,35.496956],"type":"Point"}
}