{
  "type": "Feature",
  "properties": {
    "addr:full":"130 Quade Dr Cary NC 27513",
    "addr:housenumber":"130",
    "addr:postcode":"27513",
    "addr:street":"Quade Dr",
    "iso:country":"US",
    "sg:address":"130 Quade Dr",
    "sg:city":"Cary",
    "sg:classifiers":[
        {
            "category":"Wholesale",
            "subcategory":"Machinery & Supplies",
            "type":"Manufacturing & Wholesale Goods"
        }
    ],
    "sg:phone":"+1 919 481 1031",
    "sg:postcode":"27513",
    "sg:province":"NC",
    "sg:tags":[
        "equipment",
        "industrial"
    ],
    "wof:name":"Cross System Components",
    "wof:placetype":"venue"
},
  "geometry": {"coordinates":[-78.804542,35.817291],"type":"Point"}
}