{
  "type": "Feature",
  "properties": {
    "addr:full":"711 N Dekalb St Shelby NC 28150",
    "addr:housenumber":"711",
    "addr:postcode":"28150",
    "addr:street":"N Dekalb St",
    "iso:country":"US",
    "sg:address":"711 N Dekalb St",
    "sg:city":"Shelby",
    "sg:classifiers":[
        {
            "category":"Health Services",
            "subcategory":"Doctor",
            "type":"Services"
        }
    ],
    "sg:phone":"+1 704 482 1482",
    "sg:postcode":"28150",
    "sg:province":"NC",
    "sg:tags":[
        "specializing",
        "physician",
        "surgeon",
        "internal",
        "medicine"
    ],
    "wof:name":"Shelby Medical Associates PC",
    "wof:placetype":"venue"
},
  "geometry": {"coordinates":[-81.535562,35.301573],"type":"Point"}
}