{
  "type": "Feature",
  "properties": {
    "iso:country":"US",
    "sg:address":"3728 W Wendover Ave",
    "sg:city":"Greensboro",
    "sg:classifiers":[
        {
            "category":"Retail",
            "subcategory":"Auto Repair",
            "type":"Services"
        }
    ],
    "sg:phone":"+1 336 854 1616",
    "sg:postcode":"27407",
    "sg:province":"NC",
    "sg:tags":[
        "wrecker"
    ],
    "wof:name":"Jeff's Classic",
    "wof:placetype":"venue"
},
  "geometry": {"coordinates":[-79.87078099999999,36.060193],"type":"Point"}
}