{
  "type": "Feature",
  "properties": {
    "addr:full":"1700 W Innes St Salisbury NC 28144",
    "addr:housenumber":"1700",
    "addr:postcode":"28144",
    "addr:street":"W Innes St",
    "iso:country":"US",
    "sg:address":"1700 W Innes St",
    "sg:city":"Salisbury",
    "sg:classifiers":[
        {
            "category":"Shopping",
            "subcategory":"Musical Instruments",
            "type":"Retail Goods"
        }
    ],
    "sg:phone":"+1 704 638 9955",
    "sg:postcode":"28144",
    "sg:province":"NC",
    "sg:tags":[
        "music",
        "store"
    ],
    "wof:name":"Music Center Inc",
    "wof:placetype":"venue"
},
  "geometry": {"coordinates":[-80.483065,35.684988],"type":"Point"}
}