{
  "type": "Feature",
  "properties": {
    "iso:country":"US",
    "sg:address":"1501 Ward Blvd",
    "sg:city":"Wilson",
    "sg:classifiers":[
        {
            "category":"Restaurant",
            "type":"Food & Drink"
        }
    ],
    "sg:phone":"+1 252 237 9322",
    "sg:postcode":"27893",
    "sg:province":"NC",
    "sg:tags":[
        "parlor",
        "ice",
        "cream"
    ],
    "wof:name":"Dairy O",
    "wof:placetype":"venue"
},
  "geometry": {"coordinates":[-77.93560600000001,35.725372],"type":"Point"}
}