{
  "type": "Feature",
  "properties": {
    "iso:country":"US",
    "sg:address":"258 W Main St",
    "sg:city":"Mooresboro",
    "sg:classifiers":[
        {
            "category":"Home & Garden",
            "subcategory":"Building Materials",
            "type":"Retail Goods"
        }
    ],
    "sg:phone":"+1 828 657 6969",
    "sg:postcode":"28114",
    "sg:province":"SC",
    "sg:tags":[
        "glass",
        "window",
        "plate"
    ],
    "wof:name":"Custom Stain & Glass Interiors",
    "wof:placetype":"venue"
},
  "geometry": {"coordinates":[-81.699332,35.299534],"type":"Point"}
}