{
  "type": "Feature",
  "properties": {
    "addr:full":"10309 Royster Rd NE Leland NC 28451",
    "addr:postcode":"10309;28451",
    "addr:street":"Royster Rd Ne",
    "iso:country":"US",
    "sg:address":"10309 Royster Rd NE",
    "sg:city":"Leland",
    "sg:classifiers":[
        {
            "category":"Building & Trades",
            "subcategory":"Construction",
            "type":"Services"
        }
    ],
    "sg:phone":"+1 910 371 3925",
    "sg:postcode":"28451",
    "sg:province":"NC",
    "sg:tags":[
        "house",
        "contractor"
    ],
    "wof:name":"R A Schatz Construction",
    "wof:placetype":"venue"
},
  "geometry": {"coordinates":[-78.006809,34.270422],"type":"Point"}
}