{
  "type": "Feature",
  "properties": {
    "iso:country":"US",
    "sg:address":"18015 Kings Point Dr",
    "sg:city":"Cornelius",
    "sg:classifiers":[
        {
            "category":"Real Estate",
            "subcategory":"Real Estate Operator",
            "type":"Services"
        }
    ],
    "sg:phone":"+1 704 896 0682",
    "sg:postcode":"28031",
    "sg:province":"NC",
    "sg:tags":[
        "property",
        "lessor"
    ],
    "wof:name":"Smplyred & Romott LLC",
    "wof:placetype":"venue"
},
  "geometry": {"coordinates":[-80.892674,35.458321],"type":"Point"}
}