{
  "type": "Feature",
  "properties": {
    "iso:country":"US",
    "sg:address":"4293 Brown Loop",
    "sg:city":"Randleman",
    "sg:classifiers":[
        {
            "category":"Retail",
            "subcategory":"Repair Shop",
            "type":"Services"
        }
    ],
    "sg:phone":"+1 336 498 6414",
    "sg:postcode":"27317",
    "sg:province":"NC",
    "sg:tags":[
        "upholsterer"
    ],
    "wof:name":"Harold's Custom Upholstery",
    "wof:placetype":"venue"
},
  "geometry": {"coordinates":[-79.834625,35.813438],"type":"Point"}
}