{
  "type": "Feature",
  "properties": {
    "addr:full":"5813 Stratford Ct Harrisburg NC 28075",
    "addr:housenumber":"5813",
    "addr:postcode":"28075",
    "addr:street":"Stratford Ct",
    "iso:country":"US",
    "sg:address":"5813 Stratford Ct",
    "sg:city":"Harrisburg",
    "sg:classifiers":[
        {
            "category":"Professional",
            "subcategory":"Management & Consulting",
            "type":"Services"
        }
    ],
    "sg:phone":"+1   ",
    "sg:postcode":"28075",
    "sg:province":"NC",
    "sg:tags":[
        "business"
    ],
    "wof:name":"Proven Path Consulting Inc",
    "wof:placetype":"venue"
},
  "geometry": {"coordinates":[-80.673136,35.300761],"type":"Point"}
}