{
  "type": "Feature",
  "properties": {
    "iso:country":"US",
    "sg:address":"1024 Robeson St",
    "sg:city":"Fayetteville",
    "sg:classifiers":[
        {
            "category":"Shopping",
            "subcategory":"Musical Instruments",
            "type":"Retail Goods"
        }
    ],
    "sg:phone":"+1 910 323 9187",
    "sg:postcode":"28305",
    "sg:province":"NC",
    "sg:tags":[
        "piano",
        "used",
        "organs"
    ],
    "wof:name":"JML Music",
    "wof:placetype":"venue"
},
  "geometry": {"coordinates":[-78.90167099999999,35.040655],"type":"Point"}
}