{
  "type": "Feature",
  "properties": {
    "addr:full":"803 Piedmont Ave Gibsonville NC 27249",
    "addr:housenumber":"803",
    "addr:postcode":"27249",
    "addr:street":"Piedmont Ave",
    "iso:country":"US",
    "sg:address":"803 Piedmont Ave",
    "sg:city":"Gibsonville",
    "sg:classifiers":[
        {
            "category":"Retail",
            "subcategory":"Repair Shop",
            "type":"Services"
        }
    ],
    "sg:phone":"+1   ",
    "sg:postcode":"27249",
    "sg:province":"NC",
    "sg:tags":[
        "taxidermist"
    ],
    "wof:name":"Gantos Taxidermy",
    "wof:placetype":"venue"
},
  "geometry": {"coordinates":[-79.52806099999999,36.126305],"type":"Point"}
}