{
  "type": "Feature",
  "properties": {
    "iso:country":"US",
    "sg:address":"409 Butler Bridge Rd",
    "sg:city":"Fletcher",
    "sg:classifiers":[
        {
            "category":"Freight",
            "type":"Transportation"
        }
    ],
    "sg:phone":"+1 828 684 7568",
    "sg:postcode":"28732",
    "sg:province":"NC",
    "sg:tags":[
        "trucking"
    ],
    "wof:name":"Carolina Truck Connection",
    "wof:placetype":"venue"
},
  "geometry": {"coordinates":[-82.520995,35.40691],"type":"Point"}
}