{
  "type": "Feature",
  "properties": {
    "iso:country":"US",
    "sg:address":"501 N Main St",
    "sg:city":"Louisburg",
    "sg:classifiers":[
        {
            "category":"Building & Trades",
            "subcategory":"Construction",
            "type":"Services"
        }
    ],
    "sg:phone":"+1 919 496 3875",
    "sg:postcode":"27549",
    "sg:province":"NC",
    "sg:tags":[
        "contractor"
    ],
    "wof:name":"Davis Price",
    "wof:placetype":"venue"
},
  "geometry": {"coordinates":[-78.29675,36.105019],"type":"Point"}
}