{
  "type": "Feature",
  "properties": {
    "addr:full":"343 S 5th St Saint Pauls NC 28384",
    "addr:housenumber":"343",
    "addr:postcode":"28384",
    "addr:street":"S 5Th St",
    "iso:country":"US",
    "sg:address":"343 S 5th St",
    "sg:city":"Saint Pauls",
    "sg:classifiers":[
        {
            "category":"Retail",
            "subcategory":"Auto Repair",
            "type":"Services"
        }
    ],
    "sg:phone":"+1   ",
    "sg:postcode":"28384",
    "sg:province":"NC",
    "sg:tags":[
        "transmission",
        "general"
    ],
    "wof:name":"Mastertech",
    "wof:placetype":"venue"
},
  "geometry": {"coordinates":[-78.97690299999999,34.803985],"type":"Point"}
}