{
  "type": "Feature",
  "properties": {
    "addr:full":"941 S Chapman St Greensboro NC 27403",
    "addr:housenumber":"941",
    "addr:postcode":"27403",
    "addr:street":"S Chapman St",
    "iso:country":"US",
    "sg:address":"941 S Chapman St",
    "sg:city":"Greensboro",
    "sg:classifiers":[
        {
            "category":"Autos & Motor Vehicles",
            "subcategory":"Auto Supplies",
            "type":"Retail Goods"
        }
    ],
    "sg:phone":"+1 336 378 1252",
    "sg:postcode":"27403",
    "sg:province":"NC",
    "sg:tags":[
        "equipment",
        "racing",
        "car",
        "automobile"
    ],
    "sg:website":"www.turbotuneusltd.com",
    "wof:name":"Turbo-TUNE Us LTD",
    "wof:placetype":"venue"
},
  "geometry": {"coordinates":[-79.823759,36.063509],"type":"Point"}
}