{
  "type": "Feature",
  "properties": {
    "addr:full":"2955 Cauble Rd Salisbury NC 28144",
    "addr:housenumber":"2955",
    "addr:postcode":"28144",
    "addr:street":"Cauble Rd",
    "iso:country":"US",
    "sg:address":"2955 Cauble Rd",
    "sg:city":"Salisbury",
    "sg:classifiers":[
        {
            "category":"Sports & Exercise",
            "subcategory":"Gym",
            "type":"Entertainment"
        }
    ],
    "sg:phone":"+1   ",
    "sg:postcode":"28144",
    "sg:province":"NC",
    "sg:tags":[
        "fitness",
        "physical",
        "facility"
    ],
    "wof:name":"At The Gym",
    "wof:placetype":"venue"
},
  "geometry": {"coordinates":[-80.479874,35.736306],"type":"Point"}
}