{
  "type": "Feature",
  "properties": {
    "iso:country":"US",
    "sg:address":"1503 E Center St Exd",
    "sg:city":"Lexington",
    "sg:classifiers":[
        {
            "category":"Professional",
            "subcategory":"Advertising",
            "type":"Services"
        }
    ],
    "sg:phone":"+1 336 236 7447",
    "sg:postcode":"27292",
    "sg:province":"NC",
    "sg:tags":[
        "counselor"
    ],
    "wof:name":"Media Matters",
    "wof:placetype":"venue"
},
  "geometry": {"coordinates":[-80.230512,35.8036],"type":"Point"}
}