{
  "type": "Feature",
  "properties": {
    "iso:country":"US",
    "sg:address":"102 la Mancha Dr",
    "sg:city":"Asheville",
    "sg:classifiers":[
        {
            "category":"Real Estate",
            "subcategory":"Real Estate Operator",
            "type":"Services"
        }
    ],
    "sg:phone":"+1 828 298 1970",
    "sg:postcode":"28805",
    "sg:province":"NC",
    "sg:tags":[
        "building",
        "apartment"
    ],
    "wof:name":"Parkway Crossing Apts",
    "wof:placetype":"venue"
},
  "geometry": {"coordinates":[-82.471512,35.592892],"type":"Point"}
}