{
  "type": "Feature",
  "properties": {
    "addr:full":"269 Manns Chapel Rd Pittsboro NC 27312",
    "addr:housenumber":"269",
    "addr:postcode":"27312",
    "addr:street":"Manns Chapel Rd",
    "iso:country":"US",
    "sg:address":"269 Manns Chapel Rd",
    "sg:city":"Pittsboro",
    "sg:classifiers":[
        {
            "category":"Organizations",
            "subcategory":"Religious Organization",
            "type":"Services"
        }
    ],
    "sg:phone":"+1   ",
    "sg:postcode":"27312",
    "sg:province":"NC",
    "wof:name":"Mount Plsant Untd Mthdst Chrch",
    "wof:placetype":"venue"
},
  "geometry": {"coordinates":[-79.155839,35.811211],"type":"Point"}
}