{
  "type": "Feature",
  "properties": {
    "iso:country":"US",
    "sg:address":"1917 W Innes St",
    "sg:city":"Salisbury",
    "sg:classifiers":[
        {
            "category":"Banks & Credit Unions",
            "subcategory":"Bank",
            "type":"Services"
        }
    ],
    "sg:phone":"+1 704 797 8604",
    "sg:postcode":"28144",
    "sg:province":"NC",
    "sg:tags":[
        "loan",
        "mortgage",
        "real estate"
    ],
    "wof:name":"First Metropolitan Mortgage",
    "wof:placetype":"venue"
},
  "geometry": {"coordinates":[-80.48336500000001,35.686441],"type":"Point"}
}