{
  "type": "Feature",
  "properties": {
    "iso:country":"US",
    "sg:address":"137 Broad St",
    "sg:city":"Spruce Pine",
    "sg:classifiers":[
        {
            "category":"Professional",
            "subcategory":"Lawyer & Legal Services",
            "type":"Services"
        }
    ],
    "sg:phone":"+1 828 765 1816",
    "sg:postcode":"28777",
    "sg:province":"NC",
    "sg:tags":[
        "attorney"
    ],
    "wof:name":"Brian Buchanan",
    "wof:placetype":"venue"
},
  "geometry": {"coordinates":[-82.062201,35.910354],"type":"Point"}
}