{
  "type": "Feature",
  "properties": {
    "iso:country":"US",
    "sg:address":"455 N Church St",
    "sg:city":"Winston Salem",
    "sg:classifiers":[
        {
            "category":"Government",
            "subcategory":"Office",
            "type":"Public Place"
        }
    ],
    "sg:phone":"+1 336 727 2132",
    "sg:postcode":"27101",
    "sg:province":"NC",
    "sg:tags":[
        "village"
    ],
    "wof:name":"4th-Church Street Parking Deck",
    "wof:placetype":"venue"
},
  "geometry": {"coordinates":[-80.243219,36.099313],"type":"Point"}
}