{
  "type": "Feature",
  "properties": {
    "addr:full":"516 Elkin Hwy North Wilkesboro NC 28659",
    "addr:housenumber":"516",
    "addr:postcode":"28659",
    "addr:street":"Elkin Hwy",
    "iso:country":"US",
    "sg:address":"516 Elkin Hwy",
    "sg:city":"North Wilkesboro",
    "sg:classifiers":[
        {
            "category":"Autos & Motor Vehicles",
            "subcategory":"Automobile Sales",
            "type":"Retail Goods"
        }
    ],
    "sg:phone":"+1 336 838 4188",
    "sg:postcode":"28659",
    "sg:province":"NC",
    "sg:tags":[
        "car",
        "dealer"
    ],
    "wof:name":"Carolina Auto Sales",
    "wof:placetype":"venue"
},
  "geometry": {"coordinates":[-81.13337300000001,36.182571],"type":"Point"}
}