{
  "type": "Feature",
  "properties": {
    "iso:country":"US",
    "sg:address":"5401 York Hwy",
    "sg:city":"Gastonia",
    "sg:classifiers":[
        {
            "category":"Wholesale",
            "subcategory":"Scrap",
            "type":"Manufacturing & Wholesale Goods"
        }
    ],
    "sg:phone":"+1 704 864 9001",
    "sg:postcode":"28052",
    "sg:province":"NC",
    "sg:tags":[
        "metal"
    ],
    "wof:name":"State Line Scrap Metal Inc",
    "wof:placetype":"venue"
},
  "geometry": {"coordinates":[-81.196466,35.173988],"type":"Point"}
}