{
  "type": "Feature",
  "properties": {
    "addr:full":"100 Hader St Spindale NC 28147",
    "addr:housenumber":"100",
    "addr:postcode":"28147",
    "addr:street":"Hader St",
    "iso:country":"US",
    "sg:address":"100 Hader St",
    "sg:city":"Spindale",
    "sg:classifiers":[
        {
            "category":"Retail",
            "subcategory":"Auto Repair",
            "type":"Services"
        }
    ],
    "sg:phone":"+1   ",
    "sg:postcode":"28147",
    "sg:province":"NC",
    "sg:tags":[
        "body"
    ],
    "wof:name":"Knights Body Shop",
    "wof:placetype":"venue"
},
  "geometry": {"coordinates":[-80.525739,35.625004],"type":"Point"}
}