{
  "type": "Feature",
  "properties": {
    "addr:full":"5925 Western Trl Greensboro NC 27410",
    "addr:housenumber":"5925",
    "addr:postcode":"27410",
    "addr:street":"Western Trl",
    "iso:country":"US",
    "sg:address":"5925 Western Trl",
    "sg:city":"Greensboro",
    "sg:classifiers":[
        {
            "category":"Building & Trades",
            "subcategory":"Construction",
            "type":"Services"
        }
    ],
    "sg:phone":"+1 336 989 6371",
    "sg:postcode":"27410",
    "sg:province":"NC",
    "sg:tags":[
        "roofing",
        "contractor"
    ],
    "wof:name":"S & S Construction",
    "wof:placetype":"venue"
},
  "geometry": {"coordinates":[-79.917665,36.12237],"type":"Point"}
}