{
  "type": "Feature",
  "properties": {
    "addr:full":"309 10th St North Wilkesboro NC 28659",
    "addr:housenumber":"309",
    "addr:postcode":"28659",
    "addr:street":"10Th St",
    "iso:country":"US",
    "sg:address":"309 10th St",
    "sg:city":"North Wilkesboro",
    "sg:classifiers":[
        {
            "category":"Personal",
            "subcategory":"Beauty Salon",
            "type":"Services"
        }
    ],
    "sg:phone":"+1   ",
    "sg:postcode":"28659",
    "sg:province":"NC",
    "sg:tags":[
        "shop"
    ],
    "wof:name":"Hair Designs On 10th",
    "wof:placetype":"venue"
},
  "geometry": {"coordinates":[-81.148529,36.159913],"type":"Point"}
}