{
  "type": "Feature",
  "properties": {
    "addr:full":"9005 Potter Rd S Waxhaw NC 28173",
    "addr:housenumber":"9005",
    "addr:postcode":"28173",
    "addr:street":"Potter Rd",
    "iso:country":"US",
    "sg:address":"9005 Potter Rd S",
    "sg:city":"Waxhaw",
    "sg:classifiers":[
        {
            "category":"Building & Trades",
            "subcategory":"Construction",
            "type":"Services"
        }
    ],
    "sg:phone":"+1 704 843 3108",
    "sg:postcode":"28173",
    "sg:province":"NC",
    "sg:tags":[
        "contractor"
    ],
    "wof:name":"Belk",
    "wof:placetype":"venue"
},
  "geometry": {"coordinates":[-80.645337,34.818573],"type":"Point"}
}