{
  "type": "Feature",
  "properties": {
    "iso:country":"US",
    "sg:address":"3739 Atlas Dr",
    "sg:city":"Charlotte",
    "sg:classifiers":[
        {
            "category":"Professional",
            "subcategory":"Art Services",
            "type":"Services"
        }
    ],
    "sg:phone":"+1   ",
    "sg:postcode":"28269",
    "sg:province":"NC",
    "sg:tags":[
        "photography",
        "commercial"
    ],
    "wof:name":"Pretty As Picture",
    "wof:placetype":"venue"
},
  "geometry": {"coordinates":[-80.828371,35.28999],"type":"Point"}
}