{
  "type": "Feature",
  "properties": {
    "addr:full":"1811 Lucas Rd Knightdale NC 27545",
    "addr:housenumber":"1811",
    "addr:postcode":"27545",
    "addr:street":"Lucas Rd",
    "iso:country":"US",
    "sg:address":"1811 Lucas Rd",
    "sg:city":"Knightdale",
    "sg:classifiers":[
        {
            "category":"Real Estate",
            "subcategory":"Real Estate Operator",
            "type":"Services"
        }
    ],
    "sg:phone":"+1 919 266 1467",
    "sg:postcode":"27545",
    "sg:province":"NC",
    "sg:tags":[
        "mobile",
        "home",
        "part"
    ],
    "wof:name":"Fox Run Mobile Home Subdv",
    "wof:placetype":"venue"
},
  "geometry": {"coordinates":[-78.47184900000001,35.824529],"type":"Point"}
}