{
  "type": "Feature",
  "properties": {
    "iso:country":"US",
    "sg:address":"3215 N Davidson St",
    "sg:city":"Charlotte",
    "sg:classifiers":[
        {
            "category":"Deli",
            "type":"Food & Drink"
        }
    ],
    "sg:menulink":"http://www.allmenus.com/nc/charlotte/37784-the-salvador-deli/menu/",
    "sg:phone":"+1 704 334 2344",
    "sg:postcode":"28205",
    "sg:province":"NC",
    "sg:tags":[
        "american"
    ],
    "wof:name":"The Salvador Deli",
    "wof:placetype":"venue"
},
  "geometry": {"coordinates":[-80.805594,35.247091],"type":"Point"}
}