{
  "type": "Feature",
  "properties": {
    "iso:country":"US",
    "sg:address":"6214 US Hwy 70",
    "sg:city":"Durham",
    "sg:classifiers":[
        {
            "category":"Real Estate",
            "subcategory":"Real Estate Operator",
            "type":"Services"
        }
    ],
    "sg:phone":"+1 919 383 6303",
    "sg:postcode":"27705",
    "sg:province":"NC",
    "sg:tags":[
        "building",
        "nonresidential"
    ],
    "wof:name":"Micol Properties LLC",
    "wof:placetype":"venue"
},
  "geometry": {"coordinates":[-78.989423,36.03229],"type":"Point"}
}