{
  "type": "Feature",
  "properties": {
    "iso:country":"US",
    "sg:address":"1101 Virginia St SW",
    "sg:city":"Lenoir",
    "sg:classifiers":[
        {
            "category":"Food & Beverages",
            "subcategory":"Groceries & Convenience Stores",
            "type":"Retail Goods"
        }
    ],
    "sg:phone":"+1 828 754 2524",
    "sg:postcode":"28645",
    "sg:province":"NC",
    "sg:tags":[
        "grocer",
        "gasoline"
    ],
    "wof:name":"D & D Miller Hill Grocery Inc",
    "wof:placetype":"venue"
},
  "geometry": {"coordinates":[-81.556026,35.888163],"type":"Point"}
}