{
  "type": "Feature",
  "properties": {
    "addr:full":"1424 Mordecai Dr Raleigh NC 27604",
    "addr:housenumber":"1424",
    "addr:postcode":"27604",
    "addr:street":"Mordecai Dr",
    "iso:country":"US",
    "sg:address":"1424 Mordecai Dr",
    "sg:city":"Raleigh",
    "sg:classifiers":[
        {
            "category":"Professional",
            "subcategory":"Management & Consulting",
            "type":"Services"
        }
    ],
    "sg:phone":"+1   ",
    "sg:postcode":"27604",
    "sg:province":"NC",
    "wof:name":"Julia Bryan Consulting",
    "wof:placetype":"venue"
},
  "geometry": {"coordinates":[-78.62768699999999,35.799423],"type":"Point"}
}