{
  "type": "Feature",
  "properties": {
    "addr:full":"5285 Phillips Rd Scotland Neck NC 27874",
    "addr:housenumber":"5285",
    "addr:postcode":"27874",
    "addr:street":"Phillips Rd",
    "iso:country":"US",
    "sg:address":"5285 Phillips Rd",
    "sg:city":"Scotland Neck",
    "sg:classifiers":[
        {
            "category":"Professional",
            "type":"Services"
        }
    ],
    "sg:phone":"+1 252 826 6516",
    "sg:postcode":"27874",
    "sg:province":"NC",
    "wof:name":"Murphy Brown Lnmnc",
    "wof:placetype":"venue"
},
  "geometry": {"coordinates":[-77.49740300000001,36.084841],"type":"Point"}
}