{
  "type": "Feature",
  "properties": {
    "addr:full":"379 Mark Ln North Wilkesboro NC 28659",
    "addr:housenumber":"379",
    "addr:postcode":"28659",
    "addr:street":"Mark Ln",
    "iso:country":"US",
    "sg:address":"379 Mark Ln",
    "sg:city":"North Wilkesboro",
    "sg:classifiers":[
        {
            "category":"Organizations",
            "subcategory":"Religious Organization",
            "type":"Services"
        }
    ],
    "sg:phone":"+1   ",
    "sg:postcode":"28659",
    "sg:province":"NC",
    "wof:name":"Closer Walk With God Baptist",
    "wof:placetype":"venue"
},
  "geometry": {"coordinates":[-81.095866,36.123178],"type":"Point"}
}