{
  "type": "Feature",
  "properties": {
    "addr:full":"5723 Country Club Rd Winston Salem NC 27104",
    "addr:housenumber":"5723",
    "addr:postcode":"27104",
    "addr:street":"Country Club Rd",
    "iso:country":"US",
    "sg:address":"5723 Country Club Rd",
    "sg:city":"Winston Salem",
    "sg:classifiers":[
        {
            "category":"Recreation",
            "type":"Entertainment"
        }
    ],
    "sg:phone":"+1 336 945 5063",
    "sg:postcode":"27104",
    "sg:province":"NC",
    "sg:tags":[
        "martial",
        "arts",
        "instruction"
    ],
    "sg:website":"www.karateinternational.biz",
    "wof:name":"Karate International-Lewisvill",
    "wof:placetype":"venue"
},
  "geometry": {"coordinates":[-80.37566099999999,36.093656],"type":"Point"}
}