{
  "type": "Feature",
  "properties": {
    "addr:full":"1056 N Andy Griffith Pkwy Mount Airy NC 27030",
    "addr:housenumber":"1056",
    "addr:postcode":"27030",
    "addr:street":"N Andy Griffith Pkwy",
    "iso:country":"US",
    "sg:address":"1056 N Andy Griffith Pkwy",
    "sg:city":"Mount Airy",
    "sg:classifiers":[
        {
            "category":"Shopping",
            "subcategory":"Discount & Variety Stores",
            "type":"Retail Goods"
        }
    ],
    "sg:phone":"+1 336 786 5615",
    "sg:postcode":"27030",
    "sg:province":"NC",
    "wof:name":"Dollarwise",
    "wof:placetype":"venue"
},
  "geometry": {"coordinates":[-80.62518,36.5198],"type":"Point"}
}