{
  "type": "Feature",
  "properties": {
    "addr:full":"1000 Darrington Dr Cary NC 27513",
    "addr:housenumber":"1000",
    "addr:postcode":"27513",
    "addr:street":"Darrington Dr",
    "iso:country":"US",
    "sg:address":"1000 Darrington Dr",
    "sg:city":"Cary",
    "sg:classifiers":[
        {
            "category":"Building & Trades",
            "subcategory":"Construction",
            "type":"Services"
        }
    ],
    "sg:phone":"+1 919 462 0775",
    "sg:postcode":"27513",
    "sg:province":"NC",
    "sg:tags":[
        "contractor"
    ],
    "sg:website":"www.chasepropertiesnc.com",
    "wof:name":"Wardson Construction Inc",
    "wof:placetype":"venue"
},
  "geometry": {"coordinates":[-78.814903,35.7994],"type":"Point"}
}