{
  "type": "Feature",
  "properties": {
    "iso:country":"US",
    "sg:address":"118 S Scales St",
    "sg:city":"Reidsville",
    "sg:classifiers":[
        {
            "category":"Manufacturing",
            "subcategory":"Printing",
            "type":"Manufacturing & Wholesale Goods"
        },
        {
            "category":"Manufacturing",
            "subcategory":"Motor Vehicles & Parts",
            "type":"Manufacturing & Wholesale Goods"
        }
    ],
    "sg:phone":"+1 336 349 7500",
    "sg:postcode":"27320",
    "sg:province":"NC",
    "sg:tags":[
        "screen"
    ],
    "wof:name":"Star Discount Screen Printing",
    "wof:placetype":"venue"
},
  "geometry": {"coordinates":[-79.66437500000001,36.361353],"type":"Point"}
}