{
  "type": "Feature",
  "properties": {
    "iso:country":"US",
    "sg:address":"3571 Lackey St",
    "sg:city":"Lumberton",
    "sg:classifiers":[
        {
            "category":"Banks & Credit Unions",
            "subcategory":"Bank",
            "type":"Services"
        }
    ],
    "sg:phone":"+1 910 739 0060",
    "sg:postcode":"28360",
    "sg:province":"NC",
    "sg:tags":[
        "mortgage"
    ],
    "wof:name":"Weststar Mortgage",
    "wof:placetype":"venue"
},
  "geometry": {"coordinates":[-79.017543,34.640422],"type":"Point"}
}