{
  "type": "Feature",
  "properties": {
    "addr:full":"401 E Whitaker Mill Rd Raleigh NC 27608",
    "addr:housenumber":"401",
    "addr:postcode":"27608",
    "addr:street":"E Whitaker Mill Rd",
    "iso:country":"US",
    "sg:address":"401 E Whitaker Mill Rd",
    "sg:city":"Raleigh",
    "sg:classifiers":[
        {
            "category":"Professional",
            "type":"Services"
        }
    ],
    "sg:phone":"+1 919 754 9960",
    "sg:postcode":"27608",
    "sg:province":"NC",
    "sg:tags":[
        "establishment"
    ],
    "wof:name":"C Asa Comm Alternatives",
    "wof:placetype":"venue"
},
  "geometry": {"coordinates":[-78.63236999999999,35.806636],"type":"Point"}
}