{
  "type": "Feature",
  "properties": {
    "addr:full":"1602 Camellia Dr Elizabeth City NC 27909",
    "addr:housenumber":"1602",
    "addr:postcode":"27909",
    "addr:street":"Camellia Dr",
    "iso:country":"US",
    "sg:address":"1602 Camellia Dr",
    "sg:city":"Elizabeth City",
    "sg:classifiers":[
        {
            "category":"Government",
            "subcategory":"Office",
            "type":"Public Place"
        }
    ],
    "sg:phone":"+1 252 338 6258",
    "sg:postcode":"27909",
    "sg:province":"NC",
    "wof:name":"Central State Of The Carolinas",
    "wof:placetype":"venue"
},
  "geometry": {"coordinates":[-76.219956,36.280797],"type":"Point"}
}