{
  "type": "Feature",
  "properties": {
    "iso:country":"US",
    "sg:address":"530 S Evans St",
    "sg:city":"Greenville",
    "sg:classifiers":[
        {
            "category":"Education",
            "subcategory":"Library",
            "type":"Public Place"
        }
    ],
    "sg:phone":"+1   ",
    "sg:postcode":"27858",
    "sg:province":"NC",
    "sg:website":"www.sheppardlibrary.org",
    "wof:name":"Sheppard Memorial Library",
    "wof:placetype":"venue"
},
  "geometry": {"coordinates":[-77.373362,35.610163],"type":"Point"}
}