{
  "type": "Feature",
  "properties": {
    "iso:country":"US",
    "sg:address":"124 Lucy Ln",
    "sg:city":"Statesville",
    "sg:classifiers":[
        {
            "category":"Building & Trades",
            "subcategory":"Plumbing",
            "type":"Services"
        }
    ],
    "sg:phone":"+1 704 876 1777",
    "sg:postcode":"28625",
    "sg:province":"NC",
    "sg:tags":[
        "contractor"
    ],
    "wof:name":"Johnston Heating Services",
    "wof:placetype":"venue"
},
  "geometry": {"coordinates":[-80.95450099999999,35.89247],"type":"Point"}
}