{
  "type": "Feature",
  "properties": {
    "iso:country":"US",
    "sg:address":"2832 Roxboro Rd",
    "sg:city":"Durham",
    "sg:classifiers":[
        {
            "category":"Shopping",
            "subcategory":"Discount & Variety Stores",
            "type":"Retail Goods"
        }
    ],
    "sg:phone":"+1 919 220 2497",
    "sg:postcode":"27704",
    "sg:province":"NC",
    "wof:name":"Mom & Pops Discount Var Str",
    "wof:placetype":"venue"
},
  "geometry": {"coordinates":[-78.889861,36.027606],"type":"Point"}
}