{
  "type": "Feature",
  "properties": {
    "addr:full":"404 W Ballentine St Holly Springs NC 27540",
    "addr:housenumber":"404",
    "addr:postcode":"27540",
    "addr:street":"W Ballentine St",
    "iso:country":"US",
    "sg:address":"404 W Ballentine St",
    "sg:city":"Holly Springs",
    "sg:classifiers":[
        {
            "category":"Professional",
            "subcategory":"Advertising",
            "type":"Services"
        }
    ],
    "sg:phone":"+1 919 567 3069",
    "sg:postcode":"27540",
    "sg:province":"NC",
    "sg:tags":[
        "picture"
    ],
    "wof:name":"National Cine Media",
    "wof:placetype":"venue"
},
  "geometry": {"coordinates":[-78.83473600000001,35.649962],"type":"Point"}
}