{
  "type": "Feature",
  "properties": {
    "iso:country":"US",
    "sg:address":"4401 Glenwood Ave",
    "sg:city":"Raleigh",
    "sg:classifiers":[
        {
            "category":"Banks & Credit Unions",
            "subcategory":"Bank",
            "type":"Services"
        }
    ],
    "sg:phone":"+1 919 274 3817",
    "sg:postcode":"27612",
    "sg:province":"NC",
    "sg:tags":[
        "loan",
        "real estate"
    ],
    "wof:name":"Wachovia Mortgage Corp",
    "wof:placetype":"venue"
},
  "geometry": {"coordinates":[-78.67613,35.83947],"type":"Point"}
}