{
  "type": "Feature",
  "properties": {
    "iso:country":"US",
    "sg:address":"1635 E Sugar Creek Rd",
    "sg:city":"Charlotte",
    "sg:classifiers":[
        {
            "category":"Retail",
            "subcategory":"Car Wash",
            "type":"Services"
        }
    ],
    "sg:phone":"+1 704 377 1942",
    "sg:postcode":"28205",
    "sg:province":"NC",
    "sg:tags":[
        "polishing",
        "washing"
    ],
    "sg:website":"www.autobell.com",
    "wof:name":"Autobell Car Wash Inc",
    "wof:placetype":"venue"
},
  "geometry": {"coordinates":[-80.78260299999999,35.243646],"type":"Point"}
}