{
  "type": "Feature",
  "properties": {
    "iso:country":"US",
    "sg:address":"288 Union Grove Rd",
    "sg:city":"Union Grove",
    "sg:classifiers":[
        {
            "category":"Farming",
            "subcategory":"Poultry Farm",
            "type":"Manufacturing & Wholesale Goods"
        }
    ],
    "sg:phone":"+1 704 539 4019",
    "sg:postcode":"28689",
    "sg:province":"NC",
    "wof:name":"Lakeside Poultry Farm",
    "wof:placetype":"venue"
},
  "geometry": {"coordinates":[-80.806106,36.041955],"type":"Point"}
}