{
  "type": "Feature",
  "properties": {
    "addr:full":"2009 Union Rd Gastonia NC 28054",
    "addr:housenumber":"2009",
    "addr:postcode":"28054",
    "addr:street":"Union Rd",
    "iso:country":"US",
    "sg:address":"2009 Union Rd",
    "sg:city":"Gastonia",
    "sg:classifiers":[
        {
            "category":"Organizations",
            "subcategory":"Community Association",
            "type":"Services"
        }
    ],
    "sg:phone":"+1   ",
    "sg:postcode":"28054",
    "sg:province":"NC",
    "wof:name":"Whitener Place",
    "wof:placetype":"venue"
},
  "geometry": {"coordinates":[-81.170361,35.238675],"type":"Point"}
}