{
  "type": "Feature",
  "properties": {
    "iso:country":"US",
    "sg:address":"1330 Breedlove Rd",
    "sg:city":"Louisburg",
    "sg:classifiers":[
        {
            "category":"Professional",
            "subcategory":"Business Services",
            "type":"Services"
        }
    ],
    "sg:phone":"+1 919 496 2626",
    "sg:postcode":"27549",
    "sg:province":"NC",
    "sg:tags":[
        "appraiser"
    ],
    "wof:name":"Franklin Appraisal Svc",
    "wof:placetype":"venue"
},
  "geometry": {"coordinates":[-78.32332599999999,36.164992],"type":"Point"}
}