{
  "type": "Feature",
  "properties": {
    "addr:full":"3751 Gray Rd Chocowinity NC 27817",
    "addr:housenumber":"3751",
    "addr:postcode":"27817",
    "addr:street":"Gray Rd",
    "iso:country":"US",
    "sg:address":"3751 Gray Rd",
    "sg:city":"Chocowinity",
    "sg:classifiers":[
        {
            "category":"Building & Trades",
            "subcategory":"Landscaping Services",
            "type":"Services"
        }
    ],
    "sg:phone":"+1 252 946 7018",
    "sg:postcode":"27817",
    "sg:province":"NC",
    "wof:name":"David R Silverthorn",
    "wof:placetype":"venue"
},
  "geometry": {"coordinates":[-77.090931,35.445495],"type":"Point"}
}