{
  "type": "Feature",
  "properties": {
    "addr:full":"109 E Arlington Blvd Greenville NC 27858",
    "addr:housenumber":"109",
    "addr:postcode":"27858",
    "addr:street":"E Arlington Blvd",
    "iso:country":"US",
    "sg:address":"109 E Arlington Blvd",
    "sg:city":"Greenville",
    "sg:classifiers":[
        {
            "category":"Shopping",
            "subcategory":"Used Merchandise",
            "type":"Retail Goods"
        }
    ],
    "sg:phone":"+1 252 321 6016",
    "sg:postcode":"27858",
    "sg:province":"NC",
    "wof:name":"Book Worm of Greenville",
    "wof:placetype":"venue"
},
  "geometry": {"coordinates":[-77.37804199999999,35.590974],"type":"Point"}
}