{
  "type": "Feature",
  "properties": {
    "addr:full":"835 Sedge Garden Rd Kernersville NC 27284",
    "addr:housenumber":"835",
    "addr:postcode":"27284",
    "addr:street":"Sedge Garden Rd",
    "iso:country":"US",
    "sg:address":"835 Sedge Garden Rd",
    "sg:city":"Kernersville",
    "sg:classifiers":[
        {
            "category":"Building & Trades",
            "subcategory":"Construction",
            "type":"Services"
        }
    ],
    "sg:phone":"+1 336 996 6426",
    "sg:postcode":"27284",
    "sg:province":"NC",
    "sg:tags":[
        "home",
        "improvement"
    ],
    "wof:name":"Larrimore's Home Improvement",
    "wof:placetype":"venue"
},
  "geometry": {"coordinates":[-80.115568,36.088964],"type":"Point"}
}