{
  "type": "Feature",
  "properties": {
    "iso:country":"US",
    "sg:address":"657 N Main St",
    "sg:city":"Troutman",
    "sg:classifiers":[
        {
            "category":"Shopping",
            "subcategory":"Computers & Home Electronics",
            "type":"Retail Goods"
        }
    ],
    "sg:phone":"+1 704 528 0707",
    "sg:postcode":"28010",
    "sg:province":"NC",
    "sg:tags":[
        "equipment",
        "electronic",
        "supply"
    ],
    "wof:name":"Piedmont Electronics Sales",
    "wof:placetype":"venue"
},
  "geometry": {"coordinates":[-80.897795,35.719288],"type":"Point"}
}