{
  "type": "Feature",
  "properties": {
    "addr:full":"182 Rosemont Rd Salisbury NC 28146",
    "addr:housenumber":"182",
    "addr:postcode":"28146",
    "addr:street":"Rosemont Rd",
    "iso:country":"US",
    "sg:address":"182 Rosemont Rd",
    "sg:city":"Salisbury",
    "sg:classifiers":[
        {
            "category":"Building & Trades",
            "subcategory":"Construction",
            "type":"Services"
        }
    ],
    "sg:phone":"+1 704 857 1460",
    "sg:postcode":"28146",
    "sg:province":"NC",
    "sg:tags":[
        "hanging",
        "painter",
        "contractor"
    ],
    "wof:name":"Terry's Paint & Wallpapering",
    "wof:placetype":"venue"
},
  "geometry": {"coordinates":[-80.525581,35.575496],"type":"Point"}
}