{
  "type": "Feature",
  "properties": {
    "addr:full":"14523 Carowinds Blvd Charlotte NC 28273",
    "addr:housenumber":"14523",
    "addr:postcode":"28273",
    "addr:street":"Carowinds Blvd",
    "iso:country":"US",
    "sg:address":"14523 Carowinds Blvd",
    "sg:city":"Charlotte",
    "sg:classifiers":[
        {
            "category":"Recreation",
            "subcategory":"Amusement Park",
            "type":"Entertainment"
        },
        {
            "category":"Park",
            "subcategory":"Town Common",
            "type":"Public Place"
        },
        {
            "category":"Recreation",
            "subcategory":"Picnic Area",
            "type":"Entertainment"
        },
        {
            "category":"Landmark",
            "subcategory":"Tourist Information",
            "type":"Public Place"
        }
    ],
    "sg:phone":"+1 704 588 2600",
    "sg:postcode":"28273",
    "sg:province":"NC",
    "sg:tags":[
        "arcade",
        "attraction",
        "ride",
        "water",
        "equipment",
        "slide"
    ],
    "sg:website":"http://www.carowinds.com/",
    "wof:name":"Carowinds",
    "wof:placetype":"venue"
},
  "geometry": {"coordinates":[-80.950053,35.100946],"type":"Point"}
}