{
  "type": "Feature",
  "properties": {
    "addr:full":"1346 Ramseur Rd Bessemer City NC 28016",
    "addr:housenumber":"1346",
    "addr:postcode":"28016",
    "addr:street":"Ramseur Rd",
    "iso:country":"US",
    "sg:address":"1346 Ramseur Rd",
    "sg:city":"Bessemer City",
    "sg:classifiers":[
        {
            "category":"Manufacturing",
            "subcategory":"Tools & Machinery",
            "type":"Manufacturing & Wholesale Goods"
        }
    ],
    "sg:phone":"+1 704 629 5591",
    "sg:postcode":"28016",
    "sg:province":"NC",
    "sg:tags":[
        "machine",
        "shop"
    ],
    "wof:name":"Robinson Machine & Cutter",
    "wof:placetype":"venue"
},
  "geometry": {"coordinates":[-81.307742,35.307828],"type":"Point"}
}