{
  "type": "Feature",
  "properties": {
    "addr:full":"1521 Benvenue Rd Rocky Mount NC 27804",
    "addr:housenumber":"1521",
    "addr:postcode":"27804",
    "addr:street":"Benvenue Rd",
    "iso:country":"US",
    "sg:address":"1521 Benvenue Rd",
    "sg:city":"Rocky Mount",
    "sg:classifiers":[
        {
            "category":"Shopping",
            "subcategory":"Clothing, Apparel, & Fashions",
            "type":"Retail Goods"
        }
    ],
    "sg:phone":"+1 252 212 1706",
    "sg:postcode":"27804",
    "sg:province":"NC",
    "sg:website":"www.catofashions.com",
    "wof:name":"Cato",
    "wof:placetype":"venue"
},
  "geometry": {"coordinates":[-77.808346,35.979954],"type":"Point"}
}