{
  "type": "Feature",
  "properties": {
    "iso:country":"US",
    "sg:address":"106 Ashwyn Ct",
    "sg:city":"Cary",
    "sg:classifiers":[
        {
            "category":"Manufacturing",
            "subcategory":"Printing",
            "type":"Manufacturing & Wholesale Goods"
        }
    ],
    "sg:phone":"+1 919 858 1002",
    "sg:postcode":"27518",
    "sg:province":"NC",
    "sg:tags":[
        "publisher"
    ],
    "wof:name":"BYG Publishing Inc",
    "wof:placetype":"venue"
},
  "geometry": {"coordinates":[-78.75885700000001,35.741036],"type":"Point"}
}