{
  "type": "Feature",
  "properties": {
    "addr:full":"1890 Woodleaf Barber Rd Cleveland NC 27013",
    "addr:postcode":"1890;27013",
    "addr:street":"Barber Rd",
    "iso:country":"US",
    "sg:address":"1890 Woodleaf Barber Rd",
    "sg:city":"Cleveland",
    "sg:classifiers":[
        {
            "category":"Manufacturing",
            "subcategory":"Metals",
            "type":"Manufacturing & Wholesale Goods"
        }
    ],
    "sg:phone":"+1 704 278 2357",
    "sg:postcode":"27013",
    "sg:province":"NC",
    "sg:tags":[
        "fabrication"
    ],
    "wof:name":"Robert Williams",
    "wof:placetype":"venue"
},
  "geometry": {"coordinates":[-80.616693,35.757688],"type":"Point"}
}