{
  "type": "Feature",
  "properties": {
    "addr:full":"704 Pembroke Rd Greensboro NC 27408",
    "addr:housenumber":"704",
    "addr:postcode":"27408",
    "addr:street":"Pembroke Rd",
    "iso:country":"US",
    "sg:address":"704 Pembroke Rd",
    "sg:city":"Greensboro",
    "sg:classifiers":[
        {
            "category":"Utilities",
            "subcategory":"Mobile Phone",
            "type":"Services"
        },
        {
            "category":"Shopping",
            "subcategory":"Computers & Home Electronics",
            "type":"Retail Goods"
        }
    ],
    "sg:phone":"+1 336 852 5472",
    "sg:postcode":"27408",
    "sg:province":"NC",
    "sg:tags":[
        "telephone",
        "cellular"
    ],
    "wof:name":"Radio Shack",
    "wof:placetype":"venue"
},
  "geometry": {"coordinates":[-79.83284999999999,36.087211],"type":"Point"}
}