{
  "type": "Feature",
  "properties": {
    "iso:country":"US",
    "sg:address":"339 S Wilmington St",
    "sg:city":"Raleigh",
    "sg:classifiers":[
        {
            "category":"Shopping",
            "subcategory":"Discount & Variety Stores",
            "type":"Retail Goods"
        }
    ],
    "sg:phone":"+1 919 821 7115",
    "sg:postcode":"27601",
    "sg:province":"NC",
    "sg:tags":[
        "merchandise",
        "general"
    ],
    "wof:name":"Mr Freeze Records Store No 1",
    "wof:placetype":"venue"
},
  "geometry": {"coordinates":[-78.638257,35.776074],"type":"Point"}
}