{
  "type": "Feature",
  "properties": {
    "addr:full":"13700 Imperial Oak Ln Charlotte NC 28273",
    "addr:housenumber":"13700",
    "addr:postcode":"28273",
    "addr:street":"Imperial Oak Ln",
    "iso:country":"US",
    "sg:address":"13700 Imperial Oak Ln",
    "sg:city":"Charlotte",
    "sg:classifiers":[
        {
            "category":"Professional",
            "subcategory":"Business Services",
            "type":"Services"
        }
    ],
    "sg:phone":"+1   ",
    "sg:postcode":"28273",
    "sg:province":"NC",
    "wof:name":"Q Davis Enterprises Inc",
    "wof:placetype":"venue"
},
  "geometry": {"coordinates":[-80.97221999999999,35.120957],"type":"Point"}
}