{
  "type": "Feature",
  "properties": {
    "iso:country":"US",
    "sg:address":"9868 US Hwy 311",
    "sg:city":"Archdale",
    "sg:classifiers":[
        {
            "category":"Retail",
            "subcategory":"Repair Shop",
            "type":"Services"
        }
    ],
    "sg:phone":"+1 336 431 3755",
    "sg:postcode":"27263",
    "sg:province":"NC",
    "sg:tags":[
        "upholsterer"
    ],
    "wof:name":"Krieger Manufacturing Inc",
    "wof:placetype":"venue"
},
  "geometry": {"coordinates":[-79.934291,35.889801],"type":"Point"}
}