{
  "type": "Feature",
  "properties": {
    "iso:country":"US",
    "sg:address":"4155 Friendship Ledford Rd",
    "sg:city":"Winston Salem",
    "sg:classifiers":[
        {
            "category":"Manufacturing",
            "subcategory":"Metals",
            "type":"Manufacturing & Wholesale Goods"
        },
        {
            "category":"Manufacturing",
            "subcategory":"Retail Goods",
            "type":"Manufacturing & Wholesale Goods"
        }
    ],
    "sg:phone":"+1 336 769 2427",
    "sg:postcode":"27107",
    "sg:province":"NC",
    "sg:tags":[
        "manufacturer",
        "mfg"
    ],
    "wof:name":"Triad Magnetic Van Screens Inc",
    "wof:placetype":"venue"
},
  "geometry": {"coordinates":[-80.166189,35.99102],"type":"Point"}
}