{
  "type": "Feature",
  "properties": {
    "iso:country":"US",
    "sg:address":"240 Magnolia Dr",
    "sg:city":"Calabash",
    "sg:classifiers":[
        {
            "category":"Building & Trades",
            "subcategory":"Construction",
            "type":"Services"
        }
    ],
    "sg:phone":"+1 910 579 8282",
    "sg:postcode":"28468",
    "sg:province":"NC",
    "sg:tags":[
        "painter"
    ],
    "wof:name":"Canady's Painting",
    "wof:placetype":"venue"
},
  "geometry": {"coordinates":[-78.50871100000001,33.887517],"type":"Point"}
}