{
  "type": "Feature",
  "properties": {
    "addr:full":"209 Commerce St Greenville NC 27858",
    "addr:housenumber":"209",
    "addr:postcode":"27858",
    "addr:street":"Commerce St",
    "iso:country":"US",
    "sg:address":"209 Commerce St",
    "sg:city":"Greenville",
    "sg:classifiers":[
        {
            "category":"Professional",
            "subcategory":"Lawyer & Legal Services",
            "type":"Services"
        }
    ],
    "sg:phone":"+1 252 353 7300",
    "sg:postcode":"27858",
    "sg:province":"NC",
    "sg:tags":[
        "attorney"
    ],
    "wof:name":"Harris Shields Creech & Ward",
    "wof:placetype":"venue"
},
  "geometry": {"coordinates":[-77.37356800000001,35.587398],"type":"Point"}
}