{
  "type": "Feature",
  "properties": {
    "addr:full":"770 NW Broad St Southern Pines NC 28387",
    "addr:housenumber":"770",
    "addr:postcode":"28387",
    "addr:street":"Nw Broad St",
    "iso:country":"US",
    "sg:address":"770 NW Broad St",
    "sg:city":"Southern Pines",
    "sg:classifiers":[
        {
            "category":"Health Services",
            "subcategory":"Clinic",
            "type":"Services"
        }
    ],
    "sg:phone":"+1   ",
    "sg:postcode":"28387",
    "sg:province":"NC",
    "wof:name":"Recovery Associates",
    "wof:placetype":"venue"
},
  "geometry": {"coordinates":[-79.383358,35.17939],"type":"Point"}
}