{
  "type": "Feature",
  "properties": {
    "iso:country":"US",
    "sg:address":"3229 US Hwy 15/501",
    "sg:city":"Carthage",
    "sg:classifiers":[
        {
            "category":"Retail",
            "subcategory":"Repair Shop",
            "type":"Services"
        }
    ],
    "sg:phone":"+1   ",
    "sg:postcode":"28327",
    "sg:province":"NC",
    "wof:name":"Dutton Small Engine Repair",
    "wof:placetype":"venue"
},
  "geometry": {"coordinates":[-79.374959,35.347871],"type":"Point"}
}