{
  "type": "Feature",
  "properties": {
    "iso:country":"US",
    "sg:address":"709 State Hwy 55",
    "sg:city":"Bayboro",
    "sg:classifiers":[
        {
            "category":"Autos & Motor Vehicles",
            "subcategory":"Automobile Sales",
            "type":"Retail Goods"
        }
    ],
    "sg:phone":"+1 252 745 4011",
    "sg:postcode":"28515",
    "sg:province":"NC",
    "sg:tags":[
        "car",
        "dealer"
    ],
    "wof:name":"Bayboro Chevrolet Inc",
    "wof:placetype":"venue"
},
  "geometry": {"coordinates":[-76.78102800000001,35.143483],"type":"Point"}
}