{
  "type": "Feature",
  "properties": {
    "addr:full":"1213 Culbreth Dr Wilmington NC 28405",
    "addr:housenumber":"1213",
    "addr:postcode":"28405",
    "addr:street":"Culbreth Dr",
    "iso:country":"US",
    "sg:address":"1213 Culbreth Dr",
    "sg:city":"Wilmington",
    "sg:classifiers":[
        {
            "category":"Professional",
            "subcategory":"Management & Consulting",
            "type":"Services"
        }
    ],
    "sg:phone":"+1 910 509 7220",
    "sg:postcode":"28405",
    "sg:province":"NC",
    "sg:tags":[
        "fuel"
    ],
    "wof:name":"Milestone Wealth Mgmt LLC",
    "wof:placetype":"venue"
},
  "geometry": {"coordinates":[-77.828307,34.234097],"type":"Point"}
}