{
  "type": "Feature",
  "properties": {
    "iso:country":"US",
    "sg:address":"6230 Albemarle Rd",
    "sg:city":"Charlotte",
    "sg:classifiers":[
        {
            "category":"Retail",
            "subcategory":"Auto Repair",
            "type":"Services"
        }
    ],
    "sg:phone":"+1   ",
    "sg:postcode":"28212",
    "sg:province":"NC",
    "sg:tags":[
        "automotive"
    ],
    "wof:name":"Express Lube",
    "wof:placetype":"venue"
},
  "geometry": {"coordinates":[-80.739617,35.202968],"type":"Point"}
}