{
  "type": "Feature",
  "properties": {
    "addr:full":"6813 Justice Dr Raleigh NC 27615",
    "addr:housenumber":"6813",
    "addr:postcode":"27615",
    "addr:street":"Justice Dr",
    "iso:country":"US",
    "sg:address":"6813 Justice Dr",
    "sg:city":"Raleigh",
    "sg:classifiers":[
        {
            "category":"Communications",
            "subcategory":"Film & Video Production",
            "type":"Services"
        }
    ],
    "sg:phone":"+1 919 847 7511",
    "sg:postcode":"27615",
    "sg:province":"NC",
    "sg:tags":[
        "motion",
        "taping"
    ],
    "wof:name":"Multi Vision Productions",
    "wof:placetype":"venue"
},
  "geometry": {"coordinates":[-78.62863400000001,35.878188],"type":"Point"}
}