{
  "type": "Feature",
  "properties": {
    "addr:full":"130 Wintergreen Rd Winston Salem NC 27107",
    "addr:housenumber":"130",
    "addr:postcode":"27107",
    "addr:street":"Wintergreen Rd",
    "iso:country":"US",
    "sg:address":"130 Wintergreen Rd",
    "sg:city":"Winston Salem",
    "sg:classifiers":[
        {
            "category":"Professional",
            "subcategory":"Art Services",
            "type":"Services"
        }
    ],
    "sg:phone":"+1 336 575 7500",
    "sg:postcode":"27107",
    "sg:province":"NC",
    "sg:tags":[
        "artist"
    ],
    "wof:name":"Eddie G Rosdhal Studios",
    "wof:placetype":"venue"
},
  "geometry": {"coordinates":[-80.174052,36.077322],"type":"Point"}
}