{
  "type": "Feature",
  "properties": {
    "iso:country":"US",
    "sg:address":"363 Vinson Rd",
    "sg:city":"Goldsboro",
    "sg:classifiers":[
        {
            "category":"Retail",
            "subcategory":"Auto Repair",
            "type":"Services"
        }
    ],
    "sg:phone":"+1 919 778 3267",
    "sg:postcode":"28551",
    "sg:province":"NC",
    "sg:tags":[
        "truck",
        "general"
    ],
    "wof:name":"Carraway's Truck & Equipment",
    "wof:placetype":"venue"
},
  "geometry": {"coordinates":[-77.850464,35.407237],"type":"Point"}
}