{
  "type": "Feature",
  "properties": {
    "iso:country":"US",
    "sg:address":"564 Pinetree Ln",
    "sg:city":"Spring Lake",
    "sg:classifiers":[
        {
            "category":"Retail",
            "subcategory":"Auto Repair",
            "type":"Services"
        }
    ],
    "sg:phone":"+1 910 497 2521",
    "sg:postcode":"28390",
    "sg:province":"NC",
    "sg:tags":[
        "repairing",
        "automobile",
        "automotive"
    ],
    "wof:name":"J & N Enterprises",
    "wof:placetype":"venue"
},
  "geometry": {"coordinates":[-78.96611799999999,35.17756],"type":"Point"}
}