{
  "type": "Feature",
  "properties": {
    "addr:full":"6108 Four Oaks Ct Summerfield NC 27358",
    "addr:housenumber":"6108",
    "addr:postcode":"27358",
    "addr:street":"Four Oaks Ct",
    "iso:country":"US",
    "sg:address":"6108 Four Oaks Ct",
    "sg:city":"Summerfield",
    "sg:classifiers":[
        {
            "category":"Real Estate",
            "subcategory":"Real Estate Agent",
            "type":"Services"
        }
    ],
    "sg:phone":"+1 336 643 5591",
    "sg:postcode":"27358",
    "sg:province":"NC",
    "wof:name":"Spradlin Farm Inc",
    "wof:placetype":"venue"
},
  "geometry": {"coordinates":[-79.893624,36.166471],"type":"Point"}
}