{
  "type": "Feature",
  "properties": {
    "iso:country":"US",
    "sg:address":"117 S Hamilton St",
    "sg:city":"Eden",
    "sg:classifiers":[
        {
            "category":"Retail",
            "subcategory":"Auto Repair",
            "type":"Services"
        }
    ],
    "sg:phone":"+1 336 623 3834",
    "sg:postcode":"27288",
    "sg:province":"NC",
    "sg:tags":[
        "repairing",
        "automotive",
        "radiator",
        "automobile"
    ],
    "wof:name":"Eden Radiator Repair",
    "wof:placetype":"venue"
},
  "geometry": {"coordinates":[-79.772797,36.503113],"type":"Point"}
}