{
  "type": "Feature",
  "properties": {
    "iso:country":"US",
    "sg:address":"2672 James B White Hwy N",
    "sg:city":"Whiteville",
    "sg:classifiers":[
        {
            "category":"Organizations",
            "subcategory":"Religious Organization",
            "type":"Services"
        }
    ],
    "sg:phone":"+1 910 642 7654",
    "sg:postcode":"28472",
    "sg:province":"NC",
    "sg:tags":[
        "church"
    ],
    "wof:name":"Northwood Assembly Of God",
    "wof:placetype":"venue"
},
  "geometry": {"coordinates":[-78.721906,34.376821],"type":"Point"}
}