{
  "type": "Feature",
  "properties": {
    "iso:country":"US",
    "sg:address":"110 University Heights Rd",
    "sg:city":"Cullowhee",
    "sg:classifiers":[
        {
            "category":"Professional",
            "subcategory":"Management & Consulting",
            "type":"Services"
        }
    ],
    "sg:phone":"+1 828 227 7492",
    "sg:postcode":"28723",
    "sg:province":"NC",
    "wof:name":"Center For Imprving Mtn Living",
    "wof:placetype":"venue"
},
  "geometry": {"coordinates":[-83.179053,35.32827],"type":"Point"}
}