{
  "type": "Feature",
  "properties": {
    "iso:country":"US",
    "sg:address":"101 E Garner Rd",
    "sg:city":"Garner",
    "sg:classifiers":[
        {
            "category":"Real Estate",
            "subcategory":"Architect",
            "type":"Services"
        }
    ],
    "sg:phone":"+1 919 772 4064",
    "sg:postcode":"27529",
    "sg:province":"NC",
    "wof:name":"James G Grady",
    "wof:placetype":"venue"
},
  "geometry": {"coordinates":[-78.605301,35.707278],"type":"Point"}
}