{
  "type": "Feature",
  "properties": {
    "addr:full":"5236 Murchison Rd Fayetteville NC 28311",
    "addr:postcode":"5236;28311",
    "addr:street":"Murchison Rd",
    "iso:country":"US",
    "sg:address":"5236 Murchison Rd",
    "sg:city":"Fayetteville",
    "sg:classifiers":[
        {
            "category":"Food & Beverages",
            "subcategory":"Groceries & Convenience Stores",
            "type":"Retail Goods"
        }
    ],
    "sg:phone":"+1 910 321 9425",
    "sg:postcode":"28311",
    "sg:province":"NC",
    "sg:tags":[
        "grocer"
    ],
    "wof:name":"Rita's Market & Things",
    "wof:placetype":"venue"
},
  "geometry": {"coordinates":[-78.92478699999999,35.107968],"type":"Point"}
}