{
  "type": "Feature",
  "properties": {
    "addr:full":"18 Haywood St Asheville NC 28801",
    "addr:housenumber":"18",
    "addr:postcode":"28801",
    "addr:street":"Haywood St",
    "iso:country":"US",
    "sg:address":"18 Haywood St",
    "sg:city":"Asheville",
    "sg:classifiers":[
        {
            "category":"Shopping",
            "subcategory":"Hobbies, Toys, & Games",
            "type":"Retail Goods"
        }
    ],
    "sg:phone":"+1 828 252 9007",
    "sg:postcode":"28801",
    "sg:province":"NC",
    "wof:name":"Enviro Depot Inc",
    "wof:placetype":"venue"
},
  "geometry": {"coordinates":[-82.55446000000001,35.595175],"type":"Point"}
}