{
  "type": "Feature",
  "properties": {
    "addr:full":"238 Mohawk Trl Wilmington NC 28409",
    "addr:housenumber":"238",
    "addr:postcode":"28409",
    "addr:street":"Mohawk Trl",
    "iso:country":"US",
    "sg:address":"238 Mohawk Trl",
    "sg:city":"Wilmington",
    "sg:classifiers":[
        {
            "category":"Building & Trades",
            "subcategory":"Construction",
            "type":"Services"
        }
    ],
    "sg:phone":"+1 910 470 3466",
    "sg:postcode":"28409",
    "sg:province":"NC",
    "sg:tags":[
        "contractor"
    ],
    "wof:name":"ACS",
    "wof:placetype":"venue"
},
  "geometry": {"coordinates":[-77.875984,34.155491],"type":"Point"}
}