{
  "type": "Feature",
  "properties": {
    "iso:country":"US",
    "sg:address":"114 S Pine St",
    "sg:city":"Princeton",
    "sg:classifiers":[
        {
            "category":"Government",
            "subcategory":"Police Station",
            "type":"Public Place"
        }
    ],
    "sg:phone":"+1 919 936 5131",
    "sg:postcode":"27569",
    "sg:province":"NC",
    "sg:tags":[
        "department"
    ],
    "wof:name":"Princeton Police Dept",
    "wof:placetype":"venue"
},
  "geometry": {"coordinates":[-78.16059799999999,35.465946],"type":"Point"}
}