{
  "type": "Feature",
  "properties": {
    "addr:full":"9900 S Tryon St Charlotte NC 28273",
    "addr:housenumber":"9900",
    "addr:postcode":"28273",
    "addr:street":"S Tryon St",
    "iso:country":"US",
    "sg:address":"9900 S Tryon St",
    "sg:city":"Charlotte",
    "sg:classifiers":[
        {
            "category":"Travel",
            "subcategory":"Hotels & Motels",
            "type":"Entertainment"
        }
    ],
    "sg:phone":"+1   ",
    "sg:postcode":"28273",
    "sg:province":"NC",
    "sg:tags":[
        "operation"
    ],
    "wof:name":"Yorkshire Inn",
    "wof:placetype":"venue"
},
  "geometry": {"coordinates":[-80.94867000000001,35.121679],"type":"Point"}
}