{
  "type": "Feature",
  "properties": {
    "addr:full":"631 Brawley School Rd Mooresville NC 28117",
    "addr:housenumber":"631",
    "addr:postcode":"28117",
    "addr:street":"Brawley School Rd",
    "iso:country":"US",
    "sg:address":"631 Brawley School Rd",
    "sg:city":"Mooresville",
    "sg:classifiers":[
        {
            "category":"Personal",
            "subcategory":"Beauty Salon",
            "type":"Services"
        }
    ],
    "sg:phone":"+1 704 660 6729",
    "sg:postcode":"28117",
    "sg:province":"NC",
    "wof:name":"Hair Cuttery",
    "wof:placetype":"venue"
},
  "geometry": {"coordinates":[-80.87444600000001,35.583537],"type":"Point"}
}