{
  "type": "Feature",
  "properties": {
    "iso:country":"US",
    "sg:address":"221 Colony Acres Dr",
    "sg:city":"Charlotte",
    "sg:classifiers":[
        {
            "category":"Professional",
            "type":"Services"
        }
    ],
    "sg:phone":"+1 704 522 8335",
    "sg:postcode":"28217",
    "sg:province":"NC",
    "wof:name":"Joann Pinkney Customize V",
    "wof:placetype":"venue"
},
  "geometry": {"coordinates":[-80.89659399999999,35.138631],"type":"Point"}
}