{
  "type": "Feature",
  "properties": {
    "addr:full":"218 E Blackwell Dr Hendersonville NC 28792",
    "addr:housenumber":"218",
    "addr:postcode":"28792",
    "addr:street":"E Blackwell Dr",
    "iso:country":"US",
    "sg:address":"218 E Blackwell Dr",
    "sg:city":"Hendersonville",
    "sg:classifiers":[
        {
            "category":"Building & Trades",
            "subcategory":"Electrical",
            "type":"Services"
        }
    ],
    "sg:phone":"+1 828 685 3637",
    "sg:postcode":"28792",
    "sg:province":"NC",
    "sg:tags":[
        "electric",
        "contractor"
    ],
    "wof:name":"Case Electric Co",
    "wof:placetype":"venue"
},
  "geometry": {"coordinates":[-82.365206,35.357385],"type":"Point"}
}