{
  "type": "Feature",
  "properties": {
    "iso:country":"US",
    "sg:address":"5409 Creft Cir",
    "sg:city":"Indian Trail",
    "sg:classifiers":[
        {
            "category":"Professional",
            "subcategory":"Art Services",
            "type":"Services"
        }
    ],
    "sg:phone":"+1   ",
    "sg:postcode":"28079",
    "sg:province":"NC",
    "sg:tags":[
        "commercial",
        "design"
    ],
    "wof:name":"Affirmations By Bill Kamm",
    "wof:placetype":"venue"
},
  "geometry": {"coordinates":[-80.62849900000001,35.082912],"type":"Point"}
}