{
  "type": "Feature",
  "properties": {
    "iso:country":"US",
    "sg:address":"138 Coley Rd",
    "sg:city":"Elizabethtown",
    "sg:classifiers":[
        {
            "category":"Real Estate",
            "subcategory":"Real Estate Operator",
            "type":"Services"
        }
    ],
    "sg:phone":"+1 910 645 4424",
    "sg:postcode":"28337",
    "sg:province":"NC",
    "sg:tags":[
        "property",
        "lessor"
    ],
    "wof:name":"W J Hair",
    "wof:placetype":"venue"
},
  "geometry": {"coordinates":[-78.539057,34.58338],"type":"Point"}
}