{
  "type": "Feature",
  "properties": {
    "addr:full":"46 Shoreline Dr New Bern NC 28562",
    "addr:housenumber":"46",
    "addr:postcode":"28562",
    "addr:street":"Shoreline Dr",
    "iso:country":"US",
    "sg:address":"46 Shoreline Dr",
    "sg:city":"New Bern",
    "sg:classifiers":[
        {
            "category":"Food & Beverages",
            "subcategory":"Groceries & Convenience Stores",
            "type":"Retail Goods"
        }
    ],
    "sg:phone":"+1 252 634 9206",
    "sg:postcode":"28562",
    "sg:province":"NC",
    "wof:name":"Riverbend Market",
    "wof:placetype":"venue"
},
  "geometry": {"coordinates":[-77.14794000000001,35.073182],"type":"Point"}
}