{
  "type": "Feature",
  "properties": {
    "addr:full":"2399 Corporation Pkwy Burlington NC 27215",
    "addr:housenumber":"2399",
    "addr:postcode":"27215",
    "addr:street":"Corporation Pkwy",
    "iso:country":"US",
    "sg:address":"2399 Corporation Pkwy",
    "sg:city":"Burlington",
    "sg:classifiers":[
        {
            "category":"Professional",
            "type":"Services"
        }
    ],
    "sg:phone":"+1 336 226 7919",
    "sg:postcode":"27215",
    "sg:province":"NC",
    "sg:tags":[
        "establishment"
    ],
    "wof:name":"Burlington Artists League Glry",
    "wof:placetype":"venue"
},
  "geometry": {"coordinates":[-79.43571900000001,36.066683],"type":"Point"}
}