{
  "type": "Feature",
  "properties": {
    "iso:country":"US",
    "sg:address":"1922 Peale Ter",
    "sg:city":"Greensboro",
    "sg:classifiers":[
        {
            "category":"Professional",
            "type":"Services"
        }
    ],
    "sg:phone":"+1 336 965 4898",
    "sg:postcode":"27407",
    "sg:province":"NC",
    "wof:name":"Experience Greensboro",
    "wof:placetype":"venue"
},
  "geometry": {"coordinates":[-79.85342799999999,36.041964],"type":"Point"}
}