{
  "type": "Feature",
  "properties": {
    "iso:country":"US",
    "sg:address":"104 Jeran Ln",
    "sg:city":"Gastonia",
    "sg:classifiers":[
        {
            "category":"Real Estate",
            "subcategory":"Real Estate Operator",
            "type":"Services"
        }
    ],
    "sg:phone":"+1 704 866 0165",
    "sg:postcode":"28052",
    "sg:province":"NC",
    "sg:tags":[
        "mobile",
        "home",
        "community"
    ],
    "wof:name":"Berkley Oaks",
    "wof:placetype":"venue"
},
  "geometry": {"coordinates":[-81.244108,35.188482],"type":"Point"}
}