{
  "type": "Feature",
  "properties": {
    "iso:country":"US",
    "sg:address":"182 Richland St",
    "sg:city":"Waynesville",
    "sg:classifiers":[
        {
            "category":"Home & Garden",
            "subcategory":"Furniture",
            "type":"Retail Goods"
        }
    ],
    "sg:phone":"+1 828 452 3828",
    "sg:postcode":"28786",
    "sg:province":"NC",
    "sg:tags":[
        "top",
        "counter"
    ],
    "wof:name":"Smokey Mountain Custom Kitchen",
    "wof:placetype":"venue"
},
  "geometry": {"coordinates":[-82.99466700000001,35.490298],"type":"Point"}
}