{
  "type": "Feature",
  "properties": {
    "iso:country":"US",
    "sg:address":"2315 E Main St",
    "sg:city":"Albemarle",
    "sg:classifiers":[
        {
            "category":"Home & Garden",
            "subcategory":"Mobile Homes",
            "type":"Retail Goods"
        }
    ],
    "sg:phone":"+1 704 982 5841",
    "sg:postcode":"28001",
    "sg:province":"NC",
    "wof:name":"Tillery Housing Center Inc",
    "wof:placetype":"venue"
},
  "geometry": {"coordinates":[-80.14977399999999,35.344911],"type":"Point"}
}