{
  "type": "Feature",
  "properties": {
    "iso:country":"US",
    "sg:address":"953 Wendover Heights Dr",
    "sg:city":"Shelby",
    "sg:classifiers":[
        {
            "category":"Health Services",
            "subcategory":"Nursing And Care Facility",
            "type":"Services"
        }
    ],
    "sg:phone":"+1 704 487 7018",
    "sg:postcode":"28150",
    "sg:province":"NC",
    "sg:tags":[
        "skilled"
    ],
    "wof:name":"Wendover Hospice Of Cleveland",
    "wof:placetype":"venue"
},
  "geometry": {"coordinates":[-81.519318,35.309078],"type":"Point"}
}