{
  "type": "Feature",
  "properties": {
    "iso:country":"US",
    "sg:address":"736 Dyking Rd",
    "sg:city":"Louisburg",
    "sg:classifiers":[
        {
            "category":"Building & Trades",
            "subcategory":"Construction",
            "type":"Services"
        }
    ],
    "sg:phone":"+1 919 496 3533",
    "sg:postcode":"27549",
    "sg:province":"NC",
    "sg:tags":[
        "heavy"
    ],
    "wof:name":"Stallings Loader & Backhoe",
    "wof:placetype":"venue"
},
  "geometry": {"coordinates":[-78.31023,36.133433],"type":"Point"}
}