{
  "type": "Feature",
  "properties": {
    "addr:full":"2400 Meadow Gate Dr Greensboro NC 27455",
    "addr:housenumber":"2400",
    "addr:postcode":"27455",
    "addr:street":"Meadow Gate Dr",
    "iso:country":"US",
    "sg:address":"2400 Meadow Gate Dr",
    "sg:city":"Greensboro",
    "sg:classifiers":[
        {
            "category":"Professional",
            "subcategory":"Computer Services",
            "type":"Services"
        }
    ],
    "sg:phone":"+1   ",
    "sg:postcode":"27455",
    "sg:province":"NC",
    "sg:tags":[
        "web",
        "design",
        "site"
    ],
    "wof:name":"Hosted Aspnet",
    "wof:placetype":"venue"
},
  "geometry": {"coordinates":[-79.821533,36.140094],"type":"Point"}
}