{
  "type": "Feature",
  "properties": {
    "addr:full":"258 Brushy Fork Rd Creston NC 28615",
    "addr:housenumber":"258",
    "addr:postcode":"28615",
    "addr:street":"Brushy Fork Rd",
    "iso:country":"US",
    "sg:address":"258 Brushy Fork Rd",
    "sg:city":"Creston",
    "sg:classifiers":[
        {
            "category":"Arts & Performance",
            "subcategory":"Theater",
            "type":"Entertainment"
        },
        {
            "category":"Shopping",
            "subcategory":"Gifts & Souvenirs",
            "type":"Retail Goods"
        }
    ],
    "sg:phone":"+1 336 385 6855",
    "sg:postcode":"28615",
    "sg:province":"NC",
    "sg:tags":[
        "magician"
    ],
    "wof:name":"Rash Tommy Magician",
    "wof:placetype":"venue"
},
  "geometry": {"coordinates":[-81.68994499999999,36.410089],"type":"Point"}
}