{
  "type": "Feature",
  "properties": {
    "iso:country":"US",
    "sg:address":"1646 Live Oak St",
    "sg:city":"Beaufort",
    "sg:classifiers":[
        {
            "category":"Food & Beverages",
            "subcategory":"Meat & Fish",
            "type":"Retail Goods"
        }
    ],
    "sg:phone":"+1 252 728 1980",
    "sg:postcode":"28516",
    "sg:province":"NC",
    "sg:tags":[
        "seafood"
    ],
    "wof:name":"Rose's Seafood Market",
    "wof:placetype":"venue"
},
  "geometry": {"coordinates":[-76.641149,34.727943],"type":"Point"}
}