{
  "type": "Feature",
  "properties": {
    "iso:country":"US",
    "sg:address":"2450 Streets Ferry Rd",
    "sg:city":"Vanceboro",
    "sg:classifiers":[
        {
            "category":"Autos & Motor Vehicles",
            "subcategory":"Boat Sales",
            "type":"Retail Goods"
        }
    ],
    "sg:phone":"+1 252 244 1509",
    "sg:postcode":"28586",
    "sg:province":"NC",
    "sg:tags":[
        "top",
        "upholstery",
        "cover"
    ],
    "wof:name":"A & J Canvas",
    "wof:placetype":"venue"
},
  "geometry": {"coordinates":[-77.135401,35.242347],"type":"Point"}
}