{
  "type": "Feature",
  "properties": {
    "iso:country":"US",
    "sg:address":"301 S Elm St",
    "sg:city":"Greensboro",
    "sg:classifiers":[
        {
            "category":"Professional",
            "subcategory":"Computer Services",
            "type":"Services"
        }
    ],
    "sg:phone":"+1 336 370 9119",
    "sg:postcode":"27401",
    "sg:province":"NC",
    "sg:website":"www.day.com",
    "wof:name":"Autopilot Web Management",
    "wof:placetype":"venue"
},
  "geometry": {"coordinates":[-79.790605,36.068419],"type":"Point"}
}