{
  "type": "Feature",
  "properties": {
    "iso:country":"US",
    "sg:address":"144 Morrisville Sq Way",
    "sg:city":"Morrisville",
    "sg:classifiers":[
        {
            "category":"Restaurant",
            "type":"Food & Drink"
        }
    ],
    "sg:phone":"+1 919 465 2326",
    "sg:postcode":"27560",
    "sg:province":"NC",
    "sg:tags":[
        "vegetarian",
        "indian"
    ],
    "sg:website":"www.towernc.com/",
    "wof:name":"Tower Indian Restaurant",
    "wof:placetype":"venue"
},
  "geometry": {"coordinates":[-78.82968,35.820406],"type":"Point"}
}