{
  "type": "Feature",
  "properties": {
    "addr:full":"134 5th Ave New London NC 28127",
    "addr:housenumber":"134",
    "addr:postcode":"28127",
    "addr:street":"5Th Ave",
    "iso:country":"US",
    "sg:address":"134 5th Ave",
    "sg:city":"New London",
    "sg:classifiers":[
        {
            "category":"Building & Trades",
            "subcategory":"Electrical",
            "type":"Services"
        }
    ],
    "sg:phone":"+1 919 649 6034",
    "sg:postcode":"28127",
    "sg:province":"NC",
    "sg:tags":[
        "electric",
        "contractor"
    ],
    "wof:name":"Preston Electric",
    "wof:placetype":"venue"
},
  "geometry": {"coordinates":[-80.111501,35.49804],"type":"Point"}
}