{
  "type": "Feature",
  "properties": {
    "addr:full":"204 Timberbrook Ln Granite Falls NC 28630",
    "addr:housenumber":"204",
    "addr:postcode":"28630",
    "addr:street":"Timberbrook Ln",
    "iso:country":"US",
    "sg:address":"204 Timberbrook Ln",
    "sg:city":"Granite Falls",
    "sg:classifiers":[
        {
            "category":"Organizations",
            "subcategory":"Religious Organization",
            "type":"Services"
        }
    ],
    "sg:phone":"+1 828 313 3326",
    "sg:postcode":"28630",
    "sg:province":"NC",
    "sg:tags":[
        "church"
    ],
    "wof:name":"Latter House Christian Academy",
    "wof:placetype":"venue"
},
  "geometry": {"coordinates":[-81.417633,35.792794],"type":"Point"}
}