{
  "type": "Feature",
  "properties": {
    "addr:full":"1105 Holburn Pl Raleigh NC 27610",
    "addr:housenumber":"1105",
    "addr:postcode":"27610",
    "addr:street":"Holburn Pl",
    "iso:country":"US",
    "sg:address":"1105 Holburn Pl",
    "sg:city":"Raleigh",
    "sg:classifiers":[
        {
            "category":"Professional",
            "type":"Services"
        }
    ],
    "sg:phone":"+1   ",
    "sg:postcode":"27610",
    "sg:province":"NC",
    "wof:name":"Krystal Klean Maid Service",
    "wof:placetype":"venue"
},
  "geometry": {"coordinates":[-78.606808,35.795632],"type":"Point"}
}