{
  "type": "Feature",
  "properties": {
    "addr:full":"4498 Bend of the River Rd Elm City NC 27822",
    "addr:housenumber":"4498",
    "addr:postcode":"27822",
    "addr:street":"Bend Of The River Rd",
    "iso:country":"US",
    "sg:address":"4498 Bend of the River Rd",
    "sg:city":"Elm City",
    "sg:classifiers":[
        {
            "category":"Retail",
            "subcategory":"Auto Repair",
            "type":"Services"
        }
    ],
    "sg:phone":"+1 252 442 7894",
    "sg:postcode":"27822",
    "sg:province":"NC",
    "sg:tags":[
        "wrecker"
    ],
    "wof:name":"Ralph's Wrecker Svc",
    "wof:placetype":"venue"
},
  "geometry": {"coordinates":[-77.932515,35.865494],"type":"Point"}
}