{
  "type": "Feature",
  "properties": {
    "addr:full":"1105 Walnut St Cary NC 27511",
    "addr:housenumber":"1105",
    "addr:postcode":"27511",
    "addr:street":"Walnut St",
    "iso:country":"US",
    "sg:address":"1105 Walnut St",
    "sg:city":"Cary",
    "sg:classifiers":[
        {
            "category":"Shopping",
            "subcategory":"Clothing, Apparel, & Fashions",
            "type":"Retail Goods"
        }
    ],
    "sg:phone":"+1 919 388 9996",
    "sg:postcode":"27511",
    "sg:province":"NC",
    "sg:website":"www.aeropostale.com",
    "wof:name":"Aeropostale",
    "wof:placetype":"venue"
},
  "geometry": {"coordinates":[-78.76321299999999,35.771698],"type":"Point"}
}