{
  "type": "Feature",
  "properties": {
    "addr:full":"1310 N Cannon Blvd Kannapolis NC 28083",
    "addr:housenumber":"1310",
    "addr:postcode":"28083",
    "addr:street":"N Cannon Blvd",
    "iso:country":"US",
    "sg:address":"1310 N Cannon Blvd",
    "sg:city":"Kannapolis",
    "sg:classifiers":[
        {
            "category":"Banks & Credit Unions",
            "subcategory":"Bank",
            "type":"Services"
        }
    ],
    "sg:phone":"+1 704 932 3499",
    "sg:postcode":"28083",
    "sg:province":"NC",
    "sg:tags":[
        "mortgage"
    ],
    "wof:name":"Emoh Mortgage",
    "wof:placetype":"venue"
},
  "geometry": {"coordinates":[-80.608913,35.511418],"type":"Point"}
}