{
  "type": "Feature",
  "properties": {
    "iso:country":"US",
    "sg:address":"2330 Waverly Dr",
    "sg:city":"Wilmington",
    "sg:classifiers":[
        {
            "category":"Professional",
            "subcategory":"Lawyer & Legal Services",
            "type":"Services"
        }
    ],
    "sg:phone":"+1   ",
    "sg:postcode":"28403",
    "sg:province":"NC",
    "wof:name":"Nora Hargrove",
    "wof:placetype":"venue"
},
  "geometry": {"coordinates":[-77.917669,34.199005],"type":"Point"}
}