{
  "type": "Feature",
  "properties": {
    "addr:full":"1695 Lake Tree Dr SW Ocean Isle Beach NC 28469",
    "addr:housenumber":"1695",
    "addr:postcode":"28469",
    "addr:street":"Lake Tree Dr Sw;Isle",
    "iso:country":"US",
    "sg:address":"1695 Lake Tree Dr SW",
    "sg:city":"Ocean Isle Beach",
    "sg:classifiers":[
        {
            "category":"Building & Trades",
            "subcategory":"Construction",
            "type":"Services"
        }
    ],
    "sg:phone":"+1 910 579 5361",
    "sg:postcode":"28469",
    "sg:province":"NC",
    "sg:tags":[
        "painter"
    ],
    "wof:name":"Suggs Painting Svc",
    "wof:placetype":"venue"
},
  "geometry": {"coordinates":[-78.460123,33.897899],"type":"Point"}
}