{
  "type": "Feature",
  "properties": {
    "iso:country":"US",
    "sg:address":"128 Baysden Dr",
    "sg:city":"Jacksonville",
    "sg:classifiers":[
        {
            "category":"Professional",
            "subcategory":"Business Services",
            "type":"Services"
        }
    ],
    "sg:phone":"+1   ",
    "sg:postcode":"28540",
    "sg:province":"NC",
    "wof:name":"D K Solutions",
    "wof:placetype":"venue"
},
  "geometry": {"coordinates":[-77.46627100000001,34.828303],"type":"Point"}
}