{
  "type": "Feature",
  "properties": {
    "addr:full":"1500 Park Dr Raleigh NC 27605",
    "addr:housenumber":"1500",
    "addr:postcode":"27605",
    "addr:street":"Park Dr",
    "iso:country":"US",
    "sg:address":"1500 Park Dr",
    "sg:city":"Raleigh",
    "sg:classifiers":[
        {
            "category":"Professional",
            "subcategory":"Business Services",
            "type":"Services"
        }
    ],
    "sg:phone":"+1   ",
    "sg:postcode":"27605",
    "sg:province":"NC",
    "wof:name":"Joyce Crossno Interiors",
    "wof:placetype":"venue"
},
  "geometry": {"coordinates":[-78.65487899999999,35.787219],"type":"Point"}
}