{
  "type": "Feature",
  "properties": {
    "iso:country":"US",
    "sg:address":"3029 Stoneybrook Dr",
    "sg:city":"Raleigh",
    "sg:classifiers":[
        {
            "category":"Professional",
            "subcategory":"Business Services",
            "type":"Services"
        }
    ],
    "sg:phone":"+1 919 877 0705",
    "sg:postcode":"27604",
    "sg:province":"NC",
    "sg:tags":[
        "distributor",
        "phone",
        "wholesaler",
        "card"
    ],
    "wof:name":"Conexiones Hispanas Inc",
    "wof:placetype":"venue"
},
  "geometry": {"coordinates":[-78.592501,35.817262],"type":"Point"}
}