{
  "type": "Feature",
  "properties": {
    "addr:full":"502 Water St Oriental NC 28571",
    "addr:housenumber":"502",
    "addr:postcode":"28571",
    "addr:street":"Water St",
    "iso:country":"US",
    "sg:address":"502 Water St",
    "sg:city":"Oriental",
    "sg:classifiers":[
        {
            "category":"Autos & Motor Vehicles",
            "subcategory":"Boat Sales",
            "type":"Retail Goods"
        }
    ],
    "sg:phone":"+1 252 249 7245",
    "sg:postcode":"28571",
    "sg:province":"NC",
    "sg:tags":[
        "dealership"
    ],
    "wof:name":"Saint Barts",
    "wof:placetype":"venue"
},
  "geometry": {"coordinates":[-76.69843400000001,35.025021],"type":"Point"}
}