{
  "type": "Feature",
  "properties": {
    "iso:country":"US",
    "sg:address":"5763 State Hwy 18 S",
    "sg:city":"Morganton",
    "sg:classifiers":[
        {
            "category":"Food & Beverages",
            "subcategory":"Groceries & Convenience Stores",
            "type":"Retail Goods"
        }
    ],
    "sg:phone":"+1 828 879 1511",
    "sg:postcode":"28655",
    "sg:province":"NC",
    "sg:tags":[
        "grocer"
    ],
    "wof:name":"Foothills Community Market",
    "wof:placetype":"venue"
},
  "geometry": {"coordinates":[-81.56543600000001,35.678744],"type":"Point"}
}