{
  "type": "Feature",
  "properties": {
    "addr:full":"2604 Little Rock Rd Charlotte NC 28214",
    "addr:housenumber":"2604",
    "addr:postcode":"28214",
    "addr:street":"Little Rock Rd",
    "iso:country":"US",
    "sg:address":"2604 Little Rock Rd",
    "sg:city":"Charlotte",
    "sg:classifiers":[
        {
            "category":"Restaurant",
            "type":"Food & Drink"
        }
    ],
    "sg:menulink":"http://www.allmenus.com/nc/charlotte/156183-hardees/menu/",
    "sg:phone":"+1 704 392 2239",
    "sg:postcode":"28214",
    "sg:province":"NC",
    "sg:tags":[
        "burger",
        "american"
    ],
    "wof:name":"Hardee's",
    "wof:placetype":"venue"
},
  "geometry": {"coordinates":[-80.93828600000001,35.243569],"type":"Point"}
}