{
  "type": "Feature",
  "properties": {
    "iso:country":"US",
    "sg:address":"4800 Raleigh Rd",
    "sg:city":"Kittrell",
    "sg:classifiers":[
        {
            "category":"Education",
            "subcategory":"School",
            "type":"Public Place"
        }
    ],
    "sg:phone":"+1 252 438 8492",
    "sg:postcode":"27544",
    "sg:province":"NC",
    "wof:name":"Zeb Vance Elementary School",
    "wof:placetype":"venue"
},
  "geometry": {"coordinates":[-78.413078,36.257816],"type":"Point"}
}