{
  "type": "Feature",
  "properties": {
    "addr:full":"321 Perimeter Point Blvd Winston Salem NC 27105",
    "addr:housenumber":"321",
    "addr:postcode":"27105",
    "addr:street":"Perimeter Point Blvd",
    "iso:country":"US",
    "sg:address":"321 Perimeter Point Blvd",
    "sg:city":"Winston Salem",
    "sg:classifiers":[
        {
            "category":"Building & Trades",
            "subcategory":"Construction",
            "type":"Services"
        }
    ],
    "sg:phone":"+1 336 767 3270",
    "sg:postcode":"27105",
    "sg:province":"NC",
    "sg:tags":[
        "tile",
        "dealer"
    ],
    "wof:name":"Tile Maintenance Svc",
    "wof:placetype":"venue"
},
  "geometry": {"coordinates":[-80.245063,36.139669],"type":"Point"}
}