{
  "type": "Feature",
  "properties": {
    "iso:country":"US",
    "sg:address":"1800 Four Seasons Blvd",
    "sg:city":"Hendersonville",
    "sg:classifiers":[
        {
            "category":"Shopping",
            "subcategory":"Department Store",
            "type":"Retail Goods"
        }
    ],
    "sg:phone":"+1 828 697 7991",
    "sg:postcode":"28792",
    "sg:province":"NC",
    "wof:name":"Kmart",
    "wof:placetype":"venue"
},
  "geometry": {"coordinates":[-82.446693,35.335823],"type":"Point"}
}