{
  "type": "Feature",
  "properties": {
    "addr:full":"116 US Hwy 29 Kannapolis NC 28083",
    "addr:housenumber":"116",
    "addr:postcode":"28083",
    "addr:street":"Us Hwy 29",
    "iso:country":"US",
    "sg:address":"116 US Hwy 29",
    "sg:city":"Kannapolis",
    "sg:classifiers":[
        {
            "category":"Retail",
            "subcategory":"Laundry & Dry Cleaning",
            "type":"Services"
        }
    ],
    "sg:phone":"+1 704 855 2775",
    "sg:postcode":"28083",
    "sg:province":"NC",
    "sg:tags":[
        "cleaners"
    ],
    "wof:name":"Plaza Cleaners",
    "wof:placetype":"venue"
},
  "geometry": {"coordinates":[-80.610648,35.494403],"type":"Point"}
}