{
  "type": "Feature",
  "properties": {
    "iso:country":"US",
    "sg:address":"11413 Rozzelles Ferry Rd",
    "sg:city":"Charlotte",
    "sg:classifiers":[
        {
            "category":"Building & Trades",
            "subcategory":"Construction",
            "type":"Services"
        }
    ],
    "sg:phone":"+1 704 399 1095",
    "sg:postcode":"28214",
    "sg:province":"NC",
    "sg:tags":[
        "home",
        "builder"
    ],
    "wof:name":"Portrait Homes-Rozelles",
    "wof:placetype":"venue"
},
  "geometry": {"coordinates":[-80.95947200000001,35.33084],"type":"Point"}
}