{
  "type": "Feature",
  "properties": {
    "iso:country":"US",
    "sg:address":"2800 N Main Ave",
    "sg:city":"Newton",
    "sg:classifiers":[
        {
            "category":"Autos & Motor Vehicles",
            "subcategory":"Automobile Sales",
            "type":"Retail Goods"
        }
    ],
    "sg:phone":"+1 828 466 3151",
    "sg:postcode":"28658",
    "sg:province":"NC",
    "sg:tags":[
        "car",
        "dealer"
    ],
    "wof:name":"Swanny's Auto Sales LLC",
    "wof:placetype":"venue"
},
  "geometry": {"coordinates":[-81.219167,35.692335],"type":"Point"}
}