{
  "type": "Feature",
  "properties": {
    "iso:country":"US",
    "sg:address":"9604 Callis Ct",
    "sg:city":"Harrisburg",
    "sg:classifiers":[
        {
            "category":"Building & Trades",
            "subcategory":"Construction",
            "type":"Services"
        }
    ],
    "sg:phone":"+1 704 455 8303",
    "sg:postcode":"28075",
    "sg:province":"NC",
    "sg:tags":[
        "contractor"
    ],
    "wof:name":"Ritchie Ms Construction I",
    "wof:placetype":"venue"
},
  "geometry": {"coordinates":[-80.65600999999999,35.281145],"type":"Point"}
}