{
  "type": "Feature",
  "properties": {
    "iso:country":"US",
    "sg:address":"187 Wilkesboro St",
    "sg:city":"Mocksville",
    "sg:classifiers":[
        {
            "category":"Retail",
            "subcategory":"Auto Repair",
            "type":"Services"
        }
    ],
    "sg:phone":"+1 336 753 1955",
    "sg:postcode":"27028",
    "sg:province":"NC",
    "sg:tags":[
        "muffler",
        "exhaust",
        "system"
    ],
    "wof:name":"Monster Muffler Inc LLC",
    "wof:placetype":"venue"
},
  "geometry": {"coordinates":[-80.564572,35.896621],"type":"Point"}
}