{
  "type": "Feature",
  "properties": {
    "addr:full":"3601 Airport Blvd NW Wilson NC 27896",
    "addr:housenumber":"3601",
    "addr:postcode":"27896",
    "addr:street":"Airport Blvd Nw",
    "iso:country":"US",
    "sg:address":"3601 Airport Blvd NW",
    "sg:city":"Wilson",
    "sg:classifiers":[
        {
            "category":"Shopping",
            "subcategory":"Crafts & Fabrics",
            "type":"Retail Goods"
        }
    ],
    "sg:phone":"+1 252 291 8205",
    "sg:postcode":"27896",
    "sg:province":"NC",
    "sg:tags":[
        "etc-retail",
        "trees-silk",
        "plant",
        "flowers",
        "dried"
    ],
    "sg:website":"http://www.thegalleryofflowers.com",
    "wof:name":"The Gallery Of Flowers",
    "wof:placetype":"venue"
},
  "geometry": {"coordinates":[-77.943703,35.767879],"type":"Point"}
}