{
  "type": "Feature",
  "properties": {
    "addr:full":"1424 Bascomb Dr Raleigh NC 27614",
    "addr:housenumber":"1424",
    "addr:postcode":"27614",
    "addr:street":"Bascomb Dr",
    "iso:country":"US",
    "sg:address":"1424 Bascomb Dr",
    "sg:city":"Raleigh",
    "sg:classifiers":[
        {
            "category":"Building & Trades",
            "subcategory":"Construction",
            "type":"Services"
        }
    ],
    "sg:phone":"+1 919 844 7092",
    "sg:postcode":"27614",
    "sg:province":"NC",
    "sg:tags":[
        "general",
        "contractor"
    ],
    "wof:name":"Residential Construction",
    "wof:placetype":"venue"
},
  "geometry": {"coordinates":[-78.618197,35.940464],"type":"Point"}
}