{
  "type": "Feature",
  "properties": {
    "addr:full":"589 Ridge Ln Wilkesboro NC 28697",
    "addr:housenumber":"589",
    "addr:postcode":"28697",
    "addr:street":"Ridge Ln",
    "iso:country":"US",
    "sg:address":"589 Ridge Ln",
    "sg:city":"Wilkesboro",
    "sg:classifiers":[
        {
            "category":"Freight",
            "type":"Transportation"
        }
    ],
    "sg:phone":"+1 336 973 4697",
    "sg:postcode":"28697",
    "sg:province":"NC",
    "sg:tags":[
        "trucking"
    ],
    "wof:name":"Mt Pleasant Trucking Co Inc",
    "wof:placetype":"venue"
},
  "geometry": {"coordinates":[-81.287757,36.13511],"type":"Point"}
}