{
  "type": "Feature",
  "properties": {
    "iso:country":"US",
    "sg:address":"1276 Hendersonville Rd",
    "sg:city":"Asheville",
    "sg:classifiers":[
        {
            "category":"Insurance",
            "subcategory":"Insurance Agent",
            "type":"Services"
        }
    ],
    "sg:phone":"+1 828 274 7655",
    "sg:postcode":"28803",
    "sg:province":"NC",
    "sg:tags":[
        "agency"
    ],
    "sg:website":"www.assetprotectionnetwork.net",
    "wof:name":"Asset Protection Network Inc",
    "wof:placetype":"venue"
},
  "geometry": {"coordinates":[-82.52927200000001,35.527048],"type":"Point"}
}