{
  "type": "Feature",
  "properties": {
    "iso:country":"US",
    "sg:address":"3020 Kader Lilley Rd",
    "sg:city":"Williamston",
    "sg:classifiers":[
        {
            "category":"Personal",
            "subcategory":"Beauty Salon",
            "type":"Services"
        }
    ],
    "sg:phone":"+1 252 792 1749",
    "sg:postcode":"27892",
    "sg:province":"NC",
    "wof:name":"Annie's Beauty Ctr",
    "wof:placetype":"venue"
},
  "geometry": {"coordinates":[-77.024064,35.781234],"type":"Point"}
}