{
  "type": "Feature",
  "properties": {
    "iso:country":"US",
    "sg:address":"531 E Strawberry Blvd",
    "sg:city":"Chadbourn",
    "sg:classifiers":[
        {
            "category":"Shopping",
            "subcategory":"Used Merchandise",
            "type":"Retail Goods"
        },
        {
            "category":"Shopping",
            "subcategory":"Clothing, Apparel, & Fashions",
            "type":"Retail Goods"
        }
    ],
    "sg:phone":"+1 910 654 1083",
    "sg:postcode":"28431",
    "sg:province":"NC",
    "sg:tags":[
        "shop",
        "thrift"
    ],
    "wof:name":"Ronnie's Thrift Store",
    "wof:placetype":"venue"
},
  "geometry": {"coordinates":[-78.81892499999999,34.326851],"type":"Point"}
}