{
  "type": "Feature",
  "properties": {
    "addr:full":"1945 US Hwy 70 Kinston NC 28501",
    "addr:housenumber":"1945",
    "addr:postcode":"28501",
    "addr:street":"Us Hwy 70",
    "iso:country":"US",
    "sg:address":"1945 US Hwy 70",
    "sg:city":"Kinston",
    "sg:classifiers":[
        {
            "category":"Restaurant",
            "type":"Food & Drink"
        }
    ],
    "sg:phone":"+1 252 523 7080",
    "sg:postcode":"28501",
    "sg:province":"NC",
    "wof:name":"Mary Lou's Grill & Sandwich",
    "wof:placetype":"venue"
},
  "geometry": {"coordinates":[-77.536559,35.226135],"type":"Point"}
}