{
  "type": "Feature",
  "properties": {
    "addr:full":"120 Heather Ridge Ct Durham NC 27712",
    "addr:housenumber":"120",
    "addr:postcode":"27712",
    "addr:street":"Heather Ridge Ct",
    "iso:country":"US",
    "sg:address":"120 Heather Ridge Ct",
    "sg:city":"Durham",
    "sg:classifiers":[
        {
            "category":"Retail",
            "subcategory":"Auto Repair",
            "type":"Services"
        }
    ],
    "sg:phone":"+1   ",
    "sg:postcode":"27712",
    "sg:province":"NC",
    "sg:tags":[
        "mobile",
        "installation",
        "sales",
        "tire"
    ],
    "wof:name":"Pit Stop Tire Service",
    "wof:placetype":"venue"
},
  "geometry": {"coordinates":[-78.968975,36.085402],"type":"Point"}
}