{
  "type": "Feature",
  "properties": {
    "addr:full":"421 E 3rd St Siler City NC 27344",
    "addr:housenumber":"421",
    "addr:postcode":"27344",
    "addr:street":"E 3Rd St",
    "iso:country":"US",
    "sg:address":"421 E 3rd St",
    "sg:city":"Siler City",
    "sg:classifiers":[
        {
            "category":"Retail",
            "subcategory":"Auto Repair",
            "type":"Services"
        }
    ],
    "sg:phone":"+1 919 663 2604",
    "sg:postcode":"27344",
    "sg:province":"NC",
    "sg:tags":[
        "repairing",
        "automobile"
    ],
    "wof:name":"Nelson's Auto Parts & Tires",
    "wof:placetype":"venue"
},
  "geometry": {"coordinates":[-79.458709,35.727335],"type":"Point"}
}