{
  "type": "Feature",
  "properties": {
    "iso:country":"US",
    "sg:address":"1122 Ziglar Rd",
    "sg:city":"Winston Salem",
    "sg:classifiers":[
        {
            "category":"Professional",
            "subcategory":"Art Services",
            "type":"Services"
        }
    ],
    "sg:phone":"+1 336 924 6606",
    "sg:postcode":"27105",
    "sg:province":"NC",
    "sg:tags":[
        "graphic",
        "designer"
    ],
    "wof:name":"Brewer Graphics",
    "wof:placetype":"venue"
},
  "geometry": {"coordinates":[-80.299454,36.193457],"type":"Point"}
}