{
  "type": "Feature",
  "properties": {
    "iso:country":"US",
    "sg:address":"100 Brewer Ln",
    "sg:city":"Carrboro",
    "sg:classifiers":[
        {
            "category":"Communications",
            "subcategory":"Film & Video Production",
            "type":"Services"
        }
    ],
    "sg:phone":"+1   ",
    "sg:postcode":"27510",
    "sg:province":"NC",
    "sg:tags":[
        "motion",
        "picture"
    ],
    "wof:name":"Go Rehearsal Inc",
    "wof:placetype":"venue"
},
  "geometry": {"coordinates":[-79.06525499999999,35.909693],"type":"Point"}
}