{
  "type": "Feature",
  "properties": {
    "iso:country":"US",
    "sg:address":"4125 Horseshoe Bend",
    "sg:city":"Matthews",
    "sg:classifiers":[
        {
            "category":"Home & Garden",
            "subcategory":"Furniture",
            "type":"Retail Goods"
        }
    ],
    "sg:phone":"+1 704 844 8871",
    "sg:postcode":"28104",
    "sg:province":"NC",
    "wof:name":"Sublime Furniture Service Ltd",
    "wof:placetype":"venue"
},
  "geometry": {"coordinates":[-80.74928800000001,35.045173],"type":"Point"}
}