{
  "type": "Feature",
  "properties": {
    "iso:country":"US",
    "sg:address":"350 US Hwy 701 S",
    "sg:city":"Four Oaks",
    "sg:classifiers":[
        {
            "category":"Retail",
            "subcategory":"Auto Rental",
            "type":"Services"
        }
    ],
    "sg:phone":"+1 919 934 2600",
    "sg:postcode":"27524",
    "sg:province":"NC",
    "sg:tags":[
        "renting",
        "truck",
        "leasing"
    ],
    "wof:name":"U-Haul Co",
    "wof:placetype":"venue"
},
  "geometry": {"coordinates":[-78.388919,35.454244],"type":"Point"}
}