{
  "type": "Feature",
  "properties": {
    "addr:full":"114 S Fayetteville St Liberty NC 27298",
    "addr:housenumber":"114",
    "addr:postcode":"27298",
    "addr:street":"S Fayetteville St",
    "iso:country":"US",
    "sg:address":"114 S Fayetteville St",
    "sg:city":"Liberty",
    "sg:classifiers":[
        {
            "category":"Personal",
            "subcategory":"Beauty Salon",
            "type":"Services"
        }
    ],
    "sg:phone":"+1 336 622 4951",
    "sg:postcode":"27298",
    "sg:province":"NC",
    "wof:name":"Liberty Beauty Shop",
    "wof:placetype":"venue"
},
  "geometry": {"coordinates":[-79.57062000000001,35.853217],"type":"Point"}
}