{
  "type": "Feature",
  "properties": {
    "iso:country":"US",
    "sg:address":"45 E Boiling Spring Rd",
    "sg:city":"Southport",
    "sg:classifiers":[
        {
            "category":"Organizations",
            "subcategory":"Religious Organization",
            "type":"Services"
        }
    ],
    "sg:phone":"+1 910 845 2169",
    "sg:postcode":"28461",
    "sg:province":"NC",
    "sg:tags":[
        "church"
    ],
    "sg:website":"www.bslchurch.com",
    "wof:name":"First Baptist Church Of Bsl",
    "wof:placetype":"venue"
},
  "geometry": {"coordinates":[-78.066723,34.031295],"type":"Point"}
}