{
  "type": "Feature",
  "properties": {
    "iso:country":"US",
    "sg:address":"6836 Morrison Blvd",
    "sg:city":"Charlotte",
    "sg:classifiers":[
        {
            "category":"Health Services",
            "subcategory":"Doctor",
            "type":"Services"
        }
    ],
    "sg:phone":"+1 704 365 0343",
    "sg:postcode":"28211",
    "sg:province":"NC",
    "sg:tags":[
        "physician",
        "surgeon"
    ],
    "wof:name":"Charlotte Radiology PA",
    "wof:placetype":"venue"
},
  "geometry": {"coordinates":[-80.82570200000001,35.151492],"type":"Point"}
}