{
  "type": "Feature",
  "properties": {
    "iso:country":"US",
    "sg:address":"7576 Watson Seed Farm Rd",
    "sg:city":"Whitakers",
    "sg:phone":"+1 252 443 0598",
    "sg:postcode":"27891",
    "sg:province":"NC",
    "sg:tags":[
        "farm",
        "field",
        "crop"
    ],
    "wof:name":"Massengale Farms",
    "wof:placetype":"venue"
},
  "geometry": {"coordinates":[-77.85709,36.082395],"type":"Point"}
}