{
  "type": "Feature",
  "properties": {
    "addr:full":"1900 Milan Rd Greensboro NC 27410",
    "addr:housenumber":"1900",
    "addr:postcode":"27410",
    "addr:street":"Milan Rd",
    "iso:country":"US",
    "sg:address":"1900 Milan Rd",
    "sg:city":"Greensboro",
    "sg:classifiers":[
        {
            "category":"Wholesale",
            "subcategory":"Stationery",
            "type":"Manufacturing & Wholesale Goods"
        }
    ],
    "sg:phone":"+1 336 282 0114",
    "sg:postcode":"27410",
    "sg:province":"NC",
    "sg:tags":[
        "supply"
    ],
    "wof:name":"B&R Commercial Forms",
    "wof:placetype":"venue"
},
  "geometry": {"coordinates":[-79.850123,36.107364],"type":"Point"}
}