{
  "type": "Feature",
  "properties": {
    "addr:full":"2611 New Walkertown Rd NE Winston Salem NC 27101",
    "addr:housenumber":"2611",
    "addr:postcode":"27101",
    "addr:street":"New Walkertown Rd Ne",
    "iso:country":"US",
    "sg:address":"2611 New Walkertown Rd NE",
    "sg:city":"Winston Salem",
    "sg:classifiers":[
        {
            "category":"Museum",
            "type":"Entertainment"
        }
    ],
    "sg:phone":"+1 336 722 2625",
    "sg:postcode":"27101",
    "sg:province":"NC",
    "sg:tags":[
        "organization",
        "arts",
        "information"
    ],
    "wof:name":"Delta Arts Ctr",
    "wof:placetype":"venue"
},
  "geometry": {"coordinates":[-80.21261199999999,36.111348],"type":"Point"}
}