{
  "type": "Feature",
  "properties": {
    "addr:full":"1358 Bear Creek Rd Leicester NC 28748",
    "addr:housenumber":"1358",
    "addr:postcode":"28748",
    "addr:street":"Bear Creek Rd",
    "iso:country":"US",
    "sg:address":"1358 Bear Creek Rd",
    "sg:city":"Leicester",
    "sg:classifiers":[
        {
            "category":"Professional",
            "subcategory":"Management & Consulting",
            "type":"Services"
        }
    ],
    "sg:phone":"+1 828 254 9280",
    "sg:postcode":"28748",
    "sg:province":"NC",
    "sg:tags":[
        "consultant",
        "business"
    ],
    "wof:name":"L F Zerfoss Assoc Inc",
    "wof:placetype":"venue"
},
  "geometry": {"coordinates":[-82.663371,35.659942],"type":"Point"}
}