{
  "type": "Feature",
  "properties": {
    "iso:country":"US",
    "sg:address":"3600 Manford Dr",
    "sg:city":"Durham",
    "sg:classifiers":[
        {
            "category":"Professional",
            "subcategory":"Computer Services",
            "type":"Services"
        }
    ],
    "sg:phone":"+1   ",
    "sg:postcode":"27707",
    "sg:province":"NC",
    "sg:tags":[
        "prepackaged",
        "software"
    ],
    "wof:name":"Forty Two Software Inc",
    "wof:placetype":"venue"
},
  "geometry": {"coordinates":[-78.934004,35.950303],"type":"Point"}
}