{
  "type": "Feature",
  "properties": {
    "iso:country":"US",
    "sg:address":"18 E 10th St",
    "sg:city":"Roanoke Rapids",
    "sg:classifiers":[
        {
            "category":"Insurance",
            "subcategory":"Insurance Agent",
            "type":"Services"
        }
    ],
    "sg:phone":"+1 252 537 2547",
    "sg:postcode":"27870",
    "sg:province":"NC",
    "wof:name":"Davis Insurance & Real Estate",
    "wof:placetype":"venue"
},
  "geometry": {"coordinates":[-77.656976,36.456096],"type":"Point"}
}