{
  "type": "Feature",
  "properties": {
    "iso:country":"US",
    "sg:address":"3514 Rindle Ct",
    "sg:city":"Charlotte",
    "sg:classifiers":[
        {
            "category":"Professional",
            "subcategory":"Lawyer & Legal Services",
            "type":"Services"
        }
    ],
    "sg:phone":"+1   ",
    "sg:postcode":"28269",
    "sg:province":"NC",
    "wof:name":"Spivey & Associates",
    "wof:placetype":"venue"
},
  "geometry": {"coordinates":[-80.80377900000001,35.316034],"type":"Point"}
}