{
  "type": "Feature",
  "properties": {
    "iso:country":"US",
    "sg:address":"308 White Oak Ct",
    "sg:city":"Fayetteville",
    "sg:classifiers":[
        {
            "category":"Organizations",
            "subcategory":"Non-profit Organization",
            "type":"Services"
        }
    ],
    "sg:phone":"+1 910 484 2555",
    "sg:postcode":"28303",
    "sg:province":"NC",
    "sg:tags":[
        "social"
    ],
    "wof:name":"National Society of Sons",
    "wof:placetype":"venue"
},
  "geometry": {"coordinates":[-78.92872699999999,35.060711],"type":"Point"}
}