{
  "type": "Feature",
  "properties": {
    "addr:full":"26 Highland Dr Marion NC 28752",
    "addr:housenumber":"26",
    "addr:postcode":"28752",
    "addr:street":"Highland Dr",
    "iso:country":"US",
    "sg:address":"26 Highland Dr",
    "sg:city":"Marion",
    "sg:classifiers":[
        {
            "category":"Real Estate",
            "subcategory":"Real Estate Agent",
            "type":"Services"
        }
    ],
    "sg:phone":"+1 828 659 3600",
    "sg:postcode":"28752",
    "sg:province":"NC",
    "wof:name":"Cochran Realty",
    "wof:placetype":"venue"
},
  "geometry": {"coordinates":[-81.99959800000001,35.690062],"type":"Point"}
}