{
  "type": "Feature",
  "properties": {
    "iso:country":"US",
    "sg:address":"189 Gilbert Rd",
    "sg:city":"Lincolnton",
    "sg:classifiers":[
        {
            "category":"Building & Trades",
            "subcategory":"Plumbing",
            "type":"Services"
        }
    ],
    "sg:phone":"+1 704 735 8926",
    "sg:postcode":"28092",
    "sg:province":"NC",
    "sg:tags":[
        "conditioning",
        "air",
        "system",
        "contractor"
    ],
    "wof:name":"Bob's Repair Svc Inc",
    "wof:placetype":"venue"
},
  "geometry": {"coordinates":[-81.342872,35.4809],"type":"Point"}
}