{
  "type": "Feature",
  "properties": {
    "iso:country":"US",
    "sg:address":"1820 Fayetteville Rd",
    "sg:city":"Rockingham",
    "sg:classifiers":[
        {
            "category":"Autos & Motor Vehicles",
            "subcategory":"Automobile Sales",
            "type":"Retail Goods"
        }
    ],
    "sg:phone":"+1 910 997 7711",
    "sg:postcode":"28379",
    "sg:province":"NC",
    "sg:tags":[
        "used"
    ],
    "wof:name":"Clarke Inc",
    "wof:placetype":"venue"
},
  "geometry": {"coordinates":[-79.749985,34.947739],"type":"Point"}
}