{
  "type": "Feature",
  "properties": {
    "addr:full":"1108 Crossroads Dr Statesville NC 28625",
    "addr:housenumber":"1108",
    "addr:postcode":"28625",
    "addr:street":"Crossroads Dr",
    "iso:country":"US",
    "sg:address":"1108 Crossroads Dr",
    "sg:city":"Statesville",
    "sg:classifiers":[
        {
            "category":"Shopping",
            "subcategory":"Clothing, Apparel, & Fashions",
            "type":"Retail Goods"
        }
    ],
    "sg:phone":"+1 704 873 9509",
    "sg:postcode":"28625",
    "sg:province":"NC",
    "wof:name":"Cato Plus",
    "wof:placetype":"venue"
},
  "geometry": {"coordinates":[-80.872546,35.809744],"type":"Point"}
}