{
  "type": "Feature",
  "properties": {
    "addr:full":"320 Baptist Church Rd Gold Hill NC 28071",
    "addr:housenumber":"320",
    "addr:postcode":"28071",
    "addr:street":"Baptist Church Rd",
    "iso:country":"US",
    "sg:address":"320 Baptist Church Rd",
    "sg:city":"Gold Hill",
    "sg:classifiers":[
        {
            "category":"Organizations",
            "subcategory":"Religious Organization",
            "type":"Services"
        }
    ],
    "sg:phone":"+1   ",
    "sg:postcode":"28071",
    "sg:province":"NC",
    "wof:name":"Gold Hill Baptinst Church",
    "wof:placetype":"venue"
},
  "geometry": {"coordinates":[-80.341414,35.517729],"type":"Point"}
}