{
  "type": "Feature",
  "properties": {
    "addr:full":"9051 E Old US Hwy 64 Lexington NC 27292",
    "addr:housenumber":"9051",
    "addr:postcode":"27292",
    "addr:street":"E Old Us Hwy 64",
    "iso:country":"US",
    "sg:address":"9051 E Old US Hwy 64",
    "sg:city":"Lexington",
    "sg:classifiers":[
        {
            "category":"Retail",
            "subcategory":"Auto Repair",
            "type":"Services"
        }
    ],
    "sg:phone":"+1 336 472 9245",
    "sg:postcode":"27292",
    "sg:province":"NC",
    "sg:tags":[
        "body",
        "automobile",
        "painting"
    ],
    "wof:name":"Decker Motor Co",
    "wof:placetype":"venue"
},
  "geometry": {"coordinates":[-80.135895,35.739622],"type":"Point"}
}