{
  "type": "Feature",
  "properties": {
    "iso:country":"US",
    "sg:address":"5417 Lake Edge Dr",
    "sg:city":"Holly Springs",
    "sg:classifiers":[
        {
            "category":"Real Estate",
            "subcategory":"Real Estate Agent",
            "type":"Services"
        }
    ],
    "sg:phone":"+1 919 552 7394",
    "sg:postcode":"27540",
    "sg:province":"NC",
    "wof:name":"Raleigh Property Management LL",
    "wof:placetype":"venue"
},
  "geometry": {"coordinates":[-78.79563,35.64778],"type":"Point"}
}