{
  "type": "Feature",
  "properties": {
    "addr:full":"2510 Norwood St SW Lenoir NC 28645",
    "addr:housenumber":"2510",
    "addr:postcode":"28645",
    "addr:street":"Norwood St Sw",
    "iso:country":"US",
    "sg:address":"2510 Norwood St SW",
    "sg:city":"Lenoir",
    "sg:classifiers":[
        {
            "category":"Building & Trades",
            "subcategory":"Construction",
            "type":"Services"
        }
    ],
    "sg:phone":"+1 828 728 9701",
    "sg:postcode":"28645",
    "sg:province":"NC",
    "sg:tags":[
        "nonresidential"
    ],
    "wof:name":"Steelcon",
    "wof:placetype":"venue"
},
  "geometry": {"coordinates":[-81.510673,35.869734],"type":"Point"}
}