{
  "type": "Feature",
  "properties": {
    "iso:country":"US",
    "sg:address":"3215 Baucom Manor Rd",
    "sg:city":"Monroe",
    "sg:classifiers":[
        {
            "category":"Building & Trades",
            "subcategory":"Electrical",
            "type":"Services"
        }
    ],
    "sg:phone":"+1 704 753 2158",
    "sg:postcode":"28110",
    "sg:province":"NC",
    "sg:tags":[
        "electrical",
        "contractor"
    ],
    "wof:name":"Barry Johnson Electric Co",
    "wof:placetype":"venue"
},
  "geometry": {"coordinates":[-80.453351,35.098224],"type":"Point"}
}