{
  "type": "Feature",
  "properties": {
    "addr:full":"104 W Main St Elizabeth City NC 27909",
    "addr:housenumber":"104",
    "addr:postcode":"27909",
    "addr:street":"W Main St",
    "iso:country":"US",
    "sg:address":"104 W Main St",
    "sg:city":"Elizabeth City",
    "sg:classifiers":[
        {
            "category":"Personal",
            "subcategory":"Beauty Salon",
            "type":"Services"
        }
    ],
    "sg:phone":"+1 252 338 1011",
    "sg:postcode":"27909",
    "sg:province":"NC",
    "wof:name":"Still Waters Salon & Spa",
    "wof:placetype":"venue"
},
  "geometry": {"coordinates":[-76.22454500000001,36.300447],"type":"Point"}
}