{
  "type": "Feature",
  "properties": {
    "addr:full":"12845 Old US Hwy 52 Winston Salem NC 27107",
    "addr:housenumber":"12845",
    "addr:postcode":"27107",
    "addr:street":"Old Us Hwy 52",
    "iso:country":"US",
    "sg:address":"12845 Old US Hwy 52",
    "sg:city":"Winston Salem",
    "sg:classifiers":[
        {
            "category":"Communications",
            "type":"Services"
        }
    ],
    "sg:phone":"+1 336 760 5512",
    "sg:postcode":"27107",
    "sg:province":"NC",
    "sg:tags":[
        "carrier"
    ],
    "wof:name":"Ken-Nect Communications",
    "wof:placetype":"venue"
},
  "geometry": {"coordinates":[-80.230238,35.991763],"type":"Point"}
}