{
  "type": "Feature",
  "properties": {
    "iso:country":"US",
    "sg:address":"705 Eden Ter",
    "sg:city":"Archdale",
    "sg:classifiers":[
        {
            "category":"Freight",
            "type":"Transportation"
        }
    ],
    "sg:phone":"+1 336 861 6623",
    "sg:postcode":"27263",
    "sg:province":"NC",
    "sg:tags":[
        "packing",
        "crating"
    ],
    "sg:website":"www.centralwarehouse.net",
    "wof:name":"Central Warehouse & Forwarding",
    "wof:placetype":"venue"
},
  "geometry": {"coordinates":[-79.988572,35.915043],"type":"Point"}
}