{
  "type": "Feature",
  "properties": {
    "iso:country":"US",
    "sg:address":"2700 Wycliff Rd",
    "sg:city":"Raleigh",
    "sg:classifiers":[
        {
            "category":"Social Services",
            "type":"Services"
        }
    ],
    "sg:phone":"+1   ",
    "sg:postcode":"27607",
    "sg:province":"NC",
    "wof:name":"Lake Bone Cnsling Psychlogical",
    "wof:placetype":"venue"
},
  "geometry": {"coordinates":[-78.690935,35.819835],"type":"Point"}
}