{
  "type": "Feature",
  "properties": {
    "addr:full":"1092 Dewitt Smith Rd Pittsboro NC 27312",
    "addr:housenumber":"1092",
    "addr:postcode":"27312",
    "addr:street":"Dewitt Smith Rd",
    "iso:country":"US",
    "sg:address":"1092 Dewitt Smith Rd",
    "sg:city":"Pittsboro",
    "sg:classifiers":[
        {
            "category":"Farming",
            "subcategory":"Livestock Farm",
            "type":"Manufacturing & Wholesale Goods"
        }
    ],
    "sg:phone":"+1 919 542 5890",
    "sg:postcode":"27312",
    "sg:province":"NC",
    "sg:tags":[
        "specialty",
        "animal"
    ],
    "wof:name":"Busy Bee Farm",
    "wof:placetype":"venue"
},
  "geometry": {"coordinates":[-79.271213,35.652441],"type":"Point"}
}