{
  "type": "Feature",
  "properties": {
    "addr:full":"235 Craven Dr Thomasville NC 27360",
    "addr:housenumber":"235",
    "addr:postcode":"27360",
    "addr:street":"Craven Dr",
    "iso:country":"US",
    "sg:address":"235 Craven Dr",
    "sg:city":"Thomasville",
    "sg:classifiers":[
        {
            "category":"Personal",
            "subcategory":"Beauty Salon",
            "type":"Services"
        }
    ],
    "sg:phone":"+1 336 472 7983",
    "sg:postcode":"27360",
    "sg:province":"NC",
    "sg:tags":[
        "shop"
    ],
    "wof:name":"Country Side Beauty Shop",
    "wof:placetype":"venue"
},
  "geometry": {"coordinates":[-80.11438200000001,35.894829],"type":"Point"}
}