{
  "type": "Feature",
  "properties": {
    "iso:country":"US",
    "sg:address":"1212 Tangle Ln",
    "sg:city":"High Point",
    "sg:classifiers":[
        {
            "category":"Shopping",
            "subcategory":"Gifts & Souvenirs",
            "type":"Retail Goods"
        }
    ],
    "sg:phone":"+1 336 885 2740",
    "sg:postcode":"27265",
    "sg:province":"NC",
    "wof:name":"Greens Gift Shop",
    "wof:placetype":"venue"
},
  "geometry": {"coordinates":[-79.96259000000001,36.0057],"type":"Point"}
}