{
  "type": "Feature",
  "properties": {
    "iso:country":"US",
    "sg:address":"1914 Brunswick Ave",
    "sg:city":"Charlotte",
    "sg:classifiers":[
        {
            "category":"Professional",
            "subcategory":"Business Services",
            "type":"Services"
        },
        {
            "category":"Professional",
            "subcategory":"Management & Consulting",
            "type":"Services"
        }
    ],
    "sg:phone":"+1 704 334 4932",
    "sg:postcode":"28207",
    "sg:province":"NC",
    "sg:tags":[
        "appraiser"
    ],
    "sg:website":"www.banisterfinancial.com",
    "wof:name":"Banister Financial Inc",
    "wof:placetype":"venue"
},
  "geometry": {"coordinates":[-80.834891,35.200159],"type":"Point"}
}