{
  "type": "Feature",
  "properties": {
    "iso:country":"US",
    "sg:address":"1525 2nd St NE",
    "sg:city":"Hickory",
    "sg:classifiers":[
        {
            "category":"Restaurant",
            "type":"Food & Drink"
        }
    ],
    "sg:phone":"+1 828 324 9000",
    "sg:postcode":"28601",
    "sg:province":"NC",
    "sg:tags":[
        "shop",
        "coffee"
    ],
    "wof:name":"Saxby's Coffee",
    "wof:placetype":"venue"
},
  "geometry": {"coordinates":[-81.33681900000001,35.753454],"type":"Point"}
}