{
  "type": "Feature",
  "properties": {
    "addr:full":"108 E Hargett St Richlands NC 28574",
    "addr:housenumber":"108",
    "addr:postcode":"28574",
    "addr:street":"E Hargett St",
    "iso:country":"US",
    "sg:address":"108 E Hargett St",
    "sg:city":"Richlands",
    "sg:classifiers":[
        {
            "category":"Professional",
            "subcategory":"Business Services",
            "type":"Services"
        }
    ],
    "sg:phone":"+1   ",
    "sg:postcode":"28574",
    "sg:province":"NC",
    "wof:name":"Conner Drafting & Design",
    "wof:placetype":"venue"
},
  "geometry": {"coordinates":[-77.54612299999999,34.899853],"type":"Point"}
}