{
  "type": "Feature",
  "properties": {
    "iso:country":"US",
    "sg:address":"6048 Wrightsville Ave",
    "sg:city":"Wilmington",
    "sg:classifiers":[
        {
            "category":"Shopping",
            "subcategory":"Hobbies, Toys, & Games",
            "type":"Retail Goods"
        }
    ],
    "sg:phone":"+1 910 452 7177",
    "sg:postcode":"28403",
    "sg:province":"NC",
    "sg:tags":[
        "product",
        "ceramic"
    ],
    "wof:name":"Paint N Play A Ceramic Studio",
    "wof:placetype":"venue"
},
  "geometry": {"coordinates":[-77.845224,34.220203],"type":"Point"}
}