{
  "type": "Feature",
  "properties": {
    "addr:full":"805 Cameo Ct Wilmington NC 28409",
    "addr:housenumber":"805",
    "addr:postcode":"28409",
    "addr:street":"Cameo Ct",
    "iso:country":"US",
    "sg:address":"805 Cameo Ct",
    "sg:city":"Wilmington",
    "sg:classifiers":[
        {
            "category":"Professional",
            "type":"Services"
        }
    ],
    "sg:phone":"+1 910 392 6677",
    "sg:postcode":"28409",
    "sg:province":"NC",
    "wof:name":"Michael H Fatzinger",
    "wof:placetype":"venue"
},
  "geometry": {"coordinates":[-77.88414,34.141068],"type":"Point"}
}