{
  "type": "Feature",
  "properties": {
    "iso:country":"US",
    "sg:address":"810 E Market St",
    "sg:city":"Smithfield",
    "sg:classifiers":[
        {
            "category":"Shopping",
            "subcategory":"Gifts & Souvenirs",
            "type":"Retail Goods"
        }
    ],
    "sg:phone":"+1 919 209 9994",
    "sg:postcode":"27577",
    "sg:province":"NC",
    "sg:tags":[
        "basket",
        "parcel"
    ],
    "wof:name":"Rachel's Plants & Gift Baskets",
    "wof:placetype":"venue"
},
  "geometry": {"coordinates":[-78.33945199999999,35.508381],"type":"Point"}
}