{
  "type": "Feature",
  "properties": {
    "addr:full":"6413 Windmill Way Wilmington NC 28405",
    "addr:housenumber":"6413",
    "addr:postcode":"28405",
    "addr:street":"Windmill Way",
    "iso:country":"US",
    "sg:address":"6413 Windmill Way",
    "sg:city":"Wilmington",
    "sg:classifiers":[
        {
            "category":"Building & Trades",
            "subcategory":"Construction",
            "type":"Services"
        }
    ],
    "sg:phone":"+1 910 799 7212",
    "sg:postcode":"28405",
    "sg:province":"NC",
    "sg:tags":[
        "hanging",
        "painter",
        "contractor"
    ],
    "wof:name":"Keystone Painting Corp",
    "wof:placetype":"venue"
},
  "geometry": {"coordinates":[-77.843176,34.2595],"type":"Point"}
}