{
  "type": "Feature",
  "properties": {
    "iso:country":"US",
    "sg:address":"8364 Six Forks Rd",
    "sg:city":"Raleigh",
    "sg:classifiers":[
        {
            "category":"Shopping",
            "type":"Retail Goods"
        }
    ],
    "sg:phone":"+1 919 845 0234",
    "sg:postcode":"27615",
    "sg:province":"NC",
    "sg:tags":[
        "wig",
        "artificial",
        "accessory",
        "application",
        "prosthesis",
        "breast"
    ],
    "wof:name":"Dianne's Selections",
    "wof:placetype":"venue"
},
  "geometry": {"coordinates":[-78.64833400000001,35.891739],"type":"Point"}
}