{
  "type": "Feature",
  "properties": {
    "addr:full":"158 Harbor Point Dr Cherryville NC 28021",
    "addr:housenumber":"158",
    "addr:postcode":"28021",
    "addr:street":"Harbor Point Dr",
    "iso:country":"US",
    "sg:address":"158 Harbor Point Dr",
    "sg:city":"Cherryville",
    "sg:classifiers":[
        {
            "category":"Food & Beverages",
            "subcategory":"Groceries & Convenience Stores",
            "type":"Retail Goods"
        }
    ],
    "sg:phone":"+1 704 482 1900",
    "sg:postcode":"28021",
    "sg:province":"NC",
    "wof:name":"Village Mini-Mart/R-M Oil Inc",
    "wof:placetype":"venue"
},
  "geometry": {"coordinates":[-81.446597,35.312315],"type":"Point"}
}