{
  "type": "Feature",
  "properties": {
    "iso:country":"US",
    "sg:address":"4730 Alderbrook Ln",
    "sg:city":"Durham",
    "sg:classifiers":[
        {
            "category":"Retail",
            "subcategory":"Portrait Studio",
            "type":"Services"
        }
    ],
    "sg:phone":"+1   ",
    "sg:postcode":"27713",
    "sg:province":"NC",
    "sg:tags":[
        "photo"
    ],
    "wof:name":"Engram Nate Photography",
    "wof:placetype":"venue"
},
  "geometry": {"coordinates":[-78.93276400000001,35.938056],"type":"Point"}
}