{
  "type": "Feature",
  "properties": {
    "addr:full":"10555 Paces Ave Matthews NC 28105",
    "addr:housenumber":"10555",
    "addr:postcode":"28105",
    "addr:street":"Paces Ave",
    "iso:country":"US",
    "sg:address":"10555 Paces Ave",
    "sg:city":"Matthews",
    "sg:classifiers":[
        {
            "category":"Professional",
            "subcategory":"Research",
            "type":"Services"
        }
    ],
    "sg:phone":"+1   ",
    "sg:postcode":"28105",
    "sg:province":"NC",
    "sg:tags":[
        "commercialization"
    ],
    "wof:name":"Enviro Tech Enterprises Inc",
    "wof:placetype":"venue"
},
  "geometry": {"coordinates":[-80.711579,35.124258],"type":"Point"}
}