{
  "type": "Feature",
  "properties": {
    "iso:country":"US",
    "sg:address":"118 Fayetteville St",
    "sg:city":"Clinton",
    "sg:classifiers":[
        {
            "category":"Retail",
            "subcategory":"Funeral Services",
            "type":"Services"
        }
    ],
    "sg:phone":"+1 910 592 2066",
    "sg:postcode":"28328",
    "sg:province":"NC",
    "wof:name":"Crumpler-Honeycutt Funeral Hm",
    "wof:placetype":"venue"
},
  "geometry": {"coordinates":[-78.326925,34.998243],"type":"Point"}
}