{
  "type": "Feature",
  "properties": {
    "iso:country":"US",
    "sg:address":"811 Warf Rd",
    "sg:city":"Lexington",
    "sg:classifiers":[
        {
            "category":"Organizations",
            "subcategory":"Religious Organization",
            "type":"Services"
        }
    ],
    "sg:phone":"+1 336 798 2148",
    "sg:postcode":"27292",
    "sg:province":"NC",
    "sg:tags":[
        "clergy"
    ],
    "wof:name":"Coy L Hepler",
    "wof:placetype":"venue"
},
  "geometry": {"coordinates":[-80.256165,35.709663],"type":"Point"}
}