{
  "type": "Feature",
  "properties": {
    "iso:country":"US",
    "sg:address":"3019 Kilborne Dr",
    "sg:city":"Charlotte",
    "sg:classifiers":[
        {
            "category":"Manufacturing",
            "subcategory":"Jewelry",
            "type":"Manufacturing & Wholesale Goods"
        }
    ],
    "sg:phone":"+1 704 537 7099",
    "sg:postcode":"28205",
    "sg:province":"NC",
    "sg:tags":[
        "material",
        "mfg"
    ],
    "wof:name":"Lapidary Arts",
    "wof:placetype":"venue"
},
  "geometry": {"coordinates":[-80.771204,35.213977],"type":"Point"}
}