{
  "type": "Feature",
  "properties": {
    "iso:country":"US",
    "sg:address":"112 Parham Rd",
    "sg:city":"Henderson",
    "sg:classifiers":[
        {
            "category":"Travel",
            "subcategory":"Hotels & Motels",
            "type":"Entertainment"
        }
    ],
    "sg:phone":"+1 252 438 8511",
    "sg:postcode":"27536",
    "sg:province":"NC",
    "wof:name":"Comfort Inn",
    "wof:placetype":"venue"
},
  "geometry": {"coordinates":[-78.39129699999999,36.346892],"type":"Point"}
}