{
  "type": "Feature",
  "properties": {
    "addr:full":"4660 Delway Hwy Harrells NC 28444",
    "addr:housenumber":"4660",
    "addr:postcode":"28444",
    "addr:street":"Delway Hwy",
    "iso:country":"US",
    "sg:address":"4660 Delway Hwy",
    "sg:city":"Harrells",
    "sg:classifiers":[
        {
            "category":"Wholesale",
            "subcategory":"Electrical",
            "type":"Manufacturing & Wholesale Goods"
        }
    ],
    "sg:phone":"+1 910 532 4278",
    "sg:postcode":"28444",
    "sg:province":"NC",
    "sg:tags":[
        "alarm",
        "burglar",
        "system"
    ],
    "wof:name":"Electromatic Burglar Alarm",
    "wof:placetype":"venue"
},
  "geometry": {"coordinates":[-78.194169,34.729138],"type":"Point"}
}