{
  "type": "Feature",
  "properties": {
    "iso:country":"US",
    "sg:address":"6833 Greystone Dr",
    "sg:city":"Raleigh",
    "sg:classifiers":[
        {
            "category":"Professional",
            "subcategory":"Business Services",
            "type":"Services"
        }
    ],
    "sg:phone":"+1   ",
    "sg:postcode":"27615",
    "sg:province":"NC",
    "wof:name":"Agency Capital Corp",
    "wof:placetype":"venue"
},
  "geometry": {"coordinates":[-78.610501,35.873353],"type":"Point"}
}