{
  "type": "Feature",
  "properties": {
    "iso:country":"US",
    "sg:address":"101 W 4th St",
    "sg:city":"Winston Salem",
    "sg:classifiers":[
        {
            "category":"Restaurant",
            "type":"Food & Drink"
        }
    ],
    "sg:phone":"+1 336 722 4222",
    "sg:postcode":"27101",
    "sg:province":"NC",
    "wof:name":"Bon Appetit Cafe & Deli",
    "wof:placetype":"venue"
},
  "geometry": {"coordinates":[-80.245744,36.098327],"type":"Point"}
}