{
  "type": "Feature",
  "properties": {
    "iso:country":"US",
    "sg:address":"2612 Dover Rd",
    "sg:city":"Raleigh",
    "sg:classifiers":[
        {
            "category":"Professional",
            "subcategory":"Business Services",
            "type":"Services"
        }
    ],
    "sg:phone":"+1   ",
    "sg:postcode":"27608",
    "sg:province":"NC",
    "wof:name":"Pragmatic Network Solutions",
    "wof:placetype":"venue"
},
  "geometry": {"coordinates":[-78.65743000000001,35.807373],"type":"Point"}
}