{
  "type": "Feature",
  "properties": {
    "addr:full":"1403 S Pollock St Selma NC 27576",
    "addr:housenumber":"1403",
    "addr:postcode":"27576",
    "addr:street":"S Pollock St",
    "iso:country":"US",
    "sg:address":"1403 S Pollock St",
    "sg:city":"Selma",
    "sg:classifiers":[
        {
            "category":"Shopping",
            "subcategory":"Discount & Variety Stores",
            "type":"Retail Goods"
        }
    ],
    "sg:phone":"+1 919 202 8142",
    "sg:postcode":"27576",
    "sg:province":"NC",
    "sg:website":"www.biglots.com",
    "wof:name":"Big Lots",
    "wof:placetype":"venue"
},
  "geometry": {"coordinates":[-78.299538,35.52489],"type":"Point"}
}