{
  "type": "Feature",
  "properties": {
    "addr:full":"101 E Helga St Kill Devil Hills NC 27948",
    "addr:housenumber":"101",
    "addr:postcode":"27948",
    "addr:street":"E Helga St",
    "iso:country":"US",
    "sg:address":"101 E Helga St",
    "sg:city":"Kill Devil Hills",
    "sg:classifiers":[
        {
            "category":"Building & Trades",
            "subcategory":"Cleaning & Sanitation",
            "type":"Services"
        }
    ],
    "sg:phone":"+1 252 441 2427",
    "sg:postcode":"27948",
    "sg:province":"NC",
    "sg:tags":[
        "house"
    ],
    "wof:name":"Maid For You Pro Cleaning Svc",
    "wof:placetype":"venue"
},
  "geometry": {"coordinates":[-75.68315699999999,36.051864],"type":"Point"}
}