{
  "type": "Feature",
  "properties": {
    "iso:country":"US",
    "sg:address":"306 Pleasant Dr",
    "sg:city":"Carrboro",
    "sg:classifiers":[
        {
            "category":"Wholesale",
            "subcategory":"Hardware",
            "type":"Manufacturing & Wholesale Goods"
        }
    ],
    "sg:phone":"+1 919 967 7949",
    "sg:postcode":"27510",
    "sg:province":"NC",
    "sg:tags":[
        "equipment",
        "energy",
        "solar"
    ],
    "wof:name":"Carbora Solar Works",
    "wof:placetype":"venue"
},
  "geometry": {"coordinates":[-79.069594,35.917986],"type":"Point"}
}