{
  "type": "Feature",
  "properties": {
    "iso:country":"US",
    "sg:address":"6603 Sadler Rd",
    "sg:city":"Waxhaw",
    "sg:classifiers":[
        {
            "category":"Manufacturing",
            "subcategory":"Building Materials",
            "type":"Manufacturing & Wholesale Goods"
        }
    ],
    "sg:phone":"+1 704 843 5870",
    "sg:postcode":"28173",
    "sg:province":"NC",
    "sg:tags":[
        "mfg",
        "carpentry",
        "contractor"
    ],
    "wof:name":"Frederick Becker",
    "wof:placetype":"venue"
},
  "geometry": {"coordinates":[-80.69655400000001,34.941338],"type":"Point"}
}