{
  "type": "Feature",
  "properties": {
    "addr:full":"4200 N Rivershore Dr New Bern NC 28560",
    "addr:housenumber":"4200",
    "addr:postcode":"28560",
    "addr:street":"N Rivershore Dr",
    "iso:country":"US",
    "sg:address":"4200 N Rivershore Dr",
    "sg:city":"New Bern",
    "sg:classifiers":[
        {
            "category":"Real Estate",
            "subcategory":"Real Estate Agent",
            "type":"Services"
        }
    ],
    "sg:phone":"+1 252 638 2598",
    "sg:postcode":"28560",
    "sg:province":"NC",
    "sg:tags":[
        "appraiser"
    ],
    "wof:name":"Thomas A Barton Real Estate",
    "wof:placetype":"venue"
},
  "geometry": {"coordinates":[-76.988072,35.036913],"type":"Point"}
}