{
  "type": "Feature",
  "properties": {
    "iso:country":"US",
    "sg:address":"434 Addor Rd",
    "sg:city":"Pinebluff",
    "sg:classifiers":[
        {
            "category":"Personal",
            "type":"Services"
        }
    ],
    "sg:phone":"+1 910 281 4287",
    "sg:postcode":"28373",
    "sg:province":"NC",
    "sg:tags":[
        "wedding",
        "chapel"
    ],
    "wof:name":"Elizabeth Chapel Free Will",
    "wof:placetype":"venue"
},
  "geometry": {"coordinates":[-79.47301,35.08649],"type":"Point"}
}