{
  "type": "Feature",
  "properties": {
    "iso:country":"US",
    "sg:address":"8017 Bald Eagle Ln",
    "sg:city":"Wilmington",
    "sg:classifiers":[
        {
            "category":"Real Estate",
            "subcategory":"Developer",
            "type":"Services"
        }
    ],
    "sg:phone":"+1 910 681 1127",
    "sg:postcode":"28411",
    "sg:province":"NC",
    "wof:name":"Premier Communities",
    "wof:placetype":"venue"
},
  "geometry": {"coordinates":[-77.758349,34.280362],"type":"Point"}
}