{
  "type": "Feature",
  "properties": {
    "addr:full":"872 Inspiration Dr Wilmington NC 28405",
    "addr:housenumber":"872",
    "addr:postcode":"28405",
    "addr:street":"Inspiration Dr",
    "iso:country":"US",
    "sg:address":"872 Inspiration Dr",
    "sg:city":"Wilmington",
    "sg:classifiers":[
        {
            "category":"Food & Beverages",
            "subcategory":"Groceries & Convenience Stores",
            "type":"Retail Goods"
        }
    ],
    "sg:phone":"+1 910 256 0924",
    "sg:postcode":"28405",
    "sg:province":"NC",
    "sg:tags":[
        "market"
    ],
    "wof:name":"White House/Black Market",
    "wof:placetype":"venue"
},
  "geometry": {"coordinates":[-77.830099,34.24284],"type":"Point"}
}