{
  "type": "Feature",
  "properties": {
    "iso:country":"US",
    "sg:address":"223 Williamson Rd",
    "sg:city":"Mooresville",
    "sg:classifiers":[
        {
            "category":"Professional",
            "subcategory":"Lawyer & Legal Services",
            "type":"Services"
        }
    ],
    "sg:phone":"+1 704 662 0903",
    "sg:postcode":"28117",
    "sg:province":"NC",
    "sg:tags":[
        "attorney"
    ],
    "wof:name":"Parker & Howes",
    "wof:placetype":"venue"
},
  "geometry": {"coordinates":[-80.87159699999999,35.591791],"type":"Point"}
}