{
  "type": "Feature",
  "properties": {
    "iso:country":"US",
    "sg:address":"128 James St",
    "sg:city":"Laurinburg",
    "sg:classifiers":[
        {
            "category":"Insurance",
            "subcategory":"Hazard Insurance",
            "type":"Services"
        }
    ],
    "sg:phone":"+1 910 277 0774",
    "sg:postcode":"28352",
    "sg:province":"NC",
    "sg:tags":[
        "bond"
    ],
    "wof:name":"Rainwater Bail Bonds",
    "wof:placetype":"venue"
},
  "geometry": {"coordinates":[-79.458816,34.775191],"type":"Point"}
}