{
  "type": "Feature",
  "properties": {
    "iso:country":"US",
    "sg:address":"9101 Southern Pine Blvd",
    "sg:city":"Charlotte",
    "sg:classifiers":[
        {
            "category":"Professional",
            "type":"Services"
        }
    ],
    "sg:phone":"+1 704 525 0410",
    "sg:postcode":"28273",
    "sg:province":"NC",
    "sg:tags":[
        "establishment"
    ],
    "wof:name":"Adcart",
    "wof:placetype":"venue"
},
  "geometry": {"coordinates":[-80.911734,35.135913],"type":"Point"}
}