{
  "type": "Feature",
  "properties": {
    "iso:country":"US",
    "sg:address":"643 Oak Ave",
    "sg:city":"Spruce Pine",
    "sg:classifiers":[
        {
            "category":"Shopping",
            "subcategory":"Used Merchandise",
            "type":"Retail Goods"
        }
    ],
    "sg:phone":"+1 828 765 2521",
    "sg:postcode":"28777",
    "sg:province":"NC",
    "sg:tags":[
        "antique"
    ],
    "wof:name":"B J's Antiques & Collectibles",
    "wof:placetype":"venue"
},
  "geometry": {"coordinates":[-82.062558,35.915763],"type":"Point"}
}