{
  "type": "Feature",
  "properties": {
    "iso:country":"US",
    "sg:address":"284 E Main St",
    "sg:city":"Sylva",
    "sg:classifiers":[
        {
            "category":"Professional",
            "type":"Services"
        }
    ],
    "sg:phone":"+1 828 586 1586",
    "sg:postcode":"28779",
    "sg:province":"NC",
    "sg:tags":[
        "establishment"
    ],
    "wof:name":"Hannacoles",
    "wof:placetype":"venue"
},
  "geometry": {"coordinates":[-83.206064,35.371647],"type":"Point"}
}