{
  "type": "Feature",
  "properties": {
    "addr:full":"7332 Cobble Creek Dr Matthews NC 28104",
    "addr:housenumber":"7332",
    "addr:postcode":"28104",
    "addr:street":"Cobble Creek Dr",
    "iso:country":"US",
    "sg:address":"7332 Cobble Creek Dr",
    "sg:city":"Matthews",
    "sg:classifiers":[
        {
            "category":"Building & Trades",
            "subcategory":"Landscaping Services",
            "type":"Services"
        }
    ],
    "sg:phone":"+1 704 759 0264",
    "sg:postcode":"28104",
    "sg:province":"NC",
    "wof:name":"Campbells Lawn Service",
    "wof:placetype":"venue"
},
  "geometry": {"coordinates":[-80.70503600000001,35.026811],"type":"Point"}
}