{
  "type": "Feature",
  "properties": {
    "iso:country":"US",
    "sg:address":"209 Century Blvd",
    "sg:city":"Kernersville",
    "sg:classifiers":[
        {
            "category":"Personal",
            "subcategory":"Tanning Parlor",
            "type":"Services"
        },
        {
            "category":"Personal",
            "type":"Services"
        }
    ],
    "sg:phone":"+1 336 993 1490",
    "sg:postcode":"27284",
    "sg:province":"NC",
    "sg:tags":[
        "salon"
    ],
    "wof:name":"Perfect Tan",
    "wof:placetype":"venue"
},
  "geometry": {"coordinates":[-80.093852,36.109393],"type":"Point"}
}