{
  "type": "Feature",
  "properties": {
    "iso:country":"US",
    "sg:address":"212 Arvo Ln",
    "sg:city":"Cary",
    "sg:classifiers":[
        {
            "category":"Professional",
            "subcategory":"Engineering",
            "type":"Services"
        }
    ],
    "sg:phone":"+1   ",
    "sg:postcode":"27513",
    "sg:province":"NC",
    "wof:name":"Civilworks",
    "wof:placetype":"venue"
},
  "geometry": {"coordinates":[-78.823588,35.767043],"type":"Point"}
}