{
  "type": "Feature",
  "properties": {
    "iso:country":"US",
    "sg:address":"4003 Dearborn Pl NW",
    "sg:city":"Concord",
    "sg:classifiers":[
        {
            "category":"Autos & Motor Vehicles",
            "subcategory":"Auto Supplies",
            "type":"Retail Goods"
        }
    ],
    "sg:phone":"+1 704 784 2123",
    "sg:postcode":"28027",
    "sg:province":"NC",
    "sg:tags":[
        "equipment",
        "racing",
        "car",
        "automobile"
    ],
    "wof:name":"Waterman Racing Components",
    "wof:placetype":"venue"
},
  "geometry": {"coordinates":[-80.670284,35.368076],"type":"Point"}
}