{
  "type": "Feature",
  "properties": {
    "addr:full":"4364 S Alston Ave Durham NC 27713",
    "addr:housenumber":"4364",
    "addr:postcode":"27713",
    "addr:street":"S Alston Ave",
    "iso:country":"US",
    "sg:address":"4364 S Alston Ave",
    "sg:city":"Durham",
    "sg:classifiers":[
        {
            "category":"Professional",
            "subcategory":"Research",
            "type":"Services"
        }
    ],
    "sg:phone":"+1 919 361 2286",
    "sg:postcode":"27713",
    "sg:province":"NC",
    "sg:tags":[
        "company",
        "operates",
        "as",
        "through",
        "holding",
        "subsidiary"
    ],
    "wof:name":"Cato Research LTD",
    "wof:placetype":"venue"
},
  "geometry": {"coordinates":[-78.88910300000001,35.9129],"type":"Point"}
}