{
  "type": "Feature",
  "properties": {
    "addr:full":"102 Cherry St Black Mountain NC 28711",
    "addr:housenumber":"102",
    "addr:postcode":"28711",
    "addr:street":"Cherry St",
    "iso:country":"US",
    "sg:address":"102 Cherry St",
    "sg:city":"Black Mountain",
    "sg:classifiers":[
        {
            "category":"Shopping",
            "subcategory":"Clothing, Apparel, & Fashions",
            "type":"Retail Goods"
        }
    ],
    "sg:phone":"+1 828 664 1700",
    "sg:postcode":"28711",
    "sg:province":"NC",
    "wof:name":"Periwinkles On Cherry St",
    "wof:placetype":"venue"
},
  "geometry": {"coordinates":[-82.321061,35.617186],"type":"Point"}
}