{
  "type": "Feature",
  "properties": {
    "iso:country":"US",
    "sg:address":"138 Joye Ln",
    "sg:city":"Belmont",
    "sg:classifiers":[
        {
            "category":"Personal",
            "subcategory":"Beauty Salon",
            "type":"Services"
        }
    ],
    "sg:phone":"+1   ",
    "sg:postcode":"28012",
    "sg:province":"NC",
    "sg:tags":[
        "shop"
    ],
    "wof:name":"J Co",
    "wof:placetype":"venue"
},
  "geometry": {"coordinates":[-81.02223499999999,35.199573],"type":"Point"}
}