{
  "type": "Feature",
  "properties": {
    "iso:country":"US",
    "sg:address":"318 Lake Ridge Dr",
    "sg:city":"Kernersville",
    "sg:classifiers":[
        {
            "category":"Organizations",
            "subcategory":"Community Association",
            "type":"Services"
        }
    ],
    "sg:phone":"+1 336 996 2085",
    "sg:postcode":"27284",
    "sg:province":"NC",
    "wof:name":"Toastmasters Intl Assoc",
    "wof:placetype":"venue"
},
  "geometry": {"coordinates":[-80.08849600000001,36.106277],"type":"Point"}
}