{
  "type": "Feature",
  "properties": {
    "addr:full":"2537 US Hwy 220 Ellerbe NC 28338",
    "addr:housenumber":"2537",
    "addr:postcode":"28338",
    "addr:street":"Us Hwy 220",
    "iso:country":"US",
    "sg:address":"2537 US Hwy 220",
    "sg:city":"Ellerbe",
    "sg:classifiers":[
        {
            "category":"Travel",
            "subcategory":"Hotels & Motels",
            "type":"Entertainment"
        }
    ],
    "sg:phone":"+1 910 652 5600",
    "sg:postcode":"28338",
    "sg:province":"NC",
    "sg:website":"www.ellerbesprings.com",
    "wof:name":"Ellerbe Springs Inn & Restrnt",
    "wof:placetype":"venue"
},
  "geometry": {"coordinates":[-79.75623299999999,35.100993],"type":"Point"}
}