{
  "type": "Feature",
  "properties": {
    "addr:full":"128 Beasley Ln Kill Devil Hills NC 27948",
    "addr:housenumber":"128",
    "addr:postcode":"27948",
    "addr:street":"Beasley Ln",
    "iso:country":"US",
    "sg:address":"128 Beasley Ln",
    "sg:city":"Kill Devil Hills",
    "sg:classifiers":[
        {
            "category":"Building & Trades",
            "subcategory":"Plumbing",
            "type":"Services"
        }
    ],
    "sg:phone":"+1 252 449 2980",
    "sg:postcode":"27948",
    "sg:province":"NC",
    "sg:tags":[
        "conditioning",
        "air",
        "system",
        "contractor"
    ],
    "wof:name":"Airmakers Inc",
    "wof:placetype":"venue"
},
  "geometry": {"coordinates":[-75.695241,36.016363],"type":"Point"}
}