{
  "type": "Feature",
  "properties": {
    "addr:full":"3059 US Hwy 1 Franklinton NC 27525",
    "addr:housenumber":"3059",
    "addr:postcode":"27525",
    "addr:street":"Us Hwy 1",
    "iso:country":"US",
    "sg:address":"3059 US Hwy 1",
    "sg:city":"Franklinton",
    "sg:classifiers":[
        {
            "category":"Retail",
            "subcategory":"Auto Rental",
            "type":"Services"
        }
    ],
    "sg:phone":"+1 919 569 2156",
    "sg:postcode":"27525",
    "sg:province":"NC",
    "sg:tags":[
        "renting",
        "truck",
        "leasing"
    ],
    "wof:name":"U-Haul Co",
    "wof:placetype":"venue"
},
  "geometry": {"coordinates":[-78.474493,36.085587],"type":"Point"}
}