{
  "type": "Feature",
  "properties": {
    "addr:full":"120 Roechling St Dallas NC 28034",
    "addr:housenumber":"120",
    "addr:postcode":"28034",
    "addr:street":"Roechling St",
    "iso:country":"US",
    "sg:address":"120 Roechling St",
    "sg:city":"Dallas",
    "sg:classifiers":[
        {
            "category":"Shopping",
            "type":"Retail Goods"
        }
    ],
    "sg:phone":"+1 704 922 0898",
    "sg:postcode":"28034",
    "sg:province":"NC",
    "sg:tags":[
        "plastic"
    ],
    "wof:name":"Roechling Engineered Plastics",
    "wof:placetype":"venue"
},
  "geometry": {"coordinates":[-81.187168,35.301131],"type":"Point"}
}