{
  "type": "Feature",
  "properties": {
    "addr:full":"4701 Atlantic Ave Raleigh NC 27604",
    "addr:housenumber":"4701",
    "addr:postcode":"27604",
    "addr:street":"Atlantic Ave",
    "iso:country":"US",
    "sg:address":"4701 Atlantic Ave",
    "sg:city":"Raleigh",
    "sg:classifiers":[
        {
            "category":"Food & Beverages",
            "subcategory":"Supermarket",
            "type":"Retail Goods"
        },
        {
            "category":"Shopping",
            "subcategory":"Pharmacy",
            "type":"Retail Goods"
        }
    ],
    "sg:postcode":"27604",
    "sg:province":"NC",
    "sg:tags":[
        "super",
        "store"
    ],
    "sg:website":"http://www.kroger.com",
    "wof:name":"Kroger Food Stores",
    "wof:placetype":"venue"
},
  "geometry": {"coordinates":[-78.60176800000001,35.847402],"type":"Point"}
}