{
  "type": "Feature",
  "properties": {
    "iso:country":"US",
    "sg:address":"3372 Robinwood Rd",
    "sg:city":"Gastonia",
    "sg:classifiers":[
        {
            "category":"Sports & Exercise",
            "subcategory":"Gym",
            "type":"Entertainment"
        }
    ],
    "sg:phone":"+1 704 867 8900",
    "sg:postcode":"28054",
    "sg:province":"NC",
    "sg:tags":[
        "club",
        "health",
        "studio",
        "gymnasium"
    ],
    "wof:name":"Armstrong Athletic Club",
    "wof:placetype":"venue"
},
  "geometry": {"coordinates":[-81.159819,35.216127],"type":"Point"}
}