{
  "type": "Feature",
  "properties": {
    "iso:country":"US",
    "sg:address":"2841 Lowery St",
    "sg:city":"Winston Salem",
    "sg:classifiers":[
        {
            "category":"Home & Garden",
            "subcategory":"Building Materials",
            "type":"Retail Goods"
        }
    ],
    "sg:phone":"+1 336 777 3640",
    "sg:postcode":"27101",
    "sg:province":"NC",
    "sg:tags":[
        "windows"
    ],
    "wof:name":"Salem Millwork",
    "wof:placetype":"venue"
},
  "geometry": {"coordinates":[-80.199174,36.097198],"type":"Point"}
}