{
  "type": "Feature",
  "properties": {
    "addr:full":"351 S College Rd Wilmington NC 28403",
    "addr:housenumber":"351",
    "addr:postcode":"28403",
    "addr:street":"S College Rd",
    "iso:country":"US",
    "sg:address":"351 S College Rd",
    "sg:city":"Wilmington",
    "sg:classifiers":[
        {
            "category":"Shopping",
            "subcategory":"Clothing, Apparel, & Fashions",
            "type":"Retail Goods"
        }
    ],
    "sg:phone":"+1 910 452 9779",
    "sg:postcode":"28403",
    "sg:province":"NC",
    "sg:tags":[
        "uniform"
    ],
    "wof:name":"First Medical Uniform Inc",
    "wof:placetype":"venue"
},
  "geometry": {"coordinates":[-77.874685,34.233544],"type":"Point"}
}