{
  "type": "Feature",
  "properties": {
    "addr:full":"1294 Paynes Tavern Rd Roxboro NC 27574",
    "addr:housenumber":"1294",
    "addr:postcode":"27574",
    "addr:street":"Paynes Tavern Rd",
    "iso:country":"US",
    "sg:address":"1294 Paynes Tavern Rd",
    "sg:city":"Roxboro",
    "sg:classifiers":[
        {
            "category":"Retail",
            "subcategory":"Repair Shop",
            "type":"Services"
        }
    ],
    "sg:phone":"+1   ",
    "sg:postcode":"27574",
    "sg:province":"NC",
    "sg:tags":[
        "welding"
    ],
    "wof:name":"CN Welding Service",
    "wof:placetype":"venue"
},
  "geometry": {"coordinates":[-79.033089,36.339172],"type":"Point"}
}