{
  "type": "Feature",
  "properties": {
    "iso:country":"US",
    "sg:address":"364 Williamson Rd",
    "sg:city":"Mooresville",
    "sg:classifiers":[
        {
            "category":"Professional",
            "type":"Services"
        },
        {
            "category":"Shopping",
            "type":"Retail Goods"
        }
    ],
    "sg:phone":"+1 704 658 0703",
    "sg:postcode":"28117",
    "sg:province":"NC",
    "sg:tags":[
        "cards",
        "sport",
        "baseball",
        "memorabilia"
    ],
    "wof:name":"Hirev LLC",
    "wof:placetype":"venue"
},
  "geometry": {"coordinates":[-80.873339,35.582129],"type":"Point"}
}