{
  "type": "Feature",
  "properties": {
    "addr:full":"1870 Pisgah Dr Hendersonville NC 28791",
    "addr:postcode":"1870;28791",
    "addr:street":"Pisgah Dr",
    "iso:country":"US",
    "sg:address":"1870 Pisgah Dr",
    "sg:city":"Hendersonville",
    "sg:classifiers":[
        {
            "category":"Social Services",
            "subcategory":"Job Training",
            "type":"Services"
        },
        {
            "category":"Social Services",
            "subcategory":"Retirement Home",
            "type":"Services"
        },
        {
            "category":"Health Services",
            "subcategory":"Clinic",
            "type":"Services"
        }
    ],
    "sg:phone":"+1 828 693 9796",
    "sg:postcode":"28791",
    "sg:province":"NC",
    "sg:tags":[
        "rehabilitation",
        "convalescent",
        "nursing",
        "homes-skilled",
        "facility"
    ],
    "wof:name":"Brian Center Health And Rehab Hendersonville",
    "wof:placetype":"venue"
},
  "geometry": {"coordinates":[-82.492976,35.323978],"type":"Point"}
}