{
  "type": "Feature",
  "properties": {
    "iso:country":"US",
    "sg:address":"14314 State Hwy 86",
    "sg:city":"Prospect Hill",
    "sg:classifiers":[
        {
            "category":"Shopping",
            "subcategory":"Bicycles & Sporting Goods",
            "type":"Retail Goods"
        }
    ],
    "sg:phone":"+1 336 562 5131",
    "sg:postcode":"27314",
    "sg:province":"NC",
    "wof:name":"Carolina Country Kennels",
    "wof:placetype":"venue"
},
  "geometry": {"coordinates":[-79.19305799999999,36.256198],"type":"Point"}
}