{
  "type": "Feature",
  "properties": {
    "addr:full":"5841 Brookway Dr Winston Salem NC 27105",
    "addr:housenumber":"5841",
    "addr:postcode":"27105",
    "addr:street":"Brookway Dr",
    "iso:country":"US",
    "sg:address":"5841 Brookway Dr",
    "sg:city":"Winston Salem",
    "sg:classifiers":[
        {
            "category":"Freight",
            "type":"Transportation"
        }
    ],
    "sg:phone":"+1 336 744 3333",
    "sg:postcode":"27105",
    "sg:province":"NC",
    "sg:tags":[
        "operator",
        "local",
        "trucking"
    ],
    "wof:name":"Trans Service Trucking Inc",
    "wof:placetype":"venue"
},
  "geometry": {"coordinates":[-80.248471,36.183975],"type":"Point"}
}