{
  "type": "Feature",
  "properties": {
    "addr:full":"1342 Barnardsville Hwy Barnardsville NC 28709",
    "addr:housenumber":"1342",
    "addr:postcode":"28709",
    "addr:street":"Barnardsville Hwy",
    "iso:country":"US",
    "sg:address":"1342 Barnardsville Hwy",
    "sg:city":"Barnardsville",
    "sg:classifiers":[
        {
            "category":"Building & Trades",
            "subcategory":"Electrical",
            "type":"Services"
        }
    ],
    "sg:phone":"+1 828 626 4382",
    "sg:postcode":"28709",
    "sg:province":"NC",
    "sg:tags":[
        "electric",
        "contractor"
    ],
    "wof:name":"Burleson Electrical Corp",
    "wof:placetype":"venue"
},
  "geometry": {"coordinates":[-82.48683200000001,35.784042],"type":"Point"}
}