{
  "type": "Feature",
  "properties": {
    "iso:country":"US",
    "sg:address":"232 Terrastone Pl",
    "sg:city":"Cary",
    "sg:classifiers":[
        {
            "category":"Professional",
            "type":"Services"
        }
    ],
    "sg:phone":"+1   ",
    "sg:postcode":"27519",
    "sg:province":"NC",
    "wof:name":"Marcor Services",
    "wof:placetype":"venue"
},
  "geometry": {"coordinates":[-78.855695,35.788655],"type":"Point"}
}