{
  "type": "Feature",
  "properties": {
    "addr:full":"2941 Welcome Dr Durham NC 27705",
    "addr:housenumber":"2941",
    "addr:postcode":"27705",
    "addr:street":"Welcome Dr",
    "iso:country":"US",
    "sg:address":"2941 Welcome Dr",
    "sg:city":"Durham",
    "sg:classifiers":[
        {
            "category":"Professional",
            "subcategory":"Management & Consulting",
            "type":"Services"
        }
    ],
    "sg:phone":"+1   ",
    "sg:postcode":"27705",
    "sg:province":"NC",
    "sg:tags":[
        "business"
    ],
    "wof:name":"Gwp Assoc",
    "wof:placetype":"venue"
},
  "geometry": {"coordinates":[-78.96531299999999,35.984545],"type":"Point"}
}