{
  "type": "Feature",
  "properties": {
    "iso:country":"US",
    "sg:address":"18639 Harborside Dr",
    "sg:city":"Cornelius",
    "sg:classifiers":[
        {
            "category":"Professional",
            "subcategory":"Management & Consulting",
            "type":"Services"
        }
    ],
    "sg:phone":"+1   ",
    "sg:postcode":"28031",
    "sg:province":"NC",
    "sg:tags":[
        "consultant"
    ],
    "wof:name":"David Yountz Jr",
    "wof:placetype":"venue"
},
  "geometry": {"coordinates":[-80.89255,35.464782],"type":"Point"}
}