{
  "type": "Feature",
  "properties": {
    "iso:country":"US",
    "sg:address":"216 S New Hope Rd",
    "sg:city":"Gastonia",
    "sg:classifiers":[
        {
            "category":"Personal",
            "subcategory":"Beauty Salon",
            "type":"Services"
        }
    ],
    "sg:phone":"+1 704 853 3005",
    "sg:postcode":"28054",
    "sg:province":"NC",
    "sg:tags":[
        "spa",
        "day"
    ],
    "wof:name":"Belle Vou's",
    "wof:placetype":"venue"
},
  "geometry": {"coordinates":[-81.150436,35.258502],"type":"Point"}
}