{
  "type": "Feature",
  "properties": {
    "iso:country":"US",
    "sg:address":"1013 Erins Way Ln",
    "sg:city":"Raleigh",
    "sg:classifiers":[
        {
            "category":"Professional",
            "subcategory":"Management & Consulting",
            "type":"Services"
        }
    ],
    "sg:phone":"+1   ",
    "sg:postcode":"27614",
    "sg:province":"NC",
    "sg:tags":[
        "business"
    ],
    "wof:name":"Cantando & Associates LLC",
    "wof:placetype":"venue"
},
  "geometry": {"coordinates":[-78.62978699999999,35.959327],"type":"Point"}
}