{
  "type": "Feature",
  "properties": {
    "iso:country":"US",
    "sg:address":"4020 Wiggins Mill Rd",
    "sg:city":"Wilson",
    "sg:classifiers":[
        {
            "category":"Building & Trades",
            "subcategory":"Plumbing",
            "type":"Services"
        }
    ],
    "sg:phone":"+1 252 237 6340",
    "sg:postcode":"27893",
    "sg:province":"NC",
    "sg:tags":[
        "air",
        "heating",
        "contractor",
        "system",
        "conditioning"
    ],
    "wof:name":"Lucas Heating Air & Electrical",
    "wof:placetype":"venue"
},
  "geometry": {"coordinates":[-77.962626,35.688104],"type":"Point"}
}