{
  "type": "Feature",
  "properties": {
    "addr:full":"710 Curtis St Monroe NC 28112",
    "addr:housenumber":"710",
    "addr:postcode":"28112",
    "addr:street":"Curtis St",
    "iso:country":"US",
    "sg:address":"710 Curtis St",
    "sg:city":"Monroe",
    "sg:classifiers":[
        {
            "category":"Retail",
            "subcategory":"Repair Shop",
            "type":"Services"
        }
    ],
    "sg:phone":"+1   ",
    "sg:postcode":"28112",
    "sg:province":"NC",
    "sg:tags":[
        "electrical"
    ],
    "wof:name":"Rocks Appliances",
    "wof:placetype":"venue"
},
  "geometry": {"coordinates":[-80.537756,34.980589],"type":"Point"}
}