{
  "type": "Feature",
  "properties": {
    "addr:full":"117 Landfall Ct Roanoke Rapids NC 27870",
    "addr:housenumber":"117",
    "addr:postcode":"27870",
    "addr:street":"Landfall Ct",
    "iso:country":"US",
    "sg:address":"117 Landfall Ct",
    "sg:city":"Roanoke Rapids",
    "sg:classifiers":[
        {
            "category":"Professional",
            "subcategory":"Management & Consulting",
            "type":"Services"
        }
    ],
    "sg:phone":"+1 252 535 5632",
    "sg:postcode":"27870",
    "sg:province":"NC",
    "wof:name":"Dodway Enterprises LLC",
    "wof:placetype":"venue"
},
  "geometry": {"coordinates":[-77.686128,36.472342],"type":"Point"}
}