{
  "type": "Feature",
  "properties": {
    "addr:full":"212 N Dyson St Holly Ridge NC 28445",
    "addr:housenumber":"212",
    "addr:postcode":"28445",
    "addr:street":"N Dyson St",
    "iso:country":"US",
    "sg:address":"212 N Dyson St",
    "sg:city":"Holly Ridge",
    "sg:classifiers":[
        {
            "category":"Government",
            "subcategory":"Office",
            "type":"Public Place"
        }
    ],
    "sg:phone":"+1 910 329 7081",
    "sg:postcode":"28445",
    "sg:province":"NC",
    "sg:tags":[
        "village"
    ],
    "wof:name":"Holly Ridge Clerk",
    "wof:placetype":"venue"
},
  "geometry": {"coordinates":[-77.550687,34.49538],"type":"Point"}
}