{
  "type": "Feature",
  "properties": {
    "iso:country":"US",
    "sg:address":"352 S College Rd",
    "sg:city":"Wilmington",
    "sg:classifiers":[
        {
            "category":"Shopping",
            "subcategory":"Clothing, Apparel, & Fashions",
            "type":"Retail Goods"
        }
    ],
    "sg:phone":"+1 910 792 6588",
    "sg:postcode":"28403",
    "sg:province":"NC",
    "sg:website":"www.rue21.com",
    "wof:name":"Rue 21",
    "wof:placetype":"venue"
},
  "geometry": {"coordinates":[-77.873362,34.235896],"type":"Point"}
}