{
  "type": "Feature",
  "properties": {
    "iso:country":"US",
    "sg:address":"13401 Lancaster Hwy",
    "sg:city":"Pineville",
    "sg:classifiers":[
        {
            "category":"Building & Trades",
            "subcategory":"Construction",
            "type":"Services"
        }
    ],
    "sg:phone":"+1 704 527 0355",
    "sg:postcode":"28134",
    "sg:province":"NC",
    "sg:tags":[
        "designer",
        "dealer",
        "pool",
        "swimming"
    ],
    "wof:name":"Integrity Pools LTD",
    "wof:placetype":"venue"
},
  "geometry": {"coordinates":[-80.876538,35.060016],"type":"Point"}
}