{
  "type": "Feature",
  "properties": {
    "addr:full":"4305 Fringewood Dr Concord NC 28025",
    "addr:housenumber":"4305",
    "addr:postcode":"28025",
    "addr:street":"Fringewood Dr",
    "iso:country":"US",
    "sg:address":"4305 Fringewood Dr",
    "sg:city":"Concord",
    "sg:classifiers":[
        {
            "category":"Building & Trades",
            "subcategory":"Construction",
            "type":"Services"
        }
    ],
    "sg:phone":"+1 704 788 3099",
    "sg:postcode":"28025",
    "sg:province":"NC",
    "sg:tags":[
        "house"
    ],
    "wof:name":"Maxwell Home Services",
    "wof:placetype":"venue"
},
  "geometry": {"coordinates":[-80.50743300000001,35.440726],"type":"Point"}
}