{
  "type": "Feature",
  "properties": {
    "addr:full":"6989 State Hwy 210 Smithfield NC 27577",
    "addr:housenumber":"6989",
    "addr:postcode":"27577",
    "addr:street":"State Hwy 210",
    "iso:country":"US",
    "sg:address":"6989 State Hwy 210",
    "sg:city":"Smithfield",
    "sg:classifiers":[
        {
            "category":"Organizations",
            "subcategory":"Religious Organization",
            "type":"Services"
        }
    ],
    "sg:phone":"+1   ",
    "sg:postcode":"27577",
    "sg:province":"NC",
    "wof:name":"Sanders Grove Baptist Churc H",
    "wof:placetype":"venue"
},
  "geometry": {"coordinates":[-78.46973300000001,35.507591],"type":"Point"}
}