{
  "type": "Feature",
  "properties": {
    "addr:full":"107 Muirs Chapel Rd Greensboro NC 27410",
    "addr:housenumber":"107",
    "addr:postcode":"27410",
    "addr:street":"Muirs Chapel Rd",
    "iso:country":"US",
    "sg:address":"107 Muirs Chapel Rd",
    "sg:city":"Greensboro",
    "sg:classifiers":[
        {
            "category":"Banks & Credit Unions",
            "subcategory":"Bank",
            "type":"Services"
        }
    ],
    "sg:phone":"+1 336 805 3113",
    "sg:postcode":"27410",
    "sg:province":"NC",
    "wof:name":"Bank Of America",
    "wof:placetype":"venue"
},
  "geometry": {"coordinates":[-79.86922,36.070555],"type":"Point"}
}