{
  "type": "Feature",
  "properties": {
    "iso:country":"US",
    "sg:address":"14219 Boatway Ct",
    "sg:city":"Huntersville",
    "sg:classifiers":[
        {
            "category":"Building & Trades",
            "subcategory":"Construction",
            "type":"Services"
        }
    ],
    "sg:phone":"+1 704 947 7747",
    "sg:postcode":"28078",
    "sg:province":"NC",
    "sg:tags":[
        "home",
        "improvement"
    ],
    "wof:name":"Carolina Deck Pros",
    "wof:placetype":"venue"
},
  "geometry": {"coordinates":[-80.92927899999999,35.428915],"type":"Point"}
}