{
  "type": "Feature",
  "properties": {
    "iso:country":"US",
    "sg:address":"117 W Railroad St",
    "sg:city":"Marion",
    "sg:classifiers":[
        {
            "category":"Shopping",
            "subcategory":"Music",
            "type":"Retail Goods"
        }
    ],
    "sg:phone":"+1 828 652 3600",
    "sg:postcode":"28752",
    "sg:province":"NC",
    "sg:tags":[
        "compact",
        "record",
        "disc",
        "tape"
    ],
    "wof:name":"H R Junkinstuff Records & Cd's",
    "wof:placetype":"venue"
},
  "geometry": {"coordinates":[-82.009687,35.681357],"type":"Point"}
}