{
  "type": "Feature",
  "properties": {
    "iso:country":"US",
    "sg:address":"3030 W Cornwallis Rd",
    "sg:city":"Durham",
    "sg:classifiers":[
        {
            "category":"Shopping",
            "subcategory":"Pharmacy",
            "type":"Retail Goods"
        }
    ],
    "sg:phone":"+1 919 483 2100",
    "sg:postcode":"27705",
    "sg:province":"NC",
    "wof:name":"Glaxosmithkline (nc)",
    "wof:placetype":"venue"
},
  "geometry": {"coordinates":[-78.972894,35.993309],"type":"Point"}
}