{
  "type": "Feature",
  "properties": {
    "iso:country":"US",
    "sg:address":"314 Huffman Mill Rd",
    "sg:city":"Burlington",
    "sg:classifiers":[
        {
            "category":"Personal",
            "subcategory":"Beauty Salon",
            "type":"Services"
        }
    ],
    "sg:phone":"+1 336 584 4282",
    "sg:postcode":"27215",
    "sg:province":"NC",
    "sg:tags":[
        "manicuring"
    ],
    "wof:name":"L D Nails Supply",
    "wof:placetype":"venue"
},
  "geometry": {"coordinates":[-79.486557,36.07747],"type":"Point"}
}