{
  "type": "Feature",
  "properties": {
    "iso:country":"US",
    "sg:address":"210 Harold Hart Rd",
    "sg:city":"Siler City",
    "sg:classifiers":[
        {
            "category":"Social Services",
            "type":"Services"
        }
    ],
    "sg:phone":"+1   ",
    "sg:postcode":"27344",
    "sg:province":"NC",
    "wof:name":"Birth Choice of Chatham",
    "wof:placetype":"venue"
},
  "geometry": {"coordinates":[-79.379834,35.734258],"type":"Point"}
}