{
  "type": "Feature",
  "properties": {
    "addr:full":"902 W Union St Morganton NC 28655",
    "addr:housenumber":"902",
    "addr:postcode":"28655",
    "addr:street":"W Union St",
    "iso:country":"US",
    "sg:address":"902 W Union St",
    "sg:city":"Morganton",
    "sg:classifiers":[
        {
            "category":"Restaurant",
            "type":"Food & Drink"
        }
    ],
    "sg:phone":"+1 828 433 7855",
    "sg:postcode":"28655",
    "sg:province":"NC",
    "sg:tags":[
        "shop",
        "coffee"
    ],
    "wof:name":"Pedalers Coffee",
    "wof:placetype":"venue"
},
  "geometry": {"coordinates":[-81.709844,35.735486],"type":"Point"}
}