{
  "type": "Feature",
  "properties": {
    "addr:full":"339 Gashes Creek Rd Asheville NC 28803",
    "addr:housenumber":"339",
    "addr:postcode":"28803",
    "addr:street":"Gashes Creek Rd",
    "iso:country":"US",
    "sg:address":"339 Gashes Creek Rd",
    "sg:city":"Asheville",
    "sg:classifiers":[
        {
            "category":"Wholesale",
            "subcategory":"Construction Materials",
            "type":"Manufacturing & Wholesale Goods"
        }
    ],
    "sg:phone":"+1 828 296 1134",
    "sg:postcode":"28803",
    "sg:province":"NC",
    "sg:tags":[
        "pallet",
        "skid"
    ],
    "wof:name":"Smokey Mountain Pallets",
    "wof:placetype":"venue"
},
  "geometry": {"coordinates":[-82.493494,35.565411],"type":"Point"}
}