{
  "type": "Feature",
  "properties": {
    "addr:full":"6033 Yadkin Rd Fayetteville NC 28303",
    "addr:housenumber":"6033",
    "addr:postcode":"28303",
    "addr:street":"Yadkin Rd",
    "iso:country":"US",
    "sg:address":"6033 Yadkin Rd",
    "sg:city":"Fayetteville",
    "sg:classifiers":[
        {
            "category":"Bars & Pubs",
            "type":"Food & Drink"
        }
    ],
    "sg:phone":"+1 910 864 5111",
    "sg:postcode":"28303",
    "sg:province":"NC",
    "wof:name":"Dakota's Tavern",
    "wof:placetype":"venue"
},
  "geometry": {"coordinates":[-78.98832899999999,35.096721],"type":"Point"}
}