{
  "type": "Feature",
  "properties": {
    "iso:country":"US",
    "sg:address":"6225 Old Concord Rd",
    "sg:city":"Charlotte",
    "sg:classifiers":[
        {
            "category":"Manufacturing",
            "subcategory":"Signs",
            "type":"Manufacturing & Wholesale Goods"
        }
    ],
    "sg:phone":"+1 704 597 9801",
    "sg:postcode":"28213",
    "sg:province":"NC",
    "sg:website":"www.signartsign.com",
    "wof:name":"Signart",
    "wof:placetype":"venue"
},
  "geometry": {"coordinates":[-80.76192,35.263217],"type":"Point"}
}