{
  "type": "Feature",
  "properties": {
    "iso:country":"US",
    "sg:address":"9615 E Independence Blvd",
    "sg:city":"Matthews",
    "sg:classifiers":[
        {
            "category":"Travel",
            "subcategory":"Hotels & Motels",
            "type":"Entertainment"
        }
    ],
    "sg:phone":"+1 704 841 1155",
    "sg:postcode":"28105",
    "sg:province":"NC",
    "sg:tags":[
        "operation"
    ],
    "wof:name":"Hampton Inn",
    "wof:placetype":"venue"
},
  "geometry": {"coordinates":[-80.714651,35.136238],"type":"Point"}
}