{
  "type": "Feature",
  "properties": {
    "addr:full":"3971 Heath Dairy Rd Randleman NC 27317",
    "addr:housenumber":"3971",
    "addr:postcode":"27317",
    "addr:street":"Heath Dairy Rd",
    "iso:country":"US",
    "sg:address":"3971 Heath Dairy Rd",
    "sg:city":"Randleman",
    "sg:classifiers":[
        {
            "category":"Recreation",
            "type":"Entertainment"
        }
    ],
    "sg:phone":"+1 336 498 7926",
    "sg:postcode":"27317",
    "sg:province":"NC",
    "sg:tags":[
        "amusement"
    ],
    "wof:name":"Ryan Wilson Motorsports",
    "wof:placetype":"venue"
},
  "geometry": {"coordinates":[-79.83806,35.794305],"type":"Point"}
}