{
  "type": "Feature",
  "properties": {
    "addr:full":"2205 Roxie St Kannapolis NC 28083",
    "addr:housenumber":"2205",
    "addr:postcode":"28083",
    "addr:street":"Roxie St",
    "iso:country":"US",
    "sg:address":"2205 Roxie St",
    "sg:city":"Kannapolis",
    "sg:classifiers":[
        {
            "category":"Retail",
            "subcategory":"Auto Repair",
            "type":"Services"
        }
    ],
    "sg:phone":"+1 704 788 4645",
    "sg:postcode":"28083",
    "sg:province":"NC",
    "sg:tags":[
        "automobile",
        "lubrication"
    ],
    "wof:name":"Ernie Irvans Texaco Xpress Lb",
    "wof:placetype":"venue"
},
  "geometry": {"coordinates":[-80.59246899999999,35.464825],"type":"Point"}
}