{
  "type": "Feature",
  "properties": {
    "iso:country":"US",
    "sg:address":"4829 Blue Clay Rd",
    "sg:city":"Castle Hayne",
    "sg:classifiers":[
        {
            "category":"Farming",
            "subcategory":"Nursery",
            "type":"Manufacturing & Wholesale Goods"
        }
    ],
    "sg:phone":"+1 910 675 2533",
    "sg:postcode":"28429",
    "sg:province":"NC",
    "sg:tags":[
        "greenhouse"
    ],
    "wof:name":"Brookdale Greenhouse's",
    "wof:placetype":"venue"
},
  "geometry": {"coordinates":[-77.876712,34.333031],"type":"Point"}
}