{
  "type": "Feature",
  "properties": {
    "addr:full":"20005 State Hwy 73 Cornelius NC 28001",
    "addr:housenumber":"20005",
    "addr:postcode":"28001",
    "addr:street":"State Hwy 73",
    "iso:country":"US",
    "sg:address":"20005 State Hwy 73",
    "sg:city":"Cornelius",
    "sg:classifiers":[
        {
            "category":"Banks & Credit Unions",
            "subcategory":"Bank",
            "type":"Services"
        }
    ],
    "sg:phone":"+1 704 896 0100",
    "sg:postcode":"28001",
    "sg:province":"NC",
    "wof:name":"Bank Of America",
    "wof:placetype":"venue"
},
  "geometry": {"coordinates":[-80.34036399999999,35.38336],"type":"Point"}
}