{
  "type": "Feature",
  "properties": {
    "addr:full":"714 Granville St Oxford NC 27565",
    "addr:housenumber":"714",
    "addr:postcode":"27565",
    "addr:street":"Granville St",
    "iso:country":"US",
    "sg:address":"714 Granville St",
    "sg:city":"Oxford",
    "sg:classifiers":[
        {
            "category":"Restaurant",
            "type":"Food & Drink"
        }
    ],
    "sg:menulink":"http://www.allmenus.com/nc/fishing-creek/137528-subway/menu/",
    "sg:phone":"+1 919 692 0222",
    "sg:postcode":"27565",
    "sg:province":"NC",
    "sg:tags":[
        "american",
        "sandwich"
    ],
    "wof:name":"Subway",
    "wof:placetype":"venue"
},
  "geometry": {"coordinates":[-78.584734,36.300042],"type":"Point"}
}