{
  "type": "Feature",
  "properties": {
    "iso:country":"US",
    "sg:address":"36 Green St SW",
    "sg:city":"Concord",
    "sg:classifiers":[
        {
            "category":"Government",
            "subcategory":"Fire Station",
            "type":"Public Place"
        },
        {
            "category":"Government",
            "subcategory":"Office",
            "type":"Public Place"
        }
    ],
    "sg:phone":"+1 704 786 7811",
    "sg:postcode":"28027",
    "sg:province":"NC",
    "sg:tags":[
        "department",
        "township",
        "protection",
        "government-city",
        "village"
    ],
    "wof:name":"Jackson Park Volunteer Fire Department",
    "wof:placetype":"venue"
},
  "geometry": {"coordinates":[-80.59951,35.372009],"type":"Point"}
}