{
  "type": "Feature",
  "properties": {
    "iso:country":"US",
    "sg:address":"121 Hewes St",
    "sg:city":"Winston Salem",
    "sg:classifiers":[
        {
            "category":"Retail",
            "subcategory":"Repair Shop",
            "type":"Services"
        }
    ],
    "sg:phone":"+1   ",
    "sg:postcode":"27103",
    "sg:province":"NC",
    "wof:name":"Smithdeal Taxidermy",
    "wof:placetype":"venue"
},
  "geometry": {"coordinates":[-80.31967400000001,36.054294],"type":"Point"}
}