{
  "type": "Feature",
  "properties": {
    "addr:full":"68 Orange St Asheville NC 28801",
    "addr:housenumber":"68",
    "addr:postcode":"28801",
    "addr:street":"Orange St",
    "iso:country":"US",
    "sg:address":"68 Orange St",
    "sg:city":"Asheville",
    "sg:classifiers":[
        {
            "category":"Professional",
            "subcategory":"Business Services",
            "type":"Services"
        }
    ],
    "sg:phone":"+1 828 253 9976",
    "sg:postcode":"28801",
    "sg:province":"NC",
    "sg:tags":[
        "interior",
        "consultant",
        "design",
        "decorator"
    ],
    "wof:name":"Grace Unruh Interior Design",
    "wof:placetype":"venue"
},
  "geometry": {"coordinates":[-82.55130800000001,35.60153],"type":"Point"}
}