{
  "type": "Feature",
  "properties": {
    "iso:country":"US",
    "sg:address":"213 Scottsdale Dr",
    "sg:city":"Wilmington",
    "sg:classifiers":[
        {
            "category":"Professional",
            "subcategory":"Management & Consulting",
            "type":"Services"
        }
    ],
    "sg:phone":"+1   ",
    "sg:postcode":"28411",
    "sg:province":"NC",
    "sg:tags":[
        "business"
    ],
    "wof:name":"Sandi M Consulting LLC",
    "wof:placetype":"venue"
},
  "geometry": {"coordinates":[-77.741918,34.30817],"type":"Point"}
}