{
  "type": "Feature",
  "properties": {
    "iso:country":"US",
    "sg:address":"211 Hull Rd",
    "sg:city":"Fayetteville",
    "sg:classifiers":[
        {
            "category":"Education",
            "subcategory":"Special Training",
            "type":"Public Place"
        }
    ],
    "sg:phone":"+1   ",
    "sg:postcode":"28303",
    "sg:province":"NC",
    "wof:name":"Craver Music Studio",
    "wof:placetype":"venue"
},
  "geometry": {"coordinates":[-78.920377,35.064383],"type":"Point"}
}