{
  "type": "Feature",
  "properties": {
    "addr:full":"301 N Polk St Pineville NC 28134",
    "addr:housenumber":"301",
    "addr:postcode":"28134",
    "addr:street":"N Polk St",
    "iso:country":"US",
    "sg:address":"301 N Polk St",
    "sg:city":"Pineville",
    "sg:classifiers":[
        {
            "category":"Retail",
            "subcategory":"Auto Rental",
            "type":"Services"
        }
    ],
    "sg:phone":"+1   ",
    "sg:postcode":"28134",
    "sg:province":"NC",
    "sg:tags":[
        "trailer",
        "utility"
    ],
    "wof:name":"U-Haul",
    "wof:placetype":"venue"
},
  "geometry": {"coordinates":[-80.88678,35.08754],"type":"Point"}
}