{
  "type": "Feature",
  "properties": {
    "addr:full":"106 Gilmer St Reidsville NC 27320",
    "addr:housenumber":"106",
    "addr:postcode":"27320",
    "addr:street":"Gilmer St",
    "iso:country":"US",
    "sg:address":"106 Gilmer St",
    "sg:city":"Reidsville",
    "sg:classifiers":[
        {
            "category":"Organizations",
            "subcategory":"Religious Organization",
            "type":"Services"
        }
    ],
    "sg:phone":"+1   ",
    "sg:postcode":"27320",
    "sg:province":"NC",
    "wof:name":"Right Choice Ministries",
    "wof:placetype":"venue"
},
  "geometry": {"coordinates":[-79.662982,36.360355],"type":"Point"}
}