{
  "type": "Feature",
  "properties": {
    "addr:full":"224 Eastmoor Dr Asheville NC 28805",
    "addr:housenumber":"224",
    "addr:postcode":"28805",
    "addr:street":"Eastmoor Dr",
    "iso:country":"US",
    "sg:address":"224 Eastmoor Dr",
    "sg:city":"Asheville",
    "sg:classifiers":[
        {
            "category":"Education",
            "subcategory":"Special Training",
            "type":"Public Place"
        }
    ],
    "sg:phone":"+1   ",
    "sg:postcode":"28805",
    "sg:province":"NC",
    "wof:name":"Ashville Choral Society",
    "wof:placetype":"venue"
},
  "geometry": {"coordinates":[-82.45566100000001,35.595652],"type":"Point"}
}