{
  "type": "Feature",
  "properties": {
    "iso:country":"US",
    "sg:address":"700 Bristol Blue St",
    "sg:city":"Apex",
    "sg:classifiers":[
        {
            "category":"Building & Trades",
            "subcategory":"Construction",
            "type":"Services"
        }
    ],
    "sg:phone":"+1 919 362 5985",
    "sg:postcode":"27502",
    "sg:province":"NC",
    "sg:tags":[
        "house"
    ],
    "wof:name":"Nisco Construction Inc",
    "wof:placetype":"venue"
},
  "geometry": {"coordinates":[-78.86437599999999,35.733418],"type":"Point"}
}