{
  "type": "Feature",
  "properties": {
    "addr:full":"630 Lillington Hwy Spring Lake NC 28390",
    "addr:housenumber":"630",
    "addr:postcode":"28390",
    "addr:street":"Lillington Hwy",
    "iso:country":"US",
    "sg:address":"630 Lillington Hwy",
    "sg:city":"Spring Lake",
    "sg:classifiers":[
        {
            "category":"Restaurant",
            "type":"Food & Drink"
        }
    ],
    "sg:phone":"+1 910 497 8884",
    "sg:postcode":"28390",
    "sg:province":"NC",
    "sg:tags":[
        "eating"
    ],
    "wof:name":"Peking Wok",
    "wof:placetype":"venue"
},
  "geometry": {"coordinates":[-78.969696,35.173582],"type":"Point"}
}