{
  "type": "Feature",
  "properties": {
    "addr:full":"279 Ashbrook Rd Statesville NC 28677",
    "addr:housenumber":"279",
    "addr:postcode":"28677",
    "addr:street":"Ashbrook Rd",
    "iso:country":"US",
    "sg:address":"279 Ashbrook Rd",
    "sg:city":"Statesville",
    "sg:classifiers":[
        {
            "category":"Professional",
            "type":"Services"
        }
    ],
    "sg:phone":"+1 704 878 6190",
    "sg:postcode":"28677",
    "sg:province":"NC",
    "wof:name":"Freeze Jr Robert A",
    "wof:placetype":"venue"
},
  "geometry": {"coordinates":[-80.96326500000001,35.773967],"type":"Point"}
}