{
  "type": "Feature",
  "properties": {
    "addr:full":"1414 E 11th St Siler City NC 27344",
    "addr:housenumber":"1414",
    "addr:postcode":"27344",
    "addr:street":"E 11Th St",
    "iso:country":"US",
    "sg:address":"1414 E 11th St",
    "sg:city":"Siler City",
    "sg:classifiers":[
        {
            "category":"Health Services",
            "subcategory":"Clinic",
            "type":"Services"
        }
    ],
    "sg:phone":"+1 919 663 1244",
    "sg:postcode":"27344",
    "sg:province":"NC",
    "sg:tags":[
        "home"
    ],
    "wof:name":"Community Homecare & Hospice",
    "wof:placetype":"venue"
},
  "geometry": {"coordinates":[-79.44414399999999,35.732911],"type":"Point"}
}