{
  "type": "Feature",
  "properties": {
    "iso:country":"US",
    "sg:address":"4385 Styers Ferry Rd",
    "sg:city":"Winston Salem",
    "sg:classifiers":[
        {
            "category":"Building & Trades",
            "subcategory":"Construction",
            "type":"Services"
        }
    ],
    "sg:phone":"+1 336 945 4039",
    "sg:postcode":"27023",
    "sg:province":"NC",
    "sg:tags":[
        "contractor"
    ],
    "wof:name":"Zack Rothrock Builders Inc",
    "wof:placetype":"venue"
},
  "geometry": {"coordinates":[-80.37851999999999,36.091348],"type":"Point"}
}