{
  "type": "Feature",
  "properties": {
    "iso:country":"US",
    "sg:address":"1208 Commercial Ave",
    "sg:city":"Charlotte",
    "sg:classifiers":[
        {
            "category":"Building & Trades",
            "subcategory":"Cleaning & Sanitation",
            "type":"Services"
        }
    ],
    "sg:phone":"+1 704 375 0070",
    "sg:postcode":"28205",
    "sg:province":"NC",
    "sg:tags":[
        "janitor"
    ],
    "wof:name":"All Purpose Janitorial Svc",
    "wof:placetype":"venue"
},
  "geometry": {"coordinates":[-80.784554,35.246737],"type":"Point"}
}