{
  "type": "Feature",
  "properties": {
    "addr:full":"3440 Bragg Blvd Fayetteville NC 28303",
    "addr:housenumber":"3440",
    "addr:postcode":"28303",
    "addr:street":"Bragg Blvd",
    "iso:country":"US",
    "sg:address":"3440 Bragg Blvd",
    "sg:city":"Fayetteville",
    "sg:classifiers":[
        {
            "category":"Home & Garden",
            "subcategory":"Furniture",
            "type":"Retail Goods"
        }
    ],
    "sg:phone":"+1 910 864 2337",
    "sg:postcode":"28303",
    "sg:province":"NC",
    "sg:tags":[
        "mattress"
    ],
    "wof:name":"Sleep Source",
    "wof:placetype":"venue"
},
  "geometry": {"coordinates":[-78.93478399999999,35.076626],"type":"Point"}
}