{
  "type": "Feature",
  "properties": {
    "addr:full":"305 Bessemer City Rd Gastonia NC 28052",
    "addr:housenumber":"305",
    "addr:postcode":"28052",
    "addr:street":"Bessemer City Rd",
    "iso:country":"US",
    "sg:address":"305 Bessemer City Rd",
    "sg:city":"Gastonia",
    "sg:classifiers":[
        {
            "category":"Shopping",
            "subcategory":"Hobbies, Toys, & Games",
            "type":"Retail Goods"
        }
    ],
    "sg:phone":"+1 704 866 0776",
    "sg:postcode":"28052",
    "sg:province":"NC",
    "wof:name":"Carousel Gift & Hobby Shop",
    "wof:placetype":"venue"
},
  "geometry": {"coordinates":[-81.217311,35.263453],"type":"Point"}
}