{
  "type": "Feature",
  "properties": {
    "iso:country":"US",
    "sg:address":"355 N Front St",
    "sg:city":"Wilmington",
    "sg:classifiers":[
        {
            "category":"Home & Garden",
            "subcategory":"Mobile Homes",
            "type":"Retail Goods"
        }
    ],
    "sg:phone":"+1 910 342 0345",
    "sg:postcode":"28401",
    "sg:province":"NC",
    "wof:name":"Blue Coast Properties",
    "wof:placetype":"venue"
},
  "geometry": {"coordinates":[-77.949292,34.239291],"type":"Point"}
}