{
  "type": "Feature",
  "properties": {
    "iso:country":"US",
    "sg:address":"3370 Wintergreen Rd",
    "sg:city":"Cove City",
    "sg:classifiers":[
        {
            "category":"Health Services",
            "subcategory":"Nursing And Care Facility",
            "type":"Services"
        }
    ],
    "sg:phone":"+1 252 514 6505",
    "sg:postcode":"28523",
    "sg:province":"NC",
    "wof:name":"Extensions of Life Adult Care",
    "wof:placetype":"venue"
},
  "geometry": {"coordinates":[-77.291633,35.257402],"type":"Point"}
}