{
  "type": "Feature",
  "properties": {
    "iso:country":"US",
    "sg:address":"3500 Arendell St",
    "sg:city":"Morehead City",
    "sg:classifiers":[
        {
            "category":"Health Services",
            "subcategory":"Hospital",
            "type":"Services"
        }
    ],
    "sg:phone":"+1 252 808 6821",
    "sg:postcode":"28557",
    "sg:province":"NC",
    "wof:name":"Day Surgery Ctr",
    "wof:placetype":"venue"
},
  "geometry": {"coordinates":[-76.755157,34.724778],"type":"Point"}
}