{
  "type": "Feature",
  "properties": {
    "iso:country":"US",
    "sg:address":"1140 Benson Rd",
    "sg:city":"Garner",
    "sg:classifiers":[
        {
            "category":"Building & Trades",
            "subcategory":"Cleaning & Sanitation",
            "type":"Services"
        }
    ],
    "sg:phone":"+1 919 779 7157",
    "sg:postcode":"27529",
    "sg:province":"NC",
    "sg:tags":[
        "butler",
        "maid"
    ],
    "wof:name":"Maids In Waiting",
    "wof:placetype":"venue"
},
  "geometry": {"coordinates":[-78.608549,35.694785],"type":"Point"}
}