{
  "type": "Feature",
  "properties": {
    "addr:full":"10618 Providence Rd W Charlotte NC 28277",
    "addr:housenumber":"10618",
    "addr:postcode":"28277",
    "addr:street":"Providence Rd W",
    "iso:country":"US",
    "sg:address":"10618 Providence Rd W",
    "sg:city":"Charlotte",
    "sg:classifiers":[
        {
            "category":"Insurance",
            "subcategory":"Insurance Agent",
            "type":"Services"
        }
    ],
    "sg:phone":"+1 704 846 9700",
    "sg:postcode":"28277",
    "sg:province":"NC",
    "wof:name":"Allstate",
    "wof:placetype":"venue"
},
  "geometry": {"coordinates":[-80.844962,35.041604],"type":"Point"}
}