{
  "type": "Feature",
  "properties": {
    "addr:full":"993 High Point St Randleman NC 27317",
    "addr:housenumber":"993",
    "addr:postcode":"27317",
    "addr:street":"High Point St",
    "iso:country":"US",
    "sg:address":"993 High Point St",
    "sg:city":"Randleman",
    "sg:classifiers":[
        {
            "category":"Restaurant",
            "type":"Food & Drink"
        }
    ],
    "sg:menulink":"http://www.allmenus.com/nc/randleman/137576-subway/menu/",
    "sg:phone":"+1 336 495 0025",
    "sg:postcode":"27317",
    "sg:province":"NC",
    "sg:tags":[
        "american",
        "sandwich"
    ],
    "wof:name":"Subway",
    "wof:placetype":"venue"
},
  "geometry": {"coordinates":[-79.822457,35.820499],"type":"Point"}
}