{
  "type": "Feature",
  "properties": {
    "addr:full":"108 N Graham St Charlotte NC 28202",
    "addr:housenumber":"108",
    "addr:postcode":"28202",
    "addr:street":"N Graham St",
    "iso:country":"US",
    "sg:address":"108 N Graham St",
    "sg:city":"Charlotte",
    "sg:classifiers":[
        {
            "category":"Local Transit",
            "type":"Transportation"
        }
    ],
    "sg:phone":"+1 704 376 0852",
    "sg:postcode":"28202",
    "sg:province":"NC",
    "sg:tags":[
        "passenger"
    ],
    "wof:name":"Holiday Limousine Charlotte",
    "wof:placetype":"venue"
},
  "geometry": {"coordinates":[-80.84587000000001,35.231279],"type":"Point"}
}