{
  "type": "Feature",
  "properties": {
    "addr:full":"1401 W Grantham St Goldsboro NC 27530",
    "addr:housenumber":"1401",
    "addr:postcode":"27530",
    "addr:street":"W Grantham St",
    "iso:country":"US",
    "sg:address":"1401 W Grantham St",
    "sg:city":"Goldsboro",
    "sg:classifiers":[
        {
            "category":"Retail",
            "subcategory":"Funeral Services",
            "type":"Services"
        }
    ],
    "sg:phone":"+1 919 735 5008",
    "sg:postcode":"27530",
    "sg:province":"NC",
    "wof:name":"Goldsboro Cremation Service",
    "wof:placetype":"venue"
},
  "geometry": {"coordinates":[-78.01965199999999,35.402597],"type":"Point"}
}