{
  "type": "Feature",
  "properties": {
    "addr:full":"7715 Farmstead Ln Denver NC 28037",
    "addr:housenumber":"7715",
    "addr:postcode":"28037",
    "addr:street":"Farmstead Ln",
    "iso:country":"US",
    "sg:address":"7715 Farmstead Ln",
    "sg:city":"Denver",
    "sg:classifiers":[
        {
            "category":"Shopping",
            "subcategory":"Bicycles & Sporting Goods",
            "type":"Retail Goods"
        }
    ],
    "sg:phone":"+1 704 489 8152",
    "sg:postcode":"28037",
    "sg:province":"NC",
    "wof:name":"Henson Goods",
    "wof:placetype":"venue"
},
  "geometry": {"coordinates":[-80.993332,35.460617],"type":"Point"}
}