{
  "type": "Feature",
  "properties": {
    "addr:full":"200 Elgin Dr NE Concord NC 28025",
    "addr:housenumber":"200",
    "addr:postcode":"28025",
    "addr:street":"Elgin Dr Ne",
    "iso:country":"US",
    "sg:address":"200 Elgin Dr NE",
    "sg:city":"Concord",
    "sg:classifiers":[
        {
            "category":"Home & Garden",
            "subcategory":"Building Materials",
            "type":"Retail Goods"
        }
    ],
    "sg:phone":"+1 704 782 9020",
    "sg:postcode":"28025",
    "sg:province":"NC",
    "sg:tags":[
        "paint"
    ],
    "wof:name":"Liquid Rubber Siding",
    "wof:placetype":"venue"
},
  "geometry": {"coordinates":[-80.580922,35.420828],"type":"Point"}
}