{
  "type": "Feature",
  "properties": {
    "iso:country":"US",
    "sg:address":"300 S Orange Ave",
    "sg:city":"Dunn",
    "sg:classifiers":[
        {
            "category":"Professional",
            "subcategory":"Management & Consulting",
            "type":"Services"
        }
    ],
    "sg:phone":"+1   ",
    "sg:postcode":"28334",
    "sg:province":"NC",
    "sg:tags":[
        "business"
    ],
    "wof:name":"Walker Consulting",
    "wof:placetype":"venue"
},
  "geometry": {"coordinates":[-78.617874,35.310113],"type":"Point"}
}