{
  "type": "Feature",
  "properties": {
    "iso:country":"US",
    "sg:address":"114 E 28th St",
    "sg:city":"Charlotte",
    "sg:classifiers":[
        {
            "category":"Utilities",
            "subcategory":"Recycling",
            "type":"Services"
        }
    ],
    "sg:phone":"+1 704 376 3635",
    "sg:postcode":"28206",
    "sg:province":"NC",
    "wof:name":"Top Price Recycling",
    "wof:placetype":"venue"
},
  "geometry": {"coordinates":[-80.81776499999999,35.247025],"type":"Point"}
}