{
  "type": "Feature",
  "properties": {
    "iso:country":"US",
    "sg:address":"6624 Fairview Rd",
    "sg:city":"Charlotte",
    "sg:classifiers":[
        {
            "category":"Banks & Credit Unions",
            "subcategory":"Investment Brokerage",
            "type":"Services"
        }
    ],
    "sg:phone":"+1 704 362 4940",
    "sg:postcode":"28210",
    "sg:province":"NC",
    "sg:tags":[
        "consultant",
        "planning",
        "financial"
    ],
    "wof:name":"Reliance Investments",
    "wof:placetype":"venue"
},
  "geometry": {"coordinates":[-80.82959700000001,35.147989],"type":"Point"}
}