{
  "type": "Feature",
  "properties": {
    "iso:country":"US",
    "sg:address":"10645 Ramsey St",
    "sg:city":"Linden",
    "sg:classifiers":[
        {
            "category":"Food & Beverages",
            "subcategory":"Groceries & Convenience Stores",
            "type":"Retail Goods"
        }
    ],
    "sg:phone":"+1 910 980 0121",
    "sg:postcode":"28356",
    "sg:province":"NC",
    "wof:name":"Exprezit 114",
    "wof:placetype":"venue"
},
  "geometry": {"coordinates":[-78.783996,35.255043],"type":"Point"}
}