{
  "type": "Feature",
  "properties": {
    "addr:full":"910 S Elm St Greensboro NC 27406",
    "addr:housenumber":"910",
    "addr:postcode":"27406",
    "addr:street":"S Elm St",
    "iso:country":"US",
    "sg:address":"910 S Elm St",
    "sg:city":"Greensboro",
    "sg:classifiers":[
        {
            "category":"Shopping",
            "type":"Retail Goods"
        }
    ],
    "sg:phone":"+1 336 274 1583",
    "sg:postcode":"27406",
    "sg:province":"NC",
    "sg:tags":[
        "farm",
        "supply"
    ],
    "wof:name":"S S C 7646-7",
    "wof:placetype":"venue"
},
  "geometry": {"coordinates":[-79.791408,36.058898],"type":"Point"}
}