{
  "type": "Feature",
  "properties": {
    "iso:country":"US",
    "sg:address":"413 E Innes St",
    "sg:city":"Salisbury",
    "sg:classifiers":[
        {
            "category":"Restaurant",
            "type":"Food & Drink"
        }
    ],
    "sg:phone":"+1 704 636 5680",
    "sg:postcode":"28144",
    "sg:province":"NC",
    "sg:tags":[
        "eating"
    ],
    "wof:name":"Village Inn Restaurant",
    "wof:placetype":"venue"
},
  "geometry": {"coordinates":[-80.46587,35.663832],"type":"Point"}
}