{
  "type": "Feature",
  "properties": {
    "iso:country":"US",
    "sg:address":"74 Meadow Ave NE",
    "sg:city":"Concord",
    "sg:classifiers":[
        {
            "category":"Wholesale",
            "subcategory":"Vending Machines",
            "type":"Manufacturing & Wholesale Goods"
        },
        {
            "category":"Building & Trades",
            "subcategory":"Equipment Rental",
            "type":"Services"
        }
    ],
    "sg:phone":"+1 704 795 6705",
    "sg:postcode":"28025",
    "sg:province":"NC",
    "wof:name":"Powell s Vending",
    "wof:placetype":"venue"
},
  "geometry": {"coordinates":[-80.583271,35.418434],"type":"Point"}
}