{
  "type": "Feature",
  "properties": {
    "iso:country":"US",
    "sg:address":"2706 Cochrane Dr",
    "sg:city":"Charlotte",
    "sg:classifiers":[
        {
            "category":"Personal",
            "type":"Services"
        }
    ],
    "sg:phone":"+1 704 377 3263",
    "sg:postcode":"28269",
    "sg:province":"NC",
    "sg:tags":[
        "car",
        "loading",
        "unloading"
    ],
    "wof:name":"Withers Transportation",
    "wof:placetype":"venue"
},
  "geometry": {"coordinates":[-80.843842,35.288761],"type":"Point"}
}