{
  "type": "Feature",
  "properties": {
    "addr:full":"14922 Ashlight Dr Charlotte NC 28278",
    "addr:housenumber":"14922",
    "addr:postcode":"28278",
    "addr:street":"Ashlight Dr",
    "iso:country":"US",
    "sg:address":"14922 Ashlight Dr",
    "sg:city":"Charlotte",
    "sg:classifiers":[
        {
            "category":"Professional",
            "type":"Services"
        }
    ],
    "sg:phone":"+1 704 321 5403",
    "sg:postcode":"28278",
    "sg:province":"NC",
    "sg:tags":[
        "establishment"
    ],
    "wof:name":"Cherry & Cherry",
    "wof:placetype":"venue"
},
  "geometry": {"coordinates":[-81.001368,35.091162],"type":"Point"}
}