{
  "type": "Feature",
  "properties": {
    "iso:country":"US",
    "sg:address":"1301 N Main St",
    "sg:city":"Fuquay Varina",
    "sg:classifiers":[
        {
            "category":"Restaurant",
            "type":"Food & Drink"
        }
    ],
    "sg:menulink":"http://www.allmenus.com/nc/middle-creek/73321-pizza-hut/menu/",
    "sg:phone":"+1 919 552 0771",
    "sg:postcode":"27526",
    "sg:province":"NC",
    "sg:tags":[
        "american",
        "pizza"
    ],
    "wof:name":"Pizza Hut",
    "wof:placetype":"venue"
},
  "geometry": {"coordinates":[-78.778944,35.591803],"type":"Point"}
}