{
  "type": "Feature",
  "properties": {
    "addr:full":"851 Bradley St NE Concord NC 28025",
    "addr:housenumber":"851",
    "addr:postcode":"28025",
    "addr:street":"Bradley St Ne",
    "iso:country":"US",
    "sg:address":"851 Bradley St NE",
    "sg:city":"Concord",
    "sg:classifiers":[
        {
            "category":"Health Services",
            "subcategory":"Doctor",
            "type":"Services"
        }
    ],
    "sg:phone":"+1 704 788 1134",
    "sg:postcode":"28025",
    "sg:province":"NC",
    "sg:tags":[
        "clinic",
        "dentist"
    ],
    "wof:name":"Holland Family Practice",
    "wof:placetype":"venue"
},
  "geometry": {"coordinates":[-80.591649,35.442118],"type":"Point"}
}