{
  "type": "Feature",
  "properties": {
    "iso:country":"US",
    "sg:address":"3109 Swan Creek Rd",
    "sg:city":"Jonesville",
    "sg:classifiers":[
        {
            "category":"Personal",
            "subcategory":"Beauty Salon",
            "type":"Services"
        }
    ],
    "sg:phone":"+1 336 835 3215",
    "sg:postcode":"28642",
    "sg:province":"NC",
    "sg:tags":[
        "shop"
    ],
    "wof:name":"Shear Sensations",
    "wof:placetype":"venue"
},
  "geometry": {"coordinates":[-80.863466,36.205669],"type":"Point"}
}