{
  "type": "Feature",
  "properties": {
    "iso:country":"US",
    "sg:address":"132 Homestead Farm Cir",
    "sg:city":"Hendersonville",
    "sg:classifiers":[
        {
            "category":"Health Services",
            "subcategory":"Doctor",
            "type":"Services"
        }
    ],
    "sg:phone":"+1 828 687 8670",
    "sg:postcode":"28792",
    "sg:province":"NC",
    "sg:tags":[
        "physician",
        "surgeon"
    ],
    "wof:name":"Park Ridge Medical Assoc",
    "wof:placetype":"venue"
},
  "geometry": {"coordinates":[-82.48912300000001,35.392723],"type":"Point"}
}