{
  "type": "Feature",
  "properties": {
    "iso:country":"US",
    "sg:address":"227 Fox Run Dr",
    "sg:city":"Wendell",
    "sg:classifiers":[
        {
            "category":"Shopping",
            "subcategory":"Clothing, Apparel, & Fashions",
            "type":"Retail Goods"
        }
    ],
    "sg:phone":"+1 919 365 5064",
    "sg:postcode":"27591",
    "sg:province":"NC",
    "sg:tags":[
        "dancing",
        "supply"
    ],
    "wof:name":"Dynamic Dance Attire",
    "wof:placetype":"venue"
},
  "geometry": {"coordinates":[-78.38369400000001,35.819789],"type":"Point"}
}