{
  "type": "Feature",
  "properties": {
    "addr:full":"832 Shinnville Rd Mooresville NC 28115",
    "addr:housenumber":"832",
    "addr:postcode":"28115",
    "addr:street":"Shinnville Rd",
    "iso:country":"US",
    "sg:address":"832 Shinnville Rd",
    "sg:city":"Mooresville",
    "sg:classifiers":[
        {
            "category":"Wholesale",
            "subcategory":"Durable Goods & Equipment",
            "type":"Manufacturing & Wholesale Goods"
        }
    ],
    "sg:phone":"+1 704 660 9005",
    "sg:postcode":"28115",
    "sg:province":"NC",
    "sg:tags":[
        "sign"
    ],
    "wof:name":"C & M Sign Builders Inc",
    "wof:placetype":"venue"
},
  "geometry": {"coordinates":[-80.801877,35.659951],"type":"Point"}
}