{
  "type": "Feature",
  "properties": {
    "iso:country":"US",
    "sg:address":"39 Orchard Ridge Dr",
    "sg:city":"Asheville",
    "sg:classifiers":[
        {
            "category":"Organizations",
            "subcategory":"Religious Organization",
            "type":"Services"
        }
    ],
    "sg:phone":"+1   ",
    "sg:postcode":"28804",
    "sg:province":"NC",
    "wof:name":"Sacred Nature",
    "wof:placetype":"venue"
},
  "geometry": {"coordinates":[-82.506461,35.653642],"type":"Point"}
}