{
  "type": "Feature",
  "properties": {
    "addr:full":"2910 Torrence Dr Greensboro NC 27406",
    "addr:housenumber":"2910",
    "addr:postcode":"27406",
    "addr:street":"Torrence Dr",
    "iso:country":"US",
    "sg:address":"2910 Torrence Dr",
    "sg:city":"Greensboro",
    "sg:classifiers":[
        {
            "category":"Wholesale",
            "subcategory":"Durable Goods & Equipment",
            "type":"Manufacturing & Wholesale Goods"
        }
    ],
    "sg:phone":"+1 336 273 3628",
    "sg:postcode":"27406",
    "sg:province":"NC",
    "sg:tags":[
        "representative",
        "manufacturer"
    ],
    "wof:name":"Vincent-Angel Oldham",
    "wof:placetype":"venue"
},
  "geometry": {"coordinates":[-79.794057,36.030779],"type":"Point"}
}