{
  "type": "Feature",
  "properties": {
    "addr:full":"305 Barden St Princeton NC 27569",
    "addr:housenumber":"305",
    "addr:postcode":"27569",
    "addr:street":"Barden St",
    "iso:country":"US",
    "sg:address":"305 Barden St",
    "sg:city":"Princeton",
    "sg:classifiers":[
        {
            "category":"Retail",
            "subcategory":"Funeral Services",
            "type":"Services"
        }
    ],
    "sg:phone":"+1 919 936 2828",
    "sg:postcode":"27569",
    "sg:province":"NC",
    "sg:tags":[
        "director"
    ],
    "wof:name":"Parrish Funeral Home Inc",
    "wof:placetype":"venue"
},
  "geometry": {"coordinates":[-78.16201,35.472272],"type":"Point"}
}