{
  "type": "Feature",
  "properties": {
    "iso:country":"US",
    "sg:address":"4809 Capital Blvd",
    "sg:city":"Raleigh",
    "sg:classifiers":[
        {
            "category":"Autos & Motor Vehicles",
            "subcategory":"Automobile Sales",
            "type":"Retail Goods"
        }
    ],
    "sg:phone":"+1 919 872 9500",
    "sg:postcode":"27616",
    "sg:province":"NC",
    "sg:tags":[
        "new",
        "used",
        "car"
    ],
    "sg:website":"http://www.leithlincolnmercury.com",
    "wof:name":"Leith Lincoln Mercury",
    "wof:placetype":"venue"
},
  "geometry": {"coordinates":[-78.580642,35.850096],"type":"Point"}
}