{
  "type": "Feature",
  "properties": {
    "iso:country":"US",
    "sg:address":"2687 Old Bailey Hwy",
    "sg:city":"Nashville",
    "sg:classifiers":[
        {
            "category":"Building & Trades",
            "subcategory":"Construction",
            "type":"Services"
        }
    ],
    "sg:phone":"+1 704 364 2543",
    "sg:postcode":"27856",
    "sg:province":"NC",
    "sg:tags":[
        "contractor"
    ],
    "wof:name":"Four Seasons Contractors LLC",
    "wof:placetype":"venue"
},
  "geometry": {"coordinates":[-77.98265000000001,35.935883],"type":"Point"}
}