{
  "type": "Feature",
  "properties": {
    "iso:country":"US",
    "sg:address":"110 Stockton St",
    "sg:city":"Statesville",
    "sg:classifiers":[
        {
            "category":"Professional",
            "subcategory":"Lawyer & Legal Services",
            "type":"Services"
        }
    ],
    "sg:phone":"+1 704 878 4247",
    "sg:postcode":"28677",
    "sg:province":"NC",
    "sg:tags":[
        "correctional",
        "institution"
    ],
    "wof:name":"Juvenile Justice & Delinquency",
    "wof:placetype":"venue"
},
  "geometry": {"coordinates":[-80.8891,35.788035],"type":"Point"}
}