{
  "type": "Feature",
  "properties": {
    "addr:full":"2462 Stantonsburg Rd Greenville NC 27834",
    "addr:housenumber":"2462",
    "addr:postcode":"27834",
    "addr:street":"Stantonsburg Rd",
    "iso:country":"US",
    "sg:address":"2462 Stantonsburg Rd",
    "sg:city":"Greenville",
    "sg:classifiers":[
        {
            "category":"Professional",
            "subcategory":"Business Services",
            "type":"Services"
        }
    ],
    "sg:phone":"+1 252 752 6712",
    "sg:postcode":"27834",
    "sg:province":"NC",
    "sg:tags":[
        "transportation",
        "freight",
        "arrangement"
    ],
    "wof:name":"Mail Doc The",
    "wof:placetype":"venue"
},
  "geometry": {"coordinates":[-77.41270900000001,35.605417],"type":"Point"}
}