{
  "type": "Feature",
  "properties": {
    "iso:country":"US",
    "sg:address":"3475 Forestdale Dr",
    "sg:city":"Burlington",
    "sg:classifiers":[
        {
            "category":"Real Estate",
            "subcategory":"Real Estate Operator",
            "type":"Services"
        }
    ],
    "sg:phone":"+1 336 584 6385",
    "sg:postcode":"27215",
    "sg:province":"NC",
    "sg:tags":[
        "condominium"
    ],
    "wof:name":"Oakgrove Condos",
    "wof:placetype":"venue"
},
  "geometry": {"coordinates":[-79.495257,36.076184],"type":"Point"}
}