{
  "type": "Feature",
  "properties": {
    "addr:full":"798 Oak Ridge Farm Hwy Mooresville NC 28115",
    "addr:housenumber":"798",
    "addr:postcode":"28115",
    "addr:street":"Oak Ridge Farm Hwy",
    "iso:country":"US",
    "sg:address":"798 Oak Ridge Farm Hwy",
    "sg:city":"Mooresville",
    "sg:classifiers":[
        {
            "category":"Restaurant",
            "type":"Food & Drink"
        }
    ],
    "sg:menulink":"http://www.allmenus.com/nc/coddle-creek/229294-turn-4-pizza/menu/",
    "sg:phone":"+1 704 799 2134",
    "sg:postcode":"28115",
    "sg:province":"NC",
    "sg:tags":[
        "american",
        "pizza"
    ],
    "wof:name":"Turn 4 Pizza",
    "wof:placetype":"venue"
},
  "geometry": {"coordinates":[-80.802098,35.607669],"type":"Point"}
}