{
  "type": "Feature",
  "properties": {
    "iso:country":"US",
    "sg:address":"1087 Sutton Ct",
    "sg:city":"Greensboro",
    "sg:classifiers":[
        {
            "category":"Home & Garden",
            "subcategory":"Furniture",
            "type":"Retail Goods"
        }
    ],
    "sg:phone":"+1 336 674 7307",
    "sg:postcode":"27406",
    "sg:province":"NC",
    "sg:tags":[
        "builder",
        "custom"
    ],
    "wof:name":"Atlantic Craftsman",
    "wof:placetype":"venue"
},
  "geometry": {"coordinates":[-79.824805,35.966045],"type":"Point"}
}