{
  "type": "Feature",
  "properties": {
    "iso:country":"US",
    "sg:address":"166 Mills Pond Rd",
    "sg:city":"Benson",
    "sg:classifiers":[
        {
            "category":"Building & Trades",
            "subcategory":"Construction",
            "type":"Services"
        }
    ],
    "sg:phone":"+1 919 207 1320",
    "sg:postcode":"27504",
    "sg:province":"NC",
    "sg:tags":[
        "steel",
        "erectors"
    ],
    "wof:name":"Amerson Steel Erectors Inc",
    "wof:placetype":"venue"
},
  "geometry": {"coordinates":[-78.560807,35.506449],"type":"Point"}
}