{
  "type": "Feature",
  "properties": {
    "iso:country":"US",
    "sg:address":"367 Powdermill Creek Rd",
    "sg:city":"Newland",
    "sg:classifiers":[
        {
            "category":"Freight",
            "type":"Transportation"
        }
    ],
    "sg:phone":"+1 828 733 2169",
    "sg:postcode":"28657",
    "sg:province":"NC",
    "sg:tags":[
        "operator",
        "local",
        "storage",
        "trucking"
    ],
    "wof:name":"Pittman Trucking Inc",
    "wof:placetype":"venue"
},
  "geometry": {"coordinates":[-82.018596,36.059181],"type":"Point"}
}