{
  "type": "Feature",
  "properties": {
    "iso:country":"US",
    "sg:address":"22 N Lexington Ave",
    "sg:city":"Asheville",
    "sg:classifiers":[
        {
            "category":"Professional",
            "type":"Services"
        }
    ],
    "sg:phone":"+1 828 254 3426",
    "sg:postcode":"28801",
    "sg:province":"NC",
    "sg:tags":[
        "establishment"
    ],
    "wof:name":"Bohemian",
    "wof:placetype":"venue"
},
  "geometry": {"coordinates":[-82.553004,35.596172],"type":"Point"}
}