{
  "type": "Feature",
  "properties": {
    "iso:country":"US",
    "sg:address":"236 Pleasant Hill Church Rd",
    "sg:city":"Ellerbe",
    "sg:classifiers":[
        {
            "category":"Building & Trades",
            "subcategory":"Landscaping Services",
            "type":"Services"
        }
    ],
    "sg:phone":"+1 910 652 4780",
    "sg:postcode":"28338",
    "sg:province":"NC",
    "sg:tags":[
        "nurseryman",
        "landscape"
    ],
    "wof:name":"Hawks Landscaping & Concrete",
    "wof:placetype":"venue"
},
  "geometry": {"coordinates":[-79.822472,35.024387],"type":"Point"}
}