{
  "type": "Feature",
  "properties": {
    "addr:full":"3015 S Church St Burlington NC 27215",
    "addr:housenumber":"3015",
    "addr:postcode":"27215",
    "addr:street":"S Church St",
    "iso:country":"US",
    "sg:address":"3015 S Church St",
    "sg:city":"Burlington",
    "sg:classifiers":[
        {
            "category":"Professional",
            "subcategory":"Management & Consulting",
            "type":"Services"
        }
    ],
    "sg:phone":"+1 336 584 4242",
    "sg:postcode":"27215",
    "sg:province":"NC",
    "sg:tags":[
        "medical",
        "administration",
        "business"
    ],
    "wof:name":"Mc Vey & Assoc Inc",
    "wof:placetype":"venue"
},
  "geometry": {"coordinates":[-79.494406,36.080311],"type":"Point"}
}