{
  "type": "Feature",
  "properties": {
    "iso:country":"US",
    "sg:address":"1050 McMillan Siding Rd",
    "sg:city":"Parkton",
    "sg:classifiers":[
        {
            "category":"Building & Trades",
            "subcategory":"Construction",
            "type":"Services"
        }
    ],
    "sg:phone":"+1 910 858 2245",
    "sg:postcode":"28371",
    "sg:province":"NC",
    "sg:tags":[
        "house"
    ],
    "wof:name":"Britt Construction",
    "wof:placetype":"venue"
},
  "geometry": {"coordinates":[-78.958631,34.864943],"type":"Point"}
}