{
  "type": "Feature",
  "properties": {
    "iso:country":"US",
    "sg:address":"308 W Rosemary St",
    "sg:city":"Chapel Hill",
    "sg:classifiers":[
        {
            "category":"Social Services",
            "type":"Services"
        }
    ],
    "sg:phone":"+1   ",
    "sg:postcode":"27516",
    "sg:province":"NC",
    "wof:name":"Capital Area Substance Abuse",
    "wof:placetype":"venue"
},
  "geometry": {"coordinates":[-79.062353,35.911663],"type":"Point"}
}