{
  "type": "Feature",
  "properties": {
    "iso:country":"US",
    "sg:address":"100 Lacoste Ln",
    "sg:city":"Cary",
    "sg:classifiers":[
        {
            "category":"Professional",
            "subcategory":"Management & Consulting",
            "type":"Services"
        }
    ],
    "sg:phone":"+1 919 467 7095",
    "sg:postcode":"27511",
    "sg:province":"NC",
    "sg:tags":[
        "home",
        "demonstration"
    ],
    "wof:name":"Tupperware Full Circle Ent",
    "wof:placetype":"venue"
},
  "geometry": {"coordinates":[-78.778341,35.752573],"type":"Point"}
}