{
  "type": "Feature",
  "properties": {
    "addr:full":"1094 Crossroads Dr Statesville NC 28625",
    "addr:housenumber":"1094",
    "addr:postcode":"28625",
    "addr:street":"Crossroads Dr",
    "iso:country":"US",
    "sg:address":"1094 Crossroads Dr",
    "sg:city":"Statesville",
    "sg:classifiers":[
        {
            "category":"Shopping",
            "type":"Retail Goods"
        }
    ],
    "sg:phone":"+1 704 871 1965",
    "sg:postcode":"28625",
    "sg:province":"NC",
    "sg:tags":[
        "merchandise"
    ],
    "wof:name":"Game Wizards",
    "wof:placetype":"venue"
},
  "geometry": {"coordinates":[-80.87178,35.809646],"type":"Point"}
}