{
  "type": "Feature",
  "properties": {
    "iso:country":"US",
    "sg:address":"107 Coachmans Cove Rd",
    "sg:city":"Four Oaks",
    "sg:classifiers":[
        {
            "category":"Building & Trades",
            "subcategory":"Landscaping Services",
            "type":"Services"
        }
    ],
    "sg:phone":"+1 919 963 3684",
    "sg:postcode":"27524",
    "sg:province":"NC",
    "sg:tags":[
        "landscape",
        "contractor"
    ],
    "wof:name":"Lakeside Landscapes Inc",
    "wof:placetype":"venue"
},
  "geometry": {"coordinates":[-78.394293,35.406387],"type":"Point"}
}