{
  "type": "Feature",
  "properties": {
    "iso:country":"US",
    "sg:address":"10904 Gardenia St",
    "sg:city":"Charlotte",
    "sg:classifiers":[
        {
            "category":"Freight",
            "type":"Transportation"
        }
    ],
    "sg:phone":"+1 704 569 0538",
    "sg:postcode":"28215",
    "sg:province":"NC",
    "sg:tags":[
        "operator",
        "local",
        "trucking"
    ],
    "wof:name":"Building One Trucking",
    "wof:placetype":"venue"
},
  "geometry": {"coordinates":[-80.68070400000001,35.255516],"type":"Point"}
}