{
  "type": "Feature",
  "properties": {
    "addr:full":"1950 S Main St Wake Forest NC 27587",
    "addr:housenumber":"1950",
    "addr:postcode":"27587",
    "addr:street":"S Main St",
    "iso:country":"US",
    "sg:address":"1950 S Main St",
    "sg:city":"Wake Forest",
    "sg:classifiers":[
        {
            "category":"Retail",
            "subcategory":"Auto Rental",
            "type":"Services"
        }
    ],
    "sg:phone":"+1 919 569 0006",
    "sg:postcode":"27587",
    "sg:province":"NC",
    "sg:tags":[
        "renting",
        "automobile",
        "passenger",
        "car"
    ],
    "wof:name":"Enterprise Rent A Car",
    "wof:placetype":"venue"
},
  "geometry": {"coordinates":[-78.53021,35.95023],"type":"Point"}
}