{
  "type": "Feature",
  "properties": {
    "addr:full":"304 E Walnut St Goldsboro NC 27530",
    "addr:housenumber":"304",
    "addr:postcode":"27530",
    "addr:street":"E Walnut St",
    "iso:country":"US",
    "sg:address":"304 E Walnut St",
    "sg:city":"Goldsboro",
    "sg:classifiers":[
        {
            "category":"Insurance",
            "subcategory":"Insurance Agent",
            "type":"Services"
        }
    ],
    "sg:phone":"+1 919 735 1341",
    "sg:postcode":"27530",
    "sg:province":"NC",
    "sg:website":"www.waynerealty.com",
    "wof:name":"Wayne Realty & Insurance Co",
    "wof:placetype":"venue"
},
  "geometry": {"coordinates":[-77.99255599999999,35.381657],"type":"Point"}
}