{
  "type": "Feature",
  "properties": {
    "addr:full":"115 E Bizzel St Laurinburg NC 28352",
    "addr:housenumber":"115",
    "addr:postcode":"28352",
    "addr:street":"E Bizzel St",
    "iso:country":"US",
    "sg:address":"115 E Bizzel St",
    "sg:city":"Laurinburg",
    "sg:classifiers":[
        {
            "category":"Professional",
            "type":"Services"
        }
    ],
    "sg:phone":"+1 910 277 0960",
    "sg:postcode":"28352",
    "sg:province":"NC",
    "sg:tags":[
        "establishment"
    ],
    "wof:name":"Shirtails",
    "wof:placetype":"venue"
},
  "geometry": {"coordinates":[-79.460623,34.777671],"type":"Point"}
}