{
  "type": "Feature",
  "properties": {
    "iso:country":"US",
    "sg:address":"6801 Wilgrove Mint Hill Rd",
    "sg:city":"Charlotte",
    "sg:classifiers":[
        {
            "category":"Personal",
            "subcategory":"Beauty Salon",
            "type":"Services"
        },
        {
            "category":"Personal",
            "subcategory":"Barber",
            "type":"Services"
        }
    ],
    "sg:phone":"+1 704 545 8222",
    "sg:postcode":"28227",
    "sg:province":"NC",
    "sg:tags":[
        "shop"
    ],
    "wof:name":"Style A Rena Barber Shop",
    "wof:placetype":"venue"
},
  "geometry": {"coordinates":[-80.670269,35.206273],"type":"Point"}
}