{
  "type": "Feature",
  "properties": {
    "iso:country":"US",
    "sg:address":"2000 Chapel Hill Rd",
    "sg:city":"Durham",
    "sg:classifiers":[
        {
            "category":"Shopping",
            "subcategory":"Discount & Variety Stores",
            "type":"Retail Goods"
        }
    ],
    "sg:phone":"+1 919 403 0071",
    "sg:postcode":"27707",
    "sg:province":"NC",
    "wof:name":"Maxway 586",
    "wof:placetype":"venue"
},
  "geometry": {"coordinates":[-78.926502,35.98719],"type":"Point"}
}