{
  "type": "Feature",
  "properties": {
    "addr:full":"5602 Big Laurel Rd Creston NC 28615",
    "addr:housenumber":"5602",
    "addr:postcode":"28615",
    "addr:street":"Big Laurel Rd",
    "iso:country":"US",
    "sg:address":"5602 Big Laurel Rd",
    "sg:city":"Creston",
    "sg:classifiers":[
        {
            "category":"Home & Garden",
            "subcategory":"Building Materials",
            "type":"Retail Goods"
        }
    ],
    "sg:phone":"+1 336 385 1588",
    "sg:postcode":"28615",
    "sg:province":"NC",
    "sg:tags":[
        "mixed",
        "concrete"
    ],
    "wof:name":"Hamm Septic Tanks",
    "wof:placetype":"venue"
},
  "geometry": {"coordinates":[-81.672488,36.491162],"type":"Point"}
}