{
  "type": "Feature",
  "properties": {
    "iso:country":"US",
    "sg:address":"665 Damascus Church Rd",
    "sg:city":"Wilkesboro",
    "sg:classifiers":[
        {
            "category":"Building & Trades",
            "subcategory":"Construction",
            "type":"Services"
        }
    ],
    "sg:phone":"+1 336 838 8898",
    "sg:postcode":"28697",
    "sg:province":"NC",
    "sg:tags":[
        "siding",
        "contractor"
    ],
    "wof:name":"Alvis Spray On Siding",
    "wof:placetype":"venue"
},
  "geometry": {"coordinates":[-81.120392,36.150974],"type":"Point"}
}