{
  "type": "Feature",
  "properties": {
    "iso:country":"US",
    "sg:address":"628 Grants Creek Rd",
    "sg:city":"Jacksonville",
    "sg:classifiers":[
        {
            "category":"Building & Trades",
            "subcategory":"Construction",
            "type":"Services"
        }
    ],
    "sg:phone":"+1 910 577 6489",
    "sg:postcode":"28546",
    "sg:province":"NC",
    "sg:tags":[
        "nonresidential"
    ],
    "wof:name":"Adam Morton Construction",
    "wof:placetype":"venue"
},
  "geometry": {"coordinates":[-77.29045499999999,34.79131],"type":"Point"}
}