{
  "type": "Feature",
  "properties": {
    "addr:full":"5135 Carolina Beach Rd Wilmington NC 28412",
    "addr:housenumber":"5135",
    "addr:postcode":"28412",
    "addr:street":"Carolina Beach Rd",
    "iso:country":"US",
    "sg:address":"5135 Carolina Beach Rd",
    "sg:city":"Wilmington",
    "sg:classifiers":[
        {
            "category":"Shopping",
            "subcategory":"Department Store",
            "type":"Retail Goods"
        }
    ],
    "sg:phone":"+1 910 452 0944",
    "sg:postcode":"28412",
    "sg:province":"NC",
    "wof:name":"Wal-Mart Supercenter",
    "wof:placetype":"venue"
},
  "geometry": {"coordinates":[-77.897941,34.14498],"type":"Point"}
}