{
  "type": "Feature",
  "properties": {
    "addr:full":"1321 Jackson St Burlington NC 27217",
    "addr:housenumber":"1321",
    "addr:postcode":"27217",
    "addr:street":"Jackson St",
    "iso:country":"US",
    "sg:address":"1321 Jackson St",
    "sg:city":"Burlington",
    "sg:classifiers":[
        {
            "category":"Organizations",
            "subcategory":"Religious Organization",
            "type":"Services"
        }
    ],
    "sg:phone":"+1 336 228 6727",
    "sg:postcode":"27217",
    "sg:province":"NC",
    "sg:tags":[
        "church"
    ],
    "wof:name":"Visitor's Chapel UCC",
    "wof:placetype":"venue"
},
  "geometry": {"coordinates":[-79.44019299999999,36.112973],"type":"Point"}
}