{
  "type": "Feature",
  "properties": {
    "addr:full":"807 Bethea Rd Maxton NC 28364",
    "addr:housenumber":"807",
    "addr:postcode":"28364",
    "addr:street":"Bethea Rd",
    "iso:country":"US",
    "sg:address":"807 Bethea Rd",
    "sg:city":"Maxton",
    "sg:classifiers":[
        {
            "category":"Government",
            "subcategory":"Fire Station",
            "type":"Public Place"
        }
    ],
    "sg:phone":"+1 910 844 9274",
    "sg:postcode":"28364",
    "sg:province":"NC",
    "sg:tags":[
        "protection"
    ],
    "wof:name":"Fire Station",
    "wof:placetype":"venue"
},
  "geometry": {"coordinates":[-79.402508,34.666419],"type":"Point"}
}