{
  "type": "Feature",
  "properties": {
    "iso:country":"US",
    "sg:address":"2425 Kildaire Farm Rd",
    "sg:city":"Cary",
    "sg:classifiers":[
        {
            "category":"Retail",
            "subcategory":"Laundry & Dry Cleaning",
            "type":"Services"
        }
    ],
    "sg:phone":"+1 919 859 7440",
    "sg:postcode":"27511",
    "sg:province":"NC",
    "wof:name":"Dollar Fifty Dry Clean",
    "wof:placetype":"venue"
},
  "geometry": {"coordinates":[-78.777199,35.728001],"type":"Point"}
}