{
  "type": "Feature",
  "properties": {
    "addr:full":"2246 Davie Academy Rd Mocksville NC 27028",
    "addr:housenumber":"2246",
    "addr:postcode":"27028",
    "iso:country":"US",
    "sg:address":"2246 Davie Academy Rd",
    "sg:city":"Mocksville",
    "sg:classifiers":[
        {
            "category":"Retail",
            "subcategory":"Auto Repair",
            "type":"Services"
        }
    ],
    "sg:phone":"+1   ",
    "sg:postcode":"27028",
    "sg:province":"NC",
    "sg:tags":[
        "body"
    ],
    "wof:name":"Shoms Restoration",
    "wof:placetype":"venue"
},
  "geometry": {"coordinates":[-80.679884,35.893483],"type":"Point"}
}