{
  "type": "Feature",
  "properties": {
    "iso:country":"US",
    "sg:address":"1400 Wayne Memorial Dr",
    "sg:city":"Goldsboro",
    "sg:classifiers":[
        {
            "category":"Real Estate",
            "subcategory":"Real Estate Agent",
            "type":"Services"
        }
    ],
    "sg:phone":"+1 919 735 9300",
    "sg:postcode":"27534",
    "sg:province":"NC",
    "sg:tags":[
        "consultant"
    ],
    "wof:name":"True Realty",
    "wof:placetype":"venue"
},
  "geometry": {"coordinates":[-77.97609,35.391965],"type":"Point"}
}