{
  "type": "Feature",
  "properties": {
    "addr:full":"2846 Forestdale Dr Burlington NC 27215",
    "addr:housenumber":"2846",
    "addr:postcode":"27215",
    "addr:street":"Forestdale Dr",
    "iso:country":"US",
    "sg:address":"2846 Forestdale Dr",
    "sg:city":"Burlington",
    "sg:classifiers":[
        {
            "category":"Professional",
            "subcategory":"Advertising",
            "type":"Services"
        }
    ],
    "sg:phone":"+1   ",
    "sg:postcode":"27215",
    "sg:province":"NC",
    "sg:tags":[
        "agency"
    ],
    "wof:name":"Jane Pate Vondy",
    "wof:placetype":"venue"
},
  "geometry": {"coordinates":[-79.490025,36.085785],"type":"Point"}
}