{
  "type": "Feature",
  "properties": {
    "iso:country":"US",
    "sg:address":"701 N King Charles Rd",
    "sg:city":"Raleigh",
    "sg:classifiers":[
        {
            "category":"Education",
            "subcategory":"Special Training",
            "type":"Public Place"
        }
    ],
    "sg:phone":"+1   ",
    "sg:postcode":"27610",
    "sg:province":"NC",
    "wof:name":"Crossword Tutorial Services",
    "wof:placetype":"venue"
},
  "geometry": {"coordinates":[-78.609512,35.78975],"type":"Point"}
}