{
  "type": "Feature",
  "properties": {
    "iso:country":"US",
    "sg:address":"227 W 5th St",
    "sg:city":"Winston Salem",
    "sg:classifiers":[
        {
            "category":"Shopping",
            "subcategory":"Clothing, Apparel, & Fashions",
            "type":"Retail Goods"
        }
    ],
    "sg:phone":"+1 336 721 7788",
    "sg:postcode":"27101",
    "sg:province":"NC",
    "sg:tags":[
        "furnishing"
    ],
    "wof:name":"Is That You Men's Clothing",
    "wof:placetype":"venue"
},
  "geometry": {"coordinates":[-80.24702000000001,36.099784],"type":"Point"}
}