{
  "type": "Feature",
  "properties": {
    "iso:country":"US",
    "sg:address":"1027 16th St NE",
    "sg:city":"Hickory",
    "sg:classifiers":[
        {
            "category":"Insurance",
            "subcategory":"Insurance Agent",
            "type":"Services"
        }
    ],
    "sg:phone":"+1 828 327 0290",
    "sg:postcode":"28601",
    "sg:province":"NC",
    "wof:name":"Allstate Insurance Co",
    "wof:placetype":"venue"
},
  "geometry": {"coordinates":[-81.306288,35.740642],"type":"Point"}
}