{
  "type": "Feature",
  "properties": {
    "addr:full":"7 Appalachian Village Rd Asheville NC 28804",
    "addr:housenumber":"7",
    "addr:postcode":"28804",
    "addr:street":"Appalachian Village Rd",
    "iso:country":"US",
    "sg:address":"7 Appalachian Village Rd",
    "sg:city":"Asheville",
    "sg:classifiers":[
        {
            "category":"Travel",
            "subcategory":"Hotels & Motels",
            "type":"Entertainment"
        },
        {
            "category":"Travel",
            "subcategory":"Campground",
            "type":"Entertainment"
        }
    ],
    "sg:phone":"+1 828 658 8012",
    "sg:postcode":"28804",
    "sg:province":"NC",
    "sg:tags":[
        "house",
        "operation"
    ],
    "wof:name":"Campfire Lodgings Inc",
    "wof:placetype":"venue"
},
  "geometry": {"coordinates":[-82.591899,35.659887],"type":"Point"}
}