{
  "type": "Feature",
  "properties": {
    "addr:full":"117 King St Kernersville NC 27284",
    "addr:housenumber":"117",
    "addr:postcode":"27284",
    "addr:street":"King St",
    "iso:country":"US",
    "sg:address":"117 King St",
    "sg:city":"Kernersville",
    "sg:classifiers":[
        {
            "category":"Building & Trades",
            "subcategory":"Construction",
            "type":"Services"
        }
    ],
    "sg:phone":"+1 336 996 5560",
    "sg:postcode":"27284",
    "sg:province":"NC",
    "wof:name":"Mountain Top Construction Asso",
    "wof:placetype":"venue"
},
  "geometry": {"coordinates":[-80.069216,36.121844],"type":"Point"}
}