{
  "type": "Feature",
  "properties": {
    "addr:full":"806 E Chatham St Newport NC 28570",
    "addr:housenumber":"806",
    "addr:postcode":"28570",
    "addr:street":"E Chatham St",
    "iso:country":"US",
    "sg:address":"806 E Chatham St",
    "sg:city":"Newport",
    "sg:classifiers":[
        {
            "category":"Retail",
            "subcategory":"Auto Repair",
            "type":"Services"
        }
    ],
    "sg:phone":"+1   ",
    "sg:postcode":"28570",
    "sg:province":"NC",
    "sg:tags":[
        "body",
        "automotive",
        "painting"
    ],
    "wof:name":"Bypass Paint & Body",
    "wof:placetype":"venue"
},
  "geometry": {"coordinates":[-76.853425,34.762181],"type":"Point"}
}