{
  "type": "Feature",
  "properties": {
    "addr:full":"1433 N Main St Marion NC 28752",
    "addr:housenumber":"1433",
    "addr:postcode":"28752",
    "addr:street":"N Main St",
    "iso:country":"US",
    "sg:address":"1433 N Main St",
    "sg:city":"Marion",
    "sg:classifiers":[
        {
            "category":"Health Services",
            "subcategory":"Doctor",
            "type":"Services"
        }
    ],
    "sg:phone":"+1 828 652 5291",
    "sg:postcode":"28752",
    "sg:province":"NC",
    "sg:tags":[
        "dentist"
    ],
    "wof:name":"Gary M Grindstaff DDS",
    "wof:placetype":"venue"
},
  "geometry": {"coordinates":[-82.02573700000001,35.69885],"type":"Point"}
}