{
  "type": "Feature",
  "properties": {
    "iso:country":"US",
    "sg:address":"5464 Bass Mountain Rd",
    "sg:city":"Snow Camp",
    "sg:classifiers":[
        {
            "category":"Real Estate",
            "subcategory":"Surveying",
            "type":"Services"
        }
    ],
    "sg:phone":"+1   ",
    "sg:postcode":"27349",
    "sg:province":"NC",
    "wof:name":"Parrish Surveying Inc",
    "wof:placetype":"venue"
},
  "geometry": {"coordinates":[-79.41861299999999,35.946855],"type":"Point"}
}