{
  "type": "Feature",
  "properties": {
    "addr:full":"963 Odell School Rd Concord NC 28027",
    "addr:housenumber":"963",
    "addr:postcode":"28027",
    "addr:street":"Odell School Rd",
    "iso:country":"US",
    "sg:address":"963 Odell School Rd",
    "sg:city":"Concord",
    "sg:classifiers":[
        {
            "category":"Professional",
            "type":"Services"
        }
    ],
    "sg:phone":"+1   ",
    "sg:postcode":"28027",
    "sg:province":"NC",
    "wof:name":"Anthony Productions",
    "wof:placetype":"venue"
},
  "geometry": {"coordinates":[-80.71535900000001,35.427913],"type":"Point"}
}