{
  "type": "Feature",
  "properties": {
    "addr:full":"5415 Ballantyne Commons Pkwy Charlotte NC 28277",
    "addr:housenumber":"5415",
    "addr:postcode":"28277",
    "addr:street":"Ballantyne Commons Pkwy",
    "iso:country":"US",
    "sg:address":"5415 Ballantyne Commons Pkwy",
    "sg:city":"Charlotte",
    "sg:classifiers":[
        {
            "category":"Utilities",
            "subcategory":"Mobile Phone",
            "type":"Services"
        }
    ],
    "sg:phone":"+1 704 845 2132",
    "sg:postcode":"28277",
    "sg:province":"NC",
    "sg:tags":[
        "telephone",
        "cellular"
    ],
    "wof:name":"Verizon Wireless",
    "wof:placetype":"venue"
},
  "geometry": {"coordinates":[-80.773321,35.064438],"type":"Point"}
}