{
  "type": "Feature",
  "properties": {
    "iso:country":"US",
    "sg:address":"1214 Maple Ave",
    "sg:city":"Burlington",
    "sg:classifiers":[
        {
            "category":"Manufacturing",
            "subcategory":"Apparel",
            "type":"Manufacturing & Wholesale Goods"
        }
    ],
    "sg:phone":"+1 336 226 2223",
    "sg:postcode":"27215",
    "sg:province":"NC",
    "sg:tags":[
        "athletic",
        "contract",
        "embroidery"
    ],
    "wof:name":"Piedmont Mills Co",
    "wof:placetype":"venue"
},
  "geometry": {"coordinates":[-79.42876099999999,36.08051],"type":"Point"}
}