{
  "type": "Feature",
  "properties": {
    "addr:full":"6525 Ziegler Ln Charlotte NC 28269",
    "addr:postcode":"6525;28269",
    "addr:street":"Ziegler Ln",
    "iso:country":"US",
    "sg:address":"6525 Ziegler Ln",
    "sg:city":"Charlotte",
    "sg:classifiers":[
        {
            "category":"Building & Trades",
            "subcategory":"Construction",
            "type":"Services"
        }
    ],
    "sg:phone":"+1 704 948 7150",
    "sg:postcode":"28269",
    "sg:province":"NC",
    "sg:tags":[
        "home",
        "builder"
    ],
    "wof:name":"Centex Homes Birchcroft",
    "wof:placetype":"venue"
},
  "geometry": {"coordinates":[-80.793346,35.380246],"type":"Point"}
}