{
  "type": "Feature",
  "properties": {
    "addr:full":"49 Lucerne Ave Asheville NC 28806",
    "addr:housenumber":"49",
    "addr:postcode":"28806",
    "addr:street":"Lucerne Ave",
    "iso:country":"US",
    "sg:address":"49 Lucerne Ave",
    "sg:city":"Asheville",
    "sg:classifiers":[
        {
            "category":"Retail",
            "subcategory":"Animal Services",
            "type":"Services"
        }
    ],
    "sg:phone":"+1 828 252 4516",
    "sg:postcode":"28806",
    "sg:province":"NC",
    "wof:name":"Kitty Camilles Care",
    "wof:placetype":"venue"
},
  "geometry": {"coordinates":[-82.607485,35.582958],"type":"Point"}
}