{
  "type": "Feature",
  "properties": {
    "addr:full":"52 Walnut St Waynesville NC 28786",
    "addr:housenumber":"52",
    "addr:postcode":"28786",
    "addr:street":"Walnut St",
    "iso:country":"US",
    "sg:address":"52 Walnut St",
    "sg:city":"Waynesville",
    "sg:classifiers":[
        {
            "category":"Banks & Credit Unions",
            "subcategory":"Bank",
            "type":"Services"
        }
    ],
    "sg:phone":"+1 828 452 6042",
    "sg:postcode":"28786",
    "sg:province":"NC",
    "sg:tags":[
        "loan",
        "real estate"
    ],
    "wof:name":"Smokey Mountain Mortgage",
    "wof:placetype":"venue"
},
  "geometry": {"coordinates":[-82.985175,35.494408],"type":"Point"}
}