{
  "type": "Feature",
  "properties": {
    "iso:country":"US",
    "sg:address":"925 US Hwy 264",
    "sg:city":"Manteo",
    "sg:classifiers":[
        {
            "category":"Shopping",
            "subcategory":"Clothing, Apparel, & Fashions",
            "type":"Retail Goods"
        }
    ],
    "sg:phone":"+1 252 475 9880",
    "sg:postcode":"27954",
    "sg:province":"NC",
    "wof:name":"Carolina Girls",
    "wof:placetype":"venue"
},
  "geometry": {"coordinates":[-75.66437500000001,35.892822],"type":"Point"}
}