{
  "type": "Feature",
  "properties": {
    "iso:country":"US",
    "sg:address":"4772 State Hwy 54",
    "sg:city":"Graham",
    "sg:classifiers":[
        {
            "category":"Social Services",
            "subcategory":"Child Care",
            "type":"Services"
        }
    ],
    "sg:phone":"+1 336 376 9060",
    "sg:postcode":"27253",
    "sg:province":"NC",
    "sg:tags":[
        "day"
    ],
    "wof:name":"A Storybook Farm Christn Schl",
    "wof:placetype":"venue"
},
  "geometry": {"coordinates":[-79.293773,35.994663],"type":"Point"}
}