{
  "type": "Feature",
  "properties": {
    "iso:country":"US",
    "sg:address":"308 Crutchfield St",
    "sg:city":"Durham",
    "sg:classifiers":[
        {
            "category":"Health Services",
            "subcategory":"Doctor",
            "type":"Services"
        }
    ],
    "sg:phone":"+1   ",
    "sg:postcode":"27704",
    "sg:province":"NC",
    "sg:tags":[
        "medical"
    ],
    "wof:name":"North Carlna Prf Prov Phy Hosp",
    "wof:placetype":"venue"
},
  "geometry": {"coordinates":[-78.903966,36.038964],"type":"Point"}
}