{
  "type": "Feature",
  "properties": {
    "iso:country":"US",
    "sg:address":"4210 Amesbury Ln",
    "sg:city":"Durham",
    "sg:classifiers":[
        {
            "category":"Bus Charters",
            "type":"Transportation"
        }
    ],
    "sg:phone":"+1 919 490 3166",
    "sg:postcode":"27707",
    "sg:province":"NC",
    "sg:tags":[
        "rental"
    ],
    "sg:website":"www.usaluxurytours.com",
    "wof:name":"USA Luxury Tours",
    "wof:placetype":"venue"
},
  "geometry": {"coordinates":[-78.96595600000001,35.934978],"type":"Point"}
}