{
  "type": "Feature",
  "properties": {
    "iso:country":"US",
    "sg:address":"523 S 17th St",
    "sg:city":"Wilmington",
    "sg:classifiers":[
        {
            "category":"Government",
            "subcategory":"Office",
            "type":"Public Place"
        }
    ],
    "sg:phone":"+1 910 762 7611",
    "sg:postcode":"28401",
    "sg:province":"NC",
    "wof:name":"New Hanover Cnty Alcoholic Brd",
    "wof:placetype":"venue"
},
  "geometry": {"coordinates":[-77.92674,34.230418],"type":"Point"}
}