{
  "type": "Feature",
  "properties": {
    "iso:country":"US",
    "sg:address":"7125 Brecken Ridge Ave",
    "sg:city":"Raleigh",
    "sg:classifiers":[
        {
            "category":"Shopping",
            "subcategory":"Crafts & Fabrics",
            "type":"Retail Goods"
        }
    ],
    "sg:phone":"+1 919 845 1506",
    "sg:postcode":"27615",
    "sg:province":"NC",
    "sg:tags":[
        "sewing"
    ],
    "wof:name":"Red Oak Fabrics",
    "wof:placetype":"venue"
},
  "geometry": {"coordinates":[-78.631445,35.872892],"type":"Point"}
}