{
  "type": "Feature",
  "properties": {
    "iso:country":"US",
    "sg:address":"505 Gooseneck Dr",
    "sg:city":"Cary",
    "sg:classifiers":[
        {
            "category":"Building & Trades",
            "subcategory":"Construction",
            "type":"Services"
        }
    ],
    "sg:phone":"+1 919 319 6355",
    "sg:postcode":"27513",
    "sg:province":"NC",
    "sg:tags":[
        "house"
    ],
    "wof:name":"Aiello Builders Inc",
    "wof:placetype":"venue"
},
  "geometry": {"coordinates":[-78.785364,35.811314],"type":"Point"}
}