{
  "type": "Feature",
  "properties": {
    "iso:country":"US",
    "sg:address":"500 Maple Ave",
    "sg:city":"South Boston",
    "sg:classifiers":[
        {
            "category":"Government",
            "subcategory":"Office",
            "type":"Public Place"
        }
    ],
    "sg:phone":"+1 434 575 4267",
    "sg:postcode":"24592",
    "sg:province":"NC",
    "sg:tags":[
        "village"
    ],
    "wof:name":"Sewage Treatment Plant",
    "wof:placetype":"venue"
},
  "geometry": {"coordinates":[-78.88239799999999,36.696034],"type":"Point"}
}