{
  "type": "Feature",
  "properties": {
    "addr:full":"908 S Washington St Greenville NC 27834",
    "addr:housenumber":"908",
    "addr:postcode":"27834",
    "addr:street":"S Washington St",
    "iso:country":"US",
    "sg:address":"908 S Washington St",
    "sg:city":"Greenville",
    "sg:classifiers":[
        {
            "category":"Food & Beverages",
            "subcategory":"Meat & Fish",
            "type":"Retail Goods"
        }
    ],
    "sg:phone":"+1 252 752 2332",
    "sg:postcode":"27834",
    "sg:province":"NC",
    "wof:name":"Evans Seafood Market",
    "wof:placetype":"venue"
},
  "geometry": {"coordinates":[-77.37520499999999,35.60719],"type":"Point"}
}