{
  "type": "Feature",
  "properties": {
    "addr:full":"13140 Andrew Jackson Hwy Laurinburg NC 28352",
    "addr:housenumber":"13140",
    "addr:postcode":"28352",
    "addr:street":"Andrew Jackson Hwy",
    "iso:country":"US",
    "sg:address":"13140 Andrew Jackson Hwy",
    "sg:city":"Laurinburg",
    "sg:classifiers":[
        {
            "category":"Utilities",
            "type":"Services"
        }
    ],
    "sg:phone":"+1 910 266 9274",
    "sg:postcode":"28352",
    "sg:province":"NC",
    "sg:tags":[
        "building",
        "sanitary",
        "maintenance"
    ],
    "wof:name":"Carolina Pressure Wash",
    "wof:placetype":"venue"
},
  "geometry": {"coordinates":[-79.49607399999999,34.782644],"type":"Point"}
}