{
  "type": "Feature",
  "properties": {
    "iso:country":"US",
    "sg:address":"16830 Kenton Dr",
    "sg:city":"Huntersville",
    "sg:classifiers":[
        {
            "category":"Travel",
            "subcategory":"Hotels & Motels",
            "type":"Entertainment"
        }
    ],
    "sg:phone":"+1 704 584 0000",
    "sg:postcode":"28078",
    "sg:province":"NC",
    "sg:website":"http://marriott.com/CLTRN",
    "wof:name":"Residence Inn by Marriott Charlotte Lake Norman",
    "wof:placetype":"venue"
},
  "geometry": {"coordinates":[-80.89027299999999,35.445061],"type":"Point"}
}