{
  "type": "Feature",
  "properties": {
    "addr:full":"124 Barbecue Church Rd Sanford NC 27332",
    "addr:housenumber":"124",
    "addr:postcode":"27332",
    "addr:street":"Church Rd",
    "iso:country":"US",
    "sg:address":"124 Barbecue Church Rd",
    "sg:city":"Sanford",
    "sg:classifiers":[
        {
            "category":"Organizations",
            "subcategory":"Religious Organization",
            "type":"Services"
        }
    ],
    "sg:phone":"+1   ",
    "sg:postcode":"27332",
    "sg:province":"NC",
    "wof:name":"Barbecue Presbyterian Church",
    "wof:placetype":"venue"
},
  "geometry": {"coordinates":[-79.045368,35.338268],"type":"Point"}
}