{
  "type": "Feature",
  "properties": {
    "addr:full":"6675 Falls of Neuse Rd Raleigh NC 27615",
    "addr:housenumber":"6675",
    "addr:postcode":"27615",
    "addr:street":"Falls Of Neuse Rd",
    "iso:country":"US",
    "sg:address":"6675 Falls of Neuse Rd",
    "sg:city":"Raleigh",
    "sg:classifiers":[
        {
            "category":"Restaurant",
            "type":"Food & Drink"
        }
    ],
    "sg:menulink":"http://www.allmenus.com/nc/neuse/200019-stonewoods-restaurant/menu/",
    "sg:phone":"+1 919 847 5304",
    "sg:postcode":"27615",
    "sg:province":"NC",
    "sg:tags":[
        "new",
        "american"
    ],
    "wof:name":"Stonewoods Restaurant",
    "wof:placetype":"venue"
},
  "geometry": {"coordinates":[-78.622924,35.874679],"type":"Point"}
}