{
  "type": "Feature",
  "properties": {
    "addr:full":"1819 Poole Rd Raleigh NC 27610",
    "addr:housenumber":"1819",
    "addr:postcode":"27610",
    "addr:street":"Poole Rd",
    "iso:country":"US",
    "sg:address":"1819 Poole Rd",
    "sg:city":"Raleigh",
    "sg:classifiers":[
        {
            "category":"Retail",
            "subcategory":"Auto Repair",
            "type":"Services"
        }
    ],
    "sg:phone":"+1 919 836 2230",
    "sg:postcode":"27610",
    "sg:province":"NC",
    "sg:tags":[
        "repairing",
        "automobile"
    ],
    "sg:website":"www.colonytire.com",
    "wof:name":"Colony Tire",
    "wof:placetype":"venue"
},
  "geometry": {"coordinates":[-78.611785,35.776797],"type":"Point"}
}