{
  "type": "Feature",
  "properties": {
    "iso:country":"US",
    "sg:address":"1109 Cross Link Rd",
    "sg:city":"Raleigh",
    "sg:classifiers":[
        {
            "category":"Professional",
            "subcategory":"Management & Consulting",
            "type":"Services"
        },
        {
            "category":"Social Services",
            "type":"Services"
        }
    ],
    "sg:phone":"+1 919 833 7611",
    "sg:postcode":"27610",
    "sg:province":"NC",
    "sg:tags":[
        "consultant",
        "resource",
        "human"
    ],
    "wof:name":"Joseph's Hand",
    "wof:placetype":"venue"
},
  "geometry": {"coordinates":[-78.61718,35.751379],"type":"Point"}
}