{
  "type": "Feature",
  "properties": {
    "iso:country":"US",
    "sg:address":"4221 Ivy Hill Rd",
    "sg:city":"Raleigh",
    "sg:classifiers":[
        {
            "category":"Local Transit",
            "type":"Transportation"
        }
    ],
    "sg:phone":"+1 919 875 1515",
    "sg:postcode":"27616",
    "sg:province":"NC",
    "sg:tags":[
        "limousine"
    ],
    "wof:name":"All Events Limo & Transport",
    "wof:placetype":"venue"
},
  "geometry": {"coordinates":[-78.56617199999999,35.836946],"type":"Point"}
}