{
  "type": "Feature",
  "properties": {
    "iso:country":"US",
    "sg:address":"328 Mulberry St SW",
    "sg:city":"Lenoir",
    "sg:classifiers":[
        {
            "category":"Health Services",
            "subcategory":"Doctor",
            "type":"Services"
        }
    ],
    "sg:phone":"+1 828 327 6433",
    "sg:postcode":"28645",
    "sg:province":"NC",
    "sg:tags":[
        "physician",
        "surgeon"
    ],
    "wof:name":"Catawba Valley Neurosurgical",
    "wof:placetype":"venue"
},
  "geometry": {"coordinates":[-81.536467,35.910825],"type":"Point"}
}