{
  "type": "Feature",
  "properties": {
    "iso:country":"US",
    "sg:address":"2231 E Millbrook Rd",
    "sg:city":"Raleigh",
    "sg:classifiers":[
        {
            "category":"Insurance",
            "subcategory":"Insurance Agent",
            "type":"Services"
        },
        {
            "category":"Insurance",
            "subcategory":"Hazard Insurance",
            "type":"Services"
        },
        {
            "category":"Insurance",
            "subcategory":"Title Insurance",
            "type":"Services"
        },
        {
            "category":"Insurance",
            "subcategory":"Life Insurance",
            "type":"Services"
        }
    ],
    "sg:phone":"+1 919 871 6323",
    "sg:postcode":"27604",
    "sg:province":"NC",
    "sg:tags":[
        "business",
        "auto",
        "commercial",
        "homeowner",
        "motorcycle",
        "renter"
    ],
    "wof:name":"Allstate Insurance Company - Darrell Brown",
    "wof:placetype":"venue"
},
  "geometry": {"coordinates":[-78.597488,35.848289],"type":"Point"}
}