{
  "type": "Feature",
  "properties": {
    "iso:country":"US",
    "sg:address":"515 N Church St",
    "sg:city":"Charlotte",
    "sg:classifiers":[
        {
            "category":"Real Estate",
            "subcategory":"Real Estate Operator",
            "type":"Services"
        }
    ],
    "sg:phone":"+1 704 372 5082",
    "sg:postcode":"28202",
    "sg:province":"NC",
    "sg:tags":[
        "apartment"
    ],
    "sg:website":"www.talleyproperties.com",
    "wof:name":"Fredrick Place Apartments",
    "wof:placetype":"venue"
},
  "geometry": {"coordinates":[-80.838893,35.231881],"type":"Point"}
}