{
  "type": "Feature",
  "properties": {
    "iso:country":"US",
    "sg:address":"3948 Westpoint Blvd",
    "sg:city":"Winston Salem",
    "sg:classifiers":[
        {
            "category":"Manufacturing",
            "subcategory":"Electronics",
            "type":"Manufacturing & Wholesale Goods"
        },
        {
            "category":"Manufacturing",
            "subcategory":"Tools & Machinery",
            "type":"Manufacturing & Wholesale Goods"
        }
    ],
    "sg:phone":"+1 336 768 6447",
    "sg:postcode":"27103",
    "sg:province":"NC",
    "sg:tags":[
        "physician",
        "filtration",
        "for",
        "mfg",
        "medical",
        "component",
        "devices",
        "surgeon"
    ],
    "sg:website":"www.lydall.com",
    "wof:name":"Charter Medical Ltd",
    "wof:placetype":"venue"
},
  "geometry": {"coordinates":[-80.31854300000001,36.038279],"type":"Point"}
}