{
  "type": "Feature",
  "properties": {
    "addr:full":"10905 Mill Rd Linden NC 28356",
    "addr:housenumber":"10905",
    "addr:postcode":"28356",
    "addr:street":"Mill Rd",
    "iso:country":"US",
    "sg:address":"10905 Mill Rd",
    "sg:city":"Linden",
    "sg:classifiers":[
        {
            "category":"Autos & Motor Vehicles",
            "subcategory":"Fuel & Gas Station",
            "type":"Retail Goods"
        }
    ],
    "sg:phone":"+1 910 980 0123",
    "sg:postcode":"28356",
    "sg:province":"NC",
    "sg:tags":[
        "oil"
    ],
    "wof:name":"Linden Oil Svc",
    "wof:placetype":"venue"
},
  "geometry": {"coordinates":[-78.741685,35.258859],"type":"Point"}
}