{
  "type": "Feature",
  "properties": {
    "addr:full":"2200 International Dr Statesville NC 28625",
    "addr:housenumber":"2200",
    "addr:postcode":"28625",
    "addr:street":"International Dr",
    "iso:country":"US",
    "sg:address":"2200 International Dr",
    "sg:city":"Statesville",
    "sg:classifiers":[
        {
            "category":"Retail",
            "subcategory":"Auto Rental",
            "type":"Services"
        }
    ],
    "sg:phone":"+1 704 871 8640",
    "sg:postcode":"28625",
    "sg:province":"NC",
    "sg:tags":[
        "renting",
        "truck",
        "leasing"
    ],
    "wof:name":"Logistic Leasing",
    "wof:placetype":"venue"
},
  "geometry": {"coordinates":[-80.850813,35.810089],"type":"Point"}
}