{
  "type": "Feature",
  "properties": {
    "iso:country":"US",
    "sg:address":"415 Grimes Rd",
    "sg:city":"Washington",
    "sg:classifiers":[
        {
            "category":"Freight",
            "type":"Transportation"
        }
    ],
    "sg:phone":"+1 252 946 3955",
    "sg:postcode":"27889",
    "sg:province":"NC",
    "sg:tags":[
        "trucking"
    ],
    "wof:name":"Campbell Trucking Co",
    "wof:placetype":"venue"
},
  "geometry": {"coordinates":[-77.077223,35.564794],"type":"Point"}
}