{
  "type": "Feature",
  "properties": {
    "addr:full":"270 Nottingham Dr Cary NC 27511",
    "addr:housenumber":"270",
    "addr:postcode":"27511",
    "addr:street":"Nottingham Dr",
    "iso:country":"US",
    "sg:address":"270 Nottingham Dr",
    "sg:city":"Cary",
    "sg:classifiers":[
        {
            "category":"Food & Beverages",
            "subcategory":"Groceries & Convenience Stores",
            "type":"Retail Goods"
        }
    ],
    "sg:phone":"+1 919 481 0321",
    "sg:postcode":"27511",
    "sg:province":"NC",
    "wof:name":"Olive Tree Market",
    "wof:placetype":"venue"
},
  "geometry": {"coordinates":[-78.742149,35.767627],"type":"Point"}
}