{
  "type": "Feature",
  "properties": {
    "addr:full":"2108 N New River Dr Holly Ridge NC 28445",
    "addr:housenumber":"2108",
    "addr:postcode":"28445",
    "addr:street":"N New River Dr",
    "iso:country":"US",
    "sg:address":"2108 N New River Dr",
    "sg:city":"Holly Ridge",
    "sg:classifiers":[
        {
            "category":"Banks & Credit Unions",
            "subcategory":"Bank",
            "type":"Services"
        }
    ],
    "sg:phone":"+1 910 328 5967",
    "sg:postcode":"28445",
    "sg:province":"NC",
    "sg:tags":[
        "management",
        "broker",
        "real estate",
        "home",
        "property"
    ],
    "wof:name":"First Coast Group Inc",
    "wof:placetype":"venue"
},
  "geometry": {"coordinates":[-77.51204799999999,34.446263],"type":"Point"}
}