{
  "type": "Feature",
  "properties": {
    "iso:country":"US",
    "sg:address":"4310 Shipyard Blvd",
    "sg:city":"Wilmington",
    "sg:classifiers":[
        {
            "category":"Personal",
            "subcategory":"Barber",
            "type":"Services"
        }
    ],
    "sg:phone":"+1 910 799 5029",
    "sg:postcode":"28403",
    "sg:province":"NC",
    "wof:name":"About Your Hair",
    "wof:placetype":"venue"
},
  "geometry": {"coordinates":[-77.89242299999999,34.198586],"type":"Point"}
}