{
  "type": "Feature",
  "properties": {
    "iso:country":"US",
    "sg:address":"6214 Larue Ct",
    "sg:city":"Fayetteville",
    "sg:classifiers":[
        {
            "category":"Social Services",
            "subcategory":"Child Care",
            "type":"Services"
        }
    ],
    "sg:phone":"+1   ",
    "sg:postcode":"28303",
    "sg:province":"NC",
    "sg:tags":[
        "day"
    ],
    "wof:name":"Birds Child Care Center Inc",
    "wof:placetype":"venue"
},
  "geometry": {"coordinates":[-78.99584,35.089765],"type":"Point"}
}