{
  "type": "Feature",
  "properties": {
    "addr:full":"106 Taxidermy Rd Statesville NC 28625",
    "addr:housenumber":"106",
    "addr:postcode":"28625",
    "addr:street":"Taxidermy Rd",
    "iso:country":"US",
    "sg:address":"106 Taxidermy Rd",
    "sg:city":"Statesville",
    "sg:classifiers":[
        {
            "category":"Building & Trades",
            "subcategory":"Cleaning & Sanitation",
            "type":"Services"
        }
    ],
    "sg:phone":"+1 704 873 3121",
    "sg:postcode":"28625",
    "sg:province":"NC",
    "sg:tags":[
        "janitor"
    ],
    "wof:name":"Quality Janitorial Svc",
    "wof:placetype":"venue"
},
  "geometry": {"coordinates":[-80.760144,35.835296],"type":"Point"}
}