{
  "type": "Feature",
  "properties": {
    "addr:full":"2707 Meridian Dr Greenville NC 27834",
    "addr:housenumber":"2707",
    "addr:postcode":"27834",
    "addr:street":"Meridian Dr",
    "iso:country":"US",
    "sg:address":"2707 Meridian Dr",
    "sg:city":"Greenville",
    "sg:classifiers":[
        {
            "category":"Real Estate",
            "subcategory":"Real Estate Operator",
            "type":"Services"
        }
    ],
    "sg:phone":"+1 252 321 1948",
    "sg:postcode":"27834",
    "sg:province":"NC",
    "sg:tags":[
        "building",
        "apartment"
    ],
    "wof:name":"Meridian Park",
    "wof:placetype":"venue"
},
  "geometry": {"coordinates":[-77.399193,35.589008],"type":"Point"}
}