{
  "type": "Feature",
  "properties": {
    "addr:full":"485 State Hwy 24 87 Cameron NC 28326",
    "addr:housenumber":"485;87",
    "addr:postcode":"28326",
    "addr:street":"State Hwy 24",
    "iso:country":"US",
    "sg:address":"485 State Hwy 24 87",
    "sg:city":"Cameron",
    "sg:classifiers":[
        {
            "category":"Building & Trades",
            "subcategory":"Landscaping Services",
            "type":"Services"
        }
    ],
    "sg:phone":"+1 919 499 1803",
    "sg:postcode":"28326",
    "sg:province":"NC",
    "sg:tags":[
        "landscape",
        "contractor"
    ],
    "wof:name":"Services Unlimited",
    "wof:placetype":"venue"
},
  "geometry": {"coordinates":[-79.05346400000001,35.265236],"type":"Point"}
}