{
  "type": "Feature",
  "properties": {
    "addr:full":"108 S Market St Madison NC 27025",
    "addr:housenumber":"108",
    "addr:postcode":"27025",
    "addr:street":"S Market St",
    "iso:country":"US",
    "sg:address":"108 S Market St",
    "sg:city":"Madison",
    "sg:classifiers":[
        {
            "category":"Organizations",
            "subcategory":"Membership Organization",
            "type":"Services"
        }
    ],
    "sg:phone":"+1 336 427 5920",
    "sg:postcode":"27025",
    "sg:province":"NC",
    "sg:tags":[
        "science",
        "reading",
        "christian",
        "rooms"
    ],
    "wof:name":"Christian Life Books Music",
    "wof:placetype":"venue"
},
  "geometry": {"coordinates":[-79.959701,36.387438],"type":"Point"}
}