{
  "type": "Feature",
  "properties": {
    "iso:country":"US",
    "sg:address":"1712 McAllister Dr",
    "sg:city":"Charlotte",
    "sg:classifiers":[
        {
            "category":"Shopping",
            "subcategory":"Gifts & Souvenirs",
            "type":"Retail Goods"
        }
    ],
    "sg:phone":"+1 704 605 5945",
    "sg:postcode":"28216",
    "sg:province":"NC",
    "sg:tags":[
        "retailer",
        "miscellaneous"
    ],
    "wof:name":"Unique Views Inc",
    "wof:placetype":"venue"
},
  "geometry": {"coordinates":[-80.86144400000001,35.281168],"type":"Point"}
}