{
  "type": "Feature",
  "properties": {
    "iso:country":"US",
    "sg:address":"208 New St",
    "sg:city":"New Bern",
    "sg:classifiers":[
        {
            "category":"Professional",
            "subcategory":"Lawyer & Legal Services",
            "type":"Services"
        }
    ],
    "sg:phone":"+1   ",
    "sg:postcode":"28560",
    "sg:province":"NC",
    "wof:name":"Thomas E Harris Atty",
    "wof:placetype":"venue"
},
  "geometry": {"coordinates":[-77.03606000000001,35.109215],"type":"Point"}
}