{
  "type": "Feature",
  "properties": {
    "addr:full":"2806 Crabtree St S Wilson NC 27893",
    "addr:housenumber":"2806",
    "addr:postcode":"27893",
    "addr:street":"Crabtree St S",
    "iso:country":"US",
    "sg:address":"2806 Crabtree St S",
    "sg:city":"Wilson",
    "sg:classifiers":[
        {
            "category":"Autos & Motor Vehicles",
            "subcategory":"Auto Supplies",
            "type":"Retail Goods"
        },
        {
            "category":"Autos & Motor Vehicles",
            "subcategory":"Fuel & Gas Station",
            "type":"Retail Goods"
        },
        {
            "category":"Building & Trades",
            "subcategory":"Locksmith",
            "type":"Services"
        },
        {
            "category":"Transit Center",
            "subcategory":"Freight",
            "type":"Transportation"
        },
        {
            "category":"Freight",
            "type":"Transportation"
        },
        {
            "category":"Retail",
            "subcategory":"Auto Repair",
            "type":"Services"
        },
        {
            "category":"Autos & Motor Vehicles",
            "subcategory":"Automobile Sales",
            "type":"Retail Goods"
        },
        {
            "category":"Wholesale",
            "subcategory":"Scrap",
            "type":"Manufacturing & Wholesale Goods"
        },
        {
            "category":"Personal",
            "type":"Services"
        }
    ],
    "sg:phone":"+1 252 237 4256",
    "sg:postcode":"27893",
    "sg:province":"NC",
    "sg:tags":[
        "trucking-heavy",
        "tire",
        "wrecking",
        "lock",
        "hauling",
        "trucking",
        "truck",
        "towing",
        "salvage",
        "road",
        "service-automotive"
    ],
    "wof:name":"Mangum's Towing & Recovery",
    "wof:placetype":"venue"
},
  "geometry": {"coordinates":[-77.938236,35.693173],"type":"Point"}
}