{
  "type": "Feature",
  "properties": {
    "addr:full":"904 Norwalk St Greensboro NC 27407",
    "addr:housenumber":"904",
    "addr:postcode":"27407",
    "addr:street":"Norwalk St",
    "iso:country":"US",
    "sg:address":"904 Norwalk St",
    "sg:city":"Greensboro",
    "sg:classifiers":[
        {
            "category":"Insurance",
            "subcategory":"Insurance Agent",
            "type":"Services"
        }
    ],
    "sg:phone":"+1 336 218 8007",
    "sg:postcode":"27407",
    "sg:province":"NC",
    "wof:name":"Burgess-Smith Agency",
    "wof:placetype":"venue"
},
  "geometry": {"coordinates":[-79.871854,36.055258],"type":"Point"}
}