{
  "type": "Feature",
  "properties": {
    "addr:full":"2405 Newberry St Charlotte NC 28208",
    "addr:housenumber":"2405",
    "addr:postcode":"28208",
    "addr:street":"Newberry St",
    "iso:country":"US",
    "sg:address":"2405 Newberry St",
    "sg:city":"Charlotte",
    "sg:classifiers":[
        {
            "category":"Professional",
            "subcategory":"Business Services",
            "type":"Services"
        }
    ],
    "sg:phone":"+1 704 394 5542",
    "sg:postcode":"28208",
    "sg:province":"NC",
    "sg:tags":[
        "repossessing"
    ],
    "wof:name":"Home Recovery Agency",
    "wof:placetype":"venue"
},
  "geometry": {"coordinates":[-80.93019700000001,35.230319],"type":"Point"}
}