{
  "type": "Feature",
  "properties": {
    "iso:country":"US",
    "sg:address":"1945 Skibo Rd",
    "sg:city":"Fayetteville",
    "sg:classifiers":[
        {
            "category":"Autos & Motor Vehicles",
            "subcategory":"Automobile Sales",
            "type":"Retail Goods"
        }
    ],
    "sg:phone":"+1 910 860 9300",
    "sg:postcode":"28314",
    "sg:province":"NC",
    "sg:website":"www.flowauto.com",
    "wof:name":"Flow Buick Oldsmobile",
    "wof:placetype":"venue"
},
  "geometry": {"coordinates":[-78.967495,35.065377],"type":"Point"}
}