{
  "type": "Feature",
  "properties": {
    "addr:full":"5028 Watering Pond Rd Pink Hill NC 28572",
    "addr:housenumber":"5028",
    "addr:postcode":"28572",
    "addr:street":"Watering Pond Rd",
    "iso:country":"US",
    "sg:address":"5028 Watering Pond Rd",
    "sg:city":"Pink Hill",
    "sg:phone":"+1 252 568 3220",
    "sg:postcode":"28572",
    "sg:province":"NC",
    "sg:tags":[
        "farm",
        "corn",
        "soybean"
    ],
    "wof:name":"Howard Hayward",
    "wof:placetype":"venue"
},
  "geometry": {"coordinates":[-77.688335,35.061146],"type":"Point"}
}