{
  "type": "Feature",
  "properties": {
    "iso:country":"US",
    "sg:address":"623 1st St SE",
    "sg:city":"Hickory",
    "sg:classifiers":[
        {
            "category":"Retail",
            "subcategory":"Car Wash",
            "type":"Services"
        }
    ],
    "sg:phone":"+1   ",
    "sg:postcode":"28602",
    "sg:province":"NC",
    "sg:tags":[
        "carwash"
    ],
    "wof:name":"Clean Car Concepts",
    "wof:placetype":"venue"
},
  "geometry": {"coordinates":[-81.337093,35.725488],"type":"Point"}
}