{
  "type": "Feature",
  "properties": {
    "addr:full":"923 Franklin St Durham NC 27701",
    "addr:housenumber":"923",
    "addr:postcode":"27701",
    "addr:street":"Franklin St",
    "iso:country":"US",
    "sg:address":"923 Franklin St",
    "sg:city":"Durham",
    "sg:classifiers":[
        {
            "category":"Manufacturing",
            "subcategory":"Retail Goods",
            "type":"Manufacturing & Wholesale Goods"
        }
    ],
    "sg:phone":"+1 919 321 0001",
    "sg:postcode":"27701",
    "sg:province":"NC",
    "sg:tags":[
        "assembly",
        "fabricating"
    ],
    "sg:website":"www.cersolutions.com",
    "wof:name":"Valcor Inc",
    "wof:placetype":"venue"
},
  "geometry": {"coordinates":[-78.889437,35.990456],"type":"Point"}
}