{
  "type": "Feature",
  "properties": {
    "iso:country":"US",
    "sg:address":"1730 Shoal Creek Rd",
    "sg:city":"Whittier",
    "sg:classifiers":[
        {
            "category":"Retail",
            "subcategory":"Auto Repair",
            "type":"Services"
        }
    ],
    "sg:phone":"+1 828 497 7615",
    "sg:postcode":"28789",
    "sg:province":"NC",
    "sg:tags":[
        "repairing",
        "automobile"
    ],
    "wof:name":"Floyd's Auto Repair",
    "wof:placetype":"venue"
},
  "geometry": {"coordinates":[-83.341381,35.44014],"type":"Point"}
}