{
  "type": "Feature",
  "properties": {
    "addr:full":"8532 Piccone Brook Ln Charlotte NC 28216",
    "addr:postcode":"8532;28216",
    "addr:street":"Piccone Brook Ln",
    "iso:country":"US",
    "sg:address":"8532 Piccone Brook Ln",
    "sg:city":"Charlotte",
    "sg:classifiers":[
        {
            "category":"Building & Trades",
            "subcategory":"Construction",
            "type":"Services"
        }
    ],
    "sg:phone":"+1 704 393 1296",
    "sg:postcode":"28216",
    "sg:province":"NC",
    "sg:tags":[
        "hanging",
        "contractor"
    ],
    "wof:name":"Reeps Contract PTG",
    "wof:placetype":"venue"
},
  "geometry": {"coordinates":[-80.874835,35.346847],"type":"Point"}
}