{
  "type": "Feature",
  "properties": {
    "iso:country":"US",
    "sg:address":"701 Tarboro St W",
    "sg:city":"Wilson",
    "sg:classifiers":[
        {
            "category":"Organizations",
            "subcategory":"Religious Organization",
            "type":"Services"
        }
    ],
    "sg:phone":"+1 252 237 6608",
    "sg:postcode":"27893",
    "sg:province":"NC",
    "sg:tags":[
        "church"
    ],
    "wof:name":"Wilson Community Church",
    "wof:placetype":"venue"
},
  "geometry": {"coordinates":[-77.922409,35.721767],"type":"Point"}
}