{
  "type": "Feature",
  "properties": {
    "iso:country":"US",
    "sg:address":"327 Montrose Dr",
    "sg:city":"Greensboro",
    "sg:classifiers":[
        {
            "category":"Real Estate",
            "subcategory":"Real Estate Operator",
            "type":"Services"
        }
    ],
    "sg:phone":"+1 336 854 2459",
    "sg:postcode":"27407",
    "sg:province":"NC",
    "sg:tags":[
        "apartment"
    ],
    "wof:name":"Willow Run Apts",
    "wof:placetype":"venue"
},
  "geometry": {"coordinates":[-79.865735,36.075361],"type":"Point"}
}