{
  "type": "Feature",
  "properties": {
    "iso:country":"US",
    "sg:address":"801 Friendly Center Rd",
    "sg:city":"Greensboro",
    "sg:classifiers":[
        {
            "category":"Food & Beverages",
            "subcategory":"Specialty",
            "type":"Retail Goods"
        },
        {
            "category":"Home & Garden",
            "subcategory":"Home Furnishings",
            "type":"Retail Goods"
        }
    ],
    "sg:phone":"+1 336 299 9767",
    "sg:postcode":"27408",
    "sg:province":"NC",
    "sg:tags":[
        "gourmet",
        "shop"
    ],
    "sg:website":"www.extraingredient.com",
    "wof:name":"Extra Ingredient Inc",
    "wof:placetype":"venue"
},
  "geometry": {"coordinates":[-79.829444,36.087176],"type":"Point"}
}