{
  "type": "Feature",
  "properties": {
    "addr:full":"4719 Page Mill Ln Charlotte NC 28270",
    "addr:housenumber":"4719",
    "addr:postcode":"28270",
    "addr:street":"Page Mill Ln",
    "iso:country":"US",
    "sg:address":"4719 Page Mill Ln",
    "sg:city":"Charlotte",
    "sg:classifiers":[
        {
            "category":"Building & Trades",
            "subcategory":"Construction",
            "type":"Services"
        }
    ],
    "sg:phone":"+1 704 846 2181",
    "sg:postcode":"28270",
    "sg:province":"NC",
    "sg:tags":[
        "home",
        "builder"
    ],
    "wof:name":"Portrait Homes",
    "wof:placetype":"venue"
},
  "geometry": {"coordinates":[-80.764707,35.063911],"type":"Point"}
}