{
  "type": "Feature",
  "properties": {
    "addr:full":"107 Barnett St East Flat Rock NC 28726",
    "addr:housenumber":"107",
    "addr:postcode":"28726",
    "addr:street":"Barnett St",
    "iso:country":"US",
    "sg:address":"107 Barnett St",
    "sg:city":"East Flat Rock",
    "sg:classifiers":[
        {
            "category":"Building & Trades",
            "subcategory":"Landscaping Services",
            "type":"Services"
        }
    ],
    "sg:phone":"+1 828 692 0339",
    "sg:postcode":"28726",
    "sg:province":"NC",
    "wof:name":"Mc Calls Lawn Landscaping & T",
    "wof:placetype":"venue"
},
  "geometry": {"coordinates":[-82.408163,35.269327],"type":"Point"}
}