{
  "type": "Feature",
  "properties": {
    "iso:country":"US",
    "sg:address":"1810 N Cedar St",
    "sg:city":"Lumberton",
    "sg:classifiers":[
        {
            "category":"Organizations",
            "subcategory":"Religious Organization",
            "type":"Services"
        }
    ],
    "sg:phone":"+1 910 738 4640",
    "sg:postcode":"28358",
    "sg:province":"NC",
    "wof:name":"Hote Ministries Of Lumber",
    "wof:placetype":"venue"
},
  "geometry": {"coordinates":[-79.003139,34.630332],"type":"Point"}
}