{
  "type": "Feature",
  "properties": {
    "iso:country":"US",
    "sg:address":"12704 Oldehurst Pl",
    "sg:city":"Charlotte",
    "sg:classifiers":[
        {
            "category":"Shopping",
            "type":"Retail Goods"
        }
    ],
    "sg:phone":"+1 704 549 5748",
    "sg:postcode":"28262",
    "sg:province":"NC",
    "sg:tags":[
        "product",
        "wood"
    ],
    "wof:name":"East Wood Homes",
    "wof:placetype":"venue"
},
  "geometry": {"coordinates":[-80.698391,35.344421],"type":"Point"}
}