{
  "type": "Feature",
  "properties": {
    "addr:full":"6220 Troy Caveness Rd Ramseur NC 27316",
    "addr:housenumber":"6220",
    "addr:postcode":"27316",
    "addr:street":"Troy Caveness Rd",
    "iso:country":"US",
    "sg:address":"6220 Troy Caveness Rd",
    "sg:city":"Ramseur",
    "sg:phone":"+1 336 824 5178",
    "sg:postcode":"27316",
    "sg:province":"NC",
    "sg:tags":[
        "farm",
        "tobacco"
    ],
    "wof:name":"Ritchie Kidd",
    "wof:placetype":"venue"
},
  "geometry": {"coordinates":[-79.612566,35.674042],"type":"Point"}
}