{
  "type": "Feature",
  "properties": {
    "iso:country":"US",
    "sg:address":"7898 Rhodhiss Rd",
    "sg:city":"Connellys Springs",
    "sg:classifiers":[
        {
            "category":"Food & Beverages",
            "subcategory":"Groceries & Convenience Stores",
            "type":"Retail Goods"
        }
    ],
    "sg:phone":"+1 828 879 8133",
    "sg:postcode":"28612",
    "sg:province":"NC",
    "sg:tags":[
        "a",
        "convenient",
        "operates"
    ],
    "wof:name":"Handy Mart",
    "wof:placetype":"venue"
},
  "geometry": {"coordinates":[-81.47393,35.753605],"type":"Point"}
}