{
  "type": "Feature",
  "properties": {
    "addr:full":"315 W Bridgers St Burgaw NC 28425",
    "addr:housenumber":"315",
    "addr:postcode":"28425",
    "addr:street":"W Bridgers St",
    "iso:country":"US",
    "sg:address":"315 W Bridgers St",
    "sg:city":"Burgaw",
    "sg:classifiers":[
        {
            "category":"Professional",
            "type":"Services"
        }
    ],
    "sg:phone":"+1 910 259 9297",
    "sg:postcode":"28425",
    "sg:province":"NC",
    "wof:name":"Gary Frost",
    "wof:placetype":"venue"
},
  "geometry": {"coordinates":[-77.930786,34.5517],"type":"Point"}
}