{
  "type": "Feature",
  "properties": {
    "iso:country":"US",
    "sg:address":"32 Cardinal Dr",
    "sg:city":"Brevard",
    "sg:classifiers":[
        {
            "category":"Real Estate",
            "subcategory":"Real Estate Operator",
            "type":"Services"
        }
    ],
    "sg:phone":"+1 828 883 8934",
    "sg:postcode":"28712",
    "sg:province":"NC",
    "sg:tags":[
        "building",
        "nonresidential"
    ],
    "wof:name":"College Plaza",
    "wof:placetype":"venue"
},
  "geometry": {"coordinates":[-82.751884,35.204404],"type":"Point"}
}