{
  "type": "Feature",
  "properties": {
    "addr:full":"1365 State Hwy 16 Taylorsville NC 28681",
    "addr:housenumber":"1365",
    "addr:postcode":"28681",
    "addr:street":"State Hwy 16",
    "iso:country":"US",
    "sg:address":"1365 State Hwy 16",
    "sg:city":"Taylorsville",
    "sg:classifiers":[
        {
            "category":"Banks & Credit Unions",
            "subcategory":"Bank",
            "type":"Services"
        }
    ],
    "sg:phone":"+1 828 635 5063",
    "sg:postcode":"28681",
    "sg:province":"NC",
    "sg:tags":[
        "loan",
        "real estate"
    ],
    "wof:name":"Home Equity Stores Of Nc Inc",
    "wof:placetype":"venue"
},
  "geometry": {"coordinates":[-81.195707,35.938439],"type":"Point"}
}