{
  "type": "Feature",
  "properties": {
    "addr:full":"516 Brighton Rd Durham NC 27707",
    "addr:housenumber":"516",
    "addr:postcode":"27707",
    "addr:street":"Brighton Rd",
    "iso:country":"US",
    "sg:address":"516 Brighton Rd",
    "sg:city":"Durham",
    "sg:classifiers":[
        {
            "category":"Organizations",
            "subcategory":"Religious Organization",
            "type":"Services"
        }
    ],
    "sg:phone":"+1   ",
    "sg:postcode":"27707",
    "sg:province":"NC",
    "wof:name":"Christian Revival Church",
    "wof:placetype":"venue"
},
  "geometry": {"coordinates":[-78.933172,35.951921],"type":"Point"}
}