{
  "type": "Feature",
  "properties": {
    "iso:country":"US",
    "sg:address":"5201 Old Well St",
    "sg:city":"Durham",
    "sg:classifiers":[
        {
            "category":"Government",
            "subcategory":"Post Office",
            "type":"Public Place"
        }
    ],
    "sg:phone":"+1 919 477 1568",
    "sg:postcode":"27704",
    "sg:province":"NC",
    "sg:tags":[
        "postal",
        "us"
    ],
    "wof:name":"US Post Office",
    "wof:placetype":"venue"
},
  "geometry": {"coordinates":[-78.898534,36.068059],"type":"Point"}
}