{
  "type": "Feature",
  "properties": {
    "addr:full":"205 Wesley St Lexington NC 27295",
    "addr:housenumber":"205",
    "addr:postcode":"27295",
    "addr:street":"Wesley St",
    "iso:country":"US",
    "sg:address":"205 Wesley St",
    "sg:city":"Lexington",
    "sg:classifiers":[
        {
            "category":"Building & Trades",
            "subcategory":"Electrical",
            "type":"Services"
        }
    ],
    "sg:phone":"+1 336 731 6034",
    "sg:postcode":"27295",
    "sg:province":"NC",
    "sg:tags":[
        "electrical",
        "contractor"
    ],
    "wof:name":"Vogler Electric Inc",
    "wof:placetype":"venue"
},
  "geometry": {"coordinates":[-80.261377,35.909118],"type":"Point"}
}