{
  "type": "Feature",
  "properties": {
    "addr:full":"107 Village Rd NE Leland NC 28451",
    "addr:housenumber":"107",
    "addr:postcode":"28451",
    "addr:street":"Village Rd Ne",
    "iso:country":"US",
    "sg:address":"107 Village Rd NE",
    "sg:city":"Leland",
    "sg:classifiers":[
        {
            "category":"Freight",
            "type":"Transportation"
        }
    ],
    "sg:phone":"+1 910 371 0050",
    "sg:postcode":"28451",
    "sg:province":"NC",
    "sg:tags":[
        "commercial",
        "storage"
    ],
    "wof:name":"Southeastern Mini Storage",
    "wof:placetype":"venue"
},
  "geometry": {"coordinates":[-78.009068,34.239602],"type":"Point"}
}