{
  "type": "Feature",
  "properties": {
    "addr:full":"3724 Battleground Ave Greensboro NC 27410",
    "addr:housenumber":"3724",
    "addr:postcode":"27410",
    "addr:street":"Battleground Ave",
    "iso:country":"US",
    "sg:address":"3724 Battleground Ave",
    "sg:city":"Greensboro",
    "sg:classifiers":[
        {
            "category":"Food & Beverages",
            "subcategory":"Specialty",
            "type":"Retail Goods"
        }
    ],
    "sg:phone":"+1 336 545 0333",
    "sg:postcode":"27410",
    "sg:province":"NC",
    "sg:tags":[
        "health",
        "diet"
    ],
    "wof:name":"GNC",
    "wof:placetype":"venue"
},
  "geometry": {"coordinates":[-79.85445300000001,36.130276],"type":"Point"}
}