{
  "type": "Feature",
  "properties": {
    "addr:full":"1455 E Marion St Shelby NC 28150",
    "addr:housenumber":"1455",
    "addr:postcode":"28150",
    "addr:street":"E Marion St",
    "iso:country":"US",
    "sg:address":"1455 E Marion St",
    "sg:city":"Shelby",
    "sg:classifiers":[
        {
            "category":"Professional",
            "subcategory":"Computer Services",
            "type":"Services"
        }
    ],
    "sg:phone":"+1 704 480 0047",
    "sg:postcode":"28150",
    "sg:province":"NC",
    "sg:tags":[
        "repair"
    ],
    "sg:website":"www.sweetinc.com",
    "wof:name":"Sweeting Co Inc",
    "wof:placetype":"venue"
},
  "geometry": {"coordinates":[-81.49701899999999,35.290938],"type":"Point"}
}