{
  "type": "Feature",
  "properties": {
    "addr:full":"367 Winslow St Fayetteville NC 28301",
    "addr:housenumber":"367",
    "addr:postcode":"28301",
    "addr:street":"Winslow St",
    "iso:country":"US",
    "sg:address":"367 Winslow St",
    "sg:city":"Fayetteville",
    "sg:classifiers":[
        {
            "category":"Building & Trades",
            "subcategory":"Plumbing",
            "type":"Services"
        }
    ],
    "sg:phone":"+1 910 483 1421",
    "sg:postcode":"28301",
    "sg:province":"NC",
    "sg:tags":[
        "plumbing",
        "contractor"
    ],
    "wof:name":"Haire Plumbing Co",
    "wof:placetype":"venue"
},
  "geometry": {"coordinates":[-78.88863000000001,35.048347],"type":"Point"}
}