{
  "type": "Feature",
  "properties": {
    "addr:full":"1851 W Ehringhaus St Elizabeth City NC 27909",
    "addr:housenumber":"1851",
    "addr:postcode":"27909",
    "addr:street":"W Ehringhaus St",
    "iso:country":"US",
    "sg:address":"1851 W Ehringhaus St",
    "sg:city":"Elizabeth City",
    "sg:classifiers":[
        {
            "category":"Professional",
            "subcategory":"Engineering",
            "type":"Services"
        }
    ],
    "sg:phone":"+1   ",
    "sg:postcode":"27909",
    "sg:province":"NC",
    "wof:name":"Pt Engineering Co",
    "wof:placetype":"venue"
},
  "geometry": {"coordinates":[-76.25082399999999,36.289904],"type":"Point"}
}