{
  "type": "Feature",
  "properties": {
    "addr:full":"815 W Market St Greensboro NC 27401",
    "addr:housenumber":"815",
    "addr:postcode":"27401",
    "addr:street":"W Market St",
    "iso:country":"US",
    "sg:address":"815 W Market St",
    "sg:city":"Greensboro",
    "sg:classifiers":[
        {
            "category":"Food & Beverages",
            "subcategory":"Groceries & Convenience Stores",
            "type":"Retail Goods"
        }
    ],
    "sg:phone":"+1 336 274 4934",
    "sg:postcode":"27401",
    "sg:province":"NC",
    "wof:name":"Aramark",
    "wof:placetype":"venue"
},
  "geometry": {"coordinates":[-79.799835,36.072875],"type":"Point"}
}