{
  "type": "Feature",
  "properties": {
    "addr:full":"131 McCord St Charlotte NC 28216",
    "addr:housenumber":"131",
    "addr:postcode":"28216",
    "addr:street":"Mccord St",
    "iso:country":"US",
    "sg:address":"131 McCord St",
    "sg:city":"Charlotte",
    "sg:classifiers":[
        {
            "category":"Organizations",
            "subcategory":"Religious Organization",
            "type":"Services"
        }
    ],
    "sg:phone":"+1 704 394 1055",
    "sg:postcode":"28216",
    "sg:province":"NC",
    "sg:tags":[
        "church"
    ],
    "wof:name":"Emmanuel Baptist Church Inc",
    "wof:placetype":"venue"
},
  "geometry": {"coordinates":[-80.890187,35.290575],"type":"Point"}
}