{
  "type": "Feature",
  "properties": {
    "iso:country":"US",
    "sg:address":"519 Market St",
    "sg:city":"Wilmington",
    "sg:classifiers":[
        {
            "category":"Professional",
            "subcategory":"Lawyer & Legal Services",
            "type":"Services"
        }
    ],
    "sg:phone":"+1 910 251 9922",
    "sg:postcode":"28401",
    "sg:province":"NC",
    "sg:tags":[
        "attorney"
    ],
    "wof:name":"David G Sneeden",
    "wof:placetype":"venue"
},
  "geometry": {"coordinates":[-77.943268,34.235848],"type":"Point"}
}