{
  "type": "Feature",
  "properties": {
    "iso:country":"US",
    "sg:address":"5304 Raeford Rd",
    "sg:city":"Fayetteville",
    "sg:classifiers":[
        {
            "category":"Insurance",
            "subcategory":"Insurance Agent",
            "type":"Services"
        }
    ],
    "sg:phone":"+1 910 424 0809",
    "sg:postcode":"28304",
    "sg:province":"NC",
    "wof:name":"State Farm Insurance",
    "wof:placetype":"venue"
},
  "geometry": {"coordinates":[-78.969358,35.042893],"type":"Point"}
}