{
  "type": "Feature",
  "properties": {
    "iso:country":"US",
    "sg:address":"1116 N Bridge St",
    "sg:city":"Elkin",
    "sg:classifiers":[
        {
            "category":"Shopping",
            "subcategory":"Used Merchandise",
            "type":"Retail Goods"
        }
    ],
    "sg:phone":"+1 336 835 3666",
    "sg:postcode":"28621",
    "sg:province":"NC",
    "sg:tags":[
        "shop",
        "thrift"
    ],
    "wof:name":"Twice Around Thrift",
    "wof:placetype":"venue"
},
  "geometry": {"coordinates":[-80.850843,36.264274],"type":"Point"}
}