{
  "type": "Feature",
  "properties": {
    "addr:full":"790 Buckeye Access Rd Swannanoa NC 28778",
    "addr:housenumber":"790",
    "addr:postcode":"28778",
    "addr:street":"Buckeye Access Rd",
    "iso:country":"US",
    "sg:address":"790 Buckeye Access Rd",
    "sg:city":"Swannanoa",
    "sg:classifiers":[
        {
            "category":"Retail",
            "subcategory":"Animal Services",
            "type":"Services"
        }
    ],
    "sg:phone":"+1 828 299 9500",
    "sg:postcode":"28778",
    "sg:province":"NC",
    "sg:tags":[
        "pet",
        "grooming",
        "washing"
    ],
    "wof:name":"Buckeye Kennels LLC",
    "wof:placetype":"venue"
},
  "geometry": {"coordinates":[-82.438484,35.589927],"type":"Point"}
}