{
  "type": "Feature",
  "properties": {
    "addr:full":"1014 Sidney-Cherry Grove Rd Clarendon NC 28432",
    "addr:housenumber":"1014",
    "addr:postcode":"28432",
    "addr:street":"Sidney-Cherry Grove Rd",
    "iso:country":"US",
    "sg:address":"1014 Sidney-Cherry Grove Rd",
    "sg:city":"Clarendon",
    "sg:classifiers":[
        {
            "category":"Manufacturing",
            "subcategory":"Lumber",
            "type":"Manufacturing & Wholesale Goods"
        }
    ],
    "sg:phone":"+1 910 653 3665",
    "sg:postcode":"28432",
    "sg:province":"NC",
    "sg:tags":[
        "logging"
    ],
    "wof:name":"Bullock & Sellers Inc",
    "wof:placetype":"venue"
},
  "geometry": {"coordinates":[-78.81167499999999,34.191603],"type":"Point"}
}