{
  "type": "Feature",
  "properties": {
    "iso:country":"US",
    "sg:address":"9720 S Tryon St Ste B",
    "sg:city":"Charlotte",
    "sg:classifiers":[
        {
            "category":"Health Services",
            "subcategory":"Dentist",
            "type":"Services"
        }
    ],
    "sg:phone":"+1 704 588 5600",
    "sg:postcode":"28273",
    "sg:province":"NC",
    "wof:name":"Sam Kleitches Dds Pc",
    "wof:placetype":"venue"
},
  "geometry": {"coordinates":[-80.94347999999999,35.125807],"type":"Point"}
}