{
  "type": "Feature",
  "properties": {
    "addr:full":"9004 Admaston Dr Raleigh NC 27613",
    "addr:housenumber":"9004",
    "addr:postcode":"27613",
    "addr:street":"Admaston Dr",
    "iso:country":"US",
    "sg:address":"9004 Admaston Dr",
    "sg:city":"Raleigh",
    "sg:classifiers":[
        {
            "category":"Retail",
            "subcategory":"Repair Shop",
            "type":"Services"
        }
    ],
    "sg:phone":"+1   ",
    "sg:postcode":"27613",
    "sg:province":"NC",
    "wof:name":"Capital Cleaning Inc",
    "wof:placetype":"venue"
},
  "geometry": {"coordinates":[-78.709172,35.906223],"type":"Point"}
}