{
  "type": "Feature",
  "properties": {
    "iso:country":"US",
    "sg:address":"6608 Windmill Way",
    "sg:city":"Wilmington",
    "sg:classifiers":[
        {
            "category":"Home & Garden",
            "subcategory":"Building Materials",
            "type":"Retail Goods"
        }
    ],
    "sg:phone":"+1 910 397 0200",
    "sg:postcode":"28405",
    "sg:province":"NC",
    "wof:name":"Coastal Products",
    "wof:placetype":"venue"
},
  "geometry": {"coordinates":[-77.839901,34.260609],"type":"Point"}
}