{
  "type": "Feature",
  "properties": {
    "addr:full":"100 Liberty St Red Springs NC 28379",
    "addr:housenumber":"100",
    "addr:postcode":"28379",
    "addr:street":"Liberty St",
    "iso:country":"US",
    "sg:address":"100 Liberty St",
    "sg:city":"Red Springs",
    "sg:classifiers":[
        {
            "category":"Freight",
            "type":"Transportation"
        }
    ],
    "sg:phone":"+1 910 843 8560",
    "sg:postcode":"28379",
    "sg:province":"NC",
    "sg:tags":[
        "general"
    ],
    "wof:name":"Freedom Mini Storage",
    "wof:placetype":"venue"
},
  "geometry": {"coordinates":[-79.79218299999999,34.91648],"type":"Point"}
}