{
  "type": "Feature",
  "properties": {
    "iso:country":"US",
    "sg:address":"711 E Nash St",
    "sg:city":"Spring Hope",
    "sg:classifiers":[
        {
            "category":"Autos & Motor Vehicles",
            "subcategory":"Automobile Sales",
            "type":"Retail Goods"
        }
    ],
    "sg:phone":"+1 252 478 7547",
    "sg:postcode":"27882",
    "sg:province":"NC",
    "sg:tags":[
        "car",
        "dealer"
    ],
    "wof:name":"Sessoms' Auto Sales",
    "wof:placetype":"venue"
},
  "geometry": {"coordinates":[-78.095725,35.951642],"type":"Point"}
}