{
  "type": "Feature",
  "properties": {
    "iso:country":"US",
    "sg:address":"141 Hunterpond Ln",
    "sg:city":"Statesville",
    "sg:classifiers":[
        {
            "category":"Building & Trades",
            "subcategory":"Construction",
            "type":"Services"
        }
    ],
    "sg:phone":"+1 704 878 2734",
    "sg:postcode":"28677",
    "sg:province":"NC",
    "sg:tags":[
        "painter"
    ],
    "wof:name":"Pennywise Painting & Wallpaper",
    "wof:placetype":"venue"
},
  "geometry": {"coordinates":[-81.00827,35.764486],"type":"Point"}
}