{
  "type": "Feature",
  "properties": {
    "iso:country":"US",
    "sg:address":"131 N Caswell St",
    "sg:city":"La Grange",
    "sg:classifiers":[
        {
            "category":"Restaurant",
            "type":"Food & Drink"
        }
    ],
    "sg:phone":"+1 252 566 4014",
    "sg:postcode":"28551",
    "sg:province":"NC",
    "sg:tags":[
        "eating"
    ],
    "wof:name":"Sukis Place",
    "wof:placetype":"venue"
},
  "geometry": {"coordinates":[-77.78742200000001,35.308146],"type":"Point"}
}