{
  "type": "Feature",
  "properties": {
    "addr:full":"5446 Patuxent Dr Raleigh NC 27616",
    "addr:housenumber":"5446",
    "addr:postcode":"27616",
    "addr:street":"Patuxent Dr",
    "iso:country":"US",
    "sg:address":"5446 Patuxent Dr",
    "sg:city":"Raleigh",
    "sg:classifiers":[
        {
            "category":"Shopping",
            "subcategory":"Used Merchandise",
            "type":"Retail Goods"
        }
    ],
    "sg:phone":"+1 919 850 0341",
    "sg:postcode":"27616",
    "sg:province":"NC",
    "wof:name":"North Side Antiques",
    "wof:placetype":"venue"
},
  "geometry": {"coordinates":[-78.551688,35.886959],"type":"Point"}
}