{
  "type": "Feature",
  "properties": {
    "addr:full":"312 Lewis St Oxford NC 27565",
    "addr:housenumber":"312",
    "addr:postcode":"27565",
    "addr:street":"Lewis St",
    "iso:country":"US",
    "sg:address":"312 Lewis St",
    "sg:city":"Oxford",
    "sg:classifiers":[
        {
            "category":"Shopping",
            "subcategory":"Bicycles & Sporting Goods",
            "type":"Retail Goods"
        }
    ],
    "sg:phone":"+1 919 693 2503",
    "sg:postcode":"27565",
    "sg:province":"NC",
    "sg:tags":[
        "bait",
        "fishing"
    ],
    "wof:name":"Welcome Bait & Tackle Shop",
    "wof:placetype":"venue"
},
  "geometry": {"coordinates":[-78.596209,36.305566],"type":"Point"}
}