{
  "type": "Feature",
  "properties": {
    "addr:full":"4 Fuller Ln Asheville NC 28805",
    "addr:housenumber":"4",
    "addr:postcode":"28805",
    "addr:street":"Fuller Ln",
    "iso:country":"US",
    "sg:address":"4 Fuller Ln",
    "sg:city":"Asheville",
    "sg:classifiers":[
        {
            "category":"Professional",
            "subcategory":"Business Services",
            "type":"Services"
        }
    ],
    "sg:phone":"+1   ",
    "sg:postcode":"28805",
    "sg:province":"NC",
    "wof:name":"H&F Land Development Inc",
    "wof:placetype":"venue"
},
  "geometry": {"coordinates":[-82.472174,35.649865],"type":"Point"}
}