{
  "type": "Feature",
  "properties": {
    "addr:full":"709 Tait St Lincolnton NC 28092",
    "addr:housenumber":"709",
    "addr:postcode":"28092",
    "addr:street":"Tait St",
    "iso:country":"US",
    "sg:address":"709 Tait St",
    "sg:city":"Lincolnton",
    "sg:classifiers":[
        {
            "category":"Health Services",
            "subcategory":"Nursing And Care Facility",
            "type":"Services"
        }
    ],
    "sg:phone":"+1 704 735 4419",
    "sg:postcode":"28092",
    "sg:province":"NC",
    "sg:tags":[
        "home",
        "apartment",
        "community",
        "retirement"
    ],
    "wof:name":"Lutherhaus Of Lincolnton Inc",
    "wof:placetype":"venue"
},
  "geometry": {"coordinates":[-81.24505600000001,35.469049],"type":"Point"}
}