{
  "type": "Feature",
  "properties": {
    "iso:country":"US",
    "sg:address":"2205 Plainview Dr",
    "sg:city":"High Point",
    "sg:classifiers":[
        {
            "category":"Real Estate",
            "subcategory":"Real Estate Agent",
            "type":"Services"
        }
    ],
    "sg:phone":"+1 336 454 4482",
    "sg:postcode":"27265",
    "sg:province":"NC",
    "wof:name":"R Stewart Inc",
    "wof:placetype":"venue"
},
  "geometry": {"coordinates":[-79.97595200000001,36.024067],"type":"Point"}
}