{
  "type": "Feature",
  "properties": {
    "iso:country":"US",
    "sg:address":"2935 Breezewood Ave",
    "sg:city":"Fayetteville",
    "sg:classifiers":[
        {
            "category":"Building & Trades",
            "subcategory":"Construction",
            "type":"Services"
        }
    ],
    "sg:phone":"+1 910 826 0648",
    "sg:postcode":"28303",
    "sg:province":"NC",
    "sg:tags":[
        "home",
        "builder"
    ],
    "wof:name":"Home Builders Assn",
    "wof:placetype":"venue"
},
  "geometry": {"coordinates":[-78.92748899999999,35.043918],"type":"Point"}
}