{
  "type": "Feature",
  "properties": {
    "addr:full":"9 S Lake Park Blvd Carolina Beach NC 28428",
    "addr:housenumber":"9",
    "addr:postcode":"28428",
    "addr:street":"S Lake Park Blvd",
    "iso:country":"US",
    "sg:address":"9 S Lake Park Blvd",
    "sg:city":"Carolina Beach",
    "sg:classifiers":[
        {
            "category":"Real Estate",
            "subcategory":"Real Estate Services",
            "type":"Services"
        }
    ],
    "sg:phone":"+1 910 458 5878",
    "sg:postcode":"28428",
    "sg:province":"NC",
    "sg:website":"www.atlanticshoresrealty.com",
    "wof:name":"Atlantic Shores Real Estate",
    "wof:placetype":"venue"
},
  "geometry": {"coordinates":[-77.89659899999999,34.031502],"type":"Point"}
}