{
  "type": "Feature",
  "properties": {
    "addr:full":"106 W McGee St Greensboro NC 27403",
    "addr:housenumber":"106",
    "addr:postcode":"27403",
    "addr:street":"W Mcgee St",
    "iso:country":"US",
    "sg:address":"106 W McGee St",
    "sg:city":"Greensboro",
    "sg:classifiers":[
        {
            "category":"Recreation",
            "type":"Entertainment"
        }
    ],
    "sg:phone":"+1 336 379 0054",
    "sg:postcode":"27403",
    "sg:province":"NC",
    "sg:tags":[
        "parlor",
        "billiard"
    ],
    "wof:name":"Longshank's Billiards",
    "wof:placetype":"venue"
},
  "geometry": {"coordinates":[-79.79176200000001,36.068597],"type":"Point"}
}