{
  "type": "Feature",
  "properties": {
    "addr:full":"6512 Six Forks Rd Raleigh NC 27615",
    "addr:housenumber":"6512",
    "addr:postcode":"27615",
    "addr:street":"Six Forks Rd",
    "iso:country":"US",
    "sg:address":"6512 Six Forks Rd",
    "sg:city":"Raleigh",
    "sg:classifiers":[
        {
            "category":"Personal",
            "subcategory":"Beauty Salon",
            "type":"Services"
        }
    ],
    "sg:phone":"+1 919 844 1077",
    "sg:postcode":"27615",
    "sg:province":"NC",
    "wof:name":"Jerome Daurity At Generation",
    "wof:placetype":"venue"
},
  "geometry": {"coordinates":[-78.63887099999999,35.868371],"type":"Point"}
}