{
  "type": "Feature",
  "properties": {
    "addr:full":"518 Plaza Blvd Kinston NC 28501",
    "addr:housenumber":"518",
    "addr:postcode":"28501",
    "addr:street":"Plaza Blvd",
    "iso:country":"US",
    "sg:address":"518 Plaza Blvd",
    "sg:city":"Kinston",
    "sg:classifiers":[
        {
            "category":"Education",
            "subcategory":"Special Training",
            "type":"Public Place"
        }
    ],
    "sg:phone":"+1 252 522 1690",
    "sg:postcode":"28501",
    "sg:province":"NC",
    "sg:tags":[
        "tutoring"
    ],
    "wof:name":"Sylvan Learning Ctr",
    "wof:placetype":"venue"
},
  "geometry": {"coordinates":[-77.583917,35.284653],"type":"Point"}
}