{
  "type": "Feature",
  "properties": {
    "addr:full":"2601 Heidleburg Ln Charlotte NC 28210",
    "addr:housenumber":"2601",
    "addr:postcode":"28210",
    "addr:street":"Heidleburg Ln",
    "iso:country":"US",
    "sg:address":"2601 Heidleburg Ln",
    "sg:city":"Charlotte",
    "sg:classifiers":[
        {
            "category":"Travel",
            "subcategory":"Travel Agent",
            "type":"Entertainment"
        }
    ],
    "sg:phone":"+1 704 554 9941",
    "sg:postcode":"28210",
    "sg:province":"NC",
    "sg:tags":[
        "cruise"
    ],
    "wof:name":"Pratt Travel & Tours",
    "wof:placetype":"venue"
},
  "geometry": {"coordinates":[-80.86832099999999,35.111824],"type":"Point"}
}