{
  "type": "Feature",
  "properties": {
    "iso:country":"US",
    "sg:address":"1944 Stone Rose Ave",
    "sg:city":"Rocky Mount",
    "sg:classifiers":[
        {
            "category":"Shopping",
            "subcategory":"Clothing, Apparel, & Fashions",
            "type":"Retail Goods"
        }
    ],
    "sg:phone":"+1 252 972 9889",
    "sg:postcode":"27804",
    "sg:province":"NC",
    "sg:tags":[
        "furnishing"
    ],
    "wof:name":"Manhattan",
    "wof:placetype":"venue"
},
  "geometry": {"coordinates":[-77.822203,35.956998],"type":"Point"}
}