{
  "type": "Feature",
  "properties": {
    "addr:full":"1258 Greenside Dr NW Concord NC 28027",
    "addr:housenumber":"1258",
    "addr:postcode":"28027",
    "addr:street":"Greenside Dr Nw",
    "iso:country":"US",
    "sg:address":"1258 Greenside Dr NW",
    "sg:city":"Concord",
    "sg:classifiers":[
        {
            "category":"Wholesale",
            "subcategory":"Groceries",
            "type":"Manufacturing & Wholesale Goods"
        }
    ],
    "sg:phone":"+1 704 795 4420",
    "sg:postcode":"28027",
    "sg:province":"NC",
    "sg:tags":[
        "food",
        "broker"
    ],
    "wof:name":"Pioneer Sales & Marketing",
    "wof:placetype":"venue"
},
  "geometry": {"coordinates":[-80.63961999999999,35.397865],"type":"Point"}
}