{
  "type": "Feature",
  "properties": {
    "addr:full":"3136 Georgia Rd Yadkinville NC 27055",
    "addr:housenumber":"3136",
    "addr:postcode":"27055",
    "addr:street":"Georgia Rd",
    "iso:country":"US",
    "sg:address":"3136 Georgia Rd",
    "sg:city":"Yadkinville",
    "sg:classifiers":[
        {
            "category":"Professional",
            "type":"Services"
        }
    ],
    "sg:phone":"+1   ",
    "sg:postcode":"27055",
    "sg:province":"NC",
    "wof:name":"Burnettes Services",
    "wof:placetype":"venue"
},
  "geometry": {"coordinates":[-80.547893,36.063781],"type":"Point"}
}