{
  "type": "Feature",
  "properties": {
    "addr:full":"104 Thornburg Dr SE Conover NC 28613",
    "addr:housenumber":"104",
    "addr:postcode":"28613",
    "addr:street":"Thornburg Dr Se",
    "iso:country":"US",
    "sg:address":"104 Thornburg Dr SE",
    "sg:city":"Conover",
    "sg:classifiers":[
        {
            "category":"Shopping",
            "subcategory":"Pharmacy",
            "type":"Retail Goods"
        }
    ],
    "sg:phone":"+1 828 465 6760",
    "sg:postcode":"28613",
    "sg:province":"NC",
    "sg:tags":[
        "drug",
        "store"
    ],
    "wof:name":"CVS",
    "wof:placetype":"venue"
},
  "geometry": {"coordinates":[-81.200084,35.702698],"type":"Point"}
}