{
  "type": "Feature",
  "properties": {
    "iso:country":"US",
    "sg:address":"4310 Bennett Memorial Rd",
    "sg:city":"Durham",
    "sg:classifiers":[
        {
            "category":"Building & Trades",
            "subcategory":"Construction",
            "type":"Services"
        }
    ],
    "sg:phone":"+1 919 309 2525",
    "sg:postcode":"27705",
    "sg:province":"NC",
    "sg:tags":[
        "water",
        "restoration",
        "damage"
    ],
    "wof:name":"Servicemaster Restoration",
    "wof:placetype":"venue"
},
  "geometry": {"coordinates":[-78.965529,36.030458],"type":"Point"}
}