{
  "type": "Feature",
  "properties": {
    "iso:country":"US",
    "sg:address":"6149 E Independence Blvd",
    "sg:city":"Charlotte",
    "sg:classifiers":[
        {
            "category":"Autos & Motor Vehicles",
            "subcategory":"Automobile Sales",
            "type":"Retail Goods"
        }
    ],
    "sg:phone":"+1 704 733 9525",
    "sg:postcode":"28212",
    "sg:province":"NC",
    "sg:tags":[
        "dealers-used",
        "car",
        "used",
        "cars-wholesale",
        "new"
    ],
    "wof:name":"Nour Auto Sales",
    "wof:placetype":"venue"
},
  "geometry": {"coordinates":[-80.74994,35.17661],"type":"Point"}
}