{
  "type": "Feature",
  "properties": {
    "addr:full":"86 Sherwood Rd Asheville NC 28803",
    "addr:housenumber":"86",
    "addr:postcode":"28803",
    "addr:street":"Sherwood Rd",
    "iso:country":"US",
    "sg:address":"86 Sherwood Rd",
    "sg:city":"Asheville",
    "sg:classifiers":[
        {
            "category":"Professional",
            "subcategory":"Advertising",
            "type":"Services"
        }
    ],
    "sg:phone":"+1   ",
    "sg:postcode":"28803",
    "sg:province":"NC",
    "wof:name":"George Self",
    "wof:placetype":"venue"
},
  "geometry": {"coordinates":[-82.546443,35.580167],"type":"Point"}
}