{
  "type": "Feature",
  "properties": {
    "addr:full":"212 Raintree Dr Hendersonville NC 28791",
    "addr:housenumber":"212",
    "addr:postcode":"28791",
    "addr:street":"Raintree Dr",
    "iso:country":"US",
    "sg:address":"212 Raintree Dr",
    "sg:city":"Hendersonville",
    "sg:classifiers":[
        {
            "category":"Manufacturing",
            "subcategory":"Apparel",
            "type":"Manufacturing & Wholesale Goods"
        }
    ],
    "sg:phone":"+1 828 891 7805",
    "sg:postcode":"28791",
    "sg:province":"NC",
    "sg:tags":[
        "blouse",
        "jacket",
        "skirt",
        "d",
        "mfg"
    ],
    "wof:name":"S & D Sportswear Inc",
    "wof:placetype":"venue"
},
  "geometry": {"coordinates":[-82.543093,35.3429],"type":"Point"}
}