{
  "type": "Feature",
  "properties": {
    "iso:country":"US",
    "sg:address":"704 Lexington Ave",
    "sg:city":"Charlotte",
    "sg:classifiers":[
        {
            "category":"Professional",
            "subcategory":"Lawyer & Legal Services",
            "type":"Services"
        }
    ],
    "sg:phone":"+1 704 376 2912",
    "sg:postcode":"28203",
    "sg:province":"NC",
    "sg:tags":[
        "plan"
    ],
    "wof:name":"Thomas Blackwood",
    "wof:placetype":"venue"
},
  "geometry": {"coordinates":[-80.847898,35.215209],"type":"Point"}
}