{
  "type": "Feature",
  "properties": {
    "addr:full":"1253 Nance Rd King NC 27021",
    "addr:housenumber":"1253",
    "addr:postcode":"27021",
    "addr:street":"Nance Rd",
    "iso:country":"US",
    "sg:address":"1253 Nance Rd",
    "sg:city":"King",
    "sg:classifiers":[
        {
            "category":"Retail",
            "subcategory":"Auto Repair",
            "type":"Services"
        }
    ],
    "sg:phone":"+1 336 983 9492",
    "sg:postcode":"27021",
    "sg:province":"NC",
    "sg:tags":[
        "repairing",
        "automobile"
    ],
    "wof:name":"M & D Automotive",
    "wof:placetype":"venue"
},
  "geometry": {"coordinates":[-80.324068,36.344165],"type":"Point"}
}