{
  "type": "Feature",
  "properties": {
    "addr:full":"511 Clayton Rd Durham NC 27703",
    "addr:housenumber":"511",
    "addr:postcode":"27703",
    "addr:street":"Clayton Rd",
    "iso:country":"US",
    "sg:address":"511 Clayton Rd",
    "sg:city":"Durham",
    "sg:classifiers":[
        {
            "category":"Professional",
            "subcategory":"Research",
            "type":"Services"
        }
    ],
    "sg:phone":"+1 919 596 9955",
    "sg:postcode":"27703",
    "sg:province":"NC",
    "sg:tags":[
        "organization",
        "noncommercial"
    ],
    "wof:name":"Doug Kirven",
    "wof:placetype":"venue"
},
  "geometry": {"coordinates":[-78.83203899999999,35.990345],"type":"Point"}
}