{
  "type": "Feature",
  "properties": {
    "addr:full":"156 Five Points Rd Goldsboro NC 27504",
    "addr:housenumber":"156",
    "addr:postcode":"27504",
    "addr:street":"Five Points Rd",
    "iso:country":"US",
    "sg:address":"156 Five Points Rd",
    "sg:city":"Goldsboro",
    "sg:classifiers":[
        {
            "category":"Shopping",
            "subcategory":"Clothing, Apparel, & Fashions",
            "type":"Retail Goods"
        }
    ],
    "sg:phone":"+1 919 739 5998",
    "sg:postcode":"27504",
    "sg:province":"NC",
    "wof:name":"Touch of Love Boutique",
    "wof:placetype":"venue"
},
  "geometry": {"coordinates":[-78.483863,35.350091],"type":"Point"}
}