{
  "type": "Feature",
  "properties": {
    "addr:full":"5640 Market St Wilmington NC 28405",
    "addr:housenumber":"5640",
    "addr:postcode":"28405",
    "addr:street":"Market St",
    "iso:country":"US",
    "sg:address":"5640 Market St",
    "sg:city":"Wilmington",
    "sg:classifiers":[
        {
            "category":"Autos & Motor Vehicles",
            "subcategory":"Automobile Sales",
            "type":"Retail Goods"
        }
    ],
    "sg:phone":"+1 910 791 9735",
    "sg:postcode":"28405",
    "sg:province":"NC",
    "sg:tags":[
        "car",
        "dealer"
    ],
    "sg:website":"www.toyotaofwilmington.com",
    "wof:name":"Toyota Of Wilmington",
    "wof:placetype":"venue"
},
  "geometry": {"coordinates":[-77.86212,34.248463],"type":"Point"}
}