{
  "type": "Feature",
  "properties": {
    "addr:full":"10013 Fayetteville Rd Fuquay Varina NC 27526",
    "addr:housenumber":"10013",
    "addr:postcode":"27526",
    "addr:street":"Fayetteville Rd",
    "iso:country":"US",
    "sg:address":"10013 Fayetteville Rd",
    "sg:city":"Fuquay Varina",
    "sg:classifiers":[
        {
            "category":"Building & Trades",
            "subcategory":"Construction",
            "type":"Services"
        }
    ],
    "sg:phone":"+1 919 552 4257",
    "sg:postcode":"27526",
    "sg:province":"NC",
    "sg:tags":[
        "maker",
        "cabinet"
    ],
    "wof:name":"Noles' Cabinet Inc",
    "wof:placetype":"venue"
},
  "geometry": {"coordinates":[-78.71587100000001,35.631762],"type":"Point"}
}