{
  "type": "Feature",
  "properties": {
    "addr:full":"307 Magnolia Ln Arapahoe NC 28510",
    "addr:housenumber":"307",
    "addr:postcode":"28510",
    "addr:street":"Magnolia Ln",
    "iso:country":"US",
    "sg:address":"307 Magnolia Ln",
    "sg:city":"Arapahoe",
    "sg:classifiers":[
        {
            "category":"Building & Trades",
            "subcategory":"Plumbing",
            "type":"Services"
        }
    ],
    "sg:phone":"+1 252 249 0938",
    "sg:postcode":"28510",
    "sg:province":"NC",
    "sg:tags":[
        "contractor"
    ],
    "wof:name":"Stan S Heating Air Conditionin",
    "wof:placetype":"venue"
},
  "geometry": {"coordinates":[-76.76593,34.985775],"type":"Point"}
}