{
  "type": "Feature",
  "properties": {
    "addr:full":"4749 Nijinsky Ct Charlotte NC 28216",
    "addr:housenumber":"4749",
    "addr:postcode":"28216",
    "addr:street":"Nijinsky Ct",
    "iso:country":"US",
    "sg:address":"4749 Nijinsky Ct",
    "sg:city":"Charlotte",
    "sg:classifiers":[
        {
            "category":"Professional",
            "subcategory":"Secretarial Services",
            "type":"Services"
        }
    ],
    "sg:phone":"+1 704 399 5476",
    "sg:postcode":"28216",
    "sg:province":"NC",
    "sg:tags":[
        "reporting",
        "court"
    ],
    "wof:name":"Emmanuel Enterprises",
    "wof:placetype":"venue"
},
  "geometry": {"coordinates":[-80.90534,35.340324],"type":"Point"}
}