{
  "type": "Feature",
  "properties": {
    "addr:full":"1099 S Dobson Chapel Rd Magnolia NC 28349",
    "addr:housenumber":"1099",
    "addr:postcode":"28349",
    "addr:street":"S Dobson Chapel Rd",
    "iso:country":"US",
    "sg:address":"1099 S Dobson Chapel Rd",
    "sg:city":"Magnolia",
    "sg:classifiers":[
        {
            "category":"Personal",
            "subcategory":"Beauty Salon",
            "type":"Services"
        }
    ],
    "sg:phone":"+1   ",
    "sg:postcode":"28349",
    "sg:province":"NC",
    "sg:tags":[
        "shop"
    ],
    "wof:name":"Perfect Touch Nail Salon",
    "wof:placetype":"venue"
},
  "geometry": {"coordinates":[-77.91650799999999,34.906017],"type":"Point"}
}