{
  "type": "Feature",
  "properties": {
    "iso:country":"US",
    "sg:address":"68 Main St",
    "sg:city":"Canton",
    "sg:classifiers":[
        {
            "category":"Personal",
            "subcategory":"Beauty Salon",
            "type":"Services"
        }
    ],
    "sg:phone":"+1 828 648 4767",
    "sg:postcode":"28716",
    "sg:province":"NC",
    "wof:name":"Hair",
    "wof:placetype":"venue"
},
  "geometry": {"coordinates":[-82.83981799999999,35.531527],"type":"Point"}
}