{
  "type": "Feature",
  "properties": {
    "addr:full":"171 Jackson Rd Rockingham NC 28379",
    "addr:housenumber":"171",
    "addr:postcode":"28379",
    "addr:street":"Jackson Rd",
    "iso:country":"US",
    "sg:address":"171 Jackson Rd",
    "sg:city":"Rockingham",
    "sg:classifiers":[
        {
            "category":"Government",
            "subcategory":"Office",
            "type":"Public Place"
        }
    ],
    "sg:phone":"+1 910 895 3915",
    "sg:postcode":"28379",
    "sg:province":"NC",
    "wof:name":"Richmond County Waste Cllctn",
    "wof:placetype":"venue"
},
  "geometry": {"coordinates":[-79.72694,35.009195],"type":"Point"}
}