{
  "type": "Feature",
  "properties": {
    "iso:country":"US",
    "sg:address":"512 Pershing Rd",
    "sg:city":"Raleigh",
    "sg:classifiers":[
        {
            "category":"Manufacturing",
            "subcategory":"Signs",
            "type":"Manufacturing & Wholesale Goods"
        }
    ],
    "sg:phone":"+1 919 832 6878",
    "sg:postcode":"27608",
    "sg:province":"NC",
    "sg:tags":[
        "electrical",
        "commercial",
        "mfg"
    ],
    "wof:name":"Harrell Sign Company Inc",
    "wof:placetype":"venue"
},
  "geometry": {"coordinates":[-78.630951,35.804158],"type":"Point"}
}