{
  "type": "Feature",
  "properties": {
    "addr:full":"800 Eastowne Dr Chapel Hill NC 27514",
    "addr:housenumber":"800",
    "addr:postcode":"27514",
    "addr:street":"Eastowne Dr",
    "iso:country":"US",
    "sg:address":"800 Eastowne Dr",
    "sg:city":"Chapel Hill",
    "sg:classifiers":[
        {
            "category":"Social Services",
            "type":"Services"
        }
    ],
    "sg:phone":"+1   ",
    "sg:postcode":"27514",
    "sg:province":"NC",
    "wof:name":"Betty F Pristera Mss Acsw",
    "wof:placetype":"venue"
},
  "geometry": {"coordinates":[-79.00514099999999,35.951388],"type":"Point"}
}