{
  "type": "Feature",
  "properties": {
    "addr:full":"14600 Weston Pkwy Cary NC 27513",
    "addr:housenumber":"14600",
    "addr:postcode":"27513",
    "addr:street":"Weston Pkwy",
    "iso:country":"US",
    "sg:address":"14600 Weston Pkwy",
    "sg:city":"Cary",
    "sg:classifiers":[
        {
            "category":"Professional",
            "subcategory":"Lawyer & Legal Services",
            "type":"Services"
        }
    ],
    "sg:phone":"+1 919 460 0770",
    "sg:postcode":"27513",
    "sg:province":"NC",
    "wof:name":"Higgins Frankstone Graves",
    "wof:placetype":"venue"
},
  "geometry": {"coordinates":[-78.81134,35.817071],"type":"Point"}
}