{
  "type": "Feature",
  "properties": {
    "iso:country":"US",
    "sg:address":"29 E A St",
    "sg:city":"Newton",
    "sg:classifiers":[
        {
            "category":"Shopping",
            "subcategory":"Florist",
            "type":"Retail Goods"
        }
    ],
    "sg:phone":"+1 828 465 1996",
    "sg:postcode":"28658",
    "sg:province":"NC",
    "wof:name":"Abundant Life Book Shop",
    "wof:placetype":"venue"
},
  "geometry": {"coordinates":[-81.22184799999999,35.662609],"type":"Point"}
}