{
  "type": "Feature",
  "properties": {
    "addr:full":"3820 Raeford Rd Fayetteville NC 28304",
    "addr:housenumber":"3820",
    "addr:postcode":"28304",
    "addr:street":"Raeford Rd",
    "iso:country":"US",
    "sg:address":"3820 Raeford Rd",
    "sg:city":"Fayetteville",
    "sg:classifiers":[
        {
            "category":"Insurance",
            "subcategory":"Insurance Agent",
            "type":"Services"
        }
    ],
    "sg:phone":"+1 910 323 3045",
    "sg:postcode":"28304",
    "sg:province":"NC",
    "wof:name":"Insurance Service Ctr",
    "wof:placetype":"venue"
},
  "geometry": {"coordinates":[-78.94286200000001,35.04401],"type":"Point"}
}