{
  "type": "Feature",
  "properties": {
    "addr:full":"233 Border Belt Dr Whiteville NC 28472",
    "addr:housenumber":"233",
    "addr:postcode":"28472",
    "addr:street":"Border Belt Dr",
    "iso:country":"US",
    "sg:address":"233 Border Belt Dr",
    "sg:city":"Whiteville",
    "sg:classifiers":[
        {
            "category":"Government",
            "subcategory":"Office",
            "type":"Public Place"
        }
    ],
    "sg:phone":"+1 910 648 6046",
    "sg:postcode":"28472",
    "sg:province":"NC",
    "wof:name":"N C Dept Of Agriculture Plant",
    "wof:placetype":"venue"
},
  "geometry": {"coordinates":[-78.79050700000001,34.408308],"type":"Point"}
}