{
  "type": "Feature",
  "properties": {
    "addr:full":"1201 Strathmore Cir NW Winston Salem NC 27104",
    "addr:housenumber":"1201",
    "addr:postcode":"27104",
    "addr:street":"Strathmore Cir Nw",
    "iso:country":"US",
    "sg:address":"1201 Strathmore Cir NW",
    "sg:city":"Winston Salem",
    "sg:classifiers":[
        {
            "category":"Professional",
            "subcategory":"Credit Reporting & Collection",
            "type":"Services"
        }
    ],
    "sg:phone":"+1   ",
    "sg:postcode":"27104",
    "sg:province":"NC",
    "wof:name":"Fleming Services Inc",
    "wof:placetype":"venue"
},
  "geometry": {"coordinates":[-80.31976400000001,36.109902],"type":"Point"}
}