{
  "type": "Feature",
  "properties": {
    "addr:full":"510 River Hwy Mooresville NC 28117",
    "addr:housenumber":"510",
    "addr:postcode":"28117",
    "addr:street":"River Hwy",
    "iso:country":"US",
    "sg:address":"510 River Hwy",
    "sg:city":"Mooresville",
    "sg:classifiers":[
        {
            "category":"Home & Garden",
            "subcategory":"Household Appliances",
            "type":"Retail Goods"
        },
        {
            "category":"Shopping",
            "subcategory":"Computers & Home Electronics",
            "type":"Retail Goods"
        }
    ],
    "sg:phone":"+1 704 663 8222",
    "sg:postcode":"28117",
    "sg:province":"NC",
    "wof:name":"Queen City T V & Appliance",
    "wof:placetype":"venue"
},
  "geometry": {"coordinates":[-80.86699400000001,35.594766],"type":"Point"}
}