{
  "type": "Feature",
  "properties": {
    "iso:country":"US",
    "sg:address":"122 W Broad St",
    "sg:city":"Statesville",
    "sg:classifiers":[
        {
            "category":"Retail",
            "subcategory":"Repair Shop",
            "type":"Services"
        }
    ],
    "sg:phone":"+1 704 924 7004",
    "sg:postcode":"28677",
    "sg:province":"NC",
    "sg:tags":[
        "jewelry"
    ],
    "wof:name":"Arlie's Jewelry",
    "wof:placetype":"venue"
},
  "geometry": {"coordinates":[-80.888606,35.784589],"type":"Point"}
}