{
  "type": "Feature",
  "properties": {
    "iso:country":"US",
    "sg:address":"2010 Brevard Rd",
    "sg:city":"Hendersonville",
    "sg:classifiers":[
        {
            "category":"Building & Trades",
            "subcategory":"Construction",
            "type":"Services"
        }
    ],
    "sg:phone":"+1 828 692 0211",
    "sg:postcode":"28791",
    "sg:province":"NC",
    "sg:tags":[
        "builder",
        "operative"
    ],
    "wof:name":"Moss Log Homes",
    "wof:placetype":"venue"
},
  "geometry": {"coordinates":[-82.501082,35.323392],"type":"Point"}
}