{
  "type": "Feature",
  "properties": {
    "addr:full":"1273 Burnside Rd Manteo NC 27954",
    "addr:housenumber":"1273",
    "addr:postcode":"27954",
    "addr:street":"Burnside Rd",
    "iso:country":"US",
    "sg:address":"1273 Burnside Rd",
    "sg:city":"Manteo",
    "sg:classifiers":[
        {
            "category":"Building & Trades",
            "subcategory":"Landscaping Services",
            "type":"Services"
        }
    ],
    "sg:phone":"+1 252 473 5501",
    "sg:postcode":"27954",
    "sg:province":"NC",
    "sg:tags":[
        "landscape"
    ],
    "wof:name":"Brushbusters",
    "wof:placetype":"venue"
},
  "geometry": {"coordinates":[-75.686207,35.902466],"type":"Point"}
}