{
  "type": "Feature",
  "properties": {
    "iso:country":"US",
    "sg:address":"9265 Sauls Rd",
    "sg:city":"Raleigh",
    "sg:classifiers":[
        {
            "category":"Professional",
            "type":"Services"
        }
    ],
    "sg:phone":"+1 919 773 1815",
    "sg:postcode":"27603",
    "sg:province":"NC",
    "wof:name":"William D Mosley",
    "wof:placetype":"venue"
},
  "geometry": {"coordinates":[-78.640676,35.626981],"type":"Point"}
}