{
  "type": "Feature",
  "properties": {
    "addr:full":"1903 W Church St Elizabeth City NC 27909",
    "addr:housenumber":"1903",
    "addr:postcode":"27909",
    "addr:street":"W Church St",
    "iso:country":"US",
    "sg:address":"1903 W Church St",
    "sg:city":"Elizabeth City",
    "sg:classifiers":[
        {
            "category":"Building & Trades",
            "subcategory":"Plumbing",
            "type":"Services"
        }
    ],
    "sg:phone":"+1 252 338 6090",
    "sg:postcode":"27909",
    "sg:province":"NC",
    "sg:tags":[
        "conditioning",
        "air",
        "system",
        "contractor"
    ],
    "wof:name":"Climatemasters Inc",
    "wof:placetype":"venue"
},
  "geometry": {"coordinates":[-76.25444299999999,36.299572],"type":"Point"}
}