{
  "type": "Feature",
  "properties": {
    "addr:full":"1220 Rockingham Rd Rockingham NC 28379",
    "addr:housenumber":"1220",
    "addr:postcode":"28379",
    "addr:street":"Rockingham Rd",
    "iso:country":"US",
    "sg:address":"1220 Rockingham Rd",
    "sg:city":"Rockingham",
    "sg:classifiers":[
        {
            "category":"Personal",
            "subcategory":"Beauty Salon",
            "type":"Services"
        }
    ],
    "sg:phone":"+1 910 895 6169",
    "sg:postcode":"28379",
    "sg:province":"NC",
    "wof:name":"Robin Family Salon",
    "wof:placetype":"venue"
},
  "geometry": {"coordinates":[-79.75115700000001,34.926072],"type":"Point"}
}