{
  "type": "Feature",
  "properties": {
    "addr:full":"3997 New Walkertown Rd NE Winston Salem NC 27105",
    "addr:housenumber":"3997",
    "addr:postcode":"27105",
    "addr:street":"New Walkertown Rd Ne",
    "iso:country":"US",
    "sg:address":"3997 New Walkertown Rd NE",
    "sg:city":"Winston Salem",
    "sg:classifiers":[
        {
            "category":"Building & Trades",
            "subcategory":"Construction",
            "type":"Services"
        }
    ],
    "sg:phone":"+1 336 721 0360",
    "sg:postcode":"27105",
    "sg:province":"NC",
    "wof:name":"REA Construction Company",
    "wof:placetype":"venue"
},
  "geometry": {"coordinates":[-80.185333,36.144288],"type":"Point"}
}