{
  "type": "Feature",
  "properties": {
    "iso:country":"US",
    "sg:address":"6930 Wallace Rd",
    "sg:city":"Charlotte",
    "sg:classifiers":[
        {
            "category":"Organizations",
            "subcategory":"Religious Organization",
            "type":"Services"
        }
    ],
    "sg:phone":"+1   ",
    "sg:postcode":"28212",
    "sg:province":"NC",
    "wof:name":"P C USA Inc",
    "wof:placetype":"venue"
},
  "geometry": {"coordinates":[-80.750938,35.175796],"type":"Point"}
}