{
  "type": "Feature",
  "properties": {
    "iso:country":"US",
    "sg:address":"340 Hughes St",
    "sg:city":"Greensboro",
    "sg:classifiers":[
        {
            "category":"Freight",
            "type":"Transportation"
        }
    ],
    "sg:phone":"+1 336 275 5300",
    "sg:postcode":"27401",
    "sg:province":"NC",
    "sg:tags":[
        "commercial",
        "storage"
    ],
    "wof:name":"Thomas Transfer Inc",
    "wof:placetype":"venue"
},
  "geometry": {"coordinates":[-79.785898,36.070667],"type":"Point"}
}