{
  "type": "Feature",
  "properties": {
    "iso:country":"US",
    "sg:address":"10625 Fairway Ridge Rd",
    "sg:city":"Charlotte",
    "sg:classifiers":[
        {
            "category":"Professional",
            "type":"Services"
        }
    ],
    "sg:phone":"+1   ",
    "sg:postcode":"28277",
    "sg:province":"NC",
    "wof:name":"Oldwak Services LLC",
    "wof:placetype":"venue"
},
  "geometry": {"coordinates":[-80.79799199999999,35.069067],"type":"Point"}
}