{
  "type": "Feature",
  "properties": {
    "iso:country":"US",
    "sg:address":"1320 N 12th St",
    "sg:city":"Bessemer City",
    "sg:classifiers":[
        {
            "category":"Education",
            "subcategory":"School",
            "type":"Public Place"
        }
    ],
    "sg:phone":"+1 704 629 4181",
    "sg:postcode":"28016",
    "sg:province":"NC",
    "sg:tags":[
        "primary"
    ],
    "sg:website":"www.gastoncountyschools.com",
    "wof:name":"Bessemer City Primary School",
    "wof:placetype":"venue"
},
  "geometry": {"coordinates":[-81.277423,35.300805],"type":"Point"}
}