{
  "type": "Feature",
  "properties": {
    "addr:full":"6131 Falls of Neuse Rd Raleigh NC 27609",
    "addr:housenumber":"6131",
    "addr:postcode":"27609",
    "addr:street":"Falls Of Neuse Rd",
    "iso:country":"US",
    "sg:address":"6131 Falls of Neuse Rd",
    "sg:city":"Raleigh",
    "sg:classifiers":[
        {
            "category":"Real Estate",
            "subcategory":"Real Estate Agent",
            "type":"Services"
        },
        {
            "category":"Real Estate",
            "subcategory":"Real Estate Operator",
            "type":"Services"
        }
    ],
    "sg:phone":"+1 919 954 0411",
    "sg:postcode":"27609",
    "sg:province":"NC",
    "sg:tags":[
        "building",
        "investment",
        "nonresidential"
    ],
    "wof:name":"Alpine Properties LLC",
    "wof:placetype":"venue"
},
  "geometry": {"coordinates":[-78.62070799999999,35.866591],"type":"Point"}
}