{
  "type": "Feature",
  "properties": {
    "iso:country":"US",
    "sg:address":"101 E South St",
    "sg:city":"Raleigh",
    "sg:classifiers":[
        {
            "category":"Restaurant",
            "type":"Food & Drink"
        }
    ],
    "sg:phone":"+1 919 833 7800",
    "sg:postcode":"27601",
    "sg:province":"NC",
    "wof:name":"Mc Donald's",
    "wof:placetype":"venue"
},
  "geometry": {"coordinates":[-78.63746399999999,35.772097],"type":"Point"}
}