{
  "type": "Feature",
  "properties": {
    "iso:country":"US",
    "sg:address":"282 E Millbrook Rd",
    "sg:city":"Raleigh",
    "sg:classifiers":[
        {
            "category":"Insurance",
            "subcategory":"Insurance Agent",
            "type":"Services"
        }
    ],
    "sg:phone":"+1 919 844 2995",
    "sg:postcode":"27609",
    "sg:province":"NC",
    "wof:name":"Clark Insurance Co",
    "wof:placetype":"venue"
},
  "geometry": {"coordinates":[-78.638223,35.855148],"type":"Point"}
}