{
  "type": "Feature",
  "properties": {
    "addr:full":"2229 US Hwy 17 Little River SC 29566",
    "addr:housenumber":"2229",
    "addr:postcode":"29566",
    "addr:street":"Us Hwy 17",
    "iso:country":"US",
    "sg:address":"2229 US Hwy 17",
    "sg:city":"Little River",
    "sg:classifiers":[
        {
            "category":"Wholesale",
            "subcategory":"Drugs",
            "type":"Manufacturing & Wholesale Goods"
        }
    ],
    "sg:phone":"+1 843 249 7488",
    "sg:postcode":"29566",
    "sg:province":"SC",
    "sg:tags":[
        "perfume"
    ],
    "wof:name":"Scents Unlimited",
    "wof:placetype":"venue"
},
  "geometry": {"coordinates":[-78.597493,33.886575],"type":"Point"}
}