{
  "type": "Feature",
  "properties": {
    "addr:full":"7 Oak St Belmont NC 28012",
    "addr:housenumber":"7",
    "addr:postcode":"28012",
    "addr:street":"Oak St",
    "iso:country":"US",
    "sg:address":"7 Oak St",
    "sg:city":"Belmont",
    "sg:classifiers":[
        {
            "category":"Retail",
            "subcategory":"Repair Shop",
            "type":"Services"
        }
    ],
    "sg:phone":"+1 704 829 0367",
    "sg:postcode":"28012",
    "sg:province":"NC",
    "sg:tags":[
        "real estate"
    ],
    "wof:name":"Cottage Kepers Gaston Coun LLC",
    "wof:placetype":"venue"
},
  "geometry": {"coordinates":[-81.043764,35.239069],"type":"Point"}
}