{
  "type": "Feature",
  "properties": {
    "addr:full":"2004 Yonkers Rd Raleigh NC 27604",
    "addr:housenumber":"2004",
    "addr:postcode":"27604",
    "addr:street":"Yonkers Rd",
    "iso:country":"US",
    "sg:address":"2004 Yonkers Rd",
    "sg:city":"Raleigh",
    "sg:classifiers":[
        {
            "category":"Home & Garden",
            "subcategory":"Furniture",
            "type":"Retail Goods"
        }
    ],
    "sg:phone":"+1 919 754 9754",
    "sg:postcode":"27604",
    "sg:province":"NC",
    "wof:name":"Green Front Interiors & Rugs",
    "wof:placetype":"venue"
},
  "geometry": {"coordinates":[-78.603131,35.810805],"type":"Point"}
}