{
  "type": "Feature",
  "properties": {
    "iso:country":"US",
    "sg:address":"1971 Lyons St",
    "sg:city":"Winston Salem",
    "sg:classifiers":[
        {
            "category":"Communications",
            "subcategory":"Film & Video Production",
            "type":"Services"
        }
    ],
    "sg:phone":"+1   ",
    "sg:postcode":"27107",
    "sg:province":"NC",
    "sg:tags":[
        "motion"
    ],
    "wof:name":"Miracle Presentations",
    "wof:placetype":"venue"
},
  "geometry": {"coordinates":[-80.19750500000001,36.074259],"type":"Point"}
}