{
  "type": "Feature",
  "properties": {
    "iso:country":"US",
    "sg:address":"2750 N Roberts Ave",
    "sg:city":"Lumberton",
    "sg:classifiers":[
        {
            "category":"Retail",
            "subcategory":"Portrait Studio",
            "type":"Services"
        }
    ],
    "sg:phone":"+1 910 272 9960",
    "sg:postcode":"28358",
    "sg:province":"NC",
    "wof:name":"Olan Mills Studios",
    "wof:placetype":"venue"
},
  "geometry": {"coordinates":[-79.011743,34.644828],"type":"Point"}
}