{
  "type": "Feature",
  "properties": {
    "iso:country":"US",
    "sg:address":"4831 State Hwy 55",
    "sg:city":"Durham",
    "sg:classifiers":[
        {
            "category":"Restaurant",
            "type":"Food & Drink"
        }
    ],
    "sg:phone":"+1 919 544 8385",
    "sg:postcode":"27713",
    "sg:province":"NC",
    "wof:name":"Mr Wok",
    "wof:placetype":"venue"
},
  "geometry": {"coordinates":[-78.896518,35.898901],"type":"Point"}
}