{
  "type": "Feature",
  "properties": {
    "addr:full":"290 Griffith St Davidson NC 28036",
    "addr:housenumber":"290",
    "addr:postcode":"28036",
    "addr:street":"Griffith St",
    "iso:country":"US",
    "sg:address":"290 Griffith St",
    "sg:city":"Davidson",
    "sg:classifiers":[
        {
            "category":"Manufacturing",
            "subcategory":"Metals",
            "type":"Manufacturing & Wholesale Goods"
        }
    ],
    "sg:phone":"+1 704 892 8832",
    "sg:postcode":"28036",
    "sg:province":"NC",
    "sg:tags":[
        "fabricator",
        "sheet"
    ],
    "wof:name":"Sadler Industries Inc",
    "wof:placetype":"venue"
},
  "geometry": {"coordinates":[-80.84918500000001,35.502516],"type":"Point"}
}