{
  "type": "Feature",
  "properties": {
    "iso:country":"US",
    "sg:address":"500 S Cannon Blvd",
    "sg:city":"Kannapolis",
    "sg:classifiers":[
        {
            "category":"Real Estate",
            "subcategory":"Developer",
            "type":"Services"
        }
    ],
    "sg:phone":"+1 704 933 2231",
    "sg:postcode":"28083",
    "sg:province":"NC",
    "sg:tags":[
        "builder",
        "operative"
    ],
    "wof:name":"Krea",
    "wof:placetype":"venue"
},
  "geometry": {"coordinates":[-80.61122899999999,35.49021],"type":"Point"}
}