{
  "type": "Feature",
  "properties": {
    "iso:country":"US",
    "sg:address":"741 Kenilworth Ave",
    "sg:city":"Charlotte",
    "sg:classifiers":[
        {
            "category":"Professional",
            "subcategory":"Lawyer & Legal Services",
            "type":"Services"
        }
    ],
    "sg:phone":"+1 704 375 8461",
    "sg:postcode":"28204",
    "sg:province":"NC",
    "sg:tags":[
        "attorney",
        "law",
        "administrative",
        "governmental"
    ],
    "sg:website":"http://www.fergusonstein.com",
    "wof:name":"Ferguson Stein Wallas",
    "wof:placetype":"venue"
},
  "geometry": {"coordinates":[-80.83746499999999,35.210166],"type":"Point"}
}