{
  "type": "Feature",
  "properties": {
    "addr:full":"333 Temple St Lexington NC 27292",
    "addr:housenumber":"333",
    "addr:postcode":"27292",
    "addr:street":"Temple St",
    "iso:country":"US",
    "sg:address":"333 Temple St",
    "sg:city":"Lexington",
    "sg:classifiers":[
        {
            "category":"Wholesale",
            "subcategory":"Computers",
            "type":"Manufacturing & Wholesale Goods"
        }
    ],
    "sg:phone":"+1 704 246 2982",
    "sg:postcode":"27292",
    "sg:province":"NC",
    "wof:name":"Young Tax & Accounting Svc",
    "wof:placetype":"venue"
},
  "geometry": {"coordinates":[-80.252633,35.833843],"type":"Point"}
}