{
  "type": "Feature",
  "properties": {
    "iso:country":"US",
    "sg:address":"902 Meadow St S",
    "sg:city":"Wilson",
    "sg:classifiers":[
        {
            "category":"Shopping",
            "type":"Retail Goods"
        }
    ],
    "sg:phone":"+1 252 291 2548",
    "sg:postcode":"27893",
    "sg:province":"NC",
    "sg:tags":[
        "merchandise"
    ],
    "wof:name":"Bnw Express Office Supplies",
    "wof:placetype":"venue"
},
  "geometry": {"coordinates":[-77.91904100000001,35.714284],"type":"Point"}
}