{
  "type": "Feature",
  "properties": {
    "iso:country":"US",
    "sg:address":"1403 Forest Ridge Dr",
    "sg:city":"Stanley",
    "sg:classifiers":[
        {
            "category":"Building & Trades",
            "subcategory":"Construction",
            "type":"Services"
        }
    ],
    "sg:phone":"+1 704 822 9527",
    "sg:postcode":"28164",
    "sg:province":"NC",
    "sg:tags":[
        "house"
    ],
    "wof:name":"Pewter Construction Co",
    "wof:placetype":"venue"
},
  "geometry": {"coordinates":[-80.990906,35.418936],"type":"Point"}
}