{
  "type": "Feature",
  "properties": {
    "addr:full":"2618 New Village Way Wilmington NC 28405",
    "addr:housenumber":"2618",
    "addr:postcode":"28405",
    "addr:street":"New Village Way",
    "iso:country":"US",
    "sg:address":"2618 New Village Way",
    "sg:city":"Wilmington",
    "sg:classifiers":[
        {
            "category":"Real Estate",
            "subcategory":"Developer",
            "type":"Services"
        }
    ],
    "sg:phone":"+1 910 251 8543",
    "sg:postcode":"28405",
    "sg:province":"NC",
    "sg:tags":[
        "insurance"
    ],
    "wof:name":"Williamson Group",
    "wof:placetype":"venue"
},
  "geometry": {"coordinates":[-77.875545,34.297219],"type":"Point"}
}