{
  "type": "Feature",
  "properties": {
    "addr:full":"211 Hillcrest Dr Harrisburg NC 28075",
    "addr:housenumber":"211",
    "addr:postcode":"28075",
    "addr:street":"Hillcrest Dr",
    "iso:country":"US",
    "sg:address":"211 Hillcrest Dr",
    "sg:city":"Harrisburg",
    "sg:classifiers":[
        {
            "category":"Retail",
            "subcategory":"Repair Shop",
            "type":"Services"
        }
    ],
    "sg:phone":"+1   ",
    "sg:postcode":"28075",
    "sg:province":"NC",
    "wof:name":"Honda Shop Inc",
    "wof:placetype":"venue"
},
  "geometry": {"coordinates":[-80.66813999999999,35.326764],"type":"Point"}
}