{
  "type": "Feature",
  "properties": {
    "addr:full":"206 S Churton St Hillsborough NC 27278",
    "addr:housenumber":"206",
    "addr:postcode":"27278",
    "addr:street":"S Churton St",
    "iso:country":"US",
    "sg:address":"206 S Churton St",
    "sg:city":"Hillsborough",
    "sg:classifiers":[
        {
            "category":"Government",
            "subcategory":"Fire Station",
            "type":"Public Place"
        }
    ],
    "sg:phone":"+1 919 732 7911",
    "sg:postcode":"27278",
    "sg:province":"NC",
    "sg:tags":[
        "department"
    ],
    "sg:website":"www.orfd.org",
    "wof:name":"Hillsborough Fire Dept",
    "wof:placetype":"venue"
},
  "geometry": {"coordinates":[-79.09938699999999,36.074269],"type":"Point"}
}