{
  "type": "Feature",
  "properties": {
    "addr:full":"30 Carlton Pl Asheville NC 28806",
    "addr:housenumber":"30",
    "addr:postcode":"28806",
    "addr:street":"Carlton Pl",
    "iso:country":"US",
    "sg:address":"30 Carlton Pl",
    "sg:city":"Asheville",
    "sg:classifiers":[
        {
            "category":"Building & Trades",
            "subcategory":"Cleaning & Sanitation",
            "type":"Services"
        }
    ],
    "sg:phone":"+1   ",
    "sg:postcode":"28806",
    "sg:province":"NC",
    "sg:tags":[
        "maintenance"
    ],
    "wof:name":"Coleman Services Inc",
    "wof:placetype":"venue"
},
  "geometry": {"coordinates":[-82.60181799999999,35.588137],"type":"Point"}
}