{
  "type": "Feature",
  "properties": {
    "addr:full":"2002 S Glenburnie Rd New Bern NC 28562",
    "addr:housenumber":"2002",
    "addr:postcode":"28562",
    "addr:street":"S Glenburnie Rd",
    "iso:country":"US",
    "sg:address":"2002 S Glenburnie Rd",
    "sg:city":"New Bern",
    "sg:classifiers":[
        {
            "category":"Building & Trades",
            "subcategory":"Construction",
            "type":"Services"
        }
    ],
    "sg:phone":"+1 252 635 1420",
    "sg:postcode":"28562",
    "sg:province":"NC",
    "sg:tags":[
        "heavy",
        "contractor"
    ],
    "wof:name":"Atd Land Prep Inc",
    "wof:placetype":"venue"
},
  "geometry": {"coordinates":[-77.099418,35.101901],"type":"Point"}
}