{
  "type": "Feature",
  "properties": {
    "addr:full":"1059 Swan Point Reef Rd Washington NC 27889",
    "addr:housenumber":"1059",
    "addr:postcode":"27889",
    "addr:street":"Swan Point Reef Rd",
    "iso:country":"US",
    "sg:address":"1059 Swan Point Reef Rd",
    "sg:city":"Washington",
    "sg:classifiers":[
        {
            "category":"Retail",
            "subcategory":"Auto Repair",
            "type":"Services"
        }
    ],
    "sg:phone":"+1   ",
    "sg:postcode":"27889",
    "sg:province":"NC",
    "sg:tags":[
        "shop",
        "absorber",
        "shock",
        "brake",
        "muffler",
        "replacement"
    ],
    "wof:name":"Meineke Discount Mufflers",
    "wof:placetype":"venue"
},
  "geometry": {"coordinates":[-76.979659,35.486],"type":"Point"}
}