{
  "type": "Feature",
  "properties": {
    "iso:country":"US",
    "sg:address":"2801 Royall Ave",
    "sg:city":"Goldsboro",
    "sg:classifiers":[
        {
            "category":"Manufacturing",
            "subcategory":"Printing",
            "type":"Manufacturing & Wholesale Goods"
        }
    ],
    "sg:phone":"+1 919 778 5166",
    "sg:postcode":"27534",
    "sg:province":"NC",
    "sg:tags":[
        "commercial"
    ],
    "wof:name":"Goldsboro Record Printing",
    "wof:placetype":"venue"
},
  "geometry": {"coordinates":[-77.93385499999999,35.379844],"type":"Point"}
}