{
  "type": "Feature",
  "properties": {
    "iso:country":"US",
    "sg:address":"5255 Edgar Rd",
    "sg:city":"Trinity",
    "sg:classifiers":[
        {
            "category":"Building & Trades",
            "subcategory":"Construction",
            "type":"Services"
        }
    ],
    "sg:phone":"+1 336 431 7989",
    "sg:postcode":"27350",
    "sg:province":"NC",
    "sg:tags":[
        "masonry",
        "contractor"
    ],
    "wof:name":"Bueno Masonary",
    "wof:placetype":"venue"
},
  "geometry": {"coordinates":[-79.90475499999999,35.855239],"type":"Point"}
}