{
  "type": "Feature",
  "properties": {
    "iso:country":"US",
    "sg:address":"106 Maldon Dr",
    "sg:city":"Cary",
    "sg:classifiers":[
        {
            "category":"Wholesale",
            "subcategory":"Electrical",
            "type":"Manufacturing & Wholesale Goods"
        }
    ],
    "sg:phone":"+1 919 460 5362",
    "sg:postcode":"27513",
    "sg:province":"NC",
    "sg:tags":[
        "electronic"
    ],
    "wof:name":"Coilcraft Incorporated",
    "wof:placetype":"venue"
},
  "geometry": {"coordinates":[-78.83466300000001,35.779958],"type":"Point"}
}