{
  "type": "Feature",
  "properties": {
    "iso:country":"US",
    "sg:address":"1005 Delventon Ct",
    "sg:city":"Raleigh",
    "sg:classifiers":[
        {
            "category":"Manufacturing",
            "subcategory":"Chemicals & Compounds",
            "type":"Manufacturing & Wholesale Goods"
        }
    ],
    "sg:phone":"+1 919 847 5006",
    "sg:postcode":"27614",
    "sg:province":"NC",
    "sg:tags":[
        "plastic"
    ],
    "wof:name":"Plastic Express Corp",
    "wof:placetype":"venue"
},
  "geometry": {"coordinates":[-78.627441,35.923888],"type":"Point"}
}