{
  "type": "Feature",
  "properties": {
    "addr:full":"1994 State Hwy 581 N Pikeville NC 27863",
    "addr:housenumber":"1994",
    "addr:postcode":"27863",
    "addr:street":"State Hwy 581 N",
    "iso:country":"US",
    "sg:address":"1994 State Hwy 581 N",
    "sg:city":"Pikeville",
    "sg:classifiers":[
        {
            "category":"Insurance",
            "subcategory":"Insurance Agent",
            "type":"Services"
        }
    ],
    "sg:phone":"+1 919 736 7731",
    "sg:postcode":"27863",
    "sg:province":"NC",
    "wof:name":"Wanda Jones Insurance Svc Inc",
    "wof:placetype":"venue"
},
  "geometry": {"coordinates":[-78.05613700000001,35.477858],"type":"Point"}
}