{
  "type": "Feature",
  "properties": {
    "iso:country":"US",
    "sg:address":"12011 Cartgate Ln",
    "sg:city":"Charlotte",
    "sg:classifiers":[
        {
            "category":"Personal",
            "type":"Services"
        }
    ],
    "sg:phone":"+1   ",
    "sg:postcode":"28273",
    "sg:province":"NC",
    "wof:name":"Maeya & Associates",
    "wof:placetype":"venue"
},
  "geometry": {"coordinates":[-80.972444,35.10959],"type":"Point"}
}