{
  "type": "Feature",
  "properties": {
    "iso:country":"US",
    "sg:address":"3716 Auburn Church Rd",
    "sg:city":"Garner",
    "sg:classifiers":[
        {
            "category":"Building & Trades",
            "subcategory":"Plumbing",
            "type":"Services"
        }
    ],
    "sg:phone":"+1 919 772 1346",
    "sg:postcode":"27529",
    "sg:province":"NC",
    "sg:tags":[
        "plumbing",
        "contractor"
    ],
    "wof:name":"American Plumbing Co Inc",
    "wof:placetype":"venue"
},
  "geometry": {"coordinates":[-78.577101,35.729334],"type":"Point"}
}