{
  "type": "Feature",
  "properties": {
    "addr:full":"10801 Johnston Rd Charlotte NC 28226",
    "addr:housenumber":"10801",
    "addr:postcode":"28226",
    "addr:street":"Johnston Rd",
    "iso:country":"US",
    "sg:address":"10801 Johnston Rd",
    "sg:city":"Charlotte",
    "sg:classifiers":[
        {
            "category":"Professional",
            "subcategory":"Management & Consulting",
            "type":"Services"
        }
    ],
    "sg:phone":"+1   ",
    "sg:postcode":"28226",
    "sg:province":"NC",
    "sg:tags":[
        "food",
        "product",
        "exporter"
    ],
    "wof:name":"Bnr Global Inc",
    "wof:placetype":"venue"
},
  "geometry": {"coordinates":[-80.85268499999999,35.085198],"type":"Point"}
}