{
  "type": "Feature",
  "properties": {
    "addr:full":"235 Fairmont Dr North Wilkesboro NC 28659",
    "addr:housenumber":"235",
    "addr:postcode":"28659",
    "addr:street":"Fairmont Dr",
    "iso:country":"US",
    "sg:address":"235 Fairmont Dr",
    "sg:city":"North Wilkesboro",
    "sg:classifiers":[
        {
            "category":"Building & Trades",
            "subcategory":"Electrical",
            "type":"Services"
        }
    ],
    "sg:phone":"+1 336 838 3850",
    "sg:postcode":"28659",
    "sg:province":"NC",
    "sg:tags":[
        "electrical",
        "contractor"
    ],
    "wof:name":"Michael Davidson Electric",
    "wof:placetype":"venue"
},
  "geometry": {"coordinates":[-81.14828799999999,36.203282],"type":"Point"}
}