{
  "type": "Feature",
  "properties": {
    "iso:country":"US",
    "sg:address":"19 Myrtle Ct",
    "sg:city":"Wrightsville Beach",
    "sg:classifiers":[
        {
            "category":"Building & Trades",
            "subcategory":"Construction",
            "type":"Services"
        }
    ],
    "sg:phone":"+1 910 256 5947",
    "sg:postcode":"28480",
    "sg:province":"NC",
    "sg:tags":[
        "carpentry",
        "contractor"
    ],
    "wof:name":"Carlyle Gee Carpentry",
    "wof:placetype":"venue"
},
  "geometry": {"coordinates":[-77.80304599999999,34.209456],"type":"Point"}
}