{
  "type": "Feature",
  "properties": {
    "iso:country":"US",
    "sg:address":"1257 Tommys Rd",
    "sg:city":"Goldsboro",
    "sg:classifiers":[
        {
            "category":"Professional",
            "type":"Services"
        }
    ],
    "sg:phone":"+1 919 734 9002",
    "sg:postcode":"27534",
    "sg:province":"NC",
    "sg:tags":[
        "establishment"
    ],
    "wof:name":"Anchormen Inc",
    "wof:placetype":"venue"
},
  "geometry": {"coordinates":[-77.934208,35.41336],"type":"Point"}
}