{
  "type": "Feature",
  "properties": {
    "addr:full":"13513 US Hwy 70 W Clayton NC 27520",
    "addr:housenumber":"13513",
    "addr:postcode":"27520",
    "addr:street":"Us Hwy 70 W",
    "iso:country":"US",
    "sg:address":"13513 US Hwy 70 W",
    "sg:city":"Clayton",
    "sg:classifiers":[
        {
            "category":"Autos & Motor Vehicles",
            "subcategory":"Automobile Sales",
            "type":"Retail Goods"
        }
    ],
    "sg:phone":"+1 919 828 8837",
    "sg:postcode":"27520",
    "sg:province":"NC",
    "sg:tags":[
        "car",
        "dealer"
    ],
    "wof:name":"Highway 70",
    "wof:placetype":"venue"
},
  "geometry": {"coordinates":[-78.50801300000001,35.670167],"type":"Point"}
}