{
  "type": "Feature",
  "properties": {
    "addr:full":"112 N Winstead Ave Rocky Mount NC 27804",
    "addr:housenumber":"112",
    "addr:postcode":"27804",
    "addr:street":"N Winstead Ave",
    "iso:country":"US",
    "sg:address":"112 N Winstead Ave",
    "sg:city":"Rocky Mount",
    "sg:classifiers":[
        {
            "category":"Health Services",
            "subcategory":"Chiropractor",
            "type":"Services"
        }
    ],
    "sg:phone":"+1 252 443 7496",
    "sg:postcode":"27804",
    "sg:province":"NC",
    "sg:tags":[
        "farm",
        "cotton"
    ],
    "wof:name":"Horvath Chiropractic Center",
    "wof:placetype":"venue"
},
  "geometry": {"coordinates":[-77.849695,35.966162],"type":"Point"}
}