{
  "type": "Feature",
  "properties": {
    "addr:full":"175 Bethany Church Rd Winston Salem NC 27107",
    "addr:housenumber":"175",
    "addr:postcode":"27107",
    "addr:street":"Bethany Church Rd",
    "iso:country":"US",
    "sg:address":"175 Bethany Church Rd",
    "sg:city":"Winston Salem",
    "sg:classifiers":[
        {
            "category":"Building & Trades",
            "subcategory":"Construction",
            "type":"Services"
        }
    ],
    "sg:phone":"+1 336 769 4338",
    "sg:postcode":"27107",
    "sg:province":"NC",
    "sg:tags":[
        "house"
    ],
    "wof:name":"Steve Clodfelter Const",
    "wof:placetype":"venue"
},
  "geometry": {"coordinates":[-80.175691,35.948724],"type":"Point"}
}