{
  "type": "Feature",
  "properties": {
    "addr:full":"19001 Stone Brook Chapel Hill NC 27517",
    "addr:housenumber":"19001",
    "addr:postcode":"27517",
    "addr:street":"Stone Brook",
    "iso:country":"US",
    "sg:address":"19001 Stone Brook",
    "sg:city":"Chapel Hill",
    "sg:classifiers":[
        {
            "category":"Building & Trades",
            "subcategory":"Construction",
            "type":"Services"
        }
    ],
    "sg:phone":"+1 919 932 9049",
    "sg:postcode":"27517",
    "sg:province":"NC",
    "sg:tags":[
        "maintenance",
        "contractor"
    ],
    "wof:name":"Stone Brook Maintenance",
    "wof:placetype":"venue"
},
  "geometry": {"coordinates":[-79.059589,35.842294],"type":"Point"}
}