{
  "type": "Feature",
  "properties": {
    "addr:full":"115 Morris St Blowing Rock NC 28605",
    "addr:housenumber":"115",
    "addr:postcode":"28605",
    "addr:street":"Morris St",
    "iso:country":"US",
    "sg:address":"115 Morris St",
    "sg:city":"Blowing Rock",
    "sg:classifiers":[
        {
            "category":"Home & Garden",
            "subcategory":"Garden Supply",
            "type":"Retail Goods"
        }
    ],
    "sg:phone":"+1 828 295 6305",
    "sg:postcode":"28605",
    "sg:province":"NC",
    "sg:tags":[
        "center"
    ],
    "wof:name":"Chiminea Express",
    "wof:placetype":"venue"
},
  "geometry": {"coordinates":[-81.67605399999999,36.130781],"type":"Point"}
}