{
  "type": "Feature",
  "properties": {
    "addr:full":"22 N Market St Asheville NC 28801",
    "addr:housenumber":"22",
    "addr:postcode":"28801",
    "addr:street":"N Market St",
    "iso:country":"US",
    "sg:address":"22 N Market St",
    "sg:city":"Asheville",
    "sg:classifiers":[
        {
            "category":"Bars & Pubs",
            "type":"Food & Drink"
        }
    ],
    "sg:phone":"+1 828 254 0835",
    "sg:postcode":"28801",
    "sg:province":"NC",
    "sg:tags":[
        "club",
        "night"
    ],
    "wof:name":"Cinjades",
    "wof:placetype":"venue"
},
  "geometry": {"coordinates":[-82.550906,35.596201],"type":"Point"}
}