{
  "type": "Feature",
  "properties": {
    "addr:full":"7351 Richardson Rd Castalia NC 27816",
    "addr:housenumber":"7351",
    "addr:postcode":"27816",
    "addr:street":"Richardson Rd",
    "iso:country":"US",
    "sg:address":"7351 Richardson Rd",
    "sg:city":"Castalia",
    "sg:classifiers":[
        {
            "category":"Retail",
            "subcategory":"Auto Repair",
            "type":"Services"
        }
    ],
    "sg:phone":"+1 252 459 2835",
    "sg:postcode":"27816",
    "sg:province":"NC",
    "sg:tags":[
        "repairing",
        "automobile"
    ],
    "wof:name":"Person's Garage",
    "wof:placetype":"venue"
},
  "geometry": {"coordinates":[-78.04638300000001,36.069245],"type":"Point"}
}