{
  "type": "Feature",
  "properties": {
    "addr:full":"8631 Tullamore Park Cir Charlotte NC 28226",
    "addr:housenumber":"8631",
    "addr:postcode":"28226",
    "addr:street":"Tullamore Park Cir",
    "iso:country":"US",
    "sg:address":"8631 Tullamore Park Cir",
    "sg:city":"Charlotte",
    "sg:classifiers":[
        {
            "category":"Food & Beverages",
            "subcategory":"Groceries & Convenience Stores",
            "type":"Retail Goods"
        }
    ],
    "sg:phone":"+1 704 541 5696",
    "sg:postcode":"28226",
    "sg:province":"NC",
    "wof:name":"Southern Food Group Inc",
    "wof:placetype":"venue"
},
  "geometry": {"coordinates":[-80.82377200000001,35.08793],"type":"Point"}
}