{
  "type": "Feature",
  "properties": {
    "addr:full":"710 Char-Meck Ln Charlotte NC 28205",
    "addr:housenumber":"710",
    "addr:postcode":"28205",
    "addr:street":"Char-Meck Ln",
    "iso:country":"US",
    "sg:address":"710 Char-Meck Ln",
    "sg:city":"Charlotte",
    "sg:classifiers":[
        {
            "category":"Retail",
            "subcategory":"Funeral Services",
            "type":"Services"
        }
    ],
    "sg:phone":"+1 704 000 1111",
    "sg:postcode":"28205",
    "sg:province":"NC",
    "sg:tags":[
        "director"
    ],
    "wof:name":"Carolina Mortuary Svc",
    "wof:placetype":"venue"
},
  "geometry": {"coordinates":[-80.789458,35.196213],"type":"Point"}
}