{
  "type": "Feature",
  "properties": {
    "addr:full":"2116 Capital Dr Wilmington NC 28405",
    "addr:housenumber":"2116",
    "addr:postcode":"28405",
    "addr:street":"Capital Dr",
    "iso:country":"US",
    "sg:address":"2116 Capital Dr",
    "sg:city":"Wilmington",
    "sg:classifiers":[
        {
            "category":"Professional",
            "subcategory":"Management & Consulting",
            "type":"Services"
        }
    ],
    "sg:phone":"+1 910 792 1422",
    "sg:postcode":"28405",
    "sg:province":"NC",
    "sg:tags":[
        "employee",
        "consultant",
        "benefit",
        "business"
    ],
    "sg:website":"www.wellingtonbenefits.com",
    "wof:name":"Wellington Benefits Inc",
    "wof:placetype":"venue"
},
  "geometry": {"coordinates":[-77.874191,34.283228],"type":"Point"}
}