{
  "type": "Feature",
  "properties": {
    "addr:full":"11828 Doc Arnold Dr Raleigh NC 27614",
    "addr:housenumber":"11828",
    "addr:postcode":"27614",
    "addr:street":"Doc Arnold Dr",
    "iso:country":"US",
    "sg:address":"11828 Doc Arnold Dr",
    "sg:city":"Raleigh",
    "sg:classifiers":[
        {
            "category":"Insurance",
            "subcategory":"Insurance Agent",
            "type":"Services"
        }
    ],
    "sg:phone":"+1 919 848 9888",
    "sg:postcode":"27614",
    "sg:province":"NC",
    "wof:name":"David White Insurance Agency",
    "wof:placetype":"venue"
},
  "geometry": {"coordinates":[-78.685671,35.969263],"type":"Point"}
}