{
  "type": "Feature",
  "properties": {
    "addr:full":"2057 Mount Moriah Rd Rowland NC 28383",
    "addr:housenumber":"2057",
    "addr:postcode":"28383",
    "addr:street":"Mount Moriah Rd",
    "iso:country":"US",
    "sg:address":"2057 Mount Moriah Rd",
    "sg:city":"Rowland",
    "sg:classifiers":[
        {
            "category":"Farming",
            "subcategory":"Farm",
            "type":"Manufacturing & Wholesale Goods"
        }
    ],
    "sg:phone":"+1 910 521 7222",
    "sg:postcode":"28383",
    "sg:province":"NC",
    "wof:name":"Miller Farms Of Rowland Inc",
    "wof:placetype":"venue"
},
  "geometry": {"coordinates":[-79.309646,34.624319],"type":"Point"}
}