{
  "type": "Feature",
  "properties": {
    "iso:country":"US",
    "sg:address":"3445 Muddy Creek Rd",
    "sg:city":"Nebo",
    "sg:classifiers":[
        {
            "category":"Building & Trades",
            "subcategory":"Plumbing",
            "type":"Services"
        }
    ],
    "sg:phone":"+1 828 584 2713",
    "sg:postcode":"28761",
    "sg:province":"NC",
    "sg:tags":[
        "plumbing",
        "contractor"
    ],
    "wof:name":"Bob Fox Plumbing Co",
    "wof:placetype":"venue"
},
  "geometry": {"coordinates":[-81.863204,35.709199],"type":"Point"}
}