{
  "type": "Feature",
  "properties": {
    "addr:full":"117 Forest Hills Dr Black Mountain NC 28711",
    "addr:housenumber":"117",
    "addr:postcode":"28711",
    "addr:street":"Forest Hills Dr",
    "iso:country":"US",
    "sg:address":"117 Forest Hills Dr",
    "sg:city":"Black Mountain",
    "sg:classifiers":[
        {
            "category":"Professional",
            "type":"Services"
        }
    ],
    "sg:phone":"+1 828 669 9101",
    "sg:postcode":"28711",
    "sg:province":"NC",
    "wof:name":"Jwall LLC",
    "wof:placetype":"venue"
},
  "geometry": {"coordinates":[-82.314334,35.602238],"type":"Point"}
}