{
  "type": "Feature",
  "properties": {
    "iso:country":"US",
    "sg:address":"107 Westwood Shopping Center",
    "sg:city":"Fayetteville",
    "sg:classifiers":[
        {
            "category":"Shopping",
            "subcategory":"Florist",
            "type":"Retail Goods"
        }
    ],
    "sg:phone":"+1 910 867 2900",
    "sg:postcode":"28314",
    "sg:province":"NC",
    "wof:name":"Always Flowers By Crensha Inc",
    "wof:placetype":"venue"
},
  "geometry": {"coordinates":[-78.95303,35.066503],"type":"Point"}
}