{
  "type": "Feature",
  "properties": {
    "addr:full":"105 3rd St SW Hickory NC 28602",
    "addr:housenumber":"105",
    "addr:postcode":"28602",
    "addr:street":"3Rd St Sw",
    "iso:country":"US",
    "sg:address":"105 3rd St SW",
    "sg:city":"Hickory",
    "sg:classifiers":[
        {
            "category":"Building & Trades",
            "subcategory":"Construction",
            "type":"Services"
        }
    ],
    "sg:phone":"+1 828 261 2099",
    "sg:postcode":"28602",
    "sg:province":"NC",
    "sg:tags":[
        "maker",
        "cabinet"
    ],
    "wof:name":"Circle T Custom Cabinetry",
    "wof:placetype":"venue"
},
  "geometry": {"coordinates":[-81.34212599999999,35.729964],"type":"Point"}
}