{
  "type": "Feature",
  "properties": {
    "addr:full":"1310 Peace Rd New Bern NC 28560",
    "addr:housenumber":"1310",
    "addr:postcode":"28560",
    "addr:street":"Peace Rd",
    "iso:country":"US",
    "sg:address":"1310 Peace Rd",
    "sg:city":"New Bern",
    "sg:classifiers":[
        {
            "category":"Professional",
            "subcategory":"Business Services",
            "type":"Services"
        }
    ],
    "sg:phone":"+1   ",
    "sg:postcode":"28560",
    "sg:province":"NC",
    "sg:tags":[
        "translation"
    ],
    "wof:name":"Brigitte J Setzer",
    "wof:placetype":"venue"
},
  "geometry": {"coordinates":[-77.089687,35.128121],"type":"Point"}
}