{
  "type": "Feature",
  "properties": {
    "addr:full":"913 Kathryn St Cary NC 27511",
    "addr:housenumber":"913",
    "addr:postcode":"27511",
    "addr:street":"Kathryn St",
    "iso:country":"US",
    "sg:address":"913 Kathryn St",
    "sg:city":"Cary",
    "sg:classifiers":[
        {
            "category":"Wholesale",
            "subcategory":"Non-durable Goods",
            "type":"Manufacturing & Wholesale Goods"
        }
    ],
    "sg:phone":"+1 919 468 9570",
    "sg:postcode":"27511",
    "sg:province":"NC",
    "sg:tags":[
        "specialty"
    ],
    "wof:name":"Acclamtons Advg Spclty Prmtons",
    "wof:placetype":"venue"
},
  "geometry": {"coordinates":[-78.772655,35.772091],"type":"Point"}
}