{
  "type": "Feature",
  "properties": {
    "iso:country":"US",
    "sg:address":"816 E Arrowood Rd",
    "sg:city":"Charlotte",
    "sg:classifiers":[
        {
            "category":"Utilities",
            "subcategory":"Mobile Phone",
            "type":"Services"
        }
    ],
    "sg:phone":"+1 704 552 6600",
    "sg:postcode":"28217",
    "sg:province":"NC",
    "sg:tags":[
        "telephone",
        "cellular"
    ],
    "wof:name":"Moretel Wireless",
    "wof:placetype":"venue"
},
  "geometry": {"coordinates":[-80.87821700000001,35.137625],"type":"Point"}
}