{
  "type": "Feature",
  "properties": {
    "addr:full":"6119 Harwell Rd Catawba NC 28609",
    "addr:housenumber":"6119",
    "addr:postcode":"28609",
    "addr:street":"Harwell Rd",
    "iso:country":"US",
    "sg:address":"6119 Harwell Rd",
    "sg:city":"Catawba",
    "sg:classifiers":[
        {
            "category":"Building & Trades",
            "subcategory":"Landscaping Services",
            "type":"Services"
        }
    ],
    "sg:phone":"+1 828 241 3596",
    "sg:postcode":"28609",
    "sg:province":"NC",
    "sg:tags":[
        "landscape"
    ],
    "wof:name":"Hubbard Enterprises",
    "wof:placetype":"venue"
},
  "geometry": {"coordinates":[-81.04872,35.676777],"type":"Point"}
}