{
  "type": "Feature",
  "properties": {
    "iso:country":"US",
    "sg:address":"212 W Main Ave",
    "sg:city":"Gastonia",
    "sg:classifiers":[
        {
            "category":"Government",
            "subcategory":"Office",
            "type":"Public Place"
        }
    ],
    "sg:phone":"+1 704 866 3100",
    "sg:postcode":"28052",
    "sg:province":"NC",
    "sg:website":"www.co.gaston.nc.us",
    "wof:name":"County Manager Office",
    "wof:placetype":"venue"
},
  "geometry": {"coordinates":[-81.18552699999999,35.263847],"type":"Point"}
}