{
  "type": "Feature",
  "properties": {
    "addr:full":"2806 Battleground Ave Greensboro NC 27408",
    "addr:housenumber":"2806",
    "addr:postcode":"27408",
    "addr:street":"Battleground Ave",
    "iso:country":"US",
    "sg:address":"2806 Battleground Ave",
    "sg:city":"Greensboro",
    "sg:classifiers":[
        {
            "category":"Shopping",
            "subcategory":"Clothing, Apparel, & Fashions",
            "type":"Retail Goods"
        }
    ],
    "sg:phone":"+1 866 587 5177",
    "sg:postcode":"27408",
    "sg:province":"NC",
    "sg:tags":[
        "clothing",
        "store"
    ],
    "sg:website":"http://national.citysearch.com/profile/external/6145090/greensboro_nc/men_s_wearhouse.html?publisher=yellowpages&reference_id=1&placement=ypwebsitemip",
    "wof:name":"Men's Wearhouse",
    "wof:placetype":"venue"
},
  "geometry": {"coordinates":[-79.830196,36.110261],"type":"Point"}
}