{
  "type": "Feature",
  "properties": {
    "addr:full":"610 York Rd Kings Mountain NC 28086",
    "addr:housenumber":"610",
    "addr:postcode":"28086",
    "addr:street":"York Rd",
    "iso:country":"US",
    "sg:address":"610 York Rd",
    "sg:city":"Kings Mountain",
    "sg:classifiers":[
        {
            "category":"Wholesale",
            "subcategory":"Machinery & Supplies",
            "type":"Manufacturing & Wholesale Goods"
        }
    ],
    "sg:phone":"+1 704 739 8319",
    "sg:postcode":"28086",
    "sg:province":"NC",
    "sg:tags":[
        "equipment",
        "welding"
    ],
    "wof:name":"Quality Tool Supply",
    "wof:placetype":"venue"
},
  "geometry": {"coordinates":[-81.33324399999999,35.233182],"type":"Point"}
}