{
  "type": "Feature",
  "properties": {
    "addr:full":"1005 Agner Rd Salisbury NC 28146",
    "addr:housenumber":"1005",
    "addr:postcode":"28146",
    "addr:street":"Agner Rd",
    "iso:country":"US",
    "sg:address":"1005 Agner Rd",
    "sg:city":"Salisbury",
    "sg:classifiers":[
        {
            "category":"Freight",
            "type":"Transportation"
        }
    ],
    "sg:phone":"+1 704 637 2881",
    "sg:postcode":"28146",
    "sg:province":"NC",
    "sg:tags":[
        "operator",
        "local",
        "expedite",
        "trucking"
    ],
    "wof:name":"Sidden Trucking Inc",
    "wof:placetype":"venue"
},
  "geometry": {"coordinates":[-80.34227199999999,35.605287],"type":"Point"}
}