{
  "type": "Feature",
  "properties": {
    "iso:country":"US",
    "sg:address":"2400 Freedom Dr",
    "sg:city":"Charlotte",
    "sg:classifiers":[
        {
            "category":"Shopping",
            "subcategory":"Discount & Variety Stores",
            "type":"Retail Goods"
        },
        {
            "category":"Shopping",
            "subcategory":"Department Store",
            "type":"Retail Goods"
        }
    ],
    "sg:phone":"+1 704 391 7631",
    "sg:postcode":"28208",
    "sg:province":"NC",
    "sg:tags":[
        "shop"
    ],
    "wof:name":"Family Dollar Stores",
    "wof:placetype":"venue"
},
  "geometry": {"coordinates":[-80.877724,35.23402],"type":"Point"}
}