{
  "type": "Feature",
  "properties": {
    "iso:country":"US",
    "sg:address":"1907 Sunset Ave",
    "sg:city":"Clinton",
    "sg:classifiers":[
        {
            "category":"Professional",
            "subcategory":"Management & Consulting",
            "type":"Services"
        }
    ],
    "sg:phone":"+1 910 596 2886",
    "sg:postcode":"28328",
    "sg:province":"NC",
    "sg:tags":[
        "consultant"
    ],
    "wof:name":"Automotive Dream",
    "wof:placetype":"venue"
},
  "geometry": {"coordinates":[-78.348043,34.991551],"type":"Point"}
}