{
  "type": "Feature",
  "properties": {
    "addr:full":"18033 Mollypop Ln Cornelius NC 28031",
    "addr:postcode":"18033;28031",
    "addr:street":"Mollypop Ln",
    "iso:country":"US",
    "sg:address":"18033 Mollypop Ln",
    "sg:city":"Cornelius",
    "sg:classifiers":[
        {
            "category":"Banks & Credit Unions",
            "subcategory":"Financial Services",
            "type":"Services"
        }
    ],
    "sg:phone":"+1 704 892 7521",
    "sg:postcode":"28031",
    "sg:province":"NC",
    "sg:tags":[
        "investor"
    ],
    "wof:name":"Lomax Investment Properties LL",
    "wof:placetype":"venue"
},
  "geometry": {"coordinates":[-80.938197,35.455882],"type":"Point"}
}