{
  "type": "Feature",
  "properties": {
    "addr:full":"1515 S Main St Mount Airy NC 27030",
    "addr:housenumber":"1515",
    "addr:postcode":"27030",
    "addr:street":"S Main St",
    "iso:country":"US",
    "sg:address":"1515 S Main St",
    "sg:city":"Mount Airy",
    "sg:classifiers":[
        {
            "category":"Retail",
            "subcategory":"Auto Repair",
            "type":"Services"
        }
    ],
    "sg:phone":"+1   ",
    "sg:postcode":"27030",
    "sg:province":"NC",
    "sg:tags":[
        "body"
    ],
    "wof:name":"Vinyl Top Shop",
    "wof:placetype":"venue"
},
  "geometry": {"coordinates":[-80.59466500000001,36.490203],"type":"Point"}
}