{
  "type": "Feature",
  "properties": {
    "iso:country":"US",
    "sg:address":"1 Terrace Way",
    "sg:city":"Greensboro",
    "sg:classifiers":[
        {
            "category":"Professional",
            "subcategory":"Advertising",
            "type":"Services"
        }
    ],
    "sg:phone":"+1 336 856 2200",
    "sg:postcode":"27403",
    "sg:province":"NC",
    "wof:name":"G M A Marketing",
    "wof:placetype":"venue"
},
  "geometry": {"coordinates":[-79.83503899999999,36.045536],"type":"Point"}
}