{
  "type": "Feature",
  "properties": {
    "addr:full":"4295 Lake Wendell Rd Wendell NC 27591",
    "addr:housenumber":"4295",
    "addr:postcode":"27591",
    "addr:street":"Lake Wendell Rd",
    "iso:country":"US",
    "sg:address":"4295 Lake Wendell Rd",
    "sg:city":"Wendell",
    "sg:classifiers":[
        {
            "category":"Building & Trades",
            "subcategory":"Landscaping Services",
            "type":"Services"
        }
    ],
    "sg:phone":"+1 919 365 9440",
    "sg:postcode":"27591",
    "sg:province":"NC",
    "sg:tags":[
        "tree",
        "landscape"
    ],
    "wof:name":"Jay's Landscaping & Tree Svc",
    "wof:placetype":"venue"
},
  "geometry": {"coordinates":[-78.324614,35.731538],"type":"Point"}
}