{
  "type": "Feature",
  "properties": {
    "iso:country":"US",
    "sg:address":"913 N Lake Park Blvd",
    "sg:city":"Carolina Beach",
    "sg:classifiers":[
        {
            "category":"Personal",
            "subcategory":"Beauty Salon",
            "type":"Services"
        }
    ],
    "sg:phone":"+1 910 458 8267",
    "sg:postcode":"28428",
    "sg:province":"NC",
    "sg:tags":[
        "hair"
    ],
    "wof:name":"Cutn Up Hair Salon",
    "wof:placetype":"venue"
},
  "geometry": {"coordinates":[-77.896804,34.041562],"type":"Point"}
}