{
  "type": "Feature",
  "properties": {
    "addr:full":"5514 Gordonvale Pl Charlotte NC 28226",
    "addr:housenumber":"5514",
    "addr:postcode":"28226",
    "addr:street":"Gordonvale Pl",
    "iso:country":"US",
    "sg:address":"5514 Gordonvale Pl",
    "sg:city":"Charlotte",
    "sg:classifiers":[
        {
            "category":"Professional",
            "subcategory":"Management & Consulting",
            "type":"Services"
        }
    ],
    "sg:phone":"+1   ",
    "sg:postcode":"28226",
    "sg:province":"NC",
    "sg:tags":[
        "business"
    ],
    "wof:name":"OSullivan Wright Consulting",
    "wof:placetype":"venue"
},
  "geometry": {"coordinates":[-80.80233200000001,35.122862],"type":"Point"}
}