{
  "type": "Feature",
  "properties": {
    "iso:country":"US",
    "sg:address":"190 Cactus Dr",
    "sg:city":"Prospect Hill",
    "sg:classifiers":[
        {
            "category":"Wholesale",
            "subcategory":"Farm Supplies",
            "type":"Manufacturing & Wholesale Goods"
        }
    ],
    "sg:phone":"+1 336 562 8053",
    "sg:postcode":"27320",
    "sg:province":"NC",
    "wof:name":"Hurdle Mills Feed Inc",
    "wof:placetype":"venue"
},
  "geometry": {"coordinates":[-79.63145299999999,36.285497],"type":"Point"}
}