{
  "type": "Feature",
  "properties": {
    "iso:country":"US",
    "sg:address":"7031 Albert Pick Rd",
    "sg:city":"Greensboro",
    "sg:classifiers":[
        {
            "category":"Banks & Credit Unions",
            "subcategory":"Bank",
            "type":"Services"
        }
    ],
    "sg:phone":"+1 336 664 5740",
    "sg:postcode":"27409",
    "sg:province":"NC",
    "sg:tags":[
        "loan",
        "real estate"
    ],
    "sg:website":"www.fullspectrumlending.com",
    "wof:name":"Full Spectrum Lending",
    "wof:placetype":"venue"
},
  "geometry": {"coordinates":[-79.953427,36.078308],"type":"Point"}
}