{
  "type": "Feature",
  "properties": {
    "iso:country":"US",
    "sg:address":"2701 Spring Garden St",
    "sg:city":"Greensboro",
    "sg:classifiers":[
        {
            "category":"Retail",
            "subcategory":"Auto Repair",
            "type":"Services"
        }
    ],
    "sg:phone":"+1 336 509 2094",
    "sg:postcode":"27403",
    "sg:province":"NC",
    "sg:tags":[
        "wrecker"
    ],
    "wof:name":"Big Toe Towing",
    "wof:placetype":"venue"
},
  "geometry": {"coordinates":[-79.83794,36.064155],"type":"Point"}
}