{
  "type": "Feature",
  "properties": {
    "iso:country":"US",
    "sg:address":"4801 Edwards Mill Rd",
    "sg:city":"Raleigh",
    "sg:classifiers":[
        {
            "category":"Social Services",
            "subcategory":"Retirement Home",
            "type":"Services"
        }
    ],
    "sg:phone":"+1 919 787 0777",
    "sg:postcode":"27612",
    "sg:province":"NC",
    "wof:name":"Brighton Gardens of Raleigh",
    "wof:placetype":"venue"
},
  "geometry": {"coordinates":[-78.68609600000001,35.838699],"type":"Point"}
}