{
  "type": "Feature",
  "properties": {
    "addr:full":"721 N Brightleaf Blvd Smithfield NC 27577",
    "addr:housenumber":"721",
    "addr:postcode":"27577",
    "addr:street":"N Brightleaf Blvd",
    "iso:country":"US",
    "sg:address":"721 N Brightleaf Blvd",
    "sg:city":"Smithfield",
    "sg:classifiers":[
        {
            "category":"Professional",
            "subcategory":"Printing & Photocopies",
            "type":"Services"
        }
    ],
    "sg:phone":"+1 919 989 7101",
    "sg:postcode":"27577",
    "sg:province":"NC",
    "sg:tags":[
        "duplicating",
        "copying"
    ],
    "sg:website":"www.quickprintsolutions.com",
    "wof:name":"Quickprint Solutions",
    "wof:placetype":"venue"
},
  "geometry": {"coordinates":[-78.328782,35.514668],"type":"Point"}
}