{
  "type": "Feature",
  "properties": {
    "addr:full":"2043 McCray Rd Burlington NC 27217",
    "addr:housenumber":"2043",
    "addr:postcode":"27217",
    "addr:street":"Mccray Rd",
    "iso:country":"US",
    "sg:address":"2043 McCray Rd",
    "sg:city":"Burlington",
    "sg:classifiers":[
        {
            "category":"Building & Trades",
            "subcategory":"Construction",
            "type":"Services"
        }
    ],
    "sg:phone":"+1 336 578 3774",
    "sg:postcode":"27217",
    "sg:province":"NC",
    "sg:tags":[
        "grading",
        "contractor"
    ],
    "wof:name":"Bud Capps Grading Inc",
    "wof:placetype":"venue"
},
  "geometry": {"coordinates":[-79.34532400000001,36.1561],"type":"Point"}
}