{
  "type": "Feature",
  "properties": {
    "addr:full":"1305 Hope Mills Rd Fayetteville NC 28304",
    "addr:housenumber":"1305",
    "addr:postcode":"28304",
    "addr:street":"Hope Mills Rd",
    "iso:country":"US",
    "sg:address":"1305 Hope Mills Rd",
    "sg:city":"Fayetteville",
    "sg:classifiers":[
        {
            "category":"Professional",
            "subcategory":"Accounting & Tax Preparation",
            "type":"Services"
        }
    ],
    "sg:phone":"+1   ",
    "sg:postcode":"28304",
    "sg:province":"NC",
    "sg:tags":[
        "return"
    ],
    "wof:name":"Wright Total Tax",
    "wof:placetype":"venue"
},
  "geometry": {"coordinates":[-78.96106,35.025635],"type":"Point"}
}