{
  "type": "Feature",
  "properties": {
    "iso:country":"US",
    "sg:address":"197 Worthguard Rd",
    "sg:city":"Coinjock",
    "sg:classifiers":[
        {
            "category":"Cinema",
            "subcategory":"Movie Rental",
            "type":"Entertainment"
        }
    ],
    "sg:phone":"+1   ",
    "sg:postcode":"27923",
    "sg:province":"NC",
    "sg:tags":[
        "video",
        "tape"
    ],
    "wof:name":"Outerbanks Video",
    "wof:placetype":"venue"
},
  "geometry": {"coordinates":[-75.95408399999999,36.34514],"type":"Point"}
}