{
  "type": "Feature",
  "properties": {
    "iso:country":"US",
    "sg:address":"1410 Jules Ct",
    "sg:city":"Charlotte",
    "sg:classifiers":[
        {
            "category":"Professional",
            "subcategory":"Computer Services",
            "type":"Services"
        }
    ],
    "sg:phone":"+1   ",
    "sg:postcode":"28226",
    "sg:province":"NC",
    "sg:tags":[
        "development",
        "software"
    ],
    "wof:name":"Bit Engine",
    "wof:placetype":"venue"
},
  "geometry": {"coordinates":[-80.78460699999999,35.128053],"type":"Point"}
}