{
  "type": "Feature",
  "properties": {
    "iso:country":"US",
    "sg:address":"3010 Wake Forest Rd",
    "sg:city":"Raleigh",
    "sg:classifiers":[
        {
            "category":"Restaurant",
            "type":"Food & Drink"
        }
    ],
    "sg:menulink":"http://www.allmenus.com/nc/raleigh/205242-taco-bell/menu/",
    "sg:phone":"+1 919 873 1889",
    "sg:postcode":"27609",
    "sg:province":"NC",
    "sg:tags":[
        "american",
        "mexican"
    ],
    "wof:name":"Taco Bell",
    "wof:placetype":"venue"
},
  "geometry": {"coordinates":[-78.622152,35.823574],"type":"Point"}
}