{
  "type": "Feature",
  "properties": {
    "iso:country":"US",
    "sg:address":"1820 Sharpe Rd",
    "sg:city":"Greensboro",
    "sg:classifiers":[
        {
            "category":"Building & Trades",
            "subcategory":"Landscaping Services",
            "type":"Services"
        }
    ],
    "sg:phone":"+1 336 230 1674",
    "sg:postcode":"27406",
    "sg:province":"NC",
    "wof:name":"Precision Lawn Care",
    "wof:placetype":"venue"
},
  "geometry": {"coordinates":[-79.730126,36.048646],"type":"Point"}
}