{
  "type": "Feature",
  "properties": {
    "addr:full":"4913 Forbush Rd East Bend NC 27018",
    "addr:postcode":"4913;27018",
    "addr:street":"Forbush Rd",
    "iso:country":"US",
    "sg:address":"4913 Forbush Rd",
    "sg:city":"East Bend",
    "sg:classifiers":[
        {
            "category":"Organizations",
            "subcategory":"Religious Organization",
            "type":"Services"
        }
    ],
    "sg:phone":"+1   ",
    "sg:postcode":"27018",
    "sg:province":"NC",
    "wof:name":"Mount Sinai Pentecostal Holine",
    "wof:placetype":"venue"
},
  "geometry": {"coordinates":[-80.59115199999999,36.204249],"type":"Point"}
}