{
  "type": "Feature",
  "properties": {
    "iso:country":"US",
    "sg:address":"5820 E W T Harris Blvd",
    "sg:city":"Charlotte",
    "sg:classifiers":[
        {
            "category":"Professional",
            "subcategory":"Management & Consulting",
            "type":"Services"
        }
    ],
    "sg:phone":"+1 704 537 2884",
    "sg:postcode":"28215",
    "sg:province":"NC",
    "sg:tags":[
        "marketing",
        "program"
    ],
    "wof:name":"Queen City Marketing",
    "wof:placetype":"venue"
},
  "geometry": {"coordinates":[-80.735636,35.236502],"type":"Point"}
}