{
  "type": "Feature",
  "properties": {
    "addr:full":"12 National Ave Fletcher NC 28732",
    "addr:housenumber":"12",
    "addr:postcode":"28732",
    "addr:street":"National Ave",
    "iso:country":"US",
    "sg:address":"12 National Ave",
    "sg:city":"Fletcher",
    "sg:classifiers":[
        {
            "category":"Building & Trades",
            "subcategory":"Construction",
            "type":"Services"
        }
    ],
    "sg:phone":"+1 828 684 1562",
    "sg:postcode":"28732",
    "sg:province":"NC",
    "sg:tags":[
        "contractor"
    ],
    "wof:name":"General Building Systems",
    "wof:placetype":"venue"
},
  "geometry": {"coordinates":[-82.525567,35.445189],"type":"Point"}
}