{
  "type": "Feature",
  "properties": {
    "iso:country":"US",
    "sg:address":"1410 Buffalo Church Rd",
    "sg:city":"Shelby",
    "sg:classifiers":[
        {
            "category":"Organizations",
            "subcategory":"Religious Organization",
            "type":"Services"
        }
    ],
    "sg:phone":"+1   ",
    "sg:postcode":"28150",
    "sg:province":"NC",
    "wof:name":"Buffalo Baptist Church",
    "wof:placetype":"venue"
},
  "geometry": {"coordinates":[-81.47066700000001,35.326115],"type":"Point"}
}