{
  "type": "Feature",
  "properties": {
    "iso:country":"US",
    "sg:address":"627 1st St SW",
    "sg:city":"Hickory",
    "sg:classifiers":[
        {
            "category":"Social Services",
            "type":"Services"
        }
    ],
    "sg:phone":"+1 828 345 5031",
    "sg:postcode":"28602",
    "sg:province":"NC",
    "sg:tags":[
        "organization",
        "welfare"
    ],
    "wof:name":"Hickory Branch NAACP",
    "wof:placetype":"venue"
},
  "geometry": {"coordinates":[-81.33919899999999,35.72401],"type":"Point"}
}