{
  "type": "Feature",
  "properties": {
    "iso:country":"US",
    "sg:address":"308 Wilkesboro Ave",
    "sg:city":"North Wilkesboro",
    "sg:classifiers":[
        {
            "category":"Retail",
            "subcategory":"Portrait Studio",
            "type":"Services"
        }
    ],
    "sg:phone":"+1 336 838 3134",
    "sg:postcode":"28659",
    "sg:province":"NC",
    "sg:tags":[
        "photographer"
    ],
    "wof:name":"Osbornes' Photo & Frame",
    "wof:placetype":"venue"
},
  "geometry": {"coordinates":[-81.145216,36.155238],"type":"Point"}
}