{
  "type": "Feature",
  "properties": {
    "addr:full":"148 McCall Rd Ellerbe NC 28338",
    "addr:housenumber":"148",
    "addr:postcode":"28338",
    "addr:street":"Mccall Rd",
    "iso:country":"US",
    "sg:address":"148 McCall Rd",
    "sg:city":"Ellerbe",
    "sg:classifiers":[
        {
            "category":"Building & Trades",
            "subcategory":"Construction",
            "type":"Services"
        }
    ],
    "sg:phone":"+1 910 652 3768",
    "sg:postcode":"28338",
    "sg:province":"NC",
    "sg:tags":[
        "contractor"
    ],
    "wof:name":"Swn Contracting",
    "wof:placetype":"venue"
},
  "geometry": {"coordinates":[-79.654661,35.148698],"type":"Point"}
}