{
  "type": "Feature",
  "properties": {
    "addr:full":"110 Carver Dr Roxboro NC 27573",
    "addr:housenumber":"110",
    "addr:postcode":"27573",
    "addr:street":"Carver Dr",
    "iso:country":"US",
    "sg:address":"110 Carver Dr",
    "sg:city":"Roxboro",
    "sg:classifiers":[
        {
            "category":"Shopping",
            "subcategory":"Hobbies, Toys, & Games",
            "type":"Retail Goods"
        },
        {
            "category":"Shopping",
            "subcategory":"Bicycles & Sporting Goods",
            "type":"Retail Goods"
        },
        {
            "category":"Arena",
            "subcategory":"Stadium",
            "type":"Entertainment"
        }
    ],
    "sg:phone":"+1 336 599 9266",
    "sg:postcode":"27573",
    "sg:province":"NC",
    "sg:tags":[
        "stadiums",
        "field",
        "parachute",
        "athletic"
    ],
    "wof:name":"North American Aerodynamics, Inc.",
    "wof:placetype":"venue"
},
  "geometry": {"coordinates":[-78.974902,36.407897],"type":"Point"}
}