{
  "type": "Feature",
  "properties": {
    "addr:full":"1401 Elm St Sanford NC 27330",
    "addr:housenumber":"1401",
    "addr:postcode":"27330",
    "addr:street":"Elm St",
    "iso:country":"US",
    "sg:address":"1401 Elm St",
    "sg:city":"Sanford",
    "sg:classifiers":[
        {
            "category":"Government",
            "subcategory":"Police Station",
            "type":"Public Place"
        }
    ],
    "sg:phone":"+1 919 775 5531",
    "sg:postcode":"27330",
    "sg:province":"NC",
    "sg:tags":[
        "sheriff"
    ],
    "wof:name":"Lee County Sheriff's Office",
    "wof:placetype":"venue"
},
  "geometry": {"coordinates":[-79.164581,35.467451],"type":"Point"}
}