{
  "type": "Feature",
  "properties": {
    "addr:full":"3081 E Hitesburg Rd Virgilina NC 24598",
    "addr:housenumber":"3081",
    "addr:postcode":"24598",
    "addr:street":"E Hitesburg Rd",
    "iso:country":"US",
    "sg:address":"3081 E Hitesburg Rd",
    "sg:city":"Virgilina",
    "sg:phone":"+1 434 585 2859",
    "sg:postcode":"24598",
    "sg:province":"NC",
    "sg:tags":[
        "farm",
        "grain",
        "cash"
    ],
    "wof:name":"Bowen Peele",
    "wof:placetype":"venue"
},
  "geometry": {"coordinates":[-78.72802799999999,36.605807],"type":"Point"}
}