{
  "type": "Feature",
  "properties": {
    "addr:full":"1808 Arlington St Raleigh NC 27608",
    "addr:housenumber":"1808",
    "addr:postcode":"27608",
    "addr:street":"Arlington St",
    "iso:country":"US",
    "sg:address":"1808 Arlington St",
    "sg:city":"Raleigh",
    "sg:classifiers":[
        {
            "category":"Education",
            "subcategory":"Special Training",
            "type":"Public Place"
        }
    ],
    "sg:phone":"+1   ",
    "sg:postcode":"27608",
    "sg:province":"NC",
    "wof:name":"Connections NC Inc",
    "wof:placetype":"venue"
},
  "geometry": {"coordinates":[-78.65749599999999,35.801043],"type":"Point"}
}