{
  "type": "Feature",
  "properties": {
    "addr:full":"419 S College Rd Wilmington NC 28403",
    "addr:housenumber":"419",
    "addr:postcode":"28403",
    "addr:street":"S College Rd",
    "iso:country":"US",
    "sg:address":"419 S College Rd",
    "sg:city":"Wilmington",
    "sg:classifiers":[
        {
            "category":"Shopping",
            "subcategory":"Used Merchandise",
            "type":"Retail Goods"
        }
    ],
    "sg:phone":"+1 910 799 9552",
    "sg:postcode":"28403",
    "sg:province":"NC",
    "sg:tags":[
        "shop",
        "consignment"
    ],
    "wof:name":"Repeat Performance",
    "wof:placetype":"venue"
},
  "geometry": {"coordinates":[-77.874826,34.233449],"type":"Point"}
}