{
  "type": "Feature",
  "properties": {
    "iso:country":"US",
    "sg:address":"32081 State Hwy 27",
    "sg:city":"Albemarle",
    "sg:classifiers":[
        {
            "category":"Retail",
            "subcategory":"Auto Repair",
            "type":"Services"
        }
    ],
    "sg:phone":"+1   ",
    "sg:postcode":"28001",
    "sg:province":"NC",
    "sg:tags":[
        "body"
    ],
    "wof:name":"Crowells Upholstery",
    "wof:placetype":"venue"
},
  "geometry": {"coordinates":[-80.234646,35.332222],"type":"Point"}
}