{
  "type": "Feature",
  "properties": {
    "iso:country":"US",
    "sg:address":"9325 Poole Rd",
    "sg:city":"Knightdale",
    "sg:classifiers":[
        {
            "category":"Building & Trades",
            "subcategory":"Construction",
            "type":"Services"
        }
    ],
    "sg:phone":"+1 919 266 2082",
    "sg:postcode":"27545",
    "sg:province":"NC",
    "sg:tags":[
        "grading",
        "contractor"
    ],
    "wof:name":"G B Hopkins Grading Inc",
    "wof:placetype":"venue"
},
  "geometry": {"coordinates":[-78.45525000000001,35.747645],"type":"Point"}
}