{
  "type": "Feature",
  "properties": {
    "iso:country":"US",
    "sg:address":"501 Bridleridge Dr",
    "sg:city":"Raleigh",
    "sg:classifiers":[
        {
            "category":"Professional",
            "subcategory":"Computer Services",
            "type":"Services"
        }
    ],
    "sg:phone":"+1   ",
    "sg:postcode":"27609",
    "sg:province":"NC",
    "sg:tags":[
        "related"
    ],
    "wof:name":"Nashnet",
    "wof:placetype":"venue"
},
  "geometry": {"coordinates":[-78.646241,35.869267],"type":"Point"}
}