{
  "type": "Feature",
  "properties": {
    "addr:full":"2720 Sapling Cir Wilmington NC 28411",
    "addr:housenumber":"2720",
    "addr:postcode":"28411",
    "addr:street":"Sapling Cir",
    "iso:country":"US",
    "sg:address":"2720 Sapling Cir",
    "sg:city":"Wilmington",
    "sg:classifiers":[
        {
            "category":"Social Services",
            "subcategory":"Child Care",
            "type":"Services"
        }
    ],
    "sg:phone":"+1   ",
    "sg:postcode":"28411",
    "sg:province":"NC",
    "sg:tags":[
        "day"
    ],
    "wof:name":"Ms Sandras Day Care",
    "wof:placetype":"venue"
},
  "geometry": {"coordinates":[-77.83820299999999,34.278254],"type":"Point"}
}