{
  "type": "Feature",
  "properties": {
    "addr:full":"5699 Chancellorsville Dr NW Winston Salem NC 27106",
    "addr:housenumber":"5699",
    "addr:postcode":"27106",
    "addr:street":"Chancellorsville Dr Nw",
    "iso:country":"US",
    "sg:address":"5699 Chancellorsville Dr NW",
    "sg:city":"Winston Salem",
    "sg:classifiers":[
        {
            "category":"Social Services",
            "subcategory":"Child Care",
            "type":"Services"
        }
    ],
    "sg:phone":"+1   ",
    "sg:postcode":"27106",
    "sg:province":"NC",
    "sg:tags":[
        "home",
        "family"
    ],
    "wof:name":"Happy Faces Childcare",
    "wof:placetype":"venue"
},
  "geometry": {"coordinates":[-80.28902600000001,36.157257],"type":"Point"}
}