{
  "type": "Feature",
  "properties": {
    "addr:full":"2032 Bethlehem Rd Kings Mountain NC 28086",
    "addr:housenumber":"2032",
    "addr:postcode":"28086",
    "addr:street":"Bethlehem Rd",
    "iso:country":"US",
    "sg:address":"2032 Bethlehem Rd",
    "sg:city":"Kings Mountain",
    "sg:classifiers":[
        {
            "category":"Organizations",
            "subcategory":"Religious Organization",
            "type":"Services"
        }
    ],
    "sg:phone":"+1 704 730 0075",
    "sg:postcode":"28086",
    "sg:province":"NC",
    "wof:name":"Love Valley Baptist Church",
    "wof:placetype":"venue"
},
  "geometry": {"coordinates":[-81.35788100000001,35.170372],"type":"Point"}
}