{
  "type": "Feature",
  "properties": {
    "iso:country":"US",
    "sg:address":"2032 Scott Ave",
    "sg:city":"Charlotte",
    "sg:phone":"+1 704 333 7330",
    "sg:postcode":"28203",
    "sg:province":"NC",
    "wof:name":"Steve Ascher Rl Est Appraisal",
    "wof:placetype":"venue"
},
  "geometry": {"coordinates":[-80.84527,35.200044],"type":"Point"}
}