{
  "type": "Feature",
  "properties": {
    "addr:full":"6853C Fairview Rd Charlotte NC 28210",
    "addr:housenumber":"6853c",
    "addr:postcode":"28210",
    "addr:street":"Fairview Rd",
    "iso:country":"US",
    "sg:address":"6853C Fairview Rd",
    "sg:city":"Charlotte",
    "sg:classifiers":[
        {
            "category":"Insurance",
            "subcategory":"Insurance Agent",
            "type":"Services"
        },
        {
            "category":"Insurance",
            "subcategory":"Hazard Insurance",
            "type":"Services"
        },
        {
            "category":"Insurance",
            "subcategory":"Title Insurance",
            "type":"Services"
        },
        {
            "category":"Insurance",
            "subcategory":"Life Insurance",
            "type":"Services"
        }
    ],
    "sg:phone":"+1 704 366 7779",
    "sg:postcode":"28210",
    "sg:province":"NC",
    "sg:tags":[
        "business",
        "auto",
        "commercial",
        "homeowner",
        "motorcycle",
        "renter"
    ],
    "wof:name":"Allstate Insurance Company - John Rose",
    "wof:placetype":"venue"
},
  "geometry": {"coordinates":[-80.826286,35.147139],"type":"Point"}
}