{
  "type": "Feature",
  "properties": {
    "iso:country":"US",
    "sg:address":"4403 Shoal Creek Dr",
    "sg:city":"Greensboro",
    "sg:classifiers":[
        {
            "category":"Professional",
            "subcategory":"Computer Services",
            "type":"Services"
        }
    ],
    "sg:phone":"+1   ",
    "sg:postcode":"27410",
    "sg:province":"NC",
    "sg:tags":[
        "development",
        "marketing",
        "cd",
        "direct",
        "rom"
    ],
    "wof:name":"I Connectv com",
    "wof:placetype":"venue"
},
  "geometry": {"coordinates":[-79.92434299999999,36.135653],"type":"Point"}
}