{
  "type": "Feature",
  "properties": {
    "addr:full":"1509 Buckhorn Rd Sanford NC 27330",
    "addr:housenumber":"1509",
    "addr:postcode":"27330",
    "addr:street":"Buckhorn Rd",
    "iso:country":"US",
    "sg:address":"1509 Buckhorn Rd",
    "sg:city":"Sanford",
    "sg:classifiers":[
        {
            "category":"Building & Trades",
            "subcategory":"Construction",
            "type":"Services"
        }
    ],
    "sg:phone":"+1 919 258 9249",
    "sg:postcode":"27330",
    "sg:province":"NC",
    "sg:tags":[
        "contractor"
    ],
    "wof:name":"Mark Durham Drywall",
    "wof:placetype":"venue"
},
  "geometry": {"coordinates":[-79.031414,35.487397],"type":"Point"}
}