{
  "type": "Feature",
  "properties": {
    "addr:full":"246 Georgetown Rd Jacksonville NC 28540",
    "addr:housenumber":"246",
    "addr:postcode":"28540",
    "addr:street":"Georgetown Rd",
    "iso:country":"US",
    "sg:address":"246 Georgetown Rd",
    "sg:city":"Jacksonville",
    "sg:classifiers":[
        {
            "category":"Social Services",
            "subcategory":"Child Care",
            "type":"Services"
        }
    ],
    "sg:phone":"+1   ",
    "sg:postcode":"28540",
    "sg:province":"NC",
    "sg:tags":[
        "day"
    ],
    "wof:name":"Echsa Day Care",
    "wof:placetype":"venue"
},
  "geometry": {"coordinates":[-77.44832700000001,34.747385],"type":"Point"}
}