{
  "type": "Feature",
  "properties": {
    "addr:full":"110 Carolyn Dr Garner NC 27504",
    "addr:housenumber":"110",
    "addr:postcode":"27504",
    "addr:street":"Carolyn Dr",
    "iso:country":"US",
    "sg:address":"110 Carolyn Dr",
    "sg:city":"Garner",
    "sg:classifiers":[
        {
            "category":"Restaurant",
            "type":"Food & Drink"
        }
    ],
    "sg:phone":"+1 919 771 2441",
    "sg:postcode":"27504",
    "sg:province":"NC",
    "wof:name":"Mc Donald's",
    "wof:placetype":"venue"
},
  "geometry": {"coordinates":[-78.536101,35.391311],"type":"Point"}
}