{
  "type": "Feature",
  "properties": {
    "iso:country":"US",
    "sg:address":"1321 Bobbitt Dr",
    "sg:city":"Garner",
    "sg:classifiers":[
        {
            "category":"Wholesale",
            "subcategory":"Construction Materials",
            "type":"Manufacturing & Wholesale Goods"
        }
    ],
    "sg:phone":"+1 919 772 4800",
    "sg:postcode":"27529",
    "sg:province":"NC",
    "sg:tags":[
        "building"
    ],
    "wof:name":"Lyf-Tym Products-Raleigh Inc",
    "wof:placetype":"venue"
},
  "geometry": {"coordinates":[-78.62300500000001,35.713516],"type":"Point"}
}