{
  "type": "Feature",
  "properties": {
    "addr:full":"233 Shoreline Dr New Bern NC 28562",
    "addr:housenumber":"233",
    "addr:postcode":"28562",
    "addr:street":"Shoreline Dr",
    "iso:country":"US",
    "sg:address":"233 Shoreline Dr",
    "sg:city":"New Bern",
    "sg:classifiers":[
        {
            "category":"Shopping",
            "subcategory":"Clothing, Apparel, & Fashions",
            "type":"Retail Goods"
        }
    ],
    "sg:phone":"+1 252 637 1789",
    "sg:postcode":"28562",
    "sg:province":"NC",
    "wof:name":"Uniform Computer Rel",
    "wof:placetype":"venue"
},
  "geometry": {"coordinates":[-77.152548,35.062999],"type":"Point"}
}