{
  "type": "Feature",
  "properties": {
    "addr:full":"1326 Robeson St Fayetteville NC 28305",
    "addr:housenumber":"1326",
    "addr:postcode":"28305",
    "addr:street":"Robeson St",
    "iso:country":"US",
    "sg:address":"1326 Robeson St",
    "sg:city":"Fayetteville",
    "sg:classifiers":[
        {
            "category":"Autos & Motor Vehicles",
            "subcategory":"Fuel & Gas Station",
            "type":"Retail Goods"
        }
    ],
    "sg:phone":"+1 910 484 8601",
    "sg:postcode":"28305",
    "sg:province":"NC",
    "sg:tags":[
        "station",
        "gasoline"
    ],
    "wof:name":"Etna",
    "wof:placetype":"venue"
},
  "geometry": {"coordinates":[-78.909834,35.040748],"type":"Point"}
}