{
  "type": "Feature",
  "properties": {
    "addr:full":"305 Talton St Mount Olive NC 28365",
    "addr:housenumber":"305",
    "addr:postcode":"28365",
    "addr:street":"Talton St",
    "iso:country":"US",
    "sg:address":"305 Talton St",
    "sg:city":"Mount Olive",
    "sg:classifiers":[
        {
            "category":"Shopping",
            "subcategory":"Hobbies, Toys, & Games",
            "type":"Retail Goods"
        }
    ],
    "sg:phone":"+1 919 635 0220",
    "sg:postcode":"28365",
    "sg:province":"NC",
    "wof:name":"Olde House Baskets Gifts",
    "wof:placetype":"venue"
},
  "geometry": {"coordinates":[-78.06314500000001,35.209753],"type":"Point"}
}