{
  "type": "Feature",
  "properties": {
    "addr:full":"6441 Holder Rd Clemmons NC 27012",
    "addr:housenumber":"6441",
    "addr:postcode":"27012",
    "addr:street":"Holder Rd",
    "iso:country":"US",
    "sg:address":"6441 Holder Rd",
    "sg:city":"Clemmons",
    "sg:classifiers":[
        {
            "category":"Social Services",
            "subcategory":"Adult Care",
            "type":"Services"
        },
        {
            "category":"Health Services",
            "subcategory":"Clinic",
            "type":"Services"
        }
    ],
    "sg:phone":"+1 336 778 8548",
    "sg:postcode":"27012",
    "sg:province":"NC",
    "sg:tags":[
        "home",
        "residential"
    ],
    "wof:name":"Clemmons Village II",
    "wof:placetype":"venue"
},
  "geometry": {"coordinates":[-80.381793,36.069594],"type":"Point"}
}