{
  "type": "Feature",
  "properties": {
    "addr:full":"7909 Falls of Neuse Rd Raleigh NC 27615",
    "addr:housenumber":"7909",
    "addr:postcode":"27615",
    "addr:street":"Falls Of Neuse Rd",
    "iso:country":"US",
    "sg:address":"7909 Falls of Neuse Rd",
    "sg:city":"Raleigh",
    "sg:classifiers":[
        {
            "category":"Food & Beverages",
            "subcategory":"Bakery",
            "type":"Retail Goods"
        }
    ],
    "sg:phone":"+1 919 848 1310",
    "sg:postcode":"27615",
    "sg:province":"NC",
    "sg:tags":[
        "bagel"
    ],
    "wof:name":"Manhattan Bagel",
    "wof:placetype":"venue"
},
  "geometry": {"coordinates":[-78.625516,35.893211],"type":"Point"}
}