{
  "type": "Feature",
  "properties": {
    "iso:country":"US",
    "sg:address":"3687 Sweeten Creek Rd",
    "sg:city":"Arden",
    "sg:classifiers":[
        {
            "category":"Real Estate",
            "subcategory":"Real Estate Agent",
            "type":"Services"
        }
    ],
    "sg:phone":"+1 828 684 8706",
    "sg:postcode":"28704",
    "sg:province":"NC",
    "wof:name":"Ammons Agency Real Estate",
    "wof:placetype":"venue"
},
  "geometry": {"coordinates":[-82.516505,35.475956],"type":"Point"}
}