{
  "type": "Feature",
  "properties": {
    "iso:country":"US",
    "sg:address":"9 Hollycrest Ct",
    "sg:city":"Greensboro",
    "sg:classifiers":[
        {
            "category":"Real Estate",
            "subcategory":"Real Estate Agent",
            "type":"Services"
        }
    ],
    "sg:phone":"+1 336 292 6585",
    "sg:postcode":"27410",
    "sg:province":"NC",
    "wof:name":"L G C Properties Inc",
    "wof:placetype":"venue"
},
  "geometry": {"coordinates":[-79.915492,36.093502],"type":"Point"}
}