{
  "type": "Feature",
  "properties": {
    "iso:country":"US",
    "sg:address":"376 Old Schoolhouse Rd",
    "sg:city":"Taylorsville",
    "sg:classifiers":[
        {
            "category":"Building & Trades",
            "subcategory":"Cleaning & Sanitation",
            "type":"Services"
        }
    ],
    "sg:phone":"+1   ",
    "sg:postcode":"28681",
    "sg:province":"NC",
    "sg:tags":[
        "maintenance"
    ],
    "wof:name":"Thackersons",
    "wof:placetype":"venue"
},
  "geometry": {"coordinates":[-81.32944000000001,35.850956],"type":"Point"}
}