{
  "type": "Feature",
  "properties": {
    "iso:country":"US",
    "sg:address":"11901 Eastfield Rd",
    "sg:city":"Huntersville",
    "sg:classifiers":[
        {
            "category":"Organizations",
            "subcategory":"Religious Organization",
            "type":"Services"
        }
    ],
    "sg:phone":"+1 704 947 8222",
    "sg:postcode":"28078",
    "sg:province":"NC",
    "sg:tags":[
        "church"
    ],
    "sg:website":"www.eastfieldchristian.org",
    "wof:name":"Eastfield Christian Church",
    "wof:placetype":"venue"
},
  "geometry": {"coordinates":[-80.800875,35.375565],"type":"Point"}
}