{
  "type": "Feature",
  "properties": {
    "iso:country":"US",
    "sg:address":"2009 Hunterwoods Dr",
    "sg:city":"High Point",
    "sg:classifiers":[
        {
            "category":"Building & Trades",
            "subcategory":"Construction",
            "type":"Services"
        }
    ],
    "sg:phone":"+1 336 869 6282",
    "sg:postcode":"27265",
    "sg:province":"NC",
    "sg:tags":[
        "floor",
        "laying",
        "contractor"
    ],
    "wof:name":"Jr & Associates New Hanover",
    "wof:placetype":"venue"
},
  "geometry": {"coordinates":[-80.00257999999999,36.035992],"type":"Point"}
}