{
  "type": "Feature",
  "properties": {
    "iso:country":"US",
    "sg:address":"714 E Atkins St",
    "sg:city":"Dobson",
    "sg:classifiers":[
        {
            "category":"Food & Beverages",
            "subcategory":"Groceries & Convenience Stores",
            "type":"Retail Goods"
        }
    ],
    "sg:phone":"+1 336 386 4006",
    "sg:postcode":"27017",
    "sg:province":"NC",
    "wof:name":"LA Esmeralda 3",
    "wof:placetype":"venue"
},
  "geometry": {"coordinates":[-80.712266,36.392948],"type":"Point"}
}