{
  "type": "Feature",
  "properties": {
    "addr:full":"1183 Central Dr NW Concord NC 28027",
    "addr:housenumber":"1183",
    "addr:postcode":"28027",
    "addr:street":"Central Dr Nw",
    "iso:country":"US",
    "sg:address":"1183 Central Dr NW",
    "sg:city":"Concord",
    "sg:classifiers":[
        {
            "category":"Shopping",
            "subcategory":"Catalog Store",
            "type":"Retail Goods"
        }
    ],
    "sg:phone":"+1 704 788 9088",
    "sg:postcode":"28027",
    "sg:province":"NC",
    "sg:tags":[
        "mail",
        "house"
    ],
    "wof:name":"Lm International",
    "wof:placetype":"venue"
},
  "geometry": {"coordinates":[-80.61438,35.438023],"type":"Point"}
}