{
  "type": "Feature",
  "properties": {
    "addr:full":"79 Rink Dam Rd Hickory NC 28601",
    "addr:housenumber":"79",
    "addr:postcode":"28601",
    "addr:street":"Rink Dam Rd",
    "iso:country":"US",
    "sg:address":"79 Rink Dam Rd",
    "sg:city":"Hickory",
    "sg:classifiers":[
        {
            "category":"Real Estate",
            "subcategory":"Surveying",
            "type":"Services"
        }
    ],
    "sg:phone":"+1 828 495 7377",
    "sg:postcode":"28601",
    "sg:province":"NC",
    "sg:tags":[
        "surveyor"
    ],
    "wof:name":"Kevin Hefner & Assoc",
    "wof:placetype":"venue"
},
  "geometry": {"coordinates":[-81.307428,35.815575],"type":"Point"}
}