{
  "type": "Feature",
  "properties": {
    "addr:full":"1465 Sand Hill Rd Ste 1017 Asheville NC 28715",
    "addr:housenumber":"1465",
    "addr:postcode":"28715",
    "addr:street":"Sand Hill Rd Ste 1017",
    "iso:country":"US",
    "sg:address":"1465 Sand Hill Rd Ste 1017",
    "sg:city":"Asheville",
    "sg:classifiers":[
        {
            "category":"Communications",
            "subcategory":"Newspaper",
            "type":"Services"
        }
    ],
    "sg:phone":"+1 828 687 1893",
    "sg:postcode":"28715",
    "sg:province":"NC",
    "sg:tags":[
        "print",
        "medium"
    ],
    "sg:website":"www.dynamicimage.biz",
    "wof:name":"Dynamic Image Marketing Systems, Inc.",
    "wof:placetype":"venue"
},
  "geometry": {"coordinates":[-82.656718,35.54186],"type":"Point"}
}