{
  "type": "Feature",
  "properties": {
    "iso:country":"US",
    "sg:address":"123 Johnson Hill Dr",
    "sg:city":"Waynesville",
    "sg:classifiers":[
        {
            "category":"Retail",
            "subcategory":"Repair Shop",
            "type":"Services"
        }
    ],
    "sg:phone":"+1   ",
    "sg:postcode":"28786",
    "sg:province":"NC",
    "wof:name":"Maxwell Sound Labs",
    "wof:placetype":"venue"
},
  "geometry": {"coordinates":[-82.98283000000001,35.489573],"type":"Point"}
}