{
  "type": "Feature",
  "properties": {
    "addr:full":"219 S Cool Spring St Fayetteville NC 28301",
    "addr:housenumber":"219",
    "addr:postcode":"28301",
    "addr:street":"S Cool Spring St",
    "iso:country":"US",
    "sg:address":"219 S Cool Spring St",
    "sg:city":"Fayetteville",
    "sg:classifiers":[
        {
            "category":"Retail",
            "subcategory":"Auto Repair",
            "type":"Services"
        }
    ],
    "sg:phone":"+1   ",
    "sg:postcode":"28301",
    "sg:province":"NC",
    "sg:tags":[
        "general"
    ],
    "wof:name":"USA Machine Shop",
    "wof:placetype":"venue"
},
  "geometry": {"coordinates":[-78.875522,35.048952],"type":"Point"}
}