{
  "type": "Feature",
  "properties": {
    "addr:full":"1830 Statesville Ave Charlotte NC 28206",
    "addr:housenumber":"1830",
    "addr:postcode":"28206",
    "addr:street":"Statesville Ave",
    "iso:country":"US",
    "sg:address":"1830 Statesville Ave",
    "sg:city":"Charlotte",
    "sg:classifiers":[
        {
            "category":"Freight",
            "type":"Transportation"
        }
    ],
    "sg:phone":"+1 704 792 4272",
    "sg:postcode":"28206",
    "sg:province":"NC",
    "sg:tags":[
        "warehouse"
    ],
    "wof:name":"Collett & Assoc Agent",
    "wof:placetype":"venue"
},
  "geometry": {"coordinates":[-80.836101,35.246235],"type":"Point"}
}