{
  "type": "Feature",
  "properties": {
    "iso:country":"US",
    "sg:address":"1801 E 5th St",
    "sg:city":"Charlotte",
    "sg:classifiers":[
        {
            "category":"Social Services",
            "type":"Services"
        },
        {
            "category":"Personal",
            "type":"Services"
        },
        {
            "category":"Organizations",
            "subcategory":"Religious Organization",
            "type":"Services"
        }
    ],
    "sg:phone":"+1 704 375 5354",
    "sg:postcode":"28204",
    "sg:province":"NC",
    "sg:tags":[
        "family",
        "professional",
        "counselors-licensed",
        "individual",
        "marriage",
        "child",
        "counseling",
        "counselor"
    ],
    "sg:website":"http://www.mccsvs.org",
    "wof:name":"Methodist Counseling & Consultation Services",
    "wof:placetype":"venue"
},
  "geometry": {"coordinates":[-80.82318100000001,35.213081],"type":"Point"}
}