{
  "type": "Feature",
  "properties": {
    "addr:full":"518 Lyttleton Dr Charlotte NC 28211",
    "addr:housenumber":"518",
    "addr:postcode":"28211",
    "addr:street":"Lyttleton Dr",
    "iso:country":"US",
    "sg:address":"518 Lyttleton Dr",
    "sg:city":"Charlotte",
    "sg:classifiers":[
        {
            "category":"Professional",
            "subcategory":"Employment Agencies",
            "type":"Services"
        }
    ],
    "sg:phone":"+1   ",
    "sg:postcode":"28211",
    "sg:province":"NC",
    "sg:tags":[
        "help",
        "supply"
    ],
    "wof:name":"Lifescan Inc",
    "wof:placetype":"venue"
},
  "geometry": {"coordinates":[-80.783804,35.176936],"type":"Point"}
}