{
  "type": "Feature",
  "properties": {
    "addr:full":"2543 Ravenhill Dr Fayetteville NC 28303",
    "addr:housenumber":"2543",
    "addr:postcode":"28303",
    "addr:street":"Ravenhill Dr",
    "iso:country":"US",
    "sg:address":"2543 Ravenhill Dr",
    "sg:city":"Fayetteville",
    "sg:classifiers":[
        {
            "category":"Professional",
            "subcategory":"Lawyer & Legal Services",
            "type":"Services"
        }
    ],
    "sg:phone":"+1 910 764 9200",
    "sg:postcode":"28303",
    "sg:province":"NC",
    "sg:tags":[
        "attorney"
    ],
    "wof:name":"Raper Law Firm PLLC",
    "wof:placetype":"venue"
},
  "geometry": {"coordinates":[-78.92593599999999,35.047149],"type":"Point"}
}