{
  "type": "Feature",
  "properties": {
    "iso:country":"US",
    "sg:address":"831 Glen Echo Trl",
    "sg:city":"Winston Salem",
    "sg:classifiers":[
        {
            "category":"Professional",
            "subcategory":"Business Services",
            "type":"Services"
        }
    ],
    "sg:phone":"+1   ",
    "sg:postcode":"27106",
    "sg:province":"NC",
    "wof:name":"Pat Avram Interiors Inc",
    "wof:placetype":"venue"
},
  "geometry": {"coordinates":[-80.29639899999999,36.109256],"type":"Point"}
}