{
  "type": "Feature",
  "properties": {
    "iso:country":"US",
    "sg:address":"7160 Franklin Rd",
    "sg:city":"Lewisville",
    "sg:classifiers":[
        {
            "category":"Animal Shelter",
            "type":"Public Place"
        }
    ],
    "sg:phone":"+1 336 993 1234",
    "sg:postcode":"27023",
    "sg:province":"NC",
    "sg:tags":[
        "kennel"
    ],
    "wof:name":"Willow Run Kennel",
    "wof:placetype":"venue"
},
  "geometry": {"coordinates":[-80.407872,36.113414],"type":"Point"}
}