{
  "type": "Feature",
  "properties": {
    "addr:full":"203 Barnes Ct Nashville NC 27856",
    "addr:housenumber":"203",
    "addr:postcode":"27856",
    "addr:street":"Barnes Ct",
    "iso:country":"US",
    "sg:address":"203 Barnes Ct",
    "sg:city":"Nashville",
    "sg:classifiers":[
        {
            "category":"Professional",
            "subcategory":"Lawyer & Legal Services",
            "type":"Services"
        }
    ],
    "sg:phone":"+1 252 459 1111",
    "sg:postcode":"27856",
    "sg:province":"NC",
    "sg:tags":[
        "attorney"
    ],
    "wof:name":"Valentine Adams & Lamar",
    "wof:placetype":"venue"
},
  "geometry": {"coordinates":[-77.931926,35.957155],"type":"Point"}
}