{
  "type": "Feature",
  "properties": {
    "iso:country":"US",
    "sg:address":"6501 Folger Dr",
    "sg:city":"Charlotte",
    "sg:classifiers":[
        {
            "category":"Manufacturing",
            "subcategory":"Printing",
            "type":"Manufacturing & Wholesale Goods"
        }
    ],
    "sg:phone":"+1 704 366 0301",
    "sg:postcode":"28270",
    "sg:province":"NC",
    "sg:tags":[
        "publishing"
    ],
    "wof:name":"Forebears Press",
    "wof:placetype":"venue"
},
  "geometry": {"coordinates":[-80.777647,35.150576],"type":"Point"}
}