{
  "type": "Feature",
  "properties": {
    "iso:country":"US",
    "sg:address":"4715 Central Ave",
    "sg:city":"Charlotte",
    "sg:classifiers":[
        {
            "category":"Food & Beverages",
            "subcategory":"Bakery",
            "type":"Retail Goods"
        }
    ],
    "sg:phone":"+1 704 568 9161",
    "sg:postcode":"28205",
    "sg:province":"NC",
    "wof:name":"Panaderia Salvadorena",
    "wof:placetype":"venue"
},
  "geometry": {"coordinates":[-80.763431,35.212416],"type":"Point"}
}