{
  "type": "Feature",
  "properties": {
    "addr:full":"230 Odum Rd Lumberton NC 28360",
    "addr:housenumber":"230",
    "addr:postcode":"28360",
    "addr:street":"Odum Rd",
    "iso:country":"US",
    "sg:address":"230 Odum Rd",
    "sg:city":"Lumberton",
    "sg:classifiers":[
        {
            "category":"Building & Trades",
            "subcategory":"Construction",
            "type":"Services"
        }
    ],
    "sg:phone":"+1 910 739 9630",
    "sg:postcode":"28360",
    "sg:province":"NC",
    "sg:tags":[
        "roofing",
        "contractor"
    ],
    "wof:name":"Blackburn Roofing Co",
    "wof:placetype":"venue"
},
  "geometry": {"coordinates":[-79.08024899999999,34.660054],"type":"Point"}
}