{
  "type": "Feature",
  "properties": {
    "iso:country":"US",
    "sg:address":"527 Kilgore Rd",
    "sg:city":"Kings Mountain",
    "sg:classifiers":[
        {
            "category":"Personal",
            "subcategory":"Beauty Salon",
            "type":"Services"
        }
    ],
    "sg:phone":"+1 704 937 9650",
    "sg:postcode":"28086",
    "sg:province":"NC",
    "wof:name":"Teresa's Beauty Salon",
    "wof:placetype":"venue"
},
  "geometry": {"coordinates":[-81.41919900000001,35.190735],"type":"Point"}
}