{
  "type": "Feature",
  "properties": {
    "addr:full":"1030 Rogers Ln Raleigh NC 27610",
    "addr:housenumber":"1030",
    "addr:postcode":"27610",
    "addr:street":"Rogers Ln",
    "iso:country":"US",
    "sg:address":"1030 Rogers Ln",
    "sg:city":"Raleigh",
    "sg:classifiers":[
        {
            "category":"Sports & Exercise",
            "subcategory":"Gym",
            "type":"Entertainment"
        }
    ],
    "sg:phone":"+1 919 449 0899",
    "sg:postcode":"27610",
    "sg:province":"NC",
    "sg:tags":[
        "club",
        "health",
        "studio",
        "gymnasium"
    ],
    "wof:name":"Shape Up Express-Raleigh",
    "wof:placetype":"venue"
},
  "geometry": {"coordinates":[-78.548812,35.790638],"type":"Point"}
}