{
  "type": "Feature",
  "properties": {
    "iso:country":"US",
    "sg:address":"5421 Wrightsville Ave",
    "sg:city":"Wilmington",
    "sg:classifiers":[
        {
            "category":"Retail",
            "subcategory":"Repair Shop",
            "type":"Services"
        }
    ],
    "sg:phone":"+1 910 392 2650",
    "sg:postcode":"28403",
    "sg:province":"NC",
    "sg:tags":[
        "television",
        "radio"
    ],
    "wof:name":"E-Tech Electronics",
    "wof:placetype":"venue"
},
  "geometry": {"coordinates":[-77.85130599999999,34.215403],"type":"Point"}
}