{
  "type": "Feature",
  "properties": {
    "addr:full":"312 Tar Heel Dr Greenville NC 27834",
    "addr:housenumber":"312",
    "addr:postcode":"27834",
    "addr:street":"Tar Heel Dr",
    "iso:country":"US",
    "sg:address":"312 Tar Heel Dr",
    "sg:city":"Greenville",
    "sg:classifiers":[
        {
            "category":"Shopping",
            "subcategory":"Pharmacy",
            "type":"Retail Goods"
        }
    ],
    "sg:phone":"+1 252 321 0649",
    "sg:postcode":"27834",
    "sg:province":"NC",
    "sg:tags":[
        "drug",
        "store"
    ],
    "wof:name":"Eckerd",
    "wof:placetype":"venue"
},
  "geometry": {"coordinates":[-77.433429,35.661599],"type":"Point"}
}