{
  "type": "Feature",
  "properties": {
    "iso:country":"US",
    "sg:address":"385 Ja-Max Dr",
    "sg:city":"Hillsborough",
    "sg:classifiers":[
        {
            "category":"Professional",
            "subcategory":"Accounting & Tax Preparation",
            "type":"Services"
        }
    ],
    "sg:phone":"+1   ",
    "sg:postcode":"27278",
    "sg:province":"NC",
    "sg:tags":[
        "return"
    ],
    "wof:name":"Almost Perfect Inc",
    "wof:placetype":"venue"
},
  "geometry": {"coordinates":[-79.101669,36.062535],"type":"Point"}
}