{
  "type": "Feature",
  "properties": {
    "addr:full":"7912 Reeps Grove Church Rd Vale NC 28168",
    "addr:housenumber":"7912",
    "addr:postcode":"28168",
    "addr:street":"Reeps Grove Church Rd",
    "iso:country":"US",
    "sg:address":"7912 Reeps Grove Church Rd",
    "sg:city":"Vale",
    "sg:classifiers":[
        {
            "category":"Freight",
            "type":"Transportation"
        }
    ],
    "sg:phone":"+1 704 276 2085",
    "sg:postcode":"28168",
    "sg:province":"NC",
    "sg:tags":[
        "operator",
        "local",
        "trucking"
    ],
    "wof:name":"Dedmon Grading Trucking",
    "wof:placetype":"venue"
},
  "geometry": {"coordinates":[-81.444946,35.540305],"type":"Point"}
}