{
  "type": "Feature",
  "properties": {
    "addr:full":"4000 Stuart Andrew Blvd Charlotte NC 28217",
    "addr:housenumber":"4000",
    "addr:postcode":"28217",
    "addr:street":"Stuart Andrew Blvd",
    "iso:country":"US",
    "sg:address":"4000 Stuart Andrew Blvd",
    "sg:city":"Charlotte",
    "sg:classifiers":[
        {
            "category":"Real Estate",
            "subcategory":"Surveying",
            "type":"Services"
        }
    ],
    "sg:phone":"+1 704 527 6626",
    "sg:postcode":"28217",
    "sg:province":"NC",
    "sg:tags":[
        "surveyor"
    ],
    "wof:name":"Lucas-Forman Inc",
    "wof:placetype":"venue"
},
  "geometry": {"coordinates":[-80.88729499999999,35.192922],"type":"Point"}
}