{
  "type": "Feature",
  "properties": {
    "iso:country":"US",
    "sg:address":"3546 Wade Ave",
    "sg:city":"Raleigh",
    "sg:classifiers":[
        {
            "category":"Shopping",
            "subcategory":"Bicycles & Sporting Goods",
            "type":"Retail Goods"
        },
        {
            "category":"Sports & Exercise",
            "subcategory":"Playing Field",
            "type":"Entertainment"
        },
        {
            "category":"Shopping",
            "subcategory":"Shoes",
            "type":"Retail Goods"
        }
    ],
    "sg:phone":"+1 919 832 8275",
    "sg:postcode":"27607",
    "sg:province":"NC",
    "sg:tags":[
        "instruction",
        "store",
        "fitness"
    ],
    "sg:website":"www.fleetfeetraleigh.com",
    "wof:name":"Fleet Feet Sports",
    "wof:placetype":"venue"
},
  "geometry": {"coordinates":[-78.685496,35.801293],"type":"Point"}
}