{
  "type": "Feature",
  "properties": {
    "addr:full":"2611 Whitney Hill Rd Charlotte NC 28226",
    "addr:housenumber":"2611",
    "addr:postcode":"28226",
    "addr:street":"Whitney Hill Rd",
    "iso:country":"US",
    "sg:address":"2611 Whitney Hill Rd",
    "sg:city":"Charlotte",
    "sg:classifiers":[
        {
            "category":"Professional",
            "subcategory":"Management & Consulting",
            "type":"Services"
        }
    ],
    "sg:phone":"+1   ",
    "sg:postcode":"28226",
    "sg:province":"NC",
    "wof:name":"Jambrose Marketing LLC",
    "wof:placetype":"venue"
},
  "geometry": {"coordinates":[-80.80098599999999,35.123562],"type":"Point"}
}