{
  "type": "Feature",
  "properties": {
    "addr:full":"12038 Serenade Ct Charlotte NC 28215",
    "addr:housenumber":"12038",
    "addr:postcode":"28215",
    "addr:street":"Serenade Ct",
    "iso:country":"US",
    "sg:address":"12038 Serenade Ct",
    "sg:city":"Charlotte",
    "sg:classifiers":[
        {
            "category":"Wholesale",
            "subcategory":"Computers",
            "type":"Manufacturing & Wholesale Goods"
        }
    ],
    "sg:phone":"+1 704 567 9858",
    "sg:postcode":"28215",
    "sg:province":"NC",
    "wof:name":"Becky Caza",
    "wof:placetype":"venue"
},
  "geometry": {"coordinates":[-80.656177,35.235609],"type":"Point"}
}