{
  "type": "Feature",
  "properties": {
    "iso:country":"US",
    "sg:address":"1527 Coltrane Mill Rd",
    "sg:city":"Randleman",
    "sg:classifiers":[
        {
            "category":"Real Estate",
            "subcategory":"Real Estate Operator",
            "type":"Services"
        }
    ],
    "sg:phone":"+1 336 674 3472",
    "sg:postcode":"27317",
    "sg:province":"NC",
    "sg:tags":[
        "building",
        "apartment"
    ],
    "wof:name":"Sea View Apts Inc",
    "wof:placetype":"venue"
},
  "geometry": {"coordinates":[-79.851078,35.910474],"type":"Point"}
}