{
  "type": "Feature",
  "properties": {
    "iso:country":"US",
    "sg:address":"3846 Young Rd",
    "sg:city":"Asheboro",
    "sg:classifiers":[
        {
            "category":"Retail",
            "subcategory":"Portrait Studio",
            "type":"Services"
        }
    ],
    "sg:phone":"+1   ",
    "sg:postcode":"27205",
    "sg:province":"NC",
    "sg:tags":[
        "photo"
    ],
    "wof:name":"Captured Moments Photography",
    "wof:placetype":"venue"
},
  "geometry": {"coordinates":[-79.681451,35.693472],"type":"Point"}
}