{
  "type": "Feature",
  "properties": {
    "iso:country":"US",
    "sg:address":"9913 River Rd",
    "sg:city":"Wilmington",
    "sg:classifiers":[
        {
            "category":"Real Estate",
            "subcategory":"Real Estate Services",
            "type":"Services"
        }
    ],
    "sg:phone":"+1 910 458 3388",
    "sg:postcode":"28412",
    "sg:province":"NC",
    "wof:name":"Anchor View Mobile Home Park",
    "wof:placetype":"venue"
},
  "geometry": {"coordinates":[-77.900367,34.064137],"type":"Point"}
}