{
  "type": "Feature",
  "properties": {
    "iso:country":"US",
    "sg:address":"404 7 Hills Annex Rd W",
    "sg:city":"Wilson",
    "sg:classifiers":[
        {
            "category":"Autos & Motor Vehicles",
            "subcategory":"Auto Supplies",
            "type":"Retail Goods"
        }
    ],
    "sg:phone":"+1 252 243 6660",
    "sg:postcode":"27893",
    "sg:province":"NC",
    "sg:tags":[
        "automobile",
        "stereo",
        "radio"
    ],
    "wof:name":"Street Sounds",
    "wof:placetype":"venue"
},
  "geometry": {"coordinates":[-78.03282799999999,35.504211],"type":"Point"}
}