{
  "type": "Feature",
  "properties": {
    "addr:full":"4806 College Rd Battleboro NC 27809",
    "addr:housenumber":"4806",
    "addr:postcode":"27809",
    "addr:street":"College Rd",
    "iso:country":"US",
    "sg:address":"4806 College Rd",
    "sg:city":"Battleboro",
    "sg:classifiers":[
        {
            "category":"Wholesale",
            "subcategory":"Construction Materials",
            "type":"Manufacturing & Wholesale Goods"
        }
    ],
    "sg:phone":"+1 252 977 1818",
    "sg:postcode":"27809",
    "sg:province":"NC",
    "sg:tags":[
        "fence"
    ],
    "wof:name":"Seegars Fence Co",
    "wof:placetype":"venue"
},
  "geometry": {"coordinates":[-77.76708600000001,36.014201],"type":"Point"}
}