{
  "type": "Feature",
  "properties": {
    "iso:country":"US",
    "sg:address":"3141 Garden Rd",
    "sg:city":"Burlington",
    "sg:classifiers":[
        {
            "category":"Personal",
            "subcategory":"Beauty Salon",
            "type":"Services"
        }
    ],
    "sg:phone":"+1 336 586 0209",
    "sg:postcode":"27215",
    "sg:province":"NC",
    "wof:name":"Smart Style Family Hair Salon",
    "wof:placetype":"venue"
},
  "geometry": {"coordinates":[-79.49957499999999,36.069194],"type":"Point"}
}