{
  "type": "Feature",
  "properties": {
    "addr:full":"6 Abingdon Way Durham NC 27713",
    "addr:housenumber":"6",
    "addr:postcode":"27713",
    "addr:street":"Abingdon Way",
    "iso:country":"US",
    "sg:address":"6 Abingdon Way",
    "sg:city":"Durham",
    "sg:classifiers":[
        {
            "category":"Recreation",
            "type":"Entertainment"
        },
        {
            "category":"Arena",
            "subcategory":"Sports Club",
            "type":"Entertainment"
        }
    ],
    "sg:phone":"+1 919 544 2857",
    "sg:postcode":"27713",
    "sg:province":"NC",
    "sg:tags":[
        "membership",
        "basketball"
    ],
    "sg:website":"www.juniorprepstars.com",
    "wof:name":"Junior Prep Stars Basketball",
    "wof:placetype":"venue"
},
  "geometry": {"coordinates":[-78.947902,35.913677],"type":"Point"}
}