{
  "type": "Feature",
  "properties": {
    "iso:country":"US",
    "sg:address":"217 Executive Park",
    "sg:city":"Asheville",
    "sg:classifiers":[
        {
            "category":"Banks & Credit Unions",
            "subcategory":"Bank",
            "type":"Services"
        }
    ],
    "sg:phone":"+1 828 254 8686",
    "sg:postcode":"28801",
    "sg:province":"NC",
    "sg:tags":[
        "loan",
        "real estate"
    ],
    "wof:name":"RMJ Inc",
    "wof:placetype":"venue"
},
  "geometry": {"coordinates":[-82.545422,35.59816],"type":"Point"}
}