{
  "type": "Feature",
  "properties": {
    "addr:full":"6322 Hidden Forest Dr Charlotte NC 28213",
    "addr:housenumber":"6322",
    "addr:postcode":"28213",
    "addr:street":"Hidden Forest Dr",
    "iso:country":"US",
    "sg:address":"6322 Hidden Forest Dr",
    "sg:city":"Charlotte",
    "sg:classifiers":[
        {
            "category":"Social Services",
            "subcategory":"Child Care",
            "type":"Services"
        }
    ],
    "sg:phone":"+1   ",
    "sg:postcode":"28213",
    "sg:province":"NC",
    "sg:tags":[
        "day"
    ],
    "wof:name":"Ms Chops",
    "wof:placetype":"venue"
},
  "geometry": {"coordinates":[-80.777823,35.27711],"type":"Point"}
}