{
  "type": "Feature",
  "properties": {
    "iso:country":"US",
    "sg:address":"3205 Summit Ave",
    "sg:city":"Greensboro",
    "sg:classifiers":[
        {
            "category":"Personal",
            "subcategory":"Beauty Salon",
            "type":"Services"
        }
    ],
    "sg:phone":"+1 336 621 4663",
    "sg:postcode":"27405",
    "sg:province":"NC",
    "sg:tags":[
        "shop"
    ],
    "wof:name":"We 3 Hair Salon",
    "wof:placetype":"venue"
},
  "geometry": {"coordinates":[-79.76246,36.119739],"type":"Point"}
}