{
  "type": "Feature",
  "properties": {
    "iso:country":"US",
    "sg:address":"837 Oakwood Acres Rd",
    "sg:city":"Asheboro",
    "sg:classifiers":[
        {
            "category":"Retail",
            "subcategory":"Repair Shop",
            "type":"Services"
        }
    ],
    "sg:phone":"+1   ",
    "sg:postcode":"27205",
    "sg:province":"NC",
    "sg:tags":[
        "electrical",
        "recorder",
        "video",
        "cassette"
    ],
    "wof:name":"Smith M David Electronics",
    "wof:placetype":"venue"
},
  "geometry": {"coordinates":[-79.846271,35.67042],"type":"Point"}
}