{
  "type": "Feature",
  "properties": {
    "addr:full":"24877 Thompson Rd Albemarle NC 28001",
    "addr:housenumber":"24877",
    "addr:postcode":"28001",
    "addr:street":"Thompson Rd",
    "iso:country":"US",
    "sg:address":"24877 Thompson Rd",
    "sg:city":"Albemarle",
    "sg:classifiers":[
        {
            "category":"Wholesale",
            "subcategory":"Poultry",
            "type":"Manufacturing & Wholesale Goods"
        }
    ],
    "sg:phone":"+1 704 982 2373",
    "sg:postcode":"28001",
    "sg:province":"NC",
    "wof:name":"Hinson Poultry Svc",
    "wof:placetype":"venue"
},
  "geometry": {"coordinates":[-80.255493,35.320797],"type":"Point"}
}