{
  "type": "Feature",
  "properties": {
    "addr:full":"1886 N Bragg Blvd Spring Lake NC 28390",
    "addr:housenumber":"1886",
    "addr:postcode":"28390",
    "addr:street":"N Bragg Blvd",
    "iso:country":"US",
    "sg:address":"1886 N Bragg Blvd",
    "sg:city":"Spring Lake",
    "sg:classifiers":[
        {
            "category":"Food & Beverages",
            "subcategory":"Groceries & Convenience Stores",
            "type":"Retail Goods"
        }
    ],
    "sg:phone":"+1 910 436 5623",
    "sg:postcode":"28390",
    "sg:province":"NC",
    "wof:name":"Kangaroo",
    "wof:placetype":"venue"
},
  "geometry": {"coordinates":[-78.987506,35.194764],"type":"Point"}
}