{
  "type": "Feature",
  "properties": {
    "addr:full":"7800 Falls of Neuse Rd Raleigh NC 27615",
    "addr:housenumber":"7800",
    "addr:postcode":"27615",
    "addr:street":"Falls Of Neuse Rd",
    "iso:country":"US",
    "sg:address":"7800 Falls of Neuse Rd",
    "sg:city":"Raleigh",
    "sg:classifiers":[
        {
            "category":"Professional",
            "subcategory":"Business Services",
            "type":"Services"
        }
    ],
    "sg:phone":"+1 919 846 0021",
    "sg:postcode":"27615",
    "sg:province":"NC",
    "sg:tags":[
        "process",
        "server"
    ],
    "wof:name":"Galvin Process Serving & Skip",
    "wof:placetype":"venue"
},
  "geometry": {"coordinates":[-78.62723,35.891458],"type":"Point"}
}