{
  "type": "Feature",
  "properties": {
    "iso:country":"US",
    "sg:address":"156 Bob Cat Ln",
    "sg:city":"Henderson",
    "sg:classifiers":[
        {
            "category":"Personal",
            "subcategory":"Beauty Salon",
            "type":"Services"
        }
    ],
    "sg:phone":"+1 252 431 1442",
    "sg:postcode":"27537",
    "sg:province":"NC",
    "wof:name":"Hair In Motion",
    "wof:placetype":"venue"
},
  "geometry": {"coordinates":[-78.326429,36.316303],"type":"Point"}
}