{
  "type": "Feature",
  "properties": {
    "iso:country":"US",
    "sg:address":"1029 Miller Rd",
    "sg:city":"Tabor City",
    "sg:classifiers":[
        {
            "category":"Utilities",
            "subcategory":"Mobile Phone",
            "type":"Services"
        }
    ],
    "sg:phone":"+1 910 653 9947",
    "sg:postcode":"28463",
    "sg:province":"NC",
    "sg:tags":[
        "satellite"
    ],
    "wof:name":"USA Satellites",
    "wof:placetype":"venue"
},
  "geometry": {"coordinates":[-78.76751,34.116633],"type":"Point"}
}