{
  "type": "Feature",
  "properties": {
    "iso:country":"US",
    "sg:address":"1924 S 16th St",
    "sg:city":"Wilmington",
    "sg:classifiers":[
        {
            "category":"Organizations",
            "subcategory":"Professional Association",
            "type":"Services"
        }
    ],
    "sg:phone":"+1 910 254 7124",
    "sg:postcode":"28401",
    "sg:province":"NC",
    "wof:name":"Ocean House Mental Health Assn",
    "wof:placetype":"venue"
},
  "geometry": {"coordinates":[-77.92618899999999,34.213284],"type":"Point"}
}