{
  "type": "Feature",
  "properties": {
    "iso:country":"US",
    "sg:address":"6480 Market St",
    "sg:city":"Wilmington",
    "sg:classifiers":[
        {
            "category":"Food & Beverages",
            "subcategory":"Groceries & Convenience Stores",
            "type":"Retail Goods"
        }
    ],
    "sg:phone":"+1 910 392 2741",
    "sg:postcode":"28405",
    "sg:province":"NC",
    "wof:name":"Pantry",
    "wof:placetype":"venue"
},
  "geometry": {"coordinates":[-77.84206399999999,34.256106],"type":"Point"}
}