{
  "type": "Feature",
  "properties": {
    "addr:full":"176 Commerce Blvd Statesville NC 28625",
    "addr:housenumber":"176",
    "addr:postcode":"28625",
    "addr:street":"Commerce Blvd",
    "iso:country":"US",
    "sg:address":"176 Commerce Blvd",
    "sg:city":"Statesville",
    "sg:classifiers":[
        {
            "category":"Building & Trades",
            "subcategory":"Construction",
            "type":"Services"
        }
    ],
    "sg:phone":"+1 704 872 7614",
    "sg:postcode":"28625",
    "sg:province":"NC",
    "sg:tags":[
        "water",
        "well",
        "drilling",
        "contractor"
    ],
    "wof:name":"Air Drilling Company",
    "wof:placetype":"venue"
},
  "geometry": {"coordinates":[-80.844902,35.821474],"type":"Point"}
}