{
  "type": "Feature",
  "properties": {
    "addr:full":"310 N College Rd Wilmington NC 28405",
    "addr:housenumber":"310",
    "addr:postcode":"28405",
    "addr:street":"N College Rd",
    "iso:country":"US",
    "sg:address":"310 N College Rd",
    "sg:city":"Wilmington",
    "sg:classifiers":[
        {
            "category":"Manufacturing",
            "subcategory":"Metals",
            "type":"Manufacturing & Wholesale Goods"
        }
    ],
    "sg:phone":"+1 910 784 7200",
    "sg:postcode":"28405",
    "sg:province":"NC",
    "sg:tags":[
        "fiber",
        "optics",
        "system"
    ],
    "sg:website":"www.corning.com",
    "wof:name":"Corning Inc",
    "wof:placetype":"venue"
},
  "geometry": {"coordinates":[-77.871264,34.248279],"type":"Point"}
}