{
  "type": "Feature",
  "properties": {
    "iso:country":"US",
    "sg:address":"126 S Main St",
    "sg:city":"Davidson",
    "sg:classifiers":[
        {
            "category":"Shopping",
            "subcategory":"Books",
            "type":"Retail Goods"
        }
    ],
    "sg:phone":"+1 704 892 6841",
    "sg:postcode":"28036",
    "sg:province":"NC",
    "sg:tags":[
        "dealer"
    ],
    "wof:name":"Main Street Books",
    "wof:placetype":"venue"
},
  "geometry": {"coordinates":[-80.84865000000001,35.498626],"type":"Point"}
}