{
  "type": "Feature",
  "properties": {
    "addr:full":"9200 Glenwater Dr Charlotte NC 28262",
    "addr:housenumber":"9200",
    "addr:postcode":"28262",
    "addr:street":"Glenwater Dr",
    "iso:country":"US",
    "sg:address":"9200 Glenwater Dr",
    "sg:city":"Charlotte",
    "sg:classifiers":[
        {
            "category":"Health Services",
            "subcategory":"Nursing And Care Facility",
            "type":"Services"
        }
    ],
    "sg:phone":"+1 704 549 0807",
    "sg:postcode":"28262",
    "sg:province":"NC",
    "sg:tags":[
        "home",
        "convalescent"
    ],
    "wof:name":"Britthaven Of Charlotte",
    "wof:placetype":"venue"
},
  "geometry": {"coordinates":[-80.751797,35.314634],"type":"Point"}
}