{
  "type": "Feature",
  "properties": {
    "iso:country":"US",
    "sg:address":"1076 State Hwy 58",
    "sg:city":"Cape Carteret",
    "sg:classifiers":[
        {
            "category":"Shopping",
            "subcategory":"Used Merchandise",
            "type":"Retail Goods"
        }
    ],
    "sg:phone":"+1 252 393 8083",
    "sg:postcode":"28584",
    "sg:province":"NC",
    "sg:tags":[
        "shop",
        "consignment"
    ],
    "wof:name":"Lawson Consignment & Gift Shop",
    "wof:placetype":"venue"
},
  "geometry": {"coordinates":[-77.067938,34.714255],"type":"Point"}
}