{
  "type": "Feature",
  "properties": {
    "iso:country":"US",
    "sg:address":"1847 Stanton Dr",
    "sg:city":"Greenville",
    "sg:classifiers":[
        {
            "category":"Freight",
            "type":"Transportation"
        }
    ],
    "sg:phone":"+1 252 830 4881",
    "sg:postcode":"27834",
    "sg:province":"NC",
    "sg:tags":[
        "local",
        "mover",
        "storage",
        "trucking"
    ],
    "wof:name":"A & A Moving Company",
    "wof:placetype":"venue"
},
  "geometry": {"coordinates":[-77.494058,35.602995],"type":"Point"}
}