{
  "type": "Feature",
  "properties": {
    "iso:country":"US",
    "sg:address":"7615 Six Forks Rd",
    "sg:city":"Raleigh",
    "sg:classifiers":[
        {
            "category":"Retail",
            "subcategory":"Funeral Services",
            "type":"Services"
        }
    ],
    "sg:phone":"+1 919 866 1866",
    "sg:postcode":"27615",
    "sg:province":"NC",
    "sg:tags":[
        "director"
    ],
    "wof:name":"Renaissance Funeral Home Inc",
    "wof:placetype":"venue"
},
  "geometry": {"coordinates":[-78.646207,35.882796],"type":"Point"}
}