{
  "type": "Feature",
  "properties": {
    "addr:full":"1018 Dawson Rd Chapel Hill NC 27516",
    "addr:housenumber":"1018",
    "addr:postcode":"27516",
    "addr:street":"Dawson Rd",
    "iso:country":"US",
    "sg:address":"1018 Dawson Rd",
    "sg:city":"Chapel Hill",
    "sg:classifiers":[
        {
            "category":"Retail",
            "subcategory":"Repair Shop",
            "type":"Services"
        }
    ],
    "sg:phone":"+1 919 942 2988",
    "sg:postcode":"27516",
    "sg:province":"NC",
    "sg:tags":[
        "taxidermist"
    ],
    "wof:name":"Steve's Fish & Game Mounts",
    "wof:placetype":"venue"
},
  "geometry": {"coordinates":[-79.234111,35.886913],"type":"Point"}
}