{
  "type": "Feature",
  "properties": {
    "iso:country":"US",
    "sg:address":"801 S Raiford St",
    "sg:city":"Selma",
    "sg:classifiers":[
        {
            "category":"Freight",
            "type":"Transportation"
        }
    ],
    "sg:phone":"+1 919 965 5937",
    "sg:postcode":"27576",
    "sg:province":"NC",
    "sg:tags":[
        "operator",
        "local",
        "trucking"
    ],
    "wof:name":"Stancil Trucking Co",
    "wof:placetype":"venue"
},
  "geometry": {"coordinates":[-78.288338,35.52986],"type":"Point"}
}