{
  "type": "Feature",
  "properties": {
    "addr:full":"4124 Carybrook Rd Rocky Mount NC 27803",
    "addr:housenumber":"4124",
    "addr:postcode":"27803",
    "addr:street":"Carybrook Rd",
    "iso:country":"US",
    "sg:address":"4124 Carybrook Rd",
    "sg:city":"Rocky Mount",
    "sg:classifiers":[
        {
            "category":"Real Estate",
            "subcategory":"Architect",
            "type":"Services"
        }
    ],
    "sg:phone":"+1 252 443 0404",
    "sg:postcode":"27803",
    "sg:province":"NC",
    "wof:name":"Donald Martin",
    "wof:placetype":"venue"
},
  "geometry": {"coordinates":[-77.867047,35.94789],"type":"Point"}
}