{
  "type": "Feature",
  "properties": {
    "iso:country":"US",
    "sg:address":"2631 Durham-Chapel Hill Blvd",
    "sg:city":"Durham",
    "sg:classifiers":[
        {
            "category":"Shopping",
            "subcategory":"Used Merchandise",
            "type":"Retail Goods"
        }
    ],
    "sg:phone":"+1 919 683 1865",
    "sg:postcode":"27707",
    "sg:province":"NC",
    "sg:tags":[
        "antique"
    ],
    "wof:name":"Chelsea Antiques",
    "wof:placetype":"venue"
},
  "geometry": {"coordinates":[-78.92652,35.974653],"type":"Point"}
}