{
  "type": "Feature",
  "properties": {
    "addr:full":"3111 Springbank Ln Charlotte NC 28226",
    "addr:housenumber":"3111",
    "addr:postcode":"28226",
    "addr:street":"Springbank Ln",
    "iso:country":"US",
    "sg:address":"3111 Springbank Ln",
    "sg:city":"Charlotte",
    "sg:classifiers":[
        {
            "category":"Health Services",
            "subcategory":"Doctor",
            "type":"Services"
        },
        {
            "category":"Personal",
            "subcategory":"Skin Care",
            "type":"Services"
        }
    ],
    "sg:phone":"+1 704 541 6001",
    "sg:postcode":"28226",
    "sg:province":"NC",
    "sg:tags":[
        "dermatology",
        "physician",
        "surgeon",
        "surgeons"
    ],
    "sg:website":"http://www.arboretumderm.com",
    "wof:name":"Arboretum Dermatology",
    "wof:placetype":"venue"
},
  "geometry": {"coordinates":[-80.779769,35.101667],"type":"Point"}
}