{
  "type": "Feature",
  "properties": {
    "addr:full":"21007 State Hwy 73 Albemarle NC 28001",
    "addr:housenumber":"21007",
    "addr:postcode":"28001",
    "addr:street":"State Hwy 73",
    "iso:country":"US",
    "sg:address":"21007 State Hwy 73",
    "sg:city":"Albemarle",
    "sg:classifiers":[
        {
            "category":"Farming",
            "subcategory":"Nursery",
            "type":"Manufacturing & Wholesale Goods"
        }
    ],
    "sg:phone":"+1 704 982 2264",
    "sg:postcode":"28001",
    "sg:province":"NC",
    "sg:tags":[
        "operation"
    ],
    "wof:name":"Jan-Mark Nursery",
    "wof:placetype":"venue"
},
  "geometry": {"coordinates":[-80.31057300000001,35.381121],"type":"Point"}
}