{
  "type": "Feature",
  "properties": {
    "iso:country":"US",
    "sg:address":"6014 Trysting Rd",
    "sg:city":"Charlotte",
    "sg:classifiers":[
        {
            "category":"Building & Trades",
            "subcategory":"Landscaping Services",
            "type":"Services"
        }
    ],
    "sg:phone":"+1 704 531 0937",
    "sg:postcode":"28227",
    "sg:province":"NC",
    "wof:name":"Sullens Lawn Care",
    "wof:placetype":"venue"
},
  "geometry": {"coordinates":[-80.72026,35.218996],"type":"Point"}
}