{
  "type": "Feature",
  "properties": {
    "iso:country":"US",
    "sg:address":"1144 Executive Cir",
    "sg:city":"Cary",
    "sg:classifiers":[
        {
            "category":"Health Services",
            "subcategory":"Dentist",
            "type":"Services"
        }
    ],
    "sg:phone":"+1 919 467 9921",
    "sg:postcode":"27511",
    "sg:province":"NC",
    "wof:name":"American Association of Oral & Maxillofacial Srgns",
    "wof:placetype":"venue"
},
  "geometry": {"coordinates":[-78.78089900000001,35.7663],"type":"Point"}
}