{
  "type": "Feature",
  "properties": {
    "addr:full":"9 Dundas Cir Greensboro NC 27407",
    "addr:housenumber":"9",
    "addr:postcode":"27407",
    "addr:street":"Dundas Cir",
    "iso:country":"US",
    "sg:address":"9 Dundas Cir",
    "sg:city":"Greensboro",
    "sg:classifiers":[
        {
            "category":"Professional",
            "subcategory":"Computer Services",
            "type":"Services"
        }
    ],
    "sg:phone":"+1 336 547 8007",
    "sg:postcode":"27407",
    "sg:province":"NC",
    "sg:tags":[
        "repair"
    ],
    "wof:name":"USA PC Repair",
    "wof:placetype":"venue"
},
  "geometry": {"coordinates":[-79.864096,36.067993],"type":"Point"}
}