{
  "type": "Feature",
  "properties": {
    "iso:country":"US",
    "sg:address":"12098 Big Lick Rd",
    "sg:city":"Stanfield",
    "sg:classifiers":[
        {
            "category":"Building & Trades",
            "subcategory":"Construction",
            "type":"Services"
        }
    ],
    "sg:phone":"+1 704 888 0232",
    "sg:postcode":"28163",
    "sg:province":"NC",
    "sg:tags":[
        "residential"
    ],
    "wof:name":"Mark B Waters Construction",
    "wof:placetype":"venue"
},
  "geometry": {"coordinates":[-80.401929,35.237519],"type":"Point"}
}