{
  "type": "Feature",
  "properties": {
    "iso:country":"US",
    "sg:address":"5328 Vickrey Chapel Rd",
    "sg:city":"Jamestown",
    "sg:classifiers":[
        {
            "category":"Home & Garden",
            "subcategory":"Garden Supply",
            "type":"Retail Goods"
        }
    ],
    "sg:phone":"+1 336 454 1497",
    "sg:postcode":"27282",
    "sg:province":"NC",
    "wof:name":"Winslow Lawn Maintenance",
    "wof:placetype":"venue"
},
  "geometry": {"coordinates":[-79.898038,35.964881],"type":"Point"}
}