{
  "type": "Feature",
  "properties": {
    "addr:full":"1517 Smokey Park Hwy Candler NC 28715",
    "addr:housenumber":"1517",
    "addr:postcode":"28715",
    "addr:street":"Smokey Park Hwy",
    "iso:country":"US",
    "sg:address":"1517 Smokey Park Hwy",
    "sg:city":"Candler",
    "sg:classifiers":[
        {
            "category":"Retail",
            "subcategory":"Self-service Laundry",
            "type":"Services"
        }
    ],
    "sg:phone":"+1   ",
    "sg:postcode":"28715",
    "sg:province":"NC",
    "sg:tags":[
        "coin"
    ],
    "wof:name":"Soap Box Laudromat 2",
    "wof:placetype":"venue"
},
  "geometry": {"coordinates":[-82.68443600000001,35.544272],"type":"Point"}
}