{
  "type": "Feature",
  "properties": {
    "addr:full":"807 W Mountain Dr Fayetteville NC 28306",
    "addr:housenumber":"807",
    "addr:postcode":"28306",
    "addr:street":"W Mountain Dr",
    "iso:country":"US",
    "sg:address":"807 W Mountain Dr",
    "sg:city":"Fayetteville",
    "sg:classifiers":[
        {
            "category":"Building & Trades",
            "subcategory":"Electrical",
            "type":"Services"
        }
    ],
    "sg:phone":"+1 910 481 0955",
    "sg:postcode":"28306",
    "sg:province":"NC",
    "sg:tags":[
        "electric",
        "contractor"
    ],
    "wof:name":"Joe Parker Electric Inc",
    "wof:placetype":"venue"
},
  "geometry": {"coordinates":[-78.916523,35.016031],"type":"Point"}
}