{
  "type": "Feature",
  "properties": {
    "addr:full":"3609 Artee Rd Shelby NC 28150",
    "addr:housenumber":"3609",
    "addr:postcode":"28150",
    "addr:street":"Artee Rd",
    "iso:country":"US",
    "sg:address":"3609 Artee Rd",
    "sg:city":"Shelby",
    "sg:classifiers":[
        {
            "category":"Building & Trades",
            "subcategory":"Construction",
            "type":"Services"
        }
    ],
    "sg:phone":"+1 704 434 8704",
    "sg:postcode":"28150",
    "sg:province":"NC",
    "sg:tags":[
        "contractor"
    ],
    "wof:name":"Hipps Roofing Company Inc",
    "wof:placetype":"venue"
},
  "geometry": {"coordinates":[-81.634304,35.30893],"type":"Point"}
}