{
  "type": "Feature",
  "properties": {
    "iso:country":"US",
    "sg:address":"4591 Old Mountain Rd",
    "sg:city":"Stony Point",
    "sg:classifiers":[
        {
            "category":"Building & Trades",
            "subcategory":"Construction",
            "type":"Services"
        },
        {
            "category":"Utilities",
            "subcategory":"Water",
            "type":"Services"
        }
    ],
    "sg:phone":"+1 704 585 6190",
    "sg:postcode":"28678",
    "sg:province":"NC",
    "sg:tags":[
        "company",
        "sewer",
        "line",
        "sewage"
    ],
    "wof:name":"Foothills Water and Sewer Inc",
    "wof:placetype":"venue"
},
  "geometry": {"coordinates":[-81.063041,35.847571],"type":"Point"}
}