{
  "type": "Feature",
  "properties": {
    "addr:full":"4115 Capitol St Durham NC 27704",
    "addr:housenumber":"4115",
    "addr:postcode":"27704",
    "addr:street":"Capitol St",
    "iso:country":"US",
    "sg:address":"4115 Capitol St",
    "sg:city":"Durham",
    "sg:classifiers":[
        {
            "category":"Health Services",
            "subcategory":"Doctor",
            "type":"Services"
        }
    ],
    "sg:phone":"+1 919 479 5028",
    "sg:postcode":"27704",
    "sg:province":"NC",
    "sg:tags":[
        "dentist"
    ],
    "wof:name":"Jeffrey R Cecil DDS",
    "wof:placetype":"venue"
},
  "geometry": {"coordinates":[-78.897982,36.047294],"type":"Point"}
}