{
  "type": "Feature",
  "properties": {
    "iso:country":"US",
    "sg:address":"6180 Lake Brandt Rd",
    "sg:city":"Greensboro",
    "sg:classifiers":[
        {
            "category":"Professional",
            "subcategory":"Business Services",
            "type":"Services"
        }
    ],
    "sg:phone":"+1   ",
    "sg:postcode":"27455",
    "sg:province":"NC",
    "wof:name":"Jan C McLean",
    "wof:placetype":"venue"
},
  "geometry": {"coordinates":[-79.84410699999999,36.200077],"type":"Point"}
}