{
  "type": "Feature",
  "properties": {
    "iso:country":"US",
    "sg:address":"134 Charlotte Hwy",
    "sg:city":"Asheville",
    "sg:classifiers":[
        {
            "category":"Banks & Credit Unions",
            "subcategory":"Bank",
            "type":"Services"
        }
    ],
    "sg:phone":"+1 828 277 2125",
    "sg:postcode":"28803",
    "sg:province":"NC",
    "wof:name":"First South Bank",
    "wof:placetype":"venue"
},
  "geometry": {"coordinates":[-82.481853,35.554806],"type":"Point"}
}