{
  "type": "Feature",
  "properties": {
    "iso:country":"US",
    "sg:address":"1404 Concord Ave",
    "sg:city":"Monroe",
    "sg:classifiers":[
        {
            "category":"Organizations",
            "subcategory":"Religious Organization",
            "type":"Services"
        }
    ],
    "sg:phone":"+1   ",
    "sg:postcode":"28110",
    "sg:province":"NC",
    "wof:name":"V The Bethel House Of Refuge",
    "wof:placetype":"venue"
},
  "geometry": {"coordinates":[-80.554417,34.996654],"type":"Point"}
}