{
  "type": "Feature",
  "properties": {
    "addr:full":"1907 New Sharon Church Rd Hillsborough NC 27278",
    "addr:housenumber":"1907",
    "addr:postcode":"27278",
    "addr:street":"New Sharon Church Rd",
    "iso:country":"US",
    "sg:address":"1907 New Sharon Church Rd",
    "sg:city":"Hillsborough",
    "sg:classifiers":[
        {
            "category":"Building & Trades",
            "subcategory":"Construction",
            "type":"Services"
        }
    ],
    "sg:phone":"+1 919 245 3024",
    "sg:postcode":"27278",
    "sg:province":"NC",
    "sg:tags":[
        "house"
    ],
    "wof:name":"Quality Homes of Triangle Inc",
    "wof:placetype":"venue"
},
  "geometry": {"coordinates":[-79.04043799999999,36.12301],"type":"Point"}
}