{
  "type": "Feature",
  "properties": {
    "iso:country":"US",
    "sg:address":"21 High Bluff Dr",
    "sg:city":"Weaverville",
    "sg:classifiers":[
        {
            "category":"Professional",
            "subcategory":"Management & Consulting",
            "type":"Services"
        }
    ],
    "sg:phone":"+1   ",
    "sg:postcode":"28787",
    "sg:province":"NC",
    "sg:tags":[
        "business"
    ],
    "wof:name":"Elk Mountain Technical Svcs",
    "wof:placetype":"venue"
},
  "geometry": {"coordinates":[-82.528398,35.701134],"type":"Point"}
}