{
  "type": "Feature",
  "properties": {
    "iso:country":"US",
    "sg:address":"901 Ruskin Dr",
    "sg:city":"High Point",
    "sg:classifiers":[
        {
            "category":"Social Services",
            "subcategory":"Child Care",
            "type":"Services"
        }
    ],
    "sg:phone":"+1   ",
    "sg:postcode":"27265",
    "sg:province":"NC",
    "sg:tags":[
        "day"
    ],
    "wof:name":"Diamond Day Central Inc",
    "wof:placetype":"venue"
},
  "geometry": {"coordinates":[-80.021603,36.029378],"type":"Point"}
}