{
  "type": "Feature",
  "properties": {
    "addr:full":"171 Cari Ln Matthews NC 28104",
    "addr:housenumber":"171",
    "addr:postcode":"28104",
    "addr:street":"Cari Ln",
    "iso:country":"US",
    "sg:address":"171 Cari Ln",
    "sg:city":"Matthews",
    "sg:classifiers":[
        {
            "category":"Professional",
            "subcategory":"Business Services",
            "type":"Services"
        }
    ],
    "sg:phone":"+1   ",
    "sg:postcode":"28104",
    "sg:province":"NC",
    "wof:name":"Ohara Group LLC",
    "wof:placetype":"venue"
},
  "geometry": {"coordinates":[-80.733367,35.052033],"type":"Point"}
}