{
  "type": "Feature",
  "properties": {
    "addr:full":"6629 Vance St Bailey NC 27807",
    "addr:housenumber":"6629",
    "addr:postcode":"27807",
    "addr:street":"Vance St",
    "iso:country":"US",
    "sg:address":"6629 Vance St",
    "sg:city":"Bailey",
    "sg:classifiers":[
        {
            "category":"Museum",
            "type":"Entertainment"
        }
    ],
    "sg:phone":"+1 252 235 4165",
    "sg:postcode":"27807",
    "sg:province":"NC",
    "wof:name":"Country Doctor Museum",
    "wof:placetype":"venue"
},
  "geometry": {"coordinates":[-78.12216600000001,35.778304],"type":"Point"}
}