{
  "type": "Feature",
  "properties": {
    "iso:country":"US",
    "sg:address":"4719 High Point Rd",
    "sg:city":"Greensboro",
    "sg:classifiers":[
        {
            "category":"Retail",
            "subcategory":"Self-service Laundry",
            "type":"Services"
        }
    ],
    "sg:phone":"+1   ",
    "sg:postcode":"27407",
    "sg:province":"NC",
    "sg:tags":[
        "coin"
    ],
    "wof:name":"Sedgefield Laundromat",
    "wof:placetype":"venue"
},
  "geometry": {"coordinates":[-79.869788,36.028412],"type":"Point"}
}