{
  "type": "Feature",
  "properties": {
    "addr:full":"458 Whitmire St Brevard NC 28712",
    "addr:housenumber":"458",
    "addr:postcode":"28712",
    "addr:street":"Whitmire St",
    "iso:country":"US",
    "sg:address":"458 Whitmire St",
    "sg:city":"Brevard",
    "sg:classifiers":[
        {
            "category":"Shopping",
            "subcategory":"Discount & Variety Stores",
            "type":"Retail Goods"
        }
    ],
    "sg:phone":"+1 828 862 4288",
    "sg:postcode":"28712",
    "sg:province":"NC",
    "sg:tags":[
        "merchandise",
        "general"
    ],
    "wof:name":"Hobo's General Store",
    "wof:placetype":"venue"
},
  "geometry": {"coordinates":[-82.737419,35.239583],"type":"Point"}
}