{
  "type": "Feature",
  "properties": {
    "addr:full":"605 W. Main St. Suite 109 Carrboro NC 27510",
    "addr:housenumber":"605",
    "addr:postcode":"27510",
    "addr:street":"W. Main St. Suite 109",
    "iso:country":"US",
    "sg:address":"605 W. Main St. Suite 109",
    "sg:city":"Carrboro",
    "sg:classifiers":[
        {
            "category":"Professional",
            "subcategory":"Computer Services",
            "type":"Services"
        }
    ],
    "sg:postcode":"27510",
    "sg:province":"NC",
    "sg:tags":[
        "mapping",
        "mobile",
        "schmap"
    ],
    "sg:website":"http://www.schmap.com/",
    "wof:name":"Schmap",
    "wof:placetype":"venue"
},
  "geometry": {"coordinates":[-79.079706,35.913575],"type":"Point"}
}