{
  "type": "Feature",
  "properties": {
    "addr:full":"1000 Easthampton Ln Waxhaw NC 28173",
    "addr:housenumber":"1000",
    "addr:postcode":"28173",
    "addr:street":"Easthampton Ln",
    "iso:country":"US",
    "sg:address":"1000 Easthampton Ln",
    "sg:city":"Waxhaw",
    "sg:classifiers":[
        {
            "category":"Professional",
            "subcategory":"Management & Consulting",
            "type":"Services"
        }
    ],
    "sg:phone":"+1   ",
    "sg:postcode":"28173",
    "sg:province":"NC",
    "sg:tags":[
        "business"
    ],
    "wof:name":"Labonte Consulting Group",
    "wof:placetype":"venue"
},
  "geometry": {"coordinates":[-80.67761299999999,34.983696],"type":"Point"}
}