{
  "type": "Feature",
  "properties": {
    "addr:full":"161 Parker St Jarvisburg NC 27947",
    "addr:housenumber":"161",
    "addr:postcode":"27947",
    "addr:street":"Parker St",
    "iso:country":"US",
    "sg:address":"161 Parker St",
    "sg:city":"Jarvisburg",
    "sg:classifiers":[
        {
            "category":"Personal",
            "subcategory":"Beauty Salon",
            "type":"Services"
        }
    ],
    "sg:phone":"+1 252 491 2662",
    "sg:postcode":"27947",
    "sg:province":"NC",
    "wof:name":"Diane's Family Hair Care",
    "wof:placetype":"venue"
},
  "geometry": {"coordinates":[-75.871488,36.178318],"type":"Point"}
}