{
  "type": "Feature",
  "properties": {
    "iso:country":"US",
    "sg:address":"2755 Culbreth Rd",
    "sg:city":"Fayetteville",
    "sg:classifiers":[
        {
            "category":"Building & Trades",
            "subcategory":"Construction",
            "type":"Services"
        }
    ],
    "sg:phone":"+1 910 485 4342",
    "sg:postcode":"28312",
    "sg:province":"NC",
    "sg:tags":[
        "house"
    ],
    "wof:name":"Williamson Construction",
    "wof:placetype":"venue"
},
  "geometry": {"coordinates":[-78.758925,34.969709],"type":"Point"}
}