{
  "type": "Feature",
  "properties": {
    "addr:full":"23 Sunnybrook Rd Raleigh NC 27610",
    "addr:housenumber":"23",
    "addr:postcode":"27610",
    "addr:street":"Sunnybrook Rd",
    "iso:country":"US",
    "sg:address":"23 Sunnybrook Rd",
    "sg:city":"Raleigh",
    "sg:classifiers":[
        {
            "category":"Health Services",
            "subcategory":"Doctor",
            "type":"Services"
        }
    ],
    "sg:phone":"+1 919 250 0580",
    "sg:postcode":"27610",
    "sg:province":"NC",
    "sg:tags":[
        "physician",
        "surgeon"
    ],
    "wof:name":"Hart & Matheis",
    "wof:placetype":"venue"
},
  "geometry": {"coordinates":[-78.584446,35.78546],"type":"Point"}
}