{
  "type": "Feature",
  "properties": {
    "addr:full":"4470 Greenmeadow Lakes Cir Winston Salem NC 27106",
    "addr:housenumber":"4470",
    "addr:postcode":"27106",
    "addr:street":"Greenmeadow Lakes Cir",
    "iso:country":"US",
    "sg:address":"4470 Greenmeadow Lakes Cir",
    "sg:city":"Winston Salem",
    "sg:classifiers":[
        {
            "category":"Banks & Credit Unions",
            "subcategory":"Investment Brokerage",
            "type":"Services"
        }
    ],
    "sg:phone":"+1 336 922 4580",
    "sg:postcode":"27106",
    "sg:province":"NC",
    "sg:tags":[
        "security"
    ],
    "wof:name":"J W Jennette Financial Svc",
    "wof:placetype":"venue"
},
  "geometry": {"coordinates":[-80.347216,36.152508],"type":"Point"}
}