{
  "type": "Feature",
  "properties": {
    "addr:full":"24 Canterbury Rd Asheville NC 28805",
    "addr:housenumber":"24",
    "addr:postcode":"28805",
    "addr:street":"Canterbury Rd",
    "iso:country":"US",
    "sg:address":"24 Canterbury Rd",
    "sg:city":"Asheville",
    "sg:classifiers":[
        {
            "category":"Shopping",
            "subcategory":"Florist",
            "type":"Retail Goods"
        }
    ],
    "sg:phone":"+1 828 298 8713",
    "sg:postcode":"28805",
    "sg:province":"NC",
    "wof:name":"Candy Bouquet",
    "wof:placetype":"venue"
},
  "geometry": {"coordinates":[-82.500224,35.581831],"type":"Point"}
}