{
  "type": "Feature",
  "properties": {
    "iso:country":"US",
    "sg:address":"191 Jake's Mountain Rd",
    "sg:city":"Deep Gap",
    "sg:classifiers":[
        {
            "category":"Professional",
            "type":"Services"
        }
    ],
    "sg:phone":"+1 828 264 1112",
    "sg:postcode":"28618",
    "sg:province":"NC",
    "wof:name":"Vfd of Stewart-Simmons",
    "wof:placetype":"venue"
},
  "geometry": {"coordinates":[-81.561066,36.202683],"type":"Point"}
}