{
  "type": "Feature",
  "properties": {
    "iso:country":"US",
    "sg:address":"743 Hudson Rd",
    "sg:city":"Summerfield",
    "sg:classifiers":[
        {
            "category":"Building & Trades",
            "subcategory":"Plumbing",
            "type":"Services"
        }
    ],
    "sg:phone":"+1 336 272 4113",
    "sg:postcode":"27358",
    "sg:province":"NC",
    "sg:tags":[
        "heating",
        "contractor"
    ],
    "wof:name":"Hight Service Co Inc",
    "wof:placetype":"venue"
},
  "geometry": {"coordinates":[-79.866889,36.275089],"type":"Point"}
}