{
  "type": "Feature",
  "properties": {
    "iso:country":"US",
    "sg:address":"994 Carolina Rest Home Rd",
    "sg:city":"Roanoke Rapids",
    "sg:classifiers":[
        {
            "category":"Organizations",
            "subcategory":"Religious Organization",
            "type":"Services"
        }
    ],
    "sg:phone":"+1 252 537 9123",
    "sg:postcode":"27870",
    "sg:province":"NC",
    "sg:tags":[
        "church"
    ],
    "wof:name":"Roanoke Valley Free Will Bapt",
    "wof:placetype":"venue"
},
  "geometry": {"coordinates":[-77.690732,36.413046],"type":"Point"}
}