{
  "type": "Feature",
  "properties": {
    "addr:full":"209 Olde Well Loop Rd Wilmington NC 28411",
    "addr:housenumber":"209",
    "addr:postcode":"28411",
    "addr:street":"Olde Well Loop Rd",
    "iso:country":"US",
    "sg:address":"209 Olde Well Loop Rd",
    "sg:city":"Wilmington",
    "sg:classifiers":[
        {
            "category":"Building & Trades",
            "subcategory":"Construction",
            "type":"Services"
        }
    ],
    "sg:phone":"+1 910 392 7400",
    "sg:postcode":"28411",
    "sg:province":"NC",
    "sg:tags":[
        "concrete",
        "restoration",
        "cleaning",
        "repair"
    ],
    "wof:name":"Progressive Concrete Coatings",
    "wof:placetype":"venue"
},
  "geometry": {"coordinates":[-77.83897899999999,34.271035],"type":"Point"}
}