{
  "type": "Feature",
  "properties": {
    "iso:country":"US",
    "sg:address":"6769 Old Plank Rd",
    "sg:city":"Stanley",
    "sg:classifiers":[
        {
            "category":"Utilities",
            "subcategory":"Electric",
            "type":"Services"
        }
    ],
    "sg:phone":"+1 704 742 3000",
    "sg:postcode":"28164",
    "sg:province":"NC",
    "sg:tags":[
        "power"
    ],
    "wof:name":"Duke Power",
    "wof:placetype":"venue"
},
  "geometry": {"coordinates":[-81.040441,35.423732],"type":"Point"}
}