{
  "type": "Feature",
  "properties": {
    "iso:country":"US",
    "sg:address":"6901 Walter Gibson Rd",
    "sg:city":"Red Springs",
    "sg:classifiers":[
        {
            "category":"Recreation",
            "type":"Entertainment"
        }
    ],
    "sg:phone":"+1 910 843 5342",
    "sg:postcode":"28377",
    "sg:province":"NC",
    "sg:tags":[
        "stable"
    ],
    "wof:name":"Silver Dollar Quarter Horses",
    "wof:placetype":"venue"
},
  "geometry": {"coordinates":[-79.22226499999999,34.890987],"type":"Point"}
}