{
  "type": "Feature",
  "properties": {
    "iso:country":"US",
    "sg:address":"5535 Central Ave",
    "sg:city":"Charlotte",
    "sg:classifiers":[
        {
            "category":"Utilities",
            "subcategory":"Mobile Phone",
            "type":"Services"
        }
    ],
    "sg:phone":"+1 704 532 4499",
    "sg:postcode":"28212",
    "sg:province":"NC",
    "sg:tags":[
        "communications",
        "telephone"
    ],
    "wof:name":"Stars Wireless Inc",
    "wof:placetype":"venue"
},
  "geometry": {"coordinates":[-80.754639,35.20852],"type":"Point"}
}