{
  "type": "Feature",
  "properties": {
    "addr:full":"5034 Morrowick Rd Charlotte NC 28226",
    "addr:housenumber":"5034",
    "addr:postcode":"28226",
    "addr:street":"Morrowick Rd",
    "iso:country":"US",
    "sg:address":"5034 Morrowick Rd",
    "sg:city":"Charlotte",
    "sg:classifiers":[
        {
            "category":"Wholesale",
            "subcategory":"Machinery & Supplies",
            "type":"Manufacturing & Wholesale Goods"
        }
    ],
    "sg:phone":"+1 704 544 6463",
    "sg:postcode":"28226",
    "sg:province":"NC",
    "sg:tags":[
        "packaging"
    ],
    "wof:name":"High Technology Corp",
    "wof:placetype":"venue"
},
  "geometry": {"coordinates":[-80.81033499999999,35.114223],"type":"Point"}
}