{
  "type": "Feature",
  "properties": {
    "addr:full":"300 Parkthrough St Cary NC 27511",
    "addr:housenumber":"300",
    "addr:postcode":"27511",
    "addr:street":"Parkthrough St",
    "iso:country":"US",
    "sg:address":"300 Parkthrough St",
    "sg:city":"Cary",
    "sg:classifiers":[
        {
            "category":"Banks & Credit Unions",
            "subcategory":"Financial Services",
            "type":"Services"
        }
    ],
    "sg:phone":"+1 919 481 9767",
    "sg:postcode":"27511",
    "sg:province":"NC",
    "sg:tags":[
        "broker",
        "mortgage"
    ],
    "wof:name":"Mortgage Choice",
    "wof:placetype":"venue"
},
  "geometry": {"coordinates":[-78.78448899999999,35.786469],"type":"Point"}
}