{
  "type": "Feature",
  "properties": {
    "iso:country":"US",
    "sg:address":"2020 Walker Rd",
    "sg:city":"Winston Salem",
    "sg:classifiers":[
        {
            "category":"Education",
            "subcategory":"School",
            "type":"Public Place"
        }
    ],
    "sg:phone":"+1 336 922 6612",
    "sg:postcode":"27106",
    "sg:province":"NC",
    "wof:name":"Julian Gibson Elementary Schl",
    "wof:placetype":"venue"
},
  "geometry": {"coordinates":[-80.31081,36.187895],"type":"Point"}
}