{
  "type": "Feature",
  "properties": {
    "iso:country":"US",
    "sg:address":"3433 Airport Rd",
    "sg:city":"Hays",
    "sg:classifiers":[
        {
            "category":"Retail",
            "subcategory":"Repair Shop",
            "type":"Services"
        }
    ],
    "sg:phone":"+1   ",
    "sg:postcode":"28635",
    "sg:province":"NC",
    "wof:name":"Frank Horseshoeing",
    "wof:placetype":"venue"
},
  "geometry": {"coordinates":[-81.107376,36.241848],"type":"Point"}
}