{
  "type": "Feature",
  "properties": {
    "iso:country":"US",
    "sg:address":"5106 Carolwood Ln",
    "sg:city":"Durham",
    "sg:classifiers":[
        {
            "category":"Professional",
            "type":"Services"
        }
    ],
    "sg:phone":"+1   ",
    "sg:postcode":"27713",
    "sg:province":"NC",
    "wof:name":"Flouroco",
    "wof:placetype":"venue"
},
  "geometry": {"coordinates":[-78.93960199999999,35.932572],"type":"Point"}
}