{
  "type": "Feature",
  "properties": {
    "addr:full":"2503 Clarendon Blvd New Bern NC 28562",
    "addr:housenumber":"2503",
    "addr:postcode":"28562",
    "addr:street":"Clarendon Blvd",
    "iso:country":"US",
    "sg:address":"2503 Clarendon Blvd",
    "sg:city":"New Bern",
    "sg:classifiers":[
        {
            "category":"Restaurant",
            "type":"Food & Drink"
        }
    ],
    "sg:phone":"+1 252 633 3449",
    "sg:postcode":"28562",
    "sg:province":"NC",
    "sg:tags":[
        "eating"
    ],
    "wof:name":"Burger King",
    "wof:placetype":"venue"
},
  "geometry": {"coordinates":[-77.08122400000001,35.104756],"type":"Point"}
}