{
  "type": "Feature",
  "properties": {
    "addr:full":"38 Forest Lake Cir Greensboro NC 27407",
    "addr:housenumber":"38",
    "addr:postcode":"27407",
    "addr:street":"Forest Lake Cir",
    "iso:country":"US",
    "sg:address":"38 Forest Lake Cir",
    "sg:city":"Greensboro",
    "sg:classifiers":[
        {
            "category":"Building & Trades",
            "subcategory":"Construction",
            "type":"Services"
        }
    ],
    "sg:phone":"+1 336 965 3454",
    "sg:postcode":"27407",
    "sg:province":"NC",
    "sg:tags":[
        "siding",
        "contractor"
    ],
    "wof:name":"Guilford Siding & Windows",
    "wof:placetype":"venue"
},
  "geometry": {"coordinates":[-79.895809,36.031751],"type":"Point"}
}