{
  "type": "Feature",
  "properties": {
    "addr:full":"151 Hunter Dr Dunn NC 28334",
    "addr:housenumber":"151",
    "addr:postcode":"28334",
    "addr:street":"Hunter Dr",
    "iso:country":"US",
    "sg:address":"151 Hunter Dr",
    "sg:city":"Dunn",
    "sg:classifiers":[
        {
            "category":"Building & Trades",
            "subcategory":"Landscaping Services",
            "type":"Services"
        }
    ],
    "sg:phone":"+1 910 892 4282",
    "sg:postcode":"28334",
    "sg:province":"NC",
    "sg:tags":[
        "lawn",
        "care"
    ],
    "wof:name":"Pro Lawn",
    "wof:placetype":"venue"
},
  "geometry": {"coordinates":[-78.61490499999999,35.345222],"type":"Point"}
}