{
  "type": "Feature",
  "properties": {
    "addr:full":"100 E Main St Cherryville NC 28021",
    "addr:housenumber":"100",
    "addr:postcode":"28021",
    "addr:street":"E Main St",
    "iso:country":"US",
    "sg:address":"100 E Main St",
    "sg:city":"Cherryville",
    "sg:classifiers":[
        {
            "category":"Shopping",
            "subcategory":"Pharmacy",
            "type":"Retail Goods"
        }
    ],
    "sg:phone":"+1 704 435 6011",
    "sg:postcode":"28021",
    "sg:province":"NC",
    "wof:name":"Houser Drug Co",
    "wof:placetype":"venue"
},
  "geometry": {"coordinates":[-81.37866099999999,35.379221],"type":"Point"}
}