{
  "type": "Feature",
  "properties": {
    "addr:full":"2701 State Hwy 135 Stoneville NC 27048",
    "addr:housenumber":"2701",
    "addr:postcode":"27048",
    "addr:street":"State Hwy 135",
    "iso:country":"US",
    "sg:address":"2701 State Hwy 135",
    "sg:city":"Stoneville",
    "sg:classifiers":[
        {
            "category":"Food & Beverages",
            "subcategory":"Fruits & Vegetables",
            "type":"Retail Goods"
        }
    ],
    "sg:phone":"+1 336 627 5666",
    "sg:postcode":"27048",
    "sg:province":"NC",
    "sg:tags":[
        "produce"
    ],
    "wof:name":"D L Tuttle Berry & Vegetable",
    "wof:placetype":"venue"
},
  "geometry": {"coordinates":[-79.81938700000001,36.464122],"type":"Point"}
}