{
  "type": "Feature",
  "properties": {
    "iso:country":"US",
    "sg:address":"103 Ferndale Dr",
    "sg:city":"Garner",
    "sg:phone":"+1 919 661 1491",
    "sg:postcode":"27529",
    "sg:province":"NC",
    "sg:tags":[
        "communications",
        "telegraph"
    ],
    "wof:name":"Alford Business Service",
    "wof:placetype":"venue"
},
  "geometry": {"coordinates":[-78.55155999999999,35.669309],"type":"Point"}
}