{
  "type": "Feature",
  "properties": {
    "addr:full":"970 Branchview Dr NE Concord NC 28025",
    "addr:housenumber":"970",
    "addr:postcode":"28025",
    "addr:street":"Branchview Dr Ne",
    "iso:country":"US",
    "sg:address":"970 Branchview Dr NE",
    "sg:city":"Concord",
    "sg:classifiers":[
        {
            "category":"Shopping",
            "subcategory":"Clothing, Apparel, & Fashions",
            "type":"Retail Goods"
        }
    ],
    "sg:phone":"+1 704 262 9624",
    "sg:postcode":"28025",
    "sg:province":"NC",
    "sg:tags":[
        "alteration"
    ],
    "wof:name":"Nancy Tailor",
    "wof:placetype":"venue"
},
  "geometry": {"coordinates":[-80.596204,35.4434],"type":"Point"}
}