{
  "type": "Feature",
  "properties": {
    "iso:country":"US",
    "sg:address":"1111 N Main St",
    "sg:city":"Troy",
    "sg:classifiers":[
        {
            "category":"Professional",
            "subcategory":"Business Services",
            "type":"Services"
        }
    ],
    "sg:phone":"+1   ",
    "sg:postcode":"27371",
    "sg:province":"NC",
    "wof:name":"Robinwood Enterprises",
    "wof:placetype":"venue"
},
  "geometry": {"coordinates":[-79.882615,35.381065],"type":"Point"}
}