{
  "type": "Feature",
  "properties": {
    "iso:country":"US",
    "sg:address":"600 S Main St",
    "sg:city":"Landis",
    "sg:classifiers":[
        {
            "category":"Banks & Credit Unions",
            "subcategory":"Bank",
            "type":"Services"
        }
    ],
    "sg:phone":"+1 704 857 6191",
    "sg:postcode":"28088",
    "sg:province":"NC",
    "wof:name":"Sun Trust Bank",
    "wof:placetype":"venue"
},
  "geometry": {"coordinates":[-80.616075,35.542201],"type":"Point"}
}