{
  "type": "Feature",
  "properties": {
    "addr:full":"220 Pine Ridge Rd Mocksville NC 27028",
    "addr:housenumber":"220",
    "addr:postcode":"27028",
    "addr:street":"Pine Ridge Rd",
    "iso:country":"US",
    "sg:address":"220 Pine Ridge Rd",
    "sg:city":"Mocksville",
    "sg:classifiers":[
        {
            "category":"Manufacturing",
            "subcategory":"Lumber",
            "type":"Manufacturing & Wholesale Goods"
        }
    ],
    "sg:phone":"+1 336 284 4940",
    "sg:postcode":"27028",
    "sg:province":"NC",
    "sg:tags":[
        "operation",
        "timber",
        "tract"
    ],
    "wof:name":"Carolina Timber Consultants",
    "wof:placetype":"venue"
},
  "geometry": {"coordinates":[-80.516734,35.802852],"type":"Point"}
}