{
  "type": "Feature",
  "properties": {
    "iso:country":"US",
    "sg:address":"208 Linda Loop",
    "sg:city":"Jacksonville",
    "sg:classifiers":[
        {
            "category":"Building & Trades",
            "subcategory":"Construction",
            "type":"Services"
        }
    ],
    "sg:phone":"+1 910 353 2837",
    "sg:postcode":"28546",
    "sg:province":"NC",
    "sg:tags":[
        "contractor"
    ],
    "wof:name":"Crystal Roofing Inc",
    "wof:placetype":"venue"
},
  "geometry": {"coordinates":[-77.373195,34.752042],"type":"Point"}
}