{
  "type": "Feature",
  "properties": {
    "iso:country":"US",
    "sg:address":"1625 E 12th St",
    "sg:city":"Winston Salem",
    "sg:classifiers":[
        {
            "category":"Organizations",
            "subcategory":"Religious Organization",
            "type":"Services"
        }
    ],
    "sg:phone":"+1   ",
    "sg:postcode":"27101",
    "sg:province":"NC",
    "wof:name":"St Bendcts Moor Cathlic Church",
    "wof:placetype":"venue"
},
  "geometry": {"coordinates":[-80.224074,36.109466],"type":"Point"}
}