{
  "type": "Feature",
  "properties": {
    "addr:full":"5603 Central Ave Charlotte NC 28212",
    "addr:housenumber":"5603",
    "addr:postcode":"28212",
    "addr:street":"Central Ave",
    "iso:country":"US",
    "sg:address":"5603 Central Ave",
    "sg:city":"Charlotte",
    "sg:classifiers":[
        {
            "category":"Shopping",
            "subcategory":"Clothing, Apparel, & Fashions",
            "type":"Retail Goods"
        },
        {
            "category":"Shopping",
            "subcategory":"Bicycles & Sporting Goods",
            "type":"Retail Goods"
        }
    ],
    "sg:phone":"+1 704 537 2587",
    "sg:postcode":"28212",
    "sg:province":"NC",
    "sg:tags":[
        "clothing",
        "store"
    ],
    "wof:name":"Champs Sports",
    "wof:placetype":"venue"
},
  "geometry": {"coordinates":[-80.750978,35.205856],"type":"Point"}
}