{
  "type": "Feature",
  "properties": {
    "addr:full":"116 Eden St NW Concord NC 28027",
    "addr:housenumber":"116",
    "addr:postcode":"28027",
    "addr:street":"Eden St Nw",
    "iso:country":"US",
    "sg:address":"116 Eden St NW",
    "sg:city":"Concord",
    "sg:classifiers":[
        {
            "category":"Wholesale",
            "subcategory":"Machinery & Supplies",
            "type":"Manufacturing & Wholesale Goods"
        }
    ],
    "sg:phone":"+1 704 987 1255",
    "sg:postcode":"28027",
    "sg:province":"NC",
    "sg:tags":[
        "detergent",
        "soap"
    ],
    "wof:name":"No Kidding Goat Milk Soup",
    "wof:placetype":"venue"
},
  "geometry": {"coordinates":[-80.602205,35.39947],"type":"Point"}
}