{
  "type": "Feature",
  "properties": {
    "addr:full":"309 Edgeway Loop Fayetteville NC 28314",
    "addr:housenumber":"309",
    "addr:postcode":"28314",
    "addr:street":"Edgeway Loop",
    "iso:country":"US",
    "sg:address":"309 Edgeway Loop",
    "sg:city":"Fayetteville",
    "sg:classifiers":[
        {
            "category":"Professional",
            "subcategory":"Advertising",
            "type":"Services"
        }
    ],
    "sg:phone":"+1   ",
    "sg:postcode":"28314",
    "sg:province":"NC",
    "sg:tags":[
        "representative"
    ],
    "wof:name":"Big Signal",
    "wof:placetype":"venue"
},
  "geometry": {"coordinates":[-78.990301,35.062709],"type":"Point"}
}