{
  "type": "Feature",
  "properties": {
    "iso:country":"US",
    "sg:address":"3196 Stephenson Rd",
    "sg:city":"Angier",
    "sg:classifiers":[
        {
            "category":"Manufacturing",
            "subcategory":"Retail Goods",
            "type":"Manufacturing & Wholesale Goods"
        }
    ],
    "sg:phone":"+1 919 207 1850",
    "sg:postcode":"27501",
    "sg:province":"NC",
    "sg:tags":[
        "candle",
        "mfg"
    ],
    "wof:name":"RSM of North Carolina Inc",
    "wof:placetype":"venue"
},
  "geometry": {"coordinates":[-78.59335400000001,35.489519],"type":"Point"}
}