{
  "type": "Feature",
  "properties": {
    "addr:full":"712 N Jackson St Raeford NC 28376",
    "addr:housenumber":"712",
    "addr:postcode":"28376",
    "addr:street":"N Jackson St",
    "iso:country":"US",
    "sg:address":"712 N Jackson St",
    "sg:city":"Raeford",
    "sg:classifiers":[
        {
            "category":"Building & Trades",
            "subcategory":"Cleaning & Sanitation",
            "type":"Services"
        }
    ],
    "sg:phone":"+1 910 875 8863",
    "sg:postcode":"28376",
    "sg:province":"NC",
    "sg:tags":[
        "janitorial"
    ],
    "wof:name":"Stanbacks Janitorial Service",
    "wof:placetype":"venue"
},
  "geometry": {"coordinates":[-79.21973699999999,34.987047],"type":"Point"}
}