{
  "type": "Feature",
  "properties": {
    "iso:country":"US",
    "sg:address":"7239 State Hwy 705",
    "sg:city":"Eagle Springs",
    "sg:classifiers":[
        {
            "category":"Farming",
            "subcategory":"Farm",
            "type":"Manufacturing & Wholesale Goods"
        }
    ],
    "sg:phone":"+1 910 948 4985",
    "sg:postcode":"27242",
    "sg:province":"NC",
    "sg:tags":[
        "crop",
        "general"
    ],
    "wof:name":"Stewart Farms Inc",
    "wof:placetype":"venue"
},
  "geometry": {"coordinates":[-79.57779600000001,35.39989],"type":"Point"}
}