{
  "type": "Feature",
  "properties": {
    "addr:full":"438 Eastway Dr Charlotte NC 28205",
    "addr:housenumber":"438",
    "addr:postcode":"28205",
    "addr:street":"Eastway Dr",
    "iso:country":"US",
    "sg:address":"438 Eastway Dr",
    "sg:city":"Charlotte",
    "sg:classifiers":[
        {
            "category":"Personal",
            "subcategory":"Beauty Salon",
            "type":"Services"
        }
    ],
    "sg:phone":"+1   ",
    "sg:postcode":"28205",
    "sg:province":"NC",
    "sg:tags":[
        "shop"
    ],
    "wof:name":"Artistic Hair Design",
    "wof:placetype":"venue"
},
  "geometry": {"coordinates":[-80.780227,35.253485],"type":"Point"}
}