{
  "type": "Feature",
  "properties": {
    "iso:country":"US",
    "sg:address":"1905 State Hwy 109 N",
    "sg:city":"Troy",
    "sg:classifiers":[
        {
            "category":"Retail",
            "subcategory":"Auto Repair",
            "type":"Services"
        }
    ],
    "sg:phone":"+1   ",
    "sg:postcode":"27371",
    "sg:province":"NC",
    "sg:tags":[
        "general"
    ],
    "wof:name":"Eds Auto Racing & Repair Co",
    "wof:placetype":"venue"
},
  "geometry": {"coordinates":[-79.965563,35.38885],"type":"Point"}
}