{
  "type": "Feature",
  "properties": {
    "addr:full":"32 Griffee Rd Fletcher NC 28787",
    "addr:housenumber":"32",
    "addr:postcode":"28787",
    "addr:street":"Griffee Rd",
    "iso:country":"US",
    "sg:address":"32 Griffee Rd",
    "sg:city":"Fletcher",
    "sg:classifiers":[
        {
            "category":"Professional",
            "subcategory":"Business Services",
            "type":"Services"
        }
    ],
    "sg:phone":"+1 828 628 2250",
    "sg:postcode":"28787",
    "sg:province":"NC",
    "sg:tags":[
        "recording",
        "studio"
    ],
    "wof:name":"Sun Spots Productions Inc",
    "wof:placetype":"venue"
},
  "geometry": {"coordinates":[-82.55376200000001,35.725659],"type":"Point"}
}