{
  "type": "Feature",
  "properties": {
    "iso:country":"US",
    "sg:address":"3103 Cullman Ave",
    "sg:city":"Charlotte",
    "sg:classifiers":[
        {
            "category":"Home & Garden",
            "subcategory":"Home Furnishings",
            "type":"Retail Goods"
        }
    ],
    "sg:phone":"+1 704 373 0231",
    "sg:postcode":"28206",
    "sg:province":"NC",
    "sg:tags":[
        "fireplace"
    ],
    "wof:name":"Dane Construction Svc Inc",
    "wof:placetype":"venue"
},
  "geometry": {"coordinates":[-80.809549,35.249569],"type":"Point"}
}