{
  "type": "Feature",
  "properties": {
    "iso:country":"US",
    "sg:address":"129 Furlong Industrial Dr",
    "sg:city":"Kernersville",
    "sg:classifiers":[
        {
            "category":"Wholesale",
            "subcategory":"Scrap",
            "type":"Manufacturing & Wholesale Goods"
        }
    ],
    "sg:phone":"+1 336 993 7258",
    "sg:postcode":"27284",
    "sg:province":"NC",
    "sg:tags":[
        "recycling",
        "center"
    ],
    "wof:name":"OTD Svc",
    "wof:placetype":"venue"
},
  "geometry": {"coordinates":[-80.056426,36.120661],"type":"Point"}
}