{
  "type": "Feature",
  "properties": {
    "addr:full":"1705 N Lumina Ave Wrightsville Beach NC 28480",
    "addr:housenumber":"1705",
    "addr:postcode":"28480",
    "addr:street":"N Lumina Ave",
    "iso:country":"US",
    "sg:address":"1705 N Lumina Ave",
    "sg:city":"Wrightsville Beach",
    "sg:classifiers":[
        {
            "category":"Recreation",
            "type":"Entertainment"
        }
    ],
    "sg:phone":"+1   ",
    "sg:postcode":"28480",
    "sg:province":"NC",
    "wof:name":"Predator Sport Fishing LLC",
    "wof:placetype":"venue"
},
  "geometry": {"coordinates":[-77.78626800000001,34.221146],"type":"Point"}
}