{
  "type": "Feature",
  "properties": {
    "addr:full":"776 N Church St Hendersonville NC 28792",
    "addr:housenumber":"776",
    "addr:postcode":"28792",
    "addr:street":"N Church St",
    "iso:country":"US",
    "sg:address":"776 N Church St",
    "sg:city":"Hendersonville",
    "sg:classifiers":[
        {
            "category":"Insurance",
            "subcategory":"Insurance Agent",
            "type":"Services"
        }
    ],
    "sg:phone":"+1 828 697 0555",
    "sg:postcode":"28792",
    "sg:province":"NC",
    "wof:name":"Allstate Insurance Co",
    "wof:placetype":"venue"
},
  "geometry": {"coordinates":[-82.462174,35.319816],"type":"Point"}
}