{
  "type": "Feature",
  "properties": {
    "addr:full":"116 US Hwy 321 Bus Hickory NC 28602",
    "addr:housenumber":"116",
    "addr:postcode":"28602",
    "addr:street":"Us Hwy 321 Bus",
    "iso:country":"US",
    "sg:address":"116 US Hwy 321 Bus",
    "sg:city":"Hickory",
    "sg:classifiers":[
        {
            "category":"Manufacturing",
            "subcategory":"Printing",
            "type":"Manufacturing & Wholesale Goods"
        }
    ],
    "sg:phone":"+1 828 322 8094",
    "sg:postcode":"28602",
    "sg:province":"NC",
    "sg:tags":[
        "publisher"
    ],
    "wof:name":"Better Publishing",
    "wof:placetype":"venue"
},
  "geometry": {"coordinates":[-81.34066799999999,35.717336],"type":"Point"}
}