{
  "type": "Feature",
  "properties": {
    "iso:country":"US",
    "sg:address":"1213 Culbreth Dr",
    "sg:city":"Wilmington",
    "sg:classifiers":[
        {
            "category":"Health Services",
            "subcategory":"Health Practitioner",
            "type":"Services"
        }
    ],
    "sg:phone":"+1   ",
    "sg:postcode":"28405",
    "sg:province":"NC",
    "wof:name":"Buongiorno Jane Vogt PHD",
    "wof:placetype":"venue"
},
  "geometry": {"coordinates":[-77.828307,34.234097],"type":"Point"}
}