{
  "type": "Feature",
  "properties": {
    "iso:country":"US",
    "sg:address":"1017 N Post Rd",
    "sg:city":"Shelby",
    "sg:classifiers":[
        {
            "category":"Restaurant",
            "type":"Food & Drink"
        }
    ],
    "sg:phone":"+1 704 484 0978",
    "sg:postcode":"28150",
    "sg:province":"NC",
    "sg:tags":[
        "eating"
    ],
    "wof:name":"Cotton's Seafood Restaurant",
    "wof:placetype":"venue"
},
  "geometry": {"coordinates":[-81.491332,35.313076],"type":"Point"}
}