{
  "type": "Feature",
  "properties": {
    "addr:full":"201 W Cornwallis Rd Durham NC 27707",
    "addr:housenumber":"201",
    "addr:postcode":"27707",
    "addr:street":"W Cornwallis Rd",
    "iso:country":"US",
    "sg:address":"201 W Cornwallis Rd",
    "sg:city":"Durham",
    "sg:classifiers":[
        {
            "category":"Health Services",
            "subcategory":"Nursing And Care Facility",
            "type":"Services"
        }
    ],
    "sg:phone":"+1 919 419 4418",
    "sg:postcode":"27707",
    "sg:province":"NC",
    "wof:name":"Corn Hill Home",
    "wof:placetype":"venue"
},
  "geometry": {"coordinates":[-78.923461,35.967807],"type":"Point"}
}