{
  "type": "Feature",
  "properties": {
    "addr:full":"234 Orange Grove St Hillsborough NC 27278",
    "addr:housenumber":"234",
    "addr:postcode":"27278",
    "addr:street":"Orange Grove St",
    "iso:country":"US",
    "sg:address":"234 Orange Grove St",
    "sg:city":"Hillsborough",
    "sg:classifiers":[
        {
            "category":"Social Services",
            "type":"Services"
        }
    ],
    "sg:phone":"+1 919 913 4300",
    "sg:postcode":"27278",
    "sg:province":"NC",
    "sg:tags":[
        "youth",
        "organization",
        "center"
    ],
    "wof:name":"Child & Youth Comm Support",
    "wof:placetype":"venue"
},
  "geometry": {"coordinates":[-79.099765,36.065492],"type":"Point"}
}