{
  "type": "Feature",
  "properties": {
    "addr:full":"1637 Branch Chapel Church Rd Selma NC 27576",
    "addr:housenumber":"1637",
    "addr:postcode":"27576",
    "addr:street":"Branch Chapel Church Rd",
    "iso:country":"US",
    "sg:address":"1637 Branch Chapel Church Rd",
    "sg:city":"Selma",
    "sg:classifiers":[
        {
            "category":"Professional",
            "type":"Services"
        }
    ],
    "sg:phone":"+1   ",
    "sg:postcode":"27576",
    "sg:province":"NC",
    "wof:name":"Badgett Services",
    "wof:placetype":"venue"
},
  "geometry": {"coordinates":[-78.252747,35.634317],"type":"Point"}
}