{
  "type": "Feature",
  "properties": {
    "addr:full":"1200 SE Maynard Rd Cary NC 27511",
    "addr:housenumber":"1200",
    "addr:postcode":"27511",
    "addr:street":"Se Maynard Rd",
    "iso:country":"US",
    "sg:address":"1200 SE Maynard Rd",
    "sg:city":"Cary",
    "sg:classifiers":[
        {
            "category":"Wholesale",
            "subcategory":"Durable Goods & Equipment",
            "type":"Manufacturing & Wholesale Goods"
        }
    ],
    "sg:phone":"+1 919 460 8660",
    "sg:postcode":"27511",
    "sg:province":"NC",
    "sg:tags":[
        "representative",
        "manufacturer"
    ],
    "sg:website":"www.arthur-harris.com",
    "wof:name":"Arthur Harris & Assoc",
    "wof:placetype":"venue"
},
  "geometry": {"coordinates":[-78.76419,35.784998],"type":"Point"}
}