{
  "type": "Feature",
  "properties": {
    "addr:full":"860 E Mountain Dr Fayetteville NC 28306",
    "addr:housenumber":"860",
    "addr:postcode":"28306",
    "addr:street":"E Mountain Dr",
    "iso:country":"US",
    "sg:address":"860 E Mountain Dr",
    "sg:city":"Fayetteville",
    "sg:classifiers":[
        {
            "category":"Professional",
            "subcategory":"Business Services",
            "type":"Services"
        }
    ],
    "sg:phone":"+1   ",
    "sg:postcode":"28306",
    "sg:province":"NC",
    "wof:name":"Daxwoodcom",
    "wof:placetype":"venue"
},
  "geometry": {"coordinates":[-78.87402899999999,35.009594],"type":"Point"}
}