{
  "type": "Feature",
  "properties": {
    "addr:full":"40 N French Broad Ave Asheville NC 28801",
    "addr:housenumber":"40",
    "addr:postcode":"28801",
    "addr:street":"N French Broad Ave",
    "iso:country":"US",
    "sg:address":"40 N French Broad Ave",
    "sg:city":"Asheville",
    "sg:classifiers":[
        {
            "category":"Professional",
            "type":"Services"
        }
    ],
    "sg:phone":"+1 828 251 1400",
    "sg:postcode":"28801",
    "sg:province":"NC",
    "sg:tags":[
        "establishment"
    ],
    "wof:name":"J & B Enterprises",
    "wof:placetype":"venue"
},
  "geometry": {"coordinates":[-82.558756,35.594092],"type":"Point"}
}