{
  "type": "Feature",
  "properties": {
    "addr:full":"206 E Main St Beulaville NC 28518",
    "addr:housenumber":"206",
    "addr:postcode":"28518",
    "addr:street":"E Main St",
    "iso:country":"US",
    "sg:address":"206 E Main St",
    "sg:city":"Beulaville",
    "sg:classifiers":[
        {
            "category":"Autos & Motor Vehicles",
            "subcategory":"Auto Supplies",
            "type":"Retail Goods"
        }
    ],
    "sg:phone":"+1 910 298 2035",
    "sg:postcode":"28518",
    "sg:province":"NC",
    "sg:tags":[
        "automobile",
        "parts"
    ],
    "sg:website":"www.advanceauto.com",
    "wof:name":"Advance Auto Parts Inc",
    "wof:placetype":"venue"
},
  "geometry": {"coordinates":[-77.770039,34.922987],"type":"Point"}
}