{
  "type": "Feature",
  "properties": {
    "iso:country":"US",
    "sg:address":"850 Marshallberg Rd",
    "sg:city":"Marshallberg",
    "sg:classifiers":[
        {
            "category":"Wholesale",
            "subcategory":"Electrical",
            "type":"Manufacturing & Wholesale Goods"
        }
    ],
    "sg:phone":"+1 252 729 9841",
    "sg:postcode":"28553",
    "sg:province":"NC",
    "sg:tags":[
        "recording",
        "instr"
    ],
    "wof:name":"Chadwick Instrument Svc",
    "wof:placetype":"venue"
},
  "geometry": {"coordinates":[-76.517646,34.736429],"type":"Point"}
}