{
  "type": "Feature",
  "properties": {
    "addr:full":"616 W Cornwallis Dr Greensboro NC 27408",
    "addr:housenumber":"616",
    "addr:postcode":"27408",
    "addr:street":"W Cornwallis Dr",
    "iso:country":"US",
    "sg:address":"616 W Cornwallis Dr",
    "sg:city":"Greensboro",
    "sg:classifiers":[
        {
            "category":"Wholesale",
            "subcategory":"Construction Materials",
            "type":"Manufacturing & Wholesale Goods"
        }
    ],
    "sg:phone":"+1 336 275 1194",
    "sg:postcode":"27408",
    "sg:province":"NC",
    "sg:tags":[
        "building",
        "prefabricated"
    ],
    "wof:name":"Modularcorp",
    "wof:placetype":"venue"
},
  "geometry": {"coordinates":[-79.80072,36.102868],"type":"Point"}
}