{
  "type": "Feature",
  "properties": {
    "iso:country":"US",
    "sg:address":"108 Dana Michelle Ct",
    "sg:city":"Belmont",
    "sg:classifiers":[
        {
            "category":"Freight",
            "type":"Transportation"
        }
    ],
    "sg:phone":"+1 704 825 4556",
    "sg:postcode":"28012",
    "sg:province":"NC",
    "wof:name":"American Transportation Syst",
    "wof:placetype":"venue"
},
  "geometry": {"coordinates":[-81.020081,35.172599],"type":"Point"}
}