{
  "type": "Feature",
  "properties": {
    "iso:country":"US",
    "sg:address":"3703 Pembrook Pl",
    "sg:city":"Raleigh",
    "sg:classifiers":[
        {
            "category":"Professional",
            "subcategory":"Management & Consulting",
            "type":"Services"
        }
    ],
    "sg:phone":"+1 919 510 0221",
    "sg:postcode":"27612",
    "sg:province":"NC",
    "sg:tags":[
        "consultant"
    ],
    "wof:name":"Lewis Angela Consultant",
    "wof:placetype":"venue"
},
  "geometry": {"coordinates":[-78.70237899999999,35.847817],"type":"Point"}
}