{
  "type": "Feature",
  "properties": {
    "iso:country":"US",
    "sg:address":"703 E Broad St",
    "sg:city":"Elizabethtown",
    "sg:classifiers":[
        {
            "category":"Restaurant",
            "type":"Food & Drink"
        }
    ],
    "sg:phone":"+1 910 862 2544",
    "sg:postcode":"28337",
    "sg:province":"NC",
    "sg:tags":[
        "eating"
    ],
    "wof:name":"Sunset Grille",
    "wof:placetype":"venue"
},
  "geometry": {"coordinates":[-78.598386,34.626657],"type":"Point"}
}