{
  "type": "Feature",
  "properties": {
    "addr:full":"811 Washington St Plymouth NC 27962",
    "addr:housenumber":"811",
    "addr:postcode":"27962",
    "addr:street":"Washington St",
    "iso:country":"US",
    "sg:address":"811 Washington St",
    "sg:city":"Plymouth",
    "sg:classifiers":[
        {
            "category":"Government",
            "subcategory":"Office",
            "type":"Public Place"
        }
    ],
    "sg:phone":"+1 252 793 2242",
    "sg:postcode":"27962",
    "sg:province":"NC",
    "sg:tags":[
        "state",
        "program"
    ],
    "wof:name":"Drivers License Ofc",
    "wof:placetype":"venue"
},
  "geometry": {"coordinates":[-76.74307899999999,35.854652],"type":"Point"}
}