{
  "type": "Feature",
  "properties": {
    "addr:full":"103 N Oak St Brevard SC 28712",
    "addr:housenumber":"103",
    "addr:postcode":"28712",
    "addr:street":"N Oak St",
    "iso:country":"US",
    "sg:address":"103 N Oak St",
    "sg:city":"Brevard",
    "sg:classifiers":[
        {
            "category":"Personal",
            "type":"Services"
        }
    ],
    "sg:phone":"+1 828 877 6690",
    "sg:postcode":"28712",
    "sg:province":"SC",
    "sg:tags":[
        "therapist",
        "massage"
    ],
    "wof:name":"Carolina Massage Therapy",
    "wof:placetype":"venue"
},
  "geometry": {"coordinates":[-82.720676,35.242047],"type":"Point"}
}