{
  "type": "Feature",
  "properties": {
    "addr:full":"1445 Meadowood Ln Charlotte NC 28211",
    "addr:housenumber":"1445",
    "addr:postcode":"28211",
    "addr:street":"Meadowood Ln",
    "iso:country":"US",
    "sg:address":"1445 Meadowood Ln",
    "sg:city":"Charlotte",
    "sg:classifiers":[
        {
            "category":"Real Estate",
            "subcategory":"Architect",
            "type":"Services"
        }
    ],
    "sg:phone":"+1   ",
    "sg:postcode":"28211",
    "sg:province":"NC",
    "sg:tags":[
        "architectural"
    ],
    "wof:name":"Robert L Rash",
    "wof:placetype":"venue"
},
  "geometry": {"coordinates":[-80.79771599999999,35.161673],"type":"Point"}
}