{
  "type": "Feature",
  "properties": {
    "addr:full":"225 W Nc Highway 54 Durham NC 27713",
    "addr:housenumber":"225",
    "addr:postcode":"27713",
    "addr:street":"W Nc Highway 54",
    "iso:country":"US",
    "sg:address":"225 W Nc Highway 54",
    "sg:city":"Durham",
    "sg:classifiers":[
        {
            "category":"Restaurant",
            "type":"Food & Drink"
        }
    ],
    "sg:phone":"+1 919 484 0505",
    "sg:postcode":"27713",
    "sg:province":"NC",
    "sg:tags":[
        "middle",
        "greek",
        "mediterranean",
        "eastern"
    ],
    "sg:website":"http://babaghannoujnc.com/",
    "wof:name":"Baba Ghannoug Mediterranean Bistro",
    "wof:placetype":"venue"
},
  "geometry": {"coordinates":[-78.941039,35.911236],"type":"Point"}
}