{
  "type": "Feature",
  "properties": {
    "iso:country":"US",
    "sg:address":"801 E Arrowood Rd",
    "sg:city":"Charlotte",
    "sg:classifiers":[
        {
            "category":"Retail",
            "subcategory":"Portrait Studio",
            "type":"Services"
        }
    ],
    "sg:phone":"+1 704 523 9020",
    "sg:postcode":"28217",
    "sg:province":"NC",
    "sg:tags":[
        "photo"
    ],
    "wof:name":"Wal-Mart Prtrait Studio 01464",
    "wof:placetype":"venue"
},
  "geometry": {"coordinates":[-80.878024,35.137691],"type":"Point"}
}