{
  "type": "Feature",
  "properties": {
    "iso:country":"US",
    "sg:address":"495 Watson Br Rd",
    "sg:city":"Cullowhee",
    "sg:classifiers":[
        {
            "category":"Building & Trades",
            "subcategory":"Landscaping Services",
            "type":"Services"
        }
    ],
    "sg:phone":"+1 828 293 3104",
    "sg:postcode":"28723",
    "sg:province":"NC",
    "wof:name":"Smokey Mountain Paving",
    "wof:placetype":"venue"
},
  "geometry": {"coordinates":[-83.14715700000001,35.33749],"type":"Point"}
}