{
  "type": "Feature",
  "properties": {
    "addr:full":"3929 W Dixon Blvd Shelby NC 28152",
    "addr:housenumber":"3929",
    "addr:postcode":"28152",
    "addr:street":"W Dixon Blvd",
    "iso:country":"US",
    "sg:address":"3929 W Dixon Blvd",
    "sg:city":"Shelby",
    "sg:classifiers":[
        {
            "category":"Shopping",
            "subcategory":"Music",
            "type":"Retail Goods"
        }
    ],
    "sg:phone":"+1 704 434 2747",
    "sg:postcode":"28152",
    "sg:province":"NC",
    "sg:tags":[
        "video",
        "disc",
        "tape",
        "cassette"
    ],
    "wof:name":"Video Express",
    "wof:placetype":"venue"
},
  "geometry": {"coordinates":[-81.65328599999999,35.293557],"type":"Point"}
}