{
  "type": "Feature",
  "properties": {
    "iso:country":"US",
    "sg:address":"220 Rudolph Dr",
    "sg:city":"Beaufort",
    "sg:classifiers":[
        {
            "category":"Professional",
            "subcategory":"Advertising",
            "type":"Services"
        }
    ],
    "sg:phone":"+1   ",
    "sg:postcode":"28516",
    "sg:province":"NC",
    "sg:tags":[
        "agency"
    ],
    "wof:name":"NC Contractorscom",
    "wof:placetype":"venue"
},
  "geometry": {"coordinates":[-76.669534,34.7645],"type":"Point"}
}