{
  "type": "Feature",
  "properties": {
    "iso:country":"US",
    "sg:address":"218 Cline Park Dr",
    "sg:city":"Hildebran",
    "sg:classifiers":[
        {
            "category":"Manufacturing",
            "subcategory":"Furniture",
            "type":"Manufacturing & Wholesale Goods"
        },
        {
            "category":"Manufacturing",
            "subcategory":"Retail Goods",
            "type":"Manufacturing & Wholesale Goods"
        }
    ],
    "sg:phone":"+1 828 397 4142",
    "sg:postcode":"28637",
    "sg:province":"NC",
    "sg:tags":[
        "upholstered",
        "manufacturer",
        "accent",
        "mfg"
    ],
    "sg:website":"www.coxmfg.com",
    "wof:name":"Cox Manufacturing Co Inc",
    "wof:placetype":"venue"
},
  "geometry": {"coordinates":[-81.417721,35.7203],"type":"Point"}
}