{
  "type": "Feature",
  "properties": {
    "addr:full":"2309 E Ash St Goldsboro NC 27534",
    "addr:housenumber":"2309",
    "addr:postcode":"27534",
    "addr:street":"E Ash St",
    "iso:country":"US",
    "sg:address":"2309 E Ash St",
    "sg:city":"Goldsboro",
    "sg:classifiers":[
        {
            "category":"Shopping",
            "type":"Retail Goods"
        }
    ],
    "sg:phone":"+1 919 736 7333",
    "sg:postcode":"27534",
    "sg:province":"NC",
    "sg:tags":[
        "miscellaneous",
        "store"
    ],
    "wof:name":"Double Play Sptg Gds Equip LLC",
    "wof:placetype":"venue"
},
  "geometry": {"coordinates":[-77.960232,35.375701],"type":"Point"}
}