{
  "type": "Feature",
  "properties": {
    "iso:country":"US",
    "sg:address":"6834 Market St",
    "sg:city":"Wilmington",
    "sg:classifiers":[
        {
            "category":"Retail",
            "subcategory":"Laundry & Dry Cleaning",
            "type":"Services"
        }
    ],
    "sg:phone":"+1 910 395 4222",
    "sg:postcode":"28405",
    "sg:province":"NC",
    "sg:tags":[
        "drycleaning",
        "plant",
        "cleaners"
    ],
    "wof:name":"Coastal Dry Cleaners",
    "wof:placetype":"venue"
},
  "geometry": {"coordinates":[-77.829919,34.261395],"type":"Point"}
}