{
  "type": "Feature",
  "properties": {
    "addr:full":"301 Salter Path Rd Atlantic Beach NC 28512",
    "addr:housenumber":"301",
    "addr:postcode":"28512",
    "addr:street":"Salter Path Rd",
    "iso:country":"US",
    "sg:address":"301 Salter Path Rd",
    "sg:city":"Atlantic Beach",
    "sg:classifiers":[
        {
            "category":"Organizations",
            "subcategory":"Community Association",
            "type":"Services"
        }
    ],
    "sg:phone":"+1   ",
    "sg:postcode":"28512",
    "sg:province":"NC",
    "wof:name":"Genesis Condos Homeowner Assoc",
    "wof:placetype":"venue"
},
  "geometry": {"coordinates":[-76.821941,34.695252],"type":"Point"}
}