{
  "type": "Feature",
  "properties": {
    "iso:country":"US",
    "sg:address":"3313 Warwick Dr",
    "sg:city":"Jamestown",
    "sg:classifiers":[
        {
            "category":"Shopping",
            "subcategory":"Discount & Variety Stores",
            "type":"Retail Goods"
        }
    ],
    "sg:phone":"+1 336 887 9175",
    "sg:postcode":"27282",
    "sg:province":"NC",
    "sg:tags":[
        "merchandise",
        "general"
    ],
    "wof:name":"John W Monk Retail",
    "wof:placetype":"venue"
},
  "geometry": {"coordinates":[-79.940701,35.976947],"type":"Point"}
}