{
  "type": "Feature",
  "properties": {
    "addr:full":"2115 W Roosevelt Blvd Monroe NC 28110",
    "addr:housenumber":"2115",
    "addr:postcode":"28110",
    "addr:street":"W Roosevelt Blvd",
    "iso:country":"US",
    "sg:address":"2115 W Roosevelt Blvd",
    "sg:city":"Monroe",
    "sg:classifiers":[
        {
            "category":"Personal",
            "type":"Services"
        },
        {
            "category":"Shopping",
            "subcategory":"Jewelry",
            "type":"Retail Goods"
        }
    ],
    "sg:phone":"+1 704 238 1063",
    "sg:postcode":"28110",
    "sg:province":"NC",
    "sg:tags":[
        "ear",
        "piercing"
    ],
    "wof:name":"Piercing Pagoda",
    "wof:placetype":"venue"
},
  "geometry": {"coordinates":[-80.560109,35.007096],"type":"Point"}
}