{
  "type": "Feature",
  "properties": {
    "addr:full":"13860 Ballantyne Corporate Pl Charlotte NC 28277",
    "addr:housenumber":"13860",
    "addr:postcode":"28277",
    "addr:street":"Ballantyne Corporate Pl",
    "iso:country":"US",
    "sg:address":"13860 Ballantyne Corporate Pl",
    "sg:city":"Charlotte",
    "sg:classifiers":[
        {
            "category":"Organizations",
            "subcategory":"Professional Association",
            "type":"Services"
        }
    ],
    "sg:phone":"+1 704 527 0012",
    "sg:postcode":"28277",
    "sg:province":"NC",
    "sg:tags":[
        "business",
        "trade"
    ],
    "wof:name":"Southern Piedmont Consumer Foundation",
    "wof:placetype":"venue"
},
  "geometry": {"coordinates":[-80.85358100000001,35.061491],"type":"Point"}
}