{
  "type": "Feature",
  "properties": {
    "iso:country":"US",
    "sg:address":"215 Proctor Dr",
    "sg:city":"Salisbury",
    "sg:classifiers":[
        {
            "category":"Shopping",
            "subcategory":"Clothing, Apparel, & Fashions",
            "type":"Retail Goods"
        }
    ],
    "sg:phone":"+1 704 633 7367",
    "sg:postcode":"28147",
    "sg:province":"NC",
    "wof:name":"Mary Elizabeth's",
    "wof:placetype":"venue"
},
  "geometry": {"coordinates":[-80.512923,35.709093],"type":"Point"}
}