{
  "type": "Feature",
  "properties": {
    "addr:full":"4707 Carriker Rd Monroe NC 28110",
    "addr:housenumber":"4707",
    "addr:postcode":"28110",
    "addr:street":"Carriker Rd",
    "iso:country":"US",
    "sg:address":"4707 Carriker Rd",
    "sg:city":"Monroe",
    "sg:classifiers":[
        {
            "category":"Manufacturing",
            "subcategory":"Furniture",
            "type":"Manufacturing & Wholesale Goods"
        }
    ],
    "sg:phone":"+1 704 753 1865",
    "sg:postcode":"28110",
    "sg:province":"NC",
    "sg:tags":[
        "institutional",
        "industrial",
        "mfg"
    ],
    "wof:name":"Carriker Industries Inc",
    "wof:placetype":"venue"
},
  "geometry": {"coordinates":[-80.465142,35.123618],"type":"Point"}
}