{
  "type": "Feature",
  "properties": {
    "iso:country":"US",
    "sg:address":"308 E Thom St",
    "sg:city":"China Grove",
    "sg:classifiers":[
        {
            "category":"Manufacturing",
            "subcategory":"Textiles",
            "type":"Manufacturing & Wholesale Goods"
        }
    ],
    "sg:phone":"+1 704 857 2442",
    "sg:postcode":"28023",
    "sg:province":"NC",
    "sg:tags":[
        "spinning",
        "mill",
        "yarn"
    ],
    "wof:name":"China Grove Textiles",
    "wof:placetype":"venue"
},
  "geometry": {"coordinates":[-80.586173,35.560836],"type":"Point"}
}