{
  "type": "Feature",
  "properties": {
    "addr:full":"4389 Sawmills School Rd Granite Falls NC 28630",
    "addr:postcode":"4389;28630",
    "addr:street":"School Rd",
    "iso:country":"US",
    "sg:address":"4389 Sawmills School Rd",
    "sg:city":"Granite Falls",
    "sg:classifiers":[
        {
            "category":"Wholesale",
            "subcategory":"Auto Parts",
            "type":"Manufacturing & Wholesale Goods"
        },
        {
            "category":"Wholesale",
            "subcategory":"Scrap",
            "type":"Manufacturing & Wholesale Goods"
        }
    ],
    "sg:phone":"+1 828 396 7708",
    "sg:postcode":"28630",
    "sg:province":"NC",
    "sg:tags":[
        "automobile",
        "rebuilt"
    ],
    "wof:name":"Nelson's Used Cars & Parts",
    "wof:placetype":"venue"
},
  "geometry": {"coordinates":[-81.47912599999999,35.821575],"type":"Point"}
}