{
  "type": "Feature",
  "properties": {
    "iso:country":"US",
    "sg:address":"620 Washington St",
    "sg:city":"Eden",
    "sg:classifiers":[
        {
            "category":"Professional",
            "subcategory":"Lawyer & Legal Services",
            "type":"Services"
        }
    ],
    "sg:phone":"+1 336 623 8596",
    "sg:postcode":"27288",
    "sg:province":"NC",
    "sg:tags":[
        "attorney"
    ],
    "wof:name":"John H Rush",
    "wof:placetype":"venue"
},
  "geometry": {"coordinates":[-79.76304500000001,36.4909],"type":"Point"}
}