{
  "type": "Feature",
  "properties": {
    "addr:full":"1009 N Fayetteville St Asheboro NC 27203",
    "addr:housenumber":"1009",
    "addr:postcode":"27203",
    "addr:street":"N;St",
    "iso:country":"US",
    "sg:address":"1009 N Fayetteville St",
    "sg:city":"Asheboro",
    "sg:classifiers":[
        {
            "category":"Shopping",
            "subcategory":"Discount & Variety Stores",
            "type":"Retail Goods"
        }
    ],
    "sg:phone":"+1 336 629 9009",
    "sg:postcode":"27203",
    "sg:province":"NC",
    "sg:tags":[
        "merchandise",
        "general"
    ],
    "wof:name":"Express Services",
    "wof:placetype":"venue"
},
  "geometry": {"coordinates":[-79.80991899999999,35.721695],"type":"Point"}
}