{
  "type": "Feature",
  "properties": {
    "addr:full":"149 Logan Ct Angier NC 27501",
    "addr:housenumber":"149",
    "addr:postcode":"27501",
    "addr:street":"Logan Ct",
    "iso:country":"US",
    "sg:address":"149 Logan Ct",
    "sg:city":"Angier",
    "sg:classifiers":[
        {
            "category":"Health Services",
            "subcategory":"Health Practitioner",
            "type":"Services"
        }
    ],
    "sg:phone":"+1 919 331 1189",
    "sg:postcode":"27501",
    "sg:province":"NC",
    "sg:tags":[
        "therapist",
        "physical"
    ],
    "wof:name":"Angier Physical Therapy",
    "wof:placetype":"venue"
},
  "geometry": {"coordinates":[-78.741632,35.525789],"type":"Point"}
}