{
  "type": "Feature",
  "properties": {
    "addr:full":"2608 E 7th St Charlotte NC 28204",
    "addr:housenumber":"2608",
    "addr:postcode":"28204",
    "addr:street":"E 7Th St",
    "iso:country":"US",
    "sg:address":"2608 E 7th St",
    "sg:city":"Charlotte",
    "sg:classifiers":[
        {
            "category":"Health Services",
            "subcategory":"Doctor",
            "type":"Services"
        }
    ],
    "sg:phone":"+1   ",
    "sg:postcode":"28204",
    "sg:province":"NC",
    "sg:tags":[
        "medical"
    ],
    "wof:name":"CMC Myres Pk Ms Neurology Ctr",
    "wof:placetype":"venue"
},
  "geometry": {"coordinates":[-80.811345,35.206775],"type":"Point"}
}