{
  "type": "Feature",
  "properties": {
    "addr:full":"366 W Garrison Blvd Gastonia NC 28052",
    "addr:housenumber":"366",
    "addr:postcode":"28052",
    "addr:street":"W Garrison Blvd",
    "iso:country":"US",
    "sg:address":"366 W Garrison Blvd",
    "sg:city":"Gastonia",
    "sg:classifiers":[
        {
            "category":"Education",
            "subcategory":"School",
            "type":"Public Place"
        }
    ],
    "sg:phone":"+1   ",
    "sg:postcode":"28052",
    "sg:province":"NC",
    "wof:name":"Gaston County Schools",
    "wof:placetype":"venue"
},
  "geometry": {"coordinates":[-81.187951,35.25365],"type":"Point"}
}