{
  "type": "Feature",
  "properties": {
    "iso:country":"US",
    "sg:address":"21226 Crown Lake Dr",
    "sg:city":"Cornelius",
    "sg:classifiers":[
        {
            "category":"Education",
            "subcategory":"Vocational School",
            "type":"Public Place"
        }
    ],
    "sg:phone":"+1   ",
    "sg:postcode":"28031",
    "sg:province":"NC",
    "wof:name":"Lines & Assoc",
    "wof:placetype":"venue"
},
  "geometry": {"coordinates":[-80.87619599999999,35.492299],"type":"Point"}
}