{
  "type": "Feature",
  "properties": {
    "addr:full":"63 McAdenville Rd Belmont NC 28012",
    "addr:housenumber":"63",
    "addr:postcode":"28012",
    "addr:street":"Mcadenville Rd",
    "iso:country":"US",
    "sg:address":"63 McAdenville Rd",
    "sg:city":"Belmont",
    "sg:classifiers":[
        {
            "category":"Wholesale",
            "subcategory":"Machinery & Supplies",
            "type":"Manufacturing & Wholesale Goods"
        }
    ],
    "sg:phone":"+1 704 825 3794",
    "sg:postcode":"28012",
    "sg:province":"NC",
    "sg:tags":[
        "mfg",
        "equipment",
        "industrial",
        "general"
    ],
    "sg:website":"www.andeklube.com",
    "wof:name":"Andek Lubrication Systems",
    "wof:placetype":"venue"
},
  "geometry": {"coordinates":[-81.045676,35.255952],"type":"Point"}
}