{
  "type": "Feature",
  "properties": {
    "addr:full":"9336 Blakeney Heath Rd Charlotte NC 28277",
    "addr:housenumber":"9336",
    "addr:postcode":"28277",
    "addr:street":"Blakeney Heath Rd",
    "iso:country":"US",
    "sg:address":"9336 Blakeney Heath Rd",
    "sg:city":"Charlotte",
    "sg:classifiers":[
        {
            "category":"Health Services",
            "subcategory":"Doctor",
            "type":"Services"
        }
    ],
    "sg:phone":"+1 704 759 1770",
    "sg:postcode":"28277",
    "sg:province":"NC",
    "sg:tags":[
        "physician",
        "surgeon",
        "surgeons",
        "surgery-general"
    ],
    "wof:name":"Mid Carolina Surgery Spec",
    "wof:placetype":"venue"
},
  "geometry": {"coordinates":[-80.81581300000001,35.038902],"type":"Point"}
}