{
  "type": "Feature",
  "properties": {
    "iso:country":"US",
    "sg:address":"2110 Wilson Dairy Rd",
    "sg:city":"Kernersville",
    "sg:classifiers":[
        {
            "category":"Building & Trades",
            "subcategory":"Construction",
            "type":"Services"
        }
    ],
    "sg:phone":"+1 336 399 4553",
    "sg:postcode":"27284",
    "sg:province":"NC",
    "sg:tags":[
        "contractor"
    ],
    "wof:name":"Buena Vista Tile Works",
    "wof:placetype":"venue"
},
  "geometry": {"coordinates":[-80.120251,36.151989],"type":"Point"}
}