{
  "type": "Feature",
  "properties": {
    "addr:full":"303 E Holly Hill Rd Thomasville NC 27360",
    "addr:housenumber":"303",
    "addr:postcode":"27360",
    "addr:street":"E Holly Hill Rd",
    "iso:country":"US",
    "sg:address":"303 E Holly Hill Rd",
    "sg:city":"Thomasville",
    "sg:classifiers":[
        {
            "category":"Retail",
            "subcategory":"Repair Shop",
            "type":"Services"
        }
    ],
    "sg:phone":"+1 336 476 4024",
    "sg:postcode":"27360",
    "sg:province":"NC",
    "sg:tags":[
        "refinishing",
        "furniture"
    ],
    "wof:name":"Illusion Unlimited",
    "wof:placetype":"venue"
},
  "geometry": {"coordinates":[-80.06899,35.872888],"type":"Point"}
}