{
  "type": "Feature",
  "properties": {
    "addr:full":"235 Jones Rd Fletcher NC 28732",
    "addr:housenumber":"235",
    "addr:postcode":"28732",
    "addr:street":"Jones Rd",
    "iso:country":"US",
    "sg:address":"235 Jones Rd",
    "sg:city":"Fletcher",
    "sg:classifiers":[
        {
            "category":"Insurance",
            "subcategory":"Insurance Agent",
            "type":"Services"
        }
    ],
    "sg:phone":"+1 828 684 0899",
    "sg:postcode":"28732",
    "sg:province":"NC",
    "wof:name":"Allstate Insurance Co",
    "wof:placetype":"venue"
},
  "geometry": {"coordinates":[-82.50136500000001,35.441919],"type":"Point"}
}