{
  "type": "Feature",
  "properties": {
    "iso:country":"US",
    "sg:address":"8203 Morrell Ln",
    "sg:city":"Durham",
    "sg:classifiers":[
        {
            "category":"Banks & Credit Unions",
            "subcategory":"Financial Services",
            "type":"Services"
        }
    ],
    "sg:phone":"+1 919 361 1941",
    "sg:postcode":"27713",
    "sg:province":"NC",
    "sg:tags":[
        "investor"
    ],
    "wof:name":"Mystic Investment Group LLC",
    "wof:placetype":"venue"
},
  "geometry": {"coordinates":[-78.95262700000001,35.899103],"type":"Point"}
}