{
  "type": "Feature",
  "properties": {
    "iso:country":"US",
    "sg:address":"105 O'Kelly Ln",
    "sg:city":"Cary",
    "sg:classifiers":[
        {
            "category":"Professional",
            "type":"Services"
        }
    ],
    "sg:phone":"+1 919 481 1102",
    "sg:postcode":"27511",
    "sg:province":"NC",
    "wof:name":"Mark J Costin",
    "wof:placetype":"venue"
},
  "geometry": {"coordinates":[-78.77039000000001,35.787324],"type":"Point"}
}