{
  "type": "Feature",
  "properties": {
    "iso:country":"US",
    "sg:address":"120 Mockingbird Ln",
    "sg:city":"Spring Lake",
    "sg:classifiers":[
        {
            "category":"Manufacturing",
            "subcategory":"Metals",
            "type":"Manufacturing & Wholesale Goods"
        },
        {
            "category":"Manufacturing",
            "subcategory":"Tools & Machinery",
            "type":"Manufacturing & Wholesale Goods"
        }
    ],
    "sg:phone":"+1 910 497 3172",
    "sg:postcode":"28390",
    "sg:province":"NC",
    "sg:tags":[
        "machine",
        "shop",
        "fabricating"
    ],
    "wof:name":"Custom Machine & Tooling",
    "wof:placetype":"venue"
},
  "geometry": {"coordinates":[-78.927834,35.253385],"type":"Point"}
}