{
  "type": "Feature",
  "properties": {
    "iso:country":"US",
    "sg:address":"1403 River Rd",
    "sg:city":"Elizabeth City",
    "sg:classifiers":[
        {
            "category":"Building & Trades",
            "subcategory":"Construction",
            "type":"Services"
        }
    ],
    "sg:phone":"+1 252 333 3274",
    "sg:postcode":"27909",
    "sg:province":"NC",
    "sg:tags":[
        "dry wall",
        "contractor"
    ],
    "wof:name":"Lynch Dry Wall",
    "wof:placetype":"venue"
},
  "geometry": {"coordinates":[-76.19897400000001,36.265585],"type":"Point"}
}