{
  "type": "Feature",
  "properties": {
    "addr:full":"103 Salter Path Rd Pine Knoll Shrs NC 28512",
    "addr:housenumber":"103",
    "addr:postcode":"28512",
    "addr:street":"Salter Path Rd",
    "iso:country":"US",
    "sg:address":"103 Salter Path Rd",
    "sg:city":"Pine Knoll Shrs",
    "sg:classifiers":[
        {
            "category":"Travel",
            "subcategory":"Hotels & Motels",
            "type":"Entertainment"
        }
    ],
    "sg:phone":"+1 252 247 7123",
    "sg:postcode":"28512",
    "sg:province":"NC",
    "sg:website":"www.windjammerinn.com",
    "wof:name":"Windjammer Inn",
    "wof:placetype":"venue"
},
  "geometry": {"coordinates":[-76.88372699999999,34.688704],"type":"Point"}
}