{
  "type": "Feature",
  "properties": {
    "addr:full":"349 Goodman Rd Concord NC 28027",
    "addr:housenumber":"349",
    "addr:postcode":"28027",
    "addr:street":"Goodman Rd",
    "iso:country":"US",
    "sg:address":"349 Goodman Rd",
    "sg:city":"Concord",
    "sg:classifiers":[
        {
            "category":"Retail",
            "subcategory":"Laundry & Dry Cleaning",
            "type":"Services"
        }
    ],
    "sg:phone":"+1 704 788 4843",
    "sg:postcode":"28027",
    "sg:province":"NC",
    "sg:tags":[
        "cleaners",
        "rug",
        "carpet"
    ],
    "wof:name":"Star Cleaning Inc",
    "wof:placetype":"venue"
},
  "geometry": {"coordinates":[-80.696905,35.409091],"type":"Point"}
}