{
  "type": "Feature",
  "properties": {
    "iso:country":"US",
    "sg:address":"10 W Rolling Acres Dr",
    "sg:city":"Weaverville",
    "sg:classifiers":[
        {
            "category":"Retail",
            "subcategory":"Repair Shop",
            "type":"Services"
        }
    ],
    "sg:phone":"+1   ",
    "sg:postcode":"28787",
    "sg:province":"NC",
    "wof:name":"B&E Assoc",
    "wof:placetype":"venue"
},
  "geometry": {"coordinates":[-82.586611,35.703994],"type":"Point"}
}