{
  "type": "Feature",
  "properties": {
    "addr:full":"304 Washington St Williamston NC 27892",
    "addr:housenumber":"304",
    "addr:postcode":"27892",
    "addr:street":"Washington St",
    "iso:country":"US",
    "sg:address":"304 Washington St",
    "sg:city":"Williamston",
    "sg:classifiers":[
        {
            "category":"Banks & Credit Unions",
            "subcategory":"Bank",
            "type":"Services"
        }
    ],
    "sg:phone":"+1 252 792 8408",
    "sg:postcode":"27892",
    "sg:province":"NC",
    "sg:tags":[
        "cashing",
        "check"
    ],
    "wof:name":"Friendly Check Cashing",
    "wof:placetype":"venue"
},
  "geometry": {"coordinates":[-77.056324,35.850199],"type":"Point"}
}