{
  "type": "Feature",
  "properties": {
    "addr:full":"2612 Craig Ave Concord NC 28027",
    "addr:housenumber":"2612",
    "addr:postcode":"28027",
    "addr:street":"Craig Ave",
    "iso:country":"US",
    "sg:address":"2612 Craig Ave",
    "sg:city":"Concord",
    "sg:classifiers":[
        {
            "category":"Retail",
            "subcategory":"Auto Repair",
            "type":"Services"
        }
    ],
    "sg:phone":"+1   ",
    "sg:postcode":"28027",
    "sg:province":"NC",
    "sg:tags":[
        "general"
    ],
    "wof:name":"Steves Automotive Inc",
    "wof:placetype":"venue"
},
  "geometry": {"coordinates":[-80.63681099999999,35.448919],"type":"Point"}
}