{
  "type": "Feature",
  "properties": {
    "iso:country":"US",
    "sg:address":"2220 Farmington Dr",
    "sg:city":"Chapel Hill",
    "sg:classifiers":[
        {
            "category":"Health Services",
            "subcategory":"Nursing And Care Facility",
            "type":"Services"
        }
    ],
    "sg:phone":"+1 919 933 1430",
    "sg:postcode":"27517",
    "sg:province":"NC",
    "wof:name":"Wynwood of Chapel Hill",
    "wof:placetype":"venue"
},
  "geometry": {"coordinates":[-78.984988,35.908386],"type":"Point"}
}