{
  "type": "Feature",
  "properties": {
    "iso:country":"US",
    "sg:address":"4692 Flay Rd",
    "sg:city":"Lincolnton",
    "sg:classifiers":[
        {
            "category":"Manufacturing",
            "subcategory":"Textiles",
            "type":"Manufacturing & Wholesale Goods"
        }
    ],
    "sg:phone":"+1 704 735 5719",
    "sg:postcode":"28092",
    "sg:province":"NC",
    "sg:tags":[
        "hosiery",
        "mfg"
    ],
    "wof:name":"R & C Hosiery Inc",
    "wof:placetype":"venue"
},
  "geometry": {"coordinates":[-81.374509,35.473572],"type":"Point"}
}