{
  "type": "Feature",
  "properties": {
    "iso:country":"US",
    "sg:address":"201 Merriwood Dr",
    "sg:city":"Cary",
    "sg:classifiers":[
        {
            "category":"Taxi",
            "type":"Transportation"
        }
    ],
    "sg:phone":"+1 919 271 1161",
    "sg:postcode":"27511",
    "sg:province":"NC",
    "sg:tags":[
        "taxicab"
    ],
    "wof:name":"Alpha Taxi Co",
    "wof:placetype":"venue"
},
  "geometry": {"coordinates":[-78.76204,35.782489],"type":"Point"}
}