{
  "type": "Feature",
  "properties": {
    "iso:country":"US",
    "sg:address":"312 Greenville Blvd SW",
    "sg:city":"Greenville",
    "sg:classifiers":[
        {
            "category":"Wholesale",
            "subcategory":"Motor Vehicles",
            "type":"Manufacturing & Wholesale Goods"
        }
    ],
    "sg:phone":"+1 252 355 9196",
    "sg:postcode":"27834",
    "sg:province":"NC",
    "wof:name":"Goodman Auto Brokers",
    "wof:placetype":"venue"
},
  "geometry": {"coordinates":[-77.390542,35.574508],"type":"Point"}
}