{
  "type": "Feature",
  "properties": {
    "addr:full":"1821 Umstead St Charlotte NC 28205",
    "addr:housenumber":"1821",
    "addr:postcode":"28205",
    "addr:street":"Umstead St",
    "iso:country":"US",
    "sg:address":"1821 Umstead St",
    "sg:city":"Charlotte",
    "sg:classifiers":[
        {
            "category":"Building & Trades",
            "subcategory":"Cleaning & Sanitation",
            "type":"Services"
        }
    ],
    "sg:phone":"+1 704 347 4209",
    "sg:postcode":"28205",
    "sg:province":"NC",
    "sg:tags":[
        "janitor",
        "maintenance"
    ],
    "wof:name":"Alice F Williams Cleaning Svcs",
    "wof:placetype":"venue"
},
  "geometry": {"coordinates":[-80.81253700000001,35.234321],"type":"Point"}
}