{
  "type": "Feature",
  "properties": {
    "iso:country":"US",
    "sg:address":"412 State St",
    "sg:city":"Greensboro",
    "sg:classifiers":[
        {
            "category":"Restaurant",
            "type":"Food & Drink"
        }
    ],
    "sg:phone":"+1 336 691 9820",
    "sg:postcode":"27405",
    "sg:province":"NC",
    "wof:name":"Secret Tearoom",
    "wof:placetype":"venue"
},
  "geometry": {"coordinates":[-79.78424200000001,36.101054],"type":"Point"}
}