{
  "type": "Feature",
  "properties": {
    "addr:full":"2021 Arapaho Dr Charlotte NC 28214",
    "addr:housenumber":"2021",
    "addr:postcode":"28214",
    "addr:street":"Arapaho Dr",
    "iso:country":"US",
    "sg:address":"2021 Arapaho Dr",
    "sg:city":"Charlotte",
    "sg:classifiers":[
        {
            "category":"Manufacturing",
            "subcategory":"Metals",
            "type":"Manufacturing & Wholesale Goods"
        }
    ],
    "sg:phone":"+1 704 398 7022",
    "sg:postcode":"28214",
    "sg:province":"NC",
    "sg:tags":[
        "tool",
        "manufacturers'",
        "representative",
        "agent",
        "mfg"
    ],
    "wof:name":"Billmire Co Inc",
    "wof:placetype":"venue"
},
  "geometry": {"coordinates":[-80.936638,35.251731],"type":"Point"}
}