{
  "type": "Feature",
  "properties": {
    "addr:full":"524 S Elm St Greensboro NC 27406",
    "addr:housenumber":"524",
    "addr:postcode":"27406",
    "addr:street":"S Elm St",
    "iso:country":"US",
    "sg:address":"524 S Elm St",
    "sg:city":"Greensboro",
    "sg:classifiers":[
        {
            "category":"Professional",
            "subcategory":"Business Services",
            "type":"Services"
        }
    ],
    "sg:phone":"+1   ",
    "sg:postcode":"27406",
    "sg:province":"NC",
    "sg:tags":[
        "interior",
        "design"
    ],
    "wof:name":"Metamorphosis",
    "wof:placetype":"venue"
},
  "geometry": {"coordinates":[-79.79083900000001,36.066251],"type":"Point"}
}