{
  "type": "Feature",
  "properties": {
    "iso:country":"US",
    "sg:address":"101 S Edgeworth St",
    "sg:city":"Greensboro",
    "sg:classifiers":[
        {
            "category":"Government",
            "subcategory":"Office",
            "type":"Public Place"
        }
    ],
    "sg:phone":"+1 336 333 5080",
    "sg:postcode":"27401",
    "sg:province":"NC",
    "wof:name":"Honorable William L Stocks",
    "wof:placetype":"venue"
},
  "geometry": {"coordinates":[-79.79620199999999,36.071881],"type":"Point"}
}