{
  "type": "Feature",
  "properties": {
    "addr:full":"543 Mount Zion Church Rd Thomasville NC 27360",
    "addr:housenumber":"543",
    "addr:postcode":"27360",
    "addr:street":"Mount Zion Church Rd",
    "iso:country":"US",
    "sg:address":"543 Mount Zion Church Rd",
    "sg:city":"Thomasville",
    "sg:classifiers":[
        {
            "category":"Retail",
            "subcategory":"Auto Repair",
            "type":"Services"
        }
    ],
    "sg:phone":"+1   ",
    "sg:postcode":"27360",
    "sg:province":"NC",
    "sg:tags":[
        "general"
    ],
    "wof:name":"Wright Repair",
    "wof:placetype":"venue"
},
  "geometry": {"coordinates":[-80.11344,35.798124],"type":"Point"}
}