{
  "type": "Feature",
  "properties": {
    "addr:full":"2521 Nelda Dr Monroe NC 28110",
    "addr:housenumber":"2521",
    "addr:postcode":"28110",
    "addr:street":"Nelda Dr",
    "iso:country":"US",
    "sg:address":"2521 Nelda Dr",
    "sg:city":"Monroe",
    "sg:classifiers":[
        {
            "category":"Freight",
            "type":"Transportation"
        }
    ],
    "sg:phone":"+1 704 289 6678",
    "sg:postcode":"28110",
    "sg:province":"NC",
    "sg:tags":[
        "hauling",
        "trucking"
    ],
    "sg:website":"www.bluemaxtrucking.com",
    "wof:name":"Blue Max Trucking",
    "wof:placetype":"venue"
},
  "geometry": {"coordinates":[-80.575441,35.013463],"type":"Point"}
}