{
  "type": "Feature",
  "properties": {
    "iso:country":"US",
    "sg:address":"2980 E Franklin Blvd",
    "sg:city":"Gastonia",
    "sg:classifiers":[
        {
            "category":"Utilities",
            "subcategory":"Electric",
            "type":"Services"
        }
    ],
    "sg:phone":"+1 704 864 7711",
    "sg:postcode":"28056",
    "sg:province":"NC",
    "sg:tags":[
        "company"
    ],
    "wof:name":"Duke Energy",
    "wof:placetype":"venue"
},
  "geometry": {"coordinates":[-81.12513,35.259167],"type":"Point"}
}