{
  "type": "Feature",
  "properties": {
    "addr:full":"8008 Corporate Center Dr Ste 207 Charlotte NC 28226",
    "addr:housenumber":"8008",
    "addr:postcode":"28226",
    "addr:street":"Corporate Center Dr Ste 207",
    "iso:country":"US",
    "sg:address":"8008 Corporate Center Dr Ste 207",
    "sg:city":"Charlotte",
    "sg:classifiers":[
        {
            "category":"Professional",
            "subcategory":"Engineering",
            "type":"Services"
        },
        {
            "category":"Communications",
            "type":"Services"
        },
        {
            "category":"Professional",
            "subcategory":"Computer Services",
            "type":"Services"
        }
    ],
    "sg:phone":"+1 704 752 4223",
    "sg:postcode":"28226",
    "sg:province":"NC",
    "sg:tags":[
        "engineer",
        "consultant",
        "designer",
        "system",
        "integration"
    ],
    "wof:name":"Office Media Network",
    "wof:placetype":"venue"
},
  "geometry": {"coordinates":[-80.853607,35.086453],"type":"Point"}
}