{
  "type": "Feature",
  "properties": {
    "addr:full":"4227 US Hwy 321 Granite Falls NC 28630",
    "addr:housenumber":"4227",
    "addr:postcode":"28630",
    "addr:street":"Us Hwy 321",
    "iso:country":"US",
    "sg:address":"4227 US Hwy 321",
    "sg:city":"Granite Falls",
    "sg:classifiers":[
        {
            "category":"Manufacturing",
            "subcategory":"Building Materials",
            "type":"Manufacturing & Wholesale Goods"
        }
    ],
    "sg:phone":"+1 828 313 5105",
    "sg:postcode":"28630",
    "sg:province":"NC",
    "sg:tags":[
        "plywood",
        "veneer"
    ],
    "wof:name":"Granite Hardwoods Inc",
    "wof:placetype":"venue"
},
  "geometry": {"coordinates":[-81.428754,35.806567],"type":"Point"}
}