{
  "type": "Feature",
  "properties": {
    "addr:full":"5212 US Hwy 74 Monroe NC 28110",
    "addr:housenumber":"5212",
    "addr:postcode":"28110",
    "addr:street":"Us Hwy 74",
    "iso:country":"US",
    "sg:address":"5212 US Hwy 74",
    "sg:city":"Monroe",
    "sg:classifiers":[
        {
            "category":"Restaurant",
            "type":"Food & Drink"
        }
    ],
    "sg:phone":"+1 704 289 4502",
    "sg:postcode":"28110",
    "sg:province":"NC",
    "wof:name":"J M's Family Fish House",
    "wof:placetype":"venue"
},
  "geometry": {"coordinates":[-80.628535,35.057601],"type":"Point"}
}