{
  "type": "Feature",
  "properties": {
    "iso:country":"US",
    "sg:address":"316 Grants Way",
    "sg:city":"Four Oaks",
    "sg:classifiers":[
        {
            "category":"Professional",
            "type":"Services"
        }
    ],
    "sg:phone":"+1 919 938 2177",
    "sg:postcode":"27524",
    "sg:province":"NC",
    "wof:name":"David Weeks",
    "wof:placetype":"venue"
},
  "geometry": {"coordinates":[-78.512232,35.509876],"type":"Point"}
}