{
  "type": "Feature",
  "properties": {
    "iso:country":"US",
    "sg:address":"1737 Shoreham Dr",
    "sg:city":"Charlotte",
    "sg:classifiers":[
        {
            "category":"Banks & Credit Unions",
            "subcategory":"Financial Services",
            "type":"Services"
        }
    ],
    "sg:phone":"+1 704 366 1660",
    "sg:postcode":"28211",
    "sg:province":"NC",
    "sg:tags":[
        "investor"
    ],
    "wof:name":"Newman Investments LLC",
    "wof:placetype":"venue"
},
  "geometry": {"coordinates":[-80.81321,35.174274],"type":"Point"}
}