{
  "type": "Feature",
  "properties": {
    "iso:country":"US",
    "sg:address":"107 E 2nd St",
    "sg:city":"Greenville",
    "sg:classifiers":[
        {
            "category":"Professional",
            "subcategory":"Engineering",
            "type":"Services"
        }
    ],
    "sg:phone":"+1 252 752 4135",
    "sg:postcode":"27858",
    "sg:province":"NC",
    "sg:tags":[
        "engineer"
    ],
    "sg:website":"www.riversandassociates.com",
    "wof:name":"Rivers & Assoc Inc",
    "wof:placetype":"venue"
},
  "geometry": {"coordinates":[-77.37217099999999,35.614307],"type":"Point"}
}