{
  "type": "Feature",
  "properties": {
    "addr:full":"6777 Market St Wilmington NC 28405",
    "addr:housenumber":"6777",
    "addr:postcode":"28405",
    "addr:street":"Market St",
    "iso:country":"US",
    "sg:address":"6777 Market St",
    "sg:city":"Wilmington",
    "sg:classifiers":[
        {
            "category":"Retail",
            "subcategory":"Car Wash",
            "type":"Services"
        }
    ],
    "sg:phone":"+1 910 799 0017",
    "sg:postcode":"28405",
    "sg:province":"NC",
    "sg:tags":[
        "carwash"
    ],
    "wof:name":"Mister Sdzy Fll Srvc Car Wsh/D",
    "wof:placetype":"venue"
},
  "geometry": {"coordinates":[-77.836866,34.258236],"type":"Point"}
}