{
  "type": "Feature",
  "properties": {
    "iso:country":"US",
    "sg:address":"7360 W Friendly Ave",
    "sg:city":"Greensboro",
    "sg:classifiers":[
        {
            "category":"Health Services",
            "subcategory":"Doctor",
            "type":"Services"
        }
    ],
    "sg:phone":"+1 336 218 8813",
    "sg:postcode":"27410",
    "sg:province":"NC",
    "sg:tags":[
        "physician",
        "surgeon"
    ],
    "wof:name":"Us Healthworks-N Carolina",
    "wof:placetype":"venue"
},
  "geometry": {"coordinates":[-79.922241,36.088599],"type":"Point"}
}