{
  "type": "Feature",
  "properties": {
    "iso:country":"US",
    "sg:address":"104 N Shores Rd",
    "sg:city":"Washington",
    "sg:classifiers":[
        {
            "category":"Building & Trades",
            "subcategory":"Construction",
            "type":"Services"
        }
    ],
    "sg:phone":"+1 252 946 6519",
    "sg:postcode":"27889",
    "sg:province":"NC",
    "sg:tags":[
        "roofing",
        "contractor"
    ],
    "wof:name":"Kennedy Roofing Co",
    "wof:placetype":"venue"
},
  "geometry": {"coordinates":[-77.02083399999999,35.53232],"type":"Point"}
}