{
  "type": "Feature",
  "properties": {
    "addr:full":"606 E Fearing St Elizabeth City NC 27909",
    "addr:housenumber":"606",
    "addr:postcode":"27909",
    "addr:street":"E Fearing St",
    "iso:country":"US",
    "sg:address":"606 E Fearing St",
    "sg:city":"Elizabeth City",
    "sg:classifiers":[
        {
            "category":"Shopping",
            "subcategory":"Clothing, Apparel, & Fashions",
            "type":"Retail Goods"
        }
    ],
    "sg:phone":"+1 252 338 5643",
    "sg:postcode":"27909",
    "sg:province":"NC",
    "wof:name":"Alphonso Tailor",
    "wof:placetype":"venue"
},
  "geometry": {"coordinates":[-76.21972700000001,36.299118],"type":"Point"}
}