{
  "type": "Feature",
  "properties": {
    "iso:country":"US",
    "sg:address":"3803 Dortches Blvd",
    "sg:city":"Rocky Mount",
    "sg:classifiers":[
        {
            "category":"Shopping",
            "type":"Retail Goods"
        }
    ],
    "sg:phone":"+1 252 443 5795",
    "sg:postcode":"27804",
    "sg:province":"NC",
    "sg:tags":[
        "spa",
        "pool",
        "equipment"
    ],
    "wof:name":"Carolina Splash Inc",
    "wof:placetype":"venue"
},
  "geometry": {"coordinates":[-77.85716499999999,36.011476],"type":"Point"}
}