{
  "type": "Feature",
  "properties": {
    "addr:full":"131 Corncake Cir Morehead City NC 28557",
    "addr:housenumber":"131",
    "addr:postcode":"28557",
    "addr:street":"Corncake Cir",
    "iso:country":"US",
    "sg:address":"131 Corncake Cir",
    "sg:city":"Morehead City",
    "sg:classifiers":[
        {
            "category":"Professional",
            "subcategory":"Business Services",
            "type":"Services"
        }
    ],
    "sg:phone":"+1   ",
    "sg:postcode":"28557",
    "sg:province":"NC",
    "wof:name":"Mbm Associates Inc",
    "wof:placetype":"venue"
},
  "geometry": {"coordinates":[-76.83359,34.728639],"type":"Point"}
}