{
  "type": "Feature",
  "properties": {
    "addr:full":"20723 Torrence Chapel Rd Cornelius NC 28031",
    "addr:postcode":"20723;28031",
    "addr:street":"Torrence Chapel Rd",
    "iso:country":"US",
    "sg:address":"20723 Torrence Chapel Rd",
    "sg:city":"Cornelius",
    "sg:classifiers":[
        {
            "category":"Real Estate",
            "subcategory":"Real Estate Agent",
            "type":"Services"
        }
    ],
    "sg:phone":"+1 704 895 5676",
    "sg:postcode":"28031",
    "sg:province":"NC",
    "sg:website":"www.mainsalerealty.com",
    "wof:name":"Main Sale Realty",
    "wof:placetype":"venue"
},
  "geometry": {"coordinates":[-80.87754700000001,35.484933],"type":"Point"}
}