{
  "type": "Feature",
  "properties": {
    "iso:country":"US",
    "sg:address":"3744 State Hwy 903 N",
    "sg:city":"Stokes",
    "sg:classifiers":[
        {
            "category":"Retail",
            "subcategory":"Repair Shop",
            "type":"Services"
        }
    ],
    "sg:phone":"+1 252 758 7888",
    "sg:postcode":"27884",
    "sg:province":"NC",
    "sg:tags":[
        "plumbing",
        "drain",
        "cleaning",
        "sewer"
    ],
    "wof:name":"Plumb KWIK",
    "wof:placetype":"venue"
},
  "geometry": {"coordinates":[-77.23870599999999,35.730138],"type":"Point"}
}