{
  "type": "Feature",
  "properties": {
    "addr:full":"1916 W Park Dr North Wilkesboro NC 28659",
    "addr:housenumber":"1916",
    "addr:postcode":"28659",
    "addr:street":"W Park Dr",
    "iso:country":"US",
    "sg:address":"1916 W Park Dr",
    "sg:city":"North Wilkesboro",
    "sg:classifiers":[
        {
            "category":"Health Services",
            "subcategory":"Doctor",
            "type":"Services"
        }
    ],
    "sg:phone":"+1 336 903 2900",
    "sg:postcode":"28659",
    "sg:province":"NC",
    "sg:tags":[
        "physician",
        "surgeon"
    ],
    "wof:name":"Aegis Family Health Ctr",
    "wof:placetype":"venue"
},
  "geometry": {"coordinates":[-81.164925,36.155286],"type":"Point"}
}