{
  "type": "Feature",
  "properties": {
    "iso:country":"US",
    "sg:address":"3177 Kennedy Rd",
    "sg:city":"Thomasville",
    "sg:classifiers":[
        {
            "category":"Freight",
            "type":"Transportation"
        },
        {
            "category":"Building & Trades",
            "subcategory":"Construction",
            "type":"Services"
        }
    ],
    "sg:phone":"+1 336 472 5317",
    "sg:postcode":"27360",
    "sg:province":"NC",
    "sg:tags":[
        "excavation",
        "operator",
        "contractor",
        "local",
        "trucking"
    ],
    "wof:name":"Mark R Coman Trucking",
    "wof:placetype":"venue"
},
  "geometry": {"coordinates":[-80.077095,35.814087],"type":"Point"}
}