{
  "type": "Feature",
  "properties": {
    "iso:country":"US",
    "sg:address":"5201 Moss Cove Ct",
    "sg:city":"Monroe",
    "sg:classifiers":[
        {
            "category":"Real Estate",
            "subcategory":"Real Estate Agent",
            "type":"Services"
        }
    ],
    "sg:phone":"+1 704 289 8576",
    "sg:postcode":"28110",
    "sg:province":"NC",
    "wof:name":"Grainger Co",
    "wof:placetype":"venue"
},
  "geometry": {"coordinates":[-80.65063499999999,35.035426],"type":"Point"}
}