{
  "type": "Feature",
  "properties": {
    "addr:full":"2001 Vail Ave Charlotte NC 28207",
    "addr:housenumber":"2001",
    "addr:postcode":"28207",
    "addr:street":"Vail Ave",
    "iso:country":"US",
    "sg:address":"2001 Vail Ave",
    "sg:city":"Charlotte",
    "sg:classifiers":[
        {
            "category":"Health Services",
            "subcategory":"Doctor",
            "type":"Services"
        }
    ],
    "sg:phone":"+1 704 333 0741",
    "sg:postcode":"28207",
    "sg:province":"NC",
    "sg:tags":[
        "physician",
        "surgery",
        "surgeons",
        "surgery-general",
        "vascular"
    ],
    "wof:name":"Vein Care Center",
    "wof:placetype":"venue"
},
  "geometry": {"coordinates":[-80.82186900000001,35.209831],"type":"Point"}
}