{
  "type": "Feature",
  "properties": {
    "iso:country":"US",
    "sg:address":"4716 S Plank Rd",
    "sg:city":"Sanford",
    "sg:classifiers":[
        {
            "category":"Retail",
            "subcategory":"Repair Shop",
            "type":"Services"
        }
    ],
    "sg:phone":"+1   ",
    "sg:postcode":"27330",
    "sg:province":"NC",
    "wof:name":"Plank Road Taxidermy",
    "wof:placetype":"venue"
},
  "geometry": {"coordinates":[-79.28469699999999,35.388076],"type":"Point"}
}