{
  "type": "Feature",
  "properties": {
    "addr:full":"2705 N Center St Hickory NC 28601",
    "addr:housenumber":"2705",
    "addr:postcode":"28601",
    "addr:street":"N Center St",
    "iso:country":"US",
    "sg:address":"2705 N Center St",
    "sg:city":"Hickory",
    "sg:classifiers":[
        {
            "category":"Personal",
            "type":"Services"
        }
    ],
    "sg:phone":"+1 828 327 9430",
    "sg:postcode":"28601",
    "sg:province":"NC",
    "sg:tags":[
        "therapist",
        "massage"
    ],
    "wof:name":"Preventative Health Svc",
    "wof:placetype":"venue"
},
  "geometry": {"coordinates":[-81.331732,35.767297],"type":"Point"}
}