{
  "type": "Feature",
  "properties": {
    "iso:country":"US",
    "sg:address":"314 Goodrum St",
    "sg:city":"Davidson",
    "sg:classifiers":[
        {
            "category":"Professional",
            "subcategory":"Management & Consulting",
            "type":"Services"
        }
    ],
    "sg:phone":"+1 704 895 0818",
    "sg:postcode":"28036",
    "sg:province":"NC",
    "sg:tags":[
        "pool",
        "swimming"
    ],
    "wof:name":"P H POOL Management LLC",
    "wof:placetype":"venue"
},
  "geometry": {"coordinates":[-80.851128,35.496013],"type":"Point"}
}