{
  "type": "Feature",
  "properties": {
    "iso:country":"US",
    "sg:address":"300 Beulah Church Rd",
    "sg:city":"Turkey",
    "sg:classifiers":[
        {
            "category":"Organizations",
            "subcategory":"Religious Organization",
            "type":"Services"
        }
    ],
    "sg:phone":"+1   ",
    "sg:postcode":"28393",
    "sg:province":"NC",
    "wof:name":"Greater Six Runs Misn Bapt CHR",
    "wof:placetype":"venue"
},
  "geometry": {"coordinates":[-78.210234,35.033424],"type":"Point"}
}