{
  "type": "Feature",
  "properties": {
    "addr:full":"4934 Providence Rd Charlotte NC 28226",
    "addr:housenumber":"4934",
    "addr:postcode":"28226",
    "addr:street":"Providence Rd",
    "iso:country":"US",
    "sg:address":"4934 Providence Rd",
    "sg:city":"Charlotte",
    "sg:classifiers":[
        {
            "category":"Social Services",
            "subcategory":"Adult Care",
            "type":"Services"
        }
    ],
    "sg:phone":"+1 704 442 0941",
    "sg:postcode":"28226",
    "sg:province":"NC",
    "sg:tags":[
        "home"
    ],
    "wof:name":"Grant Adult Home",
    "wof:placetype":"venue"
},
  "geometry": {"coordinates":[-80.791054,35.148229],"type":"Point"}
}