{
  "type": "Feature",
  "properties": {
    "iso:country":"US",
    "sg:address":"1002 Dobbins Mill Rd",
    "sg:city":"Elkin",
    "sg:classifiers":[
        {
            "category":"Building & Trades",
            "subcategory":"Plumbing",
            "type":"Services"
        }
    ],
    "sg:phone":"+1 336 366 4126",
    "sg:postcode":"28621",
    "sg:province":"NC",
    "sg:tags":[
        "conditioning",
        "air",
        "system",
        "contractor"
    ],
    "wof:name":"Stanley Heating & Air",
    "wof:placetype":"venue"
},
  "geometry": {"coordinates":[-80.777034,36.333317],"type":"Point"}
}