{
  "type": "Feature",
  "properties": {
    "addr:full":"5212 State Hwy 24 Newport NC 28570",
    "addr:housenumber":"5212",
    "addr:postcode":"28570",
    "addr:street":"State Hwy 24",
    "iso:country":"US",
    "sg:address":"5212 State Hwy 24",
    "sg:city":"Newport",
    "sg:classifiers":[
        {
            "category":"Professional",
            "type":"Services"
        }
    ],
    "sg:phone":"+1 252 393 2963",
    "sg:postcode":"28570",
    "sg:province":"NC",
    "sg:tags":[
        "establishment"
    ],
    "wof:name":"CETC",
    "wof:placetype":"venue"
},
  "geometry": {"coordinates":[-77.030637,34.700757],"type":"Point"}
}