{
  "type": "Feature",
  "properties": {
    "iso:country":"US",
    "sg:address":"726 Connelly Springs Rd SW",
    "sg:city":"Lenoir",
    "sg:classifiers":[
        {
            "category":"Personal",
            "subcategory":"Barber",
            "type":"Services"
        }
    ],
    "sg:phone":"+1 828 758 8501",
    "sg:postcode":"28645",
    "sg:province":"NC",
    "sg:tags":[
        "shop"
    ],
    "wof:name":"Cutting Edge",
    "wof:placetype":"venue"
},
  "geometry": {"coordinates":[-81.536411,35.881785],"type":"Point"}
}