{
  "type": "Feature",
  "properties": {
    "addr:full":"3607 Mooreland Farms Rd Charlotte NC 28226",
    "addr:housenumber":"3607",
    "addr:postcode":"28226",
    "addr:street":"Mooreland Farms Rd",
    "iso:country":"US",
    "sg:address":"3607 Mooreland Farms Rd",
    "sg:city":"Charlotte",
    "sg:classifiers":[
        {
            "category":"Manufacturing",
            "subcategory":"Printing",
            "type":"Manufacturing & Wholesale Goods"
        }
    ],
    "sg:phone":"+1 704 543 0738",
    "sg:postcode":"28226",
    "sg:province":"NC",
    "sg:tags":[
        "publishing"
    ],
    "wof:name":"Wondering Press",
    "wof:placetype":"venue"
},
  "geometry": {"coordinates":[-80.811077,35.127992],"type":"Point"}
}