{
  "type": "Feature",
  "properties": {
    "iso:country":"US",
    "sg:address":"302 Morris St",
    "sg:city":"Durham",
    "sg:classifiers":[
        {
            "category":"Building & Trades",
            "subcategory":"Cleaning & Sanitation",
            "type":"Services"
        }
    ],
    "sg:phone":"+1 919 560 3700",
    "sg:postcode":"27701",
    "sg:province":"NC",
    "sg:tags":[
        "central",
        "facility"
    ],
    "wof:name":"Durham Public Schools",
    "wof:placetype":"venue"
},
  "geometry": {"coordinates":[-78.903519,36.000213],"type":"Point"}
}