{
  "type": "Feature",
  "properties": {
    "iso:country":"US",
    "sg:address":"1316 Queens Rd",
    "sg:city":"Kinston",
    "sg:classifiers":[
        {
            "category":"Building & Trades",
            "subcategory":"Construction",
            "type":"Services"
        }
    ],
    "sg:phone":"+1 252 523 6408",
    "sg:postcode":"28501",
    "sg:province":"NC",
    "sg:tags":[
        "hanging",
        "contractor"
    ],
    "wof:name":"Lees Painting",
    "wof:placetype":"venue"
},
  "geometry": {"coordinates":[-77.581892,35.276332],"type":"Point"}
}