{
  "type": "Feature",
  "properties": {
    "iso:country":"US",
    "sg:address":"77 Muse St",
    "sg:city":"Waynesville",
    "sg:classifiers":[
        {
            "category":"Building & Trades",
            "subcategory":"Construction",
            "type":"Services"
        }
    ],
    "sg:phone":"+1 828 456 5970",
    "sg:postcode":"28786",
    "sg:province":"NC",
    "sg:tags":[
        "hanging",
        "contractor"
    ],
    "wof:name":"A D Mills Painting",
    "wof:placetype":"venue"
},
  "geometry": {"coordinates":[-83.004345,35.463029],"type":"Point"}
}