{
  "type": "Feature",
  "properties": {
    "addr:full":"211 Troxler Cir NW Concord NC 28027",
    "addr:housenumber":"211",
    "addr:postcode":"28027",
    "addr:street":"Troxler Cir Nw",
    "iso:country":"US",
    "sg:address":"211 Troxler Cir NW",
    "sg:city":"Concord",
    "sg:classifiers":[
        {
            "category":"Professional",
            "subcategory":"Business Services",
            "type":"Services"
        }
    ],
    "sg:phone":"+1   ",
    "sg:postcode":"28027",
    "sg:province":"NC",
    "sg:tags":[
        "crane"
    ],
    "wof:name":"Lancaster Scott Crane Inc",
    "wof:placetype":"venue"
},
  "geometry": {"coordinates":[-80.61834399999999,35.416546],"type":"Point"}
}