{
  "type": "Feature",
  "properties": {
    "iso:country":"US",
    "sg:address":"4250 Patterson Ave",
    "sg:city":"Winston Salem",
    "sg:classifiers":[
        {
            "category":"Shopping",
            "subcategory":"Used Merchandise",
            "type":"Retail Goods"
        }
    ],
    "sg:phone":"+1 336 767 3101",
    "sg:postcode":"27105",
    "sg:province":"NC",
    "sg:tags":[
        "clothing"
    ],
    "wof:name":"Flavorizations",
    "wof:placetype":"venue"
},
  "geometry": {"coordinates":[-80.26186,36.16825],"type":"Point"}
}