{
  "type": "Feature",
  "properties": {
    "addr:full":"1012 Roanoke Ave Roanoke Rapids NC 27870",
    "addr:housenumber":"1012",
    "addr:postcode":"27870",
    "addr:street":"Roanoke Ave",
    "iso:country":"US",
    "sg:address":"1012 Roanoke Ave",
    "sg:city":"Roanoke Rapids",
    "sg:classifiers":[
        {
            "category":"Food & Beverages",
            "subcategory":"Groceries & Convenience Stores",
            "type":"Retail Goods"
        }
    ],
    "sg:phone":"+1 252 410 0474",
    "sg:postcode":"27870",
    "sg:province":"NC",
    "sg:tags":[
        "grocer"
    ],
    "wof:name":"LA Guadalupana",
    "wof:placetype":"venue"
},
  "geometry": {"coordinates":[-77.657177,36.455857],"type":"Point"}
}