{
  "type": "Feature",
  "properties": {
    "iso:country":"US",
    "sg:address":"208 E Church St",
    "sg:city":"Smithfield",
    "sg:classifiers":[
        {
            "category":"Professional",
            "subcategory":"Lawyer & Legal Services",
            "type":"Services"
        }
    ],
    "sg:phone":"+1 919 934 1985",
    "sg:postcode":"27577",
    "sg:province":"NC",
    "sg:tags":[
        "attorney"
    ],
    "wof:name":"Cynthia Pittard",
    "wof:placetype":"venue"
},
  "geometry": {"coordinates":[-78.348887,35.50933],"type":"Point"}
}