{
  "type": "Feature",
  "properties": {
    "iso:country":"US",
    "sg:address":"235 Sylvan St",
    "sg:city":"Waynesville",
    "sg:classifiers":[
        {
            "category":"Building & Trades",
            "subcategory":"Electrical",
            "type":"Services"
        }
    ],
    "sg:phone":"+1 828 454 0048",
    "sg:postcode":"28786",
    "sg:province":"NC",
    "sg:tags":[
        "electrical",
        "contractor"
    ],
    "wof:name":"Electrical Contracting",
    "wof:placetype":"venue"
},
  "geometry": {"coordinates":[-82.998744,35.495616],"type":"Point"}
}