{
  "type": "Feature",
  "properties": {
    "iso:country":"US",
    "sg:address":"1064 Southwest Dr",
    "sg:city":"Davidson",
    "sg:classifiers":[
        {
            "category":"Sports & Exercise",
            "subcategory":"Swimming Pool",
            "type":"Entertainment"
        }
    ],
    "sg:phone":"+1 704 892 1435",
    "sg:postcode":"28036",
    "sg:province":"NC",
    "sg:tags":[
        "pools-public"
    ],
    "wof:name":"South Harbortown Pool",
    "wof:placetype":"venue"
},
  "geometry": {"coordinates":[-80.870352,35.502541],"type":"Point"}
}