{
  "type": "Feature",
  "properties": {
    "iso:country":"US",
    "sg:address":"2211 N New Hope Rd",
    "sg:city":"Gastonia",
    "sg:classifiers":[
        {
            "category":"Food & Beverages",
            "subcategory":"Groceries & Convenience Stores",
            "type":"Retail Goods"
        }
    ],
    "sg:phone":"+1 704 866 7022",
    "sg:postcode":"28054",
    "sg:province":"NC",
    "sg:tags":[
        "grocer"
    ],
    "wof:name":"Food Lion",
    "wof:placetype":"venue"
},
  "geometry": {"coordinates":[-81.159564,35.299166],"type":"Point"}
}