{
  "type": "Feature",
  "properties": {
    "iso:country":"US",
    "sg:address":"737 N Forty Rd",
    "sg:city":"Morehead City",
    "sg:classifiers":[
        {
            "category":"Building & Trades",
            "subcategory":"Construction",
            "type":"Services"
        }
    ],
    "sg:phone":"+1 252 247 5921",
    "sg:postcode":"28557",
    "sg:province":"NC",
    "sg:tags":[
        "hanging",
        "contractor"
    ],
    "wof:name":"J N T Enterprises",
    "wof:placetype":"venue"
},
  "geometry": {"coordinates":[-76.750795,34.737136],"type":"Point"}
}