{
  "type": "Feature",
  "properties": {
    "addr:full":"2500 E Independence Blvd Charlotte NC 28205",
    "addr:housenumber":"2500",
    "addr:postcode":"28205",
    "addr:street":"E Independence Blvd",
    "iso:country":"US",
    "sg:address":"2500 E Independence Blvd",
    "sg:city":"Charlotte",
    "sg:classifiers":[
        {
            "category":"Wholesale",
            "subcategory":"Jewelry",
            "type":"Manufacturing & Wholesale Goods"
        }
    ],
    "sg:phone":"+1 704 375 7440",
    "sg:postcode":"28205",
    "sg:province":"NC",
    "sg:tags":[
        "jeweler"
    ],
    "wof:name":"Michele-Lynn Wholesale Jewelry",
    "wof:placetype":"venue"
},
  "geometry": {"coordinates":[-80.796768,35.207145],"type":"Point"}
}