{
  "type": "Feature",
  "properties": {
    "addr:full":"4300 Project Rd NW Ash NC 28420",
    "addr:postcode":"4300;28420",
    "addr:street":"Project Rd Nw",
    "iso:country":"US",
    "sg:address":"4300 Project Rd NW",
    "sg:city":"Ash",
    "sg:classifiers":[
        {
            "category":"Building & Trades",
            "subcategory":"Construction",
            "type":"Services"
        }
    ],
    "sg:phone":"+1 910 287 4035",
    "sg:postcode":"28420",
    "sg:province":"NC",
    "sg:tags":[
        "carpentry",
        "contractor"
    ],
    "wof:name":"Earl Cribb Intr Trim & Finish",
    "wof:placetype":"venue"
},
  "geometry": {"coordinates":[-78.50712900000001,34.080303],"type":"Point"}
}