{
  "type": "Feature",
  "properties": {
    "iso:country":"US",
    "sg:address":"150 Charlois Blvd",
    "sg:city":"Winston Salem",
    "sg:classifiers":[
        {
            "category":"Communications",
            "subcategory":"Film & Video Production",
            "type":"Services"
        }
    ],
    "sg:phone":"+1 336 774 9910",
    "sg:postcode":"27103",
    "sg:province":"NC",
    "sg:tags":[
        "taping"
    ],
    "wof:name":"Big Wheel",
    "wof:placetype":"venue"
},
  "geometry": {"coordinates":[-80.302379,36.085093],"type":"Point"}
}