{
  "type": "Feature",
  "properties": {
    "addr:full":"7876 State Hwy 87 S Fayetteville NC 28306",
    "addr:housenumber":"7876",
    "addr:postcode":"28306",
    "addr:street":"State Hwy 87 S",
    "iso:country":"US",
    "sg:address":"7876 State Hwy 87 S",
    "sg:city":"Fayetteville",
    "sg:classifiers":[
        {
            "category":"Personal",
            "subcategory":"Beauty Salon",
            "type":"Services"
        }
    ],
    "sg:phone":"+1 910 323 8234",
    "sg:postcode":"28306",
    "sg:province":"NC",
    "sg:tags":[
        "shop"
    ],
    "wof:name":"Bonnie's Hair Design",
    "wof:placetype":"venue"
},
  "geometry": {"coordinates":[-78.850347,34.86617],"type":"Point"}
}