{
  "type": "Feature",
  "properties": {
    "addr:full":"827 Hill St Eden NC 27288",
    "addr:housenumber":"827",
    "addr:postcode":"27288",
    "addr:street":"Hill St",
    "iso:country":"US",
    "sg:address":"827 Hill St",
    "sg:city":"Eden",
    "sg:classifiers":[
        {
            "category":"Professional",
            "type":"Services"
        }
    ],
    "sg:phone":"+1 336 623 3180",
    "sg:postcode":"27288",
    "sg:province":"NC",
    "wof:name":"B&T Racing Motor Sports",
    "wof:placetype":"venue"
},
  "geometry": {"coordinates":[-79.770436,36.508585],"type":"Point"}
}