{
  "type": "Feature",
  "properties": {
    "iso:country":"US",
    "sg:address":"1974 Antioch Rd",
    "sg:city":"Rocky Mount",
    "sg:classifiers":[
        {
            "category":"Building & Trades",
            "subcategory":"Construction",
            "type":"Services"
        }
    ],
    "sg:phone":"+1 252 977 7597",
    "sg:postcode":"27801",
    "sg:province":"NC",
    "sg:tags":[
        "house"
    ],
    "wof:name":"Timothy Rhodes",
    "wof:placetype":"venue"
},
  "geometry": {"coordinates":[-77.69229799999999,35.903661],"type":"Point"}
}