{
  "type": "Feature",
  "properties": {
    "addr:full":"1028 Kerrow Rd Fayetteville NC 28314",
    "addr:housenumber":"1028",
    "addr:postcode":"28314",
    "addr:street":"Kerrow Rd",
    "iso:country":"US",
    "sg:address":"1028 Kerrow Rd",
    "sg:city":"Fayetteville",
    "sg:classifiers":[
        {
            "category":"Insurance",
            "subcategory":"Hazard Insurance",
            "type":"Services"
        }
    ],
    "sg:phone":"+1 910 826 1466",
    "sg:postcode":"28314",
    "sg:province":"NC",
    "sg:tags":[
        "bond"
    ],
    "wof:name":"Denice Bail Bonds",
    "wof:placetype":"venue"
},
  "geometry": {"coordinates":[-79.068254,35.056762],"type":"Point"}
}