{
  "type": "Feature",
  "properties": {
    "iso:country":"US",
    "sg:address":"219 Hydro Rd",
    "sg:city":"Mount Gilead",
    "sg:classifiers":[
        {
            "category":"Freight",
            "type":"Transportation"
        }
    ],
    "sg:phone":"+1 910 220 1246",
    "sg:postcode":"27306",
    "sg:province":"NC",
    "sg:tags":[
        "operator",
        "trucking"
    ],
    "wof:name":"Brandon A Montgomery",
    "wof:placetype":"venue"
},
  "geometry": {"coordinates":[-80.023281,35.214048],"type":"Point"}
}