{
  "type": "Feature",
  "properties": {
    "iso:country":"US",
    "sg:address":"104 W Main St",
    "sg:city":"Troy",
    "sg:classifiers":[
        {
            "category":"Autos & Motor Vehicles",
            "subcategory":"Auto Supplies",
            "type":"Retail Goods"
        }
    ],
    "sg:phone":"+1 910 572 3794",
    "sg:postcode":"27371",
    "sg:province":"NC",
    "sg:tags":[
        "tire"
    ],
    "wof:name":"Pigford Inc",
    "wof:placetype":"venue"
},
  "geometry": {"coordinates":[-79.894706,35.358714],"type":"Point"}
}