{
  "type": "Feature",
  "properties": {
    "iso:country":"US",
    "sg:address":"6016 Wayne Memorial Dr",
    "sg:city":"Pikeville",
    "sg:classifiers":[
        {
            "category":"Building & Trades",
            "subcategory":"Cleaning & Sanitation",
            "type":"Services"
        }
    ],
    "sg:phone":"+1   ",
    "sg:postcode":"27863",
    "sg:province":"NC",
    "sg:tags":[
        "maintenance"
    ],
    "wof:name":"William Smith",
    "wof:placetype":"venue"
},
  "geometry": {"coordinates":[-77.850455,35.458561],"type":"Point"}
}