{
  "type": "Feature",
  "properties": {
    "iso:country":"US",
    "sg:address":"3224 Ashe Ave",
    "sg:city":"Dunn",
    "sg:classifiers":[
        {
            "category":"Organizations",
            "subcategory":"Religious Organization",
            "type":"Services"
        }
    ],
    "sg:phone":"+1 910 897 7400",
    "sg:postcode":"28334",
    "sg:province":"NC",
    "sg:tags":[
        "church"
    ],
    "wof:name":"New Beginnings Worship Ctr",
    "wof:placetype":"venue"
},
  "geometry": {"coordinates":[-78.64112,35.339162],"type":"Point"}
}