{
  "type": "Feature",
  "properties": {
    "iso:country":"US",
    "sg:address":"120 N Salem St",
    "sg:city":"Apex",
    "sg:classifiers":[
        {
            "category":"Building & Trades",
            "subcategory":"Cleaning & Sanitation",
            "type":"Services"
        }
    ],
    "sg:phone":"+1 919 387 7402",
    "sg:postcode":"27502",
    "sg:province":"NC",
    "sg:tags":[
        "janitorial"
    ],
    "wof:name":"White Oak Services Inc",
    "wof:placetype":"venue"
},
  "geometry": {"coordinates":[-78.850973,35.731485],"type":"Point"}
}