{
  "type": "Feature",
  "properties": {
    "iso:country":"US",
    "sg:address":"426 S Maple St",
    "sg:city":"Graham",
    "sg:classifiers":[
        {
            "category":"Manufacturing",
            "subcategory":"Tools & Machinery",
            "type":"Manufacturing & Wholesale Goods"
        }
    ],
    "sg:phone":"+1 336 570 0185",
    "sg:postcode":"27253",
    "sg:province":"NC",
    "sg:tags":[
        "polishing",
        "car",
        "washing",
        "equipment"
    ],
    "sg:website":"www.southernpride-snm.com",
    "wof:name":"SNM Mfg Inc",
    "wof:placetype":"venue"
},
  "geometry": {"coordinates":[-79.403885,36.062749],"type":"Point"}
}