{
  "type": "Feature",
  "properties": {
    "addr:full":"1224 Laura Village Rd Apex NC 27523",
    "addr:housenumber":"1224",
    "addr:postcode":"27523",
    "addr:street":"Laura Village Rd",
    "iso:country":"US",
    "sg:address":"1224 Laura Village Rd",
    "sg:city":"Apex",
    "sg:classifiers":[
        {
            "category":"Professional",
            "type":"Services"
        }
    ],
    "sg:phone":"+1   ",
    "sg:postcode":"27523",
    "sg:province":"NC",
    "wof:name":"Plaster House",
    "wof:placetype":"venue"
},
  "geometry": {"coordinates":[-78.837789,35.749694],"type":"Point"}
}