{
  "type": "Feature",
  "properties": {
    "iso:country":"US",
    "sg:address":"1170 Majolica Rd",
    "sg:city":"Salisbury",
    "sg:classifiers":[
        {
            "category":"Real Estate",
            "subcategory":"Real Estate Operator",
            "type":"Services"
        },
        {
            "category":"Retail",
            "subcategory":"Auto Rental",
            "type":"Services"
        }
    ],
    "sg:phone":"+1 704 642 1024",
    "sg:postcode":"28147",
    "sg:province":"NC",
    "sg:tags":[
        "mobile",
        "home",
        "trailer",
        "community",
        "utility"
    ],
    "wof:name":"Oakland Meadows",
    "wof:placetype":"venue"
},
  "geometry": {"coordinates":[-80.53622,35.684747],"type":"Point"}
}