{
  "type": "Feature",
  "properties": {
    "iso:country":"US",
    "sg:address":"4045 US Hwy 21",
    "sg:city":"Hamptonville",
    "sg:classifiers":[
        {
            "category":"Building & Trades",
            "subcategory":"Plumbing",
            "type":"Services"
        }
    ],
    "sg:phone":"+1 336 468 8492",
    "sg:postcode":"27020",
    "sg:province":"NC",
    "sg:tags":[
        "contractor"
    ],
    "wof:name":"Oliver Plumbing",
    "wof:placetype":"venue"
},
  "geometry": {"coordinates":[-80.785943,36.149131],"type":"Point"}
}