{
  "type": "Feature",
  "properties": {
    "addr:full":"320 Barclay Rd Chapel Hill NC 27516",
    "addr:housenumber":"320",
    "addr:postcode":"27516",
    "addr:street":"Barclay Rd",
    "iso:country":"US",
    "sg:address":"320 Barclay Rd",
    "sg:city":"Chapel Hill",
    "sg:classifiers":[
        {
            "category":"Professional",
            "subcategory":"Management & Consulting",
            "type":"Services"
        }
    ],
    "sg:phone":"+1   ",
    "sg:postcode":"27516",
    "sg:province":"NC",
    "sg:tags":[
        "business"
    ],
    "wof:name":"Fall Apples Consulting",
    "wof:placetype":"venue"
},
  "geometry": {"coordinates":[-79.064628,35.927481],"type":"Point"}
}