{
  "type": "Feature",
  "properties": {
    "iso:country":"US",
    "sg:address":"255 E Lexington Rd",
    "sg:city":"Mocksville",
    "sg:classifiers":[
        {
            "category":"Autos & Motor Vehicles",
            "subcategory":"Automobile Sales",
            "type":"Retail Goods"
        }
    ],
    "sg:phone":"+1 336 751 3442",
    "sg:postcode":"27028",
    "sg:province":"NC",
    "sg:tags":[
        "new",
        "used",
        "dealer",
        "car"
    ],
    "wof:name":"Cleary Auto Sales Inc",
    "wof:placetype":"venue"
},
  "geometry": {"coordinates":[-80.55832100000001,35.891098],"type":"Point"}
}