{
  "type": "Feature",
  "properties": {
    "iso:country":"US",
    "sg:address":"3504 Konnoak Dr",
    "sg:city":"Winston Salem",
    "sg:classifiers":[
        {
            "category":"Building & Trades",
            "subcategory":"Construction",
            "type":"Services"
        }
    ],
    "sg:phone":"+1 336 993 6757",
    "sg:postcode":"27127",
    "sg:province":"NC",
    "sg:tags":[
        "painter"
    ],
    "wof:name":"Wayne's Custom Painting",
    "wof:placetype":"venue"
},
  "geometry": {"coordinates":[-80.242621,36.047618],"type":"Point"}
}