{
  "type": "Feature",
  "properties": {
    "addr:full":"4600 Park Rd Charlotte NC 28209",
    "addr:housenumber":"4600",
    "addr:postcode":"28209",
    "addr:street":"Park Rd",
    "iso:country":"US",
    "sg:address":"4600 Park Rd",
    "sg:city":"Charlotte",
    "sg:phone":"+1 704 523 1222",
    "sg:postcode":"28209",
    "sg:province":"NC",
    "wof:name":"Good Friends",
    "wof:placetype":"venue"
},
  "geometry": {"coordinates":[-80.850769,35.168812],"type":"Point"}
}