{
  "type": "Feature",
  "properties": {
    "iso:country":"US",
    "sg:address":"1985 N Roberts Ave",
    "sg:city":"Lumberton",
    "sg:classifiers":[
        {
            "category":"Professional",
            "type":"Services"
        },
        {
            "category":"Restaurant",
            "type":"Food & Drink"
        }
    ],
    "sg:phone":"+1 910 739 2115",
    "sg:postcode":"28358",
    "sg:province":"NC",
    "wof:name":"Mariscos Mar Y Sol",
    "wof:placetype":"venue"
},
  "geometry": {"coordinates":[-78.99529200000001,34.634548],"type":"Point"}
}