{
  "type": "Feature",
  "properties": {
    "iso:country":"US",
    "sg:address":"98 Stonebridge Trl",
    "sg:city":"Havelock",
    "sg:classifiers":[
        {
            "category":"Health Services",
            "subcategory":"Doctor",
            "type":"Services"
        }
    ],
    "sg:phone":"+1 252 447 1181",
    "sg:postcode":"28532",
    "sg:province":"NC",
    "sg:tags":[
        "dentist"
    ],
    "wof:name":"Willis Vanek Ball & Fischer",
    "wof:placetype":"venue"
},
  "geometry": {"coordinates":[-76.926872,34.89675],"type":"Point"}
}