{
  "type": "Feature",
  "properties": {
    "iso:country":"US",
    "sg:address":"14214 Arbor Ridge Dr",
    "sg:city":"Charlotte",
    "sg:classifiers":[
        {
            "category":"Professional",
            "subcategory":"Computer Services",
            "type":"Services"
        }
    ],
    "sg:phone":"+1   ",
    "sg:postcode":"28273",
    "sg:province":"NC",
    "sg:tags":[
        "programing",
        "custom"
    ],
    "wof:name":"Williams Networks Solutions",
    "wof:placetype":"venue"
},
  "geometry": {"coordinates":[-80.977963,35.11856],"type":"Point"}
}