{
  "type": "Feature",
  "properties": {
    "iso:country":"US",
    "sg:address":"8609 Keegan Ct",
    "sg:city":"Raleigh",
    "sg:classifiers":[
        {
            "category":"Professional",
            "subcategory":"Management & Consulting",
            "type":"Services"
        }
    ],
    "sg:phone":"+1 919 845 9877",
    "sg:postcode":"27613",
    "sg:province":"NC",
    "sg:tags":[
        "consultant",
        "business"
    ],
    "wof:name":"Warda",
    "wof:placetype":"venue"
},
  "geometry": {"coordinates":[-78.67954400000001,35.879236],"type":"Point"}
}