{
  "type": "Feature",
  "properties": {
    "iso:country":"US",
    "sg:address":"475 N Walnut St",
    "sg:city":"Pinebluff",
    "sg:classifiers":[
        {
            "category":"Shopping",
            "subcategory":"Hobbies, Toys, & Games",
            "type":"Retail Goods"
        }
    ],
    "sg:phone":"+1 910 281 0874",
    "sg:postcode":"28373",
    "sg:province":"NC",
    "sg:tags":[
        "supply"
    ],
    "wof:name":"C & R Games",
    "wof:placetype":"venue"
},
  "geometry": {"coordinates":[-79.470331,35.113465],"type":"Point"}
}