{
  "type": "Feature",
  "properties": {
    "iso:country":"US",
    "sg:address":"4401 Oleander Dr",
    "sg:city":"Wilmington",
    "sg:classifiers":[
        {
            "category":"Recreation",
            "type":"Entertainment"
        }
    ],
    "sg:phone":"+1 910 313 2626",
    "sg:postcode":"28403",
    "sg:province":"NC",
    "sg:tags":[
        "martial",
        "arts",
        "instruction"
    ],
    "wof:name":"Jim Erwin's Southeast Karate",
    "wof:placetype":"venue"
},
  "geometry": {"coordinates":[-77.88764399999999,34.210555],"type":"Point"}
}