{
  "type": "Feature",
  "properties": {
    "addr:full":"414 Peachtree St Rocky Mount NC 27804",
    "addr:housenumber":"414",
    "addr:postcode":"27804",
    "addr:street":"Peachtree St",
    "iso:country":"US",
    "sg:address":"414 Peachtree St",
    "sg:city":"Rocky Mount",
    "sg:classifiers":[
        {
            "category":"Building & Trades",
            "subcategory":"Cleaning & Sanitation",
            "type":"Services"
        }
    ],
    "sg:phone":"+1 252 446 3377",
    "sg:postcode":"27804",
    "sg:province":"NC",
    "sg:tags":[
        "janitor"
    ],
    "wof:name":"Royal Quality Maintenance Inc",
    "wof:placetype":"venue"
},
  "geometry": {"coordinates":[-77.79759199999999,35.949378],"type":"Point"}
}