{
  "type": "Feature",
  "properties": {
    "addr:full":"3117 Wickford Rd Wilmington NC 28409",
    "addr:housenumber":"3117",
    "addr:postcode":"28409",
    "addr:street":"Wickford Rd",
    "iso:country":"US",
    "sg:address":"3117 Wickford Rd",
    "sg:city":"Wilmington",
    "sg:classifiers":[
        {
            "category":"Farming",
            "subcategory":"Farm",
            "type":"Manufacturing & Wholesale Goods"
        }
    ],
    "sg:phone":"+1 910 799 8484",
    "sg:postcode":"28409",
    "sg:province":"NC",
    "wof:name":"Marlboro Bulb Farm",
    "wof:placetype":"venue"
},
  "geometry": {"coordinates":[-77.882648,34.177403],"type":"Point"}
}