{
  "type": "Feature",
  "properties": {
    "addr:full":"13511 Glenwyck Ln Huntersville NC 28078",
    "addr:housenumber":"13511",
    "addr:postcode":"28078",
    "addr:street":"Glenwyck Ln",
    "iso:country":"US",
    "sg:address":"13511 Glenwyck Ln",
    "sg:city":"Huntersville",
    "sg:classifiers":[
        {
            "category":"Personal",
            "subcategory":"Beauty Salon",
            "type":"Services"
        }
    ],
    "sg:phone":"+1   ",
    "sg:postcode":"28078",
    "sg:province":"NC",
    "sg:tags":[
        "shop"
    ],
    "wof:name":"Kuts Landscaping Inc",
    "wof:placetype":"venue"
},
  "geometry": {"coordinates":[-80.913239,35.400366],"type":"Point"}
}