{
  "type": "Feature",
  "properties": {
    "iso:country":"US",
    "sg:address":"202 Providence Church Rd",
    "sg:city":"Goldsboro",
    "sg:classifiers":[
        {
            "category":"Organizations",
            "subcategory":"Religious Organization",
            "type":"Services"
        }
    ],
    "sg:phone":"+1 919 734 7114",
    "sg:postcode":"27530",
    "sg:province":"NC",
    "sg:tags":[
        "church"
    ],
    "sg:website":"www.pumcg.org",
    "wof:name":"Providence United Mthdst Chr",
    "wof:placetype":"venue"
},
  "geometry": {"coordinates":[-78.073489,35.322459],"type":"Point"}
}