{
  "type": "Feature",
  "properties": {
    "iso:country":"US",
    "sg:address":"112 Walnut Dr",
    "sg:city":"Benson",
    "sg:classifiers":[
        {
            "category":"Building & Trades",
            "subcategory":"Construction",
            "type":"Services"
        }
    ],
    "sg:phone":"+1 919 207 2133",
    "sg:postcode":"27504",
    "sg:province":"NC",
    "sg:tags":[
        "contractor"
    ],
    "wof:name":"Joseph General Contractors",
    "wof:placetype":"venue"
},
  "geometry": {"coordinates":[-78.612438,35.454365],"type":"Point"}
}