{
  "type": "Feature",
  "properties": {
    "addr:full":"6542 Jackson Creek Rd Denton NC 27239",
    "addr:housenumber":"6542",
    "addr:postcode":"27239",
    "addr:street":"Jackson Creek Rd",
    "iso:country":"US",
    "sg:address":"6542 Jackson Creek Rd",
    "sg:city":"Denton",
    "sg:classifiers":[
        {
            "category":"Personal",
            "subcategory":"Beauty Salon",
            "type":"Services"
        }
    ],
    "sg:phone":"+1 336 241 2222",
    "sg:postcode":"27239",
    "sg:province":"NC",
    "wof:name":"Town & Country Beauty Salon",
    "wof:placetype":"venue"
},
  "geometry": {"coordinates":[-80.01082100000001,35.695424],"type":"Point"}
}