{
  "type": "Feature",
  "properties": {
    "iso:country":"US",
    "sg:address":"400 Lazy J Dr",
    "sg:city":"Smithfield",
    "sg:classifiers":[
        {
            "category":"Building & Trades",
            "subcategory":"Construction",
            "type":"Services"
        }
    ],
    "sg:phone":"+1 919 965 3584",
    "sg:postcode":"27577",
    "sg:province":"NC",
    "sg:tags":[
        "house"
    ],
    "wof:name":"Williams Construction",
    "wof:placetype":"venue"
},
  "geometry": {"coordinates":[-78.239475,35.468292],"type":"Point"}
}