{
  "type": "Feature",
  "properties": {
    "iso:country":"US",
    "sg:address":"2520 Lanecrest Dr",
    "sg:city":"Charlotte",
    "sg:classifiers":[
        {
            "category":"Building & Trades",
            "subcategory":"Cleaning & Sanitation",
            "type":"Services"
        }
    ],
    "sg:phone":"+1 704 531 2577",
    "sg:postcode":"28215",
    "sg:province":"NC",
    "sg:tags":[
        "janitor"
    ],
    "wof:name":"Yodi Cleaning Svc",
    "wof:placetype":"venue"
},
  "geometry": {"coordinates":[-80.74640100000001,35.240932],"type":"Point"}
}