{
  "type": "Feature",
  "properties": {
    "iso:country":"US",
    "sg:address":"1963 Chicken Foot Rd",
    "sg:city":"Tar Heel",
    "sg:classifiers":[
        {
            "category":"Education",
            "subcategory":"School",
            "type":"Public Place"
        }
    ],
    "sg:phone":"+1 910 862 2371",
    "sg:postcode":"28392",
    "sg:province":"NC",
    "wof:name":"Plainview School",
    "wof:placetype":"venue"
},
  "geometry": {"coordinates":[-78.85414900000001,34.759419],"type":"Point"}
}