{
  "type": "Feature",
  "properties": {
    "iso:country":"US",
    "sg:address":"1673 N Howe St",
    "sg:city":"Southport",
    "sg:classifiers":[
        {
            "category":"Restaurant",
            "type":"Food & Drink"
        }
    ],
    "sg:menulink":"http://www.allmenus.com/nc/smithville/157738-zacharys-american-grill/menu/",
    "sg:phone":"+1 910 454 8700",
    "sg:postcode":"28461",
    "sg:province":"NC",
    "sg:tags":[
        "american"
    ],
    "wof:name":"Zachary's American Grill",
    "wof:placetype":"venue"
},
  "geometry": {"coordinates":[-78.031177,33.945449],"type":"Point"}
}