{
  "type": "Feature",
  "properties": {
    "iso:country":"US",
    "sg:address":"2038 Claude Green Rd",
    "sg:city":"Robersonville",
    "sg:classifiers":[
        {
            "category":"Shopping",
            "subcategory":"Florist",
            "type":"Retail Goods"
        }
    ],
    "sg:phone":"+1 252 795 3034",
    "sg:postcode":"27871",
    "sg:province":"NC",
    "wof:name":"Fantasy Flowers",
    "wof:placetype":"venue"
},
  "geometry": {"coordinates":[-77.277969,35.840628],"type":"Point"}
}