{
  "type": "Feature",
  "properties": {
    "addr:full":"823 E Dixie Dr Asheboro NC 27203",
    "addr:housenumber":"823",
    "addr:postcode":"27203",
    "addr:street":"E Dixie Dr",
    "iso:country":"US",
    "sg:address":"823 E Dixie Dr",
    "sg:city":"Asheboro",
    "sg:classifiers":[
        {
            "category":"Shopping",
            "subcategory":"Used Merchandise",
            "type":"Retail Goods"
        }
    ],
    "sg:phone":"+1 336 629 6164",
    "sg:postcode":"27203",
    "sg:province":"NC",
    "sg:tags":[
        "shop",
        "firearm",
        "pawn"
    ],
    "wof:name":"Treasure World Inc",
    "wof:placetype":"venue"
},
  "geometry": {"coordinates":[-79.802756,35.691027],"type":"Point"}
}