{
  "type": "Feature",
  "properties": {
    "iso:country":"US",
    "sg:address":"3701 Bridges St",
    "sg:city":"Morehead City",
    "sg:classifiers":[
        {
            "category":"Health Services",
            "subcategory":"Clinic",
            "type":"Services"
        }
    ],
    "sg:phone":"+1   ",
    "sg:postcode":"28557",
    "sg:province":"NC",
    "wof:name":"Atlantic House",
    "wof:placetype":"venue"
},
  "geometry": {"coordinates":[-76.75879999999999,34.72605],"type":"Point"}
}