{
  "type": "Feature",
  "properties": {
    "iso:country":"US",
    "sg:address":"7921 Camellia Ln",
    "sg:city":"Charlotte",
    "sg:classifiers":[
        {
            "category":"Professional",
            "subcategory":"Business Services",
            "type":"Services"
        }
    ],
    "sg:phone":"+1   ",
    "sg:postcode":"28277",
    "sg:province":"NC",
    "wof:name":"Maier Margenia",
    "wof:placetype":"venue"
},
  "geometry": {"coordinates":[-80.810571,35.051124],"type":"Point"}
}