{
  "type": "Feature",
  "properties": {
    "iso:country":"US",
    "sg:address":"400 Ashville Ave Ste 300",
    "sg:city":"Cary",
    "sg:classifiers":[
        {
            "category":"Health Services",
            "subcategory":"Optometrist",
            "type":"Services"
        }
    ],
    "sg:phone":"+1 919 233 2020",
    "sg:postcode":"27511",
    "sg:province":"NC",
    "sg:tags":[
        "ophthalmologist"
    ],
    "wof:name":"Western Wake Eye Center PA",
    "wof:placetype":"venue"
},
  "geometry": {"coordinates":[-78.78630099999999,35.7384],"type":"Point"}
}