{
  "type": "Feature",
  "properties": {
    "addr:full":"151 Ginger Rd Wilmington NC 28405",
    "addr:housenumber":"151",
    "addr:postcode":"28405",
    "addr:street":"Ginger Rd",
    "iso:country":"US",
    "sg:address":"151 Ginger Rd",
    "sg:city":"Wilmington",
    "sg:classifiers":[
        {
            "category":"Real Estate",
            "subcategory":"Real Estate Operator",
            "type":"Services"
        }
    ],
    "sg:phone":"+1 910 791 3072",
    "sg:postcode":"28405",
    "sg:province":"NC",
    "sg:tags":[
        "building",
        "nonresidential"
    ],
    "wof:name":"Jtd Properties LLC",
    "wof:placetype":"venue"
},
  "geometry": {"coordinates":[-77.85159400000001,34.24364],"type":"Point"}
}