{
  "type": "Feature",
  "properties": {
    "iso:country":"US",
    "sg:address":"435 Lincoln St",
    "sg:city":"Burlington",
    "sg:classifiers":[
        {
            "category":"Professional",
            "type":"Services"
        }
    ],
    "sg:phone":"+1 336 227 0104",
    "sg:postcode":"27217",
    "sg:province":"NC",
    "sg:tags":[
        "establishment"
    ],
    "wof:name":"Angela's Family Care Home",
    "wof:placetype":"venue"
},
  "geometry": {"coordinates":[-79.423154,36.104247],"type":"Point"}
}