{
  "type": "Feature",
  "properties": {
    "iso:country":"US",
    "sg:address":"1779 Robert Whitfield Rd",
    "sg:city":"Hurdle Mills",
    "sg:classifiers":[
        {
            "category":"Home & Garden",
            "subcategory":"Building Materials",
            "type":"Retail Goods"
        },
        {
            "category":"Airport",
            "type":"Transportation"
        }
    ],
    "sg:phone":"+1 336 364 4444",
    "sg:postcode":"27541",
    "sg:province":"NC",
    "sg:tags":[
        "support",
        "airline"
    ],
    "wof:name":"A Aviation Association",
    "wof:placetype":"venue"
},
  "geometry": {"coordinates":[-79.08096399999999,36.276246],"type":"Point"}
}