{
  "type": "Feature",
  "properties": {
    "iso:country":"US",
    "sg:address":"333 Old Durham Rd",
    "sg:city":"Roxboro",
    "sg:classifiers":[
        {
            "category":"Shopping",
            "subcategory":"Used Merchandise",
            "type":"Retail Goods"
        }
    ],
    "sg:phone":"+1 336 597 8343",
    "sg:postcode":"27573",
    "sg:province":"NC",
    "sg:tags":[
        "antique"
    ],
    "wof:name":"Mary & Paul's Collectibles",
    "wof:placetype":"venue"
},
  "geometry": {"coordinates":[-78.978748,36.370358],"type":"Point"}
}