{
  "type": "Feature",
  "properties": {
    "addr:full":"243 Bar Mill Rd Millers Creek NC 28651",
    "addr:housenumber":"243",
    "addr:postcode":"28651",
    "addr:street":"Bar Mill Rd",
    "iso:country":"US",
    "sg:address":"243 Bar Mill Rd",
    "sg:city":"Millers Creek",
    "sg:classifiers":[
        {
            "category":"Professional",
            "subcategory":"Accounting & Tax Preparation",
            "type":"Services"
        }
    ],
    "sg:phone":"+1   ",
    "sg:postcode":"28651",
    "sg:province":"NC",
    "wof:name":"Bookkeeper",
    "wof:placetype":"venue"
},
  "geometry": {"coordinates":[-81.22278799999999,36.219057],"type":"Point"}
}