{
  "type": "Feature",
  "properties": {
    "iso:country":"US",
    "sg:address":"6301 Cayuse Ln",
    "sg:city":"Raleigh",
    "sg:classifiers":[
        {
            "category":"Building & Trades",
            "subcategory":"Construction",
            "type":"Services"
        }
    ],
    "sg:phone":"+1 919 772 2151",
    "sg:postcode":"27603",
    "sg:province":"NC",
    "wof:name":"Discount Paving",
    "wof:placetype":"venue"
},
  "geometry": {"coordinates":[-78.64400999999999,35.604285],"type":"Point"}
}