{
  "type": "Feature",
  "properties": {
    "iso:country":"US",
    "sg:address":"18617 Maplecroft Lake Ln",
    "sg:city":"Davidson",
    "sg:classifiers":[
        {
            "category":"Manufacturing",
            "subcategory":"Chemicals & Compounds",
            "type":"Manufacturing & Wholesale Goods"
        }
    ],
    "sg:phone":"+1 704 892 1182",
    "sg:postcode":"28036",
    "sg:province":"NC",
    "sg:tags":[
        "preparation",
        "pharmaceutical",
        "mfg"
    ],
    "wof:name":"Abbott Laboratories",
    "wof:placetype":"venue"
},
  "geometry": {"coordinates":[-80.800083,35.460115],"type":"Point"}
}