{
  "type": "Feature",
  "properties": {
    "addr:full":"1512 Chicopee Rd Benson NC 27504",
    "addr:housenumber":"1512",
    "addr:postcode":"27504",
    "addr:street":"Chicopee Rd",
    "iso:country":"US",
    "sg:address":"1512 Chicopee Rd",
    "sg:city":"Benson",
    "sg:classifiers":[
        {
            "category":"Organizations",
            "subcategory":"Religious Organization",
            "type":"Services"
        }
    ],
    "sg:phone":"+1   ",
    "sg:postcode":"27504",
    "sg:province":"NC",
    "wof:name":"Kyles Chapel AME Zion Church",
    "wof:placetype":"venue"
},
  "geometry": {"coordinates":[-78.556257,35.366886],"type":"Point"}
}