{
  "type": "Feature",
  "properties": {
    "iso:country":"US",
    "sg:address":"405 N Walnut St",
    "sg:city":"Fairmont",
    "sg:classifiers":[
        {
            "category":"Shopping",
            "subcategory":"Clothing, Apparel, & Fashions",
            "type":"Retail Goods"
        }
    ],
    "sg:phone":"+1 910 628 1411",
    "sg:postcode":"28340",
    "sg:province":"NC",
    "sg:tags":[
        "furnishing"
    ],
    "wof:name":"Payback",
    "wof:placetype":"venue"
},
  "geometry": {"coordinates":[-79.112347,34.503559],"type":"Point"}
}