{
  "type": "Feature",
  "properties": {
    "addr:full":"705 Trade St Winston Salem NC 27101",
    "addr:housenumber":"705",
    "addr:postcode":"27101",
    "addr:street":"Trade St",
    "iso:country":"US",
    "sg:address":"705 Trade St",
    "sg:city":"Winston Salem",
    "sg:classifiers":[
        {
            "category":"Organizations",
            "subcategory":"Religious Organization",
            "type":"Services"
        }
    ],
    "sg:phone":"+1 336 722 5775",
    "sg:postcode":"27101",
    "sg:province":"NC",
    "wof:name":"Winston-Salem Rescue Mission",
    "wof:placetype":"venue"
},
  "geometry": {"coordinates":[-80.24639999999999,36.103742],"type":"Point"}
}