{
  "type": "Feature",
  "properties": {
    "iso:country":"US",
    "sg:address":"601 E Six Forks Rd",
    "sg:city":"Raleigh",
    "sg:classifiers":[
        {
            "category":"Sports & Exercise",
            "subcategory":"Gym",
            "type":"Entertainment"
        },
        {
            "category":"Arena",
            "subcategory":"Sports Club",
            "type":"Entertainment"
        }
    ],
    "sg:phone":"+1 919 755 1706",
    "sg:postcode":"27609",
    "sg:province":"NC",
    "sg:tags":[
        "health",
        "gymnasium"
    ],
    "wof:name":"Lifestyle Family Fitness",
    "wof:placetype":"venue"
},
  "geometry": {"coordinates":[-78.622247,35.819159],"type":"Point"}
}