{
  "type": "Feature",
  "properties": {
    "addr:full":"584 US Hwy 70 W Morganton NC 28655",
    "addr:housenumber":"584",
    "addr:postcode":"28655",
    "addr:street":"Us Hwy 70 W",
    "iso:country":"US",
    "sg:address":"584 US Hwy 70 W",
    "sg:city":"Morganton",
    "sg:classifiers":[
        {
            "category":"Retail",
            "subcategory":"Repair Shop",
            "type":"Services"
        }
    ],
    "sg:phone":"+1 828 584 3971",
    "sg:postcode":"28655",
    "sg:province":"NC",
    "sg:tags":[
        "taxidermist"
    ],
    "wof:name":"Leonard's Taxidermy",
    "wof:placetype":"venue"
},
  "geometry": {"coordinates":[-81.78862700000001,35.722575],"type":"Point"}
}