{
  "type": "Feature",
  "properties": {
    "iso:country":"US",
    "sg:address":"826 S Brightleaf Blvd",
    "sg:city":"Smithfield",
    "sg:classifiers":[
        {
            "category":"Shopping",
            "subcategory":"Used Merchandise",
            "type":"Retail Goods"
        }
    ],
    "sg:phone":"+1 919 989 9391",
    "sg:postcode":"27577",
    "sg:province":"NC",
    "sg:tags":[
        "antique"
    ],
    "wof:name":"Daze of Olde Antiques",
    "wof:placetype":"venue"
},
  "geometry": {"coordinates":[-78.350578,35.500405],"type":"Point"}
}