{
  "type": "Feature",
  "properties": {
    "addr:full":"335 Deerberry Ct Asheboro NC 27205",
    "addr:housenumber":"335",
    "addr:postcode":"27205",
    "addr:street":"Deerberry Ct",
    "iso:country":"US",
    "sg:address":"335 Deerberry Ct",
    "sg:city":"Asheboro",
    "sg:classifiers":[
        {
            "category":"Health Services",
            "subcategory":"Clinic",
            "type":"Services"
        }
    ],
    "sg:phone":"+1 336 629 1930",
    "sg:postcode":"27205",
    "sg:province":"NC",
    "wof:name":"United Healthcare Svc",
    "wof:placetype":"venue"
},
  "geometry": {"coordinates":[-79.735707,35.717642],"type":"Point"}
}