{
  "type": "Feature",
  "properties": {
    "addr:full":"1551 Stallings Rd Matthews NC 28104",
    "addr:housenumber":"1551",
    "addr:postcode":"28104",
    "addr:street":"Stallings Rd",
    "iso:country":"US",
    "sg:address":"1551 Stallings Rd",
    "sg:city":"Matthews",
    "sg:classifiers":[
        {
            "category":"Retail",
            "subcategory":"Auto Repair",
            "type":"Services"
        }
    ],
    "sg:phone":"+1 704 821 0451",
    "sg:postcode":"28104",
    "sg:province":"NC",
    "sg:tags":[
        "automobile",
        "installation",
        "glass"
    ],
    "wof:name":"Southern Glass & Plastics Co",
    "wof:placetype":"venue"
},
  "geometry": {"coordinates":[-80.675389,35.097651],"type":"Point"}
}