{
  "type": "Feature",
  "properties": {
    "addr:full":"2327 Englert Dr Durham NC 27713",
    "addr:housenumber":"2327",
    "addr:postcode":"27713",
    "addr:street":"Englert Dr",
    "iso:country":"US",
    "sg:address":"2327 Englert Dr",
    "sg:city":"Durham",
    "sg:classifiers":[
        {
            "category":"Professional",
            "subcategory":"Management & Consulting",
            "type":"Services"
        }
    ],
    "sg:phone":"+1 919 484 9458",
    "sg:postcode":"27713",
    "sg:province":"NC",
    "sg:tags":[
        "consultant",
        "business"
    ],
    "wof:name":"Organization Effectiveness",
    "wof:placetype":"venue"
},
  "geometry": {"coordinates":[-78.88972099999999,35.89523],"type":"Point"}
}