{
  "type": "Feature",
  "properties": {
    "iso:country":"US",
    "sg:address":"92 Chestnut St",
    "sg:city":"Brevard",
    "sg:classifiers":[
        {
            "category":"Health Services",
            "subcategory":"Doctor",
            "type":"Services"
        }
    ],
    "sg:phone":"+1 828 884 2055",
    "sg:postcode":"28712",
    "sg:province":"NC",
    "sg:tags":[
        "physician",
        "surgeon"
    ],
    "wof:name":"Brevard Orthopedic Assoc",
    "wof:placetype":"venue"
},
  "geometry": {"coordinates":[-82.721478,35.244841],"type":"Point"}
}