{
  "type": "Feature",
  "properties": {
    "addr:full":"1122 N Main Ave Newton NC 28658",
    "addr:housenumber":"1122",
    "addr:postcode":"28658",
    "addr:street":"N Main Ave",
    "iso:country":"US",
    "sg:address":"1122 N Main Ave",
    "sg:city":"Newton",
    "sg:classifiers":[
        {
            "category":"Shopping",
            "subcategory":"Clothing, Apparel, & Fashions",
            "type":"Retail Goods"
        }
    ],
    "sg:phone":"+1 828 464 5530",
    "sg:postcode":"28658",
    "sg:province":"NC",
    "wof:name":"Newton Embroidery",
    "wof:placetype":"venue"
},
  "geometry": {"coordinates":[-81.22093099999999,35.675342],"type":"Point"}
}