{
  "type": "Feature",
  "properties": {
    "iso:country":"US",
    "sg:address":"1507 Main St E",
    "sg:city":"Valdese",
    "sg:classifiers":[
        {
            "category":"Retail",
            "subcategory":"Funeral Services",
            "type":"Services"
        }
    ],
    "sg:phone":"+1   ",
    "sg:postcode":"28690",
    "sg:province":"NC",
    "wof:name":"Heritage Funeral Service",
    "wof:placetype":"venue"
},
  "geometry": {"coordinates":[-81.541749,35.743101],"type":"Point"}
}