{
  "type": "Feature",
  "properties": {
    "addr:full":"102 N Church St Louisburg NC 27549",
    "addr:housenumber":"102",
    "addr:postcode":"27549",
    "addr:street":"N Church St",
    "iso:country":"US",
    "sg:address":"102 N Church St",
    "sg:city":"Louisburg",
    "sg:classifiers":[
        {
            "category":"Autos & Motor Vehicles",
            "subcategory":"Automobile Sales",
            "type":"Retail Goods"
        }
    ],
    "sg:phone":"+1 919 284 1020",
    "sg:postcode":"27549",
    "sg:province":"NC",
    "sg:tags":[
        "car",
        "dealer"
    ],
    "wof:name":"My Boys Motor Cars Inc",
    "wof:placetype":"venue"
},
  "geometry": {"coordinates":[-78.302032,36.100048],"type":"Point"}
}