{
  "type": "Feature",
  "properties": {
    "iso:country":"US",
    "sg:address":"1427 Garner Station Blvd",
    "sg:city":"Raleigh",
    "sg:classifiers":[
        {
            "category":"Shopping",
            "subcategory":"Clothing, Apparel, & Fashions",
            "type":"Retail Goods"
        }
    ],
    "sg:phone":"+1 919 661 1715",
    "sg:postcode":"27603",
    "sg:province":"NC",
    "wof:name":"Fashion Cents",
    "wof:placetype":"venue"
},
  "geometry": {"coordinates":[-78.657917,35.724768],"type":"Point"}
}