{
  "type": "Feature",
  "properties": {
    "addr:full":"124 College St Asheville NC 28801",
    "addr:housenumber":"124",
    "addr:postcode":"28801",
    "addr:street":"College St",
    "iso:country":"US",
    "sg:address":"124 College St",
    "sg:city":"Asheville",
    "sg:classifiers":[
        {
            "category":"Professional",
            "subcategory":"Art Services",
            "type":"Services"
        },
        {
            "category":"Professional",
            "subcategory":"Computer Services",
            "type":"Services"
        }
    ],
    "sg:phone":"+1 828 252 8577",
    "sg:postcode":"28801",
    "sg:province":"NC",
    "sg:tags":[
        "graphic",
        "datum",
        "designer"
    ],
    "wof:name":"A & M Studio Imaging",
    "wof:placetype":"venue"
},
  "geometry": {"coordinates":[-82.550577,35.595859],"type":"Point"}
}