{
  "type": "Feature",
  "properties": {
    "addr:full":"3037 US Hwy 64 Mocksville NC 27028",
    "addr:housenumber":"3037",
    "addr:postcode":"27028",
    "addr:street":"Us Hwy 64",
    "iso:country":"US",
    "sg:address":"3037 US Hwy 64",
    "sg:city":"Mocksville",
    "sg:classifiers":[
        {
            "category":"Manufacturing",
            "subcategory":"Lumber",
            "type":"Manufacturing & Wholesale Goods"
        }
    ],
    "sg:phone":"+1 336 998 2118",
    "sg:postcode":"27028",
    "sg:province":"NC",
    "sg:tags":[
        "hardwood",
        "mill"
    ],
    "wof:name":"R & D Frames",
    "wof:placetype":"venue"
},
  "geometry": {"coordinates":[-80.664777,35.918766],"type":"Point"}
}