{
  "type": "Feature",
  "properties": {
    "addr:full":"1725 Reed Rd NE Leland NC 28451",
    "addr:housenumber":"1725",
    "addr:postcode":"28451",
    "addr:street":"Reed Rd Ne",
    "iso:country":"US",
    "sg:address":"1725 Reed Rd NE",
    "sg:city":"Leland",
    "sg:classifiers":[
        {
            "category":"Restaurant",
            "type":"Food & Drink"
        }
    ],
    "sg:phone":"+1 910 371 6700",
    "sg:postcode":"28451",
    "sg:province":"NC",
    "wof:name":"Andy's Cheesesteaks & Chsbrgrs",
    "wof:placetype":"venue"
},
  "geometry": {"coordinates":[-78.05694200000001,34.259432],"type":"Point"}
}