{
  "type": "Feature",
  "properties": {
    "addr:full":"103 Sugarloaf Rd Hendersonville NC 28792",
    "addr:housenumber":"103",
    "addr:postcode":"28792",
    "addr:street":"Sugarloaf Rd",
    "iso:country":"US",
    "sg:address":"103 Sugarloaf Rd",
    "sg:city":"Hendersonville",
    "sg:classifiers":[
        {
            "category":"Food & Beverages",
            "subcategory":"Groceries & Convenience Stores",
            "type":"Retail Goods"
        }
    ],
    "sg:phone":"+1 828 692 5611",
    "sg:postcode":"28792",
    "sg:province":"NC",
    "wof:name":"Convenience King 23",
    "wof:placetype":"venue"
},
  "geometry": {"coordinates":[-82.435564,35.343964],"type":"Point"}
}