{
  "type": "Feature",
  "properties": {
    "iso:country":"US",
    "sg:address":"619 Washington St",
    "sg:city":"Washington",
    "sg:classifiers":[
        {
            "category":"Personal",
            "subcategory":"Beauty Salon",
            "type":"Services"
        }
    ],
    "sg:phone":"+1   ",
    "sg:postcode":"27889",
    "sg:province":"NC",
    "sg:tags":[
        "shop"
    ],
    "wof:name":"Rose Nails Inc",
    "wof:placetype":"venue"
},
  "geometry": {"coordinates":[-77.0587,35.552671],"type":"Point"}
}