{
  "type": "Feature",
  "properties": {
    "iso:country":"US",
    "sg:address":"3511 Buena Vista Rd",
    "sg:city":"Winston Salem",
    "sg:classifiers":[
        {
            "category":"Professional",
            "subcategory":"Lawyer & Legal Services",
            "type":"Services"
        }
    ],
    "sg:phone":"+1 336 724 7023",
    "sg:postcode":"27106",
    "sg:province":"NC",
    "sg:tags":[
        "attorney"
    ],
    "wof:name":"William C Meyers",
    "wof:placetype":"venue"
},
  "geometry": {"coordinates":[-80.29455,36.116886],"type":"Point"}
}