{
  "type": "Feature",
  "properties": {
    "addr:full":"1869 Joe Moore Rd Thomasville NC 27360",
    "addr:housenumber":"1869",
    "addr:postcode":"27360",
    "addr:street":"Joe Moore Rd",
    "iso:country":"US",
    "sg:address":"1869 Joe Moore Rd",
    "sg:city":"Thomasville",
    "sg:classifiers":[
        {
            "category":"Professional",
            "subcategory":"Business Services",
            "type":"Services"
        }
    ],
    "sg:phone":"+1   ",
    "sg:postcode":"27360",
    "sg:province":"NC",
    "wof:name":"Vision Design & Development",
    "wof:placetype":"venue"
},
  "geometry": {"coordinates":[-80.075861,35.947454],"type":"Point"}
}