{
  "type": "Feature",
  "properties": {
    "iso:country":"US",
    "sg:address":"1005 Hope Mills Rd",
    "sg:city":"Fayetteville",
    "sg:classifiers":[
        {
            "category":"Home & Garden",
            "subcategory":"Building Materials",
            "type":"Retail Goods"
        }
    ],
    "sg:phone":"+1 910 425 4510",
    "sg:postcode":"28304",
    "sg:province":"NC",
    "sg:tags":[
        "paint"
    ],
    "wof:name":"Cal Tone Paint & Wallpaper Inc",
    "wof:placetype":"venue"
},
  "geometry": {"coordinates":[-78.960904,35.032401],"type":"Point"}
}