{
  "type": "Feature",
  "properties": {
    "addr:full":"2840 Plaza Pl Ste 450 Raleigh NC 27612",
    "addr:housenumber":"2840",
    "addr:postcode":"27612",
    "addr:street":"Plaza Pl Ste 450",
    "iso:country":"US",
    "sg:address":"2840 Plaza Pl Ste 450",
    "sg:city":"Raleigh",
    "sg:classifiers":[
        {
            "category":"Professional",
            "subcategory":"Lawyer & Legal Services",
            "type":"Services"
        }
    ],
    "sg:phone":"+1 919 787 5200",
    "sg:postcode":"27612",
    "sg:province":"NC",
    "wof:name":"Brown Gregory W Atty",
    "wof:placetype":"venue"
},
  "geometry": {"coordinates":[-78.682503,35.857399],"type":"Point"}
}