{
  "type": "Feature",
  "properties": {
    "addr:full":"2100 Commonwealth Ave Charlotte NC 28205",
    "addr:housenumber":"2100",
    "addr:postcode":"28205",
    "addr:street":"Commonwealth Ave",
    "iso:country":"US",
    "sg:address":"2100 Commonwealth Ave",
    "sg:city":"Charlotte",
    "sg:classifiers":[
        {
            "category":"Banks & Credit Unions",
            "subcategory":"Bank",
            "type":"Services"
        }
    ],
    "sg:phone":"+1 704 386 5393",
    "sg:postcode":"28205",
    "sg:province":"NC",
    "sg:tags":[
        "national",
        "commercial"
    ],
    "wof:name":"Bank of America",
    "wof:placetype":"venue"
},
  "geometry": {"coordinates":[-80.80938999999999,35.217375],"type":"Point"}
}