{
  "type": "Feature",
  "properties": {
    "addr:full":"3757 Sandy Ford Rd Hickory NC 28602",
    "addr:housenumber":"3757",
    "addr:postcode":"28602",
    "addr:street":"Sandy Ford Rd",
    "iso:country":"US",
    "sg:address":"3757 Sandy Ford Rd",
    "sg:city":"Hickory",
    "sg:classifiers":[
        {
            "category":"Farming",
            "subcategory":"Nursery",
            "type":"Manufacturing & Wholesale Goods"
        }
    ],
    "sg:phone":"+1 828 294 3950",
    "sg:postcode":"28602",
    "sg:province":"NC",
    "sg:tags":[
        "greenhouse"
    ],
    "wof:name":"Ironwood Estate Orchids",
    "wof:placetype":"venue"
},
  "geometry": {"coordinates":[-81.312945,35.65729],"type":"Point"}
}