{
  "type": "Feature",
  "properties": {
    "addr:full":"134 Circadian Way Chapel Hill NC 27516",
    "addr:housenumber":"134",
    "addr:postcode":"27516",
    "addr:street":"Circadian Way",
    "iso:country":"US",
    "sg:address":"134 Circadian Way",
    "sg:city":"Chapel Hill",
    "sg:classifiers":[
        {
            "category":"Organizations",
            "subcategory":"Professional Association",
            "type":"Services"
        }
    ],
    "sg:phone":"+1 919 960 5007",
    "sg:postcode":"27516",
    "sg:province":"NC",
    "wof:name":"Arcadia Home Owners Assn",
    "wof:placetype":"venue"
},
  "geometry": {"coordinates":[-79.098516,35.938494],"type":"Point"}
}