{
  "type": "Feature",
  "properties": {
    "addr:full":"1040 Cornwallis Rd Teachey NC 28464",
    "addr:housenumber":"1040",
    "addr:postcode":"28464",
    "addr:street":"Cornwallis Rd",
    "iso:country":"US",
    "sg:address":"1040 Cornwallis Rd",
    "sg:city":"Teachey",
    "sg:classifiers":[
        {
            "category":"Farming",
            "subcategory":"Livestock Farm",
            "type":"Manufacturing & Wholesale Goods"
        }
    ],
    "sg:phone":"+1 910 289 2963",
    "sg:postcode":"28464",
    "sg:province":"NC",
    "sg:tags":[
        "animal",
        "general"
    ],
    "wof:name":"Ira D Johnson",
    "wof:placetype":"venue"
},
  "geometry": {"coordinates":[-78.069975,34.779149],"type":"Point"}
}