{
  "type": "Feature",
  "properties": {
    "iso:country":"US",
    "sg:address":"1821 Hillandale Rd",
    "sg:city":"Durham",
    "sg:classifiers":[
        {
            "category":"Banks & Credit Unions",
            "subcategory":"Bank",
            "type":"Services"
        }
    ],
    "sg:phone":"+1 919 383 0321",
    "sg:postcode":"27705",
    "sg:province":"NC",
    "sg:tags":[
        "company",
        "finance"
    ],
    "wof:name":"Wells Fargo",
    "wof:placetype":"venue"
},
  "geometry": {"coordinates":[-78.93583700000001,36.030855],"type":"Point"}
}