{
  "type": "Feature",
  "properties": {
    "addr:full":"2609 Castle Hayne Rd Wilmington NC 28401",
    "addr:housenumber":"2609",
    "addr:postcode":"28401",
    "addr:street":"Castle Hayne Rd",
    "iso:country":"US",
    "sg:address":"2609 Castle Hayne Rd",
    "sg:city":"Wilmington",
    "sg:classifiers":[
        {
            "category":"Autos & Motor Vehicles",
            "subcategory":"Auto Supplies",
            "type":"Retail Goods"
        }
    ],
    "sg:phone":"+1 910 763 3304",
    "sg:postcode":"28401",
    "sg:province":"NC",
    "sg:tags":[
        "automobile",
        "parts"
    ],
    "wof:name":"Advance Auto Parts Inc",
    "wof:placetype":"venue"
},
  "geometry": {"coordinates":[-77.92113000000001,34.290159],"type":"Point"}
}