{
  "type": "Feature",
  "properties": {
    "iso:country":"US",
    "sg:address":"1 Page Ave",
    "sg:city":"Asheville",
    "sg:classifiers":[
        {
            "category":"Organizations",
            "subcategory":"Professional Association",
            "type":"Services"
        }
    ],
    "sg:phone":"+1 828 252 7799",
    "sg:postcode":"28801",
    "sg:province":"NC",
    "sg:tags":[
        "building",
        "operator",
        "business",
        "nonresidential"
    ],
    "wof:name":"Grove ARC Pub Mkt Foundation",
    "wof:placetype":"venue"
},
  "geometry": {"coordinates":[-82.556399,35.596302],"type":"Point"}
}