{
  "type": "Feature",
  "properties": {
    "addr:full":"112 Barbour St Clayton NC 27520",
    "addr:housenumber":"112",
    "addr:postcode":"27520",
    "addr:street":"Barbour St",
    "iso:country":"US",
    "sg:address":"112 Barbour St",
    "sg:city":"Clayton",
    "sg:classifiers":[
        {
            "category":"Building & Trades",
            "subcategory":"Pest Control",
            "type":"Services"
        }
    ],
    "sg:phone":"+1 919 553 9888",
    "sg:postcode":"27520",
    "sg:province":"NC",
    "wof:name":"Neuse Termite & Pest Control",
    "wof:placetype":"venue"
},
  "geometry": {"coordinates":[-78.457857,35.651457],"type":"Point"}
}