{
  "type": "Feature",
  "properties": {
    "iso:country":"US",
    "sg:address":"6633 Lakeside Dr",
    "sg:city":"Charlotte",
    "sg:classifiers":[
        {
            "category":"Social Services",
            "type":"Services"
        }
    ],
    "sg:phone":"+1 704 293 4239",
    "sg:postcode":"28215",
    "sg:province":"NC",
    "sg:tags":[
        "human"
    ],
    "wof:name":"Health Carousel Of The Carolinas, Inc",
    "wof:placetype":"venue"
},
  "geometry": {"coordinates":[-80.725478,35.231257],"type":"Point"}
}