{
  "type": "Feature",
  "properties": {
    "addr:full":"4201 Lake Boone Trl Ste 2 Raleigh NC 27607",
    "addr:housenumber":"4201",
    "addr:postcode":"27607",
    "addr:street":"Lake Boone Trl Ste 2",
    "iso:country":"US",
    "sg:address":"4201 Lake Boone Trl Ste 2",
    "sg:city":"Raleigh",
    "sg:classifiers":[
        {
            "category":"Health Services",
            "subcategory":"Dentist",
            "type":"Services"
        }
    ],
    "sg:phone":"+1 919 787 3949",
    "sg:postcode":"27607",
    "sg:province":"NC",
    "wof:name":"Gaines Roy E Jr Dr",
    "wof:placetype":"venue"
},
  "geometry": {"coordinates":[-78.700104,35.815399],"type":"Point"}
}