{
  "type": "Feature",
  "properties": {
    "addr:full":"901 N Chestnut St Lumberton NC 28358",
    "addr:housenumber":"901",
    "addr:postcode":"28358",
    "addr:street":"N Chestnut St",
    "iso:country":"US",
    "sg:address":"901 N Chestnut St",
    "sg:city":"Lumberton",
    "sg:classifiers":[
        {
            "category":"Health Services",
            "subcategory":"Doctor",
            "type":"Services"
        }
    ],
    "sg:phone":"+1 910 739 1666",
    "sg:postcode":"28358",
    "sg:province":"NC",
    "sg:tags":[
        "physician",
        "surgeon"
    ],
    "wof:name":"Lumberton Health Ctr",
    "wof:placetype":"venue"
},
  "geometry": {"coordinates":[-79.007547,34.623973],"type":"Point"}
}