{
  "type": "Feature",
  "properties": {
    "iso:country":"US",
    "sg:address":"340 Tate St",
    "sg:city":"Greensboro",
    "sg:classifiers":[
        {
            "category":"Shopping",
            "subcategory":"Used Merchandise",
            "type":"Retail Goods"
        }
    ],
    "sg:phone":"+1 336 275 2217",
    "sg:postcode":"27403",
    "sg:province":"NC",
    "wof:name":"House Wine",
    "wof:placetype":"venue"
},
  "geometry": {"coordinates":[-79.805543,36.070373],"type":"Point"}
}