{
  "type": "Feature",
  "properties": {
    "iso:country":"US",
    "sg:address":"3304 S Memorial Dr",
    "sg:city":"Greenville",
    "sg:classifiers":[
        {
            "category":"Travel",
            "subcategory":"Hotels & Motels",
            "type":"Entertainment"
        }
    ],
    "sg:phone":"+1 252 756 7084",
    "sg:postcode":"27834",
    "sg:province":"NC",
    "sg:tags":[
        "operation",
        "lodging"
    ],
    "wof:name":"University Inn",
    "wof:placetype":"venue"
},
  "geometry": {"coordinates":[-77.400322,35.570789],"type":"Point"}
}