{
  "type": "Feature",
  "properties": {
    "iso:country":"US",
    "sg:address":"215 S Main St",
    "sg:city":"Rich Square",
    "sg:classifiers":[
        {
            "category":"Organizations",
            "subcategory":"Religious Organization",
            "type":"Services"
        }
    ],
    "sg:phone":"+1 252 539 4128",
    "sg:postcode":"27869",
    "sg:province":"NC",
    "sg:tags":[
        "church"
    ],
    "wof:name":"Willow Oak AME Church",
    "wof:placetype":"venue"
},
  "geometry": {"coordinates":[-77.290414,36.265687],"type":"Point"}
}