{
  "type": "Feature",
  "properties": {
    "addr:full":"115 Meadow View Ln Timberlake NC 27583",
    "addr:housenumber":"115",
    "addr:postcode":"27583",
    "addr:street":"Meadow View Ln",
    "iso:country":"US",
    "sg:address":"115 Meadow View Ln",
    "sg:city":"Timberlake",
    "sg:classifiers":[
        {
            "category":"Building & Trades",
            "subcategory":"Construction",
            "type":"Services"
        }
    ],
    "sg:phone":"+1 336 364 1281",
    "sg:postcode":"27583",
    "sg:province":"NC",
    "sg:tags":[
        "masonry",
        "contractor"
    ],
    "wof:name":"Service Masonry Inc",
    "wof:placetype":"venue"
},
  "geometry": {"coordinates":[-78.935016,36.307079],"type":"Point"}
}