{
  "type": "Feature",
  "properties": {
    "iso:country":"US",
    "sg:address":"1951 Clark Ave",
    "sg:city":"Raleigh",
    "sg:classifiers":[
        {
            "category":"Professional",
            "subcategory":"Business Services",
            "type":"Services"
        }
    ],
    "sg:phone":"+1 919 828 2501",
    "sg:postcode":"27605",
    "sg:province":"NC",
    "sg:tags":[
        "holding"
    ],
    "wof:name":"Icon Media Holdings",
    "wof:placetype":"venue"
},
  "geometry": {"coordinates":[-78.65751899999999,35.789055],"type":"Point"}
}