{
  "type": "Feature",
  "properties": {
    "addr:full":"8400 Fairview Rd Charlotte NC 28226",
    "addr:housenumber":"8400",
    "addr:postcode":"28226",
    "addr:street":"Fairview Rd",
    "iso:country":"US",
    "sg:address":"8400 Fairview Rd",
    "sg:city":"Charlotte",
    "sg:classifiers":[
        {
            "category":"Recreation",
            "type":"Entertainment"
        }
    ],
    "sg:phone":"+1 704 573 2155",
    "sg:postcode":"28226",
    "sg:province":"NC",
    "sg:tags":[
        "parlor",
        "billiard"
    ],
    "wof:name":"Sharky's Bar & Billiards",
    "wof:placetype":"venue"
},
  "geometry": {"coordinates":[-80.799927,35.150103],"type":"Point"}
}