{
  "type": "Feature",
  "properties": {
    "addr:full":"1240 E Main St Albemarle NC 28001",
    "addr:housenumber":"1240",
    "addr:postcode":"28001",
    "addr:street":"E Main St",
    "iso:country":"US",
    "sg:address":"1240 E Main St",
    "sg:city":"Albemarle",
    "sg:classifiers":[
        {
            "category":"Recreation",
            "type":"Entertainment"
        }
    ],
    "sg:phone":"+1   ",
    "sg:postcode":"28001",
    "sg:province":"NC",
    "wof:name":"Good Ode Putto Golf Course",
    "wof:placetype":"venue"
},
  "geometry": {"coordinates":[-80.1797,35.352468],"type":"Point"}
}