{
  "type": "Feature",
  "properties": {
    "addr:full":"630 Edgewater Club Rd Wilmington NC 28411",
    "addr:housenumber":"630",
    "addr:postcode":"28411",
    "addr:street":"Edgewater Club Rd",
    "iso:country":"US",
    "sg:address":"630 Edgewater Club Rd",
    "sg:city":"Wilmington",
    "sg:classifiers":[
        {
            "category":"Building & Trades",
            "subcategory":"Construction",
            "type":"Services"
        }
    ],
    "sg:phone":"+1 910 686 0242",
    "sg:postcode":"28411",
    "sg:province":"NC",
    "sg:tags":[
        "contractor"
    ],
    "wof:name":"R-3 Inc",
    "wof:placetype":"venue"
},
  "geometry": {"coordinates":[-77.77145299999999,34.282299],"type":"Point"}
}