{
  "type": "Feature",
  "properties": {
    "iso:country":"US",
    "sg:address":"836 Dabney Dr",
    "sg:city":"Henderson",
    "sg:classifiers":[
        {
            "category":"Shopping",
            "subcategory":"Clothing, Apparel, & Fashions",
            "type":"Retail Goods"
        }
    ],
    "sg:phone":"+1 252 430 6167",
    "sg:postcode":"27536",
    "sg:province":"NC",
    "sg:tags":[
        "shop",
        "bridal"
    ],
    "wof:name":"Glory & Aundray Fashions",
    "wof:placetype":"venue"
},
  "geometry": {"coordinates":[-78.425963,36.328109],"type":"Point"}
}