{
  "type": "Feature",
  "properties": {
    "iso:country":"US",
    "sg:address":"3035 Surl Mount Tirzah Rd",
    "sg:city":"Timberlake",
    "sg:classifiers":[
        {
            "category":"Place Of Worship",
            "subcategory":"Church",
            "type":"Public Place"
        },
        {
            "category":"Place Of Worship",
            "type":"Public Place"
        }
    ],
    "sg:phone":"+1 336 364 8389",
    "sg:postcode":"27583",
    "sg:province":"NC",
    "sg:tags":[
        "churches-baptist-general",
        "churches-baptist"
    ],
    "wof:name":"Timberlake Baptist Church",
    "wof:placetype":"venue"
},
  "geometry": {"coordinates":[-78.89959,36.300679],"type":"Point"}
}