{
  "type": "Feature",
  "properties": {
    "addr:full":"345 N Depot St Albemarle NC 28001",
    "addr:housenumber":"345",
    "addr:postcode":"28001",
    "addr:street":"N Depot St",
    "iso:country":"US",
    "sg:address":"345 N Depot St",
    "sg:city":"Albemarle",
    "sg:classifiers":[
        {
            "category":"Real Estate",
            "subcategory":"Real Estate Operator",
            "type":"Services"
        }
    ],
    "sg:phone":"+1 704 986 6800",
    "sg:postcode":"28001",
    "sg:province":"NC",
    "sg:tags":[
        "property",
        "lessor"
    ],
    "wof:name":"McCoys Reality",
    "wof:placetype":"venue"
},
  "geometry": {"coordinates":[-80.201308,35.355494],"type":"Point"}
}