{
  "type": "Feature",
  "properties": {
    "iso:country":"US",
    "sg:address":"1007 Woodland Dr NW",
    "sg:city":"Wilson",
    "sg:phone":"+1 252 243 2326",
    "sg:postcode":"27893",
    "sg:province":"NC",
    "sg:tags":[
        "farm",
        "chicken",
        "soybean",
        "corn",
        "tobacco"
    ],
    "wof:name":"Ellis A K Farm",
    "wof:placetype":"venue"
},
  "geometry": {"coordinates":[-77.932351,35.736513],"type":"Point"}
}