{
  "type": "Feature",
  "properties": {
    "addr:full":"4021 Stirrup Creek Dr Durham NC 27703",
    "addr:housenumber":"4021",
    "addr:postcode":"27703",
    "addr:street":"Stirrup Creek Dr",
    "iso:country":"US",
    "sg:address":"4021 Stirrup Creek Dr",
    "sg:city":"Durham",
    "sg:classifiers":[
        {
            "category":"Professional",
            "subcategory":"Computer Services",
            "type":"Services"
        }
    ],
    "sg:phone":"+1 919 361 8090",
    "sg:postcode":"27703",
    "sg:province":"NC",
    "sg:tags":[
        "repair"
    ],
    "sg:website":"www.micromedic.com",
    "wof:name":"Micro Medic",
    "wof:placetype":"venue"
},
  "geometry": {"coordinates":[-78.849441,35.91858],"type":"Point"}
}