{
  "type": "Feature",
  "properties": {
    "iso:country":"US",
    "sg:address":"22 E 3rd St",
    "sg:city":"Wendell",
    "sg:classifiers":[
        {
            "category":"Personal",
            "subcategory":"Beauty Salon",
            "type":"Services"
        }
    ],
    "sg:phone":"+1 919 366 1553",
    "sg:postcode":"27591",
    "sg:province":"NC",
    "wof:name":"Heads Up Beauty Salon",
    "wof:placetype":"venue"
},
  "geometry": {"coordinates":[-78.369609,35.780951],"type":"Point"}
}