{
  "type": "Feature",
  "properties": {
    "iso:country":"US",
    "sg:address":"621 E Marion St",
    "sg:city":"Shelby",
    "sg:classifiers":[
        {
            "category":"Building & Trades",
            "subcategory":"Construction",
            "type":"Services"
        }
    ],
    "sg:phone":"+1 704 484 3845",
    "sg:postcode":"28150",
    "sg:province":"NC",
    "sg:tags":[
        "coping",
        "plastering",
        "tiling",
        "pool",
        "swimming"
    ],
    "wof:name":"Roger's Pool Svc & Repair Co",
    "wof:placetype":"venue"
},
  "geometry": {"coordinates":[-81.527766,35.294432],"type":"Point"}
}