{
  "type": "Feature",
  "properties": {
    "addr:full":"1000 Stanley Dr Concord NC 28027",
    "addr:housenumber":"1000",
    "addr:postcode":"28027",
    "addr:street":"Stanley Dr",
    "iso:country":"US",
    "sg:address":"1000 Stanley Dr",
    "sg:city":"Concord",
    "sg:classifiers":[
        {
            "category":"Manufacturing",
            "subcategory":"Metals",
            "type":"Manufacturing & Wholesale Goods"
        }
    ],
    "sg:phone":"+1 704 789 7000",
    "sg:postcode":"28027",
    "sg:province":"NC",
    "sg:tags":[
        "hardware",
        "tool",
        "mfg"
    ],
    "wof:name":"Stanley Works Inc",
    "wof:placetype":"venue"
},
  "geometry": {"coordinates":[-80.667941,35.437665],"type":"Point"}
}