{
  "type": "Feature",
  "properties": {
    "addr:full":"1350 S Kings Dr Fl 2 Charlotte NC 28207",
    "addr:housenumber":"1350;2",
    "addr:postcode":"28207",
    "addr:street":"S Kings Dr",
    "iso:country":"US",
    "sg:address":"1350 S Kings Dr Fl 2",
    "sg:city":"Charlotte",
    "sg:classifiers":[
        {
            "category":"Health Services",
            "subcategory":"Clinic",
            "type":"Services"
        }
    ],
    "sg:phone":"+1 704 446 1422",
    "sg:postcode":"28207",
    "sg:province":"NC",
    "sg:tags":[
        "outpatient"
    ],
    "wof:name":"Pediatrics Dept",
    "wof:placetype":"venue"
},
  "geometry": {"coordinates":[-80.83676,35.196211],"type":"Point"}
}