{
  "type": "Feature",
  "properties": {
    "addr:full":"702 S 13th St Erwin NC 28339",
    "addr:housenumber":"702",
    "addr:postcode":"28339",
    "addr:street":"S 13Th St",
    "iso:country":"US",
    "sg:address":"702 S 13th St",
    "sg:city":"Erwin",
    "sg:classifiers":[
        {
            "category":"Manufacturing",
            "subcategory":"Printing",
            "type":"Manufacturing & Wholesale Goods"
        }
    ],
    "sg:phone":"+1 910 897 4076",
    "sg:postcode":"28339",
    "sg:province":"NC",
    "sg:tags":[
        "newspaper"
    ],
    "wof:name":"Community Leader",
    "wof:placetype":"venue"
},
  "geometry": {"coordinates":[-78.676081,35.32166],"type":"Point"}
}