{
  "type": "Feature",
  "properties": {
    "iso:country":"US",
    "sg:address":"49729 Glenmore Rd",
    "sg:city":"Gold Hill",
    "sg:classifiers":[
        {
            "category":"Freight",
            "type":"Transportation"
        }
    ],
    "sg:phone":"+1 704 463 1846",
    "sg:postcode":"28071",
    "sg:province":"NC",
    "sg:tags":[
        "operator",
        "local",
        "trucking"
    ],
    "wof:name":"Harvey Lee Smith Sr",
    "wof:placetype":"venue"
},
  "geometry": {"coordinates":[-80.29678199999999,35.486008],"type":"Point"}
}