{
  "type": "Feature",
  "properties": {
    "iso:country":"US",
    "sg:address":"1813 US Hwy 601",
    "sg:city":"Mocksville",
    "sg:classifiers":[
        {
            "category":"Organizations",
            "subcategory":"Religious Organization",
            "type":"Services"
        }
    ],
    "sg:phone":"+1 336 751 2435",
    "sg:postcode":"27028",
    "sg:province":"NC",
    "sg:tags":[
        "church"
    ],
    "wof:name":"Union Chapel Chestnut Grove",
    "wof:placetype":"venue"
},
  "geometry": {"coordinates":[-80.549223,35.855434],"type":"Point"}
}