{
  "type": "Feature",
  "properties": {
    "iso:country":"US",
    "sg:address":"1441 N Fayetteville St",
    "sg:city":"Asheboro",
    "sg:classifiers":[
        {
            "category":"Building & Trades",
            "subcategory":"Cleaning & Sanitation",
            "type":"Services"
        }
    ],
    "sg:phone":"+1 336 626 4527",
    "sg:postcode":"27203",
    "sg:province":"NC",
    "sg:tags":[
        "refrigeration",
        "maintenance"
    ],
    "wof:name":"A1 Chimney Service",
    "wof:placetype":"venue"
},
  "geometry": {"coordinates":[-79.808367,35.734023],"type":"Point"}
}