{
  "type": "Feature",
  "properties": {
    "iso:country":"US",
    "sg:address":"306 S Main St",
    "sg:city":"Kernersville",
    "sg:classifiers":[
        {
            "category":"Organizations",
            "subcategory":"Religious Organization",
            "type":"Services"
        }
    ],
    "sg:phone":"+1 336 993 3411",
    "sg:postcode":"27284",
    "sg:province":"NC",
    "sg:tags":[
        "church"
    ],
    "wof:name":"Main Street United Methodist",
    "wof:placetype":"venue"
},
  "geometry": {"coordinates":[-80.076717,36.117089],"type":"Point"}
}