{
  "type": "Feature",
  "properties": {
    "addr:full":"3500 Bush St Raleigh NC 27609",
    "addr:housenumber":"3500",
    "addr:postcode":"27609",
    "addr:street":"Bush St",
    "iso:country":"US",
    "sg:address":"3500 Bush St",
    "sg:city":"Raleigh",
    "sg:classifiers":[
        {
            "category":"Health Services",
            "subcategory":"Doctor",
            "type":"Services"
        }
    ],
    "sg:phone":"+1 919 875 8150",
    "sg:postcode":"27609",
    "sg:province":"NC",
    "sg:tags":[
        "physician",
        "family",
        "practice",
        "surgeons",
        "medicine",
        "surgeon"
    ],
    "sg:website":"http://www.fmaraleigh.com",
    "wof:name":"Family Medical Associates Of Raleigh",
    "wof:placetype":"venue"
},
  "geometry": {"coordinates":[-78.612619,35.829436],"type":"Point"}
}