{
  "type": "Feature",
  "properties": {
    "addr:full":"1328 N Lake Park Blvd Carolina Beach NC 28428",
    "addr:housenumber":"1328",
    "addr:postcode":"28428",
    "addr:street":"N Lake Park Blvd",
    "iso:country":"US",
    "sg:address":"1328 N Lake Park Blvd",
    "sg:city":"Carolina Beach",
    "sg:classifiers":[
        {
            "category":"Building & Trades",
            "subcategory":"Construction",
            "type":"Services"
        }
    ],
    "sg:phone":"+1 910 458 7707",
    "sg:postcode":"28428",
    "sg:province":"NC",
    "sg:tags":[
        "general",
        "contractor"
    ],
    "wof:name":"Saieed Construction Systems",
    "wof:placetype":"venue"
},
  "geometry": {"coordinates":[-77.899412,34.047288],"type":"Point"}
}