{
  "type": "Feature",
  "properties": {
    "iso:country":"US",
    "sg:address":"1907 S 17th St",
    "sg:city":"Wilmington",
    "sg:classifiers":[
        {
            "category":"Health Services",
            "subcategory":"Doctor",
            "type":"Services"
        }
    ],
    "sg:phone":"+1 910 343 8424",
    "sg:postcode":"28401",
    "sg:province":"NC",
    "sg:tags":[
        "physician",
        "surgeon"
    ],
    "wof:name":"Trinity Wellness Ctr",
    "wof:placetype":"venue"
},
  "geometry": {"coordinates":[-77.924949,34.213246],"type":"Point"}
}