{
  "type": "Feature",
  "properties": {
    "iso:country":"US",
    "sg:address":"100 Preston Dr",
    "sg:city":"Jacksonville",
    "sg:classifiers":[
        {
            "category":"Home & Garden",
            "subcategory":"Building Materials",
            "type":"Retail Goods"
        }
    ],
    "sg:phone":"+1 910 346 3791",
    "sg:postcode":"28540",
    "sg:province":"NC",
    "wof:name":"Stelian Glass Crafts LLC",
    "wof:placetype":"venue"
},
  "geometry": {"coordinates":[-77.466416,34.739871],"type":"Point"}
}