{
  "type": "Feature",
  "properties": {
    "addr:full":"7273 E Holly Grove Rd Thomasville NC 27360",
    "addr:housenumber":"7273",
    "addr:postcode":"27360",
    "addr:street":"E Holly Grove Rd",
    "iso:country":"US",
    "sg:address":"7273 E Holly Grove Rd",
    "sg:city":"Thomasville",
    "sg:classifiers":[
        {
            "category":"Building & Trades",
            "subcategory":"Construction",
            "type":"Services"
        }
    ],
    "sg:phone":"+1 336 476 6879",
    "sg:postcode":"27360",
    "sg:province":"NC",
    "sg:tags":[
        "residence",
        "family",
        "contractor"
    ],
    "wof:name":"Lloyd Hepler Construction",
    "wof:placetype":"venue"
},
  "geometry": {"coordinates":[-80.113118,35.836743],"type":"Point"}
}