{
  "type": "Feature",
  "properties": {
    "iso:country":"US",
    "sg:address":"302 Main St",
    "sg:city":"Pollocksville",
    "sg:classifiers":[
        {
            "category":"Restaurant",
            "type":"Food & Drink"
        }
    ],
    "sg:phone":"+1 252 224 1144",
    "sg:postcode":"28573",
    "sg:province":"NC",
    "wof:name":"Riverwalk Deli & Grill",
    "wof:placetype":"venue"
},
  "geometry": {"coordinates":[-77.221113,35.005854],"type":"Point"}
}