{
  "type": "Feature",
  "properties": {
    "iso:country":"US",
    "sg:address":"1443 Scronce Rd",
    "sg:city":"Harrells",
    "sg:classifiers":[
        {
            "category":"Farming",
            "subcategory":"Farm",
            "type":"Manufacturing & Wholesale Goods"
        }
    ],
    "sg:phone":"+1 910 532 4544",
    "sg:postcode":"28444",
    "sg:province":"NC",
    "wof:name":"J & K Farms Inc",
    "wof:placetype":"venue"
},
  "geometry": {"coordinates":[-78.292981,34.698943],"type":"Point"}
}