{
  "type": "Feature",
  "properties": {
    "iso:country":"US",
    "sg:address":"1578 Philadelphus Rd",
    "sg:city":"Pembroke",
    "sg:classifiers":[
        {
            "category":"Food & Beverages",
            "subcategory":"Groceries & Convenience Stores",
            "type":"Retail Goods"
        }
    ],
    "sg:phone":"+1 910 521 7643",
    "sg:postcode":"28372",
    "sg:province":"NC",
    "wof:name":"Callies Cnvnence Str Groceries",
    "wof:placetype":"venue"
},
  "geometry": {"coordinates":[-79.178687,34.719831],"type":"Point"}
}