{
  "type": "Feature",
  "properties": {
    "addr:full":"9 Broadway St Asheville NC 28801",
    "addr:housenumber":"9",
    "addr:postcode":"28801",
    "addr:street":"Broadway St",
    "iso:country":"US",
    "sg:address":"9 Broadway St",
    "sg:city":"Asheville",
    "sg:classifiers":[
        {
            "category":"Manufacturing",
            "subcategory":"Printing",
            "type":"Manufacturing & Wholesale Goods"
        }
    ],
    "sg:phone":"+1 828 252 2252",
    "sg:postcode":"28801",
    "sg:province":"NC",
    "sg:tags":[
        "print",
        "photocopying",
        "lithographic",
        "business"
    ],
    "wof:name":"Graphics Four",
    "wof:placetype":"venue"
},
  "geometry": {"coordinates":[-82.552108,35.595963],"type":"Point"}
}