{
  "type": "Feature",
  "properties": {
    "iso:country":"US",
    "sg:address":"3625 Banks Rd",
    "sg:city":"Raleigh",
    "sg:classifiers":[
        {
            "category":"Manufacturing",
            "subcategory":"Petroleum Products",
            "type":"Manufacturing & Wholesale Goods"
        }
    ],
    "sg:phone":"+1 919 772 6789",
    "sg:postcode":"27603",
    "sg:province":"NC",
    "sg:tags":[
        "asphalt",
        "mfg"
    ],
    "wof:name":"S T Wooten Corporation",
    "wof:placetype":"venue"
},
  "geometry": {"coordinates":[-78.709301,35.635205],"type":"Point"}
}