{
  "type": "Feature",
  "properties": {
    "iso:country":"US",
    "sg:address":"1405 Welborn St",
    "sg:city":"High Point",
    "sg:classifiers":[
        {
            "category":"Manufacturing",
            "subcategory":"Furniture",
            "type":"Manufacturing & Wholesale Goods"
        }
    ],
    "sg:phone":"+1 336 887 9141",
    "sg:postcode":"27262",
    "sg:province":"NC",
    "wof:name":"Dowdy/Gillispie Sales Inc",
    "wof:placetype":"venue"
},
  "geometry": {"coordinates":[-80.01769299999999,35.975588],"type":"Point"}
}