{
  "type": "Feature",
  "properties": {
    "addr:full":"6809 Fishers Farm Ln Charlotte NC 28277",
    "addr:housenumber":"6809",
    "addr:postcode":"28277",
    "addr:street":"Fishers Farm Ln",
    "iso:country":"US",
    "sg:address":"6809 Fishers Farm Ln",
    "sg:city":"Charlotte",
    "sg:classifiers":[
        {
            "category":"Shopping",
            "type":"Retail Goods"
        },
        {
            "category":"Shopping",
            "subcategory":"Pharmacy",
            "type":"Retail Goods"
        }
    ],
    "sg:phone":"+1 704 301 3016",
    "sg:postcode":"28277",
    "sg:province":"NC",
    "sg:tags":[
        "aid",
        "first",
        "merchandise",
        "supply"
    ],
    "wof:name":"Carolina First Aid & Safety",
    "wof:placetype":"venue"
},
  "geometry": {"coordinates":[-80.834079,35.081744],"type":"Point"}
}