{
  "type": "Feature",
  "properties": {
    "iso:country":"US",
    "sg:address":"4850 Old Pineville Rd # A",
    "sg:city":"Charlotte",
    "sg:classifiers":[
        {
            "category":"Home & Garden",
            "subcategory":"Building Materials",
            "type":"Retail Goods"
        },
        {
            "category":"Building & Trades",
            "subcategory":"Construction",
            "type":"Services"
        }
    ],
    "sg:phone":"+1 704 523 6882",
    "sg:postcode":"28217",
    "sg:province":"NC",
    "sg:tags":[
        "concrete",
        "staining",
        "contractor"
    ],
    "wof:name":"Charter Concrete",
    "wof:placetype":"venue"
},
  "geometry": {"coordinates":[-80.879041,35.174879],"type":"Point"}
}