{
  "type": "Feature",
  "properties": {
    "iso:country":"US",
    "sg:address":"126 Sheridan Dr",
    "sg:city":"Goldsboro",
    "sg:classifiers":[
        {
            "category":"Organizations",
            "subcategory":"Religious Organization",
            "type":"Services"
        }
    ],
    "sg:phone":"+1   ",
    "sg:postcode":"27534",
    "sg:province":"NC",
    "wof:name":"Church",
    "wof:placetype":"venue"
},
  "geometry": {"coordinates":[-77.93646200000001,35.338099],"type":"Point"}
}