{
  "type": "Feature",
  "properties": {
    "iso:country":"US",
    "sg:address":"207 E State St",
    "sg:city":"Black Mountain",
    "sg:classifiers":[
        {
            "category":"Professional",
            "subcategory":"Lawyer & Legal Services",
            "type":"Services"
        }
    ],
    "sg:phone":"+1 828 669 0799",
    "sg:postcode":"28711",
    "sg:province":"NC",
    "sg:tags":[
        "attorney"
    ],
    "wof:name":"Wendy A Craig Pa",
    "wof:placetype":"venue"
},
  "geometry": {"coordinates":[-82.31945399999999,35.619036],"type":"Point"}
}