{
  "type": "Feature",
  "properties": {
    "iso:country":"US",
    "sg:address":"1919 Carolina Beach Rd",
    "sg:city":"Wilmington",
    "sg:classifiers":[
        {
            "category":"Social Services",
            "type":"Services"
        }
    ],
    "sg:phone":"+1 910 232 5324",
    "sg:postcode":"28401",
    "sg:province":"NC",
    "sg:tags":[
        "professional",
        "counselor"
    ],
    "wof:name":"International Lets Play-Grow",
    "wof:placetype":"venue"
},
  "geometry": {"coordinates":[-77.94378,34.208221],"type":"Point"}
}