{
  "type": "Feature",
  "properties": {
    "addr:full":"833 Bragg Blvd Fayetteville NC 28301",
    "addr:housenumber":"833",
    "addr:postcode":"28301",
    "addr:street":"Bragg Blvd",
    "iso:country":"US",
    "sg:address":"833 Bragg Blvd",
    "sg:city":"Fayetteville",
    "sg:classifiers":[
        {
            "category":"Wholesale",
            "subcategory":"Auto Parts",
            "type":"Manufacturing & Wholesale Goods"
        }
    ],
    "sg:phone":"+1 910 321 9484",
    "sg:postcode":"28301",
    "sg:province":"NC",
    "sg:tags":[
        "automobile",
        "stereo",
        "radio",
        "system"
    ],
    "wof:name":"Sound Solutions",
    "wof:placetype":"venue"
},
  "geometry": {"coordinates":[-78.892894,35.063166],"type":"Point"}
}