{
  "type": "Feature",
  "properties": {
    "iso:country":"US",
    "sg:address":"714 Greenville Blvd SE",
    "sg:city":"Greenville",
    "sg:classifiers":[
        {
            "category":"Shopping",
            "type":"Retail Goods"
        }
    ],
    "sg:phone":"+1 252 353 1490",
    "sg:postcode":"27858",
    "sg:province":"NC",
    "sg:tags":[
        "cosmetic",
        "perfume"
    ],
    "wof:name":"Bath & Body Works Inc",
    "wof:placetype":"venue"
},
  "geometry": {"coordinates":[-77.369388,35.587113],"type":"Point"}
}