{
  "type": "Feature",
  "properties": {
    "addr:full":"210 E Arlington Blvd Greenville NC 27858",
    "addr:housenumber":"210",
    "addr:postcode":"27858",
    "addr:street":"E Arlington Blvd",
    "iso:country":"US",
    "sg:address":"210 E Arlington Blvd",
    "sg:city":"Greenville",
    "sg:classifiers":[
        {
            "category":"Health Services",
            "subcategory":"Clinic",
            "type":"Services"
        }
    ],
    "sg:phone":"+1   ",
    "sg:postcode":"27858",
    "sg:province":"NC",
    "sg:tags":[
        "loss",
        "weight"
    ],
    "wof:name":"Nutri Systems",
    "wof:placetype":"venue"
},
  "geometry": {"coordinates":[-77.374617,35.588486],"type":"Point"}
}