{
  "type": "Feature",
  "properties": {
    "iso:country":"US",
    "sg:address":"1698 US Hwy 17",
    "sg:city":"Little River",
    "sg:classifiers":[
        {
            "category":"Restaurant",
            "type":"Food & Drink"
        }
    ],
    "sg:phone":"+1 843 280 8880",
    "sg:postcode":"29566",
    "sg:province":"SC",
    "wof:name":"Pizzeli's Italian Oven",
    "wof:placetype":"venue"
},
  "geometry": {"coordinates":[-78.612296,33.877123],"type":"Point"}
}