{
  "type": "Feature",
  "properties": {
    "iso:country":"US",
    "sg:address":"143 Malibu Rd",
    "sg:city":"Mooresville",
    "sg:classifiers":[
        {
            "category":"Professional",
            "subcategory":"Business Services",
            "type":"Services"
        }
    ],
    "sg:phone":"+1   ",
    "sg:postcode":"28117",
    "sg:province":"NC",
    "wof:name":"Infragenix LLC",
    "wof:placetype":"venue"
},
  "geometry": {"coordinates":[-80.87553,35.555217],"type":"Point"}
}