{
  "type": "Feature",
  "properties": {
    "iso:country":"US",
    "sg:address":"1270 Old Whiteville Rd",
    "sg:city":"Lumberton",
    "sg:classifiers":[
        {
            "category":"Personal",
            "subcategory":"Beauty Salon",
            "type":"Services"
        }
    ],
    "sg:phone":"+1 910 738 1666",
    "sg:postcode":"28358",
    "sg:province":"NC",
    "sg:tags":[
        "manicuring"
    ],
    "wof:name":"Fabulous Nails",
    "wof:placetype":"venue"
},
  "geometry": {"coordinates":[-78.971312,34.598312],"type":"Point"}
}