{
  "type": "Feature",
  "properties": {
    "iso:country":"US",
    "sg:address":"511 N Raleigh St",
    "sg:city":"Angier",
    "sg:classifiers":[
        {
            "category":"Health Services",
            "subcategory":"Doctor",
            "type":"Services"
        }
    ],
    "sg:phone":"+1 919 639 9001",
    "sg:postcode":"27501",
    "sg:province":"NC",
    "sg:tags":[
        "medical"
    ],
    "wof:name":"Universal Family Health",
    "wof:placetype":"venue"
},
  "geometry": {"coordinates":[-78.74083899999999,35.513597],"type":"Point"}
}