{
  "type": "Feature",
  "properties": {
    "addr:full":"301 Brookstown Ave SW Winston Salem NC 27101",
    "addr:housenumber":"301",
    "addr:postcode":"27101",
    "addr:street":"Brookstown Ave Sw",
    "iso:country":"US",
    "sg:address":"301 Brookstown Ave SW",
    "sg:city":"Winston Salem",
    "sg:classifiers":[
        {
            "category":"Personal",
            "subcategory":"Beauty Salon",
            "type":"Services"
        }
    ],
    "sg:phone":"+1 336 631 8400",
    "sg:postcode":"27101",
    "sg:province":"NC",
    "sg:tags":[
        "shop",
        "barber"
    ],
    "wof:name":"Strands Brookstown Salon Inc",
    "wof:placetype":"venue"
},
  "geometry": {"coordinates":[-80.24614099999999,36.090788],"type":"Point"}
}