{
  "type": "Feature",
  "properties": {
    "iso:country":"US",
    "sg:address":"105 Harrison Ln",
    "sg:city":"Gastonia",
    "sg:classifiers":[
        {
            "category":"Professional",
            "subcategory":"Business Services",
            "type":"Services"
        }
    ],
    "sg:phone":"+1   ",
    "sg:postcode":"28056",
    "sg:province":"NC",
    "wof:name":"J T Kwik Kerb",
    "wof:placetype":"venue"
},
  "geometry": {"coordinates":[-81.074321,35.201877],"type":"Point"}
}