{
  "type": "Feature",
  "properties": {
    "iso:country":"US",
    "sg:address":"7870 Barfield Dr",
    "sg:city":"Fayetteville",
    "sg:classifiers":[
        {
            "category":"Retail",
            "subcategory":"Auto Repair",
            "type":"Services"
        }
    ],
    "sg:phone":"+1   ",
    "sg:postcode":"28314",
    "sg:province":"NC",
    "sg:tags":[
        "automotive"
    ],
    "wof:name":"On Spot Oil Change",
    "wof:placetype":"venue"
},
  "geometry": {"coordinates":[-79.06408999999999,35.037038],"type":"Point"}
}