{
  "type": "Feature",
  "properties": {
    "iso:country":"US",
    "sg:address":"150 W High Ave",
    "sg:city":"High Point",
    "sg:classifiers":[
        {
            "category":"Home & Garden",
            "subcategory":"Furniture",
            "type":"Retail Goods"
        }
    ],
    "sg:phone":"+1 336 885 6505",
    "sg:postcode":"27260",
    "sg:province":"NC",
    "wof:name":"Legends Furniture Inc",
    "wof:placetype":"venue"
},
  "geometry": {"coordinates":[-80.007221,35.956719],"type":"Point"}
}