{
  "type": "Feature",
  "properties": {
    "addr:full":"1945 Fordham Dr Fayetteville NC 28304",
    "addr:housenumber":"1945",
    "addr:postcode":"28304",
    "addr:street":"Fordham Dr",
    "iso:country":"US",
    "sg:address":"1945 Fordham Dr",
    "sg:city":"Fayetteville",
    "sg:classifiers":[
        {
            "category":"Building & Trades",
            "subcategory":"Landscaping Services",
            "type":"Services"
        }
    ],
    "sg:phone":"+1 910 484 6735",
    "sg:postcode":"28304",
    "sg:province":"NC",
    "sg:tags":[
        "landscape",
        "contractor"
    ],
    "wof:name":"Dark Branch Landscaping",
    "wof:placetype":"venue"
},
  "geometry": {"coordinates":[-78.919033,35.037655],"type":"Point"}
}