{
  "type": "Feature",
  "properties": {
    "addr:full":"1489 Old US Hwy 70 W Clayton NC 27520",
    "addr:housenumber":"1489",
    "addr:postcode":"27520",
    "addr:street":"Old Us Hwy 70 W",
    "iso:country":"US",
    "sg:address":"1489 Old US Hwy 70 W",
    "sg:city":"Clayton",
    "sg:classifiers":[
        {
            "category":"Professional",
            "type":"Services"
        }
    ],
    "sg:phone":"+1 919 359 1684",
    "sg:postcode":"27520",
    "sg:province":"NC",
    "sg:tags":[
        "establishment"
    ],
    "wof:name":"Big Plan Production",
    "wof:placetype":"venue"
},
  "geometry": {"coordinates":[-78.476302,35.668446],"type":"Point"}
}