{
  "type": "Feature",
  "properties": {
    "addr:full":"3121 Woodgreen Dr Raleigh NC 27607",
    "addr:housenumber":"3121",
    "addr:postcode":"27607",
    "addr:street":"Woodgreen Dr",
    "iso:country":"US",
    "sg:address":"3121 Woodgreen Dr",
    "sg:city":"Raleigh",
    "sg:classifiers":[
        {
            "category":"Restaurant",
            "type":"Food & Drink"
        }
    ],
    "sg:phone":"+1 919 781 2554",
    "sg:postcode":"27607",
    "sg:province":"NC",
    "sg:tags":[
        "eating"
    ],
    "wof:name":"S Fil Stidham",
    "wof:placetype":"venue"
},
  "geometry": {"coordinates":[-78.676518,35.813113],"type":"Point"}
}