{
  "type": "Feature",
  "properties": {
    "addr:full":"124 Georgia Belle Ave Belmont NC 28012",
    "addr:housenumber":"124",
    "addr:postcode":"28012",
    "addr:street":"Georgia Belle Ave",
    "iso:country":"US",
    "sg:address":"124 Georgia Belle Ave",
    "sg:city":"Belmont",
    "sg:classifiers":[
        {
            "category":"Organizations",
            "subcategory":"Religious Organization",
            "type":"Services"
        }
    ],
    "sg:phone":"+1 704 829 1091",
    "sg:postcode":"28012",
    "sg:province":"NC",
    "sg:tags":[
        "church"
    ],
    "wof:name":"Grace Korean Chr Assembly-God",
    "wof:placetype":"venue"
},
  "geometry": {"coordinates":[-81.05972,35.252499],"type":"Point"}
}