{
  "type": "Feature",
  "properties": {
    "addr:full":"222 W Hill St Warsaw NC 28398",
    "addr:housenumber":"222",
    "addr:postcode":"28398",
    "addr:street":"W Hill St",
    "iso:country":"US",
    "sg:address":"222 W Hill St",
    "sg:city":"Warsaw",
    "sg:classifiers":[
        {
            "category":"Organizations",
            "subcategory":"Non-profit Organization",
            "type":"Services"
        }
    ],
    "sg:phone":"+1 910 293 3206",
    "sg:postcode":"28398",
    "sg:province":"NC",
    "wof:name":"Sarah's Refuge Inc",
    "wof:placetype":"venue"
},
  "geometry": {"coordinates":[-78.095834,35.000465],"type":"Point"}
}