{
  "type": "Feature",
  "properties": {
    "iso:country":"US",
    "sg:address":"8325 Stryker Ct",
    "sg:city":"Raleigh",
    "sg:classifiers":[
        {
            "category":"Utilities",
            "subcategory":"Cable",
            "type":"Services"
        }
    ],
    "sg:phone":"+1 919 848 1274",
    "sg:postcode":"27615",
    "sg:province":"NC",
    "sg:tags":[
        "television"
    ],
    "wof:name":"Abp Digital Inc",
    "wof:placetype":"venue"
},
  "geometry": {"coordinates":[-78.64382000000001,35.890662],"type":"Point"}
}