{
  "type": "Feature",
  "properties": {
    "iso:country":"US",
    "sg:address":"7355 W Friendly Ave",
    "sg:city":"Greensboro",
    "sg:classifiers":[
        {
            "category":"Autos & Motor Vehicles",
            "subcategory":"Automobile Sales",
            "type":"Retail Goods"
        }
    ],
    "sg:phone":"+1 336 834 8200",
    "sg:postcode":"27410",
    "sg:province":"NC",
    "sg:tags":[
        "used"
    ],
    "wof:name":"Auto Mart Magazine",
    "wof:placetype":"venue"
},
  "geometry": {"coordinates":[-79.922301,36.088433],"type":"Point"}
}