{
  "type": "Feature",
  "properties": {
    "addr:full":"2821 Summerwind Rd Chapel Hill NC 27516",
    "addr:housenumber":"2821",
    "addr:postcode":"27516",
    "addr:street":"Summerwind Rd",
    "iso:country":"US",
    "sg:address":"2821 Summerwind Rd",
    "sg:city":"Chapel Hill",
    "sg:classifiers":[
        {
            "category":"Retail",
            "subcategory":"Repair Shop",
            "type":"Services"
        },
        {
            "category":"Building & Trades",
            "subcategory":"Construction",
            "type":"Services"
        }
    ],
    "sg:phone":"+1 919 929 4919",
    "sg:postcode":"27516",
    "sg:province":"NC",
    "sg:tags":[
        "welding",
        "contractor"
    ],
    "wof:name":"Decker Woodwind Repair Service",
    "wof:placetype":"venue"
},
  "geometry": {"coordinates":[-79.17359999999999,35.942727],"type":"Point"}
}