{
  "type": "Feature",
  "properties": {
    "addr:full":"4575 Peter Pfaff Rd Pfafftown NC 27040",
    "addr:housenumber":"4575",
    "addr:postcode":"27040",
    "addr:street":"Peter Pfaff Rd",
    "iso:country":"US",
    "sg:address":"4575 Peter Pfaff Rd",
    "sg:city":"Pfafftown",
    "sg:classifiers":[
        {
            "category":"Building & Trades",
            "subcategory":"Construction",
            "type":"Services"
        }
    ],
    "sg:phone":"+1 336 922 3325",
    "sg:postcode":"27040",
    "sg:province":"NC",
    "sg:tags":[
        "roofing",
        "contractor"
    ],
    "wof:name":"Tip Top Roofing Inc",
    "wof:placetype":"venue"
},
  "geometry": {"coordinates":[-80.358298,36.156575],"type":"Point"}
}