{
  "type": "Feature",
  "properties": {
    "addr:full":"422 Weathers Creek Rd Troutman NC 28166",
    "addr:housenumber":"422",
    "addr:postcode":"28166",
    "addr:street":"Weathers Creek Rd",
    "iso:country":"US",
    "sg:address":"422 Weathers Creek Rd",
    "sg:city":"Troutman",
    "sg:classifiers":[
        {
            "category":"Building & Trades",
            "subcategory":"Construction",
            "type":"Services"
        }
    ],
    "sg:phone":"+1 704 528 2261",
    "sg:postcode":"28166",
    "sg:province":"NC",
    "sg:tags":[
        "designer"
    ],
    "wof:name":"Lora's Designs",
    "wof:placetype":"venue"
},
  "geometry": {"coordinates":[-80.817465,35.679484],"type":"Point"}
}