{
  "type": "Feature",
  "properties": {
    "addr:full":"7881 Alcorn Rd Oak Ridge NC 27310",
    "addr:housenumber":"7881",
    "addr:postcode":"27310",
    "addr:street":"Alcorn Rd",
    "iso:country":"US",
    "sg:address":"7881 Alcorn Rd",
    "sg:city":"Oak Ridge",
    "sg:classifiers":[
        {
            "category":"Organizations",
            "subcategory":"Religious Organization",
            "type":"Services"
        }
    ],
    "sg:phone":"+1 336 644 7333",
    "sg:postcode":"27310",
    "sg:province":"NC",
    "sg:tags":[
        "church"
    ],
    "wof:name":"Cross Gate Church",
    "wof:placetype":"venue"
},
  "geometry": {"coordinates":[-79.97320000000001,36.156991],"type":"Point"}
}