{
  "type": "Feature",
  "properties": {
    "addr:full":"16717 US Hwy 17 Hampstead NC 28443",
    "addr:housenumber":"16717",
    "addr:postcode":"28443",
    "addr:street":"Us Hwy 17",
    "iso:country":"US",
    "sg:address":"16717 US Hwy 17",
    "sg:city":"Hampstead",
    "sg:classifiers":[
        {
            "category":"Sports & Exercise",
            "subcategory":"Gym",
            "type":"Entertainment"
        }
    ],
    "sg:phone":"+1 910 270 8686",
    "sg:postcode":"28443",
    "sg:province":"NC",
    "sg:tags":[
        "club",
        "health",
        "studio",
        "gymnasium"
    ],
    "wof:name":"Curves",
    "wof:placetype":"venue"
},
  "geometry": {"coordinates":[-77.68065,34.392047],"type":"Point"}
}