{
  "type": "Feature",
  "properties": {
    "iso:country":"US",
    "sg:address":"1820 N Center St",
    "sg:city":"Hickory",
    "sg:classifiers":[
        {
            "category":"Restaurant",
            "type":"Food & Drink"
        }
    ],
    "sg:menulink":"http://www.allmenus.com/nc/hickory/85393-dominos-pizza/menu/",
    "sg:phone":"+1 828 324 5111",
    "sg:postcode":"28601",
    "sg:province":"NC",
    "sg:tags":[
        "american",
        "wing",
        "pizza"
    ],
    "wof:name":"Domino's Pizza",
    "wof:placetype":"venue"
},
  "geometry": {"coordinates":[-81.335694,35.756885],"type":"Point"}
}