{
  "type": "Feature",
  "properties": {
    "iso:country":"US",
    "sg:address":"7508 E Independence Blvd",
    "sg:city":"Charlotte",
    "sg:classifiers":[
        {
            "category":"Banks & Credit Unions",
            "subcategory":"Bank",
            "type":"Services"
        }
    ],
    "sg:phone":"+1 704 567 1401",
    "sg:postcode":"28227",
    "sg:province":"NC",
    "sg:tags":[
        "financing"
    ],
    "wof:name":"JSA Premium Finance",
    "wof:placetype":"venue"
},
  "geometry": {"coordinates":[-80.738157,35.161704],"type":"Point"}
}