{
  "type": "Feature",
  "properties": {
    "addr:full":"120 Powell Dr Eden NC 27288",
    "addr:housenumber":"120",
    "addr:postcode":"27288",
    "addr:street":"Powell Dr",
    "iso:country":"US",
    "sg:address":"120 Powell Dr",
    "sg:city":"Eden",
    "sg:classifiers":[
        {
            "category":"Professional",
            "subcategory":"Business Services",
            "type":"Services"
        }
    ],
    "sg:phone":"+1   ",
    "sg:postcode":"27288",
    "sg:province":"NC",
    "wof:name":"Dreyer Enterprises",
    "wof:placetype":"venue"
},
  "geometry": {"coordinates":[-79.68212800000001,36.518634],"type":"Point"}
}