{
  "type": "Feature",
  "properties": {
    "iso:country":"US",
    "sg:address":"2678 Joe Gardner Rd",
    "sg:city":"Grifton",
    "sg:classifiers":[
        {
            "category":"Building & Trades",
            "subcategory":"Landscaping Services",
            "type":"Services"
        }
    ],
    "sg:phone":"+1 252 258 2982",
    "sg:postcode":"28530",
    "sg:province":"NC",
    "wof:name":"Eastern Tree Service",
    "wof:placetype":"venue"
},
  "geometry": {"coordinates":[-77.317667,35.368116],"type":"Point"}
}