{
  "type": "Feature",
  "properties": {
    "addr:full":"1050 John P Frank Pkwy Traphill NC 28685",
    "addr:housenumber":"1050",
    "addr:postcode":"28685",
    "addr:street":"John P Frank Pkwy",
    "iso:country":"US",
    "sg:address":"1050 John P Frank Pkwy",
    "sg:city":"Traphill",
    "sg:classifiers":[
        {
            "category":"Shopping",
            "subcategory":"Discount & Variety Stores",
            "type":"Retail Goods"
        }
    ],
    "sg:phone":"+1 336 957 8154",
    "sg:postcode":"28685",
    "sg:province":"NC",
    "sg:tags":[
        "merchandise",
        "general"
    ],
    "wof:name":"Stone Mountain Country Store",
    "wof:placetype":"venue"
},
  "geometry": {"coordinates":[-81.02612000000001,36.357525],"type":"Point"}
}