{
  "type": "Feature",
  "properties": {
    "addr:full":"746 Cullin Rd Harrellsville NC 27942",
    "addr:housenumber":"746",
    "addr:postcode":"27942",
    "addr:street":"Cullin Rd",
    "iso:country":"US",
    "sg:address":"746 Cullin Rd",
    "sg:city":"Harrellsville",
    "sg:classifiers":[
        {
            "category":"Farming",
            "subcategory":"Farm",
            "type":"Manufacturing & Wholesale Goods"
        }
    ],
    "sg:phone":"+1 252 356 4885",
    "sg:postcode":"27942",
    "sg:province":"NC",
    "wof:name":"Joseph L Holloman",
    "wof:placetype":"venue"
},
  "geometry": {"coordinates":[-76.714564,36.28198],"type":"Point"}
}