{
  "type": "Feature",
  "properties": {
    "addr:full":"218 W Palmer Dr New Bern NC 28560",
    "addr:housenumber":"218",
    "addr:postcode":"28560",
    "addr:street":"W Palmer Dr",
    "iso:country":"US",
    "sg:address":"218 W Palmer Dr",
    "sg:city":"New Bern",
    "sg:classifiers":[
        {
            "category":"Building & Trades",
            "subcategory":"Landscaping Services",
            "type":"Services"
        }
    ],
    "sg:phone":"+1 252 444 5671",
    "sg:postcode":"28560",
    "sg:province":"NC",
    "sg:tags":[
        "landscape"
    ],
    "wof:name":"Dave Smith Enterprises",
    "wof:placetype":"venue"
},
  "geometry": {"coordinates":[-76.93098500000001,34.970105],"type":"Point"}
}