{
  "type": "Feature",
  "properties": {
    "addr:full":"190 Allen Forest Ln Mt Gilead NC 27306",
    "addr:housenumber":"190",
    "addr:postcode":"27306",
    "addr:street":"Allen Forest Ln Mt",
    "iso:country":"US",
    "sg:address":"190 Allen Forest Ln",
    "sg:city":"Mt Gilead",
    "sg:classifiers":[
        {
            "category":"Manufacturing",
            "subcategory":"Lumber",
            "type":"Manufacturing & Wholesale Goods"
        }
    ],
    "sg:phone":"+1 910 576 4886",
    "sg:postcode":"27306",
    "sg:province":"NC",
    "sg:tags":[
        "forester"
    ],
    "wof:name":"Little River Forestry Conslnt",
    "wof:placetype":"venue"
},
  "geometry": {"coordinates":[-79.904158,35.272653],"type":"Point"}
}