{
  "type": "Feature",
  "properties": {
    "iso:country":"US",
    "sg:address":"112 West Blvd",
    "sg:city":"Laurinburg",
    "sg:classifiers":[
        {
            "category":"Real Estate",
            "subcategory":"Real Estate Agent",
            "type":"Services"
        }
    ],
    "sg:phone":"+1 910 276 1021",
    "sg:postcode":"28352",
    "sg:province":"NC",
    "wof:name":"Realty World Broker Network",
    "wof:placetype":"venue"
},
  "geometry": {"coordinates":[-79.466493,34.769263],"type":"Point"}
}