{
  "type": "Feature",
  "properties": {
    "iso:country":"US",
    "sg:address":"1745 Brevard Rd",
    "sg:city":"Hendersonville",
    "sg:classifiers":[
        {
            "category":"Health Services",
            "subcategory":"Doctor",
            "type":"Services"
        }
    ],
    "sg:phone":"+1 828 696 2515",
    "sg:postcode":"28791",
    "sg:province":"NC",
    "sg:tags":[
        "physician",
        "surgeon"
    ],
    "wof:name":"Laural Park Family Practice",
    "wof:placetype":"venue"
},
  "geometry": {"coordinates":[-82.49153,35.320537],"type":"Point"}
}