{
  "type": "Feature",
  "properties": {
    "addr:full":"214 W Main St Marshville NC 28103",
    "addr:housenumber":"214",
    "addr:postcode":"28103",
    "addr:street":"W Main St",
    "iso:country":"US",
    "sg:address":"214 W Main St",
    "sg:city":"Marshville",
    "sg:classifiers":[
        {
            "category":"Home & Garden",
            "subcategory":"Household Appliances",
            "type":"Retail Goods"
        },
        {
            "category":"Home & Garden",
            "subcategory":"Furniture",
            "type":"Retail Goods"
        }
    ],
    "sg:phone":"+1 704 624 2211",
    "sg:postcode":"28103",
    "sg:province":"NC",
    "sg:tags":[
        "floor",
        "covering"
    ],
    "wof:name":"Griffin Furniture & Appliances",
    "wof:placetype":"venue"
},
  "geometry": {"coordinates":[-80.369879,34.986736],"type":"Point"}
}