{
  "type": "Feature",
  "properties": {
    "addr:full":"5414 E Oak Island Dr Oak Island NC 28465",
    "addr:housenumber":"5414",
    "addr:postcode":"28465",
    "addr:street":"E Oak Island Dr Oak",
    "iso:country":"US",
    "sg:address":"5414 E Oak Island Dr",
    "sg:city":"Oak Island",
    "sg:classifiers":[
        {
            "category":"Building & Trades",
            "subcategory":"Pest Control",
            "type":"Services"
        }
    ],
    "sg:phone":"+1 910 278 9484",
    "sg:postcode":"28465",
    "sg:province":"NC",
    "wof:name":"Clegg's Termite & Pest Control",
    "wof:placetype":"venue"
},
  "geometry": {"coordinates":[-78.109647,33.912324],"type":"Point"}
}