{
  "type": "Feature",
  "properties": {
    "addr:full":"115 Keowee Cir Indian Trail NC 28079",
    "addr:housenumber":"115",
    "addr:postcode":"28079",
    "addr:street":"Keowee Cir;Trail",
    "iso:country":"US",
    "sg:address":"115 Keowee Cir",
    "sg:city":"Indian Trail",
    "sg:classifiers":[
        {
            "category":"Retail",
            "subcategory":"Auto Repair",
            "type":"Services"
        }
    ],
    "sg:phone":"+1   ",
    "sg:postcode":"28079",
    "sg:province":"NC",
    "sg:tags":[
        "body"
    ],
    "wof:name":"A & B Automotive Inc",
    "wof:placetype":"venue"
},
  "geometry": {"coordinates":[-80.67956,35.070878],"type":"Point"}
}