{
  "type": "Feature",
  "properties": {
    "iso:country":"US",
    "sg:address":"2620 S Tryon St",
    "sg:city":"Charlotte",
    "sg:classifiers":[
        {
            "category":"Professional",
            "subcategory":"Accounting & Tax Preparation",
            "type":"Services"
        }
    ],
    "sg:phone":"+1 704 295 1440",
    "sg:postcode":"28203",
    "sg:province":"NC",
    "sg:tags":[
        "return",
        "filing"
    ],
    "wof:name":"Webtax",
    "wof:placetype":"venue"
},
  "geometry": {"coordinates":[-80.870785,35.203862],"type":"Point"}
}