{
  "type": "Feature",
  "properties": {
    "iso:country":"US",
    "sg:address":"141 Linda Vista Dr",
    "sg:city":"Hendersonville",
    "sg:classifiers":[
        {
            "category":"Building & Trades",
            "subcategory":"Equipment Rental",
            "type":"Services"
        }
    ],
    "sg:phone":"+1 828 692 1000",
    "sg:postcode":"28792",
    "sg:province":"NC",
    "sg:tags":[
        "leasing",
        "furniture"
    ],
    "wof:name":"Aarons Sales & Lease Ownership",
    "wof:placetype":"venue"
},
  "geometry": {"coordinates":[-82.44966100000001,35.33353],"type":"Point"}
}