{
  "type": "Feature",
  "properties": {
    "iso:country":"US",
    "sg:address":"120 Holloman St",
    "sg:city":"Washington",
    "sg:classifiers":[
        {
            "category":"Real Estate",
            "subcategory":"Real Estate Operator",
            "type":"Services"
        }
    ],
    "sg:phone":"+1 252 975 3849",
    "sg:postcode":"27889",
    "sg:province":"NC",
    "sg:tags":[
        "building",
        "apartment"
    ],
    "wof:name":"Glenview Apartments",
    "wof:placetype":"venue"
},
  "geometry": {"coordinates":[-77.04074300000001,35.552346],"type":"Point"}
}