{
  "type": "Feature",
  "properties": {
    "addr:full":"516 Island Rd Harkers Island NC 28531",
    "addr:housenumber":"516",
    "addr:postcode":"28531",
    "addr:street":"Island Rd",
    "iso:country":"US",
    "sg:address":"516 Island Rd",
    "sg:city":"Harkers Island",
    "sg:classifiers":[
        {
            "category":"Ferry",
            "type":"Transportation"
        }
    ],
    "sg:phone":"+1 252 728 2759",
    "sg:postcode":"28531",
    "sg:province":"NC",
    "wof:name":"Local Yokel",
    "wof:placetype":"venue"
},
  "geometry": {"coordinates":[-76.578791,34.699842],"type":"Point"}
}