{
  "type": "Feature",
  "properties": {
    "addr:full":"321 Old Dutch Rd W Indian Trail NC 28079",
    "addr:housenumber":"321",
    "addr:postcode":"28079",
    "addr:street":"Old Dutch Rd W;Trail",
    "iso:country":"US",
    "sg:address":"321 Old Dutch Rd W",
    "sg:city":"Indian Trail",
    "sg:classifiers":[
        {
            "category":"Organizations",
            "subcategory":"Community Association",
            "type":"Services"
        }
    ],
    "sg:phone":"+1   ",
    "sg:postcode":"28079",
    "sg:province":"NC",
    "wof:name":"Order of Eastern Star",
    "wof:placetype":"venue"
},
  "geometry": {"coordinates":[-80.548199,35.166434],"type":"Point"}
}