{
  "type": "Feature",
  "properties": {
    "addr:full":"201 Weber St Trenton NC 28585",
    "addr:housenumber":"201",
    "addr:postcode":"28585",
    "addr:street":"Weber St",
    "iso:country":"US",
    "sg:address":"201 Weber St",
    "sg:city":"Trenton",
    "sg:classifiers":[
        {
            "category":"Building & Trades",
            "subcategory":"Construction",
            "type":"Services"
        }
    ],
    "sg:phone":"+1 252 448 1756",
    "sg:postcode":"28585",
    "sg:province":"NC",
    "sg:tags":[
        "resurfacing",
        "laying",
        "refinishing",
        "floor"
    ],
    "wof:name":"Taft's Custom Floors",
    "wof:placetype":"venue"
},
  "geometry": {"coordinates":[-77.352772,35.062005],"type":"Point"}
}