{
  "type": "Feature",
  "properties": {
    "addr:full":"106 New Waverly Pl Cary NC 27511",
    "addr:housenumber":"106",
    "addr:postcode":"27511",
    "addr:street":"New Waverly Pl",
    "iso:country":"US",
    "sg:address":"106 New Waverly Pl",
    "sg:city":"Cary",
    "sg:classifiers":[
        {
            "category":"Shopping",
            "subcategory":"Jewelry",
            "type":"Retail Goods"
        }
    ],
    "sg:phone":"+1 919 851 6412",
    "sg:postcode":"27511",
    "sg:province":"NC",
    "sg:website":"www.flamekissedbeads.com",
    "wof:name":"Flame Kissed Beads Studio & Gallery",
    "wof:placetype":"venue"
},
  "geometry": {"coordinates":[-78.77919799999999,35.736301],"type":"Point"}
}