{
  "type": "Feature",
  "properties": {
    "addr:full":"609 E Nash St Spring Hope NC 27882",
    "addr:housenumber":"609",
    "addr:postcode":"27882",
    "addr:street":"E Nash St",
    "iso:country":"US",
    "sg:address":"609 E Nash St",
    "sg:city":"Spring Hope",
    "sg:classifiers":[
        {
            "category":"Education",
            "subcategory":"Special Training",
            "type":"Public Place"
        }
    ],
    "sg:phone":"+1 252 478 7877",
    "sg:postcode":"27882",
    "sg:province":"NC",
    "sg:tags":[
        "center"
    ],
    "wof:name":"Higher Learning Christain Cdmy",
    "wof:placetype":"venue"
},
  "geometry": {"coordinates":[-78.10588799999999,35.949946],"type":"Point"}
}