{
  "type": "Feature",
  "properties": {
    "iso:country":"US",
    "sg:address":"2502 US Hwy 13 N",
    "sg:city":"Goldsboro",
    "sg:classifiers":[
        {
            "category":"Autos & Motor Vehicles",
            "subcategory":"Motorcycle Sales",
            "type":"Retail Goods"
        }
    ],
    "sg:phone":"+1 919 759 2264",
    "sg:postcode":"27534",
    "sg:province":"NC",
    "sg:tags":[
        "scooter"
    ],
    "wof:name":"Goldsboro Power Sports",
    "wof:placetype":"venue"
},
  "geometry": {"coordinates":[-77.89779799999999,35.409654],"type":"Point"}
}