{
  "type": "Feature",
  "properties": {
    "iso:country":"US",
    "sg:address":"2763 Trillium Trl",
    "sg:city":"Denver",
    "sg:classifiers":[
        {
            "category":"Professional",
            "subcategory":"Management & Consulting",
            "type":"Services"
        }
    ],
    "sg:phone":"+1   ",
    "sg:postcode":"28037",
    "sg:province":"NC",
    "sg:tags":[
        "process",
        "business"
    ],
    "wof:name":"Customer Care Solutions Inc",
    "wof:placetype":"venue"
},
  "geometry": {"coordinates":[-80.959322,35.48159],"type":"Point"}
}