{
  "type": "Feature",
  "properties": {
    "addr:full":"3708 Shadybrook Dr Raleigh NC 27609",
    "addr:housenumber":"3708",
    "addr:postcode":"27609",
    "addr:street":"Shadybrook Dr",
    "iso:country":"US",
    "sg:address":"3708 Shadybrook Dr",
    "sg:city":"Raleigh",
    "sg:classifiers":[
        {
            "category":"Insurance",
            "subcategory":"Insurance Agent",
            "type":"Services"
        }
    ],
    "sg:phone":"+1 919 848 9000",
    "sg:postcode":"27609",
    "sg:province":"NC",
    "wof:name":"H Gilliam Nicholson",
    "wof:placetype":"venue"
},
  "geometry": {"coordinates":[-78.644426,35.831521],"type":"Point"}
}