{
  "type": "Feature",
  "properties": {
    "iso:country":"US",
    "sg:address":"1100 W 15th St",
    "sg:city":"Washington",
    "sg:classifiers":[
        {
            "category":"Shopping",
            "subcategory":"Optical Goods",
            "type":"Retail Goods"
        }
    ],
    "sg:phone":"+1 252 975 8040",
    "sg:postcode":"27889",
    "sg:province":"NC",
    "wof:name":"Optometric Eye Care Center PA",
    "wof:placetype":"venue"
},
  "geometry": {"coordinates":[-77.060326,35.561917],"type":"Point"}
}