{
  "type": "Feature",
  "properties": {
    "iso:country":"US",
    "sg:address":"121 Cedarwood Dr",
    "sg:city":"Lexington",
    "sg:classifiers":[
        {
            "category":"Building & Trades",
            "subcategory":"Cleaning & Sanitation",
            "type":"Services"
        }
    ],
    "sg:phone":"+1   ",
    "sg:postcode":"27292",
    "sg:province":"NC",
    "sg:tags":[
        "maintenance"
    ],
    "wof:name":"Austins Pressure Washing Serv",
    "wof:placetype":"venue"
},
  "geometry": {"coordinates":[-80.317559,35.765027],"type":"Point"}
}