{
  "type": "Feature",
  "properties": {
    "addr:full":"228 Scarlett Dr Chapel Hill NC 27517",
    "addr:housenumber":"228",
    "addr:postcode":"27517",
    "addr:street":"Scarlett Dr",
    "iso:country":"US",
    "sg:address":"228 Scarlett Dr",
    "sg:city":"Chapel Hill",
    "sg:classifiers":[
        {
            "category":"Personal",
            "subcategory":"Beauty Salon",
            "type":"Services"
        }
    ],
    "sg:phone":"+1   ",
    "sg:postcode":"27517",
    "sg:province":"NC",
    "sg:tags":[
        "shop"
    ],
    "wof:name":"Studio 86 Hair Design",
    "wof:placetype":"venue"
},
  "geometry": {"coordinates":[-79.01157000000001,35.942547],"type":"Point"}
}