{
  "type": "Feature",
  "properties": {
    "iso:country":"US",
    "sg:address":"5843 Ramsey St",
    "sg:city":"Fayetteville",
    "sg:classifiers":[
        {
            "category":"Health Services",
            "subcategory":"Hospital",
            "type":"Services"
        }
    ],
    "sg:phone":"+1 910 822 3333",
    "sg:postcode":"28311",
    "sg:province":"NC",
    "sg:tags":[
        "mental"
    ],
    "wof:name":"Hope Catchers",
    "wof:placetype":"venue"
},
  "geometry": {"coordinates":[-78.87388300000001,35.140694],"type":"Point"}
}