{
  "type": "Feature",
  "properties": {
    "addr:full":"11515 Hambright Rd Huntersville NC 28078",
    "addr:housenumber":"11515",
    "addr:postcode":"28078",
    "addr:street":"Hambright Rd",
    "iso:country":"US",
    "sg:address":"11515 Hambright Rd",
    "sg:city":"Huntersville",
    "sg:classifiers":[
        {
            "category":"Freight",
            "type":"Transportation"
        }
    ],
    "sg:phone":"+1 704 948 5575",
    "sg:postcode":"28078",
    "sg:province":"NC",
    "sg:tags":[
        "commercial",
        "storage"
    ],
    "wof:name":"North Meck Self Storage",
    "wof:placetype":"venue"
},
  "geometry": {"coordinates":[-80.84331899999999,35.376685],"type":"Point"}
}