{
  "type": "Feature",
  "properties": {
    "addr:full":"405 N Shore Dr W Sunset Beach NC 28468",
    "addr:housenumber":"405",
    "addr:postcode":"28468",
    "addr:street":"N Shore Dr W",
    "iso:country":"US",
    "sg:address":"405 N Shore Dr W",
    "sg:city":"Sunset Beach",
    "sg:classifiers":[
        {
            "category":"Real Estate",
            "subcategory":"Architect",
            "type":"Services"
        }
    ],
    "sg:phone":"+1 910 579 9163",
    "sg:postcode":"28468",
    "sg:province":"NC",
    "sg:tags":[
        "course",
        "golf"
    ],
    "wof:name":"Tim Cates",
    "wof:placetype":"venue"
},
  "geometry": {"coordinates":[-78.51089899999999,33.870288],"type":"Point"}
}