{
  "type": "Feature",
  "properties": {
    "iso:country":"US",
    "sg:address":"3200 State Rd 54",
    "sg:city":"Chapel Hill",
    "sg:classifiers":[
        {
            "category":"Professional",
            "subcategory":"Management & Consulting",
            "type":"Services"
        }
    ],
    "sg:phone":"+1 919 406 1392",
    "sg:postcode":"27516",
    "sg:province":"NC",
    "sg:tags":[
        "consultant"
    ],
    "wof:name":"ICF Consulting",
    "wof:placetype":"venue"
},
  "geometry": {"coordinates":[-79.182248,35.922618],"type":"Point"}
}