{
  "type": "Feature",
  "properties": {
    "addr:full":"4004 Whitetail Ct High Point NC 27265",
    "addr:housenumber":"4004",
    "addr:postcode":"27265",
    "addr:street":"Whitetail Ct",
    "iso:country":"US",
    "sg:address":"4004 Whitetail Ct",
    "sg:city":"High Point",
    "sg:classifiers":[
        {
            "category":"Professional",
            "type":"Services"
        }
    ],
    "sg:phone":"+1 336 454 5084",
    "sg:postcode":"27265",
    "sg:province":"NC",
    "wof:name":"Budget PC Continuing Supp",
    "wof:placetype":"venue"
},
  "geometry": {"coordinates":[-79.989552,36.038892],"type":"Point"}
}