{
  "type": "Feature",
  "properties": {
    "addr:full":"2901 Lomond St Winston Salem NC 27127",
    "addr:housenumber":"2901",
    "addr:postcode":"27127",
    "addr:street":"Lomond St",
    "iso:country":"US",
    "sg:address":"2901 Lomond St",
    "sg:city":"Winston Salem",
    "sg:classifiers":[
        {
            "category":"Freight",
            "type":"Transportation"
        }
    ],
    "sg:phone":"+1 336 784 7708",
    "sg:postcode":"27127",
    "sg:province":"NC",
    "sg:tags":[
        "operator",
        "trucking"
    ],
    "wof:name":"Hatchers Trucking Co",
    "wof:placetype":"venue"
},
  "geometry": {"coordinates":[-80.234948,36.056405],"type":"Point"}
}