{
  "type": "Feature",
  "properties": {
    "iso:country":"US",
    "sg:address":"7672 Union Grove Church Rd",
    "sg:city":"Seagrove",
    "sg:classifiers":[
        {
            "category":"Home & Garden",
            "subcategory":"Home Furnishings",
            "type":"Retail Goods"
        }
    ],
    "sg:phone":"+1 336 879 2481",
    "sg:postcode":"27341",
    "sg:province":"NC",
    "sg:tags":[
        "pottery"
    ],
    "wof:name":"Old Hard Times Pottery",
    "wof:placetype":"venue"
},
  "geometry": {"coordinates":[-79.72110499999999,35.518872],"type":"Point"}
}