{
  "type": "Feature",
  "properties": {
    "iso:country":"US",
    "sg:address":"2503 Soco Rd",
    "sg:city":"Maggie Valley",
    "sg:classifiers":[
        {
            "category":"Banks & Credit Unions",
            "subcategory":"Bank",
            "type":"Services"
        }
    ],
    "sg:phone":"+1 828 926 6450",
    "sg:postcode":"28751",
    "sg:province":"NC",
    "sg:tags":[
        "mortgage"
    ],
    "wof:name":"Sherwood Capital",
    "wof:placetype":"venue"
},
  "geometry": {"coordinates":[-83.070426,35.512447],"type":"Point"}
}