{
  "type": "Feature",
  "properties": {
    "iso:country":"US",
    "sg:address":"4007 City of Oaks Wynd",
    "sg:city":"Raleigh",
    "sg:classifiers":[
        {
            "category":"Health Services",
            "subcategory":"Doctor",
            "type":"Services"
        }
    ],
    "sg:phone":"+1 919 881 0202",
    "sg:postcode":"27612",
    "sg:province":"NC",
    "wof:name":"Wyker Robert T MD",
    "wof:placetype":"venue"
},
  "geometry": {"coordinates":[-78.706371,35.830206],"type":"Point"}
}