{
  "type": "Feature",
  "properties": {
    "iso:country":"US",
    "sg:address":"4942 Soco Rd",
    "sg:city":"Maggie Valley",
    "sg:classifiers":[
        {
            "category":"Shopping",
            "type":"Retail Goods"
        }
    ],
    "sg:phone":"+1 828 926 1002",
    "sg:postcode":"28751",
    "sg:province":"NC",
    "sg:tags":[
        "art",
        "gallery",
        "dealer"
    ],
    "wof:name":"Blue Ridge Gallery",
    "wof:placetype":"venue"
},
  "geometry": {"coordinates":[-83.11356000000001,35.523437],"type":"Point"}
}