{
  "type": "Feature",
  "properties": {
    "addr:full":"117 N Center St Statesville NC 28677",
    "addr:housenumber":"117",
    "addr:postcode":"28677",
    "addr:street":"N Center St",
    "iso:country":"US",
    "sg:address":"117 N Center St",
    "sg:city":"Statesville",
    "sg:classifiers":[
        {
            "category":"Professional",
            "subcategory":"Employment Agencies",
            "type":"Services"
        }
    ],
    "sg:phone":"+1 704 871 9890",
    "sg:postcode":"28677",
    "sg:province":"NC",
    "wof:name":"Managment Rcriters Statesville",
    "wof:placetype":"venue"
},
  "geometry": {"coordinates":[-80.889447,35.786644],"type":"Point"}
}