{
  "type": "Feature",
  "properties": {
    "iso:country":"US",
    "sg:address":"1412 Creekstone Ln",
    "sg:city":"Cary",
    "sg:classifiers":[
        {
            "category":"Personal",
            "type":"Services"
        }
    ],
    "sg:phone":"+1 919 319 0420",
    "sg:postcode":"27511",
    "sg:province":"NC",
    "sg:tags":[
        "therapist",
        "massage"
    ],
    "wof:name":"Peter Watts",
    "wof:placetype":"venue"
},
  "geometry": {"coordinates":[-78.77056899999999,35.759118],"type":"Point"}
}