{
  "type": "Feature",
  "properties": {
    "addr:full":"2333 Brandt Village Ln Greensboro NC 27455",
    "addr:housenumber":"2333",
    "addr:postcode":"27455",
    "addr:street":"Brandt Village Ln",
    "iso:country":"US",
    "sg:address":"2333 Brandt Village Ln",
    "sg:city":"Greensboro",
    "sg:classifiers":[
        {
            "category":"Building & Trades",
            "subcategory":"Cleaning & Sanitation",
            "type":"Services"
        }
    ],
    "sg:phone":"+1   ",
    "sg:postcode":"27455",
    "sg:province":"NC",
    "sg:tags":[
        "maintenance"
    ],
    "wof:name":"Quality Choice Cleaning Svc",
    "wof:placetype":"venue"
},
  "geometry": {"coordinates":[-79.843249,36.139986],"type":"Point"}
}