{
  "type": "Feature",
  "properties": {
    "addr:full":"356 E Fleming Dr Morganton NC 28655",
    "addr:housenumber":"356",
    "addr:postcode":"28655",
    "addr:street":"E Fleming Dr",
    "iso:country":"US",
    "sg:address":"356 E Fleming Dr",
    "sg:city":"Morganton",
    "sg:classifiers":[
        {
            "category":"Personal",
            "subcategory":"Beauty Salon",
            "type":"Services"
        }
    ],
    "sg:phone":"+1 828 433 4510",
    "sg:postcode":"28655",
    "sg:province":"NC",
    "wof:name":"Clever Cut",
    "wof:placetype":"venue"
},
  "geometry": {"coordinates":[-81.667967,35.745577],"type":"Point"}
}