{
  "type": "Feature",
  "properties": {
    "iso:country":"US",
    "sg:address":"101 W King St",
    "sg:city":"Edenton",
    "sg:classifiers":[
        {
            "category":"Professional",
            "subcategory":"Accounting & Tax Preparation",
            "type":"Services"
        }
    ],
    "sg:phone":"+1 252 482 7644",
    "sg:postcode":"27932",
    "sg:province":"NC",
    "sg:tags":[
        "accountant"
    ],
    "sg:website":"www.sykes-cpa.com",
    "wof:name":"Sykes & Co",
    "wof:placetype":"venue"
},
  "geometry": {"coordinates":[-76.611885,36.058516],"type":"Point"}
}