{
  "type": "Feature",
  "properties": {
    "addr:full":"1112 Vesper Ln Fayetteville NC 28311",
    "addr:housenumber":"1112",
    "addr:postcode":"28311",
    "addr:street":"Vesper Ln",
    "iso:country":"US",
    "sg:address":"1112 Vesper Ln",
    "sg:city":"Fayetteville",
    "sg:classifiers":[
        {
            "category":"Autos & Motor Vehicles",
            "subcategory":"Motorcycle Sales",
            "type":"Retail Goods"
        }
    ],
    "sg:phone":"+1 910 484 8680",
    "sg:postcode":"28311",
    "sg:province":"NC",
    "wof:name":"Motorcycle Parts Plus",
    "wof:placetype":"venue"
},
  "geometry": {"coordinates":[-78.90608400000001,35.106729],"type":"Point"}
}