{
  "type": "Feature",
  "properties": {
    "iso:country":"US",
    "sg:address":"1932 Shadow Glen Dr",
    "sg:city":"Raleigh",
    "sg:classifiers":[
        {
            "category":"Home & Garden",
            "subcategory":"Building Materials",
            "type":"Retail Goods"
        }
    ],
    "sg:phone":"+1 919 255 1200",
    "sg:postcode":"27604",
    "sg:province":"NC",
    "sg:tags":[
        "glass",
        "window",
        "plate"
    ],
    "wof:name":"Mastercraft Auto Glass",
    "wof:placetype":"venue"
},
  "geometry": {"coordinates":[-78.544068,35.808693],"type":"Point"}
}