{
  "type": "Feature",
  "properties": {
    "addr:full":"1228 E Morehead St Charlotte NC 28204",
    "addr:housenumber":"1228",
    "addr:postcode":"28204",
    "addr:street":"E Morehead St",
    "iso:country":"US",
    "sg:address":"1228 E Morehead St",
    "sg:city":"Charlotte",
    "sg:classifiers":[
        {
            "category":"Restaurant",
            "type":"Food & Drink"
        }
    ],
    "sg:phone":"+1 704 375 9715",
    "sg:postcode":"28204",
    "sg:province":"NC",
    "wof:name":"Harper's Restaurant Inc",
    "wof:placetype":"venue"
},
  "geometry": {"coordinates":[-80.840068,35.208753],"type":"Point"}
}