{
  "type": "Feature",
  "properties": {
    "iso:country":"US",
    "sg:address":"5716 Harrington Grove Dr",
    "sg:city":"Raleigh",
    "sg:classifiers":[
        {
            "category":"Personal",
            "subcategory":"Beauty Salon",
            "type":"Services"
        }
    ],
    "sg:phone":"+1 919 961 1518",
    "sg:postcode":"27613",
    "sg:province":"NC",
    "wof:name":"Studio 10-B",
    "wof:placetype":"venue"
},
  "geometry": {"coordinates":[-78.749154,35.929606],"type":"Point"}
}