{
  "type": "Feature",
  "properties": {
    "addr:full":"9136 Privette Hill Ln Spring Hope NC 27882",
    "addr:housenumber":"9136",
    "addr:postcode":"27882",
    "addr:street":"Privette Hill Ln",
    "iso:country":"US",
    "sg:address":"9136 Privette Hill Ln",
    "sg:city":"Spring Hope",
    "sg:classifiers":[
        {
            "category":"Farming",
            "subcategory":"Livestock Farm",
            "type":"Manufacturing & Wholesale Goods"
        }
    ],
    "sg:phone":"+1 252 478 7425",
    "sg:postcode":"27882",
    "sg:province":"NC",
    "sg:tags":[
        "equine"
    ],
    "wof:name":"Forest Frame Farms",
    "wof:placetype":"venue"
},
  "geometry": {"coordinates":[-78.11293499999999,36.03478],"type":"Point"}
}