{
  "type": "Feature",
  "properties": {
    "iso:country":"US",
    "sg:address":"210 E Hargett St",
    "sg:city":"Richlands",
    "sg:classifiers":[
        {
            "category":"Retail",
            "subcategory":"Funeral Services",
            "type":"Services"
        }
    ],
    "sg:phone":"+1 910 324 4415",
    "sg:postcode":"28574",
    "sg:province":"NC",
    "sg:tags":[
        "director"
    ],
    "wof:name":"Johnson Funeral Home",
    "wof:placetype":"venue"
},
  "geometry": {"coordinates":[-77.544268,34.898769],"type":"Point"}
}