{
  "type": "Feature",
  "properties": {
    "addr:full":"76 Wild Ridge Cashiers NC 28717",
    "addr:housenumber":"76",
    "addr:postcode":"28717",
    "addr:street":"Wild Ridge",
    "iso:country":"US",
    "sg:address":"76 Wild Ridge",
    "sg:city":"Cashiers",
    "sg:classifiers":[
        {
            "category":"Building & Trades",
            "subcategory":"Electrical",
            "type":"Services"
        }
    ],
    "sg:phone":"+1 828 743 2901",
    "sg:postcode":"28717",
    "sg:province":"NC",
    "sg:tags":[
        "electric",
        "contractor"
    ],
    "wof:name":"Stone Electric",
    "wof:placetype":"venue"
},
  "geometry": {"coordinates":[-83.11055399999999,35.125882],"type":"Point"}
}