{
  "type": "Feature",
  "properties": {
    "addr:full":"230 Mulberry St South Brunswick NC 28470",
    "addr:housenumber":"230",
    "addr:postcode":"28470",
    "addr:street":"Mulberry St",
    "iso:country":"US",
    "sg:address":"230 Mulberry St",
    "sg:city":"South Brunswick",
    "sg:classifiers":[
        {
            "category":"Retail",
            "subcategory":"Auto Rental",
            "type":"Services"
        }
    ],
    "sg:phone":"+1 910 755 7210",
    "sg:postcode":"28470",
    "sg:province":"NC",
    "sg:tags":[
        "renting",
        "truck",
        "leasing"
    ],
    "wof:name":"U-Haul Co",
    "wof:placetype":"venue"
},
  "geometry": {"coordinates":[-78.38574199999999,33.973036],"type":"Point"}
}