{
  "type": "Feature",
  "properties": {
    "iso:country":"US",
    "sg:address":"5622 E Independence Blvd",
    "sg:city":"Charlotte",
    "sg:classifiers":[
        {
            "category":"Home & Garden",
            "subcategory":"Household Appliances",
            "type":"Retail Goods"
        }
    ],
    "sg:phone":"+1 704 537 3042",
    "sg:postcode":"28212",
    "sg:province":"NC",
    "sg:tags":[
        "machine",
        "sewing"
    ],
    "wof:name":"Creative Sewing & Embroidery",
    "wof:placetype":"venue"
},
  "geometry": {"coordinates":[-80.754435,35.181427],"type":"Point"}
}