{
  "type": "Feature",
  "properties": {
    "addr:full":"172 Heavenly Dr Statesville NC 28625",
    "addr:housenumber":"172",
    "addr:postcode":"28625",
    "addr:street":"Heavenly Dr",
    "iso:country":"US",
    "sg:address":"172 Heavenly Dr",
    "sg:city":"Statesville",
    "sg:classifiers":[
        {
            "category":"Manufacturing",
            "subcategory":"Metals",
            "type":"Manufacturing & Wholesale Goods"
        },
        {
            "category":"Wholesale",
            "subcategory":"Durable Goods & Equipment",
            "type":"Manufacturing & Wholesale Goods"
        }
    ],
    "sg:phone":"+1 704 878 9611",
    "sg:postcode":"28625",
    "sg:province":"NC",
    "sg:tags":[
        "furnace",
        "works",
        "relations",
        "representative",
        "blast",
        "public",
        "manufacturer"
    ],
    "wof:name":"Ingram Sales & Consulting Inc",
    "wof:placetype":"venue"
},
  "geometry": {"coordinates":[-80.922613,35.818135],"type":"Point"}
}