{
  "type": "Feature",
  "properties": {
    "addr:full":"516 Barbour St Clayton NC 27520",
    "addr:housenumber":"516",
    "addr:postcode":"27520",
    "addr:street":"Barbour St",
    "iso:country":"US",
    "sg:address":"516 Barbour St",
    "sg:city":"Clayton",
    "sg:classifiers":[
        {
            "category":"Shopping",
            "subcategory":"Bicycles & Sporting Goods",
            "type":"Retail Goods"
        }
    ],
    "sg:phone":"+1 919 553 6687",
    "sg:postcode":"27520",
    "sg:province":"NC",
    "wof:name":"Clayton Trampoline Sales",
    "wof:placetype":"venue"
},
  "geometry": {"coordinates":[-78.461405,35.648341],"type":"Point"}
}