{
  "type": "Feature",
  "properties": {
    "addr:full":"612 E Church St Nashville NC 27856",
    "addr:housenumber":"612",
    "addr:postcode":"27856",
    "addr:street":"E Church St",
    "iso:country":"US",
    "sg:address":"612 E Church St",
    "sg:city":"Nashville",
    "sg:classifiers":[
        {
            "category":"Food & Beverages",
            "subcategory":"Bakery",
            "type":"Retail Goods"
        }
    ],
    "sg:phone":"+1 252 459 6076",
    "sg:postcode":"27856",
    "sg:province":"NC",
    "wof:name":"Duncan Doughnuts",
    "wof:placetype":"venue"
},
  "geometry": {"coordinates":[-77.957956,35.970885],"type":"Point"}
}