{
  "type": "Feature",
  "properties": {
    "iso:country":"US",
    "sg:address":"2619 Sarah Ave",
    "sg:city":"Durham",
    "sg:classifiers":[
        {
            "category":"Social Services",
            "subcategory":"Child Care",
            "type":"Services"
        }
    ],
    "sg:phone":"+1   ",
    "sg:postcode":"27707",
    "sg:province":"NC",
    "sg:tags":[
        "day"
    ],
    "wof:name":"Hudson Daycare Home",
    "wof:placetype":"venue"
},
  "geometry": {"coordinates":[-78.93213900000001,35.977256],"type":"Point"}
}