{
  "type": "Feature",
  "properties": {
    "addr:full":"2703 Clifford-Ray Rd Haw River NC 27258",
    "addr:housenumber":"2703",
    "addr:postcode":"27258",
    "addr:street":"Clifford-Ray Rd",
    "iso:country":"US",
    "sg:address":"2703 Clifford-Ray Rd",
    "sg:city":"Haw River",
    "sg:classifiers":[
        {
            "category":"Building & Trades",
            "subcategory":"Construction",
            "type":"Services"
        }
    ],
    "sg:phone":"+1 336 578 8432",
    "sg:postcode":"27258",
    "sg:province":"NC",
    "sg:tags":[
        "house"
    ],
    "wof:name":"Powers Const",
    "wof:placetype":"venue"
},
  "geometry": {"coordinates":[-79.341116,36.028733],"type":"Point"}
}