{
  "type": "Feature",
  "properties": {
    "addr:full":"80 Word Church Ln Lillington NC 27546",
    "addr:housenumber":"80",
    "addr:postcode":"27546",
    "addr:street":"Word Church Ln",
    "iso:country":"US",
    "sg:address":"80 Word Church Ln",
    "sg:city":"Lillington",
    "sg:classifiers":[
        {
            "category":"Organizations",
            "subcategory":"Religious Organization",
            "type":"Services"
        }
    ],
    "sg:phone":"+1   ",
    "sg:postcode":"27546",
    "sg:province":"NC",
    "wof:name":"Soninn Hisword",
    "wof:placetype":"venue"
},
  "geometry": {"coordinates":[-78.993706,35.315891],"type":"Point"}
}