{
  "type": "Feature",
  "properties": {
    "iso:country":"US",
    "sg:address":"1607 Helmwood Dr",
    "sg:city":"Greensboro",
    "sg:classifiers":[
        {
            "category":"Real Estate",
            "subcategory":"Developer",
            "type":"Services"
        }
    ],
    "sg:phone":"+1 336 292 3449",
    "sg:postcode":"27410",
    "sg:province":"NC",
    "wof:name":"Brevard MMR Ltd Partnersh",
    "wof:placetype":"venue"
},
  "geometry": {"coordinates":[-79.864857,36.102848],"type":"Point"}
}