{
  "type": "Feature",
  "properties": {
    "addr:full":"1955 Moore Town Rd Rocky Point NC 28457",
    "addr:housenumber":"1955",
    "addr:postcode":"28457",
    "addr:street":"Moore Town Rd",
    "iso:country":"US",
    "sg:address":"1955 Moore Town Rd",
    "sg:city":"Rocky Point",
    "sg:classifiers":[
        {
            "category":"Freight",
            "type":"Transportation"
        }
    ],
    "sg:phone":"+1 910 675 3152",
    "sg:postcode":"28457",
    "sg:province":"NC",
    "sg:tags":[
        "trucking"
    ],
    "wof:name":"Colie S Doss Trucking",
    "wof:placetype":"venue"
},
  "geometry": {"coordinates":[-77.834157,34.418432],"type":"Point"}
}