{
  "type": "Feature",
  "properties": {
    "iso:country":"US",
    "sg:address":"450 Sunrise Summit",
    "sg:city":"Asheville",
    "sg:classifiers":[
        {
            "category":"Professional",
            "subcategory":"Lawyer & Legal Services",
            "type":"Services"
        }
    ],
    "sg:phone":"+1   ",
    "sg:postcode":"28804",
    "sg:province":"NC",
    "wof:name":"Malcolm E Sorrells",
    "wof:placetype":"venue"
},
  "geometry": {"coordinates":[-82.51996200000001,35.62609],"type":"Point"}
}