{
  "type": "Feature",
  "properties": {
    "addr:full":"1400 S Main St Lexington NC 27292",
    "addr:housenumber":"1400",
    "addr:postcode":"27292",
    "addr:street":"S Main St",
    "iso:country":"US",
    "sg:address":"1400 S Main St",
    "sg:city":"Lexington",
    "sg:classifiers":[
        {
            "category":"Health Services",
            "subcategory":"Chiropractor",
            "type":"Services"
        }
    ],
    "sg:phone":"+1   ",
    "sg:postcode":"27292",
    "sg:province":"NC",
    "wof:name":"Brodar Chiropractic Offices",
    "wof:placetype":"venue"
},
  "geometry": {"coordinates":[-80.26987099999999,35.809529],"type":"Point"}
}