{
  "type": "Feature",
  "properties": {
    "iso:country":"US",
    "sg:address":"814 Winston Rd",
    "sg:city":"Lexington",
    "sg:classifiers":[
        {
            "category":"Food & Beverages",
            "subcategory":"Groceries & Convenience Stores",
            "type":"Retail Goods"
        }
    ],
    "sg:phone":"+1 336 249 4772",
    "sg:postcode":"27295",
    "sg:province":"NC",
    "wof:name":"Exprezit",
    "wof:placetype":"venue"
},
  "geometry": {"coordinates":[-80.253486,35.837424],"type":"Point"}
}