{
  "type": "Feature",
  "properties": {
    "iso:country":"US",
    "sg:address":"3676 E Franklin Blvd",
    "sg:city":"Gastonia",
    "sg:classifiers":[
        {
            "category":"Manufacturing",
            "subcategory":"Printing",
            "type":"Manufacturing & Wholesale Goods"
        }
    ],
    "sg:phone":"+1 704 824 5967",
    "sg:postcode":"28056",
    "sg:province":"NC",
    "sg:tags":[
        "printer"
    ],
    "wof:name":"Instant Imprints",
    "wof:placetype":"venue"
},
  "geometry": {"coordinates":[-81.11398199999999,35.257355],"type":"Point"}
}