{
  "type": "Feature",
  "properties": {
    "addr:full":"4832 Whichard Rd Greenville NC 27834",
    "addr:postcode":"4832;27834",
    "addr:street":"Whichard Rd",
    "iso:country":"US",
    "sg:address":"4832 Whichard Rd",
    "sg:city":"Greenville",
    "sg:classifiers":[
        {
            "category":"Wholesale",
            "subcategory":"Farm Supplies",
            "type":"Manufacturing & Wholesale Goods"
        }
    ],
    "sg:phone":"+1 252 758 7718",
    "sg:postcode":"27834",
    "sg:province":"NC",
    "sg:tags":[
        "raw",
        "product",
        "material"
    ],
    "wof:name":"Genetic Concepts",
    "wof:placetype":"venue"
},
  "geometry": {"coordinates":[-77.32683299999999,35.670355],"type":"Point"}
}