{
  "type": "Feature",
  "properties": {
    "addr:full":"109 Commercial Park Dr Thomasville NC 27360",
    "addr:housenumber":"109",
    "addr:postcode":"27360",
    "addr:street":"Commercial Park Dr",
    "iso:country":"US",
    "sg:address":"109 Commercial Park Dr",
    "sg:city":"Thomasville",
    "sg:classifiers":[
        {
            "category":"Building & Trades",
            "subcategory":"Construction",
            "type":"Services"
        }
    ],
    "sg:phone":"+1 336 475 5974",
    "sg:postcode":"27360",
    "sg:province":"NC",
    "sg:tags":[
        "woodworker"
    ],
    "wof:name":"Hardee's Custom Woodwork",
    "wof:placetype":"venue"
},
  "geometry": {"coordinates":[-80.07589,35.832],"type":"Point"}
}