{
  "type": "Feature",
  "properties": {
    "iso:country":"US",
    "sg:address":"1211 Virginia St",
    "sg:city":"Greensboro",
    "sg:classifiers":[
        {
            "category":"Health Services",
            "subcategory":"Doctor",
            "type":"Services"
        }
    ],
    "sg:phone":"+1 336 272 0012",
    "sg:postcode":"27401",
    "sg:province":"NC",
    "sg:tags":[
        "clinic"
    ],
    "wof:name":"Surgical Center",
    "wof:placetype":"venue"
},
  "geometry": {"coordinates":[-79.79149200000001,36.089622],"type":"Point"}
}