{
  "type": "Feature",
  "properties": {
    "iso:country":"US",
    "sg:address":"4900 S Tryon St",
    "sg:city":"Charlotte",
    "sg:classifiers":[
        {
            "category":"Travel",
            "subcategory":"Hotels & Motels",
            "type":"Entertainment"
        }
    ],
    "sg:phone":"+1 704 523 5599",
    "sg:postcode":"28217",
    "sg:province":"NC",
    "wof:name":"LA Quinta Inn",
    "wof:placetype":"venue"
},
  "geometry": {"coordinates":[-80.89265399999999,35.177198],"type":"Point"}
}