{
  "type": "Feature",
  "properties": {
    "addr:full":"5447 US Hwy 70 Morehead City NC 28557",
    "addr:housenumber":"5447",
    "addr:postcode":"28557",
    "addr:street":"Us Hwy 70",
    "iso:country":"US",
    "sg:address":"5447 US Hwy 70",
    "sg:city":"Morehead City",
    "sg:classifiers":[
        {
            "category":"Building & Trades",
            "subcategory":"Equipment Rental",
            "type":"Services"
        }
    ],
    "sg:phone":"+1 252 247 0771",
    "sg:postcode":"28557",
    "sg:province":"NC",
    "sg:tags":[
        "party",
        "general",
        "yard",
        "store",
        "supply"
    ],
    "wof:name":"Country Aire Rental Inc",
    "wof:placetype":"venue"
},
  "geometry": {"coordinates":[-76.82799900000001,34.744155],"type":"Point"}
}