{
  "type": "Feature",
  "properties": {
    "addr:full":"40591 Airport Rd New London NC 28127",
    "addr:housenumber":"40591",
    "addr:postcode":"28127",
    "addr:street":"Airport Rd",
    "iso:country":"US",
    "sg:address":"40591 Airport Rd",
    "sg:city":"New London",
    "sg:classifiers":[
        {
            "category":"Autos & Motor Vehicles",
            "subcategory":"Automobile Sales",
            "type":"Retail Goods"
        }
    ],
    "sg:phone":"+1 704 983 6999",
    "sg:postcode":"28127",
    "sg:province":"NC",
    "sg:tags":[
        "equipment",
        "aircraft",
        "parts",
        "supply"
    ],
    "wof:name":"Aviall Inc",
    "wof:placetype":"venue"
},
  "geometry": {"coordinates":[-80.160273,35.403906],"type":"Point"}
}