{
  "type": "Feature",
  "properties": {
    "addr:full":"17 Spring St NW Concord NC 28025",
    "addr:housenumber":"17",
    "addr:postcode":"28025",
    "addr:street":"Spring St Nw",
    "iso:country":"US",
    "sg:address":"17 Spring St NW",
    "sg:city":"Concord",
    "sg:classifiers":[
        {
            "category":"Organizations",
            "subcategory":"Religious Organization",
            "type":"Services"
        }
    ],
    "sg:phone":"+1 704 788 3991",
    "sg:postcode":"28025",
    "sg:province":"NC",
    "sg:tags":[
        "clergy"
    ],
    "wof:name":"Lester B Robbins",
    "wof:placetype":"venue"
},
  "geometry": {"coordinates":[-80.58308700000001,35.409679],"type":"Point"}
}