{
  "type": "Feature",
  "properties": {
    "iso:country":"US",
    "sg:address":"7897 Karriker Rd",
    "sg:city":"Kannapolis",
    "sg:classifiers":[
        {
            "category":"Personal",
            "type":"Services"
        }
    ],
    "sg:phone":"+1 704 933 3065",
    "sg:postcode":"28081",
    "sg:province":"NC",
    "sg:tags":[
        "food"
    ],
    "wof:name":"Herbalife A Distributors",
    "wof:placetype":"venue"
},
  "geometry": {"coordinates":[-80.711879,35.530334],"type":"Point"}
}