{
  "type": "Feature",
  "properties": {
    "addr:full":"1933 Glover St Roanoke Rapids NC 27870",
    "addr:housenumber":"1933",
    "addr:postcode":"27870",
    "addr:street":"Glover St",
    "iso:country":"US",
    "sg:address":"1933 Glover St",
    "sg:city":"Roanoke Rapids",
    "sg:classifiers":[
        {
            "category":"Organizations",
            "subcategory":"Religious Organization",
            "type":"Services"
        }
    ],
    "sg:phone":"+1 252 533 9407",
    "sg:postcode":"27870",
    "sg:province":"NC",
    "sg:tags":[
        "church"
    ],
    "wof:name":"House Of Prayer Church Of God",
    "wof:placetype":"venue"
},
  "geometry": {"coordinates":[-77.662896,36.440639],"type":"Point"}
}