{
  "type": "Feature",
  "properties": {
    "addr:full":"5679 Windemere Cir Trinity NC 27370",
    "addr:housenumber":"5679",
    "addr:postcode":"27370",
    "addr:street":"Windemere Cir",
    "iso:country":"US",
    "sg:address":"5679 Windemere Cir",
    "sg:city":"Trinity",
    "sg:classifiers":[
        {
            "category":"Professional",
            "subcategory":"Business Services",
            "type":"Services"
        }
    ],
    "sg:phone":"+1   ",
    "sg:postcode":"27370",
    "sg:province":"NC",
    "wof:name":"Ruritan National Corp",
    "wof:placetype":"venue"
},
  "geometry": {"coordinates":[-79.927982,35.866834],"type":"Point"}
}