{
  "type": "Feature",
  "properties": {
    "iso:country":"US",
    "sg:address":"3906 New Bern Ave",
    "sg:city":"Raleigh",
    "sg:classifiers":[
        {
            "category":"Freight",
            "type":"Transportation"
        }
    ],
    "sg:phone":"+1 919 231 0701",
    "sg:postcode":"27610",
    "sg:province":"NC",
    "sg:tags":[
        "fixed",
        "motor",
        "facility"
    ],
    "wof:name":"Just Inspections",
    "wof:placetype":"venue"
},
  "geometry": {"coordinates":[-78.568879,35.798879],"type":"Point"}
}