{
  "type": "Feature",
  "properties": {
    "addr:full":"4233 Saddlewood Forest Dr Winston Salem NC 27106",
    "addr:housenumber":"4233",
    "addr:postcode":"27106",
    "addr:street":"Saddlewood Forest Dr",
    "iso:country":"US",
    "sg:address":"4233 Saddlewood Forest Dr",
    "sg:city":"Winston Salem",
    "sg:classifiers":[
        {
            "category":"Professional",
            "subcategory":"Engineering",
            "type":"Services"
        }
    ],
    "sg:phone":"+1 336 924 2222",
    "sg:postcode":"27106",
    "sg:province":"NC",
    "sg:tags":[
        "engineer"
    ],
    "wof:name":"Southeast Structures",
    "wof:placetype":"venue"
},
  "geometry": {"coordinates":[-80.34863900000001,36.133969],"type":"Point"}
}