{
  "type": "Feature",
  "properties": {
    "iso:country":"US",
    "sg:address":"8307 University Executive Park Dr",
    "sg:city":"Charlotte",
    "sg:classifiers":[
        {
            "category":"Manufacturing",
            "subcategory":"Printing",
            "type":"Manufacturing & Wholesale Goods"
        }
    ],
    "sg:phone":"+1 704 549 0404",
    "sg:postcode":"28262",
    "sg:province":"NC",
    "sg:tags":[
        "printer"
    ],
    "wof:name":"Alpha Graphics",
    "wof:placetype":"venue"
},
  "geometry": {"coordinates":[-80.754856,35.301125],"type":"Point"}
}