{
  "type": "Feature",
  "properties": {
    "addr:full":"1779 S Main St Laurinburg NC 28352",
    "addr:housenumber":"1779",
    "addr:postcode":"28352",
    "addr:street":"S Main St",
    "iso:country":"US",
    "sg:address":"1779 S Main St",
    "sg:city":"Laurinburg",
    "sg:classifiers":[
        {
            "category":"Shopping",
            "subcategory":"Clothing, Apparel, & Fashions",
            "type":"Retail Goods"
        }
    ],
    "sg:phone":"+1 910 277 2691",
    "sg:postcode":"28352",
    "sg:province":"NC",
    "sg:tags":[
        "uniform"
    ],
    "wof:name":"QRS",
    "wof:placetype":"venue"
},
  "geometry": {"coordinates":[-79.48293700000001,34.750059],"type":"Point"}
}