{
  "type": "Feature",
  "properties": {
    "addr:full":"107 Walden Woods Dr La Grange NC 28551",
    "addr:housenumber":"107",
    "addr:postcode":"28551",
    "addr:street":"Walden Woods Dr",
    "iso:country":"US",
    "sg:address":"107 Walden Woods Dr",
    "sg:city":"La Grange",
    "sg:classifiers":[
        {
            "category":"Wholesale",
            "subcategory":"Chemicals & Plastics",
            "type":"Manufacturing & Wholesale Goods"
        }
    ],
    "sg:phone":"+1 919 751 1412",
    "sg:postcode":"28551",
    "sg:province":"NC",
    "wof:name":"Dow Agrosciences LLC",
    "wof:placetype":"venue"
},
  "geometry": {"coordinates":[-77.832778,35.397823],"type":"Point"}
}