{
  "type": "Feature",
  "properties": {
    "iso:country":"US",
    "sg:address":"209 W High Ave",
    "sg:city":"High Point",
    "sg:classifiers":[
        {
            "category":"Shopping",
            "subcategory":"Computers & Home Electronics",
            "type":"Retail Goods"
        }
    ],
    "sg:phone":"+1 336 886 4016",
    "sg:postcode":"27260",
    "sg:province":"NC",
    "sg:tags":[
        "software"
    ],
    "wof:name":"Myriad Software LLC",
    "wof:placetype":"venue"
},
  "geometry": {"coordinates":[-80.01029200000001,35.95473],"type":"Point"}
}