{
  "type": "Feature",
  "properties": {
    "addr:full":"100 E Queen St Edenton NC 27932",
    "addr:housenumber":"100",
    "addr:postcode":"27932",
    "addr:street":"E Queen St",
    "iso:country":"US",
    "sg:address":"100 E Queen St",
    "sg:city":"Edenton",
    "sg:classifiers":[
        {
            "category":"Insurance",
            "subcategory":"Insurance Agent",
            "type":"Services"
        }
    ],
    "sg:phone":"+1 252 482 0622",
    "sg:postcode":"27932",
    "sg:province":"NC",
    "wof:name":"Brooke Insurance",
    "wof:placetype":"venue"
},
  "geometry": {"coordinates":[-76.60856,36.059903],"type":"Point"}
}