{
  "type": "Feature",
  "properties": {
    "addr:full":"705 E Dixon Blvd Shelby NC 28152",
    "addr:housenumber":"705",
    "addr:postcode":"28152",
    "addr:street":"E Dixon Blvd",
    "iso:country":"US",
    "sg:address":"705 E Dixon Blvd",
    "sg:city":"Shelby",
    "sg:classifiers":[
        {
            "category":"Shopping",
            "subcategory":"Optical Goods",
            "type":"Retail Goods"
        }
    ],
    "sg:phone":"+1 704 487 0088",
    "sg:postcode":"28152",
    "sg:province":"NC",
    "wof:name":"National Vision",
    "wof:placetype":"venue"
},
  "geometry": {"coordinates":[-81.527777,35.27421],"type":"Point"}
}