{
  "type": "Feature",
  "properties": {
    "addr:full":"4972 Bullock School Rd Rocky Mount NC 27801",
    "addr:housenumber":"4972",
    "addr:postcode":"27801",
    "addr:street":"Bullock School Rd",
    "iso:country":"US",
    "sg:address":"4972 Bullock School Rd",
    "sg:city":"Rocky Mount",
    "sg:classifiers":[
        {
            "category":"Insurance",
            "subcategory":"Insurance Agent",
            "type":"Services"
        }
    ],
    "sg:phone":"+1 252 985 1859",
    "sg:postcode":"27801",
    "sg:province":"NC",
    "wof:name":"Catrese Green Insurance",
    "wof:placetype":"venue"
},
  "geometry": {"coordinates":[-77.75236,35.875941],"type":"Point"}
}