{
  "type": "Feature",
  "properties": {
    "iso:country":"US",
    "sg:address":"100 N Yadkin Ave",
    "sg:city":"Spencer",
    "sg:classifiers":[
        {
            "category":"Retail",
            "subcategory":"Repair Shop",
            "type":"Services"
        }
    ],
    "sg:phone":"+1 704 636 4357",
    "sg:postcode":"28159",
    "sg:province":"NC",
    "sg:tags":[
        "key"
    ],
    "wof:name":"A Call For Help Lockout Svc",
    "wof:placetype":"venue"
},
  "geometry": {"coordinates":[-80.430598,35.69208],"type":"Point"}
}