{
  "type": "Feature",
  "properties": {
    "addr:full":"275 Pressly Foushee Rd Sanford NC 27330",
    "addr:housenumber":"275",
    "addr:postcode":"27330",
    "addr:street":"Pressly Foushee Rd",
    "iso:country":"US",
    "sg:address":"275 Pressly Foushee Rd",
    "sg:city":"Sanford",
    "sg:classifiers":[
        {
            "category":"Coffee & Tea",
            "type":"Food & Drink"
        },
        {
            "category":"Bakery",
            "type":"Food & Drink"
        },
        {
            "category":"Donuts",
            "type":"Food & Drink"
        }
    ],
    "sg:menulink":"http://www.allmenus.com/nc/pocket/231035-daylight-donuts/menu/",
    "sg:phone":"+1 919 865 4778",
    "sg:postcode":"27330",
    "sg:province":"NC",
    "sg:tags":[
        "american",
        "pastry"
    ],
    "wof:name":"Daylight Donuts",
    "wof:placetype":"venue"
},
  "geometry": {"coordinates":[-79.227191,35.434937],"type":"Point"}
}