{
  "type": "Feature",
  "properties": {
    "addr:full":"1935 S Main St Salisbury NC 28144",
    "addr:housenumber":"1935",
    "addr:postcode":"28144",
    "addr:street":"S Main St",
    "iso:country":"US",
    "sg:address":"1935 S Main St",
    "sg:city":"Salisbury",
    "sg:classifiers":[
        {
            "category":"Home & Garden",
            "subcategory":"Building Materials",
            "type":"Retail Goods"
        }
    ],
    "sg:phone":"+1 704 636 5834",
    "sg:postcode":"28144",
    "sg:province":"NC",
    "wof:name":"ICI Dulux Paint Centers",
    "wof:placetype":"venue"
},
  "geometry": {"coordinates":[-80.495656,35.653505],"type":"Point"}
}