{
  "type": "Feature",
  "properties": {
    "addr:full":"207 Fisher Ferry St Thomasville NC 27360",
    "addr:housenumber":"207",
    "addr:postcode":"27360",
    "addr:street":"Fisher Ferry St",
    "iso:country":"US",
    "sg:address":"207 Fisher Ferry St",
    "sg:city":"Thomasville",
    "sg:classifiers":[
        {
            "category":"Restaurant",
            "type":"Food & Drink"
        }
    ],
    "sg:phone":"+1 336 475 6211",
    "sg:postcode":"27360",
    "sg:province":"NC",
    "sg:tags":[
        "sandwich"
    ],
    "wof:name":"Mason's Sandwich Shop",
    "wof:placetype":"venue"
},
  "geometry": {"coordinates":[-80.083549,35.876987],"type":"Point"}
}