{
  "type": "Feature",
  "properties": {
    "addr:full":"817 Colonial Dr Burlington NC 27215",
    "addr:housenumber":"817",
    "addr:postcode":"27215",
    "addr:street":"Colonial Dr",
    "iso:country":"US",
    "sg:address":"817 Colonial Dr",
    "sg:city":"Burlington",
    "sg:classifiers":[
        {
            "category":"Health Services",
            "subcategory":"Doctor",
            "type":"Services"
        }
    ],
    "sg:phone":"+1   ",
    "sg:postcode":"27215",
    "sg:province":"NC",
    "sg:tags":[
        "medical"
    ],
    "wof:name":"George E Rinker MD PA",
    "wof:placetype":"venue"
},
  "geometry": {"coordinates":[-79.48502999999999,36.085279],"type":"Point"}
}