{
  "type": "Feature",
  "properties": {
    "addr:full":"1905 S Main St Wake Forest NC 27587",
    "addr:housenumber":"1905",
    "addr:postcode":"27587",
    "addr:street":"S Main St",
    "iso:country":"US",
    "sg:address":"1905 S Main St",
    "sg:city":"Wake Forest",
    "sg:classifiers":[
        {
            "category":"Personal",
            "subcategory":"Beauty Salon",
            "type":"Services"
        }
    ],
    "sg:phone":"+1 919 570 1006",
    "sg:postcode":"27587",
    "sg:province":"NC",
    "wof:name":"Shear Brilliance",
    "wof:placetype":"venue"
},
  "geometry": {"coordinates":[-78.529353,35.950645],"type":"Point"}
}