{
  "type": "Feature",
  "properties": {
    "iso:country":"US",
    "sg:address":"343 Lynch Point Rd",
    "sg:city":"Macon",
    "sg:classifiers":[
        {
            "category":"Building & Trades",
            "subcategory":"Construction",
            "type":"Services"
        }
    ],
    "sg:phone":"+1 252 257 4315",
    "sg:postcode":"27551",
    "sg:province":"NC",
    "sg:tags":[
        "painter"
    ],
    "wof:name":"Sanderson Painting",
    "wof:placetype":"venue"
},
  "geometry": {"coordinates":[-78.05479699999999,36.532867],"type":"Point"}
}