{
  "type": "Feature",
  "properties": {
    "iso:country":"US",
    "sg:address":"7017 E W T Harris Blvd",
    "sg:city":"Charlotte",
    "sg:classifiers":[
        {
            "category":"Wholesale",
            "subcategory":"Electrical",
            "type":"Manufacturing & Wholesale Goods"
        }
    ],
    "sg:phone":"+1 704 537 3331",
    "sg:postcode":"28215",
    "sg:province":"NC",
    "sg:tags":[
        "electronic"
    ],
    "wof:name":"Weams",
    "wof:placetype":"venue"
},
  "geometry": {"coordinates":[-80.725531,35.224624],"type":"Point"}
}