{
  "type": "Feature",
  "properties": {
    "addr:full":"1314 W Carthage Rd Lumberton NC 28360",
    "addr:housenumber":"1314",
    "addr:postcode":"28360",
    "addr:street":"W Carthage Rd",
    "iso:country":"US",
    "sg:address":"1314 W Carthage Rd",
    "sg:city":"Lumberton",
    "sg:classifiers":[
        {
            "category":"Retail",
            "subcategory":"Repair Shop",
            "type":"Services"
        }
    ],
    "sg:phone":"+1   ",
    "sg:postcode":"28360",
    "sg:province":"NC",
    "sg:tags":[
        "electrical"
    ],
    "wof:name":"B C D",
    "wof:placetype":"venue"
},
  "geometry": {"coordinates":[-79.03343700000001,34.651052],"type":"Point"}
}