{
  "type": "Feature",
  "properties": {
    "addr:full":"1019 Spring Ln Sanford NC 27330",
    "addr:housenumber":"1019",
    "addr:postcode":"27330",
    "addr:street":"Spring Ln",
    "iso:country":"US",
    "sg:address":"1019 Spring Ln",
    "sg:city":"Sanford",
    "sg:classifiers":[
        {
            "category":"Shopping",
            "subcategory":"Music",
            "type":"Retail Goods"
        }
    ],
    "sg:phone":"+1 919 708 7002",
    "sg:postcode":"27330",
    "sg:province":"NC",
    "sg:tags":[
        "compact",
        "record",
        "disc",
        "tape"
    ],
    "wof:name":"Sam Goody",
    "wof:placetype":"venue"
},
  "geometry": {"coordinates":[-79.198635,35.487436],"type":"Point"}
}