{
  "type": "Feature",
  "properties": {
    "addr:full":"3016 N Twelve Mile Creek Rd Matthews NC 28104",
    "addr:housenumber":"3016",
    "addr:postcode":"28104",
    "addr:street":"N Twelve Mile Creek Rd",
    "iso:country":"US",
    "sg:address":"3016 N Twelve Mile Creek Rd",
    "sg:city":"Matthews",
    "sg:classifiers":[
        {
            "category":"Organizations",
            "subcategory":"Religious Organization",
            "type":"Services"
        }
    ],
    "sg:phone":"+1 704 843 2438",
    "sg:postcode":"28104",
    "sg:province":"NC",
    "sg:tags":[
        "church"
    ],
    "wof:name":"Union United Methodist Church",
    "wof:placetype":"venue"
},
  "geometry": {"coordinates":[-80.723331,35.019343],"type":"Point"}
}