{
  "type": "Feature",
  "properties": {
    "addr:full":"5663 US Hwy 13 Mount Olive NC 28365",
    "addr:housenumber":"5663",
    "addr:postcode":"28365",
    "addr:street":"Us Hwy 13",
    "iso:country":"US",
    "sg:address":"5663 US Hwy 13",
    "sg:city":"Mount Olive",
    "sg:classifiers":[
        {
            "category":"Organizations",
            "subcategory":"Religious Organization",
            "type":"Services"
        }
    ],
    "sg:phone":"+1   ",
    "sg:postcode":"28365",
    "sg:province":"NC",
    "wof:name":"Jordans Chapel Baptist Church",
    "wof:placetype":"venue"
},
  "geometry": {"coordinates":[-78.263143,35.281691],"type":"Point"}
}