{
  "type": "Feature",
  "properties": {
    "addr:full":"209 Waterford Cir Lumberton NC 28358",
    "addr:housenumber":"209",
    "addr:postcode":"28358",
    "addr:street":"Waterford Cir",
    "iso:country":"US",
    "sg:address":"209 Waterford Cir",
    "sg:city":"Lumberton",
    "sg:classifiers":[
        {
            "category":"Professional",
            "subcategory":"Management & Consulting",
            "type":"Services"
        }
    ],
    "sg:phone":"+1 910 739 3058",
    "sg:postcode":"28358",
    "sg:province":"NC",
    "sg:tags":[
        "educational"
    ],
    "wof:name":"Leadership MGT Solutions",
    "wof:placetype":"venue"
},
  "geometry": {"coordinates":[-78.99021999999999,34.669719],"type":"Point"}
}