{
  "type": "Feature",
  "properties": {
    "iso:country":"US",
    "sg:address":"5335 Odell School Rd",
    "sg:city":"Davidson",
    "sg:classifiers":[
        {
            "category":"Organizations",
            "subcategory":"Community Association",
            "type":"Services"
        }
    ],
    "sg:phone":"+1   ",
    "sg:postcode":"28036",
    "sg:province":"NC",
    "wof:name":"Tony Gene Moose",
    "wof:placetype":"venue"
},
  "geometry": {"coordinates":[-80.759024,35.486189],"type":"Point"}
}