{
  "type": "Feature",
  "properties": {
    "iso:country":"US",
    "sg:address":"937 Harkers Island Rd",
    "sg:city":"Beaufort",
    "sg:classifiers":[
        {
            "category":"Shopping",
            "subcategory":"Gifts & Souvenirs",
            "type":"Retail Goods"
        }
    ],
    "sg:phone":"+1 252 838 8814",
    "sg:postcode":"28516",
    "sg:province":"NC",
    "sg:tags":[
        "shop"
    ],
    "wof:name":"Kindred Spirit Gifts & Access",
    "wof:placetype":"venue"
},
  "geometry": {"coordinates":[-76.558345,34.741342],"type":"Point"}
}