{
  "type": "Feature",
  "properties": {
    "addr:full":"1662 Lower Hopedale Rd Burlington NC 27217",
    "addr:housenumber":"1662",
    "addr:postcode":"27217",
    "addr:street":"Lower Hopedale Rd",
    "iso:country":"US",
    "sg:address":"1662 Lower Hopedale Rd",
    "sg:city":"Burlington",
    "sg:classifiers":[
        {
            "category":"Shopping",
            "subcategory":"Clothing, Apparel, & Fashions",
            "type":"Retail Goods"
        }
    ],
    "sg:phone":"+1 336 226 2548",
    "sg:postcode":"27217",
    "sg:province":"NC",
    "wof:name":"Johnnys Custom Caps & T-Shirts",
    "wof:placetype":"venue"
},
  "geometry": {"coordinates":[-79.42836699999999,36.117168],"type":"Point"}
}