{
  "type": "Feature",
  "properties": {
    "addr:full":"451 N Fayetteville St Asheboro NC 27203",
    "addr:housenumber":"451",
    "addr:postcode":"27203",
    "addr:street":"N;St",
    "iso:country":"US",
    "sg:address":"451 N Fayetteville St",
    "sg:city":"Asheboro",
    "sg:classifiers":[
        {
            "category":"Shopping",
            "subcategory":"Used Merchandise",
            "type":"Retail Goods"
        }
    ],
    "sg:phone":"+1 336 629 3706",
    "sg:postcode":"27203",
    "sg:province":"NC",
    "wof:name":"B&M Consignment & Gifts Inc",
    "wof:placetype":"venue"
},
  "geometry": {"coordinates":[-79.81242899999999,35.712019],"type":"Point"}
}