{
  "type": "Feature",
  "properties": {
    "addr:full":"4652 Brompton Dr Greensboro NC 27407",
    "addr:housenumber":"4652",
    "addr:postcode":"27407",
    "addr:street":"Brompton Dr",
    "iso:country":"US",
    "sg:address":"4652 Brompton Dr",
    "sg:city":"Greensboro",
    "sg:classifiers":[
        {
            "category":"Shopping",
            "subcategory":"Hobbies, Toys, & Games",
            "type":"Retail Goods"
        }
    ],
    "sg:phone":"+1 336 854 3597",
    "sg:postcode":"27407",
    "sg:province":"NC",
    "sg:tags":[
        "craft"
    ],
    "wof:name":"JWR Enterprises",
    "wof:placetype":"venue"
},
  "geometry": {"coordinates":[-79.863709,36.072987],"type":"Point"}
}