{
  "type": "Feature",
  "properties": {
    "iso:country":"US",
    "sg:address":"9369 Twisted Hickory Rd",
    "sg:city":"Bladenboro",
    "sg:classifiers":[
        {
            "category":"Professional",
            "subcategory":"Business Services",
            "type":"Services"
        },
        {
            "category":"Farming",
            "subcategory":"Farm",
            "type":"Manufacturing & Wholesale Goods"
        }
    ],
    "sg:phone":"+1 910 648 6810",
    "sg:postcode":"28320",
    "sg:province":"NC",
    "wof:name":"Britt Mark Poultry Farm",
    "wof:placetype":"venue"
},
  "geometry": {"coordinates":[-78.666025,34.551754],"type":"Point"}
}