{
  "type": "Feature",
  "properties": {
    "addr:full":"3876 Elijah Baum Rd Kitty Hawk NC 27949",
    "addr:housenumber":"3876",
    "addr:postcode":"27949",
    "addr:street":"Elijah Baum Rd",
    "iso:country":"US",
    "sg:address":"3876 Elijah Baum Rd",
    "sg:city":"Kitty Hawk",
    "sg:classifiers":[
        {
            "category":"Building & Trades",
            "subcategory":"Construction",
            "type":"Services"
        }
    ],
    "sg:phone":"+1 252 449 5008",
    "sg:postcode":"27949",
    "sg:province":"NC",
    "sg:tags":[
        "contractor"
    ],
    "wof:name":"Precision Pools Inc",
    "wof:placetype":"venue"
},
  "geometry": {"coordinates":[-75.702764,36.059174],"type":"Point"}
}