{
  "type": "Feature",
  "properties": {
    "iso:country":"US",
    "sg:address":"214 Northmont Rd",
    "sg:city":"Taylorsville",
    "sg:classifiers":[
        {
            "category":"Retail",
            "subcategory":"Auto Repair",
            "type":"Services"
        }
    ],
    "sg:phone":"+1 828 632 2086",
    "sg:postcode":"28681",
    "sg:province":"NC",
    "sg:tags":[
        "body",
        "automobile",
        "painting"
    ],
    "wof:name":"Sigmon Motor Co",
    "wof:placetype":"venue"
},
  "geometry": {"coordinates":[-81.18957899999999,35.941412],"type":"Point"}
}