{
  "type": "Feature",
  "properties": {
    "addr:full":"7101 Hunters Club Dr Trinity NC 27370",
    "addr:housenumber":"7101",
    "addr:postcode":"27370",
    "addr:street":"Hunters Club Dr",
    "iso:country":"US",
    "sg:address":"7101 Hunters Club Dr",
    "sg:city":"Trinity",
    "sg:classifiers":[
        {
            "category":"Real Estate",
            "subcategory":"Real Estate Agent",
            "type":"Services"
        }
    ],
    "sg:phone":"+1 336 476 4194",
    "sg:postcode":"27370",
    "sg:province":"NC",
    "wof:name":"GMW Properties Inc",
    "wof:placetype":"venue"
},
  "geometry": {"coordinates":[-80.03738199999999,35.854428],"type":"Point"}
}