{
  "type": "Feature",
  "properties": {
    "addr:full":"3281 Avent Ferry Rd Ste 125 Raleigh NC 27606",
    "addr:housenumber":"3281",
    "addr:postcode":"27606",
    "addr:street":"Avent Ferry Rd Ste 125",
    "iso:country":"US",
    "sg:address":"3281 Avent Ferry Rd Ste 125",
    "sg:city":"Raleigh",
    "sg:classifiers":[
        {
            "category":"Insurance",
            "subcategory":"Insurance Agent",
            "type":"Services"
        },
        {
            "category":"Insurance",
            "subcategory":"Hazard Insurance",
            "type":"Services"
        }
    ],
    "sg:phone":"+1 919 233 4990",
    "sg:postcode":"27606",
    "sg:province":"NC",
    "sg:tags":[
        "auto",
        "recreational",
        "motorcycle",
        "vehicle",
        "marine",
        "boat"
    ],
    "sg:website":"www.choice-ins.com",
    "wof:name":"Choice Insurance Services",
    "wof:placetype":"venue"
},
  "geometry": {"coordinates":[-78.695583,35.767884],"type":"Point"}
}