{
  "type": "Feature",
  "properties": {
    "addr:full":"2946 Calloway Dr Mebane NC 27302",
    "addr:housenumber":"2946",
    "addr:postcode":"27302",
    "addr:street":"Calloway Dr",
    "iso:country":"US",
    "sg:address":"2946 Calloway Dr",
    "sg:city":"Mebane",
    "sg:classifiers":[
        {
            "category":"Professional",
            "type":"Services"
        }
    ],
    "sg:phone":"+1 919 563 2670",
    "sg:postcode":"27302",
    "sg:province":"NC",
    "wof:name":"Barry Harward",
    "wof:placetype":"venue"
},
  "geometry": {"coordinates":[-79.28457299999999,36.027671],"type":"Point"}
}