{
  "type": "Feature",
  "properties": {
    "iso:country":"US",
    "sg:address":"7907 Providence Rd W",
    "sg:city":"Charlotte",
    "sg:classifiers":[
        {
            "category":"Real Estate",
            "subcategory":"Real Estate Agent",
            "type":"Services"
        }
    ],
    "sg:phone":"+1 704 650 6345",
    "sg:postcode":"28277",
    "sg:province":"NC",
    "wof:name":"Jaime Leggett",
    "wof:placetype":"venue"
},
  "geometry": {"coordinates":[-80.811785,35.054565],"type":"Point"}
}