{
  "type": "Feature",
  "properties": {
    "iso:country":"US",
    "sg:address":"113 Arendell St",
    "sg:city":"Morehead City",
    "sg:classifiers":[
        {
            "category":"Travel",
            "subcategory":"Travel Agent",
            "type":"Entertainment"
        }
    ],
    "sg:phone":"+1 252 726 2511",
    "sg:postcode":"28557",
    "sg:province":"NC",
    "sg:tags":[
        "agency",
        "steamship"
    ],
    "wof:name":"Inchcape Shipping Svc",
    "wof:placetype":"venue"
},
  "geometry": {"coordinates":[-76.69963199999999,34.720769],"type":"Point"}
}