{
  "type": "Feature",
  "properties": {
    "iso:country":"US",
    "sg:address":"2745 Woodstock Rd",
    "sg:city":"Belhaven",
    "sg:classifiers":[
        {
            "category":"Farming",
            "subcategory":"Farm",
            "type":"Manufacturing & Wholesale Goods"
        }
    ],
    "sg:phone":"+1 252 964 4125",
    "sg:postcode":"27810",
    "sg:province":"NC",
    "wof:name":"G & M Farms Inc",
    "wof:placetype":"venue"
},
  "geometry": {"coordinates":[-76.63051900000001,35.465522],"type":"Point"}
}