{
  "type": "Feature",
  "properties": {
    "addr:full":"407 Main St North Wilkesboro NC 28659",
    "addr:housenumber":"407",
    "addr:postcode":"28659",
    "addr:street":"Main St",
    "iso:country":"US",
    "sg:address":"407 Main St",
    "sg:city":"North Wilkesboro",
    "sg:classifiers":[
        {
            "category":"Insurance",
            "subcategory":"Insurance Agent",
            "type":"Services"
        }
    ],
    "sg:phone":"+1 336 667 7111",
    "sg:postcode":"28659",
    "sg:province":"NC",
    "wof:name":"Duncan Insurance",
    "wof:placetype":"venue"
},
  "geometry": {"coordinates":[-81.139376,36.162364],"type":"Point"}
}