{
  "type": "Feature",
  "properties": {
    "iso:country":"US",
    "sg:address":"8500 Athena Ct",
    "sg:city":"Fuquay Varina",
    "sg:classifiers":[
        {
            "category":"Building & Trades",
            "subcategory":"Electrical",
            "type":"Services"
        }
    ],
    "sg:phone":"+1 919 552 3215",
    "sg:postcode":"27526",
    "sg:province":"NC",
    "sg:tags":[
        "electrical",
        "contractor"
    ],
    "wof:name":"Thr Electric",
    "wof:placetype":"venue"
},
  "geometry": {"coordinates":[-78.767883,35.56544],"type":"Point"}
}