{
  "type": "Feature",
  "properties": {
    "addr:full":"5710 High Point Rd Greensboro NC 27407",
    "addr:housenumber":"5710",
    "addr:postcode":"27407",
    "addr:street":"High Point Rd",
    "iso:country":"US",
    "sg:address":"5710 High Point Rd",
    "sg:city":"Greensboro",
    "sg:classifiers":[
        {
            "category":"Wholesale",
            "subcategory":"Auto Parts",
            "type":"Manufacturing & Wholesale Goods"
        }
    ],
    "sg:phone":"+1 336 454 7720",
    "sg:postcode":"27407",
    "sg:province":"NC",
    "sg:tags":[
        "automobile",
        "supply"
    ],
    "wof:name":"Reprise Auto Parts Intl",
    "wof:placetype":"venue"
},
  "geometry": {"coordinates":[-79.8961,36.01558],"type":"Point"}
}