{
  "type": "Feature",
  "properties": {
    "iso:country":"US",
    "sg:address":"5505 Wood Pond Ct",
    "sg:city":"Raleigh",
    "sg:classifiers":[
        {
            "category":"Professional",
            "type":"Services"
        }
    ],
    "sg:phone":"+1   ",
    "sg:postcode":"27610",
    "sg:province":"NC",
    "wof:name":"Gonzales Tree Service",
    "wof:placetype":"venue"
},
  "geometry": {"coordinates":[-78.547545,35.756077],"type":"Point"}
}