{
  "type": "Feature",
  "properties": {
    "addr:full":"7605 Beale Rd Snow Camp NC 27349",
    "addr:housenumber":"7605",
    "addr:postcode":"27349",
    "addr:street":"Beale Rd",
    "iso:country":"US",
    "sg:address":"7605 Beale Rd",
    "sg:city":"Snow Camp",
    "sg:phone":"+1 336 376 1362",
    "sg:postcode":"27349",
    "sg:province":"NC",
    "sg:tags":[
        "beef",
        "farm",
        "crop",
        "field",
        "cattle",
        "feedlot"
    ],
    "wof:name":"F McPherson",
    "wof:placetype":"venue"
},
  "geometry": {"coordinates":[-79.458102,35.911821],"type":"Point"}
}