{
  "type": "Feature",
  "properties": {
    "addr:full":"685 Jones Rd Winston Salem NC 27107",
    "addr:housenumber":"685",
    "addr:postcode":"27107",
    "addr:street":"Jones Rd",
    "iso:country":"US",
    "sg:address":"685 Jones Rd",
    "sg:city":"Winston Salem",
    "sg:classifiers":[
        {
            "category":"Building & Trades",
            "subcategory":"Plumbing",
            "type":"Services"
        }
    ],
    "sg:phone":"+1 336 788 5312",
    "sg:postcode":"27107",
    "sg:province":"NC",
    "sg:tags":[
        "plumbing",
        "contractor"
    ],
    "wof:name":"Dease Plumbing",
    "wof:placetype":"venue"
},
  "geometry": {"coordinates":[-80.20564899999999,36.001932],"type":"Point"}
}