{
  "type": "Feature",
  "properties": {
    "addr:full":"925 Woodland Ave Sanford NC 27330",
    "addr:housenumber":"925",
    "addr:postcode":"27330",
    "addr:street":"Woodland Ave",
    "iso:country":"US",
    "sg:address":"925 Woodland Ave",
    "sg:city":"Sanford",
    "sg:classifiers":[
        {
            "category":"Retail",
            "subcategory":"Self-service Laundry",
            "type":"Services"
        },
        {
            "category":"Retail",
            "subcategory":"Laundry & Dry Cleaning",
            "type":"Services"
        }
    ],
    "sg:phone":"+1 919 775 3314",
    "sg:postcode":"27330",
    "sg:province":"NC",
    "sg:tags":[
        "coin"
    ],
    "wof:name":"Maytag Laundry Center",
    "wof:placetype":"venue"
},
  "geometry": {"coordinates":[-79.170771,35.469208],"type":"Point"}
}