{
  "type": "Feature",
  "properties": {
    "iso:country":"US",
    "sg:address":"4921 Hollenden Dr",
    "sg:city":"Raleigh",
    "sg:classifiers":[
        {
            "category":"Shopping",
            "type":"Retail Goods"
        }
    ],
    "sg:phone":"+1 919 829 9288",
    "sg:postcode":"27616",
    "sg:province":"NC",
    "sg:tags":[
        "mural"
    ],
    "wof:name":"Artifects",
    "wof:placetype":"venue"
},
  "geometry": {"coordinates":[-78.57538099999999,35.853348],"type":"Point"}
}