{
  "type": "Feature",
  "properties": {
    "addr:full":"8552 University City Blvd Charlotte NC 28213",
    "addr:housenumber":"8552",
    "addr:postcode":"28213",
    "addr:street":"University City Blvd",
    "iso:country":"US",
    "sg:address":"8552 University City Blvd",
    "sg:city":"Charlotte",
    "sg:classifiers":[
        {
            "category":"Restaurant",
            "type":"Food & Drink"
        }
    ],
    "sg:menulink":"http://www.allmenus.com/nc/charlotte/89180-subway/menu/",
    "sg:phone":"+1 704 549 8519",
    "sg:postcode":"28213",
    "sg:province":"NC",
    "sg:tags":[
        "american",
        "sandwich"
    ],
    "wof:name":"Subway",
    "wof:placetype":"venue"
},
  "geometry": {"coordinates":[-80.74012999999999,35.297005],"type":"Point"}
}