{
  "type": "Feature",
  "properties": {
    "addr:full":"771 Austin Ln NW Winston Salem NC 27106",
    "addr:housenumber":"771",
    "addr:postcode":"27106",
    "addr:street":"Austin Ln Nw",
    "iso:country":"US",
    "sg:address":"771 Austin Ln NW",
    "sg:city":"Winston Salem",
    "sg:classifiers":[
        {
            "category":"Professional",
            "type":"Services"
        }
    ],
    "sg:phone":"+1 336 748 2691",
    "sg:postcode":"27106",
    "sg:province":"NC",
    "sg:tags":[
        "establishment"
    ],
    "wof:name":"Jeff Kintner-Real Estate",
    "wof:placetype":"venue"
},
  "geometry": {"coordinates":[-80.286967,36.109411],"type":"Point"}
}