{
  "type": "Feature",
  "properties": {
    "addr:full":"36 Pond Rd Halifax NC 27839",
    "addr:housenumber":"36",
    "addr:postcode":"27839",
    "addr:street":"Pond Rd",
    "iso:country":"US",
    "sg:address":"36 Pond Rd",
    "sg:city":"Halifax",
    "sg:classifiers":[
        {
            "category":"Building & Trades",
            "subcategory":"Plumbing",
            "type":"Services"
        }
    ],
    "sg:phone":"+1 252 536 3996",
    "sg:postcode":"27839",
    "sg:province":"NC",
    "sg:tags":[
        "septic"
    ],
    "wof:name":"Chantilly Septic Tank Clng Svc",
    "wof:placetype":"venue"
},
  "geometry": {"coordinates":[-77.633123,36.386517],"type":"Point"}
}