{
  "type": "Feature",
  "properties": {
    "addr:full":"128 N Sterling St Morganton NC 28655",
    "addr:housenumber":"128",
    "addr:postcode":"28655",
    "addr:street":"N Sterling St",
    "iso:country":"US",
    "sg:address":"128 N Sterling St",
    "sg:city":"Morganton",
    "sg:classifiers":[
        {
            "category":"Home & Garden",
            "subcategory":"Household Appliances",
            "type":"Retail Goods"
        },
        {
            "category":"Retail",
            "subcategory":"Repair Shop",
            "type":"Services"
        }
    ],
    "sg:phone":"+1 828 439 8050",
    "sg:postcode":"28655",
    "sg:province":"NC",
    "sg:tags":[
        "machine",
        "sewing",
        "center"
    ],
    "wof:name":"Morganton Sewing Center",
    "wof:placetype":"venue"
},
  "geometry": {"coordinates":[-81.68769500000001,35.745205],"type":"Point"}
}