{
  "type": "Feature",
  "properties": {
    "addr:full":"830 Drummond Ave Charlotte NC 28205",
    "addr:housenumber":"830",
    "addr:postcode":"28205",
    "addr:street":"Drummond Ave",
    "iso:country":"US",
    "sg:address":"830 Drummond Ave",
    "sg:city":"Charlotte",
    "sg:classifiers":[
        {
            "category":"Wholesale",
            "subcategory":"Vending Machines",
            "type":"Manufacturing & Wholesale Goods"
        }
    ],
    "sg:phone":"+1 704 372 9299",
    "sg:postcode":"28205",
    "sg:province":"NC",
    "wof:name":"Gardner's Vending",
    "wof:placetype":"venue"
},
  "geometry": {"coordinates":[-80.809577,35.238798],"type":"Point"}
}