{
  "type": "Feature",
  "properties": {
    "iso:country":"US",
    "sg:address":"6130 Andrew Thomas Dr # 124",
    "sg:city":"Charlotte",
    "sg:classifiers":[
        {
            "category":"Recreation",
            "subcategory":"Picnic Area",
            "type":"Entertainment"
        }
    ],
    "sg:phone":"+1 704 598 1188",
    "sg:postcode":"28269",
    "sg:province":"NC",
    "sg:tags":[
        "farm",
        "repair",
        "equipment-parts"
    ],
    "wof:name":"Lanescapes Lighting & Irrigation",
    "wof:placetype":"venue"
},
  "geometry": {"coordinates":[-80.80023,35.331104],"type":"Point"}
}