{
  "type": "Feature",
  "properties": {
    "iso:country":"US",
    "sg:address":"217 Lindsay St",
    "sg:city":"High Point",
    "sg:classifiers":[
        {
            "category":"Professional",
            "subcategory":"Computer Services",
            "type":"Services"
        }
    ],
    "sg:phone":"+1 336 883 9866",
    "sg:postcode":"27262",
    "sg:province":"NC",
    "sg:tags":[
        "internet"
    ],
    "wof:name":"Blakeye Media",
    "wof:placetype":"venue"
},
  "geometry": {"coordinates":[-80.011747,35.956842],"type":"Point"}
}