{
  "type": "Feature",
  "properties": {
    "iso:country":"US",
    "sg:address":"5925 Carnegie Blvd",
    "sg:city":"Charlotte",
    "sg:classifiers":[
        {
            "category":"Banks & Credit Unions",
            "subcategory":"Financial Services",
            "type":"Services"
        }
    ],
    "sg:phone":"+1 704 643 5000",
    "sg:postcode":"28209",
    "sg:province":"NC",
    "sg:tags":[
        "investment"
    ],
    "wof:name":"Integrated Fincl Strategies",
    "wof:placetype":"venue"
},
  "geometry": {"coordinates":[-80.840451,35.155756],"type":"Point"}
}