{
  "type": "Feature",
  "properties": {
    "iso:country":"US",
    "sg:address":"104 Pearson Dr",
    "sg:city":"Asheville",
    "sg:classifiers":[
        {
            "category":"Building & Trades",
            "subcategory":"Construction",
            "type":"Services"
        }
    ],
    "sg:phone":"+1 828 215 1775",
    "sg:postcode":"28801",
    "sg:province":"NC",
    "sg:tags":[
        "builder",
        "operative"
    ],
    "wof:name":"Hands of Sean Perry",
    "wof:placetype":"venue"
},
  "geometry": {"coordinates":[-82.565651,35.602122],"type":"Point"}
}