{
  "type": "Feature",
  "properties": {
    "addr:full":"114 White Pines Country Club Rd Mount Airy NC 27030",
    "addr:housenumber":"114",
    "addr:postcode":"27030",
    "addr:street":"White Pines Country Club Rd",
    "iso:country":"US",
    "sg:address":"114 White Pines Country Club Rd",
    "sg:city":"Mount Airy",
    "sg:classifiers":[
        {
            "category":"Home & Garden",
            "subcategory":"Mobile Homes",
            "type":"Retail Goods"
        }
    ],
    "sg:phone":"+1 336 719 1523",
    "sg:postcode":"27030",
    "sg:province":"NC",
    "wof:name":"Top Line Homes Inc",
    "wof:placetype":"venue"
},
  "geometry": {"coordinates":[-80.653261,36.552765],"type":"Point"}
}