{
  "type": "Feature",
  "properties": {
    "addr:full":"1118 Scholastic Cir Durham NC 27713",
    "addr:housenumber":"1118",
    "addr:postcode":"27713",
    "addr:street":"Scholastic Cir",
    "iso:country":"US",
    "sg:address":"1118 Scholastic Cir",
    "sg:city":"Durham",
    "sg:classifiers":[
        {
            "category":"Professional",
            "subcategory":"Management & Consulting",
            "type":"Services"
        },
        {
            "category":"Health Services",
            "subcategory":"Health Practitioner",
            "type":"Services"
        }
    ],
    "sg:phone":"+1 919 572 2400",
    "sg:postcode":"27713",
    "sg:province":"NC",
    "sg:tags":[
        "consultant",
        "psychologist",
        "business"
    ],
    "wof:name":"Circle Consulting Group LLC",
    "wof:placetype":"venue"
},
  "geometry": {"coordinates":[-78.953667,35.890365],"type":"Point"}
}