{
  "type": "Feature",
  "properties": {
    "addr:full":"203 E Broad St St Pauls NC 28384",
    "addr:housenumber":"203",
    "addr:postcode":"28384",
    "addr:street":"E Broad St",
    "iso:country":"US",
    "sg:address":"203 E Broad St",
    "sg:city":"St Pauls",
    "sg:classifiers":[
        {
            "category":"Restaurant",
            "type":"Food & Drink"
        }
    ],
    "sg:phone":"+1 910 865 4911",
    "sg:postcode":"28384",
    "sg:province":"NC",
    "sg:tags":[
        "eating"
    ],
    "wof:name":"Pauline's Place",
    "wof:placetype":"venue"
},
  "geometry": {"coordinates":[-78.969657,34.806493],"type":"Point"}
}