{
  "type": "Feature",
  "properties": {
    "iso:country":"US",
    "sg:address":"1071 Hennis Rd",
    "sg:city":"Sandy Ridge",
    "sg:classifiers":[
        {
            "category":"Building & Trades",
            "subcategory":"Plumbing",
            "type":"Services"
        }
    ],
    "sg:phone":"+1 336 871 3939",
    "sg:postcode":"27046",
    "sg:province":"NC",
    "sg:tags":[
        "conditioning",
        "air",
        "system",
        "contractor"
    ],
    "wof:name":"Carolina Custom Comfort",
    "wof:placetype":"venue"
},
  "geometry": {"coordinates":[-80.035888,36.532061],"type":"Point"}
}