{
  "type": "Feature",
  "properties": {
    "addr:full":"128 E Franklin St Youngsville NC 27596",
    "addr:housenumber":"128",
    "addr:postcode":"27596",
    "addr:street":"E Franklin St",
    "iso:country":"US",
    "sg:address":"128 E Franklin St",
    "sg:city":"Youngsville",
    "sg:classifiers":[
        {
            "category":"Professional",
            "type":"Services"
        }
    ],
    "sg:phone":"+1 919 554 1025",
    "sg:postcode":"27596",
    "sg:province":"NC",
    "sg:tags":[
        "establishment"
    ],
    "wof:name":"Aqua-Matic Inc",
    "wof:placetype":"venue"
},
  "geometry": {"coordinates":[-78.475114,36.026086],"type":"Point"}
}