{
  "type": "Feature",
  "properties": {
    "iso:country":"US",
    "sg:address":"5544 Chaucer Trl",
    "sg:city":"Pleasant Garden",
    "sg:classifiers":[
        {
            "category":"Building & Trades",
            "subcategory":"Construction",
            "type":"Services"
        }
    ],
    "sg:phone":"+1 336 685 4597",
    "sg:postcode":"27313",
    "sg:province":"NC",
    "sg:tags":[
        "carpentry",
        "contractor"
    ],
    "wof:name":"R & W Construction",
    "wof:placetype":"venue"
},
  "geometry": {"coordinates":[-79.74362000000001,35.882269],"type":"Point"}
}