{
  "type": "Feature",
  "properties": {
    "addr:full":"6212 Sugar Pine Dr Wilmington NC 28412",
    "addr:housenumber":"6212",
    "addr:postcode":"28412",
    "addr:street":"Sugar Pine Dr",
    "iso:country":"US",
    "sg:address":"6212 Sugar Pine Dr",
    "sg:city":"Wilmington",
    "sg:classifiers":[
        {
            "category":"Building & Trades",
            "subcategory":"Plumbing",
            "type":"Services"
        }
    ],
    "sg:phone":"+1 910 392 3855",
    "sg:postcode":"28412",
    "sg:province":"NC",
    "sg:tags":[
        "contractor"
    ],
    "wof:name":"Rjp Mechanical",
    "wof:placetype":"venue"
},
  "geometry": {"coordinates":[-77.921359,34.114306],"type":"Point"}
}