{
  "type": "Feature",
  "properties": {
    "addr:full":"5164 Fallston Rd Lawndale NC 28090",
    "addr:postcode":"5164;28090",
    "addr:street":"Fallston Rd",
    "iso:country":"US",
    "sg:address":"5164 Fallston Rd",
    "sg:city":"Lawndale",
    "sg:classifiers":[
        {
            "category":"Home & Garden",
            "subcategory":"Garden Supply",
            "type":"Retail Goods"
        }
    ],
    "sg:phone":"+1 704 538 1908",
    "sg:postcode":"28090",
    "sg:province":"NC",
    "sg:tags":[
        "center"
    ],
    "wof:name":"Ginger's Gardens",
    "wof:placetype":"venue"
},
  "geometry": {"coordinates":[-81.501397,35.447435],"type":"Point"}
}