{
  "type": "Feature",
  "properties": {
    "addr:full":"736 Mial St Raleigh NC 27608",
    "addr:housenumber":"736",
    "addr:postcode":"27608",
    "addr:street":"Mial St",
    "iso:country":"US",
    "sg:address":"736 Mial St",
    "sg:city":"Raleigh",
    "sg:classifiers":[
        {
            "category":"Home & Garden",
            "subcategory":"Home Furnishings",
            "type":"Retail Goods"
        }
    ],
    "sg:phone":"+1 919 637 7537",
    "sg:postcode":"27608",
    "sg:province":"NC",
    "sg:tags":[
        "house"
    ],
    "wof:name":"Fire Stone Home Products",
    "wof:placetype":"venue"
},
  "geometry": {"coordinates":[-78.626445,35.811019],"type":"Point"}
}