{
  "type": "Feature",
  "properties": {
    "iso:country":"US",
    "sg:address":"108 Willow Ln",
    "sg:city":"Mocksville",
    "sg:classifiers":[
        {
            "category":"Organizations",
            "subcategory":"Religious Organization",
            "type":"Services"
        }
    ],
    "sg:phone":"+1 336 284 4143",
    "sg:postcode":"27028",
    "sg:province":"NC",
    "sg:tags":[
        "church"
    ],
    "wof:name":"New Shepard Baptist Church",
    "wof:placetype":"venue"
},
  "geometry": {"coordinates":[-80.602879,35.858488],"type":"Point"}
}