{
  "type": "Feature",
  "properties": {
    "addr:full":"1449 Pinefield Dr Sophia NC 27350",
    "addr:housenumber":"1449",
    "addr:postcode":"27350",
    "addr:street":"Pinefield Dr",
    "iso:country":"US",
    "sg:address":"1449 Pinefield Dr",
    "sg:city":"Sophia",
    "sg:classifiers":[
        {
            "category":"Building & Trades",
            "subcategory":"Construction",
            "type":"Services"
        }
    ],
    "sg:phone":"+1 336 498 2180",
    "sg:postcode":"27350",
    "sg:province":"NC",
    "sg:tags":[
        "contractor"
    ],
    "wof:name":"Howell Masonry",
    "wof:placetype":"venue"
},
  "geometry": {"coordinates":[-79.857485,35.792809],"type":"Point"}
}