{
  "type": "Feature",
  "properties": {
    "iso:country":"US",
    "sg:address":"104 Marina Dr",
    "sg:city":"New Bern",
    "sg:classifiers":[
        {
            "category":"Real Estate",
            "subcategory":"Real Estate Agent",
            "type":"Services"
        }
    ],
    "sg:phone":"+1 252 637 0303",
    "sg:postcode":"28560",
    "sg:province":"NC",
    "wof:name":"Robert E Lee",
    "wof:placetype":"venue"
},
  "geometry": {"coordinates":[-76.966863,35.065208],"type":"Point"}
}