{
  "type": "Feature",
  "properties": {
    "addr:full":"115 Eagles Nest Rd Waynesville NC 28786",
    "addr:housenumber":"115",
    "addr:postcode":"28786",
    "addr:street":"Eagles Nest Rd",
    "iso:country":"US",
    "sg:address":"115 Eagles Nest Rd",
    "sg:city":"Waynesville",
    "sg:classifiers":[
        {
            "category":"Shopping",
            "subcategory":"Discount & Variety Stores",
            "type":"Retail Goods"
        }
    ],
    "sg:phone":"+1 828 456 9949",
    "sg:postcode":"28786",
    "sg:province":"NC",
    "wof:name":"Dollar General",
    "wof:placetype":"venue"
},
  "geometry": {"coordinates":[-83.009733,35.482639],"type":"Point"}
}