{
  "type": "Feature",
  "properties": {
    "iso:country":"US",
    "sg:address":"700 E 4th St",
    "sg:city":"Charlotte",
    "sg:classifiers":[
        {
            "category":"Government",
            "subcategory":"Court House",
            "type":"Public Place"
        }
    ],
    "sg:phone":"+1 704 347 7800",
    "sg:postcode":"28202",
    "sg:province":"NC",
    "sg:tags":[
        "city"
    ],
    "wof:name":"Charlotte Superior Judge",
    "wof:placetype":"venue"
},
  "geometry": {"coordinates":[-80.836207,35.219533],"type":"Point"}
}