{
  "type": "Feature",
  "properties": {
    "iso:country":"US",
    "sg:address":"1824 Sherron Rd",
    "sg:city":"Durham",
    "sg:classifiers":[
        {
            "category":"Professional",
            "type":"Services"
        }
    ],
    "sg:phone":"+1 919 596 8068",
    "sg:postcode":"27703",
    "sg:province":"NC",
    "sg:tags":[
        "establishment"
    ],
    "wof:name":"Surface Solutions",
    "wof:placetype":"venue"
},
  "geometry": {"coordinates":[-78.831614,35.953412],"type":"Point"}
}