{
  "type": "Feature",
  "properties": {
    "iso:country":"US",
    "sg:address":"1909 E Firetower Rd",
    "sg:city":"Greenville",
    "sg:classifiers":[
        {
            "category":"Banks & Credit Unions",
            "subcategory":"Bank",
            "type":"Services"
        }
    ],
    "sg:phone":"+1 252 756 3837",
    "sg:postcode":"27858",
    "sg:province":"NC",
    "sg:tags":[
        "personal",
        "financing",
        "institution"
    ],
    "wof:name":"American General Finance Corp",
    "wof:placetype":"venue"
},
  "geometry": {"coordinates":[-77.35233100000001,35.566477],"type":"Point"}
}