{
  "type": "Feature",
  "properties": {
    "iso:country":"US",
    "sg:address":"2701 S Wilmington St",
    "sg:city":"Raleigh",
    "sg:classifiers":[
        {
            "category":"Restaurant",
            "type":"Food & Drink"
        }
    ],
    "sg:phone":"+1 919 828 7874",
    "sg:postcode":"27603",
    "sg:province":"NC",
    "sg:tags":[
        "eating"
    ],
    "wof:name":"Elmigueleno Restaurant",
    "wof:placetype":"venue"
},
  "geometry": {"coordinates":[-78.64567099999999,35.745233],"type":"Point"}
}