{
  "type": "Feature",
  "properties": {
    "addr:full":"7317 Shellford Dr Greensboro NC 27406",
    "addr:housenumber":"7317",
    "addr:postcode":"27406",
    "addr:street":"Shellford Dr",
    "iso:country":"US",
    "sg:address":"7317 Shellford Dr",
    "sg:city":"Greensboro",
    "sg:classifiers":[
        {
            "category":"Retail",
            "subcategory":"Portrait Studio",
            "type":"Services"
        }
    ],
    "sg:phone":"+1 336 674 8122",
    "sg:postcode":"27406",
    "sg:province":"NC",
    "sg:tags":[
        "photographer"
    ],
    "wof:name":"Cleavengers Photography",
    "wof:placetype":"venue"
},
  "geometry": {"coordinates":[-79.789461,35.914782],"type":"Point"}
}