{
  "type": "Feature",
  "properties": {
    "iso:country":"US",
    "sg:address":"2565 Joel Johnson Rd",
    "sg:city":"Lillington",
    "sg:classifiers":[
        {
            "category":"Organizations",
            "subcategory":"Religious Organization",
            "type":"Services"
        }
    ],
    "sg:phone":"+1 910 893 8452",
    "sg:postcode":"27546",
    "sg:province":"NC",
    "sg:tags":[
        "church"
    ],
    "wof:name":"Flatwoods Community Baptist",
    "wof:placetype":"venue"
},
  "geometry": {"coordinates":[-78.80643000000001,35.352079],"type":"Point"}
}