{
  "type": "Feature",
  "properties": {
    "addr:full":"410 Vine Arden Rd Morganton NC 28655",
    "addr:housenumber":"410",
    "addr:postcode":"28655",
    "addr:street":"Vine Arden Rd",
    "iso:country":"US",
    "sg:address":"410 Vine Arden Rd",
    "sg:city":"Morganton",
    "sg:classifiers":[
        {
            "category":"Food & Beverages",
            "subcategory":"Groceries & Convenience Stores",
            "type":"Retail Goods"
        }
    ],
    "sg:phone":"+1 828 438 9030",
    "sg:postcode":"28655",
    "sg:province":"NC",
    "wof:name":"Jett Xpress",
    "wof:placetype":"venue"
},
  "geometry": {"coordinates":[-81.68018499999999,35.760544],"type":"Point"}
}