{
  "type": "Feature",
  "properties": {
    "addr:full":"1816 Village Crossing Dr Chapel Hill NC 27517",
    "addr:housenumber":"1816",
    "addr:postcode":"27517",
    "addr:street":"Village Crossing Dr",
    "iso:country":"US",
    "sg:address":"1816 Village Crossing Dr",
    "sg:city":"Chapel Hill",
    "sg:classifiers":[
        {
            "category":"Health Services",
            "subcategory":"Doctor",
            "type":"Services"
        }
    ],
    "sg:phone":"+1   ",
    "sg:postcode":"27517",
    "sg:province":"NC",
    "sg:tags":[
        "surgeon"
    ],
    "wof:name":"Brett C Sheridan",
    "wof:placetype":"venue"
},
  "geometry": {"coordinates":[-79.00799000000001,35.904533],"type":"Point"}
}