{
  "type": "Feature",
  "properties": {
    "iso:country":"US",
    "sg:address":"2826 Bell Arthur Rd",
    "sg:city":"Greenville",
    "sg:classifiers":[
        {
            "category":"Wholesale",
            "subcategory":"Auto Parts",
            "type":"Manufacturing & Wholesale Goods"
        }
    ],
    "sg:phone":"+1 252 355 6352",
    "sg:postcode":"27834",
    "sg:province":"NC",
    "sg:tags":[
        "automobile",
        "rebuilt",
        "used"
    ],
    "wof:name":"Tarheel Motors & Salvage Inc",
    "wof:placetype":"venue"
},
  "geometry": {"coordinates":[-77.49745799999999,35.582498],"type":"Point"}
}