{
  "type": "Feature",
  "properties": {
    "iso:country":"US",
    "sg:address":"8366 Six Forks Rd Ste 102",
    "sg:city":"Raleigh",
    "sg:classifiers":[
        {
            "category":"Wholesale",
            "subcategory":"Medical Equipment & Supplies",
            "type":"Manufacturing & Wholesale Goods"
        },
        {
            "category":"Health Services",
            "subcategory":"Nursing And Care Facility",
            "type":"Services"
        },
        {
            "category":"Health Services",
            "subcategory":"Health Practitioner",
            "type":"Services"
        },
        {
            "category":"Shopping",
            "subcategory":"Pharmacy",
            "type":"Retail Goods"
        }
    ],
    "sg:phone":"+1 919 870 0903",
    "sg:postcode":"27615",
    "sg:province":"NC",
    "sg:tags":[
        "home",
        "eldercare-home"
    ],
    "wof:name":"Eves Home Care",
    "wof:placetype":"venue"
},
  "geometry": {"coordinates":[-78.648872,35.893269],"type":"Point"}
}