{
  "type": "Feature",
  "properties": {
    "iso:country":"US",
    "sg:address":"3810 Old Cherry Point Rd",
    "sg:city":"New Bern",
    "sg:classifiers":[
        {
            "category":"Building & Trades",
            "subcategory":"Construction",
            "type":"Services"
        }
    ],
    "sg:phone":"+1 252 633 3369",
    "sg:postcode":"28560",
    "sg:province":"NC",
    "sg:tags":[
        "contractor"
    ],
    "wof:name":"Humphrey Roofing Inc",
    "wof:placetype":"venue"
},
  "geometry": {"coordinates":[-77.003725,35.045933],"type":"Point"}
}