{
  "type": "Feature",
  "properties": {
    "iso:country":"US",
    "sg:address":"1924 McAllister Dr",
    "sg:city":"Charlotte",
    "sg:classifiers":[
        {
            "category":"Real Estate",
            "subcategory":"Real Estate Operator",
            "type":"Services"
        }
    ],
    "sg:phone":"+1 704 392 9560",
    "sg:postcode":"28216",
    "sg:province":"NC",
    "sg:tags":[
        "building",
        "apartment"
    ],
    "wof:name":"Royal Orleans Apartments LLC",
    "wof:placetype":"venue"
},
  "geometry": {"coordinates":[-80.856818,35.280651],"type":"Point"}
}