{
  "type": "Feature",
  "properties": {
    "iso:country":"US",
    "sg:address":"2501 Capital Blvd",
    "sg:city":"Raleigh",
    "sg:classifiers":[
        {
            "category":"Autos & Motor Vehicles",
            "subcategory":"Automobile Sales",
            "type":"Retail Goods"
        }
    ],
    "sg:phone":"+1 919 836 4802",
    "sg:postcode":"27604",
    "sg:province":"NC",
    "sg:tags":[
        "dealers-used",
        "car",
        "used",
        "cars-wholesale",
        "new"
    ],
    "sg:website":"http://www.bmwcharlottesville.com",
    "wof:name":"Crown Isuzu",
    "wof:placetype":"venue"
},
  "geometry": {"coordinates":[-78.611474,35.811208],"type":"Point"}
}