{
  "type": "Feature",
  "properties": {
    "addr:full":"146 Grady Dale Ln Beaufort NC 28516",
    "addr:housenumber":"146",
    "addr:postcode":"28516",
    "addr:street":"Grady Dale Ln",
    "iso:country":"US",
    "sg:address":"146 Grady Dale Ln",
    "sg:city":"Beaufort",
    "sg:classifiers":[
        {
            "category":"Building & Trades",
            "subcategory":"Construction",
            "type":"Services"
        }
    ],
    "sg:phone":"+1 252 728 3828",
    "sg:postcode":"28516",
    "sg:province":"NC",
    "sg:tags":[
        "designer",
        "marine",
        "contractor"
    ],
    "wof:name":"Mike Noe Construction",
    "wof:placetype":"venue"
},
  "geometry": {"coordinates":[-76.657766,34.741596],"type":"Point"}
}