{
  "type": "Feature",
  "properties": {
    "iso:country":"US",
    "sg:address":"1836 E Webb Ave",
    "sg:city":"Burlington",
    "sg:classifiers":[
        {
            "category":"Building & Trades",
            "subcategory":"Construction",
            "type":"Services"
        }
    ],
    "sg:phone":"+1 336 226 4532",
    "sg:postcode":"27217",
    "sg:province":"NC",
    "sg:tags":[
        "siding",
        "contractor"
    ],
    "wof:name":"Midway Blind & Awning Co",
    "wof:placetype":"venue"
},
  "geometry": {"coordinates":[-79.415254,36.07564],"type":"Point"}
}