{
  "type": "Feature",
  "properties": {
    "addr:full":"6500 Harrisburg Rd Charlotte NC 28227",
    "addr:housenumber":"6500",
    "addr:postcode":"28227",
    "addr:street":"Harrisburg Rd",
    "iso:country":"US",
    "sg:address":"6500 Harrisburg Rd",
    "sg:city":"Charlotte",
    "sg:classifiers":[
        {
            "category":"Building & Trades",
            "subcategory":"Construction",
            "type":"Services"
        }
    ],
    "sg:phone":"+1 704 537 4560",
    "sg:postcode":"28227",
    "sg:province":"NC",
    "sg:tags":[
        "floor",
        "laying",
        "contractor"
    ],
    "wof:name":"Enriquez Flooring",
    "wof:placetype":"venue"
},
  "geometry": {"coordinates":[-80.687781,35.204702],"type":"Point"}
}