{
  "type": "Feature",
  "properties": {
    "addr:full":"104 Brewer Ln Carrboro NC 27510",
    "addr:housenumber":"104",
    "addr:postcode":"27510",
    "addr:street":"Brewer Ln",
    "iso:country":"US",
    "sg:address":"104 Brewer Ln",
    "sg:city":"Carrboro",
    "sg:classifiers":[
        {
            "category":"Retail",
            "subcategory":"Portrait Studio",
            "type":"Services"
        }
    ],
    "sg:phone":"+1   ",
    "sg:postcode":"27510",
    "sg:province":"NC",
    "sg:tags":[
        "photo"
    ],
    "wof:name":"Babyangelcom",
    "wof:placetype":"venue"
},
  "geometry": {"coordinates":[-79.06534499999999,35.909736],"type":"Point"}
}