{
  "type": "Feature",
  "properties": {
    "iso:country":"US",
    "sg:address":"102 E Victoria Ct",
    "sg:city":"Greenville",
    "sg:classifiers":[
        {
            "category":"Professional",
            "subcategory":"Business Services",
            "type":"Services"
        }
    ],
    "sg:phone":"+1 252 756 7248",
    "sg:postcode":"27858",
    "sg:province":"NC",
    "sg:tags":[
        "inventory"
    ],
    "wof:name":"RGIS Inventory Specialists",
    "wof:placetype":"venue"
},
  "geometry": {"coordinates":[-77.382679,35.566388],"type":"Point"}
}