{
  "type": "Feature",
  "properties": {
    "addr:full":"2425 Charlotte Dr Charlotte NC 28203",
    "addr:housenumber":"2425",
    "addr:postcode":"28203",
    "addr:street":"Charlotte Dr",
    "iso:country":"US",
    "sg:address":"2425 Charlotte Dr",
    "sg:city":"Charlotte",
    "sg:classifiers":[
        {
            "category":"Building & Trades",
            "subcategory":"Construction",
            "type":"Services"
        }
    ],
    "sg:phone":"+1 704 527 3456",
    "sg:postcode":"28203",
    "sg:province":"NC",
    "sg:tags":[
        "general",
        "contractor"
    ],
    "wof:name":"Taylor Madison Construction Co",
    "wof:placetype":"venue"
},
  "geometry": {"coordinates":[-80.851319,35.198737],"type":"Point"}
}