{
  "type": "Feature",
  "properties": {
    "addr:full":"1104 Oak Grove Church Rd Millers Creek NC 28651",
    "addr:housenumber":"1104",
    "addr:postcode":"28651",
    "addr:street":"Oak;Church Rd",
    "iso:country":"US",
    "sg:address":"1104 Oak Grove Church Rd",
    "sg:city":"Millers Creek",
    "sg:classifiers":[
        {
            "category":"Sports & Exercise",
            "subcategory":"Gym",
            "type":"Entertainment"
        }
    ],
    "sg:phone":"+1   ",
    "sg:postcode":"28651",
    "sg:province":"NC",
    "sg:tags":[
        "fitness",
        "physical",
        "facility"
    ],
    "wof:name":"Images Salon & Spa",
    "wof:placetype":"venue"
},
  "geometry": {"coordinates":[-81.207832,36.197267],"type":"Point"}
}