{
  "type": "Feature",
  "properties": {
    "iso:country":"US",
    "sg:address":"534 Lindley Rd",
    "sg:city":"Greensboro",
    "sg:classifiers":[
        {
            "category":"Banks & Credit Unions",
            "subcategory":"Investment Brokerage",
            "type":"Services"
        }
    ],
    "sg:phone":"+1 336 315 9886",
    "sg:postcode":"27410",
    "sg:province":"NC",
    "sg:tags":[
        "security"
    ],
    "wof:name":"First Global Futures",
    "wof:placetype":"venue"
},
  "geometry": {"coordinates":[-79.896925,36.08763],"type":"Point"}
}