{
  "type": "Feature",
  "properties": {
    "addr:full":"205 Court St Louisburg NC 27549",
    "addr:housenumber":"205",
    "addr:postcode":"27549",
    "addr:street":"Court St",
    "iso:country":"US",
    "sg:address":"205 Court St",
    "sg:city":"Louisburg",
    "sg:classifiers":[
        {
            "category":"Restaurant",
            "type":"Food & Drink"
        }
    ],
    "sg:phone":"+1 919 496 1001",
    "sg:postcode":"27549",
    "sg:province":"NC",
    "sg:tags":[
        "eating"
    ],
    "wof:name":"Court Street Cafe",
    "wof:placetype":"venue"
},
  "geometry": {"coordinates":[-78.300932,36.098562],"type":"Point"}
}