{
  "type": "Feature",
  "properties": {
    "addr:full":"160 N 1st St Albemarle NC 28001",
    "addr:housenumber":"160",
    "addr:postcode":"28001",
    "addr:street":"N 1St St",
    "iso:country":"US",
    "sg:address":"160 N 1st St",
    "sg:city":"Albemarle",
    "sg:classifiers":[
        {
            "category":"Real Estate",
            "subcategory":"Real Estate Agent",
            "type":"Services"
        }
    ],
    "sg:phone":"+1 704 983 2149",
    "sg:postcode":"28001",
    "sg:province":"NC",
    "sg:website":"www.c21russhollinsrealtors.com",
    "wof:name":"Century 21",
    "wof:placetype":"venue"
},
  "geometry": {"coordinates":[-80.199457,35.351124],"type":"Point"}
}