{
  "type": "Feature",
  "properties": {
    "iso:country":"US",
    "sg:address":"119 Parkarbor Ln",
    "sg:city":"Cary",
    "sg:classifiers":[
        {
            "category":"Professional",
            "type":"Services"
        }
    ],
    "sg:phone":"+1 919 387 0655",
    "sg:postcode":"27519",
    "sg:province":"NC",
    "wof:name":"Robert Vanderpool",
    "wof:placetype":"venue"
},
  "geometry": {"coordinates":[-78.86574400000001,35.786425],"type":"Point"}
}