{
  "type": "Feature",
  "properties": {
    "iso:country":"US",
    "sg:address":"2627 Executive Point Dr",
    "sg:city":"Monroe",
    "sg:classifiers":[
        {
            "category":"Manufacturing",
            "subcategory":"Metals",
            "type":"Manufacturing & Wholesale Goods"
        }
    ],
    "sg:phone":"+1 704 289 7200",
    "sg:postcode":"28110",
    "sg:province":"NC",
    "sg:tags":[
        "finisher"
    ],
    "wof:name":"Drake Coatings Inc",
    "wof:placetype":"venue"
},
  "geometry": {"coordinates":[-80.61395899999999,35.048177],"type":"Point"}
}