{
  "type": "Feature",
  "properties": {
    "iso:country":"US",
    "sg:address":"501 Perdues Rd",
    "sg:city":"Louisburg",
    "sg:classifiers":[
        {
            "category":"Building & Trades",
            "subcategory":"Landscaping Services",
            "type":"Services"
        }
    ],
    "sg:phone":"+1 919 496 5191",
    "sg:postcode":"27549",
    "sg:province":"NC",
    "sg:tags":[
        "lawn",
        "maintenance",
        "grounds"
    ],
    "wof:name":"Top Dawg Lawn Care & Landscapg",
    "wof:placetype":"venue"
},
  "geometry": {"coordinates":[-78.24060799999999,36.144083],"type":"Point"}
}