{
  "type": "Feature",
  "properties": {
    "iso:country":"US",
    "sg:address":"8313 Rhian Brook Ln",
    "sg:city":"Charlotte",
    "sg:classifiers":[
        {
            "category":"Building & Trades",
            "subcategory":"Construction",
            "type":"Services"
        }
    ],
    "sg:phone":"+1 704 399 5282",
    "sg:postcode":"28216",
    "sg:province":"NC",
    "sg:tags":[
        "hanging",
        "contractor"
    ],
    "wof:name":"Davids All Pro Painting",
    "wof:placetype":"venue"
},
  "geometry": {"coordinates":[-80.877195,35.342409],"type":"Point"}
}