{
  "type": "Feature",
  "properties": {
    "addr:full":"125 Timber Dr Garner NC 27529",
    "addr:housenumber":"125",
    "addr:postcode":"27529",
    "addr:street":"Timber Dr",
    "iso:country":"US",
    "sg:address":"125 Timber Dr",
    "sg:city":"Garner",
    "sg:classifiers":[
        {
            "category":"Building & Trades",
            "subcategory":"Construction",
            "type":"Services"
        }
    ],
    "sg:phone":"+1 919 427 2058",
    "sg:postcode":"27529",
    "sg:province":"NC",
    "sg:tags":[
        "builder",
        "deck"
    ],
    "wof:name":"THH Construction",
    "wof:placetype":"venue"
},
  "geometry": {"coordinates":[-78.604445,35.686329],"type":"Point"}
}