{
  "type": "Feature",
  "properties": {
    "addr:full":"232 Union St Hickory NC 28650",
    "addr:housenumber":"232",
    "addr:postcode":"28650",
    "addr:street":"Union St",
    "iso:country":"US",
    "sg:address":"232 Union St",
    "sg:city":"Hickory",
    "sg:classifiers":[
        {
            "category":"Home & Garden",
            "subcategory":"Home Furnishings",
            "type":"Retail Goods"
        }
    ],
    "sg:phone":"+1 828 324 4244",
    "sg:postcode":"28650",
    "sg:province":"NC",
    "sg:tags":[
        "pottery"
    ],
    "wof:name":"Bisque N Beads",
    "wof:placetype":"venue"
},
  "geometry": {"coordinates":[-81.209334,35.575873],"type":"Point"}
}