{
  "type": "Feature",
  "properties": {
    "iso:country":"US",
    "sg:address":"220 E Beaver St",
    "sg:city":"Siler City",
    "sg:classifiers":[
        {
            "category":"Utilities",
            "subcategory":"Telephone",
            "type":"Services"
        }
    ],
    "sg:phone":"+1 919 663 3361",
    "sg:postcode":"27344",
    "sg:province":"NC",
    "sg:tags":[
        "company"
    ],
    "wof:name":"Sprint Corp",
    "wof:placetype":"venue"
},
  "geometry": {"coordinates":[-79.460421,35.722937],"type":"Point"}
}