{
  "type": "Feature",
  "properties": {
    "iso:country":"US",
    "sg:address":"5202 Carolina Beach Rd",
    "sg:city":"Wilmington",
    "sg:classifiers":[
        {
            "category":"Professional",
            "subcategory":"Advertising",
            "type":"Services"
        }
    ],
    "sg:phone":"+1 910 452 0128",
    "sg:postcode":"28412",
    "sg:province":"NC",
    "sg:tags":[
        "marketing",
        "medium",
        "counselor",
        "including"
    ],
    "wof:name":"Integrated Marketing Group Inc",
    "wof:placetype":"venue"
},
  "geometry": {"coordinates":[-77.897015,34.143417],"type":"Point"}
}