{
  "type": "Feature",
  "properties": {
    "iso:country":"US",
    "sg:address":"143 S Bragg Blvd",
    "sg:city":"Spring Lake",
    "sg:classifiers":[
        {
            "category":"Restaurant",
            "type":"Food & Drink"
        }
    ],
    "sg:menulink":"http://www.allmenus.com/nc/manchester/163115-rallys/menu/",
    "sg:phone":"+1 910 346 1134",
    "sg:postcode":"28390",
    "sg:province":"NC",
    "sg:tags":[
        "sandwich",
        "dog",
        "burger",
        "hot",
        "wrap",
        "american"
    ],
    "wof:name":"Rally's",
    "wof:placetype":"venue"
},
  "geometry": {"coordinates":[-78.97227700000001,35.166002],"type":"Point"}
}