{
  "type": "Feature",
  "properties": {
    "iso:country":"US",
    "sg:address":"320 John Godfrey Rd",
    "sg:city":"Sanford",
    "sg:classifiers":[
        {
            "category":"Building & Trades",
            "subcategory":"Landscaping Services",
            "type":"Services"
        }
    ],
    "sg:phone":"+1 919 499 5463",
    "sg:postcode":"27332",
    "sg:province":"NC",
    "sg:tags":[
        "landscape",
        "contractor"
    ],
    "wof:name":"Jesse Godfrey Landscaping",
    "wof:placetype":"venue"
},
  "geometry": {"coordinates":[-79.16166,35.354936],"type":"Point"}
}