{
  "type": "Feature",
  "properties": {
    "addr:full":"7105 Leveret Cir Raleigh NC 27615",
    "addr:postcode":"7105;27615",
    "addr:street":"Leveret Cir",
    "iso:country":"US",
    "sg:address":"7105 Leveret Cir",
    "sg:city":"Raleigh",
    "sg:classifiers":[
        {
            "category":"Professional",
            "subcategory":"Management & Consulting",
            "type":"Services"
        },
        {
            "category":"Organizations",
            "subcategory":"Professional Association",
            "type":"Services"
        }
    ],
    "sg:phone":"+1 919 848 6773",
    "sg:postcode":"27615",
    "sg:province":"NC",
    "sg:tags":[
        "consultant"
    ],
    "wof:name":"Lan Connect Consultants LLC",
    "wof:placetype":"venue"
},
  "geometry": {"coordinates":[-78.631653,35.878712],"type":"Point"}
}