{
  "type": "Feature",
  "properties": {
    "addr:full":"1326 Dothan Rd Tabor City NC 28463",
    "addr:housenumber":"1326",
    "addr:postcode":"28463",
    "addr:street":"Dothan Rd",
    "iso:country":"US",
    "sg:address":"1326 Dothan Rd",
    "sg:city":"Tabor City",
    "sg:classifiers":[
        {
            "category":"Building & Trades",
            "subcategory":"Construction",
            "type":"Services"
        }
    ],
    "sg:phone":"+1 910 653 9474",
    "sg:postcode":"28463",
    "sg:province":"NC",
    "sg:tags":[
        "floor",
        "laying",
        "contractor"
    ],
    "wof:name":"Hewitt Carpet Company",
    "wof:placetype":"venue"
},
  "geometry": {"coordinates":[-78.75953,34.066162],"type":"Point"}
}