{
  "type": "Feature",
  "properties": {
    "addr:full":"8300 Brittains Field Rd Oak Ridge NC 27310",
    "addr:postcode":"8300;27310",
    "addr:street":"Brittains Field Rd",
    "iso:country":"US",
    "sg:address":"8300 Brittains Field Rd",
    "sg:city":"Oak Ridge",
    "sg:classifiers":[
        {
            "category":"Health Services",
            "subcategory":"Health Practitioner",
            "type":"Services"
        }
    ],
    "sg:phone":"+1 336 643 8838",
    "sg:postcode":"27310",
    "sg:province":"NC",
    "wof:name":"Mu Chinese Acupuncture & Herbs",
    "wof:placetype":"venue"
},
  "geometry": {"coordinates":[-79.979383,36.153466],"type":"Point"}
}