{
  "type": "Feature",
  "properties": {
    "addr:full":"68 Thunder Rd Waynesville NC 28785",
    "addr:housenumber":"68",
    "addr:postcode":"28785",
    "addr:street":"Thunder Rd",
    "iso:country":"US",
    "sg:address":"68 Thunder Rd",
    "sg:city":"Waynesville",
    "sg:classifiers":[
        {
            "category":"Health Services",
            "subcategory":"Clinic",
            "type":"Services"
        }
    ],
    "sg:phone":"+1 828 627 2929",
    "sg:postcode":"28785",
    "sg:province":"NC",
    "sg:tags":[
        "home"
    ],
    "wof:name":"A Bit Of All Trades",
    "wof:placetype":"venue"
},
  "geometry": {"coordinates":[-82.958737,35.594892],"type":"Point"}
}