{
  "type": "Feature",
  "properties": {
    "iso:country":"US",
    "sg:address":"481 E 2nd St",
    "sg:city":"Ayden",
    "sg:classifiers":[
        {
            "category":"Autos & Motor Vehicles",
            "subcategory":"Fuel & Gas Station",
            "type":"Retail Goods"
        }
    ],
    "sg:phone":"+1 252 746 6226",
    "sg:postcode":"28513",
    "sg:province":"NC",
    "sg:tags":[
        "oil"
    ],
    "wof:name":"Louie's Exxon Svc Ctr",
    "wof:placetype":"venue"
},
  "geometry": {"coordinates":[-77.411928,35.47179],"type":"Point"}
}