{
  "type": "Feature",
  "properties": {
    "addr:full":"6084 Indian Camp Dr Pfafftown NC 27040",
    "addr:housenumber":"6084",
    "addr:postcode":"27040",
    "addr:street":"Indian Camp",
    "iso:country":"US",
    "sg:address":"6084 Indian Camp Dr",
    "sg:city":"Pfafftown",
    "sg:classifiers":[
        {
            "category":"Building & Trades",
            "subcategory":"Electrical",
            "type":"Services"
        }
    ],
    "sg:phone":"+1 336 924 4401",
    "sg:postcode":"27040",
    "sg:province":"NC",
    "sg:tags":[
        "electric",
        "contractor"
    ],
    "wof:name":"Daleco Electric",
    "wof:placetype":"venue"
},
  "geometry": {"coordinates":[-80.41004100000001,36.209278],"type":"Point"}
}