{
  "type": "Feature",
  "properties": {
    "addr:full":"3308 Bragg Blvd Fayetteville NC 28303",
    "addr:housenumber":"3308",
    "addr:postcode":"28303",
    "addr:street":"Bragg Blvd",
    "iso:country":"US",
    "sg:address":"3308 Bragg Blvd",
    "sg:city":"Fayetteville",
    "sg:classifiers":[
        {
            "category":"Personal",
            "subcategory":"Beauty Salon",
            "type":"Services"
        }
    ],
    "sg:phone":"+1 910 864 6245",
    "sg:postcode":"28303",
    "sg:province":"NC",
    "sg:tags":[
        "shop",
        "manicuring"
    ],
    "wof:name":"C A Nails",
    "wof:placetype":"venue"
},
  "geometry": {"coordinates":[-78.936227,35.077174],"type":"Point"}
}