{
  "type": "Feature",
  "properties": {
    "iso:country":"US",
    "sg:address":"265 Aberdeen Dr",
    "sg:city":"Washington",
    "sg:classifiers":[
        {
            "category":"Building & Trades",
            "subcategory":"Construction",
            "type":"Services"
        }
    ],
    "sg:phone":"+1 252 946 3945",
    "sg:postcode":"27889",
    "sg:province":"NC",
    "sg:tags":[
        "house"
    ],
    "wof:name":"H&H Construction & Remodeling",
    "wof:placetype":"venue"
},
  "geometry": {"coordinates":[-77.03101700000001,35.61136],"type":"Point"}
}