{
  "type": "Feature",
  "properties": {
    "iso:country":"US",
    "sg:address":"122 E Sherwood Dr",
    "sg:city":"Havelock",
    "sg:classifiers":[
        {
            "category":"Building & Trades",
            "subcategory":"Cleaning & Sanitation",
            "type":"Services"
        }
    ],
    "sg:phone":"+1 252 447 3611",
    "sg:postcode":"28532",
    "sg:province":"NC",
    "sg:tags":[
        "fireplace",
        "chimney"
    ],
    "wof:name":"Havelock's Chimney Sweep",
    "wof:placetype":"venue"
},
  "geometry": {"coordinates":[-76.917227,34.890527],"type":"Point"}
}