{
  "type": "Feature",
  "properties": {
    "iso:country":"US",
    "sg:address":"40894 State Hwy 12",
    "sg:city":"Avon",
    "sg:classifiers":[
        {
            "category":"Health Services",
            "subcategory":"Doctor",
            "type":"Services"
        }
    ],
    "sg:phone":"+1 252 449 2100",
    "sg:postcode":"27915",
    "sg:province":"NC",
    "sg:tags":[
        "physician",
        "surgeon"
    ],
    "wof:name":"Outer Banks Ctr For Women",
    "wof:placetype":"venue"
},
  "geometry": {"coordinates":[-75.503373,35.35171],"type":"Point"}
}