{
  "type": "Feature",
  "properties": {
    "addr:full":"3672 Gaston Day School Rd Gastonia NC 28056",
    "addr:housenumber":"3672",
    "addr:postcode":"28056",
    "addr:street":"Gaston Day School Rd",
    "iso:country":"US",
    "sg:address":"3672 Gaston Day School Rd",
    "sg:city":"Gastonia",
    "sg:classifiers":[
        {
            "category":"Building & Trades",
            "subcategory":"Construction",
            "type":"Services"
        }
    ],
    "sg:phone":"+1 704 678 8194",
    "sg:postcode":"28056",
    "sg:province":"NC",
    "sg:tags":[
        "handyman"
    ],
    "wof:name":"Carolina Handy Man",
    "wof:placetype":"venue"
},
  "geometry": {"coordinates":[-81.132975,35.215613],"type":"Point"}
}