{
  "type": "Feature",
  "properties": {
    "addr:full":"1216 Cedar Creek Rd Biscoe NC 27209",
    "addr:housenumber":"1216",
    "addr:postcode":"27209",
    "addr:street":"Cedar Creek Rd",
    "iso:country":"US",
    "sg:address":"1216 Cedar Creek Rd",
    "sg:city":"Biscoe",
    "sg:classifiers":[
        {
            "category":"Professional",
            "subcategory":"Management & Consulting",
            "type":"Services"
        }
    ],
    "sg:phone":"+1 910 974 4606",
    "sg:postcode":"27209",
    "sg:province":"NC",
    "sg:tags":[
        "retail",
        "direct",
        "sales"
    ],
    "wof:name":"Avon",
    "wof:placetype":"venue"
},
  "geometry": {"coordinates":[-79.815692,35.325549],"type":"Point"}
}