{
  "type": "Feature",
  "properties": {
    "iso:country":"US",
    "sg:address":"804 Spring Ln",
    "sg:city":"Sanford",
    "sg:classifiers":[
        {
            "category":"Restaurant",
            "type":"Food & Drink"
        }
    ],
    "sg:phone":"+1 919 718 1103",
    "sg:postcode":"27330",
    "sg:province":"NC",
    "wof:name":"Davison's",
    "wof:placetype":"venue"
},
  "geometry": {"coordinates":[-79.19443800000001,35.487348],"type":"Point"}
}