{
  "type": "Feature",
  "properties": {
    "iso:country":"US",
    "sg:address":"826 22nd St Pl SE",
    "sg:city":"Hickory",
    "sg:classifiers":[
        {
            "category":"Real Estate",
            "subcategory":"Real Estate Agent",
            "type":"Services"
        }
    ],
    "sg:phone":"+1 828 328 4406",
    "sg:postcode":"28602",
    "sg:province":"NC",
    "wof:name":"Blackwelder Properties",
    "wof:placetype":"venue"
},
  "geometry": {"coordinates":[-81.29352299999999,35.720313],"type":"Point"}
}