{
  "type": "Feature",
  "properties": {
    "addr:full":"15610 Bellaire Ridge Dr Charlotte NC 28277",
    "addr:housenumber":"15610",
    "addr:postcode":"28277",
    "addr:street":"Bellaire Ridge Dr",
    "iso:country":"US",
    "sg:address":"15610 Bellaire Ridge Dr",
    "sg:city":"Charlotte",
    "sg:classifiers":[
        {
            "category":"Professional",
            "subcategory":"Business Services",
            "type":"Services"
        }
    ],
    "sg:phone":"+1   ",
    "sg:postcode":"28277",
    "sg:province":"NC",
    "sg:tags":[
        "consulting",
        "management"
    ],
    "wof:name":"The Assa Group",
    "wof:placetype":"venue"
},
  "geometry": {"coordinates":[-80.851617,35.038427],"type":"Point"}
}