{
  "type": "Feature",
  "properties": {
    "iso:country":"US",
    "sg:address":"128 E Spring St",
    "sg:city":"Seven Springs",
    "sg:classifiers":[
        {
            "category":"Professional",
            "type":"Services"
        }
    ],
    "sg:phone":"+1 252 569 1714",
    "sg:postcode":"28578",
    "sg:province":"NC",
    "sg:tags":[
        "establishment"
    ],
    "wof:name":"Grady Mack L Farm",
    "wof:placetype":"venue"
},
  "geometry": {"coordinates":[-77.845986,35.227272],"type":"Point"}
}