{
  "type": "Feature",
  "properties": {
    "iso:country":"US",
    "sg:address":"9013 Perimeter Woods Dr",
    "sg:city":"Charlotte",
    "sg:classifiers":[
        {
            "category":"Shopping",
            "subcategory":"Computers & Home Electronics",
            "type":"Retail Goods"
        }
    ],
    "sg:phone":"+1 704 509 9474",
    "sg:postcode":"28216",
    "sg:province":"NC",
    "sg:tags":[
        "software"
    ],
    "wof:name":"Asset Management Technologies",
    "wof:placetype":"venue"
},
  "geometry": {"coordinates":[-80.850399,35.343098],"type":"Point"}
}