{
  "type": "Feature",
  "properties": {
    "addr:full":"98 Crescent Dr Beaufort NC 28516",
    "addr:housenumber":"98",
    "addr:postcode":"28516",
    "addr:street":"Crescent Dr",
    "iso:country":"US",
    "sg:address":"98 Crescent Dr",
    "sg:city":"Beaufort",
    "sg:classifiers":[
        {
            "category":"Restaurant",
            "type":"Food & Drink"
        }
    ],
    "sg:menulink":"http://www.allmenus.com/nc/beaufort/85308-dominos-pizza/menu/",
    "sg:phone":"+1 252 728 5002",
    "sg:postcode":"28516",
    "sg:province":"NC",
    "sg:tags":[
        "american",
        "wing",
        "pizza"
    ],
    "wof:name":"Domino's Pizza",
    "wof:placetype":"venue"
},
  "geometry": {"coordinates":[-76.644102,34.727622],"type":"Point"}
}