{
  "type": "Feature",
  "properties": {
    "iso:country":"US",
    "sg:address":"2535 Tattersall Dr",
    "sg:city":"Charlotte",
    "sg:classifiers":[
        {
            "category":"Professional",
            "subcategory":"Management & Consulting",
            "type":"Services"
        }
    ],
    "sg:phone":"+1 704 996 2000",
    "sg:postcode":"28210",
    "sg:province":"NC",
    "sg:tags":[
        "consultant"
    ],
    "wof:name":"Andrew's Co",
    "wof:placetype":"venue"
},
  "geometry": {"coordinates":[-80.85815700000001,35.128762],"type":"Point"}
}