{
  "type": "Feature",
  "properties": {
    "addr:full":"3905 Ketch Point Dr Rocky Mount NC 27803",
    "addr:housenumber":"3905",
    "addr:postcode":"27803",
    "addr:street":"Ketch Point Dr",
    "iso:country":"US",
    "sg:address":"3905 Ketch Point Dr",
    "sg:city":"Rocky Mount",
    "sg:classifiers":[
        {
            "category":"Professional",
            "subcategory":"Management & Consulting",
            "type":"Services"
        }
    ],
    "sg:phone":"+1   ",
    "sg:postcode":"27803",
    "sg:province":"NC",
    "wof:name":"Retirement Planning Center LLC",
    "wof:placetype":"venue"
},
  "geometry": {"coordinates":[-77.86314299999999,35.949237],"type":"Point"}
}