{
  "type": "Feature",
  "properties": {
    "iso:country":"US",
    "sg:address":"5111 Yadkin Rd",
    "sg:city":"Fayetteville",
    "sg:classifiers":[
        {
            "category":"Personal",
            "subcategory":"Beauty Salon",
            "type":"Services"
        }
    ],
    "sg:phone":"+1 910 822 8868",
    "sg:postcode":"28303",
    "sg:province":"NC",
    "wof:name":"Nana's Hair Braiding",
    "wof:placetype":"venue"
},
  "geometry": {"coordinates":[-78.971987,35.083695],"type":"Point"}
}