{
  "type": "Feature",
  "properties": {
    "addr:full":"2100 N Pine St Lumberton NC 28358",
    "addr:housenumber":"2100",
    "addr:postcode":"28358",
    "addr:street":"N Pine St",
    "iso:country":"US",
    "sg:address":"2100 N Pine St",
    "sg:city":"Lumberton",
    "sg:classifiers":[
        {
            "category":"Shopping",
            "type":"Retail Goods"
        }
    ],
    "sg:phone":"+1 910 739 9605",
    "sg:postcode":"28358",
    "sg:province":"NC",
    "sg:tags":[
        "picture",
        "frame",
        "art",
        "supply"
    ],
    "wof:name":"Golds Art & Frame",
    "wof:placetype":"venue"
},
  "geometry": {"coordinates":[-79.00380699999999,34.632529],"type":"Point"}
}