{
  "type": "Feature",
  "properties": {
    "iso:country":"US",
    "sg:address":"2308 S Memorial Dr",
    "sg:city":"Greenville",
    "sg:classifiers":[
        {
            "category":"Personal",
            "type":"Services"
        }
    ],
    "sg:phone":"+1 252 355 3045",
    "sg:postcode":"27834",
    "sg:province":"NC",
    "sg:tags":[
        "hair",
        "weaving"
    ],
    "wof:name":"Fatou African Hair Braiding",
    "wof:placetype":"venue"
},
  "geometry": {"coordinates":[-77.395341,35.597183],"type":"Point"}
}