{
  "type": "Feature",
  "properties": {
    "addr:full":"125 Hospital Dr Spruce Pine NC 28777",
    "addr:housenumber":"125",
    "addr:postcode":"28777",
    "addr:street":"Hospital Dr",
    "iso:country":"US",
    "sg:address":"125 Hospital Dr",
    "sg:city":"Spruce Pine",
    "sg:classifiers":[
        {
            "category":"Health Services",
            "subcategory":"Hospital",
            "type":"Services"
        }
    ],
    "sg:phone":"+1 828 765 4201",
    "sg:postcode":"28777",
    "sg:province":"NC",
    "sg:website":"www.spchospital.org",
    "wof:name":"Spruce Pine Community Hospital",
    "wof:placetype":"venue"
},
  "geometry": {"coordinates":[-82.06249800000001,35.910544],"type":"Point"}
}