{
  "type": "Feature",
  "properties": {
    "iso:country":"US",
    "sg:address":"1231 Shields Rd",
    "sg:city":"Kernersville",
    "sg:classifiers":[
        {
            "category":"Manufacturing",
            "subcategory":"Building Materials",
            "type":"Manufacturing & Wholesale Goods"
        }
    ],
    "sg:phone":"+1 336 993 4767",
    "sg:postcode":"27284",
    "sg:province":"NC",
    "sg:tags":[
        "door"
    ],
    "sg:website":"www.exactfinishinc.com",
    "wof:name":"Cinex America LLC",
    "wof:placetype":"venue"
},
  "geometry": {"coordinates":[-80.062045,36.094246],"type":"Point"}
}