{
  "type": "Feature",
  "properties": {
    "addr:full":"315 Jake Alexander Blvd S Salisbury NC 28147",
    "addr:housenumber":"315",
    "addr:postcode":"28147",
    "addr:street":"Jake Alexander Blvd S",
    "iso:country":"US",
    "sg:address":"315 Jake Alexander Blvd S",
    "sg:city":"Salisbury",
    "sg:classifiers":[
        {
            "category":"Manufacturing",
            "subcategory":"Metals",
            "type":"Manufacturing & Wholesale Goods"
        }
    ],
    "sg:phone":"+1 704 637 5555",
    "sg:postcode":"28147",
    "sg:province":"NC",
    "sg:tags":[
        "fabricator",
        "precision"
    ],
    "wof:name":"Interscope Inc",
    "wof:placetype":"venue"
},
  "geometry": {"coordinates":[-80.49536500000001,35.64846],"type":"Point"}
}