{
  "type": "Feature",
  "properties": {
    "addr:full":"1757 Yarborough Rd Parkton NC 28371",
    "addr:housenumber":"1757",
    "addr:postcode":"28371",
    "addr:street":"Yarborough Rd",
    "iso:country":"US",
    "sg:address":"1757 Yarborough Rd",
    "sg:city":"Parkton",
    "sg:classifiers":[
        {
            "category":"Building & Trades",
            "subcategory":"Cleaning & Sanitation",
            "type":"Services"
        }
    ],
    "sg:phone":"+1 910 423 4238",
    "sg:postcode":"28371",
    "sg:province":"NC",
    "sg:tags":[
        "janitor"
    ],
    "wof:name":"Always Cleaning",
    "wof:placetype":"venue"
},
  "geometry": {"coordinates":[-78.922403,34.864291],"type":"Point"}
}