{
  "type": "Feature",
  "properties": {
    "iso:country":"US",
    "sg:address":"8364 Six Forks Rd",
    "sg:city":"Raleigh",
    "sg:classifiers":[
        {
            "category":"Professional",
            "subcategory":"Computer Services",
            "type":"Services"
        }
    ],
    "sg:phone":"+1 919 845 7320",
    "sg:postcode":"27615",
    "sg:province":"NC",
    "sg:tags":[
        "equipment",
        "company",
        "leasing"
    ],
    "wof:name":"Tcp Leasing",
    "wof:placetype":"venue"
},
  "geometry": {"coordinates":[-78.64833400000001,35.891739],"type":"Point"}
}