{
  "type": "Feature",
  "properties": {
    "iso:country":"US",
    "sg:address":"6 W Walnut St",
    "sg:city":"Asheville",
    "sg:classifiers":[
        {
            "category":"Shopping",
            "subcategory":"Bicycles & Sporting Goods",
            "type":"Retail Goods"
        }
    ],
    "sg:phone":"+1 828 225 6400",
    "sg:postcode":"28801",
    "sg:province":"NC",
    "wof:name":"Glovers Travel Goods",
    "wof:placetype":"venue"
},
  "geometry": {"coordinates":[-82.55262500000001,35.59663],"type":"Point"}
}