{
  "type": "Feature",
  "properties": {
    "addr:full":"2591 S 17th St Wilmington NC 28401",
    "addr:housenumber":"2591",
    "addr:postcode":"28401",
    "addr:street":"S 17Th St",
    "iso:country":"US",
    "sg:address":"2591 S 17th St",
    "sg:city":"Wilmington",
    "sg:classifiers":[
        {
            "category":"Retail",
            "subcategory":"Laundry & Dry Cleaning",
            "type":"Services"
        }
    ],
    "sg:phone":"+1   ",
    "sg:postcode":"28401",
    "sg:province":"NC",
    "wof:name":"Sunrise Express Super Laundry",
    "wof:placetype":"venue"
},
  "geometry": {"coordinates":[-77.921499,34.197092],"type":"Point"}
}