{
  "type": "Feature",
  "properties": {
    "iso:country":"US",
    "sg:address":"230 E Meadow Rd",
    "sg:city":"Eden",
    "sg:classifiers":[
        {
            "category":"Autos & Motor Vehicles",
            "subcategory":"Auto Supplies",
            "type":"Retail Goods"
        }
    ],
    "sg:phone":"+1 336 623 5588",
    "sg:postcode":"27288",
    "sg:province":"NC",
    "sg:tags":[
        "tire"
    ],
    "wof:name":"Eden's Discount Tires",
    "wof:placetype":"venue"
},
  "geometry": {"coordinates":[-79.73900500000001,36.508105],"type":"Point"}
}