{
  "type": "Feature",
  "properties": {
    "iso:country":"US",
    "sg:address":"3640 Century Pl",
    "sg:city":"Charlotte",
    "sg:classifiers":[
        {
            "category":"Home & Garden",
            "subcategory":"Building Materials",
            "type":"Retail Goods"
        }
    ],
    "sg:phone":"+1 704 334 5367",
    "sg:postcode":"28206",
    "sg:province":"NC",
    "sg:tags":[
        "siding"
    ],
    "wof:name":"Revere Building Products",
    "wof:placetype":"venue"
},
  "geometry": {"coordinates":[-80.81237299999999,35.266971],"type":"Point"}
}