{
  "type": "Feature",
  "properties": {
    "iso:country":"US",
    "sg:address":"241 E Main St",
    "sg:city":"Lawndale",
    "sg:classifiers":[
        {
            "category":"Government",
            "subcategory":"Post Office",
            "type":"Public Place"
        }
    ],
    "sg:phone":"+1 704 538 7281",
    "sg:postcode":"28090",
    "sg:province":"NC",
    "wof:name":"US Post Office",
    "wof:placetype":"venue"
},
  "geometry": {"coordinates":[-81.55842699999999,35.41783],"type":"Point"}
}