{
  "type": "Feature",
  "properties": {
    "addr:full":"930 E Main St Sylva NC 28779",
    "addr:housenumber":"930",
    "addr:postcode":"28779",
    "addr:street":"E Main St",
    "iso:country":"US",
    "sg:address":"930 E Main St",
    "sg:city":"Sylva",
    "sg:classifiers":[
        {
            "category":"Personal",
            "subcategory":"Beauty Salon",
            "type":"Services"
        }
    ],
    "sg:phone":"+1 828 631 4500",
    "sg:postcode":"28779",
    "sg:province":"NC",
    "wof:name":"Perfect Reflections",
    "wof:placetype":"venue"
},
  "geometry": {"coordinates":[-83.202399,35.368108],"type":"Point"}
}