{
  "type": "Feature",
  "properties": {
    "iso:country":"US",
    "sg:address":"2828 Interstate St",
    "sg:city":"Charlotte",
    "sg:classifiers":[
        {
            "category":"Manufacturing",
            "subcategory":"Chemicals & Compounds",
            "type":"Manufacturing & Wholesale Goods"
        }
    ],
    "sg:phone":"+1 704 392 4657",
    "sg:postcode":"28208",
    "sg:province":"NC",
    "sg:tags":[
        "printing",
        "ink",
        "lithographing",
        "mfg"
    ],
    "sg:website":"www.wikoff.com",
    "wof:name":"Wikoff Color Corporation",
    "wof:placetype":"venue"
},
  "geometry": {"coordinates":[-80.910881,35.235963],"type":"Point"}
}