{
  "type": "Feature",
  "properties": {
    "iso:country":"US",
    "sg:address":"126 Bessie Dr",
    "sg:city":"Kings Mountain",
    "sg:classifiers":[
        {
            "category":"Manufacturing",
            "subcategory":"Building Materials",
            "type":"Manufacturing & Wholesale Goods"
        }
    ],
    "sg:phone":"+1 704 734 0787",
    "sg:postcode":"28086",
    "sg:province":"NC",
    "sg:tags":[
        "wood",
        "truss",
        "mfg"
    ],
    "wof:name":"Hope Lumber",
    "wof:placetype":"venue"
},
  "geometry": {"coordinates":[-81.359044,35.259078],"type":"Point"}
}