{
  "type": "Feature",
  "properties": {
    "addr:full":"610 Cotton Grove Rd Lexington NC 27292",
    "addr:housenumber":"610",
    "addr:postcode":"27292",
    "addr:street":"Cotton Grove Rd",
    "iso:country":"US",
    "sg:address":"610 Cotton Grove Rd",
    "sg:city":"Lexington",
    "sg:classifiers":[
        {
            "category":"Restaurant",
            "type":"Food & Drink"
        }
    ],
    "sg:phone":"+1 336 357 7739",
    "sg:postcode":"27292",
    "sg:province":"NC",
    "sg:tags":[
        "eating"
    ],
    "wof:name":"Wendys",
    "wof:placetype":"venue"
},
  "geometry": {"coordinates":[-80.262777,35.805391],"type":"Point"}
}