{
  "type": "Feature",
  "properties": {
    "addr:full":"9399 Deer Path Ln Kernersville NC 27284",
    "addr:housenumber":"9399",
    "addr:postcode":"27284",
    "addr:street":"Deer Path Ln",
    "iso:country":"US",
    "sg:address":"9399 Deer Path Ln",
    "sg:city":"Kernersville",
    "sg:classifiers":[
        {
            "category":"Organizations",
            "subcategory":"Community Association",
            "type":"Services"
        }
    ],
    "sg:phone":"+1   ",
    "sg:postcode":"27284",
    "sg:province":"NC",
    "wof:name":"Deer Path Home Owners Assn",
    "wof:placetype":"venue"
},
  "geometry": {"coordinates":[-80.068944,36.201284],"type":"Point"}
}