{
  "type": "Feature",
  "properties": {
    "iso:country":"US",
    "sg:address":"4700 Creedmoor Rd",
    "sg:city":"Raleigh",
    "sg:classifiers":[
        {
            "category":"Restaurant",
            "type":"Food & Drink"
        }
    ],
    "sg:phone":"+1 919 781 0342",
    "sg:postcode":"27612",
    "sg:province":"NC",
    "wof:name":"Nicola's Restaurant",
    "wof:placetype":"venue"
},
  "geometry": {"coordinates":[-78.68559999999999,35.840401],"type":"Point"}
}