{
  "type": "Feature",
  "properties": {
    "iso:country":"US",
    "sg:address":"6225 Cashion Rd",
    "sg:city":"Huntersville",
    "sg:classifiers":[
        {
            "category":"Building & Trades",
            "subcategory":"Construction",
            "type":"Services"
        }
    ],
    "sg:phone":"+1 704 875 9736",
    "sg:postcode":"28078",
    "sg:province":"NC",
    "sg:tags":[
        "steel",
        "fabrication",
        "welding"
    ],
    "wof:name":"Carolina Steel & Stone Inc",
    "wof:placetype":"venue"
},
  "geometry": {"coordinates":[-80.931652,35.414494],"type":"Point"}
}