{
  "type": "Feature",
  "properties": {
    "iso:country":"US",
    "sg:address":"8930 State Hwy 90",
    "sg:city":"Stony Point",
    "sg:classifiers":[
        {
            "category":"Autos & Motor Vehicles",
            "subcategory":"Auto Supplies",
            "type":"Retail Goods"
        }
    ],
    "sg:phone":"+1 704 585 6950",
    "sg:postcode":"28678",
    "sg:province":"NC",
    "sg:tags":[
        "tire"
    ],
    "wof:name":"Stony Point Tire Svc",
    "wof:placetype":"venue"
},
  "geometry": {"coordinates":[-81.04555499999999,35.861217],"type":"Point"}
}