{
  "type": "Feature",
  "properties": {
    "addr:full":"246 Acorn Hill Rd Tarboro NC 27886",
    "addr:housenumber":"246",
    "addr:postcode":"27886",
    "addr:street":"Acorn Hill Rd",
    "iso:country":"US",
    "sg:address":"246 Acorn Hill Rd",
    "sg:city":"Tarboro",
    "sg:classifiers":[
        {
            "category":"Organizations",
            "subcategory":"Religious Organization",
            "type":"Services"
        }
    ],
    "sg:phone":"+1 252 823 2903",
    "sg:postcode":"27886",
    "sg:province":"NC",
    "sg:tags":[
        "church"
    ],
    "wof:name":"Acorn Hill Baptist Church",
    "wof:placetype":"venue"
},
  "geometry": {"coordinates":[-77.48581799999999,35.96876],"type":"Point"}
}