{
  "type": "Feature",
  "properties": {
    "addr:full":"3073 Beaver Hills Dr Burlington NC 27215",
    "addr:housenumber":"3073",
    "addr:postcode":"27215",
    "addr:street":"Beaver Hills Dr",
    "iso:country":"US",
    "sg:address":"3073 Beaver Hills Dr",
    "sg:city":"Burlington",
    "sg:classifiers":[
        {
            "category":"Building & Trades",
            "subcategory":"Construction",
            "type":"Services"
        }
    ],
    "sg:phone":"+1 336 222 8682",
    "sg:postcode":"27215",
    "sg:province":"NC",
    "sg:tags":[
        "residential"
    ],
    "wof:name":"Horner Investments",
    "wof:placetype":"venue"
},
  "geometry": {"coordinates":[-79.538327,36.021487],"type":"Point"}
}