{
  "type": "Feature",
  "properties": {
    "addr:full":"111 McNess Rd Statesville NC 28677",
    "addr:housenumber":"111",
    "addr:postcode":"28677",
    "addr:street":"Mcness Rd",
    "iso:country":"US",
    "sg:address":"111 McNess Rd",
    "sg:city":"Statesville",
    "sg:classifiers":[
        {
            "category":"Manufacturing",
            "subcategory":"Paper Products",
            "type":"Manufacturing & Wholesale Goods"
        }
    ],
    "sg:phone":"+1 704 873 2213",
    "sg:postcode":"28677",
    "sg:province":"NC",
    "sg:tags":[
        "box",
        "fiber",
        "mfg"
    ],
    "wof:name":"Smurfit-Stone Container Corp",
    "wof:placetype":"venue"
},
  "geometry": {"coordinates":[-80.79559399999999,35.757337],"type":"Point"}
}