{
  "type": "Feature",
  "properties": {
    "iso:country":"US",
    "sg:address":"6634 Kings Lynn Dr",
    "sg:city":"Oak Island",
    "sg:classifiers":[
        {
            "category":"Food & Beverages",
            "subcategory":"Groceries & Convenience Stores",
            "type":"Retail Goods"
        }
    ],
    "sg:phone":"+1 910 278 3775",
    "sg:postcode":"28465",
    "sg:province":"NC",
    "wof:name":"Fosters Market & Supply Co",
    "wof:placetype":"venue"
},
  "geometry": {"coordinates":[-78.226022,33.914387],"type":"Point"}
}