{
  "type": "Feature",
  "properties": {
    "addr:full":"3215 Johnny Cake Ln Charlotte NC 28226",
    "addr:housenumber":"3215",
    "addr:postcode":"28226",
    "addr:street":"Johnny Cake Ln",
    "iso:country":"US",
    "sg:address":"3215 Johnny Cake Ln",
    "sg:city":"Charlotte",
    "sg:classifiers":[
        {
            "category":"Airline",
            "type":"Transportation"
        }
    ],
    "sg:phone":"+1 704 553 2911",
    "sg:postcode":"28226",
    "sg:province":"NC",
    "sg:tags":[
        "nonscheduled",
        "air"
    ],
    "sg:website":"www.carolinaaircharter.com",
    "wof:name":"Carolina Air Charter Inc",
    "wof:placetype":"venue"
},
  "geometry": {"coordinates":[-80.820042,35.131031],"type":"Point"}
}