{
  "type": "Feature",
  "properties": {
    "addr:full":"220 Oakley Dr Harrisburg NC 28075",
    "addr:housenumber":"220",
    "addr:postcode":"28075",
    "addr:street":"Oakley Dr",
    "iso:country":"US",
    "sg:address":"220 Oakley Dr",
    "sg:city":"Harrisburg",
    "sg:classifiers":[
        {
            "category":"Social Services",
            "subcategory":"Child Care",
            "type":"Services"
        }
    ],
    "sg:phone":"+1 704 455 5800",
    "sg:postcode":"28075",
    "sg:province":"NC",
    "sg:tags":[
        "day"
    ],
    "wof:name":"Child Development Center",
    "wof:placetype":"venue"
},
  "geometry": {"coordinates":[-80.655415,35.32047],"type":"Point"}
}