{
  "type": "Feature",
  "properties": {
    "addr:full":"904 Cone Ave Pineville NC 28134",
    "addr:housenumber":"904",
    "addr:postcode":"28134",
    "addr:street":"Cone Ave",
    "iso:country":"US",
    "sg:address":"904 Cone Ave",
    "sg:city":"Pineville",
    "sg:classifiers":[
        {
            "category":"Building & Trades",
            "subcategory":"Landscaping Services",
            "type":"Services"
        }
    ],
    "sg:phone":"+1 704 889 2570",
    "sg:postcode":"28134",
    "sg:province":"NC",
    "sg:tags":[
        "landscape"
    ],
    "wof:name":"A Landscape Legacy",
    "wof:placetype":"venue"
},
  "geometry": {"coordinates":[-80.89770900000001,35.07989],"type":"Point"}
}