{
  "type": "Feature",
  "properties": {
    "addr:full":"108 Moss Stock Farm Rd Kittrell NC 27544",
    "addr:housenumber":"108",
    "addr:postcode":"27544",
    "addr:street":"Moss Stock Farm Rd",
    "iso:country":"US",
    "sg:address":"108 Moss Stock Farm Rd",
    "sg:city":"Kittrell",
    "sg:classifiers":[
        {
            "category":"Restaurant",
            "type":"Food & Drink"
        }
    ],
    "sg:phone":"+1 252 438 4806",
    "sg:postcode":"27544",
    "sg:province":"NC",
    "sg:tags":[
        "eating"
    ],
    "wof:name":"Biddies Grill",
    "wof:placetype":"venue"
},
  "geometry": {"coordinates":[-78.42621,36.206212],"type":"Point"}
}