{
  "type": "Feature",
  "properties": {
    "addr:full":"3817 Bonwood Dr Charlotte NC 28211",
    "addr:housenumber":"3817",
    "addr:postcode":"28211",
    "addr:street":"Bonwood Dr",
    "iso:country":"US",
    "sg:address":"3817 Bonwood Dr",
    "sg:city":"Charlotte",
    "sg:classifiers":[
        {
            "category":"Professional",
            "subcategory":"Management & Consulting",
            "type":"Services"
        }
    ],
    "sg:phone":"+1   ",
    "sg:postcode":"28211",
    "sg:province":"NC",
    "wof:name":"Paradigm Management Inc",
    "wof:placetype":"venue"
},
  "geometry": {"coordinates":[-80.812561,35.181954],"type":"Point"}
}