{
  "type": "Feature",
  "properties": {
    "addr:full":"1442 Maple Springs Church Rd Shelby NC 28152",
    "addr:housenumber":"1442",
    "addr:postcode":"28152",
    "addr:street":"Maple Springs Church Rd",
    "iso:country":"US",
    "sg:address":"1442 Maple Springs Church Rd",
    "sg:city":"Shelby",
    "sg:classifiers":[
        {
            "category":"Shopping",
            "subcategory":"Computers & Home Electronics",
            "type":"Retail Goods"
        }
    ],
    "sg:phone":"+1 704 487 8327",
    "sg:postcode":"28152",
    "sg:province":"NC",
    "sg:tags":[
        "equipment",
        "satellite",
        "system",
        "install"
    ],
    "wof:name":"Rogers Satellite & T V",
    "wof:placetype":"venue"
},
  "geometry": {"coordinates":[-81.6249,35.231285],"type":"Point"}
}