{
  "type": "Feature",
  "properties": {
    "addr:full":"1024 Waughtown St Winston Salem NC 27107",
    "addr:housenumber":"1024",
    "addr:postcode":"27107",
    "addr:street":"Waughtown St",
    "iso:country":"US",
    "sg:address":"1024 Waughtown St",
    "sg:city":"Winston Salem",
    "sg:classifiers":[
        {
            "category":"Organizations",
            "subcategory":"Non-profit Organization",
            "type":"Services"
        }
    ],
    "sg:phone":"+1 336 785 0770",
    "sg:postcode":"27107",
    "sg:province":"NC",
    "sg:tags":[
        "info",
        "addiction",
        "abuse",
        "treatment",
        "drug"
    ],
    "sg:website":"www.prodigals.org",
    "wof:name":"Prodigals Community",
    "wof:placetype":"venue"
},
  "geometry": {"coordinates":[-80.220226,36.069307],"type":"Point"}
}