{
  "type": "Feature",
  "properties": {
    "addr:full":"1542 Haywood Rd Hendersonville NC 28791",
    "addr:housenumber":"1542",
    "addr:postcode":"28791",
    "addr:street":"Haywood Rd",
    "iso:country":"US",
    "sg:address":"1542 Haywood Rd",
    "sg:city":"Hendersonville",
    "sg:classifiers":[
        {
            "category":"Wholesale",
            "subcategory":"Motor Vehicles",
            "type":"Manufacturing & Wholesale Goods"
        }
    ],
    "sg:phone":"+1 828 696 0533",
    "sg:postcode":"28791",
    "sg:province":"NC",
    "sg:tags":[
        "ambulance"
    ],
    "wof:name":"ARC  Angel Trans Support Svcs",
    "wof:placetype":"venue"
},
  "geometry": {"coordinates":[-82.471193,35.328511],"type":"Point"}
}