{
  "type": "Feature",
  "properties": {
    "addr:full":"4740 Silver Creek Church Rd Morganton NC 28655",
    "addr:housenumber":"4740",
    "addr:postcode":"28655",
    "addr:street":"Silver Creek Church Rd",
    "iso:country":"US",
    "sg:address":"4740 Silver Creek Church Rd",
    "sg:city":"Morganton",
    "sg:classifiers":[
        {
            "category":"Retail",
            "subcategory":"Auto Repair",
            "type":"Services"
        }
    ],
    "sg:phone":"+1 828 584 3700",
    "sg:postcode":"28655",
    "sg:province":"NC",
    "sg:tags":[
        "repairing",
        "automobile"
    ],
    "wof:name":"Amigo Garage",
    "wof:placetype":"venue"
},
  "geometry": {"coordinates":[-81.81285699999999,35.624219],"type":"Point"}
}