{
  "type": "Feature",
  "properties": {
    "addr:full":"926 Howell Swamp Church Rd Walstonburg NC 27888",
    "addr:housenumber":"926",
    "addr:postcode":"27888",
    "addr:street":"Howell Swamp Church Rd",
    "iso:country":"US",
    "sg:address":"926 Howell Swamp Church Rd",
    "sg:city":"Walstonburg",
    "sg:classifiers":[
        {
            "category":"Manufacturing",
            "subcategory":"Glass & Minerals",
            "type":"Manufacturing & Wholesale Goods"
        },
        {
            "category":"Building & Trades",
            "subcategory":"Construction",
            "type":"Services"
        }
    ],
    "sg:phone":"+1 252 753 2583",
    "sg:postcode":"27888",
    "sg:province":"NC",
    "sg:tags":[
        "fiber",
        "mfg",
        "fixture",
        "plastic",
        "plumbing",
        "fabricator",
        "contractor"
    ],
    "sg:website":"www.mooresfiberglass.com",
    "wof:name":"Moore's Fiberglass Inc",
    "wof:placetype":"venue"
},
  "geometry": {"coordinates":[-77.710227,35.578894],"type":"Point"}
}