{
  "type": "Feature",
  "properties": {
    "addr:full":"480 Underwood Rd Elon College NC 27244",
    "addr:housenumber":"480",
    "addr:postcode":"27244",
    "addr:street":"Underwood Rd Elon",
    "iso:country":"US",
    "sg:address":"480 Underwood Rd",
    "sg:city":"Elon College",
    "sg:classifiers":[
        {
            "category":"Professional",
            "subcategory":"Management & Consulting",
            "type":"Services"
        }
    ],
    "sg:phone":"+1   ",
    "sg:postcode":"27244",
    "sg:province":"NC",
    "wof:name":"Brown Associates",
    "wof:placetype":"venue"
},
  "geometry": {"coordinates":[-79.49961999999999,36.269902],"type":"Point"}
}