{
  "type": "Feature",
  "properties": {
    "addr:full":"138 Gibson Dr Rockingham NC 28379",
    "addr:housenumber":"138",
    "addr:postcode":"28379",
    "addr:street":"Gibson Dr",
    "iso:country":"US",
    "sg:address":"138 Gibson Dr",
    "sg:city":"Rockingham",
    "sg:classifiers":[
        {
            "category":"Organizations",
            "subcategory":"Religious Organization",
            "type":"Services"
        }
    ],
    "sg:phone":"+1 910 895 3135",
    "sg:postcode":"28379",
    "sg:province":"NC",
    "sg:tags":[
        "church"
    ],
    "wof:name":"West Rockingham United Mthdst",
    "wof:placetype":"venue"
},
  "geometry": {"coordinates":[-79.787499,34.961142],"type":"Point"}
}