{
  "type": "Feature",
  "properties": {
    "addr:full":"1204 Lake Glad Rd Wendell NC 27591",
    "addr:housenumber":"1204",
    "addr:postcode":"27591",
    "addr:street":"Lake Glad Rd",
    "iso:country":"US",
    "sg:address":"1204 Lake Glad Rd",
    "sg:city":"Wendell",
    "sg:classifiers":[
        {
            "category":"Building & Trades",
            "subcategory":"Landscaping Services",
            "type":"Services"
        }
    ],
    "sg:phone":"+1 919 366 2633",
    "sg:postcode":"27591",
    "sg:province":"NC",
    "sg:tags":[
        "landscape"
    ],
    "wof:name":"Garrett Transport & Landscape",
    "wof:placetype":"venue"
},
  "geometry": {"coordinates":[-78.38851,35.754275],"type":"Point"}
}