{
  "type": "Feature",
  "properties": {
    "iso:country":"US",
    "sg:address":"3125 Kathleen Ave",
    "sg:city":"Greensboro",
    "sg:classifiers":[
        {
            "category":"Professional",
            "subcategory":"Printing & Photocopies",
            "type":"Services"
        },
        {
            "category":"Professional",
            "subcategory":"Business Services",
            "type":"Services"
        }
    ],
    "sg:phone":"+1 336 299 4484",
    "sg:postcode":"27408",
    "sg:province":"NC",
    "sg:tags":[
        "photocopying",
        "ad",
        "direct",
        "packaging",
        "s",
        "mail"
    ],
    "wof:name":"Shipping Depot Inc",
    "wof:placetype":"venue"
},
  "geometry": {"coordinates":[-79.83241599999999,36.085387],"type":"Point"}
}