{
  "type": "Feature",
  "properties": {
    "addr:full":"614 E Market St Smithfield NC 27577",
    "addr:housenumber":"614",
    "addr:postcode":"27577",
    "addr:street":"E Market St",
    "iso:country":"US",
    "sg:address":"614 E Market St",
    "sg:city":"Smithfield",
    "sg:classifiers":[
        {
            "category":"Insurance",
            "subcategory":"Insurance Agent",
            "type":"Services"
        }
    ],
    "sg:phone":"+1 919 934 6111",
    "sg:postcode":"27577",
    "sg:province":"NC",
    "wof:name":"Triangle Insurance Group Inc",
    "wof:placetype":"venue"
},
  "geometry": {"coordinates":[-78.34116,35.509184],"type":"Point"}
}