{
  "type": "Feature",
  "properties": {
    "addr:full":"1201 NW Maynard Rd Cary NC 27513",
    "addr:housenumber":"1201",
    "addr:postcode":"27513",
    "addr:street":"Nw Maynard Rd",
    "iso:country":"US",
    "sg:address":"1201 NW Maynard Rd",
    "sg:city":"Cary",
    "sg:classifiers":[
        {
            "category":"Cinema",
            "subcategory":"Movie Rental",
            "type":"Entertainment"
        }
    ],
    "sg:phone":"+1 919 380 8080",
    "sg:postcode":"27513",
    "sg:province":"NC",
    "sg:tags":[
        "video",
        "game",
        "disc",
        "leasing",
        "tape"
    ],
    "sg:website":"www.blockbuster.com",
    "wof:name":"Blockbuster Video",
    "wof:placetype":"venue"
},
  "geometry": {"coordinates":[-78.809799,35.783501],"type":"Point"}
}