{
  "type": "Feature",
  "properties": {
    "addr:full":"1030 Ryan Rd Cary NC 27511",
    "addr:housenumber":"1030",
    "addr:postcode":"27511",
    "addr:street":"Ryan Rd",
    "iso:country":"US",
    "sg:address":"1030 Ryan Rd",
    "sg:city":"Cary",
    "sg:classifiers":[
        {
            "category":"Personal",
            "subcategory":"Nail Salon",
            "type":"Services"
        }
    ],
    "sg:phone":"+1 919 468 3913",
    "sg:postcode":"27511",
    "sg:province":"NC",
    "wof:name":"Gorgeous Nails",
    "wof:placetype":"venue"
},
  "geometry": {"coordinates":[-78.76419799999999,35.776199],"type":"Point"}
}