{
  "type": "Feature",
  "properties": {
    "addr:full":"6304 Cotton Rd Snow Camp NC 27349",
    "addr:housenumber":"6304",
    "addr:postcode":"27349",
    "addr:street":"Cotton Rd",
    "iso:country":"US",
    "sg:address":"6304 Cotton Rd",
    "sg:city":"Snow Camp",
    "sg:classifiers":[
        {
            "category":"Retail",
            "subcategory":"Repair Shop",
            "type":"Services"
        }
    ],
    "sg:phone":"+1 336 228 3838",
    "sg:postcode":"27349",
    "sg:province":"NC",
    "sg:tags":[
        "lock",
        "locksmith"
    ],
    "wof:name":"A V Lock & Key",
    "wof:placetype":"venue"
},
  "geometry": {"coordinates":[-79.46240299999999,35.939914],"type":"Point"}
}