{
  "type": "Feature",
  "properties": {
    "addr:full":"2805 Hiatt St Greensboro NC 27403",
    "addr:housenumber":"2805",
    "addr:postcode":"27403",
    "addr:street":"Hiatt St",
    "iso:country":"US",
    "sg:address":"2805 Hiatt St",
    "sg:city":"Greensboro",
    "sg:classifiers":[
        {
            "category":"Retail",
            "subcategory":"Auto Repair",
            "type":"Services"
        }
    ],
    "sg:phone":"+1   ",
    "sg:postcode":"27403",
    "sg:province":"NC",
    "sg:tags":[
        "general"
    ],
    "wof:name":"Teh Garage",
    "wof:placetype":"venue"
},
  "geometry": {"coordinates":[-79.84193,36.061718],"type":"Point"}
}