{
  "type": "Feature",
  "properties": {
    "iso:country":"US",
    "sg:address":"312 S McCaskey Rd",
    "sg:city":"Williamston",
    "sg:classifiers":[
        {
            "category":"Health Services",
            "subcategory":"Doctor",
            "type":"Services"
        }
    ],
    "sg:phone":"+1 252 792 8101",
    "sg:postcode":"27892",
    "sg:province":"NC",
    "sg:tags":[
        "physician",
        "surgeon"
    ],
    "wof:name":"Martin Pediatric Clinic",
    "wof:placetype":"venue"
},
  "geometry": {"coordinates":[-77.070956,35.840435],"type":"Point"}
}