{
  "type": "Feature",
  "properties": {
    "iso:country":"US",
    "sg:address":"8308 Mc Crory Rd",
    "sg:city":"Stokesdale",
    "sg:classifiers":[
        {
            "category":"Building & Trades",
            "subcategory":"Construction",
            "type":"Services"
        }
    ],
    "sg:phone":"+1 336 643 4010",
    "sg:postcode":"27357",
    "sg:province":"NC",
    "sg:tags":[
        "painting",
        "contractor"
    ],
    "wof:name":"Walker Improvements",
    "wof:placetype":"venue"
},
  "geometry": {"coordinates":[-79.987854,36.237887],"type":"Point"}
}