{
  "type": "Feature",
  "properties": {
    "iso:country":"US",
    "sg:address":"200 Mendota Ave",
    "sg:city":"Lexington",
    "sg:classifiers":[
        {
            "category":"Personal",
            "subcategory":"Beauty Salon",
            "type":"Services"
        }
    ],
    "sg:phone":"+1 336 243 1615",
    "sg:postcode":"27292",
    "sg:province":"NC",
    "sg:tags":[
        "shop"
    ],
    "wof:name":"Dot's Hair Styling",
    "wof:placetype":"venue"
},
  "geometry": {"coordinates":[-80.26954000000001,35.806839],"type":"Point"}
}