{
  "type": "Feature",
  "properties": {
    "iso:country":"US",
    "sg:address":"8446 N Tryon St",
    "sg:city":"Charlotte",
    "sg:classifiers":[
        {
            "category":"Communications",
            "type":"Services"
        }
    ],
    "sg:phone":"+1 704 594 9156",
    "sg:postcode":"28262",
    "sg:province":"NC",
    "sg:tags":[
        "consultant"
    ],
    "wof:name":"Rns Communications Inc",
    "wof:placetype":"venue"
},
  "geometry": {"coordinates":[-80.751857,35.302461],"type":"Point"}
}