{
  "type": "Feature",
  "properties": {
    "addr:full":"3501 Matthews Mint Hill Rd Matthews NC 28105",
    "addr:housenumber":"3501",
    "addr:postcode":"28105",
    "addr:street":"Matthews Mint Hill Rd",
    "iso:country":"US",
    "sg:address":"3501 Matthews Mint Hill Rd",
    "sg:city":"Matthews",
    "sg:classifiers":[
        {
            "category":"Restaurant",
            "type":"Food & Drink"
        }
    ],
    "sg:menulink":"http://www.allmenus.com/nc/clear-creek/137479-subway/menu/",
    "sg:phone":"+1 704 846 7827",
    "sg:postcode":"28105",
    "sg:province":"NC",
    "sg:tags":[
        "american",
        "sandwich"
    ],
    "wof:name":"Subway",
    "wof:placetype":"venue"
},
  "geometry": {"coordinates":[-80.68326500000001,35.13749],"type":"Point"}
}