{
  "type": "Feature",
  "properties": {
    "iso:country":"US",
    "sg:address":"1009 3rd Ave NW",
    "sg:city":"Hickory",
    "sg:classifiers":[
        {
            "category":"Manufacturing",
            "subcategory":"Tools & Machinery",
            "type":"Manufacturing & Wholesale Goods"
        }
    ],
    "sg:phone":"+1 828 322 2328",
    "sg:postcode":"28601",
    "sg:province":"NC",
    "sg:tags":[
        "body",
        "automobile",
        "shop",
        "equipment"
    ],
    "wof:name":"Flowers Auto Parts Co",
    "wof:placetype":"venue"
},
  "geometry": {"coordinates":[-81.356414,35.735779],"type":"Point"}
}