{
  "type": "Feature",
  "properties": {
    "addr:full":"1810 N Cedar St Lumberton NC 28358",
    "addr:housenumber":"1810",
    "addr:postcode":"28358",
    "addr:street":"N Cedar St",
    "iso:country":"US",
    "sg:address":"1810 N Cedar St",
    "sg:city":"Lumberton",
    "sg:classifiers":[
        {
            "category":"Professional",
            "subcategory":"Art Services",
            "type":"Services"
        }
    ],
    "sg:phone":"+1   ",
    "sg:postcode":"28358",
    "sg:province":"NC",
    "sg:tags":[
        "commercial",
        "design"
    ],
    "wof:name":"Highet Krcker Freelance Partnr",
    "wof:placetype":"venue"
},
  "geometry": {"coordinates":[-79.003139,34.630332],"type":"Point"}
}