{
  "type": "Feature",
  "properties": {
    "iso:country":"US",
    "sg:address":"1041 Ham Overman Rd",
    "sg:city":"Elizabeth City",
    "sg:classifiers":[
        {
            "category":"Wholesale",
            "subcategory":"Fruits & Vegetables",
            "type":"Manufacturing & Wholesale Goods"
        }
    ],
    "sg:phone":"+1 252 335 2207",
    "sg:postcode":"27909",
    "sg:province":"NC",
    "wof:name":"Sunshine Produce",
    "wof:placetype":"venue"
},
  "geometry": {"coordinates":[-76.226011,36.260633],"type":"Point"}
}