{
  "type": "Feature",
  "properties": {
    "addr:full":"105 Griffith Plaza Dr Winston Salem NC 27103",
    "addr:housenumber":"105",
    "addr:postcode":"27103",
    "addr:street":"Griffith Plaza Dr",
    "iso:country":"US",
    "sg:address":"105 Griffith Plaza Dr",
    "sg:city":"Winston Salem",
    "sg:classifiers":[
        {
            "category":"Retail",
            "subcategory":"Auto Repair",
            "type":"Services"
        }
    ],
    "sg:phone":"+1 336 760 2756",
    "sg:postcode":"27103",
    "sg:province":"NC",
    "sg:tags":[
        "repairing",
        "automobile"
    ],
    "wof:name":"Long Vw Svc",
    "wof:placetype":"venue"
},
  "geometry": {"coordinates":[-80.314071,36.040663],"type":"Point"}
}