{
  "type": "Feature",
  "properties": {
    "iso:country":"US",
    "sg:address":"423 W Carroll St",
    "sg:city":"Rose Hill",
    "sg:classifiers":[
        {
            "category":"Organizations",
            "subcategory":"Religious Organization",
            "type":"Services"
        }
    ],
    "sg:phone":"+1 910 289 7130",
    "sg:postcode":"28453",
    "sg:province":"NC",
    "sg:tags":[
        "church"
    ],
    "wof:name":"First Baptist Church-Magnolia",
    "wof:placetype":"venue"
},
  "geometry": {"coordinates":[-78.061126,34.893605],"type":"Point"}
}