{
  "type": "Feature",
  "properties": {
    "addr:full":"201 Glenfield Rd Snow Hill NC 28580",
    "addr:housenumber":"201",
    "addr:postcode":"28580",
    "addr:street":"Glenfield Rd",
    "iso:country":"US",
    "sg:address":"201 Glenfield Rd",
    "sg:city":"Snow Hill",
    "sg:classifiers":[
        {
            "category":"Organizations",
            "subcategory":"Religious Organization",
            "type":"Services"
        }
    ],
    "sg:phone":"+1   ",
    "sg:postcode":"28580",
    "sg:province":"NC",
    "wof:name":"Greater Vctory Apstolic Church",
    "wof:placetype":"venue"
},
  "geometry": {"coordinates":[-77.66418,35.387911],"type":"Point"}
}