{
  "type": "Feature",
  "properties": {
    "addr:full":"1575 Jenkins Valley Rd Alexander NC 28701",
    "addr:housenumber":"1575",
    "addr:postcode":"28701",
    "addr:street":"Jenkins Valley Rd",
    "iso:country":"US",
    "sg:address":"1575 Jenkins Valley Rd",
    "sg:city":"Alexander",
    "sg:classifiers":[
        {
            "category":"Wholesale",
            "subcategory":"Apparel",
            "type":"Manufacturing & Wholesale Goods"
        }
    ],
    "sg:phone":"+1 828 258 3366",
    "sg:postcode":"28701",
    "sg:province":"NC",
    "sg:tags":[
        "infant",
        "wear"
    ],
    "sg:website":"www.justduckyoriginals.com",
    "wof:name":"Just Ducky Mfg",
    "wof:placetype":"venue"
},
  "geometry": {"coordinates":[-82.63820699999999,35.645131],"type":"Point"}
}