{
  "type": "Feature",
  "properties": {
    "addr:full":"400 W High Ave High Point NC 27260",
    "addr:housenumber":"400",
    "addr:postcode":"27260",
    "addr:street":"W High Ave",
    "iso:country":"US",
    "sg:address":"400 W High Ave",
    "sg:city":"High Point",
    "sg:classifiers":[
        {
            "category":"Real Estate",
            "subcategory":"Real Estate Operator",
            "type":"Services"
        }
    ],
    "sg:phone":"+1 336 887 1976",
    "sg:postcode":"27260",
    "sg:province":"NC",
    "sg:tags":[
        "apartment"
    ],
    "wof:name":"Sheraton",
    "wof:placetype":"venue"
},
  "geometry": {"coordinates":[-80.01181099999999,35.95379],"type":"Point"}
}