{
  "type": "Feature",
  "properties": {
    "addr:full":"3215 Guess Rd Durham NC 27705",
    "addr:housenumber":"3215",
    "addr:postcode":"27705",
    "addr:street":"Guess Rd",
    "iso:country":"US",
    "sg:address":"3215 Guess Rd",
    "sg:city":"Durham",
    "sg:classifiers":[
        {
            "category":"Building & Trades",
            "subcategory":"Construction",
            "type":"Services"
        }
    ],
    "sg:phone":"+1 919 477 3780",
    "sg:postcode":"27705",
    "sg:province":"NC",
    "sg:tags":[
        "contractor"
    ],
    "wof:name":"Mattachione Construction",
    "wof:placetype":"venue"
},
  "geometry": {"coordinates":[-78.929343,36.03465],"type":"Point"}
}