{
  "type": "Feature",
  "properties": {
    "iso:country":"US",
    "sg:address":"1516 Mecklenburg Hwy",
    "sg:city":"Mooresville",
    "sg:classifiers":[
        {
            "category":"Building & Trades",
            "subcategory":"Construction",
            "type":"Services"
        }
    ],
    "sg:phone":"+1 704 896 7171",
    "sg:postcode":"28115",
    "sg:province":"NC",
    "sg:tags":[
        "contractor"
    ],
    "wof:name":"Silver Oak Builders Inc",
    "wof:placetype":"venue"
},
  "geometry": {"coordinates":[-80.84041000000001,35.556341],"type":"Point"}
}