{
  "type": "Feature",
  "properties": {
    "addr:full":"1363 Scotland Crossing Dr Laurinburg NC 28352",
    "addr:housenumber":"1363",
    "addr:postcode":"28352",
    "addr:street":"Scotland Crossing Dr",
    "iso:country":"US",
    "sg:address":"1363 Scotland Crossing Dr",
    "sg:city":"Laurinburg",
    "sg:classifiers":[
        {
            "category":"Shopping",
            "subcategory":"Department Store",
            "type":"Retail Goods"
        }
    ],
    "sg:phone":"+1 910 277 8307",
    "sg:postcode":"28352",
    "sg:province":"NC",
    "sg:website":"www.cititrends.com",
    "wof:name":"Citi Trends",
    "wof:placetype":"venue"
},
  "geometry": {"coordinates":[-79.485176,34.759651],"type":"Point"}
}