{
  "type": "Feature",
  "properties": {
    "addr:full":"104 S. Estes Drive Chapel Hill NC 27515",
    "addr:housenumber":"104",
    "addr:postcode":"27515",
    "addr:street":"S. Estes Drive",
    "iso:country":"US",
    "sg:address":"104 S. Estes Drive",
    "sg:city":"Chapel Hill",
    "sg:classifiers":[
        {
            "category":"Personal",
            "subcategory":"Massage",
            "type":"Services"
        }
    ],
    "sg:phone":"+1 919 942 1510",
    "sg:postcode":"27515",
    "sg:province":"NC",
    "sg:website":"www.chapelhillmassage.com",
    "wof:name":"Chapel Hill Massage",
    "wof:placetype":"venue"
},
  "geometry": {"coordinates":[-79.034004,35.929119],"type":"Point"}
}