{
  "type": "Feature",
  "properties": {
    "addr:full":"229 S Marine Blvd Jacksonville NC 28540",
    "addr:housenumber":"229",
    "addr:postcode":"28540",
    "addr:street":"S Marine Blvd",
    "iso:country":"US",
    "sg:address":"229 S Marine Blvd",
    "sg:city":"Jacksonville",
    "sg:classifiers":[
        {
            "category":"Home & Garden",
            "subcategory":"Garden Supply",
            "type":"Retail Goods"
        }
    ],
    "sg:phone":"+1 910 455 2000",
    "sg:postcode":"28540",
    "sg:province":"NC",
    "sg:tags":[
        "lawn",
        "mower"
    ],
    "wof:name":"Cooper & Son Small Engine Inc",
    "wof:placetype":"venue"
},
  "geometry": {"coordinates":[-77.44429700000001,34.75172],"type":"Point"}
}