{
  "type": "Feature",
  "properties": {
    "iso:country":"US",
    "sg:address":"2735 Reynolda Rd",
    "sg:city":"Winston Salem",
    "sg:classifiers":[
        {
            "category":"Restaurant",
            "type":"Food & Drink"
        }
    ],
    "sg:phone":"+1 336 723 9978",
    "sg:postcode":"27106",
    "sg:province":"NC",
    "wof:name":"Wendy's",
    "wof:placetype":"venue"
},
  "geometry": {"coordinates":[-80.297878,36.142582],"type":"Point"}
}