{
  "type": "Feature",
  "properties": {
    "iso:country":"US",
    "sg:address":"339 N Shore Dr",
    "sg:city":"Lexington",
    "sg:classifiers":[
        {
            "category":"Professional",
            "subcategory":"Engineering",
            "type":"Services"
        }
    ],
    "sg:phone":"+1   ",
    "sg:postcode":"27292",
    "sg:province":"NC",
    "wof:name":"Hunter Engineering Company",
    "wof:placetype":"venue"
},
  "geometry": {"coordinates":[-80.24579300000001,35.648108],"type":"Point"}
}