{
  "type": "Feature",
  "properties": {
    "addr:full":"6865 Towbridge Rd Fayetteville NC 28306",
    "addr:housenumber":"6865",
    "addr:postcode":"28306",
    "addr:street":"Towbridge Rd",
    "iso:country":"US",
    "sg:address":"6865 Towbridge Rd",
    "sg:city":"Fayetteville",
    "sg:classifiers":[
        {
            "category":"Shopping",
            "subcategory":"Beauty & Cosmetics",
            "type":"Retail Goods"
        }
    ],
    "sg:phone":"+1 910 424 8095",
    "sg:postcode":"28306",
    "sg:province":"NC",
    "sg:tags":[
        "merchandise"
    ],
    "wof:name":"N S D",
    "wof:placetype":"venue"
},
  "geometry": {"coordinates":[-79.010606,34.993376],"type":"Point"}
}