{
  "type": "Feature",
  "properties": {
    "addr:full":"520 20th St SE Hickory NC 28602",
    "addr:housenumber":"520",
    "addr:postcode":"28602",
    "addr:street":"20Th St Se",
    "iso:country":"US",
    "sg:address":"520 20th St SE",
    "sg:city":"Hickory",
    "sg:classifiers":[
        {
            "category":"Manufacturing",
            "subcategory":"Textiles",
            "type":"Manufacturing & Wholesale Goods"
        }
    ],
    "sg:phone":"+1 828 322 1158",
    "sg:postcode":"28602",
    "sg:province":"NC",
    "sg:tags":[
        "mill",
        "spinning",
        "yarn"
    ],
    "sg:website":"www.hickorythrowing.com",
    "wof:name":"Hickory Throwing Co",
    "wof:placetype":"venue"
},
  "geometry": {"coordinates":[-81.30192099999999,35.725024],"type":"Point"}
}