{
  "type": "Feature",
  "properties": {
    "addr:full":"115 E Park Ave Unit B Charlotte NC 28203",
    "addr:housenumber":"115",
    "addr:postcode":"28203",
    "addr:street":"E Park Ave Unit B",
    "iso:country":"US",
    "sg:address":"115 E Park Ave Unit B",
    "sg:city":"Charlotte",
    "sg:classifiers":[
        {
            "category":"Building & Trades",
            "subcategory":"Construction",
            "type":"Services"
        },
        {
            "category":"Manufacturing",
            "subcategory":"Building Materials",
            "type":"Manufacturing & Wholesale Goods"
        }
    ],
    "sg:phone":"+1 704 375 1159",
    "sg:postcode":"28203",
    "sg:province":"NC",
    "sg:tags":[
        "pumice",
        "brick",
        "concrete",
        "brick-clay-common",
        "face"
    ],
    "wof:name":"Skipping Stone",
    "wof:placetype":"venue"
},
  "geometry": {"coordinates":[-80.85669900000001,35.214482],"type":"Point"}
}