{
  "type": "Feature",
  "properties": {
    "iso:country":"US",
    "sg:address":"120 Halsey St",
    "sg:city":"Lumberton",
    "sg:classifiers":[
        {
            "category":"Personal",
            "subcategory":"Beauty Salon",
            "type":"Services"
        }
    ],
    "sg:phone":"+1   ",
    "sg:postcode":"28358",
    "sg:province":"NC",
    "sg:tags":[
        "shop"
    ],
    "wof:name":"Laura Maes Beauty Shop",
    "wof:placetype":"venue"
},
  "geometry": {"coordinates":[-79.040127,34.624816],"type":"Point"}
}