{
  "type": "Feature",
  "properties": {
    "iso:country":"US",
    "sg:address":"468 Cranes Creek Rd",
    "sg:city":"Cameron",
    "sg:classifiers":[
        {
            "category":"Banks & Credit Unions",
            "subcategory":"Financial Services",
            "type":"Services"
        }
    ],
    "sg:phone":"+1 910 245 7197",
    "sg:postcode":"28326",
    "sg:province":"NC",
    "sg:tags":[
        "investor"
    ],
    "wof:name":"John D Collins",
    "wof:placetype":"venue"
},
  "geometry": {"coordinates":[-79.287419,35.308723],"type":"Point"}
}