{
  "type": "Feature",
  "properties": {
    "iso:country":"US",
    "sg:address":"1600 Glenwood Ave",
    "sg:city":"Raleigh",
    "sg:classifiers":[
        {
            "category":"Health Services",
            "subcategory":"Health Practitioner",
            "type":"Services"
        }
    ],
    "sg:phone":"+1   ",
    "sg:postcode":"27608",
    "sg:province":"NC",
    "wof:name":"Jacobs Linda F Psych",
    "wof:placetype":"venue"
},
  "geometry": {"coordinates":[-78.645843,35.804023],"type":"Point"}
}