{
  "type": "Feature",
  "properties": {
    "iso:country":"US",
    "sg:address":"746 State Rd 50",
    "sg:city":"Warsaw",
    "sg:classifiers":[
        {
            "category":"Travel",
            "subcategory":"Hotels & Motels",
            "type":"Entertainment"
        }
    ],
    "sg:phone":"+1 910 296 1831",
    "sg:postcode":"28398",
    "sg:province":"NC",
    "wof:name":"Squire's Vintage Inn",
    "wof:placetype":"venue"
},
  "geometry": {"coordinates":[-78.085159,35.004024],"type":"Point"}
}