{
  "type": "Feature",
  "properties": {
    "iso:country":"US",
    "sg:address":"107 Southbank Dr",
    "sg:city":"Cary",
    "sg:classifiers":[
        {
            "category":"Professional",
            "subcategory":"Management & Consulting",
            "type":"Services"
        }
    ],
    "sg:phone":"+1   ",
    "sg:postcode":"27518",
    "sg:province":"NC",
    "sg:tags":[
        "conference"
    ],
    "wof:name":"McElroy Bacon Consulting",
    "wof:placetype":"venue"
},
  "geometry": {"coordinates":[-78.77239899999999,35.727079],"type":"Point"}
}