{
  "type": "Feature",
  "properties": {
    "addr:full":"333 S 5th Ave Kure Beach NC 28449",
    "addr:housenumber":"333",
    "addr:postcode":"28449",
    "addr:street":"S 5Th Ave",
    "iso:country":"US",
    "sg:address":"333 S 5th Ave",
    "sg:city":"Kure Beach",
    "sg:classifiers":[
        {
            "category":"Real Estate",
            "subcategory":"Real Estate Agent",
            "type":"Services"
        }
    ],
    "sg:phone":"+1 910 458 5126",
    "sg:postcode":"28449",
    "sg:province":"NC",
    "wof:name":"Atkinson Realty",
    "wof:placetype":"venue"
},
  "geometry": {"coordinates":[-77.910285,33.994886],"type":"Point"}
}