{
  "type": "Feature",
  "properties": {
    "iso:country":"US",
    "sg:address":"391 Rainbow Rd",
    "sg:city":"Advance",
    "sg:classifiers":[
        {
            "category":"Recreation",
            "type":"Entertainment"
        }
    ],
    "sg:phone":"+1   ",
    "sg:postcode":"27006",
    "sg:province":"NC",
    "sg:tags":[
        "club",
        "membership"
    ],
    "wof:name":"Pinebrook Little League",
    "wof:placetype":"venue"
},
  "geometry": {"coordinates":[-80.49426,35.989237],"type":"Point"}
}