{
  "type": "Feature",
  "properties": {
    "addr:full":"230 Welcome Home Rd Stokesdale NC 27357",
    "addr:housenumber":"230",
    "addr:postcode":"27357",
    "addr:street":"Welcome Home Rd",
    "iso:country":"US",
    "sg:address":"230 Welcome Home Rd",
    "sg:city":"Stokesdale",
    "sg:classifiers":[
        {
            "category":"Building & Trades",
            "subcategory":"Cleaning & Sanitation",
            "type":"Services"
        }
    ],
    "sg:phone":"+1   ",
    "sg:postcode":"27357",
    "sg:province":"NC",
    "sg:tags":[
        "maintenance"
    ],
    "wof:name":"Jackies Janitorial",
    "wof:placetype":"venue"
},
  "geometry": {"coordinates":[-79.942106,36.281654],"type":"Point"}
}