{
  "type": "Feature",
  "properties": {
    "addr:full":"14717 E Rocky River Rd Davidson NC 28036",
    "addr:housenumber":"14717",
    "addr:postcode":"28036",
    "addr:street":"E Rocky River Rd",
    "iso:country":"US",
    "sg:address":"14717 E Rocky River Rd",
    "sg:city":"Davidson",
    "sg:classifiers":[
        {
            "category":"Wholesale",
            "subcategory":"Stationery",
            "type":"Manufacturing & Wholesale Goods"
        }
    ],
    "sg:phone":"+1 704 894 0089",
    "sg:postcode":"28036",
    "sg:province":"NC",
    "sg:tags":[
        "map"
    ],
    "wof:name":"Quality Maps Inc",
    "wof:placetype":"venue"
},
  "geometry": {"coordinates":[-80.79275800000001,35.472941],"type":"Point"}
}