{
  "type": "Feature",
  "properties": {
    "addr:full":"1610 Yelverton Grove Rd Smithfield NC 27577",
    "addr:housenumber":"1610",
    "addr:postcode":"27577",
    "addr:street":"Yelverton Grove Rd",
    "iso:country":"US",
    "sg:address":"1610 Yelverton Grove Rd",
    "sg:city":"Smithfield",
    "sg:classifiers":[
        {
            "category":"Freight",
            "type":"Transportation"
        }
    ],
    "sg:phone":"+1 919 934 7032",
    "sg:postcode":"27577",
    "sg:province":"NC",
    "sg:tags":[
        "trucking"
    ],
    "wof:name":"S E Powell Trucking Inc",
    "wof:placetype":"venue"
},
  "geometry": {"coordinates":[-78.310411,35.486404],"type":"Point"}
}