{
  "type": "Feature",
  "properties": {
    "iso:country":"US",
    "sg:address":"2050 Suttle Ave",
    "sg:city":"Charlotte",
    "sg:classifiers":[
        {
            "category":"Professional",
            "subcategory":"Detective & Security Services",
            "type":"Services"
        }
    ],
    "sg:phone":"+1 704 333 9611",
    "sg:postcode":"28208",
    "sg:province":"NC",
    "sg:tags":[
        "car",
        "armored"
    ],
    "sg:website":"http://www.loomisfargo.com",
    "wof:name":"Loomis Armored Us",
    "wof:placetype":"venue"
},
  "geometry": {"coordinates":[-80.87136,35.225806],"type":"Point"}
}