{
  "type": "Feature",
  "properties": {
    "iso:country":"US",
    "sg:address":"4351 Sunscape Ln",
    "sg:city":"Raleigh",
    "sg:classifiers":[
        {
            "category":"Shopping",
            "subcategory":"Bicycles & Sporting Goods",
            "type":"Retail Goods"
        }
    ],
    "sg:phone":"+1 919 789 8864",
    "sg:postcode":"27613",
    "sg:province":"NC",
    "wof:name":"Franks Cyclery LLC",
    "wof:placetype":"venue"
},
  "geometry": {"coordinates":[-78.70636,35.865707],"type":"Point"}
}