{
  "type": "Feature",
  "properties": {
    "addr:full":"3384 Farm Lake Dr SW Concord NC 28027",
    "addr:housenumber":"3384",
    "addr:postcode":"28027",
    "addr:street":"Farm Lake Dr Sw",
    "iso:country":"US",
    "sg:address":"3384 Farm Lake Dr SW",
    "sg:city":"Concord",
    "sg:classifiers":[
        {
            "category":"Professional",
            "subcategory":"Employment Agencies",
            "type":"Services"
        }
    ],
    "sg:phone":"+1   ",
    "sg:postcode":"28027",
    "sg:province":"NC",
    "wof:name":"Multilingual Placement Service",
    "wof:placetype":"venue"
},
  "geometry": {"coordinates":[-80.614369,35.368294],"type":"Point"}
}