{
  "type": "Feature",
  "properties": {
    "addr:full":"8216 Creedmoor Rd Raleigh NC 27613",
    "addr:housenumber":"8216",
    "addr:postcode":"27613",
    "addr:street":"Creedmoor Rd",
    "iso:country":"US",
    "sg:address":"8216 Creedmoor Rd",
    "sg:city":"Raleigh",
    "sg:classifiers":[
        {
            "category":"Education",
            "subcategory":"School",
            "type":"Public Place"
        },
        {
            "category":"Education",
            "subcategory":"Special Training",
            "type":"Public Place"
        }
    ],
    "sg:phone":"+1 919 676 7416",
    "sg:postcode":"27613",
    "sg:province":"NC",
    "sg:tags":[
        "language"
    ],
    "wof:name":"Accelerated Language Academy I",
    "wof:placetype":"venue"
},
  "geometry": {"coordinates":[-78.680621,35.898727],"type":"Point"}
}