{
  "type": "Feature",
  "properties": {
    "iso:country":"US",
    "sg:address":"2415 Executive St",
    "sg:city":"Charlotte",
    "sg:classifiers":[
        {
            "category":"Professional",
            "subcategory":"Detective & Security Services",
            "type":"Services"
        }
    ],
    "sg:phone":"+1 704 398 7960",
    "sg:postcode":"28208",
    "sg:province":"NC",
    "sg:tags":[
        "car",
        "armored"
    ],
    "wof:name":"Brink's Inc",
    "wof:placetype":"venue"
},
  "geometry": {"coordinates":[-80.90759199999999,35.238263],"type":"Point"}
}