{
  "type": "Feature",
  "properties": {
    "addr:full":"245 W Kings Hwy Eden NC 27288",
    "addr:housenumber":"245",
    "addr:postcode":"27288",
    "addr:street":"W Kings Hwy",
    "iso:country":"US",
    "sg:address":"245 W Kings Hwy",
    "sg:city":"Eden",
    "sg:classifiers":[
        {
            "category":"Restaurant",
            "type":"Food & Drink"
        }
    ],
    "sg:phone":"+1 336 635 6969",
    "sg:postcode":"27288",
    "sg:province":"NC",
    "wof:name":"Mama Mia Pizzeria",
    "wof:placetype":"venue"
},
  "geometry": {"coordinates":[-79.745886,36.492375],"type":"Point"}
}