{
  "type": "Feature",
  "properties": {
    "addr:full":"1616 Quail Hollow Ct Gastonia NC 28054",
    "addr:housenumber":"1616",
    "addr:postcode":"28054",
    "addr:street":"Quail Hollow Ct",
    "iso:country":"US",
    "sg:address":"1616 Quail Hollow Ct",
    "sg:city":"Gastonia",
    "sg:classifiers":[
        {
            "category":"Building & Trades",
            "subcategory":"Construction",
            "type":"Services"
        }
    ],
    "sg:phone":"+1 704 865 6262",
    "sg:postcode":"28054",
    "sg:province":"NC",
    "sg:tags":[
        "house"
    ],
    "wof:name":"Quail Hollow Construction Comp",
    "wof:placetype":"venue"
},
  "geometry": {"coordinates":[-81.143202,35.240583],"type":"Point"}
}