{
  "type": "Feature",
  "properties": {
    "addr:full":"543 Anglin Mill Rd Stoneville NC 27048",
    "addr:housenumber":"543",
    "addr:postcode":"27048",
    "addr:street":"Anglin Mill Rd",
    "iso:country":"US",
    "sg:address":"543 Anglin Mill Rd",
    "sg:city":"Stoneville",
    "sg:classifiers":[
        {
            "category":"Organizations",
            "subcategory":"Religious Organization",
            "type":"Services"
        }
    ],
    "sg:phone":"+1 336 573 1573",
    "sg:postcode":"27048",
    "sg:province":"NC",
    "sg:tags":[
        "church"
    ],
    "wof:name":"Christianveiw Christian Church",
    "wof:placetype":"venue"
},
  "geometry": {"coordinates":[-79.94535399999999,36.539268],"type":"Point"}
}