{
  "type": "Feature",
  "properties": {
    "addr:full":"2601 Wake Forest Rd Raleigh NC 27609",
    "addr:housenumber":"2601",
    "addr:postcode":"27609",
    "addr:street":"Wake Forest Rd",
    "iso:country":"US",
    "sg:address":"2601 Wake Forest Rd",
    "sg:city":"Raleigh",
    "sg:classifiers":[
        {
            "category":"Restaurant",
            "type":"Food & Drink"
        }
    ],
    "sg:menulink":"http://www.allmenus.com/nc/raleigh/158863-arbys/menu/",
    "sg:phone":"+1 919 832 6885",
    "sg:postcode":"27609",
    "sg:province":"NC",
    "sg:tags":[
        "burger",
        "american"
    ],
    "wof:name":"Arby's",
    "wof:placetype":"venue"
},
  "geometry": {"coordinates":[-78.62513199999999,35.818405],"type":"Point"}
}