{
  "type": "Feature",
  "properties": {
    "iso:country":"US",
    "sg:address":"2416 Colletta Ave",
    "sg:city":"Statesville",
    "sg:classifiers":[
        {
            "category":"Professional",
            "subcategory":"Management & Consulting",
            "type":"Services"
        }
    ],
    "sg:phone":"+1   ",
    "sg:postcode":"28625",
    "sg:province":"NC",
    "wof:name":"Craig II J",
    "wof:placetype":"venue"
},
  "geometry": {"coordinates":[-80.841629,35.782524],"type":"Point"}
}