{
  "type": "Feature",
  "properties": {
    "iso:country":"US",
    "sg:address":"3304 Collins Rd",
    "sg:city":"Waxhaw",
    "sg:classifiers":[
        {
            "category":"Wholesale",
            "subcategory":"Metals & Minerals",
            "type":"Manufacturing & Wholesale Goods"
        }
    ],
    "sg:phone":"+1 704 843 9350",
    "sg:postcode":"28173",
    "sg:province":"NC",
    "sg:tags":[
        "steel",
        "broker"
    ],
    "sg:website":"www.amsspecialtysteel.com",
    "wof:name":"Ams Specialty Steel LLC",
    "wof:placetype":"venue"
},
  "geometry": {"coordinates":[-80.709841,34.930353],"type":"Point"}
}