{
  "type": "Feature",
  "properties": {
    "iso:country":"US",
    "sg:address":"6014 Duraleigh Rd",
    "sg:city":"Raleigh",
    "sg:classifiers":[
        {
            "category":"Food & Beverages",
            "subcategory":"Groceries & Convenience Stores",
            "type":"Retail Goods"
        }
    ],
    "sg:phone":"+1 919 788 7777",
    "sg:postcode":"27612",
    "sg:province":"NC",
    "wof:name":"Kim's Asian Market",
    "wof:placetype":"venue"
},
  "geometry": {"coordinates":[-78.7127,35.859798],"type":"Point"}
}