{
  "type": "Feature",
  "properties": {
    "iso:country":"US",
    "sg:address":"104 Branchwood Dr",
    "sg:city":"Elon College",
    "sg:classifiers":[
        {
            "category":"Health Services",
            "subcategory":"Clinic",
            "type":"Services"
        }
    ],
    "sg:phone":"+1   ",
    "sg:postcode":"27244",
    "sg:province":"NC",
    "sg:tags":[
        "medical",
        "consultation"
    ],
    "wof:name":"James K Fleming MD",
    "wof:placetype":"venue"
},
  "geometry": {"coordinates":[-79.51661900000001,36.09444],"type":"Point"}
}