{
  "type": "Feature",
  "properties": {
    "iso:country":"US",
    "sg:address":"2425 Fayetteville Rd",
    "sg:city":"Durham",
    "sg:classifiers":[
        {
            "category":"Retail",
            "subcategory":"Auto Repair",
            "type":"Services"
        }
    ],
    "sg:phone":"+1 919 688 5777",
    "sg:postcode":"27707",
    "sg:province":"NC",
    "sg:tags":[
        "repairing",
        "automobile"
    ],
    "wof:name":"Tedder's Sameday Auto Svc Ctr",
    "wof:placetype":"venue"
},
  "geometry": {"coordinates":[-78.902124,35.969279],"type":"Point"}
}