{
  "type": "Feature",
  "properties": {
    "addr:full":"4900 Randall Pkwy Wilmington NC 28403",
    "addr:housenumber":"4900",
    "addr:postcode":"28403",
    "addr:street":"Randall Pkwy",
    "iso:country":"US",
    "sg:address":"4900 Randall Pkwy",
    "sg:city":"Wilmington",
    "sg:classifiers":[
        {
            "category":"Professional",
            "subcategory":"Employment Agencies",
            "type":"Services"
        }
    ],
    "sg:phone":"+1   ",
    "sg:postcode":"28403",
    "sg:province":"NC",
    "wof:name":"Anderson Dniel Personnel Assoc",
    "wof:placetype":"venue"
},
  "geometry": {"coordinates":[-77.88109300000001,34.231957],"type":"Point"}
}