{
  "type": "Feature",
  "properties": {
    "addr:full":"3805 Oleander Dr Wilmington NC 28403",
    "addr:housenumber":"3805",
    "addr:postcode":"28403",
    "addr:street":"Oleander Dr",
    "iso:country":"US",
    "sg:address":"3805 Oleander Dr",
    "sg:city":"Wilmington",
    "sg:classifiers":[
        {
            "category":"Retail",
            "subcategory":"Photofinishing",
            "type":"Services"
        }
    ],
    "sg:phone":"+1 910 392 4100",
    "sg:postcode":"28403",
    "sg:province":"NC",
    "sg:tags":[
        "film",
        "developing"
    ],
    "wof:name":"Tarheel Photo Inc",
    "wof:placetype":"venue"
},
  "geometry": {"coordinates":[-77.899483,34.213988],"type":"Point"}
}