{
  "type": "Feature",
  "properties": {
    "iso:country":"US",
    "sg:address":"110 S Depot St",
    "sg:city":"Pilot Mountain",
    "sg:classifiers":[
        {
            "category":"Wholesale",
            "subcategory":"Tobacco Products",
            "type":"Manufacturing & Wholesale Goods"
        }
    ],
    "sg:phone":"+1 336 368 7133",
    "sg:postcode":"27041",
    "sg:province":"NC",
    "sg:tags":[
        "cigarette",
        "cigar",
        "dealer"
    ],
    "wof:name":"Premium Tobacco Co Us Inc",
    "wof:placetype":"venue"
},
  "geometry": {"coordinates":[-80.467082,36.38491],"type":"Point"}
}