{
  "type": "Feature",
  "properties": {
    "iso:country":"US",
    "sg:address":"109 E Spring St",
    "sg:city":"Fuquay Varina",
    "sg:classifiers":[
        {
            "category":"Shopping",
            "type":"Retail Goods"
        }
    ],
    "sg:phone":"+1 919 552 6802",
    "sg:postcode":"27526",
    "sg:province":"NC",
    "sg:tags":[
        "merchandise"
    ],
    "wof:name":"Magnolia House",
    "wof:placetype":"venue"
},
  "geometry": {"coordinates":[-78.79965,35.580365],"type":"Point"}
}