{
  "type": "Feature",
  "properties": {
    "addr:full":"3495 Fayetteville Rd Lumberton NC 28358",
    "addr:housenumber":"3495",
    "addr:postcode":"28358",
    "addr:street":"Fayetteville Rd",
    "iso:country":"US",
    "sg:address":"3495 Fayetteville Rd",
    "sg:city":"Lumberton",
    "sg:classifiers":[
        {
            "category":"Recreation",
            "type":"Entertainment"
        }
    ],
    "sg:phone":"+1 910 738 2888",
    "sg:postcode":"28358",
    "sg:province":"NC",
    "sg:tags":[
        "skating",
        "rink"
    ],
    "wof:name":"Mr P's Skateworld",
    "wof:placetype":"venue"
},
  "geometry": {"coordinates":[-79.001239,34.639132],"type":"Point"}
}