{
  "type": "Feature",
  "properties": {
    "iso:country":"US",
    "sg:address":"3505 Roxboro Rd",
    "sg:city":"Durham",
    "sg:classifiers":[
        {
            "category":"Professional",
            "subcategory":"Management & Consulting",
            "type":"Services"
        }
    ],
    "sg:phone":"+1 919 479 2121",
    "sg:postcode":"27704",
    "sg:province":"NC",
    "sg:tags":[
        "communications",
        "consultant"
    ],
    "sg:website":"www.transglobal.com",
    "wof:name":"Trans Global Engineering",
    "wof:placetype":"venue"
},
  "geometry": {"coordinates":[-78.89572699999999,36.036556],"type":"Point"}
}