{
  "type": "Feature",
  "properties": {
    "iso:country":"US",
    "sg:address":"6440 Tivoli Ct",
    "sg:city":"Charlotte",
    "sg:classifiers":[
        {
            "category":"Retail",
            "subcategory":"Auto Repair",
            "type":"Services"
        }
    ],
    "sg:phone":"+1   ",
    "sg:postcode":"28211",
    "sg:province":"NC",
    "sg:tags":[
        "general"
    ],
    "wof:name":"Bestg Tech Auto Repair",
    "wof:placetype":"venue"
},
  "geometry": {"coordinates":[-80.753353,35.151239],"type":"Point"}
}