{
  "type": "Feature",
  "properties": {
    "iso:country":"US",
    "sg:address":"1415 S Church St",
    "sg:city":"Charlotte",
    "sg:classifiers":[
        {
            "category":"Professional",
            "subcategory":"Engineering",
            "type":"Services"
        }
    ],
    "sg:phone":"+1 704 348 2993",
    "sg:postcode":"28203",
    "sg:province":"NC",
    "sg:tags":[
        "engineer",
        "mechanical"
    ],
    "sg:website":"http://www.hesm.com",
    "wof:name":"H ESM & A Consulting Engineers",
    "wof:placetype":"venue"
},
  "geometry": {"coordinates":[-80.857433,35.219031],"type":"Point"}
}