{
  "type": "Feature",
  "properties": {
    "addr:full":"216 W Jones St Raleigh NC 27603",
    "addr:housenumber":"216",
    "addr:postcode":"27603",
    "addr:street":"W Jones St",
    "iso:country":"US",
    "sg:address":"216 W Jones St",
    "sg:city":"Raleigh",
    "sg:classifiers":[
        {
            "category":"Government",
            "subcategory":"Office",
            "type":"Public Place"
        }
    ],
    "sg:phone":"+1 919 733 3933",
    "sg:postcode":"27603",
    "sg:province":"NC",
    "sg:tags":[
        "plant",
        "industry"
    ],
    "wof:name":"Agriclture Consmr Svcs NC Dept",
    "wof:placetype":"venue"
},
  "geometry": {"coordinates":[-78.643022,35.782757],"type":"Point"}
}