{
  "type": "Feature",
  "properties": {
    "addr:full":"401 Woodland Ave Winston Salem NC 27101",
    "addr:housenumber":"401",
    "addr:postcode":"27101",
    "addr:street":"Woodland Ave",
    "iso:country":"US",
    "sg:address":"401 Woodland Ave",
    "sg:city":"Winston Salem",
    "sg:classifiers":[
        {
            "category":"Organizations",
            "subcategory":"Religious Organization",
            "type":"Services"
        }
    ],
    "sg:phone":"+1   ",
    "sg:postcode":"27101",
    "sg:province":"NC",
    "wof:name":"First Calvary Baptist Church",
    "wof:placetype":"venue"
},
  "geometry": {"coordinates":[-80.232218,36.100522],"type":"Point"}
}