{
  "type": "Feature",
  "properties": {
    "addr:full":"52 Sommerset Dr Clayton NC 27520",
    "addr:housenumber":"52",
    "addr:postcode":"27520",
    "addr:street":"Sommerset Dr",
    "iso:country":"US",
    "sg:address":"52 Sommerset Dr",
    "sg:city":"Clayton",
    "sg:classifiers":[
        {
            "category":"Building & Trades",
            "subcategory":"Construction",
            "type":"Services"
        }
    ],
    "sg:phone":"+1 919 938 0213",
    "sg:postcode":"27520",
    "sg:province":"NC",
    "sg:tags":[
        "contractor"
    ],
    "wof:name":"Bridges Iron Works",
    "wof:placetype":"venue"
},
  "geometry": {"coordinates":[-78.505194,35.548394],"type":"Point"}
}