{
  "type": "Feature",
  "properties": {
    "addr:full":"153 S End Rd Knotts Island NC 27950",
    "addr:housenumber":"153",
    "addr:postcode":"27950",
    "addr:street":"S End Rd",
    "iso:country":"US",
    "sg:address":"153 S End Rd",
    "sg:city":"Knotts Island",
    "sg:classifiers":[
        {
            "category":"Government",
            "subcategory":"Fire Station",
            "type":"Public Place"
        }
    ],
    "sg:phone":"+1 252 429 3536",
    "sg:postcode":"27950",
    "sg:province":"NC",
    "sg:tags":[
        "department"
    ],
    "wof:name":"Knotts Island Rescue Squad",
    "wof:placetype":"venue"
},
  "geometry": {"coordinates":[-75.92521499999999,36.508704],"type":"Point"}
}