{
  "type": "Feature",
  "properties": {
    "iso:country":"US",
    "sg:address":"618 S Main St",
    "sg:city":"Reidsville",
    "sg:classifiers":[
        {
            "category":"Professional",
            "type":"Services"
        }
    ],
    "sg:phone":"+1 336 349 5696",
    "sg:postcode":"27320",
    "sg:province":"NC",
    "wof:name":"Reidsville Cmnty Physicians",
    "wof:placetype":"venue"
},
  "geometry": {"coordinates":[-79.666357,36.353551],"type":"Point"}
}