{
  "type": "Feature",
  "properties": {
    "iso:country":"US",
    "sg:address":"1301 Hemlock St",
    "sg:city":"Charlotte",
    "sg:classifiers":[
        {
            "category":"Travel",
            "subcategory":"Hotels & Motels",
            "type":"Entertainment"
        }
    ],
    "sg:phone":"+1 704 335 9660",
    "sg:postcode":"28203",
    "sg:province":"NC",
    "sg:tags":[
        "resort"
    ],
    "wof:name":"Lois Lodge",
    "wof:placetype":"venue"
},
  "geometry": {"coordinates":[-80.84744499999999,35.197946],"type":"Point"}
}