{
  "type": "Feature",
  "properties": {
    "iso:country":"US",
    "sg:address":"3740 Caribou Dr",
    "sg:city":"Sherrills Ford",
    "sg:classifiers":[
        {
            "category":"Professional",
            "type":"Services"
        }
    ],
    "sg:phone":"+1 704 483 0183",
    "sg:postcode":"28673",
    "sg:province":"NC",
    "wof:name":"Darline Jordan",
    "wof:placetype":"venue"
},
  "geometry": {"coordinates":[-81.051446,35.588487],"type":"Point"}
}