{
  "type": "Feature",
  "properties": {
    "addr:full":"301 Willowbrook Dr Morganton NC 28655",
    "addr:housenumber":"301",
    "addr:postcode":"28655",
    "addr:street":"Willowbrook Dr",
    "iso:country":"US",
    "sg:address":"301 Willowbrook Dr",
    "sg:city":"Morganton",
    "sg:classifiers":[
        {
            "category":"Professional",
            "type":"Services"
        }
    ],
    "sg:phone":"+1 828 437 2918",
    "sg:postcode":"28655",
    "sg:province":"NC",
    "wof:name":"Royal & Select Masters In",
    "wof:placetype":"venue"
},
  "geometry": {"coordinates":[-81.668481,35.735532],"type":"Point"}
}