{
  "type": "Feature",
  "properties": {
    "addr:full":"8992 Old Fayetteville Rd Garland NC 28441",
    "addr:housenumber":"8992",
    "addr:postcode":"28441",
    "addr:street":"Old Fayetteville Rd",
    "iso:country":"US",
    "sg:address":"8992 Old Fayetteville Rd",
    "sg:city":"Garland",
    "sg:classifiers":[
        {
            "category":"Freight",
            "type":"Transportation"
        }
    ],
    "sg:phone":"+1 910 588 4872",
    "sg:postcode":"28441",
    "sg:province":"NC",
    "sg:tags":[
        "operator",
        "local",
        "trucking"
    ],
    "wof:name":"Smiths Trucking Inc",
    "wof:placetype":"venue"
},
  "geometry": {"coordinates":[-78.58336,34.807064],"type":"Point"}
}