{
  "type": "Feature",
  "properties": {
    "addr:full":"110 S Bragg Blvd Spring Lake NC 28390",
    "addr:housenumber":"110",
    "addr:postcode":"28390",
    "addr:street":"S Bragg Blvd",
    "iso:country":"US",
    "sg:address":"110 S Bragg Blvd",
    "sg:city":"Spring Lake",
    "sg:classifiers":[
        {
            "category":"Restaurant",
            "type":"Food & Drink"
        }
    ],
    "sg:phone":"+1 910 497 1500",
    "sg:postcode":"28390",
    "sg:province":"NC",
    "sg:tags":[
        "eating"
    ],
    "wof:name":"Baldinos Giant Jersey Subs",
    "wof:placetype":"venue"
},
  "geometry": {"coordinates":[-78.972396,35.165717],"type":"Point"}
}