{
  "type": "Feature",
  "properties": {
    "iso:country":"US",
    "sg:address":"2800 Rue Sans Famille",
    "sg:city":"Raleigh",
    "sg:classifiers":[
        {
            "category":"Manufacturing",
            "subcategory":"Paper Products",
            "type":"Manufacturing & Wholesale Goods"
        }
    ],
    "sg:phone":"+1 919 781 7761",
    "sg:postcode":"27607",
    "sg:province":"NC",
    "sg:tags":[
        "mill"
    ],
    "wof:name":"Paperwork Plus Inc",
    "wof:placetype":"venue"
},
  "geometry": {"coordinates":[-78.68769399999999,35.822882],"type":"Point"}
}