{
  "type": "Feature",
  "properties": {
    "iso:country":"US",
    "sg:address":"2130 Bishop Rd",
    "sg:city":"Greensboro",
    "sg:classifiers":[
        {
            "category":"Mining & Drilling",
            "type":"Manufacturing & Wholesale Goods"
        }
    ],
    "sg:phone":"+1 336 852 9107",
    "sg:postcode":"27406",
    "sg:province":"NC",
    "sg:tags":[
        "sand",
        "quarry"
    ],
    "wof:name":"A-1 Trucking",
    "wof:placetype":"venue"
},
  "geometry": {"coordinates":[-79.850253,35.992064],"type":"Point"}
}