{
  "type": "Feature",
  "properties": {
    "iso:country":"US",
    "sg:address":"3327 Holloway St",
    "sg:city":"Durham",
    "sg:classifiers":[
        {
            "category":"Restaurant",
            "type":"Food & Drink"
        }
    ],
    "sg:phone":"+1 919 598 6817",
    "sg:postcode":"27703",
    "sg:province":"NC",
    "sg:tags":[
        "eating"
    ],
    "wof:name":"Home Plate Restaurant",
    "wof:placetype":"venue"
},
  "geometry": {"coordinates":[-78.831487,35.983989],"type":"Point"}
}