{
  "type": "Feature",
  "properties": {
    "iso:country":"US",
    "sg:address":"9 Birchwood Ln",
    "sg:city":"Asheville",
    "sg:classifiers":[
        {
            "category":"Building & Trades",
            "subcategory":"Plumbing",
            "type":"Services"
        }
    ],
    "sg:phone":"+1 828 298 8658",
    "sg:postcode":"28805",
    "sg:province":"NC",
    "sg:tags":[
        "plumbing",
        "contractor"
    ],
    "wof:name":"Plumbing Co",
    "wof:placetype":"venue"
},
  "geometry": {"coordinates":[-82.48338099999999,35.579438],"type":"Point"}
}