{
  "type": "Feature",
  "properties": {
    "iso:country":"US",
    "sg:address":"1315 Manicott Dr",
    "sg:city":"Matthews",
    "sg:classifiers":[
        {
            "category":"Wholesale",
            "subcategory":"Stationery",
            "type":"Manufacturing & Wholesale Goods"
        }
    ],
    "sg:phone":"+1 704 708 5039",
    "sg:postcode":"28105",
    "sg:province":"NC",
    "sg:tags":[
        "product",
        "paper"
    ],
    "sg:website":"www.sappi.com",
    "wof:name":"Sappi Fine Paper",
    "wof:placetype":"venue"
},
  "geometry": {"coordinates":[-80.750244,35.10242],"type":"Point"}
}