{
  "type": "Feature",
  "properties": {
    "addr:full":"1701 E 11th St Siler City NC 27344",
    "addr:housenumber":"1701",
    "addr:postcode":"27344",
    "addr:street":"E 11Th St",
    "iso:country":"US",
    "sg:address":"1701 E 11th St",
    "sg:city":"Siler City",
    "sg:classifiers":[
        {
            "category":"Retail",
            "subcategory":"Auto Repair",
            "type":"Services"
        }
    ],
    "sg:phone":"+1 919 663 3599",
    "sg:postcode":"27344",
    "sg:province":"NC",
    "sg:tags":[
        "body",
        "automobile",
        "painting"
    ],
    "wof:name":"Superior Auto Body",
    "wof:placetype":"venue"
},
  "geometry": {"coordinates":[-79.44024,35.733401],"type":"Point"}
}