{
  "type": "Feature",
  "properties": {
    "addr:full":"230 N Church St Rocky Mount NC 27804",
    "addr:housenumber":"230",
    "addr:postcode":"27804",
    "addr:street":"N Church St",
    "iso:country":"US",
    "sg:address":"230 N Church St",
    "sg:city":"Rocky Mount",
    "sg:classifiers":[
        {
            "category":"Retail",
            "subcategory":"Auto Rental",
            "type":"Services"
        }
    ],
    "sg:phone":"+1 252 446 4912",
    "sg:postcode":"27804",
    "sg:province":"NC",
    "sg:tags":[
        "renting",
        "automobile"
    ],
    "wof:name":"Hertz Rent A Car",
    "wof:placetype":"venue"
},
  "geometry": {"coordinates":[-77.795884,35.945547],"type":"Point"}
}