{
  "type": "Feature",
  "properties": {
    "addr:full":"1247 East Blvd Ste 250 Charlotte NC 28203",
    "addr:housenumber":"1247",
    "addr:postcode":"28203",
    "addr:street":"East Blvd Ste 250",
    "iso:country":"US",
    "sg:address":"1247 East Blvd Ste 250",
    "sg:city":"Charlotte",
    "sg:classifiers":[
        {
            "category":"Sports & Exercise",
            "subcategory":"Gym",
            "type":"Entertainment"
        }
    ],
    "sg:phone":"+1 704 372 7665",
    "sg:postcode":"28203",
    "sg:province":"NC",
    "sg:tags":[
        "instruction",
        "yoga"
    ],
    "sg:website":"http://beyogaandwellness.com",
    "wof:name":"Be Yoga",
    "wof:placetype":"venue"
},
  "geometry": {"coordinates":[-80.845212,35.202367],"type":"Point"}
}