{
  "type": "Feature",
  "properties": {
    "iso:country":"US",
    "sg:address":"225 Kingsport Rd",
    "sg:city":"Holly Springs",
    "sg:classifiers":[
        {
            "category":"Professional",
            "type":"Services"
        }
    ],
    "sg:phone":"+1 919 577 0281",
    "sg:postcode":"27540",
    "sg:province":"NC",
    "wof:name":"Bourns Inc",
    "wof:placetype":"venue"
},
  "geometry": {"coordinates":[-78.815057,35.659675],"type":"Point"}
}