{
  "type": "Feature",
  "properties": {
    "addr:full":"858 S Fort Fisher Blvd Kure Beach NC 28449",
    "addr:housenumber":"858",
    "addr:postcode":"28449",
    "addr:street":"S Fort Fisher Blvd",
    "iso:country":"US",
    "sg:address":"858 S Fort Fisher Blvd",
    "sg:city":"Kure Beach",
    "sg:classifiers":[
        {
            "category":"Food & Beverages",
            "subcategory":"Groceries & Convenience Stores",
            "type":"Retail Goods"
        }
    ],
    "sg:phone":"+1 910 458 8309",
    "sg:postcode":"28449",
    "sg:province":"NC",
    "wof:name":"Trading Post Fort Fisher",
    "wof:placetype":"venue"
},
  "geometry": {"coordinates":[-77.9226,33.9673],"type":"Point"}
}