{
  "type": "Feature",
  "properties": {
    "addr:full":"1144 Bridford Lake Cir Greensboro NC 27407",
    "addr:housenumber":"1144",
    "addr:postcode":"27407",
    "addr:street":"Bridford Lake Cir",
    "iso:country":"US",
    "sg:address":"1144 Bridford Lake Cir",
    "sg:city":"Greensboro",
    "sg:classifiers":[
        {
            "category":"Shopping",
            "subcategory":"Gifts & Souvenirs",
            "type":"Retail Goods"
        }
    ],
    "sg:phone":"+1 336 323 7737",
    "sg:postcode":"27407",
    "sg:province":"NC",
    "wof:name":"Cynthias Elegant Gifts",
    "wof:placetype":"venue"
},
  "geometry": {"coordinates":[-79.902394,36.041801],"type":"Point"}
}