{
  "type": "Feature",
  "properties": {
    "iso:country":"US",
    "sg:address":"826 Central Ave",
    "sg:city":"Charlotte",
    "sg:classifiers":[
        {
            "category":"Shopping",
            "subcategory":"Used Merchandise",
            "type":"Retail Goods"
        }
    ],
    "sg:phone":"+1 704 634 4391",
    "sg:postcode":"28204",
    "sg:province":"NC",
    "sg:tags":[
        "building",
        "material"
    ],
    "wof:name":"Architectural Salvage Co",
    "wof:placetype":"venue"
},
  "geometry": {"coordinates":[-80.82204900000001,35.221688],"type":"Point"}
}