{
  "type": "Feature",
  "properties": {
    "iso:country":"US",
    "sg:address":"3140 Piper Ln",
    "sg:city":"Charlotte",
    "sg:classifiers":[
        {
            "category":"Wholesale",
            "subcategory":"Electrical",
            "type":"Manufacturing & Wholesale Goods"
        }
    ],
    "sg:phone":"+1 704 357 0797",
    "sg:postcode":"28208",
    "sg:province":"NC",
    "sg:tags":[
        "equipment"
    ],
    "wof:name":"Carolina Industrial Pdts NC",
    "wof:placetype":"venue"
},
  "geometry": {"coordinates":[-80.927654,35.194811],"type":"Point"}
}