{
  "type": "Feature",
  "properties": {
    "iso:country":"US",
    "sg:address":"102 McCoy Ct",
    "sg:city":"Cary",
    "sg:classifiers":[
        {
            "category":"Building & Trades",
            "subcategory":"Construction",
            "type":"Services"
        }
    ],
    "sg:phone":"+1 919 319 7540",
    "sg:postcode":"27511",
    "sg:province":"NC",
    "sg:tags":[
        "nonresidential"
    ],
    "wof:name":"Grizzly Construction",
    "wof:placetype":"venue"
},
  "geometry": {"coordinates":[-78.81185000000001,35.762982],"type":"Point"}
}