{
  "type": "Feature",
  "properties": {
    "addr:full":"2333 Rosewood Ave Winston Salem NC 27103",
    "addr:housenumber":"2333",
    "addr:postcode":"27103",
    "addr:street":"Rosewood Ave",
    "iso:country":"US",
    "sg:address":"2333 Rosewood Ave",
    "sg:city":"Winston Salem",
    "sg:classifiers":[
        {
            "category":"Social Services",
            "type":"Services"
        }
    ],
    "sg:phone":"+1 336 722 4324",
    "sg:postcode":"27103",
    "sg:province":"NC",
    "sg:tags":[
        "counseling"
    ],
    "wof:name":"Donna M Burke",
    "wof:placetype":"venue"
},
  "geometry": {"coordinates":[-80.278688,36.084746],"type":"Point"}
}