{
  "type": "Feature",
  "properties": {
    "addr:full":"3314 Nevin Rd Charlotte NC 28269",
    "addr:housenumber":"3314",
    "addr:postcode":"28269",
    "addr:street":"Nevin Rd",
    "iso:country":"US",
    "sg:address":"3314 Nevin Rd",
    "sg:city":"Charlotte",
    "sg:classifiers":[
        {
            "category":"Social Services",
            "subcategory":"Child Care",
            "type":"Services"
        }
    ],
    "sg:phone":"+1   ",
    "sg:postcode":"28269",
    "sg:province":"NC",
    "sg:tags":[
        "day"
    ],
    "wof:name":"Nevin Road Daycare",
    "wof:placetype":"venue"
},
  "geometry": {"coordinates":[-80.83024500000001,35.282424],"type":"Point"}
}