{
  "type": "Feature",
  "properties": {
    "iso:country":"US",
    "sg:address":"1107 Westlake Dr",
    "sg:city":"Kannapolis",
    "sg:classifiers":[
        {
            "category":"Building & Trades",
            "subcategory":"Construction",
            "type":"Services"
        }
    ],
    "sg:phone":"+1 704 363 3727",
    "sg:postcode":"28081",
    "sg:province":"NC",
    "sg:tags":[
        "operator",
        "concrete",
        "company",
        "contractor",
        "trucking"
    ],
    "wof:name":"Sol Construction Corp",
    "wof:placetype":"venue"
},
  "geometry": {"coordinates":[-80.640225,35.520099],"type":"Point"}
}