{
  "type": "Feature",
  "properties": {
    "iso:country":"US",
    "sg:address":"201 W Main St",
    "sg:city":"Battleboro",
    "sg:classifiers":[
        {
            "category":"Food & Beverages",
            "subcategory":"Groceries & Convenience Stores",
            "type":"Retail Goods"
        }
    ],
    "sg:phone":"+1 252 977 7593",
    "sg:postcode":"27897",
    "sg:province":"NC",
    "sg:tags":[
        "grocer"
    ],
    "wof:name":"Cockrell's Grocery & Grill",
    "wof:placetype":"venue"
},
  "geometry": {"coordinates":[-77.215217,36.329831],"type":"Point"}
}