{
  "type": "Feature",
  "properties": {
    "addr:full":"23500 Marston Rd Laurel Hill NC 28351",
    "addr:postcode":"23500;28351",
    "addr:street":"Marston Rd",
    "iso:country":"US",
    "sg:address":"23500 Marston Rd",
    "sg:city":"Laurel Hill",
    "sg:classifiers":[
        {
            "category":"Professional",
            "subcategory":"Management & Consulting",
            "type":"Services"
        }
    ],
    "sg:phone":"+1   ",
    "sg:postcode":"28351",
    "sg:province":"NC",
    "wof:name":"Tim Johnson",
    "wof:placetype":"venue"
},
  "geometry": {"coordinates":[-79.54388299999999,34.881173],"type":"Point"}
}