{
  "type": "Feature",
  "properties": {
    "iso:country":"US",
    "sg:address":"1435 State Hwy 61",
    "sg:city":"Whitsett",
    "sg:classifiers":[
        {
            "category":"Retail",
            "subcategory":"Repair Shop",
            "type":"Services"
        }
    ],
    "sg:phone":"+1 336 449 7860",
    "sg:postcode":"27377",
    "sg:province":"NC",
    "sg:tags":[
        "welding"
    ],
    "wof:name":"Joel's Portable Welding",
    "wof:placetype":"venue"
},
  "geometry": {"coordinates":[-79.573255,36.046426],"type":"Point"}
}