{
  "type": "Feature",
  "properties": {
    "addr:full":"58 S Main St Sparta NC 28675",
    "addr:housenumber":"58",
    "addr:postcode":"28675",
    "addr:street":"S Main St",
    "iso:country":"US",
    "sg:address":"58 S Main St",
    "sg:city":"Sparta",
    "sg:classifiers":[
        {
            "category":"Organizations",
            "subcategory":"Professional Association",
            "type":"Services"
        }
    ],
    "sg:phone":"+1 336 372 5473",
    "sg:postcode":"28675",
    "sg:province":"NC",
    "sg:tags":[
        "chambers",
        "commerce"
    ],
    "wof:name":"Alleghany County Chamber-Cmmrc",
    "wof:placetype":"venue"
},
  "geometry": {"coordinates":[-81.12013399999999,36.504792],"type":"Point"}
}