{
  "type": "Feature",
  "properties": {
    "iso:country":"US",
    "sg:address":"6925 Three Bridges Cir",
    "sg:city":"Raleigh",
    "sg:classifiers":[
        {
            "category":"Professional",
            "subcategory":"Research",
            "type":"Services"
        }
    ],
    "sg:phone":"+1   ",
    "sg:postcode":"27613",
    "sg:province":"NC",
    "sg:tags":[
        "nonphysical",
        "commercial"
    ],
    "wof:name":"Linda Lux",
    "wof:placetype":"venue"
},
  "geometry": {"coordinates":[-78.68736800000001,35.874555],"type":"Point"}
}