{
  "type": "Feature",
  "properties": {
    "iso:country":"US",
    "sg:address":"12512 Peed Rd",
    "sg:city":"Raleigh",
    "sg:classifiers":[
        {
            "category":"Real Estate",
            "subcategory":"Real Estate Agent",
            "type":"Services"
        }
    ],
    "sg:phone":"+1 919 866 1550",
    "sg:postcode":"27614",
    "sg:province":"NC",
    "wof:name":"Remax Agency",
    "wof:placetype":"venue"
},
  "geometry": {"coordinates":[-78.677994,35.986332],"type":"Point"}
}