{
  "type": "Feature",
  "properties": {
    "iso:country":"US",
    "sg:address":"1903 Asheville Hwy",
    "sg:city":"Hendersonville",
    "sg:classifiers":[
        {
            "category":"Personal",
            "type":"Services"
        }
    ],
    "sg:phone":"+1   ",
    "sg:postcode":"28791",
    "sg:province":"NC",
    "wof:name":"California Emporium of Tattoos",
    "wof:placetype":"venue"
},
  "geometry": {"coordinates":[-82.472909,35.336638],"type":"Point"}
}