{
  "type": "Feature",
  "properties": {
    "addr:full":"1006 Main St Scotland Neck NC 27874",
    "addr:housenumber":"1006",
    "addr:postcode":"27874",
    "addr:street":"Main St",
    "iso:country":"US",
    "sg:address":"1006 Main St",
    "sg:city":"Scotland Neck",
    "sg:classifiers":[
        {
            "category":"Personal",
            "subcategory":"Beauty Salon",
            "type":"Services"
        }
    ],
    "sg:phone":"+1   ",
    "sg:postcode":"27874",
    "sg:province":"NC",
    "sg:tags":[
        "shop"
    ],
    "wof:name":"Beauty Nook",
    "wof:placetype":"venue"
},
  "geometry": {"coordinates":[-77.42208599999999,36.129838],"type":"Point"}
}