{
  "type": "Feature",
  "properties": {
    "iso:country":"US",
    "sg:address":"10605 Jordan Rd",
    "sg:city":"Raleigh",
    "sg:classifiers":[
        {
            "category":"Building & Trades",
            "subcategory":"Cleaning & Sanitation",
            "type":"Services"
        }
    ],
    "sg:phone":"+1 919 771 0792",
    "sg:postcode":"27603",
    "sg:province":"NC",
    "sg:tags":[
        "janitor"
    ],
    "wof:name":"Safety Kleen",
    "wof:placetype":"venue"
},
  "geometry": {"coordinates":[-78.620746,35.616123],"type":"Point"}
}