{
  "type": "Feature",
  "properties": {
    "addr:full":"3115 Rives Chapel Church Rd Siler City NC 27344",
    "addr:housenumber":"3115",
    "addr:postcode":"27344",
    "addr:street":"Rives Chapel Church Rd",
    "iso:country":"US",
    "sg:address":"3115 Rives Chapel Church Rd",
    "sg:city":"Siler City",
    "sg:classifiers":[
        {
            "category":"Retail",
            "subcategory":"Repair Shop",
            "type":"Services"
        }
    ],
    "sg:phone":"+1   ",
    "sg:postcode":"27344",
    "sg:province":"NC",
    "sg:tags":[
        "upholstery",
        "furniture"
    ],
    "wof:name":"Holts Upholstery & Furn Co",
    "wof:placetype":"venue"
},
  "geometry": {"coordinates":[-79.37488999999999,35.694512],"type":"Point"}
}