{
  "type": "Feature",
  "properties": {
    "addr:full":"4401 E Independence Blvd Charlotte NC 28205",
    "addr:housenumber":"4401",
    "addr:postcode":"28205",
    "addr:street":"E Independence Blvd",
    "iso:country":"US",
    "sg:address":"4401 E Independence Blvd",
    "sg:city":"Charlotte",
    "sg:classifiers":[
        {
            "category":"Banks & Credit Unions",
            "subcategory":"Bank",
            "type":"Services"
        }
    ],
    "sg:phone":"+1 704 567 8248",
    "sg:postcode":"28205",
    "sg:province":"NC",
    "sg:tags":[
        "loan"
    ],
    "wof:name":"Regional Finance",
    "wof:placetype":"venue"
},
  "geometry": {"coordinates":[-80.76975299999999,35.198588],"type":"Point"}
}