{
  "type": "Feature",
  "properties": {
    "addr:full":"269 S Hoskins Rd Charlotte NC 28208",
    "addr:housenumber":"269",
    "addr:postcode":"28208",
    "addr:street":"S Hoskins Rd",
    "iso:country":"US",
    "sg:address":"269 S Hoskins Rd",
    "sg:city":"Charlotte",
    "sg:classifiers":[
        {
            "category":"Personal",
            "subcategory":"Beauty Salon",
            "type":"Services"
        }
    ],
    "sg:phone":"+1   ",
    "sg:postcode":"28208",
    "sg:province":"NC",
    "sg:tags":[
        "shop"
    ],
    "wof:name":"Claudines Beauty Salon",
    "wof:placetype":"venue"
},
  "geometry": {"coordinates":[-80.887552,35.263401],"type":"Point"}
}