{
  "type": "Feature",
  "properties": {
    "iso:country":"US",
    "sg:address":"2302 Chapel Hill Rd",
    "sg:city":"Durham",
    "sg:classifiers":[
        {
            "category":"Personal",
            "subcategory":"Beauty Salon",
            "type":"Services"
        }
    ],
    "sg:phone":"+1 919 489 5052",
    "sg:postcode":"27707",
    "sg:province":"NC",
    "wof:name":"Muhsinah's House-Weave Beauty",
    "wof:placetype":"venue"
},
  "geometry": {"coordinates":[-78.93068,35.983227],"type":"Point"}
}