{
  "type": "Feature",
  "properties": {
    "iso:country":"US",
    "sg:address":"25 Wilmington Rd",
    "sg:city":"Asheville",
    "sg:classifiers":[
        {
            "category":"Building & Trades",
            "subcategory":"Landscaping Services",
            "type":"Services"
        }
    ],
    "sg:phone":"+1 828 274 0907",
    "sg:postcode":"28803",
    "sg:province":"NC",
    "wof:name":"Nickloy Janitorial & Lawn Serv",
    "wof:placetype":"venue"
},
  "geometry": {"coordinates":[-82.507366,35.56488],"type":"Point"}
}