{
  "type": "Feature",
  "properties": {
    "iso:country":"US",
    "sg:address":"305 Cokey Rd",
    "sg:city":"Rocky Mount",
    "sg:classifiers":[
        {
            "category":"Social Services",
            "type":"Services"
        }
    ],
    "sg:phone":"+1 252 977 2628",
    "sg:postcode":"27801",
    "sg:province":"NC",
    "wof:name":"Correction North Carolina Dept",
    "wof:placetype":"venue"
},
  "geometry": {"coordinates":[-77.79064099999999,35.935824],"type":"Point"}
}