{
  "type": "Feature",
  "properties": {
    "addr:full":"4600 Durham Chapel Hill Blvd Ste 12 Durham NC 27707",
    "addr:housenumber":"4600",
    "addr:postcode":"27707",
    "addr:street":"Durham Chapel Hill Blvd Ste 12",
    "iso:country":"US",
    "sg:address":"4600 Durham Chapel Hill Blvd Ste 12",
    "sg:city":"Durham",
    "sg:classifiers":[
        {
            "category":"Personal",
            "subcategory":"Nail Salon",
            "type":"Services"
        }
    ],
    "sg:phone":"+1 919 403 0086",
    "sg:postcode":"27707",
    "sg:province":"NC",
    "wof:name":"Lee & Nails",
    "wof:placetype":"venue"
},
  "geometry": {"coordinates":[-78.97342500000001,35.963593],"type":"Point"}
}