{
  "type": "Feature",
  "properties": {
    "iso:country":"US",
    "sg:address":"2018 Knell Dr",
    "sg:city":"Charlotte",
    "sg:classifiers":[
        {
            "category":"Retail",
            "subcategory":"Auto Rental",
            "type":"Services"
        }
    ],
    "sg:phone":"+1 704 537 7588",
    "sg:postcode":"28212",
    "sg:province":"NC",
    "sg:tags":[
        "truck"
    ],
    "wof:name":"Express Leasing Inc",
    "wof:placetype":"venue"
},
  "geometry": {"coordinates":[-80.76236400000001,35.176376],"type":"Point"}
}