{
  "type": "Feature",
  "properties": {
    "iso:country":"US",
    "sg:address":"14 Weather Hill Cir",
    "sg:city":"Durham",
    "sg:classifiers":[
        {
            "category":"Professional",
            "subcategory":"Computer Services",
            "type":"Services"
        }
    ],
    "sg:phone":"+1   ",
    "sg:postcode":"27705",
    "sg:province":"NC",
    "sg:tags":[
        "datum"
    ],
    "wof:name":"Triangle Web Design",
    "wof:placetype":"venue"
},
  "geometry": {"coordinates":[-78.932551,36.057011],"type":"Point"}
}