{
  "type": "Feature",
  "properties": {
    "addr:full":"2807 Wrightsville Ave Wilmington NC 28403",
    "addr:housenumber":"2807",
    "addr:postcode":"28403",
    "addr:street":"Wrightsville Ave",
    "iso:country":"US",
    "sg:address":"2807 Wrightsville Ave",
    "sg:city":"Wilmington",
    "sg:classifiers":[
        {
            "category":"Personal",
            "subcategory":"Beauty Salon",
            "type":"Services"
        }
    ],
    "sg:phone":"+1   ",
    "sg:postcode":"28403",
    "sg:province":"NC",
    "sg:tags":[
        "shop"
    ],
    "wof:name":"N Style",
    "wof:placetype":"venue"
},
  "geometry": {"coordinates":[-77.906682,34.225689],"type":"Point"}
}