{
  "type": "Feature",
  "properties": {
    "addr:full":"13 Park Ave Brevard SC 28712",
    "addr:housenumber":"13",
    "addr:postcode":"28712",
    "addr:street":"Park Ave",
    "iso:country":"US",
    "sg:address":"13 Park Ave",
    "sg:city":"Brevard",
    "sg:classifiers":[
        {
            "category":"Real Estate",
            "subcategory":"Real Estate Agent",
            "type":"Services"
        }
    ],
    "sg:phone":"+1 828 884 4455",
    "sg:postcode":"28712",
    "sg:province":"SC",
    "wof:name":"Alin Enterprises LLC",
    "wof:placetype":"venue"
},
  "geometry": {"coordinates":[-82.728033,35.229374],"type":"Point"}
}