{
  "type": "Feature",
  "properties": {
    "iso:country":"US",
    "sg:address":"49 N Main St",
    "sg:city":"Granite Falls",
    "sg:classifiers":[
        {
            "category":"Organizations",
            "subcategory":"Religious Organization",
            "type":"Services"
        }
    ],
    "sg:phone":"+1 828 396 5661",
    "sg:postcode":"28630",
    "sg:province":"NC",
    "sg:tags":[
        "church"
    ],
    "wof:name":"Rock Chapel Church Of God",
    "wof:placetype":"venue"
},
  "geometry": {"coordinates":[-81.435413,35.799726],"type":"Point"}
}