{
  "type": "Feature",
  "properties": {
    "iso:country":"US",
    "sg:address":"310 Jeffries Cove",
    "sg:city":"Rocky Mount",
    "sg:classifiers":[
        {
            "category":"Real Estate",
            "subcategory":"Real Estate Operator",
            "type":"Services"
        }
    ],
    "sg:phone":"+1 252 972 1988",
    "sg:postcode":"27804",
    "sg:province":"NC",
    "sg:tags":[
        "apartment"
    ],
    "wof:name":"Jeffries Cove Apartments",
    "wof:placetype":"venue"
},
  "geometry": {"coordinates":[-77.79208199999999,35.986837],"type":"Point"}
}