{
  "type": "Feature",
  "properties": {
    "iso:country":"US",
    "sg:address":"1816 Genesis Park Pl",
    "sg:city":"Charlotte",
    "sg:classifiers":[
        {
            "category":"Social Services",
            "subcategory":"Child Care",
            "type":"Services"
        }
    ],
    "sg:phone":"+1 704 342 3798",
    "sg:postcode":"28206",
    "sg:province":"NC",
    "wof:name":"Gods Happy Babies Home Daycare",
    "wof:placetype":"venue"
},
  "geometry": {"coordinates":[-80.84386600000001,35.250275],"type":"Point"}
}