{
  "type": "Feature",
  "properties": {
    "iso:country":"US",
    "sg:address":"503 Belwood Dr",
    "sg:city":"Belmont",
    "sg:classifiers":[
        {
            "category":"Building & Trades",
            "subcategory":"Construction",
            "type":"Services"
        }
    ],
    "sg:phone":"+1 704 825 5579",
    "sg:postcode":"28012",
    "sg:province":"NC",
    "sg:tags":[
        "residential"
    ],
    "wof:name":"G2 Construction Co LLC",
    "wof:placetype":"venue"
},
  "geometry": {"coordinates":[-81.01978800000001,35.221556],"type":"Point"}
}