{
  "type": "Feature",
  "properties": {
    "addr:full":"1299 N Brightleaf Blvd Smithfield NC 27577",
    "addr:housenumber":"1299",
    "addr:postcode":"27577",
    "addr:street":"N Brightleaf Blvd",
    "iso:country":"US",
    "sg:address":"1299 N Brightleaf Blvd",
    "sg:city":"Smithfield",
    "sg:classifiers":[
        {
            "category":"Personal",
            "subcategory":"Beauty Salon",
            "type":"Services"
        }
    ],
    "sg:phone":"+1 919 934 8830",
    "sg:postcode":"27577",
    "sg:province":"NC",
    "wof:name":"Smart Style Family Hair Salon",
    "wof:placetype":"venue"
},
  "geometry": {"coordinates":[-78.308312,35.520688],"type":"Point"}
}