{
  "type": "Feature",
  "properties": {
    "addr:full":"1400 Nassau Blvd Charlotte NC 28205",
    "addr:housenumber":"1400",
    "addr:postcode":"28205",
    "addr:street":"Nassau Blvd",
    "iso:country":"US",
    "sg:address":"1400 Nassau Blvd",
    "sg:city":"Charlotte",
    "sg:classifiers":[
        {
            "category":"Personal",
            "subcategory":"Barber",
            "type":"Services"
        }
    ],
    "sg:phone":"+1   ",
    "sg:postcode":"28205",
    "sg:province":"NC",
    "sg:tags":[
        "shop"
    ],
    "wof:name":"Amy Barber",
    "wof:placetype":"venue"
},
  "geometry": {"coordinates":[-80.808775,35.222232],"type":"Point"}
}