{
  "type": "Feature",
  "properties": {
    "addr:full":"2408 Central Ave Charlotte NC 28205",
    "addr:housenumber":"2408",
    "addr:postcode":"28205",
    "addr:street":"Central Ave",
    "iso:country":"US",
    "sg:address":"2408 Central Ave",
    "sg:city":"Charlotte",
    "sg:classifiers":[
        {
            "category":"Professional",
            "subcategory":"Accounting & Tax Preparation",
            "type":"Services"
        },
        {
            "category":"Banks & Credit Unions",
            "subcategory":"Financial Services",
            "type":"Services"
        }
    ],
    "sg:phone":"+1 704 375 1875",
    "sg:postcode":"28205",
    "sg:province":"NC",
    "sg:tags":[
        "return",
        "preparation-business",
        "taxes-consultants",
        "loan",
        "representative",
        "alternative",
        "bookkeeping"
    ],
    "sg:website":"http://www.hrblock.com",
    "wof:name":"H & R Block",
    "wof:placetype":"venue"
},
  "geometry": {"coordinates":[-80.801575,35.219518],"type":"Point"}
}