{
  "type": "Feature",
  "properties": {
    "iso:country":"US",
    "sg:address":"2300 N Heritage St",
    "sg:city":"Kinston",
    "sg:classifiers":[
        {
            "category":"Shopping",
            "subcategory":"Optical Goods",
            "type":"Retail Goods"
        }
    ],
    "sg:phone":"+1 252 527 1110",
    "sg:postcode":"28501",
    "sg:province":"NC",
    "sg:tags":[
        "optician"
    ],
    "wof:name":"Salter Eye Assoc",
    "wof:placetype":"venue"
},
  "geometry": {"coordinates":[-77.589405,35.284793],"type":"Point"}
}