{
  "type": "Feature",
  "properties": {
    "addr:full":"500 Industry Dr Henderson NC 27537",
    "addr:housenumber":"500",
    "addr:postcode":"27537",
    "addr:street":"Industry Dr",
    "iso:country":"US",
    "sg:address":"500 Industry Dr",
    "sg:city":"Henderson",
    "sg:classifiers":[
        {
            "category":"Home & Garden",
            "subcategory":"Household Appliances",
            "type":"Retail Goods"
        }
    ],
    "sg:phone":"+1 252 431 3407",
    "sg:postcode":"27537",
    "sg:province":"NC",
    "wof:name":"PSNC Energy",
    "wof:placetype":"venue"
},
  "geometry": {"coordinates":[-78.439307,36.347495],"type":"Point"}
}