{
  "type": "Feature",
  "properties": {
    "addr:full":"3100 Duraleigh Rd Ste 309 Raleigh NC 27612",
    "addr:postcode":"3100;27612",
    "addr:street":"Duraleigh Rd Ste 309",
    "iso:country":"US",
    "sg:address":"3100 Duraleigh Rd Ste 309",
    "sg:city":"Raleigh",
    "sg:classifiers":[
        {
            "category":"Health Services",
            "subcategory":"Doctor",
            "type":"Services"
        }
    ],
    "sg:phone":"+1 919 787 1644",
    "sg:postcode":"27612",
    "sg:province":"NC",
    "wof:name":"Miller Juliana Gastroenterology",
    "wof:placetype":"venue"
},
  "geometry": {"coordinates":[-78.70553,35.822659],"type":"Point"}
}