{
  "type": "Feature",
  "properties": {
    "addr:full":"8609 Six Forks Rd Raleigh NC 27615",
    "addr:housenumber":"8609",
    "addr:postcode":"27615",
    "addr:street":"Six Forks Rd",
    "iso:country":"US",
    "sg:address":"8609 Six Forks Rd",
    "sg:city":"Raleigh",
    "sg:classifiers":[
        {
            "category":"Manufacturing",
            "subcategory":"Electronics",
            "type":"Manufacturing & Wholesale Goods"
        }
    ],
    "sg:phone":"+1 919 870 3354",
    "sg:postcode":"27615",
    "sg:province":"NC",
    "sg:tags":[
        "manufacture",
        "electronic",
        "power",
        "supply"
    ],
    "wof:name":"Lambda Holdings Inc",
    "wof:placetype":"venue"
},
  "geometry": {"coordinates":[-78.65024,35.89709],"type":"Point"}
}