{
  "type": "Feature",
  "properties": {
    "addr:full":"881 Lizard Creek Rd Henrico NC 27842",
    "addr:housenumber":"881",
    "addr:postcode":"27842",
    "addr:street":"Lizard Creek Rd",
    "iso:country":"US",
    "sg:address":"881 Lizard Creek Rd",
    "sg:city":"Henrico",
    "sg:classifiers":[
        {
            "category":"Autos & Motor Vehicles",
            "subcategory":"Automobile Sales",
            "type":"Retail Goods"
        }
    ],
    "sg:phone":"+1 252 586 2600",
    "sg:postcode":"27842",
    "sg:province":"NC",
    "sg:tags":[
        "used"
    ],
    "wof:name":"Auto Lane Inc",
    "wof:placetype":"venue"
},
  "geometry": {"coordinates":[-77.901552,36.533189],"type":"Point"}
}