{
  "type": "Feature",
  "properties": {
    "iso:country":"US",
    "sg:address":"803 Pine Ridge St",
    "sg:city":"Sanford",
    "sg:classifiers":[
        {
            "category":"Building & Trades",
            "subcategory":"Pest Control",
            "type":"Services"
        }
    ],
    "sg:phone":"+1   ",
    "sg:postcode":"27330",
    "sg:province":"NC",
    "wof:name":"Headens Pressure Washing",
    "wof:placetype":"venue"
},
  "geometry": {"coordinates":[-79.167648,35.461463],"type":"Point"}
}