{
  "type": "Feature",
  "properties": {
    "iso:country":"US",
    "sg:address":"6458 State Hwy 55",
    "sg:city":"New Bern",
    "sg:classifiers":[
        {
            "category":"Social Services",
            "subcategory":"Child Care",
            "type":"Services"
        }
    ],
    "sg:phone":"+1 252 745 4153",
    "sg:postcode":"28560",
    "sg:province":"NC",
    "wof:name":"Reelsboro Christian Day Care",
    "wof:placetype":"venue"
},
  "geometry": {"coordinates":[-76.889059,35.136284],"type":"Point"}
}