{
  "type": "Feature",
  "properties": {
    "iso:country":"US",
    "sg:address":"606 N Main St",
    "sg:city":"Rolesville",
    "sg:classifiers":[
        {
            "category":"Wholesale",
            "subcategory":"Farm Supplies",
            "type":"Manufacturing & Wholesale Goods"
        }
    ],
    "sg:phone":"+1 919 556 0146",
    "sg:postcode":"27571",
    "sg:province":"NC",
    "sg:tags":[
        "bulb",
        "seed"
    ],
    "wof:name":"Pure Seed Testing",
    "wof:placetype":"venue"
},
  "geometry": {"coordinates":[-78.441805,35.932475],"type":"Point"}
}