{
  "type": "Feature",
  "properties": {
    "iso:country":"US",
    "sg:address":"2541 E Main St",
    "sg:city":"Lincolnton",
    "sg:classifiers":[
        {
            "category":"Personal",
            "subcategory":"Beauty Salon",
            "type":"Services"
        }
    ],
    "sg:phone":"+1   ",
    "sg:postcode":"28092",
    "sg:province":"NC",
    "sg:tags":[
        "shop"
    ],
    "wof:name":"Ke Cache Beauty Salon",
    "wof:placetype":"venue"
},
  "geometry": {"coordinates":[-81.209541,35.480819],"type":"Point"}
}