{
  "type": "Feature",
  "properties": {
    "iso:country":"US",
    "sg:address":"169 Locust St",
    "sg:city":"Spruce Pine",
    "sg:classifiers":[
        {
            "category":"Shopping",
            "subcategory":"Gifts & Souvenirs",
            "type":"Retail Goods"
        }
    ],
    "sg:phone":"+1 828 765 4115",
    "sg:postcode":"28777",
    "sg:province":"NC",
    "sg:tags":[
        "shop"
    ],
    "wof:name":"Crystal Goose",
    "wof:placetype":"venue"
},
  "geometry": {"coordinates":[-82.069855,35.91601],"type":"Point"}
}