{
  "type": "Feature",
  "properties": {
    "addr:full":"1114 Barkley Rd Statesville NC 28677",
    "addr:housenumber":"1114",
    "addr:postcode":"28677",
    "addr:street":"Barkley Rd",
    "iso:country":"US",
    "sg:address":"1114 Barkley Rd",
    "sg:city":"Statesville",
    "sg:classifiers":[
        {
            "category":"Building & Trades",
            "subcategory":"Construction",
            "type":"Services"
        }
    ],
    "sg:phone":"+1 704 873 9180",
    "sg:postcode":"28677",
    "sg:province":"NC",
    "sg:tags":[
        "home",
        "improvement"
    ],
    "wof:name":"Michael L Le Van Building",
    "wof:placetype":"venue"
},
  "geometry": {"coordinates":[-80.860964,35.75922],"type":"Point"}
}