{
  "type": "Feature",
  "properties": {
    "addr:full":"322 Popular Spring Rd Roaring River NC 28669",
    "addr:housenumber":"322",
    "addr:postcode":"28669",
    "addr:street":"Popular Spring Rd",
    "iso:country":"US",
    "sg:address":"322 Popular Spring Rd",
    "sg:city":"Roaring River",
    "sg:classifiers":[
        {
            "category":"Insurance",
            "subcategory":"Insurance Agent",
            "type":"Services"
        }
    ],
    "sg:phone":"+1 336 957 4253",
    "sg:postcode":"28669",
    "sg:province":"NC",
    "wof:name":"Humana",
    "wof:placetype":"venue"
},
  "geometry": {"coordinates":[-80.983841,36.231841],"type":"Point"}
}