{
  "type": "Feature",
  "properties": {
    "addr:full":"412 V-8 St Kannapolis NC 28083",
    "addr:housenumber":"412",
    "addr:postcode":"28083",
    "addr:street":"V-8 St",
    "iso:country":"US",
    "sg:address":"412 V-8 St",
    "sg:city":"Kannapolis",
    "sg:classifiers":[
        {
            "category":"Building & Trades",
            "subcategory":"Construction",
            "type":"Services"
        },
        {
            "category":"Travel",
            "subcategory":"Travel Agent",
            "type":"Entertainment"
        }
    ],
    "sg:phone":"+1 704 938 8687",
    "sg:postcode":"28083",
    "sg:province":"NC",
    "sg:tags":[
        "agency",
        "bureau",
        "contractor"
    ],
    "wof:name":"Pleasure Seekers Travel Inc",
    "wof:placetype":"venue"
},
  "geometry": {"coordinates":[-80.614634,35.478133],"type":"Point"}
}