{
  "type": "Feature",
  "properties": {
    "iso:country":"US",
    "sg:address":"2949 Hodges Farm Rd",
    "sg:city":"La Grange",
    "sg:classifiers":[
        {
            "category":"Government",
            "subcategory":"Office",
            "type":"Public Place"
        }
    ],
    "sg:phone":"+1 252 566 5408",
    "sg:postcode":"28551",
    "sg:province":"NC",
    "sg:tags":[
        "county",
        "program"
    ],
    "wof:name":"Lenoir County Solid Waste Dept",
    "wof:placetype":"venue"
},
  "geometry": {"coordinates":[-77.715992,35.295052],"type":"Point"}
}