{
  "type": "Feature",
  "properties": {
    "addr:full":"247 N Main St Weaverville NC 28787",
    "addr:housenumber":"247",
    "addr:postcode":"28787",
    "addr:street":"N Main St",
    "iso:country":"US",
    "sg:address":"247 N Main St",
    "sg:city":"Weaverville",
    "sg:classifiers":[
        {
            "category":"Restaurant",
            "type":"Food & Drink"
        }
    ],
    "sg:phone":"+1 828 645 8458",
    "sg:postcode":"28787",
    "sg:province":"NC",
    "wof:name":"Athens Restaurant",
    "wof:placetype":"venue"
},
  "geometry": {"coordinates":[-82.56053199999999,35.707684],"type":"Point"}
}