{
  "type": "Feature",
  "properties": {
    "iso:country":"US",
    "sg:address":"6325 Olde Fox Hint Ln",
    "sg:city":"Charlotte",
    "sg:classifiers":[
        {
            "category":"Building & Trades",
            "subcategory":"Construction",
            "type":"Services"
        }
    ],
    "sg:phone":"+1 704 573 3828",
    "sg:postcode":"28227",
    "sg:province":"NC",
    "sg:tags":[
        "contractor"
    ],
    "wof:name":"Metrolina Wallboard",
    "wof:placetype":"venue"
},
  "geometry": {"coordinates":[-80.673873,35.16948],"type":"Point"}
}