{
  "type": "Feature",
  "properties": {
    "addr:full":"605 Guy Walker Way Durham NC 27703",
    "addr:housenumber":"605",
    "addr:postcode":"27703",
    "addr:street":"Guy Walker Way",
    "iso:country":"US",
    "sg:address":"605 Guy Walker Way",
    "sg:city":"Durham",
    "sg:classifiers":[
        {
            "category":"Professional",
            "subcategory":"Engineering",
            "type":"Services"
        }
    ],
    "sg:phone":"+1 919 598 9964",
    "sg:postcode":"27703",
    "sg:province":"NC",
    "sg:tags":[
        "engineer"
    ],
    "sg:website":"www.griffin-engineering.com",
    "wof:name":"Griffin Engineering & Technica",
    "wof:placetype":"venue"
},
  "geometry": {"coordinates":[-78.811154,35.96958],"type":"Point"}
}