{
  "type": "Feature",
  "properties": {
    "iso:country":"US",
    "sg:address":"128 Salem Towne Ct",
    "sg:city":"Apex",
    "sg:classifiers":[
        {
            "category":"Health Services",
            "subcategory":"Health Practitioner",
            "type":"Services"
        }
    ],
    "sg:phone":"+1   ",
    "sg:postcode":"27502",
    "sg:province":"NC",
    "wof:name":"Bilingual Therapeutic Resource",
    "wof:placetype":"venue"
},
  "geometry": {"coordinates":[-78.849513,35.738672],"type":"Point"}
}