{
  "type": "Feature",
  "properties": {
    "iso:country":"US",
    "sg:address":"511 Harpers Ln",
    "sg:city":"Jacksonville",
    "sg:classifiers":[
        {
            "category":"Retail",
            "subcategory":"Repair Shop",
            "type":"Services"
        }
    ],
    "sg:phone":"+1   ",
    "sg:postcode":"28540",
    "sg:province":"NC",
    "sg:tags":[
        "refrigeration"
    ],
    "wof:name":"Capps Refrigeration",
    "wof:placetype":"venue"
},
  "geometry": {"coordinates":[-77.477312,34.673839],"type":"Point"}
}