{
  "type": "Feature",
  "properties": {
    "iso:country":"US",
    "sg:address":"375 Depot St",
    "sg:city":"Asheville",
    "sg:classifiers":[
        {
            "category":"Professional",
            "subcategory":"Advertising",
            "type":"Services"
        }
    ],
    "sg:phone":"+1   ",
    "sg:postcode":"28801",
    "sg:province":"NC",
    "sg:tags":[
        "agency"
    ],
    "wof:name":"Ditez Design Inc",
    "wof:placetype":"venue"
},
  "geometry": {"coordinates":[-82.564419,35.580601],"type":"Point"}
}