{
  "type": "Feature",
  "properties": {
    "iso:country":"US",
    "sg:address":"1162 Cagle Loop Rd",
    "sg:city":"Seagrove",
    "sg:classifiers":[
        {
            "category":"Home & Garden",
            "subcategory":"Home Furnishings",
            "type":"Retail Goods"
        }
    ],
    "sg:phone":"+1 336 873 8463",
    "sg:postcode":"27341",
    "sg:province":"NC",
    "wof:name":"Dixieland Pottery",
    "wof:placetype":"venue"
},
  "geometry": {"coordinates":[-79.749662,35.531815],"type":"Point"}
}