{
  "type": "Feature",
  "properties": {
    "addr:full":"732 Nash Dr Raleigh NC 27608",
    "addr:housenumber":"732",
    "addr:postcode":"27608",
    "addr:street":"Nash Dr",
    "iso:country":"US",
    "sg:address":"732 Nash Dr",
    "sg:city":"Raleigh",
    "sg:classifiers":[
        {
            "category":"Communications",
            "subcategory":"Film & Video Production",
            "type":"Services"
        }
    ],
    "sg:phone":"+1 919 839 8428",
    "sg:postcode":"27608",
    "sg:province":"NC",
    "sg:tags":[
        "taping"
    ],
    "wof:name":"Warren Gentry & Assoc",
    "wof:placetype":"venue"
},
  "geometry": {"coordinates":[-78.64554200000001,35.798795],"type":"Point"}
}