{
  "type": "Feature",
  "properties": {
    "addr:full":"124 Samaritans Ridge Rd Elkin NC 28621",
    "addr:housenumber":"124",
    "addr:postcode":"28621",
    "addr:street":"Samaritans Ridge Rd",
    "iso:country":"US",
    "sg:address":"124 Samaritans Ridge Rd",
    "sg:city":"Elkin",
    "sg:classifiers":[
        {
            "category":"Health Services",
            "subcategory":"Doctor",
            "type":"Services"
        },
        {
            "category":"Health Services",
            "subcategory":"Hospital",
            "type":"Services"
        }
    ],
    "sg:phone":"+1 336 835 7700",
    "sg:postcode":"28621",
    "sg:province":"NC",
    "sg:tags":[
        "physician",
        "pediatrics-emergency",
        "pediatrics",
        "surgeons",
        "internal",
        "medicine",
        "surgeon"
    ],
    "wof:name":"Elkin Pediatric Adult Medicine",
    "wof:placetype":"venue"
},
  "geometry": {"coordinates":[-80.829487,36.261839],"type":"Point"}
}