{
  "type": "Feature",
  "properties": {
    "iso:country":"US",
    "sg:address":"200 Innovation Ave",
    "sg:city":"Morrisville",
    "sg:classifiers":[
        {
            "category":"Wholesale",
            "subcategory":"Electrical",
            "type":"Manufacturing & Wholesale Goods"
        }
    ],
    "sg:phone":"+1 919 484 8500",
    "sg:postcode":"27560",
    "sg:province":"NC",
    "sg:tags":[
        "wire",
        "cable"
    ],
    "sg:website":"www.accu-tech.com",
    "wof:name":"Accu-Tech Corp",
    "wof:placetype":"venue"
},
  "geometry": {"coordinates":[-78.818973,35.869217],"type":"Point"}
}