{
  "type": "Feature",
  "properties": {
    "addr:full":"918 W Mountain Dr Fayetteville NC 28306",
    "addr:housenumber":"918",
    "addr:postcode":"28306",
    "addr:street":"W Mountain Dr",
    "iso:country":"US",
    "sg:address":"918 W Mountain Dr",
    "sg:city":"Fayetteville",
    "sg:classifiers":[
        {
            "category":"Retail",
            "subcategory":"Repair Shop",
            "type":"Services"
        }
    ],
    "sg:phone":"+1   ",
    "sg:postcode":"28306",
    "sg:province":"NC",
    "wof:name":"T & T Upholstery Shop",
    "wof:placetype":"venue"
},
  "geometry": {"coordinates":[-78.91630499999999,35.018178],"type":"Point"}
}