{
  "type": "Feature",
  "properties": {
    "iso:country":"US",
    "sg:address":"217 S Main St",
    "sg:city":"Robbinsville",
    "sg:classifiers":[
        {
            "category":"Health Services",
            "subcategory":"Hospital",
            "type":"Services"
        }
    ],
    "sg:phone":"+1 828 479 6466",
    "sg:postcode":"28771",
    "sg:province":"NC",
    "sg:tags":[
        "mental"
    ],
    "wof:name":"Smoky Mountain Ctr For Mental",
    "wof:placetype":"venue"
},
  "geometry": {"coordinates":[-83.80659799999999,35.319632],"type":"Point"}
}