{
  "type": "Feature",
  "properties": {
    "iso:country":"US",
    "sg:address":"1950 Hendersonville Rd",
    "sg:city":"Asheville",
    "sg:classifiers":[
        {
            "category":"Shopping",
            "subcategory":"Clothing, Apparel, & Fashions",
            "type":"Retail Goods"
        }
    ],
    "sg:phone":"+1 828 687 7200",
    "sg:postcode":"28803",
    "sg:province":"NC",
    "sg:tags":[
        "baby",
        "accessory"
    ],
    "sg:website":"www.bonbebe.com",
    "wof:name":"Bon Bebe",
    "wof:placetype":"venue"
},
  "geometry": {"coordinates":[-82.522569,35.492046],"type":"Point"}
}