{
  "type": "Feature",
  "properties": {
    "addr:full":"36 Churchwell Ct Durham NC 27713",
    "addr:housenumber":"36",
    "addr:postcode":"27713",
    "addr:street":"Churchwell Ct",
    "iso:country":"US",
    "sg:address":"36 Churchwell Ct",
    "sg:city":"Durham",
    "sg:classifiers":[
        {
            "category":"Professional",
            "subcategory":"Engineering",
            "type":"Services"
        }
    ],
    "sg:phone":"+1 919 544 1159",
    "sg:postcode":"27713",
    "sg:province":"NC",
    "sg:tags":[
        "engineer"
    ],
    "wof:name":"Brunssen Engineering Services",
    "wof:placetype":"venue"
},
  "geometry": {"coordinates":[-78.947517,35.913875],"type":"Point"}
}