{
  "type": "Feature",
  "properties": {
    "addr:full":"6106 State Hwy 306 Grantsboro NC 28529",
    "addr:housenumber":"6106",
    "addr:postcode":"28529",
    "addr:street":"State Hwy 306",
    "iso:country":"US",
    "sg:address":"6106 State Hwy 306",
    "sg:city":"Grantsboro",
    "sg:classifiers":[
        {
            "category":"Freight",
            "type":"Transportation"
        }
    ],
    "sg:phone":"+1 252 670 1176",
    "sg:postcode":"28529",
    "sg:province":"NC",
    "sg:tags":[
        "commercial",
        "storage"
    ],
    "wof:name":"Williams Storage",
    "wof:placetype":"venue"
},
  "geometry": {"coordinates":[-76.835936,35.083179],"type":"Point"}
}