{
  "type": "Feature",
  "properties": {
    "addr:full":"148 S Bridge St Elkin NC 28621",
    "addr:housenumber":"148",
    "addr:postcode":"28621",
    "addr:street":"S Bridge St",
    "iso:country":"US",
    "sg:address":"148 S Bridge St",
    "sg:city":"Elkin",
    "sg:classifiers":[
        {
            "category":"Building & Trades",
            "subcategory":"Electrical",
            "type":"Services"
        }
    ],
    "sg:phone":"+1 336 835 3112",
    "sg:postcode":"28621",
    "sg:province":"NC",
    "sg:tags":[
        "electrical",
        "contractor"
    ],
    "wof:name":"Crossroads Electric",
    "wof:placetype":"venue"
},
  "geometry": {"coordinates":[-80.850038,36.242591],"type":"Point"}
}