{
  "type": "Feature",
  "properties": {
    "iso:country":"US",
    "sg:address":"611 Forest Brook Dr",
    "sg:city":"Greensboro",
    "sg:classifiers":[
        {
            "category":"Building & Trades",
            "subcategory":"Construction",
            "type":"Services"
        }
    ],
    "sg:phone":"+1 336 987 1717",
    "sg:postcode":"27406",
    "sg:province":"NC",
    "sg:tags":[
        "resurfacing",
        "laying",
        "refinishing",
        "floor"
    ],
    "wof:name":"Funderburk Floor Coverings Svc",
    "wof:placetype":"venue"
},
  "geometry": {"coordinates":[-79.80427400000001,36.047275],"type":"Point"}
}