{
  "type": "Feature",
  "properties": {
    "iso:country":"US",
    "sg:address":"710 Teachers Dr",
    "sg:city":"Fayetteville",
    "sg:classifiers":[
        {
            "category":"Retail",
            "subcategory":"Auto Repair",
            "type":"Services"
        }
    ],
    "sg:phone":"+1 910 483 5975",
    "sg:postcode":"28301",
    "sg:province":"NC",
    "sg:tags":[
        "general"
    ],
    "wof:name":"Als Truck Service Inc",
    "wof:placetype":"venue"
},
  "geometry": {"coordinates":[-78.867777,35.038576],"type":"Point"}
}