{
  "type": "Feature",
  "properties": {
    "addr:full":"320 NE Center St Faison NC 28365",
    "addr:housenumber":"320",
    "addr:postcode":"28365",
    "addr:street":"Ne Center St",
    "iso:country":"US",
    "sg:address":"320 NE Center St",
    "sg:city":"Faison",
    "sg:classifiers":[
        {
            "category":"Restaurant",
            "type":"Food & Drink"
        }
    ],
    "sg:phone":"+1 910 267 6527",
    "sg:postcode":"28365",
    "sg:province":"NC",
    "wof:name":"Andy's Cheesesteaks",
    "wof:placetype":"venue"
},
  "geometry": {"coordinates":[-78.064453,35.198114],"type":"Point"}
}