{
  "type": "Feature",
  "properties": {
    "addr:full":"428 N Laurel Ave Charlotte NC 28204",
    "addr:housenumber":"428",
    "addr:postcode":"28204",
    "addr:street":"N Laurel Ave",
    "iso:country":"US",
    "sg:address":"428 N Laurel Ave",
    "sg:city":"Charlotte",
    "sg:classifiers":[
        {
            "category":"Food & Beverages",
            "subcategory":"Bakery",
            "type":"Retail Goods"
        }
    ],
    "sg:phone":"+1 704 332 4675",
    "sg:postcode":"28204",
    "sg:province":"NC",
    "wof:name":"Evelyn Lewis Family Parnte",
    "wof:placetype":"venue"
},
  "geometry": {"coordinates":[-80.81447199999999,35.20986],"type":"Point"}
}