{
  "type": "Feature",
  "properties": {
    "addr:full":"117 Hallbrook Farms Cir Wilmington NC 28411",
    "addr:housenumber":"117",
    "addr:postcode":"28411",
    "addr:street":"Hallbrook Farms Cir",
    "iso:country":"US",
    "sg:address":"117 Hallbrook Farms Cir",
    "sg:city":"Wilmington",
    "sg:classifiers":[
        {
            "category":"Real Estate",
            "subcategory":"Architect",
            "type":"Services"
        }
    ],
    "sg:phone":"+1 910 681 3677",
    "sg:postcode":"28411",
    "sg:province":"NC",
    "sg:tags":[
        "building",
        "construction"
    ],
    "wof:name":"GME",
    "wof:placetype":"venue"
},
  "geometry": {"coordinates":[-77.765468,34.299013],"type":"Point"}
}