{
  "type": "Feature",
  "properties": {
    "iso:country":"US",
    "sg:address":"200 W Franklin St",
    "sg:city":"Chapel Hill",
    "sg:classifiers":[
        {
            "category":"Professional",
            "subcategory":"Lawyer & Legal Services",
            "type":"Services"
        }
    ],
    "sg:phone":"+1 919 967 1450",
    "sg:postcode":"27516",
    "sg:province":"NC",
    "sg:tags":[
        "attorney"
    ],
    "sg:website":"www.southernenvironment.org",
    "wof:name":"Southern Environmental Law Ctr",
    "wof:placetype":"venue"
},
  "geometry": {"coordinates":[-79.057289,35.912583],"type":"Point"}
}