{
  "type": "Feature",
  "properties": {
    "addr:full":"5915 Yadkin Rd Fayetteville NC 28303",
    "addr:housenumber":"5915",
    "addr:postcode":"28303",
    "addr:street":"Yadkin Rd",
    "iso:country":"US",
    "sg:address":"5915 Yadkin Rd",
    "sg:city":"Fayetteville",
    "sg:classifiers":[
        {
            "category":"Restaurant",
            "type":"Food & Drink"
        }
    ],
    "sg:menulink":"http://www.allmenus.com/nc/seventy-first/200659-long-john-silvers/menu/",
    "sg:phone":"+1 910 868 5729",
    "sg:postcode":"28303",
    "sg:province":"NC",
    "sg:tags":[
        "seafood",
        "american"
    ],
    "wof:name":"Long John Silver's",
    "wof:placetype":"venue"
},
  "geometry": {"coordinates":[-78.987092,35.094277],"type":"Point"}
}