{
  "type": "Feature",
  "properties": {
    "iso:country":"US",
    "sg:address":"202 Mason Ln",
    "sg:city":"Beaufort",
    "sg:classifiers":[
        {
            "category":"Real Estate",
            "subcategory":"Real Estate Agent",
            "type":"Services"
        }
    ],
    "sg:phone":"+1 252 728 1578",
    "sg:postcode":"28516",
    "sg:province":"NC",
    "wof:name":"Mason Properties",
    "wof:placetype":"venue"
},
  "geometry": {"coordinates":[-76.64907700000001,34.728996],"type":"Point"}
}