{
  "type": "Feature",
  "properties": {
    "iso:country":"US",
    "sg:address":"407 Fayetteville St",
    "sg:city":"Newton Grove",
    "sg:classifiers":[
        {
            "category":"Home & Garden",
            "subcategory":"Building Materials",
            "type":"Retail Goods"
        }
    ],
    "sg:phone":"+1 910 594 0300",
    "sg:postcode":"28366",
    "sg:province":"NC",
    "wof:name":"Newton Grove Building Supply",
    "wof:placetype":"venue"
},
  "geometry": {"coordinates":[-78.35656400000001,35.244243],"type":"Point"}
}