{
  "type": "Feature",
  "properties": {
    "iso:country":"US",
    "sg:address":"921 W Broad St",
    "sg:city":"St Pauls",
    "sg:classifiers":[
        {
            "category":"Food & Beverages",
            "subcategory":"Groceries & Convenience Stores",
            "type":"Retail Goods"
        }
    ],
    "sg:phone":"+1 910 865 2747",
    "sg:postcode":"28384",
    "sg:province":"NC",
    "wof:name":"Kangaroo Express",
    "wof:placetype":"venue"
},
  "geometry": {"coordinates":[-78.984055,34.80934],"type":"Point"}
}