{
  "type": "Feature",
  "properties": {
    "iso:country":"US",
    "sg:address":"2727 Salisbury Hwy",
    "sg:city":"Statesville",
    "sg:classifiers":[
        {
            "category":"Manufacturing",
            "subcategory":"Chemicals & Compounds",
            "type":"Manufacturing & Wholesale Goods"
        }
    ],
    "sg:phone":"+1 704 878 8681",
    "sg:postcode":"28677",
    "sg:province":"NC",
    "sg:tags":[
        "fiber",
        "mfg"
    ],
    "wof:name":"Montgomery Industries Inc",
    "wof:placetype":"venue"
},
  "geometry": {"coordinates":[-80.788747,35.75855],"type":"Point"}
}