{
  "type": "Feature",
  "properties": {
    "addr:full":"324 Wilkesboro Ave North Wilkesboro NC 28659",
    "addr:housenumber":"324",
    "addr:postcode":"28659",
    "addr:street":"Wilkesboro Ave",
    "iso:country":"US",
    "sg:address":"324 Wilkesboro Ave",
    "sg:city":"North Wilkesboro",
    "sg:classifiers":[
        {
            "category":"Freight",
            "type":"Transportation"
        }
    ],
    "sg:phone":"+1 336 838 9989",
    "sg:postcode":"28659",
    "sg:province":"NC",
    "sg:tags":[
        "commercial",
        "storage"
    ],
    "wof:name":"Brickyard Rd Self Storage Unit",
    "wof:placetype":"venue"
},
  "geometry": {"coordinates":[-81.14614899999999,36.154803],"type":"Point"}
}