{
  "type": "Feature",
  "properties": {
    "iso:country":"US",
    "sg:address":"220 Hill St NE",
    "sg:city":"Wilson",
    "sg:classifiers":[
        {
            "category":"Building & Trades",
            "subcategory":"Construction",
            "type":"Services"
        }
    ],
    "sg:phone":"+1 252 291 5376",
    "sg:postcode":"27893",
    "sg:province":"NC",
    "sg:tags":[
        "home",
        "improvement"
    ],
    "wof:name":"Quality Home Improvements",
    "wof:placetype":"venue"
},
  "geometry": {"coordinates":[-77.911693,35.730222],"type":"Point"}
}