{
  "type": "Feature",
  "properties": {
    "addr:full":"5563 Western Blvd Unit 2 Raleigh NC 27606",
    "addr:housenumber":"5563",
    "addr:postcode":"27606",
    "addr:street":"Western Blvd Unit",
    "iso:country":"US",
    "sg:address":"5563 Western Blvd Unit 2",
    "sg:city":"Raleigh",
    "sg:classifiers":[
        {
            "category":"Sports & Exercise",
            "subcategory":"Gym",
            "type":"Entertainment"
        }
    ],
    "sg:phone":"+1 919 852 0008",
    "sg:postcode":"27606",
    "sg:province":"NC",
    "sg:website":"www.planetfitness.com",
    "wof:name":"Planet Fitness",
    "wof:placetype":"venue"
},
  "geometry": {"coordinates":[-78.721141,35.785186],"type":"Point"}
}