{
  "type": "Feature",
  "properties": {
    "addr:full":"113 Oakland Ave Leland NC 28451",
    "addr:housenumber":"113",
    "addr:postcode":"28451",
    "addr:street":"Oakland Ave",
    "iso:country":"US",
    "sg:address":"113 Oakland Ave",
    "sg:city":"Leland",
    "sg:classifiers":[
        {
            "category":"Local Transit",
            "type":"Transportation"
        }
    ],
    "sg:phone":"+1 910 297 4812",
    "sg:postcode":"28451",
    "sg:province":"NC",
    "sg:tags":[
        "passenger"
    ],
    "wof:name":"Madina Taxi",
    "wof:placetype":"venue"
},
  "geometry": {"coordinates":[-78.005014,34.238645],"type":"Point"}
}