{
  "type": "Feature",
  "properties": {
    "iso:country":"US",
    "sg:address":"910 Donita Dr",
    "sg:city":"Lincolnton",
    "sg:classifiers":[
        {
            "category":"Health Services",
            "subcategory":"Doctor",
            "type":"Services"
        }
    ],
    "sg:phone":"+1 704 735 3014",
    "sg:postcode":"28092",
    "sg:province":"NC",
    "sg:tags":[
        "dentist"
    ],
    "wof:name":"Cloninger Robert T Dr",
    "wof:placetype":"venue"
},
  "geometry": {"coordinates":[-81.24328,35.468562],"type":"Point"}
}