{
  "type": "Feature",
  "properties": {
    "iso:country":"US",
    "sg:address":"7200 Stonehenge Dr",
    "sg:city":"Raleigh",
    "sg:classifiers":[
        {
            "category":"Real Estate",
            "subcategory":"Real Estate Agent",
            "type":"Services"
        }
    ],
    "sg:phone":"+1 919 846 7300",
    "sg:postcode":"27615",
    "sg:province":"NC",
    "sg:tags":[
        "management"
    ],
    "sg:website":"www.druckerandfalk.com",
    "wof:name":"Drucker & Falk",
    "wof:placetype":"venue"
},
  "geometry": {"coordinates":[-78.67943099999999,35.886212],"type":"Point"}
}