{
  "type": "Feature",
  "properties": {
    "iso:country":"US",
    "sg:address":"2199 Lynmore Dr",
    "sg:city":"Sherrills Ford",
    "sg:classifiers":[
        {
            "category":"Manufacturing",
            "subcategory":"Printing",
            "type":"Manufacturing & Wholesale Goods"
        }
    ],
    "sg:phone":"+1 828 478 2123",
    "sg:postcode":"28673",
    "sg:province":"NC",
    "sg:tags":[
        "screen"
    ],
    "wof:name":"National Sign & Decal Co",
    "wof:placetype":"venue"
},
  "geometry": {"coordinates":[-80.991596,35.635482],"type":"Point"}
}