{
  "type": "Feature",
  "properties": {
    "addr:full":"521 Eagleton Downs Dr Pineville NC 28134",
    "addr:housenumber":"521",
    "addr:postcode":"28134",
    "addr:street":"Eagleton Downs Dr",
    "iso:country":"US",
    "sg:address":"521 Eagleton Downs Dr",
    "sg:city":"Pineville",
    "sg:classifiers":[
        {
            "category":"Shopping",
            "subcategory":"Department Store",
            "type":"Retail Goods"
        }
    ],
    "sg:phone":"+1 704 588 9828",
    "sg:postcode":"28134",
    "sg:province":"NC",
    "sg:tags":[
        "oils-vegetable"
    ],
    "wof:name":"Oilmatic Of The Carolina's",
    "wof:placetype":"venue"
},
  "geometry": {"coordinates":[-80.906888,35.101436],"type":"Point"}
}