{
  "type": "Feature",
  "properties": {
    "addr:full":"2218 Toomey Ave Charlotte NC 28203",
    "addr:housenumber":"2218",
    "addr:postcode":"28203",
    "addr:street":"Toomey Ave",
    "iso:country":"US",
    "sg:address":"2218 Toomey Ave",
    "sg:city":"Charlotte",
    "sg:classifiers":[
        {
            "category":"Manufacturing",
            "subcategory":"Metals",
            "type":"Manufacturing & Wholesale Goods"
        }
    ],
    "sg:phone":"+1 704 344 8875",
    "sg:postcode":"28203",
    "sg:province":"NC",
    "sg:tags":[
        "duct",
        "fitting"
    ],
    "sg:website":"www.ductfabrication.com",
    "wof:name":"Duct Fabrication",
    "wof:placetype":"venue"
},
  "geometry": {"coordinates":[-80.87244800000001,35.211507],"type":"Point"}
}