{
  "type": "Feature",
  "properties": {
    "iso:country":"US",
    "sg:address":"2389 Raynor McLamb Rd",
    "sg:city":"Linden",
    "sg:classifiers":[
        {
            "category":"Shopping",
            "type":"Retail Goods"
        }
    ],
    "sg:phone":"+1 910 814 1122",
    "sg:postcode":"28356",
    "sg:province":"NC",
    "sg:tags":[
        "merchandise"
    ],
    "wof:name":"Brad Country Store",
    "wof:placetype":"venue"
},
  "geometry": {"coordinates":[-78.84887999999999,35.276924],"type":"Point"}
}