{
  "type": "Feature",
  "properties": {
    "addr:full":"104 Market St Louisburg NC 27549",
    "addr:housenumber":"104",
    "addr:postcode":"27549",
    "addr:street":"Market St",
    "iso:country":"US",
    "sg:address":"104 Market St",
    "sg:city":"Louisburg",
    "sg:classifiers":[
        {
            "category":"Shopping",
            "subcategory":"Bicycles & Sporting Goods",
            "type":"Retail Goods"
        }
    ],
    "sg:phone":"+1 252 492 2321",
    "sg:postcode":"27549",
    "sg:province":"NC",
    "wof:name":"Vance Athletic Supply",
    "wof:placetype":"venue"
},
  "geometry": {"coordinates":[-78.30070000000001,36.098392],"type":"Point"}
}