{
  "type": "Feature",
  "properties": {
    "addr:full":"1411 Fire Tower Rd Sanford NC 27330",
    "addr:housenumber":"1411",
    "addr:postcode":"27330",
    "addr:street":"Fire Tower Rd",
    "iso:country":"US",
    "sg:address":"1411 Fire Tower Rd",
    "sg:city":"Sanford",
    "sg:classifiers":[
        {
            "category":"Organizations",
            "subcategory":"Religious Organization",
            "type":"Services"
        }
    ],
    "sg:phone":"+1 919 776 0021",
    "sg:postcode":"27330",
    "sg:province":"NC",
    "sg:tags":[
        "church"
    ],
    "wof:name":"Central Baptist Temple",
    "wof:placetype":"venue"
},
  "geometry": {"coordinates":[-79.18988899999999,35.452705],"type":"Point"}
}