{
  "type": "Feature",
  "properties": {
    "addr:full":"922 NE Maynard Rd Cary NC 27513",
    "addr:housenumber":"922",
    "addr:postcode":"27513",
    "addr:street":"Ne Maynard Rd",
    "iso:country":"US",
    "sg:address":"922 NE Maynard Rd",
    "sg:city":"Cary",
    "sg:classifiers":[
        {
            "category":"Personal",
            "subcategory":"Beauty Salon",
            "type":"Services"
        }
    ],
    "sg:phone":"+1 919 465 0500",
    "sg:postcode":"27513",
    "sg:province":"NC",
    "wof:name":"Yah's Family Hair Salon",
    "wof:placetype":"venue"
},
  "geometry": {"coordinates":[-78.769876,35.802517],"type":"Point"}
}