{
  "type": "Feature",
  "properties": {
    "addr:full":"1 Wedgefield Drive Asheville NC 28806",
    "addr:housenumber":"1",
    "addr:postcode":"28806",
    "addr:street":"Wedgefield Drive",
    "iso:country":"US",
    "sg:address":"1 Wedgefield Drive",
    "sg:city":"Asheville",
    "sg:classifiers":[
        {
            "category":"Travel",
            "subcategory":"Hotels & Motels",
            "type":"Entertainment"
        },
        {
            "category":"Retail",
            "subcategory":"Event Space",
            "type":"Services"
        }
    ],
    "sg:phone":"+1 828 665 6519",
    "sg:postcode":"28806",
    "sg:province":"NC",
    "sg:tags":[
        "venue"
    ],
    "sg:website":"www.holidayinnexpress.com",
    "wof:name":"Holiday Inn Express - Asheville",
    "wof:placetype":"venue"
},
  "geometry": {"coordinates":[-82.605343,35.533611],"type":"Point"}
}