{
  "type": "Feature",
  "properties": {
    "addr:full":"1245 Duck Rd Kitty Hawk NC 27949",
    "addr:housenumber":"1245",
    "addr:postcode":"27949",
    "addr:street":"Duck Rd",
    "iso:country":"US",
    "sg:address":"1245 Duck Rd",
    "sg:city":"Kitty Hawk",
    "sg:classifiers":[
        {
            "category":"Personal",
            "subcategory":"Beauty Salon",
            "type":"Services"
        }
    ],
    "sg:phone":"+1 252 255 0711",
    "sg:postcode":"27949",
    "sg:province":"NC",
    "wof:name":"Eden Spa & Salon",
    "wof:placetype":"venue"
},
  "geometry": {"coordinates":[-75.756417,36.173955],"type":"Point"}
}