{
  "type": "Feature",
  "properties": {
    "iso:country":"US",
    "sg:address":"6750 Overhills Rd",
    "sg:city":"Spring Lake",
    "sg:classifiers":[
        {
            "category":"Health Services",
            "subcategory":"Doctor",
            "type":"Services"
        }
    ],
    "sg:phone":"+1 910 436 2900",
    "sg:postcode":"28390",
    "sg:province":"NC",
    "sg:tags":[
        "physician",
        "surgeon"
    ],
    "wof:name":"Anderson Creek Medical Ctr",
    "wof:placetype":"venue"
},
  "geometry": {"coordinates":[-78.96326000000001,35.255847],"type":"Point"}
}