{
  "type": "Feature",
  "properties": {
    "addr:full":"134 Westhaven Cir Winston Salem NC 27104",
    "addr:housenumber":"134",
    "addr:postcode":"27104",
    "addr:street":"Westhaven Cir",
    "iso:country":"US",
    "sg:address":"134 Westhaven Cir",
    "sg:city":"Winston Salem",
    "sg:classifiers":[
        {
            "category":"Organizations",
            "subcategory":"Membership Organization",
            "type":"Services"
        }
    ],
    "sg:phone":"+1   ",
    "sg:postcode":"27104",
    "sg:province":"NC",
    "wof:name":"Westhaven Homeowners Assn",
    "wof:placetype":"venue"
},
  "geometry": {"coordinates":[-80.307179,36.094921],"type":"Point"}
}