{
  "type": "Feature",
  "properties": {
    "iso:country":"US",
    "sg:address":"4814 Six Forks Rd",
    "sg:city":"Raleigh",
    "sg:classifiers":[
        {
            "category":"Health Services",
            "subcategory":"Doctor",
            "type":"Services"
        }
    ],
    "sg:phone":"+1   ",
    "sg:postcode":"27609",
    "sg:province":"NC",
    "sg:tags":[
        "medical"
    ],
    "wof:name":"Carolina Immediate Care",
    "wof:placetype":"venue"
},
  "geometry": {"coordinates":[-78.643992,35.845471],"type":"Point"}
}