{
  "type": "Feature",
  "properties": {
    "addr:full":"1600 Quail Grove St Willow Spring NC 27592",
    "addr:housenumber":"1600",
    "addr:postcode":"27592",
    "addr:street":"Quail Grove St",
    "iso:country":"US",
    "sg:address":"1600 Quail Grove St",
    "sg:city":"Willow Spring",
    "sg:classifiers":[
        {
            "category":"Building & Trades",
            "subcategory":"Construction",
            "type":"Services"
        }
    ],
    "sg:phone":"+1 919 427 7654",
    "sg:postcode":"27592",
    "sg:province":"NC",
    "sg:tags":[
        "steel",
        "erectors"
    ],
    "wof:name":"Low Country Erection",
    "wof:placetype":"venue"
},
  "geometry": {"coordinates":[-78.736311,35.587028],"type":"Point"}
}