{
  "type": "Feature",
  "properties": {
    "iso:country":"US",
    "sg:address":"1903 W Webb Ave",
    "sg:city":"Burlington",
    "sg:classifiers":[
        {
            "category":"Autos & Motor Vehicles",
            "subcategory":"Fuel & Gas Station",
            "type":"Retail Goods"
        },
        {
            "category":"Retail",
            "subcategory":"Auto Repair",
            "type":"Services"
        }
    ],
    "sg:phone":"+1 336 227 7858",
    "sg:postcode":"27217",
    "sg:province":"NC",
    "sg:tags":[
        "automotive",
        "oil",
        "sup"
    ],
    "wof:name":"Glen Raven Gulf Auto Svc Ctr",
    "wof:placetype":"venue"
},
  "geometry": {"coordinates":[-79.46373199999999,36.109016],"type":"Point"}
}