{
  "type": "Feature",
  "properties": {
    "addr:full":"1806 N Sandhills Blvd Aberdeen NC 28315",
    "addr:housenumber":"1806",
    "addr:postcode":"28315",
    "addr:street":"N Sandhills Blvd",
    "iso:country":"US",
    "sg:address":"1806 N Sandhills Blvd",
    "sg:city":"Aberdeen",
    "sg:classifiers":[
        {
            "category":"Shopping",
            "type":"Retail Goods"
        }
    ],
    "sg:phone":"+1 910 692 2704",
    "sg:postcode":"28315",
    "sg:province":"NC",
    "sg:tags":[
        "factory",
        "outlet"
    ],
    "wof:name":"Rolane Factory Store",
    "wof:placetype":"venue"
},
  "geometry": {"coordinates":[-79.414728,35.155081],"type":"Point"}
}