{
  "type": "Feature",
  "properties": {
    "addr:full":"1775 E International Dr Morrisville NC 27560",
    "addr:housenumber":"1775",
    "addr:postcode":"27560",
    "addr:street":"E International Dr",
    "iso:country":"US",
    "sg:address":"1775 E International Dr",
    "sg:city":"Morrisville",
    "sg:classifiers":[
        {
            "category":"Airline",
            "type":"Transportation"
        }
    ],
    "sg:phone":"+1 919 840 9894",
    "sg:postcode":"27560",
    "sg:province":"NC",
    "wof:name":"Airline Transport Professionals",
    "wof:placetype":"venue"
},
  "geometry": {"coordinates":[-78.784588,35.881353],"type":"Point"}
}