{
  "type": "Feature",
  "properties": {
    "addr:full":"2205 Boone Trail Rd Sanford NC 27330",
    "addr:housenumber":"2205",
    "addr:postcode":"27330",
    "addr:street":"Boone Trail Rd",
    "iso:country":"US",
    "sg:address":"2205 Boone Trail Rd",
    "sg:city":"Sanford",
    "sg:classifiers":[
        {
            "category":"Wholesale",
            "subcategory":"Groceries",
            "type":"Manufacturing & Wholesale Goods"
        }
    ],
    "sg:phone":"+1 919 775 5931",
    "sg:postcode":"27330",
    "sg:province":"NC",
    "sg:tags":[
        "food",
        "product"
    ],
    "sg:website":"www.bostdistributingco.com",
    "wof:name":"Bost Distributing",
    "wof:placetype":"venue"
},
  "geometry": {"coordinates":[-79.22830500000001,35.525679],"type":"Point"}
}