{
  "type": "Feature",
  "properties": {
    "iso:country":"US",
    "sg:address":"4 Magnolia Ct",
    "sg:city":"Whiteville",
    "sg:classifiers":[
        {
            "category":"Shopping",
            "type":"Retail Goods"
        }
    ],
    "sg:phone":"+1 910 642 7373",
    "sg:postcode":"28472",
    "sg:province":"NC",
    "sg:tags":[
        "hearing",
        "equipment",
        "supply",
        "impaired"
    ],
    "sg:website":"www.happyhearingcenter.com",
    "wof:name":"Happy Hearing Centers",
    "wof:placetype":"venue"
},
  "geometry": {"coordinates":[-78.706338,34.373809],"type":"Point"}
}