{
  "type": "Feature",
  "properties": {
    "addr:full":"11124 Downs Rd Pineville NC 28134",
    "addr:housenumber":"11124",
    "addr:postcode":"28134",
    "addr:street":"Downs Rd",
    "iso:country":"US",
    "sg:address":"11124 Downs Rd",
    "sg:city":"Pineville",
    "sg:classifiers":[
        {
            "category":"Home & Garden",
            "subcategory":"Furniture",
            "type":"Retail Goods"
        }
    ],
    "sg:phone":"+1 704 587 9170",
    "sg:postcode":"28134",
    "sg:province":"NC",
    "sg:tags":[
        "apartment",
        "furnishing"
    ],
    "wof:name":"Home Comforts Of Charlotte Inc",
    "wof:placetype":"venue"
},
  "geometry": {"coordinates":[-80.910077,35.111596],"type":"Point"}
}