{
  "type": "Feature",
  "properties": {
    "iso:country":"US",
    "sg:address":"318 Haven Dr",
    "sg:city":"Greenville",
    "sg:classifiers":[
        {
            "category":"Arts & Performance",
            "subcategory":"Theater",
            "type":"Entertainment"
        }
    ],
    "sg:phone":"+1   ",
    "sg:postcode":"27834",
    "sg:province":"NC",
    "sg:tags":[
        "group"
    ],
    "wof:name":"Carolina Beach Club",
    "wof:placetype":"venue"
},
  "geometry": {"coordinates":[-77.38928799999999,35.569617],"type":"Point"}
}