{
  "type": "Feature",
  "properties": {
    "iso:country":"US",
    "sg:address":"1214 Rocky Point Ln",
    "sg:city":"Durham",
    "sg:classifiers":[
        {
            "category":"Real Estate",
            "subcategory":"Real Estate Agent",
            "type":"Services"
        }
    ],
    "sg:phone":"+1 919 620 0002",
    "sg:postcode":"27712",
    "sg:province":"NC",
    "wof:name":"Treyburn Sales Center",
    "wof:placetype":"venue"
},
  "geometry": {"coordinates":[-78.865269,36.12225],"type":"Point"}
}