{
  "type": "Feature",
  "properties": {
    "addr:full":"119 S Main St Kernersville NC 27284",
    "addr:housenumber":"119",
    "addr:postcode":"27284",
    "addr:street":"S Main St",
    "iso:country":"US",
    "sg:address":"119 S Main St",
    "sg:city":"Kernersville",
    "sg:classifiers":[
        {
            "category":"Health Services",
            "subcategory":"Hospital",
            "type":"Services"
        }
    ],
    "sg:phone":"+1 336 993 0903",
    "sg:postcode":"27284",
    "sg:province":"NC",
    "sg:tags":[
        "specialty"
    ],
    "wof:name":"Twin City Counseling Center",
    "wof:placetype":"venue"
},
  "geometry": {"coordinates":[-80.073429,36.119477],"type":"Point"}
}