{
  "type": "Feature",
  "properties": {
    "iso:country":"US",
    "sg:address":"5010 High Point Rd",
    "sg:city":"Greensboro",
    "sg:classifiers":[
        {
            "category":"Restaurant",
            "type":"Food & Drink"
        }
    ],
    "sg:phone":"+1 336 299 5901",
    "sg:postcode":"27407",
    "sg:province":"NC",
    "sg:tags":[
        "banquet",
        "rooms"
    ],
    "wof:name":"Oriental Shrine Club Inc",
    "wof:placetype":"venue"
},
  "geometry": {"coordinates":[-79.875963,36.02497],"type":"Point"}
}