{
  "type": "Feature",
  "properties": {
    "iso:country":"US",
    "sg:address":"1901 Northwest Blvd",
    "sg:city":"Newton",
    "sg:classifiers":[
        {
            "category":"Food & Beverages",
            "subcategory":"Groceries & Convenience Stores",
            "type":"Retail Goods"
        }
    ],
    "sg:phone":"+1 828 464 6632",
    "sg:postcode":"28658",
    "sg:province":"NC",
    "wof:name":"LA Villa",
    "wof:placetype":"venue"
},
  "geometry": {"coordinates":[-81.229004,35.683023],"type":"Point"}
}