{
  "type": "Feature",
  "properties": {
    "addr:full":"524 Hillcrest Cir Boone NC 28607",
    "addr:housenumber":"524",
    "addr:postcode":"28607",
    "addr:street":"Hillcrest Cir",
    "iso:country":"US",
    "sg:address":"524 Hillcrest Cir",
    "sg:city":"Boone",
    "sg:classifiers":[
        {
            "category":"Professional",
            "type":"Services"
        }
    ],
    "sg:phone":"+1 828 268 0192",
    "sg:postcode":"28607",
    "sg:province":"NC",
    "wof:name":"Norris Kester",
    "wof:placetype":"venue"
},
  "geometry": {"coordinates":[-81.66721,36.222751],"type":"Point"}
}