{
  "type": "Feature",
  "properties": {
    "addr:full":"1300 Matthews-Mint Hill Rd Matthews NC 28105",
    "addr:housenumber":"1300",
    "addr:postcode":"28105",
    "addr:street":"Matthews-Mint Hill Rd",
    "iso:country":"US",
    "sg:address":"1300 Matthews-Mint Hill Rd",
    "sg:city":"Matthews",
    "sg:classifiers":[
        {
            "category":"Banks & Credit Unions",
            "subcategory":"Investment Brokerage",
            "type":"Services"
        }
    ],
    "sg:phone":"+1 704 708 4673",
    "sg:postcode":"28105",
    "sg:province":"NC",
    "wof:name":"Investment & Insurance Help",
    "wof:placetype":"venue"
},
  "geometry": {"coordinates":[-80.705797,35.117541],"type":"Point"}
}