{
  "type": "Feature",
  "properties": {
    "addr:full":"2617 Seth Williams Blvd Camp Lejeune NC 28547",
    "addr:housenumber":"2617",
    "addr:postcode":"28547",
    "addr:street":"Seth Williams Blvd Camp",
    "iso:country":"US",
    "sg:address":"2617 Seth Williams Blvd",
    "sg:city":"Camp Lejeune",
    "sg:classifiers":[
        {
            "category":"Government",
            "subcategory":"Office",
            "type":"Public Place"
        }
    ],
    "sg:phone":"+1 910 456 8554",
    "sg:postcode":"28547",
    "sg:province":"NC",
    "sg:tags":[
        "bachelor",
        "management",
        "housing",
        "for"
    ],
    "wof:name":"United States Marine Corps",
    "wof:placetype":"venue"
},
  "geometry": {"coordinates":[-77.376959,34.705922],"type":"Point"}
}