{
  "type": "Feature",
  "properties": {
    "addr:full":"8149 Carolina Blvd Clyde NC 28721",
    "addr:housenumber":"8149",
    "addr:postcode":"28721",
    "addr:street":"Carolina Blvd",
    "iso:country":"US",
    "sg:address":"8149 Carolina Blvd",
    "sg:city":"Clyde",
    "sg:classifiers":[
        {
            "category":"Retail",
            "subcategory":"Auto Repair",
            "type":"Services"
        }
    ],
    "sg:phone":"+1   ",
    "sg:postcode":"28721",
    "sg:province":"NC",
    "sg:tags":[
        "general"
    ],
    "wof:name":"Domestic Auto Inc",
    "wof:placetype":"venue"
},
  "geometry": {"coordinates":[-82.906881,35.53246],"type":"Point"}
}