{
  "type": "Feature",
  "properties": {
    "iso:country":"US",
    "sg:address":"110 E Jefferson St",
    "sg:city":"Monroe",
    "sg:classifiers":[
        {
            "category":"Professional",
            "subcategory":"Lawyer & Legal Services",
            "type":"Services"
        }
    ],
    "sg:phone":"+1 704 289 3193",
    "sg:postcode":"28112",
    "sg:province":"NC",
    "sg:tags":[
        "attorney"
    ],
    "wof:name":"W David Mc Sheehan",
    "wof:placetype":"venue"
},
  "geometry": {"coordinates":[-80.54942800000001,34.98328],"type":"Point"}
}