{
  "type": "Feature",
  "properties": {
    "iso:country":"US",
    "sg:address":"517 Rivage Promenade",
    "sg:city":"Wilmington",
    "sg:classifiers":[
        {
            "category":"Building & Trades",
            "subcategory":"Construction",
            "type":"Services"
        }
    ],
    "sg:phone":"+1 910 395 1998",
    "sg:postcode":"28412",
    "sg:province":"NC",
    "sg:tags":[
        "house"
    ],
    "wof:name":"Tennis Toolbox Inc",
    "wof:placetype":"venue"
},
  "geometry": {"coordinates":[-77.91010799999999,34.1151],"type":"Point"}
}