{
  "type": "Feature",
  "properties": {
    "addr:full":"1547 Liberty Cir Exd Asheboro NC 27205",
    "addr:housenumber":"1547",
    "addr:postcode":"27205",
    "addr:street":"Liberty Cir Exd",
    "iso:country":"US",
    "sg:address":"1547 Liberty Cir Exd",
    "sg:city":"Asheboro",
    "sg:classifiers":[
        {
            "category":"Shopping",
            "subcategory":"Gifts & Souvenirs",
            "type":"Retail Goods"
        }
    ],
    "sg:phone":"+1 336 629 4138",
    "sg:postcode":"27205",
    "sg:province":"NC",
    "wof:name":"Personal Touch Gifts",
    "wof:placetype":"venue"
},
  "geometry": {"coordinates":[-79.794488,35.653083],"type":"Point"}
}