{
  "type": "Feature",
  "properties": {
    "addr:full":"1440 Old Lenoir Rd Hickory NC 28601",
    "addr:housenumber":"1440",
    "addr:postcode":"28601",
    "addr:street":"Old Lenoir Rd",
    "iso:country":"US",
    "sg:address":"1440 Old Lenoir Rd",
    "sg:city":"Hickory",
    "sg:classifiers":[
        {
            "category":"Banks & Credit Unions",
            "subcategory":"Bank",
            "type":"Services"
        }
    ],
    "sg:phone":"+1 828 431 4615",
    "sg:postcode":"28601",
    "sg:province":"NC",
    "wof:name":"Central Carolina Bank",
    "wof:placetype":"venue"
},
  "geometry": {"coordinates":[-81.36705000000001,35.750473],"type":"Point"}
}