{
  "type": "Feature",
  "properties": {
    "addr:full":"2425 W Franklin Blvd Gastonia NC 28052",
    "addr:housenumber":"2425",
    "addr:postcode":"28052",
    "addr:street":"W Franklin Blvd",
    "iso:country":"US",
    "sg:address":"2425 W Franklin Blvd",
    "sg:city":"Gastonia",
    "sg:classifiers":[
        {
            "category":"Retail",
            "subcategory":"Funeral Services",
            "type":"Services"
        }
    ],
    "sg:phone":"+1 704 864 6787",
    "sg:postcode":"28052",
    "sg:province":"NC",
    "sg:tags":[
        "director"
    ],
    "wof:name":"Costner Funeral Home Inc",
    "wof:placetype":"venue"
},
  "geometry": {"coordinates":[-81.223389,35.259274],"type":"Point"}
}