{
  "type": "Feature",
  "properties": {
    "addr:full":"2956 Owen Dr Fayetteville NC 28306",
    "addr:housenumber":"2956",
    "addr:postcode":"28306",
    "addr:street":"Owen Dr",
    "iso:country":"US",
    "sg:address":"2956 Owen Dr",
    "sg:city":"Fayetteville",
    "sg:classifiers":[
        {
            "category":"Personal",
            "type":"Services"
        },
        {
            "category":"Personal",
            "subcategory":"Tattoo Parlor",
            "type":"Services"
        }
    ],
    "sg:phone":"+1 910 424 9617",
    "sg:postcode":"28306",
    "sg:province":"NC",
    "sg:tags":[
        "tattooing"
    ],
    "wof:name":"All American Tattoo Works",
    "wof:placetype":"venue"
},
  "geometry": {"coordinates":[-78.898639,35.019415],"type":"Point"}
}