{
  "type": "Feature",
  "properties": {
    "addr:full":"3216 Old Monroe Rd Matthews NC 28104",
    "addr:housenumber":"3216",
    "addr:postcode":"28104",
    "addr:street":"Old Monroe Rd",
    "iso:country":"US",
    "sg:address":"3216 Old Monroe Rd",
    "sg:city":"Matthews",
    "sg:classifiers":[
        {
            "category":"Retail",
            "subcategory":"Laundry & Dry Cleaning",
            "type":"Services"
        }
    ],
    "sg:phone":"+1 704 821 1217",
    "sg:postcode":"28104",
    "sg:province":"NC",
    "sg:tags":[
        "drycleaning",
        "plant",
        "cleaners"
    ],
    "wof:name":"Union Cleaners",
    "wof:placetype":"venue"
},
  "geometry": {"coordinates":[-80.691547,35.080991],"type":"Point"}
}