{
  "type": "Feature",
  "properties": {
    "addr:full":"408 McQuillan Dr Wilmington NC 28412",
    "addr:housenumber":"408",
    "addr:postcode":"28412",
    "addr:street":"Mcquillan Dr",
    "iso:country":"US",
    "sg:address":"408 McQuillan Dr",
    "sg:city":"Wilmington",
    "sg:classifiers":[
        {
            "category":"Retail",
            "subcategory":"Laundry & Dry Cleaning",
            "type":"Services"
        }
    ],
    "sg:phone":"+1 910 794 8667",
    "sg:postcode":"28412",
    "sg:province":"NC",
    "sg:tags":[
        "cleaners",
        "rug",
        "carpet"
    ],
    "wof:name":"Carpet Cleaning By Phoenix",
    "wof:placetype":"venue"
},
  "geometry": {"coordinates":[-77.90529100000001,34.084016],"type":"Point"}
}