{
  "type": "Feature",
  "properties": {
    "addr:full":"3865 Respess Rd Pinetown NC 27865",
    "addr:housenumber":"3865",
    "addr:postcode":"27865",
    "addr:street":"Respess Rd",
    "iso:country":"US",
    "sg:address":"3865 Respess Rd",
    "sg:city":"Pinetown",
    "sg:classifiers":[
        {
            "category":"Organizations",
            "subcategory":"Membership Organization",
            "type":"Services"
        }
    ],
    "sg:phone":"+1   ",
    "sg:postcode":"27865",
    "sg:province":"NC",
    "sg:tags":[
        "charity"
    ],
    "wof:name":"Charity",
    "wof:placetype":"venue"
},
  "geometry": {"coordinates":[-76.850159,35.556551],"type":"Point"}
}