{
  "type": "Feature",
  "properties": {
    "addr:full":"20 S Angela Cir Durham NC 27703",
    "addr:housenumber":"20",
    "addr:postcode":"27703",
    "addr:street":"S Angela Cir",
    "iso:country":"US",
    "sg:address":"20 S Angela Cir",
    "sg:city":"Durham",
    "sg:classifiers":[
        {
            "category":"Social Services",
            "subcategory":"Child Care",
            "type":"Services"
        }
    ],
    "sg:phone":"+1   ",
    "sg:postcode":"27703",
    "sg:province":"NC",
    "sg:tags":[
        "day"
    ],
    "wof:name":"Rosland Child Care",
    "wof:placetype":"venue"
},
  "geometry": {"coordinates":[-78.809073,35.992787],"type":"Point"}
}