{
  "type": "Feature",
  "properties": {
    "addr:full":"441 James St Clyde NC 28721",
    "addr:housenumber":"441",
    "addr:postcode":"28721",
    "addr:street":"James St",
    "iso:country":"US",
    "sg:address":"441 James St",
    "sg:city":"Clyde",
    "sg:classifiers":[
        {
            "category":"Building & Trades",
            "subcategory":"Landscaping Services",
            "type":"Services"
        }
    ],
    "sg:phone":"+1 828 235 8200",
    "sg:postcode":"28721",
    "sg:province":"NC",
    "wof:name":"Shelton Tree Service",
    "wof:placetype":"venue"
},
  "geometry": {"coordinates":[-82.873411,35.542566],"type":"Point"}
}