{
  "type": "Feature",
  "properties": {
    "addr:full":"204 Stillwater Pt Rocky Point NC 28457",
    "addr:housenumber":"204",
    "addr:postcode":"28457",
    "addr:street":"Stillwater Pt",
    "iso:country":"US",
    "sg:address":"204 Stillwater Pt",
    "sg:city":"Rocky Point",
    "sg:classifiers":[
        {
            "category":"Manufacturing",
            "subcategory":"Furniture",
            "type":"Manufacturing & Wholesale Goods"
        }
    ],
    "sg:phone":"+1 910 602 6875",
    "sg:postcode":"28457",
    "sg:province":"NC",
    "sg:tags":[
        "mfg",
        "wood",
        "cabinet"
    ],
    "wof:name":"Gregory Averitt",
    "wof:placetype":"venue"
},
  "geometry": {"coordinates":[-77.92711199999999,34.3868],"type":"Point"}
}