{
  "type": "Feature",
  "properties": {
    "addr:full":"130 Wedgewood Dr Roanoke Rapids NC 27870",
    "addr:housenumber":"130",
    "addr:postcode":"27870",
    "addr:street":"Wedgewood Dr",
    "iso:country":"US",
    "sg:address":"130 Wedgewood Dr",
    "sg:city":"Roanoke Rapids",
    "sg:classifiers":[
        {
            "category":"Airport",
            "type":"Transportation"
        }
    ],
    "sg:phone":"+1 252 392 9016",
    "sg:postcode":"27870",
    "sg:province":"NC",
    "wof:name":"Farmville Regional Airport",
    "wof:placetype":"venue"
},
  "geometry": {"coordinates":[-77.685416,36.464076],"type":"Point"}
}