{
  "type": "Feature",
  "properties": {
    "iso:country":"US",
    "sg:address":"133 Jones Franklin Rd",
    "sg:city":"Raleigh",
    "sg:classifiers":[
        {
            "category":"Shopping",
            "subcategory":"Used Merchandise",
            "type":"Retail Goods"
        }
    ],
    "sg:phone":"+1 919 859 3325",
    "sg:postcode":"27606",
    "sg:province":"NC",
    "sg:tags":[
        "shop",
        "stone",
        "pawn",
        "pawnbroker",
        "precious",
        "semi-precious"
    ],
    "wof:name":"Plaza West Jewelry & Loan",
    "wof:placetype":"venue"
},
  "geometry": {"coordinates":[-78.721245,35.783175],"type":"Point"}
}