{
  "type": "Feature",
  "properties": {
    "iso:country":"US",
    "sg:address":"114 Princess St",
    "sg:city":"Wilmington",
    "sg:classifiers":[
        {
            "category":"Real Estate",
            "subcategory":"Architect",
            "type":"Services"
        },
        {
            "category":"Building & Trades",
            "subcategory":"Construction",
            "type":"Services"
        }
    ],
    "sg:phone":"+1 910 763 9515",
    "sg:postcode":"28401",
    "sg:province":"NC",
    "sg:tags":[
        "residential",
        "designer",
        "architectural"
    ],
    "wof:name":"Shoreline Design Group",
    "wof:placetype":"venue"
},
  "geometry": {"coordinates":[-77.9477,34.236471],"type":"Point"}
}