{
  "type": "Feature",
  "properties": {
    "addr:full":"9558 Pleasant Hill Church Rd Liberty NC 27298",
    "addr:housenumber":"9558",
    "addr:postcode":"27298",
    "addr:street":"Pleasant Hill Church Rd",
    "iso:country":"US",
    "sg:address":"9558 Pleasant Hill Church Rd",
    "sg:city":"Liberty",
    "sg:phone":"+1 336 376 6412",
    "sg:postcode":"27298",
    "sg:province":"NC",
    "sg:tags":[
        "farm",
        "wheat"
    ],
    "wof:name":"Fogleman Diary",
    "wof:placetype":"venue"
},
  "geometry": {"coordinates":[-79.485286,35.86206],"type":"Point"}
}