{
  "type": "Feature",
  "properties": {
    "iso:country":"US",
    "sg:address":"2511 Guess Rd",
    "sg:city":"Durham",
    "sg:classifiers":[
        {
            "category":"Autos & Motor Vehicles",
            "subcategory":"Automobile Sales",
            "type":"Retail Goods"
        }
    ],
    "sg:phone":"+1 919 286 3121",
    "sg:postcode":"27705",
    "sg:province":"NC",
    "sg:tags":[
        "car",
        "used",
        "dealership"
    ],
    "wof:name":"Go Go Quality Auto Sales",
    "wof:placetype":"venue"
},
  "geometry": {"coordinates":[-78.924819,36.028044],"type":"Point"}
}