{
  "type": "Feature",
  "properties": {
    "addr:full":"1218 Westridge Rd Greensboro NC 27410",
    "addr:housenumber":"1218",
    "addr:postcode":"27410",
    "addr:street":"Westridge Rd",
    "iso:country":"US",
    "sg:address":"1218 Westridge Rd",
    "sg:city":"Greensboro",
    "sg:classifiers":[
        {
            "category":"Health Services",
            "subcategory":"Doctor",
            "type":"Services"
        }
    ],
    "sg:phone":"+1   ",
    "sg:postcode":"27410",
    "sg:province":"NC",
    "sg:tags":[
        "medical"
    ],
    "wof:name":"Philip H Lavine MD",
    "wof:placetype":"venue"
},
  "geometry": {"coordinates":[-79.85280299999999,36.106438],"type":"Point"}
}