{
  "type": "Feature",
  "properties": {
    "addr:full":"719 Green Valley Rd Greensboro NC 27403",
    "addr:housenumber":"719",
    "addr:postcode":"27403",
    "addr:street":"Green Valley Rd",
    "iso:country":"US",
    "sg:address":"719 Green Valley Rd",
    "sg:city":"Greensboro",
    "sg:classifiers":[
        {
            "category":"Health Services",
            "subcategory":"Medical Lab",
            "type":"Services"
        }
    ],
    "sg:phone":"+1 336 333 9224",
    "sg:postcode":"27403",
    "sg:province":"NC",
    "sg:tags":[
        "laboratory"
    ],
    "sg:website":"www.spectrumlab.org",
    "wof:name":"Spectrum Laboratory Network",
    "wof:placetype":"venue"
},
  "geometry": {"coordinates":[-79.824758,36.089243],"type":"Point"}
}