{
  "type": "Feature",
  "properties": {
    "iso:country":"US",
    "sg:address":"551 30th Avenue Cir NE",
    "sg:city":"Hickory",
    "sg:classifiers":[
        {
            "category":"Insurance",
            "subcategory":"Insurance Agent",
            "type":"Services"
        }
    ],
    "sg:phone":"+1 828 256 9820",
    "sg:postcode":"28601",
    "sg:province":"NC",
    "wof:name":"Thrivent Financial-Lutherans",
    "wof:placetype":"venue"
},
  "geometry": {"coordinates":[-81.318335,35.774581],"type":"Point"}
}