{
  "type": "Feature",
  "properties": {
    "iso:country":"US",
    "sg:address":"4416 Sardis Church Rd",
    "sg:city":"Monroe",
    "sg:classifiers":[
        {
            "category":"Education",
            "subcategory":"School",
            "type":"Public Place"
        }
    ],
    "sg:phone":"+1 704 882 4303",
    "sg:postcode":"28110",
    "sg:province":"NC",
    "sg:website":"www.sardiselementary.com",
    "wof:name":"Sardis Elementary School",
    "wof:placetype":"venue"
},
  "geometry": {"coordinates":[-80.621127,35.071456],"type":"Point"}
}