{
  "type": "Feature",
  "properties": {
    "iso:country":"US",
    "sg:address":"1213 Culbreth Dr",
    "sg:city":"Wilmington",
    "sg:classifiers":[
        {
            "category":"Professional",
            "subcategory":"Lawyer & Legal Services",
            "type":"Services"
        }
    ],
    "sg:phone":"+1 910 509 9595",
    "sg:postcode":"28405",
    "sg:province":"NC",
    "sg:tags":[
        "attorney"
    ],
    "wof:name":"Ayers Haidt & Trabucco Pa",
    "wof:placetype":"venue"
},
  "geometry": {"coordinates":[-77.828307,34.234097],"type":"Point"}
}