{
  "type": "Feature",
  "properties": {
    "addr:full":"3921 Jonesville Rd Wake Forest NC 27587",
    "addr:housenumber":"3921",
    "addr:postcode":"27587",
    "addr:street":"Jonesville Rd",
    "iso:country":"US",
    "sg:address":"3921 Jonesville Rd",
    "sg:city":"Wake Forest",
    "sg:classifiers":[
        {
            "category":"Organizations",
            "subcategory":"Religious Organization",
            "type":"Services"
        }
    ],
    "sg:phone":"+1   ",
    "sg:postcode":"27587",
    "sg:province":"NC",
    "wof:name":"Mt Calvary Holiness Church",
    "wof:placetype":"venue"
},
  "geometry": {"coordinates":[-78.47838299999999,35.894442],"type":"Point"}
}