{
  "type": "Feature",
  "properties": {
    "addr:full":"315 Fayetteville Rd Raeford NC 28376",
    "addr:housenumber":"315",
    "addr:postcode":"28376",
    "addr:street":"Fayetteville Rd",
    "iso:country":"US",
    "sg:address":"315 Fayetteville Rd",
    "sg:city":"Raeford",
    "sg:classifiers":[
        {
            "category":"Restaurant",
            "type":"Food & Drink"
        }
    ],
    "sg:menulink":"http://www.allmenus.com/nc/raeford/191123-burger-king/menu/",
    "sg:phone":"+1 919 875 2779",
    "sg:postcode":"28376",
    "sg:province":"NC",
    "sg:tags":[
        "burger",
        "american"
    ],
    "wof:name":"Burger King",
    "wof:placetype":"venue"
},
  "geometry": {"coordinates":[-79.22126900000001,34.97881],"type":"Point"}
}