{
  "type": "Feature",
  "properties": {
    "iso:country":"US",
    "sg:address":"1927 N Bryson Ct",
    "sg:city":"Fuquay Varina",
    "sg:classifiers":[
        {
            "category":"Shopping",
            "subcategory":"Musical Instruments",
            "type":"Retail Goods"
        }
    ],
    "sg:phone":"+1 919 557 2101",
    "sg:postcode":"27526",
    "sg:province":"NC",
    "sg:tags":[
        "music",
        "dealer"
    ],
    "wof:name":"J J DUMPLIN'S Music LLC",
    "wof:placetype":"venue"
},
  "geometry": {"coordinates":[-78.77395,35.608695],"type":"Point"}
}