{
  "type": "Feature",
  "properties": {
    "addr:full":"18724 Nautical Dr Cornelius NC 28031",
    "addr:housenumber":"18724",
    "addr:postcode":"28031",
    "addr:street":"Nautical Dr",
    "iso:country":"US",
    "sg:address":"18724 Nautical Dr",
    "sg:city":"Cornelius",
    "sg:classifiers":[
        {
            "category":"Real Estate",
            "subcategory":"Real Estate Operator",
            "type":"Services"
        }
    ],
    "sg:phone":"+1 704 896 7811",
    "sg:postcode":"28031",
    "sg:province":"NC",
    "sg:tags":[
        "building",
        "nonresidential"
    ],
    "wof:name":"Boozell Properties LLC",
    "wof:placetype":"venue"
},
  "geometry": {"coordinates":[-80.893148,35.461183],"type":"Point"}
}