{
  "type": "Feature",
  "properties": {
    "iso:country":"US",
    "sg:address":"2145 Hendersonville Rd",
    "sg:city":"Arden",
    "sg:classifiers":[
        {
            "category":"Home & Garden",
            "subcategory":"Home Furnishings",
            "type":"Retail Goods"
        }
    ],
    "sg:phone":"+1 828 687 7882",
    "sg:postcode":"28704",
    "sg:province":"NC",
    "sg:tags":[
        "venetian",
        "blind"
    ],
    "wof:name":"Blinds & Us",
    "wof:placetype":"venue"
},
  "geometry": {"coordinates":[-82.524826,35.48148],"type":"Point"}
}