{
  "type": "Feature",
  "properties": {
    "addr:full":"5501 Dona Rd Julian NC 27283",
    "addr:postcode":"5501;27283",
    "addr:street":"Dona Rd",
    "iso:country":"US",
    "sg:address":"5501 Dona Rd",
    "sg:city":"Julian",
    "sg:classifiers":[
        {
            "category":"Building & Trades",
            "subcategory":"Construction",
            "type":"Services"
        }
    ],
    "sg:phone":"+1 336 685 0908",
    "sg:postcode":"27283",
    "sg:province":"NC",
    "sg:tags":[
        "contractor"
    ],
    "wof:name":"S & S Builders",
    "wof:placetype":"venue"
},
  "geometry": {"coordinates":[-79.664039,35.935604],"type":"Point"}
}