{
  "type": "Feature",
  "properties": {
    "iso:country":"US",
    "sg:address":"121 W Phifer St",
    "sg:city":"Monroe",
    "sg:classifiers":[
        {
            "category":"Professional",
            "subcategory":"Detective & Security Services",
            "type":"Services"
        }
    ],
    "sg:phone":"+1 704 283 8880",
    "sg:postcode":"28110",
    "sg:province":"NC",
    "sg:tags":[
        "investigator"
    ],
    "wof:name":"Investigation Pros Inc",
    "wof:placetype":"venue"
},
  "geometry": {"coordinates":[-80.54885299999999,34.992902],"type":"Point"}
}