{
  "type": "Feature",
  "properties": {
    "iso:country":"US",
    "sg:address":"7229 Thompson Mill Rd",
    "sg:city":"Wake Forest",
    "sg:phone":"+1 919 554 4124",
    "sg:postcode":"27587",
    "sg:province":"NC",
    "sg:tags":[
        "farm"
    ],
    "wof:name":"F C Winston",
    "wof:placetype":"venue"
},
  "geometry": {"coordinates":[-78.56105100000001,35.978286],"type":"Point"}
}