{
  "type": "Feature",
  "properties": {
    "addr:full":"1221 Clanton Rd Charlotte NC 28217",
    "addr:housenumber":"1221",
    "addr:postcode":"28217",
    "addr:street":"Clanton Rd",
    "iso:country":"US",
    "sg:address":"1221 Clanton Rd",
    "sg:city":"Charlotte",
    "sg:classifiers":[
        {
            "category":"Restaurant",
            "type":"Food & Drink"
        }
    ],
    "sg:phone":"+1 704 527 6819",
    "sg:postcode":"28217",
    "sg:province":"NC",
    "sg:tags":[
        "caterer"
    ],
    "wof:name":"Dianes Caterers & Catering",
    "wof:placetype":"venue"
},
  "geometry": {"coordinates":[-80.89297000000001,35.20349],"type":"Point"}
}