{
  "type": "Feature",
  "properties": {
    "addr:full":"245 N New Hope Rd Gastonia NC 28054",
    "addr:housenumber":"245",
    "addr:postcode":"28054",
    "addr:street":"N New Hope Rd",
    "iso:country":"US",
    "sg:address":"245 N New Hope Rd",
    "sg:city":"Gastonia",
    "sg:classifiers":[
        {
            "category":"Shopping",
            "subcategory":"Clothing, Apparel, & Fashions",
            "type":"Retail Goods"
        }
    ],
    "sg:phone":"+1 704 865 0111",
    "sg:postcode":"28054",
    "sg:province":"NC",
    "sg:tags":[
        "item",
        "boutique"
    ],
    "sg:website":"www.claires.com",
    "wof:name":"Claire's Boutique",
    "wof:placetype":"venue"
},
  "geometry": {"coordinates":[-81.15108600000001,35.265421],"type":"Point"}
}