{
  "type": "Feature",
  "properties": {
    "addr:full":"630 S Bennett St Southern Pines NC 28387",
    "addr:housenumber":"630",
    "addr:postcode":"28387",
    "addr:street":"S Bennett St",
    "iso:country":"US",
    "sg:address":"630 S Bennett St",
    "sg:city":"Southern Pines",
    "sg:classifiers":[
        {
            "category":"Professional",
            "type":"Services"
        },
        {
            "category":"Health Services",
            "subcategory":"Doctor",
            "type":"Services"
        }
    ],
    "sg:phone":"+1 910 246 0211",
    "sg:postcode":"28387",
    "sg:province":"NC",
    "sg:tags":[
        "physician",
        "surgeon"
    ],
    "wof:name":"Oscar M Gualteros MD",
    "wof:placetype":"venue"
},
  "geometry": {"coordinates":[-79.400119,35.170778],"type":"Point"}
}