{
  "type": "Feature",
  "properties": {
    "iso:country":"US",
    "sg:address":"7432 Capital Blvd",
    "sg:city":"Raleigh",
    "sg:classifiers":[
        {
            "category":"Autos & Motor Vehicles",
            "subcategory":"Fuel & Gas Station",
            "type":"Retail Goods"
        }
    ],
    "sg:phone":"+1 919 876 2884",
    "sg:postcode":"27616",
    "sg:province":"NC",
    "sg:tags":[
        "grocery",
        "station",
        "gasoline"
    ],
    "wof:name":"Village Food Mart",
    "wof:placetype":"venue"
},
  "geometry": {"coordinates":[-78.569312,35.883657],"type":"Point"}
}