{
  "type": "Feature",
  "properties": {
    "iso:country":"US",
    "sg:address":"504 Hodges Rd",
    "sg:city":"Chocowinity",
    "sg:classifiers":[
        {
            "category":"Wholesale",
            "subcategory":"Construction Materials",
            "type":"Manufacturing & Wholesale Goods"
        },
        {
            "category":"Building & Trades",
            "subcategory":"Construction",
            "type":"Services"
        }
    ],
    "sg:phone":"+1 252 975 7975",
    "sg:postcode":"27817",
    "sg:province":"NC",
    "sg:tags":[
        "dry wall",
        "contractor"
    ],
    "wof:name":"Dixie's Drywall",
    "wof:placetype":"venue"
},
  "geometry": {"coordinates":[-77.162183,35.520308],"type":"Point"}
}