{
  "type": "Feature",
  "properties": {
    "addr:full":"1328 Stallings Rd Stallings NC 28104",
    "addr:housenumber":"1328",
    "addr:postcode":"28104",
    "addr:street":"Stallings Rd",
    "iso:country":"US",
    "sg:address":"1328 Stallings Rd",
    "sg:city":"Stallings",
    "sg:classifiers":[
        {
            "category":"Insurance",
            "subcategory":"Insurance Agent",
            "type":"Services"
        }
    ],
    "sg:phone":"+1 704 684 0082",
    "sg:postcode":"28104",
    "sg:province":"NC",
    "wof:name":"Marshall Insurance",
    "wof:placetype":"venue"
},
  "geometry": {"coordinates":[-80.680853,35.094324],"type":"Point"}
}