{
  "type": "Feature",
  "properties": {
    "addr:full":"12125 US Hwy 601 Midland NC 28107",
    "addr:housenumber":"12125",
    "addr:postcode":"28107",
    "addr:street":"Us Hwy 601",
    "iso:country":"US",
    "sg:address":"12125 US Hwy 601",
    "sg:city":"Midland",
    "sg:classifiers":[
        {
            "category":"Retail",
            "subcategory":"Car Wash",
            "type":"Services"
        }
    ],
    "sg:phone":"+1 704 888 3364",
    "sg:postcode":"28107",
    "sg:province":"NC",
    "sg:tags":[
        "polishing",
        "washing"
    ],
    "wof:name":"Splish Splash Car Wash",
    "wof:placetype":"venue"
},
  "geometry": {"coordinates":[-80.50105499999999,35.251199],"type":"Point"}
}