{
  "type": "Feature",
  "properties": {
    "iso:country":"US",
    "sg:address":"201 Charlie Braswell Rd",
    "sg:city":"Goldsboro",
    "sg:classifiers":[
        {
            "category":"Building & Trades",
            "subcategory":"Construction",
            "type":"Services"
        }
    ],
    "sg:phone":"+1 919 580 7100",
    "sg:postcode":"27530",
    "sg:province":"NC",
    "sg:tags":[
        "equipment",
        "installation"
    ],
    "wof:name":"Sellers Millwright",
    "wof:placetype":"venue"
},
  "geometry": {"coordinates":[-78.10890999999999,35.43523],"type":"Point"}
}