{
  "type": "Feature",
  "properties": {
    "iso:country":"US",
    "sg:address":"100 Lenoir Rd",
    "sg:city":"Morganton",
    "sg:classifiers":[
        {
            "category":"Autos & Motor Vehicles",
            "subcategory":"Fuel & Gas Station",
            "type":"Retail Goods"
        },
        {
            "category":"Food & Beverages",
            "subcategory":"Specialty",
            "type":"Retail Goods"
        },
        {
            "category":"Food & Beverages",
            "subcategory":"Groceries & Convenience Stores",
            "type":"Retail Goods"
        }
    ],
    "sg:phone":"+1 828 433 4430",
    "sg:postcode":"28655",
    "sg:province":"NC",
    "sg:tags":[
        "grocers-specialty"
    ],
    "wof:name":"Five Star",
    "wof:placetype":"venue"
},
  "geometry": {"coordinates":[-81.687828,35.75737],"type":"Point"}
}