{
  "type": "Feature",
  "properties": {
    "addr:full":"3406 W Wendover Ave Greensboro NC 27407",
    "addr:housenumber":"3406",
    "addr:postcode":"27407",
    "addr:street":"W Wendover Ave",
    "iso:country":"US",
    "sg:address":"3406 W Wendover Ave",
    "sg:city":"Greensboro",
    "sg:classifiers":[
        {
            "category":"Manufacturing",
            "subcategory":"Tools & Machinery",
            "type":"Manufacturing & Wholesale Goods"
        }
    ],
    "sg:phone":"+1 336 855 9992",
    "sg:postcode":"27407",
    "sg:province":"NC",
    "sg:tags":[
        "caster",
        "mfg"
    ],
    "wof:name":"Rwm Casters Co",
    "wof:placetype":"venue"
},
  "geometry": {"coordinates":[-79.860651,36.061563],"type":"Point"}
}