{
  "type": "Feature",
  "properties": {
    "iso:country":"US",
    "sg:address":"447 White Heron Cove Rd",
    "sg:city":"Hampstead",
    "sg:classifiers":[
        {
            "category":"Building & Trades",
            "subcategory":"Construction",
            "type":"Services"
        }
    ],
    "sg:phone":"+1 910 270 0777",
    "sg:postcode":"28443",
    "sg:province":"NC",
    "sg:tags":[
        "heavy"
    ],
    "wof:name":"Nixon Creek Dredging Project I",
    "wof:placetype":"venue"
},
  "geometry": {"coordinates":[-77.670875,34.370045],"type":"Point"}
}