{
  "type": "Feature",
  "properties": {
    "iso:country":"US",
    "sg:address":"1502 Glenwood Ave",
    "sg:city":"Greensboro",
    "sg:classifiers":[
        {
            "category":"Social Services",
            "subcategory":"Child Care",
            "type":"Services"
        }
    ],
    "sg:phone":"+1 336 373 8502",
    "sg:postcode":"27403",
    "sg:province":"NC",
    "sg:tags":[
        "day"
    ],
    "wof:name":"Gladys Home Child Care",
    "wof:placetype":"venue"
},
  "geometry": {"coordinates":[-79.811306,36.050817],"type":"Point"}
}