{
  "type": "Feature",
  "properties": {
    "addr:full":"4414 Golden View Dr Charlotte NC 28278",
    "addr:housenumber":"4414",
    "addr:postcode":"28278",
    "addr:street":"Golden View Dr",
    "iso:country":"US",
    "sg:address":"4414 Golden View Dr",
    "sg:city":"Charlotte",
    "sg:classifiers":[
        {
            "category":"Building & Trades",
            "subcategory":"Construction",
            "type":"Services"
        }
    ],
    "sg:phone":"+1 704 531 8247",
    "sg:postcode":"28278",
    "sg:province":"NC",
    "sg:tags":[
        "asbestos",
        "removal"
    ],
    "wof:name":"A D Environmental",
    "wof:placetype":"venue"
},
  "geometry": {"coordinates":[-80.99082300000001,35.12881],"type":"Point"}
}