{
  "type": "Feature",
  "properties": {
    "iso:country":"US",
    "sg:address":"503 N Topsail Dr",
    "sg:city":"Surf City",
    "sg:classifiers":[
        {
            "category":"Government",
            "subcategory":"Office",
            "type":"Public Place"
        }
    ],
    "sg:phone":"+1 910 328 1444",
    "sg:postcode":"28445",
    "sg:province":"NC",
    "sg:tags":[
        "village"
    ],
    "wof:name":"Surf City Town Medical Svc",
    "wof:placetype":"venue"
},
  "geometry": {"coordinates":[-77.53609,34.431648],"type":"Point"}
}