{
  "type": "Feature",
  "properties": {
    "addr:full":"1457 9th Ave NE Hickory NC 28601",
    "addr:housenumber":"1457",
    "addr:postcode":"28601",
    "addr:street":"9Th Ave Ne",
    "iso:country":"US",
    "sg:address":"1457 9th Ave NE",
    "sg:city":"Hickory",
    "sg:classifiers":[
        {
            "category":"Manufacturing",
            "subcategory":"Furniture",
            "type":"Manufacturing & Wholesale Goods"
        }
    ],
    "sg:phone":"+1 828 326 8435",
    "sg:postcode":"28601",
    "sg:province":"NC",
    "wof:name":"Shuford Furniture",
    "wof:placetype":"venue"
},
  "geometry": {"coordinates":[-81.309783,35.739704],"type":"Point"}
}