{
  "type": "Feature",
  "properties": {
    "iso:country":"US",
    "sg:address":"245 Keever Dr",
    "sg:city":"Denton",
    "sg:classifiers":[
        {
            "category":"Manufacturing",
            "subcategory":"Tools & Machinery",
            "type":"Manufacturing & Wholesale Goods"
        }
    ],
    "sg:phone":"+1 336 859 5072",
    "sg:postcode":"27239",
    "sg:province":"NC",
    "sg:tags":[
        "machine",
        "rebuilds"
    ],
    "wof:name":"Tex L Match L C",
    "wof:placetype":"venue"
},
  "geometry": {"coordinates":[-80.13515599999999,35.655924],"type":"Point"}
}