{
  "type": "Feature",
  "properties": {
    "addr:full":"893 US Hwy 64 Bus Hayesville NC 28904",
    "addr:housenumber":"893",
    "addr:postcode":"28904",
    "addr:street":"Us Hwy 64 Bus",
    "iso:country":"US",
    "sg:address":"893 US Hwy 64 Bus",
    "sg:city":"Hayesville",
    "sg:classifiers":[
        {
            "category":"Shopping",
            "subcategory":"Bicycles & Sporting Goods",
            "type":"Retail Goods"
        }
    ],
    "sg:phone":"+1 828 389 3100",
    "sg:postcode":"28904",
    "sg:province":"NC",
    "sg:tags":[
        "equipment",
        "hunting",
        "supply"
    ],
    "wof:name":"Clay Farmers Sporting Goods",
    "wof:placetype":"venue"
},
  "geometry": {"coordinates":[-83.81858699999999,35.045577],"type":"Point"}
}