{
  "type": "Feature",
  "properties": {
    "addr:full":"866 Mocksville Hwy Statesville NC 28625",
    "addr:housenumber":"866",
    "addr:postcode":"28625",
    "addr:street":"Mocksville Hwy",
    "iso:country":"US",
    "sg:address":"866 Mocksville Hwy",
    "sg:city":"Statesville",
    "sg:classifiers":[
        {
            "category":"Professional",
            "subcategory":"Engineering",
            "type":"Services"
        }
    ],
    "sg:phone":"+1   ",
    "sg:postcode":"28625",
    "sg:province":"NC",
    "wof:name":"Endalloss Design",
    "wof:placetype":"venue"
},
  "geometry": {"coordinates":[-80.789563,35.806964],"type":"Point"}
}