{
  "type": "Feature",
  "properties": {
    "addr:full":"622 Old Roberts Rd Benson NC 27504",
    "addr:housenumber":"622",
    "addr:postcode":"27504",
    "addr:street":"Old Roberts Rd",
    "iso:country":"US",
    "sg:address":"622 Old Roberts Rd",
    "sg:city":"Benson",
    "sg:classifiers":[
        {
            "category":"Retail",
            "subcategory":"Auto Repair",
            "type":"Services"
        }
    ],
    "sg:phone":"+1 919 938 1515",
    "sg:postcode":"27504",
    "sg:province":"NC",
    "sg:tags":[
        "body",
        "automobile",
        "painting"
    ],
    "wof:name":"Clayton Custom Collision",
    "wof:placetype":"venue"
},
  "geometry": {"coordinates":[-78.557794,35.524856],"type":"Point"}
}