{
  "type": "Feature",
  "properties": {
    "iso:country":"US",
    "sg:address":"6320 Quadrangle Dr",
    "sg:city":"Chapel Hill",
    "sg:classifiers":[
        {
            "category":"Health Services",
            "subcategory":"Clinic",
            "type":"Services"
        },
        {
            "category":"Social Services",
            "type":"Services"
        }
    ],
    "sg:phone":"+1 919 403 3300",
    "sg:postcode":"27517",
    "sg:province":"NC",
    "sg:tags":[
        "instruction",
        "care"
    ],
    "sg:website":"www.healthplanningsource.com",
    "wof:name":"Health Planning Source",
    "wof:placetype":"venue"
},
  "geometry": {"coordinates":[-78.97949,35.913707],"type":"Point"}
}