{
  "type": "Feature",
  "properties": {
    "iso:country":"US",
    "sg:address":"3485 Double Oak Dr",
    "sg:city":"Morganton",
    "sg:classifiers":[
        {
            "category":"Local Transit",
            "type":"Transportation"
        }
    ],
    "sg:phone":"+1 828 438 0826",
    "sg:postcode":"28655",
    "sg:province":"NC",
    "wof:name":"Wheeler Enterprises of Bu",
    "wof:placetype":"venue"
},
  "geometry": {"coordinates":[-81.614029,35.748028],"type":"Point"}
}