{
  "type": "Feature",
  "properties": {
    "addr:full":"211 Shady Oak Dr Biscoe NC 27209",
    "addr:housenumber":"211",
    "addr:postcode":"27209",
    "addr:street":"Shady Oak Dr",
    "iso:country":"US",
    "sg:address":"211 Shady Oak Dr",
    "sg:city":"Biscoe",
    "sg:classifiers":[
        {
            "category":"Manufacturing",
            "subcategory":"Textiles",
            "type":"Manufacturing & Wholesale Goods"
        },
        {
            "category":"Wholesale",
            "subcategory":"Apparel",
            "type":"Manufacturing & Wholesale Goods"
        }
    ],
    "sg:phone":"+1 910 428 9688",
    "sg:postcode":"27209",
    "sg:province":"NC",
    "sg:tags":[
        "manufacture",
        "hosiery"
    ],
    "wof:name":"Central Carolina Hosiery Inc",
    "wof:placetype":"venue"
},
  "geometry": {"coordinates":[-79.780356,35.37228],"type":"Point"}
}