{
  "type": "Feature",
  "properties": {
    "iso:country":"US",
    "sg:address":"51 Carl Scott Rd",
    "sg:city":"Bear Creek",
    "sg:classifiers":[
        {
            "category":"Building & Trades",
            "subcategory":"Construction",
            "type":"Services"
        }
    ],
    "sg:phone":"+1 919 837 5777",
    "sg:postcode":"27207",
    "sg:province":"NC",
    "sg:tags":[
        "house"
    ],
    "wof:name":"William B Webster Construction",
    "wof:placetype":"venue"
},
  "geometry": {"coordinates":[-79.44283299999999,35.560451],"type":"Point"}
}