{
  "type": "Feature",
  "properties": {
    "iso:country":"US",
    "sg:address":"111 Eastbrook Dr",
    "sg:city":"Greenville",
    "sg:classifiers":[
        {
            "category":"Professional",
            "subcategory":"Detective & Security Services",
            "type":"Services"
        }
    ],
    "sg:phone":"+1 252 758 2174",
    "sg:postcode":"27858",
    "sg:province":"NC",
    "sg:tags":[
        "guard",
        "patrol"
    ],
    "wof:name":"Budd Group",
    "wof:placetype":"venue"
},
  "geometry": {"coordinates":[-77.33735299999999,35.596991],"type":"Point"}
}