{
  "type": "Feature",
  "properties": {
    "iso:country":"US",
    "sg:address":"118 Wm J B Blevins Dr",
    "sg:city":"Jefferson",
    "sg:classifiers":[
        {
            "category":"Health Services",
            "subcategory":"Hospital",
            "type":"Services"
        }
    ],
    "sg:phone":"+1 336 246 2481",
    "sg:postcode":"28640",
    "sg:province":"NC",
    "sg:tags":[
        "mental"
    ],
    "wof:name":"New River Area CAP Svc",
    "wof:placetype":"venue"
},
  "geometry": {"coordinates":[-81.478112,36.420368],"type":"Point"}
}