{
  "type": "Feature",
  "properties": {
    "iso:country":"US",
    "sg:address":"603 Calvin Rd",
    "sg:city":"Robbins",
    "sg:classifiers":[
        {
            "category":"Professional",
            "subcategory":"Detective & Security Services",
            "type":"Services"
        }
    ],
    "sg:phone":"+1   ",
    "sg:postcode":"27325",
    "sg:province":"NC",
    "sg:tags":[
        "system"
    ],
    "wof:name":"Bkb Safety Services",
    "wof:placetype":"venue"
},
  "geometry": {"coordinates":[-79.497539,35.501678],"type":"Point"}
}