{
  "type": "Feature",
  "properties": {
    "iso:country":"US",
    "sg:address":"2404 Merritt Dr",
    "sg:city":"Greensboro",
    "sg:classifiers":[
        {
            "category":"Government",
            "subcategory":"Office",
            "type":"Public Place"
        }
    ],
    "sg:phone":"+1 336 632 0506",
    "sg:postcode":"27407",
    "sg:province":"NC",
    "sg:tags":[
        "national",
        "security"
    ],
    "wof:name":"Air Force Recruiting Office",
    "wof:placetype":"venue"
},
  "geometry": {"coordinates":[-79.861622,36.035578],"type":"Point"}
}