{
  "type": "Feature",
  "properties": {
    "iso:country":"US",
    "sg:address":"3506 Tuckaseegee Rd",
    "sg:city":"Charlotte",
    "sg:classifiers":[
        {
            "category":"Shopping",
            "subcategory":"Clothing, Apparel, & Fashions",
            "type":"Retail Goods"
        }
    ],
    "sg:phone":"+1 704 398 3199",
    "sg:postcode":"28208",
    "sg:province":"NC",
    "wof:name":"Marilyns Classic Shop",
    "wof:placetype":"venue"
},
  "geometry": {"coordinates":[-80.885367,35.245463],"type":"Point"}
}