{
  "type": "Feature",
  "properties": {
    "iso:country":"US",
    "sg:address":"1636 Rocky Glen Ln",
    "sg:city":"Charlotte",
    "sg:classifiers":[
        {
            "category":"Professional",
            "subcategory":"Management & Consulting",
            "type":"Services"
        }
    ],
    "sg:phone":"+1   ",
    "sg:postcode":"28214",
    "sg:province":"NC",
    "sg:tags":[
        "business"
    ],
    "wof:name":"Drp Landscaping Service Inc",
    "wof:placetype":"venue"
},
  "geometry": {"coordinates":[-80.962936,35.304985],"type":"Point"}
}