{
  "type": "Feature",
  "properties": {
    "iso:country":"US",
    "sg:address":"127 Kemberly Ct",
    "sg:city":"Jacksonville",
    "sg:classifiers":[
        {
            "category":"Taxi",
            "type":"Transportation"
        }
    ],
    "sg:phone":"+1 910 324 5524",
    "sg:postcode":"28540",
    "sg:province":"NC",
    "sg:tags":[
        "taxicab"
    ],
    "wof:name":"Pinnacle Cab Inc",
    "wof:placetype":"venue"
},
  "geometry": {"coordinates":[-77.49012,34.853873],"type":"Point"}
}