{
  "type": "Feature",
  "properties": {
    "addr:full":"1381 Slade Rd Blanch NC 27212",
    "addr:housenumber":"1381",
    "addr:postcode":"27212",
    "addr:street":"Slade Rd",
    "iso:country":"US",
    "sg:address":"1381 Slade Rd",
    "sg:city":"Blanch",
    "sg:classifiers":[
        {
            "category":"Building & Trades",
            "subcategory":"Construction",
            "type":"Services"
        }
    ],
    "sg:phone":"+1 336 694 4407",
    "sg:postcode":"27212",
    "sg:province":"NC",
    "sg:tags":[
        "house"
    ],
    "wof:name":"S H Woodcraft",
    "wof:placetype":"venue"
},
  "geometry": {"coordinates":[-79.318831,36.455213],"type":"Point"}
}