{
  "type": "Feature",
  "properties": {
    "addr:full":"306 Cross Vine Ln Greensboro NC 27455",
    "addr:housenumber":"306",
    "addr:postcode":"27455",
    "addr:street":"Cross Vine Ln",
    "iso:country":"US",
    "sg:address":"306 Cross Vine Ln",
    "sg:city":"Greensboro",
    "sg:classifiers":[
        {
            "category":"Real Estate",
            "subcategory":"Real Estate Operator",
            "type":"Services"
        }
    ],
    "sg:phone":"+1 336 282 4242",
    "sg:postcode":"27455",
    "sg:province":"NC",
    "sg:tags":[
        "building",
        "nonresidential"
    ],
    "wof:name":"Wilson Fortune Properties LLC",
    "wof:placetype":"venue"
},
  "geometry": {"coordinates":[-79.805581,36.150396],"type":"Point"}
}