{
  "type": "Feature",
  "properties": {
    "addr:full":"205 Valley Rd Hickory NC 28601",
    "addr:housenumber":"205",
    "addr:postcode":"28601",
    "addr:street":"Valley Rd",
    "iso:country":"US",
    "sg:address":"205 Valley Rd",
    "sg:city":"Hickory",
    "sg:classifiers":[
        {
            "category":"Building & Trades",
            "subcategory":"Electrical",
            "type":"Services"
        },
        {
            "category":"Wholesale",
            "subcategory":"Electrical",
            "type":"Manufacturing & Wholesale Goods"
        }
    ],
    "sg:phone":"+1 828 495 2675",
    "sg:postcode":"28601",
    "sg:province":"NC",
    "sg:tags":[
        "sound",
        "equipment",
        "system",
        "contractor"
    ],
    "wof:name":"Celestial Sound Design Inc",
    "wof:placetype":"venue"
},
  "geometry": {"coordinates":[-81.314992,35.808539],"type":"Point"}
}