{
  "type": "Feature",
  "properties": {
    "addr:full":"145 N Renfro St Mount Airy NC 27030",
    "addr:housenumber":"145",
    "addr:postcode":"27030",
    "addr:street":"N Renfro St",
    "iso:country":"US",
    "sg:address":"145 N Renfro St",
    "sg:city":"Mount Airy",
    "sg:classifiers":[
        {
            "category":"Banks & Credit Unions",
            "subcategory":"Bank",
            "type":"Services"
        }
    ],
    "sg:phone":"+1 336 719 2310",
    "sg:postcode":"27030",
    "sg:province":"NC",
    "sg:tags":[
        "state",
        "chartered"
    ],
    "wof:name":"Surrey Bancorp",
    "wof:placetype":"venue"
},
  "geometry": {"coordinates":[-80.605896,36.500872],"type":"Point"}
}