{
  "type": "Feature",
  "properties": {
    "addr:full":"750 Pleasant Plains Church Rd Whiteville NC 28472",
    "addr:housenumber":"750",
    "addr:postcode":"28472",
    "addr:street":"Pleasant;Church Rd",
    "iso:country":"US",
    "sg:address":"750 Pleasant Plains Church Rd",
    "sg:city":"Whiteville",
    "sg:classifiers":[
        {
            "category":"Arts & Performance",
            "subcategory":"Theater",
            "type":"Entertainment"
        }
    ],
    "sg:phone":"+1 910 770 1339",
    "sg:postcode":"28472",
    "sg:province":"NC",
    "sg:tags":[
        "live",
        "music"
    ],
    "wof:name":"Platinum Entertainment",
    "wof:placetype":"venue"
},
  "geometry": {"coordinates":[-78.69699300000001,34.251721],"type":"Point"}
}