{
  "type": "Feature",
  "properties": {
    "iso:country":"US",
    "sg:address":"2521 Raeford Rd",
    "sg:city":"Fayetteville",
    "sg:classifiers":[
        {
            "category":"Building & Trades",
            "subcategory":"Construction",
            "type":"Services"
        }
    ],
    "sg:phone":"+1 910 323 4301",
    "sg:postcode":"28305",
    "sg:province":"NC",
    "sg:tags":[
        "home",
        "builder"
    ],
    "wof:name":"Maxwell Homes",
    "wof:placetype":"venue"
},
  "geometry": {"coordinates":[-78.918966,35.046052],"type":"Point"}
}