{
  "type": "Feature",
  "properties": {
    "addr:full":"1270 Burlington Rd Roxboro NC 27573",
    "addr:housenumber":"1270",
    "addr:postcode":"27573",
    "addr:street":"Burlington Rd",
    "iso:country":"US",
    "sg:address":"1270 Burlington Rd",
    "sg:city":"Roxboro",
    "sg:classifiers":[
        {
            "category":"Professional",
            "type":"Services"
        }
    ],
    "sg:phone":"+1 336 599 9604",
    "sg:postcode":"27573",
    "sg:province":"NC",
    "sg:tags":[
        "establishment"
    ],
    "wof:name":"Pro Sport Marketing",
    "wof:placetype":"venue"
},
  "geometry": {"coordinates":[-79.00349900000001,36.387808],"type":"Point"}
}