{
  "type": "Feature",
  "properties": {
    "addr:full":"3206 Perry St NW Concord NC 28027",
    "addr:housenumber":"3206",
    "addr:postcode":"28027",
    "addr:street":"Perry St Nw",
    "iso:country":"US",
    "sg:address":"3206 Perry St NW",
    "sg:city":"Concord",
    "sg:classifiers":[
        {
            "category":"Building & Trades",
            "subcategory":"Pest Control",
            "type":"Services"
        }
    ],
    "sg:phone":"+1 704 786 5300",
    "sg:postcode":"28027",
    "sg:province":"NC",
    "sg:website":"www.terminix.com",
    "wof:name":"Terminix International Co",
    "wof:placetype":"venue"
},
  "geometry": {"coordinates":[-80.667528,35.371318],"type":"Point"}
}