{
  "type": "Feature",
  "properties": {
    "iso:country":"US",
    "sg:address":"4 Cross Road Dr",
    "sg:city":"Horse Shoe",
    "sg:classifiers":[
        {
            "category":"Shopping",
            "subcategory":"Pharmacy",
            "type":"Retail Goods"
        }
    ],
    "sg:phone":"+1 828 891 4585",
    "sg:postcode":"28759",
    "sg:province":"NC",
    "wof:name":"CVS Pharmacy",
    "wof:placetype":"venue"
},
  "geometry": {"coordinates":[-78.98351700000001,34.943159],"type":"Point"}
}