{
  "type": "Feature",
  "properties": {
    "iso:country":"US",
    "sg:address":"119 Middle St",
    "sg:city":"New Bern",
    "sg:classifiers":[
        {
            "category":"Manufacturing",
            "subcategory":"Paper Products",
            "type":"Manufacturing & Wholesale Goods"
        }
    ],
    "sg:phone":"+1 252 514 6600",
    "sg:postcode":"28560",
    "sg:province":"NC",
    "sg:tags":[
        "affairs",
        "public"
    ],
    "wof:name":"Weyerhaeuser Company",
    "wof:placetype":"venue"
},
  "geometry": {"coordinates":[-77.04053,35.103876],"type":"Point"}
}