{
  "type": "Feature",
  "properties": {
    "addr:full":"2220 Milton Rd Charlotte NC 28215",
    "addr:housenumber":"2220",
    "addr:postcode":"28215",
    "addr:street":"Milton Rd",
    "iso:country":"US",
    "sg:address":"2220 Milton Rd",
    "sg:city":"Charlotte",
    "sg:classifiers":[
        {
            "category":"Organizations",
            "subcategory":"Religious Organization",
            "type":"Services"
        }
    ],
    "sg:phone":"+1   ",
    "sg:postcode":"28215",
    "sg:province":"NC",
    "wof:name":"Weeping Willow AME Zion Church",
    "wof:placetype":"venue"
},
  "geometry": {"coordinates":[-80.749426,35.24093],"type":"Point"}
}