{
  "type": "Feature",
  "properties": {
    "iso:country":"US",
    "sg:address":"831 Cloverleaf Plz",
    "sg:city":"Kannapolis",
    "sg:classifiers":[
        {
            "category":"Shopping",
            "subcategory":"Gifts & Souvenirs",
            "type":"Retail Goods"
        }
    ],
    "sg:phone":"+1 704 784 2277",
    "sg:postcode":"28083",
    "sg:province":"NC",
    "sg:tags":[
        "collectible"
    ],
    "wof:name":"Scotts Toys & Collectibles",
    "wof:placetype":"venue"
},
  "geometry": {"coordinates":[-80.609317,35.450766],"type":"Point"}
}