{
  "type": "Feature",
  "properties": {
    "addr:full":"3115 Sharon Rd Charlotte NC 28211",
    "addr:housenumber":"3115",
    "addr:postcode":"28211",
    "addr:street":"Sharon Rd",
    "iso:country":"US",
    "sg:address":"3115 Sharon Rd",
    "sg:city":"Charlotte",
    "sg:classifiers":[
        {
            "category":"Personal",
            "subcategory":"Beauty Salon",
            "type":"Services"
        }
    ],
    "sg:phone":"+1 704 532 8908",
    "sg:postcode":"28211",
    "sg:province":"NC",
    "sg:tags":[
        "shop"
    ],
    "wof:name":"Hair Reflections",
    "wof:placetype":"venue"
},
  "geometry": {"coordinates":[-80.82244,35.16847],"type":"Point"}
}