{
  "type": "Feature",
  "properties": {
    "addr:full":"622 E 28th St Charlotte NC 28205",
    "addr:housenumber":"622",
    "addr:postcode":"28205",
    "addr:street":"E 28Th St",
    "iso:country":"US",
    "sg:address":"622 E 28th St",
    "sg:city":"Charlotte",
    "sg:classifiers":[
        {
            "category":"Cinema",
            "subcategory":"Movie Theater",
            "type":"Entertainment"
        }
    ],
    "sg:phone":"+1 704 377 4533",
    "sg:postcode":"28205",
    "sg:province":"NC",
    "wof:name":"Charlotte Reptory Theater",
    "wof:placetype":"venue"
},
  "geometry": {"coordinates":[-80.811395,35.241161],"type":"Point"}
}