{
  "type": "Feature",
  "properties": {
    "iso:country":"US",
    "sg:address":"984 General Hoke Dr",
    "sg:city":"Lincolnton",
    "sg:classifiers":[
        {
            "category":"Shopping",
            "subcategory":"Used Merchandise",
            "type":"Retail Goods"
        }
    ],
    "sg:phone":"+1 980 721 6303",
    "sg:postcode":"28092",
    "sg:province":"NC",
    "wof:name":"Lightbarsnet",
    "wof:placetype":"venue"
},
  "geometry": {"coordinates":[-81.225132,35.459033],"type":"Point"}
}