{
  "type": "Feature",
  "properties": {
    "iso:country":"US",
    "sg:address":"3110 Forest Hills Rd SW",
    "sg:city":"Wilson",
    "sg:classifiers":[
        {
            "category":"Government",
            "subcategory":"Office",
            "type":"Public Place"
        }
    ],
    "sg:phone":"+1 252 399 2377",
    "sg:postcode":"27893",
    "sg:province":"NC",
    "sg:tags":[
        "govt",
        "city"
    ],
    "wof:name":"Wilson Water Treatment Plant",
    "wof:placetype":"venue"
},
  "geometry": {"coordinates":[-77.94490999999999,35.693263],"type":"Point"}
}