{
  "type": "Feature",
  "properties": {
    "addr:full":"411 Fieldstream Dr Boone NC 28607",
    "addr:housenumber":"411",
    "addr:postcode":"28607",
    "addr:street":"Fieldstream Dr",
    "iso:country":"US",
    "sg:address":"411 Fieldstream Dr",
    "sg:city":"Boone",
    "sg:classifiers":[
        {
            "category":"Building & Trades",
            "subcategory":"Construction",
            "type":"Services"
        }
    ],
    "sg:phone":"+1 828 262 5782",
    "sg:postcode":"28607",
    "sg:province":"NC",
    "sg:tags":[
        "house"
    ],
    "wof:name":"Restoration Wellness Assn",
    "wof:placetype":"venue"
},
  "geometry": {"coordinates":[-81.65787899999999,36.227385],"type":"Point"}
}