{
  "type": "Feature",
  "properties": {
    "iso:country":"US",
    "sg:address":"741 Burlington Ave",
    "sg:city":"Gibsonville",
    "sg:classifiers":[
        {
            "category":"Retail",
            "subcategory":"Repair Shop",
            "type":"Services"
        }
    ],
    "sg:phone":"+1 336 449 9055",
    "sg:postcode":"27249",
    "sg:province":"NC",
    "sg:tags":[
        "welding"
    ],
    "wof:name":"Plant Maintenance Enterprises",
    "wof:placetype":"venue"
},
  "geometry": {"coordinates":[-79.528913,36.104085],"type":"Point"}
}