{
  "type": "Feature",
  "properties": {
    "addr:full":"611 Joe Cecil Rd Lexington NC 27292",
    "addr:housenumber":"611",
    "addr:postcode":"27292",
    "addr:street":"Joe Cecil Rd",
    "iso:country":"US",
    "sg:address":"611 Joe Cecil Rd",
    "sg:city":"Lexington",
    "sg:classifiers":[
        {
            "category":"Building & Trades",
            "subcategory":"Electrical",
            "type":"Services"
        }
    ],
    "sg:phone":"+1 336 798 0557",
    "sg:postcode":"27292",
    "sg:province":"NC",
    "sg:tags":[
        "electric",
        "contractor"
    ],
    "wof:name":"Lexington Electrical Svc",
    "wof:placetype":"venue"
},
  "geometry": {"coordinates":[-80.25078600000001,35.662576],"type":"Point"}
}