{
  "type": "Feature",
  "properties": {
    "iso:country":"US",
    "sg:address":"505 Howard St",
    "sg:city":"Wilmington",
    "sg:classifiers":[
        {
            "category":"Organizations",
            "subcategory":"Religious Organization",
            "type":"Services"
        }
    ],
    "sg:phone":"+1 910 341 7722",
    "sg:postcode":"28401",
    "sg:province":"NC",
    "sg:tags":[
        "church"
    ],
    "wof:name":"Taylor Homes Senior Annex",
    "wof:placetype":"venue"
},
  "geometry": {"coordinates":[-77.94504499999999,34.25136],"type":"Point"}
}