{
  "type": "Feature",
  "properties": {
    "addr:full":"320 New Rd Colerain NC 27983",
    "addr:housenumber":"320",
    "addr:postcode":"27983",
    "addr:street":"New Rd",
    "iso:country":"US",
    "sg:address":"320 New Rd",
    "sg:city":"Colerain",
    "sg:classifiers":[
        {
            "category":"Retail",
            "subcategory":"Animal Services",
            "type":"Services"
        }
    ],
    "sg:phone":"+1 252 794 9955",
    "sg:postcode":"27983",
    "sg:province":"NC",
    "wof:name":"Klassic KLIP",
    "wof:placetype":"venue"
},
  "geometry": {"coordinates":[-76.922208,36.109826],"type":"Point"}
}