{
  "type": "Feature",
  "properties": {
    "iso:country":"US",
    "sg:address":"2188 US Hwy 401 Bus",
    "sg:city":"Raeford",
    "sg:classifiers":[
        {
            "category":"Shopping",
            "subcategory":"Discount & Variety Stores",
            "type":"Retail Goods"
        }
    ],
    "sg:phone":"+1 910 848 1546",
    "sg:postcode":"28376",
    "sg:province":"NC",
    "wof:name":"99 Cents Store",
    "wof:placetype":"venue"
},
  "geometry": {"coordinates":[-79.18734600000001,34.989682],"type":"Point"}
}