{
  "type": "Feature",
  "properties": {
    "iso:country":"US",
    "sg:address":"718 Hallsville Rd",
    "sg:city":"Beulaville",
    "sg:classifiers":[
        {
            "category":"Autos & Motor Vehicles",
            "subcategory":"Automobile Sales",
            "type":"Retail Goods"
        }
    ],
    "sg:phone":"+1 910 298 4142",
    "sg:postcode":"28518",
    "sg:province":"NC",
    "sg:tags":[
        "body",
        "used"
    ],
    "wof:name":"M&B Motors",
    "wof:placetype":"venue"
},
  "geometry": {"coordinates":[-77.79490699999999,34.917743],"type":"Point"}
}