{
  "type": "Feature",
  "properties": {
    "iso:country":"US",
    "sg:address":"5995 Chapel Hill Rd Ste. 109",
    "sg:city":"Raleigh",
    "sg:classifiers":[
        {
            "category":"Professional",
            "subcategory":"Computer Services",
            "type":"Services"
        }
    ],
    "sg:phone":"+1 877 878 9248",
    "sg:postcode":"27607",
    "sg:province":"NC",
    "sg:tags":[
        "satellite-images",
        "aerial-images",
        "online-imagery"
    ],
    "sg:website":"http://www.TerraServer.com",
    "wof:name":"TerraServer.com",
    "wof:placetype":"venue"
},
  "geometry": {"coordinates":[-78.72638999999999,35.789205],"type":"Point"}
}