{
  "type": "Feature",
  "properties": {
    "iso:country":"US",
    "sg:address":"18516 River Ford Dr",
    "sg:city":"Davidson",
    "sg:classifiers":[
        {
            "category":"Professional",
            "subcategory":"Management & Consulting",
            "type":"Services"
        }
    ],
    "sg:phone":"+1   ",
    "sg:postcode":"28036",
    "sg:province":"NC",
    "wof:name":"J L Marshall and Associates",
    "wof:placetype":"venue"
},
  "geometry": {"coordinates":[-80.807725,35.463075],"type":"Point"}
}