{
  "type": "Feature",
  "properties": {
    "addr:full":"2674 Staley Store Rd Liberty NC 27298",
    "addr:housenumber":"2674",
    "addr:postcode":"27298",
    "addr:street":"Staley Store Rd",
    "iso:country":"US",
    "sg:address":"2674 Staley Store Rd",
    "sg:city":"Liberty",
    "sg:classifiers":[
        {
            "category":"Farming",
            "subcategory":"Dairy Farm",
            "type":"Manufacturing & Wholesale Goods"
        }
    ],
    "sg:phone":"+1 336 622 3993",
    "sg:postcode":"27298",
    "sg:province":"NC",
    "wof:name":"McPherson Tim Dairy Farmer",
    "wof:placetype":"venue"
},
  "geometry": {"coordinates":[-79.513441,35.855572],"type":"Point"}
}