{
  "type": "Feature",
  "properties": {
    "addr:full":"419 Brooks St Wake Forest NC 27587",
    "addr:housenumber":"419",
    "addr:postcode":"27587",
    "addr:street":"Brooks St",
    "iso:country":"US",
    "sg:address":"419 Brooks St",
    "sg:city":"Wake Forest",
    "sg:classifiers":[
        {
            "category":"Restaurant",
            "type":"Food & Drink"
        }
    ],
    "sg:phone":"+1 919 554 2456",
    "sg:postcode":"27587",
    "sg:province":"NC",
    "sg:tags":[
        "eating"
    ],
    "wof:name":"Oriental Jade Restaurant",
    "wof:placetype":"venue"
},
  "geometry": {"coordinates":[-78.509477,35.974911],"type":"Point"}
}