{
  "type": "Feature",
  "properties": {
    "iso:country":"US",
    "sg:address":"190 Biltmore Ave",
    "sg:city":"Asheville",
    "sg:classifiers":[
        {
            "category":"Health Services",
            "subcategory":"Doctor",
            "type":"Services"
        }
    ],
    "sg:phone":"+1 828 252 1116",
    "sg:postcode":"28801",
    "sg:province":"NC",
    "sg:tags":[
        "dentist"
    ],
    "wof:name":"Bouche",
    "wof:placetype":"venue"
},
  "geometry": {"coordinates":[-82.551661,35.587251],"type":"Point"}
}