{
  "type": "Feature",
  "properties": {
    "addr:full":"1221 Polk St Charlotte NC 28206",
    "addr:housenumber":"1221",
    "addr:postcode":"28206",
    "addr:street":"Polk St",
    "iso:country":"US",
    "sg:address":"1221 Polk St",
    "sg:city":"Charlotte",
    "sg:classifiers":[
        {
            "category":"Retail",
            "subcategory":"Auto Repair",
            "type":"Services"
        }
    ],
    "sg:phone":"+1   ",
    "sg:postcode":"28206",
    "sg:province":"NC",
    "sg:tags":[
        "general"
    ],
    "wof:name":"Davis Timothy Auto Repair",
    "wof:placetype":"venue"
},
  "geometry": {"coordinates":[-80.84264,35.242148],"type":"Point"}
}