{
  "type": "Feature",
  "properties": {
    "addr:full":"1213 E 36th St Charlotte NC 28205",
    "addr:housenumber":"1213",
    "addr:postcode":"28205",
    "addr:street":"E 36Th St",
    "iso:country":"US",
    "sg:address":"1213 E 36th St",
    "sg:city":"Charlotte",
    "sg:classifiers":[
        {
            "category":"Retail",
            "subcategory":"Laundry & Dry Cleaning",
            "type":"Services"
        }
    ],
    "sg:phone":"+1   ",
    "sg:postcode":"28205",
    "sg:province":"NC",
    "sg:tags":[
        "drycleaning",
        "plant",
        "coin"
    ],
    "wof:name":"Boyds Quick Service Laundry",
    "wof:placetype":"venue"
},
  "geometry": {"coordinates":[-80.796775,35.241199],"type":"Point"}
}