{
  "type": "Feature",
  "properties": {
    "addr:full":"1406 Hillsborough St Raleigh NC 27605",
    "addr:housenumber":"1406",
    "addr:postcode":"27605",
    "addr:street":"Hillsborough St",
    "iso:country":"US",
    "sg:address":"1406 Hillsborough St",
    "sg:city":"Raleigh",
    "sg:classifiers":[
        {
            "category":"Professional",
            "type":"Services"
        }
    ],
    "sg:phone":"+1 919 833 2500",
    "sg:postcode":"27605",
    "sg:province":"NC",
    "sg:tags":[
        "establishment"
    ],
    "wof:name":"Sir Walter Tourist",
    "wof:placetype":"venue"
},
  "geometry": {"coordinates":[-78.657442,35.784068],"type":"Point"}
}