{
  "type": "Feature",
  "properties": {
    "iso:country":"US",
    "sg:address":"3329 Julie Dr",
    "sg:city":"La Grange",
    "sg:classifiers":[
        {
            "category":"Personal",
            "subcategory":"Beauty Salon",
            "type":"Services"
        }
    ],
    "sg:phone":"+1   ",
    "sg:postcode":"28551",
    "sg:province":"NC",
    "sg:tags":[
        "shop"
    ],
    "wof:name":"Vickies Salon",
    "wof:placetype":"venue"
},
  "geometry": {"coordinates":[-77.71669199999999,35.319856],"type":"Point"}
}