{
  "type": "Feature",
  "properties": {
    "addr:full":"530 Causeway Dr Wrightsville Bch NC 28480",
    "addr:housenumber":"530",
    "addr:postcode":"28480",
    "addr:street":"Causeway Dr",
    "iso:country":"US",
    "sg:address":"530 Causeway Dr",
    "sg:city":"Wrightsville Bch",
    "sg:classifiers":[
        {
            "category":"Social Services",
            "type":"Services"
        }
    ],
    "sg:phone":"+1 910 256 9777",
    "sg:postcode":"28480",
    "sg:province":"NC",
    "sg:tags":[
        "counseling"
    ],
    "wof:name":"Ann Foltrauer",
    "wof:placetype":"venue"
},
  "geometry": {"coordinates":[-77.801912,34.21162],"type":"Point"}
}