{
  "type": "Feature",
  "properties": {
    "iso:country":"US",
    "sg:address":"658 White Horse Dr",
    "sg:city":"Greenville",
    "sg:classifiers":[
        {
            "category":"Shopping",
            "subcategory":"Pharmacy",
            "type":"Retail Goods"
        }
    ],
    "sg:phone":"+1 252 524 4101",
    "sg:postcode":"27834",
    "sg:province":"NC",
    "wof:name":"Hh Drug Co",
    "wof:placetype":"venue"
},
  "geometry": {"coordinates":[-77.46690700000001,35.640322],"type":"Point"}
}