{
  "type": "Feature",
  "properties": {
    "addr:full":"3425 Angier Ave Durham NC 27703",
    "addr:housenumber":"3425",
    "addr:postcode":"27703",
    "addr:street":"Angier Ave",
    "iso:country":"US",
    "sg:address":"3425 Angier Ave",
    "sg:city":"Durham",
    "sg:classifiers":[
        {
            "category":"Autos & Motor Vehicles",
            "subcategory":"Auto Supplies",
            "type":"Retail Goods"
        }
    ],
    "sg:phone":"+1 919 598 3186",
    "sg:postcode":"27703",
    "sg:province":"NC",
    "sg:tags":[
        "body"
    ],
    "wof:name":"Precision Autoworks",
    "wof:placetype":"venue"
},
  "geometry": {"coordinates":[-78.857116,35.964325],"type":"Point"}
}