{
  "type": "Feature",
  "properties": {
    "addr:full":"3830 Blue Ridge Rd Raleigh NC 27612",
    "addr:housenumber":"3830",
    "addr:postcode":"27612",
    "addr:street":"Blue Ridge Rd",
    "iso:country":"US",
    "sg:address":"3830 Blue Ridge Rd",
    "sg:city":"Raleigh",
    "sg:classifiers":[
        {
            "category":"Health Services",
            "subcategory":"Hospital",
            "type":"Services"
        }
    ],
    "sg:phone":"+1 919 424 4600",
    "sg:postcode":"27612",
    "sg:province":"NC",
    "wof:name":"Blue Ridge Health Care Center",
    "wof:placetype":"venue"
},
  "geometry": {"coordinates":[-78.68229700000001,35.832001],"type":"Point"}
}