{
  "type": "Feature",
  "properties": {
    "iso:country":"US",
    "sg:address":"3809 Forestgate Dr",
    "sg:city":"Winston Salem",
    "sg:classifiers":[
        {
            "category":"Building & Trades",
            "subcategory":"Construction",
            "type":"Services"
        }
    ],
    "sg:phone":"+1 336 768 7289",
    "sg:postcode":"27103",
    "sg:province":"NC",
    "sg:tags":[
        "general",
        "contractor"
    ],
    "wof:name":"Epco Construction Co Inc",
    "wof:placetype":"venue"
},
  "geometry": {"coordinates":[-80.315718,36.07206],"type":"Point"}
}