{
  "type": "Feature",
  "properties": {
    "addr:full":"3475 Ada Charlie Rd Morganton NC 28655",
    "addr:housenumber":"3475",
    "addr:postcode":"28655",
    "addr:street":"Ada Charlie Rd",
    "iso:country":"US",
    "sg:address":"3475 Ada Charlie Rd",
    "sg:city":"Morganton",
    "sg:classifiers":[
        {
            "category":"Building & Trades",
            "subcategory":"Electrical",
            "type":"Services"
        }
    ],
    "sg:phone":"+1 828 584 6825",
    "sg:postcode":"28655",
    "sg:province":"NC",
    "sg:tags":[
        "electric",
        "contractor"
    ],
    "wof:name":"Edney Electrical Svc",
    "wof:placetype":"venue"
},
  "geometry": {"coordinates":[-81.77054200000001,35.67012],"type":"Point"}
}