{
  "type": "Feature",
  "properties": {
    "iso:country":"US",
    "sg:address":"701 N Lake Park Blvd",
    "sg:city":"Carolina Beach",
    "sg:classifiers":[
        {
            "category":"Travel",
            "subcategory":"Hotels & Motels",
            "type":"Entertainment"
        }
    ],
    "sg:phone":"+1 910 458 5414",
    "sg:postcode":"28428",
    "sg:province":"NC",
    "wof:name":"Drifters Reef Motel",
    "wof:placetype":"venue"
},
  "geometry": {"coordinates":[-77.8964,34.0415],"type":"Point"}
}