{
  "type": "Feature",
  "properties": {
    "iso:country":"US",
    "sg:address":"7912 Summerfield Rd",
    "sg:city":"Summerfield",
    "sg:classifiers":[
        {
            "category":"Organizations",
            "subcategory":"Religious Organization",
            "type":"Services"
        }
    ],
    "sg:phone":"+1   ",
    "sg:postcode":"27358",
    "sg:province":"NC",
    "wof:name":"Fair Grove Baptist Church",
    "wof:placetype":"venue"
},
  "geometry": {"coordinates":[-79.906108,36.208352],"type":"Point"}
}