{
  "type": "Feature",
  "properties": {
    "iso:country":"US",
    "sg:address":"207 Sandymead Rd",
    "sg:city":"Matthews",
    "sg:classifiers":[
        {
            "category":"Retail",
            "subcategory":"Portrait Studio",
            "type":"Services"
        }
    ],
    "sg:phone":"+1 704 560 5770",
    "sg:postcode":"28105",
    "sg:province":"NC",
    "sg:tags":[
        "taping",
        "wedding"
    ],
    "wof:name":"Fazio Video Productions",
    "wof:placetype":"venue"
},
  "geometry": {"coordinates":[-80.750963,35.108383],"type":"Point"}
}