{
  "type": "Feature",
  "properties": {
    "addr:full":"2790 Dickinson Ave Greenville NC 27834",
    "addr:housenumber":"2790",
    "addr:postcode":"27834",
    "addr:street":"Dickinson Ave",
    "iso:country":"US",
    "sg:address":"2790 Dickinson Ave",
    "sg:city":"Greenville",
    "sg:classifiers":[
        {
            "category":"Health Services",
            "subcategory":"Nursing And Care Facility",
            "type":"Services"
        }
    ],
    "sg:phone":"+1 252 321 1586",
    "sg:postcode":"27834",
    "sg:province":"NC",
    "sg:tags":[
        "hospice"
    ],
    "wof:name":"Advantage Hospice Home Care",
    "wof:placetype":"venue"
},
  "geometry": {"coordinates":[-77.406104,35.592067],"type":"Point"}
}