{
  "type": "Feature",
  "properties": {
    "addr:full":"1311 S Hawthorne Rd Winston Salem NC 27103",
    "addr:housenumber":"1311",
    "addr:postcode":"27103",
    "addr:street":"S Hawthorne Rd",
    "iso:country":"US",
    "sg:address":"1311 S Hawthorne Rd",
    "sg:city":"Winston Salem",
    "sg:classifiers":[
        {
            "category":"Personal",
            "subcategory":"Barber",
            "type":"Services"
        }
    ],
    "sg:phone":"+1   ",
    "sg:postcode":"27103",
    "sg:province":"NC",
    "sg:tags":[
        "shop"
    ],
    "wof:name":"Ardmore Barber Shop",
    "wof:placetype":"venue"
},
  "geometry": {"coordinates":[-80.28492199999999,36.077926],"type":"Point"}
}