{
  "type": "Feature",
  "properties": {
    "iso:country":"US",
    "sg:address":"234 S Garnett St",
    "sg:city":"Henderson",
    "sg:classifiers":[
        {
            "category":"Retail",
            "subcategory":"Portrait Studio",
            "type":"Services"
        }
    ],
    "sg:phone":"+1   ",
    "sg:postcode":"27536",
    "sg:province":"NC",
    "sg:tags":[
        "photo"
    ],
    "wof:name":"Forever Memories",
    "wof:placetype":"venue"
},
  "geometry": {"coordinates":[-78.404033,36.326392],"type":"Point"}
}