{
  "type": "Feature",
  "properties": {
    "iso:country":"US",
    "sg:address":"201 Fox Meadow Rd",
    "sg:city":"Banner Elk",
    "sg:classifiers":[
        {
            "category":"Building & Trades",
            "subcategory":"Construction",
            "type":"Services"
        }
    ],
    "sg:phone":"+1 828 898 3439",
    "sg:postcode":"28604",
    "sg:province":"NC",
    "sg:tags":[
        "house"
    ],
    "wof:name":"Isenhour Construction Co",
    "wof:placetype":"venue"
},
  "geometry": {"coordinates":[-81.85917499999999,36.174612],"type":"Point"}
}