{
  "type": "Feature",
  "properties": {
    "iso:country":"US",
    "sg:address":"662 Hickory Point Rd",
    "sg:city":"Hampstead",
    "sg:classifiers":[
        {
            "category":"Social Services",
            "subcategory":"Child Care",
            "type":"Services"
        }
    ],
    "sg:phone":"+1 910 270 9946",
    "sg:postcode":"28443",
    "sg:province":"NC",
    "wof:name":"Stretch N Grow",
    "wof:placetype":"venue"
},
  "geometry": {"coordinates":[-77.626226,34.395583],"type":"Point"}
}