{
  "type": "Feature",
  "properties": {
    "addr:full":"2160 Charles St Durham NC 27707",
    "addr:housenumber":"2160",
    "addr:postcode":"27707",
    "addr:street":"Charles St",
    "iso:country":"US",
    "sg:address":"2160 Charles St",
    "sg:city":"Durham",
    "sg:classifiers":[
        {
            "category":"Building & Trades",
            "subcategory":"Cleaning & Sanitation",
            "type":"Services"
        }
    ],
    "sg:phone":"+1   ",
    "sg:postcode":"27707",
    "sg:province":"NC",
    "sg:tags":[
        "maintenance"
    ],
    "wof:name":"Certified Custodian",
    "wof:placetype":"venue"
},
  "geometry": {"coordinates":[-78.918587,35.968406],"type":"Point"}
}