{
  "type": "Feature",
  "properties": {
    "iso:country":"US",
    "sg:address":"3352 Commonwealth Ave",
    "sg:city":"Charlotte",
    "sg:classifiers":[
        {
            "category":"Building & Trades",
            "subcategory":"Plumbing",
            "type":"Services"
        }
    ],
    "sg:phone":"+1 704 567 1500",
    "sg:postcode":"28205",
    "sg:province":"NC",
    "sg:tags":[
        "contractor"
    ],
    "wof:name":"Carolina Plumbing Htg & Coolg",
    "wof:placetype":"venue"
},
  "geometry": {"coordinates":[-80.790654,35.208006],"type":"Point"}
}