{
  "type": "Feature",
  "properties": {
    "addr:full":"139 E College Ave Shelby NC 28152",
    "addr:housenumber":"139",
    "addr:postcode":"28152",
    "addr:street":"E College Ave",
    "iso:country":"US",
    "sg:address":"139 E College Ave",
    "sg:city":"Shelby",
    "sg:classifiers":[
        {
            "category":"Shopping",
            "subcategory":"Pharmacy",
            "type":"Retail Goods"
        }
    ],
    "sg:phone":"+1 704 434 9897",
    "sg:postcode":"28152",
    "sg:province":"NC",
    "wof:name":"Professional Pharmacy",
    "wof:placetype":"venue"
},
  "geometry": {"coordinates":[-81.663538,35.250607],"type":"Point"}
}