{
  "type": "Feature",
  "properties": {
    "addr:full":"4472 Brinton Pl Ramseur NC 27316",
    "addr:housenumber":"4472",
    "addr:postcode":"27316",
    "addr:street":"Brinton Pl",
    "iso:country":"US",
    "sg:address":"4472 Brinton Pl",
    "sg:city":"Ramseur",
    "sg:classifiers":[
        {
            "category":"Building & Trades",
            "subcategory":"Electrical",
            "type":"Services"
        }
    ],
    "sg:phone":"+1 336 824 8311",
    "sg:postcode":"27316",
    "sg:province":"NC",
    "sg:tags":[
        "electric",
        "contractor"
    ],
    "wof:name":"Gant Electric Co",
    "wof:placetype":"venue"
},
  "geometry": {"coordinates":[-79.657101,35.740577],"type":"Point"}
}