{
  "type": "Feature",
  "properties": {
    "addr:full":"211 S Avon St Gastonia NC 28054",
    "addr:housenumber":"211",
    "addr:postcode":"28054",
    "addr:street":"S Avon St",
    "iso:country":"US",
    "sg:address":"211 S Avon St",
    "sg:city":"Gastonia",
    "sg:classifiers":[
        {
            "category":"Autos & Motor Vehicles",
            "subcategory":"Auto Supplies",
            "type":"Retail Goods"
        }
    ],
    "sg:phone":"+1 704 867 6326",
    "sg:postcode":"28054",
    "sg:province":"NC",
    "sg:tags":[
        "automobile",
        "parts"
    ],
    "wof:name":"Gaston Auto Supply Inc",
    "wof:placetype":"venue"
},
  "geometry": {"coordinates":[-81.173492,35.260909],"type":"Point"}
}