{
  "type": "Feature",
  "properties": {
    "addr:full":"119 N Chimney Rock Rd Greensboro NC 27409",
    "addr:housenumber":"119",
    "addr:postcode":"27409",
    "addr:street":"N Chimney Rock Rd",
    "iso:country":"US",
    "sg:address":"119 N Chimney Rock Rd",
    "sg:city":"Greensboro",
    "sg:classifiers":[
        {
            "category":"Professional",
            "subcategory":"Advertising",
            "type":"Services"
        }
    ],
    "sg:phone":"+1   ",
    "sg:postcode":"27409",
    "sg:province":"NC",
    "sg:tags":[
        "agency"
    ],
    "wof:name":"Jazz Marketing",
    "wof:placetype":"venue"
},
  "geometry": {"coordinates":[-79.91898,36.079579],"type":"Point"}
}