{
  "type": "Feature",
  "properties": {
    "iso:country":"US",
    "sg:address":"310 Englewood Dr",
    "sg:city":"Wilmington",
    "sg:classifiers":[
        {
            "category":"Professional",
            "subcategory":"Computer Services",
            "type":"Services"
        }
    ],
    "sg:phone":"+1   ",
    "sg:postcode":"28409",
    "sg:province":"NC",
    "sg:tags":[
        "design",
        "system"
    ],
    "wof:name":"Crystal Cave Computers",
    "wof:placetype":"venue"
},
  "geometry": {"coordinates":[-77.862275,34.204172],"type":"Point"}
}