{
  "type": "Feature",
  "properties": {
    "addr:full":"127 Colonial Dr Burlington NC 27215",
    "addr:housenumber":"127",
    "addr:postcode":"27215",
    "addr:street":"Colonial Dr",
    "iso:country":"US",
    "sg:address":"127 Colonial Dr",
    "sg:city":"Burlington",
    "sg:classifiers":[
        {
            "category":"Shopping",
            "subcategory":"Gifts & Souvenirs",
            "type":"Retail Goods"
        }
    ],
    "sg:phone":"+1 336 584 9507",
    "sg:postcode":"27215",
    "sg:province":"NC",
    "sg:tags":[
        "party",
        "supply"
    ],
    "wof:name":"Louise's Hallmark Shop",
    "wof:placetype":"venue"
},
  "geometry": {"coordinates":[-79.475797,36.082026],"type":"Point"}
}