{
  "type": "Feature",
  "properties": {
    "iso:country":"US",
    "sg:address":"309 Northside Dr",
    "sg:city":"Lexington",
    "sg:classifiers":[
        {
            "category":"Manufacturing",
            "subcategory":"Lumber",
            "type":"Manufacturing & Wholesale Goods"
        }
    ],
    "sg:phone":"+1 336 877 2099",
    "sg:postcode":"27295",
    "sg:province":"NC",
    "sg:tags":[
        "operation",
        "timber",
        "tract"
    ],
    "wof:name":"Hodges Tree Farm",
    "wof:placetype":"venue"
},
  "geometry": {"coordinates":[-80.26411,35.856028],"type":"Point"}
}