{
  "type": "Feature",
  "properties": {
    "addr:full":"1236 Joannas Ct Charlotte NC 28214",
    "addr:housenumber":"1236",
    "addr:postcode":"28214",
    "addr:street":"Joannas Ct",
    "iso:country":"US",
    "sg:address":"1236 Joannas Ct",
    "sg:city":"Charlotte",
    "sg:classifiers":[
        {
            "category":"Professional",
            "subcategory":"Management & Consulting",
            "type":"Services"
        },
        {
            "category":"Social Services",
            "type":"Services"
        }
    ],
    "sg:phone":"+1 704 399 5545",
    "sg:postcode":"28214",
    "sg:province":"NC",
    "sg:tags":[
        "consultant",
        "educational"
    ],
    "wof:name":"Unity Children & Family Servic",
    "wof:placetype":"venue"
},
  "geometry": {"coordinates":[-80.921055,35.26785],"type":"Point"}
}