{
  "type": "Feature",
  "properties": {
    "iso:country":"US",
    "sg:address":"6800 Towbridge Rd",
    "sg:city":"Fayetteville",
    "sg:classifiers":[
        {
            "category":"Professional",
            "subcategory":"Detective & Security Services",
            "type":"Services"
        }
    ],
    "sg:phone":"+1 910 424 0542",
    "sg:postcode":"28306",
    "sg:province":"NC",
    "sg:tags":[
        "car"
    ],
    "wof:name":"Gates Four Guard House",
    "wof:placetype":"venue"
},
  "geometry": {"coordinates":[-79.008336,34.994384],"type":"Point"}
}