{
  "type": "Feature",
  "properties": {
    "iso:country":"US",
    "sg:address":"2928 Randleman Rd",
    "sg:city":"Greensboro",
    "sg:classifiers":[
        {
            "category":"Restaurant",
            "type":"Food & Drink"
        }
    ],
    "sg:phone":"+1 336 378 9503",
    "sg:postcode":"27406",
    "sg:province":"NC",
    "wof:name":"T Cooper's Ny Deli",
    "wof:placetype":"venue"
},
  "geometry": {"coordinates":[-79.80445899999999,36.015451],"type":"Point"}
}