{
  "type": "Feature",
  "properties": {
    "iso:country":"US",
    "sg:address":"660 Roberts Rd",
    "sg:city":"Newport",
    "sg:classifiers":[
        {
            "category":"Building & Trades",
            "subcategory":"Landscaping Services",
            "type":"Services"
        }
    ],
    "sg:phone":"+1 252 223 2275",
    "sg:postcode":"28570",
    "sg:province":"NC",
    "sg:tags":[
        "landscape"
    ],
    "wof:name":"Jeffrey W Shultz",
    "wof:placetype":"venue"
},
  "geometry": {"coordinates":[-76.88229,34.77695],"type":"Point"}
}