{
  "type": "Feature",
  "properties": {
    "addr:full":"13925 Erwin Rd Charlotte NC 28273",
    "addr:housenumber":"13925",
    "addr:postcode":"28273",
    "addr:street":"Erwin Rd",
    "iso:country":"US",
    "sg:address":"13925 Erwin Rd",
    "sg:city":"Charlotte",
    "sg:classifiers":[
        {
            "category":"Education",
            "subcategory":"School",
            "type":"Public Place"
        }
    ],
    "sg:phone":"+1 704 583 5499",
    "sg:postcode":"28273",
    "sg:province":"NC",
    "sg:website":"www.walnutgrovechristianschool.com",
    "wof:name":"Walnut Grove Christian School",
    "wof:placetype":"venue"
},
  "geometry": {"coordinates":[-80.97684,35.116405],"type":"Point"}
}