{
  "type": "Feature",
  "properties": {
    "addr:full":"327 Long Creek Rd Bessemer City NC 28016",
    "addr:housenumber":"327",
    "addr:postcode":"28016",
    "addr:street":"Long Creek Rd",
    "iso:country":"US",
    "sg:address":"327 Long Creek Rd",
    "sg:city":"Bessemer City",
    "sg:classifiers":[
        {
            "category":"Building & Trades",
            "subcategory":"Landscaping Services",
            "type":"Services"
        }
    ],
    "sg:phone":"+1 704 629 4325",
    "sg:postcode":"28016",
    "sg:province":"NC",
    "wof:name":"Long Creek Lawn Service",
    "wof:placetype":"venue"
},
  "geometry": {"coordinates":[-81.31539600000001,35.285147],"type":"Point"}
}