{
  "type": "Feature",
  "properties": {
    "iso:country":"US",
    "sg:address":"1819 Saint Marys St",
    "sg:city":"Raleigh",
    "sg:classifiers":[
        {
            "category":"Real Estate",
            "subcategory":"Real Estate Agent",
            "type":"Services"
        }
    ],
    "sg:phone":"+1 919 828 2508",
    "sg:postcode":"27608",
    "sg:province":"NC",
    "wof:name":"Crescent Real Estate Co",
    "wof:placetype":"venue"
},
  "geometry": {"coordinates":[-78.653756,35.804202],"type":"Point"}
}