{
  "type": "Feature",
  "properties": {
    "iso:country":"US",
    "sg:address":"167 N Canterbury Rd",
    "sg:city":"Charlotte",
    "sg:classifiers":[
        {
            "category":"Real Estate",
            "subcategory":"Architect",
            "type":"Services"
        }
    ],
    "sg:phone":"+1   ",
    "sg:postcode":"28211",
    "sg:province":"NC",
    "sg:tags":[
        "architectural"
    ],
    "wof:name":"Cooper Kirby Interior Designs",
    "wof:placetype":"venue"
},
  "geometry": {"coordinates":[-80.8044,35.182781],"type":"Point"}
}