{
  "type": "Feature",
  "properties": {
    "iso:country":"US",
    "sg:address":"6300 Albemarle Rd",
    "sg:city":"Charlotte",
    "sg:classifiers":[
        {
            "category":"Autos & Motor Vehicles",
            "subcategory":"Fuel & Gas Station",
            "type":"Retail Goods"
        }
    ],
    "sg:phone":"+1 704 568 1422",
    "sg:postcode":"28212",
    "sg:province":"NC",
    "sg:tags":[
        "station",
        "gasoline"
    ],
    "wof:name":"Crown Central Petro Stn 019",
    "wof:placetype":"venue"
},
  "geometry": {"coordinates":[-80.73463099999999,35.202801],"type":"Point"}
}