{
  "type": "Feature",
  "properties": {
    "addr:full":"11504 Providence Rd Charlotte NC 28277",
    "addr:housenumber":"11504",
    "addr:postcode":"28277",
    "addr:street":"Providence Rd",
    "iso:country":"US",
    "sg:address":"11504 Providence Rd",
    "sg:city":"Charlotte",
    "sg:classifiers":[
        {
            "category":"Professional",
            "type":"Services"
        }
    ],
    "sg:phone":"+1 704 844 2412",
    "sg:postcode":"28277",
    "sg:province":"NC",
    "sg:tags":[
        "establishment"
    ],
    "wof:name":"Crosland Group",
    "wof:placetype":"venue"
},
  "geometry": {"coordinates":[-80.769684,35.05311],"type":"Point"}
}