{
  "type": "Feature",
  "properties": {
    "addr:full":"539 Hairston Rd Lexington NC 27295",
    "addr:housenumber":"539",
    "addr:postcode":"27295",
    "addr:street":"Hairston Rd",
    "iso:country":"US",
    "sg:address":"539 Hairston Rd",
    "sg:city":"Lexington",
    "sg:classifiers":[
        {
            "category":"Organizations",
            "subcategory":"Religious Organization",
            "type":"Services"
        }
    ],
    "sg:phone":"+1 336 853 6655",
    "sg:postcode":"27295",
    "sg:province":"NC",
    "sg:tags":[
        "church"
    ],
    "wof:name":"Buncomb Baptist Church",
    "wof:placetype":"venue"
},
  "geometry": {"coordinates":[-80.415193,35.826157],"type":"Point"}
}