{
  "type": "Feature",
  "properties": {
    "addr:full":"128 Applewood Rd Dallas NC 28034",
    "addr:housenumber":"128",
    "addr:postcode":"28034",
    "addr:street":"Applewood Rd",
    "iso:country":"US",
    "sg:address":"128 Applewood Rd",
    "sg:city":"Dallas",
    "sg:classifiers":[
        {
            "category":"Retail",
            "subcategory":"Veterinary Services",
            "type":"Services"
        }
    ],
    "sg:phone":"+1 704 922 0532",
    "sg:postcode":"28034",
    "sg:province":"NC",
    "sg:tags":[
        "hospital",
        "animal"
    ],
    "wof:name":"Applewood Veterinary Hospital",
    "wof:placetype":"venue"
},
  "geometry": {"coordinates":[-81.22172,35.320518],"type":"Point"}
}