{
  "type": "Feature",
  "properties": {
    "iso:country":"US",
    "sg:address":"7210 Wrightsville Ave",
    "sg:city":"Wilmington",
    "sg:classifiers":[
        {
            "category":"Personal",
            "subcategory":"Beauty Salon",
            "type":"Services"
        }
    ],
    "sg:phone":"+1   ",
    "sg:postcode":"28403",
    "sg:province":"NC",
    "sg:tags":[
        "shop"
    ],
    "wof:name":"Looney Bin",
    "wof:placetype":"venue"
},
  "geometry": {"coordinates":[-77.815167,34.219681],"type":"Point"}
}