{
  "type": "Feature",
  "properties": {
    "addr:full":"801 Peanut Plant Rd Elizabethtown NC 28337",
    "addr:housenumber":"801",
    "addr:postcode":"28337",
    "addr:street":"Peanut Plant Rd",
    "iso:country":"US",
    "sg:address":"801 Peanut Plant Rd",
    "sg:city":"Elizabethtown",
    "sg:classifiers":[
        {
            "category":"Organizations",
            "subcategory":"Religious Organization",
            "type":"Services"
        }
    ],
    "sg:phone":"+1 910 645 4905",
    "sg:postcode":"28337",
    "sg:province":"NC",
    "sg:tags":[
        "church"
    ],
    "wof:name":"New Shiloh Church Of Christ",
    "wof:placetype":"venue"
},
  "geometry": {"coordinates":[-78.62572299999999,34.622508],"type":"Point"}
}