{
  "type": "Feature",
  "properties": {
    "addr:full":"8905 Creekstone Ct Raleigh NC 27615",
    "addr:housenumber":"8905",
    "addr:postcode":"27615",
    "addr:street":"Creekstone Ct",
    "iso:country":"US",
    "sg:address":"8905 Creekstone Ct",
    "sg:city":"Raleigh",
    "sg:classifiers":[
        {
            "category":"Wholesale",
            "subcategory":"Chemicals & Plastics",
            "type":"Manufacturing & Wholesale Goods"
        }
    ],
    "sg:phone":"+1 919 846 7787",
    "sg:postcode":"27615",
    "sg:province":"NC",
    "wof:name":"Dow Chemical",
    "wof:placetype":"venue"
},
  "geometry": {"coordinates":[-78.604049,35.900164],"type":"Point"}
}