{
  "type": "Feature",
  "properties": {
    "addr:full":"628 Holly Springs Rd Holly Springs NC 27540",
    "addr:housenumber":"628",
    "addr:postcode":"27540",
    "addr:street":"Holly Springs Rd",
    "iso:country":"US",
    "sg:address":"628 Holly Springs Rd",
    "sg:city":"Holly Springs",
    "sg:classifiers":[
        {
            "category":"Personal",
            "subcategory":"Beauty Salon",
            "type":"Services"
        }
    ],
    "sg:phone":"+1 919 567 2855",
    "sg:postcode":"27540",
    "sg:province":"NC",
    "sg:tags":[
        "manicuring"
    ],
    "wof:name":"Nail Experts",
    "wof:placetype":"venue"
},
  "geometry": {"coordinates":[-78.825968,35.654719],"type":"Point"}
}