{
  "type": "Feature",
  "properties": {
    "addr:full":"3371 US Hwy 70 W Goldsboro NC 27530",
    "addr:housenumber":"3371",
    "addr:postcode":"27530",
    "addr:street":"Us Hwy 70 W",
    "iso:country":"US",
    "sg:address":"3371 US Hwy 70 W",
    "sg:city":"Goldsboro",
    "sg:classifiers":[
        {
            "category":"Shopping",
            "subcategory":"Bicycles & Sporting Goods",
            "type":"Retail Goods"
        }
    ],
    "sg:phone":"+1 919 736 7363",
    "sg:postcode":"27530",
    "sg:province":"NC",
    "sg:tags":[
        "equipment",
        "camping"
    ],
    "wof:name":"Sasser Camping Ctr LLC",
    "wof:placetype":"venue"
},
  "geometry": {"coordinates":[-78.083648,35.438572],"type":"Point"}
}