{
  "type": "Feature",
  "properties": {
    "addr:full":"202 S Cedar St Lincolnton NC 28092",
    "addr:housenumber":"202",
    "addr:postcode":"28092",
    "addr:street":"S Cedar St",
    "iso:country":"US",
    "sg:address":"202 S Cedar St",
    "sg:city":"Lincolnton",
    "sg:classifiers":[
        {
            "category":"Utilities",
            "subcategory":"Electric",
            "type":"Services"
        }
    ],
    "sg:phone":"+1 704 735 5381",
    "sg:postcode":"28092",
    "sg:province":"NC",
    "sg:tags":[
        "company"
    ],
    "sg:website":"www.remc.com",
    "wof:name":"Rutherford Electric Corp",
    "wof:placetype":"venue"
},
  "geometry": {"coordinates":[-81.252054,35.472152],"type":"Point"}
}