{
  "type": "Feature",
  "properties": {
    "iso:country":"US",
    "sg:address":"321 Sunset Dr",
    "sg:city":"Blowing Rock",
    "sg:classifiers":[
        {
            "category":"Food & Beverages",
            "subcategory":"Groceries & Convenience Stores",
            "type":"Retail Goods"
        }
    ],
    "sg:phone":"+1 828 295 9676",
    "sg:postcode":"28605",
    "sg:province":"NC",
    "wof:name":"Scotchman 103",
    "wof:placetype":"venue"
},
  "geometry": {"coordinates":[-81.67228900000001,36.132641],"type":"Point"}
}