{
  "type": "Feature",
  "properties": {
    "iso:country":"US",
    "sg:address":"1411 Welborn St",
    "sg:city":"High Point",
    "sg:classifiers":[
        {
            "category":"Personal",
            "subcategory":"Beauty Salon",
            "type":"Services"
        }
    ],
    "sg:phone":"+1 336 869 0375",
    "sg:postcode":"27262",
    "sg:province":"NC",
    "wof:name":"Exquisite Nails",
    "wof:placetype":"venue"
},
  "geometry": {"coordinates":[-80.017642,35.975469],"type":"Point"}
}