{
  "type": "Feature",
  "properties": {
    "iso:country":"US",
    "sg:address":"35 Edith Ave",
    "sg:city":"Winston Salem",
    "sg:classifiers":[
        {
            "category":"Building & Trades",
            "subcategory":"Construction",
            "type":"Services"
        }
    ],
    "sg:phone":"+1 336 727 1234",
    "sg:postcode":"27106",
    "sg:province":"NC",
    "sg:tags":[
        "contractor"
    ],
    "wof:name":"Dry Restrtn Sys",
    "wof:placetype":"venue"
},
  "geometry": {"coordinates":[-80.308435,36.153575],"type":"Point"}
}