{
  "type": "Feature",
  "properties": {
    "iso:country":"US",
    "sg:address":"4345 Fish Pond Rd",
    "sg:city":"Salisbury",
    "sg:classifiers":[
        {
            "category":"Personal",
            "type":"Services"
        }
    ],
    "sg:phone":"+1   ",
    "sg:postcode":"28146",
    "sg:province":"NC",
    "wof:name":"Tan 2 Limit",
    "wof:placetype":"venue"
},
  "geometry": {"coordinates":[-80.423772,35.618894],"type":"Point"}
}