{
  "type": "Feature",
  "properties": {
    "addr:full":"4107 Sacramento Dr Greensboro NC 27406",
    "addr:housenumber":"4107",
    "addr:postcode":"27406",
    "addr:street":"Sacramento Dr",
    "iso:country":"US",
    "sg:address":"4107 Sacramento Dr",
    "sg:city":"Greensboro",
    "sg:classifiers":[
        {
            "category":"Wholesale",
            "subcategory":"Office Equipment",
            "type":"Manufacturing & Wholesale Goods"
        }
    ],
    "sg:phone":"+1 336 292 4653",
    "sg:postcode":"27406",
    "sg:province":"NC",
    "sg:tags":[
        "repair"
    ],
    "wof:name":"ADC Joes Lock & Key",
    "wof:placetype":"venue"
},
  "geometry": {"coordinates":[-79.83227599999999,36.012895],"type":"Point"}
}