{
  "type": "Feature",
  "properties": {
    "iso:country":"US",
    "sg:address":"148 Wakelon St",
    "sg:city":"Zebulon",
    "sg:classifiers":[
        {
            "category":"Personal",
            "subcategory":"Beauty Salon",
            "type":"Services"
        }
    ],
    "sg:phone":"+1 919 269 9010",
    "sg:postcode":"27597",
    "sg:province":"NC",
    "wof:name":"Raffles Salon # 135",
    "wof:placetype":"venue"
},
  "geometry": {"coordinates":[-78.31703,35.833096],"type":"Point"}
}