{
  "type": "Feature",
  "properties": {
    "addr:full":"2215 Cumberland Rd Fayetteville NC 28306",
    "addr:housenumber":"2215",
    "addr:postcode":"28306",
    "addr:street":"Cumberland Rd",
    "iso:country":"US",
    "sg:address":"2215 Cumberland Rd",
    "sg:city":"Fayetteville",
    "sg:classifiers":[
        {
            "category":"Real Estate",
            "subcategory":"Real Estate Agent",
            "type":"Services"
        }
    ],
    "sg:phone":"+1 910 485 6892",
    "sg:postcode":"28306",
    "sg:province":"NC",
    "wof:name":"Frank Maness Rentals",
    "wof:placetype":"venue"
},
  "geometry": {"coordinates":[-78.904652,35.02161],"type":"Point"}
}