{
  "type": "Feature",
  "properties": {
    "iso:country":"US",
    "sg:address":"205 Sage Rd Ste 203",
    "sg:city":"Chapel Hill",
    "sg:classifiers":[
        {
            "category":"Health Services",
            "subcategory":"Health Practitioner",
            "type":"Services"
        }
    ],
    "sg:phone":"+1 919 928 0204",
    "sg:postcode":"27514",
    "sg:province":"NC",
    "sg:tags":[
        "therapy",
        "physical"
    ],
    "sg:website":"www.emergeachildsplace.com",
    "wof:name":"Emerge-A Child's Place",
    "wof:placetype":"venue"
},
  "geometry": {"coordinates":[-79.014477,35.948707],"type":"Point"}
}