{
  "type": "Feature",
  "properties": {
    "iso:country":"US",
    "sg:address":"3271 S Church St",
    "sg:city":"Burlington",
    "sg:classifiers":[
        {
            "category":"Professional",
            "type":"Services"
        }
    ],
    "sg:phone":"+1 336 524 8860",
    "sg:postcode":"27215",
    "sg:province":"NC",
    "wof:name":"Vetsopoulos GE Orge",
    "wof:placetype":"venue"
},
  "geometry": {"coordinates":[-79.503939,36.080997],"type":"Point"}
}