{
  "type": "Feature",
  "properties": {
    "iso:country":"US",
    "sg:address":"2824 Olde Whitehall Rd",
    "sg:city":"Charlotte",
    "sg:classifiers":[
        {
            "category":"Retail",
            "subcategory":"Portrait Studio",
            "type":"Services"
        }
    ],
    "sg:phone":"+1   ",
    "sg:postcode":"28273",
    "sg:province":"NC",
    "sg:tags":[
        "photo"
    ],
    "wof:name":"Forever Yours Photography",
    "wof:placetype":"venue"
},
  "geometry": {"coordinates":[-80.92990899999999,35.15542],"type":"Point"}
}