{
  "type": "Feature",
  "properties": {
    "iso:country":"US",
    "sg:address":"6008 Triangle Dr",
    "sg:city":"Raleigh",
    "sg:classifiers":[
        {
            "category":"Professional",
            "type":"Services"
        },
        {
            "category":"Professional",
            "subcategory":"Research",
            "type":"Services"
        }
    ],
    "sg:phone":"+1 919 781 6315",
    "sg:postcode":"27617",
    "sg:province":"NC",
    "sg:tags":[
        "establishment",
        "medical",
        "design",
        "devices"
    ],
    "wof:name":"Innovative Devices LLC",
    "wof:placetype":"venue"
},
  "geometry": {"coordinates":[-78.745328,35.896353],"type":"Point"}
}