{
  "type": "Feature",
  "properties": {
    "addr:full":"70 Pisgah Hwy Candler NC 28711",
    "addr:housenumber":"70",
    "addr:postcode":"28711",
    "addr:street":"Pisgah Hwy",
    "iso:country":"US",
    "sg:address":"70 Pisgah Hwy",
    "sg:city":"Candler",
    "sg:classifiers":[
        {
            "category":"Professional",
            "subcategory":"Lawyer & Legal Services",
            "type":"Services"
        }
    ],
    "sg:phone":"+1 828 667 5476",
    "sg:postcode":"28711",
    "sg:province":"NC",
    "sg:tags":[
        "attorney"
    ],
    "wof:name":"Sutton Firm",
    "wof:placetype":"venue"
},
  "geometry": {"coordinates":[-82.68446299999999,35.540431],"type":"Point"}
}