{
  "type": "Feature",
  "properties": {
    "iso:country":"US",
    "sg:address":"3590 Sulphur Springs Rd",
    "sg:city":"Hiddenite",
    "sg:classifiers":[
        {
            "category":"Building & Trades",
            "subcategory":"Plumbing",
            "type":"Services"
        }
    ],
    "sg:phone":"+1 828 635 0090",
    "sg:postcode":"28636",
    "sg:province":"NC",
    "sg:tags":[
        "contractor"
    ],
    "wof:name":"Gullett Plumbing Inc",
    "wof:placetype":"venue"
},
  "geometry": {"coordinates":[-81.079397,35.947776],"type":"Point"}
}