{
  "type": "Feature",
  "properties": {
    "addr:full":"1122 Randolph St Thomasville NC 27360",
    "addr:housenumber":"1122",
    "addr:postcode":"27360",
    "addr:street":"Randolph St",
    "iso:country":"US",
    "sg:address":"1122 Randolph St",
    "sg:city":"Thomasville",
    "sg:classifiers":[
        {
            "category":"Manufacturing",
            "subcategory":"Leather Goods",
            "type":"Manufacturing & Wholesale Goods"
        }
    ],
    "sg:phone":"+1 336 475 6525",
    "sg:postcode":"27360",
    "sg:province":"NC",
    "sg:tags":[
        "shoes",
        "supply"
    ],
    "wof:name":"Shoe Show",
    "wof:placetype":"venue"
},
  "geometry": {"coordinates":[-80.07253,35.86694],"type":"Point"}
}