{
  "type": "Feature",
  "properties": {
    "iso:country":"US",
    "sg:address":"4469 State Hwy 87",
    "sg:city":"Sanford",
    "sg:classifiers":[
        {
            "category":"Building & Trades",
            "subcategory":"Construction",
            "type":"Services"
        }
    ],
    "sg:phone":"+1 919 498 0660",
    "sg:postcode":"27332",
    "sg:province":"NC",
    "sg:tags":[
        "general",
        "contractor"
    ],
    "wof:name":"Carthage Homes",
    "wof:placetype":"venue"
},
  "geometry": {"coordinates":[-79.120296,35.424445],"type":"Point"}
}