{
  "type": "Feature",
  "properties": {
    "addr:full":"2966 S Church St Burlington NC 27215",
    "addr:housenumber":"2966",
    "addr:postcode":"27215",
    "addr:street":"S Church St",
    "iso:country":"US",
    "sg:address":"2966 S Church St",
    "sg:city":"Burlington",
    "sg:classifiers":[
        {
            "category":"Wholesale",
            "subcategory":"Electrical",
            "type":"Manufacturing & Wholesale Goods"
        }
    ],
    "sg:phone":"+1 336 375 9399",
    "sg:postcode":"27215",
    "sg:province":"NC",
    "sg:tags":[
        "alarm",
        "burglar",
        "system"
    ],
    "wof:name":"Inovative Sounds & Security",
    "wof:placetype":"venue"
},
  "geometry": {"coordinates":[-79.49529699999999,36.080125],"type":"Point"}
}