{
  "type": "Feature",
  "properties": {
    "addr:full":"1505 N Cannon Blvd Kannapolis NC 28083",
    "addr:housenumber":"1505",
    "addr:postcode":"28083",
    "addr:street":"N Cannon Blvd",
    "iso:country":"US",
    "sg:address":"1505 N Cannon Blvd",
    "sg:city":"Kannapolis",
    "sg:classifiers":[
        {
            "category":"Wholesale",
            "subcategory":"Vending Machines",
            "type":"Manufacturing & Wholesale Goods"
        },
        {
            "category":"Recreation",
            "subcategory":"Arcade",
            "type":"Entertainment"
        }
    ],
    "sg:phone":"+1 704 933 7376",
    "sg:postcode":"28083",
    "sg:province":"NC",
    "sg:tags":[
        "operated",
        "phonograph",
        "amusement",
        "devices",
        "lease"
    ],
    "wof:name":"Weaver & Mc Guire Amusement Co",
    "wof:placetype":"venue"
},
  "geometry": {"coordinates":[-80.612334,35.518118],"type":"Point"}
}