{
  "type": "Feature",
  "properties": {
    "iso:country":"US",
    "sg:address":"1301 N Main St",
    "sg:city":"High Point",
    "sg:classifiers":[
        {
            "category":"Retail",
            "subcategory":"Portrait Studio",
            "type":"Services"
        }
    ],
    "sg:phone":"+1   ",
    "sg:postcode":"27262",
    "sg:province":"NC",
    "sg:tags":[
        "photo"
    ],
    "wof:name":"Emerwoods Studio",
    "wof:placetype":"venue"
},
  "geometry": {"coordinates":[-80.017393,35.972972],"type":"Point"}
}