{
  "type": "Feature",
  "properties": {
    "iso:country":"US",
    "sg:address":"115 N Sterling St",
    "sg:city":"Morganton",
    "sg:classifiers":[
        {
            "category":"Banks & Credit Unions",
            "subcategory":"Bank",
            "type":"Services"
        }
    ],
    "sg:phone":"+1 828 438 4663",
    "sg:postcode":"28655",
    "sg:province":"NC",
    "sg:tags":[
        "mortgage",
        "loan",
        "banker",
        "real estate"
    ],
    "wof:name":"Home Equity Stores of NC",
    "wof:placetype":"venue"
},
  "geometry": {"coordinates":[-81.68779600000001,35.745487],"type":"Point"}
}