{
  "type": "Feature",
  "properties": {
    "addr:full":"161 Hunters Ridge Rd Burnsville NC 28753",
    "addr:housenumber":"161",
    "addr:postcode":"28753",
    "addr:street":"Hunters Ridge Rd",
    "iso:country":"US",
    "sg:address":"161 Hunters Ridge Rd",
    "sg:city":"Burnsville",
    "sg:classifiers":[
        {
            "category":"Professional",
            "subcategory":"Computer Services",
            "type":"Services"
        }
    ],
    "sg:phone":"+1   ",
    "sg:postcode":"28753",
    "sg:province":"NC",
    "sg:tags":[
        "related"
    ],
    "wof:name":"Comp-U-Play",
    "wof:placetype":"venue"
},
  "geometry": {"coordinates":[-82.613294,35.777052],"type":"Point"}
}