{
  "type": "Feature",
  "properties": {
    "addr:full":"175 W End Ln West End NC 27376",
    "addr:housenumber":"175",
    "addr:postcode":"27376",
    "addr:street":"W End Ln",
    "iso:country":"US",
    "sg:address":"175 W End Ln",
    "sg:city":"West End",
    "sg:classifiers":[
        {
            "category":"Building & Trades",
            "subcategory":"Construction",
            "type":"Services"
        }
    ],
    "sg:phone":"+1 910 673 8136",
    "sg:postcode":"27376",
    "sg:province":"NC",
    "sg:tags":[
        "work",
        "carpentry"
    ],
    "wof:name":"Wood In The Works",
    "wof:placetype":"venue"
},
  "geometry": {"coordinates":[-79.56402199999999,35.23956],"type":"Point"}
}