{
  "type": "Feature",
  "properties": {
    "iso:country":"US",
    "sg:address":"8606 Hillsville Rd",
    "sg:city":"Trinity",
    "sg:classifiers":[
        {
            "category":"Food & Beverages",
            "subcategory":"Groceries & Convenience Stores",
            "type":"Retail Goods"
        }
    ],
    "sg:phone":"+1 336 861 1756",
    "sg:postcode":"27370",
    "sg:province":"NC",
    "wof:name":"Family Mart",
    "wof:placetype":"venue"
},
  "geometry": {"coordinates":[-79.93953399999999,35.841096],"type":"Point"}
}