{
  "type": "Feature",
  "properties": {
    "addr:full":"602 Jones Ferry Rd Carrboro NC 27510",
    "addr:housenumber":"602",
    "addr:postcode":"27510",
    "addr:street":"Jones Ferry Rd",
    "iso:country":"US",
    "sg:address":"602 Jones Ferry Rd",
    "sg:city":"Carrboro",
    "sg:classifiers":[
        {
            "category":"Restaurant",
            "type":"Food & Drink"
        }
    ],
    "sg:menulink":"http://www.allmenus.com/nc/chapel-hill/137176-subway/menu/",
    "sg:phone":"+1 919 929 2288",
    "sg:postcode":"27510",
    "sg:province":"NC",
    "sg:tags":[
        "american",
        "sandwich"
    ],
    "wof:name":"Subway",
    "wof:placetype":"venue"
},
  "geometry": {"coordinates":[-79.08783,35.905456],"type":"Point"}
}