{
  "type": "Feature",
  "properties": {
    "addr:full":"1615 N Main St Tarboro NC 27886",
    "addr:housenumber":"1615",
    "addr:postcode":"27886",
    "addr:street":"N Main St",
    "iso:country":"US",
    "sg:address":"1615 N Main St",
    "sg:city":"Tarboro",
    "sg:classifiers":[
        {
            "category":"Organizations",
            "subcategory":"Religious Organization",
            "type":"Services"
        }
    ],
    "sg:phone":"+1 252 824 7731",
    "sg:postcode":"27886",
    "sg:province":"NC",
    "sg:tags":[
        "church"
    ],
    "wof:name":"Upper Room Revival Center",
    "wof:placetype":"venue"
},
  "geometry": {"coordinates":[-77.54139000000001,35.908019],"type":"Point"}
}