{
  "type": "Feature",
  "properties": {
    "addr:full":"4316 Griffith Rd Monroe NC 28112",
    "addr:housenumber":"4316",
    "addr:postcode":"28112",
    "addr:street":"Griffith Rd",
    "iso:country":"US",
    "sg:address":"4316 Griffith Rd",
    "sg:city":"Monroe",
    "sg:classifiers":[
        {
            "category":"Retail",
            "subcategory":"Repair Shop",
            "type":"Services"
        }
    ],
    "sg:phone":"+1 704 764 3273",
    "sg:postcode":"28112",
    "sg:province":"NC",
    "sg:tags":[
        "tank",
        "septic",
        "softening",
        "i",
        "water",
        "equipment",
        "conditioning"
    ],
    "wof:name":"A Water Outlet Inc",
    "wof:placetype":"venue"
},
  "geometry": {"coordinates":[-80.57805,34.907339],"type":"Point"}
}