{
  "type": "Feature",
  "properties": {
    "iso:country":"US",
    "sg:address":"117 Sunset Ave",
    "sg:city":"Asheboro",
    "sg:classifiers":[
        {
            "category":"Professional",
            "subcategory":"Lawyer & Legal Services",
            "type":"Services"
        }
    ],
    "sg:phone":"+1 336 629 2121",
    "sg:postcode":"27203",
    "sg:province":"NC",
    "sg:tags":[
        "attorney"
    ],
    "wof:name":"Robins Thomas D Atty",
    "wof:placetype":"venue"
},
  "geometry": {"coordinates":[-79.814899,35.705618],"type":"Point"}
}