{
  "type": "Feature",
  "properties": {
    "iso:country":"US",
    "sg:address":"4811 Bridle Ridge Ln",
    "sg:city":"Charlotte",
    "sg:classifiers":[
        {
            "category":"Professional",
            "type":"Services"
        }
    ],
    "sg:phone":"+1 704 717 2445",
    "sg:postcode":"28269",
    "sg:province":"NC",
    "wof:name":"Wing Zone",
    "wof:placetype":"venue"
},
  "geometry": {"coordinates":[-80.821117,35.344812],"type":"Point"}
}