{
  "type": "Feature",
  "properties": {
    "addr:full":"200 Maple St Cleveland NC 27013",
    "addr:housenumber":"200",
    "addr:postcode":"27013",
    "addr:street":"Maple St",
    "iso:country":"US",
    "sg:address":"200 Maple St",
    "sg:city":"Cleveland",
    "sg:classifiers":[
        {
            "category":"Organizations",
            "subcategory":"Religious Organization",
            "type":"Services"
        }
    ],
    "sg:phone":"+1 704 278 4586",
    "sg:postcode":"27013",
    "sg:province":"NC",
    "sg:tags":[
        "church"
    ],
    "wof:name":"Cleveland First Baptist Church",
    "wof:placetype":"venue"
},
  "geometry": {"coordinates":[-80.680603,35.734077],"type":"Point"}
}