{
  "type": "Feature",
  "properties": {
    "addr:full":"117 Mount Lori Dr Highlands NC 28741",
    "addr:housenumber":"117",
    "addr:postcode":"28741",
    "addr:street":"Mount Lori Dr",
    "iso:country":"US",
    "sg:address":"117 Mount Lori Dr",
    "sg:city":"Highlands",
    "sg:classifiers":[
        {
            "category":"Real Estate",
            "subcategory":"Architect",
            "type":"Services"
        }
    ],
    "sg:phone":"+1 828 526 5177",
    "sg:postcode":"28741",
    "sg:province":"NC",
    "wof:name":"Ziebarth Architecture",
    "wof:placetype":"venue"
},
  "geometry": {"coordinates":[-83.214704,35.058571],"type":"Point"}
}