{
  "type": "Feature",
  "properties": {
    "addr:full":"2405 Morganton Rd Fayetteville NC 28303",
    "addr:housenumber":"2405",
    "addr:postcode":"28303",
    "addr:street":"Morganton Rd",
    "iso:country":"US",
    "sg:address":"2405 Morganton Rd",
    "sg:city":"Fayetteville",
    "sg:classifiers":[
        {
            "category":"Manufacturing",
            "subcategory":"Printing",
            "type":"Manufacturing & Wholesale Goods"
        }
    ],
    "sg:phone":"+1 910 484 0281",
    "sg:postcode":"28303",
    "sg:province":"NC",
    "sg:tags":[
        "publishing"
    ],
    "wof:name":"C & R Publishing Co Inc",
    "wof:placetype":"venue"
},
  "geometry": {"coordinates":[-78.92666699999999,35.063936],"type":"Point"}
}