{
  "type": "Feature",
  "properties": {
    "addr:full":"245 Taylors Park Rd Lexington NC 27292",
    "addr:housenumber":"245",
    "addr:postcode":"27292",
    "addr:street":"Taylors Park Rd",
    "iso:country":"US",
    "sg:address":"245 Taylors Park Rd",
    "sg:city":"Lexington",
    "sg:classifiers":[
        {
            "category":"Building & Trades",
            "subcategory":"Plumbing",
            "type":"Services"
        }
    ],
    "sg:phone":"+1 336 357 7555",
    "sg:postcode":"27292",
    "sg:province":"NC",
    "sg:tags":[
        "contractor"
    ],
    "wof:name":"All Seasons Heating & Cooling",
    "wof:placetype":"venue"
},
  "geometry": {"coordinates":[-80.267386,35.76573],"type":"Point"}
}