{
  "type": "Feature",
  "properties": {
    "iso:country":"US",
    "sg:address":"3956 Thomasville Rd",
    "sg:city":"Winston Salem",
    "sg:classifiers":[
        {
            "category":"Autos & Motor Vehicles",
            "subcategory":"Automobile Sales",
            "type":"Retail Goods"
        }
    ],
    "sg:phone":"+1 336 399 0014",
    "sg:postcode":"27107",
    "sg:province":"NC",
    "sg:tags":[
        "car",
        "dealer"
    ],
    "wof:name":"DMC Auto Sales",
    "wof:placetype":"venue"
},
  "geometry": {"coordinates":[-80.19340200000001,36.045066],"type":"Point"}
}