{
  "type": "Feature",
  "properties": {
    "iso:country":"US",
    "sg:address":"611 Highlands Rd",
    "sg:city":"Franklin",
    "sg:classifiers":[
        {
            "category":"Shopping",
            "type":"Retail Goods"
        }
    ],
    "sg:phone":"+1 828 369 2871",
    "sg:postcode":"28734",
    "sg:province":"NC",
    "sg:tags":[
        "chemical",
        "spa",
        "sales",
        "accessory"
    ],
    "wof:name":"Mountain Spring Spas & Pools",
    "wof:placetype":"venue"
},
  "geometry": {"coordinates":[-83.36701499999999,35.18133],"type":"Point"}
}