{
  "type": "Feature",
  "properties": {
    "iso:country":"US",
    "sg:address":"4808 Langley Rd",
    "sg:city":"Rocky Mount",
    "sg:classifiers":[
        {
            "category":"Manufacturing",
            "subcategory":"Wood Products",
            "type":"Manufacturing & Wholesale Goods"
        }
    ],
    "sg:phone":"+1 252 443 6592",
    "sg:postcode":"27803",
    "sg:province":"NC",
    "sg:tags":[
        "pallet",
        "skid"
    ],
    "wof:name":"Vick's Carpentry Shop",
    "wof:placetype":"venue"
},
  "geometry": {"coordinates":[-77.90473,35.924847],"type":"Point"}
}