{
  "type": "Feature",
  "properties": {
    "addr:full":"1003 High House Rd Cary NC 27513",
    "addr:housenumber":"1003",
    "addr:postcode":"27513",
    "addr:street":"High House Rd",
    "iso:country":"US",
    "sg:address":"1003 High House Rd",
    "sg:city":"Cary",
    "sg:classifiers":[
        {
            "category":"Banks & Credit Unions",
            "subcategory":"Bank",
            "type":"Services"
        }
    ],
    "sg:phone":"+1 919 465 4233",
    "sg:postcode":"27513",
    "sg:province":"NC",
    "sg:tags":[
        "loan",
        "real estate"
    ],
    "wof:name":"North Carolina Mortgage Group",
    "wof:placetype":"venue"
},
  "geometry": {"coordinates":[-78.829412,35.789811],"type":"Point"}
}