{
  "type": "Feature",
  "properties": {
    "iso:country":"US",
    "sg:address":"3701 Summit Ave",
    "sg:city":"Greensboro",
    "sg:classifiers":[
        {
            "category":"Professional",
            "subcategory":"Accounting & Tax Preparation",
            "type":"Services"
        }
    ],
    "sg:phone":"+1 336 621 4667",
    "sg:postcode":"27405",
    "sg:province":"NC",
    "sg:tags":[
        "return",
        "filing"
    ],
    "wof:name":"O'Henry Income Tax Svc Inc",
    "wof:placetype":"venue"
},
  "geometry": {"coordinates":[-79.76097,36.13144],"type":"Point"}
}