{
  "type": "Feature",
  "properties": {
    "iso:country":"US",
    "sg:address":"3221 E Lawyers Rd",
    "sg:city":"Monroe",
    "sg:phone":"+1 704 289 8054",
    "sg:postcode":"28110",
    "sg:province":"NC",
    "sg:tags":[
        "farm",
        "soybean"
    ],
    "wof:name":"Everette Medlin",
    "wof:placetype":"venue"
},
  "geometry": {"coordinates":[-80.45517,35.072165],"type":"Point"}
}