{
  "type": "Feature",
  "properties": {
    "addr:full":"207 Main St Ahoskie NC 27910",
    "addr:housenumber":"207",
    "addr:postcode":"27910",
    "addr:street":"Main St",
    "iso:country":"US",
    "sg:address":"207 Main St",
    "sg:city":"Ahoskie",
    "sg:classifiers":[
        {
            "category":"Professional",
            "subcategory":"Business Services",
            "type":"Services"
        }
    ],
    "sg:phone":"+1 252 332 7411",
    "sg:postcode":"27910",
    "sg:province":"NC",
    "sg:tags":[
        "equipment",
        "microfilming"
    ],
    "wof:name":"DRS Group",
    "wof:placetype":"venue"
},
  "geometry": {"coordinates":[-76.98469799999999,36.284967],"type":"Point"}
}