{
  "type": "Feature",
  "properties": {
    "addr:full":"104 Lee Loop Morganton NC 28655",
    "addr:housenumber":"104",
    "addr:postcode":"28655",
    "addr:street":"Lee Loop",
    "iso:country":"US",
    "sg:address":"104 Lee Loop",
    "sg:city":"Morganton",
    "sg:classifiers":[
        {
            "category":"Retail",
            "subcategory":"Car Wash",
            "type":"Services"
        }
    ],
    "sg:phone":"+1 828 433 7361",
    "sg:postcode":"28655",
    "sg:province":"NC",
    "sg:tags":[
        "polishing",
        "washing"
    ],
    "wof:name":"Auto Corral Car Wash",
    "wof:placetype":"venue"
},
  "geometry": {"coordinates":[-81.700282,35.710149],"type":"Point"}
}