{
  "type": "Feature",
  "properties": {
    "iso:country":"US",
    "sg:address":"1004 Jordans Pond Ln",
    "sg:city":"Charlotte",
    "sg:classifiers":[
        {
            "category":"Building & Trades",
            "subcategory":"Construction",
            "type":"Services"
        },
        {
            "category":"Professional",
            "subcategory":"Management & Consulting",
            "type":"Services"
        }
    ],
    "sg:phone":"+1 704 392 6633",
    "sg:postcode":"28214",
    "sg:province":"NC",
    "sg:tags":[
        "contractor",
        "business",
        "general"
    ],
    "wof:name":"Crossman Communities Inc",
    "wof:placetype":"venue"
},
  "geometry": {"coordinates":[-80.92911700000001,35.29436],"type":"Point"}
}