{
  "type": "Feature",
  "properties": {
    "addr:full":"6497 Walden Pond Ln SE Southport NC 28461",
    "addr:housenumber":"6497",
    "addr:postcode":"28461",
    "addr:street":"Walden Pond Ln Se",
    "iso:country":"US",
    "sg:address":"6497 Walden Pond Ln SE",
    "sg:city":"Southport",
    "sg:classifiers":[
        {
            "category":"Professional",
            "subcategory":"Business Services",
            "type":"Services"
        }
    ],
    "sg:phone":"+1   ",
    "sg:postcode":"28461",
    "sg:province":"NC",
    "sg:tags":[
        "resource",
        "human"
    ],
    "wof:name":"Morris Consulting",
    "wof:placetype":"venue"
},
  "geometry": {"coordinates":[-78.001135,33.972374],"type":"Point"}
}