{
  "type": "Feature",
  "properties": {
    "addr:full":"500 W Franklin Blvd Gastonia NC 28052",
    "addr:housenumber":"500",
    "addr:postcode":"28052",
    "addr:street":"W Franklin Blvd",
    "iso:country":"US",
    "sg:address":"500 W Franklin Blvd",
    "sg:city":"Gastonia",
    "sg:classifiers":[
        {
            "category":"Retail",
            "subcategory":"Auto Repair",
            "type":"Services"
        }
    ],
    "sg:phone":"+1 704 867 1754",
    "sg:postcode":"28052",
    "sg:province":"NC",
    "sg:tags":[
        "repairing",
        "automobile"
    ],
    "wof:name":"Affordable Auto Repair",
    "wof:placetype":"venue"
},
  "geometry": {"coordinates":[-81.19143699999999,35.262285],"type":"Point"}
}