{
  "type": "Feature",
  "properties": {
    "addr:full":"127 E Main St Washington NC 27889",
    "addr:housenumber":"127",
    "addr:postcode":"27889",
    "addr:street":"E Main St",
    "iso:country":"US",
    "sg:address":"127 E Main St",
    "sg:city":"Washington",
    "sg:classifiers":[
        {
            "category":"Professional",
            "subcategory":"Accounting & Tax Preparation",
            "type":"Services"
        }
    ],
    "sg:phone":"+1 252 946 4191",
    "sg:postcode":"27889",
    "sg:province":"NC",
    "sg:tags":[
        "accountant"
    ],
    "wof:name":"C H Rodman Accountants",
    "wof:placetype":"venue"
},
  "geometry": {"coordinates":[-77.054784,35.541839],"type":"Point"}
}