{
  "type": "Feature",
  "properties": {
    "addr:full":"128 Ballou Rd Elk Park NC 28615",
    "addr:housenumber":"128",
    "addr:postcode":"28615",
    "addr:street":"Ballou Rd",
    "iso:country":"US",
    "sg:address":"128 Ballou Rd",
    "sg:city":"Elk Park",
    "sg:classifiers":[
        {
            "category":"Real Estate",
            "subcategory":"Real Estate Agent",
            "type":"Services"
        }
    ],
    "sg:phone":"+1 828 733 0817",
    "sg:postcode":"28615",
    "sg:province":"NC",
    "sg:tags":[
        "agency",
        "rental"
    ],
    "wof:name":"Blue Ridge Cabin Rental",
    "wof:placetype":"venue"
},
  "geometry": {"coordinates":[-81.66837099999999,36.411159],"type":"Point"}
}