{
  "type": "Feature",
  "properties": {
    "iso:country":"US",
    "sg:address":"350 N Cox St",
    "sg:city":"Asheboro",
    "sg:classifiers":[
        {
            "category":"Health Services",
            "subcategory":"Medical Lab",
            "type":"Services"
        }
    ],
    "sg:phone":"+1 336 633 0100",
    "sg:postcode":"27203",
    "sg:province":"NC",
    "sg:tags":[
        "laboratory"
    ],
    "wof:name":"Elder Care Clinical Consulting",
    "wof:placetype":"venue"
},
  "geometry": {"coordinates":[-79.811037,35.708957],"type":"Point"}
}