{
  "type": "Feature",
  "properties": {
    "addr:full":"1530 Alleghany St Charlotte NC 28208",
    "addr:housenumber":"1530",
    "addr:postcode":"28208",
    "addr:street":"Alleghany St",
    "iso:country":"US",
    "sg:address":"1530 Alleghany St",
    "sg:city":"Charlotte",
    "sg:classifiers":[
        {
            "category":"Social Services",
            "subcategory":"Child Care",
            "type":"Services"
        }
    ],
    "sg:phone":"+1 704 398 9891",
    "sg:postcode":"28208",
    "sg:province":"NC",
    "wof:name":"Hunter's Anointed Childcare",
    "wof:placetype":"venue"
},
  "geometry": {"coordinates":[-80.892754,35.238461],"type":"Point"}
}