{
  "type": "Feature",
  "properties": {
    "iso:country":"US",
    "sg:address":"1312 Morganton Rd",
    "sg:city":"Fayetteville",
    "sg:classifiers":[
        {
            "category":"Education",
            "subcategory":"Dance Studio",
            "type":"Public Place"
        }
    ],
    "sg:phone":"+1 910 484 3466",
    "sg:postcode":"28305",
    "sg:province":"NC",
    "sg:tags":[
        "instruction",
        "dancing"
    ],
    "wof:name":"Charlotte Blume School Dance",
    "wof:placetype":"venue"
},
  "geometry": {"coordinates":[-78.901518,35.057317],"type":"Point"}
}