{
  "type": "Feature",
  "properties": {
    "addr:full":"3081 Prytania Rd Winston Salem NC 27106",
    "addr:housenumber":"3081",
    "addr:postcode":"27106",
    "addr:street":"Prytania Rd",
    "iso:country":"US",
    "sg:address":"3081 Prytania Rd",
    "sg:city":"Winston Salem",
    "sg:classifiers":[
        {
            "category":"Building & Trades",
            "subcategory":"Electrical",
            "type":"Services"
        }
    ],
    "sg:phone":"+1 336 767 7391",
    "sg:postcode":"27106",
    "sg:province":"NC",
    "sg:tags":[
        "electric",
        "contractor"
    ],
    "wof:name":"Reliable Service Plus Heating",
    "wof:placetype":"venue"
},
  "geometry": {"coordinates":[-80.293102,36.128799],"type":"Point"}
}