{
  "type": "Feature",
  "properties": {
    "iso:country":"US",
    "sg:address":"5520 Sherrills Ford Rd",
    "sg:city":"Salisbury",
    "sg:classifiers":[
        {
            "category":"Restaurant",
            "type":"Food & Drink"
        }
    ],
    "sg:phone":"+1 704 633 3774",
    "sg:postcode":"28147",
    "sg:province":"NC",
    "sg:tags":[
        "eating"
    ],
    "wof:name":"Graham's Grocery & Grill",
    "wof:placetype":"venue"
},
  "geometry": {"coordinates":[-80.58463999999999,35.686303],"type":"Point"}
}