{
  "type": "Feature",
  "properties": {
    "iso:country":"US",
    "sg:address":"526 South Church Street",
    "sg:city":"Charlotte",
    "sg:classifiers":[
        {
            "category":"Professional",
            "subcategory":"Research",
            "type":"Services"
        }
    ],
    "sg:phone":"+1 704 382 3853",
    "sg:postcode":"28202-1904",
    "sg:province":"NC",
    "sg:website":"http://www.duke-energy.com/company.asp",
    "wof:name":"Duke Energy Corporation",
    "wof:placetype":"venue"
},
  "geometry": {"coordinates":[-80.84933700000001,35.224658],"type":"Point"}
}