{
  "type": "Feature",
  "properties": {
    "iso:country":"US",
    "sg:address":"409 S Broad St",
    "sg:city":"Gastonia",
    "sg:classifiers":[
        {
            "category":"Shopping",
            "subcategory":"Clothing, Apparel, & Fashions",
            "type":"Retail Goods"
        }
    ],
    "sg:phone":"+1 704 865 3334",
    "sg:postcode":"28052",
    "sg:province":"NC",
    "sg:tags":[
        "dressmaker"
    ],
    "wof:name":"Andrea's Designs",
    "wof:placetype":"venue"
},
  "geometry": {"coordinates":[-81.179231,35.258201],"type":"Point"}
}