{
  "type": "Feature",
  "properties": {
    "addr:full":"3020 Stratford Dr Greensboro NC 27408",
    "addr:housenumber":"3020",
    "addr:postcode":"27408",
    "addr:street":"Stratford Dr",
    "iso:country":"US",
    "sg:address":"3020 Stratford Dr",
    "sg:city":"Greensboro",
    "sg:classifiers":[
        {
            "category":"Building & Trades",
            "subcategory":"Cleaning & Sanitation",
            "type":"Services"
        }
    ],
    "sg:phone":"+1   ",
    "sg:postcode":"27408",
    "sg:province":"NC",
    "sg:tags":[
        "maintenance"
    ],
    "wof:name":"Drake Agency",
    "wof:placetype":"venue"
},
  "geometry": {"coordinates":[-79.84239100000001,36.115714],"type":"Point"}
}