{
  "type": "Feature",
  "properties": {
    "addr:full":"294 W Plaza Dr Mooresville NC 28117",
    "addr:housenumber":"294",
    "addr:postcode":"28117",
    "addr:street":"W Plaza Dr",
    "iso:country":"US",
    "sg:address":"294 W Plaza Dr",
    "sg:city":"Mooresville",
    "sg:classifiers":[
        {
            "category":"Professional",
            "subcategory":"Accounting & Tax Preparation",
            "type":"Services"
        }
    ],
    "sg:phone":"+1   ",
    "sg:postcode":"28117",
    "sg:province":"NC",
    "wof:name":"H Elliot Greene & Assoc PA",
    "wof:placetype":"venue"
},
  "geometry": {"coordinates":[-80.85029299999999,35.592138],"type":"Point"}
}