{
  "type": "Feature",
  "properties": {
    "iso:country":"US",
    "sg:address":"4797 Burris Rd",
    "sg:city":"Denver",
    "sg:classifiers":[
        {
            "category":"Building & Trades",
            "subcategory":"Construction",
            "type":"Services"
        }
    ],
    "sg:phone":"+1 704 483 0215",
    "sg:postcode":"28037",
    "sg:province":"NC",
    "sg:tags":[
        "general",
        "contractor"
    ],
    "wof:name":"D'Latour Builders",
    "wof:placetype":"venue"
},
  "geometry": {"coordinates":[-81.018959,35.554624],"type":"Point"}
}