{
  "type": "Feature",
  "properties": {
    "iso:country":"US",
    "sg:address":"5412 E Oak Island Dr",
    "sg:city":"Oak Island",
    "sg:classifiers":[
        {
            "category":"Real Estate",
            "subcategory":"Real Estate Agent",
            "type":"Services"
        }
    ],
    "sg:phone":"+1 910 278 1147",
    "sg:postcode":"28465",
    "sg:province":"NC",
    "wof:name":"Better Beach Rentals Inc",
    "wof:placetype":"venue"
},
  "geometry": {"coordinates":[-78.109442,33.912391],"type":"Point"}
}