{
  "type": "Feature",
  "properties": {
    "addr:full":"113 E Main St Old Fort NC 28762",
    "addr:housenumber":"113",
    "addr:postcode":"28762",
    "addr:street":"E Main St",
    "iso:country":"US",
    "sg:address":"113 E Main St",
    "sg:city":"Old Fort",
    "sg:classifiers":[
        {
            "category":"Restaurant",
            "type":"Food & Drink"
        }
    ],
    "sg:phone":"+1 828 668 7676",
    "sg:postcode":"28762",
    "sg:province":"NC",
    "wof:name":"Whistle Stop",
    "wof:placetype":"venue"
},
  "geometry": {"coordinates":[-82.179185,35.630335],"type":"Point"}
}