{
  "type": "Feature",
  "properties": {
    "addr:full":"2579 Pinetops-Macclesfield Rd Macclesfield NC 27852",
    "addr:housenumber":"2579",
    "addr:postcode":"27852",
    "addr:street":"Pinetops-Macclesfield Rd",
    "iso:country":"US",
    "sg:address":"2579 Pinetops-Macclesfield Rd",
    "sg:city":"Macclesfield",
    "sg:classifiers":[
        {
            "category":"Shopping",
            "subcategory":"Catalog Store",
            "type":"Retail Goods"
        }
    ],
    "sg:phone":"+1 252 827 4090",
    "sg:postcode":"27852",
    "sg:province":"NC",
    "sg:tags":[
        "automotive",
        "equipment"
    ],
    "wof:name":"A-1 Automotive Equipment",
    "wof:placetype":"venue"
},
  "geometry": {"coordinates":[-77.65876400000001,35.763888],"type":"Point"}
}