{
  "type": "Feature",
  "properties": {
    "iso:country":"US",
    "sg:address":"16 Salem St",
    "sg:city":"Thomasville",
    "sg:classifiers":[
        {
            "category":"Social Services",
            "type":"Services"
        }
    ],
    "sg:phone":"+1   ",
    "sg:postcode":"27360",
    "sg:province":"NC",
    "wof:name":"F C A Inc",
    "wof:placetype":"venue"
},
  "geometry": {"coordinates":[-80.08235999999999,35.883917],"type":"Point"}
}