{
  "type": "Feature",
  "properties": {
    "iso:country":"US",
    "sg:address":"100 Gold Dust Ct",
    "sg:city":"Kings Mountain",
    "sg:classifiers":[
        {
            "category":"Home & Garden",
            "subcategory":"Building Materials",
            "type":"Retail Goods"
        }
    ],
    "sg:phone":"+1 704 739 1557",
    "sg:postcode":"28086",
    "sg:province":"NC",
    "sg:tags":[
        "shutter"
    ],
    "wof:name":"Wolfs Plantation Shutters",
    "wof:placetype":"venue"
},
  "geometry": {"coordinates":[-81.36632,35.274415],"type":"Point"}
}