{
  "type": "Feature",
  "properties": {
    "iso:country":"US",
    "sg:address":"1809 Floyd Church Rd",
    "sg:city":"Lexington",
    "sg:classifiers":[
        {
            "category":"Building & Trades",
            "subcategory":"Landscaping Services",
            "type":"Services"
        }
    ],
    "sg:phone":"+1 336 859 2801",
    "sg:postcode":"27292",
    "sg:province":"NC",
    "sg:tags":[
        "landscape"
    ],
    "wof:name":"Worley Landscaping",
    "wof:placetype":"venue"
},
  "geometry": {"coordinates":[-80.198379,35.670314],"type":"Point"}
}