{
  "type": "Feature",
  "properties": {
    "iso:country":"US",
    "sg:address":"100 Duke Ct",
    "sg:city":"Moyock",
    "sg:classifiers":[
        {
            "category":"Personal",
            "subcategory":"Beauty Salon",
            "type":"Services"
        }
    ],
    "sg:phone":"+1   ",
    "sg:postcode":"27958",
    "sg:province":"NC",
    "sg:tags":[
        "consultation"
    ],
    "wof:name":"Ckglamour",
    "wof:placetype":"venue"
},
  "geometry": {"coordinates":[-76.248475,36.533747],"type":"Point"}
}