{
  "type": "Feature",
  "properties": {
    "iso:country":"US",
    "sg:address":"4011 Carnoustie Ln",
    "sg:city":"Charlotte",
    "sg:classifiers":[
        {
            "category":"Professional",
            "type":"Services"
        }
    ],
    "sg:phone":"+1 704 643 1328",
    "sg:postcode":"28210",
    "sg:province":"NC",
    "wof:name":"Nancy F Ramseur",
    "wof:placetype":"venue"
},
  "geometry": {"coordinates":[-80.83223700000001,35.114686],"type":"Point"}
}