{
  "type": "Feature",
  "properties": {
    "addr:full":"309 E Morehead St Charlotte NC 28202",
    "addr:housenumber":"309",
    "addr:postcode":"28202",
    "addr:street":"E Morehead St",
    "iso:country":"US",
    "sg:address":"309 E Morehead St",
    "sg:city":"Charlotte",
    "sg:classifiers":[
        {
            "category":"Health Services",
            "subcategory":"Chiropractor",
            "type":"Services"
        }
    ],
    "sg:phone":"+1 704 335 8975",
    "sg:postcode":"28202",
    "sg:province":"NC",
    "wof:name":"Network Spinal Anaylsis",
    "wof:placetype":"venue"
},
  "geometry": {"coordinates":[-80.848947,35.218855],"type":"Point"}
}