{
  "type": "Feature",
  "properties": {
    "addr:full":"12 Stillhouse Pl Durham NC 27704",
    "addr:housenumber":"12",
    "addr:postcode":"27704",
    "addr:street":"Stillhouse Pl",
    "iso:country":"US",
    "sg:address":"12 Stillhouse Pl",
    "sg:city":"Durham",
    "sg:classifiers":[
        {
            "category":"Communications",
            "subcategory":"Film & Video Production",
            "type":"Services"
        }
    ],
    "sg:phone":"+1   ",
    "sg:postcode":"27704",
    "sg:province":"NC",
    "sg:tags":[
        "motion"
    ],
    "wof:name":"Digital Imagery",
    "wof:placetype":"venue"
},
  "geometry": {"coordinates":[-78.91709400000001,36.05797],"type":"Point"}
}