{
  "type": "Feature",
  "properties": {
    "iso:country":"US",
    "sg:address":"165 Simpson Rd",
    "sg:city":"Barco",
    "sg:classifiers":[
        {
            "category":"Wholesale",
            "subcategory":"Machinery & Supplies",
            "type":"Manufacturing & Wholesale Goods"
        }
    ],
    "sg:phone":"+1 252 619 7062",
    "sg:postcode":"27917",
    "sg:province":"NC",
    "sg:tags":[
        "bulkhead"
    ],
    "wof:name":"Bulkhead Service By Dad's Dirt",
    "wof:placetype":"venue"
},
  "geometry": {"coordinates":[-75.974209,36.385779],"type":"Point"}
}