{
  "type": "Feature",
  "properties": {
    "addr:full":"1117 Mount Vernon Springs Rd Siler City NC 27344",
    "addr:housenumber":"1117",
    "addr:postcode":"27344",
    "addr:street":"Mount Vernon Springs Rd",
    "iso:country":"US",
    "sg:address":"1117 Mount Vernon Springs Rd",
    "sg:city":"Siler City",
    "sg:classifiers":[
        {
            "category":"Building & Trades",
            "subcategory":"Construction",
            "type":"Services"
        }
    ],
    "sg:phone":"+1 336 580 8089",
    "sg:postcode":"27344",
    "sg:province":"NC",
    "sg:tags":[
        "contractor"
    ],
    "wof:name":"Robert H Bingham Contractor",
    "wof:placetype":"venue"
},
  "geometry": {"coordinates":[-79.44224199999999,35.659721],"type":"Point"}
}