{
  "type": "Feature",
  "properties": {
    "addr:full":"1311 Malcolm Blvd Rutherford Clg NC 28612",
    "addr:housenumber":"1311",
    "addr:postcode":"28612",
    "addr:street":"Malcolm Blvd",
    "iso:country":"US",
    "sg:address":"1311 Malcolm Blvd",
    "sg:city":"Rutherford Clg",
    "sg:classifiers":[
        {
            "category":"Restaurant",
            "type":"Food & Drink"
        }
    ],
    "sg:phone":"+1 828 879 9898",
    "sg:postcode":"28612",
    "sg:province":"NC",
    "wof:name":"River's End Restaurant",
    "wof:placetype":"venue"
},
  "geometry": {"coordinates":[-81.525741,35.764074],"type":"Point"}
}