{
  "type": "Feature",
  "properties": {
    "addr:full":"1435 Faircrest Dr Winston Salem NC 27106",
    "addr:housenumber":"1435",
    "addr:postcode":"27106",
    "addr:street":"Faircrest Dr",
    "iso:country":"US",
    "sg:address":"1435 Faircrest Dr",
    "sg:city":"Winston Salem",
    "sg:classifiers":[
        {
            "category":"Wholesale",
            "subcategory":"Auto Parts",
            "type":"Manufacturing & Wholesale Goods"
        }
    ],
    "sg:phone":"+1 336 924 8150",
    "sg:postcode":"27106",
    "sg:province":"NC",
    "sg:tags":[
        "supply"
    ],
    "wof:name":"Ingram Auto Parts",
    "wof:placetype":"venue"
},
  "geometry": {"coordinates":[-80.311362,36.196591],"type":"Point"}
}