{
  "type": "Feature",
  "properties": {
    "iso:country":"US",
    "sg:address":"301 N Pollock St",
    "sg:city":"Selma",
    "sg:classifiers":[
        {
            "category":"Food & Beverages",
            "subcategory":"Groceries & Convenience Stores",
            "type":"Retail Goods"
        }
    ],
    "sg:phone":"+1 919 965 9600",
    "sg:postcode":"27576",
    "sg:province":"NC",
    "wof:name":"A-Mart Food Stores Inc",
    "wof:placetype":"venue"
},
  "geometry": {"coordinates":[-78.282438,35.538802],"type":"Point"}
}