{
  "type": "Feature",
  "properties": {
    "addr:full":"4500 Preslyn Dr Raleigh NC 27616",
    "addr:housenumber":"4500",
    "addr:postcode":"27616",
    "addr:street":"Preslyn Dr",
    "iso:country":"US",
    "sg:address":"4500 Preslyn Dr",
    "sg:city":"Raleigh",
    "sg:classifiers":[
        {
            "category":"Retail",
            "subcategory":"Auto Repair",
            "type":"Services"
        }
    ],
    "sg:phone":"+1 919 212 0018",
    "sg:postcode":"27616",
    "sg:province":"NC",
    "sg:tags":[
        "automobile",
        "customizing"
    ],
    "wof:name":"Tops & Trends",
    "wof:placetype":"venue"
},
  "geometry": {"coordinates":[-78.569693,35.893646],"type":"Point"}
}