{
  "type": "Feature",
  "properties": {
    "addr:full":"1810 Center Park Dr Charlotte NC 28217",
    "addr:housenumber":"1810",
    "addr:postcode":"28217",
    "addr:street":"Center Park Dr",
    "iso:country":"US",
    "sg:address":"1810 Center Park Dr",
    "sg:city":"Charlotte",
    "sg:classifiers":[
        {
            "category":"Personal",
            "subcategory":"Beauty Salon",
            "type":"Services"
        }
    ],
    "sg:phone":"+1 910 695 1113",
    "sg:postcode":"28217",
    "sg:province":"NC",
    "sg:tags":[
        "manicuring"
    ],
    "wof:name":"Monique's Nails",
    "wof:placetype":"venue"
},
  "geometry": {"coordinates":[-80.92751199999999,35.174433],"type":"Point"}
}