{
  "type": "Feature",
  "properties": {
    "iso:country":"US",
    "sg:address":"190 Industrial Park Rd",
    "sg:city":"Waynesville",
    "sg:classifiers":[
        {
            "category":"Autos & Motor Vehicles",
            "subcategory":"Auto Supplies",
            "type":"Retail Goods"
        }
    ],
    "sg:phone":"+1 828 646 0182",
    "sg:postcode":"28786",
    "sg:province":"NC",
    "sg:tags":[
        "automobile",
        "parts"
    ],
    "sg:website":"www.biggerbadderfaster.com",
    "wof:name":"Extreme Motor Sports",
    "wof:placetype":"venue"
},
  "geometry": {"coordinates":[-82.966812,35.516984],"type":"Point"}
}