{
  "type": "Feature",
  "properties": {
    "addr:full":"2116 Cedar Creek Rd Fayetteville NC 28312",
    "addr:housenumber":"2116",
    "addr:postcode":"28312",
    "addr:street":"Cedar Creek Rd",
    "iso:country":"US",
    "sg:address":"2116 Cedar Creek Rd",
    "sg:city":"Fayetteville",
    "sg:classifiers":[
        {
            "category":"Restaurant",
            "type":"Food & Drink"
        }
    ],
    "sg:phone":"+1 910 323 2419",
    "sg:postcode":"28312",
    "sg:province":"NC",
    "wof:name":"Pizza Hut",
    "wof:placetype":"venue"
},
  "geometry": {"coordinates":[-78.81778300000001,35.006846],"type":"Point"}
}