{
  "type": "Feature",
  "properties": {
    "addr:full":"347 Shawcroft Rd Fayetteville NC 28311",
    "addr:housenumber":"347",
    "addr:postcode":"28311",
    "addr:street":"Shawcroft Rd",
    "iso:country":"US",
    "sg:address":"347 Shawcroft Rd",
    "sg:city":"Fayetteville",
    "sg:classifiers":[
        {
            "category":"Sports & Exercise",
            "subcategory":"Golf",
            "type":"Entertainment"
        }
    ],
    "sg:phone":"+1 910 630 3493",
    "sg:postcode":"28311",
    "sg:province":"NC",
    "sg:tags":[
        "course"
    ],
    "wof:name":"Midway Golf Packages",
    "wof:placetype":"venue"
},
  "geometry": {"coordinates":[-78.883453,35.147069],"type":"Point"}
}