{
  "type": "Feature",
  "properties": {
    "iso:country":"US",
    "sg:address":"2222 S New Hope Rd",
    "sg:city":"Gastonia",
    "sg:classifiers":[
        {
            "category":"Education",
            "subcategory":"School",
            "type":"Public Place"
        }
    ],
    "sg:phone":"+1 704 866 6600",
    "sg:postcode":"28054",
    "sg:province":"NC",
    "sg:tags":[
        "high"
    ],
    "wof:name":"Ashbrook High School",
    "wof:placetype":"venue"
},
  "geometry": {"coordinates":[-81.127663,35.242418],"type":"Point"}
}