{
  "type": "Feature",
  "properties": {
    "iso:country":"US",
    "sg:address":"3939 Glenwood Ave",
    "sg:city":"Raleigh",
    "sg:classifiers":[
        {
            "category":"Real Estate",
            "subcategory":"Real Estate Services",
            "type":"Services"
        }
    ],
    "sg:phone":"+1 877 287 5845",
    "sg:postcode":"27612",
    "sg:province":"NC",
    "sg:tags":[
        "apartment",
        "management",
        "rental",
        "finder"
    ],
    "sg:website":"http://raleigh.citysearch.com/profile/external/6190512/raleigh_nc/beckanna_on_glenwood.html?publisher=yellowpages&reference_id=1&placement=ypwebsitemip",
    "wof:name":"Beckanna on Glenwood",
    "wof:placetype":"venue"
},
  "geometry": {"coordinates":[-78.667406,35.832282],"type":"Point"}
}