{
  "type": "Feature",
  "properties": {
    "iso:country":"US",
    "sg:address":"5615 W Friendly Ave",
    "sg:city":"Greensboro",
    "sg:classifiers":[
        {
            "category":"Restaurant",
            "type":"Food & Drink"
        }
    ],
    "sg:menulink":"http://www.allmenus.com/nc/greensboro/150857-boston-market/menu/",
    "sg:phone":"+1 336 292 6336",
    "sg:postcode":"27410",
    "sg:province":"NC",
    "sg:tags":[
        "barbecue",
        "american",
        "soup"
    ],
    "wof:name":"Boston Market",
    "wof:placetype":"venue"
},
  "geometry": {"coordinates":[-79.88619799999999,36.088989],"type":"Point"}
}