{
  "type": "Feature",
  "properties": {
    "iso:country":"US",
    "sg:address":"335 US Hwy 13 S",
    "sg:city":"Goldsboro",
    "sg:classifiers":[
        {
            "category":"Food & Beverages",
            "subcategory":"Groceries & Convenience Stores",
            "type":"Retail Goods"
        }
    ],
    "sg:phone":"+1 919 736 9444",
    "sg:postcode":"27530",
    "sg:province":"NC",
    "wof:name":"Friendly Mart Inc",
    "wof:placetype":"venue"
},
  "geometry": {"coordinates":[-78.04718800000001,35.324389],"type":"Point"}
}