{
  "type": "Feature",
  "properties": {
    "addr:full":"7317 Easen Ct Charlotte NC 28211",
    "addr:housenumber":"7317",
    "addr:postcode":"28211",
    "addr:street":"Easen Ct",
    "iso:country":"US",
    "sg:address":"7317 Easen Ct",
    "sg:city":"Charlotte",
    "sg:classifiers":[
        {
            "category":"Professional",
            "subcategory":"Business Services",
            "type":"Services"
        }
    ],
    "sg:phone":"+1 704 299 6452",
    "sg:postcode":"28211",
    "sg:province":"NC",
    "sg:tags":[
        "arbitration"
    ],
    "wof:name":"Marianne M Haynes",
    "wof:placetype":"venue"
},
  "geometry": {"coordinates":[-80.758216,35.147928],"type":"Point"}
}