{
  "type": "Feature",
  "properties": {
    "iso:country":"US",
    "sg:address":"3600 S College Rd",
    "sg:city":"Wilmington",
    "sg:classifiers":[
        {
            "category":"Professional",
            "subcategory":"Advertising",
            "type":"Services"
        }
    ],
    "sg:phone":"+1 910 799 2858",
    "sg:postcode":"28412",
    "sg:province":"NC",
    "sg:tags":[
        "mailing",
        "shipping"
    ],
    "wof:name":"UPS Store",
    "wof:placetype":"venue"
},
  "geometry": {"coordinates":[-77.891267,34.175657],"type":"Point"}
}