{
  "type": "Feature",
  "properties": {
    "iso:country":"US",
    "sg:address":"104 N Chestnut St",
    "sg:city":"Lumberton",
    "sg:classifiers":[
        {
            "category":"Museum",
            "type":"Entertainment"
        }
    ],
    "sg:phone":"+1 910 738 1114",
    "sg:postcode":"28358",
    "sg:province":"NC",
    "wof:name":"Exploration Station",
    "wof:placetype":"venue"
},
  "geometry": {"coordinates":[-79.007716,34.617896],"type":"Point"}
}