{
  "type": "Feature",
  "properties": {
    "iso:country":"US",
    "sg:address":"865 Squire Ct",
    "sg:city":"Cary",
    "sg:classifiers":[
        {
            "category":"Real Estate",
            "subcategory":"Real Estate Agent",
            "type":"Services"
        }
    ],
    "sg:phone":"+1 919 468 3708",
    "sg:postcode":"27511",
    "sg:province":"NC",
    "wof:name":"Real Estate Resoures",
    "wof:placetype":"venue"
},
  "geometry": {"coordinates":[-78.794449,35.780512],"type":"Point"}
}