{
  "type": "Feature",
  "properties": {
    "addr:full":"3025 Parks Lafferty Rd Concord NC 28025",
    "addr:housenumber":"3025",
    "addr:postcode":"28025",
    "addr:street":"Parks Lafferty Rd",
    "iso:country":"US",
    "sg:address":"3025 Parks Lafferty Rd",
    "sg:city":"Concord",
    "sg:classifiers":[
        {
            "category":"Professional",
            "subcategory":"Business Services",
            "type":"Services"
        }
    ],
    "sg:phone":"+1   ",
    "sg:postcode":"28025",
    "sg:province":"NC",
    "wof:name":"A1 Automotive Inspections Inc",
    "wof:placetype":"venue"
},
  "geometry": {"coordinates":[-80.524317,35.318418],"type":"Point"}
}