{
  "type": "Feature",
  "properties": {
    "addr:full":"2216 Union Rd Gastonia NC 28054",
    "addr:housenumber":"2216",
    "addr:postcode":"28054",
    "addr:street":"Union Rd",
    "iso:country":"US",
    "sg:address":"2216 Union Rd",
    "sg:city":"Gastonia",
    "sg:classifiers":[
        {
            "category":"Restaurant",
            "type":"Food & Drink"
        }
    ],
    "sg:phone":"+1 704 865 8041",
    "sg:postcode":"28054",
    "sg:province":"NC",
    "wof:name":"Wendy's",
    "wof:placetype":"venue"
},
  "geometry": {"coordinates":[-81.169375,35.23157],"type":"Point"}
}