{
  "type": "Feature",
  "properties": {
    "addr:full":"1222 Conover Blvd W Conover NC 28613",
    "addr:housenumber":"1222",
    "addr:postcode":"28613",
    "addr:street":"Conover Blvd W Conover",
    "iso:country":"US",
    "sg:address":"1222 Conover Blvd W",
    "sg:city":"Conover",
    "sg:classifiers":[
        {
            "category":"Restaurant",
            "type":"Food & Drink"
        }
    ],
    "sg:menulink":"http://www.allmenus.com/nc/newton/238985-dos-amigos/menu/",
    "sg:phone":"+1 828 466 1920",
    "sg:postcode":"28613",
    "sg:province":"NC",
    "sg:tags":[
        "mexican"
    ],
    "wof:name":"Dos Amigos",
    "wof:placetype":"venue"
},
  "geometry": {"coordinates":[-81.25508600000001,35.696363],"type":"Point"}
}