{
  "type": "Feature",
  "properties": {
    "addr:full":"7234 Denmark Dr Denver NC 28037",
    "addr:postcode":"7234;28037",
    "addr:street":"Denmark Dr",
    "iso:country":"US",
    "sg:address":"7234 Denmark Dr",
    "sg:city":"Denver",
    "sg:classifiers":[
        {
            "category":"Professional",
            "type":"Services"
        }
    ],
    "sg:phone":"+1   ",
    "sg:postcode":"28037",
    "sg:province":"NC",
    "wof:name":"Just For Fun Art Studio",
    "wof:placetype":"venue"
},
  "geometry": {"coordinates":[-81.018046,35.455924],"type":"Point"}
}