{
  "type": "Feature",
  "properties": {
    "iso:country":"US",
    "sg:address":"1200 Piedmont Dr",
    "sg:city":"Lexington",
    "sg:classifiers":[
        {
            "category":"Organizations",
            "subcategory":"Community Association",
            "type":"Services"
        }
    ],
    "sg:phone":"+1   ",
    "sg:postcode":"27295",
    "sg:province":"NC",
    "wof:name":"Allied Veterans of America",
    "wof:placetype":"venue"
},
  "geometry": {"coordinates":[-80.232624,35.836437],"type":"Point"}
}