{
  "type": "Feature",
  "properties": {
    "iso:country":"US",
    "sg:address":"3039 Old Greensboro Rd",
    "sg:city":"Winston Salem",
    "sg:classifiers":[
        {
            "category":"Wholesale",
            "subcategory":"Construction Materials",
            "type":"Manufacturing & Wholesale Goods"
        }
    ],
    "sg:phone":"+1 336 472 3254",
    "sg:postcode":"27101",
    "sg:province":"NC",
    "sg:tags":[
        "sand",
        "gravel"
    ],
    "wof:name":"Comer Trucking & Sanitary",
    "wof:placetype":"venue"
},
  "geometry": {"coordinates":[-80.203998,36.102338],"type":"Point"}
}