{
  "type": "Feature",
  "properties": {
    "addr:full":"104 Calloway Rd King NC 27021",
    "addr:housenumber":"104",
    "addr:postcode":"27021",
    "addr:street":"Calloway Rd",
    "iso:country":"US",
    "sg:address":"104 Calloway Rd",
    "sg:city":"King",
    "sg:classifiers":[
        {
            "category":"Restaurant",
            "type":"Food & Drink"
        }
    ],
    "sg:phone":"+1 336 985 3333",
    "sg:postcode":"27021",
    "sg:province":"NC",
    "sg:tags":[
        "eating"
    ],
    "wof:name":"Grandma's Kitchen",
    "wof:placetype":"venue"
},
  "geometry": {"coordinates":[-80.391873,36.269279],"type":"Point"}
}