{
  "type": "Feature",
  "properties": {
    "addr:full":"427 Lindsey Bridge Rd Madison NC 27025",
    "addr:housenumber":"427",
    "addr:postcode":"27025",
    "addr:street":"Lindsey Bridge Rd",
    "iso:country":"US",
    "sg:address":"427 Lindsey Bridge Rd",
    "sg:city":"Madison",
    "sg:classifiers":[
        {
            "category":"Building & Trades",
            "subcategory":"Construction",
            "type":"Services"
        }
    ],
    "sg:phone":"+1 336 548 4299",
    "sg:postcode":"27025",
    "sg:province":"NC",
    "sg:tags":[
        "concrete",
        "contractor"
    ],
    "wof:name":"Chandler Concrete Co",
    "wof:placetype":"venue"
},
  "geometry": {"coordinates":[-79.985101,36.379422],"type":"Point"}
}