{
  "type": "Feature",
  "properties": {
    "iso:country":"US",
    "sg:address":"103 Gosling Ln",
    "sg:city":"Beaufort",
    "sg:classifiers":[
        {
            "category":"Arts & Performance",
            "subcategory":"Theater",
            "type":"Entertainment"
        }
    ],
    "sg:phone":"+1   ",
    "sg:postcode":"28516",
    "sg:province":"NC",
    "sg:tags":[
        "group"
    ],
    "wof:name":"Tender Mercy",
    "wof:placetype":"venue"
},
  "geometry": {"coordinates":[-76.569153,34.74936],"type":"Point"}
}