{
  "type": "Feature",
  "properties": {
    "addr:full":"352 3rd St NE Hickory NC 28601",
    "addr:housenumber":"352",
    "addr:postcode":"28601",
    "addr:street":"3Rd St Ne",
    "iso:country":"US",
    "sg:address":"352 3rd St NE",
    "sg:city":"Hickory",
    "sg:classifiers":[
        {
            "category":"Organizations",
            "subcategory":"Religious Organization",
            "type":"Services"
        }
    ],
    "sg:phone":"+1 828 261 0146",
    "sg:postcode":"28601",
    "sg:province":"NC",
    "sg:tags":[
        "church"
    ],
    "wof:name":"First United Methodist Church",
    "wof:placetype":"venue"
},
  "geometry": {"coordinates":[-81.33308,35.736152],"type":"Point"}
}