{
  "type": "Feature",
  "properties": {
    "iso:country":"US",
    "sg:address":"2601 Chimney Rock Rd",
    "sg:city":"Hendersonville",
    "sg:classifiers":[
        {
            "category":"Health Services",
            "subcategory":"Clinic",
            "type":"Services"
        }
    ],
    "sg:phone":"+1 828 698 3995",
    "sg:postcode":"28792",
    "sg:province":"NC",
    "sg:tags":[
        "specialty",
        "outpatient"
    ],
    "wof:name":"Weston Group Inc",
    "wof:placetype":"venue"
},
  "geometry": {"coordinates":[-82.42917799999999,35.352458],"type":"Point"}
}