{
  "type": "Feature",
  "properties": {
    "iso:country":"US",
    "sg:address":"225 Orange St",
    "sg:city":"Kinston",
    "sg:classifiers":[
        {
            "category":"Building & Trades",
            "subcategory":"Landscaping Services",
            "type":"Services"
        }
    ],
    "sg:phone":"+1 252 523 6262",
    "sg:postcode":"28504",
    "sg:province":"NC",
    "sg:tags":[
        "designer",
        "landscape"
    ],
    "wof:name":"Quality Yard Care & Lndscpng",
    "wof:placetype":"venue"
},
  "geometry": {"coordinates":[-77.640467,35.222883],"type":"Point"}
}