{
  "type": "Feature",
  "properties": {
    "iso:country":"US",
    "sg:address":"711 S Main St",
    "sg:city":"Biscoe",
    "sg:classifiers":[
        {
            "category":"Manufacturing",
            "subcategory":"Tools & Machinery",
            "type":"Manufacturing & Wholesale Goods"
        }
    ],
    "sg:phone":"+1 910 428 4149",
    "sg:postcode":"27209",
    "sg:province":"NC",
    "sg:tags":[
        "weft",
        "fabric",
        "mfg",
        "textile",
        "mill",
        "knit"
    ],
    "wof:name":"M & M Knitting",
    "wof:placetype":"venue"
},
  "geometry": {"coordinates":[-79.780512,35.347923],"type":"Point"}
}