{
  "type": "Feature",
  "properties": {
    "iso:country":"US",
    "sg:address":"648 N Old Stage Rd",
    "sg:city":"St Pauls",
    "sg:classifiers":[
        {
            "category":"Education",
            "subcategory":"School",
            "type":"Public Place"
        }
    ],
    "sg:phone":"+1 910 865 4177",
    "sg:postcode":"28384",
    "sg:province":"NC",
    "sg:tags":[
        "high"
    ],
    "wof:name":"St Pauls High School",
    "wof:placetype":"venue"
},
  "geometry": {"coordinates":[-78.977709,34.814876],"type":"Point"}
}