{
  "type": "Feature",
  "properties": {
    "addr:full":"6600 E Independence Blvd Charlotte NC 28212",
    "addr:housenumber":"6600",
    "addr:postcode":"28212",
    "addr:street":"E Independence Blvd",
    "iso:country":"US",
    "sg:address":"6600 E Independence Blvd",
    "sg:city":"Charlotte",
    "sg:classifiers":[
        {
            "category":"Restaurant",
            "type":"Food & Drink"
        }
    ],
    "sg:menulink":"http://www.allmenus.com/nc/charlotte/84162-papa-johns-pizza/menu/",
    "sg:phone":"+1 704 531 0500",
    "sg:postcode":"28212",
    "sg:province":"NC",
    "sg:tags":[
        "american",
        "pizza"
    ],
    "wof:name":"Papa John's Pizza",
    "wof:placetype":"venue"
},
  "geometry": {"coordinates":[-80.74570199999999,35.170856],"type":"Point"}
}