{
  "type": "Feature",
  "properties": {
    "iso:country":"US",
    "sg:address":"81 Mackenan Dr",
    "sg:city":"Cary",
    "sg:classifiers":[
        {
            "category":"Autos & Motor Vehicles",
            "subcategory":"Automobile Sales",
            "type":"Retail Goods"
        }
    ],
    "sg:phone":"+1 919 319 9225",
    "sg:postcode":"27511",
    "sg:province":"NC",
    "sg:tags":[
        "dealership"
    ],
    "sg:website":"www.hendrickauto.com",
    "wof:name":"Hendrick Dodge",
    "wof:placetype":"venue"
},
  "geometry": {"coordinates":[-78.809825,35.739798],"type":"Point"}
}