{
  "type": "Feature",
  "properties": {
    "iso:country":"US",
    "sg:address":"1010 Pennsylvania Ave",
    "sg:city":"Washington",
    "sg:classifiers":[
        {
            "category":"Government",
            "subcategory":"Office",
            "type":"Public Place"
        }
    ],
    "sg:phone":"+1 252 946 4086",
    "sg:postcode":"27889",
    "sg:province":"NC",
    "sg:tags":[
        "county"
    ],
    "wof:name":"Beaufort County Sch Board",
    "wof:placetype":"venue"
},
  "geometry": {"coordinates":[-77.036736,35.544074],"type":"Point"}
}