{
  "type": "Feature",
  "properties": {
    "addr:full":"106 E Taft Ave Asheboro NC 27203",
    "addr:housenumber":"106",
    "addr:postcode":"27203",
    "addr:street":"E Taft Ave",
    "iso:country":"US",
    "sg:address":"106 E Taft Ave",
    "sg:city":"Asheboro",
    "sg:classifiers":[
        {
            "category":"Banks & Credit Unions",
            "subcategory":"Bank",
            "type":"Services"
        }
    ],
    "sg:phone":"+1 336 626 8303",
    "sg:postcode":"27203",
    "sg:province":"NC",
    "wof:name":"First National Bank & Trust Co",
    "wof:placetype":"venue"
},
  "geometry": {"coordinates":[-79.815517,35.692132],"type":"Point"}
}