{
  "type": "Feature",
  "properties": {
    "iso:country":"US",
    "sg:address":"835 Ruebens Rd SW",
    "sg:city":"Concord",
    "sg:classifiers":[
        {
            "category":"Organizations",
            "subcategory":"Community Association",
            "type":"Services"
        }
    ],
    "sg:phone":"+1   ",
    "sg:postcode":"28027",
    "sg:province":"NC",
    "sg:tags":[
        "membership",
        "cl"
    ],
    "wof:name":"Hartsell Sports Assoc",
    "wof:placetype":"venue"
},
  "geometry": {"coordinates":[-80.611762,35.366775],"type":"Point"}
}