{
  "type": "Feature",
  "properties": {
    "iso:country":"US",
    "sg:address":"326 E 24th St",
    "sg:city":"Lumberton",
    "sg:classifiers":[
        {
            "category":"Government",
            "subcategory":"Office",
            "type":"Public Place"
        }
    ],
    "sg:phone":"+1 910 618 5527",
    "sg:postcode":"28358",
    "sg:province":"NC",
    "sg:tags":[
        "state",
        "taxation"
    ],
    "wof:name":"Revenue Dept",
    "wof:placetype":"venue"
},
  "geometry": {"coordinates":[-79.005205,34.63402],"type":"Point"}
}