{
  "type": "Feature",
  "properties": {
    "iso:country":"US",
    "sg:address":"100 Poe Ave",
    "sg:city":"Spring Lake",
    "sg:classifiers":[
        {
            "category":"Taxi",
            "type":"Transportation"
        }
    ],
    "sg:phone":"+1 910 497 6565",
    "sg:postcode":"28390",
    "sg:province":"NC",
    "sg:tags":[
        "taxicab"
    ],
    "wof:name":"Marshall Cab",
    "wof:placetype":"venue"
},
  "geometry": {"coordinates":[-78.970512,35.164069],"type":"Point"}
}