{
  "type": "Feature",
  "properties": {
    "addr:full":"1167 Edwards Rd Rural Hall NC 27045",
    "addr:housenumber":"1167",
    "addr:postcode":"27045",
    "addr:street":"Edwards Rd",
    "iso:country":"US",
    "sg:address":"1167 Edwards Rd",
    "sg:city":"Rural Hall",
    "sg:classifiers":[
        {
            "category":"Shopping",
            "type":"Retail Goods"
        }
    ],
    "sg:phone":"+1 336 969 6969",
    "sg:postcode":"27045",
    "sg:province":"NC",
    "sg:tags":[
        "awning",
        "canopy"
    ],
    "wof:name":"Awning Depot",
    "wof:placetype":"venue"
},
  "geometry": {"coordinates":[-80.279607,36.261778],"type":"Point"}
}