{
  "type": "Feature",
  "properties": {
    "iso:country":"US",
    "sg:address":"3962 Lindsey Ln",
    "sg:city":"La Grange",
    "sg:classifiers":[
        {
            "category":"Manufacturing",
            "subcategory":"Paper Products",
            "type":"Manufacturing & Wholesale Goods"
        }
    ],
    "sg:phone":"+1 252 566 2974",
    "sg:postcode":"28551",
    "sg:province":"NC",
    "sg:tags":[
        "mill"
    ],
    "wof:name":"Cindys Co",
    "wof:placetype":"venue"
},
  "geometry": {"coordinates":[-77.71815700000001,35.320222],"type":"Point"}
}