{
  "type": "Feature",
  "properties": {
    "addr:full":"1135 Virginia Blvd Murfreesboro NC 27855",
    "addr:housenumber":"1135",
    "addr:postcode":"27855",
    "addr:street":"Virginia Blvd",
    "iso:country":"US",
    "sg:address":"1135 Virginia Blvd",
    "sg:city":"Murfreesboro",
    "sg:classifiers":[
        {
            "category":"Professional",
            "subcategory":"Computer Services",
            "type":"Services"
        }
    ],
    "sg:phone":"+1 252 398 5000",
    "sg:postcode":"27855",
    "sg:province":"NC",
    "wof:name":"Hall's Computer Solutions",
    "wof:placetype":"venue"
},
  "geometry": {"coordinates":[-77.086011,36.444338],"type":"Point"}
}