{
  "type": "Feature",
  "properties": {
    "addr:full":"699 John Young Rd Lexington NC 27292",
    "addr:housenumber":"699",
    "addr:postcode":"27292",
    "addr:street":"John Young Rd",
    "iso:country":"US",
    "sg:address":"699 John Young Rd",
    "sg:city":"Lexington",
    "sg:classifiers":[
        {
            "category":"Organizations",
            "subcategory":"Religious Organization",
            "type":"Services"
        }
    ],
    "sg:phone":"+1   ",
    "sg:postcode":"27292",
    "sg:province":"NC",
    "wof:name":"Methodist Church",
    "wof:placetype":"venue"
},
  "geometry": {"coordinates":[-80.185227,35.768527],"type":"Point"}
}