{
  "type": "Feature",
  "properties": {
    "addr:full":"415 Naylor School Rd Roseboro NC 28382",
    "addr:housenumber":"415",
    "addr:postcode":"28382",
    "addr:street":"Naylor School Rd",
    "iso:country":"US",
    "sg:address":"415 Naylor School Rd",
    "sg:city":"Roseboro",
    "sg:classifiers":[
        {
            "category":"Professional",
            "type":"Services"
        }
    ],
    "sg:phone":"+1   ",
    "sg:postcode":"28382",
    "sg:province":"NC",
    "wof:name":"JMS Professional Services LLC",
    "wof:placetype":"venue"
},
  "geometry": {"coordinates":[-78.474137,35.129686],"type":"Point"}
}