{
  "type": "Feature",
  "properties": {
    "addr:full":"1214 Trogdon St North Wilkesboro NC 28659",
    "addr:housenumber":"1214",
    "addr:postcode":"28659",
    "addr:street":"Trogdon St",
    "iso:country":"US",
    "sg:address":"1214 Trogdon St",
    "sg:city":"North Wilkesboro",
    "sg:classifiers":[
        {
            "category":"Building & Trades",
            "subcategory":"Construction",
            "type":"Services"
        }
    ],
    "sg:phone":"+1 336 262 0480",
    "sg:postcode":"28659",
    "sg:province":"NC",
    "sg:tags":[
        "roofing",
        "contractor"
    ],
    "wof:name":"Randy Huffman Construction",
    "wof:placetype":"venue"
},
  "geometry": {"coordinates":[-81.150976,36.169864],"type":"Point"}
}