{
  "type": "Feature",
  "properties": {
    "iso:country":"US",
    "sg:address":"311 E Woodrow School Rd",
    "sg:city":"Murfreesboro",
    "sg:classifiers":[
        {
            "category":"Farming",
            "subcategory":"Farm",
            "type":"Manufacturing & Wholesale Goods"
        }
    ],
    "sg:phone":"+1 252 398 3349",
    "sg:postcode":"27855",
    "sg:province":"NC",
    "wof:name":"A & J Poultry Farm",
    "wof:placetype":"venue"
},
  "geometry": {"coordinates":[-77.06687599999999,36.399976],"type":"Point"}
}