{
  "type": "Feature",
  "properties": {
    "addr:full":"1905 Delaware Dr Charlotte NC 28215",
    "addr:housenumber":"1905",
    "addr:postcode":"28215",
    "addr:street":"Delaware Dr",
    "iso:country":"US",
    "sg:address":"1905 Delaware Dr",
    "sg:city":"Charlotte",
    "sg:classifiers":[
        {
            "category":"Real Estate",
            "subcategory":"Real Estate Operator",
            "type":"Services"
        }
    ],
    "sg:phone":"+1 704 536 1543",
    "sg:postcode":"28215",
    "sg:province":"NC",
    "sg:tags":[
        "apartment"
    ],
    "wof:name":"T R Lawing Realty Inc",
    "wof:placetype":"venue"
},
  "geometry": {"coordinates":[-80.754628,35.245532],"type":"Point"}
}