{
  "type": "Feature",
  "properties": {
    "iso:country":"US",
    "sg:address":"114 Pierce Rd",
    "sg:city":"Thomasville",
    "sg:classifiers":[
        {
            "category":"Building & Trades",
            "subcategory":"Plumbing",
            "type":"Services"
        }
    ],
    "sg:phone":"+1 336 472 9006",
    "sg:postcode":"27360",
    "sg:province":"NC",
    "sg:tags":[
        "tank",
        "septic"
    ],
    "wof:name":"Pierce Dolan Grading & Spetic",
    "wof:placetype":"venue"
},
  "geometry": {"coordinates":[-80.103211,35.824521],"type":"Point"}
}