{
  "type": "Feature",
  "properties": {
    "iso:country":"US",
    "sg:address":"4001 Durham-Chapel Hill Blvd",
    "sg:city":"Durham",
    "sg:classifiers":[
        {
            "category":"Restaurant",
            "type":"Food & Drink"
        }
    ],
    "sg:phone":"+1 919 490 9807",
    "sg:postcode":"27707",
    "sg:province":"NC",
    "wof:name":"Sbarro",
    "wof:placetype":"venue"
},
  "geometry": {"coordinates":[-78.958675,35.96936],"type":"Point"}
}