{
  "type": "Feature",
  "properties": {
    "addr:full":"510 Emergency Dr Lexington NC 27292",
    "addr:postcode":"27292",
    "addr:street":"Emergency Dr",
    "iso:country":"US",
    "sg:address":"510 Emergency Dr",
    "sg:city":"Lexington",
    "sg:classifiers":[
        {
            "category":"Health Services",
            "subcategory":"Doctor",
            "type":"Services"
        }
    ],
    "sg:phone":"+1   ",
    "sg:postcode":"27292",
    "sg:province":"NC",
    "sg:tags":[
        "medical"
    ],
    "wof:name":"Js Riggan MD",
    "wof:placetype":"venue"
},
  "geometry": {"coordinates":[-80.28609299999999,35.80706],"type":"Point"}
}