{
  "type": "Feature",
  "properties": {
    "addr:full":"104 Pence Ave Rockingham NC 28379",
    "addr:housenumber":"104",
    "addr:postcode":"28379",
    "addr:street":"Pence Ave",
    "iso:country":"US",
    "sg:address":"104 Pence Ave",
    "sg:city":"Rockingham",
    "sg:classifiers":[
        {
            "category":"Shopping",
            "type":"Retail Goods"
        }
    ],
    "sg:phone":"+1 910 997 2460",
    "sg:postcode":"28379",
    "sg:province":"NC",
    "sg:tags":[
        "pet",
        "shop"
    ],
    "wof:name":"Exotic Bird Shop",
    "wof:placetype":"venue"
},
  "geometry": {"coordinates":[-79.77172299999999,34.919625],"type":"Point"}
}