{
  "type": "Feature",
  "properties": {
    "addr:full":"8221 Concord Mills Blvd Concord NC 28027",
    "addr:housenumber":"8221",
    "addr:postcode":"28027",
    "addr:street":"Concord Mills Blvd",
    "iso:country":"US",
    "sg:address":"8221 Concord Mills Blvd",
    "sg:city":"Concord",
    "sg:classifiers":[
        {
            "category":"Shopping",
            "subcategory":"Clothing, Apparel, & Fashions",
            "type":"Retail Goods"
        },
        {
            "category":"Shopping",
            "subcategory":"Department Store",
            "type":"Retail Goods"
        },
        {
            "category":"Shopping",
            "subcategory":"Discount & Variety Stores",
            "type":"Retail Goods"
        }
    ],
    "sg:phone":"+1 704 979 1020",
    "sg:postcode":"28027",
    "sg:province":"NC",
    "sg:tags":[
        "apparel",
        "clothing",
        "women's"
    ],
    "wof:name":"Tj Maxx",
    "wof:placetype":"venue"
},
  "geometry": {"coordinates":[-80.718942,35.371605],"type":"Point"}
}