{
  "type": "Feature",
  "properties": {
    "iso:country":"US",
    "sg:address":"501 Miller St",
    "sg:city":"Winston Salem",
    "sg:classifiers":[
        {
            "category":"Social Services",
            "subcategory":"Child Care",
            "type":"Services"
        }
    ],
    "sg:phone":"+1 336 725 3530",
    "sg:postcode":"27103",
    "sg:province":"NC",
    "sg:tags":[
        "kindergarten",
        "academic",
        "school"
    ],
    "wof:name":"Ardmore Baptist Weekday Prgrm",
    "wof:placetype":"venue"
},
  "geometry": {"coordinates":[-80.273579,36.084847],"type":"Point"}
}