{
  "type": "Feature",
  "properties": {
    "iso:country":"US",
    "sg:address":"2802 Pinecroft Rd",
    "sg:city":"Greensboro",
    "sg:classifiers":[
        {
            "category":"Retail",
            "subcategory":"Auto Repair",
            "type":"Services"
        }
    ],
    "sg:phone":"+1 336 547 9043",
    "sg:postcode":"27407",
    "sg:province":"NC",
    "sg:tags":[
        "repairing",
        "automobile"
    ],
    "wof:name":"C & J Auto Repair",
    "wof:placetype":"venue"
},
  "geometry": {"coordinates":[-79.839624,36.021035],"type":"Point"}
}