{
  "type": "Feature",
  "properties": {
    "iso:country":"US",
    "sg:address":"8000 Fayetteville Rd",
    "sg:city":"Raleigh",
    "sg:classifiers":[
        {
            "category":"Restaurant",
            "type":"Food & Drink"
        }
    ],
    "sg:menulink":"http://www.allmenus.com/nc/swift-creek/156305-hardees/menu/",
    "sg:phone":"+1 919 772 9503",
    "sg:postcode":"27603",
    "sg:province":"NC",
    "sg:tags":[
        "burger",
        "american"
    ],
    "wof:name":"Hardee's",
    "wof:placetype":"venue"
},
  "geometry": {"coordinates":[-78.700149,35.665383],"type":"Point"}
}