{
  "type": "Feature",
  "properties": {
    "iso:country":"US",
    "sg:address":"682 Dallas Spencer Mountain Rd",
    "sg:city":"Dallas",
    "sg:classifiers":[
        {
            "category":"Organizations",
            "subcategory":"Religious Organization",
            "type":"Services"
        }
    ],
    "sg:phone":"+1 704 923 0080",
    "sg:postcode":"28034",
    "sg:province":"NC",
    "sg:tags":[
        "church"
    ],
    "wof:name":"Mountainview Freewill Bapt Chr",
    "wof:placetype":"venue"
},
  "geometry": {"coordinates":[-81.140788,35.320657],"type":"Point"}
}