{
  "type": "Feature",
  "properties": {
    "addr:full":"105 W Chatham St Cary NC 27511",
    "addr:housenumber":"105",
    "addr:postcode":"27511",
    "addr:street":"W Chatham St",
    "iso:country":"US",
    "sg:address":"105 W Chatham St",
    "sg:city":"Cary",
    "sg:classifiers":[
        {
            "category":"Shopping",
            "subcategory":"Gifts & Souvenirs",
            "type":"Retail Goods"
        }
    ],
    "sg:phone":"+1 919 467 2355",
    "sg:postcode":"27511",
    "sg:province":"NC",
    "sg:tags":[
        "stationery",
        "greeting",
        "card"
    ],
    "wof:name":"Cary R & D Enterprise",
    "wof:placetype":"venue"
},
  "geometry": {"coordinates":[-78.781502,35.787201],"type":"Point"}
}