{
  "type": "Feature",
  "properties": {
    "addr:full":"2375 N Wesleyan Blvd Rocky Mount NC 27804",
    "addr:housenumber":"2375",
    "addr:postcode":"27804",
    "addr:street":"N Wesleyan Blvd",
    "iso:country":"US",
    "sg:address":"2375 N Wesleyan Blvd",
    "sg:city":"Rocky Mount",
    "sg:classifiers":[
        {
            "category":"Building & Trades",
            "subcategory":"Construction",
            "type":"Services"
        }
    ],
    "sg:phone":"+1 252 442 3733",
    "sg:postcode":"27804",
    "sg:province":"NC",
    "sg:tags":[
        "concrete",
        "contractor"
    ],
    "wof:name":"Dpd Team Concrete",
    "wof:placetype":"venue"
},
  "geometry": {"coordinates":[-77.778599,35.995098],"type":"Point"}
}