{
  "type": "Feature",
  "properties": {
    "iso:country":"US",
    "sg:address":"3214 Jack Richardson Rd",
    "sg:city":"Elizabethtown",
    "sg:classifiers":[
        {
            "category":"Farming",
            "subcategory":"Farm",
            "type":"Manufacturing & Wholesale Goods"
        }
    ],
    "sg:phone":"+1 910 588 4347",
    "sg:postcode":"28337",
    "sg:province":"NC",
    "wof:name":"Steve Bunn Hog Farm",
    "wof:placetype":"venue"
},
  "geometry": {"coordinates":[-78.57110299999999,34.773346],"type":"Point"}
}