{
  "type": "Feature",
  "properties": {
    "iso:country":"US",
    "sg:address":"468 Crowfields Dr",
    "sg:city":"Asheville",
    "sg:classifiers":[
        {
            "category":"Banks & Credit Unions",
            "subcategory":"Financial Services",
            "type":"Services"
        }
    ],
    "sg:phone":"+1 828 274 5383",
    "sg:postcode":"28803",
    "sg:province":"NC",
    "sg:tags":[
        "trust",
        "investment",
        "real estate"
    ],
    "wof:name":"Bradley Lumber Company Inc",
    "wof:placetype":"venue"
},
  "geometry": {"coordinates":[-82.529039,35.506943],"type":"Point"}
}