{
  "type": "Feature",
  "properties": {
    "addr:full":"4505 Falls of Neuse Road Suite 420 Raleigh NC 27609",
    "addr:housenumber":"4505",
    "addr:postcode":"27609",
    "addr:street":"Falls Of Neuse Road Suite 420",
    "iso:country":"US",
    "sg:address":"4505 Falls of Neuse Road Suite 420",
    "sg:city":"Raleigh",
    "sg:classifiers":[
        {
            "category":"Professional",
            "subcategory":"Research",
            "type":"Services"
        }
    ],
    "sg:phone":"+1 919 792 1700",
    "sg:postcode":"27609",
    "sg:province":"NC",
    "sg:website":"http://www.arborpharma.com/",
    "wof:name":"Arbor Pharmaceuticals",
    "wof:placetype":"venue"
},
  "geometry": {"coordinates":[-78.61269299999999,35.842056],"type":"Point"}
}