{
  "type": "Feature",
  "properties": {
    "addr:full":"5720 Six Forks Rd Raleigh NC 27609",
    "addr:housenumber":"5720",
    "addr:postcode":"27609",
    "addr:street":"Six Forks Rd",
    "iso:country":"US",
    "sg:address":"5720 Six Forks Rd",
    "sg:city":"Raleigh",
    "sg:classifiers":[
        {
            "category":"Professional",
            "subcategory":"Credit Reporting & Collection",
            "type":"Services"
        }
    ],
    "sg:phone":"+1 919 844 8950",
    "sg:postcode":"27609",
    "sg:province":"NC",
    "sg:tags":[
        "agency"
    ],
    "wof:name":"National Tenant Network",
    "wof:placetype":"venue"
},
  "geometry": {"coordinates":[-78.63881600000001,35.859943],"type":"Point"}
}