{
  "type": "Feature",
  "properties": {
    "addr:full":"801 Lindsay St High Point NC 27262",
    "addr:housenumber":"801",
    "addr:postcode":"27262",
    "addr:street":"Lindsay St",
    "iso:country":"US",
    "sg:address":"801 Lindsay St",
    "sg:city":"High Point",
    "sg:classifiers":[
        {
            "category":"Insurance",
            "subcategory":"Life Insurance",
            "type":"Services"
        }
    ],
    "sg:phone":"+1 336 869 4208",
    "sg:postcode":"27262",
    "sg:province":"NC",
    "sg:tags":[
        "carrier"
    ],
    "wof:name":"MetLife",
    "wof:placetype":"venue"
},
  "geometry": {"coordinates":[-80.015321,35.96452],"type":"Point"}
}