{
  "type": "Feature",
  "properties": {
    "addr:full":"620 N Main St Belmont NC 28012",
    "addr:housenumber":"620",
    "addr:postcode":"28012",
    "addr:street":"N Main St",
    "iso:country":"US",
    "sg:address":"620 N Main St",
    "sg:city":"Belmont",
    "sg:classifiers":[
        {
            "category":"Government",
            "subcategory":"Office",
            "type":"Public Place"
        }
    ],
    "sg:phone":"+1 704 825 4046",
    "sg:postcode":"28012",
    "sg:province":"NC",
    "sg:tags":[
        "county",
        "program",
        "adm"
    ],
    "wof:name":"Gaston County Economic Dev",
    "wof:placetype":"venue"
},
  "geometry": {"coordinates":[-81.04286399999999,35.25369],"type":"Point"}
}