{
  "type": "Feature",
  "properties": {
    "iso:country":"US",
    "sg:address":"5638 Fairway View Dr",
    "sg:city":"Charlotte",
    "sg:classifiers":[
        {
            "category":"Building & Trades",
            "subcategory":"Landscaping Services",
            "type":"Services"
        }
    ],
    "sg:phone":"+1 704 577 2187",
    "sg:postcode":"28277",
    "sg:province":"NC",
    "sg:tags":[
        "designer",
        "landscape"
    ],
    "wof:name":"J D Furr Landscape & Design",
    "wof:placetype":"venue"
},
  "geometry": {"coordinates":[-80.81505799999999,35.077195],"type":"Point"}
}