{
  "type": "Feature",
  "properties": {
    "iso:country":"US",
    "sg:address":"1105 E Wendover Ave",
    "sg:city":"Greensboro",
    "sg:classifiers":[
        {
            "category":"Professional",
            "subcategory":"Business Services",
            "type":"Services"
        },
        {
            "category":"Building & Trades",
            "subcategory":"Construction",
            "type":"Services"
        }
    ],
    "sg:phone":"+1 336 272 6696",
    "sg:postcode":"27405",
    "sg:province":"NC",
    "sg:tags":[
        "steel"
    ],
    "wof:name":"United Steel Detailers",
    "wof:placetype":"venue"
},
  "geometry": {"coordinates":[-79.77046300000001,36.087974],"type":"Point"}
}