{
  "type": "Feature",
  "properties": {
    "iso:country":"US",
    "sg:address":"17505 W Catawba Ave",
    "sg:city":"Cornelius",
    "sg:classifiers":[
        {
            "category":"Manufacturing",
            "subcategory":"Paper Products",
            "type":"Manufacturing & Wholesale Goods"
        }
    ],
    "sg:phone":"+1 704 895 0443",
    "sg:postcode":"28031",
    "sg:province":"NC",
    "sg:tags":[
        "paperboard",
        "packing",
        "container",
        "mfg"
    ],
    "wof:name":"International Paper",
    "wof:placetype":"venue"
},
  "geometry": {"coordinates":[-80.88854600000001,35.454002],"type":"Point"}
}