{
  "type": "Feature",
  "properties": {
    "addr:full":"3637 Cokey Rd Rocky Mount NC 27801",
    "addr:housenumber":"3637",
    "addr:postcode":"27801",
    "addr:street":"Cokey Rd",
    "iso:country":"US",
    "sg:address":"3637 Cokey Rd",
    "sg:city":"Rocky Mount",
    "sg:classifiers":[
        {
            "category":"Retail",
            "subcategory":"Auto Repair",
            "type":"Services"
        }
    ],
    "sg:phone":"+1   ",
    "sg:postcode":"27801",
    "sg:province":"NC",
    "sg:tags":[
        "general"
    ],
    "wof:name":"Westside Repair",
    "wof:placetype":"venue"
},
  "geometry": {"coordinates":[-77.745082,35.908375],"type":"Point"}
}