{
  "type": "Feature",
  "properties": {
    "iso:country":"US",
    "sg:address":"6926 Jordan Rd",
    "sg:city":"Ramseur",
    "sg:classifiers":[
        {
            "category":"Restaurant",
            "type":"Food & Drink"
        }
    ],
    "sg:menulink":"http://www.allmenus.com/nc/columbia/85467-dominos-pizza/menu/",
    "sg:phone":"+1 336 824 2121",
    "sg:postcode":"27316",
    "sg:province":"NC",
    "sg:tags":[
        "american",
        "wing",
        "pizza"
    ],
    "wof:name":"Domino's Pizza",
    "wof:placetype":"venue"
},
  "geometry": {"coordinates":[-79.648538,35.73957],"type":"Point"}
}