{
  "type": "Feature",
  "properties": {
    "iso:country":"US",
    "sg:address":"3117 Millersville Rd",
    "sg:city":"Taylorsville",
    "sg:classifiers":[
        {
            "category":"Retail",
            "subcategory":"Repair Shop",
            "type":"Services"
        }
    ],
    "sg:phone":"+1   ",
    "sg:postcode":"28681",
    "sg:province":"NC",
    "sg:tags":[
        "refrigeration"
    ],
    "wof:name":"Sutphin Refrigeration",
    "wof:placetype":"venue"
},
  "geometry": {"coordinates":[-81.140456,35.866234],"type":"Point"}
}