{
  "type": "Feature",
  "properties": {
    "iso:country":"US",
    "sg:address":"205 Ridge St NW",
    "sg:city":"Lenoir",
    "sg:classifiers":[
        {
            "category":"Professional",
            "subcategory":"Lawyer & Legal Services",
            "type":"Services"
        }
    ],
    "sg:phone":"+1 828 754 4266",
    "sg:postcode":"28645",
    "sg:province":"NC",
    "sg:tags":[
        "attorney"
    ],
    "wof:name":"Macon A Clark PA",
    "wof:placetype":"venue"
},
  "geometry": {"coordinates":[-81.538506,35.916543],"type":"Point"}
}