{
  "type": "Feature",
  "properties": {
    "addr:full":"945 Osceola St Gastonia NC 28054",
    "addr:housenumber":"945",
    "addr:postcode":"28054",
    "addr:street":"Osceola St",
    "iso:country":"US",
    "sg:address":"945 Osceola St",
    "sg:city":"Gastonia",
    "sg:classifiers":[
        {
            "category":"Building & Trades",
            "subcategory":"Construction",
            "type":"Services"
        },
        {
            "category":"Government",
            "subcategory":"Office",
            "type":"Public Place"
        }
    ],
    "sg:phone":"+1 704 868 2149",
    "sg:postcode":"28054",
    "sg:province":"NC",
    "sg:tags":[
        "grading",
        "transportation",
        "contractor"
    ],
    "wof:name":"Public Works Fleet Maintenance",
    "wof:placetype":"venue"
},
  "geometry": {"coordinates":[-81.176687,35.251765],"type":"Point"}
}