{
  "type": "Feature",
  "properties": {
    "addr:full":"112 Aviation Pkwy Morrisville NC 27560",
    "addr:housenumber":"112",
    "addr:postcode":"27560",
    "addr:street":"Aviation Pkwy",
    "iso:country":"US",
    "sg:address":"112 Aviation Pkwy",
    "sg:city":"Morrisville",
    "sg:classifiers":[
        {
            "category":"Building & Trades",
            "subcategory":"Construction",
            "type":"Services"
        }
    ],
    "sg:phone":"+1 919 465 0036",
    "sg:postcode":"27560",
    "sg:province":"NC",
    "sg:tags":[
        "concrete",
        "contractor"
    ],
    "wof:name":"A & W Concrete Svc Inc",
    "wof:placetype":"venue"
},
  "geometry": {"coordinates":[-78.82360199999999,35.8241],"type":"Point"}
}