{
  "type": "Feature",
  "properties": {
    "addr:full":"1606 Page Rd Durham NC 27703",
    "addr:housenumber":"1606",
    "addr:postcode":"27703",
    "addr:street":"Page Rd",
    "iso:country":"US",
    "sg:address":"1606 Page Rd",
    "sg:city":"Durham",
    "sg:classifiers":[
        {
            "category":"Autos & Motor Vehicles",
            "subcategory":"Boat Sales",
            "type":"Retail Goods"
        }
    ],
    "sg:phone":"+1 919 596 4100",
    "sg:postcode":"27703",
    "sg:province":"NC",
    "wof:name":"Boats Unlimited",
    "wof:placetype":"venue"
},
  "geometry": {"coordinates":[-78.822981,35.938992],"type":"Point"}
}