{
  "type": "Feature",
  "properties": {
    "addr:full":"1619 Charles Raper Jonas Hwy Mount Holly NC 28120",
    "addr:housenumber":"1619",
    "addr:postcode":"28120",
    "addr:street":"Charles Raper Jonas Hwy",
    "iso:country":"US",
    "sg:address":"1619 Charles Raper Jonas Hwy",
    "sg:city":"Mount Holly",
    "sg:classifiers":[
        {
            "category":"Building & Trades",
            "subcategory":"Construction",
            "type":"Services"
        }
    ],
    "sg:phone":"+1 704 822 6393",
    "sg:postcode":"28120",
    "sg:province":"NC",
    "sg:tags":[
        "house",
        "mater"
    ],
    "wof:name":"Cvr Concrete Construction",
    "wof:placetype":"venue"
},
  "geometry": {"coordinates":[-81.053577,35.324998],"type":"Point"}
}