{
  "type": "Feature",
  "properties": {
    "addr:full":"745 Oscar Rd Zionville NC 28698",
    "addr:housenumber":"745",
    "addr:postcode":"28698",
    "addr:street":"Oscar Rd",
    "iso:country":"US",
    "sg:address":"745 Oscar Rd",
    "sg:city":"Zionville",
    "sg:classifiers":[
        {
            "category":"Manufacturing",
            "subcategory":"Building Materials",
            "type":"Manufacturing & Wholesale Goods"
        }
    ],
    "sg:phone":"+1 336 385 6063",
    "sg:postcode":"28698",
    "sg:province":"NC",
    "sg:tags":[
        "mfg"
    ],
    "wof:name":"Windfall Woodworks",
    "wof:placetype":"venue"
},
  "geometry": {"coordinates":[-81.70586900000001,36.390294],"type":"Point"}
}