{
  "type": "Feature",
  "properties": {
    "addr:full":"420 E Arlington Blvd Greenville NC 27858",
    "addr:housenumber":"420",
    "addr:postcode":"27858",
    "addr:street":"E Arlington Blvd",
    "iso:country":"US",
    "sg:address":"420 E Arlington Blvd",
    "sg:city":"Greenville",
    "sg:classifiers":[
        {
            "category":"Personal",
            "subcategory":"Beauty Salon",
            "type":"Services"
        }
    ],
    "sg:phone":"+1 252 353 4025",
    "sg:postcode":"27858",
    "sg:province":"NC",
    "sg:tags":[
        "shop"
    ],
    "wof:name":"Panache Hair Nail & Skin Spa",
    "wof:placetype":"venue"
},
  "geometry": {"coordinates":[-77.370374,35.58541],"type":"Point"}
}