{
  "type": "Feature",
  "properties": {
    "addr:full":"3225 Bessemer City Rd Bessemer City NC 28016",
    "addr:housenumber":"3225",
    "addr:postcode":"28016",
    "addr:street":"Bessemer City Rd",
    "iso:country":"US",
    "sg:address":"3225 Bessemer City Rd",
    "sg:city":"Bessemer City",
    "sg:classifiers":[
        {
            "category":"Manufacturing",
            "subcategory":"Metals",
            "type":"Manufacturing & Wholesale Goods"
        }
    ],
    "sg:phone":"+1 704 629 2327",
    "sg:postcode":"28016",
    "sg:province":"NC",
    "sg:tags":[
        "anodizing"
    ],
    "wof:name":"J V Anodizing Inc",
    "wof:placetype":"venue"
},
  "geometry": {"coordinates":[-81.25606999999999,35.287395],"type":"Point"}
}