{
  "type": "Feature",
  "properties": {
    "iso:country":"US",
    "sg:address":"521 S Main St",
    "sg:city":"King",
    "sg:classifiers":[
        {
            "category":"Restaurant",
            "type":"Food & Drink"
        }
    ],
    "sg:phone":"+1 336 983 3791",
    "sg:postcode":"27021",
    "sg:province":"NC",
    "wof:name":"King Kitchen",
    "wof:placetype":"venue"
},
  "geometry": {"coordinates":[-80.361096,36.275515],"type":"Point"}
}