{
  "type": "Feature",
  "properties": {
    "addr:full":"104 Davenport Ln Edenton NC 27932",
    "addr:housenumber":"104",
    "addr:postcode":"27932",
    "addr:street":"Davenport Ln",
    "iso:country":"US",
    "sg:address":"104 Davenport Ln",
    "sg:city":"Edenton",
    "sg:classifiers":[
        {
            "category":"Shopping",
            "subcategory":"Crafts & Fabrics",
            "type":"Retail Goods"
        }
    ],
    "sg:phone":"+1 252 482 4622",
    "sg:postcode":"27932",
    "sg:province":"NC",
    "sg:tags":[
        "shop",
        "sewing"
    ],
    "wof:name":"Mill End Shop",
    "wof:placetype":"venue"
},
  "geometry": {"coordinates":[-76.577381,36.089313],"type":"Point"}
}