{
  "type": "Feature",
  "properties": {
    "addr:full":"210 State Hwy 43 Vanceboro NC 28586",
    "addr:housenumber":"210",
    "addr:postcode":"28586",
    "addr:street":"State Hwy 43",
    "iso:country":"US",
    "sg:address":"210 State Hwy 43",
    "sg:city":"Vanceboro",
    "sg:classifiers":[
        {
            "category":"Home & Garden",
            "subcategory":"Hardware",
            "type":"Retail Goods"
        }
    ],
    "sg:phone":"+1 252 244 2444",
    "sg:postcode":"28586",
    "sg:province":"NC",
    "wof:name":"Vanceboro Hardware",
    "wof:placetype":"venue"
},
  "geometry": {"coordinates":[-77.15791,35.308313],"type":"Point"}
}