{
  "type": "Feature",
  "properties": {
    "addr:full":"204 N Drake St Nashville NC 27856",
    "addr:housenumber":"204",
    "addr:postcode":"27856",
    "addr:street":"N Drake St",
    "iso:country":"US",
    "sg:address":"204 N Drake St",
    "sg:city":"Nashville",
    "sg:classifiers":[
        {
            "category":"Organizations",
            "subcategory":"Religious Organization",
            "type":"Services"
        }
    ],
    "sg:phone":"+1   ",
    "sg:postcode":"27856",
    "sg:province":"NC",
    "wof:name":"St Luke Baptist Church",
    "wof:placetype":"venue"
},
  "geometry": {"coordinates":[-77.968008,35.977177],"type":"Point"}
}