{
  "type": "Feature",
  "properties": {
    "addr:full":"1108 Clifton St Raleigh NC 27604",
    "addr:housenumber":"1108",
    "addr:postcode":"27604",
    "addr:street":"Clifton St",
    "iso:country":"US",
    "sg:address":"1108 Clifton St",
    "sg:city":"Raleigh",
    "sg:classifiers":[
        {
            "category":"Personal",
            "subcategory":"Beauty Salon",
            "type":"Services"
        }
    ],
    "sg:phone":"+1   ",
    "sg:postcode":"27604",
    "sg:province":"NC",
    "sg:tags":[
        "shop"
    ],
    "wof:name":"Fresh Cuts By Georgette",
    "wof:placetype":"venue"
},
  "geometry": {"coordinates":[-78.62747400000001,35.793888],"type":"Point"}
}