{
  "type": "Feature",
  "properties": {
    "iso:country":"US",
    "sg:address":"1111 Chester Rd",
    "sg:city":"Winston Salem",
    "sg:classifiers":[
        {
            "category":"Professional",
            "subcategory":"Lawyer & Legal Services",
            "type":"Services"
        }
    ],
    "sg:phone":"+1 336 765 6267",
    "sg:postcode":"27104",
    "sg:province":"NC",
    "sg:tags":[
        "attorney"
    ],
    "wof:name":"Clive I Goodson",
    "wof:placetype":"venue"
},
  "geometry": {"coordinates":[-80.32095200000001,36.111128],"type":"Point"}
}