{
  "type": "Feature",
  "properties": {
    "addr:full":"3403 Hickory Blvd Hudson NC 28638",
    "addr:housenumber":"3403",
    "addr:postcode":"28638",
    "addr:street":"Hickory Blvd",
    "iso:country":"US",
    "sg:address":"3403 Hickory Blvd",
    "sg:city":"Hudson",
    "sg:classifiers":[
        {
            "category":"Food & Beverages",
            "subcategory":"Groceries & Convenience Stores",
            "type":"Retail Goods"
        }
    ],
    "sg:phone":"+1 828 396 2490",
    "sg:postcode":"28638",
    "sg:province":"NC",
    "wof:name":"Oak Hill Superette",
    "wof:placetype":"venue"
},
  "geometry": {"coordinates":[-81.45787300000001,35.832953],"type":"Point"}
}