{
  "type": "Feature",
  "properties": {
    "iso:country":"US",
    "sg:address":"240 N Pea Ridge Rd",
    "sg:city":"Pittsboro",
    "sg:classifiers":[
        {
            "category":"Building & Trades",
            "subcategory":"Landscaping Services",
            "type":"Services"
        }
    ],
    "sg:phone":"+1 919 542 4375",
    "sg:postcode":"27312",
    "sg:province":"NC",
    "wof:name":"Clark Landscaping Contractors",
    "wof:placetype":"venue"
},
  "geometry": {"coordinates":[-79.08143099999999,35.731099],"type":"Point"}
}