{
  "type": "Feature",
  "properties": {
    "iso:country":"US",
    "sg:address":"1325 Military Cutoff Rd",
    "sg:city":"Wilmington",
    "sg:classifiers":[
        {
            "category":"Banks & Credit Unions",
            "subcategory":"Bank",
            "type":"Services"
        }
    ],
    "sg:phone":"+1 910 251 5313",
    "sg:postcode":"28405",
    "sg:province":"NC",
    "sg:tags":[
        "federal",
        "agency"
    ],
    "wof:name":"Bank Of America",
    "wof:placetype":"venue"
},
  "geometry": {"coordinates":[-77.82929300000001,34.229884],"type":"Point"}
}