{
  "type": "Feature",
  "properties": {
    "iso:country":"US",
    "sg:address":"504 Eastside Dr",
    "sg:city":"Statesville",
    "sg:classifiers":[
        {
            "category":"Retail",
            "subcategory":"Repair Shop",
            "type":"Services"
        }
    ],
    "sg:phone":"+1   ",
    "sg:postcode":"28625",
    "sg:province":"NC",
    "wof:name":"Pardues Upholstery",
    "wof:placetype":"venue"
},
  "geometry": {"coordinates":[-80.858924,35.785929],"type":"Point"}
}