{
  "type": "Feature",
  "properties": {
    "iso:country":"US",
    "sg:address":"2815 S Wilmington St",
    "sg:city":"Raleigh",
    "sg:classifiers":[
        {
            "category":"Building & Trades",
            "subcategory":"Construction",
            "type":"Services"
        },
        {
            "category":"Building & Trades",
            "subcategory":"Electrical",
            "type":"Services"
        },
        {
            "category":"Home & Garden",
            "subcategory":"Household Appliances",
            "type":"Retail Goods"
        },
        {
            "category":"Home & Garden",
            "subcategory":"Building Materials",
            "type":"Retail Goods"
        },
        {
            "category":"Professional",
            "subcategory":"Engineering",
            "type":"Services"
        },
        {
            "category":"Building & Trades",
            "subcategory":"Cleaning & Sanitation",
            "type":"Services"
        }
    ],
    "sg:phone":"+1 919 926 7981",
    "sg:postcode":"27603",
    "sg:province":"NC",
    "sg:tags":[
        "repair",
        "purifying",
        "specialty",
        "quality-indoor",
        "duct",
        "systems-repairing",
        "system",
        "contractor",
        "equipment",
        "furnaces-heating",
        "furnaces-repairing",
        "pump",
        "insulation",
        "heating",
        "heat",
        "air conditioning"
    ],
    "sg:website":"http://www.tomtracker.com/redirect.cfm?bID=20757&hID=123076",
    "wof:name":"Service Experts of the Triangle",
    "wof:placetype":"venue"
},
  "geometry": {"coordinates":[-78.646787,35.743593],"type":"Point"}
}