{
  "type": "Feature",
  "properties": {
    "iso:country":"US",
    "sg:address":"2121 Central Ave",
    "sg:city":"Charlotte",
    "sg:classifiers":[
        {
            "category":"Home & Garden",
            "subcategory":"Carpets & Floor Coverings",
            "type":"Retail Goods"
        }
    ],
    "sg:phone":"+1 704 335 1121",
    "sg:postcode":"28205",
    "sg:province":"NC",
    "sg:tags":[
        "flooring",
        "contractor"
    ],
    "wof:name":"Affordable Flooring",
    "wof:placetype":"venue"
},
  "geometry": {"coordinates":[-80.805064,35.21984],"type":"Point"}
}