{
  "type": "Feature",
  "properties": {
    "addr:full":"537 Main St Hudson NC 28638",
    "addr:housenumber":"537",
    "addr:postcode":"28638",
    "addr:street":"Main St",
    "iso:country":"US",
    "sg:address":"537 Main St",
    "sg:city":"Hudson",
    "sg:classifiers":[
        {
            "category":"Banks & Credit Unions",
            "subcategory":"Bank",
            "type":"Services"
        }
    ],
    "sg:phone":"+1 828 728 1850",
    "sg:postcode":"28638",
    "sg:province":"NC",
    "sg:website":"www.bankofgranite.com",
    "wof:name":"Bank Of Granite",
    "wof:placetype":"venue"
},
  "geometry": {"coordinates":[-81.493983,35.84611],"type":"Point"}
}