{
  "type": "Feature",
  "properties": {
    "addr:full":"105 Langston Mill Ct Cary NC 27518",
    "addr:housenumber":"105",
    "addr:postcode":"27518",
    "addr:street":"Langston Mill Ct",
    "iso:country":"US",
    "sg:address":"105 Langston Mill Ct",
    "sg:city":"Cary",
    "sg:classifiers":[
        {
            "category":"Professional",
            "type":"Services"
        }
    ],
    "sg:phone":"+1 919 387 1775",
    "sg:postcode":"27518",
    "sg:province":"NC",
    "sg:tags":[
        "establishment"
    ],
    "wof:name":"DKO Enterprises",
    "wof:placetype":"venue"
},
  "geometry": {"coordinates":[-78.79068700000001,35.706761],"type":"Point"}
}