{
  "type": "Feature",
  "properties": {
    "addr:full":"209 N Oak St Spindale NC 28160",
    "addr:housenumber":"209",
    "addr:postcode":"28160",
    "addr:street":"N Oak St",
    "iso:country":"US",
    "sg:address":"209 N Oak St",
    "sg:city":"Spindale",
    "sg:classifiers":[
        {
            "category":"Arena",
            "subcategory":"Sports Club",
            "type":"Entertainment"
        }
    ],
    "sg:phone":"+1 828 286 0073",
    "sg:postcode":"28160",
    "sg:province":"NC",
    "sg:tags":[
        "soccer"
    ],
    "wof:name":"Rutherford County Soccer Assn",
    "wof:placetype":"venue"
},
  "geometry": {"coordinates":[-81.932469,35.358819],"type":"Point"}
}