{
  "type": "Feature",
  "properties": {
    "addr:full":"1105 Zion Church Rd Mount Olive NC 28365",
    "addr:housenumber":"1105",
    "addr:postcode":"28365",
    "addr:street":"Zion Church Rd",
    "iso:country":"US",
    "sg:address":"1105 Zion Church Rd",
    "sg:city":"Mount Olive",
    "sg:classifiers":[
        {
            "category":"Real Estate",
            "subcategory":"Real Estate Operator",
            "type":"Services"
        }
    ],
    "sg:phone":"+1 919 658 5675",
    "sg:postcode":"28365",
    "sg:province":"NC",
    "sg:tags":[
        "mobile",
        "home",
        "site"
    ],
    "wof:name":"Sand Hill Mobile Home Park",
    "wof:placetype":"venue"
},
  "geometry": {"coordinates":[-77.93203200000001,35.180748],"type":"Point"}
}