{
  "type": "Feature",
  "properties": {
    "iso:country":"US",
    "sg:address":"1559 S Main St",
    "sg:city":"Waynesville",
    "sg:classifiers":[
        {
            "category":"Autos & Motor Vehicles",
            "subcategory":"Auto Supplies",
            "type":"Retail Goods"
        }
    ],
    "sg:phone":"+1 828 456 7801",
    "sg:postcode":"28786",
    "sg:province":"NC",
    "sg:tags":[
        "tire"
    ],
    "wof:name":"Maynor Tire",
    "wof:placetype":"venue"
},
  "geometry": {"coordinates":[-83.000953,35.471451],"type":"Point"}
}