{
  "type": "Feature",
  "properties": {
    "iso:country":"US",
    "sg:address":"4648 Baines Loop Rd",
    "sg:city":"Spring Hope",
    "sg:classifiers":[
        {
            "category":"Recreation",
            "type":"Entertainment"
        }
    ],
    "sg:phone":"+1 252 478 4491",
    "sg:postcode":"27882",
    "sg:province":"NC",
    "sg:tags":[
        "amusement"
    ],
    "wof:name":"Stanhope Recreation Assoc Inc",
    "wof:placetype":"venue"
},
  "geometry": {"coordinates":[-78.07811700000001,35.866016],"type":"Point"}
}