{
  "type": "Feature",
  "properties": {
    "addr:full":"3638 Brentwood Dr Gastonia NC 28056",
    "addr:housenumber":"3638",
    "addr:postcode":"28056",
    "addr:street":"Brentwood Dr",
    "iso:country":"US",
    "sg:address":"3638 Brentwood Dr",
    "sg:city":"Gastonia",
    "sg:phone":"+1 704 864 7324",
    "sg:postcode":"28056",
    "sg:province":"NC",
    "sg:tags":[
        "farm",
        "cotton"
    ],
    "wof:name":"Dan S Lafar",
    "wof:placetype":"venue"
},
  "geometry": {"coordinates":[-81.150007,35.212753],"type":"Point"}
}