{
  "type": "Feature",
  "properties": {
    "iso:country":"US",
    "sg:address":"2035 Saint Matthews Church Rd",
    "sg:city":"Salisbury",
    "sg:classifiers":[
        {
            "category":"Building & Trades",
            "subcategory":"Electrical",
            "type":"Services"
        }
    ],
    "sg:phone":"+1 704 633 0107",
    "sg:postcode":"28146",
    "sg:province":"NC",
    "sg:tags":[
        "electrical",
        "contractor"
    ],
    "wof:name":"Barry E Chaffin Electric Co",
    "wof:placetype":"venue"
},
  "geometry": {"coordinates":[-80.312799,35.597444],"type":"Point"}
}