{
  "type": "Feature",
  "properties": {
    "iso:country":"US",
    "sg:address":"1000 Washington St",
    "sg:city":"Eden",
    "sg:classifiers":[
        {
            "category":"Retail",
            "subcategory":"Repair Shop",
            "type":"Services"
        }
    ],
    "sg:phone":"+1 336 623 9700",
    "sg:postcode":"27288",
    "sg:province":"NC",
    "sg:tags":[
        "cleaners",
        "parts",
        "vacuum"
    ],
    "wof:name":"Economy Vac & Sew Center",
    "wof:placetype":"venue"
},
  "geometry": {"coordinates":[-79.774704,36.487328],"type":"Point"}
}