{
  "type": "Feature",
  "properties": {
    "addr:full":"292 McSwain Rd Forest City NC 28043",
    "addr:housenumber":"292",
    "addr:postcode":"28043",
    "addr:street":"Mcswain Rd",
    "iso:country":"US",
    "sg:address":"292 McSwain Rd",
    "sg:city":"Forest City",
    "sg:classifiers":[
        {
            "category":"Government",
            "subcategory":"Fire Station",
            "type":"Public Place"
        }
    ],
    "sg:phone":"+1 828 245 6876",
    "sg:postcode":"28043",
    "sg:province":"NC",
    "sg:tags":[
        "protection"
    ],
    "wof:name":"Sandy Mush Volunteer Fire Dept",
    "wof:placetype":"venue"
},
  "geometry": {"coordinates":[-81.848139,35.28555],"type":"Point"}
}