{
  "type": "Feature",
  "properties": {
    "iso:country":"US",
    "sg:address":"10901 Coachman Cir",
    "sg:city":"Charlotte",
    "sg:classifiers":[
        {
            "category":"Shopping",
            "subcategory":"Computers & Home Electronics",
            "type":"Retail Goods"
        }
    ],
    "sg:phone":"+1 704 846 5423",
    "sg:postcode":"28277",
    "sg:province":"NC",
    "sg:tags":[
        "equipment",
        "dealer"
    ],
    "wof:name":"Small Computer Concepts",
    "wof:placetype":"venue"
},
  "geometry": {"coordinates":[-80.799736,35.060671],"type":"Point"}
}