{
  "type": "Feature",
  "properties": {
    "addr:full":"861 Corcus Ferry Rd Hampstead NC 28443",
    "addr:housenumber":"861",
    "addr:postcode":"28443",
    "addr:street":"Corcus Ferry Rd",
    "iso:country":"US",
    "sg:address":"861 Corcus Ferry Rd",
    "sg:city":"Hampstead",
    "sg:classifiers":[
        {
            "category":"Shopping",
            "subcategory":"Music",
            "type":"Retail Goods"
        }
    ],
    "sg:phone":"+1 910 270 2419",
    "sg:postcode":"28443",
    "sg:province":"NC",
    "wof:name":"Golden Altar Records Inc",
    "wof:placetype":"venue"
},
  "geometry": {"coordinates":[-77.693046,34.368318],"type":"Point"}
}