{
  "type": "Feature",
  "properties": {
    "iso:country":"US",
    "sg:address":"4110 E Greensboro Chapel Hill Rd",
    "sg:city":"Graham",
    "sg:classifiers":[
        {
            "category":"Recreation",
            "type":"Entertainment"
        }
    ],
    "sg:phone":"+1   ",
    "sg:postcode":"27253",
    "sg:province":"NC",
    "wof:name":"Whitney Eli Recreation Center",
    "wof:placetype":"venue"
},
  "geometry": {"coordinates":[-79.300743,35.90639],"type":"Point"}
}