{
  "type": "Feature",
  "properties": {
    "addr:full":"54 Red Cedar Ln Sanford NC 27332",
    "addr:housenumber":"54",
    "addr:postcode":"27332",
    "addr:street":"Red Cedar Ln",
    "iso:country":"US",
    "sg:address":"54 Red Cedar Ln",
    "sg:city":"Sanford",
    "sg:classifiers":[
        {
            "category":"Building & Trades",
            "subcategory":"Electrical",
            "type":"Services"
        }
    ],
    "sg:phone":"+1 919 774 6376",
    "sg:postcode":"27332",
    "sg:province":"NC",
    "sg:tags":[
        "electric",
        "contractor"
    ],
    "wof:name":"Simmons Electric Co",
    "wof:placetype":"venue"
},
  "geometry": {"coordinates":[-79.25364500000001,35.411858],"type":"Point"}
}