{
  "type": "Feature",
  "properties": {
    "addr:full":"2821 Chapel Hill Rd Durham NC 27707",
    "addr:housenumber":"2821",
    "addr:postcode":"27707",
    "addr:street":"Chapel Hill Rd",
    "iso:country":"US",
    "sg:address":"2821 Chapel Hill Rd",
    "sg:city":"Durham",
    "sg:classifiers":[
        {
            "category":"Banks & Credit Unions",
            "subcategory":"Investment Brokerage",
            "type":"Services"
        }
    ],
    "sg:phone":"+1 919 493 4552",
    "sg:postcode":"27707",
    "sg:province":"NC",
    "wof:name":"Wachovia Investments",
    "wof:placetype":"venue"
},
  "geometry": {"coordinates":[-78.938452,35.970865],"type":"Point"}
}