{
  "type": "Feature",
  "properties": {
    "addr:full":"4023 Brookshire Blvd Charlotte NC 28216",
    "addr:housenumber":"4023",
    "addr:postcode":"28216",
    "addr:street":"Brookshire Blvd",
    "iso:country":"US",
    "sg:address":"4023 Brookshire Blvd",
    "sg:city":"Charlotte",
    "sg:classifiers":[
        {
            "category":"Insurance",
            "subcategory":"Insurance Agent",
            "type":"Services"
        },
        {
            "category":"Banks & Credit Unions",
            "subcategory":"Investment Brokerage",
            "type":"Services"
        },
        {
            "category":"Insurance",
            "subcategory":"Hazard Insurance",
            "type":"Services"
        }
    ],
    "sg:phone":"+1 704 392 3444",
    "sg:postcode":"28216",
    "sg:province":"NC",
    "sg:tags":[
        "auto",
        "motorcycle",
        "resume"
    ],
    "sg:website":"http://www.directgeneral.com",
    "wof:name":"Direct Auto Insurance",
    "wof:placetype":"venue"
},
  "geometry": {"coordinates":[-80.88108200000001,35.264434],"type":"Point"}
}