{
  "type": "Feature",
  "properties": {
    "iso:country":"US",
    "sg:address":"5306 Bennington Dr",
    "sg:city":"Greensboro",
    "sg:classifiers":[
        {
            "category":"Shopping",
            "subcategory":"Catalog Store",
            "type":"Retail Goods"
        }
    ],
    "sg:phone":"+1 336 299 7691",
    "sg:postcode":"27410",
    "sg:province":"NC",
    "sg:tags":[
        "mail",
        "house"
    ],
    "wof:name":"First Mission Enterprises",
    "wof:placetype":"venue"
},
  "geometry": {"coordinates":[-79.87752500000001,36.100794],"type":"Point"}
}