{
  "type": "Feature",
  "properties": {
    "addr:full":"1400 E Morehead St Charlotte NC 28204",
    "addr:housenumber":"1400",
    "addr:postcode":"28204",
    "addr:street":"E Morehead St",
    "iso:country":"US",
    "sg:address":"1400 E Morehead St",
    "sg:city":"Charlotte",
    "sg:classifiers":[
        {
            "category":"Professional",
            "type":"Services"
        }
    ],
    "sg:phone":"+1 704 338 1140",
    "sg:postcode":"28204",
    "sg:province":"NC",
    "sg:tags":[
        "establishment"
    ],
    "wof:name":"Alter Group",
    "wof:placetype":"venue"
},
  "geometry": {"coordinates":[-80.83685699999999,35.205645],"type":"Point"}
}