{
  "type": "Feature",
  "properties": {
    "iso:country":"US",
    "sg:address":"401 N Gardner Ave",
    "sg:city":"Kenly",
    "sg:classifiers":[
        {
            "category":"Organizations",
            "subcategory":"Religious Organization",
            "type":"Services"
        }
    ],
    "sg:phone":"+1 919 284 4723",
    "sg:postcode":"27542",
    "sg:province":"NC",
    "sg:tags":[
        "church"
    ],
    "wof:name":"Mincey Chapel FWB Church",
    "wof:placetype":"venue"
},
  "geometry": {"coordinates":[-78.119455,35.597346],"type":"Point"}
}