{
  "type": "Feature",
  "properties": {
    "addr:full":"125 W Murphy St Madison NC 27025",
    "addr:housenumber":"125",
    "addr:postcode":"27025",
    "addr:street":"W Murphy St",
    "iso:country":"US",
    "sg:address":"125 W Murphy St",
    "sg:city":"Madison",
    "sg:classifiers":[
        {
            "category":"Shopping",
            "subcategory":"Pharmacy",
            "type":"Retail Goods"
        }
    ],
    "sg:phone":"+1 336 548 0049",
    "sg:postcode":"27025",
    "sg:province":"NC",
    "wof:name":"Madison Pharmacy & Hm Care Inc",
    "wof:placetype":"venue"
},
  "geometry": {"coordinates":[-79.96014,36.387443],"type":"Point"}
}