{
  "type": "Feature",
  "properties": {
    "addr:full":"7912 Unity Church Rd Denver NC 28037",
    "addr:housenumber":"7912",
    "addr:postcode":"28037",
    "addr:street":"Unity Church Rd",
    "iso:country":"US",
    "sg:address":"7912 Unity Church Rd",
    "sg:city":"Denver",
    "sg:classifiers":[
        {
            "category":"Shopping",
            "type":"Retail Goods"
        }
    ],
    "sg:phone":"+1 704 483 6322",
    "sg:postcode":"28037",
    "sg:province":"NC",
    "sg:tags":[
        "merchandise"
    ],
    "wof:name":"Southeastern Engraving",
    "wof:placetype":"venue"
},
  "geometry": {"coordinates":[-80.99226899999999,35.47956],"type":"Point"}
}