{
  "type": "Feature",
  "properties": {
    "addr:full":"4739 Carberry Ct Charlotte NC 28226",
    "addr:housenumber":"4739",
    "addr:postcode":"28226",
    "addr:street":"Carberry Ct",
    "iso:country":"US",
    "sg:address":"4739 Carberry Ct",
    "sg:city":"Charlotte",
    "sg:classifiers":[
        {
            "category":"Professional",
            "type":"Services"
        }
    ],
    "sg:phone":"+1   ",
    "sg:postcode":"28226",
    "sg:province":"NC",
    "wof:name":"Ivy Hill Real Estate Services",
    "wof:placetype":"venue"
},
  "geometry": {"coordinates":[-80.802324,35.09621],"type":"Point"}
}