{
  "type": "Feature",
  "properties": {
    "addr:full":"3 Cavendish Cir Greensboro NC 27455",
    "addr:housenumber":"3",
    "addr:postcode":"27455",
    "addr:street":"Cavendish Cir",
    "iso:country":"US",
    "sg:address":"3 Cavendish Cir",
    "sg:city":"Greensboro",
    "sg:classifiers":[
        {
            "category":"Manufacturing",
            "subcategory":"Printing",
            "type":"Manufacturing & Wholesale Goods"
        }
    ],
    "sg:phone":"+1 336 545 9758",
    "sg:postcode":"27455",
    "sg:province":"NC",
    "sg:tags":[
        "printer"
    ],
    "wof:name":"Printing Place",
    "wof:placetype":"venue"
},
  "geometry": {"coordinates":[-79.845054,36.13736],"type":"Point"}
}