{
  "type": "Feature",
  "properties": {
    "iso:country":"US",
    "sg:address":"8029 Fairview Rd",
    "sg:city":"Mint Hill",
    "sg:classifiers":[
        {
            "category":"Health Services",
            "subcategory":"Medical Lab",
            "type":"Services"
        }
    ],
    "sg:phone":"+1 704 573 6630",
    "sg:postcode":"28227",
    "sg:province":"NC",
    "sg:tags":[
        "resonance",
        "magnetic",
        "imaging"
    ],
    "sg:website":"www.recordsreduction.com",
    "wof:name":"Records Reduction Inc",
    "wof:placetype":"venue"
},
  "geometry": {"coordinates":[-80.64418999999999,35.179122],"type":"Point"}
}