{
  "type": "Feature",
  "properties": {
    "iso:country":"US",
    "sg:address":"3795 Lassiter Mill Rd",
    "sg:city":"Asheboro",
    "sg:classifiers":[
        {
            "category":"Real Estate",
            "subcategory":"Real Estate Agent",
            "type":"Services"
        }
    ],
    "sg:phone":"+1 336 857 2200",
    "sg:postcode":"27205",
    "sg:province":"NC",
    "wof:name":"Craven Craven & Brim LLC",
    "wof:placetype":"venue"
},
  "geometry": {"coordinates":[-79.94145899999999,35.624687],"type":"Point"}
}