{
  "type": "Feature",
  "properties": {
    "addr:full":"5065 Mallard Cove Sherrills Ford NC 28673",
    "addr:housenumber":"5065",
    "addr:postcode":"28673",
    "addr:street":"Mallard Cove",
    "iso:country":"US",
    "sg:address":"5065 Mallard Cove",
    "sg:city":"Sherrills Ford",
    "sg:classifiers":[
        {
            "category":"Cinema",
            "subcategory":"Drive-in Theater",
            "type":"Entertainment"
        }
    ],
    "sg:phone":"+1   ",
    "sg:postcode":"28673",
    "sg:province":"NC",
    "sg:tags":[
        "drive"
    ],
    "wof:name":"Diane 29 Drive In Theatre Inc",
    "wof:placetype":"venue"
},
  "geometry": {"coordinates":[-80.982286,35.556076],"type":"Point"}
}