{
  "type": "Feature",
  "properties": {
    "addr:full":"388 Northgate Plaza Dr Winston Salem NC 27105",
    "addr:housenumber":"388",
    "addr:postcode":"27105",
    "addr:street":"Northgate Plaza Dr",
    "iso:country":"US",
    "sg:address":"388 Northgate Plaza Dr",
    "sg:city":"Winston Salem",
    "sg:classifiers":[
        {
            "category":"Retail",
            "subcategory":"Auto Repair",
            "type":"Services"
        }
    ],
    "sg:phone":"+1 336 744 9200",
    "sg:postcode":"27105",
    "sg:province":"NC",
    "sg:tags":[
        "body",
        "automobile",
        "painting"
    ],
    "wof:name":"Autoworld",
    "wof:placetype":"venue"
},
  "geometry": {"coordinates":[-80.250159,36.155375],"type":"Point"}
}