{
  "type": "Feature",
  "properties": {
    "addr:full":"800 S Church St Asheboro NC 27203",
    "addr:housenumber":"800",
    "addr:postcode":"27203",
    "addr:street":"S Church St",
    "iso:country":"US",
    "sg:address":"800 S Church St",
    "sg:city":"Asheboro",
    "sg:classifiers":[
        {
            "category":"Recreation",
            "type":"Entertainment"
        }
    ],
    "sg:phone":"+1 336 629 1772",
    "sg:postcode":"27203",
    "sg:province":"NC",
    "sg:tags":[
        "tennis",
        "court"
    ],
    "wof:name":"Asheboro Tennis Ctr",
    "wof:placetype":"venue"
},
  "geometry": {"coordinates":[-79.818034,35.697709],"type":"Point"}
}