{
  "type": "Feature",
  "properties": {
    "iso:country":"US",
    "sg:address":"6209 Oleander Dr",
    "sg:city":"Wilmington",
    "sg:classifiers":[
        {
            "category":"Freight",
            "type":"Transportation"
        }
    ],
    "sg:phone":"+1 910 452 7785",
    "sg:postcode":"28403",
    "sg:province":"NC",
    "sg:tags":[
        "trucking"
    ],
    "wof:name":"Advantage Tank Lines",
    "wof:placetype":"venue"
},
  "geometry": {"coordinates":[-77.836195,34.21106],"type":"Point"}
}