{
  "type": "Feature",
  "properties": {
    "iso:country":"US",
    "sg:address":"401 Queen St",
    "sg:city":"La Grange",
    "sg:classifiers":[
        {
            "category":"Organizations",
            "subcategory":"Religious Organization",
            "type":"Services"
        }
    ],
    "sg:phone":"+1 252 566 9442",
    "sg:postcode":"28551",
    "sg:province":"NC",
    "sg:tags":[
        "church"
    ],
    "wof:name":"St James Church Of Christ",
    "wof:placetype":"venue"
},
  "geometry": {"coordinates":[-77.79414800000001,35.313686],"type":"Point"}
}