{
  "type": "Feature",
  "properties": {
    "iso:country":"US",
    "sg:address":"604 H C Powers Rd",
    "sg:city":"Wallace",
    "sg:classifiers":[
        {
            "category":"Professional",
            "type":"Services"
        }
    ],
    "sg:phone":"+1 910 285 4623",
    "sg:postcode":"28466",
    "sg:province":"NC",
    "wof:name":"Stephanie Jones",
    "wof:placetype":"venue"
},
  "geometry": {"coordinates":[-78.055702,34.73247],"type":"Point"}
}