{
  "type": "Feature",
  "properties": {
    "addr:full":"221 Whitfield St Knightdale NC 27545",
    "addr:housenumber":"221",
    "addr:postcode":"27545",
    "addr:street":"Whitfield St",
    "iso:country":"US",
    "sg:address":"221 Whitfield St",
    "sg:city":"Knightdale",
    "sg:classifiers":[
        {
            "category":"Health Services",
            "subcategory":"Doctor",
            "type":"Services"
        }
    ],
    "sg:phone":"+1   ",
    "sg:postcode":"27545",
    "sg:province":"NC",
    "wof:name":"Tripp Kenneth Jr DDS",
    "wof:placetype":"venue"
},
  "geometry": {"coordinates":[-78.526544,35.791365],"type":"Point"}
}