{
  "type": "Feature",
  "properties": {
    "addr:full":"239 Amboy Rd Asheville NC 28806",
    "addr:housenumber":"239",
    "addr:postcode":"28806",
    "addr:street":"Amboy Rd",
    "iso:country":"US",
    "sg:address":"239 Amboy Rd",
    "sg:city":"Asheville",
    "sg:classifiers":[
        {
            "category":"Building & Trades",
            "subcategory":"Construction",
            "type":"Services"
        }
    ],
    "sg:phone":"+1 828 285 9828",
    "sg:postcode":"28806",
    "sg:province":"NC",
    "sg:tags":[
        "builder",
        "stair"
    ],
    "wof:name":"Southern Classic Stairs Inc",
    "wof:placetype":"venue"
},
  "geometry": {"coordinates":[-82.58762900000001,35.566995],"type":"Point"}
}