{
  "type": "Feature",
  "properties": {
    "iso:country":"US",
    "sg:address":"4207 Saddlebrook Dr",
    "sg:city":"Castle Hayne",
    "sg:classifiers":[
        {
            "category":"Building & Trades",
            "subcategory":"Plumbing",
            "type":"Services"
        }
    ],
    "sg:phone":"+1 910 675 2968",
    "sg:postcode":"28429",
    "sg:province":"NC",
    "sg:tags":[
        "contractor"
    ],
    "wof:name":"Pages Plumbing",
    "wof:placetype":"venue"
},
  "geometry": {"coordinates":[-77.89076,34.329978],"type":"Point"}
}