{
  "type": "Feature",
  "properties": {
    "iso:country":"US",
    "sg:address":"110 US Hwy 29 S",
    "sg:city":"China Grove",
    "sg:classifiers":[
        {
            "category":"Wholesale",
            "subcategory":"Tobacco Products",
            "type":"Manufacturing & Wholesale Goods"
        },
        {
            "category":"Shopping",
            "subcategory":"Tobacco",
            "type":"Retail Goods"
        }
    ],
    "sg:phone":"+1 704 857 0761",
    "sg:postcode":"28023",
    "sg:province":"NC",
    "sg:tags":[
        "cigarette",
        "cigar",
        "dealer"
    ],
    "wof:name":"Tar Heel Tobacco 25",
    "wof:placetype":"venue"
},
  "geometry": {"coordinates":[-80.576533,35.565794],"type":"Point"}
}