{
  "type": "Feature",
  "properties": {
    "iso:country":"US",
    "sg:address":"1010 Arnette Ave",
    "sg:city":"Durham",
    "sg:classifiers":[
        {
            "category":"Professional",
            "type":"Services"
        }
    ],
    "sg:phone":"+1   ",
    "sg:postcode":"27707",
    "sg:province":"NC",
    "wof:name":"Pvf Inc",
    "wof:placetype":"venue"
},
  "geometry": {"coordinates":[-78.914378,35.990599],"type":"Point"}
}