{
  "type": "Feature",
  "properties": {
    "addr:full":"503 Main St Winton NC 27986",
    "addr:housenumber":"503",
    "addr:postcode":"27986",
    "addr:street":"Main St",
    "iso:country":"US",
    "sg:address":"503 Main St",
    "sg:city":"Winton",
    "sg:classifiers":[
        {
            "category":"Government",
            "subcategory":"Fire Station",
            "type":"Public Place"
        }
    ],
    "sg:phone":"+1 252 358 3651",
    "sg:postcode":"27986",
    "sg:province":"NC",
    "sg:tags":[
        "department"
    ],
    "wof:name":"Winton Fire Dept",
    "wof:placetype":"venue"
},
  "geometry": {"coordinates":[-76.93932,36.386208],"type":"Point"}
}