{
  "type": "Feature",
  "properties": {
    "addr:full":"6619 Glenleaf Ct Charlotte NC 28270",
    "addr:housenumber":"6619",
    "addr:postcode":"28270",
    "addr:street":"Glenleaf Ct",
    "iso:country":"US",
    "sg:address":"6619 Glenleaf Ct",
    "sg:city":"Charlotte",
    "sg:classifiers":[
        {
            "category":"Retail",
            "subcategory":"Portrait Studio",
            "type":"Services"
        }
    ],
    "sg:phone":"+1 704 364 8901",
    "sg:postcode":"28270",
    "sg:province":"NC",
    "sg:tags":[
        "photography",
        "commercial",
        "wedding"
    ],
    "wof:name":"Southern Light Photography",
    "wof:placetype":"venue"
},
  "geometry": {"coordinates":[-80.77397999999999,35.150121],"type":"Point"}
}