{
  "type": "Feature",
  "properties": {
    "iso:country":"US",
    "sg:address":"437 Quail Ridge Rd",
    "sg:city":"Henrico",
    "sg:classifiers":[
        {
            "category":"Professional",
            "subcategory":"Management & Consulting",
            "type":"Services"
        }
    ],
    "sg:phone":"+1   ",
    "sg:postcode":"27842",
    "sg:province":"NC",
    "sg:tags":[
        "job"
    ],
    "wof:name":"Stimson & Associates",
    "wof:placetype":"venue"
},
  "geometry": {"coordinates":[-77.903999,36.514559],"type":"Point"}
}