{
  "type": "Feature",
  "properties": {
    "iso:country":"US",
    "sg:address":"15 Carolina Ln",
    "sg:city":"Asheville",
    "sg:classifiers":[
        {
            "category":"Professional",
            "subcategory":"Business Services",
            "type":"Services"
        }
    ],
    "sg:phone":"+1 828 236 0987",
    "sg:postcode":"28801",
    "sg:province":"NC",
    "sg:tags":[
        "recording",
        "studio"
    ],
    "wof:name":"Altamont Recording LLC",
    "wof:placetype":"venue"
},
  "geometry": {"coordinates":[-82.553189,35.597872],"type":"Point"}
}