{
  "type": "Feature",
  "properties": {
    "iso:country":"US",
    "sg:address":"8010 Shorewood Dr",
    "sg:city":"Charlotte",
    "sg:classifiers":[
        {
            "category":"Retail",
            "subcategory":"Laundry & Dry Cleaning",
            "type":"Services"
        }
    ],
    "sg:phone":"+1   ",
    "sg:postcode":"28277",
    "sg:province":"NC",
    "wof:name":"TLC Carpet Service",
    "wof:placetype":"venue"
},
  "geometry": {"coordinates":[-80.784479,35.093757],"type":"Point"}
}