{
  "type": "Feature",
  "properties": {
    "iso:country":"US",
    "sg:address":"236 S Trade St",
    "sg:city":"Matthews",
    "sg:classifiers":[
        {
            "category":"Government",
            "subcategory":"Fire Station",
            "type":"Public Place"
        }
    ],
    "sg:phone":"+1 704 847 9400",
    "sg:postcode":"28105",
    "sg:province":"NC",
    "sg:tags":[
        "department"
    ],
    "wof:name":"Matthews Volunteer Fire Dept",
    "wof:placetype":"venue"
},
  "geometry": {"coordinates":[-80.724655,35.113737],"type":"Point"}
}