{
  "type": "Feature",
  "properties": {
    "addr:full":"6495 Raeford Rd Fayetteville NC 28304",
    "addr:housenumber":"6495",
    "addr:postcode":"28304",
    "addr:street":"Raeford Rd",
    "iso:country":"US",
    "sg:address":"6495 Raeford Rd",
    "sg:city":"Fayetteville",
    "sg:classifiers":[
        {
            "category":"Insurance",
            "subcategory":"Insurance Agent",
            "type":"Services"
        }
    ],
    "sg:phone":"+1 910 868 4515",
    "sg:postcode":"28304",
    "sg:province":"NC",
    "wof:name":"Allison Smith",
    "wof:placetype":"venue"
},
  "geometry": {"coordinates":[-78.99288199999999,35.041585],"type":"Point"}
}