{
  "type": "Feature",
  "properties": {
    "iso:country":"US",
    "sg:address":"102 Brant Point Pl",
    "sg:city":"Cary",
    "sg:classifiers":[
        {
            "category":"Professional",
            "subcategory":"Computer Services",
            "type":"Services"
        }
    ],
    "sg:phone":"+1   ",
    "sg:postcode":"27513",
    "sg:province":"NC",
    "sg:tags":[
        "programing",
        "custom"
    ],
    "wof:name":"J & L Global Corporation",
    "wof:placetype":"venue"
},
  "geometry": {"coordinates":[-78.79664200000001,35.823429],"type":"Point"}
}