{
  "type": "Feature",
  "properties": {
    "addr:full":"445 Woody Rd Green Mountain NC 28734",
    "addr:housenumber":"445",
    "addr:postcode":"28734",
    "addr:street":"Woody Rd",
    "iso:country":"US",
    "sg:address":"445 Woody Rd",
    "sg:city":"Green Mountain",
    "sg:classifiers":[
        {
            "category":"Retail",
            "subcategory":"Repair Shop",
            "type":"Services"
        }
    ],
    "sg:phone":"+1 828 675 9050",
    "sg:postcode":"28734",
    "sg:province":"NC",
    "sg:tags":[
        "related"
    ],
    "wof:name":"Action Gun & Repair",
    "wof:placetype":"venue"
},
  "geometry": {"coordinates":[-83.40406,35.224072],"type":"Point"}
}