{
  "type": "Feature",
  "properties": {
    "iso:country":"US",
    "sg:address":"8715 Shipwatch Dr",
    "sg:city":"Wilmington",
    "sg:classifiers":[
        {
            "category":"Professional",
            "subcategory":"Business Services",
            "type":"Services"
        }
    ],
    "sg:phone":"+1   ",
    "sg:postcode":"28412",
    "sg:province":"NC",
    "wof:name":"Lovitt Enterprises Inc",
    "wof:placetype":"venue"
},
  "geometry": {"coordinates":[-77.921145,34.064106],"type":"Point"}
}