{
  "type": "Feature",
  "properties": {
    "addr:full":"101 E Plaza Dr Mooresville NC 28115",
    "addr:housenumber":"101",
    "addr:postcode":"28115",
    "addr:street":"E Plaza Dr",
    "iso:country":"US",
    "sg:address":"101 E Plaza Dr",
    "sg:city":"Mooresville",
    "sg:classifiers":[
        {
            "category":"Professional",
            "subcategory":"Accounting & Tax Preparation",
            "type":"Services"
        }
    ],
    "sg:phone":"+1 704 663 0193",
    "sg:postcode":"28115",
    "sg:province":"NC",
    "sg:tags":[
        "accountant"
    ],
    "wof:name":"Daniel Ratliff & Co",
    "wof:placetype":"venue"
},
  "geometry": {"coordinates":[-80.826925,35.588682],"type":"Point"}
}