{
  "type": "Feature",
  "properties": {
    "addr:full":"1960 US Hwy 70 E Hickory NC 28602",
    "addr:housenumber":"1960",
    "addr:postcode":"28602",
    "addr:street":"Us Hwy 70 E",
    "iso:country":"US",
    "sg:address":"1960 US Hwy 70 E",
    "sg:city":"Hickory",
    "sg:classifiers":[
        {
            "category":"Personal",
            "subcategory":"Beauty Salon",
            "type":"Services"
        }
    ],
    "sg:phone":"+1 828 322 9499",
    "sg:postcode":"28602",
    "sg:province":"NC",
    "sg:tags":[
        "nail",
        "manicuring"
    ],
    "wof:name":"Today's Nails",
    "wof:placetype":"venue"
},
  "geometry": {"coordinates":[-81.46093500000001,35.722294],"type":"Point"}
}