{
  "type": "Feature",
  "properties": {
    "iso:country":"US",
    "sg:address":"815 Barn St",
    "sg:city":"Jacksonville",
    "sg:classifiers":[
        {
            "category":"Social Services",
            "subcategory":"Child Care",
            "type":"Services"
        }
    ],
    "sg:phone":"+1 910 347 5833",
    "sg:postcode":"28540",
    "sg:province":"NC",
    "wof:name":"Patty Cakes Child Care",
    "wof:placetype":"venue"
},
  "geometry": {"coordinates":[-77.432712,34.769408],"type":"Point"}
}