{
  "type": "Feature",
  "properties": {
    "iso:country":"US",
    "sg:address":"606 Lyon Tree Dr",
    "sg:city":"Durham",
    "sg:classifiers":[
        {
            "category":"Building & Trades",
            "subcategory":"Construction",
            "type":"Services"
        }
    ],
    "sg:phone":"+1 919 405 7200",
    "sg:postcode":"27713",
    "sg:province":"NC",
    "sg:tags":[
        "home",
        "builder"
    ],
    "wof:name":"Westfield Homes",
    "wof:placetype":"venue"
},
  "geometry": {"coordinates":[-78.920552,35.877085],"type":"Point"}
}