{
  "type": "Feature",
  "properties": {
    "addr:full":"1901 E Peachtree St Goldsboro NC 27530",
    "addr:housenumber":"1901",
    "addr:postcode":"27530",
    "addr:street":"E Peachtree St",
    "iso:country":"US",
    "sg:address":"1901 E Peachtree St",
    "sg:city":"Goldsboro",
    "sg:classifiers":[
        {
            "category":"Home & Garden",
            "subcategory":"Building Materials",
            "type":"Retail Goods"
        }
    ],
    "sg:phone":"+1 919 736 0091",
    "sg:postcode":"27530",
    "sg:province":"NC",
    "sg:tags":[
        "glass",
        "window",
        "plate"
    ],
    "wof:name":"Econo Auto Glass",
    "wof:placetype":"venue"
},
  "geometry": {"coordinates":[-77.965431,35.378333],"type":"Point"}
}