{
  "type": "Feature",
  "properties": {
    "addr:full":"9009 Glenwood Ave Raleigh NC 27617",
    "addr:housenumber":"9009",
    "addr:postcode":"27617",
    "addr:street":"Glenwood Ave",
    "iso:country":"US",
    "sg:address":"9009 Glenwood Ave",
    "sg:city":"Raleigh",
    "sg:classifiers":[
        {
            "category":"Building & Trades",
            "subcategory":"Equipment Rental",
            "type":"Services"
        }
    ],
    "sg:phone":"+1 919 788 8181",
    "sg:postcode":"27617",
    "sg:province":"NC",
    "sg:tags":[
        "contractor"
    ],
    "wof:name":"MSP Rents",
    "wof:placetype":"venue"
},
  "geometry": {"coordinates":[-78.75534,35.894228],"type":"Point"}
}