{
  "type": "Feature",
  "properties": {
    "addr:full":"2328 Elizabeth Ave Winston Salem NC 27103",
    "addr:housenumber":"2328",
    "addr:postcode":"27103",
    "addr:street":"Elizabeth Ave",
    "iso:country":"US",
    "sg:address":"2328 Elizabeth Ave",
    "sg:city":"Winston Salem",
    "sg:classifiers":[
        {
            "category":"Building & Trades",
            "subcategory":"Construction",
            "type":"Services"
        }
    ],
    "sg:phone":"+1 336 750 0556",
    "sg:postcode":"27103",
    "sg:province":"NC",
    "sg:tags":[
        "house"
    ],
    "wof:name":"Tycon Inc",
    "wof:placetype":"venue"
},
  "geometry": {"coordinates":[-80.27885499999999,36.085728],"type":"Point"}
}