{
  "type": "Feature",
  "properties": {
    "addr:full":"6274 Glenwood Ave Raleigh NC 27612",
    "addr:housenumber":"6274",
    "addr:postcode":"27612",
    "addr:street":"Glenwood Ave",
    "iso:country":"US",
    "sg:address":"6274 Glenwood Ave",
    "sg:city":"Raleigh",
    "sg:classifiers":[
        {
            "category":"Real Estate",
            "subcategory":"Real Estate Agent",
            "type":"Services"
        }
    ],
    "sg:phone":"+1 919 781 3665",
    "sg:postcode":"27612",
    "sg:province":"NC",
    "wof:name":"Cambridge Realty",
    "wof:placetype":"venue"
},
  "geometry": {"coordinates":[-78.700627,35.854971],"type":"Point"}
}