{
  "type": "Feature",
  "properties": {
    "addr:full":"246 Cabarrus Ave W Concord NC 28025",
    "addr:housenumber":"246",
    "addr:postcode":"28025",
    "addr:street":"Cabarrus Ave W",
    "iso:country":"US",
    "sg:address":"246 Cabarrus Ave W",
    "sg:city":"Concord",
    "sg:classifiers":[
        {
            "category":"Social Services",
            "subcategory":"Adult Care",
            "type":"Services"
        }
    ],
    "sg:phone":"+1 704 788 1018",
    "sg:postcode":"28025",
    "sg:province":"NC",
    "sg:tags":[
        "home",
        "residential"
    ],
    "wof:name":"St Andrews Living Ctr Inc",
    "wof:placetype":"venue"
},
  "geometry": {"coordinates":[-80.588446,35.405543],"type":"Point"}
}