{
  "type": "Feature",
  "properties": {
    "iso:country":"US",
    "sg:address":"609 Piner Rd",
    "sg:city":"Wilmington",
    "sg:classifiers":[
        {
            "category":"Restaurant",
            "type":"Food & Drink"
        }
    ],
    "sg:menulink":"http://www.allmenus.com/nc/federal-point/140921-j-michaels-philly-deli/menu/",
    "sg:phone":"+1 910 332 5555",
    "sg:postcode":"28409",
    "sg:province":"NC",
    "sg:tags":[
        "wrap",
        "american",
        "sandwich"
    ],
    "wof:name":"J Michaels Philly Deli",
    "wof:placetype":"venue"
},
  "geometry": {"coordinates":[-77.892408,34.139544],"type":"Point"}
}