{
  "type": "Feature",
  "properties": {
    "iso:country":"US",
    "sg:address":"3832 N Croatan Hwy",
    "sg:city":"Kitty Hawk",
    "sg:classifiers":[
        {
            "category":"Organizations",
            "subcategory":"Religious Organization",
            "type":"Services"
        }
    ],
    "sg:phone":"+1 252 255 1835",
    "sg:postcode":"27949",
    "sg:province":"NC",
    "sg:tags":[
        "church"
    ],
    "wof:name":"Still Waters Baptist Church",
    "wof:placetype":"venue"
},
  "geometry": {"coordinates":[-75.692491,36.064872],"type":"Point"}
}