{
  "type": "Feature",
  "properties": {
    "iso:country":"US",
    "sg:address":"1709 Legion Rd Ste 113",
    "sg:city":"Chapel Hill",
    "sg:classifiers":[
        {
            "category":"Shopping",
            "subcategory":"Jewelry",
            "type":"Retail Goods"
        }
    ],
    "sg:phone":"+1 919 928 9499",
    "sg:postcode":"27517",
    "sg:province":"NC",
    "sg:website":"www.kimpiracci.com",
    "wof:name":"Kim Piracci Gg Jewelry Appraisers",
    "wof:placetype":"venue"
},
  "geometry": {"coordinates":[-79.02120600000001,35.935607],"type":"Point"}
}