{
  "type": "Feature",
  "properties": {
    "iso:country":"US",
    "sg:address":"508 E Universal St",
    "sg:city":"Kannapolis",
    "sg:classifiers":[
        {
            "category":"Home & Garden",
            "subcategory":"Carpets & Floor Coverings",
            "type":"Retail Goods"
        }
    ],
    "sg:phone":"+1 704 938 8260",
    "sg:postcode":"28083",
    "sg:province":"NC",
    "sg:tags":[
        "installation",
        "sales"
    ],
    "wof:name":"A-1 Carpet Sls & Installation",
    "wof:placetype":"venue"
},
  "geometry": {"coordinates":[-80.61662,35.47842],"type":"Point"}
}