{
  "type": "Feature",
  "properties": {
    "iso:country":"US",
    "sg:address":"2050 Oak Ridge Rd",
    "sg:city":"Oak Ridge",
    "sg:classifiers":[
        {
            "category":"Education",
            "subcategory":"School",
            "type":"Public Place"
        }
    ],
    "sg:phone":"+1 336 643 8410",
    "sg:postcode":"27310",
    "sg:province":"NC",
    "wof:name":"Oak Ridge Elementary School",
    "wof:placetype":"venue"
},
  "geometry": {"coordinates":[-79.993966,36.169856],"type":"Point"}
}