{
  "type": "Feature",
  "properties": {
    "iso:country":"US",
    "sg:address":"4400 Morris Park Dr",
    "sg:city":"Charlotte",
    "sg:classifiers":[
        {
            "category":"Professional",
            "subcategory":"Detective & Security Services",
            "type":"Services"
        }
    ],
    "sg:phone":"+1 704 227 1363",
    "sg:postcode":"28227",
    "sg:province":"NC",
    "wof:name":"Plan 3 Media",
    "wof:placetype":"venue"
},
  "geometry": {"coordinates":[-80.680626,35.152251],"type":"Point"}
}