{
  "type": "Feature",
  "properties": {
    "iso:country":"US",
    "sg:address":"3064 Hickory Blvd",
    "sg:city":"Hudson",
    "sg:classifiers":[
        {
            "category":"Home & Garden",
            "subcategory":"Furniture",
            "type":"Retail Goods"
        }
    ],
    "sg:phone":"+1 828 728 4108",
    "sg:postcode":"28638",
    "sg:province":"NC",
    "wof:name":"Thomasville Furniture",
    "wof:placetype":"venue"
},
  "geometry": {"coordinates":[-81.473854,35.846139],"type":"Point"}
}