{
  "type": "Feature",
  "properties": {
    "addr:full":"3228 Sunset Dr Charlotte NC 28209",
    "addr:housenumber":"3228",
    "addr:postcode":"28209",
    "addr:street":"Sunset Dr",
    "iso:country":"US",
    "sg:address":"3228 Sunset Dr",
    "sg:city":"Charlotte",
    "sg:classifiers":[
        {
            "category":"Education",
            "subcategory":"Vocational School",
            "type":"Public Place"
        }
    ],
    "sg:phone":"+1 704 377 7618",
    "sg:postcode":"28209",
    "sg:province":"NC",
    "sg:tags":[
        "real estate"
    ],
    "sg:website":"www.realrand.com",
    "wof:name":"Rand Associates Real Est Trnng",
    "wof:placetype":"venue"
},
  "geometry": {"coordinates":[-80.85747499999999,35.189148],"type":"Point"}
}