{
  "type": "Feature",
  "properties": {
    "addr:full":"2701 Tuckaseegee Rd Charlotte NC 28208",
    "addr:housenumber":"2701",
    "addr:postcode":"28208",
    "addr:street":"Tuckaseegee Rd",
    "iso:country":"US",
    "sg:address":"2701 Tuckaseegee Rd",
    "sg:city":"Charlotte",
    "sg:classifiers":[
        {
            "category":"Professional",
            "subcategory":"Accounting & Tax Preparation",
            "type":"Services"
        }
    ],
    "sg:phone":"+1   ",
    "sg:postcode":"28208",
    "sg:province":"NC",
    "sg:tags":[
        "auditing",
        "bookkeeping"
    ],
    "wof:name":"Lum Lum & Lemeh Accounting",
    "wof:placetype":"venue"
},
  "geometry": {"coordinates":[-80.876199,35.240081],"type":"Point"}
}