{
  "type": "Feature",
  "properties": {
    "addr:full":"2463 Armstrong Dr Winston Salem NC 27103",
    "addr:housenumber":"2463",
    "addr:postcode":"27103",
    "addr:street":"Armstrong Dr",
    "iso:country":"US",
    "sg:address":"2463 Armstrong Dr",
    "sg:city":"Winston Salem",
    "sg:classifiers":[
        {
            "category":"Home & Garden",
            "subcategory":"Garden Supply",
            "type":"Retail Goods"
        }
    ],
    "sg:phone":"+1 336 768 1055",
    "sg:postcode":"27103",
    "sg:province":"NC",
    "sg:tags":[
        "engine"
    ],
    "wof:name":"Lawnmower Medic",
    "wof:placetype":"venue"
},
  "geometry": {"coordinates":[-80.31581300000001,36.039889],"type":"Point"}
}