{
  "type": "Feature",
  "properties": {
    "iso:country":"US",
    "sg:address":"7560 US Hwy 117",
    "sg:city":"Rocky Point",
    "sg:classifiers":[
        {
            "category":"Organizations",
            "subcategory":"Religious Organization",
            "type":"Services"
        }
    ],
    "sg:phone":"+1 910 675 3900",
    "sg:postcode":"28457",
    "sg:province":"NC",
    "sg:tags":[
        "church"
    ],
    "wof:name":"Lighthouse Worship Ctr",
    "wof:placetype":"venue"
},
  "geometry": {"coordinates":[-77.882558,34.449042],"type":"Point"}
}