{
  "type": "Feature",
  "properties": {
    "addr:full":"1415 US Hwy 70 W Garner NC 27529",
    "addr:housenumber":"1415",
    "addr:postcode":"27529",
    "addr:street":"Us Hwy 70 W",
    "iso:country":"US",
    "sg:address":"1415 US Hwy 70 W",
    "sg:city":"Garner",
    "sg:classifiers":[
        {
            "category":"Retail",
            "subcategory":"Auto Repair",
            "type":"Services"
        }
    ],
    "sg:phone":"+1 919 661 1162",
    "sg:postcode":"27529",
    "sg:province":"NC",
    "sg:tags":[
        "repairing",
        "automobile"
    ],
    "wof:name":"Midas Auto Svc Experts",
    "wof:placetype":"venue"
},
  "geometry": {"coordinates":[-78.64831100000001,35.724618],"type":"Point"}
}