{
  "type": "Feature",
  "properties": {
    "addr:full":"171 S Middleton St Robbins NC 27325",
    "addr:housenumber":"171",
    "addr:postcode":"27325",
    "addr:street":"S Middleton St",
    "iso:country":"US",
    "sg:address":"171 S Middleton St",
    "sg:city":"Robbins",
    "sg:classifiers":[
        {
            "category":"Sports & Exercise",
            "subcategory":"Gym",
            "type":"Entertainment"
        }
    ],
    "sg:phone":"+1 910 948 2544",
    "sg:postcode":"27325",
    "sg:province":"NC",
    "sg:tags":[
        "club",
        "health",
        "studio",
        "gymnasium"
    ],
    "wof:name":"Brick House Fitness Ctr",
    "wof:placetype":"venue"
},
  "geometry": {"coordinates":[-79.587288,35.4333],"type":"Point"}
}