{
  "type": "Feature",
  "properties": {
    "iso:country":"US",
    "sg:address":"4805 Family Circle Rd",
    "sg:city":"Apex",
    "sg:classifiers":[
        {
            "category":"Real Estate",
            "subcategory":"Real Estate Operator",
            "type":"Services"
        }
    ],
    "sg:phone":"+1 919 387 7112",
    "sg:postcode":"27539",
    "sg:province":"NC",
    "sg:tags":[
        "mobile",
        "home",
        "community"
    ],
    "wof:name":"South Breeze Inc",
    "wof:placetype":"venue"
},
  "geometry": {"coordinates":[-78.80575399999999,35.698],"type":"Point"}
}