{
  "type": "Feature",
  "properties": {
    "iso:country":"US",
    "sg:address":"205 Hillsborough Rd",
    "sg:city":"Carrboro",
    "sg:classifiers":[
        {
            "category":"Personal",
            "subcategory":"Beauty Salon",
            "type":"Services"
        }
    ],
    "sg:phone":"+1 919 942 0363",
    "sg:postcode":"27510",
    "sg:province":"NC",
    "wof:name":"Jo Ann's Hairstyling",
    "wof:placetype":"venue"
},
  "geometry": {"coordinates":[-79.08174099999999,35.916024],"type":"Point"}
}