{
  "type": "Feature",
  "properties": {
    "iso:country":"US",
    "sg:address":"178 Dakota Ln",
    "sg:city":"Mocksville",
    "sg:classifiers":[
        {
            "category":"Building & Trades",
            "subcategory":"Construction",
            "type":"Services"
        }
    ],
    "sg:phone":"+1 336 492 6208",
    "sg:postcode":"27028",
    "sg:province":"NC",
    "sg:tags":[
        "house"
    ],
    "wof:name":"Dream Builders",
    "wof:placetype":"venue"
},
  "geometry": {"coordinates":[-80.607242,35.945921],"type":"Point"}
}