{
  "type": "Feature",
  "properties": {
    "addr:full":"313 Union St Fayetteville NC 28301",
    "addr:housenumber":"313",
    "addr:postcode":"28301",
    "addr:street":"Union St",
    "iso:country":"US",
    "sg:address":"313 Union St",
    "sg:city":"Fayetteville",
    "sg:classifiers":[
        {
            "category":"Professional",
            "subcategory":"Business Services",
            "type":"Services"
        }
    ],
    "sg:phone":"+1   ",
    "sg:postcode":"28301",
    "sg:province":"NC",
    "wof:name":"Pringle Enterprise",
    "wof:placetype":"venue"
},
  "geometry": {"coordinates":[-78.878017,35.057501],"type":"Point"}
}