{
  "type": "Feature",
  "properties": {
    "addr:full":"1801 Market St Wilmington NC 28403",
    "addr:housenumber":"1801",
    "addr:postcode":"28403",
    "addr:street":"Market St",
    "iso:country":"US",
    "sg:address":"1801 Market St",
    "sg:city":"Wilmington",
    "sg:classifiers":[
        {
            "category":"Organizations",
            "subcategory":"Religious Organization",
            "type":"Services"
        }
    ],
    "sg:phone":"+1 910 763 3351",
    "sg:postcode":"28403",
    "sg:province":"NC",
    "wof:name":"Temple Baptist Church",
    "wof:placetype":"venue"
},
  "geometry": {"coordinates":[-77.92464099999999,34.237337],"type":"Point"}
}