{
  "type": "Feature",
  "properties": {
    "addr:full":"4011 Five Points Rd Shelby NC 28150",
    "addr:housenumber":"4011",
    "addr:postcode":"28150",
    "addr:street":"Five Points Rd",
    "iso:country":"US",
    "sg:address":"4011 Five Points Rd",
    "sg:city":"Shelby",
    "sg:classifiers":[
        {
            "category":"Freight",
            "type":"Transportation"
        }
    ],
    "sg:phone":"+1 704 538 1676",
    "sg:postcode":"28150",
    "sg:province":"NC",
    "sg:tags":[
        "operator",
        "local",
        "trucking"
    ],
    "wof:name":"Grading Washburn & Hauling",
    "wof:placetype":"venue"
},
  "geometry": {"coordinates":[-81.668414,35.439808],"type":"Point"}
}