{
  "type": "Feature",
  "properties": {
    "iso:country":"US",
    "sg:address":"16 S Brooks Cove Rd",
    "sg:city":"Hayesville",
    "sg:classifiers":[
        {
            "category":"Home & Garden",
            "subcategory":"Carpets & Floor Coverings",
            "type":"Retail Goods"
        }
    ],
    "sg:phone":"+1 828 389 1014",
    "sg:postcode":"28904",
    "sg:province":"NC",
    "wof:name":"Donnies Hardwood & Carpet",
    "wof:placetype":"venue"
},
  "geometry": {"coordinates":[-83.629456,35.04823],"type":"Point"}
}