{
  "type": "Feature",
  "properties": {
    "iso:country":"US",
    "sg:address":"178 Horseshoe Rd",
    "sg:city":"South Mills",
    "sg:classifiers":[
        {
            "category":"Building & Trades",
            "subcategory":"Construction",
            "type":"Services"
        }
    ],
    "sg:phone":"+1 252 771 3162",
    "sg:postcode":"27976",
    "sg:province":"NC",
    "sg:tags":[
        "house"
    ],
    "wof:name":"Christophers Construction Inc",
    "wof:placetype":"venue"
},
  "geometry": {"coordinates":[-76.34261600000001,36.448318],"type":"Point"}
}