{
  "type": "Feature",
  "properties": {
    "iso:country":"US",
    "sg:address":"148 Arcadia Ln",
    "sg:city":"Lexington",
    "sg:classifiers":[
        {
            "category":"Personal",
            "subcategory":"Beauty Salon",
            "type":"Services"
        }
    ],
    "sg:phone":"+1 336 243 4131",
    "sg:postcode":"27295",
    "sg:province":"NC",
    "wof:name":"Helen's Hair Care",
    "wof:placetype":"venue"
},
  "geometry": {"coordinates":[-80.273264,35.842225],"type":"Point"}
}