{
  "type": "Feature",
  "properties": {
    "addr:full":"2323 NW Maynard Rd Cary NC 27513",
    "addr:housenumber":"2323",
    "addr:postcode":"27513",
    "addr:street":"Nw Maynard Rd",
    "iso:country":"US",
    "sg:address":"2323 NW Maynard Rd",
    "sg:city":"Cary",
    "sg:classifiers":[
        {
            "category":"Shopping",
            "subcategory":"Pharmacy",
            "type":"Retail Goods"
        }
    ],
    "sg:phone":"+1 919 462 3432",
    "sg:postcode":"27513",
    "sg:province":"NC",
    "sg:tags":[
        "drugstore"
    ],
    "sg:website":"www.walgreens.com",
    "wof:name":"Walgreen Drug Stores",
    "wof:placetype":"venue"
},
  "geometry": {"coordinates":[-78.78579000000001,35.802415],"type":"Point"}
}