{
  "type": "Feature",
  "properties": {
    "addr:full":"2316 State Hwy 43 Warrenton NC 27589",
    "addr:housenumber":"2316",
    "addr:postcode":"27589",
    "addr:street":"State Hwy 43",
    "iso:country":"US",
    "sg:address":"2316 State Hwy 43",
    "sg:city":"Warrenton",
    "sg:classifiers":[
        {
            "category":"Manufacturing",
            "subcategory":"Wood Products",
            "type":"Manufacturing & Wholesale Goods"
        }
    ],
    "sg:phone":"+1 252 257 4923",
    "sg:postcode":"27589",
    "sg:province":"NC",
    "sg:tags":[
        "hardwood",
        "container",
        "mfg"
    ],
    "wof:name":"Arcola Hardwood Co Inc",
    "wof:placetype":"venue"
},
  "geometry": {"coordinates":[-77.977149,36.28267],"type":"Point"}
}