{
  "type": "Feature",
  "properties": {
    "iso:country":"US",
    "sg:address":"4 S Tunnel Rd",
    "sg:city":"Asheville",
    "sg:classifiers":[
        {
            "category":"Health Services",
            "subcategory":"Optometrist",
            "type":"Services"
        }
    ],
    "sg:phone":"+1   ",
    "sg:postcode":"28805",
    "sg:province":"NC",
    "wof:name":"Linda Frady Od",
    "wof:placetype":"venue"
},
  "geometry": {"coordinates":[-82.521764,35.579491],"type":"Point"}
}