{
  "type": "Feature",
  "properties": {
    "iso:country":"US",
    "sg:address":"5 Mitchell Ct",
    "sg:city":"Pinehurst",
    "sg:classifiers":[
        {
            "category":"Restaurant",
            "type":"Food & Drink"
        }
    ],
    "sg:phone":"+1 910 215 9000",
    "sg:postcode":"28374",
    "sg:province":"NC",
    "wof:name":"Players Cafe",
    "wof:placetype":"venue"
},
  "geometry": {"coordinates":[-79.42928499999999,35.225416],"type":"Point"}
}