{
  "type": "Feature",
  "properties": {
    "addr:full":"2755 Lewisville Clemmons Rd Clemmons NC 27012",
    "addr:housenumber":"2755",
    "addr:postcode":"27012",
    "addr:street":"Lewisville Clemmons Rd",
    "iso:country":"US",
    "sg:address":"2755 Lewisville Clemmons Rd",
    "sg:city":"Clemmons",
    "sg:classifiers":[
        {
            "category":"Banks & Credit Unions",
            "subcategory":"Bank",
            "type":"Services"
        }
    ],
    "sg:phone":"+1 336 778 8987",
    "sg:postcode":"27012",
    "sg:province":"NC",
    "sg:tags":[
        "state",
        "commercial"
    ],
    "wof:name":"Southern Community Bank and Tr",
    "wof:placetype":"venue"
},
  "geometry": {"coordinates":[-80.381973,36.022524],"type":"Point"}
}