{
  "type": "Feature",
  "properties": {
    "addr:full":"7706 N Tryon St Charlotte NC 28262",
    "addr:housenumber":"7706",
    "addr:postcode":"28262",
    "addr:street":"N Tryon St",
    "iso:country":"US",
    "sg:address":"7706 N Tryon St",
    "sg:city":"Charlotte",
    "sg:classifiers":[
        {
            "category":"Travel",
            "subcategory":"Hotels & Motels",
            "type":"Entertainment"
        }
    ],
    "sg:phone":"+1 704 510 5348",
    "sg:postcode":"28262",
    "sg:province":"NC",
    "wof:name":"In Town Suites Charlotte North",
    "wof:placetype":"venue"
},
  "geometry": {"coordinates":[-80.755771,35.293143],"type":"Point"}
}