{
  "type": "Feature",
  "properties": {
    "iso:country":"US",
    "sg:address":"211 S Dekalb St",
    "sg:city":"Shelby",
    "sg:classifiers":[
        {
            "category":"Real Estate",
            "subcategory":"Real Estate Agent",
            "type":"Services"
        }
    ],
    "sg:phone":"+1 704 482 7316",
    "sg:postcode":"28150",
    "sg:province":"NC",
    "wof:name":"Coldwell Banker",
    "wof:placetype":"venue"
},
  "geometry": {"coordinates":[-81.537268,35.290034],"type":"Point"}
}