{
  "type": "Feature",
  "properties": {
    "addr:full":"4123 Barringer Dr Charlotte NC 28217",
    "addr:housenumber":"4123",
    "addr:postcode":"28217",
    "addr:street":"Barringer Dr",
    "iso:country":"US",
    "sg:address":"4123 Barringer Dr",
    "sg:city":"Charlotte",
    "sg:classifiers":[
        {
            "category":"Wholesale",
            "subcategory":"Machinery & Supplies",
            "type":"Manufacturing & Wholesale Goods"
        }
    ],
    "sg:phone":"+1 704 523 0877",
    "sg:postcode":"28217",
    "sg:province":"NC",
    "sg:tags":[
        "wig"
    ],
    "wof:name":"A Born Co",
    "wof:placetype":"venue"
},
  "geometry": {"coordinates":[-80.89384,35.192536],"type":"Point"}
}