{
  "type": "Feature",
  "properties": {
    "iso:country":"US",
    "sg:address":"305 Gentry St",
    "sg:city":"North Wilkesboro",
    "sg:classifiers":[
        {
            "category":"Autos & Motor Vehicles",
            "subcategory":"Automobile Sales",
            "type":"Retail Goods"
        }
    ],
    "sg:phone":"+1 336 903 1100",
    "sg:postcode":"28659",
    "sg:province":"NC",
    "sg:tags":[
        "car",
        "dealer"
    ],
    "wof:name":"Combs Used Cars",
    "wof:placetype":"venue"
},
  "geometry": {"coordinates":[-81.150344,36.198793],"type":"Point"}
}