{
  "type": "Feature",
  "properties": {
    "addr:full":"15101 Aiken Rd Wake Forest NC 27587",
    "addr:housenumber":"15101",
    "addr:postcode":"27587",
    "addr:street":"Aiken Rd",
    "iso:country":"US",
    "sg:address":"15101 Aiken Rd",
    "sg:city":"Wake Forest",
    "sg:classifiers":[
        {
            "category":"Home & Garden",
            "subcategory":"Building Materials",
            "type":"Retail Goods"
        }
    ],
    "sg:phone":"+1 919 528 3352",
    "sg:postcode":"27587",
    "sg:province":"NC",
    "sg:tags":[
        "glass",
        "window",
        "plate"
    ],
    "wof:name":"Creedmoor Glass Svc",
    "wof:placetype":"venue"
},
  "geometry": {"coordinates":[-78.69944700000001,36.055785],"type":"Point"}
}