{
  "type": "Feature",
  "properties": {
    "addr:full":"197 East St Hudson NC 28638",
    "addr:housenumber":"197",
    "addr:postcode":"28638",
    "addr:street":"East St",
    "iso:country":"US",
    "sg:address":"197 East St",
    "sg:city":"Hudson",
    "sg:classifiers":[
        {
            "category":"Professional",
            "type":"Services"
        }
    ],
    "sg:phone":"+1 828 728 4468",
    "sg:postcode":"28638",
    "sg:province":"NC",
    "wof:name":"Ginger Kirby",
    "wof:placetype":"venue"
},
  "geometry": {"coordinates":[-81.481876,35.843712],"type":"Point"}
}