{
  "type": "Feature",
  "properties": {
    "addr:full":"3201 Edwards Mill Rd Raleigh NC 27612",
    "addr:housenumber":"3201",
    "addr:postcode":"27612",
    "addr:street":"Edwards Mill Rd",
    "iso:country":"US",
    "sg:address":"3201 Edwards Mill Rd",
    "sg:city":"Raleigh",
    "sg:classifiers":[
        {
            "category":"Food & Beverages",
            "subcategory":"Bakery",
            "type":"Retail Goods"
        }
    ],
    "sg:phone":"+1 919 782 3131",
    "sg:postcode":"27612",
    "sg:province":"NC",
    "sg:tags":[
        "sandwich"
    ],
    "wof:name":"Quizno Subs",
    "wof:placetype":"venue"
},
  "geometry": {"coordinates":[-78.70590199999999,35.825001],"type":"Point"}
}