{
  "type": "Feature",
  "properties": {
    "addr:full":"3600 Hillsborough Rd Durham NC 27705",
    "addr:housenumber":"3600",
    "addr:postcode":"27705",
    "addr:street":"Hillsborough Rd",
    "iso:country":"US",
    "sg:address":"3600 Hillsborough Rd",
    "sg:city":"Durham",
    "sg:classifiers":[
        {
            "category":"Recreation",
            "type":"Entertainment"
        }
    ],
    "sg:phone":"+1 919 382 8227",
    "sg:postcode":"27705",
    "sg:province":"NC",
    "sg:tags":[
        "bingo",
        "game"
    ],
    "wof:name":"Mel's",
    "wof:placetype":"venue"
},
  "geometry": {"coordinates":[-78.955511,36.023353],"type":"Point"}
}