{
  "type": "Feature",
  "properties": {
    "iso:country":"US",
    "sg:address":"336 Main St",
    "sg:city":"Leland",
    "sg:classifiers":[
        {
            "category":"Government",
            "subcategory":"Fire Station",
            "type":"Public Place"
        }
    ],
    "sg:phone":"+1 910 371 9988",
    "sg:postcode":"28451",
    "sg:province":"NC",
    "sg:tags":[
        "department",
        "protection"
    ],
    "wof:name":"Navassa Volunteer Fire Dept",
    "wof:placetype":"venue"
},
  "geometry": {"coordinates":[-78.01092199999999,34.257464],"type":"Point"}
}