{
  "type": "Feature",
  "properties": {
    "iso:country":"US",
    "sg:address":"400 W Cornwallis Dr",
    "sg:city":"Greensboro",
    "sg:classifiers":[
        {
            "category":"Restaurant",
            "type":"Food & Drink"
        }
    ],
    "sg:menulink":"http://www.allmenus.com/nc/greensboro/137835-ghassans/menu/",
    "sg:phone":"+1 336 378 1000",
    "sg:postcode":"27408",
    "sg:province":"NC",
    "sg:tags":[
        "cheesesteaks",
        "american"
    ],
    "wof:name":"Ghassan's",
    "wof:placetype":"venue"
},
  "geometry": {"coordinates":[-79.793249,36.103384],"type":"Point"}
}