{
  "type": "Feature",
  "properties": {
    "addr:full":"2626 Glenwood Ave Raleigh NC 27608",
    "addr:housenumber":"2626",
    "addr:postcode":"27608",
    "addr:street":"Glenwood Ave",
    "iso:country":"US",
    "sg:address":"2626 Glenwood Ave",
    "sg:city":"Raleigh",
    "sg:classifiers":[
        {
            "category":"Banks & Credit Unions",
            "subcategory":"Investment Brokerage",
            "type":"Services"
        }
    ],
    "sg:phone":"+1 919 787 7325",
    "sg:postcode":"27608",
    "sg:province":"NC",
    "sg:tags":[
        "advisory"
    ],
    "wof:name":"Real Estate Analysts",
    "wof:placetype":"venue"
},
  "geometry": {"coordinates":[-78.66193699999999,35.81753],"type":"Point"}
}