{
  "type": "Feature",
  "properties": {
    "addr:full":"1311 Kilmory Dr Cary NC 27511",
    "addr:housenumber":"1311",
    "addr:postcode":"27511",
    "addr:street":"Kilmory Dr",
    "iso:country":"US",
    "sg:address":"1311 Kilmory Dr",
    "sg:city":"Cary",
    "sg:classifiers":[
        {
            "category":"Professional",
            "type":"Services"
        }
    ],
    "sg:phone":"+1 919 461 0458",
    "sg:postcode":"27511",
    "sg:province":"NC",
    "wof:name":"Hart Senior Resource",
    "wof:placetype":"venue"
},
  "geometry": {"coordinates":[-78.818308,35.760459],"type":"Point"}
}