{
  "type": "Feature",
  "properties": {
    "iso:country":"US",
    "sg:address":"2815 Highway 105",
    "sg:city":"Boone",
    "sg:classifiers":[
        {
            "category":"Personal",
            "type":"Services"
        },
        {
            "category":"Home & Garden",
            "subcategory":"Building Materials",
            "type":"Retail Goods"
        },
        {
            "category":"Building & Trades",
            "subcategory":"Construction",
            "type":"Services"
        },
        {
            "category":"Manufacturing",
            "subcategory":"Building Materials",
            "type":"Manufacturing & Wholesale Goods"
        },
        {
            "category":"Home & Garden",
            "subcategory":"Furniture",
            "type":"Retail Goods"
        }
    ],
    "sg:phone":"+1 828 268 0450",
    "sg:postcode":"28607",
    "sg:province":"NC",
    "sg:tags":[
        "cabinet",
        "closet",
        "altering",
        "equipment-household",
        "window",
        "doors",
        "designing",
        "frames",
        "contractor",
        "accessory",
        "remodeling",
        "maker",
        "kitchen"
    ],
    "wof:name":"New River Showcase & Design Center",
    "wof:placetype":"venue"
},
  "geometry": {"coordinates":[-81.687579,36.203116],"type":"Point"}
}