{
  "type": "Feature",
  "properties": {
    "addr:full":"1208 Sandy Cross Rd Belvidere NC 27919",
    "addr:housenumber":"1208",
    "addr:postcode":"27919",
    "addr:street":"Sandy Cross Rd",
    "iso:country":"US",
    "sg:address":"1208 Sandy Cross Rd",
    "sg:city":"Belvidere",
    "sg:classifiers":[
        {
            "category":"Wholesale",
            "subcategory":"Farm Supplies",
            "type":"Manufacturing & Wholesale Goods"
        }
    ],
    "sg:phone":"+1 252 297 2381",
    "sg:postcode":"27919",
    "sg:province":"NC",
    "sg:tags":[
        "feed"
    ],
    "wof:name":"W S Winslow Inc",
    "wof:placetype":"venue"
},
  "geometry": {"coordinates":[-76.503941,36.321602],"type":"Point"}
}