{
  "type": "Feature",
  "properties": {
    "iso:country":"US",
    "sg:address":"5215 Rogers Rd",
    "sg:city":"Rolesville",
    "sg:classifiers":[
        {
            "category":"Building & Trades",
            "subcategory":"Construction",
            "type":"Services"
        }
    ],
    "sg:phone":"+1 919 570 5317",
    "sg:postcode":"27571",
    "sg:province":"NC",
    "sg:tags":[
        "house"
    ],
    "wof:name":"Parker Construction Inc",
    "wof:placetype":"venue"
},
  "geometry": {"coordinates":[-78.46463799999999,35.920957],"type":"Point"}
}