{
  "type": "Feature",
  "properties": {
    "iso:country":"US",
    "sg:address":"1739 State Hwy 24 27 109 W",
    "sg:city":"Troy",
    "sg:classifiers":[
        {
            "category":"Home & Garden",
            "subcategory":"Building Materials",
            "type":"Retail Goods"
        }
    ],
    "sg:phone":"+1 910 572 1011",
    "sg:postcode":"27371",
    "sg:province":"NC",
    "sg:tags":[
        "mixed",
        "concrete"
    ],
    "wof:name":"Troy Ready Mix",
    "wof:placetype":"venue"
},
  "geometry": {"coordinates":[-79.939159,35.325556],"type":"Point"}
}