{
  "type": "Feature",
  "properties": {
    "iso:country":"US",
    "sg:address":"14 O Henry Ave",
    "sg:city":"Asheville",
    "sg:classifiers":[
        {
            "category":"Education",
            "subcategory":"Library",
            "type":"Public Place"
        },
        {
            "category":"Manufacturing",
            "subcategory":"Printing",
            "type":"Manufacturing & Wholesale Goods"
        }
    ],
    "sg:phone":"+1 828 273 0240",
    "sg:postcode":"28801",
    "sg:province":"NC",
    "sg:tags":[
        "printer",
        "special",
        "interest"
    ],
    "sg:website":"www.citizen-times.com",
    "wof:name":"Asheville Citizen-Times Prntng",
    "wof:placetype":"venue"
},
  "geometry": {"coordinates":[-82.56728099999999,35.602711],"type":"Point"}
}