{
  "type": "Feature",
  "properties": {
    "addr:full":"2664 Bluebird Ln SW Supply NC 28462",
    "addr:housenumber":"2664",
    "addr:postcode":"28462",
    "addr:street":"Bluebird Ln Sw",
    "iso:country":"US",
    "sg:address":"2664 Bluebird Ln SW",
    "sg:city":"Supply",
    "sg:classifiers":[
        {
            "category":"Retail",
            "subcategory":"Auto Repair",
            "type":"Services"
        }
    ],
    "sg:phone":"+1   ",
    "sg:postcode":"28462",
    "sg:province":"NC",
    "sg:tags":[
        "body"
    ],
    "wof:name":"Coombs Auto Trim",
    "wof:placetype":"venue"
},
  "geometry": {"coordinates":[-78.313181,33.919331],"type":"Point"}
}