{
  "type": "Feature",
  "properties": {
    "addr:full":"11414 Larix Dr Charlotte NC 28273",
    "addr:postcode":"11414;28273",
    "addr:street":"Larix Dr",
    "iso:country":"US",
    "sg:address":"11414 Larix Dr",
    "sg:city":"Charlotte",
    "sg:classifiers":[
        {
            "category":"Building & Trades",
            "subcategory":"Cleaning & Sanitation",
            "type":"Services"
        }
    ],
    "sg:phone":"+1   ",
    "sg:postcode":"28273",
    "sg:province":"NC",
    "sg:tags":[
        "maintenance"
    ],
    "wof:name":"Action Building Services Inc",
    "wof:placetype":"venue"
},
  "geometry": {"coordinates":[-80.96644999999999,35.148275],"type":"Point"}
}