{
  "type": "Feature",
  "properties": {
    "iso:country":"US",
    "sg:address":"760 Haywood Rd",
    "sg:city":"Asheville",
    "sg:classifiers":[
        {
            "category":"Food & Beverages",
            "subcategory":"Groceries & Convenience Stores",
            "type":"Retail Goods"
        }
    ],
    "sg:phone":"+1 828 254 1397",
    "sg:postcode":"28806",
    "sg:province":"NC",
    "wof:name":"Citizens Food Stores",
    "wof:placetype":"venue"
},
  "geometry": {"coordinates":[-82.593597,35.578201],"type":"Point"}
}