{
  "type": "Feature",
  "properties": {
    "addr:full":"6420 Rea Rd Charlotte NC 28277",
    "addr:housenumber":"6420",
    "addr:postcode":"28277",
    "addr:street":"Rea Rd",
    "iso:country":"US",
    "sg:address":"6420 Rea Rd",
    "sg:city":"Charlotte",
    "sg:classifiers":[
        {
            "category":"Health Services",
            "subcategory":"Doctor",
            "type":"Services"
        }
    ],
    "sg:phone":"+1   ",
    "sg:postcode":"28277",
    "sg:province":"NC",
    "sg:tags":[
        "medical"
    ],
    "wof:name":"Shamrocbel Inc",
    "wof:placetype":"venue"
},
  "geometry": {"coordinates":[-80.816632,35.079398],"type":"Point"}
}