{
  "type": "Feature",
  "properties": {
    "iso:country":"US",
    "sg:address":"69 Iotla St",
    "sg:city":"Franklin",
    "sg:classifiers":[
        {
            "category":"Organizations",
            "subcategory":"Religious Organization",
            "type":"Services"
        }
    ],
    "sg:phone":"+1 828 369 9559",
    "sg:postcode":"28734",
    "sg:province":"NC",
    "sg:tags":[
        "churches-baptist"
    ],
    "sg:website":"http://www.fbcfranklin.org",
    "wof:name":"Faith Baptist Church",
    "wof:placetype":"venue"
},
  "geometry": {"coordinates":[-83.38149199999999,35.182638],"type":"Point"}
}