{
  "type": "Feature",
  "properties": {
    "addr:full":"217 Walker Ave Graham NC 27253",
    "addr:housenumber":"217",
    "addr:postcode":"27253",
    "addr:street":"Walker Ave",
    "iso:country":"US",
    "sg:address":"217 Walker Ave",
    "sg:city":"Graham",
    "sg:classifiers":[
        {
            "category":"Education",
            "subcategory":"Special Training",
            "type":"Public Place"
        }
    ],
    "sg:phone":"+1   ",
    "sg:postcode":"27253",
    "sg:province":"NC",
    "wof:name":"Modeling Elite",
    "wof:placetype":"venue"
},
  "geometry": {"coordinates":[-79.39364399999999,36.07273],"type":"Point"}
}