{
  "type": "Feature",
  "properties": {
    "addr:full":"1100 Ridgefield Blvd Asheville NC 28806",
    "addr:housenumber":"1100",
    "addr:postcode":"28806",
    "addr:street":"Ridgefield Blvd",
    "iso:country":"US",
    "sg:address":"1100 Ridgefield Blvd",
    "sg:city":"Asheville",
    "sg:classifiers":[
        {
            "category":"Professional",
            "subcategory":"Lawyer & Legal Services",
            "type":"Services"
        }
    ],
    "sg:phone":"+1 828 418 1283",
    "sg:postcode":"28806",
    "sg:province":"NC",
    "wof:name":"Price Phillip C Atty",
    "wof:placetype":"venue"
},
  "geometry": {"coordinates":[-82.60045100000001,35.525767],"type":"Point"}
}