{
  "type": "Feature",
  "properties": {
    "addr:full":"1420 Exchange St Charlotte NC 28208",
    "addr:housenumber":"1420",
    "addr:postcode":"28208",
    "addr:street":"Exchange St",
    "iso:country":"US",
    "sg:address":"1420 Exchange St",
    "sg:city":"Charlotte",
    "sg:classifiers":[
        {
            "category":"Professional",
            "subcategory":"Management & Consulting",
            "type":"Services"
        }
    ],
    "sg:phone":"+1 704 392 6680",
    "sg:postcode":"28208",
    "sg:province":"NC",
    "sg:tags":[
        "food",
        "organizing",
        "business",
        "services-household"
    ],
    "wof:name":"Iron Mountain",
    "wof:placetype":"venue"
},
  "geometry": {"coordinates":[-80.908477,35.272417],"type":"Point"}
}