{
  "type": "Feature",
  "properties": {
    "iso:country":"US",
    "sg:address":"156 High Valley Rd",
    "sg:city":"Bryson City",
    "sg:classifiers":[
        {
            "category":"Professional",
            "subcategory":"Accounting & Tax Preparation",
            "type":"Services"
        }
    ],
    "sg:phone":"+1 828 488 9222",
    "sg:postcode":"28713",
    "sg:province":"NC",
    "sg:tags":[
        "accountant"
    ],
    "wof:name":"Joanna Foster CPA",
    "wof:placetype":"venue"
},
  "geometry": {"coordinates":[-83.530554,35.357647],"type":"Point"}
}