{
  "type": "Feature",
  "properties": {
    "iso:country":"US",
    "sg:address":"116 Piney Green Rd",
    "sg:city":"Jacksonville",
    "sg:classifiers":[
        {
            "category":"Food & Beverages",
            "subcategory":"Groceries & Convenience Stores",
            "type":"Retail Goods"
        }
    ],
    "sg:phone":"+1 910 346 3369",
    "sg:postcode":"28546",
    "sg:province":"NC",
    "wof:name":"Dash N Convenient Store Grocr",
    "wof:placetype":"venue"
},
  "geometry": {"coordinates":[-77.377393,34.785553],"type":"Point"}
}