{
  "type": "Feature",
  "properties": {
    "addr:full":"153 Smokey Park Hwy Asheville NC 28806",
    "addr:housenumber":"153",
    "addr:postcode":"28806",
    "addr:street":"Smokey Park Hwy",
    "iso:country":"US",
    "sg:address":"153 Smokey Park Hwy",
    "sg:city":"Asheville",
    "sg:classifiers":[
        {
            "category":"Government",
            "subcategory":"Office",
            "type":"Public Place"
        }
    ],
    "sg:phone":"+1 828 667 2104",
    "sg:postcode":"28806",
    "sg:province":"NC",
    "sg:tags":[
        "state",
        "program"
    ],
    "wof:name":"Motor Vehicle-License Tag Agcy",
    "wof:placetype":"venue"
},
  "geometry": {"coordinates":[-82.627989,35.564542],"type":"Point"}
}