{
  "type": "Feature",
  "properties": {
    "addr:full":"214 Hillcrest Cir Chapel Hill NC 27514",
    "addr:housenumber":"214",
    "addr:postcode":"27514",
    "addr:street":"Hillcrest Cir",
    "iso:country":"US",
    "sg:address":"214 Hillcrest Cir",
    "sg:city":"Chapel Hill",
    "sg:classifiers":[
        {
            "category":"Real Estate",
            "subcategory":"Real Estate Operator",
            "type":"Services"
        }
    ],
    "sg:phone":"+1 919 929 6381",
    "sg:postcode":"27514",
    "sg:province":"NC",
    "sg:tags":[
        "building",
        "nonresidential"
    ],
    "wof:name":"Dancing Sheep Properties LLC",
    "wof:placetype":"venue"
},
  "geometry": {"coordinates":[-79.03517600000001,35.921215],"type":"Point"}
}