{
  "type": "Feature",
  "properties": {
    "addr:full":"2001 E Arlington Blvd Greenville NC 27858",
    "addr:housenumber":"2001",
    "addr:postcode":"27858",
    "addr:street":"E Arlington Blvd",
    "iso:country":"US",
    "sg:address":"2001 E Arlington Blvd",
    "sg:city":"Greenville",
    "sg:classifiers":[
        {
            "category":"Restaurant",
            "type":"Food & Drink"
        }
    ],
    "sg:phone":"+1 252 353 1388",
    "sg:postcode":"27858",
    "sg:province":"NC",
    "wof:name":"Bojangles' Famous Chicken",
    "wof:placetype":"venue"
},
  "geometry": {"coordinates":[-77.356211,35.566669],"type":"Point"}
}