{
  "type": "Feature",
  "properties": {
    "iso:country":"US",
    "sg:address":"723 Coliseum Dr NW",
    "sg:city":"Winston Salem",
    "sg:classifiers":[
        {
            "category":"Insurance",
            "subcategory":"Insurance Agent",
            "type":"Services"
        }
    ],
    "sg:phone":"+1 336 725 7222",
    "sg:postcode":"27106",
    "sg:province":"NC",
    "wof:name":"Googe Financial Svc",
    "wof:placetype":"venue"
},
  "geometry": {"coordinates":[-80.264154,36.123658],"type":"Point"}
}