{
  "type": "Feature",
  "properties": {
    "iso:country":"US",
    "sg:address":"2101 Rexford Rd",
    "sg:city":"Charlotte",
    "sg:classifiers":[
        {
            "category":"Manufacturing",
            "subcategory":"Paper Products",
            "type":"Manufacturing & Wholesale Goods"
        }
    ],
    "sg:phone":"+1 704 543 1881",
    "sg:postcode":"28211",
    "sg:province":"NC",
    "sg:tags":[
        "mill"
    ],
    "wof:name":"Weyerhaeuser Company",
    "wof:placetype":"venue"
},
  "geometry": {"coordinates":[-80.83225,35.157952],"type":"Point"}
}