{
  "type": "Feature",
  "properties": {
    "iso:country":"US",
    "sg:address":"714 Reed St",
    "sg:city":"Asheville",
    "sg:classifiers":[
        {
            "category":"Retail",
            "subcategory":"Animal Services",
            "type":"Services"
        }
    ],
    "sg:phone":"+1 828 274 2919",
    "sg:postcode":"28803",
    "sg:province":"NC",
    "wof:name":"Animal World",
    "wof:placetype":"venue"
},
  "geometry": {"coordinates":[-82.53554800000001,35.550671],"type":"Point"}
}