{
  "type": "Feature",
  "properties": {
    "addr:full":"4521 Sharon Rd Charlotte NC 28211",
    "addr:housenumber":"4521",
    "addr:postcode":"28211",
    "addr:street":"Sharon Rd",
    "iso:country":"US",
    "sg:address":"4521 Sharon Rd",
    "sg:city":"Charlotte",
    "sg:classifiers":[
        {
            "category":"Shopping",
            "subcategory":"Jewelry",
            "type":"Retail Goods"
        }
    ],
    "sg:phone":"+1 704 532 7761",
    "sg:postcode":"28211",
    "sg:province":"NC",
    "sg:tags":[
        "diamond"
    ],
    "wof:name":"Diamonds Direct",
    "wof:placetype":"venue"
},
  "geometry": {"coordinates":[-80.830782,35.148486],"type":"Point"}
}