{
  "type": "Feature",
  "properties": {
    "addr:full":"20117 Catawba Ave Cornelius NC 28031",
    "addr:housenumber":"20117",
    "addr:postcode":"28031",
    "addr:street":"Catawba Ave",
    "iso:country":"US",
    "sg:address":"20117 Catawba Ave",
    "sg:city":"Cornelius",
    "sg:phone":"+1 704 892 9673",
    "sg:postcode":"28031",
    "sg:province":"NC",
    "sg:website":"http://www.lakenormanrealty.com",
    "wof:name":"Lake Norman Realty Inc",
    "wof:placetype":"venue"
},
  "geometry": {"coordinates":[-80.881519,35.4823],"type":"Point"}
}