{
  "type": "Feature",
  "properties": {
    "addr:full":"3210 Caroline-Nicole Dr Kinston NC 28504",
    "addr:housenumber":"3210",
    "addr:postcode":"28504",
    "addr:street":"Caroline-Nicole Dr",
    "iso:country":"US",
    "sg:address":"3210 Caroline-Nicole Dr",
    "sg:city":"Kinston",
    "sg:classifiers":[
        {
            "category":"Personal",
            "subcategory":"Beauty Salon",
            "type":"Services"
        }
    ],
    "sg:phone":"+1   ",
    "sg:postcode":"28504",
    "sg:province":"NC",
    "sg:tags":[
        "shop"
    ],
    "wof:name":"Allure Web Designs",
    "wof:placetype":"venue"
},
  "geometry": {"coordinates":[-77.69483200000001,35.295392],"type":"Point"}
}