{
  "type": "Feature",
  "properties": {
    "addr:full":"6236 Teal St Wilmington NC 28403",
    "addr:housenumber":"6236",
    "addr:postcode":"28403",
    "addr:street":"Teal St",
    "iso:country":"US",
    "sg:address":"6236 Teal St",
    "sg:city":"Wilmington",
    "sg:classifiers":[
        {
            "category":"Personal",
            "type":"Services"
        }
    ],
    "sg:phone":"+1 910 790 9874",
    "sg:postcode":"28403",
    "sg:province":"NC",
    "sg:tags":[
        "therapist",
        "massage"
    ],
    "wof:name":"Rolfing By Judith Clinton",
    "wof:placetype":"venue"
},
  "geometry": {"coordinates":[-77.850179,34.228701],"type":"Point"}
}