{
  "type": "Feature",
  "properties": {
    "addr:full":"4100 M L King Jr Blvd New Bern NC 28562",
    "addr:housenumber":"4100",
    "addr:postcode":"28562",
    "addr:street":"M L King Jr Blvd",
    "iso:country":"US",
    "sg:address":"4100 M L King Jr Blvd",
    "sg:city":"New Bern",
    "sg:classifiers":[
        {
            "category":"Food & Beverages",
            "subcategory":"Groceries & Convenience Stores",
            "type":"Retail Goods"
        }
    ],
    "sg:phone":"+1 252 638 4668",
    "sg:postcode":"28562",
    "sg:province":"NC",
    "wof:name":"Trade Mart",
    "wof:placetype":"venue"
},
  "geometry": {"coordinates":[-77.118956,35.09497],"type":"Point"}
}