{
  "type": "Feature",
  "properties": {
    "addr:full":"185 Duke St Granite Falls NC 28630",
    "addr:housenumber":"185",
    "addr:postcode":"28630",
    "addr:street":"Duke St",
    "iso:country":"US",
    "sg:address":"185 Duke St",
    "sg:city":"Granite Falls",
    "sg:classifiers":[
        {
            "category":"Personal",
            "subcategory":"Beauty Salon",
            "type":"Services"
        }
    ],
    "sg:phone":"+1 828 396 3019",
    "sg:postcode":"28630",
    "sg:province":"NC",
    "wof:name":"Touch Of Elegance Hairstylist",
    "wof:placetype":"venue"
},
  "geometry": {"coordinates":[-81.42890300000001,35.782878],"type":"Point"}
}