{
  "type": "Feature",
  "properties": {
    "addr:full":"417 Elm St Raleigh NC 27604",
    "addr:housenumber":"417",
    "addr:postcode":"27604",
    "addr:street":"Elm St",
    "iso:country":"US",
    "sg:address":"417 Elm St",
    "sg:city":"Raleigh",
    "sg:classifiers":[
        {
            "category":"Arts & Performance",
            "subcategory":"Theater",
            "type":"Entertainment"
        }
    ],
    "sg:phone":"+1   ",
    "sg:postcode":"27604",
    "sg:province":"NC",
    "sg:tags":[
        "group"
    ],
    "wof:name":"Crew Cuts",
    "wof:placetype":"venue"
},
  "geometry": {"coordinates":[-78.630398,35.785755],"type":"Point"}
}