{
  "type": "Feature",
  "properties": {
    "addr:full":"1828 Murchison Rd Fayetteville NC 28301",
    "addr:housenumber":"1828",
    "addr:postcode":"28301",
    "addr:street":"Murchison Rd",
    "iso:country":"US",
    "sg:address":"1828 Murchison Rd",
    "sg:city":"Fayetteville",
    "sg:classifiers":[
        {
            "category":"Restaurant",
            "type":"Food & Drink"
        }
    ],
    "sg:phone":"+1 910 488 6189",
    "sg:postcode":"28301",
    "sg:province":"NC",
    "wof:name":"Bar-B-Que House",
    "wof:placetype":"venue"
},
  "geometry": {"coordinates":[-78.902237,35.081744],"type":"Point"}
}