{
  "type": "Feature",
  "properties": {
    "addr:full":"1931 Randolph Rd Shelby NC 28150",
    "addr:housenumber":"1931",
    "addr:postcode":"28150",
    "addr:street":"Randolph Rd",
    "iso:country":"US",
    "sg:address":"1931 Randolph Rd",
    "sg:city":"Shelby",
    "sg:classifiers":[
        {
            "category":"Professional",
            "type":"Services"
        }
    ],
    "sg:phone":"+1 704 482 8828",
    "sg:postcode":"28150",
    "sg:province":"NC",
    "sg:tags":[
        "establishment"
    ],
    "wof:name":"Woodchuck Chipper",
    "wof:placetype":"venue"
},
  "geometry": {"coordinates":[-81.581186,35.304918],"type":"Point"}
}