{
  "type": "Feature",
  "properties": {
    "addr:full":"1729 Sunderland Ct Raleigh NC 27603",
    "addr:housenumber":"1729",
    "addr:postcode":"27603",
    "addr:street":"Sunderland Ct",
    "iso:country":"US",
    "sg:address":"1729 Sunderland Ct",
    "sg:city":"Raleigh",
    "sg:classifiers":[
        {
            "category":"Building & Trades",
            "subcategory":"Plumbing",
            "type":"Services"
        }
    ],
    "sg:phone":"+1 919 662 7928",
    "sg:postcode":"27603",
    "sg:province":"NC",
    "sg:tags":[
        "contractor"
    ],
    "wof:name":"Teamwork Services",
    "wof:placetype":"venue"
},
  "geometry": {"coordinates":[-78.660253,35.613247],"type":"Point"}
}