{
  "type": "Feature",
  "properties": {
    "iso:country":"US",
    "sg:address":"9565 Nc Highway 65",
    "sg:city":"Stokesdale",
    "sg:classifiers":[
        {
            "category":"Social Services",
            "subcategory":"Child Care",
            "type":"Services"
        }
    ],
    "sg:phone":"+1 336 427 4930",
    "sg:postcode":"27357",
    "sg:province":"NC",
    "sg:tags":[
        "nursery",
        "day"
    ],
    "wof:name":"Stokesdale Day Care",
    "wof:placetype":"venue"
},
  "geometry": {"coordinates":[-79.94337,36.26121],"type":"Point"}
}