{
  "type": "Feature",
  "properties": {
    "addr:full":"401 N Greensboro St Carrboro NC 27510",
    "addr:housenumber":"401",
    "addr:postcode":"27510",
    "addr:street":"N Greensboro St",
    "iso:country":"US",
    "sg:address":"401 N Greensboro St",
    "sg:city":"Carrboro",
    "sg:classifiers":[
        {
            "category":"Personal",
            "subcategory":"Beauty Salon",
            "type":"Services"
        }
    ],
    "sg:phone":"+1 919 968 0005",
    "sg:postcode":"27510",
    "sg:province":"NC",
    "sg:tags":[
        "hair"
    ],
    "wof:name":"Capelli Hair Studio",
    "wof:placetype":"venue"
},
  "geometry": {"coordinates":[-79.072256,35.912955],"type":"Point"}
}