{
  "type": "Feature",
  "properties": {
    "iso:country":"US",
    "sg:address":"6807 Fayetteville Rd",
    "sg:city":"Durham",
    "sg:classifiers":[
        {
            "category":"Personal",
            "subcategory":"Tanning Parlor",
            "type":"Services"
        }
    ],
    "sg:phone":"+1 919 572 7737",
    "sg:postcode":"27713",
    "sg:province":"NC",
    "sg:tags":[
        "salon"
    ],
    "wof:name":"Planet Beach Tanning & Spa",
    "wof:placetype":"venue"
},
  "geometry": {"coordinates":[-78.938236,35.904171],"type":"Point"}
}