{
  "type": "Feature",
  "properties": {
    "addr:full":"11257 US Hwy 17 Vanceboro NC 28586",
    "addr:housenumber":"11257",
    "addr:postcode":"28586",
    "addr:street":"Us Hwy 17",
    "iso:country":"US",
    "sg:address":"11257 US Hwy 17",
    "sg:city":"Vanceboro",
    "sg:classifiers":[
        {
            "category":"Retail",
            "subcategory":"Auto Repair",
            "type":"Services"
        }
    ],
    "sg:phone":"+1 252 244 0903",
    "sg:postcode":"28586",
    "sg:province":"NC",
    "sg:tags":[
        "quick",
        "lube",
        "tire",
        "store"
    ],
    "wof:name":"Performance Plus Tires & Oil",
    "wof:placetype":"venue"
},
  "geometry": {"coordinates":[-77.149495,35.376046],"type":"Point"}
}