{
  "type": "Feature",
  "properties": {
    "addr:full":"3607 Oleander Dr Wilmington NC 28403",
    "addr:housenumber":"3607",
    "addr:postcode":"28403",
    "addr:street":"Oleander Dr",
    "iso:country":"US",
    "sg:address":"3607 Oleander Dr",
    "sg:city":"Wilmington",
    "sg:classifiers":[
        {
            "category":"Shopping",
            "subcategory":"Clothing, Apparel, & Fashions",
            "type":"Retail Goods"
        }
    ],
    "sg:phone":"+1 910 313 1100",
    "sg:postcode":"28403",
    "sg:province":"NC",
    "wof:name":"Talbots",
    "wof:placetype":"venue"
},
  "geometry": {"coordinates":[-77.903854,34.216061],"type":"Point"}
}