{
  "type": "Feature",
  "properties": {
    "addr:full":"1208 Front St Raleigh NC 27609",
    "addr:housenumber":"1208",
    "addr:postcode":"27609",
    "addr:street":"Front St",
    "iso:country":"US",
    "sg:address":"1208 Front St",
    "sg:city":"Raleigh",
    "sg:classifiers":[
        {
            "category":"Building & Trades",
            "subcategory":"Plumbing",
            "type":"Services"
        }
    ],
    "sg:phone":"+1 919 828 5895",
    "sg:postcode":"27609",
    "sg:province":"NC",
    "sg:tags":[
        "heating",
        "contractor"
    ],
    "wof:name":"Michel RE Co Inc",
    "wof:placetype":"venue"
},
  "geometry": {"coordinates":[-78.61480899999999,35.821172],"type":"Point"}
}