{
  "type": "Feature",
  "properties": {
    "addr:full":"4321 Huntsfield Rd Fayetteville NC 28314",
    "addr:housenumber":"4321",
    "addr:postcode":"28314",
    "addr:street":"Huntsfield Rd",
    "iso:country":"US",
    "sg:address":"4321 Huntsfield Rd",
    "sg:city":"Fayetteville",
    "sg:classifiers":[
        {
            "category":"Real Estate",
            "subcategory":"Real Estate Agent",
            "type":"Services"
        }
    ],
    "sg:phone":"+1 910 484 2914",
    "sg:postcode":"28314",
    "sg:province":"NC",
    "sg:tags":[
        "agency"
    ],
    "wof:name":"Dickens-Bass Realty & Cnstr",
    "wof:placetype":"venue"
},
  "geometry": {"coordinates":[-78.949556,35.053619],"type":"Point"}
}