{
  "type": "Feature",
  "properties": {
    "addr:full":"1146 State Rte 32 Corapeake NC 27926",
    "addr:housenumber":"1146",
    "addr:postcode":"27926",
    "addr:street":"State Rte 32",
    "iso:country":"US",
    "sg:address":"1146 State Rte 32",
    "sg:city":"Corapeake",
    "sg:classifiers":[
        {
            "category":"Organizations",
            "subcategory":"Religious Organization",
            "type":"Services"
        }
    ],
    "sg:phone":"+1 252 465 9920",
    "sg:postcode":"27926",
    "sg:province":"NC",
    "sg:tags":[
        "church"
    ],
    "wof:name":"Miracle Temple Deliverance Ctr",
    "wof:placetype":"venue"
},
  "geometry": {"coordinates":[-76.572197,36.496502],"type":"Point"}
}