{
  "type": "Feature",
  "properties": {
    "addr:full":"605 Scuppernong Rd Columbia NC 27928",
    "addr:housenumber":"605",
    "addr:postcode":"27928",
    "addr:street":"Scuppernong Rd",
    "iso:country":"US",
    "sg:address":"605 Scuppernong Rd",
    "sg:city":"Columbia",
    "sg:classifiers":[
        {
            "category":"Personal",
            "subcategory":"Beauty Salon",
            "type":"Services"
        }
    ],
    "sg:phone":"+1 252 796 5200",
    "sg:postcode":"27928",
    "sg:province":"NC",
    "wof:name":"Eternal Beauty",
    "wof:placetype":"venue"
},
  "geometry": {"coordinates":[-76.435823,35.91963],"type":"Point"}
}