{
  "type": "Feature",
  "properties": {
    "addr:full":"416 N Main St Hendersonville NC 28792",
    "addr:housenumber":"416",
    "addr:postcode":"28792",
    "addr:street":"N Main St",
    "iso:country":"US",
    "sg:address":"416 N Main St",
    "sg:city":"Hendersonville",
    "sg:classifiers":[
        {
            "category":"Home & Garden",
            "subcategory":"Home Furnishings",
            "type":"Retail Goods"
        }
    ],
    "sg:phone":"+1 828 693 9555",
    "sg:postcode":"28792",
    "sg:province":"NC",
    "sg:tags":[
        "gourmet",
        "cookware"
    ],
    "wof:name":"Purple Sage",
    "wof:placetype":"venue"
},
  "geometry": {"coordinates":[-82.46034299999999,35.317595],"type":"Point"}
}