{
  "type": "Feature",
  "properties": {
    "iso:country":"US",
    "sg:address":"1025 Alamance Church Rd",
    "sg:city":"Greensboro",
    "sg:classifiers":[
        {
            "category":"Restaurant",
            "type":"Food & Drink"
        }
    ],
    "sg:phone":"+1 336 273 6944",
    "sg:postcode":"27406",
    "sg:province":"NC",
    "sg:tags":[
        "eating"
    ],
    "wof:name":"Golden Pizza & Subs",
    "wof:placetype":"venue"
},
  "geometry": {"coordinates":[-79.771181,36.041564],"type":"Point"}
}