{
  "type": "Feature",
  "properties": {
    "addr:full":"2657 Appliance Ct Raleigh NC 27604",
    "addr:postcode":"2657;27604",
    "addr:street":"Appliance Ct",
    "iso:country":"US",
    "sg:address":"2657 Appliance Ct",
    "sg:city":"Raleigh",
    "sg:classifiers":[
        {
            "category":"Bakery",
            "type":"Food & Drink"
        }
    ],
    "sg:menulink":"http://www.allmenus.com/nc/st-matthews/102299-perkins-restaurant--bakery/menu/",
    "sg:phone":"+1 919 828 7375",
    "sg:postcode":"27604",
    "sg:province":"NC",
    "sg:tags":[
        "sandwich",
        "salad",
        "soup",
        "american",
        "pastry",
        "wrap"
    ],
    "wof:name":"Perkins Restaurant & Bakery",
    "wof:placetype":"venue"
},
  "geometry": {"coordinates":[-78.602621,35.815094],"type":"Point"}
}