{
  "type": "Feature",
  "properties": {
    "iso:country":"US",
    "sg:address":"2725 Old Wrightsboro Rd",
    "sg:city":"Wilmington",
    "sg:classifiers":[
        {
            "category":"Building & Trades",
            "subcategory":"Construction",
            "type":"Services"
        }
    ],
    "sg:phone":"+1 910 762 1850",
    "sg:postcode":"28405",
    "sg:province":"NC",
    "sg:tags":[
        "elevator"
    ],
    "wof:name":"Atlantic Elevators Southeast",
    "wof:placetype":"venue"
},
  "geometry": {"coordinates":[-77.909542,34.28809],"type":"Point"}
}