{
  "type": "Feature",
  "properties": {
    "iso:country":"US",
    "sg:address":"902 State Hwy 18",
    "sg:city":"North Wilkesboro",
    "sg:classifiers":[
        {
            "category":"Restaurant",
            "type":"Food & Drink"
        }
    ],
    "sg:phone":"+1 336 838 1234",
    "sg:postcode":"28659",
    "sg:province":"NC",
    "sg:tags":[
        "eating"
    ],
    "wof:name":"Coffee House / Waffle Sp 902",
    "wof:placetype":"venue"
},
  "geometry": {"coordinates":[-81.146452,36.159535],"type":"Point"}
}