{
  "type": "Feature",
  "properties": {
    "addr:full":"101 S Herndon St Fayetteville NC 28303",
    "addr:housenumber":"101",
    "addr:postcode":"28303",
    "addr:street":"S Herndon St",
    "iso:country":"US",
    "sg:address":"101 S Herndon St",
    "sg:city":"Fayetteville",
    "sg:classifiers":[
        {
            "category":"Personal",
            "subcategory":"Beauty Salon",
            "type":"Services"
        }
    ],
    "sg:phone":"+1 910 868 4640",
    "sg:postcode":"28303",
    "sg:province":"NC",
    "sg:tags":[
        "shop"
    ],
    "wof:name":"Pam's Beauty Salon",
    "wof:placetype":"venue"
},
  "geometry": {"coordinates":[-78.93877999999999,35.063328],"type":"Point"}
}