{
  "type": "Feature",
  "properties": {
    "iso:country":"US",
    "sg:address":"204 6th Ave W",
    "sg:city":"Hendersonville",
    "sg:classifiers":[
        {
            "category":"Organizations",
            "subcategory":"Religious Organization",
            "type":"Services"
        }
    ],
    "sg:phone":"+1 828 693 4275",
    "sg:postcode":"28739",
    "sg:province":"NC",
    "sg:tags":[
        "church"
    ],
    "sg:website":"www.hvlfumc.org",
    "wof:name":"First United Meth Chr",
    "wof:placetype":"venue"
},
  "geometry": {"coordinates":[-82.463711,35.318609],"type":"Point"}
}