{
  "type": "Feature",
  "properties": {
    "iso:country":"US",
    "sg:address":"125 W Main St",
    "sg:city":"Elkin",
    "sg:classifiers":[
        {
            "category":"Real Estate",
            "subcategory":"Real Estate Agent",
            "type":"Services"
        }
    ],
    "sg:phone":"+1 336 835 1313",
    "sg:postcode":"28621",
    "sg:province":"NC",
    "wof:name":"Mayberry Land Company Inc",
    "wof:placetype":"venue"
},
  "geometry": {"coordinates":[-80.85098000000001,36.243927],"type":"Point"}
}