{
  "type": "Feature",
  "properties": {
    "addr:full":"4914 Skyland Loop Wilson NC 27851",
    "addr:housenumber":"4914",
    "addr:postcode":"27851",
    "addr:street":"Skyland Loop",
    "iso:country":"US",
    "sg:address":"4914 Skyland Loop",
    "sg:city":"Wilson",
    "sg:classifiers":[
        {
            "category":"Retail",
            "subcategory":"Auto Repair",
            "type":"Services"
        }
    ],
    "sg:phone":"+1   ",
    "sg:postcode":"27851",
    "sg:province":"NC",
    "sg:tags":[
        "general"
    ],
    "wof:name":"Rouse Auto Repair",
    "wof:placetype":"venue"
},
  "geometry": {"coordinates":[-77.972199,35.677189],"type":"Point"}
}