{
  "type": "Feature",
  "properties": {
    "addr:full":"505 Cornerstone Ct Hillsborough NC 27278",
    "addr:housenumber":"505",
    "addr:postcode":"27278",
    "addr:street":"Cornerstone Ct",
    "iso:country":"US",
    "sg:address":"505 Cornerstone Ct",
    "sg:city":"Hillsborough",
    "sg:classifiers":[
        {
            "category":"Government",
            "subcategory":"Office",
            "type":"Public Place"
        }
    ],
    "sg:phone":"+1 919 644 0111",
    "sg:postcode":"27278",
    "sg:province":"NC",
    "sg:tags":[
        "city"
    ],
    "wof:name":"Joe City Roaster Inc",
    "wof:placetype":"venue"
},
  "geometry": {"coordinates":[-79.08680200000001,36.061126],"type":"Point"}
}