{
  "type": "Feature",
  "properties": {
    "addr:full":"4929 Old Beulah Rd Selma NC 27576",
    "addr:housenumber":"4929",
    "addr:postcode":"27576",
    "addr:street":"Old Beulah Rd",
    "iso:country":"US",
    "sg:address":"4929 Old Beulah Rd",
    "sg:city":"Selma",
    "sg:classifiers":[
        {
            "category":"Health Services",
            "subcategory":"Doctor",
            "type":"Services"
        }
    ],
    "sg:phone":"+1 919 934 0212",
    "sg:postcode":"27576",
    "sg:province":"NC",
    "sg:tags":[
        "physician",
        "surgeon"
    ],
    "wof:name":"Joseph Jan Creech DO",
    "wof:placetype":"venue"
},
  "geometry": {"coordinates":[-78.20461899999999,35.585957],"type":"Point"}
}