{
  "type": "Feature",
  "properties": {
    "addr:full":"3325 Quarry Rd Wake Forest NC 27587",
    "addr:housenumber":"3325",
    "addr:postcode":"27587",
    "addr:street":"Quarry Rd",
    "iso:country":"US",
    "sg:address":"3325 Quarry Rd",
    "sg:city":"Wake Forest",
    "sg:classifiers":[
        {
            "category":"Shopping",
            "type":"Retail Goods"
        }
    ],
    "sg:phone":"+1 919 556 2148",
    "sg:postcode":"27587",
    "sg:province":"NC",
    "sg:tags":[
        "merchandise"
    ],
    "wof:name":"Tolers Monuments",
    "wof:placetype":"venue"
},
  "geometry": {"coordinates":[-78.434359,35.910067],"type":"Point"}
}