{
  "type": "Feature",
  "properties": {
    "iso:country":"US",
    "sg:address":"953 Baxter Rd",
    "sg:city":"Cherryville",
    "sg:classifiers":[
        {
            "category":"Farming",
            "subcategory":"Poultry Farm",
            "type":"Manufacturing & Wholesale Goods"
        }
    ],
    "sg:phone":"+1 704 435 0249",
    "sg:postcode":"28021",
    "sg:province":"NC",
    "sg:tags":[
        "hatchery"
    ],
    "wof:name":"Doug E Beam",
    "wof:placetype":"venue"
},
  "geometry": {"coordinates":[-81.43377,35.406742],"type":"Point"}
}