{
  "type": "Feature",
  "properties": {
    "addr:full":"2100 N Main St High Point NC 27262",
    "addr:housenumber":"2100",
    "addr:postcode":"27262",
    "addr:street":"N Main St",
    "iso:country":"US",
    "sg:address":"2100 N Main St",
    "sg:city":"High Point",
    "sg:classifiers":[
        {
            "category":"Utilities",
            "subcategory":"Mobile Phone",
            "type":"Services"
        }
    ],
    "sg:phone":"+1 336 869 5453",
    "sg:postcode":"27262",
    "sg:province":"NC",
    "sg:tags":[
        "communication",
        "radiotelephone"
    ],
    "wof:name":"Spectrum Wireless",
    "wof:placetype":"venue"
},
  "geometry": {"coordinates":[-80.02358099999999,35.983686],"type":"Point"}
}