{
  "type": "Feature",
  "properties": {
    "addr:full":"717 Hale Ridge Rd Scaly Mountain NC 28741",
    "addr:housenumber":"717",
    "addr:postcode":"28741",
    "addr:street":"Hale Ridge Rd",
    "iso:country":"US",
    "sg:address":"717 Hale Ridge Rd",
    "sg:city":"Scaly Mountain",
    "sg:classifiers":[
        {
            "category":"Wholesale",
            "subcategory":"Scrap",
            "type":"Manufacturing & Wholesale Goods"
        }
    ],
    "sg:phone":"+1 828 526 0453",
    "sg:postcode":"28741",
    "sg:province":"NC",
    "sg:tags":[
        "material"
    ],
    "wof:name":"Scaly Mtn Convenience Center",
    "wof:placetype":"venue"
},
  "geometry": {"coordinates":[-83.304416,35.010899],"type":"Point"}
}