{
  "type": "Feature",
  "properties": {
    "iso:country":"US",
    "sg:address":"1601 S College Rd",
    "sg:city":"Wilmington",
    "sg:classifiers":[
        {
            "category":"Banks & Credit Unions",
            "subcategory":"Bank",
            "type":"Services"
        }
    ],
    "sg:phone":"+1 910 251 8560",
    "sg:postcode":"28403",
    "sg:province":"NC",
    "sg:tags":[
        "loan",
        "real estate"
    ],
    "wof:name":"Southern Fidelity Mortgage",
    "wof:placetype":"venue"
},
  "geometry": {"coordinates":[-77.887148,34.207857],"type":"Point"}
}