{
  "type": "Feature",
  "properties": {
    "addr:full":"257 Puddin Ridge Rd Moyock NC 27958",
    "addr:housenumber":"257",
    "addr:postcode":"27958",
    "addr:street":"Puddin Ridge Rd",
    "iso:country":"US",
    "sg:address":"257 Puddin Ridge Rd",
    "sg:city":"Moyock",
    "sg:classifiers":[
        {
            "category":"Building & Trades",
            "subcategory":"Plumbing",
            "type":"Services"
        }
    ],
    "sg:phone":"+1 252 435 6545",
    "sg:postcode":"27958",
    "sg:province":"NC",
    "sg:tags":[
        "conditioning",
        "air",
        "system",
        "contractor"
    ],
    "wof:name":"J P Aubee",
    "wof:placetype":"venue"
},
  "geometry": {"coordinates":[-76.18244799999999,36.514855],"type":"Point"}
}