{
  "type": "Feature",
  "properties": {
    "addr:full":"5511 Westerborne Dr Greensboro NC 27407",
    "addr:housenumber":"5511",
    "addr:postcode":"27407",
    "addr:street":"Westerborne Dr",
    "iso:country":"US",
    "sg:address":"5511 Westerborne Dr",
    "sg:city":"Greensboro",
    "sg:classifiers":[
        {
            "category":"Government",
            "subcategory":"Office",
            "type":"Public Place"
        }
    ],
    "sg:phone":"+1 336 323 0532",
    "sg:postcode":"27407",
    "sg:province":"NC",
    "sg:tags":[
        "grain",
        "inspection"
    ],
    "wof:name":"Grain Inspection",
    "wof:placetype":"venue"
},
  "geometry": {"coordinates":[-79.905841,36.013632],"type":"Point"}
}