{
  "type": "Feature",
  "properties": {
    "addr:full":"4008 S College Rd Wilmington NC 28412",
    "addr:housenumber":"4008",
    "addr:postcode":"28412",
    "addr:street":"S College Rd",
    "iso:country":"US",
    "sg:address":"4008 S College Rd",
    "sg:city":"Wilmington",
    "sg:classifiers":[
        {
            "category":"Education",
            "subcategory":"School",
            "type":"Public Place"
        }
    ],
    "sg:phone":"+1 910 395 9393",
    "sg:postcode":"28412",
    "sg:province":"NC",
    "wof:name":"Wilmington Montessori School",
    "wof:placetype":"venue"
},
  "geometry": {"coordinates":[-77.8916,34.169513],"type":"Point"}
}