{
  "type": "Feature",
  "properties": {
    "iso:country":"US",
    "sg:address":"124 Queens Dr",
    "sg:city":"King",
    "sg:classifiers":[
        {
            "category":"Professional",
            "subcategory":"Management & Consulting",
            "type":"Services"
        }
    ],
    "sg:phone":"+1   ",
    "sg:postcode":"27021",
    "sg:province":"NC",
    "wof:name":"Prioatory Managment",
    "wof:placetype":"venue"
},
  "geometry": {"coordinates":[-80.367861,36.278406],"type":"Point"}
}