{
  "type": "Feature",
  "properties": {
    "addr:full":"4416 S Tryon St Charlotte NC 28217",
    "addr:housenumber":"4416",
    "addr:postcode":"28217",
    "addr:street":"S Tryon St",
    "iso:country":"US",
    "sg:address":"4416 S Tryon St",
    "sg:city":"Charlotte",
    "sg:classifiers":[
        {
            "category":"Travel",
            "subcategory":"Hotels & Motels",
            "type":"Entertainment"
        }
    ],
    "sg:phone":"+1 704 522 8810",
    "sg:postcode":"28217",
    "sg:province":"NC",
    "sg:website":"www.intownsuites.com",
    "wof:name":"In Town Suites Charlotte",
    "wof:placetype":"venue"
},
  "geometry": {"coordinates":[-80.88639999999999,35.184317],"type":"Point"}
}