{
  "type": "Feature",
  "properties": {
    "iso:country":"US",
    "sg:address":"350 Eastwood Dr",
    "sg:city":"Belmont",
    "sg:classifiers":[
        {
            "category":"Manufacturing",
            "subcategory":"Textiles",
            "type":"Manufacturing & Wholesale Goods"
        },
        {
            "category":"Manufacturing",
            "subcategory":"Chemicals & Compounds",
            "type":"Manufacturing & Wholesale Goods"
        }
    ],
    "sg:phone":"+1 704 829 6290",
    "sg:postcode":"28012",
    "sg:province":"NC",
    "sg:tags":[
        "mfg",
        "fiber",
        "plastic"
    ],
    "wof:name":"Syncot Plastics Inc",
    "wof:placetype":"venue"
},
  "geometry": {"coordinates":[-81.05686,35.235085],"type":"Point"}
}