{
  "type": "Feature",
  "properties": {
    "iso:country":"US",
    "sg:address":"41 Sawmill Rd",
    "sg:city":"Weaverville",
    "sg:classifiers":[
        {
            "category":"Wholesale",
            "subcategory":"Construction Materials",
            "type":"Manufacturing & Wholesale Goods"
        }
    ],
    "sg:phone":"+1 828 645 4086",
    "sg:postcode":"28787",
    "sg:province":"NC",
    "sg:tags":[
        "lumber"
    ],
    "wof:name":"C & M Sawmill",
    "wof:placetype":"venue"
},
  "geometry": {"coordinates":[-82.600345,35.74261],"type":"Point"}
}