{
  "type": "Feature",
  "properties": {
    "iso:country":"US",
    "sg:address":"923 Main St",
    "sg:city":"North Wilkesboro",
    "sg:classifiers":[
        {
            "category":"Professional",
            "subcategory":"Engineering",
            "type":"Services"
        }
    ],
    "sg:phone":"+1 336 667 4225",
    "sg:postcode":"28659",
    "sg:province":"NC",
    "sg:tags":[
        "engineer"
    ],
    "wof:name":"Page Interworks Pa",
    "wof:placetype":"venue"
},
  "geometry": {"coordinates":[-81.14666699999999,36.159283],"type":"Point"}
}