{
  "type": "Feature",
  "properties": {
    "addr:full":"2453 US Hwy 258 Kinston NC 28504",
    "addr:housenumber":"2453",
    "addr:postcode":"28504",
    "addr:street":"Us Hwy 258",
    "iso:country":"US",
    "sg:address":"2453 US Hwy 258",
    "sg:city":"Kinston",
    "sg:classifiers":[
        {
            "category":"Retail",
            "subcategory":"Car Wash",
            "type":"Services"
        }
    ],
    "sg:phone":"+1 252 527 6041",
    "sg:postcode":"28504",
    "sg:province":"NC",
    "sg:tags":[
        "polishing",
        "washing"
    ],
    "wof:name":"Brown's Car Cleaning",
    "wof:placetype":"venue"
},
  "geometry": {"coordinates":[-77.64725799999999,35.302868],"type":"Point"}
}