{
  "type": "Feature",
  "properties": {
    "addr:full":"111 Lamon St Fayetteville NC 28301",
    "addr:housenumber":"111",
    "addr:postcode":"28301",
    "addr:street":"Lamon St",
    "iso:country":"US",
    "sg:address":"111 Lamon St",
    "sg:city":"Fayetteville",
    "sg:classifiers":[
        {
            "category":"Health Services",
            "subcategory":"Clinic",
            "type":"Services"
        }
    ],
    "sg:phone":"+1 910 483 9626",
    "sg:postcode":"28301",
    "sg:province":"NC",
    "sg:tags":[
        "organization",
        "medical",
        "surgical"
    ],
    "wof:name":"Cape Fear Paramedicals",
    "wof:placetype":"venue"
},
  "geometry": {"coordinates":[-78.87474400000001,35.058782],"type":"Point"}
}