{
  "type": "Feature",
  "properties": {
    "addr:full":"300 Westwood Ave Charlotte NC 28203",
    "addr:housenumber":"300",
    "addr:postcode":"28203",
    "addr:street":"Westwood Ave",
    "iso:country":"US",
    "sg:address":"300 Westwood Ave",
    "sg:city":"Charlotte",
    "sg:classifiers":[
        {
            "category":"Professional",
            "type":"Services"
        }
    ],
    "sg:phone":"+1 704 497 6785",
    "sg:postcode":"28203",
    "sg:province":"NC",
    "wof:name":"Val Jones & Associate",
    "wof:placetype":"venue"
},
  "geometry": {"coordinates":[-80.860996,35.217905],"type":"Point"}
}