{
  "type": "Feature",
  "properties": {
    "addr:full":"418 Colvard St Jefferson NC 28640",
    "addr:housenumber":"418",
    "addr:postcode":"28640",
    "addr:street":"Colvard St",
    "iso:country":"US",
    "sg:address":"418 Colvard St",
    "sg:city":"Jefferson",
    "sg:classifiers":[
        {
            "category":"Building & Trades",
            "subcategory":"Plumbing",
            "type":"Services"
        }
    ],
    "sg:phone":"+1 336 246 7723",
    "sg:postcode":"28640",
    "sg:province":"NC",
    "sg:tags":[
        "plumbing",
        "contractor"
    ],
    "wof:name":"W R Blevins Plumbing Co Inc",
    "wof:placetype":"venue"
},
  "geometry": {"coordinates":[-81.477405,36.417944],"type":"Point"}
}