{
  "type": "Feature",
  "properties": {
    "addr:full":"211 S Cooper Dr Henderson NC 27536",
    "addr:housenumber":"211",
    "addr:postcode":"27536",
    "addr:street":"S Cooper Dr",
    "iso:country":"US",
    "sg:address":"211 S Cooper Dr",
    "sg:city":"Henderson",
    "sg:classifiers":[
        {
            "category":"Retail",
            "subcategory":"Car Wash",
            "type":"Services"
        }
    ],
    "sg:phone":"+1 252 738 0416",
    "sg:postcode":"27536",
    "sg:province":"NC",
    "sg:tags":[
        "polishing",
        "washing"
    ],
    "wof:name":"Title Wave Car Wash",
    "wof:placetype":"venue"
},
  "geometry": {"coordinates":[-78.437754,36.330526],"type":"Point"}
}