{
  "type": "Feature",
  "properties": {
    "iso:country":"US",
    "sg:address":"24 S Main St",
    "sg:city":"Marion",
    "sg:classifiers":[
        {
            "category":"Arts & Performance",
            "subcategory":"Theater",
            "type":"Entertainment"
        },
        {
            "category":"Cinema",
            "subcategory":"Movie Theater",
            "type":"Entertainment"
        }
    ],
    "sg:phone":"+1 828 659 7529",
    "sg:postcode":"28752",
    "sg:province":"NC",
    "sg:tags":[
        "motion",
        "picture"
    ],
    "wof:name":"Foothills Community Theatre",
    "wof:placetype":"venue"
},
  "geometry": {"coordinates":[-82.008948,35.683743],"type":"Point"}
}