{
  "type": "Feature",
  "properties": {
    "iso:country":"US",
    "sg:address":"11914 Elm Ln",
    "sg:city":"Charlotte",
    "sg:classifiers":[
        {
            "category":"Banks & Credit Unions",
            "subcategory":"Bank",
            "type":"Services"
        }
    ],
    "sg:phone":"+1 704 752 7874",
    "sg:postcode":"28277",
    "sg:province":"NC",
    "sg:tags":[
        "loan",
        "real estate"
    ],
    "wof:name":"Priority Home Funding",
    "wof:placetype":"venue"
},
  "geometry": {"coordinates":[-80.815381,35.048597],"type":"Point"}
}