{
  "type": "Feature",
  "properties": {
    "iso:country":"US",
    "sg:address":"5208 Grasshopper Rd",
    "sg:city":"Raleigh",
    "sg:classifiers":[
        {
            "category":"Shopping",
            "type":"Retail Goods"
        }
    ],
    "sg:phone":"+1 919 266 2324",
    "sg:postcode":"27610",
    "sg:province":"NC",
    "sg:tags":[
        "machine",
        "supply",
        "furniture"
    ],
    "wof:name":"Carolina Typewriter Company",
    "wof:placetype":"venue"
},
  "geometry": {"coordinates":[-78.489172,35.745201],"type":"Point"}
}