{
  "type": "Feature",
  "properties": {
    "iso:country":"US",
    "sg:address":"622 Dabney Dr",
    "sg:city":"Henderson",
    "sg:classifiers":[
        {
            "category":"Insurance",
            "subcategory":"Insurance Agent",
            "type":"Services"
        }
    ],
    "sg:phone":"+1 252 438 3334",
    "sg:postcode":"27536",
    "sg:province":"NC",
    "sg:tags":[
        "life",
        "carrier"
    ],
    "wof:name":"Tate Jmmy D Assc-Frst Prtctive",
    "wof:placetype":"venue"
},
  "geometry": {"coordinates":[-78.42273900000001,36.325569],"type":"Point"}
}