{
  "type": "Feature",
  "properties": {
    "addr:full":"429 N Main St Hendersonville NC 28792",
    "addr:housenumber":"429",
    "addr:postcode":"28792",
    "addr:street":"N Main St",
    "iso:country":"US",
    "sg:address":"429 N Main St",
    "sg:city":"Hendersonville",
    "sg:classifiers":[
        {
            "category":"Shopping",
            "subcategory":"Jewelry",
            "type":"Retail Goods"
        }
    ],
    "sg:phone":"+1 828 692 3615",
    "sg:postcode":"28792",
    "sg:province":"NC",
    "sg:tags":[
        "jeweler"
    ],
    "wof:name":"Shelley's Jewelry",
    "wof:placetype":"venue"
},
  "geometry": {"coordinates":[-82.46047,35.317452],"type":"Point"}
}