{
  "type": "Feature",
  "properties": {
    "iso:country":"US",
    "sg:address":"11130 N Main St",
    "sg:city":"Archdale",
    "sg:classifiers":[
        {
            "category":"Manufacturing",
            "subcategory":"Textiles",
            "type":"Manufacturing & Wholesale Goods"
        }
    ],
    "sg:phone":"+1 336 431 9662",
    "sg:postcode":"27263",
    "sg:province":"NC",
    "sg:tags":[
        "fabric",
        "drapery"
    ],
    "wof:name":"J D Stanley & Co Inc",
    "wof:placetype":"venue"
},
  "geometry": {"coordinates":[-79.97068299999999,35.912416],"type":"Point"}
}