{
  "type": "Feature",
  "properties": {
    "addr:full":"4514 Sunset Rd Charlotte NC 28216",
    "addr:housenumber":"4514",
    "addr:postcode":"28216",
    "addr:street":"Sunset Rd",
    "iso:country":"US",
    "sg:address":"4514 Sunset Rd",
    "sg:city":"Charlotte",
    "sg:classifiers":[
        {
            "category":"Home & Garden",
            "subcategory":"Building Materials",
            "type":"Retail Goods"
        }
    ],
    "sg:phone":"+1 704 545 5150",
    "sg:postcode":"28216",
    "sg:province":"NC",
    "sg:tags":[
        "door"
    ],
    "wof:name":"Lloyds Garage Doors",
    "wof:placetype":"venue"
},
  "geometry": {"coordinates":[-80.85174000000001,35.306713],"type":"Point"}
}