{
  "type": "Feature",
  "properties": {
    "addr:full":"2110 High Point Rd Greensboro NC 27403",
    "addr:housenumber":"2110",
    "addr:postcode":"27403",
    "addr:street":"High Point Rd",
    "iso:country":"US",
    "sg:address":"2110 High Point Rd",
    "sg:city":"Greensboro",
    "sg:classifiers":[
        {
            "category":"Manufacturing",
            "subcategory":"Chemicals & Compounds",
            "type":"Manufacturing & Wholesale Goods"
        }
    ],
    "sg:phone":"+1 336 292 1781",
    "sg:postcode":"27403",
    "sg:province":"NC",
    "sg:tags":[
        "preparation",
        "pharmaceutical"
    ],
    "sg:website":"www.morflex.com",
    "wof:name":"Morflex Inc",
    "wof:placetype":"venue"
},
  "geometry": {"coordinates":[-79.82715899999999,36.059871],"type":"Point"}
}