{
  "type": "Feature",
  "properties": {
    "iso:country":"US",
    "sg:address":"14124 Carriage Lake Dr",
    "sg:city":"Charlotte",
    "sg:classifiers":[
        {
            "category":"Retail",
            "subcategory":"Repair Shop",
            "type":"Services"
        }
    ],
    "sg:phone":"+1   ",
    "sg:postcode":"28273",
    "sg:province":"NC",
    "wof:name":"Davis Lock & Key Inc",
    "wof:placetype":"venue"
},
  "geometry": {"coordinates":[-80.97108799999999,35.094576],"type":"Point"}
}