{
  "type": "Feature",
  "properties": {
    "addr:full":"13515 Steele Creek Rd Charlotte NC 28273",
    "addr:housenumber":"13515",
    "addr:postcode":"28273",
    "addr:street":"Steele Creek Rd",
    "iso:country":"US",
    "sg:address":"13515 Steele Creek Rd",
    "sg:city":"Charlotte",
    "sg:classifiers":[
        {
            "category":"Building & Trades",
            "subcategory":"Electrical",
            "type":"Services"
        }
    ],
    "sg:phone":"+1 704 583 0305",
    "sg:postcode":"28273",
    "sg:province":"NC",
    "sg:tags":[
        "electrical",
        "contractor"
    ],
    "wof:name":"All Season Electric Charlotte",
    "wof:placetype":"venue"
},
  "geometry": {"coordinates":[-80.987604,35.110242],"type":"Point"}
}