{
  "type": "Feature",
  "properties": {
    "addr:full":"507 E Green St Robersonville NC 27871",
    "addr:housenumber":"507",
    "addr:postcode":"27871",
    "addr:street":"E Green St",
    "iso:country":"US",
    "sg:address":"507 E Green St",
    "sg:city":"Robersonville",
    "sg:classifiers":[
        {
            "category":"Personal",
            "subcategory":"Beauty Salon",
            "type":"Services"
        }
    ],
    "sg:phone":"+1 252 795 4986",
    "sg:postcode":"27871",
    "sg:province":"NC",
    "wof:name":"New Image",
    "wof:placetype":"venue"
},
  "geometry": {"coordinates":[-77.24614699999999,35.828865],"type":"Point"}
}