{
  "type": "Feature",
  "properties": {
    "iso:country":"US",
    "sg:address":"3817 Cold Harbour Dr",
    "sg:city":"Raleigh",
    "sg:classifiers":[
        {
            "category":"Restaurant",
            "type":"Food & Drink"
        }
    ],
    "sg:phone":"+1 919 779 5813",
    "sg:postcode":"27610",
    "sg:province":"NC",
    "sg:tags":[
        "eating"
    ],
    "wof:name":"Angels Mobile Cafe",
    "wof:placetype":"venue"
},
  "geometry": {"coordinates":[-78.529285,35.726254],"type":"Point"}
}