{
  "type": "Feature",
  "properties": {
    "addr:full":"494 John Garner Rd Sanford NC 27332",
    "addr:housenumber":"494",
    "addr:postcode":"27332",
    "addr:street":"John Garner Rd",
    "iso:country":"US",
    "sg:address":"494 John Garner Rd",
    "sg:city":"Sanford",
    "sg:classifiers":[
        {
            "category":"Manufacturing",
            "subcategory":"Tools & Machinery",
            "type":"Manufacturing & Wholesale Goods"
        }
    ],
    "sg:phone":"+1 919 499 5661",
    "sg:postcode":"27332",
    "sg:province":"NC",
    "sg:tags":[
        "machine",
        "shop",
        "industrial",
        "mfg"
    ],
    "wof:name":"AAA Machine Shop",
    "wof:placetype":"venue"
},
  "geometry": {"coordinates":[-79.141018,35.381165],"type":"Point"}
}