{
  "type": "Feature",
  "properties": {
    "iso:country":"US",
    "sg:address":"4908 US Hwy 1",
    "sg:city":"New Hill",
    "sg:classifiers":[
        {
            "category":"Organizations",
            "subcategory":"Religious Organization",
            "type":"Services"
        }
    ],
    "sg:phone":"+1 919 362 8090",
    "sg:postcode":"27562",
    "sg:province":"NC",
    "sg:tags":[
        "church"
    ],
    "wof:name":"Cedar Rock Missionary Baptist",
    "wof:placetype":"venue"
},
  "geometry": {"coordinates":[-79.03443799999999,35.63979],"type":"Point"}
}