{
  "type": "Feature",
  "properties": {
    "iso:country":"US",
    "sg:address":"6916 Neuhoff Ln",
    "sg:city":"Charlotte",
    "sg:classifiers":[
        {
            "category":"Professional",
            "subcategory":"Computer Services",
            "type":"Services"
        }
    ],
    "sg:phone":"+1   ",
    "sg:postcode":"28269",
    "sg:province":"NC",
    "sg:tags":[
        "related"
    ],
    "wof:name":"PVL Consulting",
    "wof:placetype":"venue"
},
  "geometry": {"coordinates":[-80.802046,35.341868],"type":"Point"}
}