{
  "type": "Feature",
  "properties": {
    "iso:country":"US",
    "sg:address":"312 Canterbury Rd NW",
    "sg:city":"Wilson",
    "sg:classifiers":[
        {
            "category":"Wholesale",
            "subcategory":"Construction Materials",
            "type":"Manufacturing & Wholesale Goods"
        }
    ],
    "sg:phone":"+1 252 237 3033",
    "sg:postcode":"27896",
    "sg:province":"NC",
    "sg:tags":[
        "lumber",
        "broker"
    ],
    "wof:name":"J R Stone Lumber Co Inc",
    "wof:placetype":"venue"
},
  "geometry": {"coordinates":[-77.93643400000001,35.752507],"type":"Point"}
}