{
  "type": "Feature",
  "properties": {
    "addr:full":"1201 Washington St Roanoke Rapids NC 27870",
    "addr:housenumber":"1201",
    "addr:postcode":"27870",
    "addr:street":"Washington St",
    "iso:country":"US",
    "sg:address":"1201 Washington St",
    "sg:city":"Roanoke Rapids",
    "sg:classifiers":[
        {
            "category":"Building & Trades",
            "subcategory":"Landscaping Services",
            "type":"Services"
        }
    ],
    "sg:phone":"+1 252 535 3931",
    "sg:postcode":"27870",
    "sg:province":"NC",
    "wof:name":"Adams Lawn & Landscape",
    "wof:placetype":"venue"
},
  "geometry": {"coordinates":[-77.656537,36.451958],"type":"Point"}
}