{
  "type": "Feature",
  "properties": {
    "iso:country":"US",
    "sg:address":"708 Silverleaf Pl",
    "sg:city":"Raleigh",
    "sg:classifiers":[
        {
            "category":"Real Estate",
            "subcategory":"Real Estate Agent",
            "type":"Services"
        }
    ],
    "sg:phone":"+1 919 784 9191",
    "sg:postcode":"27609",
    "sg:province":"NC",
    "sg:tags":[
        "consultant"
    ],
    "wof:name":"Legacy Real Estate Group",
    "wof:placetype":"venue"
},
  "geometry": {"coordinates":[-78.625221,35.85841],"type":"Point"}
}