{
  "type": "Feature",
  "properties": {
    "iso:country":"US",
    "sg:address":"1109 Yadkinville Rd",
    "sg:city":"Mocksville",
    "sg:classifiers":[
        {
            "category":"Insurance",
            "subcategory":"Hazard Insurance",
            "type":"Services"
        },
        {
            "category":"Insurance",
            "subcategory":"Insurance Agent",
            "type":"Services"
        },
        {
            "category":"Insurance",
            "subcategory":"Life Insurance",
            "type":"Services"
        },
        {
            "category":"Insurance",
            "subcategory":"Title Insurance",
            "type":"Services"
        }
    ],
    "sg:phone":"+1 336 751 6131",
    "sg:postcode":"27028",
    "sg:province":"NC",
    "sg:tags":[
        "auto",
        "homeowner"
    ],
    "sg:website":"http://www.nationwide.com/agent/Mocksville-NORTH-CAROLINA-insurance-agent/hilleragency/office.html",
    "wof:name":"Keith W Hiller - Nationwide Insurance",
    "wof:placetype":"venue"
},
  "geometry": {"coordinates":[-80.579982,35.911453],"type":"Point"}
}