{
  "type": "Feature",
  "properties": {
    "iso:country":"US",
    "sg:address":"322 Mulberry St SW",
    "sg:city":"Lenoir",
    "sg:classifiers":[
        {
            "category":"Health Services",
            "subcategory":"Doctor",
            "type":"Services"
        }
    ],
    "sg:phone":"+1 828 757 6400",
    "sg:postcode":"28645",
    "sg:province":"NC",
    "sg:tags":[
        "physician",
        "surgeon"
    ],
    "wof:name":"Caldwell Internal Medicine",
    "wof:placetype":"venue"
},
  "geometry": {"coordinates":[-81.53652700000001,35.91094],"type":"Point"}
}