{
  "type": "Feature",
  "properties": {
    "addr:full":"142 Fairview Dr Emerald Isle NC 28594",
    "addr:housenumber":"142",
    "addr:postcode":"28594",
    "addr:street":"Fairview Dr",
    "iso:country":"US",
    "sg:address":"142 Fairview Dr",
    "sg:city":"Emerald Isle",
    "sg:classifiers":[
        {
            "category":"Health Services",
            "subcategory":"Health Practitioner",
            "type":"Services"
        }
    ],
    "sg:phone":"+1 252 354 6655",
    "sg:postcode":"28594",
    "sg:province":"NC",
    "sg:tags":[
        "hypnotist"
    ],
    "wof:name":"New Lease Hypnotherapy",
    "wof:placetype":"venue"
},
  "geometry": {"coordinates":[-77.03582,34.664659],"type":"Point"}
}