{
  "type": "Feature",
  "properties": {
    "addr:full":"404 W Main St Woodland NC 27897",
    "addr:housenumber":"404",
    "addr:postcode":"27897",
    "addr:street":"W Main St",
    "iso:country":"US",
    "sg:address":"404 W Main St",
    "sg:city":"Woodland",
    "sg:classifiers":[
        {
            "category":"Restaurant",
            "type":"Food & Drink"
        }
    ],
    "sg:phone":"+1 252 587 3010",
    "sg:postcode":"27897",
    "sg:province":"NC",
    "wof:name":"Sub Doctor",
    "wof:placetype":"venue"
},
  "geometry": {"coordinates":[-77.216938,36.328618],"type":"Point"}
}