{
  "type": "Feature",
  "properties": {
    "iso:country":"US",
    "sg:address":"600 Longfellow St",
    "sg:city":"Fuquay Varina",
    "sg:classifiers":[
        {
            "category":"Organizations",
            "subcategory":"Religious Organization",
            "type":"Services"
        }
    ],
    "sg:phone":"+1   ",
    "sg:postcode":"27526",
    "sg:province":"NC",
    "wof:name":"Church Of God For All People",
    "wof:placetype":"venue"
},
  "geometry": {"coordinates":[-78.809175,35.591808],"type":"Point"}
}