{
  "type": "Feature",
  "properties": {
    "iso:country":"US",
    "sg:address":"360 Ashville Ave",
    "sg:city":"Cary",
    "sg:classifiers":[
        {
            "category":"Retail",
            "subcategory":"Auto Repair",
            "type":"Services"
        }
    ],
    "sg:phone":"+1   ",
    "sg:postcode":"27518",
    "sg:province":"NC",
    "sg:tags":[
        "automotive"
    ],
    "wof:name":"Ashley Village",
    "wof:placetype":"venue"
},
  "geometry": {"coordinates":[-78.784238,35.739814],"type":"Point"}
}