{
  "type": "Feature",
  "properties": {
    "iso:country":"US",
    "sg:address":"1206 Twisted Hickory Rd",
    "sg:city":"Elizabethtown",
    "sg:classifiers":[
        {
            "category":"Health Services",
            "subcategory":"Nursing And Care Facility",
            "type":"Services"
        },
        {
            "category":"Health Services",
            "subcategory":"Clinic",
            "type":"Services"
        }
    ],
    "sg:phone":"+1 910 862 2484",
    "sg:postcode":"28337",
    "sg:province":"NC",
    "sg:tags":[
        "home",
        "intermediate"
    ],
    "wof:name":"B J Professional Svc",
    "wof:placetype":"venue"
},
  "geometry": {"coordinates":[-78.71950699999999,34.641639],"type":"Point"}
}