{
  "type": "Feature",
  "properties": {
    "addr:full":"930 High House Rd Cary NC 27513",
    "addr:housenumber":"930",
    "addr:postcode":"27513",
    "addr:street":"High House Rd",
    "iso:country":"US",
    "sg:address":"930 High House Rd",
    "sg:city":"Cary",
    "sg:classifiers":[
        {
            "category":"Food & Beverages",
            "subcategory":"Groceries & Convenience Stores",
            "type":"Retail Goods"
        }
    ],
    "sg:phone":"+1 919 467 4441",
    "sg:postcode":"27513",
    "sg:province":"NC",
    "sg:tags":[
        "grocer"
    ],
    "sg:website":"www.lowesfoods.com",
    "wof:name":"Lowe's Foods",
    "wof:placetype":"venue"
},
  "geometry": {"coordinates":[-78.825897,35.7869],"type":"Point"}
}