{
  "type": "Feature",
  "properties": {
    "iso:country":"US",
    "sg:address":"9009 Albemarle Rd",
    "sg:city":"Charlotte",
    "sg:classifiers":[
        {
            "category":"Building & Trades",
            "subcategory":"Construction",
            "type":"Services"
        }
    ],
    "sg:phone":"+1 704 537 0996",
    "sg:postcode":"28227",
    "sg:province":"NC",
    "sg:tags":[
        "residential"
    ],
    "wof:name":"Abacus Appraisals",
    "wof:placetype":"venue"
},
  "geometry": {"coordinates":[-80.69479200000001,35.211206],"type":"Point"}
}