{
  "type": "Feature",
  "properties": {
    "iso:country":"US",
    "sg:address":"1504 W Cone Blvd",
    "sg:city":"Greensboro",
    "sg:classifiers":[
        {
            "category":"Professional",
            "subcategory":"Business Services",
            "type":"Services"
        }
    ],
    "sg:phone":"+1   ",
    "sg:postcode":"27408",
    "sg:province":"NC",
    "wof:name":"Ashley & Associates",
    "wof:placetype":"venue"
},
  "geometry": {"coordinates":[-79.80750999999999,36.108305],"type":"Point"}
}