{
  "type": "Feature",
  "properties": {
    "addr:full":"1105 Walnut St Cary NC 27511",
    "addr:housenumber":"1105",
    "addr:postcode":"27511",
    "addr:street":"Walnut St",
    "iso:country":"US",
    "sg:address":"1105 Walnut St",
    "sg:city":"Cary",
    "sg:classifiers":[
        {
            "category":"Retail",
            "subcategory":"Portrait Studio",
            "type":"Services"
        }
    ],
    "sg:phone":"+1 919 467 3773",
    "sg:postcode":"27511",
    "sg:province":"NC",
    "sg:tags":[
        "photography",
        "store"
    ],
    "sg:website":"www.kerrdrug.com",
    "wof:name":"Kerr Drug",
    "wof:placetype":"venue"
},
  "geometry": {"coordinates":[-78.76282399999999,35.771465],"type":"Point"}
}