{
  "type": "Feature",
  "properties": {
    "addr:full":"2830 Tilghman Rd N Wilson NC 27896",
    "addr:housenumber":"2830",
    "addr:postcode":"27896",
    "addr:street":"Tilghman Rd N",
    "iso:country":"US",
    "sg:address":"2830 Tilghman Rd N",
    "sg:city":"Wilson",
    "sg:classifiers":[
        {
            "category":"Building & Trades",
            "subcategory":"Pest Control",
            "type":"Services"
        }
    ],
    "sg:phone":"+1 252 291 0156",
    "sg:postcode":"27896",
    "sg:province":"NC",
    "wof:name":"De-Bug-Em Exterminating Co",
    "wof:placetype":"venue"
},
  "geometry": {"coordinates":[-77.91815200000001,35.772093],"type":"Point"}
}