{
  "type": "Feature",
  "properties": {
    "iso:country":"US",
    "sg:address":"604 S Scales St",
    "sg:city":"Reidsville",
    "sg:classifiers":[
        {
            "category":"Retail",
            "subcategory":"Auto Repair",
            "type":"Services"
        }
    ],
    "sg:phone":"+1 336 342 4909",
    "sg:postcode":"27320",
    "sg:province":"NC",
    "sg:tags":[
        "repairing",
        "automobile",
        "automotive"
    ],
    "wof:name":"Toney's Automotive Repair",
    "wof:placetype":"venue"
},
  "geometry": {"coordinates":[-79.66467,36.354691],"type":"Point"}
}