{
  "type": "Feature",
  "properties": {
    "addr:full":"2809 Asbury Ter Greensboro NC 27408",
    "addr:housenumber":"2809",
    "addr:postcode":"27408",
    "addr:street":"Asbury Ter",
    "iso:country":"US",
    "sg:address":"2809 Asbury Ter",
    "sg:city":"Greensboro",
    "sg:classifiers":[
        {
            "category":"Farming",
            "subcategory":"Farm",
            "type":"Manufacturing & Wholesale Goods"
        }
    ],
    "sg:phone":"+1 336 288 9780",
    "sg:postcode":"27408",
    "sg:province":"NC",
    "sg:tags":[
        "crop",
        "general"
    ],
    "wof:name":"Alice Gaines",
    "wof:placetype":"venue"
},
  "geometry": {"coordinates":[-79.808688,36.114492],"type":"Point"}
}