{
  "type": "Feature",
  "properties": {
    "addr:full":"6700 Fishers Farm Ln Charlotte NC 28277",
    "addr:housenumber":"6700",
    "addr:postcode":"28277",
    "addr:street":"Fishers Farm Ln",
    "iso:country":"US",
    "sg:address":"6700 Fishers Farm Ln",
    "sg:city":"Charlotte",
    "sg:classifiers":[
        {
            "category":"Shopping",
            "subcategory":"Bicycles & Sporting Goods",
            "type":"Retail Goods"
        }
    ],
    "sg:phone":"+1 704 341 7768",
    "sg:postcode":"28277",
    "sg:province":"NC",
    "sg:tags":[
        "equipment",
        "playground"
    ],
    "wof:name":"Contract Connection Inc",
    "wof:placetype":"venue"
},
  "geometry": {"coordinates":[-80.833038,35.081914],"type":"Point"}
}