{
  "type": "Feature",
  "properties": {
    "iso:country":"US",
    "sg:address":"1105 Walnut St",
    "sg:city":"Cary",
    "sg:classifiers":[
        {
            "category":"Shopping",
            "subcategory":"Clothing, Apparel, & Fashions",
            "type":"Retail Goods"
        }
    ],
    "sg:phone":"+1 919 468 9171",
    "sg:postcode":"27511",
    "sg:province":"NC",
    "sg:tags":[
        "accessory",
        "clothing",
        "women's"
    ],
    "wof:name":"Talbot's",
    "wof:placetype":"venue"
},
  "geometry": {"coordinates":[-78.762901,35.771301],"type":"Point"}
}