{
  "type": "Feature",
  "properties": {
    "addr:full":"1001 Riverside Dr Asheville NC 28804",
    "addr:housenumber":"1001",
    "addr:postcode":"28804",
    "addr:street":"Riverside Dr",
    "iso:country":"US",
    "sg:address":"1001 Riverside Dr",
    "sg:city":"Asheville",
    "sg:classifiers":[
        {
            "category":"Building & Trades",
            "subcategory":"Equipment Rental",
            "type":"Services"
        }
    ],
    "sg:phone":"+1 828 254 4779",
    "sg:postcode":"28804",
    "sg:province":"NC",
    "sg:tags":[
        "crane"
    ],
    "wof:name":"Rogers & Son Welding Co",
    "wof:placetype":"venue"
},
  "geometry": {"coordinates":[-82.58058699999999,35.625724],"type":"Point"}
}