{
  "type": "Feature",
  "properties": {
    "addr:full":"413 Thornburg Dr SE Conover NC 28613",
    "addr:housenumber":"413",
    "addr:postcode":"28613",
    "addr:street":"Thornburg Dr Se",
    "iso:country":"US",
    "sg:address":"413 Thornburg Dr SE",
    "sg:city":"Conover",
    "sg:classifiers":[
        {
            "category":"Wholesale",
            "subcategory":"Stationery",
            "type":"Manufacturing & Wholesale Goods"
        }
    ],
    "sg:phone":"+1 828 466 1462",
    "sg:postcode":"28613",
    "sg:province":"NC",
    "sg:tags":[
        "paper"
    ],
    "wof:name":"Creative Pac",
    "wof:placetype":"venue"
},
  "geometry": {"coordinates":[-81.20128099999999,35.692785],"type":"Point"}
}