{
  "type": "Feature",
  "properties": {
    "iso:country":"US",
    "sg:address":"3818 Edwards Hill Church Rd",
    "sg:city":"Siler City",
    "sg:classifiers":[
        {
            "category":"Farming",
            "subcategory":"Farm & Veterinary Services",
            "type":"Manufacturing & Wholesale Goods"
        }
    ],
    "sg:phone":"+1 919 837 2921",
    "sg:postcode":"27344",
    "sg:province":"NC",
    "sg:tags":[
        "livestock"
    ],
    "wof:name":"Vivian Phillips",
    "wof:placetype":"venue"
},
  "geometry": {"coordinates":[-79.43738,35.601481],"type":"Point"}
}