{
  "type": "Feature",
  "properties": {
    "iso:country":"US",
    "sg:address":"5304 Crocus Ct",
    "sg:city":"Holly Springs",
    "sg:classifiers":[
        {
            "category":"Building & Trades",
            "subcategory":"Construction",
            "type":"Services"
        }
    ],
    "sg:phone":"+1 919 363 6868",
    "sg:postcode":"27540",
    "sg:province":"NC",
    "sg:tags":[
        "contractor"
    ],
    "wof:name":"Oakhill Drywall",
    "wof:placetype":"venue"
},
  "geometry": {"coordinates":[-78.79016799999999,35.652639],"type":"Point"}
}