{
  "type": "Feature",
  "properties": {
    "addr:full":"1207 Skyway Dr Monroe NC 28110",
    "addr:housenumber":"1207",
    "addr:postcode":"28110",
    "addr:street":"Skyway Dr",
    "iso:country":"US",
    "sg:address":"1207 Skyway Dr",
    "sg:city":"Monroe",
    "sg:classifiers":[
        {
            "category":"Health Services",
            "subcategory":"Optometrist",
            "type":"Services"
        }
    ],
    "sg:phone":"+1 704 296 0818",
    "sg:postcode":"28110",
    "sg:province":"NC",
    "wof:name":"Family Eye Care",
    "wof:placetype":"venue"
},
  "geometry": {"coordinates":[-80.548959,34.994034],"type":"Point"}
}