{
  "type": "Feature",
  "properties": {
    "addr:full":"3366 US Hwy 264 Alt Wilson NC 27893",
    "addr:housenumber":"3366",
    "addr:postcode":"27893",
    "addr:street":"Us Hwy 264",
    "iso:country":"US",
    "sg:address":"3366 US Hwy 264 Alt",
    "sg:city":"Wilson",
    "sg:classifiers":[
        {
            "category":"Social Services",
            "subcategory":"Child Care",
            "type":"Services"
        }
    ],
    "sg:phone":"+1 252 243 7269",
    "sg:postcode":"27893",
    "sg:province":"NC",
    "sg:tags":[
        "day"
    ],
    "wof:name":"Fresh Start Day Care Home",
    "wof:placetype":"venue"
},
  "geometry": {"coordinates":[-77.870649,35.694494],"type":"Point"}
}