{
  "type": "Feature",
  "properties": {
    "iso:country":"US",
    "sg:address":"9402 State Hwy 87 N",
    "sg:city":"Pittsboro",
    "sg:classifiers":[
        {
            "category":"Home & Garden",
            "subcategory":"Building Materials",
            "type":"Retail Goods"
        }
    ],
    "sg:phone":"+1 919 542 1405",
    "sg:postcode":"27312",
    "sg:province":"NC",
    "wof:name":"Potts Paint & Paper",
    "wof:placetype":"venue"
},
  "geometry": {"coordinates":[-79.26098500000001,35.831534],"type":"Point"}
}