{
  "type": "Feature",
  "properties": {
    "addr:full":"500 Robin Lake Dr Dudley NC 28333",
    "addr:housenumber":"500",
    "addr:postcode":"28333",
    "addr:street":"Robin Lake Dr",
    "iso:country":"US",
    "sg:address":"500 Robin Lake Dr",
    "sg:city":"Dudley",
    "sg:classifiers":[
        {
            "category":"Building & Trades",
            "subcategory":"Plumbing",
            "type":"Services"
        }
    ],
    "sg:phone":"+1 919 735 3337",
    "sg:postcode":"28333",
    "sg:province":"NC",
    "sg:tags":[
        "plumbing",
        "contractor"
    ],
    "wof:name":"Nelson Frank Plumbing",
    "wof:placetype":"venue"
},
  "geometry": {"coordinates":[-78.011574,35.285178],"type":"Point"}
}