{
  "type": "Feature",
  "properties": {
    "iso:country":"US",
    "sg:address":"6762 Shallowford Rd",
    "sg:city":"Lewisville",
    "sg:classifiers":[
        {
            "category":"Wholesale",
            "subcategory":"Machinery & Supplies",
            "type":"Manufacturing & Wholesale Goods"
        }
    ],
    "sg:phone":"+1 336 946 0715",
    "sg:postcode":"27023",
    "sg:province":"NC",
    "sg:tags":[
        "vacuum",
        "system",
        "cleaning"
    ],
    "wof:name":"Rainbow Vacuums Healthy Homes",
    "wof:placetype":"venue"
},
  "geometry": {"coordinates":[-80.429299,36.096518],"type":"Point"}
}