{
  "type": "Feature",
  "properties": {
    "addr:full":"815 West Blvd Charlotte NC 28203",
    "addr:housenumber":"815",
    "addr:postcode":"28203",
    "addr:street":"West Blvd",
    "iso:country":"US",
    "sg:address":"815 West Blvd",
    "sg:city":"Charlotte",
    "sg:classifiers":[
        {
            "category":"Personal",
            "subcategory":"Beauty Salon",
            "type":"Services"
        }
    ],
    "sg:phone":"+1 704 343 0550",
    "sg:postcode":"28203",
    "sg:province":"NC",
    "wof:name":"Changes Hair Studio",
    "wof:placetype":"venue"
},
  "geometry": {"coordinates":[-80.870653,35.217328],"type":"Point"}
}