{
  "type": "Feature",
  "properties": {
    "addr:full":"18 Covil Ave Wilmington NC 28403",
    "addr:housenumber":"18",
    "addr:postcode":"28403",
    "addr:street":"Covil Ave",
    "iso:country":"US",
    "sg:address":"18 Covil Ave",
    "sg:city":"Wilmington",
    "sg:classifiers":[
        {
            "category":"Home & Garden",
            "subcategory":"Building Materials",
            "type":"Retail Goods"
        }
    ],
    "sg:phone":"+1 910 392 9888",
    "sg:postcode":"28403",
    "sg:province":"NC",
    "sg:tags":[
        "lumber"
    ],
    "wof:name":"Anchor Hardwoods-The Carolinas",
    "wof:placetype":"venue"
},
  "geometry": {"coordinates":[-77.904493,34.236952],"type":"Point"}
}