{
  "type": "Feature",
  "properties": {
    "iso:country":"US",
    "sg:address":"5907 Triangle Dr",
    "sg:city":"Raleigh",
    "sg:classifiers":[
        {
            "category":"Wholesale",
            "subcategory":"Construction Materials",
            "type":"Manufacturing & Wholesale Goods"
        }
    ],
    "sg:phone":"+1 919 787 9480",
    "sg:postcode":"27617",
    "sg:province":"NC",
    "sg:tags":[
        "marble"
    ],
    "wof:name":"Corestone LLC",
    "wof:placetype":"venue"
},
  "geometry": {"coordinates":[-78.746478,35.893976],"type":"Point"}
}