{
  "type": "Feature",
  "properties": {
    "iso:country":"US",
    "sg:address":"4006 Arendell St",
    "sg:city":"Morehead City",
    "sg:classifiers":[
        {
            "category":"Restaurant",
            "type":"Food & Drink"
        }
    ],
    "sg:phone":"+1 252 726 2769",
    "sg:postcode":"28557",
    "sg:province":"NC",
    "wof:name":"Wendy's",
    "wof:placetype":"venue"
},
  "geometry": {"coordinates":[-76.764213,34.725286],"type":"Point"}
}