{
  "type": "Feature",
  "properties": {
    "iso:country":"US",
    "sg:address":"338 Duffy Field Rd",
    "sg:city":"Richlands",
    "sg:classifiers":[
        {
            "category":"Banks & Credit Unions",
            "subcategory":"Financial Services",
            "type":"Services"
        },
        {
            "category":"Building & Trades",
            "subcategory":"Construction",
            "type":"Services"
        }
    ],
    "sg:phone":"+1 910 324 7090",
    "sg:postcode":"28574",
    "sg:province":"NC",
    "sg:tags":[
        "investor",
        "contractor"
    ],
    "wof:name":"Gold Coast Investment Inc",
    "wof:placetype":"venue"
},
  "geometry": {"coordinates":[-77.555662,34.838892],"type":"Point"}
}