{
  "type": "Feature",
  "properties": {
    "iso:country":"US",
    "sg:address":"605 W Noble St",
    "sg:city":"Selma",
    "sg:classifiers":[
        {
            "category":"Social Services",
            "subcategory":"Child Care",
            "type":"Services"
        }
    ],
    "sg:phone":"+1 919 965 8631",
    "sg:postcode":"27576",
    "sg:province":"NC",
    "sg:tags":[
        "kindergarten",
        "academic",
        "school"
    ],
    "wof:name":"Johnston Lee Headstart",
    "wof:placetype":"venue"
},
  "geometry": {"coordinates":[-78.29109800000001,35.53705],"type":"Point"}
}