{
  "type": "Feature",
  "properties": {
    "addr:full":"435 Edinburgh Dr Fayetteville NC 28303",
    "addr:housenumber":"435",
    "addr:postcode":"28303",
    "addr:street":"Edinburgh Dr",
    "iso:country":"US",
    "sg:address":"435 Edinburgh Dr",
    "sg:city":"Fayetteville",
    "sg:classifiers":[
        {
            "category":"Real Estate",
            "subcategory":"Real Estate Agent",
            "type":"Services"
        }
    ],
    "sg:phone":"+1 910 867 4790",
    "sg:postcode":"28303",
    "sg:province":"NC",
    "wof:name":"Southern Exposure Property MGT",
    "wof:placetype":"venue"
},
  "geometry": {"coordinates":[-78.940363,35.056182],"type":"Point"}
}