{
  "type": "Feature",
  "properties": {
    "addr:full":"100 Roanoke Ave Roanoke Rapids NC 27870",
    "addr:housenumber":"100",
    "addr:postcode":"27870",
    "addr:street":"Roanoke Ave",
    "iso:country":"US",
    "sg:address":"100 Roanoke Ave",
    "sg:city":"Roanoke Rapids",
    "sg:classifiers":[
        {
            "category":"Taxi",
            "type":"Transportation"
        }
    ],
    "sg:phone":"+1 252 537 3011",
    "sg:postcode":"27870",
    "sg:province":"NC",
    "sg:tags":[
        "taxicab"
    ],
    "wof:name":"Phillips' Cab Co",
    "wof:placetype":"venue"
},
  "geometry": {"coordinates":[-77.649565,36.471195],"type":"Point"}
}