{
  "type": "Feature",
  "properties": {
    "iso:country":"US",
    "sg:address":"1516 Greenville Blvd SE",
    "sg:city":"Greenville",
    "sg:classifiers":[
        {
            "category":"Real Estate",
            "subcategory":"Real Estate Agent",
            "type":"Services"
        }
    ],
    "sg:phone":"+1 252 756 1322",
    "sg:postcode":"27858",
    "sg:province":"NC",
    "wof:name":"Jeannette Cox Agency",
    "wof:placetype":"venue"
},
  "geometry": {"coordinates":[-77.348592,35.589734],"type":"Point"}
}