{
  "type": "Feature",
  "properties": {
    "iso:country":"US",
    "sg:address":"150 Parcel Dr",
    "sg:city":"Statesville",
    "sg:classifiers":[
        {
            "category":"Home & Garden",
            "subcategory":"Household Appliances",
            "type":"Retail Goods"
        }
    ],
    "sg:phone":"+1 704 871 1085",
    "sg:postcode":"28625",
    "sg:province":"NC",
    "wof:name":"Blossman Propane Gas & Appl",
    "wof:placetype":"venue"
},
  "geometry": {"coordinates":[-80.87092699999999,35.820224],"type":"Point"}
}