{
  "type": "Feature",
  "properties": {
    "iso:country":"US",
    "sg:address":"5615 Carolina Beach Rd",
    "sg:city":"Wilmington",
    "sg:classifiers":[
        {
            "category":"Restaurant",
            "type":"Food & Drink"
        }
    ],
    "sg:menulink":"http://www.allmenus.com/nc/federal-point/205272-taco-bell/menu/",
    "sg:phone":"+1 910 350 1144",
    "sg:postcode":"28412",
    "sg:province":"NC",
    "sg:tags":[
        "american",
        "mexican"
    ],
    "wof:name":"Taco Bell",
    "wof:placetype":"venue"
},
  "geometry": {"coordinates":[-77.89483300000001,34.134448],"type":"Point"}
}