{
  "type": "Feature",
  "properties": {
    "addr:full":"4280 Everetts Rd Williamston NC 27892",
    "addr:postcode":"4280;27892",
    "addr:street":"Everetts Rd",
    "iso:country":"US",
    "sg:address":"4280 Everetts Rd",
    "sg:city":"Williamston",
    "sg:classifiers":[
        {
            "category":"Professional",
            "type":"Services"
        }
    ],
    "sg:phone":"+1 252 792 6518",
    "sg:postcode":"27892",
    "sg:province":"NC",
    "wof:name":"Leroy Wynn",
    "wof:placetype":"venue"
},
  "geometry": {"coordinates":[-77.168671,35.809828],"type":"Point"}
}