{
  "type": "Feature",
  "properties": {
    "addr:full":"312 Treybrooke Cir Greenville NC 27834",
    "addr:housenumber":"312",
    "addr:postcode":"27834",
    "addr:street":"Treybrooke Cir",
    "iso:country":"US",
    "sg:address":"312 Treybrooke Cir",
    "sg:city":"Greenville",
    "sg:classifiers":[
        {
            "category":"Real Estate",
            "subcategory":"Real Estate Operator",
            "type":"Services"
        }
    ],
    "sg:phone":"+1 252 551 5720",
    "sg:postcode":"27834",
    "sg:province":"NC",
    "sg:tags":[
        "building",
        "apartment"
    ],
    "wof:name":"Treybrooke LLC",
    "wof:placetype":"venue"
},
  "geometry": {"coordinates":[-77.403704,35.61493],"type":"Point"}
}