{
  "type": "Feature",
  "properties": {
    "addr:full":"21 Hillsboro St Pittsboro NC 27312",
    "addr:housenumber":"21",
    "addr:postcode":"27312",
    "addr:street":"Hillsboro St",
    "iso:country":"US",
    "sg:address":"21 Hillsboro St",
    "sg:city":"Pittsboro",
    "sg:classifiers":[
        {
            "category":"Real Estate",
            "subcategory":"Architect",
            "type":"Services"
        }
    ],
    "sg:phone":"+1 919 542 5412",
    "sg:postcode":"27312",
    "sg:province":"NC",
    "wof:name":"Kurt Floyd Lent",
    "wof:placetype":"venue"
},
  "geometry": {"coordinates":[-79.17716900000001,35.721571],"type":"Point"}
}