{
  "type": "Feature",
  "properties": {
    "addr:full":"206 W Main St Carrboro NC 27510",
    "addr:housenumber":"206",
    "addr:postcode":"27510",
    "addr:street":"W Main St",
    "iso:country":"US",
    "sg:address":"206 W Main St",
    "sg:city":"Carrboro",
    "sg:classifiers":[
        {
            "category":"Education",
            "subcategory":"School",
            "type":"Public Place"
        }
    ],
    "sg:phone":"+1   ",
    "sg:postcode":"27510",
    "sg:province":"NC",
    "sg:tags":[
        "health"
    ],
    "wof:name":"Colomb Doris W MA",
    "wof:placetype":"venue"
},
  "geometry": {"coordinates":[-79.075137,35.910093],"type":"Point"}
}