{
  "type": "Feature",
  "properties": {
    "iso:country":"US",
    "sg:address":"359 S Swing Rd",
    "sg:city":"Greensboro",
    "sg:classifiers":[
        {
            "category":"Real Estate",
            "subcategory":"Real Estate Agent",
            "type":"Services"
        }
    ],
    "sg:phone":"+1 336 834 8703",
    "sg:postcode":"27409",
    "sg:province":"NC",
    "wof:name":"Bigwood LLC",
    "wof:placetype":"venue"
},
  "geometry": {"coordinates":[-79.909565,36.065533],"type":"Point"}
}