{
  "type": "Feature",
  "properties": {
    "iso:country":"US",
    "sg:address":"636 Valley Dr",
    "sg:city":"Eden",
    "sg:classifiers":[
        {
            "category":"Recreation",
            "type":"Entertainment"
        }
    ],
    "sg:phone":"+1 336 623 6110",
    "sg:postcode":"27288",
    "sg:province":"NC",
    "sg:tags":[
        "course",
        "golf"
    ],
    "wof:name":"Lynrock Golf Club",
    "wof:placetype":"venue"
},
  "geometry": {"coordinates":[-79.753103,36.488683],"type":"Point"}
}