{
  "type": "Feature",
  "properties": {
    "addr:full":"320 Rush St Raleigh NC 27610",
    "addr:housenumber":"320",
    "addr:postcode":"27610",
    "addr:street":"Rush St",
    "iso:country":"US",
    "sg:address":"320 Rush St",
    "sg:city":"Raleigh",
    "sg:classifiers":[
        {
            "category":"Insurance",
            "subcategory":"Hazard Insurance",
            "type":"Services"
        }
    ],
    "sg:phone":"+1 919 832 6167",
    "sg:postcode":"27610",
    "sg:province":"NC",
    "sg:tags":[
        "bond"
    ],
    "wof:name":"AAA Bail Bonding Co",
    "wof:placetype":"venue"
},
  "geometry": {"coordinates":[-78.637092,35.741959],"type":"Point"}
}