{
  "type": "Feature",
  "properties": {
    "iso:country":"US",
    "sg:address":"1225 W New Bern Rd",
    "sg:city":"Kinston",
    "sg:classifiers":[
        {
            "category":"Organizations",
            "subcategory":"Religious Organization",
            "type":"Services"
        }
    ],
    "sg:phone":"+1 252 523 0303",
    "sg:postcode":"28504",
    "sg:province":"NC",
    "sg:tags":[
        "church"
    ],
    "wof:name":"New Vision Outreach Ministries",
    "wof:placetype":"venue"
},
  "geometry": {"coordinates":[-77.61054300000001,35.258446],"type":"Point"}
}