{
  "type": "Feature",
  "properties": {
    "iso:country":"US",
    "sg:address":"101 N Caswell St",
    "sg:city":"La Grange",
    "sg:classifiers":[
        {
            "category":"Banks & Credit Unions",
            "subcategory":"Bank",
            "type":"Services"
        }
    ],
    "sg:phone":"+1 252 566 5600",
    "sg:postcode":"28551",
    "sg:province":"NC",
    "sg:tags":[
        "depository",
        "banking"
    ],
    "wof:name":"Little Bank",
    "wof:placetype":"venue"
},
  "geometry": {"coordinates":[-77.787848,35.307401],"type":"Point"}
}