{
  "type": "Feature",
  "properties": {
    "addr:full":"1315 S Horner Blvd Sanford NC 27330",
    "addr:housenumber":"1315",
    "addr:postcode":"27330",
    "addr:street":"S Horner Blvd",
    "iso:country":"US",
    "sg:address":"1315 S Horner Blvd",
    "sg:city":"Sanford",
    "sg:classifiers":[
        {
            "category":"Organizations",
            "subcategory":"Religious Organization",
            "type":"Services"
        }
    ],
    "sg:phone":"+1   ",
    "sg:postcode":"27330",
    "sg:province":"NC",
    "wof:name":"Abundant Life Ministry",
    "wof:placetype":"venue"
},
  "geometry": {"coordinates":[-79.164618,35.469028],"type":"Point"}
}