{
  "type": "Feature",
  "properties": {
    "iso:country":"US",
    "sg:address":"112 Ravenwood Dr",
    "sg:city":"Lake Lure",
    "sg:classifiers":[
        {
            "category":"Retail",
            "subcategory":"Laundry & Dry Cleaning",
            "type":"Services"
        }
    ],
    "sg:phone":"+1 828 625 9989",
    "sg:postcode":"28761",
    "sg:province":"NC",
    "sg:tags":[
        "cleaners",
        "rug",
        "carpet"
    ],
    "wof:name":"Repko Carpet Cleaning",
    "wof:placetype":"venue"
},
  "geometry": {"coordinates":[-81.941033,35.739522],"type":"Point"}
}