{
  "type": "Feature",
  "properties": {
    "addr:full":"5900 Laguna Dr Fayetteville NC 28314",
    "addr:housenumber":"5900",
    "addr:postcode":"28314",
    "addr:street":"Laguna Dr",
    "iso:country":"US",
    "sg:address":"5900 Laguna Dr",
    "sg:city":"Fayetteville",
    "sg:classifiers":[
        {
            "category":"Building & Trades",
            "subcategory":"Electrical",
            "type":"Services"
        },
        {
            "category":"Retail",
            "subcategory":"Repair Shop",
            "type":"Services"
        }
    ],
    "sg:phone":"+1 910 860 3548",
    "sg:postcode":"28314",
    "sg:province":"NC",
    "sg:tags":[
        "electrical",
        "electric",
        "contractor"
    ],
    "wof:name":"Adventure Electric & Home Repa",
    "wof:placetype":"venue"
},
  "geometry": {"coordinates":[-78.987431,35.070581],"type":"Point"}
}