{
  "type": "Feature",
  "properties": {
    "iso:country":"US",
    "sg:address":"295 Miller Rd",
    "sg:city":"Mocksville",
    "sg:classifiers":[
        {
            "category":"Building & Trades",
            "subcategory":"Plumbing",
            "type":"Services"
        }
    ],
    "sg:phone":"+1 336 284 2826",
    "sg:postcode":"27028",
    "sg:province":"NC",
    "sg:tags":[
        "septic"
    ],
    "wof:name":"Randy Miller & Sons Backhoe",
    "wof:placetype":"venue"
},
  "geometry": {"coordinates":[-80.526895,35.805213],"type":"Point"}
}