{
  "type": "Feature",
  "properties": {
    "addr:full":"482 Reems Creek Rd Weaverville NC 28787",
    "addr:housenumber":"482",
    "addr:postcode":"28787",
    "addr:street":"Reems Creek Rd",
    "iso:country":"US",
    "sg:address":"482 Reems Creek Rd",
    "sg:city":"Weaverville",
    "sg:classifiers":[
        {
            "category":"Retail",
            "subcategory":"Repair Shop",
            "type":"Services"
        }
    ],
    "sg:phone":"+1 828 645 6879",
    "sg:postcode":"28787",
    "sg:province":"NC",
    "sg:tags":[
        "water",
        "well",
        "drilling"
    ],
    "wof:name":"Clearwater Well Drilling",
    "wof:placetype":"venue"
},
  "geometry": {"coordinates":[-82.52968,35.689928],"type":"Point"}
}