{
  "type": "Feature",
  "properties": {
    "iso:country":"US",
    "sg:address":"2013 US Hwy 301",
    "sg:city":"Wilson",
    "sg:classifiers":[
        {
            "category":"Shopping",
            "subcategory":"Used Merchandise",
            "type":"Retail Goods"
        }
    ],
    "sg:phone":"+1 252 237 1700",
    "sg:postcode":"27893",
    "sg:province":"NC",
    "sg:tags":[
        "antique"
    ],
    "wof:name":"Boykin Appraisals Inc",
    "wof:placetype":"venue"
},
  "geometry": {"coordinates":[-77.928365,35.702559],"type":"Point"}
}