{
  "type": "Feature",
  "properties": {
    "addr:full":"1013 Carolina St Roanoke Rapids NC 27870",
    "addr:housenumber":"1013",
    "addr:postcode":"27870",
    "addr:street":"Carolina St",
    "iso:country":"US",
    "sg:address":"1013 Carolina St",
    "sg:city":"Roanoke Rapids",
    "sg:classifiers":[
        {
            "category":"Retail",
            "subcategory":"Repair Shop",
            "type":"Services"
        }
    ],
    "sg:phone":"+1 252 535 5304",
    "sg:postcode":"27870",
    "sg:province":"NC",
    "sg:tags":[
        "welding"
    ],
    "wof:name":"Ted's Welding",
    "wof:placetype":"venue"
},
  "geometry": {"coordinates":[-77.64939699999999,36.453215],"type":"Point"}
}