{
  "type": "Feature",
  "properties": {
    "addr:full":"1270 Smokey Park Hwy Candler NC 28715",
    "addr:housenumber":"1270",
    "addr:postcode":"28715",
    "addr:street":"Smokey Park Hwy",
    "iso:country":"US",
    "sg:address":"1270 Smokey Park Hwy",
    "sg:city":"Candler",
    "sg:classifiers":[
        {
            "category":"Wholesale",
            "subcategory":"Construction Materials",
            "type":"Manufacturing & Wholesale Goods"
        }
    ],
    "sg:phone":"+1 828 665 8900",
    "sg:postcode":"28715",
    "sg:province":"NC",
    "sg:tags":[
        "fence"
    ],
    "sg:website":"www.ashevillefence.com",
    "wof:name":"Asheville Fence & Contracting",
    "wof:placetype":"venue"
},
  "geometry": {"coordinates":[-82.674746,35.545317],"type":"Point"}
}