{
  "type": "Feature",
  "properties": {
    "addr:full":"10319 Cedar Trail Ln Charlotte NC 28210",
    "addr:housenumber":"10319",
    "addr:postcode":"28210",
    "addr:street":"Cedar Trail Ln",
    "iso:country":"US",
    "sg:address":"10319 Cedar Trail Ln",
    "sg:city":"Charlotte",
    "sg:classifiers":[
        {
            "category":"Shopping",
            "subcategory":"Gifts & Souvenirs",
            "type":"Retail Goods"
        }
    ],
    "sg:phone":"+1 704 752 8380",
    "sg:postcode":"28210",
    "sg:province":"NC",
    "sg:tags":[
        "shop"
    ],
    "wof:name":"Ruth & Naomi's Gifts",
    "wof:placetype":"venue"
},
  "geometry": {"coordinates":[-80.854479,35.092047],"type":"Point"}
}