{
  "type": "Feature",
  "properties": {
    "iso:country":"US",
    "sg:address":"219 Bedrock Ct",
    "sg:city":"Wilmington",
    "sg:classifiers":[
        {
            "category":"Real Estate",
            "subcategory":"Surveying",
            "type":"Services"
        }
    ],
    "sg:phone":"+1   ",
    "sg:postcode":"28411",
    "sg:province":"NC",
    "wof:name":"Donnalley Marine Services Inc",
    "wof:placetype":"venue"
},
  "geometry": {"coordinates":[-77.78881,34.261921],"type":"Point"}
}