{
  "type": "Feature",
  "properties": {
    "addr:full":"9940 Monroe Rd Matthews NC 28105",
    "addr:housenumber":"9940",
    "addr:postcode":"28105",
    "addr:street":"Monroe Rd",
    "iso:country":"US",
    "sg:address":"9940 Monroe Rd",
    "sg:city":"Matthews",
    "sg:classifiers":[
        {
            "category":"Health Services",
            "subcategory":"Chiropractor",
            "type":"Services"
        }
    ],
    "sg:phone":"+1   ",
    "sg:postcode":"28105",
    "sg:province":"NC",
    "wof:name":"Timothy Cheuvront Dr",
    "wof:placetype":"venue"
},
  "geometry": {"coordinates":[-80.73759800000001,35.135937],"type":"Point"}
}