{
  "type": "Feature",
  "properties": {
    "addr:full":"1900 Eastwood Rd Wilmington NC 28403",
    "addr:housenumber":"1900",
    "addr:postcode":"28403",
    "addr:street":"Eastwood Rd",
    "iso:country":"US",
    "sg:address":"1900 Eastwood Rd",
    "sg:city":"Wilmington",
    "sg:classifiers":[
        {
            "category":"Professional",
            "subcategory":"Accounting & Tax Preparation",
            "type":"Services"
        }
    ],
    "sg:phone":"+1 910 509 9945",
    "sg:postcode":"28403",
    "sg:province":"NC",
    "sg:tags":[
        "accountant"
    ],
    "wof:name":"Martin J Lee II CPA Pa",
    "wof:placetype":"venue"
},
  "geometry": {"coordinates":[-77.82159799999999,34.222916],"type":"Point"}
}