{
  "type": "Feature",
  "properties": {
    "addr:full":"9548 Mount Holly Rd Charlotte NC 28214",
    "addr:housenumber":"9548",
    "addr:postcode":"28214",
    "addr:street":"Mount Holly Rd",
    "iso:country":"US",
    "sg:address":"9548 Mount Holly Rd",
    "sg:city":"Charlotte",
    "sg:classifiers":[
        {
            "category":"Restaurant",
            "type":"Food & Drink"
        }
    ],
    "sg:phone":"+1 704 394 5677",
    "sg:postcode":"28214",
    "sg:province":"NC",
    "wof:name":"Tony's Pizza",
    "wof:placetype":"venue"
},
  "geometry": {"coordinates":[-80.965188,35.289153],"type":"Point"}
}