{
  "type": "Feature",
  "properties": {
    "iso:country":"US",
    "sg:address":"5800 N Sharon Amity Rd",
    "sg:city":"Charlotte",
    "sg:classifiers":[
        {
            "category":"Personal",
            "subcategory":"Beauty Salon",
            "type":"Services"
        },
        {
            "category":"Personal",
            "subcategory":"Barber",
            "type":"Services"
        }
    ],
    "sg:phone":"+1 704 531 5550",
    "sg:postcode":"28215",
    "sg:province":"NC",
    "sg:tags":[
        "hair",
        "stylist"
    ],
    "wof:name":"Manhattan Unisex",
    "wof:placetype":"venue"
},
  "geometry": {"coordinates":[-80.737556,35.23771],"type":"Point"}
}