{
  "type": "Feature",
  "properties": {
    "iso:country":"US",
    "sg:address":"2873 Trent Rd",
    "sg:city":"New Bern",
    "sg:classifiers":[
        {
            "category":"Personal",
            "subcategory":"Beauty Salon",
            "type":"Services"
        }
    ],
    "sg:phone":"+1 252 635 1522",
    "sg:postcode":"28562",
    "sg:province":"NC",
    "sg:tags":[
        "shop",
        "manicuring"
    ],
    "wof:name":"Amazing Nails & Facials LLC",
    "wof:placetype":"venue"
},
  "geometry": {"coordinates":[-77.083792,35.095993],"type":"Point"}
}