{
  "type": "Feature",
  "properties": {
    "iso:country":"US",
    "sg:address":"309 W Montcastle Dr",
    "sg:city":"Greensboro",
    "sg:classifiers":[
        {
            "category":"Retail",
            "subcategory":"Repair Shop",
            "type":"Services"
        }
    ],
    "sg:phone":"+1   ",
    "sg:postcode":"27406",
    "sg:province":"NC",
    "wof:name":"Housing Restoration & Repair",
    "wof:placetype":"venue"
},
  "geometry": {"coordinates":[-79.797303,36.017811],"type":"Point"}
}