{
  "type": "Feature",
  "properties": {
    "iso:country":"US",
    "sg:address":"2715 US Hwy 421",
    "sg:city":"Wilmington",
    "sg:classifiers":[
        {
            "category":"Wholesale",
            "subcategory":"Machinery & Supplies",
            "type":"Manufacturing & Wholesale Goods"
        }
    ],
    "sg:phone":"+1 910 763 6281",
    "sg:postcode":"28401",
    "sg:province":"NC",
    "sg:tags":[
        "truck"
    ],
    "sg:website":"www.wemeantrucks.com",
    "wof:name":"Triple-T",
    "wof:placetype":"venue"
},
  "geometry": {"coordinates":[-77.965839,34.285011],"type":"Point"}
}