{
  "type": "Feature",
  "properties": {
    "iso:country":"US",
    "sg:address":"13925 Ballantyne Corporate Pl",
    "sg:city":"Charlotte",
    "sg:classifiers":[
        {
            "category":"Real Estate",
            "subcategory":"Real Estate Services",
            "type":"Services"
        }
    ],
    "sg:phone":"+1 704 323 8030",
    "sg:postcode":"28277",
    "sg:province":"NC",
    "sg:tags":[
        "loan"
    ],
    "wof:name":"First South Mortgage Group",
    "wof:placetype":"venue"
},
  "geometry": {"coordinates":[-80.855862,35.060444],"type":"Point"}
}