{
  "type": "Feature",
  "properties": {
    "iso:country":"US",
    "sg:address":"3259 Leota Dr",
    "sg:city":"Charlotte",
    "sg:phone":"+1 704 333 3775",
    "sg:postcode":"28206",
    "sg:province":"NC",
    "sg:tags":[
        "oil",
        "gasoline",
        "gasoline-wholesale"
    ],
    "sg:website":"http://www.purseroil.com",
    "wof:name":"Purser Oil Co Inc",
    "wof:placetype":"venue"
},
  "geometry": {"coordinates":[-80.81497299999999,35.259102],"type":"Point"}
}