{
  "type": "Feature",
  "properties": {
    "addr:full":"4860 Thales Rd Winston Salem NC 27104",
    "addr:housenumber":"4860",
    "addr:postcode":"27104",
    "addr:street":"Thales Rd",
    "iso:country":"US",
    "sg:address":"4860 Thales Rd",
    "sg:city":"Winston Salem",
    "sg:classifiers":[
        {
            "category":"Building & Trades",
            "subcategory":"Construction",
            "type":"Services"
        }
    ],
    "sg:phone":"+1 336 774 1606",
    "sg:postcode":"27104",
    "sg:province":"NC",
    "sg:tags":[
        "hanging",
        "contractor"
    ],
    "wof:name":"Artistic Rainbow",
    "wof:placetype":"venue"
},
  "geometry": {"coordinates":[-80.33942399999999,36.08525],"type":"Point"}
}