{
  "type": "Feature",
  "properties": {
    "iso:country":"US",
    "sg:address":"48 Creekside Cir",
    "sg:city":"Hayesville",
    "sg:classifiers":[
        {
            "category":"Building & Trades",
            "subcategory":"Plumbing",
            "type":"Services"
        }
    ],
    "sg:phone":"+1 828 389 8136",
    "sg:postcode":"28904",
    "sg:province":"NC",
    "sg:tags":[
        "installation",
        "pump",
        "heating",
        "contractor",
        "heat",
        "electrical",
        "co"
    ],
    "wof:name":"Woodard Electric Service Inc",
    "wof:placetype":"venue"
},
  "geometry": {"coordinates":[-83.823971,35.029045],"type":"Point"}
}