{
  "type": "Feature",
  "properties": {
    "iso:country":"US",
    "sg:address":"3815 N Liberty St",
    "sg:city":"Winston Salem",
    "sg:classifiers":[
        {
            "category":"Education",
            "subcategory":"Special Training",
            "type":"Public Place"
        }
    ],
    "sg:phone":"+1 336 744 4000",
    "sg:postcode":"27105",
    "sg:province":"NC",
    "sg:tags":[
        "aircraft",
        "school"
    ],
    "sg:website":"www.triadair.com",
    "wof:name":"Triad Air Inc",
    "wof:placetype":"venue"
},
  "geometry": {"coordinates":[-80.230046,36.136725],"type":"Point"}
}