{
  "type": "Feature",
  "properties": {
    "iso:country":"US",
    "sg:address":"157 N 2nd St",
    "sg:city":"Albemarle",
    "sg:classifiers":[
        {
            "category":"Government",
            "subcategory":"Office",
            "type":"Public Place"
        }
    ],
    "sg:phone":"+1 704 984 9400",
    "sg:postcode":"28001",
    "sg:province":"NC",
    "sg:tags":[
        "village"
    ],
    "wof:name":"Albemarle Administrative Ofcs",
    "wof:placetype":"venue"
},
  "geometry": {"coordinates":[-80.198125,35.351165],"type":"Point"}
}