{
  "type": "Feature",
  "properties": {
    "iso:country":"US",
    "sg:address":"311 S Westgate Dr",
    "sg:city":"Greensboro",
    "sg:classifiers":[
        {
            "category":"Professional",
            "subcategory":"Research",
            "type":"Services"
        }
    ],
    "sg:phone":"+1 336 510 0340",
    "sg:postcode":"27407",
    "sg:province":"NC",
    "sg:tags":[
        "environmental",
        "ecological"
    ],
    "wof:name":"Branch Residuals & Soils LLC",
    "wof:placetype":"venue"
},
  "geometry": {"coordinates":[-79.85947,36.064742],"type":"Point"}
}