{
  "type": "Feature",
  "properties": {
    "addr:full":"100 Providence Rd Chapel Hill NC 27514",
    "addr:housenumber":"100",
    "addr:postcode":"27514",
    "addr:street":"Providence Rd",
    "iso:country":"US",
    "sg:address":"100 Providence Rd",
    "sg:city":"Chapel Hill",
    "sg:classifiers":[
        {
            "category":"Professional",
            "type":"Services"
        }
    ],
    "sg:phone":"+1 919 932 7330",
    "sg:postcode":"27514",
    "sg:province":"NC",
    "sg:tags":[
        "establishment"
    ],
    "wof:name":"Providence Glen Homeowners",
    "wof:placetype":"venue"
},
  "geometry": {"coordinates":[-79.007267,35.950966],"type":"Point"}
}