{
  "type": "Feature",
  "properties": {
    "addr:full":"70 Pisgah View Ranch Rd Candler NC 28715",
    "addr:housenumber":"70",
    "addr:postcode":"28715",
    "addr:street":"Pisgah;Ranch Rd",
    "iso:country":"US",
    "sg:address":"70 Pisgah View Ranch Rd",
    "sg:city":"Candler",
    "sg:classifiers":[
        {
            "category":"Farming",
            "subcategory":"Livestock Farm",
            "type":"Manufacturing & Wholesale Goods"
        }
    ],
    "sg:phone":"+1 828 667 9100",
    "sg:postcode":"28715",
    "sg:province":"NC",
    "sg:tags":[
        "ranch"
    ],
    "sg:website":"www.pisgahviewranch.com",
    "wof:name":"Pisgah View Ranch",
    "wof:placetype":"venue"
},
  "geometry": {"coordinates":[-82.770059,35.469592],"type":"Point"}
}