{
  "type": "Feature",
  "properties": {
    "addr:full":"6241 US Hwy 70 New Bern NC 28562",
    "addr:housenumber":"6241",
    "addr:postcode":"28562",
    "addr:street":"Us Hwy 70",
    "iso:country":"US",
    "sg:address":"6241 US Hwy 70",
    "sg:city":"New Bern",
    "sg:classifiers":[
        {
            "category":"Shopping",
            "subcategory":"Used Merchandise",
            "type":"Retail Goods"
        }
    ],
    "sg:phone":"+1 252 637 8030",
    "sg:postcode":"28562",
    "sg:province":"NC",
    "sg:tags":[
        "antique"
    ],
    "wof:name":"Martha's Favorite Things",
    "wof:placetype":"venue"
},
  "geometry": {"coordinates":[-76.97087500000001,34.970516],"type":"Point"}
}