{
  "type": "Feature",
  "properties": {
    "iso:country":"US",
    "sg:address":"529 Huffman Mill Rd",
    "sg:city":"Burlington",
    "sg:classifiers":[
        {
            "category":"Retail",
            "subcategory":"Portrait Studio",
            "type":"Services"
        }
    ],
    "sg:phone":"+1 336 585 1263",
    "sg:postcode":"27215",
    "sg:province":"NC",
    "sg:tags":[
        "photographer"
    ],
    "wof:name":"Olan Mills Portrait Studio",
    "wof:placetype":"venue"
},
  "geometry": {"coordinates":[-79.489631,36.07511],"type":"Point"}
}