{
  "type": "Feature",
  "properties": {
    "iso:country":"US",
    "sg:address":"2502 E Ash St",
    "sg:city":"Goldsboro",
    "sg:classifiers":[
        {
            "category":"Professional",
            "subcategory":"Computer Services",
            "type":"Services"
        }
    ],
    "sg:phone":"+1 919 735 8118",
    "sg:postcode":"27534",
    "sg:province":"NC",
    "sg:tags":[
        "related",
        "internet"
    ],
    "wof:name":"Xpress Communications Inc",
    "wof:placetype":"venue"
},
  "geometry": {"coordinates":[-77.956519,35.374455],"type":"Point"}
}