{
  "type": "Feature",
  "properties": {
    "iso:country":"US",
    "sg:address":"5465 US Hwy 17",
    "sg:city":"Washington",
    "sg:classifiers":[
        {
            "category":"Freight",
            "type":"Transportation"
        }
    ],
    "sg:phone":"+1 252 946 6600",
    "sg:postcode":"27889",
    "sg:province":"NC",
    "sg:tags":[
        "commercial",
        "storage"
    ],
    "wof:name":"Pamlico Mini-Storage",
    "wof:placetype":"venue"
},
  "geometry": {"coordinates":[-77.06264899999999,35.628236],"type":"Point"}
}