{
  "type": "Feature",
  "properties": {
    "iso:country":"US",
    "sg:address":"1819 Four Seasons Blvd",
    "sg:city":"Hendersonville",
    "sg:classifiers":[
        {
            "category":"Restaurant",
            "type":"Food & Drink"
        }
    ],
    "sg:menulink":"http://www.allmenus.com/nc/hendersonville/205203-taco-bell/menu/",
    "sg:phone":"+1 828 697 2029",
    "sg:postcode":"28792",
    "sg:province":"NC",
    "sg:tags":[
        "american",
        "mexican"
    ],
    "wof:name":"Taco Bell",
    "wof:placetype":"venue"
},
  "geometry": {"coordinates":[-82.448373,35.333594],"type":"Point"}
}