{
  "type": "Feature",
  "properties": {
    "addr:full":"3650 Sweetgrass Ln Charlotte NC 28226",
    "addr:housenumber":"3650",
    "addr:postcode":"28226",
    "addr:street":"Sweetgrass Ln",
    "iso:country":"US",
    "sg:address":"3650 Sweetgrass Ln",
    "sg:city":"Charlotte",
    "sg:classifiers":[
        {
            "category":"Building & Trades",
            "subcategory":"Construction",
            "type":"Services"
        }
    ],
    "sg:phone":"+1 704 542 7865",
    "sg:postcode":"28226",
    "sg:province":"NC",
    "sg:tags":[
        "general",
        "contractor"
    ],
    "wof:name":"International Construction LLC",
    "wof:placetype":"venue"
},
  "geometry": {"coordinates":[-80.797376,35.101631],"type":"Point"}
}