{
  "type": "Feature",
  "properties": {
    "iso:country":"US",
    "sg:address":"4139 South Blvd",
    "sg:city":"Charlotte",
    "sg:classifiers":[
        {
            "category":"Banks & Credit Unions",
            "subcategory":"Bank",
            "type":"Services"
        }
    ],
    "sg:phone":"+1 704 679 9184",
    "sg:postcode":"28209",
    "sg:province":"NC",
    "sg:tags":[
        "money",
        "transfer"
    ],
    "wof:name":"Ficohsa Express",
    "wof:placetype":"venue"
},
  "geometry": {"coordinates":[-80.87566700000001,35.184173],"type":"Point"}
}