{
  "type": "Feature",
  "properties": {
    "addr:full":"806 Summit Ave Greensboro NC 27405",
    "addr:housenumber":"806",
    "addr:postcode":"27405",
    "addr:street":"Summit Ave",
    "iso:country":"US",
    "sg:address":"806 Summit Ave",
    "sg:city":"Greensboro",
    "sg:classifiers":[
        {
            "category":"Education",
            "subcategory":"Vocational School",
            "type":"Public Place"
        }
    ],
    "sg:phone":"+1 336 271 8124",
    "sg:postcode":"27405",
    "sg:province":"NC",
    "sg:tags":[
        "development"
    ],
    "wof:name":"Greensboro Education & Dev",
    "wof:placetype":"venue"
},
  "geometry": {"coordinates":[-79.77747599999999,36.083509],"type":"Point"}
}