{
  "type": "Feature",
  "properties": {
    "addr:full":"914 Mall Loop Rd High Point NC 27262",
    "addr:housenumber":"914",
    "addr:postcode":"27262",
    "addr:street":"Mall Loop Rd",
    "iso:country":"US",
    "sg:address":"914 Mall Loop Rd",
    "sg:city":"High Point",
    "sg:classifiers":[
        {
            "category":"Restaurant",
            "type":"Food & Drink"
        }
    ],
    "sg:menulink":"http://www.allmenus.com/nc/high-point/93214-liberty-steakhouse/menu/",
    "sg:phone":"+1 336 882 4677",
    "sg:postcode":"27262",
    "sg:province":"NC",
    "sg:tags":[
        "american",
        "steakhouse"
    ],
    "wof:name":"Liberty Steakhouse",
    "wof:placetype":"venue"
},
  "geometry": {"coordinates":[-80.00435299999999,35.988023],"type":"Point"}
}