{
  "type": "Feature",
  "properties": {
    "iso:country":"US",
    "sg:address":"702 S Main St",
    "sg:city":"Salisbury",
    "sg:classifiers":[
        {
            "category":"Autos & Motor Vehicles",
            "subcategory":"Auto Supplies",
            "type":"Retail Goods"
        }
    ],
    "sg:phone":"+1 704 633 1881",
    "sg:postcode":"28144",
    "sg:province":"NC",
    "sg:tags":[
        "tire"
    ],
    "wof:name":"Rusher Tire Service",
    "wof:placetype":"venue"
},
  "geometry": {"coordinates":[-80.47759499999999,35.661535],"type":"Point"}
}