{
  "type": "Feature",
  "properties": {
    "iso:country":"US",
    "sg:address":"40 Technology Dr",
    "sg:city":"Garner",
    "sg:classifiers":[
        {
            "category":"Retail",
            "subcategory":"Auto Repair",
            "type":"Services"
        }
    ],
    "sg:phone":"+1 919 661 4040",
    "sg:postcode":"27529",
    "sg:province":"NC",
    "sg:tags":[
        "automobile",
        "lubrication",
        "automotive"
    ],
    "wof:name":"Lane's Lube Express",
    "wof:placetype":"venue"
},
  "geometry": {"coordinates":[-78.569062,35.605637],"type":"Point"}
}