{
  "type": "Feature",
  "properties": {
    "iso:country":"US",
    "sg:address":"1475 W Mount Gilead Church Rd",
    "sg:city":"Clinton",
    "sg:classifiers":[
        {
            "category":"Farming",
            "subcategory":"Farm",
            "type":"Manufacturing & Wholesale Goods"
        }
    ],
    "sg:phone":"+1 910 592 5361",
    "sg:postcode":"28328",
    "sg:province":"NC",
    "sg:tags":[
        "crop",
        "general"
    ],
    "wof:name":"Rkk Farms Inc",
    "wof:placetype":"venue"
},
  "geometry": {"coordinates":[-78.276567,34.906796],"type":"Point"}
}