{
  "type": "Feature",
  "properties": {
    "addr:full":"2850 Wendell Blvd Wendell NC 27591",
    "addr:housenumber":"2850",
    "addr:postcode":"27591",
    "addr:street":"Wendell Blvd",
    "iso:country":"US",
    "sg:address":"2850 Wendell Blvd",
    "sg:city":"Wendell",
    "sg:classifiers":[
        {
            "category":"Insurance",
            "subcategory":"Insurance Agent",
            "type":"Services"
        }
    ],
    "sg:phone":"+1 919 365 6350",
    "sg:postcode":"27591",
    "sg:province":"NC",
    "wof:name":"Todd and Scarboro Insur Agcy",
    "wof:placetype":"venue"
},
  "geometry": {"coordinates":[-78.379642,35.793541],"type":"Point"}
}