{
  "type": "Feature",
  "properties": {
    "iso:country":"US",
    "sg:address":"169 Candler School Rd",
    "sg:city":"Candler",
    "sg:classifiers":[
        {
            "category":"Shopping",
            "subcategory":"Used Merchandise",
            "type":"Retail Goods"
        }
    ],
    "sg:phone":"+1 828 667 0000",
    "sg:postcode":"28715",
    "sg:province":"NC",
    "wof:name":"Copper Kettle Antique Mall",
    "wof:placetype":"venue"
},
  "geometry": {"coordinates":[-82.705943,35.540028],"type":"Point"}
}