{
  "type": "Feature",
  "properties": {
    "addr:full":"102 Chapman Dr Hendersonville NC 28792",
    "addr:housenumber":"102",
    "addr:postcode":"28792",
    "addr:street":"Chapman Dr",
    "iso:country":"US",
    "sg:address":"102 Chapman Dr",
    "sg:city":"Hendersonville",
    "sg:classifiers":[
        {
            "category":"Building & Trades",
            "subcategory":"Construction",
            "type":"Services"
        }
    ],
    "sg:phone":"+1 828 692 7635",
    "sg:postcode":"28792",
    "sg:province":"NC",
    "sg:tags":[
        "general",
        "contractor"
    ],
    "wof:name":"Kenneth R Wilkie Residential",
    "wof:placetype":"venue"
},
  "geometry": {"coordinates":[-82.462988,35.370194],"type":"Point"}
}