{
  "type": "Feature",
  "properties": {
    "addr:full":"3453 Clarks Chapel Rd Lenoir NC 28645",
    "addr:housenumber":"3453",
    "addr:postcode":"28645",
    "addr:street":"Clarks Chapel Rd",
    "iso:country":"US",
    "sg:address":"3453 Clarks Chapel Rd",
    "sg:city":"Lenoir",
    "sg:classifiers":[
        {
            "category":"Retail",
            "subcategory":"Animal Services",
            "type":"Services"
        }
    ],
    "sg:phone":"+1 828 726 6614",
    "sg:postcode":"28645",
    "sg:province":"NC",
    "wof:name":"Tender Loving Care Grooming",
    "wof:placetype":"venue"
},
  "geometry": {"coordinates":[-81.572265,35.842125],"type":"Point"}
}