{
  "type": "Feature",
  "properties": {
    "addr:full":"3823 Durham-Chapel Hill Blvd Durham NC 27707",
    "addr:housenumber":"3823",
    "addr:postcode":"27707",
    "addr:street":"Durham-Chapel Hill Blvd",
    "iso:country":"US",
    "sg:address":"3823 Durham-Chapel Hill Blvd",
    "sg:city":"Durham",
    "sg:classifiers":[
        {
            "category":"Retail",
            "subcategory":"Auto Repair",
            "type":"Services"
        }
    ],
    "sg:phone":"+1 919 402 8000",
    "sg:postcode":"27707",
    "sg:province":"NC",
    "sg:tags":[
        "repairing",
        "automobile"
    ],
    "wof:name":"University Collison Ctr",
    "wof:placetype":"venue"
},
  "geometry": {"coordinates":[-78.95298,35.970786],"type":"Point"}
}