{
  "type": "Feature",
  "properties": {
    "addr:full":"113 W Atkins St Dobson NC 27017",
    "addr:housenumber":"113",
    "addr:postcode":"27017",
    "addr:street":"W Atkins St",
    "iso:country":"US",
    "sg:address":"113 W Atkins St",
    "sg:city":"Dobson",
    "sg:classifiers":[
        {
            "category":"Insurance",
            "subcategory":"Insurance Agent",
            "type":"Services"
        }
    ],
    "sg:phone":"+1 336 386 8912",
    "sg:postcode":"27017",
    "sg:province":"NC",
    "wof:name":"Simpson Insurance Inc",
    "wof:placetype":"venue"
},
  "geometry": {"coordinates":[-80.72260900000001,36.395528],"type":"Point"}
}