{
  "type": "Feature",
  "properties": {
    "addr:full":"2407 Alwin Ct Raleigh NC 27604",
    "addr:housenumber":"2407",
    "addr:postcode":"27604",
    "addr:street":"Alwin Ct",
    "iso:country":"US",
    "sg:address":"2407 Alwin Ct",
    "sg:city":"Raleigh",
    "sg:classifiers":[
        {
            "category":"Manufacturing",
            "subcategory":"Metals",
            "type":"Manufacturing & Wholesale Goods"
        }
    ],
    "sg:phone":"+1 919 832 2802",
    "sg:postcode":"27604",
    "sg:province":"NC",
    "sg:tags":[
        "tool"
    ],
    "wof:name":"ABC Power Tool Inc",
    "wof:placetype":"venue"
},
  "geometry": {"coordinates":[-78.61681799999999,35.812887],"type":"Point"}
}