{
  "type": "Feature",
  "properties": {
    "iso:country":"US",
    "sg:address":"3720 Battleground Ave",
    "sg:city":"Greensboro",
    "sg:classifiers":[
        {
            "category":"Health Services",
            "subcategory":"Doctor",
            "type":"Services"
        }
    ],
    "sg:phone":"+1 336 288 9116",
    "sg:postcode":"27410",
    "sg:province":"NC",
    "sg:tags":[
        "dentist"
    ],
    "wof:name":"Beatriz R Aguero & Assoc",
    "wof:placetype":"venue"
},
  "geometry": {"coordinates":[-79.85452600000001,36.130356],"type":"Point"}
}