{
  "type": "Feature",
  "properties": {
    "iso:country":"US",
    "sg:address":"505 Copley Dr",
    "sg:city":"Kill Devil Hills",
    "sg:classifiers":[
        {
            "category":"Professional",
            "subcategory":"Business Services",
            "type":"Services"
        },
        {
            "category":"Government",
            "subcategory":"Office",
            "type":"Public Place"
        }
    ],
    "sg:phone":"+1 252 441 6672",
    "sg:postcode":"27948",
    "sg:province":"NC",
    "sg:tags":[
        "state",
        "program"
    ],
    "wof:name":"Clean Water Management Tr Fund",
    "wof:placetype":"venue"
},
  "geometry": {"coordinates":[-75.657427,35.993638],"type":"Point"}
}