{
  "type": "Feature",
  "properties": {
    "iso:country":"US",
    "sg:address":"1605 Ann St",
    "sg:city":"Beaufort",
    "sg:classifiers":[
        {
            "category":"Building & Trades",
            "subcategory":"Landscaping Services",
            "type":"Services"
        }
    ],
    "sg:phone":"+1 252 728 2811",
    "sg:postcode":"28516",
    "sg:province":"NC",
    "sg:tags":[
        "landscape",
        "contractor"
    ],
    "wof:name":"Safrit Brothers Landscaping",
    "wof:placetype":"venue"
},
  "geometry": {"coordinates":[-76.646368,34.713896],"type":"Point"}
}