{
  "type": "Feature",
  "properties": {
    "iso:country":"US",
    "sg:address":"3332 White Oak Rd",
    "sg:city":"Raleigh",
    "sg:classifiers":[
        {
            "category":"Building & Trades",
            "subcategory":"Landscaping Services",
            "type":"Services"
        },
        {
            "category":"Home & Garden",
            "subcategory":"Garden Supply",
            "type":"Retail Goods"
        },
        {
            "category":"Wholesale",
            "subcategory":"Machinery & Supplies",
            "type":"Manufacturing & Wholesale Goods"
        },
        {
            "category":"Manufacturing",
            "subcategory":"Paper Products",
            "type":"Manufacturing & Wholesale Goods"
        }
    ],
    "sg:phone":"+1 919 782 9181",
    "sg:postcode":"27609",
    "sg:province":"NC",
    "sg:tags":[
        "irrigation",
        "designer",
        "consultant",
        "system",
        "equipment",
        "bamboo",
        "landscape"
    ],
    "wof:name":"Lassiter Mill Gardens Inc.",
    "wof:placetype":"venue"
},
  "geometry": {"coordinates":[-78.64810900000001,35.822441],"type":"Point"}
}