{
  "type": "Feature",
  "properties": {
    "iso:country":"US",
    "sg:address":"4619 Pearidge Rd",
    "sg:city":"Roper",
    "sg:classifiers":[
        {
            "category":"Farming",
            "subcategory":"Poultry Farm",
            "type":"Manufacturing & Wholesale Goods"
        }
    ],
    "sg:phone":"+1 252 797 4091",
    "sg:postcode":"27970",
    "sg:province":"NC",
    "sg:tags":[
        "chicken"
    ],
    "wof:name":"Bobby Clifton",
    "wof:placetype":"venue"
},
  "geometry": {"coordinates":[-76.42264900000001,35.930847],"type":"Point"}
}