{
  "type": "Feature",
  "properties": {
    "addr:full":"1292 Briarcreek Rd King NC 27021",
    "addr:housenumber":"1292",
    "addr:postcode":"27021",
    "addr:street":"Briarcreek Rd",
    "iso:country":"US",
    "sg:address":"1292 Briarcreek Rd",
    "sg:city":"King",
    "sg:classifiers":[
        {
            "category":"Freight",
            "type":"Transportation"
        }
    ],
    "sg:phone":"+1 336 983 5383",
    "sg:postcode":"27021",
    "sg:province":"NC",
    "sg:tags":[
        "special"
    ],
    "wof:name":"Alexander Knight",
    "wof:placetype":"venue"
},
  "geometry": {"coordinates":[-80.362509,36.328749],"type":"Point"}
}