{
  "type": "Feature",
  "properties": {
    "iso:country":"US",
    "sg:address":"7174 Gourd Branch Rd",
    "sg:city":"Lucama",
    "sg:classifiers":[
        {
            "category":"Professional",
            "subcategory":"Management & Consulting",
            "type":"Services"
        }
    ],
    "sg:phone":"+1 252 239 0866",
    "sg:postcode":"27851",
    "sg:province":"NC",
    "sg:tags":[
        "business"
    ],
    "wof:name":"American Agricultural Services",
    "wof:placetype":"venue"
},
  "geometry": {"coordinates":[-77.986542,35.60593],"type":"Point"}
}