{
  "type": "Feature",
  "properties": {
    "addr:full":"3622 Lyckan Pkwy Durham NC 27707",
    "addr:postcode":"3622;27707",
    "addr:street":"Lyckan Pkwy",
    "iso:country":"US",
    "sg:address":"3622 Lyckan Pkwy",
    "sg:city":"Durham",
    "sg:classifiers":[
        {
            "category":"Professional",
            "subcategory":"Management & Consulting",
            "type":"Services"
        }
    ],
    "sg:phone":"+1   ",
    "sg:postcode":"27707",
    "sg:province":"NC",
    "sg:tags":[
        "environmental",
        "energy",
        "consultant"
    ],
    "wof:name":"E H Pechan",
    "wof:placetype":"venue"
},
  "geometry": {"coordinates":[-78.96354700000001,35.964151],"type":"Point"}
}