{
  "type": "Feature",
  "properties": {
    "iso:country":"US",
    "sg:address":"104 White Cedar Run",
    "sg:city":"Holly Springs",
    "sg:classifiers":[
        {
            "category":"Building & Trades",
            "subcategory":"Construction",
            "type":"Services"
        }
    ],
    "sg:phone":"+1 919 552 8630",
    "sg:postcode":"27540",
    "sg:province":"NC",
    "sg:tags":[
        "contractor"
    ],
    "wof:name":"Fence-Deck-Works",
    "wof:placetype":"venue"
},
  "geometry": {"coordinates":[-78.84004400000001,35.664506],"type":"Point"}
}