{
  "type": "Feature",
  "properties": {
    "iso:country":"US",
    "sg:address":"714 Faircloth St",
    "sg:city":"Raleigh",
    "sg:classifiers":[
        {
            "category":"Education",
            "subcategory":"Special Training",
            "type":"Public Place"
        }
    ],
    "sg:phone":"+1   ",
    "sg:postcode":"27607",
    "sg:province":"NC",
    "wof:name":"Bruce Emery Guitar Studio",
    "wof:placetype":"venue"
},
  "geometry": {"coordinates":[-78.68378199999999,35.799429],"type":"Point"}
}