{
  "type": "Feature",
  "properties": {
    "addr:full":"2731 Capital Blvd Raleigh NC 27604",
    "addr:housenumber":"2731",
    "addr:postcode":"27604",
    "addr:street":"Capital Blvd",
    "iso:country":"US",
    "sg:address":"2731 Capital Blvd",
    "sg:city":"Raleigh",
    "sg:classifiers":[
        {
            "category":"Shopping",
            "subcategory":"Florist",
            "type":"Retail Goods"
        }
    ],
    "sg:phone":"+1 919 872 3333",
    "sg:postcode":"27604",
    "sg:province":"NC",
    "sg:tags":[
        "flower",
        "gift"
    ],
    "sg:website":"www.watkinsflowersofdistinction.com",
    "wof:name":"Watkins Flowers Of Distinction",
    "wof:placetype":"venue"
},
  "geometry": {"coordinates":[-78.60139599999999,35.816534],"type":"Point"}
}