{
  "type": "Feature",
  "properties": {
    "iso:country":"US",
    "sg:address":"3800 Little Mountain Rd",
    "sg:city":"Gastonia",
    "sg:classifiers":[
        {
            "category":"Manufacturing",
            "subcategory":"Metals",
            "type":"Manufacturing & Wholesale Goods"
        }
    ],
    "sg:phone":"+1 704 853 0727",
    "sg:postcode":"28056",
    "sg:province":"NC",
    "sg:tags":[
        "coating",
        "powder"
    ],
    "wof:name":"R & R Powder Coating",
    "wof:placetype":"venue"
},
  "geometry": {"coordinates":[-81.19766199999999,35.208611],"type":"Point"}
}