{
  "type": "Feature",
  "properties": {
    "iso:country":"US",
    "sg:address":"417 Westbury Rd",
    "sg:city":"Charlotte",
    "sg:classifiers":[
        {
            "category":"Utilities",
            "subcategory":"Telephone",
            "type":"Services"
        }
    ],
    "sg:phone":"+1 704 365 1790",
    "sg:postcode":"28211",
    "sg:province":"NC",
    "sg:tags":[
        "application",
        "provider"
    ],
    "wof:name":"Consentsyscom Inc",
    "wof:placetype":"venue"
},
  "geometry": {"coordinates":[-80.802663,35.171838],"type":"Point"}
}