{
  "type": "Feature",
  "properties": {
    "iso:country":"US",
    "sg:address":"501 Windwood on Skye",
    "sg:city":"Fayetteville",
    "sg:classifiers":[
        {
            "category":"Banks & Credit Unions",
            "subcategory":"Financial Services",
            "type":"Services"
        }
    ],
    "sg:phone":"+1 910 483 2711",
    "sg:postcode":"28303",
    "sg:province":"NC",
    "sg:tags":[
        "investor"
    ],
    "wof:name":"Hubbard & Teachey Investments",
    "wof:placetype":"venue"
},
  "geometry": {"coordinates":[-78.93562,35.071828],"type":"Point"}
}