{
  "type": "Feature",
  "properties": {
    "addr:full":"3552 Wilkesboro Hwy Statesville NC 28625",
    "addr:housenumber":"3552",
    "addr:postcode":"28625",
    "addr:street":"Wilkesboro Hwy",
    "iso:country":"US",
    "sg:address":"3552 Wilkesboro Hwy",
    "sg:city":"Statesville",
    "sg:classifiers":[
        {
            "category":"Building & Trades",
            "subcategory":"Construction",
            "type":"Services"
        }
    ],
    "sg:phone":"+1 704 876 2699",
    "sg:postcode":"28625",
    "sg:province":"NC",
    "sg:tags":[
        "maker",
        "cabinet"
    ],
    "wof:name":"Mills Custom Cabinetry",
    "wof:placetype":"venue"
},
  "geometry": {"coordinates":[-80.950816,35.898266],"type":"Point"}
}