{
  "type": "Feature",
  "properties": {
    "iso:country":"US",
    "sg:address":"3612 Bahama Rd",
    "sg:city":"Rougemont",
    "sg:classifiers":[
        {
            "category":"Building & Trades",
            "subcategory":"Electrical",
            "type":"Services"
        }
    ],
    "sg:phone":"+1 866 670 4183",
    "sg:postcode":"27572",
    "sg:province":"NC",
    "sg:tags":[
        "electrician"
    ],
    "wof:name":"Braco Electric Co.",
    "wof:placetype":"venue"
},
  "geometry": {"coordinates":[-78.849777,36.184773],"type":"Point"}
}