{
  "type": "Feature",
  "properties": {
    "addr:full":"1321 Dellwood Rd Waynesville NC 28786",
    "addr:housenumber":"1321",
    "addr:postcode":"28786",
    "addr:street":"Dellwood Rd",
    "iso:country":"US",
    "sg:address":"1321 Dellwood Rd",
    "sg:city":"Waynesville",
    "sg:classifiers":[
        {
            "category":"Autos & Motor Vehicles",
            "subcategory":"Automobile Sales",
            "type":"Retail Goods"
        }
    ],
    "sg:phone":"+1 828 456 6727",
    "sg:postcode":"28786",
    "sg:province":"NC",
    "sg:tags":[
        "car",
        "used",
        "dealer"
    ],
    "wof:name":"S & S Auto Sales",
    "wof:placetype":"venue"
},
  "geometry": {"coordinates":[-82.985422,35.525247],"type":"Point"}
}