{
  "type": "Feature",
  "properties": {
    "addr:full":"311 1st St E Conover NC 28613",
    "addr:housenumber":"311",
    "addr:postcode":"28613",
    "addr:street":"1St St E Conover",
    "iso:country":"US",
    "sg:address":"311 1st St E",
    "sg:city":"Conover",
    "sg:classifiers":[
        {
            "category":"Restaurant",
            "type":"Food & Drink"
        }
    ],
    "sg:phone":"+1 828 465 5536",
    "sg:postcode":"28613",
    "sg:province":"NC",
    "wof:name":"Tienda Y Taqueria LA Fortuna",
    "wof:placetype":"venue"
},
  "geometry": {"coordinates":[-81.215639,35.70496],"type":"Point"}
}