{
  "type": "Feature",
  "properties": {
    "addr:full":"5881 W US Hwy 421 Wilkesboro NC 28697",
    "addr:housenumber":"5881",
    "addr:postcode":"28697",
    "addr:street":"W Us Hwy 421",
    "iso:country":"US",
    "sg:address":"5881 W US Hwy 421",
    "sg:city":"Wilkesboro",
    "sg:classifiers":[
        {
            "category":"Autos & Motor Vehicles",
            "subcategory":"Auto Supplies",
            "type":"Retail Goods"
        }
    ],
    "sg:phone":"+1 336 973 5401",
    "sg:postcode":"28697",
    "sg:province":"NC",
    "sg:tags":[
        "tire"
    ],
    "wof:name":"GCR Tire Ctr",
    "wof:placetype":"venue"
},
  "geometry": {"coordinates":[-81.27328199999999,36.146591],"type":"Point"}
}