{
  "type": "Feature",
  "properties": {
    "iso:country":"US",
    "sg:address":"8410 Six Forks Rd",
    "sg:city":"Raleigh",
    "sg:classifiers":[
        {
            "category":"Professional",
            "subcategory":"Business Services",
            "type":"Services"
        },
        {
            "category":"Wholesale",
            "subcategory":"Motor Vehicles",
            "type":"Manufacturing & Wholesale Goods"
        }
    ],
    "sg:phone":"+1 919 846 9553",
    "sg:postcode":"27615",
    "sg:province":"NC",
    "sg:tags":[
        "automobile",
        "truck",
        "broker",
        "automotive"
    ],
    "wof:name":"The Car Connection",
    "wof:placetype":"venue"
},
  "geometry": {"coordinates":[-78.649062,35.894033],"type":"Point"}
}