{
  "type": "Feature",
  "properties": {
    "iso:country":"US",
    "sg:address":"176 Sunfish Dr",
    "sg:city":"Mooresville",
    "sg:classifiers":[
        {
            "category":"Professional",
            "subcategory":"Management & Consulting",
            "type":"Services"
        }
    ],
    "sg:phone":"+1   ",
    "sg:postcode":"28117",
    "sg:province":"NC",
    "wof:name":"Ph Pool Management",
    "wof:placetype":"venue"
},
  "geometry": {"coordinates":[-80.852396,35.573668],"type":"Point"}
}