{
  "type": "Feature",
  "properties": {
    "iso:country":"US",
    "sg:address":"8137 Market St",
    "sg:city":"Wilmington",
    "sg:classifiers":[
        {
            "category":"Building & Trades",
            "subcategory":"Construction",
            "type":"Services"
        }
    ],
    "sg:phone":"+1 910 686 4061",
    "sg:postcode":"28411",
    "sg:province":"NC",
    "sg:tags":[
        "residential",
        "designer"
    ],
    "wof:name":"Van De Berg & Assoc",
    "wof:placetype":"venue"
},
  "geometry": {"coordinates":[-77.79450300000001,34.296032],"type":"Point"}
}