{
  "type": "Feature",
  "properties": {
    "addr:full":"4201 Fayetteville Rd Raleigh NC 27603",
    "addr:housenumber":"4201",
    "addr:postcode":"27603",
    "addr:street":"Fayetteville Rd",
    "iso:country":"US",
    "sg:address":"4201 Fayetteville Rd",
    "sg:city":"Raleigh",
    "sg:classifiers":[
        {
            "category":"Retail",
            "subcategory":"Repair Shop",
            "type":"Services"
        }
    ],
    "sg:phone":"+1 919 662 7033",
    "sg:postcode":"27603",
    "sg:province":"NC",
    "sg:tags":[
        "television",
        "radio"
    ],
    "wof:name":"Telerent TV Sales & Rentals",
    "wof:placetype":"venue"
},
  "geometry": {"coordinates":[-78.65263899999999,35.722503],"type":"Point"}
}