{
  "type": "Feature",
  "properties": {
    "iso:country":"US",
    "sg:address":"604 Green Valley Rd",
    "sg:city":"Greensboro",
    "sg:classifiers":[
        {
            "category":"Education",
            "subcategory":"Special Training",
            "type":"Public Place"
        }
    ],
    "sg:phone":"+1 336 316 0455",
    "sg:postcode":"27408",
    "sg:province":"NC",
    "sg:tags":[
        "tutoring"
    ],
    "wof:name":"Education Resources",
    "wof:placetype":"venue"
},
  "geometry": {"coordinates":[-79.829399,36.083663],"type":"Point"}
}