{
  "type": "Feature",
  "properties": {
    "iso:country":"US",
    "sg:address":"145 Hubert Blvd",
    "sg:city":"Hubert",
    "sg:classifiers":[
        {
            "category":"Real Estate",
            "subcategory":"Real Estate Operator",
            "type":"Services"
        }
    ],
    "sg:phone":"+1 910 353 3433",
    "sg:postcode":"28539",
    "sg:province":"NC",
    "sg:tags":[
        "mobile",
        "home",
        "community"
    ],
    "wof:name":"Gatlin Mobile Home Park",
    "wof:placetype":"venue"
},
  "geometry": {"coordinates":[-77.25608099999999,34.711766],"type":"Point"}
}