{
  "type": "Feature",
  "properties": {
    "iso:country":"US",
    "sg:address":"5477 State Hwy 24",
    "sg:city":"Newport",
    "sg:classifiers":[
        {
            "category":"Sports & Exercise",
            "subcategory":"Gym",
            "type":"Entertainment"
        }
    ],
    "sg:phone":"+1 252 393 6624",
    "sg:postcode":"28570",
    "sg:province":"NC",
    "sg:tags":[
        "club",
        "health",
        "studio",
        "gymnasium"
    ],
    "wof:name":"Silhouettes",
    "wof:placetype":"venue"
},
  "geometry": {"coordinates":[-77.040824,34.698135],"type":"Point"}
}