{
  "type": "Feature",
  "properties": {
    "addr:full":"3229 South Blvd Rear Charlotte NC 28209",
    "addr:housenumber":"3229",
    "addr:postcode":"28209",
    "addr:street":"South Blvd Rear",
    "iso:country":"US",
    "sg:address":"3229 South Blvd Rear",
    "sg:city":"Charlotte",
    "sg:classifiers":[
        {
            "category":"Building & Trades",
            "subcategory":"Electrical",
            "type":"Services"
        }
    ],
    "sg:phone":"+1 704 529 5782",
    "sg:postcode":"28209",
    "sg:province":"NC",
    "sg:tags":[
        "industrial",
        "electrician",
        "contractors-commercial",
        "electric"
    ],
    "wof:name":"Electric System Specialists Inc",
    "wof:placetype":"venue"
},
  "geometry": {"coordinates":[-80.870971,35.196165],"type":"Point"}
}