{
  "type": "Feature",
  "properties": {
    "iso:country":"US",
    "sg:address":"749 E Fork Rd",
    "sg:city":"Brevard",
    "sg:classifiers":[
        {
            "category":"Travel",
            "subcategory":"Hotels & Motels",
            "type":"Entertainment"
        }
    ],
    "sg:phone":"+1 828 885 7216",
    "sg:postcode":"28712",
    "sg:province":"NC",
    "sg:tags":[
        "chalet",
        "rental",
        "cabin"
    ],
    "wof:name":"Ash Grove Resort Cabins & Cmpg",
    "wof:placetype":"venue"
},
  "geometry": {"coordinates":[-82.706159,35.139706],"type":"Point"}
}