{
  "type": "Feature",
  "properties": {
    "iso:country":"US",
    "sg:address":"6100 Fairview Rd",
    "sg:city":"Charlotte",
    "sg:classifiers":[
        {
            "category":"Professional",
            "type":"Services"
        }
    ],
    "sg:phone":"+1 704 554 9771",
    "sg:postcode":"28210",
    "sg:province":"NC",
    "sg:tags":[
        "establishment"
    ],
    "wof:name":"Jack Morgan Assoc",
    "wof:placetype":"venue"
},
  "geometry": {"coordinates":[-80.837103,35.150807],"type":"Point"}
}