{
  "type": "Feature",
  "properties": {
    "addr:full":"1122 S 13th St Wilmington NC 28401",
    "addr:housenumber":"1122",
    "addr:postcode":"28401",
    "addr:street":"S 13Th St",
    "iso:country":"US",
    "sg:address":"1122 S 13th St",
    "sg:city":"Wilmington",
    "sg:classifiers":[
        {
            "category":"Wholesale",
            "subcategory":"Durable Goods & Equipment",
            "type":"Manufacturing & Wholesale Goods"
        }
    ],
    "sg:phone":"+1 910 762 0065",
    "sg:postcode":"28401",
    "sg:province":"NC",
    "sg:tags":[
        "thermometer"
    ],
    "sg:website":"www.kochmeasurementdevices.com",
    "wof:name":"Koch Measurments Devices Inc",
    "wof:placetype":"venue"
},
  "geometry": {"coordinates":[-77.931179,34.222083],"type":"Point"}
}