{
  "type": "Feature",
  "properties": {
    "addr:full":"2214 Barringer Dr Charlotte NC 28208",
    "addr:housenumber":"2214",
    "addr:postcode":"28208",
    "addr:street":"Barringer Dr",
    "iso:country":"US",
    "sg:address":"2214 Barringer Dr",
    "sg:city":"Charlotte",
    "sg:classifiers":[
        {
            "category":"Building & Trades",
            "subcategory":"Cleaning & Sanitation",
            "type":"Services"
        }
    ],
    "sg:phone":"+1 704 370 0337",
    "sg:postcode":"28208",
    "sg:province":"NC",
    "sg:tags":[
        "window"
    ],
    "wof:name":"Gilbert Forney Window Cleaning",
    "wof:placetype":"venue"
},
  "geometry": {"coordinates":[-80.87384900000001,35.217916],"type":"Point"}
}