{
  "type": "Feature",
  "properties": {
    "iso:country":"US",
    "sg:address":"1601 Nash St E",
    "sg:city":"Wilson",
    "sg:classifiers":[
        {
            "category":"Personal",
            "subcategory":"Beauty Salon",
            "type":"Services"
        }
    ],
    "sg:phone":"+1 252 265 4616",
    "sg:postcode":"27893",
    "sg:province":"NC",
    "wof:name":"Distinctively Yours",
    "wof:placetype":"venue"
},
  "geometry": {"coordinates":[-77.89465800000001,35.715387],"type":"Point"}
}