{
  "type": "Feature",
  "properties": {
    "addr:full":"1555 US Hwy 321 Hickory NC 28601",
    "addr:housenumber":"1555",
    "addr:postcode":"28601",
    "addr:street":"Us Hwy 321",
    "iso:country":"US",
    "sg:address":"1555 US Hwy 321",
    "sg:city":"Hickory",
    "sg:classifiers":[
        {
            "category":"Autos & Motor Vehicles",
            "subcategory":"Automobile Sales",
            "type":"Retail Goods"
        }
    ],
    "sg:phone":"+1 828 324 5040",
    "sg:postcode":"28601",
    "sg:province":"NC",
    "sg:tags":[
        "dealership"
    ],
    "sg:website":"www.nissanofhickory.com",
    "wof:name":"Nissan Of Hickory",
    "wof:placetype":"venue"
},
  "geometry": {"coordinates":[-81.3729,35.753763],"type":"Point"}
}