{
  "type": "Feature",
  "properties": {
    "iso:country":"US",
    "sg:address":"177 Mooreland Rd",
    "sg:city":"Mooresville",
    "sg:classifiers":[
        {
            "category":"Building & Trades",
            "subcategory":"Construction",
            "type":"Services"
        }
    ],
    "sg:phone":"+1 704 799 3748",
    "sg:postcode":"28117",
    "sg:province":"NC",
    "sg:tags":[
        "contractor"
    ],
    "wof:name":"T A P Interior Builders",
    "wof:placetype":"venue"
},
  "geometry": {"coordinates":[-80.871347,35.56844],"type":"Point"}
}