{
  "type": "Feature",
  "properties": {
    "addr:full":"717 Marshall St N Winston Salem NC 27101",
    "addr:housenumber":"717",
    "addr:postcode":"27101",
    "addr:street":"Marshall St N",
    "iso:country":"US",
    "sg:address":"717 Marshall St N",
    "sg:city":"Winston Salem",
    "sg:classifiers":[
        {
            "category":"Professional",
            "subcategory":"Research",
            "type":"Services"
        }
    ],
    "sg:phone":"+1 336 721 0260",
    "sg:postcode":"27101",
    "sg:province":"NC",
    "sg:tags":[
        "foundation",
        "philanthropic"
    ],
    "wof:name":"Blue Ridge Parkway Foundation",
    "wof:placetype":"venue"
},
  "geometry": {"coordinates":[-80.24942799999999,36.104187],"type":"Point"}
}