{
  "type": "Feature",
  "properties": {
    "iso:country":"US",
    "sg:address":"620 University Center Blvd",
    "sg:city":"Charlotte",
    "sg:classifiers":[
        {
            "category":"Restaurant",
            "type":"Food & Drink"
        }
    ],
    "sg:phone":"+1 704 503 7871",
    "sg:postcode":"28262",
    "sg:province":"NC",
    "sg:website":"www.cheddarsnc.com",
    "wof:name":"Cheddars",
    "wof:placetype":"venue"
},
  "geometry": {"coordinates":[-80.755751,35.308356],"type":"Point"}
}