{
  "type": "Feature",
  "properties": {
    "addr:full":"13342 Wesleyan Dr Laurinburg NC 28352",
    "addr:housenumber":"13342",
    "addr:postcode":"28352",
    "addr:street":"Wesleyan Dr",
    "iso:country":"US",
    "sg:address":"13342 Wesleyan Dr",
    "sg:city":"Laurinburg",
    "sg:classifiers":[
        {
            "category":"Professional",
            "type":"Services"
        }
    ],
    "sg:phone":"+1 910 276 2135",
    "sg:postcode":"28352",
    "sg:province":"NC",
    "wof:name":"J R Hoffman",
    "wof:placetype":"venue"
},
  "geometry": {"coordinates":[-79.510068,34.754335],"type":"Point"}
}