{
  "type": "Feature",
  "properties": {
    "addr:full":"453 Oakhurst Rd Asheboro NC 27205",
    "addr:housenumber":"453",
    "addr:postcode":"27205",
    "addr:street":"Oakhurst Rd",
    "iso:country":"US",
    "sg:address":"453 Oakhurst Rd",
    "sg:city":"Asheboro",
    "sg:classifiers":[
        {
            "category":"Home & Garden",
            "subcategory":"Furniture",
            "type":"Retail Goods"
        }
    ],
    "sg:phone":"+1 336 625 6382",
    "sg:postcode":"27205",
    "sg:province":"NC",
    "wof:name":"Klaussner Furniture Industries",
    "wof:placetype":"venue"
},
  "geometry": {"coordinates":[-79.81738799999999,35.655967],"type":"Point"}
}