{
  "type": "Feature",
  "properties": {
    "iso:country":"US",
    "sg:address":"8943 S Tryon St",
    "sg:city":"Charlotte",
    "sg:classifiers":[
        {
            "category":"Real Estate",
            "subcategory":"Real Estate Operator",
            "type":"Services"
        }
    ],
    "sg:phone":"+1 704 504 1372",
    "sg:postcode":"28273",
    "sg:province":"NC",
    "sg:tags":[
        "mall",
        "shopping",
        "center"
    ],
    "wof:name":"Village At Whitehall Shpg Ctr",
    "wof:placetype":"venue"
},
  "geometry": {"coordinates":[-80.939241,35.13453],"type":"Point"}
}