{
  "type": "Feature",
  "properties": {
    "iso:country":"US",
    "sg:address":"805 Greenland Dr",
    "sg:city":"Fayetteville",
    "sg:classifiers":[
        {
            "category":"Building & Trades",
            "subcategory":"Construction",
            "type":"Services"
        }
    ],
    "sg:phone":"+1 910 391 0553",
    "sg:postcode":"28305",
    "sg:province":"NC",
    "sg:tags":[
        "siding",
        "contractor"
    ],
    "wof:name":"Eastern Home Improvement",
    "wof:placetype":"venue"
},
  "geometry": {"coordinates":[-78.906584,35.069391],"type":"Point"}
}