{
  "type": "Feature",
  "properties": {
    "iso:country":"US",
    "sg:address":"963 Brompton Ln",
    "sg:city":"Greenville",
    "sg:classifiers":[
        {
            "category":"Autos & Motor Vehicles",
            "subcategory":"Automobile Sales",
            "type":"Retail Goods"
        }
    ],
    "sg:phone":"+1 252 830 2165",
    "sg:postcode":"27834",
    "sg:province":"NC",
    "sg:tags":[
        "car",
        "dealer"
    ],
    "wof:name":"Wheels N Things Inc",
    "wof:placetype":"venue"
},
  "geometry": {"coordinates":[-77.441576,35.575608],"type":"Point"}
}