{
  "type": "Feature",
  "properties": {
    "addr:full":"2537 E Ash St Goldsboro NC 27534",
    "addr:housenumber":"2537",
    "addr:postcode":"27534",
    "addr:street":"E Ash St",
    "iso:country":"US",
    "sg:address":"2537 E Ash St",
    "sg:city":"Goldsboro",
    "sg:classifiers":[
        {
            "category":"Home & Garden",
            "subcategory":"Building Materials",
            "type":"Retail Goods"
        }
    ],
    "sg:phone":"+1 919 778 0056",
    "sg:postcode":"27534",
    "sg:province":"NC",
    "sg:tags":[
        "paint"
    ],
    "wof:name":"Sherwin-Williams Paints",
    "wof:placetype":"venue"
},
  "geometry": {"coordinates":[-77.95518300000001,35.37329],"type":"Point"}
}