{
  "type": "Feature",
  "properties": {
    "iso:country":"US",
    "sg:address":"412 S Evans St",
    "sg:city":"Greenville",
    "sg:classifiers":[
        {
            "category":"Shopping",
            "subcategory":"Gifts & Souvenirs",
            "type":"Retail Goods"
        }
    ],
    "sg:phone":"+1 252 695 0070",
    "sg:postcode":"27858",
    "sg:province":"NC",
    "sg:tags":[
        "shop"
    ],
    "wof:name":"Links",
    "wof:placetype":"venue"
},
  "geometry": {"coordinates":[-77.373087,35.611295],"type":"Point"}
}