{
  "type": "Feature",
  "properties": {
    "iso:country":"US",
    "sg:address":"4636 Grinding Stone Dr",
    "sg:city":"Raleigh",
    "sg:classifiers":[
        {
            "category":"Arts & Performance",
            "subcategory":"Theater",
            "type":"Entertainment"
        }
    ],
    "sg:phone":"+1   ",
    "sg:postcode":"27604",
    "sg:province":"NC",
    "sg:tags":[
        "group"
    ],
    "wof:name":"Tumblin Dice Inc",
    "wof:placetype":"venue"
},
  "geometry": {"coordinates":[-78.59629700000001,35.843956],"type":"Point"}
}