{
  "type": "Feature",
  "properties": {
    "iso:country":"US",
    "sg:address":"1345 King St",
    "sg:city":"Henderson",
    "sg:classifiers":[
        {
            "category":"Building & Trades",
            "subcategory":"Construction",
            "type":"Services"
        }
    ],
    "sg:phone":"+1 252 492 3483",
    "sg:postcode":"27536",
    "sg:province":"NC",
    "sg:tags":[
        "water",
        "well",
        "drilling"
    ],
    "wof:name":"Brazil Drilling",
    "wof:placetype":"venue"
},
  "geometry": {"coordinates":[-78.39868,36.304387],"type":"Point"}
}