{
  "type": "Feature",
  "properties": {
    "addr:full":"124 Turner St Forest City NC 28043",
    "addr:housenumber":"124",
    "addr:postcode":"28043",
    "addr:street":"Turner St",
    "iso:country":"US",
    "sg:address":"124 Turner St",
    "sg:city":"Forest City",
    "sg:classifiers":[
        {
            "category":"Manufacturing",
            "subcategory":"Petroleum Products",
            "type":"Manufacturing & Wholesale Goods"
        }
    ],
    "sg:phone":"+1 828 245 1271",
    "sg:postcode":"28043",
    "sg:province":"NC",
    "wof:name":"Petroleum World",
    "wof:placetype":"venue"
},
  "geometry": {"coordinates":[-81.882305,35.343996],"type":"Point"}
}