{
  "type": "Feature",
  "properties": {
    "addr:full":"164 Industrial Dr Whiteville NC 28472",
    "addr:housenumber":"164",
    "addr:postcode":"28472",
    "addr:street":"Industrial Dr",
    "iso:country":"US",
    "sg:address":"164 Industrial Dr",
    "sg:city":"Whiteville",
    "sg:classifiers":[
        {
            "category":"Manufacturing",
            "subcategory":"Metals",
            "type":"Manufacturing & Wholesale Goods"
        }
    ],
    "sg:phone":"+1 910 642 2058",
    "sg:postcode":"28472",
    "sg:province":"NC",
    "sg:tags":[
        "pipe",
        "fitting"
    ],
    "wof:name":"Flowline Corp",
    "wof:placetype":"venue"
},
  "geometry": {"coordinates":[-78.71859600000001,34.334381],"type":"Point"}
}