{
  "type": "Feature",
  "properties": {
    "addr:full":"2198 Wallace Family Rd Kinston NC 28501",
    "addr:housenumber":"2198",
    "addr:postcode":"28501",
    "addr:street":"Family Rd",
    "iso:country":"US",
    "sg:address":"2198 Wallace Family Rd",
    "sg:city":"Kinston",
    "sg:classifiers":[
        {
            "category":"Professional",
            "subcategory":"Computer Services",
            "type":"Services"
        }
    ],
    "sg:phone":"+1   ",
    "sg:postcode":"28501",
    "sg:province":"NC",
    "wof:name":"Libertysoft",
    "wof:placetype":"venue"
},
  "geometry": {"coordinates":[-77.54563400000001,35.295592],"type":"Point"}
}