{
  "type": "Feature",
  "properties": {
    "addr:full":"38 Foster Dr Hampstead NC 28472",
    "addr:housenumber":"38",
    "addr:postcode":"28472",
    "addr:street":"Foster Dr",
    "iso:country":"US",
    "sg:address":"38 Foster Dr",
    "sg:city":"Hampstead",
    "sg:classifiers":[
        {
            "category":"Professional",
            "subcategory":"Computer Services",
            "type":"Services"
        }
    ],
    "sg:phone":"+1   ",
    "sg:postcode":"28472",
    "sg:province":"NC",
    "sg:tags":[
        "repair",
        "system"
    ],
    "wof:name":"Heath Services Inc",
    "wof:placetype":"venue"
},
  "geometry": {"coordinates":[-78.77218999999999,34.193124],"type":"Point"}
}