{
  "type": "Feature",
  "properties": {
    "addr:full":"300 Eastowne Dr Chapel Hill NC 27514",
    "addr:housenumber":"300",
    "addr:postcode":"27514",
    "addr:street":"Eastowne Dr",
    "iso:country":"US",
    "sg:address":"300 Eastowne Dr",
    "sg:city":"Chapel Hill",
    "sg:classifiers":[
        {
            "category":"Insurance",
            "subcategory":"Insurance Agent",
            "type":"Services"
        }
    ],
    "sg:phone":"+1 919 968 9511",
    "sg:postcode":"27514",
    "sg:province":"NC",
    "wof:name":"Provident Mutual",
    "wof:placetype":"venue"
},
  "geometry": {"coordinates":[-79.007963,35.949055],"type":"Point"}
}