{
  "type": "Feature",
  "properties": {
    "addr:full":"8005 Pleasant Grove Rd Charlotte NC 28216",
    "addr:housenumber":"8005",
    "addr:postcode":"28216",
    "addr:street":"Pleasant Grove Rd",
    "iso:country":"US",
    "sg:address":"8005 Pleasant Grove Rd",
    "sg:city":"Charlotte",
    "sg:classifiers":[
        {
            "category":"Shopping",
            "subcategory":"Gifts & Souvenirs",
            "type":"Retail Goods"
        }
    ],
    "sg:phone":"+1 704 398 0143",
    "sg:postcode":"28216",
    "sg:province":"NC",
    "wof:name":"By Design Florists & Gifts",
    "wof:placetype":"venue"
},
  "geometry": {"coordinates":[-80.931102,35.308173],"type":"Point"}
}