{
  "type": "Feature",
  "properties": {
    "addr:full":"6327 Albemarle Rd Charlotte NC 28212",
    "addr:housenumber":"6327",
    "addr:postcode":"28212",
    "addr:street":"Albemarle Rd",
    "iso:country":"US",
    "sg:address":"6327 Albemarle Rd",
    "sg:city":"Charlotte",
    "sg:classifiers":[
        {
            "category":"Shopping",
            "subcategory":"Discount & Variety Stores",
            "type":"Retail Goods"
        },
        {
            "category":"Shopping",
            "subcategory":"Department Store",
            "type":"Retail Goods"
        }
    ],
    "sg:phone":"+1 704 531 4694",
    "sg:postcode":"28212",
    "sg:province":"NC",
    "wof:name":"Family Dollar Stores",
    "wof:placetype":"venue"
},
  "geometry": {"coordinates":[-80.735068,35.202901],"type":"Point"}
}