{
  "type": "Feature",
  "properties": {
    "addr:full":"5365 Ballantyne Commons Pkwy Charlotte NC 28277",
    "addr:housenumber":"5365",
    "addr:postcode":"28277",
    "addr:street":"Ballantyne Commons Pkwy",
    "iso:country":"US",
    "sg:address":"5365 Ballantyne Commons Pkwy",
    "sg:city":"Charlotte",
    "sg:classifiers":[
        {
            "category":"Utilities",
            "subcategory":"Mobile Phone",
            "type":"Services"
        },
        {
            "category":"Shopping",
            "subcategory":"Mobile Phones",
            "type":"Retail Goods"
        },
        {
            "category":"Communications",
            "type":"Services"
        }
    ],
    "sg:phone":"+1 704 708 4416",
    "sg:postcode":"28277",
    "sg:province":"NC",
    "sg:tags":[
        "equipment",
        "telephone",
        "cellular",
        "supply"
    ],
    "sg:website":"http://www.nextel.com",
    "wof:name":"Nextel Retail Store",
    "wof:placetype":"venue"
},
  "geometry": {"coordinates":[-80.775108,35.063766],"type":"Point"}
}