{
  "type": "Feature",
  "properties": {
    "iso:country":"US",
    "sg:address":"3158 Hillsborough Rd",
    "sg:city":"Durham",
    "sg:classifiers":[
        {
            "category":"Professional",
            "subcategory":"Business Services",
            "type":"Services"
        }
    ],
    "sg:phone":"+1 919 383 1818",
    "sg:postcode":"27705",
    "sg:province":"NC",
    "sg:tags":[
        "designer",
        "store",
        "planner"
    ],
    "wof:name":"New Era Design & Fixture",
    "wof:placetype":"venue"
},
  "geometry": {"coordinates":[-78.940555,36.017259],"type":"Point"}
}