{
  "type": "Feature",
  "properties": {
    "addr:full":"5360 Hendersonville Rd Fletcher NC 28732",
    "addr:postcode":"5360;28732",
    "addr:street":"Hendersonville Rd",
    "iso:country":"US",
    "sg:address":"5360 Hendersonville Rd",
    "sg:city":"Fletcher",
    "sg:classifiers":[
        {
            "category":"Shopping",
            "subcategory":"Computers & Home Electronics",
            "type":"Retail Goods"
        }
    ],
    "sg:phone":"+1 828 681 0350",
    "sg:postcode":"28732",
    "sg:province":"NC",
    "sg:tags":[
        "equipment",
        "dealer"
    ],
    "wof:name":"Abba Computers",
    "wof:placetype":"venue"
},
  "geometry": {"coordinates":[-82.512551,35.410326],"type":"Point"}
}