{
  "type": "Feature",
  "properties": {
    "addr:full":"2949 Juston Dr Burlington NC 27217",
    "addr:housenumber":"2949",
    "addr:postcode":"27217",
    "addr:street":"Juston Dr",
    "iso:country":"US",
    "sg:address":"2949 Juston Dr",
    "sg:city":"Burlington",
    "sg:classifiers":[
        {
            "category":"Autos & Motor Vehicles",
            "subcategory":"Automobile Sales",
            "type":"Retail Goods"
        }
    ],
    "sg:phone":"+1 336 229 7905",
    "sg:postcode":"27217",
    "sg:province":"NC",
    "sg:tags":[
        "car",
        "dealer"
    ],
    "wof:name":"Ricky Billings Auto Sales Inc",
    "wof:placetype":"venue"
},
  "geometry": {"coordinates":[-79.451425,36.142572],"type":"Point"}
}