{
  "type": "Feature",
  "properties": {
    "iso:country":"US",
    "sg:address":"13431 US Hwy 264",
    "sg:city":"Swanquarter",
    "sg:classifiers":[
        {
            "category":"Insurance",
            "subcategory":"Insurance Agent",
            "type":"Services"
        }
    ],
    "sg:phone":"+1 252 926 9601",
    "sg:postcode":"27885",
    "sg:province":"NC",
    "wof:name":"Hyde County Farm Bureau",
    "wof:placetype":"venue"
},
  "geometry": {"coordinates":[-76.37101699999999,35.451456],"type":"Point"}
}