{
  "type": "Feature",
  "properties": {
    "addr:full":"1671 Ridge Rd Hendersonville NC 28792",
    "addr:housenumber":"1671",
    "addr:postcode":"28792",
    "addr:street":"Ridge Rd",
    "iso:country":"US",
    "sg:address":"1671 Ridge Rd",
    "sg:city":"Hendersonville",
    "sg:classifiers":[
        {
            "category":"Real Estate",
            "subcategory":"Real Estate Operator",
            "type":"Services"
        }
    ],
    "sg:phone":"+1 828 685 7342",
    "sg:postcode":"28792",
    "sg:province":"NC",
    "sg:tags":[
        "property",
        "lessor"
    ],
    "wof:name":"Pines Condo Ho Assn",
    "wof:placetype":"venue"
},
  "geometry": {"coordinates":[-82.364369,35.348806],"type":"Point"}
}