{
  "type": "Feature",
  "properties": {
    "addr:full":"3218 Tyler Finley Way Charlotte NC 28269",
    "addr:housenumber":"3218",
    "addr:postcode":"28269",
    "addr:street":"Tyler Finley Way",
    "iso:country":"US",
    "sg:address":"3218 Tyler Finley Way",
    "sg:city":"Charlotte",
    "sg:classifiers":[
        {
            "category":"Real Estate",
            "subcategory":"Real Estate Services",
            "type":"Services"
        }
    ],
    "sg:phone":"+1 704 688 1000",
    "sg:postcode":"28269",
    "sg:province":"NC",
    "sg:tags":[
        "management",
        "condominium"
    ],
    "wof:name":"Nevin Creek Condominiums",
    "wof:placetype":"venue"
},
  "geometry": {"coordinates":[-80.803876,35.302611],"type":"Point"}
}