{
  "type": "Feature",
  "properties": {
    "addr:full":"44 David Ct Asheville NC 28806",
    "addr:housenumber":"44",
    "addr:postcode":"28806",
    "addr:street":"David Ct",
    "iso:country":"US",
    "sg:address":"44 David Ct",
    "sg:city":"Asheville",
    "sg:classifiers":[
        {
            "category":"Real Estate",
            "subcategory":"Real Estate Operator",
            "type":"Services"
        }
    ],
    "sg:phone":"+1 828 683 5602",
    "sg:postcode":"28806",
    "sg:province":"NC",
    "sg:tags":[
        "mobile",
        "home",
        "community"
    ],
    "wof:name":"Rockwood Mobile Home Community",
    "wof:placetype":"venue"
},
  "geometry": {"coordinates":[-82.633146,35.626057],"type":"Point"}
}