{
  "type": "Feature",
  "properties": {
    "iso:country":"US",
    "sg:address":"419 Latimer Rd",
    "sg:city":"Raleigh",
    "sg:classifiers":[
        {
            "category":"Building & Trades",
            "subcategory":"Construction",
            "type":"Services"
        }
    ],
    "sg:phone":"+1 919 789 4058",
    "sg:postcode":"27609",
    "sg:province":"NC",
    "sg:tags":[
        "hanging",
        "floor",
        "laying",
        "contract",
        "contractor"
    ],
    "wof:name":"Professional Home Groomin",
    "wof:placetype":"venue"
},
  "geometry": {"coordinates":[-78.63130099999999,35.842971],"type":"Point"}
}