{
  "type": "Feature",
  "properties": {
    "iso:country":"US",
    "sg:address":"6416 Albemarle Rd",
    "sg:city":"Charlotte",
    "sg:classifiers":[
        {
            "category":"Restaurant",
            "type":"Food & Drink"
        }
    ],
    "sg:phone":"+1 704 535 1350",
    "sg:postcode":"28212",
    "sg:province":"NC",
    "sg:tags":[
        "eating"
    ],
    "wof:name":"Sunrise Restaurant",
    "wof:placetype":"venue"
},
  "geometry": {"coordinates":[-80.73660599999999,35.202839],"type":"Point"}
}