{
  "type": "Feature",
  "properties": {
    "addr:full":"6620 Neck Rd Huntersville NC 28078",
    "addr:postcode":"6620;28078",
    "addr:street":"Neck Rd",
    "iso:country":"US",
    "sg:address":"6620 Neck Rd",
    "sg:city":"Huntersville",
    "sg:classifiers":[
        {
            "category":"Building & Trades",
            "subcategory":"Landscaping Services",
            "type":"Services"
        }
    ],
    "sg:phone":"+1 704 875 1196",
    "sg:postcode":"28078",
    "sg:province":"NC",
    "wof:name":"Harry & Deborah Lawing",
    "wof:placetype":"venue"
},
  "geometry": {"coordinates":[-80.92021699999999,35.379512],"type":"Point"}
}