{
  "type": "Feature",
  "properties": {
    "addr:full":"2964 State Hwy 24 Newport NC 28570",
    "addr:housenumber":"2964",
    "addr:postcode":"28570",
    "addr:street":"State Hwy 24",
    "iso:country":"US",
    "sg:address":"2964 State Hwy 24",
    "sg:city":"Newport",
    "sg:classifiers":[
        {
            "category":"Manufacturing",
            "subcategory":"Aerospace",
            "type":"Manufacturing & Wholesale Goods"
        }
    ],
    "sg:phone":"+1 252 240 1676",
    "sg:postcode":"28570",
    "sg:province":"NC",
    "sg:tags":[
        "aircraft",
        "component"
    ],
    "wof:name":"Goodrich Aerospace",
    "wof:placetype":"venue"
},
  "geometry": {"coordinates":[-76.93627499999999,34.725529],"type":"Point"}
}