{
  "type": "Feature",
  "properties": {
    "addr:full":"38 Cheulah Rd Brevard SC 28712",
    "addr:housenumber":"38",
    "addr:postcode":"28712",
    "addr:street":"Cheulah Rd",
    "iso:country":"US",
    "sg:address":"38 Cheulah Rd",
    "sg:city":"Brevard",
    "sg:classifiers":[
        {
            "category":"Food & Beverages",
            "subcategory":"Fruits & Vegetables",
            "type":"Retail Goods"
        }
    ],
    "sg:phone":"+1 828 885 2054",
    "sg:postcode":"28712",
    "sg:province":"SC",
    "wof:name":"Queens Produce & Berry Farm",
    "wof:placetype":"venue"
},
  "geometry": {"coordinates":[-82.74018599999999,35.153113],"type":"Point"}
}