{
  "type": "Feature",
  "properties": {
    "iso:country":"US",
    "sg:address":"5237 Albemarle Rd",
    "sg:city":"Charlotte",
    "sg:classifiers":[
        {
            "category":"Education",
            "subcategory":"Dance Studio",
            "type":"Public Place"
        }
    ],
    "sg:phone":"+1 704 563 8693",
    "sg:postcode":"28212",
    "sg:province":"NC",
    "sg:tags":[
        "instruction",
        "dancing"
    ],
    "wof:name":"B B Dance Productions",
    "wof:placetype":"venue"
},
  "geometry": {"coordinates":[-80.75690299999999,35.203046],"type":"Point"}
}