{
  "type": "Feature",
  "properties": {
    "iso:country":"US",
    "sg:address":"1506 E Franklin St Ste 201",
    "sg:city":"Chapel Hill",
    "sg:classifiers":[
        {
            "category":"Banks & Credit Unions",
            "subcategory":"Financial Services",
            "type":"Services"
        }
    ],
    "sg:phone":"+1 919 869 8200",
    "sg:postcode":"27514",
    "sg:province":"NC",
    "sg:tags":[
        "broker",
        "mortgage"
    ],
    "sg:website":"www.carolinahomemortgage.com",
    "wof:name":"Carolina Home Mortgage",
    "wof:placetype":"venue"
},
  "geometry": {"coordinates":[-79.03390899999999,35.929533],"type":"Point"}
}