{
  "type": "Feature",
  "properties": {
    "addr:full":"7607 Holly Grove Ct Charlotte NC 28227",
    "addr:housenumber":"7607",
    "addr:postcode":"28227",
    "addr:street":"Holly Grove Ct",
    "iso:country":"US",
    "sg:address":"7607 Holly Grove Ct",
    "sg:city":"Charlotte",
    "sg:classifiers":[
        {
            "category":"Retail",
            "subcategory":"Auto Repair",
            "type":"Services"
        }
    ],
    "sg:phone":"+1   ",
    "sg:postcode":"28227",
    "sg:province":"NC",
    "sg:tags":[
        "automotive"
    ],
    "wof:name":"Benfield Electric",
    "wof:placetype":"venue"
},
  "geometry": {"coordinates":[-80.70423599999999,35.222031],"type":"Point"}
}