{
  "type": "Feature",
  "properties": {
    "addr:full":"200 Farmwood Dr Statesville NC 28625",
    "addr:housenumber":"200",
    "addr:postcode":"28625",
    "addr:street":"Farmwood Dr",
    "iso:country":"US",
    "sg:address":"200 Farmwood Dr",
    "sg:city":"Statesville",
    "sg:classifiers":[
        {
            "category":"Shopping",
            "subcategory":"Used Merchandise",
            "type":"Retail Goods"
        }
    ],
    "sg:phone":"+1 704 872 4279",
    "sg:postcode":"28625",
    "sg:province":"NC",
    "wof:name":"Martins Equipment",
    "wof:placetype":"venue"
},
  "geometry": {"coordinates":[-80.80779099999999,35.781366],"type":"Point"}
}