{
  "type": "Feature",
  "properties": {
    "iso:country":"US",
    "sg:address":"467 Woodlawn Rd",
    "sg:city":"Mebane",
    "sg:classifiers":[
        {
            "category":"Building & Trades",
            "subcategory":"Plumbing",
            "type":"Services"
        }
    ],
    "sg:phone":"+1 919 563 2959",
    "sg:postcode":"27302",
    "sg:province":"NC",
    "sg:tags":[
        "plumbing",
        "heating",
        "air"
    ],
    "wof:name":"B A Frazier Plumbing Inc",
    "wof:placetype":"venue"
},
  "geometry": {"coordinates":[-79.28968999999999,36.109271],"type":"Point"}
}