{
  "type": "Feature",
  "properties": {
    "addr:full":"1102 Gann St Durham NC 27701",
    "addr:housenumber":"1102",
    "addr:postcode":"27701",
    "addr:street":"Gann St",
    "iso:country":"US",
    "sg:address":"1102 Gann St",
    "sg:city":"Durham",
    "sg:classifiers":[
        {
            "category":"Restaurant",
            "type":"Food & Drink"
        }
    ],
    "sg:phone":"+1 919 667 1889",
    "sg:postcode":"27701",
    "sg:province":"NC",
    "sg:tags":[
        "eating"
    ],
    "wof:name":"Dougs Pub & Grill",
    "wof:placetype":"venue"
},
  "geometry": {"coordinates":[-78.88995300000001,35.983179],"type":"Point"}
}