{
  "type": "Feature",
  "properties": {
    "addr:full":"2601 Iron Gate Dr Wilmington NC 28412",
    "addr:housenumber":"2601",
    "addr:postcode":"28412",
    "addr:street":"Iron Gate Dr",
    "iso:country":"US",
    "sg:address":"2601 Iron Gate Dr",
    "sg:city":"Wilmington",
    "sg:classifiers":[
        {
            "category":"Insurance",
            "subcategory":"Insurance Agent",
            "type":"Services"
        }
    ],
    "sg:phone":"+1 910 794 5100",
    "sg:postcode":"28412",
    "sg:province":"NC",
    "sg:website":"www.gmacinsurance.com",
    "wof:name":"Gmac Insurance",
    "wof:placetype":"venue"
},
  "geometry": {"coordinates":[-77.912312,34.192203],"type":"Point"}
}