{
  "type": "Feature",
  "properties": {
    "addr:full":"3806 N Church St Greensboro NC 27405",
    "addr:housenumber":"3806",
    "addr:postcode":"27405",
    "addr:street":"N Church St",
    "iso:country":"US",
    "sg:address":"3806 N Church St",
    "sg:city":"Greensboro",
    "sg:classifiers":[
        {
            "category":"Restaurant",
            "type":"Food & Drink"
        }
    ],
    "sg:phone":"+1 336 621 3399",
    "sg:postcode":"27405",
    "sg:province":"NC",
    "sg:tags":[
        "eating",
        "pizza"
    ],
    "sg:website":"www.dominos.com",
    "wof:name":"Domino's Pizza",
    "wof:placetype":"venue"
},
  "geometry": {"coordinates":[-79.789512,36.133034],"type":"Point"}
}