{
  "type": "Feature",
  "properties": {
    "addr:full":"101 W Main St Garner NC 27529",
    "addr:housenumber":"101",
    "addr:postcode":"27529",
    "addr:street":"W Main St",
    "iso:country":"US",
    "sg:address":"101 W Main St",
    "sg:city":"Garner",
    "sg:classifiers":[
        {
            "category":"Professional",
            "type":"Services"
        }
    ],
    "sg:phone":"+1 919 779 0017",
    "sg:postcode":"27529",
    "sg:province":"NC",
    "sg:tags":[
        "consultant",
        "geological"
    ],
    "wof:name":"Carolina Geological",
    "wof:placetype":"venue"
},
  "geometry": {"coordinates":[-78.606386,35.707257],"type":"Point"}
}