{
  "type": "Feature",
  "properties": {
    "addr:full":"1104 Ryland Rd Tyner NC 27980",
    "addr:housenumber":"1104",
    "addr:postcode":"27980",
    "addr:street":"Ryland Rd",
    "iso:country":"US",
    "sg:address":"1104 Ryland Rd",
    "sg:city":"Tyner",
    "sg:classifiers":[
        {
            "category":"Freight",
            "type":"Transportation"
        }
    ],
    "sg:phone":"+1 252 297 2266",
    "sg:postcode":"27980",
    "sg:province":"NC",
    "sg:tags":[
        "operator",
        "local",
        "trucking"
    ],
    "wof:name":"Ray Wheeler Warehouse",
    "wof:placetype":"venue"
},
  "geometry": {"coordinates":[-76.570148,36.270777],"type":"Point"}
}