{
  "type": "Feature",
  "properties": {
    "iso:country":"US",
    "sg:address":"79 Parkway Maintenance Rd",
    "sg:city":"Spruce Pine",
    "sg:classifiers":[
        {
            "category":"Organizations",
            "subcategory":"Professional Association",
            "type":"Services"
        }
    ],
    "sg:phone":"+1 828 765 9483",
    "sg:postcode":"28777",
    "sg:province":"NC",
    "sg:tags":[
        "chambers",
        "commerce"
    ],
    "wof:name":"Mitchell Cnty Chamber-Commerce",
    "wof:placetype":"venue"
},
  "geometry": {"coordinates":[-82.052492,35.854888],"type":"Point"}
}