{
  "type": "Feature",
  "properties": {
    "iso:country":"US",
    "sg:address":"500 S Main St",
    "sg:city":"Lexington",
    "sg:classifiers":[
        {
            "category":"Manufacturing",
            "subcategory":"Printing",
            "type":"Manufacturing & Wholesale Goods"
        }
    ],
    "sg:phone":"+1 336 224 6960",
    "sg:postcode":"27292",
    "sg:province":"NC",
    "sg:tags":[
        "publishing"
    ],
    "wof:name":"LSB Uptown Express",
    "wof:placetype":"venue"
},
  "geometry": {"coordinates":[-80.25761300000001,35.820209],"type":"Point"}
}