{
  "type": "Feature",
  "properties": {
    "addr:full":"13 Carolina Ave Carolina Beach NC 28451",
    "addr:housenumber":"13",
    "addr:postcode":"28451",
    "addr:street":"Carolina Ave",
    "iso:country":"US",
    "sg:address":"13 Carolina Ave",
    "sg:city":"Carolina Beach",
    "sg:classifiers":[
        {
            "category":"Shopping",
            "subcategory":"Gifts & Souvenirs",
            "type":"Retail Goods"
        }
    ],
    "sg:phone":"+1 910 799 4356",
    "sg:postcode":"28451",
    "sg:province":"NC",
    "wof:name":"Boardwalk Peddler",
    "wof:placetype":"venue"
},
  "geometry": {"coordinates":[-78.001946,34.233997],"type":"Point"}
}