{
  "type": "Feature",
  "properties": {
    "iso:country":"US",
    "sg:address":"131 Industrial Ave",
    "sg:city":"Greensboro",
    "sg:classifiers":[
        {
            "category":"Professional",
            "subcategory":"Advertising",
            "type":"Services"
        }
    ],
    "sg:phone":"+1 336 379 8420",
    "sg:postcode":"27406",
    "sg:province":"NC",
    "sg:tags":[
        "real",
        "space",
        "commercial",
        "develops",
        "billboard",
        "rental"
    ],
    "wof:name":"Triad Investment Company Inc",
    "wof:placetype":"venue"
},
  "geometry": {"coordinates":[-79.786518,36.029036],"type":"Point"}
}