{
  "type": "Feature",
  "properties": {
    "addr:full":"5312 Virginia Dare Trl Kitty Hawk NC 27949",
    "addr:housenumber":"5312",
    "addr:postcode":"27949",
    "addr:street":"Virginia Dare Trl",
    "iso:country":"US",
    "sg:address":"5312 Virginia Dare Trl",
    "sg:city":"Kitty Hawk",
    "sg:classifiers":[
        {
            "category":"Shopping",
            "subcategory":"Pharmacy",
            "type":"Retail Goods"
        }
    ],
    "sg:phone":"+1 252 261 8900",
    "sg:postcode":"27949",
    "sg:province":"NC",
    "wof:name":"Eckerd",
    "wof:placetype":"venue"
},
  "geometry": {"coordinates":[-75.708471,36.096005],"type":"Point"}
}