{
  "type": "Feature",
  "properties": {
    "addr:full":"1260 Coon Rd Pinnacle NC 27043",
    "addr:housenumber":"1260",
    "addr:postcode":"27043",
    "addr:street":"Coon Rd",
    "iso:country":"US",
    "sg:address":"1260 Coon Rd",
    "sg:city":"Pinnacle",
    "sg:classifiers":[
        {
            "category":"Food & Beverages",
            "subcategory":"Specialty",
            "type":"Retail Goods"
        }
    ],
    "sg:phone":"+1 336 368 4745",
    "sg:postcode":"27043",
    "sg:province":"NC",
    "sg:tags":[
        "herb"
    ],
    "wof:name":"Herbalife Distrubiting",
    "wof:placetype":"venue"
},
  "geometry": {"coordinates":[-80.431781,36.358095],"type":"Point"}
}