{
  "type": "Feature",
  "properties": {
    "iso:country":"US",
    "sg:address":"2630 Dundle Rd",
    "sg:city":"Fayetteville",
    "sg:classifiers":[
        {
            "category":"Building & Trades",
            "subcategory":"Plumbing",
            "type":"Services"
        }
    ],
    "sg:phone":"+1 910 425 0693",
    "sg:postcode":"28306",
    "sg:province":"NC",
    "sg:tags":[
        "contractor"
    ],
    "wof:name":"Plumb Good",
    "wof:placetype":"venue"
},
  "geometry": {"coordinates":[-79.02566299999999,35.003966],"type":"Point"}
}