{
  "type": "Feature",
  "properties": {
    "iso:country":"US",
    "sg:address":"2505 W Front St",
    "sg:city":"Statesville",
    "sg:classifiers":[
        {
            "category":"Autos & Motor Vehicles",
            "subcategory":"Fuel & Gas Station",
            "type":"Retail Goods"
        }
    ],
    "sg:phone":"+1 704 872 0309",
    "sg:postcode":"28677",
    "sg:province":"NC",
    "sg:tags":[
        "towing",
        "station",
        "gasoline",
        "oil"
    ],
    "wof:name":"C & G Towing & Auto Repair",
    "wof:placetype":"venue"
},
  "geometry": {"coordinates":[-80.92933600000001,35.791058],"type":"Point"}
}