{
  "type": "Feature",
  "properties": {
    "iso:country":"US",
    "sg:address":"204 S College St",
    "sg:city":"Morganton",
    "sg:classifiers":[
        {
            "category":"Travel",
            "subcategory":"Hotels & Motels",
            "type":"Entertainment"
        },
        {
            "category":"Travel",
            "subcategory":"Bed & Breakfast",
            "type":"Entertainment"
        }
    ],
    "sg:phone":"+1 828 430 8911",
    "sg:postcode":"28655",
    "sg:province":"NC",
    "sg:tags":[
        "inn",
        "lodging"
    ],
    "wof:name":"College Street Inn",
    "wof:placetype":"venue"
},
  "geometry": {"coordinates":[-81.68897800000001,35.742836],"type":"Point"}
}