{
  "type": "Feature",
  "properties": {
    "iso:country":"US",
    "sg:address":"737 Bennett Farm Rd",
    "sg:city":"Stokesdale",
    "sg:classifiers":[
        {
            "category":"Personal",
            "type":"Services"
        }
    ],
    "sg:phone":"+1   ",
    "sg:postcode":"27357",
    "sg:province":"NC",
    "wof:name":"Oddities",
    "wof:placetype":"venue"
},
  "geometry": {"coordinates":[-79.935362,36.278887],"type":"Point"}
}