{
  "type": "Feature",
  "properties": {
    "iso:country":"US",
    "sg:address":"1731 S Main St",
    "sg:city":"Salisbury",
    "sg:classifiers":[
        {
            "category":"Retail",
            "subcategory":"Repair Shop",
            "type":"Services"
        }
    ],
    "sg:phone":"+1   ",
    "sg:postcode":"28144",
    "sg:province":"NC",
    "sg:tags":[
        "tool",
        "power"
    ],
    "wof:name":"Simmons Power Tool Service",
    "wof:placetype":"venue"
},
  "geometry": {"coordinates":[-80.49229099999999,35.655114],"type":"Point"}
}