{
  "type": "Feature",
  "properties": {
    "addr:full":"8991 US Hwy 19E Elk Park NC 28622",
    "addr:housenumber":"8991",
    "addr:postcode":"28622",
    "addr:street":"Us Hwy 19E Elk Park",
    "iso:country":"US",
    "sg:address":"8991 US Hwy 19E",
    "sg:city":"Elk Park",
    "sg:classifiers":[
        {
            "category":"Personal",
            "subcategory":"Tanning Parlor",
            "type":"Services"
        }
    ],
    "sg:phone":"+1 828 733 1300",
    "sg:postcode":"28622",
    "sg:province":"NC",
    "sg:tags":[
        "salon"
    ],
    "wof:name":"KUT Up-N-Tan",
    "wof:placetype":"venue"
},
  "geometry": {"coordinates":[-81.995105,36.167479],"type":"Point"}
}