{
  "type": "Feature",
  "properties": {
    "iso:country":"US",
    "sg:address":"740 W Burkhead St",
    "sg:city":"Whiteville",
    "sg:classifiers":[
        {
            "category":"Education",
            "subcategory":"Special Training",
            "type":"Public Place"
        }
    ],
    "sg:phone":"+1   ",
    "sg:postcode":"28472",
    "sg:province":"NC",
    "wof:name":"Minister Frink",
    "wof:placetype":"venue"
},
  "geometry": {"coordinates":[-78.717973,34.331679],"type":"Point"}
}