{
  "type": "Feature",
  "properties": {
    "iso:country":"US",
    "sg:address":"9868 US Hwy 311",
    "sg:city":"Archdale",
    "sg:classifiers":[
        {
            "category":"Building & Trades",
            "subcategory":"Plumbing",
            "type":"Services"
        }
    ],
    "sg:phone":"+1 336 434 4682",
    "sg:postcode":"27263",
    "sg:province":"NC",
    "sg:tags":[
        "conditioning",
        "air",
        "system",
        "contractor"
    ],
    "wof:name":"R & R Climate Control",
    "wof:placetype":"venue"
},
  "geometry": {"coordinates":[-79.934291,35.889801],"type":"Point"}
}