{
  "type": "Feature",
  "properties": {
    "addr:full":"2100 New Stock Rd Weaverville NC 28787",
    "addr:housenumber":"2100",
    "addr:postcode":"28787",
    "addr:street":"New Stock Rd",
    "iso:country":"US",
    "sg:address":"2100 New Stock Rd",
    "sg:city":"Weaverville",
    "sg:classifiers":[
        {
            "category":"Real Estate",
            "subcategory":"Real Estate Agent",
            "type":"Services"
        }
    ],
    "sg:phone":"+1 828 645 9346",
    "sg:postcode":"28787",
    "sg:province":"NC",
    "wof:name":"Honeycutt Realty Services",
    "wof:placetype":"venue"
},
  "geometry": {"coordinates":[-82.582857,35.757661],"type":"Point"}
}