{
  "type": "Feature",
  "properties": {
    "iso:country":"US",
    "sg:address":"1221 Corporation Pkwy",
    "sg:city":"Raleigh",
    "sg:classifiers":[
        {
            "category":"Professional",
            "subcategory":"Management & Consulting",
            "type":"Services"
        }
    ],
    "sg:phone":"+1   ",
    "sg:postcode":"27610",
    "sg:province":"NC",
    "wof:name":"Hughes Financial Services Inc",
    "wof:placetype":"venue"
},
  "geometry": {"coordinates":[-78.568364,35.795258],"type":"Point"}
}