{
  "type": "Feature",
  "properties": {
    "addr:full":"309 N Main St Tarboro NC 27886",
    "addr:housenumber":"309",
    "addr:postcode":"27886",
    "addr:street":"N Main St",
    "iso:country":"US",
    "sg:address":"309 N Main St",
    "sg:city":"Tarboro",
    "sg:classifiers":[
        {
            "category":"Professional",
            "subcategory":"Lawyer & Legal Services",
            "type":"Services"
        }
    ],
    "sg:phone":"+1   ",
    "sg:postcode":"27886",
    "sg:province":"NC",
    "sg:tags":[
        "firm",
        "practice",
        "law",
        "general"
    ],
    "wof:name":"Rountree and Boyette",
    "wof:placetype":"venue"
},
  "geometry": {"coordinates":[-77.53459599999999,35.897329],"type":"Point"}
}