{
  "type": "Feature",
  "properties": {
    "addr:full":"1200 E Morehead St Charlotte NC 28204",
    "addr:housenumber":"1200",
    "addr:postcode":"28204",
    "addr:street":"E Morehead St",
    "iso:country":"US",
    "sg:address":"1200 E Morehead St",
    "sg:city":"Charlotte",
    "sg:classifiers":[
        {
            "category":"Building & Trades",
            "subcategory":"Landscaping Services",
            "type":"Services"
        }
    ],
    "sg:phone":"+1 704 372 0927",
    "sg:postcode":"28204",
    "sg:province":"NC",
    "sg:tags":[
        "landscape"
    ],
    "wof:name":"Myron Greer Garden Design",
    "wof:placetype":"venue"
},
  "geometry": {"coordinates":[-80.83963799999999,35.208389],"type":"Point"}
}