{
  "type": "Feature",
  "properties": {
    "addr:full":"6768 Gordon Rd Wilmington NC 28411",
    "addr:housenumber":"6768",
    "addr:postcode":"28411",
    "addr:street":"Gordon Rd",
    "iso:country":"US",
    "sg:address":"6768 Gordon Rd",
    "sg:city":"Wilmington",
    "sg:classifiers":[
        {
            "category":"Personal",
            "type":"Services"
        }
    ],
    "sg:phone":"+1 910 799 9200",
    "sg:postcode":"28411",
    "sg:province":"NC",
    "sg:tags":[
        "therapist",
        "massage"
    ],
    "wof:name":"Wellness Centre",
    "wof:placetype":"venue"
},
  "geometry": {"coordinates":[-77.831621,34.263519],"type":"Point"}
}