{
  "type": "Feature",
  "properties": {
    "iso:country":"US",
    "sg:address":"6600 Idlewild Rd",
    "sg:city":"Charlotte",
    "sg:classifiers":[
        {
            "category":"Building & Trades",
            "subcategory":"Construction",
            "type":"Services"
        }
    ],
    "sg:phone":"+1 704 536 4070",
    "sg:postcode":"28212",
    "sg:province":"NC",
    "sg:tags":[
        "contractor"
    ],
    "wof:name":"Carter L Renovations",
    "wof:placetype":"venue"
},
  "geometry": {"coordinates":[-80.750756,35.183893],"type":"Point"}
}