{
  "type": "Feature",
  "properties": {
    "iso:country":"US",
    "sg:address":"1031 Archdale Dr",
    "sg:city":"Charlotte",
    "sg:classifiers":[
        {
            "category":"Organizations",
            "subcategory":"Membership Organization",
            "type":"Services"
        }
    ],
    "sg:phone":"+1 704 525 4112",
    "sg:postcode":"28217",
    "sg:province":"NC",
    "wof:name":"United Dughters of Confederacy",
    "wof:placetype":"venue"
},
  "geometry": {"coordinates":[-80.883,35.153065],"type":"Point"}
}