{
  "type": "Feature",
  "properties": {
    "addr:full":"1085 Winn Cir Vanceboro NC 28586",
    "addr:housenumber":"1085",
    "addr:postcode":"28586",
    "addr:street":"Winn Cir",
    "iso:country":"US",
    "sg:address":"1085 Winn Cir",
    "sg:city":"Vanceboro",
    "sg:phone":"+1 252 244 2563",
    "sg:postcode":"28586",
    "sg:province":"NC",
    "sg:tags":[
        "equipment",
        "commercial"
    ],
    "wof:name":"Equipment Specialists Inc",
    "wof:placetype":"venue"
},
  "geometry": {"coordinates":[-77.111187,35.243292],"type":"Point"}
}