{
  "type": "Feature",
  "properties": {
    "addr:full":"119 Old Airport Rd Concord NC 28025",
    "addr:housenumber":"119",
    "addr:postcode":"28025",
    "addr:street":"Old Airport Rd",
    "iso:country":"US",
    "sg:address":"119 Old Airport Rd",
    "sg:city":"Concord",
    "sg:classifiers":[
        {
            "category":"Banks & Credit Unions",
            "subcategory":"Financial Services",
            "type":"Services"
        }
    ],
    "sg:phone":"+1 704 782 1402",
    "sg:postcode":"28025",
    "sg:province":"NC",
    "sg:tags":[
        "investor"
    ],
    "wof:name":"Airport Investments LLC",
    "wof:placetype":"venue"
},
  "geometry": {"coordinates":[-80.550451,35.383961],"type":"Point"}
}