{
  "type": "Feature",
  "properties": {
    "addr:full":"3401 Integrity Dr Garner NC 27529",
    "addr:housenumber":"3401",
    "addr:postcode":"27529",
    "addr:street":"Integrity Dr",
    "iso:country":"US",
    "sg:address":"3401 Integrity Dr",
    "sg:city":"Garner",
    "sg:classifiers":[
        {
            "category":"Building & Trades",
            "subcategory":"Equipment Rental",
            "type":"Services"
        }
    ],
    "sg:phone":"+1 919 661 8250",
    "sg:postcode":"27529",
    "sg:province":"NC",
    "sg:tags":[
        "contractor"
    ],
    "sg:website":"www.unitedrentals.com",
    "wof:name":"United Rentals Aerial Equip",
    "wof:placetype":"venue"
},
  "geometry": {"coordinates":[-78.583106,35.727597],"type":"Point"}
}