{
  "type": "Feature",
  "properties": {
    "iso:country":"US",
    "sg:address":"305 W Roseboro St",
    "sg:city":"Roseboro",
    "sg:classifiers":[
        {
            "category":"Health Services",
            "subcategory":"Optometrist",
            "type":"Services"
        }
    ],
    "sg:phone":"+1 910 525 5296",
    "sg:postcode":"28382",
    "sg:province":"NC",
    "wof:name":"Professional Eye Care",
    "wof:placetype":"venue"
},
  "geometry": {"coordinates":[-78.51271300000001,34.952061],"type":"Point"}
}