{
  "type": "Feature",
  "properties": {
    "iso:country":"US",
    "sg:address":"5586 US Hwy 401 N",
    "sg:city":"Fuquay Varina",
    "sg:classifiers":[
        {
            "category":"Building & Trades",
            "subcategory":"Construction",
            "type":"Services"
        }
    ],
    "sg:phone":"+1 919 557 4700",
    "sg:postcode":"27526",
    "sg:province":"NC",
    "sg:tags":[
        "concrete",
        "waterproofing",
        "contractor"
    ],
    "wof:name":"Vision Specialty Coatings",
    "wof:placetype":"venue"
},
  "geometry": {"coordinates":[-78.828337,35.466202],"type":"Point"}
}