{
  "type": "Feature",
  "properties": {
    "addr:full":"1510 Dellwood Rd Waynesville NC 28786",
    "addr:housenumber":"1510",
    "addr:postcode":"28786",
    "addr:street":"Dellwood Rd",
    "iso:country":"US",
    "sg:address":"1510 Dellwood Rd",
    "sg:city":"Waynesville",
    "sg:classifiers":[
        {
            "category":"Home & Garden",
            "subcategory":"Furniture",
            "type":"Retail Goods"
        }
    ],
    "sg:phone":"+1 828 926 3999",
    "sg:postcode":"28786",
    "sg:province":"NC",
    "sg:tags":[
        "cabinet"
    ],
    "wof:name":"Cabinet Art Inc",
    "wof:placetype":"venue"
},
  "geometry": {"coordinates":[-82.993679,35.526323],"type":"Point"}
}