{
  "type": "Feature",
  "properties": {
    "iso:country":"US",
    "sg:address":"3401 Pineville Matthews Rd",
    "sg:city":"Charlotte",
    "sg:classifiers":[
        {
            "category":"Shopping",
            "subcategory":"Pets & Pet Supplies",
            "type":"Retail Goods"
        },
        {
            "category":"Retail",
            "subcategory":"Animal Services",
            "type":"Services"
        },
        {
            "category":"Museum",
            "subcategory":"Aquarium",
            "type":"Entertainment"
        }
    ],
    "sg:phone":"+1 704 541 2473",
    "sg:postcode":"28226",
    "sg:province":"NC",
    "sg:tags":[
        "food",
        "dog",
        "cat",
        "furnishing",
        "grooming",
        "store"
    ],
    "sg:website":"http://www.petco.com",
    "wof:name":"PETCO",
    "wof:placetype":"venue"
},
  "geometry": {"coordinates":[-80.786446,35.096851],"type":"Point"}
}