{
  "type": "Feature",
  "properties": {
    "addr:full":"443 Farless Rd Merry Hill NC 27957",
    "addr:housenumber":"443",
    "addr:postcode":"27957",
    "addr:street":"Farless Rd",
    "iso:country":"US",
    "sg:address":"443 Farless Rd",
    "sg:city":"Merry Hill",
    "sg:phone":"+1 252 356 4481",
    "sg:postcode":"27957",
    "sg:province":"NC",
    "sg:tags":[
        "farm",
        "field",
        "corn",
        "tobacco",
        "crop"
    ],
    "wof:name":"Carlton Hughes",
    "wof:placetype":"venue"
},
  "geometry": {"coordinates":[-76.785985,36.09405],"type":"Point"}
}