{
  "type": "Feature",
  "properties": {
    "addr:full":"5067 Shattalon Dr Winston Salem NC 27106",
    "addr:housenumber":"5067",
    "addr:postcode":"27106",
    "addr:street":"Shattalon Dr",
    "iso:country":"US",
    "sg:address":"5067 Shattalon Dr",
    "sg:city":"Winston Salem",
    "sg:classifiers":[
        {
            "category":"Building & Trades",
            "subcategory":"Landscaping Services",
            "type":"Services"
        }
    ],
    "sg:phone":"+1 336 922 3151",
    "sg:postcode":"27106",
    "sg:province":"NC",
    "wof:name":"James G Redmon",
    "wof:placetype":"venue"
},
  "geometry": {"coordinates":[-80.32021899999999,36.171207],"type":"Point"}
}