{
  "type": "Feature",
  "properties": {
    "iso:country":"US",
    "sg:address":"169 Wooten Farm Rd",
    "sg:city":"Statesville",
    "sg:classifiers":[
        {
            "category":"Professional",
            "subcategory":"Advertising",
            "type":"Services"
        }
    ],
    "sg:phone":"+1 704 871 2742",
    "sg:postcode":"28625",
    "sg:province":"NC",
    "sg:website":"www.flagshippromotional.com",
    "wof:name":"Flagship Promotional Products",
    "wof:placetype":"venue"
},
  "geometry": {"coordinates":[-80.7967,35.844384],"type":"Point"}
}