{
  "type": "Feature",
  "properties": {
    "addr:full":"937 Country Club Rd Salemburg NC 28385",
    "addr:housenumber":"937",
    "addr:postcode":"28385",
    "addr:street":"Country Club Rd",
    "iso:country":"US",
    "sg:address":"937 Country Club Rd",
    "sg:city":"Salemburg",
    "sg:classifiers":[
        {
            "category":"Retail",
            "subcategory":"Repair Shop",
            "type":"Services"
        }
    ],
    "sg:phone":"+1   ",
    "sg:postcode":"28385",
    "sg:province":"NC",
    "wof:name":"Vander Septic Tank & Supply Co",
    "wof:placetype":"venue"
},
  "geometry": {"coordinates":[-78.493669,34.978021],"type":"Point"}
}