{
  "type": "Feature",
  "properties": {
    "iso:country":"US",
    "sg:address":"3811 State Hwy 18",
    "sg:city":"Vale",
    "sg:classifiers":[
        {
            "category":"Restaurant",
            "type":"Food & Drink"
        }
    ],
    "sg:phone":"+1 704 462 1381",
    "sg:postcode":"28168",
    "sg:province":"NC",
    "wof:name":"Tri-County Music Bar & Grill",
    "wof:placetype":"venue"
},
  "geometry": {"coordinates":[-81.508105,35.575657],"type":"Point"}
}