{
  "type": "Feature",
  "properties": {
    "iso:country":"US",
    "sg:address":"1235 East Blvd",
    "sg:city":"Charlotte",
    "sg:classifiers":[
        {
            "category":"Personal",
            "subcategory":"Beauty Salon",
            "type":"Services"
        }
    ],
    "sg:phone":"+1 704 373 9764",
    "sg:postcode":"28203",
    "sg:province":"NC",
    "wof:name":"Sass & Class Hair Salon",
    "wof:placetype":"venue"
},
  "geometry": {"coordinates":[-80.84681500000001,35.203542],"type":"Point"}
}