{
  "type": "Feature",
  "properties": {
    "addr:full":"1815 N Chatham Ave Siler City NC 27344",
    "addr:housenumber":"1815",
    "addr:postcode":"27344",
    "addr:street":"N Chatham Ave",
    "iso:country":"US",
    "sg:address":"1815 N Chatham Ave",
    "sg:city":"Siler City",
    "sg:classifiers":[
        {
            "category":"Government",
            "subcategory":"Office",
            "type":"Public Place"
        }
    ],
    "sg:phone":"+1 919 663 5544",
    "sg:postcode":"27344",
    "sg:province":"NC",
    "sg:tags":[
        "village"
    ],
    "wof:name":"Siler City Town",
    "wof:placetype":"venue"
},
  "geometry": {"coordinates":[-79.476567,35.737376],"type":"Point"}
}