{
  "type": "Feature",
  "properties": {
    "addr:full":"7323 Dallas Cherryville Hwy Cherryville NC 28021",
    "addr:housenumber":"7323",
    "addr:postcode":"28021",
    "addr:street":"Dallas Cherryville Hwy",
    "iso:country":"US",
    "sg:address":"7323 Dallas Cherryville Hwy",
    "sg:city":"Cherryville",
    "sg:classifiers":[
        {
            "category":"Retail",
            "subcategory":"Repair Shop",
            "type":"Services"
        }
    ],
    "sg:phone":"+1   ",
    "sg:postcode":"28021",
    "sg:province":"NC",
    "sg:tags":[
        "electrical"
    ],
    "wof:name":"Curds Electrical Contracting",
    "wof:placetype":"venue"
},
  "geometry": {"coordinates":[-81.34197,35.381042],"type":"Point"}
}