{
  "type": "Feature",
  "properties": {
    "addr:full":"6910 Fayetteville Rd Durham NC 27713",
    "addr:housenumber":"6910",
    "addr:postcode":"27713",
    "addr:street":"Fayetteville Rd",
    "iso:country":"US",
    "sg:address":"6910 Fayetteville Rd",
    "sg:city":"Durham",
    "sg:classifiers":[
        {
            "category":"Shopping",
            "subcategory":"Jewelry",
            "type":"Retail Goods"
        }
    ],
    "sg:phone":"+1 919 484 0001",
    "sg:postcode":"27713",
    "sg:province":"NC",
    "wof:name":"White Buffalo",
    "wof:placetype":"venue"
},
  "geometry": {"coordinates":[-78.939689,35.90189],"type":"Point"}
}