{
  "type": "Feature",
  "properties": {
    "addr:full":"3103 Indian Rock Rd Charlotte NC 28270",
    "addr:housenumber":"3103",
    "addr:postcode":"28270",
    "addr:street":"Indian Rock Rd",
    "iso:country":"US",
    "sg:address":"3103 Indian Rock Rd",
    "sg:city":"Charlotte",
    "sg:classifiers":[
        {
            "category":"Professional",
            "subcategory":"Business Services",
            "type":"Services"
        }
    ],
    "sg:phone":"+1   ",
    "sg:postcode":"28270",
    "sg:province":"NC",
    "wof:name":"Wall Ventures Ltd Partnership",
    "wof:placetype":"venue"
},
  "geometry": {"coordinates":[-80.75420699999999,35.084171],"type":"Point"}
}