{
  "type": "Feature",
  "properties": {
    "addr:full":"3561 S Church St Burlington NC 27215",
    "addr:housenumber":"3561",
    "addr:postcode":"27215",
    "addr:street":"S Church St",
    "iso:country":"US",
    "sg:address":"3561 S Church St",
    "sg:city":"Burlington",
    "sg:classifiers":[
        {
            "category":"Shopping",
            "subcategory":"Pharmacy",
            "type":"Retail Goods"
        }
    ],
    "sg:phone":"+1 336 584 3374",
    "sg:postcode":"27215",
    "sg:province":"NC",
    "sg:tags":[
        "drug",
        "store"
    ],
    "wof:name":"Eckerd",
    "wof:placetype":"venue"
},
  "geometry": {"coordinates":[-79.52145299999999,36.080389],"type":"Point"}
}