{
  "type": "Feature",
  "properties": {
    "iso:country":"US",
    "sg:address":"2120 N Sharon Amity Rd",
    "sg:city":"Charlotte",
    "sg:classifiers":[
        {
            "category":"Personal",
            "subcategory":"Beauty Salon",
            "type":"Services"
        }
    ],
    "sg:phone":"+1 704 569 4796",
    "sg:postcode":"28205",
    "sg:province":"NC",
    "sg:tags":[
        "shop"
    ],
    "wof:name":"E Z Y Team Braids",
    "wof:placetype":"venue"
},
  "geometry": {"coordinates":[-80.77168500000001,35.190494],"type":"Point"}
}