{
  "type": "Feature",
  "properties": {
    "iso:country":"US",
    "sg:address":"1910 Derita Rd",
    "sg:city":"Concord",
    "sg:classifiers":[
        {
            "category":"Shopping",
            "subcategory":"Computers & Home Electronics",
            "type":"Retail Goods"
        }
    ],
    "sg:phone":"+1 704 782 3807",
    "sg:postcode":"28027",
    "sg:province":"NC",
    "sg:tags":[
        "equipment",
        "dealer"
    ],
    "sg:website":"www.avocent.com",
    "wof:name":"Avocent Corp",
    "wof:placetype":"venue"
},
  "geometry": {"coordinates":[-80.719534,35.387933],"type":"Point"}
}