{
  "type": "Feature",
  "properties": {
    "iso:country":"US",
    "sg:address":"121 E Wade St",
    "sg:city":"Wadesboro",
    "sg:classifiers":[
        {
            "category":"Utilities",
            "subcategory":"Mobile Phone",
            "type":"Services"
        }
    ],
    "sg:phone":"+1 704 695 0671",
    "sg:postcode":"28170",
    "sg:province":"NC",
    "sg:tags":[
        "telephone",
        "cellular"
    ],
    "wof:name":"Mobile Xpress Inc",
    "wof:placetype":"venue"
},
  "geometry": {"coordinates":[-80.07665299999999,34.966201],"type":"Point"}
}