{
  "type": "Feature",
  "properties": {
    "addr:full":"12809 Asbury Chapel Rd Huntersville NC 28078",
    "addr:housenumber":"12809",
    "addr:postcode":"28078",
    "addr:street":"Asbury Chapel Rd",
    "iso:country":"US",
    "sg:address":"12809 Asbury Chapel Rd",
    "sg:city":"Huntersville",
    "sg:classifiers":[
        {
            "category":"Professional",
            "subcategory":"Business Services",
            "type":"Services"
        }
    ],
    "sg:phone":"+1   ",
    "sg:postcode":"28078",
    "sg:province":"NC",
    "wof:name":"Lackey Enterprises Inc",
    "wof:placetype":"venue"
},
  "geometry": {"coordinates":[-80.80340099999999,35.398762],"type":"Point"}
}