{
  "type": "Feature",
  "properties": {
    "addr:full":"310 Carriage House Ln Enfield NC 27823",
    "addr:housenumber":"310",
    "addr:postcode":"27823",
    "addr:street":"Carriage House Ln",
    "iso:country":"US",
    "sg:address":"310 Carriage House Ln",
    "sg:city":"Enfield",
    "sg:classifiers":[
        {
            "category":"Real Estate",
            "subcategory":"Real Estate Operator",
            "type":"Services"
        }
    ],
    "sg:phone":"+1 252 445 5996",
    "sg:postcode":"27823",
    "sg:province":"NC",
    "sg:tags":[
        "apartment"
    ],
    "wof:name":"Carriage House Apartments",
    "wof:placetype":"venue"
},
  "geometry": {"coordinates":[-77.67049299999999,36.170636],"type":"Point"}
}