{
  "type": "Feature",
  "properties": {
    "addr:full":"209 Macedonia Church Rd Sparta NC 28675",
    "addr:housenumber":"209",
    "addr:postcode":"28675",
    "addr:street":"Macedonia Church Rd",
    "iso:country":"US",
    "sg:address":"209 Macedonia Church Rd",
    "sg:city":"Sparta",
    "sg:classifiers":[
        {
            "category":"Building & Trades",
            "subcategory":"Construction",
            "type":"Services"
        }
    ],
    "sg:phone":"+1 336 372 6202",
    "sg:postcode":"28675",
    "sg:province":"NC",
    "sg:tags":[
        "general",
        "contractor"
    ],
    "wof:name":"Wagoner Construction",
    "wof:placetype":"venue"
},
  "geometry": {"coordinates":[-81.08807400000001,36.482167],"type":"Point"}
}