{
  "type": "Feature",
  "properties": {
    "addr:full":"2510 Walker Rd Mt Pleasant NC 28124",
    "addr:housenumber":"2510",
    "addr:postcode":"28124",
    "addr:street":"Walker Rd",
    "iso:country":"US",
    "sg:address":"2510 Walker Rd",
    "sg:city":"Mt Pleasant",
    "sg:classifiers":[
        {
            "category":"Professional",
            "subcategory":"Engineering",
            "type":"Services"
        }
    ],
    "sg:phone":"+1 704 788 4455",
    "sg:postcode":"28124",
    "sg:province":"NC",
    "sg:tags":[
        "engineer"
    ],
    "wof:name":"Horizon Engineering & Consltng",
    "wof:placetype":"venue"
},
  "geometry": {"coordinates":[-80.486259,35.383393],"type":"Point"}
}