{
  "type": "Feature",
  "properties": {
    "addr:full":"3330 E Wendover Ave Greensboro NC 27405",
    "addr:housenumber":"3330",
    "addr:postcode":"27405",
    "addr:street":"E Wendover Ave",
    "iso:country":"US",
    "sg:address":"3330 E Wendover Ave",
    "sg:city":"Greensboro",
    "sg:classifiers":[
        {
            "category":"Freight",
            "type":"Transportation"
        }
    ],
    "sg:phone":"+1 336 375 3332",
    "sg:postcode":"27405",
    "sg:province":"NC",
    "sg:tags":[
        "trucking"
    ],
    "wof:name":"Premier Transportation",
    "wof:placetype":"venue"
},
  "geometry": {"coordinates":[-79.73773799999999,36.087524],"type":"Point"}
}