{
  "type": "Feature",
  "properties": {
    "iso:country":"US",
    "sg:address":"570 Forlines Rd",
    "sg:city":"Winterville",
    "sg:classifiers":[
        {
            "category":"Education",
            "subcategory":"School",
            "type":"Public Place"
        }
    ],
    "sg:phone":"+1 252 321 3232",
    "sg:postcode":"28590",
    "sg:province":"NC",
    "wof:name":"South Central High School",
    "wof:placetype":"venue"
},
  "geometry": {"coordinates":[-77.43319200000001,35.540877],"type":"Point"}
}