{
  "type": "Feature",
  "properties": {
    "iso:country":"US",
    "sg:address":"3816 Waynoka Dr",
    "sg:city":"Greensboro",
    "sg:classifiers":[
        {
            "category":"Shopping",
            "subcategory":"Music",
            "type":"Retail Goods"
        }
    ],
    "sg:phone":"+1 336 402 2436",
    "sg:postcode":"27410",
    "sg:province":"NC",
    "wof:name":"Tehillah Music",
    "wof:placetype":"venue"
},
  "geometry": {"coordinates":[-79.872384,36.122214],"type":"Point"}
}