{
  "type": "Feature",
  "properties": {
    "addr:full":"304 Rainbow Way Durham NC 27707",
    "addr:housenumber":"304",
    "addr:postcode":"27707",
    "addr:street":"Rainbow Way",
    "iso:country":"US",
    "sg:address":"304 Rainbow Way",
    "sg:city":"Durham",
    "sg:classifiers":[
        {
            "category":"Building & Trades",
            "subcategory":"Construction",
            "type":"Services"
        }
    ],
    "sg:phone":"+1 919 493 9738",
    "sg:postcode":"27707",
    "sg:province":"NC",
    "sg:tags":[
        "house"
    ],
    "wof:name":"Andrew Imlay Construction",
    "wof:placetype":"venue"
},
  "geometry": {"coordinates":[-78.925039,35.976277],"type":"Point"}
}