{
  "type": "Feature",
  "properties": {
    "addr:full":"408 E Spring St Wake Forest NC 27587",
    "addr:housenumber":"408",
    "addr:postcode":"27587",
    "addr:street":"E Spring St",
    "iso:country":"US",
    "sg:address":"408 E Spring St",
    "sg:city":"Wake Forest",
    "sg:classifiers":[
        {
            "category":"Professional",
            "subcategory":"Management & Consulting",
            "type":"Services"
        }
    ],
    "sg:phone":"+1 919 570 3300",
    "sg:postcode":"27587",
    "sg:province":"NC",
    "sg:tags":[
        "consultant"
    ],
    "wof:name":"Acer Consulting",
    "wof:placetype":"venue"
},
  "geometry": {"coordinates":[-78.50482,35.980132],"type":"Point"}
}