{
  "type": "Feature",
  "properties": {
    "iso:country":"US",
    "sg:address":"664 W King St",
    "sg:city":"Boone",
    "sg:classifiers":[
        {
            "category":"Restaurant",
            "type":"Food & Drink"
        }
    ],
    "sg:phone":"+1 828 268 1550",
    "sg:postcode":"28607",
    "sg:province":"NC",
    "sg:tags":[
        "grocery",
        "eating"
    ],
    "wof:name":"Ham Shoppes Corner Deli",
    "wof:placetype":"venue"
},
  "geometry": {"coordinates":[-81.68444100000001,36.219073],"type":"Point"}
}