{
  "type": "Feature",
  "properties": {
    "addr:full":"608 Eva Cir Spring Lake NC 28390",
    "addr:housenumber":"608",
    "addr:postcode":"28390",
    "addr:street":"Eva Cir",
    "iso:country":"US",
    "sg:address":"608 Eva Cir",
    "sg:city":"Spring Lake",
    "sg:classifiers":[
        {
            "category":"Professional",
            "subcategory":"Management & Consulting",
            "type":"Services"
        }
    ],
    "sg:phone":"+1   ",
    "sg:postcode":"28390",
    "sg:province":"NC",
    "sg:tags":[
        "business"
    ],
    "wof:name":"Sarrah B Beins",
    "wof:placetype":"venue"
},
  "geometry": {"coordinates":[-78.971768,35.17472],"type":"Point"}
}