{
  "type": "Feature",
  "properties": {
    "addr:full":"4939 Bragg Blvd Fayetteville NC 28303",
    "addr:housenumber":"4939",
    "addr:postcode":"28303",
    "addr:street":"Bragg Blvd",
    "iso:country":"US",
    "sg:address":"4939 Bragg Blvd",
    "sg:city":"Fayetteville",
    "sg:classifiers":[
        {
            "category":"Government",
            "subcategory":"Office",
            "type":"Public Place"
        }
    ],
    "sg:phone":"+1 910 485 8370",
    "sg:postcode":"28303",
    "sg:province":"NC",
    "wof:name":"Extension Of Life",
    "wof:placetype":"venue"
},
  "geometry": {"coordinates":[-78.95505799999999,35.093167],"type":"Point"}
}