{
  "type": "Feature",
  "properties": {
    "iso:country":"US",
    "sg:address":"5457 Central Ave",
    "sg:city":"Charlotte",
    "sg:classifiers":[
        {
            "category":"Shopping",
            "subcategory":"Shoes",
            "type":"Retail Goods"
        }
    ],
    "sg:phone":"+1 704 568 4858",
    "sg:postcode":"28212",
    "sg:province":"NC",
    "sg:website":"www.hibbett.com",
    "wof:name":"Hibbett Sporting Goods Inc",
    "wof:placetype":"venue"
},
  "geometry": {"coordinates":[-80.753512,35.207779],"type":"Point"}
}