{
  "type": "Feature",
  "properties": {
    "addr:full":"440 Oak St Highlands NC 28741",
    "addr:housenumber":"440",
    "addr:postcode":"28741",
    "addr:street":"Oak St",
    "iso:country":"US",
    "sg:address":"440 Oak St",
    "sg:city":"Highlands",
    "sg:classifiers":[
        {
            "category":"Professional",
            "subcategory":"Accounting & Tax Preparation",
            "type":"Services"
        }
    ],
    "sg:phone":"+1 828 526 2399",
    "sg:postcode":"28741",
    "sg:province":"NC",
    "sg:tags":[
        "accountant"
    ],
    "wof:name":"Lucas & Co",
    "wof:placetype":"venue"
},
  "geometry": {"coordinates":[-83.19607999999999,35.052883],"type":"Point"}
}