{
  "type": "Feature",
  "properties": {
    "iso:country":"US",
    "sg:address":"219 S Garnett St",
    "sg:city":"Henderson",
    "sg:classifiers":[
        {
            "category":"Restaurant",
            "type":"Food & Drink"
        }
    ],
    "sg:phone":"+1 252 438 2093",
    "sg:postcode":"27536",
    "sg:province":"NC",
    "wof:name":"Soul Delicious",
    "wof:placetype":"venue"
},
  "geometry": {"coordinates":[-78.40371500000001,36.326554],"type":"Point"}
}