{
  "type": "Feature",
  "properties": {
    "iso:country":"US",
    "sg:address":"5013 Rollingwood Dr",
    "sg:city":"Durham",
    "sg:classifiers":[
        {
            "category":"Building & Trades",
            "subcategory":"Construction",
            "type":"Services"
        }
    ],
    "sg:phone":"+1 919 493 8561",
    "sg:postcode":"27713",
    "sg:province":"NC",
    "sg:tags":[
        "painter"
    ],
    "wof:name":"Bennett Painting",
    "wof:placetype":"venue"
},
  "geometry": {"coordinates":[-78.940631,35.912256],"type":"Point"}
}