{
  "type": "Feature",
  "properties": {
    "iso:country":"US",
    "sg:address":"6673 High Rock Rd",
    "sg:city":"Browns Summit",
    "sg:phone":"+1 336 656 3462",
    "sg:postcode":"27214",
    "sg:province":"NC",
    "sg:tags":[
        "farm",
        "tobacco"
    ],
    "wof:name":"Johnny Brown",
    "wof:placetype":"venue"
},
  "geometry": {"coordinates":[-79.582188,36.212738],"type":"Point"}
}