{
  "type": "Feature",
  "properties": {
    "addr:full":"1001 Blythe Blvd Ste 200 Charlotte NC 28203",
    "addr:housenumber":"1001",
    "addr:postcode":"28203",
    "addr:street":"Blythe Blvd Ste 200",
    "iso:country":"US",
    "sg:address":"1001 Blythe Blvd Ste 200",
    "sg:city":"Charlotte",
    "sg:classifiers":[
        {
            "category":"Health Services",
            "subcategory":"Doctor",
            "type":"Services"
        }
    ],
    "sg:phone":"+1 704 373 0544",
    "sg:postcode":"28203",
    "sg:province":"NC",
    "sg:tags":[
        "physician",
        "pediatrics-orthopedic",
        "surgeons",
        "orthopedics",
        "surgery",
        "surgeon"
    ],
    "wof:name":"Robert B Anderson Md",
    "wof:placetype":"venue"
},
  "geometry": {"coordinates":[-80.837388,35.203678],"type":"Point"}
}