{
  "type": "Feature",
  "properties": {
    "iso:country":"US",
    "sg:address":"59 Hackley Rd",
    "sg:city":"Gates",
    "sg:classifiers":[
        {
            "category":"Professional",
            "subcategory":"Management & Consulting",
            "type":"Services"
        }
    ],
    "sg:phone":"+1 252 357 2800",
    "sg:postcode":"27937",
    "sg:province":"NC",
    "sg:tags":[
        "consultant"
    ],
    "wof:name":"Stallings Consulting Svc Inc",
    "wof:placetype":"venue"
},
  "geometry": {"coordinates":[-76.783546,36.446838],"type":"Point"}
}