{
  "type": "Feature",
  "properties": {
    "iso:country":"US",
    "sg:address":"5132 Foxbriar Trl",
    "sg:city":"Charlotte",
    "sg:classifiers":[
        {
            "category":"Building & Trades",
            "subcategory":"Construction",
            "type":"Services"
        }
    ],
    "sg:phone":"+1 704 634 4456",
    "sg:postcode":"28269",
    "sg:province":"NC",
    "sg:tags":[
        "general"
    ],
    "wof:name":"Taylor Home of Charlotte LLC",
    "wof:placetype":"venue"
},
  "geometry": {"coordinates":[-80.815167,35.342074],"type":"Point"}
}