{
  "type": "Feature",
  "properties": {
    "addr:full":"407 N McArthur St Elizabeth City NC 27909",
    "addr:housenumber":"407",
    "addr:postcode":"27909",
    "addr:street":"N Mcarthur St",
    "iso:country":"US",
    "sg:address":"407 N McArthur St",
    "sg:city":"Elizabeth City",
    "sg:classifiers":[
        {
            "category":"Shopping",
            "subcategory":"Florist",
            "type":"Retail Goods"
        }
    ],
    "sg:phone":"+1 252 335 5032",
    "sg:postcode":"27909",
    "sg:province":"NC",
    "wof:name":"Rivershore Herbs & Flowers",
    "wof:placetype":"venue"
},
  "geometry": {"coordinates":[-76.24216300000001,36.297371],"type":"Point"}
}