{
  "type": "Feature",
  "properties": {
    "addr:full":"90 Forge Mountain Rd Horse Shoe NC 28759",
    "addr:housenumber":"90",
    "addr:postcode":"28759",
    "addr:street":"Forge Mountain Rd",
    "iso:country":"US",
    "sg:address":"90 Forge Mountain Rd",
    "sg:city":"Horse Shoe",
    "sg:classifiers":[
        {
            "category":"Building & Trades",
            "subcategory":"Construction",
            "type":"Services"
        }
    ],
    "sg:phone":"+1 828 891 3789",
    "sg:postcode":"28759",
    "sg:province":"NC",
    "sg:tags":[
        "specializing",
        "contractor"
    ],
    "wof:name":"D M McCoy Enterprises Inc",
    "wof:placetype":"venue"
},
  "geometry": {"coordinates":[-78.884224,35.011109],"type":"Point"}
}