{
  "type": "Feature",
  "properties": {
    "iso:country":"US",
    "sg:address":"1500 S Horner Blvd",
    "sg:city":"Sanford",
    "sg:classifiers":[
        {
            "category":"Personal",
            "subcategory":"Beauty Salon",
            "type":"Services"
        }
    ],
    "sg:phone":"+1   ",
    "sg:postcode":"27330",
    "sg:province":"NC",
    "sg:tags":[
        "shop"
    ],
    "wof:name":"Swannie Lawrence S & S Hai",
    "wof:placetype":"venue"
},
  "geometry": {"coordinates":[-79.162454,35.467841],"type":"Point"}
}