{
  "type": "Feature",
  "properties": {
    "addr:full":"945 SW Broad St Southern Pines NC 28387",
    "addr:housenumber":"945",
    "addr:postcode":"28387",
    "addr:street":"Sw Broad St",
    "iso:country":"US",
    "sg:address":"945 SW Broad St",
    "sg:city":"Southern Pines",
    "sg:classifiers":[
        {
            "category":"Insurance",
            "subcategory":"Life Insurance",
            "type":"Services"
        }
    ],
    "sg:phone":"+1 910 692 2922",
    "sg:postcode":"28387",
    "sg:province":"NC",
    "sg:tags":[
        "carrier"
    ],
    "wof:name":"Woodman of World Lf Insur Soc",
    "wof:placetype":"venue"
},
  "geometry": {"coordinates":[-79.40259399999999,35.166707],"type":"Point"}
}