{
  "type": "Feature",
  "properties": {
    "iso:country":"US",
    "sg:address":"412 Evans St",
    "sg:city":"Morehead City",
    "sg:classifiers":[
        {
            "category":"Manufacturing",
            "subcategory":"Jewelry",
            "type":"Manufacturing & Wholesale Goods"
        }
    ],
    "sg:phone":"+1 252 240 1721",
    "sg:postcode":"28557",
    "sg:province":"NC",
    "sg:tags":[
        "costume",
        "mfg"
    ],
    "wof:name":"Whispers",
    "wof:placetype":"venue"
},
  "geometry": {"coordinates":[-76.707133,34.720033],"type":"Point"}
}