{
  "type": "Feature",
  "properties": {
    "iso:country":"US",
    "sg:address":"21 Robindale Ave",
    "sg:city":"Asheville",
    "sg:classifiers":[
        {
            "category":"Professional",
            "subcategory":"Art Services",
            "type":"Services"
        }
    ],
    "sg:phone":"+1   ",
    "sg:postcode":"28801",
    "sg:province":"NC",
    "sg:tags":[
        "commercial",
        "design"
    ],
    "wof:name":"Roundhouse Creative Comm",
    "wof:placetype":"venue"
},
  "geometry": {"coordinates":[-82.551311,35.609495],"type":"Point"}
}