{
  "type": "Feature",
  "properties": {
    "addr:full":"5540 Centerview Dr Raleigh NC 27606",
    "addr:housenumber":"5540",
    "addr:postcode":"27606",
    "addr:street":"Centerview Dr",
    "iso:country":"US",
    "sg:address":"5540 Centerview Dr",
    "sg:city":"Raleigh",
    "sg:classifiers":[
        {
            "category":"Professional",
            "subcategory":"Computer Services",
            "type":"Services"
        }
    ],
    "sg:phone":"+1 919 424 3815",
    "sg:postcode":"27606",
    "sg:province":"NC",
    "sg:tags":[
        "repair"
    ],
    "wof:name":"Agilent Networks Inc",
    "wof:placetype":"venue"
},
  "geometry": {"coordinates":[-78.73156400000001,35.7628],"type":"Point"}
}