{
  "type": "Feature",
  "properties": {
    "addr:full":"103 Bayshore Dr Elizabeth City NC 27909",
    "addr:housenumber":"103",
    "addr:postcode":"27909",
    "addr:street":"Bayshore Dr",
    "iso:country":"US",
    "sg:address":"103 Bayshore Dr",
    "sg:city":"Elizabeth City",
    "sg:classifiers":[
        {
            "category":"Building & Trades",
            "subcategory":"Construction",
            "type":"Services"
        }
    ],
    "sg:phone":"+1 252 330 2300",
    "sg:postcode":"27909",
    "sg:province":"NC",
    "wof:name":"Everett & Associates Inc",
    "wof:placetype":"venue"
},
  "geometry": {"coordinates":[-76.142527,36.256408],"type":"Point"}
}