{
  "type": "Feature",
  "properties": {
    "addr:full":"215 N Church St Durham NC 27701",
    "addr:housenumber":"215",
    "addr:postcode":"27701",
    "addr:street":"N Church St",
    "iso:country":"US",
    "sg:address":"215 N Church St",
    "sg:city":"Durham",
    "sg:classifiers":[
        {
            "category":"Organizations",
            "subcategory":"Community Association",
            "type":"Services"
        }
    ],
    "sg:phone":"+1 919 682 0516",
    "sg:postcode":"27701",
    "sg:province":"NC",
    "sg:tags":[
        "religious"
    ],
    "wof:name":"Durham Cnty Hbtat For Humanity",
    "wof:placetype":"venue"
},
  "geometry": {"coordinates":[-78.89833900000001,35.995422],"type":"Point"}
}