{
  "type": "Feature",
  "properties": {
    "addr:full":"51 Kilmayne Dr Cary NC 27511",
    "addr:housenumber":"51",
    "addr:postcode":"27511",
    "addr:street":"Kilmayne Dr",
    "iso:country":"US",
    "sg:address":"51 Kilmayne Dr",
    "sg:city":"Cary",
    "sg:classifiers":[
        {
            "category":"Professional",
            "subcategory":"Business Services",
            "type":"Services"
        }
    ],
    "sg:phone":"+1   ",
    "sg:postcode":"27511",
    "sg:province":"NC",
    "wof:name":"Interior Merchandising Group L",
    "wof:placetype":"venue"
},
  "geometry": {"coordinates":[-78.779916,35.769085],"type":"Point"}
}