{
  "type": "Feature",
  "properties": {
    "iso:country":"US",
    "sg:address":"863 Merrimon Ave",
    "sg:city":"Asheville",
    "sg:classifiers":[
        {
            "category":"Sports & Exercise",
            "subcategory":"Gym",
            "type":"Entertainment"
        }
    ],
    "sg:phone":"+1   ",
    "sg:postcode":"28804",
    "sg:province":"NC",
    "sg:tags":[
        "fitness",
        "physical",
        "facility"
    ],
    "wof:name":"Training Partners Inc",
    "wof:placetype":"venue"
},
  "geometry": {"coordinates":[-82.55300800000001,35.627154],"type":"Point"}
}