{
  "type": "Feature",
  "properties": {
    "addr:full":"4437 Bent Ridge Rd Seagrove NC 27341",
    "addr:housenumber":"4437",
    "addr:postcode":"27341",
    "addr:street":"Bent Ridge Rd",
    "iso:country":"US",
    "sg:address":"4437 Bent Ridge Rd",
    "sg:city":"Seagrove",
    "sg:classifiers":[
        {
            "category":"Organizations",
            "subcategory":"Religious Organization",
            "type":"Services"
        }
    ],
    "sg:phone":"+1   ",
    "sg:postcode":"27341",
    "sg:province":"NC",
    "wof:name":"Greater St Luke Pentecostal",
    "wof:placetype":"venue"
},
  "geometry": {"coordinates":[-79.633729,35.566463],"type":"Point"}
}