{
  "type": "Feature",
  "properties": {
    "iso:country":"US",
    "sg:address":"1906 State Hwy 54",
    "sg:city":"Durham",
    "sg:classifiers":[
        {
            "category":"Personal",
            "subcategory":"Beauty Salon",
            "type":"Services"
        }
    ],
    "sg:phone":"+1 919 572 5586",
    "sg:postcode":"27713",
    "sg:province":"NC",
    "wof:name":"Image Lost",
    "wof:placetype":"venue"
},
  "geometry": {"coordinates":[-78.900812,35.902604],"type":"Point"}
}