{
  "type": "Feature",
  "properties": {
    "addr:full":"200 N Caldwell St Charlotte NC 28202",
    "addr:housenumber":"200",
    "addr:postcode":"28202",
    "addr:street":"N Caldwell St",
    "iso:country":"US",
    "sg:address":"200 N Caldwell St",
    "sg:city":"Charlotte",
    "sg:classifiers":[
        {
            "category":"Professional",
            "subcategory":"Lawyer & Legal Services",
            "type":"Services"
        }
    ],
    "sg:phone":"+1 704 335 1324",
    "sg:postcode":"28202",
    "sg:province":"NC",
    "sg:tags":[
        "plan"
    ],
    "wof:name":"Lawrence P Margolis",
    "wof:placetype":"venue"
},
  "geometry": {"coordinates":[-80.837898,35.224541],"type":"Point"}
}