{
  "type": "Feature",
  "properties": {
    "addr:full":"1619 York St New Bern NC 28562",
    "addr:housenumber":"1619",
    "addr:postcode":"28562",
    "addr:street":"York St",
    "iso:country":"US",
    "sg:address":"1619 York St",
    "sg:city":"New Bern",
    "sg:classifiers":[
        {
            "category":"Retail",
            "subcategory":"Laundry & Dry Cleaning",
            "type":"Services"
        }
    ],
    "sg:phone":"+1 252 636 5483",
    "sg:postcode":"28562",
    "sg:province":"NC",
    "sg:tags":[
        "cleaners",
        "rug",
        "carpet"
    ],
    "wof:name":"Van Go Custom Carpet Cleaning",
    "wof:placetype":"venue"
},
  "geometry": {"coordinates":[-77.097498,35.122897],"type":"Point"}
}