{
  "type": "Feature",
  "properties": {
    "iso:country":"US",
    "sg:address":"2224 Chinquapin Rd",
    "sg:city":"Farmville",
    "sg:classifiers":[
        {
            "category":"Professional",
            "subcategory":"Business Services",
            "type":"Services"
        }
    ],
    "sg:phone":"+1   ",
    "sg:postcode":"27828",
    "sg:province":"NC",
    "wof:name":"Charles A Brown",
    "wof:placetype":"venue"
},
  "geometry": {"coordinates":[-77.523307,35.602334],"type":"Point"}
}