{
  "type": "Feature",
  "properties": {
    "iso:country":"US",
    "sg:address":"1316 Spry St",
    "sg:city":"Greensboro",
    "sg:classifiers":[
        {
            "category":"Retail",
            "subcategory":"Repair Shop",
            "type":"Services"
        }
    ],
    "sg:phone":"+1   ",
    "sg:postcode":"27405",
    "sg:province":"NC",
    "wof:name":"Smith Evelyn Registered Piano",
    "wof:placetype":"venue"
},
  "geometry": {"coordinates":[-79.77044100000001,36.11992],"type":"Point"}
}