{
  "type": "Feature",
  "properties": {
    "addr:full":"60 Dogwood Rd Asheville NC 28806",
    "addr:housenumber":"60",
    "addr:postcode":"28806",
    "addr:street":"Dogwood Rd",
    "iso:country":"US",
    "sg:address":"60 Dogwood Rd",
    "sg:city":"Asheville",
    "sg:classifiers":[
        {
            "category":"Building & Trades",
            "subcategory":"Construction",
            "type":"Services"
        }
    ],
    "sg:phone":"+1 828 667 5330",
    "sg:postcode":"28806",
    "sg:province":"NC",
    "sg:tags":[
        "house",
        "commercial"
    ],
    "wof:name":"Anthony Mascolino Construction",
    "wof:placetype":"venue"
},
  "geometry": {"coordinates":[-82.601743,35.542929],"type":"Point"}
}