{
  "type": "Feature",
  "properties": {
    "addr:full":"108 Pleasant Dr Beaufort NC 28516",
    "addr:housenumber":"108",
    "addr:postcode":"28516",
    "addr:street":"Pleasant Dr",
    "iso:country":"US",
    "sg:address":"108 Pleasant Dr",
    "sg:city":"Beaufort",
    "sg:classifiers":[
        {
            "category":"Retail",
            "subcategory":"Auto Repair",
            "type":"Services"
        }
    ],
    "sg:phone":"+1   ",
    "sg:postcode":"28516",
    "sg:province":"NC",
    "sg:tags":[
        "body"
    ],
    "wof:name":"Willis Constr & Home Repairs",
    "wof:placetype":"venue"
},
  "geometry": {"coordinates":[-76.62498600000001,34.77948],"type":"Point"}
}