{
  "type": "Feature",
  "properties": {
    "addr:full":"10618 Providence Rd Charlotte NC 28277",
    "addr:housenumber":"10618",
    "addr:postcode":"28277",
    "addr:street":"Providence Rd",
    "iso:country":"US",
    "sg:address":"10618 Providence Rd",
    "sg:city":"Charlotte",
    "sg:classifiers":[
        {
            "category":"Professional",
            "subcategory":"Management & Consulting",
            "type":"Services"
        }
    ],
    "sg:phone":"+1 704 841 8624",
    "sg:postcode":"28277",
    "sg:province":"NC",
    "sg:tags":[
        "marketing",
        "program"
    ],
    "wof:name":"Gill Marketing",
    "wof:placetype":"venue"
},
  "geometry": {"coordinates":[-80.770166,35.065038],"type":"Point"}
}