{
  "type": "Feature",
  "properties": {
    "addr:full":"1603 Old Earnhardt Rd Kannapolis NC 28083",
    "addr:housenumber":"1603",
    "addr:postcode":"28083",
    "addr:street":"Old Earnhardt Rd",
    "iso:country":"US",
    "sg:address":"1603 Old Earnhardt Rd",
    "sg:city":"Kannapolis",
    "sg:classifiers":[
        {
            "category":"Building & Trades",
            "subcategory":"Construction",
            "type":"Services"
        }
    ],
    "sg:phone":"+1 704 933 6321",
    "sg:postcode":"28083",
    "sg:province":"NC",
    "sg:tags":[
        "home",
        "improvement"
    ],
    "wof:name":"Carolina Homeworks",
    "wof:placetype":"venue"
},
  "geometry": {"coordinates":[-80.597207,35.468893],"type":"Point"}
}