{
  "type": "Feature",
  "properties": {
    "iso:country":"US",
    "sg:address":"18716 W Catawba Ave",
    "sg:city":"Cornelius",
    "sg:classifiers":[
        {
            "category":"Health Services",
            "subcategory":"Health Practitioner",
            "type":"Services"
        }
    ],
    "sg:phone":"+1 704 895 0085",
    "sg:postcode":"28031",
    "sg:province":"NC",
    "sg:tags":[
        "psychologist"
    ],
    "wof:name":"Safe Harbor Counseling & Tstng",
    "wof:placetype":"venue"
},
  "geometry": {"coordinates":[-80.89124,35.470584],"type":"Point"}
}