{
  "type": "Feature",
  "properties": {
    "addr:full":"2227 Pleasant Union Rd Roseboro NC 28382",
    "addr:housenumber":"2227",
    "addr:postcode":"28382",
    "addr:street":"Pleasant Union Rd",
    "iso:country":"US",
    "sg:address":"2227 Pleasant Union Rd",
    "sg:city":"Roseboro",
    "sg:classifiers":[
        {
            "category":"Real Estate",
            "subcategory":"Real Estate Agent",
            "type":"Services"
        }
    ],
    "sg:phone":"+1 910 525 4649",
    "sg:postcode":"28382",
    "sg:province":"NC",
    "wof:name":"Perry Butler",
    "wof:placetype":"venue"
},
  "geometry": {"coordinates":[-78.56366,34.977317],"type":"Point"}
}