{
  "type": "Feature",
  "properties": {
    "iso:country":"US",
    "sg:address":"511 E 25th St",
    "sg:city":"Charlotte",
    "sg:classifiers":[
        {
            "category":"Retail",
            "subcategory":"Animal Services",
            "type":"Services"
        }
    ],
    "sg:phone":"+1 704 376 0801",
    "sg:postcode":"28205",
    "sg:province":"NC",
    "sg:tags":[
        "pet",
        "boarding",
        "sitting"
    ],
    "wof:name":"Club K9 Of Charlotte",
    "wof:placetype":"venue"
},
  "geometry": {"coordinates":[-80.815451,35.239516],"type":"Point"}
}