{
  "type": "Feature",
  "properties": {
    "addr:full":"114 Texie Ln Jacksonville NC 28546",
    "addr:housenumber":"114",
    "addr:postcode":"28546",
    "addr:street":"Texie Ln",
    "iso:country":"US",
    "sg:address":"114 Texie Ln",
    "sg:city":"Jacksonville",
    "sg:classifiers":[
        {
            "category":"Restaurant",
            "type":"Food & Drink"
        }
    ],
    "sg:phone":"+1 910 353 2253",
    "sg:postcode":"28546",
    "sg:province":"NC",
    "sg:tags":[
        "eating"
    ],
    "wof:name":"Talk of Town II",
    "wof:placetype":"venue"
},
  "geometry": {"coordinates":[-77.383055,34.744708],"type":"Point"}
}