{
  "type": "Feature",
  "properties": {
    "addr:full":"112 Hermitage Rd Charlotte NC 28207",
    "addr:housenumber":"112",
    "addr:postcode":"28207",
    "addr:street":"Hermitage Rd",
    "iso:country":"US",
    "sg:address":"112 Hermitage Rd",
    "sg:city":"Charlotte",
    "sg:classifiers":[
        {
            "category":"Professional",
            "subcategory":"Business Services",
            "type":"Services"
        }
    ],
    "sg:phone":"+1   ",
    "sg:postcode":"28207",
    "sg:province":"NC",
    "wof:name":"Rebecca B Jones",
    "wof:placetype":"venue"
},
  "geometry": {"coordinates":[-80.82913600000001,35.20563],"type":"Point"}
}