{
  "type": "Feature",
  "properties": {
    "iso:country":"US",
    "sg:address":"109 Candlewood Rd",
    "sg:city":"Rocky Mount",
    "sg:classifiers":[
        {
            "category":"Professional",
            "subcategory":"Business Services",
            "type":"Services"
        }
    ],
    "sg:phone":"+1 252 446 3443",
    "sg:postcode":"27804",
    "sg:province":"NC",
    "sg:tags":[
        "foreground",
        "music"
    ],
    "wof:name":"Sound Ideas",
    "wof:placetype":"venue"
},
  "geometry": {"coordinates":[-77.858127,35.965452],"type":"Point"}
}