{
  "type": "Feature",
  "properties": {
    "iso:country":"US",
    "sg:address":"307 E Colonial Ave",
    "sg:city":"Elizabeth City",
    "sg:classifiers":[
        {
            "category":"Government",
            "subcategory":"Office",
            "type":"Public Place"
        }
    ],
    "sg:phone":"+1 252 337 6672",
    "sg:postcode":"27909",
    "sg:province":"NC",
    "sg:tags":[
        "village"
    ],
    "wof:name":"Elizabeth City Planning",
    "wof:placetype":"venue"
},
  "geometry": {"coordinates":[-76.221943,36.300667],"type":"Point"}
}