{
  "type": "Feature",
  "properties": {
    "addr:full":"8024 US Hwy 19 E Spruce Pine NC 28777",
    "addr:housenumber":"8024",
    "addr:postcode":"28777",
    "addr:street":"Us Hwy 19 E",
    "iso:country":"US",
    "sg:address":"8024 US Hwy 19 E",
    "sg:city":"Spruce Pine",
    "sg:classifiers":[
        {
            "category":"Real Estate",
            "subcategory":"Real Estate Agent",
            "type":"Services"
        }
    ],
    "sg:phone":"+1 828 765 7705",
    "sg:postcode":"28777",
    "sg:province":"NC",
    "wof:name":"Klondyke Co",
    "wof:placetype":"venue"
},
  "geometry": {"coordinates":[-82.019853,35.930415],"type":"Point"}
}