{
  "type": "Feature",
  "properties": {
    "addr:full":"150 Providence Rd Charlotte NC 28207",
    "addr:housenumber":"150",
    "addr:postcode":"28207",
    "addr:street":"Providence Rd",
    "iso:country":"US",
    "sg:address":"150 Providence Rd",
    "sg:city":"Charlotte",
    "sg:classifiers":[
        {
            "category":"Professional",
            "type":"Services"
        }
    ],
    "sg:phone":"+1 704 334 8311",
    "sg:postcode":"28207",
    "sg:province":"NC",
    "wof:name":"Presbyterian Laboratory Svc",
    "wof:placetype":"venue"
},
  "geometry": {"coordinates":[-80.825001,35.208686],"type":"Point"}
}