{
  "type": "Feature",
  "properties": {
    "addr:full":"3121 Murchison Rd Fayetteville NC 28301",
    "addr:postcode":"3121;28301",
    "addr:street":"Murchison Rd",
    "iso:country":"US",
    "sg:address":"3121 Murchison Rd",
    "sg:city":"Fayetteville",
    "sg:classifiers":[
        {
            "category":"Utilities",
            "subcategory":"Mobile Phone",
            "type":"Services"
        }
    ],
    "sg:phone":"+1 910 822 5155",
    "sg:postcode":"28301",
    "sg:province":"NC",
    "sg:tags":[
        "telephone",
        "cellular"
    ],
    "wof:name":"Southeast Paging & Comms Inc",
    "wof:placetype":"venue"
},
  "geometry": {"coordinates":[-78.91503299999999,35.096058],"type":"Point"}
}