{
  "type": "Feature",
  "properties": {
    "addr:full":"501 E 10th St Greenville NC 27858",
    "addr:housenumber":"501",
    "addr:postcode":"27858",
    "addr:street":"E 10Th St",
    "iso:country":"US",
    "sg:address":"501 E 10th St",
    "sg:city":"Greenville",
    "sg:classifiers":[
        {
            "category":"Restaurant",
            "type":"Food & Drink"
        }
    ],
    "sg:phone":"+1 252 758 5536",
    "sg:postcode":"27858",
    "sg:province":"NC",
    "sg:tags":[
        "eating"
    ],
    "wof:name":"Wendys",
    "wof:placetype":"venue"
},
  "geometry": {"coordinates":[-77.370255,35.605306],"type":"Point"}
}