{
  "type": "Feature",
  "properties": {
    "iso:country":"US",
    "sg:address":"4717 Plum Blossum Dr",
    "sg:city":"Knightdale",
    "sg:classifiers":[
        {
            "category":"Shopping",
            "subcategory":"Computers & Home Electronics",
            "type":"Retail Goods"
        }
    ],
    "sg:phone":"+1 919 261 8980",
    "sg:postcode":"27545",
    "sg:province":"NC",
    "sg:tags":[
        "programing",
        "custom"
    ],
    "wof:name":"Tek Source",
    "wof:placetype":"venue"
},
  "geometry": {"coordinates":[-78.481335,35.762444],"type":"Point"}
}