{
  "type": "Feature",
  "properties": {
    "addr:full":"639 Whispering Hills Rd Boone NC 28607",
    "addr:housenumber":"639",
    "addr:postcode":"28607",
    "addr:street":"Whispering Hills Rd",
    "iso:country":"US",
    "sg:address":"639 Whispering Hills Rd",
    "sg:city":"Boone",
    "sg:classifiers":[
        {
            "category":"Education",
            "subcategory":"Special Training",
            "type":"Public Place"
        }
    ],
    "sg:phone":"+1   ",
    "sg:postcode":"28607",
    "sg:province":"NC",
    "sg:tags":[
        "organization",
        "religious"
    ],
    "wof:name":"Wpec Purusha",
    "wof:placetype":"venue"
},
  "geometry": {"coordinates":[-81.58553000000001,36.17363],"type":"Point"}
}