{
  "type": "Feature",
  "properties": {
    "iso:country":"US",
    "sg:address":"1205 S Tryon St",
    "sg:city":"Charlotte",
    "sg:classifiers":[
        {
            "category":"Professional",
            "subcategory":"Lawyer & Legal Services",
            "type":"Services"
        }
    ],
    "sg:phone":"+1   ",
    "sg:postcode":"28203",
    "sg:province":"NC",
    "wof:name":"Rush Lane and Lane Pllc",
    "wof:placetype":"venue"
},
  "geometry": {"coordinates":[-80.853757,35.218359],"type":"Point"}
}