{
  "type": "Feature",
  "properties": {
    "addr:full":"401 Taberna Way New Bern NC 28562",
    "addr:postcode":"28562",
    "addr:street":"Taberna Way",
    "iso:country":"US",
    "sg:address":"401 Taberna Way",
    "sg:city":"New Bern",
    "sg:classifiers":[
        {
            "category":"Sports & Exercise",
            "subcategory":"Golf",
            "type":"Entertainment"
        }
    ],
    "sg:phone":"+1 252 636 2817",
    "sg:postcode":"28562",
    "sg:province":"NC",
    "sg:tags":[
        "course"
    ],
    "wof:name":"Taberna Country Club",
    "wof:placetype":"venue"
},
  "geometry": {"coordinates":[-77.034233,35.05119],"type":"Point"}
}