{
  "type": "Feature",
  "properties": {
    "addr:full":"1477 Patton Avenue Asheville NC 28806",
    "addr:housenumber":"1477",
    "addr:postcode":"28806",
    "addr:street":"Patton Avenue",
    "iso:country":"US",
    "sg:address":"1477 Patton Avenue",
    "sg:city":"Asheville",
    "sg:classifiers":[
        {
            "category":"Sports & Exercise",
            "subcategory":"Bowling",
            "type":"Entertainment"
        }
    ],
    "sg:phone":"+1 828 252 2269",
    "sg:postcode":"28806",
    "sg:province":"NC",
    "wof:name":"Sky-Lanes Bowling",
    "wof:placetype":"venue"
},
  "geometry": {"coordinates":[-82.610044,35.577804],"type":"Point"}
}