{
  "type": "Feature",
  "properties": {
    "addr:full":"300 Hay St Fayetteville NC 28301",
    "addr:housenumber":"300",
    "addr:postcode":"28301",
    "addr:street":"Hay St",
    "iso:country":"US",
    "sg:address":"300 Hay St",
    "sg:city":"Fayetteville",
    "sg:classifiers":[
        {
            "category":"Home & Garden",
            "subcategory":"Furniture",
            "type":"Retail Goods"
        }
    ],
    "sg:phone":"+1 910 481 9900",
    "sg:postcode":"28301",
    "sg:province":"NC",
    "wof:name":"Home Accents",
    "wof:placetype":"venue"
},
  "geometry": {"coordinates":[-78.882025,35.053858],"type":"Point"}
}