{
  "type": "Feature",
  "properties": {
    "addr:full":"188 Brandy Ln Statesville NC 28677",
    "addr:housenumber":"188",
    "addr:postcode":"28677",
    "addr:street":"Brandy Ln",
    "iso:country":"US",
    "sg:address":"188 Brandy Ln",
    "sg:city":"Statesville",
    "sg:classifiers":[
        {
            "category":"Building & Trades",
            "subcategory":"Landscaping Services",
            "type":"Services"
        }
    ],
    "sg:phone":"+1 704 873 0934",
    "sg:postcode":"28677",
    "sg:province":"NC",
    "sg:tags":[
        "landscape"
    ],
    "wof:name":"Ramseys Grounds Management",
    "wof:placetype":"venue"
},
  "geometry": {"coordinates":[-80.945994,35.778699],"type":"Point"}
}