{
  "type": "Feature",
  "properties": {
    "addr:full":"1097 Lemmons Rd Walnut Cove NC 27052",
    "addr:housenumber":"1097",
    "addr:postcode":"27052",
    "addr:street":"Lemmons Rd",
    "iso:country":"US",
    "sg:address":"1097 Lemmons Rd",
    "sg:city":"Walnut Cove",
    "sg:classifiers":[
        {
            "category":"Organizations",
            "subcategory":"Religious Organization",
            "type":"Services"
        }
    ],
    "sg:phone":"+1 336 445 0005",
    "sg:postcode":"27052",
    "sg:province":"NC",
    "sg:tags":[
        "church"
    ],
    "wof:name":"Greater Grace Temple Holiness",
    "wof:placetype":"venue"
},
  "geometry": {"coordinates":[-80.103393,36.36407],"type":"Point"}
}