{
  "type": "Feature",
  "properties": {
    "addr:full":"244 Falls Creek Rd Todd NC 28684",
    "addr:housenumber":"244",
    "addr:postcode":"28684",
    "addr:street":"Falls Creek Rd",
    "iso:country":"US",
    "sg:address":"244 Falls Creek Rd",
    "sg:city":"Todd",
    "sg:classifiers":[
        {
            "category":"Health Services",
            "subcategory":"Doctor",
            "type":"Services"
        }
    ],
    "sg:phone":"+1 336 877 5545",
    "sg:postcode":"28684",
    "sg:province":"NC",
    "sg:tags":[
        "anesthetist"
    ],
    "wof:name":"Hermitage Anesthesia Inc",
    "wof:placetype":"venue"
},
  "geometry": {"coordinates":[-81.554317,36.353818],"type":"Point"}
}