{
  "type": "Feature",
  "properties": {
    "iso:country":"US",
    "sg:address":"5066 Main St",
    "sg:city":"South Brunswick",
    "sg:classifiers":[
        {
            "category":"Restaurant",
            "type":"Food & Drink"
        }
    ],
    "sg:phone":"+1 910 754 9442",
    "sg:postcode":"28470",
    "sg:province":"NC",
    "wof:name":"KFC",
    "wof:placetype":"venue"
},
  "geometry": {"coordinates":[-78.392588,33.967696],"type":"Point"}
}