{
  "type": "Feature",
  "properties": {
    "addr:full":"841 Jerry Hughes St Asheboro NC 27205",
    "addr:housenumber":"841",
    "addr:postcode":"27205",
    "addr:street":"Jerry Hughes St",
    "iso:country":"US",
    "sg:address":"841 Jerry Hughes St",
    "sg:city":"Asheboro",
    "sg:classifiers":[
        {
            "category":"Retail",
            "subcategory":"Auto Repair",
            "type":"Services"
        }
    ],
    "sg:phone":"+1   ",
    "sg:postcode":"27205",
    "sg:province":"NC",
    "sg:tags":[
        "body"
    ],
    "wof:name":"SJS Custom Paint & Repair",
    "wof:placetype":"venue"
},
  "geometry": {"coordinates":[-79.837879,35.688908],"type":"Point"}
}