{
  "type": "Feature",
  "properties": {
    "iso:country":"US",
    "sg:address":"702 Price Ave",
    "sg:city":"Gastonia",
    "sg:classifiers":[
        {
            "category":"Home & Garden",
            "subcategory":"Furniture",
            "type":"Retail Goods"
        }
    ],
    "sg:phone":"+1 704 866 8521",
    "sg:postcode":"28054",
    "sg:province":"NC",
    "sg:tags":[
        "cabinet"
    ],
    "wof:name":"Custom Stairs & Millwork",
    "wof:placetype":"venue"
},
  "geometry": {"coordinates":[-81.170225,35.260096],"type":"Point"}
}