{
  "type": "Feature",
  "properties": {
    "iso:country":"US",
    "sg:address":"7114 Guess Rd",
    "sg:city":"Hillsborough",
    "sg:classifiers":[
        {
            "category":"Restaurant",
            "type":"Food & Drink"
        }
    ],
    "sg:phone":"+1 919 477 8787",
    "sg:postcode":"27278",
    "sg:province":"NC",
    "sg:tags":[
        "patent",
        "eating"
    ],
    "wof:name":"Mr Barbeque N Stuff",
    "wof:placetype":"venue"
},
  "geometry": {"coordinates":[-78.947461,36.133506],"type":"Point"}
}