{
  "type": "Feature",
  "properties": {
    "iso:country":"US",
    "sg:address":"66 Phil Buchanan Rd",
    "sg:city":"Spruce Pine",
    "sg:classifiers":[
        {
            "category":"Professional",
            "subcategory":"Business Services",
            "type":"Services"
        }
    ],
    "sg:phone":"+1   ",
    "sg:postcode":"28777",
    "sg:province":"NC",
    "wof:name":"Steve Tipton Enterprises",
    "wof:placetype":"venue"
},
  "geometry": {"coordinates":[-82.08502799999999,35.929533],"type":"Point"}
}