{
  "type": "Feature",
  "properties": {
    "iso:country":"US",
    "sg:address":"3412 Westgate Dr",
    "sg:city":"Durham",
    "sg:classifiers":[
        {
            "category":"Real Estate",
            "subcategory":"Real Estate Agent",
            "type":"Services"
        }
    ],
    "sg:phone":"+1 919 403 9057",
    "sg:postcode":"27707",
    "sg:province":"NC",
    "sg:tags":[
        "school",
        "vocational"
    ],
    "wof:name":"Howard Perry & Walston RE Schl",
    "wof:placetype":"venue"
},
  "geometry": {"coordinates":[-78.960802,35.965103],"type":"Point"}
}