{
  "type": "Feature",
  "properties": {
    "iso:country":"US",
    "sg:address":"17 Running Brook Ct",
    "sg:city":"Durham",
    "sg:classifiers":[
        {
            "category":"Organizations",
            "subcategory":"Professional Association",
            "type":"Services"
        }
    ],
    "sg:phone":"+1 919 489 5407",
    "sg:postcode":"27713",
    "sg:province":"NC",
    "sg:website":"www.aamro.net",
    "wof:name":"American Association Of Med",
    "wof:placetype":"venue"
},
  "geometry": {"coordinates":[-78.936014,35.921331],"type":"Point"}
}