{
  "type": "Feature",
  "properties": {
    "addr:full":"13513 Helmsley Ct Charlotte NC 28273",
    "addr:housenumber":"13513",
    "addr:postcode":"28273",
    "addr:street":"Helmsley Ct",
    "iso:country":"US",
    "sg:address":"13513 Helmsley Ct",
    "sg:city":"Charlotte",
    "sg:classifiers":[
        {
            "category":"Restaurant",
            "type":"Food & Drink"
        }
    ],
    "sg:phone":"+1 704 588 7979",
    "sg:postcode":"28273",
    "sg:province":"NC",
    "sg:tags":[
        "eating"
    ],
    "wof:name":"Shudali Inc",
    "wof:placetype":"venue"
},
  "geometry": {"coordinates":[-80.96281999999999,35.110145],"type":"Point"}
}