{
  "type": "Feature",
  "properties": {
    "addr:full":"5000 Crown Point Ln Wilmington NC 28409",
    "addr:housenumber":"5000",
    "addr:postcode":"28409",
    "addr:street":"Crown Point Ln",
    "iso:country":"US",
    "sg:address":"5000 Crown Point Ln",
    "sg:city":"Wilmington",
    "sg:classifiers":[
        {
            "category":"Manufacturing",
            "subcategory":"Retail Goods",
            "type":"Manufacturing & Wholesale Goods"
        }
    ],
    "sg:phone":"+1 919 362 6710",
    "sg:postcode":"28409",
    "sg:province":"NC",
    "sg:tags":[
        "manufacturer"
    ],
    "sg:website":"www.zoronmfg.com",
    "wof:name":"Zoron Manufacturing Inc",
    "wof:placetype":"venue"
},
  "geometry": {"coordinates":[-77.87537399999999,34.162205],"type":"Point"}
}