{
  "type": "Feature",
  "properties": {
    "iso:country":"US",
    "sg:address":"1116 Blenheim Dr",
    "sg:city":"Raleigh",
    "sg:classifiers":[
        {
            "category":"Building & Trades",
            "subcategory":"Plumbing",
            "type":"Services"
        }
    ],
    "sg:phone":"+1 919 781 6234",
    "sg:postcode":"27612",
    "sg:province":"NC",
    "sg:tags":[
        "contractor"
    ],
    "wof:name":"C H Bremer & Co",
    "wof:placetype":"venue"
},
  "geometry": {"coordinates":[-78.673101,35.829333],"type":"Point"}
}