{
  "type": "Feature",
  "properties": {
    "addr:full":"1620 E 4th St Charlotte NC 28204",
    "addr:housenumber":"1620",
    "addr:postcode":"28204",
    "addr:street":"E 4Th St",
    "iso:country":"US",
    "sg:address":"1620 E 4th St",
    "sg:city":"Charlotte",
    "sg:classifiers":[
        {
            "category":"Restaurant",
            "type":"Food & Drink"
        }
    ],
    "sg:phone":"+1 704 333 3350",
    "sg:postcode":"28204",
    "sg:province":"NC",
    "wof:name":"Wokken Sushi",
    "wof:placetype":"venue"
},
  "geometry": {"coordinates":[-80.827743,35.212965],"type":"Point"}
}