{
  "type": "Feature",
  "properties": {
    "iso:country":"US",
    "sg:address":"823 W Pine St",
    "sg:city":"Mount Airy",
    "sg:classifiers":[
        {
            "category":"Personal",
            "subcategory":"Beauty Salon",
            "type":"Services"
        }
    ],
    "sg:phone":"+1   ",
    "sg:postcode":"27030",
    "sg:province":"NC",
    "sg:tags":[
        "shop"
    ],
    "wof:name":"Uptown Nail Designs",
    "wof:placetype":"venue"
},
  "geometry": {"coordinates":[-80.625668,36.499947],"type":"Point"}
}