{
  "type": "Feature",
  "properties": {
    "addr:full":"1015 Highland Ave NE Hickory NC 28601",
    "addr:housenumber":"1015",
    "addr:postcode":"28601",
    "addr:street":"Highland Ave Ne",
    "iso:country":"US",
    "sg:address":"1015 Highland Ave NE",
    "sg:city":"Hickory",
    "sg:classifiers":[
        {
            "category":"Retail",
            "subcategory":"Repair Shop",
            "type":"Services"
        }
    ],
    "sg:phone":"+1 828 328 8052",
    "sg:postcode":"28601",
    "sg:province":"NC",
    "sg:tags":[
        "lock",
        "locksmith"
    ],
    "wof:name":"Poteat's Lock & Key",
    "wof:placetype":"venue"
},
  "geometry": {"coordinates":[-81.315039,35.73965],"type":"Point"}
}