{
  "type": "Feature",
  "properties": {
    "addr:full":"4801 Starcrest Dr Monroe NC 28110",
    "addr:housenumber":"4801",
    "addr:postcode":"28110",
    "addr:street":"Starcrest Dr",
    "iso:country":"US",
    "sg:address":"4801 Starcrest Dr",
    "sg:city":"Monroe",
    "sg:classifiers":[
        {
            "category":"Building & Trades",
            "subcategory":"Plumbing",
            "type":"Services"
        }
    ],
    "sg:phone":"+1 704 296 9048",
    "sg:postcode":"28110",
    "sg:province":"NC",
    "sg:tags":[
        "contractor"
    ],
    "wof:name":"Ingersoll-Rand",
    "wof:placetype":"venue"
},
  "geometry": {"coordinates":[-80.61674499999999,35.054463],"type":"Point"}
}