{
  "type": "Feature",
  "properties": {
    "addr:full":"1830 Lt Hardee Rd Greenville NC 27858",
    "addr:postcode":"1830;27858",
    "addr:street":"Lt Hardee Rd",
    "iso:country":"US",
    "sg:address":"1830 Lt Hardee Rd",
    "sg:city":"Greenville",
    "sg:classifiers":[
        {
            "category":"Building & Trades",
            "subcategory":"Electrical",
            "type":"Services"
        }
    ],
    "sg:phone":"+1 252 752 5002",
    "sg:postcode":"27858",
    "sg:province":"NC",
    "sg:tags":[
        "electrical",
        "contractor"
    ],
    "wof:name":"Dicks Electric Service",
    "wof:placetype":"venue"
},
  "geometry": {"coordinates":[-77.308553,35.572238],"type":"Point"}
}