{
  "type": "Feature",
  "properties": {
    "iso:country":"US",
    "sg:address":"1055 W Corbett Ave",
    "sg:city":"Swansboro",
    "sg:classifiers":[
        {
            "category":"Autos & Motor Vehicles",
            "subcategory":"Automobile Sales",
            "type":"Retail Goods"
        }
    ],
    "sg:phone":"+1 910 326 1900",
    "sg:postcode":"28584",
    "sg:province":"NC",
    "sg:tags":[
        "used"
    ],
    "wof:name":"North Shore Auto Sales",
    "wof:placetype":"venue"
},
  "geometry": {"coordinates":[-77.14608800000001,34.700619],"type":"Point"}
}