{
  "type": "Feature",
  "properties": {
    "addr:full":"4012 Greenleaf St Raleigh NC 27606",
    "addr:housenumber":"4012",
    "addr:postcode":"27606",
    "addr:street":"Greenleaf St",
    "iso:country":"US",
    "sg:address":"4012 Greenleaf St",
    "sg:city":"Raleigh",
    "sg:classifiers":[
        {
            "category":"Communications",
            "type":"Services"
        },
        {
            "category":"Professional",
            "subcategory":"Management & Consulting",
            "type":"Services"
        }
    ],
    "sg:phone":"+1 919 834 1646",
    "sg:postcode":"27606",
    "sg:province":"NC",
    "sg:tags":[
        "communication",
        "program",
        "marketing"
    ],
    "wof:name":"Dena White & Associates",
    "wof:placetype":"venue"
},
  "geometry": {"coordinates":[-78.693433,35.780874],"type":"Point"}
}