{
  "type": "Feature",
  "properties": {
    "iso:country":"US",
    "sg:address":"600 E 12th St",
    "sg:city":"Kannapolis",
    "sg:classifiers":[
        {
            "category":"Shopping",
            "subcategory":"Clothing, Apparel, & Fashions",
            "type":"Retail Goods"
        }
    ],
    "sg:phone":"+1 704 938 1812",
    "sg:postcode":"28083",
    "sg:province":"NC",
    "wof:name":"Quality Care Systems",
    "wof:placetype":"venue"
},
  "geometry": {"coordinates":[-80.608947,35.510416],"type":"Point"}
}