{
  "type": "Feature",
  "properties": {
    "iso:country":"US",
    "sg:address":"618 Shaw Rd",
    "sg:city":"Riegelwood",
    "sg:classifiers":[
        {
            "category":"Professional",
            "type":"Services"
        }
    ],
    "sg:phone":"+1 910 655 4994",
    "sg:postcode":"28456",
    "sg:province":"NC",
    "wof:name":"Graham Cw Inc",
    "wof:placetype":"venue"
},
  "geometry": {"coordinates":[-78.298519,34.358416],"type":"Point"}
}