{
  "type": "Feature",
  "properties": {
    "addr:full":"5055 Ancestry Cir Matthews NC 28104",
    "addr:housenumber":"5055",
    "addr:postcode":"28104",
    "addr:street":"Ancestry Cir",
    "iso:country":"US",
    "sg:address":"5055 Ancestry Cir",
    "sg:city":"Matthews",
    "sg:classifiers":[
        {
            "category":"Professional",
            "subcategory":"Business Services",
            "type":"Services"
        }
    ],
    "sg:phone":"+1 704 321 5092",
    "sg:postcode":"28104",
    "sg:province":"NC",
    "wof:name":"Salient Technology LLC",
    "wof:placetype":"venue"
},
  "geometry": {"coordinates":[-80.734151,35.025003],"type":"Point"}
}