{
  "type": "Feature",
  "properties": {
    "addr:full":"4831 Old Rural Hall Rd Winston Salem NC 27105",
    "addr:housenumber":"4831",
    "addr:postcode":"27105",
    "addr:street":"Old Rural Hall Rd",
    "iso:country":"US",
    "sg:address":"4831 Old Rural Hall Rd",
    "sg:city":"Winston Salem",
    "sg:classifiers":[
        {
            "category":"Retail",
            "subcategory":"Self-service Laundry",
            "type":"Services"
        }
    ],
    "sg:phone":"+1 336 661 2877",
    "sg:postcode":"27105",
    "sg:province":"NC",
    "wof:name":"Ogburn Station Coin Laundry",
    "wof:placetype":"venue"
},
  "geometry": {"coordinates":[-80.227738,36.158184],"type":"Point"}
}