{
  "type": "Feature",
  "properties": {
    "iso:country":"US",
    "sg:address":"4512 Oleander Dr",
    "sg:city":"Wilmington",
    "sg:classifiers":[
        {
            "category":"Retail",
            "subcategory":"Repair Shop",
            "type":"Services"
        }
    ],
    "sg:phone":"+1 910 784 9534",
    "sg:postcode":"28403",
    "sg:province":"NC",
    "sg:tags":[
        "recycling",
        "cartridge",
        "toner"
    ],
    "wof:name":"Cartridge World",
    "wof:placetype":"venue"
},
  "geometry": {"coordinates":[-77.886911,34.210279],"type":"Point"}
}