{
  "type": "Feature",
  "properties": {
    "addr:full":"1735 W Lee St Greensboro NC 27403",
    "addr:housenumber":"1735",
    "addr:postcode":"27403",
    "addr:street":"W Lee St",
    "iso:country":"US",
    "sg:address":"1735 W Lee St",
    "sg:city":"Greensboro",
    "sg:classifiers":[
        {
            "category":"Building & Trades",
            "subcategory":"Construction",
            "type":"Services"
        }
    ],
    "sg:phone":"+1 336 852 5651",
    "sg:postcode":"27403",
    "sg:province":"NC",
    "sg:tags":[
        "contractor"
    ],
    "wof:name":"United Masonry",
    "wof:placetype":"venue"
},
  "geometry": {"coordinates":[-79.823156,36.060691],"type":"Point"}
}