{
  "type": "Feature",
  "properties": {
    "iso:country":"US",
    "sg:address":"3609 Ramsey St",
    "sg:city":"Fayetteville",
    "sg:classifiers":[
        {
            "category":"Restaurant",
            "type":"Food & Drink"
        }
    ],
    "sg:menulink":"http://www.allmenus.com/nc/cross-creek/199675-sonic/menu/",
    "sg:phone":"+1 910 480 4133",
    "sg:postcode":"28311",
    "sg:province":"NC",
    "sg:tags":[
        "burger",
        "american"
    ],
    "wof:name":"Sonic",
    "wof:placetype":"venue"
},
  "geometry": {"coordinates":[-78.87958500000001,35.108887],"type":"Point"}
}