{
  "type": "Feature",
  "properties": {
    "iso:country":"US",
    "sg:address":"226 N Fairview Rd",
    "sg:city":"Rocky Mount",
    "sg:classifiers":[
        {
            "category":"Personal",
            "subcategory":"Barber",
            "type":"Services"
        }
    ],
    "sg:phone":"+1 252 972 7707",
    "sg:postcode":"27801",
    "sg:province":"NC",
    "wof:name":"Oakwood Creative Cutting",
    "wof:placetype":"venue"
},
  "geometry": {"coordinates":[-77.774511,35.931895],"type":"Point"}
}