{
  "type": "Feature",
  "properties": {
    "iso:country":"US",
    "sg:address":"4766 State Hwy 24",
    "sg:city":"Mt Gilead",
    "sg:classifiers":[
        {
            "category":"Real Estate",
            "subcategory":"Real Estate Agent",
            "type":"Services"
        }
    ],
    "sg:phone":"+1 910 439 4944",
    "sg:postcode":"27306",
    "sg:province":"NC",
    "wof:name":"Sun Realty",
    "wof:placetype":"venue"
},
  "geometry": {"coordinates":[-80.067213,35.306533],"type":"Point"}
}