{
  "type": "Feature",
  "properties": {
    "iso:country":"US",
    "sg:address":"460 Mayberry Ln",
    "sg:city":"Mooresville",
    "sg:classifiers":[
        {
            "category":"Organizations",
            "subcategory":"Religious Organization",
            "type":"Services"
        }
    ],
    "sg:phone":"+1 704 857 0763",
    "sg:postcode":"28115",
    "sg:province":"NC",
    "wof:name":"Rev James M Pauley",
    "wof:placetype":"venue"
},
  "geometry": {"coordinates":[-80.698256,35.559568],"type":"Point"}
}