{
  "type": "Feature",
  "properties": {
    "addr:full":"404 Earl Dr Goldsboro NC 27530",
    "addr:housenumber":"404",
    "addr:postcode":"27530",
    "addr:street":"Earl Dr",
    "iso:country":"US",
    "sg:address":"404 Earl Dr",
    "sg:city":"Goldsboro",
    "sg:classifiers":[
        {
            "category":"Professional",
            "subcategory":"Computer Services",
            "type":"Services"
        }
    ],
    "sg:phone":"+1   ",
    "sg:postcode":"27530",
    "sg:province":"NC",
    "sg:tags":[
        "related"
    ],
    "wof:name":"Madry S Computer Consulti",
    "wof:placetype":"venue"
},
  "geometry": {"coordinates":[-78.083538,35.440555],"type":"Point"}
}