{
  "type": "Feature",
  "properties": {
    "iso:country":"US",
    "sg:address":"1208 Jones Dairy Rd",
    "sg:city":"Wake Forest",
    "sg:classifiers":[
        {
            "category":"Building & Trades",
            "subcategory":"Electrical",
            "type":"Services"
        }
    ],
    "sg:phone":"+1 919 556 1154",
    "sg:postcode":"27587",
    "sg:province":"NC",
    "sg:tags":[
        "electrical",
        "contractor"
    ],
    "wof:name":"Act Electric Inc",
    "wof:placetype":"venue"
},
  "geometry": {"coordinates":[-78.47199500000001,35.951617],"type":"Point"}
}