{
  "type": "Feature",
  "properties": {
    "addr:full":"305 Copperline Dr Chapel Hill NC 27516",
    "addr:housenumber":"305",
    "addr:postcode":"27516",
    "addr:street":"Copperline Dr",
    "iso:country":"US",
    "sg:address":"305 Copperline Dr",
    "sg:city":"Chapel Hill",
    "sg:classifiers":[
        {
            "category":"Real Estate",
            "subcategory":"Real Estate Operator",
            "type":"Services"
        }
    ],
    "sg:phone":"+1 919 942 4959",
    "sg:postcode":"27516",
    "sg:province":"NC",
    "sg:tags":[
        "apartment"
    ],
    "wof:name":"Copperline Associates",
    "wof:placetype":"venue"
},
  "geometry": {"coordinates":[-79.065102,35.882702],"type":"Point"}
}