{
  "type": "Feature",
  "properties": {
    "addr:full":"607 E Gordon St Kinston NC 28501",
    "addr:housenumber":"607",
    "addr:postcode":"28501",
    "addr:street":"E Gordon St",
    "iso:country":"US",
    "sg:address":"607 E Gordon St",
    "sg:city":"Kinston",
    "sg:classifiers":[
        {
            "category":"Real Estate",
            "subcategory":"Real Estate Agent",
            "type":"Services"
        }
    ],
    "sg:phone":"+1 252 523 1239",
    "sg:postcode":"28501",
    "sg:province":"NC",
    "wof:name":"Askew Realty Inc",
    "wof:placetype":"venue"
},
  "geometry": {"coordinates":[-77.572553,35.26141],"type":"Point"}
}