{
  "type": "Feature",
  "properties": {
    "iso:country":"US",
    "sg:address":"423 Lakeview Dr",
    "sg:city":"Harrisburg",
    "sg:classifiers":[
        {
            "category":"Building & Trades",
            "subcategory":"Plumbing",
            "type":"Services"
        }
    ],
    "sg:phone":"+1 704 454 5976",
    "sg:postcode":"28075",
    "sg:province":"NC",
    "sg:tags":[
        "contractor"
    ],
    "wof:name":"Jerry Smith Plumbing",
    "wof:placetype":"venue"
},
  "geometry": {"coordinates":[-80.670699,35.325067],"type":"Point"}
}