{
  "type": "Feature",
  "properties": {
    "addr:full":"863 23rd St Ct SE Hickory NC 28602",
    "addr:housenumber":"863",
    "addr:postcode":"28602",
    "addr:street":"23Rd St Ct Se",
    "iso:country":"US",
    "sg:address":"863 23rd St Ct SE",
    "sg:city":"Hickory",
    "sg:classifiers":[
        {
            "category":"Retail",
            "subcategory":"Auto Repair",
            "type":"Services"
        }
    ],
    "sg:phone":"+1 828 324 1236",
    "sg:postcode":"28602",
    "sg:province":"NC",
    "sg:tags":[
        "repairing",
        "automobile"
    ],
    "wof:name":"Car Surgeon",
    "wof:placetype":"venue"
},
  "geometry": {"coordinates":[-81.29258799999999,35.71869],"type":"Point"}
}