{
  "type": "Feature",
  "properties": {
    "iso:country":"US",
    "sg:address":"4401 Saint Ives Pl",
    "sg:city":"Charlotte",
    "sg:classifiers":[
        {
            "category":"Real Estate",
            "subcategory":"Real Estate Agent",
            "type":"Services"
        }
    ],
    "sg:phone":"+1 704 366 3000",
    "sg:postcode":"28211",
    "sg:province":"NC",
    "wof:name":"Wheatley Real Estate Co",
    "wof:placetype":"venue"
},
  "geometry": {"coordinates":[-80.80888299999999,35.149817],"type":"Point"}
}