{
  "type": "Feature",
  "properties": {
    "addr:full":"1064 Bacon Rd Littleton NC 27850",
    "addr:housenumber":"1064",
    "addr:postcode":"27850",
    "addr:street":"Bacon Rd",
    "iso:country":"US",
    "sg:address":"1064 Bacon Rd",
    "sg:city":"Littleton",
    "sg:classifiers":[
        {
            "category":"Education",
            "subcategory":"School",
            "type":"Public Place"
        }
    ],
    "sg:phone":"+1 252 586 3219",
    "sg:postcode":"27850",
    "sg:province":"NC",
    "wof:name":"McIver Elementary School Dst",
    "wof:placetype":"venue"
},
  "geometry": {"coordinates":[-77.894469,36.443278],"type":"Point"}
}