{
  "type": "Feature",
  "properties": {
    "iso:country":"US",
    "sg:address":"6301 Oakley Rd",
    "sg:city":"Cedar Grove",
    "sg:classifiers":[
        {
            "category":"Farming",
            "subcategory":"Livestock Farm",
            "type":"Manufacturing & Wholesale Goods"
        }
    ],
    "sg:phone":"+1 919 732 8594",
    "sg:postcode":"27231",
    "sg:province":"NC",
    "sg:tags":[
        "beef",
        "feedlot",
        "cattle"
    ],
    "wof:name":"Dwight Oakley",
    "wof:placetype":"venue"
},
  "geometry": {"coordinates":[-79.174862,36.181626],"type":"Point"}
}