{
  "type": "Feature",
  "properties": {
    "iso:country":"US",
    "sg:address":"21308 Nautique Blvd",
    "sg:city":"Cornelius",
    "sg:classifiers":[
        {
            "category":"Professional",
            "subcategory":"Business Services",
            "type":"Services"
        }
    ],
    "sg:phone":"+1 704 895 4101",
    "sg:postcode":"28031",
    "sg:province":"NC",
    "sg:tags":[
        "telemarketing"
    ],
    "wof:name":"Alan Adler & Assoc Inc",
    "wof:placetype":"venue"
},
  "geometry": {"coordinates":[-80.88471199999999,35.483167],"type":"Point"}
}