{
  "type": "Feature",
  "properties": {
    "addr:full":"1109 W Murray Ave Durham NC 27704",
    "addr:housenumber":"1109",
    "addr:postcode":"27704",
    "addr:street":"W Murray Ave",
    "iso:country":"US",
    "sg:address":"1109 W Murray Ave",
    "sg:city":"Durham",
    "sg:classifiers":[
        {
            "category":"Social Services",
            "subcategory":"Adult Care",
            "type":"Services"
        }
    ],
    "sg:phone":"+1 919 220 6684",
    "sg:postcode":"27704",
    "sg:province":"NC",
    "sg:tags":[
        "home",
        "group"
    ],
    "wof:name":"Comprehensive Community Care",
    "wof:placetype":"venue"
},
  "geometry": {"coordinates":[-78.908477,36.02886],"type":"Point"}
}