{
  "type": "Feature",
  "properties": {
    "iso:country":"US",
    "sg:address":"122 Avalon Dr",
    "sg:city":"Salisbury",
    "sg:classifiers":[
        {
            "category":"Restaurant",
            "type":"Food & Drink"
        }
    ],
    "sg:phone":"+1 704 633 2672",
    "sg:postcode":"28146",
    "sg:province":"NC",
    "sg:tags":[
        "pizza"
    ],
    "wof:name":"Little Caesars Pizza",
    "wof:placetype":"venue"
},
  "geometry": {"coordinates":[-80.45800199999999,35.650124],"type":"Point"}
}