{
  "type": "Feature",
  "properties": {
    "addr:full":"8015 Maxwell Rd Wade NC 28395",
    "addr:housenumber":"8015",
    "addr:postcode":"28395",
    "addr:street":"Maxwell Rd",
    "iso:country":"US",
    "sg:address":"8015 Maxwell Rd",
    "sg:city":"Wade",
    "sg:classifiers":[
        {
            "category":"Wholesale",
            "subcategory":"Machinery & Supplies",
            "type":"Manufacturing & Wholesale Goods"
        }
    ],
    "sg:phone":"+1 910 323 3160",
    "sg:postcode":"28395",
    "sg:province":"NC",
    "sg:tags":[
        "truck"
    ],
    "wof:name":"Professional Maintenance",
    "wof:placetype":"venue"
},
  "geometry": {"coordinates":[-78.681927,35.077456],"type":"Point"}
}