{
  "type": "Feature",
  "properties": {
    "addr:full":"404 Palmetto Dr Oak Island NC 28465",
    "addr:housenumber":"404",
    "addr:postcode":"28465",
    "addr:street":"Palmetto Dr Oak",
    "iso:country":"US",
    "sg:address":"404 Palmetto Dr",
    "sg:city":"Oak Island",
    "sg:classifiers":[
        {
            "category":"Home & Garden",
            "subcategory":"Home Furnishings",
            "type":"Retail Goods"
        }
    ],
    "sg:phone":"+1 910 457 0065",
    "sg:postcode":"28465",
    "sg:province":"NC",
    "sg:tags":[
        "lamp",
        "shades"
    ],
    "wof:name":"Myrvick Enterprises",
    "wof:placetype":"venue"
},
  "geometry": {"coordinates":[-78.062918,33.907739],"type":"Point"}
}