{
  "type": "Feature",
  "properties": {
    "iso:country":"US",
    "sg:address":"297 Corban Ave SW",
    "sg:city":"Concord",
    "sg:classifiers":[
        {
            "category":"Real Estate",
            "subcategory":"Real Estate Agent",
            "type":"Services"
        }
    ],
    "sg:phone":"+1 704 782 2222",
    "sg:postcode":"28025",
    "sg:province":"NC",
    "wof:name":"M B Properties Inc",
    "wof:placetype":"venue"
},
  "geometry": {"coordinates":[-80.58790399999999,35.403199],"type":"Point"}
}