{
  "type": "Feature",
  "properties": {
    "addr:full":"901 S Church St Salisbury NC 28144",
    "addr:housenumber":"901",
    "addr:postcode":"28144",
    "addr:street":"S Church St",
    "iso:country":"US",
    "sg:address":"901 S Church St",
    "sg:city":"Salisbury",
    "sg:classifiers":[
        {
            "category":"Organizations",
            "subcategory":"Religious Organization",
            "type":"Services"
        }
    ],
    "sg:phone":"+1 704 636 2241",
    "sg:postcode":"28144",
    "sg:province":"NC",
    "sg:tags":[
        "church"
    ],
    "wof:name":"Coburn Memorial United Mthdst",
    "wof:placetype":"venue"
},
  "geometry": {"coordinates":[-80.48177699999999,35.660806],"type":"Point"}
}