{
  "type": "Feature",
  "properties": {
    "iso:country":"US",
    "sg:address":"8705 State Hwy 105",
    "sg:city":"Banner Elk",
    "sg:classifiers":[
        {
            "category":"Shopping",
            "subcategory":"Florist",
            "type":"Retail Goods"
        }
    ],
    "sg:phone":"+1 828 963 9330",
    "sg:postcode":"28604",
    "sg:province":"NC",
    "wof:name":"Pearl's Garden",
    "wof:placetype":"venue"
},
  "geometry": {"coordinates":[-81.768137,36.159925],"type":"Point"}
}