{
  "type": "Feature",
  "properties": {
    "iso:country":"US",
    "sg:address":"4107 Azalea Dr",
    "sg:city":"Morehead City",
    "sg:classifiers":[
        {
            "category":"Building & Trades",
            "subcategory":"Construction",
            "type":"Services"
        }
    ],
    "sg:phone":"+1 252 726 3381",
    "sg:postcode":"28557",
    "sg:province":"NC",
    "sg:tags":[
        "contractor"
    ],
    "wof:name":"Baysden Builders",
    "wof:placetype":"venue"
},
  "geometry": {"coordinates":[-76.769054,34.734868],"type":"Point"}
}