{
  "type": "Feature",
  "properties": {
    "addr:full":"5159 Osprey Pt Sanford NC 27332",
    "addr:housenumber":"5159",
    "addr:postcode":"27332",
    "addr:street":"Osprey Pt",
    "iso:country":"US",
    "sg:address":"5159 Osprey Pt",
    "sg:city":"Sanford",
    "sg:classifiers":[
        {
            "category":"Professional",
            "subcategory":"Management & Consulting",
            "type":"Services"
        }
    ],
    "sg:phone":"+1   ",
    "sg:postcode":"27332",
    "sg:province":"NC",
    "wof:name":"John Hooper LLC",
    "wof:placetype":"venue"
},
  "geometry": {"coordinates":[-79.09084799999999,35.42023],"type":"Point"}
}