{
  "type": "Feature",
  "properties": {
    "iso:country":"US",
    "sg:address":"110 Rock Rd",
    "sg:city":"Rocky Point",
    "sg:classifiers":[
        {
            "category":"Manufacturing",
            "subcategory":"Printing",
            "type":"Manufacturing & Wholesale Goods"
        }
    ],
    "sg:phone":"+1 910 602 3888",
    "sg:postcode":"28466",
    "sg:province":"NC",
    "sg:tags":[
        "periodical"
    ],
    "wof:name":"Colonial Cedar Log Homes",
    "wof:placetype":"venue"
},
  "geometry": {"coordinates":[-77.83532599999999,34.779671],"type":"Point"}
}