{
  "type": "Feature",
  "properties": {
    "iso:country":"US",
    "sg:address":"1501 S Main St",
    "sg:city":"Lexington",
    "sg:classifiers":[
        {
            "category":"Manufacturing",
            "subcategory":"Signs",
            "type":"Manufacturing & Wholesale Goods"
        }
    ],
    "sg:phone":"+1 336 243 6286",
    "sg:postcode":"27292",
    "sg:province":"NC",
    "sg:tags":[
        "specialty",
        "mfg"
    ],
    "sg:website":"www.bannersandsuch.com",
    "wof:name":"Banners & Such",
    "wof:placetype":"venue"
},
  "geometry": {"coordinates":[-80.270781,35.809025],"type":"Point"}
}