{
  "type": "Feature",
  "properties": {
    "addr:full":"388 Haystack Rd Mount Airy NC 27030",
    "addr:housenumber":"388",
    "addr:postcode":"27030",
    "addr:street":"Haystack Rd",
    "iso:country":"US",
    "sg:address":"388 Haystack Rd",
    "sg:city":"Mount Airy",
    "sg:classifiers":[
        {
            "category":"Professional",
            "type":"Services"
        }
    ],
    "sg:phone":"+1 336 320 2289",
    "sg:postcode":"27030",
    "sg:province":"NC",
    "wof:name":"Samuel J Nichols",
    "wof:placetype":"venue"
},
  "geometry": {"coordinates":[-80.710838,36.475953],"type":"Point"}
}