{
  "type": "Feature",
  "properties": {
    "addr:full":"3017 Irma Rd East Bend NC 27018",
    "addr:housenumber":"3017",
    "addr:postcode":"27018",
    "addr:street":"Irma Rd",
    "iso:country":"US",
    "sg:address":"3017 Irma Rd",
    "sg:city":"East Bend",
    "sg:classifiers":[
        {
            "category":"Autos & Motor Vehicles",
            "subcategory":"Automobile Sales",
            "type":"Retail Goods"
        }
    ],
    "sg:phone":"+1 336 699 3982",
    "sg:postcode":"27018",
    "sg:province":"NC",
    "sg:tags":[
        "used"
    ],
    "wof:name":"P A V Used Cars",
    "wof:placetype":"venue"
},
  "geometry": {"coordinates":[-80.566363,36.246782],"type":"Point"}
}