{
  "type": "Feature",
  "properties": {
    "addr:full":"6492 Christian Light Rd Fuquay Varina NC 27526",
    "addr:housenumber":"6492",
    "addr:postcode":"27526",
    "addr:street":"Christian Light Rd",
    "iso:country":"US",
    "sg:address":"6492 Christian Light Rd",
    "sg:city":"Fuquay Varina",
    "sg:classifiers":[
        {
            "category":"Farming",
            "subcategory":"Farm",
            "type":"Manufacturing & Wholesale Goods"
        }
    ],
    "sg:phone":"+1 919 557 0528",
    "sg:postcode":"27526",
    "sg:province":"NC",
    "wof:name":"J & J Farms",
    "wof:placetype":"venue"
},
  "geometry": {"coordinates":[-78.85972700000001,35.525361],"type":"Point"}
}