{
  "type": "Feature",
  "properties": {
    "iso:country":"US",
    "sg:address":"1431 Old Boxwood Cir",
    "sg:city":"Conover",
    "sg:classifiers":[
        {
            "category":"Real Estate",
            "subcategory":"Real Estate Operator",
            "type":"Services"
        }
    ],
    "sg:phone":"+1 828 466 3054",
    "sg:postcode":"28613",
    "sg:province":"NC",
    "sg:tags":[
        "building",
        "nonresidential"
    ],
    "wof:name":"Flg Properties LLC",
    "wof:placetype":"venue"
},
  "geometry": {"coordinates":[-81.239531,35.739603],"type":"Point"}
}