{
  "type": "Feature",
  "properties": {
    "iso:country":"US",
    "sg:address":"404 2nd St SW",
    "sg:city":"Hickory",
    "sg:classifiers":[
        {
            "category":"Personal",
            "subcategory":"Barber",
            "type":"Services"
        }
    ],
    "sg:phone":"+1 828 322 9825",
    "sg:postcode":"28602",
    "sg:province":"NC",
    "wof:name":"Bennett's Barber Shop",
    "wof:placetype":"venue"
},
  "geometry": {"coordinates":[-81.340773,35.727253],"type":"Point"}
}