{
  "type": "Feature",
  "properties": {
    "iso:country":"US",
    "sg:address":"1512 Embler Rd",
    "sg:city":"Lexington",
    "sg:classifiers":[
        {
            "category":"Manufacturing",
            "subcategory":"Watercraft",
            "type":"Manufacturing & Wholesale Goods"
        }
    ],
    "sg:phone":"+1 336 475 5730",
    "sg:postcode":"27292",
    "sg:province":"NC",
    "wof:name":"C D S Marine Inc",
    "wof:placetype":"venue"
},
  "geometry": {"coordinates":[-80.14882299999999,35.808191],"type":"Point"}
}