{
  "type": "Feature",
  "properties": {
    "addr:full":"1460 Sweetbriar Ln Hickory NC 28602",
    "addr:housenumber":"1460",
    "addr:postcode":"28602",
    "addr:street":"Sweetbriar Ln",
    "iso:country":"US",
    "sg:address":"1460 Sweetbriar Ln",
    "sg:city":"Hickory",
    "sg:classifiers":[
        {
            "category":"Freight",
            "type":"Transportation"
        },
        {
            "category":"Professional",
            "subcategory":"Business Services",
            "type":"Services"
        }
    ],
    "sg:phone":"+1 828 294 2115",
    "sg:postcode":"28602",
    "sg:province":"NC",
    "sg:tags":[
        "trucking"
    ],
    "sg:website":"www.usxpress.com",
    "wof:name":"U S Xpress Enterprise Inc",
    "wof:placetype":"venue"
},
  "geometry": {"coordinates":[-81.389999,35.670061],"type":"Point"}
}