{
  "type": "Feature",
  "properties": {
    "addr:full":"2265 Flat Shoals Rd King NC 27021",
    "addr:housenumber":"2265",
    "addr:postcode":"27021",
    "addr:street":"Flat Shoals Rd",
    "iso:country":"US",
    "sg:address":"2265 Flat Shoals Rd",
    "sg:city":"King",
    "sg:classifiers":[
        {
            "category":"Organizations",
            "subcategory":"Religious Organization",
            "type":"Services"
        }
    ],
    "sg:phone":"+1   ",
    "sg:postcode":"27021",
    "sg:province":"NC",
    "wof:name":"Quaker Gap Baptist Church",
    "wof:placetype":"venue"
},
  "geometry": {"coordinates":[-80.290038,36.35489],"type":"Point"}
}