{
  "type": "Feature",
  "properties": {
    "addr:full":"8111 Creedmoor Rd Raleigh NC 27613",
    "addr:housenumber":"8111",
    "addr:postcode":"27613",
    "addr:street":"Creedmoor Rd",
    "iso:country":"US",
    "sg:address":"8111 Creedmoor Rd",
    "sg:city":"Raleigh",
    "sg:classifiers":[
        {
            "category":"Shopping",
            "type":"Retail Goods"
        }
    ],
    "sg:phone":"+1 919 676 0220",
    "sg:postcode":"27613",
    "sg:province":"NC",
    "sg:tags":[
        "craft",
        "gallery",
        "dealer"
    ],
    "wof:name":"Paint Your Own Plaster",
    "wof:placetype":"venue"
},
  "geometry": {"coordinates":[-78.68065300000001,35.89741],"type":"Point"}
}