{
  "type": "Feature",
  "properties": {
    "iso:country":"US",
    "sg:address":"3823 Guess Rd",
    "sg:city":"Durham",
    "sg:classifiers":[
        {
            "category":"Restaurant",
            "type":"Food & Drink"
        }
    ],
    "sg:phone":"+1 919 471 0664",
    "sg:postcode":"27705",
    "sg:province":"NC",
    "wof:name":"Italian Pizzeria Restaurant",
    "wof:placetype":"venue"
},
  "geometry": {"coordinates":[-78.929115,36.05837],"type":"Point"}
}