{
  "type": "Feature",
  "properties": {
    "addr:full":"2031 W Dixon Blvd Shelby NC 28152",
    "addr:housenumber":"2031",
    "addr:postcode":"28152",
    "addr:street":"W Dixon Blvd",
    "iso:country":"US",
    "sg:address":"2031 W Dixon Blvd",
    "sg:city":"Shelby",
    "sg:classifiers":[
        {
            "category":"Banks & Credit Unions",
            "subcategory":"Bank",
            "type":"Services"
        }
    ],
    "sg:phone":"+1 704 481 0111",
    "sg:postcode":"28152",
    "sg:province":"NC",
    "sg:tags":[
        "institution",
        "business"
    ],
    "wof:name":"Amity Finance of Shelby Inc",
    "wof:placetype":"venue"
},
  "geometry": {"coordinates":[-81.589748,35.29387],"type":"Point"}
}