{
  "type": "Feature",
  "properties": {
    "iso:country":"US",
    "sg:address":"261 Oak Rd",
    "sg:city":"Beaufort",
    "sg:classifiers":[
        {
            "category":"Building & Trades",
            "subcategory":"Electrical",
            "type":"Services"
        }
    ],
    "sg:phone":"+1 252 728 3445",
    "sg:postcode":"28516",
    "sg:province":"NC",
    "sg:tags":[
        "electric",
        "contractor"
    ],
    "wof:name":"Williams Electric Co",
    "wof:placetype":"venue"
},
  "geometry": {"coordinates":[-76.65871300000001,34.75613],"type":"Point"}
}