{
  "type": "Feature",
  "properties": {
    "iso:country":"US",
    "sg:address":"1502 E Broad St",
    "sg:city":"Statesville",
    "sg:classifiers":[
        {
            "category":"Restaurant",
            "type":"Food & Drink"
        }
    ],
    "sg:menulink":"http://www.allmenus.com/nc/statesville/91725-shoneys-restaurant/menu/",
    "sg:phone":"+1 704 873 2158",
    "sg:postcode":"28625",
    "sg:province":"NC",
    "sg:tags":[
        "american"
    ],
    "wof:name":"Shoney's Restaurant",
    "wof:placetype":"venue"
},
  "geometry": {"coordinates":[-80.860393,35.790745],"type":"Point"}
}