{
  "type": "Feature",
  "properties": {
    "addr:full":"107 E Water St Plymouth NC 27962",
    "addr:housenumber":"107",
    "addr:postcode":"27962",
    "addr:street":"E Water St",
    "iso:country":"US",
    "sg:address":"107 E Water St",
    "sg:city":"Plymouth",
    "sg:classifiers":[
        {
            "category":"Restaurant",
            "type":"Food & Drink"
        }
    ],
    "sg:phone":"+1 252 793 1039",
    "sg:postcode":"27962",
    "sg:province":"NC",
    "sg:tags":[
        "eating"
    ],
    "wof:name":"Roanoke Oyster Bar",
    "wof:placetype":"venue"
},
  "geometry": {"coordinates":[-76.75023,35.867372],"type":"Point"}
}