{
  "type": "Feature",
  "properties": {
    "iso:country":"US",
    "sg:address":"1211 Parkwood Ave",
    "sg:city":"Charlotte",
    "sg:classifiers":[
        {
            "category":"Personal",
            "subcategory":"Beauty Salon",
            "type":"Services"
        }
    ],
    "sg:phone":"+1 704 333 4918",
    "sg:postcode":"28205",
    "sg:province":"NC",
    "sg:tags":[
        "shop"
    ],
    "wof:name":"Mary Brown's Beauty Palace",
    "wof:placetype":"venue"
},
  "geometry": {"coordinates":[-80.81268300000001,35.233092],"type":"Point"}
}