{
  "type": "Feature",
  "properties": {
    "addr:full":"129 Honeycutt Rd Troutman NC 28166",
    "addr:housenumber":"129",
    "addr:postcode":"28166",
    "addr:street":"Honeycutt Rd",
    "iso:country":"US",
    "sg:address":"129 Honeycutt Rd",
    "sg:city":"Troutman",
    "sg:classifiers":[
        {
            "category":"Manufacturing",
            "subcategory":"Metals",
            "type":"Manufacturing & Wholesale Goods"
        }
    ],
    "sg:phone":"+1 704 878 8823",
    "sg:postcode":"28166",
    "sg:province":"NC",
    "sg:tags":[
        "stainless",
        "mfg",
        "tubing"
    ],
    "sg:website":"www.asti-nc.com",
    "wof:name":"American Stainless Tubing Inc",
    "wof:placetype":"venue"
},
  "geometry": {"coordinates":[-80.90907799999999,35.671174],"type":"Point"}
}