{
  "type": "Feature",
  "properties": {
    "iso:country":"US",
    "sg:address":"1232 W Williams St",
    "sg:city":"Apex",
    "sg:classifiers":[
        {
            "category":"Fast Food",
            "type":"Food & Drink"
        },
        {
            "category":"Food & Beverages",
            "subcategory":"Bakery",
            "type":"Retail Goods"
        }
    ],
    "sg:phone":"+1 919 362 7977",
    "sg:postcode":"27502",
    "sg:province":"NC",
    "sg:tags":[
        "sandwich"
    ],
    "sg:website":"www.subway.com",
    "wof:name":"Subway",
    "wof:placetype":"venue"
},
  "geometry": {"coordinates":[-78.872558,35.745672],"type":"Point"}
}