{
  "type": "Feature",
  "properties": {
    "addr:full":"927 Graham Rd Riegelwood NC 28456",
    "addr:housenumber":"927",
    "addr:postcode":"28456",
    "addr:street":"Graham Rd",
    "iso:country":"US",
    "sg:address":"927 Graham Rd",
    "sg:city":"Riegelwood",
    "sg:classifiers":[
        {
            "category":"Education",
            "subcategory":"Special Training",
            "type":"Public Place"
        }
    ],
    "sg:phone":"+1 910 655 1655",
    "sg:postcode":"28456",
    "sg:province":"NC",
    "sg:tags":[
        "skill",
        "computer",
        "tutoring"
    ],
    "wof:name":"Charles & Eva Munn Foundation",
    "wof:placetype":"venue"
},
  "geometry": {"coordinates":[-78.323049,34.389172],"type":"Point"}
}