{
  "type": "Feature",
  "properties": {
    "iso:country":"US",
    "sg:address":"11 Boardwalk",
    "sg:city":"Carolina Beach",
    "sg:classifiers":[
        {
            "category":"Donuts",
            "subcategory":"None",
            "type":"Food & Drink"
        }
    ],
    "sg:postcode":"28428",
    "sg:province":"NC",
    "wof:name":"Britt's Donuts",
    "wof:placetype":"venue"
},
  "geometry": {"coordinates":[-77.89205800000001,34.03372],"type":"Point"}
}