{
  "type": "Feature",
  "properties": {
    "iso:country":"US",
    "sg:address":"3599 Old Pine Logging Rd",
    "sg:city":"Chadbourn",
    "sg:classifiers":[
        {
            "category":"Professional",
            "subcategory":"Accounting & Tax Preparation",
            "type":"Services"
        }
    ],
    "sg:phone":"+1   ",
    "sg:postcode":"28431",
    "sg:province":"NC",
    "sg:tags":[
        "return"
    ],
    "wof:name":"Hinson Income Tax Preparation",
    "wof:placetype":"venue"
},
  "geometry": {"coordinates":[-78.780581,34.310079],"type":"Point"}
}