{
  "type": "Feature",
  "properties": {
    "iso:country":"US",
    "sg:address":"32 Gator Dr",
    "sg:city":"Lake Waccamaw",
    "sg:classifiers":[
        {
            "category":"Education",
            "subcategory":"School",
            "type":"Public Place"
        }
    ],
    "sg:phone":"+1 910 646 4094",
    "sg:postcode":"28472",
    "sg:province":"NC",
    "wof:name":"East Columbus High School",
    "wof:placetype":"venue"
},
  "geometry": {"coordinates":[-78.736161,34.29131],"type":"Point"}
}