{
  "type": "Feature",
  "properties": {
    "iso:country":"US",
    "sg:address":"532 N Greensboro St",
    "sg:city":"Liberty",
    "sg:classifiers":[
        {
            "category":"Organizations",
            "subcategory":"Religious Organization",
            "type":"Services"
        }
    ],
    "sg:phone":"+1 336 622 0155",
    "sg:postcode":"27298",
    "sg:province":"NC",
    "sg:tags":[
        "church"
    ],
    "wof:name":"Step Of Faith Baptist Church",
    "wof:placetype":"venue"
},
  "geometry": {"coordinates":[-79.572971,35.86178],"type":"Point"}
}