{
  "type": "Feature",
  "properties": {
    "addr:full":"201 Skeet Club Rd High Point NC 27265",
    "addr:housenumber":"201",
    "addr:postcode":"27265",
    "addr:street":"Skeet Club Rd",
    "iso:country":"US",
    "sg:address":"201 Skeet Club Rd",
    "sg:city":"High Point",
    "sg:classifiers":[
        {
            "category":"Personal",
            "subcategory":"Beauty Salon",
            "type":"Services"
        }
    ],
    "sg:phone":"+1   ",
    "sg:postcode":"27265",
    "sg:province":"NC",
    "sg:tags":[
        "shop"
    ],
    "wof:name":"Briarwood Originals",
    "wof:placetype":"venue"
},
  "geometry": {"coordinates":[-80.043544,36.014638],"type":"Point"}
}