{
  "type": "Feature",
  "properties": {
    "addr:full":"657 Rains Mill Rd Princeton NC 27569",
    "addr:housenumber":"657",
    "addr:postcode":"27569",
    "addr:street":"Rains Mill Rd",
    "iso:country":"US",
    "sg:address":"657 Rains Mill Rd",
    "sg:city":"Princeton",
    "sg:classifiers":[
        {
            "category":"Personal",
            "subcategory":"Beauty Salon",
            "type":"Services"
        }
    ],
    "sg:phone":"+1   ",
    "sg:postcode":"27569",
    "sg:province":"NC",
    "sg:tags":[
        "shop"
    ],
    "wof:name":"Perfect Touch",
    "wof:placetype":"venue"
},
  "geometry": {"coordinates":[-78.151445,35.475571],"type":"Point"}
}