{
  "type": "Feature",
  "properties": {
    "iso:country":"US",
    "sg:address":"6111 Shiloh Church Rd",
    "sg:city":"Bailey",
    "sg:classifiers":[
        {
            "category":"Retail",
            "subcategory":"Auto Repair",
            "type":"Services"
        }
    ],
    "sg:phone":"+1 252 265 9299",
    "sg:postcode":"27807",
    "sg:province":"NC",
    "sg:tags":[
        "truck"
    ],
    "wof:name":"Browns Truck & Trailer",
    "wof:placetype":"venue"
},
  "geometry": {"coordinates":[-78.021233,35.776762],"type":"Point"}
}