{
  "type": "Feature",
  "properties": {
    "addr:full":"606 Johnson St Fayetteville NC 28303",
    "addr:housenumber":"606",
    "addr:postcode":"28303",
    "addr:street":"Johnson St",
    "iso:country":"US",
    "sg:address":"606 Johnson St",
    "sg:city":"Fayetteville",
    "sg:classifiers":[
        {
            "category":"Organizations",
            "subcategory":"Professional Association",
            "type":"Services"
        }
    ],
    "sg:phone":"+1 910 868 4010",
    "sg:postcode":"28303",
    "sg:province":"NC",
    "wof:name":"Fayetteville Chapter 82nd Air",
    "wof:placetype":"venue"
},
  "geometry": {"coordinates":[-78.946236,35.096734],"type":"Point"}
}