{
  "type": "Feature",
  "properties": {
    "iso:country":"US",
    "sg:address":"11727 Fruehauf Dr",
    "sg:city":"Charlotte",
    "sg:classifiers":[
        {
            "category":"Manufacturing",
            "subcategory":"Tools & Machinery",
            "type":"Manufacturing & Wholesale Goods"
        }
    ],
    "sg:phone":"+1 704 588 2126",
    "sg:postcode":"28273",
    "sg:province":"NC",
    "sg:tags":[
        "equipment",
        "dental"
    ],
    "wof:name":"Pelton & Crane Co",
    "wof:placetype":"venue"
},
  "geometry": {"coordinates":[-80.95862700000001,35.131583],"type":"Point"}
}