{
  "type": "Feature",
  "properties": {
    "iso:country":"US",
    "sg:address":"720 1st Ave SW",
    "sg:city":"Hickory",
    "sg:classifiers":[
        {
            "category":"Personal",
            "subcategory":"Beauty Salon",
            "type":"Services"
        }
    ],
    "sg:phone":"+1   ",
    "sg:postcode":"28602",
    "sg:province":"NC",
    "sg:tags":[
        "shop"
    ],
    "wof:name":"Yolanda Unisex",
    "wof:placetype":"venue"
},
  "geometry": {"coordinates":[-81.350539,35.730973],"type":"Point"}
}