{
  "type": "Feature",
  "properties": {
    "addr:full":"4520 State Hwy 704 Madison NC 27025",
    "addr:housenumber":"4520",
    "addr:postcode":"27025",
    "addr:street":"State Hwy 704",
    "iso:country":"US",
    "sg:address":"4520 State Hwy 704",
    "sg:city":"Madison",
    "sg:classifiers":[
        {
            "category":"Banks & Credit Unions",
            "subcategory":"Bank",
            "type":"Services"
        }
    ],
    "sg:phone":"+1 336 427 5451",
    "sg:postcode":"27025",
    "sg:province":"NC",
    "sg:tags":[
        "loan"
    ],
    "sg:website":"www.carolinafarmcredit.com",
    "wof:name":"Carolina Farm Credit",
    "wof:placetype":"venue"
},
  "geometry": {"coordinates":[-79.944889,36.376169],"type":"Point"}
}