{
  "type": "Feature",
  "properties": {
    "iso:country":"US",
    "sg:address":"208 S Walton Dr",
    "sg:city":"Benson",
    "sg:classifiers":[
        {
            "category":"Travel",
            "subcategory":"Hotels & Motels",
            "type":"Entertainment"
        }
    ],
    "sg:phone":"+1 919 894 7562",
    "sg:postcode":"27504",
    "sg:province":"NC",
    "wof:name":"Dutch Inn",
    "wof:placetype":"venue"
},
  "geometry": {"coordinates":[-78.54040000000001,35.375323],"type":"Point"}
}