{
  "type": "Feature",
  "properties": {
    "addr:full":"5188 State Hwy 119 Mebane NC 27302",
    "addr:housenumber":"5188",
    "addr:postcode":"27302",
    "addr:street":"State Hwy 119",
    "iso:country":"US",
    "sg:address":"5188 State Hwy 119",
    "sg:city":"Mebane",
    "sg:classifiers":[
        {
            "category":"Retail",
            "subcategory":"Repair Shop",
            "type":"Services"
        }
    ],
    "sg:phone":"+1   ",
    "sg:postcode":"27302",
    "sg:province":"NC",
    "wof:name":"Vernons Septic Systems",
    "wof:placetype":"venue"
},
  "geometry": {"coordinates":[-79.291859,36.218038],"type":"Point"}
}