{
  "type": "Feature",
  "properties": {
    "iso:country":"US",
    "sg:address":"1014 Robeson St",
    "sg:city":"Fayetteville",
    "sg:classifiers":[
        {
            "category":"Personal",
            "type":"Services"
        }
    ],
    "sg:phone":"+1   ",
    "sg:postcode":"28305",
    "sg:province":"NC",
    "wof:name":"Bob Jacksons Hair Additions",
    "wof:placetype":"venue"
},
  "geometry": {"coordinates":[-78.901872,35.040599],"type":"Point"}
}