{
  "type": "Feature",
  "properties": {
    "addr:full":"2250 Chicken Foot Rd Hope Mills NC 28348",
    "addr:housenumber":"2250",
    "addr:postcode":"28348",
    "addr:street":"Chicken Foot Rd",
    "iso:country":"US",
    "sg:address":"2250 Chicken Foot Rd",
    "sg:city":"Hope Mills",
    "sg:classifiers":[
        {
            "category":"Organizations",
            "subcategory":"Religious Organization",
            "type":"Services"
        }
    ],
    "sg:phone":"+1 910 426 2900",
    "sg:postcode":"28348",
    "sg:province":"NC",
    "wof:name":"World Faith Clinic Church",
    "wof:placetype":"venue"
},
  "geometry": {"coordinates":[-78.90791299999999,34.91511],"type":"Point"}
}