{
  "type": "Feature",
  "properties": {
    "addr:full":"812 Barbara Dr Raleigh NC 27606",
    "addr:housenumber":"812",
    "addr:postcode":"27606",
    "addr:street":"Barbara Dr",
    "iso:country":"US",
    "sg:address":"812 Barbara Dr",
    "sg:city":"Raleigh",
    "sg:classifiers":[
        {
            "category":"Professional",
            "type":"Services"
        }
    ],
    "sg:phone":"+1 919 859 9233",
    "sg:postcode":"27606",
    "sg:province":"NC",
    "wof:name":"Game Visions Inc",
    "wof:placetype":"venue"
},
  "geometry": {"coordinates":[-78.70008799999999,35.77111],"type":"Point"}
}