{
  "type": "Feature",
  "properties": {
    "addr:full":"1298 Fairway Dr Newton NC 28658",
    "addr:housenumber":"1298",
    "addr:postcode":"28658",
    "addr:street":"Fairway Dr",
    "iso:country":"US",
    "sg:address":"1298 Fairway Dr",
    "sg:city":"Newton",
    "sg:classifiers":[
        {
            "category":"Farming",
            "subcategory":"Farm",
            "type":"Manufacturing & Wholesale Goods"
        }
    ],
    "sg:phone":"+1 828 695 0807",
    "sg:postcode":"28658",
    "sg:province":"NC",
    "sg:tags":[
        "crop",
        "general"
    ],
    "wof:name":"B&R Farms LLC",
    "wof:placetype":"venue"
},
  "geometry": {"coordinates":[-81.28345299999999,35.64824],"type":"Point"}
}