{
  "type": "Feature",
  "properties": {
    "iso:country":"US",
    "sg:address":"111 E 3rd St",
    "sg:city":"Greenville",
    "sg:classifiers":[
        {
            "category":"Manufacturing",
            "subcategory":"Electronics",
            "type":"Manufacturing & Wholesale Goods"
        }
    ],
    "sg:phone":"+1 252 561 7733",
    "sg:postcode":"27858",
    "sg:province":"NC",
    "sg:tags":[
        "equipment",
        "mfg",
        "business",
        "communication"
    ],
    "wof:name":"Sharp Inc",
    "wof:placetype":"venue"
},
  "geometry": {"coordinates":[-77.372407,35.613256],"type":"Point"}
}