{
  "type": "Feature",
  "properties": {
    "addr:full":"11 W Front St Lillington NC 27546",
    "addr:housenumber":"11",
    "addr:postcode":"27546",
    "addr:street":"W Front St",
    "iso:country":"US",
    "sg:address":"11 W Front St",
    "sg:city":"Lillington",
    "sg:classifiers":[
        {
            "category":"Food & Beverages",
            "subcategory":"Groceries & Convenience Stores",
            "type":"Retail Goods"
        }
    ],
    "sg:phone":"+1 910 893 3046",
    "sg:postcode":"27546",
    "sg:province":"NC",
    "sg:tags":[
        "grocer"
    ],
    "wof:name":"Carlie C's IGA",
    "wof:placetype":"venue"
},
  "geometry": {"coordinates":[-78.817424,35.398995],"type":"Point"}
}