{
  "type": "Feature",
  "properties": {
    "iso:country":"US",
    "sg:address":"1683 Bud Hawkins Rd",
    "sg:city":"Dunn",
    "sg:classifiers":[
        {
            "category":"Education",
            "subcategory":"College",
            "type":"Public Place"
        }
    ],
    "sg:phone":"+1 910 892 3178",
    "sg:postcode":"28334",
    "sg:province":"NC",
    "sg:tags":[
        "academic",
        "school"
    ],
    "wof:name":"Heritage Bible College",
    "wof:placetype":"venue"
},
  "geometry": {"coordinates":[-78.613657,35.268178],"type":"Point"}
}