{
  "type": "Feature",
  "properties": {
    "iso:country":"US",
    "sg:address":"4140 Concord Pkwy S",
    "sg:city":"Concord",
    "sg:classifiers":[
        {
            "category":"Manufacturing",
            "subcategory":"Tools & Machinery",
            "type":"Manufacturing & Wholesale Goods"
        }
    ],
    "sg:phone":"+1 704 782 9336",
    "sg:postcode":"28027",
    "sg:province":"NC",
    "sg:tags":[
        "machine",
        "shop"
    ],
    "wof:name":"Ace EDM & Tool",
    "wof:placetype":"venue"
},
  "geometry": {"coordinates":[-80.66942899999999,35.363779],"type":"Point"}
}