{
  "type": "Feature",
  "properties": {
    "addr:full":"108 W Main St Benson NC 27504",
    "addr:housenumber":"108",
    "addr:postcode":"27504",
    "addr:street":"W Main St",
    "iso:country":"US",
    "sg:address":"108 W Main St",
    "sg:city":"Benson",
    "sg:classifiers":[
        {
            "category":"Professional",
            "subcategory":"Lawyer & Legal Services",
            "type":"Services"
        }
    ],
    "sg:phone":"+1 919 894 3845",
    "sg:postcode":"27504",
    "sg:province":"NC",
    "sg:tags":[
        "attorney"
    ],
    "wof:name":"Jack E Mc Lamb III",
    "wof:placetype":"venue"
},
  "geometry": {"coordinates":[-78.54807,35.381546],"type":"Point"}
}