{
  "type": "Feature",
  "properties": {
    "iso:country":"US",
    "sg:address":"1318 Ramseur Rd",
    "sg:city":"Bessemer City",
    "sg:classifiers":[
        {
            "category":"Retail",
            "subcategory":"Repair Shop",
            "type":"Services"
        }
    ],
    "sg:phone":"+1 704 629 9722",
    "sg:postcode":"28016",
    "sg:province":"NC",
    "sg:tags":[
        "industrial",
        "electronic",
        "manufacturing"
    ],
    "sg:website":"www.essautomation.com",
    "wof:name":"ESS Automation Inc",
    "wof:placetype":"venue"
},
  "geometry": {"coordinates":[-81.307039,35.309312],"type":"Point"}
}