{
  "type": "Feature",
  "properties": {
    "iso:country":"US",
    "sg:address":"5925 Falls of Neuse Rd",
    "sg:city":"Raleigh",
    "sg:classifiers":[
        {
            "category":"Real Estate",
            "subcategory":"Real Estate Agent",
            "type":"Services"
        }
    ],
    "sg:phone":"+1 919 874 7529",
    "sg:postcode":"27609",
    "sg:province":"NC",
    "wof:name":"DOT Winchester Rl Est",
    "wof:placetype":"venue"
},
  "geometry": {"coordinates":[-78.620041,35.863855],"type":"Point"}
}