{
  "type": "Feature",
  "properties": {
    "addr:full":"1000 White Oak Creek Dr Apex NC 27523",
    "addr:housenumber":"1000",
    "addr:postcode":"27523",
    "addr:street":"White Oak Creek Dr",
    "iso:country":"US",
    "sg:address":"1000 White Oak Creek Dr",
    "sg:city":"Apex",
    "sg:classifiers":[
        {
            "category":"Wholesale",
            "subcategory":"Chemicals & Plastics",
            "type":"Manufacturing & Wholesale Goods"
        }
    ],
    "sg:phone":"+1 919 367 8933",
    "sg:postcode":"27523",
    "sg:province":"NC",
    "wof:name":"Klm Chem Consultants LLC",
    "wof:placetype":"venue"
},
  "geometry": {"coordinates":[-78.90903900000001,35.765633],"type":"Point"}
}