{
  "type": "Feature",
  "properties": {
    "addr:full":"321 Rollover Creek Rd New Bern NC 28562",
    "addr:housenumber":"321",
    "addr:postcode":"28562",
    "addr:street":"Rollover Creek Rd",
    "iso:country":"US",
    "sg:address":"321 Rollover Creek Rd",
    "sg:city":"New Bern",
    "sg:classifiers":[
        {
            "category":"Building & Trades",
            "subcategory":"Plumbing",
            "type":"Services"
        }
    ],
    "sg:phone":"+1 252 638 6336",
    "sg:postcode":"28562",
    "sg:province":"NC",
    "sg:tags":[
        "tank",
        "septic"
    ],
    "wof:name":"D & D Septic Tank Svc",
    "wof:placetype":"venue"
},
  "geometry": {"coordinates":[-77.222725,35.147319],"type":"Point"}
}