{
  "type": "Feature",
  "properties": {
    "iso:country":"US",
    "sg:address":"1505 Old Winberry Rd",
    "sg:city":"Newport",
    "sg:classifiers":[
        {
            "category":"Building & Trades",
            "subcategory":"Landscaping Services",
            "type":"Services"
        }
    ],
    "sg:phone":"+1 252 727 0903",
    "sg:postcode":"28570",
    "sg:province":"NC",
    "sg:tags":[
        "ornamental",
        "nursery",
        "landscape"
    ],
    "wof:name":"Chadwicks Nursery & Ldscpg",
    "wof:placetype":"venue"
},
  "geometry": {"coordinates":[-76.73686600000001,34.818288],"type":"Point"}
}