{
  "type": "Feature",
  "properties": {
    "addr:full":"2301 Olde Whitehall Rd Charlotte NC 28273",
    "addr:housenumber":"2301",
    "addr:postcode":"28273",
    "addr:street":"Olde Whitehall Rd",
    "iso:country":"US",
    "sg:address":"2301 Olde Whitehall Rd",
    "sg:city":"Charlotte",
    "sg:classifiers":[
        {
            "category":"Social Services",
            "subcategory":"Child Care",
            "type":"Services"
        }
    ],
    "sg:phone":"+1 704 376 2231",
    "sg:postcode":"28273",
    "sg:province":"NC",
    "wof:name":"Ann's West Boulevard Child",
    "wof:placetype":"venue"
},
  "geometry": {"coordinates":[-80.923187,35.154632],"type":"Point"}
}