{
  "type": "Feature",
  "properties": {
    "addr:full":"628 Green Valley Rd Greensboro NC 27408",
    "addr:housenumber":"628",
    "addr:postcode":"27408",
    "addr:street":"Green Valley Rd",
    "iso:country":"US",
    "sg:address":"628 Green Valley Rd",
    "sg:city":"Greensboro",
    "sg:classifiers":[
        {
            "category":"Professional",
            "subcategory":"Business Services",
            "type":"Services"
        }
    ],
    "sg:phone":"+1 336 217 9415",
    "sg:postcode":"27408",
    "sg:province":"NC",
    "sg:tags":[
        "paralegal"
    ],
    "wof:name":"Settlement Source",
    "wof:placetype":"venue"
},
  "geometry": {"coordinates":[-79.82563399999999,36.088338],"type":"Point"}
}