{
  "type": "Feature",
  "properties": {
    "addr:full":"463 Old Folkstone Rd Holly Ridge NC 28445",
    "addr:housenumber":"463",
    "addr:postcode":"28445",
    "addr:street":"Old Folkstone Rd",
    "iso:country":"US",
    "sg:address":"463 Old Folkstone Rd",
    "sg:city":"Holly Ridge",
    "sg:classifiers":[
        {
            "category":"Professional",
            "subcategory":"Management & Consulting",
            "type":"Services"
        }
    ],
    "sg:phone":"+1   ",
    "sg:postcode":"28445",
    "sg:province":"NC",
    "wof:name":"Parker G&T Enterprises",
    "wof:placetype":"venue"
},
  "geometry": {"coordinates":[-77.471321,34.524974],"type":"Point"}
}