{
  "type": "Feature",
  "properties": {
    "iso:country":"US",
    "sg:address":"766 4th St SW",
    "sg:city":"Hickory",
    "sg:classifiers":[
        {
            "category":"Restaurant",
            "type":"Food & Drink"
        }
    ],
    "sg:phone":"+1 828 328 4597",
    "sg:postcode":"28602",
    "sg:province":"NC",
    "wof:name":"Charolais Steakhouse",
    "wof:placetype":"venue"
},
  "geometry": {"coordinates":[-81.345478,35.721545],"type":"Point"}
}