{
  "type": "Feature",
  "properties": {
    "iso:country":"US",
    "sg:address":"3585 Boy Scout Camp Rd",
    "sg:city":"Kannapolis",
    "sg:classifiers":[
        {
            "category":"Real Estate",
            "subcategory":"Real Estate Operator",
            "type":"Services"
        }
    ],
    "sg:phone":"+1 704 782 0032",
    "sg:postcode":"28081",
    "sg:province":"NC",
    "sg:tags":[
        "building",
        "nonresidential"
    ],
    "wof:name":"Craven Sports Properties",
    "wof:placetype":"venue"
},
  "geometry": {"coordinates":[-80.667754,35.464723],"type":"Point"}
}