{
  "type": "Feature",
  "properties": {
    "iso:country":"US",
    "sg:address":"4034 Old Beulah Rd",
    "sg:city":"Selma",
    "sg:classifiers":[
        {
            "category":"Building & Trades",
            "subcategory":"Construction",
            "type":"Services"
        }
    ],
    "sg:phone":"+1 919 868 6536",
    "sg:postcode":"27576",
    "sg:province":"NC",
    "sg:tags":[
        "contractor"
    ],
    "wof:name":"Jl Baker Masonry",
    "wof:placetype":"venue"
},
  "geometry": {"coordinates":[-78.22241,35.583177],"type":"Point"}
}