{
  "type": "Feature",
  "properties": {
    "addr:full":"10 Sugar Maple Dr Black Mountain NC 28759",
    "addr:housenumber":"10",
    "addr:postcode":"28759",
    "addr:street":"Sugar Maple Dr",
    "iso:country":"US",
    "sg:address":"10 Sugar Maple Dr",
    "sg:city":"Black Mountain",
    "sg:classifiers":[
        {
            "category":"Organizations",
            "subcategory":"Religious Organization",
            "type":"Services"
        }
    ],
    "sg:phone":"+1 828 669 8411",
    "sg:postcode":"28759",
    "sg:province":"NC",
    "sg:website":"www.cbu.org",
    "wof:name":"Christian Believers United",
    "wof:placetype":"venue"
},
  "geometry": {"coordinates":[-82.591311,35.42847],"type":"Point"}
}