{
  "type": "Feature",
  "properties": {
    "addr:full":"500 Cornerstone Ct Hillsborough NC 27278",
    "addr:housenumber":"500",
    "addr:postcode":"27278",
    "addr:street":"Cornerstone Ct",
    "iso:country":"US",
    "sg:address":"500 Cornerstone Ct",
    "sg:city":"Hillsborough",
    "sg:classifiers":[
        {
            "category":"Wholesale",
            "subcategory":"Auto Parts",
            "type":"Manufacturing & Wholesale Goods"
        }
    ],
    "sg:phone":"+1 919 732 5182",
    "sg:postcode":"27278",
    "sg:province":"NC",
    "sg:tags":[
        "equipment",
        "towing"
    ],
    "wof:name":"Big Johns Towing",
    "wof:placetype":"venue"
},
  "geometry": {"coordinates":[-79.08689099999999,36.061116],"type":"Point"}
}