{
  "type": "Feature",
  "properties": {
    "iso:country":"US",
    "sg:address":"1925 Banks School Rd",
    "sg:city":"Kinston",
    "sg:classifiers":[
        {
            "category":"Food & Beverages",
            "subcategory":"Groceries & Convenience Stores",
            "type":"Retail Goods"
        }
    ],
    "sg:phone":"+1 252 939 3910",
    "sg:postcode":"28504",
    "sg:province":"NC",
    "wof:name":"La Esperanza",
    "wof:placetype":"venue"
},
  "geometry": {"coordinates":[-77.64619,35.281666],"type":"Point"}
}