{
  "type": "Feature",
  "properties": {
    "iso:country":"US",
    "sg:address":"225 S Hancock St",
    "sg:city":"Rockingham",
    "sg:classifiers":[
        {
            "category":"Health Services",
            "subcategory":"Clinic",
            "type":"Services"
        }
    ],
    "sg:phone":"+1 910 997 7350",
    "sg:postcode":"28379",
    "sg:province":"NC",
    "sg:tags":[
        "home"
    ],
    "wof:name":"Promised Land Family Svc",
    "wof:placetype":"venue"
},
  "geometry": {"coordinates":[-79.773245,34.937581],"type":"Point"}
}