{
  "type": "Feature",
  "properties": {
    "addr:full":"2430 State Hwy 87 Graham NC 27253",
    "addr:housenumber":"2430",
    "addr:postcode":"27253",
    "addr:street":"State Hwy 87",
    "iso:country":"US",
    "sg:address":"2430 State Hwy 87",
    "sg:city":"Graham",
    "sg:classifiers":[
        {
            "category":"Building & Trades",
            "subcategory":"Plumbing",
            "type":"Services"
        }
    ],
    "sg:phone":"+1 336 226 7492",
    "sg:postcode":"27253",
    "sg:province":"NC",
    "sg:tags":[
        "plumbing",
        "contractor"
    ],
    "wof:name":"Garner-Murphy Construction Co",
    "wof:placetype":"venue"
},
  "geometry": {"coordinates":[-79.39160699999999,36.018116],"type":"Point"}
}