{
  "type": "Feature",
  "properties": {
    "iso:country":"US",
    "sg:address":"7904 Daltonshire Dr",
    "sg:city":"Oak Ridge",
    "sg:classifiers":[
        {
            "category":"Manufacturing",
            "subcategory":"Printing",
            "type":"Manufacturing & Wholesale Goods"
        }
    ],
    "sg:phone":"+1 336 643 6186",
    "sg:postcode":"27310",
    "sg:province":"NC",
    "sg:tags":[
        "publishing"
    ],
    "wof:name":"Newsletter Etc",
    "wof:placetype":"venue"
},
  "geometry": {"coordinates":[-79.98497999999999,36.20495],"type":"Point"}
}