{
  "type": "Feature",
  "properties": {
    "addr:full":"2033 Colony Hill Dr Charlotte NC 28214",
    "addr:housenumber":"2033",
    "addr:postcode":"28214",
    "addr:street":"Colony Hill Dr",
    "iso:country":"US",
    "sg:address":"2033 Colony Hill Dr",
    "sg:city":"Charlotte",
    "sg:classifiers":[
        {
            "category":"Professional",
            "subcategory":"Art Services",
            "type":"Services"
        }
    ],
    "sg:phone":"+1 704 391 7370",
    "sg:postcode":"28214",
    "sg:province":"NC",
    "sg:tags":[
        "graphic",
        "designer"
    ],
    "wof:name":"Bottomline Graphics & Design",
    "wof:placetype":"venue"
},
  "geometry": {"coordinates":[-80.96156999999999,35.300223],"type":"Point"}
}