{
  "type": "Feature",
  "properties": {
    "addr:full":"109 S Market St Willow Spring NC 27504",
    "addr:housenumber":"109",
    "addr:postcode":"27504",
    "addr:street":"S Market St",
    "iso:country":"US",
    "sg:address":"109 S Market St",
    "sg:city":"Willow Spring",
    "sg:classifiers":[
        {
            "category":"Wholesale",
            "subcategory":"Electrical",
            "type":"Manufacturing & Wholesale Goods"
        }
    ],
    "sg:phone":"+1 919 894 7027",
    "sg:postcode":"27504",
    "sg:province":"NC",
    "sg:tags":[
        "control",
        "security",
        "system"
    ],
    "wof:name":"Southern Security & Autmtns",
    "wof:placetype":"venue"
},
  "geometry": {"coordinates":[-78.546746,35.380653],"type":"Point"}
}