{
  "type": "Feature",
  "properties": {
    "addr:full":"145 Gray Sheeks Rd Advance NC 27006",
    "addr:housenumber":"145",
    "addr:postcode":"27006",
    "addr:street":"Gray Sheeks Rd",
    "iso:country":"US",
    "sg:address":"145 Gray Sheeks Rd",
    "sg:city":"Advance",
    "sg:classifiers":[
        {
            "category":"Manufacturing",
            "subcategory":"Wood Products",
            "type":"Manufacturing & Wholesale Goods"
        }
    ],
    "sg:phone":"+1 336 940 5096",
    "sg:postcode":"27006",
    "sg:province":"NC",
    "sg:tags":[
        "mfg"
    ],
    "wof:name":"Frame Master",
    "wof:placetype":"venue"
},
  "geometry": {"coordinates":[-80.452342,35.999439],"type":"Point"}
}