{
  "type": "Feature",
  "properties": {
    "addr:full":"14 N Jefferson Ave West Jefferson NC 28694",
    "addr:housenumber":"14",
    "addr:postcode":"28694",
    "addr:street":"N Jefferson Ave",
    "iso:country":"US",
    "sg:address":"14 N Jefferson Ave",
    "sg:city":"West Jefferson",
    "sg:classifiers":[
        {
            "category":"Shopping",
            "subcategory":"Clothing, Apparel, & Fashions",
            "type":"Retail Goods"
        }
    ],
    "sg:phone":"+1 336 246 9133",
    "sg:postcode":"28694",
    "sg:province":"NC",
    "wof:name":"Mountain Outfitters",
    "wof:placetype":"venue"
},
  "geometry": {"coordinates":[-81.49265699999999,36.402861],"type":"Point"}
}