{
  "type": "Feature",
  "properties": {
    "iso:country":"US",
    "sg:address":"860 Jetton St",
    "sg:city":"Davidson",
    "sg:classifiers":[
        {
            "category":"Insurance",
            "subcategory":"Insurance Agent",
            "type":"Services"
        }
    ],
    "sg:phone":"+1 704 895 1517",
    "sg:postcode":"28036",
    "sg:province":"NC",
    "wof:name":"Blue Ridge Risk Services",
    "wof:placetype":"venue"
},
  "geometry": {"coordinates":[-80.861254,35.502195],"type":"Point"}
}