{
  "type": "Feature",
  "properties": {
    "addr:full":"553 W Dixie Dr Asheboro NC 27205",
    "addr:housenumber":"553",
    "addr:postcode":"27205",
    "addr:street":"W Dixie Dr",
    "iso:country":"US",
    "sg:address":"553 W Dixie Dr",
    "sg:city":"Asheboro",
    "sg:classifiers":[
        {
            "category":"Restaurant",
            "type":"Food & Drink"
        }
    ],
    "sg:phone":"+1 336 626 6500",
    "sg:postcode":"27205",
    "sg:province":"NC",
    "wof:name":"Bojangles' Famous Chicken",
    "wof:placetype":"venue"
},
  "geometry": {"coordinates":[-79.821853,35.687762],"type":"Point"}
}