{
  "type": "Feature",
  "properties": {
    "addr:full":"1708 Shagbark Ln Charlotte NC 28226",
    "addr:housenumber":"1708",
    "addr:postcode":"28226",
    "addr:street":"Shagbark Ln",
    "iso:country":"US",
    "sg:address":"1708 Shagbark Ln",
    "sg:city":"Charlotte",
    "sg:classifiers":[
        {
            "category":"Professional",
            "subcategory":"Business Services",
            "type":"Services"
        }
    ],
    "sg:phone":"+1   ",
    "sg:postcode":"28226",
    "sg:province":"NC",
    "wof:name":"Cain Enterprises",
    "wof:placetype":"venue"
},
  "geometry": {"coordinates":[-80.797988,35.142048],"type":"Point"}
}