{
  "type": "Feature",
  "properties": {
    "addr:full":"349 Copperfield Blvd NE Concord NC 28025",
    "addr:housenumber":"349",
    "addr:postcode":"28025",
    "addr:street":"Copperfield Blvd Ne",
    "iso:country":"US",
    "sg:address":"349 Copperfield Blvd NE",
    "sg:city":"Concord",
    "sg:classifiers":[
        {
            "category":"Shopping",
            "subcategory":"Computers & Home Electronics",
            "type":"Retail Goods"
        }
    ],
    "sg:phone":"+1 704 786 1102",
    "sg:postcode":"28025",
    "sg:province":"NC",
    "wof:name":"Computer Renaissance",
    "wof:placetype":"venue"
},
  "geometry": {"coordinates":[-80.598438,35.446898],"type":"Point"}
}