{
  "type": "Feature",
  "properties": {
    "iso:country":"US",
    "sg:address":"6 Dogwood Road",
    "sg:city":"Candler",
    "sg:classifiers":[
        {
            "category":"Banks & Credit Unions",
            "subcategory":"Bank",
            "type":"Services"
        }
    ],
    "sg:phone":"+1 828 281 0012",
    "sg:postcode":"28715",
    "sg:province":"NC",
    "sg:website":"www.bankofasheville.com/",
    "wof:name":"Bank of Asheville",
    "wof:placetype":"venue"
},
  "geometry": {"coordinates":[-82.683787,35.544891],"type":"Point"}
}