{
  "type": "Feature",
  "properties": {
    "iso:country":"US",
    "sg:address":"3004 Barnsley Trl",
    "sg:city":"Raleigh",
    "sg:classifiers":[
        {
            "category":"Building & Trades",
            "subcategory":"Construction",
            "type":"Services"
        }
    ],
    "sg:phone":"+1 919 212 0201",
    "sg:postcode":"27604",
    "sg:province":"NC",
    "sg:tags":[
        "contractor"
    ],
    "wof:name":"Humphrey Homes Inc",
    "wof:placetype":"venue"
},
  "geometry": {"coordinates":[-78.550461,35.82232],"type":"Point"}
}