{
  "type": "Feature",
  "properties": {
    "addr:full":"302 W Boundary St La Grange NC 28551",
    "addr:housenumber":"302",
    "addr:postcode":"28551",
    "addr:street":"W Boundary St",
    "iso:country":"US",
    "sg:address":"302 W Boundary St",
    "sg:city":"La Grange",
    "sg:classifiers":[
        {
            "category":"Personal",
            "subcategory":"Beauty Salon",
            "type":"Services"
        }
    ],
    "sg:phone":"+1   ",
    "sg:postcode":"28551",
    "sg:province":"NC",
    "sg:tags":[
        "shop"
    ],
    "wof:name":"Ettas Hairstyling",
    "wof:placetype":"venue"
},
  "geometry": {"coordinates":[-77.796587,35.306571],"type":"Point"}
}