{
  "type": "Feature",
  "properties": {
    "addr:full":"208 Courtney Ln Matthews NC 28105",
    "addr:housenumber":"208",
    "addr:postcode":"28105",
    "addr:street":"Courtney Ln",
    "iso:country":"US",
    "sg:address":"208 Courtney Ln",
    "sg:city":"Matthews",
    "sg:classifiers":[
        {
            "category":"Professional",
            "subcategory":"Employment Agencies",
            "type":"Services"
        }
    ],
    "sg:phone":"+1   ",
    "sg:postcode":"28105",
    "sg:province":"NC",
    "wof:name":"North Carolina Nurses Assoc",
    "wof:placetype":"venue"
},
  "geometry": {"coordinates":[-80.738871,35.106513],"type":"Point"}
}