{
  "type": "Feature",
  "properties": {
    "iso:country":"US",
    "sg:address":"1041 Poncho Ln",
    "sg:city":"Yadkinville",
    "sg:classifiers":[
        {
            "category":"Professional",
            "type":"Services"
        }
    ],
    "sg:phone":"+1 336 961 2786",
    "sg:postcode":"27055",
    "sg:province":"NC",
    "sg:tags":[
        "establishment"
    ],
    "wof:name":"Sentry K9 Inc",
    "wof:placetype":"venue"
},
  "geometry": {"coordinates":[-80.596351,36.190803],"type":"Point"}
}