{
  "type": "Feature",
  "properties": {
    "addr:full":"6774 Sonnys Ln Rocky Mount NC 27803",
    "addr:housenumber":"6774",
    "addr:postcode":"27803",
    "addr:street":"Sonnys Ln",
    "iso:country":"US",
    "sg:address":"6774 Sonnys Ln",
    "sg:city":"Rocky Mount",
    "sg:classifiers":[
        {
            "category":"Building & Trades",
            "subcategory":"Cleaning & Sanitation",
            "type":"Services"
        }
    ],
    "sg:phone":"+1   ",
    "sg:postcode":"27803",
    "sg:province":"NC",
    "sg:tags":[
        "maintenance"
    ],
    "wof:name":"Pitt County Properties L L C",
    "wof:placetype":"venue"
},
  "geometry": {"coordinates":[-77.880651,35.883238],"type":"Point"}
}