{
  "type": "Feature",
  "properties": {
    "iso:country":"US",
    "sg:address":"225 N Depot St",
    "sg:city":"Albemarle",
    "sg:classifiers":[
        {
            "category":"Manufacturing",
            "subcategory":"Tools & Machinery",
            "type":"Manufacturing & Wholesale Goods"
        }
    ],
    "sg:phone":"+1 704 983 6102",
    "sg:postcode":"28001",
    "sg:province":"NC",
    "sg:tags":[
        "physician",
        "surgeon"
    ],
    "wof:name":"American Fiber & Finishing Inc",
    "wof:placetype":"venue"
},
  "geometry": {"coordinates":[-80.201387,35.353781],"type":"Point"}
}