{
  "type": "Feature",
  "properties": {
    "iso:country":"US",
    "sg:address":"3865 State Hwy 210 E",
    "sg:city":"Harrells",
    "sg:classifiers":[
        {
            "category":"Food & Beverages",
            "subcategory":"Groceries & Convenience Stores",
            "type":"Retail Goods"
        },
        {
            "category":"Shopping",
            "subcategory":"Department Store",
            "type":"Retail Goods"
        }
    ],
    "sg:phone":"+1 910 532 4288",
    "sg:postcode":"28444",
    "sg:province":"NC",
    "wof:name":"Mark's Store",
    "wof:placetype":"venue"
},
  "geometry": {"coordinates":[-78.381981,34.70694],"type":"Point"}
}