{
  "type": "Feature",
  "properties": {
    "addr:full":"342 Church St N Concord NC 28025",
    "addr:housenumber":"342",
    "addr:postcode":"28025",
    "addr:street":"Church St N",
    "iso:country":"US",
    "sg:address":"342 Church St N",
    "sg:city":"Concord",
    "sg:classifiers":[
        {
            "category":"Personal",
            "subcategory":"Beauty Salon",
            "type":"Services"
        }
    ],
    "sg:phone":"+1   ",
    "sg:postcode":"28025",
    "sg:province":"NC",
    "sg:tags":[
        "shop"
    ],
    "wof:name":"Wendys Hair Designs",
    "wof:placetype":"venue"
},
  "geometry": {"coordinates":[-80.589839,35.420051],"type":"Point"}
}