{
  "type": "Feature",
  "properties": {
    "addr:full":"907 Martin Luther King Jr Dr Greenville NC 27834",
    "addr:housenumber":"907",
    "addr:postcode":"27834",
    "addr:street":"Martin Luther King Jr Dr",
    "iso:country":"US",
    "sg:address":"907 Martin Luther King Jr Dr",
    "sg:city":"Greenville",
    "sg:classifiers":[
        {
            "category":"Organizations",
            "subcategory":"Religious Organization",
            "type":"Services"
        }
    ],
    "sg:phone":"+1 252 413 6135",
    "sg:postcode":"27834",
    "sg:province":"NC",
    "sg:tags":[
        "mosque"
    ],
    "wof:name":"Muhammad Mosque",
    "wof:placetype":"venue"
},
  "geometry": {"coordinates":[-77.38370500000001,35.612497],"type":"Point"}
}