{
  "type": "Feature",
  "properties": {
    "addr:full":"112 Market St Wilmington NC 28401",
    "addr:housenumber":"112",
    "addr:postcode":"28401",
    "addr:street":"Market St",
    "iso:country":"US",
    "sg:address":"112 Market St",
    "sg:city":"Wilmington",
    "sg:classifiers":[
        {
            "category":"Real Estate",
            "subcategory":"Real Estate Agent",
            "type":"Services"
        }
    ],
    "sg:phone":"+1 910 256 8171",
    "sg:postcode":"28401",
    "sg:province":"NC",
    "wof:name":"Re/Max Coastal Properties",
    "wof:placetype":"venue"
},
  "geometry": {"coordinates":[-77.947541,34.235283],"type":"Point"}
}