{
  "type": "Feature",
  "properties": {
    "iso:country":"US",
    "sg:address":"462 Robeson St",
    "sg:city":"Fayetteville",
    "sg:classifiers":[
        {
            "category":"Freight",
            "type":"Transportation"
        }
    ],
    "sg:phone":"+1 910 485 5329",
    "sg:postcode":"28301",
    "sg:province":"NC",
    "sg:tags":[
        "mover"
    ],
    "wof:name":"Murray Transfer & Storage Co",
    "wof:placetype":"venue"
},
  "geometry": {"coordinates":[-78.89155,35.046046],"type":"Point"}
}