{
  "type": "Feature",
  "properties": {
    "addr:full":"820 W Vernon Ave Kinston NC 28501",
    "addr:housenumber":"820",
    "addr:postcode":"28501",
    "addr:street":"W Vernon Ave",
    "iso:country":"US",
    "sg:address":"820 W Vernon Ave",
    "sg:city":"Kinston",
    "sg:classifiers":[
        {
            "category":"Autos & Motor Vehicles",
            "subcategory":"Auto Supplies",
            "type":"Retail Goods"
        }
    ],
    "sg:phone":"+1 252 523 3151",
    "sg:postcode":"28501",
    "sg:province":"NC",
    "sg:tags":[
        "automobile",
        "parts"
    ],
    "wof:name":"NAPA Auto Parts",
    "wof:placetype":"venue"
},
  "geometry": {"coordinates":[-77.592035,35.269635],"type":"Point"}
}