{
  "type": "Feature",
  "properties": {
    "addr:full":"217 Greenview Dr Wilmington NC 28411",
    "addr:housenumber":"217",
    "addr:postcode":"28411",
    "addr:street":"Greenview Dr",
    "iso:country":"US",
    "sg:address":"217 Greenview Dr",
    "sg:city":"Wilmington",
    "sg:classifiers":[
        {
            "category":"Building & Trades",
            "subcategory":"Cleaning & Sanitation",
            "type":"Services"
        }
    ],
    "sg:phone":"+1 910 686 0056",
    "sg:postcode":"28411",
    "sg:province":"NC",
    "sg:tags":[
        "janitor",
        "maintenance"
    ],
    "wof:name":"Regional Cleaning Service",
    "wof:placetype":"venue"
},
  "geometry": {"coordinates":[-77.812864,34.283856],"type":"Point"}
}