{
  "type": "Feature",
  "properties": {
    "iso:country":"US",
    "sg:address":"4243 Hamburg Mill Rd",
    "sg:city":"Summerfield",
    "sg:classifiers":[
        {
            "category":"Building & Trades",
            "subcategory":"Construction",
            "type":"Services"
        }
    ],
    "sg:phone":"+1 336 643 6591",
    "sg:postcode":"27358",
    "sg:province":"NC",
    "sg:tags":[
        "house"
    ],
    "wof:name":"M&G Custom Homes LLC",
    "wof:placetype":"venue"
},
  "geometry": {"coordinates":[-79.900603,36.165803],"type":"Point"}
}