{
  "type": "Feature",
  "properties": {
    "addr:full":"5601 W US Hwy 64 Murphy NC 28906",
    "addr:housenumber":"5601",
    "addr:postcode":"28906",
    "addr:street":"W Us Hwy 64",
    "iso:country":"US",
    "sg:address":"5601 W US Hwy 64",
    "sg:city":"Murphy",
    "sg:classifiers":[
        {
            "category":"Real Estate",
            "subcategory":"Real Estate Agent",
            "type":"Services"
        }
    ],
    "sg:phone":"+1 828 835 9101",
    "sg:postcode":"28906",
    "sg:province":"NC",
    "wof:name":"Benchmark Realty & Constr",
    "wof:placetype":"venue"
},
  "geometry": {"coordinates":[-84.146863,35.033128],"type":"Point"}
}