{
  "type": "Feature",
  "properties": {
    "addr:full":"326 Walton Dr Statesville NC 28625",
    "addr:housenumber":"326",
    "addr:postcode":"28625",
    "addr:street":"Walton Dr",
    "iso:country":"US",
    "sg:address":"326 Walton Dr",
    "sg:city":"Statesville",
    "sg:classifiers":[
        {
            "category":"Building & Trades",
            "subcategory":"Construction",
            "type":"Services"
        }
    ],
    "sg:phone":"+1 704 838 1891",
    "sg:postcode":"28625",
    "sg:province":"NC",
    "sg:tags":[
        "downspouts",
        "gutter"
    ],
    "wof:name":"J & B Seamless Gutters",
    "wof:placetype":"venue"
},
  "geometry": {"coordinates":[-80.845896,35.790131],"type":"Point"}
}