{
  "type": "Feature",
  "properties": {
    "addr:full":"9827 Mount Holly Rd Charlotte NC 28214",
    "addr:housenumber":"9827",
    "addr:postcode":"28214",
    "addr:street":"Mount Holly Rd",
    "iso:country":"US",
    "sg:address":"9827 Mount Holly Rd",
    "sg:city":"Charlotte",
    "sg:classifiers":[
        {
            "category":"Manufacturing",
            "subcategory":"Motor Vehicles & Parts",
            "type":"Manufacturing & Wholesale Goods"
        }
    ],
    "sg:phone":"+1 704 392 8460",
    "sg:postcode":"28214",
    "sg:province":"NC",
    "sg:tags":[
        "equipment",
        "truck"
    ],
    "sg:website":"www.fontainemod.com",
    "wof:name":"Fontaine Modification Co",
    "wof:placetype":"venue"
},
  "geometry": {"coordinates":[-80.96969,35.291105],"type":"Point"}
}