{
  "type": "Feature",
  "properties": {
    "addr:full":"610 Altadore Cres Moncure NC 27559",
    "addr:housenumber":"610",
    "addr:postcode":"27559",
    "addr:street":"Altadore Cres",
    "iso:country":"US",
    "sg:address":"610 Altadore Cres",
    "sg:city":"Moncure",
    "sg:classifiers":[
        {
            "category":"Building & Trades",
            "subcategory":"Construction",
            "type":"Services"
        }
    ],
    "sg:phone":"+1 919 542 0532",
    "sg:postcode":"27559",
    "sg:province":"NC",
    "sg:tags":[
        "house",
        "co"
    ],
    "wof:name":"Smith Construction L L C",
    "wof:placetype":"venue"
},
  "geometry": {"coordinates":[-79.131328,35.668026],"type":"Point"}
}