{
  "type": "Feature",
  "properties": {
    "iso:country":"US",
    "sg:address":"200 Amity Hill Rd",
    "sg:city":"Cleveland",
    "sg:classifiers":[
        {
            "category":"Social Services",
            "subcategory":"Child Care",
            "type":"Services"
        }
    ],
    "sg:phone":"+1 704 278 4119",
    "sg:postcode":"27013",
    "sg:province":"NC",
    "sg:tags":[
        "day"
    ],
    "wof:name":"Advantage Childrens Center",
    "wof:placetype":"venue"
},
  "geometry": {"coordinates":[-80.697451,35.726858],"type":"Point"}
}