{
  "type": "Feature",
  "properties": {
    "addr:full":"600 Northern Shores Ln Greensboro NC 27455",
    "addr:housenumber":"600",
    "addr:postcode":"27455",
    "addr:street":"Northern Shores Ln",
    "iso:country":"US",
    "sg:address":"600 Northern Shores Ln",
    "sg:city":"Greensboro",
    "sg:classifiers":[
        {
            "category":"Professional",
            "subcategory":"Management & Consulting",
            "type":"Services"
        }
    ],
    "sg:phone":"+1   ",
    "sg:postcode":"27455",
    "sg:province":"NC",
    "sg:tags":[
        "consultant",
        "business"
    ],
    "wof:name":"Paisley Partners Inc",
    "wof:placetype":"venue"
},
  "geometry": {"coordinates":[-79.805998,36.160705],"type":"Point"}
}