{
  "type": "Feature",
  "properties": {
    "iso:country":"US",
    "sg:address":"40 Salem St",
    "sg:city":"Thomasville",
    "sg:classifiers":[
        {
            "category":"Professional",
            "subcategory":"Lawyer & Legal Services",
            "type":"Services"
        }
    ],
    "sg:phone":"+1 336 476 3115",
    "sg:postcode":"27360",
    "sg:province":"NC",
    "sg:tags":[
        "attorney"
    ],
    "wof:name":"Randy L Cranford",
    "wof:placetype":"venue"
},
  "geometry": {"coordinates":[-80.08223,35.883685],"type":"Point"}
}