{
  "type": "Feature",
  "properties": {
    "addr:full":"240 S Caldwell St Brevard SC 28712",
    "addr:housenumber":"240",
    "addr:postcode":"28712",
    "addr:street":"S Caldwell St",
    "iso:country":"US",
    "sg:address":"240 S Caldwell St",
    "sg:city":"Brevard",
    "sg:classifiers":[
        {
            "category":"Health Services",
            "subcategory":"Doctor",
            "type":"Services"
        }
    ],
    "sg:phone":"+1 828 883 3510",
    "sg:postcode":"28712",
    "sg:province":"SC",
    "sg:tags":[
        "dentist"
    ],
    "wof:name":"Melvin L Davis DDS",
    "wof:placetype":"venue"
},
  "geometry": {"coordinates":[-82.736808,35.232367],"type":"Point"}
}