{
  "type": "Feature",
  "properties": {
    "addr:full":"1419 East Blvd Charlotte NC 28203",
    "addr:housenumber":"1419",
    "addr:postcode":"28203",
    "addr:street":"East Blvd",
    "iso:country":"US",
    "sg:address":"1419 East Blvd",
    "sg:city":"Charlotte",
    "sg:classifiers":[
        {
            "category":"Personal",
            "subcategory":"Beauty Salon",
            "type":"Services"
        }
    ],
    "sg:phone":"+1 704 344 1400",
    "sg:postcode":"28203",
    "sg:province":"NC",
    "sg:tags":[
        "manicuring"
    ],
    "wof:name":"Tina Segal",
    "wof:placetype":"venue"
},
  "geometry": {"coordinates":[-80.842608,35.200451],"type":"Point"}
}