{
  "type": "Feature",
  "properties": {
    "iso:country":"US",
    "sg:address":"27 S Kerr Ave",
    "sg:city":"Wilmington",
    "sg:classifiers":[
        {
            "category":"Wholesale",
            "subcategory":"Machinery & Supplies",
            "type":"Manufacturing & Wholesale Goods"
        }
    ],
    "sg:phone":"+1 910 350 8034",
    "sg:postcode":"28403",
    "sg:province":"NC",
    "sg:tags":[
        "salon",
        "beauty"
    ],
    "wof:name":"Davidson Beauty",
    "wof:placetype":"venue"
},
  "geometry": {"coordinates":[-77.889713,34.241326],"type":"Point"}
}