{
  "type": "Feature",
  "properties": {
    "iso:country":"US",
    "sg:address":"6000 Providence Glen Rd",
    "sg:city":"Charlotte",
    "sg:classifiers":[
        {
            "category":"Manufacturing",
            "subcategory":"Printing",
            "type":"Manufacturing & Wholesale Goods"
        }
    ],
    "sg:phone":"+1 704 841 8009",
    "sg:postcode":"28270",
    "sg:province":"NC",
    "sg:tags":[
        "periodical"
    ],
    "wof:name":"Hr Network LLC",
    "wof:placetype":"venue"
},
  "geometry": {"coordinates":[-80.747742,35.089532],"type":"Point"}
}