{
  "type": "Feature",
  "properties": {
    "addr:full":"700 Munster Ave Greensboro NC 27406",
    "addr:housenumber":"700",
    "addr:postcode":"27406",
    "addr:street":"Munster Ave",
    "iso:country":"US",
    "sg:address":"700 Munster Ave",
    "sg:city":"Greensboro",
    "sg:classifiers":[
        {
            "category":"Communications",
            "subcategory":"Film & Video Production",
            "type":"Services"
        }
    ],
    "sg:phone":"+1   ",
    "sg:postcode":"27406",
    "sg:province":"NC",
    "sg:tags":[
        "motion",
        "distribution"
    ],
    "wof:name":"Anime Connection",
    "wof:placetype":"venue"
},
  "geometry": {"coordinates":[-79.811021,36.013185],"type":"Point"}
}