{
  "type": "Feature",
  "properties": {
    "iso:country":"US",
    "sg:address":"1003 Riverway Ln",
    "sg:city":"Knightdale",
    "sg:classifiers":[
        {
            "category":"Banks & Credit Unions",
            "subcategory":"Bank",
            "type":"Services"
        }
    ],
    "sg:phone":"+1 919 217 8797",
    "sg:postcode":"27545",
    "sg:province":"NC",
    "sg:tags":[
        "mortgage"
    ],
    "wof:name":"Cashflow Professionals",
    "wof:placetype":"venue"
},
  "geometry": {"coordinates":[-78.519108,35.783831],"type":"Point"}
}