{
  "type": "Feature",
  "properties": {
    "addr:full":"12401 Softwood Ct Charlotte NC 28273",
    "addr:housenumber":"12401",
    "addr:postcode":"28273",
    "addr:street":"Softwood Ct",
    "iso:country":"US",
    "sg:address":"12401 Softwood Ct",
    "sg:city":"Charlotte",
    "sg:classifiers":[
        {
            "category":"Professional",
            "type":"Services"
        }
    ],
    "sg:phone":"+1   ",
    "sg:postcode":"28273",
    "sg:province":"NC",
    "wof:name":"Witmore Services",
    "wof:placetype":"venue"
},
  "geometry": {"coordinates":[-80.94863100000001,35.140482],"type":"Point"}
}