{
  "type": "Feature",
  "properties": {
    "iso:country":"US",
    "sg:address":"315 Metcalf St",
    "sg:city":"New Bern",
    "sg:classifiers":[
        {
            "category":"Professional",
            "subcategory":"Accounting & Tax Preparation",
            "type":"Services"
        }
    ],
    "sg:phone":"+1 252 636 6111",
    "sg:postcode":"28562",
    "sg:province":"NC",
    "sg:tags":[
        "accountant"
    ],
    "wof:name":"Dennis F Palumbo CPA",
    "wof:placetype":"venue"
},
  "geometry": {"coordinates":[-77.04296600000001,35.10825],"type":"Point"}
}