{
  "type": "Feature",
  "properties": {
    "iso:country":"US",
    "sg:address":"11 S Main St",
    "sg:city":"Lexington",
    "sg:classifiers":[
        {
            "category":"Professional",
            "subcategory":"Lawyer & Legal Services",
            "type":"Services"
        }
    ],
    "sg:phone":"+1 336 249 0547",
    "sg:postcode":"27292",
    "sg:province":"NC",
    "sg:tags":[
        "attorney"
    ],
    "wof:name":"Richard J Mc Cain",
    "wof:placetype":"venue"
},
  "geometry": {"coordinates":[-80.253359,35.823865],"type":"Point"}
}