{
  "type": "Feature",
  "properties": {
    "iso:country":"US",
    "sg:address":"124 Chavasse Ave",
    "sg:city":"Henderson",
    "sg:classifiers":[
        {
            "category":"Shopping",
            "subcategory":"Used Merchandise",
            "type":"Retail Goods"
        }
    ],
    "sg:phone":"+1 252 492 5136",
    "sg:postcode":"27536",
    "sg:province":"NC",
    "sg:tags":[
        "pawnbroker"
    ],
    "wof:name":"Parrish's Jewelry & Pawn",
    "wof:placetype":"venue"
},
  "geometry": {"coordinates":[-78.41085699999999,36.319918],"type":"Point"}
}