{
  "type": "Feature",
  "properties": {
    "addr:full":"1515 Holbrook St Greensboro NC 27403",
    "addr:housenumber":"1515",
    "addr:postcode":"27403",
    "addr:street":"Holbrook St",
    "iso:country":"US",
    "sg:address":"1515 Holbrook St",
    "sg:city":"Greensboro",
    "sg:classifiers":[
        {
            "category":"Building & Trades",
            "subcategory":"Construction",
            "type":"Services"
        }
    ],
    "sg:phone":"+1 336 230 0051",
    "sg:postcode":"27403",
    "sg:province":"NC",
    "sg:tags":[
        "carpentry",
        "contractor"
    ],
    "wof:name":"Bistyga Woodworks Inc",
    "wof:placetype":"venue"
},
  "geometry": {"coordinates":[-79.817543,36.059712],"type":"Point"}
}