{
  "type": "Feature",
  "properties": {
    "iso:country":"US",
    "sg:address":"5960 US Hwy 70",
    "sg:city":"Newport",
    "sg:classifiers":[
        {
            "category":"Personal",
            "subcategory":"Beauty Salon",
            "type":"Services"
        }
    ],
    "sg:phone":"+1   ",
    "sg:postcode":"28570",
    "sg:province":"NC",
    "sg:tags":[
        "shop"
    ],
    "wof:name":"Car Salon",
    "wof:placetype":"venue"
},
  "geometry": {"coordinates":[-76.83886699999999,34.749865],"type":"Point"}
}