{
  "type": "Feature",
  "properties": {
    "addr:full":"5831 Clinton Rd Stedman NC 28391",
    "addr:housenumber":"5831",
    "addr:postcode":"28391",
    "addr:street":"Clinton Rd",
    "iso:country":"US",
    "sg:address":"5831 Clinton Rd",
    "sg:city":"Stedman",
    "sg:classifiers":[
        {
            "category":"Freight",
            "type":"Transportation"
        }
    ],
    "sg:phone":"+1 910 323 1806",
    "sg:postcode":"28391",
    "sg:province":"NC",
    "sg:tags":[
        "commercial",
        "storage"
    ],
    "wof:name":"Cape Fear Mini Storage",
    "wof:placetype":"venue"
},
  "geometry": {"coordinates":[-78.688579,35.011322],"type":"Point"}
}