{
  "type": "Feature",
  "properties": {
    "addr:full":"3007 Commonwealth Ave Charlotte NC 28205",
    "addr:housenumber":"3007",
    "addr:postcode":"28205",
    "addr:street":"Commonwealth Ave",
    "iso:country":"US",
    "sg:address":"3007 Commonwealth Ave",
    "sg:city":"Charlotte",
    "sg:classifiers":[
        {
            "category":"Home & Garden",
            "subcategory":"Furniture",
            "type":"Retail Goods"
        }
    ],
    "sg:phone":"+1 704 376 1443",
    "sg:postcode":"28205",
    "sg:province":"NC",
    "wof:name":"Bs Furniture Sculpture",
    "wof:placetype":"venue"
},
  "geometry": {"coordinates":[-80.796387,35.210687],"type":"Point"}
}