{
  "type": "Feature",
  "properties": {
    "addr:full":"318 Ridgefield Ct Asheville NC 28806",
    "addr:housenumber":"318",
    "addr:postcode":"28806",
    "addr:street":"Ridgefield Ct",
    "iso:country":"US",
    "sg:address":"318 Ridgefield Ct",
    "sg:city":"Asheville",
    "sg:classifiers":[
        {
            "category":"Education",
            "subcategory":"University",
            "type":"Public Place"
        }
    ],
    "sg:phone":"+1 828 667 5044",
    "sg:postcode":"28806",
    "sg:province":"NC",
    "sg:tags":[
        "college"
    ],
    "wof:name":"Montreat College",
    "wof:placetype":"venue"
},
  "geometry": {"coordinates":[-82.59870100000001,35.523399],"type":"Point"}
}