{
  "type": "Feature",
  "properties": {
    "iso:country":"US",
    "sg:address":"1935 Jake Alexander Blvd W",
    "sg:city":"Salisbury",
    "sg:classifiers":[
        {
            "category":"Shopping",
            "subcategory":"Clothing, Apparel, & Fashions",
            "type":"Retail Goods"
        }
    ],
    "sg:phone":"+1 704 636 2800",
    "sg:postcode":"28147",
    "sg:province":"NC",
    "wof:name":"Grind",
    "wof:placetype":"venue"
},
  "geometry": {"coordinates":[-80.51005600000001,35.688204],"type":"Point"}
}