{
  "type": "Feature",
  "properties": {
    "addr:full":"3021 Summerland Dr Matthews NC 28105",
    "addr:housenumber":"3021",
    "addr:postcode":"28105",
    "addr:street":"Summerland Dr",
    "iso:country":"US",
    "sg:address":"3021 Summerland Dr",
    "sg:city":"Matthews",
    "sg:classifiers":[
        {
            "category":"Professional",
            "type":"Services"
        }
    ],
    "sg:phone":"+1 704 321 1434",
    "sg:postcode":"28105",
    "sg:province":"NC",
    "wof:name":"Clothes To Home",
    "wof:placetype":"venue"
},
  "geometry": {"coordinates":[-80.69718,35.139254],"type":"Point"}
}