{
  "type": "Feature",
  "properties": {
    "iso:country":"US",
    "sg:address":"412 Milsap Rd",
    "sg:city":"Shelby",
    "sg:classifiers":[
        {
            "category":"Organizations",
            "subcategory":"Religious Organization",
            "type":"Services"
        }
    ],
    "sg:phone":"+1   ",
    "sg:postcode":"28150",
    "sg:province":"NC",
    "wof:name":"B I C O M Inc",
    "wof:placetype":"venue"
},
  "geometry": {"coordinates":[-81.47899,35.2944],"type":"Point"}
}