{
  "type": "Feature",
  "properties": {
    "iso:country":"US",
    "sg:address":"1242 S 5th St",
    "sg:city":"Mebane",
    "sg:classifiers":[
        {
            "category":"Insurance",
            "subcategory":"Insurance Agent",
            "type":"Services"
        }
    ],
    "sg:phone":"+1 919 563 1248",
    "sg:postcode":"27302",
    "sg:province":"NC",
    "wof:name":"Ted B Seagroves Agency",
    "wof:placetype":"venue"
},
  "geometry": {"coordinates":[-79.296009,36.071145],"type":"Point"}
}