{
  "type": "Feature",
  "properties": {
    "addr:full":"2044 Connelly Springs Rd Lenoir NC 28645",
    "addr:housenumber":"2044",
    "addr:postcode":"28645",
    "addr:street":"Connelly Springs Rd",
    "iso:country":"US",
    "sg:address":"2044 Connelly Springs Rd",
    "sg:city":"Lenoir",
    "sg:classifiers":[
        {
            "category":"Shopping",
            "type":"Retail Goods"
        }
    ],
    "sg:phone":"+1 828 728 4646",
    "sg:postcode":"28645",
    "sg:province":"NC",
    "sg:tags":[
        "pet",
        "shop"
    ],
    "wof:name":"Franklin Pet Shop",
    "wof:placetype":"venue"
},
  "geometry": {"coordinates":[-81.538757,35.83577],"type":"Point"}
}