{
  "type": "Feature",
  "properties": {
    "addr:full":"223 Hargett St Richlands NC 28574",
    "addr:housenumber":"223",
    "addr:postcode":"28574",
    "addr:street":"Hargett St",
    "iso:country":"US",
    "sg:address":"223 Hargett St",
    "sg:city":"Richlands",
    "sg:classifiers":[
        {
            "category":"Restaurant",
            "type":"Food & Drink"
        }
    ],
    "sg:phone":"+1 910 324 5562",
    "sg:postcode":"28574",
    "sg:province":"NC",
    "wof:name":"Denny's Pizza",
    "wof:placetype":"venue"
},
  "geometry": {"coordinates":[-77.54937,34.901633],"type":"Point"}
}