{
  "type": "Feature",
  "properties": {
    "iso:country":"US",
    "sg:address":"1611 Castle Hayne Rd",
    "sg:city":"Wilmington",
    "sg:classifiers":[
        {
            "category":"Retail",
            "subcategory":"Repair Shop",
            "type":"Services"
        }
    ],
    "sg:phone":"+1 910 343 4118",
    "sg:postcode":"28401",
    "sg:province":"NC",
    "sg:tags":[
        "equipment"
    ],
    "wof:name":"Authorized Commercial Equip",
    "wof:placetype":"venue"
},
  "geometry": {"coordinates":[-77.930018,34.266916],"type":"Point"}
}