{
  "type": "Feature",
  "properties": {
    "iso:country":"US",
    "sg:address":"324 W 27th St",
    "sg:city":"Winston Salem",
    "sg:classifiers":[
        {
            "category":"Insurance",
            "subcategory":"Insurance Agent",
            "type":"Services"
        }
    ],
    "sg:phone":"+1 336 724 2451",
    "sg:postcode":"27105",
    "sg:province":"NC",
    "sg:tags":[
        "adjuster"
    ],
    "wof:name":"R E Pratt & Co",
    "wof:placetype":"venue"
},
  "geometry": {"coordinates":[-80.25187,36.123542],"type":"Point"}
}