{
  "type": "Feature",
  "properties": {
    "iso:country":"US",
    "sg:address":"1360 Benvenue Rd",
    "sg:city":"Rocky Mount",
    "sg:classifiers":[
        {
            "category":"Shopping",
            "subcategory":"Used Merchandise",
            "type":"Retail Goods"
        }
    ],
    "sg:phone":"+1 252 442 3473",
    "sg:postcode":"27804",
    "sg:province":"NC",
    "sg:tags":[
        "shop",
        "thrift"
    ],
    "wof:name":"A Second Season",
    "wof:placetype":"venue"
},
  "geometry": {"coordinates":[-77.80563600000001,35.977449],"type":"Point"}
}