{
  "type": "Feature",
  "properties": {
    "addr:full":"311 W Wendover Ave Greensboro NC 27408",
    "addr:housenumber":"311",
    "addr:postcode":"27408",
    "addr:street":"W Wendover Ave",
    "iso:country":"US",
    "sg:address":"311 W Wendover Ave",
    "sg:city":"Greensboro",
    "sg:classifiers":[
        {
            "category":"Health Services",
            "subcategory":"Doctor",
            "type":"Services"
        }
    ],
    "sg:phone":"+1 336 274 1200",
    "sg:postcode":"27408",
    "sg:province":"NC",
    "sg:tags":[
        "medical"
    ],
    "wof:name":"Charles W Lomax MD",
    "wof:placetype":"venue"
},
  "geometry": {"coordinates":[-79.794344,36.088172],"type":"Point"}
}