{
  "type": "Feature",
  "properties": {
    "iso:country":"US",
    "sg:address":"536 Paul Hare Rd",
    "sg:city":"Goldsboro",
    "sg:classifiers":[
        {
            "category":"Farming",
            "subcategory":"Poultry Farm",
            "type":"Manufacturing & Wholesale Goods"
        }
    ],
    "sg:phone":"+1 919 689 2934",
    "sg:postcode":"27530",
    "sg:province":"NC",
    "sg:tags":[
        "egg"
    ],
    "wof:name":"Brock Farms",
    "wof:placetype":"venue"
},
  "geometry": {"coordinates":[-78.196259,35.30363],"type":"Point"}
}