{
  "type": "Feature",
  "properties": {
    "iso:country":"US",
    "sg:address":"303 E Chapel Hill St",
    "sg:city":"Durham",
    "sg:classifiers":[
        {
            "category":"Shopping",
            "type":"Retail Goods"
        }
    ],
    "sg:phone":"+1 919 687 0250",
    "sg:postcode":"27701",
    "sg:province":"NC",
    "sg:tags":[
        "art",
        "gallery",
        "dealer"
    ],
    "wof:name":"Through This Lens Inc",
    "wof:placetype":"venue"
},
  "geometry": {"coordinates":[-78.90141,35.997022],"type":"Point"}
}