{
  "type": "Feature",
  "properties": {
    "iso:country":"US",
    "sg:address":"101 US Hwy 301",
    "sg:city":"Lucama",
    "sg:classifiers":[
        {
            "category":"Shopping",
            "subcategory":"Clothing, Apparel, & Fashions",
            "type":"Retail Goods"
        }
    ],
    "sg:phone":"+1 252 239 1015",
    "sg:postcode":"27851",
    "sg:province":"NC",
    "sg:tags":[
        "infant",
        "wear"
    ],
    "wof:name":"301 Clothing Outlet",
    "wof:placetype":"venue"
},
  "geometry": {"coordinates":[-78.009051,35.646927],"type":"Point"}
}