{
  "type": "Feature",
  "properties": {
    "addr:full":"2620 Raeford Rd Fayetteville NC 28303",
    "addr:housenumber":"2620",
    "addr:postcode":"28303",
    "addr:street":"Raeford Rd",
    "iso:country":"US",
    "sg:address":"2620 Raeford Rd",
    "sg:city":"Fayetteville",
    "sg:classifiers":[
        {
            "category":"Restaurant",
            "type":"Food & Drink"
        }
    ],
    "sg:phone":"+1 910 485 2948",
    "sg:postcode":"28303",
    "sg:province":"NC",
    "wof:name":"Chris's Open Hearth Steak",
    "wof:placetype":"venue"
},
  "geometry": {"coordinates":[-78.92115699999999,35.045973],"type":"Point"}
}