{
  "type": "Feature",
  "properties": {
    "addr:full":"216 N Bickett Blvd Louisburg NC 27549",
    "addr:housenumber":"216",
    "addr:postcode":"27549",
    "addr:street":"N Bickett Blvd",
    "iso:country":"US",
    "sg:address":"216 N Bickett Blvd",
    "sg:city":"Louisburg",
    "sg:classifiers":[
        {
            "category":"Government",
            "subcategory":"Office",
            "type":"Public Place"
        }
    ],
    "sg:phone":"+1 919 496 2274",
    "sg:postcode":"27549",
    "sg:province":"NC",
    "sg:tags":[
        "program",
        "administrative"
    ],
    "wof:name":"Franklin County Child Support",
    "wof:placetype":"venue"
},
  "geometry": {"coordinates":[-78.294501,36.099447],"type":"Point"}
}