{
  "type": "Feature",
  "properties": {
    "addr:full":"451 Swanson Rd SW Lenoir NC 28645",
    "addr:housenumber":"451",
    "addr:postcode":"28645",
    "addr:street":"Swanson Rd Sw",
    "iso:country":"US",
    "sg:address":"451 Swanson Rd SW",
    "sg:city":"Lenoir",
    "sg:classifiers":[
        {
            "category":"Organizations",
            "subcategory":"Religious Organization",
            "type":"Services"
        }
    ],
    "sg:phone":"+1 828 728 0905",
    "sg:postcode":"28645",
    "sg:province":"NC",
    "sg:tags":[
        "church"
    ],
    "wof:name":"Green Rock Baptist Church",
    "wof:placetype":"venue"
},
  "geometry": {"coordinates":[-81.514478,35.863722],"type":"Point"}
}