{
  "type": "Feature",
  "properties": {
    "addr:full":"815 Meadow Ln Burgaw NC 28425",
    "addr:housenumber":"815",
    "addr:postcode":"28425",
    "addr:street":"Meadow Ln",
    "iso:country":"US",
    "sg:address":"815 Meadow Ln",
    "sg:city":"Burgaw",
    "sg:classifiers":[
        {
            "category":"Building & Trades",
            "subcategory":"Construction",
            "type":"Services"
        }
    ],
    "sg:phone":"+1 910 259 3584",
    "sg:postcode":"28425",
    "sg:province":"NC",
    "sg:tags":[
        "carpentry",
        "contractor"
    ],
    "wof:name":"Interior Trim",
    "wof:placetype":"venue"
},
  "geometry": {"coordinates":[-77.894937,34.482327],"type":"Point"}
}