{
  "type": "Feature",
  "properties": {
    "iso:country":"US",
    "sg:address":"10568 State Hwy 86",
    "sg:city":"Providence",
    "sg:classifiers":[
        {
            "category":"Banks & Credit Unions",
            "subcategory":"Bank",
            "type":"Services"
        }
    ],
    "sg:phone":"+1 336 388 9069",
    "sg:postcode":"27315",
    "sg:province":"NC",
    "sg:tags":[
        "cashing",
        "check"
    ],
    "wof:name":"Check Loans",
    "wof:placetype":"venue"
},
  "geometry": {"coordinates":[-79.38977800000001,36.507239],"type":"Point"}
}