{
  "type": "Feature",
  "properties": {
    "addr:full":"1351 E Garrison Blvd Gastonia NC 28054",
    "addr:housenumber":"1351",
    "addr:postcode":"28054",
    "addr:street":"E Garrison Blvd",
    "iso:country":"US",
    "sg:address":"1351 E Garrison Blvd",
    "sg:city":"Gastonia",
    "sg:classifiers":[
        {
            "category":"Real Estate",
            "subcategory":"Surveying",
            "type":"Services"
        }
    ],
    "sg:phone":"+1 704 866 8421",
    "sg:postcode":"28054",
    "sg:province":"NC",
    "wof:name":"Tanner & McConnaughey PA Inc",
    "wof:placetype":"venue"
},
  "geometry": {"coordinates":[-81.162125,35.252701],"type":"Point"}
}