{
  "type": "Feature",
  "properties": {
    "addr:full":"13 Gash Farm Rd Asheville NC 28805",
    "addr:housenumber":"13",
    "addr:postcode":"28805",
    "addr:street":"Gash Farm Rd",
    "iso:country":"US",
    "sg:address":"13 Gash Farm Rd",
    "sg:city":"Asheville",
    "sg:classifiers":[
        {
            "category":"Professional",
            "type":"Services"
        }
    ],
    "sg:phone":"+1 828 298 7422",
    "sg:postcode":"28805",
    "sg:province":"NC",
    "wof:name":"Jeff Laibson",
    "wof:placetype":"venue"
},
  "geometry": {"coordinates":[-82.475685,35.578208],"type":"Point"}
}