{
  "type": "Feature",
  "properties": {
    "addr:full":"341 Sunset Dr SE Concord NC 28025",
    "addr:housenumber":"341",
    "addr:postcode":"28025",
    "addr:street":"Sunset Dr Se",
    "iso:country":"US",
    "sg:address":"341 Sunset Dr SE",
    "sg:city":"Concord",
    "sg:classifiers":[
        {
            "category":"Building & Trades",
            "subcategory":"Construction",
            "type":"Services"
        }
    ],
    "sg:phone":"+1 704 795 6600",
    "sg:postcode":"28025",
    "sg:province":"NC",
    "sg:tags":[
        "general",
        "contractor"
    ],
    "wof:name":"Clean Sweep Construction Inc",
    "wof:placetype":"venue"
},
  "geometry": {"coordinates":[-80.571561,35.402093],"type":"Point"}
}