{
  "type": "Feature",
  "properties": {
    "iso:country":"US",
    "sg:address":"23 Heritage Dr",
    "sg:city":"Asheville",
    "sg:classifiers":[
        {
            "category":"Wholesale",
            "subcategory":"Machinery & Supplies",
            "type":"Manufacturing & Wholesale Goods"
        }
    ],
    "sg:phone":"+1 828 254 7473",
    "sg:postcode":"28806",
    "sg:province":"NC",
    "sg:tags":[
        "contracting",
        "utility"
    ],
    "wof:name":"Willco",
    "wof:placetype":"venue"
},
  "geometry": {"coordinates":[-82.606533,35.59338],"type":"Point"}
}