{
  "type": "Feature",
  "properties": {
    "iso:country":"US",
    "sg:address":"615 Margrace Rd",
    "sg:city":"Kings Mountain",
    "sg:classifiers":[
        {
            "category":"Government",
            "subcategory":"Office",
            "type":"Public Place"
        }
    ],
    "sg:phone":"+1 704 739 5184",
    "sg:postcode":"28086",
    "sg:province":"NC",
    "sg:tags":[
        "management"
    ],
    "wof:name":"Cleveland County Waste Recycl",
    "wof:placetype":"venue"
},
  "geometry": {"coordinates":[-81.377492,35.215208],"type":"Point"}
}