{
  "type": "Feature",
  "properties": {
    "iso:country":"US",
    "sg:address":"34 New Clyde Hwy",
    "sg:city":"Canton",
    "sg:classifiers":[
        {
            "category":"Shopping",
            "subcategory":"Gifts & Souvenirs",
            "type":"Retail Goods"
        }
    ],
    "sg:phone":"+1 828 648 5422",
    "sg:postcode":"28716",
    "sg:province":"NC",
    "wof:name":"Enchanted Cottage",
    "wof:placetype":"venue"
},
  "geometry": {"coordinates":[-82.86120099999999,35.532303],"type":"Point"}
}