{
  "type": "Feature",
  "properties": {
    "iso:country":"US",
    "sg:address":"3230 Piper Ln",
    "sg:city":"Charlotte",
    "sg:classifiers":[
        {
            "category":"Organizations",
            "subcategory":"Religious Organization",
            "type":"Services"
        }
    ],
    "sg:phone":"+1 704 329 7405",
    "sg:postcode":"28208",
    "sg:province":"NC",
    "sg:tags":[
        "church"
    ],
    "wof:name":"Divine Revelation Chr Of God",
    "wof:placetype":"venue"
},
  "geometry": {"coordinates":[-80.93043900000001,35.194479],"type":"Point"}
}