{
  "type": "Feature",
  "properties": {
    "addr:full":"180 Stoneridge Ct Youngsville NC 27514",
    "addr:housenumber":"180",
    "addr:postcode":"27514",
    "addr:street":"Stoneridge Ct",
    "iso:country":"US",
    "sg:address":"180 Stoneridge Ct",
    "sg:city":"Youngsville",
    "sg:classifiers":[
        {
            "category":"Real Estate",
            "subcategory":"Real Estate Agent",
            "type":"Services"
        }
    ],
    "sg:phone":"+1 919 562 7868",
    "sg:postcode":"27514",
    "sg:province":"NC",
    "wof:name":"L&E Property Management",
    "wof:placetype":"venue"
},
  "geometry": {"coordinates":[-79.045266,35.988372],"type":"Point"}
}