{
  "type": "Feature",
  "properties": {
    "addr:full":"1965 Peace Haven Rd N Winston Salem NC 27106",
    "addr:housenumber":"1965",
    "addr:postcode":"27106",
    "addr:street":"Peace Haven Rd N",
    "iso:country":"US",
    "sg:address":"1965 Peace Haven Rd N",
    "sg:city":"Winston Salem",
    "sg:classifiers":[
        {
            "category":"Personal",
            "subcategory":"Beauty Salon",
            "type":"Services"
        }
    ],
    "sg:phone":"+1 336 760 3166",
    "sg:postcode":"27106",
    "sg:province":"NC",
    "sg:website":"www.greatclips.com",
    "wof:name":"Great Clips",
    "wof:placetype":"venue"
},
  "geometry": {"coordinates":[-80.313569,36.117631],"type":"Point"}
}