{
  "type": "Feature",
  "properties": {
    "addr:full":"1280 Roanoke Rd Newton Grove NC 28366",
    "addr:housenumber":"1280",
    "addr:postcode":"28366",
    "addr:street":"Roanoke Rd",
    "iso:country":"US",
    "sg:address":"1280 Roanoke Rd",
    "sg:city":"Newton Grove",
    "sg:classifiers":[
        {
            "category":"Restaurant",
            "type":"Food & Drink"
        }
    ],
    "sg:phone":"+1 910 567 5703",
    "sg:postcode":"28366",
    "sg:province":"NC",
    "sg:tags":[
        "eating"
    ],
    "wof:name":"Tyler's Grill",
    "wof:placetype":"venue"
},
  "geometry": {"coordinates":[-78.43803800000001,35.170772],"type":"Point"}
}