{
  "type": "Feature",
  "properties": {
    "iso:country":"US",
    "sg:address":"204 E Main St",
    "sg:city":"Glen Alpine",
    "sg:classifiers":[
        {
            "category":"Manufacturing",
            "subcategory":"Food",
            "type":"Manufacturing & Wholesale Goods"
        }
    ],
    "sg:phone":"+1 828 584 9400",
    "sg:postcode":"28628",
    "sg:province":"NC",
    "sg:tags":[
        "brewer"
    ],
    "wof:name":"Catawba Valley Brewing Co",
    "wof:placetype":"venue"
},
  "geometry": {"coordinates":[-81.775756,35.728586],"type":"Point"}
}