{
  "type": "Feature",
  "properties": {
    "addr:full":"254 Farmstead Rd Winston Salem NC 27107",
    "addr:housenumber":"254",
    "addr:postcode":"27107",
    "addr:street":"Farmstead Rd",
    "iso:country":"US",
    "sg:address":"254 Farmstead Rd",
    "sg:city":"Winston Salem",
    "sg:classifiers":[
        {
            "category":"Health Services",
            "subcategory":"Doctor",
            "type":"Services"
        }
    ],
    "sg:phone":"+1 336 659 6640",
    "sg:postcode":"27107",
    "sg:province":"NC",
    "wof:name":"Charles G New DDS Ms PA",
    "wof:placetype":"venue"
},
  "geometry": {"coordinates":[-80.21434000000001,35.955249],"type":"Point"}
}