{
  "type": "Feature",
  "properties": {
    "addr:full":"4815 Rolling Rd Kernersville NC 27284",
    "addr:housenumber":"4815",
    "addr:postcode":"27284",
    "addr:street":"Rolling Rd",
    "iso:country":"US",
    "sg:address":"4815 Rolling Rd",
    "sg:city":"Kernersville",
    "sg:classifiers":[
        {
            "category":"Retail",
            "subcategory":"Animal Services",
            "type":"Services"
        }
    ],
    "sg:phone":"+1 336 650 9555",
    "sg:postcode":"27284",
    "sg:province":"NC",
    "wof:name":"Forsyth Kennel Club",
    "wof:placetype":"venue"
},
  "geometry": {"coordinates":[-80.10695,36.104143],"type":"Point"}
}