{
  "type": "Feature",
  "properties": {
    "addr:full":"3020 Market St Wilmington NC 28403",
    "addr:housenumber":"3020",
    "addr:postcode":"28403",
    "addr:street":"Market St",
    "iso:country":"US",
    "sg:address":"3020 Market St",
    "sg:city":"Wilmington",
    "sg:classifiers":[
        {
            "category":"Shopping",
            "subcategory":"Used Merchandise",
            "type":"Retail Goods"
        }
    ],
    "sg:phone":"+1 910 815 0907",
    "sg:postcode":"28403",
    "sg:province":"NC",
    "wof:name":"Ivy Cottage",
    "wof:placetype":"venue"
},
  "geometry": {"coordinates":[-77.906088,34.239918],"type":"Point"}
}