{
  "type": "Feature",
  "properties": {
    "addr:full":"5420 Brokaw Dr Trinity NC 27370",
    "addr:postcode":"5420;27370",
    "addr:street":"Brokaw Dr",
    "iso:country":"US",
    "sg:address":"5420 Brokaw Dr",
    "sg:city":"Trinity",
    "sg:classifiers":[
        {
            "category":"Retail",
            "subcategory":"Auto Repair",
            "type":"Services"
        }
    ],
    "sg:phone":"+1   ",
    "sg:postcode":"27370",
    "sg:province":"NC",
    "sg:tags":[
        "general"
    ],
    "wof:name":"Vetell",
    "wof:placetype":"venue"
},
  "geometry": {"coordinates":[-79.983879,35.855547],"type":"Point"}
}