{
  "type": "Feature",
  "properties": {
    "addr:full":"311 Friendly Rd Morehead City NC 28557",
    "addr:housenumber":"311",
    "addr:postcode":"28557",
    "addr:street":"Friendly Rd",
    "iso:country":"US",
    "sg:address":"311 Friendly Rd",
    "sg:city":"Morehead City",
    "sg:classifiers":[
        {
            "category":"Building & Trades",
            "subcategory":"Construction",
            "type":"Services"
        }
    ],
    "sg:phone":"+1 252 726 6933",
    "sg:postcode":"28557",
    "sg:province":"NC",
    "sg:tags":[
        "general",
        "contractor"
    ],
    "wof:name":"Ronnie Gillikin Construction",
    "wof:placetype":"venue"
},
  "geometry": {"coordinates":[-76.766019,34.730929],"type":"Point"}
}