{
  "type": "Feature",
  "properties": {
    "iso:country":"US",
    "sg:address":"55 Partner Dr",
    "sg:city":"Hendersonville",
    "sg:classifiers":[
        {
            "category":"Building & Trades",
            "subcategory":"Construction",
            "type":"Services"
        }
    ],
    "sg:phone":"+1 828 698 5797",
    "sg:postcode":"28792",
    "sg:province":"NC",
    "sg:tags":[
        "painter"
    ],
    "wof:name":"Shepherd Painting",
    "wof:placetype":"venue"
},
  "geometry": {"coordinates":[-82.441676,35.312851],"type":"Point"}
}