{
  "type": "Feature",
  "properties": {
    "addr:full":"802 Old Spartanburg Rd Hendersonville NC 28792",
    "addr:housenumber":"802",
    "addr:postcode":"28792",
    "addr:street":"Old Spartanburg Rd",
    "iso:country":"US",
    "sg:address":"802 Old Spartanburg Rd",
    "sg:city":"Hendersonville",
    "sg:classifiers":[
        {
            "category":"Social Services",
            "subcategory":"Child Care",
            "type":"Services"
        },
        {
            "category":"Education",
            "subcategory":"School",
            "type":"Public Place"
        }
    ],
    "sg:phone":"+1 828 693 6845",
    "sg:postcode":"28792",
    "sg:province":"NC",
    "sg:tags":[
        "day",
        "private"
    ],
    "wof:name":"Heritage Hall School Inc",
    "wof:placetype":"venue"
},
  "geometry": {"coordinates":[-82.449117,35.307736],"type":"Point"}
}