{
  "type": "Feature",
  "properties": {
    "iso:country":"US",
    "sg:address":"301 10th St NW",
    "sg:city":"Conover",
    "sg:classifiers":[
        {
            "category":"Building & Trades",
            "subcategory":"Construction",
            "type":"Services"
        }
    ],
    "sg:phone":"+1 828 464 6911",
    "sg:postcode":"28613",
    "sg:province":"NC",
    "sg:tags":[
        "dry wall",
        "contractor"
    ],
    "wof:name":"Dry-Wall Carolina Of Hickory",
    "wof:placetype":"venue"
},
  "geometry": {"coordinates":[-81.223305,35.718925],"type":"Point"}
}