{
  "type": "Feature",
  "properties": {
    "addr:full":"725 S Jefferson Ave West Jefferson NC 28694",
    "addr:housenumber":"725",
    "addr:postcode":"28694",
    "addr:street":"S Jefferson Ave",
    "iso:country":"US",
    "sg:address":"725 S Jefferson Ave",
    "sg:city":"West Jefferson",
    "sg:classifiers":[
        {
            "category":"Autos & Motor Vehicles",
            "subcategory":"Auto Supplies",
            "type":"Retail Goods"
        }
    ],
    "sg:phone":"+1 336 246 2711",
    "sg:postcode":"28694",
    "sg:province":"NC",
    "sg:tags":[
        "automobile",
        "parts"
    ],
    "wof:name":"O'REILLY Auto Parts",
    "wof:placetype":"venue"
},
  "geometry": {"coordinates":[-81.48863799999999,36.393677],"type":"Point"}
}