{
  "type": "Feature",
  "properties": {
    "iso:country":"US",
    "sg:address":"6010 Landmark Center Blvd",
    "sg:city":"Greensboro",
    "sg:classifiers":[
        {
            "category":"Restaurant",
            "type":"Food & Drink"
        }
    ],
    "sg:menulink":"http://www.allmenus.com/nc/greensboro/156610-villa-rosa-italian-restaurant--grill/menu/",
    "sg:phone":"+1 336 294 8688",
    "sg:postcode":"27407",
    "sg:province":"NC",
    "sg:tags":[
        "italian"
    ],
    "wof:name":"Villa Rosa Italian Restaurant & Grill",
    "wof:placetype":"venue"
},
  "geometry": {"coordinates":[-79.895133,36.053691],"type":"Point"}
}