{
  "type": "Feature",
  "properties": {
    "addr:full":"216 Park St Belmont NC 28012",
    "addr:housenumber":"216",
    "addr:postcode":"28012",
    "addr:street":"Park St",
    "iso:country":"US",
    "sg:address":"216 Park St",
    "sg:city":"Belmont",
    "sg:classifiers":[
        {
            "category":"Shopping",
            "subcategory":"Stationery & Office Supplies",
            "type":"Retail Goods"
        },
        {
            "category":"Wholesale",
            "subcategory":"Stationery",
            "type":"Manufacturing & Wholesale Goods"
        }
    ],
    "sg:phone":"+1 704 829 6046",
    "sg:postcode":"28012",
    "sg:province":"NC",
    "sg:tags":[
        "equipment",
        "r"
    ],
    "wof:name":"Forbes Office Supply Inc",
    "wof:placetype":"venue"
},
  "geometry": {"coordinates":[-81.031283,35.246071],"type":"Point"}
}