{
  "type": "Feature",
  "properties": {
    "addr:full":"1393 Hasty School Rd Thomasville NC 27360",
    "addr:housenumber":"1393",
    "addr:postcode":"27360",
    "addr:street":"Hasty School Rd",
    "iso:country":"US",
    "sg:address":"1393 Hasty School Rd",
    "sg:city":"Thomasville",
    "sg:classifiers":[
        {
            "category":"Organizations",
            "subcategory":"Religious Organization",
            "type":"Services"
        }
    ],
    "sg:phone":"+1 336 475 1124",
    "sg:postcode":"27360",
    "sg:province":"NC",
    "sg:tags":[
        "church"
    ],
    "wof:name":"Pleasant Grove United Meth",
    "wof:placetype":"venue"
},
  "geometry": {"coordinates":[-80.052633,35.914022],"type":"Point"}
}