{
  "type": "Feature",
  "properties": {
    "iso:country":"US",
    "sg:address":"105 Hearthside Dr",
    "sg:city":"Greenville",
    "sg:classifiers":[
        {
            "category":"Restaurant",
            "type":"Food & Drink"
        }
    ],
    "sg:phone":"+1 252 321 3838",
    "sg:postcode":"27834",
    "sg:province":"NC",
    "wof:name":"MAT Smith Inc",
    "wof:placetype":"venue"
},
  "geometry": {"coordinates":[-77.40188499999999,35.564746],"type":"Point"}
}