{
  "type": "Feature",
  "properties": {
    "addr:full":"3888 Meadow Ridge Dr NW Concord NC 28027",
    "addr:housenumber":"3888",
    "addr:postcode":"28027",
    "addr:street":"Meadow Ridge Dr Nw",
    "iso:country":"US",
    "sg:address":"3888 Meadow Ridge Dr NW",
    "sg:city":"Concord",
    "sg:classifiers":[
        {
            "category":"Building & Trades",
            "subcategory":"Plumbing",
            "type":"Services"
        }
    ],
    "sg:phone":"+1 704 699 5153",
    "sg:postcode":"28027",
    "sg:province":"NC",
    "sg:tags":[
        "contractor"
    ],
    "wof:name":"Elite Irrigation",
    "wof:placetype":"venue"
},
  "geometry": {"coordinates":[-80.637458,35.40174],"type":"Point"}
}