{
  "type": "Feature",
  "properties": {
    "iso:country":"US",
    "sg:address":"213 S College Ave",
    "sg:city":"Newton",
    "sg:classifiers":[
        {
            "category":"Restaurant",
            "type":"Food & Drink"
        }
    ],
    "sg:phone":"+1 828 464 3339",
    "sg:postcode":"28658",
    "sg:province":"NC",
    "wof:name":"Cruiser Cafe Inc",
    "wof:placetype":"venue"
},
  "geometry": {"coordinates":[-81.22234,35.660159],"type":"Point"}
}