{
  "type": "Feature",
  "properties": {
    "addr:full":"6617 Falls Of Neuse Rd Raleigh NC 27615",
    "addr:housenumber":"6617",
    "addr:postcode":"27615",
    "addr:street":"Falls Of Neuse Rd",
    "iso:country":"US",
    "sg:address":"6617 Falls Of Neuse Rd",
    "sg:city":"Raleigh",
    "sg:classifiers":[
        {
            "category":"Personal",
            "subcategory":"Beauty Salon",
            "type":"Services"
        },
        {
            "category":"Shopping",
            "subcategory":"Party Supplies",
            "type":"Retail Goods"
        },
        {
            "category":"Personal",
            "subcategory":"Skin Care",
            "type":"Services"
        },
        {
            "category":"Personal",
            "subcategory":"Hair Removal",
            "type":"Services"
        }
    ],
    "sg:phone":"+1 919 848 0555",
    "sg:postcode":"27615",
    "sg:province":"NC",
    "sg:tags":[
        "cosmetologist",
        "stylist",
        "wedding"
    ],
    "sg:website":"http://www.salonbluhair.com",
    "wof:name":"Salon Blu-",
    "wof:placetype":"venue"
},
  "geometry": {"coordinates":[-78.62235699999999,35.873175],"type":"Point"}
}