{
  "type": "Feature",
  "properties": {
    "addr:full":"4925 Gable Ridge Ln Holly Springs NC 27540",
    "addr:housenumber":"4925",
    "addr:postcode":"27540",
    "addr:street":"Gable Ridge Ln",
    "iso:country":"US",
    "sg:address":"4925 Gable Ridge Ln",
    "sg:city":"Holly Springs",
    "sg:classifiers":[
        {
            "category":"Manufacturing",
            "subcategory":"Printing",
            "type":"Manufacturing & Wholesale Goods"
        }
    ],
    "sg:phone":"+1 919 567 3088",
    "sg:postcode":"27540",
    "sg:province":"NC",
    "sg:tags":[
        "printer"
    ],
    "wof:name":"Victor Graphics",
    "wof:placetype":"venue"
},
  "geometry": {"coordinates":[-78.81008,35.654935],"type":"Point"}
}