{
  "type": "Feature",
  "properties": {
    "addr:full":"2831 Emory Rd Morganton NC 28655",
    "addr:housenumber":"2831",
    "addr:postcode":"28655",
    "addr:street":"Emory Rd",
    "iso:country":"US",
    "sg:address":"2831 Emory Rd",
    "sg:city":"Morganton",
    "sg:classifiers":[
        {
            "category":"Insurance",
            "subcategory":"Insurance Agent",
            "type":"Services"
        }
    ],
    "sg:phone":"+1 828 437 6098",
    "sg:postcode":"28655",
    "sg:province":"NC",
    "wof:name":"Homer I Cline",
    "wof:placetype":"venue"
},
  "geometry": {"coordinates":[-81.63430099999999,35.750727],"type":"Point"}
}