{
  "type": "Feature",
  "properties": {
    "iso:country":"US",
    "sg:address":"246 E Millbrook Rd",
    "sg:city":"Raleigh",
    "sg:classifiers":[
        {
            "category":"Real Estate",
            "subcategory":"Surveying",
            "type":"Services"
        }
    ],
    "sg:phone":"+1 919 847 1800",
    "sg:postcode":"27609",
    "sg:province":"NC",
    "sg:tags":[
        "surveyor"
    ],
    "sg:website":"www.newcomblandsurveyors.com",
    "wof:name":"Newcomb Land Surveyors",
    "wof:placetype":"venue"
},
  "geometry": {"coordinates":[-78.637927,35.855024],"type":"Point"}
}