{
  "type": "Feature",
  "properties": {
    "iso:country":"US",
    "sg:address":"304 Erinshire Ct",
    "sg:city":"Wilmington",
    "sg:classifiers":[
        {
            "category":"Personal",
            "type":"Services"
        }
    ],
    "sg:phone":"+1   ",
    "sg:postcode":"28412",
    "sg:province":"NC",
    "wof:name":"Handyman Jim",
    "wof:placetype":"venue"
},
  "geometry": {"coordinates":[-77.915982,34.107237],"type":"Point"}
}