{
  "type": "Feature",
  "properties": {
    "addr:full":"2410 Owen Dr Fayetteville NC 28306",
    "addr:housenumber":"2410",
    "addr:postcode":"28306",
    "addr:street":"Owen Dr",
    "iso:country":"US",
    "sg:address":"2410 Owen Dr",
    "sg:city":"Fayetteville",
    "sg:classifiers":[
        {
            "category":"Autos & Motor Vehicles",
            "subcategory":"Fuel & Gas Station",
            "type":"Retail Goods"
        }
    ],
    "sg:phone":"+1 910 485 4687",
    "sg:postcode":"28306",
    "sg:province":"NC",
    "sg:tags":[
        "convenience",
        "station",
        "gasoline",
        "store"
    ],
    "wof:name":"Etna",
    "wof:placetype":"venue"
},
  "geometry": {"coordinates":[-78.914681,35.01855],"type":"Point"}
}