{
  "type": "Feature",
  "properties": {
    "addr:full":"703 Westchester Dr High Point NC 27262",
    "addr:housenumber":"703",
    "addr:postcode":"27262",
    "addr:street":"Westchester Dr",
    "iso:country":"US",
    "sg:address":"703 Westchester Dr",
    "sg:city":"High Point",
    "sg:classifiers":[
        {
            "category":"Shopping",
            "subcategory":"Computers & Home Electronics",
            "type":"Retail Goods"
        }
    ],
    "sg:phone":"+1 336 883 8265",
    "sg:postcode":"27262",
    "sg:province":"NC",
    "sg:tags":[
        "software"
    ],
    "wof:name":"File Net",
    "wof:placetype":"venue"
},
  "geometry": {"coordinates":[-80.032974,35.976269],"type":"Point"}
}