{
  "type": "Feature",
  "properties": {
    "addr:full":"3090 US Hwy 117 Magnolia NC 28453",
    "addr:housenumber":"3090",
    "addr:postcode":"28453",
    "addr:street":"Us Hwy 117",
    "iso:country":"US",
    "sg:address":"3090 US Hwy 117",
    "sg:city":"Magnolia",
    "sg:phone":"+1 910 289 3430",
    "sg:postcode":"28453",
    "sg:province":"NC",
    "sg:tags":[
        "farm",
        "grain",
        "cash"
    ],
    "wof:name":"Wilson John",
    "wof:placetype":"venue"
},
  "geometry": {"coordinates":[-78.04409,34.87569],"type":"Point"}
}