{
  "type": "Feature",
  "properties": {
    "iso:country":"US",
    "sg:address":"200 Fayetteville Rd",
    "sg:city":"Roseboro",
    "sg:classifiers":[
        {
            "category":"Food & Beverages",
            "subcategory":"Groceries & Convenience Stores",
            "type":"Retail Goods"
        }
    ],
    "sg:phone":"+1 910 525 5715",
    "sg:postcode":"28344",
    "sg:province":"NC",
    "wof:name":"Texaco",
    "wof:placetype":"venue"
},
  "geometry": {"coordinates":[-78.640686,35.19307],"type":"Point"}
}