{
  "type": "Feature",
  "properties": {
    "addr:full":"18301 Mainsail Pointe Dr Cornelius NC 28031",
    "addr:housenumber":"18301",
    "addr:postcode":"28031",
    "addr:street":"Mainsail Pointe Dr",
    "iso:country":"US",
    "sg:address":"18301 Mainsail Pointe Dr",
    "sg:city":"Cornelius",
    "sg:classifiers":[
        {
            "category":"Building & Trades",
            "subcategory":"Construction",
            "type":"Services"
        }
    ],
    "sg:phone":"+1 704 606 0232",
    "sg:postcode":"28031",
    "sg:province":"NC",
    "sg:tags":[
        "general",
        "contractor"
    ],
    "wof:name":"J Mack Enterprises Inc",
    "wof:placetype":"venue"
},
  "geometry": {"coordinates":[-80.91440799999999,35.461321],"type":"Point"}
}