{
  "type": "Feature",
  "properties": {
    "iso:country":"US",
    "sg:address":"444 S Jefferson Ave",
    "sg:city":"West Jefferson",
    "sg:classifiers":[
        {
            "category":"Organizations",
            "subcategory":"Religious Organization",
            "type":"Services"
        }
    ],
    "sg:phone":"+1   ",
    "sg:postcode":"28694",
    "sg:province":"NC",
    "sg:tags":[
        "baptist",
        "church"
    ],
    "wof:name":"Friendly Grove Baptist Church",
    "wof:placetype":"venue"
},
  "geometry": {"coordinates":[-81.490932,36.398411],"type":"Point"}
}