{
  "type": "Feature",
  "properties": {
    "iso:country":"US",
    "sg:address":"163 Colonial Dr",
    "sg:city":"Burlington",
    "sg:classifiers":[
        {
            "category":"Professional",
            "type":"Services"
        },
        {
            "category":"Building & Trades",
            "subcategory":"Construction",
            "type":"Services"
        },
        {
            "category":"Shopping",
            "subcategory":"Gifts & Souvenirs",
            "type":"Retail Goods"
        }
    ],
    "sg:phone":"+1 336 585 1901",
    "sg:postcode":"27215",
    "sg:province":"NC",
    "sg:tags":[
        "supply",
        "home",
        "improvement",
        "party"
    ],
    "wof:name":"Home Impression Plus",
    "wof:placetype":"venue"
},
  "geometry": {"coordinates":[-79.475673,36.081608],"type":"Point"}
}