{
  "type": "Feature",
  "properties": {
    "iso:country":"US",
    "sg:address":"4432 Courtney-Huntsville Rd",
    "sg:city":"Yadkinville",
    "sg:phone":"+1 336 463 4732",
    "sg:postcode":"27055",
    "sg:province":"NC",
    "sg:tags":[
        "farm",
        "soybean"
    ],
    "wof:name":"Tommy Cumby",
    "wof:placetype":"venue"
},
  "geometry": {"coordinates":[-80.552662,36.086484],"type":"Point"}
}