{
  "type": "Feature",
  "properties": {
    "addr:full":"830 Raleigh Rd Rocky Mount NC 27803",
    "addr:housenumber":"830",
    "addr:postcode":"27803",
    "addr:street":"Raleigh Rd",
    "iso:country":"US",
    "sg:address":"830 Raleigh Rd",
    "sg:city":"Rocky Mount",
    "sg:classifiers":[
        {
            "category":"Restaurant",
            "type":"Food & Drink"
        }
    ],
    "sg:menulink":"http://www.allmenus.com/nc/rocky-mount/156322-hardees/menu/",
    "sg:phone":"+1 252 442 2931",
    "sg:postcode":"27803",
    "sg:province":"NC",
    "sg:tags":[
        "burger",
        "american"
    ],
    "wof:name":"Hardee's",
    "wof:placetype":"venue"
},
  "geometry": {"coordinates":[-77.811245,35.932329],"type":"Point"}
}