{
  "type": "Feature",
  "properties": {
    "addr:full":"2642 Onslow Dr Jacksonville NC 28540",
    "addr:housenumber":"2642",
    "addr:postcode":"28540",
    "addr:street":"Onslow Dr",
    "iso:country":"US",
    "sg:address":"2642 Onslow Dr",
    "sg:city":"Jacksonville",
    "sg:classifiers":[
        {
            "category":"Government",
            "subcategory":"Post Office",
            "type":"Public Place"
        }
    ],
    "sg:phone":"+1 910 455 3101",
    "sg:postcode":"28540",
    "sg:province":"NC",
    "sg:tags":[
        "postal",
        "us"
    ],
    "wof:name":"Northwoods Station",
    "wof:placetype":"venue"
},
  "geometry": {"coordinates":[-77.420548,34.764627],"type":"Point"}
}