{
  "type": "Feature",
  "properties": {
    "addr:full":"110 Banks Dr Chapel Hill NC 27514",
    "addr:housenumber":"110",
    "addr:postcode":"27514",
    "addr:street":"Banks Dr",
    "iso:country":"US",
    "sg:address":"110 Banks Dr",
    "sg:city":"Chapel Hill",
    "sg:classifiers":[
        {
            "category":"Restaurant",
            "type":"Food & Drink"
        }
    ],
    "sg:menulink":"http://www.allmenus.com/nc/chapel-hill/85324-dominos-pizza/menu/",
    "sg:phone":"+1 919 932 9500",
    "sg:postcode":"27514",
    "sg:province":"NC",
    "sg:tags":[
        "american",
        "wing",
        "pizza"
    ],
    "wof:name":"Domino's Pizza",
    "wof:placetype":"venue"
},
  "geometry": {"coordinates":[-79.055227,35.961755],"type":"Point"}
}