{
  "type": "Feature",
  "properties": {
    "iso:country":"US",
    "sg:address":"2330 US Hwy 29 S",
    "sg:city":"China Grove",
    "sg:classifiers":[
        {
            "category":"Personal",
            "type":"Services"
        }
    ],
    "sg:phone":"+1   ",
    "sg:postcode":"28023",
    "sg:province":"NC",
    "wof:name":"V Nails",
    "wof:placetype":"venue"
},
  "geometry": {"coordinates":[-80.596419,35.544352],"type":"Point"}
}