{
  "type": "Feature",
  "properties": {
    "iso:country":"US",
    "sg:address":"2760 Tabernacle Church Rd",
    "sg:city":"Pleasant Garden",
    "sg:classifiers":[
        {
            "category":"Shopping",
            "type":"Retail Goods"
        }
    ],
    "sg:phone":"+1 336 674 2792",
    "sg:postcode":"27313",
    "sg:province":"NC",
    "sg:tags":[
        "merchandise"
    ],
    "wof:name":"John J Carroll",
    "wof:placetype":"venue"
},
  "geometry": {"coordinates":[-79.71920299999999,35.962424],"type":"Point"}
}