{
  "type": "Feature",
  "properties": {
    "addr:full":"5205 Apple Tree Ln Morganton NC 28655",
    "addr:housenumber":"5205",
    "addr:postcode":"28655",
    "addr:street":"Apple Tree Ln",
    "iso:country":"US",
    "sg:address":"5205 Apple Tree Ln",
    "sg:city":"Morganton",
    "sg:classifiers":[
        {
            "category":"Farming",
            "subcategory":"Orchard",
            "type":"Manufacturing & Wholesale Goods"
        }
    ],
    "sg:phone":"+1 828 437 1224",
    "sg:postcode":"28655",
    "sg:province":"NC",
    "sg:tags":[
        "fruit",
        "tree"
    ],
    "sg:website":"www.applehillorchard.com",
    "wof:name":"Apple Hill Orchrd & Cider Mill",
    "wof:placetype":"venue"
},
  "geometry": {"coordinates":[-81.659661,35.665893],"type":"Point"}
}