{
  "type": "Feature",
  "properties": {
    "iso:country":"US",
    "sg:address":"717 N Pine St",
    "sg:city":"Warsaw",
    "sg:classifiers":[
        {
            "category":"Professional",
            "subcategory":"Employment Agencies",
            "type":"Services"
        }
    ],
    "sg:phone":"+1 910 293 5400",
    "sg:postcode":"28398",
    "sg:province":"NC",
    "sg:tags":[
        "opportunity"
    ],
    "wof:name":"Mega Force Staffing",
    "wof:placetype":"venue"
},
  "geometry": {"coordinates":[-78.09439,35.006443],"type":"Point"}
}