{
  "type": "Feature",
  "properties": {
    "iso:country":"US",
    "sg:address":"3305 S Wrightsville Ave",
    "sg:city":"Nags Head",
    "sg:classifiers":[
        {
            "category":"Building & Trades",
            "subcategory":"Plumbing",
            "type":"Services"
        }
    ],
    "sg:phone":"+1 252 441 9000",
    "sg:postcode":"27959",
    "sg:province":"NC",
    "sg:tags":[
        "conditioning",
        "contractor",
        "system",
        "air"
    ],
    "wof:name":"Albemarle Mechanical Inc",
    "wof:placetype":"venue"
},
  "geometry": {"coordinates":[-75.635091,35.97298],"type":"Point"}
}