{
  "type": "Feature",
  "properties": {
    "addr:full":"302 W Market St Greensboro NC 27401",
    "addr:housenumber":"302",
    "addr:postcode":"27401",
    "addr:street":"W Market St",
    "iso:country":"US",
    "sg:address":"302 W Market St",
    "sg:city":"Greensboro",
    "sg:classifiers":[
        {
            "category":"Organizations",
            "subcategory":"Non-profit Organization",
            "type":"Services"
        },
        {
            "category":"Social Services",
            "type":"Services"
        }
    ],
    "sg:phone":"+1 336 378 0766",
    "sg:postcode":"27401",
    "sg:province":"NC",
    "wof:name":"Shepherd's Center-Greensboro",
    "wof:placetype":"venue"
},
  "geometry": {"coordinates":[-79.79366400000001,36.072736],"type":"Point"}
}