{
  "type": "Feature",
  "properties": {
    "iso:country":"US",
    "sg:address":"2009 Swepsonville Rd",
    "sg:city":"Graham",
    "sg:classifiers":[
        {
            "category":"Building & Trades",
            "subcategory":"Construction",
            "type":"Services"
        }
    ],
    "sg:phone":"+1 336 516 6103",
    "sg:postcode":"27253",
    "sg:province":"NC",
    "sg:tags":[
        "contractor"
    ],
    "wof:name":"Fitch Drywall Inc",
    "wof:placetype":"venue"
},
  "geometry": {"coordinates":[-79.380476,36.031291],"type":"Point"}
}