{
  "type": "Feature",
  "properties": {
    "iso:country":"US",
    "sg:address":"301 S McDowell St",
    "sg:city":"Charlotte",
    "sg:classifiers":[
        {
            "category":"Shopping",
            "type":"Retail Goods"
        }
    ],
    "sg:phone":"+1 704 331 8313",
    "sg:postcode":"28204",
    "sg:province":"NC",
    "sg:tags":[
        "product",
        "wood"
    ],
    "wof:name":"Strictly Wood",
    "wof:placetype":"venue"
},
  "geometry": {"coordinates":[-80.838753,35.217794],"type":"Point"}
}