{
  "type": "Feature",
  "properties": {
    "addr:full":"900 Wilson St Elizabeth City NC 27909",
    "addr:housenumber":"900",
    "addr:postcode":"27909",
    "addr:street":"Wilson St",
    "iso:country":"US",
    "sg:address":"900 Wilson St",
    "sg:city":"Elizabeth City",
    "sg:classifiers":[
        {
            "category":"Health Services",
            "subcategory":"Chiropractor",
            "type":"Services"
        },
        {
            "category":"Health Services",
            "subcategory":"Doctor",
            "type":"Services"
        }
    ],
    "sg:phone":"+1 252 338 4137",
    "sg:postcode":"27909",
    "sg:province":"NC",
    "sg:tags":[
        "medical"
    ],
    "wof:name":"Elizabeth City Chirop Clinic",
    "wof:placetype":"venue"
},
  "geometry": {"coordinates":[-76.225561,36.311335],"type":"Point"}
}