{
  "type": "Feature",
  "properties": {
    "iso:country":"US",
    "sg:address":"8 Gum Chapel Rd",
    "sg:city":"Roanoke Rapids",
    "sg:classifiers":[
        {
            "category":"Organizations",
            "subcategory":"Religious Organization",
            "type":"Services"
        }
    ],
    "sg:phone":"+1 252 537 4777",
    "sg:postcode":"27870",
    "sg:province":"NC",
    "sg:tags":[
        "church"
    ],
    "wof:name":"Open Door Fellowship",
    "wof:placetype":"venue"
},
  "geometry": {"coordinates":[-77.70008,36.446894],"type":"Point"}
}