{
  "type": "Feature",
  "properties": {
    "iso:country":"US",
    "sg:address":"4379 Republic Ct NW",
    "sg:city":"Concord",
    "sg:classifiers":[
        {
            "category":"Professional",
            "subcategory":"Advertising",
            "type":"Services"
        }
    ],
    "sg:phone":"+1 704 795 3524",
    "sg:postcode":"28027",
    "sg:province":"NC",
    "sg:tags":[
        "mailing",
        "shipping"
    ],
    "wof:name":"MAILED Inc",
    "wof:placetype":"venue"
},
  "geometry": {"coordinates":[-80.650555,35.421456],"type":"Point"}
}