{
  "type": "Feature",
  "properties": {
    "addr:full":"101 N Main St Randleman NC 27317",
    "addr:housenumber":"101",
    "addr:postcode":"27317",
    "addr:street":"N Main St",
    "iso:country":"US",
    "sg:address":"101 N Main St",
    "sg:city":"Randleman",
    "sg:classifiers":[
        {
            "category":"Shopping",
            "subcategory":"Florist",
            "type":"Retail Goods"
        }
    ],
    "sg:phone":"+1 336 498 7661",
    "sg:postcode":"27317",
    "sg:province":"NC",
    "wof:name":"Freeman's Florist & Gifts",
    "wof:placetype":"venue"
},
  "geometry": {"coordinates":[-79.80310299999999,35.817844],"type":"Point"}
}