{
  "type": "Feature",
  "properties": {
    "addr:full":"8109 Fayetteville Rd Raleigh NC 27603",
    "addr:housenumber":"8109",
    "addr:postcode":"27603",
    "addr:street":"Fayetteville Rd",
    "iso:country":"US",
    "sg:address":"8109 Fayetteville Rd",
    "sg:city":"Raleigh",
    "sg:classifiers":[
        {
            "category":"Restaurant",
            "type":"Food & Drink"
        }
    ],
    "sg:menulink":"http://www.allmenus.com/nc/middle-creek/137300-subway/menu/",
    "sg:phone":"+1 919 779 0635",
    "sg:postcode":"27603",
    "sg:province":"NC",
    "sg:tags":[
        "american",
        "sandwich"
    ],
    "wof:name":"Subway",
    "wof:placetype":"venue"
},
  "geometry": {"coordinates":[-78.700851,35.663519],"type":"Point"}
}