{
  "type": "Feature",
  "properties": {
    "addr:full":"122 S Churton St Hillsborough NC 27278",
    "addr:housenumber":"122",
    "addr:postcode":"27278",
    "addr:street":"S Churton St",
    "iso:country":"US",
    "sg:address":"122 S Churton St",
    "sg:city":"Hillsborough",
    "sg:classifiers":[
        {
            "category":"Cafe",
            "type":"Food & Drink"
        },
        {
            "category":"Restaurant",
            "type":"Food & Drink"
        }
    ],
    "sg:menulink":"http://www.allmenus.com/nc/hillsborough/140804-bandidos-mexican-cafe/menu/",
    "sg:phone":"+1 919 732 8662",
    "sg:postcode":"27278",
    "sg:province":"NC",
    "sg:tags":[
        "mexican"
    ],
    "wof:name":"Bandidos Mexican Cafe",
    "wof:placetype":"venue"
},
  "geometry": {"coordinates":[-79.099389,36.075147],"type":"Point"}
}