{
  "type": "Feature",
  "properties": {
    "addr:full":"806 Locust St Hendersonville NC 28792",
    "addr:housenumber":"806",
    "addr:postcode":"28792",
    "addr:street":"Locust St",
    "iso:country":"US",
    "sg:address":"806 Locust St",
    "sg:city":"Hendersonville",
    "sg:classifiers":[
        {
            "category":"Real Estate",
            "subcategory":"Real Estate Agent",
            "type":"Services"
        }
    ],
    "sg:phone":"+1 828 697 2422",
    "sg:postcode":"28792",
    "sg:province":"NC",
    "sg:tags":[
        "manager"
    ],
    "wof:name":"Locust Street Properties Inc",
    "wof:placetype":"venue"
},
  "geometry": {"coordinates":[-82.459463,35.322369],"type":"Point"}
}