{
  "type": "Feature",
  "properties": {
    "addr:full":"9229 Lawyers Rd Charlotte NC 28227",
    "addr:housenumber":"9229",
    "addr:postcode":"28227",
    "addr:street":"Lawyers Rd",
    "iso:country":"US",
    "sg:address":"9229 Lawyers Rd",
    "sg:city":"Charlotte",
    "sg:classifiers":[
        {
            "category":"Shopping",
            "subcategory":"Pharmacy",
            "type":"Retail Goods"
        }
    ],
    "sg:phone":"+1 704 545 3420",
    "sg:postcode":"28227",
    "sg:province":"NC",
    "sg:tags":[
        "drug",
        "store"
    ],
    "wof:name":"Cvs",
    "wof:placetype":"venue"
},
  "geometry": {"coordinates":[-80.686881,35.185482],"type":"Point"}
}