{
  "type": "Feature",
  "properties": {
    "addr:full":"1602 E Franklin St Chapel Hill NC 27514",
    "addr:housenumber":"1602",
    "addr:postcode":"27514",
    "addr:street":"E Franklin St",
    "iso:country":"US",
    "sg:address":"1602 E Franklin St",
    "sg:city":"Chapel Hill",
    "sg:classifiers":[
        {
            "category":"Health Services",
            "subcategory":"Nursing And Care Facility",
            "type":"Services"
        }
    ],
    "sg:phone":"+1 919 967 1418",
    "sg:postcode":"27514",
    "sg:province":"NC",
    "sg:tags":[
        "skilled"
    ],
    "wof:name":"Kindred Healthcare Inc",
    "wof:placetype":"venue"
},
  "geometry": {"coordinates":[-79.027051,35.936226],"type":"Point"}
}