{
  "type": "Feature",
  "properties": {
    "addr:full":"314 E Plaza Dr Mooresville NC 28115",
    "addr:housenumber":"314",
    "addr:postcode":"28115",
    "addr:street":"E Plaza Dr",
    "iso:country":"US",
    "sg:address":"314 E Plaza Dr",
    "sg:city":"Mooresville",
    "sg:classifiers":[
        {
            "category":"Shopping",
            "subcategory":"Discount & Variety Stores",
            "type":"Retail Goods"
        }
    ],
    "sg:phone":"+1 704 799 3640",
    "sg:postcode":"28115",
    "sg:province":"NC",
    "sg:website":"www.biglots.com",
    "wof:name":"Big Lots",
    "wof:placetype":"venue"
},
  "geometry": {"coordinates":[-80.817785,35.594407],"type":"Point"}
}