{
  "type": "Feature",
  "properties": {
    "iso:country":"US",
    "sg:address":"309 Commodore Loop",
    "sg:city":"Mooresville",
    "sg:classifiers":[
        {
            "category":"Building & Trades",
            "subcategory":"Construction",
            "type":"Services"
        }
    ],
    "sg:phone":"+1 704 662 6019",
    "sg:postcode":"28117",
    "sg:province":"NC",
    "sg:tags":[
        "heavy"
    ],
    "wof:name":"Floatation Services",
    "wof:placetype":"venue"
},
  "geometry": {"coordinates":[-80.895448,35.548156],"type":"Point"}
}