{
  "type": "Feature",
  "properties": {
    "addr:full":"407 Live Oak St Beaufort NC 28516",
    "addr:housenumber":"407",
    "addr:postcode":"28516",
    "addr:street":"Live Oak St",
    "iso:country":"US",
    "sg:address":"407 Live Oak St",
    "sg:city":"Beaufort",
    "sg:classifiers":[
        {
            "category":"Organizations",
            "subcategory":"Religious Organization",
            "type":"Services"
        }
    ],
    "sg:phone":"+1 252 728 2917",
    "sg:postcode":"28516",
    "sg:province":"NC",
    "sg:tags":[
        "church"
    ],
    "wof:name":"Faith & Victory Church",
    "wof:placetype":"venue"
},
  "geometry": {"coordinates":[-76.65610700000001,34.718568],"type":"Point"}
}