{
  "type": "Feature",
  "properties": {
    "addr:full":"610 N Main St Walnut Cove NC 27052",
    "addr:housenumber":"610",
    "addr:postcode":"27052",
    "addr:street":"N Main St",
    "iso:country":"US",
    "sg:address":"610 N Main St",
    "sg:city":"Walnut Cove",
    "sg:classifiers":[
        {
            "category":"Shopping",
            "subcategory":"Pharmacy",
            "type":"Retail Goods"
        }
    ],
    "sg:phone":"+1 336 591 8629",
    "sg:postcode":"27052",
    "sg:province":"NC",
    "wof:name":"CVS Pharmacy",
    "wof:placetype":"venue"
},
  "geometry": {"coordinates":[-80.14149999999999,36.299619],"type":"Point"}
}