{
  "type": "Feature",
  "properties": {
    "addr:full":"108 Bear Ln Mooresville NC 28117",
    "addr:housenumber":"108",
    "addr:postcode":"28117",
    "addr:street":"Bear Ln",
    "iso:country":"US",
    "sg:address":"108 Bear Ln",
    "sg:city":"Mooresville",
    "sg:classifiers":[
        {
            "category":"Professional",
            "type":"Services"
        }
    ],
    "sg:phone":"+1 704 799 1456",
    "sg:postcode":"28117",
    "sg:province":"NC",
    "wof:name":"Jake Emnett",
    "wof:placetype":"venue"
},
  "geometry": {"coordinates":[-80.853909,35.587079],"type":"Point"}
}