{
  "type": "Feature",
  "properties": {
    "addr:full":"13233 US Hwy 158 Reidsville NC 27320",
    "addr:housenumber":"13233",
    "addr:postcode":"27320",
    "addr:street":"Us Hwy 158",
    "iso:country":"US",
    "sg:address":"13233 US Hwy 158",
    "sg:city":"Reidsville",
    "sg:classifiers":[
        {
            "category":"Home & Garden",
            "subcategory":"Garden Supply",
            "type":"Retail Goods"
        }
    ],
    "sg:phone":"+1 336 342 2775",
    "sg:postcode":"27320",
    "sg:province":"NC",
    "sg:tags":[
        "repair"
    ],
    "wof:name":"Greensboro Farm Service Inc",
    "wof:placetype":"venue"
},
  "geometry": {"coordinates":[-79.837153,36.270568],"type":"Point"}
}