{
  "type": "Feature",
  "properties": {
    "iso:country":"US",
    "sg:address":"1688 Birchwood Dr",
    "sg:city":"Burlington",
    "sg:classifiers":[
        {
            "category":"Building & Trades",
            "subcategory":"Construction",
            "type":"Services"
        }
    ],
    "sg:phone":"+1 336 538 0641",
    "sg:postcode":"27217",
    "sg:province":"NC",
    "sg:tags":[
        "contractor"
    ],
    "wof:name":"McKinney G S Builders",
    "wof:placetype":"venue"
},
  "geometry": {"coordinates":[-79.459237,36.181517],"type":"Point"}
}