{
  "type": "Feature",
  "properties": {
    "iso:country":"US",
    "sg:address":"750 Broad Creek Rd",
    "sg:city":"New Bern",
    "sg:classifiers":[
        {
            "category":"Banks & Credit Unions",
            "subcategory":"Bank",
            "type":"Services"
        }
    ],
    "sg:phone":"+1 252 638 2075",
    "sg:postcode":"28560",
    "sg:province":"NC",
    "sg:tags":[
        "loan",
        "mortgage",
        "real estate"
    ],
    "wof:name":"National City Mortgage Co",
    "wof:placetype":"venue"
},
  "geometry": {"coordinates":[-76.947868,35.084513],"type":"Point"}
}