{
  "type": "Feature",
  "properties": {
    "iso:country":"US",
    "sg:address":"10 Tanager Trl",
    "sg:city":"Hendersonville",
    "sg:classifiers":[
        {
            "category":"Banks & Credit Unions",
            "subcategory":"Financial Services",
            "type":"Services"
        }
    ],
    "sg:phone":"+1 828 692 2910",
    "sg:postcode":"28792",
    "sg:province":"NC",
    "sg:tags":[
        "investor"
    ],
    "wof:name":"Britt Investments Henderson",
    "wof:placetype":"venue"
},
  "geometry": {"coordinates":[-82.445897,35.343753],"type":"Point"}
}