{
  "type": "Feature",
  "properties": {
    "iso:country":"US",
    "sg:address":"6841 Munford Dr",
    "sg:city":"Fayetteville",
    "sg:classifiers":[
        {
            "category":"Building & Trades",
            "subcategory":"Construction",
            "type":"Services"
        }
    ],
    "sg:phone":"+1 910 429 0732",
    "sg:postcode":"28306",
    "sg:province":"NC",
    "sg:tags":[
        "house"
    ],
    "wof:name":"GM Home Improvers",
    "wof:placetype":"venue"
},
  "geometry": {"coordinates":[-79.01866,34.996336],"type":"Point"}
}