{
  "type": "Feature",
  "properties": {
    "addr:full":"340 Spillman Rd Mocksville NC 27028",
    "addr:housenumber":"340",
    "addr:postcode":"27028",
    "addr:street":"Spillman Rd",
    "iso:country":"US",
    "sg:address":"340 Spillman Rd",
    "sg:city":"Mocksville",
    "sg:classifiers":[
        {
            "category":"Building & Trades",
            "subcategory":"Construction",
            "type":"Services"
        }
    ],
    "sg:phone":"+1 336 998 2701",
    "sg:postcode":"27028",
    "sg:province":"NC",
    "sg:tags":[
        "general",
        "contractor"
    ],
    "wof:name":"Shiloh Inc",
    "wof:placetype":"venue"
},
  "geometry": {"coordinates":[-80.50107800000001,36.025362],"type":"Point"}
}