{
  "type": "Feature",
  "properties": {
    "iso:country":"US",
    "sg:address":"1410 Asheville Hwy",
    "sg:city":"Hendersonville",
    "sg:classifiers":[
        {
            "category":"Restaurant",
            "type":"Food & Drink"
        }
    ],
    "sg:phone":"+1 828 692 8087",
    "sg:postcode":"28791",
    "sg:province":"NC",
    "wof:name":"China Garden 2",
    "wof:placetype":"venue"
},
  "geometry": {"coordinates":[-82.46825200000001,35.329186],"type":"Point"}
}