{
  "type": "Feature",
  "properties": {
    "iso:country":"US",
    "sg:address":"431 W Bay St",
    "sg:city":"Bladenboro",
    "sg:classifiers":[
        {
            "category":"Professional",
            "type":"Services"
        }
    ],
    "sg:phone":"+1 910 648 2032",
    "sg:postcode":"28398",
    "sg:province":"NC",
    "sg:tags":[
        "establishment"
    ],
    "wof:name":"Allen Bros/Bee Island",
    "wof:placetype":"venue"
},
  "geometry": {"coordinates":[-78.10098000000001,34.995584],"type":"Point"}
}