{
  "type": "Feature",
  "properties": {
    "addr:full":"2575 Peters Creek Pkwy Winston Salem NC 27127",
    "addr:housenumber":"2575",
    "addr:postcode":"27127",
    "addr:street":"Peters Creek Pkwy",
    "iso:country":"US",
    "sg:address":"2575 Peters Creek Pkwy",
    "sg:city":"Winston Salem",
    "sg:classifiers":[
        {
            "category":"Autos & Motor Vehicles",
            "subcategory":"Automobile Sales",
            "type":"Retail Goods"
        }
    ],
    "sg:phone":"+1 336 785 2222",
    "sg:postcode":"27127",
    "sg:province":"NC",
    "sg:tags":[
        "car",
        "dealer"
    ],
    "sg:website":"www.saturnofwinstonsalem.com",
    "wof:name":"Saturn Of Winston-Salem",
    "wof:placetype":"venue"
},
  "geometry": {"coordinates":[-80.258579,36.06184],"type":"Point"}
}