{
  "type": "Feature",
  "properties": {
    "addr:full":"115 W Broad St Elizabethtown NC 28337",
    "addr:housenumber":"115",
    "addr:postcode":"28337",
    "addr:street":"W Broad St",
    "iso:country":"US",
    "sg:address":"115 W Broad St",
    "sg:city":"Elizabethtown",
    "sg:classifiers":[
        {
            "category":"Building & Trades",
            "subcategory":"Construction",
            "type":"Services"
        }
    ],
    "sg:phone":"+1 910 862 5305",
    "sg:postcode":"28337",
    "sg:province":"NC",
    "sg:tags":[
        "millwright"
    ],
    "wof:name":"Knb Millwright Svc",
    "wof:placetype":"venue"
},
  "geometry": {"coordinates":[-78.607193,34.629231],"type":"Point"}
}