{
  "type": "Feature",
  "properties": {
    "iso:country":"US",
    "sg:address":"7419 Market St",
    "sg:city":"Wilmington",
    "sg:classifiers":[
        {
            "category":"Restaurant",
            "type":"Food & Drink"
        }
    ],
    "sg:phone":"+1 910 686 4014",
    "sg:postcode":"28411",
    "sg:province":"NC",
    "sg:tags":[
        "pizza"
    ],
    "sg:website":"www.papajohns.com",
    "wof:name":"Papa John's Pizza",
    "wof:placetype":"venue"
},
  "geometry": {"coordinates":[-77.813202,34.279099],"type":"Point"}
}