{
  "type": "Feature",
  "properties": {
    "iso:country":"US",
    "sg:address":"2940 Pine Run Rd",
    "sg:city":"Boone",
    "sg:classifiers":[
        {
            "category":"Organizations",
            "subcategory":"Religious Organization",
            "type":"Services"
        }
    ],
    "sg:phone":"+1   ",
    "sg:postcode":"28607",
    "sg:province":"NC",
    "wof:name":"Bethelview United Methodist",
    "wof:placetype":"venue"
},
  "geometry": {"coordinates":[-81.600273,36.250715],"type":"Point"}
}