{
  "type": "Feature",
  "properties": {
    "addr:full":"605 Toddville Rd Charlotte NC 28214",
    "addr:housenumber":"605",
    "addr:postcode":"28214",
    "addr:street":"Toddville Rd",
    "iso:country":"US",
    "sg:address":"605 Toddville Rd",
    "sg:city":"Charlotte",
    "sg:classifiers":[
        {
            "category":"Manufacturing",
            "subcategory":"Metals",
            "type":"Manufacturing & Wholesale Goods"
        },
        {
            "category":"Retail",
            "subcategory":"Repair Shop",
            "type":"Services"
        },
        {
            "category":"Retail",
            "subcategory":"Auto Repair",
            "type":"Services"
        }
    ],
    "sg:phone":"+1 704 392 7285",
    "sg:postcode":"28214",
    "sg:province":"NC",
    "sg:tags":[
        "machine",
        "automobile",
        "specialty"
    ],
    "sg:website":"http://www.derita.com",
    "wof:name":"Derita Precision Machine Co",
    "wof:placetype":"venue"
},
  "geometry": {"coordinates":[-80.91399199999999,35.275176],"type":"Point"}
}