{
  "type": "Feature",
  "properties": {
    "addr:full":"15 Carrier St Asheville NC 28806",
    "addr:housenumber":"15",
    "addr:postcode":"28806",
    "addr:street":"Carrier St",
    "iso:country":"US",
    "sg:address":"15 Carrier St",
    "sg:city":"Asheville",
    "sg:classifiers":[
        {
            "category":"Building & Trades",
            "subcategory":"Construction",
            "type":"Services"
        }
    ],
    "sg:phone":"+1 828 225 0784",
    "sg:postcode":"28806",
    "sg:province":"NC",
    "sg:tags":[
        "house"
    ],
    "wof:name":"Wright Builders Inc",
    "wof:placetype":"venue"
},
  "geometry": {"coordinates":[-82.60541499999999,35.575429],"type":"Point"}
}