{
  "type": "Feature",
  "properties": {
    "addr:full":"8425 State Rd 49 N Mt Pleasant NC 28124",
    "addr:housenumber":"8425;49",
    "addr:postcode":"28124",
    "addr:street":"State Rd;N",
    "iso:country":"US",
    "sg:address":"8425 State Rd 49 N",
    "sg:city":"Mt Pleasant",
    "sg:classifiers":[
        {
            "category":"Food & Beverages",
            "subcategory":"Groceries & Convenience Stores",
            "type":"Retail Goods"
        }
    ],
    "sg:phone":"+1 704 436 2977",
    "sg:postcode":"28124",
    "sg:province":"NC",
    "wof:name":"Circle K",
    "wof:placetype":"venue"
},
  "geometry": {"coordinates":[-80.44788800000001,35.366145],"type":"Point"}
}