{
  "type": "Feature",
  "properties": {
    "iso:country":"US",
    "sg:address":"3101 Woodland Ave",
    "sg:city":"New Bern",
    "sg:classifiers":[
        {
            "category":"Health Services",
            "subcategory":"Doctor",
            "type":"Services"
        }
    ],
    "sg:phone":"+1 252 633 4208",
    "sg:postcode":"28562",
    "sg:province":"NC",
    "sg:tags":[
        "clinic"
    ],
    "wof:name":"GE Medical Systems",
    "wof:placetype":"venue"
},
  "geometry": {"coordinates":[-77.083772,35.107596],"type":"Point"}
}