{
  "type": "Feature",
  "properties": {
    "addr:full":"2139 N Church St Burlington NC 27217",
    "addr:housenumber":"2139",
    "addr:postcode":"27217",
    "addr:street":"N Church St",
    "iso:country":"US",
    "sg:address":"2139 N Church St",
    "sg:city":"Burlington",
    "sg:classifiers":[
        {
            "category":"Food & Beverages",
            "subcategory":"Groceries & Convenience Stores",
            "type":"Retail Goods"
        }
    ],
    "sg:phone":"+1 336 570 2516",
    "sg:postcode":"27217",
    "sg:province":"NC",
    "sg:tags":[
        "grocer"
    ],
    "wof:name":"Lowes Foods",
    "wof:placetype":"venue"
},
  "geometry": {"coordinates":[-79.399919,36.093956],"type":"Point"}
}