{
  "type": "Feature",
  "properties": {
    "iso:country":"US",
    "sg:address":"1100 Navaho Dr",
    "sg:city":"Raleigh",
    "sg:classifiers":[
        {
            "category":"Wholesale",
            "subcategory":"Stationery",
            "type":"Manufacturing & Wholesale Goods"
        }
    ],
    "sg:phone":"+1 919 874 9500",
    "sg:postcode":"27609",
    "sg:province":"NC",
    "sg:tags":[
        "packaging",
        "material"
    ],
    "sg:website":"www.fabrene.com",
    "wof:name":"Pgi Nonwovens Division",
    "wof:placetype":"venue"
},
  "geometry": {"coordinates":[-78.62117499999999,35.827725],"type":"Point"}
}