{
  "type": "Feature",
  "properties": {
    "addr:full":"2710 Quailview Dr Chapel Hill NC 27516",
    "addr:housenumber":"2710",
    "addr:postcode":"27516",
    "addr:street":"Quailview Dr",
    "iso:country":"US",
    "sg:address":"2710 Quailview Dr",
    "sg:city":"Chapel Hill",
    "sg:classifiers":[
        {
            "category":"Shopping",
            "subcategory":"Clothing, Apparel, & Fashions",
            "type":"Retail Goods"
        }
    ],
    "sg:phone":"+1 919 929 7941",
    "sg:postcode":"27516",
    "sg:province":"NC",
    "wof:name":"Guy Sticker Inc",
    "wof:placetype":"venue"
},
  "geometry": {"coordinates":[-79.13603999999999,35.886627],"type":"Point"}
}