{
  "type": "Feature",
  "properties": {
    "iso:country":"US",
    "sg:address":"6312 Guess Rd",
    "sg:city":"Durham",
    "sg:classifiers":[
        {
            "category":"Building & Trades",
            "subcategory":"Construction",
            "type":"Services"
        }
    ],
    "sg:phone":"+1 919 477 9386",
    "sg:postcode":"27712",
    "sg:province":"NC",
    "sg:tags":[
        "house"
    ],
    "wof:name":"Skidmore Repair",
    "wof:placetype":"venue"
},
  "geometry": {"coordinates":[-78.937799,36.121583],"type":"Point"}
}