{
  "type": "Feature",
  "properties": {
    "addr:full":"215 Ikerd Dr SE Concord NC 28025",
    "addr:housenumber":"215",
    "addr:postcode":"28025",
    "addr:street":"Ikerd Dr Se",
    "iso:country":"US",
    "sg:address":"215 Ikerd Dr SE",
    "sg:city":"Concord",
    "sg:classifiers":[
        {
            "category":"Manufacturing",
            "subcategory":"Glass & Minerals",
            "type":"Manufacturing & Wholesale Goods"
        }
    ],
    "sg:phone":"+1 704 792 9474",
    "sg:postcode":"28025",
    "sg:province":"NC",
    "sg:tags":[
        "concrete",
        "product",
        "nonmetallic",
        "mfg"
    ],
    "wof:name":"Owens Corning",
    "wof:placetype":"venue"
},
  "geometry": {"coordinates":[-80.55525,35.391419],"type":"Point"}
}