{
  "type": "Feature",
  "properties": {
    "addr:full":"318 Cooley Rd Rocky Mount NC 27803",
    "addr:housenumber":"318",
    "addr:postcode":"27803",
    "addr:street":"Cooley Rd",
    "iso:country":"US",
    "sg:address":"318 Cooley Rd",
    "sg:city":"Rocky Mount",
    "sg:classifiers":[
        {
            "category":"Retail",
            "subcategory":"Auto Repair",
            "type":"Services"
        }
    ],
    "sg:phone":"+1 252 446 3849",
    "sg:postcode":"27803",
    "sg:province":"NC",
    "sg:tags":[
        "repairing",
        "automobile"
    ],
    "wof:name":"Mike Viverette Garage/Wrecker",
    "wof:placetype":"venue"
},
  "geometry": {"coordinates":[-77.82442399999999,35.902845],"type":"Point"}
}