{
  "type": "Feature",
  "properties": {
    "iso:country":"US",
    "sg:address":"7070 State Hwy 16 S",
    "sg:city":"Jefferson",
    "sg:classifiers":[
        {
            "category":"Organizations",
            "subcategory":"Religious Organization",
            "type":"Services"
        }
    ],
    "sg:phone":"+1 336 982 9497",
    "sg:postcode":"28640",
    "sg:province":"NC",
    "sg:tags":[
        "church"
    ],
    "wof:name":"Blue Ridge Worship Ctr",
    "wof:placetype":"venue"
},
  "geometry": {"coordinates":[-81.38253899999999,36.349257],"type":"Point"}
}