{
  "type": "Feature",
  "properties": {
    "addr:full":"4751 State Hwy 54 Graham NC 27253",
    "addr:housenumber":"4751",
    "addr:postcode":"27253",
    "addr:street":"State Hwy 54",
    "iso:country":"US",
    "sg:address":"4751 State Hwy 54",
    "sg:city":"Graham",
    "sg:classifiers":[
        {
            "category":"Retail",
            "subcategory":"Auto Repair",
            "type":"Services"
        }
    ],
    "sg:phone":"+1   ",
    "sg:postcode":"27253",
    "sg:province":"NC",
    "sg:tags":[
        "body"
    ],
    "wof:name":"Wheeleys Paint & Body",
    "wof:placetype":"venue"
},
  "geometry": {"coordinates":[-79.29416500000001,35.99524],"type":"Point"}
}