{
  "type": "Feature",
  "properties": {
    "iso:country":"US",
    "sg:address":"191 E Charity Rd",
    "sg:city":"Rose Hill",
    "sg:classifiers":[
        {
            "category":"Utilities",
            "subcategory":"Telephone",
            "type":"Services"
        }
    ],
    "sg:phone":"+1 910 381 1585",
    "sg:postcode":"28458",
    "sg:province":"NC",
    "wof:name":"G&Sjohnson/Moore Inc",
    "wof:placetype":"venue"
},
  "geometry": {"coordinates":[-77.939283,34.823108],"type":"Point"}
}