{
  "type": "Feature",
  "properties": {
    "iso:country":"US",
    "sg:address":"2201 S Sterling St",
    "sg:city":"Morganton",
    "sg:classifiers":[
        {
            "category":"Manufacturing",
            "subcategory":"Tools & Machinery",
            "type":"Manufacturing & Wholesale Goods"
        }
    ],
    "sg:phone":"+1 828 433 5050",
    "sg:postcode":"28655",
    "sg:province":"NC",
    "sg:tags":[
        "physician",
        "surgeon"
    ],
    "sg:website":"www.ahom.com",
    "wof:name":"American Home Patient Inc",
    "wof:placetype":"venue"
},
  "geometry": {"coordinates":[-81.65875800000001,35.724074],"type":"Point"}
}