{
  "type": "Feature",
  "properties": {
    "addr:full":"10825 Texland Blvd Charlotte NC 28273",
    "addr:housenumber":"10825",
    "addr:postcode":"28273",
    "addr:street":"Texland Blvd",
    "iso:country":"US",
    "sg:address":"10825 Texland Blvd",
    "sg:city":"Charlotte",
    "sg:classifiers":[
        {
            "category":"Food & Beverages",
            "subcategory":"Groceries & Convenience Stores",
            "type":"Retail Goods"
        },
        {
            "category":"Wholesale",
            "subcategory":"Groceries",
            "type":"Manufacturing & Wholesale Goods"
        }
    ],
    "sg:phone":"+1 704 504 1911",
    "sg:postcode":"28273",
    "sg:province":"NC",
    "sg:tags":[
        "frozen",
        "dairy",
        "product",
        "packaged"
    ],
    "sg:website":"www.southernfoods.com",
    "wof:name":"Southern Foods Inc",
    "wof:placetype":"venue"
},
  "geometry": {"coordinates":[-80.918817,35.117889],"type":"Point"}
}