{
  "type": "Feature",
  "properties": {
    "iso:country":"US",
    "sg:address":"4412 Central Ave",
    "sg:city":"Charlotte",
    "sg:classifiers":[
        {
            "category":"Utilities",
            "subcategory":"Mobile Phone",
            "type":"Services"
        }
    ],
    "sg:phone":"+1 704 535 2355",
    "sg:postcode":"28205",
    "sg:province":"NC",
    "sg:tags":[
        "telephone",
        "cellular"
    ],
    "wof:name":"Mundo Cellular II",
    "wof:placetype":"venue"
},
  "geometry": {"coordinates":[-80.77066600000001,35.213782],"type":"Point"}
}