{
  "type": "Feature",
  "properties": {
    "addr:full":"3124 New Hill Holleman Rd New Hill NC 27562",
    "addr:housenumber":"3124",
    "addr:postcode":"27562",
    "addr:street":"New Hill Holleman Rd New",
    "iso:country":"US",
    "sg:address":"3124 New Hill Holleman Rd",
    "sg:city":"New Hill",
    "sg:classifiers":[
        {
            "category":"Manufacturing",
            "subcategory":"Printing",
            "type":"Manufacturing & Wholesale Goods"
        }
    ],
    "sg:phone":"+1 919 362 7740",
    "sg:postcode":"27562",
    "sg:province":"NC",
    "sg:tags":[
        "publisher",
        "music"
    ],
    "sg:website":"www.urbaninspiration.org",
    "wof:name":"M 2",
    "wof:placetype":"venue"
},
  "geometry": {"coordinates":[-78.931127,35.670623],"type":"Point"}
}