{
  "type": "Feature",
  "properties": {
    "iso:country":"US",
    "sg:address":"408 Upton St",
    "sg:city":"Winston Salem",
    "sg:classifiers":[
        {
            "category":"Building & Trades",
            "subcategory":"Plumbing",
            "type":"Services"
        }
    ],
    "sg:phone":"+1 336 768 2703",
    "sg:postcode":"27103",
    "sg:province":"NC",
    "sg:tags":[
        "air",
        "heating",
        "conditioning",
        "contractor"
    ],
    "sg:website":"www.hhhoveyheatingandcooling.com",
    "wof:name":"H H Hovey Heating & Cooling",
    "wof:placetype":"venue"
},
  "geometry": {"coordinates":[-80.29957899999999,36.083394],"type":"Point"}
}