{
  "type": "Feature",
  "properties": {
    "iso:country":"US",
    "sg:address":"835 Loop Rd N",
    "sg:city":"Kannapolis",
    "sg:classifiers":[
        {
            "category":"Home & Garden",
            "subcategory":"Building Materials",
            "type":"Retail Goods"
        }
    ],
    "sg:phone":"+1 704 932 9106",
    "sg:postcode":"28081",
    "sg:province":"NC",
    "sg:tags":[
        "paint"
    ],
    "sg:website":"www.sherwinwilliams.com",
    "wof:name":"Sherwin-Williams Paints",
    "wof:placetype":"venue"
},
  "geometry": {"coordinates":[-80.631,35.501806],"type":"Point"}
}