{
  "type": "Feature",
  "properties": {
    "iso:country":"US",
    "sg:address":"6248 E Independence Blvd",
    "sg:city":"Charlotte",
    "sg:classifiers":[
        {
            "category":"Retail",
            "subcategory":"Auto Rental",
            "type":"Services"
        }
    ],
    "sg:phone":"+1   ",
    "sg:postcode":"28212",
    "sg:province":"NC",
    "sg:tags":[
        "passenger",
        "car"
    ],
    "wof:name":"Autosave of Charlotte",
    "wof:placetype":"venue"
},
  "geometry": {"coordinates":[-80.745819,35.171797],"type":"Point"}
}