{
  "type": "Feature",
  "properties": {
    "iso:country":"US",
    "sg:address":"147 S Fields Cir",
    "sg:city":"Chapel Hill",
    "sg:classifiers":[
        {
            "category":"Professional",
            "subcategory":"Management & Consulting",
            "type":"Services"
        }
    ],
    "sg:phone":"+1   ",
    "sg:postcode":"27516",
    "sg:province":"NC",
    "wof:name":"Leadership & Innovation Assoc",
    "wof:placetype":"venue"
},
  "geometry": {"coordinates":[-79.100273,35.950509],"type":"Point"}
}