{
  "type": "Feature",
  "properties": {
    "addr:full":"1141 Fourth Creek Landing Dr Statesville NC 28625",
    "addr:housenumber":"1141",
    "addr:postcode":"28625",
    "addr:street":"Fourth Creek Landing Dr",
    "iso:country":"US",
    "sg:address":"1141 Fourth Creek Landing Dr",
    "sg:city":"Statesville",
    "sg:classifiers":[
        {
            "category":"Professional",
            "type":"Services"
        }
    ],
    "sg:phone":"+1 704 871 9089",
    "sg:postcode":"28625",
    "sg:province":"NC",
    "wof:name":"Jdp Inc",
    "wof:placetype":"venue"
},
  "geometry": {"coordinates":[-80.873386,35.812997],"type":"Point"}
}