{
  "type": "Feature",
  "properties": {
    "addr:full":"116 Infield Ct Mooresville NC 28117",
    "addr:housenumber":"116",
    "addr:postcode":"28117",
    "addr:street":"Infield Ct",
    "iso:country":"US",
    "sg:address":"116 Infield Ct",
    "sg:city":"Mooresville",
    "sg:classifiers":[
        {
            "category":"Manufacturing",
            "subcategory":"Tools & Machinery",
            "type":"Manufacturing & Wholesale Goods"
        }
    ],
    "sg:phone":"+1 704 660 5296",
    "sg:postcode":"28117",
    "sg:province":"NC",
    "sg:tags":[
        "machine",
        "shop"
    ],
    "wof:name":"J B Engines",
    "wof:placetype":"venue"
},
  "geometry": {"coordinates":[-80.852761,35.599546],"type":"Point"}
}