{
  "type": "Feature",
  "properties": {
    "addr:full":"344 W John St Matthews NC 28105",
    "addr:housenumber":"344",
    "addr:postcode":"28105",
    "addr:street":"W John",
    "iso:country":"US",
    "sg:address":"344 W John St",
    "sg:city":"Matthews",
    "sg:classifiers":[
        {
            "category":"Travel",
            "subcategory":"Travel Agent",
            "type":"Entertainment"
        }
    ],
    "sg:phone":"+1 704 321 7000",
    "sg:postcode":"28105",
    "sg:province":"NC",
    "sg:tags":[
        "agency",
        "bureau"
    ],
    "wof:name":"Accent On Travel",
    "wof:placetype":"venue"
},
  "geometry": {"coordinates":[-80.72533300000001,35.117971],"type":"Point"}
}