{
  "type": "Feature",
  "properties": {
    "iso:country":"US",
    "sg:address":"106 S Maple St",
    "sg:city":"Graham",
    "sg:classifiers":[
        {
            "category":"Professional",
            "subcategory":"Lawyer & Legal Services",
            "type":"Services"
        }
    ],
    "sg:phone":"+1 336 436 0054",
    "sg:postcode":"27253",
    "sg:province":"NC",
    "sg:tags":[
        "attorney"
    ],
    "wof:name":"Keisha Bluford Attorney",
    "wof:placetype":"venue"
},
  "geometry": {"coordinates":[-79.40209,36.067977],"type":"Point"}
}