{
  "type": "Feature",
  "properties": {
    "addr:full":"101 N Main St China Grove NC 28023",
    "addr:housenumber":"101",
    "addr:postcode":"28023",
    "addr:street":"N Main St",
    "iso:country":"US",
    "sg:address":"101 N Main St",
    "sg:city":"China Grove",
    "sg:classifiers":[
        {
            "category":"Professional",
            "subcategory":"Management & Consulting",
            "type":"Services"
        }
    ],
    "sg:phone":"+1 704 855 2212",
    "sg:postcode":"28023",
    "sg:province":"NC",
    "sg:tags":[
        "consultant",
        "business"
    ],
    "wof:name":"Special Occasions Inc",
    "wof:placetype":"venue"
},
  "geometry": {"coordinates":[-80.57887599999999,35.570825],"type":"Point"}
}