{
  "type": "Feature",
  "properties": {
    "iso:country":"US",
    "sg:address":"745 Hewitt Rd",
    "sg:city":"Cleveland",
    "sg:classifiers":[
        {
            "category":"Manufacturing",
            "subcategory":"Tools & Machinery",
            "type":"Manufacturing & Wholesale Goods"
        }
    ],
    "sg:phone":"+1 704 278 0214",
    "sg:postcode":"27013",
    "sg:province":"NC",
    "sg:tags":[
        "industrial",
        "mfg"
    ],
    "wof:name":"Carolina Kiln Grinding Co",
    "wof:placetype":"venue"
},
  "geometry": {"coordinates":[-80.743914,35.747419],"type":"Point"}
}