{
  "type": "Feature",
  "properties": {
    "addr:full":"781 Old Mount Olive Hwy Dudley NC 28333",
    "addr:housenumber":"781",
    "addr:postcode":"28333",
    "addr:street":"Old Mount Olive Hwy",
    "iso:country":"US",
    "sg:address":"781 Old Mount Olive Hwy",
    "sg:city":"Dudley",
    "sg:classifiers":[
        {
            "category":"Social Services",
            "type":"Services"
        }
    ],
    "sg:phone":"+1   ",
    "sg:postcode":"28333",
    "sg:province":"NC",
    "wof:name":"Stancils Family Care",
    "wof:placetype":"venue"
},
  "geometry": {"coordinates":[-78.027529,35.321561],"type":"Point"}
}