{
  "type": "Feature",
  "properties": {
    "iso:country":"US",
    "sg:address":"3124 State Hwy 50",
    "sg:city":"Scranton",
    "sg:classifiers":[
        {
            "category":"Personal",
            "subcategory":"Beauty Salon",
            "type":"Services"
        }
    ],
    "sg:phone":"+1 843 389 4459",
    "sg:postcode":"29566",
    "sg:province":"SC",
    "wof:name":"Sandy's Beauty Salon",
    "wof:placetype":"venue"
},
  "geometry": {"coordinates":[-78.618601,33.896019],"type":"Point"}
}