{
  "type": "Feature",
  "properties": {
    "iso:country":"US",
    "sg:address":"100 Spartan Rd",
    "sg:city":"Wilmington",
    "sg:classifiers":[
        {
            "category":"Education",
            "subcategory":"Dance Studio",
            "type":"Public Place"
        }
    ],
    "sg:phone":"+1 910 397 2822",
    "sg:postcode":"28405",
    "sg:province":"NC",
    "sg:tags":[
        "instruction",
        "dancing"
    ],
    "wof:name":"Danzquest",
    "wof:placetype":"venue"
},
  "geometry": {"coordinates":[-77.83978500000001,34.253541],"type":"Point"}
}