{
  "type": "Feature",
  "properties": {
    "iso:country":"US",
    "sg:address":"1022 US Hwy 221 Bus",
    "sg:city":"Marion",
    "sg:classifiers":[
        {
            "category":"Sports & Exercise",
            "subcategory":"Gym",
            "type":"Entertainment"
        }
    ],
    "sg:phone":"+1 828 652 5122",
    "sg:postcode":"28752",
    "sg:province":"NC",
    "sg:tags":[
        "club",
        "health",
        "studio",
        "gymnasium"
    ],
    "wof:name":"Club Fitness",
    "wof:placetype":"venue"
},
  "geometry": {"coordinates":[-81.99638,35.675886],"type":"Point"}
}