{
  "type": "Feature",
  "properties": {
    "iso:country":"US",
    "sg:address":"109 Hinton Ave",
    "sg:city":"Wilmington",
    "sg:classifiers":[
        {
            "category":"Professional",
            "subcategory":"Business Services",
            "type":"Services"
        }
    ],
    "sg:phone":"+1   ",
    "sg:postcode":"28403",
    "sg:province":"NC",
    "wof:name":"Map Interiors",
    "wof:placetype":"venue"
},
  "geometry": {"coordinates":[-77.84905500000001,34.211765],"type":"Point"}
}