{
  "type": "Feature",
  "properties": {
    "addr:full":"1104 US Hwy 421 Clinton NC 28328",
    "addr:housenumber":"1104",
    "addr:postcode":"28328",
    "addr:street":"Us Hwy 421",
    "iso:country":"US",
    "sg:address":"1104 US Hwy 421",
    "sg:city":"Clinton",
    "sg:classifiers":[
        {
            "category":"Wholesale",
            "subcategory":"Apparel",
            "type":"Manufacturing & Wholesale Goods"
        }
    ],
    "sg:phone":"+1 910 592 6200",
    "sg:postcode":"28328",
    "sg:province":"NC",
    "sg:tags":[
        "sportswear"
    ],
    "wof:name":"Dodger Industry",
    "wof:placetype":"venue"
},
  "geometry": {"coordinates":[-78.313644,34.973974],"type":"Point"}
}