{
  "type": "Feature",
  "properties": {
    "iso:country":"US",
    "sg:address":"4693 Mountain View Rd",
    "sg:city":"Hays",
    "sg:classifiers":[
        {
            "category":"Building & Trades",
            "subcategory":"Construction",
            "type":"Services"
        }
    ],
    "sg:phone":"+1 336 696 2536",
    "sg:postcode":"28635",
    "sg:province":"NC",
    "sg:tags":[
        "house",
        "nonresidential"
    ],
    "wof:name":"Walker Construction",
    "wof:placetype":"venue"
},
  "geometry": {"coordinates":[-81.124672,36.243695],"type":"Point"}
}