{
  "type": "Feature",
  "properties": {
    "addr:full":"3301 N Main St Tarboro NC 27886",
    "addr:housenumber":"3301",
    "addr:postcode":"27886",
    "addr:street":"N Main St",
    "iso:country":"US",
    "sg:address":"3301 N Main St",
    "sg:city":"Tarboro",
    "sg:classifiers":[
        {
            "category":"Manufacturing",
            "subcategory":"Metals",
            "type":"Manufacturing & Wholesale Goods"
        },
        {
            "category":"Manufacturing",
            "subcategory":"Tools & Machinery",
            "type":"Manufacturing & Wholesale Goods"
        }
    ],
    "sg:phone":"+1 252 641 5900",
    "sg:postcode":"27886",
    "sg:province":"NC",
    "sg:tags":[
        "equipment",
        "metalwork",
        "sheet",
        "mfg"
    ],
    "wof:name":"Air Systems Components LP",
    "wof:placetype":"venue"
},
  "geometry": {"coordinates":[-77.568776,35.926784],"type":"Point"}
}