{
  "type": "Feature",
  "properties": {
    "iso:country":"US",
    "sg:address":"127 N Green St",
    "sg:city":"Statesville",
    "sg:classifiers":[
        {
            "category":"Professional",
            "subcategory":"Lawyer & Legal Services",
            "type":"Services"
        }
    ],
    "sg:phone":"+1 704 872 9966",
    "sg:postcode":"28677",
    "sg:province":"NC",
    "sg:tags":[
        "attorney"
    ],
    "wof:name":"Robert H Gourley Sr Attorney",
    "wof:placetype":"venue"
},
  "geometry": {"coordinates":[-80.88351,35.786165],"type":"Point"}
}