{
  "type": "Feature",
  "properties": {
    "addr:full":"7701 Raeford Rd Fayetteville NC 28304",
    "addr:housenumber":"7701",
    "addr:postcode":"28304",
    "addr:street":"Raeford Rd",
    "iso:country":"US",
    "sg:address":"7701 Raeford Rd",
    "sg:city":"Fayetteville",
    "sg:classifiers":[
        {
            "category":"Health Services",
            "subcategory":"Optometrist",
            "type":"Services"
        }
    ],
    "sg:phone":"+1 910 826 0100",
    "sg:postcode":"28304",
    "sg:province":"NC",
    "wof:name":"Risk Optometric Assoc PA",
    "wof:placetype":"venue"
},
  "geometry": {"coordinates":[-79.05673,35.030674],"type":"Point"}
}