{
  "type": "Feature",
  "properties": {
    "addr:full":"21614 Norman Shores Dr Cornelius NC 28031",
    "addr:housenumber":"21614",
    "addr:postcode":"28031",
    "addr:street":"Norman Shores Dr",
    "iso:country":"US",
    "sg:address":"21614 Norman Shores Dr",
    "sg:city":"Cornelius",
    "sg:classifiers":[
        {
            "category":"Professional",
            "type":"Services"
        }
    ],
    "sg:phone":"+1 704 655 8360",
    "sg:postcode":"28031",
    "sg:province":"NC",
    "sg:tags":[
        "establishment"
    ],
    "wof:name":"Auto Data Processing",
    "wof:placetype":"venue"
},
  "geometry": {"coordinates":[-80.880021,35.505889],"type":"Point"}
}