{
  "type": "Feature",
  "properties": {
    "iso:country":"US",
    "sg:address":"1206 N Berkeley Blvd",
    "sg:city":"Goldsboro",
    "sg:classifiers":[
        {
            "category":"Shopping",
            "subcategory":"Computers & Home Electronics",
            "type":"Retail Goods"
        }
    ],
    "sg:phone":"+1 919 778 1900",
    "sg:postcode":"27534",
    "sg:province":"NC",
    "wof:name":"Byte Back Computer",
    "wof:placetype":"venue"
},
  "geometry": {"coordinates":[-77.929952,35.382133],"type":"Point"}
}