{
  "type": "Feature",
  "properties": {
    "iso:country":"US",
    "sg:address":"4421 Stuart Andrew Blvd",
    "sg:city":"Charlotte",
    "sg:classifiers":[
        {
            "category":"Professional",
            "subcategory":"Employment Agencies",
            "type":"Services"
        }
    ],
    "sg:phone":"+1 704 945 0400",
    "sg:postcode":"28217",
    "sg:province":"NC",
    "sg:tags":[
        "contractor"
    ],
    "wof:name":"Creative Staffing Service",
    "wof:placetype":"venue"
},
  "geometry": {"coordinates":[-80.889476,35.187467],"type":"Point"}
}