{
  "type": "Feature",
  "properties": {
    "iso:country":"US",
    "sg:address":"15090 State Hwy 226",
    "sg:city":"Spruce Pine",
    "sg:classifiers":[
        {
            "category":"Shopping",
            "subcategory":"Jewelry",
            "type":"Retail Goods"
        }
    ],
    "sg:phone":"+1 828 765 7981",
    "sg:postcode":"28777",
    "sg:province":"NC",
    "wof:name":"Blue Ridge Rock & Gem Shop",
    "wof:placetype":"venue"
},
  "geometry": {"coordinates":[-82.050224,35.854413],"type":"Point"}
}