{
  "type": "Feature",
  "properties": {
    "iso:country":"US",
    "sg:address":"5690 Duchess Dr",
    "sg:city":"Fayetteville",
    "sg:classifiers":[
        {
            "category":"Building & Trades",
            "subcategory":"Electrical",
            "type":"Services"
        }
    ],
    "sg:phone":"+1 910 487 5000",
    "sg:postcode":"28304",
    "sg:province":"NC",
    "sg:tags":[
        "electric",
        "contractor"
    ],
    "wof:name":"T & N Electric Corp",
    "wof:placetype":"venue"
},
  "geometry": {"coordinates":[-78.96815700000001,35.007187],"type":"Point"}
}