{
  "type": "Feature",
  "properties": {
    "iso:country":"US",
    "sg:address":"3401 Mar Vista Cir",
    "sg:city":"Charlotte",
    "sg:classifiers":[
        {
            "category":"Building & Trades",
            "subcategory":"Cleaning & Sanitation",
            "type":"Services"
        }
    ],
    "sg:phone":"+1   ",
    "sg:postcode":"28209",
    "sg:province":"NC",
    "sg:tags":[
        "maintenance"
    ],
    "wof:name":"Caldwell Pool & Spa Inc",
    "wof:placetype":"venue"
},
  "geometry": {"coordinates":[-80.847478,35.180402],"type":"Point"}
}