{
  "type": "Feature",
  "properties": {
    "addr:full":"108 Dundee St Windsor NC 27983",
    "addr:housenumber":"108",
    "addr:postcode":"27983",
    "addr:street":"Dundee St",
    "iso:country":"US",
    "sg:address":"108 Dundee St",
    "sg:city":"Windsor",
    "sg:classifiers":[
        {
            "category":"Government",
            "subcategory":"Office",
            "type":"Public Place"
        }
    ],
    "sg:phone":"+1 252 794 5326",
    "sg:postcode":"27983",
    "sg:province":"NC",
    "sg:tags":[
        "federal"
    ],
    "wof:name":"US Fish & Wildlife Svc",
    "wof:placetype":"venue"
},
  "geometry": {"coordinates":[-76.94564200000001,35.997265],"type":"Point"}
}