{
  "type": "Feature",
  "properties": {
    "addr:full":"515 Sunpointe Dr Hope Mills NC 28348",
    "addr:housenumber":"515",
    "addr:postcode":"28348",
    "addr:street":"Sunpointe Dr",
    "iso:country":"US",
    "sg:address":"515 Sunpointe Dr",
    "sg:city":"Hope Mills",
    "sg:classifiers":[
        {
            "category":"Social Services",
            "subcategory":"Child Care",
            "type":"Services"
        }
    ],
    "sg:phone":"+1 910 484 7200",
    "sg:postcode":"28348",
    "sg:province":"NC",
    "wof:name":"Parents With Purpose Child Cr",
    "wof:placetype":"venue"
},
  "geometry": {"coordinates":[-78.91980599999999,34.970829],"type":"Point"}
}