{
  "type": "Feature",
  "properties": {
    "addr:full":"2801 Alamance Church Rd Greensboro NC 27406",
    "addr:housenumber":"2801",
    "addr:postcode":"27406",
    "addr:street":"Alamance Church Rd",
    "iso:country":"US",
    "sg:address":"2801 Alamance Church Rd",
    "sg:city":"Greensboro",
    "sg:classifiers":[
        {
            "category":"Real Estate",
            "subcategory":"Real Estate Agent",
            "type":"Services"
        }
    ],
    "sg:phone":"+1 336 697 7489",
    "sg:postcode":"27406",
    "sg:province":"NC",
    "wof:name":"June Blackard Realty Inc",
    "wof:placetype":"venue"
},
  "geometry": {"coordinates":[-79.66377199999999,35.993263],"type":"Point"}
}