{
  "type": "Feature",
  "properties": {
    "iso:country":"US",
    "sg:address":"4102 Oleander Dr",
    "sg:city":"Wilmington",
    "sg:classifiers":[
        {
            "category":"Shopping",
            "subcategory":"Gifts & Souvenirs",
            "type":"Retail Goods"
        }
    ],
    "sg:phone":"+1 910 798 5701",
    "sg:postcode":"28403",
    "sg:province":"NC",
    "sg:tags":[
        "basket",
        "parcel"
    ],
    "wof:name":"Just A Basket Case",
    "wof:placetype":"venue"
},
  "geometry": {"coordinates":[-77.89500099999999,34.211608],"type":"Point"}
}