{
  "type": "Feature",
  "properties": {
    "iso:country":"US",
    "sg:address":"916 NE Maynard Rd",
    "sg:city":"Cary",
    "sg:classifiers":[
        {
            "category":"Health Services",
            "subcategory":"Chiropractor",
            "type":"Services"
        }
    ],
    "sg:phone":"+1 919 460 1515",
    "sg:postcode":"27513",
    "sg:province":"NC",
    "wof:name":"Staker Todd DC Chiroprctr",
    "wof:placetype":"venue"
},
  "geometry": {"coordinates":[-78.767799,35.8013],"type":"Point"}
}