{
  "type": "Feature",
  "properties": {
    "addr:full":"1427 Emerywood Dr Charlotte NC 28210",
    "addr:housenumber":"1427",
    "addr:postcode":"28210",
    "addr:street":"Emerywood Dr",
    "iso:country":"US",
    "sg:address":"1427 Emerywood Dr",
    "sg:city":"Charlotte",
    "sg:classifiers":[
        {
            "category":"Insurance",
            "subcategory":"Hazard Insurance",
            "type":"Services"
        }
    ],
    "sg:phone":"+1 704 553 2327",
    "sg:postcode":"28210",
    "sg:province":"NC",
    "wof:name":"State Farm Insurance Companies",
    "wof:placetype":"venue"
},
  "geometry": {"coordinates":[-80.87427700000001,35.156046],"type":"Point"}
}