{
  "type": "Feature",
  "properties": {
    "addr:full":"4747 Old Shallotte Rd NW Shallotte NC 28470",
    "addr:housenumber":"4747",
    "addr:postcode":"28470",
    "addr:street":"Old Shallotte Rd Nw",
    "iso:country":"US",
    "sg:address":"4747 Old Shallotte Rd NW",
    "sg:city":"Shallotte",
    "sg:classifiers":[
        {
            "category":"Freight",
            "type":"Transportation"
        }
    ],
    "sg:phone":"+1 910 754 8888",
    "sg:postcode":"28470",
    "sg:province":"NC",
    "sg:tags":[
        "local",
        "storage",
        "trucking"
    ],
    "wof:name":"Moving Systems",
    "wof:placetype":"venue"
},
  "geometry": {"coordinates":[-78.421622,33.960989],"type":"Point"}
}