{
  "type": "Feature",
  "properties": {
    "iso:country":"US",
    "sg:address":"20 Candor Dr",
    "sg:city":"Fletcher",
    "sg:classifiers":[
        {
            "category":"Education",
            "subcategory":"School",
            "type":"Public Place"
        }
    ],
    "sg:phone":"+1   ",
    "sg:postcode":"28732",
    "sg:province":"NC",
    "wof:name":"Southeastern School",
    "wof:placetype":"venue"
},
  "geometry": {"coordinates":[-82.447875,35.431739],"type":"Point"}
}