{
  "type": "Feature",
  "properties": {
    "addr:full":"109 Grant Ct New Bern NC 28562",
    "addr:housenumber":"109",
    "addr:postcode":"28562",
    "addr:street":"Grant Ct",
    "iso:country":"US",
    "sg:address":"109 Grant Ct",
    "sg:city":"New Bern",
    "sg:classifiers":[
        {
            "category":"Professional",
            "type":"Services"
        }
    ],
    "sg:phone":"+1 252 637 2645",
    "sg:postcode":"28562",
    "sg:province":"NC",
    "wof:name":"Wright Way Int",
    "wof:placetype":"venue"
},
  "geometry": {"coordinates":[-77.04783399999999,35.08422],"type":"Point"}
}