{
  "type": "Feature",
  "properties": {
    "addr:full":"7810 Ballantyne Commons Pkwy Charlotte NC 28277",
    "addr:housenumber":"7810",
    "addr:postcode":"28277",
    "addr:street":"Ballantyne Commons Pkwy",
    "iso:country":"US",
    "sg:address":"7810 Ballantyne Commons Pkwy",
    "sg:city":"Charlotte",
    "sg:classifiers":[
        {
            "category":"Wholesale",
            "subcategory":"Machinery & Supplies",
            "type":"Manufacturing & Wholesale Goods"
        }
    ],
    "sg:phone":"+1 704 602 3005",
    "sg:postcode":"28277",
    "sg:province":"NC",
    "sg:tags":[
        "sell",
        "equipment",
        "buy",
        "printing",
        "used"
    ],
    "wof:name":"Centsible Prtg McHy Intl LLC",
    "wof:placetype":"venue"
},
  "geometry": {"coordinates":[-80.811503,35.058393],"type":"Point"}
}