{
  "type": "Feature",
  "properties": {
    "addr:full":"4122 Bennett Memorial Rd Durham NC 27705",
    "addr:housenumber":"4122",
    "addr:postcode":"27705",
    "addr:street":"Bennett Memorial Rd",
    "iso:country":"US",
    "sg:address":"4122 Bennett Memorial Rd",
    "sg:city":"Durham",
    "sg:classifiers":[
        {
            "category":"Building & Trades",
            "subcategory":"Construction",
            "type":"Services"
        }
    ],
    "sg:phone":"+1 919 383 0888",
    "sg:postcode":"27705",
    "sg:province":"NC",
    "sg:tags":[
        "home",
        "improvement"
    ],
    "wof:name":"Prince & Sons Home Repairs",
    "wof:placetype":"venue"
},
  "geometry": {"coordinates":[-78.968327,36.030182],"type":"Point"}
}