{
  "type": "Feature",
  "properties": {
    "iso:country":"US",
    "sg:address":"701 Green Sea Rd",
    "sg:city":"Tabor City",
    "sg:classifiers":[
        {
            "category":"Manufacturing",
            "subcategory":"Metals",
            "type":"Manufacturing & Wholesale Goods"
        }
    ],
    "sg:phone":"+1 910 653 3810",
    "sg:postcode":"28463",
    "sg:province":"NC",
    "sg:tags":[
        "plumbing",
        "fixture",
        "supply"
    ],
    "wof:name":"Bell Appliance & Supply Co",
    "wof:placetype":"venue"
},
  "geometry": {"coordinates":[-78.881721,34.141467],"type":"Point"}
}