{
  "type": "Feature",
  "properties": {
    "addr:full":"1212 US Hwy 158 Business W Norlina NC 27563",
    "addr:housenumber":"1212",
    "addr:postcode":"27563",
    "addr:street":"Us Hwy 158 Business W Norlina",
    "iso:country":"US",
    "sg:address":"1212 US Hwy 158 Business W",
    "sg:city":"Norlina",
    "sg:classifiers":[
        {
            "category":"Shopping",
            "subcategory":"Computers & Home Electronics",
            "type":"Retail Goods"
        }
    ],
    "sg:phone":"+1 252 456 1000",
    "sg:postcode":"27563",
    "sg:province":"NC",
    "sg:tags":[
        "equipment",
        "electronic",
        "supply"
    ],
    "wof:name":"Radio Shack",
    "wof:placetype":"venue"
},
  "geometry": {"coordinates":[-78.185463,36.435363],"type":"Point"}
}