{
  "type": "Feature",
  "properties": {
    "addr:full":"115 Flora Mc Donald Ln Cary NC 27511",
    "addr:housenumber":"115",
    "addr:postcode":"27511",
    "addr:street":"Flora Mc Donald Ln",
    "iso:country":"US",
    "sg:address":"115 Flora Mc Donald Ln",
    "sg:city":"Cary",
    "sg:classifiers":[
        {
            "category":"Shopping",
            "subcategory":"Optical Goods",
            "type":"Retail Goods"
        }
    ],
    "sg:phone":"+1 919 481 0410",
    "sg:postcode":"27511",
    "sg:province":"NC",
    "wof:name":"Comp Opt For Prog Eldercare",
    "wof:placetype":"venue"
},
  "geometry": {"coordinates":[-78.791372,35.761118],"type":"Point"}
}