{
  "type": "Feature",
  "properties": {
    "iso:country":"US",
    "sg:address":"307 W Main St",
    "sg:city":"Clinton",
    "sg:classifiers":[
        {
            "category":"Personal",
            "subcategory":"Barber",
            "type":"Services"
        }
    ],
    "sg:phone":"+1 910 592 7911",
    "sg:postcode":"28328",
    "sg:province":"NC",
    "sg:tags":[
        "shop",
        "equipment",
        "establishment"
    ],
    "wof:name":"Beauty and Barber Supplies",
    "wof:placetype":"venue"
},
  "geometry": {"coordinates":[-78.32628099999999,34.995582],"type":"Point"}
}