{
  "type": "Feature",
  "properties": {
    "addr:full":"2818 Raeford Rd Fayetteville NC 28303",
    "addr:housenumber":"2818",
    "addr:postcode":"28303",
    "addr:street":"Raeford Rd",
    "iso:country":"US",
    "sg:address":"2818 Raeford Rd",
    "sg:city":"Fayetteville",
    "sg:classifiers":[
        {
            "category":"Banks & Credit Unions",
            "subcategory":"Bank",
            "type":"Services"
        }
    ],
    "sg:phone":"+1 910 484 3975",
    "sg:postcode":"28303",
    "sg:province":"NC",
    "wof:name":"New Century Bank",
    "wof:placetype":"venue"
},
  "geometry": {"coordinates":[-78.927218,35.045201],"type":"Point"}
}