{
  "type": "Feature",
  "properties": {
    "addr:full":"1146 Gum Branch Rd Jacksonville NC 28540",
    "addr:housenumber":"1146",
    "addr:postcode":"28540",
    "addr:street":"Gum Branch Rd",
    "iso:country":"US",
    "sg:address":"1146 Gum Branch Rd",
    "sg:city":"Jacksonville",
    "sg:classifiers":[
        {
            "category":"Food & Beverages",
            "subcategory":"Groceries & Convenience Stores",
            "type":"Retail Goods"
        }
    ],
    "sg:phone":"+1 910 455 8566",
    "sg:postcode":"28540",
    "sg:province":"NC",
    "sg:tags":[
        "grocer"
    ],
    "wof:name":"Food Lion",
    "wof:placetype":"venue"
},
  "geometry": {"coordinates":[-77.414913,34.77814],"type":"Point"}
}