{
  "type": "Feature",
  "properties": {
    "iso:country":"US",
    "sg:address":"590 Lansdowne Pl",
    "sg:city":"Winston Salem",
    "sg:classifiers":[
        {
            "category":"Manufacturing",
            "subcategory":"Metals",
            "type":"Manufacturing & Wholesale Goods"
        }
    ],
    "sg:phone":"+1 336 769 0902",
    "sg:postcode":"27107",
    "sg:province":"NC",
    "sg:tags":[
        "tool",
        "mfg"
    ],
    "wof:name":"Snap-On Tools",
    "wof:placetype":"venue"
},
  "geometry": {"coordinates":[-80.147496,35.982894],"type":"Point"}
}