{
  "type": "Feature",
  "properties": {
    "iso:country":"US",
    "sg:address":"709 E Main St",
    "sg:city":"Jefferson",
    "sg:classifiers":[
        {
            "category":"Banks & Credit Unions",
            "subcategory":"Bank",
            "type":"Services"
        }
    ],
    "sg:phone":"+1 336 246 4555",
    "sg:postcode":"28640",
    "sg:province":"NC",
    "wof:name":"Yadkin Valley Bank & Trust Co",
    "wof:placetype":"venue"
},
  "geometry": {"coordinates":[-81.46037699999999,36.421006],"type":"Point"}
}