{
  "type": "Feature",
  "properties": {
    "iso:country":"US",
    "sg:address":"2437 Dutch Rd",
    "sg:city":"Mt Pleasant",
    "sg:classifiers":[
        {
            "category":"Wholesale",
            "subcategory":"Hardware",
            "type":"Manufacturing & Wholesale Goods"
        },
        {
            "category":"Home & Garden",
            "subcategory":"Household Appliances",
            "type":"Retail Goods"
        }
    ],
    "sg:phone":"+1 704 436 9084",
    "sg:postcode":"28124",
    "sg:province":"NC",
    "sg:tags":[
        "sell",
        "electric",
        "cleaners",
        "infra",
        "glass",
        "heat",
        "vacuum",
        "red",
        "panel"
    ],
    "wof:name":"Carolina Sun Ray",
    "wof:placetype":"venue"
},
  "geometry": {"coordinates":[-80.350696,35.437375],"type":"Point"}
}