{
  "type": "Feature",
  "properties": {
    "addr:full":"600 S Tryon St Charlotte NC 28202",
    "addr:housenumber":"600",
    "addr:postcode":"28202",
    "addr:street":"S Tryon St",
    "iso:country":"US",
    "sg:address":"600 S Tryon St",
    "sg:city":"Charlotte",
    "sg:classifiers":[
        {
            "category":"Professional",
            "subcategory":"Advertising",
            "type":"Services"
        }
    ],
    "sg:phone":"+1 704 358 5968",
    "sg:postcode":"28202",
    "sg:province":"NC",
    "sg:tags":[
        "mail"
    ],
    "wof:name":"KPC Delivery/Target Market",
    "wof:placetype":"venue"
},
  "geometry": {"coordinates":[-80.84914499999999,35.222994],"type":"Point"}
}