{
  "type": "Feature",
  "properties": {
    "addr:full":"6809 Phillips Place Ct Charlotte NC 28210",
    "addr:housenumber":"6809",
    "addr:postcode":"28210",
    "addr:street":"Phillips Place Ct",
    "iso:country":"US",
    "sg:address":"6809 Phillips Place Ct",
    "sg:city":"Charlotte",
    "sg:classifiers":[
        {
            "category":"Shopping",
            "subcategory":"Jewelry",
            "type":"Retail Goods"
        }
    ],
    "sg:phone":"+1 704 556 7747",
    "sg:postcode":"28210",
    "sg:province":"NC",
    "sg:tags":[
        "item",
        "fine",
        "gift",
        "jeweler"
    ],
    "wof:name":"Lions Jewelers",
    "wof:placetype":"venue"
},
  "geometry": {"coordinates":[-80.825926,35.146084],"type":"Point"}
}