{
  "type": "Feature",
  "properties": {
    "iso:country":"US",
    "sg:address":"3400 Wilkinson Blvd",
    "sg:city":"Charlotte",
    "sg:classifiers":[
        {
            "category":"Shopping",
            "subcategory":"Discount & Variety Stores",
            "type":"Retail Goods"
        },
        {
            "category":"Shopping",
            "subcategory":"Department Store",
            "type":"Retail Goods"
        }
    ],
    "sg:phone":"+1 704 392 3291",
    "sg:postcode":"28208",
    "sg:province":"NC",
    "wof:name":"Family Dollar Stores",
    "wof:placetype":"venue"
},
  "geometry": {"coordinates":[-80.89788299999999,35.224495],"type":"Point"}
}