{
  "type": "Feature",
  "properties": {
    "iso:country":"US",
    "sg:address":"975 Walnut St",
    "sg:city":"Cary",
    "sg:classifiers":[
        {
            "category":"Social Services",
            "type":"Services"
        }
    ],
    "sg:phone":"+1 919 460 0567",
    "sg:postcode":"27511",
    "sg:province":"NC",
    "wof:name":"Wake Intrfith Vlntr Caregivers",
    "wof:placetype":"venue"
},
  "geometry": {"coordinates":[-78.76414200000001,35.772429],"type":"Point"}
}