{
  "type": "Feature",
  "properties": {
    "iso:country":"US",
    "sg:address":"4520 Potters Rd",
    "sg:city":"Matthews",
    "sg:classifiers":[
        {
            "category":"Restaurant",
            "type":"Food & Drink"
        }
    ],
    "sg:menulink":"http://www.allmenus.com/nc/vance/61104-new-york-pizza-express/menu/",
    "sg:phone":"+1 704 821 2020",
    "sg:postcode":"28104",
    "sg:province":"NC",
    "sg:tags":[
        "american",
        "pizza"
    ],
    "wof:name":"New York Pizza Express",
    "wof:placetype":"venue"
},
  "geometry": {"coordinates":[-80.697098,35.083961],"type":"Point"}
}