{
  "type": "Feature",
  "properties": {
    "iso:country":"US",
    "sg:address":"112 Wind Chime Ct",
    "sg:city":"Raleigh",
    "sg:classifiers":[
        {
            "category":"Communications",
            "subcategory":"Film & Video Production",
            "type":"Services"
        }
    ],
    "sg:phone":"+1   ",
    "sg:postcode":"27615",
    "sg:province":"NC",
    "sg:tags":[
        "videotape",
        "corporate"
    ],
    "wof:name":"Murphy and Associates Inc",
    "wof:placetype":"venue"
},
  "geometry": {"coordinates":[-78.642225,35.875268],"type":"Point"}
}