{
  "type": "Feature",
  "properties": {
    "iso:country":"US",
    "sg:address":"201 Zeb Ln",
    "sg:city":"Benson",
    "sg:classifiers":[
        {
            "category":"Freight",
            "type":"Transportation"
        }
    ],
    "sg:phone":"+1 919 219 7912",
    "sg:postcode":"27504",
    "sg:province":"NC",
    "sg:tags":[
        "operator",
        "local",
        "trucking"
    ],
    "wof:name":"Janpat Trucking",
    "wof:placetype":"venue"
},
  "geometry": {"coordinates":[-78.553544,35.44254],"type":"Point"}
}