{
  "type": "Feature",
  "properties": {
    "addr:full":"417 Blowing Rock Rd Boone NC 28607",
    "addr:housenumber":"417",
    "addr:postcode":"28607",
    "addr:street":"Blowing Rock Rd",
    "iso:country":"US",
    "sg:address":"417 Blowing Rock Rd",
    "sg:city":"Boone",
    "sg:classifiers":[
        {
            "category":"Restaurant",
            "type":"Food & Drink"
        }
    ],
    "sg:menulink":"http://www.allmenus.com/nc/boone/137159-subway/menu/",
    "sg:phone":"+1 828 264 4438",
    "sg:postcode":"28607",
    "sg:province":"NC",
    "sg:tags":[
        "american",
        "sandwich"
    ],
    "wof:name":"Subway",
    "wof:placetype":"venue"
},
  "geometry": {"coordinates":[-81.673604,36.209266],"type":"Point"}
}