{
  "type": "Feature",
  "properties": {
    "addr:full":"2419 Wright Ave Greensboro NC 27403",
    "addr:housenumber":"2419",
    "addr:postcode":"27403",
    "addr:street":"Wright Ave",
    "iso:country":"US",
    "sg:address":"2419 Wright Ave",
    "sg:city":"Greensboro",
    "sg:classifiers":[
        {
            "category":"Education",
            "subcategory":"Special Training",
            "type":"Public Place"
        }
    ],
    "sg:phone":"+1   ",
    "sg:postcode":"27403",
    "sg:province":"NC",
    "wof:name":"Craigs Voice Parlour",
    "wof:placetype":"venue"
},
  "geometry": {"coordinates":[-79.83471299999999,36.069805],"type":"Point"}
}