{
  "type": "Feature",
  "properties": {
    "addr:full":"324 Cutler St Raleigh NC 27603",
    "addr:housenumber":"324",
    "addr:postcode":"27603",
    "addr:street":"Cutler St",
    "iso:country":"US",
    "sg:address":"324 Cutler St",
    "sg:city":"Raleigh",
    "sg:classifiers":[
        {
            "category":"Professional",
            "subcategory":"Business Services",
            "type":"Services"
        }
    ],
    "sg:phone":"+1   ",
    "sg:postcode":"27603",
    "sg:province":"NC",
    "wof:name":"Harrington Hse Intr Dsign Svcs",
    "wof:placetype":"venue"
},
  "geometry": {"coordinates":[-78.65214,35.776088],"type":"Point"}
}