{
  "type": "Feature",
  "properties": {
    "iso:country":"US",
    "sg:address":"54 Frost Pl",
    "sg:city":"Waynesville",
    "sg:classifiers":[
        {
            "category":"Farming",
            "subcategory":"Farm",
            "type":"Manufacturing & Wholesale Goods"
        }
    ],
    "sg:phone":"+1 828 926 2951",
    "sg:postcode":"28786",
    "sg:province":"NC",
    "sg:tags":[
        "crop",
        "general"
    ],
    "wof:name":"Dennis Forsythe",
    "wof:placetype":"venue"
},
  "geometry": {"coordinates":[-83.070104,35.445129],"type":"Point"}
}