{
  "type": "Feature",
  "properties": {
    "addr:full":"808 S 2nd St Albemarle NC 28001",
    "addr:housenumber":"808",
    "addr:postcode":"28001",
    "addr:street":"S 2Nd St",
    "iso:country":"US",
    "sg:address":"808 S 2nd St",
    "sg:city":"Albemarle",
    "sg:classifiers":[
        {
            "category":"Retail",
            "subcategory":"Auto Repair",
            "type":"Services"
        }
    ],
    "sg:phone":"+1 704 982 5004",
    "sg:postcode":"28001",
    "sg:province":"NC",
    "sg:tags":[
        "recapping",
        "shop",
        "tire",
        "automotive"
    ],
    "wof:name":"Southside Tire and Recapping",
    "wof:placetype":"venue"
},
  "geometry": {"coordinates":[-80.197817,35.343584],"type":"Point"}
}