{
  "type": "Feature",
  "properties": {
    "iso:country":"US",
    "sg:address":"11211 Lawyers Rd",
    "sg:city":"Charlotte",
    "sg:classifiers":[
        {
            "category":"Food & Beverages",
            "subcategory":"Bakery",
            "type":"Retail Goods"
        }
    ],
    "sg:phone":"+1 704 545 4537",
    "sg:postcode":"28227",
    "sg:province":"NC",
    "wof:name":"Scrumdillyochus Confectionery",
    "wof:placetype":"venue"
},
  "geometry": {"coordinates":[-80.659823,35.17588],"type":"Point"}
}