{
  "type": "Feature",
  "properties": {
    "addr:full":"17830 Statesville Rd Cornelius NC 28031",
    "addr:housenumber":"17830",
    "addr:postcode":"28031",
    "addr:street":"Statesville Rd",
    "iso:country":"US",
    "sg:address":"17830 Statesville Rd",
    "sg:city":"Cornelius",
    "sg:classifiers":[
        {
            "category":"Building & Trades",
            "subcategory":"Construction",
            "type":"Services"
        }
    ],
    "sg:phone":"+1 704 987 3055",
    "sg:postcode":"28031",
    "sg:province":"NC",
    "sg:tags":[
        "home",
        "builder"
    ],
    "wof:name":"Vintage Homes Group",
    "wof:placetype":"venue"
},
  "geometry": {"coordinates":[-80.868382,35.457744],"type":"Point"}
}