{
  "type": "Feature",
  "properties": {
    "addr:full":"3900 Sardis Church Rd Monroe NC 28110",
    "addr:housenumber":"3900",
    "addr:postcode":"28110",
    "addr:street":"Sardis Church Rd",
    "iso:country":"US",
    "sg:address":"3900 Sardis Church Rd",
    "sg:city":"Monroe",
    "sg:classifiers":[
        {
            "category":"Building & Trades",
            "subcategory":"Plumbing",
            "type":"Services"
        }
    ],
    "sg:phone":"+1 704 321 3555",
    "sg:postcode":"28110",
    "sg:province":"NC",
    "sg:tags":[
        "plumbing",
        "contractor"
    ],
    "wof:name":"C & C Plumbing Inc",
    "wof:placetype":"venue"
},
  "geometry": {"coordinates":[-80.63261799999999,35.064215],"type":"Point"}
}