{
  "type": "Feature",
  "properties": {
    "addr:full":"6052 Bayfield Pkwy Concord NC 28027",
    "addr:housenumber":"6052",
    "addr:postcode":"28027",
    "addr:street":"Bayfield Pkwy",
    "iso:country":"US",
    "sg:address":"6052 Bayfield Pkwy",
    "sg:city":"Concord",
    "sg:classifiers":[
        {
            "category":"Sports & Exercise",
            "subcategory":"Gym",
            "type":"Entertainment"
        },
        {
            "category":"Building & Trades",
            "subcategory":"Construction",
            "type":"Services"
        }
    ],
    "sg:phone":"+1 704 784 0678",
    "sg:postcode":"28027",
    "sg:province":"NC",
    "sg:tags":[
        "supply",
        "gymnasium",
        "equipment",
        "program",
        "fitness",
        "gymnasiums-equipment",
        "physical"
    ],
    "sg:website":"http://www.snapfitness.com/concordnc",
    "wof:name":"Snap Fitness - Fitness Club",
    "wof:placetype":"venue"
},
  "geometry": {"coordinates":[-80.6771,35.42187],"type":"Point"}
}