{
  "type": "Feature",
  "properties": {
    "iso:country":"US",
    "sg:address":"3 Lima Ct",
    "sg:city":"Pinehurst",
    "sg:classifiers":[
        {
            "category":"Wholesale",
            "subcategory":"Durable Goods & Equipment",
            "type":"Manufacturing & Wholesale Goods"
        }
    ],
    "sg:phone":"+1 910 235 0363",
    "sg:postcode":"28374",
    "sg:province":"NC",
    "sg:tags":[
        "fire",
        "extinguisher"
    ],
    "wof:name":"Resort Fire & Safety Equipment",
    "wof:placetype":"venue"
},
  "geometry": {"coordinates":[-79.457033,35.212208],"type":"Point"}
}