{
  "type": "Feature",
  "properties": {
    "iso:country":"US",
    "sg:address":"314 E Millbrook Rd",
    "sg:city":"Raleigh",
    "sg:classifiers":[
        {
            "category":"Banks & Credit Unions",
            "subcategory":"Bank",
            "type":"Services"
        }
    ],
    "sg:phone":"+1 919 848 8991",
    "sg:postcode":"27609",
    "sg:province":"NC",
    "sg:tags":[
        "mortgage"
    ],
    "wof:name":"S A Taft",
    "wof:placetype":"venue"
},
  "geometry": {"coordinates":[-78.636461,35.854039],"type":"Point"}
}