{
  "type": "Feature",
  "properties": {
    "addr:full":"415 Deaverview Rd Asheville NC 28806",
    "addr:housenumber":"415",
    "addr:postcode":"28806",
    "addr:street":"Deaverview Rd",
    "iso:country":"US",
    "sg:address":"415 Deaverview Rd",
    "sg:city":"Asheville",
    "sg:classifiers":[
        {
            "category":"Autos & Motor Vehicles",
            "subcategory":"Fuel & Gas Station",
            "type":"Retail Goods"
        }
    ],
    "sg:phone":"+1 828 255 7717",
    "sg:postcode":"28806",
    "sg:province":"NC",
    "wof:name":"Johnson's Service Station",
    "wof:placetype":"venue"
},
  "geometry": {"coordinates":[-82.62497399999999,35.582506],"type":"Point"}
}