{
  "type": "Feature",
  "properties": {
    "iso:country":"US",
    "sg:address":"2080 US Hwy 74 Bus",
    "sg:city":"Ellenboro",
    "sg:classifiers":[
        {
            "category":"Retail",
            "subcategory":"Auto Repair",
            "type":"Services"
        }
    ],
    "sg:phone":"+1   ",
    "sg:postcode":"28040",
    "sg:province":"NC",
    "sg:tags":[
        "general"
    ],
    "wof:name":"Blackwoods Garage",
    "wof:placetype":"venue"
},
  "geometry": {"coordinates":[-81.775566,35.336893],"type":"Point"}
}