{
  "type": "Feature",
  "properties": {
    "addr:full":"2100 N Fork Rd Zionville NC 28698",
    "addr:housenumber":"2100",
    "addr:postcode":"28698",
    "addr:street":"N Fork Rd",
    "iso:country":"US",
    "sg:address":"2100 N Fork Rd",
    "sg:city":"Zionville",
    "sg:classifiers":[
        {
            "category":"Farming",
            "subcategory":"Farm",
            "type":"Manufacturing & Wholesale Goods"
        }
    ],
    "sg:phone":"+1 828 297 3000",
    "sg:postcode":"28698",
    "sg:province":"NC",
    "wof:name":"Seasons Farm Inc",
    "wof:placetype":"venue"
},
  "geometry": {"coordinates":[-81.781621,36.336037],"type":"Point"}
}