{
  "type": "Feature",
  "properties": {
    "iso:country":"US",
    "sg:address":"1241 Cobb Corners Dr",
    "sg:city":"Rocky Mount",
    "sg:classifiers":[
        {
            "category":"Personal",
            "subcategory":"Beauty Salon",
            "type":"Services"
        }
    ],
    "sg:phone":"+1 252 937 5000",
    "sg:postcode":"27804",
    "sg:province":"NC",
    "sg:tags":[
        "shop"
    ],
    "sg:website":"www.greatclips.com",
    "wof:name":"Great Clips",
    "wof:placetype":"venue"
},
  "geometry": {"coordinates":[-77.80970000000001,35.97765],"type":"Point"}
}