{
  "type": "Feature",
  "properties": {
    "iso:country":"US",
    "sg:address":"644 Nikanor Rd",
    "sg:city":"West Jefferson",
    "sg:classifiers":[
        {
            "category":"Organizations",
            "subcategory":"Non-profit Organization",
            "type":"Services"
        },
        {
            "category":"Organizations",
            "subcategory":"Religious Organization",
            "type":"Services"
        }
    ],
    "sg:phone":"+1 336 877 4181",
    "sg:postcode":"28694",
    "sg:province":"NC",
    "wof:name":"Gideons International Th",
    "wof:placetype":"venue"
},
  "geometry": {"coordinates":[-81.420914,36.336362],"type":"Point"}
}