{
  "type": "Feature",
  "properties": {
    "iso:country":"US",
    "sg:address":"412 Oaks Dr",
    "sg:city":"Kinston",
    "sg:classifiers":[
        {
            "category":"Retail",
            "subcategory":"Repair Shop",
            "type":"Services"
        }
    ],
    "sg:phone":"+1 252 523 1390",
    "sg:postcode":"28504",
    "sg:province":"NC",
    "sg:tags":[
        "refinishing",
        "furniture"
    ],
    "wof:name":"Carolina Furniture Refinishing",
    "wof:placetype":"venue"
},
  "geometry": {"coordinates":[-77.66835,35.206731],"type":"Point"}
}