{
  "type": "Feature",
  "properties": {
    "addr:full":"202 E Union St Marshville NC 28103",
    "addr:housenumber":"202",
    "addr:postcode":"28103",
    "addr:street":"E Union St",
    "iso:country":"US",
    "sg:address":"202 E Union St",
    "sg:city":"Marshville",
    "sg:classifiers":[
        {
            "category":"Wholesale",
            "subcategory":"Electrical",
            "type":"Manufacturing & Wholesale Goods"
        }
    ],
    "sg:phone":"+1 704 624 5546",
    "sg:postcode":"28103",
    "sg:province":"NC",
    "sg:tags":[
        "operated",
        "telephone",
        "card"
    ],
    "wof:name":"Telaleasing Enterprises Inc",
    "wof:placetype":"venue"
},
  "geometry": {"coordinates":[-80.363213,34.989827],"type":"Point"}
}