{
  "type": "Feature",
  "properties": {
    "addr:full":"1815 N Cannon Blvd Kannapolis NC 28083",
    "addr:housenumber":"1815",
    "addr:postcode":"28083",
    "addr:street":"N Cannon Blvd",
    "iso:country":"US",
    "sg:address":"1815 N Cannon Blvd",
    "sg:city":"Kannapolis",
    "sg:classifiers":[
        {
            "category":"Shopping",
            "subcategory":"Shoes",
            "type":"Retail Goods"
        }
    ],
    "sg:phone":"+1 704 938 6711",
    "sg:postcode":"28083",
    "sg:province":"NC",
    "wof:name":"Bills Boots",
    "wof:placetype":"venue"
},
  "geometry": {"coordinates":[-80.61229299999999,35.519967],"type":"Point"}
}