{
  "type": "Feature",
  "properties": {
    "addr:full":"10509 US Hwy 117 Rocky Point NC 28457",
    "addr:housenumber":"10509",
    "addr:postcode":"28457",
    "addr:street":"Us Hwy 117",
    "iso:country":"US",
    "sg:address":"10509 US Hwy 117",
    "sg:city":"Rocky Point",
    "sg:classifiers":[
        {
            "category":"Building & Trades",
            "subcategory":"Construction",
            "type":"Services"
        }
    ],
    "sg:phone":"+1 910 675 8170",
    "sg:postcode":"28457",
    "sg:province":"NC",
    "sg:tags":[
        "contractor"
    ],
    "sg:website":"www.pbarbourandson.com",
    "wof:name":"Paul Barbour & Son",
    "wof:placetype":"venue"
},
  "geometry": {"coordinates":[-77.88798199999999,34.407305],"type":"Point"}
}