{
  "type": "Feature",
  "properties": {
    "addr:full":"496 Majestic Ct SE Concord NC 28025",
    "addr:housenumber":"496",
    "addr:postcode":"28025",
    "addr:street":"Majestic Ct Se",
    "iso:country":"US",
    "sg:address":"496 Majestic Ct SE",
    "sg:city":"Concord",
    "sg:classifiers":[
        {
            "category":"Autos & Motor Vehicles",
            "subcategory":"Automobile Sales",
            "type":"Retail Goods"
        }
    ],
    "sg:phone":"+1 704 786 2419",
    "sg:postcode":"28025",
    "sg:province":"NC",
    "sg:tags":[
        "dealers-used",
        "car",
        "used",
        "cars-wholesale"
    ],
    "wof:name":"Dons Auto Mart",
    "wof:placetype":"venue"
},
  "geometry": {"coordinates":[-80.546994,35.409214],"type":"Point"}
}