{
  "type": "Feature",
  "properties": {
    "iso:country":"US",
    "sg:address":"3400 S Memorial Dr",
    "sg:city":"Greenville",
    "sg:classifiers":[
        {
            "category":"Restaurant",
            "type":"Food & Drink"
        }
    ],
    "sg:phone":"+1 252 754 2244",
    "sg:postcode":"27834",
    "sg:province":"NC",
    "sg:tags":[
        "eating"
    ],
    "wof:name":"Thai Spoon Sushi",
    "wof:placetype":"venue"
},
  "geometry": {"coordinates":[-77.401195,35.56955],"type":"Point"}
}