{
  "type": "Feature",
  "properties": {
    "addr:full":"12000 State Hwy 209 Hot Springs NC 28743",
    "addr:housenumber":"12000",
    "addr:postcode":"28743",
    "addr:street":"State Hwy 209",
    "iso:country":"US",
    "sg:address":"12000 State Hwy 209",
    "sg:city":"Hot Springs",
    "sg:classifiers":[
        {
            "category":"Organizations",
            "subcategory":"Religious Organization",
            "type":"Services"
        }
    ],
    "sg:phone":"+1   ",
    "sg:postcode":"28743",
    "sg:province":"NC",
    "wof:name":"Spring Creek Untd Mthdst Chrch",
    "wof:placetype":"venue"
},
  "geometry": {"coordinates":[-82.85408700000001,35.801045],"type":"Point"}
}