{
  "type": "Feature",
  "properties": {
    "addr:full":"2504 Dearborn Dr Durham NC 27704",
    "addr:housenumber":"2504",
    "addr:postcode":"27704",
    "addr:street":"Dearborn Dr",
    "iso:country":"US",
    "sg:address":"2504 Dearborn Dr",
    "sg:city":"Durham",
    "sg:classifiers":[
        {
            "category":"Social Services",
            "subcategory":"Child Care",
            "type":"Services"
        }
    ],
    "sg:phone":"+1   ",
    "sg:postcode":"27704",
    "sg:province":"NC",
    "sg:tags":[
        "day"
    ],
    "wof:name":"Jack-Rocks In Home Day Care",
    "wof:placetype":"venue"
},
  "geometry": {"coordinates":[-78.87024,36.030179],"type":"Point"}
}