{
  "type": "Feature",
  "properties": {
    "iso:country":"US",
    "sg:address":"407 S Griffin St",
    "sg:city":"Elizabeth City",
    "sg:classifiers":[
        {
            "category":"Shopping",
            "subcategory":"Clothing, Apparel, & Fashions",
            "type":"Retail Goods"
        }
    ],
    "sg:phone":"+1 252 333 1770",
    "sg:postcode":"27909",
    "sg:province":"NC",
    "wof:name":"Image",
    "wof:placetype":"venue"
},
  "geometry": {"coordinates":[-76.234375,36.296589],"type":"Point"}
}