{
  "type": "Feature",
  "properties": {
    "iso:country":"US",
    "sg:address":"17 Matthew Dr",
    "sg:city":"Franklin",
    "sg:classifiers":[
        {
            "category":"Utilities",
            "subcategory":"Telephone",
            "type":"Services"
        }
    ],
    "sg:phone":"+1 828 369 1599",
    "sg:postcode":"28734",
    "sg:province":"NC",
    "sg:tags":[
        "distance",
        "local",
        "telecommunication",
        "long"
    ],
    "wof:name":"Unicom Communications LLC",
    "wof:placetype":"venue"
},
  "geometry": {"coordinates":[-83.38622100000001,35.21856],"type":"Point"}
}