{
  "type": "Feature",
  "properties": {
    "addr:full":"8526 Mount Holly Rd Charlotte NC 28214",
    "addr:housenumber":"8526",
    "addr:postcode":"28214",
    "addr:street":"Mount Holly Rd",
    "iso:country":"US",
    "sg:address":"8526 Mount Holly Rd",
    "sg:city":"Charlotte",
    "sg:classifiers":[
        {
            "category":"Bars & Pubs",
            "type":"Food & Drink"
        }
    ],
    "sg:phone":"+1 704 391 8873",
    "sg:postcode":"28214",
    "sg:province":"NC",
    "sg:tags":[
        "club",
        "drinking",
        "night"
    ],
    "wof:name":"Tody Brown's",
    "wof:placetype":"venue"
},
  "geometry": {"coordinates":[-80.949988,35.284821],"type":"Point"}
}