{
  "type": "Feature",
  "properties": {
    "iso:country":"US",
    "sg:address":"1409 East Blvd",
    "sg:city":"Charlotte",
    "sg:classifiers":[
        {
            "category":"Professional",
            "subcategory":"Management & Consulting",
            "type":"Services"
        }
    ],
    "sg:phone":"+1 704 343 9770",
    "sg:postcode":"28203",
    "sg:province":"NC",
    "sg:tags":[
        "marketing",
        "consultant"
    ],
    "wof:name":"Morisen",
    "wof:placetype":"venue"
},
  "geometry": {"coordinates":[-80.843237,35.201016],"type":"Point"}
}