{
  "type": "Feature",
  "properties": {
    "iso:country":"US",
    "sg:address":"6060 Providence Church Rd",
    "sg:city":"Winston Salem",
    "sg:classifiers":[
        {
            "category":"Building & Trades",
            "subcategory":"Construction",
            "type":"Services"
        }
    ],
    "sg:phone":"+1 336 767 0747",
    "sg:postcode":"27105",
    "sg:province":"NC",
    "sg:tags":[
        "water",
        "well",
        "drilling"
    ],
    "wof:name":"Billy Clayton Water Well Drill",
    "wof:placetype":"venue"
},
  "geometry": {"coordinates":[-80.23784499999999,36.203894],"type":"Point"}
}