{
  "type": "Feature",
  "properties": {
    "addr:full":"3470 Kildaire Farm Rd Ste 164 Cary NC 27511",
    "addr:housenumber":"3470",
    "addr:postcode":"27511",
    "addr:street":"Kildaire Farm Rd Ste 164",
    "iso:country":"US",
    "sg:address":"3470 Kildaire Farm Rd Ste 164",
    "sg:city":"Cary",
    "sg:classifiers":[
        {
            "category":"Wholesale",
            "subcategory":"Stationery",
            "type":"Manufacturing & Wholesale Goods"
        }
    ],
    "sg:phone":"+1 919 387 0650",
    "sg:postcode":"27511",
    "sg:province":"NC",
    "sg:tags":[
        "card"
    ],
    "wof:name":"Lynn's Hallmark Shop",
    "wof:placetype":"venue"
},
  "geometry": {"coordinates":[-78.778198,35.752602],"type":"Point"}
}