{
  "type": "Feature",
  "properties": {
    "addr:full":"3447 Boat Club Rd Belmont NC 28012",
    "addr:housenumber":"3447",
    "addr:postcode":"28012",
    "addr:street":"Boat Club Rd",
    "iso:country":"US",
    "sg:address":"3447 Boat Club Rd",
    "sg:city":"Belmont",
    "sg:classifiers":[
        {
            "category":"Retail",
            "subcategory":"Repair Shop",
            "type":"Services"
        },
        {
            "category":"Manufacturing",
            "subcategory":"Tools & Machinery",
            "type":"Manufacturing & Wholesale Goods"
        }
    ],
    "sg:phone":"+1 704 825 1469",
    "sg:postcode":"28012",
    "sg:province":"NC",
    "sg:tags":[
        "machine",
        "industrial",
        "welding",
        "mfg"
    ],
    "wof:name":"South Point Machine Co",
    "wof:placetype":"venue"
},
  "geometry": {"coordinates":[-81.01349399999999,35.196814],"type":"Point"}
}