{
  "type": "Feature",
  "properties": {
    "addr:full":"233 Center St Star NC 27356",
    "addr:housenumber":"233",
    "addr:postcode":"27356",
    "addr:street":"Center St",
    "iso:country":"US",
    "sg:address":"233 Center St",
    "sg:city":"Star",
    "sg:classifiers":[
        {
            "category":"Real Estate",
            "subcategory":"Real Estate Agent",
            "type":"Services"
        }
    ],
    "sg:phone":"+1 910 428 2387",
    "sg:postcode":"27356",
    "sg:province":"NC",
    "sg:tags":[
        "authorities",
        "housing"
    ],
    "wof:name":"Star Housing Authority",
    "wof:placetype":"venue"
},
  "geometry": {"coordinates":[-79.781031,35.396733],"type":"Point"}
}