{
  "type": "Feature",
  "properties": {
    "addr:full":"2004 Upland Ct Raleigh NC 27615",
    "addr:housenumber":"2004",
    "addr:postcode":"27615",
    "addr:street":"Upland Ct",
    "iso:country":"US",
    "sg:address":"2004 Upland Ct",
    "sg:city":"Raleigh",
    "sg:classifiers":[
        {
            "category":"Professional",
            "subcategory":"Computer Services",
            "type":"Services"
        }
    ],
    "sg:phone":"+1   ",
    "sg:postcode":"27615",
    "sg:province":"NC",
    "sg:tags":[
        "prepackaged",
        "software"
    ],
    "wof:name":"Einstein Development LLC",
    "wof:placetype":"venue"
},
  "geometry": {"coordinates":[-78.60366399999999,35.907029],"type":"Point"}
}