{
  "type": "Feature",
  "properties": {
    "addr:full":"27726 Hatley Farm Rd Albemarle NC 28001",
    "addr:postcode":"27726;28001",
    "addr:street":"Farm Rd",
    "iso:country":"US",
    "sg:address":"27726 Hatley Farm Rd",
    "sg:city":"Albemarle",
    "sg:classifiers":[
        {
            "category":"Organizations",
            "subcategory":"Religious Organization",
            "type":"Services"
        }
    ],
    "sg:phone":"+1   ",
    "sg:postcode":"28001",
    "sg:province":"NC",
    "wof:name":"Fellowship Baptist Church",
    "wof:placetype":"venue"
},
  "geometry": {"coordinates":[-80.28017199999999,35.365642],"type":"Point"}
}