{
  "type": "Feature",
  "properties": {
    "addr:full":"6321 Sentry Oaks Dr Wilmington NC 28409",
    "addr:housenumber":"6321",
    "addr:postcode":"28409",
    "addr:street":"Sentry Oaks Dr",
    "iso:country":"US",
    "sg:address":"6321 Sentry Oaks Dr",
    "sg:city":"Wilmington",
    "sg:classifiers":[
        {
            "category":"Banks & Credit Unions",
            "subcategory":"Bank",
            "type":"Services"
        }
    ],
    "sg:phone":"+1 910 452 9595",
    "sg:postcode":"28409",
    "sg:province":"NC",
    "sg:tags":[
        "loan",
        "real estate"
    ],
    "sg:website":"www.firstgreensboro.com",
    "wof:name":"First Greensboro Home Equity",
    "wof:placetype":"venue"
},
  "geometry": {"coordinates":[-77.884472,34.121491],"type":"Point"}
}