{
  "type": "Feature",
  "properties": {
    "addr:full":"283 Thomas Rd Franklin NC 28734",
    "addr:housenumber":"283",
    "addr:postcode":"nc 28734",
    "addr:street":"Thomas Rd",
    "iso:country":"US",
    "sg:address":"283 Thomas Rd",
    "sg:city":"Franklin",
    "sg:classifiers":[
        {
            "category":"Home & Garden",
            "subcategory":"Hardware",
            "type":"Retail Goods"
        },
        {
            "category":"Home & Garden",
            "subcategory":"Building Materials",
            "type":"Retail Goods"
        }
    ],
    "sg:phone":"+1 828 369 1786",
    "sg:postcode":"28734",
    "sg:province":"NC",
    "sg:tags":[
        "store"
    ],
    "wof:name":"Jennings Builders Supply and Hardware",
    "wof:placetype":"venue"
},
  "geometry": {"coordinates":[-83.35911,35.178303],"type":"Point"}
}