{
  "type": "Feature",
  "properties": {
    "addr:full":"832 Purser Dr Raleigh NC 27603",
    "addr:housenumber":"832",
    "addr:postcode":"27603",
    "addr:street":"Purser Dr",
    "iso:country":"US",
    "sg:address":"832 Purser Dr",
    "sg:city":"Raleigh",
    "sg:classifiers":[
        {
            "category":"Recreation",
            "subcategory":"Arcade",
            "type":"Entertainment"
        }
    ],
    "sg:phone":"+1 919 661 2738",
    "sg:postcode":"27603",
    "sg:province":"NC",
    "sg:tags":[
        "amusement",
        "devices"
    ],
    "wof:name":"ARCADEGAMES4U.COM",
    "wof:placetype":"venue"
},
  "geometry": {"coordinates":[-78.66261,35.717033],"type":"Point"}
}