{
  "type": "Feature",
  "properties": {
    "iso:country":"US",
    "sg:address":"115 Exeter St",
    "sg:city":"Manteo",
    "sg:classifiers":[
        {
            "category":"Health Services",
            "subcategory":"Doctor",
            "type":"Services"
        }
    ],
    "sg:phone":"+1 252 475 3530",
    "sg:postcode":"27954",
    "sg:province":"NC",
    "sg:tags":[
        "physician",
        "surgeon"
    ],
    "wof:name":"Dare County Dialysis Ctr",
    "wof:placetype":"venue"
},
  "geometry": {"coordinates":[-75.674914,35.903643],"type":"Point"}
}