{
  "type": "Feature",
  "properties": {
    "iso:country":"US",
    "sg:address":"428 Cedar Hill Ln",
    "sg:city":"Raleigh",
    "sg:classifiers":[
        {
            "category":"Insurance",
            "subcategory":"Insurance Agent",
            "type":"Services"
        }
    ],
    "sg:phone":"+1 919 787 7441",
    "sg:postcode":"27609",
    "sg:province":"NC",
    "wof:name":"Long Term Benefits Inc",
    "wof:placetype":"venue"
},
  "geometry": {"coordinates":[-78.63027599999999,35.853459],"type":"Point"}
}