{
  "type": "Feature",
  "properties": {
    "iso:country":"US",
    "sg:address":"36 Providence Pl",
    "sg:city":"Waynesville",
    "sg:classifiers":[
        {
            "category":"Shopping",
            "subcategory":"Used Merchandise",
            "type":"Retail Goods"
        }
    ],
    "sg:phone":"+1 828 456 7229",
    "sg:postcode":"28786",
    "sg:province":"NC",
    "wof:name":"Barbers Orchard Antique Mall",
    "wof:placetype":"venue"
},
  "geometry": {"coordinates":[-83.0562,35.450753],"type":"Point"}
}