{
  "type": "Feature",
  "properties": {
    "addr:full":"319 Arvo Ln Cary NC 27513",
    "addr:housenumber":"319",
    "addr:postcode":"27513",
    "addr:street":"Arvo Ln",
    "iso:country":"US",
    "sg:address":"319 Arvo Ln",
    "sg:city":"Cary",
    "sg:classifiers":[
        {
            "category":"Social Services",
            "type":"Services"
        }
    ],
    "sg:phone":"+1 919 677 8585",
    "sg:postcode":"27513",
    "sg:province":"NC",
    "sg:tags":[
        "organization",
        "welfare"
    ],
    "wof:name":"Lamaze Of Cary",
    "wof:placetype":"venue"
},
  "geometry": {"coordinates":[-78.82501000000001,35.766437],"type":"Point"}
}