{
  "type": "Feature",
  "properties": {
    "iso:country":"US",
    "sg:address":"1013 Central Dr NW",
    "sg:city":"Concord",
    "sg:classifiers":[
        {
            "category":"Building & Trades",
            "subcategory":"Construction",
            "type":"Services"
        }
    ],
    "sg:phone":"+1 704 784 9121",
    "sg:postcode":"28027",
    "sg:province":"NC",
    "sg:tags":[
        "insulation",
        "heat",
        "contractor"
    ],
    "sg:website":"www.31w.com",
    "wof:name":"31-W Insulation Co Inc",
    "wof:placetype":"venue"
},
  "geometry": {"coordinates":[-80.61545099999999,35.432565],"type":"Point"}
}