{
  "type": "Feature",
  "properties": {
    "addr:full":"324 S Sharon Amity Rd Charlotte NC 28211",
    "addr:housenumber":"324",
    "addr:postcode":"28211",
    "addr:street":"S Sharon Amity Rd",
    "iso:country":"US",
    "sg:address":"324 S Sharon Amity Rd",
    "sg:city":"Charlotte",
    "sg:classifiers":[
        {
            "category":"Personal",
            "subcategory":"Beauty Salon",
            "type":"Services"
        }
    ],
    "sg:phone":"+1 704 364 0270",
    "sg:postcode":"28211",
    "sg:province":"NC",
    "sg:tags":[
        "spa"
    ],
    "sg:website":"www.carmencarmensalon.com",
    "wof:name":"Carmen Carmen Salon E Spa",
    "wof:placetype":"venue"
},
  "geometry": {"coordinates":[-80.799521,35.175678],"type":"Point"}
}