{
  "type": "Feature",
  "properties": {
    "iso:country":"US",
    "sg:address":"336 Old Swamp Rd",
    "sg:city":"South Mills",
    "sg:classifiers":[
        {
            "category":"Wholesale",
            "subcategory":"Durable Goods & Equipment",
            "type":"Manufacturing & Wholesale Goods"
        }
    ],
    "sg:phone":"+1 252 771 3030",
    "sg:postcode":"27976",
    "sg:province":"NC",
    "wof:name":"Riggs Music Co",
    "wof:placetype":"venue"
},
  "geometry": {"coordinates":[-76.29145,36.457192],"type":"Point"}
}