{
  "type": "Feature",
  "properties": {
    "iso:country":"US",
    "sg:address":"323 N Arlington St",
    "sg:city":"Salisbury",
    "sg:classifiers":[
        {
            "category":"Shopping",
            "subcategory":"Department Store",
            "type":"Retail Goods"
        }
    ],
    "sg:phone":"+1 704 639 9718",
    "sg:postcode":"28144",
    "sg:province":"NC",
    "sg:tags":[
        "grocery"
    ],
    "wof:name":"Wal-Mart",
    "wof:placetype":"venue"
},
  "geometry": {"coordinates":[-80.458303,35.662535],"type":"Point"}
}