{
  "type": "Feature",
  "properties": {
    "addr:full":"706 Pineburr Pl Durham NC 27703",
    "addr:housenumber":"706",
    "addr:postcode":"27703",
    "addr:street":"Pineburr Pl",
    "iso:country":"US",
    "sg:address":"706 Pineburr Pl",
    "sg:city":"Durham",
    "sg:classifiers":[
        {
            "category":"Professional",
            "subcategory":"Management & Consulting",
            "type":"Services"
        }
    ],
    "sg:phone":"+1 919 957 1269",
    "sg:postcode":"27703",
    "sg:province":"NC",
    "sg:tags":[
        "retail",
        "direct",
        "sales"
    ],
    "wof:name":"Shoppe With Alease",
    "wof:placetype":"venue"
},
  "geometry": {"coordinates":[-78.82881500000001,35.993346],"type":"Point"}
}