{
  "type": "Feature",
  "properties": {
    "addr:full":"685 Bridges Rd Sanford NC 27330",
    "addr:housenumber":"685",
    "addr:postcode":"27330",
    "addr:street":"Bridges Rd",
    "iso:country":"US",
    "sg:address":"685 Bridges Rd",
    "sg:city":"Sanford",
    "sg:classifiers":[
        {
            "category":"Building & Trades",
            "subcategory":"Landscaping Services",
            "type":"Services"
        }
    ],
    "sg:phone":"+1 919 776 7807",
    "sg:postcode":"27330",
    "sg:province":"NC",
    "wof:name":"Palmer Landscaping",
    "wof:placetype":"venue"
},
  "geometry": {"coordinates":[-79.252359,35.456544],"type":"Point"}
}