{
  "type": "Feature",
  "properties": {
    "iso:country":"US",
    "sg:address":"7142 Knightdale Blvd",
    "sg:city":"Knightdale",
    "sg:classifiers":[
        {
            "category":"Restaurant",
            "type":"Food & Drink"
        }
    ],
    "sg:menulink":"http://www.allmenus.com/nc/st-matthews/158151-remington-grill/menu/",
    "sg:phone":"+1 919 217 8005",
    "sg:postcode":"27545",
    "sg:province":"NC",
    "sg:tags":[
        "american"
    ],
    "wof:name":"Remington Grill",
    "wof:placetype":"venue"
},
  "geometry": {"coordinates":[-78.490138,35.798208],"type":"Point"}
}