{
  "type": "Feature",
  "properties": {
    "addr:full":"4005 Durham-Chapel Hill Blvd Durham NC 27707",
    "addr:housenumber":"4005",
    "addr:postcode":"27707",
    "addr:street":"Durham-Chapel Hill Blvd",
    "iso:country":"US",
    "sg:address":"4005 Durham-Chapel Hill Blvd",
    "sg:city":"Durham",
    "sg:classifiers":[
        {
            "category":"Real Estate",
            "subcategory":"Real Estate Operator",
            "type":"Services"
        }
    ],
    "sg:phone":"+1 919 489 8160",
    "sg:postcode":"27707",
    "sg:province":"NC",
    "sg:tags":[
        "mall",
        "shopping",
        "center"
    ],
    "wof:name":"Sam's Club",
    "wof:placetype":"venue"
},
  "geometry": {"coordinates":[-78.958291,35.969405],"type":"Point"}
}