{
  "type": "Feature",
  "properties": {
    "addr:full":"218 Front St Beaufort NC 28516",
    "addr:housenumber":"218",
    "addr:postcode":"28516",
    "addr:street":"Front St",
    "iso:country":"US",
    "sg:address":"218 Front St",
    "sg:city":"Beaufort",
    "sg:classifiers":[
        {
            "category":"Restaurant",
            "type":"Food & Drink"
        }
    ],
    "sg:menulink":"http://www.allmenus.com/nc/beaufort/158072-the-spouter-inn/menu/",
    "sg:phone":"+1 252 728 5190",
    "sg:postcode":"28516",
    "sg:province":"NC",
    "sg:tags":[
        "american"
    ],
    "wof:name":"The Spouter Inn",
    "wof:placetype":"venue"
},
  "geometry": {"coordinates":[-76.668262,34.718336],"type":"Point"}
}