{
  "type": "Feature",
  "properties": {
    "iso:country":"US",
    "sg:address":"8657 Adkins Rd",
    "sg:city":"Colfax",
    "sg:classifiers":[
        {
            "category":"Real Estate",
            "subcategory":"Real Estate Operator",
            "type":"Services"
        }
    ],
    "sg:phone":"+1 336 393 0352",
    "sg:postcode":"27235",
    "sg:province":"NC",
    "sg:tags":[
        "property",
        "lessor"
    ],
    "wof:name":"Barreau & Ward Properties",
    "wof:placetype":"venue"
},
  "geometry": {"coordinates":[-80.009139,36.072055],"type":"Point"}
}