{
  "type": "Feature",
  "properties": {
    "iso:country":"US",
    "sg:address":"4122 Bennett Memorial Rd",
    "sg:city":"Durham",
    "sg:classifiers":[
        {
            "category":"Building & Trades",
            "subcategory":"Pest Control",
            "type":"Services"
        }
    ],
    "sg:phone":"+1 919 382 0651",
    "sg:postcode":"27705",
    "sg:province":"NC",
    "sg:tags":[
        "trapper",
        "animal"
    ],
    "wof:name":"Critter Control",
    "wof:placetype":"venue"
},
  "geometry": {"coordinates":[-78.968327,36.030182],"type":"Point"}
}