{
  "type": "Feature",
  "properties": {
    "iso:country":"US",
    "sg:address":"190 School Rd",
    "sg:city":"Asheville",
    "sg:classifiers":[
        {
            "category":"Health Services",
            "subcategory":"Doctor",
            "type":"Services"
        }
    ],
    "sg:phone":"+1   ",
    "sg:postcode":"28806",
    "sg:province":"NC",
    "wof:name":"DDS Investments LLC",
    "wof:placetype":"venue"
},
  "geometry": {"coordinates":[-82.61485500000001,35.569609],"type":"Point"}
}