{
  "type": "Feature",
  "properties": {
    "iso:country":"US",
    "sg:address":"5030 Southport-Supply Rd SE",
    "sg:city":"Southport",
    "sg:classifiers":[
        {
            "category":"Manufacturing",
            "subcategory":"Furniture",
            "type":"Manufacturing & Wholesale Goods"
        }
    ],
    "sg:phone":"+1 910 454 9500",
    "sg:postcode":"28461",
    "sg:province":"NC",
    "sg:tags":[
        "patio",
        "mfg"
    ],
    "wof:name":"Woodell Lawn & Patio Furniture",
    "wof:placetype":"venue"
},
  "geometry": {"coordinates":[-78.048474,33.952443],"type":"Point"}
}