{
  "type": "Feature",
  "properties": {
    "iso:country":"US",
    "sg:address":"4720 Tobacco Rd",
    "sg:city":"Orrum",
    "sg:classifiers":[
        {
            "category":"Farming",
            "subcategory":"Poultry Farm",
            "type":"Manufacturing & Wholesale Goods"
        }
    ],
    "sg:phone":"+1 910 628 1748",
    "sg:postcode":"28369",
    "sg:province":"NC",
    "sg:tags":[
        "egg"
    ],
    "wof:name":"S & S Farms",
    "wof:placetype":"venue"
},
  "geometry": {"coordinates":[-79.09549,34.416343],"type":"Point"}
}