{
  "type": "Feature",
  "properties": {
    "iso:country":"US",
    "sg:address":"8813 Gulf Ct",
    "sg:city":"Raleigh",
    "sg:classifiers":[
        {
            "category":"Recreation",
            "subcategory":"Arcade",
            "type":"Entertainment"
        }
    ],
    "sg:phone":"+1   ",
    "sg:postcode":"27617",
    "sg:province":"NC",
    "sg:tags":[
        "device",
        "operator",
        "amusement"
    ],
    "wof:name":"Personal Touch Vending",
    "wof:placetype":"venue"
},
  "geometry": {"coordinates":[-78.763246,35.90382],"type":"Point"}
}