{
  "type": "Feature",
  "properties": {
    "addr:full":"1600 W Center St Exd Lexington NC 27295",
    "addr:housenumber":"1600",
    "addr:postcode":"27295",
    "addr:street":"W Center St Exd",
    "iso:country":"US",
    "sg:address":"1600 W Center St Exd",
    "sg:city":"Lexington",
    "sg:classifiers":[
        {
            "category":"Government",
            "subcategory":"Fire Station",
            "type":"Public Place"
        }
    ],
    "sg:phone":"+1 336 248 2120",
    "sg:postcode":"27295",
    "sg:province":"NC",
    "sg:tags":[
        "department"
    ],
    "sg:website":"www.wlfd.com",
    "wof:name":"West Lexington Fire Dept",
    "wof:placetype":"venue"
},
  "geometry": {"coordinates":[-80.279133,35.852957],"type":"Point"}
}