{
  "type": "Feature",
  "properties": {
    "addr:full":"2208 New Hill Olive Chapel Rd New Hill NC 27562",
    "addr:housenumber":"2208",
    "addr:postcode":"27562",
    "addr:street":"New Hill Olive Chapel Rd New",
    "iso:country":"US",
    "sg:address":"2208 New Hill Olive Chapel Rd",
    "sg:city":"New Hill",
    "sg:classifiers":[
        {
            "category":"Building & Trades",
            "subcategory":"Construction",
            "type":"Services"
        }
    ],
    "sg:phone":"+1 919 362 7775",
    "sg:postcode":"27562",
    "sg:province":"NC",
    "sg:tags":[
        "contractor"
    ],
    "wof:name":"Ashscot Homes Inc",
    "wof:placetype":"venue"
},
  "geometry": {"coordinates":[-78.94157199999999,35.694196],"type":"Point"}
}