{
  "type": "Feature",
  "properties": {
    "addr:full":"601 Margrace Rd Kings Mountain NC 28086",
    "addr:housenumber":"601",
    "addr:postcode":"28086",
    "addr:street":"Margrace Rd",
    "iso:country":"US",
    "sg:address":"601 Margrace Rd",
    "sg:city":"Kings Mountain",
    "sg:classifiers":[
        {
            "category":"Freight",
            "type":"Transportation"
        }
    ],
    "sg:phone":"+1 704 739 5421",
    "sg:postcode":"28086",
    "sg:province":"NC",
    "sg:tags":[
        "warehouse",
        "self",
        "storage"
    ],
    "wof:name":"Bunch Inc Warehouse",
    "wof:placetype":"venue"
},
  "geometry": {"coordinates":[-81.376769,35.215916],"type":"Point"}
}