{
  "type": "Feature",
  "properties": {
    "iso:country":"US",
    "sg:address":"1203 Castalia Dr",
    "sg:city":"Cary",
    "sg:classifiers":[
        {
            "category":"Professional",
            "subcategory":"Business Services",
            "type":"Services"
        }
    ],
    "sg:phone":"+1   ",
    "sg:postcode":"27513",
    "sg:province":"NC",
    "wof:name":"H W Brown and Associates",
    "wof:placetype":"venue"
},
  "geometry": {"coordinates":[-78.814329,35.778496],"type":"Point"}
}