{
  "type": "Feature",
  "properties": {
    "addr:full":"501 Executive Pl Fayetteville NC 28305",
    "addr:housenumber":"501",
    "addr:postcode":"28305",
    "addr:street":"Executive Pl",
    "iso:country":"US",
    "sg:address":"501 Executive Pl",
    "sg:city":"Fayetteville",
    "sg:classifiers":[
        {
            "category":"Health Services",
            "subcategory":"Hospital",
            "type":"Services"
        }
    ],
    "sg:phone":"+1 910 485 6843",
    "sg:postcode":"28305",
    "sg:province":"NC",
    "sg:tags":[
        "mental"
    ],
    "wof:name":"Evergreen Health Svc",
    "wof:placetype":"venue"
},
  "geometry": {"coordinates":[-78.92223199999999,35.049406],"type":"Point"}
}