{
  "type": "Feature",
  "properties": {
    "iso:country":"US",
    "sg:address":"332 Old Wilkesboro Rd Exd",
    "sg:city":"Taylorsville",
    "sg:classifiers":[
        {
            "category":"Building & Trades",
            "subcategory":"Construction",
            "type":"Services"
        }
    ],
    "sg:phone":"+1 828 632 3511",
    "sg:postcode":"28681",
    "sg:province":"NC",
    "sg:tags":[
        "grading",
        "contractor"
    ],
    "wof:name":"Boyd Adams Grading",
    "wof:placetype":"venue"
},
  "geometry": {"coordinates":[-81.192989,35.960832],"type":"Point"}
}