{
  "type": "Feature",
  "properties": {
    "iso:country":"US",
    "sg:address":"640 Old Hwy 86",
    "sg:city":"Yanceyville",
    "sg:classifiers":[
        {
            "category":"Education",
            "subcategory":"School",
            "type":"Public Place"
        }
    ],
    "sg:phone":"+1 336 694 6264",
    "sg:postcode":"27379",
    "sg:province":"NC",
    "wof:name":"Noahs Educ",
    "wof:placetype":"venue"
},
  "geometry": {"coordinates":[-79.358453,36.418664],"type":"Point"}
}