{
  "type": "Feature",
  "properties": {
    "addr:full":"5 Oakcrest Dr Asheville NC 28806",
    "addr:housenumber":"5",
    "addr:postcode":"28806",
    "addr:street":"Oakcrest Dr",
    "iso:country":"US",
    "sg:address":"5 Oakcrest Dr",
    "sg:city":"Asheville",
    "sg:classifiers":[
        {
            "category":"Building & Trades",
            "subcategory":"Landscaping Services",
            "type":"Services"
        }
    ],
    "sg:phone":"+1 828 215 4827",
    "sg:postcode":"28806",
    "sg:province":"NC",
    "sg:tags":[
        "tree"
    ],
    "sg:website":"treeservicesasheville.com/#cid=yelp",
    "wof:name":"Trees Unlimited",
    "wof:placetype":"venue"
},
  "geometry": {"coordinates":[-82.617226,35.579036],"type":"Point"}
}