{
  "type": "Feature",
  "properties": {
    "addr:full":"293 E Front St Burlington NC 27215",
    "addr:housenumber":"293",
    "addr:postcode":"27215",
    "addr:street":"E Front St",
    "iso:country":"US",
    "sg:address":"293 E Front St",
    "sg:city":"Burlington",
    "sg:classifiers":[
        {
            "category":"Professional",
            "subcategory":"Accounting & Tax Preparation",
            "type":"Services"
        }
    ],
    "sg:phone":"+1 336 222 0068",
    "sg:postcode":"27215",
    "sg:province":"NC",
    "sg:tags":[
        "accountant"
    ],
    "wof:name":"William Gordon Phillips CPA",
    "wof:placetype":"venue"
},
  "geometry": {"coordinates":[-79.436111,36.0931],"type":"Point"}
}