{
  "type": "Feature",
  "properties": {
    "addr:full":"3208 S College Rd Wilmington NC 28412",
    "addr:housenumber":"3208",
    "addr:postcode":"28412",
    "addr:street":"S College Rd",
    "iso:country":"US",
    "sg:address":"3208 S College Rd",
    "sg:city":"Wilmington",
    "sg:classifiers":[
        {
            "category":"Professional",
            "subcategory":"Lawyer & Legal Services",
            "type":"Services"
        }
    ],
    "sg:phone":"+1 910 270 1043",
    "sg:postcode":"28412",
    "sg:province":"NC",
    "sg:tags":[
        "attorney"
    ],
    "wof:name":"Mako & Assoc",
    "wof:placetype":"venue"
},
  "geometry": {"coordinates":[-77.889985,34.190948],"type":"Point"}
}