{
  "type": "Feature",
  "properties": {
    "iso:country":"US",
    "sg:address":"134 Miller St",
    "sg:city":"Waynesville",
    "sg:classifiers":[
        {
            "category":"Real Estate",
            "subcategory":"Surveying",
            "type":"Services"
        }
    ],
    "sg:phone":"+1 828 452 2362",
    "sg:postcode":"28786",
    "sg:province":"NC",
    "sg:tags":[
        "surveyor"
    ],
    "wof:name":"Sechser Precision Surveying",
    "wof:placetype":"venue"
},
  "geometry": {"coordinates":[-82.991463,35.492144],"type":"Point"}
}