{
  "type": "Feature",
  "properties": {
    "addr:full":"10910 State Hwy 222 W Middlesex NC 27557",
    "addr:housenumber":"10910",
    "addr:postcode":"27557",
    "addr:street":"State Hwy 222 W",
    "iso:country":"US",
    "sg:address":"10910 State Hwy 222 W",
    "sg:city":"Middlesex",
    "sg:classifiers":[
        {
            "category":"Social Services",
            "subcategory":"Adult Care",
            "type":"Services"
        }
    ],
    "sg:phone":"+1 919 284 0100",
    "sg:postcode":"27557",
    "sg:province":"NC",
    "sg:tags":[
        "home",
        "group"
    ],
    "wof:name":"Hodges Group Home",
    "wof:placetype":"venue"
},
  "geometry": {"coordinates":[-78.228729,35.7154],"type":"Point"}
}