{
  "type": "Feature",
  "properties": {
    "iso:country":"US",
    "sg:address":"1278 Minter School Rd",
    "sg:city":"Sanford",
    "sg:classifiers":[
        {
            "category":"Building & Trades",
            "subcategory":"Construction",
            "type":"Services"
        }
    ],
    "sg:phone":"+1 919 718 4911",
    "sg:postcode":"27332",
    "sg:province":"NC",
    "sg:tags":[
        "contractor"
    ],
    "wof:name":"Jeffery Ward",
    "wof:placetype":"venue"
},
  "geometry": {"coordinates":[-79.184827,35.424464],"type":"Point"}
}