{
  "type": "Feature",
  "properties": {
    "addr:full":"1400 Mount Jefferson Rd West Jefferson NC 28694",
    "addr:housenumber":"1400",
    "addr:postcode":"28694",
    "addr:street":"Mount Jefferson Rd",
    "iso:country":"US",
    "sg:address":"1400 Mount Jefferson Rd",
    "sg:city":"West Jefferson",
    "sg:classifiers":[
        {
            "category":"Restaurant",
            "type":"Food & Drink"
        }
    ],
    "sg:menulink":"http://www.allmenus.com/nc/west-jefferson/137691-subway/menu/",
    "sg:phone":"+1 336 246 7827",
    "sg:postcode":"28694",
    "sg:province":"NC",
    "sg:tags":[
        "american",
        "sandwich"
    ],
    "wof:name":"Subway",
    "wof:placetype":"venue"
},
  "geometry": {"coordinates":[-81.481362,36.394414],"type":"Point"}
}