{
  "type": "Feature",
  "properties": {
    "addr:full":"5621 Departure Dr Raleigh NC 27616",
    "addr:postcode":"5621;27616",
    "addr:street":"Departure Dr",
    "iso:country":"US",
    "sg:address":"5621 Departure Dr",
    "sg:city":"Raleigh",
    "sg:classifiers":[
        {
            "category":"Insurance",
            "subcategory":"Insurance Agent",
            "type":"Services"
        }
    ],
    "sg:phone":"+1 919 877 9933",
    "sg:postcode":"27616",
    "sg:province":"NC",
    "sg:tags":[
        "processing"
    ],
    "sg:website":"www.ims-tpa.com",
    "wof:name":"Interactive Medical Systems",
    "wof:placetype":"venue"
},
  "geometry": {"coordinates":[-78.591739,35.860814],"type":"Point"}
}