{
  "type": "Feature",
  "properties": {
    "iso:country":"US",
    "sg:address":"8000 Mount Pleasant Church Rd",
    "sg:city":"Willow Spring",
    "sg:classifiers":[
        {
            "category":"Organizations",
            "subcategory":"Religious Organization",
            "type":"Services"
        }
    ],
    "sg:phone":"+1 919 552 1063",
    "sg:postcode":"27592",
    "sg:province":"NC",
    "sg:tags":[
        "church"
    ],
    "wof:name":"Mt Pleaseant Presybyterian",
    "wof:placetype":"venue"
},
  "geometry": {"coordinates":[-78.665757,35.57607],"type":"Point"}
}