{
  "type": "Feature",
  "properties": {
    "iso:country":"US",
    "sg:address":"5335 Country Club Rd",
    "sg:city":"Winston Salem",
    "sg:classifiers":[
        {
            "category":"Real Estate",
            "subcategory":"Real Estate Operator",
            "type":"Services"
        }
    ],
    "sg:phone":"+1 336 765 9217",
    "sg:postcode":"27104",
    "sg:province":"NC",
    "sg:tags":[
        "apartment"
    ],
    "wof:name":"Quail Lakes Apartments",
    "wof:placetype":"venue"
},
  "geometry": {"coordinates":[-80.36248999999999,36.089058],"type":"Point"}
}