{
  "type": "Feature",
  "properties": {
    "iso:country":"US",
    "sg:address":"6512 Six Forks Rd",
    "sg:city":"Raleigh",
    "sg:classifiers":[
        {
            "category":"Health Services",
            "subcategory":"Doctor",
            "type":"Services"
        }
    ],
    "sg:phone":"+1   ",
    "sg:postcode":"27615",
    "sg:province":"NC",
    "sg:tags":[
        "medical"
    ],
    "wof:name":"David L Smoot Phd",
    "wof:placetype":"venue"
},
  "geometry": {"coordinates":[-78.63887099999999,35.868371],"type":"Point"}
}