{
  "type": "Feature",
  "properties": {
    "iso:country":"US",
    "sg:address":"1200 N Salem St",
    "sg:city":"Apex",
    "sg:classifiers":[
        {
            "category":"Organizations",
            "subcategory":"Religious Organization",
            "type":"Services"
        }
    ],
    "sg:phone":"+1   ",
    "sg:postcode":"27523",
    "sg:province":"NC",
    "wof:name":"Prince Of Peace Episcopal",
    "wof:placetype":"venue"
},
  "geometry": {"coordinates":[-78.851145,35.745739],"type":"Point"}
}