{
  "type": "Feature",
  "properties": {
    "addr:full":"4975 State Hwy 54 Graham NC 27253",
    "addr:housenumber":"4975",
    "addr:postcode":"27253",
    "addr:street":"State Hwy 54",
    "iso:country":"US",
    "sg:address":"4975 State Hwy 54",
    "sg:city":"Graham",
    "sg:classifiers":[
        {
            "category":"Building & Trades",
            "subcategory":"Construction",
            "type":"Services"
        }
    ],
    "sg:phone":"+1 336 376 8349",
    "sg:postcode":"27253",
    "sg:province":"NC",
    "sg:tags":[
        "house"
    ],
    "wof:name":"Sharpe Custom Homes",
    "wof:placetype":"venue"
},
  "geometry": {"coordinates":[-79.291357,35.988983],"type":"Point"}
}