{
  "type": "Feature",
  "properties": {
    "addr:full":"8161 Rockingham Rd Laurel Hill NC 28351",
    "addr:housenumber":"8161",
    "addr:postcode":"28351",
    "addr:street":"Rockingham Rd",
    "iso:country":"US",
    "sg:address":"8161 Rockingham Rd",
    "sg:city":"Laurel Hill",
    "sg:classifiers":[
        {
            "category":"Retail",
            "subcategory":"Auto Repair",
            "type":"Services"
        }
    ],
    "sg:phone":"+1   ",
    "sg:postcode":"28351",
    "sg:province":"NC",
    "sg:tags":[
        "general"
    ],
    "wof:name":"Kellys Garage",
    "wof:placetype":"venue"
},
  "geometry": {"coordinates":[-79.578475,34.7992],"type":"Point"}
}