{
  "type": "Feature",
  "properties": {
    "iso:country":"US",
    "sg:address":"2408 Circle Dr",
    "sg:city":"Wake Forest",
    "sg:classifiers":[
        {
            "category":"Building & Trades",
            "subcategory":"Construction",
            "type":"Services"
        }
    ],
    "sg:phone":"+1 919 270 9690",
    "sg:postcode":"27587",
    "sg:province":"NC",
    "sg:tags":[
        "home",
        "improvement"
    ],
    "wof:name":"Further Development",
    "wof:placetype":"venue"
},
  "geometry": {"coordinates":[-78.54808800000001,35.917167],"type":"Point"}
}