{
  "type": "Feature",
  "properties": {
    "addr:full":"46 3rd St NW Hickory NC 28601",
    "addr:housenumber":"46",
    "addr:postcode":"28601",
    "addr:street":"3Rd St Nw",
    "iso:country":"US",
    "sg:address":"46 3rd St NW",
    "sg:city":"Hickory",
    "sg:classifiers":[
        {
            "category":"Professional",
            "type":"Services"
        }
    ],
    "sg:phone":"+1 828 322 8156",
    "sg:postcode":"28601",
    "sg:province":"NC",
    "sg:tags":[
        "establishment"
    ],
    "wof:name":"Panders Ship Travel Agency Inc",
    "wof:placetype":"venue"
},
  "geometry": {"coordinates":[-81.3421,35.73232],"type":"Point"}
}