{
  "type": "Feature",
  "properties": {
    "addr:full":"903 Main Ave SW Hickory NC 28602",
    "addr:housenumber":"903",
    "addr:postcode":"28602",
    "addr:street":"Main Ave Sw",
    "iso:country":"US",
    "sg:address":"903 Main Ave SW",
    "sg:city":"Hickory",
    "sg:classifiers":[
        {
            "category":"Restaurant",
            "type":"Food & Drink"
        }
    ],
    "sg:phone":"+1 828 304 0604",
    "sg:postcode":"28602",
    "sg:province":"NC",
    "sg:tags":[
        "eating"
    ],
    "wof:name":"Burbon Street Cafe",
    "wof:placetype":"venue"
},
  "geometry": {"coordinates":[-81.35391199999999,35.731642],"type":"Point"}
}