{
  "type": "Feature",
  "properties": {
    "addr:full":"207 Pelican Walk Hampstead NC 28443",
    "addr:housenumber":"207",
    "addr:postcode":"28443",
    "addr:street":"Pelican Walk",
    "iso:country":"US",
    "sg:address":"207 Pelican Walk",
    "sg:city":"Hampstead",
    "sg:classifiers":[
        {
            "category":"Farming",
            "subcategory":"Aquatic Farm",
            "type":"Manufacturing & Wholesale Goods"
        }
    ],
    "sg:phone":"+1 910 270 2438",
    "sg:postcode":"28443",
    "sg:province":"NC",
    "sg:tags":[
        "fish"
    ],
    "wof:name":"Sloopoint Seafood & Crabhouse",
    "wof:placetype":"venue"
},
  "geometry": {"coordinates":[-77.612959,34.402608],"type":"Point"}
}