{
  "type": "Feature",
  "properties": {
    "addr:full":"200 Nash St NE Wilson NC 27893",
    "addr:housenumber":"200",
    "addr:postcode":"27893",
    "addr:street":"Nash St Ne",
    "iso:country":"US",
    "sg:address":"200 Nash St NE",
    "sg:city":"Wilson",
    "sg:classifiers":[
        {
            "category":"Education",
            "subcategory":"Special Training",
            "type":"Public Place"
        }
    ],
    "sg:phone":"+1 252 399 7726",
    "sg:postcode":"27893",
    "sg:province":"NC",
    "sg:tags":[
        "educational"
    ],
    "wof:name":"Wilson Education Partnership",
    "wof:placetype":"venue"
},
  "geometry": {"coordinates":[-77.913483,35.728415],"type":"Point"}
}