{
  "type": "Feature",
  "properties": {
    "addr:full":"296 Muellers Cir Statesville NC 28625",
    "addr:housenumber":"296",
    "addr:postcode":"28625",
    "addr:street":"Muellers Cir",
    "iso:country":"US",
    "sg:address":"296 Muellers Cir",
    "sg:city":"Statesville",
    "sg:classifiers":[
        {
            "category":"Real Estate",
            "subcategory":"Real Estate Operator",
            "type":"Services"
        }
    ],
    "sg:phone":"+1 704 878 0344",
    "sg:postcode":"28625",
    "sg:province":"NC",
    "sg:tags":[
        "building",
        "apartment"
    ],
    "wof:name":"North Pointe Apartments",
    "wof:placetype":"venue"
},
  "geometry": {"coordinates":[-80.883966,35.817352],"type":"Point"}
}