{
  "type": "Feature",
  "properties": {
    "iso:country":"US",
    "sg:address":"1501 E 11th St",
    "sg:city":"Siler City",
    "sg:classifiers":[
        {
            "category":"Autos & Motor Vehicles",
            "subcategory":"Auto Supplies",
            "type":"Retail Goods"
        }
    ],
    "sg:phone":"+1 919 742 1253",
    "sg:postcode":"27344",
    "sg:province":"NC",
    "sg:tags":[
        "automobile",
        "parts"
    ],
    "wof:name":"Autozone",
    "wof:placetype":"venue"
},
  "geometry": {"coordinates":[-79.442785,35.733136],"type":"Point"}
}