{
  "type": "Feature",
  "properties": {
    "addr:full":"462 N Bridge St Jonesville NC 28642",
    "addr:housenumber":"462",
    "addr:postcode":"28642",
    "addr:street":"N Bridge St",
    "iso:country":"US",
    "sg:address":"462 N Bridge St",
    "sg:city":"Jonesville",
    "sg:classifiers":[
        {
            "category":"Autos & Motor Vehicles",
            "subcategory":"Automobile Sales",
            "type":"Retail Goods"
        }
    ],
    "sg:phone":"+1 336 526 3523",
    "sg:postcode":"28642",
    "sg:province":"NC",
    "sg:tags":[
        "used"
    ],
    "wof:name":"N & W Auto Sales",
    "wof:placetype":"venue"
},
  "geometry": {"coordinates":[-80.84613,36.240513],"type":"Point"}
}