{
  "type": "Feature",
  "properties": {
    "addr:full":"5950 Fairview Rd Charlotte NC 28210",
    "addr:housenumber":"5950",
    "addr:postcode":"28210",
    "addr:street":"Fairview Rd",
    "iso:country":"US",
    "sg:address":"5950 Fairview Rd",
    "sg:city":"Charlotte",
    "sg:classifiers":[
        {
            "category":"Professional",
            "subcategory":"Lawyer & Legal Services",
            "type":"Services"
        }
    ],
    "sg:phone":"+1 704 554 9022",
    "sg:postcode":"28210",
    "sg:province":"NC",
    "sg:tags":[
        "attorney"
    ],
    "wof:name":"Gunst & Gunst",
    "wof:placetype":"venue"
},
  "geometry": {"coordinates":[-80.840929,35.151326],"type":"Point"}
}