{
  "type": "Feature",
  "properties": {
    "iso:country":"US",
    "sg:address":"7707 Hap Ct",
    "sg:city":"Kernersville",
    "sg:classifiers":[
        {
            "category":"Professional",
            "type":"Services"
        }
    ],
    "sg:phone":"+1 336 643 9631",
    "sg:postcode":"27284",
    "sg:province":"NC",
    "wof:name":"Go Big Inc",
    "wof:placetype":"venue"
},
  "geometry": {"coordinates":[-80.003479,36.212915],"type":"Point"}
}