{
  "type": "Feature",
  "properties": {
    "addr:full":"200 Willa Mae Ct Thomasville NC 27360",
    "addr:housenumber":"200",
    "addr:postcode":"27360",
    "addr:street":"Willa Mae Ct",
    "iso:country":"US",
    "sg:address":"200 Willa Mae Ct",
    "sg:city":"Thomasville",
    "sg:classifiers":[
        {
            "category":"Professional",
            "subcategory":"Business Services",
            "type":"Services"
        }
    ],
    "sg:phone":"+1   ",
    "sg:postcode":"27360",
    "sg:province":"NC",
    "wof:name":"Spangler Family Enterprises LL",
    "wof:placetype":"venue"
},
  "geometry": {"coordinates":[-80.080941,35.832898],"type":"Point"}
}