{
  "type": "Feature",
  "properties": {
    "iso:country":"US",
    "sg:address":"3737 Atmore St",
    "sg:city":"Charlotte",
    "sg:classifiers":[
        {
            "category":"Autos & Motor Vehicles",
            "subcategory":"Auto Supplies",
            "type":"Retail Goods"
        },
        {
            "category":"Wholesale",
            "subcategory":"Auto Parts",
            "type":"Manufacturing & Wholesale Goods"
        }
    ],
    "sg:phone":"+1 704 342 2327",
    "sg:postcode":"28205",
    "sg:province":"NC",
    "sg:tags":[
        "automobile"
    ],
    "sg:website":"www.enginepartssupply.com",
    "wof:name":"Engine Parts Supply Co Inc",
    "wof:placetype":"venue"
},
  "geometry": {"coordinates":[-80.794037,35.248227],"type":"Point"}
}