{
  "type": "Feature",
  "properties": {
    "addr:full":"1549 Prison Camp Rd Newton NC 28658",
    "addr:housenumber":"1549",
    "addr:postcode":"28658",
    "addr:street":"Prison Camp Rd",
    "iso:country":"US",
    "sg:address":"1549 Prison Camp Rd",
    "sg:city":"Newton",
    "sg:classifiers":[
        {
            "category":"Building & Trades",
            "subcategory":"Construction",
            "type":"Services"
        }
    ],
    "sg:phone":"+1 828 465 3324",
    "sg:postcode":"28658",
    "sg:province":"NC",
    "sg:tags":[
        "contractor"
    ],
    "wof:name":"Styers Custom Services Inc",
    "wof:placetype":"venue"
},
  "geometry": {"coordinates":[-81.202718,35.620945],"type":"Point"}
}