{
  "type": "Feature",
  "properties": {
    "iso:country":"US",
    "sg:address":"3600 N Duke St",
    "sg:city":"Durham",
    "sg:classifiers":[
        {
            "category":"Personal",
            "subcategory":"Beauty Salon",
            "type":"Services"
        }
    ],
    "sg:phone":"+1 919 620 1555",
    "sg:postcode":"27704",
    "sg:province":"NC",
    "sg:tags":[
        "shop"
    ],
    "wof:name":"Terri's Total You Salon",
    "wof:placetype":"venue"
},
  "geometry": {"coordinates":[-78.90572899999999,36.050094],"type":"Point"}
}