{
  "type": "Feature",
  "properties": {
    "iso:country":"US",
    "sg:address":"3515 Latrobe Dr",
    "sg:city":"Charlotte",
    "sg:classifiers":[
        {
            "category":"Professional",
            "type":"Services"
        },
        {
            "category":"Health Services",
            "subcategory":"Clinic",
            "type":"Services"
        }
    ],
    "sg:phone":"+1 704 366 5299",
    "sg:postcode":"28211",
    "sg:province":"NC",
    "sg:tags":[
        "establishment",
        "kidney",
        "dialysis",
        "center"
    ],
    "wof:name":"Dialysis Care Mecklenberg Cnty",
    "wof:placetype":"venue"
},
  "geometry": {"coordinates":[-80.799937,35.197821],"type":"Point"}
}