{
  "type": "Feature",
  "properties": {
    "addr:full":"2030 Castle Hayne Rd Wilmington NC 28401",
    "addr:housenumber":"2030",
    "addr:postcode":"28401",
    "addr:street":"Castle Hayne Rd",
    "iso:country":"US",
    "sg:address":"2030 Castle Hayne Rd",
    "sg:city":"Wilmington",
    "sg:classifiers":[
        {
            "category":"Home & Garden",
            "subcategory":"Garden Supply",
            "type":"Retail Goods"
        }
    ],
    "sg:phone":"+1 910 675 1055",
    "sg:postcode":"28401",
    "sg:province":"NC",
    "sg:tags":[
        "nurseryman"
    ],
    "wof:name":"Swart Gardens",
    "wof:placetype":"venue"
},
  "geometry": {"coordinates":[-77.92400499999999,34.278812],"type":"Point"}
}