{
  "type": "Feature",
  "properties": {
    "addr:full":"134 Fairview St Atlantic Beach NC 28512",
    "addr:housenumber":"134",
    "addr:postcode":"28512",
    "addr:street":"Fairview St",
    "iso:country":"US",
    "sg:address":"134 Fairview St",
    "sg:city":"Atlantic Beach",
    "sg:classifiers":[
        {
            "category":"Building & Trades",
            "subcategory":"Construction",
            "type":"Services"
        }
    ],
    "sg:phone":"+1 252 247 6063",
    "sg:postcode":"28512",
    "sg:province":"NC",
    "sg:tags":[
        "roofing",
        "contractor"
    ],
    "wof:name":"USA Roofing Co",
    "wof:placetype":"venue"
},
  "geometry": {"coordinates":[-76.78307700000001,34.700194],"type":"Point"}
}