{
  "type": "Feature",
  "properties": {
    "iso:country":"US",
    "sg:address":"1017 Bettie St",
    "sg:city":"Yadkinville",
    "sg:classifiers":[
        {
            "category":"Restaurant",
            "type":"Food & Drink"
        }
    ],
    "sg:phone":"+1 336 463 2825",
    "sg:postcode":"27055",
    "sg:province":"NC",
    "wof:name":"Walkers Grill",
    "wof:placetype":"venue"
},
  "geometry": {"coordinates":[-80.68176200000001,36.133351],"type":"Point"}
}