{
  "type": "Feature",
  "properties": {
    "addr:full":"114 S Oakwood Dr Statesville NC 28677",
    "addr:housenumber":"114",
    "addr:postcode":"28677",
    "addr:street":"S Oakwood Dr",
    "iso:country":"US",
    "sg:address":"114 S Oakwood Dr",
    "sg:city":"Statesville",
    "sg:classifiers":[
        {
            "category":"Government",
            "subcategory":"Office",
            "type":"Public Place"
        }
    ],
    "sg:phone":"+1 704 878 3428",
    "sg:postcode":"28677",
    "sg:province":"NC",
    "sg:tags":[
        "village"
    ],
    "wof:name":"Public Grounds",
    "wof:placetype":"venue"
},
  "geometry": {"coordinates":[-80.876349,35.788358],"type":"Point"}
}