{
  "type": "Feature",
  "properties": {
    "iso:country":"US",
    "sg:address":"607 Plaza Blvd",
    "sg:city":"Kinston",
    "sg:classifiers":[
        {
            "category":"Banks & Credit Unions",
            "subcategory":"Bank",
            "type":"Services"
        }
    ],
    "sg:phone":"+1 252 939 3020",
    "sg:postcode":"28501",
    "sg:province":"NC",
    "wof:name":"First-Citizens Bank & Trust Co",
    "wof:placetype":"venue"
},
  "geometry": {"coordinates":[-77.589264,35.285024],"type":"Point"}
}