{
  "type": "Feature",
  "properties": {
    "addr:full":"8680 US Hwy 264 E Washington NC 27889",
    "addr:housenumber":"8680",
    "addr:postcode":"27889",
    "addr:street":"Us Hwy 264 E",
    "iso:country":"US",
    "sg:address":"8680 US Hwy 264 E",
    "sg:city":"Washington",
    "sg:classifiers":[
        {
            "category":"Retail",
            "subcategory":"Repair Shop",
            "type":"Services"
        }
    ],
    "sg:phone":"+1 252 946 9117",
    "sg:postcode":"27889",
    "sg:province":"NC",
    "sg:tags":[
        "upholsterer"
    ],
    "wof:name":"Mitchell's Upholstery Svc",
    "wof:placetype":"venue"
},
  "geometry": {"coordinates":[-76.88466,35.524554],"type":"Point"}
}