{
  "type": "Feature",
  "properties": {
    "iso:country":"US",
    "sg:address":"209 W Front St",
    "sg:city":"Statesville",
    "sg:classifiers":[
        {
            "category":"Shopping",
            "subcategory":"Gifts & Souvenirs",
            "type":"Retail Goods"
        }
    ],
    "sg:phone":"+1 704 881 0133",
    "sg:postcode":"28677",
    "sg:province":"NC",
    "sg:tags":[
        "shop"
    ],
    "wof:name":"Front Street Gifts & Awards",
    "wof:placetype":"venue"
},
  "geometry": {"coordinates":[-80.889033,35.782175],"type":"Point"}
}