{
  "type": "Feature",
  "properties": {
    "addr:full":"693 Franklintown Rd Spruce Pine NC 28777",
    "addr:housenumber":"693",
    "addr:postcode":"28777",
    "addr:street":"Franklintown Rd",
    "iso:country":"US",
    "sg:address":"693 Franklintown Rd",
    "sg:city":"Spruce Pine",
    "sg:classifiers":[
        {
            "category":"Wholesale",
            "subcategory":"Construction Materials",
            "type":"Manufacturing & Wholesale Goods"
        }
    ],
    "sg:phone":"+1 828 765 1217",
    "sg:postcode":"28777",
    "sg:province":"NC",
    "sg:tags":[
        "brick",
        "stone",
        "related"
    ],
    "wof:name":"J & K Mountain Stone",
    "wof:placetype":"venue"
},
  "geometry": {"coordinates":[-82.006287,35.925748],"type":"Point"}
}