{
  "type": "Feature",
  "properties": {
    "iso:country":"US",
    "sg:address":"1601 South Blvd",
    "sg:city":"Charlotte",
    "sg:classifiers":[
        {
            "category":"Restaurant",
            "type":"Food & Drink"
        }
    ],
    "sg:menulink":"http://www.allmenus.com/nc/charlotte/235258-sub-station-ii/menu/",
    "sg:phone":"+1 704 332 3100",
    "sg:postcode":"28203",
    "sg:province":"NC",
    "sg:tags":[
        "wrap",
        "american",
        "sandwich"
    ],
    "wof:name":"Sub Station II",
    "wof:placetype":"venue"
},
  "geometry": {"coordinates":[-80.855616,35.213663],"type":"Point"}
}