{
  "type": "Feature",
  "properties": {
    "addr:full":"1200 Overstream Ln Matthews NC 28105",
    "addr:housenumber":"1200",
    "addr:postcode":"28105",
    "addr:street":"Overstream Ln",
    "iso:country":"US",
    "sg:address":"1200 Overstream Ln",
    "sg:city":"Matthews",
    "sg:classifiers":[
        {
            "category":"Wholesale",
            "subcategory":"Electrical",
            "type":"Manufacturing & Wholesale Goods"
        }
    ],
    "sg:phone":"+1 704 844 8156",
    "sg:postcode":"28105",
    "sg:province":"NC",
    "sg:tags":[
        "cards",
        "phone",
        "paid"
    ],
    "wof:name":"Patricia Warren Yandle",
    "wof:placetype":"venue"
},
  "geometry": {"coordinates":[-80.71379,35.077601],"type":"Point"}
}