{
  "type": "Feature",
  "properties": {
    "addr:full":"204 Marion St Tryon NC 28782",
    "addr:housenumber":"204",
    "addr:postcode":"28782",
    "addr:street":"Marion St",
    "iso:country":"US",
    "sg:address":"204 Marion St",
    "sg:city":"Tryon",
    "sg:classifiers":[
        {
            "category":"Manufacturing",
            "subcategory":"Retail Goods",
            "type":"Manufacturing & Wholesale Goods"
        }
    ],
    "sg:phone":"+1 828 468 4101",
    "sg:postcode":"28782",
    "sg:province":"NC",
    "sg:tags":[
        "manufacturer"
    ],
    "wof:name":"Carver Industries",
    "wof:placetype":"venue"
},
  "geometry": {"coordinates":[-82.248903,35.210574],"type":"Point"}
}