{
  "type": "Feature",
  "properties": {
    "addr:full":"201 K St North Wilkesboro NC 28659",
    "addr:housenumber":"201",
    "addr:postcode":"28659",
    "addr:street":"K St",
    "iso:country":"US",
    "sg:address":"201 K St",
    "sg:city":"North Wilkesboro",
    "sg:classifiers":[
        {
            "category":"Retail",
            "subcategory":"Auto Repair",
            "type":"Services"
        }
    ],
    "sg:phone":"+1 336 838 5771",
    "sg:postcode":"28659",
    "sg:province":"NC",
    "sg:tags":[
        "repairing",
        "automobile",
        "automotive",
        "general"
    ],
    "wof:name":"Tiny's Alignment & Brake Svc",
    "wof:placetype":"venue"
},
  "geometry": {"coordinates":[-81.141688,36.171584],"type":"Point"}
}