{
  "type": "Feature",
  "properties": {
    "addr:full":"912 Burkemont Ave Morganton NC 28655",
    "addr:housenumber":"912",
    "addr:postcode":"28655",
    "addr:street":"Burkemont Ave",
    "iso:country":"US",
    "sg:address":"912 Burkemont Ave",
    "sg:city":"Morganton",
    "sg:classifiers":[
        {
            "category":"Real Estate",
            "subcategory":"Real Estate Agent",
            "type":"Services"
        }
    ],
    "sg:phone":"+1 828 437 9686",
    "sg:postcode":"28655",
    "sg:province":"NC",
    "wof:name":"Sharon Marlowe Realty Inc",
    "wof:placetype":"venue"
},
  "geometry": {"coordinates":[-81.69278799999999,35.724454],"type":"Point"}
}