{
  "type": "Feature",
  "properties": {
    "iso:country":"US",
    "sg:address":"5712 Carriage Park Ct",
    "sg:city":"Fuquay Varina",
    "sg:classifiers":[
        {
            "category":"Real Estate",
            "subcategory":"Real Estate Agent",
            "type":"Services"
        }
    ],
    "sg:phone":"+1 919 557 0380",
    "sg:postcode":"27526",
    "sg:province":"NC",
    "sg:tags":[
        "consultant"
    ],
    "wof:name":"Blair Group",
    "wof:placetype":"venue"
},
  "geometry": {"coordinates":[-78.776352,35.62269],"type":"Point"}
}