{
  "type": "Feature",
  "properties": {
    "addr:full":"5944 Old Providence Rd Charlotte NC 28226",
    "addr:housenumber":"5944",
    "addr:postcode":"28226",
    "addr:street":"Old Providence Rd",
    "iso:country":"US",
    "sg:address":"5944 Old Providence Rd",
    "sg:city":"Charlotte",
    "sg:classifiers":[
        {
            "category":"Professional",
            "subcategory":"Computer Services",
            "type":"Services"
        }
    ],
    "sg:phone":"+1   ",
    "sg:postcode":"28226",
    "sg:province":"NC",
    "sg:tags":[
        "related"
    ],
    "wof:name":"Simpson Taliaferro III",
    "wof:placetype":"venue"
},
  "geometry": {"coordinates":[-80.78504700000001,35.131162],"type":"Point"}
}