{
  "type": "Feature",
  "properties": {
    "addr:full":"7066 Mendenhall Rd Archdale NC 27263",
    "addr:housenumber":"7066",
    "addr:postcode":"27263",
    "addr:street":"Mendenhall Rd",
    "iso:country":"US",
    "sg:address":"7066 Mendenhall Rd",
    "sg:city":"Archdale",
    "sg:classifiers":[
        {
            "category":"Manufacturing",
            "subcategory":"Printing",
            "type":"Manufacturing & Wholesale Goods"
        }
    ],
    "sg:phone":"+1 336 434 6544",
    "sg:postcode":"27263",
    "sg:province":"NC",
    "sg:tags":[
        "screen"
    ],
    "sg:website":"www.cranfordsilkscreen.com",
    "wof:name":"Cranford Silk Screen Process",
    "wof:placetype":"venue"
},
  "geometry": {"coordinates":[-80.02801700000001,35.908684],"type":"Point"}
}