{
  "type": "Feature",
  "properties": {
    "addr:full":"2883 Westfield Ave NW Concord NC 28027",
    "addr:housenumber":"2883",
    "addr:postcode":"28027",
    "addr:street":"Westfield Ave Nw",
    "iso:country":"US",
    "sg:address":"2883 Westfield Ave NW",
    "sg:city":"Concord",
    "sg:classifiers":[
        {
            "category":"Organizations",
            "subcategory":"Religious Organization",
            "type":"Services"
        }
    ],
    "sg:phone":"+1 704 786 5964",
    "sg:postcode":"28027",
    "sg:province":"NC",
    "sg:tags":[
        "clergy"
    ],
    "wof:name":"Thomas D Smith",
    "wof:placetype":"venue"
},
  "geometry": {"coordinates":[-80.626622,35.403153],"type":"Point"}
}