{
  "type": "Feature",
  "properties": {
    "addr:full":"3184 Hickory Hwy Statesville NC 28677",
    "addr:housenumber":"3184",
    "addr:postcode":"28677",
    "addr:street":"Hickory Hwy",
    "iso:country":"US",
    "sg:address":"3184 Hickory Hwy",
    "sg:city":"Statesville",
    "sg:classifiers":[
        {
            "category":"Retail",
            "subcategory":"Auto Repair",
            "type":"Services"
        }
    ],
    "sg:phone":"+1 704 873 2048",
    "sg:postcode":"28677",
    "sg:province":"NC",
    "sg:tags":[
        "body",
        "automobile",
        "painting"
    ],
    "wof:name":"Joseys Paint & Body Shop Inc",
    "wof:placetype":"venue"
},
  "geometry": {"coordinates":[-80.942052,35.776179],"type":"Point"}
}