{
  "type": "Feature",
  "properties": {
    "iso:country":"US",
    "sg:address":"795 Fairview Rd",
    "sg:city":"Asheville",
    "sg:classifiers":[
        {
            "category":"Home & Garden",
            "subcategory":"Building Materials",
            "type":"Retail Goods"
        }
    ],
    "sg:phone":"+1 828 274 5400",
    "sg:postcode":"28803",
    "sg:province":"NC",
    "sg:website":"www.homedepot.com",
    "wof:name":"Home Depot",
    "wof:placetype":"venue"
},
  "geometry": {"coordinates":[-82.5089,35.566608],"type":"Point"}
}