{
  "type": "Feature",
  "properties": {
    "addr:full":"6304 Radds St Lexington NC 27295",
    "addr:housenumber":"6304",
    "addr:postcode":"27295",
    "addr:street":"Radds St",
    "iso:country":"US",
    "sg:address":"6304 Radds St",
    "sg:city":"Lexington",
    "sg:classifiers":[
        {
            "category":"Freight",
            "type":"Transportation"
        }
    ],
    "sg:phone":"+1 336 764 5320",
    "sg:postcode":"27295",
    "sg:province":"NC",
    "sg:tags":[
        "operator",
        "local",
        "trucking"
    ],
    "wof:name":"Timmons Trucking Co",
    "wof:placetype":"venue"
},
  "geometry": {"coordinates":[-80.25326699999999,35.977064],"type":"Point"}
}