{
  "type": "Feature",
  "properties": {
    "iso:country":"US",
    "sg:address":"1673 Old Clear Creek Rd",
    "sg:city":"Hendersonville",
    "sg:classifiers":[
        {
            "category":"Building & Trades",
            "subcategory":"Construction",
            "type":"Services"
        }
    ],
    "sg:phone":"+1 828 685 8367",
    "sg:postcode":"28792",
    "sg:province":"NC",
    "sg:tags":[
        "contractor"
    ],
    "wof:name":"Thomas Masonry",
    "wof:placetype":"venue"
},
  "geometry": {"coordinates":[-82.37653400000001,35.403655],"type":"Point"}
}