{
  "type": "Feature",
  "properties": {
    "addr:full":"509 E Graham St Mebane NC 27302",
    "addr:housenumber":"509",
    "addr:postcode":"27302",
    "addr:street":"E Graham St",
    "iso:country":"US",
    "sg:address":"509 E Graham St",
    "sg:city":"Mebane",
    "sg:classifiers":[
        {
            "category":"Building & Trades",
            "subcategory":"Construction",
            "type":"Services"
        }
    ],
    "sg:phone":"+1 919 563 1690",
    "sg:postcode":"27302",
    "sg:province":"NC",
    "sg:tags":[
        "house"
    ],
    "wof:name":"Thomas Construction Cliff",
    "wof:placetype":"venue"
},
  "geometry": {"coordinates":[-79.25757,36.096744],"type":"Point"}
}