{
  "type": "Feature",
  "properties": {
    "addr:full":"520 New Grady Brown School Rd Hillsborough NC 27278",
    "addr:housenumber":"520",
    "addr:postcode":"27278",
    "addr:street":"New Grady Brown School Rd",
    "iso:country":"US",
    "sg:address":"520 New Grady Brown School Rd",
    "sg:city":"Hillsborough",
    "sg:classifiers":[
        {
            "category":"Building & Trades",
            "subcategory":"Construction",
            "type":"Services"
        }
    ],
    "sg:phone":"+1 919 732 5028",
    "sg:postcode":"27278",
    "sg:province":"NC",
    "sg:tags":[
        "roofing",
        "contractor"
    ],
    "wof:name":"Chief Roofing Co Inc",
    "wof:placetype":"venue"
},
  "geometry": {"coordinates":[-79.118432,36.047647],"type":"Point"}
}