{
  "type": "Feature",
  "properties": {
    "iso:country":"US",
    "sg:address":"2918 Newark Dr",
    "sg:city":"Raleigh",
    "sg:classifiers":[
        {
            "category":"Government",
            "subcategory":"Office",
            "type":"Public Place"
        }
    ],
    "sg:phone":"+1 919 819 6653",
    "sg:postcode":"27610",
    "sg:province":"NC",
    "sg:tags":[
        "nonprofit"
    ],
    "wof:name":"Blazoo Development Corporation",
    "wof:placetype":"venue"
},
  "geometry": {"coordinates":[-78.62315700000001,35.740474],"type":"Point"}
}