{
  "type": "Feature",
  "properties": {
    "iso:country":"US",
    "sg:address":"4900 Chestnut Lake Dr",
    "sg:city":"Charlotte",
    "sg:classifiers":[
        {
            "category":"Sports & Exercise",
            "subcategory":"Gym",
            "type":"Entertainment"
        }
    ],
    "sg:phone":"+1 704 882 3449",
    "sg:postcode":"28227",
    "sg:province":"NC",
    "sg:tags":[
        "personal",
        "trainer"
    ],
    "wof:name":"Creative Player Inc",
    "wof:placetype":"venue"
},
  "geometry": {"coordinates":[-80.715627,35.191626],"type":"Point"}
}