{
  "type": "Feature",
  "properties": {
    "addr:full":"108 Clayton Rd Durham NC 27703",
    "addr:housenumber":"108",
    "addr:postcode":"27703",
    "addr:street":"Clayton Rd",
    "iso:country":"US",
    "sg:address":"108 Clayton Rd",
    "sg:city":"Durham",
    "sg:classifiers":[
        {
            "category":"Restaurant",
            "type":"Food & Drink"
        }
    ],
    "sg:phone":"+1 919 596 5340",
    "sg:postcode":"27703",
    "sg:province":"NC",
    "sg:tags":[
        "eating"
    ],
    "wof:name":"Grove Cafe",
    "wof:placetype":"venue"
},
  "geometry": {"coordinates":[-78.830978,35.985155],"type":"Point"}
}