{
  "type": "Feature",
  "properties": {
    "iso:country":"US",
    "sg:address":"218 Greenhall Rd",
    "sg:city":"Edenton",
    "sg:phone":"+1 252 482 3022",
    "sg:postcode":"27932",
    "sg:province":"NC",
    "sg:tags":[
        "wheat",
        "oat",
        "grain",
        "soybean",
        "peanuts",
        "cotton"
    ],
    "wof:name":"F T Eure & Son",
    "wof:placetype":"venue"
},
  "geometry": {"coordinates":[-76.62491900000001,36.117595],"type":"Point"}
}