{
  "type": "Feature",
  "properties": {
    "addr:full":"1109 W Wright Rd Greenville NC 27858",
    "addr:housenumber":"1109",
    "addr:postcode":"27858",
    "addr:street":"W Wright Rd",
    "iso:country":"US",
    "sg:address":"1109 W Wright Rd",
    "sg:city":"Greenville",
    "sg:classifiers":[
        {
            "category":"Real Estate",
            "subcategory":"Real Estate Agent",
            "type":"Services"
        },
        {
            "category":"Real Estate",
            "subcategory":"Real Estate Operator",
            "type":"Services"
        }
    ],
    "sg:phone":"+1 252 752 3002",
    "sg:postcode":"27858",
    "sg:province":"NC",
    "sg:tags":[
        "apartment"
    ],
    "sg:website":"www.pinnaclepropertymanagement.com",
    "wof:name":"Pinnacle Property Management O",
    "wof:placetype":"venue"
},
  "geometry": {"coordinates":[-77.350015,35.59866],"type":"Point"}
}