{
  "type": "Feature",
  "properties": {
    "iso:country":"US",
    "sg:address":"610 W Morgan St",
    "sg:city":"Durham",
    "sg:classifiers":[
        {
            "category":"Communications",
            "subcategory":"Radio Station",
            "type":"Services"
        }
    ],
    "sg:phone":"+1 919 683 1361",
    "sg:postcode":"27701",
    "sg:province":"NC",
    "wof:name":"Jessica A Jones",
    "wof:placetype":"venue"
},
  "geometry": {"coordinates":[-78.90649999999999,35.999653],"type":"Point"}
}