{
  "type": "Feature",
  "properties": {
    "iso:country":"US",
    "sg:address":"2828 Capital Blvd",
    "sg:city":"Raleigh",
    "sg:classifiers":[
        {
            "category":"Shopping",
            "type":"Retail Goods"
        }
    ],
    "sg:phone":"+1 919 954 1130",
    "sg:postcode":"27604",
    "sg:province":"NC",
    "sg:tags":[
        "trophy",
        "medal",
        "award"
    ],
    "sg:website":"www.trophyusa.com",
    "wof:name":"TROPHYUSA.COM",
    "wof:placetype":"venue"
},
  "geometry": {"coordinates":[-78.598578,35.817841],"type":"Point"}
}