{
  "type": "Feature",
  "properties": {
    "addr:full":"33 Oak Hill Dr Asheville NC 28806",
    "addr:housenumber":"33",
    "addr:postcode":"28806",
    "addr:street":"Oak Hill Dr",
    "iso:country":"US",
    "sg:address":"33 Oak Hill Dr",
    "sg:city":"Asheville",
    "sg:classifiers":[
        {
            "category":"Professional",
            "subcategory":"Business Services",
            "type":"Services"
        },
        {
            "category":"Retail",
            "subcategory":"Auto Repair",
            "type":"Services"
        }
    ],
    "sg:phone":"+1 828 665 4357",
    "sg:postcode":"28806",
    "sg:province":"NC",
    "sg:tags":[
        "wrecker",
        "key",
        "locksmith"
    ],
    "wof:name":"Carolina Towing & Transport",
    "wof:placetype":"venue"
},
  "geometry": {"coordinates":[-82.603351,35.592853],"type":"Point"}
}