{
  "type": "Feature",
  "properties": {
    "iso:country":"US",
    "sg:address":"6515 US Hwy 17",
    "sg:city":"Vanceboro",
    "sg:classifiers":[
        {
            "category":"Manufacturing",
            "subcategory":"Lumber",
            "type":"Manufacturing & Wholesale Goods"
        }
    ],
    "sg:phone":"+1 252 244 0402",
    "sg:postcode":"28586",
    "sg:province":"NC",
    "sg:tags":[
        "logging"
    ],
    "wof:name":"C L Holland Logging Co",
    "wof:placetype":"venue"
},
  "geometry": {"coordinates":[-77.102738,35.26237],"type":"Point"}
}