{
  "type": "Feature",
  "properties": {
    "addr:full":"665 Huffman Mill Rd Burlington NC 27215",
    "addr:housenumber":"665",
    "addr:postcode":"27215",
    "addr:street":"Huffman Mill Rd",
    "iso:country":"US",
    "sg:address":"665 Huffman Mill Rd",
    "sg:city":"Burlington",
    "sg:classifiers":[
        {
            "category":"Restaurant",
            "type":"Food & Drink"
        }
    ],
    "sg:menulink":"http://www.allmenus.com/nc/boone-station/183292-kfc---kentucky-fried-chicken/menu/",
    "sg:phone":"+1 336 524 9578",
    "sg:postcode":"27215",
    "sg:province":"NC",
    "sg:tags":[
        "american",
        "chicken"
    ],
    "wof:name":"KFC - Kentucky Fried Chicken",
    "wof:placetype":"venue"
},
  "geometry": {"coordinates":[-79.49156499999999,36.073195],"type":"Point"}
}