{
  "type": "Feature",
  "properties": {
    "addr:full":"6406 Siloam Rd Siloam NC 27047",
    "addr:housenumber":"6406",
    "addr:postcode":"27047",
    "addr:street":"Siloam Rd",
    "iso:country":"US",
    "sg:address":"6406 Siloam Rd",
    "sg:city":"Siloam",
    "sg:classifiers":[
        {
            "category":"Freight",
            "type":"Transportation"
        }
    ],
    "sg:phone":"+1 336 374 5043",
    "sg:postcode":"27047",
    "sg:province":"NC",
    "sg:tags":[
        "arrangement"
    ],
    "wof:name":"HB Logistics",
    "wof:placetype":"venue"
},
  "geometry": {"coordinates":[-80.578034,36.298012],"type":"Point"}
}