{
  "type": "Feature",
  "properties": {
    "iso:country":"US",
    "sg:address":"425 Providence Rd",
    "sg:city":"Charlotte",
    "sg:classifiers":[
        {
            "category":"Retail",
            "subcategory":"Laundry & Dry Cleaning",
            "type":"Services"
        }
    ],
    "sg:phone":"+1   ",
    "sg:postcode":"28207",
    "sg:province":"NC",
    "sg:tags":[
        "drycleaning",
        "plant"
    ],
    "wof:name":"Dry Clean U S A",
    "wof:placetype":"venue"
},
  "geometry": {"coordinates":[-80.824459,35.204019],"type":"Point"}
}