{
  "type": "Feature",
  "properties": {
    "iso:country":"US",
    "sg:address":"481 Rollins Rd",
    "sg:city":"Marshall",
    "sg:phone":"+1 828 649 2312",
    "sg:postcode":"28753",
    "sg:province":"NC",
    "sg:tags":[
        "oil"
    ],
    "wof:name":"O A Gregory Inc",
    "wof:placetype":"venue"
},
  "geometry": {"coordinates":[-82.66892,35.792709],"type":"Point"}
}