{
  "type": "Feature",
  "properties": {
    "iso:country":"US",
    "sg:address":"18307 Bowsprit Pointe Rd",
    "sg:city":"Cornelius",
    "sg:classifiers":[
        {
            "category":"Real Estate",
            "subcategory":"Real Estate Operator",
            "type":"Services"
        }
    ],
    "sg:phone":"+1 704 892 7746",
    "sg:postcode":"28031",
    "sg:province":"NC",
    "sg:tags":[
        "building",
        "nonresidential"
    ],
    "wof:name":"Bella Properties LLC",
    "wof:placetype":"venue"
},
  "geometry": {"coordinates":[-80.911452,35.461199],"type":"Point"}
}