{
  "type": "Feature",
  "properties": {
    "addr:full":"9 Bland Spring Pl Durham NC 27713",
    "addr:housenumber":"9",
    "addr:postcode":"27713",
    "addr:street":"Bland Spring Pl",
    "iso:country":"US",
    "sg:address":"9 Bland Spring Pl",
    "sg:city":"Durham",
    "sg:classifiers":[
        {
            "category":"Real Estate",
            "subcategory":"Real Estate Agent",
            "type":"Services"
        },
        {
            "category":"Banks & Credit Unions",
            "subcategory":"Financial Services",
            "type":"Services"
        }
    ],
    "sg:phone":"+1 919 806 1000",
    "sg:postcode":"27713",
    "sg:province":"NC",
    "sg:tags":[
        "development"
    ],
    "wof:name":"Thunder Road Holdings LLC",
    "wof:placetype":"venue"
},
  "geometry": {"coordinates":[-78.956907,35.892081],"type":"Point"}
}