{
  "type": "Feature",
  "properties": {
    "addr:full":"4026 Wiggins Mill Rd Wilson NC 27893",
    "addr:postcode":"4026;27893",
    "addr:street":"Wiggins Mill Rd",
    "iso:country":"US",
    "sg:address":"4026 Wiggins Mill Rd",
    "sg:city":"Wilson",
    "sg:classifiers":[
        {
            "category":"Personal",
            "subcategory":"Beauty Salon",
            "type":"Services"
        }
    ],
    "sg:phone":"+1   ",
    "sg:postcode":"27893",
    "sg:province":"NC",
    "sg:tags":[
        "shop"
    ],
    "wof:name":"All About Hair",
    "wof:placetype":"venue"
},
  "geometry": {"coordinates":[-77.96286499999999,35.688014],"type":"Point"}
}