{
  "type": "Feature",
  "properties": {
    "addr:full":"1206 Brooks Ave Raleigh NC 27607",
    "addr:housenumber":"1206",
    "addr:postcode":"27607",
    "addr:street":"Brooks Ave",
    "iso:country":"US",
    "sg:address":"1206 Brooks Ave",
    "sg:city":"Raleigh",
    "sg:classifiers":[
        {
            "category":"Professional",
            "subcategory":"Lawyer & Legal Services",
            "type":"Services"
        }
    ],
    "sg:phone":"+1 919 828 6775",
    "sg:postcode":"27607",
    "sg:province":"NC",
    "sg:tags":[
        "attorney",
        "practice"
    ],
    "wof:name":"Johnson & Johnson Pa",
    "wof:placetype":"venue"
},
  "geometry": {"coordinates":[-78.67092100000001,35.800664],"type":"Point"}
}