{
  "type": "Feature",
  "properties": {
    "addr:full":"720 Upper Glady Fork Rd Candler NC 28715",
    "addr:housenumber":"720",
    "addr:postcode":"28715",
    "addr:street":"Upper Glady Fork Rd",
    "iso:country":"US",
    "sg:address":"720 Upper Glady Fork Rd",
    "sg:city":"Candler",
    "sg:classifiers":[
        {
            "category":"Professional",
            "type":"Services"
        }
    ],
    "sg:phone":"+1 828 667 8590",
    "sg:postcode":"28715",
    "sg:province":"NC",
    "wof:name":"Serranolee Spanish Translator",
    "wof:placetype":"venue"
},
  "geometry": {"coordinates":[-82.717203,35.488602],"type":"Point"}
}