{
  "type": "Feature",
  "properties": {
    "iso:country":"US",
    "sg:address":"6345 Albemarle Rd",
    "sg:city":"Charlotte",
    "sg:classifiers":[
        {
            "category":"Shopping",
            "subcategory":"Beauty & Cosmetics",
            "type":"Retail Goods"
        },
        {
            "category":"Personal",
            "subcategory":"Barber",
            "type":"Services"
        },
        {
            "category":"Personal",
            "subcategory":"Beauty Salon",
            "type":"Services"
        }
    ],
    "sg:phone":"+1 704 569 4222",
    "sg:postcode":"28212",
    "sg:province":"NC",
    "sg:tags":[
        "equipment",
        "perfume",
        "salons-equipment",
        "supply"
    ],
    "wof:name":"Beauty Plus",
    "wof:placetype":"venue"
},
  "geometry": {"coordinates":[-80.737128,35.20302],"type":"Point"}
}