{
  "type": "Feature",
  "properties": {
    "iso:country":"US",
    "sg:address":"1616 Sunset Ave",
    "sg:city":"Rocky Mount",
    "sg:classifiers":[
        {
            "category":"Personal",
            "subcategory":"Piercing",
            "type":"Services"
        }
    ],
    "sg:phone":"+1 252 977 2639",
    "sg:postcode":"27804",
    "sg:province":"NC",
    "sg:tags":[
        "body"
    ],
    "wof:name":"Culture Shock",
    "wof:placetype":"venue"
},
  "geometry": {"coordinates":[-77.817695,35.948886],"type":"Point"}
}