{
  "type": "Feature",
  "properties": {
    "iso:country":"US",
    "sg:address":"118 E Charles St",
    "sg:city":"Matthews",
    "sg:classifiers":[
        {
            "category":"Retail",
            "subcategory":"Portrait Studio",
            "type":"Services"
        }
    ],
    "sg:phone":"+1 704 847 9634",
    "sg:postcode":"28105",
    "sg:province":"NC",
    "sg:tags":[
        "photographer"
    ],
    "wof:name":"Portrait Gallery",
    "wof:placetype":"venue"
},
  "geometry": {"coordinates":[-80.721199,35.116785],"type":"Point"}
}