{
  "type": "Feature",
  "properties": {
    "addr:full":"41 J S Stevens Ln Turkey NC 28393",
    "addr:housenumber":"41",
    "addr:postcode":"28393",
    "addr:street":"J S Stevens Ln",
    "iso:country":"US",
    "sg:address":"41 J S Stevens Ln",
    "sg:city":"Turkey",
    "sg:classifiers":[
        {
            "category":"Retail",
            "subcategory":"Repair Shop",
            "type":"Services"
        }
    ],
    "sg:phone":"+1 910 592 4065",
    "sg:postcode":"28393",
    "sg:province":"NC",
    "sg:tags":[
        "welding"
    ],
    "wof:name":"John's Welding & Fabrication",
    "wof:placetype":"venue"
},
  "geometry": {"coordinates":[-78.209155,34.985719],"type":"Point"}
}