{
  "type": "Feature",
  "properties": {
    "addr:full":"6101 Sardis Rd Charlotte NC 28270",
    "addr:housenumber":"6101",
    "addr:postcode":"28270",
    "addr:street":"Sardis Rd",
    "iso:country":"US",
    "sg:address":"6101 Sardis Rd",
    "sg:city":"Charlotte",
    "sg:classifiers":[
        {
            "category":"Restaurant",
            "type":"Food & Drink"
        }
    ],
    "sg:phone":"+1 704 364 0876",
    "sg:postcode":"28270",
    "sg:province":"NC",
    "sg:tags":[
        "eating"
    ],
    "wof:name":"Scout Hut",
    "wof:placetype":"venue"
},
  "geometry": {"coordinates":[-80.777193,35.15951],"type":"Point"}
}