{
  "type": "Feature",
  "properties": {
    "iso:country":"US",
    "sg:address":"1820 Capital Blvd",
    "sg:city":"Raleigh",
    "sg:classifiers":[
        {
            "category":"Autos & Motor Vehicles",
            "subcategory":"Automobile Sales",
            "type":"Retail Goods"
        }
    ],
    "sg:phone":"+1 919 834 6441",
    "sg:postcode":"27616",
    "sg:province":"NC",
    "sg:tags":[
        "car",
        "dealer"
    ],
    "wof:name":"Bobby Murray Chevrolet",
    "wof:placetype":"venue"
},
  "geometry": {"coordinates":[-78.616878,35.805312],"type":"Point"}
}