{
  "type": "Feature",
  "properties": {
    "addr:full":"3510 Springs Rd NE Hickory NC 28601",
    "addr:housenumber":"3510",
    "addr:postcode":"28601",
    "addr:street":"Springs Rd Ne",
    "iso:country":"US",
    "sg:address":"3510 Springs Rd NE",
    "sg:city":"Hickory",
    "sg:classifiers":[
        {
            "category":"Restaurant",
            "type":"Food & Drink"
        }
    ],
    "sg:phone":"+1 828 441 0993",
    "sg:postcode":"28601",
    "sg:province":"NC",
    "sg:tags":[
        "eating"
    ],
    "wof:name":"Roadside Grill",
    "wof:placetype":"venue"
},
  "geometry": {"coordinates":[-81.268148,35.76476],"type":"Point"}
}