{
  "type": "Feature",
  "properties": {
    "addr:full":"349 Sunset Ave Asheboro NC 27203",
    "addr:housenumber":"349",
    "addr:postcode":"27203",
    "addr:street":"Sunset Ave",
    "iso:country":"US",
    "sg:address":"349 Sunset Ave",
    "sg:city":"Asheboro",
    "sg:classifiers":[
        {
            "category":"Social Services",
            "subcategory":"Child Care",
            "type":"Services"
        }
    ],
    "sg:phone":"+1 336 629 2128",
    "sg:postcode":"27203",
    "sg:province":"NC",
    "sg:tags":[
        "organization",
        "nonprofit"
    ],
    "wof:name":"Randolph County Partnership",
    "wof:placetype":"venue"
},
  "geometry": {"coordinates":[-79.81811399999999,35.705776],"type":"Point"}
}