{
  "type": "Feature",
  "properties": {
    "addr:full":"319 Court Sq Sanford NC 27330",
    "addr:housenumber":"319",
    "addr:postcode":"27330",
    "addr:street":"Court Sq",
    "iso:country":"US",
    "sg:address":"319 Court Sq",
    "sg:city":"Sanford",
    "sg:classifiers":[
        {
            "category":"Restaurant",
            "type":"Food & Drink"
        }
    ],
    "sg:phone":"+1 919 774 6733",
    "sg:postcode":"27330",
    "sg:province":"NC",
    "wof:name":"Burger King",
    "wof:placetype":"venue"
},
  "geometry": {"coordinates":[-79.163088,35.46601],"type":"Point"}
}