{
  "type": "Feature",
  "properties": {
    "addr:full":"185 Summit Square Blvd Winston Salem NC 27105",
    "addr:housenumber":"185",
    "addr:postcode":"27105",
    "addr:street":"Summit Square Blvd",
    "iso:country":"US",
    "sg:address":"185 Summit Square Blvd",
    "sg:city":"Winston Salem",
    "sg:classifiers":[
        {
            "category":"Food & Beverages",
            "subcategory":"Liquor & Beverages",
            "type":"Retail Goods"
        }
    ],
    "sg:phone":"+1 336 788 7141",
    "sg:postcode":"27105",
    "sg:province":"NC",
    "wof:name":"Forsyth Municipal ABC Board",
    "wof:placetype":"venue"
},
  "geometry": {"coordinates":[-80.274415,36.189545],"type":"Point"}
}