{
  "type": "Feature",
  "properties": {
    "addr:full":"206 Westwood Shopping Center Fayetteville NC 28314",
    "addr:housenumber":"206",
    "addr:postcode":"28314",
    "addr:street":"Westwood Shopping Center",
    "iso:country":"US",
    "sg:address":"206 Westwood Shopping Center",
    "sg:city":"Fayetteville",
    "sg:classifiers":[
        {
            "category":"Banks & Credit Unions",
            "subcategory":"Bank",
            "type":"Services"
        }
    ],
    "sg:phone":"+1 910 864 4198",
    "sg:postcode":"28314",
    "sg:province":"NC",
    "sg:tags":[
        "personal",
        "institution"
    ],
    "wof:name":"Advance America",
    "wof:placetype":"venue"
},
  "geometry": {"coordinates":[-78.95310499999999,35.066811],"type":"Point"}
}