{
  "type": "Feature",
  "properties": {
    "iso:country":"US",
    "sg:address":"607 E Elm St",
    "sg:city":"Graham",
    "sg:classifiers":[
        {
            "category":"Organizations",
            "subcategory":"Religious Organization",
            "type":"Services"
        }
    ],
    "sg:phone":"+1   ",
    "sg:postcode":"27253",
    "sg:province":"NC",
    "wof:name":"United True Vine Pentecostal",
    "wof:placetype":"venue"
},
  "geometry": {"coordinates":[-79.38852799999999,36.075146],"type":"Point"}
}