{
  "type": "Feature",
  "properties": {
    "iso:country":"US",
    "sg:address":"132 N Main St",
    "sg:city":"Salisbury",
    "sg:classifiers":[
        {
            "category":"Government",
            "subcategory":"Office",
            "type":"Public Place"
        }
    ],
    "sg:phone":"+1 704 638 5314",
    "sg:postcode":"28144",
    "sg:province":"NC",
    "sg:tags":[
        "village"
    ],
    "wof:name":"Salisbury Telecommunications",
    "wof:placetype":"venue"
},
  "geometry": {"coordinates":[-80.469139,35.668044],"type":"Point"}
}