{
  "type": "Feature",
  "properties": {
    "addr:full":"400 Broadpointe Dr Fletcher NC 28732",
    "addr:housenumber":"400",
    "addr:postcode":"28732",
    "addr:street":"Broadpointe Dr",
    "iso:country":"US",
    "sg:address":"400 Broadpointe Dr",
    "sg:city":"Fletcher",
    "sg:classifiers":[
        {
            "category":"Manufacturing",
            "subcategory":"Paper Products",
            "type":"Manufacturing & Wholesale Goods"
        }
    ],
    "sg:phone":"+1 828 651 4800",
    "sg:postcode":"28732",
    "sg:province":"NC",
    "sg:tags":[
        "label"
    ],
    "sg:website":"www.raflatac.com",
    "wof:name":"UPM-Raflatac Inc",
    "wof:placetype":"venue"
},
  "geometry": {"coordinates":[-82.550543,35.421243],"type":"Point"}
}