{
  "type": "Feature",
  "properties": {
    "addr:full":"5265 Hornes Church Rd Wilson NC 27896",
    "addr:housenumber":"5265",
    "addr:postcode":"27896",
    "addr:street":"Hornes Church Rd",
    "iso:country":"US",
    "sg:address":"5265 Hornes Church Rd",
    "sg:city":"Wilson",
    "sg:classifiers":[
        {
            "category":"Shopping",
            "subcategory":"Gifts & Souvenirs",
            "type":"Retail Goods"
        }
    ],
    "sg:phone":"+1 252 293 1291",
    "sg:postcode":"27896",
    "sg:province":"NC",
    "sg:tags":[
        "shop"
    ],
    "wof:name":"Rainbow Gift Shop",
    "wof:placetype":"venue"
},
  "geometry": {"coordinates":[-77.951814,35.796008],"type":"Point"}
}