{
  "type": "Feature",
  "properties": {
    "addr:full":"519 2nd Ave SW Hickory NC 28602",
    "addr:housenumber":"519",
    "addr:postcode":"28602",
    "addr:street":"2Nd Ave Sw",
    "iso:country":"US",
    "sg:address":"519 2nd Ave SW",
    "sg:city":"Hickory",
    "sg:classifiers":[
        {
            "category":"Wholesale",
            "subcategory":"Plants",
            "type":"Manufacturing & Wholesale Goods"
        }
    ],
    "sg:phone":"+1 828 322 7641",
    "sg:postcode":"28602",
    "sg:province":"NC",
    "sg:tags":[
        "supply"
    ],
    "wof:name":"Jacks Wholsale",
    "wof:placetype":"venue"
},
  "geometry": {"coordinates":[-81.346885,35.729906],"type":"Point"}
}