{
  "type": "Feature",
  "properties": {
    "addr:full":"84 Palmer Sloan Rd Sanford NC 27332",
    "addr:housenumber":"84",
    "addr:postcode":"27332",
    "addr:street":"Palmer Sloan Rd",
    "iso:country":"US",
    "sg:address":"84 Palmer Sloan Rd",
    "sg:city":"Sanford",
    "sg:classifiers":[
        {
            "category":"Food & Beverages",
            "subcategory":"Fruits & Vegetables",
            "type":"Retail Goods"
        }
    ],
    "sg:phone":"+1 919 258 6632",
    "sg:postcode":"27332",
    "sg:province":"NC",
    "sg:tags":[
        "produce"
    ],
    "wof:name":"Broadway Produce Farms",
    "wof:placetype":"venue"
},
  "geometry": {"coordinates":[-79.074804,35.447836],"type":"Point"}
}