{
  "type": "Feature",
  "properties": {
    "iso:country":"US",
    "sg:address":"2230 Farmington Dr",
    "sg:city":"Chapel Hill",
    "sg:classifiers":[
        {
            "category":"Social Services",
            "subcategory":"Adult Care",
            "type":"Services"
        }
    ],
    "sg:phone":"+1 919 929 5850",
    "sg:postcode":"27517",
    "sg:province":"NC",
    "sg:tags":[
        "home",
        "residential"
    ],
    "sg:website":"www.assisted.com",
    "wof:name":"Alterra Clare Bridge",
    "wof:placetype":"venue"
},
  "geometry": {"coordinates":[-78.98515399999999,35.908332],"type":"Point"}
}