{
  "type": "Feature",
  "properties": {
    "iso:country":"US",
    "sg:address":"63 Rector Rd",
    "sg:city":"Weaverville",
    "sg:classifiers":[
        {
            "category":"Shopping",
            "type":"Retail Goods"
        }
    ],
    "sg:phone":"+1 828 255 0844",
    "sg:postcode":"28787",
    "sg:province":"NC",
    "sg:tags":[
        "typewriter"
    ],
    "wof:name":"A & A Business Machines",
    "wof:placetype":"venue"
},
  "geometry": {"coordinates":[-82.472674,35.676565],"type":"Point"}
}