{
  "type": "Feature",
  "properties": {
    "iso:country":"US",
    "sg:address":"2144 Page Rd",
    "sg:city":"Durham",
    "sg:classifiers":[
        {
            "category":"Freight",
            "type":"Transportation"
        }
    ],
    "sg:phone":"+1 919 957 1650",
    "sg:postcode":"27703",
    "sg:province":"NC",
    "sg:tags":[
        "commercial",
        "storage"
    ],
    "wof:name":"Brassfield Self Storage",
    "wof:placetype":"venue"
},
  "geometry": {"coordinates":[-78.820857,35.933944],"type":"Point"}
}