{
  "type": "Feature",
  "properties": {
    "addr:full":"601 Halifax St Sanford NC 27330",
    "addr:housenumber":"601",
    "addr:postcode":"27330",
    "addr:street":"Halifax St",
    "iso:country":"US",
    "sg:address":"601 Halifax St",
    "sg:city":"Sanford",
    "sg:classifiers":[
        {
            "category":"Professional",
            "type":"Services"
        }
    ],
    "sg:phone":"+1 919 776 9321",
    "sg:postcode":"27330",
    "sg:province":"NC",
    "wof:name":"Post Kitchen & Bath Inc",
    "wof:placetype":"venue"
},
  "geometry": {"coordinates":[-79.198201,35.481528],"type":"Point"}
}