{
  "type": "Feature",
  "properties": {
    "addr:full":"7832 Thompson Mill Rd Wake Forest NC 27587",
    "addr:housenumber":"7832",
    "addr:postcode":"27587",
    "addr:street":"Thompson Mill Rd",
    "iso:country":"US",
    "sg:address":"7832 Thompson Mill Rd",
    "sg:city":"Wake Forest",
    "sg:classifiers":[
        {
            "category":"Building & Trades",
            "subcategory":"Construction",
            "type":"Services"
        }
    ],
    "sg:phone":"+1 919 570 3001",
    "sg:postcode":"27587",
    "sg:province":"NC",
    "sg:tags":[
        "roofing",
        "contractor"
    ],
    "wof:name":"Aboveboard Roofing",
    "wof:placetype":"venue"
},
  "geometry": {"coordinates":[-78.556522,35.992948],"type":"Point"}
}