{
  "type": "Feature",
  "properties": {
    "addr:full":"4881 Hampton Rd Clemmons NC 27012",
    "addr:housenumber":"4881",
    "addr:postcode":"27012",
    "addr:street":"Hampton Rd",
    "iso:country":"US",
    "sg:address":"4881 Hampton Rd",
    "sg:city":"Clemmons",
    "sg:classifiers":[
        {
            "category":"Professional",
            "subcategory":"Business Services",
            "type":"Services"
        }
    ],
    "sg:phone":"+1 336 778 2917",
    "sg:postcode":"27012",
    "sg:province":"NC",
    "sg:tags":[
        "fund",
        "promotion",
        "raising"
    ],
    "wof:name":"Ray Flynn Promotions",
    "wof:placetype":"venue"
},
  "geometry": {"coordinates":[-80.37156299999999,35.992159],"type":"Point"}
}