{
  "type": "Feature",
  "properties": {
    "iso:country":"US",
    "sg:address":"415 Chunns Cove Rd",
    "sg:city":"Asheville",
    "sg:classifiers":[
        {
            "category":"Professional",
            "subcategory":"Engineering",
            "type":"Services"
        }
    ],
    "sg:phone":"+1   ",
    "sg:postcode":"28805",
    "sg:province":"NC",
    "wof:name":"Aztek Engineering & Surveying",
    "wof:placetype":"venue"
},
  "geometry": {"coordinates":[-82.525173,35.611846],"type":"Point"}
}