{
  "type": "Feature",
  "properties": {
    "addr:full":"5108 Reagan Dr Charlotte NC 28206",
    "addr:housenumber":"5108",
    "addr:postcode":"28206",
    "addr:street":"Reagan Dr",
    "iso:country":"US",
    "sg:address":"5108 Reagan Dr",
    "sg:city":"Charlotte",
    "sg:classifiers":[
        {
            "category":"Insurance",
            "subcategory":"Life Insurance",
            "type":"Services"
        }
    ],
    "sg:phone":"+1 704 598 4853",
    "sg:postcode":"28206",
    "sg:province":"NC",
    "sg:tags":[
        "consulting",
        "management"
    ],
    "wof:name":"Golden State Mutl Lf Insur Co",
    "wof:placetype":"venue"
},
  "geometry": {"coordinates":[-80.797521,35.277317],"type":"Point"}
}