{
  "type": "Feature",
  "properties": {
    "iso:country":"US",
    "sg:address":"4102 Kivett Dr",
    "sg:city":"Jamestown",
    "sg:classifiers":[
        {
            "category":"Autos & Motor Vehicles",
            "subcategory":"Automobile Sales",
            "type":"Retail Goods"
        }
    ],
    "sg:phone":"+1 336 889 8320",
    "sg:postcode":"27282",
    "sg:province":"NC",
    "sg:tags":[
        "car",
        "dealer"
    ],
    "wof:name":"J C Halipilias",
    "wof:placetype":"venue"
},
  "geometry": {"coordinates":[-79.90641599999999,35.959083],"type":"Point"}
}