{
  "type": "Feature",
  "properties": {
    "addr:full":"96 Evans Rd Franklin NC 28734",
    "addr:housenumber":"96",
    "addr:postcode":"nc 28734",
    "addr:street":"Evans Rd",
    "iso:country":"US",
    "sg:address":"96 Evans Rd",
    "sg:city":"Franklin",
    "sg:classifiers":[
        {
            "category":"Professional",
            "subcategory":"Detective & Security Services",
            "type":"Services"
        }
    ],
    "sg:phone":"+1 828 369 2637",
    "sg:postcode":"28734",
    "sg:province":"NC",
    "sg:tags":[
        "information",
        "bureau"
    ],
    "wof:name":"Beeson Refrigeration Service",
    "wof:placetype":"venue"
},
  "geometry": {"coordinates":[-83.300714,35.143112],"type":"Point"}
}