{
  "type": "Feature",
  "properties": {
    "addr:full":"234 N Main St Kernersville NC 27284",
    "addr:housenumber":"234",
    "addr:postcode":"27284",
    "addr:street":"N Main St",
    "iso:country":"US",
    "sg:address":"234 N Main St",
    "sg:city":"Kernersville",
    "sg:classifiers":[
        {
            "category":"Shopping",
            "subcategory":"Clothing, Apparel, & Fashions",
            "type":"Retail Goods"
        }
    ],
    "sg:phone":"+1 336 993 9938",
    "sg:postcode":"27284",
    "sg:province":"NC",
    "wof:name":"Sunshine School Unf & Sup Co",
    "wof:placetype":"venue"
},
  "geometry": {"coordinates":[-80.071349,36.122227],"type":"Point"}
}