{
  "type": "Feature",
  "properties": {
    "addr:full":"1316 Ann St Rockingham NC 28379",
    "addr:housenumber":"1316",
    "addr:postcode":"28379",
    "addr:street":"Ann St",
    "iso:country":"US",
    "sg:address":"1316 Ann St",
    "sg:city":"Rockingham",
    "sg:classifiers":[
        {
            "category":"Shopping",
            "subcategory":"Gifts & Souvenirs",
            "type":"Retail Goods"
        }
    ],
    "sg:phone":"+1 910 997 2420",
    "sg:postcode":"28379",
    "sg:province":"NC",
    "wof:name":"Shady Oak Treasures",
    "wof:placetype":"venue"
},
  "geometry": {"coordinates":[-79.75726299999999,34.946089],"type":"Point"}
}