{
  "type": "Feature",
  "properties": {
    "iso:country":"US",
    "sg:address":"3403 Oak Tree Ln",
    "sg:city":"Liberty",
    "sg:classifiers":[
        {
            "category":"Organizations",
            "subcategory":"Religious Organization",
            "type":"Services"
        }
    ],
    "sg:phone":"+1   ",
    "sg:postcode":"27298",
    "sg:province":"NC",
    "wof:name":"True Gospel Holiness Church",
    "wof:placetype":"venue"
},
  "geometry": {"coordinates":[-79.53625700000001,35.889402],"type":"Point"}
}