{
  "type": "Feature",
  "properties": {
    "addr:full":"2604 Sydney Dr Fayetteville NC 28304",
    "addr:housenumber":"2604",
    "addr:postcode":"28304",
    "addr:street":"Sydney Dr",
    "iso:country":"US",
    "sg:address":"2604 Sydney Dr",
    "sg:city":"Fayetteville",
    "sg:classifiers":[
        {
            "category":"Building & Trades",
            "subcategory":"Construction",
            "type":"Services"
        }
    ],
    "sg:phone":"+1 910 485 7734",
    "sg:postcode":"28304",
    "sg:province":"NC",
    "sg:tags":[
        "house"
    ],
    "wof:name":"1st Choice Builders LLC",
    "wof:placetype":"venue"
},
  "geometry": {"coordinates":[-78.90812200000001,35.032436],"type":"Point"}
}