{
  "type": "Feature",
  "properties": {
    "iso:country":"US",
    "sg:address":"804 Hutch Mountain Rd",
    "sg:city":"Fletcher",
    "sg:classifiers":[
        {
            "category":"Building & Trades",
            "subcategory":"Construction",
            "type":"Services"
        }
    ],
    "sg:phone":"+1 828 687 0593",
    "sg:postcode":"28732",
    "sg:province":"NC",
    "sg:tags":[
        "painter"
    ],
    "wof:name":"Pro-Wash & Paint Co",
    "wof:placetype":"venue"
},
  "geometry": {"coordinates":[-82.463922,35.419001],"type":"Point"}
}