{
  "type": "Feature",
  "properties": {
    "addr:full":"3319 Argyle Ln Greensboro NC 27406",
    "addr:housenumber":"3319",
    "addr:postcode":"27406",
    "addr:street":"Argyle Ln",
    "iso:country":"US",
    "sg:address":"3319 Argyle Ln",
    "sg:city":"Greensboro",
    "sg:classifiers":[
        {
            "category":"Retail",
            "subcategory":"Car Wash",
            "type":"Services"
        }
    ],
    "sg:phone":"+1   ",
    "sg:postcode":"27406",
    "sg:province":"NC",
    "sg:tags":[
        "carwash"
    ],
    "wof:name":"Feel Pressure Power Wash",
    "wof:placetype":"venue"
},
  "geometry": {"coordinates":[-79.810227,36.009582],"type":"Point"}
}