{
  "type": "Feature",
  "properties": {
    "addr:full":"1905 Chapel Hill Rd Durham NC 27707",
    "addr:housenumber":"1905",
    "addr:postcode":"27707",
    "addr:street":"Chapel Hill Rd",
    "iso:country":"US",
    "sg:address":"1905 Chapel Hill Rd",
    "sg:city":"Durham",
    "sg:classifiers":[
        {
            "category":"Insurance",
            "subcategory":"Insurance Agent",
            "type":"Services"
        }
    ],
    "sg:phone":"+1 919 493 4422",
    "sg:postcode":"27707",
    "sg:province":"NC",
    "wof:name":"Triangle Insurance Agency",
    "wof:placetype":"venue"
},
  "geometry": {"coordinates":[-78.92505300000001,35.988657],"type":"Point"}
}