{
  "type": "Feature",
  "properties": {
    "addr:full":"340 Meadow Springs Rd Seagrove NC 27341",
    "addr:housenumber":"340",
    "addr:postcode":"27341",
    "addr:street":"Meadow Springs Rd",
    "iso:country":"US",
    "sg:address":"340 Meadow Springs Rd",
    "sg:city":"Seagrove",
    "sg:classifiers":[
        {
            "category":"Professional",
            "subcategory":"Engineering",
            "type":"Services"
        }
    ],
    "sg:phone":"+1   ",
    "sg:postcode":"27341",
    "sg:province":"NC",
    "sg:tags":[
        "bus",
        "consulting",
        "management"
    ],
    "wof:name":"Saunders Randy Radco",
    "wof:placetype":"venue"
},
  "geometry": {"coordinates":[-79.71235900000001,35.510658],"type":"Point"}
}