{
  "type": "Feature",
  "properties": {
    "iso:country":"US",
    "sg:address":"2447 Sylvan Dr",
    "sg:city":"Asheboro",
    "sg:classifiers":[
        {
            "category":"Professional",
            "subcategory":"Management & Consulting",
            "type":"Services"
        }
    ],
    "sg:phone":"+1   ",
    "sg:postcode":"27203",
    "sg:province":"NC",
    "sg:tags":[
        "business"
    ],
    "wof:name":"Its Leather Inc",
    "wof:placetype":"venue"
},
  "geometry": {"coordinates":[-79.72314799999999,35.719622],"type":"Point"}
}