{
  "type": "Feature",
  "properties": {
    "addr:full":"6108 Old Mount Holly Rd Charlotte NC 28208",
    "addr:housenumber":"6108",
    "addr:postcode":"28208",
    "addr:street":"Old Mount Holly Rd",
    "iso:country":"US",
    "sg:address":"6108 Old Mount Holly Rd",
    "sg:city":"Charlotte",
    "sg:classifiers":[
        {
            "category":"Freight",
            "type":"Transportation"
        }
    ],
    "sg:phone":"+1 704 393 3163",
    "sg:postcode":"28208",
    "sg:province":"NC",
    "sg:tags":[
        "trucking"
    ],
    "wof:name":"MTM Transportation",
    "wof:placetype":"venue"
},
  "geometry": {"coordinates":[-80.90741199999999,35.281283],"type":"Point"}
}