{
  "type": "Feature",
  "properties": {
    "addr:full":"9027 Carrington Ridge Dr Raleigh NC 27615",
    "addr:housenumber":"9027",
    "addr:postcode":"27615",
    "addr:street":"Carrington Ridge Dr",
    "iso:country":"US",
    "sg:address":"9027 Carrington Ridge Dr",
    "sg:city":"Raleigh",
    "sg:classifiers":[
        {
            "category":"Real Estate",
            "subcategory":"Real Estate Agent",
            "type":"Services"
        }
    ],
    "sg:phone":"+1 919 844 5005",
    "sg:postcode":"27615",
    "sg:province":"NC",
    "wof:name":"Ray Barker & Associates Inc",
    "wof:placetype":"venue"
},
  "geometry": {"coordinates":[-78.659691,35.906443],"type":"Point"}
}