{
  "type": "Feature",
  "properties": {
    "addr:full":"502 S Fieldcrest Rd Eden NC 27288",
    "addr:housenumber":"502",
    "addr:postcode":"27288",
    "addr:street":"S Fieldcrest Rd",
    "iso:country":"US",
    "sg:address":"502 S Fieldcrest Rd",
    "sg:city":"Eden",
    "sg:classifiers":[
        {
            "category":"Organizations",
            "subcategory":"Religious Organization",
            "type":"Services"
        }
    ],
    "sg:phone":"+1 336 635 1964",
    "sg:postcode":"27288",
    "sg:province":"NC",
    "sg:tags":[
        "church"
    ],
    "wof:name":"Friends Church-Immanuel",
    "wof:placetype":"venue"
},
  "geometry": {"coordinates":[-79.68569599999999,36.508109],"type":"Point"}
}