{
  "type": "Feature",
  "properties": {
    "iso:country":"US",
    "sg:address":"341 Finley Forest Cir",
    "sg:city":"Chapel Hill",
    "sg:classifiers":[
        {
            "category":"Organizations",
            "subcategory":"Community Association",
            "type":"Services"
        }
    ],
    "sg:phone":"+1 919 967 6090",
    "sg:postcode":"27517",
    "sg:province":"NC",
    "sg:tags":[
        "condominium"
    ],
    "wof:name":"Finley Forest Condominium Assn",
    "wof:placetype":"venue"
},
  "geometry": {"coordinates":[-79.00837900000001,35.898452],"type":"Point"}
}