{
  "type": "Feature",
  "properties": {
    "addr:full":"2700 Old Monroe Rd Matthews NC 28104",
    "addr:housenumber":"2700",
    "addr:postcode":"28104",
    "addr:street":"Old Monroe Rd",
    "iso:country":"US",
    "sg:address":"2700 Old Monroe Rd",
    "sg:city":"Matthews",
    "sg:classifiers":[
        {
            "category":"Communications",
            "type":"Services"
        }
    ],
    "sg:phone":"+1 704 821 8659",
    "sg:postcode":"28104",
    "sg:province":"NC",
    "wof:name":"Call Communication Inc",
    "wof:placetype":"venue"
},
  "geometry": {"coordinates":[-80.69602399999999,35.086466],"type":"Point"}
}