{
  "type": "Feature",
  "properties": {
    "addr:full":"189 Ebenezer Forest Rd Garland NC 28441",
    "addr:housenumber":"189",
    "addr:postcode":"28441",
    "addr:street":"Ebenezer Forest Rd",
    "iso:country":"US",
    "sg:address":"189 Ebenezer Forest Rd",
    "sg:city":"Garland",
    "sg:classifiers":[
        {
            "category":"Farming",
            "subcategory":"Farm",
            "type":"Manufacturing & Wholesale Goods"
        }
    ],
    "sg:phone":"+1 910 564 6975",
    "sg:postcode":"28441",
    "sg:province":"NC",
    "wof:name":"Boykin Lake",
    "wof:placetype":"venue"
},
  "geometry": {"coordinates":[-78.43232999999999,34.893533],"type":"Point"}
}