{
  "type": "Feature",
  "properties": {
    "iso:country":"US",
    "sg:address":"315 W Zion Church Rd",
    "sg:city":"Shelby",
    "sg:classifiers":[
        {
            "category":"Building & Trades",
            "subcategory":"Construction",
            "type":"Services"
        }
    ],
    "sg:phone":"+1 704 482 6959",
    "sg:postcode":"28150",
    "sg:province":"NC",
    "sg:tags":[
        "general",
        "contractor"
    ],
    "wof:name":"Carswell Construction",
    "wof:placetype":"venue"
},
  "geometry": {"coordinates":[-81.546728,35.345487],"type":"Point"}
}