{
  "type": "Feature",
  "properties": {
    "iso:country":"US",
    "sg:address":"102 S Lucas Dr",
    "sg:city":"Fort Bragg",
    "sg:classifiers":[
        {
            "category":"Building & Trades",
            "subcategory":"Construction",
            "type":"Services"
        }
    ],
    "sg:phone":"+1 910 960 9543",
    "sg:postcode":"28307",
    "sg:province":"NC",
    "sg:tags":[
        "roofing",
        "contractor"
    ],
    "wof:name":"Consolidated Roofing Syst Inc",
    "wof:placetype":"venue"
},
  "geometry": {"coordinates":[-78.974946,35.140437],"type":"Point"}
}