{
  "type": "Feature",
  "properties": {
    "iso:country":"US",
    "sg:address":"1307 Market St",
    "sg:city":"Wilmington",
    "sg:classifiers":[
        {
            "category":"Education",
            "subcategory":"School",
            "type":"Public Place"
        }
    ],
    "sg:phone":"+1 910 251 6100",
    "sg:postcode":"28401",
    "sg:province":"NC",
    "wof:name":"New Hanover Senior High School",
    "wof:placetype":"venue"
},
  "geometry": {"coordinates":[-77.931618,34.236859],"type":"Point"}
}