{
  "type": "Feature",
  "properties": {
    "iso:country":"US",
    "sg:address":"215 S Trade St",
    "sg:city":"Shelby",
    "sg:classifiers":[
        {
            "category":"Shopping",
            "subcategory":"Computers & Home Electronics",
            "type":"Retail Goods"
        }
    ],
    "sg:phone":"+1 704 487 4311",
    "sg:postcode":"28150",
    "sg:province":"NC",
    "sg:tags":[
        "equipment",
        "dealer"
    ],
    "wof:name":"Pharr Technologies Co",
    "wof:placetype":"venue"
},
  "geometry": {"coordinates":[-81.541082,35.29056],"type":"Point"}
}