{
  "type": "Feature",
  "properties": {
    "addr:full":"5114 E Greensboro Chapel Hill Rd Graham NC 27253",
    "addr:housenumber":"5114",
    "addr:postcode":"27253",
    "addr:street":"E;Chapel Hill Rd",
    "iso:country":"US",
    "sg:address":"5114 E Greensboro Chapel Hill Rd",
    "sg:city":"Graham",
    "sg:classifiers":[
        {
            "category":"Manufacturing",
            "subcategory":"Lumber",
            "type":"Manufacturing & Wholesale Goods"
        }
    ],
    "sg:phone":"+1 336 376 8332",
    "sg:postcode":"27253",
    "sg:province":"NC",
    "sg:tags":[
        "logging"
    ],
    "wof:name":"Braxton Logging",
    "wof:placetype":"venue"
},
  "geometry": {"coordinates":[-79.268749,35.899896],"type":"Point"}
}