{
  "type": "Feature",
  "properties": {
    "iso:country":"US",
    "sg:address":"1705 W Lee St",
    "sg:city":"Greensboro",
    "sg:classifiers":[
        {
            "category":"Professional",
            "subcategory":"Business Services",
            "type":"Services"
        }
    ],
    "sg:phone":"+1 336 299 2292",
    "sg:postcode":"27403",
    "sg:province":"NC",
    "sg:tags":[
        "auctioneer"
    ],
    "wof:name":"King's Auction & Realty Co",
    "wof:placetype":"venue"
},
  "geometry": {"coordinates":[-79.823779,36.060708],"type":"Point"}
}