{
  "type": "Feature",
  "properties": {
    "addr:full":"151 Patton Ave Asheville NC 28801",
    "addr:housenumber":"151",
    "addr:postcode":"28801",
    "addr:street":"Patton Ave",
    "iso:country":"US",
    "sg:address":"151 Patton Ave",
    "sg:city":"Asheville",
    "sg:classifiers":[
        {
            "category":"Government",
            "subcategory":"Office",
            "type":"Public Place"
        }
    ],
    "sg:phone":"+1 828 271 4800",
    "sg:postcode":"28801",
    "sg:province":"NC",
    "wof:name":"National Climatic Ctr",
    "wof:placetype":"venue"
},
  "geometry": {"coordinates":[-82.55691400000001,35.594012],"type":"Point"}
}