{
  "type": "Feature",
  "properties": {
    "addr:full":"4119 Carolina Pointe Ct SW Concord NC 28027",
    "addr:housenumber":"4119",
    "addr:postcode":"28027",
    "addr:street":"Carolina Pointe Ct Sw",
    "iso:country":"US",
    "sg:address":"4119 Carolina Pointe Ct SW",
    "sg:city":"Concord",
    "sg:classifiers":[
        {
            "category":"Professional",
            "subcategory":"Advertising",
            "type":"Services"
        }
    ],
    "sg:phone":"+1 704 795 3800",
    "sg:postcode":"28027",
    "sg:province":"NC",
    "sg:tags":[
        "mail"
    ],
    "wof:name":"Money Mailer Inc",
    "wof:placetype":"venue"
},
  "geometry": {"coordinates":[-80.649203,35.353947],"type":"Point"}
}