{
  "type": "Feature",
  "properties": {
    "addr:full":"8254 Smith Rd Kannapolis NC 28081",
    "addr:housenumber":"8254",
    "addr:postcode":"28081",
    "addr:street":"Smith Rd",
    "iso:country":"US",
    "sg:address":"8254 Smith Rd",
    "sg:city":"Kannapolis",
    "sg:classifiers":[
        {
            "category":"Taxi",
            "type":"Transportation"
        }
    ],
    "sg:phone":"+1 704 938 5440",
    "sg:postcode":"28081",
    "sg:province":"NC",
    "sg:tags":[
        "taxicab"
    ],
    "wof:name":"Tj Taxi",
    "wof:placetype":"venue"
},
  "geometry": {"coordinates":[-80.67871700000001,35.528308],"type":"Point"}
}