{
  "type": "Feature",
  "properties": {
    "iso:country":"US",
    "sg:address":"409 College Dr",
    "sg:city":"Raeford",
    "sg:classifiers":[
        {
            "category":"Retail",
            "subcategory":"Auto Repair",
            "type":"Services"
        }
    ],
    "sg:phone":"+1   ",
    "sg:postcode":"28376",
    "sg:province":"NC",
    "sg:tags":[
        "truck",
        "general"
    ],
    "wof:name":"Jacks Auto Service",
    "wof:placetype":"venue"
},
  "geometry": {"coordinates":[-79.241542,34.980256],"type":"Point"}
}