{
  "type": "Feature",
  "properties": {
    "iso:country":"US",
    "sg:address":"5922 Weddington Rd",
    "sg:city":"Monroe",
    "sg:classifiers":[
        {
            "category":"Restaurant",
            "type":"Food & Drink"
        }
    ],
    "sg:phone":"+1 704 684 0188",
    "sg:postcode":"28110",
    "sg:province":"NC",
    "sg:tags":[
        "shop",
        "coffee"
    ],
    "wof:name":"Covenant Coffee",
    "wof:placetype":"venue"
},
  "geometry": {"coordinates":[-80.668757,35.006647],"type":"Point"}
}