{
  "type": "Feature",
  "properties": {
    "addr:full":"230 Williamson St Burlington NC 27215",
    "addr:housenumber":"230",
    "addr:postcode":"27215",
    "addr:street":"Williamson St",
    "iso:country":"US",
    "sg:address":"230 Williamson St",
    "sg:city":"Burlington",
    "sg:classifiers":[
        {
            "category":"Professional",
            "type":"Services"
        }
    ],
    "sg:phone":"+1 336 226 1046",
    "sg:postcode":"27215",
    "sg:province":"NC",
    "sg:tags":[
        "establishment"
    ],
    "wof:name":"Office",
    "wof:placetype":"venue"
},
  "geometry": {"coordinates":[-79.42134,36.075867],"type":"Point"}
}