{
  "type": "Feature",
  "properties": {
    "iso:country":"US",
    "sg:address":"2505 Rockett Ln",
    "sg:city":"Morganton",
    "sg:classifiers":[
        {
            "category":"Building & Trades",
            "subcategory":"Electrical",
            "type":"Services"
        }
    ],
    "sg:phone":"+1 828 433 1804",
    "sg:postcode":"28655",
    "sg:province":"NC",
    "sg:tags":[
        "electrical",
        "contractor"
    ],
    "wof:name":"John Rockett Electric",
    "wof:placetype":"venue"
},
  "geometry": {"coordinates":[-81.643373,35.739522],"type":"Point"}
}