{
  "type": "Feature",
  "properties": {
    "iso:country":"US",
    "sg:address":"810 Wicker St",
    "sg:city":"Burlington",
    "sg:classifiers":[
        {
            "category":"Recreation",
            "type":"Entertainment"
        }
    ],
    "sg:phone":"+1 336 222 5049",
    "sg:postcode":"27217",
    "sg:province":"NC",
    "sg:tags":[
        "hall",
        "auditorium"
    ],
    "wof:name":"Burlington Elmira Comm Ctr",
    "wof:placetype":"venue"
},
  "geometry": {"coordinates":[-79.44362099999999,36.107075],"type":"Point"}
}