{
  "type": "Feature",
  "properties": {
    "iso:country":"US",
    "sg:address":"9000 Dodsons Cros",
    "sg:city":"Chapel Hill",
    "sg:classifiers":[
        {
            "category":"Retail",
            "subcategory":"Animal Services",
            "type":"Services"
        }
    ],
    "sg:phone":"+1 919 929 3092",
    "sg:postcode":"27514",
    "sg:province":"NC",
    "sg:tags":[
        "pet"
    ],
    "sg:website":"www.wereabouthorses.com",
    "wof:name":"Montross Horse Training Center",
    "wof:placetype":"venue"
},
  "geometry": {"coordinates":[-79.046204,35.9352],"type":"Point"}
}