{
  "type": "Feature",
  "properties": {
    "iso:country":"US",
    "sg:address":"3210 Union Rd",
    "sg:city":"Gastonia",
    "sg:classifiers":[
        {
            "category":"Sports & Exercise",
            "subcategory":"Gym",
            "type":"Entertainment"
        }
    ],
    "sg:phone":"+1 704 865 2193",
    "sg:postcode":"28056",
    "sg:province":"NC",
    "sg:tags":[
        "club",
        "studio",
        "health",
        "gymnasium"
    ],
    "sg:website":"http://www.ymca.net",
    "wof:name":"YMCA",
    "wof:placetype":"venue"
},
  "geometry": {"coordinates":[-81.165223,35.209429],"type":"Point"}
}