{
  "type": "Feature",
  "properties": {
    "iso:country":"US",
    "sg:address":"5160 US Hwy 70",
    "sg:city":"Morehead City",
    "sg:classifiers":[
        {
            "category":"Recreation",
            "type":"Entertainment"
        }
    ],
    "sg:phone":"+1 252 247 4444",
    "sg:postcode":"28557",
    "sg:province":"NC",
    "sg:tags":[
        "skating",
        "rink"
    ],
    "wof:name":"Sportsworld",
    "wof:placetype":"venue"
},
  "geometry": {"coordinates":[-76.80581599999999,34.737955],"type":"Point"}
}