{
  "type": "Feature",
  "properties": {
    "iso:country":"US",
    "sg:address":"3155 State Hwy 210 S",
    "sg:city":"Bunnlevel",
    "sg:classifiers":[
        {
            "category":"Manufacturing",
            "subcategory":"Glass & Minerals",
            "type":"Manufacturing & Wholesale Goods"
        }
    ],
    "sg:phone":"+1 910 893 8308",
    "sg:postcode":"28323",
    "sg:province":"NC",
    "sg:tags":[
        "stone",
        "cut",
        "product"
    ],
    "wof:name":"Hanson Gardner Plant Inc",
    "wof:placetype":"venue"
},
  "geometry": {"coordinates":[-78.843762,35.359265],"type":"Point"}
}