{
  "type": "Feature",
  "properties": {
    "iso:country":"US",
    "sg:address":"6602 Beach Dr SW",
    "sg:city":"Ocean Isle Beach",
    "sg:classifiers":[
        {
            "category":"Manufacturing",
            "subcategory":"Signs",
            "type":"Manufacturing & Wholesale Goods"
        }
    ],
    "sg:phone":"+1 910 579 9101",
    "sg:postcode":"28469",
    "sg:province":"NC",
    "sg:tags":[
        "specialty",
        "mfg"
    ],
    "wof:name":"Rite Signs",
    "wof:placetype":"venue"
},
  "geometry": {"coordinates":[-78.45785100000001,33.90028],"type":"Point"}
}