{
  "type": "Feature",
  "properties": {
    "iso:country":"US",
    "sg:address":"421 Fayetteville Street Mall",
    "sg:city":"Raleigh",
    "sg:classifiers":[
        {
            "category":"Travel",
            "subcategory":"Travel Agent",
            "type":"Entertainment"
        }
    ],
    "sg:phone":"+1 919 834 5900",
    "sg:postcode":"27601",
    "sg:province":"NC",
    "sg:tags":[
        "information",
        "tourist"
    ],
    "wof:name":"Greater Raleigh Convention Bur",
    "wof:placetype":"venue"
},
  "geometry": {"coordinates":[-78.63934,35.774403],"type":"Point"}
}