{
  "type": "Feature",
  "properties": {
    "addr:full":"3722 Durham Rd Raleigh NC 27614",
    "addr:housenumber":"3722",
    "addr:postcode":"27614",
    "addr:street":"Durham Rd",
    "iso:country":"US",
    "sg:address":"3722 Durham Rd",
    "sg:city":"Raleigh",
    "sg:classifiers":[
        {
            "category":"Building & Trades",
            "subcategory":"Landscaping Services",
            "type":"Services"
        }
    ],
    "sg:phone":"+1 919 870 9771",
    "sg:postcode":"27614",
    "sg:province":"NC",
    "wof:name":"Area Mulch & Soils",
    "wof:placetype":"venue"
},
  "geometry": {"coordinates":[-78.65224000000001,35.984334],"type":"Point"}
}