{
  "type": "Feature",
  "properties": {
    "addr:full":"603 Country Club Dr Fayetteville NC 28301",
    "addr:housenumber":"603",
    "addr:postcode":"28301",
    "addr:street":"Country Club Dr",
    "iso:country":"US",
    "sg:address":"603 Country Club Dr",
    "sg:city":"Fayetteville",
    "sg:classifiers":[
        {
            "category":"Education",
            "subcategory":"College",
            "type":"Public Place"
        }
    ],
    "sg:phone":"+1   ",
    "sg:postcode":"28301",
    "sg:province":"NC",
    "wof:name":"Fayetteville Cape Center",
    "wof:placetype":"venue"
},
  "geometry": {"coordinates":[-78.890004,35.104108],"type":"Point"}
}