{
  "type": "Feature",
  "properties": {
    "iso:country":"US",
    "sg:address":"3385 US Hwy 441",
    "sg:city":"Whittier",
    "sg:classifiers":[
        {
            "category":"Food & Beverages",
            "subcategory":"Groceries & Convenience Stores",
            "type":"Retail Goods"
        }
    ],
    "sg:phone":"+1 828 497 0401",
    "sg:postcode":"28789",
    "sg:province":"NC",
    "wof:name":"Wintex Corp",
    "wof:placetype":"venue"
},
  "geometry": {"coordinates":[-83.27419399999999,35.387121],"type":"Point"}
}