{
  "type": "Feature",
  "properties": {
    "addr:full":"1809 W Front St Statesville NC 28677",
    "addr:housenumber":"1809",
    "addr:postcode":"28677",
    "addr:street":"W Front St",
    "iso:country":"US",
    "sg:address":"1809 W Front St",
    "sg:city":"Statesville",
    "sg:classifiers":[
        {
            "category":"Autos & Motor Vehicles",
            "subcategory":"Boat Sales",
            "type":"Retail Goods"
        },
        {
            "category":"Autos & Motor Vehicles",
            "subcategory":"Motorcycle Sales",
            "type":"Retail Goods"
        }
    ],
    "sg:phone":"+1 704 872 1658",
    "sg:postcode":"28677",
    "sg:province":"NC",
    "sg:tags":[
        "sales",
        "dealer"
    ],
    "wof:name":"Honda Yamaha of Statesville",
    "wof:placetype":"venue"
},
  "geometry": {"coordinates":[-80.915325,35.785642],"type":"Point"}
}