{
  "type": "Feature",
  "properties": {
    "addr:full":"1097 Flat Rock Church Rd Louisburg NC 27549",
    "addr:housenumber":"1097",
    "addr:postcode":"27549",
    "addr:street":"Flat Rock Church Rd",
    "iso:country":"US",
    "sg:address":"1097 Flat Rock Church Rd",
    "sg:city":"Louisburg",
    "sg:classifiers":[
        {
            "category":"Building & Trades",
            "subcategory":"Construction",
            "type":"Services"
        }
    ],
    "sg:phone":"+1 919 556 1763",
    "sg:postcode":"27549",
    "sg:province":"NC",
    "sg:tags":[
        "contractor",
        "general"
    ],
    "wof:name":"Wiggins Builders Inc",
    "wof:placetype":"venue"
},
  "geometry": {"coordinates":[-78.386002,36.019131],"type":"Point"}
}