{
  "type": "Feature",
  "properties": {
    "iso:country":"US",
    "sg:address":"2610 South Blvd",
    "sg:city":"Charlotte",
    "sg:classifiers":[
        {
            "category":"Retail",
            "subcategory":"Repair Shop",
            "type":"Services"
        }
    ],
    "sg:phone":"+1 704 523 0012",
    "sg:postcode":"28209",
    "sg:province":"NC",
    "sg:tags":[
        "equipment",
        "photographic"
    ],
    "wof:name":"Southern Photo Technical Servi",
    "wof:placetype":"venue"
},
  "geometry": {"coordinates":[-80.866023,35.201482],"type":"Point"}
}