{
  "type": "Feature",
  "properties": {
    "iso:country":"US",
    "sg:address":"4361 Stantonsburg Rd",
    "sg:city":"Greenville",
    "sg:classifiers":[
        {
            "category":"Social Services",
            "subcategory":"Child Care",
            "type":"Services"
        }
    ],
    "sg:phone":"+1   ",
    "sg:postcode":"27834",
    "sg:province":"NC",
    "sg:tags":[
        "day"
    ],
    "wof:name":"Kidsville N C Child Care Ctr",
    "wof:placetype":"venue"
},
  "geometry": {"coordinates":[-77.467831,35.603964],"type":"Point"}
}