{
  "type": "Feature",
  "properties": {
    "addr:full":"304 W Weaver St Carrboro NC 27510",
    "addr:housenumber":"304",
    "addr:postcode":"27510",
    "addr:street":"W Weaver St",
    "iso:country":"US",
    "sg:address":"304 W Weaver St",
    "sg:city":"Carrboro",
    "sg:classifiers":[
        {
            "category":"Professional",
            "subcategory":"Research",
            "type":"Services"
        }
    ],
    "sg:phone":"+1 919 932 1117",
    "sg:postcode":"27510",
    "sg:province":"NC",
    "sg:tags":[
        "market",
        "analysis"
    ],
    "wof:name":"W 5",
    "wof:placetype":"venue"
},
  "geometry": {"coordinates":[-79.07512800000001,35.911257],"type":"Point"}
}