{
  "type": "Feature",
  "properties": {
    "iso:country":"US",
    "sg:address":"1001 Wide Waters Pkwy",
    "sg:city":"Knightdale",
    "sg:classifiers":[
        {
            "category":"Health Services",
            "subcategory":"Optometrist",
            "type":"Services"
        },
        {
            "category":"Shopping",
            "subcategory":"Optical Goods",
            "type":"Retail Goods"
        }
    ],
    "sg:phone":"+1 919 861 2020",
    "sg:postcode":"27545",
    "sg:province":"NC",
    "sg:tags":[
        "lens",
        "eyeglass",
        "contact"
    ],
    "sg:website":"http://ecanc.com",
    "wof:name":"Eye Care Assoc",
    "wof:placetype":"venue"
},
  "geometry": {"coordinates":[-78.505341,35.793251],"type":"Point"}
}