{
  "type": "Feature",
  "properties": {
    "addr:full":"177 Homestead Rd Candler NC 28715",
    "addr:housenumber":"177",
    "addr:postcode":"28715",
    "addr:street":"Homestead Rd",
    "iso:country":"US",
    "sg:address":"177 Homestead Rd",
    "sg:city":"Candler",
    "sg:classifiers":[
        {
            "category":"Organizations",
            "subcategory":"Non-profit Organization",
            "type":"Services"
        }
    ],
    "sg:phone":"+1   ",
    "sg:postcode":"28715",
    "sg:province":"NC",
    "sg:tags":[
        "social"
    ],
    "wof:name":"Ruffed Grouse Society",
    "wof:placetype":"venue"
},
  "geometry": {"coordinates":[-82.650361,35.563479],"type":"Point"}
}