{
  "type": "Feature",
  "properties": {
    "addr:full":"6510 Chapel Hill Rd Raleigh NC 27607",
    "addr:housenumber":"6510",
    "addr:postcode":"27607",
    "addr:street":"Chapel Hill Rd",
    "iso:country":"US",
    "sg:address":"6510 Chapel Hill Rd",
    "sg:city":"Raleigh",
    "sg:classifiers":[
        {
            "category":"Organizations",
            "subcategory":"Professional Association",
            "type":"Services"
        }
    ],
    "sg:phone":"+1 919 233 2033",
    "sg:postcode":"27607",
    "sg:province":"NC",
    "sg:tags":[
        "trade"
    ],
    "wof:name":"Home Bldrs Assc of Raleigh Wak",
    "wof:placetype":"venue"
},
  "geometry": {"coordinates":[-78.73654999999999,35.790072],"type":"Point"}
}