{
  "type": "Feature",
  "properties": {
    "addr:full":"5203 Stardust Dr Durham NC 27712",
    "addr:housenumber":"5203",
    "addr:postcode":"27712",
    "addr:street":"Stardust Dr",
    "iso:country":"US",
    "sg:address":"5203 Stardust Dr",
    "sg:city":"Durham",
    "sg:classifiers":[
        {
            "category":"Bus Charters",
            "type":"Transportation"
        }
    ],
    "sg:phone":"+1 919 477 3170",
    "sg:postcode":"27712",
    "sg:province":"NC",
    "sg:tags":[
        "rental"
    ],
    "wof:name":"Personalized Transporter",
    "wof:placetype":"venue"
},
  "geometry": {"coordinates":[-78.89399,36.084968],"type":"Point"}
}