{
  "type": "Feature",
  "properties": {
    "iso:country":"US",
    "sg:address":"3710 Richlands Hwy",
    "sg:city":"Jacksonville",
    "sg:classifiers":[
        {
            "category":"Building & Trades",
            "subcategory":"Construction",
            "type":"Services"
        }
    ],
    "sg:phone":"+1 910 455 6262",
    "sg:postcode":"28540",
    "sg:province":"NC",
    "sg:tags":[
        "mfg",
        "prefabricated",
        "meta",
        "house"
    ],
    "wof:name":"Newbold Decks & Stor Buildings",
    "wof:placetype":"venue"
},
  "geometry": {"coordinates":[-77.490103,34.7705],"type":"Point"}
}