{
  "type": "Feature",
  "properties": {
    "iso:country":"US",
    "sg:address":"2420 State Hwy 87",
    "sg:city":"Reidsville",
    "sg:classifiers":[
        {
            "category":"Personal",
            "subcategory":"Beauty Salon",
            "type":"Services"
        }
    ],
    "sg:phone":"+1   ",
    "sg:postcode":"27320",
    "sg:province":"NC",
    "sg:tags":[
        "shop"
    ],
    "wof:name":"Styles R US Hair Salon LLC",
    "wof:placetype":"venue"
},
  "geometry": {"coordinates":[-79.641752,36.326195],"type":"Point"}
}