{
  "type": "Feature",
  "properties": {
    "iso:country":"US",
    "sg:address":"1450 Asheville Hwy",
    "sg:city":"Hendersonville",
    "sg:classifiers":[
        {
            "category":"Real Estate",
            "subcategory":"Real Estate Agent",
            "type":"Services"
        }
    ],
    "sg:phone":"+1 828 697 0515",
    "sg:postcode":"28791",
    "sg:province":"NC",
    "wof:name":"Beverly-Hanks & Assoc",
    "wof:placetype":"venue"
},
  "geometry": {"coordinates":[-82.46794199999999,35.328423],"type":"Point"}
}