{
  "type": "Feature",
  "properties": {
    "addr:full":"4944 Wrightsville Ave Wilmington NC 28403",
    "addr:housenumber":"4944",
    "addr:postcode":"28403",
    "addr:street":"Wrightsville Ave",
    "iso:country":"US",
    "sg:address":"4944 Wrightsville Ave",
    "sg:city":"Wilmington",
    "sg:classifiers":[
        {
            "category":"Social Services",
            "subcategory":"Child Care",
            "type":"Services"
        }
    ],
    "sg:phone":"+1   ",
    "sg:postcode":"28403",
    "sg:province":"NC",
    "sg:tags":[
        "day"
    ],
    "wof:name":"Parents Community Preschool",
    "wof:placetype":"venue"
},
  "geometry": {"coordinates":[-77.87643799999999,34.213075],"type":"Point"}
}