{
  "type": "Feature",
  "properties": {
    "addr:full":"3201 Tallia Ct Charlotte NC 28269",
    "addr:housenumber":"3201",
    "addr:postcode":"28269",
    "addr:street":"Tallia Ct",
    "iso:country":"US",
    "sg:address":"3201 Tallia Ct",
    "sg:city":"Charlotte",
    "sg:classifiers":[
        {
            "category":"Wholesale",
            "subcategory":"Non-durable Goods",
            "type":"Manufacturing & Wholesale Goods"
        }
    ],
    "sg:phone":"+1 704 596 2780",
    "sg:postcode":"28269",
    "sg:province":"NC",
    "sg:tags":[
        "interior"
    ],
    "wof:name":"Robin's Nest Artwork",
    "wof:placetype":"venue"
},
  "geometry": {"coordinates":[-80.79308399999999,35.31487],"type":"Point"}
}