{
  "type": "Feature",
  "properties": {
    "addr:full":"56 Rock Pillar Rd Clayton NC 27520",
    "addr:housenumber":"56",
    "addr:postcode":"27520",
    "addr:street":"Rock Pillar Rd",
    "iso:country":"US",
    "sg:address":"56 Rock Pillar Rd",
    "sg:city":"Clayton",
    "sg:classifiers":[
        {
            "category":"Building & Trades",
            "subcategory":"Plumbing",
            "type":"Services"
        }
    ],
    "sg:phone":"+1 919 938 4357",
    "sg:postcode":"27520",
    "sg:province":"NC",
    "sg:tags":[
        "contractor"
    ],
    "wof:name":"Commissioned Heating & Air",
    "wof:placetype":"venue"
},
  "geometry": {"coordinates":[-78.39957099999999,35.552058],"type":"Point"}
}