{
  "type": "Feature",
  "properties": {
    "addr:full":"7 Regional Cir Pinehurst NC 28374",
    "addr:housenumber":"7",
    "addr:postcode":"28374",
    "addr:street":"Regional Cir",
    "iso:country":"US",
    "sg:address":"7 Regional Cir",
    "sg:city":"Pinehurst",
    "sg:classifiers":[
        {
            "category":"Health Services",
            "subcategory":"Doctor",
            "type":"Services"
        }
    ],
    "sg:phone":"+1 910 295 4222",
    "sg:postcode":"28374",
    "sg:province":"NC",
    "sg:tags":[
        "physician",
        "surgeon"
    ],
    "wof:name":"Pinehurst Cardiology Cnsltnts",
    "wof:placetype":"venue"
},
  "geometry": {"coordinates":[-79.453148,35.210981],"type":"Point"}
}