{
  "type": "Feature",
  "properties": {
    "iso:country":"US",
    "sg:address":"4602 Beechcroft Dr",
    "sg:city":"Greensboro",
    "sg:classifiers":[
        {
            "category":"Building & Trades",
            "subcategory":"Construction",
            "type":"Services"
        }
    ],
    "sg:phone":"+1 336 294 6210",
    "sg:postcode":"27407",
    "sg:province":"NC",
    "sg:tags":[
        "home",
        "builder"
    ],
    "wof:name":"Hawthorne Homes",
    "wof:placetype":"venue"
},
  "geometry": {"coordinates":[-79.883278,36.042231],"type":"Point"}
}