{
  "type": "Feature",
  "properties": {
    "addr:full":"1011 Macey Jo Ct Elizabeth City NC 27909",
    "addr:housenumber":"1011",
    "addr:postcode":"27909",
    "addr:street":"Macey Jo Ct",
    "iso:country":"US",
    "sg:address":"1011 Macey Jo Ct",
    "sg:city":"Elizabeth City",
    "sg:classifiers":[
        {
            "category":"Real Estate",
            "subcategory":"Surveying",
            "type":"Services"
        }
    ],
    "sg:phone":"+1 252 335 1097",
    "sg:postcode":"27909",
    "sg:province":"NC",
    "sg:tags":[
        "surveyor"
    ],
    "wof:name":"Henry C Cunningham Forester",
    "wof:placetype":"venue"
},
  "geometry": {"coordinates":[-76.244337,36.311931],"type":"Point"}
}