{
  "type": "Feature",
  "properties": {
    "iso:country":"US",
    "sg:address":"201 Foster St",
    "sg:city":"Durham",
    "sg:classifiers":[
        {
            "category":"Travel",
            "subcategory":"Hotels & Motels",
            "type":"Entertainment"
        }
    ],
    "sg:phone":"+1 919 768 6000",
    "sg:postcode":"27701",
    "sg:province":"NC",
    "sg:website":"www.shanercorp.com",
    "wof:name":"Marriott-Civic Center",
    "wof:placetype":"venue"
},
  "geometry": {"coordinates":[-78.901659,35.998148],"type":"Point"}
}