{
  "type": "Feature",
  "properties": {
    "iso:country":"US",
    "sg:address":"4949 Lake Fisher Rd",
    "sg:city":"Kannapolis",
    "sg:classifiers":[
        {
            "category":"Building & Trades",
            "subcategory":"Construction",
            "type":"Services"
        }
    ],
    "sg:phone":"+1 704 934 2832",
    "sg:postcode":"28083",
    "sg:province":"NC",
    "sg:tags":[
        "house"
    ],
    "wof:name":"Henry Backhoe Mobile Homes",
    "wof:placetype":"venue"
},
  "geometry": {"coordinates":[-80.58037,35.485778],"type":"Point"}
}