{
  "type": "Feature",
  "properties": {
    "iso:country":"US",
    "sg:address":"4405 Old Monroe Rd",
    "sg:city":"Indian Trail",
    "sg:classifiers":[
        {
            "category":"Shopping",
            "subcategory":"Department Store",
            "type":"Retail Goods"
        }
    ],
    "sg:phone":"+1 704 684 0040",
    "sg:postcode":"28079",
    "sg:province":"NC",
    "wof:name":"Bang For Your Buck",
    "wof:placetype":"venue"
},
  "geometry": {"coordinates":[-80.67282299999999,35.065514],"type":"Point"}
}