{
  "type": "Feature",
  "properties": {
    "addr:full":"1348 Charlotte Hwy Fairview NC 28730",
    "addr:housenumber":"1348",
    "addr:postcode":"28730",
    "addr:street":"Charlotte Hwy",
    "iso:country":"US",
    "sg:address":"1348 Charlotte Hwy",
    "sg:city":"Fairview",
    "sg:classifiers":[
        {
            "category":"Banks & Credit Unions",
            "subcategory":"Bank",
            "type":"Services"
        }
    ],
    "sg:phone":"+1 828 628 3585",
    "sg:postcode":"28730",
    "sg:province":"NC",
    "wof:name":"First Citizens Bank",
    "wof:placetype":"venue"
},
  "geometry": {"coordinates":[-82.414832,35.523579],"type":"Point"}
}