{
  "type": "Feature",
  "properties": {
    "addr:full":"103 E Main St Lincolnton NC 28092",
    "addr:housenumber":"103",
    "addr:postcode":"28092",
    "addr:street":"E Main St",
    "iso:country":"US",
    "sg:address":"103 E Main St",
    "sg:city":"Lincolnton",
    "sg:classifiers":[
        {
            "category":"Utilities",
            "subcategory":"Mobile Phone",
            "type":"Services"
        },
        {
            "category":"Utilities",
            "subcategory":"Telephone",
            "type":"Services"
        },
        {
            "category":"Shopping",
            "subcategory":"Mobile Phones",
            "type":"Retail Goods"
        },
        {
            "category":"Manufacturing",
            "subcategory":"Electronics",
            "type":"Manufacturing & Wholesale Goods"
        },
        {
            "category":"Communications",
            "type":"Services"
        }
    ],
    "sg:phone":"+1 704 748 9229",
    "sg:postcode":"28092",
    "sg:province":"NC",
    "sg:tags":[
        "equipment",
        "telecommunications-equipment",
        "system",
        "cellular",
        "supply"
    ],
    "sg:website":"http://www.alltel.com",
    "wof:name":"Alltel Wireless",
    "wof:placetype":"venue"
},
  "geometry": {"coordinates":[-81.257856,35.471058],"type":"Point"}
}