{
  "type": "Feature",
  "properties": {
    "addr:full":"1194 Hendersonville Rd Asheville NC 28803",
    "addr:housenumber":"1194",
    "addr:postcode":"28803",
    "addr:street":"Hendersonville Rd",
    "iso:country":"US",
    "sg:address":"1194 Hendersonville Rd",
    "sg:city":"Asheville",
    "sg:classifiers":[
        {
            "category":"Home & Garden",
            "subcategory":"Building Materials",
            "type":"Retail Goods"
        }
    ],
    "sg:phone":"+1 828 277 7599",
    "sg:postcode":"28803",
    "sg:province":"NC",
    "sg:tags":[
        "glass",
        "window",
        "plate"
    ],
    "sg:website":"www.binswangerglass.com",
    "wof:name":"Binswanger Glass Co",
    "wof:placetype":"venue"
},
  "geometry": {"coordinates":[-82.528649,35.530051],"type":"Point"}
}