{
  "type": "Feature",
  "properties": {
    "iso:country":"US",
    "sg:address":"3203 Waldron Dr",
    "sg:city":"Greensboro",
    "sg:classifiers":[
        {
            "category":"Professional",
            "subcategory":"Employment Agencies",
            "type":"Services"
        }
    ],
    "sg:phone":"+1   ",
    "sg:postcode":"27408",
    "sg:province":"NC",
    "sg:tags":[
        "help",
        "supply"
    ],
    "wof:name":"Brock Aviation LLC",
    "wof:placetype":"venue"
},
  "geometry": {"coordinates":[-79.807675,36.116812],"type":"Point"}
}