{
  "type": "Feature",
  "properties": {
    "addr:full":"289 Byers Dr Hendersonville NC 28792",
    "addr:housenumber":"289",
    "addr:postcode":"28792",
    "addr:street":"Byers Dr",
    "iso:country":"US",
    "sg:address":"289 Byers Dr",
    "sg:city":"Hendersonville",
    "sg:classifiers":[
        {
            "category":"Building & Trades",
            "subcategory":"Landscaping Services",
            "type":"Services"
        }
    ],
    "sg:phone":"+1 828 692 9727",
    "sg:postcode":"28792",
    "sg:province":"NC",
    "sg:tags":[
        "lawn",
        "maintenance",
        "grounds"
    ],
    "wof:name":"Epperson & Son Lawn & Tree",
    "wof:placetype":"venue"
},
  "geometry": {"coordinates":[-82.416297,35.323558],"type":"Point"}
}