{
  "type": "Feature",
  "properties": {
    "addr:full":"100 Timber Ridge Dr Durham NC 27713",
    "addr:housenumber":"100",
    "addr:postcode":"27713",
    "addr:street":"Timber Ridge Dr",
    "iso:country":"US",
    "sg:address":"100 Timber Ridge Dr",
    "sg:city":"Durham",
    "sg:classifiers":[
        {
            "category":"Arts & Performance",
            "subcategory":"Theater",
            "type":"Entertainment"
        }
    ],
    "sg:phone":"+1 919 490 8603",
    "sg:postcode":"27713",
    "sg:province":"NC",
    "wof:name":"Bull City Players",
    "wof:placetype":"venue"
},
  "geometry": {"coordinates":[-78.941592,35.925898],"type":"Point"}
}