{
  "type": "Feature",
  "properties": {
    "iso:country":"US",
    "sg:address":"156 N Jefferson Ave",
    "sg:city":"West Jefferson",
    "sg:classifiers":[
        {
            "category":"Building & Trades",
            "subcategory":"Construction",
            "type":"Services"
        }
    ],
    "sg:phone":"+1 336 877 5464",
    "sg:postcode":"28694",
    "sg:province":"NC",
    "sg:tags":[
        "hanging",
        "contractor"
    ],
    "wof:name":"Luxury Painting",
    "wof:placetype":"venue"
},
  "geometry": {"coordinates":[-81.49258500000001,36.402406],"type":"Point"}
}