{
  "type": "Feature",
  "properties": {
    "iso:country":"US",
    "sg:address":"2843 Jones Franklin Rd",
    "sg:city":"Raleigh",
    "sg:classifiers":[
        {
            "category":"Health Services",
            "subcategory":"Optometrist",
            "type":"Services"
        }
    ],
    "sg:phone":"+1 919 851 9966",
    "sg:postcode":"27606",
    "sg:province":"NC",
    "wof:name":"Bigsby David M Dr Opt OD",
    "wof:placetype":"venue"
},
  "geometry": {"coordinates":[-78.737396,35.7463],"type":"Point"}
}