{
  "type": "Feature",
  "properties": {
    "iso:country":"US",
    "sg:address":"294 Bennet Rd",
    "sg:city":"Goldsboro",
    "sg:classifiers":[
        {
            "category":"Retail",
            "subcategory":"Repair Shop",
            "type":"Services"
        }
    ],
    "sg:phone":"+1   ",
    "sg:postcode":"27530",
    "sg:province":"NC",
    "sg:tags":[
        "waste",
        "cleaning"
    ],
    "wof:name":"EZ Flow Septic Tank & Toil Svc",
    "wof:placetype":"venue"
},
  "geometry": {"coordinates":[-78.174311,35.305791],"type":"Point"}
}