{
  "type": "Feature",
  "properties": {
    "addr:full":"5105 Tulip Dr Fayetteville NC 28304",
    "addr:housenumber":"5105",
    "addr:postcode":"28304",
    "addr:street":"Tulip Dr",
    "iso:country":"US",
    "sg:address":"5105 Tulip Dr",
    "sg:city":"Fayetteville",
    "sg:classifiers":[
        {
            "category":"Autos & Motor Vehicles",
            "subcategory":"Automobile Sales",
            "type":"Retail Goods"
        }
    ],
    "sg:phone":"+1 910 860 8972",
    "sg:postcode":"28304",
    "sg:province":"NC",
    "sg:tags":[
        "used"
    ],
    "wof:name":"Kevins Cars",
    "wof:placetype":"venue"
},
  "geometry": {"coordinates":[-78.964201,35.029327],"type":"Point"}
}