{
  "type": "Feature",
  "properties": {
    "iso:country":"US",
    "sg:address":"109 Conner Dr",
    "sg:city":"Chapel Hill",
    "sg:classifiers":[
        {
            "category":"Health Services",
            "subcategory":"Doctor",
            "type":"Services"
        }
    ],
    "sg:phone":"+1   ",
    "sg:postcode":"27514",
    "sg:province":"NC",
    "sg:tags":[
        "medical"
    ],
    "wof:name":"Chapel Hl Fcial Plstic Surgery",
    "wof:placetype":"venue"
},
  "geometry": {"coordinates":[-79.03035800000001,35.930425],"type":"Point"}
}