{
  "type": "Feature",
  "properties": {
    "iso:country":"US",
    "sg:address":"2325 Market St",
    "sg:city":"Wilmington",
    "sg:classifiers":[
        {
            "category":"Retail",
            "subcategory":"Auto Repair",
            "type":"Services"
        }
    ],
    "sg:phone":"+1   ",
    "sg:postcode":"28403",
    "sg:province":"NC",
    "sg:tags":[
        "general"
    ],
    "wof:name":"Lulu S Garage",
    "wof:placetype":"venue"
},
  "geometry": {"coordinates":[-77.916273,34.238387],"type":"Point"}
}