{
  "type": "Feature",
  "properties": {
    "addr:full":"103 Starmount Dr Fayetteville NC 28311",
    "addr:housenumber":"103",
    "addr:postcode":"28311",
    "addr:street":"Starmount Dr",
    "iso:country":"US",
    "sg:address":"103 Starmount Dr",
    "sg:city":"Fayetteville",
    "sg:classifiers":[
        {
            "category":"Real Estate",
            "subcategory":"Developer",
            "type":"Services"
        }
    ],
    "sg:phone":"+1 910 875 6854",
    "sg:postcode":"28311",
    "sg:province":"NC",
    "sg:tags":[
        "company",
        "land"
    ],
    "wof:name":"KACO Enterprises Inc",
    "wof:placetype":"venue"
},
  "geometry": {"coordinates":[-78.897239,35.106516],"type":"Point"}
}