{
  "type": "Feature",
  "properties": {
    "iso:country":"US",
    "sg:address":"717 Baker Ct",
    "sg:city":"Haw River",
    "sg:classifiers":[
        {
            "category":"Professional",
            "type":"Services"
        }
    ],
    "sg:phone":"+1 336 578 6197",
    "sg:postcode":"27258",
    "sg:province":"NC",
    "wof:name":"Edward H Summey Jr",
    "wof:placetype":"venue"
},
  "geometry": {"coordinates":[-79.334228,36.078728],"type":"Point"}
}