{
  "type": "Feature",
  "properties": {
    "iso:country":"US",
    "sg:address":"1012 Old Spartanburg Rd",
    "sg:city":"Hendersonville",
    "sg:classifiers":[
        {
            "category":"Banks & Credit Unions",
            "subcategory":"Bank",
            "type":"Services"
        }
    ],
    "sg:phone":"+1 828 697 9731",
    "sg:postcode":"28792",
    "sg:province":"NC",
    "sg:tags":[
        "personal",
        "institution"
    ],
    "sg:website":"www.blueridgesavings.com",
    "wof:name":"Blue Ridge Savings Bank Inc",
    "wof:placetype":"venue"
},
  "geometry": {"coordinates":[-82.44221400000001,35.304913],"type":"Point"}
}