{
  "type": "Feature",
  "properties": {
    "addr:full":"107 Weeks Dr Roxboro NC 27504",
    "addr:housenumber":"107",
    "addr:postcode":"27504",
    "addr:street":"Weeks Dr",
    "iso:country":"US",
    "sg:address":"107 Weeks Dr",
    "sg:city":"Roxboro",
    "sg:classifiers":[
        {
            "category":"Wholesale",
            "subcategory":"Hardware",
            "type":"Manufacturing & Wholesale Goods"
        }
    ],
    "sg:phone":"+1 336 503 8001",
    "sg:postcode":"27504",
    "sg:province":"NC",
    "sg:tags":[
        "fastener"
    ],
    "sg:website":"www.fastenal.com",
    "wof:name":"Fastenal Co",
    "wof:placetype":"venue"
},
  "geometry": {"coordinates":[-78.612634,35.461457],"type":"Point"}
}