{
  "type": "Feature",
  "properties": {
    "addr:full":"4500 Steepleton Way Charlotte NC 28215",
    "addr:housenumber":"4500",
    "addr:postcode":"28215",
    "addr:street":"Steepleton Way",
    "iso:country":"US",
    "sg:address":"4500 Steepleton Way",
    "sg:city":"Charlotte",
    "sg:classifiers":[
        {
            "category":"Professional",
            "subcategory":"Management & Consulting",
            "type":"Services"
        }
    ],
    "sg:phone":"+1 704 509 0298",
    "sg:postcode":"28215",
    "sg:province":"NC",
    "sg:tags":[
        "consultant"
    ],
    "wof:name":"Andre Richman",
    "wof:placetype":"venue"
},
  "geometry": {"coordinates":[-80.69066599999999,35.267029],"type":"Point"}
}