{
  "type": "Feature",
  "properties": {
    "addr:full":"1860 Powell Farm Rd Lillington NC 27546",
    "addr:housenumber":"1860",
    "addr:postcode":"27546",
    "addr:street":"Powell Farm Rd",
    "iso:country":"US",
    "sg:address":"1860 Powell Farm Rd",
    "sg:city":"Lillington",
    "sg:classifiers":[
        {
            "category":"Personal",
            "type":"Services"
        }
    ],
    "sg:phone":"+1   ",
    "sg:postcode":"27546",
    "sg:province":"NC",
    "wof:name":"Ltkr Complete Inc",
    "wof:placetype":"venue"
},
  "geometry": {"coordinates":[-78.941411,35.302564],"type":"Point"}
}