{
  "type": "Feature",
  "properties": {
    "addr:full":"631 Meadowbrook Rd Asheboro NC 27203",
    "addr:housenumber":"631",
    "addr:postcode":"27203",
    "addr:street":"Meadowbrook Rd",
    "iso:country":"US",
    "sg:address":"631 Meadowbrook Rd",
    "sg:city":"Asheboro",
    "sg:classifiers":[
        {
            "category":"Organizations",
            "subcategory":"Religious Organization",
            "type":"Services"
        }
    ],
    "sg:phone":"+1 336 625 5948",
    "sg:postcode":"27203",
    "sg:province":"NC",
    "sg:tags":[
        "church"
    ],
    "wof:name":"Church Of Christ",
    "wof:placetype":"venue"
},
  "geometry": {"coordinates":[-79.804395,35.71645],"type":"Point"}
}