{
  "type": "Feature",
  "properties": {
    "iso:country":"US",
    "sg:address":"9818 Monroe Rd",
    "sg:city":"Charlotte",
    "sg:classifiers":[
        {
            "category":"Recreation",
            "type":"Entertainment"
        }
    ],
    "sg:phone":"+1   ",
    "sg:postcode":"28270",
    "sg:province":"NC",
    "wof:name":"Tae Kwon Do America",
    "wof:placetype":"venue"
},
  "geometry": {"coordinates":[-80.738829,35.138477],"type":"Point"}
}