{
  "type": "Feature",
  "properties": {
    "addr:full":"5140 Sellers St South Brunswick NC 28470",
    "addr:housenumber":"5140",
    "addr:postcode":"28470",
    "addr:street":"Sellers St",
    "iso:country":"US",
    "sg:address":"5140 Sellers St",
    "sg:city":"South Brunswick",
    "sg:classifiers":[
        {
            "category":"Organizations",
            "subcategory":"Professional Association",
            "type":"Services"
        }
    ],
    "sg:phone":"+1 910 754 8415",
    "sg:postcode":"28470",
    "sg:province":"NC",
    "wof:name":"Mental Health Assn Nc",
    "wof:placetype":"venue"
},
  "geometry": {"coordinates":[-78.39619500000001,33.962734],"type":"Point"}
}