{
  "type": "Feature",
  "properties": {
    "addr:full":"329 W Main St Durham NC 27701",
    "addr:housenumber":"329",
    "addr:postcode":"27701",
    "addr:street":"W Main St",
    "iso:country":"US",
    "sg:address":"329 W Main St",
    "sg:city":"Durham",
    "sg:classifiers":[
        {
            "category":"Shopping",
            "type":"Retail Goods"
        }
    ],
    "sg:phone":"+1 919 956 7212",
    "sg:postcode":"27701",
    "sg:province":"NC",
    "sg:tags":[
        "material",
        "artist",
        "supply"
    ],
    "wof:name":"Main Street Art Supply",
    "wof:placetype":"venue"
},
  "geometry": {"coordinates":[-78.903622,35.99657],"type":"Point"}
}