{
  "type": "Feature",
  "properties": {
    "addr:full":"2032 Eagle Rock Rd Wendell NC 27591",
    "addr:housenumber":"2032",
    "addr:postcode":"27591",
    "addr:street":"Eagle Rock Rd",
    "iso:country":"US",
    "sg:address":"2032 Eagle Rock Rd",
    "sg:city":"Wendell",
    "sg:classifiers":[
        {
            "category":"Wholesale",
            "subcategory":"Machinery & Supplies",
            "type":"Manufacturing & Wholesale Goods"
        }
    ],
    "sg:phone":"+1 919 365 3188",
    "sg:postcode":"27591",
    "sg:province":"NC",
    "sg:tags":[
        "pump"
    ],
    "wof:name":"Fuller Water Pump Svc",
    "wof:placetype":"venue"
},
  "geometry": {"coordinates":[-78.39357200000001,35.759501],"type":"Point"}
}