{
  "type": "Feature",
  "properties": {
    "addr:full":"1647 Jameston Dr Charlotte NC 28209",
    "addr:housenumber":"1647",
    "addr:postcode":"28209",
    "addr:street":"Jameston Dr",
    "iso:country":"US",
    "sg:address":"1647 Jameston Dr",
    "sg:city":"Charlotte",
    "sg:classifiers":[
        {
            "category":"Professional",
            "subcategory":"Employment Agencies",
            "type":"Services"
        }
    ],
    "sg:phone":"+1 704 366 1817",
    "sg:postcode":"28209",
    "sg:province":"NC",
    "sg:tags":[
        "opportunity"
    ],
    "wof:name":"Pharma Reps",
    "wof:placetype":"venue"
},
  "geometry": {"coordinates":[-80.844414,35.185226],"type":"Point"}
}