{
  "type": "Feature",
  "properties": {
    "addr:full":"118 School St Belmont NC 28012",
    "addr:housenumber":"118",
    "addr:postcode":"28012",
    "addr:street":"School St",
    "iso:country":"US",
    "sg:address":"118 School St",
    "sg:city":"Belmont",
    "sg:classifiers":[
        {
            "category":"Organizations",
            "subcategory":"Religious Organization",
            "type":"Services"
        }
    ],
    "sg:phone":"+1 704 827 7071",
    "sg:postcode":"28012",
    "sg:province":"NC",
    "sg:tags":[
        "church"
    ],
    "wof:name":"Power Of The Spirit Church",
    "wof:placetype":"venue"
},
  "geometry": {"coordinates":[-81.048552,35.273089],"type":"Point"}
}