{
  "type": "Feature",
  "properties": {
    "addr:full":"1365 Westgate Center Dr Winston Salem NC 27103",
    "addr:housenumber":"1365",
    "addr:postcode":"27103",
    "addr:street":"Westgate Center Dr",
    "iso:country":"US",
    "sg:address":"1365 Westgate Center Dr",
    "sg:city":"Winston Salem",
    "sg:classifiers":[
        {
            "category":"Wholesale",
            "subcategory":"Electrical",
            "type":"Manufacturing & Wholesale Goods"
        }
    ],
    "sg:phone":"+1 336 659 7140",
    "sg:postcode":"27103",
    "sg:province":"NC",
    "sg:tags":[
        "alarm",
        "burglar",
        "system"
    ],
    "wof:name":"PSI",
    "wof:placetype":"venue"
},
  "geometry": {"coordinates":[-80.31209699999999,36.074016],"type":"Point"}
}