{
  "type": "Feature",
  "properties": {
    "addr:full":"7917 Water Oaks Dr Denver NC 28037",
    "addr:housenumber":"7917",
    "addr:postcode":"28037",
    "addr:street":"Water Oaks Dr",
    "iso:country":"US",
    "sg:address":"7917 Water Oaks Dr",
    "sg:city":"Denver",
    "sg:classifiers":[
        {
            "category":"Personal",
            "subcategory":"Barber",
            "type":"Services"
        }
    ],
    "sg:phone":"+1   ",
    "sg:postcode":"28037",
    "sg:province":"NC",
    "sg:tags":[
        "shop"
    ],
    "wof:name":"A R Benton",
    "wof:placetype":"venue"
},
  "geometry": {"coordinates":[-80.985947,35.458674],"type":"Point"}
}