{
  "type": "Feature",
  "properties": {
    "iso:country":"US",
    "sg:address":"5919 Brace Rd",
    "sg:city":"Charlotte",
    "sg:classifiers":[
        {
            "category":"Professional",
            "subcategory":"Business Services",
            "type":"Services"
        },
        {
            "category":"Building & Trades",
            "subcategory":"Construction",
            "type":"Services"
        }
    ],
    "sg:phone":"+1 704 365 7870",
    "sg:postcode":"28211",
    "sg:province":"NC",
    "sg:tags":[
        "general",
        "contractor"
    ],
    "wof:name":"Iron River Building Group Inc",
    "wof:placetype":"venue"
},
  "geometry": {"coordinates":[-80.774562,35.165846],"type":"Point"}
}