{
  "type": "Feature",
  "properties": {
    "addr:full":"1966 5th Street Ln NW Hickory NC 28601",
    "addr:housenumber":"1966",
    "addr:postcode":"28601",
    "addr:street":"5Th Street Ln Nw",
    "iso:country":"US",
    "sg:address":"1966 5th Street Ln NW",
    "sg:city":"Hickory",
    "sg:classifiers":[
        {
            "category":"Wholesale",
            "subcategory":"Apparel",
            "type":"Manufacturing & Wholesale Goods"
        }
    ],
    "sg:phone":"+1 828 324 0233",
    "sg:postcode":"28601",
    "sg:province":"NC",
    "sg:tags":[
        "clothing"
    ],
    "wof:name":"Neeley Ham Industries Inc",
    "wof:placetype":"venue"
},
  "geometry": {"coordinates":[-81.35258899999999,35.759845],"type":"Point"}
}