{
  "type": "Feature",
  "properties": {
    "iso:country":"US",
    "sg:address":"115 Skateway Dr",
    "sg:city":"Fayetteville",
    "sg:classifiers":[
        {
            "category":"Recreation",
            "type":"Entertainment"
        }
    ],
    "sg:phone":"+1 910 860 8900",
    "sg:postcode":"28304",
    "sg:province":"NC",
    "sg:tags":[
        "skating",
        "rink"
    ],
    "wof:name":"Round-A-Bout Skating Ctr",
    "wof:placetype":"venue"
},
  "geometry": {"coordinates":[-79.012674,35.036939],"type":"Point"}
}