{
  "type": "Feature",
  "properties": {
    "iso:country":"US",
    "sg:address":"3512 Providence Rd S",
    "sg:city":"Waxhaw",
    "sg:classifiers":[
        {
            "category":"Education",
            "subcategory":"Dance Studio",
            "type":"Public Place"
        }
    ],
    "sg:phone":"+1 704 843 4869",
    "sg:postcode":"28173",
    "sg:province":"NC",
    "sg:tags":[
        "instruction",
        "dancing"
    ],
    "wof:name":"Carolina Dance Co",
    "wof:placetype":"venue"
},
  "geometry": {"coordinates":[-80.75488900000001,34.94722],"type":"Point"}
}