{
  "type": "Feature",
  "properties": {
    "addr:full":"216 Bost St Kernersville NC 27284",
    "addr:housenumber":"216",
    "addr:postcode":"27284",
    "addr:street":"Bost St",
    "iso:country":"US",
    "sg:address":"216 Bost St",
    "sg:city":"Kernersville",
    "sg:classifiers":[
        {
            "category":"Shopping",
            "type":"Retail Goods"
        }
    ],
    "sg:phone":"+1 336 996 5320",
    "sg:postcode":"27284",
    "sg:province":"NC",
    "sg:tags":[
        "merchandise"
    ],
    "wof:name":"Mabes Discount",
    "wof:placetype":"venue"
},
  "geometry": {"coordinates":[-80.063346,36.131435],"type":"Point"}
}