{
  "type": "Feature",
  "properties": {
    "addr:full":"638 Twin Oaks Rd Elkin NC 28621",
    "addr:housenumber":"638",
    "addr:postcode":"28621",
    "addr:street":"Twin Oaks Rd",
    "iso:country":"US",
    "sg:address":"638 Twin Oaks Rd",
    "sg:city":"Elkin",
    "sg:phone":"+1 336 366 2225",
    "sg:postcode":"28621",
    "sg:province":"NC",
    "sg:tags":[
        "farm",
        "tobacco"
    ],
    "wof:name":"Clyde Stanley Farm",
    "wof:placetype":"venue"
},
  "geometry": {"coordinates":[-80.775031,36.381624],"type":"Point"}
}