{
  "type": "Feature",
  "properties": {
    "iso:country":"US",
    "sg:address":"101 W W T Harris Blvd",
    "sg:city":"Charlotte",
    "sg:classifiers":[
        {
            "category":"Health Services",
            "subcategory":"Health Practitioner",
            "type":"Services"
        }
    ],
    "sg:phone":"+1 704 548 5780",
    "sg:postcode":"28262",
    "sg:province":"NC",
    "sg:tags":[
        "therapist",
        "physical"
    ],
    "wof:name":"Carolinas Physical Therapy",
    "wof:placetype":"venue"
},
  "geometry": {"coordinates":[-80.74972099999999,35.305755],"type":"Point"}
}