{
  "type": "Feature",
  "properties": {
    "iso:country":"US",
    "sg:address":"46841 Wesley Chapel Rd",
    "sg:city":"Richfield",
    "sg:classifiers":[
        {
            "category":"Building & Trades",
            "subcategory":"Construction",
            "type":"Services"
        }
    ],
    "sg:phone":"+1 704 463 5073",
    "sg:postcode":"28137",
    "sg:province":"NC",
    "sg:tags":[
        "house"
    ],
    "wof:name":"Kimrey Construction",
    "wof:placetype":"venue"
},
  "geometry": {"coordinates":[-80.290097,35.471263],"type":"Point"}
}