{
  "type": "Feature",
  "properties": {
    "iso:country":"US",
    "sg:address":"2155 Tar River Rd",
    "sg:city":"Creedmoor",
    "sg:classifiers":[
        {
            "category":"Manufacturing",
            "subcategory":"Lumber",
            "type":"Manufacturing & Wholesale Goods"
        }
    ],
    "sg:phone":"+1 919 528 2370",
    "sg:postcode":"27522",
    "sg:province":"NC",
    "sg:tags":[
        "logging"
    ],
    "wof:name":"Dannles Logging Inc",
    "wof:placetype":"venue"
},
  "geometry": {"coordinates":[-78.630369,36.136212],"type":"Point"}
}