{
  "type": "Feature",
  "properties": {
    "iso:country":"US",
    "sg:address":"1915 Rexford Rd",
    "sg:city":"Charlotte",
    "sg:classifiers":[
        {
            "category":"Utilities",
            "subcategory":"Natural Gas",
            "type":"Services"
        }
    ],
    "sg:phone":"+1 704 364 3120",
    "sg:postcode":"28211",
    "sg:province":"NC",
    "sg:tags":[
        "distribution"
    ],
    "sg:website":"http://www.piedmontng.com",
    "wof:name":"Piedmont Energy Company",
    "wof:placetype":"venue"
},
  "geometry": {"coordinates":[-80.834368,35.158533],"type":"Point"}
}