{
  "type": "Feature",
  "properties": {
    "iso:country":"US",
    "sg:address":"5248 Westfield Rd",
    "sg:city":"Mount Airy",
    "sg:classifiers":[
        {
            "category":"Retail",
            "subcategory":"Car Wash",
            "type":"Services"
        }
    ],
    "sg:phone":"+1   ",
    "sg:postcode":"27030",
    "sg:province":"NC",
    "sg:tags":[
        "carwash"
    ],
    "wof:name":"Leons",
    "wof:placetype":"venue"
},
  "geometry": {"coordinates":[-80.481071,36.502201],"type":"Point"}
}