{
  "type": "Feature",
  "properties": {
    "iso:country":"US",
    "sg:address":"220 George W Liles Pkwy",
    "sg:city":"Concord",
    "sg:classifiers":[
        {
            "category":"Organizations",
            "subcategory":"Religious Organization",
            "type":"Services"
        }
    ],
    "sg:phone":"+1 704 795 0423",
    "sg:postcode":"28027",
    "sg:province":"NC",
    "sg:tags":[
        "church"
    ],
    "wof:name":"Crossroads United Methodist",
    "wof:placetype":"venue"
},
  "geometry": {"coordinates":[-80.668437,35.415876],"type":"Point"}
}