{
  "type": "Feature",
  "properties": {
    "iso:country":"US",
    "sg:address":"14001 Weston Pkwy",
    "sg:city":"Cary",
    "sg:classifiers":[
        {
            "category":"Professional",
            "type":"Services"
        }
    ],
    "sg:phone":"+1 919 678 8822",
    "sg:postcode":"27513",
    "sg:province":"NC",
    "sg:tags":[
        "establishment"
    ],
    "wof:name":"Verisign",
    "wof:placetype":"venue"
},
  "geometry": {"coordinates":[-78.810248,35.819044],"type":"Point"}
}