{
  "type": "Feature",
  "properties": {
    "iso:country":"US",
    "sg:address":"95 Killdeer Dr",
    "sg:city":"Spring Lake",
    "sg:classifiers":[
        {
            "category":"Restaurant",
            "type":"Food & Drink"
        }
    ],
    "sg:phone":"+1 910 497 8228",
    "sg:postcode":"28390",
    "sg:province":"NC",
    "sg:tags":[
        "catering"
    ],
    "wof:name":"B & B Catering Inc",
    "wof:placetype":"venue"
},
  "geometry": {"coordinates":[-78.96968200000001,35.239772],"type":"Point"}
}