{
  "type": "Feature",
  "properties": {
    "addr:full":"95 Clearwater Ln Spruce Pine NC 28777",
    "addr:housenumber":"95",
    "addr:postcode":"28777",
    "addr:street":"Clearwater Ln",
    "iso:country":"US",
    "sg:address":"95 Clearwater Ln",
    "sg:city":"Spruce Pine",
    "sg:classifiers":[
        {
            "category":"Government",
            "subcategory":"Office",
            "type":"Public Place"
        }
    ],
    "sg:phone":"+1 828 765 3011",
    "sg:postcode":"28777",
    "sg:province":"NC",
    "sg:tags":[
        "govt",
        "city"
    ],
    "wof:name":"Spruce Pine Water Treatment",
    "wof:placetype":"venue"
},
  "geometry": {"coordinates":[-82.059608,35.923863],"type":"Point"}
}