{
  "type": "Feature",
  "properties": {
    "iso:country":"US",
    "sg:address":"32 Longstreet Rd",
    "sg:city":"Weldon",
    "sg:classifiers":[
        {
            "category":"Building & Trades",
            "subcategory":"Construction",
            "type":"Services"
        }
    ],
    "sg:phone":"+1 252 536 4421",
    "sg:postcode":"27890",
    "sg:province":"NC",
    "sg:tags":[
        "home",
        "improvement"
    ],
    "wof:name":"Pittard & Pittard",
    "wof:placetype":"venue"
},
  "geometry": {"coordinates":[-77.615432,36.424116],"type":"Point"}
}