{
  "type": "Feature",
  "properties": {
    "iso:country":"US",
    "sg:address":"905 Washington St",
    "sg:city":"Plymouth",
    "sg:classifiers":[
        {
            "category":"Organizations",
            "subcategory":"Religious Organization",
            "type":"Services"
        }
    ],
    "sg:phone":"+1 252 793 5820",
    "sg:postcode":"27962",
    "sg:province":"NC",
    "sg:tags":[
        "church"
    ],
    "sg:website":"www.plymouthchurchofchrist.org",
    "wof:name":"Plymouth Church Of Christ",
    "wof:placetype":"venue"
},
  "geometry": {"coordinates":[-76.742773,35.853597],"type":"Point"}
}