{
  "type": "Feature",
  "properties": {
    "addr:full":"54 Pepsi Hts Sylva NC 28779",
    "addr:housenumber":"54",
    "addr:postcode":"28779",
    "addr:street":"Pepsi Hts",
    "iso:country":"US",
    "sg:address":"54 Pepsi Hts",
    "sg:city":"Sylva",
    "sg:classifiers":[
        {
            "category":"Personal",
            "subcategory":"Beauty Salon",
            "type":"Services"
        }
    ],
    "sg:phone":"+1   ",
    "sg:postcode":"28779",
    "sg:province":"NC",
    "sg:tags":[
        "shop"
    ],
    "wof:name":"Mt View Beauty Salon",
    "wof:placetype":"venue"
},
  "geometry": {"coordinates":[-83.302363,35.265488],"type":"Point"}
}