{
  "type": "Feature",
  "properties": {
    "addr:full":"2101 Sardis Rd N Charlotte NC 28227",
    "addr:housenumber":"2101",
    "addr:postcode":"28227",
    "addr:street":"Sardis Rd N",
    "iso:country":"US",
    "sg:address":"2101 Sardis Rd N",
    "sg:city":"Charlotte",
    "sg:classifiers":[
        {
            "category":"Professional",
            "subcategory":"Employment Agencies",
            "type":"Services"
        },
        {
            "category":"Organizations",
            "subcategory":"Professional Association",
            "type":"Services"
        }
    ],
    "sg:phone":"+1 704 367 1331",
    "sg:postcode":"28227",
    "sg:province":"NC",
    "sg:tags":[
        "employer",
        "business",
        "trade"
    ],
    "sg:website":"http://www.abctennessee.com",
    "wof:name":"Abc Of The Carolinas",
    "wof:placetype":"venue"
},
  "geometry": {"coordinates":[-80.73226200000001,35.142811],"type":"Point"}
}