{
  "type": "Feature",
  "properties": {
    "iso:country":"US",
    "sg:address":"14900 Forest Mist Way",
    "sg:city":"Charlotte",
    "sg:classifiers":[
        {
            "category":"Professional",
            "type":"Services"
        }
    ],
    "sg:phone":"+1 704 583 0628",
    "sg:postcode":"28273",
    "sg:province":"NC",
    "wof:name":"James A Cooper",
    "wof:placetype":"venue"
},
  "geometry": {"coordinates":[-80.970427,35.091863],"type":"Point"}
}