{
  "type": "Feature",
  "properties": {
    "iso:country":"US",
    "sg:address":"4420 Page Rd",
    "sg:city":"Morrisville",
    "sg:classifiers":[
        {
            "category":"Recreation",
            "type":"Entertainment"
        }
    ],
    "sg:phone":"+1   ",
    "sg:postcode":"27560",
    "sg:province":"NC",
    "sg:tags":[
        "amusement"
    ],
    "wof:name":"Bunkers Paintball",
    "wof:placetype":"venue"
},
  "geometry": {"coordinates":[-78.829241,35.88682],"type":"Point"}
}