{
  "type": "Feature",
  "properties": {
    "addr:full":"7980 River Rd Vanceboro NC 28586",
    "addr:housenumber":"7980",
    "addr:postcode":"28586",
    "addr:street":"River Rd",
    "iso:country":"US",
    "sg:address":"7980 River Rd",
    "sg:city":"Vanceboro",
    "sg:classifiers":[
        {
            "category":"Manufacturing",
            "subcategory":"Apparel",
            "type":"Manufacturing & Wholesale Goods"
        },
        {
            "category":"Professional",
            "subcategory":"Business Services",
            "type":"Services"
        }
    ],
    "sg:phone":"+1 252 244 1998",
    "sg:postcode":"28586",
    "sg:province":"NC",
    "sg:tags":[
        "sewing",
        "contractor"
    ],
    "wof:name":"M & H Enterprises Inc",
    "wof:placetype":"venue"
},
  "geometry": {"coordinates":[-77.2538,35.285171],"type":"Point"}
}