{
  "type": "Feature",
  "properties": {
    "iso:country":"US",
    "sg:address":"7016 Toby Ct",
    "sg:city":"Charlotte",
    "sg:classifiers":[
        {
            "category":"Shopping",
            "subcategory":"Catalog Store",
            "type":"Retail Goods"
        }
    ],
    "sg:phone":"+1 704 597 0402",
    "sg:postcode":"28213",
    "sg:province":"NC",
    "sg:tags":[
        "internet"
    ],
    "wof:name":"Cruzin For A Deal",
    "wof:placetype":"venue"
},
  "geometry": {"coordinates":[-80.74817299999999,35.277798],"type":"Point"}
}