{
  "type": "Feature",
  "properties": {
    "addr:full":"1904 Associates Ln Charlotte NC 28217",
    "addr:housenumber":"1904",
    "addr:postcode":"28217",
    "addr:street":"Associates Ln",
    "iso:country":"US",
    "sg:address":"1904 Associates Ln",
    "sg:city":"Charlotte",
    "sg:classifiers":[
        {
            "category":"Freight",
            "type":"Transportation"
        }
    ],
    "sg:phone":"+1 704 394 7900",
    "sg:postcode":"28217",
    "sg:province":"NC",
    "sg:tags":[
        "foreign",
        "forwarder",
        "domestic",
        "air"
    ],
    "wof:name":"Lynden Air Freight Inc",
    "wof:placetype":"venue"
},
  "geometry": {"coordinates":[-80.930449,35.176696],"type":"Point"}
}