{
  "type": "Feature",
  "properties": {
    "iso:country":"US",
    "sg:address":"2837 Rosemeade Dr",
    "sg:city":"Monroe",
    "sg:classifiers":[
        {
            "category":"Personal",
            "subcategory":"Beauty Salon",
            "type":"Services"
        }
    ],
    "sg:phone":"+1 704 254 4014",
    "sg:postcode":"28110",
    "sg:province":"NC",
    "wof:name":"Intimate Hair Design",
    "wof:placetype":"venue"
},
  "geometry": {"coordinates":[-80.608726,35.049253],"type":"Point"}
}