{
  "type": "Feature",
  "properties": {
    "addr:full":"2202 Burnett Blvd Wilmington NC 28401",
    "addr:housenumber":"2202",
    "addr:postcode":"28401",
    "addr:street":"Burnett Blvd",
    "iso:country":"US",
    "sg:address":"2202 Burnett Blvd",
    "sg:city":"Wilmington",
    "sg:classifiers":[
        {
            "category":"Wholesale",
            "subcategory":"Durable Goods & Equipment",
            "type":"Manufacturing & Wholesale Goods"
        }
    ],
    "sg:phone":"+1 910 362 0282",
    "sg:postcode":"28401",
    "sg:province":"NC",
    "sg:tags":[
        "exporter"
    ],
    "wof:name":"Carolina Bulk Transfer",
    "wof:placetype":"venue"
},
  "geometry": {"coordinates":[-77.94789,34.196297],"type":"Point"}
}