{
  "type": "Feature",
  "properties": {
    "iso:country":"US",
    "sg:address":"243 Yulan Dr",
    "sg:city":"Wilmington",
    "sg:classifiers":[
        {
            "category":"Professional",
            "type":"Services"
        }
    ],
    "sg:phone":"+1 910 313 6991",
    "sg:postcode":"28412",
    "sg:province":"NC",
    "wof:name":"Babys Away",
    "wof:placetype":"venue"
},
  "geometry": {"coordinates":[-77.91230299999999,34.149806],"type":"Point"}
}