{
  "type": "Feature",
  "properties": {
    "iso:country":"US",
    "sg:address":"2997 Laboratory Rd",
    "sg:city":"Lincolnton",
    "sg:classifiers":[
        {
            "category":"Building & Trades",
            "subcategory":"Construction",
            "type":"Services"
        }
    ],
    "sg:phone":"+1 704 735 5324",
    "sg:postcode":"28092",
    "sg:province":"NC",
    "sg:tags":[
        "repair",
        "industrial",
        "well",
        "water",
        "equipment",
        "drilling",
        "se"
    ],
    "wof:name":"Dysart Well & Pump Inc",
    "wof:placetype":"venue"
},
  "geometry": {"coordinates":[-81.257895,35.434474],"type":"Point"}
}