{
  "type": "Feature",
  "properties": {
    "iso:country":"US",
    "sg:address":"224 Sneed Ln",
    "sg:city":"Fuquay Varina",
    "sg:classifiers":[
        {
            "category":"Communications",
            "subcategory":"Radio Station",
            "type":"Services"
        }
    ],
    "sg:phone":"+1 919 552 8642",
    "sg:postcode":"27526",
    "sg:province":"NC",
    "sg:tags":[
        "broadcast"
    ],
    "wof:name":"North Carolina Miracle Revival",
    "wof:placetype":"venue"
},
  "geometry": {"coordinates":[-78.831485,35.547534],"type":"Point"}
}