{
  "type": "Feature",
  "properties": {
    "addr:full":"104 Wafco Ln Greensboro NC 27401",
    "addr:housenumber":"104",
    "addr:postcode":"27401",
    "addr:street":"Wafco Ln",
    "iso:country":"US",
    "sg:address":"104 Wafco Ln",
    "sg:city":"Greensboro",
    "sg:classifiers":[
        {
            "category":"Retail",
            "subcategory":"Repair Shop",
            "type":"Services"
        }
    ],
    "sg:phone":"+1 336 574 1251",
    "sg:postcode":"27401",
    "sg:province":"NC",
    "sg:tags":[
        "equipment",
        "electronic",
        "supply"
    ],
    "wof:name":"Inlet Consultants",
    "wof:placetype":"venue"
},
  "geometry": {"coordinates":[-79.798754,36.068654],"type":"Point"}
}