{
  "type": "Feature",
  "properties": {
    "iso:country":"US",
    "sg:address":"598 W Main St",
    "sg:city":"Sylva",
    "sg:classifiers":[
        {
            "category":"Professional",
            "subcategory":"Accounting & Tax Preparation",
            "type":"Services"
        }
    ],
    "sg:phone":"+1 828 586 9939",
    "sg:postcode":"28779",
    "sg:province":"NC",
    "sg:tags":[
        "bookkeeping",
        "general"
    ],
    "wof:name":"KUDZU Bookkeeping & Taxes Inc",
    "wof:placetype":"venue"
},
  "geometry": {"coordinates":[-83.222246,35.373543],"type":"Point"}
}