{
  "type": "Feature",
  "properties": {
    "iso:country":"US",
    "sg:address":"224 Flanagan Rd",
    "sg:city":"Henderson",
    "sg:classifiers":[
        {
            "category":"Building & Trades",
            "subcategory":"Construction",
            "type":"Services"
        }
    ],
    "sg:phone":"+1 252 492 2873",
    "sg:postcode":"27537",
    "sg:province":"NC",
    "sg:tags":[
        "concrete",
        "contractor"
    ],
    "wof:name":"Annie Williamson Cnstr Co",
    "wof:placetype":"venue"
},
  "geometry": {"coordinates":[-78.420058,36.404219],"type":"Point"}
}