{
  "type": "Feature",
  "properties": {
    "addr:full":"1470 Old Lennon Rd SE Bolivia NC 28422",
    "addr:housenumber":"1470",
    "addr:postcode":"28422",
    "addr:street":"Old Lennon Rd Se",
    "iso:country":"US",
    "sg:address":"1470 Old Lennon Rd SE",
    "sg:city":"Bolivia",
    "sg:classifiers":[
        {
            "category":"Manufacturing",
            "subcategory":"Lumber",
            "type":"Manufacturing & Wholesale Goods"
        }
    ],
    "sg:phone":"+1 910 253 7669",
    "sg:postcode":"28422",
    "sg:province":"NC",
    "sg:tags":[
        "company",
        "logging"
    ],
    "wof:name":"Wood Duck Construction",
    "wof:placetype":"venue"
},
  "geometry": {"coordinates":[-78.22475300000001,34.002691],"type":"Point"}
}