{
  "type": "Feature",
  "properties": {
    "addr:full":"8321 Old McCullers Rd Raleigh NC 27603",
    "addr:housenumber":"8321",
    "addr:postcode":"27603",
    "addr:street":"Old Mccullers Rd",
    "iso:country":"US",
    "sg:address":"8321 Old McCullers Rd",
    "sg:city":"Raleigh",
    "sg:classifiers":[
        {
            "category":"Freight",
            "type":"Transportation"
        }
    ],
    "sg:phone":"+1 919 773 8382",
    "sg:postcode":"27603",
    "sg:province":"NC",
    "sg:tags":[
        "operator",
        "hauling",
        "trucking"
    ],
    "wof:name":"Warren Transport Inc",
    "wof:placetype":"venue"
},
  "geometry": {"coordinates":[-78.700853,35.652549],"type":"Point"}
}