{
  "type": "Feature",
  "properties": {
    "iso:country":"US",
    "sg:address":"5807 Stratford Ct",
    "sg:city":"Harrisburg",
    "sg:classifiers":[
        {
            "category":"Autos & Motor Vehicles",
            "subcategory":"Auto Supplies",
            "type":"Retail Goods"
        }
    ],
    "sg:phone":"+1 704 455 3077",
    "sg:postcode":"28075",
    "sg:province":"NC",
    "wof:name":"Hh Supply",
    "wof:placetype":"venue"
},
  "geometry": {"coordinates":[-80.673247,35.300749],"type":"Point"}
}