{
  "type": "Feature",
  "properties": {
    "addr:full":"1639 S Asbury Church Rd Washington NC 27889",
    "addr:housenumber":"1639",
    "addr:postcode":"27889",
    "addr:street":"S Asbury Church Rd",
    "iso:country":"US",
    "sg:address":"1639 S Asbury Church Rd",
    "sg:city":"Washington",
    "sg:classifiers":[
        {
            "category":"Building & Trades",
            "subcategory":"Construction",
            "type":"Services"
        }
    ],
    "sg:phone":"+1 252 946 1801",
    "sg:postcode":"27889",
    "sg:province":"NC",
    "sg:tags":[
        "house"
    ],
    "wof:name":"David J Evans",
    "wof:placetype":"venue"
},
  "geometry": {"coordinates":[-76.99093999999999,35.526248],"type":"Point"}
}