{
  "type": "Feature",
  "properties": {
    "iso:country":"US",
    "sg:address":"404 W Kings Hwy",
    "sg:city":"Eden",
    "sg:classifiers":[
        {
            "category":"Freight",
            "type":"Transportation"
        }
    ],
    "sg:phone":"+1 336 623 7050",
    "sg:postcode":"27288",
    "sg:province":"NC",
    "sg:tags":[
        "commercial",
        "storage"
    ],
    "wof:name":"Central Mini-Storage",
    "wof:placetype":"venue"
},
  "geometry": {"coordinates":[-79.755171,36.490685],"type":"Point"}
}