{
  "type": "Feature",
  "properties": {
    "addr:full":"142 NW Main St Rocky Mount NC 27804",
    "addr:housenumber":"142",
    "addr:postcode":"27804",
    "addr:street":"Nw Main St",
    "iso:country":"US",
    "sg:address":"142 NW Main St",
    "sg:city":"Rocky Mount",
    "sg:classifiers":[
        {
            "category":"Shopping",
            "subcategory":"Used Merchandise",
            "type":"Retail Goods"
        }
    ],
    "sg:phone":"+1 252 442 7722",
    "sg:postcode":"27804",
    "sg:province":"NC",
    "sg:tags":[
        "book",
        "rare",
        "dealer"
    ],
    "wof:name":"J J Harpers Bookshop",
    "wof:placetype":"venue"
},
  "geometry": {"coordinates":[-77.795753,35.941812],"type":"Point"}
}