{
  "type": "Feature",
  "properties": {
    "addr:full":"1529 Union Cross Rd Kernersville NC 27284",
    "addr:housenumber":"1529",
    "addr:postcode":"27284",
    "addr:street":"Union Cross Rd",
    "iso:country":"US",
    "sg:address":"1529 Union Cross Rd",
    "sg:city":"Kernersville",
    "sg:classifiers":[
        {
            "category":"Shopping",
            "subcategory":"Discount & Variety Stores",
            "type":"Retail Goods"
        },
        {
            "category":"Professional",
            "type":"Services"
        }
    ],
    "sg:phone":"+1 336 996 5691",
    "sg:postcode":"27284",
    "sg:province":"NC",
    "wof:name":"Tammy's 99 Cents & Up",
    "wof:placetype":"venue"
},
  "geometry": {"coordinates":[-80.10875,36.07658],"type":"Point"}
}