{
  "type": "Feature",
  "properties": {
    "iso:country":"US",
    "sg:address":"6021 Plaza Ln",
    "sg:city":"Charlotte",
    "sg:classifiers":[
        {
            "category":"Shopping",
            "subcategory":"Pharmacy",
            "type":"Retail Goods"
        }
    ],
    "sg:phone":"+1 704 537 0191",
    "sg:postcode":"28215",
    "sg:province":"NC",
    "wof:name":"Medicine Shoppe Inc",
    "wof:placetype":"venue"
},
  "geometry": {"coordinates":[-80.743301,35.254352],"type":"Point"}
}