{
  "type": "Feature",
  "properties": {
    "iso:country":"US",
    "sg:address":"4801 E Independence Blvd",
    "sg:city":"Charlotte",
    "sg:classifiers":[
        {
            "category":"Banks & Credit Unions",
            "subcategory":"Bank",
            "type":"Services"
        }
    ],
    "sg:phone":"+1 704 537 2767",
    "sg:postcode":"28212",
    "sg:province":"NC",
    "sg:tags":[
        "loan",
        "real estate"
    ],
    "wof:name":"Stockton Turner Mtg Banker",
    "wof:placetype":"venue"
},
  "geometry": {"coordinates":[-80.764759,35.19332],"type":"Point"}
}