{
  "type": "Feature",
  "properties": {
    "iso:country":"US",
    "sg:address":"110 Ocean Spray Dr",
    "sg:city":"Swansboro",
    "sg:classifiers":[
        {
            "category":"Professional",
            "subcategory":"Business Services",
            "type":"Services"
        }
    ],
    "sg:phone":"+1 252 393 3062",
    "sg:postcode":"28584",
    "sg:province":"NC",
    "sg:tags":[
        "merchandise"
    ],
    "wof:name":"Willard Pool Svc",
    "wof:placetype":"venue"
},
  "geometry": {"coordinates":[-77.070961,34.698118],"type":"Point"}
}