{
  "type": "Feature",
  "properties": {
    "iso:country":"US",
    "sg:address":"6308 Falls of Neuse Rd",
    "sg:city":"Raleigh",
    "sg:classifiers":[
        {
            "category":"Banks & Credit Unions",
            "subcategory":"Investment Brokerage",
            "type":"Services"
        }
    ],
    "sg:phone":"+1 919 872 9713",
    "sg:postcode":"27615",
    "sg:province":"NC",
    "sg:tags":[
        "advisory",
        "financial"
    ],
    "wof:name":"American General Financial Svc",
    "wof:placetype":"venue"
},
  "geometry": {"coordinates":[-78.62101,35.869212],"type":"Point"}
}