{
  "type": "Feature",
  "properties": {
    "addr:full":"20 Brunswick St Wilmington NC 28401",
    "addr:housenumber":"20",
    "addr:postcode":"28401",
    "addr:street":"Brunswick St",
    "iso:country":"US",
    "sg:address":"20 Brunswick St",
    "sg:city":"Wilmington",
    "sg:classifiers":[
        {
            "category":"Building & Trades",
            "subcategory":"Equipment Rental",
            "type":"Services"
        }
    ],
    "sg:phone":"+1 910 251 8809",
    "sg:postcode":"28401",
    "sg:province":"NC",
    "sg:tags":[
        "leasing"
    ],
    "wof:name":"Bovis Lend Lease PPD",
    "wof:placetype":"venue"
},
  "geometry": {"coordinates":[-77.949866,34.244141],"type":"Point"}
}