{
  "type": "Feature",
  "properties": {
    "iso:country":"US",
    "sg:address":"6320 Quadrangle Dr Ste 120",
    "sg:city":"Chapel Hill",
    "sg:classifiers":[
        {
            "category":"Banks & Credit Unions",
            "subcategory":"Investment Brokerage",
            "type":"Services"
        },
        {
            "category":"Banks & Credit Unions",
            "subcategory":"Financial Services",
            "type":"Services"
        }
    ],
    "sg:phone":"+1 919 408 3131",
    "sg:postcode":"27517",
    "sg:province":"NC",
    "sg:tags":[
        "investing",
        "advising"
    ],
    "sg:website":"www.ameripriseadvisors.com/donal...",
    "wof:name":"Donald Rutledge - Ameriprise Financial Advisor",
    "wof:placetype":"venue"
},
  "geometry": {"coordinates":[-78.977709,35.911077],"type":"Point"}
}