{
  "type": "Feature",
  "properties": {
    "iso:country":"US",
    "sg:address":"18 E 11th St",
    "sg:city":"Roanoke Rapids",
    "sg:classifiers":[
        {
            "category":"Insurance",
            "subcategory":"Insurance Agent",
            "type":"Services"
        }
    ],
    "sg:phone":"+1 252 537 3934",
    "sg:postcode":"27870",
    "sg:province":"NC",
    "sg:tags":[
        "adjuster"
    ],
    "wof:name":"Myco Adjusting Svc",
    "wof:placetype":"venue"
},
  "geometry": {"coordinates":[-77.657878,36.454272],"type":"Point"}
}