{
  "type": "Feature",
  "properties": {
    "addr:full":"2147 Ten Ten Rd Apex NC 27539",
    "addr:housenumber":"2147",
    "addr:postcode":"27539",
    "addr:street":"Ten Ten Rd",
    "iso:country":"US",
    "sg:address":"2147 Ten Ten Rd",
    "sg:city":"Apex",
    "sg:classifiers":[
        {
            "category":"Retail",
            "subcategory":"Auto Rental",
            "type":"Services"
        }
    ],
    "sg:phone":"+1 919 267 3941",
    "sg:postcode":"27539",
    "sg:province":"NC",
    "sg:tags":[
        "car"
    ],
    "wof:name":"Thrifty Car Rental",
    "wof:placetype":"venue"
},
  "geometry": {"coordinates":[-78.818235,35.720157],"type":"Point"}
}