{
  "type": "Feature",
  "properties": {
    "addr:full":"1507 E Sugar Creek Rd Charlotte NC 28205",
    "addr:housenumber":"1507",
    "addr:postcode":"28205",
    "addr:street":"E Sugar Creek Rd",
    "iso:country":"US",
    "sg:address":"1507 E Sugar Creek Rd",
    "sg:city":"Charlotte",
    "sg:classifiers":[
        {
            "category":"Wholesale",
            "subcategory":"Durable Goods & Equipment",
            "type":"Manufacturing & Wholesale Goods"
        }
    ],
    "sg:phone":"+1 704 338 9573",
    "sg:postcode":"28205",
    "sg:province":"NC",
    "sg:tags":[
        "exporter"
    ],
    "wof:name":"Lomax Tile & Marble Inc",
    "wof:placetype":"venue"
},
  "geometry": {"coordinates":[-80.779976,35.242644],"type":"Point"}
}