{
  "type": "Feature",
  "properties": {
    "iso:country":"US",
    "sg:address":"2514 Sand Hill Rd",
    "sg:city":"Fayetteville",
    "sg:classifiers":[
        {
            "category":"Social Services",
            "subcategory":"Child Care",
            "type":"Services"
        }
    ],
    "sg:phone":"+1 910 484 1060",
    "sg:postcode":"28306",
    "sg:province":"NC",
    "sg:tags":[
        "day"
    ],
    "wof:name":"Sandy Ridge Day Care",
    "wof:placetype":"venue"
},
  "geometry": {"coordinates":[-78.85888199999999,34.931516],"type":"Point"}
}