{
  "type": "Feature",
  "properties": {
    "addr:full":"3725 S Memorial Dr Greenville NC 27834",
    "addr:housenumber":"3725",
    "addr:postcode":"27834",
    "addr:street":"S Memorial Dr",
    "iso:country":"US",
    "sg:address":"3725 S Memorial Dr",
    "sg:city":"Greenville",
    "sg:classifiers":[
        {
            "category":"Retail",
            "subcategory":"Veterinary Services",
            "type":"Services"
        }
    ],
    "sg:phone":"+1 252 355 6167",
    "sg:postcode":"27834",
    "sg:province":"NC",
    "sg:tags":[
        "a",
        "clinic",
        "veterinarian",
        "as",
        "operates"
    ],
    "wof:name":"McLawhorn Animal Clinic P A",
    "wof:placetype":"venue"
},
  "geometry": {"coordinates":[-77.404892,35.562552],"type":"Point"}
}