{
  "type": "Feature",
  "properties": {
    "iso:country":"US",
    "sg:address":"1101 Tuxedo Ct",
    "sg:city":"Charlotte",
    "sg:classifiers":[
        {
            "category":"Wholesale",
            "subcategory":"Machinery & Supplies",
            "type":"Manufacturing & Wholesale Goods"
        }
    ],
    "sg:phone":"+1 704 364 4448",
    "sg:postcode":"28211",
    "sg:province":"NC",
    "sg:tags":[
        "equipment",
        "printing"
    ],
    "wof:name":"Ketchie & Associates",
    "wof:placetype":"venue"
},
  "geometry": {"coordinates":[-80.767478,35.163245],"type":"Point"}
}