{
  "type": "Feature",
  "properties": {
    "iso:country":"US",
    "sg:address":"112 Smith St",
    "sg:city":"Locust",
    "sg:classifiers":[
        {
            "category":"Home & Garden",
            "subcategory":"Building Materials",
            "type":"Retail Goods"
        }
    ],
    "sg:phone":"+1 704 888 3441",
    "sg:postcode":"28097",
    "sg:province":"NC",
    "wof:name":"Piedmont Overhead Door",
    "wof:placetype":"venue"
},
  "geometry": {"coordinates":[-80.428361,35.265986],"type":"Point"}
}