{
  "type": "Feature",
  "properties": {
    "iso:country":"US",
    "sg:address":"1280 N Webb St",
    "sg:city":"Selma",
    "sg:classifiers":[
        {
            "category":"Organizations",
            "subcategory":"Religious Organization",
            "type":"Services"
        }
    ],
    "sg:phone":"+1 919 965 3414",
    "sg:postcode":"27576",
    "sg:province":"NC",
    "sg:tags":[
        "church"
    ],
    "wof:name":"Vision Of The Lamb Ministries",
    "wof:placetype":"venue"
},
  "geometry": {"coordinates":[-78.27537100000001,35.543455],"type":"Point"}
}