{
  "type": "Feature",
  "properties": {
    "iso:country":"US",
    "sg:address":"504 Schnapps Ln",
    "sg:city":"Holly Springs",
    "sg:classifiers":[
        {
            "category":"Building & Trades",
            "subcategory":"Plumbing",
            "type":"Services"
        }
    ],
    "sg:phone":"+1 919 557 6340",
    "sg:postcode":"27540",
    "sg:province":"NC",
    "sg:tags":[
        "conditioning",
        "air",
        "system",
        "contractor"
    ],
    "wof:name":"Tatum Refrigeration & Air Cond",
    "wof:placetype":"venue"
},
  "geometry": {"coordinates":[-78.812955,35.618049],"type":"Point"}
}