{
  "type": "Feature",
  "properties": {
    "addr:full":"583 Oakwood Cir Lexington NC 27295",
    "addr:housenumber":"583",
    "addr:postcode":"27295",
    "addr:street":"Oakwood Cir",
    "iso:country":"US",
    "sg:address":"583 Oakwood Cir",
    "sg:city":"Lexington",
    "sg:classifiers":[
        {
            "category":"Building & Trades",
            "subcategory":"Cleaning & Sanitation",
            "type":"Services"
        }
    ],
    "sg:phone":"+1 336 787 3880",
    "sg:postcode":"27295",
    "sg:province":"NC",
    "sg:tags":[
        "janitor"
    ],
    "wof:name":"Piedmont Cleaning Svc",
    "wof:placetype":"venue"
},
  "geometry": {"coordinates":[-80.33275999999999,35.87151],"type":"Point"}
}