{
  "type": "Feature",
  "properties": {
    "addr:full":"1396 Sand Hill Rd Candler NC 28715",
    "addr:housenumber":"1396",
    "addr:postcode":"28715",
    "addr:street":"Sand Hill Rd",
    "iso:country":"US",
    "sg:address":"1396 Sand Hill Rd",
    "sg:city":"Candler",
    "sg:classifiers":[
        {
            "category":"Health Services",
            "subcategory":"Dentist",
            "type":"Services"
        }
    ],
    "sg:phone":"+1 828 670 1966",
    "sg:postcode":"28715",
    "sg:province":"NC",
    "wof:name":"Yoon Stuart S DDS PA",
    "wof:placetype":"venue"
},
  "geometry": {"coordinates":[-82.650235,35.539316],"type":"Point"}
}