{
  "type": "Feature",
  "properties": {
    "addr:full":"4942 Tanbark Dr Wilmington NC 28412",
    "addr:housenumber":"4942",
    "addr:postcode":"28412",
    "addr:street":"Tanbark Dr",
    "iso:country":"US",
    "sg:address":"4942 Tanbark Dr",
    "sg:city":"Wilmington",
    "sg:classifiers":[
        {
            "category":"Home & Garden",
            "subcategory":"Furniture",
            "type":"Retail Goods"
        }
    ],
    "sg:phone":"+1 910 675 3350",
    "sg:postcode":"28412",
    "sg:province":"NC",
    "sg:tags":[
        "builder",
        "custom"
    ],
    "wof:name":"Homestead Country Built Frntr",
    "wof:placetype":"venue"
},
  "geometry": {"coordinates":[-77.919123,34.143433],"type":"Point"}
}