{
  "type": "Feature",
  "properties": {
    "addr:full":"417 S Mountain St Cherryville NC 28021",
    "addr:housenumber":"417",
    "addr:postcode":"28021",
    "addr:street":"S Mountain St",
    "iso:country":"US",
    "sg:address":"417 S Mountain St",
    "sg:city":"Cherryville",
    "sg:classifiers":[
        {
            "category":"Organizations",
            "subcategory":"Religious Organization",
            "type":"Services"
        }
    ],
    "sg:phone":"+1 704 435 5621",
    "sg:postcode":"28021",
    "sg:province":"NC",
    "sg:tags":[
        "church"
    ],
    "wof:name":"Rudisill Chpel AME Zion Church",
    "wof:placetype":"venue"
},
  "geometry": {"coordinates":[-81.377807,35.374233],"type":"Point"}
}