{
  "type": "Feature",
  "properties": {
    "addr:full":"3060 State Hwy 18 S Morganton NC 28655",
    "addr:housenumber":"3060",
    "addr:postcode":"28655",
    "addr:street":"State Hwy 18 S",
    "iso:country":"US",
    "sg:address":"3060 State Hwy 18 S",
    "sg:city":"Morganton",
    "sg:classifiers":[
        {
            "category":"Real Estate",
            "subcategory":"Real Estate Agent",
            "type":"Services"
        }
    ],
    "sg:phone":"+1 828 430 8750",
    "sg:postcode":"28655",
    "sg:province":"NC",
    "wof:name":"United Country Property Place",
    "wof:placetype":"venue"
},
  "geometry": {"coordinates":[-81.64031199999999,35.709229],"type":"Point"}
}