{
  "type": "Feature",
  "properties": {
    "iso:country":"US",
    "sg:address":"1801 Westfield Rd",
    "sg:city":"Mount Airy",
    "sg:classifiers":[
        {
            "category":"Personal",
            "subcategory":"Barber",
            "type":"Services"
        }
    ],
    "sg:phone":"+1   ",
    "sg:postcode":"27030",
    "sg:province":"NC",
    "sg:tags":[
        "shop"
    ],
    "wof:name":"Bannertown Baber Shop",
    "wof:placetype":"venue"
},
  "geometry": {"coordinates":[-80.587474,36.486422],"type":"Point"}
}