{
  "type": "Feature",
  "properties": {
    "addr:full":"1375 Onsville Dr Jacksonville NC 28546",
    "addr:housenumber":"1375",
    "addr:postcode":"28546",
    "addr:street":"Onsville Dr",
    "iso:country":"US",
    "sg:address":"1375 Onsville Dr",
    "sg:city":"Jacksonville",
    "sg:classifiers":[
        {
            "category":"Organizations",
            "subcategory":"Community Association",
            "type":"Services"
        }
    ],
    "sg:phone":"+1 910 347 3258",
    "sg:postcode":"28546",
    "sg:province":"NC",
    "sg:tags":[
        "club"
    ],
    "wof:name":"Awana Clubs",
    "wof:placetype":"venue"
},
  "geometry": {"coordinates":[-77.413912,34.781186],"type":"Point"}
}