{
  "type": "Feature",
  "properties": {
    "iso:country":"US",
    "sg:address":"108 S Main St",
    "sg:city":"Reidsville",
    "sg:classifiers":[
        {
            "category":"Professional",
            "subcategory":"Lawyer & Legal Services",
            "type":"Services"
        }
    ],
    "sg:phone":"+1 336 349 4364",
    "sg:postcode":"27320",
    "sg:province":"NC",
    "sg:tags":[
        "attorney"
    ],
    "wof:name":"Farver Skidmore & Mc Donough",
    "wof:placetype":"venue"
},
  "geometry": {"coordinates":[-79.66597,36.361449],"type":"Point"}
}