{
  "type": "Feature",
  "properties": {
    "addr:full":"11823 Retail Dr Wake Forest NC 27587",
    "addr:housenumber":"11823",
    "addr:postcode":"27587",
    "addr:street":"Retail Dr",
    "iso:country":"US",
    "sg:address":"11823 Retail Dr",
    "sg:city":"Wake Forest",
    "sg:classifiers":[
        {
            "category":"Utilities",
            "subcategory":"Mobile Phone",
            "type":"Services"
        }
    ],
    "sg:phone":"+1 919 562 8881",
    "sg:postcode":"27587",
    "sg:province":"NC",
    "sg:tags":[
        "telephone",
        "cellular"
    ],
    "wof:name":"Sprint PCS",
    "wof:placetype":"venue"
},
  "geometry": {"coordinates":[-78.54133,35.971484],"type":"Point"}
}