{
  "type": "Feature",
  "properties": {
    "addr:full":"211 NW Broad St Southern Pines NC 28387",
    "addr:housenumber":"211",
    "addr:postcode":"28387",
    "addr:street":"Nw Broad St",
    "iso:country":"US",
    "sg:address":"211 NW Broad St",
    "sg:city":"Southern Pines",
    "sg:classifiers":[
        {
            "category":"Shopping",
            "subcategory":"Clothing, Apparel, & Fashions",
            "type":"Retail Goods"
        }
    ],
    "sg:phone":"+1 910 246 0383",
    "sg:postcode":"28387",
    "sg:province":"NC",
    "sg:tags":[
        "alteration"
    ],
    "wof:name":"Alteration By Bonnie Moore",
    "wof:placetype":"venue"
},
  "geometry": {"coordinates":[-79.38961399999999,35.175427],"type":"Point"}
}