{
  "type": "Feature",
  "properties": {
    "iso:country":"US",
    "sg:address":"1000 E Chatham St",
    "sg:city":"Cary",
    "sg:classifiers":[
        {
            "category":"Shopping",
            "type":"Retail Goods"
        }
    ],
    "sg:phone":"+1 919 481 0037",
    "sg:postcode":"27511",
    "sg:province":"NC",
    "sg:tags":[
        "equipment",
        "installation",
        "telephone",
        "sales"
    ],
    "wof:name":"Dynamic Telecom",
    "wof:placetype":"venue"
},
  "geometry": {"coordinates":[-78.75501199999999,35.790566],"type":"Point"}
}