{
  "type": "Feature",
  "properties": {
    "addr:full":"42 S Market St Asheville NC 28801",
    "addr:housenumber":"42",
    "addr:postcode":"28801",
    "addr:street":"S Market St",
    "iso:country":"US",
    "sg:address":"42 S Market St",
    "sg:city":"Asheville",
    "sg:classifiers":[
        {
            "category":"Restaurant",
            "type":"Food & Drink"
        }
    ],
    "sg:phone":"+1 828 225 3031",
    "sg:postcode":"28801",
    "sg:province":"NC",
    "wof:name":"Ritz",
    "wof:placetype":"venue"
},
  "geometry": {"coordinates":[-82.550301,35.59495],"type":"Point"}
}