{
  "type": "Feature",
  "properties": {
    "addr:full":"201 N Main St Laurinburg NC 28352",
    "addr:housenumber":"201",
    "addr:postcode":"28352",
    "addr:street":"N Main St",
    "iso:country":"US",
    "sg:address":"201 N Main St",
    "sg:city":"Laurinburg",
    "sg:classifiers":[
        {
            "category":"Restaurant",
            "type":"Food & Drink"
        }
    ],
    "sg:phone":"+1 910 277 8538",
    "sg:postcode":"28352",
    "sg:province":"NC",
    "sg:tags":[
        "eating"
    ],
    "wof:name":"Jesse's Pizza & Hot Subs",
    "wof:placetype":"venue"
},
  "geometry": {"coordinates":[-79.46041700000001,34.778565],"type":"Point"}
}