{
  "type": "Feature",
  "properties": {
    "iso:country":"US",
    "sg:address":"3011 Spring Garden St",
    "sg:city":"Greensboro",
    "sg:classifiers":[
        {
            "category":"Professional",
            "subcategory":"Accounting & Tax Preparation",
            "type":"Services"
        }
    ],
    "sg:phone":"+1   ",
    "sg:postcode":"27403",
    "sg:province":"NC",
    "sg:tags":[
        "return"
    ],
    "wof:name":"Freedom Tax Service",
    "wof:placetype":"venue"
},
  "geometry": {"coordinates":[-79.843206,36.062214],"type":"Point"}
}