{
  "type": "Feature",
  "properties": {
    "addr:full":"1730 Link Rd Winston Salem NC 27103",
    "addr:housenumber":"1730",
    "addr:postcode":"27103",
    "addr:street":"Link Rd",
    "iso:country":"US",
    "sg:address":"1730 Link Rd",
    "sg:city":"Winston Salem",
    "sg:classifiers":[
        {
            "category":"Education",
            "subcategory":"School",
            "type":"Public Place"
        }
    ],
    "sg:phone":"+1 336 722 7204",
    "sg:postcode":"27103",
    "sg:province":"NC",
    "sg:tags":[
        "religious"
    ],
    "sg:website":"www.ourladyofmercyschool.org",
    "wof:name":"Our Lady Of Mercy School",
    "wof:placetype":"venue"
},
  "geometry": {"coordinates":[-80.262843,36.070199],"type":"Point"}
}