{
  "type": "Feature",
  "properties": {
    "addr:full":"2606 Branchwood Dr Greensboro NC 27408",
    "addr:housenumber":"2606",
    "addr:postcode":"27408",
    "addr:street":"Branchwood Dr",
    "iso:country":"US",
    "sg:address":"2606 Branchwood Dr",
    "sg:city":"Greensboro",
    "sg:classifiers":[
        {
            "category":"Real Estate",
            "subcategory":"Real Estate Agent",
            "type":"Services"
        }
    ],
    "sg:phone":"+1 336 286 7080",
    "sg:postcode":"27408",
    "sg:province":"NC",
    "sg:tags":[
        "appraiser"
    ],
    "wof:name":"Michael J Hunter",
    "wof:placetype":"venue"
},
  "geometry": {"coordinates":[-79.823516,36.106004],"type":"Point"}
}