{
  "type": "Feature",
  "properties": {
    "iso:country":"US",
    "sg:address":"3515 Frog Pond Pl",
    "sg:city":"Wilmington",
    "sg:classifiers":[
        {
            "category":"Retail",
            "subcategory":"Car Wash",
            "type":"Services"
        }
    ],
    "sg:phone":"+1   ",
    "sg:postcode":"28403",
    "sg:province":"NC",
    "sg:tags":[
        "carwash"
    ],
    "wof:name":"Special Touch Detailing",
    "wof:placetype":"venue"
},
  "geometry": {"coordinates":[-77.90199,34.235373],"type":"Point"}
}