{
  "type": "Feature",
  "properties": {
    "addr:full":"14135 Steele Creek Rd Charlotte NC 28273",
    "addr:housenumber":"14135",
    "addr:postcode":"28273",
    "addr:street":"Steele Creek Rd",
    "iso:country":"US",
    "sg:address":"14135 Steele Creek Rd",
    "sg:city":"Charlotte",
    "sg:classifiers":[
        {
            "category":"Shopping",
            "subcategory":"Beauty & Cosmetics",
            "type":"Retail Goods"
        },
        {
            "category":"Home & Garden",
            "subcategory":"Home Furnishings",
            "type":"Retail Goods"
        },
        {
            "category":"Personal",
            "subcategory":"Skin Care",
            "type":"Services"
        }
    ],
    "sg:phone":"+1 704 588 1179",
    "sg:postcode":"28273",
    "sg:province":"NC",
    "sg:tags":[
        "candle",
        "perfume"
    ],
    "sg:website":"http://www.bathandbodyworks.com/",
    "wof:name":"Bath & Body Works",
    "wof:placetype":"venue"
},
  "geometry": {"coordinates":[-80.988445,35.101951],"type":"Point"}
}