{
  "type": "Feature",
  "properties": {
    "addr:full":"6631 Union Rd Gastonia NC 28056",
    "addr:housenumber":"6631",
    "addr:postcode":"28056",
    "addr:street":"Union Rd",
    "iso:country":"US",
    "sg:address":"6631 Union Rd",
    "sg:city":"Gastonia",
    "sg:classifiers":[
        {
            "category":"Professional",
            "type":"Services"
        }
    ],
    "sg:phone":"+1 704 853 8438",
    "sg:postcode":"28056",
    "sg:province":"NC",
    "wof:name":"Tony C Crowson",
    "wof:placetype":"venue"
},
  "geometry": {"coordinates":[-81.105277,35.165482],"type":"Point"}
}