{
  "type": "Feature",
  "properties": {
    "addr:full":"405 Chaps Ct Jacksonville NC 28546",
    "addr:housenumber":"405",
    "addr:postcode":"28546",
    "addr:street":"Chaps Ct",
    "iso:country":"US",
    "sg:address":"405 Chaps Ct",
    "sg:city":"Jacksonville",
    "sg:classifiers":[
        {
            "category":"Travel",
            "subcategory":"Travel Agent",
            "type":"Entertainment"
        }
    ],
    "sg:phone":"+1 910 577 0026",
    "sg:postcode":"28546",
    "sg:province":"NC",
    "sg:tags":[
        "cruise"
    ],
    "wof:name":"Cruise Planners",
    "wof:placetype":"venue"
},
  "geometry": {"coordinates":[-77.301348,34.760078],"type":"Point"}
}