{
  "type": "Feature",
  "properties": {
    "iso:country":"US",
    "sg:address":"1100 National Hwy",
    "sg:city":"Thomasville",
    "sg:classifiers":[
        {
            "category":"Wholesale",
            "subcategory":"Machinery & Supplies",
            "type":"Manufacturing & Wholesale Goods"
        }
    ],
    "sg:phone":"+1 336 474 2531",
    "sg:postcode":"27360",
    "sg:province":"NC",
    "sg:tags":[
        "contractor"
    ],
    "wof:name":"Southern Drill Inc",
    "wof:placetype":"venue"
},
  "geometry": {"coordinates":[-80.062978,35.905589],"type":"Point"}
}