{
  "type": "Feature",
  "properties": {
    "addr:full":"103 Outer Banks Dr Havelock NC 28532",
    "addr:housenumber":"103",
    "addr:postcode":"28532",
    "addr:street":"Outer Banks Dr",
    "iso:country":"US",
    "sg:address":"103 Outer Banks Dr",
    "sg:city":"Havelock",
    "sg:classifiers":[
        {
            "category":"Shopping",
            "subcategory":"Florist",
            "type":"Retail Goods"
        }
    ],
    "sg:phone":"+1 252 447 1177",
    "sg:postcode":"28532",
    "sg:province":"NC",
    "wof:name":"House Of Silk Flowers",
    "wof:placetype":"venue"
},
  "geometry": {"coordinates":[-76.87060200000001,34.882185],"type":"Point"}
}