{
  "type": "Feature",
  "properties": {
    "iso:country":"US",
    "sg:address":"4415 Raspberry Rd",
    "sg:city":"Wilmington",
    "sg:classifiers":[
        {
            "category":"Professional",
            "subcategory":"Business Services",
            "type":"Services"
        }
    ],
    "sg:phone":"+1 910 791 3196",
    "sg:postcode":"28405",
    "sg:province":"NC",
    "wof:name":"Creations Furniture",
    "wof:placetype":"venue"
},
  "geometry": {"coordinates":[-77.87035400000001,34.280057],"type":"Point"}
}