{
  "type": "Feature",
  "properties": {
    "iso:country":"US",
    "sg:address":"655 Highland Dr",
    "sg:city":"Eden",
    "sg:classifiers":[
        {
            "category":"Professional",
            "subcategory":"Accounting & Tax Preparation",
            "type":"Services"
        }
    ],
    "sg:phone":"+1   ",
    "sg:postcode":"27288",
    "sg:province":"NC",
    "wof:name":"Joseph W Chandler III CPA",
    "wof:placetype":"venue"
},
  "geometry": {"coordinates":[-79.755718,36.487598],"type":"Point"}
}