{
  "type": "Feature",
  "properties": {
    "addr:full":"720 Tuckaseegee Rd Charlotte NC 28208",
    "addr:housenumber":"720",
    "addr:postcode":"28208",
    "addr:street":"Tuckaseegee Rd",
    "iso:country":"US",
    "sg:address":"720 Tuckaseegee Rd",
    "sg:city":"Charlotte",
    "sg:classifiers":[
        {
            "category":"Home & Garden",
            "subcategory":"Building Materials",
            "type":"Retail Goods"
        }
    ],
    "sg:phone":"+1 704 376 5513",
    "sg:postcode":"28208",
    "sg:province":"NC",
    "sg:tags":[
        "siding"
    ],
    "wof:name":"Carolina Wholesale Building Co",
    "wof:placetype":"venue"
},
  "geometry": {"coordinates":[-80.87027,35.23668],"type":"Point"}
}