{
  "type": "Feature",
  "properties": {
    "addr:full":"769 Baker Ct Haw River NC 27258",
    "addr:housenumber":"769",
    "addr:postcode":"27258",
    "addr:street":"Baker Ct",
    "iso:country":"US",
    "sg:address":"769 Baker Ct",
    "sg:city":"Haw River",
    "sg:classifiers":[
        {
            "category":"Professional",
            "subcategory":"Computer Services",
            "type":"Services"
        }
    ],
    "sg:phone":"+1   ",
    "sg:postcode":"27258",
    "sg:province":"NC",
    "wof:name":"Advanced Computer Upgrade",
    "wof:placetype":"venue"
},
  "geometry": {"coordinates":[-79.330496,36.080123],"type":"Point"}
}