{
  "type": "Feature",
  "properties": {
    "iso:country":"US",
    "sg:address":"239 Teas St",
    "sg:city":"Andrews",
    "sg:classifiers":[
        {
            "category":"Retail",
            "subcategory":"Laundry & Dry Cleaning",
            "type":"Services"
        }
    ],
    "sg:phone":"+1 828 321 4338",
    "sg:postcode":"28901",
    "sg:province":"NC",
    "wof:name":"Sherrill Laundry Mat",
    "wof:placetype":"venue"
},
  "geometry": {"coordinates":[-83.834005,35.198227],"type":"Point"}
}