{
  "type": "Feature",
  "properties": {
    "addr:full":"6050 Murchison Rd Fayetteville NC 28311",
    "addr:postcode":"6050;28311",
    "addr:street":"Murchison Rd",
    "iso:country":"US",
    "sg:address":"6050 Murchison Rd",
    "sg:city":"Fayetteville",
    "sg:classifiers":[
        {
            "category":"Professional",
            "subcategory":"Research",
            "type":"Services"
        }
    ],
    "sg:phone":"+1 910 630 6111",
    "sg:postcode":"28311",
    "sg:province":"NC",
    "sg:tags":[
        "environmental",
        "ecological"
    ],
    "wof:name":"US Filter",
    "wof:placetype":"venue"
},
  "geometry": {"coordinates":[-78.93339899999999,35.118261],"type":"Point"}
}