{
  "type": "Feature",
  "properties": {
    "addr:full":"308 Metcalf St New Bern NC 28562",
    "addr:housenumber":"308",
    "addr:postcode":"28562",
    "addr:street":"Metcalf St",
    "iso:country":"US",
    "sg:address":"308 Metcalf St",
    "sg:city":"New Bern",
    "sg:classifiers":[
        {
            "category":"Personal",
            "subcategory":"Beauty Salon",
            "type":"Services"
        }
    ],
    "sg:phone":"+1 252 633 5938",
    "sg:postcode":"28562",
    "sg:province":"NC",
    "wof:name":"Judy's Beauty Salon",
    "wof:placetype":"venue"
},
  "geometry": {"coordinates":[-77.042806,35.108313],"type":"Point"}
}