{
  "type": "Feature",
  "properties": {
    "iso:country":"US",
    "sg:address":"5411 W Friendly Ave",
    "sg:city":"Greensboro",
    "sg:classifiers":[
        {
            "category":"Health Services",
            "subcategory":"Podiatrist",
            "type":"Services"
        },
        {
            "category":"Health Services",
            "subcategory":"Doctor",
            "type":"Services"
        }
    ],
    "sg:phone":"+1 336 218 8490",
    "sg:postcode":"27410",
    "sg:province":"NC",
    "sg:tags":[
        "medical"
    ],
    "wof:name":"Friendly Foot Center",
    "wof:placetype":"venue"
},
  "geometry": {"coordinates":[-79.884334,36.089071],"type":"Point"}
}