{
  "type": "Feature",
  "properties": {
    "iso:country":"US",
    "sg:address":"511 Constitution Dr",
    "sg:city":"Durham",
    "sg:classifiers":[
        {
            "category":"Building & Trades",
            "subcategory":"Construction",
            "type":"Services"
        }
    ],
    "sg:phone":"+1 919 272 2072",
    "sg:postcode":"27705",
    "sg:province":"NC",
    "sg:tags":[
        "driveway"
    ],
    "wof:name":"Classic Conrete Design",
    "wof:placetype":"venue"
},
  "geometry": {"coordinates":[-78.966926,36.018985],"type":"Point"}
}