{
  "type": "Feature",
  "properties": {
    "addr:full":"299 Swannanoa River Rd Asheville NC 28805",
    "addr:housenumber":"299",
    "addr:postcode":"28805",
    "addr:street":"Swannanoa River Rd",
    "iso:country":"US",
    "sg:address":"299 Swannanoa River Rd",
    "sg:city":"Asheville",
    "sg:classifiers":[
        {
            "category":"Restaurant",
            "type":"Food & Drink"
        }
    ],
    "sg:phone":"+1 828 298 6530",
    "sg:postcode":"28805",
    "sg:province":"NC",
    "wof:name":"Bonefish Grill",
    "wof:placetype":"venue"
},
  "geometry": {"coordinates":[-82.526703,35.574405],"type":"Point"}
}