{
  "type": "Feature",
  "properties": {
    "iso:country":"US",
    "sg:address":"614 N Raleigh St",
    "sg:city":"Rocky Mount",
    "sg:classifiers":[
        {
            "category":"Personal",
            "subcategory":"Beauty Salon",
            "type":"Services"
        }
    ],
    "sg:phone":"+1 252 977 0047",
    "sg:postcode":"27801",
    "sg:province":"NC",
    "sg:tags":[
        "shop"
    ],
    "wof:name":"Taylor's Beauty Salon",
    "wof:placetype":"venue"
},
  "geometry": {"coordinates":[-77.78352,35.942374],"type":"Point"}
}