{
  "type": "Feature",
  "properties": {
    "addr:full":"11830 Virgilina Rd Roxboro NC 27574",
    "addr:housenumber":"11830",
    "addr:postcode":"27574",
    "addr:street":"Virgilina Rd",
    "iso:country":"US",
    "sg:address":"11830 Virgilina Rd",
    "sg:city":"Roxboro",
    "sg:classifiers":[
        {
            "category":"Food & Beverages",
            "subcategory":"Groceries & Convenience Stores",
            "type":"Retail Goods"
        }
    ],
    "sg:phone":"+1 336 599 7770",
    "sg:postcode":"27574",
    "sg:province":"NC",
    "sg:tags":[
        "grocer"
    ],
    "wof:name":"C T Gentry Store",
    "wof:placetype":"venue"
},
  "geometry": {"coordinates":[-78.831407,36.508479],"type":"Point"}
}