{
  "type": "Feature",
  "properties": {
    "addr:full":"100 Byrd Rd Fairmont NC 28340",
    "addr:housenumber":"100",
    "addr:postcode":"28340",
    "addr:street":"Byrd Rd",
    "iso:country":"US",
    "sg:address":"100 Byrd Rd",
    "sg:city":"Fairmont",
    "sg:classifiers":[
        {
            "category":"Professional",
            "type":"Services"
        }
    ],
    "sg:phone":"+1 910 628 1440",
    "sg:postcode":"28340",
    "sg:province":"NC",
    "wof:name":"Custom Kolors",
    "wof:placetype":"venue"
},
  "geometry": {"coordinates":[-79.04076999999999,34.458417],"type":"Point"}
}