{
  "type": "Feature",
  "properties": {
    "addr:full":"18435 Harborside Dr Cornelius NC 28031",
    "addr:postcode":"18435;28031",
    "addr:street":"Harborside Dr",
    "iso:country":"US",
    "sg:address":"18435 Harborside Dr",
    "sg:city":"Cornelius",
    "sg:classifiers":[
        {
            "category":"Real Estate",
            "subcategory":"Real Estate Operator",
            "type":"Services"
        }
    ],
    "sg:phone":"+1 704 894 9455",
    "sg:postcode":"28031",
    "sg:province":"NC",
    "sg:tags":[
        "apartment"
    ],
    "wof:name":"Harborside Townhomes",
    "wof:placetype":"venue"
},
  "geometry": {"coordinates":[-80.891763,35.463801],"type":"Point"}
}