{
  "type": "Feature",
  "properties": {
    "addr:full":"628 Lanier Rd Norwood NC 28128",
    "addr:housenumber":"628",
    "addr:postcode":"28128",
    "addr:street":"Lanier Rd",
    "iso:country":"US",
    "sg:address":"628 Lanier Rd",
    "sg:city":"Norwood",
    "sg:classifiers":[
        {
            "category":"Social Services",
            "subcategory":"Child Care",
            "type":"Services"
        }
    ],
    "sg:phone":"+1 704 474 3343",
    "sg:postcode":"28128",
    "sg:province":"NC",
    "sg:tags":[
        "day"
    ],
    "wof:name":"Countryside Day Care Inc",
    "wof:placetype":"venue"
},
  "geometry": {"coordinates":[-80.109696,35.215897],"type":"Point"}
}