{
  "type": "Feature",
  "properties": {
    "addr:full":"102 E Jackson Blvd Erwin NC 28339",
    "addr:housenumber":"102",
    "addr:postcode":"28339",
    "addr:street":"E Jackson Blvd",
    "iso:country":"US",
    "sg:address":"102 E Jackson Blvd",
    "sg:city":"Erwin",
    "sg:classifiers":[
        {
            "category":"Organizations",
            "subcategory":"Religious Organization",
            "type":"Services"
        }
    ],
    "sg:phone":"+1 910 891 5200",
    "sg:postcode":"28339",
    "sg:province":"NC",
    "sg:tags":[
        "church"
    ],
    "wof:name":"Hope Inc",
    "wof:placetype":"venue"
},
  "geometry": {"coordinates":[-78.67522700000001,35.336397],"type":"Point"}
}