{
  "type": "Feature",
  "properties": {
    "iso:country":"US",
    "sg:address":"222 N Steele St",
    "sg:city":"Sanford",
    "sg:classifiers":[
        {
            "category":"Personal",
            "subcategory":"Barber",
            "type":"Services"
        }
    ],
    "sg:phone":"+1   ",
    "sg:postcode":"27330",
    "sg:province":"NC",
    "sg:tags":[
        "shop",
        "beauty"
    ],
    "wof:name":"Father & Son Barber Shop",
    "wof:placetype":"venue"
},
  "geometry": {"coordinates":[-79.181377,35.483446],"type":"Point"}
}