{
  "type": "Feature",
  "properties": {
    "iso:country":"US",
    "sg:address":"5140 Irish Potato Rd",
    "sg:city":"Kannapolis",
    "sg:classifiers":[
        {
            "category":"Organizations",
            "subcategory":"Religious Organization",
            "type":"Services"
        }
    ],
    "sg:phone":"+1 704 786 5987",
    "sg:postcode":"28083",
    "sg:province":"NC",
    "sg:tags":[
        "church"
    ],
    "wof:name":"New Testament Baptist",
    "wof:placetype":"venue"
},
  "geometry": {"coordinates":[-80.526825,35.49069],"type":"Point"}
}