{
  "type": "Feature",
  "properties": {
    "addr:full":"3312 Northside Dr Raleigh NC 27615",
    "addr:housenumber":"3312",
    "addr:postcode":"27615",
    "addr:street":"Northside Dr",
    "iso:country":"US",
    "sg:address":"3312 Northside Dr",
    "sg:city":"Raleigh",
    "sg:classifiers":[
        {
            "category":"Wholesale",
            "subcategory":"Machinery & Supplies",
            "type":"Manufacturing & Wholesale Goods"
        },
        {
            "category":"Manufacturing",
            "subcategory":"Tools & Machinery",
            "type":"Manufacturing & Wholesale Goods"
        }
    ],
    "sg:phone":"+1 919 790 3535",
    "sg:postcode":"27615",
    "sg:province":"NC",
    "sg:tags":[
        "handling",
        "for",
        "material",
        "representative",
        "crane",
        "manufacturer"
    ],
    "sg:website":"www.midatlanticcrane.com",
    "wof:name":"Mid-Atlantic Crane & Equipment",
    "wof:placetype":"venue"
},
  "geometry": {"coordinates":[-78.58058,35.88388],"type":"Point"}
}