{
  "type": "Feature",
  "properties": {
    "iso:country":"US",
    "sg:address":"3073 Soco Rd",
    "sg:city":"Maggie Valley",
    "sg:classifiers":[
        {
            "category":"Manufacturing",
            "subcategory":"Buildings",
            "type":"Manufacturing & Wholesale Goods"
        }
    ],
    "sg:phone":"+1 828 926 6999",
    "sg:postcode":"28751",
    "sg:province":"NC",
    "sg:tags":[
        "home",
        "log",
        "cabin"
    ],
    "wof:name":"Top Notch Log Homes",
    "wof:placetype":"venue"
},
  "geometry": {"coordinates":[-83.079615,35.513017],"type":"Point"}
}