{
  "type": "Feature",
  "properties": {
    "iso:country":"US",
    "sg:address":"7533 Sparkleberry Dr",
    "sg:city":"Indian Trail",
    "sg:classifiers":[
        {
            "category":"Professional",
            "subcategory":"Computer Services",
            "type":"Services"
        }
    ],
    "sg:phone":"+1   ",
    "sg:postcode":"28079",
    "sg:province":"NC",
    "sg:tags":[
        "consulting"
    ],
    "wof:name":"Access em All",
    "wof:placetype":"venue"
},
  "geometry": {"coordinates":[-80.65853300000001,35.040638],"type":"Point"}
}