{
  "type": "Feature",
  "properties": {
    "addr:full":"2050 New Bern Ave Raleigh NC 27610",
    "addr:housenumber":"2050",
    "addr:postcode":"27610",
    "addr:street":"New Bern Ave",
    "iso:country":"US",
    "sg:address":"2050 New Bern Ave",
    "sg:city":"Raleigh",
    "sg:classifiers":[
        {
            "category":"Building & Trades",
            "subcategory":"Equipment Rental",
            "type":"Services"
        }
    ],
    "sg:phone":"+1 919 231 8808",
    "sg:postcode":"27610",
    "sg:province":"NC",
    "sg:tags":[
        "household",
        "appliance"
    ],
    "wof:name":"Rent-A-Center",
    "wof:placetype":"venue"
},
  "geometry": {"coordinates":[-78.606809,35.779521],"type":"Point"}
}