{
  "type": "Feature",
  "properties": {
    "addr:full":"150 S Main St Troutman NC 28166",
    "addr:housenumber":"150",
    "addr:postcode":"28166",
    "addr:street":"S Main St",
    "iso:country":"US",
    "sg:address":"150 S Main St",
    "sg:city":"Troutman",
    "sg:classifiers":[
        {
            "category":"Restaurant",
            "type":"Food & Drink"
        }
    ],
    "sg:menulink":"http://www.allmenus.com/nc/fallstown/137664-subway/menu/",
    "sg:phone":"+1 704 528 8250",
    "sg:postcode":"28166",
    "sg:province":"NC",
    "sg:tags":[
        "american",
        "sandwich"
    ],
    "wof:name":"Subway",
    "wof:placetype":"venue"
},
  "geometry": {"coordinates":[-80.888892,35.701996],"type":"Point"}
}