{
  "type": "Feature",
  "properties": {
    "iso:country":"US",
    "sg:address":"665 Oak Ave",
    "sg:city":"Spruce Pine",
    "sg:classifiers":[
        {
            "category":"Home & Garden",
            "subcategory":"Garden Supply",
            "type":"Retail Goods"
        }
    ],
    "sg:phone":"+1 828 765 9133",
    "sg:postcode":"28777",
    "sg:province":"NC",
    "sg:tags":[
        "center"
    ],
    "wof:name":"Lakeview Nursery & Garden Ctr",
    "wof:placetype":"venue"
},
  "geometry": {"coordinates":[-82.06287399999999,35.915739],"type":"Point"}
}