{
  "type": "Feature",
  "properties": {
    "addr:full":"1390 US Hwy 17 Little River SC 29566",
    "addr:housenumber":"1390",
    "addr:postcode":"29566",
    "addr:street":"Us Hwy 17",
    "iso:country":"US",
    "sg:address":"1390 US Hwy 17",
    "sg:city":"Little River",
    "sg:classifiers":[
        {
            "category":"Banks & Credit Unions",
            "subcategory":"Bank",
            "type":"Services"
        }
    ],
    "sg:phone":"+1 843 249 7993",
    "sg:postcode":"29566",
    "sg:province":"SC",
    "sg:tags":[
        "state"
    ],
    "wof:name":"Carolina First Bank",
    "wof:placetype":"venue"
},
  "geometry": {"coordinates":[-78.621645,33.873409],"type":"Point"}
}