{
  "type": "Feature",
  "properties": {
    "iso:country":"US",
    "sg:address":"8125 Rising Meadow Rd",
    "sg:city":"Charlotte",
    "sg:classifiers":[
        {
            "category":"Manufacturing",
            "subcategory":"Tools & Machinery",
            "type":"Manufacturing & Wholesale Goods"
        }
    ],
    "sg:phone":"+1 704 544 9178",
    "sg:postcode":"28277",
    "sg:province":"NC",
    "sg:tags":[
        "textile"
    ],
    "wof:name":"Demtronics",
    "wof:placetype":"venue"
},
  "geometry": {"coordinates":[-80.79110900000001,35.092602],"type":"Point"}
}