{
  "type": "Feature",
  "properties": {
    "addr:full":"4633 W Gate Rd Wilmington NC 28405",
    "addr:housenumber":"4633",
    "addr:postcode":"28405",
    "addr:street":"W Gate Rd",
    "iso:country":"US",
    "sg:address":"4633 W Gate Rd",
    "sg:city":"Wilmington",
    "sg:classifiers":[
        {
            "category":"Building & Trades",
            "subcategory":"Construction",
            "type":"Services"
        }
    ],
    "sg:phone":"+1 910 231 1530",
    "sg:postcode":"28405",
    "sg:province":"NC",
    "sg:tags":[
        "concrete",
        "contractor"
    ],
    "wof:name":"Sanford Concrete Pavement Inc",
    "wof:placetype":"venue"
},
  "geometry": {"coordinates":[-77.885059,34.273705],"type":"Point"}
}