{
  "type": "Feature",
  "properties": {
    "iso:country":"US",
    "sg:address":"1512 E Franklin St",
    "sg:city":"Chapel Hill",
    "sg:classifiers":[
        {
            "category":"Professional",
            "type":"Services"
        }
    ],
    "sg:phone":"+1 919 929 5896",
    "sg:postcode":"27514",
    "sg:province":"NC",
    "sg:tags":[
        "establishment"
    ],
    "wof:name":"Summit Biosearch Inc",
    "wof:placetype":"venue"
},
  "geometry": {"coordinates":[-79.030283,35.934037],"type":"Point"}
}