{
  "type": "Feature",
  "properties": {
    "iso:country":"US",
    "sg:address":"116 Goldsboro St SW",
    "sg:city":"Wilson",
    "sg:classifiers":[
        {
            "category":"Travel",
            "subcategory":"Travel Agent",
            "type":"Entertainment"
        }
    ],
    "sg:phone":"+1 252 291 5651",
    "sg:postcode":"27893",
    "sg:province":"NC",
    "sg:tags":[
        "tours",
        "promoter"
    ],
    "wof:name":"Stallion Tours",
    "wof:placetype":"venue"
},
  "geometry": {"coordinates":[-77.91047399999999,35.724917],"type":"Point"}
}