{
  "type": "Feature",
  "properties": {
    "iso:country":"US",
    "sg:address":"403 Hobbs Rd",
    "sg:city":"Greensboro",
    "sg:classifiers":[
        {
            "category":"Professional",
            "type":"Services"
        }
    ],
    "sg:phone":"+1 336 299 5215",
    "sg:postcode":"27403",
    "sg:province":"NC",
    "wof:name":"Kindercise Ltd",
    "wof:placetype":"venue"
},
  "geometry": {"coordinates":[-79.837232,36.082786],"type":"Point"}
}