{
  "type": "Feature",
  "properties": {
    "addr:full":"3704 Alliance Dr Greensboro NC 27407",
    "addr:housenumber":"3704",
    "addr:postcode":"27407",
    "addr:street":"Alliance Dr",
    "iso:country":"US",
    "sg:address":"3704 Alliance Dr",
    "sg:city":"Greensboro",
    "sg:classifiers":[
        {
            "category":"Shopping",
            "subcategory":"Shoes",
            "type":"Retail Goods"
        }
    ],
    "sg:phone":"+1 336 547 9072",
    "sg:postcode":"27407",
    "sg:province":"NC",
    "wof:name":"Titan Industrial Footwear",
    "wof:placetype":"venue"
},
  "geometry": {"coordinates":[-79.87285799999999,36.055583],"type":"Point"}
}