{
  "type": "Feature",
  "properties": {
    "addr:full":"2723 Lexington Pointe Pl Matthews NC 28104",
    "addr:housenumber":"2723",
    "addr:postcode":"28104",
    "addr:street":"Lexington Pointe Pl",
    "iso:country":"US",
    "sg:address":"2723 Lexington Pointe Pl",
    "sg:city":"Matthews",
    "sg:classifiers":[
        {
            "category":"Professional",
            "subcategory":"Business Services",
            "type":"Services"
        }
    ],
    "sg:phone":"+1   ",
    "sg:postcode":"28104",
    "sg:province":"NC",
    "wof:name":"Framework Technologies Inc",
    "wof:placetype":"venue"
},
  "geometry": {"coordinates":[-80.667619,35.1119],"type":"Point"}
}