{
  "type": "Feature",
  "properties": {
    "addr:full":"2700 E Independence Blvd Charlotte NC 28205",
    "addr:housenumber":"2700",
    "addr:postcode":"28205",
    "addr:street":"E Independence Blvd",
    "iso:country":"US",
    "sg:address":"2700 E Independence Blvd",
    "sg:city":"Charlotte",
    "sg:classifiers":[
        {
            "category":"Exhibition Hall",
            "type":"Public Place"
        }
    ],
    "sg:phone":"+1 704 372 3600",
    "sg:postcode":"28205",
    "sg:province":"NC",
    "sg:tags":[
        "halls",
        "ballroom",
        "auditorium"
    ],
    "sg:website":"http://www.cricketarenacharlotte.com",
    "wof:name":"Ovens Auditorium",
    "wof:placetype":"venue"
},
  "geometry": {"coordinates":[-80.794466,35.205483],"type":"Point"}
}