{
  "type": "Feature",
  "properties": {
    "iso:country":"US",
    "sg:address":"516 Westchester Dr",
    "sg:city":"Greenville",
    "sg:classifiers":[
        {
            "category":"Real Estate",
            "subcategory":"Real Estate Operator",
            "type":"Services"
        }
    ],
    "sg:phone":"+1 252 756 9060",
    "sg:postcode":"27858",
    "sg:province":"NC",
    "sg:tags":[
        "property",
        "lessor"
    ],
    "wof:name":"Pridgeonfarm Inc",
    "wof:placetype":"venue"
},
  "geometry": {"coordinates":[-77.337129,35.580853],"type":"Point"}
}