{
  "type": "Feature",
  "properties": {
    "addr:full":"7151 Market St Wilmington NC 28411",
    "addr:housenumber":"7151",
    "addr:postcode":"28411",
    "addr:street":"Market St",
    "iso:country":"US",
    "sg:address":"7151 Market St",
    "sg:city":"Wilmington",
    "sg:classifiers":[
        {
            "category":"Autos & Motor Vehicles",
            "subcategory":"Automobile Sales",
            "type":"Retail Goods"
        }
    ],
    "sg:phone":"+1 910 681 0601",
    "sg:postcode":"28411",
    "sg:province":"NC",
    "sg:tags":[
        "car",
        "dealer"
    ],
    "wof:name":"R C Auto Sales LLC",
    "wof:placetype":"venue"
},
  "geometry": {"coordinates":[-77.819131,34.272153],"type":"Point"}
}