{
  "type": "Feature",
  "properties": {
    "iso:country":"US",
    "sg:address":"1022 Daisy Lee Dr",
    "sg:city":"Wilmington",
    "sg:classifiers":[
        {
            "category":"Organizations",
            "subcategory":"Religious Organization",
            "type":"Services"
        }
    ],
    "sg:phone":"+1   ",
    "sg:postcode":"28411",
    "sg:province":"NC",
    "wof:name":"C R Price Rev",
    "wof:placetype":"venue"
},
  "geometry": {"coordinates":[-77.844409,34.27178],"type":"Point"}
}