{
  "type": "Feature",
  "properties": {
    "addr:full":"5889 Lowland Rd Lowland NC 28552",
    "addr:housenumber":"5889",
    "addr:postcode":"28552",
    "addr:street":"Lowland Rd",
    "iso:country":"US",
    "sg:address":"5889 Lowland Rd",
    "sg:city":"Lowland",
    "sg:classifiers":[
        {
            "category":"Freight",
            "type":"Transportation"
        }
    ],
    "sg:phone":"+1 252 745 4103",
    "sg:postcode":"28552",
    "sg:province":"NC",
    "sg:tags":[
        "operator",
        "local",
        "trucking"
    ],
    "wof:name":"Ray Luptons Trucking",
    "wof:placetype":"venue"
},
  "geometry": {"coordinates":[-76.58150500000001,35.304095],"type":"Point"}
}