{
  "type": "Feature",
  "properties": {
    "iso:country":"US",
    "sg:address":"2730 24th Street Ct NE",
    "sg:city":"Hickory",
    "sg:classifiers":[
        {
            "category":"Professional",
            "subcategory":"Business Services",
            "type":"Services"
        }
    ],
    "sg:phone":"+1 828 312 8158",
    "sg:postcode":"28601",
    "sg:province":"NC",
    "sg:tags":[
        "engineering",
        "machining",
        "stamping",
        "molding"
    ],
    "wof:name":"Ory Inc",
    "wof:placetype":"venue"
},
  "geometry": {"coordinates":[-81.283766,35.76532],"type":"Point"}
}