{
  "type": "Feature",
  "properties": {
    "addr:full":"30 Vaughn Cir Fletcher NC 28732",
    "addr:housenumber":"30",
    "addr:postcode":"28732",
    "addr:street":"Vaughn Cir",
    "iso:country":"US",
    "sg:address":"30 Vaughn Cir",
    "sg:city":"Fletcher",
    "sg:classifiers":[
        {
            "category":"Professional",
            "subcategory":"Employment Agencies",
            "type":"Services"
        }
    ],
    "sg:phone":"+1 828 651 9230",
    "sg:postcode":"28732",
    "sg:province":"NC",
    "sg:tags":[
        "help",
        "contractor"
    ],
    "wof:name":"Professional Certified Stffng",
    "wof:placetype":"venue"
},
  "geometry": {"coordinates":[-82.51794,35.407537],"type":"Point"}
}