{
  "type": "Feature",
  "properties": {
    "iso:country":"US",
    "sg:address":"3714 Concord Pkwy S",
    "sg:city":"Concord",
    "sg:classifiers":[
        {
            "category":"Restaurant",
            "type":"Food & Drink"
        }
    ],
    "sg:phone":"+1 704 782 2226",
    "sg:postcode":"28027",
    "sg:province":"NC",
    "wof:name":"Ted's Family Restaurant",
    "wof:placetype":"venue"
},
  "geometry": {"coordinates":[-80.665817,35.369972],"type":"Point"}
}