{
  "type": "Feature",
  "properties": {
    "iso:country":"US",
    "sg:address":"1344 Patton Ave",
    "sg:city":"Asheville",
    "sg:classifiers":[
        {
            "category":"Food & Beverages",
            "subcategory":"Groceries & Convenience Stores",
            "type":"Retail Goods"
        }
    ],
    "sg:phone":"+1 828 252 4139",
    "sg:postcode":"28806",
    "sg:province":"NC",
    "sg:tags":[
        "grocer"
    ],
    "sg:website":"www.aldi.com",
    "wof:name":"Aldi",
    "wof:placetype":"venue"
},
  "geometry": {"coordinates":[-82.604992,35.583608],"type":"Point"}
}