{
  "type": "Feature",
  "properties": {
    "addr:full":"2507 Delaney Ave Wilmington NC 28403",
    "addr:housenumber":"2507",
    "addr:postcode":"28403",
    "addr:street":"Delaney Ave",
    "iso:country":"US",
    "sg:address":"2507 Delaney Ave",
    "sg:city":"Wilmington",
    "sg:classifiers":[
        {
            "category":"Health Services",
            "subcategory":"Doctor",
            "type":"Services"
        }
    ],
    "sg:phone":"+1 910 772 8091",
    "sg:postcode":"28403",
    "sg:province":"NC",
    "sg:tags":[
        "physician",
        "surgeon"
    ],
    "wof:name":"University Professional Svc",
    "wof:placetype":"venue"
},
  "geometry": {"coordinates":[-77.920277,34.198654],"type":"Point"}
}