{
  "type": "Feature",
  "properties": {
    "addr:full":"700 Washington St Graham NC 27253",
    "addr:housenumber":"700",
    "addr:postcode":"27253",
    "addr:street":"Washington St",
    "iso:country":"US",
    "sg:address":"700 Washington St",
    "sg:city":"Graham",
    "sg:classifiers":[
        {
            "category":"Building & Trades",
            "subcategory":"Construction",
            "type":"Services"
        }
    ],
    "sg:phone":"+1 336 228 8946",
    "sg:postcode":"27253",
    "sg:province":"NC",
    "sg:tags":[
        "house"
    ],
    "wof:name":"A Wright Way Home Improvements",
    "wof:placetype":"venue"
},
  "geometry": {"coordinates":[-79.40779499999999,36.078494],"type":"Point"}
}