{
  "type": "Feature",
  "properties": {
    "addr:full":"1500 S Madison St Whiteville NC 28472",
    "addr:housenumber":"1500",
    "addr:postcode":"28472",
    "addr:street":"S Madison St",
    "iso:country":"US",
    "sg:address":"1500 S Madison St",
    "sg:city":"Whiteville",
    "sg:classifiers":[
        {
            "category":"Autos & Motor Vehicles",
            "subcategory":"Automobile Sales",
            "type":"Retail Goods"
        }
    ],
    "sg:phone":"+1 910 642 8897",
    "sg:postcode":"28472",
    "sg:province":"NC",
    "sg:tags":[
        "used"
    ],
    "wof:name":"A & B Auto Sales",
    "wof:placetype":"venue"
},
  "geometry": {"coordinates":[-78.71229099999999,34.307978],"type":"Point"}
}