{
  "type": "Feature",
  "properties": {
    "iso:country":"US",
    "sg:address":"300 Price Rd",
    "sg:city":"Seven Springs",
    "sg:classifiers":[
        {
            "category":"Government",
            "subcategory":"Office",
            "type":"Public Place"
        }
    ],
    "sg:phone":"+1 252 569 0721",
    "sg:postcode":"28578",
    "sg:province":"NC",
    "sg:tags":[
        "management"
    ],
    "wof:name":"Seven Springs Recycling Center",
    "wof:placetype":"venue"
},
  "geometry": {"coordinates":[-77.880842,35.210588],"type":"Point"}
}