{
  "type": "Feature",
  "properties": {
    "addr:full":"1310 E Dixon Blvd Shelby NC 28152",
    "addr:housenumber":"1310",
    "addr:postcode":"28152",
    "addr:street":"E Dixon Blvd",
    "iso:country":"US",
    "sg:address":"1310 E Dixon Blvd",
    "sg:city":"Shelby",
    "sg:classifiers":[
        {
            "category":"Autos & Motor Vehicles",
            "subcategory":"Automobile Sales",
            "type":"Retail Goods"
        }
    ],
    "sg:phone":"+1 704 487 4561",
    "sg:postcode":"28152",
    "sg:province":"NC",
    "sg:tags":[
        "used"
    ],
    "wof:name":"McCluneys Used Cars",
    "wof:placetype":"venue"
},
  "geometry": {"coordinates":[-81.52055900000001,35.272861],"type":"Point"}
}