{
  "type": "Feature",
  "properties": {
    "addr:full":"2109 Saint Andrew St Tarboro NC 27886",
    "addr:housenumber":"2109",
    "addr:postcode":"27886",
    "addr:street":"Saint Andrew St",
    "iso:country":"US",
    "sg:address":"2109 Saint Andrew St",
    "sg:city":"Tarboro",
    "sg:classifiers":[
        {
            "category":"Retail",
            "subcategory":"Laundry & Dry Cleaning",
            "type":"Services"
        }
    ],
    "sg:phone":"+1 252 823 3755",
    "sg:postcode":"27886",
    "sg:province":"NC",
    "sg:tags":[
        "cleaners"
    ],
    "wof:name":"Zirkle's Cleaners & Laundry",
    "wof:placetype":"venue"
},
  "geometry": {"coordinates":[-77.542801,35.913095],"type":"Point"}
}