{
  "type": "Feature",
  "properties": {
    "iso:country":"US",
    "sg:address":"312 Dixie Trl",
    "sg:city":"Raleigh",
    "sg:classifiers":[
        {
            "category":"Social Services",
            "subcategory":"Job Training",
            "type":"Services"
        }
    ],
    "sg:phone":"+1 919 781 8698",
    "sg:postcode":"27607",
    "sg:province":"NC",
    "sg:tags":[
        "rehabilitation"
    ],
    "wof:name":"Medinsights Inc Rehab Nurse",
    "wof:placetype":"venue"
},
  "geometry": {"coordinates":[-78.675838,35.795103],"type":"Point"}
}