{
  "type": "Feature",
  "properties": {
    "iso:country":"US",
    "sg:address":"1495 State Hwy 66",
    "sg:city":"Kernersville",
    "sg:classifiers":[
        {
            "category":"Retail",
            "subcategory":"Auto Repair",
            "type":"Services"
        },
        {
            "category":"Wholesale",
            "subcategory":"Auto Parts",
            "type":"Manufacturing & Wholesale Goods"
        }
    ],
    "sg:phone":"+1 336 996 5591",
    "sg:postcode":"27284",
    "sg:province":"NC",
    "sg:tags":[
        "repairing",
        "automobile",
        "tire",
        "general"
    ],
    "sg:website":"www.tirekingdom.com",
    "wof:name":"Merchants Tire & Auto Center",
    "wof:placetype":"venue"
},
  "geometry": {"coordinates":[-80.062336,36.090027],"type":"Point"}
}