{
  "type": "Feature",
  "properties": {
    "iso:country":"US",
    "sg:address":"622 Eastern Ave",
    "sg:city":"Rocky Mount",
    "sg:classifiers":[
        {
            "category":"Building & Trades",
            "subcategory":"Construction",
            "type":"Services"
        }
    ],
    "sg:phone":"+1 252 972 8090",
    "sg:postcode":"27801",
    "sg:province":"NC",
    "sg:tags":[
        "concrete",
        "contractor"
    ],
    "wof:name":"James Lucas Concrete",
    "wof:placetype":"venue"
},
  "geometry": {"coordinates":[-77.787007,35.939146],"type":"Point"}
}