{
  "type": "Feature",
  "properties": {
    "iso:country":"US",
    "sg:address":"741 E Juniper Ave",
    "sg:city":"Wake Forest",
    "sg:classifiers":[
        {
            "category":"Organizations",
            "subcategory":"Religious Organization",
            "type":"Services"
        }
    ],
    "sg:phone":"+1 919 556 0322",
    "sg:postcode":"27587",
    "sg:province":"NC",
    "sg:tags":[
        "church"
    ],
    "wof:name":"Faith Tabernacle Uhc",
    "wof:placetype":"venue"
},
  "geometry": {"coordinates":[-78.498964,35.98245],"type":"Point"}
}