{
  "type": "Feature",
  "properties": {
    "addr:full":"854 Tiffany Blvd Rocky Mount NC 27804",
    "addr:housenumber":"854",
    "addr:postcode":"27804",
    "addr:street":"Tiffany Blvd",
    "iso:country":"US",
    "sg:address":"854 Tiffany Blvd",
    "sg:city":"Rocky Mount",
    "sg:classifiers":[
        {
            "category":"Health Services",
            "subcategory":"Clinic",
            "type":"Services"
        },
        {
            "category":"Social Services",
            "type":"Services"
        }
    ],
    "sg:phone":"+1 252 446 1411",
    "sg:postcode":"27804",
    "sg:province":"NC",
    "sg:tags":[
        "home"
    ],
    "wof:name":"Open-Minded Developmental Svc",
    "wof:placetype":"venue"
},
  "geometry": {"coordinates":[-77.80136299999999,35.976906],"type":"Point"}
}