{
  "type": "Feature",
  "properties": {
    "addr:full":"7900 Stevens Mill Rd Matthews NC 28104",
    "addr:housenumber":"7900",
    "addr:postcode":"28104",
    "addr:street":"Stevens Mill Rd",
    "iso:country":"US",
    "sg:address":"7900 Stevens Mill Rd",
    "sg:city":"Matthews",
    "sg:classifiers":[
        {
            "category":"Professional",
            "subcategory":"Business Services",
            "type":"Services"
        }
    ],
    "sg:phone":"+1   ",
    "sg:postcode":"28104",
    "sg:province":"NC",
    "wof:name":"SDC Technology",
    "wof:placetype":"venue"
},
  "geometry": {"coordinates":[-80.624983,35.142309],"type":"Point"}
}