{
  "type": "Feature",
  "properties": {
    "iso:country":"US",
    "sg:address":"8932 Nottoway Dr",
    "sg:city":"Charlotte",
    "sg:classifiers":[
        {
            "category":"Professional",
            "subcategory":"Engineering",
            "type":"Services"
        }
    ],
    "sg:phone":"+1   ",
    "sg:postcode":"28213",
    "sg:province":"NC",
    "wof:name":"Capper Art",
    "wof:placetype":"venue"
},
  "geometry": {"coordinates":[-80.735141,35.296111],"type":"Point"}
}