{
  "type": "Feature",
  "properties": {
    "addr:full":"6437 Eaglecrest Rd Charlotte NC 28212",
    "addr:housenumber":"6437",
    "addr:postcode":"28212",
    "addr:street":"Eaglecrest Rd",
    "iso:country":"US",
    "sg:address":"6437 Eaglecrest Rd",
    "sg:city":"Charlotte",
    "sg:classifiers":[
        {
            "category":"Freight",
            "type":"Transportation"
        }
    ],
    "sg:phone":"+1 704 537 9109",
    "sg:postcode":"28212",
    "sg:province":"NC",
    "sg:tags":[
        "courier"
    ],
    "wof:name":"Universal Parcel Service",
    "wof:placetype":"venue"
},
  "geometry": {"coordinates":[-80.753066,35.188381],"type":"Point"}
}