{
  "type": "Feature",
  "properties": {
    "addr:full":"3040 Old Cullowhee Rd Cullowhee NC 28723",
    "addr:housenumber":"3040",
    "addr:postcode":"28723",
    "addr:street":"Old Cullowhee Rd",
    "iso:country":"US",
    "sg:address":"3040 Old Cullowhee Rd",
    "sg:city":"Cullowhee",
    "sg:classifiers":[
        {
            "category":"Food & Beverages",
            "subcategory":"Groceries & Convenience Stores",
            "type":"Retail Goods"
        }
    ],
    "sg:phone":"+1 828 293 9198",
    "sg:postcode":"28723",
    "sg:province":"NC",
    "wof:name":"Frady Cats Convenience Store",
    "wof:placetype":"venue"
},
  "geometry": {"coordinates":[-83.17788299999999,35.31578],"type":"Point"}
}