{
  "type": "Feature",
  "properties": {
    "addr:full":"6999 Old Joyner Ln Rocky Mount NC 27803",
    "addr:housenumber":"6999",
    "addr:postcode":"27803",
    "addr:street":"Old Joyner Ln",
    "iso:country":"US",
    "sg:address":"6999 Old Joyner Ln",
    "sg:city":"Rocky Mount",
    "sg:classifiers":[
        {
            "category":"Wholesale",
            "subcategory":"Hardware",
            "type":"Manufacturing & Wholesale Goods"
        }
    ],
    "sg:phone":"+1 252 446 4293",
    "sg:postcode":"27803",
    "sg:province":"NC",
    "sg:tags":[
        "refrigeration"
    ],
    "wof:name":"S&S Refrigeration Inc",
    "wof:placetype":"venue"
},
  "geometry": {"coordinates":[-77.865341,35.862062],"type":"Point"}
}