{
  "type": "Feature",
  "properties": {
    "iso:country":"US",
    "sg:address":"5750 Farm Pond Ln",
    "sg:city":"Charlotte",
    "sg:classifiers":[
        {
            "category":"Social Services",
            "subcategory":"Child Care",
            "type":"Services"
        }
    ],
    "sg:phone":"+1 704 568 2419",
    "sg:postcode":"28212",
    "sg:province":"NC",
    "sg:website":"www.kindercare.com",
    "wof:name":"Kinder Care Learning Ctr",
    "wof:placetype":"venue"
},
  "geometry": {"coordinates":[-80.73893099999999,35.202066],"type":"Point"}
}