{
  "type": "Feature",
  "properties": {
    "iso:country":"US",
    "sg:address":"5517 Thornburg Dr",
    "sg:city":"Wake Forest",
    "sg:classifiers":[
        {
            "category":"Building & Trades",
            "subcategory":"Construction",
            "type":"Services"
        },
        {
            "category":"Restaurant",
            "type":"Food & Drink"
        }
    ],
    "sg:phone":"+1 919 556 7488",
    "sg:postcode":"27587",
    "sg:province":"NC",
    "sg:tags":[
        "product",
        "eating",
        "asphalt"
    ],
    "wof:name":"Quality Management Specialists",
    "wof:placetype":"venue"
},
  "geometry": {"coordinates":[-78.425163,35.925363],"type":"Point"}
}