{
  "type": "Feature",
  "properties": {
    "addr:full":"7805 Brown Mountain Beach Rd Collettsville NC 28611",
    "addr:housenumber":"7805",
    "addr:postcode":"28611",
    "addr:street":"Brown Mountain Beach Rd",
    "iso:country":"US",
    "sg:address":"7805 Brown Mountain Beach Rd",
    "sg:city":"Collettsville",
    "sg:classifiers":[
        {
            "category":"Professional",
            "subcategory":"Business Services",
            "type":"Services"
        },
        {
            "category":"Travel",
            "subcategory":"Travel Agent",
            "type":"Entertainment"
        }
    ],
    "sg:phone":"+1 828 759 0005",
    "sg:postcode":"28611",
    "sg:province":"NC",
    "sg:tags":[
        "information",
        "tourist"
    ],
    "wof:name":"Wilsons Creek Visitor Center",
    "wof:placetype":"venue"
},
  "geometry": {"coordinates":[-81.761169,35.953796],"type":"Point"}
}