{
  "type": "Feature",
  "properties": {
    "iso:country":"US",
    "sg:address":"60 Ormond Ave",
    "sg:city":"Arden",
    "sg:classifiers":[
        {
            "category":"Restaurant",
            "type":"Food & Drink"
        }
    ],
    "sg:phone":"+1 828 684 1480",
    "sg:postcode":"28704",
    "sg:province":"NC",
    "sg:tags":[
        "caterer"
    ],
    "wof:name":"Food For Thought",
    "wof:placetype":"venue"
},
  "geometry": {"coordinates":[-82.50582799999999,35.464245],"type":"Point"}
}