{
  "type": "Feature",
  "properties": {
    "iso:country":"US",
    "sg:address":"6442 Burnt Poplar Rd",
    "sg:city":"Greensboro",
    "sg:classifiers":[
        {
            "category":"Autos & Motor Vehicles",
            "subcategory":"Automobile Sales",
            "type":"Retail Goods"
        },
        {
            "category":"Wholesale",
            "subcategory":"Auto Parts",
            "type":"Manufacturing & Wholesale Goods"
        },
        {
            "category":"Retail",
            "subcategory":"Auto Repair",
            "type":"Services"
        }
    ],
    "sg:phone":"+1 336 668 2961",
    "sg:postcode":"27409",
    "sg:province":"NC",
    "sg:tags":[
        "equipment",
        "truck",
        "new"
    ],
    "sg:website":"http://coopertrucks.com/",
    "wof:name":"Cooper Kenworth",
    "wof:placetype":"venue"
},
  "geometry": {"coordinates":[-79.945612,36.07671],"type":"Point"}
}