{
  "type": "Feature",
  "properties": {
    "iso:country":"US",
    "sg:address":"1648 S Main St",
    "sg:city":"Waynesville",
    "sg:classifiers":[
        {
            "category":"Organizations",
            "subcategory":"Non-profit Organization",
            "type":"Services"
        }
    ],
    "sg:phone":"+1 828 456 1977",
    "sg:postcode":"28786",
    "sg:province":"NC",
    "sg:tags":[
        "information",
        "alcoholism",
        "treatment"
    ],
    "wof:name":"Gateway Clinic",
    "wof:placetype":"venue"
},
  "geometry": {"coordinates":[-83.00208600000001,35.470618],"type":"Point"}
}