{
  "type": "Feature",
  "properties": {
    "addr:full":"1931 US Hwy 421 Wilkesboro NC 28697",
    "addr:housenumber":"1931",
    "addr:postcode":"28697",
    "addr:street":"Us Hwy 421",
    "iso:country":"US",
    "sg:address":"1931 US Hwy 421",
    "sg:city":"Wilkesboro",
    "sg:classifiers":[
        {
            "category":"Autos & Motor Vehicles",
            "subcategory":"Automobile Sales",
            "type":"Retail Goods"
        }
    ],
    "sg:phone":"+1 336 903 1076",
    "sg:postcode":"28697",
    "sg:province":"NC",
    "sg:tags":[
        "car",
        "dealer"
    ],
    "sg:website":"www.empiredodge.com",
    "wof:name":"Empire Chrysler Dodge Jeep",
    "wof:placetype":"venue"
},
  "geometry": {"coordinates":[-81.202118,36.149911],"type":"Point"}
}