{
  "type": "Feature",
  "properties": {
    "iso:country":"US",
    "sg:address":"7608 State Hwy 62",
    "sg:city":"Trinity",
    "sg:classifiers":[
        {
            "category":"Personal",
            "subcategory":"Beauty Salon",
            "type":"Services"
        }
    ],
    "sg:phone":"+1 336 431 5974",
    "sg:postcode":"27370",
    "sg:province":"NC",
    "wof:name":"KLIP N KURL Beauty Shop",
    "wof:placetype":"venue"
},
  "geometry": {"coordinates":[-79.986459,35.902509],"type":"Point"}
}