{
  "type": "Feature",
  "properties": {
    "iso:country":"US",
    "sg:address":"3718 Randolph Rd",
    "sg:city":"Durham",
    "sg:classifiers":[
        {
            "category":"Real Estate",
            "subcategory":"Real Estate Agent",
            "type":"Services"
        }
    ],
    "sg:phone":"+1 919 489 0505",
    "sg:postcode":"27705",
    "sg:province":"NC",
    "wof:name":"La Union Properties",
    "wof:placetype":"venue"
},
  "geometry": {"coordinates":[-78.98894900000001,35.973624],"type":"Point"}
}