{
  "type": "Feature",
  "properties": {
    "iso:country":"US",
    "sg:address":"219 Boyd Lake Rd",
    "sg:city":"Hamlet",
    "sg:classifiers":[
        {
            "category":"Government",
            "subcategory":"Office",
            "type":"Public Place"
        }
    ],
    "sg:phone":"+1 910 582 2737",
    "sg:postcode":"28345",
    "sg:province":"NC",
    "sg:tags":[
        "state",
        "security"
    ],
    "wof:name":"National Guard",
    "wof:placetype":"venue"
},
  "geometry": {"coordinates":[-79.68362399999999,34.894204],"type":"Point"}
}