{
  "type": "Feature",
  "properties": {
    "addr:full":"3725 N Main St Farmville NC 27828",
    "addr:housenumber":"3725",
    "addr:postcode":"27828",
    "addr:street":"N Main St",
    "iso:country":"US",
    "sg:address":"3725 N Main St",
    "sg:city":"Farmville",
    "sg:classifiers":[
        {
            "category":"Government",
            "subcategory":"Office",
            "type":"Public Place"
        }
    ],
    "sg:phone":"+1 252 753 8184",
    "sg:postcode":"27828",
    "sg:province":"NC",
    "sg:tags":[
        "village"
    ],
    "sg:website":"www.farmvillenc.com",
    "wof:name":"Farmville Downtown Partnership",
    "wof:placetype":"venue"
},
  "geometry": {"coordinates":[-77.58502799999999,35.597268],"type":"Point"}
}