{
  "type": "Feature",
  "properties": {
    "addr:full":"5853 US Hwy 301 S Four Oaks NC 27524",
    "addr:housenumber":"5853",
    "addr:postcode":"27524",
    "addr:street":"Us Hwy 301 S Four",
    "iso:country":"US",
    "sg:address":"5853 US Hwy 301 S",
    "sg:city":"Four Oaks",
    "sg:classifiers":[
        {
            "category":"Personal",
            "subcategory":"Beauty Salon",
            "type":"Services"
        }
    ],
    "sg:phone":"+1   ",
    "sg:postcode":"27524",
    "sg:province":"NC",
    "sg:tags":[
        "shop"
    ],
    "wof:name":"B & B Beauty & Barber Salon",
    "wof:placetype":"venue"
},
  "geometry": {"coordinates":[-78.417349,35.448595],"type":"Point"}
}