{
  "type": "Feature",
  "properties": {
    "iso:country":"US",
    "sg:address":"1308 Queens Rd W",
    "sg:city":"Charlotte",
    "sg:classifiers":[
        {
            "category":"Professional",
            "subcategory":"Management & Consulting",
            "type":"Services"
        }
    ],
    "sg:phone":"+1 704 331 9429",
    "sg:postcode":"28207",
    "sg:province":"NC",
    "sg:tags":[
        "farm"
    ],
    "wof:name":"Rockhouse Vineyards",
    "wof:placetype":"venue"
},
  "geometry": {"coordinates":[-80.83472999999999,35.195282],"type":"Point"}
}