{
  "type": "Feature",
  "properties": {
    "iso:country":"US",
    "sg:address":"317 Norwood Blanchard Rd",
    "sg:city":"Wallace",
    "sg:phone":"+1 910 285 6135",
    "sg:postcode":"28521",
    "sg:province":"NC",
    "sg:tags":[
        "farm",
        "corn",
        "soybean"
    ],
    "wof:name":"Allen Smith",
    "wof:placetype":"venue"
},
  "geometry": {"coordinates":[-77.814876,34.810322],"type":"Point"}
}