{
  "type": "Feature",
  "properties": {
    "iso:country":"US",
    "sg:address":"123 W Union St",
    "sg:city":"Morganton",
    "sg:classifiers":[
        {
            "category":"Health Services",
            "subcategory":"Clinic",
            "type":"Services"
        }
    ],
    "sg:phone":"+1 828 438 8921",
    "sg:postcode":"28655",
    "sg:province":"NC",
    "sg:tags":[
        "specialty",
        "outpatient"
    ],
    "wof:name":"Mental Health Assn In NC",
    "wof:placetype":"venue"
},
  "geometry": {"coordinates":[-81.688255,35.745327],"type":"Point"}
}