{
  "type": "Feature",
  "properties": {
    "addr:full":"420 W 5th St Charlotte NC 28202",
    "addr:housenumber":"420",
    "addr:postcode":"28202",
    "addr:street":"W 5Th St",
    "iso:country":"US",
    "sg:address":"420 W 5th St",
    "sg:city":"Charlotte",
    "sg:classifiers":[
        {
            "category":"Museum",
            "type":"Entertainment"
        }
    ],
    "sg:phone":"+1 704 338 7233",
    "sg:postcode":"28202",
    "sg:province":"NC",
    "sg:tags":[
        "gallery"
    ],
    "wof:name":"Fire Museum & Education Center",
    "wof:placetype":"venue"
},
  "geometry": {"coordinates":[-80.845607,35.231292],"type":"Point"}
}