{
  "type": "Feature",
  "properties": {
    "iso:country":"US",
    "sg:address":"446 Jones Turner Rd",
    "sg:city":"Mount Olive",
    "sg:classifiers":[
        {
            "category":"Building & Trades",
            "subcategory":"Construction",
            "type":"Services"
        }
    ],
    "sg:phone":"+1 919 658 8046",
    "sg:postcode":"28365",
    "sg:province":"NC",
    "sg:tags":[
        "house"
    ],
    "wof:name":"Anderson & Phillips Home Imprv",
    "wof:placetype":"venue"
},
  "geometry": {"coordinates":[-78.022425,35.184003],"type":"Point"}
}