{
  "type": "Feature",
  "properties": {
    "addr:full":"4100 Carmel Rd Charlotte NC 28226",
    "addr:housenumber":"4100",
    "addr:postcode":"28226",
    "addr:street":"Carmel Rd",
    "iso:country":"US",
    "sg:address":"4100 Carmel Rd",
    "sg:city":"Charlotte",
    "sg:classifiers":[
        {
            "category":"Professional",
            "subcategory":"Advertising",
            "type":"Services"
        },
        {
            "category":"Wholesale",
            "subcategory":"Non-durable Goods",
            "type":"Manufacturing & Wholesale Goods"
        }
    ],
    "sg:phone":"+1 704 377 6567",
    "sg:postcode":"28226",
    "sg:province":"NC",
    "wof:name":"Adams Promotional Products",
    "wof:placetype":"venue"
},
  "geometry": {"coordinates":[-80.822429,35.11777],"type":"Point"}
}