{
  "type": "Feature",
  "properties": {
    "iso:country":"US",
    "sg:address":"1426 Regan Church Rd",
    "sg:city":"Lumberton",
    "sg:phone":"+1 910 739 6807",
    "sg:postcode":"28358",
    "sg:province":"NC",
    "sg:tags":[
        "farm",
        "tobacco"
    ],
    "wof:name":"Rozier Fields Farms",
    "wof:placetype":"venue"
},
  "geometry": {"coordinates":[-78.91901799999999,34.660356],"type":"Point"}
}