{
  "type": "Feature",
  "properties": {
    "iso:country":"US",
    "sg:address":"104 S White St",
    "sg:city":"Wake Forest",
    "sg:classifiers":[
        {
            "category":"Organizations",
            "subcategory":"Professional Association",
            "type":"Services"
        }
    ],
    "sg:phone":"+1 919 569 0152",
    "sg:postcode":"27587",
    "sg:province":"NC",
    "wof:name":"Partnership Of Drug Free Nc",
    "wof:placetype":"venue"
},
  "geometry": {"coordinates":[-78.509467,35.979182],"type":"Point"}
}