{
  "type": "Feature",
  "properties": {
    "iso:country":"US",
    "sg:address":"1916 Rayconda Pl",
    "sg:city":"Fayetteville",
    "sg:classifiers":[
        {
            "category":"Real Estate",
            "subcategory":"Real Estate Operator",
            "type":"Services"
        }
    ],
    "sg:phone":"+1 910 864 0671",
    "sg:postcode":"28304",
    "sg:province":"NC",
    "sg:tags":[
        "apartment"
    ],
    "wof:name":"Woodland Village Apartments",
    "wof:placetype":"venue"
},
  "geometry": {"coordinates":[-79.0188,35.032345],"type":"Point"}
}