{
  "type": "Feature",
  "properties": {
    "iso:country":"US",
    "sg:address":"147 Walker St",
    "sg:city":"Goldsboro",
    "sg:classifiers":[
        {
            "category":"Manufacturing",
            "subcategory":"Tools & Machinery",
            "type":"Manufacturing & Wholesale Goods"
        }
    ],
    "sg:phone":"+1 919 734 2076",
    "sg:postcode":"27530",
    "sg:province":"NC",
    "sg:tags":[
        "woodworking",
        "product",
        "wood",
        "mfg"
    ],
    "wof:name":"F L Shanle Inc",
    "wof:placetype":"venue"
},
  "geometry": {"coordinates":[-78.085885,35.436452],"type":"Point"}
}