{
  "type": "Feature",
  "properties": {
    "addr:full":"813 Grays Creek Ln Charlotte NC 28214",
    "addr:housenumber":"813",
    "addr:postcode":"28214",
    "addr:street":"Grays Creek Ln",
    "iso:country":"US",
    "sg:address":"813 Grays Creek Ln",
    "sg:city":"Charlotte",
    "sg:classifiers":[
        {
            "category":"Banks & Credit Unions",
            "subcategory":"Investment Brokerage",
            "type":"Services"
        }
    ],
    "sg:phone":"+1 704 392 8824",
    "sg:postcode":"28214",
    "sg:province":"NC",
    "sg:tags":[
        "advisory",
        "financial"
    ],
    "wof:name":"W C Reed & Assoc Inc",
    "wof:placetype":"venue"
},
  "geometry": {"coordinates":[-80.978472,35.304781],"type":"Point"}
}