{
  "type": "Feature",
  "properties": {
    "addr:full":"800 Hull Rd Kinston NC 28504",
    "addr:housenumber":"800",
    "addr:postcode":"28504",
    "addr:street":"Hull Rd",
    "iso:country":"US",
    "sg:address":"800 Hull Rd",
    "sg:city":"Kinston",
    "sg:classifiers":[
        {
            "category":"Manufacturing",
            "subcategory":"Lumber",
            "type":"Manufacturing & Wholesale Goods"
        }
    ],
    "sg:phone":"+1 252 522 1343",
    "sg:postcode":"28504",
    "sg:province":"NC",
    "sg:tags":[
        "planing",
        "mills",
        "sawmill"
    ],
    "wof:name":"Coastal Lumber Co",
    "wof:placetype":"venue"
},
  "geometry": {"coordinates":[-77.61909,35.274754],"type":"Point"}
}