{
  "type": "Feature",
  "properties": {
    "addr:full":"501 Willie Hatcher Rd Chinquapin NC 28521",
    "addr:housenumber":"501",
    "addr:postcode":"28521",
    "addr:street":"Willie Hatcher Rd",
    "iso:country":"US",
    "sg:address":"501 Willie Hatcher Rd",
    "sg:city":"Chinquapin",
    "sg:classifiers":[
        {
            "category":"Insurance",
            "subcategory":"Life Insurance",
            "type":"Services"
        }
    ],
    "sg:phone":"+1 910 285 7893",
    "sg:postcode":"28521",
    "sg:province":"NC",
    "sg:tags":[
        "carrier"
    ],
    "wof:name":"Woodman of World",
    "wof:placetype":"venue"
},
  "geometry": {"coordinates":[-77.766116,34.823506],"type":"Point"}
}