{
  "type": "Feature",
  "properties": {
    "iso:country":"US",
    "sg:address":"2004 Osbourne Ct",
    "sg:city":"Raleigh",
    "sg:classifiers":[
        {
            "category":"Manufacturing",
            "subcategory":"Printing",
            "type":"Manufacturing & Wholesale Goods"
        }
    ],
    "sg:phone":"+1 919 212 1912",
    "sg:postcode":"27604",
    "sg:province":"NC",
    "sg:tags":[
        "publishing"
    ],
    "wof:name":"Lightwriting Media",
    "wof:placetype":"venue"
},
  "geometry": {"coordinates":[-78.561984,35.807831],"type":"Point"}
}