{
  "type": "Feature",
  "properties": {
    "iso:country":"US",
    "sg:address":"701 W Main St",
    "sg:city":"Haw River",
    "sg:classifiers":[
        {
            "category":"Education",
            "subcategory":"School",
            "type":"Public Place"
        }
    ],
    "sg:phone":"+1 336 578 0177",
    "sg:postcode":"27258",
    "sg:province":"NC",
    "sg:tags":[
        "elementary"
    ],
    "wof:name":"Haw River Elementary School",
    "wof:placetype":"venue"
},
  "geometry": {"coordinates":[-79.376437,36.088524],"type":"Point"}
}