{
  "type": "Feature",
  "properties": {
    "iso:country":"US",
    "sg:address":"333 Fayetteville Street Mall",
    "sg:city":"Raleigh",
    "sg:classifiers":[
        {
            "category":"Real Estate",
            "subcategory":"Architect",
            "type":"Services"
        }
    ],
    "sg:phone":"+1 919 836 9751",
    "sg:postcode":"27601",
    "sg:province":"NC",
    "sg:website":"www.pbclarchitecture.com",
    "wof:name":"Pearce Brinkley Cease & Lee",
    "wof:placetype":"venue"
},
  "geometry": {"coordinates":[-78.639245,35.77603],"type":"Point"}
}