{
  "type": "Feature",
  "properties": {
    "iso:country":"US",
    "sg:address":"1526 Patton Ave",
    "sg:city":"Asheville",
    "sg:classifiers":[
        {
            "category":"Wholesale",
            "subcategory":"Medical Equipment & Supplies",
            "type":"Manufacturing & Wholesale Goods"
        }
    ],
    "sg:phone":"+1 828 258 1840",
    "sg:postcode":"28806",
    "sg:province":"NC",
    "sg:tags":[
        "physician",
        "surgeon"
    ],
    "wof:name":"G & J Medical Supplies",
    "wof:placetype":"venue"
},
  "geometry": {"coordinates":[-82.61215,35.576039],"type":"Point"}
}