{
  "type": "Feature",
  "properties": {
    "addr:full":"10 Commerce St Waynesville NC 28786",
    "addr:housenumber":"10",
    "addr:postcode":"28786",
    "addr:street":"Commerce St",
    "iso:country":"US",
    "sg:address":"10 Commerce St",
    "sg:city":"Waynesville",
    "sg:classifiers":[
        {
            "category":"Home & Garden",
            "subcategory":"Hardware",
            "type":"Retail Goods"
        }
    ],
    "sg:phone":"+1 828 456 7561",
    "sg:postcode":"28786",
    "sg:province":"NC",
    "wof:name":"Waynesville Supply Co",
    "wof:placetype":"venue"
},
  "geometry": {"coordinates":[-82.99038299999999,35.494009],"type":"Point"}
}