{
  "type": "Feature",
  "properties": {
    "iso:country":"US",
    "sg:address":"400 E Pinewood St",
    "sg:city":"Roseboro",
    "sg:classifiers":[
        {
            "category":"Organizations",
            "subcategory":"Religious Organization",
            "type":"Services"
        }
    ],
    "sg:phone":"+1   ",
    "sg:postcode":"28382",
    "sg:province":"NC",
    "wof:name":"Hwy 24 East Church of God",
    "wof:placetype":"venue"
},
  "geometry": {"coordinates":[-78.50400399999999,34.948789],"type":"Point"}
}