{
  "type": "Feature",
  "properties": {
    "addr:full":"372 Webb Rd Madison NC 27025",
    "addr:housenumber":"372",
    "addr:postcode":"27025",
    "addr:street":"Webb Rd",
    "iso:country":"US",
    "sg:address":"372 Webb Rd",
    "sg:city":"Madison",
    "sg:classifiers":[
        {
            "category":"Building & Trades",
            "subcategory":"Construction",
            "type":"Services"
        }
    ],
    "sg:phone":"+1 336 427 2419",
    "sg:postcode":"27025",
    "sg:province":"NC",
    "sg:tags":[
        "hanging",
        "contractor"
    ],
    "wof:name":"Simpsons Painting",
    "wof:placetype":"venue"
},
  "geometry": {"coordinates":[-79.855456,36.370113],"type":"Point"}
}