{
  "type": "Feature",
  "properties": {
    "addr:full":"3541 Tryclan Dr Charlotte NC 28217",
    "addr:housenumber":"3541",
    "addr:postcode":"28217",
    "addr:street":"Tryclan Dr",
    "iso:country":"US",
    "sg:address":"3541 Tryclan Dr",
    "sg:city":"Charlotte",
    "sg:classifiers":[
        {
            "category":"Shopping",
            "subcategory":"Music",
            "type":"Retail Goods"
        }
    ],
    "sg:phone":"+1 704 523 7107",
    "sg:postcode":"28217",
    "sg:province":"NC",
    "wof:name":"Video House",
    "wof:placetype":"venue"
},
  "geometry": {"coordinates":[-80.877492,35.194413],"type":"Point"}
}