{
  "type": "Feature",
  "properties": {
    "addr:full":"105 Industrial Dr King NC 27021",
    "addr:housenumber":"105",
    "addr:postcode":"27021",
    "addr:street":"Industrial Dr",
    "iso:country":"US",
    "sg:address":"105 Industrial Dr",
    "sg:city":"King",
    "sg:classifiers":[
        {
            "category":"Manufacturing",
            "subcategory":"Paper Products",
            "type":"Manufacturing & Wholesale Goods"
        }
    ],
    "sg:phone":"+1 336 983 4545",
    "sg:postcode":"27021",
    "sg:province":"NC",
    "sg:tags":[
        "sanitary",
        "mfg"
    ],
    "sg:website":"www.merfin.com",
    "wof:name":"Merfin Systems Inc",
    "wof:placetype":"venue"
},
  "geometry": {"coordinates":[-80.37095600000001,36.265588],"type":"Point"}
}