{
  "type": "Feature",
  "properties": {
    "addr:full":"3445 Robinhood Rd Winston Salem NC 27106",
    "addr:housenumber":"3445",
    "addr:postcode":"27106",
    "addr:street":"Robinhood Rd",
    "iso:country":"US",
    "sg:address":"3445 Robinhood Rd",
    "sg:city":"Winston Salem",
    "sg:classifiers":[
        {
            "category":"Insurance",
            "subcategory":"Insurance Agent",
            "type":"Services"
        }
    ],
    "sg:phone":"+1 336 659 9010",
    "sg:postcode":"27106",
    "sg:province":"NC",
    "wof:name":"Jim Annas Agency",
    "wof:placetype":"venue"
},
  "geometry": {"coordinates":[-80.316901,36.118064],"type":"Point"}
}