{
  "type": "Feature",
  "properties": {
    "iso:country":"US",
    "sg:address":"1104 Downing St SW",
    "sg:city":"Wilson",
    "sg:classifiers":[
        {
            "category":"Personal",
            "subcategory":"Beauty Salon",
            "type":"Services"
        }
    ],
    "sg:phone":"+1 252 237 6265",
    "sg:postcode":"27893",
    "sg:province":"NC",
    "sg:tags":[
        "shop"
    ],
    "wof:name":"Special Touch Beauty Salon Two",
    "wof:placetype":"venue"
},
  "geometry": {"coordinates":[-77.924081,35.715615],"type":"Point"}
}