{
  "type": "Feature",
  "properties": {
    "iso:country":"US",
    "sg:address":"1318 Patton Ave",
    "sg:city":"Asheville",
    "sg:classifiers":[
        {
            "category":"Professional",
            "type":"Services"
        }
    ],
    "sg:phone":"+1 828 240 7325",
    "sg:postcode":"28806",
    "sg:province":"NC",
    "sg:tags":[
        "establishment"
    ],
    "wof:name":"WPEK",
    "wof:placetype":"venue"
},
  "geometry": {"coordinates":[-82.602861,35.584808],"type":"Point"}
}