{
  "type": "Feature",
  "properties": {
    "iso:country":"US",
    "sg:address":"25 Miller St",
    "sg:city":"Waynesville",
    "sg:classifiers":[
        {
            "category":"Shopping",
            "subcategory":"Clothing, Apparel, & Fashions",
            "type":"Retail Goods"
        }
    ],
    "sg:phone":"+1 828 456 4297",
    "sg:postcode":"28786",
    "sg:province":"NC",
    "sg:tags":[
        "wear"
    ],
    "wof:name":"Just Ducky Originals",
    "wof:placetype":"venue"
},
  "geometry": {"coordinates":[-82.98808699999999,35.490888],"type":"Point"}
}