{
  "type": "Feature",
  "properties": {
    "addr:full":"491 Woodfield Scout Trl Asheboro NC 27205",
    "addr:housenumber":"491",
    "addr:postcode":"27205",
    "addr:street":"Woodfield Scout Trl",
    "iso:country":"US",
    "sg:address":"491 Woodfield Scout Trl",
    "sg:city":"Asheboro",
    "sg:classifiers":[
        {
            "category":"Organizations",
            "subcategory":"Professional Association",
            "type":"Services"
        }
    ],
    "sg:phone":"+1   ",
    "sg:postcode":"27205",
    "sg:province":"NC",
    "sg:tags":[
        "business"
    ],
    "wof:name":"All North State Council",
    "wof:placetype":"venue"
},
  "geometry": {"coordinates":[-79.975621,35.726678],"type":"Point"}
}