{
  "type": "Feature",
  "properties": {
    "addr:full":"23 Shepherd St Raleigh NC 27607",
    "addr:housenumber":"23",
    "addr:postcode":"27607",
    "addr:street":"Shepherd St",
    "iso:country":"US",
    "sg:address":"23 Shepherd St",
    "sg:city":"Raleigh",
    "sg:classifiers":[
        {
            "category":"Professional",
            "subcategory":"Management & Consulting",
            "type":"Services"
        }
    ],
    "sg:phone":"+1 919 834 7182",
    "sg:postcode":"27607",
    "sg:province":"NC",
    "sg:tags":[
        "consultant",
        "business"
    ],
    "wof:name":"Thomas E Sappington Phd Inc",
    "wof:placetype":"venue"
},
  "geometry": {"coordinates":[-78.678375,35.792317],"type":"Point"}
}