{
  "type": "Feature",
  "properties": {
    "addr:full":"635 Rowan Mill Rd Salisbury NC 28147",
    "addr:housenumber":"635",
    "addr:postcode":"28147",
    "addr:street":"Rowan Mill Rd",
    "iso:country":"US",
    "sg:address":"635 Rowan Mill Rd",
    "sg:city":"Salisbury",
    "sg:classifiers":[
        {
            "category":"Real Estate",
            "subcategory":"Surveying",
            "type":"Services"
        }
    ],
    "sg:phone":"+1 704 633 0744",
    "sg:postcode":"28147",
    "sg:province":"NC",
    "sg:tags":[
        "surveyor"
    ],
    "wof:name":"Gobble Land Surveying",
    "wof:placetype":"venue"
},
  "geometry": {"coordinates":[-80.509061,35.651561],"type":"Point"}
}