{
  "type": "Feature",
  "properties": {
    "addr:full":"6468 Basin Dr Fayetteville NC 28304",
    "addr:housenumber":"6468",
    "addr:postcode":"28304",
    "addr:street":"Basin Dr",
    "iso:country":"US",
    "sg:address":"6468 Basin Dr",
    "sg:city":"Fayetteville",
    "sg:classifiers":[
        {
            "category":"Shopping",
            "subcategory":"Clothing, Apparel, & Fashions",
            "type":"Retail Goods"
        }
    ],
    "sg:phone":"+1 910 868 6682",
    "sg:postcode":"28304",
    "sg:province":"NC",
    "sg:tags":[
        "shop",
        "beauty"
    ],
    "wof:name":"Drop Zone Fox Hole",
    "wof:placetype":"venue"
},
  "geometry": {"coordinates":[-79.001009,35.011235],"type":"Point"}
}