{
  "type": "Feature",
  "properties": {
    "iso:country":"US",
    "sg:address":"59 Countryview Dr",
    "sg:city":"Sparta",
    "sg:classifiers":[
        {
            "category":"Wholesale",
            "subcategory":"Non-durable Goods",
            "type":"Manufacturing & Wholesale Goods"
        }
    ],
    "sg:phone":"+1 336 372 7337",
    "sg:postcode":"28675",
    "sg:province":"NC",
    "wof:name":"First Aid Express Inc",
    "wof:placetype":"venue"
},
  "geometry": {"coordinates":[-81.04729500000001,36.424981],"type":"Point"}
}