{
  "type": "Feature",
  "properties": {
    "addr:full":"103 Queen Anne Ave Nashville NC 27804",
    "addr:housenumber":"103",
    "addr:postcode":"27804",
    "addr:street":"Queen Anne Ave",
    "iso:country":"US",
    "sg:address":"103 Queen Anne Ave",
    "sg:city":"Nashville",
    "sg:classifiers":[
        {
            "category":"Freight",
            "type":"Transportation"
        }
    ],
    "sg:phone":"+1 252 462 0686",
    "sg:postcode":"27804",
    "sg:province":"NC",
    "sg:tags":[
        "operator",
        "trucking"
    ],
    "wof:name":"Robbins Brothers Inc",
    "wof:placetype":"venue"
},
  "geometry": {"coordinates":[-77.93110799999999,35.973772],"type":"Point"}
}