{
  "type": "Feature",
  "properties": {
    "iso:country":"US",
    "sg:address":"4240 Williamsbrook Ln",
    "sg:city":"Greenville",
    "sg:classifiers":[
        {
            "category":"Personal",
            "type":"Services"
        }
    ],
    "sg:phone":"+1   ",
    "sg:postcode":"27858",
    "sg:province":"NC",
    "wof:name":"Figure 8 Group Inc",
    "wof:placetype":"venue"
},
  "geometry": {"coordinates":[-77.32323100000001,35.577457],"type":"Point"}
}