{
  "type": "Feature",
  "properties": {
    "iso:country":"US",
    "sg:address":"6407 Idlewild Rd",
    "sg:city":"Charlotte",
    "sg:classifiers":[
        {
            "category":"Utilities",
            "subcategory":"Fuel Oil & Lpg",
            "type":"Services"
        }
    ],
    "sg:phone":"+1 704 943 2260",
    "sg:postcode":"28212",
    "sg:province":"NC",
    "sg:tags":[
        "oils-fuel"
    ],
    "wof:name":"Zmax",
    "wof:placetype":"venue"
},
  "geometry": {"coordinates":[-80.753848,35.183483],"type":"Point"}
}