{
  "type": "Feature",
  "properties": {
    "iso:country":"US",
    "sg:address":"6317 Market St",
    "sg:city":"Wilmington",
    "sg:classifiers":[
        {
            "category":"Restaurant",
            "type":"Food & Drink"
        }
    ],
    "sg:phone":"+1 910 799 0504",
    "sg:postcode":"28405",
    "sg:province":"NC",
    "wof:name":"Firehouse Grille",
    "wof:placetype":"venue"
},
  "geometry": {"coordinates":[-77.84737800000001,34.254152],"type":"Point"}
}