{
  "type": "Feature",
  "properties": {
    "addr:full":"602 Cinnamon Way Flat Rock NC 28731",
    "addr:housenumber":"602",
    "addr:postcode":"28731",
    "addr:street":"Cinnamon Way",
    "iso:country":"US",
    "sg:address":"602 Cinnamon Way",
    "sg:city":"Flat Rock",
    "sg:classifiers":[
        {
            "category":"Home & Garden",
            "subcategory":"Building Materials",
            "type":"Retail Goods"
        }
    ],
    "sg:phone":"+1 828 698 2556",
    "sg:postcode":"28731",
    "sg:province":"NC",
    "wof:name":"Congree Home Bldrs",
    "wof:placetype":"venue"
},
  "geometry": {"coordinates":[-82.415953,35.262488],"type":"Point"}
}