{
  "type": "Feature",
  "properties": {
    "iso:country":"US",
    "sg:address":"1273 N Brightleaf Blvd",
    "sg:city":"Smithfield",
    "sg:classifiers":[
        {
            "category":"Restaurant",
            "type":"Food & Drink"
        }
    ],
    "sg:phone":"+1 919 989 8088",
    "sg:postcode":"27577",
    "sg:province":"NC",
    "sg:tags":[
        "style",
        "pan",
        "family",
        "chinese",
        "asian"
    ],
    "wof:name":"Hibachi Grill",
    "wof:placetype":"venue"
},
  "geometry": {"coordinates":[-78.31225499999999,35.519596],"type":"Point"}
}