{
  "type": "Feature",
  "properties": {
    "iso:country":"US",
    "sg:address":"4206 Brambletye Dr",
    "sg:city":"Greensboro",
    "sg:classifiers":[
        {
            "category":"Professional",
            "subcategory":"Management & Consulting",
            "type":"Services"
        }
    ],
    "sg:phone":"+1   ",
    "sg:postcode":"27407",
    "sg:province":"NC",
    "wof:name":"Jdk Properties LLC",
    "wof:placetype":"venue"
},
  "geometry": {"coordinates":[-79.895899,35.998917],"type":"Point"}
}