{
  "type": "Feature",
  "properties": {
    "addr:full":"1040 Red Hill Rd Cameron NC 28326",
    "addr:housenumber":"1040",
    "addr:postcode":"28326",
    "addr:street":"Red Hill Rd",
    "iso:country":"US",
    "sg:address":"1040 Red Hill Rd",
    "sg:city":"Cameron",
    "sg:classifiers":[
        {
            "category":"Restaurant",
            "type":"Food & Drink"
        }
    ],
    "sg:phone":"+1 910 245 7618",
    "sg:postcode":"28326",
    "sg:province":"NC",
    "sg:tags":[
        "eating",
        "supply"
    ],
    "wof:name":"McDonalds Nursery",
    "wof:placetype":"venue"
},
  "geometry": {"coordinates":[-79.30730200000001,35.336921],"type":"Point"}
}