{
  "type": "Feature",
  "properties": {
    "addr:full":"3509 Clinton Rd Fayetteville NC 28312",
    "addr:housenumber":"3509",
    "addr:postcode":"28312",
    "addr:street":"Clinton Rd",
    "iso:country":"US",
    "sg:address":"3509 Clinton Rd",
    "sg:city":"Fayetteville",
    "sg:classifiers":[
        {
            "category":"Government",
            "subcategory":"Fire Station",
            "type":"Public Place"
        }
    ],
    "sg:phone":"+1 910 483 5042",
    "sg:postcode":"28312",
    "sg:province":"NC",
    "sg:tags":[
        "protection"
    ],
    "wof:name":"Vander Fire District",
    "wof:placetype":"venue"
},
  "geometry": {"coordinates":[-78.79466499999999,35.032398],"type":"Point"}
}