{
  "type": "Feature",
  "properties": {
    "iso:country":"US",
    "sg:address":"7604 Raeford Rd",
    "sg:city":"Fayetteville",
    "sg:classifiers":[
        {
            "category":"Restaurant",
            "type":"Food & Drink"
        }
    ],
    "sg:phone":"+1 910 860 7669",
    "sg:postcode":"28304",
    "sg:province":"NC",
    "sg:tags":[
        "parlor",
        "ice",
        "cream"
    ],
    "wof:name":"Rainbow Snowball",
    "wof:placetype":"venue"
},
  "geometry": {"coordinates":[-79.05134,35.030612],"type":"Point"}
}