{
  "type": "Feature",
  "properties": {
    "addr:full":"86 Valley Hideaway Dr Hayesville NC 28902",
    "addr:housenumber":"86",
    "addr:postcode":"28902",
    "addr:street":"Valley Hideaway Dr",
    "iso:country":"US",
    "sg:address":"86 Valley Hideaway Dr",
    "sg:city":"Hayesville",
    "sg:classifiers":[
        {
            "category":"Health Services",
            "subcategory":"Nursing And Care Facility",
            "type":"Services"
        }
    ],
    "sg:phone":"+1 828 389 8479",
    "sg:postcode":"28902",
    "sg:province":"NC",
    "sg:tags":[
        "home",
        "convalescent"
    ],
    "wof:name":"Centennial Healthcare",
    "wof:placetype":"venue"
},
  "geometry": {"coordinates":[-83.804282,35.041846],"type":"Point"}
}