{
  "type": "Feature",
  "properties": {
    "addr:full":"402 Patton Ave Monroe NC 28110",
    "addr:housenumber":"402",
    "addr:postcode":"28110",
    "addr:street":"Patton Ave",
    "iso:country":"US",
    "sg:address":"402 Patton Ave",
    "sg:city":"Monroe",
    "sg:classifiers":[
        {
            "category":"Personal",
            "subcategory":"Beauty Salon",
            "type":"Services"
        }
    ],
    "sg:phone":"+1 704 238 9897",
    "sg:postcode":"28110",
    "sg:province":"NC",
    "wof:name":"Urban Images Barber & Beauty",
    "wof:placetype":"venue"
},
  "geometry": {"coordinates":[-80.554001,34.998826],"type":"Point"}
}