{
  "type": "Feature",
  "properties": {
    "addr:full":"416 Carpenter Ave Mooresville NC 28115",
    "addr:housenumber":"416",
    "addr:postcode":"28115",
    "addr:street":"Carpenter Ave",
    "iso:country":"US",
    "sg:address":"416 Carpenter Ave",
    "sg:city":"Mooresville",
    "sg:classifiers":[
        {
            "category":"Shopping",
            "subcategory":"Hobbies, Toys, & Games",
            "type":"Retail Goods"
        }
    ],
    "sg:phone":"+1 704 664 1144",
    "sg:postcode":"28115",
    "sg:province":"NC",
    "wof:name":"Ceramics House",
    "wof:placetype":"venue"
},
  "geometry": {"coordinates":[-80.806864,35.581324],"type":"Point"}
}