{
  "type": "Feature",
  "properties": {
    "addr:full":"10418 N Main St Archdale NC 27263",
    "addr:housenumber":"10418",
    "addr:postcode":"27263",
    "addr:street":"N Main St",
    "iso:country":"US",
    "sg:address":"10418 N Main St",
    "sg:city":"Archdale",
    "sg:classifiers":[
        {
            "category":"Retail",
            "subcategory":"Laundry & Dry Cleaning",
            "type":"Services"
        }
    ],
    "sg:phone":"+1 336 434 3155",
    "sg:postcode":"27263",
    "sg:province":"NC",
    "sg:tags":[
        "cleaners"
    ],
    "wof:name":"Crystal Cleaners",
    "wof:placetype":"venue"
},
  "geometry": {"coordinates":[-79.961994,35.907711],"type":"Point"}
}