{
  "type": "Feature",
  "properties": {
    "iso:country":"US",
    "sg:address":"123 Doolie Rd",
    "sg:city":"Mooresville",
    "sg:classifiers":[
        {
            "category":"Autos & Motor Vehicles",
            "subcategory":"Auto Supplies",
            "type":"Retail Goods"
        }
    ],
    "sg:phone":"+1 704 662 8299",
    "sg:postcode":"28117",
    "sg:province":"NC",
    "sg:tags":[
        "equipment",
        "racing",
        "car",
        "automobile"
    ],
    "wof:name":"Carolina Racing Supply Inc",
    "wof:placetype":"venue"
},
  "geometry": {"coordinates":[-80.897654,35.600428],"type":"Point"}
}