{
  "type": "Feature",
  "properties": {
    "addr:full":"18824 Balmore Pines Ln Cornelius NC 28031",
    "addr:postcode":"18824;28031",
    "addr:street":"Balmore Pines Ln",
    "iso:country":"US",
    "sg:address":"18824 Balmore Pines Ln",
    "sg:city":"Cornelius",
    "sg:classifiers":[
        {
            "category":"Professional",
            "subcategory":"Business Services",
            "type":"Services"
        }
    ],
    "sg:phone":"+1   ",
    "sg:postcode":"28031",
    "sg:province":"NC",
    "wof:name":"N&T Design Services Inc",
    "wof:placetype":"venue"
},
  "geometry": {"coordinates":[-80.90936499999999,35.466576],"type":"Point"}
}