{
  "type": "Feature",
  "properties": {
    "addr:full":"537 Ownley Rd Elizabeth City NC 27909",
    "addr:housenumber":"537",
    "addr:postcode":"27909",
    "addr:street":"Ownley Rd",
    "iso:country":"US",
    "sg:address":"537 Ownley Rd",
    "sg:city":"Elizabeth City",
    "sg:classifiers":[
        {
            "category":"Farming",
            "subcategory":"Farm",
            "type":"Manufacturing & Wholesale Goods"
        }
    ],
    "sg:phone":"+1 252 264 2376",
    "sg:postcode":"27909",
    "sg:province":"NC",
    "sg:tags":[
        "crop",
        "general"
    ],
    "wof:name":"K & L Farms Inc",
    "wof:placetype":"venue"
},
  "geometry": {"coordinates":[-76.365915,36.277976],"type":"Point"}
}