{
  "type": "Feature",
  "properties": {
    "iso:country":"US",
    "sg:address":"134 Walnut Dr",
    "sg:city":"Spring Lake",
    "sg:classifiers":[
        {
            "category":"Building & Trades",
            "subcategory":"Cleaning & Sanitation",
            "type":"Services"
        }
    ],
    "sg:phone":"+1   ",
    "sg:postcode":"28390",
    "sg:province":"NC",
    "sg:tags":[
        "maintenance"
    ],
    "wof:name":"Professional Cleaning Service",
    "wof:placetype":"venue"
},
  "geometry": {"coordinates":[-78.984882,35.28766],"type":"Point"}
}