{
  "type": "Feature",
  "properties": {
    "iso:country":"US",
    "sg:address":"1000 Essick Rd",
    "sg:city":"Lexington",
    "sg:classifiers":[
        {
            "category":"Real Estate",
            "subcategory":"Real Estate Agent",
            "type":"Services"
        }
    ],
    "sg:phone":"+1 336 787 3686",
    "sg:postcode":"27295",
    "sg:province":"NC",
    "sg:tags":[
        "agency",
        "rental"
    ],
    "wof:name":"RJR Rental Property",
    "wof:placetype":"venue"
},
  "geometry": {"coordinates":[-80.35966999999999,35.89384],"type":"Point"}
}