{
  "type": "Feature",
  "properties": {
    "iso:country":"US",
    "sg:address":"709 Poplar Branch Rd",
    "sg:city":"Grandy",
    "sg:classifiers":[
        {
            "category":"Organizations",
            "subcategory":"Religious Organization",
            "type":"Services"
        }
    ],
    "sg:phone":"+1 252 453 8242",
    "sg:postcode":"27939",
    "sg:province":"NC",
    "sg:tags":[
        "church"
    ],
    "wof:name":"Poplar Branch Baptist Church",
    "wof:placetype":"venue"
},
  "geometry": {"coordinates":[-75.882987,36.256273],"type":"Point"}
}