{
  "type": "Feature",
  "properties": {
    "iso:country":"US",
    "sg:address":"10821 Cahill Rd",
    "sg:city":"Raleigh",
    "sg:classifiers":[
        {
            "category":"Professional",
            "subcategory":"Business Services",
            "type":"Services"
        }
    ],
    "sg:phone":"+1   ",
    "sg:postcode":"27614",
    "sg:province":"NC",
    "wof:name":"A D Civilc Inc",
    "wof:placetype":"venue"
},
  "geometry": {"coordinates":[-78.630071,35.923592],"type":"Point"}
}