{
  "type": "Feature",
  "properties": {
    "addr:full":"7521 Leesville Rd Raleigh NC 27613",
    "addr:housenumber":"7521",
    "addr:postcode":"27613",
    "addr:street":"Leesville Rd",
    "iso:country":"US",
    "sg:address":"7521 Leesville Rd",
    "sg:city":"Raleigh",
    "sg:classifiers":[
        {
            "category":"Shopping",
            "type":"Retail Goods"
        }
    ],
    "sg:phone":"+1 919 781 2614",
    "sg:postcode":"27613",
    "sg:province":"NC",
    "sg:tags":[
        "album",
        "photo",
        "frame"
    ],
    "wof:name":"Moments In Time",
    "wof:placetype":"venue"
},
  "geometry": {"coordinates":[-78.706667,35.879058],"type":"Point"}
}