{
  "type": "Feature",
  "properties": {
    "addr:full":"830 Main St North Wilkesboro NC 28659",
    "addr:housenumber":"830",
    "addr:postcode":"28659",
    "addr:street":"Main St",
    "iso:country":"US",
    "sg:address":"830 Main St",
    "sg:city":"North Wilkesboro",
    "sg:classifiers":[
        {
            "category":"Real Estate",
            "subcategory":"Real Estate Operator",
            "type":"Services"
        }
    ],
    "sg:phone":"+1 336 838 8552",
    "sg:postcode":"28659",
    "sg:province":"NC",
    "sg:tags":[
        "apartment"
    ],
    "wof:name":"Wilkes Towers LTD",
    "wof:placetype":"venue"
},
  "geometry": {"coordinates":[-81.145802,36.159735],"type":"Point"}
}