{
  "type": "Feature",
  "properties": {
    "addr:full":"3055 Old Hollow Rd Walkertown NC 27051",
    "addr:housenumber":"3055",
    "addr:postcode":"27051",
    "addr:street":"Old Hollow Rd",
    "iso:country":"US",
    "sg:address":"3055 Old Hollow Rd",
    "sg:city":"Walkertown",
    "sg:classifiers":[
        {
            "category":"Personal",
            "subcategory":"Beauty Salon",
            "type":"Services"
        }
    ],
    "sg:phone":"+1 336 595 3019",
    "sg:postcode":"27051",
    "sg:province":"NC",
    "wof:name":"Razor's Edge",
    "wof:placetype":"venue"
},
  "geometry": {"coordinates":[-80.149485,36.168624],"type":"Point"}
}