{
  "type": "Feature",
  "properties": {
    "iso:country":"US",
    "sg:address":"389 Old Miller Rd",
    "sg:city":"Blowing Rock",
    "sg:classifiers":[
        {
            "category":"Building & Trades",
            "subcategory":"Construction",
            "type":"Services"
        }
    ],
    "sg:phone":"+1 828 295 7044",
    "sg:postcode":"28625",
    "sg:province":"NC",
    "sg:tags":[
        "contractor"
    ],
    "wof:name":"Canton Drywall Construction",
    "wof:placetype":"venue"
},
  "geometry": {"coordinates":[-81.024798,35.780772],"type":"Point"}
}