{
  "type": "Feature",
  "properties": {
    "addr:full":"1800 N Main St Mount Holly NC 28120",
    "addr:housenumber":"1800",
    "addr:postcode":"28120",
    "addr:street":"N Main St",
    "iso:country":"US",
    "sg:address":"1800 N Main St",
    "sg:city":"Mount Holly",
    "sg:classifiers":[
        {
            "category":"Professional",
            "subcategory":"Computer Services",
            "type":"Services"
        }
    ],
    "sg:phone":"+1   ",
    "sg:postcode":"28120",
    "sg:province":"NC",
    "sg:tags":[
        "related"
    ],
    "wof:name":"Allen Levern",
    "wof:placetype":"venue"
},
  "geometry": {"coordinates":[-81.00165200000001,35.327121],"type":"Point"}
}