{
  "type": "Feature",
  "properties": {
    "addr:full":"337 Godfrey Creek Rd Hampstead NC 28443",
    "addr:housenumber":"337",
    "addr:postcode":"28443",
    "addr:street":"Godfrey Creek Rd",
    "iso:country":"US",
    "sg:address":"337 Godfrey Creek Rd",
    "sg:city":"Hampstead",
    "sg:classifiers":[
        {
            "category":"Recreation",
            "type":"Entertainment"
        }
    ],
    "sg:phone":"+1   ",
    "sg:postcode":"28443",
    "sg:province":"NC",
    "wof:name":"Bang Tail Stables",
    "wof:placetype":"venue"
},
  "geometry": {"coordinates":[-77.721132,34.393641],"type":"Point"}
}