{
  "type": "Feature",
  "properties": {
    "iso:country":"US",
    "sg:address":"108 Briarwood Dr",
    "sg:city":"Selma",
    "sg:classifiers":[
        {
            "category":"Professional",
            "subcategory":"Management & Consulting",
            "type":"Services"
        }
    ],
    "sg:phone":"+1   ",
    "sg:postcode":"27576",
    "sg:province":"NC",
    "sg:tags":[
        "international",
        "subcontractor",
        "consultant"
    ],
    "wof:name":"Latin Amrcn Affairs Consulting",
    "wof:placetype":"venue"
},
  "geometry": {"coordinates":[-78.309352,35.604428],"type":"Point"}
}