{
  "type": "Feature",
  "properties": {
    "iso:country":"US",
    "sg:address":"763 Piney Grove Church Rd",
    "sg:city":"Kenly",
    "sg:classifiers":[
        {
            "category":"Social Services",
            "subcategory":"Child Care",
            "type":"Services"
        }
    ],
    "sg:phone":"+1 919 284 3203",
    "sg:postcode":"27542",
    "sg:province":"NC",
    "wof:name":"Sweet & Tender Loving Daycare",
    "wof:placetype":"venue"
},
  "geometry": {"coordinates":[-78.123293,35.5794],"type":"Point"}
}