{
  "type": "Feature",
  "properties": {
    "iso:country":"US",
    "sg:address":"1362 Ellis Ferry Rd",
    "sg:city":"Shelby",
    "sg:classifiers":[
        {
            "category":"Mining & Drilling",
            "type":"Manufacturing & Wholesale Goods"
        }
    ],
    "sg:phone":"+1 704 487 0779",
    "sg:postcode":"28152",
    "sg:province":"NC",
    "sg:tags":[
        "construction"
    ],
    "wof:name":"Glenn Forest Products",
    "wof:placetype":"venue"
},
  "geometry": {"coordinates":[-81.623428,35.185952],"type":"Point"}
}