{
  "type": "Feature",
  "properties": {
    "addr:full":"333 Killian Ct Matthews NC 28104",
    "addr:housenumber":"333",
    "addr:postcode":"28104",
    "addr:street":"Killian Ct",
    "iso:country":"US",
    "sg:address":"333 Killian Ct",
    "sg:city":"Matthews",
    "sg:classifiers":[
        {
            "category":"Health Services",
            "subcategory":"Doctor",
            "type":"Services"
        }
    ],
    "sg:phone":"+1 704 882 6737",
    "sg:postcode":"28104",
    "sg:province":"NC",
    "sg:tags":[
        "physician",
        "surgeon"
    ],
    "wof:name":"Peggy Wells Naturepath",
    "wof:placetype":"venue"
},
  "geometry": {"coordinates":[-80.64523,35.123592],"type":"Point"}
}