{
  "type": "Feature",
  "properties": {
    "addr:full":"135 Brady St Exd Ramseur NC 27316",
    "addr:housenumber":"135",
    "addr:postcode":"27316",
    "addr:street":"Brady St Exd",
    "iso:country":"US",
    "sg:address":"135 Brady St Exd",
    "sg:city":"Ramseur",
    "sg:classifiers":[
        {
            "category":"Food & Beverages",
            "subcategory":"Groceries & Convenience Stores",
            "type":"Retail Goods"
        }
    ],
    "sg:phone":"+1 336 824 5145",
    "sg:postcode":"27316",
    "sg:province":"NC",
    "sg:tags":[
        "grocer"
    ],
    "sg:website":"www.lowesfoods.com",
    "wof:name":"Lowes Foods",
    "wof:placetype":"venue"
},
  "geometry": {"coordinates":[-79.65595500000001,35.739197],"type":"Point"}
}