{
  "type": "Feature",
  "properties": {
    "addr:full":"129 E Murphy St Madison NC 27025",
    "addr:housenumber":"129",
    "addr:postcode":"27025",
    "addr:street":"E Murphy St",
    "iso:country":"US",
    "sg:address":"129 E Murphy St",
    "sg:city":"Madison",
    "sg:classifiers":[
        {
            "category":"Professional",
            "subcategory":"Lawyer & Legal Services",
            "type":"Services"
        }
    ],
    "sg:phone":"+1   ",
    "sg:postcode":"27025",
    "sg:province":"NC",
    "wof:name":"Leigh Rodenbough Attorney",
    "wof:placetype":"venue"
},
  "geometry": {"coordinates":[-79.959412,36.387602],"type":"Point"}
}