{
  "type": "Feature",
  "properties": {
    "iso:country":"US",
    "sg:address":"3917 Fayetteville Rd",
    "sg:city":"Durham",
    "sg:classifiers":[
        {
            "category":"Banks & Credit Unions",
            "subcategory":"Bank",
            "type":"Services"
        }
    ],
    "sg:phone":"+1 919 682 7986",
    "sg:postcode":"27713",
    "sg:province":"NC",
    "sg:tags":[
        "savings",
        "loan",
        "association"
    ],
    "wof:name":"Mutual Community Savings Bank",
    "wof:placetype":"venue"
},
  "geometry": {"coordinates":[-78.90447,35.951484],"type":"Point"}
}