{
  "type": "Feature",
  "properties": {
    "addr:full":"2120 Statesville Blvd Salisbury NC 28147",
    "addr:housenumber":"2120",
    "addr:postcode":"28147",
    "addr:street":"Statesville Blvd",
    "iso:country":"US",
    "sg:address":"2120 Statesville Blvd",
    "sg:city":"Salisbury",
    "sg:classifiers":[
        {
            "category":"Shopping",
            "subcategory":"Shoes",
            "type":"Retail Goods"
        }
    ],
    "sg:phone":"+1 704 633 6280",
    "sg:postcode":"28147",
    "sg:province":"NC",
    "sg:website":"www.rackroomshoes.com",
    "wof:name":"Rack Room Shoes 201",
    "wof:placetype":"venue"
},
  "geometry": {"coordinates":[-80.516176,35.694536],"type":"Point"}
}