{
  "type": "Feature",
  "properties": {
    "iso:country":"US",
    "sg:address":"144 Capel Ln",
    "sg:city":"Eagle Springs",
    "sg:classifiers":[
        {
            "category":"Shopping",
            "subcategory":"Florist",
            "type":"Retail Goods"
        }
    ],
    "sg:phone":"+1 910 673 3307",
    "sg:postcode":"27242",
    "sg:province":"NC",
    "wof:name":"Eagle Springs Florist",
    "wof:placetype":"venue"
},
  "geometry": {"coordinates":[-79.697942,35.298647],"type":"Point"}
}