{
  "type": "Feature",
  "properties": {
    "addr:full":"104 S Center St Goldsboro NC 27530",
    "addr:housenumber":"104",
    "addr:postcode":"27530",
    "addr:street":"S Center St",
    "iso:country":"US",
    "sg:address":"104 S Center St",
    "sg:city":"Goldsboro",
    "sg:classifiers":[
        {
            "category":"Health Services",
            "subcategory":"Health Practitioner",
            "type":"Services"
        }
    ],
    "sg:phone":"+1 919 736 7959",
    "sg:postcode":"27530",
    "sg:province":"NC",
    "sg:tags":[
        "psychologist"
    ],
    "wof:name":"Jerome Albert PHD",
    "wof:placetype":"venue"
},
  "geometry": {"coordinates":[-77.99747000000001,35.381756],"type":"Point"}
}