{
  "type": "Feature",
  "properties": {
    "addr:full":"440 N Eugene St Greensboro NC 27401",
    "addr:housenumber":"440",
    "addr:postcode":"27401",
    "addr:street":"N Eugene St",
    "iso:country":"US",
    "sg:address":"440 N Eugene St",
    "sg:city":"Greensboro",
    "sg:classifiers":[
        {
            "category":"Professional",
            "subcategory":"Business Services",
            "type":"Services"
        },
        {
            "category":"Personal",
            "subcategory":"Beauty Salon",
            "type":"Services"
        }
    ],
    "sg:phone":"+1 336 273 0025",
    "sg:postcode":"27401",
    "sg:province":"NC",
    "wof:name":"Orrell Design LLC",
    "wof:placetype":"venue"
},
  "geometry": {"coordinates":[-79.793701,36.077647],"type":"Point"}
}