{
  "type": "Feature",
  "properties": {
    "addr:full":"2826 Timber Ridge Lake Rd Liberty NC 27298",
    "addr:housenumber":"2826",
    "addr:postcode":"27298",
    "addr:street":"Timber Ridge Lake Rd",
    "iso:country":"US",
    "sg:address":"2826 Timber Ridge Lake Rd",
    "sg:city":"Liberty",
    "sg:classifiers":[
        {
            "category":"Freight",
            "type":"Transportation"
        }
    ],
    "sg:phone":"+1 336 565 4567",
    "sg:postcode":"27298",
    "sg:province":"NC",
    "sg:tags":[
        "operator",
        "trucking"
    ],
    "wof:name":"James F Thompson Trucking",
    "wof:placetype":"venue"
},
  "geometry": {"coordinates":[-79.51030299999999,35.909357],"type":"Point"}
}