{
  "type": "Feature",
  "properties": {
    "iso:country":"US",
    "sg:address":"125 Floyd Smith Ofc Park Dr",
    "sg:city":"Charlotte",
    "sg:classifiers":[
        {
            "category":"Professional",
            "subcategory":"Management & Consulting",
            "type":"Services"
        }
    ],
    "sg:phone":"+1 704 295 1300",
    "sg:postcode":"28262",
    "sg:province":"NC",
    "sg:tags":[
        "fire",
        "consultant",
        "protection"
    ],
    "wof:name":"Schirmer Engineering Corp",
    "wof:placetype":"venue"
},
  "geometry": {"coordinates":[-80.698656,35.346636],"type":"Point"}
}