{
  "type": "Feature",
  "properties": {
    "addr:full":"8801 J M Keynes Dr Charlotte NC 28262",
    "addr:housenumber":"8801",
    "addr:postcode":"28262",
    "addr:street":"J M Keynes Dr",
    "iso:country":"US",
    "sg:address":"8801 J M Keynes Dr",
    "sg:city":"Charlotte",
    "sg:classifiers":[
        {
            "category":"Building & Trades",
            "subcategory":"Equipment Rental",
            "type":"Services"
        }
    ],
    "sg:phone":"+1 704 596 1310",
    "sg:postcode":"28262",
    "sg:province":"NC",
    "sg:tags":[
        "leasing"
    ],
    "wof:name":"Flex Lease Financial Services",
    "wof:placetype":"venue"
},
  "geometry": {"coordinates":[-80.748881,35.308428],"type":"Point"}
}