{
  "type": "Feature",
  "properties": {
    "iso:country":"US",
    "sg:address":"3917 South Blvd",
    "sg:city":"Charlotte",
    "sg:classifiers":[
        {
            "category":"Personal",
            "subcategory":"Beauty Salon",
            "type":"Services"
        }
    ],
    "sg:phone":"+1   ",
    "sg:postcode":"28209",
    "sg:province":"NC",
    "sg:tags":[
        "shop"
    ],
    "wof:name":"Curls & Swirls",
    "wof:placetype":"venue"
},
  "geometry": {"coordinates":[-80.875541,35.188984],"type":"Point"}
}