{
  "type": "Feature",
  "properties": {
    "iso:country":"US",
    "sg:address":"723 Bayshore Dr",
    "sg:city":"Wilmington",
    "sg:classifiers":[
        {
            "category":"Banks & Credit Unions",
            "subcategory":"Financial Services",
            "type":"Services"
        }
    ],
    "sg:phone":"+1 910 686 4615",
    "sg:postcode":"28411",
    "sg:province":"NC",
    "sg:tags":[
        "company",
        "holding"
    ],
    "wof:name":"Preferred Holding Corp",
    "wof:placetype":"venue"
},
  "geometry": {"coordinates":[-77.791068,34.281727],"type":"Point"}
}