{
  "type": "Feature",
  "properties": {
    "iso:country":"US",
    "sg:address":"2910 Agner Rd",
    "sg:city":"Salisbury",
    "sg:classifiers":[
        {
            "category":"Building & Trades",
            "subcategory":"Construction",
            "type":"Services"
        }
    ],
    "sg:phone":"+1 704 637 9591",
    "sg:postcode":"28146",
    "sg:province":"NC",
    "sg:tags":[
        "contractor"
    ],
    "wof:name":"Mike Fink",
    "wof:placetype":"venue"
},
  "geometry": {"coordinates":[-80.335043,35.628845],"type":"Point"}
}