{
  "type": "Feature",
  "properties": {
    "iso:country":"US",
    "sg:address":"3300 N Patterson Ave",
    "sg:city":"Winston Salem",
    "sg:classifiers":[
        {
            "category":"Restaurant",
            "type":"Food & Drink"
        }
    ],
    "sg:menulink":"http://www.allmenus.com/nc/winston/153344-bojangles/menu/",
    "sg:phone":"+1 336 724 9746",
    "sg:postcode":"27105",
    "sg:province":"NC",
    "sg:tags":[
        "chicken",
        "sandwich",
        "american"
    ],
    "wof:name":"Bojangle's",
    "wof:placetype":"venue"
},
  "geometry": {"coordinates":[-80.242062,36.132955],"type":"Point"}
}