{
  "type": "Feature",
  "properties": {
    "iso:country":"US",
    "sg:address":"5910 Duraleigh Rd Ste 131",
    "sg:city":"Raleigh",
    "sg:classifiers":[
        {
            "category":"Restaurant",
            "type":"Food & Drink"
        }
    ],
    "sg:phone":"+1 919 571 9111",
    "sg:postcode":"27612",
    "sg:province":"NC",
    "sg:tags":[
        "mexican"
    ],
    "wof:name":"Salsa Fresh Mexican Grill",
    "wof:placetype":"venue"
},
  "geometry": {"coordinates":[-78.7127,35.858501],"type":"Point"}
}