{
  "type": "Feature",
  "properties": {
    "iso:country":"US",
    "sg:address":"206 N Little Egypt Rd",
    "sg:city":"Denver",
    "sg:classifiers":[
        {
            "category":"Education",
            "subcategory":"School",
            "type":"Public Place"
        }
    ],
    "sg:phone":"+1 704 736 1895",
    "sg:postcode":"28037",
    "sg:province":"NC",
    "wof:name":"Catawba Springs Elementary",
    "wof:placetype":"venue"
},
  "geometry": {"coordinates":[-81.022828,35.462354],"type":"Point"}
}