{
  "type": "Feature",
  "properties": {
    "iso:country":"US",
    "sg:address":"834 Fork Point Rd",
    "sg:city":"Oriental",
    "sg:classifiers":[
        {
            "category":"Building & Trades",
            "subcategory":"Landscaping Services",
            "type":"Services"
        }
    ],
    "sg:phone":"+1 252 249 0003",
    "sg:postcode":"28571",
    "sg:province":"NC",
    "wof:name":"Newmans Tree Care",
    "wof:placetype":"venue"
},
  "geometry": {"coordinates":[-76.638876,35.095491],"type":"Point"}
}