{
  "type": "Feature",
  "properties": {
    "iso:country":"US",
    "sg:address":"503 Piedmont St",
    "sg:city":"Reidsville",
    "sg:classifiers":[
        {
            "category":"Professional",
            "subcategory":"Business Services",
            "type":"Services"
        }
    ],
    "sg:phone":"+1   ",
    "sg:postcode":"27320",
    "sg:province":"NC",
    "wof:name":"Gryffon Enterprises Inc",
    "wof:placetype":"venue"
},
  "geometry": {"coordinates":[-79.669522,36.356208],"type":"Point"}
}