{
  "type": "Feature",
  "properties": {
    "iso:country":"US",
    "sg:address":"77 Central Ave",
    "sg:city":"Asheville",
    "sg:classifiers":[
        {
            "category":"Real Estate",
            "subcategory":"Real Estate Services",
            "type":"Services"
        }
    ],
    "sg:phone":"+1 828 225 8572",
    "sg:postcode":"28801",
    "sg:province":"NC",
    "sg:tags":[
        "company",
        "title"
    ],
    "wof:name":"North Carolina Closing & Title",
    "wof:placetype":"venue"
},
  "geometry": {"coordinates":[-82.549899,35.601094],"type":"Point"}
}