{
  "type": "Feature",
  "properties": {
    "addr:full":"1267 Tredwell Dr Winston Salem NC 27103",
    "addr:housenumber":"1267",
    "addr:postcode":"27103",
    "addr:street":"Tredwell Dr",
    "iso:country":"US",
    "sg:address":"1267 Tredwell Dr",
    "sg:city":"Winston Salem",
    "sg:classifiers":[
        {
            "category":"Professional",
            "type":"Services"
        }
    ],
    "sg:phone":"+1 336 722 6779",
    "sg:postcode":"27103",
    "sg:province":"NC",
    "wof:name":"Charles L Canty",
    "wof:placetype":"venue"
},
  "geometry": {"coordinates":[-80.266008,36.073385],"type":"Point"}
}