{
  "type": "Feature",
  "properties": {
    "addr:full":"8316 Pineville-Matthews Rd Charlotte NC 28226",
    "addr:housenumber":"8316",
    "addr:postcode":"28226",
    "addr:street":"Pineville-Matthews Rd",
    "iso:country":"US",
    "sg:address":"8316 Pineville-Matthews Rd",
    "sg:city":"Charlotte",
    "sg:classifiers":[
        {
            "category":"Banks & Credit Unions",
            "subcategory":"Bank",
            "type":"Services"
        }
    ],
    "sg:phone":"+1 704 541 7114",
    "sg:postcode":"28226",
    "sg:province":"NC",
    "sg:tags":[
        "mortgage"
    ],
    "wof:name":"Wells Fargo",
    "wof:placetype":"venue"
},
  "geometry": {"coordinates":[-80.861724,35.087616],"type":"Point"}
}