{
  "type": "Feature",
  "properties": {
    "iso:country":"US",
    "sg:address":"143 Rattlesnake Ln",
    "sg:city":"Millers Creek",
    "sg:classifiers":[
        {
            "category":"Building & Trades",
            "subcategory":"Construction",
            "type":"Services"
        }
    ],
    "sg:phone":"+1 336 667 5429",
    "sg:postcode":"28651",
    "sg:province":"NC",
    "sg:tags":[
        "contractor"
    ],
    "wof:name":"Dolinger Construction",
    "wof:placetype":"venue"
},
  "geometry": {"coordinates":[-81.24440300000001,36.18913],"type":"Point"}
}