{
  "type": "Feature",
  "properties": {
    "addr:full":"305 Charles Rd Shelby NC 28152",
    "addr:housenumber":"305",
    "addr:postcode":"28152",
    "addr:street":"Charles Rd",
    "iso:country":"US",
    "sg:address":"305 Charles Rd",
    "sg:city":"Shelby",
    "sg:classifiers":[
        {
            "category":"Personal",
            "subcategory":"Beauty Salon",
            "type":"Services"
        }
    ],
    "sg:phone":"+1   ",
    "sg:postcode":"28152",
    "sg:province":"NC",
    "sg:tags":[
        "shop"
    ],
    "wof:name":"Tangles Salon",
    "wof:placetype":"venue"
},
  "geometry": {"coordinates":[-81.561583,35.288354],"type":"Point"}
}