{
  "type": "Feature",
  "properties": {
    "iso:country":"US",
    "sg:address":"6131 Falls of Neuse Rd",
    "sg:city":"Raleigh",
    "sg:classifiers":[
        {
            "category":"Banks & Credit Unions",
            "subcategory":"Bank",
            "type":"Services"
        }
    ],
    "sg:phone":"+1 919 790 8011",
    "sg:postcode":"27609",
    "sg:province":"NC",
    "sg:tags":[
        "residential",
        "banker",
        "mortgage"
    ],
    "wof:name":"Charter One",
    "wof:placetype":"venue"
},
  "geometry": {"coordinates":[-78.62070799999999,35.866591],"type":"Point"}
}