{
  "type": "Feature",
  "properties": {
    "iso:country":"US",
    "sg:address":"2609 E 10th St",
    "sg:city":"Greenville",
    "sg:classifiers":[
        {
            "category":"Food & Beverages",
            "subcategory":"Groceries & Convenience Stores",
            "type":"Retail Goods"
        }
    ],
    "sg:phone":"+1 252 758 6425",
    "sg:postcode":"27858",
    "sg:province":"NC",
    "wof:name":"LA Perla Del Pacifico",
    "wof:placetype":"venue"
},
  "geometry": {"coordinates":[-77.343312,35.603597],"type":"Point"}
}