{
  "type": "Feature",
  "properties": {
    "iso:country":"US",
    "sg:address":"12311 Danielle Christina Ct",
    "sg:city":"Charlotte",
    "sg:classifiers":[
        {
            "category":"Professional",
            "type":"Services"
        }
    ],
    "sg:phone":"+1 704 399 0661",
    "sg:postcode":"28216",
    "sg:province":"NC",
    "wof:name":"Angelique R Wignot",
    "wof:placetype":"venue"
},
  "geometry": {"coordinates":[-80.94687500000001,35.340687],"type":"Point"}
}