{
  "type": "Feature",
  "properties": {
    "iso:country":"US",
    "sg:address":"3001 Maplewood Ave",
    "sg:city":"Winston Salem",
    "sg:classifiers":[
        {
            "category":"Shopping",
            "subcategory":"Optical Goods",
            "type":"Retail Goods"
        }
    ],
    "sg:phone":"+1 336 765 2865",
    "sg:postcode":"27103",
    "sg:province":"NC",
    "wof:name":"Ardmore Opticians Inc",
    "wof:placetype":"venue"
},
  "geometry": {"coordinates":[-80.29422,36.08029],"type":"Point"}
}