{
  "type": "Feature",
  "properties": {
    "iso:country":"US",
    "sg:address":"140 US Hwy 321",
    "sg:city":"Hickory",
    "sg:classifiers":[
        {
            "category":"Food & Beverages",
            "subcategory":"Groceries & Convenience Stores",
            "type":"Retail Goods"
        }
    ],
    "sg:phone":"+1 828 322 4720",
    "sg:postcode":"28601",
    "sg:province":"NC",
    "wof:name":"Wilco Hess",
    "wof:placetype":"venue"
},
  "geometry": {"coordinates":[-81.364609,35.731241],"type":"Point"}
}