{
  "type": "Feature",
  "properties": {
    "iso:country":"US",
    "sg:address":"3316 Boat Club Rd",
    "sg:city":"Belmont",
    "sg:classifiers":[
        {
            "category":"Building & Trades",
            "subcategory":"Construction",
            "type":"Services"
        }
    ],
    "sg:phone":"+1 704 825 2561",
    "sg:postcode":"28012",
    "sg:province":"NC",
    "sg:tags":[
        "roofing",
        "contractor"
    ],
    "wof:name":"Riverside Home Improvement",
    "wof:placetype":"venue"
},
  "geometry": {"coordinates":[-81.02328300000001,35.202147],"type":"Point"}
}