{
  "type": "Feature",
  "properties": {
    "iso:country":"US",
    "sg:address":"140 State Hwy 9",
    "sg:city":"Black Mountain",
    "sg:classifiers":[
        {
            "category":"Restaurant",
            "type":"Food & Drink"
        }
    ],
    "sg:phone":"+1 828 669 5062",
    "sg:postcode":"28711",
    "sg:province":"NC",
    "sg:tags":[
        "eating"
    ],
    "wof:name":"McDonalds",
    "wof:placetype":"venue"
},
  "geometry": {"coordinates":[-82.32162599999999,35.621196],"type":"Point"}
}