{
  "type": "Feature",
  "properties": {
    "iso:country":"US",
    "sg:address":"3934 Pekin Rd",
    "sg:city":"Candor",
    "sg:classifiers":[
        {
            "category":"Organizations",
            "subcategory":"Religious Organization",
            "type":"Services"
        }
    ],
    "sg:phone":"+1   ",
    "sg:postcode":"27229",
    "sg:province":"NC",
    "wof:name":"Hickory Grove Pentecostl Hlnss",
    "wof:placetype":"venue"
},
  "geometry": {"coordinates":[-79.854191,35.253588],"type":"Point"}
}