{
  "type": "Feature",
  "properties": {
    "addr:full":"3591 Old Linwood Rd Lexington NC 27292",
    "addr:housenumber":"3591",
    "addr:postcode":"27292",
    "addr:street":"Old Linwood Rd",
    "iso:country":"US",
    "sg:address":"3591 Old Linwood Rd",
    "sg:city":"Lexington",
    "sg:classifiers":[
        {
            "category":"Organizations",
            "subcategory":"Religious Organization",
            "type":"Services"
        }
    ],
    "sg:phone":"+1 336 956 6287",
    "sg:postcode":"27292",
    "sg:province":"NC",
    "sg:tags":[
        "church"
    ],
    "sg:website":"www.newtestamentbaptist.org",
    "wof:name":"New Testament Baptist Church",
    "wof:placetype":"venue"
},
  "geometry": {"coordinates":[-80.308561,35.768051],"type":"Point"}
}