{
  "type": "Feature",
  "properties": {
    "addr:full":"6118 Saint Giles St # 130 Raleigh NC 27612",
    "addr:housenumber":"6118",
    "addr:postcode":"27612",
    "addr:street":"Saint Giles St # 130",
    "iso:country":"US",
    "sg:address":"6118 Saint Giles St # 130",
    "sg:city":"Raleigh",
    "sg:classifiers":[
        {
            "category":"Professional",
            "subcategory":"Engineering",
            "type":"Services"
        },
        {
            "category":"Wholesale",
            "subcategory":"Electrical",
            "type":"Manufacturing & Wholesale Goods"
        }
    ],
    "sg:phone":"+1 919 781 8011",
    "sg:postcode":"27612",
    "sg:province":"NC",
    "sg:tags":[
        "system",
        "systems-wholesale",
        "equipment",
        "air conditioning",
        "manufacturer"
    ],
    "sg:website":"http://www.hoffman-hoffman.com",
    "wof:name":"Hoffman & Hoffman, Inc.",
    "wof:placetype":"venue"
},
  "geometry": {"coordinates":[-78.703873,35.85453],"type":"Point"}
}