{
  "type": "Feature",
  "properties": {
    "iso:country":"US",
    "sg:address":"1309 Buck Shoals Rd",
    "sg:city":"Hamptonville",
    "sg:classifiers":[
        {
            "category":"Utilities",
            "subcategory":"Fuel Oil & Lpg",
            "type":"Services"
        }
    ],
    "sg:phone":"+1 336 468 1446",
    "sg:postcode":"27020",
    "sg:province":"NC",
    "sg:tags":[
        "propane"
    ],
    "wof:name":"Javelina Propane LLC",
    "wof:placetype":"venue"
},
  "geometry": {"coordinates":[-80.821065,36.117545],"type":"Point"}
}