{
  "type": "Feature",
  "properties": {
    "iso:country":"US",
    "sg:address":"2330 Tipton Dr Ste 900",
    "sg:city":"Charlotte",
    "sg:classifiers":[
        {
            "category":"Home & Garden",
            "subcategory":"Building Materials",
            "type":"Retail Goods"
        }
    ],
    "sg:phone":"+1 704 333 3220",
    "sg:postcode":"28206",
    "sg:province":"NC",
    "sg:tags":[
        "garage",
        "opener",
        "door"
    ],
    "wof:name":"Southern Ideal Door",
    "wof:placetype":"venue"
},
  "geometry": {"coordinates":[-80.842206,35.270425],"type":"Point"}
}