{
  "type": "Feature",
  "properties": {
    "addr:full":"1670 Lowery St Winston Salem NC 27101",
    "addr:housenumber":"1670",
    "addr:postcode":"27101",
    "addr:street":"Lowery St",
    "iso:country":"US",
    "sg:address":"1670 Lowery St",
    "sg:city":"Winston Salem",
    "sg:classifiers":[
        {
            "category":"Manufacturing",
            "subcategory":"Signs",
            "type":"Manufacturing & Wholesale Goods"
        }
    ],
    "sg:phone":"+1 336 499 1341",
    "sg:postcode":"27101",
    "sg:province":"NC",
    "sg:tags":[
        "specialty",
        "mfg"
    ],
    "wof:name":"Sign Source South LLC",
    "wof:placetype":"venue"
},
  "geometry": {"coordinates":[-80.218058,36.094356],"type":"Point"}
}