{
  "type": "Feature",
  "properties": {
    "addr:full":"164 Marion St Marion NC 28752",
    "addr:housenumber":"164",
    "addr:postcode":"28752",
    "addr:street":"Marion St",
    "iso:country":"US",
    "sg:address":"164 Marion St",
    "sg:city":"Marion",
    "sg:classifiers":[
        {
            "category":"Shopping",
            "subcategory":"Discount & Variety Stores",
            "type":"Retail Goods"
        }
    ],
    "sg:phone":"+1 828 659 8301",
    "sg:postcode":"28752",
    "sg:province":"NC",
    "wof:name":"Dollar General",
    "wof:placetype":"venue"
},
  "geometry": {"coordinates":[-81.98835,35.675343],"type":"Point"}
}