{
  "type": "Feature",
  "properties": {
    "iso:country":"US",
    "sg:address":"1569 Stanley Lucia Rd",
    "sg:city":"Stanley",
    "sg:classifiers":[
        {
            "category":"Manufacturing",
            "subcategory":"Leather Goods",
            "type":"Manufacturing & Wholesale Goods"
        }
    ],
    "sg:phone":"+1 704 263 8475",
    "sg:postcode":"28120",
    "sg:province":"NC",
    "wof:name":"Earl Alexander Co",
    "wof:placetype":"venue"
},
  "geometry": {"coordinates":[-81.04986100000001,35.360992],"type":"Point"}
}