{
  "type": "Feature",
  "properties": {
    "addr:full":"3000 Old US Hwy 52 Lexington NC 27295",
    "addr:housenumber":"3000",
    "addr:postcode":"27295",
    "addr:street":"Old Us Hwy 52",
    "iso:country":"US",
    "sg:address":"3000 Old US Hwy 52",
    "sg:city":"Lexington",
    "sg:classifiers":[
        {
            "category":"Shopping",
            "subcategory":"Bicycles & Sporting Goods",
            "type":"Retail Goods"
        }
    ],
    "sg:phone":"+1 336 249 4388",
    "sg:postcode":"27295",
    "sg:province":"NC",
    "sg:tags":[
        "gun",
        "gunsmith"
    ],
    "wof:name":"Gun Store",
    "wof:placetype":"venue"
},
  "geometry": {"coordinates":[-80.250125,35.867332],"type":"Point"}
}