{
  "type": "Feature",
  "properties": {
    "addr:full":"2648 Somers Rd Hamptonville NC 27020",
    "addr:housenumber":"2648",
    "addr:postcode":"27020",
    "addr:street":"Somers Rd",
    "iso:country":"US",
    "sg:address":"2648 Somers Rd",
    "sg:city":"Hamptonville",
    "sg:classifiers":[
        {
            "category":"Building & Trades",
            "subcategory":"Pest Control",
            "type":"Services"
        }
    ],
    "sg:phone":"+1 336 246 4222",
    "sg:postcode":"27020",
    "sg:province":"NC",
    "wof:name":"Rid-A-Bug Exterminating",
    "wof:placetype":"venue"
},
  "geometry": {"coordinates":[-80.901793,36.122911],"type":"Point"}
}