{
  "type": "Feature",
  "properties": {
    "addr:full":"103 Weaverville Rd Asheville NC 28804",
    "addr:housenumber":"103",
    "addr:postcode":"28804",
    "addr:street":"Weaverville Rd",
    "iso:country":"US",
    "sg:address":"103 Weaverville Rd",
    "sg:city":"Asheville",
    "sg:classifiers":[
        {
            "category":"Building & Trades",
            "subcategory":"Construction",
            "type":"Services"
        }
    ],
    "sg:phone":"+1 828 645 3183",
    "sg:postcode":"28804",
    "sg:province":"NC",
    "sg:tags":[
        "hanging",
        "contractor"
    ],
    "wof:name":"Coat of Many Colors",
    "wof:placetype":"venue"
},
  "geometry": {"coordinates":[-82.579516,35.643236],"type":"Point"}
}