{
  "type": "Feature",
  "properties": {
    "addr:full":"217 S Steele St Sanford NC 27330",
    "addr:housenumber":"217",
    "addr:postcode":"27330",
    "addr:street":"S Steele St",
    "iso:country":"US",
    "sg:address":"217 S Steele St",
    "sg:city":"Sanford",
    "sg:classifiers":[
        {
            "category":"Professional",
            "subcategory":"Accounting & Tax Preparation",
            "type":"Services"
        }
    ],
    "sg:phone":"+1 919 774 9436",
    "sg:postcode":"27330",
    "sg:province":"NC",
    "sg:tags":[
        "accountant"
    ],
    "wof:name":"Elizabeth C Kelly",
    "wof:placetype":"venue"
},
  "geometry": {"coordinates":[-79.177995,35.479382],"type":"Point"}
}