{
  "type": "Feature",
  "properties": {
    "addr:full":"2330 Freedom Dr Ste 2 Charlotte NC 28208",
    "addr:housenumber":"2330",
    "addr:postcode":"28208",
    "addr:street":"Freedom Dr Ste 2",
    "iso:country":"US",
    "sg:address":"2330 Freedom Dr Ste 2",
    "sg:city":"Charlotte",
    "sg:classifiers":[
        {
            "category":"Home & Garden",
            "subcategory":"Furniture",
            "type":"Retail Goods"
        }
    ],
    "sg:phone":"+1 704 393 2750",
    "sg:postcode":"28208",
    "sg:province":"NC",
    "sg:tags":[
        "store"
    ],
    "wof:name":"Factory Direct Furniture",
    "wof:placetype":"venue"
},
  "geometry": {"coordinates":[-80.878593,35.23458],"type":"Point"}
}