{
  "type": "Feature",
  "properties": {
    "iso:country":"US",
    "sg:address":"801 E Center St",
    "sg:city":"Lexington",
    "sg:classifiers":[
        {
            "category":"Health Services",
            "subcategory":"Optometrist",
            "type":"Services"
        }
    ],
    "sg:phone":"+1   ",
    "sg:postcode":"27292",
    "sg:province":"NC",
    "wof:name":"David J Kowal Od Faao",
    "wof:placetype":"venue"
},
  "geometry": {"coordinates":[-80.24650099999999,35.81361],"type":"Point"}
}