{
  "type": "Feature",
  "properties": {
    "iso:country":"US",
    "sg:address":"184 E Chestnut St",
    "sg:city":"Asheville",
    "sg:classifiers":[
        {
            "category":"Social Services",
            "subcategory":"Job Training",
            "type":"Services"
        }
    ],
    "sg:phone":"+1 828 254 1276",
    "sg:postcode":"28801",
    "sg:province":"NC",
    "sg:tags":[
        "rehabilitation"
    ],
    "wof:name":"Facial Paralysis Ctr",
    "wof:placetype":"venue"
},
  "geometry": {"coordinates":[-82.549162,35.603156],"type":"Point"}
}