{
  "type": "Feature",
  "properties": {
    "iso:country":"US",
    "sg:address":"3212 Lintel Rd",
    "sg:city":"Midland",
    "sg:classifiers":[
        {
            "category":"Professional",
            "subcategory":"Management & Consulting",
            "type":"Services"
        }
    ],
    "sg:phone":"+1   ",
    "sg:postcode":"28107",
    "sg:province":"NC",
    "wof:name":"Enduracare Therapy Mgmt",
    "wof:placetype":"venue"
},
  "geometry": {"coordinates":[-80.519785,35.244048],"type":"Point"}
}