{
  "type": "Feature",
  "properties": {
    "iso:country":"US",
    "sg:address":"600 N 13th St",
    "sg:city":"Butner",
    "sg:classifiers":[
        {
            "category":"Professional",
            "subcategory":"Computer Services",
            "type":"Services"
        }
    ],
    "sg:phone":"+1 919 575 0275",
    "sg:postcode":"27509",
    "sg:province":"NC",
    "sg:tags":[
        "internet"
    ],
    "wof:name":"Allen Marketing",
    "wof:placetype":"venue"
},
  "geometry": {"coordinates":[-78.77043999999999,36.13667],"type":"Point"}
}