{
  "type": "Feature",
  "properties": {
    "addr:full":"8638 Common Oak Ln Huntersville NC 28078",
    "addr:housenumber":"8638",
    "addr:postcode":"28078",
    "addr:street":"Common Oak Ln",
    "iso:country":"US",
    "sg:address":"8638 Common Oak Ln",
    "sg:city":"Huntersville",
    "sg:classifiers":[
        {
            "category":"Professional",
            "type":"Services"
        }
    ],
    "sg:phone":"+1 704 339 2278",
    "sg:postcode":"28078",
    "sg:province":"NC",
    "wof:name":"Jennifer St John",
    "wof:placetype":"venue"
},
  "geometry": {"coordinates":[-80.892765,35.435564],"type":"Point"}
}