{
  "type": "Feature",
  "properties": {
    "addr:full":"3300 State Hwy 82 Dunn NC 28334",
    "addr:housenumber":"3300",
    "addr:postcode":"28334",
    "addr:street":"State Hwy 82",
    "iso:country":"US",
    "sg:address":"3300 State Hwy 82",
    "sg:city":"Dunn",
    "sg:classifiers":[
        {
            "category":"Museum",
            "type":"Entertainment"
        }
    ],
    "sg:phone":"+1 910 891 5019",
    "sg:postcode":"28334",
    "sg:province":"NC",
    "sg:website":"www.averasboro.com",
    "wof:name":"Averasboro Battlefield Museum",
    "wof:placetype":"venue"
},
  "geometry": {"coordinates":[-78.67191800000001,35.266095],"type":"Point"}
}