{
  "type": "Feature",
  "properties": {
    "addr:full":"1005 Monroe St Carthage NC 28327",
    "addr:housenumber":"1005",
    "addr:postcode":"28327",
    "addr:street":"Monroe St",
    "iso:country":"US",
    "sg:address":"1005 Monroe St",
    "sg:city":"Carthage",
    "sg:classifiers":[
        {
            "category":"Professional",
            "subcategory":"Accounting & Tax Preparation",
            "type":"Services"
        }
    ],
    "sg:phone":"+1 910 947 2114",
    "sg:postcode":"28327",
    "sg:province":"NC",
    "sg:tags":[
        "return",
        "filing"
    ],
    "wof:name":"H & R Block Tax Svc",
    "wof:placetype":"venue"
},
  "geometry": {"coordinates":[-79.401578,35.341109],"type":"Point"}
}