{
  "type": "Feature",
  "properties": {
    "addr:full":"3308 Timberview Cir Greensboro NC 27410",
    "addr:housenumber":"3308",
    "addr:postcode":"27410",
    "addr:street":"Timberview Cir",
    "iso:country":"US",
    "sg:address":"3308 Timberview Cir",
    "sg:city":"Greensboro",
    "sg:classifiers":[
        {
            "category":"Professional",
            "subcategory":"Management & Consulting",
            "type":"Services"
        }
    ],
    "sg:phone":"+1 336 286 0084",
    "sg:postcode":"27410",
    "sg:province":"NC",
    "sg:tags":[
        "consultant",
        "business"
    ],
    "wof:name":"Thomas Mc Goldrick",
    "wof:placetype":"venue"
},
  "geometry": {"coordinates":[-79.864457,36.124273],"type":"Point"}
}