{
  "type": "Feature",
  "properties": {
    "addr:full":"7124 Ryan St Fayetteville NC 28314",
    "addr:housenumber":"7124",
    "addr:postcode":"28314",
    "addr:street":"Ryan St",
    "iso:country":"US",
    "sg:address":"7124 Ryan St",
    "sg:city":"Fayetteville",
    "sg:classifiers":[
        {
            "category":"Building & Trades",
            "subcategory":"Cleaning & Sanitation",
            "type":"Services"
        }
    ],
    "sg:phone":"+1 910 864 4626",
    "sg:postcode":"28314",
    "sg:province":"NC",
    "sg:tags":[
        "janitor"
    ],
    "wof:name":"Clean Inc",
    "wof:placetype":"venue"
},
  "geometry": {"coordinates":[-79.007772,35.071216],"type":"Point"}
}