{
  "type": "Feature",
  "properties": {
    "addr:full":"1014 W Knox St Durham NC 27701",
    "addr:housenumber":"1014",
    "addr:postcode":"27701",
    "addr:street":"W Knox St",
    "iso:country":"US",
    "sg:address":"1014 W Knox St",
    "sg:city":"Durham",
    "sg:classifiers":[
        {
            "category":"Wholesale",
            "subcategory":"Durable Goods & Equipment",
            "type":"Manufacturing & Wholesale Goods"
        }
    ],
    "sg:phone":"+1 919 667 0334",
    "sg:postcode":"27701",
    "sg:province":"NC",
    "sg:tags":[
        "laboratory",
        "supply",
        "professional"
    ],
    "wof:name":"Glakad Science LLC",
    "wof:placetype":"venue"
},
  "geometry": {"coordinates":[-78.90954000000001,36.013233],"type":"Point"}
}