{
  "type": "Feature",
  "properties": {
    "addr:full":"8511 State Hwy 210 W Garland NC 28441",
    "addr:housenumber":"8511",
    "addr:postcode":"28441",
    "addr:street":"State Hwy 210 W",
    "iso:country":"US",
    "sg:address":"8511 State Hwy 210 W",
    "sg:city":"Garland",
    "sg:classifiers":[
        {
            "category":"Recreation",
            "type":"Entertainment"
        }
    ],
    "sg:phone":"+1   ",
    "sg:postcode":"28441",
    "sg:province":"NC",
    "wof:name":"Rusnik Catfish Farm",
    "wof:placetype":"venue"
},
  "geometry": {"coordinates":[-78.500454,34.842664],"type":"Point"}
}