{
  "type": "Feature",
  "properties": {
    "addr:full":"201 Hardy Ave Richlands NC 28574",
    "addr:housenumber":"201",
    "addr:postcode":"28574",
    "addr:street":"Hardy Ave",
    "iso:country":"US",
    "sg:address":"201 Hardy Ave",
    "sg:city":"Richlands",
    "sg:classifiers":[
        {
            "category":"Social Services",
            "subcategory":"Child Care",
            "type":"Services"
        }
    ],
    "sg:phone":"+1   ",
    "sg:postcode":"28574",
    "sg:province":"NC",
    "sg:tags":[
        "day"
    ],
    "wof:name":"Day Farms",
    "wof:placetype":"venue"
},
  "geometry": {"coordinates":[-77.55300200000001,34.89766],"type":"Point"}
}