{
  "type": "Feature",
  "properties": {
    "iso:country":"US",
    "sg:address":"3724 Rolling Rd",
    "sg:city":"High Point",
    "sg:classifiers":[
        {
            "category":"Wholesale",
            "subcategory":"Home Furnishings",
            "type":"Manufacturing & Wholesale Goods"
        }
    ],
    "sg:phone":"+1 336 869 5220",
    "sg:postcode":"27265",
    "sg:province":"NC",
    "sg:tags":[
        "carpet"
    ],
    "wof:name":"Carolina Wholesale Associates",
    "wof:placetype":"venue"
},
  "geometry": {"coordinates":[-80.01602,36.005742],"type":"Point"}
}