{
  "type": "Feature",
  "properties": {
    "iso:country":"US",
    "sg:address":"5676 Hampton Rd",
    "sg:city":"Clemmons",
    "sg:classifiers":[
        {
            "category":"Building & Trades",
            "subcategory":"Construction",
            "type":"Services"
        }
    ],
    "sg:phone":"+1 336 766 0209",
    "sg:postcode":"27012",
    "sg:province":"NC",
    "sg:tags":[
        "excavation",
        "contractor"
    ],
    "wof:name":"Redmonds Backhoe Service Inc",
    "wof:placetype":"venue"
},
  "geometry": {"coordinates":[-80.36702,35.973881],"type":"Point"}
}