{
  "type": "Feature",
  "properties": {
    "addr:full":"628 Grooms Rd Reidsville NC 27320",
    "addr:housenumber":"628",
    "addr:postcode":"27320",
    "addr:street":"Grooms Rd",
    "iso:country":"US",
    "sg:address":"628 Grooms Rd",
    "sg:city":"Reidsville",
    "sg:classifiers":[
        {
            "category":"Manufacturing",
            "subcategory":"Metals",
            "type":"Manufacturing & Wholesale Goods"
        }
    ],
    "sg:phone":"+1 336 342 0308",
    "sg:postcode":"27320",
    "sg:province":"NC",
    "sg:tags":[
        "treating",
        "heat"
    ],
    "sg:website":"www.ccht.com",
    "wof:name":"Carolina Commercial Heat Trtng",
    "wof:placetype":"venue"
},
  "geometry": {"coordinates":[-79.552981,36.376341],"type":"Point"}
}