{
  "type": "Feature",
  "properties": {
    "iso:country":"US",
    "sg:address":"9 Buck Shoals Rd",
    "sg:city":"Arden",
    "sg:classifiers":[
        {
            "category":"Building & Trades",
            "subcategory":"Landscaping Services",
            "type":"Services"
        }
    ],
    "sg:phone":"+1 828 654 0063",
    "sg:postcode":"28704",
    "sg:province":"NC",
    "sg:tags":[
        "lawn",
        "maintenance",
        "grounds"
    ],
    "wof:name":"Charlie's Lawn & Garden Repair",
    "wof:placetype":"venue"
},
  "geometry": {"coordinates":[-82.51393,35.461434],"type":"Point"}
}