{
  "type": "Feature",
  "properties": {
    "addr:full":"6733 Matthews Weddington Rd Matthews NC 28104",
    "addr:housenumber":"6733",
    "addr:postcode":"28104",
    "addr:street":"Matthews Weddington Rd",
    "iso:country":"US",
    "sg:address":"6733 Matthews Weddington Rd",
    "sg:city":"Matthews",
    "sg:classifiers":[
        {
            "category":"Building & Trades",
            "subcategory":"Construction",
            "type":"Services"
        }
    ],
    "sg:phone":"+1 704 846 2009",
    "sg:postcode":"28104",
    "sg:province":"NC",
    "sg:tags":[
        "contractor",
        "restoration",
        "cleaning",
        "patio",
        "deck"
    ],
    "wof:name":"A-1 Pressure Washing Inc",
    "wof:placetype":"venue"
},
  "geometry": {"coordinates":[-80.756793,35.025948],"type":"Point"}
}