{
  "type": "Feature",
  "properties": {
    "addr:full":"10481 US Hwy 117 Rocky Point NC 28457",
    "addr:housenumber":"10481",
    "addr:postcode":"28457",
    "addr:street":"Us Hwy 117",
    "iso:country":"US",
    "sg:address":"10481 US Hwy 117",
    "sg:city":"Rocky Point",
    "sg:classifiers":[
        {
            "category":"Freight",
            "type":"Transportation"
        }
    ],
    "sg:phone":"+1 910 602 3233",
    "sg:postcode":"28457",
    "sg:province":"NC",
    "sg:tags":[
        "hauling",
        "trucking"
    ],
    "wof:name":"American Hauling Svc",
    "wof:placetype":"venue"
},
  "geometry": {"coordinates":[-77.887901,34.407669],"type":"Point"}
}