{
  "type": "Feature",
  "properties": {
    "iso:country":"US",
    "sg:address":"928 S Main St",
    "sg:city":"Kannapolis",
    "sg:classifiers":[
        {
            "category":"Professional",
            "type":"Services"
        }
    ],
    "sg:phone":"+1 704 933 8311",
    "sg:postcode":"28081",
    "sg:province":"NC",
    "wof:name":"Sun City Corporation",
    "wof:placetype":"venue"
},
  "geometry": {"coordinates":[-80.62670199999999,35.481913],"type":"Point"}
}