{
  "type": "Feature",
  "properties": {
    "iso:country":"US",
    "sg:address":"201 N Hartman Rd",
    "sg:city":"Dallas",
    "sg:classifiers":[
        {
            "category":"Manufacturing",
            "subcategory":"Glass & Minerals",
            "type":"Manufacturing & Wholesale Goods"
        }
    ],
    "sg:phone":"+1 704 922 8638",
    "sg:postcode":"28034",
    "sg:province":"NC",
    "sg:tags":[
        "ready"
    ],
    "sg:website":"www.concretesupplyco.com",
    "wof:name":"Concrete Supply Co",
    "wof:placetype":"venue"
},
  "geometry": {"coordinates":[-81.18556,35.29869],"type":"Point"}
}