{
  "type": "Feature",
  "properties": {
    "iso:country":"US",
    "sg:address":"4606 State Hwy 87",
    "sg:city":"Saxapahaw",
    "sg:classifiers":[
        {
            "category":"Government",
            "subcategory":"Fire Station",
            "type":"Public Place"
        }
    ],
    "sg:phone":"+1 336 376 9399",
    "sg:postcode":"27330",
    "sg:province":"NC",
    "sg:tags":[
        "department"
    ],
    "wof:name":"Eighty-Seven South Volunteer",
    "wof:placetype":"venue"
},
  "geometry": {"coordinates":[-79.192927,35.57384],"type":"Point"}
}