{
  "type": "Feature",
  "properties": {
    "addr:full":"186 W Side Ln Powells Point NC 27966",
    "addr:housenumber":"186",
    "addr:postcode":"27966",
    "addr:street":"W Side Ln",
    "iso:country":"US",
    "sg:address":"186 W Side Ln",
    "sg:city":"Powells Point",
    "sg:classifiers":[
        {
            "category":"Building & Trades",
            "subcategory":"Construction",
            "type":"Services"
        }
    ],
    "sg:phone":"+1 252 491 2463",
    "sg:postcode":"27966",
    "sg:province":"NC",
    "sg:tags":[
        "contractor"
    ],
    "wof:name":"Home Town Builders - Outer",
    "wof:placetype":"venue"
},
  "geometry": {"coordinates":[-75.83543400000001,36.120385],"type":"Point"}
}