{
  "type": "Feature",
  "properties": {
    "iso:country":"US",
    "sg:address":"418 Kentucky Ave",
    "sg:city":"Wilmington",
    "sg:classifiers":[
        {
            "category":"Retail",
            "subcategory":"Auto Repair",
            "type":"Services"
        }
    ],
    "sg:phone":"+1 910 762 7591",
    "sg:postcode":"28401",
    "sg:province":"NC",
    "sg:tags":[
        "wrecker"
    ],
    "wof:name":"Earl Chambers Wrecker Svc Inc",
    "wof:placetype":"venue"
},
  "geometry": {"coordinates":[-77.945307,34.210224],"type":"Point"}
}