{
  "type": "Feature",
  "properties": {
    "iso:country":"US",
    "sg:address":"801 Mumford Rd",
    "sg:city":"Greenville",
    "sg:classifiers":[
        {
            "category":"Government",
            "subcategory":"Office",
            "type":"Public Place"
        }
    ],
    "sg:phone":"+1 252 551 1517",
    "sg:postcode":"27834",
    "sg:province":"NC",
    "sg:tags":[
        "commission",
        "utility"
    ],
    "wof:name":"Utilities Wareshouse",
    "wof:placetype":"venue"
},
  "geometry": {"coordinates":[-77.363518,35.629381],"type":"Point"}
}