{
  "type": "Feature",
  "properties": {
    "addr:full":"201 N Green Meadows Dr Wilmington NC 28405",
    "addr:housenumber":"201",
    "addr:postcode":"28405",
    "addr:street":"N Green Meadows Dr",
    "iso:country":"US",
    "sg:address":"201 N Green Meadows Dr",
    "sg:city":"Wilmington",
    "sg:classifiers":[
        {
            "category":"Wholesale",
            "subcategory":"Construction Materials",
            "type":"Manufacturing & Wholesale Goods"
        }
    ],
    "sg:phone":"+1 910 791 9787",
    "sg:postcode":"28405",
    "sg:province":"NC",
    "sg:tags":[
        "sand",
        "gravel"
    ],
    "wof:name":"Hackney Stone",
    "wof:placetype":"venue"
},
  "geometry": {"coordinates":[-77.84697,34.25796],"type":"Point"}
}