{
  "type": "Feature",
  "properties": {
    "addr:full":"1209 Culbreth Dr Wilmington NC 28405",
    "addr:housenumber":"1209",
    "addr:postcode":"28405",
    "addr:street":"Culbreth Dr",
    "iso:country":"US",
    "sg:address":"1209 Culbreth Dr",
    "sg:city":"Wilmington",
    "sg:classifiers":[
        {
            "category":"Professional",
            "subcategory":"Lawyer & Legal Services",
            "type":"Services"
        }
    ],
    "sg:phone":"+1 910 256 1051",
    "sg:postcode":"28405",
    "sg:province":"NC",
    "sg:tags":[
        "attorney"
    ],
    "wof:name":"Iplax Inc",
    "wof:placetype":"venue"
},
  "geometry": {"coordinates":[-77.828535,34.234111],"type":"Point"}
}