{
  "type": "Feature",
  "properties": {
    "addr:full":"120 E Pritchard St Asheboro NC 27203",
    "addr:housenumber":"120",
    "addr:postcode":"27203",
    "addr:street":"E Pritchard St",
    "iso:country":"US",
    "sg:address":"120 E Pritchard St",
    "sg:city":"Asheboro",
    "sg:classifiers":[
        {
            "category":"Manufacturing",
            "subcategory":"Tools & Machinery",
            "type":"Manufacturing & Wholesale Goods"
        }
    ],
    "sg:phone":"+1 336 629 3000",
    "sg:postcode":"27203",
    "sg:province":"NC",
    "sg:tags":[
        "physician",
        "surgeon"
    ],
    "wof:name":"Vesture Corp",
    "wof:placetype":"venue"
},
  "geometry": {"coordinates":[-79.810608,35.716868],"type":"Point"}
}