{
  "type": "Feature",
  "properties": {
    "addr:full":"104 City Hall Plz Durham NC 27701",
    "addr:housenumber":"104",
    "addr:postcode":"27701",
    "addr:street":"City Hall Plz",
    "iso:country":"US",
    "sg:address":"104 City Hall Plz",
    "sg:city":"Durham",
    "sg:classifiers":[
        {
            "category":"Professional",
            "type":"Services"
        }
    ],
    "sg:phone":"+1 919 530 1919",
    "sg:postcode":"27701",
    "sg:province":"NC",
    "sg:tags":[
        "establishment"
    ],
    "wof:name":"Five Gen",
    "wof:placetype":"venue"
},
  "geometry": {"coordinates":[-78.898054,35.995804],"type":"Point"}
}