{
  "type": "Feature",
  "properties": {
    "addr:full":"271 Executive Park Dr Concord NC 28025",
    "addr:housenumber":"271",
    "addr:postcode":"28025",
    "addr:street":"Executive Park Dr",
    "iso:country":"US",
    "sg:address":"271 Executive Park Dr",
    "sg:city":"Concord",
    "sg:classifiers":[
        {
            "category":"Health Services",
            "subcategory":"Clinic",
            "type":"Services"
        }
    ],
    "sg:phone":"+1 704 721 4232",
    "sg:postcode":"28025",
    "sg:province":"NC",
    "sg:tags":[
        "medical"
    ],
    "wof:name":"Mercy Cabarrus Clinic",
    "wof:placetype":"venue"
},
  "geometry": {"coordinates":[-80.599846,35.450248],"type":"Point"}
}