{
  "type": "Feature",
  "properties": {
    "iso:country":"US",
    "sg:address":"801 Corporate Ctr Dr Ste 110",
    "sg:city":"Raleigh",
    "sg:classifiers":[
        {
            "category":"Professional",
            "subcategory":"Detective & Security Services",
            "type":"Services"
        }
    ],
    "sg:phone":"+1 919 398 6445",
    "sg:postcode":"27607",
    "sg:province":"NC",
    "sg:tags":[
        "system"
    ],
    "sg:website":"www.SunstatesSecurity.com",
    "wof:name":"Sunstates Security",
    "wof:placetype":"venue"
},
  "geometry": {"coordinates":[-78.741585,35.793469],"type":"Point"}
}