{
  "type": "Feature",
  "properties": {
    "iso:country":"US",
    "sg:address":"131 Person St",
    "sg:city":"Fayetteville",
    "sg:classifiers":[
        {
            "category":"Personal",
            "subcategory":"Beauty Salon",
            "type":"Services"
        }
    ],
    "sg:phone":"+1   ",
    "sg:postcode":"28301",
    "sg:province":"NC",
    "sg:tags":[
        "shop"
    ],
    "wof:name":"Amazon Brids Hair Stylist Slon",
    "wof:placetype":"venue"
},
  "geometry": {"coordinates":[-78.87666900000001,35.052104],"type":"Point"}
}