{
  "type": "Feature",
  "properties": {
    "iso:country":"US",
    "sg:address":"2334 Cragmore Rd SE",
    "sg:city":"Winston Salem",
    "sg:classifiers":[
        {
            "category":"Wholesale",
            "subcategory":"Non-durable Goods",
            "type":"Manufacturing & Wholesale Goods"
        }
    ],
    "sg:phone":"+1 336 650 9010",
    "sg:postcode":"27107",
    "sg:province":"NC",
    "wof:name":"Sambro Marketing",
    "wof:placetype":"venue"
},
  "geometry": {"coordinates":[-80.18732799999999,36.072751],"type":"Point"}
}