{
  "type": "Feature",
  "properties": {
    "iso:country":"US",
    "sg:address":"1130 Red Oak Rd",
    "sg:city":"Nashville",
    "sg:classifiers":[
        {
            "category":"Building & Trades",
            "subcategory":"Construction",
            "type":"Services"
        }
    ],
    "sg:phone":"+1 252 459 5894",
    "sg:postcode":"27856",
    "sg:province":"NC",
    "sg:tags":[
        "house"
    ],
    "wof:name":"R&R Builders Inc",
    "wof:placetype":"venue"
},
  "geometry": {"coordinates":[-77.939306,35.987685],"type":"Point"}
}