{
  "type": "Feature",
  "properties": {
    "iso:country":"US",
    "sg:address":"5615 Harrisburg Industrial Park Dr",
    "sg:city":"Harrisburg",
    "sg:classifiers":[
        {
            "category":"Professional",
            "subcategory":"Management & Consulting",
            "type":"Services"
        }
    ],
    "sg:phone":"+1 704 455 3444",
    "sg:postcode":"28075",
    "sg:province":"NC",
    "sg:tags":[
        "consultant",
        "automation"
    ],
    "wof:name":"Automation Technologies Inc",
    "wof:placetype":"venue"
},
  "geometry": {"coordinates":[-80.669416,35.31352],"type":"Point"}
}