{
  "type": "Feature",
  "properties": {
    "addr:full":"8717 W Market St Greensboro NC 27409",
    "addr:housenumber":"8717",
    "addr:postcode":"27409",
    "addr:street":"W Market St",
    "iso:country":"US",
    "sg:address":"8717 W Market St",
    "sg:city":"Greensboro",
    "sg:classifiers":[
        {
            "category":"Professional",
            "subcategory":"Advertising",
            "type":"Services"
        }
    ],
    "sg:phone":"+1 336 665 2472",
    "sg:postcode":"27409",
    "sg:province":"NC",
    "sg:tags":[
        "mailing",
        "shipping"
    ],
    "wof:name":"Mail Transport",
    "wof:placetype":"venue"
},
  "geometry": {"coordinates":[-79.984272,36.103947],"type":"Point"}
}