{
  "type": "Feature",
  "properties": {
    "addr:full":"233 Market St Cramerton NC 28032",
    "addr:housenumber":"233",
    "addr:postcode":"28032",
    "addr:street":"Market St",
    "iso:country":"US",
    "sg:address":"233 Market St",
    "sg:city":"Cramerton",
    "sg:classifiers":[
        {
            "category":"Retail",
            "subcategory":"Auto Repair",
            "type":"Services"
        }
    ],
    "sg:phone":"+1 704 824 3638",
    "sg:postcode":"28032",
    "sg:province":"NC",
    "sg:tags":[
        "repairing",
        "automobile"
    ],
    "wof:name":"Ledford's Garage",
    "wof:placetype":"venue"
},
  "geometry": {"coordinates":[-81.08126900000001,35.24927],"type":"Point"}
}