{
  "type": "Feature",
  "properties": {
    "iso:country":"US",
    "sg:address":"1509 Cotherstone Dr",
    "sg:city":"Durham",
    "sg:classifiers":[
        {
            "category":"Professional",
            "subcategory":"Computer Services",
            "type":"Services"
        }
    ],
    "sg:phone":"+1 919 423 9557",
    "sg:postcode":"27712",
    "sg:province":"NC",
    "sg:tags":[
        "website",
        "design"
    ],
    "wof:name":"E Bizz Tools",
    "wof:placetype":"venue"
},
  "geometry": {"coordinates":[-78.938197,36.099097],"type":"Point"}
}