{
  "type": "Feature",
  "properties": {
    "iso:country":"US",
    "sg:address":"1316 N Queen St",
    "sg:city":"Kinston",
    "sg:classifiers":[
        {
            "category":"Shopping",
            "subcategory":"Department Store",
            "type":"Retail Goods"
        }
    ],
    "sg:phone":"+1 252 520 0070",
    "sg:postcode":"28501",
    "sg:province":"NC",
    "sg:tags":[
        "shop"
    ],
    "wof:name":"Dollar Power",
    "wof:placetype":"venue"
},
  "geometry": {"coordinates":[-77.58082400000001,35.275428],"type":"Point"}
}