{
  "type": "Feature",
  "properties": {
    "iso:country":"US",
    "sg:address":"536 Barbara Jane Ave NE",
    "sg:city":"Winston Salem",
    "sg:classifiers":[
        {
            "category":"Travel",
            "subcategory":"Campground",
            "type":"Entertainment"
        }
    ],
    "sg:phone":"+1 336 724 2811",
    "sg:postcode":"27101",
    "sg:province":"NC",
    "sg:tags":[
        "camp"
    ],
    "wof:name":"Unique Kids Camps",
    "wof:placetype":"venue"
},
  "geometry": {"coordinates":[-80.20539599999999,36.102736],"type":"Point"}
}