{
  "type": "Feature",
  "properties": {
    "iso:country":"US",
    "sg:address":"910 N Spence Ave",
    "sg:city":"Goldsboro",
    "sg:classifiers":[
        {
            "category":"Wholesale",
            "subcategory":"Machinery & Supplies",
            "type":"Manufacturing & Wholesale Goods"
        }
    ],
    "sg:phone":"+1 919 751 2360",
    "sg:postcode":"27534",
    "sg:province":"NC",
    "sg:tags":[
        "shop",
        "equipment",
        "salon",
        "barber",
        "beauty"
    ],
    "wof:name":"Sally Beauty Supply 604",
    "wof:placetype":"venue"
},
  "geometry": {"coordinates":[-77.94692999999999,35.387613],"type":"Point"}
}