{
  "type": "Feature",
  "properties": {
    "iso:country":"US",
    "sg:address":"411 W Chapel Hill St",
    "sg:city":"Durham",
    "sg:classifiers":[
        {
            "category":"Organizations",
            "subcategory":"Non-profit Organization",
            "type":"Services"
        },
        {
            "category":"Organizations",
            "subcategory":"Membership Organization",
            "type":"Services"
        }
    ],
    "sg:phone":"+1 919 683 3006",
    "sg:postcode":"27701",
    "sg:province":"NC",
    "sg:website":"www.dacinc.org",
    "wof:name":"Durham Area Corp",
    "wof:placetype":"venue"
},
  "geometry": {"coordinates":[-78.908699,35.996908],"type":"Point"}
}