{
  "type": "Feature",
  "properties": {
    "iso:country":"US",
    "sg:address":"2513 Sunset Ave",
    "sg:city":"Rocky Mount",
    "sg:classifiers":[
        {
            "category":"Retail",
            "subcategory":"Repair Shop",
            "type":"Services"
        }
    ],
    "sg:phone":"+1 252 443 1665",
    "sg:postcode":"27804",
    "sg:province":"NC",
    "sg:tags":[
        "jewelry"
    ],
    "wof:name":"Floras Jewelry Company",
    "wof:placetype":"venue"
},
  "geometry": {"coordinates":[-77.827997,35.961808],"type":"Point"}
}