{
  "type": "Feature",
  "properties": {
    "addr:full":"119 E Gordon St Kinston NC 28501",
    "addr:housenumber":"119",
    "addr:postcode":"28501",
    "addr:street":"E Gordon St",
    "iso:country":"US",
    "sg:address":"119 E Gordon St",
    "sg:city":"Kinston",
    "sg:classifiers":[
        {
            "category":"Professional",
            "subcategory":"Credit Reporting & Collection",
            "type":"Services"
        }
    ],
    "sg:phone":"+1   ",
    "sg:postcode":"28501",
    "sg:province":"NC",
    "sg:tags":[
        "agency"
    ],
    "wof:name":"East Coast Collections Inc",
    "wof:placetype":"venue"
},
  "geometry": {"coordinates":[-77.580825,35.261704],"type":"Point"}
}