{
  "type": "Feature",
  "properties": {
    "iso:country":"US",
    "sg:address":"5235 US Hwy 17",
    "sg:city":"Vanceboro",
    "sg:classifiers":[
        {
            "category":"Autos & Motor Vehicles",
            "subcategory":"Automobile Sales",
            "type":"Retail Goods"
        }
    ],
    "sg:phone":"+1 252 244 9972",
    "sg:postcode":"28586",
    "sg:province":"NC",
    "sg:tags":[
        "car",
        "dealer"
    ],
    "wof:name":"Manning Auto Sales",
    "wof:placetype":"venue"
},
  "geometry": {"coordinates":[-77.08832700000001,35.248985],"type":"Point"}
}