{
  "type": "Feature",
  "properties": {
    "iso:country":"US",
    "sg:address":"109 Conch Ct",
    "sg:city":"Emerald Isle",
    "sg:classifiers":[
        {
            "category":"Professional",
            "subcategory":"Art Services",
            "type":"Services"
        }
    ],
    "sg:phone":"+1 252 354 7400",
    "sg:postcode":"28594",
    "sg:province":"NC",
    "sg:tags":[
        "photographer"
    ],
    "wof:name":"Pennell Photography",
    "wof:placetype":"venue"
},
  "geometry": {"coordinates":[-77.067735,34.658146],"type":"Point"}
}