{
  "type": "Feature",
  "properties": {
    "iso:country":"US",
    "sg:address":"11 Howland Rd",
    "sg:city":"Asheville",
    "sg:classifiers":[
        {
            "category":"Insurance",
            "subcategory":"Insurance Agent",
            "type":"Services"
        }
    ],
    "sg:phone":"+1 828 258 2007",
    "sg:postcode":"28804",
    "sg:province":"NC",
    "wof:name":"Michaels Group Insurance",
    "wof:placetype":"venue"
},
  "geometry": {"coordinates":[-82.539556,35.613987],"type":"Point"}
}