{
  "type": "Feature",
  "properties": {
    "addr:full":"71 N Beaverdam Rd Candler NC 28715",
    "addr:housenumber":"71",
    "addr:postcode":"28715",
    "addr:street":"N Beaverdam Rd",
    "iso:country":"US",
    "sg:address":"71 N Beaverdam Rd",
    "sg:city":"Candler",
    "sg:classifiers":[
        {
            "category":"Real Estate",
            "subcategory":"Real Estate Operator",
            "type":"Services"
        }
    ],
    "sg:phone":"+1 828 667 1418",
    "sg:postcode":"28715",
    "sg:province":"NC",
    "sg:tags":[
        "property",
        "lessor"
    ],
    "wof:name":"Jack Ferguson",
    "wof:placetype":"venue"
},
  "geometry": {"coordinates":[-82.692061,35.529978],"type":"Point"}
}