{
  "type": "Feature",
  "properties": {
    "iso:country":"US",
    "sg:address":"3110 Arendell St",
    "sg:city":"Morehead City",
    "sg:classifiers":[
        {
            "category":"Professional",
            "type":"Services"
        }
    ],
    "sg:phone":"+1 252 247 9200",
    "sg:postcode":"28557",
    "sg:province":"NC",
    "wof:name":"Easter Seal Ucp",
    "wof:placetype":"venue"
},
  "geometry": {"coordinates":[-76.746612,34.724169],"type":"Point"}
}