{
  "type": "Feature",
  "properties": {
    "addr:full":"2127 Ayrsley Town Blvd Charlotte NC 28273",
    "addr:housenumber":"2127",
    "addr:postcode":"28273",
    "addr:street":"Ayrsley Town Blvd",
    "iso:country":"US",
    "sg:address":"2127 Ayrsley Town Blvd",
    "sg:city":"Charlotte",
    "sg:classifiers":[
        {
            "category":"Restaurant",
            "type":"Food & Drink"
        }
    ],
    "sg:phone":"+1 980 297 7177",
    "sg:postcode":"28273",
    "sg:province":"NC",
    "sg:website":"www.thejazzcafenc.com",
    "wof:name":"Jazz Cafe",
    "wof:placetype":"venue"
},
  "geometry": {"coordinates":[-80.93514999999999,35.138199],"type":"Point"}
}