{
  "type": "Feature",
  "properties": {
    "addr:full":"225 N Main St Troy NC 27371",
    "addr:housenumber":"225",
    "addr:postcode":"27371",
    "addr:street":"N Main St",
    "iso:country":"US",
    "sg:address":"225 N Main St",
    "sg:city":"Troy",
    "sg:classifiers":[
        {
            "category":"Professional",
            "subcategory":"Accounting & Tax Preparation",
            "type":"Services"
        }
    ],
    "sg:phone":"+1 910 576 1655",
    "sg:postcode":"27371",
    "sg:province":"NC",
    "sg:tags":[
        "accountant"
    ],
    "wof:name":"CBC Business Svc",
    "wof:placetype":"venue"
},
  "geometry": {"coordinates":[-79.893739,35.360541],"type":"Point"}
}