{
  "type": "Feature",
  "properties": {
    "iso:country":"US",
    "sg:address":"1410 Desoto Pl",
    "sg:city":"Greensboro",
    "sg:classifiers":[
        {
            "category":"Professional",
            "subcategory":"Lawyer & Legal Services",
            "type":"Services"
        }
    ],
    "sg:phone":"+1 336 379 9287",
    "sg:postcode":"27408",
    "sg:province":"NC",
    "sg:tags":[
        "attorney"
    ],
    "wof:name":"Ann R Harris",
    "wof:placetype":"venue"
},
  "geometry": {"coordinates":[-79.811271,36.081932],"type":"Point"}
}