{
  "type": "Feature",
  "properties": {
    "iso:country":"US",
    "sg:address":"3807 E Shepard St",
    "sg:city":"Fayetteville",
    "sg:classifiers":[
        {
            "category":"Retail",
            "subcategory":"Laundry & Dry Cleaning",
            "type":"Services"
        }
    ],
    "sg:phone":"+1 910 485 7453",
    "sg:postcode":"28304",
    "sg:province":"NC",
    "sg:tags":[
        "cleaners",
        "rug",
        "carpet"
    ],
    "wof:name":"Mlt Professional Carpet Clng",
    "wof:placetype":"venue"
},
  "geometry": {"coordinates":[-78.941244,35.040868],"type":"Point"}
}