{
  "type": "Feature",
  "properties": {
    "addr:full":"301 S College St Charlotte NC 28202",
    "addr:housenumber":"301",
    "addr:postcode":"28202",
    "addr:street":"S College St",
    "iso:country":"US",
    "sg:address":"301 S College St",
    "sg:city":"Charlotte",
    "sg:classifiers":[
        {
            "category":"Insurance",
            "subcategory":"Hazard Insurance",
            "type":"Services"
        }
    ],
    "sg:phone":"+1 704 332 1970",
    "sg:postcode":"28202",
    "sg:province":"NC",
    "sg:tags":[
        "commercial",
        "business"
    ],
    "sg:website":"http://www.statefarm.com",
    "wof:name":"State Farm Insurance",
    "wof:placetype":"venue"
},
  "geometry": {"coordinates":[-80.844238,35.22472],"type":"Point"}
}