{
  "type": "Feature",
  "properties": {
    "iso:country":"US",
    "sg:address":"1023 S Main St",
    "sg:city":"Burlington",
    "sg:classifiers":[
        {
            "category":"Health Services",
            "subcategory":"Doctor",
            "type":"Services"
        }
    ],
    "sg:phone":"+1   ",
    "sg:postcode":"27215",
    "sg:province":"NC",
    "sg:tags":[
        "medical"
    ],
    "wof:name":"James J Walsh MD",
    "wof:placetype":"venue"
},
  "geometry": {"coordinates":[-79.444833,36.088908],"type":"Point"}
}