{
  "type": "Feature",
  "properties": {
    "iso:country":"US",
    "sg:address":"15831 Burlingame Dr",
    "sg:city":"Huntersville",
    "sg:classifiers":[
        {
            "category":"Real Estate",
            "subcategory":"Real Estate Agent",
            "type":"Services"
        }
    ],
    "sg:phone":"+1 704 895 8339",
    "sg:postcode":"28078",
    "sg:province":"NC",
    "sg:tags":[
        "appraiser"
    ],
    "wof:name":"Lutz Appraisal Svc",
    "wof:placetype":"venue"
},
  "geometry": {"coordinates":[-80.89119100000001,35.432337],"type":"Point"}
}