{
  "type": "Feature",
  "properties": {
    "iso:country":"US",
    "sg:address":"418 W 5th Ave",
    "sg:city":"Lexington",
    "sg:classifiers":[
        {
            "category":"Professional",
            "subcategory":"Accounting & Tax Preparation",
            "type":"Services"
        }
    ],
    "sg:phone":"+1 336 248 8281",
    "sg:postcode":"27292",
    "sg:province":"NC",
    "sg:tags":[
        "accountant"
    ],
    "wof:name":"Rives & Associates LLP",
    "wof:placetype":"venue"
},
  "geometry": {"coordinates":[-80.26339400000001,35.823727],"type":"Point"}
}