{
  "type": "Feature",
  "properties": {
    "addr:full":"1911 Fidelity Dr Durham NC 27703",
    "addr:housenumber":"1911",
    "addr:postcode":"27703",
    "addr:street":"Fidelity Dr",
    "iso:country":"US",
    "sg:address":"1911 Fidelity Dr",
    "sg:city":"Durham",
    "sg:classifiers":[
        {
            "category":"Real Estate",
            "subcategory":"Real Estate Agent",
            "type":"Services"
        }
    ],
    "sg:phone":"+1 919 682 2000",
    "sg:postcode":"27703",
    "sg:province":"NC",
    "wof:name":"Cambridge Apartments",
    "wof:placetype":"venue"
},
  "geometry": {"coordinates":[-78.86576700000001,35.993848],"type":"Point"}
}