{
  "type": "Feature",
  "properties": {
    "iso:country":"US",
    "sg:address":"207 Plaza Dr",
    "sg:city":"Greenville",
    "sg:classifiers":[
        {
            "category":"Education",
            "subcategory":"Dance Studio",
            "type":"Public Place"
        }
    ],
    "sg:phone":"+1 252 355 2140",
    "sg:postcode":"27858",
    "sg:province":"NC",
    "sg:tags":[
        "instruction",
        "dancing"
    ],
    "wof:name":"N C Academy Of Dance Arts",
    "wof:placetype":"venue"
},
  "geometry": {"coordinates":[-77.37738299999999,35.584418],"type":"Point"}
}