{
  "type": "Feature",
  "properties": {
    "addr:full":"4453 Scott Rd Morganton NC 28655",
    "addr:housenumber":"4453",
    "addr:postcode":"28655",
    "addr:street":"Scott Rd",
    "iso:country":"US",
    "sg:address":"4453 Scott Rd",
    "sg:city":"Morganton",
    "sg:classifiers":[
        {
            "category":"Manufacturing",
            "subcategory":"Wood Products",
            "type":"Manufacturing & Wholesale Goods"
        }
    ],
    "sg:phone":"+1 828 584 6322",
    "sg:postcode":"28655",
    "sg:province":"NC",
    "sg:tags":[
        "mfg"
    ],
    "wof:name":"Hudgins Wood Products",
    "wof:placetype":"venue"
},
  "geometry": {"coordinates":[-81.79869100000001,35.678887],"type":"Point"}
}