{
  "type": "Feature",
  "properties": {
    "iso:country":"US",
    "sg:address":"471 Keenan Dr SE",
    "sg:city":"Concord",
    "sg:classifiers":[
        {
            "category":"Home & Garden",
            "subcategory":"Furniture",
            "type":"Retail Goods"
        }
    ],
    "sg:phone":"+1 704 782 8190",
    "sg:postcode":"28025",
    "sg:province":"NC",
    "sg:tags":[
        "a",
        "as",
        "operates",
        "decorating",
        "furnishing"
    ],
    "wof:name":"Collins Contract Interiors",
    "wof:placetype":"venue"
},
  "geometry": {"coordinates":[-80.56370699999999,35.415981],"type":"Point"}
}