{
  "type": "Feature",
  "properties": {
    "addr:full":"539 Crooked Run Rd Elizabeth City NC 27909",
    "addr:housenumber":"539",
    "addr:postcode":"27909",
    "addr:street":"Crooked Run Rd",
    "iso:country":"US",
    "sg:address":"539 Crooked Run Rd",
    "sg:city":"Elizabeth City",
    "sg:classifiers":[
        {
            "category":"Building & Trades",
            "subcategory":"Construction",
            "type":"Services"
        }
    ],
    "sg:phone":"+1 252 771 2134",
    "sg:postcode":"27909",
    "sg:province":"NC",
    "sg:tags":[
        "contractor"
    ],
    "wof:name":"Cw Masonry",
    "wof:placetype":"venue"
},
  "geometry": {"coordinates":[-76.39232699999999,36.430428],"type":"Point"}
}