{
  "type": "Feature",
  "properties": {
    "addr:full":"705 Porters Neck Rd Wilmington NC 28411",
    "addr:housenumber":"705",
    "addr:postcode":"28411",
    "addr:street":"Porters Neck Rd",
    "iso:country":"US",
    "sg:address":"705 Porters Neck Rd",
    "sg:city":"Wilmington",
    "sg:classifiers":[
        {
            "category":"Professional",
            "subcategory":"Business Services",
            "type":"Services"
        }
    ],
    "sg:phone":"+1   ",
    "sg:postcode":"28411",
    "sg:province":"NC",
    "wof:name":"Siedentop Enterprises Inc",
    "wof:placetype":"venue"
},
  "geometry": {"coordinates":[-77.77731900000001,34.293489],"type":"Point"}
}