{
  "type": "Feature",
  "properties": {
    "addr:full":"1320 Fillmore Ave Charlotte NC 28203",
    "addr:housenumber":"1320",
    "addr:postcode":"28203",
    "addr:street":"Fillmore Ave",
    "iso:country":"US",
    "sg:address":"1320 Fillmore Ave",
    "sg:city":"Charlotte",
    "sg:classifiers":[
        {
            "category":"Banks & Credit Unions",
            "subcategory":"Investment Brokerage",
            "type":"Services"
        }
    ],
    "sg:phone":"+1 704 335 1640",
    "sg:postcode":"28203",
    "sg:province":"NC",
    "sg:tags":[
        "advisory",
        "financial"
    ],
    "wof:name":"Lincoln Financial Group",
    "wof:placetype":"venue"
},
  "geometry": {"coordinates":[-80.84303199999999,35.202199],"type":"Point"}
}