{
  "type": "Feature",
  "properties": {
    "iso:country":"US",
    "sg:address":"9350 Old US Hwy 70",
    "sg:city":"Cove City",
    "sg:classifiers":[
        {
            "category":"Food & Beverages",
            "subcategory":"Meat & Fish",
            "type":"Retail Goods"
        }
    ],
    "sg:phone":"+1 252 636 8300",
    "sg:postcode":"28523",
    "sg:province":"NC",
    "wof:name":"White's Meat Market",
    "wof:placetype":"venue"
},
  "geometry": {"coordinates":[-77.295008,35.180392],"type":"Point"}
}