{
  "type": "Feature",
  "properties": {
    "iso:country":"US",
    "sg:address":"1216 Fairlane Rd",
    "sg:city":"Cary",
    "sg:classifiers":[
        {
            "category":"Shopping",
            "subcategory":"Music",
            "type":"Retail Goods"
        }
    ],
    "sg:phone":"+1 919 469 0801",
    "sg:postcode":"27511",
    "sg:province":"NC",
    "wof:name":"Hot Rod Hell Records",
    "wof:placetype":"venue"
},
  "geometry": {"coordinates":[-78.75378499999999,35.759904],"type":"Point"}
}