{
  "type": "Feature",
  "properties": {
    "addr:full":"3257 Georgia Rd Franklin NC 28734",
    "addr:housenumber":"3257",
    "addr:postcode":"nc 28734",
    "addr:street":"Georgia Rd",
    "iso:country":"US",
    "sg:address":"3257 Georgia Rd",
    "sg:city":"Franklin",
    "sg:classifiers":[
        {
            "category":"Organizations",
            "subcategory":"Religious Organization",
            "type":"Services"
        }
    ],
    "sg:phone":"+1 828 349 0907",
    "sg:postcode":"28734",
    "sg:province":"NC",
    "sg:tags":[
        "church"
    ],
    "wof:name":"Peace Lutheran Church",
    "wof:placetype":"venue"
},
  "geometry": {"coordinates":[-83.383433,35.030271],"type":"Point"}
}