{
  "type": "Feature",
  "properties": {
    "iso:country":"US",
    "sg:address":"Smokey Park Hwy",
    "sg:city":"Candler",
    "sg:classifiers":[
        {
            "category":"Shopping",
            "subcategory":"Discount & Variety Stores",
            "type":"Retail Goods"
        }
    ],
    "sg:phone":"+1 828 667 4571",
    "sg:postcode":"28715",
    "sg:province":"NC",
    "sg:tags":[
        "outlet"
    ],
    "wof:name":"Davis Clothing Outlet",
    "wof:placetype":"venue"
},
  "geometry": {"coordinates":[-82.70169799999999,35.523701],"type":"Point"}
}