{
  "type": "Feature",
  "properties": {
    "iso:country":"US",
    "sg:address":"107 Fernworth Ct",
    "sg:city":"Clemmons",
    "sg:classifiers":[
        {
            "category":"Manufacturing",
            "subcategory":"Printing",
            "type":"Manufacturing & Wholesale Goods"
        }
    ],
    "sg:phone":"+1 336 766 5544",
    "sg:postcode":"27012",
    "sg:province":"NC",
    "sg:tags":[
        "news",
        "publication"
    ],
    "wof:name":"Huntex Report",
    "wof:placetype":"venue"
},
  "geometry": {"coordinates":[-80.390433,36.009819],"type":"Point"}
}