{
  "type": "Feature",
  "properties": {
    "iso:country":"US",
    "sg:address":"1726 Riverview Rd",
    "sg:city":"Lincolnton",
    "sg:classifiers":[
        {
            "category":"Building & Trades",
            "subcategory":"Construction",
            "type":"Services"
        }
    ],
    "sg:phone":"+1 704 732 1959",
    "sg:postcode":"28092",
    "sg:province":"NC",
    "sg:tags":[
        "roofing",
        "metal",
        "contractor"
    ],
    "sg:website":"www.carolinaroofing.com",
    "wof:name":"Carolina Roofing Inc",
    "wof:placetype":"venue"
},
  "geometry": {"coordinates":[-81.272868,35.432383],"type":"Point"}
}