{
  "type": "Feature",
  "properties": {
    "addr:full":"3565 Dunns Mountain Rd Salisbury NC 28146",
    "addr:housenumber":"3565",
    "addr:postcode":"28146",
    "addr:street":"Dunns Mountain Rd",
    "iso:country":"US",
    "sg:address":"3565 Dunns Mountain Rd",
    "sg:city":"Salisbury",
    "sg:classifiers":[
        {
            "category":"Real Estate",
            "subcategory":"Surveying",
            "type":"Services"
        }
    ],
    "sg:phone":"+1 704 633 0744",
    "sg:postcode":"28146",
    "sg:province":"NC",
    "wof:name":"Riley O Gobble Jr",
    "wof:placetype":"venue"
},
  "geometry": {"coordinates":[-80.410798,35.651588],"type":"Point"}
}