{
  "type": "Feature",
  "properties": {
    "addr:full":"35 Russett Dr Four Oaks NC 27524",
    "addr:housenumber":"35",
    "addr:postcode":"27524",
    "addr:street":"Russett Dr",
    "iso:country":"US",
    "sg:address":"35 Russett Dr",
    "sg:city":"Four Oaks",
    "sg:classifiers":[
        {
            "category":"Professional",
            "subcategory":"Computer Services",
            "type":"Services"
        }
    ],
    "sg:phone":"+1   ",
    "sg:postcode":"27524",
    "sg:province":"NC",
    "sg:tags":[
        "prepackaged",
        "software"
    ],
    "wof:name":"Barbour Software Inc",
    "wof:placetype":"venue"
},
  "geometry": {"coordinates":[-78.459705,35.480354],"type":"Point"}
}