{
  "type": "Feature",
  "properties": {
    "addr:full":"8570 State Hwy 109 Winston Salem NC 27107",
    "addr:housenumber":"8570",
    "addr:postcode":"27107",
    "addr:street":"State Hwy 109",
    "iso:country":"US",
    "sg:address":"8570 State Hwy 109",
    "sg:city":"Winston Salem",
    "sg:classifiers":[
        {
            "category":"Home & Garden",
            "subcategory":"Furniture",
            "type":"Retail Goods"
        }
    ],
    "sg:phone":"+1 336 769 9605",
    "sg:postcode":"27107",
    "sg:province":"NC",
    "sg:tags":[
        "equipment",
        "kitchen",
        "cabinet"
    ],
    "sg:website":"www.hdcabinets.com",
    "wof:name":"H & D Cabinet Co",
    "wof:placetype":"venue"
},
  "geometry": {"coordinates":[-80.136241,36.008223],"type":"Point"}
}