{
  "type": "Feature",
  "properties": {
    "addr:full":"4421 Sharon Rd Charlotte NC 28211",
    "addr:housenumber":"4421",
    "addr:postcode":"28211",
    "addr:street":"Sharon Rd",
    "iso:country":"US",
    "sg:address":"4421 Sharon Rd",
    "sg:city":"Charlotte",
    "sg:classifiers":[
        {
            "category":"Professional",
            "subcategory":"Lawyer & Legal Services",
            "type":"Services"
        }
    ],
    "sg:phone":"+1 704 362 1056",
    "sg:postcode":"28211",
    "sg:province":"NC",
    "sg:tags":[
        "attorney"
    ],
    "wof:name":"Buckley Mc Mullen & Buie PA",
    "wof:placetype":"venue"
},
  "geometry": {"coordinates":[-80.82461000000001,35.154777],"type":"Point"}
}