{
  "type": "Feature",
  "properties": {
    "iso:country":"US",
    "sg:address":"126 Becker Dr",
    "sg:city":"Roanoke Rapids",
    "sg:classifiers":[
        {
            "category":"Shopping",
            "subcategory":"Music",
            "type":"Retail Goods"
        }
    ],
    "sg:phone":"+1 252 535 1227",
    "sg:postcode":"27870",
    "sg:province":"NC",
    "sg:tags":[
        "instrument",
        "musical"
    ],
    "wof:name":"Camelot Music 1151",
    "wof:placetype":"venue"
},
  "geometry": {"coordinates":[-77.640906,36.442738],"type":"Point"}
}