{
  "type": "Feature",
  "properties": {
    "addr:full":"4737 US Hwy 441 S Sylva NC 28779",
    "addr:housenumber":"4737",
    "addr:postcode":"28779",
    "addr:street":"Us Hwy 441 S",
    "iso:country":"US",
    "sg:address":"4737 US Hwy 441 S",
    "sg:city":"Sylva",
    "sg:classifiers":[
        {
            "category":"Autos & Motor Vehicles",
            "subcategory":"Fuel & Gas Station",
            "type":"Retail Goods"
        }
    ],
    "sg:phone":"+1 828 631 9995",
    "sg:postcode":"28779",
    "sg:province":"NC",
    "sg:tags":[
        "grocery",
        "station",
        "gasoline"
    ],
    "wof:name":"Rons Savannah Quick Stop",
    "wof:placetype":"venue"
},
  "geometry": {"coordinates":[-83.26208,35.325741],"type":"Point"}
}