{
  "type": "Feature",
  "properties": {
    "iso:country":"US",
    "sg:address":"1101 S George St",
    "sg:city":"Goldsboro",
    "sg:classifiers":[
        {
            "category":"Autos & Motor Vehicles",
            "subcategory":"Automobile Sales",
            "type":"Retail Goods"
        }
    ],
    "sg:phone":"+1 919 731 2168",
    "sg:postcode":"27530",
    "sg:province":"NC",
    "sg:tags":[
        "car",
        "dealer"
    ],
    "wof:name":"Harold's Auto Sales",
    "wof:placetype":"venue"
},
  "geometry": {"coordinates":[-78.00820899999999,35.366492],"type":"Point"}
}