{
  "type": "Feature",
  "properties": {
    "addr:full":"123 W Main St Forest City NC 28043",
    "addr:housenumber":"123",
    "addr:postcode":"28043",
    "addr:street":"W Main St",
    "iso:country":"US",
    "sg:address":"123 W Main St",
    "sg:city":"Forest City",
    "sg:classifiers":[
        {
            "category":"Restaurant",
            "type":"Food & Drink"
        }
    ],
    "sg:phone":"+1 828 245 7986",
    "sg:postcode":"28043",
    "sg:province":"NC",
    "sg:tags":[
        "eating"
    ],
    "wof:name":"Best Friends Deli",
    "wof:placetype":"venue"
},
  "geometry": {"coordinates":[-81.86513100000001,35.333694],"type":"Point"}
}