{
  "type": "Feature",
  "properties": {
    "iso:country":"US",
    "sg:address":"7605 Prospector Pl",
    "sg:city":"Raleigh",
    "sg:classifiers":[
        {
            "category":"Manufacturing",
            "subcategory":"Metals",
            "type":"Manufacturing & Wholesale Goods"
        }
    ],
    "sg:phone":"+1 919 845 0460",
    "sg:postcode":"27615",
    "sg:province":"NC",
    "sg:tags":[
        "product",
        "machinery",
        "fabricated",
        "transport",
        "except"
    ],
    "wof:name":"Sheridan Designs Inc",
    "wof:placetype":"venue"
},
  "geometry": {"coordinates":[-78.659526,35.881342],"type":"Point"}
}