{
  "type": "Feature",
  "properties": {
    "iso:country":"US",
    "sg:address":"232 N Greensboro St",
    "sg:city":"Liberty",
    "sg:classifiers":[
        {
            "category":"Autos & Motor Vehicles",
            "subcategory":"Auto Supplies",
            "type":"Retail Goods"
        }
    ],
    "sg:phone":"+1 336 622 2248",
    "sg:postcode":"27298",
    "sg:province":"NC",
    "sg:tags":[
        "tire"
    ],
    "wof:name":"Liberty Tire & Auto",
    "wof:placetype":"venue"
},
  "geometry": {"coordinates":[-79.572615,35.856734],"type":"Point"}
}