{
  "type": "Feature",
  "properties": {
    "iso:country":"US",
    "sg:address":"229 Wild Oak Dr",
    "sg:city":"Swansboro",
    "sg:classifiers":[
        {
            "category":"Professional",
            "subcategory":"Management & Consulting",
            "type":"Services"
        },
        {
            "category":"Wholesale",
            "subcategory":"Electrical",
            "type":"Manufacturing & Wholesale Goods"
        }
    ],
    "sg:phone":"+1 910 325 0700",
    "sg:postcode":"28584",
    "sg:province":"NC",
    "sg:tags":[
        "intercommunication",
        "business"
    ],
    "wof:name":"Center Point Consulting Inc",
    "wof:placetype":"venue"
},
  "geometry": {"coordinates":[-77.157067,34.681446],"type":"Point"}
}