{
  "type": "Feature",
  "properties": {
    "addr:full":"743 Pineborough Rd Charlotte NC 28212",
    "addr:housenumber":"743",
    "addr:postcode":"28212",
    "addr:street":"Pineborough Rd",
    "iso:country":"US",
    "sg:address":"743 Pineborough Rd",
    "sg:city":"Charlotte",
    "sg:classifiers":[
        {
            "category":"Professional",
            "type":"Services"
        }
    ],
    "sg:phone":"+1 704 569 7945",
    "sg:postcode":"28212",
    "sg:province":"NC",
    "wof:name":"Discover Spanish LLC",
    "wof:placetype":"venue"
},
  "geometry": {"coordinates":[-80.749993,35.171991],"type":"Point"}
}