{
  "type": "Feature",
  "properties": {
    "addr:full":"1012 Elm St Sanford NC 27330",
    "addr:housenumber":"1012",
    "addr:postcode":"27330",
    "addr:street":"Elm St",
    "iso:country":"US",
    "sg:address":"1012 Elm St",
    "sg:city":"Sanford",
    "sg:classifiers":[
        {
            "category":"Real Estate",
            "subcategory":"Real Estate Agent",
            "type":"Services"
        }
    ],
    "sg:phone":"+1 919 777 2590",
    "sg:postcode":"27330",
    "sg:province":"NC",
    "wof:name":"Ideal Realty",
    "wof:placetype":"venue"
},
  "geometry": {"coordinates":[-79.169127,35.469717],"type":"Point"}
}