{
  "type": "Feature",
  "properties": {
    "addr:full":"7400 Cormwell Ln Charlotte NC 28217",
    "addr:housenumber":"7400",
    "addr:postcode":"28217",
    "addr:street":"Cormwell Ln",
    "iso:country":"US",
    "sg:address":"7400 Cormwell Ln",
    "sg:city":"Charlotte",
    "sg:classifiers":[
        {
            "category":"Building & Trades",
            "subcategory":"Cleaning & Sanitation",
            "type":"Services"
        }
    ],
    "sg:phone":"+1   ",
    "sg:postcode":"28217",
    "sg:province":"NC",
    "sg:tags":[
        "maintenance"
    ],
    "wof:name":"Majestic Cleaning Services",
    "wof:placetype":"venue"
},
  "geometry": {"coordinates":[-80.921983,35.148235],"type":"Point"}
}