{
  "type": "Feature",
  "properties": {
    "addr:full":"1103 Central Dr Kannapolis NC 28083",
    "addr:housenumber":"1103",
    "addr:postcode":"28083",
    "addr:street":"Central Dr",
    "iso:country":"US",
    "sg:address":"1103 Central Dr",
    "sg:city":"Kannapolis",
    "sg:classifiers":[
        {
            "category":"Professional",
            "subcategory":"Computer Services",
            "type":"Services"
        }
    ],
    "sg:phone":"+1 704 224 1002",
    "sg:postcode":"28083",
    "sg:province":"NC",
    "sg:tags":[
        "website",
        "design"
    ],
    "wof:name":"Deko Technical & Graphical Svc",
    "wof:placetype":"venue"
},
  "geometry": {"coordinates":[-80.604832,35.502818],"type":"Point"}
}