{
  "type": "Feature",
  "properties": {
    "iso:country":"US",
    "sg:address":"101 Stockton St",
    "sg:city":"Lattimore",
    "sg:classifiers":[
        {
            "category":"Education",
            "subcategory":"College",
            "type":"Public Place"
        }
    ],
    "sg:phone":"+1 704 434 0303",
    "sg:postcode":"28089",
    "sg:province":"NC",
    "sg:tags":[
        "academic",
        "school"
    ],
    "wof:name":"Ambassador Baptist College",
    "wof:placetype":"venue"
},
  "geometry": {"coordinates":[-81.65797999999999,35.321419],"type":"Point"}
}