{
  "type": "Feature",
  "properties": {
    "addr:full":"5522 Uwharrie Rd Archdale NC 27263",
    "addr:housenumber":"5522",
    "addr:postcode":"27263",
    "addr:street":"Uwharrie Rd",
    "iso:country":"US",
    "sg:address":"5522 Uwharrie Rd",
    "sg:city":"Archdale",
    "sg:classifiers":[
        {
            "category":"Manufacturing",
            "subcategory":"Furniture",
            "type":"Manufacturing & Wholesale Goods"
        }
    ],
    "sg:phone":"+1 336 861 4180",
    "sg:postcode":"27263",
    "sg:province":"NC",
    "sg:tags":[
        "bedding",
        "supply"
    ],
    "wof:name":"High Point Quilting",
    "wof:placetype":"venue"
},
  "geometry": {"coordinates":[-80.011166,35.901585],"type":"Point"}
}