{
  "type": "Feature",
  "properties": {
    "iso:country":"US",
    "sg:address":"1217 Trollingwood Hawfields Rd",
    "sg:city":"Mebane",
    "sg:classifiers":[
        {
            "category":"Food & Beverages",
            "subcategory":"Groceries & Convenience Stores",
            "type":"Retail Goods"
        }
    ],
    "sg:phone":"+1 919 563 3450",
    "sg:postcode":"27302",
    "sg:province":"NC",
    "wof:name":"Circle K",
    "wof:placetype":"venue"
},
  "geometry": {"coordinates":[-79.313025,36.068507],"type":"Point"}
}