{
  "type": "Feature",
  "properties": {
    "addr:full":"708 W Main St Jamestown NC 27282",
    "addr:housenumber":"708",
    "addr:postcode":"27282",
    "addr:street":"W Main St",
    "iso:country":"US",
    "sg:address":"708 W Main St",
    "sg:city":"Jamestown",
    "sg:classifiers":[
        {
            "category":"Real Estate",
            "subcategory":"Real Estate Operator",
            "type":"Services"
        }
    ],
    "sg:phone":"+1 336 883 9887",
    "sg:postcode":"27282",
    "sg:province":"NC",
    "sg:tags":[
        "apartment"
    ],
    "wof:name":"Parkview Terrace Apartments",
    "wof:placetype":"venue"
},
  "geometry": {"coordinates":[-79.95140600000001,35.99314],"type":"Point"}
}