{
  "type": "Feature",
  "properties": {
    "iso:country":"US",
    "sg:address":"2235 Westover Dr",
    "sg:city":"Winston Salem",
    "sg:classifiers":[
        {
            "category":"Real Estate",
            "subcategory":"Real Estate Operator",
            "type":"Services"
        }
    ],
    "sg:phone":"+1 336 723 7915",
    "sg:postcode":"27103",
    "sg:province":"NC",
    "sg:tags":[
        "building",
        "nonresidential"
    ],
    "wof:name":"Stave Properties LLC",
    "wof:placetype":"venue"
},
  "geometry": {"coordinates":[-80.275338,36.083747],"type":"Point"}
}