{
  "type": "Feature",
  "properties": {
    "addr:full":"2235 Laurel Valley Rd Mars Hill NC 28754",
    "addr:housenumber":"2235",
    "addr:postcode":"28754",
    "addr:street":"Laurel Valley Rd Mars Hill",
    "iso:country":"US",
    "sg:address":"2235 Laurel Valley Rd",
    "sg:city":"Mars Hill",
    "sg:classifiers":[
        {
            "category":"Building & Trades",
            "subcategory":"Construction",
            "type":"Services"
        }
    ],
    "sg:phone":"+1 828 689 5250",
    "sg:postcode":"28754",
    "sg:province":"NC",
    "sg:tags":[
        "special",
        "contractor"
    ],
    "wof:name":"Arrington Construction",
    "wof:placetype":"venue"
},
  "geometry": {"coordinates":[-82.51169899999999,35.91124],"type":"Point"}
}