{
  "type": "Feature",
  "properties": {
    "iso:country":"US",
    "sg:address":"416 Russell Twiford Rd",
    "sg:city":"Manteo",
    "sg:classifiers":[
        {
            "category":"Autos & Motor Vehicles",
            "subcategory":"Boat Sales",
            "type":"Retail Goods"
        }
    ],
    "sg:phone":"+1 252 473 5007",
    "sg:postcode":"27954",
    "sg:province":"NC",
    "sg:tags":[
        "marine",
        "supply"
    ],
    "wof:name":"Mike Keller Ltd",
    "wof:placetype":"venue"
},
  "geometry": {"coordinates":[-75.65966299999999,35.891861],"type":"Point"}
}