{
  "type": "Feature",
  "properties": {
    "addr:full":"1115 Sweet Spot Cir Morrisville NC 27560",
    "addr:housenumber":"1115",
    "addr:postcode":"27560",
    "addr:street":"Spot Cir",
    "iso:country":"US",
    "sg:address":"1115 Sweet Spot Cir",
    "sg:city":"Morrisville",
    "sg:classifiers":[
        {
            "category":"Professional",
            "type":"Services"
        }
    ],
    "sg:phone":"+1 919 462 9996",
    "sg:postcode":"27560",
    "sg:province":"NC",
    "sg:tags":[
        "establishment"
    ],
    "wof:name":"Legends At Preston",
    "wof:placetype":"venue"
},
  "geometry": {"coordinates":[-78.83062099999999,35.813551],"type":"Point"}
}