{
  "type": "Feature",
  "properties": {
    "iso:country":"US",
    "sg:address":"404 Railroad Ave",
    "sg:city":"Harrisburg",
    "sg:classifiers":[
        {
            "category":"Retail",
            "subcategory":"Auto Repair",
            "type":"Services"
        }
    ],
    "sg:phone":"+1 704 455 2056",
    "sg:postcode":"28075",
    "sg:province":"NC",
    "sg:tags":[
        "body",
        "automobile",
        "painting"
    ],
    "wof:name":"Ray Helms Body Shop Inc",
    "wof:placetype":"venue"
},
  "geometry": {"coordinates":[-80.649832,35.316727],"type":"Point"}
}