{
  "type": "Feature",
  "properties": {
    "addr:full":"765 Lakeview Rd Salisbury NC 28147",
    "addr:housenumber":"765",
    "addr:postcode":"28147",
    "addr:street":"Lakeview Rd",
    "iso:country":"US",
    "sg:address":"765 Lakeview Rd",
    "sg:city":"Salisbury",
    "sg:classifiers":[
        {
            "category":"Retail",
            "subcategory":"Auto Repair",
            "type":"Services"
        }
    ],
    "sg:phone":"+1 704 637 1694",
    "sg:postcode":"28147",
    "sg:province":"NC",
    "sg:tags":[
        "repairing",
        "automobile",
        "automotive"
    ],
    "wof:name":"Leon's Garage",
    "wof:placetype":"venue"
},
  "geometry": {"coordinates":[-80.57284300000001,35.700796],"type":"Point"}
}