{
  "type": "Feature",
  "properties": {
    "addr:full":"3750 Statesville Blvd Salisbury NC 28147",
    "addr:housenumber":"3750",
    "addr:postcode":"28147",
    "addr:street":"Statesville Blvd",
    "iso:country":"US",
    "sg:address":"3750 Statesville Blvd",
    "sg:city":"Salisbury",
    "sg:classifiers":[
        {
            "category":"Restaurant",
            "type":"Food & Drink"
        }
    ],
    "sg:phone":"+1 704 633 5672",
    "sg:postcode":"28147",
    "sg:province":"NC",
    "wof:name":"Deb N Joe's Pub Grill",
    "wof:placetype":"venue"
},
  "geometry": {"coordinates":[-80.55174100000001,35.705118],"type":"Point"}
}