{
  "type": "Feature",
  "properties": {
    "addr:full":"3917 Mc Clain St Holly Springs NC 27540",
    "addr:housenumber":"3917",
    "addr:postcode":"27540",
    "addr:street":"Mc Clain St",
    "iso:country":"US",
    "sg:address":"3917 Mc Clain St",
    "sg:city":"Holly Springs",
    "sg:classifiers":[
        {
            "category":"Manufacturing",
            "subcategory":"Apparel",
            "type":"Manufacturing & Wholesale Goods"
        }
    ],
    "sg:phone":"+1 919 362 0918",
    "sg:postcode":"27540",
    "sg:province":"NC",
    "sg:tags":[
        "sewing",
        "contractor"
    ],
    "wof:name":"Annie's Fashion & Fabric",
    "wof:placetype":"venue"
},
  "geometry": {"coordinates":[-78.837667,35.673716],"type":"Point"}
}