{
  "type": "Feature",
  "properties": {
    "addr:full":"801 E Garrison Blvd Gastonia NC 28054",
    "addr:housenumber":"801",
    "addr:postcode":"28054",
    "addr:street":"E Garrison Blvd",
    "iso:country":"US",
    "sg:address":"801 E Garrison Blvd",
    "sg:city":"Gastonia",
    "sg:classifiers":[
        {
            "category":"Autos & Motor Vehicles",
            "subcategory":"Auto Supplies",
            "type":"Retail Goods"
        },
        {
            "category":"Retail",
            "subcategory":"Auto Repair",
            "type":"Services"
        }
    ],
    "sg:phone":"+1 704 854 8307",
    "sg:postcode":"28054",
    "sg:province":"NC",
    "sg:tags":[
        "oil",
        "automotive",
        "automobile",
        "lube",
        "equipment-service",
        "air conditioning",
        "tune"
    ],
    "sg:website":"http://www.jiffylube.com",
    "wof:name":"Jiffy Lube",
    "wof:placetype":"venue"
},
  "geometry": {"coordinates":[-81.17009,35.25325],"type":"Point"}
}