{
  "type": "Feature",
  "properties": {
    "addr:full":"10905 Six Forks Rd Raleigh NC 27614",
    "addr:housenumber":"10905",
    "addr:postcode":"27614",
    "addr:street":"Six Forks Rd",
    "iso:country":"US",
    "sg:address":"10905 Six Forks Rd",
    "sg:city":"Raleigh",
    "sg:classifiers":[
        {
            "category":"Retail",
            "subcategory":"Veterinary Services",
            "type":"Services"
        }
    ],
    "sg:phone":"+1 919 847 2255",
    "sg:postcode":"27614",
    "sg:province":"NC",
    "sg:tags":[
        "veterinarian",
        "specialty"
    ],
    "wof:name":"Veterinary Home Service",
    "wof:placetype":"venue"
},
  "geometry": {"coordinates":[-78.647428,35.931184],"type":"Point"}
}