{
  "type": "Feature",
  "properties": {
    "addr:full":"236 Orville St Henderson NC 27536",
    "addr:housenumber":"236",
    "addr:postcode":"27536",
    "addr:street":"Orville St",
    "iso:country":"US",
    "sg:address":"236 Orville St",
    "sg:city":"Henderson",
    "sg:classifiers":[
        {
            "category":"Real Estate",
            "subcategory":"Real Estate Operator",
            "type":"Services"
        }
    ],
    "sg:phone":"+1 252 492 9425",
    "sg:postcode":"27536",
    "sg:province":"NC",
    "sg:tags":[
        "mobile",
        "home",
        "community"
    ],
    "wof:name":"Brookhaven Village Mobile Home",
    "wof:placetype":"venue"
},
  "geometry": {"coordinates":[-78.382572,36.317028],"type":"Point"}
}