{
  "type": "Feature",
  "properties": {
    "iso:country":"US",
    "sg:address":"409 W Ehringhaus St",
    "sg:city":"Elizabeth City",
    "sg:classifiers":[
        {
            "category":"Insurance",
            "subcategory":"Insurance Agent",
            "type":"Services"
        }
    ],
    "sg:phone":"+1 252 338 1776",
    "sg:postcode":"27909",
    "sg:province":"NC",
    "wof:name":"Central Insurance",
    "wof:placetype":"venue"
},
  "geometry": {"coordinates":[-76.22703300000001,36.296107],"type":"Point"}
}