{
  "type": "Feature",
  "properties": {
    "iso:country":"US",
    "sg:address":"760 E Oakwood Ave",
    "sg:city":"Albemarle",
    "sg:classifiers":[
        {
            "category":"Wholesale",
            "subcategory":"Groceries",
            "type":"Manufacturing & Wholesale Goods"
        }
    ],
    "sg:phone":"+1 704 982 6839",
    "sg:postcode":"28001",
    "sg:province":"NC",
    "sg:tags":[
        "general"
    ],
    "wof:name":"Piedmont Food Brokers Inc",
    "wof:placetype":"venue"
},
  "geometry": {"coordinates":[-80.18709200000001,35.356052],"type":"Point"}
}