{
  "type": "Feature",
  "properties": {
    "addr:full":"1100 Marlborough Rd Fayetteville NC 28304",
    "addr:housenumber":"1100",
    "addr:postcode":"28304",
    "addr:street":"Marlborough Rd",
    "iso:country":"US",
    "sg:address":"1100 Marlborough Rd",
    "sg:city":"Fayetteville",
    "sg:classifiers":[
        {
            "category":"Real Estate",
            "subcategory":"Real Estate Operator",
            "type":"Services"
        }
    ],
    "sg:phone":"+1 910 323 3011",
    "sg:postcode":"28304",
    "sg:province":"NC",
    "sg:tags":[
        "building",
        "apartment"
    ],
    "wof:name":"Tree Top Apartment",
    "wof:placetype":"venue"
},
  "geometry": {"coordinates":[-78.928772,35.043555],"type":"Point"}
}