{
  "type": "Feature",
  "properties": {
    "iso:country":"US",
    "sg:address":"1220 Eastchester Dr",
    "sg:city":"High Point",
    "sg:classifiers":[
        {
            "category":"Insurance",
            "subcategory":"Insurance Agent",
            "type":"Services"
        }
    ],
    "sg:phone":"+1 336 883 4460",
    "sg:postcode":"27265",
    "sg:province":"NC",
    "wof:name":"Woodmen Of The World Insurance",
    "wof:placetype":"venue"
},
  "geometry": {"coordinates":[-79.997953,35.992994],"type":"Point"}
}