{
  "type": "Feature",
  "properties": {
    "iso:country":"US",
    "sg:address":"610 W Franklin St",
    "sg:city":"Chapel Hill",
    "sg:classifiers":[
        {
            "category":"Restaurant",
            "type":"Food & Drink"
        }
    ],
    "sg:phone":"+1 919 929 7643",
    "sg:postcode":"27516",
    "sg:province":"NC",
    "sg:tags":[
        "breakfast",
        "southern",
        "brunch"
    ],
    "sg:website":"www.crookscorner.com",
    "wof:name":"Crook's Corner",
    "wof:placetype":"venue"
},
  "geometry": {"coordinates":[-79.06500200000001,35.909801],"type":"Point"}
}