{
  "type": "Feature",
  "properties": {
    "addr:full":"4126 Wilkinson Blvd Charlotte NC 28208",
    "addr:housenumber":"4126",
    "addr:postcode":"28208",
    "addr:street":"Wilkinson Blvd",
    "iso:country":"US",
    "sg:address":"4126 Wilkinson Blvd",
    "sg:city":"Charlotte",
    "sg:classifiers":[
        {
            "category":"Retail",
            "subcategory":"Repair Shop",
            "type":"Services"
        },
        {
            "category":"Building & Trades",
            "subcategory":"Plumbing",
            "type":"Services"
        }
    ],
    "sg:phone":"+1 704 394 8234",
    "sg:postcode":"28208",
    "sg:province":"NC",
    "sg:tags":[
        "commercial",
        "refrigeration",
        "heating",
        "contractor"
    ],
    "sg:website":"www.freemanrefrigeration.com",
    "wof:name":"Freeman Citywide Refrigeration",
    "wof:placetype":"venue"
},
  "geometry": {"coordinates":[-80.90911199999999,35.225885],"type":"Point"}
}