{
  "type": "Feature",
  "properties": {
    "iso:country":"US",
    "sg:address":"500 Courthouse Dr",
    "sg:city":"Wilkesboro",
    "sg:classifiers":[
        {
            "category":"Government",
            "subcategory":"Office",
            "type":"Public Place"
        }
    ],
    "sg:phone":"+1 336 667 3201",
    "sg:postcode":"28697",
    "sg:province":"NC",
    "wof:name":"Magistrate Office",
    "wof:placetype":"venue"
},
  "geometry": {"coordinates":[-81.150588,36.142443],"type":"Point"}
}