{
  "type": "Feature",
  "properties": {
    "addr:full":"621 E Marion St Shelby NC 28150",
    "addr:housenumber":"621",
    "addr:postcode":"28150",
    "addr:street":"E Marion St",
    "iso:country":"US",
    "sg:address":"621 E Marion St",
    "sg:city":"Shelby",
    "sg:classifiers":[
        {
            "category":"Professional",
            "subcategory":"Business Services",
            "type":"Services"
        }
    ],
    "sg:phone":"+1   ",
    "sg:postcode":"28150",
    "sg:province":"NC",
    "wof:name":"Craft Store",
    "wof:placetype":"venue"
},
  "geometry": {"coordinates":[-81.527766,35.294432],"type":"Point"}
}