{
  "type": "Feature",
  "properties": {
    "addr:full":"124 McDonald Ln Whiteville NC 28472",
    "addr:housenumber":"124",
    "addr:postcode":"28472",
    "addr:street":"Mcdonald Ln",
    "iso:country":"US",
    "sg:address":"124 McDonald Ln",
    "sg:city":"Whiteville",
    "sg:classifiers":[
        {
            "category":"Building & Trades",
            "subcategory":"Construction",
            "type":"Services"
        }
    ],
    "sg:phone":"+1 910 642 4514",
    "sg:postcode":"28472",
    "sg:province":"NC",
    "sg:tags":[
        "concrete",
        "contractor"
    ],
    "wof:name":"Edwards Concrete Contractors",
    "wof:placetype":"venue"
},
  "geometry": {"coordinates":[-78.75432000000001,34.388002],"type":"Point"}
}