{
  "type": "Feature",
  "properties": {
    "iso:country":"US",
    "sg:address":"2626 Bexley Ave",
    "sg:city":"Durham",
    "sg:classifiers":[
        {
            "category":"Professional",
            "type":"Services"
        }
    ],
    "sg:phone":"+1 919 489 8626",
    "sg:postcode":"27707",
    "sg:province":"NC",
    "wof:name":"Christopher P Meyer",
    "wof:placetype":"venue"
},
  "geometry": {"coordinates":[-78.92786099999999,35.966832],"type":"Point"}
}