{
  "type": "Feature",
  "properties": {
    "addr:full":"356 Biltmore Ave Asheville NC 28801",
    "addr:housenumber":"356",
    "addr:postcode":"28801",
    "addr:street":"Biltmore Ave",
    "iso:country":"US",
    "sg:address":"356 Biltmore Ave",
    "sg:city":"Asheville",
    "sg:classifiers":[
        {
            "category":"Health Services",
            "subcategory":"Hospital",
            "type":"Services"
        }
    ],
    "sg:phone":"+1 828 258 3500",
    "sg:postcode":"28801",
    "sg:province":"NC",
    "sg:tags":[
        "mental"
    ],
    "sg:website":"www.blueridge.org",
    "wof:name":"Blue Ridge Ctr-Mental",
    "wof:placetype":"venue"
},
  "geometry": {"coordinates":[-82.551058,35.582378],"type":"Point"}
}