{
  "type": "Feature",
  "properties": {
    "addr:full":"2540 Needmore Rd Woodleaf NC 27054",
    "addr:housenumber":"2540",
    "addr:postcode":"27054",
    "addr:street":"Needmore Rd",
    "iso:country":"US",
    "sg:address":"2540 Needmore Rd",
    "sg:city":"Woodleaf",
    "sg:classifiers":[
        {
            "category":"Manufacturing",
            "subcategory":"Furniture",
            "type":"Manufacturing & Wholesale Goods"
        }
    ],
    "sg:phone":"+1 704 278 0395",
    "sg:postcode":"27054",
    "sg:province":"NC",
    "wof:name":"Custom Table LTD",
    "wof:placetype":"venue"
},
  "geometry": {"coordinates":[-80.61364500000001,35.811593],"type":"Point"}
}