{
  "type": "Feature",
  "properties": {
    "addr:full":"3195 Range Rd Stem NC 27581",
    "addr:housenumber":"3195",
    "addr:postcode":"27581",
    "addr:street":"Range Rd",
    "iso:country":"US",
    "sg:address":"3195 Range Rd",
    "sg:city":"Stem",
    "sg:classifiers":[
        {
            "category":"Shopping",
            "subcategory":"Florist",
            "type":"Retail Goods"
        }
    ],
    "sg:phone":"+1 919 528 4884",
    "sg:postcode":"27581",
    "sg:province":"NC",
    "wof:name":"Butner Florist & Garden Center",
    "wof:placetype":"venue"
},
  "geometry": {"coordinates":[-78.74100900000001,36.193106],"type":"Point"}
}