{
  "type": "Feature",
  "properties": {
    "addr:full":"240 Alvin Hough Rd Midland NC 28107",
    "addr:housenumber":"240",
    "addr:postcode":"28107",
    "addr:street":"Alvin Hough Rd",
    "iso:country":"US",
    "sg:address":"240 Alvin Hough Rd",
    "sg:city":"Midland",
    "sg:classifiers":[
        {
            "category":"Building & Trades",
            "subcategory":"Plumbing",
            "type":"Services"
        }
    ],
    "sg:phone":"+1 704 888 6358",
    "sg:postcode":"28107",
    "sg:province":"NC",
    "sg:tags":[
        "plumbing",
        "contractor"
    ],
    "wof:name":"Adams Plumbing",
    "wof:placetype":"venue"
},
  "geometry": {"coordinates":[-80.574124,35.225165],"type":"Point"}
}