{
  "type": "Feature",
  "properties": {
    "iso:country":"US",
    "sg:address":"139 Creekside Dr",
    "sg:city":"Four Oaks",
    "sg:classifiers":[
        {
            "category":"Shopping",
            "subcategory":"Florist",
            "type":"Retail Goods"
        }
    ],
    "sg:phone":"+1 919 963 2423",
    "sg:postcode":"27524",
    "sg:province":"NC",
    "wof:name":"Flowers Dclm Inc",
    "wof:placetype":"venue"
},
  "geometry": {"coordinates":[-78.429317,35.440089],"type":"Point"}
}