{
  "type": "Feature",
  "properties": {
    "addr:full":"47192 Middle Ridge Rd Buxton NC 27920",
    "addr:housenumber":"47192",
    "addr:postcode":"27920",
    "addr:street":"Middle Ridge Rd",
    "iso:country":"US",
    "sg:address":"47192 Middle Ridge Rd",
    "sg:city":"Buxton",
    "sg:classifiers":[
        {
            "category":"Airline",
            "type":"Transportation"
        }
    ],
    "sg:phone":"+1 252 995 7933",
    "sg:postcode":"27920",
    "sg:province":"NC",
    "sg:tags":[
        "company"
    ],
    "wof:name":"Delta Air Lines Inc",
    "wof:placetype":"venue"
},
  "geometry": {"coordinates":[-75.54736699999999,35.259589],"type":"Point"}
}