{
  "type": "Feature",
  "properties": {
    "iso:country":"US",
    "sg:address":"6030 US Hwy 74",
    "sg:city":"Indian Trail",
    "sg:classifiers":[
        {
            "category":"Health Services",
            "subcategory":"Doctor",
            "type":"Services"
        }
    ],
    "sg:phone":"+1 704 246 2777",
    "sg:postcode":"28079",
    "sg:province":"NC",
    "sg:tags":[
        "physician",
        "surgeon"
    ],
    "sg:website":"www.carolinashealthcare.org",
    "wof:name":"Carolinas Healthcare System",
    "wof:placetype":"venue"
},
  "geometry": {"coordinates":[-80.64224299999999,35.067125],"type":"Point"}
}