{
  "type": "Feature",
  "properties": {
    "iso:country":"US",
    "sg:address":"3428 Genie Rd",
    "sg:city":"East Bend",
    "sg:classifiers":[
        {
            "category":"Retail",
            "subcategory":"Repair Shop",
            "type":"Services"
        }
    ],
    "sg:phone":"+1   ",
    "sg:postcode":"27018",
    "sg:province":"NC",
    "wof:name":"Carter Cleaning",
    "wof:placetype":"venue"
},
  "geometry": {"coordinates":[-80.580253,36.217778],"type":"Point"}
}