{
  "type": "Feature",
  "properties": {
    "iso:country":"US",
    "sg:address":"715 Grandview Dr NE",
    "sg:city":"Concord",
    "sg:classifiers":[
        {
            "category":"Shopping",
            "subcategory":"Department Store",
            "type":"Retail Goods"
        }
    ],
    "sg:phone":"+1 704 795 7283",
    "sg:postcode":"28025",
    "sg:province":"NC",
    "sg:tags":[
        "shop"
    ],
    "wof:name":"Carolina Coupons",
    "wof:placetype":"venue"
},
  "geometry": {"coordinates":[-80.59213699999999,35.435057],"type":"Point"}
}