{
  "type": "Feature",
  "properties": {
    "iso:country":"US",
    "sg:address":"808 E Franklin St",
    "sg:city":"Chapel Hill",
    "sg:classifiers":[
        {
            "category":"Professional",
            "type":"Services"
        }
    ],
    "sg:phone":"+1 919 929 1454",
    "sg:postcode":"27514",
    "sg:province":"NC",
    "wof:name":"Tarpangroup LLC",
    "wof:placetype":"venue"
},
  "geometry": {"coordinates":[-79.043702,35.916844],"type":"Point"}
}