{
  "type": "Feature",
  "properties": {
    "iso:country":"US",
    "sg:address":"1135 Shinn Farm Rd",
    "sg:city":"Mooresville",
    "sg:classifiers":[
        {
            "category":"Manufacturing",
            "subcategory":"Tools & Machinery",
            "type":"Manufacturing & Wholesale Goods"
        },
        {
            "category":"Autos & Motor Vehicles",
            "subcategory":"Auto Supplies",
            "type":"Retail Goods"
        }
    ],
    "sg:phone":"+1 704 660 0707",
    "sg:postcode":"28115",
    "sg:province":"NC",
    "sg:tags":[
        "automobile",
        "part",
        "accessory"
    ],
    "wof:name":"Motorsport Tools",
    "wof:placetype":"venue"
},
  "geometry": {"coordinates":[-80.741438,35.579519],"type":"Point"}
}