{
  "type": "Feature",
  "properties": {
    "iso:country":"US",
    "sg:address":"3008 Old Hollow Rd",
    "sg:city":"Walkertown",
    "sg:classifiers":[
        {
            "category":"Food & Beverages",
            "subcategory":"Groceries & Convenience Stores",
            "type":"Retail Goods"
        }
    ],
    "sg:phone":"+1 336 595 2156",
    "sg:postcode":"27051",
    "sg:province":"NC",
    "sg:website":"www.winndixie.com",
    "wof:name":"Winn-Dixie",
    "wof:placetype":"venue"
},
  "geometry": {"coordinates":[-80.14847,36.16809],"type":"Point"}
}