{
  "type": "Feature",
  "properties": {
    "addr:full":"1013 S Main St China Grove NC 28023",
    "addr:housenumber":"1013",
    "addr:postcode":"28023",
    "addr:street":"S Main St",
    "iso:country":"US",
    "sg:address":"1013 S Main St",
    "sg:city":"China Grove",
    "sg:classifiers":[
        {
            "category":"Restaurant",
            "type":"Food & Drink"
        }
    ],
    "sg:phone":"+1 704 857 3303",
    "sg:postcode":"28023",
    "sg:province":"NC",
    "wof:name":"Laura's Bar-B-Que",
    "wof:placetype":"venue"
},
  "geometry": {"coordinates":[-80.58599599999999,35.562089],"type":"Point"}
}