{
  "type": "Feature",
  "properties": {
    "addr:full":"510 W Cama St Charlotte NC 28217",
    "addr:housenumber":"510",
    "addr:postcode":"28217",
    "addr:street":"W Cama St",
    "iso:country":"US",
    "sg:address":"510 W Cama St",
    "sg:city":"Charlotte",
    "sg:classifiers":[
        {
            "category":"Freight",
            "type":"Transportation"
        }
    ],
    "sg:phone":"+1 704 289 7756",
    "sg:postcode":"28217",
    "sg:province":"NC",
    "sg:tags":[
        "distance",
        "local",
        "long",
        "trucking"
    ],
    "wof:name":"3 TS Trucking Inc",
    "wof:placetype":"venue"
},
  "geometry": {"coordinates":[-80.88361500000001,35.193099],"type":"Point"}
}