{
  "type": "Feature",
  "properties": {
    "addr:full":"1707 S Madison St Whiteville NC 28472",
    "addr:housenumber":"1707",
    "addr:postcode":"28472",
    "addr:street":"S Madison St",
    "iso:country":"US",
    "sg:address":"1707 S Madison St",
    "sg:city":"Whiteville",
    "sg:classifiers":[
        {
            "category":"Food & Beverages",
            "subcategory":"Groceries & Convenience Stores",
            "type":"Retail Goods"
        }
    ],
    "sg:phone":"+1 910 642 0385",
    "sg:postcode":"28472",
    "sg:province":"NC",
    "wof:name":"Sam's Pit Stop",
    "wof:placetype":"venue"
},
  "geometry": {"coordinates":[-78.715585,34.305043],"type":"Point"}
}