{
  "type": "Feature",
  "properties": {
    "iso:country":"US",
    "sg:address":"1419 Rock Corner Rd",
    "sg:city":"Forest City",
    "sg:classifiers":[
        {
            "category":"Professional",
            "subcategory":"Business Services",
            "type":"Services"
        }
    ],
    "sg:phone":"+1   ",
    "sg:postcode":"28043",
    "sg:province":"NC",
    "wof:name":"Carpenter Design Inc",
    "wof:placetype":"venue"
},
  "geometry": {"coordinates":[-81.88521299999999,35.401085],"type":"Point"}
}