{
  "type": "Feature",
  "properties": {
    "addr:full":"2419 Britt Dr Raleigh NC 27610",
    "addr:housenumber":"2419",
    "addr:postcode":"27610",
    "addr:street":"Britt Dr",
    "iso:country":"US",
    "sg:address":"2419 Britt Dr",
    "sg:city":"Raleigh",
    "sg:classifiers":[
        {
            "category":"Building & Trades",
            "subcategory":"Cleaning & Sanitation",
            "type":"Services"
        }
    ],
    "sg:phone":"+1 919 231 6795",
    "sg:postcode":"27610",
    "sg:province":"NC",
    "sg:tags":[
        "janitor"
    ],
    "wof:name":"T & M Janitoral & Carpet Clean",
    "wof:placetype":"venue"
},
  "geometry": {"coordinates":[-78.53336400000001,35.748278],"type":"Point"}
}