{
  "type": "Feature",
  "properties": {
    "addr:full":"6201 Fairview Rd Charlotte NC 28210",
    "addr:housenumber":"6201",
    "addr:postcode":"28210",
    "addr:street":"Fairview Rd",
    "iso:country":"US",
    "sg:address":"6201 Fairview Rd",
    "sg:city":"Charlotte",
    "sg:phone":"+1 704 553 0777",
    "sg:postcode":"28210",
    "sg:province":"NC",
    "wof:name":"Executive Suites Of Southpark",
    "wof:placetype":"venue"
},
  "geometry": {"coordinates":[-80.836853,35.150841],"type":"Point"}
}