{
  "type": "Feature",
  "properties": {
    "addr:full":"301 Battleground Ave Greensboro NC 27410",
    "addr:housenumber":"301",
    "addr:postcode":"27410",
    "addr:street":"Battleground Ave",
    "iso:country":"US",
    "sg:address":"301 Battleground Ave",
    "sg:city":"Greensboro",
    "sg:classifiers":[
        {
            "category":"Professional",
            "type":"Services"
        },
        {
            "category":"Professional",
            "subcategory":"Business Services",
            "type":"Services"
        }
    ],
    "sg:phone":"+1 336 274 2844",
    "sg:postcode":"27410",
    "sg:province":"NC",
    "wof:name":"Geodax Imaging",
    "wof:placetype":"venue"
},
  "geometry": {"coordinates":[-79.792417,36.076819],"type":"Point"}
}