{
  "type": "Feature",
  "properties": {
    "iso:country":"US",
    "sg:address":"700 James Dr",
    "sg:city":"Newport",
    "sg:classifiers":[
        {
            "category":"Building & Trades",
            "subcategory":"Construction",
            "type":"Services"
        }
    ],
    "sg:phone":"+1 252 222 4553",
    "sg:postcode":"28570",
    "sg:province":"NC",
    "sg:tags":[
        "hanging",
        "contractor"
    ],
    "wof:name":"Martys Interior Designs",
    "wof:placetype":"venue"
},
  "geometry": {"coordinates":[-76.888125,34.743657],"type":"Point"}
}