{
  "type": "Feature",
  "properties": {
    "iso:country":"US",
    "sg:address":"2619 Park Ln",
    "sg:city":"Charlotte",
    "sg:classifiers":[
        {
            "category":"Building & Trades",
            "subcategory":"Construction",
            "type":"Services"
        }
    ],
    "sg:phone":"+1 704 517 3411",
    "sg:postcode":"28214",
    "sg:province":"NC",
    "sg:tags":[
        "contractor"
    ],
    "wof:name":"LAW Roofing Inc",
    "wof:placetype":"venue"
},
  "geometry": {"coordinates":[-80.947748,35.248527],"type":"Point"}
}