{
  "type": "Feature",
  "properties": {
    "addr:full":"269 Greenhouse Rd Banner Elk NC 28604",
    "addr:housenumber":"269",
    "addr:postcode":"28604",
    "addr:street":"Greenhouse Rd",
    "iso:country":"US",
    "sg:address":"269 Greenhouse Rd",
    "sg:city":"Banner Elk",
    "sg:classifiers":[
        {
            "category":"Professional",
            "subcategory":"Computer Services",
            "type":"Services"
        }
    ],
    "sg:phone":"+1 828 963 8674",
    "sg:postcode":"28604",
    "sg:province":"NC",
    "sg:tags":[
        "website",
        "design"
    ],
    "wof:name":"Extra Touch",
    "wof:placetype":"venue"
},
  "geometry": {"coordinates":[-81.766896,36.210103],"type":"Point"}
}