{
  "type": "Feature",
  "properties": {
    "iso:country":"US",
    "sg:address":"279 Quiet Pl",
    "sg:city":"Todd",
    "sg:classifiers":[
        {
            "category":"Building & Trades",
            "subcategory":"Electrical",
            "type":"Services"
        }
    ],
    "sg:phone":"+1 336 877 4127",
    "sg:postcode":"28684",
    "sg:province":"NC",
    "sg:tags":[
        "electrical",
        "contractor"
    ],
    "wof:name":"Worleys Electric Inc",
    "wof:placetype":"venue"
},
  "geometry": {"coordinates":[-81.560852,36.343553],"type":"Point"}
}