{
  "type": "Feature",
  "properties": {
    "addr:full":"3023 Market St Wilmington NC 28403",
    "addr:housenumber":"3023",
    "addr:postcode":"28403",
    "addr:street":"Market St",
    "iso:country":"US",
    "sg:address":"3023 Market St",
    "sg:city":"Wilmington",
    "sg:classifiers":[
        {
            "category":"Retail",
            "subcategory":"Repair Shop",
            "type":"Services"
        }
    ],
    "sg:phone":"+1 910 762 1610",
    "sg:postcode":"28403",
    "sg:province":"NC",
    "sg:tags":[
        "refinishing",
        "furniture"
    ],
    "wof:name":"Jerry's Furniture Refinishing",
    "wof:placetype":"venue"
},
  "geometry": {"coordinates":[-77.90613999999999,34.240061],"type":"Point"}
}