{
  "type": "Feature",
  "properties": {
    "addr:full":"4735 Kester Mill Rd Winston Salem NC 27103",
    "addr:postcode":"4735;27103",
    "addr:street":"Mill Rd",
    "iso:country":"US",
    "sg:address":"4735 Kester Mill Rd",
    "sg:city":"Winston Salem",
    "sg:classifiers":[
        {
            "category":"Education",
            "subcategory":"Special Training",
            "type":"Public Place"
        }
    ],
    "sg:phone":"+1 336 774 9080",
    "sg:postcode":"27103",
    "sg:province":"NC",
    "sg:tags":[
        "instruction",
        "driving"
    ],
    "wof:name":"Piedmont Driving School",
    "wof:placetype":"venue"
},
  "geometry": {"coordinates":[-80.343322,36.069366],"type":"Point"}
}