{
  "type": "Feature",
  "properties": {
    "addr:full":"865 Old Murphy Rd Murphy NC 28906",
    "addr:housenumber":"865",
    "addr:postcode":"28906",
    "addr:street":"Old Murphy Rd",
    "iso:country":"US",
    "sg:address":"865 Old Murphy Rd",
    "sg:city":"Murphy",
    "sg:classifiers":[
        {
            "category":"Professional",
            "subcategory":"Business Services",
            "type":"Services"
        }
    ],
    "sg:phone":"+1   ",
    "sg:postcode":"28906",
    "sg:province":"NC",
    "wof:name":"Real Estate Services",
    "wof:placetype":"venue"
},
  "geometry": {"coordinates":[-84.069878,35.057805],"type":"Point"}
}