{
  "type": "Feature",
  "properties": {
    "iso:country":"US",
    "sg:address":"5000 Frank Price Church Rd",
    "sg:city":"Wilson",
    "sg:classifiers":[
        {
            "category":"Food & Beverages",
            "subcategory":"Groceries & Convenience Stores",
            "type":"Retail Goods"
        }
    ],
    "sg:phone":"+1 252 237 4711",
    "sg:postcode":"27893",
    "sg:province":"NC",
    "sg:tags":[
        "station",
        "gasoline"
    ],
    "wof:name":"Community Mart",
    "wof:placetype":"venue"
},
  "geometry": {"coordinates":[-77.913636,35.653827],"type":"Point"}
}