{
  "type": "Feature",
  "properties": {
    "addr:full":"162 Hazelton Loop Mooresville NC 28117",
    "addr:housenumber":"162",
    "addr:postcode":"28117",
    "addr:street":"Hazelton Loop",
    "iso:country":"US",
    "sg:address":"162 Hazelton Loop",
    "sg:city":"Mooresville",
    "sg:classifiers":[
        {
            "category":"Social Services",
            "subcategory":"Child Care",
            "type":"Services"
        }
    ],
    "sg:phone":"+1   ",
    "sg:postcode":"28117",
    "sg:province":"NC",
    "sg:tags":[
        "day"
    ],
    "wof:name":"Sidway Day Nursery",
    "wof:placetype":"venue"
},
  "geometry": {"coordinates":[-80.879627,35.574204],"type":"Point"}
}