{
  "type": "Feature",
  "properties": {
    "iso:country":"US",
    "sg:address":"1996 State Hwy 163",
    "sg:city":"West Jefferson",
    "sg:classifiers":[
        {
            "category":"Building & Trades",
            "subcategory":"Construction",
            "type":"Services"
        }
    ],
    "sg:phone":"+1 336 246 9011",
    "sg:postcode":"28694",
    "sg:province":"NC",
    "sg:tags":[
        "contractor"
    ],
    "wof:name":"Polysteel Wall Systems Inc",
    "wof:placetype":"venue"
},
  "geometry": {"coordinates":[-81.49493,36.408272],"type":"Point"}
}