{
  "type": "Feature",
  "properties": {
    "iso:country":"US",
    "sg:address":"7014 Kings Lynn Loop",
    "sg:city":"Fayetteville",
    "sg:classifiers":[
        {
            "category":"Real Estate",
            "subcategory":"Real Estate Agent",
            "type":"Services"
        }
    ],
    "sg:phone":"+1 910 868 2289",
    "sg:postcode":"28304",
    "sg:province":"NC",
    "wof:name":"Chrishirl Inc",
    "wof:placetype":"venue"
},
  "geometry": {"coordinates":[-79.06641999999999,35.029981],"type":"Point"}
}