{
  "type": "Feature",
  "properties": {
    "iso:country":"US",
    "sg:address":"1687 Government Rd",
    "sg:city":"Clayton",
    "sg:classifiers":[
        {
            "category":"Retail",
            "subcategory":"Repair Shop",
            "type":"Services"
        }
    ],
    "sg:phone":"+1   ",
    "sg:postcode":"27520",
    "sg:province":"NC",
    "wof:name":"Olde Raleigh Taxidermy",
    "wof:placetype":"venue"
},
  "geometry": {"coordinates":[-78.509152,35.601723],"type":"Point"}
}