{
  "type": "Feature",
  "properties": {
    "iso:country":"US",
    "sg:address":"4641 Fillmore Dr",
    "sg:city":"Wilmington",
    "sg:classifiers":[
        {
            "category":"Real Estate",
            "subcategory":"Real Estate Operator",
            "type":"Services"
        }
    ],
    "sg:phone":"+1 910 791 7044",
    "sg:postcode":"28403",
    "sg:province":"NC",
    "sg:tags":[
        "apartment"
    ],
    "sg:website":"www.phillipsmanagement.com",
    "wof:name":"Glen",
    "wof:placetype":"venue"
},
  "geometry": {"coordinates":[-77.882886,34.22595],"type":"Point"}
}