{
  "type": "Feature",
  "properties": {
    "addr:full":"2219 Shore St High Point NC 27263",
    "addr:housenumber":"2219",
    "addr:postcode":"27263",
    "addr:street":"Shore St",
    "iso:country":"US",
    "sg:address":"2219 Shore St",
    "sg:city":"High Point",
    "sg:classifiers":[
        {
            "category":"Manufacturing",
            "subcategory":"Furniture",
            "type":"Manufacturing & Wholesale Goods"
        }
    ],
    "sg:phone":"+1 336 431 9115",
    "sg:postcode":"27263",
    "sg:province":"NC",
    "sg:tags":[
        "upholstered",
        "household",
        "wood",
        "mfg"
    ],
    "sg:website":"www.kohler.com",
    "wof:name":"Baker Furniture Co",
    "wof:placetype":"venue"
},
  "geometry": {"coordinates":[-80.003319,35.919266],"type":"Point"}
}