{
  "type": "Feature",
  "properties": {
    "addr:full":"8700 Piccone Brook Ln Charlotte NC 28216",
    "addr:postcode":"8700;28216",
    "addr:street":"Piccone Brook Ln",
    "iso:country":"US",
    "sg:address":"8700 Piccone Brook Ln",
    "sg:city":"Charlotte",
    "sg:classifiers":[
        {
            "category":"Real Estate",
            "subcategory":"Real Estate Agent",
            "type":"Services"
        }
    ],
    "sg:phone":"+1 704 398 2416",
    "sg:postcode":"28216",
    "sg:province":"NC",
    "wof:name":"James O Horne Jr",
    "wof:placetype":"venue"
},
  "geometry": {"coordinates":[-80.876693,35.347853],"type":"Point"}
}