{
  "type": "Feature",
  "properties": {
    "iso:country":"US",
    "sg:address":"647 Signal Hill Drive Ext",
    "sg:city":"Statesville",
    "sg:classifiers":[
        {
            "category":"Restaurant",
            "type":"Food & Drink"
        }
    ],
    "sg:menulink":"http://www.allmenus.com/nc/statesville/219544-king-of-the-sea-seafood/menu/",
    "sg:phone":"+1 704 872 0177",
    "sg:postcode":"28625",
    "sg:province":"NC",
    "sg:tags":[
        "seafood",
        "american"
    ],
    "wof:name":"King of the Sea Seafood",
    "wof:placetype":"venue"
},
  "geometry": {"coordinates":[-80.851617,35.803569],"type":"Point"}
}