{
  "type": "Feature",
  "properties": {
    "iso:country":"US",
    "sg:address":"115 Main St Exd",
    "sg:city":"Swansboro",
    "sg:classifiers":[
        {
            "category":"Professional",
            "subcategory":"Accounting & Tax Preparation",
            "type":"Services"
        }
    ],
    "sg:phone":"+1 910 326 3499",
    "sg:postcode":"28584",
    "sg:province":"NC",
    "sg:tags":[
        "accountant"
    ],
    "wof:name":"James W Bean Jr CPA",
    "wof:placetype":"venue"
},
  "geometry": {"coordinates":[-77.11911600000001,34.687688],"type":"Point"}
}