{
  "type": "Feature",
  "properties": {
    "iso:country":"US",
    "sg:address":"605 Harney St",
    "sg:city":"Elizabeth City",
    "sg:classifiers":[
        {
            "category":"Food & Beverages",
            "subcategory":"Groceries & Convenience Stores",
            "type":"Retail Goods"
        }
    ],
    "sg:phone":"+1 252 335 5101",
    "sg:postcode":"27909",
    "sg:province":"NC",
    "sg:tags":[
        "grocer"
    ],
    "wof:name":"Clary's Grocery",
    "wof:placetype":"venue"
},
  "geometry": {"coordinates":[-76.225273,36.306678],"type":"Point"}
}