{
  "type": "Feature",
  "properties": {
    "addr:full":"2600 Wake Forest Rd Raleigh NC 27608",
    "addr:housenumber":"2600",
    "addr:postcode":"27608",
    "addr:street":"Wake Forest Rd",
    "iso:country":"US",
    "sg:address":"2600 Wake Forest Rd",
    "sg:city":"Raleigh",
    "sg:classifiers":[
        {
            "category":"Retail",
            "subcategory":"Auto Rental",
            "type":"Services"
        }
    ],
    "sg:phone":"+1   ",
    "sg:postcode":"27608",
    "sg:province":"NC",
    "sg:tags":[
        "passenger",
        "car"
    ],
    "wof:name":"Enterprise Rent-A-Car",
    "wof:placetype":"venue"
},
  "geometry": {"coordinates":[-78.624985,35.817851],"type":"Point"}
}