{
  "type": "Feature",
  "properties": {
    "iso:country":"US",
    "sg:address":"532 Caratoke Hwy",
    "sg:city":"Moyock",
    "sg:classifiers":[
        {
            "category":"Health Services",
            "subcategory":"Health Practitioner",
            "type":"Services"
        }
    ],
    "sg:phone":"+1 252 435 6046",
    "sg:postcode":"27958",
    "sg:province":"NC",
    "sg:tags":[
        "therapist",
        "physical"
    ],
    "wof:name":"Coastal Rehabilitation Inc",
    "wof:placetype":"venue"
},
  "geometry": {"coordinates":[-76.17831099999999,36.524794],"type":"Point"}
}