{
  "type": "Feature",
  "properties": {
    "iso:country":"US",
    "sg:address":"411 Coldwater Dr",
    "sg:city":"Garner",
    "sg:classifiers":[
        {
            "category":"Education",
            "subcategory":"Dance Studio",
            "type":"Public Place"
        }
    ],
    "sg:phone":"+1 919 779 5242",
    "sg:postcode":"27529",
    "sg:province":"NC",
    "sg:tags":[
        "instruction",
        "dancing"
    ],
    "wof:name":"Center Stage",
    "wof:placetype":"venue"
},
  "geometry": {"coordinates":[-78.634227,35.713545],"type":"Point"}
}