{
  "type": "Feature",
  "properties": {
    "addr:full":"5721 Bear Creek Cir Fayetteville NC 28304",
    "addr:housenumber":"5721",
    "addr:postcode":"28304",
    "addr:street":"Bear Creek Cir",
    "iso:country":"US",
    "sg:address":"5721 Bear Creek Cir",
    "sg:city":"Fayetteville",
    "sg:classifiers":[
        {
            "category":"Organizations",
            "subcategory":"Religious Organization",
            "type":"Services"
        }
    ],
    "sg:phone":"+1 910 433 2063",
    "sg:postcode":"28304",
    "sg:province":"NC",
    "wof:name":"Soteria",
    "wof:placetype":"venue"
},
  "geometry": {"coordinates":[-78.981182,35.016044],"type":"Point"}
}