{
  "type": "Feature",
  "properties": {
    "addr:full":"1601 Cargill Ave S Wilson NC 27893",
    "addr:housenumber":"1601",
    "addr:postcode":"27893",
    "addr:street":"Cargill Ave S",
    "iso:country":"US",
    "sg:address":"1601 Cargill Ave S",
    "sg:city":"Wilson",
    "sg:classifiers":[
        {
            "category":"Retail",
            "subcategory":"Auto Repair",
            "type":"Services"
        }
    ],
    "sg:phone":"+1 252 237 7137",
    "sg:postcode":"27893",
    "sg:province":"NC",
    "sg:tags":[
        "repairing",
        "automobile"
    ],
    "wof:name":"Alignment Service",
    "wof:placetype":"venue"
},
  "geometry": {"coordinates":[-77.907583,35.70482],"type":"Point"}
}