{
  "type": "Feature",
  "properties": {
    "addr:full":"108 Fallsworth Dr Cary NC 27513",
    "addr:housenumber":"108",
    "addr:postcode":"27513",
    "addr:street":"Fallsworth Dr",
    "iso:country":"US",
    "sg:address":"108 Fallsworth Dr",
    "sg:city":"Cary",
    "sg:classifiers":[
        {
            "category":"Education",
            "subcategory":"School",
            "type":"Public Place"
        }
    ],
    "sg:phone":"+1 919 219 1622",
    "sg:postcode":"27513",
    "sg:province":"NC",
    "sg:website":"ezrstats.com",
    "wof:name":"EZ-R Stats, LLC",
    "wof:placetype":"venue"
},
  "geometry": {"coordinates":[-78.820035,35.774329],"type":"Point"}
}