{
  "type": "Feature",
  "properties": {
    "addr:full":"28 N Hill Rd Weaverville NC 28787",
    "addr:housenumber":"28",
    "addr:postcode":"28787",
    "addr:street":"N Hill Rd",
    "iso:country":"US",
    "sg:address":"28 N Hill Rd",
    "sg:city":"Weaverville",
    "sg:classifiers":[
        {
            "category":"Real Estate",
            "subcategory":"Real Estate Operator",
            "type":"Services"
        }
    ],
    "sg:phone":"+1 828 658 0998",
    "sg:postcode":"28787",
    "sg:province":"NC",
    "sg:tags":[
        "mobile",
        "home",
        "site"
    ],
    "wof:name":"North View Park",
    "wof:placetype":"venue"
},
  "geometry": {"coordinates":[-82.603393,35.719816],"type":"Point"}
}