{
  "type": "Feature",
  "properties": {
    "addr:full":"208 W Wendover Ave Greensboro NC 27408",
    "addr:housenumber":"208",
    "addr:postcode":"27408",
    "addr:street":"W Wendover Ave",
    "iso:country":"US",
    "sg:address":"208 W Wendover Ave",
    "sg:city":"Greensboro",
    "sg:classifiers":[
        {
            "category":"Professional",
            "subcategory":"Lawyer & Legal Services",
            "type":"Services"
        }
    ],
    "sg:phone":"+1 336 273 3812",
    "sg:postcode":"27408",
    "sg:province":"NC",
    "sg:tags":[
        "attorney"
    ],
    "sg:website":"www.donaldsonandblack.com",
    "wof:name":"Donaldson & Black",
    "wof:placetype":"venue"
},
  "geometry": {"coordinates":[-79.78903099999999,36.088052],"type":"Point"}
}