{
  "type": "Feature",
  "properties": {
    "addr:full":"1908 Eastwood Rd Wilmington NC 28403",
    "addr:housenumber":"1908",
    "addr:postcode":"28403",
    "addr:street":"Eastwood Rd",
    "iso:country":"US",
    "sg:address":"1908 Eastwood Rd",
    "sg:city":"Wilmington",
    "sg:classifiers":[
        {
            "category":"Building & Trades",
            "subcategory":"Construction",
            "type":"Services"
        }
    ],
    "sg:phone":"+1 910 256 4945",
    "sg:postcode":"28403",
    "sg:province":"NC",
    "sg:tags":[
        "general",
        "contractor"
    ],
    "wof:name":"Collins Building Inc",
    "wof:placetype":"venue"
},
  "geometry": {"coordinates":[-77.822372,34.223366],"type":"Point"}
}