{
  "type": "Feature",
  "properties": {
    "addr:full":"7413 Six Forks Rd Raleigh NC 27615",
    "addr:housenumber":"7413",
    "addr:postcode":"27615",
    "addr:street":"Six Forks Rd",
    "iso:country":"US",
    "sg:address":"7413 Six Forks Rd",
    "sg:city":"Raleigh",
    "sg:classifiers":[
        {
            "category":"Wholesale",
            "subcategory":"Groceries",
            "type":"Manufacturing & Wholesale Goods"
        }
    ],
    "sg:phone":"+1 919 790 3803",
    "sg:postcode":"27615",
    "sg:province":"NC",
    "sg:tags":[
        "olive",
        "oil"
    ],
    "wof:name":"Oliva Verde USA",
    "wof:placetype":"venue"
},
  "geometry": {"coordinates":[-78.645912,35.880394],"type":"Point"}
}