{
  "type": "Feature",
  "properties": {
    "iso:country":"US",
    "sg:address":"4594 W Church St",
    "sg:city":"Polkton",
    "sg:classifiers":[
        {
            "category":"Shopping",
            "subcategory":"Hobbies, Toys, & Games",
            "type":"Retail Goods"
        }
    ],
    "sg:phone":"+1 704 826 8963",
    "sg:postcode":"28137",
    "sg:province":"NC",
    "wof:name":"Davis Hobby Shop",
    "wof:placetype":"venue"
},
  "geometry": {"coordinates":[-80.272389,35.474731],"type":"Point"}
}