{
  "type": "Feature",
  "properties": {
    "addr:full":"4161 Hampton Rd Clemmons NC 27012",
    "addr:housenumber":"4161",
    "addr:postcode":"27012",
    "addr:street":"Hampton Rd",
    "iso:country":"US",
    "sg:address":"4161 Hampton Rd",
    "sg:city":"Clemmons",
    "sg:classifiers":[
        {
            "category":"Building & Trades",
            "subcategory":"Construction",
            "type":"Services"
        }
    ],
    "sg:phone":"+1 336 766 4438",
    "sg:postcode":"27012",
    "sg:province":"NC",
    "sg:tags":[
        "contractor"
    ],
    "wof:name":"C Beckner Drywall",
    "wof:placetype":"venue"
},
  "geometry": {"coordinates":[-80.37296600000001,36.01725],"type":"Point"}
}