{
  "type": "Feature",
  "properties": {
    "addr:full":"711 Will Boone Rd Mocksville NC 27028",
    "addr:housenumber":"711",
    "addr:postcode":"27028",
    "addr:street":"Will Boone Rd",
    "iso:country":"US",
    "sg:address":"711 Will Boone Rd",
    "sg:city":"Mocksville",
    "sg:classifiers":[
        {
            "category":"Freight",
            "type":"Transportation"
        }
    ],
    "sg:phone":"+1 336 998 8115",
    "sg:postcode":"27028",
    "sg:province":"NC",
    "sg:tags":[
        "operator",
        "local",
        "trucking"
    ],
    "wof:name":"Je Bodford Trucking",
    "wof:placetype":"venue"
},
  "geometry": {"coordinates":[-80.52981200000001,35.862317],"type":"Point"}
}