{
  "type": "Feature",
  "properties": {
    "addr:full":"220 Avondale Ave Wilmington NC 28403",
    "addr:housenumber":"220",
    "addr:postcode":"28403",
    "addr:street":"Avondale Ave",
    "iso:country":"US",
    "sg:address":"220 Avondale Ave",
    "sg:city":"Wilmington",
    "sg:classifiers":[
        {
            "category":"Health Services",
            "subcategory":"Clinic",
            "type":"Services"
        }
    ],
    "sg:phone":"+1 910 792 1212",
    "sg:postcode":"28403",
    "sg:province":"NC",
    "sg:tags":[
        "home"
    ],
    "wof:name":"A Touch Of Care",
    "wof:placetype":"venue"
},
  "geometry": {"coordinates":[-77.86527599999999,34.208738],"type":"Point"}
}