{
  "type": "Feature",
  "properties": {
    "iso:country":"US",
    "sg:address":"1404 Granada Dr",
    "sg:city":"Fayetteville",
    "sg:classifiers":[
        {
            "category":"Social Services",
            "subcategory":"Child Care",
            "type":"Services"
        }
    ],
    "sg:phone":"+1 910 223 0157",
    "sg:postcode":"28314",
    "sg:province":"NC",
    "wof:name":"Childrens Paradise",
    "wof:placetype":"venue"
},
  "geometry": {"coordinates":[-79.02082900000001,35.045292],"type":"Point"}
}