{
  "type": "Feature",
  "properties": {
    "iso:country":"US",
    "sg:address":"216 E Chatham St Ste 110",
    "sg:city":"Cary",
    "sg:classifiers":[
        {
            "category":"Personal",
            "subcategory":"Massage",
            "type":"Services"
        }
    ],
    "sg:phone":"+1 919 466 9494",
    "sg:postcode":"27511",
    "sg:province":"NC",
    "wof:name":"Moonshadow Therapeutic Massage",
    "wof:placetype":"venue"
},
  "geometry": {"coordinates":[-78.777199,35.787498],"type":"Point"}
}