{
  "type": "Feature",
  "properties": {
    "iso:country":"US",
    "sg:address":"359 State Hwy 24",
    "sg:city":"Cameron",
    "sg:classifiers":[
        {
            "category":"Food & Beverages",
            "subcategory":"Groceries & Convenience Stores",
            "type":"Retail Goods"
        }
    ],
    "sg:phone":"+1 919 499 5125",
    "sg:postcode":"28326",
    "sg:province":"NC",
    "sg:tags":[
        "grocer"
    ],
    "wof:name":"Atkins Grocery",
    "wof:placetype":"venue"
},
  "geometry": {"coordinates":[-79.204031,35.297715],"type":"Point"}
}