{
  "type": "Feature",
  "properties": {
    "addr:full":"2463 Morningside Dr Burlington NC 27217",
    "addr:housenumber":"2463",
    "addr:postcode":"27217",
    "addr:street":"Morningside Dr",
    "iso:country":"US",
    "sg:address":"2463 Morningside Dr",
    "sg:city":"Burlington",
    "sg:classifiers":[
        {
            "category":"Manufacturing",
            "subcategory":"Tools & Machinery",
            "type":"Manufacturing & Wholesale Goods"
        }
    ],
    "sg:phone":"+1 336 227 4117",
    "sg:postcode":"27217",
    "sg:province":"NC",
    "sg:tags":[
        "machine",
        "shop"
    ],
    "wof:name":"A & N Tool & Machine Inc",
    "wof:placetype":"venue"
},
  "geometry": {"coordinates":[-79.390334,36.102829],"type":"Point"}
}