{
  "type": "Feature",
  "properties": {
    "addr:full":"2261 Nash St NW Wilson NC 27896",
    "addr:housenumber":"2261",
    "addr:postcode":"27896",
    "addr:street":"Nash St Nw",
    "iso:country":"US",
    "sg:address":"2261 Nash St NW",
    "sg:city":"Wilson",
    "sg:classifiers":[
        {
            "category":"Professional",
            "subcategory":"Management & Consulting",
            "type":"Services"
        }
    ],
    "sg:phone":"+1   ",
    "sg:postcode":"27896",
    "sg:province":"NC",
    "sg:tags":[
        "business"
    ],
    "wof:name":"Ruffin Consulting Inc",
    "wof:placetype":"venue"
},
  "geometry": {"coordinates":[-77.931532,35.753923],"type":"Point"}
}