{
  "type": "Feature",
  "properties": {
    "iso:country":"US",
    "sg:address":"400 Westwood Shopping Center",
    "sg:city":"Fayetteville",
    "sg:classifiers":[
        {
            "category":"Building & Trades",
            "subcategory":"Construction",
            "type":"Services"
        }
    ],
    "sg:phone":"+1 910 868 2121",
    "sg:postcode":"28314",
    "sg:province":"NC",
    "sg:tags":[
        "general",
        "contractor"
    ],
    "wof:name":"Player Inc",
    "wof:placetype":"venue"
},
  "geometry": {"coordinates":[-78.952967,35.067335],"type":"Point"}
}