{
  "type": "Feature",
  "properties": {
    "iso:country":"US",
    "sg:address":"832 S Van Buren Rd",
    "sg:city":"Eden",
    "sg:classifiers":[
        {
            "category":"Retail",
            "subcategory":"Auto Repair",
            "type":"Services"
        }
    ],
    "sg:phone":"+1 336 623 3616",
    "sg:postcode":"27288",
    "sg:province":"NC",
    "sg:tags":[
        "general"
    ],
    "wof:name":"Xpress Lube Of Eden",
    "wof:placetype":"venue"
},
  "geometry": {"coordinates":[-79.739132,36.486196],"type":"Point"}
}