{
  "type": "Feature",
  "properties": {
    "iso:country":"US",
    "sg:address":"1003 Knott St",
    "sg:city":"Eden",
    "sg:classifiers":[
        {
            "category":"Professional",
            "type":"Services"
        }
    ],
    "sg:phone":"+1 336 635 4072",
    "sg:postcode":"27288",
    "sg:province":"NC",
    "sg:tags":[
        "establishment"
    ],
    "wof:name":"Knott's Landing",
    "wof:placetype":"venue"
},
  "geometry": {"coordinates":[-79.708905,36.505992],"type":"Point"}
}