{
  "type": "Feature",
  "properties": {
    "iso:country":"US",
    "sg:address":"1748 Terrapin Track Rd",
    "sg:city":"Washington",
    "sg:classifiers":[
        {
            "category":"Restaurant",
            "type":"Food & Drink"
        }
    ],
    "sg:phone":"+1 252 975 2308",
    "sg:postcode":"27889",
    "sg:province":"NC",
    "wof:name":"Granny's Country Kitchen",
    "wof:placetype":"venue"
},
  "geometry": {"coordinates":[-76.945837,35.559814],"type":"Point"}
}