{
  "type": "Feature",
  "properties": {
    "iso:country":"US",
    "sg:address":"4709 Wolf Pond Rd",
    "sg:city":"Monroe",
    "sg:classifiers":[
        {
            "category":"Professional",
            "subcategory":"Business Services",
            "type":"Services"
        }
    ],
    "sg:phone":"+1 704 764 3273",
    "sg:postcode":"28112",
    "sg:province":"NC",
    "sg:tags":[
        "water",
        "treatment"
    ],
    "wof:name":"A Water Outlet Inc",
    "wof:placetype":"venue"
},
  "geometry": {"coordinates":[-80.541184,34.888268],"type":"Point"}
}