{
  "type": "Feature",
  "properties": {
    "addr:full":"155 Airport Rd Raeford NC 28328",
    "addr:housenumber":"155",
    "addr:postcode":"28328",
    "addr:street":"Airport Rd",
    "iso:country":"US",
    "sg:address":"155 Airport Rd",
    "sg:city":"Raeford",
    "sg:classifiers":[
        {
            "category":"Restaurant",
            "type":"Food & Drink"
        }
    ],
    "sg:phone":"+1 910 904 6761",
    "sg:postcode":"28328",
    "sg:province":"NC",
    "sg:tags":[
        "eating"
    ],
    "wof:name":"Aviator's Grill & Pub",
    "wof:placetype":"venue"
},
  "geometry": {"coordinates":[-78.35673,34.988449],"type":"Point"}
}