{
  "type": "Feature",
  "properties": {
    "addr:full":"2815 Goldmine Rd Monroe NC 28110",
    "addr:housenumber":"2815",
    "addr:postcode":"28110",
    "addr:street":"Goldmine Rd",
    "iso:country":"US",
    "sg:address":"2815 Goldmine Rd",
    "sg:city":"Monroe",
    "sg:classifiers":[
        {
            "category":"Professional",
            "type":"Services"
        }
    ],
    "sg:phone":"+1 704 283 4165",
    "sg:postcode":"28110",
    "sg:province":"NC",
    "wof:name":"Johnny F Mullis Jr",
    "wof:placetype":"venue"
},
  "geometry": {"coordinates":[-80.598208,35.006208],"type":"Point"}
}