{
  "type": "Feature",
  "properties": {
    "iso:country":"US",
    "sg:address":"1321 Anderson St",
    "sg:city":"Charlotte",
    "sg:classifiers":[
        {
            "category":"Professional",
            "type":"Services"
        }
    ],
    "sg:phone":"+1   ",
    "sg:postcode":"28205",
    "sg:province":"NC",
    "wof:name":"Four Seasons Yard Service",
    "wof:placetype":"venue"
},
  "geometry": {"coordinates":[-80.793132,35.243301],"type":"Point"}
}