{
  "type": "Feature",
  "properties": {
    "addr:full":"1321 Anderson St Charlotte NC 28205",
    "addr:housenumber":"1321",
    "addr:postcode":"28205",
    "addr:street":"Anderson St",
    "iso:country":"US",
    "sg:address":"1321 Anderson St",
    "sg:city":"Charlotte",
    "sg:classifiers":[
        {
            "category":"Professional",
            "type":"Services"
        }
    ],
    "sg:phone":"+1   ",
    "sg:postcode":"28205",
    "sg:province":"NC",
    "wof:name":"Four Seasons Yard Service",
    "wof:placetype":"venue"
},
  "geometry": {"coordinates":[-80.793132,35.243301],"type":"Point"}
}