{
  "type": "Feature",
  "properties": {
    "addr:full":"14 Bennett St Burnsville NC 28714",
    "addr:housenumber":"14",
    "addr:postcode":"28714",
    "addr:street":"Bennett St",
    "iso:country":"US",
    "sg:address":"14 Bennett St",
    "sg:city":"Burnsville",
    "sg:classifiers":[
        {
            "category":"Building & Trades",
            "subcategory":"Construction",
            "type":"Services"
        }
    ],
    "sg:phone":"+1 828 682 0800",
    "sg:postcode":"28714",
    "sg:province":"NC",
    "sg:tags":[
        "general",
        "contractor"
    ],
    "wof:name":"CBA Construction Inc",
    "wof:placetype":"venue"
},
  "geometry": {"coordinates":[-82.29342699999999,35.917065],"type":"Point"}
}