{
  "type": "Feature",
  "properties": {
    "addr:full":"8456 Wards Gap Rd Connellys Spgs NC 28612",
    "addr:housenumber":"8456",
    "addr:postcode":"28612",
    "addr:street":"Wards Gap Rd",
    "iso:country":"US",
    "sg:address":"8456 Wards Gap Rd",
    "sg:city":"Connellys Spgs",
    "sg:classifiers":[
        {
            "category":"Travel",
            "subcategory":"Hotels & Motels",
            "type":"Entertainment"
        }
    ],
    "sg:phone":"+1 828 433 1180",
    "sg:postcode":"28612",
    "sg:province":"NC",
    "sg:tags":[
        "resort"
    ],
    "wof:name":"Pine Mountain Security",
    "wof:placetype":"venue"
},
  "geometry": {"coordinates":[-81.585072,35.590477],"type":"Point"}
}