{
  "type": "Feature",
  "properties": {
    "iso:country":"US",
    "sg:address":"4675 Oxford School Rd",
    "sg:city":"Claremont",
    "sg:classifiers":[
        {
            "category":"Education",
            "subcategory":"School",
            "type":"Public Place"
        }
    ],
    "sg:phone":"+1 828 241 3355",
    "sg:postcode":"28610",
    "sg:province":"NC",
    "wof:name":"Bunker Hill High School",
    "wof:placetype":"venue"
},
  "geometry": {"coordinates":[-81.104833,35.73934],"type":"Point"}
}