{
  "type": "Feature",
  "properties": {
    "iso:country":"US",
    "sg:address":"216 W Sunset Dr",
    "sg:city":"Red Springs",
    "sg:classifiers":[
        {
            "category":"Professional",
            "subcategory":"Business Services",
            "type":"Services"
        }
    ],
    "sg:phone":"+1   ",
    "sg:postcode":"28377",
    "sg:province":"NC",
    "wof:name":"Hh Enterprises",
    "wof:placetype":"venue"
},
  "geometry": {"coordinates":[-79.18018499999999,34.806325],"type":"Point"}
}