{
  "type": "Feature",
  "properties": {
    "addr:full":"1951 Cheek Rd Durham NC 27704",
    "addr:housenumber":"1951",
    "addr:postcode":"27704",
    "addr:street":"Cheek Rd",
    "iso:country":"US",
    "sg:address":"1951 Cheek Rd",
    "sg:city":"Durham",
    "sg:classifiers":[
        {
            "category":"Retail",
            "subcategory":"Auto Repair",
            "type":"Services"
        }
    ],
    "sg:phone":"+1 919 667 9058",
    "sg:postcode":"27704",
    "sg:province":"NC",
    "sg:tags":[
        "repairing",
        "automobile"
    ],
    "wof:name":"B & R Car Care",
    "wof:placetype":"venue"
},
  "geometry": {"coordinates":[-78.864024,36.005492],"type":"Point"}
}