{
  "type": "Feature",
  "properties": {
    "addr:full":"615 Green Willow Cir Wendell NC 27591",
    "addr:housenumber":"615",
    "addr:postcode":"27591",
    "addr:street":"Green Willow Cir",
    "iso:country":"US",
    "sg:address":"615 Green Willow Cir",
    "sg:city":"Wendell",
    "sg:classifiers":[
        {
            "category":"Shopping",
            "subcategory":"Clothing, Apparel, & Fashions",
            "type":"Retail Goods"
        }
    ],
    "sg:phone":"+1 919 365 2765",
    "sg:postcode":"27591",
    "sg:province":"NC",
    "sg:tags":[
        "shop",
        "bridal"
    ],
    "sg:website":"www.aminister.com",
    "wof:name":"AMINISTER.COM",
    "wof:placetype":"venue"
},
  "geometry": {"coordinates":[-78.36776999999999,35.788847],"type":"Point"}
}