{
  "type": "Feature",
  "properties": {
    "iso:country":"US",
    "sg:address":"101 Western Blvd",
    "sg:city":"Jacksonville",
    "sg:classifiers":[
        {
            "category":"Retail",
            "subcategory":"Auto Rental",
            "type":"Services"
        }
    ],
    "sg:phone":"+1 910 353 1777",
    "sg:postcode":"28546",
    "sg:province":"NC",
    "sg:tags":[
        "renting",
        "automobile"
    ],
    "wof:name":"Dollar Rent A Car",
    "wof:placetype":"venue"
},
  "geometry": {"coordinates":[-77.379586,34.747187],"type":"Point"}
}