{
  "type": "Feature",
  "properties": {
    "iso:country":"US",
    "sg:address":"2615 State Rd 98",
    "sg:city":"Louisburg",
    "sg:classifiers":[
        {
            "category":"Food & Beverages",
            "subcategory":"Groceries & Convenience Stores",
            "type":"Retail Goods"
        }
    ],
    "sg:phone":"+1 919 496 2578",
    "sg:postcode":"27549",
    "sg:province":"NC",
    "sg:tags":[
        "grocer"
    ],
    "wof:name":"Floyd's Grocery",
    "wof:placetype":"venue"
},
  "geometry": {"coordinates":[-78.337706,35.969658],"type":"Point"}
}