{
  "type": "Feature",
  "properties": {
    "addr:full":"3334 Old Halifax Rd South Boston NC 24592",
    "addr:housenumber":"3334",
    "addr:postcode":"24592",
    "addr:street":"Old Halifax Rd",
    "iso:country":"US",
    "sg:address":"3334 Old Halifax Rd",
    "sg:city":"South Boston",
    "sg:classifiers":[
        {
            "category":"Shopping",
            "subcategory":"Clothing, Apparel, & Fashions",
            "type":"Retail Goods"
        }
    ],
    "sg:phone":"+1 434 575 8747",
    "sg:postcode":"24592",
    "sg:province":"NC",
    "wof:name":"Gloria's Boutique",
    "wof:placetype":"venue"
},
  "geometry": {"coordinates":[-78.90589300000001,36.730979],"type":"Point"}
}