{
  "type": "Feature",
  "properties": {
    "addr:full":"80 Wheatstone Dr Glenville NC 28717",
    "addr:housenumber":"80",
    "addr:postcode":"28717",
    "addr:street":"Wheatstone Dr",
    "iso:country":"US",
    "sg:address":"80 Wheatstone Dr",
    "sg:city":"Glenville",
    "sg:classifiers":[
        {
            "category":"Building & Trades",
            "subcategory":"Electrical",
            "type":"Services"
        }
    ],
    "sg:phone":"+1 828 743 9618",
    "sg:postcode":"28717",
    "sg:province":"NC",
    "sg:tags":[
        "electrical",
        "contractor"
    ],
    "wof:name":"Tritts Electrical Service",
    "wof:placetype":"venue"
},
  "geometry": {"coordinates":[-83.122348,35.154209],"type":"Point"}
}