{
  "type": "Feature",
  "properties": {
    "addr:full":"148 S Oakwoods Trce Wilkesboro NC 28697",
    "addr:housenumber":"148",
    "addr:postcode":"28697",
    "addr:street":"S Oakwoods Trce",
    "iso:country":"US",
    "sg:address":"148 S Oakwoods Trce",
    "sg:city":"Wilkesboro",
    "sg:classifiers":[
        {
            "category":"Professional",
            "subcategory":"Business Services",
            "type":"Services"
        }
    ],
    "sg:phone":"+1 336 667 1228",
    "sg:postcode":"28697",
    "sg:province":"NC",
    "sg:tags":[
        "auctioneer"
    ],
    "wof:name":"Hendrix Auction Co",
    "wof:placetype":"venue"
},
  "geometry": {"coordinates":[-81.144836,36.11164],"type":"Point"}
}