{
  "type": "Feature",
  "properties": {
    "iso:country":"US",
    "sg:address":"200 S College St",
    "sg:city":"Charlotte",
    "sg:classifiers":[
        {
            "category":"Banks & Credit Unions",
            "subcategory":"Financial Services",
            "type":"Services"
        }
    ],
    "sg:phone":"+1 800 275 3862",
    "sg:postcode":"28202",
    "sg:province":"NC",
    "sg:tags":[
        "mortgage"
    ],
    "sg:website":"http://www.tomtracker.com/redirect.cfm?bID=15770&hID=35610",
    "wof:name":"Wachovia Mortgage",
    "wof:placetype":"venue"
},
  "geometry": {"coordinates":[-80.843102,35.225479],"type":"Point"}
}