{
  "type": "Feature",
  "properties": {
    "iso:country":"US",
    "sg:address":"6517 Englehardt Dr",
    "sg:city":"Raleigh",
    "sg:classifiers":[
        {
            "category":"Wholesale",
            "subcategory":"Electrical",
            "type":"Manufacturing & Wholesale Goods"
        }
    ],
    "sg:phone":"+1 919 870 0597",
    "sg:postcode":"27617",
    "sg:province":"NC",
    "sg:tags":[
        "electronic"
    ],
    "wof:name":"Global Creations Inc",
    "wof:placetype":"venue"
},
  "geometry": {"coordinates":[-78.743807,35.911914],"type":"Point"}
}