{
  "type": "Feature",
  "properties": {
    "iso:country":"US",
    "sg:address":"9606 Sherrill Estates Rd",
    "sg:city":"Huntersville",
    "sg:classifiers":[
        {
            "category":"Personal",
            "type":"Services"
        }
    ],
    "sg:phone":"+1   ",
    "sg:postcode":"28078",
    "sg:province":"NC",
    "wof:name":"A Place In The Sun Inc",
    "wof:placetype":"venue"
},
  "geometry": {"coordinates":[-80.86421300000001,35.437352],"type":"Point"}
}