{
  "type": "Feature",
  "properties": {
    "addr:full":"513 Spainhour Rd King NC 27021",
    "addr:housenumber":"513",
    "addr:postcode":"27021",
    "addr:street":"Spainhour Rd",
    "iso:country":"US",
    "sg:address":"513 Spainhour Rd",
    "sg:city":"King",
    "sg:classifiers":[
        {
            "category":"Autos & Motor Vehicles",
            "subcategory":"Motorcycle Sales",
            "type":"Retail Goods"
        }
    ],
    "sg:phone":"+1 336 591 4141",
    "sg:postcode":"27021",
    "sg:province":"NC",
    "wof:name":"Bike Works Limited",
    "wof:placetype":"venue"
},
  "geometry": {"coordinates":[-80.351231,36.267987],"type":"Point"}
}