{
  "type": "Feature",
  "properties": {
    "iso:country":"US",
    "sg:address":"735 Bonham Ave",
    "sg:city":"Wilmington",
    "sg:classifiers":[
        {
            "category":"Building & Trades",
            "subcategory":"Landscaping Services",
            "type":"Services"
        }
    ],
    "sg:phone":"+1 910 452 7300",
    "sg:postcode":"28403",
    "sg:province":"NC",
    "sg:tags":[
        "landscape"
    ],
    "wof:name":"Louisa Canady Landscaping",
    "wof:placetype":"venue"
},
  "geometry": {"coordinates":[-77.890395,34.225558],"type":"Point"}
}