{
  "type": "Feature",
  "properties": {
    "addr:full":"3308 Tolley St Claremont NC 28610",
    "addr:housenumber":"3308",
    "addr:postcode":"28610",
    "addr:street":"Tolley St",
    "iso:country":"US",
    "sg:address":"3308 Tolley St",
    "sg:city":"Claremont",
    "sg:classifiers":[
        {
            "category":"Shopping",
            "subcategory":"Jewelry",
            "type":"Retail Goods"
        }
    ],
    "sg:phone":"+1 828 322 8599",
    "sg:postcode":"28610",
    "sg:province":"NC",
    "wof:name":"Hmong Jewelry",
    "wof:placetype":"venue"
},
  "geometry": {"coordinates":[-81.14507500000001,35.677242],"type":"Point"}
}