{
  "type": "Feature",
  "properties": {
    "addr:full":"102 Martingale Ln Wilmington NC 28409",
    "addr:housenumber":"102",
    "addr:postcode":"28409",
    "addr:street":"Martingale Ln",
    "iso:country":"US",
    "sg:address":"102 Martingale Ln",
    "sg:city":"Wilmington",
    "sg:classifiers":[
        {
            "category":"Real Estate",
            "subcategory":"Real Estate Agent",
            "type":"Services"
        }
    ],
    "sg:phone":"+1 910 799 7680",
    "sg:postcode":"28409",
    "sg:province":"NC",
    "wof:name":"Cutting & Co Inc",
    "wof:placetype":"venue"
},
  "geometry": {"coordinates":[-77.828018,34.2035],"type":"Point"}
}