{
  "type": "Feature",
  "properties": {
    "addr:full":"5400 W W T Harris Blvd Charlotte NC 28269",
    "addr:housenumber":"5400",
    "addr:postcode":"28269",
    "addr:street":"W W T Harris Blvd",
    "iso:country":"US",
    "sg:address":"5400 W W T Harris Blvd",
    "sg:city":"Charlotte",
    "sg:classifiers":[
        {
            "category":"Autos & Motor Vehicles",
            "subcategory":"Automobile Sales",
            "type":"Retail Goods"
        }
    ],
    "sg:phone":"+1 704 598 2130",
    "sg:postcode":"28269",
    "sg:province":"NC",
    "sg:tags":[
        "car",
        "dealer"
    ],
    "wof:name":"Gateway Classic Cars",
    "wof:placetype":"venue"
},
  "geometry": {"coordinates":[-80.816153,35.333295],"type":"Point"}
}