{
  "type": "Feature",
  "properties": {
    "iso:country":"US",
    "sg:address":"201 Frazier Ave",
    "sg:city":"Charlotte",
    "sg:classifiers":[
        {
            "category":"Real Estate",
            "subcategory":"Real Estate Agent",
            "type":"Services"
        }
    ],
    "sg:phone":"+1 704 336 5282",
    "sg:postcode":"28216",
    "sg:province":"NC",
    "wof:name":"Tarlton Hills",
    "wof:placetype":"venue"
},
  "geometry": {"coordinates":[-80.856798,35.238834],"type":"Point"}
}