{
  "type": "Feature",
  "properties": {
    "addr:full":"214 Commerce Pl Greensboro NC 27401",
    "addr:housenumber":"214",
    "addr:postcode":"27401",
    "addr:street":"Commerce Pl",
    "iso:country":"US",
    "sg:address":"214 Commerce Pl",
    "sg:city":"Greensboro",
    "sg:classifiers":[
        {
            "category":"Professional",
            "subcategory":"Lawyer & Legal Services",
            "type":"Services"
        }
    ],
    "sg:phone":"+1 336 275 9381",
    "sg:postcode":"27401",
    "sg:province":"NC",
    "sg:tags":[
        "law"
    ],
    "wof:name":"Clontz J Stewart",
    "wof:placetype":"venue"
},
  "geometry": {"coordinates":[-79.792452,36.074018],"type":"Point"}
}