{
  "type": "Feature",
  "properties": {
    "addr:full":"1050 Classic Rd Apex NC 27539",
    "addr:housenumber":"1050",
    "addr:postcode":"27539",
    "addr:street":"Classic Rd",
    "iso:country":"US",
    "sg:address":"1050 Classic Rd",
    "sg:city":"Apex",
    "sg:classifiers":[
        {
            "category":"Wholesale",
            "subcategory":"Electrical",
            "type":"Manufacturing & Wholesale Goods"
        }
    ],
    "sg:phone":"+1 919 481 1530",
    "sg:postcode":"27539",
    "sg:province":"NC",
    "sg:tags":[
        "equipment",
        "electronic",
        "supply"
    ],
    "wof:name":"Group 2000 Sales Inc",
    "wof:placetype":"venue"
},
  "geometry": {"coordinates":[-78.82512699999999,35.717338],"type":"Point"}
}