{
  "type": "Feature",
  "properties": {
    "addr:full":"6616 State Hwy 205 Marshville NC 28103",
    "addr:housenumber":"6616",
    "addr:postcode":"28103",
    "addr:street":"State Hwy 205",
    "iso:country":"US",
    "sg:address":"6616 State Hwy 205",
    "sg:city":"Marshville",
    "sg:classifiers":[
        {
            "category":"Building & Trades",
            "subcategory":"Plumbing",
            "type":"Services"
        }
    ],
    "sg:phone":"+1 704 385 9977",
    "sg:postcode":"28103",
    "sg:province":"NC",
    "sg:tags":[
        "contractor"
    ],
    "wof:name":"Ricky Medlin Heating & Air Con",
    "wof:placetype":"venue"
},
  "geometry": {"coordinates":[-80.35445199999999,35.158276],"type":"Point"}
}