{
  "type": "Feature",
  "properties": {
    "addr:full":"580 Church St Morrisville NC 27560",
    "addr:housenumber":"580",
    "addr:postcode":"27560",
    "addr:street":"Church St",
    "iso:country":"US",
    "sg:address":"580 Church St",
    "sg:city":"Morrisville",
    "sg:classifiers":[
        {
            "category":"Home & Garden",
            "subcategory":"Garden Supply",
            "type":"Retail Goods"
        }
    ],
    "sg:phone":"+1 919 380 8555",
    "sg:postcode":"27560",
    "sg:province":"NC",
    "sg:tags":[
        "nursery",
        "gardening"
    ],
    "wof:name":"Shemin Nurseries",
    "wof:placetype":"venue"
},
  "geometry": {"coordinates":[-78.83290100000001,35.8298],"type":"Point"}
}