{
  "type": "Feature",
  "properties": {
    "iso:country":"US",
    "sg:address":"2024 York Rd",
    "sg:city":"Greenville",
    "sg:classifiers":[
        {
            "category":"Building & Trades",
            "subcategory":"Construction",
            "type":"Services"
        }
    ],
    "sg:phone":"+1 252 756 9719",
    "sg:postcode":"27858",
    "sg:province":"NC",
    "sg:tags":[
        "general",
        "contractor"
    ],
    "wof:name":"M & L Sheppard",
    "wof:placetype":"venue"
},
  "geometry": {"coordinates":[-77.33851900000001,35.583071],"type":"Point"}
}