{
  "type": "Feature",
  "properties": {
    "iso:country":"US",
    "sg:address":"1915 Ivy Rd",
    "sg:city":"Greenville",
    "sg:classifiers":[
        {
            "category":"Building & Trades",
            "subcategory":"Construction",
            "type":"Services"
        }
    ],
    "sg:phone":"+1 252 321 7501",
    "sg:postcode":"27858",
    "sg:province":"NC",
    "sg:tags":[
        "tile",
        "dealer",
        "contractor"
    ],
    "wof:name":"Custom Tile Works Inc",
    "wof:placetype":"venue"
},
  "geometry": {"coordinates":[-77.330978,35.501535],"type":"Point"}
}