{
  "type": "Feature",
  "properties": {
    "addr:full":"629 S 8th St Mebane NC 27302",
    "addr:housenumber":"629",
    "addr:postcode":"27302",
    "addr:street":"S 8Th St",
    "iso:country":"US",
    "sg:address":"629 S 8th St",
    "sg:city":"Mebane",
    "sg:classifiers":[
        {
            "category":"Social Services",
            "subcategory":"Child Care",
            "type":"Services"
        }
    ],
    "sg:phone":"+1   ",
    "sg:postcode":"27302",
    "sg:province":"NC",
    "sg:tags":[
        "day"
    ],
    "wof:name":"Beautiful Babies Day Care",
    "wof:placetype":"venue"
},
  "geometry": {"coordinates":[-79.267245,36.088171],"type":"Point"}
}