{
  "type": "Feature",
  "properties": {
    "addr:full":"14000 Creekside Dr Matthews NC 28105",
    "addr:housenumber":"14000",
    "addr:postcode":"28105",
    "addr:street":"Creekside Dr",
    "iso:country":"US",
    "sg:address":"14000 Creekside Dr",
    "sg:city":"Matthews",
    "sg:classifiers":[
        {
            "category":"Professional",
            "subcategory":"Business Services",
            "type":"Services"
        }
    ],
    "sg:phone":"+1   ",
    "sg:postcode":"28105",
    "sg:province":"NC",
    "wof:name":"Creative Solutions Inc",
    "wof:placetype":"venue"
},
  "geometry": {"coordinates":[-80.67082600000001,35.127307],"type":"Point"}
}