{
  "type": "Feature",
  "properties": {
    "addr:full":"900 W Trade St Charlotte NC 28202",
    "addr:housenumber":"900",
    "addr:postcode":"28202",
    "addr:street":"W Trade St",
    "iso:country":"US",
    "sg:address":"900 W Trade St",
    "sg:city":"Charlotte",
    "sg:classifiers":[
        {
            "category":"Professional",
            "subcategory":"Management & Consulting",
            "type":"Services"
        }
    ],
    "sg:phone":"+1 704 332 6411",
    "sg:postcode":"28202",
    "sg:province":"NC",
    "sg:tags":[
        "datum"
    ],
    "wof:name":"Accenture LLP",
    "wof:placetype":"venue"
},
  "geometry": {"coordinates":[-80.85242100000001,35.23475],"type":"Point"}
}