{
  "type": "Feature",
  "properties": {
    "iso:country":"US",
    "sg:address":"186 Ash Branch Cir",
    "sg:city":"Hayesville",
    "sg:classifiers":[
        {
            "category":"Building & Trades",
            "subcategory":"Construction",
            "type":"Services"
        }
    ],
    "sg:phone":"+1 828 389 4116",
    "sg:postcode":"28904",
    "sg:province":"NC",
    "sg:tags":[
        "house"
    ],
    "wof:name":"A & B Builders Inc",
    "wof:placetype":"venue"
},
  "geometry": {"coordinates":[-83.74055199999999,35.04764],"type":"Point"}
}