{
  "type": "Feature",
  "properties": {
    "addr:full":"310 Pensacola Rd Burnsville NC 28714",
    "addr:housenumber":"310",
    "addr:postcode":"28714",
    "addr:street":"Pensacola Rd",
    "iso:country":"US",
    "sg:address":"310 Pensacola Rd",
    "sg:city":"Burnsville",
    "sg:classifiers":[
        {
            "category":"Health Services",
            "subcategory":"Nursing And Care Facility",
            "type":"Services"
        }
    ],
    "sg:phone":"+1 828 682 9759",
    "sg:postcode":"28714",
    "sg:province":"NC",
    "sg:tags":[
        "home",
        "convalescent"
    ],
    "wof:name":"Brookside Rehabilitation-Care",
    "wof:placetype":"venue"
},
  "geometry": {"coordinates":[-82.290459,35.910843],"type":"Point"}
}