{
  "type": "Feature",
  "properties": {
    "iso:country":"US",
    "sg:address":"120 Adams Hill Rd",
    "sg:city":"Asheville",
    "sg:classifiers":[
        {
            "category":"Food & Beverages",
            "subcategory":"Groceries & Convenience Stores",
            "type":"Retail Goods"
        }
    ],
    "sg:phone":"+1 828 252 6962",
    "sg:postcode":"28806",
    "sg:province":"NC",
    "wof:name":"Altamont Mobile Home Court",
    "wof:placetype":"venue"
},
  "geometry": {"coordinates":[-82.596358,35.60698],"type":"Point"}
}