{
  "type": "Feature",
  "properties": {
    "iso:country":"US",
    "sg:address":"135 S Steele St",
    "sg:city":"Sanford",
    "sg:classifiers":[
        {
            "category":"Restaurant",
            "type":"Food & Drink"
        }
    ],
    "sg:phone":"+1 919 708 5957",
    "sg:postcode":"27330",
    "sg:province":"NC",
    "sg:tags":[
        "eating"
    ],
    "wof:name":"Local Joe's Tap & Grill",
    "wof:placetype":"venue"
},
  "geometry": {"coordinates":[-79.17883999999999,35.480338],"type":"Point"}
}