{
  "type": "Feature",
  "properties": {
    "addr:full":"215 Bayshore Dr Elizabeth City NC 27909",
    "addr:housenumber":"215",
    "addr:postcode":"27909",
    "addr:street":"Bayshore Dr",
    "iso:country":"US",
    "sg:address":"215 Bayshore Dr",
    "sg:city":"Elizabeth City",
    "sg:classifiers":[
        {
            "category":"Professional",
            "type":"Services"
        }
    ],
    "sg:phone":"+1   ",
    "sg:postcode":"27909",
    "sg:province":"NC",
    "wof:name":"Certified Services of NC",
    "wof:placetype":"venue"
},
  "geometry": {"coordinates":[-76.145071,36.258343],"type":"Point"}
}