{
  "type": "Feature",
  "properties": {
    "iso:country":"US",
    "sg:address":"9101 Leesville Rd Suite 111",
    "sg:city":"Raleigh",
    "sg:classifiers":[
        {
            "category":"Insurance",
            "subcategory":"Insurance Agent",
            "type":"Services"
        },
        {
            "category":"Insurance",
            "subcategory":"Hazard Insurance",
            "type":"Services"
        },
        {
            "category":"Insurance",
            "subcategory":"Title Insurance",
            "type":"Services"
        }
    ],
    "sg:phone":"+1 919 323 3679",
    "sg:postcode":"27613",
    "sg:province":"NC",
    "sg:tags":[
        "auto",
        "homeowner",
        "renter",
        "marine",
        "boat"
    ],
    "sg:website":"http://clickserve.dartsearch.net/link/click?lid=43000000142087377",
    "wof:name":"Lauri W. Fair - Allstate Insurance Company",
    "wof:placetype":"venue"
},
  "geometry": {"coordinates":[-78.72305299999999,35.89661],"type":"Point"}
}