{
  "type": "Feature",
  "properties": {
    "addr:full":"515 College Rd Greensboro NC 27410",
    "addr:housenumber":"515",
    "addr:postcode":"27410",
    "addr:street":"College Rd",
    "iso:country":"US",
    "sg:address":"515 College Rd",
    "sg:city":"Greensboro",
    "sg:classifiers":[
        {
            "category":"Insurance",
            "subcategory":"Insurance Agent",
            "type":"Services"
        }
    ],
    "sg:phone":"+1 336 294 8427",
    "sg:postcode":"27410",
    "sg:province":"NC",
    "wof:name":"Assar & Assoc",
    "wof:placetype":"venue"
},
  "geometry": {"coordinates":[-79.891015,36.084221],"type":"Point"}
}