{
  "type": "Feature",
  "properties": {
    "addr:full":"4116 N Croatan Hwy Kitty Hawk NC 27949",
    "addr:housenumber":"4116",
    "addr:postcode":"27949",
    "addr:street":"N Croatan Hwy",
    "iso:country":"US",
    "sg:address":"4116 N Croatan Hwy",
    "sg:city":"Kitty Hawk",
    "sg:classifiers":[
        {
            "category":"Shopping",
            "subcategory":"Department Store",
            "type":"Retail Goods"
        }
    ],
    "sg:phone":"+1 252 261 7455",
    "sg:postcode":"27949",
    "sg:province":"NC",
    "wof:name":"Wings",
    "wof:placetype":"venue"
},
  "geometry": {"coordinates":[-75.69636199999999,36.07093],"type":"Point"}
}