{
  "type": "Feature",
  "properties": {
    "iso:country":"US",
    "sg:address":"3015 N Main St",
    "sg:city":"High Point",
    "sg:classifiers":[
        {
            "category":"Autos & Motor Vehicles",
            "subcategory":"Auto Supplies",
            "type":"Retail Goods"
        }
    ],
    "sg:phone":"+1 336 841 6550",
    "sg:postcode":"27265",
    "sg:province":"NC",
    "sg:tags":[
        "parts",
        "accessory"
    ],
    "wof:name":"Parts Depot Inc",
    "wof:placetype":"venue"
},
  "geometry": {"coordinates":[-80.03614399999999,36.001032],"type":"Point"}
}