{
  "type": "Feature",
  "properties": {
    "iso:country":"US",
    "sg:address":"2207 Lane St",
    "sg:city":"Kannapolis",
    "sg:classifiers":[
        {
            "category":"Insurance",
            "subcategory":"Insurance Agent",
            "type":"Services"
        }
    ],
    "sg:phone":"+1 704 932 4422",
    "sg:postcode":"28083",
    "sg:province":"NC",
    "wof:name":"IAB",
    "wof:placetype":"venue"
},
  "geometry": {"coordinates":[-80.585296,35.502976],"type":"Point"}
}