{
  "type": "Feature",
  "properties": {
    "addr:full":"6422 Serena Ct Wilmington NC 28411",
    "addr:housenumber":"6422",
    "addr:postcode":"28411",
    "addr:street":"Serena Ct",
    "iso:country":"US",
    "sg:address":"6422 Serena Ct",
    "sg:city":"Wilmington",
    "sg:classifiers":[
        {
            "category":"Professional",
            "subcategory":"Business Services",
            "type":"Services"
        }
    ],
    "sg:phone":"+1   ",
    "sg:postcode":"28411",
    "sg:province":"NC",
    "sg:tags":[
        "investigation",
        "background"
    ],
    "wof:name":"Donald Wofford Raynor",
    "wof:placetype":"venue"
},
  "geometry": {"coordinates":[-77.81438900000001,34.26089],"type":"Point"}
}