{
  "type": "Feature",
  "properties": {
    "iso:country":"US",
    "sg:address":"200 Twin Harbor Dr",
    "sg:city":"Mount Gilead",
    "sg:classifiers":[
        {
            "category":"Travel",
            "subcategory":"Campground",
            "type":"Entertainment"
        }
    ],
    "sg:phone":"+1   ",
    "sg:postcode":"27306",
    "sg:province":"NC",
    "sg:tags":[
        "trailer"
    ],
    "wof:name":"Twin Harbor Property Owners",
    "wof:placetype":"venue"
},
  "geometry": {"coordinates":[-80.076323,35.264581],"type":"Point"}
}