{
  "type": "Feature",
  "properties": {
    "iso:country":"US",
    "sg:address":"2980 Greenwich Rd",
    "sg:city":"Winston Salem",
    "sg:classifiers":[
        {
            "category":"Real Estate",
            "subcategory":"Real Estate Operator",
            "type":"Services"
        }
    ],
    "sg:phone":"+1 336 774 1792",
    "sg:postcode":"27104",
    "sg:province":"NC",
    "sg:tags":[
        "building",
        "nonresidential"
    ],
    "wof:name":"Avant Properties LLC",
    "wof:placetype":"venue"
},
  "geometry": {"coordinates":[-80.294448,36.092184],"type":"Point"}
}