{
  "type": "Feature",
  "properties": {
    "addr:full":"104 W Franklin St Chapel Hill NC 27516",
    "addr:housenumber":"104",
    "addr:postcode":"27516",
    "addr:street":"W Franklin St",
    "iso:country":"US",
    "sg:address":"104 W Franklin St",
    "sg:city":"Chapel Hill",
    "sg:classifiers":[
        {
            "category":"Coffee & Tea",
            "type":"Food & Drink"
        },
        {
            "category":"Bagels",
            "type":"Food & Drink"
        }
    ],
    "sg:menulink":"http://www.allmenus.com/nc/chapel-hill/114725-brueggers/menu/",
    "sg:phone":"+1 919 967 5248",
    "sg:postcode":"27516",
    "sg:province":"NC",
    "sg:tags":[
        "wrap",
        "soup",
        "american",
        "sandwich",
        "salad"
    ],
    "wof:name":"Bruegger's",
    "wof:placetype":"venue"
},
  "geometry": {"coordinates":[-79.05597,35.913067],"type":"Point"}
}