{
  "type": "Feature",
  "properties": {
    "iso:country":"US",
    "sg:address":"723 Irving Ave",
    "sg:city":"Eden",
    "sg:classifiers":[
        {
            "category":"Retail",
            "subcategory":"Auto Repair",
            "type":"Services"
        }
    ],
    "sg:phone":"+1 336 623 7663",
    "sg:postcode":"27288",
    "sg:province":"NC",
    "sg:tags":[
        "repairing",
        "automobile"
    ],
    "wof:name":"Hopper's Auto Repair",
    "wof:placetype":"venue"
},
  "geometry": {"coordinates":[-79.770487,36.499244],"type":"Point"}
}