{
  "type": "Feature",
  "properties": {
    "addr:full":"31 2nd St NW Hickory NC 28601",
    "addr:housenumber":"31",
    "addr:postcode":"28601",
    "addr:street":"2Nd St Nw",
    "iso:country":"US",
    "sg:address":"31 2nd St NW",
    "sg:city":"Hickory",
    "sg:classifiers":[
        {
            "category":"Professional",
            "subcategory":"Lawyer & Legal Services",
            "type":"Services"
        }
    ],
    "sg:phone":"+1   ",
    "sg:postcode":"28601",
    "sg:province":"NC",
    "wof:name":"Lisa Andrew Dubs Attrny",
    "wof:placetype":"venue"
},
  "geometry": {"coordinates":[-81.33972199999999,35.732336],"type":"Point"}
}