{
  "type": "Feature",
  "properties": {
    "iso:country":"US",
    "sg:address":"1415 N Charlotte Ave",
    "sg:city":"Monroe",
    "sg:classifiers":[
        {
            "category":"Building & Trades",
            "subcategory":"Construction",
            "type":"Services"
        }
    ],
    "sg:phone":"+1 704 296 9144",
    "sg:postcode":"28110",
    "sg:province":"NC",
    "sg:tags":[
        "house"
    ],
    "wof:name":"Griffin & Company",
    "wof:placetype":"venue"
},
  "geometry": {"coordinates":[-80.560081,34.995307],"type":"Point"}
}