{
  "type": "Feature",
  "properties": {
    "iso:country":"US",
    "sg:address":"4439 Peele Rd",
    "sg:city":"Clayton",
    "sg:classifiers":[
        {
            "category":"Wholesale",
            "subcategory":"Plants",
            "type":"Manufacturing & Wholesale Goods"
        }
    ],
    "sg:phone":"+1 919 553 5927",
    "sg:postcode":"27520",
    "sg:province":"NC",
    "sg:tags":[
        "supply"
    ],
    "wof:name":"Tarheel Native Trees",
    "wof:placetype":"venue"
},
  "geometry": {"coordinates":[-78.444051,35.594877],"type":"Point"}
}