{
  "type": "Feature",
  "properties": {
    "addr:full":"4760 Castelloe Dr La Grange NC 28551",
    "addr:housenumber":"4760",
    "addr:postcode":"28551",
    "addr:street":"Castelloe Dr",
    "iso:country":"US",
    "sg:address":"4760 Castelloe Dr",
    "sg:city":"La Grange",
    "sg:classifiers":[
        {
            "category":"Organizations",
            "subcategory":"Religious Organization",
            "type":"Services"
        }
    ],
    "sg:phone":"+1   ",
    "sg:postcode":"28551",
    "sg:province":"NC",
    "wof:name":"Church of God Parsonage",
    "wof:placetype":"venue"
},
  "geometry": {"coordinates":[-77.760481,35.288257],"type":"Point"}
}