{
  "type": "Feature",
  "properties": {
    "iso:country":"US",
    "sg:address":"329 N Harrison Ave Ste A",
    "sg:city":"Cary",
    "sg:classifiers":[
        {
            "category":"Ice Cream",
            "type":"Food & Drink"
        }
    ],
    "sg:phone":"+1 919 460 1300",
    "sg:postcode":"27513",
    "sg:province":"NC",
    "sg:tags":[
        "frozen",
        "yogurt"
    ],
    "wof:name":"Kebab House the",
    "wof:placetype":"venue"
},
  "geometry": {"coordinates":[-78.783401,35.789398],"type":"Point"}
}