{
  "type": "Feature",
  "properties": {
    "addr:full":"730 Sutton Rd Rocky Mount NC 27801",
    "addr:housenumber":"730",
    "addr:postcode":"27801",
    "addr:street":"Sutton Rd",
    "iso:country":"US",
    "sg:address":"730 Sutton Rd",
    "sg:city":"Rocky Mount",
    "sg:classifiers":[
        {
            "category":"Organizations",
            "subcategory":"Religious Organization",
            "type":"Services"
        }
    ],
    "sg:phone":"+1   ",
    "sg:postcode":"27801",
    "sg:province":"NC",
    "wof:name":"Shiloh Baptist Church",
    "wof:placetype":"venue"
},
  "geometry": {"coordinates":[-77.797804,35.915119],"type":"Point"}
}