{
  "type": "Feature",
  "properties": {
    "iso:country":"US",
    "sg:address":"400 N Elm St",
    "sg:city":"High Point",
    "sg:classifiers":[
        {
            "category":"Health Services",
            "subcategory":"Doctor",
            "type":"Services"
        }
    ],
    "sg:phone":"+1 336 802 2120",
    "sg:postcode":"27262",
    "sg:province":"NC",
    "sg:tags":[
        "physician",
        "surgeon"
    ],
    "wof:name":"High Point Ob-Gyn Assoc",
    "wof:placetype":"venue"
},
  "geometry": {"coordinates":[-80.011625,35.961541],"type":"Point"}
}