{
  "type": "Feature",
  "properties": {
    "addr:full":"327 N Oakwood Dr Statesville NC 28677",
    "addr:housenumber":"327",
    "addr:postcode":"28677",
    "addr:street":"N Oakwood Dr",
    "iso:country":"US",
    "sg:address":"327 N Oakwood Dr",
    "sg:city":"Statesville",
    "sg:classifiers":[
        {
            "category":"Professional",
            "subcategory":"Detective & Security Services",
            "type":"Services"
        }
    ],
    "sg:phone":"+1   ",
    "sg:postcode":"28677",
    "sg:province":"NC",
    "sg:tags":[
        "investigator"
    ],
    "wof:name":"Leo Tony Brown",
    "wof:placetype":"venue"
},
  "geometry": {"coordinates":[-80.881895,35.796381],"type":"Point"}
}