{
  "type": "Feature",
  "properties": {
    "addr:full":"225 Hill Rd Southern Pines NC 28387",
    "addr:housenumber":"225",
    "addr:postcode":"28387",
    "addr:street":"Hill Rd",
    "iso:country":"US",
    "sg:address":"225 Hill Rd",
    "sg:city":"Southern Pines",
    "sg:classifiers":[
        {
            "category":"Restaurant",
            "type":"Food & Drink"
        }
    ],
    "sg:phone":"+1 910 692 4309",
    "sg:postcode":"28387",
    "sg:province":"NC",
    "sg:website":"www.backyardburgers.com",
    "wof:name":"Back Yard Burgers",
    "wof:placetype":"venue"
},
  "geometry": {"coordinates":[-79.386731,35.157821],"type":"Point"}
}