{
  "type": "Feature",
  "properties": {
    "iso:country":"US",
    "sg:address":"8 Pisgah Pkwy",
    "sg:city":"Asheville",
    "sg:classifiers":[
        {
            "category":"Organizations",
            "subcategory":"Religious Organization",
            "type":"Services"
        }
    ],
    "sg:phone":"+1 828 665 6669",
    "sg:postcode":"28806",
    "sg:province":"NC",
    "sg:tags":[
        "church"
    ],
    "wof:name":"Pisgah Motorsports",
    "wof:placetype":"venue"
},
  "geometry": {"coordinates":[-82.635441,35.575514],"type":"Point"}
}