{
  "type": "Feature",
  "properties": {
    "iso:country":"US",
    "sg:address":"315 Jackson Park Rd",
    "sg:city":"Cornelius",
    "sg:classifiers":[
        {
            "category":"Personal",
            "subcategory":"Barber",
            "type":"Services"
        }
    ],
    "sg:phone":"+1 704 933 4277",
    "sg:postcode":"28083",
    "sg:province":"NC",
    "sg:tags":[
        "shop"
    ],
    "wof:name":"Mullis Barber Shop",
    "wof:placetype":"venue"
},
  "geometry": {"coordinates":[-80.61538,35.504505],"type":"Point"}
}