{
  "type": "Feature",
  "properties": {
    "iso:country":"US",
    "sg:address":"3900 Liberty Rd",
    "sg:city":"Greensboro",
    "sg:classifiers":[
        {
            "category":"Autos & Motor Vehicles",
            "subcategory":"Motorcycle Sales",
            "type":"Retail Goods"
        }
    ],
    "sg:phone":"+1 336 508 3445",
    "sg:postcode":"27406",
    "sg:province":"NC",
    "sg:tags":[
        "scooter"
    ],
    "wof:name":"Custom Cycle Creations",
    "wof:placetype":"venue"
},
  "geometry": {"coordinates":[-79.75675099999999,36.009251],"type":"Point"}
}