{
  "type": "Feature",
  "properties": {
    "addr:full":"1609 E Broad St Statesville NC 28625",
    "addr:housenumber":"1609",
    "addr:postcode":"28625",
    "addr:street":"E Broad St",
    "iso:country":"US",
    "sg:address":"1609 E Broad St",
    "sg:city":"Statesville",
    "sg:classifiers":[
        {
            "category":"Banks & Credit Unions",
            "subcategory":"Bank",
            "type":"Services"
        }
    ],
    "sg:phone":"+1 704 878 3880",
    "sg:postcode":"28625",
    "sg:province":"NC",
    "sg:tags":[
        "national",
        "commercial"
    ],
    "wof:name":"Wachovia Bank National Assn",
    "wof:placetype":"venue"
},
  "geometry": {"coordinates":[-80.862323,35.791263],"type":"Point"}
}