{
  "type": "Feature",
  "properties": {
    "addr:full":"253 S Kerr Ave Wilmington NC 28403",
    "addr:housenumber":"253",
    "addr:postcode":"28403",
    "addr:street":"S Kerr Ave",
    "iso:country":"US",
    "sg:address":"253 S Kerr Ave",
    "sg:city":"Wilmington",
    "sg:classifiers":[
        {
            "category":"Freight",
            "type":"Transportation"
        }
    ],
    "sg:phone":"+1 910 799 6390",
    "sg:postcode":"28403",
    "sg:province":"NC",
    "sg:tags":[
        "general"
    ],
    "wof:name":"South KERR Public Storage",
    "wof:placetype":"venue"
},
  "geometry": {"coordinates":[-77.888628,34.237172],"type":"Point"}
}