{
  "type": "Feature",
  "properties": {
    "addr:full":"2401 S Lakeshore Dr Lake Junaluska NC 28745",
    "addr:housenumber":"2401",
    "addr:postcode":"28745",
    "addr:street":"S Lakeshore Dr",
    "iso:country":"US",
    "sg:address":"2401 S Lakeshore Dr",
    "sg:city":"Lake Junaluska",
    "sg:classifiers":[
        {
            "category":"Banks & Credit Unions",
            "subcategory":"Bank",
            "type":"Services"
        }
    ],
    "sg:phone":"+1 828 452 4594",
    "sg:postcode":"28745",
    "sg:province":"NC",
    "sg:tags":[
        "mortgage"
    ],
    "wof:name":"Accelerated Mortgage",
    "wof:placetype":"venue"
},
  "geometry": {"coordinates":[-82.974486,35.522726],"type":"Point"}
}