{
  "type": "Feature",
  "properties": {
    "addr:full":"232 Elmhurst Rd Charlotte NC 28209",
    "addr:housenumber":"232",
    "addr:postcode":"28209",
    "addr:street":"Elmhurst Rd",
    "iso:country":"US",
    "sg:address":"232 Elmhurst Rd",
    "sg:city":"Charlotte",
    "sg:classifiers":[
        {
            "category":"Retail",
            "subcategory":"Repair Shop",
            "type":"Services"
        }
    ],
    "sg:phone":"+1   ",
    "sg:postcode":"28209",
    "sg:province":"NC",
    "wof:name":"I Clean",
    "wof:placetype":"venue"
},
  "geometry": {"coordinates":[-80.866598,35.199547],"type":"Point"}
}