{
  "type": "Feature",
  "properties": {
    "addr:full":"6 Warehouse Dr Salisbury NC 28144",
    "addr:housenumber":"6",
    "addr:postcode":"28144",
    "addr:street":"Warehouse Dr",
    "iso:country":"US",
    "sg:address":"6 Warehouse Dr",
    "sg:city":"Salisbury",
    "sg:classifiers":[
        {
            "category":"Building & Trades",
            "subcategory":"Landscaping Services",
            "type":"Services"
        }
    ],
    "sg:phone":"+1 704 636 5570",
    "sg:postcode":"28144",
    "sg:province":"NC",
    "sg:tags":[
        "landscape",
        "contractor"
    ],
    "wof:name":"Safrit Landscape Construction",
    "wof:placetype":"venue"
},
  "geometry": {"coordinates":[-80.485648,35.679194],"type":"Point"}
}