{
  "type": "Feature",
  "properties": {
    "addr:full":"971 W King St Boone NC 28607",
    "addr:housenumber":"971",
    "addr:postcode":"28607",
    "addr:street":"W King St",
    "iso:country":"US",
    "sg:address":"971 W King St",
    "sg:city":"Boone",
    "sg:classifiers":[
        {
            "category":"Government",
            "subcategory":"Office",
            "type":"Public Place"
        }
    ],
    "sg:phone":"+1 828 264 3943",
    "sg:postcode":"28607",
    "sg:province":"NC",
    "sg:tags":[
        "federal"
    ],
    "wof:name":"Natural Resources Conservation",
    "wof:placetype":"venue"
},
  "geometry": {"coordinates":[-81.688142,36.220691],"type":"Point"}
}