{
  "type": "Feature",
  "properties": {
    "addr:full":"210 E Morgan St Wadesboro NC 28170",
    "addr:housenumber":"210",
    "addr:postcode":"28170",
    "addr:street":"E Morgan St",
    "iso:country":"US",
    "sg:address":"210 E Morgan St",
    "sg:city":"Wadesboro",
    "sg:classifiers":[
        {
            "category":"Professional",
            "subcategory":"Accounting & Tax Preparation",
            "type":"Services"
        }
    ],
    "sg:phone":"+1 704 694 7596",
    "sg:postcode":"28170",
    "sg:province":"NC",
    "sg:tags":[
        "return",
        "filing"
    ],
    "wof:name":"Anson Co Tax Office",
    "wof:placetype":"venue"
},
  "geometry": {"coordinates":[-80.07514999999999,34.965068],"type":"Point"}
}