{
  "type": "Feature",
  "properties": {
    "iso:country":"US",
    "sg:address":"6277 E Raynham Rd",
    "sg:city":"Fairmont",
    "sg:classifiers":[
        {
            "category":"Building & Trades",
            "subcategory":"Construction",
            "type":"Services"
        }
    ],
    "sg:phone":"+1 910 628 7278",
    "sg:postcode":"28340",
    "sg:province":"NC",
    "sg:tags":[
        "contractor"
    ],
    "wof:name":"Felix Dwayne Deal",
    "wof:placetype":"venue"
},
  "geometry": {"coordinates":[-79.179562,34.471066],"type":"Point"}
}