{
  "type": "Feature",
  "properties": {
    "iso:country":"US",
    "sg:address":"2301 South Blvd",
    "sg:city":"Charlotte",
    "sg:classifiers":[
        {
            "category":"Animal Shelter",
            "type":"Public Place"
        },
        {
            "category":"Retail",
            "subcategory":"Pet Boarding",
            "type":"Services"
        },
        {
            "category":"Retail",
            "subcategory":"Animal Services",
            "type":"Services"
        }
    ],
    "sg:phone":"+1 704 527 9247",
    "sg:postcode":"28203",
    "sg:province":"NC",
    "sg:tags":[
        "exercising",
        "kennel",
        "sitting"
    ],
    "wof:name":"All Wags",
    "wof:placetype":"venue"
},
  "geometry": {"coordinates":[-80.86245700000001,35.20549],"type":"Point"}
}