{
  "type": "Feature",
  "properties": {
    "iso:country":"US",
    "sg:address":"1337 National Hwy",
    "sg:city":"Thomasville",
    "sg:classifiers":[
        {
            "category":"Wholesale",
            "subcategory":"Auto Parts",
            "type":"Manufacturing & Wholesale Goods"
        }
    ],
    "sg:phone":"+1 336 882 2439",
    "sg:postcode":"27360",
    "sg:province":"NC",
    "sg:tags":[
        "automobile",
        "used",
        "general"
    ],
    "wof:name":"Gary Essick Import Specialist",
    "wof:placetype":"venue"
},
  "geometry": {"coordinates":[-80.062274,35.906998],"type":"Point"}
}