{
  "type": "Feature",
  "properties": {
    "iso:country":"US",
    "sg:address":"6 Brandy Branch Rd",
    "sg:city":"Horse Shoe",
    "sg:classifiers":[
        {
            "category":"Professional",
            "type":"Services"
        }
    ],
    "sg:phone":"+1 828 891 9517",
    "sg:postcode":"28759",
    "sg:province":"NC",
    "wof:name":"Solid Surface Arts",
    "wof:placetype":"venue"
},
  "geometry": {"coordinates":[-79.39834399999999,35.326831],"type":"Point"}
}