{
  "type": "Feature",
  "properties": {
    "addr:full":"100 N Grove St Hendersonville NC 28792",
    "addr:housenumber":"100",
    "addr:postcode":"28792",
    "addr:street":"N Grove St",
    "iso:country":"US",
    "sg:address":"100 N Grove St",
    "sg:city":"Hendersonville",
    "sg:classifiers":[
        {
            "category":"Government",
            "subcategory":"Office",
            "type":"Public Place"
        }
    ],
    "sg:phone":"+1 828 697 4828",
    "sg:postcode":"28792",
    "sg:province":"NC",
    "wof:name":"Henderson County Data Proc",
    "wof:placetype":"venue"
},
  "geometry": {"coordinates":[-82.457476,35.315256],"type":"Point"}
}