{
  "type": "Feature",
  "properties": {
    "iso:country":"US",
    "sg:address":"7410 Henderson Park Rd",
    "sg:city":"Huntersville",
    "sg:classifiers":[
        {
            "category":"Professional",
            "subcategory":"Business Services",
            "type":"Services"
        }
    ],
    "sg:phone":"+1   ",
    "sg:postcode":"28078",
    "sg:province":"NC",
    "wof:name":"Fun Furniture Wacky Walls",
    "wof:placetype":"venue"
},
  "geometry": {"coordinates":[-80.910674,35.403198],"type":"Point"}
}