{
  "type": "Feature",
  "properties": {
    "addr:full":"4416 Whisperwood Dr Raleigh NC 27616",
    "addr:housenumber":"4416",
    "addr:postcode":"27616",
    "addr:street":"Whisperwood Dr",
    "iso:country":"US",
    "sg:address":"4416 Whisperwood Dr",
    "sg:city":"Raleigh",
    "sg:classifiers":[
        {
            "category":"Professional",
            "subcategory":"Management & Consulting",
            "type":"Services"
        }
    ],
    "sg:phone":"+1   ",
    "sg:postcode":"27616",
    "sg:province":"NC",
    "sg:tags":[
        "business"
    ],
    "wof:name":"Glass Onion Consulting &",
    "wof:placetype":"venue"
},
  "geometry": {"coordinates":[-78.56698400000001,35.881559],"type":"Point"}
}