{
  "type": "Feature",
  "properties": {
    "addr:full":"2568 Moores Spring Rd Westfield NC 27053",
    "addr:housenumber":"2568",
    "addr:postcode":"27053",
    "addr:street":"Moores Spring Rd",
    "iso:country":"US",
    "sg:address":"2568 Moores Spring Rd",
    "sg:city":"Westfield",
    "sg:classifiers":[
        {
            "category":"Shopping",
            "subcategory":"Bicycles & Sporting Goods",
            "type":"Retail Goods"
        }
    ],
    "sg:phone":"+1 336 593 3139",
    "sg:postcode":"27053",
    "sg:province":"NC",
    "sg:tags":[
        "equipment",
        "camping"
    ],
    "wof:name":"Hanging Rock Outdoor Ctr",
    "wof:placetype":"venue"
},
  "geometry": {"coordinates":[-80.28764200000001,36.420795],"type":"Point"}
}