{
  "type": "Feature",
  "properties": {
    "addr:full":"212 Hillstone Dr Jamestown NC 27282",
    "addr:housenumber":"212",
    "addr:postcode":"27282",
    "addr:street":"Hillstone Dr",
    "iso:country":"US",
    "sg:address":"212 Hillstone Dr",
    "sg:city":"Jamestown",
    "sg:classifiers":[
        {
            "category":"Professional",
            "type":"Services"
        }
    ],
    "sg:phone":"+1 336 887 5080",
    "sg:postcode":"27282",
    "sg:province":"NC",
    "sg:tags":[
        "establishment"
    ],
    "wof:name":"Cnc-Access Inc",
    "wof:placetype":"venue"
},
  "geometry": {"coordinates":[-79.931026,35.994803],"type":"Point"}
}