{
  "type": "Feature",
  "properties": {
    "iso:country":"US",
    "sg:address":"21701 Bundy St",
    "sg:city":"Wagram",
    "sg:classifiers":[
        {
            "category":"Professional",
            "type":"Services"
        }
    ],
    "sg:phone":"+1 910 369 0531",
    "sg:postcode":"28396",
    "sg:province":"NC",
    "wof:name":"Miracle Haven",
    "wof:placetype":"venue"
},
  "geometry": {"coordinates":[-79.374218,34.892215],"type":"Point"}
}