{
  "type": "Feature",
  "properties": {
    "addr:full":"6838 Ludwig Dr Charlotte NC 28215",
    "addr:housenumber":"6838",
    "addr:postcode":"28215",
    "addr:street":"Ludwig Dr",
    "iso:country":"US",
    "sg:address":"6838 Ludwig Dr",
    "sg:city":"Charlotte",
    "sg:classifiers":[
        {
            "category":"Building & Trades",
            "subcategory":"Plumbing",
            "type":"Services"
        }
    ],
    "sg:phone":"+1 704 568 3147",
    "sg:postcode":"28215",
    "sg:province":"NC",
    "sg:tags":[
        "conditioning",
        "air",
        "system",
        "contractor"
    ],
    "wof:name":"At's Heating & AC",
    "wof:placetype":"venue"
},
  "geometry": {"coordinates":[-80.745743,35.256462],"type":"Point"}
}