{
  "type": "Feature",
  "properties": {
    "addr:full":"503 Loop Rd Garner NC 27529",
    "addr:housenumber":"503",
    "addr:postcode":"27529",
    "addr:street":"Loop Rd",
    "iso:country":"US",
    "sg:address":"503 Loop Rd",
    "sg:city":"Garner",
    "sg:classifiers":[
        {
            "category":"Wholesale",
            "subcategory":"Machinery & Supplies",
            "type":"Manufacturing & Wholesale Goods"
        }
    ],
    "sg:phone":"+1 919 662 7507",
    "sg:postcode":"27529",
    "sg:province":"NC",
    "sg:tags":[
        "appliance",
        "parts",
        "gas",
        "retail"
    ],
    "wof:name":"Grill Parts & Service",
    "wof:placetype":"venue"
},
  "geometry": {"coordinates":[-78.63308000000001,35.719506],"type":"Point"}
}