{
  "type": "Feature",
  "properties": {
    "addr:full":"305 N Main St Hendersonville NC 28792",
    "addr:housenumber":"305",
    "addr:postcode":"28792",
    "addr:street":"N Main St",
    "iso:country":"US",
    "sg:address":"305 N Main St",
    "sg:city":"Hendersonville",
    "sg:classifiers":[
        {
            "category":"Shopping",
            "subcategory":"Hobbies, Toys, & Games",
            "type":"Retail Goods"
        }
    ],
    "sg:phone":"+1 828 698 7673",
    "sg:postcode":"28792",
    "sg:province":"NC",
    "sg:tags":[
        "arts",
        "craft",
        "supply"
    ],
    "wof:name":"A Show Of Hands",
    "wof:placetype":"venue"
},
  "geometry": {"coordinates":[-82.460303,35.316733],"type":"Point"}
}