{
  "type": "Feature",
  "properties": {
    "addr:full":"1001 Rainey St Burlington NC 27217",
    "addr:housenumber":"1001",
    "addr:postcode":"27217",
    "addr:street":"Rainey St",
    "iso:country":"US",
    "sg:address":"1001 Rainey St",
    "sg:city":"Burlington",
    "sg:classifiers":[
        {
            "category":"Organizations",
            "subcategory":"Religious Organization",
            "type":"Services"
        }
    ],
    "sg:phone":"+1   ",
    "sg:postcode":"27217",
    "sg:province":"NC",
    "wof:name":"Piedmont Presbyterian Church",
    "wof:placetype":"venue"
},
  "geometry": {"coordinates":[-79.420906,36.095445],"type":"Point"}
}