{
  "type": "Feature",
  "properties": {
    "iso:country":"US",
    "sg:address":"206 Lithia Inn Rd",
    "sg:city":"Lincolnton",
    "sg:classifiers":[
        {
            "category":"Insurance",
            "subcategory":"Insurance Agent",
            "type":"Services"
        }
    ],
    "sg:phone":"+1 704 735 2425",
    "sg:postcode":"28092",
    "sg:province":"NC",
    "wof:name":"Nationwide Insurance",
    "wof:placetype":"venue"
},
  "geometry": {"coordinates":[-81.215011,35.479095],"type":"Point"}
}