{
  "type": "Feature",
  "properties": {
    "addr:full":"7920 Moores Chapel Rd Charlotte NC 28214",
    "addr:housenumber":"7920",
    "addr:postcode":"28214",
    "addr:street":"Moores Chapel Rd",
    "iso:country":"US",
    "sg:address":"7920 Moores Chapel Rd",
    "sg:city":"Charlotte",
    "sg:classifiers":[
        {
            "category":"Health Services",
            "subcategory":"Doctor",
            "type":"Services"
        }
    ],
    "sg:phone":"+1 704 392 8199",
    "sg:postcode":"28214",
    "sg:province":"NC",
    "sg:tags":[
        "dentist"
    ],
    "wof:name":"Mc Cord Nelsen & Assoc",
    "wof:placetype":"venue"
},
  "geometry": {"coordinates":[-80.938349,35.275661],"type":"Point"}
}