{
  "type": "Feature",
  "properties": {
    "iso:country":"US",
    "sg:address":"5715 Lawrence Orr Rd",
    "sg:city":"Charlotte",
    "sg:classifiers":[
        {
            "category":"Retail",
            "subcategory":"Photofinishing",
            "type":"Services"
        }
    ],
    "sg:phone":"+1   ",
    "sg:postcode":"28212",
    "sg:province":"NC",
    "sg:tags":[
        "laboratory"
    ],
    "wof:name":"Ferguson Photo",
    "wof:placetype":"venue"
},
  "geometry": {"coordinates":[-80.735895,35.21162],"type":"Point"}
}