{
  "type": "Feature",
  "properties": {
    "addr:full":"1714 Sherwood St Greensboro NC 27403",
    "addr:housenumber":"1714",
    "addr:postcode":"27403",
    "addr:street":"Sherwood St",
    "iso:country":"US",
    "sg:address":"1714 Sherwood St",
    "sg:city":"Greensboro",
    "sg:classifiers":[
        {
            "category":"Professional",
            "subcategory":"Management & Consulting",
            "type":"Services"
        }
    ],
    "sg:phone":"+1 336 275 3698",
    "sg:postcode":"27403",
    "sg:province":"NC",
    "sg:tags":[
        "consultant",
        "energy",
        "conservation"
    ],
    "wof:name":"AJC Grant Resources",
    "wof:placetype":"venue"
},
  "geometry": {"coordinates":[-79.82124899999999,36.065588],"type":"Point"}
}