{
  "type": "Feature",
  "properties": {
    "addr:full":"2668 Whiteville Rd NW Ash NC 28420",
    "addr:postcode":"2668;28420",
    "addr:street":"Whiteville Rd Nw",
    "iso:country":"US",
    "sg:address":"2668 Whiteville Rd NW",
    "sg:city":"Ash",
    "sg:classifiers":[
        {
            "category":"Organizations",
            "subcategory":"Religious Organization",
            "type":"Services"
        }
    ],
    "sg:phone":"+1   ",
    "sg:postcode":"28420",
    "sg:province":"NC",
    "wof:name":"Zion Baptist Church",
    "wof:placetype":"venue"
},
  "geometry": {"coordinates":[-78.498377,34.031005],"type":"Point"}
}