{
  "type": "Feature",
  "properties": {
    "addr:full":"6324 Deerview Dr Raleigh NC 27606",
    "addr:housenumber":"6324",
    "addr:postcode":"27606",
    "addr:street":"Deerview Dr",
    "iso:country":"US",
    "sg:address":"6324 Deerview Dr",
    "sg:city":"Raleigh",
    "sg:classifiers":[
        {
            "category":"Professional",
            "subcategory":"Art Services",
            "type":"Services"
        }
    ],
    "sg:phone":"+1 919 856 0010",
    "sg:postcode":"27606",
    "sg:province":"NC",
    "sg:tags":[
        "photographer",
        "photography",
        "commercial"
    ],
    "wof:name":"Scott Dingman Photographer Inc",
    "wof:placetype":"venue"
},
  "geometry": {"coordinates":[-78.74207800000001,35.703812],"type":"Point"}
}