{
  "type": "Feature",
  "properties": {
    "addr:full":"435 Eastwood Rd Wilmington NC 28403",
    "addr:housenumber":"435",
    "addr:postcode":"28403",
    "addr:street":"Eastwood Rd",
    "iso:country":"US",
    "sg:address":"435 Eastwood Rd",
    "sg:city":"Wilmington",
    "sg:classifiers":[
        {
            "category":"Shopping",
            "subcategory":"Bicycles & Sporting Goods",
            "type":"Retail Goods"
        }
    ],
    "sg:phone":"+1 910 798 9922",
    "sg:postcode":"28403",
    "sg:province":"NC",
    "wof:name":"Cape Fear Kayaks",
    "wof:placetype":"venue"
},
  "geometry": {"coordinates":[-77.857799,34.241902],"type":"Point"}
}