{
  "type": "Feature",
  "properties": {
    "iso:country":"US",
    "sg:address":"2001 Veasley St",
    "sg:city":"Greensboro",
    "sg:classifiers":[
        {
            "category":"Travel",
            "subcategory":"Hotels & Motels",
            "type":"Entertainment"
        }
    ],
    "sg:phone":"+1 336 294 6220",
    "sg:postcode":"27407",
    "sg:province":"NC",
    "wof:name":"Comfort Inn",
    "wof:placetype":"venue"
},
  "geometry": {"coordinates":[-79.845114,36.042871],"type":"Point"}
}