{
  "type": "Feature",
  "properties": {
    "addr:full":"4093 Davis Dr Morrisville NC 27560",
    "addr:housenumber":"4093",
    "addr:postcode":"27560",
    "addr:street":"Davis Dr",
    "iso:country":"US",
    "sg:address":"4093 Davis Dr",
    "sg:city":"Morrisville",
    "sg:classifiers":[
        {
            "category":"Food & Beverages",
            "subcategory":"Groceries & Convenience Stores",
            "type":"Retail Goods"
        }
    ],
    "sg:phone":"+1 919 380 0354",
    "sg:postcode":"27560",
    "sg:province":"NC",
    "sg:website":"www.harristeeter.com",
    "wof:name":"Harris Teeter",
    "wof:placetype":"venue"
},
  "geometry": {"coordinates":[-78.85420499999999,35.842901],"type":"Point"}
}