{
  "type": "Feature",
  "properties": {
    "addr:full":"630 N Church St Mount Olive NC 28365",
    "addr:housenumber":"630",
    "addr:postcode":"28365",
    "addr:street":"N Church St",
    "iso:country":"US",
    "sg:address":"630 N Church St",
    "sg:city":"Mount Olive",
    "sg:classifiers":[
        {
            "category":"Shopping",
            "subcategory":"Used Merchandise",
            "type":"Retail Goods"
        }
    ],
    "sg:phone":"+1 919 635 2737",
    "sg:postcode":"28365",
    "sg:province":"NC",
    "wof:name":"Antiques Plus",
    "wof:placetype":"venue"
},
  "geometry": {"coordinates":[-78.060486,35.199331],"type":"Point"}
}