{
  "type": "Feature",
  "properties": {
    "iso:country":"US",
    "sg:address":"8313 Bratt Ave",
    "sg:city":"Wake Forest",
    "sg:classifiers":[
        {
            "category":"Building & Trades",
            "subcategory":"Construction",
            "type":"Services"
        }
    ],
    "sg:phone":"+1 919 625 5384",
    "sg:postcode":"27587",
    "sg:province":"NC",
    "sg:tags":[
        "framing",
        "contractor"
    ],
    "wof:name":"Rice Construction",
    "wof:placetype":"venue"
},
  "geometry": {"coordinates":[-78.53142699999999,35.915723],"type":"Point"}
}