{
  "type": "Feature",
  "properties": {
    "addr:full":"1709 N Marine Blvd Jacksonville NC 28546",
    "addr:housenumber":"1709",
    "addr:postcode":"28546",
    "addr:street":"N Marine Blvd",
    "iso:country":"US",
    "sg:address":"1709 N Marine Blvd",
    "sg:city":"Jacksonville",
    "sg:classifiers":[
        {
            "category":"Autos & Motor Vehicles",
            "subcategory":"Fuel & Gas Station",
            "type":"Retail Goods"
        }
    ],
    "sg:phone":"+1 910 347 3379",
    "sg:postcode":"28546",
    "sg:province":"NC",
    "sg:tags":[
        "oil"
    ],
    "wof:name":"Caroline Gas",
    "wof:placetype":"venue"
},
  "geometry": {"coordinates":[-77.398577,34.773144],"type":"Point"}
}