{
  "type": "Feature",
  "properties": {
    "iso:country":"US",
    "sg:address":"408 W Wilson St",
    "sg:city":"Tarboro",
    "sg:classifiers":[
        {
            "category":"Food & Beverages",
            "subcategory":"Groceries & Convenience Stores",
            "type":"Retail Goods"
        }
    ],
    "sg:phone":"+1 252 641 4606",
    "sg:postcode":"27886",
    "sg:province":"NC",
    "wof:name":"Lou's Quick Stop",
    "wof:placetype":"venue"
},
  "geometry": {"coordinates":[-77.540249,35.898115],"type":"Point"}
}