{
  "type": "Feature",
  "properties": {
    "addr:full":"1920 Tower Industrial Dr Monroe NC 28110",
    "addr:housenumber":"1920",
    "addr:postcode":"28110",
    "addr:street":"Tower Industrial Dr",
    "iso:country":"US",
    "sg:address":"1920 Tower Industrial Dr",
    "sg:city":"Monroe",
    "sg:classifiers":[
        {
            "category":"Professional",
            "subcategory":"Business Services",
            "type":"Services"
        }
    ],
    "sg:phone":"+1 704 226 9898",
    "sg:postcode":"28110",
    "sg:province":"NC",
    "sg:tags":[
        "cutting",
        "metal"
    ],
    "sg:website":"www.whitecaps.com",
    "wof:name":"Whitecaps Manufacturing Co",
    "wof:placetype":"venue"
},
  "geometry": {"coordinates":[-80.625636,35.033828],"type":"Point"}
}