{
  "type": "Feature",
  "properties": {
    "addr:full":"100 Quail Roost Dr Carrboro NC 27510",
    "addr:housenumber":"100",
    "addr:postcode":"27510",
    "addr:street":"Quail Roost Dr",
    "iso:country":"US",
    "sg:address":"100 Quail Roost Dr",
    "sg:city":"Carrboro",
    "sg:classifiers":[
        {
            "category":"Personal",
            "subcategory":"Beauty Salon",
            "type":"Services"
        }
    ],
    "sg:phone":"+1   ",
    "sg:postcode":"27510",
    "sg:province":"NC",
    "sg:tags":[
        "shop"
    ],
    "wof:name":"Hairlines Inc",
    "wof:placetype":"venue"
},
  "geometry": {"coordinates":[-79.094391,35.926705],"type":"Point"}
}