{
  "type": "Feature",
  "properties": {
    "addr:full":"1718 E 4th St Charlotte NC 28204",
    "addr:housenumber":"1718",
    "addr:postcode":"28204",
    "addr:street":"E 4Th St",
    "iso:country":"US",
    "sg:address":"1718 E 4th St",
    "sg:city":"Charlotte",
    "sg:classifiers":[
        {
            "category":"Health Services",
            "subcategory":"Medical Lab",
            "type":"Services"
        }
    ],
    "sg:phone":"+1 704 347 2754",
    "sg:postcode":"28204",
    "sg:province":"NC",
    "sg:tags":[
        "laboratory"
    ],
    "wof:name":"Laboratory Corp Of America",
    "wof:placetype":"venue"
},
  "geometry": {"coordinates":[-80.825866,35.21163],"type":"Point"}
}