{
  "type": "Feature",
  "properties": {
    "addr:full":"924 US Hwy 64 W Apex NC 27523",
    "addr:housenumber":"924",
    "addr:postcode":"27523",
    "addr:street":"Us Hwy 64 W",
    "iso:country":"US",
    "sg:address":"924 US Hwy 64 W",
    "sg:city":"Apex",
    "sg:classifiers":[
        {
            "category":"Wholesale",
            "subcategory":"Metals & Minerals",
            "type":"Manufacturing & Wholesale Goods"
        }
    ],
    "sg:phone":"+1 919 462 9088",
    "sg:postcode":"27523",
    "sg:province":"NC",
    "sg:tags":[
        "center"
    ],
    "wof:name":"Nail Tek",
    "wof:placetype":"venue"
},
  "geometry": {"coordinates":[-78.82245500000001,35.744051],"type":"Point"}
}