{
  "type": "Feature",
  "properties": {
    "addr:full":"635 Poindexter Dr Charlotte NC 28209",
    "addr:housenumber":"635",
    "addr:postcode":"28209",
    "addr:street":"Poindexter Dr",
    "iso:country":"US",
    "sg:address":"635 Poindexter Dr",
    "sg:city":"Charlotte",
    "sg:classifiers":[
        {
            "category":"Professional",
            "subcategory":"Management & Consulting",
            "type":"Services"
        }
    ],
    "sg:phone":"+1   ",
    "sg:postcode":"28209",
    "sg:province":"NC",
    "sg:tags":[
        "business"
    ],
    "wof:name":"Travis Group LTD",
    "wof:placetype":"venue"
},
  "geometry": {"coordinates":[-80.859173,35.196841],"type":"Point"}
}