{
  "type": "Feature",
  "properties": {
    "iso:country":"US",
    "sg:address":"5421 Wrightsville Ave",
    "sg:city":"Wilmington",
    "sg:classifiers":[
        {
            "category":"Retail",
            "subcategory":"Portrait Studio",
            "type":"Services"
        }
    ],
    "sg:phone":"+1 910 794 2215",
    "sg:postcode":"28403",
    "sg:province":"NC",
    "sg:tags":[
        "photographer"
    ],
    "wof:name":"Delia Model & Talent Mgmt Intl",
    "wof:placetype":"venue"
},
  "geometry": {"coordinates":[-77.85130599999999,34.215403],"type":"Point"}
}