{
  "type": "Feature",
  "properties": {
    "addr:full":"14100 Whistling Duck Ct Charlotte NC 28273",
    "addr:housenumber":"14100",
    "addr:postcode":"28273",
    "addr:street":"Whistling Duck Ct",
    "iso:country":"US",
    "sg:address":"14100 Whistling Duck Ct",
    "sg:city":"Charlotte",
    "sg:classifiers":[
        {
            "category":"Professional",
            "subcategory":"Business Services",
            "type":"Services"
        }
    ],
    "sg:phone":"+1 704 583 2009",
    "sg:postcode":"28273",
    "sg:province":"NC",
    "sg:tags":[
        "telemarketing"
    ],
    "wof:name":"Ted Dubose",
    "wof:placetype":"venue"
},
  "geometry": {"coordinates":[-80.96752600000001,35.099537],"type":"Point"}
}