{
  "type": "Feature",
  "properties": {
    "addr:full":"5429 Griggs Rd Greensboro NC 27405",
    "addr:housenumber":"5429",
    "addr:postcode":"27405",
    "addr:street":"Griggs Rd",
    "iso:country":"US",
    "sg:address":"5429 Griggs Rd",
    "sg:city":"Greensboro",
    "sg:classifiers":[
        {
            "category":"Health Services",
            "subcategory":"Medical Lab",
            "type":"Services"
        }
    ],
    "sg:phone":"+1 336 621 2465",
    "sg:postcode":"27405",
    "sg:province":"NC",
    "wof:name":"A Step Above Denture Svc",
    "wof:placetype":"venue"
},
  "geometry": {"coordinates":[-79.725764,36.15649],"type":"Point"}
}