{
  "type": "Feature",
  "properties": {
    "iso:country":"US",
    "sg:address":"112 S Kerr Ave",
    "sg:city":"Wilmington",
    "sg:classifiers":[
        {
            "category":"Banks & Credit Unions",
            "subcategory":"Bank",
            "type":"Services"
        }
    ],
    "sg:phone":"+1 910 790 9525",
    "sg:postcode":"28403",
    "sg:province":"NC",
    "sg:tags":[
        "loan",
        "real estate"
    ],
    "wof:name":"Minority Financial Svc",
    "wof:placetype":"venue"
},
  "geometry": {"coordinates":[-77.88914,34.23842],"type":"Point"}
}