{
  "type": "Feature",
  "properties": {
    "iso:country":"US",
    "sg:address":"1352 Benvenue Rd",
    "sg:city":"Rocky Mount",
    "sg:classifiers":[
        {
            "category":"Shopping",
            "subcategory":"Clothing, Apparel, & Fashions",
            "type":"Retail Goods"
        }
    ],
    "sg:phone":"+1 252 977 9655",
    "sg:postcode":"27804",
    "sg:province":"NC",
    "sg:tags":[
        "shop",
        "bridal"
    ],
    "wof:name":"Uniquely Yours Bridal Shop",
    "wof:placetype":"venue"
},
  "geometry": {"coordinates":[-77.805797,35.977637],"type":"Point"}
}