{
  "type": "Feature",
  "properties": {
    "addr:full":"5107 Timbertop Ln Charlotte NC 28215",
    "addr:postcode":"5107;28215",
    "addr:street":"Timbertop Ln",
    "iso:country":"US",
    "sg:address":"5107 Timbertop Ln",
    "sg:city":"Charlotte",
    "sg:classifiers":[
        {
            "category":"Retail",
            "subcategory":"Repair Shop",
            "type":"Services"
        }
    ],
    "sg:phone":"+1   ",
    "sg:postcode":"28215",
    "sg:province":"NC",
    "sg:tags":[
        "refrigeration"
    ],
    "wof:name":"Costas Refrigeration",
    "wof:placetype":"venue"
},
  "geometry": {"coordinates":[-80.662463,35.233132],"type":"Point"}
}