{
  "type": "Feature",
  "properties": {
    "addr:full":"221 Bainbridge Cir Garner NC 27529",
    "addr:housenumber":"221",
    "addr:postcode":"27529",
    "addr:street":"Bainbridge Cir",
    "iso:country":"US",
    "sg:address":"221 Bainbridge Cir",
    "sg:city":"Garner",
    "sg:classifiers":[
        {
            "category":"Organizations",
            "subcategory":"Religious Organization",
            "type":"Services"
        }
    ],
    "sg:phone":"+1   ",
    "sg:postcode":"27529",
    "sg:province":"NC",
    "wof:name":"Good Samaritan Baptist Church",
    "wof:placetype":"venue"
},
  "geometry": {"coordinates":[-78.59772,35.689483],"type":"Point"}
}