{
  "type": "Feature",
  "properties": {
    "addr:full":"1717 Owen Dr Fayetteville NC 28304",
    "addr:housenumber":"1717",
    "addr:postcode":"28304",
    "addr:street":"Owen Dr",
    "iso:country":"US",
    "sg:address":"1717 Owen Dr",
    "sg:city":"Fayetteville",
    "sg:classifiers":[
        {
            "category":"Food & Beverages",
            "subcategory":"Groceries & Convenience Stores",
            "type":"Retail Goods"
        }
    ],
    "sg:phone":"+1 910 433 1717",
    "sg:postcode":"28304",
    "sg:province":"NC",
    "wof:name":"Knight Brothers Food Mart",
    "wof:placetype":"venue"
},
  "geometry": {"coordinates":[-78.928258,35.028252],"type":"Point"}
}