{
  "type": "Feature",
  "properties": {
    "iso:country":"US",
    "sg:address":"365 Corvette Ln",
    "sg:city":"Lexington",
    "sg:classifiers":[
        {
            "category":"Building & Trades",
            "subcategory":"Construction",
            "type":"Services"
        }
    ],
    "sg:phone":"+1 336 798 1859",
    "sg:postcode":"27292",
    "sg:province":"NC",
    "sg:tags":[
        "dock"
    ],
    "wof:name":"Ccc Pier Deck & Mulch",
    "wof:placetype":"venue"
},
  "geometry": {"coordinates":[-80.289356,35.666593],"type":"Point"}
}