{
  "type": "Feature",
  "properties": {
    "addr:full":"698 S Key St Pilot Mountain NC 27041",
    "addr:housenumber":"698",
    "addr:postcode":"27041",
    "addr:street":"S Key St",
    "iso:country":"US",
    "sg:address":"698 S Key St",
    "sg:city":"Pilot Mountain",
    "sg:classifiers":[
        {
            "category":"Banks & Credit Unions",
            "subcategory":"Bank",
            "type":"Services"
        }
    ],
    "sg:phone":"+1 336 368 4761",
    "sg:postcode":"27041",
    "sg:province":"NC",
    "sg:tags":[
        "loan",
        "real estate"
    ],
    "sg:website":"www.carolinafarmcredit.com",
    "wof:name":"Carolina Farm Credit",
    "wof:placetype":"venue"
},
  "geometry": {"coordinates":[-80.482788,36.377417],"type":"Point"}
}