{
  "type": "Feature",
  "properties": {
    "iso:country":"US",
    "sg:address":"2531 State Hwy 305",
    "sg:city":"Aulander",
    "sg:classifiers":[
        {
            "category":"Restaurant",
            "type":"Food & Drink"
        }
    ],
    "sg:phone":"+1 252 345 3936",
    "sg:postcode":"27805",
    "sg:province":"NC",
    "wof:name":"H & S Catering",
    "wof:placetype":"venue"
},
  "geometry": {"coordinates":[-77.10473500000001,36.21354],"type":"Point"}
}