{
  "type": "Feature",
  "properties": {
    "addr:full":"1499 28th St SW Hickory NC 28602",
    "addr:housenumber":"1499",
    "addr:postcode":"28602",
    "addr:street":"28Th St Sw",
    "iso:country":"US",
    "sg:address":"1499 28th St SW",
    "sg:city":"Hickory",
    "sg:classifiers":[
        {
            "category":"Real Estate",
            "subcategory":"Real Estate Agent",
            "type":"Services"
        }
    ],
    "sg:phone":"+1 828 322 4114",
    "sg:postcode":"28602",
    "sg:province":"NC",
    "wof:name":"T and L Rentals",
    "wof:placetype":"venue"
},
  "geometry": {"coordinates":[-81.385997,35.713414],"type":"Point"}
}