{
  "type": "Feature",
  "properties": {
    "addr:full":"5929 Market St Wilmington NC 28405",
    "addr:housenumber":"5929",
    "addr:postcode":"28405",
    "addr:street":"Market St",
    "iso:country":"US",
    "sg:address":"5929 Market St",
    "sg:city":"Wilmington",
    "sg:classifiers":[
        {
            "category":"Manufacturing",
            "subcategory":"Wood Products",
            "type":"Manufacturing & Wholesale Goods"
        }
    ],
    "sg:phone":"+1 910 799 1622",
    "sg:postcode":"28405",
    "sg:province":"NC",
    "sg:tags":[
        "personal",
        "leather",
        "woo",
        "mfg"
    ],
    "sg:website":"www.epi4gifts.com",
    "wof:name":"Enhanced Presentations Inc",
    "wof:placetype":"venue"
},
  "geometry": {"coordinates":[-77.856967,34.250496],"type":"Point"}
}