{
  "type": "Feature",
  "properties": {
    "addr:full":"4095 Hastings Rd Kernersville NC 27284",
    "addr:housenumber":"4095",
    "addr:postcode":"27284",
    "addr:street":"Hastings Rd",
    "iso:country":"US",
    "sg:address":"4095 Hastings Rd",
    "sg:city":"Kernersville",
    "sg:classifiers":[
        {
            "category":"Building & Trades",
            "subcategory":"Plumbing",
            "type":"Services"
        }
    ],
    "sg:phone":"+1 336 769 2429",
    "sg:postcode":"27284",
    "sg:province":"NC",
    "sg:tags":[
        "plumbing",
        "contractor"
    ],
    "wof:name":"K & W Plumbing Inc",
    "wof:placetype":"venue"
},
  "geometry": {"coordinates":[-80.118576,36.025453],"type":"Point"}
}