{
  "type": "Feature",
  "properties": {
    "iso:country":"US",
    "sg:address":"794 Darrell Dr",
    "sg:city":"Greenville",
    "sg:classifiers":[
        {
            "category":"Professional",
            "subcategory":"Management & Consulting",
            "type":"Services"
        }
    ],
    "sg:phone":"+1   ",
    "sg:postcode":"27834",
    "sg:province":"NC",
    "sg:tags":[
        "business"
    ],
    "wof:name":"Aristos Consulting",
    "wof:placetype":"venue"
},
  "geometry": {"coordinates":[-77.438648,35.562478],"type":"Point"}
}