{
  "type": "Feature",
  "properties": {
    "iso:country":"US",
    "sg:address":"402 Bay Ct",
    "sg:city":"Carolina Beach",
    "sg:classifiers":[
        {
            "category":"Professional",
            "type":"Services"
        }
    ],
    "sg:phone":"+1 910 458 9732",
    "sg:postcode":"28428",
    "sg:province":"NC",
    "wof:name":"Regina H Fitzpatrick",
    "wof:placetype":"venue"
},
  "geometry": {"coordinates":[-77.897803,34.040225],"type":"Point"}
}