{
  "type": "Feature",
  "properties": {
    "iso:country":"US",
    "sg:address":"328 N Main St",
    "sg:city":"Hendersonville",
    "sg:classifiers":[
        {
            "category":"Building & Trades",
            "subcategory":"Construction",
            "type":"Services"
        }
    ],
    "sg:phone":"+1 828 692 4990",
    "sg:postcode":"28792",
    "sg:province":"NC",
    "sg:tags":[
        "residential",
        "designer"
    ],
    "wof:name":"Raymond W Smith Residential",
    "wof:placetype":"venue"
},
  "geometry": {"coordinates":[-82.460115,35.31653],"type":"Point"}
}