{
  "type": "Feature",
  "properties": {
    "iso:country":"US",
    "sg:address":"3211 Bramer Dr",
    "sg:city":"Raleigh",
    "sg:classifiers":[
        {
            "category":"Organizations",
            "subcategory":"Professional Association",
            "type":"Services"
        }
    ],
    "sg:phone":"+1 919 855 9665",
    "sg:postcode":"27604",
    "sg:province":"NC",
    "sg:website":"www.ncarf.com",
    "wof:name":"NC Assn Of Rehab Facilities",
    "wof:placetype":"venue"
},
  "geometry": {"coordinates":[-78.604874,35.826921],"type":"Point"}
}