{
  "type": "Feature",
  "properties": {
    "iso:country":"US",
    "sg:address":"513 Heather Ct",
    "sg:city":"Asheboro",
    "sg:classifiers":[
        {
            "category":"Professional",
            "subcategory":"Secretarial Services",
            "type":"Services"
        }
    ],
    "sg:phone":"+1 336 625 0700",
    "sg:postcode":"27203",
    "sg:province":"NC",
    "sg:tags":[
        "reporting"
    ],
    "wof:name":"Quick-Writer",
    "wof:placetype":"venue"
},
  "geometry": {"coordinates":[-79.819605,35.722385],"type":"Point"}
}