{
  "type": "Feature",
  "properties": {
    "addr:full":"117 E Main St Elkin NC 28621",
    "addr:housenumber":"117",
    "addr:postcode":"28621",
    "addr:street":"E Main St",
    "iso:country":"US",
    "sg:address":"117 E Main St",
    "sg:city":"Elkin",
    "sg:classifiers":[
        {
            "category":"Home & Garden",
            "subcategory":"Household Appliances",
            "type":"Retail Goods"
        }
    ],
    "sg:phone":"+1 336 526 3744",
    "sg:postcode":"28621",
    "sg:province":"NC",
    "sg:tags":[
        "repair",
        "electrical"
    ],
    "wof:name":"Vac Store",
    "wof:placetype":"venue"
},
  "geometry": {"coordinates":[-80.850044,36.244333],"type":"Point"}
}