{
  "type": "Feature",
  "properties": {
    "iso:country":"US",
    "sg:address":"225 E Sugar Creek Rd",
    "sg:city":"Charlotte",
    "sg:classifiers":[
        {
            "category":"Retail",
            "subcategory":"Self-service Laundry",
            "type":"Services"
        }
    ],
    "sg:phone":"+1 704 494 2646",
    "sg:postcode":"28213",
    "sg:province":"NC",
    "wof:name":"B's Coin Laundry",
    "wof:placetype":"venue"
},
  "geometry": {"coordinates":[-80.793201,35.255048],"type":"Point"}
}