{
  "type": "Feature",
  "properties": {
    "iso:country":"US",
    "sg:address":"5031 Falls of Neuse Rd",
    "sg:city":"Raleigh",
    "sg:classifiers":[
        {
            "category":"Professional",
            "subcategory":"Business Services",
            "type":"Services"
        }
    ],
    "sg:phone":"+1 919 875 9132",
    "sg:postcode":"27609",
    "sg:province":"NC",
    "sg:tags":[
        "appraiser"
    ],
    "wof:name":"Jack Ragan & Assoc Inc",
    "wof:placetype":"venue"
},
  "geometry": {"coordinates":[-78.61465,35.850091],"type":"Point"}
}