{
  "type": "Feature",
  "properties": {
    "addr:full":"136 Shoffners Loop Burlington NC 27217",
    "addr:housenumber":"136",
    "addr:postcode":"27217",
    "addr:street":"Shoffners Loop",
    "iso:country":"US",
    "sg:address":"136 Shoffners Loop",
    "sg:city":"Burlington",
    "sg:classifiers":[
        {
            "category":"Personal",
            "subcategory":"Beauty Salon",
            "type":"Services"
        }
    ],
    "sg:phone":"+1 336 421 1628",
    "sg:postcode":"27217",
    "sg:province":"NC",
    "wof:name":"Hair Styles By Niki",
    "wof:placetype":"venue"
},
  "geometry": {"coordinates":[-79.318521,36.246364],"type":"Point"}
}