{
  "type": "Feature",
  "properties": {
    "addr:full":"154 Yellow Jacket Dr Hayesville NC 28904",
    "addr:housenumber":"154",
    "addr:postcode":"28904",
    "addr:street":"Yellow Jacket Dr",
    "iso:country":"US",
    "sg:address":"154 Yellow Jacket Dr",
    "sg:city":"Hayesville",
    "sg:classifiers":[
        {
            "category":"Utilities",
            "subcategory":"Telephone",
            "type":"Services"
        }
    ],
    "sg:phone":"+1 828 389 0197",
    "sg:postcode":"28904",
    "sg:province":"NC",
    "sg:tags":[
        "communications"
    ],
    "wof:name":"Eaton Communication",
    "wof:placetype":"venue"
},
  "geometry": {"coordinates":[-83.81697200000001,35.040074],"type":"Point"}
}