{
  "type": "Feature",
  "properties": {
    "iso:country":"US",
    "sg:address":"230 McIver St",
    "sg:city":"Sanford",
    "sg:classifiers":[
        {
            "category":"Restaurant",
            "type":"Food & Drink"
        }
    ],
    "sg:phone":"+1 919 777 9989",
    "sg:postcode":"27330",
    "sg:province":"NC",
    "wof:name":"Los Antojitos",
    "wof:placetype":"venue"
},
  "geometry": {"coordinates":[-79.171694,35.481398],"type":"Point"}
}