{
  "type": "Feature",
  "properties": {
    "iso:country":"US",
    "sg:address":"300 Beaver Dam Rd",
    "sg:city":"Vilas",
    "sg:classifiers":[
        {
            "category":"Professional",
            "subcategory":"Art Services",
            "type":"Services"
        }
    ],
    "sg:phone":"+1 828 297 4274",
    "sg:postcode":"28692",
    "sg:province":"NC",
    "sg:tags":[
        "artist"
    ],
    "wof:name":"Little Guys",
    "wof:placetype":"venue"
},
  "geometry": {"coordinates":[-81.81004900000001,36.334365],"type":"Point"}
}