{
  "type": "Feature",
  "properties": {
    "addr:full":"106 N New River Dr Holly Ridge NC 28445",
    "addr:housenumber":"106",
    "addr:postcode":"28445",
    "addr:street":"N New River Dr",
    "iso:country":"US",
    "sg:address":"106 N New River Dr",
    "sg:city":"Holly Ridge",
    "sg:classifiers":[
        {
            "category":"Restaurant",
            "type":"Food & Drink"
        },
        {
            "category":"Ice Cream",
            "type":"Food & Drink"
        }
    ],
    "sg:menulink":"http://www.allmenus.com/nc/topsail/167673-dairy-queen/menu/",
    "sg:phone":"+1 910 328 3112",
    "sg:postcode":"28445",
    "sg:province":"NC",
    "sg:tags":[
        "burger",
        "american",
        "ice",
        "cream"
    ],
    "wof:name":"Dairy Queen",
    "wof:placetype":"venue"
},
  "geometry": {"coordinates":[-77.545867,34.427112],"type":"Point"}
}