{
  "type": "Feature",
  "properties": {
    "addr:full":"16905 Northcross Dr Huntersville NC 28078",
    "addr:housenumber":"16905",
    "addr:postcode":"28078",
    "addr:street":"Northcross Dr",
    "iso:country":"US",
    "sg:address":"16905 Northcross Dr",
    "sg:city":"Huntersville",
    "sg:classifiers":[
        {
            "category":"Professional",
            "subcategory":"Management & Consulting",
            "type":"Services"
        }
    ],
    "sg:phone":"+1 704 987 7400",
    "sg:postcode":"28078",
    "sg:province":"NC",
    "sg:tags":[
        "food"
    ],
    "sg:website":"www.rubbermaid.com",
    "wof:name":"Rubbermaid Food Svc Products",
    "wof:placetype":"venue"
},
  "geometry": {"coordinates":[-80.874331,35.444602],"type":"Point"}
}