{
  "type": "Feature",
  "properties": {
    "iso:country":"US",
    "sg:address":"2602 W Broad St",
    "sg:city":"Elizabethtown",
    "sg:classifiers":[
        {
            "category":"Organizations",
            "subcategory":"Religious Organization",
            "type":"Services"
        }
    ],
    "sg:phone":"+1 910 862 3015",
    "sg:postcode":"28337",
    "sg:province":"NC",
    "sg:tags":[
        "church"
    ],
    "wof:name":"St Christopher's Church",
    "wof:placetype":"venue"
},
  "geometry": {"coordinates":[-78.638122,34.640118],"type":"Point"}
}