{
  "type": "Feature",
  "properties": {
    "addr:full":"400 S Water St Elizabeth City NC 27909",
    "addr:housenumber":"400",
    "addr:postcode":"27909",
    "addr:street":"S Water St",
    "iso:country":"US",
    "sg:address":"400 S Water St",
    "sg:city":"Elizabeth City",
    "sg:classifiers":[
        {
            "category":"Manufacturing",
            "subcategory":"Chemicals & Compounds",
            "type":"Manufacturing & Wholesale Goods"
        }
    ],
    "sg:phone":"+1 252 338 6160",
    "sg:postcode":"27909",
    "sg:province":"NC",
    "sg:tags":[
        "preparation",
        "toilet",
        "mfg"
    ],
    "wof:name":"Avon",
    "wof:placetype":"venue"
},
  "geometry": {"coordinates":[-76.219059,36.297705],"type":"Point"}
}