{
  "type": "Feature",
  "properties": {
    "iso:country":"US",
    "sg:address":"130 Bozeman Loop NW",
    "sg:city":"Shallotte",
    "sg:classifiers":[
        {
            "category":"Professional",
            "subcategory":"Employment Agencies",
            "type":"Services"
        }
    ],
    "sg:phone":"+1   ",
    "sg:postcode":"28470",
    "sg:province":"NC",
    "sg:tags":[
        "help",
        "supply"
    ],
    "wof:name":"Chris Bozeman Truckg",
    "wof:placetype":"venue"
},
  "geometry": {"coordinates":[-78.359244,33.988509],"type":"Point"}
}