{
  "type": "Feature",
  "properties": {
    "addr:full":"12210 Windywood Ct Charlotte NC 28273",
    "addr:housenumber":"12210",
    "addr:postcode":"28273",
    "addr:street":"Windywood Ct",
    "iso:country":"US",
    "sg:address":"12210 Windywood Ct",
    "sg:city":"Charlotte",
    "sg:classifiers":[
        {
            "category":"Manufacturing",
            "subcategory":"Metals",
            "type":"Manufacturing & Wholesale Goods"
        }
    ],
    "sg:phone":"+1 704 588 8990",
    "sg:postcode":"28273",
    "sg:province":"NC",
    "sg:tags":[
        "fence"
    ],
    "wof:name":"M & M Fence Co",
    "wof:placetype":"venue"
},
  "geometry": {"coordinates":[-80.951756,35.140522],"type":"Point"}
}