{
  "type": "Feature",
  "properties": {
    "iso:country":"US",
    "sg:address":"5003 Topsail Dr",
    "sg:city":"Oriental",
    "sg:classifiers":[
        {
            "category":"Professional",
            "type":"Services"
        }
    ],
    "sg:phone":"+1 252 249 3788",
    "sg:postcode":"28571",
    "sg:province":"NC",
    "sg:tags":[
        "establishment"
    ],
    "wof:name":"SCS Frigette Inc",
    "wof:placetype":"venue"
},
  "geometry": {"coordinates":[-76.671561,35.033564],"type":"Point"}
}