{
  "type": "Feature",
  "properties": {
    "iso:country":"US",
    "sg:address":"302 Old County Home Rd",
    "sg:city":"Asheville",
    "sg:classifiers":[
        {
            "category":"Wholesale",
            "subcategory":"Machinery & Supplies",
            "type":"Manufacturing & Wholesale Goods"
        }
    ],
    "sg:phone":"+1 828 251 1535",
    "sg:postcode":"28806",
    "sg:province":"NC",
    "sg:tags":[
        "equipment",
        "industrial"
    ],
    "sg:website":"www.conveyor-sales.com",
    "wof:name":"KME Inc",
    "wof:placetype":"venue"
},
  "geometry": {"coordinates":[-82.62359499999999,35.599289],"type":"Point"}
}