{
  "type": "Feature",
  "properties": {
    "addr:full":"1130 Montreat Rd Black Mountain NC 28711",
    "addr:housenumber":"1130",
    "addr:postcode":"28711",
    "addr:street":"Montreat Rd",
    "iso:country":"US",
    "sg:address":"1130 Montreat Rd",
    "sg:city":"Black Mountain",
    "sg:classifiers":[
        {
            "category":"Travel",
            "subcategory":"Hotels & Motels",
            "type":"Entertainment"
        }
    ],
    "sg:phone":"+1 828 669 9177",
    "sg:postcode":"28711",
    "sg:province":"NC",
    "sg:tags":[
        "chalet",
        "rental",
        "cabin"
    ],
    "wof:name":"Cabin Creek Lodge",
    "wof:placetype":"venue"
},
  "geometry": {"coordinates":[-82.314728,35.636174],"type":"Point"}
}