{
  "type": "Feature",
  "properties": {
    "addr:full":"65 Smith Valley Rd Taylorsville NC 28681",
    "addr:housenumber":"65",
    "addr:postcode":"28681",
    "addr:street":"Smith Valley Rd",
    "iso:country":"US",
    "sg:address":"65 Smith Valley Rd",
    "sg:city":"Taylorsville",
    "sg:classifiers":[
        {
            "category":"Building & Trades",
            "subcategory":"Electrical",
            "type":"Services"
        }
    ],
    "sg:phone":"+1 828 632 5044",
    "sg:postcode":"28681",
    "sg:province":"NC",
    "sg:tags":[
        "electrical",
        "electric",
        "contractor"
    ],
    "wof:name":"Smith Electrical Wiring Contr",
    "wof:placetype":"venue"
},
  "geometry": {"coordinates":[-81.229403,35.884312],"type":"Point"}
}