{
  "type": "Feature",
  "properties": {
    "iso:country":"US",
    "sg:address":"103 Michael Dr",
    "sg:city":"Castle Hayne",
    "sg:classifiers":[
        {
            "category":"Real Estate",
            "subcategory":"Real Estate Operator",
            "type":"Services"
        }
    ],
    "sg:phone":"+1 910 675 8313",
    "sg:postcode":"28429",
    "sg:province":"NC",
    "sg:tags":[
        "building",
        "nonresidential"
    ],
    "wof:name":"Wilkes Bros Properties LLC",
    "wof:placetype":"venue"
},
  "geometry": {"coordinates":[-77.90082,34.339406],"type":"Point"}
}