{
  "type": "Feature",
  "properties": {
    "addr:full":"5391 US Hwy 158 Advance NC 27006",
    "addr:housenumber":"5391",
    "addr:postcode":"27006",
    "addr:street":"Us Hwy 158",
    "iso:country":"US",
    "sg:address":"5391 US Hwy 158",
    "sg:city":"Advance",
    "sg:classifiers":[
        {
            "category":"Health Services",
            "subcategory":"Doctor",
            "type":"Services"
        }
    ],
    "sg:phone":"+1 336 940 2290",
    "sg:postcode":"27006",
    "sg:province":"NC",
    "sg:tags":[
        "physician",
        "medical",
        "surgeon"
    ],
    "wof:name":"Hillsdale Family Practice",
    "wof:placetype":"venue"
},
  "geometry": {"coordinates":[-80.43702500000001,36.005862],"type":"Point"}
}