{
  "type": "Feature",
  "properties": {
    "addr:full":"107 Rustic Wood Ln Cary NC 27518",
    "addr:housenumber":"107",
    "addr:postcode":"27518",
    "addr:street":"Rustic Wood Ln",
    "iso:country":"US",
    "sg:address":"107 Rustic Wood Ln",
    "sg:city":"Cary",
    "sg:classifiers":[
        {
            "category":"Professional",
            "subcategory":"Management & Consulting",
            "type":"Services"
        }
    ],
    "sg:phone":"+1   ",
    "sg:postcode":"27518",
    "sg:province":"NC",
    "sg:tags":[
        "business"
    ],
    "wof:name":"Sygma Consulting",
    "wof:placetype":"venue"
},
  "geometry": {"coordinates":[-78.76101,35.73494],"type":"Point"}
}