{
  "type": "Feature",
  "properties": {
    "addr:full":"420 N Center St Hickory NC 28601",
    "addr:housenumber":"420",
    "addr:postcode":"28601",
    "addr:street":"N Center St",
    "iso:country":"US",
    "sg:address":"420 N Center St",
    "sg:city":"Hickory",
    "sg:classifiers":[
        {
            "category":"Health Services",
            "subcategory":"Health Practitioner",
            "type":"Services"
        }
    ],
    "sg:phone":"+1 828 324 3601",
    "sg:postcode":"28601",
    "sg:province":"NC",
    "sg:tags":[
        "therapist",
        "physical"
    ],
    "wof:name":"Frye Regional Rehab Svc",
    "wof:placetype":"venue"
},
  "geometry": {"coordinates":[-81.33769599999999,35.736692],"type":"Point"}
}