{
  "type": "Feature",
  "properties": {
    "addr:full":"207 Vance St E Wilson NC 27893",
    "addr:housenumber":"207",
    "addr:postcode":"27893",
    "addr:street":"Vance St E",
    "iso:country":"US",
    "sg:address":"207 Vance St E",
    "sg:city":"Wilson",
    "sg:classifiers":[
        {
            "category":"Personal",
            "subcategory":"Beauty Salon",
            "type":"Services"
        }
    ],
    "sg:phone":"+1 252 291 8733",
    "sg:postcode":"27893",
    "sg:province":"NC",
    "sg:tags":[
        "shop"
    ],
    "wof:name":"Peggy's Beauty Salon",
    "wof:placetype":"venue"
},
  "geometry": {"coordinates":[-77.907614,35.726712],"type":"Point"}
}