{
  "type": "Feature",
  "properties": {
    "addr:full":"105 N West St Roseboro NC 28382",
    "addr:housenumber":"105",
    "addr:postcode":"28382",
    "addr:street":"N West St",
    "iso:country":"US",
    "sg:address":"105 N West St",
    "sg:city":"Roseboro",
    "sg:classifiers":[
        {
            "category":"Health Services",
            "subcategory":"Doctor",
            "type":"Services"
        }
    ],
    "sg:phone":"+1 910 525 5451",
    "sg:postcode":"28382",
    "sg:province":"NC",
    "sg:tags":[
        "clinic"
    ],
    "wof:name":"Atlanic Diagnostic Ctr",
    "wof:placetype":"venue"
},
  "geometry": {"coordinates":[-78.512111,34.953316],"type":"Point"}
}