{
  "type": "Feature",
  "properties": {
    "iso:country":"US",
    "sg:address":"230 S 2nd St",
    "sg:city":"Albemarle",
    "sg:classifiers":[
        {
            "category":"Organizations",
            "subcategory":"Religious Organization",
            "type":"Services"
        }
    ],
    "sg:phone":"+1 704 982 8139",
    "sg:postcode":"28001",
    "sg:province":"NC",
    "sg:tags":[
        "church"
    ],
    "sg:website":"www.lutheran.org",
    "wof:name":"First Lutheran Church",
    "wof:placetype":"venue"
},
  "geometry": {"coordinates":[-80.198211,35.349089],"type":"Point"}
}