{
  "type": "Feature",
  "properties": {
    "addr:full":"219 N Boylan Ave Raleigh NC 27603",
    "addr:housenumber":"219",
    "addr:postcode":"27603",
    "addr:street":"N Boylan Ave",
    "iso:country":"US",
    "sg:address":"219 N Boylan Ave",
    "sg:city":"Raleigh",
    "sg:classifiers":[
        {
            "category":"Professional",
            "subcategory":"Art Services",
            "type":"Services"
        }
    ],
    "sg:phone":"+1 919 838 4928",
    "sg:postcode":"27603",
    "sg:province":"NC",
    "sg:tags":[
        "graphic",
        "designer"
    ],
    "wof:name":"Apple Designs",
    "wof:placetype":"venue"
},
  "geometry": {"coordinates":[-78.649113,35.783975],"type":"Point"}
}