{
  "type": "Feature",
  "properties": {
    "iso:country":"US",
    "sg:address":"2602 US Hwy 70",
    "sg:city":"Mebane",
    "sg:classifiers":[
        {
            "category":"Health Services",
            "subcategory":"Chiropractor",
            "type":"Services"
        }
    ],
    "sg:phone":"+1   ",
    "sg:postcode":"27302",
    "sg:province":"NC",
    "wof:name":"Mebane Chiropractic",
    "wof:placetype":"venue"
},
  "geometry": {"coordinates":[-79.30177999999999,36.099038],"type":"Point"}
}