{
  "type": "Feature",
  "properties": {
    "iso:country":"US",
    "sg:address":"4132 Maple Springs Dr",
    "sg:city":"Apex",
    "sg:classifiers":[
        {
            "category":"Shopping",
            "subcategory":"Gifts & Souvenirs",
            "type":"Retail Goods"
        }
    ],
    "sg:phone":"+1 919 387 1467",
    "sg:postcode":"27523",
    "sg:province":"NC",
    "wof:name":"Ceramic Images",
    "wof:placetype":"venue"
},
  "geometry": {"coordinates":[-78.92128,35.777187],"type":"Point"}
}