{
  "type": "Feature",
  "properties": {
    "iso:country":"US",
    "sg:address":"1911 Associates Ln",
    "sg:city":"Charlotte",
    "sg:classifiers":[
        {
            "category":"Wholesale",
            "subcategory":"Machinery & Supplies",
            "type":"Manufacturing & Wholesale Goods"
        }
    ],
    "sg:phone":"+1 704 392 9448",
    "sg:postcode":"28217",
    "sg:province":"NC",
    "sg:tags":[
        "spraying",
        "equipment"
    ],
    "sg:website":"www.spray.com",
    "wof:name":"Spraying Systems Co",
    "wof:placetype":"venue"
},
  "geometry": {"coordinates":[-80.930491,35.176522],"type":"Point"}
}