{
  "type": "Feature",
  "properties": {
    "iso:country":"US",
    "sg:address":"6750 Brevard Rd",
    "sg:city":"Etowah",
    "sg:classifiers":[
        {
            "category":"Building & Trades",
            "subcategory":"Construction",
            "type":"Services"
        }
    ],
    "sg:phone":"+1 828 890 0115",
    "sg:postcode":"28729",
    "sg:province":"NC",
    "sg:tags":[
        "concrete",
        "contractor"
    ],
    "wof:name":"Foundation Specialties",
    "wof:placetype":"venue"
},
  "geometry": {"coordinates":[-82.60772,35.314172],"type":"Point"}
}