{
  "type": "Feature",
  "properties": {
    "iso:country":"US",
    "sg:address":"4017 Chesapeake Dr",
    "sg:city":"Charlotte",
    "sg:classifiers":[
        {
            "category":"Retail",
            "subcategory":"Repair Shop",
            "type":"Services"
        }
    ],
    "sg:phone":"+1   ",
    "sg:postcode":"28216",
    "sg:province":"NC",
    "wof:name":"RJP Truck Parts & Repair",
    "wof:placetype":"venue"
},
  "geometry": {"coordinates":[-80.87321300000001,35.27408],"type":"Point"}
}