{
  "type": "Feature",
  "properties": {
    "iso:country":"US",
    "sg:address":"231 W Main St",
    "sg:city":"Brevard",
    "sg:classifiers":[
        {
            "category":"Social Services",
            "subcategory":"Child Care",
            "type":"Services"
        }
    ],
    "sg:phone":"+1   ",
    "sg:postcode":"28712",
    "sg:province":"NC",
    "sg:tags":[
        "day"
    ],
    "wof:name":"Bright Beginnings",
    "wof:placetype":"venue"
},
  "geometry": {"coordinates":[-82.73665,35.234873],"type":"Point"}
}