{
  "type": "Feature",
  "properties": {
    "iso:country":"US",
    "sg:address":"608 E Water St",
    "sg:city":"Lincolnton",
    "sg:classifiers":[
        {
            "category":"Personal",
            "subcategory":"Barber",
            "type":"Services"
        }
    ],
    "sg:phone":"+1   ",
    "sg:postcode":"28092",
    "sg:province":"NC",
    "sg:tags":[
        "shop",
        "beauty"
    ],
    "wof:name":"Vincent Hair Studio",
    "wof:placetype":"venue"
},
  "geometry": {"coordinates":[-81.24781400000001,35.473458],"type":"Point"}
}