{
  "type": "Feature",
  "properties": {
    "iso:country":"US",
    "sg:address":"700 E Parker Rd",
    "sg:city":"Morganton",
    "sg:classifiers":[
        {
            "category":"Education",
            "subcategory":"School",
            "type":"Public Place"
        }
    ],
    "sg:phone":"+1 828 439 4312",
    "sg:postcode":"28655",
    "sg:province":"NC",
    "wof:name":"Burke County School Supt",
    "wof:placetype":"venue"
},
  "geometry": {"coordinates":[-81.64637399999999,35.725775],"type":"Point"}
}