{
  "type": "Feature",
  "properties": {
    "addr:full":"5000 Lindstrom Dr Charlotte NC 28226",
    "addr:housenumber":"5000",
    "addr:postcode":"28226",
    "addr:street":"Lindstrom Dr",
    "iso:country":"US",
    "sg:address":"5000 Lindstrom Dr",
    "sg:city":"Charlotte",
    "sg:classifiers":[
        {
            "category":"Building & Trades",
            "subcategory":"Construction",
            "type":"Services"
        }
    ],
    "sg:phone":"+1 704 540 4337",
    "sg:postcode":"28226",
    "sg:province":"NC",
    "sg:tags":[
        "general",
        "contractor"
    ],
    "wof:name":"Lighthouse Construction Of NC",
    "wof:placetype":"venue"
},
  "geometry": {"coordinates":[-80.837942,35.106095],"type":"Point"}
}