{
  "type": "Feature",
  "properties": {
    "iso:country":"US",
    "sg:address":"1111 Central Ave",
    "sg:city":"Charlotte",
    "sg:classifiers":[
        {
            "category":"Recreation",
            "type":"Entertainment"
        }
    ],
    "sg:phone":"+1 704 333 5024",
    "sg:postcode":"28204",
    "sg:province":"NC",
    "sg:tags":[
        "instruction",
        "yoga"
    ],
    "wof:name":"Bodhi Tree Yoga Studio",
    "wof:placetype":"venue"
},
  "geometry": {"coordinates":[-80.819727,35.221622],"type":"Point"}
}