{
  "type": "Feature",
  "properties": {
    "iso:country":"US",
    "sg:address":"2925 Beatties Ford Rd",
    "sg:city":"Charlotte",
    "sg:classifiers":[
        {
            "category":"Shopping",
            "type":"Retail Goods"
        }
    ],
    "sg:phone":"+1 704 392 8100",
    "sg:postcode":"28216",
    "sg:province":"NC",
    "sg:tags":[
        "banner"
    ],
    "sg:website":"www.churchsigns.com",
    "wof:name":"Churchsigns",
    "wof:placetype":"venue"
},
  "geometry": {"coordinates":[-80.85491500000001,35.27521],"type":"Point"}
}