{
  "type": "Feature",
  "properties": {
    "iso:country":"US",
    "sg:address":"808 S 3rd St",
    "sg:city":"Smithfield",
    "sg:classifiers":[
        {
            "category":"Wholesale",
            "subcategory":"Machinery & Supplies",
            "type":"Manufacturing & Wholesale Goods"
        }
    ],
    "sg:phone":"+1 919 938 1113",
    "sg:postcode":"27577",
    "sg:province":"NC",
    "sg:tags":[
        "salon",
        "beauty"
    ],
    "wof:name":"Decarious Beauty Supply",
    "wof:placetype":"venue"
},
  "geometry": {"coordinates":[-78.351122,35.501504],"type":"Point"}
}