{
  "type": "Feature",
  "properties": {
    "iso:country":"US",
    "sg:address":"104 N Cherry St",
    "sg:city":"Cherryville",
    "sg:classifiers":[
        {
            "category":"Restaurant",
            "type":"Food & Drink"
        }
    ],
    "sg:menulink":"http://www.allmenus.com/nc/cherryville/229359-hong-kong/menu/",
    "sg:phone":"+1 704 435 2888",
    "sg:postcode":"28021",
    "sg:province":"NC",
    "sg:tags":[
        "asian",
        "chinese"
    ],
    "wof:name":"Hong Kong",
    "wof:placetype":"venue"
},
  "geometry": {"coordinates":[-81.367847,35.38298],"type":"Point"}
}