{
  "type": "Feature",
  "properties": {
    "addr:full":"2317 S 17th St Wilmington NC 28401",
    "addr:housenumber":"2317",
    "addr:postcode":"28401",
    "addr:street":"S 17Th St",
    "iso:country":"US",
    "sg:address":"2317 S 17th St",
    "sg:city":"Wilmington",
    "sg:classifiers":[
        {
            "category":"Restaurant",
            "type":"Food & Drink"
        }
    ],
    "sg:phone":"+1 910 794 1764",
    "sg:postcode":"28401",
    "sg:province":"NC",
    "wof:name":"Original 17th Street Deli",
    "wof:placetype":"venue"
},
  "geometry": {"coordinates":[-77.922738,34.201653],"type":"Point"}
}