{
  "type": "Feature",
  "properties": {
    "iso:country":"US",
    "sg:address":"2274 Golden Gate Dr",
    "sg:city":"Greensboro",
    "sg:classifiers":[
        {
            "category":"Personal",
            "subcategory":"Beauty Salon",
            "type":"Services"
        }
    ],
    "sg:phone":"+1 336 274 2555",
    "sg:postcode":"27405",
    "sg:province":"NC",
    "wof:name":"Alexander's Design & Co",
    "wof:placetype":"venue"
},
  "geometry": {"coordinates":[-79.784313,36.102728],"type":"Point"}
}