{
  "type": "Feature",
  "properties": {
    "addr:full":"110 W Market St Elkin NC 28621",
    "addr:housenumber":"110",
    "addr:postcode":"28621",
    "addr:street":"W Market St",
    "iso:country":"US",
    "sg:address":"110 W Market St",
    "sg:city":"Elkin",
    "sg:classifiers":[
        {
            "category":"Banks & Credit Unions",
            "subcategory":"Bank",
            "type":"Services"
        }
    ],
    "sg:phone":"+1 336 526 6301",
    "sg:postcode":"28621",
    "sg:province":"NC",
    "sg:website":"www.yadkinvalleybank.com",
    "wof:name":"Yadkin Valley Bank & Trust Co",
    "wof:placetype":"venue"
},
  "geometry": {"coordinates":[-80.85103700000001,36.244844],"type":"Point"}
}