{
  "type": "Feature",
  "properties": {
    "iso:country":"US",
    "sg:address":"212 Stratford Dr",
    "sg:city":"Chapel Hill",
    "sg:classifiers":[
        {
            "category":"Professional",
            "subcategory":"Research",
            "type":"Services"
        },
        {
            "category":"Professional",
            "subcategory":"Management & Consulting",
            "type":"Services"
        }
    ],
    "sg:phone":"+1 919 942 9633",
    "sg:postcode":"27516",
    "sg:province":"NC",
    "wof:name":"Platinum Research Consultants",
    "wof:placetype":"venue"
},
  "geometry": {"coordinates":[-79.096068,35.937831],"type":"Point"}
}