{
  "type": "Feature",
  "properties": {
    "addr:full":"16060 Bee Tree Ln Wagram NC 28396",
    "addr:housenumber":"16060",
    "addr:postcode":"28396",
    "addr:street":"Bee Tree Ln",
    "iso:country":"US",
    "sg:address":"16060 Bee Tree Ln",
    "sg:city":"Wagram",
    "sg:classifiers":[
        {
            "category":"Shopping",
            "type":"Retail Goods"
        }
    ],
    "sg:phone":"+1 910 369 0275",
    "sg:postcode":"28396",
    "sg:province":"NC",
    "sg:tags":[
        "miscellaneous",
        "store"
    ],
    "wof:name":"J & E Dinkins Inc",
    "wof:placetype":"venue"
},
  "geometry": {"coordinates":[-79.43429399999999,34.958895],"type":"Point"}
}