{
  "type": "Feature",
  "properties": {
    "addr:full":"209 Elisha Dr Wilmington NC 28405",
    "addr:housenumber":"209",
    "addr:postcode":"28405",
    "addr:street":"Elisha Dr",
    "iso:country":"US",
    "sg:address":"209 Elisha Dr",
    "sg:city":"Wilmington",
    "sg:classifiers":[
        {
            "category":"Professional",
            "subcategory":"Advertising",
            "type":"Services"
        }
    ],
    "sg:phone":"+1   ",
    "sg:postcode":"28405",
    "sg:province":"NC",
    "sg:tags":[
        "agency"
    ],
    "wof:name":"Aardvark Advertising Inc",
    "wof:placetype":"venue"
},
  "geometry": {"coordinates":[-77.843745,34.247272],"type":"Point"}
}