{
  "type": "Feature",
  "properties": {
    "addr:full":"7735 University City Blvd Charlotte NC 28213",
    "addr:housenumber":"7735",
    "addr:postcode":"28213",
    "addr:street":"University City Blvd",
    "iso:country":"US",
    "sg:address":"7735 University City Blvd",
    "sg:city":"Charlotte",
    "sg:classifiers":[
        {
            "category":"Travel",
            "subcategory":"Hotels & Motels",
            "type":"Entertainment"
        }
    ],
    "sg:phone":"+1 704 547 0049",
    "sg:postcode":"28213",
    "sg:province":"NC",
    "sg:tags":[
        "lodging"
    ],
    "sg:website":"http://www.comfortsuites.com/hotel-charlotte-north_carolina-NC046",
    "wof:name":"Comfort Suites University Area Charlotte",
    "wof:placetype":"venue"
},
  "geometry": {"coordinates":[-80.753443,35.291695],"type":"Point"}
}