{
  "type": "Feature",
  "properties": {
    "addr:full":"6340 Burnt Poplar Rd Greensboro NC 27409",
    "addr:housenumber":"6340",
    "addr:postcode":"27409",
    "addr:street":"Burnt Poplar Rd",
    "iso:country":"US",
    "sg:address":"6340 Burnt Poplar Rd",
    "sg:city":"Greensboro",
    "sg:classifiers":[
        {
            "category":"Wholesale",
            "subcategory":"Auto Parts",
            "type":"Manufacturing & Wholesale Goods"
        }
    ],
    "sg:phone":"+1 336 370 0691",
    "sg:postcode":"27409",
    "sg:province":"NC",
    "wof:name":"Carolina Bumper",
    "wof:placetype":"venue"
},
  "geometry": {"coordinates":[-79.93932599999999,36.075164],"type":"Point"}
}