{
  "type": "Feature",
  "properties": {
    "iso:country":"US",
    "sg:address":"15 S 2nd St",
    "sg:city":"Wilmington",
    "sg:classifiers":[
        {
            "category":"Real Estate",
            "subcategory":"Architect",
            "type":"Services"
        }
    ],
    "sg:phone":"+1 910 343 0660",
    "sg:postcode":"28401",
    "sg:province":"NC",
    "sg:tags":[
        "architectural",
        "business"
    ],
    "wof:name":"Ligon B Flynn Architects",
    "wof:placetype":"venue"
},
  "geometry": {"coordinates":[-77.947326,34.235279],"type":"Point"}
}