{
  "type": "Feature",
  "properties": {
    "addr:full":"919 Fitzgerald St Monroe NC 28112",
    "addr:housenumber":"919",
    "addr:postcode":"28112",
    "addr:street":"Fitzgerald St",
    "iso:country":"US",
    "sg:address":"919 Fitzgerald St",
    "sg:city":"Monroe",
    "sg:classifiers":[
        {
            "category":"Social Services",
            "type":"Services"
        },
        {
            "category":"Health Services",
            "subcategory":"Nursing And Care Facility",
            "type":"Services"
        }
    ],
    "sg:phone":"+1 704 225 9556",
    "sg:postcode":"28112",
    "sg:province":"NC",
    "sg:tags":[
        "alzheimer's",
        "senior",
        "intermediate",
        "citizen"
    ],
    "sg:website":"http://www.brookdaleliving.com",
    "wof:name":"Discovery Program At Monroe Square",
    "wof:placetype":"venue"
},
  "geometry": {"coordinates":[-80.521935,34.972614],"type":"Point"}
}