{
  "type": "Feature",
  "properties": {
    "iso:country":"US",
    "sg:address":"227 Hardin St",
    "sg:city":"Boone",
    "sg:classifiers":[
        {
            "category":"Cafe",
            "type":"Food & Drink"
        }
    ],
    "sg:menulink":"http://www.allmenus.com/nc/stony-fork/291681-red-onion-cafe/menu/",
    "sg:phone":"+1 828 264 5470",
    "sg:postcode":"28607",
    "sg:province":"NC",
    "sg:tags":[
        "american"
    ],
    "wof:name":"Red Onion Cafe",
    "wof:placetype":"venue"
},
  "geometry": {"coordinates":[-81.56197899999999,36.235582],"type":"Point"}
}