{
  "type": "Feature",
  "properties": {
    "iso:country":"US",
    "sg:address":"2784 Zacks Fork Rd",
    "sg:city":"Lenoir",
    "sg:classifiers":[
        {
            "category":"Food & Beverages",
            "subcategory":"Groceries & Convenience Stores",
            "type":"Retail Goods"
        }
    ],
    "sg:phone":"+1 828 758 4418",
    "sg:postcode":"28645",
    "sg:province":"NC",
    "wof:name":"Ricky Greene Garage",
    "wof:placetype":"venue"
},
  "geometry": {"coordinates":[-81.428759,36.011383],"type":"Point"}
}