{
  "type": "Feature",
  "properties": {
    "addr:full":"124 Saint Jones Rd Knightdale NC 27589",
    "addr:housenumber":"124",
    "addr:postcode":"27589",
    "addr:street":"Saint Jones Rd",
    "iso:country":"US",
    "sg:address":"124 Saint Jones Rd",
    "sg:city":"Knightdale",
    "sg:classifiers":[
        {
            "category":"Organizations",
            "subcategory":"Religious Organization",
            "type":"Services"
        }
    ],
    "sg:phone":"+1   ",
    "sg:postcode":"27589",
    "sg:province":"NC",
    "sg:website":"www.sonview.org",
    "wof:name":"Sonview Baptist Church",
    "wof:placetype":"venue"
},
  "geometry": {"coordinates":[-77.981898,36.262455],"type":"Point"}
}