{
  "type": "Feature",
  "properties": {
    "addr:full":"8151 Spearman Rd Browns Summit NC 27214",
    "addr:housenumber":"8151",
    "addr:postcode":"27214",
    "addr:street":"Spearman Rd",
    "iso:country":"US",
    "sg:address":"8151 Spearman Rd",
    "sg:city":"Browns Summit",
    "sg:classifiers":[
        {
            "category":"Farming",
            "subcategory":"Farm",
            "type":"Manufacturing & Wholesale Goods"
        }
    ],
    "sg:phone":"+1 336 656 7309",
    "sg:postcode":"27214",
    "sg:province":"NC",
    "wof:name":"Oakmere Farm",
    "wof:placetype":"venue"
},
  "geometry": {"coordinates":[-79.755985,36.233006],"type":"Point"}
}