{
  "type": "Feature",
  "properties": {
    "addr:full":"5529 Cottage Cove Ln Charlotte NC 28215",
    "addr:housenumber":"5529",
    "addr:postcode":"28215",
    "addr:street":"Cottage Cove Ln",
    "iso:country":"US",
    "sg:address":"5529 Cottage Cove Ln",
    "sg:city":"Charlotte",
    "sg:classifiers":[
        {
            "category":"Health Services",
            "subcategory":"Hospital",
            "type":"Services"
        }
    ],
    "sg:phone":"+1 704 535 3009",
    "sg:postcode":"28215",
    "sg:province":"NC",
    "sg:tags":[
        "mental"
    ],
    "wof:name":"Scholars Inc",
    "wof:placetype":"venue"
},
  "geometry": {"coordinates":[-80.754284,35.243468],"type":"Point"}
}