{
  "type": "Feature",
  "properties": {
    "addr:full":"214 Drummer Kellum Rd Jacksonville NC 28546",
    "addr:housenumber":"214",
    "addr:postcode":"28546",
    "addr:street":"Drummer Kellum Rd",
    "iso:country":"US",
    "sg:address":"214 Drummer Kellum Rd",
    "sg:city":"Jacksonville",
    "sg:classifiers":[
        {
            "category":"Building & Trades",
            "subcategory":"Construction",
            "type":"Services"
        }
    ],
    "sg:phone":"+1 910 346 9075",
    "sg:postcode":"28546",
    "sg:province":"NC",
    "sg:tags":[
        "insulation",
        "heat",
        "contractor"
    ],
    "wof:name":"Down East Insulation",
    "wof:placetype":"venue"
},
  "geometry": {"coordinates":[-77.376637,34.797621],"type":"Point"}
}