{
  "type": "Feature",
  "properties": {
    "addr:full":"1365 Kerner Rd Kernersville NC 27284",
    "addr:housenumber":"1365",
    "addr:postcode":"27284",
    "addr:street":"Kerner Rd",
    "iso:country":"US",
    "sg:address":"1365 Kerner Rd",
    "sg:city":"Kernersville",
    "sg:classifiers":[
        {
            "category":"Building & Trades",
            "subcategory":"Electrical",
            "type":"Services"
        }
    ],
    "sg:phone":"+1 336 993 0771",
    "sg:postcode":"27284",
    "sg:province":"NC",
    "sg:tags":[
        "electric",
        "contractor"
    ],
    "wof:name":"Electrical South Electrical",
    "wof:placetype":"venue"
},
  "geometry": {"coordinates":[-80.08166199999999,36.153871],"type":"Point"}
}