{
  "type": "Feature",
  "properties": {
    "iso:country":"US",
    "sg:address":"805 Newsome Rd",
    "sg:city":"Salisbury",
    "sg:classifiers":[
        {
            "category":"Real Estate",
            "subcategory":"Real Estate Operator",
            "type":"Services"
        }
    ],
    "sg:phone":"+1 704 797 0314",
    "sg:postcode":"28146",
    "sg:province":"NC",
    "sg:tags":[
        "building",
        "apartment"
    ],
    "wof:name":"Whispering Oaks LLC",
    "wof:placetype":"venue"
},
  "geometry": {"coordinates":[-80.44869799999999,35.657435],"type":"Point"}
}