{
  "type": "Feature",
  "properties": {
    "addr:full":"75 S Elliott Rd Chapel Hill NC 27514",
    "addr:housenumber":"75",
    "addr:postcode":"27514",
    "addr:street":"S Elliott Rd",
    "iso:country":"US",
    "sg:address":"75 S Elliott Rd",
    "sg:city":"Chapel Hill",
    "sg:classifiers":[
        {
            "category":"Professional",
            "type":"Services"
        }
    ],
    "sg:phone":"+1 919 967 9108",
    "sg:postcode":"27514",
    "sg:province":"NC",
    "sg:tags":[
        "writer"
    ],
    "wof:name":"Ross Pipes & Assoc Inc",
    "wof:placetype":"venue"
},
  "geometry": {"coordinates":[-79.02847300000001,35.934278],"type":"Point"}
}