{
  "type": "Feature",
  "properties": {
    "iso:country":"US",
    "sg:address":"9700 David Taylor Dr",
    "sg:city":"Charlotte",
    "sg:classifiers":[
        {
            "category":"Farming",
            "subcategory":"Poultry Farm",
            "type":"Manufacturing & Wholesale Goods"
        }
    ],
    "sg:phone":"+1 704 788 2188",
    "sg:postcode":"28262",
    "sg:province":"NC",
    "sg:tags":[
        "hatchery",
        "chicken"
    ],
    "wof:name":"Perdue Farms Incorporated",
    "wof:placetype":"venue"
},
  "geometry": {"coordinates":[-80.755366,35.324413],"type":"Point"}
}