{
  "type": "Feature",
  "properties": {
    "addr:full":"4483 Spies Rd Star NC 27356",
    "addr:housenumber":"4483",
    "addr:postcode":"27356",
    "addr:street":"Spies Rd",
    "iso:country":"US",
    "sg:address":"4483 Spies Rd",
    "sg:city":"Star",
    "sg:classifiers":[
        {
            "category":"Manufacturing",
            "subcategory":"Paper Products",
            "type":"Manufacturing & Wholesale Goods"
        }
    ],
    "sg:phone":"+1 910 428 9048",
    "sg:postcode":"27356",
    "sg:province":"NC",
    "sg:tags":[
        "pulp"
    ],
    "wof:name":"Cotton Creek Chip Co",
    "wof:placetype":"venue"
},
  "geometry": {"coordinates":[-79.72096000000001,35.407792],"type":"Point"}
}