{
  "type": "Feature",
  "properties": {
    "iso:country":"US",
    "sg:address":"2951 State Hwy 222 E",
    "sg:city":"Kenly",
    "sg:classifiers":[
        {
            "category":"Real Estate",
            "subcategory":"Real Estate Agent",
            "type":"Services"
        }
    ],
    "sg:phone":"+1 919 284 6683",
    "sg:postcode":"27542",
    "sg:province":"NC",
    "wof:name":"Green Valley Realty",
    "wof:placetype":"venue"
},
  "geometry": {"coordinates":[-78.098921,35.579064],"type":"Point"}
}