{
  "type": "Feature",
  "properties": {
    "addr:full":"3515 Monroe Rd Charlotte NC 28205",
    "addr:housenumber":"3515",
    "addr:postcode":"28205",
    "addr:street":"Monroe Rd",
    "iso:country":"US",
    "sg:address":"3515 Monroe Rd",
    "sg:city":"Charlotte",
    "sg:classifiers":[
        {
            "category":"Education",
            "subcategory":"Special Training",
            "type":"Public Place"
        }
    ],
    "sg:phone":"+1 704 376 1930",
    "sg:postcode":"28205",
    "sg:province":"NC",
    "sg:tags":[
        "tutoring"
    ],
    "wof:name":"Reading Connection-Mind Gym",
    "wof:placetype":"venue"
},
  "geometry": {"coordinates":[-80.796803,35.200527],"type":"Point"}
}