{
  "type": "Feature",
  "properties": {
    "addr:full":"4638 Capital Blvd Raleigh NC 27604",
    "addr:housenumber":"4638",
    "addr:postcode":"27604",
    "addr:street":"Capital Blvd",
    "iso:country":"US",
    "sg:address":"4638 Capital Blvd",
    "sg:city":"Raleigh",
    "sg:classifiers":[
        {
            "category":"Restaurant",
            "type":"Food & Drink"
        }
    ],
    "sg:menulink":"http://www.allmenus.com/nc/neuse/28141-lees-kitchen/menu/",
    "sg:phone":"+1 919 872 7422",
    "sg:postcode":"27604",
    "sg:province":"NC",
    "sg:tags":[
        "jamaican"
    ],
    "wof:name":"Lee's Kitchen",
    "wof:placetype":"venue"
},
  "geometry": {"coordinates":[-78.58026099999999,35.848194],"type":"Point"}
}