{
  "type": "Feature",
  "properties": {
    "iso:country":"US",
    "sg:address":"10610 Independence Pointe Pkwy",
    "sg:city":"Matthews",
    "sg:classifiers":[
        {
            "category":"Health Services",
            "subcategory":"Chiropractor",
            "type":"Services"
        }
    ],
    "sg:phone":"+1 704 849 9393",
    "sg:postcode":"28105",
    "sg:province":"NC",
    "sg:website":"www.charlottechiropractic.com",
    "wof:name":"Independence Pointe Chiro",
    "wof:placetype":"venue"
},
  "geometry": {"coordinates":[-80.708135,35.122562],"type":"Point"}
}