{
  "type": "Feature",
  "properties": {
    "iso:country":"US",
    "sg:address":"451 Catawba Valley Blvd SE",
    "sg:city":"Hickory",
    "sg:classifiers":[
        {
            "category":"Education",
            "subcategory":"School",
            "type":"Public Place"
        }
    ],
    "sg:phone":"+1 828 328 2289",
    "sg:postcode":"28602",
    "sg:province":"NC",
    "wof:name":"Grandview Middle School",
    "wof:placetype":"venue"
},
  "geometry": {"coordinates":[-81.331181,35.702907],"type":"Point"}
}