{
  "type": "Feature",
  "properties": {
    "iso:country":"US",
    "sg:address":"3400 Ramsey St",
    "sg:city":"Fayetteville",
    "sg:classifiers":[
        {
            "category":"Food & Beverages",
            "subcategory":"Groceries & Convenience Stores",
            "type":"Retail Goods"
        }
    ],
    "sg:phone":"+1 910 822 6842",
    "sg:postcode":"28311",
    "sg:province":"NC",
    "sg:tags":[
        "grocer"
    ],
    "wof:name":"Short Stop Food Mart",
    "wof:placetype":"venue"
},
  "geometry": {"coordinates":[-78.878665,35.106674],"type":"Point"}
}