{
  "type": "Feature",
  "properties": {
    "iso:country":"US",
    "sg:address":"1907 Martin Luther King Dr",
    "sg:city":"Elizabethtown",
    "sg:classifiers":[
        {
            "category":"Freight",
            "type":"Transportation"
        }
    ],
    "sg:phone":"+1 910 862 4856",
    "sg:postcode":"28337",
    "sg:province":"NC",
    "sg:tags":[
        "operator",
        "local",
        "trucking"
    ],
    "wof:name":"Lesane & Sons Trucking Inc",
    "wof:placetype":"venue"
},
  "geometry": {"coordinates":[-78.6216,34.615733],"type":"Point"}
}