{
  "type": "Feature",
  "properties": {
    "iso:country":"US",
    "sg:address":"4801 Six Forks Rd",
    "sg:city":"Raleigh",
    "sg:classifiers":[
        {
            "category":"Social Services",
            "subcategory":"Child Care",
            "type":"Services"
        }
    ],
    "sg:phone":"+1 919 787 1832",
    "sg:postcode":"27609",
    "sg:province":"NC",
    "sg:tags":[
        "kindergarten",
        "academic",
        "school"
    ],
    "sg:website":"www.stmarkspreschool.org",
    "wof:name":"St Mark's Methodist Preschool",
    "wof:placetype":"venue"
},
  "geometry": {"coordinates":[-78.644041,35.84569],"type":"Point"}
}