{
  "type": "Feature",
  "properties": {
    "iso:country":"US",
    "sg:address":"314 W Main St",
    "sg:city":"Clayton",
    "sg:classifiers":[
        {
            "category":"Shopping",
            "type":"Retail Goods"
        }
    ],
    "sg:phone":"+1 919 553 7635",
    "sg:postcode":"27520",
    "sg:province":"NC",
    "sg:tags":[
        "merchandise"
    ],
    "wof:name":"Sy Shop Inc",
    "wof:placetype":"venue"
},
  "geometry": {"coordinates":[-78.462817,35.655616],"type":"Point"}
}