{
  "type": "Feature",
  "properties": {
    "addr:full":"2601 Valley Woods Ct Raleigh NC 27613",
    "addr:housenumber":"2601",
    "addr:postcode":"27613",
    "addr:street":"Valley Woods Ct",
    "iso:country":"US",
    "sg:address":"2601 Valley Woods Ct",
    "sg:city":"Raleigh",
    "sg:classifiers":[
        {
            "category":"Professional",
            "subcategory":"Art Services",
            "type":"Services"
        }
    ],
    "sg:phone":"+1   ",
    "sg:postcode":"27613",
    "sg:province":"NC",
    "sg:tags":[
        "photography",
        "commercial"
    ],
    "wof:name":"Fred Reno",
    "wof:placetype":"venue"
},
  "geometry": {"coordinates":[-78.68520599999999,35.873832],"type":"Point"}
}