{
  "type": "Feature",
  "properties": {
    "iso:country":"US",
    "sg:address":"1408 Jenks Carpenter Rd",
    "sg:city":"Cary",
    "sg:classifiers":[
        {
            "category":"Retail",
            "subcategory":"Repair Shop",
            "type":"Services"
        }
    ],
    "sg:phone":"+1 919 467 5282",
    "sg:postcode":"27519",
    "sg:province":"NC",
    "sg:tags":[
        "appliance"
    ],
    "wof:name":"ABC Appliance Repair",
    "wof:placetype":"venue"
},
  "geometry": {"coordinates":[-78.858785,35.781702],"type":"Point"}
}