{
  "type": "Feature",
  "properties": {
    "addr:full":"202 Old Mill Dr Summerfield NC 27358",
    "addr:housenumber":"202",
    "addr:postcode":"27358",
    "addr:street":"Old Mill Dr",
    "iso:country":"US",
    "sg:address":"202 Old Mill Dr",
    "sg:city":"Summerfield",
    "sg:classifiers":[
        {
            "category":"Freight",
            "type":"Transportation"
        }
    ],
    "sg:phone":"+1 336 643 8368",
    "sg:postcode":"27358",
    "sg:province":"NC",
    "sg:tags":[
        "operator",
        "local",
        "trucking"
    ],
    "wof:name":"R&J Xpress Inc",
    "wof:placetype":"venue"
},
  "geometry": {"coordinates":[-79.88644499999999,36.257151],"type":"Point"}
}