{
  "type": "Feature",
  "properties": {
    "iso:country":"US",
    "sg:address":"133 E New Hampshire Ave",
    "sg:city":"Southern Pines",
    "sg:classifiers":[
        {
            "category":"Bars & Pubs",
            "type":"Food & Drink"
        }
    ],
    "sg:phone":"+1 910 695 1915",
    "sg:postcode":"28387",
    "sg:province":"NC",
    "sg:tags":[
        "drinking"
    ],
    "wof:name":"O Donnell S Pub",
    "wof:placetype":"venue"
},
  "geometry": {"coordinates":[-79.390237,35.174188],"type":"Point"}
}