{
  "type": "Feature",
  "properties": {
    "addr:full":"702 W Green St Franklinton NC 27525",
    "addr:housenumber":"702",
    "addr:postcode":"27525",
    "addr:street":"W Green St",
    "iso:country":"US",
    "sg:address":"702 W Green St",
    "sg:city":"Franklinton",
    "sg:classifiers":[
        {
            "category":"Building & Trades",
            "subcategory":"Construction",
            "type":"Services"
        }
    ],
    "sg:phone":"+1 919 494 2440",
    "sg:postcode":"27525",
    "sg:province":"NC",
    "sg:tags":[
        "water",
        "well",
        "drilling"
    ],
    "wof:name":"Durwood Davis Well Drilling",
    "wof:placetype":"venue"
},
  "geometry": {"coordinates":[-78.480996,36.112582],"type":"Point"}
}