{
  "type": "Feature",
  "properties": {
    "iso:country":"US",
    "sg:address":"4208 Windsor Pl",
    "sg:city":"Raleigh",
    "sg:classifiers":[
        {
            "category":"Professional",
            "type":"Services"
        }
    ],
    "sg:phone":"+1 919 329 0880",
    "sg:postcode":"27609",
    "sg:province":"NC",
    "sg:tags":[
        "establishment"
    ],
    "wof:name":"Directional Sign Placement",
    "wof:placetype":"venue"
},
  "geometry": {"coordinates":[-78.631336,35.839615],"type":"Point"}
}