{
  "type": "Feature",
  "properties": {
    "iso:country":"US",
    "sg:address":"7421 Carmel Executive Park Dr",
    "sg:city":"Charlotte",
    "sg:classifiers":[
        {
            "category":"Professional",
            "subcategory":"Lawyer & Legal Services",
            "type":"Services"
        }
    ],
    "sg:phone":"+1   ",
    "sg:postcode":"28226",
    "sg:province":"NC",
    "wof:name":"Robert G Hoefling Atty",
    "wof:placetype":"venue"
},
  "geometry": {"coordinates":[-80.84470899999999,35.088975],"type":"Point"}
}