{
  "type": "Feature",
  "properties": {
    "iso:country":"US",
    "sg:address":"401 Hawthorne Ln Ste 1101",
    "sg:city":"Charlotte",
    "sg:classifiers":[
        {
            "category":"Manufacturing",
            "subcategory":"Wood Products",
            "type":"Manufacturing & Wholesale Goods"
        }
    ],
    "sg:phone":"+1 704 662 8388",
    "sg:postcode":"28204",
    "sg:province":"NC",
    "sg:tags":[
        "millwork-wholesale",
        "millwork",
        "manufacturer"
    ],
    "wof:name":"Derbys Woodworks",
    "wof:placetype":"venue"
},
  "geometry": {"coordinates":[-80.822113,35.215778],"type":"Point"}
}