{
  "type": "Feature",
  "properties": {
    "iso:country":"US",
    "sg:address":"17925 Kings Point Dr",
    "sg:city":"Cornelius",
    "sg:classifiers":[
        {
            "category":"Wholesale",
            "subcategory":"Chemicals & Plastics",
            "type":"Manufacturing & Wholesale Goods"
        }
    ],
    "sg:phone":"+1 704 655 0988",
    "sg:postcode":"28031",
    "sg:province":"NC",
    "wof:name":"First Film Extruding",
    "wof:placetype":"venue"
},
  "geometry": {"coordinates":[-80.89139900000001,35.458309],"type":"Point"}
}