{
  "type": "Feature",
  "properties": {
    "addr:full":"5317 Greyfield Blvd Durham NC 27713",
    "addr:housenumber":"5317",
    "addr:postcode":"27713",
    "addr:street":"Greyfield Blvd",
    "iso:country":"US",
    "sg:address":"5317 Greyfield Blvd",
    "sg:city":"Durham",
    "sg:classifiers":[
        {
            "category":"Building & Trades",
            "subcategory":"Electrical",
            "type":"Services"
        }
    ],
    "sg:phone":"+1 919 401 5252",
    "sg:postcode":"27713",
    "sg:province":"NC",
    "sg:tags":[
        "electric",
        "contractor"
    ],
    "wof:name":"George Moore Electrical",
    "wof:placetype":"venue"
},
  "geometry": {"coordinates":[-78.927589,35.936778],"type":"Point"}
}