{
  "type": "Feature",
  "properties": {
    "addr:full":"220 N Maple St Graham NC 27253",
    "addr:housenumber":"220",
    "addr:postcode":"27253",
    "addr:street":"N Maple St",
    "iso:country":"US",
    "sg:address":"220 N Maple St",
    "sg:city":"Graham",
    "sg:classifiers":[
        {
            "category":"Home & Garden",
            "subcategory":"Carpets & Floor Coverings",
            "type":"Retail Goods"
        }
    ],
    "sg:phone":"+1 336 221 0910",
    "sg:postcode":"27253",
    "sg:province":"NC",
    "sg:tags":[
        "dealer",
        "laying",
        "rug",
        "contractor"
    ],
    "wof:name":"Rodriquez Floor Covering",
    "wof:placetype":"venue"
},
  "geometry": {"coordinates":[-79.402062,36.071937],"type":"Point"}
}