{
  "type": "Feature",
  "properties": {
    "addr:full":"620 N Modena St Gastonia NC 28054",
    "addr:housenumber":"620",
    "addr:postcode":"28054",
    "addr:street":"N Modena St",
    "iso:country":"US",
    "sg:address":"620 N Modena St",
    "sg:city":"Gastonia",
    "sg:classifiers":[
        {
            "category":"Professional",
            "type":"Services"
        }
    ],
    "sg:phone":"+1   ",
    "sg:postcode":"28054",
    "sg:province":"NC",
    "wof:name":"County Tree Service Inc",
    "wof:placetype":"venue"
},
  "geometry": {"coordinates":[-81.166297,35.271689],"type":"Point"}
}