{
  "type": "Feature",
  "properties": {
    "iso:country":"US",
    "sg:address":"102 Tawn Dr",
    "sg:city":"Burnsville",
    "sg:classifiers":[
        {
            "category":"Travel",
            "subcategory":"Hotels & Motels",
            "type":"Entertainment"
        }
    ],
    "sg:phone":"+1 828 682 2329",
    "sg:postcode":"28726",
    "sg:province":"NC",
    "sg:tags":[
        "breakfast",
        "accommodation",
        "bed"
    ],
    "sg:website":"www.nuwrayinn.com",
    "wof:name":"Nu-WRAY Inn",
    "wof:placetype":"venue"
},
  "geometry": {"coordinates":[-82.41754,35.288065],"type":"Point"}
}