{
  "type": "Feature",
  "properties": {
    "addr:full":"6901 Falls of Neuse Rd Raleigh NC 27615",
    "addr:housenumber":"6901",
    "addr:postcode":"27615",
    "addr:street":"Falls Of Neuse Rd",
    "iso:country":"US",
    "sg:address":"6901 Falls of Neuse Rd",
    "sg:city":"Raleigh",
    "sg:classifiers":[
        {
            "category":"Food & Beverages",
            "subcategory":"Groceries & Convenience Stores",
            "type":"Retail Goods"
        }
    ],
    "sg:phone":"+1 919 870 7427",
    "sg:postcode":"27615",
    "sg:province":"NC",
    "wof:name":"Fast Friendly Mart",
    "wof:placetype":"venue"
},
  "geometry": {"coordinates":[-78.62582399999999,35.881201],"type":"Point"}
}