{
  "type": "Feature",
  "properties": {
    "iso:country":"US",
    "sg:address":"302 Maple Creek Ct",
    "sg:city":"Apex",
    "sg:classifiers":[
        {
            "category":"Professional",
            "subcategory":"Computer Services",
            "type":"Services"
        }
    ],
    "sg:phone":"+1   ",
    "sg:postcode":"27502",
    "sg:province":"NC",
    "sg:tags":[
        "programing",
        "custom"
    ],
    "wof:name":"Killersoftware Llc",
    "wof:placetype":"venue"
},
  "geometry": {"coordinates":[-78.87988900000001,35.727712],"type":"Point"}
}