{
  "type": "Feature",
  "properties": {
    "addr:full":"104 N Elm St Greensboro NC 27401",
    "addr:housenumber":"104",
    "addr:postcode":"27401",
    "addr:street":"N Elm St",
    "iso:country":"US",
    "sg:address":"104 N Elm St",
    "sg:city":"Greensboro",
    "sg:classifiers":[
        {
            "category":"Personal",
            "subcategory":"Beauty Salon",
            "type":"Services"
        }
    ],
    "sg:phone":"+1 336 378 0155",
    "sg:postcode":"27401",
    "sg:province":"NC",
    "wof:name":"Tahiti Tan",
    "wof:placetype":"venue"
},
  "geometry": {"coordinates":[-79.79015200000001,36.073398],"type":"Point"}
}