{
  "type": "Feature",
  "properties": {
    "addr:full":"7660 Bud Davis Rd Vale NC 28168",
    "addr:postcode":"7660;28168",
    "addr:street":"Bud Davis Rd",
    "iso:country":"US",
    "sg:address":"7660 Bud Davis Rd",
    "sg:city":"Vale",
    "sg:classifiers":[
        {
            "category":"Social Services",
            "subcategory":"Child Care",
            "type":"Services"
        }
    ],
    "sg:phone":"+1   ",
    "sg:postcode":"28168",
    "sg:province":"NC",
    "sg:tags":[
        "day"
    ],
    "wof:name":"Lawn & Land Care By G&J LLC",
    "wof:placetype":"venue"
},
  "geometry": {"coordinates":[-81.445958,35.547173],"type":"Point"}
}