{
  "type": "Feature",
  "properties": {
    "iso:country":"US",
    "sg:address":"3159 Natal St",
    "sg:city":"Fayetteville",
    "sg:classifiers":[
        {
            "category":"Wholesale",
            "subcategory":"Machinery & Supplies",
            "type":"Manufacturing & Wholesale Goods"
        }
    ],
    "sg:phone":"+1 910 483 2544",
    "sg:postcode":"28306",
    "sg:province":"NC",
    "sg:tags":[
        "janitor"
    ],
    "wof:name":"Cape Fear Janitorial Supply",
    "wof:placetype":"venue"
},
  "geometry": {"coordinates":[-78.91869199999999,35.015394],"type":"Point"}
}