{
  "type": "Feature",
  "properties": {
    "iso:country":"US",
    "sg:address":"1928 River Knoll Dr",
    "sg:city":"Raleigh",
    "sg:classifiers":[
        {
            "category":"Banks & Credit Unions",
            "subcategory":"Financial Services",
            "type":"Services"
        }
    ],
    "sg:phone":"+1 919 231 0188",
    "sg:postcode":"27610",
    "sg:province":"NC",
    "sg:tags":[
        "investor"
    ],
    "wof:name":"Financial Freedom Investment C",
    "wof:placetype":"venue"
},
  "geometry": {"coordinates":[-78.546233,35.756807],"type":"Point"}
}