{
  "type": "Feature",
  "properties": {
    "addr:full":"186 Faw St Exd Millers Creek NC 28651",
    "addr:housenumber":"186",
    "addr:postcode":"28651",
    "addr:street":"Faw St Exd",
    "iso:country":"US",
    "sg:address":"186 Faw St Exd",
    "sg:city":"Millers Creek",
    "sg:classifiers":[
        {
            "category":"Retail",
            "subcategory":"Repair Shop",
            "type":"Services"
        }
    ],
    "sg:phone":"+1 336 667 7516",
    "sg:postcode":"28651",
    "sg:province":"NC",
    "sg:tags":[
        "welding"
    ],
    "wof:name":"Handy's Welding Svc",
    "wof:placetype":"venue"
},
  "geometry": {"coordinates":[-81.23387,36.183675],"type":"Point"}
}