{
  "type": "Feature",
  "properties": {
    "iso:country":"US",
    "sg:address":"202 Carpenter Brook Dr",
    "sg:city":"Cary",
    "sg:classifiers":[
        {
            "category":"Professional",
            "subcategory":"Management & Consulting",
            "type":"Services"
        }
    ],
    "sg:phone":"+1   ",
    "sg:postcode":"27519",
    "sg:province":"NC",
    "wof:name":"Dezec Inc",
    "wof:placetype":"venue"
},
  "geometry": {"coordinates":[-78.86410600000001,35.775492],"type":"Point"}
}