{
  "type": "Feature",
  "properties": {
    "addr:full":"3138 Wrightsville Ave Wilmington NC 28403",
    "addr:housenumber":"3138",
    "addr:postcode":"28403",
    "addr:street":"Wrightsville Ave",
    "iso:country":"US",
    "sg:address":"3138 Wrightsville Ave",
    "sg:city":"Wilmington",
    "sg:classifiers":[
        {
            "category":"Professional",
            "subcategory":"Lawyer & Legal Services",
            "type":"Services"
        }
    ],
    "sg:phone":"+1 910 772 1678",
    "sg:postcode":"28403",
    "sg:province":"NC",
    "sg:tags":[
        "attorney"
    ],
    "wof:name":"C Wess Hodges II",
    "wof:placetype":"venue"
},
  "geometry": {"coordinates":[-77.903937,34.224739],"type":"Point"}
}