{
  "type": "Feature",
  "properties": {
    "iso:country":"US",
    "sg:address":"6577 Marks Rd",
    "sg:city":"Cameron",
    "sg:classifiers":[
        {
            "category":"Building & Trades",
            "subcategory":"Construction",
            "type":"Services"
        }
    ],
    "sg:phone":"+1 910 245 1050",
    "sg:postcode":"28326",
    "sg:province":"NC",
    "sg:tags":[
        "floor",
        "laying",
        "contractor"
    ],
    "wof:name":"Jamerson Floors & Walls",
    "wof:placetype":"venue"
},
  "geometry": {"coordinates":[-79.13489300000001,35.206709],"type":"Point"}
}