{
  "type": "Feature",
  "properties": {
    "addr:full":"2430 Walnut St Cary NC 27511",
    "addr:housenumber":"2430",
    "addr:postcode":"27511",
    "addr:street":"Walnut St",
    "iso:country":"US",
    "sg:address":"2430 Walnut St",
    "sg:city":"Cary",
    "sg:classifiers":[
        {
            "category":"Shopping",
            "subcategory":"Pets & Pet Supplies",
            "type":"Retail Goods"
        }
    ],
    "sg:phone":"+1 919 858 5442",
    "sg:postcode":"27511",
    "sg:province":"NC",
    "sg:tags":[
        "training"
    ],
    "sg:website":"www.petsmart.com/",
    "wof:name":"Petsmart",
    "wof:placetype":"venue"
},
  "geometry": {"coordinates":[-78.741501,35.752998],"type":"Point"}
}