{
  "type": "Feature",
  "properties": {
    "addr:full":"1237 Shipp St Hendersonville NC 28791",
    "addr:housenumber":"1237",
    "addr:postcode":"28791",
    "addr:street":"Shipp St",
    "iso:country":"US",
    "sg:address":"1237 Shipp St",
    "sg:city":"Hendersonville",
    "sg:classifiers":[
        {
            "category":"Manufacturing",
            "subcategory":"Wood Products",
            "type":"Manufacturing & Wholesale Goods"
        }
    ],
    "sg:phone":"+1 828 693 1333",
    "sg:postcode":"28791",
    "sg:province":"NC",
    "sg:tags":[
        "picture",
        "art",
        "supply",
        "frame",
        "mfg",
        "mail",
        "order"
    ],
    "wof:name":"Presto Picture Frames",
    "wof:placetype":"venue"
},
  "geometry": {"coordinates":[-82.467033,35.325225],"type":"Point"}
}