{
  "type": "Feature",
  "properties": {
    "iso:country":"US",
    "sg:address":"2004 Southfort Dr",
    "sg:city":"Garner",
    "sg:classifiers":[
        {
            "category":"Banks & Credit Unions",
            "subcategory":"Financial Services",
            "type":"Services"
        }
    ],
    "sg:phone":"+1 919 779 9997",
    "sg:postcode":"27529",
    "sg:province":"NC",
    "sg:tags":[
        "investor"
    ],
    "wof:name":"William Lester Investments LLC",
    "wof:placetype":"venue"
},
  "geometry": {"coordinates":[-78.56086999999999,35.591768],"type":"Point"}
}