{
  "type": "Feature",
  "properties": {
    "iso:country":"US",
    "sg:address":"1904 Slippery Logging Rd",
    "sg:city":"Whiteville",
    "sg:classifiers":[
        {
            "category":"Professional",
            "subcategory":"Detective & Security Services",
            "type":"Services"
        }
    ],
    "sg:phone":"+1 910 642 9968",
    "sg:postcode":"28472",
    "sg:province":"NC",
    "sg:tags":[
        "investigator"
    ],
    "wof:name":"Investigations Unlimited Inc",
    "wof:placetype":"venue"
},
  "geometry": {"coordinates":[-78.749439,34.308104],"type":"Point"}
}