{
  "type": "Feature",
  "properties": {
    "addr:full":"104 Pocono Ln Cary NC 27513",
    "addr:housenumber":"104",
    "addr:postcode":"27513",
    "addr:street":"Pocono Ln",
    "iso:country":"US",
    "sg:address":"104 Pocono Ln",
    "sg:city":"Cary",
    "sg:classifiers":[
        {
            "category":"Professional",
            "subcategory":"Computer Services",
            "type":"Services"
        }
    ],
    "sg:phone":"+1   ",
    "sg:postcode":"27513",
    "sg:province":"NC",
    "wof:name":"Peripherals Plus",
    "wof:placetype":"venue"
},
  "geometry": {"coordinates":[-78.81986000000001,35.766709],"type":"Point"}
}