{
  "type": "Feature",
  "properties": {
    "addr:full":"603 12th Ave NE Hickory NC 28601",
    "addr:housenumber":"603",
    "addr:postcode":"28601",
    "addr:street":"12Th Ave Ne",
    "iso:country":"US",
    "sg:address":"603 12th Ave NE",
    "sg:city":"Hickory",
    "sg:classifiers":[
        {
            "category":"Health Services",
            "subcategory":"Doctor",
            "type":"Services"
        }
    ],
    "sg:phone":"+1   ",
    "sg:postcode":"28601",
    "sg:province":"NC",
    "sg:tags":[
        "medical"
    ],
    "wof:name":"Smoot Baker Dr",
    "wof:placetype":"venue"
},
  "geometry": {"coordinates":[-81.325935,35.747785],"type":"Point"}
}