{
  "type": "Feature",
  "properties": {
    "addr:full":"4004 Dickens Ave Hope Mills NC 28348",
    "addr:housenumber":"4004",
    "addr:postcode":"28348",
    "addr:street":"Dickens Ave",
    "iso:country":"US",
    "sg:address":"4004 Dickens Ave",
    "sg:city":"Hope Mills",
    "sg:classifiers":[
        {
            "category":"Social Services",
            "subcategory":"Child Care",
            "type":"Services"
        }
    ],
    "sg:phone":"+1   ",
    "sg:postcode":"28348",
    "sg:province":"NC",
    "sg:tags":[
        "day"
    ],
    "wof:name":"Inez Family Childcare",
    "wof:placetype":"venue"
},
  "geometry": {"coordinates":[-78.98510899999999,34.964631],"type":"Point"}
}