{
  "type": "Feature",
  "properties": {
    "iso:country":"US",
    "sg:address":"160 S Randolph Ave",
    "sg:city":"Asheboro",
    "sg:classifiers":[
        {
            "category":"Shopping",
            "subcategory":"Music",
            "type":"Retail Goods"
        }
    ],
    "sg:phone":"+1 336 626 4690",
    "sg:postcode":"27203",
    "sg:province":"NC",
    "sg:tags":[
        "compact",
        "record",
        "disc",
        "tape"
    ],
    "sg:website":"www.fye.com",
    "wof:name":"F Ye",
    "wof:placetype":"venue"
},
  "geometry": {"coordinates":[-79.805734,35.704291],"type":"Point"}
}