{
  "type": "Feature",
  "properties": {
    "addr:full":"9 E Main St Burnsville NC 28714",
    "addr:housenumber":"9",
    "addr:postcode":"28714",
    "addr:street":"E Main St",
    "iso:country":"US",
    "sg:address":"9 E Main St",
    "sg:city":"Burnsville",
    "sg:classifiers":[
        {
            "category":"Professional",
            "subcategory":"Lawyer & Legal Services",
            "type":"Services"
        }
    ],
    "sg:phone":"+1 828 682 7410",
    "sg:postcode":"28714",
    "sg:province":"NC",
    "sg:tags":[
        "attorney"
    ],
    "wof:name":"Staunton Norris",
    "wof:placetype":"venue"
},
  "geometry": {"coordinates":[-82.299126,35.917467],"type":"Point"}
}