{
  "type": "Feature",
  "properties": {
    "addr:full":"135 Alton Ln Boone NC 28607",
    "addr:housenumber":"135",
    "addr:postcode":"28607",
    "addr:street":"Alton Ln",
    "iso:country":"US",
    "sg:address":"135 Alton Ln",
    "sg:city":"Boone",
    "sg:classifiers":[
        {
            "category":"Professional",
            "type":"Services"
        }
    ],
    "sg:phone":"+1 828 264 8348",
    "sg:postcode":"28607",
    "sg:province":"NC",
    "wof:name":"Jimmie G West",
    "wof:placetype":"venue"
},
  "geometry": {"coordinates":[-81.668098,36.220393],"type":"Point"}
}