{
  "type": "Feature",
  "properties": {
    "addr:full":"2350 W Roosevelt Blvd Monroe NC 28110",
    "addr:housenumber":"2350",
    "addr:postcode":"28110",
    "addr:street":"W Roosevelt Blvd",
    "iso:country":"US",
    "sg:address":"2350 W Roosevelt Blvd",
    "sg:city":"Monroe",
    "sg:classifiers":[
        {
            "category":"Home & Garden",
            "subcategory":"Building Materials",
            "type":"Retail Goods"
        }
    ],
    "sg:phone":"+1 704 226 1744",
    "sg:postcode":"28110",
    "sg:province":"NC",
    "wof:name":"Lowes",
    "wof:placetype":"venue"
},
  "geometry": {"coordinates":[-80.561418,35.008369],"type":"Point"}
}