{
  "type": "Feature",
  "properties": {
    "iso:country":"US",
    "sg:address":"3157 Turf Ct",
    "sg:city":"Gastonia",
    "sg:classifiers":[
        {
            "category":"Health Services",
            "subcategory":"Doctor",
            "type":"Services"
        }
    ],
    "sg:phone":"+1   ",
    "sg:postcode":"28056",
    "sg:province":"NC",
    "sg:tags":[
        "medical"
    ],
    "wof:name":"Emergency & Acute Care",
    "wof:placetype":"venue"
},
  "geometry": {"coordinates":[-81.15665300000001,35.213808],"type":"Point"}
}