{
  "type": "Feature",
  "properties": {
    "addr:full":"130 English Oak Rd Fletcher NC 28732",
    "addr:housenumber":"130",
    "addr:postcode":"28732",
    "addr:street":"English Oak Rd",
    "iso:country":"US",
    "sg:address":"130 English Oak Rd",
    "sg:city":"Fletcher",
    "sg:classifiers":[
        {
            "category":"Professional",
            "subcategory":"Advertising",
            "type":"Services"
        }
    ],
    "sg:phone":"+1 828 654 9393",
    "sg:postcode":"28732",
    "sg:province":"NC",
    "wof:name":"Highland Promotional Marketing",
    "wof:placetype":"venue"
},
  "geometry": {"coordinates":[-82.457125,35.433903],"type":"Point"}
}