{
  "type": "Feature",
  "properties": {
    "iso:country":"US",
    "sg:address":"918 Cherry St",
    "sg:city":"North Wilkesboro",
    "sg:classifiers":[
        {
            "category":"Retail",
            "subcategory":"Auto Repair",
            "type":"Services"
        }
    ],
    "sg:phone":"+1 336 838 2264",
    "sg:postcode":"28659",
    "sg:province":"NC",
    "sg:tags":[
        "exchanging",
        "engine"
    ],
    "wof:name":"Blue Ridge Auto Machine Shop",
    "wof:placetype":"venue"
},
  "geometry": {"coordinates":[-81.145807,36.158338],"type":"Point"}
}