{
  "type": "Feature",
  "properties": {
    "addr:full":"111 E 3rd St Greenville NC 27858",
    "addr:housenumber":"111",
    "addr:postcode":"27858",
    "addr:street":"E 3Rd St",
    "iso:country":"US",
    "sg:address":"111 E 3rd St",
    "sg:city":"Greenville",
    "sg:classifiers":[
        {
            "category":"Insurance",
            "subcategory":"Hazard Insurance",
            "type":"Services"
        }
    ],
    "sg:phone":"+1 252 758 7884",
    "sg:postcode":"27858",
    "sg:province":"NC",
    "sg:tags":[
        "bond"
    ],
    "wof:name":"A Way Out Bail Bonding",
    "wof:placetype":"venue"
},
  "geometry": {"coordinates":[-77.372407,35.613256],"type":"Point"}
}