{
  "type": "Feature",
  "properties": {
    "iso:country":"US",
    "sg:address":"115 Crow Run",
    "sg:city":"Rockingham",
    "sg:classifiers":[
        {
            "category":"Building & Trades",
            "subcategory":"Construction",
            "type":"Services"
        }
    ],
    "sg:phone":"+1 910 997 3153",
    "sg:postcode":"28379",
    "sg:province":"NC",
    "sg:tags":[
        "contractor"
    ],
    "wof:name":"Southern Builders Inc",
    "wof:placetype":"venue"
},
  "geometry": {"coordinates":[-79.750741,34.934334],"type":"Point"}
}