{
  "type": "Feature",
  "properties": {
    "addr:full":"1900 S Hawthorne Rd Winston Salem NC 27103",
    "addr:housenumber":"1900",
    "addr:postcode":"27103",
    "addr:street":"S Hawthorne Rd",
    "iso:country":"US",
    "sg:address":"1900 S Hawthorne Rd",
    "sg:city":"Winston Salem",
    "sg:classifiers":[
        {
            "category":"Professional",
            "type":"Services"
        }
    ],
    "sg:phone":"+1 336 718 0050",
    "sg:postcode":"27103",
    "sg:province":"NC",
    "wof:name":"A Call Nurse",
    "wof:placetype":"venue"
},
  "geometry": {"coordinates":[-80.295464,36.078174],"type":"Point"}
}