{
  "type": "Feature",
  "properties": {
    "addr:full":"804 E Williams St Apex NC 27502",
    "addr:housenumber":"804",
    "addr:postcode":"27502",
    "addr:street":"E Williams St",
    "iso:country":"US",
    "sg:address":"804 E Williams St",
    "sg:city":"Apex",
    "sg:classifiers":[
        {
            "category":"Banks & Credit Unions",
            "subcategory":"Bank",
            "type":"Services"
        }
    ],
    "sg:phone":"+1 919 387 6865",
    "sg:postcode":"27502",
    "sg:province":"NC",
    "sg:tags":[
        "commercial"
    ],
    "sg:website":"www.fidelitybanknc.com",
    "wof:name":"Fidelity Bank",
    "wof:placetype":"venue"
},
  "geometry": {"coordinates":[-78.845398,35.7229],"type":"Point"}
}