{
  "type": "Feature",
  "properties": {
    "iso:country":"US",
    "sg:address":"19 Reynolds Pl",
    "sg:city":"Asheville",
    "sg:classifiers":[
        {
            "category":"Building & Trades",
            "subcategory":"Construction",
            "type":"Services"
        }
    ],
    "sg:phone":"+1 828 258 0922",
    "sg:postcode":"28804",
    "sg:province":"NC",
    "sg:tags":[
        "siding",
        "nonresidential",
        "contractor"
    ],
    "wof:name":"Our Next Generation Inc",
    "wof:placetype":"venue"
},
  "geometry": {"coordinates":[-82.562088,35.631604],"type":"Point"}
}