{
  "type": "Feature",
  "properties": {
    "addr:full":"413 N Lee St Whiteville NC 28472",
    "addr:housenumber":"413",
    "addr:postcode":"28472",
    "addr:street":"N Lee St",
    "iso:country":"US",
    "sg:address":"413 N Lee St",
    "sg:city":"Whiteville",
    "sg:classifiers":[
        {
            "category":"Education",
            "subcategory":"School",
            "type":"Public Place"
        }
    ],
    "sg:phone":"+1 910 914 4189",
    "sg:postcode":"28472",
    "sg:province":"NC",
    "wof:name":"Whiteville High School",
    "wof:placetype":"venue"
},
  "geometry": {"coordinates":[-78.70617,34.335963],"type":"Point"}
}