{
  "type": "Feature",
  "properties": {
    "addr:full":"4750 State Hwy 87 S Fayetteville NC 28306",
    "addr:housenumber":"4750",
    "addr:postcode":"28306",
    "addr:street":"State Hwy 87 S",
    "iso:country":"US",
    "sg:address":"4750 State Hwy 87 S",
    "sg:city":"Fayetteville",
    "sg:classifiers":[
        {
            "category":"Autos & Motor Vehicles",
            "subcategory":"Automobile Sales",
            "type":"Retail Goods"
        }
    ],
    "sg:phone":"+1 910 485 7520",
    "sg:postcode":"28306",
    "sg:province":"NC",
    "sg:tags":[
        "used"
    ],
    "wof:name":"Sunbelt Auto Sales",
    "wof:placetype":"venue"
},
  "geometry": {"coordinates":[-78.848963,34.934813],"type":"Point"}
}