{
  "type": "Feature",
  "properties": {
    "addr:full":"505 E Plaza Dr Mooresville NC 28115",
    "addr:housenumber":"505",
    "addr:postcode":"28115",
    "addr:street":"E Plaza Dr",
    "iso:country":"US",
    "sg:address":"505 E Plaza Dr",
    "sg:city":"Mooresville",
    "sg:classifiers":[
        {
            "category":"Autos & Motor Vehicles",
            "subcategory":"Automobile Sales",
            "type":"Retail Goods"
        }
    ],
    "sg:phone":"+1 704 660 3008",
    "sg:postcode":"28115",
    "sg:province":"NC",
    "sg:tags":[
        "used"
    ],
    "wof:name":"Xtreme Automotive Inc",
    "wof:placetype":"venue"
},
  "geometry": {"coordinates":[-80.815135,35.596522],"type":"Point"}
}