{
  "type": "Feature",
  "properties": {
    "addr:full":"5880 State Hwy 16 N Crumpler NC 28617",
    "addr:housenumber":"5880",
    "addr:postcode":"28617",
    "addr:street":"State Hwy 16 N",
    "iso:country":"US",
    "sg:address":"5880 State Hwy 16 N",
    "sg:city":"Crumpler",
    "sg:classifiers":[
        {
            "category":"Farming",
            "subcategory":"Poultry Farm",
            "type":"Manufacturing & Wholesale Goods"
        }
    ],
    "sg:phone":"+1 336 982 2300",
    "sg:postcode":"28617",
    "sg:province":"NC",
    "sg:tags":[
        "chicken"
    ],
    "wof:name":"McCoy Tanner L",
    "wof:placetype":"venue"
},
  "geometry": {"coordinates":[-81.41015,36.496323],"type":"Point"}
}