{
  "type": "Feature",
  "properties": {
    "addr:full":"3256 Union Rd Gastonia NC 28056",
    "addr:housenumber":"3256",
    "addr:postcode":"28056",
    "addr:street":"Union Rd",
    "iso:country":"US",
    "sg:address":"3256 Union Rd",
    "sg:city":"Gastonia",
    "sg:classifiers":[
        {
            "category":"Home & Garden",
            "subcategory":"Carpets & Floor Coverings",
            "type":"Retail Goods"
        }
    ],
    "sg:phone":"+1 704 853 1900",
    "sg:postcode":"28056",
    "sg:province":"NC",
    "wof:name":"Stonemountain Carpet Mill",
    "wof:placetype":"venue"
},
  "geometry": {"coordinates":[-81.164951,35.208359],"type":"Point"}
}