{
  "type": "Feature",
  "properties": {
    "iso:country":"US",
    "sg:address":"251 Gap Creek Rd",
    "sg:city":"Fletcher",
    "sg:classifiers":[
        {
            "category":"Building & Trades",
            "subcategory":"Construction",
            "type":"Services"
        }
    ],
    "sg:phone":"+1 828 628 1937",
    "sg:postcode":"28732",
    "sg:province":"NC",
    "wof:name":"L & S Contracting",
    "wof:placetype":"venue"
},
  "geometry": {"coordinates":[-82.436373,35.51933],"type":"Point"}
}