{
  "type": "Feature",
  "properties": {
    "addr:full":"219 W 4th St Winston Salem NC 27101",
    "addr:housenumber":"219",
    "addr:postcode":"27101",
    "addr:street":"W 4Th St",
    "iso:country":"US",
    "sg:address":"219 W 4th St",
    "sg:city":"Winston Salem",
    "sg:classifiers":[
        {
            "category":"Restaurant",
            "type":"Food & Drink"
        }
    ],
    "sg:phone":"+1 336 777 1422",
    "sg:postcode":"27101",
    "sg:province":"NC",
    "wof:name":"Downtown Thai Restaurant",
    "wof:placetype":"venue"
},
  "geometry": {"coordinates":[-80.247005,36.098244],"type":"Point"}
}