{
  "type": "Feature",
  "properties": {
    "addr:full":"207 N Hall St Chapel Hill NC 27504",
    "addr:housenumber":"207",
    "addr:postcode":"27504",
    "addr:street":"N Hall St",
    "iso:country":"US",
    "sg:address":"207 N Hall St",
    "sg:city":"Chapel Hill",
    "sg:classifiers":[
        {
            "category":"Education",
            "subcategory":"Special Training",
            "type":"Public Place"
        }
    ],
    "sg:phone":"+1   ",
    "sg:postcode":"27504",
    "sg:province":"NC",
    "sg:tags":[
        "educational"
    ],
    "wof:name":"David Potenziani",
    "wof:placetype":"venue"
},
  "geometry": {"coordinates":[-78.538794,35.382848],"type":"Point"}
}