{
  "type": "Feature",
  "properties": {
    "iso:country":"US",
    "sg:address":"350 Tower Rd",
    "sg:city":"Taylorsville",
    "sg:classifiers":[
        {
            "category":"Communications",
            "subcategory":"Television Station",
            "type":"Services"
        }
    ],
    "sg:phone":"+1 828 632 0349",
    "sg:postcode":"28681",
    "sg:province":"NC",
    "sg:tags":[
        "broadcasting",
        "co"
    ],
    "wof:name":"Apple City Broadcast",
    "wof:placetype":"venue"
},
  "geometry": {"coordinates":[-81.16296699999999,35.929306],"type":"Point"}
}