{
  "type": "Feature",
  "properties": {
    "iso:country":"US",
    "sg:address":"1500 Harbour Dr",
    "sg:city":"Wilmington",
    "sg:classifiers":[
        {
            "category":"Building & Trades",
            "subcategory":"Landscaping Services",
            "type":"Services"
        }
    ],
    "sg:phone":"+1 910 763 6800",
    "sg:postcode":"28401",
    "sg:province":"NC",
    "sg:tags":[
        "lawn",
        "maintenance",
        "grounds"
    ],
    "wof:name":"Morley's Creative Earthworks",
    "wof:placetype":"venue"
},
  "geometry": {"coordinates":[-77.92244100000001,34.196763],"type":"Point"}
}