{
  "type": "Feature",
  "properties": {
    "iso:country":"US",
    "sg:address":"474 State Hwy 62",
    "sg:city":"Yanceyville",
    "sg:classifiers":[
        {
            "category":"Social Services",
            "type":"Services"
        }
    ],
    "sg:phone":"+1 336 694 0906",
    "sg:postcode":"27379",
    "sg:province":"NC",
    "sg:tags":[
        "youth",
        "organization",
        "center"
    ],
    "wof:name":"Hearthstone Youth & Family Svc",
    "wof:placetype":"venue"
},
  "geometry": {"coordinates":[-79.276794,36.449139],"type":"Point"}
}