{
  "type": "Feature",
  "properties": {
    "iso:country":"US",
    "sg:address":"3494 US Hwy 64",
    "sg:city":"Advance",
    "sg:classifiers":[
        {
            "category":"Real Estate",
            "subcategory":"Real Estate Agent",
            "type":"Services"
        }
    ],
    "sg:phone":"+1 336 998 5442",
    "sg:postcode":"27006",
    "sg:province":"NC",
    "wof:name":"Sidden Realty Inc",
    "wof:placetype":"venue"
},
  "geometry": {"coordinates":[-80.431495,35.872229],"type":"Point"}
}