{
  "type": "Feature",
  "properties": {
    "iso:country":"US",
    "sg:address":"1200 E Morehead St",
    "sg:city":"Charlotte",
    "sg:classifiers":[
        {
            "category":"Banks & Credit Unions",
            "subcategory":"Financial Services",
            "type":"Services"
        },
        {
            "category":"Organizations",
            "subcategory":"Community Association",
            "type":"Services"
        }
    ],
    "sg:phone":"+1 704 376 1839",
    "sg:postcode":"28204",
    "sg:province":"NC",
    "sg:tags":[
        "trust",
        "org",
        "management",
        "environmental"
    ],
    "sg:website":"www.tpl.org",
    "wof:name":"Trust For Public Land",
    "wof:placetype":"venue"
},
  "geometry": {"coordinates":[-80.83963799999999,35.208389],"type":"Point"}
}