{
  "type": "Feature",
  "properties": {
    "iso:country":"US",
    "sg:address":"20 3rd St NW",
    "sg:city":"Hickory",
    "sg:classifiers":[
        {
            "category":"Banks & Credit Unions",
            "subcategory":"Investment Brokerage",
            "type":"Services"
        }
    ],
    "sg:phone":"+1 828 327 9727",
    "sg:postcode":"28601",
    "sg:province":"NC",
    "sg:tags":[
        "advisory",
        "financial"
    ],
    "wof:name":"R2S Financial Group",
    "wof:placetype":"venue"
},
  "geometry": {"coordinates":[-81.342174,35.732555],"type":"Point"}
}