{
  "type": "Feature",
  "properties": {
    "iso:country":"US",
    "sg:address":"254 Caratoke Hwy",
    "sg:city":"Moyock",
    "sg:classifiers":[
        {
            "category":"Wholesale",
            "subcategory":"Construction Materials",
            "type":"Manufacturing & Wholesale Goods"
        }
    ],
    "sg:phone":"+1 252 435 0616",
    "sg:postcode":"27958",
    "sg:province":"NC",
    "sg:tags":[
        "sand",
        "gravel"
    ],
    "wof:name":"Moyock Farms Sand Pit",
    "wof:placetype":"venue"
},
  "geometry": {"coordinates":[-76.192864,36.550456],"type":"Point"}
}