{
  "type": "Feature",
  "properties": {
    "iso:country":"US",
    "sg:address":"310 Caledonia Way",
    "sg:city":"Weddington",
    "sg:classifiers":[
        {
            "category":"Building & Trades",
            "subcategory":"Construction",
            "type":"Services"
        }
    ],
    "sg:phone":"+1 704 844 2424",
    "sg:postcode":"28173",
    "sg:province":"NC",
    "sg:tags":[
        "general",
        "contractor"
    ],
    "wof:name":"Providence Contracting",
    "wof:placetype":"venue"
},
  "geometry": {"coordinates":[-80.75658300000001,35.000661],"type":"Point"}
}