{
  "type": "Feature",
  "properties": {
    "iso:country":"US",
    "sg:address":"4820 Monroe Rd",
    "sg:city":"Charlotte",
    "sg:classifiers":[
        {
            "category":"Wholesale",
            "subcategory":"Machinery & Supplies",
            "type":"Manufacturing & Wholesale Goods"
        }
    ],
    "sg:phone":"+1 704 488 4257",
    "sg:postcode":"28205",
    "sg:province":"NC",
    "sg:tags":[
        "equipment",
        "establishment"
    ],
    "wof:name":"Massage In Motion Referral Svc",
    "wof:placetype":"venue"
},
  "geometry": {"coordinates":[-80.78046399999999,35.192893],"type":"Point"}
}