{
  "type": "Feature",
  "properties": {
    "iso:country":"US",
    "sg:address":"106 E Main Ave",
    "sg:city":"Gastonia",
    "sg:classifiers":[
        {
            "category":"Building & Trades",
            "subcategory":"Pest Control",
            "type":"Services"
        }
    ],
    "sg:phone":"+1 704 724 1450",
    "sg:postcode":"28052",
    "sg:province":"NC",
    "wof:name":"HomeSpectors Termite and Pest Control",
    "wof:placetype":"venue"
},
  "geometry": {"coordinates":[-81.18182299999999,35.263791],"type":"Point"}
}