{
  "type": "Feature",
  "properties": {
    "addr:full":"1408 Christian Ave Durham NC 27705",
    "addr:housenumber":"1408",
    "addr:postcode":"27705",
    "addr:street":"Christian Ave",
    "iso:country":"US",
    "sg:address":"1408 Christian Ave",
    "sg:city":"Durham",
    "sg:classifiers":[
        {
            "category":"Education",
            "subcategory":"Dance Studio",
            "type":"Public Place"
        },
        {
            "category":"Recreation",
            "type":"Entertainment"
        }
    ],
    "sg:phone":"+1 919 382 5552",
    "sg:postcode":"27705",
    "sg:province":"NC",
    "sg:tags":[
        "instruction",
        "dancing"
    ],
    "wof:name":"Acro Sport Gymnastics",
    "wof:placetype":"venue"
},
  "geometry": {"coordinates":[-78.952049,36.024192],"type":"Point"}
}