{
  "type": "Feature",
  "properties": {
    "addr:full":"215 Thompson St Hendersonville NC 28792",
    "addr:housenumber":"215",
    "addr:postcode":"28792",
    "addr:street":"Thompson St",
    "iso:country":"US",
    "sg:address":"215 Thompson St",
    "sg:city":"Hendersonville",
    "sg:classifiers":[
        {
            "category":"Health Services",
            "subcategory":"Doctor",
            "type":"Services"
        }
    ],
    "sg:phone":"+1 828 693 4161",
    "sg:postcode":"28792",
    "sg:province":"NC",
    "sg:tags":[
        "physician",
        "surgeon"
    ],
    "sg:website":"www.lookingglasseye.com",
    "wof:name":"Looking Glass Eye Ctr",
    "wof:placetype":"venue"
},
  "geometry": {"coordinates":[-82.44686,35.3382],"type":"Point"}
}