{
  "type": "Feature",
  "properties": {
    "iso:country":"US",
    "sg:address":"4622 Brenda Ct",
    "sg:city":"Charlotte",
    "sg:classifiers":[
        {
            "category":"Government",
            "subcategory":"Police Station",
            "type":"Public Place"
        }
    ],
    "sg:phone":"+1 704 336 2337",
    "sg:postcode":"28269",
    "sg:province":"NC",
    "sg:tags":[
        "protection"
    ],
    "wof:name":"Police Dept",
    "wof:placetype":"venue"
},
  "geometry": {"coordinates":[-80.81691499999999,35.285234],"type":"Point"}
}