{
  "type": "Feature",
  "properties": {
    "addr:full":"5041 New Centre Dr Wilmington NC 28403",
    "addr:housenumber":"5041",
    "addr:postcode":"28403",
    "addr:street":"New Centre Dr",
    "iso:country":"US",
    "sg:address":"5041 New Centre Dr",
    "sg:city":"Wilmington",
    "sg:classifiers":[
        {
            "category":"Professional",
            "subcategory":"Employment Agencies",
            "type":"Services"
        }
    ],
    "sg:phone":"+1 910 791 9022",
    "sg:postcode":"28403",
    "sg:province":"NC",
    "sg:tags":[
        "opportunity"
    ],
    "wof:name":"Arc Employment & Training",
    "wof:placetype":"venue"
},
  "geometry": {"coordinates":[-77.877324,34.240372],"type":"Point"}
}