{
  "type": "Feature",
  "properties": {
    "addr:full":"833 Water St Henderson NC 27536",
    "addr:housenumber":"833",
    "addr:postcode":"27536",
    "addr:street":"Water St",
    "iso:country":"US",
    "sg:address":"833 Water St",
    "sg:city":"Henderson",
    "sg:classifiers":[
        {
            "category":"Professional",
            "subcategory":"Detective & Security Services",
            "type":"Services"
        }
    ],
    "sg:phone":"+1 252 226 4985",
    "sg:postcode":"27536",
    "sg:province":"NC",
    "sg:tags":[
        "information",
        "bureau"
    ],
    "wof:name":"Jalil's Unique Catering Service",
    "wof:placetype":"venue"
},
  "geometry": {"coordinates":[-78.389399,36.328434],"type":"Point"}
}