{
  "type": "Feature",
  "properties": {
    "iso:country":"US",
    "sg:address":"14333 Hunters Rd",
    "sg:city":"Huntersville",
    "sg:classifiers":[
        {
            "category":"Manufacturing",
            "subcategory":"Metals",
            "type":"Manufacturing & Wholesale Goods"
        }
    ],
    "sg:phone":"+1 704 875 1065",
    "sg:postcode":"28078",
    "sg:province":"NC",
    "sg:tags":[
        "decorative",
        "cooper",
        "mfg",
        "work",
        "brass",
        "sculptor"
    ],
    "wof:name":"Max Howard Studio",
    "wof:placetype":"venue"
},
  "geometry": {"coordinates":[-80.855755,35.418159],"type":"Point"}
}