{
  "type": "Feature",
  "properties": {
    "iso:country":"US",
    "sg:address":"1472 Ridgewood Cir",
    "sg:city":"Asheboro",
    "sg:classifiers":[
        {
            "category":"Personal",
            "type":"Services"
        }
    ],
    "sg:phone":"+1 336 625 3311",
    "sg:postcode":"27203",
    "sg:province":"NC",
    "sg:tags":[
        "therapist",
        "massage"
    ],
    "wof:name":"Asheboro Therapeutic Massage",
    "wof:placetype":"venue"
},
  "geometry": {"coordinates":[-79.785681,35.7378],"type":"Point"}
}