{
  "type": "Feature",
  "properties": {
    "addr:full":"1343 W Charity Rd Rose Hill NC 28458",
    "addr:housenumber":"1343",
    "addr:postcode":"28458",
    "addr:street":"W Charity Rd",
    "iso:country":"US",
    "sg:address":"1343 W Charity Rd",
    "sg:city":"Rose Hill",
    "sg:classifiers":[
        {
            "category":"Organizations",
            "subcategory":"Religious Organization",
            "type":"Services"
        }
    ],
    "sg:phone":"+1   ",
    "sg:postcode":"28458",
    "sg:province":"NC",
    "wof:name":"Island Creek AME Church",
    "wof:placetype":"venue"
},
  "geometry": {"coordinates":[-77.962824,34.822924],"type":"Point"}
}