{
  "type": "Feature",
  "properties": {
    "addr:full":"135 Dale Earnhardt Blvd Kannapolis NC 28081",
    "addr:housenumber":"135",
    "addr:postcode":"28081",
    "addr:street":"Dale Earnhardt Blvd",
    "iso:country":"US",
    "sg:address":"135 Dale Earnhardt Blvd",
    "sg:city":"Kannapolis",
    "sg:classifiers":[
        {
            "category":"Shopping",
            "subcategory":"Pharmacy",
            "type":"Retail Goods"
        }
    ],
    "sg:phone":"+1 704 938 6151",
    "sg:postcode":"28081",
    "sg:province":"NC",
    "wof:name":"Eckerd Drugs",
    "wof:placetype":"venue"
},
  "geometry": {"coordinates":[-80.628756,35.488939],"type":"Point"}
}