{
  "type": "Feature",
  "properties": {
    "addr:full":"1012 Philadelphia Church Rd Dallas NC 28034",
    "addr:housenumber":"1012",
    "addr:postcode":"28034",
    "addr:street":"Church Rd",
    "iso:country":"US",
    "sg:address":"1012 Philadelphia Church Rd",
    "sg:city":"Dallas",
    "sg:classifiers":[
        {
            "category":"Building & Trades",
            "subcategory":"Equipment Rental",
            "type":"Services"
        }
    ],
    "sg:phone":"+1 704 922 0944",
    "sg:postcode":"28034",
    "sg:province":"NC",
    "sg:tags":[
        "crane"
    ],
    "wof:name":"AME Inc",
    "wof:placetype":"venue"
},
  "geometry": {"coordinates":[-81.17412400000001,35.326631],"type":"Point"}
}