{
  "type": "Feature",
  "properties": {
    "iso:country":"US",
    "sg:address":"926 Arnold Rd",
    "sg:city":"Wilmington",
    "sg:classifiers":[
        {
            "category":"Building & Trades",
            "subcategory":"Construction",
            "type":"Services"
        }
    ],
    "sg:phone":"+1 910 793 4143",
    "sg:postcode":"28412",
    "sg:province":"NC",
    "sg:tags":[
        "dock"
    ],
    "wof:name":"Carolina Marine Construction",
    "wof:placetype":"venue"
},
  "geometry": {"coordinates":[-77.91459399999999,34.137268],"type":"Point"}
}