{
  "type": "Feature",
  "properties": {
    "addr:full":"1200 Sutton Dr Kinston NC 28501",
    "addr:housenumber":"1200",
    "addr:postcode":"28501",
    "addr:street":"Sutton Dr",
    "iso:country":"US",
    "sg:address":"1200 Sutton Dr",
    "sg:city":"Kinston",
    "sg:classifiers":[
        {
            "category":"Professional",
            "subcategory":"Lawyer & Legal Services",
            "type":"Services"
        }
    ],
    "sg:phone":"+1   ",
    "sg:postcode":"28501",
    "sg:province":"NC",
    "wof:name":"Stuart L Stroud Atty",
    "wof:placetype":"venue"
},
  "geometry": {"coordinates":[-77.595079,35.276627],"type":"Point"}
}