{
  "type": "Feature",
  "properties": {
    "iso:country":"US",
    "sg:address":"1210 Corporation Pkwy",
    "sg:city":"Raleigh",
    "sg:classifiers":[
        {
            "category":"Building & Trades",
            "subcategory":"Electrical",
            "type":"Services"
        }
    ],
    "sg:phone":"+1 919 779 4166",
    "sg:postcode":"27610",
    "sg:province":"NC",
    "sg:tags":[
        "telecommunication",
        "contractor"
    ],
    "wof:name":"AFL Network Svc",
    "wof:placetype":"venue"
},
  "geometry": {"coordinates":[-78.568271,35.795024],"type":"Point"}
}