{
  "type": "Feature",
  "properties": {
    "iso:country":"US",
    "sg:address":"3832 Monroe Rd",
    "sg:city":"Charlotte",
    "sg:classifiers":[
        {
            "category":"Retail",
            "subcategory":"Veterinary Services",
            "type":"Services"
        }
    ],
    "sg:phone":"+1 704 334 4684",
    "sg:postcode":"28205",
    "sg:province":"NC",
    "sg:tags":[
        "hospital",
        "animal"
    ],
    "wof:name":"Animal Medical Hospital",
    "wof:placetype":"venue"
},
  "geometry": {"coordinates":[-80.794364,35.198645],"type":"Point"}
}