{
  "type": "Feature",
  "properties": {
    "addr:full":"8724 Bodkin Ct Charlotte NC 28215",
    "addr:housenumber":"8724",
    "addr:postcode":"28215",
    "addr:street":"Bodkin Ct",
    "iso:country":"US",
    "sg:address":"8724 Bodkin Ct",
    "sg:city":"Charlotte",
    "sg:classifiers":[
        {
            "category":"Shopping",
            "subcategory":"Crafts & Fabrics",
            "type":"Retail Goods"
        }
    ],
    "sg:phone":"+1 704 561 5600",
    "sg:postcode":"28215",
    "sg:province":"NC",
    "sg:tags":[
        "sewing"
    ],
    "wof:name":"Commercial Piping Fabric",
    "wof:placetype":"venue"
},
  "geometry": {"coordinates":[-80.66333899999999,35.256529],"type":"Point"}
}