{
  "type": "Feature",
  "properties": {
    "iso:country":"US",
    "sg:address":"1017 Beech Tree Rd",
    "sg:city":"Jacksonville",
    "sg:classifiers":[
        {
            "category":"Professional",
            "subcategory":"Business Services",
            "type":"Services"
        }
    ],
    "sg:phone":"+1 910 938 9440",
    "sg:postcode":"28546",
    "sg:province":"NC",
    "sg:tags":[
        "appraiser"
    ],
    "wof:name":"Eddie Mann & Assoc",
    "wof:placetype":"venue"
},
  "geometry": {"coordinates":[-77.36624999999999,34.773475],"type":"Point"}
}