{
  "type": "Feature",
  "properties": {
    "iso:country":"US",
    "sg:address":"1241 Hobbton Hwy",
    "sg:city":"Clinton",
    "sg:classifiers":[
        {
            "category":"Autos & Motor Vehicles",
            "subcategory":"Auto Supplies",
            "type":"Retail Goods"
        },
        {
            "category":"Retail",
            "subcategory":"Auto Repair",
            "type":"Services"
        }
    ],
    "sg:phone":"+1 910 592 0167",
    "sg:postcode":"28328",
    "sg:province":"NC",
    "sg:tags":[
        "automotive",
        "tire",
        "general"
    ],
    "wof:name":"Spivey-Lewis Tire Company Inc",
    "wof:placetype":"venue"
},
  "geometry": {"coordinates":[-78.327054,35.019803],"type":"Point"}
}