{
  "type": "Feature",
  "properties": {
    "addr:full":"305 Mc Lean St Hamlet NC 28345",
    "addr:housenumber":"305",
    "addr:postcode":"28345",
    "addr:street":"Mc Lean St",
    "iso:country":"US",
    "sg:address":"305 Mc Lean St",
    "sg:city":"Hamlet",
    "sg:classifiers":[
        {
            "category":"Insurance",
            "subcategory":"Life Insurance",
            "type":"Services"
        }
    ],
    "sg:phone":"+1 910 582 1375",
    "sg:postcode":"28345",
    "sg:province":"NC",
    "sg:tags":[
        "provider"
    ],
    "wof:name":"John Hancock",
    "wof:placetype":"venue"
},
  "geometry": {"coordinates":[-79.72001400000001,34.877163],"type":"Point"}
}