{
  "type": "Feature",
  "properties": {
    "addr:full":"111 Paladin Pl Cary NC 27513",
    "addr:housenumber":"111",
    "addr:postcode":"27513",
    "addr:street":"Paladin Pl",
    "iso:country":"US",
    "sg:address":"111 Paladin Pl",
    "sg:city":"Cary",
    "sg:classifiers":[
        {
            "category":"Professional",
            "type":"Services"
        }
    ],
    "sg:phone":"+1 919 481 0793",
    "sg:postcode":"27513",
    "sg:province":"NC",
    "sg:website":"www.metrologic.com",
    "wof:name":"Metrologic Instruments",
    "wof:placetype":"venue"
},
  "geometry": {"coordinates":[-78.84660599999999,35.781249],"type":"Point"}
}