{
  "type": "Feature",
  "properties": {
    "iso:country":"US",
    "sg:address":"2840 Richlands Hwy",
    "sg:city":"Jacksonville",
    "sg:classifiers":[
        {
            "category":"Autos & Motor Vehicles",
            "subcategory":"Fuel & Gas Station",
            "type":"Retail Goods"
        }
    ],
    "sg:phone":"+1 910 455 8633",
    "sg:postcode":"28540",
    "sg:province":"NC",
    "sg:tags":[
        "oil"
    ],
    "wof:name":"Speedway/Sunoco",
    "wof:placetype":"venue"
},
  "geometry": {"coordinates":[-77.465301,34.755465],"type":"Point"}
}