{
  "type": "Feature",
  "properties": {
    "addr:full":"3346 Little Rock Rd Charlotte NC 28214",
    "addr:housenumber":"3346",
    "addr:postcode":"28214",
    "addr:street":"Little Rock Rd",
    "iso:country":"US",
    "sg:address":"3346 Little Rock Rd",
    "sg:city":"Charlotte",
    "sg:phone":"+1 704 395 1477",
    "sg:postcode":"28214",
    "sg:province":"NC",
    "wof:name":"Charlotte Airport Authority",
    "wof:placetype":"venue"
},
  "geometry": {"coordinates":[-80.94454899999999,35.232312],"type":"Point"}
}