{
  "type": "Feature",
  "properties": {
    "iso:country":"US",
    "sg:address":"46 Orchard St",
    "sg:city":"Asheville",
    "sg:classifiers":[
        {
            "category":"Real Estate",
            "subcategory":"Real Estate Agent",
            "type":"Services"
        }
    ],
    "sg:phone":"+1 828 254 1154",
    "sg:postcode":"28801",
    "sg:province":"NC",
    "wof:name":"Quality 1 Realty",
    "wof:placetype":"venue"
},
  "geometry": {"coordinates":[-82.54992900000001,35.600683],"type":"Point"}
}