{
  "type": "Feature",
  "properties": {
    "addr:full":"1019 Durham Rd Roxboro NC 27573",
    "addr:housenumber":"1019",
    "addr:postcode":"27573",
    "addr:street":"Durham Rd",
    "iso:country":"US",
    "sg:address":"1019 Durham Rd",
    "sg:city":"Roxboro",
    "sg:classifiers":[
        {
            "category":"Shopping",
            "subcategory":"Music",
            "type":"Retail Goods"
        }
    ],
    "sg:phone":"+1 336 322 0048",
    "sg:postcode":"27573",
    "sg:province":"NC",
    "sg:tags":[
        "video",
        "disc",
        "tape",
        "cassette"
    ],
    "wof:name":"Blockbuster Entertainment",
    "wof:placetype":"venue"
},
  "geometry": {"coordinates":[-78.983949,36.378999],"type":"Point"}
}