{
  "type": "Feature",
  "properties": {
    "addr:full":"2114 Atlantic Ave Raleigh NC 27604",
    "addr:housenumber":"2114",
    "addr:postcode":"27604",
    "addr:street":"Atlantic Ave",
    "iso:country":"US",
    "sg:address":"2114 Atlantic Ave",
    "sg:city":"Raleigh",
    "sg:classifiers":[
        {
            "category":"Manufacturing",
            "subcategory":"Tools & Machinery",
            "type":"Manufacturing & Wholesale Goods"
        }
    ],
    "sg:phone":"+1 919 484 8515",
    "sg:postcode":"27604",
    "sg:province":"NC",
    "sg:tags":[
        "photographic",
        "supply"
    ],
    "wof:name":"Qualex Warehouse",
    "wof:placetype":"venue"
},
  "geometry": {"coordinates":[-78.620144,35.808827],"type":"Point"}
}