{
  "type": "Feature",
  "properties": {
    "iso:country":"US",
    "sg:address":"6410 Fox Hunt Rd",
    "sg:city":"Indian Trail",
    "sg:classifiers":[
        {
            "category":"Shopping",
            "subcategory":"Photographic Equipment",
            "type":"Retail Goods"
        },
        {
            "category":"Professional",
            "subcategory":"Art Services",
            "type":"Services"
        }
    ],
    "sg:phone":"+1 704 893 2015",
    "sg:postcode":"28079",
    "sg:province":"NC",
    "sg:tags":[
        "photography",
        "commercial",
        "supply"
    ],
    "wof:name":"Terri's View Photography",
    "wof:placetype":"venue"
},
  "geometry": {"coordinates":[-80.627424,35.111533],"type":"Point"}
}