{
  "type": "Feature",
  "properties": {
    "iso:country":"US",
    "sg:address":"1777 N Fordham Blvd",
    "sg:city":"Chapel Hill",
    "sg:classifiers":[
        {
            "category":"Social Services",
            "type":"Services"
        }
    ],
    "sg:phone":"+1 919 969 9993",
    "sg:postcode":"27514",
    "sg:province":"NC",
    "sg:tags":[
        "youth",
        "organization",
        "center"
    ],
    "wof:name":"Young Life",
    "wof:placetype":"venue"
},
  "geometry": {"coordinates":[-79.02627,35.91297],"type":"Point"}
}