{
  "type": "Feature",
  "properties": {
    "addr:full":"108 6th Ave NE Conover NC 28613",
    "addr:housenumber":"108",
    "addr:postcode":"28613",
    "addr:street":"6Th Ave Ne",
    "iso:country":"US",
    "sg:address":"108 6th Ave NE",
    "sg:city":"Conover",
    "sg:classifiers":[
        {
            "category":"Real Estate",
            "subcategory":"Real Estate Agent",
            "type":"Services"
        }
    ],
    "sg:phone":"+1 828 465 8680",
    "sg:postcode":"28613",
    "sg:province":"NC",
    "wof:name":"Realty Connection",
    "wof:placetype":"venue"
},
  "geometry": {"coordinates":[-81.21061899999999,35.704831],"type":"Point"}
}