{
  "type": "Feature",
  "properties": {
    "iso:country":"US",
    "sg:address":"5911 US Hwy 70 E",
    "sg:city":"Nebo",
    "sg:classifiers":[
        {
            "category":"Wholesale",
            "subcategory":"Non-durable Goods",
            "type":"Manufacturing & Wholesale Goods"
        }
    ],
    "sg:phone":"+1 828 652 2608",
    "sg:postcode":"28761",
    "sg:province":"NC",
    "wof:name":"Clinton Wholesale",
    "wof:placetype":"venue"
},
  "geometry": {"coordinates":[-81.91636,35.709536],"type":"Point"}
}