{
  "type": "Feature",
  "properties": {
    "addr:full":"10 W Main St Thomasville NC 27360",
    "addr:housenumber":"10",
    "addr:postcode":"27360",
    "addr:street":"W Main St",
    "iso:country":"US",
    "sg:address":"10 W Main St",
    "sg:city":"Thomasville",
    "sg:classifiers":[
        {
            "category":"Utilities",
            "subcategory":"Electric",
            "type":"Services"
        }
    ],
    "sg:phone":"+1 336 885 8071",
    "sg:postcode":"27360",
    "sg:province":"NC",
    "sg:tags":[
        "company"
    ],
    "wof:name":"Duke Power",
    "wof:placetype":"venue"
},
  "geometry": {"coordinates":[-80.082733,35.882913],"type":"Point"}
}