{
  "type": "Feature",
  "properties": {
    "addr:full":"1500 Midway Elementary School Rd Dunn NC 28334",
    "addr:housenumber":"1500",
    "addr:postcode":"28334",
    "addr:street":"Elementary School Rd",
    "iso:country":"US",
    "sg:address":"1500 Midway Elementary School Rd",
    "sg:city":"Dunn",
    "sg:classifiers":[
        {
            "category":"Education",
            "subcategory":"School",
            "type":"Public Place"
        }
    ],
    "sg:phone":"+1 910 567 2244",
    "sg:postcode":"28334",
    "sg:province":"NC",
    "sg:website":"www.sampson.k12.nc.us",
    "wof:name":"Midway Elementary School",
    "wof:placetype":"venue"
},
  "geometry": {"coordinates":[-78.505014,35.190563],"type":"Point"}
}