{
  "type": "Feature",
  "properties": {
    "iso:country":"US",
    "sg:address":"219 Dumont Dr",
    "sg:city":"Winston Salem",
    "sg:classifiers":[
        {
            "category":"Real Estate",
            "subcategory":"Real Estate Services",
            "type":"Services"
        }
    ],
    "sg:phone":"+1 336 784 5557",
    "sg:postcode":"27107",
    "sg:province":"NC",
    "sg:tags":[
        "abstract",
        "title"
    ],
    "wof:name":"Southern Title Services Inc",
    "wof:placetype":"venue"
},
  "geometry": {"coordinates":[-80.154651,36.090923],"type":"Point"}
}