{
  "type": "Feature",
  "properties": {
    "iso:country":"US",
    "sg:address":"100 Spindale St",
    "sg:city":"Spindale",
    "sg:classifiers":[
        {
            "category":"Manufacturing",
            "subcategory":"Apparel",
            "type":"Manufacturing & Wholesale Goods"
        },
        {
            "category":"Building & Trades",
            "subcategory":"Construction",
            "type":"Services"
        }
    ],
    "sg:phone":"+1 828 287 5599",
    "sg:postcode":"28160",
    "sg:province":"NC",
    "sg:tags":[
        "household",
        "mfg",
        "furnishing",
        "woodworker"
    ],
    "wof:name":"Manual Woodworkers Weavers Inc",
    "wof:placetype":"venue"
},
  "geometry": {"coordinates":[-81.928769,35.358582],"type":"Point"}
}