{
  "type": "Feature",
  "properties": {
    "iso:country":"US",
    "sg:address":"3605 Summit Ave",
    "sg:city":"Greensboro",
    "sg:classifiers":[
        {
            "category":"Organizations",
            "subcategory":"Religious Organization",
            "type":"Services"
        }
    ],
    "sg:phone":"+1 336 954 8441",
    "sg:postcode":"27405",
    "sg:province":"NC",
    "sg:tags":[
        "church"
    ],
    "wof:name":"North Greensboro Church Of God",
    "wof:placetype":"venue"
},
  "geometry": {"coordinates":[-79.76177800000001,36.129549],"type":"Point"}
}