{
  "type": "Feature",
  "properties": {
    "addr:full":"12457 US Hwy 421 Broadway NC 27505",
    "addr:housenumber":"12457",
    "addr:postcode":"27505",
    "addr:street":"Us Hwy 421",
    "iso:country":"US",
    "sg:address":"12457 US Hwy 421",
    "sg:city":"Broadway",
    "sg:classifiers":[
        {
            "category":"Food & Beverages",
            "subcategory":"Groceries & Convenience Stores",
            "type":"Retail Goods"
        }
    ],
    "sg:phone":"+1 919 258 5923",
    "sg:postcode":"27505",
    "sg:province":"NC",
    "wof:name":"Pantry Inc",
    "wof:placetype":"venue"
},
  "geometry": {"coordinates":[-79.031105,35.437463],"type":"Point"}
}