{
  "type": "Feature",
  "properties": {
    "iso:country":"US",
    "sg:address":"5427 Village Dr NW",
    "sg:city":"Concord",
    "sg:classifiers":[
        {
            "category":"Building & Trades",
            "subcategory":"Construction",
            "type":"Services"
        }
    ],
    "sg:phone":"+1 704 782 2666",
    "sg:postcode":"28027",
    "sg:province":"NC",
    "sg:tags":[
        "house",
        "general",
        "contractor"
    ],
    "wof:name":"David Wightman Homes",
    "wof:placetype":"venue"
},
  "geometry": {"coordinates":[-80.669603,35.414613],"type":"Point"}
}