{
  "type": "Feature",
  "properties": {
    "iso:country":"US",
    "sg:address":"6465 Goldfish Rd",
    "sg:city":"Kannapolis",
    "sg:classifiers":[
        {
            "category":"Shopping",
            "type":"Retail Goods"
        }
    ],
    "sg:phone":"+1 704 933 1798",
    "sg:postcode":"28083",
    "sg:province":"NC",
    "sg:tags":[
        "pet",
        "shop"
    ],
    "wof:name":"Greendale Tropical & Saltwater",
    "wof:placetype":"venue"
},
  "geometry": {"coordinates":[-80.55642,35.513833],"type":"Point"}
}