{
  "type": "Feature",
  "properties": {
    "iso:country":"US",
    "sg:address":"115 Foothills Dr",
    "sg:city":"Morganton",
    "sg:classifiers":[
        {
            "category":"Health Services",
            "subcategory":"Doctor",
            "type":"Services"
        }
    ],
    "sg:phone":"+1   ",
    "sg:postcode":"28655",
    "sg:province":"NC",
    "sg:tags":[
        "medical"
    ],
    "wof:name":"Deekens S Andrews MD",
    "wof:placetype":"venue"
},
  "geometry": {"coordinates":[-81.651869,35.728105],"type":"Point"}
}