{
  "type": "Feature",
  "properties": {
    "addr:full":"212 Westmont Dr Fayetteville NC 28305",
    "addr:housenumber":"212",
    "addr:postcode":"28305",
    "addr:street":"Westmont Dr",
    "iso:country":"US",
    "sg:address":"212 Westmont Dr",
    "sg:city":"Fayetteville",
    "sg:classifiers":[
        {
            "category":"Health Services",
            "subcategory":"Doctor",
            "type":"Services"
        }
    ],
    "sg:phone":"+1   ",
    "sg:postcode":"28305",
    "sg:province":"NC",
    "sg:tags":[
        "physician"
    ],
    "wof:name":"Morgan Radiology Pa",
    "wof:placetype":"venue"
},
  "geometry": {"coordinates":[-78.90519,35.061594],"type":"Point"}
}