{
  "type": "Feature",
  "properties": {
    "addr:full":"608 Moores Pond Rd Youngsville NC 27549",
    "addr:housenumber":"608",
    "addr:postcode":"27549",
    "addr:street":"Moores Pond Rd",
    "iso:country":"US",
    "sg:address":"608 Moores Pond Rd",
    "sg:city":"Youngsville",
    "sg:classifiers":[
        {
            "category":"Organizations",
            "subcategory":"Religious Organization",
            "type":"Services"
        }
    ],
    "sg:phone":"+1 919 556 7581",
    "sg:postcode":"27549",
    "sg:province":"NC",
    "sg:tags":[
        "church"
    ],
    "wof:name":"Little Zion Missionary Baptist",
    "wof:placetype":"venue"
},
  "geometry": {"coordinates":[-78.414073,36.005682],"type":"Point"}
}