{
  "type": "Feature",
  "properties": {
    "addr:full":"6258 Boston Rd Roxboro NC 27574",
    "addr:housenumber":"6258",
    "addr:postcode":"27574",
    "addr:street":"Boston Rd",
    "iso:country":"US",
    "sg:address":"6258 Boston Rd",
    "sg:city":"Roxboro",
    "sg:classifiers":[
        {
            "category":"Social Services",
            "subcategory":"Child Care",
            "type":"Services"
        }
    ],
    "sg:phone":"+1 336 599 3927",
    "sg:postcode":"27574",
    "sg:province":"NC",
    "wof:name":"Golden Years Family Care Home",
    "wof:placetype":"venue"
},
  "geometry": {"coordinates":[-78.93388299999999,36.448577],"type":"Point"}
}