{
  "type": "Feature",
  "properties": {
    "iso:country":"US",
    "sg:address":"2717 Chapel Hill Rd",
    "sg:city":"Durham",
    "sg:classifiers":[
        {
            "category":"Personal",
            "subcategory":"Beauty Salon",
            "type":"Services"
        }
    ],
    "sg:phone":"+1 919 493 1355",
    "sg:postcode":"27707",
    "sg:province":"NC",
    "wof:name":"Hairy Dayz",
    "wof:placetype":"venue"
},
  "geometry": {"coordinates":[-78.936314,35.976378],"type":"Point"}
}