{
  "type": "Feature",
  "properties": {
    "addr:full":"620 Green Valley Rd Greensboro NC 27408",
    "addr:housenumber":"620",
    "addr:postcode":"27408",
    "addr:street":"Green Valley Rd",
    "iso:country":"US",
    "sg:address":"620 Green Valley Rd",
    "sg:city":"Greensboro",
    "sg:classifiers":[
        {
            "category":"Insurance",
            "subcategory":"Life Insurance",
            "type":"Services"
        }
    ],
    "sg:phone":"+1 336 292 7908",
    "sg:postcode":"27408",
    "sg:province":"NC",
    "sg:tags":[
        "carrier"
    ],
    "wof:name":"Great Western Life & Annuity",
    "wof:placetype":"venue"
},
  "geometry": {"coordinates":[-79.82563399999999,36.088338],"type":"Point"}
}