{
  "type": "Feature",
  "properties": {
    "iso:country":"US",
    "sg:address":"125 Drawbridge Ct",
    "sg:city":"Mooresville",
    "sg:classifiers":[
        {
            "category":"Professional",
            "subcategory":"Business Services",
            "type":"Services"
        }
    ],
    "sg:phone":"+1   ",
    "sg:postcode":"28117",
    "sg:province":"NC",
    "wof:name":"Munro Tavormina & Assoc",
    "wof:placetype":"venue"
},
  "geometry": {"coordinates":[-80.84679300000001,35.578937],"type":"Point"}
}