{
  "type": "Feature",
  "properties": {
    "addr:full":"3400 Queensferry Dr Wilson NC 27896",
    "addr:postcode":"3400;27896",
    "addr:street":"Queensferry Dr",
    "iso:country":"US",
    "sg:address":"3400 Queensferry Dr",
    "sg:city":"Wilson",
    "sg:classifiers":[
        {
            "category":"Autos & Motor Vehicles",
            "subcategory":"Automobile Sales",
            "type":"Retail Goods"
        }
    ],
    "sg:phone":"+1 252 291 4856",
    "sg:postcode":"27896",
    "sg:province":"NC",
    "sg:tags":[
        "car",
        "dealer"
    ],
    "wof:name":"G & M Capital",
    "wof:placetype":"venue"
},
  "geometry": {"coordinates":[-77.952127,35.75682],"type":"Point"}
}