{
  "type": "Feature",
  "properties": {
    "addr:full":"107 Catherine St Winfall NC 27985",
    "addr:housenumber":"107",
    "addr:postcode":"27985",
    "addr:street":"Catherine St",
    "iso:country":"US",
    "sg:address":"107 Catherine St",
    "sg:city":"Winfall",
    "sg:classifiers":[
        {
            "category":"Food & Beverages",
            "subcategory":"Groceries & Convenience Stores",
            "type":"Retail Goods"
        }
    ],
    "sg:phone":"+1 252 426 7321",
    "sg:postcode":"27985",
    "sg:province":"NC",
    "wof:name":"Layden's Country Convenience",
    "wof:placetype":"venue"
},
  "geometry": {"coordinates":[-76.46306,36.217123],"type":"Point"}
}