{
  "type": "Feature",
  "properties": {
    "addr:full":"2136 S Church St Burlington NC 27215",
    "addr:housenumber":"2136",
    "addr:postcode":"27215",
    "addr:street":"S Church St",
    "iso:country":"US",
    "sg:address":"2136 S Church St",
    "sg:city":"Burlington",
    "sg:classifiers":[
        {
            "category":"Personal",
            "subcategory":"Beauty Salon",
            "type":"Services"
        }
    ],
    "sg:phone":"+1 336 229 9882",
    "sg:postcode":"27215",
    "sg:province":"NC",
    "sg:tags":[
        "shop"
    ],
    "wof:name":"Angel's Hair Studio",
    "wof:placetype":"venue"
},
  "geometry": {"coordinates":[-79.467208,36.082361],"type":"Point"}
}