{
  "type": "Feature",
  "properties": {
    "iso:country":"US",
    "sg:address":"1445 Andrews Rd",
    "sg:city":"Murphy",
    "sg:classifiers":[
        {
            "category":"Shopping",
            "subcategory":"Discount & Variety Stores",
            "type":"Retail Goods"
        }
    ],
    "sg:phone":"+1 828 837 7131",
    "sg:postcode":"28906",
    "sg:province":"NC",
    "sg:website":"http://www.dollargeneral.com",
    "wof:name":"Dollar General",
    "wof:placetype":"venue"
},
  "geometry": {"coordinates":[-84.009911,35.108929],"type":"Point"}
}