{
  "type": "Feature",
  "properties": {
    "iso:country":"US",
    "sg:address":"122 Cedar Trl",
    "sg:city":"Winston Salem",
    "sg:classifiers":[
        {
            "category":"Professional",
            "type":"Services"
        }
    ],
    "sg:phone":"+1 336 760 2777",
    "sg:postcode":"27104",
    "sg:province":"NC",
    "wof:name":"Sheila Cote",
    "wof:placetype":"venue"
},
  "geometry": {"coordinates":[-80.345218,36.097816],"type":"Point"}
}