{
  "type": "Feature",
  "properties": {
    "iso:country":"US",
    "sg:address":"103 3rd St SE",
    "sg:city":"Conover",
    "sg:classifiers":[
        {
            "category":"Insurance",
            "subcategory":"Insurance Agent",
            "type":"Services"
        }
    ],
    "sg:phone":"+1 828 465 1350",
    "sg:postcode":"28613",
    "sg:province":"NC",
    "wof:name":"H Smitty Bolick Insurance",
    "wof:placetype":"venue"
},
  "geometry": {"coordinates":[-81.219103,35.704431],"type":"Point"}
}