{
  "type": "Feature",
  "properties": {
    "addr:full":"202 Tabor View Ln Winston Salem NC 27106",
    "addr:housenumber":"202",
    "addr:postcode":"27106",
    "addr:street":"Tabor View Ln",
    "iso:country":"US",
    "sg:address":"202 Tabor View Ln",
    "sg:city":"Winston Salem",
    "sg:classifiers":[
        {
            "category":"Wholesale",
            "subcategory":"Hardware",
            "type":"Manufacturing & Wholesale Goods"
        }
    ],
    "sg:phone":"+1 336 760 3149",
    "sg:postcode":"27106",
    "sg:province":"NC",
    "sg:tags":[
        "heater",
        "le",
        "tank",
        "heating",
        "water",
        "cooling"
    ],
    "wof:name":"Advanced Environmental Systems",
    "wof:placetype":"venue"
},
  "geometry": {"coordinates":[-80.303445,36.127525],"type":"Point"}
}