{
  "type": "Feature",
  "properties": {
    "addr:full":"3126 Milton Rd Charlotte NC 28215",
    "addr:housenumber":"3126",
    "addr:postcode":"28215",
    "addr:street":"Milton Rd",
    "iso:country":"US",
    "sg:address":"3126 Milton Rd",
    "sg:city":"Charlotte",
    "sg:classifiers":[
        {
            "category":"Arts & Performance",
            "subcategory":"Theater",
            "type":"Entertainment"
        }
    ],
    "sg:phone":"+1 704 563 9696",
    "sg:postcode":"28215",
    "sg:province":"NC",
    "sg:tags":[
        "bureau"
    ],
    "wof:name":"Secret Entertainment",
    "wof:placetype":"venue"
},
  "geometry": {"coordinates":[-80.73627999999999,35.2367],"type":"Point"}
}