{
  "type": "Feature",
  "properties": {
    "addr:full":"407 E West St Southport NC 28461",
    "addr:housenumber":"407 e",
    "addr:postcode":"28461",
    "addr:street":"West St",
    "iso:country":"US",
    "sg:address":"407 E West St",
    "sg:city":"Southport",
    "sg:classifiers":[
        {
            "category":"Organizations",
            "subcategory":"Religious Organization",
            "type":"Services"
        }
    ],
    "sg:phone":"+1 910 457 6857",
    "sg:postcode":"28461",
    "sg:province":"NC",
    "sg:tags":[
        "church"
    ],
    "wof:name":"Saint James AME Zion",
    "wof:placetype":"venue"
},
  "geometry": {"coordinates":[-78.01652900000001,33.921913],"type":"Point"}
}