{
  "type": "Feature",
  "properties": {
    "addr:full":"407 Memorial Dr Warsaw NC 28398",
    "addr:housenumber":"407",
    "addr:postcode":"28398",
    "addr:street":"Memorial Dr",
    "iso:country":"US",
    "sg:address":"407 Memorial Dr",
    "sg:city":"Warsaw",
    "sg:classifiers":[
        {
            "category":"Manufacturing",
            "subcategory":"Signs",
            "type":"Manufacturing & Wholesale Goods"
        }
    ],
    "sg:phone":"+1 910 293 4884",
    "sg:postcode":"28398",
    "sg:province":"NC",
    "wof:name":"L & L Signs & Designs",
    "wof:placetype":"venue"
},
  "geometry": {"coordinates":[-78.09082600000001,35.006421],"type":"Point"}
}