{
  "type": "Feature",
  "properties": {
    "addr:full":"2507 Nash St NW Wilson NC 27896",
    "addr:housenumber":"2507",
    "addr:postcode":"27896",
    "addr:street":"Nash St Nw",
    "iso:country":"US",
    "sg:address":"2507 Nash St NW",
    "sg:city":"Wilson",
    "sg:classifiers":[
        {
            "category":"Real Estate",
            "subcategory":"Real Estate Operator",
            "type":"Services"
        }
    ],
    "sg:phone":"+1 252 291 9139",
    "sg:postcode":"27896",
    "sg:province":"NC",
    "sg:tags":[
        "building",
        "nonresidential"
    ],
    "sg:website":"www.wilsoncoldwellbanker.com",
    "wof:name":"Gregory Properties",
    "wof:placetype":"venue"
},
  "geometry": {"coordinates":[-77.934032,35.76054],"type":"Point"}
}