{
  "type": "Feature",
  "properties": {
    "iso:country":"US",
    "sg:address":"3901 State Hwy 62",
    "sg:city":"Liberty",
    "sg:classifiers":[
        {
            "category":"Retail",
            "subcategory":"Auto Repair",
            "type":"Services"
        }
    ],
    "sg:phone":"+1 336 685 9448",
    "sg:postcode":"27298",
    "sg:province":"NC",
    "sg:tags":[
        "repairing",
        "automobile"
    ],
    "wof:name":"Shoffner Automotive & Svc",
    "wof:placetype":"venue"
},
  "geometry": {"coordinates":[-79.540159,35.993504],"type":"Point"}
}