{
  "type": "Feature",
  "properties": {
    "addr:full":"1111 Middle Sound Loop Rd Wilmington NC 28411",
    "addr:housenumber":"1111",
    "addr:postcode":"28411",
    "addr:street":"Middle Sound Loop Rd",
    "iso:country":"US",
    "sg:address":"1111 Middle Sound Loop Rd",
    "sg:city":"Wilmington",
    "sg:classifiers":[
        {
            "category":"Home & Garden",
            "subcategory":"Carpets & Floor Coverings",
            "type":"Retail Goods"
        }
    ],
    "sg:phone":"+1 910 231 7227",
    "sg:postcode":"28411",
    "sg:province":"NC",
    "sg:tags":[
        "dealer",
        "rug"
    ],
    "wof:name":"Premiere Carpet & Tile",
    "wof:placetype":"venue"
},
  "geometry": {"coordinates":[-77.792215,34.269615],"type":"Point"}
}