{
  "type": "Feature",
  "properties": {
    "iso:country":"US",
    "sg:address":"1905 Rouse Rd",
    "sg:city":"Kinston",
    "sg:classifiers":[
        {
            "category":"Building & Trades",
            "subcategory":"Cleaning & Sanitation",
            "type":"Services"
        }
    ],
    "sg:phone":"+1 252 527 4260",
    "sg:postcode":"28504",
    "sg:province":"NC",
    "sg:tags":[
        "janitor"
    ],
    "wof:name":"Lawson Services",
    "wof:placetype":"venue"
},
  "geometry": {"coordinates":[-77.62106799999999,35.28892],"type":"Point"}
}