{
  "type": "Feature",
  "properties": {
    "iso:country":"US",
    "sg:address":"2001 Canterbury Rd",
    "sg:city":"Clayton",
    "sg:classifiers":[
        {
            "category":"Professional",
            "subcategory":"Business Services",
            "type":"Services"
        }
    ],
    "sg:phone":"+1   ",
    "sg:postcode":"27520",
    "sg:province":"NC",
    "wof:name":"Concerned Bikers Assoc",
    "wof:placetype":"venue"
},
  "geometry": {"coordinates":[-78.50323299999999,35.613118],"type":"Point"}
}