{
  "type": "Feature",
  "properties": {
    "iso:country":"US",
    "sg:address":"407 Becker Dr",
    "sg:city":"Roanoke Rapids",
    "sg:classifiers":[
        {
            "category":"Personal",
            "subcategory":"Beauty Salon",
            "type":"Services"
        }
    ],
    "sg:phone":"+1 252 537 1533",
    "sg:postcode":"27870",
    "sg:province":"NC",
    "sg:tags":[
        "shop"
    ],
    "wof:name":"Naomi & Company",
    "wof:placetype":"venue"
},
  "geometry": {"coordinates":[-77.636841,36.440654],"type":"Point"}
}