{
  "type": "Feature",
  "properties": {
    "iso:country":"US",
    "sg:address":"4905 Sunset Forest Cir",
    "sg:city":"Holly Springs",
    "sg:classifiers":[
        {
            "category":"Professional",
            "subcategory":"Research",
            "type":"Services"
        }
    ],
    "sg:phone":"+1 919 557 0551",
    "sg:postcode":"27540",
    "sg:province":"NC",
    "sg:tags":[
        "development",
        "laboratory"
    ],
    "wof:name":"Axios Group Inc",
    "wof:placetype":"venue"
},
  "geometry": {"coordinates":[-78.805809,35.658042],"type":"Point"}
}