{
  "type": "Feature",
  "properties": {
    "addr:full":"5104 Reagan Dr Charlotte NC 28206",
    "addr:housenumber":"5104",
    "addr:postcode":"28206",
    "addr:street":"Reagan Dr",
    "iso:country":"US",
    "sg:address":"5104 Reagan Dr",
    "sg:city":"Charlotte",
    "sg:classifiers":[
        {
            "category":"Professional",
            "subcategory":"Business Services",
            "type":"Services"
        }
    ],
    "sg:phone":"+1   ",
    "sg:postcode":"28206",
    "sg:province":"NC",
    "wof:name":"Icandi Art",
    "wof:placetype":"venue"
},
  "geometry": {"coordinates":[-80.79746799999999,35.277334],"type":"Point"}
}