{
  "type": "Feature",
  "properties": {
    "addr:full":"3924 Taylors Bridge Hwy Clinton NC 28328",
    "addr:housenumber":"3924",
    "addr:postcode":"28328",
    "addr:street":"Taylors Bridge Hwy",
    "iso:country":"US",
    "sg:address":"3924 Taylors Bridge Hwy",
    "sg:city":"Clinton",
    "sg:classifiers":[
        {
            "category":"Food & Beverages",
            "subcategory":"Groceries & Convenience Stores",
            "type":"Retail Goods"
        }
    ],
    "sg:phone":"+1 910 592 6098",
    "sg:postcode":"28328",
    "sg:province":"NC",
    "sg:tags":[
        "grocer"
    ],
    "wof:name":"Easy-O-Mart",
    "wof:placetype":"venue"
},
  "geometry": {"coordinates":[-78.254496,34.91485],"type":"Point"}
}