{
  "type": "Feature",
  "properties": {
    "addr:full":"226 Glen Raven Rd Burlington NC 27217",
    "addr:housenumber":"226",
    "addr:postcode":"27217",
    "addr:street":"Glen Raven Rd",
    "iso:country":"US",
    "sg:address":"226 Glen Raven Rd",
    "sg:city":"Burlington",
    "sg:classifiers":[
        {
            "category":"Professional",
            "type":"Services"
        }
    ],
    "sg:phone":"+1 336 226 0141",
    "sg:postcode":"27217",
    "sg:province":"NC",
    "sg:tags":[
        "establishment"
    ],
    "wof:name":"National Spinning Co",
    "wof:placetype":"venue"
},
  "geometry": {"coordinates":[-79.463832,36.111028],"type":"Point"}
}