{
  "type": "Feature",
  "properties": {
    "addr:full":"8320 Falls of Neuse Rd Raleigh NC 27615",
    "addr:housenumber":"8320",
    "addr:postcode":"27615",
    "addr:street":"Falls Of Neuse Rd",
    "iso:country":"US",
    "sg:address":"8320 Falls of Neuse Rd",
    "sg:city":"Raleigh",
    "sg:classifiers":[
        {
            "category":"Real Estate",
            "subcategory":"Developer",
            "type":"Services"
        }
    ],
    "sg:phone":"+1 919 841 0703",
    "sg:postcode":"27615",
    "sg:province":"NC",
    "wof:name":"I R Development",
    "wof:placetype":"venue"
},
  "geometry": {"coordinates":[-78.62128,35.894186],"type":"Point"}
}