{
  "type": "Feature",
  "properties": {
    "iso:country":"US",
    "sg:address":"2231 Lake Wendell Rd",
    "sg:city":"Wendell",
    "sg:classifiers":[
        {
            "category":"Freight",
            "type":"Transportation"
        },
        {
            "category":"Retail",
            "subcategory":"Auto Rental",
            "type":"Services"
        }
    ],
    "sg:phone":"+1 919 365 3057",
    "sg:postcode":"27591",
    "sg:province":"NC",
    "sg:tags":[
        "storage",
        "commercial",
        "trailer",
        "utility"
    ],
    "wof:name":"A-Mobile Mini Inc",
    "wof:placetype":"venue"
},
  "geometry": {"coordinates":[-78.35295600000001,35.729054],"type":"Point"}
}