{
  "type": "Feature",
  "properties": {
    "addr:full":"223 W Main Ave Gastonia NC 28052",
    "addr:housenumber":"223",
    "addr:postcode":"28052",
    "addr:street":"W Main Ave",
    "iso:country":"US",
    "sg:address":"223 W Main Ave",
    "sg:city":"Gastonia",
    "sg:classifiers":[
        {
            "category":"Professional",
            "subcategory":"Lawyer & Legal Services",
            "type":"Services"
        }
    ],
    "sg:phone":"+1 704 864 3236",
    "sg:postcode":"28052",
    "sg:province":"NC",
    "sg:tags":[
        "attorney"
    ],
    "wof:name":"Katzenstein & Lorance",
    "wof:placetype":"venue"
},
  "geometry": {"coordinates":[-81.18537000000001,35.263699],"type":"Point"}
}