{
  "type": "Feature",
  "properties": {
    "iso:country":"US",
    "sg:address":"3317 New Salem Rd",
    "sg:city":"Monroe",
    "sg:classifiers":[
        {
            "category":"Building & Trades",
            "subcategory":"Plumbing",
            "type":"Services"
        }
    ],
    "sg:phone":"+1 704 289 7637",
    "sg:postcode":"28110",
    "sg:province":"NC",
    "sg:tags":[
        "septic"
    ],
    "wof:name":"A Stevens Septic Tank Svc",
    "wof:placetype":"venue"
},
  "geometry": {"coordinates":[-80.441097,35.06733],"type":"Point"}
}