{
  "type": "Feature",
  "properties": {
    "addr:full":"313 W Main St Durham NC 27701",
    "addr:housenumber":"313",
    "addr:postcode":"27701",
    "addr:street":"W Main St",
    "iso:country":"US",
    "sg:address":"313 W Main St",
    "sg:city":"Durham",
    "sg:classifiers":[
        {
            "category":"Organizations",
            "subcategory":"Religious Organization",
            "type":"Services"
        }
    ],
    "sg:phone":"+1   ",
    "sg:postcode":"27701",
    "sg:province":"NC",
    "wof:name":"Gods Resurrection Church of C",
    "wof:placetype":"venue"
},
  "geometry": {"coordinates":[-78.903874,35.996748],"type":"Point"}
}