{
  "type": "Feature",
  "properties": {
    "iso:country":"US",
    "sg:address":"1 Oak Ln",
    "sg:city":"Asheville",
    "sg:classifiers":[
        {
            "category":"Professional",
            "type":"Services"
        }
    ],
    "sg:phone":"+1 828 285 0406",
    "sg:postcode":"28801",
    "sg:province":"NC",
    "sg:tags":[
        "establishment"
    ],
    "wof:name":"One Oak Plaza Maintenance",
    "wof:placetype":"venue"
},
  "geometry": {"coordinates":[-82.544591,35.609595],"type":"Point"}
}