{
  "type": "Feature",
  "properties": {
    "addr:full":"4025 Premier Dr High Point NC 27265",
    "addr:housenumber":"4025",
    "addr:postcode":"27265",
    "addr:street":"Premier Dr",
    "iso:country":"US",
    "sg:address":"4025 Premier Dr",
    "sg:city":"High Point",
    "sg:classifiers":[
        {
            "category":"Banks & Credit Unions",
            "subcategory":"Bank",
            "type":"Services"
        }
    ],
    "sg:phone":"+1 336 888 0221",
    "sg:postcode":"27265",
    "sg:province":"NC",
    "sg:website":"www.bbandt.com",
    "wof:name":"B B & T",
    "wof:placetype":"venue"
},
  "geometry": {"coordinates":[-79.96053499999999,36.039275],"type":"Point"}
}