{
  "type": "Feature",
  "properties": {
    "addr:full":"413 W Main St Williamston NC 27892",
    "addr:housenumber":"413",
    "addr:postcode":"27892",
    "addr:street":"W Main St",
    "iso:country":"US",
    "sg:address":"413 W Main St",
    "sg:city":"Williamston",
    "sg:classifiers":[
        {
            "category":"Professional",
            "subcategory":"Lawyer & Legal Services",
            "type":"Services"
        }
    ],
    "sg:phone":"+1 252 809 4930",
    "sg:postcode":"27892",
    "sg:province":"NC",
    "sg:tags":[
        "attorney"
    ],
    "wof:name":"Irvine Law Firm",
    "wof:placetype":"venue"
},
  "geometry": {"coordinates":[-77.058818,35.85279],"type":"Point"}
}