{
  "type": "Feature",
  "properties": {
    "addr:full":"315 S Grace St Rocky Mount NC 27804",
    "addr:housenumber":"315",
    "addr:postcode":"27804",
    "addr:street":"S Grace St",
    "iso:country":"US",
    "sg:address":"315 S Grace St",
    "sg:city":"Rocky Mount",
    "sg:classifiers":[
        {
            "category":"Government",
            "subcategory":"Office",
            "type":"Public Place"
        }
    ],
    "sg:phone":"+1 252 442 4134",
    "sg:postcode":"27804",
    "sg:province":"NC",
    "sg:tags":[
        "housing",
        "program"
    ],
    "wof:name":"Signature Communities",
    "wof:placetype":"venue"
},
  "geometry": {"coordinates":[-77.802632,35.940836],"type":"Point"}
}