{
  "type": "Feature",
  "properties": {
    "addr:full":"202 E Washington St Mebane NC 27302",
    "addr:housenumber":"202",
    "addr:postcode":"27302",
    "addr:street":"E Washington St",
    "iso:country":"US",
    "sg:address":"202 E Washington St",
    "sg:city":"Mebane",
    "sg:classifiers":[
        {
            "category":"Organizations",
            "subcategory":"Membership Organization",
            "type":"Services"
        }
    ],
    "sg:phone":"+1   ",
    "sg:postcode":"27302",
    "sg:province":"NC",
    "wof:name":"NC Forestry Association",
    "wof:placetype":"venue"
},
  "geometry": {"coordinates":[-79.26673099999999,36.095333],"type":"Point"}
}