{
  "type": "Feature",
  "properties": {
    "iso:country":"US",
    "sg:address":"2420 US Hwy 64",
    "sg:city":"Highlands",
    "sg:classifiers":[
        {
            "category":"Professional",
            "subcategory":"Management & Consulting",
            "type":"Services"
        }
    ],
    "sg:phone":"+1 828 526 4200",
    "sg:postcode":"28741",
    "sg:province":"NC",
    "sg:tags":[
        "communications",
        "consultant"
    ],
    "wof:name":"Cooper Co",
    "wof:placetype":"venue"
},
  "geometry": {"coordinates":[-83.189646,35.074636],"type":"Point"}
}