{
  "type": "Feature",
  "properties": {
    "addr:full":"7554 US Hwy 29 Browns Summit NC 27214",
    "addr:housenumber":"7554",
    "addr:postcode":"27214",
    "addr:street":"Us Hwy 29",
    "iso:country":"US",
    "sg:address":"7554 US Hwy 29",
    "sg:city":"Browns Summit",
    "sg:classifiers":[
        {
            "category":"Personal",
            "subcategory":"Barber",
            "type":"Services"
        }
    ],
    "sg:phone":"+1 336 656 3820",
    "sg:postcode":"27214",
    "sg:province":"NC",
    "wof:name":"Faison Barber Shop",
    "wof:placetype":"venue"
},
  "geometry": {"coordinates":[-79.67682000000001,36.230306],"type":"Point"}
}