{
  "type": "Feature",
  "properties": {
    "iso:country":"US",
    "sg:address":"2201 Jefferson Davis Hwy",
    "sg:city":"Sanford",
    "sg:classifiers":[
        {
            "category":"Communications",
            "subcategory":"Radio Station",
            "type":"Services"
        }
    ],
    "sg:phone":"+1 919 776 0123",
    "sg:postcode":"27330",
    "sg:province":"NC",
    "sg:tags":[
        "company",
        "broadcasting"
    ],
    "wof:name":"WFJA Oldies",
    "wof:placetype":"venue"
},
  "geometry": {"coordinates":[-79.21698000000001,35.439957],"type":"Point"}
}