{
  "type": "Feature",
  "properties": {
    "iso:country":"US",
    "sg:address":"490 Debra Cir SW",
    "sg:city":"Concord",
    "sg:classifiers":[
        {
            "category":"Organizations",
            "subcategory":"Religious Organization",
            "type":"Services"
        }
    ],
    "sg:phone":"+1   ",
    "sg:postcode":"28025",
    "sg:province":"NC",
    "wof:name":"Macedonia Church of God",
    "wof:placetype":"venue"
},
  "geometry": {"coordinates":[-80.584254,35.367475],"type":"Point"}
}