{
  "type": "Feature",
  "properties": {
    "iso:country":"US",
    "sg:address":"8658 New Sandy Hill Church Rd",
    "sg:city":"Bailey",
    "sg:classifiers":[
        {
            "category":"Organizations",
            "subcategory":"Religious Organization",
            "type":"Services"
        }
    ],
    "sg:phone":"+1 252 235 4256",
    "sg:postcode":"27807",
    "sg:province":"NC",
    "sg:tags":[
        "church"
    ],
    "wof:name":"Pleasant Grove United Meth",
    "wof:placetype":"venue"
},
  "geometry": {"coordinates":[-78.142321,35.7443],"type":"Point"}
}