{
  "type": "Feature",
  "properties": {
    "addr:full":"123 2nd Ave NW Hickory NC 28601",
    "addr:housenumber":"123",
    "addr:postcode":"28601",
    "addr:street":"2Nd Ave Nw",
    "iso:country":"US",
    "sg:address":"123 2nd Ave NW",
    "sg:city":"Hickory",
    "sg:classifiers":[
        {
            "category":"Health Services",
            "subcategory":"Nursing And Care Facility",
            "type":"Services"
        }
    ],
    "sg:phone":"+1 828 327 7166",
    "sg:postcode":"28601",
    "sg:province":"NC",
    "sg:tags":[
        "skilled"
    ],
    "wof:name":"Genesis",
    "wof:placetype":"venue"
},
  "geometry": {"coordinates":[-81.33859699999999,35.734271],"type":"Point"}
}