{
  "type": "Feature",
  "properties": {
    "iso:country":"US",
    "sg:address":"214 N Tryon St",
    "sg:city":"Charlotte",
    "sg:classifiers":[
        {
            "category":"Banks & Credit Unions",
            "subcategory":"Bank",
            "type":"Services"
        }
    ],
    "sg:phone":"+1 704 632 1434",
    "sg:postcode":"28202",
    "sg:province":"NC",
    "wof:name":"Bank Of America",
    "wof:placetype":"venue"
},
  "geometry": {"coordinates":[-80.840915,35.228605],"type":"Point"}
}