{
  "type": "Feature",
  "properties": {
    "addr:full":"8119 Lansford Rd Charlotte NC 28277",
    "addr:housenumber":"8119",
    "addr:postcode":"28277",
    "addr:street":"Lansford Rd",
    "iso:country":"US",
    "sg:address":"8119 Lansford Rd",
    "sg:city":"Charlotte",
    "sg:classifiers":[
        {
            "category":"Professional",
            "type":"Services"
        }
    ],
    "sg:phone":"+1 704 759 8691",
    "sg:postcode":"28277",
    "sg:province":"NC",
    "wof:name":"Extreme Resources Inc",
    "wof:placetype":"venue"
},
  "geometry": {"coordinates":[-80.82709699999999,35.048472],"type":"Point"}
}