{
  "type": "Feature",
  "properties": {
    "iso:country":"US",
    "sg:address":"104 Jefferson St",
    "sg:city":"Hamlet",
    "sg:classifiers":[
        {
            "category":"Health Services",
            "subcategory":"Doctor",
            "type":"Services"
        }
    ],
    "sg:phone":"+1 910 205 8600",
    "sg:postcode":"28345",
    "sg:province":"NC",
    "sg:tags":[
        "physician",
        "surgeon"
    ],
    "wof:name":"Afaque Akhtar MD",
    "wof:placetype":"venue"
},
  "geometry": {"coordinates":[-79.702483,34.88655],"type":"Point"}
}