{
  "type": "Feature",
  "properties": {
    "addr:full":"111 Commercial Blvd Flat Rock NC 28731",
    "addr:housenumber":"111",
    "addr:postcode":"28731",
    "addr:street":"Commercial Blvd",
    "iso:country":"US",
    "sg:address":"111 Commercial Blvd",
    "sg:city":"Flat Rock",
    "sg:classifiers":[
        {
            "category":"Travel",
            "subcategory":"Hotels & Motels",
            "type":"Entertainment"
        }
    ],
    "sg:phone":"+1 828 698 8899",
    "sg:postcode":"28731",
    "sg:province":"NC",
    "wof:name":"Holiday Inn Express",
    "wof:placetype":"venue"
},
  "geometry": {"coordinates":[-82.409916,35.295847],"type":"Point"}
}