{
  "type": "Feature",
  "properties": {
    "iso:country":"US",
    "sg:address":"11000 Randleman Rd",
    "sg:city":"Randleman",
    "sg:classifiers":[
        {
            "category":"Retail",
            "subcategory":"Auto Repair",
            "type":"Services"
        }
    ],
    "sg:phone":"+1   ",
    "sg:postcode":"27317",
    "sg:province":"NC",
    "sg:tags":[
        "shop",
        "automotive",
        "general"
    ],
    "wof:name":"Jeff Kivet Auto Care Inc",
    "wof:placetype":"venue"
},
  "geometry": {"coordinates":[-79.81004799999999,35.90887],"type":"Point"}
}