{
  "type": "Feature",
  "properties": {
    "addr:full":"7522 Brame Rd Kenly NC 27542",
    "addr:housenumber":"7522",
    "addr:postcode":"27542",
    "addr:street":"Brame Rd",
    "iso:country":"US",
    "sg:address":"7522 Brame Rd",
    "sg:city":"Kenly",
    "sg:classifiers":[
        {
            "category":"Building & Trades",
            "subcategory":"Electrical",
            "type":"Services"
        }
    ],
    "sg:phone":"+1 252 246 9037",
    "sg:postcode":"27542",
    "sg:province":"NC",
    "sg:tags":[
        "telecommunication",
        "contractor"
    ],
    "wof:name":"HTI",
    "wof:placetype":"venue"
},
  "geometry": {"coordinates":[-78.090628,35.678642],"type":"Point"}
}