{
  "type": "Feature",
  "properties": {
    "addr:full":"4565 Long Beach Rd SE Southport NC 28461",
    "addr:housenumber":"4565",
    "addr:postcode":"28461",
    "addr:street":"Long Beach Rd Se",
    "iso:country":"US",
    "sg:address":"4565 Long Beach Rd SE",
    "sg:city":"Southport",
    "sg:classifiers":[
        {
            "category":"Real Estate",
            "subcategory":"Real Estate Agent",
            "type":"Services"
        }
    ],
    "sg:phone":"+1 910 202 1180",
    "sg:postcode":"28461",
    "sg:province":"NC",
    "sg:tags":[
        "management"
    ],
    "wof:name":"Southern Retreats",
    "wof:placetype":"venue"
},
  "geometry": {"coordinates":[-78.059651,33.940824],"type":"Point"}
}