{
  "type": "Feature",
  "properties": {
    "iso:country":"US",
    "sg:address":"10130 Ocean Hwy W",
    "sg:city":"Calabash",
    "sg:classifiers":[
        {
            "category":"Real Estate",
            "subcategory":"Real Estate Agent",
            "type":"Services"
        }
    ],
    "sg:phone":"+1 910 579 4200",
    "sg:postcode":"28467",
    "sg:province":"NC",
    "wof:name":"CEDAC Builders & Realty",
    "wof:placetype":"venue"
},
  "geometry": {"coordinates":[-78.590107,33.898952],"type":"Point"}
}