{
  "type": "Feature",
  "properties": {
    "iso:country":"US",
    "sg:address":"5853 US Hwy 701 N",
    "sg:city":"Elizabethtown",
    "sg:classifiers":[
        {
            "category":"Government",
            "subcategory":"Jail",
            "type":"Public Place"
        }
    ],
    "sg:phone":"+1 910 862 3107",
    "sg:postcode":"28337",
    "sg:province":"NC",
    "sg:tags":[
        "correctional",
        "institution"
    ],
    "wof:name":"Bladen Correctional Center",
    "wof:placetype":"venue"
},
  "geometry": {"coordinates":[-78.521969,34.650164],"type":"Point"}
}