{
  "type": "Feature",
  "properties": {
    "addr:full":"1672 Crows Foot Rd Mount Olive NC 28365",
    "addr:housenumber":"1672",
    "addr:postcode":"28365",
    "addr:street":"Crows Foot Rd",
    "iso:country":"US",
    "sg:address":"1672 Crows Foot Rd",
    "sg:city":"Mount Olive",
    "sg:classifiers":[
        {
            "category":"Building & Trades",
            "subcategory":"Electrical",
            "type":"Services"
        }
    ],
    "sg:phone":"+1 919 689 2109",
    "sg:postcode":"28365",
    "sg:province":"NC",
    "sg:tags":[
        "electrical",
        "contractor"
    ],
    "wof:name":"Trading At Wr Joyner Electric",
    "wof:placetype":"venue"
},
  "geometry": {"coordinates":[-78.214665,35.242266],"type":"Point"}
}