{
  "type": "Feature",
  "properties": {
    "addr:full":"104 Church Ln Kernersville NC 27284",
    "addr:housenumber":"104",
    "addr:postcode":"27284",
    "addr:street":"Church Ln",
    "iso:country":"US",
    "sg:address":"104 Church Ln",
    "sg:city":"Kernersville",
    "sg:classifiers":[
        {
            "category":"Personal",
            "subcategory":"Beauty Salon",
            "type":"Services"
        }
    ],
    "sg:phone":"+1   ",
    "sg:postcode":"27284",
    "sg:province":"NC",
    "sg:tags":[
        "shop"
    ],
    "wof:name":"Styles By Mr Jones Hair Studio",
    "wof:placetype":"venue"
},
  "geometry": {"coordinates":[-80.071668,36.119641],"type":"Point"}
}