{
  "type": "Feature",
  "properties": {
    "addr:full":"519 Industrial Park Dr Smithfield NC 27577",
    "addr:housenumber":"519",
    "addr:postcode":"27577",
    "addr:street":"Industrial Park Dr",
    "iso:country":"US",
    "sg:address":"519 Industrial Park Dr",
    "sg:city":"Smithfield",
    "sg:classifiers":[
        {
            "category":"Restaurant",
            "type":"Food & Drink"
        }
    ],
    "sg:phone":"+1 919 989 9889",
    "sg:postcode":"27577",
    "sg:province":"NC",
    "wof:name":"El Sombrero",
    "wof:placetype":"venue"
},
  "geometry": {"coordinates":[-78.320713,35.505785],"type":"Point"}
}