{
  "type": "Feature",
  "properties": {
    "addr:full":"901 N Davidson St Charlotte NC 28206",
    "addr:housenumber":"901",
    "addr:postcode":"28206",
    "addr:street":"N Davidson St",
    "iso:country":"US",
    "sg:address":"901 N Davidson St",
    "sg:city":"Charlotte",
    "sg:classifiers":[
        {
            "category":"Government",
            "subcategory":"Office",
            "type":"Public Place"
        }
    ],
    "sg:phone":"+1 704 336 2420",
    "sg:postcode":"28206",
    "sg:province":"NC",
    "sg:tags":[
        "city",
        "program"
    ],
    "wof:name":"Charlotte Transportation Dept",
    "wof:placetype":"venue"
},
  "geometry": {"coordinates":[-80.828266,35.229837],"type":"Point"}
}