{
  "type": "Feature",
  "properties": {
    "iso:country":"US",
    "sg:address":"322 Laurel Dr",
    "sg:city":"Spring Lake",
    "sg:classifiers":[
        {
            "category":"Wholesale",
            "subcategory":"Jewelry",
            "type":"Manufacturing & Wholesale Goods"
        }
    ],
    "sg:phone":"+1 910 436 2330",
    "sg:postcode":"28390",
    "sg:province":"NC",
    "sg:tags":[
        "stone"
    ],
    "wof:name":"Nia Autumn",
    "wof:placetype":"venue"
},
  "geometry": {"coordinates":[-78.976,35.249073],"type":"Point"}
}