{
  "type": "Feature",
  "properties": {
    "iso:country":"US",
    "sg:address":"131 Eastridge Ct",
    "sg:city":"Advance",
    "sg:classifiers":[
        {
            "category":"Building & Trades",
            "subcategory":"Construction",
            "type":"Services"
        }
    ],
    "sg:phone":"+1 336 940 5927",
    "sg:postcode":"27006",
    "sg:province":"NC",
    "sg:tags":[
        "house",
        "contractor"
    ],
    "wof:name":"Decked Out",
    "wof:placetype":"venue"
},
  "geometry": {"coordinates":[-80.415678,35.978431],"type":"Point"}
}