{
  "type": "Feature",
  "properties": {
    "iso:country":"US",
    "sg:address":"304 Western Blvd",
    "sg:city":"Jacksonville",
    "sg:classifiers":[
        {
            "category":"Restaurant",
            "type":"Food & Drink"
        }
    ],
    "sg:menulink":"http://www.allmenus.com/nc/jacksonville/127881-red-lobster/menu/",
    "sg:phone":"+1 910 353 9454",
    "sg:postcode":"28546",
    "sg:province":"NC",
    "sg:tags":[
        "seafood",
        "american"
    ],
    "wof:name":"Red Lobster",
    "wof:placetype":"venue"
},
  "geometry": {"coordinates":[-77.381913,34.759929],"type":"Point"}
}