{
  "type": "Feature",
  "properties": {
    "iso:country":"US",
    "sg:address":"5574 Smiley Wyrick Rd",
    "sg:city":"Mc Leansville",
    "sg:classifiers":[
        {
            "category":"Building & Trades",
            "subcategory":"Landscaping Services",
            "type":"Services"
        }
    ],
    "sg:phone":"+1 336 656 3176",
    "sg:postcode":"27301",
    "sg:province":"NC",
    "wof:name":"Northeast Lawn Care",
    "wof:placetype":"venue"
},
  "geometry": {"coordinates":[-79.64009900000001,36.181245],"type":"Point"}
}