{
  "type": "Feature",
  "properties": {
    "iso:country":"US",
    "sg:address":"3319 Anvil Ct",
    "sg:city":"Raleigh",
    "sg:classifiers":[
        {
            "category":"Shopping",
            "type":"Retail Goods"
        }
    ],
    "sg:phone":"+1 919 779 6141",
    "sg:postcode":"27603",
    "sg:province":"NC",
    "sg:tags":[
        "enforcement",
        "law",
        "supply"
    ],
    "sg:website":"www.lawmens.com",
    "wof:name":"Lawmen's Safety Supply Inc",
    "wof:placetype":"venue"
},
  "geometry": {"coordinates":[-78.64315499999999,35.7299],"type":"Point"}
}