{
  "type": "Feature",
  "properties": {
    "addr:full":"3561 Willow Creek Rd Hendersonville NC 28739",
    "addr:housenumber":"3561",
    "addr:postcode":"28739",
    "addr:street":"Willow Creek Rd",
    "iso:country":"US",
    "sg:address":"3561 Willow Creek Rd",
    "sg:city":"Hendersonville",
    "sg:classifiers":[
        {
            "category":"Professional",
            "subcategory":"Research",
            "type":"Services"
        }
    ],
    "sg:phone":"+1   ",
    "sg:postcode":"28739",
    "sg:province":"NC",
    "sg:tags":[
        "fuel",
        "cell",
        "development"
    ],
    "wof:name":"Shining Rock Technologies LLC",
    "wof:placetype":"venue"
},
  "geometry": {"coordinates":[-82.549047,35.303342],"type":"Point"}
}