{
  "type": "Feature",
  "properties": {
    "iso:country":"US",
    "sg:address":"400 Brushy Creek Rd",
    "sg:city":"Spruce Pine",
    "sg:classifiers":[
        {
            "category":"Travel",
            "subcategory":"Travel Agent",
            "type":"Entertainment"
        }
    ],
    "sg:phone":"+1 828 766 7661",
    "sg:postcode":"28777",
    "sg:province":"NC",
    "sg:tags":[
        "passenger",
        "transportation",
        "se",
        "arrangement"
    ],
    "wof:name":"Avery County Airport",
    "wof:placetype":"venue"
},
  "geometry": {"coordinates":[-82.00121799999999,35.950237],"type":"Point"}
}