{
  "type": "Feature",
  "properties": {
    "addr:full":"4501 S Tryon St Charlotte NC 28217",
    "addr:housenumber":"4501",
    "addr:postcode":"28217",
    "addr:street":"S Tryon St",
    "iso:country":"US",
    "sg:address":"4501 S Tryon St",
    "sg:city":"Charlotte",
    "sg:classifiers":[
        {
            "category":"Building & Trades",
            "subcategory":"Plumbing",
            "type":"Services"
        }
    ],
    "sg:phone":"+1 704 525 9600",
    "sg:postcode":"28217",
    "sg:province":"NC",
    "sg:tags":[
        "conditioning",
        "air",
        "system",
        "contractor"
    ],
    "wof:name":"Trane Co",
    "wof:placetype":"venue"
},
  "geometry": {"coordinates":[-80.88717,35.183161],"type":"Point"}
}