{
  "type": "Feature",
  "properties": {
    "iso:country":"US",
    "sg:address":"1324 Gay St",
    "sg:city":"Rocky Mount",
    "sg:classifiers":[
        {
            "category":"Retail",
            "subcategory":"Animal Services",
            "type":"Services"
        }
    ],
    "sg:phone":"+1 252 977 7485",
    "sg:postcode":"27804",
    "sg:province":"NC",
    "sg:tags":[
        "training",
        "dog"
    ],
    "wof:name":"Dogstar Dog Training",
    "wof:placetype":"venue"
},
  "geometry": {"coordinates":[-77.81337000000001,35.950522],"type":"Point"}
}