{
  "type": "Feature",
  "properties": {
    "addr:full":"1614 Lansdown Ave Greensboro NC 27401",
    "addr:housenumber":"1614",
    "addr:postcode":"27401",
    "addr:street":"Lansdown Ave",
    "iso:country":"US",
    "sg:address":"1614 Lansdown Ave",
    "sg:city":"Greensboro",
    "sg:classifiers":[
        {
            "category":"Professional",
            "subcategory":"Accounting & Tax Preparation",
            "type":"Services"
        }
    ],
    "sg:phone":"+1   ",
    "sg:postcode":"27401",
    "sg:province":"NC",
    "sg:tags":[
        "return"
    ],
    "wof:name":"Marthas Tax Service",
    "wof:placetype":"venue"
},
  "geometry": {"coordinates":[-79.758303,36.053021],"type":"Point"}
}