{
  "type": "Feature",
  "properties": {
    "iso:country":"US",
    "sg:address":"136 Furman Rd",
    "sg:city":"Boone",
    "sg:classifiers":[
        {
            "category":"Health Services",
            "subcategory":"Chiropractor",
            "type":"Services"
        }
    ],
    "sg:phone":"+1 828 264 4521",
    "sg:postcode":"28607",
    "sg:province":"NC",
    "wof:name":"Hawthorne Chiropractic Center",
    "wof:placetype":"venue"
},
  "geometry": {"coordinates":[-81.655244,36.198303],"type":"Point"}
}