{
  "type": "Feature",
  "properties": {
    "addr:full":"393 Holmes St Shelby NC 28152",
    "addr:housenumber":"393",
    "addr:postcode":"28152",
    "addr:street":"Holmes St",
    "iso:country":"US",
    "sg:address":"393 Holmes St",
    "sg:city":"Shelby",
    "sg:classifiers":[
        {
            "category":"Autos & Motor Vehicles",
            "subcategory":"Automobile Sales",
            "type":"Retail Goods"
        }
    ],
    "sg:phone":"+1 704 487 4561",
    "sg:postcode":"28152",
    "sg:province":"NC",
    "sg:tags":[
        "car",
        "dealer"
    ],
    "wof:name":"Mc Cluney's Used Cars",
    "wof:placetype":"venue"
},
  "geometry": {"coordinates":[-81.480617,35.291428],"type":"Point"}
}