{
  "type": "Feature",
  "properties": {
    "addr:full":"722 N West St Raleigh NC 27603",
    "addr:housenumber":"722",
    "addr:postcode":"27603",
    "addr:street":"N West",
    "iso:country":"US",
    "sg:address":"722 N West St",
    "sg:city":"Raleigh",
    "sg:classifiers":[
        {
            "category":"Personal",
            "subcategory":"Beauty Salon",
            "type":"Services"
        }
    ],
    "sg:phone":"+1 919 832 0095",
    "sg:postcode":"27603",
    "sg:province":"NC",
    "sg:tags":[
        "hair",
        "braiding",
        "accessory",
        "stylist",
        "supply"
    ],
    "sg:website":"http://raleigh.citysearch.com/profile/external/44048999/raleigh_nc/glam_lounge.html?publisher=yellowpages&reference_id=1&placement=ypwebsitemip",
    "wof:name":"Glam Lounge",
    "wof:placetype":"venue"
},
  "geometry": {"coordinates":[-78.64526600000001,35.788672],"type":"Point"}
}