{
  "type": "Feature",
  "properties": {
    "iso:country":"US",
    "sg:address":"715 Spruce St",
    "sg:city":"Mooresville",
    "sg:classifiers":[
        {
            "category":"Professional",
            "type":"Services"
        }
    ],
    "sg:phone":"+1 704 663 7433",
    "sg:postcode":"28115",
    "sg:province":"NC",
    "wof:name":"Willilam L Hunter",
    "wof:placetype":"venue"
},
  "geometry": {"coordinates":[-80.82353999999999,35.572197],"type":"Point"}
}