{
  "type": "Feature",
  "properties": {
    "iso:country":"US",
    "sg:address":"14348 McLester Rd",
    "sg:city":"Oakboro",
    "sg:phone":"+1 704 485 4476",
    "sg:postcode":"28129",
    "sg:province":"NC",
    "sg:tags":[
        "farm",
        "corn",
        "wheat",
        "soybean"
    ],
    "wof:name":"Lee Farms",
    "wof:placetype":"venue"
},
  "geometry": {"coordinates":[-80.31908199999999,35.259549],"type":"Point"}
}