{
  "type": "Feature",
  "properties": {
    "iso:country":"US",
    "sg:address":"908 E Elm St",
    "sg:city":"Goldsboro",
    "sg:classifiers":[
        {
            "category":"Personal",
            "subcategory":"Beauty Salon",
            "type":"Services"
        }
    ],
    "sg:phone":"+1   ",
    "sg:postcode":"27530",
    "sg:province":"NC",
    "sg:tags":[
        "shop",
        "barber"
    ],
    "wof:name":"Christ Made A Way Barber Shop",
    "wof:placetype":"venue"
},
  "geometry": {"coordinates":[-77.98491,35.373594],"type":"Point"}
}