{
  "type": "Feature",
  "properties": {
    "iso:country":"US",
    "sg:address":"701 Silverleaf Rd",
    "sg:city":"Charlotte",
    "sg:classifiers":[
        {
            "category":"Education",
            "subcategory":"School",
            "type":"Public Place"
        }
    ],
    "sg:phone":"+1 704 522 9538",
    "sg:postcode":"28217",
    "sg:province":"NC",
    "wof:name":"Victory Christian Ctr Guest Ho",
    "wof:placetype":"venue"
},
  "geometry": {"coordinates":[-80.883093,35.145444],"type":"Point"}
}