{
  "type": "Feature",
  "properties": {
    "iso:country":"US",
    "sg:address":"650 Oak Grove Rd",
    "sg:city":"Trenton",
    "sg:classifiers":[
        {
            "category":"Manufacturing",
            "subcategory":"Printing",
            "type":"Manufacturing & Wholesale Goods"
        }
    ],
    "sg:phone":"+1 252 224 1231",
    "sg:postcode":"28585",
    "sg:province":"NC",
    "sg:tags":[
        "commercial"
    ],
    "wof:name":"William G Macintosh",
    "wof:placetype":"venue"
},
  "geometry": {"coordinates":[-77.282826,35.032492],"type":"Point"}
}