{
  "type": "Feature",
  "properties": {
    "addr:full":"1648 US Hwy 1 Cameron NC 28326",
    "addr:housenumber":"1648",
    "addr:postcode":"28326",
    "addr:street":"Us Hwy 1",
    "iso:country":"US",
    "sg:address":"1648 US Hwy 1",
    "sg:city":"Cameron",
    "sg:classifiers":[
        {
            "category":"Autos & Motor Vehicles",
            "subcategory":"Automobile Sales",
            "type":"Retail Goods"
        }
    ],
    "sg:phone":"+1 910 245 4432",
    "sg:postcode":"28326",
    "sg:province":"NC",
    "sg:tags":[
        "used"
    ],
    "wof:name":"Cardinal Motors",
    "wof:placetype":"venue"
},
  "geometry": {"coordinates":[-79.269231,35.303666],"type":"Point"}
}