{
  "type": "Feature",
  "properties": {
    "addr:full":"1307 S Collegiate Dr Wilkesboro NC 28697",
    "addr:housenumber":"1307",
    "addr:postcode":"28697",
    "addr:street":"Collegiate Dr",
    "iso:country":"US",
    "sg:address":"1307 S Collegiate Dr",
    "sg:city":"Wilkesboro",
    "sg:classifiers":[
        {
            "category":"Banks & Credit Unions",
            "subcategory":"Bank",
            "type":"Services"
        }
    ],
    "sg:phone":"+1 336 667 5770",
    "sg:postcode":"28697",
    "sg:province":"NC",
    "sg:tags":[
        "mortgage",
        "loan",
        "banker",
        "real estate"
    ],
    "wof:name":"First Greensboro Home Equity",
    "wof:placetype":"venue"
},
  "geometry": {"coordinates":[-81.17821499999999,36.139423],"type":"Point"}
}