{
  "type": "Feature",
  "properties": {
    "addr:full":"918 Martin Luther King Jr Dr Maxton NC 28364",
    "addr:housenumber":"918",
    "addr:postcode":"28364",
    "addr:street":"Martin Luther King Jr Dr",
    "iso:country":"US",
    "sg:address":"918 Martin Luther King Jr Dr",
    "sg:city":"Maxton",
    "sg:classifiers":[
        {
            "category":"Retail",
            "subcategory":"Auto Repair",
            "type":"Services"
        }
    ],
    "sg:phone":"+1 910 844 9106",
    "sg:postcode":"28364",
    "sg:province":"NC",
    "sg:tags":[
        "muffler",
        "exhaust",
        "system"
    ],
    "wof:name":"Clark's Auto Parts",
    "wof:placetype":"venue"
},
  "geometry": {"coordinates":[-79.336795,34.731268],"type":"Point"}
}