{
  "type": "Feature",
  "properties": {
    "iso:country":"US",
    "sg:address":"2278 Golden Gate Dr",
    "sg:city":"Greensboro",
    "sg:classifiers":[
        {
            "category":"Restaurant",
            "type":"Food & Drink"
        }
    ],
    "sg:phone":"+1 336 275 4141",
    "sg:postcode":"27405",
    "sg:province":"NC",
    "sg:tags":[
        "eating"
    ],
    "wof:name":"Golden Pizza and Sub",
    "wof:placetype":"venue"
},
  "geometry": {"coordinates":[-79.784329,36.102644],"type":"Point"}
}