{
  "type": "Feature",
  "properties": {
    "iso:country":"US",
    "sg:address":"704 Northampton Dr",
    "sg:city":"Cary",
    "sg:classifiers":[
        {
            "category":"Retail",
            "subcategory":"Animal Services",
            "type":"Services"
        }
    ],
    "sg:phone":"+1 919 460 6355",
    "sg:postcode":"27513",
    "sg:province":"NC",
    "sg:tags":[
        "pet"
    ],
    "wof:name":"Precious Paws",
    "wof:placetype":"venue"
},
  "geometry": {"coordinates":[-78.781857,35.794602],"type":"Point"}
}