{
  "type": "Feature",
  "properties": {
    "addr:full":"801 New Bern Ave Raleigh NC 27601",
    "addr:housenumber":"801",
    "addr:postcode":"27601",
    "addr:street":"New Bern Ave",
    "iso:country":"US",
    "sg:address":"801 New Bern Ave",
    "sg:city":"Raleigh",
    "sg:classifiers":[
        {
            "category":"Building & Trades",
            "subcategory":"Plumbing",
            "type":"Services"
        }
    ],
    "sg:phone":"+1 919 839 5990",
    "sg:postcode":"27601",
    "sg:province":"NC",
    "sg:tags":[
        "contractor"
    ],
    "wof:name":"Burns Plumbing",
    "wof:placetype":"venue"
},
  "geometry": {"coordinates":[-78.625756,35.78],"type":"Point"}
}