{
  "type": "Feature",
  "properties": {
    "addr:full":"2038 State Hwy 49 Burlington NC 27217",
    "addr:housenumber":"2038",
    "addr:postcode":"27217",
    "addr:street":"State Hwy 49",
    "iso:country":"US",
    "sg:address":"2038 State Hwy 49",
    "sg:city":"Burlington",
    "sg:classifiers":[
        {
            "category":"Building & Trades",
            "subcategory":"Construction",
            "type":"Services"
        }
    ],
    "sg:phone":"+1 336 578 9009",
    "sg:postcode":"27217",
    "sg:province":"NC",
    "sg:tags":[
        "repairing",
        "remodeling",
        "contractor"
    ],
    "wof:name":"T Clark Remodeling",
    "wof:placetype":"venue"
},
  "geometry": {"coordinates":[-79.345,36.13482],"type":"Point"}
}