{
  "type": "Feature",
  "properties": {
    "addr:full":"6509 Derby Ln NW Concord NC 28027",
    "addr:housenumber":"6509",
    "addr:postcode":"28027",
    "addr:street":"Derby Ln Nw",
    "iso:country":"US",
    "sg:address":"6509 Derby Ln NW",
    "sg:city":"Concord",
    "sg:classifiers":[
        {
            "category":"Professional",
            "type":"Services"
        },
        {
            "category":"Professional",
            "subcategory":"Business Services",
            "type":"Services"
        }
    ],
    "sg:phone":"+1 704 788 1990",
    "sg:postcode":"28027",
    "sg:province":"NC",
    "wof:name":"Davash Strategic Solutions",
    "wof:placetype":"venue"
},
  "geometry": {"coordinates":[-80.68788499999999,35.403025],"type":"Point"}
}