{
  "type": "Feature",
  "properties": {
    "addr:full":"1744 Lane Rd Mount Holly NC 28120",
    "addr:housenumber":"1744",
    "addr:postcode":"28120",
    "addr:street":"Lane Rd",
    "iso:country":"US",
    "sg:address":"1744 Lane Rd",
    "sg:city":"Mount Holly",
    "sg:classifiers":[
        {
            "category":"Education",
            "subcategory":"School",
            "type":"Public Place"
        }
    ],
    "sg:phone":"+1 704 827 7251",
    "sg:postcode":"28120",
    "sg:province":"NC",
    "sg:tags":[
        "high"
    ],
    "wof:name":"East Gaston High School",
    "wof:placetype":"venue"
},
  "geometry": {"coordinates":[-81.07545399999999,35.314357],"type":"Point"}
}