{
  "type": "Feature",
  "properties": {
    "addr:full":"3380 Shamrock Hts Hudson NC 28638",
    "addr:housenumber":"3380",
    "addr:postcode":"28638",
    "addr:street":"Shamrock Hts",
    "iso:country":"US",
    "sg:address":"3380 Shamrock Hts",
    "sg:city":"Hudson",
    "sg:classifiers":[
        {
            "category":"Building & Trades",
            "subcategory":"Construction",
            "type":"Services"
        }
    ],
    "sg:phone":"+1 828 396 9722",
    "sg:postcode":"28638",
    "sg:province":"NC",
    "wof:name":"Perry S Construction",
    "wof:placetype":"venue"
},
  "geometry": {"coordinates":[-81.442027,35.816614],"type":"Point"}
}