{
  "type": "Feature",
  "properties": {
    "iso:country":"US",
    "sg:address":"130 Zeb Cline Rd",
    "sg:city":"Shelby",
    "sg:classifiers":[
        {
            "category":"Professional",
            "subcategory":"Business Services",
            "type":"Services"
        }
    ],
    "sg:phone":"+1   ",
    "sg:postcode":"28150",
    "sg:province":"NC",
    "wof:name":"C & J Sales",
    "wof:placetype":"venue"
},
  "geometry": {"coordinates":[-81.43950700000001,35.303964],"type":"Point"}
}