{
  "type": "Feature",
  "properties": {
    "addr:full":"9 Brookcliff Dr Asheville NC 28804",
    "addr:housenumber":"9",
    "addr:postcode":"28804",
    "addr:street":"Brookcliff Dr",
    "iso:country":"US",
    "sg:address":"9 Brookcliff Dr",
    "sg:city":"Asheville",
    "sg:classifiers":[
        {
            "category":"Professional",
            "subcategory":"Computer Services",
            "type":"Services"
        }
    ],
    "sg:phone":"+1   ",
    "sg:postcode":"28804",
    "sg:province":"NC",
    "wof:name":"PC Gear",
    "wof:placetype":"venue"
},
  "geometry": {"coordinates":[-82.52994,35.643656],"type":"Point"}
}