{
  "type": "Feature",
  "properties": {
    "addr:full":"107 W Main St Rockwell NC 28138",
    "addr:housenumber":"107",
    "addr:postcode":"28138",
    "addr:street":"W Main St",
    "iso:country":"US",
    "sg:address":"107 W Main St",
    "sg:city":"Rockwell",
    "sg:classifiers":[
        {
            "category":"Personal",
            "type":"Services"
        }
    ],
    "sg:phone":"+1   ",
    "sg:postcode":"28138",
    "sg:province":"NC",
    "wof:name":"Sunseekers Tanning",
    "wof:placetype":"venue"
},
  "geometry": {"coordinates":[-80.407946,35.552054],"type":"Point"}
}