{
  "type": "Feature",
  "properties": {
    "iso:country":"US",
    "sg:address":"19611 Meta Rd",
    "sg:city":"Cornelius",
    "sg:classifiers":[
        {
            "category":"Travel",
            "subcategory":"Travel Agent",
            "type":"Entertainment"
        }
    ],
    "sg:phone":"+1 704 895 1685",
    "sg:postcode":"28031",
    "sg:province":"NC",
    "sg:tags":[
        "information",
        "tourist"
    ],
    "sg:website":"www.lakenorman.com",
    "wof:name":"LAKENORMAN.COM",
    "wof:placetype":"venue"
},
  "geometry": {"coordinates":[-80.91403800000001,35.47895],"type":"Point"}
}