{
  "type": "Feature",
  "properties": {
    "addr:full":"150 Liledoun Rd Taylorsville NC 28681",
    "addr:housenumber":"150",
    "addr:postcode":"28681",
    "addr:street":"Liledoun Rd",
    "iso:country":"US",
    "sg:address":"150 Liledoun Rd",
    "sg:city":"Taylorsville",
    "sg:classifiers":[
        {
            "category":"Food & Beverages",
            "subcategory":"Groceries & Convenience Stores",
            "type":"Retail Goods"
        }
    ],
    "sg:phone":"+1 828 632 9811",
    "sg:postcode":"28681",
    "sg:province":"NC",
    "sg:tags":[
        "grocer"
    ],
    "wof:name":"Market Basket",
    "wof:placetype":"venue"
},
  "geometry": {"coordinates":[-81.18534099999999,35.920091],"type":"Point"}
}