{
  "type": "Feature",
  "properties": {
    "addr:full":"2408 Hillsborough Rd Durham NC 27705",
    "addr:housenumber":"2408",
    "addr:postcode":"27705",
    "addr:street":"Hillsborough Rd",
    "iso:country":"US",
    "sg:address":"2408 Hillsborough Rd",
    "sg:city":"Durham",
    "sg:classifiers":[
        {
            "category":"Personal",
            "subcategory":"Beauty Salon",
            "type":"Services"
        }
    ],
    "sg:phone":"+1   ",
    "sg:postcode":"27705",
    "sg:province":"NC",
    "sg:tags":[
        "shop"
    ],
    "wof:name":"A New Reflection",
    "wof:placetype":"venue"
},
  "geometry": {"coordinates":[-78.927302,36.010584],"type":"Point"}
}