{
  "type": "Feature",
  "properties": {
    "iso:country":"US",
    "sg:address":"192 N Main St",
    "sg:city":"Mount Airy",
    "sg:classifiers":[
        {
            "category":"Professional",
            "subcategory":"Employment Agencies",
            "type":"Services"
        }
    ],
    "sg:phone":"+1   ",
    "sg:postcode":"27030",
    "sg:province":"NC",
    "wof:name":"Execquest",
    "wof:placetype":"venue"
},
  "geometry": {"coordinates":[-80.607811,36.500839],"type":"Point"}
}