{
  "type": "Feature",
  "properties": {
    "addr:full":"307 E Nash St Louisburg NC 27549",
    "addr:housenumber":"307",
    "addr:postcode":"27549",
    "addr:street":"E Nash St",
    "iso:country":"US",
    "sg:address":"307 E Nash St",
    "sg:city":"Louisburg",
    "sg:classifiers":[
        {
            "category":"Social Services",
            "type":"Services"
        }
    ],
    "sg:phone":"+1 919 496 0200",
    "sg:postcode":"27549",
    "sg:province":"NC",
    "sg:tags":[
        "probation"
    ],
    "wof:name":"Adult Probation District Ofc",
    "wof:placetype":"venue"
},
  "geometry": {"coordinates":[-78.299514,36.098355],"type":"Point"}
}