{
  "type": "Feature",
  "properties": {
    "iso:country":"US",
    "sg:address":"307 W McCubbins St",
    "sg:city":"Salisbury",
    "sg:classifiers":[
        {
            "category":"Social Services",
            "subcategory":"Child Care",
            "type":"Services"
        }
    ],
    "sg:phone":"+1 704 642 1125",
    "sg:postcode":"28144",
    "sg:province":"NC",
    "wof:name":"TRINITY Homes Inc",
    "wof:placetype":"venue"
},
  "geometry": {"coordinates":[-80.480977,35.663988],"type":"Point"}
}