{
  "type": "Feature",
  "properties": {
    "addr:full":"1 Castle St Wilmington NC 28401",
    "addr:housenumber":"1",
    "addr:postcode":"28401",
    "addr:street":"Castle St",
    "iso:country":"US",
    "sg:address":"1 Castle St",
    "sg:city":"Wilmington",
    "sg:classifiers":[
        {
            "category":"Personal",
            "subcategory":"Barber",
            "type":"Services"
        }
    ],
    "sg:phone":"+1 910 763 7303",
    "sg:postcode":"28401",
    "sg:province":"NC",
    "wof:name":"Glamour Beauty Shop",
    "wof:placetype":"venue"
},
  "geometry": {"coordinates":[-77.94783,34.227779],"type":"Point"}
}