{
  "type": "Feature",
  "properties": {
    "iso:country":"US",
    "sg:address":"701 Julian R Allsbrook Hwy",
    "sg:city":"Weldon",
    "sg:classifiers":[
        {
            "category":"Autos & Motor Vehicles",
            "subcategory":"Automobile Sales",
            "type":"Retail Goods"
        }
    ],
    "sg:phone":"+1 252 536 0411",
    "sg:postcode":"27890",
    "sg:province":"NC",
    "sg:tags":[
        "car",
        "dealer"
    ],
    "wof:name":"Lo's Auto Sales",
    "wof:placetype":"venue"
},
  "geometry": {"coordinates":[-77.61189,36.431421],"type":"Point"}
}