{
  "type": "Feature",
  "properties": {
    "addr:full":"105 Main St Cleveland NC 27013",
    "addr:housenumber":"105",
    "addr:postcode":"27013",
    "addr:street":"Main St",
    "iso:country":"US",
    "sg:address":"105 Main St",
    "sg:city":"Cleveland",
    "sg:classifiers":[
        {
            "category":"Government",
            "subcategory":"Post Office",
            "type":"Public Place"
        }
    ],
    "sg:phone":"+1 704 278 9192",
    "sg:postcode":"27013",
    "sg:province":"NC",
    "wof:name":"US Post Office",
    "wof:placetype":"venue"
},
  "geometry": {"coordinates":[-80.676483,35.733509],"type":"Point"}
}