{
  "type": "Feature",
  "properties": {
    "iso:country":"US",
    "sg:address":"545 Bat Cave Rd",
    "sg:city":"Old Fort",
    "sg:classifiers":[
        {
            "category":"Autos & Motor Vehicles",
            "subcategory":"Auto Supplies",
            "type":"Retail Goods"
        }
    ],
    "sg:phone":"+1 828 668 4999",
    "sg:postcode":"28762",
    "sg:province":"NC",
    "sg:tags":[
        "automobile",
        "parts"
    ],
    "wof:name":"Yount's Auto Supply Inc",
    "wof:placetype":"venue"
},
  "geometry": {"coordinates":[-82.179616,35.621172],"type":"Point"}
}