{
  "type": "Feature",
  "properties": {
    "iso:country":"US",
    "sg:address":"391 Palmer Rd",
    "sg:city":"Mount Airy",
    "sg:classifiers":[
        {
            "category":"Professional",
            "type":"Services"
        }
    ],
    "sg:phone":"+1   ",
    "sg:postcode":"27030",
    "sg:province":"NC",
    "sg:tags":[
        "livestock"
    ],
    "wof:name":"Lewis Stevens Livestock",
    "wof:placetype":"venue"
},
  "geometry": {"coordinates":[-80.76952300000001,36.485376],"type":"Point"}
}