{
  "type": "Feature",
  "properties": {
    "iso:country":"US",
    "sg:address":"1728 E 10th St",
    "sg:city":"Roanoke Rapids",
    "sg:classifiers":[
        {
            "category":"Building & Trades",
            "subcategory":"Equipment Rental",
            "type":"Services"
        }
    ],
    "sg:phone":"+1 252 535 4600",
    "sg:postcode":"27870",
    "sg:province":"NC",
    "wof:name":"Rent-Way",
    "wof:placetype":"venue"
},
  "geometry": {"coordinates":[-77.64375800000001,36.438404],"type":"Point"}
}