{
  "type": "Feature",
  "properties": {
    "addr:full":"3429 Toringdon Way Charlotte NC 28277",
    "addr:housenumber":"3429",
    "addr:postcode":"28277",
    "addr:street":"Toringdon Way",
    "iso:country":"US",
    "sg:address":"3429 Toringdon Way",
    "sg:city":"Charlotte",
    "sg:classifiers":[
        {
            "category":"Restaurant",
            "type":"Food & Drink"
        }
    ],
    "sg:menulink":"http://www.allmenus.com/nc/charlotte/49719-house-of-shoto/menu/",
    "sg:phone":"+1 704 541 1788",
    "sg:postcode":"28277",
    "sg:province":"NC",
    "sg:tags":[
        "sushi",
        "japanese",
        "asian"
    ],
    "wof:name":"House Of Shoto",
    "wof:placetype":"venue"
},
  "geometry": {"coordinates":[-80.842759,35.068583],"type":"Point"}
}