{
  "type": "Feature",
  "properties": {
    "addr:full":"1384 Shelton Ave Statesville NC 28677",
    "addr:housenumber":"1384",
    "addr:postcode":"28677",
    "addr:street":"Shelton Ave",
    "iso:country":"US",
    "sg:address":"1384 Shelton Ave",
    "sg:city":"Statesville",
    "sg:classifiers":[
        {
            "category":"Shopping",
            "subcategory":"Discount & Variety Stores",
            "type":"Retail Goods"
        },
        {
            "category":"Shopping",
            "subcategory":"Department Store",
            "type":"Retail Goods"
        }
    ],
    "sg:phone":"+1 704 872 8760",
    "sg:postcode":"28677",
    "sg:province":"NC",
    "wof:name":"Family Dollar Stores",
    "wof:placetype":"venue"
},
  "geometry": {"coordinates":[-80.88490400000001,35.766435],"type":"Point"}
}