{
  "type": "Feature",
  "properties": {
    "iso:country":"US",
    "sg:address":"114 S Academy St",
    "sg:city":"Cary",
    "sg:classifiers":[
        {
            "category":"Shopping",
            "subcategory":"Florist",
            "type":"Retail Goods"
        }
    ],
    "sg:phone":"+1 919 467 4161",
    "sg:postcode":"27511",
    "sg:province":"NC",
    "wof:name":"Flower Cupboard the",
    "wof:placetype":"venue"
},
  "geometry": {"coordinates":[-78.781508,35.78685],"type":"Point"}
}