{
  "type": "Feature",
  "properties": {
    "iso:country":"US",
    "sg:address":"9151 Deer Hill Rd",
    "sg:city":"Belews Creek",
    "sg:classifiers":[
        {
            "category":"Freight",
            "type":"Transportation"
        }
    ],
    "sg:phone":"+1 336 595 5308",
    "sg:postcode":"27009",
    "sg:province":"NC",
    "sg:tags":[
        "operator",
        "trucking"
    ],
    "wof:name":"Guyers Mobile Home Transport",
    "wof:placetype":"venue"
},
  "geometry": {"coordinates":[-80.069321,36.230224],"type":"Point"}
}