{
  "type": "Feature",
  "properties": {
    "iso:country":"US",
    "sg:address":"135 E Wilson Ave",
    "sg:city":"Mooresville",
    "sg:classifiers":[
        {
            "category":"Professional",
            "type":"Services"
        }
    ],
    "sg:phone":"+1 704 664 1437",
    "sg:postcode":"28115",
    "sg:province":"NC",
    "wof:name":"Toolworks Inc",
    "wof:placetype":"venue"
},
  "geometry": {"coordinates":[-80.81783900000001,35.577877],"type":"Point"}
}