{
  "type": "Feature",
  "properties": {
    "iso:country":"US",
    "sg:address":"80 Duck Woods Dr",
    "sg:city":"Kitty Hawk",
    "sg:classifiers":[
        {
            "category":"Professional",
            "subcategory":"Business Services",
            "type":"Services"
        }
    ],
    "sg:phone":"+1   ",
    "sg:postcode":"27949",
    "sg:province":"NC",
    "sg:tags":[
        "a",
        "as",
        "operates"
    ],
    "wof:name":"Seaside Stabilization",
    "wof:placetype":"venue"
},
  "geometry": {"coordinates":[-75.729713,36.104643],"type":"Point"}
}