{
  "type": "Feature",
  "properties": {
    "addr:full":"3516 Williamsborough Cir Raleigh NC 27609",
    "addr:housenumber":"3516",
    "addr:postcode":"27609",
    "addr:street":"Williamsborough Cir",
    "iso:country":"US",
    "sg:address":"3516 Williamsborough Cir",
    "sg:city":"Raleigh",
    "sg:classifiers":[
        {
            "category":"Manufacturing",
            "subcategory":"Tools & Machinery",
            "type":"Manufacturing & Wholesale Goods"
        }
    ],
    "sg:phone":"+1 919 782 8114",
    "sg:postcode":"27609",
    "sg:province":"NC",
    "sg:tags":[
        "mold"
    ],
    "wof:name":"Turner Co",
    "wof:placetype":"venue"
},
  "geometry": {"coordinates":[-78.651937,35.83149],"type":"Point"}
}