{
  "type": "Feature",
  "properties": {
    "addr:full":"4399 Peele Rd Clayton NC 27520",
    "addr:housenumber":"4399",
    "addr:postcode":"27520",
    "addr:street":"Peele Rd",
    "iso:country":"US",
    "sg:address":"4399 Peele Rd",
    "sg:city":"Clayton",
    "sg:classifiers":[
        {
            "category":"Building & Trades",
            "subcategory":"Construction",
            "type":"Services"
        }
    ],
    "sg:phone":"+1 919 553 7958",
    "sg:postcode":"27520",
    "sg:province":"NC",
    "sg:tags":[
        "contractor"
    ],
    "wof:name":"Charles Barbour Masonry",
    "wof:placetype":"venue"
},
  "geometry": {"coordinates":[-78.443968,35.595502],"type":"Point"}
}