{
  "type": "Feature",
  "properties": {
    "addr:full":"604 Forest Hill Dr Shelby NC 28150",
    "addr:housenumber":"604",
    "addr:postcode":"28150",
    "addr:street":"Forest Hill Dr",
    "iso:country":"US",
    "sg:address":"604 Forest Hill Dr",
    "sg:city":"Shelby",
    "sg:classifiers":[
        {
            "category":"Professional",
            "subcategory":"Management & Consulting",
            "type":"Services"
        }
    ],
    "sg:phone":"+1   ",
    "sg:postcode":"28150",
    "sg:province":"NC",
    "wof:name":"Rhea Consulting Inc",
    "wof:placetype":"venue"
},
  "geometry": {"coordinates":[-81.521636,35.290097],"type":"Point"}
}