{
  "type": "Feature",
  "properties": {
    "iso:country":"US",
    "sg:address":"105 Promenade Ln",
    "sg:city":"Kitty Hawk",
    "sg:classifiers":[
        {
            "category":"Building & Trades",
            "subcategory":"Construction",
            "type":"Services"
        }
    ],
    "sg:phone":"+1 252 261 3844",
    "sg:postcode":"27949",
    "sg:province":"NC",
    "sg:tags":[
        "contractor"
    ],
    "wof:name":"Newman Homes Construction Inc",
    "wof:placetype":"venue"
},
  "geometry": {"coordinates":[-75.739887,36.092278],"type":"Point"}
}