{
  "type": "Feature",
  "properties": {
    "addr:full":"2475 N Church St Burlington NC 27217",
    "addr:housenumber":"2475",
    "addr:postcode":"27217",
    "addr:street":"N Church St",
    "iso:country":"US",
    "sg:address":"2475 N Church St",
    "sg:city":"Burlington",
    "sg:classifiers":[
        {
            "category":"Autos & Motor Vehicles",
            "subcategory":"Automobile Sales",
            "type":"Retail Goods"
        }
    ],
    "sg:phone":"+1 336 226 6361",
    "sg:postcode":"27217",
    "sg:province":"NC",
    "sg:tags":[
        "used"
    ],
    "wof:name":"Cox Toyota Supercenter",
    "wof:placetype":"venue"
},
  "geometry": {"coordinates":[-79.389304,36.09167],"type":"Point"}
}