{
  "type": "Feature",
  "properties": {
    "iso:country":"US",
    "sg:address":"639 Creek Ridge Rd",
    "sg:city":"Greensboro",
    "sg:classifiers":[
        {
            "category":"Building & Trades",
            "subcategory":"Cleaning & Sanitation",
            "type":"Services"
        }
    ],
    "sg:phone":"+1 336 215 0566",
    "sg:postcode":"27406",
    "sg:province":"NC",
    "sg:tags":[
        "janitor",
        "maintenance"
    ],
    "wof:name":"Ambitious Cleaning Services",
    "wof:placetype":"venue"
},
  "geometry": {"coordinates":[-79.80787599999999,36.029224],"type":"Point"}
}