{
  "type": "Feature",
  "properties": {
    "iso:country":"US",
    "sg:address":"1049 Glenn King Rd",
    "sg:city":"Lansing",
    "sg:classifiers":[
        {
            "category":"Building & Trades",
            "subcategory":"Construction",
            "type":"Services"
        }
    ],
    "sg:phone":"+1 336 384 9809",
    "sg:postcode":"28643",
    "sg:province":"NC",
    "wof:name":"Raco Incorporated",
    "wof:placetype":"venue"
},
  "geometry": {"coordinates":[-81.497512,36.519116],"type":"Point"}
}