{
  "type": "Feature",
  "properties": {
    "iso:country":"US",
    "sg:address":"1839 S Wendover Rd",
    "sg:city":"Charlotte",
    "sg:classifiers":[
        {
            "category":"Professional",
            "subcategory":"Business Services",
            "type":"Services"
        }
    ],
    "sg:phone":"+1 704 364 7914",
    "sg:postcode":"28211",
    "sg:province":"NC",
    "sg:tags":[
        "interior",
        "consultant",
        "design",
        "decorator"
    ],
    "wof:name":"Holly Sturm Interiors",
    "wof:placetype":"venue"
},
  "geometry": {"coordinates":[-80.81839100000001,35.176621],"type":"Point"}
}