{
  "type": "Feature",
  "properties": {
    "addr:full":"1213 Oaklawn St SE Lenoir NC 28645",
    "addr:housenumber":"1213",
    "addr:postcode":"28645",
    "addr:street":"Oaklawn St Se",
    "iso:country":"US",
    "sg:address":"1213 Oaklawn St SE",
    "sg:city":"Lenoir",
    "sg:classifiers":[
        {
            "category":"Building & Trades",
            "subcategory":"Construction",
            "type":"Services"
        }
    ],
    "sg:phone":"+1 828 726 8145",
    "sg:postcode":"28645",
    "sg:province":"NC",
    "sg:tags":[
        "house"
    ],
    "wof:name":"Hamby Builders LLC",
    "wof:placetype":"venue"
},
  "geometry": {"coordinates":[-81.514106,35.893962],"type":"Point"}
}