{
  "type": "Feature",
  "properties": {
    "addr:full":"8305 University Executive Park Dr Charlotte NC 28262",
    "addr:housenumber":"8305",
    "addr:postcode":"28262",
    "addr:street":"University Executive Park Dr",
    "iso:country":"US",
    "sg:address":"8305 University Executive Park Dr",
    "sg:city":"Charlotte",
    "sg:classifiers":[
        {
            "category":"Shopping",
            "subcategory":"Hobbies, Toys, & Games",
            "type":"Retail Goods"
        }
    ],
    "sg:phone":"+1 704 595 9118",
    "sg:postcode":"28262",
    "sg:province":"NC",
    "sg:tags":[
        "equipment",
        "ceramic",
        "supply"
    ],
    "wof:name":"Thermal Ceramics",
    "wof:placetype":"venue"
},
  "geometry": {"coordinates":[-80.754864,35.301096],"type":"Point"}
}