{
  "type": "Feature",
  "properties": {
    "addr:full":"239 Cherry Run Rd Washington NC 27889",
    "addr:housenumber":"239",
    "addr:postcode":"27889",
    "addr:street":"Cherry Run Rd",
    "iso:country":"US",
    "sg:address":"239 Cherry Run Rd",
    "sg:city":"Washington",
    "sg:classifiers":[
        {
            "category":"Organizations",
            "subcategory":"Religious Organization",
            "type":"Services"
        }
    ],
    "sg:phone":"+1   ",
    "sg:postcode":"27889",
    "sg:province":"NC",
    "wof:name":"Beebe Chapel CME Church",
    "wof:placetype":"venue"
},
  "geometry": {"coordinates":[-77.076909,35.589905],"type":"Point"}
}