{
  "type": "Feature",
  "properties": {
    "iso:country":"US",
    "sg:address":"2520 Garner Rd",
    "sg:city":"Raleigh",
    "sg:classifiers":[
        {
            "category":"Organizations",
            "subcategory":"Religious Organization",
            "type":"Services"
        }
    ],
    "sg:phone":"+1   ",
    "sg:postcode":"27610",
    "sg:province":"NC",
    "wof:name":"G A Jones Rev",
    "wof:placetype":"venue"
},
  "geometry": {"coordinates":[-78.631441,35.745454],"type":"Point"}
}