{
  "type": "Feature",
  "properties": {
    "iso:country":"US",
    "sg:address":"32 N Lumina Ave",
    "sg:city":"Wrightsville Bch",
    "sg:classifiers":[
        {
            "category":"Food & Beverages",
            "subcategory":"Groceries & Convenience Stores",
            "type":"Retail Goods"
        }
    ],
    "sg:phone":"+1 910 256 2641",
    "sg:postcode":"28480",
    "sg:province":"NC",
    "sg:tags":[
        "grocer"
    ],
    "wof:name":"Roberts Market Inc",
    "wof:placetype":"venue"
},
  "geometry": {"coordinates":[-77.79479499999999,34.209362],"type":"Point"}
}