{
  "type": "Feature",
  "properties": {
    "iso:country":"US",
    "sg:address":"8601 Six Forks Rd",
    "sg:city":"Raleigh",
    "sg:classifiers":[
        {
            "category":"Professional",
            "subcategory":"Lawyer & Legal Services",
            "type":"Services"
        },
        {
            "category":"Health Services",
            "subcategory":"Doctor",
            "type":"Services"
        }
    ],
    "sg:phone":"+1 919 882 2191",
    "sg:postcode":"27615",
    "sg:province":"NC",
    "sg:tags":[
        "firm",
        "attorney",
        "law"
    ],
    "wof:name":"Wardell & Associates Pllc",
    "wof:placetype":"venue"
},
  "geometry": {"coordinates":[-78.65028599999999,35.897207],"type":"Point"}
}