{
  "type": "Feature",
  "properties": {
    "iso:country":"US",
    "sg:address":"12563 Cleveland Rd",
    "sg:city":"Garner",
    "sg:classifiers":[
        {
            "category":"Building & Trades",
            "subcategory":"Construction",
            "type":"Services"
        }
    ],
    "sg:phone":"+1 919 772 8335",
    "sg:postcode":"27529",
    "sg:province":"NC",
    "sg:tags":[
        "house"
    ],
    "wof:name":"Home Improvements Services",
    "wof:placetype":"venue"
},
  "geometry": {"coordinates":[-78.57194200000001,35.60375],"type":"Point"}
}