{
  "type": "Feature",
  "properties": {
    "iso:country":"US",
    "sg:address":"706 E 18th St",
    "sg:city":"Lumberton",
    "sg:classifiers":[
        {
            "category":"Personal",
            "subcategory":"Beauty Salon",
            "type":"Services"
        }
    ],
    "sg:phone":"+1 910 738 5020",
    "sg:postcode":"28358",
    "sg:province":"NC",
    "sg:tags":[
        "shop"
    ],
    "wof:name":"L & L Styling Salon",
    "wof:placetype":"venue"
},
  "geometry": {"coordinates":[-78.997891,34.629555],"type":"Point"}
}