{
  "type": "Feature",
  "properties": {
    "iso:country":"US",
    "sg:address":"6521 Creedmoor Rd",
    "sg:city":"Raleigh",
    "sg:classifiers":[
        {
            "category":"Health Services",
            "subcategory":"Chiropractor",
            "type":"Services"
        }
    ],
    "sg:phone":"+1   ",
    "sg:postcode":"27613",
    "sg:province":"NC",
    "wof:name":"Catherine Hoag DC",
    "wof:placetype":"venue"
},
  "geometry": {"coordinates":[-78.679294,35.875026],"type":"Point"}
}