{
  "type": "Feature",
  "properties": {
    "iso:country":"US",
    "sg:address":"110 Kyle Dr",
    "sg:city":"Jacksonville",
    "sg:classifiers":[
        {
            "category":"Retail",
            "subcategory":"Laundry & Dry Cleaning",
            "type":"Services"
        }
    ],
    "sg:phone":"+1   ",
    "sg:postcode":"28546",
    "sg:province":"NC",
    "wof:name":"Estelas Altrations Consignment",
    "wof:placetype":"venue"
},
  "geometry": {"coordinates":[-77.44421,34.813856],"type":"Point"}
}