{
  "type": "Feature",
  "properties": {
    "addr:full":"6480 Caratoke Hwy Grandy NC 27939",
    "addr:housenumber":"6480",
    "addr:postcode":"27939",
    "addr:street":"Caratoke Hwy",
    "iso:country":"US",
    "sg:address":"6480 Caratoke Hwy",
    "sg:city":"Grandy",
    "sg:classifiers":[
        {
            "category":"Social Services",
            "subcategory":"Child Care",
            "type":"Services"
        }
    ],
    "sg:phone":"+1 252 453 4585",
    "sg:postcode":"27939",
    "sg:province":"NC",
    "wof:name":"Kingdom Kids Learning Ctr",
    "wof:placetype":"venue"
},
  "geometry": {"coordinates":[-75.873853,36.232881],"type":"Point"}
}