{
  "type": "Feature",
  "properties": {
    "addr:full":"14565 US Hwy 17 Hampstead NC 28443",
    "addr:housenumber":"14565",
    "addr:postcode":"28443",
    "addr:street":"Us Hwy 17",
    "iso:country":"US",
    "sg:address":"14565 US Hwy 17",
    "sg:city":"Hampstead",
    "sg:classifiers":[
        {
            "category":"Food & Beverages",
            "subcategory":"Groceries & Convenience Stores",
            "type":"Retail Goods"
        }
    ],
    "sg:phone":"+1 910 270 9626",
    "sg:postcode":"28443",
    "sg:province":"NC",
    "wof:name":"Hampstead Country Store",
    "wof:placetype":"venue"
},
  "geometry": {"coordinates":[-77.713652,34.364616],"type":"Point"}
}