{
  "type": "Feature",
  "properties": {
    "addr:full":"132 Roxboro Rd Oxford NC 27565",
    "addr:housenumber":"132",
    "addr:postcode":"27565",
    "addr:street":"Roxboro Rd",
    "iso:country":"US",
    "sg:address":"132 Roxboro Rd",
    "sg:city":"Oxford",
    "sg:classifiers":[
        {
            "category":"Cinema",
            "subcategory":"Movie Rental",
            "type":"Entertainment"
        }
    ],
    "sg:phone":"+1 919 603 5533",
    "sg:postcode":"27565",
    "sg:province":"NC",
    "sg:tags":[
        "retail",
        "videocassette",
        "rent"
    ],
    "wof:name":"M G A Inc",
    "wof:placetype":"venue"
},
  "geometry": {"coordinates":[-78.596018,36.322733],"type":"Point"}
}