{
  "type": "Feature",
  "properties": {
    "iso:country":"US",
    "sg:address":"704 Dellwood Rd",
    "sg:city":"Waynesville",
    "sg:classifiers":[
        {
            "category":"Retail",
            "subcategory":"Auto Repair",
            "type":"Services"
        }
    ],
    "sg:phone":"+1 828 452 3636",
    "sg:postcode":"28786",
    "sg:province":"NC",
    "sg:tags":[
        "automotive"
    ],
    "wof:name":"Waynesville Xpress Lube",
    "wof:placetype":"venue"
},
  "geometry": {"coordinates":[-82.988544,35.501367],"type":"Point"}
}