{
  "type": "Feature",
  "properties": {
    "iso:country":"US",
    "sg:address":"420 Steeple Chase Trl",
    "sg:city":"Salisbury",
    "sg:classifiers":[
        {
            "category":"Professional",
            "subcategory":"Management & Consulting",
            "type":"Services"
        }
    ],
    "sg:phone":"+1 704 639 1105",
    "sg:postcode":"28144",
    "sg:province":"NC",
    "sg:tags":[
        "retail",
        "direct",
        "sales"
    ],
    "wof:name":"Simplicity Heart Inc",
    "wof:placetype":"venue"
},
  "geometry": {"coordinates":[-80.419572,35.713559],"type":"Point"}
}