{
  "type": "Feature",
  "properties": {
    "addr:full":"7004 Cape Harbor Dr Wilmington NC 28411",
    "addr:housenumber":"7004",
    "addr:postcode":"28411",
    "addr:street":"Cape Harbor Dr",
    "iso:country":"US",
    "sg:address":"7004 Cape Harbor Dr",
    "sg:city":"Wilmington",
    "sg:classifiers":[
        {
            "category":"Building & Trades",
            "subcategory":"Plumbing",
            "type":"Services"
        }
    ],
    "sg:phone":"+1 910 798 1750",
    "sg:postcode":"28411",
    "sg:province":"NC",
    "sg:tags":[
        "contractor"
    ],
    "wof:name":"Premier Plumbing",
    "wof:placetype":"venue"
},
  "geometry": {"coordinates":[-77.830083,34.266485],"type":"Point"}
}