{
  "type": "Feature",
  "properties": {
    "addr:full":"657 Britton Ct Sanford NC 27330",
    "addr:housenumber":"657",
    "addr:postcode":"27330",
    "addr:street":"Britton Ct",
    "iso:country":"US",
    "sg:address":"657 Britton Ct",
    "sg:city":"Sanford",
    "sg:classifiers":[
        {
            "category":"Building & Trades",
            "subcategory":"Construction",
            "type":"Services"
        }
    ],
    "sg:phone":"+1 919 777 0779",
    "sg:postcode":"27330",
    "sg:province":"NC",
    "sg:tags":[
        "home",
        "builder"
    ],
    "wof:name":"Beazer Homes",
    "wof:placetype":"venue"
},
  "geometry": {"coordinates":[-79.192109,35.455163],"type":"Point"}
}