{
  "type": "Feature",
  "properties": {
    "iso:country":"US",
    "sg:address":"1501 Freedom Dr",
    "sg:city":"Charlotte",
    "sg:classifiers":[
        {
            "category":"Home & Garden",
            "subcategory":"Carpets & Floor Coverings",
            "type":"Retail Goods"
        }
    ],
    "sg:phone":"+1 704 377 1648",
    "sg:postcode":"28208",
    "sg:province":"NC",
    "sg:tags":[
        "building",
        "material"
    ],
    "wof:name":"Bradshaw-Hayes Inc",
    "wof:placetype":"venue"
},
  "geometry": {"coordinates":[-80.866997,35.22757],"type":"Point"}
}