{
  "type": "Feature",
  "properties": {
    "addr:full":"3940 Plymouth Rd Durham NC 27707",
    "addr:housenumber":"3940",
    "addr:postcode":"27707",
    "addr:street":"Plymouth Rd",
    "iso:country":"US",
    "sg:address":"3940 Plymouth Rd",
    "sg:city":"Durham",
    "sg:classifiers":[
        {
            "category":"Professional",
            "type":"Services"
        }
    ],
    "sg:phone":"+1 919 493 7303",
    "sg:postcode":"27707",
    "sg:province":"NC",
    "sg:tags":[
        "establishment"
    ],
    "wof:name":"Jones Southgate III",
    "wof:placetype":"venue"
},
  "geometry": {"coordinates":[-78.949783,35.942125],"type":"Point"}
}