{
  "type": "Feature",
  "properties": {
    "iso:country":"US",
    "sg:address":"127 Depot St",
    "sg:city":"Roxboro",
    "sg:classifiers":[
        {
            "category":"Shopping",
            "subcategory":"Used Merchandise",
            "type":"Retail Goods"
        }
    ],
    "sg:phone":"+1 336 599 5028",
    "sg:postcode":"27573",
    "sg:province":"NC",
    "sg:tags":[
        "antique"
    ],
    "wof:name":"Carol's Collectables",
    "wof:placetype":"venue"
},
  "geometry": {"coordinates":[-78.98281799999999,36.39406],"type":"Point"}
}