{
  "type": "Feature",
  "properties": {
    "addr:full":"790 Crescent Rd Rockwell NC 28138",
    "addr:housenumber":"790",
    "addr:postcode":"28138",
    "addr:street":"Crescent Rd",
    "iso:country":"US",
    "sg:address":"790 Crescent Rd",
    "sg:city":"Rockwell",
    "sg:classifiers":[
        {
            "category":"Social Services",
            "subcategory":"Child Care",
            "type":"Services"
        }
    ],
    "sg:phone":"+1 704 279 1742",
    "sg:postcode":"28138",
    "sg:province":"NC",
    "sg:website":"http://www.rowanymca.com",
    "wof:name":"East Rowan Ymca",
    "wof:placetype":"venue"
},
  "geometry": {"coordinates":[-80.425718,35.569973],"type":"Point"}
}