{
  "type": "Feature",
  "properties": {
    "addr:full":"2642 Overhill Loop Mc Leansville NC 27301",
    "addr:housenumber":"2642",
    "addr:postcode":"27301",
    "addr:street":"Overhill Loop Mc Leansville",
    "iso:country":"US",
    "sg:address":"2642 Overhill Loop",
    "sg:city":"Mc Leansville",
    "sg:classifiers":[
        {
            "category":"Building & Trades",
            "subcategory":"Landscaping Services",
            "type":"Services"
        }
    ],
    "sg:phone":"+1 336 697 0386",
    "sg:postcode":"27301",
    "sg:province":"NC",
    "wof:name":"Whitesell Tree & Ldscpg Svc",
    "wof:placetype":"venue"
},
  "geometry": {"coordinates":[-79.655129,36.030721],"type":"Point"}
}