{
  "type": "Feature",
  "properties": {
    "iso:country":"US",
    "sg:address":"171 Grayrock Dr",
    "sg:city":"Statesville",
    "sg:classifiers":[
        {
            "category":"Wholesale",
            "subcategory":"Toys & Hobbies",
            "type":"Manufacturing & Wholesale Goods"
        }
    ],
    "sg:phone":"+1 704 528 1400",
    "sg:postcode":"28677",
    "sg:province":"NC",
    "sg:tags":[
        "wholesaler"
    ],
    "wof:name":"Empire Wholesale Lumber",
    "wof:placetype":"venue"
},
  "geometry": {"coordinates":[-80.98454599999999,35.702089],"type":"Point"}
}