{
  "type": "Feature",
  "properties": {
    "iso:country":"US",
    "sg:address":"6 Wall St",
    "sg:city":"Asheville",
    "sg:classifiers":[
        {
            "category":"Banks & Credit Unions",
            "subcategory":"Investment Brokerage",
            "type":"Services"
        }
    ],
    "sg:phone":"+1 828 255 8951",
    "sg:postcode":"28801",
    "sg:province":"NC",
    "sg:tags":[
        "consultant",
        "planning",
        "financial"
    ],
    "sg:website":"www.parsecfinancial.com",
    "wof:name":"Parsec Financial",
    "wof:placetype":"venue"
},
  "geometry": {"coordinates":[-82.55693599999999,35.594353],"type":"Point"}
}