{
  "type": "Feature",
  "properties": {
    "addr:full":"29 Cardinal Rd Tarboro NC 27886",
    "addr:housenumber":"29",
    "addr:postcode":"27886",
    "addr:street":"Cardinal Rd",
    "iso:country":"US",
    "sg:address":"29 Cardinal Rd",
    "sg:city":"Tarboro",
    "sg:classifiers":[
        {
            "category":"Building & Trades",
            "subcategory":"Construction",
            "type":"Services"
        }
    ],
    "sg:phone":"+1 252 823 8012",
    "sg:postcode":"27886",
    "sg:province":"NC",
    "sg:tags":[
        "house"
    ],
    "wof:name":"Dudley Construction Inc",
    "wof:placetype":"venue"
},
  "geometry": {"coordinates":[-77.62720899999999,35.859285],"type":"Point"}
}