{
  "type": "Feature",
  "properties": {
    "iso:country":"US",
    "sg:address":"201 Hillview Blvd",
    "sg:city":"Hendersonville",
    "sg:classifiers":[
        {
            "category":"Real Estate",
            "subcategory":"Real Estate Agent",
            "type":"Services"
        }
    ],
    "sg:phone":"+1 828 693 1300",
    "sg:postcode":"28792",
    "sg:province":"NC",
    "sg:tags":[
        "appraiser"
    ],
    "wof:name":"BRB Appraisal Assoc",
    "wof:placetype":"venue"
},
  "geometry": {"coordinates":[-82.45236199999999,35.307517],"type":"Point"}
}