{
  "type": "Feature",
  "properties": {
    "addr:full":"1400 Nowell Rd Raleigh NC 27607",
    "addr:housenumber":"1400",
    "addr:postcode":"27607",
    "addr:street":"Nowell Rd",
    "iso:country":"US",
    "sg:address":"1400 Nowell Rd",
    "sg:city":"Raleigh",
    "sg:classifiers":[
        {
            "category":"Building & Trades",
            "subcategory":"Construction",
            "type":"Services"
        }
    ],
    "sg:phone":"+1 919 851 6060",
    "sg:postcode":"27607",
    "sg:province":"NC",
    "sg:tags":[
        "general",
        "contractor"
    ],
    "sg:website":"www.jedcoconstruction.com",
    "wof:name":"Jedco Construction Inc",
    "wof:placetype":"venue"
},
  "geometry": {"coordinates":[-78.73412,35.797388],"type":"Point"}
}