{
  "type": "Feature",
  "properties": {
    "iso:country":"US",
    "sg:address":"555 Peyton Dr",
    "sg:city":"Hendersonville",
    "sg:classifiers":[
        {
            "category":"Building & Trades",
            "subcategory":"Construction",
            "type":"Services"
        }
    ],
    "sg:phone":"+1 828 891 4549",
    "sg:postcode":"28739",
    "sg:province":"NC",
    "sg:tags":[
        "house",
        "improvement",
        "home"
    ],
    "wof:name":"Murphy Home Improvements",
    "wof:placetype":"venue"
},
  "geometry": {"coordinates":[-82.53538399999999,35.338507],"type":"Point"}
}