{
  "type": "Feature",
  "properties": {
    "iso:country":"US",
    "sg:address":"6201 Fairview Rd Ste 200",
    "sg:city":"Charlotte",
    "sg:classifiers":[
        {
            "category":"Professional",
            "subcategory":"Lawyer & Legal Services",
            "type":"Services"
        },
        {
            "category":"Home & Garden",
            "subcategory":"Carpets & Floor Coverings",
            "type":"Retail Goods"
        }
    ],
    "sg:phone":"+1 704 944 4290",
    "sg:postcode":"28210",
    "sg:province":"NC",
    "sg:tags":[
        "security",
        "law",
        "investment",
        "attorney"
    ],
    "wof:name":"Partners For Wellness Inc.",
    "wof:placetype":"venue"
},
  "geometry": {"coordinates":[-80.836853,35.150841],"type":"Point"}
}