{
  "type": "Feature",
  "properties": {
    "iso:country":"US",
    "sg:address":"2329 E W T Harris Blvd",
    "sg:city":"Charlotte",
    "sg:classifiers":[
        {
            "category":"Banks & Credit Unions",
            "subcategory":"Investment Brokerage",
            "type":"Services"
        }
    ],
    "sg:phone":"+1 704 509 2200",
    "sg:postcode":"28213",
    "sg:province":"NC",
    "sg:tags":[
        "advisory",
        "financial"
    ],
    "sg:website":"www.ifsllc.net",
    "wof:name":"Integritiy Financial Svc LLC",
    "wof:placetype":"venue"
},
  "geometry": {"coordinates":[-80.72751100000001,35.276625],"type":"Point"}
}