{
  "type": "Feature",
  "properties": {
    "iso:country":"US",
    "sg:address":"634 Waugh St",
    "sg:city":"Greensboro",
    "sg:classifiers":[
        {
            "category":"Social Services",
            "subcategory":"Child Care",
            "type":"Services"
        }
    ],
    "sg:phone":"+1 336 274 5516",
    "sg:postcode":"27405",
    "sg:province":"NC",
    "wof:name":"Hester's Creative Schools Inc",
    "wof:placetype":"venue"
},
  "geometry": {"coordinates":[-79.75125,36.087486],"type":"Point"}
}