{
  "type": "Feature",
  "properties": {
    "iso:country":"US",
    "sg:address":"3108 Aileen Dr",
    "sg:city":"Raleigh",
    "sg:classifiers":[
        {
            "category":"Organizations",
            "subcategory":"Community Association",
            "type":"Services"
        }
    ],
    "sg:phone":"+1   ",
    "sg:postcode":"27606",
    "sg:province":"NC",
    "wof:name":"Ceres Fraternity",
    "wof:placetype":"venue"
},
  "geometry": {"coordinates":[-78.69560799999999,35.760424],"type":"Point"}
}