{
  "type": "Feature",
  "properties": {
    "iso:country":"US",
    "sg:address":"226 State Hwy 16",
    "sg:city":"Taylorsville",
    "sg:classifiers":[
        {
            "category":"Health Services",
            "subcategory":"Hospital",
            "type":"Services"
        }
    ],
    "sg:phone":"+1 828 635 4000",
    "sg:postcode":"28681",
    "sg:province":"NC",
    "wof:name":"Frye Regional Medical Ctr",
    "wof:placetype":"venue"
},
  "geometry": {"coordinates":[-81.179163,35.921915],"type":"Point"}
}