{
  "type": "Feature",
  "properties": {
    "iso:country":"US",
    "sg:address":"420 N Center St",
    "sg:city":"Hickory",
    "sg:classifiers":[
        {
            "category":"Health Services",
            "subcategory":"Doctor",
            "type":"Services"
        }
    ],
    "sg:phone":"+1   ",
    "sg:postcode":"28601",
    "sg:province":"NC",
    "sg:tags":[
        "medical"
    ],
    "wof:name":"Center For Dbtes Self MGT Care",
    "wof:placetype":"venue"
},
  "geometry": {"coordinates":[-81.33769599999999,35.736692],"type":"Point"}
}