{
  "type": "Feature",
  "properties": {
    "iso:country":"US",
    "sg:address":"611 S Green St",
    "sg:city":"Statesville",
    "sg:classifiers":[
        {
            "category":"Retail",
            "subcategory":"Funeral Services",
            "type":"Services"
        }
    ],
    "sg:phone":"+1 704 873 3031",
    "sg:postcode":"28677",
    "sg:province":"NC",
    "sg:tags":[
        "director"
    ],
    "wof:name":"Davis & Mangum Funeral Home",
    "wof:placetype":"venue"
},
  "geometry": {"coordinates":[-80.880449,35.779736],"type":"Point"}
}