{
  "type": "Feature",
  "properties": {
    "addr:full":"833 Durham Rd Wake Forest NC 27587",
    "addr:housenumber":"833",
    "addr:postcode":"27587",
    "addr:street":"Durham Rd",
    "iso:country":"US",
    "sg:address":"833 Durham Rd",
    "sg:city":"Wake Forest",
    "sg:classifiers":[
        {
            "category":"Health Services",
            "subcategory":"Doctor",
            "type":"Services"
        }
    ],
    "sg:phone":"+1 919 556 0379",
    "sg:postcode":"27587",
    "sg:province":"NC",
    "sg:tags":[
        "physician",
        "surgeon"
    ],
    "wof:name":"Munther S Tabet MD",
    "wof:placetype":"venue"
},
  "geometry": {"coordinates":[-78.53464700000001,35.979709],"type":"Point"}
}