{
  "type": "Feature",
  "properties": {
    "iso:country":"US",
    "sg:address":"5574 Garden Village Way",
    "sg:city":"Greensboro",
    "sg:classifiers":[
        {
            "category":"Home & Garden",
            "subcategory":"Garden Supply",
            "type":"Retail Goods"
        }
    ],
    "sg:phone":"+1 336 664 8020",
    "sg:postcode":"27410",
    "sg:province":"NC",
    "sg:tags":[
        "house",
        "bird",
        "feeder"
    ],
    "wof:name":"Wild Bird House",
    "wof:placetype":"venue"
},
  "geometry": {"coordinates":[-79.90464799999999,36.115453],"type":"Point"}
}