{
  "type": "Feature",
  "properties": {
    "addr:full":"206 E Woodlawn Rd Charlotte NC 28217",
    "addr:housenumber":"206",
    "addr:postcode":"28217",
    "addr:street":"E Woodlawn Rd",
    "iso:country":"US",
    "sg:address":"206 E Woodlawn Rd",
    "sg:city":"Charlotte",
    "sg:classifiers":[
        {
            "category":"Utilities",
            "subcategory":"Telephone",
            "type":"Services"
        },
        {
            "category":"Professional",
            "subcategory":"Management & Consulting",
            "type":"Services"
        }
    ],
    "sg:phone":"+1 704 525 4115",
    "sg:postcode":"28217",
    "sg:province":"NC",
    "sg:tags":[
        "communications",
        "telecommunication",
        "consultant"
    ],
    "wof:name":"Tele Sys Technology Inc",
    "wof:placetype":"venue"
},
  "geometry": {"coordinates":[-80.882508,35.178773],"type":"Point"}
}