{
  "type": "Feature",
  "properties": {
    "iso:country":"US",
    "sg:address":"101 Government Ave SW",
    "sg:city":"Hickory",
    "sg:classifiers":[
        {
            "category":"Professional",
            "subcategory":"Employment Agencies",
            "type":"Services"
        }
    ],
    "sg:phone":"+1 828 323 8900",
    "sg:postcode":"28602",
    "sg:province":"NC",
    "sg:tags":[
        "consultant",
        "search",
        "executive"
    ],
    "wof:name":"Hanson Group",
    "wof:placetype":"venue"
},
  "geometry": {"coordinates":[-81.339584,35.731396],"type":"Point"}
}