{
  "type": "Feature",
  "properties": {
    "addr:full":"220 W Acadia Ave Winston Salem NC 27127",
    "addr:housenumber":"220",
    "addr:postcode":"27127",
    "addr:street":"W Acadia Ave",
    "iso:country":"US",
    "sg:address":"220 W Acadia Ave",
    "sg:city":"Winston Salem",
    "sg:classifiers":[
        {
            "category":"Organizations",
            "subcategory":"Labor Organization",
            "type":"Services"
        }
    ],
    "sg:phone":"+1 336 723 3712",
    "sg:postcode":"27127",
    "sg:province":"NC",
    "sg:website":"www.nalc.org",
    "wof:name":"National Assn-Letter Carriers",
    "wof:placetype":"venue"
},
  "geometry": {"coordinates":[-80.244427,36.071157],"type":"Point"}
}