{
  "type": "Feature",
  "properties": {
    "addr:full":"6050 Brookshire Blvd Charlotte NC 28216",
    "addr:housenumber":"6050",
    "addr:postcode":"28216",
    "addr:street":"Brookshire Blvd",
    "iso:country":"US",
    "sg:address":"6050 Brookshire Blvd",
    "sg:city":"Charlotte",
    "sg:classifiers":[
        {
            "category":"Building & Trades",
            "subcategory":"Electrical",
            "type":"Services"
        }
    ],
    "sg:phone":"+1 704 399 1372",
    "sg:postcode":"28216",
    "sg:province":"NC",
    "sg:tags":[
        "electrician"
    ],
    "wof:name":"Horne Electric Co Inc",
    "wof:placetype":"venue"
},
  "geometry": {"coordinates":[-80.903915,35.284071],"type":"Point"}
}