{
  "type": "Feature",
  "properties": {
    "iso:country":"US",
    "sg:address":"525 S Henry St",
    "sg:city":"Stoneville",
    "sg:classifiers":[
        {
            "category":"Professional",
            "subcategory":"Management & Consulting",
            "type":"Services"
        }
    ],
    "sg:phone":"+1 336 573 3902",
    "sg:postcode":"27048",
    "sg:province":"NC",
    "sg:tags":[
        "logistics"
    ],
    "sg:website":"www.servicelogisticsinc.com",
    "wof:name":"Service Logistics Inc",
    "wof:placetype":"venue"
},
  "geometry": {"coordinates":[-79.91010900000001,36.458273],"type":"Point"}
}