{
  "type": "Feature",
  "properties": {
    "addr:full":"3101 New Bern Ave Raleigh NC 27610",
    "addr:housenumber":"3101",
    "addr:postcode":"27610",
    "addr:street":"New Bern Ave",
    "iso:country":"US",
    "sg:address":"3101 New Bern Ave",
    "sg:city":"Raleigh",
    "sg:phone":"+1 919 231 5074",
    "sg:postcode":"27610",
    "sg:province":"NC",
    "sg:website":"http://www.walgreens.com/default.jsp?ec=iyp_yellowpages_trademark",
    "wof:name":"Walgreens Pharmacies",
    "wof:placetype":"venue"
},
  "geometry": {"coordinates":[-78.587929,35.787922],"type":"Point"}
}