{
  "type": "Feature",
  "properties": {
    "iso:country":"US",
    "sg:address":"8378 Six Forks Rd",
    "sg:city":"Raleigh",
    "sg:classifiers":[
        {
            "category":"Professional",
            "subcategory":"Advertising",
            "type":"Services"
        }
    ],
    "sg:phone":"+1 919 870 6623",
    "sg:postcode":"27615",
    "sg:province":"NC",
    "wof:name":"Success By Design",
    "wof:placetype":"venue"
},
  "geometry": {"coordinates":[-78.64830000000001,35.891606],"type":"Point"}
}