{
  "type": "Feature",
  "properties": {
    "iso:country":"US",
    "sg:address":"143 May St",
    "sg:city":"Saint Pauls",
    "sg:classifiers":[
        {
            "category":"Professional",
            "subcategory":"Business Services",
            "type":"Services"
        }
    ],
    "sg:phone":"+1   ",
    "sg:postcode":"28384",
    "sg:province":"NC",
    "wof:name":"J&M Enterprises",
    "wof:placetype":"venue"
},
  "geometry": {"coordinates":[-78.95468099999999,34.80541],"type":"Point"}
}