{
  "type": "Feature",
  "properties": {
    "addr:full":"9025 Stack Rd Colfax NC 27235",
    "addr:housenumber":"9025",
    "addr:postcode":"27235",
    "addr:street":"Stack Rd",
    "iso:country":"US",
    "sg:address":"9025 Stack Rd",
    "sg:city":"Colfax",
    "sg:classifiers":[
        {
            "category":"Autos & Motor Vehicles",
            "subcategory":"Auto Supplies",
            "type":"Retail Goods"
        }
    ],
    "sg:phone":"+1 336 996 1104",
    "sg:postcode":"27235",
    "sg:province":"NC",
    "wof:name":"Tires For Less",
    "wof:placetype":"venue"
},
  "geometry": {"coordinates":[-80.02372099999999,36.099156],"type":"Point"}
}