{
  "type": "Feature",
  "properties": {
    "iso:country":"US",
    "sg:address":"8525 Bella Reese Rd",
    "sg:city":"Charlotte",
    "sg:classifiers":[
        {
            "category":"Social Services",
            "subcategory":"Job Training",
            "type":"Services"
        }
    ],
    "sg:phone":"+1 704 540 0113",
    "sg:postcode":"28277",
    "sg:province":"NC",
    "sg:tags":[
        "retardation",
        "disabled",
        "mental",
        "dev"
    ],
    "wof:name":"United Support Svc Inc",
    "wof:placetype":"venue"
},
  "geometry": {"coordinates":[-80.81112,35.052009],"type":"Point"}
}