{
  "type": "Feature",
  "properties": {
    "iso:country":"US",
    "sg:address":"127 E Main St",
    "sg:city":"Cherryville",
    "sg:classifiers":[
        {
            "category":"Shopping",
            "subcategory":"Jewelry",
            "type":"Retail Goods"
        }
    ],
    "sg:phone":"+1 704 435 4666",
    "sg:postcode":"28021",
    "sg:province":"NC",
    "wof:name":"Stroupe Jewelry",
    "wof:placetype":"venue"
},
  "geometry": {"coordinates":[-81.378882,35.379217],"type":"Point"}
}