{
  "type": "Feature",
  "properties": {
    "iso:country":"US",
    "sg:address":"7740 McArtans Ford",
    "sg:city":"Linden",
    "sg:classifiers":[
        {
            "category":"Professional",
            "subcategory":"Business Services",
            "type":"Services"
        }
    ],
    "sg:phone":"+1 910 822 2515",
    "sg:postcode":"28356",
    "sg:province":"NC",
    "sg:tags":[
        "construction",
        "nonresidential"
    ],
    "wof:name":"Jenkins Design & Build LLC",
    "wof:placetype":"venue"
},
  "geometry": {"coordinates":[-78.822925,35.208093],"type":"Point"}
}