{
  "type": "Feature",
  "properties": {
    "addr:full":"1251 Dabney Dr Henderson NC 27536",
    "addr:housenumber":"1251",
    "addr:postcode":"27536",
    "addr:street":"Dabney Dr",
    "iso:country":"US",
    "sg:address":"1251 Dabney Dr",
    "sg:city":"Henderson",
    "sg:classifiers":[
        {
            "category":"Personal",
            "type":"Services"
        }
    ],
    "sg:phone":"+1 252 430 6621",
    "sg:postcode":"27536",
    "sg:province":"NC",
    "sg:tags":[
        "program",
        "physical",
        "exercise",
        "fitness"
    ],
    "wof:name":"T J's Fitness & Beyond",
    "wof:placetype":"venue"
},
  "geometry": {"coordinates":[-78.430892,36.330355],"type":"Point"}
}