{
  "type": "Feature",
  "properties": {
    "addr:full":"814 Dunn Rd Fayetteville NC 28312",
    "addr:housenumber":"814",
    "addr:postcode":"28312",
    "addr:street":"Dunn Rd",
    "iso:country":"US",
    "sg:address":"814 Dunn Rd",
    "sg:city":"Fayetteville",
    "sg:classifiers":[
        {
            "category":"Retail",
            "subcategory":"Auto Repair",
            "type":"Services"
        }
    ],
    "sg:phone":"+1 910 483 6805",
    "sg:postcode":"28312",
    "sg:province":"NC",
    "sg:tags":[
        "repairing",
        "automobile"
    ],
    "wof:name":"Tatum Brothers Auto Svc Inc",
    "wof:placetype":"venue"
},
  "geometry": {"coordinates":[-78.845511,35.056089],"type":"Point"}
}