{
  "type": "Feature",
  "properties": {
    "addr:full":"120 Hay St Fayetteville NC 28301",
    "addr:housenumber":"120",
    "addr:postcode":"28301",
    "addr:street":"Hay St",
    "iso:country":"US",
    "sg:address":"120 Hay St",
    "sg:city":"Fayetteville",
    "sg:classifiers":[
        {
            "category":"Shopping",
            "subcategory":"Used Merchandise",
            "type":"Retail Goods"
        }
    ],
    "sg:phone":"+1 910 485 1270",
    "sg:postcode":"28301",
    "sg:province":"NC",
    "sg:tags":[
        "antique"
    ],
    "wof:name":"Good Place Antiques & Things",
    "wof:placetype":"venue"
},
  "geometry": {"coordinates":[-78.879458,35.053032],"type":"Point"}
}