{
  "type": "Feature",
  "properties": {
    "addr:full":"9700 Erinsbrook Dr Raleigh NC 27617",
    "addr:postcode":"9700;27617",
    "addr:street":"Erinsbrook Dr",
    "iso:country":"US",
    "sg:address":"9700 Erinsbrook Dr",
    "sg:city":"Raleigh",
    "sg:classifiers":[
        {
            "category":"Professional",
            "subcategory":"Computer Services",
            "type":"Services"
        }
    ],
    "sg:phone":"+1   ",
    "sg:postcode":"27617",
    "sg:province":"NC",
    "sg:tags":[
        "programing",
        "custom"
    ],
    "wof:name":"Savante Systems",
    "wof:placetype":"venue"
},
  "geometry": {"coordinates":[-78.747136,35.915204],"type":"Point"}
}