{
  "type": "Feature",
  "properties": {
    "iso:country":"US",
    "sg:address":"149 Providence Rd",
    "sg:city":"Charlotte",
    "sg:classifiers":[
        {
            "category":"Health Services",
            "subcategory":"Medical Lab",
            "type":"Services"
        }
    ],
    "sg:phone":"+1 704 384 7186",
    "sg:postcode":"28207",
    "sg:province":"NC",
    "sg:tags":[
        "laboratory"
    ],
    "wof:name":"Allison J Dudley",
    "wof:placetype":"venue"
},
  "geometry": {"coordinates":[-80.824853,35.208739],"type":"Point"}
}