{
  "type": "Feature",
  "properties": {
    "iso:country":"US",
    "sg:address":"126 Wells Rd",
    "sg:city":"Lawndale",
    "sg:classifiers":[
        {
            "category":"Home & Garden",
            "subcategory":"Garden Supply",
            "type":"Retail Goods"
        }
    ],
    "sg:phone":"+1 704 538 0427",
    "sg:postcode":"28090",
    "sg:province":"NC",
    "sg:tags":[
        "lawn",
        "mower"
    ],
    "wof:name":"Searcy's Small Engine Repair",
    "wof:placetype":"venue"
},
  "geometry": {"coordinates":[-81.496673,35.423327],"type":"Point"}
}