{
  "type": "Feature",
  "properties": {
    "addr:full":"3910 Seaton Rd Winston Salem NC 27104",
    "addr:housenumber":"3910",
    "addr:postcode":"27104",
    "addr:street":"Seaton Rd",
    "iso:country":"US",
    "sg:address":"3910 Seaton Rd",
    "sg:city":"Winston Salem",
    "sg:classifiers":[
        {
            "category":"Professional",
            "type":"Services"
        }
    ],
    "sg:phone":"+1 336 768 0830",
    "sg:postcode":"27104",
    "sg:province":"NC",
    "wof:name":"Salem Trombone Choir Inc",
    "wof:placetype":"venue"
},
  "geometry": {"coordinates":[-80.330128,36.095652],"type":"Point"}
}