{
  "type": "Feature",
  "properties": {
    "iso:country":"US",
    "sg:address":"2208 Duxbak Ln",
    "sg:city":"Waxhaw",
    "sg:classifiers":[
        {
            "category":"Real Estate",
            "subcategory":"Developer",
            "type":"Services"
        }
    ],
    "sg:phone":"+1 704 843 0690",
    "sg:postcode":"28173",
    "sg:province":"NC",
    "sg:tags":[
        "land",
        "subdivider"
    ],
    "wof:name":"Nassar Investments",
    "wof:placetype":"venue"
},
  "geometry": {"coordinates":[-80.739543,34.956563],"type":"Point"}
}