{
  "type": "Feature",
  "properties": {
    "addr:full":"4196 Spirea Dr Wilmington NC 28403",
    "addr:housenumber":"4196",
    "addr:postcode":"28403",
    "addr:street":"Spirea Dr",
    "iso:country":"US",
    "sg:address":"4196 Spirea Dr",
    "sg:city":"Wilmington",
    "sg:classifiers":[
        {
            "category":"Banks & Credit Unions",
            "subcategory":"Investment Brokerage",
            "type":"Services"
        },
        {
            "category":"Professional",
            "subcategory":"Management & Consulting",
            "type":"Services"
        }
    ],
    "sg:phone":"+1 910 509 1676",
    "sg:postcode":"28403",
    "sg:province":"NC",
    "sg:tags":[
        "consultant",
        "planning",
        "financial"
    ],
    "wof:name":"Verity Asset Management",
    "wof:placetype":"venue"
},
  "geometry": {"coordinates":[-77.893019,34.209085],"type":"Point"}
}