{
  "type": "Feature",
  "properties": {
    "addr:full":"2051 Wagon Ln Hickory NC 28601",
    "addr:housenumber":"2051",
    "addr:postcode":"28601",
    "addr:street":"Wagon Ln",
    "iso:country":"US",
    "sg:address":"2051 Wagon Ln",
    "sg:city":"Hickory",
    "sg:classifiers":[
        {
            "category":"Shopping",
            "subcategory":"Discount & Variety Stores",
            "type":"Retail Goods"
        }
    ],
    "sg:phone":"+1 828 256 8207",
    "sg:postcode":"28601",
    "sg:province":"NC",
    "sg:tags":[
        "merchandise",
        "general"
    ],
    "wof:name":"Carter Factory Close-Outs Inc",
    "wof:placetype":"venue"
},
  "geometry": {"coordinates":[-81.261062,35.75397],"type":"Point"}
}