{
  "type": "Feature",
  "properties": {
    "iso:country":"US",
    "sg:address":"209 S Main St",
    "sg:city":"Dobson",
    "sg:classifiers":[
        {
            "category":"Insurance",
            "subcategory":"Insurance Agent",
            "type":"Services"
        }
    ],
    "sg:phone":"+1 336 386 8087",
    "sg:postcode":"27017",
    "sg:province":"NC",
    "wof:name":"Chappell Insurance Inc",
    "wof:placetype":"venue"
},
  "geometry": {"coordinates":[-80.721963,36.394766],"type":"Point"}
}