{
  "type": "Feature",
  "properties": {
    "iso:country":"US",
    "sg:address":"3702 Alliance Dr",
    "sg:city":"Greensboro",
    "sg:classifiers":[
        {
            "category":"Retail",
            "subcategory":"Self-service Laundry",
            "type":"Services"
        }
    ],
    "sg:phone":"+1 336 292 9954",
    "sg:postcode":"27407",
    "sg:province":"NC",
    "sg:tags":[
        "operated",
        "washer",
        "coin",
        "dryer"
    ],
    "wof:name":"Web Service Co Inc",
    "wof:placetype":"venue"
},
  "geometry": {"coordinates":[-79.872955,36.055611],"type":"Point"}
}