{
  "type": "Feature",
  "properties": {
    "iso:country":"US",
    "sg:address":"6420 Brevard Rd",
    "sg:city":"Etowah",
    "sg:classifiers":[
        {
            "category":"Building & Trades",
            "subcategory":"Plumbing",
            "type":"Services"
        }
    ],
    "sg:phone":"+1 828 890 8127",
    "sg:postcode":"28729",
    "sg:province":"NC",
    "sg:tags":[
        "conditioning",
        "air",
        "system",
        "contractor"
    ],
    "wof:name":"Stews Heating & Cooling",
    "wof:placetype":"venue"
},
  "geometry": {"coordinates":[-82.589011,35.318135],"type":"Point"}
}