{
  "type": "Feature",
  "properties": {
    "addr:full":"2205 River Rd Troy NC 27371",
    "addr:housenumber":"2205",
    "addr:postcode":"27371",
    "addr:street":"River Rd",
    "iso:country":"US",
    "sg:address":"2205 River Rd",
    "sg:city":"Troy",
    "sg:classifiers":[
        {
            "category":"Real Estate",
            "subcategory":"Real Estate Agent",
            "type":"Services"
        }
    ],
    "sg:phone":"+1 910 572 3892",
    "sg:postcode":"27371",
    "sg:province":"NC",
    "wof:name":"Carolina Forest Guardhouse",
    "wof:placetype":"venue"
},
  "geometry": {"coordinates":[-80.04161499999999,35.361283],"type":"Point"}
}