{
  "type": "Feature",
  "properties": {
    "addr:full":"360 N Main St Sparta NC 28675",
    "addr:housenumber":"360",
    "addr:postcode":"28675",
    "addr:street":"N Main St",
    "iso:country":"US",
    "sg:address":"360 N Main St",
    "sg:city":"Sparta",
    "sg:classifiers":[
        {
            "category":"Restaurant",
            "type":"Food & Drink"
        }
    ],
    "sg:phone":"+1 336 372 7500",
    "sg:postcode":"28675",
    "sg:province":"NC",
    "wof:name":"Senator's House",
    "wof:placetype":"venue"
},
  "geometry": {"coordinates":[-81.122851,36.507436],"type":"Point"}
}