{
  "type": "Feature",
  "properties": {
    "iso:country":"US",
    "sg:address":"277 Jones Turner Rd",
    "sg:city":"Mount Olive",
    "sg:classifiers":[
        {
            "category":"Shopping",
            "subcategory":"Florist",
            "type":"Retail Goods"
        }
    ],
    "sg:phone":"+1 919 658 2151",
    "sg:postcode":"28365",
    "sg:province":"NC",
    "wof:name":"Floral Designs By Clara",
    "wof:placetype":"venue"
},
  "geometry": {"coordinates":[-78.028806,35.183036],"type":"Point"}
}