{
  "type": "Feature",
  "properties": {
    "addr:full":"501 Martin St Elizabethtown NC 28337",
    "addr:housenumber":"501",
    "addr:postcode":"28337",
    "addr:street":"Martin St",
    "iso:country":"US",
    "sg:address":"501 Martin St",
    "sg:city":"Elizabethtown",
    "sg:classifiers":[
        {
            "category":"Organizations",
            "subcategory":"Religious Organization",
            "type":"Services"
        }
    ],
    "sg:phone":"+1   ",
    "sg:postcode":"28337",
    "sg:province":"NC",
    "wof:name":"First Baptist Church",
    "wof:placetype":"venue"
},
  "geometry": {"coordinates":[-78.613866,34.62658],"type":"Point"}
}