{
  "type": "Feature",
  "properties": {
    "iso:country":"US",
    "sg:address":"9301 South Blvd",
    "sg:city":"Charlotte",
    "sg:classifiers":[
        {
            "category":"Government",
            "subcategory":"Office",
            "type":"Public Place"
        }
    ],
    "sg:phone":"+1 704 588 2660",
    "sg:postcode":"28273",
    "sg:province":"NC",
    "wof:name":"North Carolina Welcome Ctr",
    "wof:placetype":"venue"
},
  "geometry": {"coordinates":[-80.882389,35.110637],"type":"Point"}
}