{
  "type": "Feature",
  "properties": {
    "iso:country":"US",
    "sg:address":"128 Quail Run",
    "sg:city":"Smithfield",
    "sg:classifiers":[
        {
            "category":"Professional",
            "subcategory":"Business Services",
            "type":"Services"
        }
    ],
    "sg:phone":"+1   ",
    "sg:postcode":"27577",
    "sg:province":"NC",
    "wof:name":"Utility Partners America In",
    "wof:placetype":"venue"
},
  "geometry": {"coordinates":[-78.385255,35.475897],"type":"Point"}
}