{
  "type": "Feature",
  "properties": {
    "addr:full":"125 Ridge Trl Chapel Hill NC 27516",
    "addr:housenumber":"125",
    "addr:postcode":"27516",
    "addr:street":"Ridge Trl",
    "iso:country":"US",
    "sg:address":"125 Ridge Trl",
    "sg:city":"Chapel Hill",
    "sg:classifiers":[
        {
            "category":"Food & Beverages",
            "subcategory":"Bakery",
            "type":"Retail Goods"
        }
    ],
    "sg:phone":"+1 919 260 7700",
    "sg:postcode":"27516",
    "sg:province":"NC",
    "sg:tags":[
        "baker"
    ],
    "wof:name":"Art Of Cake",
    "wof:placetype":"venue"
},
  "geometry": {"coordinates":[-79.067528,35.921987],"type":"Point"}
}