{
  "type": "Feature",
  "properties": {
    "addr:full":"2820 Industrial Dr Raleigh NC 27609",
    "addr:housenumber":"2820",
    "addr:postcode":"27609",
    "addr:street":"Industrial Dr",
    "iso:country":"US",
    "sg:address":"2820 Industrial Dr",
    "sg:city":"Raleigh",
    "sg:classifiers":[
        {
            "category":"Bars & Pubs",
            "type":"Food & Drink"
        }
    ],
    "sg:phone":"+1 919 836 8535",
    "sg:postcode":"27609",
    "sg:province":"NC",
    "sg:tags":[
        "club",
        "night"
    ],
    "sg:website":"www.ritztheater.com",
    "wof:name":"Ritz Theatre",
    "wof:placetype":"venue"
},
  "geometry": {"coordinates":[-78.620175,35.817835],"type":"Point"}
}