{
  "type": "Feature",
  "properties": {
    "iso:country":"US",
    "sg:address":"2535 Nealwood Ave",
    "sg:city":"Graham",
    "sg:classifiers":[
        {
            "category":"Real Estate",
            "subcategory":"Real Estate Operator",
            "type":"Services"
        }
    ],
    "sg:phone":"+1 336 228 8284",
    "sg:postcode":"27253",
    "sg:province":"NC",
    "sg:tags":[
        "property",
        "lessor"
    ],
    "wof:name":"Foley Family LLC",
    "wof:placetype":"venue"
},
  "geometry": {"coordinates":[-79.383134,36.013911],"type":"Point"}
}