{
  "type": "Feature",
  "properties": {
    "addr:full":"18610 Statesville Rd Cornelius NC 28031",
    "addr:housenumber":"18610",
    "addr:postcode":"28031",
    "addr:street":"Statesville Rd",
    "iso:country":"US",
    "sg:address":"18610 Statesville Rd",
    "sg:city":"Cornelius",
    "sg:classifiers":[
        {
            "category":"Autos & Motor Vehicles",
            "subcategory":"Automobile Sales",
            "type":"Retail Goods"
        }
    ],
    "sg:phone":"+1 704 895 0717",
    "sg:postcode":"28031",
    "sg:province":"NC",
    "sg:tags":[
        "car",
        "dealer"
    ],
    "wof:name":"Auto Ventures",
    "wof:placetype":"venue"
},
  "geometry": {"coordinates":[-80.87102899999999,35.464492],"type":"Point"}
}