{
  "type": "Feature",
  "properties": {
    "addr:full":"8615 Nations Ford Rd Charlotte NC 28217",
    "addr:housenumber":"8615",
    "addr:postcode":"28217",
    "addr:street":"Nations Ford Rd",
    "iso:country":"US",
    "sg:address":"8615 Nations Ford Rd",
    "sg:city":"Charlotte",
    "sg:classifiers":[
        {
            "category":"Wholesale",
            "subcategory":"Jewelry",
            "type":"Manufacturing & Wholesale Goods"
        }
    ],
    "sg:phone":"+1 704 527 0263",
    "sg:postcode":"28217",
    "sg:province":"NC",
    "sg:tags":[
        "american",
        "african"
    ],
    "wof:name":"Kumasi Afrique",
    "wof:placetype":"venue"
},
  "geometry": {"coordinates":[-80.893855,35.139881],"type":"Point"}
}