{
  "type": "Feature",
  "properties": {
    "iso:country":"US",
    "sg:address":"5117 Boone Village Trl",
    "sg:city":"Cedar Grove",
    "sg:classifiers":[
        {
            "category":"Freight",
            "type":"Transportation"
        }
    ],
    "sg:phone":"+1 919 562 2426",
    "sg:postcode":"27231",
    "sg:province":"NC",
    "sg:tags":[
        "operator",
        "local",
        "trucking"
    ],
    "wof:name":"A1 Hauling",
    "wof:placetype":"venue"
},
  "geometry": {"coordinates":[-79.202679,36.205187],"type":"Point"}
}