{
  "type": "Feature",
  "properties": {
    "addr:full":"1690 Hardin Rd Lumberton NC 28358",
    "addr:housenumber":"1690",
    "addr:postcode":"28358",
    "addr:street":"Hardin Rd",
    "iso:country":"US",
    "sg:address":"1690 Hardin Rd",
    "sg:city":"Lumberton",
    "sg:classifiers":[
        {
            "category":"Organizations",
            "subcategory":"Religious Organization",
            "type":"Services"
        }
    ],
    "sg:phone":"+1 910 738 1556",
    "sg:postcode":"28358",
    "sg:province":"NC",
    "sg:tags":[
        "church"
    ],
    "wof:name":"Pentecostal Faith Of God",
    "wof:placetype":"venue"
},
  "geometry": {"coordinates":[-78.985387,34.62845],"type":"Point"}
}