{
  "type": "Feature",
  "properties": {
    "addr:full":"3522 Oleander Dr Wilmington NC 28403",
    "addr:housenumber":"3522",
    "addr:postcode":"28403",
    "addr:street":"Oleander Dr",
    "iso:country":"US",
    "sg:address":"3522 Oleander Dr",
    "sg:city":"Wilmington",
    "sg:classifiers":[
        {
            "category":"Cafe",
            "type":"Food & Drink"
        },
        {
            "category":"Restaurant",
            "type":"Food & Drink"
        }
    ],
    "sg:menulink":"http://www.allmenus.com/nc/wilmington/140817-bear-rock-cafe/menu/",
    "sg:phone":"+1 910 794 5551",
    "sg:postcode":"28403",
    "sg:province":"NC",
    "sg:tags":[
        "american"
    ],
    "wof:name":"Bear Rock Cafe",
    "wof:placetype":"venue"
},
  "geometry": {"coordinates":[-77.90462100000001,34.216143],"type":"Point"}
}