{
  "type": "Feature",
  "properties": {
    "iso:country":"US",
    "sg:address":"3424 Olive Chapel Rd",
    "sg:city":"Apex",
    "sg:classifiers":[
        {
            "category":"Education",
            "subcategory":"Library",
            "type":"Public Place"
        }
    ],
    "sg:phone":"+1   ",
    "sg:postcode":"27502",
    "sg:province":"NC",
    "wof:name":"Olive Branch Farm Inc",
    "wof:placetype":"venue"
},
  "geometry": {"coordinates":[-78.947307,35.731547],"type":"Point"}
}