{
  "type": "Feature",
  "properties": {
    "addr:full":"140 W Main Ave Taylorsville NC 28681",
    "addr:housenumber":"140",
    "addr:postcode":"28681",
    "addr:street":"W Main Ave",
    "iso:country":"US",
    "sg:address":"140 W Main Ave",
    "sg:city":"Taylorsville",
    "sg:classifiers":[
        {
            "category":"Autos & Motor Vehicles",
            "subcategory":"Auto Supplies",
            "type":"Retail Goods"
        }
    ],
    "sg:phone":"+1 828 635 6887",
    "sg:postcode":"28681",
    "sg:province":"NC",
    "sg:tags":[
        "automobile",
        "parts"
    ],
    "wof:name":"Autozone",
    "wof:placetype":"venue"
},
  "geometry": {"coordinates":[-81.17774300000001,35.922293],"type":"Point"}
}