{
  "type": "Feature",
  "properties": {
    "iso:country":"US",
    "sg:address":"2712 N Church St",
    "sg:city":"Greensboro",
    "sg:classifiers":[
        {
            "category":"Shopping",
            "subcategory":"Computers & Home Electronics",
            "type":"Retail Goods"
        }
    ],
    "sg:phone":"+1 336 621 2914",
    "sg:postcode":"27405",
    "sg:province":"NC",
    "wof:name":"Radio Shack",
    "wof:placetype":"venue"
},
  "geometry": {"coordinates":[-79.78114100000001,36.112379],"type":"Point"}
}