{
  "type": "Feature",
  "properties": {
    "addr:full":"1107 Wellington Ave Wilmington NC 28401",
    "addr:housenumber":"1107",
    "addr:postcode":"28401",
    "addr:street":"Wellington Ave",
    "iso:country":"US",
    "sg:address":"1107 Wellington Ave",
    "sg:city":"Wilmington",
    "sg:classifiers":[
        {
            "category":"Real Estate",
            "subcategory":"Real Estate Operator",
            "type":"Services"
        }
    ],
    "sg:phone":"+1 910 763 4878",
    "sg:postcode":"28401",
    "sg:province":"NC",
    "sg:tags":[
        "apartment"
    ],
    "wof:name":"Wellington Apartments",
    "wof:placetype":"venue"
},
  "geometry": {"coordinates":[-77.931363,34.195515],"type":"Point"}
}