{
  "type": "Feature",
  "properties": {
    "addr:full":"204 E Lawson Rd Hot Springs NC 28743",
    "addr:housenumber":"204",
    "addr:postcode":"28743",
    "addr:street":"E Lawson Rd",
    "iso:country":"US",
    "sg:address":"204 E Lawson Rd",
    "sg:city":"Hot Springs",
    "sg:classifiers":[
        {
            "category":"Travel",
            "subcategory":"Hotels & Motels",
            "type":"Entertainment"
        }
    ],
    "sg:phone":"+1 828 622 3543",
    "sg:postcode":"28743",
    "sg:province":"NC",
    "sg:tags":[
        "breakfast",
        "accommodation",
        "bed"
    ],
    "sg:website":"www.mountainmagnoliainn.com",
    "wof:name":"Mountain Magnolia Inn & Rtrt",
    "wof:placetype":"venue"
},
  "geometry": {"coordinates":[-82.862239,35.898585],"type":"Point"}
}