{
  "type": "Feature",
  "properties": {
    "iso:country":"US",
    "sg:address":"880 Piney Green Rd",
    "sg:city":"Jacksonville",
    "sg:classifiers":[
        {
            "category":"Organizations",
            "subcategory":"Religious Organization",
            "type":"Services"
        }
    ],
    "sg:phone":"+1 910 347 1157",
    "sg:postcode":"28546",
    "sg:province":"NC",
    "sg:tags":[
        "church"
    ],
    "wof:name":"Emmanuel Free Will Bapt Church",
    "wof:placetype":"venue"
},
  "geometry": {"coordinates":[-77.35450299999999,34.770462],"type":"Point"}
}