{
  "type": "Feature",
  "properties": {
    "iso:country":"US",
    "sg:address":"1701 Sparrow Dr",
    "sg:city":"Pleasant Garden",
    "sg:classifiers":[
        {
            "category":"Organizations",
            "subcategory":"Religious Organization",
            "type":"Services"
        }
    ],
    "sg:phone":"+1   ",
    "sg:postcode":"27313",
    "sg:province":"NC",
    "wof:name":"Pleasant Grove Church",
    "wof:placetype":"venue"
},
  "geometry": {"coordinates":[-79.756146,35.981505],"type":"Point"}
}