{
  "type": "Feature",
  "properties": {
    "iso:country":"US",
    "sg:address":"958 N Cannon Blvd",
    "sg:city":"Kannapolis",
    "sg:classifiers":[
        {
            "category":"Shopping",
            "subcategory":"Used Merchandise",
            "type":"Retail Goods"
        }
    ],
    "sg:phone":"+1 704 933 6427",
    "sg:postcode":"28083",
    "sg:province":"NC",
    "sg:tags":[
        "appliance"
    ],
    "wof:name":"Eathan's Used Appliance",
    "wof:placetype":"venue"
},
  "geometry": {"coordinates":[-80.608998,35.507908],"type":"Point"}
}