{
  "type": "Feature",
  "properties": {
    "iso:country":"US",
    "sg:address":"6118 Carmon Rd",
    "sg:city":"Gibsonville",
    "sg:classifiers":[
        {
            "category":"Building & Trades",
            "subcategory":"Landscaping Services",
            "type":"Services"
        }
    ],
    "sg:phone":"+1 336 697 9586",
    "sg:postcode":"27249",
    "sg:province":"NC",
    "wof:name":"Blades & Spades Lawn Care Inc",
    "wof:placetype":"venue"
},
  "geometry": {"coordinates":[-79.602727,36.111148],"type":"Point"}
}