{
  "type": "Feature",
  "properties": {
    "iso:country":"US",
    "sg:address":"3525 Robinwest Ct",
    "sg:city":"Pfafftown",
    "sg:classifiers":[
        {
            "category":"Building & Trades",
            "subcategory":"Landscaping Services",
            "type":"Services"
        }
    ],
    "sg:phone":"+1 336 946 0400",
    "sg:postcode":"27040",
    "sg:province":"NC",
    "wof:name":"Todd J Landscaping",
    "wof:placetype":"venue"
},
  "geometry": {"coordinates":[-80.417052,36.129261],"type":"Point"}
}