{
  "type": "Feature",
  "properties": {
    "addr:full":"2757 Grantham School Rd Mount Olive NC 28365",
    "addr:housenumber":"2757",
    "addr:postcode":"28365",
    "addr:street":"Grantham School Rd",
    "iso:country":"US",
    "sg:address":"2757 Grantham School Rd",
    "sg:city":"Mount Olive",
    "sg:classifiers":[
        {
            "category":"Building & Trades",
            "subcategory":"Construction",
            "type":"Services"
        }
    ],
    "sg:phone":"+1 919 658 0442",
    "sg:postcode":"28365",
    "sg:province":"NC",
    "sg:tags":[
        "house"
    ],
    "wof:name":"Eddies Home Improvement",
    "wof:placetype":"venue"
},
  "geometry": {"coordinates":[-78.158986,35.211249],"type":"Point"}
}