{
  "type": "Feature",
  "properties": {
    "addr:full":"1141 Mecklenburg Hwy Mooresville NC 28115",
    "addr:housenumber":"1141",
    "addr:postcode":"28115",
    "addr:street":"Mecklenburg Hwy",
    "iso:country":"US",
    "sg:address":"1141 Mecklenburg Hwy",
    "sg:city":"Mooresville",
    "sg:classifiers":[
        {
            "category":"Home & Garden",
            "subcategory":"Garden Supply",
            "type":"Retail Goods"
        }
    ],
    "sg:phone":"+1 704 664 5418",
    "sg:postcode":"28115",
    "sg:province":"NC",
    "sg:tags":[
        "equipment",
        "lawn",
        "supplies-wholesale",
        "manufacturer"
    ],
    "wof:name":"Ervin F J Construction & Supply",
    "wof:placetype":"venue"
},
  "geometry": {"coordinates":[-80.834384,35.559662],"type":"Point"}
}