{
  "type": "Feature",
  "properties": {
    "iso:country":"US",
    "sg:address":"2929 New Leicester Hwy",
    "sg:city":"Leicester",
    "sg:classifiers":[
        {
            "category":"Home & Garden",
            "subcategory":"Hardware",
            "type":"Retail Goods"
        }
    ],
    "sg:phone":"+1 828 683 2079",
    "sg:postcode":"28748",
    "sg:province":"NC",
    "wof:name":"Leicester Supply Co",
    "wof:placetype":"venue"
},
  "geometry": {"coordinates":[-82.71411999999999,35.655817],"type":"Point"}
}