{
  "type": "Feature",
  "properties": {
    "addr:full":"108 Speed St Elizabeth City NC 27909",
    "addr:housenumber":"108",
    "addr:postcode":"27909",
    "addr:street":"Speed St",
    "iso:country":"US",
    "sg:address":"108 Speed St",
    "sg:city":"Elizabeth City",
    "sg:classifiers":[
        {
            "category":"Organizations",
            "subcategory":"Professional Association",
            "type":"Services"
        }
    ],
    "sg:phone":"+1   ",
    "sg:postcode":"27909",
    "sg:province":"NC",
    "sg:tags":[
        "business"
    ],
    "wof:name":"National Assoc University Wome",
    "wof:placetype":"venue"
},
  "geometry": {"coordinates":[-76.22344200000001,36.295338],"type":"Point"}
}