{
  "type": "Feature",
  "properties": {
    "addr:full":"310 Tern Ct Kill Devil Hills NC 27948",
    "addr:housenumber":"310",
    "addr:postcode":"27948",
    "addr:street":"Tern Ct",
    "iso:country":"US",
    "sg:address":"310 Tern Ct",
    "sg:city":"Kill Devil Hills",
    "sg:classifiers":[
        {
            "category":"Retail",
            "subcategory":"Portrait Studio",
            "type":"Services"
        }
    ],
    "sg:phone":"+1   ",
    "sg:postcode":"27948",
    "sg:province":"NC",
    "sg:tags":[
        "photo",
        "photography",
        "commercial"
    ],
    "wof:name":"Ralph Rippe Photography",
    "wof:placetype":"venue"
},
  "geometry": {"coordinates":[-75.67426,36.028658],"type":"Point"}
}