{
  "type": "Feature",
  "properties": {
    "addr:full":"312 N Front St Warsaw NC 28398",
    "addr:housenumber":"312",
    "addr:postcode":"28398",
    "addr:street":"N Front St",
    "iso:country":"US",
    "sg:address":"312 N Front St",
    "sg:city":"Warsaw",
    "sg:classifiers":[
        {
            "category":"Home & Garden",
            "subcategory":"Household Appliances",
            "type":"Retail Goods"
        }
    ],
    "sg:phone":"+1 910 293 3134",
    "sg:postcode":"28398",
    "sg:province":"NC",
    "wof:name":"Page Audio-Video-Appliances",
    "wof:placetype":"venue"
},
  "geometry": {"coordinates":[-78.094177,35.000924],"type":"Point"}
}