{
  "type": "Feature",
  "properties": {
    "iso:country":"US",
    "sg:address":"1099 Griers Church Rd",
    "sg:city":"Leasburg",
    "sg:classifiers":[
        {
            "category":"Freight",
            "type":"Transportation"
        }
    ],
    "sg:phone":"+1 336 694 9283",
    "sg:postcode":"27291",
    "sg:province":"NC",
    "sg:tags":[
        "help",
        "supply",
        "mfg",
        "trucking",
        "operator",
        "local"
    ],
    "wof:name":"Sievert Transport",
    "wof:placetype":"venue"
},
  "geometry": {"coordinates":[-79.20603699999999,36.350392],"type":"Point"}
}