{
  "type": "Feature",
  "properties": {
    "iso:country":"US",
    "sg:address":"7342 Funston Rd SE",
    "sg:city":"Winnabow",
    "sg:classifiers":[
        {
            "category":"Organizations",
            "subcategory":"Religious Organization",
            "type":"Services"
        }
    ],
    "sg:phone":"+1 910 253 4077",
    "sg:postcode":"28479",
    "sg:province":"NC",
    "sg:tags":[
        "church"
    ],
    "wof:name":"Lebanon Baptist Church",
    "wof:placetype":"venue"
},
  "geometry": {"coordinates":[-78.036477,34.108304],"type":"Point"}
}