{
  "type": "Feature",
  "properties": {
    "iso:country":"US",
    "sg:address":"155 S Eastway Dr",
    "sg:city":"Troutman",
    "sg:classifiers":[
        {
            "category":"Commercial Area",
            "type":"Public Place"
        }
    ],
    "sg:phone":"+1 704 528 0589",
    "sg:postcode":"28166",
    "sg:province":"NC",
    "sg:tags":[
        "front",
        "store"
    ],
    "wof:name":"A1 Glass And Aluminum",
    "wof:placetype":"venue"
},
  "geometry": {"coordinates":[-80.887602,35.701501],"type":"Point"}
}