{
  "type": "Feature",
  "properties": {
    "iso:country":"US",
    "sg:address":"416 S Highway 27",
    "sg:city":"Stanley",
    "sg:classifiers":[
        {
            "category":"Banks & Credit Unions",
            "subcategory":"Bank",
            "type":"Services"
        },
        {
            "category":"Banks & Credit Unions",
            "subcategory":"Financial Services",
            "type":"Services"
        }
    ],
    "sg:phone":"+1 704 263 5096",
    "sg:postcode":"28164",
    "sg:province":"NC",
    "sg:tags":[
        "financing",
        "loan"
    ],
    "sg:website":"http://www.SunTrust.com",
    "wof:name":"SunTrust Bank - Stanley",
    "wof:placetype":"venue"
},
  "geometry": {"coordinates":[-81.090947,35.354421],"type":"Point"}
}