{
  "type": "Feature",
  "properties": {
    "iso:country":"US",
    "sg:address":"4023 Brookshire Blvd",
    "sg:city":"Charlotte",
    "sg:classifiers":[
        {
            "category":"Restaurant",
            "type":"Food & Drink"
        }
    ],
    "sg:phone":"+1 704 394 9633",
    "sg:postcode":"28216",
    "sg:province":"NC",
    "sg:tags":[
        "eating"
    ],
    "wof:name":"Fonda LA Penita",
    "wof:placetype":"venue"
},
  "geometry": {"coordinates":[-80.881055,35.26443],"type":"Point"}
}