{
  "type": "Feature",
  "properties": {
    "addr:full":"3400 Wendell Blvd Wendell NC 27591",
    "addr:housenumber":"3400",
    "addr:postcode":"27591",
    "addr:street":"Wendell Blvd",
    "iso:country":"US",
    "sg:address":"3400 Wendell Blvd",
    "sg:city":"Wendell",
    "sg:classifiers":[
        {
            "category":"Retail",
            "subcategory":"Auto Repair",
            "type":"Services"
        }
    ],
    "sg:phone":"+1 919 365 6484",
    "sg:postcode":"27591",
    "sg:province":"NC",
    "sg:tags":[
        "wrecker"
    ],
    "wof:name":"Fleet Fuels Inc",
    "wof:placetype":"venue"
},
  "geometry": {"coordinates":[-78.372063,35.784621],"type":"Point"}
}