{
  "type": "Feature",
  "properties": {
    "addr:full":"205 11th St SE Conover NC 28613",
    "addr:housenumber":"205",
    "addr:postcode":"28613",
    "addr:street":"11Th St Se",
    "iso:country":"US",
    "sg:address":"205 11th St SE",
    "sg:city":"Conover",
    "sg:classifiers":[
        {
            "category":"Building & Trades",
            "subcategory":"Landscaping Services",
            "type":"Services"
        }
    ],
    "sg:phone":"+1 828 464 5306",
    "sg:postcode":"28613",
    "sg:province":"NC",
    "sg:tags":[
        "landscape",
        "contractor"
    ],
    "sg:website":"www.ingleandson.com",
    "wof:name":"Ingle & Son Landscaping",
    "wof:placetype":"venue"
},
  "geometry": {"coordinates":[-81.218518,35.696776],"type":"Point"}
}