{
  "type": "Feature",
  "properties": {
    "addr:full":"239 Susan Dr Garner NC 27529",
    "addr:housenumber":"239",
    "addr:postcode":"27529",
    "addr:street":"Susan Dr",
    "iso:country":"US",
    "sg:address":"239 Susan Dr",
    "sg:city":"Garner",
    "sg:classifiers":[
        {
            "category":"Building & Trades",
            "subcategory":"Construction",
            "type":"Services"
        }
    ],
    "sg:phone":"+1 919 773 9341",
    "sg:postcode":"27529",
    "sg:province":"NC",
    "sg:tags":[
        "hanging",
        "contractor"
    ],
    "wof:name":"Morans Painting Wallpaper",
    "wof:placetype":"venue"
},
  "geometry": {"coordinates":[-78.600725,35.568513],"type":"Point"}
}