{
  "type": "Feature",
  "properties": {
    "addr:full":"1241 Dabney Dr Henderson NC 27536",
    "addr:housenumber":"1241",
    "addr:postcode":"27536",
    "addr:street":"Dabney Dr",
    "iso:country":"US",
    "sg:address":"1241 Dabney Dr",
    "sg:city":"Henderson",
    "sg:classifiers":[
        {
            "category":"Food & Beverages",
            "subcategory":"Groceries & Convenience Stores",
            "type":"Retail Goods"
        }
    ],
    "sg:phone":"+1 252 430 8812",
    "sg:postcode":"27536",
    "sg:province":"NC",
    "sg:tags":[
        "grocer"
    ],
    "sg:website":"www.foodlion.com",
    "wof:name":"Food Lion",
    "wof:placetype":"venue"
},
  "geometry": {"coordinates":[-78.43104,36.330435],"type":"Point"}
}