{
  "type": "Feature",
  "properties": {
    "iso:country":"US",
    "sg:address":"5678 Georgia Rd",
    "sg:city":"Franklin",
    "sg:classifiers":[
        {
            "category":"Retail",
            "subcategory":"Auto Repair",
            "type":"Services"
        }
    ],
    "sg:phone":"+1 828 524 4885",
    "sg:postcode":"28734",
    "sg:province":"NC",
    "sg:tags":[
        "repairing",
        "automobile",
        "general"
    ],
    "wof:name":"Shirley's Quality Auto Care",
    "wof:placetype":"venue"
},
  "geometry": {"coordinates":[-83.386251,35.010706],"type":"Point"}
}