{
  "type": "Feature",
  "properties": {
    "iso:country":"US",
    "sg:address":"1323 Catawba St",
    "sg:city":"Belmont",
    "sg:classifiers":[
        {
            "category":"Government",
            "subcategory":"Office",
            "type":"Public Place"
        }
    ],
    "sg:phone":"+1 704 829 0923",
    "sg:postcode":"28012",
    "sg:province":"NC",
    "sg:tags":[
        "executive"
    ],
    "wof:name":"City of Belmont Dixie 15",
    "wof:placetype":"venue"
},
  "geometry": {"coordinates":[-81.01544800000001,35.242148],"type":"Point"}
}