{
  "type": "Feature",
  "properties": {
    "addr:full":"300 New Home St Winston Salem NC 27104",
    "addr:housenumber":"300",
    "addr:postcode":"27104",
    "addr:street":"New Home St",
    "iso:country":"US",
    "sg:address":"300 New Home St",
    "sg:city":"Winston Salem",
    "sg:classifiers":[
        {
            "category":"Shopping",
            "subcategory":"Florist",
            "type":"Retail Goods"
        }
    ],
    "sg:phone":"+1 336 765 3101",
    "sg:postcode":"27104",
    "sg:province":"NC",
    "wof:name":"Company S Coming Florist",
    "wof:placetype":"venue"
},
  "geometry": {"coordinates":[-80.316457,36.082957],"type":"Point"}
}