{
  "type": "Feature",
  "properties": {
    "addr:full":"4103 US Hwy 74 Monroe NC 28110",
    "addr:housenumber":"4103",
    "addr:postcode":"28110",
    "addr:street":"Us Hwy 74",
    "iso:country":"US",
    "sg:address":"4103 US Hwy 74",
    "sg:city":"Monroe",
    "sg:classifiers":[
        {
            "category":"Banks & Credit Unions",
            "subcategory":"Bank",
            "type":"Services"
        }
    ],
    "sg:phone":"+1 704 238 0679",
    "sg:postcode":"28110",
    "sg:province":"NC",
    "sg:tags":[
        "machine",
        "teller",
        "automated"
    ],
    "wof:name":"USA Atm",
    "wof:placetype":"venue"
},
  "geometry": {"coordinates":[-80.605548,35.04043],"type":"Point"}
}