{
  "type": "Feature",
  "properties": {
    "addr:full":"886 Jackson Store Rd Beulaville NC 28518",
    "addr:housenumber":"886",
    "addr:postcode":"28518",
    "addr:street":"Jackson Store Rd",
    "iso:country":"US",
    "sg:address":"886 Jackson Store Rd",
    "sg:city":"Beulaville",
    "sg:classifiers":[
        {
            "category":"Shopping",
            "type":"Retail Goods"
        }
    ],
    "sg:phone":"+1 910 298 4989",
    "sg:postcode":"28518",
    "sg:province":"NC",
    "sg:tags":[
        "cosmetic",
        "perfume"
    ],
    "wof:name":"Beauti Control Cosmetics Inc",
    "wof:placetype":"venue"
},
  "geometry": {"coordinates":[-77.78470799999999,34.886931],"type":"Point"}
}