{
  "type": "Feature",
  "properties": {
    "iso:country":"US",
    "sg:address":"225 Airport Rd",
    "sg:city":"Arden",
    "sg:classifiers":[
        {
            "category":"Autos & Motor Vehicles",
            "subcategory":"Automobile Sales",
            "type":"Retail Goods"
        }
    ],
    "sg:phone":"+1 828 651 0051",
    "sg:postcode":"28704",
    "sg:province":"NC",
    "sg:tags":[
        "used"
    ],
    "wof:name":"B & S Auto Sales",
    "wof:placetype":"venue"
},
  "geometry": {"coordinates":[-82.524165,35.452033],"type":"Point"}
}