{
  "type": "Feature",
  "properties": {
    "addr:full":"30 12th Ave Kitty Hawk NC 27949",
    "addr:housenumber":"30",
    "addr:postcode":"27949",
    "addr:street":"12Th Ave",
    "iso:country":"US",
    "sg:address":"30 12th Ave",
    "sg:city":"Kitty Hawk",
    "sg:classifiers":[
        {
            "category":"Insurance",
            "subcategory":"Insurance Agent",
            "type":"Services"
        }
    ],
    "sg:phone":"+1 252 255 2484",
    "sg:postcode":"27949",
    "sg:province":"NC",
    "wof:name":"One On One Concepts Inc",
    "wof:placetype":"venue"
},
  "geometry": {"coordinates":[-75.74339500000001,36.148849],"type":"Point"}
}