{
  "type": "Feature",
  "properties": {
    "iso:country":"US",
    "sg:address":"2719 Rothgeb Dr",
    "sg:city":"Raleigh",
    "sg:classifiers":[
        {
            "category":"Professional",
            "subcategory":"Management & Consulting",
            "type":"Services"
        }
    ],
    "sg:phone":"+1   ",
    "sg:postcode":"27609",
    "sg:province":"NC",
    "wof:name":"Prg Consulting Services Inc",
    "wof:placetype":"venue"
},
  "geometry": {"coordinates":[-78.641783,35.821273],"type":"Point"}
}