{
  "type": "Feature",
  "properties": {
    "addr:full":"148 N Bridge St Jonesville NC 28642",
    "addr:housenumber":"148",
    "addr:postcode":"28642",
    "addr:street":"N Bridge St",
    "iso:country":"US",
    "sg:address":"148 N Bridge St",
    "sg:city":"Jonesville",
    "sg:classifiers":[
        {
            "category":"Personal",
            "subcategory":"Beauty Salon",
            "type":"Services"
        }
    ],
    "sg:phone":"+1 336 835 2525",
    "sg:postcode":"28642",
    "sg:province":"NC",
    "wof:name":"Hair'm",
    "wof:placetype":"venue"
},
  "geometry": {"coordinates":[-80.846468,36.24097],"type":"Point"}
}