{
  "type": "Feature",
  "properties": {
    "addr:full":"1187 Shields Rd Kernersville NC 27284",
    "addr:housenumber":"1187",
    "addr:postcode":"27284",
    "addr:street":"Shields Rd",
    "iso:country":"US",
    "sg:address":"1187 Shields Rd",
    "sg:city":"Kernersville",
    "sg:classifiers":[
        {
            "category":"Bakery",
            "type":"Food & Drink"
        }
    ],
    "sg:menulink":"http://www.allmenus.com/nc/abbotts-creek/121262-krispy-kreme/menu/",
    "sg:phone":"+1 336 993 1844",
    "sg:postcode":"27284",
    "sg:province":"NC",
    "sg:tags":[
        "american",
        "pastry"
    ],
    "wof:name":"Krispy Kreme",
    "wof:placetype":"venue"
},
  "geometry": {"coordinates":[-80.074471,36.097335],"type":"Point"}
}