{
  "type": "Feature",
  "properties": {
    "iso:country":"US",
    "sg:address":"20 Beach Rd S",
    "sg:city":"Wilmington",
    "sg:classifiers":[
        {
            "category":"Real Estate",
            "subcategory":"Real Estate Operator",
            "type":"Services"
        }
    ],
    "sg:phone":"+1 910 681 0281",
    "sg:postcode":"28411",
    "sg:province":"NC",
    "sg:tags":[
        "building",
        "nonresidential"
    ],
    "wof:name":"Ekt Properties LLC",
    "wof:placetype":"venue"
},
  "geometry": {"coordinates":[-77.746664,34.266747],"type":"Point"}
}