{
  "type": "Feature",
  "properties": {
    "addr:full":"2417 Asheville Hwy Hendersonville NC 28791",
    "addr:housenumber":"2417",
    "addr:postcode":"28791",
    "addr:street":"Asheville Hwy",
    "iso:country":"US",
    "sg:address":"2417 Asheville Hwy",
    "sg:city":"Hendersonville",
    "sg:classifiers":[
        {
            "category":"Retail",
            "subcategory":"Auto Rental",
            "type":"Services"
        }
    ],
    "sg:phone":"+1 828 697 8551",
    "sg:postcode":"28791",
    "sg:province":"NC",
    "sg:tags":[
        "passenger",
        "car"
    ],
    "wof:name":"Enterprise Lsg Cmpny-Southeast",
    "wof:placetype":"venue"
},
  "geometry": {"coordinates":[-82.474024,35.347074],"type":"Point"}
}