{
  "type": "Feature",
  "properties": {
    "addr:full":"968 NC-210 Sneads Ferry NC 28460",
    "addr:housenumber":"968",
    "addr:postcode":"28460",
    "addr:street":"Nc-210",
    "iso:country":"US",
    "sg:address":"968 NC-210",
    "sg:city":"Sneads Ferry",
    "sg:classifiers":[
        {
            "category":"Restaurant",
            "type":"Food & Drink"
        }
    ],
    "sg:menulink":"http://www.allmenus.com/nc/stump-sound/154632-hardees/menu/",
    "sg:phone":"+1 910 327 2535",
    "sg:postcode":"28460",
    "sg:province":"NC",
    "sg:tags":[
        "burger",
        "american"
    ],
    "wof:name":"Hardee's",
    "wof:placetype":"venue"
},
  "geometry": {"coordinates":[-77.432469,34.5442],"type":"Point"}
}