{
  "type": "Feature",
  "properties": {
    "iso:country":"US",
    "sg:address":"1010 Lakeview Dr",
    "sg:city":"Pineville",
    "sg:classifiers":[
        {
            "category":"Shopping",
            "subcategory":"Pharmacy",
            "type":"Retail Goods"
        }
    ],
    "sg:phone":"+1 704 889 5434",
    "sg:postcode":"28134",
    "sg:province":"NC",
    "wof:name":"Care Pharmacy",
    "wof:placetype":"venue"
},
  "geometry": {"coordinates":[-80.896722,35.079011],"type":"Point"}
}