{
  "type": "Feature",
  "properties": {
    "addr:full":"221 Ivy Run Ct Statesville NC 28625",
    "addr:housenumber":"221",
    "addr:postcode":"28625",
    "addr:street":"Ivy Run Ct",
    "iso:country":"US",
    "sg:address":"221 Ivy Run Ct",
    "sg:city":"Statesville",
    "sg:classifiers":[
        {
            "category":"Organizations",
            "subcategory":"Religious Organization",
            "type":"Services"
        }
    ],
    "sg:phone":"+1   ",
    "sg:postcode":"28625",
    "sg:province":"NC",
    "wof:name":"Statesville Korean Arp Church",
    "wof:placetype":"venue"
},
  "geometry": {"coordinates":[-80.84849,35.788861],"type":"Point"}
}