{
  "type": "Feature",
  "properties": {
    "addr:full":"151 Golfview Dr Advance NC 27006",
    "addr:housenumber":"151",
    "addr:postcode":"27006",
    "addr:street":"Golfview Dr",
    "iso:country":"US",
    "sg:address":"151 Golfview Dr",
    "sg:city":"Advance",
    "sg:classifiers":[
        {
            "category":"Wholesale",
            "subcategory":"Home Furnishings",
            "type":"Manufacturing & Wholesale Goods"
        }
    ],
    "sg:phone":"+1 336 998 8800",
    "sg:postcode":"27006",
    "sg:province":"NC",
    "wof:name":"Bermuda Run Mailing Address",
    "wof:placetype":"venue"
},
  "geometry": {"coordinates":[-80.423693,36.001982],"type":"Point"}
}