{
  "type": "Feature",
  "properties": {
    "addr:full":"4106 US Hwy 29 Greensboro NC 27405",
    "addr:housenumber":"4106",
    "addr:postcode":"27405",
    "addr:street":"Us Hwy 29",
    "iso:country":"US",
    "sg:address":"4106 US Hwy 29",
    "sg:city":"Greensboro",
    "sg:classifiers":[
        {
            "category":"Freight",
            "type":"Transportation"
        }
    ],
    "sg:phone":"+1 336 954 1515",
    "sg:postcode":"27405",
    "sg:province":"NC",
    "sg:tags":[
        "commercial",
        "storage"
    ],
    "wof:name":"Glade Self Storage",
    "wof:placetype":"venue"
},
  "geometry": {"coordinates":[-79.732598,36.146873],"type":"Point"}
}