{
  "type": "Feature",
  "properties": {
    "iso:country":"US",
    "sg:address":"1008 Oxford Ridge Dr",
    "sg:city":"Wake Forest",
    "sg:classifiers":[
        {
            "category":"Shopping",
            "subcategory":"Computers & Home Electronics",
            "type":"Retail Goods"
        }
    ],
    "sg:phone":"+1 919 554 0388",
    "sg:postcode":"27587",
    "sg:province":"NC",
    "sg:tags":[
        "software"
    ],
    "wof:name":"Polytheoretics Inc",
    "wof:placetype":"venue"
},
  "geometry": {"coordinates":[-78.55341900000001,36.058275],"type":"Point"}
}