{
  "type": "Feature",
  "properties": {
    "addr:full":"4808 Atlantic Ave Raleigh NC 27616",
    "addr:housenumber":"4808",
    "addr:postcode":"27616",
    "addr:street":"Atlantic Ave",
    "iso:country":"US",
    "sg:address":"4808 Atlantic Ave",
    "sg:city":"Raleigh",
    "sg:classifiers":[
        {
            "category":"Retail",
            "subcategory":"Auto Repair",
            "type":"Services"
        }
    ],
    "sg:phone":"+1   ",
    "sg:postcode":"27616",
    "sg:province":"NC",
    "sg:tags":[
        "automotive"
    ],
    "wof:name":"Precision Tune Auto Care",
    "wof:placetype":"venue"
},
  "geometry": {"coordinates":[-78.60093500000001,35.850629],"type":"Point"}
}