{
  "type": "Feature",
  "properties": {
    "iso:country":"US",
    "sg:address":"8810 Reed Mine Rd",
    "sg:city":"Midland",
    "sg:classifiers":[
        {
            "category":"Organizations",
            "subcategory":"Religious Organization",
            "type":"Services"
        }
    ],
    "sg:phone":"+1 704 888 3090",
    "sg:postcode":"28107",
    "sg:province":"NC",
    "sg:tags":[
        "church"
    ],
    "wof:name":"Pine Bluff United Methodist",
    "wof:placetype":"venue"
},
  "geometry": {"coordinates":[-80.46294399999999,35.295974],"type":"Point"}
}