{
  "type": "Feature",
  "properties": {
    "addr:full":"1126 Gettys Rd Ellenboro NC 28040",
    "addr:housenumber":"1126",
    "addr:postcode":"28040",
    "addr:street":"Gettys Rd",
    "iso:country":"US",
    "sg:address":"1126 Gettys Rd",
    "sg:city":"Ellenboro",
    "sg:classifiers":[
        {
            "category":"Farming",
            "subcategory":"Farm & Veterinary Services",
            "type":"Manufacturing & Wholesale Goods"
        }
    ],
    "sg:phone":"+1 828 453 7485",
    "sg:postcode":"28040",
    "sg:province":"NC",
    "sg:tags":[
        "livestock"
    ],
    "wof:name":"Gettys",
    "wof:placetype":"venue"
},
  "geometry": {"coordinates":[-81.759998,35.4322],"type":"Point"}
}