{
  "type": "Feature",
  "properties": {
    "addr:full":"12445 Grey Commercial Dr Midland NC 28107",
    "addr:housenumber":"12445",
    "addr:postcode":"28107",
    "addr:street":"Grey Commercial Dr",
    "iso:country":"US",
    "sg:address":"12445 Grey Commercial Dr",
    "sg:city":"Midland",
    "sg:classifiers":[
        {
            "category":"Wholesale",
            "subcategory":"Construction Materials",
            "type":"Manufacturing & Wholesale Goods"
        },
        {
            "category":"Manufacturing",
            "subcategory":"Glass & Minerals",
            "type":"Manufacturing & Wholesale Goods"
        }
    ],
    "sg:phone":"+1 704 888 3470",
    "sg:postcode":"28107",
    "sg:province":"NC",
    "sg:tags":[
        "mfr",
        "marble"
    ],
    "wof:name":"Tarheel Marble Inc",
    "wof:placetype":"venue"
},
  "geometry": {"coordinates":[-80.587034,35.245984],"type":"Point"}
}