{
  "type": "Feature",
  "properties": {
    "addr:full":"220 Davidson County Landfill Rd Lexington NC 27292",
    "addr:housenumber":"220",
    "addr:postcode":"27292",
    "addr:street":"Landfill Rd",
    "iso:country":"US",
    "sg:address":"220 Davidson County Landfill Rd",
    "sg:city":"Lexington",
    "sg:classifiers":[
        {
            "category":"Government",
            "subcategory":"Office",
            "type":"Public Place"
        }
    ],
    "sg:phone":"+1 336 242 2284",
    "sg:postcode":"27292",
    "sg:province":"NC",
    "wof:name":"Davidson Integrated Solid Wst",
    "wof:placetype":"venue"
},
  "geometry": {"coordinates":[-80.174977,35.833789],"type":"Point"}
}