{
  "type": "Feature",
  "properties": {
    "addr:full":"6109 US Hwy 70 E La Grange NC 28551",
    "addr:housenumber":"6109",
    "addr:postcode":"28551",
    "addr:street":"Us Hwy 70 E",
    "iso:country":"US",
    "sg:address":"6109 US Hwy 70 E",
    "sg:city":"La Grange",
    "sg:classifiers":[
        {
            "category":"Building & Trades",
            "subcategory":"Plumbing",
            "type":"Services"
        }
    ],
    "sg:phone":"+1 252 566 8880",
    "sg:postcode":"28551",
    "sg:province":"NC",
    "sg:tags":[
        "plumbing",
        "contractor"
    ],
    "wof:name":"Atlantic Plumbing",
    "wof:placetype":"venue"
},
  "geometry": {"coordinates":[-77.851204,35.317592],"type":"Point"}
}