{
  "type": "Feature",
  "properties": {
    "addr:full":"5036 Wrightsville Ave Wilmington NC 28403",
    "addr:housenumber":"5036",
    "addr:postcode":"28403",
    "addr:street":"Wrightsville Ave",
    "iso:country":"US",
    "sg:address":"5036 Wrightsville Ave",
    "sg:city":"Wilmington",
    "sg:classifiers":[
        {
            "category":"Education",
            "subcategory":"College",
            "type":"Public Place"
        }
    ],
    "sg:phone":"+1 910 791 6430",
    "sg:postcode":"28403",
    "sg:province":"NC",
    "sg:tags":[
        "academic",
        "school"
    ],
    "wof:name":"1209 S College Rd",
    "wof:placetype":"venue"
},
  "geometry": {"coordinates":[-77.871453,34.212607],"type":"Point"}
}