{
  "type": "Feature",
  "properties": {
    "addr:full":"1460 US Hwy 15/501 Southern Pines NC 28387",
    "addr:housenumber":"1460;501",
    "addr:postcode":"28387",
    "addr:street":"Us Hwy 15 /",
    "iso:country":"US",
    "sg:address":"1460 US Hwy 15/501",
    "sg:city":"Southern Pines",
    "sg:classifiers":[
        {
            "category":"Retail",
            "subcategory":"Portrait Studio",
            "type":"Services"
        }
    ],
    "sg:phone":"+1 910 695 7806",
    "sg:postcode":"28387",
    "sg:province":"NC",
    "wof:name":"Olan Mills Inc",
    "wof:placetype":"venue"
},
  "geometry": {"coordinates":[-79.43583599999999,35.181185],"type":"Point"}
}