{
  "type": "Feature",
  "properties": {
    "addr:full":"3953 US Hwy 70 E Smithfield NC 27577",
    "addr:housenumber":"3953",
    "addr:postcode":"27577",
    "addr:street":"Us Hwy 70 E",
    "iso:country":"US",
    "sg:address":"3953 US Hwy 70 E",
    "sg:city":"Smithfield",
    "sg:classifiers":[
        {
            "category":"Bars & Pubs",
            "type":"Food & Drink"
        }
    ],
    "sg:phone":"+1 919 989 8235",
    "sg:postcode":"27577",
    "sg:province":"NC",
    "sg:tags":[
        "drinking"
    ],
    "wof:name":"Lei & Lee Inc",
    "wof:placetype":"venue"
},
  "geometry": {"coordinates":[-78.24348500000001,35.48301],"type":"Point"}
}