{
  "type": "Feature",
  "properties": {
    "iso:country":"US",
    "sg:address":"125 Herring St",
    "sg:city":"Mount Airy",
    "sg:classifiers":[
        {
            "category":"Building & Trades",
            "subcategory":"Construction",
            "type":"Services"
        }
    ],
    "sg:phone":"+1 336 719 2762",
    "sg:postcode":"27030",
    "sg:province":"NC",
    "sg:tags":[
        "hanging",
        "contractor"
    ],
    "wof:name":"Travis Flippen Painting Contg",
    "wof:placetype":"venue"
},
  "geometry": {"coordinates":[-80.63873,36.497919],"type":"Point"}
}