{
  "type": "Feature",
  "properties": {
    "addr:full":"162 Waccamaw Rd Carthage NC 28327",
    "addr:housenumber":"162",
    "addr:postcode":"28327",
    "addr:street":"Waccamaw Rd",
    "iso:country":"US",
    "sg:address":"162 Waccamaw Rd",
    "sg:city":"Carthage",
    "sg:classifiers":[
        {
            "category":"Professional",
            "subcategory":"Engineering",
            "type":"Services"
        }
    ],
    "sg:phone":"+1   ",
    "sg:postcode":"28327",
    "sg:province":"NC",
    "wof:name":"Robinson Engineering",
    "wof:placetype":"venue"
},
  "geometry": {"coordinates":[-79.38672,35.220209],"type":"Point"}
}