{
  "type": "Feature",
  "properties": {
    "addr:full":"7303 Stony Hill Rd Wake Forest NC 27587",
    "addr:housenumber":"7303",
    "addr:postcode":"27587",
    "addr:street":"Stony Hill Rd",
    "iso:country":"US",
    "sg:address":"7303 Stony Hill Rd",
    "sg:city":"Wake Forest",
    "sg:classifiers":[
        {
            "category":"Building & Trades",
            "subcategory":"Electrical",
            "type":"Services"
        }
    ],
    "sg:phone":"+1 919 556 5117",
    "sg:postcode":"27587",
    "sg:province":"NC",
    "sg:tags":[
        "electrical",
        "contractor"
    ],
    "wof:name":"C Tron Electric Eqpt",
    "wof:placetype":"venue"
},
  "geometry": {"coordinates":[-78.60724999999999,35.993894],"type":"Point"}
}