{
  "type": "Feature",
  "properties": {
    "addr:full":"326 Albemarle Rd Troy NC 27371",
    "addr:housenumber":"326",
    "addr:postcode":"27371",
    "addr:street":"Albemarle Rd",
    "iso:country":"US",
    "sg:address":"326 Albemarle Rd",
    "sg:city":"Troy",
    "sg:classifiers":[
        {
            "category":"Health Services",
            "subcategory":"Optometrist",
            "type":"Services"
        }
    ],
    "sg:phone":"+1 910 576 7371",
    "sg:postcode":"27371",
    "sg:province":"NC",
    "wof:name":"Doctor's Vision Ctr",
    "wof:placetype":"venue"
},
  "geometry": {"coordinates":[-79.89956100000001,35.356384],"type":"Point"}
}