{
  "type": "Feature",
  "properties": {
    "iso:country":"US",
    "sg:address":"2062 Smith Holden Rd",
    "sg:city":"Franklinville",
    "sg:classifiers":[
        {
            "category":"Wholesale",
            "subcategory":"Electrical",
            "type":"Manufacturing & Wholesale Goods"
        }
    ],
    "sg:phone":"+1 336 498 1051",
    "sg:postcode":"27248",
    "sg:province":"NC",
    "sg:tags":[
        "electric",
        "motor"
    ],
    "wof:name":"Holden Motor Co",
    "wof:placetype":"venue"
},
  "geometry": {"coordinates":[-79.731263,35.831697],"type":"Point"}
}