{
  "type": "Feature",
  "properties": {
    "iso:country":"US",
    "sg:address":"2505 W Market St",
    "sg:city":"Greensboro",
    "sg:classifiers":[
        {
            "category":"Professional",
            "subcategory":"Management & Consulting",
            "type":"Services"
        }
    ],
    "sg:phone":"+1   ",
    "sg:postcode":"27403",
    "sg:province":"NC",
    "wof:name":"Carpenter Editha Fine Arts",
    "wof:placetype":"venue"
},
  "geometry": {"coordinates":[-79.826509,36.074167],"type":"Point"}
}