{
  "type": "Feature",
  "properties": {
    "addr:full":"5009 Archdale Rd Trinity NC 27370",
    "addr:housenumber":"5009",
    "addr:postcode":"27370",
    "addr:street":"Archdale Rd",
    "iso:country":"US",
    "sg:address":"5009 Archdale Rd",
    "sg:city":"Trinity",
    "sg:classifiers":[
        {
            "category":"Building & Trades",
            "subcategory":"Construction",
            "type":"Services"
        }
    ],
    "sg:phone":"+1 336 431 7307",
    "sg:postcode":"27370",
    "sg:province":"NC",
    "sg:tags":[
        "concrete",
        "contractor"
    ],
    "wof:name":"Rhoades Concrete",
    "wof:placetype":"venue"
},
  "geometry": {"coordinates":[-79.957926,35.885774],"type":"Point"}
}