{
  "type": "Feature",
  "properties": {
    "iso:country":"US",
    "sg:address":"455 Providence Rd S",
    "sg:city":"Waxhaw",
    "sg:classifiers":[
        {
            "category":"Banks & Credit Unions",
            "subcategory":"Financial Services",
            "type":"Services"
        }
    ],
    "sg:phone":"+1 704 846 1740",
    "sg:postcode":"28173",
    "sg:province":"NC",
    "sg:tags":[
        "trust",
        "nonprofit",
        "management"
    ],
    "wof:name":"Swimmer Family Foundation",
    "wof:placetype":"venue"
},
  "geometry": {"coordinates":[-80.76812700000001,35.003627],"type":"Point"}
}