{
  "type": "Feature",
  "properties": {
    "addr:full":"7301 Hurstbourne Green Dr Charlotte NC 28277",
    "addr:housenumber":"7301",
    "addr:postcode":"28277",
    "addr:street":"Hurstbourne Green Dr",
    "iso:country":"US",
    "sg:address":"7301 Hurstbourne Green Dr",
    "sg:city":"Charlotte",
    "sg:classifiers":[
        {
            "category":"Organizations",
            "subcategory":"Professional Association",
            "type":"Services"
        }
    ],
    "sg:phone":"+1 704 847 0431",
    "sg:postcode":"28277",
    "sg:province":"NC",
    "wof:name":"Greenhurst Home Owners Assoc",
    "wof:placetype":"venue"
},
  "geometry": {"coordinates":[-80.814206,35.066362],"type":"Point"}
}