{
  "type": "Feature",
  "properties": {
    "addr:full":"6692 Camden Rd Fayetteville NC 28306",
    "addr:housenumber":"6692",
    "addr:postcode":"28306",
    "addr:street":"Camden Rd",
    "iso:country":"US",
    "sg:address":"6692 Camden Rd",
    "sg:city":"Fayetteville",
    "sg:classifiers":[
        {
            "category":"Building & Trades",
            "subcategory":"Construction",
            "type":"Services"
        }
    ],
    "sg:phone":"+1 910 425 8393",
    "sg:postcode":"28306",
    "sg:province":"NC",
    "sg:tags":[
        "drywall",
        "contractor"
    ],
    "wof:name":"Baxley Drywall",
    "wof:placetype":"venue"
},
  "geometry": {"coordinates":[-78.993731,34.975679],"type":"Point"}
}