{
  "type": "Feature",
  "properties": {
    "addr:full":"2406 Kannapolis Hwy Concord NC 28027",
    "addr:postcode":"2406;28027",
    "addr:street":"Kannapolis Hwy",
    "iso:country":"US",
    "sg:address":"2406 Kannapolis Hwy",
    "sg:city":"Concord",
    "sg:classifiers":[
        {
            "category":"Personal",
            "type":"Services"
        }
    ],
    "sg:phone":"+1   ",
    "sg:postcode":"28027",
    "sg:province":"NC",
    "wof:name":"Hair Co The",
    "wof:placetype":"venue"
},
  "geometry": {"coordinates":[-80.61031699999999,35.441215],"type":"Point"}
}