{
  "type": "Feature",
  "properties": {
    "addr:full":"1909 Kyle Ct Gastonia NC 28052",
    "addr:housenumber":"1909",
    "addr:postcode":"28052",
    "addr:street":"Kyle Ct",
    "iso:country":"US",
    "sg:address":"1909 Kyle Ct",
    "sg:city":"Gastonia",
    "sg:classifiers":[
        {
            "category":"Autos & Motor Vehicles",
            "subcategory":"Auto Supplies",
            "type":"Retail Goods"
        }
    ],
    "sg:phone":"+1 704 810 0500",
    "sg:postcode":"28052",
    "sg:province":"NC",
    "wof:name":"Aksys Usa Inc",
    "wof:placetype":"venue"
},
  "geometry": {"coordinates":[-81.241108,35.27897],"type":"Point"}
}