{
  "type": "Feature",
  "properties": {
    "iso:country":"US",
    "sg:address":"6222 White Store Paglnd Rd",
    "sg:city":"Marshville",
    "sg:classifiers":[
        {
            "category":"Building & Trades",
            "subcategory":"Construction",
            "type":"Services"
        }
    ],
    "sg:phone":"+1 704 624 2535",
    "sg:postcode":"28103",
    "sg:province":"NC",
    "sg:tags":[
        "floor",
        "laying",
        "contractor"
    ],
    "wof:name":"Nsc Flooring Inc",
    "wof:placetype":"venue"
},
  "geometry": {"coordinates":[-80.330313,34.825922],"type":"Point"}
}