{
  "type": "Feature",
  "properties": {
    "addr:full":"735 NW Blvd Clinton NC 28328",
    "addr:housenumber":"735",
    "addr:postcode":"28328",
    "addr:street":"Nw Blvd",
    "iso:country":"US",
    "sg:address":"735 NW Blvd",
    "sg:city":"Clinton",
    "sg:classifiers":[
        {
            "category":"Retail",
            "subcategory":"Auto Repair",
            "type":"Services"
        }
    ],
    "sg:phone":"+1 910 592 4664",
    "sg:postcode":"28328",
    "sg:province":"NC",
    "sg:tags":[
        "repairing",
        "automobile",
        "general"
    ],
    "wof:name":"Romeros Body Shop",
    "wof:placetype":"venue"
},
  "geometry": {"coordinates":[-78.343571,35.013353],"type":"Point"}
}