{
  "type": "Feature",
  "properties": {
    "addr:full":"351 Bell Rd Pantego NC 27889",
    "addr:housenumber":"351",
    "addr:postcode":"27889",
    "addr:street":"Bell Rd",
    "iso:country":"US",
    "sg:address":"351 Bell Rd",
    "sg:city":"Pantego",
    "sg:classifiers":[
        {
            "category":"Farming",
            "subcategory":"Farm",
            "type":"Manufacturing & Wholesale Goods"
        }
    ],
    "sg:phone":"+1 252 935 5311",
    "sg:postcode":"27889",
    "sg:province":"NC",
    "wof:name":"Bell Farms Inc",
    "wof:placetype":"venue"
},
  "geometry": {"coordinates":[-76.610342,35.665925],"type":"Point"}
}