{
  "type": "Feature",
  "properties": {
    "iso:country":"US",
    "sg:address":"1017 E Morehead St Ste 200",
    "sg:city":"Charlotte",
    "sg:classifiers":[
        {
            "category":"Banks & Credit Unions",
            "subcategory":"Investment Brokerage",
            "type":"Services"
        },
        {
            "category":"Banks & Credit Unions",
            "subcategory":"Bank",
            "type":"Services"
        },
        {
            "category":"Banks & Credit Unions",
            "subcategory":"Financial Services",
            "type":"Services"
        }
    ],
    "sg:phone":"+1 704 333 9203",
    "sg:postcode":"28204",
    "sg:province":"NC",
    "sg:tags":[
        "retirement",
        "transfer",
        "broker",
        "agent",
        "planning",
        "plan",
        "annuity",
        "bond",
        "security",
        "stock",
        "insurance",
        "consultant"
    ],
    "sg:website":"http://www.smithbarney.com",
    "wof:name":"Morgan Stanley Smith Barney",
    "wof:placetype":"venue"
},
  "geometry": {"coordinates":[-80.84356099999999,35.212674],"type":"Point"}
}