{
  "type": "Feature",
  "properties": {
    "addr:full":"221 E Trade St Forest City NC 28043",
    "addr:housenumber":"221",
    "addr:postcode":"28043",
    "addr:street":"E Trade St",
    "iso:country":"US",
    "sg:address":"221 E Trade St",
    "sg:city":"Forest City",
    "sg:classifiers":[
        {
            "category":"Wholesale",
            "subcategory":"Non-durable Goods",
            "type":"Manufacturing & Wholesale Goods"
        }
    ],
    "sg:phone":"+1 828 245 5340",
    "sg:postcode":"28043",
    "sg:province":"NC",
    "sg:tags":[
        "general",
        "including",
        "merchandise",
        "furniture"
    ],
    "wof:name":"Broadway Salvage & Office Furn",
    "wof:placetype":"venue"
},
  "geometry": {"coordinates":[-81.85957000000001,35.334443],"type":"Point"}
}