{
  "type": "Feature",
  "properties": {
    "iso:country":"US",
    "sg:address":"207 Avery Ave",
    "sg:city":"Morganton",
    "sg:classifiers":[
        {
            "category":"Professional",
            "subcategory":"Lawyer & Legal Services",
            "type":"Services"
        }
    ],
    "sg:phone":"+1 828 438 4000",
    "sg:postcode":"28655",
    "sg:province":"NC",
    "sg:tags":[
        "attorney"
    ],
    "wof:name":"Cox Gage & Sasser",
    "wof:placetype":"venue"
},
  "geometry": {"coordinates":[-81.68721499999999,35.749846],"type":"Point"}
}