{
  "type": "Feature",
  "properties": {
    "iso:country":"US",
    "sg:address":"516 W Main St",
    "sg:city":"Beulaville",
    "sg:classifiers":[
        {
            "category":"Autos & Motor Vehicles",
            "subcategory":"Auto Supplies",
            "type":"Retail Goods"
        }
    ],
    "sg:phone":"+1 910 298 4246",
    "sg:postcode":"28518",
    "sg:province":"NC",
    "sg:tags":[
        "automobile",
        "parts"
    ],
    "wof:name":"Western Auto",
    "wof:placetype":"venue"
},
  "geometry": {"coordinates":[-77.778741,34.924764],"type":"Point"}
}