{
  "type": "Feature",
  "properties": {
    "addr:full":"621 Stroud Rd Trenton NC 28585",
    "addr:housenumber":"621",
    "addr:postcode":"28585",
    "addr:street":"Stroud Rd",
    "iso:country":"US",
    "sg:address":"621 Stroud Rd",
    "sg:city":"Trenton",
    "sg:classifiers":[
        {
            "category":"Farming",
            "subcategory":"Farm & Veterinary Services",
            "type":"Manufacturing & Wholesale Goods"
        }
    ],
    "sg:phone":"+1 252 448 1811",
    "sg:postcode":"28585",
    "sg:province":"NC",
    "sg:tags":[
        "breeder",
        "livestock"
    ],
    "wof:name":"Robert Gina Farms",
    "wof:placetype":"venue"
},
  "geometry": {"coordinates":[-77.43735599999999,35.058294],"type":"Point"}
}