{
  "type": "Feature",
  "properties": {
    "addr:full":"7200 Stonehenge Dr Raleigh NC 27615",
    "addr:housenumber":"7200",
    "addr:postcode":"27615",
    "addr:street":"Stonehenge Dr",
    "iso:country":"US",
    "sg:address":"7200 Stonehenge Dr",
    "sg:city":"Raleigh",
    "sg:classifiers":[
        {
            "category":"Health Services",
            "subcategory":"Health Practitioner",
            "type":"Services"
        }
    ],
    "sg:phone":"+1 919 676 2001",
    "sg:postcode":"27615",
    "sg:province":"NC",
    "sg:tags":[
        "therapist",
        "physical"
    ],
    "wof:name":"Dunn Physical Therapy",
    "wof:placetype":"venue"
},
  "geometry": {"coordinates":[-78.67943099999999,35.886212],"type":"Point"}
}