{
  "type": "Feature",
  "properties": {
    "addr:full":"70 Court Plz Asheville NC 28801",
    "addr:housenumber":"70",
    "addr:postcode":"28801",
    "addr:street":"Court Plz",
    "iso:country":"US",
    "sg:address":"70 Court Plz",
    "sg:city":"Asheville",
    "sg:classifiers":[
        {
            "category":"Government",
            "subcategory":"Office",
            "type":"Public Place"
        }
    ],
    "sg:phone":"+1 828 259 5830",
    "sg:postcode":"28801",
    "sg:province":"NC",
    "sg:tags":[
        "village"
    ],
    "wof:name":"Asheville Planning Office",
    "wof:placetype":"venue"
},
  "geometry": {"coordinates":[-82.548756,35.595596],"type":"Point"}
}