{
  "type": "Feature",
  "properties": {
    "iso:country":"US",
    "sg:address":"404 N Jackson St",
    "sg:city":"Salisbury",
    "sg:classifiers":[
        {
            "category":"Government",
            "subcategory":"Office",
            "type":"Public Place"
        }
    ],
    "sg:phone":"+1 704 638 5262",
    "sg:postcode":"28144",
    "sg:province":"NC",
    "sg:tags":[
        "village"
    ],
    "wof:name":"Salisbury Cty Code Enforcement",
    "wof:placetype":"venue"
},
  "geometry": {"coordinates":[-80.467697,35.67265],"type":"Point"}
}