{
  "type": "Feature",
  "properties": {
    "addr:full":"141 Ridgewood Rd Youngsville NC 27596",
    "addr:housenumber":"141",
    "addr:postcode":"27596",
    "addr:street":"Ridgewood Rd",
    "iso:country":"US",
    "sg:address":"141 Ridgewood Rd",
    "sg:city":"Youngsville",
    "sg:classifiers":[
        {
            "category":"Building & Trades",
            "subcategory":"Construction",
            "type":"Services"
        }
    ],
    "sg:phone":"+1 919 556 8746",
    "sg:postcode":"27596",
    "sg:province":"NC",
    "sg:tags":[
        "concrete",
        "contractor"
    ],
    "wof:name":"W E Rogers Inc",
    "wof:placetype":"venue"
},
  "geometry": {"coordinates":[-78.51461500000001,36.056784],"type":"Point"}
}