{
  "type": "Feature",
  "properties": {
    "addr:full":"112 Hinton Ave Wilmington NC 28403",
    "addr:housenumber":"112",
    "addr:postcode":"28403",
    "addr:street":"Hinton Ave",
    "iso:country":"US",
    "sg:address":"112 Hinton Ave",
    "sg:city":"Wilmington",
    "sg:classifiers":[
        {
            "category":"Retail",
            "subcategory":"Repair Shop",
            "type":"Services"
        }
    ],
    "sg:phone":"+1   ",
    "sg:postcode":"28403",
    "sg:province":"NC",
    "wof:name":"Doctor Ding Surfboard Repair",
    "wof:placetype":"venue"
},
  "geometry": {"coordinates":[-77.849074,34.211522],"type":"Point"}
}