{
  "type": "Feature",
  "properties": {
    "iso:country":"US",
    "sg:address":"2026 State Hwy 11",
    "sg:city":"Kinston",
    "sg:classifiers":[
        {
            "category":"Government",
            "subcategory":"Office",
            "type":"Public Place"
        }
    ],
    "sg:phone":"+1 252 523 3169",
    "sg:postcode":"28504",
    "sg:province":"NC",
    "sg:tags":[
        "conservation"
    ],
    "wof:name":"Lenoir Soil & Water Conservatn",
    "wof:placetype":"venue"
},
  "geometry": {"coordinates":[-77.66776400000001,35.187315],"type":"Point"}
}