{
  "type": "Feature",
  "properties": {
    "addr:full":"115 S Goldsboro St Lucama NC 27851",
    "addr:housenumber":"115",
    "addr:postcode":"27851",
    "addr:street":"S Goldsboro St",
    "iso:country":"US",
    "sg:address":"115 S Goldsboro St",
    "sg:city":"Lucama",
    "sg:classifiers":[
        {
            "category":"Professional",
            "subcategory":"Business Services",
            "type":"Services"
        }
    ],
    "sg:phone":"+1 919 242 6673",
    "sg:postcode":"27851",
    "sg:province":"NC",
    "sg:tags":[
        "fund",
        "promotion",
        "raising"
    ],
    "wof:name":"R & A Promotions",
    "wof:placetype":"venue"
},
  "geometry": {"coordinates":[-78.011044,35.644479],"type":"Point"}
}