{
  "type": "Feature",
  "properties": {
    "addr:full":"3702 E Independence Blvd Charlotte NC 28205",
    "addr:housenumber":"3702",
    "addr:postcode":"28205",
    "addr:street":"E Independence Blvd",
    "iso:country":"US",
    "sg:address":"3702 E Independence Blvd",
    "sg:city":"Charlotte",
    "sg:classifiers":[
        {
            "category":"Shopping",
            "subcategory":"Bicycles & Sporting Goods",
            "type":"Retail Goods"
        }
    ],
    "sg:phone":"+1 704 537 5252",
    "sg:postcode":"28205",
    "sg:province":"NC",
    "sg:tags":[
        "equipment",
        "skateboard"
    ],
    "sg:website":"www.infinitysend.com",
    "wof:name":"Queen City Skateboards",
    "wof:placetype":"venue"
},
  "geometry": {"coordinates":[-80.777092,35.200973],"type":"Point"}
}