{
  "type": "Feature",
  "properties": {
    "iso:country":"US",
    "sg:address":"164 Barbours Chapel Rd",
    "sg:city":"Four Oaks",
    "sg:classifiers":[
        {
            "category":"Organizations",
            "subcategory":"Religious Organization",
            "type":"Services"
        }
    ],
    "sg:phone":"+1 919 963 2022",
    "sg:postcode":"27524",
    "sg:province":"NC",
    "sg:tags":[
        "church"
    ],
    "wof:name":"Barbour's Chapel Advent Church",
    "wof:placetype":"venue"
},
  "geometry": {"coordinates":[-78.451275,35.45476],"type":"Point"}
}