{
  "type": "Feature",
  "properties": {
    "iso:country":"US",
    "sg:address":"3510 Stokes Ferry Rd",
    "sg:city":"Salisbury",
    "sg:classifiers":[
        {
            "category":"Shopping",
            "subcategory":"Bicycles & Sporting Goods",
            "type":"Retail Goods"
        }
    ],
    "sg:phone":"+1 704 637 3810",
    "sg:postcode":"28146",
    "sg:province":"NC",
    "sg:tags":[
        "tackle",
        "fishing"
    ],
    "wof:name":"Pine Ridge General Store",
    "wof:placetype":"venue"
},
  "geometry": {"coordinates":[-80.43087199999999,35.63183],"type":"Point"}
}