{
  "type": "Feature",
  "properties": {
    "addr:full":"1911 Elmwood Dr Graham NC 27253",
    "addr:housenumber":"1911",
    "addr:postcode":"27253",
    "addr:street":"Elmwood Dr",
    "iso:country":"US",
    "sg:address":"1911 Elmwood Dr",
    "sg:city":"Graham",
    "sg:classifiers":[
        {
            "category":"Real Estate",
            "subcategory":"Real Estate Agent",
            "type":"Services"
        }
    ],
    "sg:phone":"+1 336 229 6573",
    "sg:postcode":"27253",
    "sg:province":"NC",
    "wof:name":"Michael Brown & Assoc Rlty Co",
    "wof:placetype":"venue"
},
  "geometry": {"coordinates":[-79.411086,36.03427],"type":"Point"}
}