{
  "type": "Feature",
  "properties": {
    "iso:country":"US",
    "sg:address":"1364 US 221S Hwy",
    "sg:city":"Rutherfordton",
    "sg:classifiers":[
        {
            "category":"Restaurant",
            "type":"Food & Drink"
        }
    ],
    "sg:phone":"+1 828 288 8600",
    "sg:postcode":"28139",
    "sg:province":"NC",
    "sg:tags":[
        "eating"
    ],
    "wof:name":"Becky's Restaurant",
    "wof:placetype":"venue"
},
  "geometry": {"coordinates":[-81.929821,35.316915],"type":"Point"}
}