{
  "type": "Feature",
  "properties": {
    "addr:full":"4910 Archdale Rd Trinity NC 27370",
    "addr:housenumber":"4910",
    "addr:postcode":"27370",
    "addr:street":"Archdale Rd",
    "iso:country":"US",
    "sg:address":"4910 Archdale Rd",
    "sg:city":"Trinity",
    "sg:classifiers":[
        {
            "category":"Social Services",
            "subcategory":"Child Care",
            "type":"Services"
        }
    ],
    "sg:phone":"+1 336 431 7910",
    "sg:postcode":"27370",
    "sg:province":"NC",
    "wof:name":"Linda's Child Day Care Ctr",
    "wof:placetype":"venue"
},
  "geometry": {"coordinates":[-79.95969100000001,35.887546],"type":"Point"}
}