{
  "type": "Feature",
  "properties": {
    "addr:full":"3220 Latrobe Dr Charlotte NC 28211",
    "addr:housenumber":"3220",
    "addr:postcode":"28211",
    "addr:street":"Latrobe Dr",
    "iso:country":"US",
    "sg:address":"3220 Latrobe Dr",
    "sg:city":"Charlotte",
    "sg:classifiers":[
        {
            "category":"Health Services",
            "subcategory":"Clinic",
            "type":"Services"
        },
        {
            "category":"Health Services",
            "subcategory":"Doctor",
            "type":"Services"
        }
    ],
    "sg:phone":"+1 704 362 2085",
    "sg:postcode":"28211",
    "sg:province":"NC",
    "sg:tags":[
        "information",
        "surgeon",
        "abortion",
        "physician"
    ],
    "wof:name":"A Preferred Women's Health Ctr",
    "wof:placetype":"venue"
},
  "geometry": {"coordinates":[-80.802862,35.199176],"type":"Point"}
}