{
  "type": "Feature",
  "properties": {
    "addr:full":"9920 Leitner Dr Pineville NC 28134",
    "addr:postcode":"9920;28134",
    "addr:street":"Leitner Dr",
    "iso:country":"US",
    "sg:address":"9920 Leitner Dr",
    "sg:city":"Pineville",
    "sg:classifiers":[
        {
            "category":"Restaurant",
            "type":"Food & Drink"
        }
    ],
    "sg:menulink":"http://www.allmenus.com/nc/pineville/100478-tony-romas/menu/",
    "sg:phone":"+1 704 544 3302",
    "sg:postcode":"28134",
    "sg:province":"NC",
    "sg:tags":[
        "seafood",
        "american",
        "italian"
    ],
    "wof:name":"Tony Romas",
    "wof:placetype":"venue"
},
  "geometry": {"coordinates":[-80.881404,35.086334],"type":"Point"}
}