{
  "type": "Feature",
  "properties": {
    "iso:country":"US",
    "sg:address":"44 Shannon Dr",
    "sg:city":"Asheville",
    "sg:classifiers":[
        {
            "category":"Building & Trades",
            "subcategory":"Construction",
            "type":"Services"
        }
    ],
    "sg:phone":"+1 828 274 9309",
    "sg:postcode":"28803",
    "sg:province":"NC",
    "sg:tags":[
        "contractor"
    ],
    "wof:name":"Tile Services",
    "wof:placetype":"venue"
},
  "geometry": {"coordinates":[-82.521579,35.56174],"type":"Point"}
}