{
  "type": "Feature",
  "properties": {
    "addr:full":"2801 Foxfield Ct Gastonia NC 28054",
    "addr:housenumber":"2801",
    "addr:postcode":"28054",
    "addr:street":"Foxfield Ct",
    "iso:country":"US",
    "sg:address":"2801 Foxfield Ct",
    "sg:city":"Gastonia",
    "sg:classifiers":[
        {
            "category":"Manufacturing",
            "subcategory":"Tools & Machinery",
            "type":"Manufacturing & Wholesale Goods"
        }
    ],
    "sg:phone":"+1 704 864 5241",
    "sg:postcode":"28054",
    "sg:province":"NC",
    "sg:tags":[
        "machine",
        "shop"
    ],
    "wof:name":"Metro Associates LTD",
    "wof:placetype":"venue"
},
  "geometry": {"coordinates":[-81.157117,35.225987],"type":"Point"}
}