{
  "type": "Feature",
  "properties": {
    "iso:country":"US",
    "sg:address":"1175 Asheford Green Ave NW",
    "sg:city":"Concord",
    "sg:classifiers":[
        {
            "category":"Professional",
            "subcategory":"Business Services",
            "type":"Services"
        }
    ],
    "sg:phone":"+1   ",
    "sg:postcode":"28027",
    "sg:province":"NC",
    "wof:name":"Pmr Investments Inc",
    "wof:placetype":"venue"
},
  "geometry": {"coordinates":[-80.64104,35.397708],"type":"Point"}
}