{
  "type": "Feature",
  "properties": {
    "iso:country":"US",
    "sg:address":"2160 29th Avenue Dr NE",
    "sg:city":"Hickory",
    "sg:classifiers":[
        {
            "category":"Organizations",
            "subcategory":"Religious Organization",
            "type":"Services"
        }
    ],
    "sg:phone":"+1   ",
    "sg:postcode":"28601",
    "sg:province":"NC",
    "wof:name":"Living Waters Church",
    "wof:placetype":"venue"
},
  "geometry": {"coordinates":[-81.293329,35.76096],"type":"Point"}
}