{
  "type": "Feature",
  "properties": {
    "addr:full":"417 S Post Rd Shelby NC 28152",
    "addr:housenumber":"417",
    "addr:postcode":"28152",
    "addr:street":"S Post Rd",
    "iso:country":"US",
    "sg:address":"417 S Post Rd",
    "sg:city":"Shelby",
    "sg:classifiers":[
        {
            "category":"Autos & Motor Vehicles",
            "subcategory":"Automobile Sales",
            "type":"Retail Goods"
        }
    ],
    "sg:phone":"+1 704 487 0570",
    "sg:postcode":"28152",
    "sg:province":"NC",
    "sg:tags":[
        "car",
        "used",
        "dealer"
    ],
    "wof:name":"S & R Auto Sales Inc",
    "wof:placetype":"venue"
},
  "geometry": {"coordinates":[-81.496533,35.27519],"type":"Point"}
}