{
  "type": "Feature",
  "properties": {
    "iso:country":"US",
    "sg:address":"145 Pine Tree Rd",
    "sg:city":"Winston Salem",
    "sg:classifiers":[
        {
            "category":"Organizations",
            "subcategory":"Religious Organization",
            "type":"Services"
        }
    ],
    "sg:phone":"+1   ",
    "sg:postcode":"27105",
    "sg:province":"NC",
    "wof:name":"Mercy Seat Holy Church",
    "wof:placetype":"venue"
},
  "geometry": {"coordinates":[-80.250681,36.146414],"type":"Point"}
}