{
  "type": "Feature",
  "properties": {
    "addr:full":"1401 Old Ivey Rd Apex NC 27523",
    "addr:housenumber":"1401",
    "addr:postcode":"27523",
    "addr:street":"Old Ivey Rd",
    "iso:country":"US",
    "sg:address":"1401 Old Ivey Rd",
    "sg:city":"Apex",
    "sg:classifiers":[
        {
            "category":"Retail",
            "subcategory":"Animal Services",
            "type":"Services"
        }
    ],
    "sg:phone":"+1 919 362 7877",
    "sg:postcode":"27523",
    "sg:province":"NC",
    "sg:tags":[
        "pet",
        "boarding",
        "sitting"
    ],
    "wof:name":"Green Level Kennel",
    "wof:placetype":"venue"
},
  "geometry": {"coordinates":[-78.904347,35.760377],"type":"Point"}
}