{
  "type": "Feature",
  "properties": {
    "iso:country":"US",
    "sg:address":"2800 Reynolda Rd",
    "sg:city":"Winston Salem",
    "sg:classifiers":[
        {
            "category":"Autos & Motor Vehicles",
            "subcategory":"Fuel & Gas Station",
            "type":"Retail Goods"
        }
    ],
    "sg:phone":"+1 336 725 6231",
    "sg:postcode":"27106",
    "sg:province":"NC",
    "sg:tags":[
        "oil"
    ],
    "wof:name":"Reynolda Manor Chevron",
    "wof:placetype":"venue"
},
  "geometry": {"coordinates":[-80.29878600000001,36.143481],"type":"Point"}
}