{
  "type": "Feature",
  "properties": {
    "addr:full":"403 Island Ford Rd Maiden NC 28650",
    "addr:housenumber":"403",
    "addr:postcode":"28650",
    "addr:street":"Island Ford Rd",
    "iso:country":"US",
    "sg:address":"403 Island Ford Rd",
    "sg:city":"Maiden",
    "sg:classifiers":[
        {
            "category":"Freight",
            "type":"Transportation"
        },
        {
            "category":"Professional",
            "subcategory":"Employment Agencies",
            "type":"Services"
        }
    ],
    "sg:phone":"+1 828 428 8292",
    "sg:postcode":"28650",
    "sg:province":"NC",
    "sg:tags":[
        "supply",
        "help",
        "trucking"
    ],
    "wof:name":"Piedmont Express Svc",
    "wof:placetype":"venue"
},
  "geometry": {"coordinates":[-81.19519,35.563448],"type":"Point"}
}