{
  "type": "Feature",
  "properties": {
    "iso:country":"US",
    "sg:address":"55 S Main St",
    "sg:city":"Sparta",
    "sg:classifiers":[
        {
            "category":"Shopping",
            "subcategory":"Pharmacy",
            "type":"Retail Goods"
        }
    ],
    "sg:phone":"+1 336 372 5599",
    "sg:postcode":"28675",
    "sg:province":"NC",
    "wof:name":"Halsey Drug",
    "wof:placetype":"venue"
},
  "geometry": {"coordinates":[-81.11953699999999,36.50455],"type":"Point"}
}