{
  "type": "Feature",
  "properties": {
    "addr:full":"4257 Mourning Dove Dr Matthews NC 28104",
    "addr:housenumber":"4257",
    "addr:postcode":"28104",
    "addr:street":"Mourning Dove Dr",
    "iso:country":"US",
    "sg:address":"4257 Mourning Dove Dr",
    "sg:city":"Matthews",
    "sg:classifiers":[
        {
            "category":"Building & Trades",
            "subcategory":"Construction",
            "type":"Services"
        }
    ],
    "sg:phone":"+1 704 814 7011",
    "sg:postcode":"28104",
    "sg:province":"NC",
    "sg:tags":[
        "house"
    ],
    "wof:name":"McGee Builders & Design Inc",
    "wof:placetype":"venue"
},
  "geometry": {"coordinates":[-80.727678,35.014729],"type":"Point"}
}