{
  "type": "Feature",
  "properties": {
    "iso:country":"US",
    "sg:address":"701 Kirkman St",
    "sg:city":"Greensboro",
    "sg:classifiers":[
        {
            "category":"Social Services",
            "subcategory":"Child Care",
            "type":"Services"
        }
    ],
    "sg:phone":"+1 336 275 5677",
    "sg:postcode":"27406",
    "sg:province":"NC",
    "wof:name":"Kid's Corner",
    "wof:placetype":"venue"
},
  "geometry": {"coordinates":[-79.808791,36.040825],"type":"Point"}
}