{
  "type": "Feature",
  "properties": {
    "iso:country":"US",
    "sg:address":"636 Nuway Cir",
    "sg:city":"Lenoir",
    "sg:classifiers":[
        {
            "category":"Freight",
            "type":"Transportation"
        }
    ],
    "sg:phone":"+1 828 759 1900",
    "sg:postcode":"28645",
    "sg:province":"NC",
    "sg:tags":[
        "commercial",
        "storage",
        "special"
    ],
    "wof:name":"A A A Mini Storage",
    "wof:placetype":"venue"
},
  "geometry": {"coordinates":[-81.53743799999999,35.941772],"type":"Point"}
}