{
  "type": "Feature",
  "properties": {
    "addr:full":"5347 State Hwy 43 N Greenville NC 27834",
    "addr:housenumber":"5347",
    "addr:postcode":"27834",
    "addr:street":"State Hwy 43 N",
    "iso:country":"US",
    "sg:address":"5347 State Hwy 43 N",
    "sg:city":"Greenville",
    "sg:classifiers":[
        {
            "category":"Autos & Motor Vehicles",
            "subcategory":"Automobile Sales",
            "type":"Retail Goods"
        }
    ],
    "sg:phone":"+1 252 355 5400",
    "sg:postcode":"27834",
    "sg:province":"NC",
    "sg:tags":[
        "car",
        "dealer"
    ],
    "wof:name":"Auto Outlet",
    "wof:placetype":"venue"
},
  "geometry": {"coordinates":[-77.496269,35.689637],"type":"Point"}
}