{
  "type": "Feature",
  "properties": {
    "addr:full":"6979 Charles Mtn Rd Denton NC 27239",
    "addr:housenumber":"6979",
    "addr:postcode":"27239",
    "addr:street":"Charles Mtn Rd",
    "iso:country":"US",
    "sg:address":"6979 Charles Mtn Rd",
    "sg:city":"Denton",
    "sg:classifiers":[
        {
            "category":"Farming",
            "subcategory":"Farm",
            "type":"Manufacturing & Wholesale Goods"
        }
    ],
    "sg:phone":"+1 336 857 3288",
    "sg:postcode":"27239",
    "sg:province":"NC",
    "wof:name":"Rae Lee Farms",
    "wof:placetype":"venue"
},
  "geometry": {"coordinates":[-80.028549,35.559152],"type":"Point"}
}