{
  "type": "Feature",
  "properties": {
    "iso:country":"US",
    "sg:address":"1600 Virginia Dare Trl",
    "sg:city":"Kill Devil Hills",
    "sg:classifiers":[
        {
            "category":"Restaurant",
            "type":"Food & Drink"
        }
    ],
    "sg:phone":"+1 252 441 3332",
    "sg:postcode":"27948",
    "sg:province":"NC",
    "wof:name":"American Pie Pizza & Homemade",
    "wof:placetype":"venue"
},
  "geometry": {"coordinates":[-75.666697,36.029672],"type":"Point"}
}