{
  "type": "Feature",
  "properties": {
    "iso:country":"US",
    "sg:address":"1711 E Mulberry St",
    "sg:city":"Goldsboro",
    "sg:classifiers":[
        {
            "category":"Professional",
            "subcategory":"Business Services",
            "type":"Services"
        }
    ],
    "sg:phone":"+1   ",
    "sg:postcode":"27530",
    "sg:province":"NC",
    "wof:name":"Eagle Enterprises",
    "wof:placetype":"venue"
},
  "geometry": {"coordinates":[-77.96948399999999,35.376975],"type":"Point"}
}