{
  "type": "Feature",
  "properties": {
    "addr:full":"225 Broad St S Winston Salem NC 27101",
    "addr:housenumber":"225",
    "addr:postcode":"27101",
    "addr:street":"Broad St S Winston",
    "iso:country":"US",
    "sg:address":"225 Broad St S",
    "sg:city":"Winston Salem",
    "sg:classifiers":[
        {
            "category":"Food & Beverages",
            "subcategory":"Groceries & Convenience Stores",
            "type":"Retail Goods"
        }
    ],
    "sg:phone":"+1 336 722 7099",
    "sg:postcode":"27101",
    "sg:province":"NC",
    "wof:name":"Fairway One Stop",
    "wof:placetype":"venue"
},
  "geometry": {"coordinates":[-80.25077,36.09043],"type":"Point"}
}