{
  "type": "Feature",
  "properties": {
    "addr:full":"8607 Deerwood Rd Charlotte NC 28214",
    "addr:housenumber":"8607",
    "addr:postcode":"28214",
    "addr:street":"Deerwood Rd",
    "iso:country":"US",
    "sg:address":"8607 Deerwood Rd",
    "sg:city":"Charlotte",
    "sg:classifiers":[
        {
            "category":"Retail",
            "subcategory":"Auto Repair",
            "type":"Services"
        }
    ],
    "sg:phone":"+1 704 517 0176",
    "sg:postcode":"28214",
    "sg:province":"NC",
    "sg:tags":[
        "body",
        "painting",
        "repairing",
        "automobile"
    ],
    "wof:name":"Beannie's Body Therapy & Products",
    "wof:placetype":"venue"
},
  "geometry": {"coordinates":[-80.956287,35.280251],"type":"Point"}
}