{
  "type": "Feature",
  "properties": {
    "addr:full":"8416 Neuse Rapids Rd Raleigh NC 27616",
    "addr:housenumber":"8416",
    "addr:postcode":"27616",
    "addr:street":"Neuse Rapids Rd",
    "iso:country":"US",
    "sg:address":"8416 Neuse Rapids Rd",
    "sg:city":"Raleigh",
    "sg:classifiers":[
        {
            "category":"Professional",
            "subcategory":"Accounting & Tax Preparation",
            "type":"Services"
        }
    ],
    "sg:phone":"+1 919 850 2282",
    "sg:postcode":"27616",
    "sg:province":"NC",
    "sg:tags":[
        "accountant"
    ],
    "wof:name":"Gilbert B Brazel CPA",
    "wof:placetype":"venue"
},
  "geometry": {"coordinates":[-78.54795300000001,35.89325],"type":"Point"}
}