{
  "type": "Feature",
  "properties": {
    "iso:country":"US",
    "sg:address":"100 Europa Dr",
    "sg:city":"Chapel Hill",
    "sg:classifiers":[
        {
            "category":"Professional",
            "subcategory":"Lawyer & Legal Services",
            "type":"Services"
        }
    ],
    "sg:phone":"+1 919 942 5200",
    "sg:postcode":"27517",
    "sg:province":"NC",
    "sg:tags":[
        "attorney"
    ],
    "wof:name":"Patterson Harkavy LLP",
    "wof:placetype":"venue"
},
  "geometry": {"coordinates":[-79.01812099999999,35.940487],"type":"Point"}
}