{
  "type": "Feature",
  "properties": {
    "addr:full":"1119 Crab Orchard Dr Raleigh NC 27606",
    "addr:housenumber":"1119",
    "addr:postcode":"27606",
    "addr:street":"Crab Orchard Dr",
    "iso:country":"US",
    "sg:address":"1119 Crab Orchard Dr",
    "sg:city":"Raleigh",
    "sg:classifiers":[
        {
            "category":"Professional",
            "type":"Services"
        }
    ],
    "sg:phone":"+1 919 852 1510",
    "sg:postcode":"27606",
    "sg:province":"NC",
    "wof:name":"Suswee Infotech Corp",
    "wof:placetype":"venue"
},
  "geometry": {"coordinates":[-78.70131499999999,35.766738],"type":"Point"}
}