{
  "type": "Feature",
  "properties": {
    "iso:country":"US",
    "sg:address":"911 E Atkins St",
    "sg:city":"Dobson",
    "sg:classifiers":[
        {
            "category":"Restaurant",
            "type":"Food & Drink"
        }
    ],
    "sg:phone":"+1 336 374 4496",
    "sg:postcode":"27017",
    "sg:province":"NC",
    "wof:name":"Surry Diner",
    "wof:placetype":"venue"
},
  "geometry": {"coordinates":[-80.706968,36.392153],"type":"Point"}
}