{
  "type": "Feature",
  "properties": {
    "iso:country":"US",
    "sg:address":"1417 Creekbend Ln",
    "sg:city":"Graham",
    "sg:classifiers":[
        {
            "category":"Professional",
            "subcategory":"Management & Consulting",
            "type":"Services"
        }
    ],
    "sg:phone":"+1   ",
    "sg:postcode":"27253",
    "sg:province":"NC",
    "wof:name":"Lea & Assoc Ltd",
    "wof:placetype":"venue"
},
  "geometry": {"coordinates":[-79.361541,36.051118],"type":"Point"}
}