{
  "type": "Feature",
  "properties": {
    "iso:country":"US",
    "sg:address":"3027 Rocky Hock Rd",
    "sg:city":"Edenton",
    "sg:classifiers":[
        {
            "category":"Social Services",
            "subcategory":"Child Care",
            "type":"Services"
        }
    ],
    "sg:phone":"+1 252 221 3045",
    "sg:postcode":"27932",
    "sg:province":"NC",
    "sg:tags":[
        "day"
    ],
    "wof:name":"Laydens Day Care Ctr Preschool",
    "wof:placetype":"venue"
},
  "geometry": {"coordinates":[-76.69434099999999,36.183895],"type":"Point"}
}