{
  "type": "Feature",
  "properties": {
    "addr:full":"1807 Enoch Ln Greensboro NC 27405",
    "addr:housenumber":"1807",
    "addr:postcode":"27405",
    "addr:street":"Enoch Ln",
    "iso:country":"US",
    "sg:address":"1807 Enoch Ln",
    "sg:city":"Greensboro",
    "sg:classifiers":[
        {
            "category":"Professional",
            "subcategory":"Management & Consulting",
            "type":"Services"
        }
    ],
    "sg:phone":"+1 336 358 2510",
    "sg:postcode":"27405",
    "sg:province":"NC",
    "sg:tags":[
        "consultant"
    ],
    "wof:name":"Carrington Consultants Inc 2",
    "wof:placetype":"venue"
},
  "geometry": {"coordinates":[-79.72204600000001,36.096206],"type":"Point"}
}