{
  "type": "Feature",
  "properties": {
    "iso:country":"US",
    "sg:address":"1724 Eastwood Rd",
    "sg:city":"Wilmington",
    "sg:classifiers":[
        {
            "category":"Banks & Credit Unions",
            "subcategory":"Bank",
            "type":"Services"
        }
    ],
    "sg:phone":"+1 910 509 2816",
    "sg:postcode":"28403",
    "sg:province":"NC",
    "sg:website":"www.ecbbancorp.com",
    "wof:name":"East Carolina Bank",
    "wof:placetype":"venue"
},
  "geometry": {"coordinates":[-77.827071,34.226081],"type":"Point"}
}