{
  "type": "Feature",
  "properties": {
    "addr:full":"101 E Cleveland St Dunn NC 28334",
    "addr:housenumber":"101",
    "addr:postcode":"28334",
    "addr:street":"E Cleveland St",
    "iso:country":"US",
    "sg:address":"101 E Cleveland St",
    "sg:city":"Dunn",
    "sg:classifiers":[
        {
            "category":"Building & Trades",
            "subcategory":"Construction",
            "type":"Services"
        }
    ],
    "sg:phone":"+1 910 892 2948",
    "sg:postcode":"28334",
    "sg:province":"NC",
    "sg:tags":[
        "marking",
        "maintenance",
        "parking"
    ],
    "sg:website":"www.dunn-nc.org",
    "wof:name":"Dunn Public Works Dept",
    "wof:placetype":"venue"
},
  "geometry": {"coordinates":[-78.607405,35.31156],"type":"Point"}
}