{
  "type": "Feature",
  "properties": {
    "addr:full":"4 Harbour Walk New Bern NC 28562",
    "addr:housenumber":"4",
    "addr:postcode":"28562",
    "addr:street":"Harbour Walk",
    "iso:country":"US",
    "sg:address":"4 Harbour Walk",
    "sg:city":"New Bern",
    "sg:classifiers":[
        {
            "category":"Personal",
            "subcategory":"Beauty Salon",
            "type":"Services"
        }
    ],
    "sg:phone":"+1   ",
    "sg:postcode":"28562",
    "sg:province":"NC",
    "sg:tags":[
        "shop"
    ],
    "wof:name":"A Perfect Ten",
    "wof:placetype":"venue"
},
  "geometry": {"coordinates":[-77.145971,35.074047],"type":"Point"}
}