{
  "type": "Feature",
  "properties": {
    "addr:full":"1106 Webb Rd Salisbury NC 28146",
    "addr:housenumber":"1106",
    "addr:postcode":"28146",
    "addr:street":"Webb Rd",
    "iso:country":"US",
    "sg:address":"1106 Webb Rd",
    "sg:city":"Salisbury",
    "sg:classifiers":[
        {
            "category":"Building & Trades",
            "subcategory":"Construction",
            "type":"Services"
        }
    ],
    "sg:phone":"+1 704 637 7200",
    "sg:postcode":"28146",
    "sg:province":"NC",
    "sg:tags":[
        "carpentry",
        "contractor"
    ],
    "wof:name":"Steve Koon Carpentry",
    "wof:placetype":"venue"
},
  "geometry": {"coordinates":[-80.51489100000001,35.595791],"type":"Point"}
}