{
  "type": "Feature",
  "properties": {
    "iso:country":"US",
    "sg:address":"1917 Baronsmede Dr",
    "sg:city":"Raleigh",
    "sg:classifiers":[
        {
            "category":"Building & Trades",
            "subcategory":"Construction",
            "type":"Services"
        }
    ],
    "sg:phone":"+1 919 518 8310",
    "sg:postcode":"27615",
    "sg:province":"NC",
    "sg:tags":[
        "floor"
    ],
    "wof:name":"Southeast Polymer Instltns",
    "wof:placetype":"venue"
},
  "geometry": {"coordinates":[-78.610151,35.894332],"type":"Point"}
}