{
  "type": "Feature",
  "properties": {
    "addr:full":"171 Windy Hill Dr Franklin NC 28734",
    "addr:housenumber":"171",
    "addr:postcode":"nc 28734",
    "addr:street":"Windy Hill Dr",
    "iso:country":"US",
    "sg:address":"171 Windy Hill Dr",
    "sg:city":"Franklin",
    "sg:classifiers":[
        {
            "category":"Building & Trades",
            "subcategory":"Construction",
            "type":"Services"
        }
    ],
    "sg:phone":"+1 828 369 2091",
    "sg:postcode":"28734",
    "sg:province":"NC",
    "sg:tags":[
        "roofing",
        "contractor"
    ],
    "wof:name":"Phil's Roofing",
    "wof:placetype":"venue"
},
  "geometry": {"coordinates":[-83.370015,35.15687],"type":"Point"}
}