{
  "type": "Feature",
  "properties": {
    "iso:country":"US",
    "sg:address":"2779 State Rd 98",
    "sg:city":"Louisburg",
    "sg:classifiers":[
        {
            "category":"Organizations",
            "subcategory":"Religious Organization",
            "type":"Services"
        }
    ],
    "sg:phone":"+1   ",
    "sg:postcode":"27549",
    "sg:province":"NC",
    "wof:name":"New York Christian Church",
    "wof:placetype":"venue"
},
  "geometry": {"coordinates":[-78.34186800000001,35.971939],"type":"Point"}
}