{
  "type": "Feature",
  "properties": {
    "iso:country":"US",
    "sg:address":"7295 Jesse Briggs Rd",
    "sg:city":"Rural Hall",
    "sg:classifiers":[
        {
            "category":"Farming",
            "subcategory":"Farm",
            "type":"Manufacturing & Wholesale Goods"
        }
    ],
    "sg:phone":"+1 336 922 4424",
    "sg:postcode":"27045",
    "sg:province":"NC",
    "wof:name":"Shady Oaks Farm",
    "wof:placetype":"venue"
},
  "geometry": {"coordinates":[-80.347804,36.216373],"type":"Point"}
}