{
  "type": "Feature",
  "properties": {
    "iso:country":"US",
    "sg:address":"1401 N 2nd Ave",
    "sg:city":"Siler City",
    "sg:classifiers":[
        {
            "category":"Retail",
            "subcategory":"Veterinary Services",
            "type":"Services"
        }
    ],
    "sg:phone":"+1 919 742 3646",
    "sg:postcode":"27344",
    "sg:province":"NC",
    "sg:tags":[
        "veterinarian"
    ],
    "wof:name":"Tysor Veterinary Clinic",
    "wof:placetype":"venue"
},
  "geometry": {"coordinates":[-79.467381,35.738746],"type":"Point"}
}