{
  "type": "Feature",
  "properties": {
    "iso:country":"US",
    "sg:address":"1416 Country Lake Dr",
    "sg:city":"Greensboro",
    "sg:classifiers":[
        {
            "category":"Professional",
            "type":"Services"
        }
    ],
    "sg:phone":"+1 336 674 3551",
    "sg:postcode":"27406",
    "sg:province":"NC",
    "wof:name":"Bck Inc",
    "wof:placetype":"venue"
},
  "geometry": {"coordinates":[-79.83543899999999,35.959323],"type":"Point"}
}