{
  "type": "Feature",
  "properties": {
    "addr:full":"2103 Margaret Wallace Rd Matthews NC 28105",
    "addr:housenumber":"2103",
    "addr:postcode":"28105",
    "addr:street":"Margaret Wallace Rd",
    "iso:country":"US",
    "sg:address":"2103 Margaret Wallace Rd",
    "sg:city":"Matthews",
    "sg:classifiers":[
        {
            "category":"Manufacturing",
            "subcategory":"Printing",
            "type":"Manufacturing & Wholesale Goods"
        }
    ],
    "sg:phone":"+1 704 537 2001",
    "sg:postcode":"28105",
    "sg:province":"NC",
    "sg:tags":[
        "screen",
        "commercial"
    ],
    "sg:website":"www.johnstreet.net",
    "wof:name":"John Street Graphics",
    "wof:placetype":"venue"
},
  "geometry": {"coordinates":[-80.73990000000001,35.164406],"type":"Point"}
}