{
  "type": "Feature",
  "properties": {
    "addr:full":"701 E Roosevelt Blvd Monroe NC 28112",
    "addr:housenumber":"701",
    "addr:postcode":"28112",
    "addr:street":"E Roosevelt Blvd",
    "iso:country":"US",
    "sg:address":"701 E Roosevelt Blvd",
    "sg:city":"Monroe",
    "sg:classifiers":[
        {
            "category":"Health Services",
            "subcategory":"Health Practitioner",
            "type":"Services"
        }
    ],
    "sg:phone":"+1 704 291 7755",
    "sg:postcode":"28112",
    "sg:province":"NC",
    "wof:name":"Carolnas Physcl Therapy Netwrk",
    "wof:placetype":"venue"
},
  "geometry": {"coordinates":[-80.519428,34.975267],"type":"Point"}
}