{
  "type": "Feature",
  "properties": {
    "iso:country":"US",
    "sg:address":"3451 Springs Rd NE",
    "sg:city":"Hickory",
    "sg:classifiers":[
        {
            "category":"Professional",
            "subcategory":"Business Services",
            "type":"Services"
        }
    ],
    "sg:phone":"+1   ",
    "sg:postcode":"28601",
    "sg:province":"NC",
    "wof:name":"Springs Road Flea Market",
    "wof:placetype":"venue"
},
  "geometry": {"coordinates":[-81.26932600000001,35.762391],"type":"Point"}
}