{
  "type": "Feature",
  "properties": {
    "addr:full":"2266 Lightwood Knot Rd Kinston NC 28504",
    "addr:postcode":"2266;28504",
    "addr:street":"Knot Rd",
    "iso:country":"US",
    "sg:address":"2266 Lightwood Knot Rd",
    "sg:city":"Kinston",
    "sg:classifiers":[
        {
            "category":"Building & Trades",
            "subcategory":"Construction",
            "type":"Services"
        }
    ],
    "sg:phone":"+1 252 527 4399",
    "sg:postcode":"28504",
    "sg:province":"NC",
    "sg:tags":[
        "contractor"
    ],
    "wof:name":"CL Sandblasting",
    "wof:placetype":"venue"
},
  "geometry": {"coordinates":[-77.556212,35.152871],"type":"Point"}
}