{
  "type": "Feature",
  "properties": {
    "iso:country":"US",
    "sg:address":"111 Oak Ave",
    "sg:city":"Spruce Pine",
    "sg:classifiers":[
        {
            "category":"Autos & Motor Vehicles",
            "subcategory":"Fuel & Gas Station",
            "type":"Retail Goods"
        },
        {
            "category":"Retail",
            "subcategory":"Auto Repair",
            "type":"Services"
        }
    ],
    "sg:phone":"+1 828 765 9332",
    "sg:postcode":"28777",
    "sg:province":"NC",
    "sg:tags":[
        "oil",
        "tire"
    ],
    "wof:name":"Toe River Service Station",
    "wof:placetype":"venue"
},
  "geometry": {"coordinates":[-82.072076,35.917175],"type":"Point"}
}