{
  "type": "Feature",
  "properties": {
    "addr:full":"101 N Smithfield Rd Knightdale NC 27545",
    "addr:housenumber":"101",
    "addr:postcode":"27545",
    "addr:street":"N Smithfield Rd",
    "iso:country":"US",
    "sg:address":"101 N Smithfield Rd",
    "sg:city":"Knightdale",
    "sg:classifiers":[
        {
            "category":"Organizations",
            "subcategory":"Religious Organization",
            "type":"Services"
        }
    ],
    "sg:phone":"+1 919 261 9899",
    "sg:postcode":"27545",
    "sg:province":"NC",
    "sg:tags":[
        "church"
    ],
    "wof:name":"Breakthru Tabernacle",
    "wof:placetype":"venue"
},
  "geometry": {"coordinates":[-78.48231199999999,35.787896],"type":"Point"}
}