{
  "type": "Feature",
  "properties": {
    "addr:full":"4325 Glenwood Ave Raleigh NC 27612",
    "addr:housenumber":"4325",
    "addr:postcode":"27612",
    "addr:street":"Glenwood Ave",
    "iso:country":"US",
    "sg:address":"4325 Glenwood Ave",
    "sg:city":"Raleigh",
    "sg:classifiers":[
        {
            "category":"Shopping",
            "subcategory":"Jewelry",
            "type":"Retail Goods"
        }
    ],
    "sg:phone":"+1 919 787 6147",
    "sg:postcode":"27612",
    "sg:province":"NC",
    "sg:tags":[
        "store"
    ],
    "wof:name":"Zales Jewelers",
    "wof:placetype":"venue"
},
  "geometry": {"coordinates":[-78.677879,35.840788],"type":"Point"}
}