{
  "type": "Feature",
  "properties": {
    "addr:full":"367 Centennial Rd Rutherfordton NC 28139",
    "addr:housenumber":"367",
    "addr:postcode":"28139",
    "addr:street":"Centennial Rd",
    "iso:country":"US",
    "sg:address":"367 Centennial Rd",
    "sg:city":"Rutherfordton",
    "sg:classifiers":[
        {
            "category":"Professional",
            "subcategory":"Business Services",
            "type":"Services"
        }
    ],
    "sg:phone":"+1   ",
    "sg:postcode":"28139",
    "sg:province":"NC",
    "wof:name":"Etec Enterprises",
    "wof:placetype":"venue"
},
  "geometry": {"coordinates":[-81.887822,35.460824],"type":"Point"}
}