{
  "type": "Feature",
  "properties": {
    "iso:country":"US",
    "sg:address":"9613 Grove Crest Ln",
    "sg:city":"Charlotte",
    "sg:classifiers":[
        {
            "category":"Manufacturing",
            "subcategory":"Chemicals & Compounds",
            "type":"Manufacturing & Wholesale Goods"
        }
    ],
    "sg:phone":"+1 704 510 0977",
    "sg:postcode":"28262",
    "sg:province":"NC",
    "sg:tags":[
        "dye",
        "mfg",
        "pigment"
    ],
    "wof:name":"Dyfarben USA Inc",
    "wof:placetype":"venue"
},
  "geometry": {"coordinates":[-80.74664,35.317187],"type":"Point"}
}