{
  "type": "Feature",
  "properties": {
    "iso:country":"US",
    "sg:address":"204 N Sterling St",
    "sg:city":"Morganton",
    "sg:classifiers":[
        {
            "category":"Shopping",
            "subcategory":"Computers & Home Electronics",
            "type":"Retail Goods"
        }
    ],
    "sg:phone":"+1 828 438 9456",
    "sg:postcode":"28655",
    "sg:province":"NC",
    "sg:tags":[
        "hardware",
        "software"
    ],
    "wof:name":"Mountain Micro Systems",
    "wof:placetype":"venue"
},
  "geometry": {"coordinates":[-81.68865700000001,35.745864],"type":"Point"}
}