{
  "type": "Feature",
  "properties": {
    "iso:country":"US",
    "sg:address":"211 W Camden Forest Dr",
    "sg:city":"Cary",
    "sg:classifiers":[
        {
            "category":"Professional",
            "subcategory":"Computer Services",
            "type":"Services"
        }
    ],
    "sg:phone":"+1   ",
    "sg:postcode":"27518",
    "sg:province":"NC",
    "sg:tags":[
        "consulting"
    ],
    "wof:name":"I3 Technology Designers LLC",
    "wof:placetype":"venue"
},
  "geometry": {"coordinates":[-78.753377,35.734065],"type":"Point"}
}