{
  "type": "Feature",
  "properties": {
    "iso:country":"US",
    "sg:address":"148 Fernbrook Dr",
    "sg:city":"Mooresville",
    "sg:classifiers":[
        {
            "category":"Travel",
            "subcategory":"Hotels & Motels",
            "type":"Entertainment"
        }
    ],
    "sg:phone":"+1 704 658 1402",
    "sg:postcode":"28117",
    "sg:province":"NC",
    "wof:name":"Marriott International Inc",
    "wof:placetype":"venue"
},
  "geometry": {"coordinates":[-80.88997999999999,35.577224],"type":"Point"}
}