{
  "type": "Feature",
  "properties": {
    "addr:full":"1008 Mulberry Rd Clayton NC 27520",
    "addr:housenumber":"1008",
    "addr:postcode":"27520",
    "addr:street":"Mulberry Rd",
    "iso:country":"US",
    "sg:address":"1008 Mulberry Rd",
    "sg:city":"Clayton",
    "sg:classifiers":[
        {
            "category":"Professional",
            "subcategory":"Computer Services",
            "type":"Services"
        }
    ],
    "sg:phone":"+1 919 219 0451",
    "sg:postcode":"27520",
    "sg:province":"NC",
    "sg:tags":[
        "website",
        "design"
    ],
    "wof:name":"Cereberus Web Design",
    "wof:placetype":"venue"
},
  "geometry": {"coordinates":[-78.49054700000001,35.65594],"type":"Point"}
}