{
  "type": "Feature",
  "properties": {
    "iso:country":"US",
    "sg:address":"5481 State Hwy 226",
    "sg:city":"Bakersville",
    "sg:classifiers":[
        {
            "category":"Personal",
            "subcategory":"Beauty Salon",
            "type":"Services"
        }
    ],
    "sg:phone":"+1 828 688 3564",
    "sg:postcode":"28705",
    "sg:province":"NC",
    "wof:name":"Hair Affair",
    "wof:placetype":"venue"
},
  "geometry": {"coordinates":[-82.111137,35.961902],"type":"Point"}
}