{
  "type": "Feature",
  "properties": {
    "iso:country":"US",
    "sg:address":"2709 Lab Ln",
    "sg:city":"Burlington",
    "sg:classifiers":[
        {
            "category":"Professional",
            "type":"Services"
        },
        {
            "category":"Building & Trades",
            "subcategory":"Construction",
            "type":"Services"
        }
    ],
    "sg:phone":"+1 336 584 4444",
    "sg:postcode":"27217",
    "sg:province":"NC",
    "sg:tags":[
        "coping",
        "plastering",
        "tiling",
        "pool",
        "swimming"
    ],
    "wof:name":"David Bristow's Pool Svc & Rpr",
    "wof:placetype":"venue"
},
  "geometry": {"coordinates":[-79.478889,36.216369],"type":"Point"}
}