{
  "type": "Feature",
  "properties": {
    "addr:full":"135 Franklin Farm Rd Franklin NC 28734",
    "addr:housenumber":"135",
    "addr:postcode":"nc 28734",
    "addr:street":"Franklin Farm Rd",
    "iso:country":"US",
    "sg:address":"135 Franklin Farm Rd",
    "sg:city":"Franklin",
    "sg:classifiers":[
        {
            "category":"Health Services",
            "subcategory":"Clinic",
            "type":"Services"
        }
    ],
    "sg:phone":"+1 828 349 0529",
    "sg:postcode":"28734",
    "sg:province":"NC",
    "sg:tags":[
        "home",
        "merchandise",
        "care"
    ],
    "wof:name":"American Homepatient",
    "wof:placetype":"venue"
},
  "geometry": {"coordinates":[-83.326905,35.212298],"type":"Point"}
}