{
  "type": "Feature",
  "properties": {
    "addr:full":"607 N Central Ave Locust NC 28097",
    "addr:housenumber":"607",
    "addr:postcode":"28097",
    "addr:street":"N Central Ave",
    "iso:country":"US",
    "sg:address":"607 N Central Ave",
    "sg:city":"Locust",
    "sg:classifiers":[
        {
            "category":"Home & Garden",
            "subcategory":"Furniture",
            "type":"Retail Goods"
        }
    ],
    "sg:phone":"+1 704 598 4455",
    "sg:postcode":"28097",
    "sg:province":"NC",
    "sg:tags":[
        "equipment",
        "kitchen",
        "cabinet"
    ],
    "wof:name":"Normac Kitchens Inc",
    "wof:placetype":"venue"
},
  "geometry": {"coordinates":[-80.42545,35.282639],"type":"Point"}
}