{
  "type": "Feature",
  "properties": {
    "addr:full":"1108 State Hwy 242 N Benson NC 27504",
    "addr:housenumber":"1108",
    "addr:postcode":"27504",
    "addr:street":"State Hwy 242 N",
    "iso:country":"US",
    "sg:address":"1108 State Hwy 242 N",
    "sg:city":"Benson",
    "sg:classifiers":[
        {
            "category":"Food & Beverages",
            "subcategory":"Groceries & Convenience Stores",
            "type":"Retail Goods"
        }
    ],
    "sg:phone":"+1 919 894 3121",
    "sg:postcode":"27504",
    "sg:province":"NC",
    "sg:tags":[
        "grocer"
    ],
    "wof:name":"Country Mart",
    "wof:placetype":"venue"
},
  "geometry": {"coordinates":[-78.543261,35.389104],"type":"Point"}
}