{
  "type": "Feature",
  "properties": {
    "addr:full":"2215 N Marine Blvd Jacksonville NC 28546",
    "addr:housenumber":"2215",
    "addr:postcode":"28546",
    "addr:street":"N Marine Blvd",
    "iso:country":"US",
    "sg:address":"2215 N Marine Blvd",
    "sg:city":"Jacksonville",
    "sg:classifiers":[
        {
            "category":"Autos & Motor Vehicles",
            "subcategory":"Automobile Sales",
            "type":"Retail Goods"
        }
    ],
    "sg:phone":"+1 910 455 1551",
    "sg:postcode":"28546",
    "sg:province":"NC",
    "sg:tags":[
        "car",
        "dealer"
    ],
    "sg:website":"www.lejeunemotorco.com",
    "wof:name":"Lejeune Motor Co-Lincoln Isuzu",
    "wof:placetype":"venue"
},
  "geometry": {"coordinates":[-77.38780800000001,34.780933],"type":"Point"}
}