{
  "type": "Feature",
  "properties": {
    "iso:country":"US",
    "sg:address":"349 Allison Hatchel Ave",
    "sg:city":"Jacksonville",
    "sg:classifiers":[
        {
            "category":"Taxi",
            "type":"Transportation"
        }
    ],
    "sg:phone":"+1 910 346 2772",
    "sg:postcode":"28540",
    "sg:province":"NC",
    "sg:tags":[
        "taxicab"
    ],
    "wof:name":"Star Taxi",
    "wof:placetype":"venue"
},
  "geometry": {"coordinates":[-77.443219,34.741416],"type":"Point"}
}