{
  "type": "Feature",
  "properties": {
    "addr:full":"528 Maple Ln Raleigh NC 27603",
    "addr:housenumber":"528",
    "addr:postcode":"27603",
    "addr:street":"Maple Ln",
    "iso:country":"US",
    "sg:address":"528 Maple Ln",
    "sg:city":"Raleigh",
    "sg:classifiers":[
        {
            "category":"Building & Trades",
            "subcategory":"Cleaning & Sanitation",
            "type":"Services"
        }
    ],
    "sg:phone":"+1   ",
    "sg:postcode":"27603",
    "sg:province":"NC",
    "wof:name":"Boykin Cleaning Services Inc",
    "wof:placetype":"venue"
},
  "geometry": {"coordinates":[-78.644559,35.705035],"type":"Point"}
}