{
  "type": "Feature",
  "properties": {
    "addr:full":"8111 Concord Mills Blvd Concord NC 28027",
    "addr:housenumber":"8111",
    "addr:postcode":"28027",
    "addr:street":"Concord Mills Blvd",
    "iso:country":"US",
    "sg:address":"8111 Concord Mills Blvd",
    "sg:city":"Concord",
    "sg:classifiers":[
        {
            "category":"Professional",
            "type":"Services"
        }
    ],
    "sg:phone":"+1 704 979 1018",
    "sg:postcode":"28027",
    "sg:province":"NC",
    "wof:name":"Natural Success Inc",
    "wof:placetype":"venue"
},
  "geometry": {"coordinates":[-80.71385600000001,35.368795],"type":"Point"}
}