{
  "type": "Feature",
  "properties": {
    "addr:full":"1563 Queens Rd W Charlotte NC 28207",
    "addr:housenumber":"1563",
    "addr:postcode":"28207",
    "addr:street":"Queens Rd W",
    "iso:country":"US",
    "sg:address":"1563 Queens Rd W",
    "sg:city":"Charlotte",
    "sg:classifiers":[
        {
            "category":"Professional",
            "subcategory":"Management & Consulting",
            "type":"Services"
        }
    ],
    "sg:phone":"+1   ",
    "sg:postcode":"28207",
    "sg:province":"NC",
    "wof:name":"Ken Craven",
    "wof:placetype":"venue"
},
  "geometry": {"coordinates":[-80.837408,35.191992],"type":"Point"}
}