{
  "type": "Feature",
  "properties": {
    "iso:country":"US",
    "sg:address":"112 Sidney Green St",
    "sg:city":"Chapel Hill",
    "sg:classifiers":[
        {
            "category":"Personal",
            "subcategory":"Adult",
            "type":"Services"
        }
    ],
    "sg:phone":"+1 919 967 8765",
    "sg:postcode":"27516",
    "sg:province":"NC",
    "sg:tags":[
        "escort"
    ],
    "wof:name":"Inscoe Finishing",
    "wof:placetype":"venue"
},
  "geometry": {"coordinates":[-79.14868300000001,35.879752],"type":"Point"}
}