{
  "type": "Feature",
  "properties": {
    "addr:full":"1146 Abeyance Moncure NC 27559",
    "addr:housenumber":"1146",
    "addr:postcode":"27559",
    "addr:street":"Abeyance Moncure",
    "iso:country":"US",
    "sg:address":"1146 Abeyance",
    "sg:city":"Moncure",
    "sg:classifiers":[
        {
            "category":"Real Estate",
            "subcategory":"Surveying",
            "type":"Services"
        }
    ],
    "sg:phone":"+1 919 545 0180",
    "sg:postcode":"27559",
    "sg:province":"NC",
    "sg:tags":[
        "surveyor"
    ],
    "wof:name":"Derward W Baker & Assoc",
    "wof:placetype":"venue"
},
  "geometry": {"coordinates":[-79.12341000000001,35.668653],"type":"Point"}
}