{
  "type": "Feature",
  "properties": {
    "iso:country":"US",
    "sg:address":"1378 Hendersonville Rd",
    "sg:city":"Asheville",
    "sg:classifiers":[
        {
            "category":"Personal",
            "subcategory":"Beauty Salon",
            "type":"Services"
        }
    ],
    "sg:phone":"+1 828 274 5353",
    "sg:postcode":"28803",
    "sg:province":"NC",
    "sg:website":"www.greatclips.com",
    "wof:name":"Great Clips",
    "wof:placetype":"venue"
},
  "geometry": {"coordinates":[-82.529484,35.522891],"type":"Point"}
}