{
  "type": "Feature",
  "properties": {
    "iso:country":"US",
    "sg:address":"1500 S York Rd",
    "sg:city":"Gastonia",
    "sg:classifiers":[
        {
            "category":"Local Transit",
            "type":"Transportation"
        }
    ],
    "sg:phone":"+1 704 865 3200",
    "sg:postcode":"28052",
    "sg:province":"NC",
    "sg:tags":[
        "passenger"
    ],
    "wof:name":"Grand",
    "wof:placetype":"venue"
},
  "geometry": {"coordinates":[-81.194141,35.24264],"type":"Point"}
}