{
  "type": "Feature",
  "properties": {
    "addr:full":"409 Airport Blvd Ste C100 Morrisville NC 27560",
    "addr:housenumber":"409",
    "addr:postcode":"27560",
    "addr:street":"Airport Blvd Ste C100",
    "iso:country":"US",
    "sg:address":"409 Airport Blvd Ste C100",
    "sg:city":"Morrisville",
    "sg:classifiers":[
        {
            "category":"Food & Beverages",
            "subcategory":"Groceries & Convenience Stores",
            "type":"Retail Goods"
        }
    ],
    "sg:phone":"+1 919 467 1672",
    "sg:postcode":"27560",
    "sg:province":"NC",
    "sg:website":"http://www.wholefoodmarkets.com",
    "wof:name":"Whole Foods Market Group, Inc.",
    "wof:placetype":"venue"
},
  "geometry": {"coordinates":[-78.829536,35.84145],"type":"Point"}
}