{
  "type": "Feature",
  "properties": {
    "addr:full":"624 Old Oxford Rd Durham NC 27704",
    "addr:housenumber":"624",
    "addr:postcode":"27704",
    "addr:street":"Old Oxford Rd",
    "iso:country":"US",
    "sg:address":"624 Old Oxford Rd",
    "sg:city":"Durham",
    "sg:classifiers":[
        {
            "category":"Social Services",
            "subcategory":"Child Care",
            "type":"Services"
        }
    ],
    "sg:phone":"+1   ",
    "sg:postcode":"27704",
    "sg:province":"NC",
    "sg:tags":[
        "day"
    ],
    "wof:name":"Wee Learning Center",
    "wof:placetype":"venue"
},
  "geometry": {"coordinates":[-78.88296,36.040141],"type":"Point"}
}