{
  "type": "Feature",
  "properties": {
    "iso:country":"US",
    "sg:address":"5955 Bridges St",
    "sg:city":"Catawba",
    "sg:classifiers":[
        {
            "category":"Building & Trades",
            "subcategory":"Landscaping Services",
            "type":"Services"
        }
    ],
    "sg:phone":"+1 828 241 2338",
    "sg:postcode":"28609",
    "sg:province":"NC",
    "wof:name":"Browns Landscaping & Design",
    "wof:placetype":"venue"
},
  "geometry": {"coordinates":[-81.05648600000001,35.69275],"type":"Point"}
}