{
  "type": "Feature",
  "properties": {
    "iso:country":"US",
    "sg:address":"3008 Providence Rd",
    "sg:city":"Weddington",
    "sg:classifiers":[
        {
            "category":"Building & Trades",
            "subcategory":"Construction",
            "type":"Services"
        }
    ],
    "sg:phone":"+1 704 849 7981",
    "sg:postcode":"28104",
    "sg:province":"NC",
    "sg:tags":[
        "home",
        "builder"
    ],
    "wof:name":"Parker Lancaster & Orleons",
    "wof:placetype":"venue"
},
  "geometry": {"coordinates":[-80.76463,35.029059],"type":"Point"}
}