{
  "type": "Feature",
  "properties": {
    "addr:full":"2116 Gresham Lake Rd Raleigh NC 27615",
    "addr:housenumber":"2116",
    "addr:postcode":"27615",
    "addr:street":"Gresham Lake Rd",
    "iso:country":"US",
    "sg:address":"2116 Gresham Lake Rd",
    "sg:city":"Raleigh",
    "sg:classifiers":[
        {
            "category":"Real Estate",
            "subcategory":"Real Estate Agent",
            "type":"Services"
        }
    ],
    "sg:phone":"+1 919 873 1120",
    "sg:postcode":"27615",
    "sg:province":"NC",
    "wof:name":"Jennie Closson & Co",
    "wof:placetype":"venue"
},
  "geometry": {"coordinates":[-78.601862,35.886252],"type":"Point"}
}