{
  "type": "Feature",
  "properties": {
    "iso:country":"US",
    "sg:address":"110 Professional Dr",
    "sg:city":"Roanoke Rapids",
    "sg:classifiers":[
        {
            "category":"Health Services",
            "subcategory":"Doctor",
            "type":"Services"
        }
    ],
    "sg:phone":"+1 252 537 0438",
    "sg:postcode":"27870",
    "sg:province":"NC",
    "wof:name":"Peedin Jr C D DDS",
    "wof:placetype":"venue"
},
  "geometry": {"coordinates":[-77.63954099999999,36.442421],"type":"Point"}
}