{
  "type": "Feature",
  "properties": {
    "addr:full":"409 Viverette Ave Battleboro NC 27809",
    "addr:housenumber":"409",
    "addr:postcode":"27809",
    "addr:street":"Viverette Ave",
    "iso:country":"US",
    "sg:address":"409 Viverette Ave",
    "sg:city":"Battleboro",
    "sg:classifiers":[
        {
            "category":"Personal",
            "subcategory":"Beauty Salon",
            "type":"Services"
        }
    ],
    "sg:phone":"+1 252 442 6522",
    "sg:postcode":"27809",
    "sg:province":"NC",
    "wof:name":"E's Unisex Salon",
    "wof:placetype":"venue"
},
  "geometry": {"coordinates":[-77.74215,36.043488],"type":"Point"}
}