{
  "type": "Feature",
  "properties": {
    "addr:full":"1201 Terry Rd SE Winston Salem NC 27107",
    "addr:housenumber":"1201",
    "addr:postcode":"27107",
    "addr:street":"Terry Rd Se",
    "iso:country":"US",
    "sg:address":"1201 Terry Rd SE",
    "sg:city":"Winston Salem",
    "sg:classifiers":[
        {
            "category":"Real Estate",
            "subcategory":"Real Estate Operator",
            "type":"Services"
        }
    ],
    "sg:phone":"+1 336 784 5611",
    "sg:postcode":"27107",
    "sg:province":"NC",
    "sg:tags":[
        "building",
        "apartment"
    ],
    "wof:name":"Salem Garden Apartments",
    "wof:placetype":"venue"
},
  "geometry": {"coordinates":[-80.186038,36.08224],"type":"Point"}
}