{
  "type": "Feature",
  "properties": {
    "iso:country":"US",
    "sg:address":"4288 State Hwy 49 N",
    "sg:city":"Liberty",
    "sg:classifiers":[
        {
            "category":"Shopping",
            "subcategory":"Tobacco",
            "type":"Retail Goods"
        }
    ],
    "sg:phone":"+1 336 622 0318",
    "sg:postcode":"27298",
    "sg:province":"NC",
    "sg:tags":[
        "cigarette",
        "cigar",
        "dealer"
    ],
    "wof:name":"Tobacco & Things",
    "wof:placetype":"venue"
},
  "geometry": {"coordinates":[-79.58160700000001,35.803913],"type":"Point"}
}