{
  "type": "Feature",
  "properties": {
    "addr:full":"6838 Market St Wilmington NC 28405",
    "addr:housenumber":"6838",
    "addr:postcode":"28405",
    "addr:street":"Market St",
    "iso:country":"US",
    "sg:address":"6838 Market St",
    "sg:city":"Wilmington",
    "sg:classifiers":[
        {
            "category":"Shopping",
            "subcategory":"Discount & Variety Stores",
            "type":"Retail Goods"
        }
    ],
    "sg:phone":"+1 910 392 0905",
    "sg:postcode":"28405",
    "sg:province":"NC",
    "wof:name":"Dollar General",
    "wof:placetype":"venue"
},
  "geometry": {"coordinates":[-77.830282,34.26119],"type":"Point"}
}