{
  "type": "Feature",
  "properties": {
    "iso:country":"US",
    "sg:address":"181 Mocksville Hwy",
    "sg:city":"Statesville",
    "sg:classifiers":[
        {
            "category":"Retail",
            "subcategory":"Pet Boarding",
            "type":"Services"
        },
        {
            "category":"Animal Shelter",
            "type":"Public Place"
        },
        {
            "category":"Shopping",
            "subcategory":"Pets & Pet Supplies",
            "type":"Retail Goods"
        },
        {
            "category":"Retail",
            "subcategory":"Veterinary Services",
            "type":"Services"
        },
        {
            "category":"Recreation",
            "subcategory":"Dog Park",
            "type":"Entertainment"
        },
        {
            "category":"Retail",
            "subcategory":"Animal Services",
            "type":"Services"
        }
    ],
    "sg:phone":"+1 704 872 3625",
    "sg:postcode":"28625",
    "sg:province":"NC",
    "sg:tags":[
        "hospital",
        "day",
        "clinic",
        "veterinarian",
        "kennel",
        "store",
        "care"
    ],
    "wof:name":"Animal Hospital Of Statesville",
    "wof:placetype":"venue"
},
  "geometry": {"coordinates":[-80.836861,35.812123],"type":"Point"}
}