{
  "type": "Feature",
  "properties": {
    "addr:full":"1515 Lemmons Rd Walnut Cove NC 27052",
    "addr:housenumber":"1515",
    "addr:postcode":"27052",
    "addr:street":"Lemmons Rd",
    "iso:country":"US",
    "sg:address":"1515 Lemmons Rd",
    "sg:city":"Walnut Cove",
    "sg:classifiers":[
        {
            "category":"Farming",
            "subcategory":"Livestock Farm",
            "type":"Manufacturing & Wholesale Goods"
        }
    ],
    "sg:phone":"+1 336 427 3238",
    "sg:postcode":"27052",
    "sg:province":"NC",
    "sg:tags":[
        "beef",
        "feedlot",
        "cattle"
    ],
    "wof:name":"Durham Herefords Farm",
    "wof:placetype":"venue"
},
  "geometry": {"coordinates":[-80.11244499999999,36.352926],"type":"Point"}
}