{
  "type": "Feature",
  "properties": {
    "iso:country":"US",
    "sg:address":"851 S Laurel St",
    "sg:city":"Lincolnton",
    "sg:classifiers":[
        {
            "category":"Food & Beverages",
            "subcategory":"Groceries & Convenience Stores",
            "type":"Retail Goods"
        }
    ],
    "sg:phone":"+1 704 732 3048",
    "sg:postcode":"28092",
    "sg:province":"NC",
    "wof:name":"Gasland Store 02",
    "wof:placetype":"venue"
},
  "geometry": {"coordinates":[-81.244145,35.467926],"type":"Point"}
}