{
  "type": "Feature",
  "properties": {
    "iso:country":"US",
    "sg:address":"2912 Crosby Rd",
    "sg:city":"Charlotte",
    "sg:classifiers":[
        {
            "category":"Personal",
            "subcategory":"Beauty Salon",
            "type":"Services"
        }
    ],
    "sg:phone":"+1 704 362 6069",
    "sg:postcode":"28211",
    "sg:province":"NC",
    "sg:tags":[
        "manicuring"
    ],
    "wof:name":"Choi Nail Spa",
    "wof:placetype":"venue"
},
  "geometry": {"coordinates":[-80.803907,35.170516],"type":"Point"}
}