{
  "type": "Feature",
  "properties": {
    "iso:country":"US",
    "sg:address":"400 S Center St",
    "sg:city":"Hildebran",
    "sg:classifiers":[
        {
            "category":"Food & Beverages",
            "subcategory":"Groceries & Convenience Stores",
            "type":"Retail Goods"
        }
    ],
    "sg:phone":"+1 828 397 6187",
    "sg:postcode":"28637",
    "sg:province":"NC",
    "wof:name":"Fast Track Convenience Stores",
    "wof:placetype":"venue"
},
  "geometry": {"coordinates":[-81.423017,35.706395],"type":"Point"}
}