{
  "type": "Feature",
  "properties": {
    "iso:country":"US",
    "sg:address":"7150 Yellow Creek Rd",
    "sg:city":"Robbinsville",
    "sg:classifiers":[
        {
            "category":"Shopping",
            "subcategory":"Gifts & Souvenirs",
            "type":"Retail Goods"
        }
    ],
    "sg:phone":"+1 828 479 4084",
    "sg:postcode":"28771",
    "sg:province":"NC",
    "sg:tags":[
        "shop"
    ],
    "wof:name":"Irene's Accessories & Gifts",
    "wof:placetype":"venue"
},
  "geometry": {"coordinates":[-83.86783,35.399178],"type":"Point"}
}