{
  "type": "Feature",
  "properties": {
    "iso:country":"US",
    "sg:address":"4911 Long Beach Rd SE",
    "sg:city":"Southport",
    "sg:classifiers":[
        {
            "category":"Shopping",
            "type":"Retail Goods"
        }
    ],
    "sg:phone":"+1 910 457 6006",
    "sg:postcode":"28461",
    "sg:province":"NC",
    "sg:tags":[
        "merchandise"
    ],
    "wof:name":"Avada Hearing",
    "wof:placetype":"venue"
},
  "geometry": {"coordinates":[-78.049604,33.950426],"type":"Point"}
}