{
  "type": "Feature",
  "properties": {
    "addr:full":"142 Pleasant Hill Rd Cullowhee NC 28721",
    "addr:housenumber":"142",
    "addr:postcode":"28721",
    "addr:street":"Pleasant Hill Rd",
    "iso:country":"US",
    "sg:address":"142 Pleasant Hill Rd",
    "sg:city":"Cullowhee",
    "sg:classifiers":[
        {
            "category":"Organizations",
            "subcategory":"Religious Organization",
            "type":"Services"
        }
    ],
    "sg:phone":"+1 828 349 4075",
    "sg:postcode":"28721",
    "sg:province":"NC",
    "sg:tags":[
        "church"
    ],
    "wof:name":"Pleasant Hill Baptist Church",
    "wof:placetype":"venue"
},
  "geometry": {"coordinates":[-82.90289900000001,35.529781],"type":"Point"}
}