{
  "type": "Feature",
  "properties": {
    "addr:full":"1510 Logan St Durham NC 27704",
    "addr:housenumber":"1510",
    "addr:postcode":"27704",
    "addr:street":"Logan St",
    "iso:country":"US",
    "sg:address":"1510 Logan St",
    "sg:city":"Durham",
    "sg:classifiers":[
        {
            "category":"Farming",
            "subcategory":"Farm",
            "type":"Manufacturing & Wholesale Goods"
        }
    ],
    "sg:phone":"+1 919 682 3275",
    "sg:postcode":"27704",
    "sg:province":"NC",
    "sg:tags":[
        "crop",
        "general"
    ],
    "wof:name":"Mooning Bear Farms",
    "wof:placetype":"venue"
},
  "geometry": {"coordinates":[-78.84979300000001,36.010567],"type":"Point"}
}