{
  "type": "Feature",
  "properties": {
    "iso:country":"US",
    "sg:address":"221 Cranford Stable Rd",
    "sg:city":"Olin",
    "sg:classifiers":[
        {
            "category":"Farming",
            "subcategory":"Livestock Farm",
            "type":"Manufacturing & Wholesale Goods"
        }
    ],
    "sg:phone":"+1 704 539 4423",
    "sg:postcode":"28660",
    "sg:province":"NC",
    "sg:tags":[
        "animal",
        "general"
    ],
    "wof:name":"Flying C Ranch Rodeo LLC",
    "wof:placetype":"venue"
},
  "geometry": {"coordinates":[-80.890698,35.971923],"type":"Point"}
}