{
  "type": "Feature",
  "properties": {
    "iso:country":"US",
    "sg:address":"2730 Bragg Blvd",
    "sg:city":"Fayetteville",
    "sg:classifiers":[
        {
            "category":"Shopping",
            "subcategory":"Shoes",
            "type":"Retail Goods"
        }
    ],
    "sg:phone":"+1 910 223 0467",
    "sg:postcode":"28303",
    "sg:province":"NC",
    "wof:name":"Foot Locker",
    "wof:placetype":"venue"
},
  "geometry": {"coordinates":[-78.92451,35.072852],"type":"Point"}
}