{
  "type": "Feature",
  "properties": {
    "iso:country":"US",
    "sg:address":"1924 Cherryville Rd",
    "sg:city":"Cherryville",
    "sg:classifiers":[
        {
            "category":"Professional",
            "type":"Services"
        }
    ],
    "sg:phone":"+1 704 435 5684",
    "sg:postcode":"28021",
    "sg:province":"NC",
    "sg:tags":[
        "establishment"
    ],
    "wof:name":"Cutting S Edge",
    "wof:placetype":"venue"
},
  "geometry": {"coordinates":[-81.44126,35.353094],"type":"Point"}
}