{
  "type": "Feature",
  "properties": {
    "iso:country":"US",
    "sg:address":"109 South Rd",
    "sg:city":"Chapel Hill",
    "sg:classifiers":[
        {
            "category":"Restaurant",
            "type":"Food & Drink"
        }
    ],
    "sg:phone":"+1 919 942 7713",
    "sg:postcode":"27514",
    "sg:province":"NC",
    "sg:tags":[
        "eating"
    ],
    "wof:name":"Pizza Hut",
    "wof:placetype":"venue"
},
  "geometry": {"coordinates":[-79.042607,35.910807],"type":"Point"}
}