{
  "type": "Feature",
  "properties": {
    "iso:country":"US",
    "sg:address":"504 S Main St",
    "sg:city":"Kernersville",
    "sg:classifiers":[
        {
            "category":"Organizations",
            "subcategory":"Religious Organization",
            "type":"Services"
        }
    ],
    "sg:phone":"+1 336 993 3620",
    "sg:postcode":"27284",
    "sg:province":"NC",
    "wof:name":"Kernersville Moravian Church",
    "wof:placetype":"venue"
},
  "geometry": {"coordinates":[-80.079482,36.115025],"type":"Point"}
}