{
  "type": "Feature",
  "properties": {
    "iso:country":"US",
    "sg:address":"410 Market St",
    "sg:city":"Jacksonville",
    "sg:classifiers":[
        {
            "category":"Banks & Credit Unions",
            "subcategory":"Bank",
            "type":"Services"
        }
    ],
    "sg:phone":"+1 800 411 5522",
    "sg:postcode":"28546",
    "sg:province":"NC",
    "sg:tags":[
        "mortgage"
    ],
    "wof:name":"Centura Securities Inc",
    "wof:placetype":"venue"
},
  "geometry": {"coordinates":[-77.40081000000001,34.766806],"type":"Point"}
}