{
  "type": "Feature",
  "properties": {
    "iso:country":"US",
    "sg:address":"7001 Weston Pkwy",
    "sg:city":"Cary",
    "sg:classifiers":[
        {
            "category":"Manufacturing",
            "subcategory":"Tools & Machinery",
            "type":"Manufacturing & Wholesale Goods"
        }
    ],
    "sg:phone":"+1 919 651 5000",
    "sg:postcode":"27513",
    "sg:province":"NC",
    "sg:tags":[
        "provide",
        "process",
        "datum",
        "software"
    ],
    "wof:name":"Railinc Corp",
    "wof:placetype":"venue"
},
  "geometry": {"coordinates":[-78.790825,35.828911],"type":"Point"}
}