{
  "type": "Feature",
  "properties": {
    "iso:country":"US",
    "sg:address":"4020 Neck Rd",
    "sg:city":"Huntersville",
    "sg:classifiers":[
        {
            "category":"Farming",
            "subcategory":"Livestock Farm",
            "type":"Manufacturing & Wholesale Goods"
        }
    ],
    "sg:phone":"+1 704 875 2216",
    "sg:postcode":"28078",
    "sg:province":"NC",
    "sg:tags":[
        "beef",
        "feedlot",
        "cattle"
    ],
    "wof:name":"Robert Parks",
    "wof:placetype":"venue"
},
  "geometry": {"coordinates":[-80.958237,35.382208],"type":"Point"}
}