{
  "type": "Feature",
  "properties": {
    "addr:full":"1620 Tate Blvd SE Hickory NC 28602",
    "addr:housenumber":"1620",
    "addr:postcode":"28602",
    "addr:street":"Tate Blvd Se",
    "iso:country":"US",
    "sg:address":"1620 Tate Blvd SE",
    "sg:city":"Hickory",
    "sg:classifiers":[
        {
            "category":"Shopping",
            "subcategory":"Clothing, Apparel, & Fashions",
            "type":"Retail Goods"
        }
    ],
    "sg:phone":"+1 828 322 6700",
    "sg:postcode":"28602",
    "sg:province":"NC",
    "sg:tags":[
        "uniform"
    ],
    "wof:name":"Debi's Uniform Of Hickory",
    "wof:placetype":"venue"
},
  "geometry": {"coordinates":[-81.310698,35.729088],"type":"Point"}
}