{
  "type": "Feature",
  "properties": {
    "addr:full":"291 N Green Meadows Dr Wilmington NC 28405",
    "addr:housenumber":"291",
    "addr:postcode":"28405",
    "addr:street":"N Green Meadows Dr",
    "iso:country":"US",
    "sg:address":"291 N Green Meadows Dr",
    "sg:city":"Wilmington",
    "sg:classifiers":[
        {
            "category":"Autos & Motor Vehicles",
            "subcategory":"Boat Sales",
            "type":"Retail Goods"
        }
    ],
    "sg:phone":"+1 910 392 5005",
    "sg:postcode":"28405",
    "sg:province":"NC",
    "sg:tags":[
        "equipment",
        "supply"
    ],
    "wof:name":"Lighthouse Marine Supply Inc",
    "wof:placetype":"venue"
},
  "geometry": {"coordinates":[-77.846214,34.256155],"type":"Point"}
}