{
  "type": "Feature",
  "properties": {
    "iso:country":"US",
    "sg:address":"172 29th Street Pl SW",
    "sg:city":"Hickory",
    "sg:classifiers":[
        {
            "category":"Professional",
            "type":"Services"
        },
        {
            "category":"Organizations",
            "subcategory":"Religious Organization",
            "type":"Services"
        }
    ],
    "sg:phone":"+1 828 431 4463",
    "sg:postcode":"28602",
    "sg:province":"NC",
    "sg:tags":[
        "establishment"
    ],
    "wof:name":"United Associated Churches Dh",
    "wof:placetype":"venue"
},
  "geometry": {"coordinates":[-81.38787600000001,35.727175],"type":"Point"}
}