{
  "type": "Feature",
  "properties": {
    "iso:country":"US",
    "sg:address":"3317 Lemon Springs Rd",
    "sg:city":"Sanford",
    "sg:classifiers":[
        {
            "category":"Personal",
            "type":"Services"
        }
    ],
    "sg:phone":"+1   ",
    "sg:postcode":"27332",
    "sg:province":"NC",
    "wof:name":"Fun Rides & Picnics",
    "wof:placetype":"venue"
},
  "geometry": {"coordinates":[-79.16592300000001,35.439151],"type":"Point"}
}