{
  "type": "Feature",
  "properties": {
    "iso:country":"US",
    "sg:address":"6339 Albemarle Rd",
    "sg:city":"Charlotte",
    "sg:classifiers":[
        {
            "category":"Banks & Credit Unions",
            "subcategory":"Bank",
            "type":"Services"
        }
    ],
    "sg:phone":"+1 704 535 5569",
    "sg:postcode":"28212",
    "sg:province":"NC",
    "sg:tags":[
        "loan"
    ],
    "wof:name":"Nationwide Budget Finance",
    "wof:placetype":"venue"
},
  "geometry": {"coordinates":[-80.73527199999999,35.202913],"type":"Point"}
}