{
  "type": "Feature",
  "properties": {
    "addr:full":"312 Fulcher Landing Rd Sneads Ferry NC 28460",
    "addr:housenumber":"312",
    "addr:postcode":"28460",
    "addr:street":"Fulcher Landing Rd",
    "iso:country":"US",
    "sg:address":"312 Fulcher Landing Rd",
    "sg:city":"Sneads Ferry",
    "sg:classifiers":[
        {
            "category":"Recreation",
            "subcategory":"Marina",
            "type":"Entertainment"
        }
    ],
    "sg:phone":"+1 910 327 2131",
    "sg:postcode":"28460",
    "sg:province":"NC",
    "wof:name":"Parts Cove Marina",
    "wof:placetype":"venue"
},
  "geometry": {"coordinates":[-77.382509,34.564358],"type":"Point"}
}