{
  "type": "Feature",
  "properties": {
    "iso:country":"US",
    "sg:address":"1232 East Blvd",
    "sg:city":"Charlotte",
    "sg:classifiers":[
        {
            "category":"Home & Garden",
            "subcategory":"Furniture",
            "type":"Retail Goods"
        }
    ],
    "sg:phone":"+1 704 375 1888",
    "sg:postcode":"28203",
    "sg:province":"NC",
    "sg:tags":[
        "store"
    ],
    "wof:name":"Cottage Chic",
    "wof:placetype":"venue"
},
  "geometry": {"coordinates":[-80.845659,35.202699],"type":"Point"}
}