{
  "type": "Feature",
  "properties": {
    "addr:full":"1915 Cedar Creek Rd Fayetteville NC 28312",
    "addr:housenumber":"1915",
    "addr:postcode":"28312",
    "addr:street":"Cedar Creek Rd",
    "iso:country":"US",
    "sg:address":"1915 Cedar Creek Rd",
    "sg:city":"Fayetteville",
    "sg:classifiers":[
        {
            "category":"Travel",
            "subcategory":"Hotels & Motels",
            "type":"Entertainment"
        }
    ],
    "sg:phone":"+1 910 433 9090",
    "sg:postcode":"28312",
    "sg:province":"NC",
    "wof:name":"Sleep Inn",
    "wof:placetype":"venue"
},
  "geometry": {"coordinates":[-78.83112300000001,35.010945],"type":"Point"}
}