{
  "type": "Feature",
  "properties": {
    "addr:full":"950 Churchill Downs Ct Charlotte NC 28211",
    "addr:housenumber":"950",
    "addr:postcode":"28211",
    "addr:street":"Churchill Downs Ct",
    "iso:country":"US",
    "sg:address":"950 Churchill Downs Ct",
    "sg:city":"Charlotte",
    "sg:classifiers":[
        {
            "category":"Professional",
            "type":"Services"
        }
    ],
    "sg:phone":"+1 704 442 8327",
    "sg:postcode":"28211",
    "sg:province":"NC",
    "sg:tags":[
        "establishment"
    ],
    "wof:name":"Churchill Downs At Cotswall",
    "wof:placetype":"venue"
},
  "geometry": {"coordinates":[-80.790699,35.187916],"type":"Point"}
}