{
  "type": "Feature",
  "properties": {
    "addr:full":"230 W Academy St Asheboro NC 27203",
    "addr:housenumber":"230",
    "addr:postcode":"27203",
    "addr:street":"W Academy St",
    "iso:country":"US",
    "sg:address":"230 W Academy St",
    "sg:city":"Asheboro",
    "sg:classifiers":[
        {
            "category":"Manufacturing",
            "subcategory":"Lumber",
            "type":"Manufacturing & Wholesale Goods"
        }
    ],
    "sg:phone":"+1 336 629 2828",
    "sg:postcode":"27203",
    "sg:province":"NC",
    "sg:tags":[
        "component",
        "furniture"
    ],
    "sg:website":"www.bhpanel.com",
    "wof:name":"B & H Panel Co",
    "wof:placetype":"venue"
},
  "geometry": {"coordinates":[-79.816642,35.703555],"type":"Point"}
}