{
  "type": "Feature",
  "properties": {
    "addr:full":"123 Kistler Farm Rd Mooresville NC 28115",
    "addr:housenumber":"123",
    "addr:postcode":"28115",
    "addr:street":"Kistler Farm Rd",
    "iso:country":"US",
    "sg:address":"123 Kistler Farm Rd",
    "sg:city":"Mooresville",
    "sg:classifiers":[
        {
            "category":"Retail",
            "subcategory":"Auto Repair",
            "type":"Services"
        }
    ],
    "sg:phone":"+1   ",
    "sg:postcode":"28115",
    "sg:province":"NC",
    "sg:tags":[
        "general"
    ],
    "wof:name":"Select Automotive",
    "wof:placetype":"venue"
},
  "geometry": {"coordinates":[-80.788905,35.560901],"type":"Point"}
}