{
  "type": "Feature",
  "properties": {
    "iso:country":"US",
    "sg:address":"4220 W Sugar Creek Rd",
    "sg:city":"Charlotte",
    "sg:classifiers":[
        {
            "category":"Organizations",
            "subcategory":"Religious Organization",
            "type":"Services"
        }
    ],
    "sg:phone":"+1   ",
    "sg:postcode":"28269",
    "sg:province":"NC",
    "wof:name":"Derita United House Of Prayer",
    "wof:placetype":"venue"
},
  "geometry": {"coordinates":[-80.810766,35.313928],"type":"Point"}
}