{
  "type": "Feature",
  "properties": {
    "addr:full":"8611 Blue Heron Dr Terrell NC 28682",
    "addr:housenumber":"8611",
    "addr:postcode":"28682",
    "addr:street":"Blue Heron Dr",
    "iso:country":"US",
    "sg:address":"8611 Blue Heron Dr",
    "sg:city":"Terrell",
    "sg:classifiers":[
        {
            "category":"Shopping",
            "type":"Retail Goods"
        }
    ],
    "sg:phone":"+1 828 478 9941",
    "sg:postcode":"28682",
    "sg:province":"NC",
    "sg:tags":[
        "merchandise"
    ],
    "wof:name":"Fab Shop LLC",
    "wof:placetype":"venue"
},
  "geometry": {"coordinates":[-80.96289,35.585173],"type":"Point"}
}