{
  "type": "Feature",
  "properties": {
    "addr:full":"110 Smith St Mount Olive NC 28365",
    "addr:housenumber":"110",
    "addr:postcode":"28365",
    "addr:street":"Smith St",
    "iso:country":"US",
    "sg:address":"110 Smith St",
    "sg:city":"Mount Olive",
    "sg:classifiers":[
        {
            "category":"Organizations",
            "subcategory":"Religious Organization",
            "type":"Services"
        }
    ],
    "sg:phone":"+1   ",
    "sg:postcode":"28365",
    "sg:province":"NC",
    "wof:name":"Winn Chapel Missionary",
    "wof:placetype":"venue"
},
  "geometry": {"coordinates":[-78.074173,35.189146],"type":"Point"}
}