{
  "type": "Feature",
  "properties": {
    "addr:full":"106 Park Cir Faison NC 28341",
    "addr:housenumber":"106",
    "addr:postcode":"28341",
    "addr:street":"Park Cir",
    "iso:country":"US",
    "sg:address":"106 Park Cir",
    "sg:city":"Faison",
    "sg:classifiers":[
        {
            "category":"Education",
            "subcategory":"Library",
            "type":"Public Place"
        }
    ],
    "sg:phone":"+1 910 267 0601",
    "sg:postcode":"28341",
    "sg:province":"NC",
    "wof:name":"Faison Library",
    "wof:placetype":"venue"
},
  "geometry": {"coordinates":[-78.140361,35.11952],"type":"Point"}
}