{
  "type": "Feature",
  "properties": {
    "iso:country":"US",
    "sg:address":"730 Long St",
    "sg:city":"East Spencer",
    "sg:classifiers":[
        {
            "category":"Organizations",
            "subcategory":"Religious Organization",
            "type":"Services"
        }
    ],
    "sg:phone":"+1   ",
    "sg:postcode":"28083",
    "sg:province":"NC",
    "wof:name":"Church of God of Prophecy",
    "wof:placetype":"venue"
},
  "geometry": {"coordinates":[-80.61756200000001,35.492222],"type":"Point"}
}