{
  "type": "Feature",
  "properties": {
    "addr:full":"632 Charlotte Ave Sanford NC 27330",
    "addr:housenumber":"632",
    "addr:postcode":"27330",
    "addr:street":"Charlotte Ave",
    "iso:country":"US",
    "sg:address":"632 Charlotte Ave",
    "sg:city":"Sanford",
    "sg:classifiers":[
        {
            "category":"Food & Beverages",
            "subcategory":"Groceries & Convenience Stores",
            "type":"Retail Goods"
        }
    ],
    "sg:phone":"+1 919 777 9922",
    "sg:postcode":"27330",
    "sg:province":"NC",
    "wof:name":"Mi Bandera",
    "wof:placetype":"venue"
},
  "geometry": {"coordinates":[-79.161554,35.484663],"type":"Point"}
}