{
  "type": "Feature",
  "properties": {
    "addr:full":"265 Racine Dr Wilmington NC 28403",
    "addr:housenumber":"265",
    "addr:postcode":"28403",
    "addr:street":"Racine Dr",
    "iso:country":"US",
    "sg:address":"265 Racine Dr",
    "sg:city":"Wilmington",
    "sg:classifiers":[
        {
            "category":"Banks & Credit Unions",
            "subcategory":"Investment Brokerage",
            "type":"Services"
        }
    ],
    "sg:phone":"+1 910 798 4747",
    "sg:postcode":"28403",
    "sg:province":"NC",
    "sg:tags":[
        "consultant",
        "planning",
        "financial"
    ],
    "wof:name":"Starr Financial Resources",
    "wof:placetype":"venue"
},
  "geometry": {"coordinates":[-77.86357700000001,34.241495],"type":"Point"}
}