{
  "type": "Feature",
  "properties": {
    "addr:full":"1130 Marlborough Rd Raleigh NC 27610",
    "addr:housenumber":"1130",
    "addr:postcode":"27610",
    "addr:street":"Marlborough Rd",
    "iso:country":"US",
    "sg:address":"1130 Marlborough Rd",
    "sg:city":"Raleigh",
    "sg:classifiers":[
        {
            "category":"Education",
            "subcategory":"School",
            "type":"Public Place"
        }
    ],
    "sg:phone":"+1 919 856 7737",
    "sg:postcode":"27610",
    "sg:province":"NC",
    "sg:tags":[
        "elementary"
    ],
    "wof:name":"Powell Elementary School",
    "wof:placetype":"venue"
},
  "geometry": {"coordinates":[-78.60444699999999,35.795608],"type":"Point"}
}