{
  "type": "Feature",
  "properties": {
    "addr:full":"316 E Lewis St Whiteville NC 28472",
    "addr:housenumber":"316",
    "addr:postcode":"28472",
    "addr:street":"E Lewis St",
    "iso:country":"US",
    "sg:address":"316 E Lewis St",
    "sg:city":"Whiteville",
    "sg:classifiers":[
        {
            "category":"Building & Trades",
            "subcategory":"Electrical",
            "type":"Services"
        }
    ],
    "sg:phone":"+1 910 642 2180",
    "sg:postcode":"28472",
    "sg:province":"NC",
    "sg:tags":[
        "electrical",
        "contractor"
    ],
    "wof:name":"Waccamaw Electric Co Inc",
    "wof:placetype":"venue"
},
  "geometry": {"coordinates":[-78.697175,34.329626],"type":"Point"}
}