{
  "type": "Feature",
  "properties": {
    "iso:country":"US",
    "sg:address":"1128 Tomlinson Blvd",
    "sg:city":"New Bern",
    "sg:classifiers":[
        {
            "category":"Real Estate",
            "subcategory":"Real Estate Operator",
            "type":"Services"
        }
    ],
    "sg:phone":"+1 252 635 6800",
    "sg:postcode":"28562",
    "sg:province":"NC",
    "sg:tags":[
        "building",
        "apartment"
    ],
    "wof:name":"Academy Common Apts",
    "wof:placetype":"venue"
},
  "geometry": {"coordinates":[-77.121019,35.098382],"type":"Point"}
}