{
  "type": "Feature",
  "properties": {
    "addr:full":"409 Gatewood Ave High Point NC 27262",
    "addr:housenumber":"409",
    "addr:postcode":"27262",
    "addr:street":"Gatewood Ave",
    "iso:country":"US",
    "sg:address":"409 Gatewood Ave",
    "sg:city":"High Point",
    "sg:classifiers":[
        {
            "category":"Arts & Performance",
            "subcategory":"Theater",
            "type":"Entertainment"
        }
    ],
    "sg:phone":"+1 336 885 6465",
    "sg:postcode":"27262",
    "sg:province":"NC",
    "sg:tags":[
        "clown"
    ],
    "wof:name":"A Mile Of Smiles Entertainment",
    "wof:placetype":"venue"
},
  "geometry": {"coordinates":[-80.015539,35.958944],"type":"Point"}
}