{
  "type": "Feature",
  "properties": {
    "iso:country":"US",
    "sg:address":"1012 S Garnett St",
    "sg:city":"Henderson",
    "sg:classifiers":[
        {
            "category":"Travel",
            "subcategory":"Hotels & Motels",
            "type":"Entertainment"
        }
    ],
    "sg:phone":"+1 252 438 4825",
    "sg:postcode":"27536",
    "sg:province":"NC",
    "wof:name":"Little Hotel",
    "wof:placetype":"venue"
},
  "geometry": {"coordinates":[-78.411636,36.321742],"type":"Point"}
}