{
  "type": "Feature",
  "properties": {
    "addr:full":"565 Morton Ave Asheboro NC 27205",
    "addr:housenumber":"565",
    "addr:postcode":"27205",
    "addr:street":"Morton Ave",
    "iso:country":"US",
    "sg:address":"565 Morton Ave",
    "sg:city":"Asheboro",
    "sg:classifiers":[
        {
            "category":"Building & Trades",
            "subcategory":"Construction",
            "type":"Services"
        }
    ],
    "sg:phone":"+1 336 629 0266",
    "sg:postcode":"27205",
    "sg:province":"NC",
    "sg:tags":[
        "heavy"
    ],
    "wof:name":"Jcs Enterprises",
    "wof:placetype":"venue"
},
  "geometry": {"coordinates":[-79.81638599999999,35.669255],"type":"Point"}
}