{
  "type": "Feature",
  "properties": {
    "iso:country":"US",
    "sg:address":"1602 National Hwy",
    "sg:city":"Thomasville",
    "sg:classifiers":[
        {
            "category":"Restaurant",
            "type":"Food & Drink"
        }
    ],
    "sg:phone":"+1 336 885 7588",
    "sg:postcode":"27360",
    "sg:province":"NC",
    "sg:tags":[
        "eating"
    ],
    "wof:name":"China City",
    "wof:placetype":"venue"
},
  "geometry": {"coordinates":[-80.062274,35.908027],"type":"Point"}
}