{
  "type": "Feature",
  "properties": {
    "iso:country":"US",
    "sg:address":"635 Carl Eller Rd",
    "sg:city":"Mars Hill",
    "sg:classifiers":[
        {
            "category":"Shopping",
            "type":"Retail Goods"
        },
        {
            "category":"Shopping",
            "subcategory":"Computers & Home Electronics",
            "type":"Retail Goods"
        }
    ],
    "sg:phone":"+1 828 689 4905",
    "sg:postcode":"28754",
    "sg:province":"NC",
    "sg:tags":[
        "repair",
        "electrical",
        "telephone",
        "cellular"
    ],
    "wof:name":"Radio Shack",
    "wof:placetype":"venue"
},
  "geometry": {"coordinates":[-82.546134,35.825131],"type":"Point"}
}