{
  "type": "Feature",
  "properties": {
    "addr:full":"11307 Albemarle Rd Charlotte NC 28227",
    "addr:housenumber":"11307",
    "addr:postcode":"28227",
    "addr:street":"Albemarle Rd",
    "iso:country":"US",
    "sg:address":"11307 Albemarle Rd",
    "sg:city":"Charlotte",
    "sg:classifiers":[
        {
            "category":"Utilities",
            "subcategory":"Refuse",
            "type":"Services"
        }
    ],
    "sg:phone":"+1 704 393 6900",
    "sg:postcode":"28227",
    "sg:province":"NC",
    "sg:tags":[
        "garbage",
        "collection"
    ],
    "wof:name":"BFI",
    "wof:placetype":"venue"
},
  "geometry": {"coordinates":[-80.65899,35.214708],"type":"Point"}
}