{
  "type": "Feature",
  "properties": {
    "addr:full":"5630 Six Forks Rd Raleigh NC 27609",
    "addr:housenumber":"5630",
    "addr:postcode":"27609",
    "addr:street":"Six Forks Rd",
    "iso:country":"US",
    "sg:address":"5630 Six Forks Rd",
    "sg:city":"Raleigh",
    "sg:classifiers":[
        {
            "category":"Personal",
            "subcategory":"Beauty Salon",
            "type":"Services"
        }
    ],
    "sg:phone":"+1 919 876 0969",
    "sg:postcode":"27609",
    "sg:province":"NC",
    "wof:name":"Montage Hair Design & Day Spa",
    "wof:placetype":"venue"
},
  "geometry": {"coordinates":[-78.640462,35.857048],"type":"Point"}
}