{
  "type": "Feature",
  "properties": {
    "addr:full":"1800 Perimeter Park Ste 140 Morrisville NC 27560",
    "addr:housenumber":"1800",
    "addr:postcode":"27560",
    "addr:street":"Perimeter Park Ste 140",
    "iso:country":"US",
    "sg:address":"1800 Perimeter Park Ste 140",
    "sg:city":"Morrisville",
    "sg:classifiers":[
        {
            "category":"Education",
            "subcategory":"Special Training",
            "type":"Public Place"
        }
    ],
    "sg:phone":"+1 919 674 3100",
    "sg:postcode":"27560",
    "sg:province":"NC",
    "sg:tags":[
        "adult"
    ],
    "sg:website":"www.fastlaneus.com",
    "wof:name":"Fast Lane Consulting & Education Services",
    "wof:placetype":"venue"
},
  "geometry": {"coordinates":[-78.830127,35.853412],"type":"Point"}
}