{
  "type": "Feature",
  "properties": {
    "iso:country":"US",
    "sg:address":"4925 Thoreau Dr",
    "sg:city":"Conover",
    "sg:classifiers":[
        {
            "category":"Professional",
            "subcategory":"Computer Services",
            "type":"Services"
        }
    ],
    "sg:phone":"+1 828 459 2098",
    "sg:postcode":"28613",
    "sg:province":"NC",
    "sg:tags":[
        "e",
        "programing",
        "custom"
    ],
    "wof:name":"PC Systems",
    "wof:placetype":"venue"
},
  "geometry": {"coordinates":[-81.184319,35.768377],"type":"Point"}
}