{
  "type": "Feature",
  "properties": {
    "addr:full":"2518 Fayetteville Rd Durham NC 27707",
    "addr:housenumber":"2518",
    "addr:postcode":"27707",
    "addr:street":"Fayetteville Rd",
    "iso:country":"US",
    "sg:address":"2518 Fayetteville Rd",
    "sg:city":"Durham",
    "sg:classifiers":[
        {
            "category":"Personal",
            "subcategory":"Beauty Salon",
            "type":"Services"
        }
    ],
    "sg:phone":"+1   ",
    "sg:postcode":"27707",
    "sg:province":"NC",
    "sg:tags":[
        "shop"
    ],
    "wof:name":"Vivians Beauty Salon",
    "wof:placetype":"venue"
},
  "geometry": {"coordinates":[-78.902162,35.969479],"type":"Point"}
}