{
  "type": "Feature",
  "properties": {
    "iso:country":"US",
    "sg:address":"2389 Niagara Carthage Rd",
    "sg:city":"Carthage",
    "sg:classifiers":[
        {
            "category":"Bars & Pubs",
            "type":"Food & Drink"
        }
    ],
    "sg:phone":"+1 910 483 3560",
    "sg:postcode":"28327",
    "sg:province":"NC",
    "sg:tags":[
        "drinking"
    ],
    "wof:name":"John Js",
    "wof:placetype":"venue"
},
  "geometry": {"coordinates":[-79.362988,35.279502],"type":"Point"}
}