{
  "type": "Feature",
  "properties": {
    "iso:country":"US",
    "sg:address":"2950 Village Dr",
    "sg:city":"Fayetteville",
    "sg:classifiers":[
        {
            "category":"Professional",
            "type":"Services"
        }
    ],
    "sg:phone":"+1 910 433 9356",
    "sg:postcode":"28304",
    "sg:province":"NC",
    "sg:tags":[
        "establishment"
    ],
    "wof:name":"Offices Consumer Banking",
    "wof:placetype":"venue"
},
  "geometry": {"coordinates":[-78.927136,35.031507],"type":"Point"}
}