{
  "type": "Feature",
  "properties": {
    "addr:full":"701 W 9th St Southport NC 28461",
    "addr:housenumber":"701",
    "addr:postcode":"28461",
    "addr:street":"W 9Th St",
    "iso:country":"US",
    "sg:address":"701 W 9th St",
    "sg:city":"Southport",
    "sg:classifiers":[
        {
            "category":"Education",
            "subcategory":"School",
            "type":"Public Place"
        }
    ],
    "sg:phone":"+1 910 457 6036",
    "sg:postcode":"28461",
    "sg:province":"NC",
    "sg:website":"www.bcswan.net",
    "wof:name":"Southport Elementary After Sch",
    "wof:placetype":"venue"
},
  "geometry": {"coordinates":[-78.03098199999999,33.92629],"type":"Point"}
}