{
  "type": "Feature",
  "properties": {
    "iso:country":"US",
    "sg:address":"6331 Sandy Creek Church Rd",
    "sg:city":"Staley",
    "sg:classifiers":[
        {
            "category":"Farming",
            "subcategory":"Poultry Farm",
            "type":"Manufacturing & Wholesale Goods"
        }
    ],
    "sg:phone":"+1 336 622 2181",
    "sg:postcode":"27355",
    "sg:province":"NC",
    "sg:tags":[
        "chicken",
        "egg"
    ],
    "wof:name":"Jeff & Jennifer Ambrose",
    "wof:placetype":"venue"
},
  "geometry": {"coordinates":[-79.597482,35.821207],"type":"Point"}
}