{
  "type": "Feature",
  "properties": {
    "addr:full":"1167 Bland Howell Rd Kinston NC 28504",
    "addr:housenumber":"1167",
    "addr:postcode":"28504",
    "addr:street":"Bland Howell Rd",
    "iso:country":"US",
    "sg:address":"1167 Bland Howell Rd",
    "sg:city":"Kinston",
    "sg:classifiers":[
        {
            "category":"Farming",
            "subcategory":"Livestock Farm",
            "type":"Manufacturing & Wholesale Goods"
        },
        {
            "category":"Farming",
            "subcategory":"Farm & Veterinary Services",
            "type":"Manufacturing & Wholesale Goods"
        }
    ],
    "sg:phone":"+1 252 522 3852",
    "sg:postcode":"28504",
    "sg:province":"NC",
    "sg:tags":[
        "breeder",
        "hog",
        "or",
        "feedlot"
    ],
    "wof:name":"Lenoir Swine Breeders Inc",
    "wof:placetype":"venue"
},
  "geometry": {"coordinates":[-77.70076400000001,35.179674],"type":"Point"}
}