{
  "type": "Feature",
  "properties": {
    "addr:full":"123 Hall Ave Hudson NC 28638",
    "addr:housenumber":"123",
    "addr:postcode":"28638",
    "addr:street":"Hall Ave",
    "iso:country":"US",
    "sg:address":"123 Hall Ave",
    "sg:city":"Hudson",
    "sg:classifiers":[
        {
            "category":"Home & Garden",
            "subcategory":"Furniture",
            "type":"Retail Goods"
        },
        {
            "category":"Wholesale",
            "subcategory":"Furniture",
            "type":"Manufacturing & Wholesale Goods"
        }
    ],
    "sg:phone":"+1 828 728 2691",
    "sg:postcode":"28638",
    "sg:province":"NC",
    "wof:name":"Clark's Furniture",
    "wof:placetype":"venue"
},
  "geometry": {"coordinates":[-81.505679,35.863465],"type":"Point"}
}