{
  "type": "Feature",
  "properties": {
    "iso:country":"US",
    "sg:address":"1650 Pepperchase Dr",
    "sg:city":"Fayetteville",
    "sg:classifiers":[
        {
            "category":"Professional",
            "subcategory":"Business Services",
            "type":"Services"
        }
    ],
    "sg:phone":"+1   ",
    "sg:postcode":"28312",
    "sg:province":"NC",
    "wof:name":"Walker Enterprise",
    "wof:placetype":"venue"
},
  "geometry": {"coordinates":[-78.85003,35.09056],"type":"Point"}
}