{
  "type": "Feature",
  "properties": {
    "addr:full":"512 Pine Ridge Cir Bladenboro NC 28320",
    "addr:housenumber":"512",
    "addr:postcode":"28320",
    "addr:street":"Pine Ridge Cir",
    "iso:country":"US",
    "sg:address":"512 Pine Ridge Cir",
    "sg:city":"Bladenboro",
    "sg:classifiers":[
        {
            "category":"Personal",
            "subcategory":"Beauty Salon",
            "type":"Services"
        }
    ],
    "sg:phone":"+1 910 863 4651",
    "sg:postcode":"28320",
    "sg:province":"NC",
    "wof:name":"Pine Ridge Hair Care",
    "wof:placetype":"venue"
},
  "geometry": {"coordinates":[-78.80398099999999,34.543187],"type":"Point"}
}