{
  "type": "Feature",
  "properties": {
    "addr:full":"71 S Main St Denton NC 27239",
    "addr:housenumber":"71",
    "addr:postcode":"27239",
    "addr:street":"S Main St",
    "iso:country":"US",
    "sg:address":"71 S Main St",
    "sg:city":"Denton",
    "sg:classifiers":[
        {
            "category":"Banks & Credit Unions",
            "subcategory":"Bank",
            "type":"Services"
        }
    ],
    "sg:phone":"+1 336 859 2131",
    "sg:postcode":"27239",
    "sg:province":"NC",
    "wof:name":"Central Carolina Bank",
    "wof:placetype":"venue"
},
  "geometry": {"coordinates":[-80.11294100000001,35.632399],"type":"Point"}
}