{
  "type": "Feature",
  "properties": {
    "addr:full":"791 Sand Ridge Rd Hubert NC 28539",
    "addr:housenumber":"791",
    "addr:postcode":"28539",
    "addr:street":"Sand Ridge Rd",
    "iso:country":"US",
    "sg:address":"791 Sand Ridge Rd",
    "sg:city":"Hubert",
    "sg:classifiers":[
        {
            "category":"Retail",
            "subcategory":"Auto Repair",
            "type":"Services"
        }
    ],
    "sg:phone":"+1 910 326 4635",
    "sg:postcode":"28539",
    "sg:province":"NC",
    "sg:tags":[
        "repairing",
        "automobile"
    ],
    "wof:name":"Sandridge Auto Ctr",
    "wof:placetype":"venue"
},
  "geometry": {"coordinates":[-77.189441,34.666519],"type":"Point"}
}