{
  "type": "Feature",
  "properties": {
    "iso:country":"US",
    "sg:address":"323 S Academy St",
    "sg:city":"Cary",
    "sg:classifiers":[
        {
            "category":"Health Services",
            "subcategory":"Doctor",
            "type":"Services"
        }
    ],
    "sg:phone":"+1   ",
    "sg:postcode":"27511",
    "sg:province":"NC",
    "wof:name":"Glynda Reimann",
    "wof:placetype":"venue"
},
  "geometry": {"coordinates":[-78.781165,35.783813],"type":"Point"}
}