{
  "type": "Feature",
  "properties": {
    "addr:full":"8304 Arborgate Rd Garner NC 27529",
    "addr:housenumber":"8304",
    "addr:postcode":"27529",
    "addr:street":"Arborgate Rd",
    "iso:country":"US",
    "sg:address":"8304 Arborgate Rd",
    "sg:city":"Garner",
    "sg:classifiers":[
        {
            "category":"Real Estate",
            "subcategory":"Real Estate Operator",
            "type":"Services"
        }
    ],
    "sg:phone":"+1 919 779 7044",
    "sg:postcode":"27529",
    "sg:province":"NC",
    "sg:tags":[
        "mobile",
        "home",
        "site"
    ],
    "wof:name":"Mill Run",
    "wof:placetype":"venue"
},
  "geometry": {"coordinates":[-78.628289,35.654808],"type":"Point"}
}