{
  "type": "Feature",
  "properties": {
    "iso:country":"US",
    "sg:address":"2501 Wooten Blvd SW",
    "sg:city":"Wilson",
    "sg:classifiers":[
        {
            "category":"Professional",
            "type":"Services"
        }
    ],
    "sg:phone":"+1 252 293 0669",
    "sg:postcode":"27893",
    "sg:province":"NC",
    "sg:tags":[
        "establishment"
    ],
    "wof:name":"PCI",
    "wof:placetype":"venue"
},
  "geometry": {"coordinates":[-77.94963199999999,35.717315],"type":"Point"}
}