{
  "type": "Feature",
  "properties": {
    "addr:full":"231 Smith Farm Rd Lexington NC 27292",
    "addr:housenumber":"231",
    "addr:postcode":"27292",
    "addr:street":"Smith Farm Rd",
    "iso:country":"US",
    "sg:address":"231 Smith Farm Rd",
    "sg:city":"Lexington",
    "sg:classifiers":[
        {
            "category":"Retail",
            "subcategory":"Auto Repair",
            "type":"Services"
        }
    ],
    "sg:phone":"+1   ",
    "sg:postcode":"27292",
    "sg:province":"NC",
    "sg:tags":[
        "body"
    ],
    "wof:name":"Mikes Automotive",
    "wof:placetype":"venue"
},
  "geometry": {"coordinates":[-80.15577999999999,35.801943],"type":"Point"}
}