{
  "type": "Feature",
  "properties": {
    "iso:country":"US",
    "sg:address":"2148 Old Red Springs Rd",
    "sg:city":"Maxton",
    "sg:classifiers":[
        {
            "category":"Home & Garden",
            "subcategory":"Furniture",
            "type":"Retail Goods"
        }
    ],
    "sg:phone":"+1 910 844 2300",
    "sg:postcode":"28364",
    "sg:province":"NC",
    "sg:tags":[
        "cabinet"
    ],
    "wof:name":"Lambert's Cabinets",
    "wof:placetype":"venue"
},
  "geometry": {"coordinates":[-79.291133,34.757275],"type":"Point"}
}