{
  "type": "Feature",
  "properties": {
    "addr:full":"19676 Peacock Rd Clarendon NC 28432",
    "addr:housenumber":"19676",
    "addr:postcode":"28432",
    "addr:street":"Peacock Rd",
    "iso:country":"US",
    "sg:address":"19676 Peacock Rd",
    "sg:city":"Clarendon",
    "sg:classifiers":[
        {
            "category":"Manufacturing",
            "subcategory":"Lumber",
            "type":"Manufacturing & Wholesale Goods"
        }
    ],
    "sg:phone":"+1 910 653 5662",
    "sg:postcode":"28432",
    "sg:province":"NC",
    "sg:tags":[
        "logging"
    ],
    "wof:name":"Carolina Wood Inc",
    "wof:placetype":"venue"
},
  "geometry": {"coordinates":[-78.785549,34.176055],"type":"Point"}
}