{
  "type": "Feature",
  "properties": {
    "addr:full":"212 Hickory Grove Rd Clinton NC 28328",
    "addr:housenumber":"212",
    "addr:postcode":"28328",
    "addr:street":"Hickory Grove Rd",
    "iso:country":"US",
    "sg:address":"212 Hickory Grove Rd",
    "sg:city":"Clinton",
    "sg:classifiers":[
        {
            "category":"Building & Trades",
            "subcategory":"Construction",
            "type":"Services"
        }
    ],
    "sg:phone":"+1 910 564 5038",
    "sg:postcode":"28328",
    "sg:province":"NC",
    "sg:tags":[
        "house"
    ],
    "wof:name":"Herring Contracting",
    "wof:placetype":"venue"
},
  "geometry": {"coordinates":[-78.435061,35.132331],"type":"Point"}
}