{
  "type": "Feature",
  "properties": {
    "addr:full":"205 Lloyd St Carrboro NC 27510",
    "addr:housenumber":"205",
    "addr:postcode":"27510",
    "addr:street":"Lloyd St",
    "iso:country":"US",
    "sg:address":"205 Lloyd St",
    "sg:city":"Carrboro",
    "sg:classifiers":[
        {
            "category":"Health Services",
            "subcategory":"Clinic",
            "type":"Services"
        }
    ],
    "sg:phone":"+1 919 357 8305",
    "sg:postcode":"27510",
    "sg:province":"NC",
    "sg:tags":[
        "counseling",
        "mental"
    ],
    "sg:website":"www.aberdium5.com",
    "wof:name":"Aberdium5",
    "wof:placetype":"venue"
},
  "geometry": {"coordinates":[-79.069345,35.912377],"type":"Point"}
}