{
  "type": "Feature",
  "properties": {
    "addr:full":"601 E Thomas St Rocky Mount NC 27801",
    "addr:housenumber":"601",
    "addr:postcode":"27801",
    "addr:street":"E Thomas St",
    "iso:country":"US",
    "sg:address":"601 E Thomas St",
    "sg:city":"Rocky Mount",
    "sg:classifiers":[
        {
            "category":"Personal",
            "subcategory":"Beauty Salon",
            "type":"Services"
        }
    ],
    "sg:phone":"+1 252 442 1224",
    "sg:postcode":"27801",
    "sg:province":"NC",
    "sg:tags":[
        "shop"
    ],
    "wof:name":"A G's Hair Image",
    "wof:placetype":"venue"
},
  "geometry": {"coordinates":[-77.78726399999999,35.94217],"type":"Point"}
}