{
  "type": "Feature",
  "properties": {
    "addr:full":"511 W Ehringhaus St Elizabeth City NC 27909",
    "addr:housenumber":"511",
    "addr:postcode":"27909",
    "addr:street":"W Ehringhaus St",
    "iso:country":"US",
    "sg:address":"511 W Ehringhaus St",
    "sg:city":"Elizabeth City",
    "sg:classifiers":[
        {
            "category":"Home & Garden",
            "subcategory":"Hardware",
            "type":"Retail Goods"
        }
    ],
    "sg:phone":"+1 252 338 5685",
    "sg:postcode":"27909",
    "sg:province":"NC",
    "sg:website":"www.acehardware.com",
    "wof:name":"Ace Hardware",
    "wof:placetype":"venue"
},
  "geometry": {"coordinates":[-76.227918,36.296],"type":"Point"}
}