{
  "type": "Feature",
  "properties": {
    "addr:full":"285 Providence Church Rd Randleman NC 27317",
    "addr:housenumber":"285",
    "addr:postcode":"27317",
    "addr:street":"Providence Church Rd",
    "iso:country":"US",
    "sg:address":"285 Providence Church Rd",
    "sg:city":"Randleman",
    "sg:classifiers":[
        {
            "category":"Building & Trades",
            "subcategory":"Construction",
            "type":"Services"
        }
    ],
    "sg:phone":"+1 336 498 2767",
    "sg:postcode":"27317",
    "sg:province":"NC",
    "sg:tags":[
        "house"
    ],
    "wof:name":"Cecil Neil General Contracter",
    "wof:placetype":"venue"
},
  "geometry": {"coordinates":[-79.79215000000001,35.88017],"type":"Point"}
}