{
  "type": "Feature",
  "properties": {
    "iso:country":"US",
    "sg:address":"1021 Washington Ave",
    "sg:city":"Sanford",
    "sg:classifiers":[
        {
            "category":"Organizations",
            "subcategory":"Religious Organization",
            "type":"Services"
        }
    ],
    "sg:phone":"+1 919 776 2614",
    "sg:postcode":"27330",
    "sg:province":"NC",
    "sg:tags":[
        "place",
        "worship",
        "church"
    ],
    "wof:name":"Mt Sinai United Holy Church Inc",
    "wof:placetype":"venue"
},
  "geometry": {"coordinates":[-79.17813099999999,35.470619],"type":"Point"}
}