{
  "type": "Feature",
  "properties": {
    "addr:full":"200 Woodside Dr Havelock NC 28532",
    "addr:housenumber":"200",
    "addr:postcode":"28532",
    "addr:street":"Woodside Dr",
    "iso:country":"US",
    "sg:address":"200 Woodside Dr",
    "sg:city":"Havelock",
    "sg:classifiers":[
        {
            "category":"Restaurant",
            "type":"Food & Drink"
        }
    ],
    "sg:menulink":"http://www.allmenus.com/nc/havelock/137365-subway/menu/",
    "sg:phone":"+1 252 444 1864",
    "sg:postcode":"28532",
    "sg:province":"NC",
    "sg:tags":[
        "american",
        "sandwich"
    ],
    "wof:name":"Subway",
    "wof:placetype":"venue"
},
  "geometry": {"coordinates":[-76.906533,34.897334],"type":"Point"}
}