{
  "type": "Feature",
  "properties": {
    "iso:country":"US",
    "sg:address":"201 N Piedmont Ave",
    "sg:city":"Kings Mountain",
    "sg:classifiers":[
        {
            "category":"Social Services",
            "subcategory":"Child Care",
            "type":"Services"
        }
    ],
    "sg:phone":"+1 704 739 7467",
    "sg:postcode":"28086",
    "sg:province":"NC",
    "sg:tags":[
        "kindergarten",
        "academic",
        "school"
    ],
    "wof:name":"St Matthew's Preschool",
    "wof:placetype":"venue"
},
  "geometry": {"coordinates":[-81.34231699999999,35.244157],"type":"Point"}
}