{
  "type": "Feature",
  "properties": {
    "addr:full":"3324 Shopton Rd Charlotte NC 28217",
    "addr:housenumber":"3324",
    "addr:postcode":"28217",
    "addr:street":"Shopton Rd",
    "iso:country":"US",
    "sg:address":"3324 Shopton Rd",
    "sg:city":"Charlotte",
    "sg:classifiers":[
        {
            "category":"Manufacturing",
            "subcategory":"Watercraft",
            "type":"Manufacturing & Wholesale Goods"
        }
    ],
    "sg:phone":"+1 704 588 4571",
    "sg:postcode":"28217",
    "sg:province":"NC",
    "wof:name":"Select Sanitation",
    "wof:placetype":"venue"
},
  "geometry": {"coordinates":[-80.939662,35.167371],"type":"Point"}
}