{
  "type": "Feature",
  "properties": {
    "addr:full":"1018 E Main St Franklin NC 28734",
    "addr:housenumber":"1018",
    "addr:postcode":"nc 28734",
    "addr:street":"E Main St",
    "iso:country":"US",
    "sg:address":"1018 E Main St",
    "sg:city":"Franklin",
    "sg:classifiers":[
        {
            "category":"Health Services",
            "subcategory":"Doctor",
            "type":"Services"
        }
    ],
    "sg:phone":"+1 828 369 1975",
    "sg:postcode":"28734",
    "sg:province":"NC",
    "sg:tags":[
        "physician",
        "surgeon"
    ],
    "wof:name":"James Lewis MD",
    "wof:placetype":"venue"
},
  "geometry": {"coordinates":[-83.36639,35.192104],"type":"Point"}
}