{
  "type": "Feature",
  "properties": {
    "iso:country":"US",
    "sg:address":"6519 Castle Hayne Rd",
    "sg:city":"Castle Hayne",
    "sg:classifiers":[
        {
            "category":"Building & Trades",
            "subcategory":"Construction",
            "type":"Services"
        }
    ],
    "sg:phone":"+1 910 675 3276",
    "sg:postcode":"28429",
    "sg:province":"NC",
    "sg:tags":[
        "excavation",
        "excavating",
        "contractor",
        "railroad",
        "grading"
    ],
    "wof:name":"T & H Construction",
    "wof:placetype":"venue"
},
  "geometry": {"coordinates":[-77.898779,34.361858],"type":"Point"}
}