{
  "type": "Feature",
  "properties": {
    "iso:country":"US",
    "sg:address":"100 Woodhill Ct",
    "sg:city":"Kitty Hawk",
    "sg:classifiers":[
        {
            "category":"Building & Trades",
            "subcategory":"Construction",
            "type":"Services"
        }
    ],
    "sg:phone":"+1 252 255 1929",
    "sg:postcode":"27949",
    "sg:province":"NC",
    "sg:tags":[
        "residential",
        "designer"
    ],
    "wof:name":"Precision Design & Drafting",
    "wof:placetype":"venue"
},
  "geometry": {"coordinates":[-75.705619,36.075369],"type":"Point"}
}