{
  "type": "Feature",
  "properties": {
    "addr:full":"1009 Maple Ave Burlington NC 27215",
    "addr:housenumber":"1009",
    "addr:postcode":"27215",
    "addr:street":"Maple Ave",
    "iso:country":"US",
    "sg:address":"1009 Maple Ave",
    "sg:city":"Burlington",
    "sg:classifiers":[
        {
            "category":"Manufacturing",
            "subcategory":"Apparel",
            "type":"Manufacturing & Wholesale Goods"
        }
    ],
    "sg:phone":"+1 336 226 9275",
    "sg:postcode":"27215",
    "sg:province":"NC",
    "sg:tags":[
        "distributor",
        "jean",
        "manufacturer"
    ],
    "wof:name":"Gurkin Jeans",
    "wof:placetype":"venue"
},
  "geometry": {"coordinates":[-79.429401,36.083112],"type":"Point"}
}