{
  "type": "Feature",
  "properties": {
    "addr:full":"6303 Carmel Rd Charlotte NC 28226",
    "addr:housenumber":"6303",
    "addr:postcode":"28226",
    "addr:street":"Carmel Rd",
    "iso:country":"US",
    "sg:address":"6303 Carmel Rd",
    "sg:city":"Charlotte",
    "sg:classifiers":[
        {
            "category":"Arts & Performance",
            "subcategory":"Theater",
            "type":"Entertainment"
        }
    ],
    "sg:phone":"+1 704 541 9816",
    "sg:postcode":"28226",
    "sg:province":"NC",
    "sg:tags":[
        "training",
        "pageant",
        "supply"
    ],
    "wof:name":"Miss United States Orgnztn",
    "wof:placetype":"venue"
},
  "geometry": {"coordinates":[-80.84426999999999,35.091524],"type":"Point"}
}