{
  "type": "Feature",
  "properties": {
    "iso:country":"US",
    "sg:address":"4245 State Hwy 133",
    "sg:city":"Rocky Point",
    "sg:classifiers":[
        {
            "category":"Manufacturing",
            "subcategory":"Signs",
            "type":"Manufacturing & Wholesale Goods"
        }
    ],
    "sg:phone":"+1 910 675 9000",
    "sg:postcode":"28457",
    "sg:province":"NC",
    "wof:name":"Majestic Designs",
    "wof:placetype":"venue"
},
  "geometry": {"coordinates":[-77.96126599999999,34.426258],"type":"Point"}
}