{
  "type": "Feature",
  "properties": {
    "addr:full":"220 1st Ave Vanceboro NC 28560",
    "addr:housenumber":"220",
    "addr:postcode":"28560",
    "addr:street":"1St Ave",
    "iso:country":"US",
    "sg:address":"220 1st Ave",
    "sg:city":"Vanceboro",
    "sg:classifiers":[
        {
            "category":"Organizations",
            "subcategory":"Religious Organization",
            "type":"Services"
        }
    ],
    "sg:phone":"+1 252 244 2001",
    "sg:postcode":"28560",
    "sg:province":"NC",
    "sg:tags":[
        "church"
    ],
    "wof:name":"Christian Vanceboro Church",
    "wof:placetype":"venue"
},
  "geometry": {"coordinates":[-77.153813,35.299564],"type":"Point"}
}