{
  "type": "Feature",
  "properties": {
    "addr:full":"20808 N Main St Ste 103 Cornelius NC 28031",
    "addr:housenumber":"20808",
    "addr:postcode":"28031",
    "addr:street":"N Main St Ste 103",
    "iso:country":"US",
    "sg:address":"20808 N Main St Ste 103",
    "sg:city":"Cornelius",
    "sg:classifiers":[
        {
            "category":"Health Services",
            "subcategory":"Doctor",
            "type":"Services"
        }
    ],
    "sg:phone":"+1 704 658 9730",
    "sg:postcode":"28031",
    "sg:province":"NC",
    "sg:tags":[
        "dermatology",
        "physician",
        "surgeons"
    ],
    "wof:name":"Lake Norman Dermatology, P.A.",
    "wof:placetype":"venue"
},
  "geometry": {"coordinates":[-80.857665,35.490908],"type":"Point"}
}