{
  "type": "Feature",
  "properties": {
    "iso:country":"US",
    "sg:address":"2562 US Hwy 70 W",
    "sg:city":"Goldsboro",
    "sg:classifiers":[
        {
            "category":"Manufacturing",
            "subcategory":"Watercraft",
            "type":"Manufacturing & Wholesale Goods"
        }
    ],
    "sg:phone":"+1 919 734 4872",
    "sg:postcode":"27530",
    "sg:province":"NC",
    "sg:tags":[
        "boat"
    ],
    "wof:name":"Mitch Craft Boats",
    "wof:placetype":"venue"
},
  "geometry": {"coordinates":[-78.048653,35.418466],"type":"Point"}
}