{
  "type": "Feature",
  "properties": {
    "iso:country":"US",
    "sg:address":"421 E Virginia Ave",
    "sg:city":"Bessemer City",
    "sg:classifiers":[
        {
            "category":"Wholesale",
            "subcategory":"Hardware",
            "type":"Manufacturing & Wholesale Goods"
        }
    ],
    "sg:phone":"+1 704 629 2999",
    "sg:postcode":"28016",
    "sg:province":"NC",
    "sg:tags":[
        "refrigerating"
    ],
    "wof:name":"Campbell Refrigeration Heating",
    "wof:placetype":"venue"
},
  "geometry": {"coordinates":[-81.277069,35.283543],"type":"Point"}
}