{
  "type": "Feature",
  "properties": {
    "iso:country":"US",
    "sg:address":"316 E Main St",
    "sg:city":"Clayton",
    "sg:classifiers":[
        {
            "category":"Professional",
            "subcategory":"Accounting & Tax Preparation",
            "type":"Services"
        }
    ],
    "sg:phone":"+1   ",
    "sg:postcode":"27520",
    "sg:province":"NC",
    "sg:tags":[
        "return"
    ],
    "wof:name":"William M Becker Pa",
    "wof:placetype":"venue"
},
  "geometry": {"coordinates":[-78.457539,35.651372],"type":"Point"}
}