{
  "type": "Feature",
  "properties": {
    "iso:country":"US",
    "sg:address":"9554 Sparta Rd",
    "sg:city":"Mc Grady",
    "sg:classifiers":[
        {
            "category":"Wholesale",
            "subcategory":"Machinery & Supplies",
            "type":"Manufacturing & Wholesale Goods"
        }
    ],
    "sg:phone":"+1 336 670 3439",
    "sg:postcode":"28649",
    "sg:province":"NC",
    "sg:tags":[
        "equipment",
        "industrial"
    ],
    "wof:name":"Multivac",
    "wof:placetype":"venue"
},
  "geometry": {"coordinates":[-81.20974099999999,36.29696],"type":"Point"}
}