{
  "type": "Feature",
  "properties": {
    "addr:full":"8108 Idlewild Rd Charlotte NC 28227",
    "addr:housenumber":"8108",
    "addr:postcode":"28227",
    "addr:street":"Idlewild Rd",
    "iso:country":"US",
    "sg:address":"8108 Idlewild Rd",
    "sg:city":"Charlotte",
    "sg:classifiers":[
        {
            "category":"Restaurant",
            "type":"Food & Drink"
        }
    ],
    "sg:menulink":"http://www.allmenus.com/nc/charlotte/43240-china-taste/menu/",
    "sg:phone":"+1 704 566 9390",
    "sg:postcode":"28227",
    "sg:province":"NC",
    "sg:tags":[
        "asian",
        "chinese"
    ],
    "wof:name":"China Taste",
    "wof:placetype":"venue"
},
  "geometry": {"coordinates":[-80.728466,35.18441],"type":"Point"}
}