{
  "type": "Feature",
  "properties": {
    "iso:country":"US",
    "sg:address":"329 N Harrison Ave",
    "sg:city":"Cary",
    "sg:classifiers":[
        {
            "category":"Retail",
            "subcategory":"Laundry & Dry Cleaning",
            "type":"Services"
        }
    ],
    "sg:phone":"+1 919 468 2622",
    "sg:postcode":"27513",
    "sg:province":"NC",
    "wof:name":"Acc Cleaners",
    "wof:placetype":"venue"
},
  "geometry": {"coordinates":[-78.783401,35.789398],"type":"Point"}
}