{
  "type": "Feature",
  "properties": {
    "addr:full":"803 Stoney Brook Dr Roanoke Rapids NC 27870",
    "addr:housenumber":"803",
    "addr:postcode":"27870",
    "addr:street":"Stoney Brook Dr",
    "iso:country":"US",
    "sg:address":"803 Stoney Brook Dr",
    "sg:city":"Roanoke Rapids",
    "sg:classifiers":[
        {
            "category":"Real Estate",
            "subcategory":"Real Estate Operator",
            "type":"Services"
        }
    ],
    "sg:phone":"+1 252 308 6995",
    "sg:postcode":"27870",
    "sg:province":"NC",
    "sg:tags":[
        "building",
        "nonresidential"
    ],
    "wof:name":"Og Properties LLC",
    "wof:placetype":"venue"
},
  "geometry": {"coordinates":[-77.63848900000001,36.449189],"type":"Point"}
}