{
  "type": "Feature",
  "properties": {
    "addr:full":"4807 Elder Ave Charlotte NC 28205",
    "addr:housenumber":"4807",
    "addr:postcode":"28205",
    "addr:street":"Elder Ave",
    "iso:country":"US",
    "sg:address":"4807 Elder Ave",
    "sg:city":"Charlotte",
    "sg:classifiers":[
        {
            "category":"Freight",
            "type":"Transportation"
        }
    ],
    "sg:phone":"+1 704 536 5870",
    "sg:postcode":"28205",
    "sg:province":"NC",
    "sg:tags":[
        "piano",
        "moving",
        "organ"
    ],
    "wof:name":"Charlotte Piano Co",
    "wof:placetype":"venue"
},
  "geometry": {"coordinates":[-80.782669,35.191378],"type":"Point"}
}