{
  "type": "Feature",
  "properties": {
    "addr:full":"1907 Rosehill Rd Fayetteville NC 28301",
    "addr:housenumber":"1907",
    "addr:postcode":"28301",
    "addr:street":"Rosehill Rd",
    "iso:country":"US",
    "sg:address":"1907 Rosehill Rd",
    "sg:city":"Fayetteville",
    "sg:classifiers":[
        {
            "category":"Personal",
            "subcategory":"Beauty Salon",
            "type":"Services"
        }
    ],
    "sg:phone":"+1   ",
    "sg:postcode":"28301",
    "sg:province":"NC",
    "sg:tags":[
        "shop"
    ],
    "wof:name":"Contempo Styling Co",
    "wof:placetype":"venue"
},
  "geometry": {"coordinates":[-78.88275,35.083237],"type":"Point"}
}