{
  "type": "Feature",
  "properties": {
    "iso:country":"US",
    "sg:address":"22 Winston St",
    "sg:city":"Thomasville",
    "sg:classifiers":[
        {
            "category":"Banks & Credit Unions",
            "subcategory":"Bank",
            "type":"Services"
        }
    ],
    "sg:phone":"+1 336 475 4663",
    "sg:postcode":"27360",
    "sg:province":"NC",
    "sg:tags":[
        "federal",
        "savings",
        "institution"
    ],
    "wof:name":"First Bank",
    "wof:placetype":"venue"
},
  "geometry": {"coordinates":[-80.084551,35.883416],"type":"Point"}
}