{
  "type": "Feature",
  "properties": {
    "iso:country":"US",
    "sg:address":"7 N Lafayette St",
    "sg:city":"Shelby",
    "sg:classifiers":[
        {
            "category":"Insurance",
            "subcategory":"Insurance Agent",
            "type":"Services"
        }
    ],
    "sg:phone":"+1 704 484 0100",
    "sg:postcode":"28150",
    "sg:province":"NC",
    "wof:name":"AFLAC",
    "wof:placetype":"venue"
},
  "geometry": {"coordinates":[-81.540255,35.291908],"type":"Point"}
}