{
  "type": "Feature",
  "properties": {
    "addr:full":"3926 Bragg Blvd Fayetteville NC 28303",
    "addr:housenumber":"3926",
    "addr:postcode":"28303",
    "addr:street":"Bragg Blvd",
    "iso:country":"US",
    "sg:address":"3926 Bragg Blvd",
    "sg:city":"Fayetteville",
    "sg:classifiers":[
        {
            "category":"Organizations",
            "subcategory":"Religious Organization",
            "type":"Services"
        }
    ],
    "sg:phone":"+1 910 868 7616",
    "sg:postcode":"28303",
    "sg:province":"NC",
    "sg:tags":[
        "church"
    ],
    "wof:name":"Bethel Baptist Church",
    "wof:placetype":"venue"
},
  "geometry": {"coordinates":[-78.939758,35.078531],"type":"Point"}
}