{
  "type": "Feature",
  "properties": {
    "addr:full":"200 Mackenan Dr Cary NC 27511",
    "addr:housenumber":"200",
    "addr:postcode":"27511",
    "addr:street":"Mackenan Dr",
    "iso:country":"US",
    "sg:address":"200 Mackenan Dr",
    "sg:city":"Cary",
    "sg:classifiers":[
        {
            "category":"Manufacturing",
            "subcategory":"Tools & Machinery",
            "type":"Manufacturing & Wholesale Goods"
        }
    ],
    "sg:phone":"+1 919 481 4200",
    "sg:postcode":"27511",
    "sg:province":"NC",
    "sg:tags":[
        "equipment",
        "printing"
    ],
    "sg:website":"www.containergraphics.com",
    "wof:name":"Container Graphics Corp",
    "wof:placetype":"venue"
},
  "geometry": {"coordinates":[-78.80663,35.731225],"type":"Point"}
}