{
  "type": "Feature",
  "properties": {
    "iso:country":"US",
    "sg:address":"701 Carrier Dr",
    "sg:city":"Charlotte",
    "sg:classifiers":[
        {
            "category":"Wholesale",
            "subcategory":"Electrical",
            "type":"Manufacturing & Wholesale Goods"
        }
    ],
    "sg:phone":"+1 704 588 5610",
    "sg:postcode":"28216",
    "sg:province":"NC",
    "sg:tags":[
        "transmission",
        "equipment",
        "power"
    ],
    "sg:website":"www.bostongear.com",
    "wof:name":"Boston Gear",
    "wof:placetype":"venue"
},
  "geometry": {"coordinates":[-80.873311,35.267213],"type":"Point"}
}