{
  "type": "Feature",
  "properties": {
    "iso:country":"US",
    "sg:address":"3777 US Hwy 70 Bus W",
    "sg:city":"Clayton",
    "sg:classifiers":[
        {
            "category":"Real Estate",
            "subcategory":"Real Estate Operator",
            "type":"Services"
        }
    ],
    "sg:phone":"+1 919 934 5159",
    "sg:postcode":"27520",
    "sg:province":"NC",
    "sg:tags":[
        "building",
        "nonresidential"
    ],
    "wof:name":"Byrds Wholesale",
    "wof:placetype":"venue"
},
  "geometry": {"coordinates":[-78.39185000000001,35.563719],"type":"Point"}
}