{
  "type": "Feature",
  "properties": {
    "iso:country":"US",
    "sg:address":"617 W King St",
    "sg:city":"Boone",
    "sg:classifiers":[
        {
            "category":"Shopping",
            "subcategory":"Pharmacy",
            "type":"Retail Goods"
        }
    ],
    "sg:phone":"+1 828 264 3766",
    "sg:postcode":"28607",
    "sg:province":"NC",
    "sg:website":"www.boonedrug.com",
    "wof:name":"Boone Drugs",
    "wof:placetype":"venue"
},
  "geometry": {"coordinates":[-81.683924,36.218602],"type":"Point"}
}