{
  "type": "Feature",
  "properties": {
    "iso:country":"US",
    "sg:address":"3723 Laurel Heights Dr",
    "sg:city":"Morganton",
    "sg:classifiers":[
        {
            "category":"Shopping",
            "subcategory":"Hobbies, Toys, & Games",
            "type":"Retail Goods"
        }
    ],
    "sg:phone":"+1 828 438 6252",
    "sg:postcode":"28655",
    "sg:province":"NC",
    "wof:name":"American Specialty Toy Co",
    "wof:placetype":"venue"
},
  "geometry": {"coordinates":[-81.629482,35.705048],"type":"Point"}
}