{
  "type": "Feature",
  "properties": {
    "addr:full":"1865 Buckeye Rd Elk Park NC 28622",
    "addr:housenumber":"1865",
    "addr:postcode":"28622",
    "addr:street":"Buckeye Rd",
    "iso:country":"US",
    "sg:address":"1865 Buckeye Rd",
    "sg:city":"Elk Park",
    "sg:classifiers":[
        {
            "category":"Building & Trades",
            "subcategory":"Construction",
            "type":"Services"
        }
    ],
    "sg:phone":"+1 828 898 3240",
    "sg:postcode":"28622",
    "sg:province":"NC",
    "sg:tags":[
        "house"
    ],
    "wof:name":"Rattlesnake Mt Const Co",
    "wof:placetype":"venue"
},
  "geometry": {"coordinates":[-81.912808,36.239176],"type":"Point"}
}