{
  "type": "Feature",
  "properties": {
    "iso:country":"US",
    "sg:address":"368 US Hwy 1",
    "sg:city":"Rockingham",
    "sg:classifiers":[
        {
            "category":"Retail",
            "subcategory":"Auto Repair",
            "type":"Services"
        }
    ],
    "sg:phone":"+1 910 997 2971",
    "sg:postcode":"28379",
    "sg:province":"NC",
    "sg:tags":[
        "repairing",
        "automobile"
    ],
    "wof:name":"King Buck",
    "wof:placetype":"venue"
},
  "geometry": {"coordinates":[-79.784812,34.917998],"type":"Point"}
}