{
  "type": "Feature",
  "properties": {
    "addr:full":"214 Nottingham Dr Cary NC 27511",
    "addr:housenumber":"214",
    "addr:postcode":"27511",
    "addr:street":"Nottingham Dr",
    "iso:country":"US",
    "sg:address":"214 Nottingham Dr",
    "sg:city":"Cary",
    "sg:classifiers":[
        {
            "category":"Personal",
            "subcategory":"Beauty Salon",
            "type":"Services"
        }
    ],
    "sg:phone":"+1   ",
    "sg:postcode":"27511",
    "sg:province":"NC",
    "sg:tags":[
        "shop"
    ],
    "wof:name":"Bladez",
    "wof:placetype":"venue"
},
  "geometry": {"coordinates":[-78.741714,35.7678],"type":"Point"}
}