{
  "type": "Feature",
  "properties": {
    "addr:full":"400 Jaslie Dr Cary NC 27518",
    "addr:housenumber":"400",
    "addr:postcode":"27518",
    "addr:street":"Jaslie Dr",
    "iso:country":"US",
    "sg:address":"400 Jaslie Dr",
    "sg:city":"Cary",
    "sg:classifiers":[
        {
            "category":"Home & Garden",
            "subcategory":"Building Materials",
            "type":"Retail Goods"
        }
    ],
    "sg:phone":"+1 919 851 3454",
    "sg:postcode":"27518",
    "sg:province":"NC",
    "sg:tags":[
        "door"
    ],
    "wof:name":"Garage Door Co",
    "wof:placetype":"venue"
},
  "geometry": {"coordinates":[-78.75981899999999,35.740469],"type":"Point"}
}