{
  "type": "Feature",
  "properties": {
    "iso:country":"US",
    "sg:address":"1603 S Church St",
    "sg:city":"Burlington",
    "sg:classifiers":[
        {
            "category":"Autos & Motor Vehicles",
            "subcategory":"Motorcycle Sales",
            "type":"Retail Goods"
        }
    ],
    "sg:phone":"+1 336 227 9001",
    "sg:postcode":"27215",
    "sg:province":"NC",
    "sg:tags":[
        "scooter"
    ],
    "wof:name":"Chrome Alley",
    "wof:placetype":"venue"
},
  "geometry": {"coordinates":[-79.458957,36.083256],"type":"Point"}
}