{
  "type": "Feature",
  "properties": {
    "iso:country":"US",
    "sg:address":"3776 Hayfield Rd",
    "sg:city":"Wade",
    "sg:classifiers":[
        {
            "category":"Organizations",
            "subcategory":"Religious Organization",
            "type":"Services"
        }
    ],
    "sg:phone":"+1 910 323 3603",
    "sg:postcode":"28395",
    "sg:province":"NC",
    "sg:tags":[
        "church"
    ],
    "wof:name":"Four Point Church Of God",
    "wof:placetype":"venue"
},
  "geometry": {"coordinates":[-78.708855,35.112698],"type":"Point"}
}