{
  "type": "Feature",
  "properties": {
    "addr:full":"345 S Elm St Greensboro NC 27401",
    "addr:housenumber":"345",
    "addr:postcode":"27401",
    "addr:street":"S Elm St",
    "iso:country":"US",
    "sg:address":"345 S Elm St",
    "sg:city":"Greensboro",
    "sg:classifiers":[
        {
            "category":"Restaurant",
            "type":"Food & Drink"
        }
    ],
    "sg:phone":"+1 336 279 8488",
    "sg:postcode":"27401",
    "sg:province":"NC",
    "sg:tags":[
        "eating"
    ],
    "wof:name":"Paisley Pineapple",
    "wof:placetype":"venue"
},
  "geometry": {"coordinates":[-79.790481,36.069097],"type":"Point"}
}