{
  "type": "Feature",
  "properties": {
    "iso:country":"US",
    "sg:address":"2921 Moser Ln",
    "sg:city":"Burlington",
    "sg:classifiers":[
        {
            "category":"Building & Trades",
            "subcategory":"Construction",
            "type":"Services"
        }
    ],
    "sg:phone":"+1 336 229 7973",
    "sg:postcode":"27215",
    "sg:province":"NC",
    "sg:tags":[
        "house"
    ],
    "wof:name":"Kennith W Russell Construction",
    "wof:placetype":"venue"
},
  "geometry": {"coordinates":[-79.44978500000001,36.024904],"type":"Point"}
}