{
  "type": "Feature",
  "properties": {
    "iso:country":"US",
    "sg:address":"12910 State Hwy 210 S",
    "sg:city":"Roseboro",
    "sg:classifiers":[
        {
            "category":"Farming",
            "subcategory":"Livestock Farm",
            "type":"Manufacturing & Wholesale Goods"
        }
    ],
    "sg:phone":"+1 910 531 3470",
    "sg:postcode":"28390",
    "sg:province":"NC",
    "sg:tags":[
        "hog",
        "or",
        "feedlot"
    ],
    "wof:name":"Murphy Brown Hog Farm",
    "wof:placetype":"venue"
},
  "geometry": {"coordinates":[-78.931686,35.240558],"type":"Point"}
}