{
  "type": "Feature",
  "properties": {
    "iso:country":"US",
    "sg:address":"78 Cabe Cove Rd",
    "sg:city":"Franklin",
    "sg:classifiers":[
        {
            "category":"Autos & Motor Vehicles",
            "subcategory":"Boat Sales",
            "type":"Retail Goods"
        }
    ],
    "sg:phone":"+1 828 369 0406",
    "sg:postcode":"28734",
    "sg:province":"NC",
    "sg:tags":[
        "top",
        "upholstery",
        "cover"
    ],
    "wof:name":"Canvasmasters",
    "wof:placetype":"venue"
},
  "geometry": {"coordinates":[-83.51259899999999,35.279252],"type":"Point"}
}