{
  "type": "Feature",
  "properties": {
    "iso:country":"US",
    "sg:address":"567 Edwards Church St",
    "sg:city":"State Road",
    "sg:classifiers":[
        {
            "category":"Shopping",
            "subcategory":"Catalog Store",
            "type":"Retail Goods"
        }
    ],
    "sg:phone":"+1 336 874 7212",
    "sg:postcode":"28676",
    "sg:province":"NC",
    "sg:tags":[
        "mail",
        "house"
    ],
    "wof:name":"Mary K Cosmetics",
    "wof:placetype":"venue"
},
  "geometry": {"coordinates":[-80.888903,36.303681],"type":"Point"}
}