{
  "type": "Feature",
  "properties": {
    "addr:full":"1109 Austin Traphill Rd Elkin NC 28621",
    "addr:housenumber":"1109",
    "addr:postcode":"28621",
    "addr:street":"Austin Traphill Rd",
    "iso:country":"US",
    "sg:address":"1109 Austin Traphill Rd",
    "sg:city":"Elkin",
    "sg:classifiers":[
        {
            "category":"Building & Trades",
            "subcategory":"Construction",
            "type":"Services"
        }
    ],
    "sg:phone":"+1 336 835 1494",
    "sg:postcode":"28621",
    "sg:province":"NC",
    "sg:tags":[
        "contractor"
    ],
    "wof:name":"De Celle Post & Beam Inc",
    "wof:placetype":"venue"
},
  "geometry": {"coordinates":[-80.891009,36.259528],"type":"Point"}
}