{
  "type": "Feature",
  "properties": {
    "addr:full":"1350 E Arlington Blvd Greenville NC 27858",
    "addr:housenumber":"1350",
    "addr:postcode":"27858",
    "addr:street":"E Arlington Blvd",
    "iso:country":"US",
    "sg:address":"1350 E Arlington Blvd",
    "sg:city":"Greenville",
    "sg:classifiers":[
        {
            "category":"Shopping",
            "type":"Retail Goods"
        }
    ],
    "sg:phone":"+1 252 321 6988",
    "sg:postcode":"27858",
    "sg:province":"NC",
    "sg:tags":[
        "cosmetic",
        "perfume"
    ],
    "wof:name":"Varicosmetics Pllc",
    "wof:placetype":"venue"
},
  "geometry": {"coordinates":[-77.361251,35.574971],"type":"Point"}
}