{
  "type": "Feature",
  "properties": {
    "addr:full":"302 N Logan St Burlington NC 27217",
    "addr:housenumber":"302",
    "addr:postcode":"27217",
    "addr:street":"N Logan St",
    "iso:country":"US",
    "sg:address":"302 N Logan St",
    "sg:city":"Burlington",
    "sg:classifiers":[
        {
            "category":"Organizations",
            "subcategory":"Religious Organization",
            "type":"Services"
        }
    ],
    "sg:phone":"+1 336 226 4461",
    "sg:postcode":"27217",
    "sg:province":"NC",
    "wof:name":"Hocutt Memorial Baptist Church",
    "wof:placetype":"venue"
},
  "geometry": {"coordinates":[-79.441755,36.104068],"type":"Point"}
}