{
  "type": "Feature",
  "properties": {
    "iso:country":"US",
    "sg:address":"1409 Golden Needles St",
    "sg:city":"Wilkesboro",
    "sg:classifiers":[
        {
            "category":"Professional",
            "subcategory":"Business Services",
            "type":"Services"
        }
    ],
    "sg:phone":"+1 336 667 3579",
    "sg:postcode":"28697",
    "sg:province":"NC",
    "sg:tags":[
        "packaging"
    ],
    "wof:name":"Wilke's Packaging Inc",
    "wof:placetype":"venue"
},
  "geometry": {"coordinates":[-81.180736,36.142663],"type":"Point"}
}