{
  "type": "Feature",
  "properties": {
    "iso:country":"US",
    "sg:address":"212 W Windjammer Rd",
    "sg:city":"Nags Head",
    "sg:classifiers":[
        {
            "category":"Professional",
            "subcategory":"Management & Consulting",
            "type":"Services"
        }
    ],
    "sg:phone":"+1   ",
    "sg:postcode":"27959",
    "sg:province":"NC",
    "sg:tags":[
        "public",
        "relations"
    ],
    "wof:name":"Winning Promotions Inc",
    "wof:placetype":"venue"
},
  "geometry": {"coordinates":[-75.636116,35.96677],"type":"Point"}
}