{
  "type": "Feature",
  "properties": {
    "addr:full":"620 Brownlee Dr SW Concord NC 28025",
    "addr:housenumber":"620",
    "addr:postcode":"28025",
    "addr:street":"Brownlee Dr Sw",
    "iso:country":"US",
    "sg:address":"620 Brownlee Dr SW",
    "sg:city":"Concord",
    "sg:classifiers":[
        {
            "category":"Professional",
            "type":"Services"
        }
    ],
    "sg:phone":"+1 704 786 7667",
    "sg:postcode":"28025",
    "sg:province":"NC",
    "wof:name":"Wm Jessie McDonald",
    "wof:placetype":"venue"
},
  "geometry": {"coordinates":[-80.58951,35.367971],"type":"Point"}
}