{
  "type": "Feature",
  "properties": {
    "iso:country":"US",
    "sg:address":"615 Creech Johnson Rd",
    "sg:city":"Zebulon",
    "sg:classifiers":[
        {
            "category":"Building & Trades",
            "subcategory":"Construction",
            "type":"Services"
        }
    ],
    "sg:phone":"+1 919 269 3522",
    "sg:postcode":"27597",
    "sg:province":"NC",
    "wof:name":"Privette Cable Construction",
    "wof:placetype":"venue"
},
  "geometry": {"coordinates":[-78.249966,35.762114],"type":"Point"}
}