{
  "type": "Feature",
  "properties": {
    "iso:country":"US",
    "sg:address":"4616 Brooklane Dr",
    "sg:city":"Durham",
    "sg:classifiers":[
        {
            "category":"Professional",
            "subcategory":"Business Services",
            "type":"Services"
        }
    ],
    "sg:phone":"+1   ",
    "sg:postcode":"27712",
    "sg:province":"NC",
    "wof:name":"BLT Enterprises of NC Inc",
    "wof:placetype":"venue"
},
  "geometry": {"coordinates":[-78.918173,36.075812],"type":"Point"}
}