{
  "type": "Feature",
  "properties": {
    "addr:full":"1806 Mews Dr Wilmington NC 28405",
    "addr:housenumber":"1806",
    "addr:postcode":"28405",
    "addr:street":"Mews Dr",
    "iso:country":"US",
    "sg:address":"1806 Mews Dr",
    "sg:city":"Wilmington",
    "sg:classifiers":[
        {
            "category":"Professional",
            "subcategory":"Business Services",
            "type":"Services"
        }
    ],
    "sg:phone":"+1 910 256 8232",
    "sg:postcode":"28405",
    "sg:province":"NC",
    "sg:tags":[
        "appraiser"
    ],
    "wof:name":"Koster Group Of N Carolina Inc",
    "wof:placetype":"venue"
},
  "geometry": {"coordinates":[-77.825531,34.226196],"type":"Point"}
}