{
  "type": "Feature",
  "properties": {
    "addr:full":"823 Carrington Dr Charlotte NC 28214",
    "addr:housenumber":"823",
    "addr:postcode":"28214",
    "addr:street":"Carrington Dr",
    "iso:country":"US",
    "sg:address":"823 Carrington Dr",
    "sg:city":"Charlotte",
    "sg:classifiers":[
        {
            "category":"Wholesale",
            "subcategory":"Machinery & Supplies",
            "type":"Manufacturing & Wholesale Goods"
        }
    ],
    "sg:phone":"+1 704 392 3313",
    "sg:postcode":"28214",
    "sg:province":"NC",
    "sg:tags":[
        "equipment",
        "transportation"
    ],
    "wof:name":"Kenneth D Kramer",
    "wof:placetype":"venue"
},
  "geometry": {"coordinates":[-80.95096100000001,35.27639],"type":"Point"}
}