{
  "type": "Feature",
  "properties": {
    "iso:country":"US",
    "sg:address":"132 S College St",
    "sg:city":"Charlotte",
    "sg:phone":"+1 704 625 2689",
    "sg:postcode":"28202",
    "sg:province":"NC",
    "wof:name":"0-15 Minutes Charlotte locksmith",
    "wof:placetype":"venue"
},
  "geometry": {"coordinates":[-80.842341,35.226006],"type":"Point"}
}