{
  "type": "Feature",
  "properties": {
    "iso:country":"US",
    "sg:address":"6647 Falls of Neuse Rd",
    "sg:city":"Raleigh",
    "sg:classifiers":[
        {
            "category":"Shopping",
            "subcategory":"Department Store",
            "type":"Retail Goods"
        }
    ],
    "sg:phone":"+1 919 847 1602",
    "sg:postcode":"27615",
    "sg:province":"NC",
    "sg:website":"www.tjmaxx.com",
    "wof:name":"T J Maxx",
    "wof:placetype":"venue"
},
  "geometry": {"coordinates":[-78.62291,35.874149],"type":"Point"}
}