{
  "type": "Feature",
  "properties": {
    "iso:country":"US",
    "sg:address":"303 Nash St E",
    "sg:city":"Wilson",
    "sg:classifiers":[
        {
            "category":"Organizations",
            "subcategory":"Religious Organization",
            "type":"Services"
        }
    ],
    "sg:phone":"+1   ",
    "sg:postcode":"27893",
    "sg:province":"NC",
    "wof:name":"Miracle Christian Intl Life Ce",
    "wof:placetype":"venue"
},
  "geometry": {"coordinates":[-77.909323,35.724166],"type":"Point"}
}