{
  "type": "Feature",
  "properties": {
    "addr:full":"603 Mount Willing Rd Efland NC 27243",
    "addr:housenumber":"603",
    "addr:postcode":"27243",
    "addr:street":"Mount Willing Rd",
    "iso:country":"US",
    "sg:address":"603 Mount Willing Rd",
    "sg:city":"Efland",
    "sg:classifiers":[
        {
            "category":"Retail",
            "subcategory":"Auto Repair",
            "type":"Services"
        }
    ],
    "sg:phone":"+1 919 732 8063",
    "sg:postcode":"27243",
    "sg:province":"NC",
    "sg:tags":[
        "body",
        "automobile",
        "painting"
    ],
    "wof:name":"Lloyd's Body Shop",
    "wof:placetype":"venue"
},
  "geometry": {"coordinates":[-79.168363,36.066745],"type":"Point"}
}