{
  "type": "Feature",
  "properties": {
    "addr:full":"1440 Yadkinville Rd Mocksville NC 27028",
    "addr:housenumber":"1440",
    "addr:postcode":"27028",
    "addr:street":"Yadkinville Rd",
    "iso:country":"US",
    "sg:address":"1440 Yadkinville Rd",
    "sg:city":"Mocksville",
    "sg:classifiers":[
        {
            "category":"Restaurant",
            "type":"Food & Drink"
        }
    ],
    "sg:menulink":"http://www.allmenus.com/nc/mocksville/211945-mcdonalds/menu/",
    "sg:phone":"+1 363 751 1818",
    "sg:postcode":"27028",
    "sg:province":"NC",
    "sg:tags":[
        "burger",
        "american"
    ],
    "wof:name":"McDonald's",
    "wof:placetype":"venue"
},
  "geometry": {"coordinates":[-80.584503,35.919282],"type":"Point"}
}