{
  "type": "Feature",
  "properties": {
    "addr:full":"817 Broad Ave Greensboro NC 27406",
    "addr:housenumber":"817",
    "addr:postcode":"27406",
    "addr:street":"Broad Ave",
    "iso:country":"US",
    "sg:address":"817 Broad Ave",
    "sg:city":"Greensboro",
    "sg:classifiers":[
        {
            "category":"Building & Trades",
            "subcategory":"Cleaning & Sanitation",
            "type":"Services"
        }
    ],
    "sg:phone":"+1 336 273 1862",
    "sg:postcode":"27406",
    "sg:province":"NC",
    "sg:tags":[
        "janitor"
    ],
    "wof:name":"John Troxler & Son",
    "wof:placetype":"venue"
},
  "geometry": {"coordinates":[-79.77631,36.058971],"type":"Point"}
}