{
  "type": "Feature",
  "properties": {
    "addr:full":"4687 Gallant Ln Winston Salem NC 27101",
    "addr:housenumber":"4687",
    "addr:postcode":"27101",
    "addr:street":"Gallant Ln",
    "iso:country":"US",
    "sg:address":"4687 Gallant Ln",
    "sg:city":"Winston Salem",
    "sg:classifiers":[
        {
            "category":"Building & Trades",
            "subcategory":"Electrical",
            "type":"Services"
        }
    ],
    "sg:phone":"+1 336 725 5154",
    "sg:postcode":"27101",
    "sg:province":"NC",
    "sg:tags":[
        "electrical",
        "contractor"
    ],
    "wof:name":"Ladd Electric Co",
    "wof:placetype":"venue"
},
  "geometry": {"coordinates":[-80.138553,36.143881],"type":"Point"}
}