{
  "type": "Feature",
  "properties": {
    "addr:full":"4105 E Maiden Rd Maiden NC 28650",
    "addr:housenumber":"4105",
    "addr:postcode":"28650",
    "addr:street":"E Maiden Rd",
    "iso:country":"US",
    "sg:address":"4105 E Maiden Rd",
    "sg:city":"Maiden",
    "sg:classifiers":[
        {
            "category":"Retail",
            "subcategory":"Auto Repair",
            "type":"Services"
        }
    ],
    "sg:phone":"+1   ",
    "sg:postcode":"28650",
    "sg:province":"NC",
    "sg:tags":[
        "general"
    ],
    "wof:name":"Little Mountain Automotive",
    "wof:placetype":"venue"
},
  "geometry": {"coordinates":[-81.117645,35.560076],"type":"Point"}
}