{
  "type": "Feature",
  "properties": {
    "addr:full":"103 Bright Sand Ct Cary NC 27519",
    "addr:housenumber":"103",
    "addr:postcode":"27519",
    "addr:street":"Bright Sand Ct",
    "iso:country":"US",
    "sg:address":"103 Bright Sand Ct",
    "sg:city":"Cary",
    "sg:classifiers":[
        {
            "category":"Building & Trades",
            "subcategory":"Construction",
            "type":"Services"
        }
    ],
    "sg:phone":"+1 919 460 8860",
    "sg:postcode":"27519",
    "sg:province":"NC",
    "sg:tags":[
        "contractor"
    ],
    "sg:website":"www.kbhome.com/martha/neighborho...",
    "wof:name":"Twin Lakes Sales Office Kb Homes",
    "wof:placetype":"venue"
},
  "geometry": {"coordinates":[-78.84772,35.831064],"type":"Point"}
}