{
  "type": "Feature",
  "properties": {
    "iso:country":"US",
    "sg:address":"676 Pike Rd",
    "sg:city":"Pantego",
    "sg:classifiers":[
        {
            "category":"Recreation",
            "type":"Entertainment"
        }
    ],
    "sg:phone":"+1 252 935 5415",
    "sg:postcode":"27860",
    "sg:province":"NC",
    "sg:tags":[
        "guide"
    ],
    "wof:name":"Pungo Acres Hunting Retreat",
    "wof:placetype":"venue"
},
  "geometry": {"coordinates":[-76.628608,35.682732],"type":"Point"}
}