{
  "type": "Feature",
  "properties": {
    "iso:country":"US",
    "sg:address":"5908 Prospect St",
    "sg:city":"Archdale",
    "sg:classifiers":[
        {
            "category":"Wholesale",
            "subcategory":"Furniture",
            "type":"Manufacturing & Wholesale Goods"
        }
    ],
    "sg:phone":"+1 336 889 6738",
    "sg:postcode":"27263",
    "sg:province":"NC",
    "wof:name":"Gable Express",
    "wof:placetype":"venue"
},
  "geometry": {"coordinates":[-80.03076299999999,35.908485],"type":"Point"}
}