{
  "type": "Feature",
  "properties": {
    "addr:full":"16 Westminister Dr Jacksonville NC 28540",
    "addr:housenumber":"16",
    "addr:postcode":"28540",
    "addr:street":"Westminister Dr",
    "iso:country":"US",
    "sg:address":"16 Westminister Dr",
    "sg:city":"Jacksonville",
    "sg:classifiers":[
        {
            "category":"Building & Trades",
            "subcategory":"Landscaping Services",
            "type":"Services"
        }
    ],
    "sg:phone":"+1 910 455 9268",
    "sg:postcode":"28540",
    "sg:province":"NC",
    "wof:name":"Gunnys Lawn Care",
    "wof:placetype":"venue"
},
  "geometry": {"coordinates":[-77.42441700000001,34.744892],"type":"Point"}
}