{
  "type": "Feature",
  "properties": {
    "addr:full":"6208 Fayetteville Rd Durham NC 27713",
    "addr:housenumber":"6208",
    "addr:postcode":"27713",
    "addr:street":"Fayetteville Rd",
    "iso:country":"US",
    "sg:address":"6208 Fayetteville Rd",
    "sg:city":"Durham",
    "sg:classifiers":[
        {
            "category":"Real Estate",
            "subcategory":"Real Estate Agent",
            "type":"Services"
        }
    ],
    "sg:phone":"+1 919 806 3262",
    "sg:postcode":"27713",
    "sg:province":"NC",
    "wof:name":"Real Estate Co",
    "wof:placetype":"venue"
},
  "geometry": {"coordinates":[-78.933075,35.913987],"type":"Point"}
}