{
  "type": "Feature",
  "properties": {
    "addr:full":"20401 Zion Ave Cornelius NC 28031",
    "addr:housenumber":"20401",
    "addr:postcode":"28031",
    "addr:street":"Zion Ave",
    "iso:country":"US",
    "sg:address":"20401 Zion Ave",
    "sg:city":"Cornelius",
    "sg:classifiers":[
        {
            "category":"Manufacturing",
            "subcategory":"Metals",
            "type":"Manufacturing & Wholesale Goods"
        }
    ],
    "sg:phone":"+1 704 892 5503",
    "sg:postcode":"28031",
    "sg:province":"NC",
    "sg:tags":[
        "machine",
        "screw",
        "product"
    ],
    "sg:website":"www.curtisscrew.com",
    "wof:name":"Curtis Screw Co",
    "wof:placetype":"venue"
},
  "geometry": {"coordinates":[-80.85685599999999,35.487028],"type":"Point"}
}