{
  "type": "Feature",
  "properties": {
    "iso:country":"US",
    "sg:address":"1025 Regency Dr",
    "sg:city":"Charlotte",
    "sg:classifiers":[
        {
            "category":"Building & Trades",
            "subcategory":"Construction",
            "type":"Services"
        },
        {
            "category":"Building & Trades",
            "subcategory":"Plumbing",
            "type":"Services"
        }
    ],
    "sg:phone":"+1 704 442 5761",
    "sg:postcode":"28211",
    "sg:province":"NC",
    "sg:tags":[
        "bathroom",
        "remodeling",
        "contractor"
    ],
    "wof:name":"Cipriano Plumbing and Til",
    "wof:placetype":"venue"
},
  "geometry": {"coordinates":[-80.76825700000001,35.164687],"type":"Point"}
}