{
  "type": "Feature",
  "properties": {
    "iso:country":"US",
    "sg:address":"228 Hickory Hills Ln",
    "sg:city":"Lexington",
    "sg:classifiers":[
        {
            "category":"Professional",
            "subcategory":"Computer Services",
            "type":"Services"
        }
    ],
    "sg:phone":"+1   ",
    "sg:postcode":"27295",
    "sg:province":"NC",
    "sg:tags":[
        "related"
    ],
    "wof:name":"Ketch Consulting Company",
    "wof:placetype":"venue"
},
  "geometry": {"coordinates":[-80.262103,35.955476],"type":"Point"}
}