{
  "type": "Feature",
  "properties": {
    "iso:country":"US",
    "sg:address":"1994 Adam St",
    "sg:city":"Conover",
    "sg:classifiers":[
        {
            "category":"Building & Trades",
            "subcategory":"Construction",
            "type":"Services"
        }
    ],
    "sg:phone":"+1 828 256 3829",
    "sg:postcode":"28613",
    "sg:province":"NC",
    "sg:tags":[
        "concrete",
        "contractor"
    ],
    "wof:name":"Carrolls Concrete Finishing Co",
    "wof:placetype":"venue"
},
  "geometry": {"coordinates":[-81.257716,35.731073],"type":"Point"}
}