{
  "type": "Feature",
  "properties": {
    "addr:full":"1638 Freedom Mill Rd Gastonia NC 28052",
    "addr:housenumber":"1638",
    "addr:postcode":"28052",
    "addr:street":"Freedom Mill Rd",
    "iso:country":"US",
    "sg:address":"1638 Freedom Mill Rd",
    "sg:city":"Gastonia",
    "sg:classifiers":[
        {
            "category":"Organizations",
            "subcategory":"Religious Organization",
            "type":"Services"
        }
    ],
    "sg:phone":"+1   ",
    "sg:postcode":"28052",
    "sg:province":"NC",
    "wof:name":"Trinity AME Zion Church",
    "wof:placetype":"venue"
},
  "geometry": {"coordinates":[-81.252752,35.184474],"type":"Point"}
}