{
  "type": "Feature",
  "properties": {
    "iso:country":"US",
    "sg:address":"100 Industrial Blvd",
    "sg:city":"Greenville",
    "sg:classifiers":[
        {
            "category":"Retail",
            "subcategory":"Auto Rental",
            "type":"Services"
        }
    ],
    "sg:phone":"+1 252 830 4919",
    "sg:postcode":"27834",
    "sg:province":"NC",
    "sg:tags":[
        "leasing",
        "vehicle"
    ],
    "wof:name":"Ryder",
    "wof:placetype":"venue"
},
  "geometry": {"coordinates":[-77.366821,35.645599],"type":"Point"}
}