{
  "type": "Feature",
  "properties": {
    "addr:full":"6000 Keener Rd Clinton NC 28328",
    "addr:postcode":"6000;28328",
    "addr:street":"Keener Rd",
    "iso:country":"US",
    "sg:address":"6000 Keener Rd",
    "sg:city":"Clinton",
    "sg:classifiers":[
        {
            "category":"Insurance",
            "subcategory":"Insurance Agent",
            "type":"Services"
        }
    ],
    "sg:phone":"+1 910 564 6403",
    "sg:postcode":"28328",
    "sg:province":"NC",
    "sg:tags":[
        "c",
        "general"
    ],
    "wof:name":"Wiggins Insurance Agency",
    "wof:placetype":"venue"
},
  "geometry": {"coordinates":[-78.332185,35.106071],"type":"Point"}
}