{
  "type": "Feature",
  "properties": {
    "iso:country":"US",
    "sg:address":"160 N Main St",
    "sg:city":"Waynesville",
    "sg:classifiers":[
        {
            "category":"Professional",
            "subcategory":"Lawyer & Legal Services",
            "type":"Services"
        }
    ],
    "sg:phone":"+1 828 452 9099",
    "sg:postcode":"28786",
    "sg:province":"NC",
    "sg:tags":[
        "attorney",
        "practice",
        "general"
    ],
    "wof:name":"Decker Wenzel & Wenzel Pllc",
    "wof:placetype":"venue"
},
  "geometry": {"coordinates":[-82.987199,35.491185],"type":"Point"}
}