{
  "type": "Feature",
  "properties": {
    "addr:full":"1005 State Hwy 61 Whitsett NC 27377",
    "addr:housenumber":"1005",
    "addr:postcode":"27377",
    "addr:street":"State Hwy 61",
    "iso:country":"US",
    "sg:address":"1005 State Hwy 61",
    "sg:city":"Whitsett",
    "sg:classifiers":[
        {
            "category":"Organizations",
            "subcategory":"Religious Organization",
            "type":"Services"
        }
    ],
    "sg:phone":"+1 336 449 7682",
    "sg:postcode":"27377",
    "sg:province":"NC",
    "sg:tags":[
        "church"
    ],
    "wof:name":"Cornerstone Baptist Church",
    "wof:placetype":"venue"
},
  "geometry": {"coordinates":[-79.564486,36.064917],"type":"Point"}
}