{
  "type": "Feature",
  "properties": {
    "iso:country":"US",
    "sg:address":"1722 Julian R Allsbrook Hwy",
    "sg:city":"Roanoke Rapids",
    "sg:classifiers":[
        {
            "category":"Shopping",
            "subcategory":"Clothing, Apparel, & Fashions",
            "type":"Retail Goods"
        }
    ],
    "sg:phone":"+1 252 535 4455",
    "sg:postcode":"27870",
    "sg:province":"NC",
    "wof:name":"Sugahill Fashions Inc",
    "wof:placetype":"venue"
},
  "geometry": {"coordinates":[-77.634995,36.432859],"type":"Point"}
}