{
  "type": "Feature",
  "properties": {
    "addr:full":"3209 Guess Rd Durham NC 27705",
    "addr:housenumber":"3209",
    "addr:postcode":"27705",
    "addr:street":"Guess Rd",
    "iso:country":"US",
    "sg:address":"3209 Guess Rd",
    "sg:city":"Durham",
    "sg:classifiers":[
        {
            "category":"Personal",
            "type":"Services"
        },
        {
            "category":"Personal",
            "subcategory":"Beauty Salon",
            "type":"Services"
        }
    ],
    "sg:phone":"+1 919 477 9089",
    "sg:postcode":"27705",
    "sg:province":"NC",
    "wof:name":"Lavandou Spa",
    "wof:placetype":"venue"
},
  "geometry": {"coordinates":[-78.929348,36.034713],"type":"Point"}
}