{
  "type": "Feature",
  "properties": {
    "iso:country":"US",
    "sg:address":"2213 Rocky Ford Rd",
    "sg:city":"Apex",
    "sg:classifiers":[
        {
            "category":"Shopping",
            "type":"Retail Goods"
        }
    ],
    "sg:phone":"+1 919 601 8703",
    "sg:postcode":"27544",
    "sg:province":"NC",
    "sg:tags":[
        "merchandise"
    ],
    "wof:name":"Michelle Bennett",
    "wof:placetype":"venue"
},
  "geometry": {"coordinates":[-78.36699,36.210422],"type":"Point"}
}