{
  "type": "Feature",
  "properties": {
    "addr:full":"3796 Jonathan Creek Rd Waynesville NC 28785",
    "addr:housenumber":"3796",
    "addr:postcode":"28785",
    "addr:street":"Jonathan Creek Rd",
    "iso:country":"US",
    "sg:address":"3796 Jonathan Creek Rd",
    "sg:city":"Waynesville",
    "sg:classifiers":[
        {
            "category":"Building & Trades",
            "subcategory":"Construction",
            "type":"Services"
        }
    ],
    "sg:phone":"+1 828 926 3726",
    "sg:postcode":"28785",
    "sg:province":"NC",
    "sg:tags":[
        "contractor"
    ],
    "wof:name":"Charles 66",
    "wof:placetype":"venue"
},
  "geometry": {"coordinates":[-83.015517,35.574984],"type":"Point"}
}