{
  "type": "Feature",
  "properties": {
    "addr:full":"302 Versailles Dr Cary NC 27511",
    "addr:housenumber":"302",
    "addr:postcode":"27511",
    "addr:street":"Versailles Dr",
    "iso:country":"US",
    "sg:address":"302 Versailles Dr",
    "sg:city":"Cary",
    "sg:classifiers":[
        {
            "category":"Organizations",
            "subcategory":"Professional Association",
            "type":"Services"
        }
    ],
    "sg:phone":"+1 919 463 0333",
    "sg:postcode":"27511",
    "sg:province":"NC",
    "sg:website":"www.aiatriangle.org",
    "wof:name":"AIA Triangle",
    "wof:placetype":"venue"
},
  "geometry": {"coordinates":[-78.810469,35.746665],"type":"Point"}
}