{
  "type": "Feature",
  "properties": {
    "iso:country":"US",
    "sg:address":"108 N 4th St",
    "sg:city":"Mebane",
    "sg:classifiers":[
        {
            "category":"Shopping",
            "subcategory":"Hobbies, Toys, & Games",
            "type":"Retail Goods"
        }
    ],
    "sg:phone":"+1 919 563 7034",
    "sg:postcode":"27302",
    "sg:province":"NC",
    "sg:tags":[
        "model",
        "supply"
    ],
    "wof:name":"Thursday Night Speedway Hobby",
    "wof:placetype":"venue"
},
  "geometry": {"coordinates":[-79.26755900000001,36.096932],"type":"Point"}
}