{
  "type": "Feature",
  "properties": {
    "iso:country":"US",
    "sg:address":"17213 Jetton Rd",
    "sg:city":"Cornelius",
    "sg:classifiers":[
        {
            "category":"Professional",
            "type":"Services"
        }
    ],
    "sg:phone":"+1 704 895 7708",
    "sg:postcode":"28031",
    "sg:province":"NC",
    "wof:name":"Curtis D Depuy",
    "wof:placetype":"venue"
},
  "geometry": {"coordinates":[-80.925729,35.470665],"type":"Point"}
}