{
  "type": "Feature",
  "properties": {
    "iso:country":"US",
    "sg:address":"2815 E 10th St",
    "sg:city":"Greenville",
    "sg:classifiers":[
        {
            "category":"Government",
            "subcategory":"Office",
            "type":"Public Place"
        }
    ],
    "sg:phone":"+1 252 752 4435",
    "sg:postcode":"27858",
    "sg:province":"NC",
    "sg:tags":[
        "enforcement",
        "section"
    ],
    "wof:name":"Enforcement Section",
    "wof:placetype":"venue"
},
  "geometry": {"coordinates":[-77.340732,35.603207],"type":"Point"}
}