{
  "type": "Feature",
  "properties": {
    "addr:full":"9044 Lawyers Rd Charlotte NC 28227",
    "addr:housenumber":"9044",
    "addr:postcode":"28227",
    "addr:street":"Lawyers Rd",
    "iso:country":"US",
    "sg:address":"9044 Lawyers Rd",
    "sg:city":"Charlotte",
    "sg:classifiers":[
        {
            "category":"Personal",
            "type":"Services"
        }
    ],
    "sg:phone":"+1   ",
    "sg:postcode":"28227",
    "sg:province":"NC",
    "wof:name":"Marshall Poplin - Tantastic",
    "wof:placetype":"venue"
},
  "geometry": {"coordinates":[-80.689988,35.187545],"type":"Point"}
}