{
  "type": "Feature",
  "properties": {
    "iso:country":"US",
    "sg:address":"5628 Green Pine Rd",
    "sg:city":"Cedar Grove",
    "sg:classifiers":[
        {
            "category":"Building & Trades",
            "subcategory":"Construction",
            "type":"Services"
        }
    ],
    "sg:phone":"+1 919 732 6744",
    "sg:postcode":"27231",
    "sg:province":"NC",
    "sg:tags":[
        "contractor"
    ],
    "wof:name":"JLT Welding",
    "wof:placetype":"venue"
},
  "geometry": {"coordinates":[-79.13032699999999,36.182951],"type":"Point"}
}