{
  "type": "Feature",
  "properties": {
    "iso:country":"US",
    "sg:address":"7023 Guess Rd",
    "sg:city":"Rougemont",
    "sg:classifiers":[
        {
            "category":"Home & Garden",
            "subcategory":"Furniture",
            "type":"Retail Goods"
        }
    ],
    "sg:phone":"+1 919 477 0690",
    "sg:postcode":"27572",
    "sg:province":"NC",
    "sg:tags":[
        "cabinet"
    ],
    "wof:name":"Hill & Co Inc",
    "wof:placetype":"venue"
},
  "geometry": {"coordinates":[-79.016828,36.189608],"type":"Point"}
}