{
  "type": "Feature",
  "properties": {
    "addr:full":"2609 Lynn Rd Raleigh NC 27612",
    "addr:housenumber":"2609",
    "addr:postcode":"27612",
    "addr:street":"Lynn Rd",
    "iso:country":"US",
    "sg:address":"2609 Lynn Rd",
    "sg:city":"Raleigh",
    "sg:classifiers":[
        {
            "category":"Social Services",
            "type":"Services"
        }
    ],
    "sg:phone":"+1   ",
    "sg:postcode":"27612",
    "sg:province":"NC",
    "wof:name":"Women Embracing Recovery",
    "wof:placetype":"venue"
},
  "geometry": {"coordinates":[-78.68535300000001,35.873174],"type":"Point"}
}