{
  "type": "Feature",
  "properties": {
    "addr:full":"2315 N Church St Burlington NC 27217",
    "addr:housenumber":"2315",
    "addr:postcode":"27217",
    "addr:street":"N Church St",
    "iso:country":"US",
    "sg:address":"2315 N Church St",
    "sg:city":"Burlington",
    "sg:classifiers":[
        {
            "category":"Food & Beverages",
            "subcategory":"Liquor & Beverages",
            "type":"Retail Goods"
        }
    ],
    "sg:phone":"+1 336 228 7233",
    "sg:postcode":"27217",
    "sg:province":"NC",
    "sg:tags":[
        "drinking",
        "alcoholic"
    ],
    "wof:name":"Plaza Bar",
    "wof:placetype":"venue"
},
  "geometry": {"coordinates":[-79.393789,36.092626],"type":"Point"}
}