{
  "type": "Feature",
  "properties": {
    "iso:country":"US",
    "sg:address":"5014 West Rd",
    "sg:city":"Kernersville",
    "sg:classifiers":[
        {
            "category":"Real Estate",
            "subcategory":"Real Estate Operator",
            "type":"Services"
        }
    ],
    "sg:phone":"+1 336 993 4904",
    "sg:postcode":"27284",
    "sg:province":"NC",
    "sg:tags":[
        "building",
        "nonresidential"
    ],
    "wof:name":"Cale Properties LLC",
    "wof:placetype":"venue"
},
  "geometry": {"coordinates":[-80.132457,36.135309],"type":"Point"}
}