{
  "type": "Feature",
  "properties": {
    "iso:country":"US",
    "sg:address":"1772 Trueblood Rd",
    "sg:city":"Weldon",
    "sg:classifiers":[
        {
            "category":"Professional",
            "subcategory":"Management & Consulting",
            "type":"Services"
        }
    ],
    "sg:phone":"+1 252 538 4156",
    "sg:postcode":"27839",
    "sg:province":"NC",
    "sg:tags":[
        "consultant",
        "energy",
        "conservation"
    ],
    "wof:name":"Coastal Forest Resources Co",
    "wof:placetype":"venue"
},
  "geometry": {"coordinates":[-77.612745,36.400503],"type":"Point"}
}