{
  "type": "Feature",
  "properties": {
    "iso:country":"US",
    "sg:address":"1001 Red Banks Rd",
    "sg:city":"Greenville",
    "sg:classifiers":[
        {
            "category":"Banks & Credit Unions",
            "subcategory":"Bank",
            "type":"Services"
        }
    ],
    "sg:phone":"+1 252 355 8200",
    "sg:postcode":"27858",
    "sg:province":"NC",
    "sg:tags":[
        "national",
        "commercial"
    ],
    "sg:website":"www.ecbbancorp.com",
    "wof:name":"East Carolina Bank",
    "wof:placetype":"venue"
},
  "geometry": {"coordinates":[-77.361318,35.583653],"type":"Point"}
}