{
  "type": "Feature",
  "properties": {
    "addr:full":"1835 Eaton Ferry Rd Littleton NC 27850",
    "addr:housenumber":"1835",
    "addr:postcode":"27850",
    "addr:street":"Eaton Ferry Rd",
    "iso:country":"US",
    "sg:address":"1835 Eaton Ferry Rd",
    "sg:city":"Littleton",
    "sg:classifiers":[
        {
            "category":"Real Estate",
            "subcategory":"Real Estate Agent",
            "type":"Services"
        }
    ],
    "sg:phone":"+1 252 586 3700",
    "sg:postcode":"27850",
    "sg:province":"NC",
    "wof:name":"Gaston Pointe Properties",
    "wof:placetype":"venue"
},
  "geometry": {"coordinates":[-77.964573,36.508196],"type":"Point"}
}