{
  "type": "Feature",
  "properties": {
    "addr:full":"55 Woodscape Dr Horse Shoe NC 28759",
    "addr:housenumber":"55",
    "addr:postcode":"28759",
    "addr:street":"Woodscape Dr Horse",
    "iso:country":"US",
    "sg:address":"55 Woodscape Dr",
    "sg:city":"Horse Shoe",
    "sg:classifiers":[
        {
            "category":"Professional",
            "subcategory":"Accounting & Tax Preparation",
            "type":"Services"
        }
    ],
    "sg:phone":"+1   ",
    "sg:postcode":"28759",
    "sg:province":"NC",
    "sg:tags":[
        "return"
    ],
    "wof:name":"Rainbow Professional Services",
    "wof:placetype":"venue"
},
  "geometry": {"coordinates":[-79.535308,35.303763],"type":"Point"}
}