{
  "type": "Feature",
  "properties": {
    "addr:full":"723 Flynn Rd Rutherfordton NC 28139",
    "addr:housenumber":"723",
    "addr:postcode":"28139",
    "addr:street":"Flynn Rd",
    "iso:country":"US",
    "sg:address":"723 Flynn Rd",
    "sg:city":"Rutherfordton",
    "sg:classifiers":[
        {
            "category":"Retail",
            "subcategory":"Repair Shop",
            "type":"Services"
        }
    ],
    "sg:phone":"+1 828 287 5354",
    "sg:postcode":"28139",
    "sg:province":"NC",
    "sg:tags":[
        "appliance"
    ],
    "wof:name":"Koone's Service",
    "wof:placetype":"venue"
},
  "geometry": {"coordinates":[-81.988434,35.377249],"type":"Point"}
}