{
  "type": "Feature",
  "properties": {
    "addr:full":"113 Fayetteville Rd Raeford NC 28376",
    "addr:housenumber":"113",
    "addr:postcode":"28376",
    "addr:street":"Fayetteville Rd",
    "iso:country":"US",
    "sg:address":"113 Fayetteville Rd",
    "sg:city":"Raeford",
    "sg:classifiers":[
        {
            "category":"Autos & Motor Vehicles",
            "subcategory":"Auto Supplies",
            "type":"Retail Goods"
        }
    ],
    "sg:phone":"+1 910 904 2431",
    "sg:postcode":"28376",
    "sg:province":"NC",
    "sg:tags":[
        "automobile",
        "parts"
    ],
    "sg:website":"www.autozone.com",
    "wof:name":"Autozone",
    "wof:placetype":"venue"
},
  "geometry": {"coordinates":[-79.236519,34.979244],"type":"Point"}
}