{
  "type": "Feature",
  "properties": {
    "iso:country":"US",
    "sg:address":"5255 Windy Hill Dr",
    "sg:city":"Raleigh",
    "sg:classifiers":[
        {
            "category":"Professional",
            "type":"Services"
        }
    ],
    "sg:phone":"+1 919 247 4261",
    "sg:postcode":"27609",
    "sg:province":"NC",
    "wof:name":"Home Job",
    "wof:placetype":"venue"
},
  "geometry": {"coordinates":[-78.607608,35.853967],"type":"Point"}
}