{
  "type": "Feature",
  "properties": {
    "iso:country":"US",
    "sg:address":"102 Trinity Dr",
    "sg:city":"Leland",
    "sg:classifiers":[
        {
            "category":"Organizations",
            "subcategory":"Religious Organization",
            "type":"Services"
        }
    ],
    "sg:phone":"+1   ",
    "sg:postcode":"28451",
    "sg:province":"NC",
    "wof:name":"New Jerusalem Outreach",
    "wof:placetype":"venue"
},
  "geometry": {"coordinates":[-78.020163,34.233251],"type":"Point"}
}