{
  "type": "Feature",
  "properties": {
    "iso:country":"US",
    "sg:address":"1039 S Church St",
    "sg:city":"Burlington",
    "sg:classifiers":[
        {
            "category":"Personal",
            "subcategory":"Beauty Salon",
            "type":"Services"
        }
    ],
    "sg:phone":"+1   ",
    "sg:postcode":"27215",
    "sg:province":"NC",
    "sg:tags":[
        "shop"
    ],
    "wof:name":"Ten Thirty Nine Salon",
    "wof:placetype":"venue"
},
  "geometry": {"coordinates":[-79.446291,36.0905],"type":"Point"}
}