{
  "type": "Feature",
  "properties": {
    "addr:full":"2117 Wright Ave Greensboro NC 27403",
    "addr:housenumber":"2117",
    "addr:postcode":"27403",
    "addr:street":"Wright Ave",
    "iso:country":"US",
    "sg:address":"2117 Wright Ave",
    "sg:city":"Greensboro",
    "sg:classifiers":[
        {
            "category":"Manufacturing",
            "subcategory":"Tools & Machinery",
            "type":"Manufacturing & Wholesale Goods"
        }
    ],
    "sg:phone":"+1 336 272 9264",
    "sg:postcode":"27403",
    "sg:province":"NC",
    "sg:tags":[
        "woodworking",
        "mfg"
    ],
    "wof:name":"Forsyth & Kirby Smith Designs",
    "wof:placetype":"venue"
},
  "geometry": {"coordinates":[-79.825895,36.069848],"type":"Point"}
}