{
  "type": "Feature",
  "properties": {
    "addr:full":"704 Buford St Shelby NC 28152",
    "addr:housenumber":"704",
    "addr:postcode":"28152",
    "addr:street":"Buford St",
    "iso:country":"US",
    "sg:address":"704 Buford St",
    "sg:city":"Shelby",
    "sg:classifiers":[
        {
            "category":"Banks & Credit Unions",
            "subcategory":"Investment Brokerage",
            "type":"Services"
        }
    ],
    "sg:phone":"+1 704 482 6288",
    "sg:postcode":"28152",
    "sg:province":"NC",
    "sg:tags":[
        "security"
    ],
    "wof:name":"Edward Jones 18246",
    "wof:placetype":"venue"
},
  "geometry": {"coordinates":[-81.564785,35.273614],"type":"Point"}
}