{
  "type": "Feature",
  "properties": {
    "addr:full":"2501 Honeycutt-Simpson Rd Monroe NC 28110",
    "addr:housenumber":"2501",
    "addr:postcode":"28110",
    "addr:street":"Honeycutt-Simpson Rd",
    "iso:country":"US",
    "sg:address":"2501 Honeycutt-Simpson Rd",
    "sg:city":"Monroe",
    "sg:classifiers":[
        {
            "category":"Professional",
            "type":"Services"
        }
    ],
    "sg:phone":"+1   ",
    "sg:postcode":"28110",
    "sg:province":"NC",
    "wof:name":"Amazing Cleansing Service",
    "wof:placetype":"venue"
},
  "geometry": {"coordinates":[-80.481607,35.078418],"type":"Point"}
}