{
  "type": "Feature",
  "properties": {
    "iso:country":"US",
    "sg:address":"103 N Oakum St",
    "sg:city":"Edenton",
    "sg:classifiers":[
        {
            "category":"Food & Beverages",
            "subcategory":"Groceries & Convenience Stores",
            "type":"Retail Goods"
        }
    ],
    "sg:phone":"+1 252 482 3212",
    "sg:postcode":"27932",
    "sg:province":"NC",
    "sg:tags":[
        "grocer"
    ],
    "wof:name":"Harrell's Community Groc Inc",
    "wof:placetype":"venue"
},
  "geometry": {"coordinates":[-76.604074,36.061116],"type":"Point"}
}