{
  "type": "Feature",
  "properties": {
    "addr:full":"2340 Sunset Ave Rocky Mount NC 27804",
    "addr:housenumber":"2340",
    "addr:postcode":"27804",
    "addr:street":"Sunset Ave",
    "iso:country":"US",
    "sg:address":"2340 Sunset Ave",
    "sg:city":"Rocky Mount",
    "sg:classifiers":[
        {
            "category":"Banks & Credit Unions",
            "subcategory":"Bank",
            "type":"Services"
        }
    ],
    "sg:phone":"+1 252 454 3622",
    "sg:postcode":"27804",
    "sg:province":"NC",
    "wof:name":"RBC Centura Bank",
    "wof:placetype":"venue"
},
  "geometry": {"coordinates":[-77.825337,35.959225],"type":"Point"}
}