{
  "type": "Feature",
  "properties": {
    "iso:country":"US",
    "sg:address":"234 Snow Hill Church Cir",
    "sg:city":"Dobson",
    "sg:classifiers":[
        {
            "category":"Building & Trades",
            "subcategory":"Construction",
            "type":"Services"
        }
    ],
    "sg:phone":"+1 336 366 4348",
    "sg:postcode":"27017",
    "sg:province":"NC",
    "sg:tags":[
        "marking",
        "maintenance",
        "parking"
    ],
    "wof:name":"A Plus Svc",
    "wof:placetype":"venue"
},
  "geometry": {"coordinates":[-80.770004,36.369668],"type":"Point"}
}