{
  "type": "Feature",
  "properties": {
    "addr:full":"216 N Chestnut St Lumberton NC 28358",
    "addr:housenumber":"216",
    "addr:postcode":"28358",
    "addr:street":"N Chestnut St",
    "iso:country":"US",
    "sg:address":"216 N Chestnut St",
    "sg:city":"Lumberton",
    "sg:classifiers":[
        {
            "category":"Food & Beverages",
            "subcategory":"Bakery",
            "type":"Retail Goods"
        }
    ],
    "sg:phone":"+1 910 739 5207",
    "sg:postcode":"28358",
    "sg:province":"NC",
    "sg:tags":[
        "baker",
        "eating"
    ],
    "wof:name":"Blanton's Old Fashion Bakery",
    "wof:placetype":"venue"
},
  "geometry": {"coordinates":[-79.007745,34.618004],"type":"Point"}
}