{
  "type": "Feature",
  "properties": {
    "addr:full":"154 Magnolia Ln Clyde NC 28721",
    "addr:housenumber":"154",
    "addr:postcode":"28721",
    "addr:street":"Magnolia Ln",
    "iso:country":"US",
    "sg:address":"154 Magnolia Ln",
    "sg:city":"Clyde",
    "sg:classifiers":[
        {
            "category":"Manufacturing",
            "subcategory":"Rubber & Plastics",
            "type":"Manufacturing & Wholesale Goods"
        }
    ],
    "sg:phone":"+1 828 627 2854",
    "sg:postcode":"28721",
    "sg:province":"NC",
    "sg:tags":[
        "sealing",
        "devices",
        "gasket"
    ],
    "wof:name":"Webbco Inc",
    "wof:placetype":"venue"
},
  "geometry": {"coordinates":[-82.92574399999999,35.578281],"type":"Point"}
}