{
  "type": "Feature",
  "properties": {
    "iso:country":"US",
    "sg:address":"1565 Lowrance Rd",
    "sg:city":"Catawba",
    "sg:classifiers":[
        {
            "category":"Home & Garden",
            "subcategory":"Garden Supply",
            "type":"Retail Goods"
        }
    ],
    "sg:phone":"+1 828 320 5965",
    "sg:postcode":"28609",
    "sg:province":"NC",
    "wof:name":"Eden Farm",
    "wof:placetype":"venue"
},
  "geometry": {"coordinates":[-81.066785,35.679757],"type":"Point"}
}