{
  "type": "Feature",
  "properties": {
    "iso:country":"US",
    "sg:address":"3528 Hartland Rd",
    "sg:city":"Morganton",
    "sg:classifiers":[
        {
            "category":"Retail",
            "subcategory":"Auto Repair",
            "type":"Services"
        }
    ],
    "sg:phone":"+1   ",
    "sg:postcode":"28655",
    "sg:province":"NC",
    "sg:tags":[
        "automotive"
    ],
    "wof:name":"Poarch",
    "wof:placetype":"venue"
},
  "geometry": {"coordinates":[-81.650826,35.84301],"type":"Point"}
}