{
  "type": "Feature",
  "properties": {
    "addr:full":"284 Arnette Rd Banner Elk NC 28604",
    "addr:housenumber":"284",
    "addr:postcode":"28604",
    "addr:street":"Arnette Rd",
    "iso:country":"US",
    "sg:address":"284 Arnette Rd",
    "sg:city":"Banner Elk",
    "sg:classifiers":[
        {
            "category":"Health Services",
            "subcategory":"Doctor",
            "type":"Services"
        }
    ],
    "sg:phone":"+1 828 898 4490",
    "sg:postcode":"28604",
    "sg:province":"NC",
    "sg:tags":[
        "physician",
        "surgeon"
    ],
    "wof:name":"Robert J Egidio Family Prctc",
    "wof:placetype":"venue"
},
  "geometry": {"coordinates":[-81.844916,36.135421],"type":"Point"}
}