{
  "type": "Feature",
  "properties": {
    "addr:full":"257 Woltz Ln Advance NC 27006",
    "addr:housenumber":"257",
    "addr:postcode":"27006",
    "addr:street":"Woltz Ln",
    "iso:country":"US",
    "sg:address":"257 Woltz Ln",
    "sg:city":"Advance",
    "sg:classifiers":[
        {
            "category":"Farming",
            "subcategory":"Fish & Marine Products",
            "type":"Manufacturing & Wholesale Goods"
        }
    ],
    "sg:phone":"+1 336 998 7085",
    "sg:postcode":"27006",
    "sg:province":"NC",
    "sg:tags":[
        "preserves",
        "fishing",
        "hunting"
    ],
    "wof:name":"Yadkin Point Hunt & Kennel",
    "wof:placetype":"venue"
},
  "geometry": {"coordinates":[-80.384866,35.912112],"type":"Point"}
}