{
  "type": "Feature",
  "properties": {
    "addr:full":"13663 Providence Rd Matthews NC 28104",
    "addr:housenumber":"13663",
    "addr:postcode":"28104",
    "addr:street":"Providence Rd",
    "iso:country":"US",
    "sg:address":"13663 Providence Rd",
    "sg:city":"Matthews",
    "sg:classifiers":[
        {
            "category":"Building & Trades",
            "subcategory":"Construction",
            "type":"Services"
        }
    ],
    "sg:phone":"+1 704 846 4889",
    "sg:postcode":"28104",
    "sg:province":"NC",
    "sg:tags":[
        "fire",
        "restoration",
        "damage"
    ],
    "wof:name":"Garment Restoration",
    "wof:placetype":"venue"
},
  "geometry": {"coordinates":[-80.763518,35.02641],"type":"Point"}
}