{
  "type": "Feature",
  "properties": {
    "iso:country":"US",
    "sg:address":"920 New Leicester Hwy",
    "sg:city":"Asheville",
    "sg:classifiers":[
        {
            "category":"Retail",
            "subcategory":"Auto Repair",
            "type":"Services"
        }
    ],
    "sg:phone":"+1 828 683 5854",
    "sg:postcode":"28806",
    "sg:province":"NC",
    "sg:tags":[
        "automobile",
        "top",
        "upholstery"
    ],
    "wof:name":"Automotive Trim Tech",
    "wof:placetype":"venue"
},
  "geometry": {"coordinates":[-82.65104100000001,35.617287],"type":"Point"}
}