{
  "type": "Feature",
  "properties": {
    "iso:country":"US",
    "sg:address":"212 W Main St",
    "sg:city":"Gibsonville",
    "sg:classifiers":[
        {
            "category":"Bars & Pubs",
            "type":"Food & Drink"
        }
    ],
    "sg:phone":"+1 336 446 2004",
    "sg:postcode":"27249",
    "sg:province":"NC",
    "sg:tags":[
        "club",
        "night"
    ],
    "wof:name":"Splash Nightclub",
    "wof:placetype":"venue"
},
  "geometry": {"coordinates":[-79.54286500000001,36.106393],"type":"Point"}
}