{
  "type": "Feature",
  "properties": {
    "addr:full":"708 N English St Greensboro NC 27405",
    "addr:housenumber":"708",
    "addr:postcode":"27405",
    "addr:street":"N English St",
    "iso:country":"US",
    "sg:address":"708 N English St",
    "sg:city":"Greensboro",
    "sg:classifiers":[
        {
            "category":"Personal",
            "subcategory":"Beauty Salon",
            "type":"Services"
        }
    ],
    "sg:phone":"+1 336 691 9817",
    "sg:postcode":"27405",
    "sg:province":"NC",
    "sg:tags":[
        "shop"
    ],
    "wof:name":"Janice's Beauty Salon",
    "wof:placetype":"venue"
},
  "geometry": {"coordinates":[-79.75662199999999,36.087353],"type":"Point"}
}