{
  "type": "Feature",
  "properties": {
    "iso:country":"US",
    "sg:address":"102 S Reilly Rd",
    "sg:city":"Fayetteville",
    "sg:classifiers":[
        {
            "category":"Retail",
            "subcategory":"Car Wash",
            "type":"Services"
        }
    ],
    "sg:phone":"+1 910 868 0901",
    "sg:postcode":"28314",
    "sg:province":"NC",
    "sg:tags":[
        "polishing",
        "washing"
    ],
    "wof:name":"Wet Willie's Car Wash",
    "wof:placetype":"venue"
},
  "geometry": {"coordinates":[-79.010149,35.080834],"type":"Point"}
}