{
  "type": "Feature",
  "properties": {
    "iso:country":"US",
    "sg:address":"400 Budleigh St",
    "sg:city":"Manteo",
    "sg:classifiers":[
        {
            "category":"Shopping",
            "subcategory":"Crafts & Fabrics",
            "type":"Retail Goods"
        }
    ],
    "sg:phone":"+1 252 473 6330",
    "sg:postcode":"27954",
    "sg:province":"NC",
    "sg:tags":[
        "yarn"
    ],
    "wof:name":"Fine Yarns At Kimbeeba",
    "wof:placetype":"venue"
},
  "geometry": {"coordinates":[-75.674179,35.908545],"type":"Point"}
}