{
  "type": "Feature",
  "properties": {
    "iso:country":"US",
    "sg:address":"7133 Roberts Rd",
    "sg:city":"Cary",
    "sg:classifiers":[
        {
            "category":"Professional",
            "subcategory":"Computer Services",
            "type":"Services"
        }
    ],
    "sg:phone":"+1 919 303 9008",
    "sg:postcode":"27519",
    "sg:province":"NC",
    "sg:tags":[
        "house",
        "datum",
        "mail"
    ],
    "wof:name":"Innovatative Creations Etc",
    "wof:placetype":"venue"
},
  "geometry": {"coordinates":[-78.88366000000001,35.763162],"type":"Point"}
}