{
  "type": "Feature",
  "properties": {
    "iso:country":"US",
    "sg:address":"2201 N Main St",
    "sg:city":"Kannapolis",
    "sg:classifiers":[
        {
            "category":"Retail",
            "subcategory":"Auto Repair",
            "type":"Services"
        }
    ],
    "sg:phone":"+1 704 938 7456",
    "sg:postcode":"28081",
    "sg:province":"NC",
    "sg:tags":[
        "automobile",
        "top",
        "upholstery"
    ],
    "wof:name":"Severt's Automobile Upholstery",
    "wof:placetype":"venue"
},
  "geometry": {"coordinates":[-80.614211,35.5237],"type":"Point"}
}