{
  "type": "Feature",
  "properties": {
    "addr:full":"5901 Old US Hwy 52 Lexington NC 27295",
    "addr:housenumber":"5901",
    "addr:postcode":"27295",
    "addr:street":"Old Us Hwy 52",
    "iso:country":"US",
    "sg:address":"5901 Old US Hwy 52",
    "sg:city":"Lexington",
    "sg:classifiers":[
        {
            "category":"Professional",
            "type":"Services"
        }
    ],
    "sg:phone":"+1 336 731 2236",
    "sg:postcode":"27295",
    "sg:province":"NC",
    "wof:name":"Welcome Service Ctr",
    "wof:placetype":"venue"
},
  "geometry": {"coordinates":[-80.256688,35.905446],"type":"Point"}
}