{
  "type": "Feature",
  "properties": {
    "iso:country":"US",
    "sg:address":"6612 Glenwood Ave",
    "sg:city":"Raleigh",
    "sg:classifiers":[
        {
            "category":"Fast Food",
            "type":"Food & Drink"
        }
    ],
    "sg:phone":"+1 919 571 8480",
    "sg:postcode":"27613",
    "sg:province":"NC",
    "sg:website":"chick-fil-a.com",
    "wof:name":"Chick-Fil-A",
    "wof:placetype":"venue"
},
  "geometry": {"coordinates":[-78.708662,35.861041],"type":"Point"}
}