{
  "type": "Feature",
  "properties": {
    "addr:full":"1114 Crossroads Dr Statesville NC 28625",
    "addr:housenumber":"1114",
    "addr:postcode":"28625",
    "addr:street":"Crossroads Dr",
    "iso:country":"US",
    "sg:address":"1114 Crossroads Dr",
    "sg:city":"Statesville",
    "sg:classifiers":[
        {
            "category":"Shopping",
            "subcategory":"Jewelry",
            "type":"Retail Goods"
        }
    ],
    "sg:phone":"+1 704 873 7989",
    "sg:postcode":"28625",
    "sg:province":"NC",
    "sg:tags":[
        "jeweler"
    ],
    "wof:name":"Friedman's",
    "wof:placetype":"venue"
},
  "geometry": {"coordinates":[-80.87275200000001,35.809901],"type":"Point"}
}