{
  "type": "Feature",
  "properties": {
    "addr:full":"505 Watauga St Raleigh NC 27604",
    "addr:housenumber":"505",
    "addr:postcode":"27604",
    "addr:street":"Watauga St",
    "iso:country":"US",
    "sg:address":"505 Watauga St",
    "sg:city":"Raleigh",
    "sg:classifiers":[
        {
            "category":"Health Services",
            "subcategory":"Doctor",
            "type":"Services"
        }
    ],
    "sg:phone":"+1   ",
    "sg:postcode":"27604",
    "sg:province":"NC",
    "sg:tags":[
        "medical"
    ],
    "wof:name":"Tara Pressley MD",
    "wof:placetype":"venue"
},
  "geometry": {"coordinates":[-78.628716,35.786516],"type":"Point"}
}