{
  "type": "Feature",
  "properties": {
    "addr:full":"1820 Ridgeville Rd Prospect Hill NC 27291",
    "addr:housenumber":"1820",
    "addr:postcode":"27291",
    "addr:street":"Ridgeville Rd",
    "iso:country":"US",
    "sg:address":"1820 Ridgeville Rd",
    "sg:city":"Prospect Hill",
    "sg:classifiers":[
        {
            "category":"Organizations",
            "subcategory":"Religious Organization",
            "type":"Services"
        }
    ],
    "sg:phone":"+1   ",
    "sg:postcode":"27291",
    "sg:province":"NC",
    "wof:name":"Lea Bethel Baptist Church",
    "wof:placetype":"venue"
},
  "geometry": {"coordinates":[-79.181375,36.291259],"type":"Point"}
}