{
  "type": "Feature",
  "properties": {
    "addr:full":"1700 Yates Store Rd Cary NC 27519",
    "addr:housenumber":"1700",
    "addr:postcode":"27519",
    "addr:street":"Yates Store Rd",
    "iso:country":"US",
    "sg:address":"1700 Yates Store Rd",
    "sg:city":"Cary",
    "sg:classifiers":[
        {
            "category":"Building & Trades",
            "subcategory":"Cleaning & Sanitation",
            "type":"Services"
        },
        {
            "category":"Retail",
            "subcategory":"Repair Shop",
            "type":"Services"
        }
    ],
    "sg:phone":"+1 919 319 3333",
    "sg:postcode":"27519",
    "sg:province":"NC",
    "sg:tags":[
        "ventilating",
        "refrigeration",
        "system"
    ],
    "wof:name":"Duct Doctor U S A of Raleigh",
    "wof:placetype":"venue"
},
  "geometry": {"coordinates":[-78.912988,35.82242],"type":"Point"}
}