{
  "type": "Feature",
  "properties": {
    "iso:country":"US",
    "sg:address":"1411 Broad St",
    "sg:city":"Durham",
    "sg:classifiers":[
        {
            "category":"Health Services",
            "subcategory":"Health Practitioner",
            "type":"Services"
        }
    ],
    "sg:phone":"+1 919 286 3031",
    "sg:postcode":"27705",
    "sg:province":"NC",
    "sg:tags":[
        "psychologist"
    ],
    "wof:name":"Meggan Moorhead",
    "wof:placetype":"venue"
},
  "geometry": {"coordinates":[-78.91887199999999,36.023122],"type":"Point"}
}