{
  "type": "Feature",
  "properties": {
    "iso:country":"US",
    "sg:address":"3081 Walters Rd",
    "sg:city":"Creedmoor",
    "sg:classifiers":[
        {
            "category":"Wholesale",
            "subcategory":"Non-durable Goods",
            "type":"Manufacturing & Wholesale Goods"
        }
    ],
    "sg:phone":"+1 919 528 4956",
    "sg:postcode":"27522",
    "sg:province":"NC",
    "sg:tags":[
        "advertising"
    ],
    "wof:name":"Premier Promotions",
    "wof:placetype":"venue"
},
  "geometry": {"coordinates":[-78.60609700000001,36.124355],"type":"Point"}
}