{
  "type": "Feature",
  "properties": {
    "iso:country":"US",
    "sg:address":"6412 Cheek Rd",
    "sg:city":"Durham",
    "sg:classifiers":[
        {
            "category":"Building & Trades",
            "subcategory":"Construction",
            "type":"Services"
        }
    ],
    "sg:phone":"+1 919 683 2302",
    "sg:postcode":"27704",
    "sg:province":"NC",
    "wof:name":"D Hawley Gen Contract",
    "wof:placetype":"venue"
},
  "geometry": {"coordinates":[-78.76302800000001,36.041885],"type":"Point"}
}