{
  "type": "Feature",
  "properties": {
    "iso:country":"US",
    "sg:address":"2210 N Church St",
    "sg:city":"Greensboro",
    "sg:classifiers":[
        {
            "category":"Wholesale",
            "subcategory":"Durable Goods & Equipment",
            "type":"Manufacturing & Wholesale Goods"
        },
        {
            "category":"Wholesale",
            "subcategory":"Non-durable Goods",
            "type":"Manufacturing & Wholesale Goods"
        }
    ],
    "sg:phone":"+1 336 389 1354",
    "sg:postcode":"27405",
    "sg:province":"NC",
    "sg:tags":[
        "import",
        "representative",
        "gift",
        "manufacturer"
    ],
    "wof:name":"Fancy That Gift & Decor Inc",
    "wof:placetype":"venue"
},
  "geometry": {"coordinates":[-79.781012,36.102281],"type":"Point"}
}