{
  "type": "Feature",
  "properties": {
    "iso:country":"US",
    "sg:address":"20 Josie Dr",
    "sg:city":"Benson",
    "sg:classifiers":[
        {
            "category":"Professional",
            "type":"Services"
        },
        {
            "category":"Organizations",
            "subcategory":"Community Association",
            "type":"Services"
        }
    ],
    "sg:phone":"+1 919 207 0099",
    "sg:postcode":"27504",
    "sg:province":"NC",
    "sg:tags":[
        "club"
    ],
    "wof:name":"Victoria's Pond",
    "wof:placetype":"venue"
},
  "geometry": {"coordinates":[-78.602397,35.466773],"type":"Point"}
}