{
  "type": "Feature",
  "properties": {
    "iso:country":"US",
    "sg:address":"400 E Trade St",
    "sg:city":"Charlotte",
    "sg:classifiers":[
        {
            "category":"Professional",
            "type":"Services"
        }
    ],
    "sg:phone":"+1 704 940 0437",
    "sg:postcode":"28202",
    "sg:province":"NC",
    "sg:tags":[
        "establishment"
    ],
    "wof:name":"Direct Marketing Solutions",
    "wof:placetype":"venue"
},
  "geometry": {"coordinates":[-80.83902399999999,35.223756],"type":"Point"}
}