{
  "type": "Feature",
  "properties": {
    "iso:country":"US",
    "sg:address":"532 S Elm St",
    "sg:city":"Greensboro",
    "sg:classifiers":[
        {
            "category":"Shopping",
            "subcategory":"Used Merchandise",
            "type":"Retail Goods"
        }
    ],
    "sg:phone":"+1 336 370 9900",
    "sg:postcode":"27406",
    "sg:province":"NC",
    "sg:tags":[
        "antique"
    ],
    "wof:name":"Rhyne's Antiques",
    "wof:placetype":"venue"
},
  "geometry": {"coordinates":[-79.790835,36.066328],"type":"Point"}
}