{
  "type": "Feature",
  "properties": {
    "iso:country":"US",
    "sg:address":"2734 W Center St Exd",
    "sg:city":"Lexington",
    "sg:classifiers":[
        {
            "category":"Real Estate",
            "subcategory":"Real Estate Agent",
            "type":"Services"
        }
    ],
    "sg:phone":"+1 336 243 2557",
    "sg:postcode":"27295",
    "sg:province":"NC",
    "wof:name":"Glenda S Pierce Realty",
    "wof:placetype":"venue"
},
  "geometry": {"coordinates":[-80.29006,35.864537],"type":"Point"}
}