{
  "type": "Feature",
  "properties": {
    "iso:country":"US",
    "sg:address":"509 S Edgeworth St",
    "sg:city":"Greensboro",
    "sg:classifiers":[
        {
            "category":"Restaurant",
            "type":"Food & Drink"
        }
    ],
    "sg:phone":"+1 336 370 0426",
    "sg:postcode":"27401",
    "sg:province":"NC",
    "sg:tags":[
        "personal",
        "equipment",
        "eating",
        "caterer"
    ],
    "sg:website":"www.cateringbyellyn.com",
    "wof:name":"Catering By Ellyn",
    "wof:placetype":"venue"
},
  "geometry": {"coordinates":[-79.796289,36.067094],"type":"Point"}
}