{
  "type": "Feature",
  "properties": {
    "addr:full":"1035 5th St SE Hickory NC 28602",
    "addr:housenumber":"1035",
    "addr:postcode":"28602",
    "addr:street":"5Th St Se",
    "iso:country":"US",
    "sg:address":"1035 5th St SE",
    "sg:city":"Hickory",
    "sg:classifiers":[
        {
            "category":"Building & Trades",
            "subcategory":"Construction",
            "type":"Services"
        }
    ],
    "sg:phone":"+1 828 327 0314",
    "sg:postcode":"28602",
    "sg:province":"NC",
    "sg:tags":[
        "concrete",
        "cutting",
        "breaking",
        "sawing"
    ],
    "wof:name":"A Plus Concrete Sawing",
    "wof:placetype":"venue"
},
  "geometry": {"coordinates":[-81.33041799999999,35.720703],"type":"Point"}
}