{
  "type": "Feature",
  "properties": {
    "iso:country":"US",
    "sg:address":"2615 Lake Dr Ste 301",
    "sg:city":"Raleigh",
    "sg:classifiers":[
        {
            "category":"Health Services",
            "subcategory":"Doctor",
            "type":"Services"
        }
    ],
    "sg:phone":"+1 919 960 7100",
    "sg:postcode":"27607",
    "sg:province":"NC",
    "sg:tags":[
        "cardiologist"
    ],
    "wof:name":"Piedmont Cardiology PA",
    "wof:placetype":"venue"
},
  "geometry": {"coordinates":[-78.706987,35.816661],"type":"Point"}
}