{
  "type": "Feature",
  "properties": {
    "iso:country":"US",
    "sg:address":"1100 Raleigh Blvd",
    "sg:city":"Raleigh",
    "sg:classifiers":[
        {
            "category":"Shopping",
            "subcategory":"Clothing, Apparel, & Fashions",
            "type":"Retail Goods"
        }
    ],
    "sg:phone":"+1 919 755 1167",
    "sg:postcode":"27610",
    "sg:province":"NC",
    "wof:name":"Simply Fashions",
    "wof:placetype":"venue"
},
  "geometry": {"coordinates":[-78.61283,35.793999],"type":"Point"}
}