{
  "type": "Feature",
  "properties": {
    "addr:full":"2018 Rock Ave Fayetteville NC 28303",
    "addr:housenumber":"2018",
    "addr:postcode":"28303",
    "addr:street":"Rock Ave",
    "iso:country":"US",
    "sg:address":"2018 Rock Ave",
    "sg:city":"Fayetteville",
    "sg:classifiers":[
        {
            "category":"Social Services",
            "subcategory":"Child Care",
            "type":"Services"
        }
    ],
    "sg:phone":"+1   ",
    "sg:postcode":"28303",
    "sg:province":"NC",
    "sg:tags":[
        "day"
    ],
    "wof:name":"Muffett Day Care",
    "wof:placetype":"venue"
},
  "geometry": {"coordinates":[-78.917123,35.063439],"type":"Point"}
}