{
  "type": "Feature",
  "properties": {
    "iso:country":"US",
    "sg:address":"1256 Dellwood Rd",
    "sg:city":"Waynesville",
    "sg:classifiers":[
        {
            "category":"Autos & Motor Vehicles",
            "subcategory":"Automobile Sales",
            "type":"Retail Goods"
        }
    ],
    "sg:phone":"+1 828 452 5046",
    "sg:postcode":"28786",
    "sg:province":"NC",
    "sg:tags":[
        "performance",
        "race",
        "dealer"
    ],
    "wof:name":"Smokey Racing Inc",
    "wof:placetype":"venue"
},
  "geometry": {"coordinates":[-82.98631,35.525792],"type":"Point"}
}