{
  "type": "Feature",
  "properties": {
    "addr:full":"105 Central Ave Butner NC 27509",
    "addr:housenumber":"105",
    "addr:postcode":"27509",
    "addr:street":"Central Ave",
    "iso:country":"US",
    "sg:address":"105 Central Ave",
    "sg:city":"Butner",
    "sg:classifiers":[
        {
            "category":"Government",
            "subcategory":"Office",
            "type":"Public Place"
        }
    ],
    "sg:phone":"+1 919 575 5185",
    "sg:postcode":"27509",
    "sg:province":"NC",
    "sg:tags":[
        "federal",
        "security"
    ],
    "wof:name":"Army National Guard",
    "wof:placetype":"venue"
},
  "geometry": {"coordinates":[-78.75487800000001,36.130284],"type":"Point"}
}