{
  "type": "Feature",
  "properties": {
    "iso:country":"US",
    "sg:address":"2700 Connemara Dr",
    "sg:city":"Matthews",
    "sg:classifiers":[
        {
            "category":"Arena",
            "subcategory":"Sports Club",
            "type":"Entertainment"
        }
    ],
    "sg:phone":"+1   ",
    "sg:postcode":"28105",
    "sg:province":"NC",
    "wof:name":"Kos LLC",
    "wof:placetype":"venue"
},
  "geometry": {"coordinates":[-80.67594,35.127447],"type":"Point"}
}