{
  "type": "Feature",
  "properties": {
    "addr:full":"3269 Hutchinson McDonald Rd Charlotte NC 28269",
    "addr:housenumber":"3269",
    "addr:postcode":"28269",
    "addr:street":"Hutchinson Mcdonald Rd",
    "iso:country":"US",
    "sg:address":"3269 Hutchinson McDonald Rd",
    "sg:city":"Charlotte",
    "sg:classifiers":[
        {
            "category":"Banks & Credit Unions",
            "subcategory":"Bank",
            "type":"Services"
        }
    ],
    "sg:phone":"+1 704 599 6501",
    "sg:postcode":"28269",
    "sg:province":"NC",
    "sg:tags":[
        "company",
        "mortgage"
    ],
    "wof:name":"Wells Fargo",
    "wof:placetype":"venue"
},
  "geometry": {"coordinates":[-80.83578799999999,35.281377],"type":"Point"}
}