{
  "type": "Feature",
  "properties": {
    "addr:full":"10710 Sikes Pl Ste 180 Charlotte NC 28277",
    "addr:housenumber":"10710",
    "addr:postcode":"28277",
    "addr:street":"Sikes Pl Ste 180",
    "iso:country":"US",
    "sg:address":"10710 Sikes Pl Ste 180",
    "sg:city":"Charlotte",
    "sg:classifiers":[
        {
            "category":"Real Estate",
            "subcategory":"Real Estate Services",
            "type":"Services"
        },
        {
            "category":"Banks & Credit Unions",
            "subcategory":"Financial Services",
            "type":"Services"
        }
    ],
    "sg:phone":"+1 704 841 2597",
    "sg:postcode":"28277",
    "sg:province":"NC",
    "sg:tags":[
        "financing",
        "loan"
    ],
    "sg:website":"http://www.citifinancial.com",
    "wof:name":"CitiFinancial",
    "wof:placetype":"venue"
},
  "geometry": {"coordinates":[-80.768474,35.062017],"type":"Point"}
}