{
  "type": "Feature",
  "properties": {
    "addr:full":"205 W Main St Mayodan NC 27027",
    "addr:housenumber":"205",
    "addr:postcode":"27027",
    "addr:street":"W Main St",
    "iso:country":"US",
    "sg:address":"205 W Main St",
    "sg:city":"Mayodan",
    "sg:classifiers":[
        {
            "category":"Retail",
            "subcategory":"Repair Shop",
            "type":"Services"
        }
    ],
    "sg:phone":"+1 336 548 6181",
    "sg:postcode":"27027",
    "sg:province":"NC",
    "sg:tags":[
        "appliance"
    ],
    "wof:name":"Main Street Appliances",
    "wof:placetype":"venue"
},
  "geometry": {"coordinates":[-79.966656,36.412479],"type":"Point"}
}