{
  "type": "Feature",
  "properties": {
    "addr:full":"1495 US Hwy 1 S Southern Pines NC 28387",
    "addr:housenumber":"1495",
    "addr:postcode":"28387",
    "addr:street":"Us Hwy 1 S",
    "iso:country":"US",
    "sg:address":"1495 US Hwy 1 S",
    "sg:city":"Southern Pines",
    "sg:classifiers":[
        {
            "category":"Shopping",
            "type":"Retail Goods"
        }
    ],
    "sg:phone":"+1 910 692 1636",
    "sg:postcode":"28387",
    "sg:province":"NC",
    "sg:tags":[
        "pet",
        "shop"
    ],
    "wof:name":"Creature Comforts",
    "wof:placetype":"venue"
},
  "geometry": {"coordinates":[-79.409638,35.162354],"type":"Point"}
}