{
  "type": "Feature",
  "properties": {
    "addr:full":"367 Dellwood Rd Waynesville NC 28786",
    "addr:housenumber":"367",
    "addr:postcode":"28786",
    "addr:street":"Dellwood Rd",
    "iso:country":"US",
    "sg:address":"367 Dellwood Rd",
    "sg:city":"Waynesville",
    "sg:classifiers":[
        {
            "category":"Insurance",
            "subcategory":"Insurance Agent",
            "type":"Services"
        }
    ],
    "sg:phone":"+1 828 456 3560",
    "sg:postcode":"28786",
    "sg:province":"NC",
    "wof:name":"Nationwide Insurance",
    "wof:placetype":"venue"
},
  "geometry": {"coordinates":[-82.990194,35.497546],"type":"Point"}
}