{
  "type": "Feature",
  "properties": {
    "iso:country":"US",
    "sg:address":"17051 Frog Pond Rd",
    "sg:city":"Oakboro",
    "sg:classifiers":[
        {
            "category":"Professional",
            "subcategory":"Employment Agencies",
            "type":"Services"
        }
    ],
    "sg:phone":"+1   ",
    "sg:postcode":"28129",
    "sg:province":"NC",
    "sg:tags":[
        "help",
        "supply"
    ],
    "wof:name":"Whitley High Pressure Washing",
    "wof:placetype":"venue"
},
  "geometry": {"coordinates":[-80.31352099999999,35.271007],"type":"Point"}
}