{
  "type": "Feature",
  "properties": {
    "iso:country":"US",
    "sg:address":"6820 Brookbank Rd",
    "sg:city":"Summerfield",
    "sg:classifiers":[
        {
            "category":"Professional",
            "type":"Services"
        }
    ],
    "sg:phone":"+1 336 643 3575",
    "sg:postcode":"27358",
    "sg:province":"NC",
    "wof:name":"1988 Greensboro Lady Gate",
    "wof:placetype":"venue"
},
  "geometry": {"coordinates":[-79.94747,36.18387],"type":"Point"}
}