{
  "type": "Feature",
  "properties": {
    "iso:country":"US",
    "sg:address":"4299 State Hwy 150",
    "sg:city":"Lexington",
    "sg:classifiers":[
        {
            "category":"Organizations",
            "subcategory":"Religious Organization",
            "type":"Services"
        }
    ],
    "sg:phone":"+1 336 853 8090",
    "sg:postcode":"27295",
    "sg:province":"NC",
    "sg:tags":[
        "church"
    ],
    "wof:name":"St Luke's Lutheran Church",
    "wof:placetype":"venue"
},
  "geometry": {"coordinates":[-80.37294199999999,35.809054],"type":"Point"}
}