{
  "type": "Feature",
  "properties": {
    "iso:country":"US",
    "sg:address":"124 Five Oaks Dr",
    "sg:city":"King",
    "sg:classifiers":[
        {
            "category":"Professional",
            "subcategory":"Business Services",
            "type":"Services"
        }
    ],
    "sg:phone":"+1 336 985 3024",
    "sg:postcode":"27021",
    "sg:province":"NC",
    "sg:tags":[
        "packaging"
    ],
    "wof:name":"Goin' Postal",
    "wof:placetype":"venue"
},
  "geometry": {"coordinates":[-80.389589,36.263633],"type":"Point"}
}