{
  "type": "Feature",
  "properties": {
    "iso:country":"US",
    "sg:address":"2701 Moxley Rd",
    "sg:city":"Hays",
    "sg:classifiers":[
        {
            "category":"Building & Trades",
            "subcategory":"Construction",
            "type":"Services"
        }
    ],
    "sg:phone":"+1 336 957 2487",
    "sg:postcode":"28685",
    "sg:province":"NC",
    "sg:tags":[
        "excavation",
        "contractor"
    ],
    "wof:name":"D JS Backhoe Service",
    "wof:placetype":"venue"
},
  "geometry": {"coordinates":[-81.121021,36.366876],"type":"Point"}
}