{
  "type": "Feature",
  "properties": {
    "iso:country":"US",
    "sg:address":"332 S Salisbury Gq Ave",
    "sg:city":"Granite Quarry",
    "sg:classifiers":[
        {
            "category":"Building & Trades",
            "subcategory":"Construction",
            "type":"Services"
        }
    ],
    "sg:phone":"+1 704 209 3329",
    "sg:postcode":"28072",
    "sg:province":"NC",
    "sg:tags":[
        "tennis",
        "court"
    ],
    "sg:website":"www.court1.com",
    "wof:name":"Court One",
    "wof:placetype":"venue"
},
  "geometry": {"coordinates":[-80.44139,35.613204],"type":"Point"}
}