{
  "type": "Feature",
  "properties": {
    "iso:country":"US",
    "sg:address":"4609 Old Mill Rd",
    "sg:city":"Gastonia",
    "sg:classifiers":[
        {
            "category":"Building & Trades",
            "subcategory":"Construction",
            "type":"Services"
        }
    ],
    "sg:phone":"+1 704 824 5644",
    "sg:postcode":"28056",
    "sg:province":"NC",
    "sg:tags":[
        "painter"
    ],
    "wof:name":"Turn Key Drywall Inc",
    "wof:placetype":"venue"
},
  "geometry": {"coordinates":[-81.09413000000001,35.234182],"type":"Point"}
}