{
  "type": "Feature",
  "properties": {
    "addr:full":"1531 Iredell Dr Raleigh NC 27608",
    "addr:housenumber":"1531",
    "addr:postcode":"27608",
    "addr:street":"Iredell Dr",
    "iso:country":"US",
    "sg:address":"1531 Iredell Dr",
    "sg:city":"Raleigh",
    "sg:classifiers":[
        {
            "category":"Banks & Credit Unions",
            "subcategory":"Financial Services",
            "type":"Services"
        }
    ],
    "sg:phone":"+1 919 821 3507",
    "sg:postcode":"27608",
    "sg:province":"NC",
    "sg:tags":[
        "investor"
    ],
    "wof:name":"U K Investments LLC",
    "wof:placetype":"venue"
},
  "geometry": {"coordinates":[-78.650763,35.800667],"type":"Point"}
}