{
  "type": "Feature",
  "properties": {
    "addr:full":"238 N McPherson Church Rd Fayetteville NC 28303",
    "addr:housenumber":"238",
    "addr:postcode":"28303",
    "addr:street":"N Mcpherson Church Rd",
    "iso:country":"US",
    "sg:address":"238 N McPherson Church Rd",
    "sg:city":"Fayetteville",
    "sg:classifiers":[
        {
            "category":"Real Estate",
            "subcategory":"Real Estate Operator",
            "type":"Services"
        }
    ],
    "sg:phone":"+1 910 826 2028",
    "sg:postcode":"28303",
    "sg:province":"NC",
    "sg:tags":[
        "apartment"
    ],
    "wof:name":"Watauga Manor Apartments",
    "wof:placetype":"venue"
},
  "geometry": {"coordinates":[-78.95201900000001,35.071915],"type":"Point"}
}