{
  "type": "Feature",
  "properties": {
    "iso:country":"US",
    "sg:address":"2326 Olive Branch Rd",
    "sg:city":"Monroe",
    "sg:classifiers":[
        {
            "category":"Professional",
            "type":"Services"
        }
    ],
    "sg:phone":"+1 704 283 6090",
    "sg:postcode":"28110",
    "sg:province":"NC",
    "wof:name":"Petrea Studios",
    "wof:placetype":"venue"
},
  "geometry": {"coordinates":[-80.512593,35.005226],"type":"Point"}
}