{
  "type": "Feature",
  "properties": {
    "addr:full":"1501 Carters Grove Rd Clemmons NC 27012",
    "addr:housenumber":"1501",
    "addr:postcode":"27012",
    "addr:street":"Carters Grove Rd",
    "iso:country":"US",
    "sg:address":"1501 Carters Grove Rd",
    "sg:city":"Clemmons",
    "sg:classifiers":[
        {
            "category":"Education",
            "subcategory":"Library",
            "type":"Public Place"
        }
    ],
    "sg:phone":"+1   ",
    "sg:postcode":"27012",
    "sg:province":"NC",
    "wof:name":"Ashley Branch",
    "wof:placetype":"venue"
},
  "geometry": {"coordinates":[-80.403228,36.069737],"type":"Point"}
}