{
  "type": "Feature",
  "properties": {
    "iso:country":"US",
    "sg:address":"4990 US Hwy 70",
    "sg:city":"New Bern",
    "sg:classifiers":[
        {
            "category":"Wholesale",
            "subcategory":"Auto Parts",
            "type":"Manufacturing & Wholesale Goods"
        }
    ],
    "sg:phone":"+1 252 638 3189",
    "sg:postcode":"28560",
    "sg:province":"NC",
    "sg:tags":[
        "equipment",
        "truck"
    ],
    "wof:name":"Truck & Equipment Etc",
    "wof:placetype":"venue"
},
  "geometry": {"coordinates":[-76.988073,35.002862],"type":"Point"}
}