{
  "type": "Feature",
  "properties": {
    "addr:full":"902 Friendly Rd Dunn NC 28334",
    "addr:housenumber":"902",
    "addr:postcode":"28334",
    "addr:street":"Friendly Rd",
    "iso:country":"US",
    "sg:address":"902 Friendly Rd",
    "sg:city":"Dunn",
    "sg:classifiers":[
        {
            "category":"Building & Trades",
            "subcategory":"Electrical",
            "type":"Services"
        }
    ],
    "sg:phone":"+1 910 892 2452",
    "sg:postcode":"28334",
    "sg:province":"NC",
    "sg:tags":[
        "electric",
        "contractor"
    ],
    "wof:name":"Electrical Solutions",
    "wof:placetype":"venue"
},
  "geometry": {"coordinates":[-78.608178,35.324417],"type":"Point"}
}