{
  "type": "Feature",
  "properties": {
    "iso:country":"US",
    "sg:address":"150 Koa Ln",
    "sg:city":"Statesville",
    "sg:classifiers":[
        {
            "category":"Retail",
            "subcategory":"Repair Shop",
            "type":"Services"
        }
    ],
    "sg:phone":"+1   ",
    "sg:postcode":"28677",
    "sg:province":"NC",
    "wof:name":"R C Lawnmower Repair Service",
    "wof:placetype":"venue"
},
  "geometry": {"coordinates":[-80.85790900000001,35.73093],"type":"Point"}
}