{
  "type": "Feature",
  "properties": {
    "iso:country":"US",
    "sg:address":"5308 Bent Leaf Dr",
    "sg:city":"Raleigh",
    "sg:classifiers":[
        {
            "category":"Building & Trades",
            "subcategory":"Construction",
            "type":"Services"
        }
    ],
    "sg:phone":"+1 919 271 2497",
    "sg:postcode":"27606",
    "sg:province":"NC",
    "sg:tags":[
        "contractor"
    ],
    "wof:name":"Higher Concepts Custom Bldrs",
    "wof:placetype":"venue"
},
  "geometry": {"coordinates":[-78.702884,35.699816],"type":"Point"}
}