{
  "type": "Feature",
  "properties": {
    "addr:full":"2639 Cedar Island Rd Cedar Island NC 28520",
    "addr:housenumber":"2639",
    "addr:postcode":"28520",
    "addr:street":"Cedar Island Rd",
    "iso:country":"US",
    "sg:address":"2639 Cedar Island Rd",
    "sg:city":"Cedar Island",
    "sg:classifiers":[
        {
            "category":"Building & Trades",
            "subcategory":"Construction",
            "type":"Services"
        }
    ],
    "sg:phone":"+1 252 225 0275",
    "sg:postcode":"28520",
    "sg:province":"NC",
    "sg:tags":[
        "resurfacing",
        "laying",
        "refinishing",
        "floor"
    ],
    "wof:name":"Sierchios Floor Sanding",
    "wof:placetype":"venue"
},
  "geometry": {"coordinates":[-76.304479,34.985818],"type":"Point"}
}