{
  "type": "Feature",
  "properties": {
    "addr:full":"1705 Sawgrass Ct Raleigh NC 27615",
    "addr:housenumber":"1705",
    "addr:postcode":"27615",
    "addr:street":"Sawgrass Ct",
    "iso:country":"US",
    "sg:address":"1705 Sawgrass Ct",
    "sg:city":"Raleigh",
    "sg:classifiers":[
        {
            "category":"Professional",
            "subcategory":"Business Services",
            "type":"Services"
        }
    ],
    "sg:phone":"+1 919 870 5757",
    "sg:postcode":"27615",
    "sg:province":"NC",
    "sg:tags":[
        "interior",
        "consultant",
        "design",
        "decorator"
    ],
    "wof:name":"Etcetera Of Raleigh Inc",
    "wof:placetype":"venue"
},
  "geometry": {"coordinates":[-78.60763,35.883681],"type":"Point"}
}