{
  "type": "Feature",
  "properties": {
    "iso:country":"US",
    "sg:address":"41 Pelican Point Rd",
    "sg:city":"Wilmington",
    "sg:classifiers":[
        {
            "category":"Professional",
            "subcategory":"Business Services",
            "type":"Services"
        }
    ],
    "sg:phone":"+1 910 392 0839",
    "sg:postcode":"28409",
    "sg:province":"NC",
    "sg:tags":[
        "interior",
        "consultant",
        "design",
        "decorator"
    ],
    "wof:name":"Decorating Problem Solver",
    "wof:placetype":"venue"
},
  "geometry": {"coordinates":[-77.85934899999999,34.154381],"type":"Point"}
}