{
  "type": "Feature",
  "properties": {
    "addr:full":"1371 Cedar Valley Church Rd Lenoir NC 28645",
    "addr:housenumber":"1371",
    "addr:postcode":"28645",
    "addr:street":"Cedar Valley Church Rd",
    "iso:country":"US",
    "sg:address":"1371 Cedar Valley Church Rd",
    "sg:city":"Lenoir",
    "sg:classifiers":[
        {
            "category":"Building & Trades",
            "subcategory":"Construction",
            "type":"Services"
        }
    ],
    "sg:phone":"+1 828 758 5392",
    "sg:postcode":"28645",
    "sg:province":"NC",
    "sg:tags":[
        "carpentry",
        "contractor"
    ],
    "wof:name":"Pennington Carpentry",
    "wof:placetype":"venue"
},
  "geometry": {"coordinates":[-81.43437900000001,35.90146],"type":"Point"}
}