{
  "type": "Feature",
  "properties": {
    "iso:country":"US",
    "sg:address":"2751 John Brewer Rd",
    "sg:city":"Leasburg",
    "sg:classifiers":[
        {
            "category":"Manufacturing",
            "subcategory":"Lumber",
            "type":"Manufacturing & Wholesale Goods"
        }
    ],
    "sg:phone":"+1 336 599 2136",
    "sg:postcode":"27291",
    "sg:province":"NC",
    "sg:tags":[
        "hardwood",
        "mills",
        "dimension",
        "flooring"
    ],
    "wof:name":"C & C Decking & Miscellaneous",
    "wof:placetype":"venue"
},
  "geometry": {"coordinates":[-79.12144499999999,36.422966],"type":"Point"}
}