{
  "type": "Feature",
  "properties": {
    "addr:full":"204 Brook Rd Kings Mountain NC 28086",
    "addr:housenumber":"204",
    "addr:postcode":"28086",
    "addr:street":"Brook Rd",
    "iso:country":"US",
    "sg:address":"204 Brook Rd",
    "sg:city":"Kings Mountain",
    "sg:classifiers":[
        {
            "category":"Personal",
            "subcategory":"Beauty Salon",
            "type":"Services"
        }
    ],
    "sg:phone":"+1 704 739 9142",
    "sg:postcode":"28086",
    "sg:province":"NC",
    "wof:name":"Salon Phifer Inc",
    "wof:placetype":"venue"
},
  "geometry": {"coordinates":[-81.385778,35.284191],"type":"Point"}
}