{
  "type": "Feature",
  "properties": {
    "iso:country":"US",
    "sg:address":"349 Water Plant Rd",
    "sg:city":"Manteo",
    "sg:classifiers":[
        {
            "category":"Government",
            "subcategory":"Office",
            "type":"Public Place"
        }
    ],
    "sg:phone":"+1 252 473 3637",
    "sg:postcode":"27954",
    "sg:province":"NC",
    "sg:tags":[
        "state",
        "program"
    ],
    "wof:name":"Transportation Dept",
    "wof:placetype":"venue"
},
  "geometry": {"coordinates":[-75.663506,35.884301],"type":"Point"}
}