{
  "type": "Feature",
  "properties": {
    "iso:country":"US",
    "sg:address":"2116 Spicer Mountain Rd",
    "sg:city":"Sparta",
    "sg:classifiers":[
        {
            "category":"Farming",
            "subcategory":"Dairy Farm",
            "type":"Manufacturing & Wholesale Goods"
        }
    ],
    "sg:phone":"+1 336 372 5580",
    "sg:postcode":"28675",
    "sg:province":"NC",
    "wof:name":"Jones Dairy",
    "wof:placetype":"venue"
},
  "geometry": {"coordinates":[-81.167827,36.494675],"type":"Point"}
}