{
  "type": "Feature",
  "properties": {
    "addr:full":"4158 Rimer Rd Concord NC 28025",
    "addr:postcode":"4158;28025",
    "addr:street":"Rimer Rd",
    "iso:country":"US",
    "sg:address":"4158 Rimer Rd",
    "sg:city":"Concord",
    "sg:classifiers":[
        {
            "category":"Professional",
            "subcategory":"Business Services",
            "type":"Services"
        }
    ],
    "sg:phone":"+1 704 782 3539",
    "sg:postcode":"28025",
    "sg:province":"NC",
    "sg:tags":[
        "auctioneer"
    ],
    "wof:name":"Farmers Livestock Barn",
    "wof:placetype":"venue"
},
  "geometry": {"coordinates":[-80.484477,35.473767],"type":"Point"}
}