{
  "type": "Feature",
  "properties": {
    "iso:country":"US",
    "sg:address":"404 Main St",
    "sg:city":"Ahoskie",
    "sg:classifiers":[
        {
            "category":"Insurance",
            "subcategory":"Insurance Agent",
            "type":"Services"
        }
    ],
    "sg:phone":"+1 252 332 6302",
    "sg:postcode":"27910",
    "sg:province":"NC",
    "wof:name":"Woodmen Of The World Insurance",
    "wof:placetype":"venue"
},
  "geometry": {"coordinates":[-76.989621,36.287567],"type":"Point"}
}