{
  "type": "Feature",
  "properties": {
    "iso:country":"US",
    "sg:address":"2730 Van Dyke Ave",
    "sg:city":"Raleigh",
    "sg:classifiers":[
        {
            "category":"Real Estate",
            "subcategory":"Real Estate Operator",
            "type":"Services"
        }
    ],
    "sg:phone":"+1 919 848 0100",
    "sg:postcode":"27607",
    "sg:province":"NC",
    "sg:tags":[
        "property",
        "lessor"
    ],
    "wof:name":"Charles Averre",
    "wof:placetype":"venue"
},
  "geometry": {"coordinates":[-78.67187,35.795223],"type":"Point"}
}