{
  "type": "Feature",
  "properties": {
    "addr:full":"13021 Seascape Ln Charlotte NC 28278",
    "addr:housenumber":"13021",
    "addr:postcode":"28278",
    "addr:street":"Seascape Ln",
    "iso:country":"US",
    "sg:address":"13021 Seascape Ln",
    "sg:city":"Charlotte",
    "sg:classifiers":[
        {
            "category":"Home & Garden",
            "subcategory":"Furniture",
            "type":"Retail Goods"
        }
    ],
    "sg:phone":"+1 704 263 1451",
    "sg:postcode":"28278",
    "sg:province":"NC",
    "sg:tags":[
        "bedding"
    ],
    "wof:name":"Niagra Adjustable Beds & Chair",
    "wof:placetype":"venue"
},
  "geometry": {"coordinates":[-80.98853699999999,35.122643],"type":"Point"}
}