{
  "type": "Feature",
  "properties": {
    "iso:country":"US",
    "sg:address":"710 Tracy Grove Rd",
    "sg:city":"Flat Rock",
    "sg:classifiers":[
        {
            "category":"Shopping",
            "subcategory":"Florist",
            "type":"Retail Goods"
        }
    ],
    "sg:phone":"+1 828 693 0410",
    "sg:postcode":"28731",
    "sg:province":"NC",
    "wof:name":"Petals Distributors",
    "wof:placetype":"venue"
},
  "geometry": {"coordinates":[-82.423489,35.315681],"type":"Point"}
}