{
  "type": "Feature",
  "properties": {
    "addr:full":"250 Branchview Dr NE Concord NC 28025",
    "addr:housenumber":"250",
    "addr:postcode":"28025",
    "addr:street":"Branchview Dr Ne",
    "iso:country":"US",
    "sg:address":"250 Branchview Dr NE",
    "sg:city":"Concord",
    "sg:classifiers":[
        {
            "category":"Organizations",
            "subcategory":"Professional Association",
            "type":"Services"
        }
    ],
    "sg:phone":"+1 704 786 5512",
    "sg:postcode":"28025",
    "sg:province":"NC",
    "wof:name":"Central Carolina Assoc-Realtor",
    "wof:placetype":"venue"
},
  "geometry": {"coordinates":[-80.57323599999999,35.42],"type":"Point"}
}