{
  "type": "Feature",
  "properties": {
    "addr:full":"3908 Patriot Dr Durham NC 27703",
    "addr:housenumber":"3908",
    "addr:postcode":"27703",
    "addr:street":"Patriot Dr",
    "iso:country":"US",
    "sg:address":"3908 Patriot Dr",
    "sg:city":"Durham",
    "sg:classifiers":[
        {
            "category":"Professional",
            "subcategory":"Research",
            "type":"Services"
        }
    ],
    "sg:phone":"+1 919 544 1023",
    "sg:postcode":"27703",
    "sg:province":"NC",
    "sg:tags":[
        "pharmaceutical",
        "information"
    ],
    "sg:website":"www.ribonomics.com",
    "wof:name":"Ribonomics",
    "wof:placetype":"venue"
},
  "geometry": {"coordinates":[-78.850022,35.911835],"type":"Point"}
}