{
  "type": "Feature",
  "properties": {
    "iso:country":"US",
    "sg:address":"1692 NC-68 N",
    "sg:city":"Oak Ridge",
    "sg:classifiers":[
        {
            "category":"Restaurant",
            "type":"Food & Drink"
        }
    ],
    "sg:menulink":"http://www.allmenus.com/nc/oak-ridge/85450-dominos-pizza/menu/",
    "sg:phone":"+1 336 644 0665",
    "sg:postcode":"27310",
    "sg:province":"NC",
    "sg:tags":[
        "american",
        "wing",
        "pizza"
    ],
    "wof:name":"Domino's Pizza",
    "wof:placetype":"venue"
},
  "geometry": {"coordinates":[-79.988742,36.172746],"type":"Point"}
}