{
  "type": "Feature",
  "properties": {
    "iso:country":"US",
    "sg:address":"18645 Peacock Rd",
    "sg:city":"Whiteville",
    "sg:classifiers":[
        {
            "category":"Building & Trades",
            "subcategory":"Construction",
            "type":"Services"
        }
    ],
    "sg:phone":"+1 910 653 3498",
    "sg:postcode":"28472",
    "sg:province":"NC",
    "sg:tags":[
        "roofing",
        "contractor"
    ],
    "wof:name":"Barnes & Barnes Roofing Contr",
    "wof:placetype":"venue"
},
  "geometry": {"coordinates":[-78.790527,34.190157],"type":"Point"}
}