{
  "type": "Feature",
  "properties": {
    "iso:country":"US",
    "sg:address":"223 Club Ct",
    "sg:city":"Wilmington",
    "sg:classifiers":[
        {
            "category":"Professional",
            "type":"Services"
        }
    ],
    "sg:phone":"+1 910 794 8865",
    "sg:postcode":"28412",
    "sg:province":"NC",
    "wof:name":"Richard K Hutter & Rosalie A H",
    "wof:placetype":"venue"
},
  "geometry": {"coordinates":[-77.916116,34.073852],"type":"Point"}
}