{
  "type": "Feature",
  "properties": {
    "iso:country":"US",
    "sg:address":"36 Waldroup Rd",
    "sg:city":"Hayesville",
    "sg:classifiers":[
        {
            "category":"Health Services",
            "subcategory":"Doctor",
            "type":"Services"
        }
    ],
    "sg:phone":"+1 828 389 8714",
    "sg:postcode":"28904",
    "sg:province":"NC",
    "sg:tags":[
        "dentist"
    ],
    "wof:name":"John W Hooker DDS PA",
    "wof:placetype":"venue"
},
  "geometry": {"coordinates":[-83.824127,35.031767],"type":"Point"}
}