{
  "type": "Feature",
  "properties": {
    "addr:full":"3604 Esther Rd Indian Trail NC 28079",
    "addr:housenumber":"3604",
    "addr:postcode":"28079",
    "addr:street":"Esther Rd",
    "iso:country":"US",
    "sg:address":"3604 Esther Rd",
    "sg:city":"Indian Trail",
    "sg:classifiers":[
        {
            "category":"Professional",
            "subcategory":"Business Services",
            "type":"Services"
        }
    ],
    "sg:phone":"+1   ",
    "sg:postcode":"28079",
    "sg:province":"NC",
    "wof:name":"Investech Enterprises Inc",
    "wof:placetype":"venue"
},
  "geometry": {"coordinates":[-80.63025399999999,35.07937],"type":"Point"}
}