{
  "type": "Feature",
  "properties": {
    "addr:full":"104 W Gordon St Kinston NC 28501",
    "addr:housenumber":"104",
    "addr:postcode":"28501",
    "addr:street":"W Gordon St",
    "iso:country":"US",
    "sg:address":"104 W Gordon St",
    "sg:city":"Kinston",
    "sg:classifiers":[
        {
            "category":"Professional",
            "subcategory":"Accounting & Tax Preparation",
            "type":"Services"
        }
    ],
    "sg:phone":"+1 252 527 5343",
    "sg:postcode":"28501",
    "sg:province":"NC",
    "sg:tags":[
        "accountant"
    ],
    "wof:name":"Angie Johnson CPA",
    "wof:placetype":"venue"
},
  "geometry": {"coordinates":[-77.58154,35.261558],"type":"Point"}
}