{
  "type": "Feature",
  "properties": {
    "addr:full":"2103 E Cone Blvd Greensboro NC 27405",
    "addr:housenumber":"2103",
    "addr:postcode":"27405",
    "addr:street":"E Cone Blvd",
    "iso:country":"US",
    "sg:address":"2103 E Cone Blvd",
    "sg:city":"Greensboro",
    "sg:classifiers":[
        {
            "category":"Wholesale",
            "subcategory":"Machinery & Supplies",
            "type":"Manufacturing & Wholesale Goods"
        }
    ],
    "sg:phone":"+1 336 358 2499",
    "sg:postcode":"27405",
    "sg:province":"NC",
    "sg:tags":[
        "equipment",
        "establishment"
    ],
    "wof:name":"All Beauty Supply & Wireless",
    "wof:placetype":"venue"
},
  "geometry": {"coordinates":[-79.749123,36.112713],"type":"Point"}
}