{
  "type": "Feature",
  "properties": {
    "iso:country":"US",
    "sg:address":"1819 Goldsboro St SW",
    "sg:city":"Wilson",
    "sg:classifiers":[
        {
            "category":"Freight",
            "type":"Transportation"
        }
    ],
    "sg:phone":"+1 252 237 3151",
    "sg:postcode":"27893",
    "sg:province":"NC",
    "sg:tags":[
        "trucking"
    ],
    "sg:website":"www.forbestransfer.com",
    "wof:name":"Forbes Transfer Co",
    "wof:placetype":"venue"
},
  "geometry": {"coordinates":[-77.92625,35.707366],"type":"Point"}
}