{
  "type": "Feature",
  "properties": {
    "addr:full":"4173 Winona Dr Maiden NC 28650",
    "addr:housenumber":"4173",
    "addr:postcode":"28650",
    "addr:street":"Winona Dr",
    "iso:country":"US",
    "sg:address":"4173 Winona Dr",
    "sg:city":"Maiden",
    "sg:classifiers":[
        {
            "category":"Utilities",
            "subcategory":"Telephone",
            "type":"Services"
        }
    ],
    "sg:phone":"+1 704 483 5221",
    "sg:postcode":"28650",
    "sg:province":"NC",
    "sg:tags":[
        "company"
    ],
    "wof:name":"American Tel & Tel Co",
    "wof:placetype":"venue"
},
  "geometry": {"coordinates":[-81.067863,35.577672],"type":"Point"}
}