{
  "type": "Feature",
  "properties": {
    "addr:full":"170 Oliver Cooper Rd Richlands NC 28574",
    "addr:housenumber":"170",
    "addr:postcode":"28574",
    "addr:street":"Oliver Cooper Rd",
    "iso:country":"US",
    "sg:address":"170 Oliver Cooper Rd",
    "sg:city":"Richlands",
    "sg:classifiers":[
        {
            "category":"Building & Trades",
            "subcategory":"Construction",
            "type":"Services"
        }
    ],
    "sg:phone":"+1 910 324 6282",
    "sg:postcode":"28574",
    "sg:province":"NC",
    "sg:tags":[
        "residential"
    ],
    "wof:name":"Measure Up Inc",
    "wof:placetype":"venue"
},
  "geometry": {"coordinates":[-77.578272,34.824909],"type":"Point"}
}