{
  "type": "Feature",
  "properties": {
    "iso:country":"US",
    "sg:address":"4301 State Hwy 197",
    "sg:city":"Green Mountain",
    "sg:classifiers":[
        {
            "category":"Shopping",
            "subcategory":"Discount & Variety Stores",
            "type":"Retail Goods"
        }
    ],
    "sg:phone":"+1 828 688 2369",
    "sg:postcode":"28705",
    "sg:province":"NC",
    "sg:tags":[
        "merchandise",
        "general"
    ],
    "wof:name":"Frank Griffith & Son",
    "wof:placetype":"venue"
},
  "geometry": {"coordinates":[-82.282478,36.042845],"type":"Point"}
}