{
  "type": "Feature",
  "properties": {
    "addr:full":"201 S Estes Dr Chapel Hill NC 27514",
    "addr:housenumber":"201",
    "addr:postcode":"27514",
    "addr:street":"S Estes Dr",
    "iso:country":"US",
    "sg:address":"201 S Estes Dr",
    "sg:city":"Chapel Hill",
    "sg:classifiers":[
        {
            "category":"Shopping",
            "type":"Retail Goods"
        }
    ],
    "sg:phone":"+1 919 967 4810",
    "sg:postcode":"27514",
    "sg:province":"NC",
    "sg:tags":[
        "merchandise"
    ],
    "wof:name":"Dubeys Inc",
    "wof:placetype":"venue"
},
  "geometry": {"coordinates":[-79.02960899999999,35.927358],"type":"Point"}
}