{
  "type": "Feature",
  "properties": {
    "addr:full":"2605 Blue Ridge Rd Raleigh NC 27607",
    "addr:housenumber":"2605",
    "addr:postcode":"27607",
    "addr:street":"Blue Ridge Rd",
    "iso:country":"US",
    "sg:address":"2605 Blue Ridge Rd",
    "sg:city":"Raleigh",
    "sg:classifiers":[
        {
            "category":"Health Services",
            "subcategory":"Doctor",
            "type":"Services"
        }
    ],
    "sg:phone":"+1 919 881 9009",
    "sg:postcode":"27607",
    "sg:province":"NC",
    "wof:name":"Willey Leanna B MD",
    "wof:placetype":"venue"
},
  "geometry": {"coordinates":[-78.705299,35.815601],"type":"Point"}
}