{
  "type": "Feature",
  "properties": {
    "iso:country":"US",
    "sg:address":"758 US Hwy 70A E",
    "sg:city":"Selma",
    "sg:classifiers":[
        {
            "category":"Autos & Motor Vehicles",
            "subcategory":"Automobile Sales",
            "type":"Retail Goods"
        }
    ],
    "sg:phone":"+1 919 965 3010",
    "sg:postcode":"27576",
    "sg:province":"NC",
    "sg:tags":[
        "car",
        "dealer"
    ],
    "wof:name":"Crocker's Auto Sales",
    "wof:placetype":"venue"
},
  "geometry": {"coordinates":[-78.27091299999999,35.51445],"type":"Point"}
}