{
  "type": "Feature",
  "properties": {
    "iso:country":"US",
    "sg:address":"217 N Bragg St",
    "sg:city":"Warrenton",
    "sg:classifiers":[
        {
            "category":"Real Estate",
            "subcategory":"Real Estate Agent",
            "type":"Services"
        }
    ],
    "sg:phone":"+1 252 257 1779",
    "sg:postcode":"27589",
    "sg:province":"NC",
    "sg:tags":[
        "appraiser"
    ],
    "wof:name":"Fleming Appraisal & Investment",
    "wof:placetype":"venue"
},
  "geometry": {"coordinates":[-78.152933,36.402037],"type":"Point"}
}