{
  "type": "Feature",
  "properties": {
    "iso:country":"US",
    "sg:address":"500 Radar Rd",
    "sg:city":"Greensboro",
    "sg:classifiers":[
        {
            "category":"Wholesale",
            "subcategory":"Furniture",
            "type":"Manufacturing & Wholesale Goods"
        }
    ],
    "sg:phone":"+1 336 218 0305",
    "sg:postcode":"27410",
    "sg:province":"NC",
    "wof:name":"Business Furniture Solutions",
    "wof:placetype":"venue"
},
  "geometry": {"coordinates":[-79.92228299999999,36.096164],"type":"Point"}
}