{
  "type": "Feature",
  "properties": {
    "iso:country":"US",
    "sg:address":"5303 Lower Shoal Creek Ct",
    "sg:city":"Charlotte",
    "sg:classifiers":[
        {
            "category":"Social Services",
            "subcategory":"Job Training",
            "type":"Services"
        }
    ],
    "sg:phone":"+1 704 846 1613",
    "sg:postcode":"28277",
    "sg:province":"NC",
    "sg:tags":[
        "sale"
    ],
    "wof:name":"Jerry Moss & Associates Inccoporated",
    "wof:placetype":"venue"
},
  "geometry": {"coordinates":[-80.778223,35.038274],"type":"Point"}
}