{
  "type": "Feature",
  "properties": {
    "addr:full":"921 Green St Durham NC 27701",
    "addr:housenumber":"921",
    "addr:postcode":"27701",
    "addr:street":"Green St",
    "iso:country":"US",
    "sg:address":"921 Green St",
    "sg:city":"Durham",
    "sg:classifiers":[
        {
            "category":"Real Estate",
            "subcategory":"Real Estate Operator",
            "type":"Services"
        }
    ],
    "sg:phone":"+1 919 682 4086",
    "sg:postcode":"27701",
    "sg:province":"NC",
    "sg:tags":[
        "building",
        "apartment",
        "dwelling"
    ],
    "wof:name":"Edmund F Bumann",
    "wof:placetype":"venue"
},
  "geometry": {"coordinates":[-78.907826,36.010985],"type":"Point"}
}