{
  "type": "Feature",
  "properties": {
    "addr:full":"2917 Freedom Dr Charlotte NC 28208",
    "addr:housenumber":"2917",
    "addr:postcode":"28208",
    "addr:street":"Freedom Dr",
    "iso:country":"US",
    "sg:address":"2917 Freedom Dr",
    "sg:city":"Charlotte",
    "sg:classifiers":[
        {
            "category":"Shopping",
            "subcategory":"Used Merchandise",
            "type":"Retail Goods"
        }
    ],
    "sg:phone":"+1 704 393 3492",
    "sg:postcode":"28208",
    "sg:province":"NC",
    "sg:tags":[
        "shop",
        "thrift"
    ],
    "sg:website":"www.carolinavaluevillage.com",
    "wof:name":"Value Village Thrift Store",
    "wof:placetype":"venue"
},
  "geometry": {"coordinates":[-80.89209099999999,35.244368],"type":"Point"}
}