{
  "type": "Feature",
  "properties": {
    "addr:full":"1007 Shallowford Dr Wilmington NC 28412",
    "addr:housenumber":"1007",
    "addr:postcode":"28412",
    "addr:street":"Shallowford Dr",
    "iso:country":"US",
    "sg:address":"1007 Shallowford Dr",
    "sg:city":"Wilmington",
    "sg:classifiers":[
        {
            "category":"Shopping",
            "type":"Retail Goods"
        }
    ],
    "sg:phone":"+1 910 452 0007",
    "sg:postcode":"28412",
    "sg:province":"NC",
    "sg:tags":[
        "equipment",
        "telephone",
        "supply"
    ],
    "wof:name":"Communications Co",
    "wof:placetype":"venue"
},
  "geometry": {"coordinates":[-77.921443,34.154021],"type":"Point"}
}