{
  "type": "Feature",
  "properties": {
    "addr:full":"1901 Mill Rd Jamesville NC 27846",
    "addr:housenumber":"1901",
    "addr:postcode":"27846",
    "addr:street":"Mill Rd",
    "iso:country":"US",
    "sg:address":"1901 Mill Rd",
    "sg:city":"Jamesville",
    "sg:classifiers":[
        {
            "category":"Manufacturing",
            "subcategory":"Lumber",
            "type":"Manufacturing & Wholesale Goods"
        }
    ],
    "sg:phone":"+1 252 792 5687",
    "sg:postcode":"27846",
    "sg:province":"NC",
    "sg:tags":[
        "hardwood",
        "logging",
        "mill",
        "m"
    ],
    "wof:name":"Price Logging Inc",
    "wof:placetype":"venue"
},
  "geometry": {"coordinates":[-76.92138,35.799637],"type":"Point"}
}