{
  "type": "Feature",
  "properties": {
    "addr:full":"4263 State Hwy 801 Advance NC 27006",
    "addr:housenumber":"4263",
    "addr:postcode":"27006",
    "addr:street":"State Hwy 801",
    "iso:country":"US",
    "sg:address":"4263 State Hwy 801",
    "sg:city":"Advance",
    "sg:classifiers":[
        {
            "category":"Freight",
            "type":"Transportation"
        }
    ],
    "sg:phone":"+1 336 998 6364",
    "sg:postcode":"27006",
    "sg:province":"NC",
    "sg:tags":[
        "trucking"
    ],
    "wof:name":"R J Transports Inc",
    "wof:placetype":"venue"
},
  "geometry": {"coordinates":[-80.43990599999999,35.875434],"type":"Point"}
}