{
  "type": "Feature",
  "properties": {
    "iso:country":"US",
    "sg:address":"924 Hanes Mall Blvd",
    "sg:city":"Winston Salem",
    "sg:classifiers":[
        {
            "category":"Restaurant",
            "type":"Food & Drink"
        }
    ],
    "sg:menulink":"http://www.allmenus.com/nc/winston/178992-chick-fil-a/menu/",
    "sg:phone":"+1 336 765 0713",
    "sg:postcode":"27103",
    "sg:province":"NC",
    "sg:tags":[
        "wrap",
        "soup",
        "american",
        "sandwich",
        "salad"
    ],
    "wof:name":"Chick-fil-A",
    "wof:placetype":"venue"
},
  "geometry": {"coordinates":[-80.31248600000001,36.065069],"type":"Point"}
}