{
  "type": "Feature",
  "properties": {
    "addr:full":"6026 Dovefield Rd Charlotte NC 28277",
    "addr:housenumber":"6026",
    "addr:postcode":"28277",
    "addr:street":"Dovefield Rd",
    "iso:country":"US",
    "sg:address":"6026 Dovefield Rd",
    "sg:city":"Charlotte",
    "sg:classifiers":[
        {
            "category":"Professional",
            "type":"Services"
        }
    ],
    "sg:phone":"+1 704 846 4008",
    "sg:postcode":"28277",
    "sg:province":"NC",
    "sg:tags":[
        "establishment"
    ],
    "wof:name":"Witco Corp",
    "wof:placetype":"venue"
},
  "geometry": {"coordinates":[-80.785415,35.067123],"type":"Point"}
}