{
  "type": "Feature",
  "properties": {
    "addr:full":"101 S Elm St Greensboro NC 27401",
    "addr:housenumber":"101",
    "addr:postcode":"27401",
    "addr:street":"S Elm St",
    "iso:country":"US",
    "sg:address":"101 S Elm St",
    "sg:city":"Greensboro",
    "sg:classifiers":[
        {
            "category":"Professional",
            "subcategory":"Lawyer & Legal Services",
            "type":"Services"
        }
    ],
    "sg:phone":"+1   ",
    "sg:postcode":"27401",
    "sg:province":"NC",
    "wof:name":"Morgan John R/Attorney At Law",
    "wof:placetype":"venue"
},
  "geometry": {"coordinates":[-79.790359,36.071517],"type":"Point"}
}