{
  "type": "Feature",
  "properties": {
    "addr:full":"1717 Legion Rd, Suite 202 Chapel Hill NC 27517",
    "addr:housenumber":"1717",
    "addr:postcode":"27517",
    "addr:street":"Legion Rd Suite 202",
    "iso:country":"US",
    "sg:address":"1717 Legion Rd, Suite 202",
    "sg:city":"Chapel Hill",
    "sg:classifiers":[
        {
            "category":"Health Services",
            "subcategory":"Health Practitioner",
            "type":"Services"
        },
        {
            "category":"Health Services",
            "subcategory":"Chiropractor",
            "type":"Services"
        }
    ],
    "sg:phone":"+1 919 968 4417",
    "sg:postcode":"27517",
    "sg:province":"NC",
    "sg:tags":[
        "therapy",
        "physical"
    ],
    "sg:website":"www.chapelhillchiropracticcentre...",
    "wof:name":"Chapel Hill Chiropractic Centre",
    "wof:placetype":"venue"
},
  "geometry": {"coordinates":[-79.020432,35.93589],"type":"Point"}
}