{
  "type": "Feature",
  "properties": {
    "iso:country":"US",
    "sg:address":"2206 Rouse Rd",
    "sg:city":"Kinston",
    "sg:classifiers":[
        {
            "category":"Health Services",
            "subcategory":"Nursing And Care Facility",
            "type":"Services"
        }
    ],
    "sg:phone":"+1 252 522 1968",
    "sg:postcode":"28504",
    "sg:province":"NC",
    "sg:tags":[
        "home",
        "institution"
    ],
    "wof:name":"Barbara's Loving Care Home",
    "wof:placetype":"venue"
},
  "geometry": {"coordinates":[-77.618205,35.291854],"type":"Point"}
}