{
  "type": "Feature",
  "properties": {
    "addr:full":"9140 Arrowpoint Blvd Charlotte NC 28273",
    "addr:postcode":"9140;28273",
    "addr:street":"Arrowpoint Blvd",
    "iso:country":"US",
    "sg:address":"9140 Arrowpoint Blvd",
    "sg:city":"Charlotte",
    "sg:classifiers":[
        {
            "category":"Wholesale",
            "subcategory":"Office Equipment",
            "type":"Manufacturing & Wholesale Goods"
        }
    ],
    "sg:phone":"+1 704 519 4900",
    "sg:postcode":"28273",
    "sg:province":"NC",
    "sg:tags":[
        "repair",
        "electrical"
    ],
    "wof:name":"Danka Sales & Service",
    "wof:placetype":"venue"
},
  "geometry": {"coordinates":[-80.913769,35.139521],"type":"Point"}
}