{
  "type": "Feature",
  "properties": {
    "addr:full":"210 W Dallas Rd Stanley NC 28164",
    "addr:housenumber":"210",
    "addr:postcode":"28164",
    "addr:street":"W Dallas Rd",
    "iso:country":"US",
    "sg:address":"210 W Dallas Rd",
    "sg:city":"Stanley",
    "sg:classifiers":[
        {
            "category":"Manufacturing",
            "subcategory":"Apparel",
            "type":"Manufacturing & Wholesale Goods"
        }
    ],
    "sg:phone":"+1 704 263 2338",
    "sg:postcode":"28164",
    "sg:province":"NC",
    "sg:tags":[
        "sewing",
        "contractor"
    ],
    "wof:name":"Connie's Custom Sewing",
    "wof:placetype":"venue"
},
  "geometry": {"coordinates":[-81.09252600000001,35.351917],"type":"Point"}
}