{
  "type": "Feature",
  "properties": {
    "iso:country":"US",
    "sg:address":"15696 US Hwy 17",
    "sg:city":"Hampstead",
    "sg:classifiers":[
        {
            "category":"Real Estate",
            "subcategory":"Surveying",
            "type":"Services"
        }
    ],
    "sg:phone":"+1   ",
    "sg:postcode":"28443",
    "sg:province":"NC",
    "wof:name":"Benson John Surveying Land Plg",
    "wof:placetype":"venue"
},
  "geometry": {"coordinates":[-77.697903,34.378589],"type":"Point"}
}