{
  "type": "Feature",
  "properties": {
    "iso:country":"US",
    "sg:address":"9021 Bud Smith Rd",
    "sg:city":"Wake Forest",
    "sg:classifiers":[
        {
            "category":"Building & Trades",
            "subcategory":"Construction",
            "type":"Services"
        }
    ],
    "sg:phone":"+1 919 556 9405",
    "sg:postcode":"27587",
    "sg:province":"NC",
    "sg:tags":[
        "house"
    ],
    "wof:name":"Fritts Builders Inc",
    "wof:placetype":"venue"
},
  "geometry": {"coordinates":[-78.555198,36.017557],"type":"Point"}
}