{
  "type": "Feature",
  "properties": {
    "addr:full":"2801 Ward Blvd Wilson NC 27893",
    "addr:housenumber":"2801",
    "addr:postcode":"blvd;27893",
    "addr:street":"Ward",
    "iso:country":"US",
    "sg:address":"2801 Ward Blvd",
    "sg:city":"Wilson",
    "sg:classifiers":[
        {
            "category":"Personal",
            "subcategory":"Beauty Salon",
            "type":"Services"
        }
    ],
    "sg:phone":"+1   ",
    "sg:postcode":"27893",
    "sg:province":"NC",
    "sg:tags":[
        "shop"
    ],
    "wof:name":"Center Stage Hair & Nail Salon",
    "wof:placetype":"venue"
},
  "geometry": {"coordinates":[-77.925466,35.754965],"type":"Point"}
}