{
  "type": "Feature",
  "properties": {
    "iso:country":"US",
    "sg:address":"120 Old Squaw Trl",
    "sg:city":"Mooresville",
    "sg:classifiers":[
        {
            "category":"Wholesale",
            "subcategory":"Machinery & Supplies",
            "type":"Manufacturing & Wholesale Goods"
        }
    ],
    "sg:phone":"+1 704 662 3711",
    "sg:postcode":"28117",
    "sg:province":"NC",
    "sg:tags":[
        "equipment",
        "industrial"
    ],
    "wof:name":"Presentation Systems Inc",
    "wof:placetype":"venue"
},
  "geometry": {"coordinates":[-80.88980100000001,35.568402],"type":"Point"}
}