{
  "type": "Feature",
  "properties": {
    "iso:country":"US",
    "sg:address":"202 S Main St",
    "sg:city":"Davidson",
    "sg:classifiers":[
        {
            "category":"Professional",
            "type":"Services"
        }
    ],
    "sg:phone":"+1 704 655 2650",
    "sg:postcode":"28036",
    "sg:province":"NC",
    "wof:name":"Fiore Home & Garden",
    "wof:placetype":"venue"
},
  "geometry": {"coordinates":[-80.84912,35.497981],"type":"Point"}
}