{
  "type": "Feature",
  "properties": {
    "iso:country":"US",
    "sg:address":"826 Rollover Creek Rd",
    "sg:city":"New Bern",
    "sg:phone":"+1 252 637 9528",
    "sg:postcode":"28562",
    "sg:province":"NC",
    "sg:tags":[
        "farm",
        "grain",
        "cash"
    ],
    "wof:name":"William Jackson",
    "wof:placetype":"venue"
},
  "geometry": {"coordinates":[-77.243381,35.155159],"type":"Point"}
}