{
  "type": "Feature",
  "properties": {
    "addr:full":"211 W Main St Locust NC 28097",
    "addr:housenumber":"211",
    "addr:postcode":"28097",
    "addr:street":"W Main St",
    "iso:country":"US",
    "sg:address":"211 W Main St",
    "sg:city":"Locust",
    "sg:classifiers":[
        {
            "category":"Retail",
            "subcategory":"Auto Repair",
            "type":"Services"
        }
    ],
    "sg:phone":"+1 704 888 5242",
    "sg:postcode":"28097",
    "sg:province":"NC",
    "sg:tags":[
        "repairing",
        "automobile"
    ],
    "wof:name":"Locust Tire & Quick Lube",
    "wof:placetype":"venue"
},
  "geometry": {"coordinates":[-80.426934,35.259752],"type":"Point"}
}