{
  "type": "Feature",
  "properties": {
    "addr:full":"2309 Randleman Rd Greensboro NC 27406",
    "addr:housenumber":"2309",
    "addr:postcode":"27406",
    "addr:street":"Randleman Rd",
    "iso:country":"US",
    "sg:address":"2309 Randleman Rd",
    "sg:city":"Greensboro",
    "sg:classifiers":[
        {
            "category":"Shopping",
            "type":"Retail Goods"
        }
    ],
    "sg:phone":"+1 336 691 9555",
    "sg:postcode":"27406",
    "sg:province":"NC",
    "sg:tags":[
        "cosmetic",
        "perfume"
    ],
    "wof:name":"Save Dollar Beauty Supply",
    "wof:placetype":"venue"
},
  "geometry": {"coordinates":[-79.80056399999999,36.044486],"type":"Point"}
}