{
  "type": "Feature",
  "properties": {
    "addr:full":"7600 Statesville Rd Charlotte NC 28269",
    "addr:housenumber":"7600",
    "addr:postcode":"28269",
    "addr:street":"Statesville Rd",
    "iso:country":"US",
    "sg:address":"7600 Statesville Rd",
    "sg:city":"Charlotte",
    "sg:classifiers":[
        {
            "category":"Freight",
            "type":"Transportation"
        }
    ],
    "sg:phone":"+1 704 598 5436",
    "sg:postcode":"28269",
    "sg:province":"NC",
    "sg:tags":[
        "warehouse",
        "merchandise"
    ],
    "sg:website":"www.ryder.com",
    "wof:name":"Ryder Integrated Logistics Inc",
    "wof:placetype":"venue"
},
  "geometry": {"coordinates":[-80.843416,35.326177],"type":"Point"}
}