{
  "type": "Feature",
  "properties": {
    "addr:full":"2612 Catalina Ave Charlotte NC 28206",
    "addr:housenumber":"2612",
    "addr:postcode":"28206",
    "addr:street":"Catalina Ave",
    "iso:country":"US",
    "sg:address":"2612 Catalina Ave",
    "sg:city":"Charlotte",
    "sg:classifiers":[
        {
            "category":"Freight",
            "type":"Transportation"
        }
    ],
    "sg:phone":"+1 704 334 8546",
    "sg:postcode":"28206",
    "sg:province":"NC",
    "sg:tags":[
        "local",
        "without",
        "storage",
        "trucking"
    ],
    "wof:name":"Tyson Trucking",
    "wof:placetype":"venue"
},
  "geometry": {"coordinates":[-80.820806,35.25074],"type":"Point"}
}