{
  "type": "Feature",
  "properties": {
    "iso:country":"US",
    "sg:address":"1717 Toal St",
    "sg:city":"Charlotte",
    "sg:classifiers":[
        {
            "category":"Retail",
            "subcategory":"Auto Repair",
            "type":"Services"
        }
    ],
    "sg:phone":"+1 704 596 3318",
    "sg:postcode":"28206",
    "sg:province":"NC",
    "sg:tags":[
        "automobile",
        "top",
        "upholstery"
    ],
    "sg:website":"www.classicsofttrim.com",
    "wof:name":"Classic Soft Trim",
    "wof:placetype":"venue"
},
  "geometry": {"coordinates":[-80.81875599999999,35.266079],"type":"Point"}
}