{
  "type": "Feature",
  "properties": {
    "iso:country":"US",
    "sg:address":"197 Browntown Rd",
    "sg:city":"Magnolia",
    "sg:classifiers":[
        {
            "category":"Building & Trades",
            "subcategory":"Construction",
            "type":"Services"
        }
    ],
    "sg:phone":"+1 910 296 1193",
    "sg:postcode":"28453",
    "sg:province":"NC",
    "sg:tags":[
        "contractor"
    ],
    "wof:name":"Roger Tharpe Drywall Service",
    "wof:placetype":"venue"
},
  "geometry": {"coordinates":[-77.971659,34.892303],"type":"Point"}
}