{
  "type": "Feature",
  "properties": {
    "iso:country":"US",
    "sg:address":"1514 Purdue Dr",
    "sg:city":"Fayetteville",
    "sg:classifiers":[
        {
            "category":"Shopping",
            "type":"Retail Goods"
        }
    ],
    "sg:phone":"+1 910 323 3488",
    "sg:postcode":"28303",
    "sg:province":"NC",
    "sg:tags":[
        "pet",
        "shop"
    ],
    "wof:name":"Pet Land Aquatics",
    "wof:placetype":"venue"
},
  "geometry": {"coordinates":[-78.924333,35.044913],"type":"Point"}
}