{
  "type": "Feature",
  "properties": {
    "iso:country":"US",
    "sg:address":"7 Bluffside Ct",
    "sg:city":"Durham",
    "sg:classifiers":[
        {
            "category":"Wholesale",
            "subcategory":"Stationery",
            "type":"Manufacturing & Wholesale Goods"
        }
    ],
    "sg:phone":"+1 919 471 4821",
    "sg:postcode":"27712",
    "sg:province":"NC",
    "sg:tags":[
        "supply"
    ],
    "wof:name":"CB Forms LLC",
    "wof:placetype":"venue"
},
  "geometry": {"coordinates":[-78.893552,36.085888],"type":"Point"}
}