{
  "type": "Feature",
  "properties": {
    "addr:full":"904 Stone St Burlington NC 27215",
    "addr:housenumber":"904",
    "addr:postcode":"27215",
    "addr:street":"Stone St",
    "iso:country":"US",
    "sg:address":"904 Stone St",
    "sg:city":"Burlington",
    "sg:classifiers":[
        {
            "category":"Organizations",
            "subcategory":"Non-profit Organization",
            "type":"Services"
        }
    ],
    "sg:phone":"+1 336 227 3500",
    "sg:postcode":"27215",
    "sg:province":"NC",
    "sg:tags":[
        "info",
        "addiction",
        "abuse",
        "treatment",
        "drug"
    ],
    "wof:name":"God Did It Recovery Home-Women",
    "wof:placetype":"venue"
},
  "geometry": {"coordinates":[-79.42633600000001,36.08325],"type":"Point"}
}