{
  "type": "Feature",
  "properties": {
    "iso:country":"US",
    "sg:address":"317 N Front St",
    "sg:city":"Wilmington",
    "sg:classifiers":[
        {
            "category":"Shopping",
            "subcategory":"Gifts & Souvenirs",
            "type":"Retail Goods"
        }
    ],
    "sg:phone":"+1 910 815 3410",
    "sg:postcode":"28401",
    "sg:province":"NC",
    "sg:tags":[
        "shop"
    ],
    "wof:name":"A Zoo Train Shop",
    "wof:placetype":"venue"
},
  "geometry": {"coordinates":[-77.949326,34.239705],"type":"Point"}
}