{
  "type": "Feature",
  "properties": {
    "addr:full":"1012 Riverview Dr Boonville NC 27011",
    "addr:housenumber":"1012",
    "addr:postcode":"27011",
    "addr:street":"Riverview Dr",
    "iso:country":"US",
    "sg:address":"1012 Riverview Dr",
    "sg:city":"Boonville",
    "sg:phone":"+1 336 367 5357",
    "sg:postcode":"27011",
    "sg:province":"NC",
    "sg:tags":[
        "farm",
        "vineyard",
        "grape",
        "tobacco"
    ],
    "wof:name":"Kerry Von Johnson",
    "wof:placetype":"venue"
},
  "geometry": {"coordinates":[-80.69367200000001,36.263469],"type":"Point"}
}