{
  "type": "Feature",
  "properties": {
    "iso:country":"US",
    "sg:address":"615 Burton St",
    "sg:city":"Madison",
    "sg:classifiers":[
        {
            "category":"Restaurant",
            "type":"Food & Drink"
        }
    ],
    "sg:phone":"+1 336 427 6520",
    "sg:postcode":"27025",
    "sg:province":"NC",
    "wof:name":"Tiano Pizza",
    "wof:placetype":"venue"
},
  "geometry": {"coordinates":[-79.974744,36.401959],"type":"Point"}
}