{
  "type": "Feature",
  "properties": {
    "iso:country":"US",
    "sg:address":"8213 Oak Leaf Ct",
    "sg:city":"Raleigh",
    "sg:classifiers":[
        {
            "category":"Professional",
            "type":"Services"
        }
    ],
    "sg:phone":"+1 919 848 0959",
    "sg:postcode":"27615",
    "sg:province":"NC",
    "wof:name":"1310 CP LLC",
    "wof:placetype":"venue"
},
  "geometry": {"coordinates":[-78.639583,35.889868],"type":"Point"}
}