{
  "type": "Feature",
  "properties": {
    "iso:country":"US",
    "sg:address":"1702 Dunbar St",
    "sg:city":"Greensboro",
    "sg:classifiers":[
        {
            "category":"Personal",
            "type":"Services"
        }
    ],
    "sg:phone":"+1 336 988 5005",
    "sg:postcode":"27401",
    "sg:province":"NC",
    "sg:tags":[
        "miscellaneous"
    ],
    "wof:name":"U R First Protection Svc",
    "wof:placetype":"venue"
},
  "geometry": {"coordinates":[-79.763291,36.049006],"type":"Point"}
}