{
  "type": "Feature",
  "properties": {
    "addr:full":"102 Hilliard Rd Morrisville NC 27526",
    "addr:housenumber":"102",
    "addr:postcode":"27526",
    "addr:street":"Hilliard Rd",
    "iso:country":"US",
    "sg:address":"102 Hilliard Rd",
    "sg:city":"Morrisville",
    "sg:classifiers":[
        {
            "category":"Building & Trades",
            "subcategory":"Construction",
            "type":"Services"
        }
    ],
    "sg:phone":"+1 919 460 7755",
    "sg:postcode":"27526",
    "sg:province":"NC",
    "sg:tags":[
        "house"
    ],
    "wof:name":"Apex Construction Co",
    "wof:placetype":"venue"
},
  "geometry": {"coordinates":[-78.804851,35.534713],"type":"Point"}
}