{
  "type": "Feature",
  "properties": {
    "addr:full":"3231 W Highway 74 Monroe NC 28110",
    "addr:housenumber":"3231",
    "addr:postcode":"28110",
    "addr:street":"W Highway 74",
    "iso:country":"US",
    "sg:address":"3231 W Highway 74",
    "sg:city":"Monroe",
    "sg:classifiers":[
        {
            "category":"Autos & Motor Vehicles",
            "subcategory":"Auto Supplies",
            "type":"Retail Goods"
        },
        {
            "category":"Wholesale",
            "subcategory":"Electrical",
            "type":"Manufacturing & Wholesale Goods"
        }
    ],
    "sg:phone":"+1 704 225 8018",
    "sg:postcode":"28110",
    "sg:province":"NC",
    "sg:tags":[
        "battery",
        "automobile",
        "part",
        "batteries-storage",
        "accessory"
    ],
    "sg:website":"http://www.autozone.com",
    "wof:name":"AutoZone",
    "wof:placetype":"venue"
},
  "geometry": {"coordinates":[-80.58591800000001,35.026157],"type":"Point"}
}