{
  "type": "Feature",
  "properties": {
    "addr:full":"8910 Douglas Dr Charlotte NC 28217",
    "addr:housenumber":"8910",
    "addr:postcode":"28217",
    "addr:street":"Douglas Dr",
    "iso:country":"US",
    "sg:address":"8910 Douglas Dr",
    "sg:city":"Charlotte",
    "sg:classifiers":[
        {
            "category":"Education",
            "subcategory":"Special Training",
            "type":"Public Place"
        }
    ],
    "sg:phone":"+1 704 504 1461",
    "sg:postcode":"28217",
    "sg:province":"NC",
    "sg:tags":[
        "instruction",
        "driving"
    ],
    "wof:name":"Brunswick Driving School",
    "wof:placetype":"venue"
},
  "geometry": {"coordinates":[-80.954937,35.180466],"type":"Point"}
}