{
  "type": "Feature",
  "properties": {
    "addr:full":"1817 Fleetwood Dr Charlotte NC 28208",
    "addr:housenumber":"1817",
    "addr:postcode":"28208",
    "addr:street":"Fleetwood Dr",
    "iso:country":"US",
    "sg:address":"1817 Fleetwood Dr",
    "sg:city":"Charlotte",
    "sg:classifiers":[
        {
            "category":"Professional",
            "subcategory":"Management & Consulting",
            "type":"Services"
        }
    ],
    "sg:phone":"+1   ",
    "sg:postcode":"28208",
    "sg:province":"NC",
    "sg:tags":[
        "consultant",
        "executive",
        "it"
    ],
    "wof:name":"Innovative Technology Resource",
    "wof:placetype":"venue"
},
  "geometry": {"coordinates":[-80.876926,35.228999],"type":"Point"}
}