{
  "type": "Feature",
  "properties": {
    "addr:full":"2607 Bennington Rd Fayetteville NC 28303",
    "addr:housenumber":"2607",
    "addr:postcode":"28303",
    "addr:street":"Bennington Rd",
    "iso:country":"US",
    "sg:address":"2607 Bennington Rd",
    "sg:city":"Fayetteville",
    "sg:classifiers":[
        {
            "category":"Freight",
            "type":"Transportation"
        },
        {
            "category":"Retail",
            "subcategory":"Auto Repair",
            "type":"Services"
        }
    ],
    "sg:phone":"+1 910 826 1820",
    "sg:postcode":"28303",
    "sg:province":"NC",
    "sg:tags":[
        "automobile",
        "co",
        "drive",
        "transporter"
    ],
    "wof:name":"Mulvey Transport Inc",
    "wof:placetype":"venue"
},
  "geometry": {"coordinates":[-78.925651,35.060106],"type":"Point"}
}