{
  "type": "Feature",
  "properties": {
    "iso:country":"US",
    "sg:address":"1005 Glenway Dr",
    "sg:city":"Statesville",
    "sg:classifiers":[
        {
            "category":"Restaurant",
            "type":"Food & Drink"
        }
    ],
    "sg:menulink":"http://www.allmenus.com/nc/statesville/183446-kfc---kentucky-fried-chicken/menu/",
    "sg:phone":"+1 704 871 8118",
    "sg:postcode":"28625",
    "sg:province":"NC",
    "sg:tags":[
        "american",
        "chicken"
    ],
    "wof:name":"KFC - Kentucky Fried Chicken",
    "wof:placetype":"venue"
},
  "geometry": {"coordinates":[-80.868967,35.808876],"type":"Point"}
}