{
  "type": "Feature",
  "properties": {
    "iso:country":"US",
    "sg:address":"614 Capital Blvd",
    "sg:city":"Raleigh",
    "sg:classifiers":[
        {
            "category":"Real Estate",
            "subcategory":"Real Estate Operator",
            "type":"Services"
        }
    ],
    "sg:phone":"+1 919 828 2458",
    "sg:postcode":"27603",
    "sg:province":"NC",
    "sg:tags":[
        "condominium"
    ],
    "wof:name":"Cotton Mill Condo HOA Inc",
    "wof:placetype":"venue"
},
  "geometry": {"coordinates":[-78.641707,35.793647],"type":"Point"}
}