{
  "type": "Feature",
  "properties": {
    "iso:country":"US",
    "sg:address":"1006 Brantley St",
    "sg:city":"Mooresville",
    "sg:classifiers":[
        {
            "category":"Government",
            "subcategory":"Office",
            "type":"Public Place"
        }
    ],
    "sg:phone":"+1 704 663 4124",
    "sg:postcode":"28115",
    "sg:province":"NC",
    "sg:tags":[
        "management"
    ],
    "wof:name":"Probe Technology Inc",
    "wof:placetype":"venue"
},
  "geometry": {"coordinates":[-80.790267,35.586524],"type":"Point"}
}