{
  "type": "Feature",
  "properties": {
    "iso:country":"US",
    "sg:address":"5501 Josh Birmingham Pkwy",
    "sg:city":"Charlotte",
    "sg:classifiers":[
        {
            "category":"Shopping",
            "subcategory":"Clothing, Apparel, & Fashions",
            "type":"Retail Goods"
        },
        {
            "category":"Manufacturing",
            "subcategory":"Leather Goods",
            "type":"Manufacturing & Wholesale Goods"
        },
        {
            "category":"Shopping",
            "subcategory":"Shoes",
            "type":"Retail Goods"
        }
    ],
    "sg:phone":"+1 704 359 0133",
    "sg:postcode":"28208",
    "sg:province":"NC",
    "sg:tags":[
        "men's",
        "clothing",
        "store"
    ],
    "sg:website":"http://www.johnstonmurphy.com",
    "wof:name":"Johnston & Murphy",
    "wof:placetype":"venue"
},
  "geometry": {"coordinates":[-80.92774199999999,35.223251],"type":"Point"}
}