{
  "type": "Feature",
  "properties": {
    "iso:country":"US",
    "sg:address":"1211 Dorsey Ave",
    "sg:city":"Henderson",
    "sg:classifiers":[
        {
            "category":"Organizations",
            "subcategory":"Religious Organization",
            "type":"Services"
        }
    ],
    "sg:phone":"+1 252 492 2416",
    "sg:postcode":"27536",
    "sg:province":"NC",
    "sg:tags":[
        "church"
    ],
    "wof:name":"Church Of Christ",
    "wof:placetype":"venue"
},
  "geometry": {"coordinates":[-78.413589,36.319417],"type":"Point"}
}