{
  "type": "Feature",
  "properties": {
    "iso:country":"US",
    "sg:address":"1016 White Jenkins Rd",
    "sg:city":"Bessemer City",
    "sg:classifiers":[
        {
            "category":"Manufacturing",
            "subcategory":"Tools & Machinery",
            "type":"Manufacturing & Wholesale Goods"
        }
    ],
    "sg:phone":"+1 704 922 1725",
    "sg:postcode":"28016",
    "sg:province":"NC",
    "sg:tags":[
        "textile",
        "parts"
    ],
    "wof:name":"American Machine Co",
    "wof:placetype":"venue"
},
  "geometry": {"coordinates":[-81.229158,35.326569],"type":"Point"}
}