{
  "type": "Feature",
  "properties": {
    "addr:full":"329 New Leicester Hwy Asheville NC 28806",
    "addr:housenumber":"329",
    "addr:postcode":"28806",
    "addr:street":"New Leicester Hwy",
    "iso:country":"US",
    "sg:address":"329 New Leicester Hwy",
    "sg:city":"Asheville",
    "sg:classifiers":[
        {
            "category":"Shopping",
            "subcategory":"Beauty & Cosmetics",
            "type":"Retail Goods"
        }
    ],
    "sg:phone":"+1 828 450 5482",
    "sg:postcode":"28806",
    "sg:province":"NC",
    "sg:tags":[
        "supply"
    ],
    "sg:website":"www.goodjudy.com",
    "wof:name":"Good Judy",
    "wof:placetype":"venue"
},
  "geometry": {"coordinates":[-82.622204,35.599669],"type":"Point"}
}