{
  "type": "Feature",
  "properties": {
    "addr:full":"1407 N Cansler St Kings Mountain NC 28086",
    "addr:housenumber":"1407",
    "addr:postcode":"28086",
    "addr:street":"N Cansler St",
    "iso:country":"US",
    "sg:address":"1407 N Cansler St",
    "sg:city":"Kings Mountain",
    "sg:classifiers":[
        {
            "category":"Mining & Drilling",
            "type":"Manufacturing & Wholesale Goods"
        }
    ],
    "sg:phone":"+1 704 734 3537",
    "sg:postcode":"28086",
    "sg:province":"NC",
    "sg:tags":[
        "nonmetallic",
        "mineral"
    ],
    "wof:name":"Patterson Plant",
    "wof:placetype":"venue"
},
  "geometry": {"coordinates":[-81.34714099999999,35.259507],"type":"Point"}
}