{
  "type": "Feature",
  "properties": {
    "iso:country":"US",
    "sg:address":"890 Brevard Road",
    "sg:city":"Asheville",
    "sg:classifiers":[
        {
            "category":"Travel",
            "subcategory":"Hotels & Motels",
            "type":"Entertainment"
        }
    ],
    "sg:phone":"+1 828 665 4000",
    "sg:postcode":"28806",
    "sg:province":"NC",
    "sg:website":"www.comfortsuites.com/hotel-ashe...",
    "wof:name":"Comfort Suites",
    "wof:placetype":"venue"
},
  "geometry": {"coordinates":[-82.60478999999999,35.532351],"type":"Point"}
}