{
  "type": "Feature",
  "properties": {
    "iso:country":"US",
    "sg:address":"110 Bosswood Ct",
    "sg:city":"Cary",
    "sg:classifiers":[
        {
            "category":"Banks & Credit Unions",
            "subcategory":"Investment Brokerage",
            "type":"Services"
        }
    ],
    "sg:phone":"+1 919 303 9360",
    "sg:postcode":"27518",
    "sg:province":"NC",
    "sg:tags":[
        "advisory",
        "financial"
    ],
    "wof:name":"QST Financial Group",
    "wof:placetype":"venue"
},
  "geometry": {"coordinates":[-78.80403200000001,35.718764],"type":"Point"}
}