{
  "type": "Feature",
  "properties": {
    "addr:full":"1905 Northview Dr Kinston NC 28501",
    "addr:housenumber":"1905",
    "addr:postcode":"28501",
    "addr:street":"Northview Dr",
    "iso:country":"US",
    "sg:address":"1905 Northview Dr",
    "sg:city":"Kinston",
    "sg:classifiers":[
        {
            "category":"Freight",
            "type":"Transportation"
        }
    ],
    "sg:phone":"+1 252 522 4153",
    "sg:postcode":"28501",
    "sg:province":"NC",
    "sg:tags":[
        "operator",
        "distance",
        "long",
        "trucking"
    ],
    "wof:name":"Nbs Trucking Inc",
    "wof:placetype":"venue"
},
  "geometry": {"coordinates":[-77.55461699999999,35.280236],"type":"Point"}
}