{
  "type": "Feature",
  "properties": {
    "iso:country":"US",
    "sg:address":"106 York Way",
    "sg:city":"Advance",
    "sg:classifiers":[
        {
            "category":"Banks & Credit Unions",
            "subcategory":"Bank",
            "type":"Services"
        }
    ],
    "sg:phone":"+1 336 998 1799",
    "sg:postcode":"27006",
    "sg:province":"NC",
    "wof:name":"Bank Of The Carolinas",
    "wof:placetype":"venue"
},
  "geometry": {"coordinates":[-80.426011,36.010681],"type":"Point"}
}