{
  "type": "Feature",
  "properties": {
    "iso:country":"US",
    "sg:address":"2 Jackson St",
    "sg:city":"Sylva",
    "sg:classifiers":[
        {
            "category":"Professional",
            "subcategory":"Art Services",
            "type":"Services"
        }
    ],
    "sg:phone":"+1 828 631 4644",
    "sg:postcode":"28779",
    "sg:province":"NC",
    "sg:tags":[
        "graphic",
        "designer"
    ],
    "wof:name":"Hard Times Imageworks",
    "wof:placetype":"venue"
},
  "geometry": {"coordinates":[-83.22478700000001,35.372693],"type":"Point"}
}