{
  "type": "Feature",
  "properties": {
    "iso:country":"US",
    "sg:address":"204 Springwood Pl",
    "sg:city":"Clayton",
    "sg:classifiers":[
        {
            "category":"Health Services",
            "subcategory":"Clinic",
            "type":"Services"
        }
    ],
    "sg:phone":"+1 919 553 3424",
    "sg:postcode":"27520",
    "sg:province":"NC",
    "wof:name":"Cigna Tmanage",
    "wof:placetype":"venue"
},
  "geometry": {"coordinates":[-78.491799,35.64773],"type":"Point"}
}