{
  "type": "Feature",
  "properties": {
    "addr:full":"2314 Starnes St Morganton NC 28655",
    "addr:housenumber":"2314",
    "addr:postcode":"28655",
    "addr:street":"Starnes St",
    "iso:country":"US",
    "sg:address":"2314 Starnes St",
    "sg:city":"Morganton",
    "sg:classifiers":[
        {
            "category":"Organizations",
            "subcategory":"Religious Organization",
            "type":"Services"
        }
    ],
    "sg:phone":"+1 828 433 1100",
    "sg:postcode":"28655",
    "sg:province":"NC",
    "sg:tags":[
        "church"
    ],
    "wof:name":"Christ United Methodist Church",
    "wof:placetype":"venue"
},
  "geometry": {"coordinates":[-81.617915,35.745888],"type":"Point"}
}