{
  "type": "Feature",
  "properties": {
    "addr:full":"9782 Lebanon Church Rd Clarendon NC 28432",
    "addr:housenumber":"9782",
    "addr:postcode":"28432",
    "addr:street":"Lebanon Church Rd",
    "iso:country":"US",
    "sg:address":"9782 Lebanon Church Rd",
    "sg:city":"Clarendon",
    "sg:classifiers":[
        {
            "category":"Farming",
            "subcategory":"Farm",
            "type":"Manufacturing & Wholesale Goods"
        }
    ],
    "sg:phone":"+1 910 653 5572",
    "sg:postcode":"28432",
    "sg:province":"NC",
    "sg:tags":[
        "crop",
        "general"
    ],
    "wof:name":"Bay Ridge Farms Inc",
    "wof:placetype":"venue"
},
  "geometry": {"coordinates":[-78.717505,34.09608],"type":"Point"}
}