{
  "type": "Feature",
  "properties": {
    "addr:full":"110 Cape Fear Dr Southport NC 28461",
    "addr:housenumber":"110",
    "addr:postcode":"28461",
    "addr:street":"Cape Fear Dr",
    "iso:country":"US",
    "sg:address":"110 Cape Fear Dr",
    "sg:city":"Southport",
    "sg:classifiers":[
        {
            "category":"Organizations",
            "subcategory":"Community Association",
            "type":"Services"
        }
    ],
    "sg:phone":"+1   ",
    "sg:postcode":"28461",
    "sg:province":"NC",
    "wof:name":"Masonic Lodge",
    "wof:placetype":"venue"
},
  "geometry": {"coordinates":[-78.006348,33.92531],"type":"Point"}
}