{
  "type": "Feature",
  "properties": {
    "iso:country":"US",
    "sg:address":"6810 Beach Dr SW",
    "sg:city":"Ocean Isle Beach",
    "sg:classifiers":[
        {
            "category":"Home & Garden",
            "subcategory":"Building Materials",
            "type":"Retail Goods"
        }
    ],
    "sg:phone":"+1 910 575 2379",
    "sg:postcode":"28469",
    "sg:province":"NC",
    "sg:tags":[
        "windows"
    ],
    "wof:name":"Coastal Window & Door",
    "wof:placetype":"venue"
},
  "geometry": {"coordinates":[-78.46344000000001,33.899772],"type":"Point"}
}