{
  "type": "Feature",
  "properties": {
    "iso:country":"US",
    "sg:address":"82 Court Sq",
    "sg:city":"Mocksville",
    "sg:classifiers":[
        {
            "category":"Professional",
            "subcategory":"Advertising",
            "type":"Services"
        }
    ],
    "sg:phone":"+1 336 753 0480",
    "sg:postcode":"27028",
    "sg:province":"NC",
    "sg:tags":[
        "counselor"
    ],
    "wof:name":"Madison Avenue South Ad Agency",
    "wof:placetype":"venue"
},
  "geometry": {"coordinates":[-80.561577,35.894353],"type":"Point"}
}