{
  "type": "Feature",
  "properties": {
    "iso:country":"US",
    "sg:address":"1410 Blowing Rock Blvd",
    "sg:city":"Lenoir",
    "sg:classifiers":[
        {
            "category":"Real Estate",
            "subcategory":"Real Estate Agent",
            "type":"Services"
        }
    ],
    "sg:phone":"+1 828 758 7053",
    "sg:postcode":"28645",
    "sg:province":"NC",
    "wof:name":"Tuttle Realty Company Inc",
    "wof:placetype":"venue"
},
  "geometry": {"coordinates":[-81.529597,35.932669],"type":"Point"}
}