{
  "type": "Feature",
  "properties": {
    "addr:full":"1416 Lakewind Ct Raleigh NC 27603",
    "addr:housenumber":"1416",
    "addr:postcode":"27603",
    "addr:street":"Lakewind Ct",
    "iso:country":"US",
    "sg:address":"1416 Lakewind Ct",
    "sg:city":"Raleigh",
    "sg:classifiers":[
        {
            "category":"Retail",
            "subcategory":"Repair Shop",
            "type":"Services"
        }
    ],
    "sg:phone":"+1   ",
    "sg:postcode":"27603",
    "sg:province":"NC",
    "sg:tags":[
        "test",
        "air",
        "balance",
        "system",
        "conditioning"
    ],
    "wof:name":"Tester Technical Services Inc",
    "wof:placetype":"venue"
},
  "geometry": {"coordinates":[-78.69411599999999,35.69701],"type":"Point"}
}