{
  "type": "Feature",
  "properties": {
    "iso:country":"US",
    "sg:address":"3410 Old Onslow Rd",
    "sg:city":"Greensboro",
    "sg:classifiers":[
        {
            "category":"Wholesale",
            "subcategory":"Furniture",
            "type":"Manufacturing & Wholesale Goods"
        }
    ],
    "sg:phone":"+1 336 852 4242",
    "sg:postcode":"27407",
    "sg:province":"NC",
    "wof:name":"Lucky Ducks Ltd Inc",
    "wof:placetype":"venue"
},
  "geometry": {"coordinates":[-79.876104,36.012546],"type":"Point"}
}