{
  "type": "Feature",
  "properties": {
    "iso:country":"US",
    "sg:address":"800 N Mangum St",
    "sg:city":"Durham",
    "sg:classifiers":[
        {
            "category":"Retail",
            "subcategory":"Laundry & Dry Cleaning",
            "type":"Services"
        }
    ],
    "sg:phone":"+1 919 680 2032",
    "sg:postcode":"27701",
    "sg:province":"NC",
    "sg:tags":[
        "cleaners",
        "rug",
        "carpet"
    ],
    "wof:name":"Mobley Professional Carpet",
    "wof:placetype":"venue"
},
  "geometry": {"coordinates":[-78.89519,36.001917],"type":"Point"}
}