{
  "type": "Feature",
  "properties": {
    "addr:full":"1007 N Scales St Reidsville NC 27320",
    "addr:housenumber":"1007",
    "addr:postcode":"27320",
    "addr:street":"N Scales St",
    "iso:country":"US",
    "sg:address":"1007 N Scales St",
    "sg:city":"Reidsville",
    "sg:classifiers":[
        {
            "category":"Social Services",
            "type":"Services"
        }
    ],
    "sg:phone":"+1 336 342 0780",
    "sg:postcode":"27320",
    "sg:province":"NC",
    "sg:tags":[
        "domestic",
        "violence",
        "sexual"
    ],
    "wof:name":"Help Inc",
    "wof:placetype":"venue"
},
  "geometry": {"coordinates":[-79.666735,36.375123],"type":"Point"}
}