{
  "type": "Feature",
  "properties": {
    "iso:country":"US",
    "sg:address":"433 Albemarle Rd",
    "sg:city":"Troy",
    "sg:classifiers":[
        {
            "category":"Food & Beverages",
            "subcategory":"Groceries & Convenience Stores",
            "type":"Retail Goods"
        }
    ],
    "sg:phone":"+1 910 576 1745",
    "sg:postcode":"27371",
    "sg:province":"NC",
    "wof:name":"Quik Chek Inc",
    "wof:placetype":"venue"
},
  "geometry": {"coordinates":[-79.900925,35.35516],"type":"Point"}
}