{
  "type": "Feature",
  "properties": {
    "addr:full":"4650 Kahn Dr Lumberton NC 28358",
    "addr:postcode":"4650;28358",
    "addr:street":"Kahn Dr",
    "iso:country":"US",
    "sg:address":"4650 Kahn Dr",
    "sg:city":"Lumberton",
    "sg:classifiers":[
        {
            "category":"Government",
            "subcategory":"Police Station",
            "type":"Public Place"
        }
    ],
    "sg:phone":"+1 910 618 5555",
    "sg:postcode":"28358",
    "sg:province":"NC",
    "sg:tags":[
        "protection"
    ],
    "wof:name":"State Hwy Patrol-Troop B",
    "wof:placetype":"venue"
},
  "geometry": {"coordinates":[-79.00782599999999,34.662897],"type":"Point"}
}