{
  "type": "Feature",
  "properties": {
    "addr:full":"225 Glenwood Ave Raleigh NC 27603",
    "addr:housenumber":"225",
    "addr:postcode":"27603",
    "addr:street":"Glenwood Ave",
    "iso:country":"US",
    "sg:address":"225 Glenwood Ave",
    "sg:city":"Raleigh",
    "sg:classifiers":[
        {
            "category":"Museum",
            "type":"Entertainment"
        }
    ],
    "sg:phone":"+1   ",
    "sg:postcode":"27603",
    "sg:province":"NC",
    "sg:tags":[
        "art",
        "gallery"
    ],
    "wof:name":"Lee Hansley Gallery",
    "wof:placetype":"venue"
},
  "geometry": {"coordinates":[-78.64748,35.78384],"type":"Point"}
}