{
  "type": "Feature",
  "properties": {
    "iso:country":"US",
    "sg:address":"510 State Hwy 27",
    "sg:city":"Stanley",
    "sg:classifiers":[
        {
            "category":"Health Services",
            "subcategory":"Doctor",
            "type":"Services"
        }
    ],
    "sg:phone":"+1 704 263 4716",
    "sg:postcode":"28164",
    "sg:province":"NC",
    "sg:tags":[
        "physician",
        "surgeon"
    ],
    "wof:name":"James S Forrester MD",
    "wof:placetype":"venue"
},
  "geometry": {"coordinates":[-81.089922,35.352666],"type":"Point"}
}