{
  "type": "Feature",
  "properties": {
    "addr:full":"721 Clayton Carriker Rd Ellerbe NC 28338",
    "addr:housenumber":"721",
    "addr:postcode":"28338",
    "addr:street":"Clayton Carriker Rd",
    "iso:country":"US",
    "sg:address":"721 Clayton Carriker Rd",
    "sg:city":"Ellerbe",
    "sg:classifiers":[
        {
            "category":"Building & Trades",
            "subcategory":"Construction",
            "type":"Services"
        }
    ],
    "sg:phone":"+1 910 652 5817",
    "sg:postcode":"28338",
    "sg:province":"NC",
    "sg:tags":[
        "house"
    ],
    "wof:name":"Parsons Construction Co",
    "wof:placetype":"venue"
},
  "geometry": {"coordinates":[-79.770916,35.132257],"type":"Point"}
}