{
  "type": "Feature",
  "properties": {
    "iso:country":"US",
    "sg:address":"370 Hilliard Dr",
    "sg:city":"Fayetteville",
    "sg:classifiers":[
        {
            "category":"Organizations",
            "subcategory":"Religious Organization",
            "type":"Services"
        }
    ],
    "sg:phone":"+1 910 488 9289",
    "sg:postcode":"28311",
    "sg:province":"NC",
    "sg:tags":[
        "clergy"
    ],
    "wof:name":"J C White",
    "wof:placetype":"venue"
},
  "geometry": {"coordinates":[-78.89087499999999,35.116248],"type":"Point"}
}