{
  "type": "Feature",
  "properties": {
    "addr:full":"705 Cotton Grove Rd Lexington NC 27292",
    "addr:housenumber":"705",
    "addr:postcode":"27292",
    "addr:street":"Cotton Grove Rd",
    "iso:country":"US",
    "sg:address":"705 Cotton Grove Rd",
    "sg:city":"Lexington",
    "sg:classifiers":[
        {
            "category":"Home & Garden",
            "subcategory":"Building Materials",
            "type":"Retail Goods"
        }
    ],
    "sg:phone":"+1 336 243 1388",
    "sg:postcode":"27292",
    "sg:province":"NC",
    "sg:tags":[
        "mixed",
        "concrete"
    ],
    "wof:name":"Black Concrete Inc",
    "wof:placetype":"venue"
},
  "geometry": {"coordinates":[-80.263169,35.804537],"type":"Point"}
}