{
  "type": "Feature",
  "properties": {
    "iso:country":"US",
    "sg:address":"929 Harper Rd",
    "sg:city":"Gastonia",
    "sg:classifiers":[
        {
            "category":"Retail",
            "subcategory":"Auto Repair",
            "type":"Services"
        }
    ],
    "sg:phone":"+1 704 867 4301",
    "sg:postcode":"28056",
    "sg:province":"NC",
    "sg:tags":[
        "repairing",
        "automotive",
        "automobile"
    ],
    "wof:name":"Wink's Front End Shop",
    "wof:placetype":"venue"
},
  "geometry": {"coordinates":[-81.144307,35.18982],"type":"Point"}
}