{
  "type": "Feature",
  "properties": {
    "addr:full":"8300 Arrowridge Blvd Charlotte NC 28273",
    "addr:housenumber":"8300",
    "addr:postcode":"28273",
    "addr:street":"Arrowridge Blvd",
    "iso:country":"US",
    "sg:address":"8300 Arrowridge Blvd",
    "sg:city":"Charlotte",
    "sg:classifiers":[
        {
            "category":"Autos & Motor Vehicles",
            "subcategory":"Automobile Sales",
            "type":"Retail Goods"
        }
    ],
    "sg:phone":"+1 704 523 8616",
    "sg:postcode":"28273",
    "sg:province":"NC",
    "wof:name":"Toyota Industries North Americ",
    "wof:placetype":"venue"
},
  "geometry": {"coordinates":[-80.911765,35.130832],"type":"Point"}
}