{
  "type": "Feature",
  "properties": {
    "addr:full":"737 Franklin St Roanoke Rapids NC 27870",
    "addr:housenumber":"737",
    "addr:postcode":"27870",
    "addr:street":"Franklin St",
    "iso:country":"US",
    "sg:address":"737 Franklin St",
    "sg:city":"Roanoke Rapids",
    "sg:classifiers":[
        {
            "category":"Insurance",
            "subcategory":"Insurance Agent",
            "type":"Services"
        }
    ],
    "sg:phone":"+1 252 519 0700",
    "sg:postcode":"27870",
    "sg:province":"NC",
    "wof:name":"Manning J Rives Jr Insur Off",
    "wof:placetype":"venue"
},
  "geometry": {"coordinates":[-77.660652,36.462394],"type":"Point"}
}