{
  "type": "Feature",
  "properties": {
    "iso:country":"US",
    "sg:address":"108 Ponderosa Rd",
    "sg:city":"Stoneville",
    "sg:classifiers":[
        {
            "category":"Sports & Exercise",
            "subcategory":"Golf",
            "type":"Entertainment"
        },
        {
            "category":"Recreation",
            "type":"Entertainment"
        }
    ],
    "sg:phone":"+1 336 573 9025",
    "sg:postcode":"27048",
    "sg:province":"NC",
    "sg:tags":[
        "course",
        "public"
    ],
    "wof:name":"Ponderosa Golf Clubs",
    "wof:placetype":"venue"
},
  "geometry": {"coordinates":[-79.89552999999999,36.46411],"type":"Point"}
}