{
  "type": "Feature",
  "properties": {
    "iso:country":"US",
    "sg:address":"7113 Little Mountain Rd",
    "sg:city":"Sherrills Ford",
    "sg:classifiers":[
        {
            "category":"Professional",
            "subcategory":"Business Services",
            "type":"Services"
        }
    ],
    "sg:phone":"+1   ",
    "sg:postcode":"28673",
    "sg:province":"NC",
    "wof:name":"Nancy Holmes Interiors",
    "wof:placetype":"venue"
},
  "geometry": {"coordinates":[-81.015517,35.586178],"type":"Point"}
}