{
  "type": "Feature",
  "properties": {
    "addr:full":"3775 Vest Mill Rd Winston Salem NC 27103",
    "addr:housenumber":"3775",
    "addr:postcode":"27103",
    "addr:street":"Vest Mill Rd",
    "iso:country":"US",
    "sg:address":"3775 Vest Mill Rd",
    "sg:city":"Winston Salem",
    "sg:classifiers":[
        {
            "category":"Social Services",
            "subcategory":"Job Training",
            "type":"Services"
        }
    ],
    "sg:phone":"+1   ",
    "sg:postcode":"27103",
    "sg:province":"NC",
    "wof:name":"Leadership Performance Systems",
    "wof:placetype":"venue"
},
  "geometry": {"coordinates":[-80.313889,36.074272],"type":"Point"}
}