{
  "type": "Feature",
  "properties": {
    "iso:country":"US",
    "sg:address":"1005 Tomlinson Blvd",
    "sg:city":"New Bern",
    "sg:classifiers":[
        {
            "category":"Professional",
            "subcategory":"Business Services",
            "type":"Services"
        }
    ],
    "sg:phone":"+1 252 633 6302",
    "sg:postcode":"28562",
    "sg:province":"NC",
    "sg:tags":[
        "interior",
        "consultant",
        "design",
        "decorator"
    ],
    "wof:name":"Window Wall & Interior Decor",
    "wof:placetype":"venue"
},
  "geometry": {"coordinates":[-77.119889,35.098266],"type":"Point"}
}