{
  "type": "Feature",
  "properties": {
    "addr:full":"109 E Main St Jamestown NC 27282",
    "addr:housenumber":"109",
    "addr:postcode":"27282",
    "addr:street":"E Main St",
    "iso:country":"US",
    "sg:address":"109 E Main St",
    "sg:city":"Jamestown",
    "sg:classifiers":[
        {
            "category":"Shopping",
            "subcategory":"Stationery & Office Supplies",
            "type":"Retail Goods"
        }
    ],
    "sg:phone":"+1 336 886 4859",
    "sg:postcode":"27282",
    "sg:province":"NC",
    "sg:tags":[
        "map"
    ],
    "wof:name":"Cartographic Aerial Mapping",
    "wof:placetype":"venue"
},
  "geometry": {"coordinates":[-79.935461,35.99531],"type":"Point"}
}