{
  "type": "Feature",
  "properties": {
    "addr:full":"13501 Albemarle Rd Charlotte NC 28227",
    "addr:housenumber":"13501",
    "addr:postcode":"28227",
    "addr:street":"Albemarle Rd",
    "iso:country":"US",
    "sg:address":"13501 Albemarle Rd",
    "sg:city":"Charlotte",
    "sg:classifiers":[
        {
            "category":"Education",
            "subcategory":"School",
            "type":"Public Place"
        }
    ],
    "sg:phone":"+1 704 343 6922",
    "sg:postcode":"28227",
    "sg:province":"NC",
    "sg:tags":[
        "elementary"
    ],
    "wof:name":"Clear Creek Elementary",
    "wof:placetype":"venue"
},
  "geometry": {"coordinates":[-80.625964,35.223223],"type":"Point"}
}