{
  "type": "Feature",
  "properties": {
    "iso:country":"US",
    "sg:address":"602 Catherine Creek Rd",
    "sg:city":"Ahoskie",
    "sg:classifiers":[
        {
            "category":"Manufacturing",
            "subcategory":"Printing",
            "type":"Manufacturing & Wholesale Goods"
        }
    ],
    "sg:phone":"+1 252 332 4999",
    "sg:postcode":"27910",
    "sg:province":"NC",
    "sg:tags":[
        "lithographic",
        "commercial"
    ],
    "wof:name":"Dilday Printing",
    "wof:placetype":"venue"
},
  "geometry": {"coordinates":[-76.97915999999999,36.277735],"type":"Point"}
}