{
  "type": "Feature",
  "properties": {
    "addr:full":"3553 N Sharon Amity Rd Charlotte NC 28205",
    "addr:housenumber":"3553",
    "addr:postcode":"28205",
    "addr:street":"N Sharon Amity Rd",
    "iso:country":"US",
    "sg:address":"3553 N Sharon Amity Rd",
    "sg:city":"Charlotte",
    "sg:classifiers":[
        {
            "category":"Professional",
            "subcategory":"Art Services",
            "type":"Services"
        }
    ],
    "sg:phone":"+1 704 537 8881",
    "sg:postcode":"28205",
    "sg:province":"NC",
    "sg:tags":[
        "photographer"
    ],
    "wof:name":"Fotovision",
    "wof:placetype":"venue"
},
  "geometry": {"coordinates":[-80.757318,35.209547],"type":"Point"}
}