{
  "type": "Feature",
  "properties": {
    "iso:country":"US",
    "sg:address":"1645 Hoover Rd",
    "sg:city":"Hampstead",
    "sg:classifiers":[
        {
            "category":"Communications",
            "type":"Services"
        }
    ],
    "sg:phone":"+1 910 270 1622",
    "sg:postcode":"28443",
    "sg:province":"NC",
    "sg:tags":[
        "communication"
    ],
    "wof:name":"Underground Comm Specialist",
    "wof:placetype":"venue"
},
  "geometry": {"coordinates":[-77.710055,34.395225],"type":"Point"}
}