{
  "type": "Feature",
  "properties": {
    "addr:full":"114 Dixie Blvd Morganton NC 28655",
    "addr:housenumber":"114",
    "addr:postcode":"28655",
    "addr:street":"Dixie Blvd",
    "iso:country":"US",
    "sg:address":"114 Dixie Blvd",
    "sg:city":"Morganton",
    "sg:classifiers":[
        {
            "category":"Manufacturing",
            "subcategory":"Paper Products",
            "type":"Manufacturing & Wholesale Goods"
        }
    ],
    "sg:phone":"+1 828 584 1511",
    "sg:postcode":"28655",
    "sg:province":"NC",
    "sg:tags":[
        "corrugated",
        "box",
        "fiber",
        "container",
        "mfg",
        "solid"
    ],
    "sg:website":"www.packagingcorp.com",
    "wof:name":"Packaging Corporation America",
    "wof:placetype":"venue"
},
  "geometry": {"coordinates":[-81.74489199999999,35.72764],"type":"Point"}
}