{
  "type": "Feature",
  "properties": {
    "iso:country":"US",
    "sg:address":"3823 Barringer Dr",
    "sg:city":"Charlotte",
    "sg:classifiers":[
        {
            "category":"Building & Trades",
            "subcategory":"Equipment Rental",
            "type":"Services"
        },
        {
            "category":"Wholesale",
            "subcategory":"Electrical",
            "type":"Manufacturing & Wholesale Goods"
        }
    ],
    "sg:phone":"+1 704 679 9488",
    "sg:postcode":"28217",
    "sg:province":"NC",
    "sg:tags":[
        "audio",
        "leasing"
    ],
    "sg:website":"www.illuminationdynamics.com",
    "wof:name":"Illumination Dynamics",
    "wof:placetype":"venue"
},
  "geometry": {"coordinates":[-80.888091,35.196808],"type":"Point"}
}