{
  "type": "Feature",
  "properties": {
    "iso:country":"US",
    "sg:address":"1029 Sewickley Dr",
    "sg:city":"Charlotte",
    "sg:classifiers":[
        {
            "category":"Building & Trades",
            "subcategory":"Landscaping Services",
            "type":"Services"
        }
    ],
    "sg:phone":"+1 704 523 0147",
    "sg:postcode":"28209",
    "sg:province":"NC",
    "wof:name":"Pine Ridge Nursery",
    "wof:placetype":"venue"
},
  "geometry": {"coordinates":[-80.859675,35.178565],"type":"Point"}
}