{
  "type": "Feature",
  "properties": {
    "iso:country":"US",
    "sg:address":"8731 Emerald Plantation Rd",
    "sg:city":"Emerald Isle",
    "sg:classifiers":[
        {
            "category":"Professional",
            "type":"Services"
        }
    ],
    "sg:phone":"+1 252 354 5605",
    "sg:postcode":"28594",
    "sg:province":"NC",
    "sg:tags":[
        "establishment"
    ],
    "wof:name":"Emerald Plantation",
    "wof:placetype":"venue"
},
  "geometry": {"coordinates":[-77.04894400000001,34.666446],"type":"Point"}
}