{
  "type": "Feature",
  "properties": {
    "iso:country":"US",
    "sg:address":"318 S South St",
    "sg:city":"Gastonia",
    "sg:classifiers":[
        {
            "category":"Real Estate",
            "subcategory":"Real Estate Agent",
            "type":"Services"
        }
    ],
    "sg:phone":"+1 704 865 0646",
    "sg:postcode":"28052",
    "sg:province":"NC",
    "sg:tags":[
        "appraiser"
    ],
    "wof:name":"Norris & Assoc Appraisals",
    "wof:placetype":"venue"
},
  "geometry": {"coordinates":[-81.183724,35.259401],"type":"Point"}
}