{
  "type": "Feature",
  "properties": {
    "addr:full":"2009 Allenwood Rd Mc Leansville NC 27301",
    "addr:housenumber":"2009",
    "addr:postcode":"27301",
    "addr:street":"Allenwood Rd",
    "iso:country":"US",
    "sg:address":"2009 Allenwood Rd",
    "sg:city":"Mc Leansville",
    "sg:classifiers":[
        {
            "category":"Retail",
            "subcategory":"Repair Shop",
            "type":"Services"
        }
    ],
    "sg:phone":"+1   ",
    "sg:postcode":"27301",
    "sg:province":"NC",
    "sg:tags":[
        "equipment",
        "printing"
    ],
    "wof:name":"Holcomb Mickey Sales & Service",
    "wof:placetype":"venue"
},
  "geometry": {"coordinates":[-79.652018,36.111953],"type":"Point"}
}