{
  "type": "Feature",
  "properties": {
    "addr:full":"270 Tuggie Eure Rd Eure NC 27937",
    "addr:housenumber":"270",
    "addr:postcode":"27937",
    "addr:street":"Tuggie Eure Rd",
    "iso:country":"US",
    "sg:address":"270 Tuggie Eure Rd",
    "sg:city":"Eure",
    "sg:classifiers":[
        {
            "category":"Building & Trades",
            "subcategory":"Construction",
            "type":"Services"
        }
    ],
    "sg:phone":"+1 252 357 0627",
    "sg:postcode":"27937",
    "sg:province":"NC",
    "sg:tags":[
        "residential",
        "nonresidential"
    ],
    "wof:name":"Hall Construction Co",
    "wof:placetype":"venue"
},
  "geometry": {"coordinates":[-76.828951,36.478682],"type":"Point"}
}