{
  "type": "Feature",
  "properties": {
    "iso:country":"US",
    "sg:address":"815 Broad St",
    "sg:city":"New Bern",
    "sg:classifiers":[
        {
            "category":"Food & Beverages",
            "subcategory":"Groceries & Convenience Stores",
            "type":"Retail Goods"
        }
    ],
    "sg:phone":"+1 252 637 4131",
    "sg:postcode":"28560",
    "sg:province":"NC",
    "wof:name":"Handy Mart 7",
    "wof:placetype":"venue"
},
  "geometry": {"coordinates":[-77.047574,35.108185],"type":"Point"}
}