{
  "type": "Feature",
  "properties": {
    "iso:country":"US",
    "sg:address":"4360 Glenn High Rd",
    "sg:city":"Winston Salem",
    "sg:classifiers":[
        {
            "category":"Professional",
            "subcategory":"Management & Consulting",
            "type":"Services"
        }
    ],
    "sg:phone":"+1   ",
    "sg:postcode":"27107",
    "sg:province":"NC",
    "sg:tags":[
        "business"
    ],
    "wof:name":"Carol Smith Tax Consultant",
    "wof:placetype":"venue"
},
  "geometry": {"coordinates":[-80.128057,36.069994],"type":"Point"}
}