{
  "type": "Feature",
  "properties": {
    "addr:full":"3944 Justin Brook Ln Walkertown NC 27051",
    "addr:housenumber":"3944",
    "addr:postcode":"27051",
    "addr:street":"Justin Brook Ln",
    "iso:country":"US",
    "sg:address":"3944 Justin Brook Ln",
    "sg:city":"Walkertown",
    "sg:classifiers":[
        {
            "category":"Professional",
            "subcategory":"Art Services",
            "type":"Services"
        }
    ],
    "sg:phone":"+1   ",
    "sg:postcode":"27051",
    "sg:province":"NC",
    "sg:tags":[
        "photography",
        "commercial"
    ],
    "wof:name":"Cff",
    "wof:placetype":"venue"
},
  "geometry": {"coordinates":[-80.14672299999999,36.180911],"type":"Point"}
}