{
  "type": "Feature",
  "properties": {
    "iso:country":"US",
    "sg:address":"221 Charles St",
    "sg:city":"Elizabeth City",
    "sg:classifiers":[
        {
            "category":"Building & Trades",
            "subcategory":"Plumbing",
            "type":"Services"
        }
    ],
    "sg:phone":"+1 252 338 6589",
    "sg:postcode":"27909",
    "sg:province":"NC",
    "sg:tags":[
        "conditioning",
        "air",
        "system",
        "contractor"
    ],
    "wof:name":"Ward & Son Inc",
    "wof:placetype":"venue"
},
  "geometry": {"coordinates":[-76.241525,36.300881],"type":"Point"}
}