{
  "type": "Feature",
  "properties": {
    "addr:full":"4301 Waterleaf Ct Greensboro NC 27410",
    "addr:housenumber":"4301",
    "addr:postcode":"27410",
    "addr:street":"Waterleaf Ct",
    "iso:country":"US",
    "sg:address":"4301 Waterleaf Ct",
    "sg:city":"Greensboro",
    "sg:classifiers":[
        {
            "category":"Manufacturing",
            "subcategory":"Printing",
            "type":"Manufacturing & Wholesale Goods"
        }
    ],
    "sg:phone":"+1 336 292 4000",
    "sg:postcode":"27410",
    "sg:province":"NC",
    "sg:tags":[
        "printer"
    ],
    "sg:website":"www.graphicprinting.com",
    "wof:name":"Graphic Printing Svc",
    "wof:placetype":"venue"
},
  "geometry": {"coordinates":[-79.943443,36.0597],"type":"Point"}
}