{
  "type": "Feature",
  "properties": {
    "addr:full":"2123 US Hwy 13 N Ahoskie NC 27910",
    "addr:housenumber":"2123",
    "addr:postcode":"27910",
    "addr:street":"Us Hwy 13 N",
    "iso:country":"US",
    "sg:address":"2123 US Hwy 13 N",
    "sg:city":"Ahoskie",
    "sg:classifiers":[
        {
            "category":"Shopping",
            "subcategory":"Pharmacy",
            "type":"Retail Goods"
        }
    ],
    "sg:phone":"+1 252 862 1050",
    "sg:postcode":"27910",
    "sg:province":"NC",
    "wof:name":"Hospicare Rx",
    "wof:placetype":"venue"
},
  "geometry": {"coordinates":[-76.96302799999999,36.16552],"type":"Point"}
}