{
  "type": "Feature",
  "properties": {
    "iso:country":"US",
    "sg:address":"1908 Blowing Rock Blvd",
    "sg:city":"Lenoir",
    "sg:classifiers":[
        {
            "category":"Organizations",
            "subcategory":"Religious Organization",
            "type":"Services"
        }
    ],
    "sg:phone":"+1 828 758 8888",
    "sg:postcode":"28645",
    "sg:province":"NC",
    "sg:tags":[
        "church"
    ],
    "wof:name":"Crest View Baptist Church",
    "wof:placetype":"venue"
},
  "geometry": {"coordinates":[-81.546841,35.945609],"type":"Point"}
}