{
  "type": "Feature",
  "properties": {
    "iso:country":"US",
    "sg:address":"3301 Woodpark Blvd",
    "sg:city":"Charlotte",
    "sg:classifiers":[
        {
            "category":"Wholesale",
            "subcategory":"Groceries",
            "type":"Manufacturing & Wholesale Goods"
        }
    ],
    "sg:phone":"+1 704 921 8838",
    "sg:postcode":"28206",
    "sg:province":"NC",
    "sg:tags":[
        "general"
    ],
    "wof:name":"Siema of North Carolina",
    "wof:placetype":"venue"
},
  "geometry": {"coordinates":[-80.82222,35.270096],"type":"Point"}
}