{
  "type": "Feature",
  "properties": {
    "addr:full":"1606 N Market Dr Raleigh NC 27609",
    "addr:housenumber":"1606",
    "addr:postcode":"27609",
    "addr:street":"N Market Dr",
    "iso:country":"US",
    "sg:address":"1606 N Market Dr",
    "sg:city":"Raleigh",
    "sg:classifiers":[
        {
            "category":"Food & Beverages",
            "subcategory":"Groceries & Convenience Stores",
            "type":"Retail Goods"
        }
    ],
    "sg:phone":"+1 919 954 0046",
    "sg:postcode":"27609",
    "sg:province":"NC",
    "wof:name":"AB Grocery",
    "wof:placetype":"venue"
},
  "geometry": {"coordinates":[-78.607152,35.839475],"type":"Point"}
}