{
  "type": "Feature",
  "properties": {
    "addr:full":"500 Savannah St Greensboro NC 27406",
    "addr:housenumber":"500",
    "addr:postcode":"27406",
    "addr:street":"Savannah St",
    "iso:country":"US",
    "sg:address":"500 Savannah St",
    "sg:city":"Greensboro",
    "sg:classifiers":[
        {
            "category":"Real Estate",
            "subcategory":"Real Estate Operator",
            "type":"Services"
        }
    ],
    "sg:phone":"+1 336 275 5203",
    "sg:postcode":"27406",
    "sg:province":"NC",
    "sg:tags":[
        "apartment"
    ],
    "wof:name":"Savannah Place Apartments",
    "wof:placetype":"venue"
},
  "geometry": {"coordinates":[-79.802528,36.045091],"type":"Point"}
}