{
  "type": "Feature",
  "properties": {
    "addr:full":"235 Branchview Dr NE Concord NC 28025",
    "addr:housenumber":"235",
    "addr:postcode":"28025",
    "addr:street":"Branchview Dr Ne",
    "iso:country":"US",
    "sg:address":"235 Branchview Dr NE",
    "sg:city":"Concord",
    "sg:classifiers":[
        {
            "category":"Manufacturing",
            "subcategory":"Signs",
            "type":"Manufacturing & Wholesale Goods"
        }
    ],
    "sg:phone":"+1 704 782 2661",
    "sg:postcode":"28025",
    "sg:province":"NC",
    "sg:tags":[
        "specialty",
        "mfg"
    ],
    "sg:website":"www.goquicksigns.com",
    "wof:name":"Quick Signs",
    "wof:placetype":"venue"
},
  "geometry": {"coordinates":[-80.573757,35.420313],"type":"Point"}
}