{
  "type": "Feature",
  "properties": {
    "addr:full":"102 Valley Vista Dr Black Mountain NC 28711",
    "addr:housenumber":"102",
    "addr:postcode":"28711",
    "addr:street":"Valley Vista Dr",
    "iso:country":"US",
    "sg:address":"102 Valley Vista Dr",
    "sg:city":"Black Mountain",
    "sg:classifiers":[
        {
            "category":"Building & Trades",
            "subcategory":"Construction",
            "type":"Services"
        }
    ],
    "sg:phone":"+1 828 669 5677",
    "sg:postcode":"28711",
    "sg:province":"NC",
    "sg:tags":[
        "contractor"
    ],
    "wof:name":"Clean Lot Inc",
    "wof:placetype":"venue"
},
  "geometry": {"coordinates":[-82.337514,35.629081],"type":"Point"}
}