{
  "type": "Feature",
  "properties": {
    "addr:full":"3475 US Hwy 421 Clinton NC 28328",
    "addr:housenumber":"3475",
    "addr:postcode":"28328",
    "addr:street":"Us Hwy 421",
    "iso:country":"US",
    "sg:address":"3475 US Hwy 421",
    "sg:city":"Clinton",
    "sg:classifiers":[
        {
            "category":"Professional",
            "subcategory":"Business Services",
            "type":"Services"
        }
    ],
    "sg:phone":"+1   ",
    "sg:postcode":"28328",
    "sg:province":"NC",
    "wof:name":"Jacob Sales",
    "wof:placetype":"venue"
},
  "geometry": {"coordinates":[-78.29665900000001,34.958601],"type":"Point"}
}