{
  "type": "Feature",
  "properties": {
    "iso:country":"US",
    "sg:address":"113 Dogwood Dr",
    "sg:city":"Black Mountain",
    "sg:classifiers":[
        {
            "category":"Shopping",
            "subcategory":"Pharmacy",
            "type":"Retail Goods"
        }
    ],
    "sg:phone":"+1 828 669 2511",
    "sg:postcode":"28711",
    "sg:province":"NC",
    "sg:tags":[
        "proprietary",
        "drug",
        "store"
    ],
    "wof:name":"Black Mountain Drug Co",
    "wof:placetype":"venue"
},
  "geometry": {"coordinates":[-82.339117,35.627832],"type":"Point"}
}