{
  "type": "Feature",
  "properties": {
    "iso:country":"US",
    "sg:address":"167 Haws Run Rd",
    "sg:city":"Jacksonville",
    "sg:classifiers":[
        {
            "category":"Manufacturing",
            "subcategory":"Apparel",
            "type":"Manufacturing & Wholesale Goods"
        },
        {
            "category":"Shopping",
            "subcategory":"Crafts & Fabrics",
            "type":"Retail Goods"
        }
    ],
    "sg:phone":"+1 910 346 6430",
    "sg:postcode":"28540",
    "sg:province":"NC",
    "sg:tags":[
        "textile",
        "product",
        "fabricated",
        "yarn",
        "mfg"
    ],
    "wof:name":"Phootsy's Crochet Cottage",
    "wof:placetype":"venue"
},
  "geometry": {"coordinates":[-77.516374,34.734095],"type":"Point"}
}