{
  "type": "Feature",
  "properties": {
    "addr:full":"2908 Hiking Trl Raleigh NC 27615",
    "addr:housenumber":"2908",
    "addr:postcode":"27615",
    "addr:street":"Hiking Trl",
    "iso:country":"US",
    "sg:address":"2908 Hiking Trl",
    "sg:city":"Raleigh",
    "sg:classifiers":[
        {
            "category":"Organizations",
            "subcategory":"Religious Organization",
            "type":"Services"
        }
    ],
    "sg:phone":"+1   ",
    "sg:postcode":"27615",
    "sg:province":"NC",
    "wof:name":"Church At White Oak",
    "wof:placetype":"venue"
},
  "geometry": {"coordinates":[-78.590476,35.898989],"type":"Point"}
}