{
  "type": "Feature",
  "properties": {
    "addr:full":"12740 Spruce Tree Way Raleigh NC 27614",
    "addr:housenumber":"12740",
    "addr:postcode":"27614",
    "addr:street":"Spruce Tree Way",
    "iso:country":"US",
    "sg:address":"12740 Spruce Tree Way",
    "sg:city":"Raleigh",
    "sg:classifiers":[
        {
            "category":"Health Services",
            "subcategory":"Doctor",
            "type":"Services"
        }
    ],
    "sg:phone":"+1   ",
    "sg:postcode":"27614",
    "sg:province":"NC",
    "wof:name":"Davidian Fmly Cosmtc Denistry",
    "wof:placetype":"venue"
},
  "geometry": {"coordinates":[-78.563284,35.94152],"type":"Point"}
}