{
  "type": "Feature",
  "properties": {
    "addr:full":"1103 13th Ave NW Hickory NC 28601",
    "addr:housenumber":"1103",
    "addr:postcode":"28601",
    "addr:street":"13Th Ave Nw",
    "iso:country":"US",
    "sg:address":"1103 13th Ave NW",
    "sg:city":"Hickory",
    "sg:classifiers":[
        {
            "category":"Restaurant",
            "type":"Food & Drink"
        }
    ],
    "sg:menulink":"http://www.allmenus.com/nc/hickory/240692-kobe/menu/",
    "sg:phone":"+1 828 328 5688",
    "sg:postcode":"28601",
    "sg:province":"NC",
    "sg:tags":[
        "japanese",
        "asian"
    ],
    "wof:name":"Kobe",
    "wof:placetype":"venue"
},
  "geometry": {"coordinates":[-81.365019,35.750826],"type":"Point"}
}