{
  "type": "Feature",
  "properties": {
    "addr:full":"635 Dashland Dr Fayetteville NC 28303",
    "addr:housenumber":"635",
    "addr:postcode":"28303",
    "addr:street":"Dashland Dr",
    "iso:country":"US",
    "sg:address":"635 Dashland Dr",
    "sg:city":"Fayetteville",
    "sg:classifiers":[
        {
            "category":"Health Services",
            "subcategory":"Nursing And Care Facility",
            "type":"Services"
        }
    ],
    "sg:phone":"+1 910 868 6208",
    "sg:postcode":"28303",
    "sg:province":"NC",
    "wof:name":"Cumberland Cnty Retardd Adults",
    "wof:placetype":"venue"
},
  "geometry": {"coordinates":[-78.96595499999999,35.089512],"type":"Point"}
}