{
  "type": "Feature",
  "properties": {
    "addr:full":"1223 Craig Ave Gastonia NC 28054",
    "addr:housenumber":"1223",
    "addr:postcode":"28054",
    "addr:street":"Craig Ave",
    "iso:country":"US",
    "sg:address":"1223 Craig Ave",
    "sg:city":"Gastonia",
    "sg:classifiers":[
        {
            "category":"Social Services",
            "subcategory":"Child Care",
            "type":"Services"
        }
    ],
    "sg:phone":"+1 704 866 5251",
    "sg:postcode":"28054",
    "sg:province":"NC",
    "wof:name":"A Toddler Tech University",
    "wof:placetype":"venue"
},
  "geometry": {"coordinates":[-81.158625,35.263942],"type":"Point"}
}