{
  "type": "Feature",
  "properties": {
    "iso:country":"US",
    "sg:address":"1800 McLean Rd",
    "sg:city":"Charlotte",
    "sg:classifiers":[
        {
            "category":"Organizations",
            "subcategory":"Religious Organization",
            "type":"Services"
        }
    ],
    "sg:phone":"+1 704 596 9471",
    "sg:postcode":"28213",
    "sg:province":"NC",
    "sg:tags":[
        "church"
    ],
    "wof:name":"Mc Lean Road Baptist Church",
    "wof:placetype":"venue"
},
  "geometry": {"coordinates":[-80.722436,35.288669],"type":"Point"}
}