{
  "type": "Feature",
  "properties": {
    "addr:full":"704 Slippery Bank Ct Benson NC 27504",
    "addr:housenumber":"704",
    "addr:postcode":"27504",
    "addr:street":"Slippery Bank Ct",
    "iso:country":"US",
    "sg:address":"704 Slippery Bank Ct",
    "sg:city":"Benson",
    "sg:classifiers":[
        {
            "category":"Shopping",
            "subcategory":"Books",
            "type":"Retail Goods"
        }
    ],
    "sg:phone":"+1 919 989 6595",
    "sg:postcode":"27504",
    "sg:province":"NC",
    "wof:name":"Book Subscribers",
    "wof:placetype":"venue"
},
  "geometry": {"coordinates":[-78.547832,35.537955],"type":"Point"}
}