{
  "type": "Feature",
  "properties": {
    "addr:full":"106 S Cherry St Wilkesboro NC 28697",
    "addr:housenumber":"106",
    "addr:postcode":"28697",
    "addr:street":"S Cherry St",
    "iso:country":"US",
    "sg:address":"106 S Cherry St",
    "sg:city":"Wilkesboro",
    "sg:classifiers":[
        {
            "category":"Real Estate",
            "subcategory":"Real Estate Agent",
            "type":"Services"
        }
    ],
    "sg:phone":"+1 336 667 1719",
    "sg:postcode":"28697",
    "sg:province":"NC",
    "sg:website":"www.blairandward.com",
    "wof:name":"Blair & Ward Properties",
    "wof:placetype":"venue"
},
  "geometry": {"coordinates":[-81.16121,36.145784],"type":"Point"}
}