{
  "type": "Feature",
  "properties": {
    "iso:country":"US",
    "sg:address":"3571 Friday Rd",
    "sg:city":"Bailey",
    "sg:classifiers":[
        {
            "category":"Wholesale",
            "subcategory":"Meat",
            "type":"Manufacturing & Wholesale Goods"
        }
    ],
    "sg:phone":"+1 252 235 3558",
    "sg:postcode":"27807",
    "sg:province":"NC",
    "sg:tags":[
        "packer"
    ],
    "wof:name":"Bailey Slaughter House",
    "wof:placetype":"venue"
},
  "geometry": {"coordinates":[-78.06576200000001,35.783767],"type":"Point"}
}