{
  "type": "Feature",
  "properties": {
    "addr:full":"5009 Beatties Ford Rd Charlotte NC 28216",
    "addr:housenumber":"5009",
    "addr:postcode":"28216",
    "addr:street":"Beatties Ford Rd",
    "iso:country":"US",
    "sg:address":"5009 Beatties Ford Rd",
    "sg:city":"Charlotte",
    "sg:classifiers":[
        {
            "category":"Professional",
            "subcategory":"Accounting & Tax Preparation",
            "type":"Services"
        },
        {
            "category":"Professional",
            "subcategory":"Management & Consulting",
            "type":"Services"
        },
        {
            "category":"Banks & Credit Unions",
            "subcategory":"Financial Services",
            "type":"Services"
        }
    ],
    "sg:phone":"+1 704 395 3626",
    "sg:postcode":"28216",
    "sg:province":"NC",
    "sg:tags":[
        "financing",
        "return",
        "preparation-business",
        "consultant",
        "planning",
        "bookkeeping"
    ],
    "wof:name":"Rapid Tax",
    "wof:placetype":"venue"
},
  "geometry": {"coordinates":[-80.857191,35.303567],"type":"Point"}
}