{
  "type": "Feature",
  "properties": {
    "iso:country":"US",
    "sg:address":"108 Picturesque Ln",
    "sg:city":"Cary",
    "sg:classifiers":[
        {
            "category":"Professional",
            "type":"Services"
        }
    ],
    "sg:phone":"+1   ",
    "sg:postcode":"27519",
    "sg:province":"NC",
    "wof:name":"Expedite Group Inc",
    "wof:placetype":"venue"
},
  "geometry": {"coordinates":[-78.88364,35.792607],"type":"Point"}
}