{
  "type": "Feature",
  "properties": {
    "iso:country":"US",
    "sg:address":"550 Hedgecock Rd",
    "sg:city":"High Point",
    "sg:classifiers":[
        {
            "category":"Arena",
            "subcategory":"Sports Club",
            "type":"Entertainment"
        }
    ],
    "sg:phone":"+1   ",
    "sg:postcode":"27265",
    "sg:province":"NC",
    "wof:name":"Piedmont Soccer Alliance",
    "wof:placetype":"venue"
},
  "geometry": {"coordinates":[-80.04854400000001,36.005162],"type":"Point"}
}