{
  "type": "Feature",
  "properties": {
    "addr:full":"1200 Corporation Pkwy Raleigh NC 27610",
    "addr:housenumber":"1200",
    "addr:postcode":"27610",
    "addr:street":"Corporation Pkwy",
    "iso:country":"US",
    "sg:address":"1200 Corporation Pkwy",
    "sg:city":"Raleigh",
    "sg:classifiers":[
        {
            "category":"Shopping",
            "subcategory":"Books",
            "type":"Retail Goods"
        }
    ],
    "sg:phone":"+1 919 255 1919",
    "sg:postcode":"27610",
    "sg:province":"NC",
    "sg:tags":[
        "dealer"
    ],
    "wof:name":"Scholastic Book Fairs",
    "wof:placetype":"venue"
},
  "geometry": {"coordinates":[-78.56847399999999,35.794805],"type":"Point"}
}