{
  "type": "Feature",
  "properties": {
    "addr:full":"145 E Court St Marion NC 28752",
    "addr:housenumber":"145",
    "addr:postcode":"28752",
    "addr:street":"E Court St",
    "iso:country":"US",
    "sg:address":"145 E Court St",
    "sg:city":"Marion",
    "sg:classifiers":[
        {
            "category":"Government",
            "subcategory":"Office",
            "type":"Public Place"
        },
        {
            "category":"Social Services",
            "type":"Services"
        }
    ],
    "sg:phone":"+1 828 652 3355",
    "sg:postcode":"28752",
    "sg:province":"NC",
    "sg:tags":[
        "county",
        "organization",
        "resource",
        "welfare"
    ],
    "wof:name":"Mc Dowell County Social Svc",
    "wof:placetype":"venue"
},
  "geometry": {"coordinates":[-82.004701,35.685773],"type":"Point"}
}