{
  "type": "Feature",
  "properties": {
    "addr:full":"213 S Racepath St Fayetteville NC 28301",
    "addr:housenumber":"213",
    "addr:postcode":"28301",
    "addr:street":"S Racepath St",
    "iso:country":"US",
    "sg:address":"213 S Racepath St",
    "sg:city":"Fayetteville",
    "sg:classifiers":[
        {
            "category":"Building & Trades",
            "subcategory":"Construction",
            "type":"Services"
        }
    ],
    "sg:phone":"+1 910 323 0770",
    "sg:postcode":"28301",
    "sg:province":"NC",
    "sg:tags":[
        "painter"
    ],
    "wof:name":"Larry Buie Drywall & Painting",
    "wof:placetype":"venue"
},
  "geometry": {"coordinates":[-78.86293999999999,35.044471],"type":"Point"}
}