{
  "type": "Feature",
  "properties": {
    "addr:full":"800 Brevard Rd Asheville NC 28806",
    "addr:housenumber":"800",
    "addr:postcode":"28806",
    "addr:street":"Brevard Rd",
    "iso:country":"US",
    "sg:address":"800 Brevard Rd",
    "sg:city":"Asheville",
    "sg:classifiers":[
        {
            "category":"Shopping",
            "subcategory":"Jewelry",
            "type":"Retail Goods"
        }
    ],
    "sg:phone":"+1 828 665 7878",
    "sg:postcode":"28806",
    "sg:province":"NC",
    "sg:tags":[
        "jeweler"
    ],
    "wof:name":"Whitehall Co Jewellers",
    "wof:placetype":"venue"
},
  "geometry": {"coordinates":[-82.60579,35.529739],"type":"Point"}
}