{
  "type": "Feature",
  "properties": {
    "iso:country":"US",
    "sg:address":"2805 Meridian Pkwy",
    "sg:city":"Durham",
    "sg:classifiers":[
        {
            "category":"Real Estate",
            "subcategory":"Architect",
            "type":"Services"
        }
    ],
    "sg:phone":"+1 919 544 0087",
    "sg:postcode":"27713",
    "sg:province":"NC",
    "sg:tags":[
        "engineering",
        "architectural"
    ],
    "sg:website":"www.lmht.com",
    "wof:name":"Lehmann Mehler Hirst Thornton",
    "wof:placetype":"venue"
},
  "geometry": {"coordinates":[-78.899856,35.914706],"type":"Point"}
}