{
  "type": "Feature",
  "properties": {
    "iso:country":"US",
    "sg:address":"166 Friar Tuck Ter",
    "sg:city":"Lexington",
    "sg:classifiers":[
        {
            "category":"Building & Trades",
            "subcategory":"Landscaping Services",
            "type":"Services"
        }
    ],
    "sg:phone":"+1 336 442 2076",
    "sg:postcode":"27292",
    "sg:province":"NC",
    "sg:tags":[
        "lawn",
        "maintenance",
        "grounds"
    ],
    "wof:name":"Bass Lawn Care & Maintenance",
    "wof:placetype":"venue"
},
  "geometry": {"coordinates":[-80.23741800000001,35.677442],"type":"Point"}
}