{
  "type": "Feature",
  "properties": {
    "addr:full":"218 Ashville Ave Cary NC 27518",
    "addr:housenumber":"218",
    "addr:postcode":"27518",
    "addr:street":"Ashville Ave",
    "iso:country":"US",
    "sg:address":"218 Ashville Ave",
    "sg:city":"Cary",
    "sg:classifiers":[
        {
            "category":"Health Services",
            "subcategory":"Doctor",
            "type":"Services"
        },
        {
            "category":"Health Services",
            "subcategory":"Health Practitioner",
            "type":"Services"
        }
    ],
    "sg:phone":"+1 919 233 6644",
    "sg:postcode":"27518",
    "sg:province":"NC",
    "sg:tags":[
        "control",
        "physician",
        "management",
        "weight",
        "loss",
        "surgeons",
        "surgeon"
    ],
    "sg:website":"http://www.drbartels.com",
    "wof:name":"Bartels Medical Associates PLLC",
    "wof:placetype":"venue"
},
  "geometry": {"coordinates":[-78.783719,35.739614],"type":"Point"}
}