{
  "type": "Feature",
  "properties": {
    "addr:full":"200 Hawthorne Ln Charlotte NC 28204",
    "addr:housenumber":"200",
    "addr:postcode":"28204",
    "addr:street":"Hawthorne Ln",
    "iso:country":"US",
    "sg:address":"200 Hawthorne Ln",
    "sg:city":"Charlotte",
    "sg:classifiers":[
        {
            "category":"Health Services",
            "subcategory":"Doctor",
            "type":"Services"
        }
    ],
    "sg:phone":"+1 704 384 4188",
    "sg:postcode":"28204",
    "sg:province":"NC",
    "sg:tags":[
        "physician",
        "surgeon"
    ],
    "sg:website":"www.novanthealth.org",
    "wof:name":"Radiation Oncology",
    "wof:placetype":"venue"
},
  "geometry": {"coordinates":[-80.82649000000001,35.212167],"type":"Point"}
}