{
  "type": "Feature",
  "properties": {
    "addr:full":"338 NE 48th St Oak Island NC 28465",
    "addr:housenumber":"338",
    "addr:postcode":"28465",
    "addr:street":"Ne 48Th St",
    "iso:country":"US",
    "sg:address":"338 NE 48th St",
    "sg:city":"Oak Island",
    "sg:classifiers":[
        {
            "category":"Insurance",
            "subcategory":"Insurance Agent",
            "type":"Services"
        }
    ],
    "sg:phone":"+1 910 278 6249",
    "sg:postcode":"28465",
    "sg:province":"NC",
    "wof:name":"Hirst Insurance Services",
    "wof:placetype":"venue"
},
  "geometry": {"coordinates":[-78.113742,33.917939],"type":"Point"}
}