{
  "type": "Feature",
  "properties": {
    "iso:country":"US",
    "sg:address":"9319 Forsyth Park Dr",
    "sg:city":"Charlotte",
    "sg:classifiers":[
        {
            "category":"Home & Garden",
            "subcategory":"Carpets & Floor Coverings",
            "type":"Retail Goods"
        }
    ],
    "sg:phone":"+1 704 583 0005",
    "sg:postcode":"28273",
    "sg:province":"NC",
    "sg:tags":[
        "installation",
        "sale"
    ],
    "sg:website":"www.burtonfloor.com",
    "wof:name":"Burton Floor Covering Inc",
    "wof:placetype":"venue"
},
  "geometry": {"coordinates":[-80.953869,35.134999],"type":"Point"}
}