{
  "type": "Feature",
  "properties": {
    "iso:country":"US",
    "sg:address":"3511 Providence Rd",
    "sg:city":"Charlotte",
    "sg:classifiers":[
        {
            "category":"Arena",
            "subcategory":"Sports Club",
            "type":"Entertainment"
        }
    ],
    "sg:phone":"+1 704 364 2337",
    "sg:postcode":"28211",
    "sg:province":"NC",
    "sg:tags":[
        "manager",
        "recruiter",
        "promoter"
    ],
    "wof:name":"Road Runner Solutions",
    "wof:placetype":"venue"
},
  "geometry": {"coordinates":[-80.80193199999999,35.164037],"type":"Point"}
}