{
  "type": "Feature",
  "properties": {
    "iso:country":"US",
    "sg:address":"43 Renaissance Pl",
    "sg:city":"Leicester",
    "sg:classifiers":[
        {
            "category":"Social Services",
            "subcategory":"Adult Care",
            "type":"Services"
        }
    ],
    "sg:phone":"+1 828 683 4119",
    "sg:postcode":"28748",
    "sg:province":"NC",
    "sg:tags":[
        "residential"
    ],
    "wof:name":"Childrens Home Society O",
    "wof:placetype":"venue"
},
  "geometry": {"coordinates":[-82.676146,35.679825],"type":"Point"}
}