{
  "type": "Feature",
  "properties": {
    "addr:full":"4543 South Blvd Charlotte NC 28209",
    "addr:housenumber":"4543",
    "addr:postcode":"28209",
    "addr:street":"South Blvd",
    "iso:country":"US",
    "sg:address":"4543 South Blvd",
    "sg:city":"Charlotte",
    "sg:classifiers":[
        {
            "category":"Building & Trades",
            "subcategory":"Construction",
            "type":"Services"
        }
    ],
    "sg:phone":"+1 704 529 8405",
    "sg:postcode":"28209",
    "sg:province":"NC",
    "sg:tags":[
        "painting",
        "contractor"
    ],
    "sg:website":"http://www.advancepaintingnc.com",
    "wof:name":"Advance Painting Contractors",
    "wof:placetype":"venue"
},
  "geometry": {"coordinates":[-80.875839,35.179999],"type":"Point"}
}