{
  "type": "Feature",
  "properties": {
    "iso:country":"US",
    "sg:address":"1702 Cedar Creek Rd",
    "sg:city":"Shelby",
    "sg:classifiers":[
        {
            "category":"Manufacturing",
            "subcategory":"Apparel",
            "type":"Manufacturing & Wholesale Goods"
        }
    ],
    "sg:phone":"+1 704 481 9596",
    "sg:postcode":"28152",
    "sg:province":"NC",
    "wof:name":"J & S Embroidery",
    "wof:placetype":"venue"
},
  "geometry": {"coordinates":[-81.534333,35.242464],"type":"Point"}
}