{
  "type": "Feature",
  "properties": {
    "addr:full":"1926 Hartford Dr Gastonia NC 28052",
    "addr:housenumber":"1926",
    "addr:postcode":"28052",
    "addr:street":"Hartford Dr",
    "iso:country":"US",
    "sg:address":"1926 Hartford Dr",
    "sg:city":"Gastonia",
    "sg:classifiers":[
        {
            "category":"Real Estate",
            "subcategory":"Real Estate Operator",
            "type":"Services"
        }
    ],
    "sg:phone":"+1 704 865 6581",
    "sg:postcode":"28052",
    "sg:province":"NC",
    "sg:tags":[
        "apartment"
    ],
    "wof:name":"Linwood Park Apartments",
    "wof:placetype":"venue"
},
  "geometry": {"coordinates":[-81.216655,35.235801],"type":"Point"}
}