{
  "type": "Feature",
  "properties": {
    "iso:country":"US",
    "sg:address":"212 E Camp Kiro Rd",
    "sg:city":"New Bern",
    "sg:classifiers":[
        {
            "category":"Manufacturing",
            "subcategory":"Printing",
            "type":"Manufacturing & Wholesale Goods"
        }
    ],
    "sg:phone":"+1 252 633 5459",
    "sg:postcode":"28560",
    "sg:province":"NC",
    "sg:tags":[
        "printer"
    ],
    "wof:name":"Gallery Arts Printing",
    "wof:placetype":"venue"
},
  "geometry": {"coordinates":[-76.984742,35.011693],"type":"Point"}
}