{
  "type": "Feature",
  "properties": {
    "iso:country":"US",
    "sg:address":"109 W Main St",
    "sg:city":"Spindale",
    "sg:classifiers":[
        {
            "category":"Shopping",
            "subcategory":"Crafts & Fabrics",
            "type":"Retail Goods"
        }
    ],
    "sg:phone":"+1 828 248 9666",
    "sg:postcode":"28160",
    "sg:province":"NC",
    "sg:tags":[
        "embroidery"
    ],
    "wof:name":"Kathies Creations",
    "wof:placetype":"venue"
},
  "geometry": {"coordinates":[-81.93186300000001,35.357707],"type":"Point"}
}