{
  "type": "Feature",
  "properties": {
    "addr:full":"1525 Land St Lenoir NC 28645",
    "addr:housenumber":"1525",
    "addr:postcode":"28645",
    "addr:street":"Land St",
    "iso:country":"US",
    "sg:address":"1525 Land St",
    "sg:city":"Lenoir",
    "sg:classifiers":[
        {
            "category":"Retail",
            "subcategory":"Auto Repair",
            "type":"Services"
        }
    ],
    "sg:phone":"+1   ",
    "sg:postcode":"28645",
    "sg:province":"NC",
    "sg:tags":[
        "general"
    ],
    "wof:name":"Land Automotive",
    "wof:placetype":"venue"
},
  "geometry": {"coordinates":[-81.538743,35.839223],"type":"Point"}
}