{
  "type": "Feature",
  "properties": {
    "addr:full":"603 E 17th St Winston Salem NC 27105",
    "addr:housenumber":"603",
    "addr:postcode":"27105",
    "addr:street":"E 17Th St",
    "iso:country":"US",
    "sg:address":"603 E 17th St",
    "sg:city":"Winston Salem",
    "sg:classifiers":[
        {
            "category":"Home & Garden",
            "subcategory":"Building Materials",
            "type":"Retail Goods"
        }
    ],
    "sg:phone":"+1 336 722 8167",
    "sg:postcode":"27105",
    "sg:province":"NC",
    "sg:tags":[
        "lumber"
    ],
    "sg:website":"www.smithphillipslumber.com",
    "wof:name":"Smith Phillips Lumber & Bldg",
    "wof:placetype":"venue"
},
  "geometry": {"coordinates":[-80.237664,36.115457],"type":"Point"}
}