{
  "type": "Feature",
  "properties": {
    "iso:country":"US",
    "sg:address":"160 Industrial Dr",
    "sg:city":"Welcome",
    "sg:classifiers":[
        {
            "category":"Recreation",
            "type":"Entertainment"
        }
    ],
    "sg:phone":"+1 336 731 7771",
    "sg:postcode":"27320",
    "sg:province":"NC",
    "sg:tags":[
        "instruction",
        "swimming"
    ],
    "wof:name":"Welcome Swim Club",
    "wof:placetype":"venue"
},
  "geometry": {"coordinates":[-79.663574,36.331063],"type":"Point"}
}