{
  "type": "Feature",
  "properties": {
    "addr:full":"134 Angus Hill Dr Union Grove NC 28689",
    "addr:housenumber":"134",
    "addr:postcode":"28689",
    "addr:street":"Angus Hill Dr",
    "iso:country":"US",
    "sg:address":"134 Angus Hill Dr",
    "sg:city":"Union Grove",
    "sg:classifiers":[
        {
            "category":"Farming",
            "subcategory":"Livestock Farm",
            "type":"Manufacturing & Wholesale Goods"
        }
    ],
    "sg:phone":"+1 704 539 4339",
    "sg:postcode":"28689",
    "sg:province":"NC",
    "sg:tags":[
        "beef",
        "feedlot",
        "cattle"
    ],
    "wof:name":"Boger Angus Farm",
    "wof:placetype":"venue"
},
  "geometry": {"coordinates":[-80.871701,36.029011],"type":"Point"}
}