{
  "type": "Feature",
  "properties": {
    "iso:country":"US",
    "sg:address":"3351 Service St",
    "sg:city":"Charlotte",
    "sg:classifiers":[
        {
            "category":"Professional",
            "subcategory":"Business Services",
            "type":"Services"
        }
    ],
    "sg:phone":"+1   ",
    "sg:postcode":"28206",
    "sg:province":"NC",
    "wof:name":"Aramark",
    "wof:placetype":"venue"
},
  "geometry": {"coordinates":[-80.821382,35.264848],"type":"Point"}
}