{
  "type": "Feature",
  "properties": {
    "addr:full":"3445 Whiteville Rd NW Ash NC 28420",
    "addr:housenumber":"3445",
    "addr:postcode":"28420",
    "addr:street":"Whiteville Rd Nw",
    "iso:country":"US",
    "sg:address":"3445 Whiteville Rd NW",
    "sg:city":"Ash",
    "sg:classifiers":[
        {
            "category":"Autos & Motor Vehicles",
            "subcategory":"Auto Supplies",
            "type":"Retail Goods"
        }
    ],
    "sg:phone":"+1 910 287 6429",
    "sg:postcode":"28420",
    "sg:province":"NC",
    "wof:name":"Hughes Tires",
    "wof:placetype":"venue"
},
  "geometry": {"coordinates":[-78.512998,34.048629],"type":"Point"}
}