{
  "type": "Feature",
  "properties": {
    "addr:full":"8105 Six Forks Rd Raleigh NC 27615",
    "addr:housenumber":"8105",
    "addr:postcode":"27615",
    "addr:street":"Six Forks Rd",
    "iso:country":"US",
    "sg:address":"8105 Six Forks Rd",
    "sg:city":"Raleigh",
    "sg:classifiers":[
        {
            "category":"Building & Trades",
            "subcategory":"Construction",
            "type":"Services"
        }
    ],
    "sg:phone":"+1 919 847 2451",
    "sg:postcode":"27615",
    "sg:province":"NC",
    "sg:tags":[
        "contractor"
    ],
    "wof:name":"Emerald Sweeping",
    "wof:placetype":"venue"
},
  "geometry": {"coordinates":[-78.647769,35.88933],"type":"Point"}
}