{
  "type": "Feature",
  "properties": {
    "addr:full":"1527 Garner Station Blvd Raleigh NC 27603",
    "addr:housenumber":"1527",
    "addr:postcode":"27603",
    "addr:street":"Garner Station Blvd",
    "iso:country":"US",
    "sg:address":"1527 Garner Station Blvd",
    "sg:city":"Raleigh",
    "sg:classifiers":[
        {
            "category":"Restaurant",
            "type":"Food & Drink"
        }
    ],
    "sg:phone":"+1 919 773 1800",
    "sg:postcode":"27603",
    "sg:province":"NC",
    "sg:tags":[
        "eating"
    ],
    "wof:name":"McDonalds",
    "wof:placetype":"venue"
},
  "geometry": {"coordinates":[-78.65655,35.724764],"type":"Point"}
}