{
  "type": "Feature",
  "properties": {
    "iso:country":"US",
    "sg:address":"201 S McPherson Church Rd",
    "sg:city":"Fayetteville",
    "sg:classifiers":[
        {
            "category":"Insurance",
            "subcategory":"Insurance Agent",
            "type":"Services"
        }
    ],
    "sg:phone":"+1 910 868 9825",
    "sg:postcode":"28303",
    "sg:province":"NC",
    "wof:name":"Belin & Assoc",
    "wof:placetype":"venue"
},
  "geometry": {"coordinates":[-78.950524,35.066651],"type":"Point"}
}