{
  "type": "Feature",
  "properties": {
    "iso:country":"US",
    "sg:address":"1017 S Horner Blvd",
    "sg:city":"Sanford",
    "sg:classifiers":[
        {
            "category":"Professional",
            "subcategory":"Printing & Photocopies",
            "type":"Services"
        }
    ],
    "sg:phone":"+1 919 776 0821",
    "sg:postcode":"27330",
    "sg:province":"NC",
    "sg:tags":[
        "duplicating",
        "copying"
    ],
    "wof:name":"Copy Center Of Sanford",
    "wof:placetype":"venue"
},
  "geometry": {"coordinates":[-79.167727,35.470486],"type":"Point"}
}