{
  "type": "Feature",
  "properties": {
    "iso:country":"US",
    "sg:address":"9113 Leesville Rd",
    "sg:city":"Raleigh",
    "sg:classifiers":[
        {
            "category":"Recreation",
            "type":"Entertainment"
        }
    ],
    "sg:phone":"+1 919 844 5555",
    "sg:postcode":"27613",
    "sg:province":"NC",
    "sg:tags":[
        "martial",
        "arts",
        "instruction"
    ],
    "wof:name":"Triangle's Best Karate",
    "wof:placetype":"venue"
},
  "geometry": {"coordinates":[-78.72352600000001,35.896999],"type":"Point"}
}