{
  "type": "Feature",
  "properties": {
    "iso:country":"US",
    "sg:address":"2805 Spring Forest Rd",
    "sg:city":"Raleigh",
    "sg:classifiers":[
        {
            "category":"Health Services",
            "subcategory":"Clinic",
            "type":"Services"
        }
    ],
    "sg:phone":"+1 919 790 1953",
    "sg:postcode":"27616",
    "sg:province":"NC",
    "sg:tags":[
        "home"
    ],
    "wof:name":"Support Staff Healthcare Svcs",
    "wof:placetype":"venue"
},
  "geometry": {"coordinates":[-78.594199,35.857594],"type":"Point"}
}