{
  "type": "Feature",
  "properties": {
    "addr:full":"652 E Arlington Blvd Greenville NC 27858",
    "addr:housenumber":"652",
    "addr:postcode":"27858",
    "addr:street":"E Arlington Blvd",
    "iso:country":"US",
    "sg:address":"652 E Arlington Blvd",
    "sg:city":"Greenville",
    "sg:classifiers":[
        {
            "category":"Shopping",
            "subcategory":"Clothing, Apparel, & Fashions",
            "type":"Retail Goods"
        }
    ],
    "sg:phone":"+1 252 756 3320",
    "sg:postcode":"27858",
    "sg:province":"NC",
    "sg:tags":[
        "ready",
        "to",
        "wear"
    ],
    "wof:name":"Certain Things Inc",
    "wof:placetype":"venue"
},
  "geometry": {"coordinates":[-77.36685900000001,35.582904],"type":"Point"}
}