{
  "type": "Feature",
  "properties": {
    "iso:country":"US",
    "sg:address":"7225 Cool Springs Rd",
    "sg:city":"Broadway",
    "sg:classifiers":[
        {
            "category":"Building & Trades",
            "subcategory":"Construction",
            "type":"Services"
        }
    ],
    "sg:phone":"+1 919 258 3282",
    "sg:postcode":"27505",
    "sg:province":"NC",
    "sg:tags":[
        "house"
    ],
    "wof:name":"Dewars Home Improvement",
    "wof:placetype":"venue"
},
  "geometry": {"coordinates":[-79.001684,35.443624],"type":"Point"}
}