{
  "type": "Feature",
  "properties": {
    "iso:country":"US",
    "sg:address":"311 Judges Rd",
    "sg:city":"Wilmington",
    "sg:classifiers":[
        {
            "category":"Professional",
            "type":"Services"
        }
    ],
    "sg:phone":"+1   ",
    "sg:postcode":"28405",
    "sg:province":"NC",
    "wof:name":"Old Goats Shop Inc",
    "wof:placetype":"venue"
},
  "geometry": {"coordinates":[-77.855058,34.252705],"type":"Point"}
}