{
  "type": "Feature",
  "properties": {
    "addr:full":"8411 Beverly Crest Blvd Charlotte NC 28270",
    "addr:housenumber":"8411",
    "addr:postcode":"28270",
    "addr:street":"Beverly Crest Blvd",
    "iso:country":"US",
    "sg:address":"8411 Beverly Crest Blvd",
    "sg:city":"Charlotte",
    "sg:classifiers":[
        {
            "category":"Education",
            "subcategory":"Special Training",
            "type":"Public Place"
        },
        {
            "category":"Social Services",
            "subcategory":"Child Care",
            "type":"Services"
        },
        {
            "category":"Education",
            "subcategory":"Preschool",
            "type":"Public Place"
        }
    ],
    "sg:phone":"+1 704 708 6371",
    "sg:postcode":"28270",
    "sg:province":"NC",
    "sg:tags":[
        "school",
        "educational",
        "kindergarten",
        "nursery",
        "day"
    ],
    "sg:website":"http://www.chesterbrookacademy.com",
    "wof:name":"Chesterbrook Academy",
    "wof:placetype":"venue"
},
  "geometry": {"coordinates":[-80.767448,35.107398],"type":"Point"}
}