{
  "type": "Feature",
  "properties": {
    "addr:full":"462 Seastone St Raleigh NC 27603",
    "addr:housenumber":"462",
    "addr:postcode":"27603",
    "addr:street":"Seastone St",
    "iso:country":"US",
    "sg:address":"462 Seastone St",
    "sg:city":"Raleigh",
    "sg:classifiers":[
        {
            "category":"Building & Trades",
            "subcategory":"Construction",
            "type":"Services"
        }
    ],
    "sg:phone":"+1 919 329 9996",
    "sg:postcode":"27603",
    "sg:province":"NC",
    "sg:tags":[
        "concrete",
        "contractor"
    ],
    "wof:name":"Driveway Specialists",
    "wof:placetype":"venue"
},
  "geometry": {"coordinates":[-78.671136,35.663769],"type":"Point"}
}