{
  "type": "Feature",
  "properties": {
    "addr:full":"6112 Westgate Rd Raleigh NC 27617",
    "addr:housenumber":"6112",
    "addr:postcode":"27617",
    "addr:street":"Westgate Rd",
    "iso:country":"US",
    "sg:address":"6112 Westgate Rd",
    "sg:city":"Raleigh",
    "sg:classifiers":[
        {
            "category":"Home & Garden",
            "subcategory":"Building Materials",
            "type":"Retail Goods"
        }
    ],
    "sg:phone":"+1 919 781 5120",
    "sg:postcode":"27617",
    "sg:province":"NC",
    "sg:tags":[
        "mixed",
        "concrete"
    ],
    "wof:name":"Ready Mix Concrete Co Lab",
    "wof:placetype":"venue"
},
  "geometry": {"coordinates":[-78.75258599999999,35.903451],"type":"Point"}
}