{
  "type": "Feature",
  "properties": {
    "addr:full":"740 W 5th St Charlotte NC 28202",
    "addr:housenumber":"740",
    "addr:postcode":"28202",
    "addr:street":"W 5Th St",
    "iso:country":"US",
    "sg:address":"740 W 5th St",
    "sg:city":"Charlotte",
    "sg:classifiers":[
        {
            "category":"Social Services",
            "type":"Services"
        }
    ],
    "sg:phone":"+1 704 334 0053",
    "sg:postcode":"28202",
    "sg:province":"NC",
    "sg:tags":[
        "organization",
        "welfare"
    ],
    "wof:name":"National Conference For Comm",
    "wof:placetype":"venue"
},
  "geometry": {"coordinates":[-80.84905000000001,35.234012],"type":"Point"}
}