{
  "type": "Feature",
  "properties": {
    "iso:country":"US",
    "sg:address":"2316 South Blvd",
    "sg:city":"Charlotte",
    "sg:classifiers":[
        {
            "category":"Professional",
            "subcategory":"Management & Consulting",
            "type":"Services"
        },
        {
            "category":"Wholesale",
            "subcategory":"Chemicals & Plastics",
            "type":"Manufacturing & Wholesale Goods"
        }
    ],
    "sg:phone":"+1 704 333 8930",
    "sg:postcode":"28203",
    "sg:province":"NC",
    "sg:tags":[
        "item"
    ],
    "wof:name":"Georgia-Carolina Products Co",
    "wof:placetype":"venue"
},
  "geometry": {"coordinates":[-80.863311,35.204783],"type":"Point"}
}