{
  "type": "Feature",
  "properties": {
    "iso:country":"US",
    "sg:address":"11052 Despa Dr",
    "sg:city":"Charlotte",
    "sg:classifiers":[
        {
            "category":"Real Estate",
            "subcategory":"Real Estate Agent",
            "type":"Services"
        }
    ],
    "sg:phone":"+1 704 545 3561",
    "sg:postcode":"28227",
    "sg:province":"NC",
    "wof:name":"Jrd Capital Ventures Inc",
    "wof:placetype":"venue"
},
  "geometry": {"coordinates":[-80.65799699999999,35.179439],"type":"Point"}
}