{
  "type": "Feature",
  "properties": {
    "addr:full":"940 Payne Rd Lexington NC 27295",
    "addr:housenumber":"940",
    "addr:postcode":"27295",
    "addr:street":"Payne Rd",
    "iso:country":"US",
    "sg:address":"940 Payne Rd",
    "sg:city":"Lexington",
    "sg:classifiers":[
        {
            "category":"Building & Trades",
            "subcategory":"Construction",
            "type":"Services"
        }
    ],
    "sg:phone":"+1 336 764 2083",
    "sg:postcode":"27295",
    "sg:province":"NC",
    "sg:tags":[
        "roofing",
        "contractor"
    ],
    "wof:name":"Bassett Roofing",
    "wof:placetype":"venue"
},
  "geometry": {"coordinates":[-80.255802,35.957172],"type":"Point"}
}