{
  "type": "Feature",
  "properties": {
    "addr:full":"6495 State Hwy 770 Stoneville NC 27048",
    "addr:housenumber":"6495",
    "addr:postcode":"27048",
    "addr:street":"State Hwy 770",
    "iso:country":"US",
    "sg:address":"6495 State Hwy 770",
    "sg:city":"Stoneville",
    "sg:classifiers":[
        {
            "category":"Professional",
            "subcategory":"Management & Consulting",
            "type":"Services"
        }
    ],
    "sg:phone":"+1   ",
    "sg:postcode":"27048",
    "sg:province":"NC",
    "sg:tags":[
        "business"
    ],
    "wof:name":"Herm Tech Inc",
    "wof:placetype":"venue"
},
  "geometry": {"coordinates":[-79.821112,36.478265],"type":"Point"}
}