{
  "type": "Feature",
  "properties": {
    "iso:country":"US",
    "sg:address":"1710 Dawson St",
    "sg:city":"Wilmington",
    "sg:classifiers":[
        {
            "category":"Wholesale",
            "subcategory":"Non-durable Goods",
            "type":"Manufacturing & Wholesale Goods"
        }
    ],
    "sg:phone":"+1 910 254 9383",
    "sg:postcode":"28403",
    "sg:province":"NC",
    "sg:tags":[
        "financial",
        "premium",
        "insurance"
    ],
    "sg:website":"www.imageproductsusa.com",
    "wof:name":"Image Products Inc",
    "wof:placetype":"venue"
},
  "geometry": {"coordinates":[-77.925006,34.22574],"type":"Point"}
}