{
  "type": "Feature",
  "properties": {
    "addr:full":"104 W Main St Faison NC 28341",
    "addr:housenumber":"104",
    "addr:postcode":"28341",
    "addr:street":"W Main St",
    "iso:country":"US",
    "sg:address":"104 W Main St",
    "sg:city":"Faison",
    "sg:classifiers":[
        {
            "category":"Retail",
            "subcategory":"Laundry & Dry Cleaning",
            "type":"Services"
        }
    ],
    "sg:phone":"+1 910 267 1842",
    "sg:postcode":"28341",
    "sg:province":"NC",
    "sg:tags":[
        "cleaners"
    ],
    "wof:name":"Faison Dry Cleaners",
    "wof:placetype":"venue"
},
  "geometry": {"coordinates":[-78.13714299999999,35.116479],"type":"Point"}
}