{
  "type": "Feature",
  "properties": {
    "addr:full":"3105 Central Heights Rd Goldsboro NC 27534",
    "addr:housenumber":"3105",
    "addr:postcode":"27534",
    "addr:street":"Central Heights Rd",
    "iso:country":"US",
    "sg:address":"3105 Central Heights Rd",
    "sg:city":"Goldsboro",
    "sg:classifiers":[
        {
            "category":"Manufacturing",
            "subcategory":"Tools & Machinery",
            "type":"Manufacturing & Wholesale Goods"
        }
    ],
    "sg:phone":"+1 919 751 3461",
    "sg:postcode":"27534",
    "sg:province":"NC",
    "sg:tags":[
        "machine",
        "shop"
    ],
    "wof:name":"Petra Precision Machining",
    "wof:placetype":"venue"
},
  "geometry": {"coordinates":[-77.92388099999999,35.378438],"type":"Point"}
}