{
  "type": "Feature",
  "properties": {
    "iso:country":"US",
    "sg:address":"3804 Cottonwood Dr",
    "sg:city":"Durham",
    "sg:classifiers":[
        {
            "category":"Health Services",
            "subcategory":"Doctor",
            "type":"Services"
        }
    ],
    "sg:phone":"+1 919 419 8828",
    "sg:postcode":"27705",
    "sg:province":"NC",
    "wof:name":"Allingham R Rand MD",
    "wof:placetype":"venue"
},
  "geometry": {"coordinates":[-78.9842,35.969799],"type":"Point"}
}