{
  "type": "Feature",
  "properties": {
    "addr:full":"2604 Small Woods Dr Wingate NC 28174",
    "addr:housenumber":"2604",
    "addr:postcode":"28174",
    "addr:street":"Small Woods Dr Wingate",
    "iso:country":"US",
    "sg:address":"2604 Small Woods Dr",
    "sg:city":"Wingate",
    "sg:classifiers":[
        {
            "category":"Retail",
            "subcategory":"Repair Shop",
            "type":"Services"
        }
    ],
    "sg:phone":"+1   ",
    "sg:postcode":"28174",
    "sg:province":"NC",
    "wof:name":"Jimmys Mower and Engine S",
    "wof:placetype":"venue"
},
  "geometry": {"coordinates":[-80.428045,34.907841],"type":"Point"}
}