{
  "type": "Feature",
  "properties": {
    "addr:full":"541 Cherry St Greenville NC 27834",
    "addr:housenumber":"541",
    "addr:postcode":"27834",
    "addr:street":"Cherry St",
    "iso:country":"US",
    "sg:address":"541 Cherry St",
    "sg:city":"Greenville",
    "sg:classifiers":[
        {
            "category":"Organizations",
            "subcategory":"Religious Organization",
            "type":"Services"
        }
    ],
    "sg:phone":"+1 252 758 9174",
    "sg:postcode":"27834",
    "sg:province":"NC",
    "sg:tags":[
        "church"
    ],
    "wof:name":"Hayes Chapel Missionary Bptst",
    "wof:placetype":"venue"
},
  "geometry": {"coordinates":[-77.21824700000001,35.625684],"type":"Point"}
}