{
  "type": "Feature",
  "properties": {
    "addr:full":"1817 Lee Ave Sanford NC 27330",
    "addr:housenumber":"1817",
    "addr:postcode":"27330",
    "addr:street":"Lee Ave",
    "iso:country":"US",
    "sg:address":"1817 Lee Ave",
    "sg:city":"Sanford",
    "sg:classifiers":[
        {
            "category":"Social Services",
            "type":"Services"
        }
    ],
    "sg:phone":"+1 919 775 5447",
    "sg:postcode":"27330",
    "sg:province":"NC",
    "sg:tags":[
        "organization",
        "welfare"
    ],
    "wof:name":"Hispanic Task Force",
    "wof:placetype":"venue"
},
  "geometry": {"coordinates":[-79.158086,35.465161],"type":"Point"}
}