{
  "type": "Feature",
  "properties": {
    "iso:country":"US",
    "sg:address":"928 Sunset Ave",
    "sg:city":"Asheboro",
    "sg:classifiers":[
        {
            "category":"Banks & Credit Unions",
            "subcategory":"Investment Brokerage",
            "type":"Services"
        }
    ],
    "sg:phone":"+1 336 625 0550",
    "sg:postcode":"27203",
    "sg:province":"NC",
    "sg:tags":[
        "stock",
        "bond"
    ],
    "wof:name":"Raymond James Financial Svc",
    "wof:placetype":"venue"
},
  "geometry": {"coordinates":[-79.828305,35.706561],"type":"Point"}
}