{
  "type": "Feature",
  "properties": {
    "addr:full":"1304 University Dr Durham NC 27707",
    "addr:housenumber":"1304",
    "addr:postcode":"27707",
    "addr:street":"University Dr",
    "iso:country":"US",
    "sg:address":"1304 University Dr",
    "sg:city":"Durham",
    "sg:classifiers":[
        {
            "category":"Food & Beverages",
            "subcategory":"Meat & Fish",
            "type":"Retail Goods"
        }
    ],
    "sg:phone":"+1 919 402 0777",
    "sg:postcode":"27707",
    "sg:province":"NC",
    "sg:tags":[
        "seafood"
    ],
    "wof:name":"Capital Seafood Market",
    "wof:placetype":"venue"
},
  "geometry": {"coordinates":[-78.911412,35.984621],"type":"Point"}
}