{
  "type": "Feature",
  "properties": {
    "iso:country":"US",
    "sg:address":"4213 Baker Farm Rd",
    "sg:city":"Sophia",
    "sg:classifiers":[
        {
            "category":"Manufacturing",
            "subcategory":"Lumber",
            "type":"Manufacturing & Wholesale Goods"
        }
    ],
    "sg:phone":"+1 336 498 3619",
    "sg:postcode":"27350",
    "sg:province":"NC",
    "sg:tags":[
        "logging"
    ],
    "wof:name":"Akines Logging",
    "wof:placetype":"venue"
},
  "geometry": {"coordinates":[-79.89213700000001,35.834663],"type":"Point"}
}