{
  "type": "Feature",
  "properties": {
    "addr:full":"2025 Creek View Dr Hickory NC 28601",
    "addr:housenumber":"2025",
    "addr:postcode":"28601",
    "addr:street":"Creek View Dr",
    "iso:country":"US",
    "sg:address":"2025 Creek View Dr",
    "sg:city":"Hickory",
    "sg:classifiers":[
        {
            "category":"Organizations",
            "subcategory":"Community Association",
            "type":"Services"
        }
    ],
    "sg:phone":"+1   ",
    "sg:postcode":"28601",
    "sg:province":"NC",
    "wof:name":"Ladies Aux To VFW 195",
    "wof:placetype":"venue"
},
  "geometry": {"coordinates":[-81.403155,35.758751],"type":"Point"}
}