{
  "type": "Feature",
  "properties": {
    "addr:full":"9701 Tenencia Charlotte NC 28277",
    "addr:housenumber":"9701",
    "addr:postcode":"28277",
    "addr:street":"Tenencia",
    "iso:country":"US",
    "sg:address":"9701 Tenencia",
    "sg:city":"Charlotte",
    "sg:classifiers":[
        {
            "category":"Manufacturing",
            "subcategory":"Metals",
            "type":"Manufacturing & Wholesale Goods"
        }
    ],
    "sg:phone":"+1 704 543 7595",
    "sg:postcode":"28277",
    "sg:province":"NC",
    "wof:name":"Western Piedmont Metal Inc",
    "wof:placetype":"venue"
},
  "geometry": {"coordinates":[-80.830461,35.038852],"type":"Point"}
}