{
  "type": "Feature",
  "properties": {
    "addr:full":"902 State Hwy 108 Columbus NC 28722",
    "addr:housenumber":"902",
    "addr:postcode":"28722",
    "addr:street":"State Hwy 108",
    "iso:country":"US",
    "sg:address":"902 State Hwy 108",
    "sg:city":"Columbus",
    "sg:classifiers":[
        {
            "category":"Education",
            "subcategory":"College",
            "type":"Public Place"
        }
    ],
    "sg:phone":"+1 828 286 3636",
    "sg:postcode":"28722",
    "sg:province":"NC",
    "wof:name":"Isothermal Cmty Clg-Polk",
    "wof:placetype":"venue"
},
  "geometry": {"coordinates":[-82.193612,35.256292],"type":"Point"}
}