{
  "type": "Feature",
  "properties": {
    "addr:full":"8196 Hills-View Rd Oakboro NC 28129",
    "addr:housenumber":"8196",
    "addr:postcode":"28129",
    "addr:street":"Hills-View Rd",
    "iso:country":"US",
    "sg:address":"8196 Hills-View Rd",
    "sg:city":"Oakboro",
    "sg:classifiers":[
        {
            "category":"Building & Trades",
            "subcategory":"Plumbing",
            "type":"Services"
        }
    ],
    "sg:phone":"+1 704 485 8362",
    "sg:postcode":"28129",
    "sg:province":"NC",
    "sg:tags":[
        "plumbing",
        "heating",
        "air"
    ],
    "wof:name":"Anchor Steam Power Co Inc",
    "wof:placetype":"venue"
},
  "geometry": {"coordinates":[-80.279674,35.200274],"type":"Point"}
}