{
  "type": "Feature",
  "properties": {
    "iso:country":"US",
    "sg:address":"3100 Basilwood Cir",
    "sg:city":"Monroe",
    "sg:classifiers":[
        {
            "category":"Building & Trades",
            "subcategory":"Equipment Rental",
            "type":"Services"
        }
    ],
    "sg:phone":"+1   ",
    "sg:postcode":"28110",
    "sg:province":"NC",
    "wof:name":"Incredible Inflatables Inc",
    "wof:placetype":"venue"
},
  "geometry": {"coordinates":[-80.60800399999999,34.981474],"type":"Point"}
}