{
  "type": "Feature",
  "properties": {
    "iso:country":"US",
    "sg:address":"342 N Main St",
    "sg:city":"Troy",
    "sg:classifiers":[
        {
            "category":"Education",
            "subcategory":"Dance Studio",
            "type":"Public Place"
        }
    ],
    "sg:phone":"+1   ",
    "sg:postcode":"27371",
    "sg:province":"NC",
    "wof:name":"Studio J Dance",
    "wof:placetype":"venue"
},
  "geometry": {"coordinates":[-79.89392100000001,35.360975],"type":"Point"}
}