{
  "type": "Feature",
  "properties": {
    "addr:full":"1584 Old Neal Rd Marion NC 28752",
    "addr:housenumber":"1584",
    "addr:postcode":"28752",
    "addr:street":"Old Neal Rd",
    "iso:country":"US",
    "sg:address":"1584 Old Neal Rd",
    "sg:city":"Marion",
    "sg:classifiers":[
        {
            "category":"Home & Garden",
            "subcategory":"Furniture",
            "type":"Retail Goods"
        }
    ],
    "sg:phone":"+1 828 738 8335",
    "sg:postcode":"28752",
    "sg:province":"NC",
    "sg:tags":[
        "cabinet"
    ],
    "wof:name":"Jaybird Fine Cabinetry",
    "wof:placetype":"venue"
},
  "geometry": {"coordinates":[-81.993889,35.593583],"type":"Point"}
}