{
  "type": "Feature",
  "properties": {
    "addr:full":"108 W Main St Locust NC 28097",
    "addr:housenumber":"108",
    "addr:postcode":"28097",
    "addr:street":"W Main St",
    "iso:country":"US",
    "sg:address":"108 W Main St",
    "sg:city":"Locust",
    "sg:classifiers":[
        {
            "category":"Shopping",
            "subcategory":"Gifts & Souvenirs",
            "type":"Retail Goods"
        }
    ],
    "sg:phone":"+1 704 888 0428",
    "sg:postcode":"28097",
    "sg:province":"NC",
    "wof:name":"Gifts & Wraps Unlimited",
    "wof:placetype":"venue"
},
  "geometry": {"coordinates":[-80.425141,35.260241],"type":"Point"}
}