{
  "type": "Feature",
  "properties": {
    "addr:full":"302 E Franklin Blvd Gastonia NC 28054",
    "addr:housenumber":"302",
    "addr:postcode":"28054",
    "addr:street":"E Franklin Blvd",
    "iso:country":"US",
    "sg:address":"302 E Franklin Blvd",
    "sg:city":"Gastonia",
    "sg:classifiers":[
        {
            "category":"Banks & Credit Unions",
            "subcategory":"Bank",
            "type":"Services"
        }
    ],
    "sg:phone":"+1 704 884 0041",
    "sg:postcode":"28054",
    "sg:province":"NC",
    "sg:tags":[
        "depository",
        "banking",
        "check",
        "cashing"
    ],
    "wof:name":"Charlotte Check Cashers",
    "wof:placetype":"venue"
},
  "geometry": {"coordinates":[-81.176075,35.262335],"type":"Point"}
}