{
  "type": "Feature",
  "properties": {
    "addr:full":"220 E Meadow Rd Eden NC 27288",
    "addr:housenumber":"220",
    "addr:postcode":"27288",
    "addr:street":"E Meadow Rd",
    "iso:country":"US",
    "sg:address":"220 E Meadow Rd",
    "sg:city":"Eden",
    "sg:classifiers":[
        {
            "category":"Banks & Credit Unions",
            "subcategory":"Bank",
            "type":"Services"
        }
    ],
    "sg:phone":"+1 336 623 5626",
    "sg:postcode":"27288",
    "sg:province":"NC",
    "sg:tags":[
        "mortgage"
    ],
    "wof:name":"Wells Fargo",
    "wof:placetype":"venue"
},
  "geometry": {"coordinates":[-79.73876,36.508188],"type":"Point"}
}