{
  "type": "Feature",
  "properties": {
    "addr:full":"411 Hay St Fayetteville NC 28301",
    "addr:housenumber":"411",
    "addr:postcode":"28301",
    "addr:street":"Hay St",
    "iso:country":"US",
    "sg:address":"411 Hay St",
    "sg:city":"Fayetteville",
    "sg:classifiers":[
        {
            "category":"Real Estate",
            "subcategory":"Real Estate Agent",
            "type":"Services"
        }
    ],
    "sg:phone":"+1 910 484 8831",
    "sg:postcode":"28301",
    "sg:province":"NC",
    "wof:name":"Wagon Yard Properties",
    "wof:placetype":"venue"
},
  "geometry": {"coordinates":[-78.883475,35.054261],"type":"Point"}
}