{
  "type": "Feature",
  "properties": {
    "iso:country":"US",
    "sg:address":"1002 Grove Ave SW",
    "sg:city":"Lenoir",
    "sg:classifiers":[
        {
            "category":"Organizations",
            "subcategory":"Religious Organization",
            "type":"Services"
        }
    ],
    "sg:phone":"+1   ",
    "sg:postcode":"28645",
    "sg:province":"NC",
    "wof:name":"Central Advent Christn Church",
    "wof:placetype":"venue"
},
  "geometry": {"coordinates":[-81.53913300000001,35.90903],"type":"Point"}
}