{
  "type": "Feature",
  "properties": {
    "iso:country":"US",
    "sg:address":"302 Turnersburg Hwy",
    "sg:city":"Statesville",
    "sg:classifiers":[
        {
            "category":"Personal",
            "subcategory":"Beauty Salon",
            "type":"Services"
        }
    ],
    "sg:phone":"+1 704 872 4242",
    "sg:postcode":"28625",
    "sg:province":"NC",
    "wof:name":"Ad'Lib Hair & Nail Gallery",
    "wof:placetype":"venue"
},
  "geometry": {"coordinates":[-80.874495,35.828924],"type":"Point"}
}