{
  "type": "Feature",
  "properties": {
    "addr:full":"230 Hillsborough Rd Timberlake NC 27583",
    "addr:housenumber":"230",
    "addr:postcode":"27583",
    "addr:street":"Hillsborough Rd",
    "iso:country":"US",
    "sg:address":"230 Hillsborough Rd",
    "sg:city":"Timberlake",
    "sg:classifiers":[
        {
            "category":"Building & Trades",
            "subcategory":"Plumbing",
            "type":"Services"
        }
    ],
    "sg:phone":"+1 919 418 2557",
    "sg:postcode":"27583",
    "sg:province":"NC",
    "sg:tags":[
        "contractor"
    ],
    "wof:name":"Finks Mechanical Service",
    "wof:placetype":"venue"
},
  "geometry": {"coordinates":[-78.940663,36.24532],"type":"Point"}
}