{
  "type": "Feature",
  "properties": {
    "iso:country":"US",
    "sg:address":"2275 Vanstory St",
    "sg:city":"Greensboro",
    "sg:classifiers":[
        {
            "category":"Health Services",
            "subcategory":"Doctor",
            "type":"Services"
        }
    ],
    "sg:phone":"+1 336 292 5029",
    "sg:postcode":"27403",
    "sg:province":"NC",
    "sg:tags":[
        "dentist"
    ],
    "wof:name":"Access Dental Care",
    "wof:placetype":"venue"
},
  "geometry": {"coordinates":[-79.83241599999999,36.041315],"type":"Point"}
}