{
  "type": "Feature",
  "properties": {
    "addr:full":"1609 Zelma Ave High Point NC 27265",
    "addr:housenumber":"1609",
    "addr:postcode":"27265",
    "addr:street":"Zelma Ave",
    "iso:country":"US",
    "sg:address":"1609 Zelma Ave",
    "sg:city":"High Point",
    "sg:classifiers":[
        {
            "category":"Professional",
            "subcategory":"Accounting & Tax Preparation",
            "type":"Services"
        }
    ],
    "sg:phone":"+1 336 889 6812",
    "sg:postcode":"27265",
    "sg:province":"NC",
    "sg:tags":[
        "return",
        "filing"
    ],
    "wof:name":"Tax Matters",
    "wof:placetype":"venue"
},
  "geometry": {"coordinates":[-79.991291,35.986854],"type":"Point"}
}