{
  "type": "Feature",
  "properties": {
    "iso:country":"US",
    "sg:address":"1236 Millerwood Dr",
    "sg:city":"Winston Salem",
    "sg:classifiers":[
        {
            "category":"Professional",
            "subcategory":"Business Services",
            "type":"Services"
        }
    ],
    "sg:phone":"+1   ",
    "sg:postcode":"27106",
    "sg:province":"NC",
    "wof:name":"Weddings By Design",
    "wof:placetype":"venue"
},
  "geometry": {"coordinates":[-80.308504,36.124098],"type":"Point"}
}