{
  "type": "Feature",
  "properties": {
    "addr:full":"159 Barley Park Ln Mooresville NC 28115",
    "addr:housenumber":"159",
    "addr:postcode":"28115",
    "addr:street":"Barley Park Ln",
    "iso:country":"US",
    "sg:address":"159 Barley Park Ln",
    "sg:city":"Mooresville",
    "sg:classifiers":[
        {
            "category":"Professional",
            "type":"Services"
        }
    ],
    "sg:phone":"+1 704 663 3166",
    "sg:postcode":"28115",
    "sg:province":"NC",
    "sg:tags":[
        "establishment"
    ],
    "wof:name":"Rabb Global Technologies",
    "wof:placetype":"venue"
},
  "geometry": {"coordinates":[-80.80222999999999,35.623598],"type":"Point"}
}