{
  "type": "Feature",
  "properties": {
    "iso:country":"US",
    "sg:address":"155 McArthur St",
    "sg:city":"Asheboro",
    "sg:classifiers":[
        {
            "category":"Health Services",
            "subcategory":"Doctor",
            "type":"Services"
        }
    ],
    "sg:phone":"+1   ",
    "sg:postcode":"27203",
    "sg:province":"NC",
    "sg:tags":[
        "medical"
    ],
    "wof:name":"Achreja Ranvir Dr",
    "wof:placetype":"venue"
},
  "geometry": {"coordinates":[-79.813788,35.710666],"type":"Point"}
}