{
  "type": "Feature",
  "properties": {
    "addr:full":"2617 N Main St High Point NC 27265",
    "addr:housenumber":"2617",
    "addr:postcode":"27265",
    "addr:street":"N Main St",
    "iso:country":"US",
    "sg:address":"2617 N Main St",
    "sg:city":"High Point",
    "sg:classifiers":[
        {
            "category":"Sports & Exercise",
            "subcategory":"Bowling",
            "type":"Entertainment"
        }
    ],
    "sg:phone":"+1 336 869 7189",
    "sg:postcode":"27265",
    "sg:province":"NC",
    "sg:tags":[
        "center"
    ],
    "wof:name":"Brunswick Tar Heel Lanes",
    "wof:placetype":"venue"
},
  "geometry": {"coordinates":[-80.029768,35.992366],"type":"Point"}
}