{
  "type": "Feature",
  "properties": {
    "iso:country":"US",
    "sg:address":"120 N Franklin St",
    "sg:city":"Rocky Mount",
    "sg:classifiers":[
        {
            "category":"Health Services",
            "subcategory":"Clinic",
            "type":"Services"
        }
    ],
    "sg:phone":"+1 252 985 1181",
    "sg:postcode":"27804",
    "sg:province":"NC",
    "sg:tags":[
        "home"
    ],
    "wof:name":"Dove Health Care Inc",
    "wof:placetype":"venue"
},
  "geometry": {"coordinates":[-77.797956,35.944711],"type":"Point"}
}