{
  "type": "Feature",
  "properties": {
    "iso:country":"US",
    "sg:address":"6232 Gravel Hill Rd",
    "sg:city":"Denton",
    "sg:classifiers":[
        {
            "category":"Food & Beverages",
            "subcategory":"Groceries & Convenience Stores",
            "type":"Retail Goods"
        }
    ],
    "sg:phone":"+1 336 857 2174",
    "sg:postcode":"27239",
    "sg:province":"NC",
    "wof:name":"Laniers Grocery & Service",
    "wof:placetype":"venue"
},
  "geometry": {"coordinates":[-80.02164500000001,35.580771],"type":"Point"}
}