{
  "type": "Feature",
  "properties": {
    "iso:country":"US",
    "sg:address":"6301 South Blvd",
    "sg:city":"Charlotte",
    "sg:classifiers":[
        {
            "category":"Food & Beverages",
            "subcategory":"Groceries & Convenience Stores",
            "type":"Retail Goods"
        }
    ],
    "sg:phone":"+1 704 643 2428",
    "sg:postcode":"28217",
    "sg:province":"NC",
    "sg:tags":[
        "grocer"
    ],
    "wof:name":"Romero's Super Market",
    "wof:placetype":"venue"
},
  "geometry": {"coordinates":[-80.876407,35.147866],"type":"Point"}
}