{
  "type": "Feature",
  "properties": {
    "iso:country":"US",
    "sg:address":"26 Hampstead Rd",
    "sg:city":"Asheville",
    "sg:classifiers":[
        {
            "category":"Professional",
            "subcategory":"Management & Consulting",
            "type":"Services"
        }
    ],
    "sg:phone":"+1   ",
    "sg:postcode":"28804",
    "sg:province":"NC",
    "wof:name":"Forest Guide",
    "wof:placetype":"venue"
},
  "geometry": {"coordinates":[-82.549654,35.627496],"type":"Point"}
}