{
  "type": "Feature",
  "properties": {
    "addr:full":"512 Wicker St Burlington NC 27217",
    "addr:housenumber":"512",
    "addr:postcode":"27217",
    "addr:street":"Wicker St",
    "iso:country":"US",
    "sg:address":"512 Wicker St",
    "sg:city":"Burlington",
    "sg:classifiers":[
        {
            "category":"Organizations",
            "subcategory":"Religious Organization",
            "type":"Services"
        }
    ],
    "sg:phone":"+1   ",
    "sg:postcode":"27217",
    "sg:province":"NC",
    "sg:tags":[
        "church"
    ],
    "wof:name":"Wicker Street Baptist Church",
    "wof:placetype":"venue"
},
  "geometry": {"coordinates":[-79.438428,36.107364],"type":"Point"}
}