{
  "type": "Feature",
  "properties": {
    "addr:full":"327 Hillsborough St Raleigh NC 27603",
    "addr:housenumber":"327",
    "addr:postcode":"27603",
    "addr:street":"Hillsborough St",
    "iso:country":"US",
    "sg:address":"327 Hillsborough St",
    "sg:city":"Raleigh",
    "sg:classifiers":[
        {
            "category":"Professional",
            "subcategory":"Lawyer & Legal Services",
            "type":"Services"
        }
    ],
    "sg:phone":"+1 919 856 3940",
    "sg:postcode":"27603",
    "sg:province":"NC",
    "sg:tags":[
        "attorney",
        "criminal",
        "family",
        "accident",
        "divorce",
        "wills",
        "damage",
        "planning",
        "real estate",
        "trust",
        "property",
        "law",
        "bankruptcy"
    ],
    "sg:website":"http://www.hatchlittlebunn.com",
    "wof:name":"Hatch Little Bunn LLP",
    "wof:placetype":"venue"
},
  "geometry": {"coordinates":[-78.643784,35.780559],"type":"Point"}
}