{
  "type": "Feature",
  "properties": {
    "addr:full":"1087 Main St Yanceyville NC 27379",
    "addr:housenumber":"1087",
    "addr:postcode":"27379",
    "addr:street":"Main St",
    "iso:country":"US",
    "sg:address":"1087 Main St",
    "sg:city":"Yanceyville",
    "sg:classifiers":[
        {
            "category":"Retail",
            "subcategory":"Laundry & Dry Cleaning",
            "type":"Services"
        }
    ],
    "sg:phone":"+1 336 694 5116",
    "sg:postcode":"27379",
    "sg:province":"NC",
    "sg:tags":[
        "cleaners"
    ],
    "wof:name":"Top Hat Cleaners",
    "wof:placetype":"venue"
},
  "geometry": {"coordinates":[-79.345034,36.409226],"type":"Point"}
}