{
  "type": "Feature",
  "properties": {
    "addr:full":"14914 Hope Ct Huntersville NC 28078",
    "addr:housenumber":"14914",
    "addr:postcode":"28078",
    "addr:street":"Hope Ct",
    "iso:country":"US",
    "sg:address":"14914 Hope Ct",
    "sg:city":"Huntersville",
    "sg:classifiers":[
        {
            "category":"Wholesale",
            "subcategory":"Computers",
            "type":"Manufacturing & Wholesale Goods"
        }
    ],
    "sg:phone":"+1 704 948 6875",
    "sg:postcode":"28078",
    "sg:province":"NC",
    "wof:name":"Cie America",
    "wof:placetype":"venue"
},
  "geometry": {"coordinates":[-80.88153699999999,35.414017],"type":"Point"}
}