{
  "type": "Feature",
  "properties": {
    "iso:country":"US",
    "sg:address":"115 Dunn Rd",
    "sg:city":"Fayetteville",
    "sg:classifiers":[
        {
            "category":"Bars & Pubs",
            "type":"Food & Drink"
        }
    ],
    "sg:phone":"+1 910 860 0819",
    "sg:postcode":"28312",
    "sg:province":"NC",
    "wof:name":"Cadyns Tavern",
    "wof:placetype":"venue"
},
  "geometry": {"coordinates":[-78.85512300000001,35.048959],"type":"Point"}
}