{
  "type": "Feature",
  "properties": {
    "addr:full":"103 Emory Pl Huntersville NC 28078",
    "addr:housenumber":"103",
    "addr:postcode":"28078",
    "addr:street":"Emory Pl",
    "iso:country":"US",
    "sg:address":"103 Emory Pl",
    "sg:city":"Huntersville",
    "sg:classifiers":[
        {
            "category":"Retail",
            "subcategory":"Auto Repair",
            "type":"Services"
        }
    ],
    "sg:phone":"+1 704 875 2921",
    "sg:postcode":"28078",
    "sg:province":"NC",
    "sg:tags":[
        "wrecker"
    ],
    "wof:name":"Saxon Towing",
    "wof:placetype":"venue"
},
  "geometry": {"coordinates":[-80.84639199999999,35.421438],"type":"Point"}
}