{
  "type": "Feature",
  "properties": {
    "addr:full":"5576 NC-42 W Garner NC 27529",
    "addr:housenumber":"5576",
    "addr:postcode":"27529",
    "addr:street":"Nc-42 W",
    "iso:country":"US",
    "sg:address":"5576 NC-42 W",
    "sg:city":"Garner",
    "sg:classifiers":[
        {
            "category":"Restaurant",
            "type":"Food & Drink"
        }
    ],
    "sg:menulink":"http://www.allmenus.com/nc/cleveland/85378-dominos-pizza/menu/",
    "sg:phone":"+1 919 662 0303",
    "sg:postcode":"27529",
    "sg:province":"NC",
    "sg:tags":[
        "american",
        "wing",
        "pizza"
    ],
    "wof:name":"Domino's Pizza",
    "wof:placetype":"venue"
},
  "geometry": {"coordinates":[-78.568438,35.60461],"type":"Point"}
}