{
  "type": "Feature",
  "properties": {
    "addr:full":"128 Majestic Way Ct Kernersville NC 27284",
    "addr:housenumber":"128",
    "addr:postcode":"27284",
    "addr:street":"Majestic Way Ct",
    "iso:country":"US",
    "sg:address":"128 Majestic Way Ct",
    "sg:city":"Kernersville",
    "sg:classifiers":[
        {
            "category":"Retail",
            "subcategory":"Repair Shop",
            "type":"Services"
        }
    ],
    "sg:phone":"+1 336 996 3756",
    "sg:postcode":"27284",
    "sg:province":"NC",
    "wof:name":"Abbott Rt-Rter Sewer Drain Svc",
    "wof:placetype":"venue"
},
  "geometry": {"coordinates":[-80.057931,36.116383],"type":"Point"}
}