{
  "type": "Feature",
  "properties": {
    "addr:full":"11 Pennsylvania Ave Canton NC 28716",
    "addr:housenumber":"11",
    "addr:postcode":"28716",
    "addr:street":"Pennsylvania Ave",
    "iso:country":"US",
    "sg:address":"11 Pennsylvania Ave",
    "sg:city":"Canton",
    "sg:classifiers":[
        {
            "category":"Education",
            "subcategory":"Library",
            "type":"Public Place"
        }
    ],
    "sg:phone":"+1 828 648 2924",
    "sg:postcode":"28716",
    "sg:province":"NC",
    "wof:name":"Canton Branch Library",
    "wof:placetype":"venue"
},
  "geometry": {"coordinates":[-82.835837,35.529713],"type":"Point"}
}