{
  "type": "Feature",
  "properties": {
    "addr:full":"8009 Horse Chestnut Ln Charlotte NC 28277",
    "addr:housenumber":"8009",
    "addr:postcode":"28277",
    "addr:street":"Horse Chestnut Ln",
    "iso:country":"US",
    "sg:address":"8009 Horse Chestnut Ln",
    "sg:city":"Charlotte",
    "sg:classifiers":[
        {
            "category":"Building & Trades",
            "subcategory":"Landscaping Services",
            "type":"Services"
        }
    ],
    "sg:phone":"+1 704 341 9682",
    "sg:postcode":"28277",
    "sg:province":"NC",
    "wof:name":"Alwood Tree Service",
    "wof:placetype":"venue"
},
  "geometry": {"coordinates":[-80.785083,35.093529],"type":"Point"}
}