{
  "type": "Feature",
  "properties": {
    "addr:full":"3151 Apex Peakway Apex NC 27502",
    "addr:housenumber":"3151",
    "addr:postcode":"27502",
    "addr:street":"Apex Peakway",
    "iso:country":"US",
    "sg:address":"3151 Apex Peakway",
    "sg:city":"Apex",
    "sg:classifiers":[
        {
            "category":"Personal",
            "subcategory":"Beauty Salon",
            "type":"Services"
        }
    ],
    "sg:phone":"+1 919 303 4322",
    "sg:postcode":"27502",
    "sg:province":"NC",
    "sg:tags":[
        "hair"
    ],
    "wof:name":"Smartstyle",
    "wof:placetype":"venue"
},
  "geometry": {"coordinates":[-78.845815,35.714426],"type":"Point"}
}