{
  "type": "Feature",
  "properties": {
    "addr:full":"201 E Bragg St Raleigh NC 27601",
    "addr:housenumber":"201",
    "addr:postcode":"27601",
    "addr:street":"E Bragg St",
    "iso:country":"US",
    "sg:address":"201 E Bragg St",
    "sg:city":"Raleigh",
    "sg:classifiers":[
        {
            "category":"Food & Beverages",
            "subcategory":"Groceries & Convenience Stores",
            "type":"Retail Goods"
        }
    ],
    "sg:phone":"+1 919 828 5682",
    "sg:postcode":"27601",
    "sg:province":"NC",
    "wof:name":"Community Mart",
    "wof:placetype":"venue"
},
  "geometry": {"coordinates":[-78.63560699999999,35.765824],"type":"Point"}
}