{
  "type": "Feature",
  "properties": {
    "iso:country":"US",
    "sg:address":"49 Peachtree Rd",
    "sg:city":"Asheville",
    "sg:classifiers":[
        {
            "category":"Wholesale",
            "subcategory":"Construction Materials",
            "type":"Manufacturing & Wholesale Goods"
        }
    ],
    "sg:phone":"+1 828 274 4113",
    "sg:postcode":"28803",
    "sg:province":"NC",
    "wof:name":"Huntsinger & Sons Cabinet Shop",
    "wof:placetype":"venue"
},
  "geometry": {"coordinates":[-82.52270300000001,35.514147],"type":"Point"}
}