{
  "type": "Feature",
  "properties": {
    "iso:country":"US",
    "sg:address":"130 Bay St",
    "sg:city":"Rural Hall",
    "sg:classifiers":[
        {
            "category":"Professional",
            "subcategory":"Art Services",
            "type":"Services"
        }
    ],
    "sg:phone":"+1 336 969 2733",
    "sg:postcode":"27045",
    "sg:province":"NC",
    "sg:tags":[
        "graphic"
    ],
    "wof:name":"Graphic Rewards Inc",
    "wof:placetype":"venue"
},
  "geometry": {"coordinates":[-80.294918,36.238782],"type":"Point"}
}