{
  "type": "Feature",
  "properties": {
    "iso:country":"US",
    "sg:address":"643 Haywood Rd",
    "sg:city":"Asheville",
    "sg:classifiers":[
        {
            "category":"Shopping",
            "subcategory":"Clothing, Apparel, & Fashions",
            "type":"Retail Goods"
        }
    ],
    "sg:phone":"+1 828 225 4909",
    "sg:postcode":"28806",
    "sg:province":"NC",
    "sg:tags":[
        "infant",
        "wear"
    ],
    "wof:name":"Wb Fashions",
    "wof:placetype":"venue"
},
  "geometry": {"coordinates":[-82.59017299999999,35.57837],"type":"Point"}
}