{
  "type": "Feature",
  "properties": {
    "iso:country":"US",
    "sg:address":"303 S 19th St",
    "sg:city":"Butner",
    "sg:classifiers":[
        {
            "category":"Building & Trades",
            "subcategory":"Construction",
            "type":"Services"
        }
    ],
    "sg:phone":"+1 919 575 4435",
    "sg:postcode":"27509",
    "sg:province":"NC",
    "sg:tags":[
        "contractor"
    ],
    "wof:name":"Stillman Tate Drywall",
    "wof:placetype":"venue"
},
  "geometry": {"coordinates":[-78.756568,36.13727],"type":"Point"}
}