{
  "type": "Feature",
  "properties": {
    "iso:country":"US",
    "sg:address":"7107 Mount Herman Church Rd",
    "sg:city":"Durham",
    "sg:classifiers":[
        {
            "category":"Organizations",
            "subcategory":"Religious Organization",
            "type":"Services"
        }
    ],
    "sg:phone":"+1   ",
    "sg:postcode":"27705",
    "sg:province":"NC",
    "wof:name":"Mt Gillead Church",
    "wof:placetype":"venue"
},
  "geometry": {"coordinates":[-79.014827,36.040809],"type":"Point"}
}