{
  "type": "Feature",
  "properties": {
    "addr:full":"5200 Creedmoor Rd Raleigh NC 27612",
    "addr:housenumber":"5200",
    "addr:postcode":"27612",
    "addr:street":"Creedmoor Rd",
    "iso:country":"US",
    "sg:address":"5200 Creedmoor Rd",
    "sg:city":"Raleigh",
    "sg:classifiers":[
        {
            "category":"Retail",
            "subcategory":"Auto Repair",
            "type":"Services"
        }
    ],
    "sg:phone":"+1   ",
    "sg:postcode":"27612",
    "sg:province":"NC",
    "sg:tags":[
        "general"
    ],
    "wof:name":"Chavis Repairs",
    "wof:placetype":"venue"
},
  "geometry": {"coordinates":[-78.68028099999999,35.851555],"type":"Point"}
}