{
  "type": "Feature",
  "properties": {
    "iso:country":"US",
    "sg:address":"500 W Trade St",
    "sg:city":"Charlotte",
    "sg:classifiers":[
        {
            "category":"Professional",
            "subcategory":"Management & Consulting",
            "type":"Services"
        }
    ],
    "sg:phone":"+1   ",
    "sg:postcode":"28202",
    "sg:province":"NC",
    "sg:tags":[
        "trainer",
        "educational"
    ],
    "wof:name":"Charlotte Teacch Center The",
    "wof:placetype":"venue"
},
  "geometry": {"coordinates":[-80.84778,35.231245],"type":"Point"}
}