{
  "type": "Feature",
  "properties": {
    "addr:full":"806 S Andrews Ave Goldsboro NC 27530",
    "addr:housenumber":"806",
    "addr:postcode":"27530",
    "addr:street":"S Andrews Ave",
    "iso:country":"US",
    "sg:address":"806 S Andrews Ave",
    "sg:city":"Goldsboro",
    "sg:classifiers":[
        {
            "category":"Building & Trades",
            "subcategory":"Construction",
            "type":"Services"
        }
    ],
    "sg:phone":"+1 919 738 4833",
    "sg:postcode":"27530",
    "sg:province":"NC",
    "sg:tags":[
        "home",
        "improvement"
    ],
    "wof:name":"Daniels Home Improvement",
    "wof:placetype":"venue"
},
  "geometry": {"coordinates":[-77.979016,35.368393],"type":"Point"}
}