{
  "type": "Feature",
  "properties": {
    "addr:full":"990 US Hwy 70 E Connellys Spgs NC 28612",
    "addr:housenumber":"990",
    "addr:postcode":"28612",
    "addr:street":"Us Hwy 70 E Connellys Spgs",
    "iso:country":"US",
    "sg:address":"990 US Hwy 70 E",
    "sg:city":"Connellys Spgs",
    "sg:classifiers":[
        {
            "category":"Shopping",
            "subcategory":"Discount & Variety Stores",
            "type":"Retail Goods"
        }
    ],
    "sg:phone":"+1 828 874 2575",
    "sg:postcode":"28612",
    "sg:province":"NC",
    "wof:name":"Dollar General",
    "wof:placetype":"venue"
},
  "geometry": {"coordinates":[-81.49287,35.733713],"type":"Point"}
}