{
  "type": "Feature",
  "properties": {
    "iso:country":"US",
    "sg:address":"1206 Venable Rd",
    "sg:city":"Pilot Mountain",
    "sg:classifiers":[
        {
            "category":"Building & Trades",
            "subcategory":"Electrical",
            "type":"Services"
        }
    ],
    "sg:phone":"+1 336 351 4057",
    "sg:postcode":"27041",
    "sg:province":"NC",
    "sg:tags":[
        "electric",
        "contractor"
    ],
    "wof:name":"J W Bowman Electric",
    "wof:placetype":"venue"
},
  "geometry": {"coordinates":[-80.429558,36.393185],"type":"Point"}
}