{
  "type": "Feature",
  "properties": {
    "addr:full":"1400 S Church St Burlington NC 27215",
    "addr:housenumber":"1400",
    "addr:postcode":"27215",
    "addr:street":"S Church St",
    "iso:country":"US",
    "sg:address":"1400 S Church St",
    "sg:city":"Burlington",
    "sg:classifiers":[
        {
            "category":"Building & Trades",
            "subcategory":"Construction",
            "type":"Services"
        }
    ],
    "sg:phone":"+1 336 226 2225",
    "sg:postcode":"27215",
    "sg:province":"NC",
    "sg:tags":[
        "home",
        "general"
    ],
    "wof:name":"H C Construction",
    "wof:placetype":"venue"
},
  "geometry": {"coordinates":[-79.45361200000001,36.084976],"type":"Point"}
}