{
  "type": "Feature",
  "properties": {
    "addr:full":"2837 US Hwy 64 Mocksville NC 27028",
    "addr:housenumber":"2837",
    "addr:postcode":"27028",
    "addr:street":"Us Hwy 64",
    "iso:country":"US",
    "sg:address":"2837 US Hwy 64",
    "sg:city":"Mocksville",
    "sg:classifiers":[
        {
            "category":"Restaurant",
            "type":"Food & Drink"
        }
    ],
    "sg:phone":"+1 336 998 8230",
    "sg:postcode":"27028",
    "sg:province":"NC",
    "sg:tags":[
        "barbecue"
    ],
    "wof:name":"Hendrix Bar-B-Cue",
    "wof:placetype":"venue"
},
  "geometry": {"coordinates":[-80.457553,35.88155],"type":"Point"}
}