{
  "type": "Feature",
  "properties": {
    "iso:country":"US",
    "sg:address":"859 Sand Ridge Rd",
    "sg:city":"Hubert",
    "sg:classifiers":[
        {
            "category":"Personal",
            "type":"Services"
        }
    ],
    "sg:phone":"+1   ",
    "sg:postcode":"28539",
    "sg:province":"NC",
    "wof:name":"Marilu Donaty Rn Cmt",
    "wof:placetype":"venue"
},
  "geometry": {"coordinates":[-77.189846,34.666396],"type":"Point"}
}