{
  "type": "Feature",
  "properties": {
    "addr:full":"4401 Patrick Ave Wilmington NC 28403",
    "addr:housenumber":"4401",
    "addr:postcode":"28403",
    "addr:street":"Patrick Ave",
    "iso:country":"US",
    "sg:address":"4401 Patrick Ave",
    "sg:city":"Wilmington",
    "sg:classifiers":[
        {
            "category":"Building & Trades",
            "subcategory":"Construction",
            "type":"Services"
        }
    ],
    "sg:phone":"+1 910 392 9073",
    "sg:postcode":"28403",
    "sg:province":"NC",
    "sg:tags":[
        "tile",
        "installation"
    ],
    "wof:name":"Robert Khouri",
    "wof:placetype":"venue"
},
  "geometry": {"coordinates":[-77.88805000000001,34.230402],"type":"Point"}
}