{
  "type": "Feature",
  "properties": {
    "iso:country":"US",
    "sg:address":"3651 Salem Church Rd",
    "sg:city":"Goldsboro",
    "sg:classifiers":[
        {
            "category":"Organizations",
            "subcategory":"Religious Organization",
            "type":"Services"
        }
    ],
    "sg:phone":"+1   ",
    "sg:postcode":"27530",
    "sg:province":"NC",
    "wof:name":"United Pntcstal Chrch Gldsboro",
    "wof:placetype":"venue"
},
  "geometry": {"coordinates":[-77.991772,35.442813],"type":"Point"}
}