{
  "type": "Feature",
  "properties": {
    "addr:full":"3240 Barfield Dr Charlotte NC 28217",
    "addr:housenumber":"3240",
    "addr:postcode":"28217",
    "addr:street":"Barfield Dr",
    "iso:country":"US",
    "sg:address":"3240 Barfield Dr",
    "sg:city":"Charlotte",
    "sg:classifiers":[
        {
            "category":"Local Transit",
            "type":"Transportation"
        }
    ],
    "sg:phone":"+1 704 965 1359",
    "sg:postcode":"28217",
    "sg:province":"NC",
    "sg:tags":[
        "limousine"
    ],
    "wof:name":"Sky Cap Limousine Svc",
    "wof:placetype":"venue"
},
  "geometry": {"coordinates":[-80.884807,35.200197],"type":"Point"}
}