{
  "type": "Feature",
  "properties": {
    "iso:country":"US",
    "sg:address":"1439 Hood Swamp Rd",
    "sg:city":"Goldsboro",
    "sg:classifiers":[
        {
            "category":"Manufacturing",
            "subcategory":"Pet Food",
            "type":"Manufacturing & Wholesale Goods"
        }
    ],
    "sg:phone":"+1 919 778 3491",
    "sg:postcode":"27534",
    "sg:province":"NC",
    "sg:tags":[
        "feed",
        "mfg"
    ],
    "wof:name":"Coker Feed Mill Inc",
    "wof:placetype":"venue"
},
  "geometry": {"coordinates":[-77.87397,35.406518],"type":"Point"}
}