{
  "type": "Feature",
  "properties": {
    "iso:country":"US",
    "sg:address":"112 E Hargett St",
    "sg:city":"Raleigh",
    "sg:classifiers":[
        {
            "category":"Professional",
            "subcategory":"Management & Consulting",
            "type":"Services"
        }
    ],
    "sg:phone":"+1 919 832 2323",
    "sg:postcode":"27601",
    "sg:province":"NC",
    "wof:name":"Wiess Hollmann & Company",
    "wof:placetype":"venue"
},
  "geometry": {"coordinates":[-78.63674,35.778115],"type":"Point"}
}