{
  "type": "Feature",
  "properties": {
    "iso:country":"US",
    "sg:address":"3241 Landing Falls Ln",
    "sg:city":"Raleigh",
    "sg:classifiers":[
        {
            "category":"Building & Trades",
            "subcategory":"Plumbing",
            "type":"Services"
        }
    ],
    "sg:phone":"+1 919 266 7299",
    "sg:postcode":"27616",
    "sg:province":"NC",
    "sg:tags":[
        "plumber",
        "industrial",
        "contractors-commercial"
    ],
    "wof:name":"Charlie's Plumbing Inc",
    "wof:placetype":"venue"
},
  "geometry": {"coordinates":[-78.522825,35.872509],"type":"Point"}
}