{
  "type": "Feature",
  "properties": {
    "addr:full":"3917 N Duke St Durham NC 27704",
    "addr:housenumber":"3917",
    "addr:postcode":"27704",
    "addr:street":"N Duke St",
    "iso:country":"US",
    "sg:address":"3917 N Duke St",
    "sg:city":"Durham",
    "sg:classifiers":[
        {
            "category":"Shopping",
            "subcategory":"Bicycles & Sporting Goods",
            "type":"Retail Goods"
        }
    ],
    "sg:phone":"+1 919 477 1865",
    "sg:postcode":"27704",
    "sg:province":"NC",
    "sg:tags":[
        "printing",
        "commercial"
    ],
    "wof:name":"Firehead Sports",
    "wof:placetype":"venue"
},
  "geometry": {"coordinates":[-78.90413100000001,36.054508],"type":"Point"}
}