{
  "type": "Feature",
  "properties": {
    "iso:country":"US",
    "sg:address":"1317 Beaman St",
    "sg:city":"Clinton",
    "sg:classifiers":[
        {
            "category":"Home & Garden",
            "subcategory":"Furniture",
            "type":"Retail Goods"
        }
    ],
    "sg:phone":"+1 910 592 1263",
    "sg:postcode":"28328",
    "sg:province":"NC",
    "wof:name":"Quality Furniture Outlet",
    "wof:placetype":"venue"
},
  "geometry": {"coordinates":[-78.326998,35.017348],"type":"Point"}
}