{
  "type": "Feature",
  "properties": {
    "iso:country":"US",
    "sg:address":"122 Stroupe Rd",
    "sg:city":"Gastonia",
    "sg:classifiers":[
        {
            "category":"Wholesale",
            "subcategory":"Office Equipment",
            "type":"Manufacturing & Wholesale Goods"
        }
    ],
    "sg:phone":"+1 704 824 6541",
    "sg:postcode":"28056",
    "sg:province":"NC",
    "sg:tags":[
        "machine",
        "counting"
    ],
    "wof:name":"WAK/Count Industries",
    "wof:placetype":"venue"
},
  "geometry": {"coordinates":[-81.11188300000001,35.225365],"type":"Point"}
}