{
  "type": "Feature",
  "properties": {
    "addr:full":"2931 N Church St Rocky Mount NC 27804",
    "addr:housenumber":"2931",
    "addr:postcode":"27804",
    "addr:street":"N Church St",
    "iso:country":"US",
    "sg:address":"2931 N Church St",
    "sg:city":"Rocky Mount",
    "sg:classifiers":[
        {
            "category":"Retail",
            "subcategory":"Auto Repair",
            "type":"Services"
        }
    ],
    "sg:phone":"+1 252 977 6646",
    "sg:postcode":"27804",
    "sg:province":"NC",
    "sg:tags":[
        "wrecker"
    ],
    "wof:name":"Robbie's Recker & Recovery",
    "wof:placetype":"venue"
},
  "geometry": {"coordinates":[-77.78269,35.982502],"type":"Point"}
}