{
  "type": "Feature",
  "properties": {
    "iso:country":"US",
    "sg:address":"790 Ed Deal Rd",
    "sg:city":"China Grove",
    "sg:classifiers":[
        {
            "category":"Professional",
            "type":"Services"
        }
    ],
    "sg:phone":"+1 704 855 2665",
    "sg:postcode":"28023",
    "sg:province":"NC",
    "wof:name":"T & D Charolais",
    "wof:placetype":"venue"
},
  "geometry": {"coordinates":[-80.663372,35.600869],"type":"Point"}
}