{
  "type": "Feature",
  "properties": {
    "addr:full":"1614 Red Robin St Charlotte NC 28214",
    "addr:housenumber":"1614",
    "addr:postcode":"28214",
    "addr:street":"Red Robin St",
    "iso:country":"US",
    "sg:address":"1614 Red Robin St",
    "sg:city":"Charlotte",
    "sg:classifiers":[
        {
            "category":"Organizations",
            "subcategory":"Religious Organization",
            "type":"Services"
        },
        {
            "category":"Building & Trades",
            "subcategory":"Construction",
            "type":"Services"
        }
    ],
    "sg:phone":"+1 704 391 1785",
    "sg:postcode":"28214",
    "sg:province":"NC",
    "sg:tags":[
        "home",
        "builder"
    ],
    "wof:name":"Westport Homes NC Moores",
    "wof:placetype":"venue"
},
  "geometry": {"coordinates":[-80.972555,35.271111],"type":"Point"}
}