{
  "type": "Feature",
  "properties": {
    "iso:country":"US",
    "sg:address":"2305 Genesis Dr",
    "sg:city":"Monroe",
    "sg:classifiers":[
        {
            "category":"Professional",
            "type":"Services"
        }
    ],
    "sg:phone":"+1 704 238 1432",
    "sg:postcode":"28110",
    "sg:province":"NC",
    "wof:name":"Michael Kijanski",
    "wof:placetype":"venue"
},
  "geometry": {"coordinates":[-80.637146,35.022591],"type":"Point"}
}