{
  "type": "Feature",
  "properties": {
    "addr:full":"3419 Old Lexington Rd Asheboro NC 27205",
    "addr:housenumber":"3419",
    "addr:postcode":"27205",
    "addr:street":"Old Lexington Rd",
    "iso:country":"US",
    "sg:address":"3419 Old Lexington Rd",
    "sg:city":"Asheboro",
    "sg:classifiers":[
        {
            "category":"Shopping",
            "subcategory":"Gifts & Souvenirs",
            "type":"Retail Goods"
        }
    ],
    "sg:phone":"+1 336 625 5539",
    "sg:postcode":"27205",
    "sg:province":"NC",
    "wof:name":"Barbs Nik Naks",
    "wof:placetype":"venue"
},
  "geometry": {"coordinates":[-79.88439,35.738505],"type":"Point"}
}