{
  "type": "Feature",
  "properties": {
    "addr:full":"927 Pressley Rd Charlotte NC 28217",
    "addr:housenumber":"927",
    "addr:postcode":"28217",
    "addr:street":"Pressley Rd",
    "iso:country":"US",
    "sg:address":"927 Pressley Rd",
    "sg:city":"Charlotte",
    "sg:classifiers":[
        {
            "category":"Building & Trades",
            "subcategory":"Plumbing",
            "type":"Services"
        }
    ],
    "sg:phone":"+1 704 525 0141",
    "sg:postcode":"28217",
    "sg:province":"NC",
    "sg:tags":[
        "conditioning",
        "air",
        "system",
        "contractor"
    ],
    "wof:name":"Climate Systems Inc",
    "wof:placetype":"venue"
},
  "geometry": {"coordinates":[-80.893466,35.189757],"type":"Point"}
}