{
  "type": "Feature",
  "properties": {
    "iso:country":"US",
    "sg:address":"3331 Wilkesboro Hwy",
    "sg:city":"Statesville",
    "sg:classifiers":[
        {
            "category":"Freight",
            "type":"Transportation"
        }
    ],
    "sg:phone":"+1 704 876 3135",
    "sg:postcode":"28625",
    "sg:province":"NC",
    "sg:tags":[
        "interstate",
        "trucking"
    ],
    "wof:name":"Hager Trucking Company Inc",
    "wof:placetype":"venue"
},
  "geometry": {"coordinates":[-80.94720700000001,35.884878],"type":"Point"}
}