{
  "type": "Feature",
  "properties": {
    "addr:full":"1021 N Winstead Ave Rocky Mount NC 27804",
    "addr:housenumber":"1021",
    "addr:postcode":"27804",
    "addr:street":"N Winstead Ave",
    "iso:country":"US",
    "sg:address":"1021 N Winstead Ave",
    "sg:city":"Rocky Mount",
    "sg:classifiers":[
        {
            "category":"Home & Garden",
            "subcategory":"Furniture",
            "type":"Retail Goods"
        }
    ],
    "sg:phone":"+1 252 937 5762",
    "sg:postcode":"27804",
    "sg:province":"NC",
    "sg:tags":[
        "interior",
        "design",
        "store"
    ],
    "wof:name":"Gracie's Interiors",
    "wof:placetype":"venue"
},
  "geometry": {"coordinates":[-77.843199,35.979665],"type":"Point"}
}