{
  "type": "Feature",
  "properties": {
    "iso:country":"US",
    "sg:address":"1594 Dudley Shoals Rd",
    "sg:city":"Granite Falls",
    "sg:phone":"+1 828 396 7313",
    "sg:postcode":"28630",
    "sg:province":"NC",
    "sg:tags":[
        "farm",
        "corn",
        "soybean",
        "tobacco"
    ],
    "wof:name":"Jimmy Hall",
    "wof:placetype":"venue"
},
  "geometry": {"coordinates":[-81.37367999999999,35.861922],"type":"Point"}
}