{
  "type": "Feature",
  "properties": {
    "addr:full":"109 SE 2nd St Snow Hill NC 28580",
    "addr:housenumber":"109",
    "addr:postcode":"28580",
    "addr:street":"Se 2Nd St",
    "iso:country":"US",
    "sg:address":"109 SE 2nd St",
    "sg:city":"Snow Hill",
    "sg:classifiers":[
        {
            "category":"Professional",
            "subcategory":"Lawyer & Legal Services",
            "type":"Services"
        }
    ],
    "sg:phone":"+1 252 747 5152",
    "sg:postcode":"28580",
    "sg:province":"NC",
    "sg:tags":[
        "attorney"
    ],
    "sg:website":"www.whiteandallen.com",
    "wof:name":"White & Allen",
    "wof:placetype":"venue"
},
  "geometry": {"coordinates":[-77.67067,35.455251],"type":"Point"}
}