{
  "type": "Feature",
  "properties": {
    "iso:country":"US",
    "sg:address":"3505 Whichard Rd",
    "sg:city":"Greenville",
    "sg:classifiers":[
        {
            "category":"Professional",
            "subcategory":"Business Services",
            "type":"Services"
        }
    ],
    "sg:phone":"+1 252 757 3311",
    "sg:postcode":"27834",
    "sg:province":"NC",
    "sg:tags":[
        "repairing",
        "sign"
    ],
    "wof:name":"Atlantic Petroleum Equipment",
    "wof:placetype":"venue"
},
  "geometry": {"coordinates":[-77.325591,35.632565],"type":"Point"}
}