{
  "type": "Feature",
  "properties": {
    "addr:full":"1364 Chestnut Grove Rd King NC 27021",
    "addr:housenumber":"1364",
    "addr:postcode":"27021",
    "addr:street":"Chestnut Grove Rd",
    "iso:country":"US",
    "sg:address":"1364 Chestnut Grove Rd",
    "sg:city":"King",
    "sg:classifiers":[
        {
            "category":"Retail",
            "subcategory":"Repair Shop",
            "type":"Services"
        }
    ],
    "sg:phone":"+1   ",
    "sg:postcode":"27021",
    "sg:province":"NC",
    "wof:name":"Wildlife Recreations Taxidermy",
    "wof:placetype":"venue"
},
  "geometry": {"coordinates":[-80.345462,36.323718],"type":"Point"}
}