{
  "type": "Feature",
  "properties": {
    "iso:country":"US",
    "sg:address":"3010 Monroe Rd Ste 207",
    "sg:city":"Charlotte",
    "sg:classifiers":[
        {
            "category":"Insurance",
            "subcategory":"Hazard Insurance",
            "type":"Services"
        },
        {
            "category":"Insurance",
            "subcategory":"Insurance Agent",
            "type":"Services"
        },
        {
            "category":"Insurance",
            "subcategory":"Life Insurance",
            "type":"Services"
        },
        {
            "category":"Insurance",
            "subcategory":"Title Insurance",
            "type":"Services"
        }
    ],
    "sg:phone":"+1 704 342 2886",
    "sg:postcode":"28205",
    "sg:province":"NC",
    "sg:tags":[
        "auto",
        "homeowner"
    ],
    "sg:website":"http://www.nationwide.com/agent/Charlotte-NORTH-CAROLINA-insurance-agent/bill-laurie/office.html",
    "wof:name":"William Laurie Agency - Nationwide Insurance",
    "wof:placetype":"venue"
},
  "geometry": {"coordinates":[-80.804782,35.204258],"type":"Point"}
}