{
  "type": "Feature",
  "properties": {
    "iso:country":"US",
    "sg:address":"640 Old Evans Rd",
    "sg:city":"Garner",
    "sg:classifiers":[
        {
            "category":"Building & Trades",
            "subcategory":"Landscaping Services",
            "type":"Services"
        }
    ],
    "sg:phone":"+1 919 553 7235",
    "sg:postcode":"27529",
    "sg:province":"NC",
    "wof:name":"Albaughs Lawnscaping",
    "wof:placetype":"venue"
},
  "geometry": {"coordinates":[-78.545799,35.617098],"type":"Point"}
}