{
  "type": "Feature",
  "properties": {
    "iso:country":"US",
    "sg:address":"5750 State Hwy 96 S",
    "sg:city":"Four Oaks",
    "sg:phone":"+1 919 894 4439",
    "sg:postcode":"27524",
    "sg:province":"NC",
    "sg:tags":[
        "irish",
        "tobacco",
        "potato",
        "farm",
        "crop",
        "field"
    ],
    "wof:name":"Clifton Temple",
    "wof:placetype":"venue"
},
  "geometry": {"coordinates":[-78.434523,35.368462],"type":"Point"}
}