{
  "type": "Feature",
  "properties": {
    "addr:full":"12113 Oakwood View Dr Raleigh NC 27614",
    "addr:housenumber":"12113",
    "addr:postcode":"27614",
    "addr:street":"Oakwood View Dr",
    "iso:country":"US",
    "sg:address":"12113 Oakwood View Dr",
    "sg:city":"Raleigh",
    "sg:classifiers":[
        {
            "category":"Professional",
            "type":"Services"
        }
    ],
    "sg:phone":"+1 919 556 7035",
    "sg:postcode":"27614",
    "sg:province":"NC",
    "wof:name":"Thomas Hill",
    "wof:placetype":"venue"
},
  "geometry": {"coordinates":[-78.564452,35.942959],"type":"Point"}
}