{
  "type": "Feature",
  "properties": {
    "addr:full":"121 W Main St Whiteville NC 28472",
    "addr:housenumber":"121",
    "addr:postcode":"28472",
    "addr:street":"W Main St",
    "iso:country":"US",
    "sg:address":"121 W Main St",
    "sg:city":"Whiteville",
    "sg:classifiers":[
        {
            "category":"Health Services",
            "subcategory":"Nursing And Care Facility",
            "type":"Services"
        }
    ],
    "sg:phone":"+1 910 642 9051",
    "sg:postcode":"28472",
    "sg:province":"NC",
    "sg:tags":[
        "hospice"
    ],
    "wof:name":"Lower Cape Fear Hospice",
    "wof:placetype":"venue"
},
  "geometry": {"coordinates":[-78.70429300000001,34.322261],"type":"Point"}
}