{
  "type": "Feature",
  "properties": {
    "iso:country":"US",
    "sg:address":"117 Edinburgh Dr",
    "sg:city":"Cary",
    "sg:classifiers":[
        {
            "category":"Professional",
            "subcategory":"Accounting & Tax Preparation",
            "type":"Services"
        }
    ],
    "sg:phone":"+1 919 380 0970",
    "sg:postcode":"27511",
    "sg:province":"NC",
    "sg:tags":[
        "accountant"
    ],
    "wof:name":"Leslie A Iannucci Pa",
    "wof:placetype":"venue"
},
  "geometry": {"coordinates":[-78.798258,35.741756],"type":"Point"}
}