{
  "type": "Feature",
  "properties": {
    "iso:country":"US",
    "sg:address":"942 Mr Henry Rd",
    "sg:city":"Mocksville",
    "sg:classifiers":[
        {
            "category":"Home & Garden",
            "subcategory":"Carpets & Floor Coverings",
            "type":"Retail Goods"
        }
    ],
    "sg:phone":"+1 336 492 2735",
    "sg:postcode":"27028",
    "sg:province":"NC",
    "wof:name":"Matlocks Carpet Service",
    "wof:placetype":"venue"
},
  "geometry": {"coordinates":[-80.62720899999999,35.841009],"type":"Point"}
}