{
  "type": "Feature",
  "properties": {
    "iso:country":"US",
    "sg:address":"3760 S Main St",
    "sg:city":"Farmville",
    "sg:classifiers":[
        {
            "category":"Shopping",
            "subcategory":"Used Merchandise",
            "type":"Retail Goods"
        }
    ],
    "sg:phone":"+1 252 753 9929",
    "sg:postcode":"27828",
    "sg:province":"NC",
    "sg:tags":[
        "antique"
    ],
    "wof:name":"Woodside Antiques & Auction",
    "wof:placetype":"venue"
},
  "geometry": {"coordinates":[-77.58609300000001,35.596407],"type":"Point"}
}