{
  "type": "Feature",
  "properties": {
    "iso:country":"US",
    "sg:address":"1678 N Minton Rd",
    "sg:city":"Millers Creek",
    "sg:classifiers":[
        {
            "category":"Retail",
            "subcategory":"Animal Services",
            "type":"Services"
        }
    ],
    "sg:phone":"+1 336 973 4148",
    "sg:postcode":"28651",
    "sg:province":"NC",
    "wof:name":"Tommy Minton",
    "wof:placetype":"venue"
},
  "geometry": {"coordinates":[-81.265278,36.169546],"type":"Point"}
}