{
  "type": "Feature",
  "properties": {
    "iso:country":"US",
    "sg:address":"1025 Industrial Park Dr",
    "sg:city":"Smithfield",
    "sg:classifiers":[
        {
            "category":"Shopping",
            "subcategory":"Hobbies, Toys, & Games",
            "type":"Retail Goods"
        }
    ],
    "sg:phone":"+1 919 934 4108",
    "sg:postcode":"27577",
    "sg:province":"NC",
    "sg:tags":[
        "store"
    ],
    "wof:name":"Kb Toy Outlet",
    "wof:placetype":"venue"
},
  "geometry": {"coordinates":[-78.313292,35.508419],"type":"Point"}
}