{
  "type": "Feature",
  "properties": {
    "iso:country":"US",
    "sg:address":"403 Statesville Rd",
    "sg:city":"Como",
    "sg:classifiers":[
        {
            "category":"Building & Trades",
            "subcategory":"Electrical",
            "type":"Services"
        }
    ],
    "sg:phone":"+1 252 398 4954",
    "sg:postcode":"27818",
    "sg:province":"NC",
    "sg:tags":[
        "electric",
        "contractor"
    ],
    "wof:name":"Frank Benthall",
    "wof:placetype":"venue"
},
  "geometry": {"coordinates":[-77.055803,36.471629],"type":"Point"}
}