{
  "type": "Feature",
  "properties": {
    "addr:full":"1373 Elk Park Hwy Newland NC 28657",
    "addr:housenumber":"1373",
    "addr:postcode":"28657",
    "addr:street":"Elk Park Hwy",
    "iso:country":"US",
    "sg:address":"1373 Elk Park Hwy",
    "sg:city":"Newland",
    "sg:classifiers":[
        {
            "category":"Utilities",
            "subcategory":"Electric",
            "type":"Services"
        }
    ],
    "sg:phone":"+1 828 733 0159",
    "sg:postcode":"28657",
    "sg:province":"NC",
    "sg:tags":[
        "company"
    ],
    "wof:name":"Mountain Electric Co-Op",
    "wof:placetype":"venue"
},
  "geometry": {"coordinates":[-81.93479600000001,36.129447],"type":"Point"}
}