{
  "type": "Feature",
  "properties": {
    "iso:country":"US",
    "sg:address":"2906 Poole Rd",
    "sg:city":"Raleigh",
    "sg:classifiers":[
        {
            "category":"Professional",
            "subcategory":"Business Services",
            "type":"Services"
        }
    ],
    "sg:phone":"+1   ",
    "sg:postcode":"27610",
    "sg:province":"NC",
    "wof:name":"Lucas Assoc",
    "wof:placetype":"venue"
},
  "geometry": {"coordinates":[-78.590971,35.772556],"type":"Point"}
}