{
  "type": "Feature",
  "properties": {
    "addr:full":"11537 US Hwy 70 W Clayton NC 27520",
    "addr:housenumber":"11537",
    "addr:postcode":"27520",
    "addr:street":"Us Hwy 70 W",
    "iso:country":"US",
    "sg:address":"11537 US Hwy 70 W",
    "sg:city":"Clayton",
    "sg:classifiers":[
        {
            "category":"Retail",
            "subcategory":"Auto Rental",
            "type":"Services"
        }
    ],
    "sg:phone":"+1 919 553 1145",
    "sg:postcode":"27520",
    "sg:province":"NC",
    "sg:tags":[
        "renting",
        "automobile"
    ],
    "wof:name":"Enterprise Rent A Car",
    "wof:placetype":"venue"
},
  "geometry": {"coordinates":[-78.47264800000001,35.652883],"type":"Point"}
}