{
  "type": "Feature",
  "properties": {
    "addr:full":"10963 Busbin Rd Mt Pleasant NC 28124",
    "addr:housenumber":"10963",
    "addr:postcode":"28124",
    "addr:street":"Busbin Rd",
    "iso:country":"US",
    "sg:address":"10963 Busbin Rd",
    "sg:city":"Mt Pleasant",
    "sg:classifiers":[
        {
            "category":"Building & Trades",
            "subcategory":"Cleaning & Sanitation",
            "type":"Services"
        }
    ],
    "sg:phone":"+1 704 436 9003",
    "sg:postcode":"28124",
    "sg:province":"NC",
    "sg:tags":[
        "house"
    ],
    "wof:name":"Economy Cleaning Svc",
    "wof:placetype":"venue"
},
  "geometry": {"coordinates":[-80.392864,35.424536],"type":"Point"}
}