{
  "type": "Feature",
  "properties": {
    "iso:country":"US",
    "sg:address":"5473 Grimes Rd",
    "sg:city":"Fayetteville",
    "sg:classifiers":[
        {
            "category":"Wholesale",
            "subcategory":"Home Furnishings",
            "type":"Manufacturing & Wholesale Goods"
        }
    ],
    "sg:phone":"+1 910 486 9222",
    "sg:postcode":"28306",
    "sg:province":"NC",
    "wof:name":"Phenomenally Yours",
    "wof:placetype":"venue"
},
  "geometry": {"coordinates":[-79.032816,34.998937],"type":"Point"}
}