{
  "type": "Feature",
  "properties": {
    "iso:country":"US",
    "sg:address":"7913 State Hwy 194 N",
    "sg:city":"Lansing",
    "sg:classifiers":[
        {
            "category":"Manufacturing",
            "subcategory":"Metals",
            "type":"Manufacturing & Wholesale Goods"
        }
    ],
    "sg:phone":"+1 336 384 3312",
    "sg:postcode":"28643",
    "sg:province":"NC",
    "sg:tags":[
        "mfg",
        "forging"
    ],
    "wof:name":"Axle Shop",
    "wof:placetype":"venue"
},
  "geometry": {"coordinates":[-81.49910199999999,36.484387],"type":"Point"}
}