{
  "type": "Feature",
  "properties": {
    "iso:country":"US",
    "sg:address":"1437 Reeves Mill Rd",
    "sg:city":"Mount Airy",
    "sg:classifiers":[
        {
            "category":"Organizations",
            "subcategory":"Religious Organization",
            "type":"Services"
        }
    ],
    "sg:phone":"+1   ",
    "sg:postcode":"27030",
    "sg:province":"NC",
    "wof:name":"Skyline Pentecostal",
    "wof:placetype":"venue"
},
  "geometry": {"coordinates":[-80.542449,36.465815],"type":"Point"}
}