{
  "type": "Feature",
  "properties": {
    "iso:country":"US",
    "sg:address":"107 Ridge Trl",
    "sg:city":"Chapel Hill",
    "sg:classifiers":[
        {
            "category":"Professional",
            "type":"Services"
        }
    ],
    "sg:phone":"+1 919 929 2991",
    "sg:postcode":"27516",
    "sg:province":"NC",
    "wof:name":"Infocus",
    "wof:placetype":"venue"
},
  "geometry": {"coordinates":[-79.067431,35.921762],"type":"Point"}
}