{
  "type": "Feature",
  "properties": {
    "addr:full":"815 Spring Garden St Greensboro NC 27403",
    "addr:housenumber":"815",
    "addr:postcode":"27403",
    "addr:street":"Spring Garden St",
    "iso:country":"US",
    "sg:address":"815 Spring Garden St",
    "sg:city":"Greensboro",
    "sg:classifiers":[
        {
            "category":"Museum",
            "type":"Entertainment"
        }
    ],
    "sg:phone":"+1 336 275 8834",
    "sg:postcode":"27403",
    "sg:province":"NC",
    "sg:tags":[
        "organization",
        "arts",
        "information"
    ],
    "wof:name":"Brighton Art Svc",
    "wof:placetype":"venue"
},
  "geometry": {"coordinates":[-79.802688,36.06642],"type":"Point"}
}