{
  "type": "Feature",
  "properties": {
    "addr:full":"639 Garren Creek Rd Fairview NC 28730",
    "addr:housenumber":"639",
    "addr:postcode":"28730",
    "addr:street":"Garren Creek Rd",
    "iso:country":"US",
    "sg:address":"639 Garren Creek Rd",
    "sg:city":"Fairview",
    "sg:classifiers":[
        {
            "category":"Building & Trades",
            "subcategory":"Construction",
            "type":"Services"
        }
    ],
    "sg:phone":"+1 828 628 1155",
    "sg:postcode":"28730",
    "sg:province":"NC",
    "sg:tags":[
        "house"
    ],
    "wof:name":"Lytle Construction Co",
    "wof:placetype":"venue"
},
  "geometry": {"coordinates":[-82.362461,35.522202],"type":"Point"}
}