{
  "type": "Feature",
  "properties": {
    "iso:country":"US",
    "sg:address":"2121 Kenric Dr",
    "sg:city":"Lumberton",
    "sg:classifiers":[
        {
            "category":"Autos & Motor Vehicles",
            "subcategory":"Automobile Sales",
            "type":"Retail Goods"
        }
    ],
    "sg:phone":"+1 910 618 0600",
    "sg:postcode":"28358",
    "sg:province":"NC",
    "sg:tags":[
        "motorcycle"
    ],
    "wof:name":"I-95 Cycles",
    "wof:placetype":"venue"
},
  "geometry": {"coordinates":[-79.099141,34.604849],"type":"Point"}
}