{
  "type": "Feature",
  "properties": {
    "addr:full":"1517 W Raleigh St Siler City NC 27344",
    "addr:housenumber":"1517",
    "addr:postcode":"27344",
    "addr:street":"W Raleigh St",
    "iso:country":"US",
    "sg:address":"1517 W Raleigh St",
    "sg:city":"Siler City",
    "sg:classifiers":[
        {
            "category":"Retail",
            "subcategory":"Repair Shop",
            "type":"Services"
        }
    ],
    "sg:phone":"+1   ",
    "sg:postcode":"27344",
    "sg:province":"NC",
    "wof:name":"Junction",
    "wof:placetype":"venue"
},
  "geometry": {"coordinates":[-79.47009300000001,35.714609],"type":"Point"}
}