{
  "type": "Feature",
  "properties": {
    "iso:country":"US",
    "sg:address":"1135 Kildaire Farm Rd",
    "sg:city":"Cary",
    "sg:classifiers":[
        {
            "category":"Professional",
            "type":"Services"
        }
    ],
    "sg:phone":"+1 919 657 0845",
    "sg:postcode":"27511",
    "sg:province":"NC",
    "sg:tags":[
        "establishment"
    ],
    "wof:name":"Larry P Ward & Assoc",
    "wof:placetype":"venue"
},
  "geometry": {"coordinates":[-78.78243999999999,35.767451],"type":"Point"}
}