{
  "type": "Feature",
  "properties": {
    "addr:full":"5300 Old Pineville Rd Charlotte NC 28217",
    "addr:housenumber":"5300",
    "addr:postcode":"28217",
    "addr:street":"Old Pineville Rd",
    "iso:country":"US",
    "sg:address":"5300 Old Pineville Rd",
    "sg:city":"Charlotte",
    "sg:classifiers":[
        {
            "category":"Professional",
            "subcategory":"Accounting & Tax Preparation",
            "type":"Services"
        }
    ],
    "sg:phone":"+1   ",
    "sg:postcode":"28217",
    "sg:province":"NC",
    "wof:name":"Daniel W Geiser CPA PA",
    "wof:placetype":"venue"
},
  "geometry": {"coordinates":[-80.87800300000001,35.168768],"type":"Point"}
}