{
  "type": "Feature",
  "properties": {
    "iso:country":"US",
    "sg:address":"2847 Asheville Hwy",
    "sg:city":"Canton",
    "sg:classifiers":[
        {
            "category":"Professional",
            "subcategory":"Business Services",
            "type":"Services"
        }
    ],
    "sg:phone":"+1 828 648 8040",
    "sg:postcode":"28716",
    "sg:province":"NC",
    "sg:tags":[
        "painter",
        "sign"
    ],
    "wof:name":"Rose Art & Sign Co",
    "wof:placetype":"venue"
},
  "geometry": {"coordinates":[-82.816126,35.535604],"type":"Point"}
}