{
  "type": "Feature",
  "properties": {
    "addr:full":"36 Hayes St Waynesville NC 28785",
    "addr:housenumber":"36",
    "addr:postcode":"28785",
    "addr:street":"Hayes St",
    "iso:country":"US",
    "sg:address":"36 Hayes St",
    "sg:city":"Waynesville",
    "sg:classifiers":[
        {
            "category":"Banks & Credit Unions",
            "subcategory":"Bank",
            "type":"Services"
        }
    ],
    "sg:phone":"+1 828 926 3580",
    "sg:postcode":"28785",
    "sg:province":"NC",
    "sg:tags":[
        "mortgage"
    ],
    "wof:name":"Gold Key Mortgage",
    "wof:placetype":"venue"
},
  "geometry": {"coordinates":[-83.019077,35.52406],"type":"Point"}
}