{
  "type": "Feature",
  "properties": {
    "addr:full":"1516 S Main St Mount Airy NC 27030",
    "addr:housenumber":"1516",
    "addr:postcode":"27030",
    "addr:street":"S Main St",
    "iso:country":"US",
    "sg:address":"1516 S Main St",
    "sg:city":"Mount Airy",
    "sg:classifiers":[
        {
            "category":"Restaurant",
            "type":"Food & Drink"
        }
    ],
    "sg:phone":"+1 336 789 2396",
    "sg:postcode":"27030",
    "sg:province":"NC",
    "sg:tags":[
        "eating"
    ],
    "wof:name":"Speedy Chef",
    "wof:placetype":"venue"
},
  "geometry": {"coordinates":[-80.594786,36.490107],"type":"Point"}
}