{
  "type": "Feature",
  "properties": {
    "iso:country":"US",
    "sg:address":"151 Walker Rd",
    "sg:city":"Murphy",
    "sg:classifiers":[
        {
            "category":"Organizations",
            "subcategory":"Religious Organization",
            "type":"Services"
        }
    ],
    "sg:phone":"+1   ",
    "sg:postcode":"28906",
    "sg:province":"NC",
    "wof:name":"Ranger Baptist Church",
    "wof:placetype":"venue"
},
  "geometry": {"coordinates":[-84.13642,35.032719],"type":"Point"}
}