{
  "type": "Feature",
  "properties": {
    "addr:full":"2501 University Dr Durham NC 27707",
    "addr:housenumber":"2501",
    "addr:postcode":"27707",
    "addr:street":"University Dr",
    "iso:country":"US",
    "sg:address":"2501 University Dr",
    "sg:city":"Durham",
    "sg:classifiers":[
        {
            "category":"Cafe",
            "type":"Food & Drink"
        }
    ],
    "sg:menulink":"http://www.allmenus.com/nc/durham/270860-thai-cafe/menu/",
    "sg:phone":"+1 919 493 9794",
    "sg:postcode":"27707",
    "sg:province":"NC",
    "sg:tags":[
        "thai",
        "asian"
    ],
    "wof:name":"Thai Cafe",
    "wof:placetype":"venue"
},
  "geometry": {"coordinates":[-78.92353799999999,35.974711],"type":"Point"}
}