{
  "type": "Feature",
  "properties": {
    "addr:full":"309 W College St Warsaw NC 28398",
    "addr:housenumber":"309",
    "addr:postcode":"28398",
    "addr:street":"W College St",
    "iso:country":"US",
    "sg:address":"309 W College St",
    "sg:city":"Warsaw",
    "sg:classifiers":[
        {
            "category":"Shopping",
            "subcategory":"Clothing, Apparel, & Fashions",
            "type":"Retail Goods"
        }
    ],
    "sg:phone":"+1 910 293 4404",
    "sg:postcode":"28398",
    "sg:province":"NC",
    "sg:tags":[
        "furnishing"
    ],
    "wof:name":"Mia's Mini Shop",
    "wof:placetype":"venue"
},
  "geometry": {"coordinates":[-78.097268,34.997717],"type":"Point"}
}