{
  "type": "Feature",
  "properties": {
    "addr:full":"2325 US Hwy 52 Albemarle NC 28001",
    "addr:housenumber":"2325",
    "addr:postcode":"28001",
    "addr:street":"Us Hwy 52",
    "iso:country":"US",
    "sg:address":"2325 US Hwy 52",
    "sg:city":"Albemarle",
    "sg:classifiers":[
        {
            "category":"Autos & Motor Vehicles",
            "subcategory":"Fuel & Gas Station",
            "type":"Retail Goods"
        }
    ],
    "sg:phone":"+1 704 982 2144",
    "sg:postcode":"28001",
    "sg:province":"NC",
    "sg:tags":[
        "oil"
    ],
    "wof:name":"Wilco",
    "wof:placetype":"venue"
},
  "geometry": {"coordinates":[-80.199271,35.394827],"type":"Point"}
}