{
  "type": "Feature",
  "properties": {
    "addr:full":"1525 Central Ave Charlotte NC 28205",
    "addr:housenumber":"1525",
    "addr:postcode":"28205",
    "addr:street":"Central Ave",
    "iso:country":"US",
    "sg:address":"1525 Central Ave",
    "sg:city":"Charlotte",
    "sg:classifiers":[
        {
            "category":"Banks & Credit Unions",
            "subcategory":"Bank",
            "type":"Services"
        }
    ],
    "sg:phone":"+1 704 370 0004",
    "sg:postcode":"28205",
    "sg:province":"NC",
    "sg:tags":[
        "loan",
        "real estate"
    ],
    "wof:name":"Reliable Source Mortgage Inc",
    "wof:placetype":"venue"
},
  "geometry": {"coordinates":[-80.812485,35.220423],"type":"Point"}
}