{
  "type": "Feature",
  "properties": {
    "iso:country":"US",
    "sg:address":"628 22nd Ave NE",
    "sg:city":"Hickory",
    "sg:classifiers":[
        {
            "category":"Professional",
            "type":"Services"
        }
    ],
    "sg:phone":"+1 828 322 7875",
    "sg:postcode":"28601",
    "sg:province":"NC",
    "sg:tags":[
        "establishment"
    ],
    "wof:name":"North West Developmental Coi",
    "wof:placetype":"venue"
},
  "geometry": {"coordinates":[-81.320413,35.759185],"type":"Point"}
}