{
  "type": "Feature",
  "properties": {
    "addr:full":"3412 Lonesome Spur Cir Wake Forest NC 27587",
    "addr:housenumber":"3412",
    "addr:postcode":"27587",
    "addr:street":"Lonesome Spur Cir",
    "iso:country":"US",
    "sg:address":"3412 Lonesome Spur Cir",
    "sg:city":"Wake Forest",
    "sg:classifiers":[
        {
            "category":"Wholesale",
            "subcategory":"Medical Equipment & Supplies",
            "type":"Manufacturing & Wholesale Goods"
        }
    ],
    "sg:phone":"+1 919 562 5280",
    "sg:postcode":"27587",
    "sg:province":"NC",
    "wof:name":"First Quality Products",
    "wof:placetype":"venue"
},
  "geometry": {"coordinates":[-78.519965,35.913614],"type":"Point"}
}