{
  "type": "Feature",
  "properties": {
    "addr:full":"594 Old Settlement Rd Sylva NC 28779",
    "addr:housenumber":"594",
    "addr:postcode":"28779",
    "addr:street":"Old Settlement Rd",
    "iso:country":"US",
    "sg:address":"594 Old Settlement Rd",
    "sg:city":"Sylva",
    "sg:classifiers":[
        {
            "category":"Health Services",
            "subcategory":"Hospital",
            "type":"Services"
        }
    ],
    "sg:phone":"+1 828 586 8731",
    "sg:postcode":"28779",
    "sg:province":"NC",
    "sg:tags":[
        "medical",
        "surgical",
        "emergency"
    ],
    "wof:name":"West Care Emergency Svc",
    "wof:placetype":"venue"
},
  "geometry": {"coordinates":[-83.215046,35.33965],"type":"Point"}
}