{
  "type": "Feature",
  "properties": {
    "addr:full":"80 Moose Loop Rd Louisburg NC 27549",
    "addr:housenumber":"80",
    "addr:postcode":"27549",
    "addr:street":"Moose Loop Rd",
    "iso:country":"US",
    "sg:address":"80 Moose Loop Rd",
    "sg:city":"Louisburg",
    "sg:classifiers":[
        {
            "category":"Wholesale",
            "subcategory":"Machinery & Supplies",
            "type":"Manufacturing & Wholesale Goods"
        },
        {
            "category":"Manufacturing",
            "subcategory":"Tools & Machinery",
            "type":"Manufacturing & Wholesale Goods"
        }
    ],
    "sg:phone":"+1 919 496 1013",
    "sg:postcode":"27549",
    "sg:province":"NC",
    "sg:tags":[
        "machine",
        "equipment",
        "industrial",
        "shop"
    ],
    "wof:name":"Creative Automation Systems",
    "wof:placetype":"venue"
},
  "geometry": {"coordinates":[-78.269508,36.094508],"type":"Point"}
}