{
  "type": "Feature",
  "properties": {
    "addr:full":"455 Club Knolls Rd Dudley NC 28333",
    "addr:housenumber":"455",
    "addr:postcode":"28333",
    "addr:street":"Club Knolls Rd",
    "iso:country":"US",
    "sg:address":"455 Club Knolls Rd",
    "sg:city":"Dudley",
    "sg:classifiers":[
        {
            "category":"Building & Trades",
            "subcategory":"Landscaping Services",
            "type":"Services"
        }
    ],
    "sg:phone":"+1 919 735 6326",
    "sg:postcode":"28333",
    "sg:province":"NC",
    "wof:name":"Swinson Landscape Service",
    "wof:placetype":"venue"
},
  "geometry": {"coordinates":[-78.0686,35.249091],"type":"Point"}
}