{
  "type": "Feature",
  "properties": {
    "addr:full":"128 E Garrison Blvd Gastonia NC 28054",
    "addr:housenumber":"128",
    "addr:postcode":"28054",
    "addr:street":"E Garrison Blvd",
    "iso:country":"US",
    "sg:address":"128 E Garrison Blvd",
    "sg:city":"Gastonia",
    "sg:classifiers":[
        {
            "category":"Insurance",
            "subcategory":"Insurance Agent",
            "type":"Services"
        }
    ],
    "sg:phone":"+1 704 868 4045",
    "sg:postcode":"28054",
    "sg:province":"NC",
    "wof:name":"Vericlaim",
    "wof:placetype":"venue"
},
  "geometry": {"coordinates":[-81.17975800000001,35.25352],"type":"Point"}
}