{
  "type": "Feature",
  "properties": {
    "addr:full":"254 Leighton Hall Rd Wallace NC 28466",
    "addr:housenumber":"254",
    "addr:postcode":"28466",
    "addr:street":"Leighton Hall Rd",
    "iso:country":"US",
    "sg:address":"254 Leighton Hall Rd",
    "sg:city":"Wallace",
    "sg:classifiers":[
        {
            "category":"Farming",
            "subcategory":"Farm",
            "type":"Manufacturing & Wholesale Goods"
        }
    ],
    "sg:phone":"+1 910 532 4465",
    "sg:postcode":"28466",
    "sg:province":"NC",
    "sg:tags":[
        "crop",
        "animal",
        "general"
    ],
    "wof:name":"George W Rivenbark",
    "wof:placetype":"venue"
},
  "geometry": {"coordinates":[-78.17931799999999,34.769722],"type":"Point"}
}