{
  "type": "Feature",
  "properties": {
    "addr:full":"500 Dexter St Greenville NC 27834",
    "addr:housenumber":"500",
    "addr:postcode":"27834",
    "addr:street":"Dexter St",
    "iso:country":"US",
    "sg:address":"500 Dexter St",
    "sg:city":"Greenville",
    "sg:classifiers":[
        {
            "category":"Shopping",
            "subcategory":"Discount & Variety Stores",
            "type":"Retail Goods"
        }
    ],
    "sg:phone":"+1 252 757 2511",
    "sg:postcode":"27834",
    "sg:province":"NC",
    "sg:tags":[
        "merchandise",
        "general"
    ],
    "wof:name":"Map Store",
    "wof:placetype":"venue"
},
  "geometry": {"coordinates":[-77.394209,35.576786],"type":"Point"}
}