{
  "type": "Feature",
  "properties": {
    "addr:full":"5145 Margaret Wallace Rd Matthews NC 28105",
    "addr:housenumber":"5145",
    "addr:postcode":"28105",
    "addr:street":"Margaret Wallace Rd",
    "iso:country":"US",
    "sg:address":"5145 Margaret Wallace Rd",
    "sg:city":"Matthews",
    "sg:classifiers":[
        {
            "category":"Building & Trades",
            "subcategory":"Construction",
            "type":"Services"
        }
    ],
    "sg:phone":"+1 704 545 3177",
    "sg:postcode":"28105",
    "sg:province":"NC",
    "sg:tags":[
        "house"
    ],
    "wof:name":"Metheney Construction",
    "wof:placetype":"venue"
},
  "geometry": {"coordinates":[-80.697862,35.179859],"type":"Point"}
}