{
  "type": "Feature",
  "properties": {
    "addr:full":"1610 Sunset Ave Rocky Mount NC 27804",
    "addr:housenumber":"1610",
    "addr:postcode":"27804",
    "addr:street":"Sunset Ave",
    "iso:country":"US",
    "sg:address":"1610 Sunset Ave",
    "sg:city":"Rocky Mount",
    "sg:classifiers":[
        {
            "category":"Shopping",
            "type":"Retail Goods"
        }
    ],
    "sg:phone":"+1 252 985 1595",
    "sg:postcode":"27804",
    "sg:province":"NC",
    "sg:tags":[
        "spa",
        "hot",
        "tub"
    ],
    "wof:name":"Swim World",
    "wof:placetype":"venue"
},
  "geometry": {"coordinates":[-77.81772599999999,35.94896],"type":"Point"}
}