{
  "type": "Feature",
  "properties": {
    "iso:country":"US",
    "sg:address":"164 Vine St",
    "sg:city":"Mount Airy",
    "sg:classifiers":[
        {
            "category":"Freight",
            "type":"Transportation"
        }
    ],
    "sg:phone":"+1 336 789 1462",
    "sg:postcode":"27030",
    "sg:province":"NC",
    "sg:tags":[
        "operator",
        "local",
        "trucking"
    ],
    "wof:name":"Mantzway Trucking Inc",
    "wof:placetype":"venue"
},
  "geometry": {"coordinates":[-80.57829599999999,36.488058],"type":"Point"}
}