{
  "type": "Feature",
  "properties": {
    "iso:country":"US",
    "sg:address":"2925 Middleton St",
    "sg:city":"Winston Salem",
    "sg:classifiers":[
        {
            "category":"Retail",
            "subcategory":"Auto Repair",
            "type":"Services"
        }
    ],
    "sg:phone":"+1   ",
    "sg:postcode":"27107",
    "sg:province":"NC",
    "sg:tags":[
        "automotive"
    ],
    "wof:name":"Roberts Wrecker Service",
    "wof:placetype":"venue"
},
  "geometry": {"coordinates":[-80.226854,36.060411],"type":"Point"}
}