{
  "type": "Feature",
  "properties": {
    "addr:full":"850 Mountain St Kannapolis NC 28081",
    "addr:housenumber":"850",
    "addr:postcode":"28081",
    "addr:street":"Mountain St",
    "iso:country":"US",
    "sg:address":"850 Mountain St",
    "sg:city":"Kannapolis",
    "sg:classifiers":[
        {
            "category":"Education",
            "subcategory":"Library",
            "type":"Public Place"
        }
    ],
    "sg:phone":"+1 704 920 1180",
    "sg:postcode":"28081",
    "sg:province":"NC",
    "sg:tags":[
        "executive"
    ],
    "wof:name":"Kannapolis Branch Library",
    "wof:placetype":"venue"
},
  "geometry": {"coordinates":[-80.635409,35.505257],"type":"Point"}
}