{
  "type": "Feature",
  "properties": {
    "addr:full":"2032 Homestead Rd Chapel Hill NC 27516",
    "addr:housenumber":"2032",
    "addr:postcode":"27516",
    "addr:street":"Homestead Rd",
    "iso:country":"US",
    "sg:address":"2032 Homestead Rd",
    "sg:city":"Chapel Hill",
    "sg:classifiers":[
        {
            "category":"Building & Trades",
            "subcategory":"Construction",
            "type":"Services"
        }
    ],
    "sg:phone":"+1 919 968 0125",
    "sg:postcode":"27516",
    "sg:province":"NC",
    "sg:tags":[
        "house"
    ],
    "wof:name":"T L McClendon & Son Constructi",
    "wof:placetype":"venue"
},
  "geometry": {"coordinates":[-79.080184,35.951111],"type":"Point"}
}