{
  "type": "Feature",
  "properties": {
    "iso:country":"US",
    "sg:address":"208 Bloomington Ln",
    "sg:city":"Wilmington",
    "sg:classifiers":[
        {
            "category":"Building & Trades",
            "subcategory":"Construction",
            "type":"Services"
        }
    ],
    "sg:phone":"+1 910 686 0448",
    "sg:postcode":"28411",
    "sg:province":"NC",
    "sg:tags":[
        "painter"
    ],
    "wof:name":"Spectrum",
    "wof:placetype":"venue"
},
  "geometry": {"coordinates":[-77.812955,34.270675],"type":"Point"}
}