{
  "type": "Feature",
  "properties": {
    "iso:country":"US",
    "sg:address":"2700 Sumner Blvd",
    "sg:city":"Raleigh",
    "sg:classifiers":[
        {
            "category":"Shopping",
            "subcategory":"Crafts & Fabrics",
            "type":"Retail Goods"
        }
    ],
    "sg:phone":"+1 919 873 9449",
    "sg:postcode":"27616",
    "sg:province":"NC",
    "sg:tags":[
        "shop"
    ],
    "wof:name":"Grand South Design",
    "wof:placetype":"venue"
},
  "geometry": {"coordinates":[-78.589896,35.871453],"type":"Point"}
}