{
  "type": "Feature",
  "properties": {
    "iso:country":"US",
    "sg:address":"57316 Eagle Pass Rd",
    "sg:city":"Hatteras",
    "sg:classifiers":[
        {
            "category":"Travel",
            "subcategory":"Campground",
            "type":"Entertainment"
        }
    ],
    "sg:phone":"+1 252 986 2422",
    "sg:postcode":"27943",
    "sg:province":"NC",
    "wof:name":"Hatteras Sands Camping Resort",
    "wof:placetype":"venue"
},
  "geometry": {"coordinates":[-75.687568,35.215716],"type":"Point"}
}