{
  "type": "Feature",
  "properties": {
    "addr:full":"1664 S Main St Laurinburg NC 28352",
    "addr:housenumber":"1664",
    "addr:postcode":"28352",
    "addr:street":"S Main St",
    "iso:country":"US",
    "sg:address":"1664 S Main St",
    "sg:city":"Laurinburg",
    "sg:classifiers":[
        {
            "category":"Shopping",
            "subcategory":"Pharmacy",
            "type":"Retail Goods"
        }
    ],
    "sg:phone":"+1 910 277 8665",
    "sg:postcode":"28352",
    "sg:province":"NC",
    "wof:name":"Kmart Pharmacies Inc",
    "wof:placetype":"venue"
},
  "geometry": {"coordinates":[-79.476978,34.754137],"type":"Point"}
}