{
  "type": "Feature",
  "properties": {
    "addr:full":"2124 Dunn Rd Raleigh NC 27614",
    "addr:housenumber":"2124",
    "addr:postcode":"27614",
    "addr:street":"Dunn Rd",
    "iso:country":"US",
    "sg:address":"2124 Dunn Rd",
    "sg:city":"Raleigh",
    "sg:classifiers":[
        {
            "category":"Building & Trades",
            "subcategory":"Cleaning & Sanitation",
            "type":"Services"
        }
    ],
    "sg:phone":"+1   ",
    "sg:postcode":"27614",
    "sg:province":"NC",
    "sg:tags":[
        "maintenance"
    ],
    "wof:name":"Reborn Again Cleaning Service",
    "wof:placetype":"venue"
},
  "geometry": {"coordinates":[-78.571827,35.920884],"type":"Point"}
}