{
  "type": "Feature",
  "properties": {
    "iso:country":"US",
    "sg:address":"3829 Old Julian Rd",
    "sg:city":"Julian",
    "sg:classifiers":[
        {
            "category":"Organizations",
            "subcategory":"Religious Organization",
            "type":"Services"
        }
    ],
    "sg:phone":"+1   ",
    "sg:postcode":"27283",
    "sg:province":"NC",
    "wof:name":"Welkers Crossroads Ev Meth Ch",
    "wof:placetype":"venue"
},
  "geometry": {"coordinates":[-79.61717400000001,35.986849],"type":"Point"}
}