{
  "type": "Feature",
  "properties": {
    "addr:full":"4111 Rose Lake Dr Charlotte NC 28217",
    "addr:housenumber":"4111",
    "addr:postcode":"28217",
    "addr:street":"Rose Lake Dr",
    "iso:country":"US",
    "sg:address":"4111 Rose Lake Dr",
    "sg:city":"Charlotte",
    "sg:classifiers":[
        {
            "category":"Wholesale",
            "subcategory":"Office Equipment",
            "type":"Manufacturing & Wholesale Goods"
        }
    ],
    "sg:phone":"+1 704 357 1350",
    "sg:postcode":"28217",
    "sg:province":"NC",
    "wof:name":"Xerox",
    "wof:placetype":"venue"
},
  "geometry": {"coordinates":[-80.92803499999999,35.180018],"type":"Point"}
}