{
  "type": "Feature",
  "properties": {
    "iso:country":"US",
    "sg:address":"1401 E 7th St 100",
    "sg:city":"Charlotte",
    "sg:classifiers":[
        {
            "category":"Professional",
            "subcategory":"Management & Consulting",
            "type":"Services"
        }
    ],
    "sg:phone":"+1 704 333 5606",
    "sg:postcode":"28204",
    "sg:province":"NC",
    "sg:tags":[
        "consultant"
    ],
    "wof:name":"A A Management Corp.",
    "wof:placetype":"venue"
},
  "geometry": {"coordinates":[-80.82617999999999,35.218571],"type":"Point"}
}