{
  "type": "Feature",
  "properties": {
    "iso:country":"US",
    "sg:address":"1234 S Main St",
    "sg:city":"Graham",
    "sg:classifiers":[
        {
            "category":"Bars & Pubs",
            "type":"Food & Drink"
        }
    ],
    "sg:menulink":"http://www.allmenus.com/nc/graham/141005-hurseys-bar-b-q/menu/",
    "sg:phone":"+1 336 570 3838",
    "sg:postcode":"27253",
    "sg:province":"NC",
    "sg:tags":[
        "barbecue",
        "american"
    ],
    "wof:name":"Hursey's Bar-b-q",
    "wof:placetype":"venue"
},
  "geometry": {"coordinates":[-79.395714,36.044322],"type":"Point"}
}