{
  "type": "Feature",
  "properties": {
    "iso:country":"US",
    "sg:address":"1407 McDonald Ave",
    "sg:city":"Hamlet",
    "sg:classifiers":[
        {
            "category":"Organizations",
            "subcategory":"Religious Organization",
            "type":"Services"
        }
    ],
    "sg:phone":"+1   ",
    "sg:postcode":"28345",
    "sg:province":"NC",
    "wof:name":"First Pntcstal Hlness Chrch Ha",
    "wof:placetype":"venue"
},
  "geometry": {"coordinates":[-79.72322,34.890729],"type":"Point"}
}