{
  "type": "Feature",
  "properties": {
    "iso:country":"US",
    "sg:address":"10901 University City Blvd",
    "sg:city":"Charlotte",
    "sg:classifiers":[
        {
            "category":"Personal",
            "type":"Services"
        },
        {
            "category":"Personal",
            "subcategory":"Tattoo Parlor",
            "type":"Services"
        }
    ],
    "sg:phone":"+1 704 510 5100",
    "sg:postcode":"28213",
    "sg:province":"NC",
    "sg:tags":[
        "tattooing"
    ],
    "wof:name":"University Tattoo",
    "wof:placetype":"venue"
},
  "geometry": {"coordinates":[-80.700791,35.313942],"type":"Point"}
}