{
  "type": "Feature",
  "properties": {
    "addr:full":"300 Spring Branch Rd Dunn NC 28334",
    "addr:housenumber":"300",
    "addr:postcode":"28334",
    "addr:street":"Spring Branch Rd",
    "iso:country":"US",
    "sg:address":"300 Spring Branch Rd",
    "sg:city":"Dunn",
    "sg:classifiers":[
        {
            "category":"Building & Trades",
            "subcategory":"Construction",
            "type":"Services"
        }
    ],
    "sg:phone":"+1 910 892 2881",
    "sg:postcode":"28334",
    "sg:province":"NC",
    "sg:tags":[
        "woodworker"
    ],
    "wof:name":"J & J Custom Woodworks Inc",
    "wof:placetype":"venue"
},
  "geometry": {"coordinates":[-78.60605700000001,35.297934],"type":"Point"}
}