{
  "type": "Feature",
  "properties": {
    "iso:country":"US",
    "sg:address":"18700 Nantz Rd",
    "sg:city":"Cornelius",
    "sg:classifiers":[
        {
            "category":"Autos & Motor Vehicles",
            "subcategory":"Auto Supplies",
            "type":"Retail Goods"
        }
    ],
    "sg:phone":"+1 704 892 5923",
    "sg:postcode":"28031",
    "sg:province":"NC",
    "wof:name":"Zero 2 Sixty Motorsports",
    "wof:placetype":"venue"
},
  "geometry": {"coordinates":[-80.892276,35.469471],"type":"Point"}
}