{
  "type": "Feature",
  "properties": {
    "addr:full":"671 Washington St Washington NC 27889",
    "addr:housenumber":"671",
    "addr:postcode":"27889",
    "addr:street":"Washington St",
    "iso:country":"US",
    "sg:address":"671 Washington St",
    "sg:city":"Washington",
    "sg:classifiers":[
        {
            "category":"Banks & Credit Unions",
            "subcategory":"Bank",
            "type":"Services"
        }
    ],
    "sg:phone":"+1 252 948 0618",
    "sg:postcode":"27889",
    "sg:province":"NC",
    "sg:tags":[
        "cashing",
        "personal",
        "check",
        "institution"
    ],
    "wof:name":"Advance America",
    "wof:placetype":"venue"
},
  "geometry": {"coordinates":[-77.05925499999999,35.551724],"type":"Point"}
}