{
  "type": "Feature",
  "properties": {
    "addr:full":"262 Shady Grove Dr Timberlake NC 27583",
    "addr:housenumber":"262",
    "addr:postcode":"27583",
    "addr:street":"Shady Grove Dr",
    "iso:country":"US",
    "sg:address":"262 Shady Grove Dr",
    "sg:city":"Timberlake",
    "sg:classifiers":[
        {
            "category":"Building & Trades",
            "subcategory":"Construction",
            "type":"Services"
        }
    ],
    "sg:phone":"+1 336 364 8287",
    "sg:postcode":"27583",
    "sg:province":"NC",
    "sg:tags":[
        "contractor"
    ],
    "wof:name":"A&A Masonry",
    "wof:placetype":"venue"
},
  "geometry": {"coordinates":[-78.929813,36.294433],"type":"Point"}
}