{
  "type": "Feature",
  "properties": {
    "addr:full":"110 Roswell Dr Kernersville NC 27284",
    "addr:housenumber":"110",
    "addr:postcode":"27284",
    "addr:street":"Roswell Dr",
    "iso:country":"US",
    "sg:address":"110 Roswell Dr",
    "sg:city":"Kernersville",
    "sg:classifiers":[
        {
            "category":"Shopping",
            "subcategory":"Clothing, Apparel, & Fashions",
            "type":"Retail Goods"
        }
    ],
    "sg:phone":"+1 336 993 4899",
    "sg:postcode":"27284",
    "sg:province":"NC",
    "wof:name":"T & T Fashions",
    "wof:placetype":"venue"
},
  "geometry": {"coordinates":[-80.073814,36.150856],"type":"Point"}
}