{
  "type": "Feature",
  "properties": {
    "addr:full":"6304 Westgate Rd Raleigh NC 27617",
    "addr:housenumber":"6304",
    "addr:postcode":"27617",
    "addr:street":"Westgate Rd",
    "iso:country":"US",
    "sg:address":"6304 Westgate Rd",
    "sg:city":"Raleigh",
    "sg:classifiers":[
        {
            "category":"Manufacturing",
            "subcategory":"Electronics",
            "type":"Manufacturing & Wholesale Goods"
        }
    ],
    "sg:phone":"+1 919 420 0920",
    "sg:postcode":"27617",
    "sg:province":"NC",
    "sg:tags":[
        "semiconductor",
        "devices"
    ],
    "wof:name":"Power Technology Svc",
    "wof:placetype":"venue"
},
  "geometry": {"coordinates":[-78.758222,35.903597],"type":"Point"}
}