{
  "type": "Feature",
  "properties": {
    "iso:country":"US",
    "sg:address":"3758 Carvette Ct",
    "sg:city":"High Point",
    "sg:classifiers":[
        {
            "category":"Professional",
            "subcategory":"Business Services",
            "type":"Services"
        }
    ],
    "sg:phone":"+1   ",
    "sg:postcode":"27265",
    "sg:province":"NC",
    "wof:name":"Rapid Appraisal Service",
    "wof:placetype":"venue"
},
  "geometry": {"coordinates":[-79.986715,36.029782],"type":"Point"}
}