{
  "type": "Feature",
  "properties": {
    "iso:country":"US",
    "sg:address":"3121 Plateau Rd",
    "sg:city":"Newton",
    "sg:classifiers":[
        {
            "category":"Health Services",
            "subcategory":"Doctor",
            "type":"Services"
        }
    ],
    "sg:phone":"+1 704 276 9200",
    "sg:postcode":"28658",
    "sg:province":"NC",
    "sg:tags":[
        "physician",
        "surgeon"
    ],
    "wof:name":"Bill J Parker MD",
    "wof:placetype":"venue"
},
  "geometry": {"coordinates":[-81.36037399999999,35.607557],"type":"Point"}
}