{
  "type": "Feature",
  "properties": {
    "iso:country":"US",
    "sg:address":"1421 Rock Spring St",
    "sg:city":"Greensboro",
    "sg:classifiers":[
        {
            "category":"Retail",
            "subcategory":"Repair Shop",
            "type":"Services"
        }
    ],
    "sg:phone":"+1 336 621 4954",
    "sg:postcode":"27405",
    "sg:province":"NC",
    "sg:tags":[
        "lock",
        "locksmith"
    ],
    "wof:name":"Hood Lock Svc",
    "wof:placetype":"venue"
},
  "geometry": {"coordinates":[-79.770695,36.122511],"type":"Point"}
}