{
  "type": "Feature",
  "properties": {
    "iso:country":"US",
    "sg:address":"3642 Shannon Rd",
    "sg:city":"Durham",
    "sg:classifiers":[
        {
            "category":"Professional",
            "subcategory":"Business Services",
            "type":"Services"
        }
    ],
    "sg:phone":"+1 919 401 4999",
    "sg:postcode":"27707",
    "sg:province":"NC",
    "sg:tags":[
        "embroidery"
    ],
    "wof:name":"Print Marks",
    "wof:placetype":"venue"
},
  "geometry": {"coordinates":[-78.955523,35.956616],"type":"Point"}
}