{
  "type": "Feature",
  "properties": {
    "iso:country":"US",
    "sg:address":"601 James Griffin Dr",
    "sg:city":"Graham",
    "sg:classifiers":[
        {
            "category":"Professional",
            "subcategory":"Computer Services",
            "type":"Services"
        }
    ],
    "sg:phone":"+1   ",
    "sg:postcode":"27253",
    "sg:province":"NC",
    "sg:tags":[
        "consulting"
    ],
    "wof:name":"Iws",
    "wof:placetype":"venue"
},
  "geometry": {"coordinates":[-79.37803099999999,36.033121],"type":"Point"}
}