{
  "type": "Feature",
  "properties": {
    "addr:full":"13301 Melvin Arnold Rd Raleigh NC 27613",
    "addr:housenumber":"13301",
    "addr:postcode":"27613",
    "addr:street":"Melvin Arnold Rd",
    "iso:country":"US",
    "sg:address":"13301 Melvin Arnold Rd",
    "sg:city":"Raleigh",
    "sg:classifiers":[
        {
            "category":"Professional",
            "type":"Services"
        }
    ],
    "sg:phone":"+1 919 676 8479",
    "sg:postcode":"27613",
    "sg:province":"NC",
    "wof:name":"M&W Aviation Inc",
    "wof:placetype":"venue"
},
  "geometry": {"coordinates":[-78.69435900000001,35.967588],"type":"Point"}
}