{
  "type": "Feature",
  "properties": {
    "iso:country":"US",
    "sg:address":"2021 Walden Glade Run",
    "sg:city":"Apex",
    "sg:classifiers":[
        {
            "category":"Communications",
            "type":"Services"
        }
    ],
    "sg:phone":"+1 919 303 7334",
    "sg:postcode":"27523",
    "sg:province":"NC",
    "sg:tags":[
        "web",
        "design"
    ],
    "wof:name":"Abriyah Internet Services",
    "wof:placetype":"venue"
},
  "geometry": {"coordinates":[-78.87915700000001,35.753274],"type":"Point"}
}