{
  "type": "Feature",
  "properties": {
    "addr:full":"1441 Pine Needle Ln Mooresville NC 28115",
    "addr:housenumber":"1441",
    "addr:postcode":"28115",
    "addr:street":"Pine Needle Ln",
    "iso:country":"US",
    "sg:address":"1441 Pine Needle Ln",
    "sg:city":"Mooresville",
    "sg:classifiers":[
        {
            "category":"Wholesale",
            "subcategory":"Machinery & Supplies",
            "type":"Manufacturing & Wholesale Goods"
        }
    ],
    "sg:phone":"+1 704 662 3061",
    "sg:postcode":"28115",
    "sg:province":"NC",
    "sg:tags":[
        "equipment",
        "industrial"
    ],
    "wof:name":"Total First Aid & Safety Inc",
    "wof:placetype":"venue"
},
  "geometry": {"coordinates":[-80.802852,35.547922],"type":"Point"}
}