{
  "type": "Feature",
  "properties": {
    "iso:country":"US",
    "sg:address":"395 Glovers Chapel Rd",
    "sg:city":"Siler City",
    "sg:classifiers":[
        {
            "category":"Building & Trades",
            "subcategory":"Construction",
            "type":"Services"
        }
    ],
    "sg:phone":"+1 919 837 0096",
    "sg:postcode":"27344",
    "sg:province":"NC",
    "sg:tags":[
        "concrete",
        "contractor"
    ],
    "wof:name":"Bear Creek Concrete Inc",
    "wof:placetype":"venue"
},
  "geometry": {"coordinates":[-79.34654500000001,35.667499],"type":"Point"}
}