{
  "type": "Feature",
  "properties": {
    "addr:full":"2669 Owen Dr Fayetteville NC 28306",
    "addr:housenumber":"2669",
    "addr:postcode":"28306",
    "addr:street":"Owen Dr",
    "iso:country":"US",
    "sg:address":"2669 Owen Dr",
    "sg:city":"Fayetteville",
    "sg:classifiers":[
        {
            "category":"Utilities",
            "subcategory":"Fuel Oil & Lpg",
            "type":"Services"
        }
    ],
    "sg:phone":"+1 910 323 8283",
    "sg:postcode":"28306",
    "sg:province":"NC",
    "sg:tags":[
        "liquefied",
        "gas",
        "petroleum"
    ],
    "wof:name":"Parker Gas Stedman",
    "wof:placetype":"venue"
},
  "geometry": {"coordinates":[-78.907832,35.018091],"type":"Point"}
}