{
  "type": "Feature",
  "properties": {
    "iso:country":"US",
    "sg:address":"2350 Old Lexington Rd",
    "sg:city":"Winston Salem",
    "sg:classifiers":[
        {
            "category":"Retail",
            "subcategory":"Auto Repair",
            "type":"Services"
        }
    ],
    "sg:phone":"+1   ",
    "sg:postcode":"27107",
    "sg:province":"NC",
    "sg:tags":[
        "general"
    ],
    "wof:name":"Jr & Son Auto Repair",
    "wof:placetype":"venue"
},
  "geometry": {"coordinates":[-80.227026,36.068232],"type":"Point"}
}