{
  "type": "Feature",
  "properties": {
    "iso:country":"US",
    "sg:address":"1814 N Berkeley Blvd",
    "sg:city":"Goldsboro",
    "sg:classifiers":[
        {
            "category":"Food & Beverages",
            "subcategory":"Groceries & Convenience Stores",
            "type":"Retail Goods"
        }
    ],
    "sg:phone":"+1 919 751 3551",
    "sg:postcode":"27534",
    "sg:province":"NC",
    "wof:name":"Pantry Inc",
    "wof:placetype":"venue"
},
  "geometry": {"coordinates":[-77.92028500000001,35.388476],"type":"Point"}
}