{
  "type": "Feature",
  "properties": {
    "iso:country":"US",
    "sg:address":"1435 N Aspen St",
    "sg:city":"Lincolnton",
    "sg:classifiers":[
        {
            "category":"Health Services",
            "subcategory":"Dentist",
            "type":"Services"
        }
    ],
    "sg:phone":"+1 704 735 7001",
    "sg:postcode":"28092",
    "sg:province":"NC",
    "sg:tags":[
        "dentists-cosmetic",
        "dentistry"
    ],
    "sg:website":"http://www.realpagessites.com/dedmondanddedmond",
    "wof:name":"Dedmond Family Dentistry",
    "wof:placetype":"venue"
},
  "geometry": {"coordinates":[-81.250722,35.490405],"type":"Point"}
}