{
  "type": "Feature",
  "properties": {
    "addr:full":"2647 Lillington Hwy Spring Lake NC 28390",
    "addr:postcode":"2647;28390",
    "addr:street":"Lillington Hwy",
    "iso:country":"US",
    "sg:address":"2647 Lillington Hwy",
    "sg:city":"Spring Lake",
    "sg:classifiers":[
        {
            "category":"Wholesale",
            "subcategory":"Auto Parts",
            "type":"Manufacturing & Wholesale Goods"
        }
    ],
    "sg:phone":"+1 910 497 2745",
    "sg:postcode":"28390",
    "sg:province":"NC",
    "sg:tags":[
        "tire"
    ],
    "wof:name":"Bea's Used Tires",
    "wof:placetype":"venue"
},
  "geometry": {"coordinates":[-78.94890100000001,35.209289],"type":"Point"}
}