{
  "type": "Feature",
  "properties": {
    "addr:full":"118 W A St Newton NC 28658",
    "addr:housenumber":"118",
    "addr:postcode":"28658",
    "addr:street":"W A St",
    "iso:country":"US",
    "sg:address":"118 W A St",
    "sg:city":"Newton",
    "sg:classifiers":[
        {
            "category":"Shopping",
            "subcategory":"Used Merchandise",
            "type":"Retail Goods"
        }
    ],
    "sg:phone":"+1 828 465 2776",
    "sg:postcode":"28658",
    "sg:province":"NC",
    "wof:name":"Salvation Army Thrift Store",
    "wof:placetype":"venue"
},
  "geometry": {"coordinates":[-81.22443199999999,35.663365],"type":"Point"}
}