{
  "type": "Feature",
  "properties": {
    "iso:country":"US",
    "sg:address":"7069 Market St",
    "sg:city":"Wilmington",
    "sg:classifiers":[
        {
            "category":"Recreation",
            "type":"Entertainment"
        }
    ],
    "sg:phone":"+1 910 686 3269",
    "sg:postcode":"28411",
    "sg:province":"NC",
    "sg:tags":[
        "parks"
    ],
    "wof:name":"New Hanover County Park Dept",
    "wof:placetype":"venue"
},
  "geometry": {"coordinates":[-77.821343,34.270012],"type":"Point"}
}