{
  "type": "Feature",
  "properties": {
    "iso:country":"US",
    "sg:address":"3011 Raeford Rd",
    "sg:city":"Fayetteville",
    "sg:classifiers":[
        {
            "category":"Building & Trades",
            "subcategory":"Construction",
            "type":"Services"
        },
        {
            "category":"Retail",
            "subcategory":"Auto Repair",
            "type":"Services"
        },
        {
            "category":"Autos & Motor Vehicles",
            "subcategory":"Auto Supplies",
            "type":"Retail Goods"
        }
    ],
    "sg:phone":"+1 910 423 8468",
    "sg:postcode":"28303",
    "sg:province":"NC",
    "sg:tags":[
        "automobile",
        "coating",
        "tinting",
        "accessory",
        "glass",
        "contractor"
    ],
    "wof:name":"Diamond Window Tint Inc",
    "wof:placetype":"venue"
},
  "geometry": {"coordinates":[-78.930286,35.044804],"type":"Point"}
}