{
  "type": "Feature",
  "properties": {
    "addr:full":"8805 Running Oak Dr Raleigh NC 27617",
    "addr:housenumber":"8805",
    "addr:postcode":"27617",
    "addr:street":"Running Oak Dr",
    "iso:country":"US",
    "sg:address":"8805 Running Oak Dr",
    "sg:city":"Raleigh",
    "sg:classifiers":[
        {
            "category":"Autos & Motor Vehicles",
            "subcategory":"Automobile Sales",
            "type":"Retail Goods"
        }
    ],
    "sg:phone":"+1 919 783 5520",
    "sg:postcode":"27617",
    "sg:province":"NC",
    "sg:tags":[
        "performance",
        "race",
        "dealer"
    ],
    "wof:name":"Tuner Solutions",
    "wof:placetype":"venue"
},
  "geometry": {"coordinates":[-78.759664,35.904706],"type":"Point"}
}