{
  "type": "Feature",
  "properties": {
    "addr:full":"5275 Parkway Plaza Blvd Charlotte NC 28217",
    "addr:housenumber":"5275",
    "addr:postcode":"28217",
    "addr:street":"Parkway Plaza Blvd",
    "iso:country":"US",
    "sg:address":"5275 Parkway Plaza Blvd",
    "sg:city":"Charlotte",
    "sg:classifiers":[
        {
            "category":"Wholesale",
            "subcategory":"Computers",
            "type":"Manufacturing & Wholesale Goods"
        }
    ],
    "sg:phone":"+1 704 357 5100",
    "sg:postcode":"28217",
    "sg:province":"NC",
    "sg:tags":[
        "peripheral",
        "mfg"
    ],
    "wof:name":"Cisco Systems",
    "wof:placetype":"venue"
},
  "geometry": {"coordinates":[-80.90412999999999,35.18052],"type":"Point"}
}