{
  "type": "Feature",
  "properties": {
    "addr:full":"2545 Crab Catcher Ct Wilmington NC 28409",
    "addr:housenumber":"2545",
    "addr:postcode":"28409",
    "addr:street":"Crab Catcher Ct",
    "iso:country":"US",
    "sg:address":"2545 Crab Catcher Ct",
    "sg:city":"Wilmington",
    "sg:classifiers":[
        {
            "category":"Professional",
            "subcategory":"Computer Services",
            "type":"Services"
        }
    ],
    "sg:phone":"+1 843 290 2993",
    "sg:postcode":"28409",
    "sg:province":"NC",
    "sg:tags":[
        "industrial",
        "for",
        "process",
        "equipment",
        "interface",
        "con"
    ],
    "wof:name":"GPA",
    "wof:placetype":"venue"
},
  "geometry": {"coordinates":[-77.88113300000001,34.10649],"type":"Point"}
}