{
  "type": "Feature",
  "properties": {
    "addr:full":"307 Dover St Pineville NC 28134",
    "addr:housenumber":"307",
    "addr:postcode":"28134",
    "addr:street":"Dover St",
    "iso:country":"US",
    "sg:address":"307 Dover St",
    "sg:city":"Pineville",
    "sg:classifiers":[
        {
            "category":"Real Estate",
            "subcategory":"Surveying",
            "type":"Services"
        }
    ],
    "sg:phone":"+1 704 889 7601",
    "sg:postcode":"28134",
    "sg:province":"NC",
    "sg:tags":[
        "surveyor"
    ],
    "wof:name":"Carolina Surveyors Inc",
    "wof:placetype":"venue"
},
  "geometry": {"coordinates":[-80.89345,35.083759],"type":"Point"}
}