{
  "type": "Feature",
  "properties": {
    "iso:country":"US",
    "sg:address":"315 Arlington Ave",
    "sg:city":"Charlotte",
    "sg:classifiers":[
        {
            "category":"Real Estate",
            "subcategory":"Real Estate Agent",
            "type":"Services"
        }
    ],
    "sg:phone":"+1 704 844 6844",
    "sg:postcode":"28203",
    "sg:province":"NC",
    "sg:tags":[
        "investment"
    ],
    "wof:name":"Primitive Bark",
    "wof:placetype":"venue"
},
  "geometry": {"coordinates":[-80.852146,35.216538],"type":"Point"}
}