{
  "type": "Feature",
  "properties": {
    "iso:country":"US",
    "sg:address":"4118 Buckhorn Rd",
    "sg:city":"Bullock",
    "sg:classifiers":[
        {
            "category":"Organizations",
            "subcategory":"Religious Organization",
            "type":"Services"
        }
    ],
    "sg:phone":"+1   ",
    "sg:postcode":"27565",
    "sg:province":"NC",
    "wof:name":"Baptist Grove Church",
    "wof:placetype":"venue"
},
  "geometry": {"coordinates":[-78.53716799999999,36.491377],"type":"Point"}
}