{
  "type": "Feature",
  "properties": {
    "iso:country":"US",
    "sg:address":"978 Airport Rd",
    "sg:city":"Rockingham",
    "sg:classifiers":[
        {
            "category":"Shopping",
            "subcategory":"Florist",
            "type":"Retail Goods"
        }
    ],
    "sg:phone":"+1 910 582 5781",
    "sg:postcode":"28379",
    "sg:province":"NC",
    "wof:name":"Floral Designs By Sue",
    "wof:placetype":"venue"
},
  "geometry": {"coordinates":[-79.74378900000001,34.877689],"type":"Point"}
}