{
  "type": "Feature",
  "properties": {
    "iso:country":"US",
    "sg:address":"929 N Brightleaf Blvd",
    "sg:city":"Smithfield",
    "sg:classifiers":[
        {
            "category":"Professional",
            "subcategory":"Business Services",
            "type":"Services"
        }
    ],
    "sg:phone":"+1   ",
    "sg:postcode":"27577",
    "sg:province":"NC",
    "wof:name":"Business Computer Solutions LL",
    "wof:placetype":"venue"
},
  "geometry": {"coordinates":[-78.32383400000001,35.516197],"type":"Point"}
}