{
  "type": "Feature",
  "properties": {
    "iso:country":"US",
    "sg:address":"10535 New Britton Hwy E",
    "sg:city":"Whiteville",
    "sg:classifiers":[
        {
            "category":"Building & Trades",
            "subcategory":"Plumbing",
            "type":"Services"
        }
    ],
    "sg:phone":"+1 910 640 0992",
    "sg:postcode":"28472",
    "sg:province":"NC",
    "sg:tags":[
        "tank",
        "septic"
    ],
    "wof:name":"Register's Excavation & Septic",
    "wof:placetype":"venue"
},
  "geometry": {"coordinates":[-78.605226,34.191461],"type":"Point"}
}