{
  "type": "Feature",
  "properties": {
    "addr:full":"1424 Dellwood Rd Waynesville NC 28786",
    "addr:housenumber":"1424",
    "addr:postcode":"28786",
    "addr:street":"Dellwood Rd",
    "iso:country":"US",
    "sg:address":"1424 Dellwood Rd",
    "sg:city":"Waynesville",
    "sg:classifiers":[
        {
            "category":"Communications",
            "type":"Services"
        }
    ],
    "sg:phone":"+1 828 926 9171",
    "sg:postcode":"28786",
    "sg:province":"NC",
    "wof:name":"K & S Communication",
    "wof:placetype":"venue"
},
  "geometry": {"coordinates":[-82.988798,35.526163],"type":"Point"}
}