{
  "type": "Feature",
  "properties": {
    "iso:country":"US",
    "sg:address":"1332 Maccripine Rd",
    "sg:city":"Pinetops",
    "sg:classifiers":[
        {
            "category":"Organizations",
            "subcategory":"Community Association",
            "type":"Services"
        }
    ],
    "sg:phone":"+1 252 827 5636",
    "sg:postcode":"27864",
    "sg:province":"NC",
    "sg:tags":[
        "club"
    ],
    "wof:name":"Mac Cripine Country Club",
    "wof:placetype":"venue"
},
  "geometry": {"coordinates":[-77.659278,35.767482],"type":"Point"}
}