{
  "type": "Feature",
  "properties": {
    "iso:country":"US",
    "sg:address":"1732 Racetrack Rd",
    "sg:city":"New Bern",
    "sg:classifiers":[
        {
            "category":"Manufacturing",
            "subcategory":"Building Materials",
            "type":"Manufacturing & Wholesale Goods"
        }
    ],
    "sg:phone":"+1 252 638 6506",
    "sg:postcode":"28562",
    "sg:province":"NC",
    "sg:tags":[
        "truss"
    ],
    "sg:website":"www.ebctruss.com",
    "wof:name":"Eastern Building Components",
    "wof:placetype":"venue"
},
  "geometry": {"coordinates":[-77.09646600000001,35.127337],"type":"Point"}
}