{
  "type": "Feature",
  "properties": {
    "iso:country":"US",
    "sg:address":"80 Green Forest Rd",
    "sg:city":"Swannanoa",
    "sg:classifiers":[
        {
            "category":"Manufacturing",
            "subcategory":"Printing",
            "type":"Manufacturing & Wholesale Goods"
        }
    ],
    "sg:phone":"+1 828 686 3469",
    "sg:postcode":"28778",
    "sg:province":"NC",
    "sg:tags":[
        "high",
        "speed",
        "duplicating",
        "offset"
    ],
    "wof:name":"Rapid Impressions Inc",
    "wof:placetype":"venue"
},
  "geometry": {"coordinates":[-82.413466,35.609773],"type":"Point"}
}