{
  "type": "Feature",
  "properties": {
    "addr:full":"227 Kensington Rd Greensboro NC 27403",
    "addr:housenumber":"227",
    "addr:postcode":"27403",
    "addr:street":"Kensington Rd",
    "iso:country":"US",
    "sg:address":"227 Kensington Rd",
    "sg:city":"Greensboro",
    "sg:classifiers":[
        {
            "category":"Health Services",
            "subcategory":"Health Practitioner",
            "type":"Services"
        }
    ],
    "sg:phone":"+1   ",
    "sg:postcode":"27403",
    "sg:province":"NC",
    "wof:name":"Smith Betty K MA Liscense Phys",
    "wof:placetype":"venue"
},
  "geometry": {"coordinates":[-79.819834,36.070268],"type":"Point"}
}