{
  "type": "Feature",
  "properties": {
    "addr:full":"509 W 14th St Greenville NC 27834",
    "addr:housenumber":"509",
    "addr:postcode":"27834",
    "addr:street":"W 14Th St",
    "iso:country":"US",
    "sg:address":"509 W 14th St",
    "sg:city":"Greenville",
    "sg:classifiers":[
        {
            "category":"Retail",
            "subcategory":"Repair Shop",
            "type":"Services"
        }
    ],
    "sg:phone":"+1   ",
    "sg:postcode":"27834",
    "sg:province":"NC",
    "wof:name":"Winterville Refinishing",
    "wof:placetype":"venue"
},
  "geometry": {"coordinates":[-77.380523,35.602547],"type":"Point"}
}