{
  "type": "Feature",
  "properties": {
    "iso:country":"US",
    "sg:address":"172 Isaacs Rock Ln",
    "sg:city":"Mount Airy",
    "sg:classifiers":[
        {
            "category":"Building & Trades",
            "subcategory":"Landscaping Services",
            "type":"Services"
        }
    ],
    "sg:phone":"+1 336 352 3319",
    "sg:postcode":"27030",
    "sg:province":"NC",
    "sg:tags":[
        "landscape"
    ],
    "wof:name":"Oakleys Landscaping",
    "wof:placetype":"venue"
},
  "geometry": {"coordinates":[-80.818428,36.46003],"type":"Point"}
}