{
  "type": "Feature",
  "properties": {
    "iso:country":"US",
    "sg:address":"142 Bluewing Ln",
    "sg:city":"Mooresville",
    "sg:classifiers":[
        {
            "category":"Retail",
            "subcategory":"Repair Shop",
            "type":"Services"
        }
    ],
    "sg:phone":"+1 704 664 5154",
    "sg:postcode":"28117",
    "sg:province":"NC",
    "sg:tags":[
        "trade",
        "contractor"
    ],
    "wof:name":"Lake Electronics",
    "wof:placetype":"venue"
},
  "geometry": {"coordinates":[-80.899835,35.551998],"type":"Point"}
}