{
  "type": "Feature",
  "properties": {
    "iso:country":"US",
    "sg:address":"204 Dexter St",
    "sg:city":"Greenville",
    "sg:classifiers":[
        {
            "category":"Wholesale",
            "subcategory":"Machinery & Supplies",
            "type":"Manufacturing & Wholesale Goods"
        }
    ],
    "sg:phone":"+1 252 756 9765",
    "sg:postcode":"27834",
    "sg:province":"NC",
    "sg:tags":[
        "equipment",
        "industrial",
        "electrical",
        "who"
    ],
    "wof:name":"Grainger Industrial Supplies",
    "wof:placetype":"venue"
},
  "geometry": {"coordinates":[-77.396016,35.577042],"type":"Point"}
}