{
  "type": "Feature",
  "properties": {
    "iso:country":"US",
    "sg:address":"1460 Henderson Grove Church Rd",
    "sg:city":"Salisbury",
    "sg:classifiers":[
        {
            "category":"Building & Trades",
            "subcategory":"Construction",
            "type":"Services"
        }
    ],
    "sg:phone":"+1 704 637 8792",
    "sg:postcode":"28147",
    "sg:province":"NC",
    "sg:tags":[
        "mobile",
        "home"
    ],
    "wof:name":"Badger Refurb Ctr",
    "wof:placetype":"venue"
},
  "geometry": {"coordinates":[-80.50479799999999,35.625717],"type":"Point"}
}