{
  "type": "Feature",
  "properties": {
    "iso:country":"US",
    "sg:address":"299 Barry Oak Rd",
    "sg:city":"Statesville",
    "sg:classifiers":[
        {
            "category":"Retail",
            "subcategory":"Auto Repair",
            "type":"Services"
        }
    ],
    "sg:phone":"+1   ",
    "sg:postcode":"28625",
    "sg:province":"NC",
    "sg:tags":[
        "body"
    ],
    "wof:name":"Benfields Body Shop",
    "wof:placetype":"venue"
},
  "geometry": {"coordinates":[-80.755555,35.803595],"type":"Point"}
}