{
  "type": "Feature",
  "properties": {
    "addr:full":"305 N State St Lexington NC 27292",
    "addr:housenumber":"305",
    "addr:postcode":"27292",
    "addr:street":"N State St",
    "iso:country":"US",
    "sg:address":"305 N State St",
    "sg:city":"Lexington",
    "sg:classifiers":[
        {
            "category":"Banks & Credit Unions",
            "subcategory":"Bank",
            "type":"Services"
        }
    ],
    "sg:phone":"+1 336 224 5125",
    "sg:postcode":"27292",
    "sg:province":"NC",
    "sg:tags":[
        "broker",
        "mortgage"
    ],
    "wof:name":"Family First Mortgage Corp",
    "wof:placetype":"venue"
},
  "geometry": {"coordinates":[-80.251485,35.827482],"type":"Point"}
}