{
  "type": "Feature",
  "properties": {
    "iso:country":"US",
    "sg:address":"1212 Cana Rd",
    "sg:city":"Mocksville",
    "sg:classifiers":[
        {
            "category":"Retail",
            "subcategory":"Animal Services",
            "type":"Services"
        }
    ],
    "sg:phone":"+1 336 998 8208",
    "sg:postcode":"27028",
    "sg:province":"NC",
    "sg:tags":[
        "pet"
    ],
    "wof:name":"Critters' Place",
    "wof:placetype":"venue"
},
  "geometry": {"coordinates":[-80.577648,35.974544],"type":"Point"}
}