{
  "type": "Feature",
  "properties": {
    "addr:full":"217 Norman Ave Trinity NC 27370",
    "addr:housenumber":"217",
    "addr:postcode":"27370",
    "addr:street":"Norman Ave",
    "iso:country":"US",
    "sg:address":"217 Norman Ave",
    "sg:city":"Trinity",
    "sg:classifiers":[
        {
            "category":"Retail",
            "subcategory":"Self-service Laundry",
            "type":"Services"
        }
    ],
    "sg:phone":"+1   ",
    "sg:postcode":"27370",
    "sg:province":"NC",
    "sg:tags":[
        "coin"
    ],
    "wof:name":"English Road Launderette Inc",
    "wof:placetype":"venue"
},
  "geometry": {"coordinates":[-79.96799799999999,35.889395],"type":"Point"}
}