{
  "type": "Feature",
  "properties": {
    "iso:country":"US",
    "sg:address":"4424 Taggart Creek Rd",
    "sg:city":"Charlotte",
    "sg:classifiers":[
        {
            "category":"Government",
            "subcategory":"Office",
            "type":"Public Place"
        }
    ],
    "sg:phone":"+1 704 394 2190",
    "sg:postcode":"28208",
    "sg:province":"NC",
    "sg:tags":[
        "international",
        "affairs"
    ],
    "wof:name":"Mexican Consulate",
    "wof:placetype":"venue"
},
  "geometry": {"coordinates":[-80.922012,35.228269],"type":"Point"}
}