{
  "type": "Feature",
  "properties": {
    "addr:full":"1950 Lakeside Dr Franklin NC 28734",
    "addr:housenumber":"1950",
    "addr:postcode":"nc 28734",
    "addr:street":"Lakeside Dr",
    "iso:country":"US",
    "sg:address":"1950 Lakeside Dr",
    "sg:city":"Franklin",
    "sg:classifiers":[
        {
            "category":"Health Services",
            "subcategory":"Hospital",
            "type":"Services"
        }
    ],
    "sg:phone":"+1 828 631 3973",
    "sg:postcode":"28734",
    "sg:province":"NC",
    "sg:tags":[
        "mental"
    ],
    "wof:name":"Meridian Behaviorial Health",
    "wof:placetype":"venue"
},
  "geometry": {"coordinates":[-83.36995899999999,35.194674],"type":"Point"}
}