{
  "type": "Feature",
  "properties": {
    "addr:full":"3801 Back Creek Church Rd Charlotte NC 28213",
    "addr:housenumber":"3801",
    "addr:postcode":"28213",
    "addr:street":"Back Creek Church Rd",
    "iso:country":"US",
    "sg:address":"3801 Back Creek Church Rd",
    "sg:city":"Charlotte",
    "sg:classifiers":[
        {
            "category":"Manufacturing",
            "subcategory":"Printing",
            "type":"Manufacturing & Wholesale Goods"
        }
    ],
    "sg:phone":"+1 704 921 1909",
    "sg:postcode":"28213",
    "sg:province":"NC",
    "sg:tags":[
        "commercial"
    ],
    "wof:name":"Flexographic Training Svc",
    "wof:placetype":"venue"
},
  "geometry": {"coordinates":[-80.700664,35.284932],"type":"Point"}
}