{
  "type": "Feature",
  "properties": {
    "addr:full":"9967 US Hwy 64 E Ramseur NC 27316",
    "addr:housenumber":"9967",
    "addr:postcode":"27316",
    "addr:street":"Us Hwy 64 E",
    "iso:country":"US",
    "sg:address":"9967 US Hwy 64 E",
    "sg:city":"Ramseur",
    "sg:classifiers":[
        {
            "category":"Building & Trades",
            "subcategory":"Construction",
            "type":"Services"
        }
    ],
    "sg:phone":"+1 336 824 8155",
    "sg:postcode":"27316",
    "sg:province":"NC",
    "sg:tags":[
        "general",
        "contractor"
    ],
    "wof:name":"Mapso Ic",
    "wof:placetype":"venue"
},
  "geometry": {"coordinates":[-79.569883,35.742345],"type":"Point"}
}