{
  "type": "Feature",
  "properties": {
    "addr:full":"914 N Elm St Greensboro NC 27401",
    "addr:housenumber":"914",
    "addr:postcode":"27401",
    "addr:street":"N Elm St",
    "iso:country":"US",
    "sg:address":"914 N Elm St",
    "sg:city":"Greensboro",
    "sg:classifiers":[
        {
            "category":"Insurance",
            "subcategory":"Insurance Agent",
            "type":"Services"
        }
    ],
    "sg:phone":"+1 336 379 1511",
    "sg:postcode":"27401",
    "sg:province":"NC",
    "wof:name":"Old Republic Insurance",
    "wof:placetype":"venue"
},
  "geometry": {"coordinates":[-79.789159,36.085891],"type":"Point"}
}