{
  "type": "Feature",
  "properties": {
    "iso:country":"US",
    "sg:address":"4 Austin Ct",
    "sg:city":"Greensboro",
    "sg:classifiers":[
        {
            "category":"Retail",
            "subcategory":"Laundry & Dry Cleaning",
            "type":"Services"
        }
    ],
    "sg:phone":"+1 336 275 7566",
    "sg:postcode":"27406",
    "sg:province":"NC",
    "wof:name":"Stitch & Fit",
    "wof:placetype":"venue"
},
  "geometry": {"coordinates":[-79.79628099999999,36.06158],"type":"Point"}
}