{
  "type": "Feature",
  "properties": {
    "addr:full":"1310 Rio Falls Dr Raleigh NC 27614",
    "addr:housenumber":"1310",
    "addr:postcode":"27614",
    "addr:street":"Rio Falls Dr",
    "iso:country":"US",
    "sg:address":"1310 Rio Falls Dr",
    "sg:city":"Raleigh",
    "sg:classifiers":[
        {
            "category":"Professional",
            "subcategory":"Computer Services",
            "type":"Services"
        }
    ],
    "sg:phone":"+1 919 846 6524",
    "sg:postcode":"27614",
    "sg:province":"NC",
    "sg:tags":[
        "website",
        "design"
    ],
    "wof:name":"JBI Co Inc",
    "wof:placetype":"venue"
},
  "geometry": {"coordinates":[-78.59359000000001,35.909092],"type":"Point"}
}