{
  "type": "Feature",
  "properties": {
    "addr:full":"101 Railroad St N Ahoskie NC 27910",
    "addr:housenumber":"101",
    "addr:postcode":"27910",
    "addr:street":"Railroad St N",
    "iso:country":"US",
    "sg:address":"101 Railroad St N",
    "sg:city":"Ahoskie",
    "sg:classifiers":[
        {
            "category":"Professional",
            "subcategory":"Lawyer & Legal Services",
            "type":"Services"
        }
    ],
    "sg:phone":"+1 252 332 3302",
    "sg:postcode":"27910",
    "sg:province":"NC",
    "sg:tags":[
        "plan"
    ],
    "wof:name":"Overton Larry S PA",
    "wof:placetype":"venue"
},
  "geometry": {"coordinates":[-76.982437,36.290661],"type":"Point"}
}