{
  "type": "Feature",
  "properties": {
    "addr:full":"1020 N Wesleyan Blvd Rocky Mount NC 27804",
    "addr:housenumber":"1020",
    "addr:postcode":"27804",
    "addr:street":"N Wesleyan Blvd",
    "iso:country":"US",
    "sg:address":"1020 N Wesleyan Blvd",
    "sg:city":"Rocky Mount",
    "sg:classifiers":[
        {
            "category":"Restaurant",
            "type":"Food & Drink"
        }
    ],
    "sg:phone":"+1 252 937 2933",
    "sg:postcode":"27804",
    "sg:province":"NC",
    "sg:tags":[
        "eating"
    ],
    "wof:name":"Canton Restaurant Take Out",
    "wof:placetype":"venue"
},
  "geometry": {"coordinates":[-77.811848,35.96976],"type":"Point"}
}