{
  "type": "Feature",
  "properties": {
    "iso:country":"US",
    "sg:address":"810 Fletcher Branch Rd",
    "sg:city":"Vilas",
    "sg:classifiers":[
        {
            "category":"Home & Garden",
            "subcategory":"Building Materials",
            "type":"Retail Goods"
        }
    ],
    "sg:phone":"+1 828 262 5139",
    "sg:postcode":"28679",
    "sg:province":"NC",
    "sg:tags":[
        "door"
    ],
    "wof:name":"Automatic Door Co",
    "wof:placetype":"venue"
},
  "geometry": {"coordinates":[-81.78634599999999,36.282958],"type":"Point"}
}