{
  "type": "Feature",
  "properties": {
    "iso:country":"US",
    "sg:address":"619 Ayersville Rd",
    "sg:city":"Madison",
    "sg:classifiers":[
        {
            "category":"Banks & Credit Unions",
            "subcategory":"Bank",
            "type":"Services"
        }
    ],
    "sg:phone":"+1 336 548 3790",
    "sg:postcode":"27025",
    "sg:province":"NC",
    "sg:tags":[
        "financial",
        "institution"
    ],
    "wof:name":"Community Bank",
    "wof:placetype":"venue"
},
  "geometry": {"coordinates":[-79.97011999999999,36.397386],"type":"Point"}
}