{
  "type": "Feature",
  "properties": {
    "addr:full":"208 Nelson Park Rd Maple Hill NC 28454",
    "addr:housenumber":"208",
    "addr:postcode":"28454",
    "addr:street":"Nelson Park Rd",
    "iso:country":"US",
    "sg:address":"208 Nelson Park Rd",
    "sg:city":"Maple Hill",
    "sg:classifiers":[
        {
            "category":"Building & Trades",
            "subcategory":"Construction",
            "type":"Services"
        }
    ],
    "sg:phone":"+1 910 346 9838",
    "sg:postcode":"28454",
    "sg:province":"NC",
    "sg:tags":[
        "general",
        "contractor"
    ],
    "wof:name":"Seashore Builders",
    "wof:placetype":"venue"
},
  "geometry": {"coordinates":[-77.58332900000001,34.703425],"type":"Point"}
}