{
  "type": "Feature",
  "properties": {
    "addr:full":"1230 N Main St Roxboro NC 27573",
    "addr:housenumber":"1230",
    "addr:postcode":"27573",
    "addr:street":"N Main St",
    "iso:country":"US",
    "sg:address":"1230 N Main St",
    "sg:city":"Roxboro",
    "sg:classifiers":[
        {
            "category":"Shopping",
            "subcategory":"Gifts & Souvenirs",
            "type":"Retail Goods"
        }
    ],
    "sg:phone":"+1 336 599 0813",
    "sg:postcode":"27573",
    "sg:province":"NC",
    "sg:tags":[
        "shop"
    ],
    "wof:name":"Brass Eagle Jewelry & Bridal",
    "wof:placetype":"venue"
},
  "geometry": {"coordinates":[-78.96923,36.418259],"type":"Point"}
}