{
  "type": "Feature",
  "properties": {
    "addr:full":"328 Gant Rd Eden NC 27288",
    "addr:housenumber":"328",
    "addr:postcode":"27288",
    "addr:street":"Gant Rd",
    "iso:country":"US",
    "sg:address":"328 Gant Rd",
    "sg:city":"Eden",
    "sg:classifiers":[
        {
            "category":"Manufacturing",
            "subcategory":"Textiles",
            "type":"Manufacturing & Wholesale Goods"
        }
    ],
    "sg:phone":"+1 336 635 0300",
    "sg:postcode":"27288",
    "sg:province":"NC",
    "sg:tags":[
        "spinning",
        "mill",
        "yarn"
    ],
    "wof:name":"Eden Yarns Inc",
    "wof:placetype":"venue"
},
  "geometry": {"coordinates":[-79.674277,36.53513],"type":"Point"}
}