{
  "type": "Feature",
  "properties": {
    "addr:full":"501 W Ehringhaus St Elizabeth City NC 27909",
    "addr:housenumber":"501",
    "addr:postcode":"27909",
    "addr:street":"W Ehringhaus St",
    "iso:country":"US",
    "sg:address":"501 W Ehringhaus St",
    "sg:city":"Elizabeth City",
    "sg:classifiers":[
        {
            "category":"Banks & Credit Unions",
            "subcategory":"Bank",
            "type":"Services"
        }
    ],
    "sg:phone":"+1 252 335 9080",
    "sg:postcode":"27909",
    "sg:province":"NC",
    "sg:tags":[
        "financing"
    ],
    "wof:name":"Time Financing Svc",
    "wof:placetype":"venue"
},
  "geometry": {"coordinates":[-76.22780299999999,36.296092],"type":"Point"}
}