{
  "type": "Feature",
  "properties": {
    "iso:country":"US",
    "sg:address":"5015 New Hope Rd",
    "sg:city":"Denton",
    "sg:classifiers":[
        {
            "category":"Organizations",
            "subcategory":"Religious Organization",
            "type":"Services"
        }
    ],
    "sg:phone":"+1   ",
    "sg:postcode":"27239",
    "sg:province":"NC",
    "wof:name":"Farmer United Methodist Church",
    "wof:placetype":"venue"
},
  "geometry": {"coordinates":[-80.02037,35.606554],"type":"Point"}
}