{
  "type": "Feature",
  "properties": {
    "iso:country":"US",
    "sg:address":"3030 N Main St",
    "sg:city":"Hope Mills",
    "sg:classifiers":[
        {
            "category":"Shopping",
            "subcategory":"Department Store",
            "type":"Retail Goods"
        }
    ],
    "sg:phone":"+1 910 429 7401",
    "sg:postcode":"28348",
    "sg:province":"NC",
    "sg:tags":[
        "grocery"
    ],
    "wof:name":"Wal-Mart",
    "wof:placetype":"venue"
},
  "geometry": {"coordinates":[-78.964641,34.984485],"type":"Point"}
}