{
  "type": "Feature",
  "properties": {
    "iso:country":"US",
    "sg:address":"1007 Holly Hedge St",
    "sg:city":"Indian Trail",
    "sg:classifiers":[
        {
            "category":"Professional",
            "subcategory":"Management & Consulting",
            "type":"Services"
        }
    ],
    "sg:phone":"+1   ",
    "sg:postcode":"28079",
    "sg:province":"NC",
    "sg:tags":[
        "se",
        "mail",
        "direct",
        "business",
        "advertising"
    ],
    "wof:name":"Tessera Sales and Consulting",
    "wof:placetype":"venue"
},
  "geometry": {"coordinates":[-80.667886,35.049935],"type":"Point"}
}