{
  "type": "Feature",
  "properties": {
    "iso:country":"US",
    "sg:address":"210 W Carver St",
    "sg:city":"Durham",
    "sg:classifiers":[
        {
            "category":"Professional",
            "subcategory":"Employment Agencies",
            "type":"Services"
        }
    ],
    "sg:phone":"+1   ",
    "sg:postcode":"27704",
    "sg:province":"NC",
    "sg:tags":[
        "help",
        "supply"
    ],
    "wof:name":"Legal Eagles Personal Staffing",
    "wof:placetype":"venue"
},
  "geometry": {"coordinates":[-78.902281,36.040217],"type":"Point"}
}