{
  "type": "Feature",
  "properties": {
    "iso:country":"US",
    "sg:address":"1409 W Ehringhaus St",
    "sg:city":"Elizabeth City",
    "sg:classifiers":[
        {
            "category":"Restaurant",
            "type":"Food & Drink"
        }
    ],
    "sg:phone":"+1 252 338 6888",
    "sg:postcode":"27909",
    "sg:province":"NC",
    "wof:name":"Volcano Sushi",
    "wof:placetype":"venue"
},
  "geometry": {"coordinates":[-76.24084499999999,36.294426],"type":"Point"}
}