{
  "type": "Feature",
  "properties": {
    "addr:full":"408 W Center St Mebane NC 27302",
    "addr:housenumber":"408",
    "addr:postcode":"27302",
    "addr:street":"W Center St",
    "iso:country":"US",
    "sg:address":"408 W Center St",
    "sg:city":"Mebane",
    "sg:classifiers":[
        {
            "category":"Retail",
            "subcategory":"Auto Rental",
            "type":"Services"
        }
    ],
    "sg:phone":"+1 919 563 7010",
    "sg:postcode":"27302",
    "sg:province":"NC",
    "sg:tags":[
        "renting",
        "automobile"
    ],
    "wof:name":"Enterprise Rent A Car",
    "wof:placetype":"venue"
},
  "geometry": {"coordinates":[-79.27469499999999,36.097856],"type":"Point"}
}