{
  "type": "Feature",
  "properties": {
    "addr:full":"3018 Dixon Rd Durham NC 27707",
    "addr:housenumber":"3018",
    "addr:postcode":"27707",
    "addr:street":"Dixon Rd",
    "iso:country":"US",
    "sg:address":"3018 Dixon Rd",
    "sg:city":"Durham",
    "sg:classifiers":[
        {
            "category":"Building & Trades",
            "subcategory":"Construction",
            "type":"Services"
        }
    ],
    "sg:phone":"+1 919 493 9696",
    "sg:postcode":"27707",
    "sg:province":"NC",
    "sg:tags":[
        "hanging",
        "contractor"
    ],
    "wof:name":"Hansell Painting Co",
    "wof:placetype":"venue"
},
  "geometry": {"coordinates":[-78.94000800000001,35.967352],"type":"Point"}
}