{
  "type": "Feature",
  "properties": {
    "iso:country":"US",
    "sg:address":"314 Braken Pl",
    "sg:city":"Jacksonville",
    "sg:classifiers":[
        {
            "category":"Personal",
            "subcategory":"Beauty Salon",
            "type":"Services"
        }
    ],
    "sg:phone":"+1   ",
    "sg:postcode":"28540",
    "sg:province":"NC",
    "sg:tags":[
        "shop"
    ],
    "wof:name":"Skipper Prints Inc",
    "wof:placetype":"venue"
},
  "geometry": {"coordinates":[-77.41780199999999,34.776118],"type":"Point"}
}