{
  "type": "Feature",
  "properties": {
    "iso:country":"US",
    "sg:address":"401 N West St",
    "sg:city":"Raleigh",
    "sg:classifiers":[
        {
            "category":"Health Services",
            "subcategory":"Health Practitioner",
            "type":"Services"
        },
        {
            "category":"Health Services",
            "subcategory":"Chiropractor",
            "type":"Services"
        }
    ],
    "sg:phone":"+1 888 681 9951",
    "sg:postcode":"27603",
    "sg:province":"NC",
    "sg:tags":[
        "homeopathic",
        "chiropractic"
    ],
    "sg:website":"http://local.ingenio.com/Listings/Details.aspx?NUM=a%3a9246186%3a13%3a4859924%3a14%3a0%3a7",
    "wof:name":"Corrective Chiropractic",
    "wof:placetype":"venue"
},
  "geometry": {"coordinates":[-78.64569899999999,35.78487],"type":"Point"}
}