{
  "type": "Feature",
  "properties": {
    "addr:full":"9505 Parkton Rd Charlotte NC 28215",
    "addr:housenumber":"9505",
    "addr:postcode":"28215",
    "addr:street":"Parkton Rd",
    "iso:country":"US",
    "sg:address":"9505 Parkton Rd",
    "sg:city":"Charlotte",
    "sg:classifiers":[
        {
            "category":"Organizations",
            "subcategory":"Religious Organization",
            "type":"Services"
        }
    ],
    "sg:phone":"+1 704 535 8106",
    "sg:postcode":"28215",
    "sg:province":"NC",
    "sg:tags":[
        "church"
    ],
    "wof:name":"Logan Chapel Christian Church",
    "wof:placetype":"venue"
},
  "geometry": {"coordinates":[-80.685056,35.212821],"type":"Point"}
}