{
  "type": "Feature",
  "properties": {
    "addr:full":"7109 Cape Harbor Dr Wilmington NC 28411",
    "addr:housenumber":"7109",
    "addr:postcode":"28411",
    "addr:street":"Cape Harbor Dr",
    "iso:country":"US",
    "sg:address":"7109 Cape Harbor Dr",
    "sg:city":"Wilmington",
    "sg:classifiers":[
        {
            "category":"Retail",
            "subcategory":"Repair Shop",
            "type":"Services"
        }
    ],
    "sg:phone":"+1 910 792 0980",
    "sg:postcode":"28411",
    "sg:province":"NC",
    "sg:tags":[
        "equipment",
        "golf",
        "refinishing"
    ],
    "wof:name":"Eagles & Birdies Golf Shop",
    "wof:placetype":"venue"
},
  "geometry": {"coordinates":[-77.831896,34.265005],"type":"Point"}
}