{
  "type": "Feature",
  "properties": {
    "addr:full":"1934 US Hwy 301 S Dunn NC 28334",
    "addr:housenumber":"1934",
    "addr:postcode":"28334",
    "addr:street":"Us Hwy 301 S",
    "iso:country":"US",
    "sg:address":"1934 US Hwy 301 S",
    "sg:city":"Dunn",
    "sg:classifiers":[
        {
            "category":"Organizations",
            "subcategory":"Religious Organization",
            "type":"Services"
        }
    ],
    "sg:phone":"+1   ",
    "sg:postcode":"28334",
    "sg:province":"NC",
    "wof:name":"Harvest Time Church Of God",
    "wof:placetype":"venue"
},
  "geometry": {"coordinates":[-78.62652799999999,35.282174],"type":"Point"}
}