{
  "type": "Feature",
  "properties": {
    "iso:country":"US",
    "sg:address":"1715 Athens Ave",
    "sg:city":"Durham",
    "sg:classifiers":[
        {
            "category":"Organizations",
            "subcategory":"Religious Organization",
            "type":"Services"
        }
    ],
    "sg:phone":"+1 919 688 5066",
    "sg:postcode":"27707",
    "sg:province":"NC",
    "sg:tags":[
        "church"
    ],
    "wof:name":"Mount Calvary United Church",
    "wof:placetype":"venue"
},
  "geometry": {"coordinates":[-78.889225,35.966113],"type":"Point"}
}