{
  "type": "Feature",
  "properties": {
    "iso:country":"US",
    "sg:address":"112 Hawkins Rd",
    "sg:city":"Marion",
    "sg:classifiers":[
        {
            "category":"Retail",
            "subcategory":"Auto Repair",
            "type":"Services"
        }
    ],
    "sg:phone":"+1 828 668 9352",
    "sg:postcode":"28752",
    "sg:province":"NC",
    "sg:tags":[
        "body",
        "automobile",
        "painting"
    ],
    "wof:name":"Mc Dowell Auto Body Repair",
    "wof:placetype":"venue"
},
  "geometry": {"coordinates":[-82.053614,35.699694],"type":"Point"}
}