{
  "type": "Feature",
  "properties": {
    "addr:full":"1814 Carrington Dr Raleigh NC 27615",
    "addr:housenumber":"1814",
    "addr:postcode":"27615",
    "addr:street":"Carrington Dr",
    "iso:country":"US",
    "sg:address":"1814 Carrington Dr",
    "sg:city":"Raleigh",
    "sg:classifiers":[
        {
            "category":"Professional",
            "subcategory":"Management & Consulting",
            "type":"Services"
        }
    ],
    "sg:phone":"+1   ",
    "sg:postcode":"27615",
    "sg:province":"NC",
    "sg:tags":[
        "business"
    ],
    "wof:name":"Tim McKay Consulting",
    "wof:placetype":"venue"
},
  "geometry": {"coordinates":[-78.60865200000001,35.896148],"type":"Point"}
}