{
  "type": "Feature",
  "properties": {
    "addr:full":"10120 Albemarle Rd Charlotte NC 28227",
    "addr:housenumber":"10120",
    "addr:postcode":"28227",
    "addr:street":"Albemarle Rd",
    "iso:country":"US",
    "sg:address":"10120 Albemarle Rd",
    "sg:city":"Charlotte",
    "sg:classifiers":[
        {
            "category":"Autos & Motor Vehicles",
            "subcategory":"Auto Supplies",
            "type":"Retail Goods"
        },
        {
            "category":"Wholesale",
            "subcategory":"Auto Parts",
            "type":"Manufacturing & Wholesale Goods"
        }
    ],
    "sg:phone":"+1 704 568 6272",
    "sg:postcode":"28227",
    "sg:province":"NC",
    "sg:tags":[
        "automobile"
    ],
    "wof:name":"NAPA Auto Parts",
    "wof:placetype":"venue"
},
  "geometry": {"coordinates":[-80.67171399999999,35.208565],"type":"Point"}
}