{
  "type": "Feature",
  "properties": {
    "iso:country":"US",
    "sg:address":"203 Government Cir",
    "sg:city":"Greenville",
    "sg:classifiers":[
        {
            "category":"Government",
            "subcategory":"Office",
            "type":"Public Place"
        }
    ],
    "sg:phone":"+1 252 413 1600",
    "sg:postcode":"27834",
    "sg:province":"NC",
    "sg:tags":[
        "legislative",
        "body"
    ],
    "wof:name":"Dept Mental Health",
    "wof:placetype":"venue"
},
  "geometry": {"coordinates":[-77.361964,35.63719],"type":"Point"}
}