{
  "type": "Feature",
  "properties": {
    "addr:full":"321 N Eastern Blvd Fayetteville NC 28301",
    "addr:housenumber":"321",
    "addr:postcode":"28301",
    "addr:street":"N Eastern Blvd",
    "iso:country":"US",
    "sg:address":"321 N Eastern Blvd",
    "sg:city":"Fayetteville",
    "sg:classifiers":[
        {
            "category":"Travel",
            "subcategory":"Hotels & Motels",
            "type":"Entertainment"
        }
    ],
    "sg:phone":"+1   ",
    "sg:postcode":"28301",
    "sg:province":"NC",
    "sg:tags":[
        "operation"
    ],
    "wof:name":"Travel Inn",
    "wof:placetype":"venue"
},
  "geometry": {"coordinates":[-78.864577,35.051718],"type":"Point"}
}