{
  "type": "Feature",
  "properties": {
    "addr:full":"816 W Mauney Ave Gastonia NC 28052",
    "addr:housenumber":"816",
    "addr:postcode":"28052",
    "addr:street":"W Mauney Ave",
    "iso:country":"US",
    "sg:address":"816 W Mauney Ave",
    "sg:city":"Gastonia",
    "sg:classifiers":[
        {
            "category":"Government",
            "subcategory":"Office",
            "type":"Public Place"
        }
    ],
    "sg:phone":"+1 704 866 3206",
    "sg:postcode":"28052",
    "sg:province":"NC",
    "wof:name":"Gaston County Access-Central",
    "wof:placetype":"venue"
},
  "geometry": {"coordinates":[-81.195825,35.268932],"type":"Point"}
}