{
  "type": "Feature",
  "properties": {
    "iso:country":"US",
    "sg:address":"3120 Lariat Ridge Dr",
    "sg:city":"Wake Forest",
    "sg:classifiers":[
        {
            "category":"Building & Trades",
            "subcategory":"Landscaping Services",
            "type":"Services"
        }
    ],
    "sg:phone":"+1 919 562 0563",
    "sg:postcode":"27587",
    "sg:province":"NC",
    "wof:name":"Pampered Lawn",
    "wof:placetype":"venue"
},
  "geometry": {"coordinates":[-78.526329,35.914467],"type":"Point"}
}