{
  "type": "Feature",
  "properties": {
    "addr:full":"1281 Georgia Rd Franklin NC 28734",
    "addr:housenumber":"1281",
    "addr:postcode":"nc 28734",
    "addr:street":"Georgia Rd",
    "iso:country":"US",
    "sg:address":"1281 Georgia Rd",
    "sg:city":"Franklin",
    "sg:classifiers":[
        {
            "category":"Building & Trades",
            "subcategory":"Construction",
            "type":"Services"
        },
        {
            "category":"Building & Trades",
            "subcategory":"Electrical",
            "type":"Services"
        },
        {
            "category":"Industrial Area",
            "type":"Public Place"
        }
    ],
    "sg:phone":"+1 866 427 1071",
    "sg:postcode":"28734",
    "sg:province":"NC",
    "sg:tags":[
        "systems-repairing",
        "electrician",
        "electric",
        "contractors-commercial",
        "specialty",
        "equipment",
        "heating",
        "air conditioning",
        "contractor",
        "equipment-repairing",
        "system"
    ],
    "wof:name":"All County Services Heating & Air",
    "wof:placetype":"venue"
},
  "geometry": {"coordinates":[-83.39183,35.154918],"type":"Point"}
}