{
  "type": "Feature",
  "properties": {
    "iso:country":"US",
    "sg:address":"11841 Barnes Bridge Rd",
    "sg:city":"Laurinburg",
    "sg:classifiers":[
        {
            "category":"Social Services",
            "subcategory":"Child Care",
            "type":"Services"
        }
    ],
    "sg:phone":"+1 910 276 9415",
    "sg:postcode":"28352",
    "sg:province":"NC",
    "wof:name":"Childrens World Preschl/Day Cr",
    "wof:placetype":"venue"
},
  "geometry": {"coordinates":[-79.50957099999999,34.705632],"type":"Point"}
}