{
  "type": "Feature",
  "properties": {
    "addr:full":"211 Cedarwood Ln Dallas NC 28034",
    "addr:housenumber":"211",
    "addr:postcode":"28034",
    "addr:street":"Cedarwood Ln",
    "iso:country":"US",
    "sg:address":"211 Cedarwood Ln",
    "sg:city":"Dallas",
    "sg:classifiers":[
        {
            "category":"Building & Trades",
            "subcategory":"Construction",
            "type":"Services"
        }
    ],
    "sg:phone":"+1 704 860 1062",
    "sg:postcode":"28034",
    "sg:province":"NC",
    "sg:tags":[
        "painter"
    ],
    "wof:name":"Weather's Custom Interior Pnt",
    "wof:placetype":"venue"
},
  "geometry": {"coordinates":[-81.137314,35.321091],"type":"Point"}
}