{
  "type": "Feature",
  "properties": {
    "iso:country":"US",
    "sg:address":"9300 Arrowpoint Blvd",
    "sg:city":"Charlotte",
    "sg:classifiers":[
        {
            "category":"Building & Trades",
            "subcategory":"Equipment Rental",
            "type":"Services"
        }
    ],
    "sg:phone":"+1 704 571 5073",
    "sg:postcode":"28273",
    "sg:province":"NC",
    "sg:tags":[
        "yard",
        "leasing",
        "store"
    ],
    "wof:name":"Direct Chassislink",
    "wof:placetype":"venue"
},
  "geometry": {"coordinates":[-80.91741399999999,35.137779],"type":"Point"}
}