{
  "type": "Feature",
  "properties": {
    "addr:full":"3737 SE School Rd Greensboro NC 27406",
    "addr:housenumber":"3737",
    "addr:postcode":"27406",
    "addr:street":"Se School Rd",
    "iso:country":"US",
    "sg:address":"3737 SE School Rd",
    "sg:city":"Greensboro",
    "sg:classifiers":[
        {
            "category":"Wholesale",
            "subcategory":"Farm Supplies",
            "type":"Manufacturing & Wholesale Goods"
        }
    ],
    "sg:phone":"+1 336 674 0037",
    "sg:postcode":"27406",
    "sg:province":"NC",
    "sg:tags":[
        "livestock"
    ],
    "wof:name":"Dunlap Livestock Barn",
    "wof:placetype":"venue"
},
  "geometry": {"coordinates":[-79.69385,36.000177],"type":"Point"}
}