{
  "type": "Feature",
  "properties": {
    "iso:country":"US",
    "sg:address":"436 Peace St",
    "sg:city":"Kernersville",
    "sg:classifiers":[
        {
            "category":"Freight",
            "type":"Transportation"
        }
    ],
    "sg:phone":"+1 336 996 2722",
    "sg:postcode":"27262",
    "sg:province":"NC",
    "wof:name":"UTI United States Inc",
    "wof:placetype":"venue"
},
  "geometry": {"coordinates":[-80.03915499999999,35.9377],"type":"Point"}
}