{
  "type": "Feature",
  "properties": {
    "iso:country":"US",
    "sg:address":"3716 Performance Rd",
    "sg:city":"Charlotte",
    "sg:classifiers":[
        {
            "category":"Building & Trades",
            "subcategory":"Construction",
            "type":"Services"
        }
    ],
    "sg:phone":"+1 704 392 1114",
    "sg:postcode":"28214",
    "sg:province":"NC",
    "sg:tags":[
        "piping",
        "contractor"
    ],
    "wof:name":"Carolina Piping Systems Inc",
    "wof:placetype":"venue"
},
  "geometry": {"coordinates":[-80.987112,35.257727],"type":"Point"}
}