{
  "type": "Feature",
  "properties": {
    "iso:country":"US",
    "sg:address":"7526 Ruben Linker Rd NW",
    "sg:city":"Concord",
    "sg:classifiers":[
        {
            "category":"Professional",
            "type":"Services"
        }
    ],
    "sg:phone":"+1 704 721 5940",
    "sg:postcode":"28027",
    "sg:province":"NC",
    "wof:name":"Kings Keep/The",
    "wof:placetype":"venue"
},
  "geometry": {"coordinates":[-80.70314999999999,35.382079],"type":"Point"}
}