{
  "type": "Feature",
  "properties": {
    "addr:full":"1700 Richardson Dr Reidsville NC 27320",
    "addr:housenumber":"1700",
    "addr:postcode":"27320",
    "addr:street":"Richardson Dr",
    "iso:country":"US",
    "sg:address":"1700 Richardson Dr",
    "sg:city":"Reidsville",
    "sg:classifiers":[
        {
            "category":"Professional",
            "subcategory":"Business Services",
            "type":"Services"
        }
    ],
    "sg:phone":"+1   ",
    "sg:postcode":"27320",
    "sg:province":"NC",
    "sg:tags":[
        "event",
        "special",
        "hosting"
    ],
    "wof:name":"Belmont",
    "wof:placetype":"venue"
},
  "geometry": {"coordinates":[-79.677645,36.342966],"type":"Point"}
}