{
  "type": "Feature",
  "properties": {
    "iso:country":"US",
    "sg:address":"334 Bridge Rd",
    "sg:city":"Ellenboro",
    "sg:classifiers":[
        {
            "category":"Retail",
            "subcategory":"Auto Repair",
            "type":"Services"
        }
    ],
    "sg:phone":"+1   ",
    "sg:postcode":"28040",
    "sg:province":"NC",
    "sg:tags":[
        "body"
    ],
    "wof:name":"Rollins Body Shop",
    "wof:placetype":"venue"
},
  "geometry": {"coordinates":[-81.801435,35.350003],"type":"Point"}
}