{
  "type": "Feature",
  "properties": {
    "iso:country":"US",
    "sg:address":"8009 Windsor Ridge Dr",
    "sg:city":"Raleigh",
    "sg:classifiers":[
        {
            "category":"Retail",
            "subcategory":"Animal Services",
            "type":"Services"
        }
    ],
    "sg:phone":"+1 919 414 7671",
    "sg:postcode":"27615",
    "sg:province":"NC",
    "sg:tags":[
        "pet"
    ],
    "wof:name":"4 Your Pets Only Pet Sitting",
    "wof:placetype":"venue"
},
  "geometry": {"coordinates":[-78.66186,35.891526],"type":"Point"}
}