{
  "type": "Feature",
  "properties": {
    "addr:full":"231 Caratoke Hwy Moyock NC 27958",
    "addr:housenumber":"231",
    "addr:postcode":"27958",
    "addr:street":"Caratoke Hwy",
    "iso:country":"US",
    "sg:address":"231 Caratoke Hwy",
    "sg:city":"Moyock",
    "sg:classifiers":[
        {
            "category":"Building & Trades",
            "subcategory":"Construction",
            "type":"Services"
        }
    ],
    "sg:phone":"+1 252 435 2700",
    "sg:postcode":"27958",
    "sg:province":"NC",
    "sg:tags":[
        "contractor"
    ],
    "wof:name":"Shade Tree Custom Homes LLC",
    "wof:placetype":"venue"
},
  "geometry": {"coordinates":[-76.19277099999999,36.550588],"type":"Point"}
}