{
  "type": "Feature",
  "properties": {
    "addr:full":"613 Cedar St Beaufort NC 28516",
    "addr:housenumber":"613",
    "addr:postcode":"28516",
    "addr:street":"Cedar St",
    "iso:country":"US",
    "sg:address":"613 Cedar St",
    "sg:city":"Beaufort",
    "sg:classifiers":[
        {
            "category":"Government",
            "subcategory":"Office",
            "type":"Public Place"
        }
    ],
    "sg:phone":"+1 252 728 8440",
    "sg:postcode":"28516",
    "sg:province":"NC",
    "wof:name":"Carteret County Veterans Ofc",
    "wof:placetype":"venue"
},
  "geometry": {"coordinates":[-76.660566,34.719527],"type":"Point"}
}