{
  "type": "Feature",
  "properties": {
    "iso:country":"US",
    "sg:address":"913 Buffalo Shoals Rd",
    "sg:city":"Statesville",
    "sg:classifiers":[
        {
            "category":"Home & Garden",
            "subcategory":"Garden Supply",
            "type":"Retail Goods"
        }
    ],
    "sg:phone":"+1 704 881 0440",
    "sg:postcode":"28677",
    "sg:province":"NC",
    "sg:tags":[
        "mulch"
    ],
    "wof:name":"L T Lingle Landscape Products",
    "wof:placetype":"venue"
},
  "geometry": {"coordinates":[-80.919499,35.763495],"type":"Point"}
}