{
  "type": "Feature",
  "properties": {
    "iso:country":"US",
    "sg:address":"1872 Quail Ridge Rd",
    "sg:city":"Greenville",
    "sg:classifiers":[
        {
            "category":"Social Services",
            "type":"Services"
        }
    ],
    "sg:phone":"+1   ",
    "sg:postcode":"27858",
    "sg:province":"NC",
    "wof:name":"Everett Lou Rn Edd",
    "wof:placetype":"venue"
},
  "geometry": {"coordinates":[-77.343282,35.582205],"type":"Point"}
}