{
  "type": "Feature",
  "properties": {
    "addr:full":"5416 Oleander Dr Wilmington NC 28403",
    "addr:housenumber":"5416",
    "addr:postcode":"28403",
    "addr:street":"Oleander Dr",
    "iso:country":"US",
    "sg:address":"5416 Oleander Dr",
    "sg:city":"Wilmington",
    "sg:classifiers":[
        {
            "category":"Professional",
            "subcategory":"Lawyer & Legal Services",
            "type":"Services"
        }
    ],
    "sg:phone":"+1 910 352 2445",
    "sg:postcode":"28403",
    "sg:province":"NC",
    "sg:tags":[
        "planning",
        "estate"
    ],
    "wof:name":"Axa Advisors",
    "wof:placetype":"venue"
},
  "geometry": {"coordinates":[-77.858885,34.208231],"type":"Point"}
}