{
  "type": "Feature",
  "properties": {
    "iso:country":"US",
    "sg:address":"421 Merrimon Rd",
    "sg:city":"Beaufort",
    "sg:classifiers":[
        {
            "category":"Wholesale",
            "subcategory":"Seafood",
            "type":"Manufacturing & Wholesale Goods"
        }
    ],
    "sg:phone":"+1 252 728 6230",
    "sg:postcode":"28516",
    "sg:province":"NC",
    "wof:name":"Ocean Technology",
    "wof:placetype":"venue"
},
  "geometry": {"coordinates":[-76.63058700000001,34.791246],"type":"Point"}
}