{
  "type": "Feature",
  "properties": {
    "iso:country":"US",
    "sg:address":"3309 Fort Bragg Rd",
    "sg:city":"Fayetteville",
    "sg:classifiers":[
        {
            "category":"Wholesale",
            "subcategory":"Plants",
            "type":"Manufacturing & Wholesale Goods"
        }
    ],
    "sg:phone":"+1 910 864 9223",
    "sg:postcode":"28303",
    "sg:province":"NC",
    "sg:tags":[
        "florist",
        "supply"
    ],
    "wof:name":"Lee's Floral & Home Decor",
    "wof:placetype":"venue"
},
  "geometry": {"coordinates":[-78.932076,35.07551],"type":"Point"}
}