{
  "type": "Feature",
  "properties": {
    "iso:country":"US",
    "sg:address":"309 E Loch Haven Dr",
    "sg:city":"Fayetteville",
    "sg:classifiers":[
        {
            "category":"Real Estate",
            "subcategory":"Real Estate Agent",
            "type":"Services"
        }
    ],
    "sg:phone":"+1 910 488 2480",
    "sg:postcode":"28314",
    "sg:province":"NC",
    "wof:name":"Verna Bradford Real State",
    "wof:placetype":"venue"
},
  "geometry": {"coordinates":[-78.98164,35.067298],"type":"Point"}
}