{
  "type": "Feature",
  "properties": {
    "addr:full":"3507 S Holden Rd Greensboro NC 27407",
    "addr:housenumber":"3507",
    "addr:postcode":"27407",
    "addr:street":"S Holden Rd",
    "iso:country":"US",
    "sg:address":"3507 S Holden Rd",
    "sg:city":"Greensboro",
    "sg:classifiers":[
        {
            "category":"Restaurant",
            "type":"Food & Drink"
        }
    ],
    "sg:phone":"+1 336 292 5183",
    "sg:postcode":"27407",
    "sg:province":"NC",
    "sg:tags":[
        "caterer"
    ],
    "wof:name":"Real Catering",
    "wof:placetype":"venue"
},
  "geometry": {"coordinates":[-79.844126,36.017347],"type":"Point"}
}