{
  "type": "Feature",
  "properties": {
    "iso:country":"US",
    "sg:address":"116 Riverside Ct",
    "sg:city":"Morganton",
    "sg:classifiers":[
        {
            "category":"Professional",
            "type":"Services"
        }
    ],
    "sg:phone":"+1 828 433 8844",
    "sg:postcode":"28655",
    "sg:province":"NC",
    "wof:name":"W D Sharp",
    "wof:placetype":"venue"
},
  "geometry": {"coordinates":[-81.70515,35.74192],"type":"Point"}
}