{
  "type": "Feature",
  "properties": {
    "addr:full":"3 Crooked Creek Dr Asheville NC 28804",
    "addr:housenumber":"3",
    "addr:postcode":"28804",
    "addr:street":"Crooked Creek Dr",
    "iso:country":"US",
    "sg:address":"3 Crooked Creek Dr",
    "sg:city":"Asheville",
    "sg:classifiers":[
        {
            "category":"Wholesale",
            "subcategory":"Machinery & Supplies",
            "type":"Manufacturing & Wholesale Goods"
        }
    ],
    "sg:phone":"+1 828 251 9959",
    "sg:postcode":"28804",
    "sg:province":"NC",
    "sg:tags":[
        "tape"
    ],
    "wof:name":"PHOENIX Paper & Packaging Inc",
    "wof:placetype":"venue"
},
  "geometry": {"coordinates":[-82.617132,35.646793],"type":"Point"}
}