{
  "type": "Feature",
  "properties": {
    "iso:country":"US",
    "sg:address":"11385 US Hwy 70 W",
    "sg:city":"Clayton",
    "sg:classifiers":[
        {
            "category":"Recreation",
            "type":"Entertainment"
        }
    ],
    "sg:phone":"+1 919 359 0747",
    "sg:postcode":"27520",
    "sg:province":"NC",
    "sg:tags":[
        "martial",
        "arts",
        "instruction"
    ],
    "wof:name":"Parker's Self Defense",
    "wof:placetype":"venue"
},
  "geometry": {"coordinates":[-78.47146499999999,35.651688],"type":"Point"}
}