{
  "type": "Feature",
  "properties": {
    "addr:full":"1403 Harpoon Ct Kill Devil Hills NC 27948",
    "addr:housenumber":"1403",
    "addr:postcode":"27948",
    "addr:street":"Harpoon Ct",
    "iso:country":"US",
    "sg:address":"1403 Harpoon Ct",
    "sg:city":"Kill Devil Hills",
    "sg:classifiers":[
        {
            "category":"Building & Trades",
            "subcategory":"Construction",
            "type":"Services"
        }
    ],
    "sg:phone":"+1 252 441 6017",
    "sg:postcode":"27948",
    "sg:province":"NC",
    "sg:tags":[
        "contractor"
    ],
    "wof:name":"Beach Drywall",
    "wof:placetype":"venue"
},
  "geometry": {"coordinates":[-75.67764,36.021333],"type":"Point"}
}