{
  "type": "Feature",
  "properties": {
    "iso:country":"US",
    "sg:address":"532 8th St NE",
    "sg:city":"Hickory",
    "sg:classifiers":[
        {
            "category":"Home & Garden",
            "subcategory":"Furniture",
            "type":"Retail Goods"
        }
    ],
    "sg:phone":"+1 828 345 6343",
    "sg:postcode":"28601",
    "sg:province":"NC",
    "wof:name":"North Carolina Furniture",
    "wof:placetype":"venue"
},
  "geometry": {"coordinates":[-81.32556,35.737029],"type":"Point"}
}