{
  "type": "Feature",
  "properties": {
    "iso:country":"US",
    "sg:address":"4408 Falls of Neuse Rd",
    "sg:city":"Raleigh",
    "sg:classifiers":[
        {
            "category":"Restaurant",
            "type":"Food & Drink"
        }
    ],
    "sg:phone":"+1 919 878 5110",
    "sg:postcode":"27609",
    "sg:province":"NC",
    "wof:name":"Crazy Fire Mongolian Grill",
    "wof:placetype":"venue"
},
  "geometry": {"coordinates":[-78.611577,35.840388],"type":"Point"}
}