{
  "type": "Feature",
  "properties": {
    "addr:full":"819 Cotton St Monroe NC 28112",
    "addr:housenumber":"819",
    "addr:postcode":"28112",
    "addr:street":"Cotton St",
    "iso:country":"US",
    "sg:address":"819 Cotton St",
    "sg:city":"Monroe",
    "sg:classifiers":[
        {
            "category":"Social Services",
            "subcategory":"Adult Care",
            "type":"Services"
        },
        {
            "category":"Real Estate",
            "subcategory":"Real Estate Agent",
            "type":"Services"
        }
    ],
    "sg:phone":"+1 704 283 5136",
    "sg:postcode":"28112",
    "sg:province":"NC",
    "sg:tags":[
        "residential",
        "home"
    ],
    "wof:name":"Cotton Street Commons",
    "wof:placetype":"venue"
},
  "geometry": {"coordinates":[-80.537494,34.974837],"type":"Point"}
}