{
  "type": "Feature",
  "properties": {
    "iso:country":"US",
    "sg:address":"4008 Huntscroft Ln",
    "sg:city":"Winston Salem",
    "sg:classifiers":[
        {
            "category":"Education",
            "subcategory":"Special Training",
            "type":"Public Place"
        }
    ],
    "sg:phone":"+1 336 768 4660",
    "sg:postcode":"27106",
    "sg:province":"NC",
    "sg:tags":[
        "school",
        "instruction",
        "art"
    ],
    "wof:name":"Abrakadoodle",
    "wof:placetype":"venue"
},
  "geometry": {"coordinates":[-80.32626399999999,36.115024],"type":"Point"}
}