{
  "type": "Feature",
  "properties": {
    "addr:full":"803 E Main St Havelock NC 28532",
    "addr:housenumber":"803",
    "addr:postcode":"28532",
    "addr:street":"E Main St",
    "iso:country":"US",
    "sg:address":"803 E Main St",
    "sg:city":"Havelock",
    "sg:classifiers":[
        {
            "category":"Education",
            "subcategory":"Vocational School",
            "type":"Public Place"
        }
    ],
    "sg:phone":"+1 252 447 9609",
    "sg:postcode":"28532",
    "sg:province":"NC",
    "wof:name":"Allied Health Institute",
    "wof:placetype":"venue"
},
  "geometry": {"coordinates":[-76.899305,34.866566],"type":"Point"}
}