{
  "type": "Feature",
  "properties": {
    "iso:country":"US",
    "sg:address":"717 N Anderson Blvd",
    "sg:city":"Topsail Beach",
    "sg:classifiers":[
        {
            "category":"Real Estate",
            "subcategory":"Real Estate Agent",
            "type":"Services"
        }
    ],
    "sg:phone":"+1 910 328 3353",
    "sg:postcode":"28445",
    "sg:province":"NC",
    "wof:name":"Sun Spots Realty",
    "wof:placetype":"venue"
},
  "geometry": {"coordinates":[-77.603161,34.385998],"type":"Point"}
}