{
  "type": "Feature",
  "properties": {
    "iso:country":"US",
    "sg:address":"738 NW Blvd",
    "sg:city":"Clinton",
    "sg:classifiers":[
        {
            "category":"Food & Beverages",
            "subcategory":"Groceries & Convenience Stores",
            "type":"Retail Goods"
        }
    ],
    "sg:phone":"+1 910 592 3288",
    "sg:postcode":"28328",
    "sg:province":"NC",
    "wof:name":"Bestway Amoco",
    "wof:placetype":"venue"
},
  "geometry": {"coordinates":[-78.343571,35.013353],"type":"Point"}
}