{
  "type": "Feature",
  "properties": {
    "addr:full":"214 Ramsey Ford Rd Nakina NC 28455",
    "addr:housenumber":"214",
    "addr:postcode":"28455",
    "addr:street":"Ramsey Ford Rd",
    "iso:country":"US",
    "sg:address":"214 Ramsey Ford Rd",
    "sg:city":"Nakina",
    "sg:classifiers":[
        {
            "category":"Government",
            "subcategory":"Fire Station",
            "type":"Public Place"
        }
    ],
    "sg:phone":"+1 910 642 2410",
    "sg:postcode":"28455",
    "sg:province":"NC",
    "sg:tags":[
        "department"
    ],
    "wof:name":"Nakina Fire & Rescue",
    "wof:placetype":"venue"
},
  "geometry": {"coordinates":[-78.654686,34.102862],"type":"Point"}
}