{
  "type": "Feature",
  "properties": {
    "addr:full":"248 Sharon Ave NW Lenoir NC 28645",
    "addr:housenumber":"248",
    "addr:postcode":"28645",
    "addr:street":"Sharon Ave Nw",
    "iso:country":"US",
    "sg:address":"248 Sharon Ave NW",
    "sg:city":"Lenoir",
    "sg:classifiers":[
        {
            "category":"Social Services",
            "subcategory":"Child Care",
            "type":"Services"
        }
    ],
    "sg:phone":"+1 828 758 5860",
    "sg:postcode":"28645",
    "sg:province":"NC",
    "sg:tags":[
        "day"
    ],
    "wof:name":"A New Begining Chld Lrng Ctr",
    "wof:placetype":"venue"
},
  "geometry": {"coordinates":[-81.526394,35.919003],"type":"Point"}
}