{
  "type": "Feature",
  "properties": {
    "addr:full":"130 W Pine St Norwood NC 28128",
    "addr:housenumber":"130",
    "addr:postcode":"28128",
    "addr:street":"W Pine St",
    "iso:country":"US",
    "sg:address":"130 W Pine St",
    "sg:city":"Norwood",
    "sg:classifiers":[
        {
            "category":"Organizations",
            "subcategory":"Religious Organization",
            "type":"Services"
        }
    ],
    "sg:phone":"+1   ",
    "sg:postcode":"28128",
    "sg:province":"NC",
    "wof:name":"Norwood Church God Parsonage",
    "wof:placetype":"venue"
},
  "geometry": {"coordinates":[-80.124534,35.22692],"type":"Point"}
}