{
  "type": "Feature",
  "properties": {
    "addr:full":"901 S Kings Dr Charlotte NC 28204",
    "addr:housenumber":"901",
    "addr:postcode":"28204",
    "addr:street":"S Kings Dr",
    "iso:country":"US",
    "sg:address":"901 S Kings Dr",
    "sg:city":"Charlotte",
    "sg:classifiers":[
        {
            "category":"Personal",
            "subcategory":"Beauty Salon",
            "type":"Services"
        }
    ],
    "sg:phone":"+1 704 358 8291",
    "sg:postcode":"28204",
    "sg:province":"NC",
    "sg:tags":[
        "manicuring"
    ],
    "wof:name":"Myers Park Nails",
    "wof:placetype":"venue"
},
  "geometry": {"coordinates":[-80.83613,35.206255],"type":"Point"}
}