{
  "type": "Feature",
  "properties": {
    "addr:full":"106 Church St Pineville NC 28134",
    "addr:housenumber":"106",
    "addr:postcode":"28134",
    "addr:street":"Church St",
    "iso:country":"US",
    "sg:address":"106 Church St",
    "sg:city":"Pineville",
    "sg:classifiers":[
        {
            "category":"Professional",
            "subcategory":"Management & Consulting",
            "type":"Services"
        }
    ],
    "sg:phone":"+1 704 889 7954",
    "sg:postcode":"28134",
    "sg:province":"NC",
    "sg:tags":[
        "consultant",
        "safety"
    ],
    "wof:name":"Rapid Fire & Safety",
    "wof:placetype":"venue"
},
  "geometry": {"coordinates":[-80.88978899999999,35.085549],"type":"Point"}
}