{
  "type": "Feature",
  "properties": {
    "addr:full":"745 Biltmore Ave Asheville NC 28801",
    "addr:housenumber":"745",
    "addr:postcode":"28801",
    "addr:street":"Biltmore Ave",
    "iso:country":"US",
    "sg:address":"745 Biltmore Ave",
    "sg:city":"Asheville",
    "sg:classifiers":[
        {
            "category":"Home & Garden",
            "subcategory":"Furniture",
            "type":"Retail Goods"
        }
    ],
    "sg:phone":"+1 828 252 2337",
    "sg:postcode":"28801",
    "sg:province":"NC",
    "sg:tags":[
        "bedding"
    ],
    "sg:website":"www.davidsbedrooms.com",
    "wof:name":"David's Bedrooms",
    "wof:placetype":"venue"
},
  "geometry": {"coordinates":[-82.54512099999999,35.571076],"type":"Point"}
}