{
  "type": "Feature",
  "properties": {
    "addr:full":"2223 E State Hwy 54 Durham NC 27713",
    "addr:housenumber":"2223",
    "addr:postcode":"27713",
    "addr:street":"E State Hwy 54",
    "iso:country":"US",
    "sg:address":"2223 E State Hwy 54",
    "sg:city":"Durham",
    "sg:classifiers":[
        {
            "category":"Health Services",
            "subcategory":"Chiropractor",
            "type":"Services"
        }
    ],
    "sg:phone":"+1   ",
    "sg:postcode":"27713",
    "sg:province":"NC",
    "wof:name":"Yarasheski David DC",
    "wof:placetype":"venue"
},
  "geometry": {"coordinates":[-78.89290200000001,35.901706],"type":"Point"}
}