{
  "type": "Feature",
  "properties": {
    "iso:country":"US",
    "sg:address":"301 Westbury Dr",
    "sg:city":"Chapel Hill",
    "sg:classifiers":[
        {
            "category":"Professional",
            "subcategory":"Management & Consulting",
            "type":"Services"
        }
    ],
    "sg:phone":"+1   ",
    "sg:postcode":"27516",
    "sg:province":"NC",
    "sg:tags":[
        "business"
    ],
    "wof:name":"Gw Consulting",
    "wof:placetype":"venue"
},
  "geometry": {"coordinates":[-79.06989400000001,35.89307],"type":"Point"}
}