{
  "type": "Feature",
  "properties": {
    "addr:full":"697 Oxford Ridge Dr Wake Forest NC 27587",
    "addr:housenumber":"697",
    "addr:postcode":"27587",
    "addr:street":"Oxford Ridge Dr",
    "iso:country":"US",
    "sg:address":"697 Oxford Ridge Dr",
    "sg:city":"Wake Forest",
    "sg:classifiers":[
        {
            "category":"Shopping",
            "type":"Retail Goods"
        }
    ],
    "sg:phone":"+1 919 623 7948",
    "sg:postcode":"27587",
    "sg:province":"NC",
    "sg:tags":[
        "merchandise"
    ],
    "wof:name":"Pets Rn",
    "wof:placetype":"venue"
},
  "geometry": {"coordinates":[-78.552269,36.055952],"type":"Point"}
}