{
  "type": "Feature",
  "properties": {
    "addr:full":"102 N Old Statesville Rd Huntersville NC 28078",
    "addr:housenumber":"102",
    "addr:postcode":"28078",
    "addr:street":"N Old Statesville Rd",
    "iso:country":"US",
    "sg:address":"102 N Old Statesville Rd",
    "sg:city":"Huntersville",
    "sg:classifiers":[
        {
            "category":"Autos & Motor Vehicles",
            "subcategory":"Auto Supplies",
            "type":"Retail Goods"
        }
    ],
    "sg:phone":"+1 704 875 1110",
    "sg:postcode":"28078",
    "sg:province":"NC",
    "wof:name":"Carquest",
    "wof:placetype":"venue"
},
  "geometry": {"coordinates":[-80.84310499999999,35.414205],"type":"Point"}
}