{
  "type": "Feature",
  "properties": {
    "addr:full":"1341 N Main St Fuquay Varina NC 27526",
    "addr:housenumber":"1341",
    "addr:postcode":"27526",
    "addr:street":"N Main St",
    "iso:country":"US",
    "sg:address":"1341 N Main St",
    "sg:city":"Fuquay Varina",
    "sg:classifiers":[
        {
            "category":"Restaurant",
            "type":"Food & Drink"
        }
    ],
    "sg:menulink":"http://www.allmenus.com/nc/middle-creek/153726-zaxbys/menu/",
    "sg:phone":"+1 919 552 3981",
    "sg:postcode":"27526",
    "sg:province":"NC",
    "sg:tags":[
        "american",
        "wing"
    ],
    "wof:name":"Zaxby's",
    "wof:placetype":"venue"
},
  "geometry": {"coordinates":[-78.77674,35.591829],"type":"Point"}
}