{
  "type": "Feature",
  "properties": {
    "addr:full":"122 E 1st St Lowell NC 28098",
    "addr:housenumber":"122",
    "addr:postcode":"28098",
    "addr:street":"E 1St St",
    "iso:country":"US",
    "sg:address":"122 E 1st St",
    "sg:city":"Lowell",
    "sg:classifiers":[
        {
            "category":"Personal",
            "subcategory":"Barber",
            "type":"Services"
        }
    ],
    "sg:phone":"+1   ",
    "sg:postcode":"28098",
    "sg:province":"NC",
    "sg:tags":[
        "shop",
        "beauty"
    ],
    "wof:name":"Hair Depot",
    "wof:placetype":"venue"
},
  "geometry": {"coordinates":[-81.10050099999999,35.266009],"type":"Point"}
}