{
  "type": "Feature",
  "properties": {
    "iso:country":"US",
    "sg:address":"102 Ridge Dr",
    "sg:city":"Mount Holly",
    "sg:classifiers":[
        {
            "category":"Professional",
            "subcategory":"Business Services",
            "type":"Services"
        }
    ],
    "sg:phone":"+1   ",
    "sg:postcode":"28120",
    "sg:province":"NC",
    "wof:name":"JD Helton Enterprises LLC",
    "wof:placetype":"venue"
},
  "geometry": {"coordinates":[-81.048402,35.297675],"type":"Point"}
}