{
  "type": "Feature",
  "properties": {
    "iso:country":"US",
    "sg:address":"438 E Garrison Blvd",
    "sg:city":"Gastonia",
    "sg:classifiers":[
        {
            "category":"Health Services",
            "subcategory":"Chiropractor",
            "type":"Services"
        },
        {
            "category":"Health Services",
            "subcategory":"Doctor",
            "type":"Services"
        }
    ],
    "sg:phone":"+1 704 861 0224",
    "sg:postcode":"28054",
    "sg:province":"NC",
    "sg:tags":[
        "clinic"
    ],
    "wof:name":"Giannaras Chiropractic Center",
    "wof:placetype":"venue"
},
  "geometry": {"coordinates":[-81.175313,35.253535],"type":"Point"}
}