{
  "type": "Feature",
  "properties": {
    "iso:country":"US",
    "sg:address":"11800 Hookston Ln",
    "sg:city":"Charlotte",
    "sg:classifiers":[
        {
            "category":"Utilities",
            "subcategory":"Telephone",
            "type":"Services"
        }
    ],
    "sg:phone":"+1 704 737 3390",
    "sg:postcode":"28273",
    "sg:province":"NC",
    "sg:tags":[
        "communications"
    ],
    "wof:name":"Miplanet",
    "wof:placetype":"venue"
},
  "geometry": {"coordinates":[-80.968153,35.106373],"type":"Point"}
}