{
  "type": "Feature",
  "properties": {
    "iso:country":"US",
    "sg:address":"545 Providence Rd",
    "sg:city":"Charlotte",
    "sg:classifiers":[
        {
            "category":"Restaurant",
            "type":"Food & Drink"
        }
    ],
    "sg:phone":"+1 704 370 0208",
    "sg:postcode":"28207",
    "sg:province":"NC",
    "sg:tags":[
        "eating"
    ],
    "wof:name":"Volare Italian Restaurant",
    "wof:placetype":"venue"
},
  "geometry": {"coordinates":[-80.824607,35.203647],"type":"Point"}
}