{
  "type": "Feature",
  "properties": {
    "addr:full":"6812 River Hills Dr Greensboro NC 27410",
    "addr:housenumber":"6812",
    "addr:postcode":"27410",
    "addr:street":"River Hills Dr",
    "iso:country":"US",
    "sg:address":"6812 River Hills Dr",
    "sg:city":"Greensboro",
    "sg:classifiers":[
        {
            "category":"Professional",
            "subcategory":"Computer Services",
            "type":"Services"
        }
    ],
    "sg:phone":"+1   ",
    "sg:postcode":"27410",
    "sg:province":"NC",
    "sg:tags":[
        "programing",
        "custom"
    ],
    "wof:name":"Curve",
    "wof:placetype":"venue"
},
  "geometry": {"coordinates":[-79.935817,36.133763],"type":"Point"}
}