{
  "type": "Feature",
  "properties": {
    "iso:country":"US",
    "sg:address":"713 N Pine St",
    "sg:city":"Warsaw",
    "sg:classifiers":[
        {
            "category":"Professional",
            "type":"Services"
        }
    ],
    "sg:phone":"+1   ",
    "sg:postcode":"28398",
    "sg:province":"NC",
    "wof:name":"Pee Wees Service Center",
    "wof:placetype":"venue"
},
  "geometry": {"coordinates":[-78.094463,35.006677],"type":"Point"}
}