{
  "type": "Feature",
  "properties": {
    "iso:country":"US",
    "sg:address":"415 W Graham St",
    "sg:city":"Shelby",
    "sg:classifiers":[
        {
            "category":"Organizations",
            "subcategory":"Religious Organization",
            "type":"Services"
        }
    ],
    "sg:phone":"+1   ",
    "sg:postcode":"28150",
    "sg:province":"NC",
    "wof:name":"Hoppers Chapel Baptist Church",
    "wof:placetype":"venue"
},
  "geometry": {"coordinates":[-81.546577,35.289692],"type":"Point"}
}