{
  "type": "Feature",
  "properties": {
    "iso:country":"US",
    "sg:address":"2909 Amherst Ave",
    "sg:city":"Burlington",
    "sg:classifiers":[
        {
            "category":"Professional",
            "type":"Services"
        }
    ],
    "sg:phone":"+1 336 584 1319",
    "sg:postcode":"27215",
    "sg:province":"NC",
    "wof:name":"Ccmag Inc",
    "wof:placetype":"venue"
},
  "geometry": {"coordinates":[-79.49326499999999,36.084645],"type":"Point"}
}