{
  "type": "Feature",
  "properties": {
    "iso:country":"US",
    "sg:address":"35 S Talbert Blvd",
    "sg:city":"Lexington",
    "sg:classifiers":[
        {
            "category":"Personal",
            "subcategory":"Beauty Salon",
            "type":"Services"
        }
    ],
    "sg:phone":"+1 336 249 8879",
    "sg:postcode":"27292",
    "sg:province":"NC",
    "sg:tags":[
        "shop"
    ],
    "wof:name":"Hair Biz",
    "wof:placetype":"venue"
},
  "geometry": {"coordinates":[-80.248676,35.814184],"type":"Point"}
}