{
  "type": "Feature",
  "properties": {
    "addr:full":"2806 Page Rd Morrisville NC 27560",
    "addr:housenumber":"2806",
    "addr:postcode":"27560",
    "addr:street":"Page Rd",
    "iso:country":"US",
    "sg:address":"2806 Page Rd",
    "sg:city":"Morrisville",
    "sg:classifiers":[
        {
            "category":"Social Services",
            "type":"Services"
        }
    ],
    "sg:phone":"+1   ",
    "sg:postcode":"27560",
    "sg:province":"NC",
    "sg:tags":[
        "human"
    ],
    "wof:name":"Henderson Grove Community Outr",
    "wof:placetype":"venue"
},
  "geometry": {"coordinates":[-78.816517,35.912001],"type":"Point"}
}