{
  "type": "Feature",
  "properties": {
    "iso:country":"US",
    "sg:address":"7122 Big Horn Dr",
    "sg:city":"Hillsborough",
    "sg:classifiers":[
        {
            "category":"Building & Trades",
            "subcategory":"Construction",
            "type":"Services"
        }
    ],
    "sg:phone":"+1 919 479 9700",
    "sg:postcode":"27278",
    "sg:province":"NC",
    "sg:tags":[
        "carpentry",
        "contractor"
    ],
    "wof:name":"Garage Doors By Louis",
    "wof:placetype":"venue"
},
  "geometry": {"coordinates":[-78.944895,36.134126],"type":"Point"}
}