{
  "type": "Feature",
  "properties": {
    "addr:full":"1413 Futch Creek Rd Wilmington NC 28411",
    "addr:housenumber":"1413",
    "addr:postcode":"28411",
    "addr:street":"Futch Creek Rd",
    "iso:country":"US",
    "sg:address":"1413 Futch Creek Rd",
    "sg:city":"Wilmington",
    "sg:classifiers":[
        {
            "category":"Health Services",
            "subcategory":"Health Practitioner",
            "type":"Services"
        }
    ],
    "sg:phone":"+1   ",
    "sg:postcode":"28411",
    "sg:province":"NC",
    "sg:tags":[
        "occupational",
        "therapy"
    ],
    "wof:name":"Restart Rehabilitation",
    "wof:placetype":"venue"
},
  "geometry": {"coordinates":[-77.757256,34.298477],"type":"Point"}
}