{
  "type": "Feature",
  "properties": {
    "addr:full":"10119 Chapel Hill Rd Morrisville NC 27560",
    "addr:housenumber":"10119",
    "addr:postcode":"27560",
    "addr:street":"Chapel Hill Rd",
    "iso:country":"US",
    "sg:address":"10119 Chapel Hill Rd",
    "sg:city":"Morrisville",
    "sg:classifiers":[
        {
            "category":"Autos & Motor Vehicles",
            "subcategory":"Motorcycle Sales",
            "type":"Retail Goods"
        },
        {
            "category":"Retail",
            "subcategory":"Auto Repair",
            "type":"Services"
        }
    ],
    "sg:phone":"+1 919 469 0811",
    "sg:postcode":"27560",
    "sg:province":"NC",
    "sg:tags":[
        "scooters-repairing",
        "scooters-parts",
        "supply"
    ],
    "wof:name":"J & D Custom Cycles & Parts",
    "wof:placetype":"venue"
},
  "geometry": {"coordinates":[-78.826155,35.824839],"type":"Point"}
}