{
  "type": "Feature",
  "properties": {
    "iso:country":"US",
    "sg:address":"1533 Cajah Mountain Rd",
    "sg:city":"Hudson",
    "sg:classifiers":[
        {
            "category":"Building & Trades",
            "subcategory":"Construction",
            "type":"Services"
        }
    ],
    "sg:phone":"+1 828 396 7165",
    "sg:postcode":"28638",
    "sg:province":"NC",
    "sg:tags":[
        "residential"
    ],
    "wof:name":"Dwight & Janie Miller Cnstr",
    "wof:placetype":"venue"
},
  "geometry": {"coordinates":[-81.497629,35.82949],"type":"Point"}
}