{
  "type": "Feature",
  "properties": {
    "addr:full":"4106 Rose Lake Dr Greensboro NC 27407",
    "addr:housenumber":"4106",
    "addr:postcode":"27407",
    "addr:street":"Rose Lake Dr",
    "iso:country":"US",
    "sg:address":"4106 Rose Lake Dr",
    "sg:city":"Greensboro",
    "sg:classifiers":[
        {
            "category":"Building & Trades",
            "subcategory":"Construction",
            "type":"Services"
        }
    ],
    "sg:phone":"+1 336 547 8236",
    "sg:postcode":"27407",
    "sg:province":"NC",
    "sg:tags":[
        "house"
    ],
    "wof:name":"Jim Mackey Construction Ltd",
    "wof:placetype":"venue"
},
  "geometry": {"coordinates":[-79.87161,36.003051],"type":"Point"}
}