{
  "type": "Feature",
  "properties": {
    "addr:full":"520 N New River Dr Surf City NC 28445",
    "addr:housenumber":"520",
    "addr:postcode":"28445",
    "addr:street":"N New River Dr",
    "iso:country":"US",
    "sg:address":"520 N New River Dr",
    "sg:city":"Surf City",
    "sg:classifiers":[
        {
            "category":"Home & Garden",
            "subcategory":"Furniture",
            "type":"Retail Goods"
        }
    ],
    "sg:phone":"+1 910 328 4181",
    "sg:postcode":"28445",
    "sg:province":"NC",
    "wof:name":"Beech Furniture Outfitters",
    "wof:placetype":"venue"
},
  "geometry": {"coordinates":[-77.536536,34.432127],"type":"Point"}
}