{
  "type": "Feature",
  "properties": {
    "addr:full":"141 Providence Rd Chapel Hill NC 27514",
    "addr:housenumber":"141",
    "addr:postcode":"27514",
    "addr:street":"Providence Rd",
    "iso:country":"US",
    "sg:address":"141 Providence Rd",
    "sg:city":"Chapel Hill",
    "sg:classifiers":[
        {
            "category":"Wholesale",
            "subcategory":"Farm Supplies",
            "type":"Manufacturing & Wholesale Goods"
        }
    ],
    "sg:phone":"+1 919 493 9885",
    "sg:postcode":"27514",
    "sg:province":"NC",
    "sg:tags":[
        "leaf",
        "tobacco"
    ],
    "wof:name":"Astra Tobacco Corp",
    "wof:placetype":"venue"
},
  "geometry": {"coordinates":[-79.007582,35.951325],"type":"Point"}
}