{
  "type": "Feature",
  "properties": {
    "iso:country":"US",
    "sg:address":"133 Zacchaeus Ave",
    "sg:city":"Newport",
    "sg:classifiers":[
        {
            "category":"Retail",
            "subcategory":"Auto Repair",
            "type":"Services"
        }
    ],
    "sg:phone":"+1 252 726 5120",
    "sg:postcode":"28570",
    "sg:province":"NC",
    "sg:tags":[
        "body",
        "automobile",
        "painting"
    ],
    "wof:name":"Potter's Body Works",
    "wof:placetype":"venue"
},
  "geometry": {"coordinates":[-76.81104999999999,34.742575],"type":"Point"}
}