{
  "type": "Feature",
  "properties": {
    "addr:full":"1913 Poole Rd Raleigh NC 27610",
    "addr:housenumber":"1913",
    "addr:postcode":"27610",
    "addr:street":"Poole Rd",
    "iso:country":"US",
    "sg:address":"1913 Poole Rd",
    "sg:city":"Raleigh",
    "sg:classifiers":[
        {
            "category":"Personal",
            "subcategory":"Beauty Salon",
            "type":"Services"
        }
    ],
    "sg:phone":"+1 919 231 4888",
    "sg:postcode":"27610",
    "sg:province":"NC",
    "wof:name":"Jan's Glamour Studio",
    "wof:placetype":"venue"
},
  "geometry": {"coordinates":[-78.610646,35.776542],"type":"Point"}
}