{
  "type": "Feature",
  "properties": {
    "iso:country":"US",
    "sg:address":"134 S Main St",
    "sg:city":"Graham",
    "sg:classifiers":[
        {
            "category":"Banks & Credit Unions",
            "subcategory":"Financial Services",
            "type":"Services"
        }
    ],
    "sg:phone":"+1 336 226 1919",
    "sg:postcode":"27253",
    "sg:province":"NC",
    "sg:tags":[
        "annuity",
        "insurance"
    ],
    "wof:name":"Financial Marketing Solutions",
    "wof:placetype":"venue"
},
  "geometry": {"coordinates":[-79.40034300000001,36.068289],"type":"Point"}
}