{
  "type": "Feature",
  "properties": {
    "iso:country":"US",
    "sg:address":"7169 Old Hwy 8",
    "sg:city":"Lexington",
    "sg:classifiers":[
        {
            "category":"Food & Beverages",
            "subcategory":"Groceries & Convenience Stores",
            "type":"Retail Goods"
        }
    ],
    "sg:phone":"+1 336 798 3588",
    "sg:postcode":"27292",
    "sg:province":"NC",
    "wof:name":"Mimi's Mini Mart",
    "wof:placetype":"venue"
},
  "geometry": {"coordinates":[-80.26946,35.683977],"type":"Point"}
}