{
  "type": "Feature",
  "properties": {
    "addr:full":"120 Gallery Center Dr Mooresville NC 28117",
    "addr:housenumber":"120",
    "addr:postcode":"28117",
    "addr:street":"Center",
    "iso:country":"US",
    "sg:address":"120 Gallery Center Dr",
    "sg:city":"Mooresville",
    "sg:classifiers":[
        {
            "category":"Restaurant",
            "type":"Food & Drink"
        }
    ],
    "sg:phone":"+1 704 660 6622",
    "sg:postcode":"28117",
    "sg:province":"NC",
    "wof:name":"Golden Corral Buffet & Grill",
    "wof:placetype":"venue"
},
  "geometry": {"coordinates":[-80.86138200000001,35.597319],"type":"Point"}
}