{
  "type": "Feature",
  "properties": {
    "addr:full":"341 Snowshoe Trl Whittier NC 28789",
    "addr:housenumber":"341",
    "addr:postcode":"28789",
    "addr:street":"Snowshoe Trl",
    "iso:country":"US",
    "sg:address":"341 Snowshoe Trl",
    "sg:city":"Whittier",
    "sg:classifiers":[
        {
            "category":"Travel",
            "subcategory":"Campground",
            "type":"Entertainment"
        }
    ],
    "sg:phone":"+1 828 631 0692",
    "sg:postcode":"28789",
    "sg:province":"NC",
    "wof:name":"Holly Cove Inc",
    "wof:placetype":"venue"
},
  "geometry": {"coordinates":[-83.287217,35.399463],"type":"Point"}
}