{
  "type": "Feature",
  "properties": {
    "addr:full":"3725 Ramsey St Fayetteville NC 28311",
    "addr:housenumber":"3725",
    "addr:postcode":"28311",
    "addr:street":"Ramsey St",
    "iso:country":"US",
    "sg:address":"3725 Ramsey St",
    "sg:city":"Fayetteville",
    "sg:classifiers":[
        {
            "category":"Utilities",
            "subcategory":"Telephone",
            "type":"Services"
        }
    ],
    "sg:phone":"+1 910 488 8962",
    "sg:postcode":"28311",
    "sg:province":"NC",
    "sg:tags":[
        "communications"
    ],
    "wof:name":"Alltel",
    "wof:placetype":"venue"
},
  "geometry": {"coordinates":[-78.87989399999999,35.114531],"type":"Point"}
}