{
  "type": "Feature",
  "properties": {
    "addr:full":"6445 Shiloh Church Rd Bailey NC 27807",
    "addr:housenumber":"6445",
    "addr:postcode":"27807",
    "addr:street":"Shiloh Church Rd",
    "iso:country":"US",
    "sg:address":"6445 Shiloh Church Rd",
    "sg:city":"Bailey",
    "sg:classifiers":[
        {
            "category":"Building & Trades",
            "subcategory":"Construction",
            "type":"Services"
        }
    ],
    "sg:phone":"+1 252 291 6360",
    "sg:postcode":"27807",
    "sg:province":"NC",
    "sg:tags":[
        "carpentry",
        "contractor"
    ],
    "wof:name":"Leonard N Griffin",
    "wof:placetype":"venue"
},
  "geometry": {"coordinates":[-78.033675,35.783859],"type":"Point"}
}