{
  "type": "Feature",
  "properties": {
    "iso:country":"US",
    "sg:address":"3627 Sana Ct",
    "sg:city":"Durham",
    "sg:phone":"+1 919 361 4370",
    "sg:postcode":"27713",
    "sg:province":"NC",
    "sg:tags":[
        "equipment",
        "commercial"
    ],
    "wof:name":"Southstern Rest Eqp Design LLC",
    "wof:placetype":"venue"
},
  "geometry": {"coordinates":[-78.89721299999999,35.929684],"type":"Point"}
}