{
  "type": "Feature",
  "properties": {
    "iso:country":"US",
    "sg:address":"4045 Teakwood Dr",
    "sg:city":"Charlotte",
    "sg:classifiers":[
        {
            "category":"Shopping",
            "subcategory":"Beauty & Cosmetics",
            "type":"Retail Goods"
        }
    ],
    "sg:phone":"+1 704 525 8577",
    "sg:postcode":"28217",
    "sg:province":"NC",
    "sg:tags":[
        "sell",
        "equipment",
        "supply"
    ],
    "wof:name":"Lydia Discount Beauty Supply",
    "wof:placetype":"venue"
},
  "geometry": {"coordinates":[-80.89787,35.177829],"type":"Point"}
}