{
  "type": "Feature",
  "properties": {
    "iso:country":"US",
    "sg:address":"3121 Chelmshire Ct",
    "sg:city":"Raleigh",
    "sg:classifiers":[
        {
            "category":"Professional",
            "type":"Services"
        }
    ],
    "sg:phone":"+1 919 779 5735",
    "sg:postcode":"27529",
    "sg:province":"NC",
    "wof:name":"Beatice Leathers",
    "wof:placetype":"venue"
},
  "geometry": {"coordinates":[-78.567013,35.737947],"type":"Point"}
}