{
  "type": "Feature",
  "properties": {
    "addr:full":"5214 Market St Wilmington NC 28405",
    "addr:housenumber":"5214",
    "addr:postcode":"28405",
    "addr:street":"Market St",
    "iso:country":"US",
    "sg:address":"5214 Market St",
    "sg:city":"Wilmington",
    "sg:classifiers":[
        {
            "category":"Restaurant",
            "type":"Food & Drink"
        }
    ],
    "sg:phone":"+1 910 796 8885",
    "sg:postcode":"28405",
    "sg:province":"NC",
    "wof:name":"Chopstix",
    "wof:placetype":"venue"
},
  "geometry": {"coordinates":[-77.876857,34.244921],"type":"Point"}
}