{
  "type": "Feature",
  "properties": {
    "iso:country":"US",
    "sg:address":"145 W Vermont Ave",
    "sg:city":"Southern Pines",
    "sg:classifiers":[
        {
            "category":"Professional",
            "subcategory":"Management & Consulting",
            "type":"Services"
        }
    ],
    "sg:phone":"+1   ",
    "sg:postcode":"28387",
    "sg:province":"NC",
    "sg:tags":[
        "business"
    ],
    "wof:name":"Capital Consultants Inc",
    "wof:placetype":"venue"
},
  "geometry": {"coordinates":[-79.388079,35.176278],"type":"Point"}
}