{
  "type": "Feature",
  "properties": {
    "iso:country":"US",
    "sg:address":"609 Country Club Dr",
    "sg:city":"Greenville",
    "sg:classifiers":[
        {
            "category":"Professional",
            "subcategory":"Employment Agencies",
            "type":"Services"
        }
    ],
    "sg:phone":"+1 252 756 0300",
    "sg:postcode":"27834",
    "sg:province":"NC",
    "sg:tags":[
        "opportunity"
    ],
    "wof:name":"Action Health Staffing",
    "wof:placetype":"venue"
},
  "geometry": {"coordinates":[-77.396013,35.579019],"type":"Point"}
}