{
  "type": "Feature",
  "properties": {
    "addr:full":"336 John Oakley Rd Prospect Hill NC 27314",
    "addr:housenumber":"336",
    "addr:postcode":"27314",
    "addr:street":"John Oakley Rd",
    "iso:country":"US",
    "sg:address":"336 John Oakley Rd",
    "sg:city":"Prospect Hill",
    "sg:classifiers":[
        {
            "category":"Farming",
            "subcategory":"Livestock Farm",
            "type":"Manufacturing & Wholesale Goods"
        }
    ],
    "sg:phone":"+1 919 493 3391",
    "sg:postcode":"27314",
    "sg:province":"NC",
    "sg:tags":[
        "equine"
    ],
    "wof:name":"Lockhaven Farm Inc",
    "wof:placetype":"venue"
},
  "geometry": {"coordinates":[-79.214258,36.321633],"type":"Point"}
}