{
  "type": "Feature",
  "properties": {
    "iso:country":"US",
    "sg:address":"1275 Old US Hwy 1",
    "sg:city":"Southern Pines",
    "sg:classifiers":[
        {
            "category":"Insurance",
            "subcategory":"Insurance Agent",
            "type":"Services"
        }
    ],
    "sg:phone":"+1 910 692 2126",
    "sg:postcode":"28387",
    "sg:province":"NC",
    "wof:name":"Met Life",
    "wof:placetype":"venue"
},
  "geometry": {"coordinates":[-79.40580300000001,35.165645],"type":"Point"}
}