{
  "type": "Feature",
  "properties": {
    "addr:full":"901 N Wendover Rd Charlotte NC 28211",
    "addr:housenumber":"901",
    "addr:postcode":"28211",
    "addr:street":"N Wendover Rd",
    "iso:country":"US",
    "sg:address":"901 N Wendover Rd",
    "sg:city":"Charlotte",
    "sg:classifiers":[
        {
            "category":"Professional",
            "subcategory":"Accounting & Tax Preparation",
            "type":"Services"
        }
    ],
    "sg:phone":"+1 704 365 3850",
    "sg:postcode":"28211",
    "sg:province":"NC",
    "sg:tags":[
        "return",
        "filing"
    ],
    "wof:name":"N & J Tax Svc",
    "wof:placetype":"venue"
},
  "geometry": {"coordinates":[-80.797101,35.190664],"type":"Point"}
}