{
  "type": "Feature",
  "properties": {
    "addr:full":"136 John Webb Rd Ellerbe NC 28338",
    "addr:housenumber":"136",
    "addr:postcode":"28338",
    "addr:street":"John Webb Rd",
    "iso:country":"US",
    "sg:address":"136 John Webb Rd",
    "sg:city":"Ellerbe",
    "sg:classifiers":[
        {
            "category":"Building & Trades",
            "subcategory":"Plumbing",
            "type":"Services"
        }
    ],
    "sg:phone":"+1 910 206 1386",
    "sg:postcode":"28338",
    "sg:province":"NC",
    "sg:tags":[
        "conditioning",
        "air",
        "system",
        "contractor"
    ],
    "wof:name":"Brigman Heating & Air Cond",
    "wof:placetype":"venue"
},
  "geometry": {"coordinates":[-79.784691,35.03789],"type":"Point"}
}