{
  "type": "Feature",
  "properties": {
    "addr:full":"6525 State Hwy 770 Stoneville NC 27048",
    "addr:housenumber":"6525",
    "addr:postcode":"27048",
    "addr:street":"State Hwy 770",
    "iso:country":"US",
    "sg:address":"6525 State Hwy 770",
    "sg:city":"Stoneville",
    "sg:classifiers":[
        {
            "category":"Organizations",
            "subcategory":"Religious Organization",
            "type":"Services"
        }
    ],
    "sg:phone":"+1   ",
    "sg:postcode":"27048",
    "sg:province":"NC",
    "wof:name":"Fairview Baptist Church",
    "wof:placetype":"venue"
},
  "geometry": {"coordinates":[-79.821218,36.478256],"type":"Point"}
}