{
  "type": "Feature",
  "properties": {
    "iso:country":"US",
    "sg:address":"2034 Randolph Rd",
    "sg:city":"Charlotte",
    "sg:classifiers":[
        {
            "category":"Real Estate",
            "subcategory":"Real Estate Agent",
            "type":"Services"
        }
    ],
    "sg:phone":"+1 704 334 6677",
    "sg:postcode":"28207",
    "sg:province":"NC",
    "wof:name":"Charlotte Kirby",
    "wof:placetype":"venue"
},
  "geometry": {"coordinates":[-80.821901,35.207983],"type":"Point"}
}