{
  "type": "Feature",
  "properties": {
    "iso:country":"US",
    "sg:address":"7413 Ridgeview Pl",
    "sg:city":"Wilmington",
    "sg:classifiers":[
        {
            "category":"Education",
            "subcategory":"Dance Studio",
            "type":"Public Place"
        }
    ],
    "sg:phone":"+1   ",
    "sg:postcode":"28411",
    "sg:province":"NC",
    "sg:tags":[
        "instructor"
    ],
    "wof:name":"Babs McCullen",
    "wof:placetype":"venue"
},
  "geometry": {"coordinates":[-77.81394899999999,34.279959],"type":"Point"}
}