{
  "type": "Feature",
  "properties": {
    "addr:full":"2538 W Dixon Blvd Shelby NC 28152",
    "addr:housenumber":"2538",
    "addr:postcode":"28152",
    "addr:street":"W Dixon Blvd",
    "iso:country":"US",
    "sg:address":"2538 W Dixon Blvd",
    "sg:city":"Shelby",
    "sg:classifiers":[
        {
            "category":"Home & Garden",
            "subcategory":"Mobile Homes",
            "type":"Retail Goods"
        }
    ],
    "sg:phone":"+1 704 471 2005",
    "sg:postcode":"28152",
    "sg:province":"NC",
    "wof:name":"Home Sales New & Used",
    "wof:placetype":"venue"
},
  "geometry": {"coordinates":[-81.600679,35.29353],"type":"Point"}
}