{
  "type": "Feature",
  "properties": {
    "addr:full":"9577 Piney Woods Rd Watha NC 28478",
    "addr:housenumber":"9577",
    "addr:postcode":"28478",
    "addr:street":"Piney Woods Rd",
    "iso:country":"US",
    "sg:address":"9577 Piney Woods Rd",
    "sg:city":"Watha",
    "sg:classifiers":[
        {
            "category":"Restaurant",
            "type":"Food & Drink"
        }
    ],
    "sg:phone":"+1 910 283 5220",
    "sg:postcode":"28478",
    "sg:province":"NC",
    "sg:tags":[
        "caterer"
    ],
    "wof:name":"Parker's BBQ & Catering",
    "wof:placetype":"venue"
},
  "geometry": {"coordinates":[-78.112534,34.564582],"type":"Point"}
}