{
  "type": "Feature",
  "properties": {
    "addr:full":"133 Wagstaff Rd Fuquay Varina NC 27526",
    "addr:housenumber":"133",
    "addr:postcode":"27526",
    "addr:street":"Wagstaff Rd",
    "iso:country":"US",
    "sg:address":"133 Wagstaff Rd",
    "sg:city":"Fuquay Varina",
    "sg:classifiers":[
        {
            "category":"Building & Trades",
            "subcategory":"Landscaping Services",
            "type":"Services"
        }
    ],
    "sg:phone":"+1 919 557 7395",
    "sg:postcode":"27526",
    "sg:province":"NC",
    "sg:tags":[
        "lawn",
        "maintenance",
        "grounds"
    ],
    "wof:name":"Tanners Landscape Maintenance",
    "wof:placetype":"venue"
},
  "geometry": {"coordinates":[-78.80800000000001,35.566376],"type":"Point"}
}