{
  "type": "Feature",
  "properties": {
    "iso:country":"US",
    "sg:address":"106 Pebble Ridge Farms Ct",
    "sg:city":"Cary",
    "sg:classifiers":[
        {
            "category":"Manufacturing",
            "subcategory":"Food",
            "type":"Manufacturing & Wholesale Goods"
        }
    ],
    "sg:phone":"+1 919 677 7880",
    "sg:postcode":"27513",
    "sg:province":"NC",
    "sg:tags":[
        "drink",
        "soft",
        "mfg"
    ],
    "wof:name":"Dr Pepper/Seven-Up Inc",
    "wof:placetype":"venue"
},
  "geometry": {"coordinates":[-78.80302500000001,35.81336],"type":"Point"}
}