{
  "type": "Feature",
  "properties": {
    "iso:country":"US",
    "sg:address":"203 State Hwy 161",
    "sg:city":"Bessemer City",
    "sg:classifiers":[
        {
            "category":"Building & Trades",
            "subcategory":"Construction",
            "type":"Services"
        }
    ],
    "sg:phone":"+1 704 629 3705",
    "sg:postcode":"28016",
    "sg:province":"NC",
    "sg:tags":[
        "contractor"
    ],
    "wof:name":"Cochrans Roofing",
    "wof:placetype":"venue"
},
  "geometry": {"coordinates":[-81.28632500000001,35.284326],"type":"Point"}
}