{
  "type": "Feature",
  "properties": {
    "addr:full":"104 Mulberry St SW Lenoir NC 28645",
    "addr:housenumber":"104",
    "addr:postcode":"28645",
    "addr:street":"Mulberry St Sw",
    "iso:country":"US",
    "sg:address":"104 Mulberry St SW",
    "sg:city":"Lenoir",
    "sg:classifiers":[
        {
            "category":"Organizations",
            "subcategory":"Religious Organization",
            "type":"Services"
        }
    ],
    "sg:phone":"+1   ",
    "sg:postcode":"28645",
    "sg:province":"NC",
    "wof:name":"Trinity Baptist Church",
    "wof:placetype":"venue"
},
  "geometry": {"coordinates":[-81.53854,35.914112],"type":"Point"}
}