{
  "type": "Feature",
  "properties": {
    "iso:country":"US",
    "sg:address":"117 Williamsboro St",
    "sg:city":"Oxford",
    "sg:classifiers":[
        {
            "category":"Health Services",
            "subcategory":"Clinic",
            "type":"Services"
        }
    ],
    "sg:phone":"+1 919 693 2464",
    "sg:postcode":"27565",
    "sg:province":"NC",
    "sg:tags":[
        "medical"
    ],
    "wof:name":"Superior Health Care Service",
    "wof:placetype":"venue"
},
  "geometry": {"coordinates":[-78.58871499999999,36.311811],"type":"Point"}
}