{
  "type": "Feature",
  "properties": {
    "iso:country":"US",
    "sg:address":"644 Roy Goodman Rd",
    "sg:city":"Crumpler",
    "sg:classifiers":[
        {
            "category":"Building & Trades",
            "subcategory":"Landscaping Services",
            "type":"Services"
        }
    ],
    "sg:phone":"+1 336 982 6285",
    "sg:postcode":"28617",
    "sg:province":"NC",
    "sg:tags":[
        "tree"
    ],
    "wof:name":"Mountain Advantage Tree",
    "wof:placetype":"venue"
},
  "geometry": {"coordinates":[-81.421205,36.438346],"type":"Point"}
}