{
  "type": "Feature",
  "properties": {
    "iso:country":"US",
    "sg:address":"4838 Butterwick Ln",
    "sg:city":"Charlotte",
    "sg:classifiers":[
        {
            "category":"Wholesale",
            "subcategory":"Electrical",
            "type":"Manufacturing & Wholesale Goods"
        }
    ],
    "sg:phone":"+1 704 535 6599",
    "sg:postcode":"28212",
    "sg:province":"NC",
    "sg:tags":[
        "equipment",
        "fixtures-wholesale",
        "lighting",
        "manufacturer"
    ],
    "wof:name":"Ici Lamp Company",
    "wof:placetype":"venue"
},
  "geometry": {"coordinates":[-80.739904,35.21623],"type":"Point"}
}