{
  "type": "Feature",
  "properties": {
    "addr:full":"350 Blowing Rock Blvd Lenoir NC 28645",
    "addr:housenumber":"350",
    "addr:postcode":"28645",
    "addr:street":"Blowing Rock Blvd",
    "iso:country":"US",
    "sg:address":"350 Blowing Rock Blvd",
    "sg:city":"Lenoir",
    "sg:classifiers":[
        {
            "category":"Professional",
            "type":"Services"
        }
    ],
    "sg:phone":"+1 828 757 3515",
    "sg:postcode":"28645",
    "sg:province":"NC",
    "sg:tags":[
        "establishment"
    ],
    "wof:name":"Glenora Way LLC",
    "wof:placetype":"venue"
},
  "geometry": {"coordinates":[-81.52459399999999,35.916344],"type":"Point"}
}