{
  "type": "Feature",
  "properties": {
    "iso:country":"US",
    "sg:address":"7728 Arboretum Dr",
    "sg:city":"Charlotte",
    "sg:classifiers":[
        {
            "category":"Professional",
            "type":"Services"
        }
    ],
    "sg:phone":"+1 704 542 0377",
    "sg:postcode":"28270",
    "sg:province":"NC",
    "sg:tags":[
        "establishment"
    ],
    "wof:name":"R & M Materials Handling Inc",
    "wof:placetype":"venue"
},
  "geometry": {"coordinates":[-80.77708800000001,35.101728],"type":"Point"}
}