{
  "type": "Feature",
  "properties": {
    "iso:country":"US",
    "sg:address":"1019 Roanoke Ave",
    "sg:city":"Roanoke Rapids",
    "sg:classifiers":[
        {
            "category":"Restaurant",
            "type":"Food & Drink"
        }
    ],
    "sg:phone":"+1 252 410 5282",
    "sg:postcode":"27870",
    "sg:province":"NC",
    "sg:tags":[
        "eating"
    ],
    "wof:name":"Java Junction",
    "wof:placetype":"venue"
},
  "geometry": {"coordinates":[-77.657358,36.45581],"type":"Point"}
}