{
  "type": "Feature",
  "properties": {
    "addr:full":"1349 Blowing Rock Blvd Lenoir NC 28645",
    "addr:housenumber":"1349",
    "addr:postcode":"28645",
    "addr:street":"Blowing Rock Blvd",
    "iso:country":"US",
    "sg:address":"1349 Blowing Rock Blvd",
    "sg:city":"Lenoir",
    "sg:classifiers":[
        {
            "category":"Real Estate",
            "subcategory":"Real Estate Agent",
            "type":"Services"
        }
    ],
    "sg:phone":"+1 828 758 0885",
    "sg:postcode":"28645",
    "sg:province":"NC",
    "wof:name":"American Realty Company",
    "wof:placetype":"venue"
},
  "geometry": {"coordinates":[-81.52916399999999,35.932028],"type":"Point"}
}