{
  "type": "Feature",
  "properties": {
    "addr:full":"116 Armstrong Dr Sharpsburg NC 27822",
    "addr:housenumber":"116",
    "addr:postcode":"27822",
    "addr:street":"Armstrong Dr",
    "iso:country":"US",
    "sg:address":"116 Armstrong Dr",
    "sg:city":"Sharpsburg",
    "sg:classifiers":[
        {
            "category":"Personal",
            "subcategory":"Barber",
            "type":"Services"
        }
    ],
    "sg:phone":"+1 252 446 7990",
    "sg:postcode":"27822",
    "sg:province":"NC",
    "wof:name":"Kew's Barber Shop",
    "wof:placetype":"venue"
},
  "geometry": {"coordinates":[-77.832334,35.859741],"type":"Point"}
}