{
  "type": "Feature",
  "properties": {
    "iso:country":"US",
    "sg:address":"2115 Rockford St",
    "sg:city":"Mount Airy",
    "sg:classifiers":[
        {
            "category":"Professional",
            "subcategory":"Accounting & Tax Preparation",
            "type":"Services"
        }
    ],
    "sg:phone":"+1 336 783 7476",
    "sg:postcode":"27030",
    "sg:province":"NC",
    "sg:tags":[
        "return"
    ],
    "wof:name":"Jackson Hewitt Tax Service",
    "wof:placetype":"venue"
},
  "geometry": {"coordinates":[-80.617786,36.477476],"type":"Point"}
}