{
  "type": "Feature",
  "properties": {
    "iso:country":"US",
    "sg:address":"11921 Springpoint Ln",
    "sg:city":"Charlotte",
    "sg:classifiers":[
        {
            "category":"Real Estate",
            "subcategory":"Real Estate Agent",
            "type":"Services"
        }
    ],
    "sg:phone":"+1 704 588 1264",
    "sg:postcode":"28278",
    "sg:province":"NC",
    "wof:name":"G&B Property Co A North Caroli",
    "wof:placetype":"venue"
},
  "geometry": {"coordinates":[-81.00116800000001,35.149398],"type":"Point"}
}