{
  "type": "Feature",
  "properties": {
    "addr:full":"286 Comanche Dr Advance NC 27006",
    "addr:housenumber":"286",
    "addr:postcode":"27006",
    "addr:street":"Comanche Dr",
    "iso:country":"US",
    "sg:address":"286 Comanche Dr",
    "sg:city":"Advance",
    "sg:classifiers":[
        {
            "category":"Building & Trades",
            "subcategory":"Construction",
            "type":"Services"
        }
    ],
    "sg:phone":"+1 336 998 6200",
    "sg:postcode":"27006",
    "sg:province":"NC",
    "sg:tags":[
        "contractor"
    ],
    "wof:name":"Danny Walser Masonry",
    "wof:placetype":"venue"
},
  "geometry": {"coordinates":[-80.455173,35.910904],"type":"Point"}
}