{
  "type": "Feature",
  "properties": {
    "iso:country":"US",
    "sg:address":"223 N Main St",
    "sg:city":"Oakboro",
    "sg:classifiers":[
        {
            "category":"Restaurant",
            "type":"Food & Drink"
        }
    ],
    "sg:phone":"+1 704 485 8401",
    "sg:postcode":"28129",
    "sg:province":"NC",
    "sg:tags":[
        "parlor",
        "ice",
        "cream"
    ],
    "wof:name":"Paleteria LA Potosina Inc",
    "wof:placetype":"venue"
},
  "geometry": {"coordinates":[-80.32667600000001,35.224066],"type":"Point"}
}