{
  "type": "Feature",
  "properties": {
    "iso:country":"US",
    "sg:address":"2216 Loblolly Ct",
    "sg:city":"Wilmington",
    "sg:classifiers":[
        {
            "category":"Building & Trades",
            "subcategory":"Construction",
            "type":"Services"
        },
        {
            "category":"Professional",
            "subcategory":"Management & Consulting",
            "type":"Services"
        }
    ],
    "sg:phone":"+1 910 792 1708",
    "sg:postcode":"28411",
    "sg:province":"NC",
    "sg:tags":[
        "general",
        "contractor"
    ],
    "wof:name":"Construction Management & Dev",
    "wof:placetype":"venue"
},
  "geometry": {"coordinates":[-77.84380400000001,34.277863],"type":"Point"}
}