{
  "type": "Feature",
  "properties": {
    "addr:full":"200 Red Roof Ln Sparta NC 28675",
    "addr:housenumber":"200",
    "addr:postcode":"28675",
    "addr:street":"Red Roof Ln",
    "iso:country":"US",
    "sg:address":"200 Red Roof Ln",
    "sg:city":"Sparta",
    "sg:classifiers":[
        {
            "category":"Travel",
            "subcategory":"Hotels & Motels",
            "type":"Entertainment"
        }
    ],
    "sg:phone":"+1   ",
    "sg:postcode":"28675",
    "sg:province":"NC",
    "sg:tags":[
        "operation"
    ],
    "wof:name":"Red Roof Farm",
    "wof:placetype":"venue"
},
  "geometry": {"coordinates":[-81.08339599999999,36.551226],"type":"Point"}
}