{
  "type": "Feature",
  "properties": {
    "addr:full":"170 Wey Bosset Rd Henderson NC 27536",
    "addr:housenumber":"170",
    "addr:postcode":"27536",
    "addr:street":"Wey Bosset Rd",
    "iso:country":"US",
    "sg:address":"170 Wey Bosset Rd",
    "sg:city":"Henderson",
    "sg:classifiers":[
        {
            "category":"Building & Trades",
            "subcategory":"Construction",
            "type":"Services"
        }
    ],
    "sg:phone":"+1 252 492 4993",
    "sg:postcode":"27536",
    "sg:province":"NC",
    "sg:tags":[
        "house"
    ],
    "wof:name":"M&M Construction",
    "wof:placetype":"venue"
},
  "geometry": {"coordinates":[-78.461895,36.305127],"type":"Point"}
}