{
  "type": "Feature",
  "properties": {
    "iso:country":"US",
    "sg:address":"102 E Church St",
    "sg:city":"Rose Hill",
    "sg:classifiers":[
        {
            "category":"Food & Beverages",
            "subcategory":"Bakery",
            "type":"Retail Goods"
        }
    ],
    "sg:phone":"+1 910 282 0755",
    "sg:postcode":"28458",
    "sg:province":"NC",
    "wof:name":"Rosehill Bakery",
    "wof:placetype":"venue"
},
  "geometry": {"coordinates":[-78.028682,34.823658],"type":"Point"}
}