{
  "type": "Feature",
  "properties": {
    "addr:full":"334 W Main Ave Gastonia NC 28052",
    "addr:housenumber":"334",
    "addr:postcode":"28052",
    "addr:street":"W Main Ave",
    "iso:country":"US",
    "sg:address":"334 W Main Ave",
    "sg:city":"Gastonia",
    "sg:classifiers":[
        {
            "category":"Retail",
            "subcategory":"Repair Shop",
            "type":"Services"
        }
    ],
    "sg:phone":"+1 704 864 6967",
    "sg:postcode":"28052",
    "sg:province":"NC",
    "sg:tags":[
        "television",
        "radio"
    ],
    "wof:name":"Kings Mountain TV Svc Inc",
    "wof:placetype":"venue"
},
  "geometry": {"coordinates":[-81.186787,35.263835],"type":"Point"}
}