{
  "type": "Feature",
  "properties": {
    "iso:country":"US",
    "sg:address":"33 Haywood St",
    "sg:city":"Asheville",
    "sg:classifiers":[
        {
            "category":"Manufacturing",
            "subcategory":"Apparel",
            "type":"Manufacturing & Wholesale Goods"
        }
    ],
    "sg:phone":"+1 828 255 7818",
    "sg:postcode":"28801",
    "sg:province":"NC",
    "sg:tags":[
        "blouse",
        "house",
        "mfg",
        "mail"
    ],
    "sg:website":"www.earthguild.com",
    "wof:name":"Earth Guild",
    "wof:placetype":"venue"
},
  "geometry": {"coordinates":[-82.55463899999999,35.595686],"type":"Point"}
}