{
  "type": "Feature",
  "properties": {
    "iso:country":"US",
    "sg:address":"890 Highland Ave NE",
    "sg:city":"Hickory",
    "sg:classifiers":[
        {
            "category":"Retail",
            "subcategory":"Repair Shop",
            "type":"Services"
        }
    ],
    "sg:phone":"+1 828 267 1855",
    "sg:postcode":"28601",
    "sg:province":"NC",
    "sg:tags":[
        "refinishing",
        "furniture"
    ],
    "wof:name":"Highland Repair & Refinishing",
    "wof:placetype":"venue"
},
  "geometry": {"coordinates":[-81.32147999999999,35.738608],"type":"Point"}
}