{
  "type": "Feature",
  "properties": {
    "iso:country":"US",
    "sg:address":"1300 Falls River Ave",
    "sg:city":"Raleigh",
    "sg:classifiers":[
        {
            "category":"Recreation",
            "type":"Entertainment"
        }
    ],
    "sg:phone":"+1 919 848 0776",
    "sg:postcode":"27614",
    "sg:province":"NC",
    "sg:tags":[
        "club",
        "membership",
        "pool",
        "swimming"
    ],
    "sg:website":"www.fallsriverclub.com",
    "wof:name":"Falls River Swim Club Inc",
    "wof:placetype":"venue"
},
  "geometry": {"coordinates":[-78.58774699999999,35.910565],"type":"Point"}
}