{
  "type": "Feature",
  "properties": {
    "addr:full":"4456 Old High Point St Randleman NC 27317",
    "addr:housenumber":"4456",
    "addr:postcode":"27317",
    "addr:street":"Old High Point St",
    "iso:country":"US",
    "sg:address":"4456 Old High Point St",
    "sg:city":"Randleman",
    "sg:classifiers":[
        {
            "category":"Banks & Credit Unions",
            "subcategory":"Investment Brokerage",
            "type":"Services"
        }
    ],
    "sg:phone":"+1 336 495 3300",
    "sg:postcode":"27317",
    "sg:province":"NC",
    "sg:tags":[
        "advisory"
    ],
    "wof:name":"Hunt Investments North Caro",
    "wof:placetype":"venue"
},
  "geometry": {"coordinates":[-79.83041799999999,35.818153],"type":"Point"}
}