{
  "type": "Feature",
  "properties": {
    "addr:full":"251 Indian Trl Indian Trail NC 28043",
    "addr:housenumber":"251",
    "addr:postcode":"28043",
    "addr:street":"Indian Trl;Trail",
    "iso:country":"US",
    "sg:address":"251 Indian Trl",
    "sg:city":"Indian Trail",
    "sg:classifiers":[
        {
            "category":"Insurance",
            "subcategory":"Insurance Agent",
            "type":"Services"
        }
    ],
    "sg:phone":"+1 704 821 4460",
    "sg:postcode":"28043",
    "sg:province":"NC",
    "wof:name":"Spivey Insurance",
    "wof:placetype":"venue"
},
  "geometry": {"coordinates":[-81.917818,35.387632],"type":"Point"}
}