{
  "type": "Feature",
  "properties": {
    "addr:full":"1250 E 10th St Winston Salem NC 27101",
    "addr:housenumber":"1250",
    "addr:postcode":"27101",
    "addr:street":"E 10Th St",
    "iso:country":"US",
    "sg:address":"1250 E 10th St",
    "sg:city":"Winston Salem",
    "sg:classifiers":[
        {
            "category":"Organizations",
            "subcategory":"Religious Organization",
            "type":"Services"
        }
    ],
    "sg:phone":"+1 336 723 7196",
    "sg:postcode":"27101",
    "sg:province":"NC",
    "sg:tags":[
        "church"
    ],
    "wof:name":"Pleasant Union Baptist Church",
    "wof:placetype":"venue"
},
  "geometry": {"coordinates":[-80.23029,36.106734],"type":"Point"}
}