{
  "type": "Feature",
  "properties": {
    "addr:full":"5417 Williams Place Ct Winston Salem NC 27106",
    "addr:housenumber":"5417",
    "addr:postcode":"27106",
    "addr:street":"Williams Place Ct",
    "iso:country":"US",
    "sg:address":"5417 Williams Place Ct",
    "sg:city":"Winston Salem",
    "sg:classifiers":[
        {
            "category":"Professional",
            "type":"Services"
        }
    ],
    "sg:phone":"+1 336 922 6655",
    "sg:postcode":"27106",
    "sg:province":"NC",
    "sg:tags":[
        "establishment"
    ],
    "wof:name":"Simington & Simington",
    "wof:placetype":"venue"
},
  "geometry": {"coordinates":[-80.37783399999999,36.138501],"type":"Point"}
}