{
  "type": "Feature",
  "properties": {
    "addr:full":"4900 Oak Garden Dr Kernersville NC 27284",
    "addr:housenumber":"4900",
    "addr:postcode":"27284",
    "addr:street":"Oak Garden Dr",
    "iso:country":"US",
    "sg:address":"4900 Oak Garden Dr",
    "sg:city":"Kernersville",
    "sg:classifiers":[
        {
            "category":"Building & Trades",
            "subcategory":"Electrical",
            "type":"Services"
        }
    ],
    "sg:phone":"+1 336 784 7682",
    "sg:postcode":"27284",
    "sg:province":"NC",
    "sg:tags":[
        "electrical",
        "electric",
        "contractor"
    ],
    "wof:name":"C B Atkins Electrical Contr",
    "wof:placetype":"venue"
},
  "geometry": {"coordinates":[-80.133871,36.082262],"type":"Point"}
}