{
  "type": "Feature",
  "properties": {
    "addr:full":"7340 Six Forks Rd Raleigh NC 27615",
    "addr:housenumber":"7340",
    "addr:postcode":"27615",
    "addr:street":"Six Forks Rd",
    "iso:country":"US",
    "sg:address":"7340 Six Forks Rd",
    "sg:city":"Raleigh",
    "sg:classifiers":[
        {
            "category":"Building & Trades",
            "subcategory":"Construction",
            "type":"Services"
        }
    ],
    "sg:phone":"+1 919 846 9999",
    "sg:postcode":"27615",
    "sg:province":"NC",
    "sg:tags":[
        "home",
        "builder"
    ],
    "wof:name":"Thomas Gipson Homes",
    "wof:placetype":"venue"
},
  "geometry": {"coordinates":[-78.64603700000001,35.881588],"type":"Point"}
}