{
  "type": "Feature",
  "properties": {
    "addr:full":"1901 Sunset Ave Clinton NC 28328",
    "addr:housenumber":"1901",
    "addr:postcode":"28328",
    "addr:street":"Sunset Ave",
    "iso:country":"US",
    "sg:address":"1901 Sunset Ave",
    "sg:city":"Clinton",
    "sg:classifiers":[
        {
            "category":"Social Services",
            "subcategory":"Child Care",
            "type":"Services"
        }
    ],
    "sg:phone":"+1 910 592 3624",
    "sg:postcode":"28328",
    "sg:province":"NC",
    "wof:name":"Bright Beginnings Child Dvlpmt",
    "wof:placetype":"venue"
},
  "geometry": {"coordinates":[-78.348337,34.991628],"type":"Point"}
}