{
  "type": "Feature",
  "properties": {
    "addr:full":"7512 Bradgate Rd Charlotte NC 28217",
    "addr:housenumber":"7512",
    "addr:postcode":"28217",
    "addr:street":"Bradgate Rd",
    "iso:country":"US",
    "sg:address":"7512 Bradgate Rd",
    "sg:city":"Charlotte",
    "sg:classifiers":[
        {
            "category":"Retail",
            "subcategory":"Auto Repair",
            "type":"Services"
        }
    ],
    "sg:phone":"+1 704 522 0473",
    "sg:postcode":"28217",
    "sg:province":"NC",
    "sg:tags":[
        "body"
    ],
    "wof:name":"Phils Paint & Auto Body Shop",
    "wof:placetype":"venue"
},
  "geometry": {"coordinates":[-80.916546,35.147217],"type":"Point"}
}