{
  "type": "Feature",
  "properties": {
    "iso:country":"US",
    "sg:address":"2000 Regency Pkwy Ste 100",
    "sg:city":"Cary",
    "sg:classifiers":[
        {
            "category":"Health Services",
            "subcategory":"Optometrist",
            "type":"Services"
        }
    ],
    "sg:phone":"+1 919 297 0900",
    "sg:postcode":"27518",
    "sg:province":"NC",
    "sg:website":"www.dukeeye.org",
    "wof:name":"Duke Eye Center of Cary",
    "wof:placetype":"venue"
},
  "geometry": {"coordinates":[-78.789783,35.734167],"type":"Point"}
}