{
  "type": "Feature",
  "properties": {
    "iso:country":"US",
    "sg:address":"107 Adventure Trl",
    "sg:city":"Cary",
    "sg:classifiers":[
        {
            "category":"Professional",
            "type":"Services"
        }
    ],
    "sg:phone":"+1 919 462 8058",
    "sg:postcode":"27513",
    "sg:province":"NC",
    "wof:name":"Two Guys & Power Washer Inc",
    "wof:placetype":"venue"
},
  "geometry": {"coordinates":[-78.803403,35.787663],"type":"Point"}
}