{
  "type": "Feature",
  "properties": {
    "addr:full":"601 Milner Dr Greensboro NC 27410",
    "addr:housenumber":"601",
    "addr:postcode":"27410",
    "addr:street":"Milner Dr",
    "iso:country":"US",
    "sg:address":"601 Milner Dr",
    "sg:city":"Greensboro",
    "sg:classifiers":[
        {
            "category":"Restaurant",
            "type":"Food & Drink"
        }
    ],
    "sg:phone":"+1 336 855 8783",
    "sg:postcode":"27410",
    "sg:province":"NC",
    "wof:name":"J & S Cafeteria",
    "wof:placetype":"venue"
},
  "geometry": {"coordinates":[-79.886912,36.086988],"type":"Point"}
}