{
  "type": "Feature",
  "properties": {
    "addr:full":"9117 Heathsville Rd Enfield NC 27823",
    "addr:housenumber":"9117",
    "addr:postcode":"27823",
    "addr:street":"Heathsville Rd",
    "iso:country":"US",
    "sg:address":"9117 Heathsville Rd",
    "sg:city":"Enfield",
    "sg:classifiers":[
        {
            "category":"Farming",
            "subcategory":"Farm",
            "type":"Manufacturing & Wholesale Goods"
        }
    ],
    "sg:phone":"+1 252 445 2304",
    "sg:postcode":"27823",
    "sg:province":"NC",
    "sg:tags":[
        "crop",
        "general"
    ],
    "wof:name":"C W Locke & Sons Inc",
    "wof:placetype":"venue"
},
  "geometry": {"coordinates":[-77.732421,36.214846],"type":"Point"}
}