{
  "type": "Feature",
  "properties": {
    "iso:country":"US",
    "sg:address":"2301 Narrawood St",
    "sg:city":"Raleigh",
    "sg:classifiers":[
        {
            "category":"Professional",
            "subcategory":"Management & Consulting",
            "type":"Services"
        }
    ],
    "sg:phone":"+1 919 781 4862",
    "sg:postcode":"27614",
    "sg:province":"NC",
    "sg:tags":[
        "consultant",
        "hospital",
        "health"
    ],
    "wof:name":"Rtp Medical Gas Consultants",
    "wof:placetype":"venue"
},
  "geometry": {"coordinates":[-78.56627899999999,35.950497],"type":"Point"}
}