{
  "type": "Feature",
  "properties": {
    "iso:country":"US",
    "sg:address":"1222 Long Branch Rd",
    "sg:city":"Grover",
    "sg:classifiers":[
        {
            "category":"Organizations",
            "subcategory":"Religious Organization",
            "type":"Services"
        }
    ],
    "sg:phone":"+1 704 937 7961",
    "sg:postcode":"28073",
    "sg:province":"NC",
    "wof:name":"Allen Memorial Baptist Church",
    "wof:placetype":"venue"
},
  "geometry": {"coordinates":[-81.447357,35.199274],"type":"Point"}
}