{
  "type": "Feature",
  "properties": {
    "addr:full":"3251 State Hwy 87 S Sanford NC 27332",
    "addr:housenumber":"3251",
    "addr:postcode":"27332",
    "addr:street":"State Hwy 87 S",
    "iso:country":"US",
    "sg:address":"3251 State Hwy 87 S",
    "sg:city":"Sanford",
    "sg:classifiers":[
        {
            "category":"Home & Garden",
            "subcategory":"Mobile Homes",
            "type":"Retail Goods"
        }
    ],
    "sg:phone":"+1 919 776 2477",
    "sg:postcode":"27332",
    "sg:province":"NC",
    "wof:name":"Factory Housing Outlet",
    "wof:placetype":"venue"
},
  "geometry": {"coordinates":[-79.128418,35.444897],"type":"Point"}
}