{
  "type": "Feature",
  "properties": {
    "iso:country":"US",
    "sg:address":"123 Sunset Dr",
    "sg:city":"Taylorsville",
    "sg:classifiers":[
        {
            "category":"Professional",
            "subcategory":"Management & Consulting",
            "type":"Services"
        }
    ],
    "sg:phone":"+1 828 632 3260",
    "sg:postcode":"28681",
    "sg:province":"NC",
    "sg:tags":[
        "retail",
        "direct",
        "sales"
    ],
    "wof:name":"Hubbard Clyde",
    "wof:placetype":"venue"
},
  "geometry": {"coordinates":[-81.18986,35.930654],"type":"Point"}
}