{
  "type": "Feature",
  "properties": {
    "iso:country":"US",
    "sg:address":"1514 Glenwood Ave",
    "sg:city":"Raleigh",
    "sg:classifiers":[
        {
            "category":"Professional",
            "type":"Services"
        },
        {
            "category":"Professional",
            "subcategory":"Advertising",
            "type":"Services"
        }
    ],
    "sg:phone":"+1 919 232 5080",
    "sg:postcode":"27608",
    "sg:province":"NC",
    "sg:tags":[
        "counselor"
    ],
    "wof:name":"Hardin & Bowles Adv",
    "wof:placetype":"venue"
},
  "geometry": {"coordinates":[-78.646029,35.800644],"type":"Point"}
}