{
  "type": "Feature",
  "properties": {
    "iso:country":"US",
    "sg:address":"600 Granville St",
    "sg:city":"Oxford",
    "sg:classifiers":[
        {
            "category":"Professional",
            "subcategory":"Accounting & Tax Preparation",
            "type":"Services"
        }
    ],
    "sg:phone":"+1 919 693 5704",
    "sg:postcode":"27565",
    "sg:province":"NC",
    "sg:tags":[
        "return",
        "filing"
    ],
    "wof:name":"H & R Block Tax Svc",
    "wof:placetype":"venue"
},
  "geometry": {"coordinates":[-78.58628899999999,36.302099],"type":"Point"}
}