{
  "type": "Feature",
  "properties": {
    "iso:country":"US",
    "sg:address":"2630 25th St NE",
    "sg:city":"Hickory",
    "sg:classifiers":[
        {
            "category":"Building & Trades",
            "subcategory":"Construction",
            "type":"Services"
        }
    ],
    "sg:phone":"+1 828 256 8320",
    "sg:postcode":"28601",
    "sg:province":"NC",
    "sg:tags":[
        "house"
    ],
    "wof:name":"J L Eckard Construction Co",
    "wof:placetype":"venue"
},
  "geometry": {"coordinates":[-81.282526,35.763236],"type":"Point"}
}