{
  "type": "Feature",
  "properties": {
    "iso:country":"US",
    "sg:address":"6833 Holts Store Rd",
    "sg:city":"Burlington",
    "sg:classifiers":[
        {
            "category":"Retail",
            "subcategory":"Repair Shop",
            "type":"Services"
        }
    ],
    "sg:phone":"+1   ",
    "sg:postcode":"27215",
    "sg:province":"NC",
    "wof:name":"Bescher & Associates",
    "wof:placetype":"venue"
},
  "geometry": {"coordinates":[-79.578581,36.000459],"type":"Point"}
}