{
  "type": "Feature",
  "properties": {
    "addr:full":"12113 Old Creedmoor Rd Raleigh NC 27613",
    "addr:housenumber":"12113",
    "addr:postcode":"27613",
    "addr:street":"Old Creedmoor Rd",
    "iso:country":"US",
    "sg:address":"12113 Old Creedmoor Rd",
    "sg:city":"Raleigh",
    "sg:classifiers":[
        {
            "category":"Retail",
            "subcategory":"Veterinary Services",
            "type":"Services"
        }
    ],
    "sg:phone":"+1 919 855 0084",
    "sg:postcode":"27613",
    "sg:province":"NC",
    "wof:name":"Szabo Muri Dvm",
    "wof:placetype":"venue"
},
  "geometry": {"coordinates":[-78.706463,35.964234],"type":"Point"}
}