{
  "type": "Feature",
  "properties": {
    "addr:full":"100 Ferncrest Ct Cary NC 27519",
    "addr:housenumber":"100",
    "addr:postcode":"27519",
    "addr:street":"Ferncrest Ct",
    "iso:country":"US",
    "sg:address":"100 Ferncrest Ct",
    "sg:city":"Cary",
    "sg:classifiers":[
        {
            "category":"Building & Trades",
            "subcategory":"Landscaping Services",
            "type":"Services"
        }
    ],
    "sg:phone":"+1 919 367 7779",
    "sg:postcode":"27519",
    "sg:province":"NC",
    "sg:tags":[
        "landscape",
        "contractor"
    ],
    "wof:name":"Artworks Landscaping & Design",
    "wof:placetype":"venue"
},
  "geometry": {"coordinates":[-78.87438899999999,35.790399],"type":"Point"}
}