{
  "type": "Feature",
  "properties": {
    "iso:country":"US",
    "sg:address":"108 Henderson St",
    "sg:city":"Chapel Hill",
    "sg:classifiers":[
        {
            "category":"Recreation",
            "type":"Entertainment"
        }
    ],
    "sg:phone":"+1 919 933 8252",
    "sg:postcode":"27514",
    "sg:province":"NC",
    "sg:tags":[
        "parlor",
        "billiard",
        "bar",
        "diva"
    ],
    "sg:website":"zogsbar.wordpress.com",
    "wof:name":"Zogs Pool",
    "wof:placetype":"venue"
},
  "geometry": {"coordinates":[-79.052902,35.9146],"type":"Point"}
}