{
  "type": "Feature",
  "properties": {
    "iso:country":"US",
    "sg:address":"3886 Green Point Dr",
    "sg:city":"Greensboro",
    "sg:classifiers":[
        {
            "category":"Social Services",
            "type":"Services"
        }
    ],
    "sg:phone":"+1   ",
    "sg:postcode":"27407",
    "sg:province":"NC",
    "sg:tags":[
        "organization",
        "religious"
    ],
    "wof:name":"Faith Hrvest Fellowship Church",
    "wof:placetype":"venue"
},
  "geometry": {"coordinates":[-79.85984999999999,36.040369],"type":"Point"}
}