{
  "type": "Feature",
  "properties": {
    "iso:country":"US",
    "sg:address":"502 Salisbury Ave",
    "sg:city":"Albemarle",
    "sg:classifiers":[
        {
            "category":"Professional",
            "type":"Services"
        }
    ],
    "sg:phone":"+1 704 983 6786",
    "sg:postcode":"28001",
    "sg:province":"NC",
    "sg:tags":[
        "establishment"
    ],
    "wof:name":"Paycom Inc",
    "wof:placetype":"venue"
},
  "geometry": {"coordinates":[-80.205686,35.362338],"type":"Point"}
}