{
  "type": "Feature",
  "properties": {
    "iso:country":"US",
    "sg:address":"1022 S Cox St",
    "sg:city":"Asheboro",
    "sg:classifiers":[
        {
            "category":"Shopping",
            "subcategory":"Beauty & Cosmetics",
            "type":"Retail Goods"
        }
    ],
    "sg:phone":"+1 336 625 6980",
    "sg:postcode":"27203",
    "sg:province":"NC",
    "sg:tags":[
        "toiletry",
        "perfume"
    ],
    "wof:name":"Beauticontrol",
    "wof:placetype":"venue"
},
  "geometry": {"coordinates":[-79.81316099999999,35.692513],"type":"Point"}
}