{
  "type": "Feature",
  "properties": {
    "addr:full":"400 Carbon City Rd Morganton NC 28655",
    "addr:housenumber":"400",
    "addr:postcode":"28655",
    "addr:street":"Carbon City Rd",
    "iso:country":"US",
    "sg:address":"400 Carbon City Rd",
    "sg:city":"Morganton",
    "sg:classifiers":[
        {
            "category":"Home & Garden",
            "subcategory":"Mobile Homes",
            "type":"Retail Goods"
        }
    ],
    "sg:phone":"+1 828 438 4030",
    "sg:postcode":"28655",
    "sg:province":"NC",
    "wof:name":"LCI Housing",
    "wof:placetype":"venue"
},
  "geometry": {"coordinates":[-81.72167,35.735942],"type":"Point"}
}