{
  "type": "Feature",
  "properties": {
    "addr:full":"1210B E Mountain St Kernersville NC 27284",
    "addr:housenumber":"1210b",
    "addr:postcode":"27284",
    "addr:street":"E Mountain St",
    "iso:country":"US",
    "sg:address":"1210B E Mountain St",
    "sg:city":"Kernersville",
    "sg:classifiers":[
        {
            "category":"Real Estate",
            "subcategory":"Real Estate Services",
            "type":"Services"
        },
        {
            "category":"Real Estate",
            "subcategory":"Real Estate Agent",
            "type":"Services"
        }
    ],
    "sg:phone":"+1 336 996 0717",
    "sg:postcode":"27284",
    "sg:province":"NC",
    "sg:tags":[
        "buyer",
        "broker"
    ],
    "sg:website":"http://www.realestatebook.com",
    "wof:name":"The Real Estate Book",
    "wof:placetype":"venue"
},
  "geometry": {"coordinates":[-80.04676600000001,36.111462],"type":"Point"}
}