{
  "type": "Feature",
  "properties": {
    "iso:country":"US",
    "sg:address":"559 Executive Pl",
    "sg:city":"Fayetteville",
    "sg:classifiers":[
        {
            "category":"Real Estate",
            "subcategory":"Surveying",
            "type":"Services"
        }
    ],
    "sg:phone":"+1 910 323 1977",
    "sg:postcode":"28305",
    "sg:province":"NC",
    "sg:tags":[
        "surveyor"
    ],
    "wof:name":"Haddock Roy J Surveyor PC",
    "wof:placetype":"venue"
},
  "geometry": {"coordinates":[-78.92389300000001,35.049487],"type":"Point"}
}