{
  "type": "Feature",
  "properties": {
    "addr:full":"2619 West Blvd Charlotte NC 28208",
    "addr:housenumber":"2619",
    "addr:postcode":"28208",
    "addr:street":"West Blvd",
    "iso:country":"US",
    "sg:address":"2619 West Blvd",
    "sg:city":"Charlotte",
    "sg:classifiers":[
        {
            "category":"Wholesale",
            "subcategory":"Hardware",
            "type":"Manufacturing & Wholesale Goods"
        },
        {
            "category":"Autos & Motor Vehicles",
            "subcategory":"Auto Supplies",
            "type":"Retail Goods"
        }
    ],
    "sg:phone":"+1 704 391 7474",
    "sg:postcode":"28208",
    "sg:province":"NC",
    "sg:tags":[
        "filter",
        "gas",
        "filtration",
        "equipment",
        "air"
    ],
    "sg:website":"www.bruceairfilter.com",
    "wof:name":"Bruce Air Filter Company",
    "wof:placetype":"venue"
},
  "geometry": {"coordinates":[-80.90579,35.210591],"type":"Point"}
}