{
  "type": "Feature",
  "properties": {
    "addr:full":"2314 Reichard St Durham NC 27705",
    "addr:housenumber":"2314",
    "addr:postcode":"27705",
    "addr:street":"Reichard St",
    "iso:country":"US",
    "sg:address":"2314 Reichard St",
    "sg:city":"Durham",
    "sg:classifiers":[
        {
            "category":"Home & Garden",
            "subcategory":"Furniture",
            "type":"Retail Goods"
        }
    ],
    "sg:phone":"+1 919 620 8010",
    "sg:postcode":"27705",
    "sg:province":"NC",
    "wof:name":"Hometex Furnishing Inc",
    "wof:placetype":"venue"
},
  "geometry": {"coordinates":[-78.93057399999999,36.029639],"type":"Point"}
}