{
  "type": "Feature",
  "properties": {
    "addr:full":"221 E Main St Battleboro NC 27825",
    "addr:housenumber":"221",
    "addr:postcode":"27825",
    "addr:street":"E Main St",
    "iso:country":"US",
    "sg:address":"221 E Main St",
    "sg:city":"Battleboro",
    "sg:classifiers":[
        {
            "category":"Food & Beverages",
            "subcategory":"Groceries & Convenience Stores",
            "type":"Retail Goods"
        }
    ],
    "sg:phone":"+1 252 985 5851",
    "sg:postcode":"27825",
    "sg:province":"NC",
    "sg:tags":[
        "grocer"
    ],
    "wof:name":"A & P Food Store",
    "wof:placetype":"venue"
},
  "geometry": {"coordinates":[-77.162851,35.835408],"type":"Point"}
}