{
  "type": "Feature",
  "properties": {
    "iso:country":"US",
    "sg:address":"4420 State Hwy 705",
    "sg:city":"Robbins",
    "sg:classifiers":[
        {
            "category":"Organizations",
            "subcategory":"Religious Organization",
            "type":"Services"
        }
    ],
    "sg:phone":"+1   ",
    "sg:postcode":"27325",
    "sg:province":"NC",
    "wof:name":"Church of God of Prophecy",
    "wof:placetype":"venue"
},
  "geometry": {"coordinates":[-79.616975,35.462653],"type":"Point"}
}