{
  "type": "Feature",
  "properties": {
    "addr:full":"21025 Catawba Ave Cornelius NC 28031",
    "addr:housenumber":"21025",
    "addr:postcode":"28031",
    "addr:street":"Catawba Ave",
    "iso:country":"US",
    "sg:address":"21025 Catawba Ave",
    "sg:city":"Cornelius",
    "sg:classifiers":[
        {
            "category":"Real Estate",
            "subcategory":"Real Estate Services",
            "type":"Services"
        },
        {
            "category":"Real Estate",
            "subcategory":"Real Estate Agent",
            "type":"Services"
        }
    ],
    "sg:phone":"+1 704 655 0586",
    "sg:postcode":"28031",
    "sg:province":"NC",
    "sg:tags":[
        "buyer",
        "broker"
    ],
    "wof:name":"Ivester Jackson",
    "wof:placetype":"venue"
},
  "geometry": {"coordinates":[-80.86607600000001,35.48351],"type":"Point"}
}