{
  "type": "Feature",
  "properties": {
    "addr:full":"3299 Christy Rd Hudson NC 28638",
    "addr:housenumber":"3299",
    "addr:postcode":"28638",
    "addr:street":"Christy Rd",
    "iso:country":"US",
    "sg:address":"3299 Christy Rd",
    "sg:city":"Hudson",
    "sg:classifiers":[
        {
            "category":"Retail",
            "subcategory":"Auto Repair",
            "type":"Services"
        }
    ],
    "sg:phone":"+1 828 728 2441",
    "sg:postcode":"28638",
    "sg:province":"NC",
    "sg:tags":[
        "repairing",
        "automobile"
    ],
    "wof:name":"Ekard's Garage",
    "wof:placetype":"venue"
},
  "geometry": {"coordinates":[-81.44805599999999,35.848475],"type":"Point"}
}