{
  "type": "Feature",
  "properties": {
    "addr:full":"426 Camelia Dr Washington NC 27889",
    "addr:housenumber":"426",
    "addr:postcode":"27889",
    "addr:street":"Camelia Dr",
    "iso:country":"US",
    "sg:address":"426 Camelia Dr",
    "sg:city":"Washington",
    "sg:classifiers":[
        {
            "category":"Professional",
            "type":"Services"
        }
    ],
    "sg:phone":"+1 252 946 4768",
    "sg:postcode":"27889",
    "sg:province":"NC",
    "wof:name":"John T Webster",
    "wof:placetype":"venue"
},
  "geometry": {"coordinates":[-77.026995,35.550385],"type":"Point"}
}