{
  "type": "Feature",
  "properties": {
    "iso:country":"US",
    "sg:address":"505 E Parker Rd",
    "sg:city":"Morganton",
    "sg:classifiers":[
        {
            "category":"Health Services",
            "subcategory":"Doctor",
            "type":"Services"
        }
    ],
    "sg:phone":"+1 828 437 5812",
    "sg:postcode":"28655",
    "sg:province":"NC",
    "sg:tags":[
        "physician",
        "surgeon"
    ],
    "wof:name":"Cardiology Associates",
    "wof:placetype":"venue"
},
  "geometry": {"coordinates":[-81.65364599999999,35.729688],"type":"Point"}
}