{
  "type": "Feature",
  "properties": {
    "addr:full":"116 N Person St Raleigh NC 27601",
    "addr:housenumber":"116",
    "addr:postcode":"27601",
    "addr:street":"N Person St",
    "iso:country":"US",
    "sg:address":"116 N Person St",
    "sg:city":"Raleigh",
    "sg:classifiers":[
        {
            "category":"Professional",
            "subcategory":"Lawyer & Legal Services",
            "type":"Services"
        }
    ],
    "sg:phone":"+1 919 836 5551",
    "sg:postcode":"27601",
    "sg:province":"NC",
    "sg:tags":[
        "attorney"
    ],
    "wof:name":"Steve Gugenheim PC Law Office",
    "wof:placetype":"venue"
},
  "geometry": {"coordinates":[-78.634654,35.782201],"type":"Point"}
}