{
  "type": "Feature",
  "properties": {
    "iso:country":"US",
    "sg:address":"3000 Northline Ave",
    "sg:city":"Greensboro",
    "sg:classifiers":[
        {
            "category":"Shopping",
            "subcategory":"Clothing, Apparel, & Fashions",
            "type":"Retail Goods"
        }
    ],
    "sg:phone":"+1 336 218 0268",
    "sg:postcode":"27410",
    "sg:province":"NC",
    "sg:tags":[
        "family"
    ],
    "sg:website":"www.oldnavy.com",
    "wof:name":"Old Navy",
    "wof:placetype":"venue"
},
  "geometry": {"coordinates":[-79.829444,36.087176],"type":"Point"}
}