{
  "type": "Feature",
  "properties": {
    "iso:country":"US",
    "sg:address":"614 Chief Martin St",
    "sg:city":"Madison",
    "sg:classifiers":[
        {
            "category":"Shopping",
            "subcategory":"Clothing, Apparel, & Fashions",
            "type":"Retail Goods"
        }
    ],
    "sg:phone":"+1 336 427 7200",
    "sg:postcode":"27025",
    "sg:province":"NC",
    "wof:name":"Khouri's Fashion",
    "wof:placetype":"venue"
},
  "geometry": {"coordinates":[-79.972431,36.393933],"type":"Point"}
}