{
  "type": "Feature",
  "properties": {
    "addr:full":"3315 Norman Blalock Rd Willow Spring NC 27592",
    "addr:housenumber":"3315",
    "addr:postcode":"27592",
    "addr:street":"Norman Blalock Rd",
    "iso:country":"US",
    "sg:address":"3315 Norman Blalock Rd",
    "sg:city":"Willow Spring",
    "sg:classifiers":[
        {
            "category":"Retail",
            "subcategory":"Auto Repair",
            "type":"Services"
        }
    ],
    "sg:phone":"+1   ",
    "sg:postcode":"27592",
    "sg:province":"NC",
    "sg:tags":[
        "automotive",
        "general",
        "exhaust"
    ],
    "wof:name":"Pearson Automotive",
    "wof:placetype":"venue"
},
  "geometry": {"coordinates":[-78.693782,35.601845],"type":"Point"}
}