{
  "type": "Feature",
  "properties": {
    "iso:country":"US",
    "sg:address":"105 Tiffany Ct",
    "sg:city":"Jacksonville",
    "sg:classifiers":[
        {
            "category":"Professional",
            "subcategory":"Accounting & Tax Preparation",
            "type":"Services"
        }
    ],
    "sg:phone":"+1   ",
    "sg:postcode":"28546",
    "sg:province":"NC",
    "wof:name":"McC Medical",
    "wof:placetype":"venue"
},
  "geometry": {"coordinates":[-77.36164100000001,34.749458],"type":"Point"}
}