{
  "type": "Feature",
  "properties": {
    "addr:full":"3804 Garden Ave Wilmington NC 28403",
    "addr:housenumber":"3804",
    "addr:postcode":"28403",
    "addr:street":"Garden Ave",
    "iso:country":"US",
    "sg:address":"3804 Garden Ave",
    "sg:city":"Wilmington",
    "sg:classifiers":[
        {
            "category":"Personal",
            "subcategory":"Beauty Salon",
            "type":"Services"
        }
    ],
    "sg:phone":"+1 910 793 2411",
    "sg:postcode":"28403",
    "sg:province":"NC",
    "sg:tags":[
        "shop"
    ],
    "wof:name":"A Sharper Image Hair Nail Slon",
    "wof:placetype":"venue"
},
  "geometry": {"coordinates":[-77.896652,34.218192],"type":"Point"}
}