{
  "type": "Feature",
  "properties": {
    "addr:full":"3940 Western Blvd Raleigh NC 27606",
    "addr:housenumber":"3940",
    "addr:postcode":"27606",
    "addr:street":"Western Blvd",
    "iso:country":"US",
    "sg:address":"3940 Western Blvd",
    "sg:city":"Raleigh",
    "sg:classifiers":[
        {
            "category":"Food & Beverages",
            "subcategory":"Bakery",
            "type":"Retail Goods"
        }
    ],
    "sg:phone":"+1 919 828 6518",
    "sg:postcode":"27606",
    "sg:province":"NC",
    "sg:tags":[
        "sandwich"
    ],
    "sg:website":"www.subway.com/",
    "wof:name":"Subway",
    "wof:placetype":"venue"
},
  "geometry": {"coordinates":[-78.692398,35.7845],"type":"Point"}
}