{
  "type": "Feature",
  "properties": {
    "iso:country":"US",
    "sg:address":"1680 S Main St",
    "sg:city":"Laurinburg",
    "sg:classifiers":[
        {
            "category":"Food & Beverages",
            "subcategory":"Groceries & Convenience Stores",
            "type":"Retail Goods"
        }
    ],
    "sg:phone":"+1 910 276 1222",
    "sg:postcode":"28352",
    "sg:province":"NC",
    "wof:name":"X Way Groceries",
    "wof:placetype":"venue"
},
  "geometry": {"coordinates":[-79.478343,34.753206],"type":"Point"}
}