{
  "type": "Feature",
  "properties": {
    "addr:full":"109 E 1st St Kill Devil Hills NC 27948",
    "addr:housenumber":"109",
    "addr:postcode":"27948",
    "addr:street":"E 1St St",
    "iso:country":"US",
    "sg:address":"109 E 1st St",
    "sg:city":"Kill Devil Hills",
    "sg:classifiers":[
        {
            "category":"Social Services",
            "subcategory":"Child Care",
            "type":"Services"
        }
    ],
    "sg:phone":"+1 252 441 3808",
    "sg:postcode":"27948",
    "sg:province":"NC",
    "wof:name":"Ferris Wheel Day Care",
    "wof:placetype":"venue"
},
  "geometry": {"coordinates":[-75.667795,36.029149],"type":"Point"}
}