{
  "type": "Feature",
  "properties": {
    "iso:country":"US",
    "sg:address":"9313 Tiger Lily Ln",
    "sg:city":"Charlotte",
    "sg:classifiers":[
        {
            "category":"Building & Trades",
            "subcategory":"Landscaping Services",
            "type":"Services"
        }
    ],
    "sg:phone":"+1 704 953 9034",
    "sg:postcode":"28215",
    "sg:province":"NC",
    "wof:name":"Touch of Grass Lawn Care",
    "wof:placetype":"venue"
},
  "geometry": {"coordinates":[-80.664333,35.230647],"type":"Point"}
}