{
  "type": "Feature",
  "properties": {
    "addr:full":"13325 S Point Blvd Charlotte NC 28273",
    "addr:housenumber":"13325",
    "addr:postcode":"28273",
    "addr:street":"S Point Blvd",
    "iso:country":"US",
    "sg:address":"13325 S Point Blvd",
    "sg:city":"Charlotte",
    "sg:classifiers":[
        {
            "category":"Professional",
            "type":"Services"
        }
    ],
    "sg:phone":"+1 704 587 2450",
    "sg:postcode":"28273",
    "sg:province":"NC",
    "sg:tags":[
        "establishment"
    ],
    "sg:website":"www.bobstgroup.com",
    "wof:name":"Bobst Group",
    "wof:placetype":"venue"
},
  "geometry": {"coordinates":[-80.95746699999999,35.108069],"type":"Point"}
}