{
  "type": "Feature",
  "properties": {
    "addr:full":"748 4th St SW Hickory NC 28602",
    "addr:housenumber":"748",
    "addr:postcode":"28602",
    "addr:street":"4Th St Sw",
    "iso:country":"US",
    "sg:address":"748 4th St SW",
    "sg:city":"Hickory",
    "sg:classifiers":[
        {
            "category":"Professional",
            "subcategory":"Accounting & Tax Preparation",
            "type":"Services"
        }
    ],
    "sg:phone":"+1 828 328 6064",
    "sg:postcode":"28602",
    "sg:province":"NC",
    "sg:tags":[
        "accountant"
    ],
    "wof:name":"Hickory Accounting & Tax Svc",
    "wof:placetype":"venue"
},
  "geometry": {"coordinates":[-81.345247,35.723669],"type":"Point"}
}