{
  "type": "Feature",
  "properties": {
    "iso:country":"US",
    "sg:address":"8927 J M Keynes Dr",
    "sg:city":"Charlotte",
    "sg:classifiers":[
        {
            "category":"Banks & Credit Unions",
            "subcategory":"Financial Services",
            "type":"Services"
        }
    ],
    "sg:phone":"+1 704 547 1998",
    "sg:postcode":"28262",
    "sg:province":"NC",
    "sg:tags":[
        "marketing",
        "sport",
        "licensing"
    ],
    "wof:name":"Motorsprts Decisions Group Inc",
    "wof:placetype":"venue"
},
  "geometry": {"coordinates":[-80.748198,35.309913],"type":"Point"}
}