{
  "type": "Feature",
  "properties": {
    "addr:full":"5306 State Hwy 72 W Lumberton NC 28360",
    "addr:housenumber":"5306",
    "addr:postcode":"28360",
    "addr:street":"State Hwy 72 W",
    "iso:country":"US",
    "sg:address":"5306 State Hwy 72 W",
    "sg:city":"Lumberton",
    "sg:classifiers":[
        {
            "category":"Professional",
            "subcategory":"Accounting & Tax Preparation",
            "type":"Services"
        }
    ],
    "sg:phone":"+1 910 739 2659",
    "sg:postcode":"28360",
    "sg:province":"NC",
    "sg:tags":[
        "accountant"
    ],
    "wof:name":"Griffin's Accounting Firm",
    "wof:placetype":"venue"
},
  "geometry": {"coordinates":[-79.127291,34.674845],"type":"Point"}
}