{
  "type": "Feature",
  "properties": {
    "iso:country":"US",
    "sg:address":"4122 Deepwood Cir",
    "sg:city":"Durham",
    "sg:classifiers":[
        {
            "category":"Education",
            "subcategory":"College",
            "type":"Public Place"
        }
    ],
    "sg:phone":"+1   ",
    "sg:postcode":"27707",
    "sg:province":"NC",
    "wof:name":"Lloyd Bailey",
    "wof:placetype":"venue"
},
  "geometry": {"coordinates":[-78.96066,35.952709],"type":"Point"}
}