{
  "type": "Feature",
  "properties": {
    "addr:full":"1076 Lillington Hwy Spring Lake NC 28390",
    "addr:housenumber":"1076",
    "addr:postcode":"28390",
    "addr:street":"Lillington Hwy",
    "iso:country":"US",
    "sg:address":"1076 Lillington Hwy",
    "sg:city":"Spring Lake",
    "sg:classifiers":[
        {
            "category":"Insurance",
            "subcategory":"Insurance Agent",
            "type":"Services"
        }
    ],
    "sg:phone":"+1 910 497 5154",
    "sg:postcode":"28390",
    "sg:province":"NC",
    "wof:name":"Abbott Auto Insurance",
    "wof:placetype":"venue"
},
  "geometry": {"coordinates":[-78.96471699999999,35.182036],"type":"Point"}
}