{
  "type": "Feature",
  "properties": {
    "addr:full":"601 W Main St Carrboro NC 27510",
    "addr:housenumber":"601",
    "addr:postcode":"27510",
    "addr:street":"W Main St",
    "iso:country":"US",
    "sg:address":"601 W Main St",
    "sg:city":"Carrboro",
    "sg:classifiers":[
        {
            "category":"Building & Trades",
            "subcategory":"Construction",
            "type":"Services"
        }
    ],
    "sg:phone":"+1 919 967 3753",
    "sg:postcode":"27510",
    "sg:province":"NC",
    "sg:tags":[
        "contractor"
    ],
    "wof:name":"Carrboro West Partners",
    "wof:placetype":"venue"
},
  "geometry": {"coordinates":[-79.078886,35.913012],"type":"Point"}
}