{
  "type": "Feature",
  "properties": {
    "iso:country":"US",
    "sg:address":"18 Old Barn Rd",
    "sg:city":"Hendersonville",
    "sg:classifiers":[
        {
            "category":"Building & Trades",
            "subcategory":"Construction",
            "type":"Services"
        }
    ],
    "sg:phone":"+1 828 697 6452",
    "sg:postcode":"28791",
    "sg:province":"NC",
    "sg:tags":[
        "restoration",
        "cleaning",
        "patio",
        "deck"
    ],
    "wof:name":"Blue Seal Pressure Wash",
    "wof:placetype":"venue"
},
  "geometry": {"coordinates":[-82.550804,35.343406],"type":"Point"}
}