{
  "type": "Feature",
  "properties": {
    "addr:full":"1612 Camden Rd Charlotte NC 28203",
    "addr:housenumber":"1612",
    "addr:postcode":"28203",
    "addr:street":"Camden Rd",
    "iso:country":"US",
    "sg:address":"1612 Camden Rd",
    "sg:city":"Charlotte",
    "sg:classifiers":[
        {
            "category":"Professional",
            "type":"Services"
        }
    ],
    "sg:phone":"+1 704 333 2088",
    "sg:postcode":"28203",
    "sg:province":"NC",
    "sg:tags":[
        "establishment"
    ],
    "wof:name":"Chicken Coup",
    "wof:placetype":"venue"
},
  "geometry": {"coordinates":[-80.857885,35.21385],"type":"Point"}
}