{
  "type": "Feature",
  "properties": {
    "iso:country":"US",
    "sg:address":"13342 Wesleyan Dr",
    "sg:city":"Laurinburg",
    "sg:classifiers":[
        {
            "category":"Airport",
            "type":"Transportation"
        }
    ],
    "sg:phone":"+1 910 844 3601",
    "sg:postcode":"28352",
    "sg:province":"NC",
    "sg:tags":[
        "aviation",
        "general"
    ],
    "wof:name":"Scotland Aero Services Inc",
    "wof:placetype":"venue"
},
  "geometry": {"coordinates":[-79.510068,34.754335],"type":"Point"}
}