{
  "type": "Feature",
  "properties": {
    "addr:full":"501 Parkwood Ln Goldsboro NC 27530",
    "addr:housenumber":"501",
    "addr:postcode":"27530",
    "addr:street":"Parkwood Ln",
    "iso:country":"US",
    "sg:address":"501 Parkwood Ln",
    "sg:city":"Goldsboro",
    "sg:classifiers":[
        {
            "category":"Professional",
            "subcategory":"Management & Consulting",
            "type":"Services"
        }
    ],
    "sg:phone":"+1   ",
    "sg:postcode":"27530",
    "sg:province":"NC",
    "sg:tags":[
        "business"
    ],
    "wof:name":"Quest Consulting LLC",
    "wof:placetype":"venue"
},
  "geometry": {"coordinates":[-78.09838499999999,35.414575],"type":"Point"}
}