{
  "type": "Feature",
  "properties": {
    "iso:country":"US",
    "sg:address":"186 Towerview Ct",
    "sg:city":"Cary",
    "sg:classifiers":[
        {
            "category":"Wholesale",
            "subcategory":"Electrical",
            "type":"Manufacturing & Wholesale Goods"
        }
    ],
    "sg:phone":"+1 919 460 0336",
    "sg:postcode":"27513",
    "sg:province":"NC",
    "sg:tags":[
        "equipment",
        "electronics",
        "consumer",
        "electric",
        "supply"
    ],
    "wof:name":"Womack Electric Supply Company",
    "wof:placetype":"venue"
},
  "geometry": {"coordinates":[-78.809922,35.800661],"type":"Point"}
}