{
  "type": "Feature",
  "properties": {
    "iso:country":"US",
    "sg:address":"231 Twin Oaks Rd",
    "sg:city":"Statesville",
    "sg:classifiers":[
        {
            "category":"Health Services",
            "subcategory":"Clinic",
            "type":"Services"
        }
    ],
    "sg:phone":"+1   ",
    "sg:postcode":"28625",
    "sg:province":"NC",
    "sg:tags":[
        "agency",
        "mental"
    ],
    "wof:name":"Twin Oaks",
    "wof:placetype":"venue"
},
  "geometry": {"coordinates":[-80.82206100000001,35.771029],"type":"Point"}
}