{
  "type": "Feature",
  "properties": {
    "addr:full":"1882 Dudley Shoals Rd Granite Falls NC 28630",
    "addr:housenumber":"1882",
    "addr:postcode":"28630",
    "addr:street":"Dudley Shoals Rd",
    "iso:country":"US",
    "sg:address":"1882 Dudley Shoals Rd",
    "sg:city":"Granite Falls",
    "sg:classifiers":[
        {
            "category":"Organizations",
            "subcategory":"Religious Organization",
            "type":"Services"
        }
    ],
    "sg:phone":"+1 828 396 7300",
    "sg:postcode":"28630",
    "sg:province":"NC",
    "wof:name":"Dudley Shoals Baptist Church",
    "wof:placetype":"venue"
},
  "geometry": {"coordinates":[-81.37179399999999,35.86324],"type":"Point"}
}