{
  "type": "Feature",
  "properties": {
    "addr:full":"13175 State Hwy 50 Holly Ridge NC 28445",
    "addr:housenumber":"13175",
    "addr:postcode":"28445",
    "addr:street":"State Hwy 50",
    "iso:country":"US",
    "sg:address":"13175 State Hwy 50",
    "sg:city":"Holly Ridge",
    "sg:classifiers":[
        {
            "category":"Organizations",
            "subcategory":"Community Association",
            "type":"Services"
        }
    ],
    "sg:phone":"+1 910 329 3541",
    "sg:postcode":"28445",
    "sg:province":"NC",
    "sg:tags":[
        "fraternal"
    ],
    "wof:name":"Loyal Order Of Moose",
    "wof:placetype":"venue"
},
  "geometry": {"coordinates":[-77.56388699999999,34.452084],"type":"Point"}
}