{
  "type": "Feature",
  "properties": {
    "iso:country":"US",
    "sg:address":"306 Pensacola Rd",
    "sg:city":"Burnsville",
    "sg:classifiers":[
        {
            "category":"Health Services",
            "subcategory":"Hospital",
            "type":"Services"
        }
    ],
    "sg:phone":"+1 828 682 2112",
    "sg:postcode":"28714",
    "sg:province":"NC",
    "sg:tags":[
        "specialty"
    ],
    "wof:name":"Blue Ridge Center",
    "wof:placetype":"venue"
},
  "geometry": {"coordinates":[-82.29045499999999,35.910849],"type":"Point"}
}