{
  "type": "Feature",
  "properties": {
    "iso:country":"US",
    "sg:address":"33 Main St",
    "sg:city":"Hayesville",
    "sg:classifiers":[
        {
            "category":"Government",
            "subcategory":"Office",
            "type":"Public Place"
        }
    ],
    "sg:phone":"+1 828 389 0089",
    "sg:postcode":"28904",
    "sg:province":"NC",
    "wof:name":"Clay County Commissioners Ofc",
    "wof:placetype":"venue"
},
  "geometry": {"coordinates":[-83.818305,35.045856],"type":"Point"}
}