{
  "type": "Feature",
  "properties": {
    "iso:country":"US",
    "sg:address":"9302 State Hwy 127",
    "sg:city":"Hickory",
    "sg:classifiers":[
        {
            "category":"Personal",
            "subcategory":"Beauty Salon",
            "type":"Services"
        }
    ],
    "sg:phone":"+1 828 495 3446",
    "sg:postcode":"28601",
    "sg:province":"NC",
    "wof:name":"Steele Magnolia",
    "wof:placetype":"venue"
},
  "geometry": {"coordinates":[-81.30669899999999,35.818482],"type":"Point"}
}