{
  "type": "Feature",
  "properties": {
    "addr:full":"13000 York Rd Charlotte NC 28278",
    "addr:housenumber":"13000",
    "addr:postcode":"28278",
    "addr:street":"York Rd",
    "iso:country":"US",
    "sg:address":"13000 York Rd",
    "sg:city":"Charlotte",
    "sg:classifiers":[
        {
            "category":"Autos & Motor Vehicles",
            "subcategory":"Boat Sales",
            "type":"Retail Goods"
        }
    ],
    "sg:phone":"+1 704 588 1020",
    "sg:postcode":"28278",
    "sg:province":"NC",
    "sg:tags":[
        "equipment",
        "marine",
        "supply"
    ],
    "wof:name":"West Marine",
    "wof:placetype":"venue"
},
  "geometry": {"coordinates":[-80.989886,35.102064],"type":"Point"}
}