{
  "type": "Feature",
  "properties": {
    "iso:country":"US",
    "sg:address":"222 Motor Rd",
    "sg:city":"Winston Salem",
    "sg:classifiers":[
        {
            "category":"Professional",
            "subcategory":"Lawyer & Legal Services",
            "type":"Services"
        }
    ],
    "sg:phone":"+1 336 767 1666",
    "sg:postcode":"27105",
    "sg:province":"NC",
    "wof:name":"Legal Select",
    "wof:placetype":"venue"
},
  "geometry": {"coordinates":[-80.25345,36.154606],"type":"Point"}
}