{
  "type": "Feature",
  "properties": {
    "iso:country":"US",
    "sg:address":"884 Great Egret Cir SW",
    "sg:city":"Sunset Beach",
    "sg:classifiers":[
        {
            "category":"Professional",
            "type":"Services"
        }
    ],
    "sg:phone":"+1 910 575 7932",
    "sg:postcode":"28468",
    "sg:province":"NC",
    "sg:tags":[
        "establishment"
    ],
    "wof:name":"Cox & Cox",
    "wof:placetype":"venue"
},
  "geometry": {"coordinates":[-78.51364700000001,33.916062],"type":"Point"}
}