{
  "type": "Feature",
  "properties": {
    "iso:country":"US",
    "sg:address":"5412 Apex Peakway",
    "sg:city":"Apex",
    "sg:classifiers":[
        {
            "category":"Restaurant",
            "type":"Food & Drink"
        }
    ],
    "sg:menulink":"http://www.allmenus.com/nc/white-oak/115724-quiznos-sub/menu/",
    "sg:phone":"+1 919 362 7827",
    "sg:postcode":"27502",
    "sg:province":"NC",
    "sg:tags":[
        "wrap",
        "american",
        "sandwich"
    ],
    "wof:name":"Quiznos Sub",
    "wof:placetype":"venue"
},
  "geometry": {"coordinates":[-78.866347,35.738096],"type":"Point"}
}