{
  "type": "Feature",
  "properties": {
    "iso:country":"US",
    "sg:address":"107 Main St",
    "sg:city":"Stovall",
    "sg:classifiers":[
        {
            "category":"Government",
            "subcategory":"Office",
            "type":"Public Place"
        }
    ],
    "sg:phone":"+1 919 693 4646",
    "sg:postcode":"27536",
    "sg:province":"NC",
    "sg:tags":[
        "city"
    ],
    "wof:name":"Stovall City Hall",
    "wof:placetype":"venue"
},
  "geometry": {"coordinates":[-78.393844,36.33787],"type":"Point"}
}