{
  "type": "Feature",
  "properties": {
    "addr:full":"10835 Independence Pointe Pkwy Matthews NC 28105",
    "addr:housenumber":"10835",
    "addr:postcode":"28105",
    "addr:street":"Independence Pointe Pkwy",
    "iso:country":"US",
    "sg:address":"10835 Independence Pointe Pkwy",
    "sg:city":"Matthews",
    "sg:classifiers":[
        {
            "category":"Manufacturing",
            "subcategory":"Printing",
            "type":"Manufacturing & Wholesale Goods"
        }
    ],
    "sg:phone":"+1 704 321 9692",
    "sg:postcode":"28105",
    "sg:province":"NC",
    "sg:tags":[
        "screen",
        "commercial"
    ],
    "wof:name":"Altan Graphics Inc",
    "wof:placetype":"venue"
},
  "geometry": {"coordinates":[-80.706226,35.117989],"type":"Point"}
}