{
  "type": "Feature",
  "properties": {
    "addr:full":"950 Monroe St Carthage NC 28327",
    "addr:housenumber":"950",
    "addr:postcode":"28327",
    "addr:street":"Monroe St",
    "iso:country":"US",
    "sg:address":"950 Monroe St",
    "sg:city":"Carthage",
    "sg:classifiers":[
        {
            "category":"Restaurant",
            "type":"Food & Drink"
        }
    ],
    "sg:menulink":"http://www.allmenus.com/nc/carthage/211794-mcdonalds/menu/",
    "sg:phone":"+1 910 407 6007",
    "sg:postcode":"28327",
    "sg:province":"NC",
    "sg:tags":[
        "burger",
        "american"
    ],
    "wof:name":"McDonald's",
    "wof:placetype":"venue"
},
  "geometry": {"coordinates":[-79.40404700000001,35.340939],"type":"Point"}
}