{
  "type": "Feature",
  "properties": {
    "addr:full":"624 Matthews-Mint Hill Rd Matthews NC 28105",
    "addr:housenumber":"624",
    "addr:postcode":"28105",
    "addr:street":"Matthews-Mint Hill Rd",
    "iso:country":"US",
    "sg:address":"624 Matthews-Mint Hill Rd",
    "sg:city":"Matthews",
    "sg:classifiers":[
        {
            "category":"Professional",
            "type":"Services"
        }
    ],
    "sg:phone":"+1 704 841 8902",
    "sg:postcode":"28105",
    "sg:province":"NC",
    "sg:tags":[
        "establishment"
    ],
    "wof:name":"Carmel Brothers Inc",
    "wof:placetype":"venue"
},
  "geometry": {"coordinates":[-80.71316299999999,35.11759],"type":"Point"}
}