{
  "type": "Feature",
  "properties": {
    "addr:full":"303 S Main St Red Springs NC 28377",
    "addr:housenumber":"303",
    "addr:postcode":"28377",
    "addr:street":"S Main St",
    "iso:country":"US",
    "sg:address":"303 S Main St",
    "sg:city":"Red Springs",
    "sg:classifiers":[
        {
            "category":"Real Estate",
            "subcategory":"Surveying",
            "type":"Services"
        }
    ],
    "sg:phone":"+1   ",
    "sg:postcode":"28377",
    "sg:province":"NC",
    "wof:name":"J P McMillan Jr",
    "wof:placetype":"venue"
},
  "geometry": {"coordinates":[-79.183119,34.813496],"type":"Point"}
}