{
  "type": "Feature",
  "properties": {
    "iso:country":"US",
    "sg:address":"103 N Wall St",
    "sg:city":"Clinton",
    "sg:classifiers":[
        {
            "category":"Insurance",
            "subcategory":"Insurance Agent",
            "type":"Services"
        }
    ],
    "sg:phone":"+1 910 592 8811",
    "sg:postcode":"28328",
    "sg:province":"NC",
    "sg:website":"www.woodmen.com",
    "wof:name":"Woodmen Of The World Insurance",
    "wof:placetype":"venue"
},
  "geometry": {"coordinates":[-78.324532,34.997868],"type":"Point"}
}