{
  "type": "Feature",
  "properties": {
    "iso:country":"US",
    "sg:address":"4917 Waters Edge Dr",
    "sg:city":"Raleigh",
    "sg:classifiers":[
        {
            "category":"Manufacturing",
            "subcategory":"Printing",
            "type":"Manufacturing & Wholesale Goods"
        }
    ],
    "sg:phone":"+1 919 851 7861",
    "sg:postcode":"27606",
    "sg:province":"NC",
    "sg:tags":[
        "magazine"
    ],
    "wof:name":"Progressive Farmer Magazine",
    "wof:placetype":"venue"
},
  "geometry": {"coordinates":[-78.721816,35.773432],"type":"Point"}
}