{
  "type": "Feature",
  "properties": {
    "addr:full":"7839 Jackson School Rd Browns Summit NC 27214",
    "addr:housenumber":"7839",
    "addr:postcode":"27214",
    "addr:street":"Jackson School Rd",
    "iso:country":"US",
    "sg:address":"7839 Jackson School Rd",
    "sg:city":"Browns Summit",
    "sg:phone":"+1 336 656 7601",
    "sg:postcode":"27214",
    "sg:province":"NC",
    "sg:tags":[
        "farm",
        "tobacco"
    ],
    "wof:name":"Spencer Farm",
    "wof:placetype":"venue"
},
  "geometry": {"coordinates":[-79.65874700000001,36.214566],"type":"Point"}
}