{
  "type": "Feature",
  "properties": {
    "addr:full":"701 Back Swamp Rd Lumberton NC 28360",
    "addr:housenumber":"701",
    "addr:postcode":"28360",
    "addr:street":"Back Swamp Rd",
    "iso:country":"US",
    "sg:address":"701 Back Swamp Rd",
    "sg:city":"Lumberton",
    "sg:classifiers":[
        {
            "category":"Retail",
            "subcategory":"Auto Repair",
            "type":"Services"
        }
    ],
    "sg:phone":"+1 910 738 9303",
    "sg:postcode":"28360",
    "sg:province":"NC",
    "sg:tags":[
        "repairing",
        "automobile",
        "general"
    ],
    "wof:name":"John's Garage",
    "wof:placetype":"venue"
},
  "geometry": {"coordinates":[-79.13199400000001,34.601261],"type":"Point"}
}