{
  "type": "Feature",
  "properties": {
    "addr:full":"13015 Ballantyne Corporate Pl Charlotte NC 28277",
    "addr:housenumber":"13015",
    "addr:postcode":"28277",
    "addr:street":"Ballantyne Corporate Pl",
    "iso:country":"US",
    "sg:address":"13015 Ballantyne Corporate Pl",
    "sg:city":"Charlotte",
    "sg:classifiers":[
        {
            "category":"Travel",
            "subcategory":"Hotels & Motels",
            "type":"Entertainment"
        }
    ],
    "sg:phone":"+1 704 248 4000",
    "sg:postcode":"28277",
    "sg:province":"NC",
    "wof:name":"Lodge At Ballantyne Resort",
    "wof:placetype":"venue"
},
  "geometry": {"coordinates":[-80.84375799999999,35.055629],"type":"Point"}
}