{
  "type": "Feature",
  "properties": {
    "iso:country":"US",
    "sg:address":"120 N Main St",
    "sg:city":"Broadway",
    "sg:classifiers":[
        {
            "category":"Building & Trades",
            "subcategory":"Construction",
            "type":"Services"
        }
    ],
    "sg:phone":"+1 919 258 5087",
    "sg:postcode":"27505",
    "sg:province":"NC",
    "sg:tags":[
        "painter"
    ],
    "wof:name":"American Coating Svc Inc",
    "wof:placetype":"venue"
},
  "geometry": {"coordinates":[-79.055448,35.46131],"type":"Point"}
}