{
  "type": "Feature",
  "properties": {
    "iso:country":"US",
    "sg:address":"7211 Colleton Pl",
    "sg:city":"Charlotte",
    "sg:classifiers":[
        {
            "category":"Professional",
            "subcategory":"Business Services",
            "type":"Services"
        }
    ],
    "sg:phone":"+1   ",
    "sg:postcode":"28270",
    "sg:province":"NC",
    "wof:name":"Stolen Car Reports",
    "wof:placetype":"venue"
},
  "geometry": {"coordinates":[-80.768095,35.122188],"type":"Point"}
}