{
  "type": "Feature",
  "properties": {
    "addr:full":"3313 Donovan Pl Charlotte NC 28215",
    "addr:housenumber":"3313",
    "addr:postcode":"28215",
    "addr:street":"Donovan Pl",
    "iso:country":"US",
    "sg:address":"3313 Donovan Pl",
    "sg:city":"Charlotte",
    "sg:classifiers":[
        {
            "category":"Professional",
            "subcategory":"Management & Consulting",
            "type":"Services"
        }
    ],
    "sg:phone":"+1   ",
    "sg:postcode":"28215",
    "sg:province":"NC",
    "sg:tags":[
        "business"
    ],
    "wof:name":"Robert Brandon",
    "wof:placetype":"venue"
},
  "geometry": {"coordinates":[-80.763256,35.240443],"type":"Point"}
}