{
  "type": "Feature",
  "properties": {
    "addr:full":"437 Valley St Stanley NC 28164",
    "addr:housenumber":"437",
    "addr:postcode":"28164",
    "addr:street":"Valley St",
    "iso:country":"US",
    "sg:address":"437 Valley St",
    "sg:city":"Stanley",
    "sg:classifiers":[
        {
            "category":"Personal",
            "subcategory":"Beauty Salon",
            "type":"Services"
        }
    ],
    "sg:phone":"+1 704 263 2041",
    "sg:postcode":"28164",
    "sg:province":"NC",
    "wof:name":"Jo's Hair Care",
    "wof:placetype":"venue"
},
  "geometry": {"coordinates":[-81.102301,35.361656],"type":"Point"}
}