{
  "type": "Feature",
  "properties": {
    "addr:full":"2429 E Broad St Statesville NC 28625",
    "addr:housenumber":"2429",
    "addr:postcode":"28625",
    "addr:street":"E Broad St",
    "iso:country":"US",
    "sg:address":"2429 E Broad St",
    "sg:city":"Statesville",
    "sg:classifiers":[
        {
            "category":"Organizations",
            "subcategory":"Religious Organization",
            "type":"Services"
        }
    ],
    "sg:phone":"+1 704 878 2448",
    "sg:postcode":"28625",
    "sg:province":"NC",
    "sg:tags":[
        "church"
    ],
    "wof:name":"Seventh Day Adventist Church",
    "wof:placetype":"venue"
},
  "geometry": {"coordinates":[-80.85847200000001,35.790901],"type":"Point"}
}