{
  "type": "Feature",
  "properties": {
    "iso:country":"US",
    "sg:address":"117 Golfview Dr",
    "sg:city":"Advance",
    "sg:classifiers":[
        {
            "category":"Professional",
            "subcategory":"Business Services",
            "type":"Services"
        }
    ],
    "sg:phone":"+1   ",
    "sg:postcode":"27006",
    "sg:province":"NC",
    "sg:tags":[
        "interior",
        "decorator"
    ],
    "wof:name":"Guthries Decorating",
    "wof:placetype":"venue"
},
  "geometry": {"coordinates":[-80.424291,36.001505],"type":"Point"}
}