{
  "type": "Feature",
  "properties": {
    "addr:full":"2909 Phillips Ave Greensboro NC 27405",
    "addr:housenumber":"2909",
    "addr:postcode":"27405",
    "addr:street":"Phillips Ave",
    "iso:country":"US",
    "sg:address":"2909 Phillips Ave",
    "sg:city":"Greensboro",
    "sg:classifiers":[
        {
            "category":"Organizations",
            "subcategory":"Religious Organization",
            "type":"Services"
        }
    ],
    "sg:phone":"+1 336 375 3647",
    "sg:postcode":"27405",
    "sg:province":"NC",
    "wof:name":"Emmanuel United Church Christ",
    "wof:placetype":"venue"
},
  "geometry": {"coordinates":[-79.736208,36.094166],"type":"Point"}
}