{
  "type": "Feature",
  "properties": {
    "iso:country":"US",
    "sg:address":"5856 Farringdon Pl",
    "sg:city":"Raleigh",
    "sg:classifiers":[
        {
            "category":"Professional",
            "subcategory":"Lawyer & Legal Services",
            "type":"Services"
        }
    ],
    "sg:phone":"+1 919 872 4911",
    "sg:postcode":"27609",
    "sg:province":"NC",
    "sg:tags":[
        "attorney"
    ],
    "wof:name":"Rosenthal & Putterman",
    "wof:placetype":"venue"
},
  "geometry": {"coordinates":[-78.621707,35.861551],"type":"Point"}
}