{
  "type": "Feature",
  "properties": {
    "iso:country":"US",
    "sg:address":"301 N Hughes Blvd",
    "sg:city":"Elizabeth City",
    "sg:classifiers":[
        {
            "category":"Home & Garden",
            "subcategory":"Building Materials",
            "type":"Retail Goods"
        }
    ],
    "sg:phone":"+1 252 335 5454",
    "sg:postcode":"27909",
    "sg:province":"NC",
    "wof:name":"Allstate Building Supply",
    "wof:placetype":"venue"
},
  "geometry": {"coordinates":[-76.231118,36.306692],"type":"Point"}
}