{
  "type": "Feature",
  "properties": {
    "iso:country":"US",
    "sg:address":"110 Myrover St",
    "sg:city":"Fayetteville",
    "sg:classifiers":[
        {
            "category":"Travel",
            "subcategory":"Hotels & Motels",
            "type":"Entertainment"
        }
    ],
    "sg:phone":"+1 910 433 9123",
    "sg:postcode":"28305",
    "sg:province":"NC",
    "sg:tags":[
        "membership",
        "lodging"
    ],
    "wof:name":"Oxford House Lyon",
    "wof:placetype":"venue"
},
  "geometry": {"coordinates":[-78.895138,35.054956],"type":"Point"}
}