{
  "type": "Feature",
  "properties": {
    "addr:full":"15055 Andrew Jackson Hwy SW Fair Bluff NC 28439",
    "addr:housenumber":"15055",
    "addr:postcode":"28439",
    "addr:street":"Andrew Jackson Hwy Sw",
    "iso:country":"US",
    "sg:address":"15055 Andrew Jackson Hwy SW",
    "sg:city":"Fair Bluff",
    "sg:classifiers":[
        {
            "category":"Government",
            "subcategory":"Office",
            "type":"Public Place"
        }
    ],
    "sg:phone":"+1 910 649 7675",
    "sg:postcode":"28439",
    "sg:province":"NC",
    "sg:tags":[
        "state",
        "security"
    ],
    "wof:name":"National Guard",
    "wof:placetype":"venue"
},
  "geometry": {"coordinates":[-79.042209,34.300763],"type":"Point"}
}