{
  "type": "Feature",
  "properties": {
    "iso:country":"US",
    "sg:address":"2317 Sunset Ave",
    "sg:city":"Rocky Mount",
    "sg:classifiers":[
        {
            "category":"Professional",
            "subcategory":"Lawyer & Legal Services",
            "type":"Services"
        }
    ],
    "sg:phone":"+1 252 443 2111",
    "sg:postcode":"27804",
    "sg:province":"NC",
    "sg:tags":[
        "attorney"
    ],
    "sg:website":"www.lawmed.com",
    "wof:name":"Henson & Fuerst",
    "wof:placetype":"venue"
},
  "geometry": {"coordinates":[-77.825532,35.959236],"type":"Point"}
}