{
  "type": "Feature",
  "properties": {
    "addr:full":"1 Aspen Dr Greensboro NC 27409",
    "addr:housenumber":"1",
    "addr:postcode":"27409",
    "addr:street":"Aspen Dr",
    "iso:country":"US",
    "sg:address":"1 Aspen Dr",
    "sg:city":"Greensboro",
    "sg:classifiers":[
        {
            "category":"Real Estate",
            "subcategory":"Real Estate Operator",
            "type":"Services"
        }
    ],
    "sg:phone":"+1 336 292 6814",
    "sg:postcode":"27409",
    "sg:province":"NC",
    "sg:tags":[
        "building",
        "apartment"
    ],
    "wof:name":"Aimco",
    "wof:placetype":"venue"
},
  "geometry": {"coordinates":[-79.880505,36.072862],"type":"Point"}
}