{
  "type": "Feature",
  "properties": {
    "addr:full":"1608 Skyway Dr Monroe NC 28110",
    "addr:housenumber":"1608",
    "addr:postcode":"28110",
    "addr:street":"Skyway Dr",
    "iso:country":"US",
    "sg:address":"1608 Skyway Dr",
    "sg:city":"Monroe",
    "sg:classifiers":[
        {
            "category":"Shopping",
            "subcategory":"Musical Instruments",
            "type":"Retail Goods"
        }
    ],
    "sg:phone":"+1 704 283 2814",
    "sg:postcode":"28110",
    "sg:province":"NC",
    "wof:name":"Holloways Music Ctr",
    "wof:placetype":"venue"
},
  "geometry": {"coordinates":[-80.54876400000001,34.997529],"type":"Point"}
}