{
  "type": "Feature",
  "properties": {
    "iso:country":"US",
    "sg:address":"410 E Salisbury St",
    "sg:city":"Asheboro",
    "sg:classifiers":[
        {
            "category":"Retail",
            "subcategory":"Auto Repair",
            "type":"Services"
        }
    ],
    "sg:phone":"+1   ",
    "sg:postcode":"27203",
    "sg:province":"NC",
    "sg:tags":[
        "body",
        "general"
    ],
    "wof:name":"Allen Automotive & Imports",
    "wof:placetype":"venue"
},
  "geometry": {"coordinates":[-79.806252,35.706628],"type":"Point"}
}