{
  "type": "Feature",
  "properties": {
    "iso:country":"US",
    "sg:address":"346 3rd Ave NW",
    "sg:city":"Hickory",
    "sg:classifiers":[
        {
            "category":"Freight",
            "type":"Transportation"
        }
    ],
    "sg:phone":"+1 828 327 8622",
    "sg:postcode":"28601",
    "sg:province":"NC",
    "sg:tags":[
        "trucking"
    ],
    "wof:name":"Linzell Trucking LLC",
    "wof:placetype":"venue"
},
  "geometry": {"coordinates":[-81.343481,35.735719],"type":"Point"}
}