{
  "type": "Feature",
  "properties": {
    "iso:country":"US",
    "sg:address":"6356 Cephis Dr",
    "sg:city":"Clemmons",
    "sg:classifiers":[
        {
            "category":"Shopping",
            "subcategory":"Clothing, Apparel, & Fashions",
            "type":"Retail Goods"
        }
    ],
    "sg:phone":"+1 336 778 1553",
    "sg:postcode":"27012",
    "sg:province":"NC",
    "sg:tags":[
        "hosiery"
    ],
    "wof:name":"Speciality Dyeing & Finishing",
    "wof:placetype":"venue"
},
  "geometry": {"coordinates":[-80.38335600000001,36.029328],"type":"Point"}
}