{
  "type": "Feature",
  "properties": {
    "addr:full":"299 Woodsdale Rd Roxboro NC 27573",
    "addr:housenumber":"299",
    "addr:postcode":"27573",
    "addr:street":"Woodsdale Rd",
    "iso:country":"US",
    "sg:address":"299 Woodsdale Rd",
    "sg:city":"Roxboro",
    "sg:classifiers":[
        {
            "category":"Building & Trades",
            "subcategory":"Construction",
            "type":"Services"
        }
    ],
    "sg:phone":"+1 336 599 8068",
    "sg:postcode":"27573",
    "sg:province":"NC",
    "sg:tags":[
        "house"
    ],
    "wof:name":"Lacies Home Improvement",
    "wof:placetype":"venue"
},
  "geometry": {"coordinates":[-78.95774,36.448885],"type":"Point"}
}