{
  "type": "Feature",
  "properties": {
    "addr:full":"159 Ruth Ln Beaufort NC 28516",
    "addr:housenumber":"159",
    "addr:postcode":"28516",
    "addr:street":"Ruth Ln",
    "iso:country":"US",
    "sg:address":"159 Ruth Ln",
    "sg:city":"Beaufort",
    "sg:classifiers":[
        {
            "category":"Building & Trades",
            "subcategory":"Plumbing",
            "type":"Services"
        }
    ],
    "sg:phone":"+1 252 728 5999",
    "sg:postcode":"28516",
    "sg:province":"NC",
    "sg:tags":[
        "conditioning",
        "air",
        "system",
        "contractor"
    ],
    "wof:name":"Eastern Heating & Cooling",
    "wof:placetype":"venue"
},
  "geometry": {"coordinates":[-76.55471799999999,34.76206],"type":"Point"}
}