{
  "type": "Feature",
  "properties": {
    "iso:country":"US",
    "sg:address":"1132 Hampton Park Dr",
    "sg:city":"High Point",
    "sg:classifiers":[
        {
            "category":"Shopping",
            "subcategory":"Gifts & Souvenirs",
            "type":"Retail Goods"
        }
    ],
    "sg:phone":"+1 336 882 2405",
    "sg:postcode":"27265",
    "sg:province":"NC",
    "sg:tags":[
        "shop"
    ],
    "wof:name":"Beading Hearts & Gifts",
    "wof:placetype":"venue"
},
  "geometry": {"coordinates":[-80.027674,36.024466],"type":"Point"}
}