{
  "type": "Feature",
  "properties": {
    "addr:full":"3260 Randleman Rd Greensboro NC 27406",
    "addr:housenumber":"3260",
    "addr:postcode":"27406",
    "addr:street":"Randleman Rd",
    "iso:country":"US",
    "sg:address":"3260 Randleman Rd",
    "sg:city":"Greensboro",
    "sg:classifiers":[
        {
            "category":"Wholesale",
            "subcategory":"Auto Parts",
            "type":"Manufacturing & Wholesale Goods"
        }
    ],
    "sg:phone":"+1 336 379 8133",
    "sg:postcode":"27406",
    "sg:province":"NC",
    "sg:tags":[
        "equipment",
        "truck"
    ],
    "wof:name":"Rhino Of The Triad",
    "wof:placetype":"venue"
},
  "geometry": {"coordinates":[-79.80591,36.006477],"type":"Point"}
}