{
  "type": "Feature",
  "properties": {
    "addr:full":"450 Degatide Dr Murphy NC 28906",
    "addr:housenumber":"450",
    "addr:postcode":"28906",
    "addr:street":"Degatide Dr",
    "iso:country":"US",
    "sg:address":"450 Degatide Dr",
    "sg:city":"Murphy",
    "sg:classifiers":[
        {
            "category":"Building & Trades",
            "subcategory":"Construction",
            "type":"Services"
        }
    ],
    "sg:phone":"+1 828 644 5041",
    "sg:postcode":"28906",
    "sg:province":"NC",
    "sg:tags":[
        "carpentry",
        "carpenter",
        "contractor"
    ],
    "wof:name":"Victor Marrone Carpentry",
    "wof:placetype":"venue"
},
  "geometry": {"coordinates":[-84.14151099999999,35.065529],"type":"Point"}
}