{
  "type": "Feature",
  "properties": {
    "iso:country":"US",
    "sg:address":"106 Hispaniola Ln",
    "sg:city":"Surf City",
    "sg:classifiers":[
        {
            "category":"Professional",
            "type":"Services"
        }
    ],
    "sg:phone":"+1 910 328 3001",
    "sg:postcode":"28445",
    "sg:province":"NC",
    "sg:tags":[
        "establishment"
    ],
    "wof:name":"Alternative Target Marketing",
    "wof:placetype":"venue"
},
  "geometry": {"coordinates":[-77.593863,34.393904],"type":"Point"}
}