{
  "type": "Feature",
  "properties": {
    "addr:full":"7594 Shumont Dr Fayetteville NC 28314",
    "addr:housenumber":"7594",
    "addr:postcode":"28314",
    "addr:street":"Shumont Dr",
    "iso:country":"US",
    "sg:address":"7594 Shumont Dr",
    "sg:city":"Fayetteville",
    "sg:classifiers":[
        {
            "category":"Home & Garden",
            "subcategory":"Home Furnishings",
            "type":"Retail Goods"
        }
    ],
    "sg:phone":"+1 910 864 6781",
    "sg:postcode":"28314",
    "sg:province":"NC",
    "sg:tags":[
        "curtain",
        "made",
        "drapery"
    ],
    "wof:name":"Quality Draperies Workroom",
    "wof:placetype":"venue"
},
  "geometry": {"coordinates":[-79.053416,35.039063],"type":"Point"}
}