{
  "type": "Feature",
  "properties": {
    "addr:full":"739 S Main St King NC 27021",
    "addr:housenumber":"739",
    "addr:postcode":"27021",
    "addr:street":"S Main St",
    "iso:country":"US",
    "sg:address":"739 S Main St",
    "sg:city":"King",
    "sg:classifiers":[
        {
            "category":"Restaurant",
            "type":"Food & Drink"
        }
    ],
    "sg:menulink":"http://www.allmenus.com/nc/yadkin/191182-burger-king/menu/",
    "sg:phone":"+1 336 983 4836",
    "sg:postcode":"27021",
    "sg:province":"NC",
    "sg:tags":[
        "burger",
        "american"
    ],
    "wof:name":"Burger King",
    "wof:placetype":"venue"
},
  "geometry": {"coordinates":[-80.36166799999999,36.264421],"type":"Point"}
}