{
  "type": "Feature",
  "properties": {
    "addr:full":"1726 State Hwy 111 Goldsboro NC 27530",
    "addr:housenumber":"1726",
    "addr:postcode":"27530",
    "addr:street":"State Hwy 111",
    "iso:country":"US",
    "sg:address":"1726 State Hwy 111",
    "sg:city":"Goldsboro",
    "sg:classifiers":[
        {
            "category":"Real Estate",
            "subcategory":"Real Estate Operator",
            "type":"Services"
        }
    ],
    "sg:phone":"+1 919 734 1365",
    "sg:postcode":"27530",
    "sg:province":"NC",
    "sg:tags":[
        "property",
        "lessor"
    ],
    "wof:name":"Madge King",
    "wof:placetype":"venue"
},
  "geometry": {"coordinates":[-77.963539,35.428466],"type":"Point"}
}