{
  "type": "Feature",
  "properties": {
    "iso:country":"US",
    "sg:address":"1542 State Hwy 705",
    "sg:city":"Seagrove",
    "sg:classifiers":[
        {
            "category":"Professional",
            "subcategory":"Business Services",
            "type":"Services"
        }
    ],
    "sg:phone":"+1 336 879 3500",
    "sg:postcode":"27341",
    "sg:province":"NC",
    "sg:tags":[
        "auctioneer"
    ],
    "wof:name":"Reeder's Auction",
    "wof:placetype":"venue"
},
  "geometry": {"coordinates":[-79.756434,35.525064],"type":"Point"}
}