{
  "type": "Feature",
  "properties": {
    "iso:country":"US",
    "sg:address":"168 NE 1st St",
    "sg:city":"Oak Island",
    "sg:classifiers":[
        {
            "category":"Organizations",
            "subcategory":"Religious Organization",
            "type":"Services"
        }
    ],
    "sg:phone":"+1 910 278 6251",
    "sg:postcode":"28465",
    "sg:province":"NC",
    "sg:tags":[
        "church"
    ],
    "wof:name":"Jehovah's Witnesses",
    "wof:placetype":"venue"
},
  "geometry": {"coordinates":[-78.159649,33.920834],"type":"Point"}
}