{
  "type": "Feature",
  "properties": {
    "iso:country":"US",
    "sg:address":"417 Thomas Dr",
    "sg:city":"Jacksonville",
    "sg:classifiers":[
        {
            "category":"Health Services",
            "subcategory":"Medical Lab",
            "type":"Services"
        }
    ],
    "sg:phone":"+1   ",
    "sg:postcode":"28546",
    "sg:province":"NC",
    "sg:tags":[
        "laboratory",
        "dental"
    ],
    "wof:name":"Fine Dental Lab",
    "wof:placetype":"venue"
},
  "geometry": {"coordinates":[-77.374218,34.750535],"type":"Point"}
}