{
  "type": "Feature",
  "properties": {
    "addr:full":"1900 Teabrook Ct Raleigh NC 27610",
    "addr:postcode":"1900;27610",
    "addr:street":"Teabrook Ct",
    "iso:country":"US",
    "sg:address":"1900 Teabrook Ct",
    "sg:city":"Raleigh",
    "sg:classifiers":[
        {
            "category":"Building & Trades",
            "subcategory":"Cleaning & Sanitation",
            "type":"Services"
        }
    ],
    "sg:phone":"+1 919 231 5471",
    "sg:postcode":"27610",
    "sg:province":"NC",
    "sg:tags":[
        "janitor"
    ],
    "wof:name":"Unique Cleaning Svc",
    "wof:placetype":"venue"
},
  "geometry": {"coordinates":[-78.550754,35.752302],"type":"Point"}
}