{
  "type": "Feature",
  "properties": {
    "iso:country":"US",
    "sg:address":"1213 W Morehead St",
    "sg:city":"Charlotte",
    "sg:classifiers":[
        {
            "category":"Manufacturing",
            "subcategory":"Printing",
            "type":"Manufacturing & Wholesale Goods"
        }
    ],
    "sg:phone":"+1 704 342 3600",
    "sg:postcode":"28208",
    "sg:province":"NC",
    "sg:tags":[
        "work"
    ],
    "wof:name":"Document Binding Service Inc",
    "wof:placetype":"venue"
},
  "geometry": {"coordinates":[-80.86177000000001,35.229072],"type":"Point"}
}