{
  "type": "Feature",
  "properties": {
    "iso:country":"US",
    "sg:address":"8219 Andrew Jackson Hwy SW",
    "sg:city":"Cerro Gordo",
    "sg:classifiers":[
        {
            "category":"Retail",
            "subcategory":"Animal Services",
            "type":"Services"
        }
    ],
    "sg:phone":"+1 910 654 1940",
    "sg:postcode":"28430",
    "sg:province":"NC",
    "sg:tags":[
        "pet",
        "grooming",
        "washing"
    ],
    "wof:name":"Pampered Pets Grooming Shop",
    "wof:placetype":"venue"
},
  "geometry": {"coordinates":[-78.938137,34.331149],"type":"Point"}
}