{
  "type": "Feature",
  "properties": {
    "addr:full":"725 Lewis Rd Zebulon NC 27597",
    "addr:housenumber":"725",
    "addr:postcode":"27597",
    "addr:street":"Lewis Rd",
    "iso:country":"US",
    "sg:address":"725 Lewis Rd",
    "sg:city":"Zebulon",
    "sg:classifiers":[
        {
            "category":"Building & Trades",
            "subcategory":"Plumbing",
            "type":"Services"
        }
    ],
    "sg:phone":"+1 919 269 0532",
    "sg:postcode":"27597",
    "sg:province":"NC",
    "sg:tags":[
        "contractor"
    ],
    "wof:name":"Michael Griffin",
    "wof:placetype":"venue"
},
  "geometry": {"coordinates":[-78.24102499999999,35.863598],"type":"Point"}
}