{
  "type": "Feature",
  "properties": {
    "addr:full":"205 Highview Dr Youngsville NC 27517",
    "addr:housenumber":"205",
    "addr:postcode":"27517",
    "addr:street":"Highview Dr",
    "iso:country":"US",
    "sg:address":"205 Highview Dr",
    "sg:city":"Youngsville",
    "sg:classifiers":[
        {
            "category":"Building & Trades",
            "subcategory":"Construction",
            "type":"Services"
        }
    ],
    "sg:phone":"+1 919 570 0707",
    "sg:postcode":"27517",
    "sg:province":"NC",
    "sg:tags":[
        "contractor"
    ],
    "wof:name":"Elliott-STROUD LLC",
    "wof:placetype":"venue"
},
  "geometry": {"coordinates":[-79.003737,35.938051],"type":"Point"}
}