{
  "type": "Feature",
  "properties": {
    "addr:full":"2151 Glascock St Raleigh NC 27610",
    "addr:housenumber":"2151",
    "addr:postcode":"27610",
    "addr:street":"Glascock St",
    "iso:country":"US",
    "sg:address":"2151 Glascock St",
    "sg:city":"Raleigh",
    "sg:classifiers":[
        {
            "category":"Real Estate",
            "subcategory":"Real Estate Services",
            "type":"Services"
        },
        {
            "category":"Real Estate",
            "subcategory":"Real Estate Agent",
            "type":"Services"
        },
        {
            "category":"Real Estate",
            "subcategory":"Real Estate Operator",
            "type":"Services"
        }
    ],
    "sg:phone":"+1 919 833 9365",
    "sg:postcode":"27610",
    "sg:province":"NC",
    "sg:tags":[
        "apartment",
        "vacancy",
        "management",
        "listing",
        "rental",
        "finder"
    ],
    "wof:name":"Carolina Terrace Apartments",
    "wof:placetype":"venue"
},
  "geometry": {"coordinates":[-78.610573,35.792751],"type":"Point"}
}