{
  "type": "Feature",
  "properties": {
    "addr:full":"153 Red Top Rd Ferguson NC 28624",
    "addr:housenumber":"153",
    "addr:postcode":"28624",
    "addr:street":"Red Top Rd",
    "iso:country":"US",
    "sg:address":"153 Red Top Rd",
    "sg:city":"Ferguson",
    "sg:classifiers":[
        {
            "category":"Manufacturing",
            "subcategory":"Lumber",
            "type":"Manufacturing & Wholesale Goods"
        }
    ],
    "sg:phone":"+1 336 973 8729",
    "sg:postcode":"28624",
    "sg:province":"NC",
    "sg:tags":[
        "company",
        "logging"
    ],
    "wof:name":"Ray Church Logging",
    "wof:placetype":"venue"
},
  "geometry": {"coordinates":[-81.343593,36.134359],"type":"Point"}
}