{
  "type": "Feature",
  "properties": {
    "iso:country":"US",
    "sg:address":"3360 Jennings Rd",
    "sg:city":"Union Grove",
    "sg:classifiers":[
        {
            "category":"Building & Trades",
            "subcategory":"Plumbing",
            "type":"Services"
        }
    ],
    "sg:phone":"+1 704 539 4544",
    "sg:postcode":"28689",
    "sg:province":"NC",
    "sg:tags":[
        "tank",
        "septic"
    ],
    "wof:name":"A-1 Backhoe Svc",
    "wof:placetype":"venue"
},
  "geometry": {"coordinates":[-80.87930799999999,36.013884],"type":"Point"}
}