{
  "type": "Feature",
  "properties": {
    "iso:country":"US",
    "sg:address":"210 N Columbia St",
    "sg:city":"Chapel Hill",
    "sg:classifiers":[
        {
            "category":"Professional",
            "subcategory":"Accounting & Tax Preparation",
            "type":"Services"
        }
    ],
    "sg:phone":"+1 919 448 4417",
    "sg:postcode":"27514",
    "sg:province":"NC",
    "sg:tags":[
        "accountant"
    ],
    "sg:website":"www.zyczkiewicz.com",
    "wof:name":"Richard Zyczkiewicz CPA MBA",
    "wof:placetype":"venue"
},
  "geometry": {"coordinates":[-79.056375,35.915182],"type":"Point"}
}