{
  "type": "Feature",
  "properties": {
    "addr:full":"229 Snug Harbor Rd Hertford NC 27944",
    "addr:housenumber":"229",
    "addr:postcode":"27944",
    "addr:street":"Snug Harbor Rd",
    "iso:country":"US",
    "sg:address":"229 Snug Harbor Rd",
    "sg:city":"Hertford",
    "sg:classifiers":[
        {
            "category":"Building & Trades",
            "subcategory":"Plumbing",
            "type":"Services"
        }
    ],
    "sg:phone":"+1 252 426 1428",
    "sg:postcode":"27944",
    "sg:province":"NC",
    "sg:tags":[
        "contractor"
    ],
    "wof:name":"Jonathan Nixon Heating & Cool",
    "wof:placetype":"venue"
},
  "geometry": {"coordinates":[-76.488333,36.125847],"type":"Point"}
}