{
  "type": "Feature",
  "properties": {
    "iso:country":"US",
    "sg:address":"1714 Terry Rd",
    "sg:city":"Durham",
    "sg:classifiers":[
        {
            "category":"Real Estate",
            "subcategory":"Developer",
            "type":"Services"
        }
    ],
    "sg:phone":"+1 919 479 2072",
    "sg:postcode":"27712",
    "sg:province":"NC",
    "wof:name":"Piedmont Planning Associates",
    "wof:placetype":"venue"
},
  "geometry": {"coordinates":[-78.94008599999999,36.103933],"type":"Point"}
}