{
  "type": "Feature",
  "properties": {
    "addr:full":"3931 New Bern Ave Raleigh NC 27610",
    "addr:housenumber":"3931",
    "addr:postcode":"27610",
    "addr:street":"New Bern Ave",
    "iso:country":"US",
    "sg:address":"3931 New Bern Ave",
    "sg:city":"Raleigh",
    "sg:classifiers":[
        {
            "category":"Personal",
            "subcategory":"Beauty Salon",
            "type":"Services"
        }
    ],
    "sg:phone":"+1 919 231 9962",
    "sg:postcode":"27610",
    "sg:province":"NC",
    "sg:tags":[
        "shop",
        "make",
        "studio"
    ],
    "wof:name":"Trinity Center Of Permanent",
    "wof:placetype":"venue"
},
  "geometry": {"coordinates":[-78.56964499999999,35.799076],"type":"Point"}
}