{
  "type": "Feature",
  "properties": {
    "addr:full":"5135 Carolina Beach Rd Wilmington NC 28412",
    "addr:housenumber":"5135",
    "addr:postcode":"28412",
    "addr:street":"Carolina Beach Rd",
    "iso:country":"US",
    "sg:address":"5135 Carolina Beach Rd",
    "sg:city":"Wilmington",
    "sg:classifiers":[
        {
            "category":"Personal",
            "subcategory":"Beauty Salon",
            "type":"Services"
        }
    ],
    "sg:phone":"+1 910 794 4468",
    "sg:postcode":"28412",
    "sg:province":"NC",
    "wof:name":"Smart Style Family Hair Salon",
    "wof:placetype":"venue"
},
  "geometry": {"coordinates":[-77.897941,34.14498],"type":"Point"}
}