{
  "type": "Feature",
  "properties": {
    "iso:country":"US",
    "sg:address":"5335 US Hwy 220",
    "sg:city":"Summerfield",
    "sg:classifiers":[
        {
            "category":"Banks & Credit Unions",
            "subcategory":"Bank",
            "type":"Services"
        }
    ],
    "sg:phone":"+1 336 643 4173",
    "sg:postcode":"27358",
    "sg:province":"NC",
    "sg:tags":[
        "loan",
        "real estate"
    ],
    "wof:name":"Spantex Greensboro Plant",
    "wof:placetype":"venue"
},
  "geometry": {"coordinates":[-79.910968,36.221941],"type":"Point"}
}