{
  "type": "Feature",
  "properties": {
    "iso:country":"US",
    "sg:address":"110 Fields Dr",
    "sg:city":"Sanford",
    "sg:classifiers":[
        {
            "category":"Social Services",
            "type":"Services"
        }
    ],
    "sg:phone":"+1 919 718 5417",
    "sg:postcode":"27330",
    "sg:province":"NC",
    "sg:tags":[
        "instruction",
        "health",
        "care"
    ],
    "wof:name":"Community Home Care & Hospice",
    "wof:placetype":"venue"
},
  "geometry": {"coordinates":[-79.18695200000001,35.467892],"type":"Point"}
}