{
  "type": "Feature",
  "properties": {
    "addr:full":"816 E Arrowood Rd Ste C Charlotte NC 28217",
    "addr:housenumber":"816",
    "addr:postcode":"28217",
    "addr:street":"E Arrowood Rd Ste C",
    "iso:country":"US",
    "sg:address":"816 E Arrowood Rd Ste C",
    "sg:city":"Charlotte",
    "sg:classifiers":[
        {
            "category":"Professional",
            "subcategory":"Accounting & Tax Preparation",
            "type":"Services"
        },
        {
            "category":"Banks & Credit Unions",
            "subcategory":"Financial Services",
            "type":"Services"
        }
    ],
    "sg:phone":"+1 704 552 6863",
    "sg:postcode":"28217",
    "sg:province":"NC",
    "sg:tags":[
        "return",
        "preparation-business",
        "taxes-consultants",
        "loan",
        "representative",
        "alternative",
        "bookkeeping"
    ],
    "sg:website":"http://www.hrblock.com",
    "wof:name":"H & R Block",
    "wof:placetype":"venue"
},
  "geometry": {"coordinates":[-80.878777,35.137753],"type":"Point"}
}