{
  "type": "Feature",
  "properties": {
    "iso:country":"US",
    "sg:address":"445 Biltmore Ave",
    "sg:city":"Asheville",
    "sg:classifiers":[
        {
            "category":"Health Services",
            "subcategory":"Doctor",
            "type":"Services"
        }
    ],
    "sg:phone":"+1 828 258 0397",
    "sg:postcode":"28801",
    "sg:province":"NC",
    "sg:tags":[
        "medicine",
        "physician",
        "internal"
    ],
    "wof:name":"Kubitschek Kenneth R MD Facp",
    "wof:placetype":"venue"
},
  "geometry": {"coordinates":[-82.550309,35.579789],"type":"Point"}
}