{
  "type": "Feature",
  "properties": {
    "addr:full":"622 Kemswick Cir Gastonia NC 28054",
    "addr:housenumber":"622",
    "addr:postcode":"28054",
    "addr:street":"Kemswick Cir",
    "iso:country":"US",
    "sg:address":"622 Kemswick Cir",
    "sg:city":"Gastonia",
    "sg:classifiers":[
        {
            "category":"Building & Trades",
            "subcategory":"Plumbing",
            "type":"Services"
        }
    ],
    "sg:phone":"+1 704 861 8217",
    "sg:postcode":"28054",
    "sg:province":"NC",
    "sg:tags":[
        "contractor"
    ],
    "wof:name":"Dellinger Heating & Air",
    "wof:placetype":"venue"
},
  "geometry": {"coordinates":[-81.160471,35.254906],"type":"Point"}
}