{
  "type": "Feature",
  "properties": {
    "iso:country":"US",
    "sg:address":"303 Mc Daniels St",
    "sg:city":"Fairmont",
    "sg:classifiers":[
        {
            "category":"Retail",
            "subcategory":"Auto Repair",
            "type":"Services"
        }
    ],
    "sg:phone":"+1 910 628 0472",
    "sg:postcode":"28340",
    "sg:province":"NC",
    "sg:tags":[
        "wheel",
        "axle",
        "alignment"
    ],
    "wof:name":"Hayes Auto Alignment",
    "wof:placetype":"venue"
},
  "geometry": {"coordinates":[-79.11257999999999,34.499803],"type":"Point"}
}