{
  "type": "Feature",
  "properties": {
    "iso:country":"US",
    "sg:address":"11704 Man O War Trl",
    "sg:city":"Raleigh",
    "sg:classifiers":[
        {
            "category":"Arts & Performance",
            "subcategory":"Theater",
            "type":"Entertainment"
        }
    ],
    "sg:phone":"+1   ",
    "sg:postcode":"27613",
    "sg:province":"NC",
    "sg:tags":[
        "theatrical"
    ],
    "wof:name":"Kay Burwell Foundation",
    "wof:placetype":"venue"
},
  "geometry": {"coordinates":[-78.70972999999999,35.954667],"type":"Point"}
}