{
  "type": "Feature",
  "properties": {
    "addr:full":"2424 Erwin Rd Durham NC 27705",
    "addr:housenumber":"2424",
    "addr:postcode":"27705",
    "addr:street":"Erwin Rd",
    "iso:country":"US",
    "sg:address":"2424 Erwin Rd",
    "sg:city":"Durham",
    "sg:classifiers":[
        {
            "category":"Shopping",
            "subcategory":"Used Merchandise",
            "type":"Retail Goods"
        }
    ],
    "sg:phone":"+1 919 286 4597",
    "sg:postcode":"27705",
    "sg:province":"NC",
    "sg:tags":[
        "shop",
        "thrift"
    ],
    "wof:name":"Nearly New Shoppe",
    "wof:placetype":"venue"
},
  "geometry": {"coordinates":[-78.93937200000001,36.008448],"type":"Point"}
}