{
  "type": "Feature",
  "properties": {
    "iso:country":"US",
    "sg:address":"100 Jenkins Valley Rd",
    "sg:city":"Alexander",
    "sg:classifiers":[
        {
            "category":"Building & Trades",
            "subcategory":"Plumbing",
            "type":"Services"
        }
    ],
    "sg:phone":"+1 828 253 2370",
    "sg:postcode":"28701",
    "sg:province":"NC",
    "sg:tags":[
        "plumbing",
        "contractor"
    ],
    "wof:name":"All Pro Plumbing",
    "wof:placetype":"venue"
},
  "geometry": {"coordinates":[-82.633394,35.693002],"type":"Point"}
}