{
  "type": "Feature",
  "properties": {
    "addr:full":"796a Moye Blvd Greenville NC 27834",
    "addr:housenumber":"796a",
    "addr:postcode":"27834",
    "addr:street":"Moye Blvd",
    "iso:country":"US",
    "sg:address":"796a Moye Blvd",
    "sg:city":"Greenville",
    "sg:classifiers":[
        {
            "category":"Restaurant",
            "type":"Food & Drink"
        }
    ],
    "sg:menulink":"http://www.allmenus.com/nc/greenville/228794-jersey-mikes/menu/",
    "sg:phone":"+1 252 695 6161",
    "sg:postcode":"27834",
    "sg:province":"NC",
    "sg:tags":[
        "american",
        "sandwich"
    ],
    "wof:name":"Jersey Mike's",
    "wof:placetype":"venue"
},
  "geometry": {"coordinates":[-77.400918,35.607107],"type":"Point"}
}