{
  "type": "Feature",
  "properties": {
    "addr:full":"320 Old Buckeye Cove Rd Swannanoa NC 28778",
    "addr:housenumber":"320",
    "addr:postcode":"28778",
    "addr:street":"Old Buckeye Cove Rd",
    "iso:country":"US",
    "sg:address":"320 Old Buckeye Cove Rd",
    "sg:city":"Swannanoa",
    "sg:classifiers":[
        {
            "category":"Freight",
            "type":"Transportation"
        }
    ],
    "sg:phone":"+1 828 298 4235",
    "sg:postcode":"28778",
    "sg:province":"NC",
    "sg:tags":[
        "commercial",
        "storage"
    ],
    "wof:name":"John Wayne Inc Ministorage",
    "wof:placetype":"venue"
},
  "geometry": {"coordinates":[-82.421273,35.591742],"type":"Point"}
}