{
  "type": "Feature",
  "properties": {
    "addr:full":"1701 N Main St Roxboro NC 27573",
    "addr:housenumber":"1701",
    "addr:postcode":"27573",
    "addr:street":"N Main St",
    "iso:country":"US",
    "sg:address":"1701 N Main St",
    "sg:city":"Roxboro",
    "sg:classifiers":[
        {
            "category":"Organizations",
            "subcategory":"Religious Organization",
            "type":"Services"
        }
    ],
    "sg:phone":"+1   ",
    "sg:postcode":"27573",
    "sg:province":"NC",
    "wof:name":"Cavel United Methodist Church",
    "wof:placetype":"venue"
},
  "geometry": {"coordinates":[-78.965683,36.429916],"type":"Point"}
}