{
  "type": "Feature",
  "properties": {
    "iso:country":"US",
    "sg:address":"56 Clayton St",
    "sg:city":"Asheville",
    "sg:classifiers":[
        {
            "category":"Personal",
            "subcategory":"Beauty Salon",
            "type":"Services"
        }
    ],
    "sg:phone":"+1 828 258 0009",
    "sg:postcode":"28801",
    "sg:province":"NC",
    "wof:name":"Suzette's Salon-Salon",
    "wof:placetype":"venue"
},
  "geometry": {"coordinates":[-82.548451,35.601907],"type":"Point"}
}