{
  "type": "Feature",
  "properties": {
    "addr:full":"2611 Reynolds Dr Winston Salem NC 27104",
    "addr:housenumber":"2611",
    "addr:postcode":"27104",
    "addr:street":"Reynolds Dr",
    "iso:country":"US",
    "sg:address":"2611 Reynolds Dr",
    "sg:city":"Winston Salem",
    "sg:classifiers":[
        {
            "category":"Autos & Motor Vehicles",
            "subcategory":"Auto Supplies",
            "type":"Retail Goods"
        },
        {
            "category":"Manufacturing",
            "subcategory":"Motor Vehicles & Parts",
            "type":"Manufacturing & Wholesale Goods"
        }
    ],
    "sg:phone":"+1 336 761 0643",
    "sg:postcode":"27104",
    "sg:province":"NC",
    "sg:tags":[
        "engine",
        "head",
        "power",
        "f",
        "automobile",
        "rebuild",
        "high",
        "equipment",
        "build",
        "car",
        "performance",
        "racing"
    ],
    "wof:name":"Precision Performance Services",
    "wof:placetype":"venue"
},
  "geometry": {"coordinates":[-80.285117,36.101881],"type":"Point"}
}