{
  "type": "Feature",
  "properties": {
    "addr:full":"111 Minden Ln Raleigh NC 27607",
    "addr:housenumber":"111",
    "addr:postcode":"27607",
    "addr:street":"Minden Ln",
    "iso:country":"US",
    "sg:address":"111 Minden Ln",
    "sg:city":"Raleigh",
    "sg:classifiers":[
        {
            "category":"Shopping",
            "type":"Retail Goods"
        }
    ],
    "sg:phone":"+1 919 783 5711",
    "sg:postcode":"27607",
    "sg:province":"NC",
    "sg:tags":[
        "merchandise"
    ],
    "wof:name":"Successories of Carolina Inc",
    "wof:placetype":"venue"
},
  "geometry": {"coordinates":[-78.754098,35.797179],"type":"Point"}
}