{
  "type": "Feature",
  "properties": {
    "addr:full":"505 Hollyberry Ln Fayetteville NC 28314",
    "addr:housenumber":"505",
    "addr:postcode":"28314",
    "addr:street":"Hollyberry Ln",
    "iso:country":"US",
    "sg:address":"505 Hollyberry Ln",
    "sg:city":"Fayetteville",
    "sg:classifiers":[
        {
            "category":"Shopping",
            "subcategory":"Gifts & Souvenirs",
            "type":"Retail Goods"
        }
    ],
    "sg:phone":"+1 910 487 1977",
    "sg:postcode":"28314",
    "sg:province":"NC",
    "wof:name":"Fantasy Creations",
    "wof:placetype":"venue"
},
  "geometry": {"coordinates":[-79.00582,35.062697],"type":"Point"}
}