{
  "type": "Feature",
  "properties": {
    "addr:full":"829 Live Oak Rd Coats NC 27521",
    "addr:housenumber":"829",
    "addr:postcode":"oak;27521",
    "addr:street":"Live;Rd",
    "iso:country":"US",
    "sg:address":"829 Live Oak Rd",
    "sg:city":"Coats",
    "sg:classifiers":[
        {
            "category":"Building & Trades",
            "subcategory":"Landscaping Services",
            "type":"Services"
        }
    ],
    "sg:phone":"+1 910 897 4287",
    "sg:postcode":"27521",
    "sg:province":"NC",
    "sg:tags":[
        "landscape"
    ],
    "wof:name":"Tonys Landscaping",
    "wof:placetype":"venue"
},
  "geometry": {"coordinates":[-78.65453100000001,35.441783],"type":"Point"}
}