{
  "type": "Feature",
  "properties": {
    "iso:country":"US",
    "sg:address":"335 N Broad St",
    "sg:city":"Seagrove",
    "sg:classifiers":[
        {
            "category":"Retail",
            "subcategory":"Auto Repair",
            "type":"Services"
        }
    ],
    "sg:phone":"+1 336 873 7006",
    "sg:postcode":"27341",
    "sg:province":"NC",
    "sg:tags":[
        "repairing",
        "automobile"
    ],
    "wof:name":"Seagrove Motor Co",
    "wof:placetype":"venue"
},
  "geometry": {"coordinates":[-79.780653,35.544527],"type":"Point"}
}