{
  "type": "Feature",
  "properties": {
    "iso:country":"US",
    "sg:address":"952 Golf House Rd W",
    "sg:city":"Whitsett",
    "sg:classifiers":[
        {
            "category":"Professional",
            "subcategory":"Business Services",
            "type":"Services"
        }
    ],
    "sg:phone":"+1 336 446 6888",
    "sg:postcode":"27377",
    "sg:province":"NC",
    "sg:tags":[
        "interior",
        "consultant",
        "design",
        "decorator"
    ],
    "sg:website":"www.decoratingden.com",
    "wof:name":"Interiors By Decorating Den",
    "wof:placetype":"venue"
},
  "geometry": {"coordinates":[-79.60468299999999,36.066628],"type":"Point"}
}