{
  "type": "Feature",
  "properties": {
    "addr:full":"1529 S College Rd Wilmington NC 28403",
    "addr:housenumber":"1529",
    "addr:postcode":"28403",
    "addr:street":"S College Rd",
    "iso:country":"US",
    "sg:address":"1529 S College Rd",
    "sg:city":"Wilmington",
    "sg:classifiers":[
        {
            "category":"Retail",
            "subcategory":"Auto Repair",
            "type":"Services"
        }
    ],
    "sg:phone":"+1 910 791 4440",
    "sg:postcode":"28403",
    "sg:province":"NC",
    "sg:tags":[
        "general"
    ],
    "wof:name":"Custer Auto Repair Inc",
    "wof:placetype":"venue"
},
  "geometry": {"coordinates":[-77.886792,34.210339],"type":"Point"}
}