{
  "type": "Feature",
  "properties": {
    "iso:country":"US",
    "sg:address":"223 Third Creek Rd",
    "sg:city":"Statesville",
    "sg:classifiers":[
        {
            "category":"Building & Trades",
            "subcategory":"Electrical",
            "type":"Services"
        }
    ],
    "sg:phone":"+1 704 872 0605",
    "sg:postcode":"28677",
    "sg:province":"NC",
    "sg:tags":[
        "electrical",
        "contractor"
    ],
    "wof:name":"Earl Elmore Electric",
    "wof:placetype":"venue"
},
  "geometry": {"coordinates":[-80.838815,35.752649],"type":"Point"}
}