{
  "type": "Feature",
  "properties": {
    "addr:full":"1302 Walkup Ave Monroe NC 28110",
    "addr:housenumber":"1302",
    "addr:postcode":"28110",
    "addr:street":"Walkup Ave",
    "iso:country":"US",
    "sg:address":"1302 Walkup Ave",
    "sg:city":"Monroe",
    "sg:classifiers":[
        {
            "category":"Shopping",
            "subcategory":"Gifts & Souvenirs",
            "type":"Retail Goods"
        }
    ],
    "sg:phone":"+1 704 296 0777",
    "sg:postcode":"28110",
    "sg:province":"NC",
    "sg:tags":[
        "party",
        "production",
        "supply"
    ],
    "wof:name":"Blacktop Entrmt Pty Centl",
    "wof:placetype":"venue"
},
  "geometry": {"coordinates":[-80.532427,34.984236],"type":"Point"}
}