{
  "type": "Feature",
  "properties": {
    "addr:full":"4708 Carriage Drive Cir Charlotte NC 28205",
    "addr:housenumber":"4708",
    "addr:postcode":"28205",
    "addr:street":"Carriage Drive Cir",
    "iso:country":"US",
    "sg:address":"4708 Carriage Drive Cir",
    "sg:city":"Charlotte",
    "sg:classifiers":[
        {
            "category":"Organizations",
            "subcategory":"Non-profit Organization",
            "type":"Services"
        }
    ],
    "sg:phone":"+1 704 532 9022",
    "sg:postcode":"28205",
    "sg:province":"NC",
    "sg:tags":[
        "information",
        "alcoholism",
        "treatment"
    ],
    "wof:name":"Oxford House Carriage",
    "wof:placetype":"venue"
},
  "geometry": {"coordinates":[-80.763232,35.214542],"type":"Point"}
}