{
  "type": "Feature",
  "properties": {
    "iso:country":"US",
    "sg:address":"5411 Frieden Church Rd",
    "sg:city":"Mc Leansville",
    "sg:classifiers":[
        {
            "category":"Real Estate",
            "subcategory":"Real Estate Agent",
            "type":"Services"
        }
    ],
    "sg:phone":"+1 336 698 0673",
    "sg:postcode":"27301",
    "sg:province":"NC",
    "wof:name":"Forthright Real Estate",
    "wof:placetype":"venue"
},
  "geometry": {"coordinates":[-79.657871,36.10775],"type":"Point"}
}