{
  "type": "Feature",
  "properties": {
    "addr:full":"6035 State Hwy 32 S Plymouth NC 27962",
    "addr:housenumber":"6035",
    "addr:postcode":"27962",
    "addr:street":"State Hwy 32 S",
    "iso:country":"US",
    "sg:address":"6035 State Hwy 32 S",
    "sg:city":"Plymouth",
    "sg:phone":"+1 252 793 3681",
    "sg:postcode":"27962",
    "sg:province":"NC",
    "sg:tags":[
        "farm",
        "field",
        "crop"
    ],
    "wof:name":"Long Be Farm",
    "wof:placetype":"venue"
},
  "geometry": {"coordinates":[-76.731053,35.777185],"type":"Point"}
}