{
  "type": "Feature",
  "properties": {
    "iso:country":"US",
    "sg:address":"4120 Woodbury Ter NW",
    "sg:city":"Concord",
    "sg:classifiers":[
        {
            "category":"Building & Trades",
            "subcategory":"Cleaning & Sanitation",
            "type":"Services"
        }
    ],
    "sg:phone":"+1   ",
    "sg:postcode":"28027",
    "sg:province":"NC",
    "sg:tags":[
        "provides",
        "maintenance"
    ],
    "wof:name":"Big Johns Cleaning Service",
    "wof:placetype":"venue"
},
  "geometry": {"coordinates":[-80.646056,35.426774],"type":"Point"}
}