{
  "type": "Feature",
  "properties": {
    "iso:country":"US",
    "sg:address":"307 W Graham St",
    "sg:city":"Shelby",
    "sg:classifiers":[
        {
            "category":"Shopping",
            "subcategory":"Discount & Variety Stores",
            "type":"Retail Goods"
        }
    ],
    "sg:phone":"+1 704 481 0660",
    "sg:postcode":"28150",
    "sg:province":"NC",
    "wof:name":"Sam's Place",
    "wof:placetype":"venue"
},
  "geometry": {"coordinates":[-81.544512,35.289559],"type":"Point"}
}