{
  "type": "Feature",
  "properties": {
    "addr:full":"208 Avena Rd Hendersonville NC 28711",
    "addr:housenumber":"208",
    "addr:postcode":"28711",
    "addr:street":"Avena Rd",
    "iso:country":"US",
    "sg:address":"208 Avena Rd",
    "sg:city":"Hendersonville",
    "sg:classifiers":[
        {
            "category":"Organizations",
            "subcategory":"Religious Organization",
            "type":"Services"
        }
    ],
    "sg:phone":"+1 828 693 6901",
    "sg:postcode":"28711",
    "sg:province":"NC",
    "wof:name":"Immaculate Conception Church",
    "wof:placetype":"venue"
},
  "geometry": {"coordinates":[-82.311854,35.625254],"type":"Point"}
}