{
  "type": "Feature",
  "properties": {
    "addr:full":"11500 US Highway 15 501 N Chapel Hill NC 27517",
    "addr:housenumber":"501",
    "addr:postcode":"11500;27517",
    "addr:street":"Us Highway 15;N",
    "iso:country":"US",
    "sg:address":"11500 US Highway 15 501 N",
    "sg:city":"Chapel Hill",
    "sg:classifiers":[
        {
            "category":"Restaurant",
            "type":"Food & Drink"
        }
    ],
    "sg:phone":"+1 919 932 4440",
    "sg:postcode":"27517",
    "sg:province":"NC",
    "sg:tags":[
        "pizza"
    ],
    "wof:name":"Ciao Bella Pizzeria",
    "wof:placetype":"venue"
},
  "geometry": {"coordinates":[-79.062202,35.881199],"type":"Point"}
}