{
  "type": "Feature",
  "properties": {
    "addr:full":"3671 US Hwy 301 Rowland NC 28358",
    "addr:housenumber":"3671",
    "addr:postcode":"28358",
    "addr:street":"Us Hwy 301",
    "iso:country":"US",
    "sg:address":"3671 US Hwy 301",
    "sg:city":"Rowland",
    "sg:classifiers":[
        {
            "category":"Food & Beverages",
            "subcategory":"Groceries & Convenience Stores",
            "type":"Retail Goods"
        }
    ],
    "sg:phone":"+1 910 739 2336",
    "sg:postcode":"28358",
    "sg:province":"NC",
    "wof:name":"Hunt 301 Convenient Mart",
    "wof:placetype":"venue"
},
  "geometry": {"coordinates":[-79.16604100000001,34.580605],"type":"Point"}
}