{
  "type": "Feature",
  "properties": {
    "addr:full":"197 Deaverview Rd Asheville NC 28806",
    "addr:housenumber":"197",
    "addr:postcode":"28806",
    "addr:street":"Deaverview Rd",
    "iso:country":"US",
    "sg:address":"197 Deaverview Rd",
    "sg:city":"Asheville",
    "sg:classifiers":[
        {
            "category":"Building & Trades",
            "subcategory":"Construction",
            "type":"Services"
        }
    ],
    "sg:phone":"+1 828 350 0338",
    "sg:postcode":"28806",
    "sg:province":"NC",
    "sg:tags":[
        "painter"
    ],
    "wof:name":"Xtreme Metals & Signs Inc",
    "wof:placetype":"venue"
},
  "geometry": {"coordinates":[-82.618573,35.580905],"type":"Point"}
}