{
  "type": "Feature",
  "properties": {
    "iso:country":"US",
    "sg:address":"4733 Dawnridge Dr",
    "sg:city":"Charlotte",
    "sg:classifiers":[
        {
            "category":"Personal",
            "subcategory":"Beauty Salon",
            "type":"Services"
        }
    ],
    "sg:phone":"+1   ",
    "sg:postcode":"28226",
    "sg:province":"NC",
    "sg:tags":[
        "shop"
    ],
    "wof:name":"Cameo Skin Care Center",
    "wof:placetype":"venue"
},
  "geometry": {"coordinates":[-80.83340200000001,35.098792],"type":"Point"}
}