{
  "type": "Feature",
  "properties": {
    "addr:full":"401 E Main St Clayton NC 27520",
    "addr:housenumber":"401",
    "addr:postcode":"27520",
    "addr:street":"E Main St",
    "iso:country":"US",
    "sg:address":"401 E Main St",
    "sg:city":"Clayton",
    "sg:classifiers":[
        {
            "category":"Organizations",
            "subcategory":"Non-profit Organization",
            "type":"Services"
        }
    ],
    "sg:phone":"+1 919 359 9276",
    "sg:postcode":"27520",
    "sg:province":"NC",
    "sg:tags":[
        "human"
    ],
    "wof:name":"Feed His Sheep Ministries",
    "wof:placetype":"venue"
},
  "geometry": {"coordinates":[-78.456598,35.650557],"type":"Point"}
}