{
  "type": "Feature",
  "properties": {
    "iso:country":"US",
    "sg:address":"893 US Hwy 70 W",
    "sg:city":"Garner",
    "sg:classifiers":[
        {
            "category":"Professional",
            "type":"Services"
        }
    ],
    "sg:phone":"+1 919 662 9100",
    "sg:postcode":"27529",
    "sg:province":"NC",
    "wof:name":"Transworld Lighting Inc",
    "wof:placetype":"venue"
},
  "geometry": {"coordinates":[-78.628888,35.713661],"type":"Point"}
}