{
  "type": "Feature",
  "properties": {
    "addr:full":"325 Yadkin Valley Rd Advance NC 27006",
    "addr:housenumber":"325",
    "addr:postcode":"27006",
    "addr:street":"Yadkin Valley Rd",
    "iso:country":"US",
    "sg:address":"325 Yadkin Valley Rd",
    "sg:city":"Advance",
    "sg:classifiers":[
        {
            "category":"Building & Trades",
            "subcategory":"Construction",
            "type":"Services"
        }
    ],
    "sg:phone":"+1 336 998 5292",
    "sg:postcode":"27006",
    "sg:province":"NC",
    "sg:tags":[
        "contractor"
    ],
    "wof:name":"Snider and Associates",
    "wof:placetype":"venue"
},
  "geometry": {"coordinates":[-80.44406499999999,36.01649],"type":"Point"}
}