{
  "type": "Feature",
  "properties": {
    "iso:country":"US",
    "sg:address":"6131 Town Creek Rd",
    "sg:city":"Elm City",
    "sg:classifiers":[
        {
            "category":"Farming",
            "subcategory":"Livestock Farm",
            "type":"Manufacturing & Wholesale Goods"
        },
        {
            "category":"Recreation",
            "type":"Entertainment"
        }
    ],
    "sg:phone":"+1 252 243 3519",
    "sg:postcode":"27822",
    "sg:province":"NC",
    "sg:tags":[
        "equine",
        "stable"
    ],
    "wof:name":"Willowbranch Farms Inc",
    "wof:placetype":"venue"
},
  "geometry": {"coordinates":[-77.771407,35.752558],"type":"Point"}
}