{
  "type": "Feature",
  "properties": {
    "addr:full":"234 Thomas Rd Sanford NC 27330",
    "addr:housenumber":"234",
    "addr:postcode":"27330",
    "addr:street":"Thomas Rd",
    "iso:country":"US",
    "sg:address":"234 Thomas Rd",
    "sg:city":"Sanford",
    "sg:classifiers":[
        {
            "category":"Organizations",
            "subcategory":"Religious Organization",
            "type":"Services"
        }
    ],
    "sg:phone":"+1 919 258 6463",
    "sg:postcode":"27330",
    "sg:province":"NC",
    "sg:tags":[
        "church"
    ],
    "wof:name":"Catholic Church St Stevens",
    "wof:placetype":"venue"
},
  "geometry": {"coordinates":[-79.10915199999999,35.466305],"type":"Point"}
}