{
  "type": "Feature",
  "properties": {
    "addr:full":"2200 Silas Creek Pkwy SW Winston Salem NC 27103",
    "addr:housenumber":"2200",
    "addr:postcode":"27103",
    "addr:street":"Silas Creek Pkwy Sw",
    "iso:country":"US",
    "sg:address":"2200 Silas Creek Pkwy SW",
    "sg:city":"Winston Salem",
    "sg:classifiers":[
        {
            "category":"Insurance",
            "subcategory":"Insurance Agent",
            "type":"Services"
        }
    ],
    "sg:phone":"+1 336 773 1801",
    "sg:postcode":"27103",
    "sg:province":"NC",
    "wof:name":"Allstate",
    "wof:placetype":"venue"
},
  "geometry": {"coordinates":[-80.27601199999999,36.069886],"type":"Point"}
}