{
  "type": "Feature",
  "properties": {
    "addr:full":"945 Washburn Switch Rd Shelby NC 28150",
    "addr:housenumber":"945",
    "addr:postcode":"28150",
    "addr:street":"Washburn Switch Rd",
    "iso:country":"US",
    "sg:address":"945 Washburn Switch Rd",
    "sg:city":"Shelby",
    "sg:classifiers":[
        {
            "category":"Building & Trades",
            "subcategory":"Electrical",
            "type":"Services"
        }
    ],
    "sg:phone":"+1 704 434 7401",
    "sg:postcode":"28150",
    "sg:province":"NC",
    "sg:tags":[
        "electric",
        "contractor"
    ],
    "sg:website":"www.ies.com",
    "wof:name":"Davis Electrical Constructors",
    "wof:placetype":"venue"
},
  "geometry": {"coordinates":[-81.622567,35.325686],"type":"Point"}
}