{
  "type": "Feature",
  "properties": {
    "addr:full":"137 Douglas St Rocky Mount NC 27804",
    "addr:housenumber":"137",
    "addr:postcode":"27804",
    "addr:street":"Douglas St",
    "iso:country":"US",
    "sg:address":"137 Douglas St",
    "sg:city":"Rocky Mount",
    "sg:classifiers":[
        {
            "category":"Home & Garden",
            "subcategory":"Carpets & Floor Coverings",
            "type":"Retail Goods"
        }
    ],
    "sg:phone":"+1 252 937 2514",
    "sg:postcode":"27804",
    "sg:province":"NC",
    "wof:name":"Cunningham Floor Coverings",
    "wof:placetype":"venue"
},
  "geometry": {"coordinates":[-77.828836,35.976592],"type":"Point"}
}