{
  "type": "Feature",
  "properties": {
    "iso:country":"US",
    "sg:address":"3200 York Hwy",
    "sg:city":"Gastonia",
    "sg:classifiers":[
        {
            "category":"Manufacturing",
            "subcategory":"Textiles",
            "type":"Manufacturing & Wholesale Goods"
        }
    ],
    "sg:phone":"+1 704 864 4541",
    "sg:postcode":"28052",
    "sg:province":"NC",
    "sg:tags":[
        "thread"
    ],
    "wof:name":"American & Efird Inc",
    "wof:placetype":"venue"
},
  "geometry": {"coordinates":[-81.200329,35.222528],"type":"Point"}
}