{
  "type": "Feature",
  "properties": {
    "addr:full":"5816 Creedmoor Road Suite 205 Raleigh NC 27612",
    "addr:housenumber":"5816",
    "addr:postcode":"27612",
    "addr:street":"Creedmoor Road Suite 205",
    "iso:country":"US",
    "sg:address":"5816 Creedmoor Road Suite 205",
    "sg:city":"Raleigh",
    "sg:classifiers":[
        {
            "category":"Communications",
            "type":"Services"
        }
    ],
    "sg:phone":"+1 919 301 8406",
    "sg:postcode":"27612",
    "sg:province":"NC",
    "sg:tags":[
        "web",
        "design"
    ],
    "sg:website":"www.clickoptimize.com",
    "wof:name":"Click Optimize",
    "wof:placetype":"venue"
},
  "geometry": {"coordinates":[-78.68016900000001,35.862814],"type":"Point"}
}