{
  "type": "Feature",
  "properties": {
    "iso:country":"US",
    "sg:address":"1305 Surry Dr",
    "sg:city":"Greensboro",
    "sg:classifiers":[
        {
            "category":"Professional",
            "subcategory":"Advertising",
            "type":"Services"
        }
    ],
    "sg:phone":"+1 336 389 9939",
    "sg:postcode":"27408",
    "sg:province":"NC",
    "sg:tags":[
        "counselor"
    ],
    "wof:name":"Double Truck Inc",
    "wof:placetype":"venue"
},
  "geometry": {"coordinates":[-79.831699,36.098351],"type":"Point"}
}