{
  "type": "Feature",
  "properties": {
    "addr:full":"104 Fox Walk Path Garner NC 27529",
    "addr:housenumber":"104",
    "addr:postcode":"27529",
    "addr:street":"Fox Walk Path",
    "iso:country":"US",
    "sg:address":"104 Fox Walk Path",
    "sg:city":"Garner",
    "sg:classifiers":[
        {
            "category":"Building & Trades",
            "subcategory":"Construction",
            "type":"Services"
        }
    ],
    "sg:phone":"+1 919 772 7848",
    "sg:postcode":"27529",
    "sg:province":"NC",
    "sg:tags":[
        "general",
        "contractor"
    ],
    "wof:name":"Voss Construction",
    "wof:placetype":"venue"
},
  "geometry": {"coordinates":[-78.591487,35.683067],"type":"Point"}
}