{
  "type": "Feature",
  "properties": {
    "addr:full":"301 Cedar St Roanoke Rapids NC 27870",
    "addr:housenumber":"301",
    "addr:postcode":"27870",
    "addr:street":"Cedar St",
    "iso:country":"US",
    "sg:address":"301 Cedar St",
    "sg:city":"Roanoke Rapids",
    "sg:classifiers":[
        {
            "category":"Building & Trades",
            "subcategory":"Construction",
            "type":"Services"
        }
    ],
    "sg:phone":"+1 252 537 3950",
    "sg:postcode":"27870",
    "sg:province":"NC",
    "sg:tags":[
        "fire",
        "restoration",
        "damage"
    ],
    "wof:name":"A & W Restoration Inc",
    "wof:placetype":"venue"
},
  "geometry": {"coordinates":[-77.659232,36.470445],"type":"Point"}
}