{
  "type": "Feature",
  "properties": {
    "iso:country":"US",
    "sg:address":"1658 Gores Landing Rd SW",
    "sg:city":"Ocean Isle Beach",
    "sg:classifiers":[
        {
            "category":"Building & Trades",
            "subcategory":"Construction",
            "type":"Services"
        }
    ],
    "sg:phone":"+1 910 579 8007",
    "sg:postcode":"28469",
    "sg:province":"NC",
    "sg:tags":[
        "general",
        "contractor"
    ],
    "wof:name":"J C Ward Construction",
    "wof:placetype":"venue"
},
  "geometry": {"coordinates":[-78.420535,33.908001],"type":"Point"}
}