{
  "type": "Feature",
  "properties": {
    "addr:full":"135 Craven St Beaufort NC 28516",
    "addr:housenumber":"135",
    "addr:postcode":"28516",
    "addr:street":"Craven St",
    "iso:country":"US",
    "sg:address":"135 Craven St",
    "sg:city":"Beaufort",
    "sg:classifiers":[
        {
            "category":"Travel",
            "subcategory":"Hotels & Motels",
            "type":"Entertainment"
        }
    ],
    "sg:phone":"+1 252 728 5499",
    "sg:postcode":"28516",
    "sg:province":"NC",
    "sg:tags":[
        "breakfast",
        "accommodation",
        "bed"
    ],
    "sg:website":"www.langdonhouse.com",
    "wof:name":"Langdon House Bed & Breakfast",
    "wof:placetype":"venue"
},
  "geometry": {"coordinates":[-76.663723,34.717703],"type":"Point"}
}