{
  "type": "Feature",
  "properties": {
    "addr:full":"875 Walnut St Ste 320 Cary NC 27511",
    "addr:housenumber":"875",
    "addr:postcode":"27511",
    "addr:street":"Walnut St Ste 320",
    "iso:country":"US",
    "sg:address":"875 Walnut St Ste 320",
    "sg:city":"Cary",
    "sg:classifiers":[
        {
            "category":"Health Services",
            "subcategory":"Health Practitioner",
            "type":"Services"
        }
    ],
    "sg:phone":"+1 919 461 0730",
    "sg:postcode":"27511",
    "sg:province":"NC",
    "sg:tags":[
        "acupuncture"
    ],
    "sg:website":"www.acupuncturecenterofcary.com",
    "wof:name":"Acupuncture Center of Cary",
    "wof:placetype":"venue"
},
  "geometry": {"coordinates":[-78.766296,35.773998],"type":"Point"}
}