{
  "type": "Feature",
  "properties": {
    "addr:full":"1227 Porter Rd Greenville NC 27858",
    "addr:housenumber":"1227",
    "addr:postcode":"27858",
    "addr:street":"Porter Rd",
    "iso:country":"US",
    "sg:address":"1227 Porter Rd",
    "sg:city":"Greenville",
    "sg:classifiers":[
        {
            "category":"Professional",
            "type":"Services"
        }
    ],
    "sg:phone":"+1   ",
    "sg:postcode":"27858",
    "sg:province":"NC",
    "wof:name":"Stewards Handyman Service Inc",
    "wof:placetype":"venue"
},
  "geometry": {"coordinates":[-77.30121200000001,35.550007],"type":"Point"}
}