{
  "type": "Feature",
  "properties": {
    "iso:country":"US",
    "sg:address":"1060 Pine Lake Dr",
    "sg:city":"Winston Salem",
    "sg:classifiers":[
        {
            "category":"Manufacturing",
            "subcategory":"Printing",
            "type":"Manufacturing & Wholesale Goods"
        }
    ],
    "sg:phone":"+1 336 776 1060",
    "sg:postcode":"27105",
    "sg:province":"NC",
    "sg:tags":[
        "lithographic",
        "commercial"
    ],
    "wof:name":"Good Impressions Inc",
    "wof:placetype":"venue"
},
  "geometry": {"coordinates":[-80.256539,36.189536],"type":"Point"}
}