{
  "type": "Feature",
  "properties": {
    "addr:full":"4448 Bunnlevel Erwin Rd Erwin NC 28339",
    "addr:housenumber":"4448",
    "addr:postcode":"28339",
    "addr:street":"Bunnlevel Erwin Rd",
    "iso:country":"US",
    "sg:address":"4448 Bunnlevel Erwin Rd",
    "sg:city":"Erwin",
    "sg:classifiers":[
        {
            "category":"Organizations",
            "subcategory":"Religious Organization",
            "type":"Services"
        }
    ],
    "sg:phone":"+1   ",
    "sg:postcode":"28339",
    "sg:province":"NC",
    "wof:name":"Westwood Church of God P Ro",
    "wof:placetype":"venue"
},
  "geometry": {"coordinates":[-78.71028099999999,35.317592],"type":"Point"}
}