{
  "type": "Feature",
  "properties": {
    "addr:full":"2000 N New River Dr Topsail Beach NC 28445",
    "addr:housenumber":"2000",
    "addr:postcode":"28445",
    "addr:street":"N New River Dr",
    "iso:country":"US",
    "sg:address":"2000 N New River Dr",
    "sg:city":"Topsail Beach",
    "sg:classifiers":[
        {
            "category":"Restaurant",
            "type":"Food & Drink"
        }
    ],
    "sg:phone":"+1 910 328 2002",
    "sg:postcode":"28445",
    "sg:province":"NC",
    "wof:name":"Atlantis",
    "wof:placetype":"venue"
},
  "geometry": {"coordinates":[-77.512708,34.445806],"type":"Point"}
}