{
  "type": "Feature",
  "properties": {
    "addr:full":"4305 Scaup Ct Raleigh NC 27616",
    "addr:housenumber":"4305",
    "addr:postcode":"27616",
    "addr:street":"Scaup Ct",
    "iso:country":"US",
    "sg:address":"4305 Scaup Ct",
    "sg:city":"Raleigh",
    "sg:classifiers":[
        {
            "category":"Retail",
            "subcategory":"Laundry & Dry Cleaning",
            "type":"Services"
        }
    ],
    "sg:phone":"+1   ",
    "sg:postcode":"27616",
    "sg:province":"NC",
    "sg:tags":[
        "drycleaning",
        "plant"
    ],
    "wof:name":"Cordova George",
    "wof:placetype":"venue"
},
  "geometry": {"coordinates":[-78.493599,35.845083],"type":"Point"}
}