{
  "type": "Feature",
  "properties": {
    "addr:full":"911 W Ehringhaus St Elizabeth City NC 27909",
    "addr:housenumber":"911",
    "addr:postcode":"27909",
    "addr:street":"W Ehringhaus St",
    "iso:country":"US",
    "sg:address":"911 W Ehringhaus St",
    "sg:city":"Elizabeth City",
    "sg:classifiers":[
        {
            "category":"Personal",
            "subcategory":"Beauty Salon",
            "type":"Services"
        }
    ],
    "sg:phone":"+1 252 338 5024",
    "sg:postcode":"27909",
    "sg:province":"NC",
    "wof:name":"OCI Braids & Supplies",
    "wof:placetype":"venue"
},
  "geometry": {"coordinates":[-76.233113,36.295478],"type":"Point"}
}