{
  "type": "Feature",
  "properties": {
    "iso:country":"US",
    "sg:address":"37 Brickyard Rd",
    "sg:city":"Asheville",
    "sg:classifiers":[
        {
            "category":"Education",
            "subcategory":"School",
            "type":"Public Place"
        }
    ],
    "sg:phone":"+1 828 232 4272",
    "sg:postcode":"28806",
    "sg:province":"NC",
    "sg:tags":[
        "high",
        "middle",
        "elementary"
    ],
    "sg:website":"www.buncombe.k12.nc.us/ees",
    "wof:name":"Buncombe County Schools",
    "wof:placetype":"venue"
},
  "geometry": {"coordinates":[-82.594241,35.598417],"type":"Point"}
}