{
  "type": "Feature",
  "properties": {
    "iso:country":"US",
    "sg:address":"201 E Grover St",
    "sg:city":"Shelby",
    "sg:classifiers":[
        {
            "category":"Health Services",
            "subcategory":"Doctor",
            "type":"Services"
        }
    ],
    "sg:phone":"+1 704 487 3131",
    "sg:postcode":"28150",
    "sg:province":"NC",
    "sg:tags":[
        "physician",
        "surgeon"
    ],
    "wof:name":"Shelby Emergency Assoc",
    "wof:placetype":"venue"
},
  "geometry": {"coordinates":[-81.536579,35.301511],"type":"Point"}
}