{
  "type": "Feature",
  "properties": {
    "iso:country":"US",
    "sg:address":"14 Forest Lake Dr",
    "sg:city":"Jackson Springs",
    "sg:classifiers":[
        {
            "category":"Building & Trades",
            "subcategory":"Construction",
            "type":"Services"
        }
    ],
    "sg:phone":"+1 910 295 5926",
    "sg:postcode":"27281",
    "sg:province":"NC",
    "sg:tags":[
        "general",
        "contractor"
    ],
    "wof:name":"Dream Developers LLC",
    "wof:placetype":"venue"
},
  "geometry": {"coordinates":[-79.55826999999999,35.170445],"type":"Point"}
}