{
  "type": "Feature",
  "properties": {
    "addr:full":"508 W 8th St Roanoke Rapids NC 27870",
    "addr:housenumber":"508",
    "addr:postcode":"27870",
    "addr:street":"W 8Th St",
    "iso:country":"US",
    "sg:address":"508 W 8th St",
    "sg:city":"Roanoke Rapids",
    "sg:classifiers":[
        {
            "category":"Building & Trades",
            "subcategory":"Plumbing",
            "type":"Services"
        }
    ],
    "sg:phone":"+1 252 535 2665",
    "sg:postcode":"27870",
    "sg:province":"NC",
    "sg:tags":[
        "conditioning",
        "air",
        "system",
        "contractor"
    ],
    "wof:name":"Affordable Heating & Air Cond",
    "wof:placetype":"venue"
},
  "geometry": {"coordinates":[-77.66226,36.461577],"type":"Point"}
}