{
  "type": "Feature",
  "properties": {
    "iso:country":"US",
    "sg:address":"6829 Fillyaw Rd",
    "sg:city":"Fayetteville",
    "sg:classifiers":[
        {
            "category":"Professional",
            "subcategory":"Accounting & Tax Preparation",
            "type":"Services"
        }
    ],
    "sg:phone":"+1   ",
    "sg:postcode":"28303",
    "sg:province":"NC",
    "wof:name":"B At Ease Services Inc",
    "wof:placetype":"venue"
},
  "geometry": {"coordinates":[-78.99551200000001,35.105382],"type":"Point"}
}