{
  "type": "Feature",
  "properties": {
    "iso:country":"US",
    "sg:address":"6626 Riverwood Rd",
    "sg:city":"Walkertown",
    "sg:classifiers":[
        {
            "category":"Wholesale",
            "subcategory":"Durable Goods & Equipment",
            "type":"Manufacturing & Wholesale Goods"
        }
    ],
    "sg:phone":"+1 336 595 1044",
    "sg:postcode":"27051",
    "sg:province":"NC",
    "wof:name":"Klaus Tschrnko Intl Inc",
    "wof:placetype":"venue"
},
  "geometry": {"coordinates":[-80.123897,36.189122],"type":"Point"}
}