{
  "type": "Feature",
  "properties": {
    "addr:full":"108 Kilmer Ln Reidsville NC 27320",
    "addr:housenumber":"108",
    "addr:postcode":"27320",
    "addr:street":"Kilmer Ln",
    "iso:country":"US",
    "sg:address":"108 Kilmer Ln",
    "sg:city":"Reidsville",
    "sg:classifiers":[
        {
            "category":"Food & Beverages",
            "subcategory":"Specialty",
            "type":"Retail Goods"
        }
    ],
    "sg:phone":"+1 336 348 6962",
    "sg:postcode":"27320",
    "sg:province":"NC",
    "sg:tags":[
        "health",
        "diet"
    ],
    "wof:name":"Herbalife Distributors",
    "wof:placetype":"venue"
},
  "geometry": {"coordinates":[-79.70452899999999,36.400901],"type":"Point"}
}