{
  "type": "Feature",
  "properties": {
    "iso:country":"US",
    "sg:address":"4126 Lake Lynn Dr",
    "sg:city":"Raleigh",
    "sg:classifiers":[
        {
            "category":"Professional",
            "subcategory":"Testing Lab",
            "type":"Services"
        }
    ],
    "sg:phone":"+1 919 676 0025",
    "sg:postcode":"27613",
    "sg:province":"NC",
    "sg:tags":[
        "soil"
    ],
    "sg:website":"www.ksatinc.com",
    "wof:name":"KSAT",
    "wof:placetype":"venue"
},
  "geometry": {"coordinates":[-78.702921,35.878641],"type":"Point"}
}