{
  "type": "Feature",
  "properties": {
    "addr:full":"1518 Woodmere Dr Greensboro NC 27405",
    "addr:housenumber":"1518",
    "addr:postcode":"27405",
    "addr:street":"Woodmere Dr",
    "iso:country":"US",
    "sg:address":"1518 Woodmere Dr",
    "sg:city":"Greensboro",
    "sg:classifiers":[
        {
            "category":"Organizations",
            "subcategory":"Religious Organization",
            "type":"Services"
        }
    ],
    "sg:phone":"+1 336 574 0933",
    "sg:postcode":"27405",
    "sg:province":"NC",
    "sg:tags":[
        "church"
    ],
    "wof:name":"New Beginnings Cmnty Outreach",
    "wof:placetype":"venue"
},
  "geometry": {"coordinates":[-79.753198,36.095001],"type":"Point"}
}