{
  "type": "Feature",
  "properties": {
    "iso:country":"US",
    "sg:address":"105 McRae St",
    "sg:city":"Laurinburg",
    "sg:classifiers":[
        {
            "category":"Professional",
            "subcategory":"Business Services",
            "type":"Services"
        }
    ],
    "sg:phone":"+1   ",
    "sg:postcode":"28352",
    "sg:province":"NC",
    "wof:name":"Sandhills Mediation Center",
    "wof:placetype":"venue"
},
  "geometry": {"coordinates":[-79.46366999999999,34.772352],"type":"Point"}
}