{
  "type": "Feature",
  "properties": {
    "iso:country":"US",
    "sg:address":"1619 Garland Ave",
    "sg:city":"Gastonia",
    "sg:classifiers":[
        {
            "category":"Organizations",
            "subcategory":"Labor Organization",
            "type":"Services"
        }
    ],
    "sg:phone":"+1   ",
    "sg:postcode":"28052",
    "sg:province":"NC",
    "wof:name":"North Carolina Assn Letter-",
    "wof:placetype":"venue"
},
  "geometry": {"coordinates":[-81.215766,35.239826],"type":"Point"}
}