{
  "type": "Feature",
  "properties": {
    "addr:full":"61 Sequoyah Dr Highlands NC 28741",
    "addr:housenumber":"61",
    "addr:postcode":"28741",
    "addr:street":"Sequoyah Dr",
    "iso:country":"US",
    "sg:address":"61 Sequoyah Dr",
    "sg:city":"Highlands",
    "sg:classifiers":[
        {
            "category":"Travel",
            "subcategory":"Hotels & Motels",
            "type":"Entertainment"
        }
    ],
    "sg:phone":"+1 828 526 3889",
    "sg:postcode":"28741",
    "sg:province":"NC",
    "sg:tags":[
        "breakfast",
        "accommodation",
        "bed"
    ],
    "wof:name":"Toad Hall Bed & Breakfast",
    "wof:placetype":"venue"
},
  "geometry": {"coordinates":[-83.221648,35.068067],"type":"Point"}
}