{
  "type": "Feature",
  "properties": {
    "iso:country":"US",
    "sg:address":"210 Horse Shoe Ln",
    "sg:city":"Morganton",
    "sg:classifiers":[
        {
            "category":"Professional",
            "subcategory":"Business Services",
            "type":"Services"
        }
    ],
    "sg:phone":"+1   ",
    "sg:postcode":"28655",
    "sg:province":"NC",
    "wof:name":"Karst Enterprises Inc",
    "wof:placetype":"venue"
},
  "geometry": {"coordinates":[-81.731235,35.764852],"type":"Point"}
}