{
  "type": "Feature",
  "properties": {
    "addr:full":"3274 Wellons Blvd New Bern NC 28562",
    "addr:housenumber":"3274",
    "addr:postcode":"28562",
    "addr:street":"Wellons Blvd",
    "iso:country":"US",
    "sg:address":"3274 Wellons Blvd",
    "sg:city":"New Bern",
    "sg:classifiers":[
        {
            "category":"Shopping",
            "subcategory":"Clothing, Apparel, & Fashions",
            "type":"Retail Goods"
        }
    ],
    "sg:phone":"+1 252 634 1666",
    "sg:postcode":"28562",
    "sg:province":"NC",
    "sg:tags":[
        "alteration"
    ],
    "wof:name":"Pas Alterations",
    "wof:placetype":"venue"
},
  "geometry": {"coordinates":[-77.096357,35.103687],"type":"Point"}
}