{
  "type": "Feature",
  "properties": {
    "iso:country":"US",
    "sg:address":"3250 Green Park Cir",
    "sg:city":"Charlotte",
    "sg:classifiers":[
        {
            "category":"Shopping",
            "type":"Retail Goods"
        },
        {
            "category":"Professional",
            "subcategory":"Business Services",
            "type":"Services"
        }
    ],
    "sg:phone":"+1 704 329 8068",
    "sg:postcode":"28217",
    "sg:province":"NC",
    "sg:tags":[
        "equipment",
        "telephone",
        "supply"
    ],
    "wof:name":"Business Communications Inc",
    "wof:placetype":"venue"
},
  "geometry": {"coordinates":[-80.93351800000001,35.173125],"type":"Point"}
}