{
  "type": "Feature",
  "properties": {
    "addr:full":"116 W Central Ave Asheboro NC 27203",
    "addr:housenumber":"116",
    "addr:postcode":"27203",
    "addr:street":"W Central Ave",
    "iso:country":"US",
    "sg:address":"116 W Central Ave",
    "sg:city":"Asheboro",
    "sg:classifiers":[
        {
            "category":"Wholesale",
            "subcategory":"Hardware",
            "type":"Manufacturing & Wholesale Goods"
        }
    ],
    "sg:phone":"+1 336 672 0146",
    "sg:postcode":"27203",
    "sg:province":"NC",
    "wof:name":"C C Dickson Co",
    "wof:placetype":"venue"
},
  "geometry": {"coordinates":[-79.80938399999999,35.75416],"type":"Point"}
}