{
  "type": "Feature",
  "properties": {
    "addr:full":"5427 N Sharon Amity Rd Charlotte NC 28215",
    "addr:housenumber":"5427",
    "addr:postcode":"28215",
    "addr:street":"N Sharon Amity Rd",
    "iso:country":"US",
    "sg:address":"5427 N Sharon Amity Rd",
    "sg:city":"Charlotte",
    "sg:classifiers":[
        {
            "category":"Home & Garden",
            "subcategory":"Garden Supply",
            "type":"Retail Goods"
        }
    ],
    "sg:phone":"+1 704 566 1222",
    "sg:postcode":"28215",
    "sg:province":"NC",
    "sg:tags":[
        "lawn",
        "mower"
    ],
    "wof:name":"Roberts Small Engine Repair",
    "wof:placetype":"venue"
},
  "geometry": {"coordinates":[-80.740329,35.231517],"type":"Point"}
}