{
  "type": "Feature",
  "properties": {
    "iso:country":"US",
    "sg:address":"2008 Poole Rd",
    "sg:city":"Raleigh",
    "sg:classifiers":[
        {
            "category":"Shopping",
            "subcategory":"Florist",
            "type":"Retail Goods"
        }
    ],
    "sg:phone":"+1 919 231 1849",
    "sg:postcode":"27610",
    "sg:province":"NC",
    "wof:name":"Pee Wee Hunter's Florist",
    "wof:placetype":"venue"
},
  "geometry": {"coordinates":[-78.61011499999999,35.776216],"type":"Point"}
}