{
  "type": "Feature",
  "properties": {
    "iso:country":"US",
    "sg:address":"101 S Church St",
    "sg:city":"Waxhaw",
    "sg:classifiers":[
        {
            "category":"Insurance",
            "subcategory":"Insurance Agent",
            "type":"Services"
        }
    ],
    "sg:phone":"+1 704 843 4140",
    "sg:postcode":"28173",
    "sg:province":"NC",
    "wof:name":"Primerica Financial Svc",
    "wof:placetype":"venue"
},
  "geometry": {"coordinates":[-80.744615,34.925036],"type":"Point"}
}