{
  "type": "Feature",
  "properties": {
    "iso:country":"US",
    "sg:address":"3010 S Stratford Rd",
    "sg:city":"Winston Salem",
    "sg:classifiers":[
        {
            "category":"Shopping",
            "subcategory":"Bicycles & Sporting Goods",
            "type":"Retail Goods"
        }
    ],
    "sg:phone":"+1 336 760 9226",
    "sg:postcode":"27103",
    "sg:province":"NC",
    "sg:tags":[
        "equipment",
        "diver",
        "supply"
    ],
    "sg:website":"www.bluedolphindive.com",
    "wof:name":"Blue Dolphin Dive Ctr",
    "wof:placetype":"venue"
},
  "geometry": {"coordinates":[-80.348811,36.023881],"type":"Point"}
}