{
  "type": "Feature",
  "properties": {
    "addr:full":"1616 Spain Bridge Rd Fountain NC 27829",
    "addr:housenumber":"1616",
    "addr:postcode":"27829",
    "addr:street":"Spain Bridge Rd",
    "iso:country":"US",
    "sg:address":"1616 Spain Bridge Rd",
    "sg:city":"Fountain",
    "sg:phone":"+1 252 749 2135",
    "sg:postcode":"27829",
    "sg:province":"NC",
    "sg:tags":[
        "farm",
        "tobacco"
    ],
    "wof:name":"William Purvis",
    "wof:placetype":"venue"
},
  "geometry": {"coordinates":[-77.57259999999999,35.711982],"type":"Point"}
}