{
  "type": "Feature",
  "properties": {
    "addr:full":"2408 Kings Rd Shelby NC 28152",
    "addr:housenumber":"2408",
    "addr:postcode":"28152",
    "addr:street":"Kings Rd",
    "iso:country":"US",
    "sg:address":"2408 Kings Rd",
    "sg:city":"Shelby",
    "sg:classifiers":[
        {
            "category":"Wholesale",
            "subcategory":"Electrical",
            "type":"Manufacturing & Wholesale Goods"
        }
    ],
    "sg:phone":"+1 704 482 9896",
    "sg:postcode":"28152",
    "sg:province":"NC",
    "sg:tags":[
        "alarm",
        "burglar",
        "system"
    ],
    "sg:website":"www.shelbyalarm.com",
    "wof:name":"Shelby Alarm Co",
    "wof:placetype":"venue"
},
  "geometry": {"coordinates":[-81.490866,35.275905],"type":"Point"}
}