{
  "type": "Feature",
  "properties": {
    "addr:full":"179 Morrison Hill Rd Davidson NC 28036",
    "addr:housenumber":"179",
    "addr:postcode":"28036",
    "addr:street":"Morrison Hill Rd",
    "iso:country":"US",
    "sg:address":"179 Morrison Hill Rd",
    "sg:city":"Davidson",
    "sg:classifiers":[
        {
            "category":"Professional",
            "type":"Services"
        }
    ],
    "sg:phone":"+1 704 896 7469",
    "sg:postcode":"28036",
    "sg:province":"NC",
    "wof:name":"Mitchell Server",
    "wof:placetype":"venue"
},
  "geometry": {"coordinates":[-80.825181,35.487861],"type":"Point"}
}