{
  "type": "Feature",
  "properties": {
    "iso:country":"US",
    "sg:address":"2566 Asheville Rd",
    "sg:city":"Waynesville",
    "sg:classifiers":[
        {
            "category":"Building & Trades",
            "subcategory":"Plumbing",
            "type":"Services"
        }
    ],
    "sg:phone":"+1 828 452 4513",
    "sg:postcode":"28786",
    "sg:province":"NC",
    "sg:tags":[
        "plumbing",
        "heating",
        "contractor"
    ],
    "wof:name":"Plemmons Plumbing & Heating",
    "wof:placetype":"venue"
},
  "geometry": {"coordinates":[-82.967366,35.510479],"type":"Point"}
}