{
  "type": "Feature",
  "properties": {
    "addr:full":"2724 Briarcreek Pl Fayetteville NC 28304",
    "addr:housenumber":"2724",
    "addr:postcode":"28304",
    "addr:street":"Briarcreek Pl",
    "iso:country":"US",
    "sg:address":"2724 Briarcreek Pl",
    "sg:city":"Fayetteville",
    "sg:classifiers":[
        {
            "category":"Professional",
            "subcategory":"Management & Consulting",
            "type":"Services"
        }
    ],
    "sg:phone":"+1   ",
    "sg:postcode":"28304",
    "sg:province":"NC",
    "sg:tags":[
        "training",
        "leadership"
    ],
    "wof:name":"Suzan Cheek & Associates LLC",
    "wof:placetype":"venue"
},
  "geometry": {"coordinates":[-78.92187800000001,35.02735],"type":"Point"}
}