{
  "type": "Feature",
  "properties": {
    "iso:country":"US",
    "sg:address":"1413 Old Buckhorn Rd",
    "sg:city":"Garner",
    "sg:classifiers":[
        {
            "category":"Building & Trades",
            "subcategory":"Plumbing",
            "type":"Services"
        }
    ],
    "sg:phone":"+1 919 369 0322",
    "sg:postcode":"27529",
    "sg:province":"NC",
    "sg:tags":[
        "plumbing",
        "contractor"
    ],
    "wof:name":"Worthwhile Plumbing Inc",
    "wof:placetype":"venue"
},
  "geometry": {"coordinates":[-78.638836,35.706419],"type":"Point"}
}