{
  "type": "Feature",
  "properties": {
    "addr:full":"100 E Durham St Kill Devil Hills NC 27948",
    "addr:housenumber":"100",
    "addr:postcode":"27948",
    "addr:street":"E Durham St",
    "iso:country":"US",
    "sg:address":"100 E Durham St",
    "sg:city":"Kill Devil Hills",
    "sg:classifiers":[
        {
            "category":"Building & Trades",
            "subcategory":"Construction",
            "type":"Services"
        }
    ],
    "sg:phone":"+1 252 441 8020",
    "sg:postcode":"27948",
    "sg:province":"NC",
    "sg:tags":[
        "house",
        "nonresidential"
    ],
    "wof:name":"Dare Coast Realty and Cnstr",
    "wof:placetype":"venue"
},
  "geometry": {"coordinates":[-75.67356100000001,36.039367],"type":"Point"}
}