{
  "type": "Feature",
  "properties": {
    "iso:country":"US",
    "sg:address":"11016 Capital Blvd",
    "sg:city":"Wake Forest",
    "sg:classifiers":[
        {
            "category":"Building & Trades",
            "subcategory":"Construction",
            "type":"Services"
        }
    ],
    "sg:phone":"+1 919 556 1609",
    "sg:postcode":"27587",
    "sg:province":"NC",
    "sg:tags":[
        "general",
        "contractor"
    ],
    "wof:name":"Construction By J Inc",
    "wof:placetype":"venue"
},
  "geometry": {"coordinates":[-78.53938100000001,35.943808],"type":"Point"}
}