{
  "type": "Feature",
  "properties": {
    "addr:full":"1014 Airport Rd Marion NC 28752",
    "addr:housenumber":"1014",
    "addr:postcode":"28752",
    "addr:street":"Airport Rd",
    "iso:country":"US",
    "sg:address":"1014 Airport Rd",
    "sg:city":"Marion",
    "sg:classifiers":[
        {
            "category":"Organizations",
            "subcategory":"Religious Organization",
            "type":"Services"
        }
    ],
    "sg:phone":"+1   ",
    "sg:postcode":"28752",
    "sg:province":"NC",
    "wof:name":"Missionary Alliance Church",
    "wof:placetype":"venue"
},
  "geometry": {"coordinates":[-82.01672499999999,35.699859],"type":"Point"}
}