{
  "type": "Feature",
  "properties": {
    "addr:full":"5885 Shady Grove Cir Raleigh NC 27609",
    "addr:housenumber":"5885",
    "addr:postcode":"27609",
    "addr:street":"Shady Grove Cir",
    "iso:country":"US",
    "sg:address":"5885 Shady Grove Cir",
    "sg:city":"Raleigh",
    "sg:classifiers":[
        {
            "category":"Manufacturing",
            "subcategory":"Rubber & Plastics",
            "type":"Manufacturing & Wholesale Goods"
        }
    ],
    "sg:phone":"+1 919 877 8172",
    "sg:postcode":"27609",
    "sg:province":"NC",
    "sg:tags":[
        "product"
    ],
    "wof:name":"East Coast Plastic & Metal",
    "wof:placetype":"venue"
},
  "geometry": {"coordinates":[-78.601354,35.860287],"type":"Point"}
}