{
  "type": "Feature",
  "properties": {
    "iso:country":"US",
    "sg:address":"293 Brookdale St",
    "sg:city":"Kannapolis",
    "sg:classifiers":[
        {
            "category":"Professional",
            "subcategory":"Art Services",
            "type":"Services"
        }
    ],
    "sg:phone":"+1 704 933 5715",
    "sg:postcode":"28083",
    "sg:province":"NC",
    "sg:tags":[
        "graphic",
        "designer"
    ],
    "sg:website":"www.omegaart.com",
    "wof:name":"Omega Graphics Inc",
    "wof:placetype":"venue"
},
  "geometry": {"coordinates":[-80.615561,35.507526],"type":"Point"}
}