{
  "type": "Feature",
  "properties": {
    "iso:country":"US",
    "sg:address":"233 Raintree Rd",
    "sg:city":"Jacksonville",
    "sg:classifiers":[
        {
            "category":"Professional",
            "subcategory":"Art Services",
            "type":"Services"
        }
    ],
    "sg:phone":"+1   ",
    "sg:postcode":"28540",
    "sg:province":"NC",
    "sg:tags":[
        "commercial",
        "design"
    ],
    "wof:name":"Kathryn Foster Deas",
    "wof:placetype":"venue"
},
  "geometry": {"coordinates":[-77.45419800000001,34.814036],"type":"Point"}
}