{
  "type": "Feature",
  "properties": {
    "addr:full":"435 W Meadowview Rd Greensboro NC 27406",
    "addr:housenumber":"435",
    "addr:postcode":"27406",
    "addr:street":"W Meadowview Rd",
    "iso:country":"US",
    "sg:address":"435 W Meadowview Rd",
    "sg:city":"Greensboro",
    "sg:classifiers":[
        {
            "category":"Professional",
            "subcategory":"Research",
            "type":"Services"
        }
    ],
    "sg:phone":"+1 336 275 3100",
    "sg:postcode":"27406",
    "sg:province":"NC",
    "sg:tags":[
        "nonphysical",
        "commercial"
    ],
    "sg:website":"www.measinc.com",
    "wof:name":"Measurement Inc",
    "wof:placetype":"venue"
},
  "geometry": {"coordinates":[-79.802114,36.038852],"type":"Point"}
}