{
  "type": "Feature",
  "properties": {
    "addr:full":"5183 Clinton Rd Stedman NC 28391",
    "addr:housenumber":"5183",
    "addr:postcode":"28391",
    "addr:street":"Clinton Rd",
    "iso:country":"US",
    "sg:address":"5183 Clinton Rd",
    "sg:city":"Stedman",
    "sg:classifiers":[
        {
            "category":"Health Services",
            "subcategory":"Chiropractor",
            "type":"Services"
        }
    ],
    "sg:phone":"+1 910 482 4444",
    "sg:postcode":"28391",
    "sg:province":"NC",
    "wof:name":"Walker Chiropractic Ctr",
    "wof:placetype":"venue"
},
  "geometry": {"coordinates":[-78.69061499999999,35.012214],"type":"Point"}
}