{
  "type": "Feature",
  "properties": {
    "addr:full":"158 Morning Glory Dr Moravian Falls NC 28636",
    "addr:housenumber":"158",
    "addr:postcode":"28636",
    "addr:street":"Morning Glory Dr",
    "iso:country":"US",
    "sg:address":"158 Morning Glory Dr",
    "sg:city":"Moravian Falls",
    "sg:classifiers":[
        {
            "category":"Manufacturing",
            "subcategory":"Printing",
            "type":"Manufacturing & Wholesale Goods"
        }
    ],
    "sg:phone":"+1 336 921 2249",
    "sg:postcode":"28636",
    "sg:province":"NC",
    "sg:tags":[
        "publisher"
    ],
    "wof:name":"Morningstar Publications",
    "wof:placetype":"venue"
},
  "geometry": {"coordinates":[-81.083178,35.869225],"type":"Point"}
}