{
  "type": "Feature",
  "properties": {
    "addr:full":"416 Eastchester Dr High Point NC 27262",
    "addr:housenumber":"416",
    "addr:postcode":"27262",
    "addr:street":"Eastchester Dr",
    "iso:country":"US",
    "sg:address":"416 Eastchester Dr",
    "sg:city":"High Point",
    "sg:classifiers":[
        {
            "category":"Autos & Motor Vehicles",
            "subcategory":"Automobile Sales",
            "type":"Retail Goods"
        }
    ],
    "sg:phone":"+1 336 841 6300",
    "sg:postcode":"27262",
    "sg:province":"NC",
    "sg:tags":[
        "car",
        "dealer"
    ],
    "wof:name":"Vann York Used Cars/Isuzu",
    "wof:placetype":"venue"
},
  "geometry": {"coordinates":[-80.011808,35.983834],"type":"Point"}
}