{
  "type": "Feature",
  "properties": {
    "addr:full":"187 Sleepy Gap Rd Arden NC 28704",
    "addr:housenumber":"187",
    "addr:postcode":"28704",
    "addr:street":"Sleepy Gap Rd",
    "iso:country":"US",
    "sg:address":"187 Sleepy Gap Rd",
    "sg:city":"Arden",
    "sg:classifiers":[
        {
            "category":"Building & Trades",
            "subcategory":"Cleaning & Sanitation",
            "type":"Services"
        }
    ],
    "sg:phone":"+1 828 681 0406",
    "sg:postcode":"28704",
    "sg:province":"NC",
    "wof:name":"Mark Terry",
    "wof:placetype":"venue"
},
  "geometry": {"coordinates":[-82.613868,35.456508],"type":"Point"}
}