{
  "type": "Feature",
  "properties": {
    "addr:full":"225 S Water St Wilmington NC 28401",
    "addr:housenumber":"225",
    "addr:postcode":"28401",
    "addr:street":"S Water St",
    "iso:country":"US",
    "sg:address":"225 S Water St",
    "sg:city":"Wilmington",
    "sg:classifiers":[
        {
            "category":"Retail",
            "subcategory":"Repair Shop",
            "type":"Services"
        }
    ],
    "sg:phone":"+1 910 251 0966",
    "sg:postcode":"28401",
    "sg:province":"NC",
    "wof:name":"Waste Industries USA Inc",
    "wof:placetype":"venue"
},
  "geometry": {"coordinates":[-77.94905799999999,34.231815],"type":"Point"}
}