{
  "type": "Feature",
  "properties": {
    "iso:country":"US",
    "sg:address":"264 Alderson Rd",
    "sg:city":"Greenville",
    "sg:classifiers":[
        {
            "category":"Retail",
            "subcategory":"Repair Shop",
            "type":"Services"
        }
    ],
    "sg:phone":"+1 252 355 5007",
    "sg:postcode":"27889",
    "sg:province":"NC",
    "sg:tags":[
        "steel",
        "sales",
        "welding"
    ],
    "wof:name":"Archies Steel Service Inc",
    "wof:placetype":"venue"
},
  "geometry": {"coordinates":[-77.026078,35.560068],"type":"Point"}
}