{
  "type": "Feature",
  "properties": {
    "addr:full":"10115 Kincey Ave Huntersville NC 28078",
    "addr:housenumber":"10115",
    "addr:postcode":"28078",
    "addr:street":"Kincey Ave",
    "iso:country":"US",
    "sg:address":"10115 Kincey Ave",
    "sg:city":"Huntersville",
    "sg:classifiers":[
        {
            "category":"Insurance",
            "subcategory":"Insurance Agent",
            "type":"Services"
        }
    ],
    "sg:phone":"+1 704 948 3722",
    "sg:postcode":"28078",
    "sg:province":"NC",
    "wof:name":"Aflac",
    "wof:placetype":"venue"
},
  "geometry": {"coordinates":[-80.858856,35.403634],"type":"Point"}
}