{
  "type": "Feature",
  "properties": {
    "addr:full":"4401 Glenwood Ave Raleigh NC 27612",
    "addr:housenumber":"4401",
    "addr:postcode":"27612",
    "addr:street":"Glenwood Ave",
    "iso:country":"US",
    "sg:address":"4401 Glenwood Ave",
    "sg:city":"Raleigh",
    "sg:classifiers":[
        {
            "category":"Banks & Credit Unions",
            "subcategory":"Bank",
            "type":"Services"
        }
    ],
    "sg:phone":"+1 919 881 6208",
    "sg:postcode":"27612",
    "sg:province":"NC",
    "sg:tags":[
        "national"
    ],
    "wof:name":"Crabtree Office",
    "wof:placetype":"venue"
},
  "geometry": {"coordinates":[-78.67613,35.83947],"type":"Point"}
}