{
  "type": "Feature",
  "properties": {
    "addr:full":"Timberlyne Shopping Center 1129 Weaver Dairy Rd Ste N Chapel Hill NC 27514",
    "addr:housenumber":"1129",
    "addr:postcode":"27514",
    "addr:street":"Weaver Dairy Rd Ste N",
    "iso:country":"US",
    "sg:address":"Timberlyne Shopping Center 1129 Weaver Dairy Rd Ste N",
    "sg:city":"Chapel Hill",
    "sg:classifiers":[
        {
            "category":"Real Estate",
            "subcategory":"Real Estate Agent",
            "type":"Services"
        }
    ],
    "sg:phone":"+1 919 969 0066",
    "sg:postcode":"27514",
    "sg:province":"NC",
    "sg:website":"sheltertoday.wordpress.com/",
    "wof:name":"Shelter Real Estate",
    "wof:placetype":"venue"
},
  "geometry": {"coordinates":[-79.053742,35.962579],"type":"Point"}
}