{
  "type": "Feature",
  "properties": {
    "iso:country":"US",
    "sg:address":"1506 Purdue Dr",
    "sg:city":"Fayetteville",
    "sg:classifiers":[
        {
            "category":"Travel",
            "subcategory":"Travel Agent",
            "type":"Entertainment"
        }
    ],
    "sg:phone":"+1 910 485 4182",
    "sg:postcode":"28303",
    "sg:province":"NC",
    "sg:tags":[
        "agency",
        "bureau"
    ],
    "wof:name":"Major Travel Ctr",
    "wof:placetype":"venue"
},
  "geometry": {"coordinates":[-78.924288,35.044575],"type":"Point"}
}