{
  "type": "Feature",
  "properties": {
    "iso:country":"US",
    "sg:address":"3000 N Graham St",
    "sg:city":"Charlotte",
    "sg:classifiers":[
        {
            "category":"Personal",
            "subcategory":"Barber",
            "type":"Services"
        }
    ],
    "sg:phone":"+1 704 332 5922",
    "sg:postcode":"28206",
    "sg:province":"NC",
    "wof:name":"Dewitts Barber Shop",
    "wof:placetype":"venue"
},
  "geometry": {"coordinates":[-80.821281,35.25906],"type":"Point"}
}