{
  "type": "Feature",
  "properties": {
    "iso:country":"US",
    "sg:address":"106 Pine Circle Dr",
    "sg:city":"Rockingham",
    "sg:classifiers":[
        {
            "category":"Home & Garden",
            "subcategory":"Garden Supply",
            "type":"Retail Goods"
        }
    ],
    "sg:phone":"+1 910 895 0820",
    "sg:postcode":"28379",
    "sg:province":"NC",
    "sg:tags":[
        "fountain",
        "display"
    ],
    "wof:name":"Southern Union Studios",
    "wof:placetype":"venue"
},
  "geometry": {"coordinates":[-79.831003,34.958298],"type":"Point"}
}