{
  "type": "Feature",
  "properties": {
    "iso:country":"US",
    "sg:address":"6878 Old 125 Rd",
    "sg:city":"Scotland Neck",
    "sg:classifiers":[
        {
            "category":"Education",
            "subcategory":"School",
            "type":"Public Place"
        }
    ],
    "sg:phone":"+1 252 826 4905",
    "sg:postcode":"27874",
    "sg:province":"NC",
    "wof:name":"Dawson Elementary School",
    "wof:placetype":"venue"
},
  "geometry": {"coordinates":[-77.52636,36.167139],"type":"Point"}
}