{
  "type": "Feature",
  "properties": {
    "iso:country":"US",
    "sg:address":"400 Peyton St",
    "sg:city":"Raleigh",
    "sg:classifiers":[
        {
            "category":"Education",
            "subcategory":"School",
            "type":"Public Place"
        }
    ],
    "sg:phone":"+1 919 250 4777",
    "sg:postcode":"27610",
    "sg:province":"NC",
    "sg:tags":[
        "elementary"
    ],
    "sg:website":"www.wcpss.net",
    "wof:name":"Poe Elementary School",
    "wof:placetype":"venue"
},
  "geometry": {"coordinates":[-78.606983,35.772268],"type":"Point"}
}