{
  "type": "Feature",
  "properties": {
    "addr:full":"1530 Patton Ave Asheville NC 28806",
    "addr:housenumber":"1530",
    "addr:postcode":"28806",
    "addr:street":"Patton Ave",
    "iso:country":"US",
    "sg:address":"1530 Patton Ave",
    "sg:city":"Asheville",
    "sg:classifiers":[
        {
            "category":"Autos & Motor Vehicles",
            "subcategory":"Automobile Sales",
            "type":"Retail Goods"
        }
    ],
    "sg:phone":"+1 828 254 9730",
    "sg:postcode":"28806",
    "sg:province":"NC",
    "sg:tags":[
        "car"
    ],
    "wof:name":"Lindsay Jim Auto Sales",
    "wof:placetype":"venue"
},
  "geometry": {"coordinates":[-82.61309799999999,35.5755],"type":"Point"}
}