{
  "type": "Feature",
  "properties": {
    "addr:full":"2020 Northwest Blvd Newton NC 28658",
    "addr:housenumber":"2020",
    "addr:postcode":"28658",
    "addr:street":"Northwest Blvd",
    "iso:country":"US",
    "sg:address":"2020 Northwest Blvd",
    "sg:city":"Newton",
    "sg:classifiers":[
        {
            "category":"Home & Garden",
            "subcategory":"Furniture",
            "type":"Retail Goods"
        }
    ],
    "sg:phone":"+1 828 322 2187",
    "sg:postcode":"28658",
    "sg:province":"NC",
    "sg:tags":[
        "mattress"
    ],
    "sg:website":"www.factorymattressusa.com",
    "wof:name":"Factory Mattresses Sales",
    "wof:placetype":"venue"
},
  "geometry": {"coordinates":[-81.229235,35.682086],"type":"Point"}
}