{
  "type": "Feature",
  "properties": {
    "addr:full":"905 Linden Rd Pinehurst NC 28374",
    "addr:housenumber":"905",
    "addr:postcode":"28374",
    "addr:street":"Linden Rd",
    "iso:country":"US",
    "sg:address":"905 Linden Rd",
    "sg:city":"Pinehurst",
    "sg:classifiers":[
        {
            "category":"Shopping",
            "subcategory":"Gifts & Souvenirs",
            "type":"Retail Goods"
        }
    ],
    "sg:phone":"+1 910 295 1761",
    "sg:postcode":"28374",
    "sg:province":"NC",
    "sg:tags":[
        "shop"
    ],
    "wof:name":"Pinehurst Place",
    "wof:placetype":"venue"
},
  "geometry": {"coordinates":[-79.500325,35.189395],"type":"Point"}
}