{
  "type": "Feature",
  "properties": {
    "addr:full":"228 E Palmer St Franklin NC 28734",
    "addr:housenumber":"228",
    "addr:postcode":"nc 28734",
    "addr:street":"E Palmer St",
    "iso:country":"US",
    "sg:address":"228 E Palmer St",
    "sg:city":"Franklin",
    "sg:classifiers":[
        {
            "category":"Organizations",
            "subcategory":"Community Association",
            "type":"Services"
        }
    ],
    "sg:phone":"+1   ",
    "sg:postcode":"28734",
    "sg:province":"NC",
    "wof:name":"VFW Post 7339",
    "wof:placetype":"venue"
},
  "geometry": {"coordinates":[-83.378952,35.181381],"type":"Point"}
}