{
  "type": "Feature",
  "properties": {
    "addr:full":"108 Stacy Ln New Bern NC 28560",
    "addr:housenumber":"108",
    "addr:postcode":"28560",
    "addr:street":"Stacy Ln",
    "iso:country":"US",
    "sg:address":"108 Stacy Ln",
    "sg:city":"New Bern",
    "sg:classifiers":[
        {
            "category":"Professional",
            "type":"Services"
        }
    ],
    "sg:phone":"+1 252 637 2195",
    "sg:postcode":"28560",
    "sg:province":"NC",
    "wof:name":"Chance Steel Inc",
    "wof:placetype":"venue"
},
  "geometry": {"coordinates":[-77.05010799999999,35.153878],"type":"Point"}
}