{
  "type": "Feature",
  "properties": {
    "addr:full":"636 State Hwy 210 E Harrells NC 28444",
    "addr:housenumber":"636",
    "addr:postcode":"28444",
    "addr:street":"State Hwy 210 E Harrells",
    "iso:country":"US",
    "sg:address":"636 State Hwy 210 E",
    "sg:city":"Harrells",
    "sg:classifiers":[
        {
            "category":"Freight",
            "type":"Transportation"
        }
    ],
    "sg:phone":"+1 910 529 7221",
    "sg:postcode":"28444",
    "sg:province":"NC",
    "sg:tags":[
        "distance",
        "long",
        "trucking"
    ],
    "wof:name":"Tomahawk Trucking Inc",
    "wof:placetype":"venue"
},
  "geometry": {"coordinates":[-78.411627,34.744606],"type":"Point"}
}