{
  "type": "Feature",
  "properties": {
    "addr:full":"2024 Kildaire Farm Rd Cary NC 27518",
    "addr:housenumber":"2024",
    "addr:postcode":"27518",
    "addr:street":"Kildaire Farm Rd",
    "iso:country":"US",
    "sg:address":"2024 Kildaire Farm Rd",
    "sg:city":"Cary",
    "sg:classifiers":[
        {
            "category":"Banks & Credit Unions",
            "subcategory":"Bank",
            "type":"Services"
        }
    ],
    "sg:phone":"+1 919 233 7453",
    "sg:postcode":"27518",
    "sg:province":"NC",
    "wof:name":"Coastal Federal Credit Union",
    "wof:placetype":"venue"
},
  "geometry": {"coordinates":[-78.780348,35.738248],"type":"Point"}
}