{
  "type": "Feature",
  "properties": {
    "addr:full":"342 W Rosemary St Chapel Hill NC 27516",
    "addr:housenumber":"342",
    "addr:postcode":"27516",
    "addr:street":"W Rosemary St",
    "iso:country":"US",
    "sg:address":"342 W Rosemary St",
    "sg:city":"Chapel Hill",
    "sg:classifiers":[
        {
            "category":"Real Estate",
            "subcategory":"Real Estate Agent",
            "type":"Services"
        }
    ],
    "sg:phone":"+1 919 942 1938",
    "sg:postcode":"27516",
    "sg:province":"NC",
    "sg:tags":[
        "home",
        "contractor"
    ],
    "wof:name":"Tate Realty & Construction Co",
    "wof:placetype":"venue"
},
  "geometry": {"coordinates":[-79.061666,35.911998],"type":"Point"}
}