{
  "type": "Feature",
  "properties": {
    "iso:country":"US",
    "sg:address":"1240 Matthews Mint Hill Rd",
    "sg:city":"Matthews",
    "sg:classifiers":[
        {
            "category":"Restaurant",
            "type":"Food & Drink"
        }
    ],
    "sg:menulink":"http://www.allmenus.com/nc/morning-star/50625-dorians/menu/",
    "sg:phone":"+1 704 847 4901",
    "sg:postcode":"28105",
    "sg:province":"NC",
    "sg:tags":[
        "american"
    ],
    "wof:name":"Dorian's",
    "wof:placetype":"venue"
},
  "geometry": {"coordinates":[-80.702606,35.117683],"type":"Point"}
}