{
  "type": "Feature",
  "properties": {
    "addr:full":"1905 Poole Rd Raleigh NC 27610",
    "addr:housenumber":"1905",
    "addr:postcode":"27610",
    "addr:street":"Poole Rd",
    "iso:country":"US",
    "sg:address":"1905 Poole Rd",
    "sg:city":"Raleigh",
    "sg:classifiers":[
        {
            "category":"Shopping",
            "subcategory":"Clothing, Apparel, & Fashions",
            "type":"Retail Goods"
        }
    ],
    "sg:phone":"+1 919 231 0830",
    "sg:postcode":"27610",
    "sg:province":"NC",
    "wof:name":"Windstar Fashion & Gifts",
    "wof:placetype":"venue"
},
  "geometry": {"coordinates":[-78.610568,35.776507],"type":"Point"}
}