{
  "type": "Feature",
  "properties": {
    "addr:full":"601 S College St Henderson NC 27536",
    "addr:housenumber":"601",
    "addr:postcode":"27536",
    "addr:street":"S College St",
    "iso:country":"US",
    "sg:address":"601 S College St",
    "sg:city":"Henderson",
    "sg:classifiers":[
        {
            "category":"Real Estate",
            "subcategory":"Real Estate Agent",
            "type":"Services"
        }
    ],
    "sg:phone":"+1 252 430 6452",
    "sg:postcode":"27536",
    "sg:province":"NC",
    "wof:name":"Heavenly Housing",
    "wof:placetype":"venue"
},
  "geometry": {"coordinates":[-78.403397,36.322198],"type":"Point"}
}