{
  "type": "Feature",
  "properties": {
    "addr:full":"817 S Main St Graham NC 27253",
    "addr:housenumber":"817",
    "addr:postcode":"27253",
    "addr:street":"S Main St",
    "iso:country":"US",
    "sg:address":"817 S Main St",
    "sg:city":"Graham",
    "sg:classifiers":[
        {
            "category":"Restaurant",
            "type":"Food & Drink"
        }
    ],
    "sg:menulink":"http://www.allmenus.com/nc/graham/137323-subway/menu/",
    "sg:phone":"+1 336 228 7690",
    "sg:postcode":"27253",
    "sg:province":"NC",
    "sg:tags":[
        "american",
        "sandwich"
    ],
    "wof:name":"Subway",
    "wof:placetype":"venue"
},
  "geometry": {"coordinates":[-79.40027000000001,36.057216],"type":"Point"}
}