{
  "type": "Feature",
  "properties": {
    "addr:full":"3018 N Center St Hickory NC 28601",
    "addr:housenumber":"3018",
    "addr:postcode":"28601",
    "addr:street":"N Center St",
    "iso:country":"US",
    "sg:address":"3018 N Center St",
    "sg:city":"Hickory",
    "sg:classifiers":[
        {
            "category":"Restaurant",
            "type":"Food & Drink"
        }
    ],
    "sg:menulink":"http://www.allmenus.com/nc/hickory/228758-jersey-mikes/menu/",
    "sg:phone":"+1 828 322 2989",
    "sg:postcode":"28601",
    "sg:province":"NC",
    "sg:tags":[
        "american",
        "sandwich"
    ],
    "wof:name":"Jersey Mike's",
    "wof:placetype":"venue"
},
  "geometry": {"coordinates":[-81.329668,35.772105],"type":"Point"}
}