{
  "type": "Feature",
  "properties": {
    "iso:country":"US",
    "sg:address":"903 Hay St",
    "sg:city":"Fayetteville",
    "sg:classifiers":[
        {
            "category":"Real Estate",
            "subcategory":"Real Estate Agent",
            "type":"Services"
        }
    ],
    "sg:phone":"+1 910 484 5193",
    "sg:postcode":"28305",
    "sg:province":"NC",
    "wof:name":"Broadwell Land Co",
    "wof:placetype":"venue"
},
  "geometry": {"coordinates":[-78.896266,35.056115],"type":"Point"}
}