{
  "type": "Feature",
  "properties": {
    "addr:full":"300 Front St Beaufort NC 28516",
    "addr:housenumber":"300",
    "addr:postcode":"28516",
    "addr:street":"Front St",
    "iso:country":"US",
    "sg:address":"300 Front St",
    "sg:city":"Beaufort",
    "sg:classifiers":[
        {
            "category":"Food & Beverages",
            "subcategory":"Groceries & Convenience Stores",
            "type":"Retail Goods"
        }
    ],
    "sg:phone":"+1 252 728 2653",
    "sg:postcode":"28516",
    "sg:province":"NC",
    "wof:name":"Fantasy Food Emporium",
    "wof:placetype":"venue"
},
  "geometry": {"coordinates":[-76.663563,34.715647],"type":"Point"}
}