{
  "type": "Feature",
  "properties": {
    "addr:full":"6 Airline St Belmont NC 28012",
    "addr:housenumber":"6",
    "addr:postcode":"28012",
    "addr:street":"Airline St",
    "iso:country":"US",
    "sg:address":"6 Airline St",
    "sg:city":"Belmont",
    "sg:classifiers":[
        {
            "category":"Manufacturing",
            "subcategory":"Metals",
            "type":"Manufacturing & Wholesale Goods"
        }
    ],
    "sg:phone":"+1 704 825 7768",
    "sg:postcode":"28012",
    "sg:province":"NC",
    "sg:tags":[
        "commercial",
        "printing",
        "lithographic",
        "mfg"
    ],
    "wof:name":"Graphically Speaking",
    "wof:placetype":"venue"
},
  "geometry": {"coordinates":[-81.03798,35.2421],"type":"Point"}
}