{
  "type": "Feature",
  "properties": {
    "iso:country":"US",
    "sg:address":"3602 Greensboro St",
    "sg:city":"Greensboro",
    "sg:classifiers":[
        {
            "category":"Freight",
            "type":"Transportation"
        }
    ],
    "sg:phone":"+1 336 230 1277",
    "sg:postcode":"27401",
    "sg:province":"NC",
    "sg:tags":[
        "hauling",
        "trucking"
    ],
    "wof:name":"Miller & Son Hauling",
    "wof:placetype":"venue"
},
  "geometry": {"coordinates":[-79.74584,36.079525],"type":"Point"}
}