{
  "type": "Feature",
  "properties": {
    "addr:full":"80 Memorial Dr Pinehurst NC 28374",
    "addr:housenumber":"80",
    "addr:postcode":"28374",
    "addr:street":"Memorial Dr",
    "iso:country":"US",
    "sg:address":"80 Memorial Dr",
    "sg:city":"Pinehurst",
    "sg:classifiers":[
        {
            "category":"Health Services",
            "subcategory":"Clinic",
            "type":"Services"
        }
    ],
    "sg:phone":"+1 910 295 3823",
    "sg:postcode":"28374",
    "sg:province":"NC",
    "sg:tags":[
        "home"
    ],
    "sg:website":"www.libertyhomecare.com",
    "wof:name":"Liberty Home Care Group",
    "wof:placetype":"venue"
},
  "geometry": {"coordinates":[-79.45532799999999,35.20862],"type":"Point"}
}