{
  "type": "Feature",
  "properties": {
    "addr:full":"1418 Wilkesboro Rd Salisbury NC 28144",
    "addr:housenumber":"1418",
    "addr:postcode":"28144",
    "addr:street":"Wilkesboro Rd",
    "iso:country":"US",
    "sg:address":"1418 Wilkesboro Rd",
    "sg:city":"Salisbury",
    "sg:classifiers":[
        {
            "category":"Organizations",
            "subcategory":"Religious Organization",
            "type":"Services"
        }
    ],
    "sg:phone":"+1 704 633 5720",
    "sg:postcode":"28144",
    "sg:province":"NC",
    "wof:name":"Salt & Light Evangelistic",
    "wof:placetype":"venue"
},
  "geometry": {"coordinates":[-80.489459,35.67538],"type":"Point"}
}