{
  "type": "Feature",
  "properties": {
    "addr:full":"4364 S Alston Ave Durham NC 27713",
    "addr:housenumber":"4364",
    "addr:postcode":"27713",
    "addr:street":"S Alston Ave",
    "iso:country":"US",
    "sg:address":"4364 S Alston Ave",
    "sg:city":"Durham",
    "sg:classifiers":[
        {
            "category":"Shopping",
            "subcategory":"Computers & Home Electronics",
            "type":"Retail Goods"
        }
    ],
    "sg:phone":"+1 919 572 8908",
    "sg:postcode":"27713",
    "sg:province":"NC",
    "sg:tags":[
        "software"
    ],
    "wof:name":"Triangle Systems Inc",
    "wof:placetype":"venue"
},
  "geometry": {"coordinates":[-78.88910300000001,35.9129],"type":"Point"}
}