{
  "type": "Feature",
  "properties": {
    "iso:country":"US",
    "sg:address":"P.O. Box 119",
    "sg:city":"Knightdale",
    "sg:classifiers":[
        {
            "category":"Professional",
            "subcategory":"Business Services",
            "type":"Services"
        },
        {
            "category":"Government",
            "subcategory":"Post Office",
            "type":"Public Place"
        }
    ],
    "sg:phone":"+1 919 261 9489",
    "sg:postcode":"27545",
    "sg:province":"NC",
    "sg:tags":[
        "delivery",
        "messenger",
        "courier"
    ],
    "sg:website":"http://www.quickcourierinc.com",
    "wof:name":"Quick Courier, Inc.",
    "wof:placetype":"venue"
},
  "geometry": {"coordinates":[-78.49118,35.7916],"type":"Point"}
}