{
  "type": "Feature",
  "properties": {
    "iso:country":"US",
    "sg:address":"2094 Ellisboro Rd",
    "sg:city":"Madison",
    "sg:classifiers":[
        {
            "category":"Freight",
            "type":"Transportation"
        }
    ],
    "sg:phone":"+1 336 445 0191",
    "sg:postcode":"27025",
    "sg:province":"NC",
    "sg:tags":[
        "warehouse"
    ],
    "wof:name":"Kamino International Transport",
    "wof:placetype":"venue"
},
  "geometry": {"coordinates":[-79.976005,36.340167],"type":"Point"}
}