{
  "type": "Feature",
  "properties": {
    "iso:country":"US",
    "sg:address":"822 W Warren St",
    "sg:city":"Shelby",
    "sg:classifiers":[
        {
            "category":"Retail",
            "subcategory":"Car Wash",
            "type":"Services"
        }
    ],
    "sg:phone":"+1 704 471 2638",
    "sg:postcode":"28150",
    "sg:province":"NC",
    "sg:tags":[
        "automobile",
        "detail",
        "clean"
    ],
    "wof:name":"A 1 Auto Detail",
    "wof:placetype":"venue"
},
  "geometry": {"coordinates":[-81.554925,35.290864],"type":"Point"}
}