{
  "type": "Feature",
  "properties": {
    "iso:country":"US",
    "sg:address":"12200 Herbert Wayne Ct",
    "sg:city":"Huntersville",
    "sg:classifiers":[
        {
            "category":"Professional",
            "type":"Services"
        }
    ],
    "sg:phone":"+1 704 948 6316",
    "sg:postcode":"28078",
    "sg:province":"NC",
    "sg:tags":[
        "establishment"
    ],
    "wof:name":"Comdisco Inc",
    "wof:placetype":"venue"
},
  "geometry": {"coordinates":[-80.868746,35.389014],"type":"Point"}
}