{
  "type": "Feature",
  "properties": {
    "addr:full":"3456 N Nc 16 Hwy Conover NC 28613",
    "addr:housenumber":"3456",
    "addr:postcode":"28613",
    "addr:street":"N Nc 16 Hwy",
    "iso:country":"US",
    "sg:address":"3456 N Nc 16 Hwy",
    "sg:city":"Conover",
    "sg:classifiers":[
        {
            "category":"Home & Garden",
            "subcategory":"Garden Supply",
            "type":"Retail Goods"
        }
    ],
    "sg:phone":"+1 828 465 1920",
    "sg:postcode":"28613",
    "sg:province":"NC",
    "sg:tags":[
        "landscaping",
        "lawn"
    ],
    "wof:name":"Greenwood Nursery Inc",
    "wof:placetype":"venue"
},
  "geometry": {"coordinates":[-81.17662,35.755227],"type":"Point"}
}