{
  "type": "Feature",
  "properties": {
    "iso:country":"US",
    "sg:address":"122 Swanson Southard Rd",
    "sg:city":"Elkin",
    "sg:classifiers":[
        {
            "category":"Organizations",
            "subcategory":"Religious Organization",
            "type":"Services"
        }
    ],
    "sg:phone":"+1 336 366 2733",
    "sg:postcode":"28621",
    "sg:province":"NC",
    "sg:tags":[
        "church"
    ],
    "wof:name":"Rock Church",
    "wof:placetype":"venue"
},
  "geometry": {"coordinates":[-80.797478,36.32723],"type":"Point"}
}