{
  "type": "Feature",
  "properties": {
    "iso:country":"US",
    "sg:address":"122 Dobbin Ln",
    "sg:city":"Mooresville",
    "sg:classifiers":[
        {
            "category":"Farming",
            "subcategory":"Farm",
            "type":"Manufacturing & Wholesale Goods"
        }
    ],
    "sg:phone":"+1 704 663 6855",
    "sg:postcode":"28117",
    "sg:province":"NC",
    "sg:tags":[
        "crop",
        "general"
    ],
    "wof:name":"Briarfield Farm LLC",
    "wof:placetype":"venue"
},
  "geometry": {"coordinates":[-80.91970000000001,35.58405],"type":"Point"}
}