{
  "type": "Feature",
  "properties": {
    "addr:full":"291 Shiloh Rd Forest City NC 28043",
    "addr:housenumber":"291",
    "addr:postcode":"28043",
    "addr:street":"Shiloh Rd",
    "iso:country":"US",
    "sg:address":"291 Shiloh Rd",
    "sg:city":"Forest City",
    "sg:classifiers":[
        {
            "category":"Manufacturing",
            "subcategory":"Rubber & Plastics",
            "type":"Manufacturing & Wholesale Goods"
        }
    ],
    "sg:phone":"+1 828 248 1002",
    "sg:postcode":"28043",
    "sg:province":"NC",
    "wof:name":"Integrity Plastics Inc",
    "wof:placetype":"venue"
},
  "geometry": {"coordinates":[-81.912869,35.296747],"type":"Point"}
}