{
  "type": "Feature",
  "properties": {
    "iso:country":"US",
    "sg:address":"101 Pinegate Cir",
    "sg:city":"Chapel Hill",
    "sg:classifiers":[
        {
            "category":"Retail",
            "subcategory":"Laundry & Dry Cleaning",
            "type":"Services"
        }
    ],
    "sg:phone":"+1   ",
    "sg:postcode":"27514",
    "sg:province":"NC",
    "sg:tags":[
        "drycleaning",
        "plant"
    ],
    "wof:name":"Sparkle Cleaners Inc",
    "wof:placetype":"venue"
},
  "geometry": {"coordinates":[-79.007982,35.948636],"type":"Point"}
}