{
  "type": "Feature",
  "properties": {
    "addr:full":"208 N Caswell St La Grange NC 28551",
    "addr:housenumber":"208",
    "addr:postcode":"28551",
    "addr:street":"N Caswell St",
    "iso:country":"US",
    "sg:address":"208 N Caswell St",
    "sg:city":"La Grange",
    "sg:classifiers":[
        {
            "category":"Banks & Credit Unions",
            "subcategory":"Bank",
            "type":"Services"
        }
    ],
    "sg:phone":"+1 252 566 4029",
    "sg:postcode":"28551",
    "sg:province":"NC",
    "wof:name":"Southern Bank & Trust Co",
    "wof:placetype":"venue"
},
  "geometry": {"coordinates":[-77.786771,35.309102],"type":"Point"}
}