{
  "type": "Feature",
  "properties": {
    "iso:country":"US",
    "sg:address":"120 C St",
    "sg:city":"Bridgeton",
    "sg:classifiers":[
        {
            "category":"Manufacturing",
            "subcategory":"Motor Vehicles & Parts",
            "type":"Manufacturing & Wholesale Goods"
        }
    ],
    "sg:phone":"+1 252 633 6003",
    "sg:postcode":"28519",
    "sg:province":"NC",
    "sg:tags":[
        "mfg"
    ],
    "wof:name":"Eastern Carolina Customs",
    "wof:placetype":"venue"
},
  "geometry": {"coordinates":[-77.016329,35.117666],"type":"Point"}
}