{
  "type": "Feature",
  "properties": {
    "iso:country":"US",
    "sg:address":"8069 Rhodes Pond Rd",
    "sg:city":"Dunn",
    "sg:classifiers":[
        {
            "category":"Building & Trades",
            "subcategory":"Construction",
            "type":"Services"
        }
    ],
    "sg:phone":"+1 910 980 1354",
    "sg:postcode":"28342",
    "sg:province":"NC",
    "sg:tags":[
        "general",
        "contractor"
    ],
    "wof:name":"James Brown Builders Inc",
    "wof:placetype":"venue"
},
  "geometry": {"coordinates":[-78.63099099999999,35.23016],"type":"Point"}
}