{
  "type": "Feature",
  "properties": {
    "addr:full":"6300 Creedmoor Rd Raleigh NC 27612",
    "addr:housenumber":"6300",
    "addr:postcode":"27612",
    "addr:street":"Creedmoor Rd",
    "iso:country":"US",
    "sg:address":"6300 Creedmoor Rd",
    "sg:city":"Raleigh",
    "sg:classifiers":[
        {
            "category":"Insurance",
            "subcategory":"Insurance Agent",
            "type":"Services"
        }
    ],
    "sg:phone":"+1 919 847 4909",
    "sg:postcode":"27612",
    "sg:province":"NC",
    "wof:name":"Providence Insurance Inc",
    "wof:placetype":"venue"
},
  "geometry": {"coordinates":[-78.679474,35.87297],"type":"Point"}
}