{
  "type": "Feature",
  "properties": {
    "addr:full":"4912 Stillmeadow Dr Raleigh NC 27604",
    "addr:housenumber":"4912",
    "addr:postcode":"27604",
    "addr:street":"Stillmeadow Dr",
    "iso:country":"US",
    "sg:address":"4912 Stillmeadow Dr",
    "sg:city":"Raleigh",
    "sg:classifiers":[
        {
            "category":"Building & Trades",
            "subcategory":"Construction",
            "type":"Services"
        }
    ],
    "sg:phone":"+1 919 876 8970",
    "sg:postcode":"27604",
    "sg:province":"NC",
    "sg:tags":[
        "contractor"
    ],
    "wof:name":"Mark Dike Contractor",
    "wof:placetype":"venue"
},
  "geometry": {"coordinates":[-78.55573,35.825656],"type":"Point"}
}