{
  "type": "Feature",
  "properties": {
    "addr:full":"2535 State Hwy 101 Beaufort NC 28516",
    "addr:housenumber":"2535",
    "addr:postcode":"28516",
    "addr:street":"State Hwy 101",
    "iso:country":"US",
    "sg:address":"2535 State Hwy 101",
    "sg:city":"Beaufort",
    "sg:classifiers":[
        {
            "category":"Real Estate",
            "subcategory":"Real Estate Agent",
            "type":"Services"
        },
        {
            "category":"Professional",
            "subcategory":"Business Services",
            "type":"Services"
        }
    ],
    "sg:phone":"+1 252 725 0433",
    "sg:postcode":"28516",
    "sg:province":"NC",
    "sg:tags":[
        "inspection"
    ],
    "wof:name":"Homestead Inspection Svc",
    "wof:placetype":"venue"
},
  "geometry": {"coordinates":[-76.673615,34.808127],"type":"Point"}
}