{
  "type": "Feature",
  "properties": {
    "addr:full":"10 Cedar Hill Dr Asheville NC 28803",
    "addr:housenumber":"10",
    "addr:postcode":"28803",
    "addr:street":"Cedar Hill Dr",
    "iso:country":"US",
    "sg:address":"10 Cedar Hill Dr",
    "sg:city":"Asheville",
    "sg:classifiers":[
        {
            "category":"Manufacturing",
            "subcategory":"Toys & Sporting Goods",
            "type":"Manufacturing & Wholesale Goods"
        }
    ],
    "sg:phone":"+1 828 277 1170",
    "sg:postcode":"28803",
    "sg:province":"NC",
    "sg:tags":[
        "mfg"
    ],
    "wof:name":"G & H At Lake Lure LLC",
    "wof:placetype":"venue"
},
  "geometry": {"coordinates":[-82.54776,35.518407],"type":"Point"}
}