{
  "type": "Feature",
  "properties": {
    "iso:country":"US",
    "sg:address":"364 N River Rd",
    "sg:city":"Camden",
    "sg:classifiers":[
        {
            "category":"Wholesale",
            "subcategory":"Hardware",
            "type":"Manufacturing & Wholesale Goods"
        },
        {
            "category":"Retail",
            "subcategory":"Repair Shop",
            "type":"Services"
        }
    ],
    "sg:phone":"+1 252 336 2791",
    "sg:postcode":"27921",
    "sg:province":"NC",
    "sg:tags":[
        "water",
        "equipment",
        "plumbing",
        "softening"
    ],
    "wof:name":"Buds Water Conditioning Inc",
    "wof:placetype":"venue"
},
  "geometry": {"coordinates":[-76.09537899999999,36.337423],"type":"Point"}
}