{
  "type": "Feature",
  "properties": {
    "iso:country":"US",
    "sg:address":"305 W Fleming Dr",
    "sg:city":"Morganton",
    "sg:classifiers":[
        {
            "category":"Shopping",
            "subcategory":"Computers & Home Electronics",
            "type":"Retail Goods"
        }
    ],
    "sg:phone":"+1 828 430 8309",
    "sg:postcode":"28655",
    "sg:province":"NC",
    "sg:tags":[
        "equipment",
        "dealer"
    ],
    "wof:name":"Select Tech Solutions",
    "wof:placetype":"venue"
},
  "geometry": {"coordinates":[-81.68390100000001,35.734675],"type":"Point"}
}