{
  "type": "Feature",
  "properties": {
    "iso:country":"US",
    "sg:address":"2317 Riddle Rd",
    "sg:city":"Durham",
    "sg:classifiers":[
        {
            "category":"Wholesale",
            "subcategory":"Motor Vehicles",
            "type":"Manufacturing & Wholesale Goods"
        }
    ],
    "sg:phone":"+1 919 957 1211",
    "sg:postcode":"27703",
    "sg:province":"NC",
    "sg:tags":[
        "auction",
        "automobile"
    ],
    "wof:name":"Triangle Auto Auction",
    "wof:placetype":"venue"
},
  "geometry": {"coordinates":[-78.881567,35.95689],"type":"Point"}
}