{
  "type": "Feature",
  "properties": {
    "iso:country":"US",
    "sg:address":"1627 Spencer Mountain Rd",
    "sg:city":"Gastonia",
    "sg:classifiers":[
        {
            "category":"Manufacturing",
            "subcategory":"Motor Vehicles & Parts",
            "type":"Manufacturing & Wholesale Goods"
        }
    ],
    "sg:phone":"+1 704 824 5996",
    "sg:postcode":"28054",
    "sg:province":"NC",
    "sg:tags":[
        "automobile",
        "supply"
    ],
    "wof:name":"BMI Inc",
    "wof:placetype":"venue"
},
  "geometry": {"coordinates":[-81.130405,35.286253],"type":"Point"}
}