{
  "type": "Feature",
  "properties": {
    "addr:full":"1260 State Rd 343 South Mills NC 27976",
    "addr:housenumber":"1260",
    "addr:postcode":"27976",
    "addr:street":"State Rd 343 South",
    "iso:country":"US",
    "sg:address":"1260 State Rd 343",
    "sg:city":"South Mills",
    "sg:classifiers":[
        {
            "category":"Organizations",
            "subcategory":"Religious Organization",
            "type":"Services"
        }
    ],
    "sg:phone":"+1   ",
    "sg:postcode":"27976",
    "sg:province":"NC",
    "wof:name":"Pleasent Branch Baptist Church",
    "wof:placetype":"venue"
},
  "geometry": {"coordinates":[-76.30920500000001,36.435078],"type":"Point"}
}