{
  "type": "Feature",
  "properties": {
    "iso:country":"US",
    "sg:address":"4413 Republic Ct NW",
    "sg:city":"Concord",
    "sg:classifiers":[
        {
            "category":"Wholesale",
            "subcategory":"Construction Materials",
            "type":"Manufacturing & Wholesale Goods"
        }
    ],
    "sg:phone":"+1 704 788 4182",
    "sg:postcode":"28027",
    "sg:province":"NC",
    "sg:tags":[
        "wholesaler",
        "building"
    ],
    "wof:name":"Buffalo Forming Equipment Inc",
    "wof:placetype":"venue"
},
  "geometry": {"coordinates":[-80.651022,35.421258],"type":"Point"}
}