{
  "type": "Feature",
  "properties": {
    "iso:country":"US",
    "sg:address":"75 Tennessee St",
    "sg:city":"Murphy",
    "sg:classifiers":[
        {
            "category":"Health Services",
            "subcategory":"Chiropractor",
            "type":"Services"
        }
    ],
    "sg:phone":"+1 828 835 7997",
    "sg:postcode":"28906",
    "sg:province":"NC",
    "wof:name":"Family Life Chiropractic Ctr",
    "wof:placetype":"venue"
},
  "geometry": {"coordinates":[-84.034531,35.088083],"type":"Point"}
}