{
  "type": "Feature",
  "properties": {
    "iso:country":"US",
    "sg:address":"3760 Richard Wright Rd",
    "sg:city":"Tabor City",
    "sg:classifiers":[
        {
            "category":"Education",
            "subcategory":"Special Training",
            "type":"Public Place"
        }
    ],
    "sg:phone":"+1   ",
    "sg:postcode":"28463",
    "sg:province":"NC",
    "wof:name":"Meta Mercer Music Studio",
    "wof:placetype":"venue"
},
  "geometry": {"coordinates":[-78.819998,34.151892],"type":"Point"}
}