{
  "type": "Feature",
  "properties": {
    "iso:country":"US",
    "sg:address":"13435 Walkers Creek Dr",
    "sg:city":"Charlotte",
    "sg:classifiers":[
        {
            "category":"Shopping",
            "subcategory":"Gifts & Souvenirs",
            "type":"Retail Goods"
        }
    ],
    "sg:phone":"+1 704 504 1533",
    "sg:postcode":"28273",
    "sg:province":"NC",
    "wof:name":"Sterling Gifts",
    "wof:placetype":"venue"
},
  "geometry": {"coordinates":[-80.97851300000001,35.100709],"type":"Point"}
}