{
  "type": "Feature",
  "properties": {
    "iso:country":"US",
    "sg:address":"4642 Wilkinson Blvd",
    "sg:city":"Charlotte",
    "sg:classifiers":[
        {
            "category":"Autos & Motor Vehicles",
            "subcategory":"Fuel & Gas Station",
            "type":"Retail Goods"
        }
    ],
    "sg:phone":"+1 704 392 9905",
    "sg:postcode":"28208",
    "sg:province":"NC",
    "sg:tags":[
        "oil"
    ],
    "wof:name":"Phillips 66",
    "wof:placetype":"venue"
},
  "geometry": {"coordinates":[-80.915606,35.228707],"type":"Point"}
}