{
  "type": "Feature",
  "properties": {
    "addr:full":"2288 Pritchard Rd Clayton NC 27527",
    "addr:housenumber":"2288",
    "addr:postcode":"27527",
    "addr:street":"Pritchard Rd",
    "iso:country":"US",
    "sg:address":"2288 Pritchard Rd",
    "sg:city":"Clayton",
    "sg:classifiers":[
        {
            "category":"Education",
            "subcategory":"School",
            "type":"Public Place"
        }
    ],
    "sg:phone":"+1 919 359 1666",
    "sg:postcode":"27527",
    "sg:province":"NC",
    "wof:name":"Riverwood Middle Sch Nutrition",
    "wof:placetype":"venue"
},
  "geometry": {"coordinates":[-76.287881,36.332423],"type":"Point"}
}