{
  "type": "Feature",
  "properties": {
    "iso:country":"US",
    "sg:address":"2931 Hope Mills Rd",
    "sg:city":"Fayetteville",
    "sg:classifiers":[
        {
            "category":"Retail",
            "subcategory":"Auto Repair",
            "type":"Services"
        },
        {
            "category":"Autos & Motor Vehicles",
            "subcategory":"Auto Supplies",
            "type":"Retail Goods"
        }
    ],
    "sg:phone":"+1 910 426 3260",
    "sg:postcode":"28306",
    "sg:province":"NC",
    "sg:tags":[
        "stereo",
        "automobile",
        "coating",
        "tinting",
        "glass",
        "radio"
    ],
    "wof:name":"Tint & Stereo Plus",
    "wof:placetype":"venue"
},
  "geometry": {"coordinates":[-78.96507800000001,34.986562],"type":"Point"}
}