{
  "type": "Feature",
  "properties": {
    "addr:full":"3150 S Evans St Greenville NC 27834",
    "addr:housenumber":"3150",
    "addr:postcode":"27834",
    "addr:street":"S Evans St",
    "iso:country":"US",
    "sg:address":"3150 S Evans St",
    "sg:city":"Greenville",
    "sg:classifiers":[
        {
            "category":"Shopping",
            "subcategory":"Clothing, Apparel, & Fashions",
            "type":"Retail Goods"
        }
    ],
    "sg:phone":"+1 252 355 2325",
    "sg:postcode":"27834",
    "sg:province":"NC",
    "sg:tags":[
        "shop",
        "bridal"
    ],
    "wof:name":"David's Bridal",
    "wof:placetype":"venue"
},
  "geometry": {"coordinates":[-77.382137,35.575697],"type":"Point"}
}