{
  "type": "Feature",
  "properties": {
    "iso:country":"US",
    "sg:address":"3829 High Point Rd",
    "sg:city":"Greensboro",
    "sg:classifiers":[
        {
            "category":"Banks & Credit Unions",
            "subcategory":"Bank",
            "type":"Services"
        }
    ],
    "sg:phone":"+1 336 294 8885",
    "sg:postcode":"27407",
    "sg:province":"NC",
    "sg:tags":[
        "cashing",
        "personal",
        "check",
        "institution"
    ],
    "wof:name":"Advance America",
    "wof:placetype":"venue"
},
  "geometry": {"coordinates":[-79.858019,36.037529],"type":"Point"}
}