{
  "type": "Feature",
  "properties": {
    "iso:country":"US",
    "sg:address":"65 N Belgrade Ave",
    "sg:city":"Garland",
    "sg:classifiers":[
        {
            "category":"Retail",
            "subcategory":"Funeral Services",
            "type":"Services"
        }
    ],
    "sg:phone":"+1 910 529 1341",
    "sg:postcode":"28441",
    "sg:province":"NC",
    "sg:tags":[
        "director"
    ],
    "wof:name":"Summerville-Boykin Mortuary",
    "wof:placetype":"venue"
},
  "geometry": {"coordinates":[-78.39121299999999,34.783065],"type":"Point"}
}