{
  "type": "Feature",
  "properties": {
    "iso:country":"US",
    "sg:address":"52 Broadway St",
    "sg:city":"Asheville",
    "sg:classifiers":[
        {
            "category":"Shopping",
            "subcategory":"Used Merchandise",
            "type":"Retail Goods"
        }
    ],
    "sg:phone":"+1 828 251 5253",
    "sg:postcode":"28801",
    "sg:province":"NC",
    "sg:tags":[
        "antique"
    ],
    "wof:name":"Beauregard's Magnolia",
    "wof:placetype":"venue"
},
  "geometry": {"coordinates":[-82.552474,35.597794],"type":"Point"}
}