{
  "type": "Feature",
  "properties": {
    "iso:country":"US",
    "sg:address":"11205 Reames Rd",
    "sg:city":"Charlotte",
    "sg:classifiers":[
        {
            "category":"Building & Trades",
            "subcategory":"Construction",
            "type":"Services"
        }
    ],
    "sg:phone":"+1 704 598 6969",
    "sg:postcode":"28269",
    "sg:province":"NC",
    "sg:tags":[
        "excavating",
        "tank",
        "grading",
        "recycling",
        "removal",
        "concrete",
        "contractor"
    ],
    "sg:website":"www.mcgrawcorp.com",
    "wof:name":"Mc Graw Inc",
    "wof:placetype":"venue"
},
  "geometry": {"coordinates":[-80.833035,35.350141],"type":"Point"}
}