{
  "type": "Feature",
  "properties": {
    "addr:full":"125 Bridlewood Trl Horse Shoe NC 28759",
    "addr:housenumber":"125",
    "addr:postcode":"28759",
    "addr:street":"Bridlewood Trl",
    "iso:country":"US",
    "sg:address":"125 Bridlewood Trl",
    "sg:city":"Horse Shoe",
    "sg:classifiers":[
        {
            "category":"Shopping",
            "subcategory":"Stationery & Office Supplies",
            "type":"Retail Goods"
        }
    ],
    "sg:phone":"+1 828 891 9408",
    "sg:postcode":"28759",
    "sg:province":"NC",
    "wof:name":"Hamco Western Carolina",
    "wof:placetype":"venue"
},
  "geometry": {"coordinates":[-78.835182,35.177142],"type":"Point"}
}