{
  "type": "Feature",
  "properties": {
    "addr:full":"1018 Asheville Hwy Hendersonville NC 28791",
    "addr:housenumber":"1018",
    "addr:postcode":"28791",
    "addr:street":"Asheville Hwy",
    "iso:country":"US",
    "sg:address":"1018 Asheville Hwy",
    "sg:city":"Hendersonville",
    "sg:classifiers":[
        {
            "category":"Shopping",
            "subcategory":"Bicycles & Sporting Goods",
            "type":"Retail Goods"
        }
    ],
    "sg:phone":"+1 828 693 3211",
    "sg:postcode":"28791",
    "sg:province":"NC",
    "wof:name":"Sports Cellar",
    "wof:placetype":"venue"
},
  "geometry": {"coordinates":[-82.464202,35.324434],"type":"Point"}
}