{
  "type": "Feature",
  "properties": {
    "iso:country":"US",
    "sg:address":"470 B Leazer Rd",
    "sg:city":"Salisbury",
    "sg:classifiers":[
        {
            "category":"Building & Trades",
            "subcategory":"Construction",
            "type":"Services"
        }
    ],
    "sg:phone":"+1 704 638 0722",
    "sg:postcode":"28147",
    "sg:province":"NC",
    "sg:tags":[
        "house"
    ],
    "wof:name":"Locktite Log Systems",
    "wof:placetype":"venue"
},
  "geometry": {"coordinates":[-80.57692400000001,35.632404],"type":"Point"}
}