{
  "type": "Feature",
  "properties": {
    "iso:country":"US",
    "sg:address":"424 S McDowell St",
    "sg:city":"Raleigh",
    "sg:classifiers":[
        {
            "category":"Bars & Pubs",
            "type":"Food & Drink"
        }
    ],
    "sg:phone":"+1 919 831 1005",
    "sg:postcode":"27601",
    "sg:province":"NC",
    "sg:tags":[
        "club",
        "night"
    ],
    "wof:name":"King's",
    "wof:placetype":"venue"
},
  "geometry": {"coordinates":[-78.64205200000001,35.775359],"type":"Point"}
}