{
  "type": "Feature",
  "properties": {
    "addr:full":"508 Crowfields Ln Asheville NC 28803",
    "addr:housenumber":"508",
    "addr:postcode":"28803",
    "addr:street":"Crowfields Ln",
    "iso:country":"US",
    "sg:address":"508 Crowfields Ln",
    "sg:city":"Asheville",
    "sg:classifiers":[
        {
            "category":"Professional",
            "subcategory":"Management & Consulting",
            "type":"Services"
        }
    ],
    "sg:phone":"+1   ",
    "sg:postcode":"28803",
    "sg:province":"NC",
    "wof:name":"John F Cress",
    "wof:placetype":"venue"
},
  "geometry": {"coordinates":[-82.5286,35.505803],"type":"Point"}
}