{
  "type": "Feature",
  "properties": {
    "addr:full":"1019 Edna St Shelby NC 28152",
    "addr:housenumber":"1019",
    "addr:postcode":"28152",
    "addr:street":"Edna St",
    "iso:country":"US",
    "sg:address":"1019 Edna St",
    "sg:city":"Shelby",
    "sg:classifiers":[
        {
            "category":"Building & Trades",
            "subcategory":"Landscaping Services",
            "type":"Services"
        }
    ],
    "sg:phone":"+1 704 482 0230",
    "sg:postcode":"28152",
    "sg:province":"NC",
    "sg:tags":[
        "contractor"
    ],
    "wof:name":"Beams Landscaping",
    "wof:placetype":"venue"
},
  "geometry": {"coordinates":[-81.468042,35.257837],"type":"Point"}
}