{
  "type": "Feature",
  "properties": {
    "iso:country":"US",
    "sg:address":"1147 Salisbury Rd",
    "sg:city":"Statesville",
    "sg:classifiers":[
        {
            "category":"Building & Trades",
            "subcategory":"Construction",
            "type":"Services"
        }
    ],
    "sg:phone":"+1 704 873 3755",
    "sg:postcode":"28625",
    "sg:province":"NC",
    "sg:tags":[
        "maintenance",
        "contractor"
    ],
    "wof:name":"Iredell Statesville Sch Mntnc",
    "wof:placetype":"venue"
},
  "geometry": {"coordinates":[-80.863238,35.774756],"type":"Point"}
}