{
  "type": "Feature",
  "properties": {
    "addr:full":"160 Pointe South Dr Randleman NC 27317",
    "addr:housenumber":"160",
    "addr:postcode":"27317",
    "addr:street":"Pointe South Dr",
    "iso:country":"US",
    "sg:address":"160 Pointe South Dr",
    "sg:city":"Randleman",
    "sg:classifiers":[
        {
            "category":"Social Services",
            "subcategory":"Child Care",
            "type":"Services"
        }
    ],
    "sg:phone":"+1 336 495 0517",
    "sg:postcode":"27317",
    "sg:province":"NC",
    "sg:tags":[
        "day"
    ],
    "wof:name":"Good Shepherd After School",
    "wof:placetype":"venue"
},
  "geometry": {"coordinates":[-79.811082,35.80115],"type":"Point"}
}