{
  "type": "Feature",
  "properties": {
    "addr:full":"6801 Northlake Mall Dr Charlotte NC 28216",
    "addr:housenumber":"6801",
    "addr:postcode":"28216",
    "addr:street":"Northlake Mall Dr",
    "iso:country":"US",
    "sg:address":"6801 Northlake Mall Dr",
    "sg:city":"Charlotte",
    "sg:classifiers":[
        {
            "category":"Coffee & Tea",
            "type":"Food & Drink"
        }
    ],
    "sg:menulink":"http://www.allmenus.com/nc/long-creek/125063-starbucks-coffee/menu/",
    "sg:phone":"+1 704 597 5883",
    "sg:postcode":"28216",
    "sg:province":"NC",
    "sg:tags":[
        "american"
    ],
    "wof:name":"Starbucks Coffee",
    "wof:placetype":"venue"
},
  "geometry": {"coordinates":[-80.855135,35.353322],"type":"Point"}
}