{
  "type": "Feature",
  "properties": {
    "iso:country":"US",
    "sg:address":"7881 Webbs Mill Rd",
    "sg:city":"Spring Hope",
    "sg:classifiers":[
        {
            "category":"Retail",
            "subcategory":"Funeral Services",
            "type":"Services"
        }
    ],
    "sg:phone":"+1 252 478 5560",
    "sg:postcode":"27882",
    "sg:province":"NC",
    "sg:tags":[
        "director"
    ],
    "wof:name":"Spring Hope Funeral Home",
    "wof:placetype":"venue"
},
  "geometry": {"coordinates":[-78.126846,35.938733],"type":"Point"}
}