{
  "type": "Feature",
  "properties": {
    "addr:full":"3523 Spicebush Trl Greensboro NC 27410",
    "addr:housenumber":"3523",
    "addr:postcode":"27410",
    "addr:street":"Spicebush Trl",
    "iso:country":"US",
    "sg:address":"3523 Spicebush Trl",
    "sg:city":"Greensboro",
    "sg:classifiers":[
        {
            "category":"Wholesale",
            "subcategory":"Chemicals & Plastics",
            "type":"Manufacturing & Wholesale Goods"
        }
    ],
    "sg:phone":"+1 336 288 2561",
    "sg:postcode":"27410",
    "sg:province":"NC",
    "wof:name":"Dic Americas Inc",
    "wof:placetype":"venue"
},
  "geometry": {"coordinates":[-79.854782,36.115866],"type":"Point"}
}