{
  "type": "Feature",
  "properties": {
    "iso:country":"US",
    "sg:address":"633 Summit St",
    "sg:city":"Winston Salem",
    "sg:classifiers":[
        {
            "category":"Travel",
            "subcategory":"Campground",
            "type":"Entertainment"
        }
    ],
    "sg:phone":"+1 336 761 1040",
    "sg:postcode":"27101",
    "sg:province":"NC",
    "sg:tags":[
        "camp"
    ],
    "sg:website":"www.enf.org",
    "wof:name":"Eagle's Nest Foundation",
    "wof:placetype":"venue"
},
  "geometry": {"coordinates":[-80.257617,36.100877],"type":"Point"}
}