{
  "type": "Feature",
  "properties": {
    "addr:full":"10120 Albemarle Rd Charlotte NC 28227",
    "addr:housenumber":"10120",
    "addr:postcode":"28227",
    "addr:street":"Albemarle Rd",
    "iso:country":"US",
    "sg:address":"10120 Albemarle Rd",
    "sg:city":"Charlotte",
    "sg:classifiers":[
        {
            "category":"Retail",
            "subcategory":"Repair Shop",
            "type":"Services"
        }
    ],
    "sg:phone":"+1 704 545 2629",
    "sg:postcode":"28227",
    "sg:province":"NC",
    "sg:tags":[
        "scooter",
        "motorcycle",
        "motor"
    ],
    "wof:name":"Cisco's American Motorcycle",
    "wof:placetype":"venue"
},
  "geometry": {"coordinates":[-80.67171399999999,35.208565],"type":"Point"}
}