{
  "type": "Feature",
  "properties": {
    "addr:full":"2323 Underwood Rd Fayetteville NC 28312",
    "addr:housenumber":"2323",
    "addr:postcode":"28312",
    "addr:street":"Underwood Rd",
    "iso:country":"US",
    "sg:address":"2323 Underwood Rd",
    "sg:city":"Fayetteville",
    "sg:classifiers":[
        {
            "category":"Professional",
            "subcategory":"Management & Consulting",
            "type":"Services"
        }
    ],
    "sg:phone":"+1   ",
    "sg:postcode":"28312",
    "sg:province":"NC",
    "wof:name":"Concord Associated Marketing",
    "wof:placetype":"venue"
},
  "geometry": {"coordinates":[-78.84787799999999,35.088048],"type":"Point"}
}