{
  "type": "Feature",
  "properties": {
    "addr:full":"12516 Capital Blvd Wake Forest NC 27587",
    "addr:housenumber":"12516",
    "addr:postcode":"27587",
    "addr:street":"Capital Blvd",
    "iso:country":"US",
    "sg:address":"12516 Capital Blvd",
    "sg:city":"Wake Forest",
    "sg:classifiers":[
        {
            "category":"Personal",
            "type":"Services"
        }
    ],
    "sg:phone":"+1   ",
    "sg:postcode":"27587",
    "sg:province":"NC",
    "wof:name":"A Beautiful Tan",
    "wof:placetype":"venue"
},
  "geometry": {"coordinates":[-78.53378600000001,35.987394],"type":"Point"}
}