{
  "type": "Feature",
  "properties": {
    "addr:full":"1601 Sound Watch Dr Wilmington NC 28409",
    "addr:housenumber":"1601",
    "addr:postcode":"28409",
    "addr:street":"Sound Watch Dr",
    "iso:country":"US",
    "sg:address":"1601 Sound Watch Dr",
    "sg:city":"Wilmington",
    "sg:classifiers":[
        {
            "category":"Professional",
            "type":"Services"
        }
    ],
    "sg:phone":"+1 910 796 0448",
    "sg:postcode":"28409",
    "sg:province":"NC",
    "sg:tags":[
        "establishment"
    ],
    "wof:name":"Intercoastal Watch",
    "wof:placetype":"venue"
},
  "geometry": {"coordinates":[-77.876441,34.117155],"type":"Point"}
}