{
  "type": "Feature",
  "properties": {
    "addr:full":"10506 Chapel Hill Rd Morrisville NC 27560",
    "addr:housenumber":"10506",
    "addr:postcode":"27560",
    "addr:street":"Chapel Hill Rd",
    "iso:country":"US",
    "sg:address":"10506 Chapel Hill Rd",
    "sg:city":"Morrisville",
    "sg:classifiers":[
        {
            "category":"Home & Garden",
            "subcategory":"Building Materials",
            "type":"Retail Goods"
        }
    ],
    "sg:phone":"+1 919 468 9091",
    "sg:postcode":"27560",
    "sg:province":"NC",
    "sg:website":"www.bestsupply.com",
    "wof:name":"Best Supply",
    "wof:placetype":"venue"
},
  "geometry": {"coordinates":[-78.831756,35.839866],"type":"Point"}
}