{
  "type": "Feature",
  "properties": {
    "addr:full":"232 N Bridge St Washington NC 27889",
    "addr:housenumber":"232",
    "addr:postcode":"27889",
    "addr:street":"N Bridge St",
    "iso:country":"US",
    "sg:address":"232 N Bridge St",
    "sg:city":"Washington",
    "sg:classifiers":[
        {
            "category":"Shopping",
            "subcategory":"Used Merchandise",
            "type":"Retail Goods"
        }
    ],
    "sg:phone":"+1 252 946 0687",
    "sg:postcode":"27889",
    "sg:province":"NC",
    "sg:tags":[
        "furniture"
    ],
    "wof:name":"Kapricorn Korners",
    "wof:placetype":"venue"
},
  "geometry": {"coordinates":[-77.05968,35.546681],"type":"Point"}
}