{
  "type": "Feature",
  "properties": {
    "addr:full":"2555 Capitol Dr Creedmoor NC 27522",
    "addr:housenumber":"2555",
    "addr:postcode":"27522",
    "addr:street":"Capitol Dr",
    "iso:country":"US",
    "sg:address":"2555 Capitol Dr",
    "sg:city":"Creedmoor",
    "sg:classifiers":[
        {
            "category":"Restaurant",
            "type":"Food & Drink"
        },
        {
            "category":"Food & Beverages",
            "subcategory":"Groceries & Convenience Stores",
            "type":"Retail Goods"
        }
    ],
    "sg:phone":"+1 919 592 1836",
    "sg:postcode":"27522",
    "sg:province":"NC",
    "sg:tags":[
        "american",
        "latin",
        "mexican"
    ],
    "wof:name":"Tienda La Familia",
    "wof:placetype":"venue"
},
  "geometry": {"coordinates":[-78.718864,36.143013],"type":"Point"}
}