{
  "type": "Feature",
  "properties": {
    "addr:full":"2235 Massengill Pond Rd Angier NC 27501",
    "addr:housenumber":"2235",
    "addr:postcode":"27501",
    "addr:street":"Massengill Pond Rd",
    "iso:country":"US",
    "sg:address":"2235 Massengill Pond Rd",
    "sg:city":"Angier",
    "sg:classifiers":[
        {
            "category":"Social Services",
            "subcategory":"Child Care",
            "type":"Services"
        }
    ],
    "sg:phone":"+1 919 639 8734",
    "sg:postcode":"27501",
    "sg:province":"NC",
    "sg:tags":[
        "day"
    ],
    "wof:name":"Kidsville Child Care Center",
    "wof:placetype":"venue"
},
  "geometry": {"coordinates":[-78.653144,35.496926],"type":"Point"}
}