{
  "type": "Feature",
  "properties": {
    "iso:country":"US",
    "sg:address":"900 W West St",
    "sg:city":"Southport",
    "sg:classifiers":[
        {
            "category":"Real Estate",
            "subcategory":"Developer",
            "type":"Services"
        }
    ],
    "sg:phone":"+1 910 457 4561",
    "sg:postcode":"28461",
    "sg:province":"NC",
    "wof:name":"Sweeney Family LLC",
    "wof:placetype":"venue"
},
  "geometry": {"coordinates":[-78.02700900000001,33.919386],"type":"Point"}
}