{
  "type": "Feature",
  "properties": {
    "iso:country":"US",
    "sg:address":"4821 Hargrove Rd",
    "sg:city":"Raleigh",
    "sg:classifiers":[
        {
            "category":"Shopping",
            "subcategory":"Musical Instruments",
            "type":"Retail Goods"
        }
    ],
    "sg:phone":"+1 919 878 0001",
    "sg:postcode":"27616",
    "sg:province":"NC",
    "sg:tags":[
        "music",
        "dealer"
    ],
    "wof:name":"Miller Music",
    "wof:placetype":"venue"
},
  "geometry": {"coordinates":[-78.59097300000001,35.850212],"type":"Point"}
}