{
  "type": "Feature",
  "properties": {
    "iso:country":"US",
    "sg:address":"214 N Tryon St",
    "sg:city":"Charlotte",
    "sg:classifiers":[
        {
            "category":"Professional",
            "subcategory":"Accounting & Tax Preparation",
            "type":"Services"
        }
    ],
    "sg:phone":"+1 704 344 7571",
    "sg:postcode":"28202",
    "sg:province":"NC",
    "sg:tags":[
        "accountant"
    ],
    "sg:website":"www.pwc.com",
    "wof:name":"Price Waterhouse Coopers",
    "wof:placetype":"venue"
},
  "geometry": {"coordinates":[-80.840915,35.228605],"type":"Point"}
}