{
  "type": "Feature",
  "properties": {
    "addr:full":"71 Cliffview Dr Asheville NC 28803",
    "addr:housenumber":"71",
    "addr:postcode":"28803",
    "addr:street":"Cliffview Dr",
    "iso:country":"US",
    "sg:address":"71 Cliffview Dr",
    "sg:city":"Asheville",
    "sg:classifiers":[
        {
            "category":"Restaurant",
            "type":"Food & Drink"
        }
    ],
    "sg:phone":"+1 828 296 0961",
    "sg:postcode":"28803",
    "sg:province":"NC",
    "sg:tags":[
        "eating"
    ],
    "wof:name":"Out In Asheville Inc",
    "wof:placetype":"venue"
},
  "geometry": {"coordinates":[-82.461665,35.552653],"type":"Point"}
}