{
  "type": "Feature",
  "properties": {
    "addr:full":"5401 Capital Blvd Raleigh NC 27616",
    "addr:housenumber":"5401",
    "addr:postcode":"27616",
    "addr:street":"Capital Blvd",
    "iso:country":"US",
    "sg:address":"5401 Capital Blvd",
    "sg:city":"Raleigh",
    "sg:classifiers":[
        {
            "category":"Autos & Motor Vehicles",
            "subcategory":"Automobile Sales",
            "type":"Retail Goods"
        }
    ],
    "sg:phone":"+1 919 872 1011",
    "sg:postcode":"27616",
    "sg:province":"NC",
    "sg:tags":[
        "car",
        "dealer"
    ],
    "wof:name":"Leith Mitsubishi",
    "wof:placetype":"venue"
},
  "geometry": {"coordinates":[-78.581665,35.861314],"type":"Point"}
}