{
  "type": "Feature",
  "properties": {
    "iso:country":"US",
    "sg:address":"108 Robbins Ave",
    "sg:city":"Jamestown",
    "sg:classifiers":[
        {
            "category":"Building & Trades",
            "subcategory":"Landscaping Services",
            "type":"Services"
        }
    ],
    "sg:phone":"+1 336 812 8198",
    "sg:postcode":"27282",
    "sg:province":"NC",
    "sg:tags":[
        "landscape",
        "contractor"
    ],
    "wof:name":"Moss Landscaping Co",
    "wof:placetype":"venue"
},
  "geometry": {"coordinates":[-79.954429,35.991113],"type":"Point"}
}