{
  "type": "Feature",
  "properties": {
    "iso:country":"US",
    "sg:address":"18700 Shearer Rd",
    "sg:city":"Davidson",
    "sg:classifiers":[
        {
            "category":"Building & Trades",
            "subcategory":"Construction",
            "type":"Services"
        }
    ],
    "sg:phone":"+1 704 892 1451",
    "sg:postcode":"28036",
    "sg:province":"NC",
    "sg:tags":[
        "house"
    ],
    "wof:name":"T&B Remodeling",
    "wof:placetype":"venue"
},
  "geometry": {"coordinates":[-80.780648,35.467168],"type":"Point"}
}