{
  "type": "Feature",
  "properties": {
    "iso:country":"US",
    "sg:address":"110 Fairview St",
    "sg:city":"Locust",
    "sg:classifiers":[
        {
            "category":"Freight",
            "type":"Transportation"
        }
    ],
    "sg:phone":"+1 704 888 8153",
    "sg:postcode":"28097",
    "sg:province":"NC",
    "sg:tags":[
        "operator",
        "local",
        "trucking"
    ],
    "wof:name":"Shadow Ridge Inc",
    "wof:placetype":"venue"
},
  "geometry": {"coordinates":[-80.42303,35.260275],"type":"Point"}
}