{
  "type": "Feature",
  "properties": {
    "addr:full":"100 Europa Dr Chapel Hill NC 27517",
    "addr:housenumber":"100",
    "addr:postcode":"27517",
    "addr:street":"Europa Dr",
    "iso:country":"US",
    "sg:address":"100 Europa Dr",
    "sg:city":"Chapel Hill",
    "sg:classifiers":[
        {
            "category":"Professional",
            "subcategory":"Lawyer & Legal Services",
            "type":"Services"
        }
    ],
    "sg:phone":"+1   ",
    "sg:postcode":"27517",
    "sg:province":"NC",
    "wof:name":"Clement Nathaniel E Assoc Pllc",
    "wof:placetype":"venue"
},
  "geometry": {"coordinates":[-79.01812099999999,35.940487],"type":"Point"}
}