{
  "type": "Feature",
  "properties": {
    "addr:full":"4827 Arbor Rd Fayetteville NC 28311",
    "addr:housenumber":"4827",
    "addr:postcode":"28311",
    "addr:street":"Arbor Rd",
    "iso:country":"US",
    "sg:address":"4827 Arbor Rd",
    "sg:city":"Fayetteville",
    "sg:classifiers":[
        {
            "category":"Building & Trades",
            "subcategory":"Electrical",
            "type":"Services"
        }
    ],
    "sg:phone":"+1 910 630 1990",
    "sg:postcode":"28311",
    "sg:province":"NC",
    "sg:tags":[
        "electrical",
        "contractor"
    ],
    "wof:name":"Caw Electric",
    "wof:placetype":"venue"
},
  "geometry": {"coordinates":[-78.882124,35.127127],"type":"Point"}
}