{
  "type": "Feature",
  "properties": {
    "addr:full":"1302 N Salem St Apex NC 27502",
    "addr:housenumber":"1302",
    "addr:postcode":"27502",
    "addr:street":"N Salem St",
    "iso:country":"US",
    "sg:address":"1302 N Salem St",
    "sg:city":"Apex",
    "sg:classifiers":[
        {
            "category":"Personal",
            "type":"Services"
        },
        {
            "category":"Building & Trades",
            "subcategory":"Cleaning & Sanitation",
            "type":"Services"
        }
    ],
    "sg:phone":"+1 919 363 9274",
    "sg:postcode":"27502",
    "sg:province":"NC",
    "sg:tags":[
        "house",
        "cleaning-industrial",
        "washing",
        "cleaning-exterior",
        "contractor"
    ],
    "sg:website":"http://www.kellysnc.com",
    "wof:name":"Kellys NC Hot Pressure Washing",
    "wof:placetype":"venue"
},
  "geometry": {"coordinates":[-78.851569,35.746526],"type":"Point"}
}