{
  "type": "Feature",
  "properties": {
    "addr:full":"716 Raleigh Rd Rocky Mount NC 27803",
    "addr:housenumber":"716",
    "addr:postcode":"27803",
    "addr:street":"Raleigh Rd",
    "iso:country":"US",
    "sg:address":"716 Raleigh Rd",
    "sg:city":"Rocky Mount",
    "sg:classifiers":[
        {
            "category":"Food & Beverages",
            "subcategory":"Liquor & Beverages",
            "type":"Retail Goods"
        }
    ],
    "sg:phone":"+1 252 442 2057",
    "sg:postcode":"27803",
    "sg:province":"NC",
    "sg:tags":[
        "alcoholic"
    ],
    "wof:name":"Nash County ABC Board",
    "wof:placetype":"venue"
},
  "geometry": {"coordinates":[-77.809949,35.933612],"type":"Point"}
}