{
  "type": "Feature",
  "properties": {
    "iso:country":"US",
    "sg:address":"214 E Hammond St",
    "sg:city":"Durham",
    "sg:classifiers":[
        {
            "category":"Professional",
            "subcategory":"Management & Consulting",
            "type":"Services"
        }
    ],
    "sg:phone":"+1   ",
    "sg:postcode":"27704",
    "sg:province":"NC",
    "wof:name":"Valjeanne Estes",
    "wof:placetype":"venue"
},
  "geometry": {"coordinates":[-78.889974,36.024633],"type":"Point"}
}