{
  "type": "Feature",
  "properties": {
    "iso:country":"US",
    "sg:address":"1221 Woodridge Center Dr",
    "sg:city":"Charlotte",
    "sg:classifiers":[
        {
            "category":"Professional",
            "subcategory":"Employment Agencies",
            "type":"Services"
        }
    ],
    "sg:phone":"+1 704 329 8180",
    "sg:postcode":"28217",
    "sg:province":"NC",
    "sg:tags":[
        "consultant",
        "search",
        "executive"
    ],
    "sg:website":"www.teksystems.com",
    "wof:name":"Tek Systems",
    "wof:placetype":"venue"
},
  "geometry": {"coordinates":[-80.901062,35.187592],"type":"Point"}
}