{
  "type": "Feature",
  "properties": {
    "addr:full":"118 Washington St Plymouth NC 27962",
    "addr:housenumber":"118",
    "addr:postcode":"27962",
    "addr:street":"Washington St",
    "iso:country":"US",
    "sg:address":"118 Washington St",
    "sg:city":"Plymouth",
    "sg:classifiers":[
        {
            "category":"Personal",
            "subcategory":"Beauty Salon",
            "type":"Services"
        }
    ],
    "sg:phone":"+1 252 793 4875",
    "sg:postcode":"27962",
    "sg:province":"NC",
    "sg:tags":[
        "shop"
    ],
    "wof:name":"Sandras Hand Painted Treasures",
    "wof:placetype":"venue"
},
  "geometry": {"coordinates":[-76.75067900000001,35.866775],"type":"Point"}
}