{
  "type": "Feature",
  "properties": {
    "iso:country":"US",
    "sg:address":"121 Timber Creek Rd",
    "sg:city":"Advance",
    "sg:classifiers":[
        {
            "category":"Shopping",
            "subcategory":"Computers & Home Electronics",
            "type":"Retail Goods"
        }
    ],
    "sg:phone":"+1 336 998 0937",
    "sg:postcode":"27006",
    "sg:province":"NC",
    "sg:tags":[
        "software"
    ],
    "wof:name":"Carter Equipment & Software",
    "wof:placetype":"venue"
},
  "geometry": {"coordinates":[-80.450965,35.979605],"type":"Point"}
}