{
  "type": "Feature",
  "properties": {
    "iso:country":"US",
    "sg:address":"555 Turnersburg Hwy",
    "sg:city":"Statesville",
    "sg:classifiers":[
        {
            "category":"Professional",
            "type":"Services"
        }
    ],
    "sg:phone":"+1 704 881 0446",
    "sg:postcode":"28625",
    "sg:province":"NC",
    "sg:tags":[
        "establishment"
    ],
    "wof:name":"Marloz Of Statesville",
    "wof:placetype":"venue"
},
  "geometry": {"coordinates":[-80.874544,35.827832],"type":"Point"}
}