{
  "type": "Feature",
  "properties": {
    "addr:full":"4047 State Hwy 242 S Elizabethtown NC 28337",
    "addr:housenumber":"4047",
    "addr:postcode":"28337",
    "addr:street":"State Hwy 242 S",
    "iso:country":"US",
    "sg:address":"4047 State Hwy 242 S",
    "sg:city":"Elizabethtown",
    "sg:classifiers":[
        {
            "category":"Organizations",
            "subcategory":"Religious Organization",
            "type":"Services"
        }
    ],
    "sg:phone":"+1 910 645 4976",
    "sg:postcode":"28337",
    "sg:province":"NC",
    "sg:tags":[
        "church"
    ],
    "wof:name":"Baldwin Branch Baptist Church",
    "wof:placetype":"venue"
},
  "geometry": {"coordinates":[-78.647492,34.592657],"type":"Point"}
}