{
  "type": "Feature",
  "properties": {
    "iso:country":"US",
    "sg:address":"319 N Spence Ave",
    "sg:city":"Goldsboro",
    "sg:classifiers":[
        {
            "category":"Shopping",
            "subcategory":"Clothing, Apparel, & Fashions",
            "type":"Retail Goods"
        }
    ],
    "sg:phone":"+1 919 778 8444",
    "sg:postcode":"27534",
    "sg:province":"NC",
    "wof:name":"Aries Formal Wear",
    "wof:placetype":"venue"
},
  "geometry": {"coordinates":[-77.950678,35.375294],"type":"Point"}
}