{
  "type": "Feature",
  "properties": {
    "iso:country":"US",
    "sg:address":"111 Catherwood Pl",
    "sg:city":"Cary",
    "sg:classifiers":[
        {
            "category":"Professional",
            "subcategory":"Computer Services",
            "type":"Services"
        }
    ],
    "sg:phone":"+1   ",
    "sg:postcode":"27518",
    "sg:province":"NC",
    "sg:tags":[
        "development",
        "web",
        "application"
    ],
    "wof:name":"Indicium Design Inc",
    "wof:placetype":"venue"
},
  "geometry": {"coordinates":[-78.755837,35.754703],"type":"Point"}
}