{
  "type": "Feature",
  "properties": {
    "addr:full":"161 Cari Ln Matthews NC 28104",
    "addr:housenumber":"161",
    "addr:postcode":"28104",
    "addr:street":"Cari Ln",
    "iso:country":"US",
    "sg:address":"161 Cari Ln",
    "sg:city":"Matthews",
    "sg:classifiers":[
        {
            "category":"Building & Trades",
            "subcategory":"Construction",
            "type":"Services"
        }
    ],
    "sg:phone":"+1 704 846 8424",
    "sg:postcode":"28104",
    "sg:province":"NC",
    "sg:tags":[
        "house",
        "nonresidential"
    ],
    "wof:name":"Caskey Construction Co",
    "wof:placetype":"venue"
},
  "geometry": {"coordinates":[-80.73326299999999,35.052665],"type":"Point"}
}