{
  "type": "Feature",
  "properties": {
    "iso:country":"US",
    "sg:address":"118 Limestone Ln",
    "sg:city":"Pinnacle",
    "sg:classifiers":[
        {
            "category":"Building & Trades",
            "subcategory":"Landscaping Services",
            "type":"Services"
        }
    ],
    "sg:phone":"+1 336 325 3148",
    "sg:postcode":"27043",
    "sg:province":"NC",
    "sg:tags":[
        "landscape"
    ],
    "wof:name":"Pro Lawn Maintenance",
    "wof:placetype":"venue"
},
  "geometry": {"coordinates":[-80.458037,36.3223],"type":"Point"}
}