{
  "type": "Feature",
  "properties": {
    "addr:full":"115 Clifton St Fuquay Varina NC 27526",
    "addr:housenumber":"115",
    "addr:postcode":"27526",
    "addr:street":"Clifton St",
    "iso:country":"US",
    "sg:address":"115 Clifton St",
    "sg:city":"Fuquay Varina",
    "sg:classifiers":[
        {
            "category":"Professional",
            "type":"Services"
        }
    ],
    "sg:phone":"+1 919 552 9137",
    "sg:postcode":"27526",
    "sg:province":"NC",
    "wof:name":"Wagoner Studios",
    "wof:placetype":"venue"
},
  "geometry": {"coordinates":[-78.791961,35.583245],"type":"Point"}
}