{
  "type": "Feature",
  "properties": {
    "iso:country":"US",
    "sg:address":"426 Cottonfield Cir",
    "sg:city":"Waxhaw",
    "sg:classifiers":[
        {
            "category":"Building & Trades",
            "subcategory":"Electrical",
            "type":"Services"
        }
    ],
    "sg:phone":"+1 704 846 6996",
    "sg:postcode":"28173",
    "sg:province":"NC",
    "sg:tags":[
        "electrical",
        "contractor"
    ],
    "wof:name":"H L Grice Electric Inc",
    "wof:placetype":"venue"
},
  "geometry": {"coordinates":[-80.774607,35.004766],"type":"Point"}
}