{
  "type": "Feature",
  "properties": {
    "iso:country":"US",
    "sg:address":"530 Dudley Shoals Rd",
    "sg:city":"Granite Falls",
    "sg:classifiers":[
        {
            "category":"Restaurant",
            "type":"Food & Drink"
        }
    ],
    "sg:menulink":"http://www.allmenus.com/nc/lovelady/85385-dominos-pizza/menu/",
    "sg:phone":"+1 828 313 0555",
    "sg:postcode":"28630",
    "sg:province":"NC",
    "sg:tags":[
        "american",
        "wing",
        "pizza"
    ],
    "wof:name":"Domino's Pizza",
    "wof:placetype":"venue"
},
  "geometry": {"coordinates":[-81.42485499999999,35.817225],"type":"Point"}
}