{
  "type": "Feature",
  "properties": {
    "addr:full":"343 Upper Thomas Branch Rd Marshall NC 28753",
    "addr:housenumber":"343",
    "addr:postcode":"28753",
    "addr:street":"Upper Thomas Branch Rd",
    "iso:country":"US",
    "sg:address":"343 Upper Thomas Branch Rd",
    "sg:city":"Marshall",
    "sg:classifiers":[
        {
            "category":"Professional",
            "subcategory":"Management & Consulting",
            "type":"Services"
        }
    ],
    "sg:phone":"+1   ",
    "sg:postcode":"28753",
    "sg:province":"NC",
    "sg:tags":[
        "business"
    ],
    "wof:name":"Southeast Precision Products",
    "wof:placetype":"venue"
},
  "geometry": {"coordinates":[-82.728163,35.858189],"type":"Point"}
}