{
  "type": "Feature",
  "properties": {
    "iso:country":"US",
    "sg:address":"114 Barwood Ter",
    "sg:city":"Trinity",
    "sg:classifiers":[
        {
            "category":"Autos & Motor Vehicles",
            "subcategory":"Automobile Sales",
            "type":"Retail Goods"
        }
    ],
    "sg:phone":"+1 336 431 7617",
    "sg:postcode":"27370",
    "sg:province":"NC",
    "sg:tags":[
        "performance",
        "race",
        "dealer"
    ],
    "wof:name":"Jarrett Harvey Racing",
    "wof:placetype":"venue"
},
  "geometry": {"coordinates":[-79.96334899999999,35.88991],"type":"Point"}
}