{
  "type": "Feature",
  "properties": {
    "addr:full":"304 Ann St Morganton NC 28655",
    "addr:housenumber":"304",
    "addr:postcode":"28655",
    "addr:street":"Ann St",
    "iso:country":"US",
    "sg:address":"304 Ann St",
    "sg:city":"Morganton",
    "sg:classifiers":[
        {
            "category":"Education",
            "subcategory":"School",
            "type":"Public Place"
        }
    ],
    "sg:phone":"+1 828 437 5906",
    "sg:postcode":"28655",
    "sg:province":"NC",
    "sg:tags":[
        "elementary"
    ],
    "sg:website":"www.burke.k12.nc.us",
    "wof:name":"Forest Hill Elementary School",
    "wof:placetype":"venue"
},
  "geometry": {"coordinates":[-81.700682,35.731957],"type":"Point"}
}