{
  "type": "Feature",
  "properties": {
    "iso:country":"US",
    "sg:address":"708 E Main St",
    "sg:city":"Havelock",
    "sg:classifiers":[
        {
            "category":"Personal",
            "subcategory":"Beauty Salon",
            "type":"Services"
        }
    ],
    "sg:phone":"+1   ",
    "sg:postcode":"28532",
    "sg:province":"NC",
    "sg:tags":[
        "shop",
        "barber"
    ],
    "wof:name":"Visions Ahead",
    "wof:placetype":"venue"
},
  "geometry": {"coordinates":[-76.89982500000001,34.867207],"type":"Point"}
}