{
  "type": "Feature",
  "properties": {
    "addr:full":"1509 Haywood Rd Hendersonville NC 28791",
    "addr:housenumber":"1509",
    "addr:postcode":"28791",
    "addr:street":"Haywood Rd",
    "iso:country":"US",
    "sg:address":"1509 Haywood Rd",
    "sg:city":"Hendersonville",
    "sg:classifiers":[
        {
            "category":"Professional",
            "subcategory":"Lawyer & Legal Services",
            "type":"Services"
        }
    ],
    "sg:phone":"+1 828 692 4130",
    "sg:postcode":"28791",
    "sg:province":"NC",
    "sg:tags":[
        "attorney"
    ],
    "wof:name":"J Michael Edney",
    "wof:placetype":"venue"
},
  "geometry": {"coordinates":[-82.469757,35.32788],"type":"Point"}
}