{
  "type": "Feature",
  "properties": {
    "addr:full":"211 N Clinton Ave Dunn NC 28334",
    "addr:housenumber":"211",
    "addr:postcode":"28334",
    "addr:street":"N Clinton Ave",
    "iso:country":"US",
    "sg:address":"211 N Clinton Ave",
    "sg:city":"Dunn",
    "sg:classifiers":[
        {
            "category":"Food & Beverages",
            "subcategory":"Groceries & Convenience Stores",
            "type":"Retail Goods"
        }
    ],
    "sg:phone":"+1 910 892 7941",
    "sg:postcode":"28334",
    "sg:province":"NC",
    "sg:tags":[
        "grocer"
    ],
    "wof:name":"Ideal Foods",
    "wof:placetype":"venue"
},
  "geometry": {"coordinates":[-78.60700199999999,35.30873],"type":"Point"}
}