{
  "type": "Feature",
  "properties": {
    "addr:full":"400 Fontana Blvd Havelock NC 28532",
    "addr:housenumber":"400",
    "addr:postcode":"28532",
    "addr:street":"Fontana Blvd",
    "iso:country":"US",
    "sg:address":"400 Fontana Blvd",
    "sg:city":"Havelock",
    "sg:classifiers":[
        {
            "category":"Bars & Pubs",
            "type":"Food & Drink"
        }
    ],
    "sg:phone":"+1 252 447 7178",
    "sg:postcode":"28532",
    "sg:province":"NC",
    "sg:tags":[
        "club",
        "night"
    ],
    "wof:name":"Olivia's",
    "wof:placetype":"venue"
},
  "geometry": {"coordinates":[-76.89697700000001,34.88246],"type":"Point"}
}