{
  "type": "Feature",
  "properties": {
    "addr:full":"716 Eastchester Dr High Point NC 27262",
    "addr:housenumber":"716",
    "addr:postcode":"27262",
    "addr:street":"Eastchester Dr",
    "iso:country":"US",
    "sg:address":"716 Eastchester Dr",
    "sg:city":"High Point",
    "sg:classifiers":[
        {
            "category":"Food & Beverages",
            "subcategory":"Groceries & Convenience Stores",
            "type":"Retail Goods"
        }
    ],
    "sg:phone":"+1 336 885 9058",
    "sg:postcode":"27262",
    "sg:province":"NC",
    "wof:name":"Bass Food Mart",
    "wof:placetype":"venue"
},
  "geometry": {"coordinates":[-80.006913,35.984613],"type":"Point"}
}