{
  "type": "Feature",
  "properties": {
    "iso:country":"US",
    "sg:address":"14 Glenwood Ave",
    "sg:city":"Raleigh",
    "sg:classifiers":[
        {
            "category":"Building & Trades",
            "subcategory":"Construction",
            "type":"Services"
        }
    ],
    "sg:phone":"+1 919 833 5933",
    "sg:postcode":"27603",
    "sg:province":"NC",
    "sg:tags":[
        "hanging",
        "contractor"
    ],
    "wof:name":"Fab Faux",
    "wof:placetype":"venue"
},
  "geometry": {"coordinates":[-78.64744399999999,35.781766],"type":"Point"}
}