{
  "type": "Feature",
  "properties": {
    "iso:country":"US",
    "sg:address":"4700 N College Rd",
    "sg:city":"Castle Hayne",
    "sg:classifiers":[
        {
            "category":"Freight",
            "type":"Transportation"
        }
    ],
    "sg:phone":"+1 910 675 1600",
    "sg:postcode":"28429",
    "sg:province":"NC",
    "sg:tags":[
        "general"
    ],
    "wof:name":"Castle Hayne Mini Storage",
    "wof:placetype":"venue"
},
  "geometry": {"coordinates":[-77.89304199999999,34.338411],"type":"Point"}
}