{
  "type": "Feature",
  "properties": {
    "iso:country":"US",
    "sg:address":"1201 S Main St",
    "sg:city":"Kannapolis",
    "sg:classifiers":[
        {
            "category":"Retail",
            "subcategory":"Auto Repair",
            "type":"Services"
        }
    ],
    "sg:phone":"+1   ",
    "sg:postcode":"28081",
    "sg:province":"NC",
    "sg:tags":[
        "general"
    ],
    "wof:name":"Lube Shop",
    "wof:placetype":"venue"
},
  "geometry": {"coordinates":[-80.624904,35.477402],"type":"Point"}
}