{
  "type": "Feature",
  "properties": {
    "addr:full":"2617 Hendersonville Rd Arden NC 28704",
    "addr:housenumber":"2617",
    "addr:postcode":"28704",
    "addr:street":"Hendersonville Rd",
    "iso:country":"US",
    "sg:address":"2617 Hendersonville Rd",
    "sg:city":"Arden",
    "sg:classifiers":[
        {
            "category":"Wholesale",
            "subcategory":"Furniture",
            "type":"Manufacturing & Wholesale Goods"
        }
    ],
    "sg:phone":"+1 828 681 5011",
    "sg:postcode":"28704",
    "sg:province":"NC",
    "wof:name":"Carolina Furniture Concepts",
    "wof:placetype":"venue"
},
  "geometry": {"coordinates":[-82.50822599999999,35.447846],"type":"Point"}
}