{
  "type": "Feature",
  "properties": {
    "addr:full":"2016 Poplar St Wilmington NC 28401",
    "addr:housenumber":"2016",
    "addr:postcode":"28401",
    "addr:street":"Poplar St",
    "iso:country":"US",
    "sg:address":"2016 Poplar St",
    "sg:city":"Wilmington",
    "sg:classifiers":[
        {
            "category":"Building & Trades",
            "subcategory":"Construction",
            "type":"Services"
        }
    ],
    "sg:phone":"+1 910 793 6133",
    "sg:postcode":"28401",
    "sg:province":"NC",
    "sg:tags":[
        "contractor"
    ],
    "wof:name":"Solar Shield",
    "wof:placetype":"venue"
},
  "geometry": {"coordinates":[-77.94011999999999,34.206419],"type":"Point"}
}