{
  "type": "Feature",
  "properties": {
    "iso:country":"US",
    "sg:address":"251 N Cannon Blvd",
    "sg:city":"Kannapolis",
    "sg:classifiers":[
        {
            "category":"Shopping",
            "subcategory":"Shoes",
            "type":"Retail Goods"
        }
    ],
    "sg:phone":"+1 704 932 1813",
    "sg:postcode":"28083",
    "sg:province":"NC",
    "sg:website":"www.shoeshow.com",
    "wof:name":"Shoe Show",
    "wof:placetype":"venue"
},
  "geometry": {"coordinates":[-80.60996900000001,35.497375],"type":"Point"}
}