{
  "type": "Feature",
  "properties": {
    "iso:country":"US",
    "sg:address":"1810 Walnut St",
    "sg:city":"Cary",
    "sg:classifiers":[
        {
            "category":"Autos & Motor Vehicles",
            "subcategory":"Auto Supplies",
            "type":"Retail Goods"
        },
        {
            "category":"Retail",
            "subcategory":"Auto Repair",
            "type":"Services"
        }
    ],
    "sg:phone":"+1 919 851 1129",
    "sg:postcode":"27518",
    "sg:province":"NC",
    "sg:tags":[
        "oil",
        "automotive",
        "automobile",
        "lube",
        "equipment-service",
        "air conditioning",
        "tune"
    ],
    "sg:website":"http://www.jiffylube.com",
    "wof:name":"Jiffy Lube",
    "wof:placetype":"venue"
},
  "geometry": {"coordinates":[-78.74118,35.753502],"type":"Point"}
}