{
  "type": "Feature",
  "properties": {
    "addr:full":"1510 E Dixie Dr Asheboro NC 27203",
    "addr:housenumber":"1510",
    "addr:postcode":"27203",
    "addr:street":"E Dixie Dr",
    "iso:country":"US",
    "sg:address":"1510 E Dixie Dr",
    "sg:city":"Asheboro",
    "sg:classifiers":[
        {
            "category":"Personal",
            "subcategory":"Beauty Salon",
            "type":"Services"
        }
    ],
    "sg:phone":"+1 336 629 4736",
    "sg:postcode":"27203",
    "sg:province":"NC",
    "sg:tags":[
        "shop",
        "manicuring"
    ],
    "wof:name":"A Nails",
    "wof:placetype":"venue"
},
  "geometry": {"coordinates":[-79.784284,35.700922],"type":"Point"}
}