{
  "type": "Feature",
  "properties": {
    "addr:full":"527 Little Rock Rd Charlotte NC 28214",
    "addr:housenumber":"527",
    "addr:postcode":"28214",
    "addr:street":"Little Rock Rd",
    "iso:country":"US",
    "sg:address":"527 Little Rock Rd",
    "sg:city":"Charlotte",
    "sg:classifiers":[
        {
            "category":"Restaurant",
            "type":"Food & Drink"
        }
    ],
    "sg:phone":"+1 704 391 1118",
    "sg:postcode":"28214",
    "sg:province":"NC",
    "sg:tags":[
        "eating"
    ],
    "wof:name":"Dong MEI Inc",
    "wof:placetype":"venue"
},
  "geometry": {"coordinates":[-80.938348,35.272131],"type":"Point"}
}