{
  "type": "Feature",
  "properties": {
    "iso:country":"US",
    "sg:address":"9 Park Ct S",
    "sg:city":"Arden",
    "sg:classifiers":[
        {
            "category":"Professional",
            "type":"Services"
        }
    ],
    "sg:phone":"+1 828 650 9996",
    "sg:postcode":"28732",
    "sg:province":"NC",
    "sg:tags":[
        "establishment"
    ],
    "wof:name":"Beavex USA",
    "wof:placetype":"venue"
},
  "geometry": {"coordinates":[-82.50846199999999,35.448992],"type":"Point"}
}