{
  "type": "Feature",
  "properties": {
    "addr:full":"935 Sunset Ave Clinton NC 28328",
    "addr:housenumber":"935",
    "addr:postcode":"28328",
    "addr:street":"Sunset Ave",
    "iso:country":"US",
    "sg:address":"935 Sunset Ave",
    "sg:city":"Clinton",
    "sg:classifiers":[
        {
            "category":"Banks & Credit Unions",
            "subcategory":"Bank",
            "type":"Services"
        }
    ],
    "sg:phone":"+1 910 590 3584",
    "sg:postcode":"28328",
    "sg:province":"NC",
    "sg:tags":[
        "cashing",
        "check"
    ],
    "wof:name":"First Southern Cash Advance",
    "wof:placetype":"venue"
},
  "geometry": {"coordinates":[-78.335421,34.99591],"type":"Point"}
}