{
  "type": "Feature",
  "properties": {
    "addr:full":"1157 Executive Cir Cary NC 27511",
    "addr:housenumber":"1157",
    "addr:postcode":"27511",
    "addr:street":"Executive Cir",
    "iso:country":"US",
    "sg:address":"1157 Executive Cir",
    "sg:city":"Cary",
    "sg:classifiers":[
        {
            "category":"Professional",
            "subcategory":"Management & Consulting",
            "type":"Services"
        }
    ],
    "sg:phone":"+1 919 481 3713",
    "sg:postcode":"27511",
    "sg:province":"NC",
    "sg:tags":[
        "construction"
    ],
    "wof:name":"Construction Control Corp",
    "wof:placetype":"venue"
},
  "geometry": {"coordinates":[-78.78229399999999,35.764697],"type":"Point"}
}