{
  "type": "Feature",
  "properties": {
    "addr:full":"1140 S Wesleyan Blvd Rocky Mount NC 27803",
    "addr:housenumber":"1140",
    "addr:postcode":"27803",
    "addr:street":"S Wesleyan Blvd",
    "iso:country":"US",
    "sg:address":"1140 S Wesleyan Blvd",
    "sg:city":"Rocky Mount",
    "sg:classifiers":[
        {
            "category":"Recreation",
            "type":"Entertainment"
        }
    ],
    "sg:phone":"+1 252 823 8240",
    "sg:postcode":"27803",
    "sg:province":"NC",
    "sg:tags":[
        "hall",
        "auditorium"
    ],
    "wof:name":"Chandalay",
    "wof:placetype":"venue"
},
  "geometry": {"coordinates":[-77.831596,35.920718],"type":"Point"}
}