{
  "type": "Feature",
  "properties": {
    "iso:country":"US",
    "sg:address":"215 E Blume St",
    "sg:city":"Landis",
    "sg:classifiers":[
        {
            "category":"Professional",
            "subcategory":"Business Services",
            "type":"Services"
        }
    ],
    "sg:phone":"+1   ",
    "sg:postcode":"28088",
    "sg:province":"NC",
    "wof:name":"Stanaland Enterprizes Inc",
    "wof:placetype":"venue"
},
  "geometry": {"coordinates":[-80.606877,35.547985],"type":"Point"}
}