{
  "type": "Feature",
  "properties": {
    "iso:country":"US",
    "sg:address":"1600 N Main St",
    "sg:city":"Fuquay Varina",
    "sg:classifiers":[
        {
            "category":"Shopping",
            "subcategory":"Bicycles & Sporting Goods",
            "type":"Retail Goods"
        }
    ],
    "sg:phone":"+1 919 552 1159",
    "sg:postcode":"27526",
    "sg:province":"NC",
    "sg:tags":[
        "tackle",
        "fishing"
    ],
    "wof:name":"T's Tackle",
    "wof:placetype":"venue"
},
  "geometry": {"coordinates":[-78.762512,35.595714],"type":"Point"}
}