{
  "type": "Feature",
  "properties": {
    "addr:full":"194 Busbee Mountain Rd Asheville NC 28803",
    "addr:housenumber":"194",
    "addr:postcode":"28803",
    "addr:street":"Busbee Mountain Rd",
    "iso:country":"US",
    "sg:address":"194 Busbee Mountain Rd",
    "sg:city":"Asheville",
    "sg:classifiers":[
        {
            "category":"Professional",
            "type":"Services"
        }
    ],
    "sg:phone":"+1 828 298 3371",
    "sg:postcode":"28803",
    "sg:province":"NC",
    "wof:name":"Carolina Christian Broadc",
    "wof:placetype":"venue"
},
  "geometry": {"coordinates":[-82.49436900000001,35.52763],"type":"Point"}
}