{
  "type": "Feature",
  "properties": {
    "iso:country":"US",
    "sg:address":"108 E Phifer St",
    "sg:city":"Monroe",
    "sg:classifiers":[
        {
            "category":"Real Estate",
            "subcategory":"Real Estate Agent",
            "type":"Services"
        }
    ],
    "sg:phone":"+1 704 291 9349",
    "sg:postcode":"28110",
    "sg:province":"NC",
    "wof:name":"Greater Carolinas Realty Inc",
    "wof:placetype":"venue"
},
  "geometry": {"coordinates":[-80.54698999999999,34.993001],"type":"Point"}
}