{
  "type": "Feature",
  "properties": {
    "iso:country":"US",
    "sg:address":"245 E Main St",
    "sg:city":"Lawndale",
    "sg:classifiers":[
        {
            "category":"Shopping",
            "subcategory":"Department Store",
            "type":"Retail Goods"
        }
    ],
    "sg:phone":"+1 704 538 3311",
    "sg:postcode":"28090",
    "sg:province":"NC",
    "sg:tags":[
        "shop"
    ],
    "wof:name":"This That N More",
    "wof:placetype":"venue"
},
  "geometry": {"coordinates":[-81.55716,35.417496],"type":"Point"}
}