{
  "type": "Feature",
  "properties": {
    "iso:country":"US",
    "sg:address":"462 44th Avenue Dr NW",
    "sg:city":"Hickory",
    "sg:classifiers":[
        {
            "category":"Professional",
            "subcategory":"Computer Services",
            "type":"Services"
        }
    ],
    "sg:phone":"+1 828 328 5929",
    "sg:postcode":"28601",
    "sg:province":"NC",
    "sg:tags":[
        "website",
        "design"
    ],
    "wof:name":"WSI Internet Consltng & Ed",
    "wof:placetype":"venue"
},
  "geometry": {"coordinates":[-81.3254,35.794039],"type":"Point"}
}