{
  "type": "Feature",
  "properties": {
    "addr:full":"145 Scaleybark Rd Charlotte NC 28209",
    "addr:housenumber":"145",
    "addr:postcode":"28209",
    "addr:street":"Scaleybark Rd",
    "iso:country":"US",
    "sg:address":"145 Scaleybark Rd",
    "sg:city":"Charlotte",
    "sg:classifiers":[
        {
            "category":"Professional",
            "subcategory":"Management & Consulting",
            "type":"Services"
        }
    ],
    "sg:phone":"+1   ",
    "sg:postcode":"28209",
    "sg:province":"NC",
    "wof:name":"Michael Robert D & Valerie L",
    "wof:placetype":"venue"
},
  "geometry": {"coordinates":[-80.873458,35.187969],"type":"Point"}
}