{
  "type": "Feature",
  "properties": {
    "iso:country":"US",
    "sg:address":"216 W Academy St",
    "sg:city":"Madison",
    "sg:classifiers":[
        {
            "category":"Food & Beverages",
            "subcategory":"Liquor & Beverages",
            "type":"Retail Goods"
        }
    ],
    "sg:phone":"+1 336 427 0440",
    "sg:postcode":"27025",
    "sg:province":"NC",
    "wof:name":"ABC Store",
    "wof:placetype":"venue"
},
  "geometry": {"coordinates":[-79.96182899999999,36.38525],"type":"Point"}
}