{
  "type": "Feature",
  "properties": {
    "iso:country":"US",
    "sg:address":"516 N Main St",
    "sg:city":"Salisbury",
    "sg:classifiers":[
        {
            "category":"Professional",
            "subcategory":"Engineering",
            "type":"Services"
        },
        {
            "category":"Building & Trades",
            "subcategory":"Landscaping Services",
            "type":"Services"
        }
    ],
    "sg:phone":"+1 704 633 8550",
    "sg:postcode":"28144",
    "sg:province":"NC",
    "sg:tags":[
        "planning",
        "land"
    ],
    "wof:name":"Salisbury Engineering & Plnng",
    "wof:placetype":"venue"
},
  "geometry": {"coordinates":[-80.464595,35.671559],"type":"Point"}
}