{
  "type": "Feature",
  "properties": {
    "iso:country":"US",
    "sg:address":"710 New Leicester Hwy",
    "sg:city":"Asheville",
    "sg:classifiers":[
        {
            "category":"Personal",
            "subcategory":"Beauty Salon",
            "type":"Services"
        }
    ],
    "sg:phone":"+1 828 251 9321",
    "sg:postcode":"28806",
    "sg:province":"NC",
    "wof:name":"Klipper's",
    "wof:placetype":"venue"
},
  "geometry": {"coordinates":[-82.63876399999999,35.613159],"type":"Point"}
}