{
  "type": "Feature",
  "properties": {
    "addr:full":"807 W Ehringhaus St Elizabeth City NC 27909",
    "addr:housenumber":"807",
    "addr:postcode":"27909",
    "addr:street":"W Ehringhaus St",
    "iso:country":"US",
    "sg:address":"807 W Ehringhaus St",
    "sg:city":"Elizabeth City",
    "sg:classifiers":[
        {
            "category":"Restaurant",
            "type":"Food & Drink"
        }
    ],
    "sg:menulink":"http://www.allmenus.com/nc/elizabeth-city/153212-bojangles/menu/",
    "sg:phone":"+1 252 333 1096",
    "sg:postcode":"27909",
    "sg:province":"NC",
    "sg:tags":[
        "chicken",
        "sandwich",
        "american"
    ],
    "wof:name":"Bojangle's",
    "wof:placetype":"venue"
},
  "geometry": {"coordinates":[-76.231622,36.295756],"type":"Point"}
}