{
  "type": "Feature",
  "properties": {
    "addr:full":"1800 N Elm St Greensboro NC 27408",
    "addr:housenumber":"1800",
    "addr:postcode":"27408",
    "addr:street":"N Elm St",
    "iso:country":"US",
    "sg:address":"1800 N Elm St",
    "sg:city":"Greensboro",
    "sg:classifiers":[
        {
            "category":"Shopping",
            "subcategory":"Used Merchandise",
            "type":"Retail Goods"
        }
    ],
    "sg:phone":"+1 336 210 1462",
    "sg:postcode":"27408",
    "sg:province":"NC",
    "wof:name":"Tommytoons",
    "wof:placetype":"venue"
},
  "geometry": {"coordinates":[-79.78830000000001,36.097556],"type":"Point"}
}