{
  "type": "Feature",
  "properties": {
    "iso:country":"US",
    "sg:address":"10710 Old Bridge Ln",
    "sg:city":"Charlotte",
    "sg:classifiers":[
        {
            "category":"Banks & Credit Unions",
            "subcategory":"Bank",
            "type":"Services"
        }
    ],
    "sg:phone":"+1 704 503 1334",
    "sg:postcode":"28269",
    "sg:province":"NC",
    "sg:tags":[
        "mortgage"
    ],
    "wof:name":"Financial Netwrk Ctr Mrtg Rlty",
    "wof:placetype":"venue"
},
  "geometry": {"coordinates":[-80.775818,35.356677],"type":"Point"}
}