{
  "type": "Feature",
  "properties": {
    "addr:full":"15 E Peace St Raleigh NC 27604",
    "addr:housenumber":"15",
    "addr:postcode":"27604",
    "addr:street":"E Peace St",
    "iso:country":"US",
    "sg:address":"15 E Peace St",
    "sg:city":"Raleigh",
    "sg:classifiers":[
        {
            "category":"Banks & Credit Unions",
            "subcategory":"Bank",
            "type":"Services"
        }
    ],
    "sg:phone":"+1 919 716 7000",
    "sg:postcode":"27604",
    "sg:province":"NC",
    "wof:name":"First-Citizens Bank & Trust Co",
    "wof:placetype":"venue"
},
  "geometry": {"coordinates":[-78.63795,35.788077],"type":"Point"}
}