{
  "type": "Feature",
  "properties": {
    "addr:full":"701 Church St Eden NC 27288",
    "addr:housenumber":"701",
    "addr:postcode":"27288",
    "addr:street":"Church St",
    "iso:country":"US",
    "sg:address":"701 Church St",
    "sg:city":"Eden",
    "sg:classifiers":[
        {
            "category":"Professional",
            "type":"Services"
        }
    ],
    "sg:phone":"+1 336 623 9190",
    "sg:postcode":"27288",
    "sg:province":"NC",
    "wof:name":"Dream Makers Inc",
    "wof:placetype":"venue"
},
  "geometry": {"coordinates":[-79.768237,36.506006],"type":"Point"}
}