{
  "type": "Feature",
  "properties": {
    "addr:full":"3507 Grapevine Rd Marshall NC 28753",
    "addr:housenumber":"3507",
    "addr:postcode":"28753",
    "addr:street":"Grapevine Rd",
    "iso:country":"US",
    "sg:address":"3507 Grapevine Rd",
    "sg:city":"Marshall",
    "sg:classifiers":[
        {
            "category":"Organizations",
            "subcategory":"Religious Organization",
            "type":"Services"
        }
    ],
    "sg:phone":"+1 828 689 5528",
    "sg:postcode":"28753",
    "sg:province":"NC",
    "sg:tags":[
        "church"
    ],
    "wof:name":"Grapevine Baptist Church",
    "wof:placetype":"venue"
},
  "geometry": {"coordinates":[-82.614904,35.839111],"type":"Point"}
}