{
  "type": "Feature",
  "properties": {
    "addr:full":"102 Scoter Ct Grandy NC 27939",
    "addr:housenumber":"102",
    "addr:postcode":"27939",
    "addr:street":"Scoter Ct",
    "iso:country":"US",
    "sg:address":"102 Scoter Ct",
    "sg:city":"Grandy",
    "sg:classifiers":[
        {
            "category":"Freight",
            "type":"Transportation"
        }
    ],
    "sg:phone":"+1 252 453 6697",
    "sg:postcode":"27939",
    "sg:province":"NC",
    "wof:name":"Outer Banks Exp Transportation",
    "wof:placetype":"venue"
},
  "geometry": {"coordinates":[-75.877793,36.247413],"type":"Point"}
}