{
  "type": "Feature",
  "properties": {
    "addr:full":"5020 Hangar Rd Charlotte NC 28208",
    "addr:housenumber":"5020",
    "addr:postcode":"28208",
    "addr:street":"Hangar Rd",
    "iso:country":"US",
    "sg:address":"5020 Hangar Rd",
    "sg:city":"Charlotte",
    "sg:classifiers":[
        {
            "category":"Professional",
            "type":"Services"
        }
    ],
    "sg:phone":"+1 704 359 8507",
    "sg:postcode":"28208",
    "sg:province":"NC",
    "wof:name":"Airbus Service Co Inc",
    "wof:placetype":"venue"
},
  "geometry": {"coordinates":[-80.945679,35.205296],"type":"Point"}
}