{
  "type": "Feature",
  "properties": {
    "iso:country":"US",
    "sg:address":"6963 State Hwy 705",
    "sg:city":"Robbins",
    "sg:classifiers":[
        {
            "category":"Organizations",
            "subcategory":"Religious Organization",
            "type":"Services"
        }
    ],
    "sg:phone":"+1 910 948 4100",
    "sg:postcode":"27325",
    "sg:province":"NC",
    "sg:tags":[
        "church"
    ],
    "wof:name":"St Juan Diego Mission",
    "wof:placetype":"venue"
},
  "geometry": {"coordinates":[-79.57549299999999,35.405745],"type":"Point"}
}