{
  "type": "Feature",
  "properties": {
    "iso:country":"US",
    "sg:address":"3025 N Davidson St",
    "sg:city":"Charlotte",
    "sg:classifiers":[
        {
            "category":"Social Services",
            "type":"Services"
        },
        {
            "category":"Professional",
            "subcategory":"Employment Agencies",
            "type":"Services"
        }
    ],
    "sg:phone":"+1 704 333 6206",
    "sg:postcode":"28205",
    "sg:province":"NC",
    "sg:tags":[
        "workers'",
        "placement",
        "volunteer"
    ],
    "sg:website":"http://www.ymca.net",
    "wof:name":"Ymca",
    "wof:placetype":"venue"
},
  "geometry": {"coordinates":[-80.807771,35.24582],"type":"Point"}
}