{
  "type": "Feature",
  "properties": {
    "addr:full":"1759 Vargrave St Winston Salem NC 27127",
    "addr:housenumber":"1759",
    "addr:postcode":"27127",
    "addr:street":"Vargrave St",
    "iso:country":"US",
    "sg:address":"1759 Vargrave St",
    "sg:city":"Winston Salem",
    "sg:classifiers":[
        {
            "category":"Building & Trades",
            "subcategory":"Construction",
            "type":"Services"
        }
    ],
    "sg:phone":"+1 336 724 3818",
    "sg:postcode":"27127",
    "sg:province":"NC",
    "wof:name":"Kdt Grading",
    "wof:placetype":"venue"
},
  "geometry": {"coordinates":[-80.22977,36.074535],"type":"Point"}
}