{
  "type": "Feature",
  "properties": {
    "iso:country":"US",
    "sg:address":"903 E Trinity Ave",
    "sg:city":"Durham",
    "sg:classifiers":[
        {
            "category":"Building & Trades",
            "subcategory":"Construction",
            "type":"Services"
        }
    ],
    "sg:phone":"+1 919 309 7713",
    "sg:postcode":"27704",
    "sg:province":"NC",
    "sg:tags":[
        "residential",
        "general",
        "commercial",
        "contractor"
    ],
    "wof:name":"Sunrise Contracting Services",
    "wof:placetype":"venue"
},
  "geometry": {"coordinates":[-78.883242,36.007574],"type":"Point"}
}