{
  "type": "Feature",
  "properties": {
    "addr:full":"273 Lake Royale Louisburg NC 27549",
    "addr:housenumber":"273",
    "addr:postcode":"27549",
    "addr:street":"Lake Royale",
    "iso:country":"US",
    "sg:address":"273 Lake Royale",
    "sg:city":"Louisburg",
    "sg:classifiers":[
        {
            "category":"Real Estate",
            "subcategory":"Real Estate Operator",
            "type":"Services"
        }
    ],
    "sg:phone":"+1 252 478 5199",
    "sg:postcode":"27549",
    "sg:province":"NC",
    "sg:tags":[
        "building",
        "nonresidential"
    ],
    "wof:name":"Guardian Properties & MGT",
    "wof:placetype":"venue"
},
  "geometry": {"coordinates":[-78.206205,35.981736],"type":"Point"}
}