{
  "type": "Feature",
  "properties": {
    "addr:full":"4815 Alliance Church Rd Pleasant Garden NC 27313",
    "addr:housenumber":"4815",
    "addr:postcode":"27313",
    "addr:street":"Alliance Church Rd",
    "iso:country":"US",
    "sg:address":"4815 Alliance Church Rd",
    "sg:city":"Pleasant Garden",
    "sg:classifiers":[
        {
            "category":"Wholesale",
            "subcategory":"Durable Goods & Equipment",
            "type":"Manufacturing & Wholesale Goods"
        }
    ],
    "sg:phone":"+1 336 676 8200",
    "sg:postcode":"27313",
    "sg:province":"NC",
    "sg:tags":[
        "importer"
    ],
    "wof:name":"Alamo Importers Inc",
    "wof:placetype":"venue"
},
  "geometry": {"coordinates":[-79.75179300000001,35.981203],"type":"Point"}
}