{
  "type": "Feature",
  "properties": {
    "iso:country":"US",
    "sg:address":"608 Hillside Dr",
    "sg:city":"Kings Mountain",
    "sg:classifiers":[
        {
            "category":"Wholesale",
            "subcategory":"Non-durable Goods",
            "type":"Manufacturing & Wholesale Goods"
        }
    ],
    "sg:phone":"+1 704 739 8863",
    "sg:postcode":"28086",
    "sg:province":"NC",
    "sg:tags":[
        "industrial",
        "wiper",
        "fabric",
        "yarn"
    ],
    "wof:name":"Lake Textiles",
    "wof:placetype":"venue"
},
  "geometry": {"coordinates":[-81.35624300000001,35.234832],"type":"Point"}
}