{
  "type": "Feature",
  "properties": {
    "iso:country":"US",
    "sg:address":"4422 River Estates Dr",
    "sg:city":"Asheboro",
    "sg:classifiers":[
        {
            "category":"Building & Trades",
            "subcategory":"Plumbing",
            "type":"Services"
        }
    ],
    "sg:phone":"+1 336 626 0294",
    "sg:postcode":"27205",
    "sg:province":"NC",
    "sg:tags":[
        "plumbing",
        "contractor"
    ],
    "wof:name":"Econo-Rooter",
    "wof:placetype":"venue"
},
  "geometry": {"coordinates":[-79.841189,35.569321],"type":"Point"}
}