{
  "type": "Feature",
  "properties": {
    "iso:country":"US",
    "sg:address":"440 McCullough Dr",
    "sg:city":"Charlotte",
    "sg:classifiers":[
        {
            "category":"Personal",
            "subcategory":"Beauty Salon",
            "type":"Services"
        }
    ],
    "sg:phone":"+1 704 549 0174",
    "sg:postcode":"28262",
    "sg:province":"NC",
    "wof:name":"Hair Color Xperts Grande",
    "wof:placetype":"venue"
},
  "geometry": {"coordinates":[-80.756703,35.303413],"type":"Point"}
}