{
  "type": "Feature",
  "properties": {
    "iso:country":"US",
    "sg:address":"3001 Calvary Dr",
    "sg:city":"Raleigh",
    "sg:classifiers":[
        {
            "category":"Building & Trades",
            "subcategory":"Construction",
            "type":"Services"
        }
    ],
    "sg:phone":"+1 919 876 0127",
    "sg:postcode":"27604",
    "sg:province":"NC",
    "sg:tags":[
        "general",
        "contractor"
    ],
    "wof:name":"New Co Construction",
    "wof:placetype":"venue"
},
  "geometry": {"coordinates":[-78.584856,35.845228],"type":"Point"}
}