{
  "type": "Feature",
  "properties": {
    "addr:full":"1300 Oakwood Ave Raleigh NC 27610",
    "addr:housenumber":"1300",
    "addr:postcode":"27610",
    "addr:street":"Oakwood Ave",
    "iso:country":"US",
    "sg:address":"1300 Oakwood Ave",
    "sg:city":"Raleigh",
    "sg:classifiers":[
        {
            "category":"Food & Beverages",
            "subcategory":"Groceries & Convenience Stores",
            "type":"Retail Goods"
        }
    ],
    "sg:phone":"+1 919 833 2033",
    "sg:postcode":"27610",
    "sg:province":"NC",
    "wof:name":"College Station",
    "wof:placetype":"venue"
},
  "geometry": {"coordinates":[-78.62073599999999,35.784227],"type":"Point"}
}