{
  "type": "Feature",
  "properties": {
    "addr:full":"10923 N Main St Archdale NC 27263",
    "addr:housenumber":"10923",
    "addr:postcode":"27263",
    "addr:street":"N Main St",
    "iso:country":"US",
    "sg:address":"10923 N Main St",
    "sg:city":"Archdale",
    "sg:classifiers":[
        {
            "category":"Shopping",
            "subcategory":"Used Merchandise",
            "type":"Retail Goods"
        }
    ],
    "sg:phone":"+1 336 434 4998",
    "sg:postcode":"27263",
    "sg:province":"NC",
    "sg:tags":[
        "shop",
        "consignment"
    ],
    "wof:name":"Blooming Deal's Consignment",
    "wof:placetype":"venue"
},
  "geometry": {"coordinates":[-79.969508,35.910628],"type":"Point"}
}