{
  "type": "Feature",
  "properties": {
    "addr:full":"1805 Chapel Hill Rd Durham NC 27707",
    "addr:housenumber":"1805",
    "addr:postcode":"27707",
    "addr:street":"Chapel Hill Rd",
    "iso:country":"US",
    "sg:address":"1805 Chapel Hill Rd",
    "sg:city":"Durham",
    "sg:classifiers":[
        {
            "category":"Home & Garden",
            "subcategory":"Carpets & Floor Coverings",
            "type":"Retail Goods"
        }
    ],
    "sg:phone":"+1 919 402 0070",
    "sg:postcode":"27707",
    "sg:province":"NC",
    "wof:name":"Trustin LLC",
    "wof:placetype":"venue"
},
  "geometry": {"coordinates":[-78.924267,35.989892],"type":"Point"}
}