{
  "type": "Feature",
  "properties": {
    "addr:full":"127 I K Beatty St Charlotte NC 28214",
    "addr:housenumber":"127 i k",
    "addr:postcode":"28214",
    "addr:street":"Beatty St",
    "iso:country":"US",
    "sg:address":"127 I K Beatty St",
    "sg:city":"Charlotte",
    "sg:classifiers":[
        {
            "category":"Professional",
            "subcategory":"Computer Services",
            "type":"Services"
        }
    ],
    "sg:phone":"+1   ",
    "sg:postcode":"28214",
    "sg:province":"NC",
    "sg:tags":[
        "programing",
        "custom"
    ],
    "wof:name":"Advanced Solutions Data Inc",
    "wof:placetype":"venue"
},
  "geometry": {"coordinates":[-80.95197,35.283047],"type":"Point"}
}