{
  "type": "Feature",
  "properties": {
    "iso:country":"US",
    "sg:address":"101 W Main St",
    "sg:city":"Jamestown",
    "sg:classifiers":[
        {
            "category":"Personal",
            "subcategory":"Barber",
            "type":"Services"
        }
    ],
    "sg:phone":"+1 336 454 4248",
    "sg:postcode":"27282",
    "sg:province":"NC",
    "sg:tags":[
        "shop"
    ],
    "wof:name":"Rob's Barber Shop",
    "wof:placetype":"venue"
},
  "geometry": {"coordinates":[-79.93573499999999,35.994105],"type":"Point"}
}