{
  "type": "Feature",
  "properties": {
    "iso:country":"US",
    "sg:address":"615 Halifax Rd",
    "sg:city":"Roxboro",
    "sg:classifiers":[
        {
            "category":"Farming",
            "subcategory":"Farm",
            "type":"Manufacturing & Wholesale Goods"
        }
    ],
    "sg:phone":"+1 336 599 2945",
    "sg:postcode":"27573",
    "sg:province":"NC",
    "sg:tags":[
        "crop",
        "general"
    ],
    "wof:name":"Bryant D Gravitte",
    "wof:placetype":"venue"
},
  "geometry": {"coordinates":[-78.950266,36.400045],"type":"Point"}
}