{
  "type": "Feature",
  "properties": {
    "addr:full":"913 Poole Dr Garner NC 27529",
    "addr:housenumber":"913",
    "addr:postcode":"27529",
    "addr:street":"Poole Dr",
    "iso:country":"US",
    "sg:address":"913 Poole Dr",
    "sg:city":"Garner",
    "sg:classifiers":[
        {
            "category":"Organizations",
            "subcategory":"Community Association",
            "type":"Services"
        }
    ],
    "sg:phone":"+1   ",
    "sg:postcode":"27529",
    "sg:province":"NC",
    "wof:name":"Garner Civitan Civic Club",
    "wof:placetype":"venue"
},
  "geometry": {"coordinates":[-78.616743,35.695372],"type":"Point"}
}