{
  "type": "Feature",
  "properties": {
    "iso:country":"US",
    "sg:address":"3049 Cloninger Rd",
    "sg:city":"Dallas",
    "sg:classifiers":[
        {
            "category":"Wholesale",
            "subcategory":"Electrical",
            "type":"Manufacturing & Wholesale Goods"
        }
    ],
    "sg:phone":"+1 704 922 3791",
    "sg:postcode":"28034",
    "sg:province":"NC",
    "sg:tags":[
        "control"
    ],
    "wof:name":"United Design Inc",
    "wof:placetype":"venue"
},
  "geometry": {"coordinates":[-81.191726,35.356287],"type":"Point"}
}