{
  "type": "Feature",
  "properties": {
    "iso:country":"US",
    "sg:address":"4111 Romaine St",
    "sg:city":"Greensboro",
    "sg:classifiers":[
        {
            "category":"Freight",
            "type":"Transportation"
        }
    ],
    "sg:phone":"+1 336 855 5231",
    "sg:postcode":"27407",
    "sg:province":"NC",
    "sg:tags":[
        "commercial",
        "storage"
    ],
    "wof:name":"High Point Road Self Storage",
    "wof:placetype":"venue"
},
  "geometry": {"coordinates":[-79.86719600000001,36.036684],"type":"Point"}
}