{
  "type": "Feature",
  "properties": {
    "iso:country":"US",
    "sg:address":"4201 Reedy Creek Rd",
    "sg:city":"Raleigh",
    "sg:classifiers":[
        {
            "category":"Banks & Credit Unions",
            "subcategory":"Investment Brokerage",
            "type":"Services"
        }
    ],
    "sg:phone":"+1 919 664 6200",
    "sg:postcode":"27607",
    "sg:province":"NC",
    "sg:tags":[
        "federal",
        "funds",
        "manages",
        "property"
    ],
    "wof:name":"US Prprty Fscal Officer For NC",
    "wof:placetype":"venue"
},
  "geometry": {"coordinates":[-78.70876199999999,35.811298],"type":"Point"}
}