{
  "type": "Feature",
  "properties": {
    "iso:country":"US",
    "sg:address":"400 Wood Ct",
    "sg:city":"Conway",
    "sg:classifiers":[
        {
            "category":"Real Estate",
            "subcategory":"Real Estate Operator",
            "type":"Services"
        }
    ],
    "sg:phone":"+1 252 585 0524",
    "sg:postcode":"27820",
    "sg:province":"NC",
    "sg:tags":[
        "apartment"
    ],
    "wof:name":"Conway Park Apartments",
    "wof:placetype":"venue"
},
  "geometry": {"coordinates":[-77.218614,36.443894],"type":"Point"}
}