{
  "type": "Feature",
  "properties": {
    "iso:country":"US",
    "sg:address":"101 E Harnett St",
    "sg:city":"Dunn",
    "sg:classifiers":[
        {
            "category":"Retail",
            "subcategory":"Funeral Services",
            "type":"Services"
        }
    ],
    "sg:phone":"+1 910 892 3246",
    "sg:postcode":"28334",
    "sg:province":"NC",
    "sg:tags":[
        "director"
    ],
    "wof:name":"Payton's Funeral Home",
    "wof:placetype":"venue"
},
  "geometry": {"coordinates":[-78.608784,35.309866],"type":"Point"}
}