{
  "type": "Feature",
  "properties": {
    "addr:full":"150 S Equity Dr Smithfield NC 27577",
    "addr:housenumber":"150",
    "addr:postcode":"27577",
    "addr:street":"S Equity Dr",
    "iso:country":"US",
    "sg:address":"150 S Equity Dr",
    "sg:city":"Smithfield",
    "sg:classifiers":[
        {
            "category":"Restaurant",
            "type":"Food & Drink"
        }
    ],
    "sg:menulink":"http://www.allmenus.com/nc/smithfield/137625-subway/menu/",
    "sg:phone":"+1 919 938 0004",
    "sg:postcode":"27577",
    "sg:province":"NC",
    "sg:tags":[
        "american",
        "sandwich"
    ],
    "wof:name":"Subway",
    "wof:placetype":"venue"
},
  "geometry": {"coordinates":[-78.322153,35.5077],"type":"Point"}
}