{
  "type": "Feature",
  "properties": {
    "iso:country":"US",
    "sg:address":"708 Westwood Dr",
    "sg:city":"Rocky Mount",
    "sg:classifiers":[
        {
            "category":"Professional",
            "subcategory":"Management & Consulting",
            "type":"Services"
        }
    ],
    "sg:phone":"+1 252 972 6560",
    "sg:postcode":"27803",
    "sg:province":"NC",
    "sg:tags":[
        "consultant",
        "business"
    ],
    "sg:website":"www.completebusinessservices.com",
    "wof:name":"Complete Business Svc",
    "wof:placetype":"venue"
},
  "geometry": {"coordinates":[-77.81944900000001,35.938557],"type":"Point"}
}