{
  "type": "Feature",
  "properties": {
    "addr:full":"124 Sondley Pkwy Asheville NC 28805",
    "addr:housenumber":"124",
    "addr:postcode":"28805",
    "addr:street":"Sondley Pkwy",
    "iso:country":"US",
    "sg:address":"124 Sondley Pkwy",
    "sg:city":"Asheville",
    "sg:classifiers":[
        {
            "category":"Professional",
            "type":"Services"
        }
    ],
    "sg:phone":"+1 828 298 7270",
    "sg:postcode":"28805",
    "sg:province":"NC",
    "wof:name":"Alpha Storage Trlrs & Cntrs I",
    "wof:placetype":"venue"
},
  "geometry": {"coordinates":[-82.501549,35.620469],"type":"Point"}
}