{
  "type": "Feature",
  "properties": {
    "addr:full":"4713 High Point Rd Greensboro NC 27407",
    "addr:housenumber":"4713",
    "addr:postcode":"27407",
    "addr:street":"High Point Rd",
    "iso:country":"US",
    "sg:address":"4713 High Point Rd",
    "sg:city":"Greensboro",
    "sg:classifiers":[
        {
            "category":"Insurance",
            "subcategory":"Insurance Agent",
            "type":"Services"
        }
    ],
    "sg:phone":"+1 336 852 5160",
    "sg:postcode":"27407",
    "sg:province":"NC",
    "wof:name":"Insurance Outlet",
    "wof:placetype":"venue"
},
  "geometry": {"coordinates":[-79.86855199999999,36.029861],"type":"Point"}
}