{
  "type": "Feature",
  "properties": {
    "addr:full":"8019 Hogan Dr Wake Forest NC 27587",
    "addr:housenumber":"8019",
    "addr:postcode":"27587",
    "addr:street":"Hogan Dr",
    "iso:country":"US",
    "sg:address":"8019 Hogan Dr",
    "sg:city":"Wake Forest",
    "sg:classifiers":[
        {
            "category":"Professional",
            "subcategory":"Business Services",
            "type":"Services"
        }
    ],
    "sg:phone":"+1   ",
    "sg:postcode":"27587",
    "sg:province":"NC",
    "wof:name":"Belle Venture Group LLC",
    "wof:placetype":"venue"
},
  "geometry": {"coordinates":[-78.53729800000001,36.005956],"type":"Point"}
}