{
  "type": "Feature",
  "properties": {
    "iso:country":"US",
    "sg:address":"6832 Morrison Blvd",
    "sg:city":"Charlotte",
    "sg:classifiers":[
        {
            "category":"Professional",
            "subcategory":"Lawyer & Legal Services",
            "type":"Services"
        }
    ],
    "sg:phone":"+1 704 364 0010",
    "sg:postcode":"28211",
    "sg:province":"NC",
    "sg:tags":[
        "attorney"
    ],
    "sg:website":"www.wnhplaw.com",
    "wof:name":"Wishart Norris Henninger & P",
    "wof:placetype":"venue"
},
  "geometry": {"coordinates":[-80.82611900000001,35.151927],"type":"Point"}
}