{
  "type": "Feature",
  "properties": {
    "iso:country":"US",
    "sg:address":"122 S Center St",
    "sg:city":"Goldsboro",
    "sg:classifiers":[
        {
            "category":"Building & Trades",
            "subcategory":"Construction",
            "type":"Services"
        }
    ],
    "sg:phone":"+1 919 734 7336",
    "sg:postcode":"27530",
    "sg:province":"NC",
    "sg:tags":[
        "general",
        "contractor"
    ],
    "wof:name":"Reconstruction Co",
    "wof:placetype":"venue"
},
  "geometry": {"coordinates":[-77.997364,35.382],"type":"Point"}
}