{
  "type": "Feature",
  "properties": {
    "addr:full":"2980 E Franklin Blvd Gastonia NC 28056",
    "addr:housenumber":"2980",
    "addr:postcode":"28056",
    "addr:street":"E Franklin Blvd",
    "iso:country":"US",
    "sg:address":"2980 E Franklin Blvd",
    "sg:city":"Gastonia",
    "sg:classifiers":[
        {
            "category":"Shopping",
            "subcategory":"Clothing, Apparel, & Fashions",
            "type":"Retail Goods"
        }
    ],
    "sg:phone":"+1 704 867 3445",
    "sg:postcode":"28056",
    "sg:province":"NC",
    "sg:website":"www.catofashions.com",
    "wof:name":"Cato",
    "wof:placetype":"venue"
},
  "geometry": {"coordinates":[-81.12513,35.259167],"type":"Point"}
}