{
  "type": "Feature",
  "properties": {
    "addr:full":"185 Robin Ln Vilas NC 28692",
    "addr:housenumber":"185",
    "addr:postcode":"28692",
    "addr:street":"Robin Ln",
    "iso:country":"US",
    "sg:address":"185 Robin Ln",
    "sg:city":"Vilas",
    "sg:classifiers":[
        {
            "category":"Organizations",
            "subcategory":"Religious Organization",
            "type":"Services"
        }
    ],
    "sg:phone":"+1 828 297 6470",
    "sg:postcode":"28692",
    "sg:province":"NC",
    "sg:tags":[
        "church"
    ],
    "wof:name":"Apostolic Church Of Christ",
    "wof:placetype":"venue"
},
  "geometry": {"coordinates":[-81.768461,36.242117],"type":"Point"}
}