{
  "type": "Feature",
  "properties": {
    "addr:full":"617 US Hwy 52 Albemarle NC 28001",
    "addr:housenumber":"617",
    "addr:postcode":"28001",
    "addr:street":"Us Hwy 52",
    "iso:country":"US",
    "sg:address":"617 US Hwy 52",
    "sg:city":"Albemarle",
    "sg:classifiers":[
        {
            "category":"Building & Trades",
            "subcategory":"Landscaping Services",
            "type":"Services"
        }
    ],
    "sg:phone":"+1 704 982 1864",
    "sg:postcode":"28001",
    "sg:province":"NC",
    "sg:tags":[
        "landscape"
    ],
    "wof:name":"David Kirk Landscaping",
    "wof:placetype":"venue"
},
  "geometry": {"coordinates":[-80.20714099999999,35.35831],"type":"Point"}
}