{
  "type": "Feature",
  "properties": {
    "iso:country":"US",
    "sg:address":"200 Dalton Ave",
    "sg:city":"Charlotte",
    "sg:classifiers":[
        {
            "category":"Wholesale",
            "subcategory":"Electrical",
            "type":"Manufacturing & Wholesale Goods"
        }
    ],
    "sg:phone":"+1 704 376 7437",
    "sg:postcode":"28206",
    "sg:province":"NC",
    "sg:tags":[
        "supply",
        "sign"
    ],
    "sg:website":"www.diamondsupply.us",
    "wof:name":"Diamond Supply Inc",
    "wof:placetype":"venue"
},
  "geometry": {"coordinates":[-80.831254,35.239536],"type":"Point"}
}