{
  "type": "Feature",
  "properties": {
    "addr:full":"105 Binnacle Ct Elizabeth City NC 27909",
    "addr:housenumber":"105",
    "addr:postcode":"27909",
    "addr:street":"Binnacle Ct",
    "iso:country":"US",
    "sg:address":"105 Binnacle Ct",
    "sg:city":"Elizabeth City",
    "sg:classifiers":[
        {
            "category":"Building & Trades",
            "subcategory":"Construction",
            "type":"Services"
        }
    ],
    "sg:phone":"+1 252 335 1190",
    "sg:postcode":"27909",
    "sg:province":"NC",
    "sg:tags":[
        "painter"
    ],
    "wof:name":"Trimmer Wayne Paintng Contr",
    "wof:placetype":"venue"
},
  "geometry": {"coordinates":[-76.194149,36.279771],"type":"Point"}
}