{
  "type": "Feature",
  "properties": {
    "addr:full":"482 N Roberts Ave Lumberton NC 28358",
    "addr:housenumber":"482",
    "addr:postcode":"28358",
    "addr:street":"N Roberts Ave",
    "iso:country":"US",
    "sg:address":"482 N Roberts Ave",
    "sg:city":"Lumberton",
    "sg:classifiers":[
        {
            "category":"Home & Garden",
            "subcategory":"Building Materials",
            "type":"Retail Goods"
        }
    ],
    "sg:phone":"+1 910 272 0024",
    "sg:postcode":"28358",
    "sg:province":"NC",
    "wof:name":"Builder's Discount Ctr",
    "wof:placetype":"venue"
},
  "geometry": {"coordinates":[-78.98045,34.618928],"type":"Point"}
}