{
  "type": "Feature",
  "properties": {
    "iso:country":"US",
    "sg:address":"200 Campen Rd",
    "sg:city":"Beaufort",
    "sg:classifiers":[
        {
            "category":"Personal",
            "subcategory":"Beauty Salon",
            "type":"Services"
        }
    ],
    "sg:phone":"+1   ",
    "sg:postcode":"28516",
    "sg:province":"NC",
    "wof:name":"Hair Trends",
    "wof:placetype":"venue"
},
  "geometry": {"coordinates":[-76.644775,34.733698],"type":"Point"}
}