{
  "type": "Feature",
  "properties": {
    "addr:full":"3037 S I - 85 Svc Rd Charlotte NC 28208",
    "addr:housenumber":"3037;85",
    "addr:postcode":"28208",
    "addr:street":"S I",
    "iso:country":"US",
    "sg:address":"3037 S I - 85 Svc Rd",
    "sg:city":"Charlotte",
    "sg:classifiers":[
        {
            "category":"Wholesale",
            "subcategory":"Groceries",
            "type":"Manufacturing & Wholesale Goods"
        }
    ],
    "sg:phone":"+1 704 392 1783",
    "sg:postcode":"28208",
    "sg:province":"NC",
    "sg:tags":[
        "baker"
    ],
    "wof:name":"Sara Lee Bakery Group",
    "wof:placetype":"venue"
},
  "geometry": {"coordinates":[-80.961185,35.204586],"type":"Point"}
}