{
  "type": "Feature",
  "properties": {
    "iso:country":"US",
    "sg:address":"1535 Carr St",
    "sg:city":"Raleigh",
    "sg:classifiers":[
        {
            "category":"Professional",
            "subcategory":"Management & Consulting",
            "type":"Services"
        }
    ],
    "sg:phone":"+1 919 832 3006",
    "sg:postcode":"27608",
    "sg:province":"NC",
    "sg:tags":[
        "counselor",
        "public",
        "relations"
    ],
    "wof:name":"Mike Hoyt & Assoc",
    "wof:placetype":"venue"
},
  "geometry": {"coordinates":[-78.648949,35.800207],"type":"Point"}
}