{
  "type": "Feature",
  "properties": {
    "iso:country":"US",
    "sg:address":"7201 Graybeard Ct",
    "sg:city":"Charlotte",
    "sg:classifiers":[
        {
            "category":"Professional",
            "subcategory":"Computer Services",
            "type":"Services"
        },
        {
            "category":"Shopping",
            "subcategory":"Computers & Home Electronics",
            "type":"Retail Goods"
        }
    ],
    "sg:phone":"+1 704 540 4740",
    "sg:postcode":"28226",
    "sg:province":"NC",
    "sg:tags":[
        "related",
        "software"
    ],
    "wof:name":"Watchtower Consulting",
    "wof:placetype":"venue"
},
  "geometry": {"coordinates":[-80.80064900000001,35.102827],"type":"Point"}
}