{
  "type": "Feature",
  "properties": {
    "iso:country":"US",
    "sg:address":"22116 Satilla Dr",
    "sg:city":"Cornelius",
    "sg:classifiers":[
        {
            "category":"Wholesale",
            "subcategory":"Electrical",
            "type":"Manufacturing & Wholesale Goods"
        }
    ],
    "sg:phone":"+1 704 895 9774",
    "sg:postcode":"28031",
    "sg:province":"NC",
    "sg:tags":[
        "electronic"
    ],
    "wof:name":"Kasar Inc",
    "wof:placetype":"venue"
},
  "geometry": {"coordinates":[-80.886562,35.500731],"type":"Point"}
}