{
  "type": "Feature",
  "properties": {
    "addr:full":"3206 Trent St Greensboro NC 27405",
    "addr:housenumber":"3206",
    "addr:postcode":"27405",
    "addr:street":"Trent St",
    "iso:country":"US",
    "sg:address":"3206 Trent St",
    "sg:city":"Greensboro",
    "sg:classifiers":[
        {
            "category":"Education",
            "subcategory":"Special Training",
            "type":"Public Place"
        }
    ],
    "sg:phone":"+1   ",
    "sg:postcode":"27405",
    "sg:province":"NC",
    "wof:name":"Denises Modeling Agency",
    "wof:placetype":"venue"
},
  "geometry": {"coordinates":[-79.75505800000001,36.119474],"type":"Point"}
}