{
  "type": "Feature",
  "properties": {
    "iso:country":"US",
    "sg:address":"1136 Greenwood Rd",
    "sg:city":"Spruce Pine",
    "sg:classifiers":[
        {
            "category":"Professional",
            "subcategory":"Accounting & Tax Preparation",
            "type":"Services"
        }
    ],
    "sg:phone":"+1 828 765 4400",
    "sg:postcode":"28777",
    "sg:province":"NC",
    "sg:tags":[
        "accountant"
    ],
    "wof:name":"Mc Kinney & Brown",
    "wof:placetype":"venue"
},
  "geometry": {"coordinates":[-82.08859099999999,35.911865],"type":"Point"}
}