{
  "type": "Feature",
  "properties": {
    "iso:country":"US",
    "sg:address":"2909 Gray Fox Rd",
    "sg:city":"Monroe",
    "sg:classifiers":[
        {
            "category":"Building & Trades",
            "subcategory":"Plumbing",
            "type":"Services"
        }
    ],
    "sg:phone":"+1 704 289 9480",
    "sg:postcode":"28110",
    "sg:province":"NC",
    "sg:tags":[
        "plumber",
        "industrial",
        "contractors-commercial"
    ],
    "wof:name":"Kisiah W R Plumbing Inc",
    "wof:placetype":"venue"
},
  "geometry": {"coordinates":[-80.620813,35.059775],"type":"Point"}
}