{
  "type": "Feature",
  "properties": {
    "iso:country":"US",
    "sg:address":"204 W Chestnut St",
    "sg:city":"Goldsboro",
    "sg:classifiers":[
        {
            "category":"Real Estate",
            "subcategory":"Real Estate Agent",
            "type":"Services"
        }
    ],
    "sg:phone":"+1 919 734 2340",
    "sg:postcode":"27530",
    "sg:province":"NC",
    "wof:name":"Career Properties Inc",
    "wof:placetype":"venue"
},
  "geometry": {"coordinates":[-78.00073399999999,35.382555],"type":"Point"}
}