{
  "type": "Feature",
  "properties": {
    "addr:full":"1946 Stone Rose Ave Rocky Mount NC 27804",
    "addr:housenumber":"1946",
    "addr:postcode":"27804",
    "addr:street":"Stone Rose Ave",
    "iso:country":"US",
    "sg:address":"1946 Stone Rose Ave",
    "sg:city":"Rocky Mount",
    "sg:classifiers":[
        {
            "category":"Shopping",
            "subcategory":"Pharmacy",
            "type":"Retail Goods"
        }
    ],
    "sg:phone":"+1 252 446 2248",
    "sg:postcode":"27804",
    "sg:province":"NC",
    "sg:tags":[
        "drug",
        "store"
    ],
    "wof:name":"Kerr Drug 728",
    "wof:placetype":"venue"
},
  "geometry": {"coordinates":[-77.822193,35.956994],"type":"Point"}
}