{
  "type": "Feature",
  "properties": {
    "addr:full":"2581 Hawkins Ave Sanford NC 27330",
    "addr:housenumber":"2581",
    "addr:postcode":"27330",
    "addr:street":"Hawkins Ave",
    "iso:country":"US",
    "sg:address":"2581 Hawkins Ave",
    "sg:city":"Sanford",
    "sg:classifiers":[
        {
            "category":"Food & Beverages",
            "subcategory":"Groceries & Convenience Stores",
            "type":"Retail Goods"
        }
    ],
    "sg:phone":"+1 919 774 4175",
    "sg:postcode":"27330",
    "sg:province":"NC",
    "sg:tags":[
        "grocer"
    ],
    "wof:name":"Food Lion",
    "wof:placetype":"venue"
},
  "geometry": {"coordinates":[-79.18104599999999,35.519234],"type":"Point"}
}