{
  "type": "Feature",
  "properties": {
    "iso:country":"US",
    "sg:address":"126 Circle G Ln",
    "sg:city":"Willow Spring",
    "sg:classifiers":[
        {
            "category":"Building & Trades",
            "subcategory":"Construction",
            "type":"Services"
        }
    ],
    "sg:phone":"+1 919 639 6132",
    "sg:postcode":"27592",
    "sg:province":"NC",
    "sg:tags":[
        "clearing",
        "land",
        "landscaping"
    ],
    "wof:name":"Lloyd Allen Glover",
    "wof:placetype":"venue"
},
  "geometry": {"coordinates":[-78.643603,35.531408],"type":"Point"}
}