{
  "type": "Feature",
  "properties": {
    "addr:full":"6400 Falls of Neuse Rd Raleigh NC 27615",
    "addr:housenumber":"6400",
    "addr:postcode":"27615",
    "addr:street":"Falls Of Neuse Rd",
    "iso:country":"US",
    "sg:address":"6400 Falls of Neuse Rd",
    "sg:city":"Raleigh",
    "sg:classifiers":[
        {
            "category":"Health Services",
            "subcategory":"Doctor",
            "type":"Services"
        }
    ],
    "sg:phone":"+1 919 872 5411",
    "sg:postcode":"27615",
    "sg:province":"NC",
    "sg:tags":[
        "medical"
    ],
    "wof:name":"North Raleigh Pediatric Care",
    "wof:placetype":"venue"
},
  "geometry": {"coordinates":[-78.622006,35.87208],"type":"Point"}
}