{
  "type": "Feature",
  "properties": {
    "addr:full":"111 Wilmington St Richlands NC 28574",
    "addr:housenumber":"111",
    "addr:postcode":"28574",
    "addr:street":"Wilmington St",
    "iso:country":"US",
    "sg:address":"111 Wilmington St",
    "sg:city":"Richlands",
    "sg:phone":"+1 910 324 4623",
    "sg:postcode":"28574",
    "sg:province":"NC",
    "sg:tags":[
        "gas"
    ],
    "wof:name":"Jenkins Gas & Oil Co",
    "wof:placetype":"venue"
},
  "geometry": {"coordinates":[-77.54563400000001,34.900899],"type":"Point"}
}