{
  "type": "Feature",
  "properties": {
    "iso:country":"US",
    "sg:address":"3733 Zoo Pkwy",
    "sg:city":"Asheboro",
    "sg:classifiers":[
        {
            "category":"Building & Trades",
            "subcategory":"Construction",
            "type":"Services"
        }
    ],
    "sg:phone":"+1 336 625 6310",
    "sg:postcode":"27205",
    "sg:province":"NC",
    "sg:tags":[
        "painter"
    ],
    "wof:name":"Yow Painting & Pressure Wshng",
    "wof:placetype":"venue"
},
  "geometry": {"coordinates":[-79.78657699999999,35.649561],"type":"Point"}
}