{
  "type": "Feature",
  "properties": {
    "iso:country":"US",
    "sg:address":"180 Canterbury Rd",
    "sg:city":"Reidsville",
    "sg:classifiers":[
        {
            "category":"Food & Beverages",
            "subcategory":"Groceries & Convenience Stores",
            "type":"Retail Goods"
        }
    ],
    "sg:phone":"+1 336 342 3805",
    "sg:postcode":"27320",
    "sg:province":"NC",
    "wof:name":"Jim Scott",
    "wof:placetype":"venue"
},
  "geometry": {"coordinates":[-79.68298299999999,36.388248],"type":"Point"}
}