{
  "type": "Feature",
  "properties": {
    "addr:full":"1703 Country Club Rd Jacksonville NC 28546",
    "addr:housenumber":"1703",
    "addr:postcode":"28546",
    "addr:street":"Country Club Rd",
    "iso:country":"US",
    "sg:address":"1703 Country Club Rd",
    "sg:city":"Jacksonville",
    "sg:classifiers":[
        {
            "category":"Health Services",
            "subcategory":"Doctor",
            "type":"Services"
        }
    ],
    "sg:phone":"+1 910 347 3010",
    "sg:postcode":"28546",
    "sg:province":"NC",
    "sg:tags":[
        "medical"
    ],
    "wof:name":"Carolina Physlogical Hlth Svcs",
    "wof:placetype":"venue"
},
  "geometry": {"coordinates":[-77.382014,34.767597],"type":"Point"}
}