{
  "type": "Feature",
  "properties": {
    "iso:country":"US",
    "sg:address":"629 Green Valley Rd",
    "sg:city":"Greensboro",
    "sg:classifiers":[
        {
            "category":"Professional",
            "subcategory":"Research",
            "type":"Services"
        }
    ],
    "sg:phone":"+1 336 235 0997",
    "sg:postcode":"27403",
    "sg:province":"NC",
    "wof:name":"Main Street Research LLC",
    "wof:placetype":"venue"
},
  "geometry": {"coordinates":[-79.82563399999999,36.088338],"type":"Point"}
}