{
  "type": "Feature",
  "properties": {
    "addr:full":"500 S College St Charlotte NC 28202",
    "addr:housenumber":"500",
    "addr:postcode":"28202",
    "addr:street":"S College St",
    "iso:country":"US",
    "sg:address":"500 S College St",
    "sg:city":"Charlotte",
    "sg:classifiers":[
        {
            "category":"Professional",
            "subcategory":"Business Services",
            "type":"Services"
        }
    ],
    "sg:phone":"+1 704 334 2282",
    "sg:postcode":"28202",
    "sg:province":"NC",
    "sg:tags":[
        "visitor",
        "bureau",
        "convention"
    ],
    "wof:name":"Visit Charlotte",
    "wof:placetype":"venue"
},
  "geometry": {"coordinates":[-80.84743400000001,35.222501],"type":"Point"}
}