{
  "type": "Feature",
  "properties": {
    "addr:full":"7 S 5th St Wilmington NC 28401",
    "addr:housenumber":"7",
    "addr:postcode":"28401",
    "addr:street":"S 5Th St",
    "iso:country":"US",
    "sg:address":"7 S 5th St",
    "sg:city":"Wilmington",
    "sg:classifiers":[
        {
            "category":"Professional",
            "subcategory":"Lawyer & Legal Services",
            "type":"Services"
        }
    ],
    "sg:phone":"+1 910 762 1845",
    "sg:postcode":"28401",
    "sg:province":"NC",
    "sg:tags":[
        "attorney"
    ],
    "wof:name":"Carlton S Prickett Jr",
    "wof:placetype":"venue"
},
  "geometry": {"coordinates":[-77.943168,34.235589],"type":"Point"}
}