{
  "type": "Feature",
  "properties": {
    "addr:full":"220 Goldfield Dr Garner NC 27529",
    "addr:housenumber":"220",
    "addr:postcode":"27529",
    "addr:street":"Goldfield Dr",
    "iso:country":"US",
    "sg:address":"220 Goldfield Dr",
    "sg:city":"Garner",
    "sg:classifiers":[
        {
            "category":"Education",
            "subcategory":"Special Training",
            "type":"Public Place"
        }
    ],
    "sg:phone":"+1   ",
    "sg:postcode":"27529",
    "sg:province":"NC",
    "wof:name":"Center For Literacy Alter",
    "wof:placetype":"venue"
},
  "geometry": {"coordinates":[-78.53511399999999,35.590818],"type":"Point"}
}