{
  "type": "Feature",
  "properties": {
    "iso:country":"US",
    "sg:address":"5620 Bridgetowne Way",
    "sg:city":"Raleigh",
    "sg:classifiers":[
        {
            "category":"Real Estate",
            "subcategory":"Real Estate Operator",
            "type":"Services"
        }
    ],
    "sg:phone":"+1 919 876 8983",
    "sg:postcode":"27609",
    "sg:province":"NC",
    "sg:tags":[
        "building",
        "nonresidential"
    ],
    "wof:name":"Carter Gt Properties LLC",
    "wof:placetype":"venue"
},
  "geometry": {"coordinates":[-78.603447,35.855797],"type":"Point"}
}