{
  "type": "Feature",
  "properties": {
    "addr:full":"1019 N Lafayette St Shelby NC 28150",
    "addr:housenumber":"1019",
    "addr:postcode":"28150",
    "addr:street":"N Lafayette St",
    "iso:country":"US",
    "sg:address":"1019 N Lafayette St",
    "sg:city":"Shelby",
    "sg:classifiers":[
        {
            "category":"Health Services",
            "subcategory":"Doctor",
            "type":"Services"
        }
    ],
    "sg:phone":"+1 704 487 9766",
    "sg:postcode":"28150",
    "sg:province":"NC",
    "sg:tags":[
        "physician",
        "surgeon"
    ],
    "wof:name":"Nephrology Assoc-Carolinas",
    "wof:placetype":"venue"
},
  "geometry": {"coordinates":[-81.53958799999999,35.304137],"type":"Point"}
}