{
  "type": "Feature",
  "properties": {
    "iso:country":"US",
    "sg:address":"3024 Brassfield Rd",
    "sg:city":"Creedmoor",
    "sg:classifiers":[
        {
            "category":"Professional",
            "type":"Services"
        }
    ],
    "sg:phone":"+1 919 528 6656",
    "sg:postcode":"27522",
    "sg:province":"NC",
    "wof:name":"Gail C Corrigan",
    "wof:placetype":"venue"
},
  "geometry": {"coordinates":[-78.613986,36.106608],"type":"Point"}
}