{
  "type": "Feature",
  "properties": {
    "iso:country":"US",
    "sg:address":"6900 Northpark Blvd",
    "sg:city":"Charlotte",
    "sg:classifiers":[
        {
            "category":"Professional",
            "subcategory":"Business Services",
            "type":"Services"
        }
    ],
    "sg:phone":"+1 704 509 9859",
    "sg:postcode":"28216",
    "sg:province":"NC",
    "sg:tags":[
        "interior",
        "consultant",
        "design",
        "decorator"
    ],
    "wof:name":"Home Decor Liquidators",
    "wof:placetype":"venue"
},
  "geometry": {"coordinates":[-80.84939799999999,35.314195],"type":"Point"}
}