{
  "type": "Feature",
  "properties": {
    "iso:country":"US",
    "sg:address":"2631 Stonehaven Dr",
    "sg:city":"Fayetteville",
    "sg:classifiers":[
        {
            "category":"Building & Trades",
            "subcategory":"Plumbing",
            "type":"Services"
        }
    ],
    "sg:phone":"+1 910 868 6206",
    "sg:postcode":"28306",
    "sg:province":"NC",
    "sg:tags":[
        "contractor"
    ],
    "wof:name":"All Seasons AC & Htg",
    "wof:placetype":"venue"
},
  "geometry": {"coordinates":[-78.95455699999999,35.007179],"type":"Point"}
}