{
  "type": "Feature",
  "properties": {
    "iso:country":"US",
    "sg:address":"1500 Applethorn Dr",
    "sg:city":"Apex",
    "sg:classifiers":[
        {
            "category":"Building & Trades",
            "subcategory":"Construction",
            "type":"Services"
        }
    ],
    "sg:phone":"+1 919 244 6908",
    "sg:postcode":"27502",
    "sg:province":"NC",
    "sg:tags":[
        "contractor"
    ],
    "sg:website":"www.harrisonfence.com",
    "wof:name":"Harrison Fence",
    "wof:placetype":"venue"
},
  "geometry": {"coordinates":[-78.868273,35.726074],"type":"Point"}
}