{
  "type": "Feature",
  "properties": {
    "addr:full":"100 Parkwood Dr Jacksonville NC 28546",
    "addr:housenumber":"100",
    "addr:postcode":"28546",
    "addr:street":"Parkwood Dr",
    "iso:country":"US",
    "sg:address":"100 Parkwood Dr",
    "sg:city":"Jacksonville",
    "sg:classifiers":[
        {
            "category":"Home & Garden",
            "subcategory":"Hardware",
            "type":"Retail Goods"
        }
    ],
    "sg:phone":"+1 910 455 1404",
    "sg:postcode":"28546",
    "sg:province":"NC",
    "wof:name":"Askew's Builders Supply",
    "wof:placetype":"venue"
},
  "geometry": {"coordinates":[-77.388509,34.778061],"type":"Point"}
}