{
  "type": "Feature",
  "properties": {
    "iso:country":"US",
    "sg:address":"710 Butler Rd",
    "sg:city":"Salemburg",
    "sg:classifiers":[
        {
            "category":"Organizations",
            "subcategory":"Religious Organization",
            "type":"Services"
        }
    ],
    "sg:phone":"+1   ",
    "sg:postcode":"28385",
    "sg:province":"NC",
    "wof:name":"James Curtis Williams Reverend",
    "wof:placetype":"venue"
},
  "geometry": {"coordinates":[-78.55273699999999,35.09949],"type":"Point"}
}