{
  "type": "Feature",
  "properties": {
    "iso:country":"US",
    "sg:address":"104 Fern Berry Ct",
    "sg:city":"Apex",
    "sg:classifiers":[
        {
            "category":"Banks & Credit Unions",
            "subcategory":"Financial Services",
            "type":"Services"
        }
    ],
    "sg:phone":"+1 919 367 9577",
    "sg:postcode":"27502",
    "sg:province":"NC",
    "sg:tags":[
        "investor"
    ],
    "wof:name":"M & K Investment Prpts LLC",
    "wof:placetype":"venue"
},
  "geometry": {"coordinates":[-78.889231,35.730128],"type":"Point"}
}