{
  "type": "Feature",
  "properties": {
    "addr:full":"3285 Doc Bennett Rd Fayetteville NC 28306",
    "addr:housenumber":"3285",
    "addr:postcode":"28306",
    "addr:street":"Doc Bennett Rd",
    "iso:country":"US",
    "sg:address":"3285 Doc Bennett Rd",
    "sg:city":"Fayetteville",
    "sg:classifiers":[
        {
            "category":"Freight",
            "type":"Transportation"
        }
    ],
    "sg:phone":"+1 910 485 5553",
    "sg:postcode":"28306",
    "sg:province":"NC",
    "sg:tags":[
        "commercial",
        "storage"
    ],
    "wof:name":"Airport Mini Storage",
    "wof:placetype":"venue"
},
  "geometry": {"coordinates":[-78.890249,34.985096],"type":"Point"}
}