{
  "type": "Feature",
  "properties": {
    "addr:full":"8312 Stayman Ct Huntersville NC 28078",
    "addr:housenumber":"8312",
    "addr:postcode":"28078",
    "addr:street":"Stayman Ct",
    "iso:country":"US",
    "sg:address":"8312 Stayman Ct",
    "sg:city":"Huntersville",
    "sg:classifiers":[
        {
            "category":"Building & Trades",
            "subcategory":"Construction",
            "type":"Services"
        }
    ],
    "sg:phone":"+1 704 875 2523",
    "sg:postcode":"28078",
    "sg:province":"NC",
    "sg:tags":[
        "hanging",
        "contractor"
    ],
    "wof:name":"A Custom Painting By Terry",
    "wof:placetype":"venue"
},
  "geometry": {"coordinates":[-80.891734,35.397227],"type":"Point"}
}