{
  "type": "Feature",
  "properties": {
    "addr:full":"2 Greenwood Ter Granite Falls NC 28630",
    "addr:housenumber":"2",
    "addr:postcode":"28630",
    "addr:street":"Greenwood Ter",
    "iso:country":"US",
    "sg:address":"2 Greenwood Ter",
    "sg:city":"Granite Falls",
    "sg:classifiers":[
        {
            "category":"Personal",
            "subcategory":"Beauty Salon",
            "type":"Services"
        }
    ],
    "sg:phone":"+1   ",
    "sg:postcode":"28630",
    "sg:province":"NC",
    "sg:tags":[
        "shop"
    ],
    "wof:name":"James Klassy Kurl",
    "wof:placetype":"venue"
},
  "geometry": {"coordinates":[-81.46450900000001,35.812799],"type":"Point"}
}