{
  "type": "Feature",
  "properties": {
    "iso:country":"US",
    "sg:address":"302 Roxboro St",
    "sg:city":"Haw River",
    "sg:classifiers":[
        {
            "category":"Manufacturing",
            "subcategory":"Textiles",
            "type":"Manufacturing & Wholesale Goods"
        }
    ],
    "sg:phone":"+1 336 578 0871",
    "sg:postcode":"27258",
    "sg:province":"NC",
    "sg:tags":[
        "hosiery"
    ],
    "wof:name":"Sue-Lynn Textiles",
    "wof:placetype":"venue"
},
  "geometry": {"coordinates":[-79.35356899999999,36.097942],"type":"Point"}
}