{
  "type": "Feature",
  "properties": {
    "addr:full":"1025 Appalachin Dr Fayetteville NC 28311",
    "addr:housenumber":"1025",
    "addr:postcode":"28311",
    "addr:street":"Appalachin Dr",
    "iso:country":"US",
    "sg:address":"1025 Appalachin Dr",
    "sg:city":"Fayetteville",
    "sg:classifiers":[
        {
            "category":"Building & Trades",
            "subcategory":"Landscaping Services",
            "type":"Services"
        }
    ],
    "sg:phone":"+1 910 488 6160",
    "sg:postcode":"28311",
    "sg:province":"NC",
    "wof:name":"Carolina Lawn Care",
    "wof:placetype":"venue"
},
  "geometry": {"coordinates":[-78.91215,35.157838],"type":"Point"}
}