{
  "type": "Feature",
  "properties": {
    "addr:full":"340 S Cooper Dr Henderson NC 27536",
    "addr:housenumber":"340",
    "addr:postcode":"27536",
    "addr:street":"S Cooper Dr",
    "iso:country":"US",
    "sg:address":"340 S Cooper Dr",
    "sg:city":"Henderson",
    "sg:classifiers":[
        {
            "category":"Shopping",
            "subcategory":"Clothing, Apparel, & Fashions",
            "type":"Retail Goods"
        }
    ],
    "sg:phone":"+1 252 492 3445",
    "sg:postcode":"27536",
    "sg:province":"NC",
    "wof:name":"Style Setter",
    "wof:placetype":"venue"
},
  "geometry": {"coordinates":[-78.438007,36.330403],"type":"Point"}
}